{
  "type": "Feature",
  "properties": {
    "iso:country":"GB",
    "wof:name":"OX2 6EG",
    "wof:placetype":"postalcode"
},
  "geometry": {"coordinates":[-1.26831571659239,51.76233023005154],"type":"Point"}
}