{
  "type": "Feature",
  "properties": {
    "iso:country":"GB",
    "wof:name":"LS8 3AL",
    "wof:placetype":"postalcode"
},
  "geometry": {"coordinates":[-1.50321517294589,53.81711800265875],"type":"Point"}
}