{
  "type": "Feature",
  "properties": {
    "iso:country":"GB",
    "wof:name":"HA8 0BS",
    "wof:placetype":"postalcode"
},
  "geometry": {"coordinates":[-0.26877005975088,51.60504495296834],"type":"Point"}
}