{
  "type": "Feature",
  "properties": {
    "iso:country": "GB",
    "wof:name": "HA8 0BS",
    "wof:placetype": "postalcode"
  },
  "geometry": {"coordinates":[-0.26877,51.605045],"type":"Point"}
}
