{
  "type": "Feature",
  "properties": {
    "iso:country":"GB",
    "wof:name":"SY10 7AG",
    "wof:placetype":"postalcode"
},
  "geometry": {"coordinates":[-3.03268529950124,52.88421194951564],"type":"Point"}
}