{
  "type": "Feature",
  "properties": {
    "date:inception_lower": "1980-01-01",
    "date:inception_upper": "1980-01-01",
    "iso:country": "GB",
    "wof:name": "YO17 9QH",
    "wof:placetype": "postalcode"
  },
  "geometry": {"coordinates":[-0.758553,54.094992],"type":"Point"}
}
