{
  "type": "Feature",
  "properties": {
    "date:inception_lower": "1980-01-01",
    "date:inception_upper": "1980-01-01",
    "iso:country": "GB",
    "wof:name": "ST5 7BQ",
    "wof:placetype": "postalcode"
  },
  "geometry": {"coordinates":[-2.255372,53.046261],"type":"Point"}
}
