{
  "type": "Feature",
  "properties": {
    "iso:country": "GB",
    "wof:name": "CH3 6GT",
    "wof:placetype": "postalcode"
  },
  "geometry": {"coordinates":[-2.831835,53.152942],"type":"Point"}
}
