{
  "type": "Feature",
  "properties": {
    "iso:country": "GB",
    "wof:name": "ST18 0LD",
    "wof:placetype": "postalcode"
  },
  "geometry": {"coordinates":[-1.994747,52.842876],"type":"Point"}
}
