{
  "type": "Feature",
  "properties": {
    "iso:country":"GB",
    "wof:name":"SE22 0JW",
    "wof:placetype":"postalcode"
},
  "geometry": {"coordinates":[-0.07128475335628,51.4523117316745],"type":"Point"}
}