{
  "type": "Feature",
  "properties": {
    "iso:country":"GB",
    "wof:name":"NR10 4RB",
    "wof:placetype":"postalcode"
},
  "geometry": {"coordinates":[1.11049976120458,52.75278375452432],"type":"Point"}
}