{
  "type": "Feature",
  "properties": {
    "iso:country": "GB",
    "wof:name": "NR10 4RB",
    "wof:placetype": "postalcode"
  },
  "geometry": {"coordinates":[1.1105,52.752784],"type":"Point"}
}
