{
  "type": "Feature",
  "properties": {
    "date:inception_lower":"1980-01-01",
    "date:inception_upper":"1980-01-31",
    "iso:country":"GB",
    "wof:name":"NR10 4RB",
    "wof:placetype":"postalcode"
},
  "geometry": {"coordinates":[1.1105,52.752784],"type":"Point"}
}