{
  "type": "Feature",
  "properties": {
    "iso:country": "GB",
    "wof:name": "IV51 9UN",
    "wof:placetype": "postalcode"
  },
  "geometry": {"coordinates":[-6.292004,57.687518],"type":"Point"}
}
