{
  "type": "Feature",
  "properties": {
    "iso:country":"GB",
    "wof:name":"IV51 9UN",
    "wof:placetype":"postalcode"
},
  "geometry": {"coordinates":[-6.29200440264532,57.68751812442492],"type":"Point"}
}