{
  "type": "Feature",
  "properties": {
    "iso:country":"GB",
    "wof:name":"NE1 2DZ",
    "wof:placetype":"postalcode"
},
  "geometry": {"coordinates":[-1.59376203102566,54.97244872047295],"type":"Point"}
}