{
  "type": "Feature",
  "properties": {
    "iso:country":"GB",
    "wof:name":"BS37 5NL",
    "wof:placetype":"postalcode"
},
  "geometry": {"coordinates":[-2.4330399985301,51.54659566832146],"type":"Point"}
}