{
  "type": "Feature",
  "properties": {
    "date:inception_lower":"1980-01-01",
    "date:inception_upper":"1980-01-31",
    "iso:country":"GB",
    "wof:name":"SA33 5NX",
    "wof:placetype":"postalcode"
},
  "geometry": {"coordinates":[-4.458942,51.860019],"type":"Point"}
}