{
  "type": "Feature",
  "properties": {
    "iso:country":"GB",
    "wof:name":"SA33 5NX",
    "wof:placetype":"postalcode"
},
  "geometry": {"coordinates":[-4.45913304501016,51.86022885221119],"type":"Point"}
}