{
  "type": "Feature",
  "properties": {
    "iso:country":"GB",
    "wof:name":"LS9 6EQ",
    "wof:placetype":"postalcode"
},
  "geometry": {"coordinates":[-1.50711029420073,53.80488336935863],"type":"Point"}
}