{
  "type": "Feature",
  "properties": {
    "iso:country":"GB",
    "wof:name":"NG16 2WE",
    "wof:placetype":"postalcode"
},
  "geometry": {"coordinates":[-1.28685368685659,53.00346290024829],"type":"Point"}
}