{
  "type": "Feature",
  "properties": {
    "iso:country": "GB",
    "wof:name": "NN12 6FX",
    "wof:placetype": "postalcode"
  },
  "geometry": {"coordinates":[-0.988926,52.132891],"type":"Point"}
}
