{
  "type": "Feature",
  "properties": {
    "iso:country":"GB",
    "wof:name":"SA73 1NJ",
    "wof:placetype":"postalcode"
},
  "geometry": {"coordinates":[-4.91919982020912,51.73045596795414],"type":"Point"}
}