{
  "type": "Feature",
  "properties": {
    "iso:country": "GB",
    "wof:name": "SA73 1NJ",
    "wof:placetype": "postalcode"
  },
  "geometry": {"coordinates":[-4.916994,51.730569],"type":"Point"}
}
