{
  "type": "Feature",
  "properties": {
    "iso:country":"GB",
    "wof:name":"TQ4 7QW",
    "wof:placetype":"postalcode"
},
  "geometry": {"coordinates":[-3.59046570782123,50.42223723774934],"type":"Point"}
}