{
  "type": "Feature",
  "properties": {
    "date:inception_lower": "1983-07-01",
    "date:inception_upper": "1983-07-01",
    "iso:country": "GB",
    "wof:name": "NE6 2EJ",
    "wof:placetype": "postalcode"
  },
  "geometry": {"coordinates":[-1.575123,54.972655],"type":"Point"}
}
