{
  "type": "Feature",
  "properties": {
    "iso:country":"GB",
    "wof:name":"NE6 2EJ",
    "wof:placetype":"postalcode"
},
  "geometry": {"coordinates":[-1.575123218863,54.97265466871353],"type":"Point"}
}