{
  "type": "Feature",
  "properties": {
    "iso:country":"GB",
    "wof:name":"HP16 0QD",
    "wof:placetype":"postalcode"
},
  "geometry": {"coordinates":[-0.72904069855101,51.69675624350555],"type":"Point"}
}