{
  "type": "Feature",
  "properties": {
    "iso:country":"GB",
    "wof:name":"B29 5DN",
    "wof:placetype":"postalcode"
},
  "geometry": {"coordinates":[-1.97087713956685,52.43341753327167],"type":"Point"}
}