{
  "type": "Feature",
  "properties": {
    "iso:country": "GB",
    "wof:name": "LA9 7QE",
    "wof:placetype": "postalcode"
  },
  "geometry": {"coordinates":[-2.739888,54.297537],"type":"Point"}
}
