{
  "type": "Feature",
  "properties": {
    "iso:country":"GB",
    "wof:name":"TN33 9PU",
    "wof:placetype":"postalcode"
},
  "geometry": {"coordinates":[0.45401045248682,50.94177504167283],"type":"Point"}
}