{
  "type": "Feature",
  "properties": {
    "iso:country": "GB",
    "wof:name": "NE66 1TB",
    "wof:placetype": "postalcode"
  },
  "geometry": {"coordinates":[-1.704311,55.412565],"type":"Point"}
}
