{
  "type": "Feature",
  "properties": {
    "iso:country":"GB",
    "wof:name":"G68 9LF",
    "wof:placetype":"postalcode"
},
  "geometry": {"coordinates":[-4.06261515820808,55.9421207762154],"type":"Point"}
}