{
  "type": "Feature",
  "properties": {
    "iso:country":"GB",
    "wof:name":"NW8 8RT",
    "wof:placetype":"postalcode"
},
  "geometry": {"coordinates":[-0.17164056019293,51.52446606971655],"type":"Point"}
}