{
  "type": "Feature",
  "properties": {
    "date:inception_lower": "2006-09-01",
    "date:inception_upper": "2006-09-01",
    "iso:country": "GB",
    "wof:name": "NW8 8RT",
    "wof:placetype": "postalcode"
  },
  "geometry": {"coordinates":[-0.171274,51.524355],"type":"Point"}
}
