{
  "type": "Feature",
  "properties": {
    "iso:country":"GB",
    "wof:name":"EH7 6PT",
    "wof:placetype":"postalcode"
},
  "geometry": {"coordinates":[-3.1391291693802,55.95850691937457],"type":"Point"}
}