{
  "type": "Feature",
  "properties": {
    "date:inception_lower": "1980-01-01",
    "date:inception_upper": "1980-01-01",
    "iso:country": "GB",
    "wof:name": "NE66 3TD",
    "wof:placetype": "postalcode"
  },
  "geometry": {"coordinates":[-1.60629,55.472852],"type":"Point"}
}
