{
  "type": "Feature",
  "properties": {
    "iso:country":"GB",
    "wof:name":"NE66 3TD",
    "wof:placetype":"postalcode"
},
  "geometry": {"coordinates":[-1.60627317521286,55.47285157492382],"type":"Point"}
}