{
  "type": "Feature",
  "properties": {
    "iso:country":"GB",
    "wof:name":"SE1 7BW",
    "wof:placetype":"postalcode"
},
  "geometry": {"coordinates":[-0.11229286424522,51.49759149892287],"type":"Point"}
}