{
  "type": "Feature",
  "properties": {
    "date:inception_lower":"1983-01-01",
    "date:inception_upper":"1983-01-31",
    "iso:country":"GB",
    "wof:name":"CF5 2SD",
    "wof:placetype":"postalcode"
},
  "geometry": {"coordinates":[-3.245545,51.502683],"type":"Point"}
}