{
  "type": "Feature",
  "properties": {
    "date:inception_lower":"1998-12-01",
    "date:inception_upper":"1998-12-31",
    "iso:country":"GB",
    "wof:name":"HU6 9PB",
    "wof:placetype":"postalcode"
},
  "geometry": {"coordinates":[-0.371094,53.782602],"type":"Point"}
}