{
  "type": "Feature",
  "properties": {
    "iso:country":"GB",
    "wof:name":"CT21 6DJ",
    "wof:placetype":"postalcode"
},
  "geometry": {"coordinates":[1.0821064454608,51.06732423850624],"type":"Point"}
}