{
  "type": "Feature",
  "properties": {
    "iso:country": "GB",
    "wof:name": "BD20 7SZ",
    "wof:placetype": "postalcode"
  },
  "geometry": {"coordinates":[-1.97347,53.895771],"type":"Point"}
}
