{
  "type": "Feature",
  "properties": {
    "iso:country":"GB",
    "wof:name":"BD20 7SZ",
    "wof:placetype":"postalcode"
},
  "geometry": {"coordinates":[-1.97347042639433,53.89577090089272],"type":"Point"}
}