{
  "type": "Feature",
  "properties": {
    "date:inception_lower": "2008-01-01",
    "date:inception_upper": "2008-01-01",
    "iso:country": "GB",
    "wof:name": "OX33 1HP",
    "wof:placetype": "postalcode"
  },
  "geometry": {"coordinates":[-1.154475,51.76591],"type":"Point"}
}
