{
  "type": "Feature",
  "properties": {
    "iso:country": "GB",
    "wof:name": "OX33 1HP",
    "wof:placetype": "postalcode"
  },
  "geometry": {"coordinates":[-1.154475,51.76591],"type":"Point"}
}
