{
  "type": "Feature",
  "properties": {
    "iso:country":"GB",
    "wof:name":"LS17 9LH",
    "wof:placetype":"postalcode"
},
  "geometry": {"coordinates":[-1.51216182721162,53.90209093011381],"type":"Point"}
}