{
  "type": "Feature",
  "properties": {
    "iso:country":"GB",
    "wof:name":"SK15 3BY",
    "wof:placetype":"postalcode"
},
  "geometry": {"coordinates":[-2.04605445411602,53.49384344549417],"type":"Point"}
}