{
  "type": "Feature",
  "properties": {
    "iso:country":"GB",
    "wof:name":"NE28 9BB",
    "wof:placetype":"postalcode"
},
  "geometry": {"coordinates":[-1.52797920125552,55.0057571254221],"type":"Point"}
}