{
  "type": "Feature",
  "properties": {
    "iso:country": "GB",
    "wof:name": "HP3 9QS",
    "wof:placetype": "postalcode"
  },
  "geometry": {"coordinates":[-0.464399,51.738465],"type":"Point"}
}
