{
  "type": "Feature",
  "properties": {
    "iso:country": "GB",
    "wof:name": "ST9 9AB",
    "wof:placetype": "postalcode"
  },
  "geometry": {"coordinates":[-2.10553,53.08596],"type":"Point"}
}
