{
  "type": "Feature",
  "properties": {
    "iso:country":"GB",
    "wof:name":"ST9 9AB",
    "wof:placetype":"postalcode"
},
  "geometry": {"coordinates":[-2.10552972895187,53.08596003371445],"type":"Point"}
}