{
  "type": "Feature",
  "properties": {
    "iso:country": "GB",
    "wof:name": "L31 3EX",
    "wof:placetype": "postalcode"
  },
  "geometry": {"coordinates":[-2.93012,53.508829],"type":"Point"}
}
