{
  "type": "Feature",
  "properties": {
    "date:inception_lower": "1980-01-01",
    "date:inception_upper": "1980-01-01",
    "iso:country": "GB",
    "wof:name": "PR8 1LX",
    "wof:placetype": "postalcode"
  },
  "geometry": {"coordinates":[-3.01214,53.640539],"type":"Point"}
}
