{
  "type": "Feature",
  "properties": {
    "iso:country":"GB",
    "wof:name":"TW19 5AE",
    "wof:placetype":"postalcode"
},
  "geometry": {"coordinates":[-0.56297375207863,51.44919920485472],"type":"Point"}
}