{
  "type": "Feature",
  "properties": {
    "iso:country": "GB",
    "wof:name": "GU51 1LD",
    "wof:placetype": "postalcode"
  },
  "geometry": {"coordinates":[-0.849158,51.290788],"type":"Point"}
}
