{
  "type": "Feature",
  "properties": {
    "iso:country":"GB",
    "wof:name":"WA8 3AQ",
    "wof:placetype":"postalcode"
},
  "geometry": {"coordinates":[-2.71278789023186,53.38546118064692],"type":"Point"}
}