{
  "type": "Feature",
  "properties": {
    "date:inception_lower": "2016-02-01",
    "date:inception_upper": "2016-02-01",
    "iso:country": "GB",
    "wof:name": "WA8 3AQ",
    "wof:placetype": "postalcode"
  },
  "geometry": {"coordinates":[-2.712788,53.385461],"type":"Point"}
}
