{
  "type": "Feature",
  "properties": {
    "date:inception_lower": "2024-09-01",
    "date:inception_upper": "2024-09-01",
    "iso:country": "GB",
    "wof:name": "TQ1 4WT",
    "wof:placetype": "postalcode"
  },
  "geometry": {"coordinates":[-3.53908,50.471193],"type":"Point"}
}
