{
  "type": "Feature",
  "properties": {
    "iso:country": "GB",
    "wof:name": "LS5 3DE",
    "wof:placetype": "postalcode"
  },
  "geometry": {"coordinates":[-1.602699,53.820688],"type":"Point"}
}
