{
  "type": "Feature",
  "properties": {
    "date:inception_lower":"1994-12-01",
    "date:inception_upper":"1994-12-31",
    "iso:country":"GB",
    "wof:name":"LS5 3DE",
    "wof:placetype":"postalcode"
},
  "geometry": {"coordinates":[-1.602699,53.820688],"type":"Point"}
}