{
  "type": "Feature",
  "properties": {
    "date:inception_lower":"1992-01-01",
    "date:inception_upper":"1992-01-31",
    "iso:country":"GB",
    "wof:name":"WN1 1JP",
    "wof:placetype":"postalcode"
},
  "geometry": {"coordinates":[-2.628089,53.55332],"type":"Point"}
}