{
  "type": "Feature",
  "properties": {
    "iso:country":"GB",
    "wof:name":"WN1 1JP",
    "wof:placetype":"postalcode"
},
  "geometry": {"coordinates":[-2.62808949904482,53.55330487921457],"type":"Point"}
}