{
  "type": "Feature",
  "properties": {
    "iso:country":"GB",
    "wof:name":"LN8 3UN",
    "wof:placetype":"postalcode"
},
  "geometry": {"coordinates":[-0.31957621231304,53.40150401480975],"type":"Point"}
}