{
  "type": "Feature",
  "properties": {
    "date:inception_lower": "1994-05-01",
    "date:inception_upper": "1994-05-01",
    "iso:country": "GB",
    "wof:name": "M25 2RE",
    "wof:placetype": "postalcode"
  },
  "geometry": {"coordinates":[-2.268902,53.543271],"type":"Point"}
}
