{
  "type": "Feature",
  "properties": {
    "iso:country":"GB",
    "wof:name":"M25 2RE",
    "wof:placetype":"postalcode"
},
  "geometry": {"coordinates":[-2.26879838432413,53.5431745948238],"type":"Point"}
}