{
  "type": "Feature",
  "properties": {
    "iso:country":"GB",
    "wof:name":"L36 9GF",
    "wof:placetype":"postalcode"
},
  "geometry": {"coordinates":[-2.83988851355926,53.41190654764087],"type":"Point"}
}