{
  "type": "Feature",
  "properties": {
    "iso:country":"GB",
    "wof:name":"TS6 0TB",
    "wof:placetype":"postalcode"
},
  "geometry": {"coordinates":[-1.15087152008446,54.55339940927148],"type":"Point"}
}