{
  "type": "Feature",
  "properties": {
    "date:inception_lower": "1980-01-01",
    "date:inception_upper": "1980-01-01",
    "iso:country": "GB",
    "wof:name": "NG2 4QZ",
    "wof:placetype": "postalcode"
  },
  "geometry": {"coordinates":[-1.132804,52.952539],"type":"Point"}
}
