{
  "type": "Feature",
  "properties": {
    "iso:country":"GB",
    "wof:name":"MK41 0LZ",
    "wof:placetype":"postalcode"
},
  "geometry": {"coordinates":[-0.41749367178686,52.15005351833844],"type":"Point"}
}