{
  "type": "Feature",
  "properties": {
    "iso:country":"GB",
    "wof:name":"LU6 3PQ",
    "wof:placetype":"postalcode"
},
  "geometry": {"coordinates":[-0.51970271100484,51.87416673899344],"type":"Point"}
}