{
  "type": "Feature",
  "properties": {
    "iso:country": "GB",
    "wof:name": "LU6 3PQ",
    "wof:placetype": "postalcode"
  },
  "geometry": {"coordinates":[-0.519703,51.874167],"type":"Point"}
}
