{
  "type": "Feature",
  "properties": {
    "iso:country":"GB",
    "wof:name":"BS40 7TP",
    "wof:placetype":"postalcode"
},
  "geometry": {"coordinates":[-2.7203160114662,51.32498490527621],"type":"Point"}
}