{
  "type": "Feature",
  "properties": {
    "iso:country": "GB",
    "wof:name": "CT16 1LE",
    "wof:placetype": "postalcode"
  },
  "geometry": {"coordinates":[1.314882,51.123259],"type":"Point"}
}
