{
  "type": "Feature",
  "properties": {
    "date:inception_lower": "1987-04-01",
    "date:inception_upper": "1987-04-01",
    "iso:country": "GB",
    "wof:name": "CT16 1LE",
    "wof:placetype": "postalcode"
  },
  "geometry": {"coordinates":[1.314882,51.123259],"type":"Point"}
}
