{
  "type": "Feature",
  "properties": {
    "date:inception_lower":"1980-01-01",
    "date:inception_upper":"1980-01-31",
    "iso:country":"GB",
    "wof:name":"BH24 2NX",
    "wof:placetype":"postalcode"
},
  "geometry": {"coordinates":[-1.826946,50.834342],"type":"Point"}
}