{
  "type": "Feature",
  "properties": {
    "iso:country":"GB",
    "wof:name":"RH20 3EJ",
    "wof:placetype":"postalcode"
},
  "geometry": {"coordinates":[-0.43043603705477,50.94188773155113],"type":"Point"}
}