{
  "type": "Feature",
  "properties": {
    "iso:country": "GB",
    "wof:name": "RH20 3EJ",
    "wof:placetype": "postalcode"
  },
  "geometry": {"coordinates":[-0.43009,50.942129],"type":"Point"}
}
