{
  "type": "Feature",
  "properties": {
    "iso:country":"GB",
    "wof:name":"BN26 6SJ",
    "wof:placetype":"postalcode"
},
  "geometry": {"coordinates":[0.21059846664239,50.84776067713849],"type":"Point"}
}