{
  "type": "Feature",
  "properties": {
    "iso:country":"GB",
    "wof:name":"N15 4JX",
    "wof:placetype":"postalcode"
},
  "geometry": {"coordinates":[-0.07784956664352,51.58818038560114],"type":"Point"}
}