{
  "type": "Feature",
  "properties": {
    "date:inception_lower": "1980-01-01",
    "date:inception_upper": "1980-01-01",
    "iso:country": "GB",
    "wof:name": "KY16 0JZ",
    "wof:placetype": "postalcode"
  },
  "geometry": {"coordinates":[-2.87322,56.383136],"type":"Point"}
}
