{
  "type": "Feature",
  "properties": {
    "iso:country":"GB",
    "wof:name":"KY16 0JZ",
    "wof:placetype":"postalcode"
},
  "geometry": {"coordinates":[-2.87322050757099,56.38313566025347],"type":"Point"}
}