{
  "type": "Feature",
  "properties": {
    "date:inception_lower": "2021-03-01",
    "date:inception_upper": "2021-03-01",
    "iso:country": "GB",
    "wof:name": "KA11 2GZ",
    "wof:placetype": "postalcode"
  },
  "geometry": {"coordinates":[-4.617185,55.630989],"type":"Point"}
}
