{
  "type": "Feature",
  "properties": {
    "iso:country":"GB",
    "wof:name":"GL54 5TL",
    "wof:placetype":"postalcode"
},
  "geometry": {"coordinates":[-1.98149413302472,51.9034154966692],"type":"Point"}
}