{
  "type": "Feature",
  "properties": {
    "iso:country": "GB",
    "wof:name": "GL54 5TL",
    "wof:placetype": "postalcode"
  },
  "geometry": {"coordinates":[-1.981494,51.903415],"type":"Point"}
}
