{
  "type": "Feature",
  "properties": {
    "iso:country":"GB",
    "wof:name":"SS11 8QJ",
    "wof:placetype":"postalcode"
},
  "geometry": {"coordinates":[0.54201009761054,51.6083148422742],"type":"Point"}
}