{
  "type": "Feature",
  "properties": {
    "iso:country": "GB",
    "wof:name": "SS11 8QJ",
    "wof:placetype": "postalcode"
  },
  "geometry": {"coordinates":[0.54201,51.608315],"type":"Point"}
}
