{
  "type": "Feature",
  "properties": {
    "iso:country":"GB",
    "wof:name":"RG17 8QU",
    "wof:placetype":"postalcode"
},
  "geometry": {"coordinates":[-1.54998464491931,51.52527795345182],"type":"Point"}
}