{
  "type": "Feature",
  "properties": {
    "iso:country":"GB",
    "wof:name":"DE6 1LS",
    "wof:placetype":"postalcode"
},
  "geometry": {"coordinates":[-1.69343702689714,52.99447204893959],"type":"Point"}
}