{
  "type": "Feature",
  "properties": {
    "iso:country": "GB",
    "wof:name": "DE6 1LS",
    "wof:placetype": "postalcode"
  },
  "geometry": {"coordinates":[-1.693437,52.994472],"type":"Point"}
}
