{
  "type": "Feature",
  "properties": {
    "iso:country":"GB",
    "wof:name":"LE9 9GW",
    "wof:placetype":"postalcode"
},
  "geometry": {"coordinates":[-1.30129647822667,52.62563370961605],"type":"Point"}
}