{
  "type": "Feature",
  "properties": {
    "iso:country":"GB",
    "wof:name":"CA2 7HZ",
    "wof:placetype":"postalcode"
},
  "geometry": {"coordinates":[-2.95419167217675,54.89392907024072],"type":"Point"}
}