{
  "type": "Feature",
  "properties": {
    "iso:country":"GB",
    "wof:name":"CV9 1BZ",
    "wof:placetype":"postalcode"
},
  "geometry": {"coordinates":[-1.55013553291142,52.5779885200568],"type":"Point"}
}