{
  "type": "Feature",
  "properties": {
    "iso:country": "GB",
    "wof:name": "CV9 1BZ",
    "wof:placetype": "postalcode"
  },
  "geometry": {"coordinates":[-1.549994,52.57797],"type":"Point"}
}
