{
  "type": "Feature",
  "properties": {
    "date:inception_lower": "1980-01-01",
    "date:inception_upper": "1980-01-01",
    "iso:country": "GB",
    "wof:name": "B78 2LB",
    "wof:placetype": "postalcode"
  },
  "geometry": {"coordinates":[-1.676385,52.569537],"type":"Point"}
}
