{
  "type": "Feature",
  "properties": {
    "iso:country": "GB",
    "wof:name": "B78 2LB",
    "wof:placetype": "postalcode"
  },
  "geometry": {"coordinates":[-1.676385,52.569537],"type":"Point"}
}
