{
  "type": "Feature",
  "properties": {
    "iso:country":"GB",
    "wof:name":"DN6 0LJ",
    "wof:placetype":"postalcode"
},
  "geometry": {"coordinates":[-1.14395769986556,53.61515542644295],"type":"Point"}
}