{
  "type": "Feature",
  "properties": {
    "iso:country": "GB",
    "wof:name": "DN6 0LJ",
    "wof:placetype": "postalcode"
  },
  "geometry": {"coordinates":[-1.143958,53.615155],"type":"Point"}
}
