{
  "type": "Feature",
  "properties": {
    "iso:country":"GB",
    "wof:name":"SE9 6PU",
    "wof:placetype":"postalcode"
},
  "geometry": {"coordinates":[0.04964153684341,51.45285862158337],"type":"Point"}
}