{
  "type": "Feature",
  "properties": {
    "iso:country": "GB",
    "wof:name": "BN25 2BU",
    "wof:placetype": "postalcode"
  },
  "geometry": {"coordinates":[0.100831,50.777965],"type":"Point"}
}
