{
  "type": "Feature",
  "properties": {
    "iso:country":"GB",
    "wof:name":"HX2 7FW",
    "wof:placetype":"postalcode"
},
  "geometry": {"coordinates":[-1.92215611525705,53.72408805250214],"type":"Point"}
}