{
  "type": "Feature",
  "properties": {
    "iso:country": "GB",
    "wof:name": "HX2 7FW",
    "wof:placetype": "postalcode"
  },
  "geometry": {"coordinates":[-1.922158,53.724103],"type":"Point"}
}
