{
  "type": "Feature",
  "properties": {
    "iso:country":"GB",
    "wof:name":"LA8 8BZ",
    "wof:placetype":"postalcode"
},
  "geometry": {"coordinates":[-2.86469085768668,54.30366217913858],"type":"Point"}
}