{
  "type": "Feature",
  "properties": {
    "iso:country":"GB",
    "wof:name":"HU4 7JX",
    "wof:placetype":"postalcode"
},
  "geometry": {"coordinates":[-0.41876195665498,53.7326854220547],"type":"Point"}
}