{
  "type": "Feature",
  "properties": {
    "iso:country":"GB",
    "wof:name":"OL8 3TB",
    "wof:placetype":"postalcode"
},
  "geometry": {"coordinates":[-2.13586801806693,53.51547291492511],"type":"Point"}
}