{
  "type": "Feature",
  "properties": {
    "iso:country":"GB",
    "wof:name":"LU5 6AS",
    "wof:placetype":"postalcode"
},
  "geometry": {"coordinates":[-0.54771420773925,51.94479352233575],"type":"Point"}
}