{
  "type": "Feature",
  "properties": {
    "iso:country": "GB",
    "wof:name": "LU5 6AS",
    "wof:placetype": "postalcode"
  },
  "geometry": {"coordinates":[-0.54769,51.944802],"type":"Point"}
}
