{
  "type": "Feature",
  "properties": {
    "iso:country": "GB",
    "wof:name": "EH6 6JR",
    "wof:placetype": "postalcode"
  },
  "geometry": {"coordinates":[-3.177799,55.976563],"type":"Point"}
}
