{
  "type": "Feature",
  "properties": {
    "iso:country":"GB",
    "wof:name":"B25 8DD",
    "wof:placetype":"postalcode"
},
  "geometry": {"coordinates":[-1.82960818001555,52.46217462269983],"type":"Point"}
}