{
  "type": "Feature",
  "properties": {
    "date:inception_lower": "2020-07-01",
    "date:inception_upper": "2020-07-01",
    "iso:country": "GB",
    "wof:name": "CO12 5FH",
    "wof:placetype": "postalcode"
  },
  "geometry": {"coordinates":[1.183521,51.890025],"type":"Point"}
}
