{
  "type": "Feature",
  "properties": {
    "iso:country":"GB",
    "wof:name":"SR6 7JX",
    "wof:placetype":"postalcode"
},
  "geometry": {"coordinates":[-1.37225358703543,54.94889788749743],"type":"Point"}
}