{
  "type": "Feature",
  "properties": {
    "iso:country":"GB",
    "wof:name":"SK10 2EB",
    "wof:placetype":"postalcode"
},
  "geometry": {"coordinates":[-2.12859883322444,53.26642547427618],"type":"Point"}
}