{
  "type": "Feature",
  "properties": {
    "date:inception_lower":"1980-01-01",
    "date:inception_upper":"1980-01-31",
    "iso:country":"GB",
    "wof:name":"DL12 9HX",
    "wof:placetype":"postalcode"
},
  "geometry": {"coordinates":[-2.006262,54.516494],"type":"Point"}
}