{
  "type": "Feature",
  "properties": {
    "iso:country":"GB",
    "wof:name":"DL12 9HX",
    "wof:placetype":"postalcode"
},
  "geometry": {"coordinates":[-2.00625391569926,54.51648429921982],"type":"Point"}
}