{
  "type": "Feature",
  "properties": {
    "iso:country": "GB",
    "wof:name": "DL12 9HX",
    "wof:placetype": "postalcode"
  },
  "geometry": {"coordinates":[-2.006262,54.516494],"type":"Point"}
}
