{
  "type": "Feature",
  "properties": {
    "iso:country":"GB",
    "wof:name":"EH30 9WA",
    "wof:placetype":"postalcode"
},
  "geometry": {"coordinates":[-3.3863523929962,55.98284946116404],"type":"Point"}
}