{
  "type": "Feature",
  "properties": {
    "iso:country":"GB",
    "wof:name":"LE9 1TJ",
    "wof:placetype":"postalcode"
},
  "geometry": {"coordinates":[-1.19083181328259,52.55696642193011],"type":"Point"}
}