{
  "type": "Feature",
  "properties": {
    "iso:country": "GB",
    "wof:name": "SY13 1TB",
    "wof:placetype": "postalcode"
  },
  "geometry": {"coordinates":[-2.689804,52.960556],"type":"Point"}
}
