{
  "type": "Feature",
  "properties": {
    "iso:country": "GB",
    "wof:name": "ST15 0TX",
    "wof:placetype": "postalcode"
  },
  "geometry": {"coordinates":[-2.194451,52.890108],"type":"Point"}
}
