{
  "type": "Feature",
  "properties": {
    "iso:country":"GB",
    "wof:name":"ST15 0TX",
    "wof:placetype":"postalcode"
},
  "geometry": {"coordinates":[-2.19445137576451,52.89010801678162],"type":"Point"}
}