{
  "type": "Feature",
  "properties": {
    "iso:country": "GB",
    "wof:name": "BB4 7QB",
    "wof:placetype": "postalcode"
  },
  "geometry": {"coordinates":[-2.275705,53.700094],"type":"Point"}
}
