{
  "type": "Feature",
  "properties": {
    "date:inception_lower": "2007-07-01",
    "date:inception_upper": "2007-07-01",
    "iso:country": "GB",
    "wof:name": "BB4 7QB",
    "wof:placetype": "postalcode"
  },
  "geometry": {"coordinates":[-2.275705,53.700094],"type":"Point"}
}
