{
  "type": "Feature",
  "properties": {
    "iso:country":"GB",
    "wof:name":"SA31 2HT",
    "wof:placetype":"postalcode"
},
  "geometry": {"coordinates":[-4.28689075850606,51.85357048622429],"type":"Point"}
}