{
  "type": "Feature",
  "properties": {
    "iso:country":"GB",
    "wof:name":"BA11 2YA",
    "wof:placetype":"postalcode"
},
  "geometry": {"coordinates":[-2.30177057438552,51.24166836842164],"type":"Point"}
}