{
  "type": "Feature",
  "properties": {
    "date:inception_lower": "2021-05-01",
    "date:inception_upper": "2021-05-01",
    "iso:country": "GB",
    "wof:name": "EC2M 4AH",
    "wof:placetype": "postalcode"
  },
  "geometry": {"coordinates":[-0.079456,51.516916],"type":"Point"}
}
