{
  "type": "Feature",
  "properties": {
    "date:inception_lower":"1980-01-01",
    "date:inception_upper":"1980-01-31",
    "iso:country":"GB",
    "wof:name":"TF3 2BT",
    "wof:placetype":"postalcode"
},
  "geometry": {"coordinates":[-2.440171,52.673665],"type":"Point"}
}