{
  "type": "Feature",
  "properties": {
    "iso:country":"GB",
    "wof:name":"TF3 2BT",
    "wof:placetype":"postalcode"
},
  "geometry": {"coordinates":[-2.4401712955738,52.67366549150128],"type":"Point"}
}