{
  "type": "Feature",
  "properties": {
    "iso:country": "GB",
    "wof:name": "TF3 2BT",
    "wof:placetype": "postalcode"
  },
  "geometry": {"coordinates":[-2.440171,52.673665],"type":"Point"}
}
