{
  "type": "Feature",
  "properties": {
    "date:inception_lower": "1980-01-01",
    "date:inception_upper": "1980-01-01",
    "iso:country": "GB",
    "wof:name": "YO17 8BQ",
    "wof:placetype": "postalcode"
  },
  "geometry": {"coordinates":[-0.678685,54.119965],"type":"Point"}
}
