{
  "type": "Feature",
  "properties": {
    "iso:country":"GB",
    "wof:name":"YO17 8BQ",
    "wof:placetype":"postalcode"
},
  "geometry": {"coordinates":[-0.66736281229767,54.1219884641807],"type":"Point"}
}