{
  "type": "Feature",
  "properties": {
    "date:inception_lower": "2000-06-01",
    "date:inception_upper": "2000-06-01",
    "iso:country": "GB",
    "wof:name": "TF1 7XX",
    "wof:placetype": "postalcode"
  },
  "geometry": {"coordinates":[-2.469773,52.71441],"type":"Point"}
}
