{
  "type": "Feature",
  "properties": {
    "iso:country":"GB",
    "wof:name":"TF1 7XX",
    "wof:placetype":"postalcode"
},
  "geometry": {"coordinates":[-2.4697730834087,52.71441003955252],"type":"Point"}
}