{
  "type": "Feature",
  "properties": {
    "iso:country": "GB",
    "wof:name": "SP6 1BL",
    "wof:placetype": "postalcode"
  },
  "geometry": {"coordinates":[-1.79862,50.922665],"type":"Point"}
}
