{
  "type": "Feature",
  "properties": {
    "iso:country":"GB",
    "wof:name":"NE42 5AP",
    "wof:placetype":"postalcode"
},
  "geometry": {"coordinates":[-1.84524357891769,54.95887483173934],"type":"Point"}
}