{
  "type": "Feature",
  "properties": {
    "date:inception_lower": "1980-01-01",
    "date:inception_upper": "1980-01-01",
    "iso:country": "GB",
    "wof:name": "HU10 7ED",
    "wof:placetype": "postalcode"
  },
  "geometry": {"coordinates":[-0.449867,53.741829],"type":"Point"}
}
