{
  "type": "Feature",
  "properties": {
    "iso:country":"GB",
    "wof:name":"HU10 7ED",
    "wof:placetype":"postalcode"
},
  "geometry": {"coordinates":[-0.4498672314363,53.74182915165719],"type":"Point"}
}