{
  "type": "Feature",
  "properties": {
    "iso:country":"GB",
    "wof:name":"RH13 5TE",
    "wof:placetype":"postalcode"
},
  "geometry": {"coordinates":[-0.31706608801893,51.05834258507407],"type":"Point"}
}