{
  "type": "Feature",
  "properties": {
    "iso:country": "GB",
    "wof:name": "RH13 5TE",
    "wof:placetype": "postalcode"
  },
  "geometry": {"coordinates":[-0.317055,51.058294],"type":"Point"}
}
