{
  "type": "Feature",
  "properties": {
    "iso:country":"GB",
    "wof:name":"LE17 6PL",
    "wof:placetype":"postalcode"
},
  "geometry": {"coordinates":[-1.08212854034188,52.51140275528962],"type":"Point"}
}