{
  "type": "Feature",
  "properties": {
    "date:inception_lower":"1980-01-01",
    "date:inception_upper":"1980-01-31",
    "iso:country":"GB",
    "wof:name":"SN11 8PJ",
    "wof:placetype":"postalcode"
},
  "geometry": {"coordinates":[-1.993232,51.439336],"type":"Point"}
}