{
  "type": "Feature",
  "properties": {
    "iso:country": "GB",
    "wof:name": "DN22 7ZL",
    "wof:placetype": "postalcode"
  },
  "geometry": {"coordinates":[-0.944979,53.31181],"type":"Point"}
}
