{
  "type": "Feature",
  "properties": {
    "iso:country": "GB",
    "wof:name": "WF10 2FT",
    "wof:placetype": "postalcode"
  },
  "geometry": {"coordinates":[-1.358706,53.744779],"type":"Point"}
}
