{
  "type": "Feature",
  "properties": {
    "date:inception_lower": "1980-01-01",
    "date:inception_upper": "1980-01-01",
    "iso:country": "GB",
    "wof:name": "TN22 3BJ",
    "wof:placetype": "postalcode"
  },
  "geometry": {"coordinates":[0.09089,51.026601],"type":"Point"}
}
