{
  "type": "Feature",
  "properties": {
    "iso:country":"GB",
    "wof:name":"PE31 7HZ",
    "wof:placetype":"postalcode"
},
  "geometry": {"coordinates":[0.50302720091633,52.91097968264634],"type":"Point"}
}