{
  "type": "Feature",
  "properties": {
    "iso:country": "GB",
    "wof:name": "PE31 7HZ",
    "wof:placetype": "postalcode"
  },
  "geometry": {"coordinates":[0.502994,52.910996],"type":"Point"}
}
