{
  "type": "Feature",
  "properties": {
    "date:inception_lower": "2023-04-01",
    "date:inception_upper": "2023-04-01",
    "iso:country": "GB",
    "wof:name": "IP30 9FY",
    "wof:placetype": "postalcode"
  },
  "geometry": {"coordinates":[0.918824,52.237471],"type":"Point"}
}
