{
  "type": "Feature",
  "properties": {
    "iso:country": "GB",
    "wof:name": "BH24 4DF",
    "wof:placetype": "postalcode"
  },
  "geometry": {"coordinates":[-1.707075,50.845649],"type":"Point"}
}
