{
  "type": "Feature",
  "properties": {
    "date:inception_lower": "1980-01-01",
    "date:inception_upper": "1980-01-01",
    "iso:country": "GB",
    "wof:name": "BL5 3TF",
    "wof:placetype": "postalcode"
  },
  "geometry": {"coordinates":[-2.523818,53.550841],"type":"Point"}
}
