{
  "type": "Feature",
  "properties": {
    "iso:country":"GB",
    "wof:name":"NN1 1HW",
    "wof:placetype":"postalcode"
},
  "geometry": {"coordinates":[-0.89573725304155,52.23123852536285],"type":"Point"}
}