{
  "type": "Feature",
  "properties": {
    "iso:country":"GB",
    "wof:name":"DE4 4BZ",
    "wof:placetype":"postalcode"
},
  "geometry": {"coordinates":[-1.6481640484292,53.10949759653243],"type":"Point"}
}