{
  "type": "Feature",
  "properties": {
    "date:inception_lower": "1980-01-01",
    "date:inception_upper": "1980-01-01",
    "iso:country": "GB",
    "wof:name": "DE4 4BZ",
    "wof:placetype": "postalcode"
  },
  "geometry": {"coordinates":[-1.648164,53.109498],"type":"Point"}
}
