{
  "type": "Feature",
  "properties": {
    "iso:country":"GB",
    "wof:name":"N10 1QZ",
    "wof:placetype":"postalcode"
},
  "geometry": {"coordinates":[-0.15654981717046,51.60146577194269],"type":"Point"}
}