{
  "type": "Feature",
  "properties": {
    "iso:country": "GB",
    "wof:name": "N10 1QZ",
    "wof:placetype": "postalcode"
  },
  "geometry": {"coordinates":[-0.15655,51.601466],"type":"Point"}
}
