{
  "type": "Feature",
  "properties": {
    "date:inception_lower": "2002-05-01",
    "date:inception_upper": "2002-05-01",
    "iso:country": "GB",
    "wof:name": "N10 1QZ",
    "wof:placetype": "postalcode"
  },
  "geometry": {"coordinates":[-0.15655,51.601466],"type":"Point"}
}
