{
  "type": "Feature",
  "properties": {
    "iso:country": "GB",
    "wof:name": "LS13 4QN",
    "wof:placetype": "postalcode"
  },
  "geometry": {"coordinates":[-1.64699,53.797485],"type":"Point"}
}
