{
  "type": "Feature",
  "properties": {
    "iso:country":"GB",
    "wof:name":"LS13 4QN",
    "wof:placetype":"postalcode"
},
  "geometry": {"coordinates":[-1.64699028520703,53.79748485452137],"type":"Point"}
}