{
  "type": "Feature",
  "properties": {
    "iso:country":"GB",
    "wof:name":"RH10 5NQ",
    "wof:placetype":"postalcode"
},
  "geometry": {"coordinates":[-0.18081996302243,51.10409040130188],"type":"Point"}
}