{
  "type": "Feature",
  "properties": {
    "iso:country":"GB",
    "wof:name":"RG41 4EN",
    "wof:placetype":"postalcode"
},
  "geometry": {"coordinates":[-0.86155757069645,51.40404754745121],"type":"Point"}
}