{
  "type": "Feature",
  "properties": {
    "iso:country": "GB",
    "wof:name": "RG41 4EN",
    "wof:placetype": "postalcode"
  },
  "geometry": {"coordinates":[-0.861558,51.404048],"type":"Point"}
}
