{
  "type": "Feature",
  "properties": {
    "date:inception_lower": "1998-12-01",
    "date:inception_upper": "1998-12-01",
    "iso:country": "GB",
    "wof:name": "RG41 4EN",
    "wof:placetype": "postalcode"
  },
  "geometry": {"coordinates":[-0.861558,51.404048],"type":"Point"}
}
