{
  "type": "Feature",
  "properties": {
    "iso:country":"GB",
    "wof:name":"CM0 7EQ",
    "wof:placetype":"postalcode"
},
  "geometry": {"coordinates":[0.83683559549293,51.66192297740101],"type":"Point"}
}