{
  "type": "Feature",
  "properties": {
    "iso:country": "GB",
    "wof:name": "ME8 6AT",
    "wof:placetype": "postalcode"
  },
  "geometry": {"coordinates":[0.570798,51.372301],"type":"Point"}
}
