{
  "type": "Feature",
  "properties": {
    "date:inception_lower":"1986-07-01",
    "date:inception_upper":"1986-07-31",
    "iso:country":"GB",
    "wof:name":"ME8 6AT",
    "wof:placetype":"postalcode"
},
  "geometry": {"coordinates":[0.570798,51.372301],"type":"Point"}
}