{
  "type": "Feature",
  "properties": {
    "iso:country":"GB",
    "wof:name":"HR2 8DT",
    "wof:placetype":"postalcode"
},
  "geometry": {"coordinates":[-2.7715222291633,51.98285715656753],"type":"Point"}
}