{
  "type": "Feature",
  "properties": {
    "iso:country": "GB",
    "wof:name": "HR2 8DT",
    "wof:placetype": "postalcode"
  },
  "geometry": {"coordinates":[-2.771522,51.982857],"type":"Point"}
}
