{
  "type": "Feature",
  "properties": {
    "iso:country": "GB",
    "wof:name": "PE12 9RN",
    "wof:placetype": "postalcode"
  },
  "geometry": {"coordinates":[0.183895,52.766946],"type":"Point"}
}
