{
  "type": "Feature",
  "properties": {
    "iso:country":"GB",
    "wof:name":"PE12 9RN",
    "wof:placetype":"postalcode"
},
  "geometry": {"coordinates":[0.18468926687442,52.76680403442859],"type":"Point"}
}