{
  "type": "Feature",
  "properties": {
    "iso:country": "GB",
    "wof:name": "PE21 8DD",
    "wof:placetype": "postalcode"
  },
  "geometry": {"coordinates":[-0.043893,52.974004],"type":"Point"}
}
