{
  "type": "Feature",
  "properties": {
    "iso:country":"GB",
    "wof:name":"PE21 8DD",
    "wof:placetype":"postalcode"
},
  "geometry": {"coordinates":[-0.04389338314242,52.9740036180904],"type":"Point"}
}