{
  "type": "Feature",
  "properties": {
    "iso:country":"GB",
    "wof:name":"TN31 6HD",
    "wof:placetype":"postalcode"
},
  "geometry": {"coordinates":[0.59073364191054,50.93977390634114],"type":"Point"}
}