{
  "type": "Feature",
  "properties": {
    "iso:country": "GB",
    "wof:name": "TS5 8AE",
    "wof:placetype": "postalcode"
  },
  "geometry": {"coordinates":[-1.264496,54.547502],"type":"Point"}
}
