{
  "type": "Feature",
  "properties": {
    "iso:country":"GB",
    "wof:name":"TS5 8AE",
    "wof:placetype":"postalcode"
},
  "geometry": {"coordinates":[-1.26449557738845,54.54750179386249],"type":"Point"}
}