{
  "type": "Feature",
  "properties": {
    "iso:country":"GB",
    "wof:name":"TS20 2XE",
    "wof:placetype":"postalcode"
},
  "geometry": {"coordinates":[-1.30427303391206,54.57469806514116],"type":"Point"}
}