{
  "type": "Feature",
  "properties": {
    "date:inception_lower": "1992-08-01",
    "date:inception_upper": "1992-08-01",
    "iso:country": "GB",
    "wof:name": "TS20 2XE",
    "wof:placetype": "postalcode"
  },
  "geometry": {"coordinates":[-1.304273,54.574698],"type":"Point"}
}
