{
  "type": "Feature",
  "properties": {
    "iso:country": "GB",
    "wof:name": "TS20 2XE",
    "wof:placetype": "postalcode"
  },
  "geometry": {"coordinates":[-1.304273,54.574698],"type":"Point"}
}
