{
  "type": "Feature",
  "properties": {
    "iso:country": "GB",
    "wof:name": "HP7 9EB",
    "wof:placetype": "postalcode"
  },
  "geometry": {"coordinates":[-0.596803,51.668726],"type":"Point"}
}
