{
  "type": "Feature",
  "properties": {
    "iso:country":"GB",
    "wof:name":"CH8 9LY",
    "wof:placetype":"postalcode"
},
  "geometry": {"coordinates":[-3.34248835921714,53.32348727788921],"type":"Point"}
}