{
  "type": "Feature",
  "properties": {
    "date:inception_lower": "1980-01-01",
    "date:inception_upper": "1980-01-01",
    "iso:country": "GB",
    "wof:name": "CH8 9LY",
    "wof:placetype": "postalcode"
  },
  "geometry": {"coordinates":[-3.34262,53.323378],"type":"Point"}
}
