{
  "type": "Feature",
  "properties": {
    "date:inception_lower": "1980-01-01",
    "date:inception_upper": "1980-01-01",
    "iso:country": "GB",
    "wof:name": "CA12 4QZ",
    "wof:placetype": "postalcode"
  },
  "geometry": {"coordinates":[-3.210634,54.663864],"type":"Point"}
}
