{
  "type": "Feature",
  "properties": {
    "iso:country":"GB",
    "wof:name":"CF83 8QP",
    "wof:placetype":"postalcode"
},
  "geometry": {"coordinates":[-3.15413218683239,51.59628799062894],"type":"Point"}
}