{
  "type": "Feature",
  "properties": {
    "iso:country": "GB",
    "wof:name": "DL1 5TS",
    "wof:placetype": "postalcode"
  },
  "geometry": {"coordinates":[-1.554813,54.509411],"type":"Point"}
}
