{
  "type": "Feature",
  "properties": {
    "iso:country":"GB",
    "wof:name":"DL1 5TS",
    "wof:placetype":"postalcode"
},
  "geometry": {"coordinates":[-1.55481281747111,54.50941114340058],"type":"Point"}
}