{
  "type": "Feature",
  "properties": {
    "iso:country":"GB",
    "wof:name":"CV35 7UF",
    "wof:placetype":"postalcode"
},
  "geometry": {"coordinates":[-1.63149327359023,52.3024362432279],"type":"Point"}
}