{
  "type": "Feature",
  "properties": {
    "iso:country": "GB",
    "wof:name": "CV35 7UF",
    "wof:placetype": "postalcode"
  },
  "geometry": {"coordinates":[-1.631493,52.302436],"type":"Point"}
}
