{
  "type": "Feature",
  "properties": {
    "date:inception_lower": "2021-02-01",
    "date:inception_upper": "2021-02-01",
    "iso:country": "GB",
    "wof:name": "ME5 0FL",
    "wof:placetype": "postalcode"
  },
  "geometry": {"coordinates":[0.53626,51.365383],"type":"Point"}
}
