{
  "type": "Feature",
  "properties": {
    "iso:country":"GB",
    "wof:name":"WD3 4DB",
    "wof:placetype":"postalcode"
},
  "geometry": {"coordinates":[-0.49205365700091,51.64465090980083],"type":"Point"}
}