{
  "type": "Feature",
  "properties": {
    "iso:country":"GB",
    "wof:name":"OX1 4QB",
    "wof:placetype":"postalcode"
},
  "geometry": {"coordinates":[-1.25618684788886,51.74121460767299],"type":"Point"}
}