{
  "type": "Feature",
  "properties": {
    "iso:country":"GB",
    "wof:name":"B13 8PW",
    "wof:placetype":"postalcode"
},
  "geometry": {"coordinates":[-1.90386002752523,52.43565666935235],"type":"Point"}
}