{
  "type": "Feature",
  "properties": {
    "iso:country": "GB",
    "wof:name": "PE28 5UZ",
    "wof:placetype": "postalcode"
  },
  "geometry": {"coordinates":[-0.279119,52.433058],"type":"Point"}
}
