{
  "type": "Feature",
  "properties": {
    "iso:country":"GB",
    "wof:name":"E1W 1LW",
    "wof:placetype":"postalcode"
},
  "geometry": {"coordinates":[-0.06594216102399,51.50480368207112],"type":"Point"}
}