{
  "type": "Feature",
  "properties": {
    "iso:country": "GB",
    "wof:name": "IP7 6HB",
    "wof:placetype": "postalcode"
  },
  "geometry": {"coordinates":[0.892927,52.050652],"type":"Point"}
}
