{
  "type": "Feature",
  "properties": {
    "iso:country":"GB",
    "wof:name":"IP7 6HB",
    "wof:placetype":"postalcode"
},
  "geometry": {"coordinates":[0.89292699257139,52.05065246323668],"type":"Point"}
}