{
  "type": "Feature",
  "properties": {
    "iso:country":"GB",
    "wof:name":"EN3 5XX",
    "wof:placetype":"postalcode"
},
  "geometry": {"coordinates":[-0.0463974362185,51.66174994390056],"type":"Point"}
}