{
  "type": "Feature",
  "properties": {
    "date:inception_lower": "1980-01-01",
    "date:inception_upper": "1980-01-01",
    "iso:country": "GB",
    "wof:name": "EN3 5XX",
    "wof:placetype": "postalcode"
  },
  "geometry": {"coordinates":[-0.046397,51.66175],"type":"Point"}
}
