{
  "type": "Feature",
  "properties": {
    "iso:country": "GB",
    "wof:name": "DY14 0BS",
    "wof:placetype": "postalcode"
  },
  "geometry": {"coordinates":[-2.510325,52.355291],"type":"Point"}
}
