{
  "type": "Feature",
  "properties": {
    "iso:country":"GB",
    "wof:name":"DY14 0BS",
    "wof:placetype":"postalcode"
},
  "geometry": {"coordinates":[-2.51032515736087,52.35529097359753],"type":"Point"}
}