{
  "type": "Feature",
  "properties": {
    "iso:country":"GB",
    "wof:name":"SY5 9NW",
    "wof:placetype":"postalcode"
},
  "geometry": {"coordinates":[-2.87969107633393,52.6983849579601],"type":"Point"}
}