{
  "type": "Feature",
  "properties": {
    "iso:country": "GB",
    "wof:name": "SY5 9NW",
    "wof:placetype": "postalcode"
  },
  "geometry": {"coordinates":[-2.879691,52.698385],"type":"Point"}
}
