{
  "type": "Feature",
  "properties": {
    "iso:country": "GB",
    "wof:name": "BB10 2JW",
    "wof:placetype": "postalcode"
  },
  "geometry": {"coordinates":[-2.20203,53.813292],"type":"Point"}
}
