{
  "type": "Feature",
  "properties": {
    "iso:country":"GB",
    "wof:name":"FY3 9AR",
    "wof:placetype":"postalcode"
},
  "geometry": {"coordinates":[-3.03567502591358,53.81684516054255],"type":"Point"}
}