{
  "type": "Feature",
  "properties": {
    "date:inception_lower": "1980-01-01",
    "date:inception_upper": "1980-01-01",
    "iso:country": "GB",
    "wof:name": "PA61 7YP",
    "wof:placetype": "postalcode"
  },
  "geometry": {"coordinates":[-6.196358,56.06891],"type":"Point"}
}
