{
  "type": "Feature",
  "properties": {
    "iso:country":"GB",
    "wof:name":"NE37 1DN",
    "wof:placetype":"postalcode"
},
  "geometry": {"coordinates":[-1.54108120709392,54.91525216208659],"type":"Point"}
}