{
  "type": "Feature",
  "properties": {
    "iso:country": "GB",
    "wof:name": "LA12 8JB",
    "wof:placetype": "postalcode"
  },
  "geometry": {"coordinates":[-3.032753,54.261257],"type":"Point"}
}
