{
  "type": "Feature",
  "properties": {
    "date:inception_lower": "2006-10-01",
    "date:inception_upper": "2006-10-01",
    "iso:country": "GB",
    "wof:name": "PO36 9FG",
    "wof:placetype": "postalcode"
  },
  "geometry": {"coordinates":[-1.151088,50.662903],"type":"Point"}
}
