{
  "type": "Feature",
  "properties": {
    "iso:country":"GB",
    "wof:name":"B60 4JW",
    "wof:placetype":"postalcode"
},
  "geometry": {"coordinates":[-2.08048811759733,52.31409455639911],"type":"Point"}
}