{
  "type": "Feature",
  "properties": {
    "date:inception_lower": "1980-01-01",
    "date:inception_upper": "1980-01-01",
    "iso:country": "GB",
    "wof:name": "B60 4JW",
    "wof:placetype": "postalcode"
  },
  "geometry": {"coordinates":[-2.080488,52.314095],"type":"Point"}
}
