{
  "type": "Feature",
  "properties": {
    "date:inception_lower":"2011-08-01",
    "date:inception_upper":"2011-08-31",
    "iso:country":"GB",
    "wof:name":"FK10 4RD",
    "wof:placetype":"postalcode"
},
  "geometry": {"coordinates":[-3.714144,56.070637],"type":"Point"}
}