{
  "type": "Feature",
  "properties": {
    "iso:country":"GB",
    "wof:name":"EX10 9QH",
    "wof:placetype":"postalcode"
},
  "geometry": {"coordinates":[-3.21889611635486,50.70204555771165],"type":"Point"}
}