{
  "type": "Feature",
  "properties": {
    "iso:country":"GB",
    "wof:name":"S26 5LQ",
    "wof:placetype":"postalcode"
},
  "geometry": {"coordinates":[-1.28504233071014,53.3388623263351],"type":"Point"}
}