{
  "type": "Feature",
  "properties": {
    "iso:country": "GB",
    "wof:name": "S26 5LQ",
    "wof:placetype": "postalcode"
  },
  "geometry": {"coordinates":[-1.285042,53.338862],"type":"Point"}
}
