{
  "type": "Feature",
  "properties": {
    "iso:country":"GB",
    "wof:name":"TS18 4ES",
    "wof:placetype":"postalcode"
},
  "geometry": {"coordinates":[-1.33593103409804,54.55994844568104],"type":"Point"}
}