{
  "type": "Feature",
  "properties": {
    "iso:country":"GB",
    "wof:name":"CW12 3QU",
    "wof:placetype":"postalcode"
},
  "geometry": {"coordinates":[-2.16133743521489,53.15345861219958],"type":"Point"}
}