{
  "type": "Feature",
  "properties": {
    "iso:country":"GB",
    "wof:name":"RH12 1TE",
    "wof:placetype":"postalcode"
},
  "geometry": {"coordinates":[-0.33471618467333,51.0591889319958],"type":"Point"}
}