{
  "type": "Feature",
  "properties": {
    "iso:country":"GB",
    "wof:name":"ME1 2LY",
    "wof:placetype":"postalcode"
},
  "geometry": {"coordinates":[0.50263898407718,51.36797607732431],"type":"Point"}
}