{
  "type": "Feature",
  "properties": {
    "iso:country":"GB",
    "wof:name":"LS11 9BJ",
    "wof:placetype":"postalcode"
},
  "geometry": {"coordinates":[-1.54743050329458,53.7888457468668],"type":"Point"}
}