{
  "type": "Feature",
  "properties": {
    "iso:country": "GB",
    "wof:name": "LS11 9BJ",
    "wof:placetype": "postalcode"
  },
  "geometry": {"coordinates":[-1.54743,53.788846],"type":"Point"}
}
