{
  "type": "Feature",
  "properties": {
    "iso:country": "GB",
    "wof:name": "DH1 5XG",
    "wof:placetype": "postalcode"
  },
  "geometry": {"coordinates":[-1.564718,54.800564],"type":"Point"}
}
