{
  "type": "Feature",
  "properties": {
    "iso:country":"GB",
    "wof:name":"BN25 1SN",
    "wof:placetype":"postalcode"
},
  "geometry": {"coordinates":[0.10704114602661,50.77252850632342],"type":"Point"}
}