{
  "type": "Feature",
  "properties": {
    "date:inception_lower": "1980-01-01",
    "date:inception_upper": "1980-01-01",
    "iso:country": "GB",
    "wof:name": "BN25 1SN",
    "wof:placetype": "postalcode"
  },
  "geometry": {"coordinates":[0.107041,50.772529],"type":"Point"}
}
