{
  "type": "Feature",
  "properties": {
    "iso:country":"GB",
    "wof:name":"LA15 8RN",
    "wof:placetype":"postalcode"
},
  "geometry": {"coordinates":[-3.17740781853197,54.15846618312766],"type":"Point"}
}