{
  "type": "Feature",
  "properties": {
    "iso:country": "GB",
    "wof:name": "LA15 8RN",
    "wof:placetype": "postalcode"
  },
  "geometry": {"coordinates":[-3.177408,54.158466],"type":"Point"}
}
