{
  "type": "Feature",
  "properties": {
    "iso:country":"GB",
    "wof:name":"NG4 3PQ",
    "wof:placetype":"postalcode"
},
  "geometry": {"coordinates":[-1.10393531272489,52.97953619575726],"type":"Point"}
}