{
  "type": "Feature",
  "properties": {
    "iso:country":"GB",
    "wof:name":"TA19 9QZ",
    "wof:placetype":"postalcode"
},
  "geometry": {"coordinates":[-2.97474256491938,50.93142004946309],"type":"Point"}
}