{
  "type": "Feature",
  "properties": {
    "date:inception_lower": "1990-07-01",
    "date:inception_upper": "1990-07-01",
    "iso:country": "GB",
    "wof:name": "PL15 9TF",
    "wof:placetype": "postalcode"
  },
  "geometry": {"coordinates":[-4.360723,50.633779],"type":"Point"}
}
