{
  "type": "Feature",
  "properties": {
    "iso:country":"GB",
    "wof:name":"PL15 9TF",
    "wof:placetype":"postalcode"
},
  "geometry": {"coordinates":[-4.36072313763226,50.63377868476614],"type":"Point"}
}