{
  "type": "Feature",
  "properties": {
    "iso:country":"GB",
    "wof:name":"RG2 7LB",
    "wof:placetype":"postalcode"
},
  "geometry": {"coordinates":[-0.95887047217259,51.43452663995851],"type":"Point"}
}