{
  "type": "Feature",
  "properties": {
    "iso:country": "GB",
    "wof:name": "RG2 7LB",
    "wof:placetype": "postalcode"
  },
  "geometry": {"coordinates":[-0.95887,51.434527],"type":"Point"}
}
