{
  "type": "Feature",
  "properties": {
    "iso:country":"GB",
    "wof:name":"CB24 6AL",
    "wof:placetype":"postalcode"
},
  "geometry": {"coordinates":[0.15701768834289,52.2402518389969],"type":"Point"}
}