{
  "type": "Feature",
  "properties": {
    "iso:country": "GB",
    "wof:name": "WN5 0LH",
    "wof:placetype": "postalcode"
  },
  "geometry": {"coordinates":[-2.698546,53.554927],"type":"Point"}
}
