{
  "type": "Feature",
  "properties": {
    "iso:country":"GB",
    "wof:name":"SE15 6TB",
    "wof:placetype":"postalcode"
},
  "geometry": {"coordinates":[-0.06838716258983,51.4807167819142],"type":"Point"}
}