{
  "type": "Feature",
  "properties": {
    "iso:country": "GB",
    "wof:name": "SE15 6TB",
    "wof:placetype": "postalcode"
  },
  "geometry": {"coordinates":[-0.068387,51.480717],"type":"Point"}
}
