{
  "type": "Feature",
  "properties": {
    "iso:country": "GB",
    "wof:name": "LA8 9EW",
    "wof:placetype": "postalcode"
  },
  "geometry": {"coordinates":[-2.691942,54.391541],"type":"Point"}
}
