{
  "type": "Feature",
  "properties": {
    "iso:country":"GB",
    "wof:name":"LA8 9EW",
    "wof:placetype":"postalcode"
},
  "geometry": {"coordinates":[-2.69194252070542,54.39154091027044],"type":"Point"}
}