{
  "type": "Feature",
  "properties": {
    "iso:country":"GB",
    "wof:name":"SP6 1NA",
    "wof:placetype":"postalcode"
},
  "geometry": {"coordinates":[-1.78359992208385,50.94652181454457],"type":"Point"}
}