{
  "type": "Feature",
  "properties": {
    "iso:country":"GB",
    "wof:name":"E3 3EF",
    "wof:placetype":"postalcode"
},
  "geometry": {"coordinates":[-0.01984810832121,51.52768511312527],"type":"Point"}
}