{
  "type": "Feature",
  "properties": {
    "iso:country":"GB",
    "wof:name":"B38 9US",
    "wof:placetype":"postalcode"
},
  "geometry": {"coordinates":[-1.94124967826029,52.39228604996834],"type":"Point"}
}