{
  "type": "Feature",
  "properties": {
    "iso:country":"GB",
    "wof:name":"CR5 2NE",
    "wof:placetype":"postalcode"
},
  "geometry": {"coordinates":[-0.13881310203398,51.32061733940215],"type":"Point"}
}