{
  "type": "Feature",
  "properties": {
    "iso:country": "GB",
    "wof:name": "CR5 2NE",
    "wof:placetype": "postalcode"
  },
  "geometry": {"coordinates":[-0.138893,51.320491],"type":"Point"}
}
