{
  "type": "Feature",
  "properties": {
    "date:inception_lower":"1980-01-01",
    "date:inception_upper":"1980-01-31",
    "iso:country":"GB",
    "wof:name":"ST14 7QP",
    "wof:placetype":"postalcode"
},
  "geometry": {"coordinates":[-1.870434,52.897963],"type":"Point"}
}