{
  "type": "Feature",
  "properties": {
    "date:inception_lower": "1985-11-01",
    "date:inception_upper": "1985-11-01",
    "iso:country": "GB",
    "wof:name": "G20 8DA",
    "wof:placetype": "postalcode"
  },
  "geometry": {"coordinates":[-4.281986,55.884362],"type":"Point"}
}
