{
  "type": "Feature",
  "properties": {
    "iso:country": "GB",
    "wof:name": "G20 8DA",
    "wof:placetype": "postalcode"
  },
  "geometry": {"coordinates":[-4.281986,55.884362],"type":"Point"}
}
