{
  "type": "Feature",
  "properties": {
    "iso:country": "GB",
    "wof:name": "CT18 7LE",
    "wof:placetype": "postalcode"
  },
  "geometry": {"coordinates":[1.216274,51.101918],"type":"Point"}
}
