{
  "type": "Feature",
  "properties": {
    "iso:country":"GB",
    "wof:name":"CT18 7LE",
    "wof:placetype":"postalcode"
},
  "geometry": {"coordinates":[1.21627382166547,51.10191763404551],"type":"Point"}
}