{
  "type": "Feature",
  "properties": {
    "date:inception_lower": "1980-01-01",
    "date:inception_upper": "1980-01-01",
    "iso:country": "GB",
    "wof:name": "SW17 9JE",
    "wof:placetype": "postalcode"
  },
  "geometry": {"coordinates":[-0.159881,51.422747],"type":"Point"}
}
