{
  "type": "Feature",
  "properties": {
    "iso:country": "GB",
    "wof:name": "SW17 9JE",
    "wof:placetype": "postalcode"
  },
  "geometry": {"coordinates":[-0.159881,51.422747],"type":"Point"}
}
