{
  "type": "Feature",
  "properties": {
    "date:inception_lower": "1980-01-01",
    "date:inception_upper": "1980-01-01",
    "iso:country": "GB",
    "wof:name": "M3 1LS",
    "wof:placetype": "postalcode"
  },
  "geometry": {"coordinates":[-2.246554,53.491063],"type":"Point"}
}
