{
  "type": "Feature",
  "properties": {
    "iso:country":"GB",
    "wof:name":"S45 0DU",
    "wof:placetype":"postalcode"
},
  "geometry": {"coordinates":[-1.49351423224427,53.16996710713497],"type":"Point"}
}