{
  "type": "Feature",
  "properties": {
    "iso:country": "GB",
    "wof:name": "S45 0DU",
    "wof:placetype": "postalcode"
  },
  "geometry": {"coordinates":[-1.493392,53.170003],"type":"Point"}
}
