{
  "type": "Feature",
  "properties": {
    "iso:country":"GB",
    "wof:name":"CR7 7QF",
    "wof:placetype":"postalcode"
},
  "geometry": {"coordinates":[-0.10861895554085,51.40042986388376],"type":"Point"}
}