{
  "type": "Feature",
  "properties": {
    "iso:country":"GB",
    "wof:name":"GU14 0BJ",
    "wof:placetype":"postalcode"
},
  "geometry": {"coordinates":[-0.76675302168136,51.28920278571864],"type":"Point"}
}