{
  "type": "Feature",
  "properties": {
    "date:inception_lower": "1980-01-01",
    "date:inception_upper": "1980-01-01",
    "iso:country": "GB",
    "wof:name": "GU14 0BJ",
    "wof:placetype": "postalcode"
  },
  "geometry": {"coordinates":[-0.766753,51.289203],"type":"Point"}
}
