{
  "type": "Feature",
  "properties": {
    "iso:country":"GB",
    "wof:name":"ML4 1AB",
    "wof:placetype":"postalcode"
},
  "geometry": {"coordinates":[-4.02215735471222,55.81869122293261],"type":"Point"}
}