{
  "type": "Feature",
  "properties": {
    "iso:country": "GB",
    "wof:name": "BN6 8HE",
    "wof:placetype": "postalcode"
  },
  "geometry": {"coordinates":[-0.143511,50.925187],"type":"Point"}
}
