{
  "type": "Feature",
  "properties": {
    "iso:country":"GB",
    "wof:name":"BN6 8HE",
    "wof:placetype":"postalcode"
},
  "geometry": {"coordinates":[-0.14351128707015,50.92518684959687],"type":"Point"}
}