{
  "type": "Feature",
  "properties": {
    "iso:country":"GB",
    "wof:name":"PL27 7DR",
    "wof:placetype":"postalcode"
},
  "geometry": {"coordinates":[-4.83887457095361,50.51644794229024],"type":"Point"}
}