{
  "type": "Feature",
  "properties": {
    "date:inception_lower": "1983-01-01",
    "date:inception_upper": "1983-01-01",
    "iso:country": "GB",
    "wof:name": "SA3 5JL",
    "wof:placetype": "postalcode"
  },
  "geometry": {"coordinates":[-4.008733,51.591577],"type":"Point"}
}
