{
  "type": "Feature",
  "properties": {
    "iso:country":"GB",
    "wof:name":"SA3 5JL",
    "wof:placetype":"postalcode"
},
  "geometry": {"coordinates":[-4.00873326252727,51.59157722221505],"type":"Point"}
}