{
  "type": "Feature",
  "properties": {
    "date:inception_lower": "2017-10-01",
    "date:inception_upper": "2017-10-01",
    "iso:country": "GB",
    "wof:name": "WR3 7SJ",
    "wof:placetype": "postalcode"
  },
  "geometry": {"coordinates":[-2.198803,52.232318],"type":"Point"}
}
