{
  "type": "Feature",
  "properties": {
    "iso:country":"GB",
    "wof:name":"PL5 3DQ",
    "wof:placetype":"postalcode"
},
  "geometry": {"coordinates":[-4.13591557647423,50.40397352993067],"type":"Point"}
}