{
  "type": "Feature",
  "properties": {
    "iso:country": "GB",
    "wof:name": "PL5 3DQ",
    "wof:placetype": "postalcode"
  },
  "geometry": {"coordinates":[-4.135916,50.403974],"type":"Point"}
}
