{
  "type": "Feature",
  "properties": {
    "date:inception_lower":"1980-01-01",
    "date:inception_upper":"1980-01-31",
    "iso:country":"GB",
    "wof:name":"SE1 2HZ",
    "wof:placetype":"postalcode"
},
  "geometry": {"coordinates":[-0.081304,51.504076],"type":"Point"}
}