{
  "type": "Feature",
  "properties": {
    "iso:country": "GB",
    "wof:name": "CW2 8FA",
    "wof:placetype": "postalcode"
  },
  "geometry": {"coordinates":[-2.45976,53.085828],"type":"Point"}
}
