{
  "type": "Feature",
  "properties": {
    "date:inception_lower":"1994-05-01",
    "date:inception_upper":"1994-05-31",
    "iso:country":"GB",
    "wof:name":"CW2 8FA",
    "wof:placetype":"postalcode"
},
  "geometry": {"coordinates":[-2.45976,53.085828],"type":"Point"}
}