{
  "type": "Feature",
  "properties": {
    "iso:country":"GB",
    "wof:name":"CW2 8FA",
    "wof:placetype":"postalcode"
},
  "geometry": {"coordinates":[-2.45976017268136,53.08582818904353],"type":"Point"}
}