{
  "type": "Feature",
  "properties": {
    "iso:country":"GB",
    "wof:name":"TS19 7RJ",
    "wof:placetype":"postalcode"
},
  "geometry": {"coordinates":[-1.36426686392619,54.56452217245978],"type":"Point"}
}