{
  "type": "Feature",
  "properties": {
    "iso:country": "GB",
    "wof:name": "TS19 7RJ",
    "wof:placetype": "postalcode"
  },
  "geometry": {"coordinates":[-1.364267,54.564522],"type":"Point"}
}
