{
  "type": "Feature",
  "properties": {
    "date:inception_lower":"1987-04-01",
    "date:inception_upper":"1987-04-30",
    "iso:country":"GB",
    "wof:name":"LA14 3XT",
    "wof:placetype":"postalcode"
},
  "geometry": {"coordinates":[-3.262694,54.116203],"type":"Point"}
}