{
  "type": "Feature",
  "properties": {
    "date:inception_lower": "1980-01-01",
    "date:inception_upper": "1980-01-01",
    "iso:country": "GB",
    "wof:name": "BD8 8HG",
    "wof:placetype": "postalcode"
  },
  "geometry": {"coordinates":[-1.768745,53.801256],"type":"Point"}
}
