{
  "type": "Feature",
  "properties": {
    "iso:country":"GB",
    "wof:name":"BD8 8HG",
    "wof:placetype":"postalcode"
},
  "geometry": {"coordinates":[-1.76874169663071,53.80124152105642],"type":"Point"}
}