{
  "type": "Feature",
  "properties": {
    "iso:country": "GB",
    "wof:name": "TF2 9QP",
    "wof:placetype": "postalcode"
  },
  "geometry": {"coordinates":[-2.430523,52.686601],"type":"Point"}
}
