{
  "type": "Feature",
  "properties": {
    "iso:country":"GB",
    "wof:name":"TF2 9QP",
    "wof:placetype":"postalcode"
},
  "geometry": {"coordinates":[-2.43052285885651,52.68660119626111],"type":"Point"}
}