{
  "type": "Feature",
  "properties": {
    "iso:country":"GB",
    "wof:name":"B77 5BJ",
    "wof:placetype":"postalcode"
},
  "geometry": {"coordinates":[-1.67018496213867,52.60929943853355],"type":"Point"}
}