{
  "type": "Feature",
  "properties": {
    "iso:country": "GB",
    "wof:name": "NG11 6QH",
    "wof:placetype": "postalcode"
  },
  "geometry": {"coordinates":[-1.136789,52.856937],"type":"Point"}
}
