{
  "type": "Feature",
  "properties": {
    "iso:country":"GB",
    "wof:name":"NG11 6QH",
    "wof:placetype":"postalcode"
},
  "geometry": {"coordinates":[-1.13678928707924,52.85693679078076],"type":"Point"}
}