{
  "type": "Feature",
  "properties": {
    "iso:country": "GB",
    "wof:name": "HD8 8QQ",
    "wof:placetype": "postalcode"
  },
  "geometry": {"coordinates":[-1.660764,53.568847],"type":"Point"}
}
