{
  "type": "Feature",
  "properties": {
    "iso:country":"GB",
    "wof:name":"TR20 8UL",
    "wof:placetype":"postalcode"
},
  "geometry": {"coordinates":[-5.54724341337756,50.13130935352942],"type":"Point"}
}