{
  "type": "Feature",
  "properties": {
    "date:inception_lower": "1992-01-01",
    "date:inception_upper": "1992-01-01",
    "iso:country": "GB",
    "wof:name": "GU8 4DU",
    "wof:placetype": "postalcode"
  },
  "geometry": {"coordinates":[-0.624633,51.136915],"type":"Point"}
}
