{
  "type": "Feature",
  "properties": {
    "iso:country": "GB",
    "wof:name": "GU8 4DU",
    "wof:placetype": "postalcode"
  },
  "geometry": {"coordinates":[-0.624633,51.136915],"type":"Point"}
}
