{
  "type": "Feature",
  "properties": {
    "iso:country":"GB",
    "wof:name":"NE8 1RD",
    "wof:placetype":"postalcode"
},
  "geometry": {"coordinates":[-1.60505413217417,54.953569763647],"type":"Point"}
}