{
  "type": "Feature",
  "properties": {
    "iso:country": "GB",
    "wof:name": "NE8 1RD",
    "wof:placetype": "postalcode"
  },
  "geometry": {"coordinates":[-1.605054,54.95357],"type":"Point"}
}
