{
  "type": "Feature",
  "properties": {
    "iso:country": "GB",
    "wof:name": "NG32 3JS",
    "wof:placetype": "postalcode"
  },
  "geometry": {"coordinates":[-0.589672,53.04209],"type":"Point"}
}
