{
  "type": "Feature",
  "properties": {
    "iso:country":"GB",
    "wof:name":"NG32 3JS",
    "wof:placetype":"postalcode"
},
  "geometry": {"coordinates":[-0.58967175259084,53.04208964734684],"type":"Point"}
}