{
  "type": "Feature",
  "properties": {
    "iso:country":"GB",
    "wof:name":"DT6 6DP",
    "wof:placetype":"postalcode"
},
  "geometry": {"coordinates":[-2.84522995862792,50.7402289046905],"type":"Point"}
}