{
  "type": "Feature",
  "properties": {
    "iso:country": "GB",
    "wof:name": "DT6 6DP",
    "wof:placetype": "postalcode"
  },
  "geometry": {"coordinates":[-2.84523,50.740229],"type":"Point"}
}
