{
  "type": "Feature",
  "properties": {
    "iso:country": "GB",
    "wof:name": "EH5 3NE",
    "wof:placetype": "postalcode"
  },
  "geometry": {"coordinates":[-3.210814,55.974087],"type":"Point"}
}
