{
  "type": "Feature",
  "properties": {
    "date:inception_lower": "1980-01-01",
    "date:inception_upper": "1980-01-01",
    "iso:country": "GB",
    "wof:name": "EH5 3NE",
    "wof:placetype": "postalcode"
  },
  "geometry": {"coordinates":[-3.210814,55.974087],"type":"Point"}
}
