{
  "type": "Feature",
  "properties": {
    "iso:country":"GB",
    "wof:name":"SS2 4RJ",
    "wof:placetype":"postalcode"
},
  "geometry": {"coordinates":[0.73940008392637,51.54784167273237],"type":"Point"}
}