{
  "type": "Feature",
  "properties": {
    "iso:country": "GB",
    "wof:name": "CA28 9SA",
    "wof:placetype": "postalcode"
  },
  "geometry": {"coordinates":[-3.58519,54.522063],"type":"Point"}
}
