{
  "type": "Feature",
  "properties": {
    "date:inception_lower": "2016-05-01",
    "date:inception_upper": "2016-05-01",
    "iso:country": "GB",
    "wof:name": "CA28 9SA",
    "wof:placetype": "postalcode"
  },
  "geometry": {"coordinates":[-3.58564,54.522093],"type":"Point"}
}
