{
  "type": "Feature",
  "properties": {
    "iso:country": "GB",
    "wof:name": "EH21 8DP",
    "wof:placetype": "postalcode"
  },
  "geometry": {"coordinates":[-3.020149,55.940734],"type":"Point"}
}
