{
  "type": "Feature",
  "properties": {
    "iso:country": "GB",
    "wof:name": "IP32 6HJ",
    "wof:placetype": "postalcode"
  },
  "geometry": {"coordinates":[0.703662,52.266474],"type":"Point"}
}
