{
  "type": "Feature",
  "properties": {
    "date:inception_lower":"1980-01-01",
    "date:inception_upper":"1980-01-31",
    "iso:country":"GB",
    "wof:name":"IP32 6HJ",
    "wof:placetype":"postalcode"
},
  "geometry": {"coordinates":[0.703662,52.266474],"type":"Point"}
}