{
  "type": "Feature",
  "properties": {
    "iso:country": "GB",
    "wof:name": "TN38 8EH",
    "wof:placetype": "postalcode"
  },
  "geometry": {"coordinates":[0.527544,50.851811],"type":"Point"}
}
