{
  "type": "Feature",
  "properties": {
    "date:inception_lower":"1992-01-01",
    "date:inception_upper":"1992-01-31",
    "iso:country":"GB",
    "wof:name":"TN38 8EH",
    "wof:placetype":"postalcode"
},
  "geometry": {"coordinates":[0.527544,50.851811],"type":"Point"}
}