{
  "type": "Feature",
  "properties": {
    "iso:country":"GB",
    "wof:name":"DE13 0QX",
    "wof:placetype":"postalcode"
},
  "geometry": {"coordinates":[-1.66157586629863,52.81792477512516],"type":"Point"}
}