{
  "type": "Feature",
  "properties": {
    "iso:country": "GB",
    "wof:name": "PH1 1NH",
    "wof:placetype": "postalcode"
  },
  "geometry": {"coordinates":[-3.46178,56.39426],"type":"Point"}
}
