{
  "type": "Feature",
  "properties": {
    "date:inception_lower": "1980-01-01",
    "date:inception_upper": "1980-01-01",
    "iso:country": "GB",
    "wof:name": "PH1 1NH",
    "wof:placetype": "postalcode"
  },
  "geometry": {"coordinates":[-3.46178,56.39426],"type":"Point"}
}
