{
  "type": "Feature",
  "properties": {
    "iso:country": "GB",
    "wof:name": "NR28 0BB",
    "wof:placetype": "postalcode"
  },
  "geometry": {"coordinates":[1.385166,52.824509],"type":"Point"}
}
