{
  "type": "Feature",
  "properties": {
    "iso:country":"GB",
    "wof:name":"NR28 0BB",
    "wof:placetype":"postalcode"
},
  "geometry": {"coordinates":[1.38516612239283,52.82450857438438],"type":"Point"}
}