{
  "type": "Feature",
  "properties": {
    "date:inception_lower": "1980-01-01",
    "date:inception_upper": "1980-01-01",
    "iso:country": "GB",
    "wof:name": "NR28 0BB",
    "wof:placetype": "postalcode"
  },
  "geometry": {"coordinates":[1.385166,52.824509],"type":"Point"}
}
