{
  "type": "Feature",
  "properties": {
    "date:inception_lower":"1992-08-01",
    "date:inception_upper":"1992-08-31",
    "iso:country":"GB",
    "wof:name":"BN17 5BF",
    "wof:placetype":"postalcode"
},
  "geometry": {"coordinates":[-0.548432,50.810254],"type":"Point"}
}