{
  "type": "Feature",
  "properties": {
    "iso:country": "GB",
    "wof:name": "BN17 5BF",
    "wof:placetype": "postalcode"
  },
  "geometry": {"coordinates":[-0.548432,50.810254],"type":"Point"}
}
