{
  "type": "Feature",
  "properties": {
    "iso:country":"GB",
    "wof:name":"SP8 4XE",
    "wof:placetype":"postalcode"
},
  "geometry": {"coordinates":[-2.2793516367726,51.03584221154544],"type":"Point"}
}