{
  "type": "Feature",
  "properties": {
    "iso:country":"GB",
    "wof:name":"BA14 7EH",
    "wof:placetype":"postalcode"
},
  "geometry": {"coordinates":[-2.20260520191293,51.31857342894866],"type":"Point"}
}