{
  "type": "Feature",
  "properties": {
    "iso:country": "GB",
    "wof:name": "BA14 7EH",
    "wof:placetype": "postalcode"
  },
  "geometry": {"coordinates":[-2.202645,51.318597],"type":"Point"}
}
