{
  "type": "Feature",
  "properties": {
    "date:inception_lower": "1993-01-01",
    "date:inception_upper": "1993-01-01",
    "iso:country": "GB",
    "wof:name": "BA14 7EH",
    "wof:placetype": "postalcode"
  },
  "geometry": {"coordinates":[-2.202601,51.31857],"type":"Point"}
}
