{
  "type": "Feature",
  "properties": {
    "iso:country":"GB",
    "wof:name":"BS37 4FG",
    "wof:placetype":"postalcode"
},
  "geometry": {"coordinates":[-2.40622685605026,51.53636943059938],"type":"Point"}
}