{
  "type": "Feature",
  "properties": {
    "iso:country": "GB",
    "wof:name": "BS37 4FG",
    "wof:placetype": "postalcode"
  },
  "geometry": {"coordinates":[-2.406227,51.536369],"type":"Point"}
}
