{
  "type": "Feature",
  "properties": {
    "date:inception_lower":"2011-09-01",
    "date:inception_upper":"2011-09-30",
    "iso:country":"GB",
    "wof:name":"BS37 4FG",
    "wof:placetype":"postalcode"
},
  "geometry": {"coordinates":[-2.406227,51.536369],"type":"Point"}
}