{
  "type": "Feature",
  "properties": {
    "iso:country":"GB",
    "wof:name":"KY1 2TF",
    "wof:placetype":"postalcode"
},
  "geometry": {"coordinates":[-3.1244675917045,56.12494988076644],"type":"Point"}
}