{
  "type": "Feature",
  "properties": {
    "date:inception_lower":"1980-01-01",
    "date:inception_upper":"1980-01-31",
    "iso:country":"GB",
    "wof:name":"TR15 3YA",
    "wof:placetype":"postalcode"
},
  "geometry": {"coordinates":[-5.266224,50.21317],"type":"Point"}
}