{
  "type": "Feature",
  "properties": {
    "date:inception_lower": "2016-05-01",
    "date:inception_upper": "2016-05-01",
    "iso:country": "GB",
    "wof:name": "CW9 7YJ",
    "wof:placetype": "postalcode"
  },
  "geometry": {"coordinates":[-2.455447,53.270901],"type":"Point"}
}
