{
  "type": "Feature",
  "properties": {
    "date:inception_lower": "1980-01-01",
    "date:inception_upper": "1980-01-01",
    "iso:country": "GB",
    "wof:name": "CT4 6TT",
    "wof:placetype": "postalcode"
  },
  "geometry": {"coordinates":[1.11189,51.151563],"type":"Point"}
}
