{
  "type": "Feature",
  "properties": {
    "iso:country":"GB",
    "wof:name":"CT4 6TT",
    "wof:placetype":"postalcode"
},
  "geometry": {"coordinates":[1.11188948383904,51.15156301411677],"type":"Point"}
}