{
  "type": "Feature",
  "properties": {
    "iso:country":"GB",
    "wof:name":"IV3 5TH",
    "wof:placetype":"postalcode"
},
  "geometry": {"coordinates":[-4.23756972493352,57.46207754086036],"type":"Point"}
}