{
  "type": "Feature",
  "properties": {
    "date:inception_lower": "2009-10-01",
    "date:inception_upper": "2009-10-01",
    "iso:country": "GB",
    "wof:name": "IV3 5TH",
    "wof:placetype": "postalcode"
  },
  "geometry": {"coordinates":[-4.23757,57.462078],"type":"Point"}
}
