{
  "type": "Feature",
  "properties": {
    "iso:country":"GB",
    "wof:name":"CW11 1EP",
    "wof:placetype":"postalcode"
},
  "geometry": {"coordinates":[-2.37707713632715,53.14213877159462],"type":"Point"}
}