{
  "type": "Feature",
  "properties": {
    "iso:country": "GB",
    "wof:name": "BS16 1FD",
    "wof:placetype": "postalcode"
  },
  "geometry": {"coordinates":[-2.562224,51.497511],"type":"Point"}
}
