{
  "type": "Feature",
  "properties": {
    "date:inception_lower":"2012-11-01",
    "date:inception_upper":"2012-11-30",
    "iso:country":"GB",
    "wof:name":"BS16 1FD",
    "wof:placetype":"postalcode"
},
  "geometry": {"coordinates":[-2.562224,51.497511],"type":"Point"}
}