{
  "type": "Feature",
  "properties": {
    "iso:country":"GB",
    "wof:name":"BS16 1FD",
    "wof:placetype":"postalcode"
},
  "geometry": {"coordinates":[-2.56222384960265,51.49751125856535],"type":"Point"}
}