{
  "type": "Feature",
  "properties": {
    "iso:country":"GB",
    "wof:name":"HA7 4FP",
    "wof:placetype":"postalcode"
},
  "geometry": {"coordinates":[-0.31589188862376,51.61320295985995],"type":"Point"}
}