{
  "type": "Feature",
  "properties": {
    "date:inception_lower": "1980-01-01",
    "date:inception_upper": "1980-01-01",
    "iso:country": "GB",
    "wof:name": "BS7 0SG",
    "wof:placetype": "postalcode"
  },
  "geometry": {"coordinates":[-2.579499,51.50104],"type":"Point"}
}
