{
  "type": "Feature",
  "properties": {
    "iso:country":"GB",
    "wof:name":"BS7 0SG",
    "wof:placetype":"postalcode"
},
  "geometry": {"coordinates":[-2.57949902547699,51.50114965162482],"type":"Point"}
}