{
  "type": "Feature",
  "properties": {
    "date:inception_lower": "1986-07-01",
    "date:inception_upper": "1986-07-01",
    "iso:country": "GB",
    "wof:name": "IP26 5NP",
    "wof:placetype": "postalcode"
  },
  "geometry": {"coordinates":[0.603627,52.522113],"type":"Point"}
}
