{
  "type": "Feature",
  "properties": {
    "iso:country":"GB",
    "wof:name":"IP26 5NP",
    "wof:placetype":"postalcode"
},
  "geometry": {"coordinates":[0.60362663229482,52.52211283923347],"type":"Point"}
}