{
  "type": "Feature",
  "properties": {
    "iso:country":"GB",
    "wof:name":"TA12 6LR",
    "wof:placetype":"postalcode"
},
  "geometry": {"coordinates":[-2.77654258554688,50.95945257830387],"type":"Point"}
}