{
  "type": "Feature",
  "properties": {
    "iso:country": "GB",
    "wof:name": "SL0 9RQ",
    "wof:placetype": "postalcode"
  },
  "geometry": {"coordinates":[-0.525935,51.509681],"type":"Point"}
}
