{
  "type": "Feature",
  "properties": {
    "iso:country":"GB",
    "wof:name":"MK9 3NS",
    "wof:placetype":"postalcode"
},
  "geometry": {"coordinates":[-0.75270647629831,52.04773715610187],"type":"Point"}
}