{
  "type": "Feature",
  "properties": {
    "date:inception_lower": "1990-02-01",
    "date:inception_upper": "1990-02-01",
    "iso:country": "GB",
    "wof:name": "MK9 3NS",
    "wof:placetype": "postalcode"
  },
  "geometry": {"coordinates":[-0.752706,52.047737],"type":"Point"}
}
