{
  "type": "Feature",
  "properties": {
    "iso:country":"GB",
    "wof:name":"BN14 8PY",
    "wof:placetype":"postalcode"
},
  "geometry": {"coordinates":[-0.36374777054468,50.83194831484108],"type":"Point"}
}