{
  "type": "Feature",
  "properties": {
    "iso:country":"GB",
    "wof:name":"SG9 0BS",
    "wof:placetype":"postalcode"
},
  "geometry": {"coordinates":[0.03830868985069,51.9826303463906],"type":"Point"}
}