{
  "type": "Feature",
  "properties": {
    "iso:country":"GB",
    "wof:name":"LL65 3RD",
    "wof:placetype":"postalcode"
},
  "geometry": {"coordinates":[-4.48042031170202,53.27504496785185],"type":"Point"}
}