{
  "type": "Feature",
  "properties": {
    "iso:country": "GB",
    "wof:name": "LL65 3RD",
    "wof:placetype": "postalcode"
  },
  "geometry": {"coordinates":[-4.48042,53.275045],"type":"Point"}
}
