{
  "type": "Feature",
  "properties": {
    "iso:country":"GB",
    "wof:name":"CR4 1FJ",
    "wof:placetype":"postalcode"
},
  "geometry": {"coordinates":[-0.14532213355814,51.39759032873888],"type":"Point"}
}