{
  "type": "Feature",
  "properties": {
    "date:inception_lower": "2023-01-01",
    "date:inception_upper": "2023-01-01",
    "iso:country": "GB",
    "wof:name": "KA5 6JT",
    "wof:placetype": "postalcode"
  },
  "geometry": {"coordinates":[-4.348785,55.508879],"type":"Point"}
}
