{
  "type": "Feature",
  "properties": {
    "date:inception_lower":"1980-01-01",
    "date:inception_upper":"1980-01-31",
    "iso:country":"GB",
    "wof:name":"B69 3JS",
    "wof:placetype":"postalcode"
},
  "geometry": {"coordinates":[-2.040127,52.515888],"type":"Point"}
}