{
  "type": "Feature",
  "properties": {
    "iso:country":"GB",
    "wof:name":"B69 3JS",
    "wof:placetype":"postalcode"
},
  "geometry": {"coordinates":[-2.04012698037081,52.51588811034973],"type":"Point"}
}