{
  "type": "Feature",
  "properties": {
    "iso:country":"GB",
    "wof:name":"NE37 2EF",
    "wof:placetype":"postalcode"
},
  "geometry": {"coordinates":[-1.51784781705639,54.91181034306934],"type":"Point"}
}