{
  "type": "Feature",
  "properties": {
    "iso:country": "GB",
    "wof:name": "CW7 4EU",
    "wof:placetype": "postalcode"
  },
  "geometry": {"coordinates":[-2.521093,53.188275],"type":"Point"}
}
