{
  "type": "Feature",
  "properties": {
    "date:inception_lower":"2014-02-01",
    "date:inception_upper":"2014-02-28",
    "iso:country":"GB",
    "wof:name":"CW7 4EU",
    "wof:placetype":"postalcode"
},
  "geometry": {"coordinates":[-2.521093,53.188275],"type":"Point"}
}