{
  "type": "Feature",
  "properties": {
    "date:inception_lower":"1980-01-01",
    "date:inception_upper":"1980-01-31",
    "iso:country":"GB",
    "wof:name":"M35 9WJ",
    "wof:placetype":"postalcode"
},
  "geometry": {"coordinates":[-2.122797,53.501357],"type":"Point"}
}