{
  "type": "Feature",
  "properties": {
    "iso:country": "GB",
    "wof:name": "M35 9WJ",
    "wof:placetype": "postalcode"
  },
  "geometry": {"coordinates":[-2.122797,53.501357],"type":"Point"}
}
