{
  "type": "Feature",
  "properties": {
    "iso:country":"GB",
    "wof:name":"NE6 2JB",
    "wof:placetype":"postalcode"
},
  "geometry": {"coordinates":[-1.56414731144315,54.97497026233954],"type":"Point"}
}