{
  "type": "Feature",
  "properties": {
    "date:inception_lower": "1991-09-01",
    "date:inception_upper": "1991-09-01",
    "iso:country": "GB",
    "wof:name": "BN27 3TJ",
    "wof:placetype": "postalcode"
  },
  "geometry": {"coordinates":[0.249916,50.852945],"type":"Point"}
}
