{
  "type": "Feature",
  "properties": {
    "iso:country":"GB",
    "wof:name":"TS6 9LR",
    "wof:placetype":"postalcode"
},
  "geometry": {"coordinates":[-1.1435650364278,54.56119370123153],"type":"Point"}
}