{
  "type": "Feature",
  "properties": {
    "iso:country":"GB",
    "wof:name":"GL3 2NJ",
    "wof:placetype":"postalcode"
},
  "geometry": {"coordinates":[-2.16670226935061,51.87343978767073],"type":"Point"}
}