{
  "type": "Feature",
  "properties": {
    "date:inception_lower":"1980-01-01",
    "date:inception_upper":"1980-01-31",
    "iso:country":"GB",
    "wof:name":"GL3 2NJ",
    "wof:placetype":"postalcode"
},
  "geometry": {"coordinates":[-2.16677,51.873446],"type":"Point"}
}