{
  "type": "Feature",
  "properties": {
    "iso:country":"GB",
    "wof:name":"E7 0HX",
    "wof:placetype":"postalcode"
},
  "geometry": {"coordinates":[0.02587425208953,51.55185898015873],"type":"Point"}
}