{
  "type": "Feature",
  "properties": {
    "date:inception_lower": "2010-08-01",
    "date:inception_upper": "2010-08-01",
    "iso:country": "GB",
    "wof:name": "E7 0HX",
    "wof:placetype": "postalcode"
  },
  "geometry": {"coordinates":[0.025874,51.551859],"type":"Point"}
}
