{
  "type": "Feature",
  "properties": {
    "date:inception_lower": "1980-01-01",
    "date:inception_upper": "1980-01-01",
    "iso:country": "GB",
    "wof:name": "PO9 5PR",
    "wof:placetype": "postalcode"
  },
  "geometry": {"coordinates":[-0.966228,50.871008],"type":"Point"}
}
