{
  "type": "Feature",
  "properties": {
    "iso:country": "GB",
    "wof:name": "EH18 1BD",
    "wof:placetype": "postalcode"
  },
  "geometry": {"coordinates":[-3.097063,55.896525],"type":"Point"}
}
