{
  "type": "Feature",
  "properties": {
    "iso:country":"GB",
    "wof:name":"NR27 9DX",
    "wof:placetype":"postalcode"
},
  "geometry": {"coordinates":[1.29664026263999,52.93035460800324],"type":"Point"}
}