{
  "type": "Feature",
  "properties": {
    "iso:country":"GB",
    "wof:name":"G42 9JD",
    "wof:placetype":"postalcode"
},
  "geometry": {"coordinates":[-4.25937579952765,55.82408730133575],"type":"Point"}
}