{
  "type": "Feature",
  "properties": {
    "iso:country":"GB",
    "wof:name":"OX4 7FR",
    "wof:placetype":"postalcode"
},
  "geometry": {"coordinates":[-1.20215038766893,51.71490239882691],"type":"Point"}
}