{
  "type": "Feature",
  "properties": {
    "iso:country": "GB",
    "wof:name": "G68 0HU",
    "wof:placetype": "postalcode"
  },
  "geometry": {"coordinates":[-3.984943,55.961676],"type":"Point"}
}
