{
  "type": "Feature",
  "properties": {
    "iso:country": "GB",
    "wof:name": "NP16 6TL",
    "wof:placetype": "postalcode"
  },
  "geometry": {"coordinates":[-2.690989,51.698726],"type":"Point"}
}
