{
  "type": "Feature",
  "properties": {
    "iso:country":"GB",
    "wof:name":"NP16 6TL",
    "wof:placetype":"postalcode"
},
  "geometry": {"coordinates":[-2.69098929641076,51.69872634475392],"type":"Point"}
}