{
  "type": "Feature",
  "properties": {
    "date:inception_lower": "2008-10-01",
    "date:inception_upper": "2008-10-01",
    "iso:country": "GB",
    "wof:name": "OX10 0DZ",
    "wof:placetype": "postalcode"
  },
  "geometry": {"coordinates":[-1.134529,51.60534],"type":"Point"}
}
