{
  "type": "Feature",
  "properties": {
    "iso:country":"GB",
    "wof:name":"OX10 0DZ",
    "wof:placetype":"postalcode"
},
  "geometry": {"coordinates":[-1.13452949535631,51.6053396402653],"type":"Point"}
}