{
  "type": "Feature",
  "properties": {
    "iso:country":"GB",
    "wof:name":"PO21 2DS",
    "wof:placetype":"postalcode"
},
  "geometry": {"coordinates":[-0.67765675541434,50.79248253302711],"type":"Point"}
}