{
  "type": "Feature",
  "properties": {
    "date:inception_lower": "1987-04-01",
    "date:inception_upper": "1987-04-01",
    "iso:country": "GB",
    "wof:name": "B63 2UJ",
    "wof:placetype": "postalcode"
  },
  "geometry": {"coordinates":[-2.08833,52.46084],"type":"Point"}
}
