{
  "type": "Feature",
  "properties": {
    "date:inception_lower": "1995-07-01",
    "date:inception_upper": "1995-07-01",
    "iso:country": "GB",
    "wof:name": "TN13 1XH",
    "wof:placetype": "postalcode"
  },
  "geometry": {"coordinates":[0.186352,51.274942],"type":"Point"}
}
