{
  "type": "Feature",
  "properties": {
    "iso:country":"GB",
    "wof:name":"TN13 1XH",
    "wof:placetype":"postalcode"
},
  "geometry": {"coordinates":[0.18635238942103,51.27494171041715],"type":"Point"}
}