{
  "type": "Feature",
  "properties": {
    "iso:country":"GB",
    "wof:name":"CT1 3HQ",
    "wof:placetype":"postalcode"
},
  "geometry": {"coordinates":[1.08486223703171,51.27538108433451],"type":"Point"}
}