{
  "type": "Feature",
  "properties": {
    "iso:country": "GB",
    "wof:name": "RG7 2LS",
    "wof:placetype": "postalcode"
  },
  "geometry": {"coordinates":[-1.085245,51.346885],"type":"Point"}
}
