{
  "type": "Feature",
  "properties": {
    "date:inception_lower":"1980-01-01",
    "date:inception_upper":"1980-01-31",
    "iso:country":"GB",
    "wof:name":"RG7 2LS",
    "wof:placetype":"postalcode"
},
  "geometry": {"coordinates":[-1.085245,51.346885],"type":"Point"}
}