{
  "type": "Feature",
  "properties": {
    "date:inception_lower": "2013-10-01",
    "date:inception_upper": "2013-10-01",
    "iso:country": "GB",
    "wof:name": "HD1 9UY",
    "wof:placetype": "postalcode"
  },
  "geometry": {"coordinates":[-1.78391,53.644311],"type":"Point"}
}
