{
  "type": "Feature",
  "properties": {
    "iso:country":"GB",
    "wof:name":"LU3 2TU",
    "wof:placetype":"postalcode"
},
  "geometry": {"coordinates":[-0.45753989100718,51.90695201752816],"type":"Point"}
}