{
  "type": "Feature",
  "properties": {
    "date:inception_lower": "2000-06-01",
    "date:inception_upper": "2000-06-01",
    "iso:country": "GB",
    "wof:name": "LU3 2TU",
    "wof:placetype": "postalcode"
  },
  "geometry": {"coordinates":[-0.45754,51.906952],"type":"Point"}
}
