{
  "type": "Feature",
  "properties": {
    "iso:country":"GB",
    "wof:name":"FK2 0RQ",
    "wof:placetype":"postalcode"
},
  "geometry": {"coordinates":[-3.70002666599016,55.98824056736414],"type":"Point"}
}