{
  "type": "Feature",
  "properties": {
    "date:inception_lower": "1980-01-01",
    "date:inception_upper": "1980-01-01",
    "iso:country": "GB",
    "wof:name": "SG19 2HY",
    "wof:placetype": "postalcode"
  },
  "geometry": {"coordinates":[-0.212554,52.160658],"type":"Point"}
}
