{
  "type": "Feature",
  "properties": {
    "iso:country":"GB",
    "wof:name":"HP5 2RL",
    "wof:placetype":"postalcode"
},
  "geometry": {"coordinates":[-0.62607742878971,51.71248385064342],"type":"Point"}
}