{
  "type": "Feature",
  "properties": {
    "iso:country": "GB",
    "wof:name": "OX28 4FA",
    "wof:placetype": "postalcode"
  },
  "geometry": {"coordinates":[-1.484655,51.77691],"type":"Point"}
}
