{
  "type": "Feature",
  "properties": {
    "iso:country": "GB",
    "wof:name": "BN14 9NA",
    "wof:placetype": "postalcode"
  },
  "geometry": {"coordinates":[-0.370948,50.831132],"type":"Point"}
}
