{
  "type": "Feature",
  "properties": {
    "date:inception_lower": "1984-10-01",
    "date:inception_upper": "1984-10-01",
    "iso:country": "GB",
    "wof:name": "BN14 9NA",
    "wof:placetype": "postalcode"
  },
  "geometry": {"coordinates":[-0.370948,50.831132],"type":"Point"}
}
