{
  "type": "Feature",
  "properties": {
    "date:inception_lower": "2020-04-01",
    "date:inception_upper": "2020-04-01",
    "iso:country": "GB",
    "wof:name": "CV47 0NL",
    "wof:placetype": "postalcode"
  },
  "geometry": {"coordinates":[-1.395926,52.252989],"type":"Point"}
}
