{
  "type": "Feature",
  "properties": {
    "iso:country":"GB",
    "wof:name":"W5 3EF",
    "wof:placetype":"postalcode"
},
  "geometry": {"coordinates":[-0.28594034237229,51.52370103180949],"type":"Point"}
}