{
  "type": "Feature",
  "properties": {
    "date:inception_lower":"1980-01-01",
    "date:inception_upper":"1980-01-31",
    "iso:country":"GB",
    "wof:name":"W5 3EF",
    "wof:placetype":"postalcode"
},
  "geometry": {"coordinates":[-0.28594,51.523701],"type":"Point"}
}