{
  "type": "Feature",
  "properties": {
    "iso:country":"GB",
    "wof:name":"BB3 0JX",
    "wof:placetype":"postalcode"
},
  "geometry": {"coordinates":[-2.4654814548674,53.69909281813027],"type":"Point"}
}