{
  "type": "Feature",
  "properties": {
    "iso:country": "GB",
    "wof:name": "BB3 0JX",
    "wof:placetype": "postalcode"
  },
  "geometry": {"coordinates":[-2.465481,53.699093],"type":"Point"}
}
