{
  "type": "Feature",
  "properties": {
    "date:inception_lower": "1991-01-01",
    "date:inception_upper": "1991-01-01",
    "iso:country": "GB",
    "wof:name": "BB3 0JX",
    "wof:placetype": "postalcode"
  },
  "geometry": {"coordinates":[-2.465481,53.699093],"type":"Point"}
}
