{
  "type": "Feature",
  "properties": {
    "iso:country":"GB",
    "wof:name":"N18 2LY",
    "wof:placetype":"postalcode"
},
  "geometry": {"coordinates":[-0.06373133015478,51.61601381297908],"type":"Point"}
}