{
  "type": "Feature",
  "properties": {
    "iso:country":"GB",
    "wof:name":"SL6 3XB",
    "wof:placetype":"postalcode"
},
  "geometry": {"coordinates":[-0.76313044840976,51.49902194881285],"type":"Point"}
}