{
  "type": "Feature",
  "properties": {
    "iso:country":"GB",
    "wof:name":"S80 1SE",
    "wof:placetype":"postalcode"
},
  "geometry": {"coordinates":[-1.12628087392518,53.30795347178402],"type":"Point"}
}