{
  "type": "Feature",
  "properties": {
    "iso:country":"GB",
    "wof:name":"SW5 0ER",
    "wof:placetype":"postalcode"
},
  "geometry": {"coordinates":[-0.19003310090068,51.49214465913726],"type":"Point"}
}