{
  "type": "Feature",
  "properties": {
    "iso:country": "GB",
    "wof:name": "AB45 2PY",
    "wof:placetype": "postalcode"
  },
  "geometry": {"coordinates":[-2.696031,57.680703],"type":"Point"}
}
