{
  "type": "Feature",
  "properties": {
    "date:inception_lower":"1990-08-01",
    "date:inception_upper":"1990-08-31",
    "iso:country":"GB",
    "wof:name":"AB45 2PY",
    "wof:placetype":"postalcode"
},
  "geometry": {"coordinates":[-2.696031,57.680703],"type":"Point"}
}