{
  "type": "Feature",
  "properties": {
    "iso:country":"GB",
    "wof:name":"AB45 2PY",
    "wof:placetype":"postalcode"
},
  "geometry": {"coordinates":[-2.6960306445414,57.68070314698727],"type":"Point"}
}