{
  "type": "Feature",
  "properties": {
    "iso:country": "GB",
    "wof:name": "DE1 2JY",
    "wof:placetype": "postalcode"
  },
  "geometry": {"coordinates":[-1.469918,52.918544],"type":"Point"}
}
