{
  "type": "Feature",
  "properties": {
    "iso:country": "GB",
    "wof:name": "SA14 8HJ",
    "wof:placetype": "postalcode"
  },
  "geometry": {"coordinates":[-4.120682,51.733874],"type":"Point"}
}
