{
  "type": "Feature",
  "properties": {
    "iso:country":"GB",
    "wof:name":"SA14 8HJ",
    "wof:placetype":"postalcode"
},
  "geometry": {"coordinates":[-4.1206598104477,51.733867245048],"type":"Point"}
}