{
  "type": "Feature",
  "properties": {
    "date:inception_lower": "1980-01-01",
    "date:inception_upper": "1980-01-01",
    "iso:country": "GB",
    "wof:name": "SA14 8HJ",
    "wof:placetype": "postalcode"
  },
  "geometry": {"coordinates":[-4.120682,51.733874],"type":"Point"}
}
