{
  "type": "Feature",
  "properties": {
    "date:inception_lower": "2024-05-01",
    "date:inception_upper": "2024-05-01",
    "iso:country": "GB",
    "wof:name": "WA10 3AE",
    "wof:placetype": "postalcode"
  },
  "geometry": {"coordinates":[-2.762253,53.437702],"type":"Point"}
}
