{
  "type": "Feature",
  "properties": {
    "iso:country": "GB",
    "wof:name": "ST1 5LA",
    "wof:placetype": "postalcode"
  },
  "geometry": {"coordinates":[-2.177246,53.025935],"type":"Point"}
}
