{
  "type": "Feature",
  "properties": {
    "date:inception_lower": "1980-01-01",
    "date:inception_upper": "1980-01-01",
    "iso:country": "GB",
    "wof:name": "CM16 6TN",
    "wof:placetype": "postalcode"
  },
  "geometry": {"coordinates":[0.12393,51.704295],"type":"Point"}
}
