{
  "type": "Feature",
  "properties": {
    "iso:country":"GB",
    "wof:name":"CM16 6TN",
    "wof:placetype":"postalcode"
},
  "geometry": {"coordinates":[0.12393028971638,51.70429516736282],"type":"Point"}
}