{
  "type": "Feature",
  "properties": {
    "iso:country": "GB",
    "wof:name": "WA14 4TT",
    "wof:placetype": "postalcode"
  },
  "geometry": {"coordinates":[-2.352112,53.39027],"type":"Point"}
}
