{
  "type": "Feature",
  "properties": {
    "iso:country":"GB",
    "wof:name":"WA14 4TT",
    "wof:placetype":"postalcode"
},
  "geometry": {"coordinates":[-2.35211216840446,53.39027040229013],"type":"Point"}
}