{
  "type": "Feature",
  "properties": {
    "date:inception_lower":"2003-11-01",
    "date:inception_upper":"2003-11-30",
    "iso:country":"GB",
    "wof:name":"WA14 4TT",
    "wof:placetype":"postalcode"
},
  "geometry": {"coordinates":[-2.352112,53.39027],"type":"Point"}
}