{
  "type": "Feature",
  "properties": {
    "iso:country": "GB",
    "wof:name": "TQ12 1DY",
    "wof:placetype": "postalcode"
  },
  "geometry": {"coordinates":[-3.600396,50.522561],"type":"Point"}
}
