{
  "type": "Feature",
  "properties": {
    "iso:country": "GB",
    "wof:name": "GU21 7RS",
    "wof:placetype": "postalcode"
  },
  "geometry": {"coordinates":[-0.595559,51.311518],"type":"Point"}
}
