{
  "type": "Feature",
  "properties": {
    "iso:country": "GB",
    "wof:name": "SN16 0AL",
    "wof:placetype": "postalcode"
  },
  "geometry": {"coordinates":[-2.101478,51.58686],"type":"Point"}
}
