{
  "type": "Feature",
  "properties": {
    "date:inception_lower":"1980-01-01",
    "date:inception_upper":"1980-01-31",
    "iso:country":"GB",
    "wof:name":"SN16 0AL",
    "wof:placetype":"postalcode"
},
  "geometry": {"coordinates":[-2.101478,51.58686],"type":"Point"}
}