{
  "type": "Feature",
  "properties": {
    "iso:country":"GB",
    "wof:name":"SN16 0AL",
    "wof:placetype":"postalcode"
},
  "geometry": {"coordinates":[-2.10147786559188,51.58685962150766],"type":"Point"}
}