{
  "type": "Feature",
  "properties": {
    "iso:country": "GB",
    "wof:name": "LL41 3SG",
    "wof:placetype": "postalcode"
  },
  "geometry": {"coordinates":[-3.956421,52.987071],"type":"Point"}
}
