{
  "type": "Feature",
  "properties": {
    "iso:country":"GB",
    "wof:name":"LL41 3SG",
    "wof:placetype":"postalcode"
},
  "geometry": {"coordinates":[-3.95642102301664,52.9870711363085],"type":"Point"}
}