{
  "type": "Feature",
  "properties": {
    "date:inception_lower": "1980-01-01",
    "date:inception_upper": "1980-01-01",
    "iso:country": "GB",
    "wof:name": "LL41 3SG",
    "wof:placetype": "postalcode"
  },
  "geometry": {"coordinates":[-3.956421,52.987071],"type":"Point"}
}
