{
  "type": "Feature",
  "properties": {
    "iso:country":"GB",
    "wof:name":"NG1 4DS",
    "wof:placetype":"postalcode"
},
  "geometry": {"coordinates":[-1.15057174406228,52.95882508646496],"type":"Point"}
}