{
  "type": "Feature",
  "properties": {
    "iso:country":"GB",
    "wof:name":"LE2 0AS",
    "wof:placetype":"postalcode"
},
  "geometry": {"coordinates":[-1.11439023474822,52.63634110722364],"type":"Point"}
}