{
  "type": "Feature",
  "properties": {
    "iso:country":"GB",
    "wof:name":"OX18 3FF",
    "wof:placetype":"postalcode"
},
  "geometry": {"coordinates":[-1.58503264244678,51.75896503886722],"type":"Point"}
}