{
  "type": "Feature",
  "properties": {
    "date:inception_lower": "2012-11-01",
    "date:inception_upper": "2012-11-01",
    "iso:country": "GB",
    "wof:name": "OX18 3FF",
    "wof:placetype": "postalcode"
  },
  "geometry": {"coordinates":[-1.585033,51.758965],"type":"Point"}
}
