{
  "type": "Feature",
  "properties": {
    "date:inception_lower":"1980-01-01",
    "date:inception_upper":"1980-01-31",
    "iso:country":"GB",
    "wof:name":"SL1 8HL",
    "wof:placetype":"postalcode"
},
  "geometry": {"coordinates":[-0.662709,51.538627],"type":"Point"}
}