{
  "type": "Feature",
  "properties": {
    "iso:country": "GB",
    "wof:name": "SL1 8HL",
    "wof:placetype": "postalcode"
  },
  "geometry": {"coordinates":[-0.662709,51.538627],"type":"Point"}
}
