{
  "type": "Feature",
  "properties": {
    "iso:country":"GB",
    "wof:name":"PA2 6LZ",
    "wof:placetype":"postalcode"
},
  "geometry": {"coordinates":[-4.42306638485364,55.83525182638248],"type":"Point"}
}