{
  "type": "Feature",
  "properties": {
    "iso:country":"GB",
    "wof:name":"DY4 8NY",
    "wof:placetype":"postalcode"
},
  "geometry": {"coordinates":[-2.06798426436451,52.51980391228951],"type":"Point"}
}