{
  "type": "Feature",
  "properties": {
    "date:inception_lower": "2014-12-01",
    "date:inception_upper": "2014-12-01",
    "iso:country": "GB",
    "wof:name": "DY4 8NY",
    "wof:placetype": "postalcode"
  },
  "geometry": {"coordinates":[-2.066491,52.520081],"type":"Point"}
}
