{
  "type": "Feature",
  "properties": {
    "iso:country":"GB",
    "wof:name":"S63 7FX",
    "wof:placetype":"postalcode"
},
  "geometry": {"coordinates":[-1.34750120126417,53.50916918779197],"type":"Point"}
}