{
  "type": "Feature",
  "properties": {
    "date:inception_lower":"2012-11-01",
    "date:inception_upper":"2012-11-30",
    "iso:country":"GB",
    "wof:name":"S63 7FX",
    "wof:placetype":"postalcode"
},
  "geometry": {"coordinates":[-1.347501,53.509169],"type":"Point"}
}