{
  "type": "Feature",
  "properties": {
    "iso:country":"GB",
    "wof:name":"BB5 4AL",
    "wof:placetype":"postalcode"
},
  "geometry": {"coordinates":[-2.38355719741496,53.75922619637485],"type":"Point"}
}