{
  "type": "Feature",
  "properties": {
    "iso:country":"GB",
    "wof:name":"SO50 7NU",
    "wof:placetype":"postalcode"
},
  "geometry": {"coordinates":[-1.29097567108769,50.9631136274474],"type":"Point"}
}