{
  "type": "Feature",
  "properties": {
    "iso:country":"GB",
    "wof:name":"CF42 5DD",
    "wof:placetype":"postalcode"
},
  "geometry": {"coordinates":[-3.54991264321053,51.68118040709641],"type":"Point"}
}