{
  "type": "Feature",
  "properties": {
    "date:inception_lower": "1980-01-01",
    "date:inception_upper": "1980-01-01",
    "iso:country": "GB",
    "wof:name": "BS9 3HT",
    "wof:placetype": "postalcode"
  },
  "geometry": {"coordinates":[-2.616189,51.495505],"type":"Point"}
}
