{
  "type": "Feature",
  "properties": {
    "iso:country":"GB",
    "wof:name":"DY2 0BL",
    "wof:placetype":"postalcode"
},
  "geometry": {"coordinates":[-2.09320309696382,52.47960169355218],"type":"Point"}
}