{
  "type": "Feature",
  "properties": {
    "iso:country":"GB",
    "wof:name":"SO22 6PY",
    "wof:placetype":"postalcode"
},
  "geometry": {"coordinates":[-1.35005768673356,51.08541102506769],"type":"Point"}
}