{
  "type": "Feature",
  "properties": {
    "iso:country":"GB",
    "wof:name":"KT14 6EB",
    "wof:placetype":"postalcode"
},
  "geometry": {"coordinates":[-0.50508102809818,51.33885019891713],"type":"Point"}
}