{
  "type": "Feature",
  "properties": {
    "date:inception_lower":"1999-06-01",
    "date:inception_upper":"1999-06-30",
    "iso:country":"GB",
    "wof:name":"KT14 6EB",
    "wof:placetype":"postalcode"
},
  "geometry": {"coordinates":[-0.505081,51.33885],"type":"Point"}
}