{
  "type": "Feature",
  "properties": {
    "iso:country":"GB",
    "wof:name":"OX16 0LU",
    "wof:placetype":"postalcode"
},
  "geometry": {"coordinates":[-1.36453591594889,52.0605442948079],"type":"Point"}
}