{
  "type": "Feature",
  "properties": {
    "iso:country":"GB",
    "wof:name":"BR7 6LT",
    "wof:placetype":"postalcode"
},
  "geometry": {"coordinates":[0.07618728259697,51.41868615915354],"type":"Point"}
}