{
  "type": "Feature",
  "properties": {
    "iso:country":"GB",
    "wof:name":"BB5 5RG",
    "wof:placetype":"postalcode"
},
  "geometry": {"coordinates":[-2.38023882198688,53.77805777009759],"type":"Point"}
}