{
  "type": "Feature",
  "properties": {
    "iso:country":"GB",
    "wof:name":"MK46 5LZ",
    "wof:placetype":"postalcode"
},
  "geometry": {"coordinates":[-0.71188774378622,52.15273666198603],"type":"Point"}
}