{
  "type": "Feature",
  "properties": {
    "date:inception_lower":"1994-12-01",
    "date:inception_upper":"1994-12-31",
    "iso:country":"GB",
    "wof:name":"SO31 5PP",
    "wof:placetype":"postalcode"
},
  "geometry": {"coordinates":[-1.343245,50.877505],"type":"Point"}
}