{
  "type": "Feature",
  "properties": {
    "iso:country":"GB",
    "wof:name":"SO31 5PP",
    "wof:placetype":"postalcode"
},
  "geometry": {"coordinates":[-1.34324498736549,50.87750494123438],"type":"Point"}
}