{
  "type": "Feature",
  "properties": {
    "iso:country": "GB",
    "wof:name": "SO31 5PP",
    "wof:placetype": "postalcode"
  },
  "geometry": {"coordinates":[-1.343245,50.877505],"type":"Point"}
}
