{
  "type": "Feature",
  "properties": {
    "iso:country": "GB",
    "wof:name": "CW5 5AG",
    "wof:placetype": "postalcode"
  },
  "geometry": {"coordinates":[-2.52199,53.067439],"type":"Point"}
}
