{
  "type": "Feature",
  "properties": {
    "date:inception_lower": "1980-01-01",
    "date:inception_upper": "1980-01-01",
    "iso:country": "GB",
    "wof:name": "DD9 7TY",
    "wof:placetype": "postalcode"
  },
  "geometry": {"coordinates":[-2.623058,56.793356],"type":"Point"}
}
