{
  "type": "Feature",
  "properties": {
    "iso:country":"GB",
    "wof:name":"DD9 7TY",
    "wof:placetype":"postalcode"
},
  "geometry": {"coordinates":[-2.62305794052243,56.79335567085483],"type":"Point"}
}