{
  "type": "Feature",
  "properties": {
    "iso:country":"GB",
    "wof:name":"HX2 8SJ",
    "wof:placetype":"postalcode"
},
  "geometry": {"coordinates":[-1.90969776907784,53.75284109364779],"type":"Point"}
}