{
  "type": "Feature",
  "properties": {
    "iso:country": "GB",
    "wof:name": "NR28 9QU",
    "wof:placetype": "postalcode"
  },
  "geometry": {"coordinates":[1.4448,52.797959],"type":"Point"}
}
