{
  "type": "Feature",
  "properties": {
    "date:inception_lower": "2023-10-01",
    "date:inception_upper": "2023-10-01",
    "iso:country": "GB",
    "wof:name": "CM7 4FS",
    "wof:placetype": "postalcode"
  },
  "geometry": {"coordinates":[0.447984,51.963665],"type":"Point"}
}
