{
  "type": "Feature",
  "properties": {
    "iso:country":"GB",
    "wof:name":"L32 5TL",
    "wof:placetype":"postalcode"
},
  "geometry": {"coordinates":[-2.89723182252193,53.47733238316938],"type":"Point"}
}