{
  "type": "Feature",
  "properties": {
    "date:inception_lower": "1980-01-01",
    "date:inception_upper": "1980-01-01",
    "iso:country": "GB",
    "wof:name": "L32 5TL",
    "wof:placetype": "postalcode"
  },
  "geometry": {"coordinates":[-2.897232,53.477332],"type":"Point"}
}
