{
  "type": "Feature",
  "properties": {
    "date:inception_lower":"1980-01-01",
    "date:inception_upper":"1980-01-31",
    "iso:country":"GB",
    "wof:name":"PA18 6BG",
    "wof:placetype":"postalcode"
},
  "geometry": {"coordinates":[-4.89052,55.886482],"type":"Point"}
}