{
  "type": "Feature",
  "properties": {
    "iso:country": "GB",
    "wof:name": "SW18 4RL",
    "wof:placetype": "postalcode"
  },
  "geometry": {"coordinates":[-0.19036,51.440955],"type":"Point"}
}
