{
  "type": "Feature",
  "properties": {
    "iso:country":"GB",
    "wof:name":"SW18 4RL",
    "wof:placetype":"postalcode"
},
  "geometry": {"coordinates":[-0.19035960804884,51.44095530909922],"type":"Point"}
}