{
  "type": "Feature",
  "properties": {
    "iso:country":"GB",
    "wof:name":"DY6 7BF",
    "wof:placetype":"postalcode"
},
  "geometry": {"coordinates":[-2.14288797871246,52.50872437780943],"type":"Point"}
}