{
  "type": "Feature",
  "properties": {
    "iso:country":"GB",
    "wof:name":"PO33 4LS",
    "wof:placetype":"postalcode"
},
  "geometry": {"coordinates":[-1.23399250098888,50.72424212385582],"type":"Point"}
}