{
  "type": "Feature",
  "properties": {
    "iso:country": "GB",
    "wof:name": "PO33 4LS",
    "wof:placetype": "postalcode"
  },
  "geometry": {"coordinates":[-1.233992,50.724242],"type":"Point"}
}
