{
  "type": "Feature",
  "properties": {
    "iso:country": "GB",
    "wof:name": "S42 5RA",
    "wof:placetype": "postalcode"
  },
  "geometry": {"coordinates":[-1.354309,53.188379],"type":"Point"}
}
