{
  "type": "Feature",
  "properties": {
    "iso:country":"GB",
    "wof:name":"S73 9PL",
    "wof:placetype":"postalcode"
},
  "geometry": {"coordinates":[-1.38879898560202,53.5345102829211],"type":"Point"}
}