{
  "type": "Feature",
  "properties": {
    "date:inception_lower":"1980-01-01",
    "date:inception_upper":"1980-01-31",
    "iso:country":"GB",
    "wof:name":"S73 9PL",
    "wof:placetype":"postalcode"
},
  "geometry": {"coordinates":[-1.388799,53.53451],"type":"Point"}
}