{
  "type": "Feature",
  "properties": {
    "date:inception_lower": "1980-01-01",
    "date:inception_upper": "1980-01-01",
    "iso:country": "GB",
    "wof:name": "OL1 3DF",
    "wof:placetype": "postalcode"
  },
  "geometry": {"coordinates":[-2.113584,53.545409],"type":"Point"}
}
