{
  "type": "Feature",
  "properties": {
    "iso:country":"GB",
    "wof:name":"OL1 3DF",
    "wof:placetype":"postalcode"
},
  "geometry": {"coordinates":[-2.11358371734801,53.54540948761911],"type":"Point"}
}