{
  "type": "Feature",
  "properties": {
    "iso:country": "GB",
    "wof:name": "OL1 3DF",
    "wof:placetype": "postalcode"
  },
  "geometry": {"coordinates":[-2.113584,53.545409],"type":"Point"}
}
