{
  "type": "Feature",
  "properties": {
    "iso:country": "GB",
    "wof:name": "NG13 8XG",
    "wof:placetype": "postalcode"
  },
  "geometry": {"coordinates":[-0.95192,52.954004],"type":"Point"}
}
