{
  "type": "Feature",
  "properties": {
    "iso:country":"GB",
    "wof:name":"NW1 9JW",
    "wof:placetype":"postalcode"
},
  "geometry": {"coordinates":[-0.13867934075612,51.54373112645113],"type":"Point"}
}