{
  "type": "Feature",
  "properties": {
    "iso:country":"GB",
    "wof:name":"LE16 7LQ",
    "wof:placetype":"postalcode"
},
  "geometry": {"coordinates":[-0.92137471090259,52.48583608725224],"type":"Point"}
}