{
  "type": "Feature",
  "properties": {
    "iso:country": "GB",
    "wof:name": "AB42 5BJ",
    "wof:placetype": "postalcode"
  },
  "geometry": {"coordinates":[-1.96916,57.489143],"type":"Point"}
}
