{
  "type": "Feature",
  "properties": {
    "iso:country":"GB",
    "wof:name":"AB42 5BJ",
    "wof:placetype":"postalcode"
},
  "geometry": {"coordinates":[-1.96915966376145,57.48914323231613],"type":"Point"}
}