{
  "type": "Feature",
  "properties": {
    "iso:country":"GB",
    "wof:name":"WV2 4WW",
    "wof:placetype":"postalcode"
},
  "geometry": {"coordinates":[-2.13347922214491,52.57864957841895],"type":"Point"}
}