{
  "type": "Feature",
  "properties": {
    "iso:country": "GB",
    "wof:name": "WV2 4WW",
    "wof:placetype": "postalcode"
  },
  "geometry": {"coordinates":[-2.133479,52.57865],"type":"Point"}
}
