{
  "type": "Feature",
  "properties": {
    "date:inception_lower":"1999-12-01",
    "date:inception_upper":"1999-12-31",
    "iso:country":"GB",
    "wof:name":"WV2 4WW",
    "wof:placetype":"postalcode"
},
  "geometry": {"coordinates":[-2.133479,52.57865],"type":"Point"}
}