{
  "type": "Feature",
  "properties": {
    "iso:country": "GB",
    "wof:name": "KA24 4BA",
    "wof:placetype": "postalcode"
  },
  "geometry": {"coordinates":[-4.72847,55.705626],"type":"Point"}
}
