{
  "type": "Feature",
  "properties": {
    "iso:country":"GB",
    "wof:name":"KA24 4BA",
    "wof:placetype":"postalcode"
},
  "geometry": {"coordinates":[-4.72847006941301,55.7056264729236],"type":"Point"}
}