{
  "type": "Feature",
  "properties": {
    "iso:country":"GB",
    "wof:name":"HA6 3FJ",
    "wof:placetype":"postalcode"
},
  "geometry": {"coordinates":[-0.41877784905692,51.61759219758191],"type":"Point"}
}