{
  "type": "Feature",
  "properties": {
    "iso:country": "GB",
    "wof:name": "HA6 3FJ",
    "wof:placetype": "postalcode"
  },
  "geometry": {"coordinates":[-0.418778,51.617592],"type":"Point"}
}
