{
  "type": "Feature",
  "properties": {
    "iso:country":"GB",
    "wof:name":"LA8 9LW",
    "wof:placetype":"postalcode"
},
  "geometry": {"coordinates":[-2.81491561767694,54.37523421251966],"type":"Point"}
}