{
  "type": "Feature",
  "properties": {
    "date:inception_lower": "1980-01-01",
    "date:inception_upper": "1980-01-01",
    "iso:country": "GB",
    "wof:name": "LA8 9LW",
    "wof:placetype": "postalcode"
  },
  "geometry": {"coordinates":[-2.814916,54.375234],"type":"Point"}
}
