{
  "type": "Feature",
  "properties": {
    "iso:country":"GB",
    "wof:name":"G53 6RU",
    "wof:placetype":"postalcode"
},
  "geometry": {"coordinates":[-4.35146809711009,55.81723739622942],"type":"Point"}
}