{
  "type": "Feature",
  "properties": {
    "date:inception_lower": "1980-01-01",
    "date:inception_upper": "1980-01-01",
    "iso:country": "GB",
    "wof:name": "G53 6RU",
    "wof:placetype": "postalcode"
  },
  "geometry": {"coordinates":[-4.351468,55.817237],"type":"Point"}
}
