{
  "type": "Feature",
  "properties": {
    "date:inception_lower":"1980-01-01",
    "date:inception_upper":"1980-01-31",
    "iso:country":"GB",
    "wof:name":"TR4 8EE",
    "wof:placetype":"postalcode"
},
  "geometry": {"coordinates":[-5.215993,50.281791],"type":"Point"}
}