{
  "type": "Feature",
  "properties": {
    "iso:country":"GB",
    "wof:name":"TR4 8EE",
    "wof:placetype":"postalcode"
},
  "geometry": {"coordinates":[-5.21304765743293,50.28066631491602],"type":"Point"}
}