{
  "type": "Feature",
  "properties": {
    "iso:country": "GB",
    "wof:name": "M12 5ER",
    "wof:placetype": "postalcode"
  },
  "geometry": {"coordinates":[-2.19642,53.467417],"type":"Point"}
}
