{
  "type": "Feature",
  "properties": {
    "iso:country":"GB",
    "wof:name":"M12 5ER",
    "wof:placetype":"postalcode"
},
  "geometry": {"coordinates":[-2.19642048559946,53.46741736644698],"type":"Point"}
}