{
  "type": "Feature",
  "properties": {
    "iso:country":"GB",
    "wof:name":"DL13 4BQ",
    "wof:placetype":"postalcode"
},
  "geometry": {"coordinates":[-1.82214060041757,54.75116793938161],"type":"Point"}
}