{
  "type": "Feature",
  "properties": {
    "iso:country":"GB",
    "wof:name":"LL58 8YS",
    "wof:placetype":"postalcode"
},
  "geometry": {"coordinates":[-4.10857076353413,53.26342260862017],"type":"Point"}
}