{
  "type": "Feature",
  "properties": {
    "iso:country": "GB",
    "wof:name": "LL58 8YS",
    "wof:placetype": "postalcode"
  },
  "geometry": {"coordinates":[-4.108571,53.263423],"type":"Point"}
}
