{
  "type": "Feature",
  "properties": {
    "iso:country":"GB",
    "wof:name":"CH1 5UT",
    "wof:placetype":"postalcode"
},
  "geometry": {"coordinates":[-2.91650543779211,53.20994394341496],"type":"Point"}
}