{
  "type": "Feature",
  "properties": {
    "iso:country": "GB",
    "wof:name": "CH1 5UT",
    "wof:placetype": "postalcode"
  },
  "geometry": {"coordinates":[-2.916505,53.209944],"type":"Point"}
}
