{
  "type": "Feature",
  "properties": {
    "date:inception_lower":"2000-10-01",
    "date:inception_upper":"2000-10-31",
    "iso:country":"GB",
    "wof:name":"GU16 8TY",
    "wof:placetype":"postalcode"
},
  "geometry": {"coordinates":[-0.73905,51.322584],"type":"Point"}
}