{
  "type": "Feature",
  "properties": {
    "iso:country": "GB",
    "wof:name": "PE32 1PB",
    "wof:placetype": "postalcode"
  },
  "geometry": {"coordinates":[0.554459,52.745762],"type":"Point"}
}
