{
  "type": "Feature",
  "properties": {
    "iso:country": "GB",
    "wof:name": "NP44 4QQ",
    "wof:placetype": "postalcode"
  },
  "geometry": {"coordinates":[-3.043547,51.646175],"type":"Point"}
}
