{
  "type": "Feature",
  "properties": {
    "iso:country":"GB",
    "wof:name":"NP44 4QQ",
    "wof:placetype":"postalcode"
},
  "geometry": {"coordinates":[-3.04354675816914,51.64617493078857],"type":"Point"}
}