{
  "type": "Feature",
  "properties": {
    "date:inception_lower": "1980-01-01",
    "date:inception_upper": "1980-01-01",
    "iso:country": "GB",
    "wof:name": "NP44 4QQ",
    "wof:placetype": "postalcode"
  },
  "geometry": {"coordinates":[-3.043547,51.646175],"type":"Point"}
}
