{
  "type": "Feature",
  "properties": {
    "iso:country":"GB",
    "wof:name":"SN3 3EJ",
    "wof:placetype":"postalcode"
},
  "geometry": {"coordinates":[-1.7597903809807,51.5650342469586],"type":"Point"}
}