{
  "type": "Feature",
  "properties": {
    "iso:country": "GB",
    "wof:name": "SN3 3EJ",
    "wof:placetype": "postalcode"
  },
  "geometry": {"coordinates":[-1.75979,51.565034],"type":"Point"}
}
