{
  "type": "Feature",
  "properties": {
    "iso:country":"GB",
    "wof:name":"DY5 2PR",
    "wof:placetype":"postalcode"
},
  "geometry": {"coordinates":[-2.12562031948309,52.46754305942812],"type":"Point"}
}