{
  "type": "Feature",
  "properties": {
    "iso:country":"GB",
    "wof:name":"M25 9NR",
    "wof:placetype":"postalcode"
},
  "geometry": {"coordinates":[-2.27524972919595,53.51879238473212],"type":"Point"}
}