{
  "type": "Feature",
  "properties": {
    "date:inception_lower":"1980-01-01",
    "date:inception_upper":"1980-01-31",
    "iso:country":"GB",
    "wof:name":"DL16 7DQ",
    "wof:placetype":"postalcode"
},
  "geometry": {"coordinates":[-1.615685,54.688071],"type":"Point"}
}