{
  "type": "Feature",
  "properties": {
    "iso:country": "GB",
    "wof:name": "DL16 7DQ",
    "wof:placetype": "postalcode"
  },
  "geometry": {"coordinates":[-1.615685,54.688071],"type":"Point"}
}
