{
  "type": "Feature",
  "properties": {
    "iso:country":"GB",
    "wof:name":"HX6 2TZ",
    "wof:placetype":"postalcode"
},
  "geometry": {"coordinates":[-1.91623481813719,53.71423314055829],"type":"Point"}
}