{
  "type": "Feature",
  "properties": {
    "iso:country":"GB",
    "wof:name":"DD4 6BD",
    "wof:placetype":"postalcode"
},
  "geometry": {"coordinates":[-2.95497386268747,56.46664612227215],"type":"Point"}
}