{
  "type": "Feature",
  "properties": {
    "iso:country":"GB",
    "wof:name":"AB55 4ED",
    "wof:placetype":"postalcode"
},
  "geometry": {"coordinates":[-3.04941624912291,57.44689802908702],"type":"Point"}
}