{
  "type": "Feature",
  "properties": {
    "date:inception_lower": "1990-08-01",
    "date:inception_upper": "1990-08-01",
    "iso:country": "GB",
    "wof:name": "AB55 4ED",
    "wof:placetype": "postalcode"
  },
  "geometry": {"coordinates":[-3.036544,57.448328],"type":"Point"}
}
