{
  "type": "Feature",
  "properties": {
    "iso:country":"GB",
    "wof:name":"NG19 0EE",
    "wof:placetype":"postalcode"
},
  "geometry": {"coordinates":[-1.16201531604859,53.15212328515202],"type":"Point"}
}