{
  "type": "Feature",
  "properties": {
    "date:inception_lower":"1980-01-01",
    "date:inception_upper":"1980-01-31",
    "iso:country":"GB",
    "wof:name":"NG19 0EE",
    "wof:placetype":"postalcode"
},
  "geometry": {"coordinates":[-1.162015,53.152123],"type":"Point"}
}