{
  "type": "Feature",
  "properties": {
    "iso:country":"GB",
    "wof:name":"HP9 2YH",
    "wof:placetype":"postalcode"
},
  "geometry": {"coordinates":[-0.60378832522432,51.61834650820611],"type":"Point"}
}