{
  "type": "Feature",
  "properties": {
    "iso:country": "GB",
    "wof:name": "HP9 2YH",
    "wof:placetype": "postalcode"
  },
  "geometry": {"coordinates":[-0.603788,51.618347],"type":"Point"}
}
