{
  "type": "Feature",
  "properties": {
    "iso:country":"GB",
    "wof:name":"YO51 9HR",
    "wof:placetype":"postalcode"
},
  "geometry": {"coordinates":[-1.39769933518172,54.09311972376897],"type":"Point"}
}