{
  "type": "Feature",
  "properties": {
    "iso:country":"GB",
    "wof:name":"FK5 4UB",
    "wof:placetype":"postalcode"
},
  "geometry": {"coordinates":[-3.80240247814779,56.03368562014372],"type":"Point"}
}