{
  "type": "Feature",
  "properties": {
    "iso:country":"GB",
    "wof:name":"NR4 7AB",
    "wof:placetype":"postalcode"
},
  "geometry": {"coordinates":[1.2519867699633,52.60902016467195],"type":"Point"}
}