{
  "type": "Feature",
  "properties": {
    "iso:country":"GB",
    "wof:name":"IG1 2TB",
    "wof:placetype":"postalcode"
},
  "geometry": {"coordinates":[0.083899163912,51.55174188508732],"type":"Point"}
}