{
  "type": "Feature",
  "properties": {
    "iso:country": "GB",
    "wof:name": "PE15 0TS",
    "wof:placetype": "postalcode"
  },
  "geometry": {"coordinates":[0.062591,52.493831],"type":"Point"}
}
