{
  "type": "Feature",
  "properties": {
    "date:inception_lower":"1997-12-01",
    "date:inception_upper":"1997-12-31",
    "iso:country":"GB",
    "wof:name":"BS39 4EU",
    "wof:placetype":"postalcode"
},
  "geometry": {"coordinates":[-2.578747,51.379173],"type":"Point"}
}