{
  "type": "Feature",
  "properties": {
    "iso:country":"GB",
    "wof:name":"WV1 2TE",
    "wof:placetype":"postalcode"
},
  "geometry": {"coordinates":[-2.09396510692693,52.57432755113688],"type":"Point"}
}