{
  "type": "Feature",
  "properties": {
    "iso:country": "GB",
    "wof:name": "WV1 2TE",
    "wof:placetype": "postalcode"
  },
  "geometry": {"coordinates":[-2.093965,52.574328],"type":"Point"}
}
