{
  "type": "Feature",
  "properties": {
    "date:inception_lower":"1995-07-01",
    "date:inception_upper":"1995-07-31",
    "iso:country":"GB",
    "wof:name":"CM1 6QY",
    "wof:placetype":"postalcode"
},
  "geometry": {"coordinates":[0.501009,51.749858],"type":"Point"}
}