{
  "type": "Feature",
  "properties": {
    "iso:country":"GB",
    "wof:name":"CM1 6QY",
    "wof:placetype":"postalcode"
},
  "geometry": {"coordinates":[0.50100881108224,51.7498579358514],"type":"Point"}
}