{
  "type": "Feature",
  "properties": {
    "iso:country": "GB",
    "wof:name": "NN10 9GB",
    "wof:placetype": "postalcode"
  },
  "geometry": {"coordinates":[-0.601181,52.287335],"type":"Point"}
}
