{
  "type": "Feature",
  "properties": {
    "date:inception_lower": "2013-05-01",
    "date:inception_upper": "2013-05-01",
    "iso:country": "GB",
    "wof:name": "NN10 9GB",
    "wof:placetype": "postalcode"
  },
  "geometry": {"coordinates":[-0.601181,52.287335],"type":"Point"}
}
