{
  "type": "Feature",
  "properties": {
    "iso:country":"GB",
    "wof:name":"NN10 9GB",
    "wof:placetype":"postalcode"
},
  "geometry": {"coordinates":[-0.60112461982574,52.28727554996077],"type":"Point"}
}