{
  "type": "Feature",
  "properties": {
    "iso:country": "GB",
    "wof:name": "DL1 3SF",
    "wof:placetype": "postalcode"
  },
  "geometry": {"coordinates":[-1.514163,54.54276],"type":"Point"}
}
