{
  "type": "Feature",
  "properties": {
    "iso:country": "GB",
    "wof:name": "TF3 5DB",
    "wof:placetype": "postalcode"
  },
  "geometry": {"coordinates":[-2.464171,52.683112],"type":"Point"}
}
