{
  "type": "Feature",
  "properties": {
    "date:inception_lower": "1985-10-01",
    "date:inception_upper": "1985-10-01",
    "iso:country": "GB",
    "wof:name": "TF3 5DB",
    "wof:placetype": "postalcode"
  },
  "geometry": {"coordinates":[-2.464171,52.683112],"type":"Point"}
}
