{
  "type": "Feature",
  "properties": {
    "date:inception_lower":"1988-11-01",
    "date:inception_upper":"1988-11-30",
    "iso:country":"GB",
    "wof:name":"EH21 6UQ",
    "wof:placetype":"postalcode"
},
  "geometry": {"coordinates":[-3.073728,55.938769],"type":"Point"}
}