{
  "type": "Feature",
  "properties": {
    "iso:country":"GB",
    "wof:name":"TW1 3AX",
    "wof:placetype":"postalcode"
},
  "geometry": {"coordinates":[-0.32139691722221,51.45165452051692],"type":"Point"}
}