{
  "type": "Feature",
  "properties": {
    "date:inception_lower": "1980-01-01",
    "date:inception_upper": "1980-01-01",
    "iso:country": "GB",
    "wof:name": "TW1 3AX",
    "wof:placetype": "postalcode"
  },
  "geometry": {"coordinates":[-0.321397,51.451655],"type":"Point"}
}
