{
  "type": "Feature",
  "properties": {
    "iso:country": "GB",
    "wof:name": "GL1 5JW",
    "wof:placetype": "postalcode"
  },
  "geometry": {"coordinates":[-2.240142,51.846196],"type":"Point"}
}
