{
  "type": "Feature",
  "properties": {
    "iso:country":"GB",
    "wof:name":"GL1 5JW",
    "wof:placetype":"postalcode"
},
  "geometry": {"coordinates":[-2.24014165757424,51.84619602357076],"type":"Point"}
}