{
  "type": "Feature",
  "properties": {
    "date:inception_lower": "1980-01-01",
    "date:inception_upper": "1980-01-01",
    "iso:country": "GB",
    "wof:name": "WA8 6EF",
    "wof:placetype": "postalcode"
  },
  "geometry": {"coordinates":[-2.728414,53.369888],"type":"Point"}
}
