{
  "type": "Feature",
  "properties": {
    "iso:country": "GB",
    "wof:name": "S6 6DF",
    "wof:placetype": "postalcode"
  },
  "geometry": {"coordinates":[-1.550017,53.391247],"type":"Point"}
}
