{
  "type": "Feature",
  "properties": {
    "iso:country":"GB",
    "wof:name":"BB3 3RP",
    "wof:placetype":"postalcode"
},
  "geometry": {"coordinates":[-2.44951629082397,53.69332048547775],"type":"Point"}
}