{
  "type": "Feature",
  "properties": {
    "iso:country":"GB",
    "wof:name":"WD6 1SD",
    "wof:placetype":"postalcode"
},
  "geometry": {"coordinates":[-0.25320008088855,51.65890246207042],"type":"Point"}
}