{
  "type": "Feature",
  "properties": {
    "date:inception_lower": "1980-01-01",
    "date:inception_upper": "1980-01-01",
    "iso:country": "GB",
    "wof:name": "WD6 1SD",
    "wof:placetype": "postalcode"
  },
  "geometry": {"coordinates":[-0.255413,51.659749],"type":"Point"}
}
