{
  "type": "Feature",
  "properties": {
    "iso:country":"GB",
    "wof:name":"WA7 5YW",
    "wof:placetype":"postalcode"
},
  "geometry": {"coordinates":[-2.70968150924438,53.32342984249068],"type":"Point"}
}