{
  "type": "Feature",
  "properties": {
    "date:inception_lower": "1980-01-01",
    "date:inception_upper": "1980-01-01",
    "iso:country": "GB",
    "wof:name": "WA7 5YW",
    "wof:placetype": "postalcode"
  },
  "geometry": {"coordinates":[-2.709681,53.32343],"type":"Point"}
}
