{
  "type": "Feature",
  "properties": {
    "iso:country":"GB",
    "wof:name":"TR1 3HR",
    "wof:placetype":"postalcode"
},
  "geometry": {"coordinates":[-5.05944524659293,50.26330608000247],"type":"Point"}
}