{
  "type": "Feature",
  "properties": {
    "iso:country":"GB",
    "wof:name":"IP19 9LW",
    "wof:placetype":"postalcode"
},
  "geometry": {"coordinates":[1.5973563933776,52.31968020126843],"type":"Point"}
}