{
  "type": "Feature",
  "properties": {
    "iso:country": "GB",
    "wof:name": "IP19 9LW",
    "wof:placetype": "postalcode"
  },
  "geometry": {"coordinates":[1.597356,52.31968],"type":"Point"}
}
