{
  "type": "Feature",
  "properties": {
    "iso:country":"GB",
    "wof:name":"LE1 2FB",
    "wof:placetype":"postalcode"
},
  "geometry": {"coordinates":[-1.12461633920794,52.64002206475355],"type":"Point"}
}