{
  "type": "Feature",
  "properties": {
    "iso:country":"GB",
    "wof:name":"NE37 2HJ",
    "wof:placetype":"postalcode"
},
  "geometry": {"coordinates":[-1.52933910983132,54.91889170017667],"type":"Point"}
}