{
  "type": "Feature",
  "properties": {
    "date:inception_lower": "1980-01-01",
    "date:inception_upper": "1980-01-01",
    "iso:country": "GB",
    "wof:name": "PO18 9JB",
    "wof:placetype": "postalcode"
  },
  "geometry": {"coordinates":[-0.836443,50.924741],"type":"Point"}
}
