{
  "type": "Feature",
  "properties": {
    "iso:country": "GB",
    "wof:name": "B60 2BP",
    "wof:placetype": "postalcode"
  },
  "geometry": {"coordinates":[-2.063659,52.331672],"type":"Point"}
}
