{
  "type": "Feature",
  "properties": {
    "iso:country":"GB",
    "wof:name":"B60 2BP",
    "wof:placetype":"postalcode"
},
  "geometry": {"coordinates":[-2.06365877633593,52.33167171199357],"type":"Point"}
}