{
  "type": "Feature",
  "properties": {
    "iso:country":"GB",
    "wof:name":"YO51 9HL",
    "wof:placetype":"postalcode"
},
  "geometry": {"coordinates":[-1.39365333652129,54.09062780439358],"type":"Point"}
}