{
  "type": "Feature",
  "properties": {
    "iso:country": "GB",
    "wof:name": "TA16 5PR",
    "wof:placetype": "postalcode"
  },
  "geometry": {"coordinates":[-2.790712,50.912587],"type":"Point"}
}
