{
  "type": "Feature",
  "properties": {
    "iso:country": "GB",
    "wof:name": "WN1 3TA",
    "wof:placetype": "postalcode"
  },
  "geometry": {"coordinates":[-2.62112,53.548416],"type":"Point"}
}
