{
  "type": "Feature",
  "properties": {
    "date:inception_lower": "1980-01-01",
    "date:inception_upper": "1980-01-01",
    "iso:country": "GB",
    "wof:name": "BB11 2PP",
    "wof:placetype": "postalcode"
  },
  "geometry": {"coordinates":[-2.25029,53.779308],"type":"Point"}
}
