{
  "type": "Feature",
  "properties": {
    "iso:country":"GB",
    "wof:name":"BD7 1NP",
    "wof:placetype":"postalcode"
},
  "geometry": {"coordinates":[-1.77157265035279,53.79157587467141],"type":"Point"}
}