{
  "type": "Feature",
  "properties": {
    "iso:country":"GB",
    "wof:name":"LL24 0HP",
    "wof:placetype":"postalcode"
},
  "geometry": {"coordinates":[-3.70788477147222,53.04538337373558],"type":"Point"}
}