{
  "type": "Feature",
  "properties": {
    "iso:country": "GB",
    "wof:name": "LL24 0HP",
    "wof:placetype": "postalcode"
  },
  "geometry": {"coordinates":[-3.707889,53.045399],"type":"Point"}
}
