{
  "type": "Feature",
  "properties": {
    "iso:country":"GB",
    "wof:name":"SP7 9JA",
    "wof:placetype":"postalcode"
},
  "geometry": {"coordinates":[-2.21599751645856,51.05658668909343],"type":"Point"}
}