{
  "type": "Feature",
  "properties": {
    "iso:country": "GB",
    "wof:name": "IP14 4EP",
    "wof:placetype": "postalcode"
  },
  "geometry": {"coordinates":[1.027552,52.261891],"type":"Point"}
}
