{
  "type": "Feature",
  "properties": {
    "date:inception_lower": "2016-04-01",
    "date:inception_upper": "2016-04-01",
    "iso:country": "GB",
    "wof:name": "SN25 2PR",
    "wof:placetype": "postalcode"
  },
  "geometry": {"coordinates":[-1.814107,51.60466],"type":"Point"}
}
