{
  "type": "Feature",
  "properties": {
    "iso:country": "GB",
    "wof:name": "LS15 8ES",
    "wof:placetype": "postalcode"
  },
  "geometry": {"coordinates":[-1.449928,53.804707],"type":"Point"}
}
