{
  "type": "Feature",
  "properties": {
    "iso:country":"GB",
    "wof:name":"DG2 7NY",
    "wof:placetype":"postalcode"
},
  "geometry": {"coordinates":[-3.62765583300593,55.06521656030897],"type":"Point"}
}