{
  "type": "Feature",
  "properties": {
    "iso:country":"GB",
    "wof:name":"CB11 3UF",
    "wof:placetype":"postalcode"
},
  "geometry": {"coordinates":[0.18594487940854,51.97900178331061],"type":"Point"}
}