{
  "type": "Feature",
  "properties": {
    "date:inception_lower": "2008-08-01",
    "date:inception_upper": "2008-08-01",
    "iso:country": "GB",
    "wof:name": "SA31 2BN",
    "wof:placetype": "postalcode"
  },
  "geometry": {"coordinates":[-4.303951,51.853813],"type":"Point"}
}
