{
  "type": "Feature",
  "properties": {
    "iso:country":"GB",
    "wof:name":"W1H 6EQ",
    "wof:placetype":"postalcode"
},
  "geometry": {"coordinates":[-0.15351334647696,51.51643959323933],"type":"Point"}
}