{
  "type": "Feature",
  "properties": {
    "iso:country": "GB",
    "wof:name": "W1H 6EQ",
    "wof:placetype": "postalcode"
  },
  "geometry": {"coordinates":[-0.153513,51.51644],"type":"Point"}
}
