{
  "type": "Feature",
  "properties": {
    "iso:country":"GB",
    "wof:name":"BA3 2HJ",
    "wof:placetype":"postalcode"
},
  "geometry": {"coordinates":[-2.48427392854468,51.28508851818158],"type":"Point"}
}