{
  "type": "Feature",
  "properties": {
    "iso:country": "GB",
    "wof:name": "BA3 2HJ",
    "wof:placetype": "postalcode"
  },
  "geometry": {"coordinates":[-2.484274,51.285089],"type":"Point"}
}
