{
  "type": "Feature",
  "properties": {
    "iso:country":"GB",
    "wof:name":"SW6 3QF",
    "wof:placetype":"postalcode"
},
  "geometry": {"coordinates":[-0.20449349899664,51.47130656529794],"type":"Point"}
}