{
  "type": "Feature",
  "properties": {
    "date:inception_lower":"1995-12-01",
    "date:inception_upper":"1995-12-31",
    "iso:country":"GB",
    "wof:name":"DN31 1PY",
    "wof:placetype":"postalcode"
},
  "geometry": {"coordinates":[-0.081216,53.571758],"type":"Point"}
}