{
  "type": "Feature",
  "properties": {
    "iso:country":"GB",
    "wof:name":"DN31 1PY",
    "wof:placetype":"postalcode"
},
  "geometry": {"coordinates":[-0.08121607007513,53.5717578191072],"type":"Point"}
}