{
  "type": "Feature",
  "properties": {
    "iso:country": "GB",
    "wof:name": "BN27 4FR",
    "wof:placetype": "postalcode"
  },
  "geometry": {"coordinates":[0.267169,50.878815],"type":"Point"}
}
