{
  "type": "Feature",
  "properties": {
    "iso:country": "GB",
    "wof:name": "G60 5JY",
    "wof:placetype": "postalcode"
  },
  "geometry": {"coordinates":[-4.460161,55.925608],"type":"Point"}
}
