{
  "type": "Feature",
  "properties": {
    "iso:country":"GB",
    "wof:name":"OX11 0ND",
    "wof:placetype":"postalcode"
},
  "geometry": {"coordinates":[-1.26054805369074,51.58561925397227],"type":"Point"}
}