{
  "type": "Feature",
  "properties": {
    "iso:country":"GB",
    "wof:name":"WS11 9PB",
    "wof:placetype":"postalcode"
},
  "geometry": {"coordinates":[-1.97530519249266,52.67102919330394],"type":"Point"}
}