{
  "type": "Feature",
  "properties": {
    "iso:country":"GB",
    "wof:name":"SN10 3DX",
    "wof:placetype":"postalcode"
},
  "geometry": {"coordinates":[-1.979979324863,51.34522807710034],"type":"Point"}
}