{
  "type": "Feature",
  "properties": {
    "iso:country":"GB",
    "wof:name":"GL51 8LW",
    "wof:placetype":"postalcode"
},
  "geometry": {"coordinates":[-2.09829460898106,51.90937253529591],"type":"Point"}
}