{
  "type": "Feature",
  "properties": {
    "iso:country":"GB",
    "wof:name":"SN8 2HH",
    "wof:placetype":"postalcode"
},
  "geometry": {"coordinates":[-1.56290898563136,51.47006486907745],"type":"Point"}
}