{
  "type": "Feature",
  "properties": {
    "iso:country": "GB",
    "wof:name": "TQ12 5JA",
    "wof:placetype": "postalcode"
  },
  "geometry": {"coordinates":[-3.578738,50.498376],"type":"Point"}
}
