{
  "type": "Feature",
  "properties": {
    "iso:country":"GB",
    "wof:name":"WA14 3LD",
    "wof:placetype":"postalcode"
},
  "geometry": {"coordinates":[-2.36759309914804,53.37555425733875],"type":"Point"}
}