{
  "type": "Feature",
  "properties": {
    "iso:country":"GB",
    "wof:name":"BH24 1NN",
    "wof:placetype":"postalcode"
},
  "geometry": {"coordinates":[-1.78521747369798,50.84241063506923],"type":"Point"}
}