{
  "type": "Feature",
  "properties": {
    "iso:country":"GB",
    "wof:name":"BN16 1BS",
    "wof:placetype":"postalcode"
},
  "geometry": {"coordinates":[-0.47375285001648,50.81605527681178],"type":"Point"}
}