{
  "type": "Feature",
  "properties": {
    "iso:country":"GB",
    "wof:name":"M44 5DD",
    "wof:placetype":"postalcode"
},
  "geometry": {"coordinates":[-2.43779219316457,53.42565364879565],"type":"Point"}
}