{
  "type": "Feature",
  "properties": {
    "iso:country":"GB",
    "wof:name":"SK9 1AA",
    "wof:placetype":"postalcode"
},
  "geometry": {"coordinates":[-2.23113751998689,53.32796026050448],"type":"Point"}
}