{
  "type": "Feature",
  "properties": {
    "date:inception_lower": "1994-05-01",
    "date:inception_upper": "1994-05-01",
    "iso:country": "GB",
    "wof:name": "M27 4TU",
    "wof:placetype": "postalcode"
  },
  "geometry": {"coordinates":[-2.331546,53.508636],"type":"Point"}
}
