{
  "type": "Feature",
  "properties": {
    "iso:country":"GB",
    "wof:name":"LL30 1SA",
    "wof:placetype":"postalcode"
},
  "geometry": {"coordinates":[-3.8161641673617,53.3001337240476],"type":"Point"}
}