{
  "type": "Feature",
  "properties": {
    "iso:country": "GB",
    "wof:name": "CB6 2TL",
    "wof:placetype": "postalcode"
  },
  "geometry": {"coordinates":[0.237219,52.429423],"type":"Point"}
}
