{
  "type": "Feature",
  "properties": {
    "iso:country":"GB",
    "wof:name":"CB6 2TL",
    "wof:placetype":"postalcode"
},
  "geometry": {"coordinates":[0.23721930747745,52.42942313570412],"type":"Point"}
}