{
  "type": "Feature",
  "properties": {
    "iso:country": "GB",
    "wof:name": "CB8 0PU",
    "wof:placetype": "postalcode"
  },
  "geometry": {"coordinates":[0.396045,52.244498],"type":"Point"}
}
