{
  "type": "Feature",
  "properties": {
    "iso:country": "GB",
    "wof:name": "CV37 8AY",
    "wof:placetype": "postalcode"
  },
  "geometry": {"coordinates":[-1.795573,52.144702],"type":"Point"}
}
