{
  "type": "Feature",
  "properties": {
    "iso:country":"GB",
    "wof:name":"NW2 6QB",
    "wof:placetype":"postalcode"
},
  "geometry": {"coordinates":[-0.22237210393893,51.5595337591115],"type":"Point"}
}