{
  "type": "Feature",
  "properties": {
    "date:inception_lower": "1980-01-01",
    "date:inception_upper": "1980-01-01",
    "iso:country": "GB",
    "wof:name": "NW2 6QB",
    "wof:placetype": "postalcode"
  },
  "geometry": {"coordinates":[-0.222372,51.559534],"type":"Point"}
}
