{
  "type": "Feature",
  "properties": {
    "iso:country":"GB",
    "wof:name":"L36 4HE",
    "wof:placetype":"postalcode"
},
  "geometry": {"coordinates":[-2.84972775295468,53.40889757506979],"type":"Point"}
}