{
  "type": "Feature",
  "properties": {
    "iso:country": "GB",
    "wof:name": "L36 4HE",
    "wof:placetype": "postalcode"
  },
  "geometry": {"coordinates":[-2.849728,53.408898],"type":"Point"}
}
