{
  "type": "Feature",
  "properties": {
    "date:inception_lower": "1992-08-01",
    "date:inception_upper": "1992-08-01",
    "iso:country": "GB",
    "wof:name": "LE65 2UH",
    "wof:placetype": "postalcode"
  },
  "geometry": {"coordinates":[-1.477915,52.764742],"type":"Point"}
}
