{
  "type": "Feature",
  "properties": {
    "iso:country": "GB",
    "wof:name": "LE65 2UH",
    "wof:placetype": "postalcode"
  },
  "geometry": {"coordinates":[-1.477915,52.764742],"type":"Point"}
}
