{
  "type": "Feature",
  "properties": {
    "iso:country":"GB",
    "wof:name":"LE65 2UH",
    "wof:placetype":"postalcode"
},
  "geometry": {"coordinates":[-1.47792293950013,52.76472438245067],"type":"Point"}
}