{
  "type": "Feature",
  "properties": {
    "iso:country": "GB",
    "wof:name": "NG31 9QE",
    "wof:placetype": "postalcode"
  },
  "geometry": {"coordinates":[-0.624069,52.924392],"type":"Point"}
}
