{
  "type": "Feature",
  "properties": {
    "date:inception_lower": "1980-01-01",
    "date:inception_upper": "1980-01-01",
    "iso:country": "GB",
    "wof:name": "NG31 9QE",
    "wof:placetype": "postalcode"
  },
  "geometry": {"coordinates":[-0.624069,52.924392],"type":"Point"}
}
