{
  "type": "Feature",
  "properties": {
    "iso:country":"GB",
    "wof:name":"NG31 9QE",
    "wof:placetype":"postalcode"
},
  "geometry": {"coordinates":[-0.62406885780057,52.92439211603194],"type":"Point"}
}