{
  "type": "Feature",
  "properties": {
    "iso:country":"GB",
    "wof:name":"HU3 5AU",
    "wof:placetype":"postalcode"
},
  "geometry": {"coordinates":[-0.37675552330552,53.73578235830906],"type":"Point"}
}