{
  "type": "Feature",
  "properties": {
    "iso:country":"GB",
    "wof:name":"B66 4HZ",
    "wof:placetype":"postalcode"
},
  "geometry": {"coordinates":[-1.96988675439843,52.48421073405676],"type":"Point"}
}