{
  "type": "Feature",
  "properties": {
    "iso:country": "GB",
    "wof:name": "B66 4HZ",
    "wof:placetype": "postalcode"
  },
  "geometry": {"coordinates":[-1.969887,52.484211],"type":"Point"}
}
