{
  "type": "Feature",
  "properties": {
    "iso:country": "GB",
    "wof:name": "TR13 8TW",
    "wof:placetype": "postalcode"
  },
  "geometry": {"coordinates":[-5.272147,50.102871],"type":"Point"}
}
