{
  "type": "Feature",
  "properties": {
    "iso:country":"GB",
    "wof:name":"TR13 8TW",
    "wof:placetype":"postalcode"
},
  "geometry": {"coordinates":[-5.27208059726102,50.10286446444555],"type":"Point"}
}