{
  "type": "Feature",
  "properties": {
    "iso:country": "GB",
    "wof:name": "L1 4JS",
    "wof:placetype": "postalcode"
  },
  "geometry": {"coordinates":[-2.977153,53.400669],"type":"Point"}
}
