{
  "type": "Feature",
  "properties": {
    "iso:country": "GB",
    "wof:name": "G78 2JA",
    "wof:placetype": "postalcode"
  },
  "geometry": {"coordinates":[-4.387431,55.793221],"type":"Point"}
}
