{
  "type": "Feature",
  "properties": {
    "iso:country": "GB",
    "wof:name": "TS17 8PY",
    "wof:placetype": "postalcode"
  },
  "geometry": {"coordinates":[-1.306498,54.542969],"type":"Point"}
}
