{
  "type": "Feature",
  "properties": {
    "date:inception_lower": "1980-01-01",
    "date:inception_upper": "1980-01-01",
    "iso:country": "GB",
    "wof:name": "TS17 8PY",
    "wof:placetype": "postalcode"
  },
  "geometry": {"coordinates":[-1.306498,54.542969],"type":"Point"}
}
