{
  "type": "Feature",
  "properties": {
    "date:inception_lower": "1980-01-01",
    "date:inception_upper": "1980-01-01",
    "iso:country": "GB",
    "wof:name": "ST7 3LF",
    "wof:placetype": "postalcode"
  },
  "geometry": {"coordinates":[-2.231536,53.113072],"type":"Point"}
}
