{
  "type": "Feature",
  "properties": {
    "iso:country":"GB",
    "wof:name":"ST7 3LF",
    "wof:placetype":"postalcode"
},
  "geometry": {"coordinates":[-2.23153593996759,53.11307204059624],"type":"Point"}
}