{
  "type": "Feature",
  "properties": {
    "iso:country":"GB",
    "wof:name":"EH6 8PG",
    "wof:placetype":"postalcode"
},
  "geometry": {"coordinates":[-3.17461440506432,55.96506557406989],"type":"Point"}
}