{
  "type": "Feature",
  "properties": {
    "iso:country": "GB",
    "wof:name": "EH6 8PG",
    "wof:placetype": "postalcode"
  },
  "geometry": {"coordinates":[-3.174614,55.965066],"type":"Point"}
}
