{
  "type": "Feature",
  "properties": {
    "iso:country":"GB",
    "wof:name":"DE23 8UE",
    "wof:placetype":"postalcode"
},
  "geometry": {"coordinates":[-1.48557944025525,52.89969945520338],"type":"Point"}
}