{
  "type": "Feature",
  "properties": {
    "iso:country": "GB",
    "wof:name": "OX20 1BP",
    "wof:placetype": "postalcode"
  },
  "geometry": {"coordinates":[-1.387824,51.908012],"type":"Point"}
}
