{
  "type": "Feature",
  "properties": {
    "iso:country":"GB",
    "wof:name":"WN7 1NY",
    "wof:placetype":"postalcode"
},
  "geometry": {"coordinates":[-2.51577857540071,53.50660777614027],"type":"Point"}
}