{
  "type": "Feature",
  "properties": {
    "date:inception_lower": "1980-01-01",
    "date:inception_upper": "1980-01-01",
    "iso:country": "GB",
    "wof:name": "EH12 7AF",
    "wof:placetype": "postalcode"
  },
  "geometry": {"coordinates":[-3.278098,55.941015],"type":"Point"}
}
