{
  "type": "Feature",
  "properties": {
    "iso:country": "GB",
    "wof:name": "M33 7QY",
    "wof:placetype": "postalcode"
  },
  "geometry": {"coordinates":[-2.326127,53.425319],"type":"Point"}
}
