{
  "type": "Feature",
  "properties": {
    "iso:country": "GB",
    "wof:name": "RG9 6ED",
    "wof:placetype": "postalcode"
  },
  "geometry": {"coordinates":[-1.033092,51.614718],"type":"Point"}
}
