{
  "type": "Feature",
  "properties": {
    "iso:country":"GB",
    "wof:name":"RG9 6ED",
    "wof:placetype":"postalcode"
},
  "geometry": {"coordinates":[-1.0330922800484,51.61471768167078],"type":"Point"}
}