{
  "type": "Feature",
  "properties": {
    "iso:country": "GB",
    "wof:name": "DH7 8AU",
    "wof:placetype": "postalcode"
  },
  "geometry": {"coordinates":[-1.63423,54.747674],"type":"Point"}
}
