{
  "type": "Feature",
  "properties": {
    "iso:country":"GB",
    "wof:name":"N9 7PA",
    "wof:placetype":"postalcode"
},
  "geometry": {"coordinates":[-0.06282930887383,51.63482011588417],"type":"Point"}
}