{
  "type": "Feature",
  "properties": {
    "iso:country":"GB",
    "wof:name":"KA3 2ES",
    "wof:placetype":"postalcode"
},
  "geometry": {"coordinates":[-4.49543699519597,55.62997915565298],"type":"Point"}
}