{
  "type": "Feature",
  "properties": {
    "iso:country":"GB",
    "wof:name":"LA7 7JZ",
    "wof:placetype":"postalcode"
},
  "geometry": {"coordinates":[-2.80996332007838,54.20720132442358],"type":"Point"}
}