{
  "type": "Feature",
  "properties": {
    "iso:country":"GB",
    "wof:name":"BL8 4AN",
    "wof:placetype":"postalcode"
},
  "geometry": {"coordinates":[-2.34359733512208,53.61517722087955],"type":"Point"}
}