{
  "type": "Feature",
  "properties": {
    "date:inception_lower":"1997-06-01",
    "date:inception_upper":"1997-06-30",
    "iso:country":"GB",
    "wof:name":"S26 6PR",
    "wof:placetype":"postalcode"
},
  "geometry": {"coordinates":[-1.253576,53.339829],"type":"Point"}
}