{
  "type": "Feature",
  "properties": {
    "iso:country":"GB",
    "wof:name":"S26 6PR",
    "wof:placetype":"postalcode"
},
  "geometry": {"coordinates":[-1.25357653968631,53.33982928716947],"type":"Point"}
}