{
  "type": "Feature",
  "properties": {
    "iso:country": "GB",
    "wof:name": "E15 1JE",
    "wof:placetype": "postalcode"
  },
  "geometry": {"coordinates":[0.002383,51.547074],"type":"Point"}
}
