{
  "type": "Feature",
  "properties": {
    "date:inception_lower":"1990-07-01",
    "date:inception_upper":"1990-07-31",
    "iso:country":"GB",
    "wof:name":"E15 1JE",
    "wof:placetype":"postalcode"
},
  "geometry": {"coordinates":[0.002383,51.547074],"type":"Point"}
}