{
  "type": "Feature",
  "properties": {
    "iso:country":"GB",
    "wof:name":"E15 1JE",
    "wof:placetype":"postalcode"
},
  "geometry": {"coordinates":[0.00238289586748,51.54707353852616],"type":"Point"}
}