{
  "type": "Feature",
  "properties": {
    "date:inception_lower": "1981-06-01",
    "date:inception_upper": "1981-06-01",
    "iso:country": "GB",
    "wof:name": "S9 5DE",
    "wof:placetype": "postalcode"
  },
  "geometry": {"coordinates":[-1.409977,53.399023],"type":"Point"}
}
