{
  "type": "Feature",
  "properties": {
    "iso:country":"GB",
    "wof:name":"S9 5DE",
    "wof:placetype":"postalcode"
},
  "geometry": {"coordinates":[-1.40981159676284,53.39902284825842],"type":"Point"}
}