{
  "type": "Feature",
  "properties": {
    "iso:country":"GB",
    "wof:name":"B65 9JJ",
    "wof:placetype":"postalcode"
},
  "geometry": {"coordinates":[-2.03292844579415,52.4866101600069],"type":"Point"}
}