{
  "type": "Feature",
  "properties": {
    "iso:country":"GB",
    "wof:name":"PE9 1JE",
    "wof:placetype":"postalcode"
},
  "geometry": {"coordinates":[-0.48394115391017,52.66328910415167],"type":"Point"}
}