{
  "type": "Feature",
  "properties": {
    "date:inception_lower": "1993-01-01",
    "date:inception_upper": "1993-01-01",
    "iso:country": "GB",
    "wof:name": "RH12 4RU",
    "wof:placetype": "postalcode"
  },
  "geometry": {"coordinates":[-0.283621,51.084862],"type":"Point"}
}
