{
  "type": "Feature",
  "properties": {
    "iso:country":"GB",
    "wof:name":"RH12 4RU",
    "wof:placetype":"postalcode"
},
  "geometry": {"coordinates":[-0.28362108447172,51.08486210759205],"type":"Point"}
}