{
  "type": "Feature",
  "properties": {
    "iso:country":"GB",
    "wof:name":"EX31 3RW",
    "wof:placetype":"postalcode"
},
  "geometry": {"coordinates":[-4.08855791149217,51.06894718426759],"type":"Point"}
}