{
  "type": "Feature",
  "properties": {
    "date:inception_lower": "1999-06-01",
    "date:inception_upper": "1999-06-01",
    "iso:country": "GB",
    "wof:name": "NP10 8QZ",
    "wof:placetype": "postalcode"
  },
  "geometry": {"coordinates":[-3.071095,51.581486],"type":"Point"}
}
