{
  "type": "Feature",
  "properties": {
    "iso:country":"GB",
    "wof:name":"NP10 8QZ",
    "wof:placetype":"postalcode"
},
  "geometry": {"coordinates":[-3.07090161789818,51.58155739304445],"type":"Point"}
}