{
  "type": "Feature",
  "properties": {
    "date:inception_lower":"1999-06-01",
    "date:inception_upper":"1999-06-30",
    "iso:country":"GB",
    "wof:name":"NP10 8QZ",
    "wof:placetype":"postalcode"
},
  "geometry": {"coordinates":[-3.070902,51.581557],"type":"Point"}
}