{
  "type": "Feature",
  "properties": {
    "iso:country":"GB",
    "wof:name":"LE67 1GA",
    "wof:placetype":"postalcode"
},
  "geometry": {"coordinates":[-1.36325939054086,52.68133322447781],"type":"Point"}
}