{
  "type": "Feature",
  "properties": {
    "date:inception_lower": "1992-08-01",
    "date:inception_upper": "1992-08-01",
    "iso:country": "GB",
    "wof:name": "LE67 1GA",
    "wof:placetype": "postalcode"
  },
  "geometry": {"coordinates":[-1.363259,52.681333],"type":"Point"}
}
