{
  "type": "Feature",
  "properties": {
    "iso:country": "GB",
    "wof:name": "LE67 1GA",
    "wof:placetype": "postalcode"
  },
  "geometry": {"coordinates":[-1.363259,52.681333],"type":"Point"}
}
