{
  "type": "Feature",
  "properties": {
    "iso:country": "GB",
    "wof:name": "HU8 7AB",
    "wof:placetype": "postalcode"
  },
  "geometry": {"coordinates":[-0.330239,53.748621],"type":"Point"}
}
