{
  "type": "Feature",
  "properties": {
    "iso:country":"GB",
    "wof:name":"HU8 7AB",
    "wof:placetype":"postalcode"
},
  "geometry": {"coordinates":[-0.33023311080817,53.74859997082569],"type":"Point"}
}