{
  "type": "Feature",
  "properties": {
    "date:inception_lower": "1998-06-01",
    "date:inception_upper": "1998-06-01",
    "iso:country": "GB",
    "wof:name": "WD7 8HQ",
    "wof:placetype": "postalcode"
  },
  "geometry": {"coordinates":[-0.325939,51.678239],"type":"Point"}
}
