{
  "type": "Feature",
  "properties": {
    "date:inception_lower": "2018-05-01",
    "date:inception_upper": "2018-05-01",
    "iso:country": "GB",
    "wof:name": "MK10 9TT",
    "wof:placetype": "postalcode"
  },
  "geometry": {"coordinates":[-0.720179,52.039676],"type":"Point"}
}
