{
  "type": "Feature",
  "properties": {
    "iso:country": "GB",
    "wof:name": "HP9 2FL",
    "wof:placetype": "postalcode"
  },
  "geometry": {"coordinates":[-0.649022,51.612734],"type":"Point"}
}
