{
  "type": "Feature",
  "properties": {
    "date:inception_lower":"1995-12-01",
    "date:inception_upper":"1995-12-31",
    "iso:country":"GB",
    "wof:name":"HP9 2FL",
    "wof:placetype":"postalcode"
},
  "geometry": {"coordinates":[-0.649022,51.612734],"type":"Point"}
}