{
  "type": "Feature",
  "properties": {
    "date:inception_lower": "1980-01-01",
    "date:inception_upper": "1980-01-01",
    "iso:country": "GB",
    "wof:name": "RH12 4RE",
    "wof:placetype": "postalcode"
  },
  "geometry": {"coordinates":[-0.269924,51.12208],"type":"Point"}
}
