{
  "type": "Feature",
  "properties": {
    "iso:country":"GB",
    "wof:name":"RH12 4RE",
    "wof:placetype":"postalcode"
},
  "geometry": {"coordinates":[-0.26992441942449,51.12207982435128],"type":"Point"}
}