{
  "type": "Feature",
  "properties": {
    "iso:country":"GB",
    "wof:name":"B70 8ND",
    "wof:placetype":"postalcode"
},
  "geometry": {"coordinates":[-1.99457731569619,52.51933802176851],"type":"Point"}
}