{
  "type": "Feature",
  "properties": {
    "iso:country":"GB",
    "wof:name":"BA2 6UZ",
    "wof:placetype":"postalcode"
},
  "geometry": {"coordinates":[-2.31991819624798,51.39382392663075],"type":"Point"}
}