{
  "type": "Feature",
  "properties": {
    "date:inception_lower": "2022-09-01",
    "date:inception_upper": "2022-09-01",
    "iso:country": "GB",
    "wof:name": "CT20 3XA",
    "wof:placetype": "postalcode"
  },
  "geometry": {"coordinates":[1.129413,51.07779],"type":"Point"}
}
