{
  "type": "Feature",
  "properties": {
    "iso:country": "GB",
    "wof:name": "BN2 6SQ",
    "wof:placetype": "postalcode"
  },
  "geometry": {"coordinates":[-0.068511,50.836419],"type":"Point"}
}
