{
  "type": "Feature",
  "properties": {
    "date:inception_lower":"1980-01-01",
    "date:inception_upper":"1980-01-31",
    "iso:country":"GB",
    "wof:name":"BN2 6SQ",
    "wof:placetype":"postalcode"
},
  "geometry": {"coordinates":[-0.068511,50.836419],"type":"Point"}
}