{
  "type": "Feature",
  "properties": {
    "iso:country":"GB",
    "wof:name":"BN2 6SQ",
    "wof:placetype":"postalcode"
},
  "geometry": {"coordinates":[-0.06851060961493,50.83641879912699],"type":"Point"}
}