{
  "type": "Feature",
  "properties": {
    "iso:country":"GB",
    "wof:name":"CR4 2DN",
    "wof:placetype":"postalcode"
},
  "geometry": {"coordinates":[-0.15583853537838,51.41669479880617],"type":"Point"}
}