{
  "type": "Feature",
  "properties": {
    "iso:country":"GB",
    "wof:name":"WC2B 5PZ",
    "wof:placetype":"postalcode"
},
  "geometry": {"coordinates":[-0.12039715038351,51.51631824118549],"type":"Point"}
}