{
  "type": "Feature",
  "properties": {
    "date:inception_lower": "1980-01-01",
    "date:inception_upper": "1980-01-01",
    "iso:country": "GB",
    "wof:name": "PR3 3YP",
    "wof:placetype": "postalcode"
  },
  "geometry": {"coordinates":[-2.532936,53.81355],"type":"Point"}
}
