{
  "type": "Feature",
  "properties": {
    "iso:country":"GB",
    "wof:name":"PR3 3YP",
    "wof:placetype":"postalcode"
},
  "geometry": {"coordinates":[-2.53286075384666,53.81353647433255],"type":"Point"}
}