{
  "type": "Feature",
  "properties": {
    "iso:country": "GB",
    "wof:name": "DE65 5PD",
    "wof:placetype": "postalcode"
  },
  "geometry": {"coordinates":[-1.628647,52.863142],"type":"Point"}
}
