{
  "type": "Feature",
  "properties": {
    "iso:country":"GB",
    "wof:name":"LN13 0JS",
    "wof:placetype":"postalcode"
},
  "geometry": {"coordinates":[0.20710577175937,53.32132791332789],"type":"Point"}
}