{
  "type": "Feature",
  "properties": {
    "date:inception_lower":"1990-02-01",
    "date:inception_upper":"1990-02-28",
    "iso:country":"GB",
    "wof:name":"GL5 3NH",
    "wof:placetype":"postalcode"
},
  "geometry": {"coordinates":[-2.238699,51.738208],"type":"Point"}
}