{
  "type": "Feature",
  "properties": {
    "iso:country":"GB",
    "wof:name":"W1U 2QH",
    "wof:placetype":"postalcode"
},
  "geometry": {"coordinates":[-0.15120151482255,51.51729343259912],"type":"Point"}
}