{
  "type": "Feature",
  "properties": {
    "date:inception_lower": "2001-12-01",
    "date:inception_upper": "2001-12-01",
    "iso:country": "GB",
    "wof:name": "W1U 2QH",
    "wof:placetype": "postalcode"
  },
  "geometry": {"coordinates":[-0.151201,51.517293],"type":"Point"}
}
