{
  "type": "Feature",
  "properties": {
    "iso:country":"GB",
    "wof:name":"SE1 3AY",
    "wof:placetype":"postalcode"
},
  "geometry": {"coordinates":[-0.07391870774186,51.49401793523433],"type":"Point"}
}