{
  "type": "Feature",
  "properties": {
    "iso:country":"GB",
    "wof:name":"SK6 1LG",
    "wof:placetype":"postalcode"
},
  "geometry": {"coordinates":[-2.09101154277894,53.4280849059864],"type":"Point"}
}