{
  "type": "Feature",
  "properties": {
    "date:inception_lower": "2019-02-01",
    "date:inception_upper": "2019-02-01",
    "iso:country": "GB",
    "wof:name": "MK45 3NS",
    "wof:placetype": "postalcode"
  },
  "geometry": {"coordinates":[-0.485074,52.081495],"type":"Point"}
}
