{
  "type": "Feature",
  "properties": {
    "iso:country":"GB",
    "wof:name":"NP44 2AL",
    "wof:placetype":"postalcode"
},
  "geometry": {"coordinates":[-3.00348834163072,51.65622604895204],"type":"Point"}
}