{
  "type": "Feature",
  "properties": {
    "date:inception_lower": "1987-05-01",
    "date:inception_upper": "1987-05-01",
    "iso:country": "GB",
    "wof:name": "FK1 1EU",
    "wof:placetype": "postalcode"
  },
  "geometry": {"coordinates":[-3.786392,55.999964],"type":"Point"}
}
