{
  "type": "Feature",
  "properties": {
    "iso:country": "GB",
    "wof:name": "FK1 1EU",
    "wof:placetype": "postalcode"
  },
  "geometry": {"coordinates":[-3.786293,55.999902],"type":"Point"}
}
