{
  "type": "Feature",
  "properties": {
    "date:inception_lower": "2018-09-01",
    "date:inception_upper": "2018-09-01",
    "iso:country": "GB",
    "wof:name": "OX3 9FX",
    "wof:placetype": "postalcode"
  },
  "geometry": {"coordinates":[-1.21746,51.771117],"type":"Point"}
}
