{
  "type": "Feature",
  "properties": {
    "date:inception_lower":"1980-01-01",
    "date:inception_upper":"1980-01-31",
    "iso:country":"GB",
    "wof:name":"TW1 4RQ",
    "wof:placetype":"postalcode"
},
  "geometry": {"coordinates":[-0.334288,51.44031],"type":"Point"}
}