{
  "type": "Feature",
  "properties": {
    "iso:country":"GB",
    "wof:name":"PL21 9LU",
    "wof:placetype":"postalcode"
},
  "geometry": {"coordinates":[-3.91724714404892,50.36098809460349],"type":"Point"}
}