{
  "type": "Feature",
  "properties": {
    "iso:country": "GB",
    "wof:name": "OX16 2AS",
    "wof:placetype": "postalcode"
  },
  "geometry": {"coordinates":[-1.340923,52.063391],"type":"Point"}
}
