{
  "type": "Feature",
  "properties": {
    "date:inception_lower": "1998-06-01",
    "date:inception_upper": "1998-06-01",
    "iso:country": "GB",
    "wof:name": "WF3 3UB",
    "wof:placetype": "postalcode"
  },
  "geometry": {"coordinates":[-1.509001,53.740464],"type":"Point"}
}
