{
  "type": "Feature",
  "properties": {
    "iso:country":"GB",
    "wof:name":"WF3 3UB",
    "wof:placetype":"postalcode"
},
  "geometry": {"coordinates":[-1.50900106040615,53.74046447479957],"type":"Point"}
}