{
  "type": "Feature",
  "properties": {
    "iso:country":"GB",
    "wof:name":"L39 3BY",
    "wof:placetype":"postalcode"
},
  "geometry": {"coordinates":[-2.89000784676792,53.56765981709785],"type":"Point"}
}