{
  "type": "Feature",
  "properties": {
    "date:inception_lower": "1980-01-01",
    "date:inception_upper": "1980-01-01",
    "iso:country": "GB",
    "wof:name": "L39 3BY",
    "wof:placetype": "postalcode"
  },
  "geometry": {"coordinates":[-2.887272,53.566896],"type":"Point"}
}
