{
  "type": "Feature",
  "properties": {
    "iso:country":"GB",
    "wof:name":"CA11 0SH",
    "wof:placetype":"postalcode"
},
  "geometry": {"coordinates":[-2.96529093389485,54.64054483934967],"type":"Point"}
}