{
  "type": "Feature",
  "properties": {
    "iso:country":"GB",
    "wof:name":"LS24 9HA",
    "wof:placetype":"postalcode"
},
  "geometry": {"coordinates":[-1.26447447812326,53.88394113184913],"type":"Point"}
}