{
  "type": "Feature",
  "properties": {
    "iso:country":"GB",
    "wof:name":"KT19 9JY",
    "wof:placetype":"postalcode"
},
  "geometry": {"coordinates":[-0.27072105342383,51.36247663360101],"type":"Point"}
}