{
  "type": "Feature",
  "properties": {
    "iso:country": "GB",
    "wof:name": "L19 8JT",
    "wof:placetype": "postalcode"
  },
  "geometry": {"coordinates":[-2.891953,53.345532],"type":"Point"}
}
