{
  "type": "Feature",
  "properties": {
    "iso:country":"GB",
    "wof:name":"L19 8JT",
    "wof:placetype":"postalcode"
},
  "geometry": {"coordinates":[-2.89195293428028,53.34553238885687],"type":"Point"}
}