{
  "type": "Feature",
  "properties": {
    "date:inception_lower": "2010-04-01",
    "date:inception_upper": "2010-04-01",
    "iso:country": "GB",
    "wof:name": "EC2A 3AG",
    "wof:placetype": "postalcode"
  },
  "geometry": {"coordinates":[-0.080571,51.524945],"type":"Point"}
}
