{
  "type": "Feature",
  "properties": {
    "iso:country":"GB",
    "wof:name":"LE10 1UX",
    "wof:placetype":"postalcode"
},
  "geometry": {"coordinates":[-1.36498162276687,52.54608944765118],"type":"Point"}
}