{
  "type": "Feature",
  "properties": {
    "iso:country":"GB",
    "wof:name":"KY13 9FR",
    "wof:placetype":"postalcode"
},
  "geometry": {"coordinates":[-3.42059030741565,56.22250909531891],"type":"Point"}
}