{
  "type": "Feature",
  "properties": {
    "date:inception_lower": "1998-12-01",
    "date:inception_upper": "1998-12-01",
    "iso:country": "GB",
    "wof:name": "KY13 9FR",
    "wof:placetype": "postalcode"
  },
  "geometry": {"coordinates":[-3.42059,56.222509],"type":"Point"}
}
