{
  "type": "Feature",
  "properties": {
    "iso:country":"GB",
    "wof:name":"B36 9HB",
    "wof:placetype":"postalcode"
},
  "geometry": {"coordinates":[-1.76961167609627,52.50832651248543],"type":"Point"}
}