{
  "type": "Feature",
  "properties": {
    "iso:country":"GB",
    "wof:name":"BS9 4RS",
    "wof:placetype":"postalcode"
},
  "geometry": {"coordinates":[-2.60042886980341,51.48886074067898],"type":"Point"}
}