{
  "type": "Feature",
  "properties": {
    "date:inception_lower": "2019-04-01",
    "date:inception_upper": "2019-04-01",
    "iso:country": "GB",
    "wof:name": "G51 1AZ",
    "wof:placetype": "postalcode"
  },
  "geometry": {"coordinates":[-4.31009,55.850291],"type":"Point"}
}
