{
  "type": "Feature",
  "properties": {
    "iso:country": "GB",
    "wof:name": "G51 1AZ",
    "wof:placetype": "postalcode"
  },
  "geometry": {"coordinates":[-4.31009,55.850291],"type":"Point"}
}
