{
  "type": "Feature",
  "properties": {
    "date:inception_lower":"1990-02-01",
    "date:inception_upper":"1990-02-28",
    "iso:country":"GB",
    "wof:name":"BD2 3JG",
    "wof:placetype":"postalcode"
},
  "geometry": {"coordinates":[-1.716488,53.807008],"type":"Point"}
}