{
  "type": "Feature",
  "properties": {
    "iso:country":"GB",
    "wof:name":"BD2 3JG",
    "wof:placetype":"postalcode"
},
  "geometry": {"coordinates":[-1.71648850673212,53.80700763945855],"type":"Point"}
}