{
  "type": "Feature",
  "properties": {
    "iso:country":"GB",
    "wof:name":"IV12 5BS",
    "wof:placetype":"postalcode"
},
  "geometry": {"coordinates":[-3.85121713186035,57.58697438965336],"type":"Point"}
}