{
  "type": "Feature",
  "properties": {
    "iso:country":"GB",
    "wof:name":"BA22 7DG",
    "wof:placetype":"postalcode"
},
  "geometry": {"coordinates":[-2.52152275674704,51.04519112805521],"type":"Point"}
}