{
  "type": "Feature",
  "properties": {
    "iso:country": "GB",
    "wof:name": "NE27 0QE",
    "wof:placetype": "postalcode"
  },
  "geometry": {"coordinates":[-1.496607,55.01894],"type":"Point"}
}
