{
  "type": "Feature",
  "properties": {
    "iso:country":"GB",
    "wof:name":"NE27 0QE",
    "wof:placetype":"postalcode"
},
  "geometry": {"coordinates":[-1.49660741784809,55.01894009617458],"type":"Point"}
}