{
  "type": "Feature",
  "properties": {
    "iso:country":"GB",
    "wof:name":"CF41 7RT",
    "wof:placetype":"postalcode"
},
  "geometry": {"coordinates":[-3.46366729555788,51.64553722682094],"type":"Point"}
}