{
  "type": "Feature",
  "properties": {
    "iso:country": "GB",
    "wof:name": "HU17 0TJ",
    "wof:placetype": "postalcode"
  },
  "geometry": {"coordinates":[-0.395338,53.825815],"type":"Point"}
}
