{
  "type": "Feature",
  "properties": {
    "iso:country":"GB",
    "wof:name":"HU17 0TJ",
    "wof:placetype":"postalcode"
},
  "geometry": {"coordinates":[-0.3953381506864,53.8258151702859],"type":"Point"}
}