{
  "type": "Feature",
  "properties": {
    "date:inception_lower":"1980-01-01",
    "date:inception_upper":"1980-01-31",
    "iso:country":"GB",
    "wof:name":"HU17 0TJ",
    "wof:placetype":"postalcode"
},
  "geometry": {"coordinates":[-0.395338,53.825815],"type":"Point"}
}