{
  "type": "Feature",
  "properties": {
    "iso:country":"GB",
    "wof:name":"RH15 0TJ",
    "wof:placetype":"postalcode"
},
  "geometry": {"coordinates":[-0.11401290035935,50.95686520285579],"type":"Point"}
}