{
  "type": "Feature",
  "properties": {
    "iso:country":"GB",
    "wof:name":"HR4 8SP",
    "wof:placetype":"postalcode"
},
  "geometry": {"coordinates":[-2.87132111650691,52.1566101507519],"type":"Point"}
}