{
  "type": "Feature",
  "properties": {
    "iso:country": "GB",
    "wof:name": "HR4 8SP",
    "wof:placetype": "postalcode"
  },
  "geometry": {"coordinates":[-2.87162,52.156869],"type":"Point"}
}
