{
  "type": "Feature",
  "properties": {
    "date:inception_lower": "1980-01-01",
    "date:inception_upper": "1980-01-01",
    "iso:country": "GB",
    "wof:name": "NR11 6HA",
    "wof:placetype": "postalcode"
  },
  "geometry": {"coordinates":[1.249139,52.797277],"type":"Point"}
}
