{
  "type": "Feature",
  "properties": {
    "iso:country":"GB",
    "wof:name":"SW17 7EB",
    "wof:placetype":"postalcode"
},
  "geometry": {"coordinates":[-0.16684128824354,51.44470847759182],"type":"Point"}
}