{
  "type": "Feature",
  "properties": {
    "iso:country":"GB",
    "wof:name":"NP15 1JP",
    "wof:placetype":"postalcode"
},
  "geometry": {"coordinates":[-2.93859127089961,51.75672044491055],"type":"Point"}
}