{
  "type": "Feature",
  "properties": {
    "iso:country":"GB",
    "wof:name":"CB24 9XZ",
    "wof:placetype":"postalcode"
},
  "geometry": {"coordinates":[0.10777835246326,52.25765054455019],"type":"Point"}
}