{
  "type": "Feature",
  "properties": {
    "iso:country": "GB",
    "wof:name": "CB24 9XZ",
    "wof:placetype": "postalcode"
  },
  "geometry": {"coordinates":[0.107778,52.257651],"type":"Point"}
}
