{
  "type": "Feature",
  "properties": {
    "iso:country":"GB",
    "wof:name":"LL28 4DU",
    "wof:placetype":"postalcode"
},
  "geometry": {"coordinates":[-3.73915924392256,53.30442825771672],"type":"Point"}
}