{
  "type": "Feature",
  "properties": {
    "iso:country": "GB",
    "wof:name": "LS20 8BB",
    "wof:placetype": "postalcode"
  },
  "geometry": {"coordinates":[-1.711962,53.869328],"type":"Point"}
}
