{
  "type": "Feature",
  "properties": {
    "iso:country":"GB",
    "wof:name":"LS20 8BB",
    "wof:placetype":"postalcode"
},
  "geometry": {"coordinates":[-1.71196157282363,53.86932814949864],"type":"Point"}
}