{
  "type": "Feature",
  "properties": {
    "date:inception_lower": "2020-11-01",
    "date:inception_upper": "2020-11-01",
    "iso:country": "GB",
    "wof:name": "DE56 9GA",
    "wof:placetype": "postalcode"
  },
  "geometry": {"coordinates":[-1.485417,53.017388],"type":"Point"}
}
