{
  "type": "Feature",
  "properties": {
    "iso:country": "GB",
    "wof:name": "ME10 5BS",
    "wof:placetype": "postalcode"
  },
  "geometry": {"coordinates":[0.709369,51.350021],"type":"Point"}
}
