{
  "type": "Feature",
  "properties": {
    "iso:country":"GB",
    "wof:name":"B98 0DG",
    "wof:placetype":"postalcode"
},
  "geometry": {"coordinates":[-1.89592197070316,52.28942531861555],"type":"Point"}
}