{
  "type": "Feature",
  "properties": {
    "date:inception_lower":"1980-01-01",
    "date:inception_upper":"1980-01-31",
    "iso:country":"GB",
    "wof:name":"YO7 1PA",
    "wof:placetype":"postalcode"
},
  "geometry": {"coordinates":[-1.342162,54.221936],"type":"Point"}
}