{
  "type": "Feature",
  "properties": {
    "iso:country":"GB",
    "wof:name":"YO7 1PA",
    "wof:placetype":"postalcode"
},
  "geometry": {"coordinates":[-1.34216211908573,54.22193591427922],"type":"Point"}
}