{
  "type": "Feature",
  "properties": {
    "iso:country":"GB",
    "wof:name":"TW8 9JS",
    "wof:placetype":"postalcode"
},
  "geometry": {"coordinates":[-0.31601129117875,51.49162032728793],"type":"Point"}
}