{
  "type": "Feature",
  "properties": {
    "iso:country": "GB",
    "wof:name": "TW8 9JS",
    "wof:placetype": "postalcode"
  },
  "geometry": {"coordinates":[-0.316011,51.49162],"type":"Point"}
}
