{
  "type": "Feature",
  "properties": {
    "date:inception_lower":"1980-01-01",
    "date:inception_upper":"1980-01-31",
    "iso:country":"GB",
    "wof:name":"FK10 3JU",
    "wof:placetype":"postalcode"
},
  "geometry": {"coordinates":[-3.778233,56.128949],"type":"Point"}
}