{
  "type": "Feature",
  "properties": {
    "iso:country": "GB",
    "wof:name": "FK10 3JU",
    "wof:placetype": "postalcode"
  },
  "geometry": {"coordinates":[-3.778233,56.128949],"type":"Point"}
}
