{
  "type": "Feature",
  "properties": {
    "iso:country":"GB",
    "wof:name":"NE12 8QZ",
    "wof:placetype":"postalcode"
},
  "geometry": {"coordinates":[-1.58741288315407,55.0112209855696],"type":"Point"}
}