{
  "type": "Feature",
  "properties": {
    "date:inception_lower": "1980-01-01",
    "date:inception_upper": "1980-01-01",
    "iso:country": "GB",
    "wof:name": "NE12 8QZ",
    "wof:placetype": "postalcode"
  },
  "geometry": {"coordinates":[-1.587427,55.011228],"type":"Point"}
}
