{
  "type": "Feature",
  "properties": {
    "iso:country": "GB",
    "wof:name": "NE12 8QZ",
    "wof:placetype": "postalcode"
  },
  "geometry": {"coordinates":[-1.587427,55.011228],"type":"Point"}
}
