{
  "type": "Feature",
  "properties": {
    "iso:country":"GB",
    "wof:name":"ME12 1NS",
    "wof:placetype":"postalcode"
},
  "geometry": {"coordinates":[0.76173509345575,51.43998558988567],"type":"Point"}
}