{
  "type": "Feature",
  "properties": {
    "iso:country":"GB",
    "wof:name":"SO14 2DA",
    "wof:placetype":"postalcode"
},
  "geometry": {"coordinates":[-1.40523298665945,50.90298014796257],"type":"Point"}
}