{
  "type": "Feature",
  "properties": {
    "date:inception_lower": "1980-01-01",
    "date:inception_upper": "1980-01-01",
    "iso:country": "GB",
    "wof:name": "SP3 4TB",
    "wof:placetype": "postalcode"
  },
  "geometry": {"coordinates":[-1.891731,51.170504],"type":"Point"}
}
