{
  "type": "Feature",
  "properties": {
    "iso:country":"GB",
    "wof:name":"SP3 4TB",
    "wof:placetype":"postalcode"
},
  "geometry": {"coordinates":[-1.89173145305287,51.17050444989986],"type":"Point"}
}