{
  "type": "Feature",
  "properties": {
    "iso:country": "GB",
    "wof:name": "HP27 9FT",
    "wof:placetype": "postalcode"
  },
  "geometry": {"coordinates":[-0.860548,51.740362],"type":"Point"}
}
