{
  "type": "Feature",
  "properties": {
    "date:inception_lower": "2019-02-01",
    "date:inception_upper": "2019-02-01",
    "iso:country": "GB",
    "wof:name": "HP27 9FT",
    "wof:placetype": "postalcode"
  },
  "geometry": {"coordinates":[-0.860406,51.740243],"type":"Point"}
}
