{
  "type": "Feature",
  "properties": {
    "iso:country":"GB",
    "wof:name":"SN25 4GF",
    "wof:placetype":"postalcode"
},
  "geometry": {"coordinates":[-1.795950347206,51.60550071787047],"type":"Point"}
}