{
  "type": "Feature",
  "properties": {
    "date:inception_lower": "2000-06-01",
    "date:inception_upper": "2000-06-01",
    "iso:country": "GB",
    "wof:name": "SN25 4GF",
    "wof:placetype": "postalcode"
  },
  "geometry": {"coordinates":[-1.79595,51.605501],"type":"Point"}
}
