{
  "type": "Feature",
  "properties": {
    "iso:country":"GB",
    "wof:name":"GL19 3EF",
    "wof:placetype":"postalcode"
},
  "geometry": {"coordinates":[-2.38172814763894,51.86766052264377],"type":"Point"}
}