{
  "type": "Feature",
  "properties": {
    "iso:country":"GB",
    "wof:name":"W1U 6BU",
    "wof:placetype":"postalcode"
},
  "geometry": {"coordinates":[-0.15844439767353,51.52104033379747],"type":"Point"}
}