{
  "type": "Feature",
  "properties": {
    "date:inception_lower": "1980-01-01",
    "date:inception_upper": "1980-01-01",
    "iso:country": "GB",
    "wof:name": "DH3 4PG",
    "wof:placetype": "postalcode"
  },
  "geometry": {"coordinates":[-1.519082,54.861869],"type":"Point"}
}
