{
  "type": "Feature",
  "properties": {
    "iso:country":"GB",
    "wof:name":"DH3 4PG",
    "wof:placetype":"postalcode"
},
  "geometry": {"coordinates":[-1.51908223144438,54.86186865700218],"type":"Point"}
}