{
  "type": "Feature",
  "properties": {
    "iso:country":"GB",
    "wof:name":"PR25 3UT",
    "wof:placetype":"postalcode"
},
  "geometry": {"coordinates":[-2.69888404994039,53.70162526540523],"type":"Point"}
}