{
  "type": "Feature",
  "properties": {
    "iso:country": "GB",
    "wof:name": "PR25 3UT",
    "wof:placetype": "postalcode"
  },
  "geometry": {"coordinates":[-2.698884,53.701625],"type":"Point"}
}
