{
  "type": "Feature",
  "properties": {
    "date:inception_lower":"1980-01-01",
    "date:inception_upper":"1980-01-31",
    "iso:country":"GB",
    "wof:name":"WA15 0NA",
    "wof:placetype":"postalcode"
},
  "geometry": {"coordinates":[-2.337819,53.370222],"type":"Point"}
}