{
  "type": "Feature",
  "properties": {
    "iso:country":"GB",
    "wof:name":"WA15 0NA",
    "wof:placetype":"postalcode"
},
  "geometry": {"coordinates":[-2.33781912101833,53.37022213627417],"type":"Point"}
}