{
  "type": "Feature",
  "properties": {
    "iso:country":"GB",
    "wof:name":"ST5 0SU",
    "wof:placetype":"postalcode"
},
  "geometry": {"coordinates":[-2.2136073151386,53.01641002920389],"type":"Point"}
}