{
  "type": "Feature",
  "properties": {
    "iso:country": "GB",
    "wof:name": "SL9 0EH",
    "wof:placetype": "postalcode"
  },
  "geometry": {"coordinates":[-0.546758,51.620703],"type":"Point"}
}
