{
  "type": "Feature",
  "properties": {
    "iso:country":"GB",
    "wof:name":"SL9 0EH",
    "wof:placetype":"postalcode"
},
  "geometry": {"coordinates":[-0.54675796175181,51.62070274575091],"type":"Point"}
}