{
  "type": "Feature",
  "properties": {
    "date:inception_lower": "2015-11-01",
    "date:inception_upper": "2015-11-01",
    "iso:country": "GB",
    "wof:name": "SL9 0EH",
    "wof:placetype": "postalcode"
  },
  "geometry": {"coordinates":[-0.546883,51.620662],"type":"Point"}
}
