{
  "type": "Feature",
  "properties": {
    "iso:country":"GB",
    "wof:name":"BB10 2AN",
    "wof:placetype":"postalcode"
},
  "geometry": {"coordinates":[-2.2237301212227,53.7984954960102],"type":"Point"}
}