{
  "type": "Feature",
  "properties": {
    "date:inception_lower": "1980-01-01",
    "date:inception_upper": "1980-01-01",
    "iso:country": "GB",
    "wof:name": "DH5 8AA",
    "wof:placetype": "postalcode"
  },
  "geometry": {"coordinates":[-1.466325,54.842345],"type":"Point"}
}
