{
  "type": "Feature",
  "properties": {
    "iso:country":"GB",
    "wof:name":"DH5 8AA",
    "wof:placetype":"postalcode"
},
  "geometry": {"coordinates":[-1.46632470210557,54.84234540550812],"type":"Point"}
}