{
  "type": "Feature",
  "properties": {
    "iso:country":"GB",
    "wof:name":"CH42 7JD",
    "wof:placetype":"postalcode"
},
  "geometry": {"coordinates":[-3.03022700527605,53.37933185332191],"type":"Point"}
}