{
  "type": "Feature",
  "properties": {
    "iso:country":"GB",
    "wof:name":"OL13 9DE",
    "wof:placetype":"postalcode"
},
  "geometry": {"coordinates":[-2.19793724099762,53.70534390018271],"type":"Point"}
}