{
  "type": "Feature",
  "properties": {
    "date:inception_lower": "2019-09-01",
    "date:inception_upper": "2019-09-01",
    "iso:country": "GB",
    "wof:name": "L34 1AY",
    "wof:placetype": "postalcode"
  },
  "geometry": {"coordinates":[-2.810682,53.421158],"type":"Point"}
}
