{
  "type": "Feature",
  "properties": {
    "iso:country": "GB",
    "wof:name": "L34 1AY",
    "wof:placetype": "postalcode"
  },
  "geometry": {"coordinates":[-2.810682,53.421158],"type":"Point"}
}
