{
  "type": "Feature",
  "properties": {
    "iso:country":"GB",
    "wof:name":"BN1 4EH",
    "wof:placetype":"postalcode"
},
  "geometry": {"coordinates":[-0.13912183275627,50.82793439578592],"type":"Point"}
}