{
  "type": "Feature",
  "properties": {
    "iso:country":"GB",
    "wof:name":"DL12 0EP",
    "wof:placetype":"postalcode"
},
  "geometry": {"coordinates":[-2.19474745553879,54.65440927924944],"type":"Point"}
}