{
  "type": "Feature",
  "properties": {
    "date:inception_lower": "2016-03-01",
    "date:inception_upper": "2016-03-01",
    "iso:country": "GB",
    "wof:name": "BB12 0AF",
    "wof:placetype": "postalcode"
  },
  "geometry": {"coordinates":[-2.245562,53.798431],"type":"Point"}
}
