{
  "type": "Feature",
  "properties": {
    "iso:country":"GB",
    "wof:name":"GU23 6DX",
    "wof:placetype":"postalcode"
},
  "geometry": {"coordinates":[-0.50871079312623,51.29909607256072],"type":"Point"}
}