{
  "type": "Feature",
  "properties": {
    "iso:country":"GB",
    "wof:name":"SW16 1NJ",
    "wof:placetype":"postalcode"
},
  "geometry": {"coordinates":[-0.13042764561315,51.43533859632142],"type":"Point"}
}