{
  "type": "Feature",
  "properties": {
    "iso:country": "GB",
    "wof:name": "SW16 1NJ",
    "wof:placetype": "postalcode"
  },
  "geometry": {"coordinates":[-0.130428,51.435339],"type":"Point"}
}
