{
  "type": "Feature",
  "properties": {
    "iso:country":"GB",
    "wof:name":"CF3 2TS",
    "wof:placetype":"postalcode"
},
  "geometry": {"coordinates":[-3.06674576162067,51.51747515615438],"type":"Point"}
}