{
  "type": "Feature",
  "properties": {
    "iso:country":"GB",
    "wof:name":"EH11 1TL",
    "wof:placetype":"postalcode"
},
  "geometry": {"coordinates":[-3.23231625252694,55.93723995379758],"type":"Point"}
}