{
  "type": "Feature",
  "properties": {
    "iso:country":"GB",
    "wof:name":"NE63 9YG",
    "wof:placetype":"postalcode"
},
  "geometry": {"coordinates":[-1.54957545824707,55.18801425848215],"type":"Point"}
}