{
  "type": "Feature",
  "properties": {
    "date:inception_lower": "1996-06-01",
    "date:inception_upper": "1996-06-01",
    "iso:country": "GB",
    "wof:name": "AB42 1HD",
    "wof:placetype": "postalcode"
  },
  "geometry": {"coordinates":[-1.795635,57.512678],"type":"Point"}
}
