{
  "type": "Feature",
  "properties": {
    "iso:country":"GB",
    "wof:name":"LS23 7BG",
    "wof:placetype":"postalcode"
},
  "geometry": {"coordinates":[-1.3300051344811,53.922505567526],"type":"Point"}
}