{
  "type": "Feature",
  "properties": {
    "date:inception_lower": "1980-01-01",
    "date:inception_upper": "1980-01-01",
    "iso:country": "GB",
    "wof:name": "LS23 7BG",
    "wof:placetype": "postalcode"
  },
  "geometry": {"coordinates":[-1.330005,53.922506],"type":"Point"}
}
