{
  "type": "Feature",
  "properties": {
    "iso:country": "GB",
    "wof:name": "PL19 9RF",
    "wof:placetype": "postalcode"
  },
  "geometry": {"coordinates":[-4.143177,50.546336],"type":"Point"}
}
