{
  "type": "Feature",
  "properties": {
    "iso:country": "GB",
    "wof:name": "TN16 2LT",
    "wof:placetype": "postalcode"
  },
  "geometry": {"coordinates":[0.042354,51.291005],"type":"Point"}
}
