{
  "type": "Feature",
  "properties": {
    "iso:country":"GB",
    "wof:name":"M24 2BL",
    "wof:placetype":"postalcode"
},
  "geometry": {"coordinates":[-2.17828813481551,53.54376642083482],"type":"Point"}
}