{
  "type": "Feature",
  "properties": {
    "iso:country":"GB",
    "wof:name":"HP5 3JN",
    "wof:placetype":"postalcode"
},
  "geometry": {"coordinates":[-0.60209745164911,51.71703858585739],"type":"Point"}
}