{
  "type": "Feature",
  "properties": {
    "iso:country":"GB",
    "wof:name":"GL2 9BW",
    "wof:placetype":"postalcode"
},
  "geometry": {"coordinates":[-2.23389031100098,51.88915823337869],"type":"Point"}
}