{
  "type": "Feature",
  "properties": {
    "iso:country": "GB",
    "wof:name": "GL2 9BW",
    "wof:placetype": "postalcode"
  },
  "geometry": {"coordinates":[-2.23389,51.889158],"type":"Point"}
}
