{
  "type": "Feature",
  "properties": {
    "iso:country":"GB",
    "wof:name":"TS10 5AH",
    "wof:placetype":"postalcode"
},
  "geometry": {"coordinates":[-1.08803684437942,54.61710147201799],"type":"Point"}
}