{
  "type": "Feature",
  "properties": {
    "iso:country":"GB",
    "wof:name":"WD19 4HH",
    "wof:placetype":"postalcode"
},
  "geometry": {"coordinates":[-0.3844883641193,51.64315743757574],"type":"Point"}
}