{
  "type": "Feature",
  "properties": {
    "iso:country": "GB",
    "wof:name": "WD19 4HH",
    "wof:placetype": "postalcode"
  },
  "geometry": {"coordinates":[-0.384488,51.643157],"type":"Point"}
}
