{
  "type": "Feature",
  "properties": {
    "date:inception_lower":"2000-10-01",
    "date:inception_upper":"2000-10-31",
    "iso:country":"GB",
    "wof:name":"WD19 4HH",
    "wof:placetype":"postalcode"
},
  "geometry": {"coordinates":[-0.384488,51.643157],"type":"Point"}
}