{
  "type": "Feature",
  "properties": {
    "iso:country":"GB",
    "wof:name":"LL12 9HT",
    "wof:placetype":"postalcode"
},
  "geometry": {"coordinates":[-3.04639791801353,53.10461540544008],"type":"Point"}
}