{
  "type": "Feature",
  "properties": {
    "date:inception_lower": "2020-02-01",
    "date:inception_upper": "2020-02-01",
    "iso:country": "GB",
    "wof:name": "LE17 4FU",
    "wof:placetype": "postalcode"
  },
  "geometry": {"coordinates":[-1.221993,52.454822],"type":"Point"}
}
