{
  "type": "Feature",
  "properties": {
    "date:inception_lower":"1980-01-01",
    "date:inception_upper":"1980-01-31",
    "iso:country":"GB",
    "wof:name":"DN35 8HT",
    "wof:placetype":"postalcode"
},
  "geometry": {"coordinates":[-0.028854,53.557134],"type":"Point"}
}