{
  "type": "Feature",
  "properties": {
    "iso:country": "GB",
    "wof:name": "NR11 8SH",
    "wof:placetype": "postalcode"
  },
  "geometry": {"coordinates":[1.298325,52.884028],"type":"Point"}
}
