{
  "type": "Feature",
  "properties": {
    "iso:country":"GB",
    "wof:name":"NR11 8SH",
    "wof:placetype":"postalcode"
},
  "geometry": {"coordinates":[1.29832536474111,52.88402794730317],"type":"Point"}
}