{
  "type": "Feature",
  "properties": {
    "date:inception_lower":"1980-01-01",
    "date:inception_upper":"1980-01-31",
    "iso:country":"GB",
    "wof:name":"NR11 8SH",
    "wof:placetype":"postalcode"
},
  "geometry": {"coordinates":[1.298325,52.884028],"type":"Point"}
}