{
  "type": "Feature",
  "properties": {
    "iso:country":"GB",
    "wof:name":"EN2 8DF",
    "wof:placetype":"postalcode"
},
  "geometry": {"coordinates":[-0.09176621713961,51.65462763522283],"type":"Point"}
}