{
  "type": "Feature",
  "properties": {
    "iso:country":"GB",
    "wof:name":"SN5 5RS",
    "wof:placetype":"postalcode"
},
  "geometry": {"coordinates":[-1.83661968541096,51.56709931940831],"type":"Point"}
}