{
  "type": "Feature",
  "properties": {
    "date:inception_lower": "2000-06-01",
    "date:inception_upper": "2000-06-01",
    "iso:country": "GB",
    "wof:name": "SN5 5RS",
    "wof:placetype": "postalcode"
  },
  "geometry": {"coordinates":[-1.83662,51.567099],"type":"Point"}
}
