{
  "type": "Feature",
  "properties": {
    "iso:country": "GB",
    "wof:name": "LE9 7QF",
    "wof:placetype": "postalcode"
  },
  "geometry": {"coordinates":[-1.327023,52.603056],"type":"Point"}
}
