{
  "type": "Feature",
  "properties": {
    "iso:country":"GB",
    "wof:name":"LE9 7QF",
    "wof:placetype":"postalcode"
},
  "geometry": {"coordinates":[-1.32702297990042,52.60305607618149],"type":"Point"}
}