{
  "type": "Feature",
  "properties": {
    "date:inception_lower":"1983-03-01",
    "date:inception_upper":"1983-03-31",
    "iso:country":"GB",
    "wof:name":"LE9 7QF",
    "wof:placetype":"postalcode"
},
  "geometry": {"coordinates":[-1.327023,52.603056],"type":"Point"}
}