{
  "type": "Feature",
  "properties": {
    "iso:country": "GB",
    "wof:name": "YO17 8TJ",
    "wof:placetype": "postalcode"
  },
  "geometry": {"coordinates":[-0.54315,54.121008],"type":"Point"}
}
