{
  "type": "Feature",
  "properties": {
    "iso:country":"GB",
    "wof:name":"M25 0GU",
    "wof:placetype":"postalcode"
},
  "geometry": {"coordinates":[-2.26127379596144,53.52204162006829],"type":"Point"}
}