{
  "type": "Feature",
  "properties": {
    "date:inception_lower": "1996-06-01",
    "date:inception_upper": "1996-06-01",
    "iso:country": "GB",
    "wof:name": "M25 0GU",
    "wof:placetype": "postalcode"
  },
  "geometry": {"coordinates":[-2.261274,53.522042],"type":"Point"}
}
