{
  "type": "Feature",
  "properties": {
    "iso:country":"GB",
    "wof:name":"SM5 1HL",
    "wof:placetype":"postalcode"
},
  "geometry": {"coordinates":[-0.17353924976258,51.3875391352172],"type":"Point"}
}