{
  "type": "Feature",
  "properties": {
    "iso:country":"GB",
    "wof:name":"RG14 2PQ",
    "wof:placetype":"postalcode"
},
  "geometry": {"coordinates":[-1.29635974146045,51.4076523756446],"type":"Point"}
}