{
  "type": "Feature",
  "properties": {
    "iso:country": "GB",
    "wof:name": "SS0 7QT",
    "wof:placetype": "postalcode"
  },
  "geometry": {"coordinates":[0.698146,51.535919],"type":"Point"}
}
