{
  "type": "Feature",
  "properties": {
    "date:inception_lower": "1992-08-01",
    "date:inception_upper": "1992-08-01",
    "iso:country": "GB",
    "wof:name": "SS0 7QT",
    "wof:placetype": "postalcode"
  },
  "geometry": {"coordinates":[0.698146,51.535919],"type":"Point"}
}
