{
  "type": "Feature",
  "properties": {
    "iso:country":"GB",
    "wof:name":"SS0 7QT",
    "wof:placetype":"postalcode"
},
  "geometry": {"coordinates":[0.69814600577715,51.53591919514064],"type":"Point"}
}