{
  "type": "Feature",
  "properties": {
    "iso:country": "GB",
    "wof:name": "SO31 4RJ",
    "wof:placetype": "postalcode"
  },
  "geometry": {"coordinates":[-1.322434,50.86128],"type":"Point"}
}
