{
  "type": "Feature",
  "properties": {
    "iso:country":"GB",
    "wof:name":"SO31 4RJ",
    "wof:placetype":"postalcode"
},
  "geometry": {"coordinates":[-1.32244392855109,50.861289407331],"type":"Point"}
}