{
  "type": "Feature",
  "properties": {
    "iso:country":"GB",
    "wof:name":"CF71 7DU",
    "wof:placetype":"postalcode"
},
  "geometry": {"coordinates":[-3.43546027254636,51.45881552161549],"type":"Point"}
}