{
  "type": "Feature",
  "properties": {
    "iso:country":"GB",
    "wof:name":"FK2 8BY",
    "wof:placetype":"postalcode"
},
  "geometry": {"coordinates":[-3.78691380879951,56.02951671588645],"type":"Point"}
}