{
  "type": "Feature",
  "properties": {
    "iso:country": "GB",
    "wof:name": "FK2 8BY",
    "wof:placetype": "postalcode"
  },
  "geometry": {"coordinates":[-3.786914,56.029517],"type":"Point"}
}
