{
  "type": "Feature",
  "properties": {
    "iso:country":"GB",
    "wof:name":"N1 9BW",
    "wof:placetype":"postalcode"
},
  "geometry": {"coordinates":[-0.12212169435402,51.53150724162664],"type":"Point"}
}