{
  "type": "Feature",
  "properties": {
    "iso:country": "GB",
    "wof:name": "PE13 4ST",
    "wof:placetype": "postalcode"
  },
  "geometry": {"coordinates":[0.095014,52.652912],"type":"Point"}
}
