{
  "type": "Feature",
  "properties": {
    "date:inception_lower":"1991-09-01",
    "date:inception_upper":"1991-09-30",
    "iso:country":"GB",
    "wof:name":"PE13 4ST",
    "wof:placetype":"postalcode"
},
  "geometry": {"coordinates":[0.095014,52.652912],"type":"Point"}
}