{
  "type": "Feature",
  "properties": {
    "iso:country":"GB",
    "wof:name":"CW3 9AD",
    "wof:placetype":"postalcode"
},
  "geometry": {"coordinates":[-2.36991841598884,53.0379867967654],"type":"Point"}
}