{
  "type": "Feature",
  "properties": {
    "iso:country":"GB",
    "wof:name":"TS16 0DX",
    "wof:placetype":"postalcode"
},
  "geometry": {"coordinates":[-1.35543719540907,54.5173565144643],"type":"Point"}
}