{
  "type": "Feature",
  "properties": {
    "iso:country":"GB",
    "wof:name":"NG31 9HL",
    "wof:placetype":"postalcode"
},
  "geometry": {"coordinates":[-0.63583039879882,52.91887302575793],"type":"Point"}
}