{
  "type": "Feature",
  "properties": {
    "iso:country":"GB",
    "wof:name":"RM18 8AS",
    "wof:placetype":"postalcode"
},
  "geometry": {"coordinates":[0.37299873000616,51.46456458487827],"type":"Point"}
}