{
  "type": "Feature",
  "properties": {
    "iso:country":"GB",
    "wof:name":"LN4 1JY",
    "wof:placetype":"postalcode"
},
  "geometry": {"coordinates":[-0.47638359883931,53.21489812632786],"type":"Point"}
}