{
  "type": "Feature",
  "properties": {
    "iso:country": "GB",
    "wof:name": "LN4 1JY",
    "wof:placetype": "postalcode"
  },
  "geometry": {"coordinates":[-0.476384,53.214898],"type":"Point"}
}
