{
  "type": "Feature",
  "properties": {
    "date:inception_lower":"1980-01-01",
    "date:inception_upper":"1980-01-31",
    "iso:country":"GB",
    "wof:name":"LN4 1JY",
    "wof:placetype":"postalcode"
},
  "geometry": {"coordinates":[-0.476384,53.214898],"type":"Point"}
}