{
  "type": "Feature",
  "properties": {
    "iso:country": "GB",
    "wof:name": "NG8 3PY",
    "wof:placetype": "postalcode"
  },
  "geometry": {"coordinates":[-1.199176,52.96356],"type":"Point"}
}
