{
  "type": "Feature",
  "properties": {
    "date:inception_lower": "2019-04-01",
    "date:inception_upper": "2019-04-01",
    "iso:country": "GB",
    "wof:name": "NG8 3PY",
    "wof:placetype": "postalcode"
  },
  "geometry": {"coordinates":[-1.198566,52.96352],"type":"Point"}
}
