{
  "type": "Feature",
  "properties": {
    "date:inception_lower":"2019-04-01",
    "date:inception_upper":"2019-04-30",
    "iso:country":"GB",
    "wof:name":"NG8 3PY",
    "wof:placetype":"postalcode"
},
  "geometry": {"coordinates":[-1.199176,52.96356],"type":"Point"}
}