{
  "type": "Feature",
  "properties": {
    "date:inception_lower":"1980-01-01",
    "date:inception_upper":"1980-01-31",
    "iso:country":"GB",
    "wof:name":"NG1 1DF",
    "wof:placetype":"postalcode"
},
  "geometry": {"coordinates":[-1.137281,52.954785],"type":"Point"}
}