{
  "type": "Feature",
  "properties": {
    "iso:country": "GB",
    "wof:name": "NG1 1DF",
    "wof:placetype": "postalcode"
  },
  "geometry": {"coordinates":[-1.137281,52.954785],"type":"Point"}
}
