{
  "type": "Feature",
  "properties": {
    "iso:country":"GB",
    "wof:name":"NG1 1DF",
    "wof:placetype":"postalcode"
},
  "geometry": {"coordinates":[-1.13725613314621,52.95468393303157],"type":"Point"}
}