{
  "type": "Feature",
  "properties": {
    "iso:country":"GB",
    "wof:name":"NE27 0BW",
    "wof:placetype":"postalcode"
},
  "geometry": {"coordinates":[-1.51964025130855,55.03110163654296],"type":"Point"}
}