{
  "type": "Feature",
  "properties": {
    "date:inception_lower":"2007-04-01",
    "date:inception_upper":"2007-04-30",
    "iso:country":"GB",
    "wof:name":"NE27 0BW",
    "wof:placetype":"postalcode"
},
  "geometry": {"coordinates":[-1.51964,55.031102],"type":"Point"}
}