{
  "type": "Feature",
  "properties": {
    "date:inception_lower": "2021-06-01",
    "date:inception_upper": "2021-06-01",
    "iso:country": "GB",
    "wof:name": "EX9 7DD",
    "wof:placetype": "postalcode"
  },
  "geometry": {"coordinates":[-3.2952,50.664249],"type":"Point"}
}
