{
  "type": "Feature",
  "properties": {
    "date:inception_lower": "2023-04-01",
    "date:inception_upper": "2023-04-01",
    "iso:country": "GB",
    "wof:name": "KT22 0DA",
    "wof:placetype": "postalcode"
  },
  "geometry": {"coordinates":[-0.351456,51.326006],"type":"Point"}
}
