{
  "type": "Feature",
  "properties": {
    "iso:country":"GB",
    "wof:name":"RH13 0YB",
    "wof:placetype":"postalcode"
},
  "geometry": {"coordinates":[-0.36079797236353,51.04515996034898],"type":"Point"}
}