{
  "type": "Feature",
  "properties": {
    "iso:country": "GB",
    "wof:name": "RH13 0YB",
    "wof:placetype": "postalcode"
  },
  "geometry": {"coordinates":[-0.360798,51.04516],"type":"Point"}
}
