{
  "type": "Feature",
  "properties": {
    "iso:country":"GB",
    "wof:name":"BH20 6LN",
    "wof:placetype":"postalcode"
},
  "geometry": {"coordinates":[-2.2498817499416,50.69767557230576],"type":"Point"}
}