{
  "type": "Feature",
  "properties": {
    "iso:country": "GB",
    "wof:name": "BS36 1LN",
    "wof:placetype": "postalcode"
  },
  "geometry": {"coordinates":[-2.497628,51.525173],"type":"Point"}
}
