{
  "type": "Feature",
  "properties": {
    "iso:country": "GB",
    "wof:name": "KT3 5QG",
    "wof:placetype": "postalcode"
  },
  "geometry": {"coordinates":[-0.257842,51.394263],"type":"Point"}
}
