{
  "type": "Feature",
  "properties": {
    "iso:country":"GB",
    "wof:name":"KT3 5QG",
    "wof:placetype":"postalcode"
},
  "geometry": {"coordinates":[-0.25786512144385,51.3942637254122],"type":"Point"}
}