{
  "type": "Feature",
  "properties": {
    "date:inception_lower": "2000-12-01",
    "date:inception_upper": "2000-12-01",
    "iso:country": "GB",
    "wof:name": "L40 5YF",
    "wof:placetype": "postalcode"
  },
  "geometry": {"coordinates":[-2.836486,53.593232],"type":"Point"}
}
