{
  "type": "Feature",
  "properties": {
    "iso:country": "GB",
    "wof:name": "L40 5YF",
    "wof:placetype": "postalcode"
  },
  "geometry": {"coordinates":[-2.836486,53.593232],"type":"Point"}
}
