{
  "type": "Feature",
  "properties": {
    "iso:country":"GB",
    "wof:name":"L40 5YF",
    "wof:placetype":"postalcode"
},
  "geometry": {"coordinates":[-2.83648609137426,53.59323213369146],"type":"Point"}
}