{
  "type": "Feature",
  "properties": {
    "iso:country":"GB",
    "wof:name":"AB56 5EP",
    "wof:placetype":"postalcode"
},
  "geometry": {"coordinates":[-2.98430452508022,57.64096208416002],"type":"Point"}
}