{
  "type": "Feature",
  "properties": {
    "date:inception_lower": "1980-01-01",
    "date:inception_upper": "1980-01-01",
    "iso:country": "GB",
    "wof:name": "SG4 8PF",
    "wof:placetype": "postalcode"
  },
  "geometry": {"coordinates":[-0.333105,51.890085],"type":"Point"}
}
