{
  "type": "Feature",
  "properties": {
    "date:inception_lower":"1993-08-01",
    "date:inception_upper":"1993-08-31",
    "iso:country":"GB",
    "wof:name":"B50 4LY",
    "wof:placetype":"postalcode"
},
  "geometry": {"coordinates":[-1.83081,52.162955],"type":"Point"}
}