{
  "type": "Feature",
  "properties": {
    "iso:country":"GB",
    "wof:name":"B50 4LY",
    "wof:placetype":"postalcode"
},
  "geometry": {"coordinates":[-1.83080997784301,52.16295471848649],"type":"Point"}
}