{
  "type": "Feature",
  "properties": {
    "iso:country": "GB",
    "wof:name": "B50 4LY",
    "wof:placetype": "postalcode"
  },
  "geometry": {"coordinates":[-1.83081,52.162955],"type":"Point"}
}
