{
  "type": "Feature",
  "properties": {
    "date:inception_lower": "2007-10-01",
    "date:inception_upper": "2007-10-01",
    "iso:country": "GB",
    "wof:name": "CT11 0BZ",
    "wof:placetype": "postalcode"
  },
  "geometry": {"coordinates":[1.405204,51.332879],"type":"Point"}
}
