{
  "type": "Feature",
  "properties": {
    "iso:country":"GB",
    "wof:name":"CT11 0BZ",
    "wof:placetype":"postalcode"
},
  "geometry": {"coordinates":[1.40520425284744,51.33287874390575],"type":"Point"}
}