{
  "type": "Feature",
  "properties": {
    "date:inception_lower": "2000-12-01",
    "date:inception_upper": "2000-12-01",
    "iso:country": "GB",
    "wof:name": "W1T 7PT",
    "wof:placetype": "postalcode"
  },
  "geometry": {"coordinates":[-0.13319,51.519976],"type":"Point"}
}
