{
  "type": "Feature",
  "properties": {
    "date:inception_lower":"1980-01-01",
    "date:inception_upper":"1980-01-31",
    "iso:country":"GB",
    "wof:name":"WF1 2QX",
    "wof:placetype":"postalcode"
},
  "geometry": {"coordinates":[-1.50684,53.688001],"type":"Point"}
}