{
  "type": "Feature",
  "properties": {
    "iso:country":"GB",
    "wof:name":"CA17 4AJ",
    "wof:placetype":"postalcode"
},
  "geometry": {"coordinates":[-2.34758538379074,54.46895545966436],"type":"Point"}
}