{
  "type": "Feature",
  "properties": {
    "iso:country":"GB",
    "wof:name":"OX5 1JH",
    "wof:placetype":"postalcode"
},
  "geometry": {"coordinates":[-1.31071677995608,51.84482843778167],"type":"Point"}
}