{
  "type": "Feature",
  "properties": {
    "iso:country": "GB",
    "wof:name": "NE5 1JU",
    "wof:placetype": "postalcode"
  },
  "geometry": {"coordinates":[-1.720399,54.995999],"type":"Point"}
}
