{
  "type": "Feature",
  "properties": {
    "iso:country": "GB",
    "wof:name": "NE35 9BH",
    "wof:placetype": "postalcode"
  },
  "geometry": {"coordinates":[-1.458396,54.947182],"type":"Point"}
}
