{
  "type": "Feature",
  "properties": {
    "iso:country":"GB",
    "wof:name":"NE35 9BH",
    "wof:placetype":"postalcode"
},
  "geometry": {"coordinates":[-1.45839608686283,54.94718214646971],"type":"Point"}
}