{
  "type": "Feature",
  "properties": {
    "iso:country":"GB",
    "wof:name":"DD8 3ER",
    "wof:placetype":"postalcode"
},
  "geometry": {"coordinates":[-2.88160652841065,56.64964163184295],"type":"Point"}
}