{
  "type": "Feature",
  "properties": {
    "iso:country":"GB",
    "wof:name":"DA2 6RQ",
    "wof:placetype":"postalcode"
},
  "geometry": {"coordinates":[0.23768261498031,51.44616412797179],"type":"Point"}
}