{
  "type": "Feature",
  "properties": {
    "iso:country":"GB",
    "wof:name":"UB5 6QS",
    "wof:placetype":"postalcode"
},
  "geometry": {"coordinates":[-0.3974636910714,51.5382263103559],"type":"Point"}
}