{
  "type": "Feature",
  "properties": {
    "date:inception_lower": "1989-07-01",
    "date:inception_upper": "1989-07-01",
    "iso:country": "GB",
    "wof:name": "KA14 3BX",
    "wof:placetype": "postalcode"
  },
  "geometry": {"coordinates":[-4.661227,55.737723],"type":"Point"}
}
