{
  "type": "Feature",
  "properties": {
    "iso:country": "GB",
    "wof:name": "KA14 3BX",
    "wof:placetype": "postalcode"
  },
  "geometry": {"coordinates":[-4.661227,55.737723],"type":"Point"}
}
