{
  "type": "Feature",
  "properties": {
    "iso:country":"GB",
    "wof:name":"KA14 3BX",
    "wof:placetype":"postalcode"
},
  "geometry": {"coordinates":[-4.66124642714968,55.73772689539021],"type":"Point"}
}