{
  "type": "Feature",
  "properties": {
    "iso:country": "GB",
    "wof:name": "KA14 3BX",
    "wof:placetype": "postalcode"
  },
  "geometry": {"coordinates":[-4.663396,55.737523],"type":"Point"}
}
