{
  "type": "Feature",
  "properties": {
    "date:inception_lower": "1980-01-01",
    "date:inception_upper": "1980-01-01",
    "iso:country": "GB",
    "wof:name": "SK16 5NL",
    "wof:placetype": "postalcode"
  },
  "geometry": {"coordinates":[-2.076745,53.478206],"type":"Point"}
}
