{
  "type": "Feature",
  "properties": {
    "iso:country":"GB",
    "wof:name":"SK16 5NL",
    "wof:placetype":"postalcode"
},
  "geometry": {"coordinates":[-2.07674477218694,53.47820572426791],"type":"Point"}
}