{
  "type": "Feature",
  "properties": {
    "date:inception_lower":"1980-01-01",
    "date:inception_upper":"1980-01-31",
    "iso:country":"GB",
    "wof:name":"WV14 6QS",
    "wof:placetype":"postalcode"
},
  "geometry": {"coordinates":[-2.082217,52.57315],"type":"Point"}
}