{
  "type": "Feature",
  "properties": {
    "date:inception_lower":"1992-08-01",
    "date:inception_upper":"1992-08-31",
    "iso:country":"GB",
    "wof:name":"MK18 3QF",
    "wof:placetype":"postalcode"
},
  "geometry": {"coordinates":[-0.87945,51.898552],"type":"Point"}
}