{
  "type": "Feature",
  "properties": {
    "iso:country":"GB",
    "wof:name":"MK18 3QF",
    "wof:placetype":"postalcode"
},
  "geometry": {"coordinates":[-0.87945041972447,51.89855247656991],"type":"Point"}
}