{
  "type": "Feature",
  "properties": {
    "iso:country":"GB",
    "wof:name":"ME8 6RA",
    "wof:placetype":"postalcode"
},
  "geometry": {"coordinates":[0.58628762294614,51.3786688253788],"type":"Point"}
}