{
  "type": "Feature",
  "properties": {
    "iso:country":"GB",
    "wof:name":"LS25 7RR",
    "wof:placetype":"postalcode"
},
  "geometry": {"coordinates":[-1.37597159695286,53.76534543957226],"type":"Point"}
}