{
  "type": "Feature",
  "properties": {
    "date:inception_lower": "1994-12-01",
    "date:inception_upper": "1994-12-01",
    "iso:country": "GB",
    "wof:name": "LS25 7RR",
    "wof:placetype": "postalcode"
  },
  "geometry": {"coordinates":[-1.375972,53.765345],"type":"Point"}
}
