{
  "type": "Feature",
  "properties": {
    "iso:country":"GB",
    "wof:name":"OL6 9EB",
    "wof:placetype":"postalcode"
},
  "geometry": {"coordinates":[-2.07401716815694,53.50385141626592],"type":"Point"}
}