{
  "type": "Feature",
  "properties": {
    "date:inception_lower":"1980-01-01",
    "date:inception_upper":"1980-01-31",
    "iso:country":"GB",
    "wof:name":"SS0 7SZ",
    "wof:placetype":"postalcode"
},
  "geometry": {"coordinates":[0.68857,51.535905],"type":"Point"}
}