{
  "type": "Feature",
  "properties": {
    "iso:country":"GB",
    "wof:name":"NR24 2JE",
    "wof:placetype":"postalcode"
},
  "geometry": {"coordinates":[1.06838238457329,52.84912573514406],"type":"Point"}
}