{
  "type": "Feature",
  "properties": {
    "iso:country":"GB",
    "wof:name":"S73 8QX",
    "wof:placetype":"postalcode"
},
  "geometry": {"coordinates":[-1.41572679550479,53.52490129185824],"type":"Point"}
}