{
  "type": "Feature",
  "properties": {
    "iso:country": "GB",
    "wof:name": "S73 8QX",
    "wof:placetype": "postalcode"
  },
  "geometry": {"coordinates":[-1.415727,53.524901],"type":"Point"}
}
