{
  "type": "Feature",
  "properties": {
    "iso:country":"GB",
    "wof:name":"OX44 7UZ",
    "wof:placetype":"postalcode"
},
  "geometry": {"coordinates":[-1.1435297298333,51.68490820252467],"type":"Point"}
}