{
  "type": "Feature",
  "properties": {
    "iso:country": "GB",
    "wof:name": "SW17 9HH",
    "wof:placetype": "postalcode"
  },
  "geometry": {"coordinates":[-0.162065,51.421739],"type":"Point"}
}
