{
  "type": "Feature",
  "properties": {
    "iso:country":"GB",
    "wof:name":"SW17 9HH",
    "wof:placetype":"postalcode"
},
  "geometry": {"coordinates":[-0.1620647967601,51.42173854351529],"type":"Point"}
}