{
  "type": "Feature",
  "properties": {
    "date:inception_lower": "1980-01-01",
    "date:inception_upper": "1980-01-01",
    "iso:country": "GB",
    "wof:name": "N7 7RT",
    "wof:placetype": "postalcode"
  },
  "geometry": {"coordinates":[-0.114128,51.563051],"type":"Point"}
}
