{
  "type": "Feature",
  "properties": {
    "iso:country":"GB",
    "wof:name":"N7 7RT",
    "wof:placetype":"postalcode"
},
  "geometry": {"coordinates":[-0.11412792754119,51.56305055130407],"type":"Point"}
}