{
  "type": "Feature",
  "properties": {
    "iso:country":"GB",
    "wof:name":"BH15 3EE",
    "wof:placetype":"postalcode"
},
  "geometry": {"coordinates":[-1.98382150784912,50.7370340156092],"type":"Point"}
}