{
  "type": "Feature",
  "properties": {
    "date:inception_lower":"1980-01-01",
    "date:inception_upper":"1980-01-31",
    "iso:country":"GB",
    "wof:name":"SK17 8NZ",
    "wof:placetype":"postalcode"
},
  "geometry": {"coordinates":[-1.76934,53.280466],"type":"Point"}
}