{
  "type": "Feature",
  "properties": {
    "iso:country":"GB",
    "wof:name":"EX5 1JZ",
    "wof:placetype":"postalcode"
},
  "geometry": {"coordinates":[-3.40919238814642,50.67608574169967],"type":"Point"}
}