{
  "type": "Feature",
  "properties": {
    "iso:country":"GB",
    "wof:name":"OL16 5DH",
    "wof:placetype":"postalcode"
},
  "geometry": {"coordinates":[-2.14331805552667,53.61361661140825],"type":"Point"}
}