{
  "type": "Feature",
  "properties": {
    "iso:country": "GB",
    "wof:name": "OL16 5DH",
    "wof:placetype": "postalcode"
  },
  "geometry": {"coordinates":[-2.143318,53.613617],"type":"Point"}
}
