{
  "type": "Feature",
  "properties": {
    "iso:country":"GB",
    "wof:name":"LU2 9JX",
    "wof:placetype":"postalcode"
},
  "geometry": {"coordinates":[-0.38229263847973,51.88839897383166],"type":"Point"}
}