{
  "type": "Feature",
  "properties": {
    "date:inception_lower":"1980-01-01",
    "date:inception_upper":"1980-01-31",
    "iso:country":"GB",
    "wof:name":"DN32 0BZ",
    "wof:placetype":"postalcode"
},
  "geometry": {"coordinates":[-0.083565,53.550876],"type":"Point"}
}