{
  "type": "Feature",
  "properties": {
    "iso:country":"GB",
    "wof:name":"DN32 0BZ",
    "wof:placetype":"postalcode"
},
  "geometry": {"coordinates":[-0.08356488402342,53.55087623620644],"type":"Point"}
}