{
  "type": "Feature",
  "properties": {
    "iso:country":"GB",
    "wof:name":"NG5 1JZ",
    "wof:placetype":"postalcode"
},
  "geometry": {"coordinates":[-1.17139488284551,52.98236261640078],"type":"Point"}
}