{
  "type": "Feature",
  "properties": {
    "iso:country":"GB",
    "wof:name":"W1H 2PY",
    "wof:placetype":"postalcode"
},
  "geometry": {"coordinates":[-0.16181132468722,51.51904286219418],"type":"Point"}
}