{
  "type": "Feature",
  "properties": {
    "date:inception_lower": "1980-01-01",
    "date:inception_upper": "1980-01-01",
    "iso:country": "GB",
    "wof:name": "LL63 5YT",
    "wof:placetype": "postalcode"
  },
  "geometry": {"coordinates":[-4.469845,53.200009],"type":"Point"}
}
