{
  "type": "Feature",
  "properties": {
    "iso:country":"GB",
    "wof:name":"TR2 5SW",
    "wof:placetype":"postalcode"
},
  "geometry": {"coordinates":[-4.86412574907315,50.26368222023066],"type":"Point"}
}