{
  "type": "Feature",
  "properties": {
    "iso:country": "GB",
    "wof:name": "TR2 5SW",
    "wof:placetype": "postalcode"
  },
  "geometry": {"coordinates":[-4.864126,50.263682],"type":"Point"}
}
