{
  "type": "Feature",
  "properties": {
    "iso:country":"GB",
    "wof:name":"IP22 1BH",
    "wof:placetype":"postalcode"
},
  "geometry": {"coordinates":[1.00812638936919,52.34379506374408],"type":"Point"}
}