{
  "type": "Feature",
  "properties": {
    "iso:country": "GB",
    "wof:name": "NE66 1LY",
    "wof:placetype": "postalcode"
  },
  "geometry": {"coordinates":[-1.709579,55.415749],"type":"Point"}
}
