{
  "type": "Feature",
  "properties": {
    "iso:country":"GB",
    "wof:name":"NE66 1LY",
    "wof:placetype":"postalcode"
},
  "geometry": {"coordinates":[-1.70957856558521,55.41574936577034],"type":"Point"}
}