{
  "type": "Feature",
  "properties": {
    "date:inception_lower": "1994-12-01",
    "date:inception_upper": "1994-12-01",
    "iso:country": "GB",
    "wof:name": "NE66 1LY",
    "wof:placetype": "postalcode"
  },
  "geometry": {"coordinates":[-1.709579,55.415749],"type":"Point"}
}
