{
  "type": "Feature",
  "properties": {
    "date:inception_lower": "1980-01-01",
    "date:inception_upper": "1980-01-01",
    "iso:country": "GB",
    "wof:name": "GL54 4DE",
    "wof:placetype": "postalcode"
  },
  "geometry": {"coordinates":[-1.929115,51.835452],"type":"Point"}
}
