{
  "type": "Feature",
  "properties": {
    "iso:country": "GB",
    "wof:name": "WA16 7QJ",
    "wof:placetype": "postalcode"
  },
  "geometry": {"coordinates":[-2.333574,53.329136],"type":"Point"}
}
