{
  "type": "Feature",
  "properties": {
    "iso:country": "GB",
    "wof:name": "GL15 6UY",
    "wof:placetype": "postalcode"
  },
  "geometry": {"coordinates":[-2.659861,51.720287],"type":"Point"}
}
