{
  "type": "Feature",
  "properties": {
    "iso:country":"GB",
    "wof:name":"B78 1LD",
    "wof:placetype":"postalcode"
},
  "geometry": {"coordinates":[-1.61563935350212,52.61372893075369],"type":"Point"}
}