{
  "type": "Feature",
  "properties": {
    "iso:country": "GB",
    "wof:name": "N1 0TP",
    "wof:placetype": "postalcode"
  },
  "geometry": {"coordinates":[-0.113935,51.535971],"type":"Point"}
}
