{
  "type": "Feature",
  "properties": {
    "iso:country":"GB",
    "wof:name":"CF72 9HH",
    "wof:placetype":"postalcode"
},
  "geometry": {"coordinates":[-3.40262048706181,51.51256314892576],"type":"Point"}
}