{
  "type": "Feature",
  "properties": {
    "iso:country":"GB",
    "wof:name":"E1 2QA",
    "wof:placetype":"postalcode"
},
  "geometry": {"coordinates":[-0.05534884910011,51.51365708633734],"type":"Point"}
}