{
  "type": "Feature",
  "properties": {
    "iso:country":"GB",
    "wof:name":"NE62 5AN",
    "wof:placetype":"postalcode"
},
  "geometry": {"coordinates":[-1.58917562966684,55.16608443923042],"type":"Point"}
}