{
  "type": "Feature",
  "properties": {
    "iso:country":"GB",
    "wof:name":"GL54 5LL",
    "wof:placetype":"postalcode"
},
  "geometry": {"coordinates":[-1.96527914496849,51.9526904676195],"type":"Point"}
}