{
  "type": "Feature",
  "properties": {
    "date:inception_lower":"1980-01-01",
    "date:inception_upper":"1980-01-31",
    "iso:country":"GB",
    "wof:name":"GL54 5LL",
    "wof:placetype":"postalcode"
},
  "geometry": {"coordinates":[-1.965279,51.95269],"type":"Point"}
}