{
  "type": "Feature",
  "properties": {
    "date:inception_lower": "1980-01-01",
    "date:inception_upper": "1980-01-01",
    "iso:country": "GB",
    "wof:name": "CO10 0DY",
    "wof:placetype": "postalcode"
  },
  "geometry": {"coordinates":[0.757967,52.03402],"type":"Point"}
}
