{
  "type": "Feature",
  "properties": {
    "date:inception_lower": "1980-01-01",
    "date:inception_upper": "1980-01-01",
    "iso:country": "GB",
    "wof:name": "LL51 9YT",
    "wof:placetype": "postalcode"
  },
  "geometry": {"coordinates":[-4.182742,52.949636],"type":"Point"}
}
