{
  "type": "Feature",
  "properties": {
    "iso:country": "GB",
    "wof:name": "LL51 9YT",
    "wof:placetype": "postalcode"
  },
  "geometry": {"coordinates":[-4.182798,52.951038],"type":"Point"}
}
