{
  "type": "Feature",
  "properties": {
    "iso:country":"GB",
    "wof:name":"B98 0DD",
    "wof:placetype":"postalcode"
},
  "geometry": {"coordinates":[-1.90392101421728,52.29210218321885],"type":"Point"}
}