{
  "type": "Feature",
  "properties": {
    "iso:country": "GB",
    "wof:name": "M24 1NU",
    "wof:placetype": "postalcode"
  },
  "geometry": {"coordinates":[-2.202102,53.534461],"type":"Point"}
}
