{
  "type": "Feature",
  "properties": {
    "iso:country": "GB",
    "wof:name": "LA1 2HT",
    "wof:placetype": "postalcode"
  },
  "geometry": {"coordinates":[-2.801503,54.060939],"type":"Point"}
}
