{
  "type": "Feature",
  "properties": {
    "iso:country":"GB",
    "wof:name":"TW9 2RE",
    "wof:placetype":"postalcode"
},
  "geometry": {"coordinates":[-0.303021174986,51.46437501442592],"type":"Point"}
}