{
  "type": "Feature",
  "properties": {
    "date:inception_lower": "2019-03-01",
    "date:inception_upper": "2019-03-01",
    "iso:country": "GB",
    "wof:name": "CT5 4FP",
    "wof:placetype": "postalcode"
  },
  "geometry": {"coordinates":[1.003019,51.341862],"type":"Point"}
}
