{
  "type": "Feature",
  "properties": {
    "iso:country":"GB",
    "wof:name":"CM2 9NH",
    "wof:placetype":"postalcode"
},
  "geometry": {"coordinates":[0.47611086015975,51.71477283048193],"type":"Point"}
}