{
  "type": "Feature",
  "properties": {
    "iso:country":"GB",
    "wof:name":"NP26 4RS",
    "wof:placetype":"postalcode"
},
  "geometry": {"coordinates":[-2.74112839723407,51.58989428192218],"type":"Point"}
}