{
  "type": "Feature",
  "properties": {
    "iso:country":"GB",
    "wof:name":"W3 6DW",
    "wof:placetype":"postalcode"
},
  "geometry": {"coordinates":[-0.26816464842365,51.50969062837623],"type":"Point"}
}