{
  "type": "Feature",
  "properties": {
    "date:inception_lower":"2004-06-01",
    "date:inception_upper":"2004-06-30",
    "iso:country":"GB",
    "wof:name":"FK4 2FB",
    "wof:placetype":"postalcode"
},
  "geometry": {"coordinates":[-3.889801,55.99041],"type":"Point"}
}