{
  "type": "Feature",
  "properties": {
    "iso:country": "GB",
    "wof:name": "FK4 2FB",
    "wof:placetype": "postalcode"
  },
  "geometry": {"coordinates":[-3.889801,55.99041],"type":"Point"}
}
