{
  "type": "Feature",
  "properties": {
    "date:inception_lower": "2009-06-01",
    "date:inception_upper": "2009-06-01",
    "iso:country": "GB",
    "wof:name": "LE65 1RG",
    "wof:placetype": "postalcode"
  },
  "geometry": {"coordinates":[-1.469148,52.789838],"type":"Point"}
}
