{
  "type": "Feature",
  "properties": {
    "iso:country":"GB",
    "wof:name":"LE65 1RG",
    "wof:placetype":"postalcode"
},
  "geometry": {"coordinates":[-1.47023974185179,52.78968144589679],"type":"Point"}
}