{
  "type": "Feature",
  "properties": {
    "iso:country":"GB",
    "wof:name":"SA3 1HA",
    "wof:placetype":"postalcode"
},
  "geometry": {"coordinates":[-4.18403517942363,51.60550410075744],"type":"Point"}
}