{
  "type": "Feature",
  "properties": {
    "iso:country": "GB",
    "wof:name": "SA3 1HA",
    "wof:placetype": "postalcode"
  },
  "geometry": {"coordinates":[-4.184267,51.605518],"type":"Point"}
}
