{
  "type": "Feature",
  "properties": {
    "date:inception_lower": "1980-01-01",
    "date:inception_upper": "1980-01-01",
    "iso:country": "GB",
    "wof:name": "SA3 1HA",
    "wof:placetype": "postalcode"
  },
  "geometry": {"coordinates":[-4.184267,51.605518],"type":"Point"}
}
