{
  "type": "Feature",
  "properties": {
    "date:inception_lower": "1980-01-01",
    "date:inception_upper": "1980-01-01",
    "iso:country": "GB",
    "wof:name": "PO12 3SR",
    "wof:placetype": "postalcode"
  },
  "geometry": {"coordinates":[-1.153657,50.793048],"type":"Point"}
}
