{
  "type": "Feature",
  "properties": {
    "iso:country": "GB",
    "wof:name": "CV11 4ND",
    "wof:placetype": "postalcode"
  },
  "geometry": {"coordinates":[-1.46231,52.513335],"type":"Point"}
}
