{
  "type": "Feature",
  "properties": {
    "date:inception_lower":"1996-12-01",
    "date:inception_upper":"1996-12-31",
    "iso:country":"GB",
    "wof:name":"CV11 4ND",
    "wof:placetype":"postalcode"
},
  "geometry": {"coordinates":[-1.46231,52.513335],"type":"Point"}
}