{
  "type": "Feature",
  "properties": {
    "iso:country":"GB",
    "wof:name":"L36 9YU",
    "wof:placetype":"postalcode"
},
  "geometry": {"coordinates":[-2.83998086470962,53.41048566451472],"type":"Point"}
}