{
  "type": "Feature",
  "properties": {
    "iso:country": "GB",
    "wof:name": "BA11 3BB",
    "wof:placetype": "postalcode"
  },
  "geometry": {"coordinates":[-2.32889,51.231812],"type":"Point"}
}
