{
  "type": "Feature",
  "properties": {
    "iso:country":"GB",
    "wof:name":"OX33 1DX",
    "wof:placetype":"postalcode"
},
  "geometry": {"coordinates":[-1.15673752311046,51.76735541330942],"type":"Point"}
}