{
  "type": "Feature",
  "properties": {
    "iso:country":"GB",
    "wof:name":"LA3 3AR",
    "wof:placetype":"postalcode"
},
  "geometry": {"coordinates":[-2.83757755827179,54.06470048684507],"type":"Point"}
}