{
  "type": "Feature",
  "properties": {
    "iso:country":"GB",
    "wof:name":"SK13 8PL",
    "wof:placetype":"postalcode"
},
  "geometry": {"coordinates":[-1.93112928045582,53.44344345286235],"type":"Point"}
}