{
  "type": "Feature",
  "properties": {
    "iso:country": "GB",
    "wof:name": "SK13 8PL",
    "wof:placetype": "postalcode"
  },
  "geometry": {"coordinates":[-1.931129,53.443443],"type":"Point"}
}
