{
  "type": "Feature",
  "properties": {
    "date:inception_lower": "1980-01-01",
    "date:inception_upper": "1980-01-01",
    "iso:country": "GB",
    "wof:name": "L35 7JA",
    "wof:placetype": "postalcode"
  },
  "geometry": {"coordinates":[-2.789751,53.426802],"type":"Point"}
}
