{
  "type": "Feature",
  "properties": {
    "iso:country": "GB",
    "wof:name": "L35 7JA",
    "wof:placetype": "postalcode"
  },
  "geometry": {"coordinates":[-2.789751,53.426802],"type":"Point"}
}
