{
  "type": "Feature",
  "properties": {
    "iso:country": "GB",
    "wof:name": "DY13 0RZ",
    "wof:placetype": "postalcode"
  },
  "geometry": {"coordinates":[-2.278022,52.30733],"type":"Point"}
}
