{
  "type": "Feature",
  "properties": {
    "iso:country":"GB",
    "wof:name":"LN1 3BA",
    "wof:placetype":"postalcode"
},
  "geometry": {"coordinates":[-0.53870403247161,53.23721775817563],"type":"Point"}
}