{
  "type": "Feature",
  "properties": {
    "iso:country": "GB",
    "wof:name": "LN1 3BA",
    "wof:placetype": "postalcode"
  },
  "geometry": {"coordinates":[-0.538704,53.237218],"type":"Point"}
}
