{
  "type": "Feature",
  "properties": {
    "iso:country":"GB",
    "wof:name":"G69 0DX",
    "wof:placetype":"postalcode"
},
  "geometry": {"coordinates":[-4.08717306485409,55.91222967810018],"type":"Point"}
}