{
  "type": "Feature",
  "properties": {
    "iso:country":"GB",
    "wof:name":"PH13 9ND",
    "wof:placetype":"postalcode"
},
  "geometry": {"coordinates":[-3.32101993997021,56.52064064474618],"type":"Point"}
}