{
  "type": "Feature",
  "properties": {
    "iso:country":"GB",
    "wof:name":"HA5 2EY",
    "wof:placetype":"postalcode"
},
  "geometry": {"coordinates":[-0.40092196911194,51.58929499624525],"type":"Point"}
}