{
  "type": "Feature",
  "properties": {
    "iso:country":"GB",
    "wof:name":"B73 5HN",
    "wof:placetype":"postalcode"
},
  "geometry": {"coordinates":[-1.83390486895085,52.53683316645778],"type":"Point"}
}