{
  "type": "Feature",
  "properties": {
    "iso:country":"GB",
    "wof:name":"BS37 8SB",
    "wof:placetype":"postalcode"
},
  "geometry": {"coordinates":[-2.42997648488606,51.52910955480504],"type":"Point"}
}