{
  "type": "Feature",
  "properties": {
    "iso:country":"GB",
    "wof:name":"PA14 5RT",
    "wof:placetype":"postalcode"
},
  "geometry": {"coordinates":[-4.67138382894599,55.9277669389573],"type":"Point"}
}