{
  "type": "Feature",
  "properties": {
    "date:inception_lower": "1980-01-01",
    "date:inception_upper": "1980-01-01",
    "iso:country": "GB",
    "wof:name": "PA14 5RT",
    "wof:placetype": "postalcode"
  },
  "geometry": {"coordinates":[-4.671317,55.927762],"type":"Point"}
}
