{
  "type": "Feature",
  "properties": {
    "date:inception_lower": "1994-05-01",
    "date:inception_upper": "1994-05-01",
    "iso:country": "GB",
    "wof:name": "SL4 2LD",
    "wof:placetype": "postalcode"
  },
  "geometry": {"coordinates":[-0.637029,51.459338],"type":"Point"}
}
