{
  "type": "Feature",
  "properties": {
    "iso:country":"GB",
    "wof:name":"SL4 2LD",
    "wof:placetype":"postalcode"
},
  "geometry": {"coordinates":[-0.63590585042661,51.4589275957786],"type":"Point"}
}