{
  "type": "Feature",
  "properties": {
    "iso:country": "GB",
    "wof:name": "SL4 2LD",
    "wof:placetype": "postalcode"
  },
  "geometry": {"coordinates":[-0.635906,51.458928],"type":"Point"}
}
