{
  "type": "Feature",
  "properties": {
    "iso:country":"GB",
    "wof:name":"M40 8PL",
    "wof:placetype":"postalcode"
},
  "geometry": {"coordinates":[-2.21128173768202,53.49942681244221],"type":"Point"}
}