{
  "type": "Feature",
  "properties": {
    "iso:country": "GB",
    "wof:name": "GL2 9FP",
    "wof:placetype": "postalcode"
  },
  "geometry": {"coordinates":[-2.226653,51.88392],"type":"Point"}
}
