{
  "type": "Feature",
  "properties": {
    "date:inception_lower": "2016-07-01",
    "date:inception_upper": "2016-07-01",
    "iso:country": "GB",
    "wof:name": "GL2 9FP",
    "wof:placetype": "postalcode"
  },
  "geometry": {"coordinates":[-2.226683,51.88401],"type":"Point"}
}
