{
  "type": "Feature",
  "properties": {
    "iso:country": "GB",
    "wof:name": "DA1 4FA",
    "wof:placetype": "postalcode"
  },
  "geometry": {"coordinates":[0.188847,51.452068],"type":"Point"}
}
