{
  "type": "Feature",
  "properties": {
    "iso:country":"GB",
    "wof:name":"DA1 4FA",
    "wof:placetype":"postalcode"
},
  "geometry": {"coordinates":[0.18884649718735,51.45206845800057],"type":"Point"}
}