{
  "type": "Feature",
  "properties": {
    "date:inception_lower": "2012-02-01",
    "date:inception_upper": "2012-02-01",
    "iso:country": "GB",
    "wof:name": "DA1 4FA",
    "wof:placetype": "postalcode"
  },
  "geometry": {"coordinates":[0.188847,51.452068],"type":"Point"}
}
