{
  "type": "Feature",
  "properties": {
    "iso:country":"GB",
    "wof:name":"TF8 7LA",
    "wof:placetype":"postalcode"
},
  "geometry": {"coordinates":[-2.47163474849374,52.62211386701321],"type":"Point"}
}