{
  "type": "Feature",
  "properties": {
    "iso:country": "GB",
    "wof:name": "TF8 7LA",
    "wof:placetype": "postalcode"
  },
  "geometry": {"coordinates":[-2.471635,52.622114],"type":"Point"}
}
