{
  "type": "Feature",
  "properties": {
    "iso:country":"GB",
    "wof:name":"BS34 6PJ",
    "wof:placetype":"postalcode"
},
  "geometry": {"coordinates":[-2.56794830727606,51.52922381171724],"type":"Point"}
}