{
  "type": "Feature",
  "properties": {
    "iso:country":"GB",
    "wof:name":"RH12 4YL",
    "wof:placetype":"postalcode"
},
  "geometry": {"coordinates":[-0.30452620319438,51.07543681857423],"type":"Point"}
}