{
  "type": "Feature",
  "properties": {
    "date:inception_lower":"1990-02-01",
    "date:inception_upper":"1990-02-28",
    "iso:country":"GB",
    "wof:name":"RH12 4YL",
    "wof:placetype":"postalcode"
},
  "geometry": {"coordinates":[-0.304484,51.075478],"type":"Point"}
}