{
  "type": "Feature",
  "properties": {
    "iso:country":"GB",
    "wof:name":"M25 0LR",
    "wof:placetype":"postalcode"
},
  "geometry": {"coordinates":[-2.26836961082832,53.51834963170734],"type":"Point"}
}