{
  "type": "Feature",
  "properties": {
    "date:inception_lower": "1994-05-01",
    "date:inception_upper": "1994-05-01",
    "iso:country": "GB",
    "wof:name": "M25 0LR",
    "wof:placetype": "postalcode"
  },
  "geometry": {"coordinates":[-2.26837,53.51835],"type":"Point"}
}
