{
  "type": "Feature",
  "properties": {
    "date:inception_lower": "1980-01-01",
    "date:inception_upper": "1980-01-01",
    "iso:country": "GB",
    "wof:name": "TN14 7EU",
    "wof:placetype": "postalcode"
  },
  "geometry": {"coordinates":[0.133937,51.328537],"type":"Point"}
}
