{
  "type": "Feature",
  "properties": {
    "iso:country":"GB",
    "wof:name":"SA16 0AP",
    "wof:placetype":"postalcode"
},
  "geometry": {"coordinates":[-4.25683506025205,51.68401876954953],"type":"Point"}
}