{
  "type": "Feature",
  "properties": {
    "date:inception_lower": "2023-02-01",
    "date:inception_upper": "2023-02-01",
    "iso:country": "GB",
    "wof:name": "GL10 3FU",
    "wof:placetype": "postalcode"
  },
  "geometry": {"coordinates":[-2.307678,51.755774],"type":"Point"}
}
