{
  "type": "Feature",
  "properties": {
    "date:inception_lower": "1980-01-01",
    "date:inception_upper": "1980-01-01",
    "iso:country": "GB",
    "wof:name": "EH30 9TR",
    "wof:placetype": "postalcode"
  },
  "geometry": {"coordinates":[-3.316004,55.97294],"type":"Point"}
}
