{
  "type": "Feature",
  "properties": {
    "date:inception_lower": "2010-07-01",
    "date:inception_upper": "2010-07-01",
    "iso:country": "GB",
    "wof:name": "SP2 8BY",
    "wof:placetype": "postalcode"
  },
  "geometry": {"coordinates":[-1.788521,51.054033],"type":"Point"}
}
