{
  "type": "Feature",
  "properties": {
    "iso:country":"GB",
    "wof:name":"SP2 8BY",
    "wof:placetype":"postalcode"
},
  "geometry": {"coordinates":[-1.78852144854965,51.0540331570967],"type":"Point"}
}