{
  "type": "Feature",
  "properties": {
    "iso:country": "GB",
    "wof:name": "B21 0EP",
    "wof:placetype": "postalcode"
  },
  "geometry": {"coordinates":[-1.952061,52.504963],"type":"Point"}
}
