{
  "type": "Feature",
  "properties": {
    "iso:country":"GB",
    "wof:name":"EH4 7TE",
    "wof:placetype":"postalcode"
},
  "geometry": {"coordinates":[-3.26715679674771,55.95700516284573],"type":"Point"}
}