{
  "type": "Feature",
  "properties": {
    "iso:country": "GB",
    "wof:name": "EH4 7TE",
    "wof:placetype": "postalcode"
  },
  "geometry": {"coordinates":[-3.267156,55.957],"type":"Point"}
}
