{
  "type": "Feature",
  "properties": {
    "iso:country":"GB",
    "wof:name":"BR6 8AP",
    "wof:placetype":"postalcode"
},
  "geometry": {"coordinates":[0.08124089262552,51.37224693417095],"type":"Point"}
}