{
  "type": "Feature",
  "properties": {
    "iso:country": "GB",
    "wof:name": "BR6 8AP",
    "wof:placetype": "postalcode"
  },
  "geometry": {"coordinates":[0.081241,51.372247],"type":"Point"}
}
