{
  "type": "Feature",
  "properties": {
    "date:inception_lower":"1980-01-01",
    "date:inception_upper":"1980-01-31",
    "iso:country":"GB",
    "wof:name":"LL18 2UE",
    "wof:placetype":"postalcode"
},
  "geometry": {"coordinates":[-3.465272,53.292754],"type":"Point"}
}