{
  "type": "Feature",
  "properties": {
    "iso:country": "GB",
    "wof:name": "LL18 2UE",
    "wof:placetype": "postalcode"
  },
  "geometry": {"coordinates":[-3.465272,53.292754],"type":"Point"}
}
