{
  "type": "Feature",
  "properties": {
    "iso:country":"GB",
    "wof:name":"LL18 2UE",
    "wof:placetype":"postalcode"
},
  "geometry": {"coordinates":[-3.46527183735589,53.2927541431092],"type":"Point"}
}