{
  "type": "Feature",
  "properties": {
    "iso:country":"GB",
    "wof:name":"MK16 9BY",
    "wof:placetype":"postalcode"
},
  "geometry": {"coordinates":[-0.71795576126485,52.08444371481311],"type":"Point"}
}