{
  "type": "Feature",
  "properties": {
    "iso:country": "GB",
    "wof:name": "BB10 4DE",
    "wof:placetype": "postalcode"
  },
  "geometry": {"coordinates":[-2.227083,53.786904],"type":"Point"}
}
