{
  "type": "Feature",
  "properties": {
    "iso:country":"GB",
    "wof:name":"TN31 7RZ",
    "wof:placetype":"postalcode"
},
  "geometry": {"coordinates":[0.79851458652724,50.9354803508269],"type":"Point"}
}