{
  "type": "Feature",
  "properties": {
    "iso:country":"GB",
    "wof:name":"B77 3JG",
    "wof:placetype":"postalcode"
},
  "geometry": {"coordinates":[-1.66889847404148,52.63303786488878],"type":"Point"}
}