{
  "type": "Feature",
  "properties": {
    "iso:country":"GB",
    "wof:name":"GL2 2BX",
    "wof:placetype":"postalcode"
},
  "geometry": {"coordinates":[-2.26942522193229,51.82498577440978],"type":"Point"}
}