{
  "type": "Feature",
  "properties": {
    "date:inception_lower":"2006-07-01",
    "date:inception_upper":"2006-07-31",
    "iso:country":"GB",
    "wof:name":"GL2 2BX",
    "wof:placetype":"postalcode"
},
  "geometry": {"coordinates":[-2.269425,51.824986],"type":"Point"}
}