{
  "type": "Feature",
  "properties": {
    "iso:country":"GB",
    "wof:name":"BH23 4RD",
    "wof:placetype":"postalcode"
},
  "geometry": {"coordinates":[-1.71503291117279,50.74577015418438],"type":"Point"}
}