{
  "type": "Feature",
  "properties": {
    "iso:country":"GB",
    "wof:name":"B77 4NQ",
    "wof:placetype":"postalcode"
},
  "geometry": {"coordinates":[-1.65801590774349,52.63024712052984],"type":"Point"}
}