{
  "type": "Feature",
  "properties": {
    "date:inception_lower":"1980-01-01",
    "date:inception_upper":"1980-01-31",
    "iso:country":"GB",
    "wof:name":"ME19 5EW",
    "wof:placetype":"postalcode"
},
  "geometry": {"coordinates":[0.36634,51.325725],"type":"Point"}
}