{
  "type": "Feature",
  "properties": {
    "iso:country":"GB",
    "wof:name":"ME19 5EW",
    "wof:placetype":"postalcode"
},
  "geometry": {"coordinates":[0.36633997715805,51.32572545783416],"type":"Point"}
}