{
  "type": "Feature",
  "properties": {
    "iso:country": "GB",
    "wof:name": "ME19 5EW",
    "wof:placetype": "postalcode"
  },
  "geometry": {"coordinates":[0.36634,51.325725],"type":"Point"}
}
