{
  "type": "Feature",
  "properties": {
    "iso:country": "GB",
    "wof:name": "IP20 9BA",
    "wof:placetype": "postalcode"
  },
  "geometry": {"coordinates":[1.301381,52.403134],"type":"Point"}
}
