{
  "type": "Feature",
  "properties": {
    "date:inception_lower": "1980-01-01",
    "date:inception_upper": "1980-01-01",
    "iso:country": "GB",
    "wof:name": "IP20 9BA",
    "wof:placetype": "postalcode"
  },
  "geometry": {"coordinates":[1.301381,52.403134],"type":"Point"}
}
