{
  "type": "Feature",
  "properties": {
    "iso:country":"GB",
    "wof:name":"CA28 7NP",
    "wof:placetype":"postalcode"
},
  "geometry": {"coordinates":[-3.58545315705804,54.548762154173],"type":"Point"}
}