{
  "type": "Feature",
  "properties": {
    "iso:country": "GB",
    "wof:name": "RG12 8GS",
    "wof:placetype": "postalcode"
  },
  "geometry": {"coordinates":[-0.77888,51.405473],"type":"Point"}
}
