{
  "type": "Feature",
  "properties": {
    "iso:country":"GB",
    "wof:name":"RM14 2EN",
    "wof:placetype":"postalcode"
},
  "geometry": {"coordinates":[0.24581169988133,51.54664050785654],"type":"Point"}
}