{
  "type": "Feature",
  "properties": {
    "date:inception_lower": "1980-01-01",
    "date:inception_upper": "1980-01-01",
    "iso:country": "GB",
    "wof:name": "RM14 2EN",
    "wof:placetype": "postalcode"
  },
  "geometry": {"coordinates":[0.245812,51.546641],"type":"Point"}
}
