{
  "type": "Feature",
  "properties": {
    "iso:country": "GB",
    "wof:name": "EH43 6BA",
    "wof:placetype": "postalcode"
  },
  "geometry": {"coordinates":[-3.02303,55.625552],"type":"Point"}
}
