{
  "type": "Feature",
  "properties": {
    "date:inception_lower": "1980-01-01",
    "date:inception_upper": "1980-01-01",
    "iso:country": "GB",
    "wof:name": "EH43 6BA",
    "wof:placetype": "postalcode"
  },
  "geometry": {"coordinates":[-3.02303,55.625552],"type":"Point"}
}
