{
  "type": "Feature",
  "properties": {
    "iso:country":"GB",
    "wof:name":"EH43 6BA",
    "wof:placetype":"postalcode"
},
  "geometry": {"coordinates":[-3.02302974414797,55.62555218978642],"type":"Point"}
}