{
  "type": "Feature",
  "properties": {
    "iso:country": "GB",
    "wof:name": "EH33 2PT",
    "wof:placetype": "postalcode"
  },
  "geometry": {"coordinates":[-2.940902,55.938166],"type":"Point"}
}
