{
  "type": "Feature",
  "properties": {
    "iso:country": "GB",
    "wof:name": "SW8 4BX",
    "wof:placetype": "postalcode"
  },
  "geometry": {"coordinates":[-0.145997,51.477213],"type":"Point"}
}
