{
  "type": "Feature",
  "properties": {
    "iso:country":"GB",
    "wof:name":"SE18 4PW",
    "wof:placetype":"postalcode"
},
  "geometry": {"coordinates":[0.04669292608307,51.47510436804244],"type":"Point"}
}