{
  "type": "Feature",
  "properties": {
    "date:inception_lower":"2002-05-01",
    "date:inception_upper":"2002-05-31",
    "iso:country":"GB",
    "wof:name":"SE18 4PW",
    "wof:placetype":"postalcode"
},
  "geometry": {"coordinates":[0.046693,51.475104],"type":"Point"}
}