{
  "type": "Feature",
  "properties": {
    "iso:country": "GB",
    "wof:name": "EH4 1RN",
    "wof:placetype": "postalcode"
  },
  "geometry": {"coordinates":[-3.222754,55.956394],"type":"Point"}
}
