{
  "type": "Feature",
  "properties": {
    "iso:country":"GB",
    "wof:name":"FK10 2EN",
    "wof:placetype":"postalcode"
},
  "geometry": {"coordinates":[-3.81642027538292,56.126335008268],"type":"Point"}
}