{
  "type": "Feature",
  "properties": {
    "date:inception_lower": "1980-01-01",
    "date:inception_upper": "1980-01-01",
    "iso:country": "GB",
    "wof:name": "SS16 5EW",
    "wof:placetype": "postalcode"
  },
  "geometry": {"coordinates":[0.459946,51.560835],"type":"Point"}
}
