{
  "type": "Feature",
  "properties": {
    "iso:country":"GB",
    "wof:name":"SS16 5EW",
    "wof:placetype":"postalcode"
},
  "geometry": {"coordinates":[0.45994630682018,51.56083503211934],"type":"Point"}
}