{
  "type": "Feature",
  "properties": {
    "iso:country": "GB",
    "wof:name": "TN12 6SA",
    "wof:placetype": "postalcode"
  },
  "geometry": {"coordinates":[0.357427,51.184285],"type":"Point"}
}
