{
  "type": "Feature",
  "properties": {
    "date:inception_lower":"1997-06-01",
    "date:inception_upper":"1997-06-30",
    "iso:country":"GB",
    "wof:name":"TN12 6SA",
    "wof:placetype":"postalcode"
},
  "geometry": {"coordinates":[0.357427,51.184285],"type":"Point"}
}