{
  "type": "Feature",
  "properties": {
    "iso:country":"GB",
    "wof:name":"G31 1RN",
    "wof:placetype":"postalcode"
},
  "geometry": {"coordinates":[-4.22070586361995,55.85766775714656],"type":"Point"}
}