{
  "type": "Feature",
  "properties": {
    "date:inception_lower": "1980-01-01",
    "date:inception_upper": "1980-01-01",
    "iso:country": "GB",
    "wof:name": "G31 1RN",
    "wof:placetype": "postalcode"
  },
  "geometry": {"coordinates":[-4.220706,55.857668],"type":"Point"}
}
