{
  "type": "Feature",
  "properties": {
    "iso:country":"GB",
    "wof:name":"SE15 2PX",
    "wof:placetype":"postalcode"
},
  "geometry": {"coordinates":[-0.06288843217175,51.47351288402766],"type":"Point"}
}