{
  "type": "Feature",
  "properties": {
    "date:inception_lower":"2015-02-01",
    "date:inception_upper":"2015-02-28",
    "iso:country":"GB",
    "wof:name":"SN16 0JL",
    "wof:placetype":"postalcode"
},
  "geometry": {"coordinates":[-2.139097,51.604302],"type":"Point"}
}