{
  "type": "Feature",
  "properties": {
    "iso:country":"GB",
    "wof:name":"SN16 0JL",
    "wof:placetype":"postalcode"
},
  "geometry": {"coordinates":[-2.13871320112091,51.60466921629949],"type":"Point"}
}