{
  "type": "Feature",
  "properties": {
    "iso:country":"GB",
    "wof:name":"M30 8QD",
    "wof:placetype":"postalcode"
},
  "geometry": {"coordinates":[-2.3620187575783,53.48025214959743],"type":"Point"}
}