{
  "type": "Feature",
  "properties": {
    "iso:country": "GB",
    "wof:name": "M30 8QD",
    "wof:placetype": "postalcode"
  },
  "geometry": {"coordinates":[-2.362019,53.480252],"type":"Point"}
}
