{
  "type": "Feature",
  "properties": {
    "iso:country":"GB",
    "wof:name":"PE11 4JA",
    "wof:placetype":"postalcode"
},
  "geometry": {"coordinates":[-0.16398204187363,52.86040871371699],"type":"Point"}
}