{
  "type": "Feature",
  "properties": {
    "iso:country": "GB",
    "wof:name": "PE11 4JA",
    "wof:placetype": "postalcode"
  },
  "geometry": {"coordinates":[-0.163968,52.860399],"type":"Point"}
}
