{
  "type": "Feature",
  "properties": {
    "iso:country": "GB",
    "wof:name": "BL3 6LQ",
    "wof:placetype": "postalcode"
  },
  "geometry": {"coordinates":[-2.445793,53.567328],"type":"Point"}
}
