{
  "type": "Feature",
  "properties": {
    "iso:country":"GB",
    "wof:name":"BL3 6LQ",
    "wof:placetype":"postalcode"
},
  "geometry": {"coordinates":[-2.44579274859593,53.56732758661134],"type":"Point"}
}