{
  "type": "Feature",
  "properties": {
    "iso:country":"GB",
    "wof:name":"CT7 9JR",
    "wof:placetype":"postalcode"
},
  "geometry": {"coordinates":[1.29922246323037,51.38026893498625],"type":"Point"}
}