{
  "type": "Feature",
  "properties": {
    "iso:country":"GB",
    "wof:name":"CT15 4BL",
    "wof:placetype":"postalcode"
},
  "geometry": {"coordinates":[1.273702362927,51.19696600348853],"type":"Point"}
}