{
  "type": "Feature",
  "properties": {
    "iso:country":"GB",
    "wof:name":"CA8 7EP",
    "wof:placetype":"postalcode"
},
  "geometry": {"coordinates":[-2.5668004740082,54.99357825635832],"type":"Point"}
}