{
  "type": "Feature",
  "properties": {
    "iso:country":"GB",
    "wof:name":"SR6 9AE",
    "wof:placetype":"postalcode"
},
  "geometry": {"coordinates":[-1.38350276914188,54.92897860477039],"type":"Point"}
}