{
  "type": "Feature",
  "properties": {
    "date:inception_lower": "1994-05-01",
    "date:inception_upper": "1994-05-01",
    "iso:country": "GB",
    "wof:name": "M26 3UB",
    "wof:placetype": "postalcode"
  },
  "geometry": {"coordinates":[-2.34826,53.560955],"type":"Point"}
}
