{
  "type": "Feature",
  "properties": {
    "iso:country": "GB",
    "wof:name": "CV23 0SJ",
    "wof:placetype": "postalcode"
  },
  "geometry": {"coordinates":[-1.27095,52.459306],"type":"Point"}
}
