{
  "type": "Feature",
  "properties": {
    "iso:country":"GB",
    "wof:name":"CV23 0SJ",
    "wof:placetype":"postalcode"
},
  "geometry": {"coordinates":[-1.27094956118221,52.45930578811182],"type":"Point"}
}