{
  "type": "Feature",
  "properties": {
    "date:inception_lower":"1980-01-01",
    "date:inception_upper":"1980-01-31",
    "iso:country":"GB",
    "wof:name":"CV23 0SJ",
    "wof:placetype":"postalcode"
},
  "geometry": {"coordinates":[-1.27095,52.459306],"type":"Point"}
}