{
  "type": "Feature",
  "properties": {
    "date:inception_lower":"1980-01-01",
    "date:inception_upper":"1980-01-31",
    "iso:country":"GB",
    "wof:name":"SR6 9NL",
    "wof:placetype":"postalcode"
},
  "geometry": {"coordinates":[-1.369454,54.928269],"type":"Point"}
}