{
  "type": "Feature",
  "properties": {
    "iso:country": "GB",
    "wof:name": "RG45 6HE",
    "wof:placetype": "postalcode"
  },
  "geometry": {"coordinates":[-0.806256,51.371791],"type":"Point"}
}
