{
  "type": "Feature",
  "properties": {
    "iso:country": "GB",
    "wof:name": "NG34 0UE",
    "wof:placetype": "postalcode"
  },
  "geometry": {"coordinates":[-0.414645,52.890263],"type":"Point"}
}
