{
  "type": "Feature",
  "properties": {
    "date:inception_lower": "1999-12-01",
    "date:inception_upper": "1999-12-01",
    "iso:country": "GB",
    "wof:name": "NG34 0UE",
    "wof:placetype": "postalcode"
  },
  "geometry": {"coordinates":[-0.414645,52.890263],"type":"Point"}
}
