{
  "type": "Feature",
  "properties": {
    "iso:country":"GB",
    "wof:name":"LA12 8HQ",
    "wof:placetype":"postalcode"
},
  "geometry": {"coordinates":[-3.036908975297,54.27452337919303],"type":"Point"}
}