{
  "type": "Feature",
  "properties": {
    "date:inception_lower":"1980-01-01",
    "date:inception_upper":"1980-01-31",
    "iso:country":"GB",
    "wof:name":"LA12 8HQ",
    "wof:placetype":"postalcode"
},
  "geometry": {"coordinates":[-3.036985,54.274496],"type":"Point"}
}