{
  "type": "Feature",
  "properties": {
    "iso:country":"GB",
    "wof:name":"M6 5TY",
    "wof:placetype":"postalcode"
},
  "geometry": {"coordinates":[-2.2989200793892,53.48337497766727],"type":"Point"}
}