{
  "type": "Feature",
  "properties": {
    "date:inception_lower": "1994-05-01",
    "date:inception_upper": "1994-05-01",
    "iso:country": "GB",
    "wof:name": "M6 5TY",
    "wof:placetype": "postalcode"
  },
  "geometry": {"coordinates":[-2.29892,53.483375],"type":"Point"}
}
