{
  "type": "Feature",
  "properties": {
    "iso:country": "GB",
    "wof:name": "M6 5TY",
    "wof:placetype": "postalcode"
  },
  "geometry": {"coordinates":[-2.29892,53.483375],"type":"Point"}
}
