{
  "type": "Feature",
  "properties": {
    "iso:country":"GB",
    "wof:name":"WN7 5EY",
    "wof:placetype":"postalcode"
},
  "geometry": {"coordinates":[-2.53794357746806,53.50548535339756],"type":"Point"}
}