{
  "type": "Feature",
  "properties": {
    "date:inception_lower":"1980-01-01",
    "date:inception_upper":"1980-01-31",
    "iso:country":"GB",
    "wof:name":"WN7 5EY",
    "wof:placetype":"postalcode"
},
  "geometry": {"coordinates":[-2.537944,53.505485],"type":"Point"}
}