{
  "type": "Feature",
  "properties": {
    "date:inception_lower": "1980-01-01",
    "date:inception_upper": "1980-01-01",
    "iso:country": "GB",
    "wof:name": "S12 2UE",
    "wof:placetype": "postalcode"
  },
  "geometry": {"coordinates":[-1.427673,53.35227],"type":"Point"}
}
