{
  "type": "Feature",
  "properties": {
    "iso:country": "GB",
    "wof:name": "S12 2UE",
    "wof:placetype": "postalcode"
  },
  "geometry": {"coordinates":[-1.427673,53.35227],"type":"Point"}
}
