{
  "type": "Feature",
  "properties": {
    "iso:country":"GB",
    "wof:name":"S12 2UE",
    "wof:placetype":"postalcode"
},
  "geometry": {"coordinates":[-1.4279622930852,53.35204618889884],"type":"Point"}
}