{
  "type": "Feature",
  "properties": {
    "date:inception_lower": "1980-01-01",
    "date:inception_upper": "1980-01-01",
    "iso:country": "GB",
    "wof:name": "N17 7ER",
    "wof:placetype": "postalcode"
  },
  "geometry": {"coordinates":[-0.084558,51.599603],"type":"Point"}
}
