{
  "type": "Feature",
  "properties": {
    "iso:country":"GB",
    "wof:name":"NE31 1YR",
    "wof:placetype":"postalcode"
},
  "geometry": {"coordinates":[-1.52776847714424,54.98108900268861],"type":"Point"}
}