{
  "type": "Feature",
  "properties": {
    "iso:country":"GB",
    "wof:name":"BA13 4HX",
    "wof:placetype":"postalcode"
},
  "geometry": {"coordinates":[-2.20236139506459,51.269730426356],"type":"Point"}
}