{
  "type": "Feature",
  "properties": {
    "iso:country": "GB",
    "wof:name": "TN23 6JY",
    "wof:placetype": "postalcode"
  },
  "geometry": {"coordinates":[0.86699,51.133119],"type":"Point"}
}
