{
  "type": "Feature",
  "properties": {
    "date:inception_lower": "1980-01-01",
    "date:inception_upper": "1980-01-01",
    "iso:country": "GB",
    "wof:name": "CM6 1TG",
    "wof:placetype": "postalcode"
  },
  "geometry": {"coordinates":[0.322753,51.861223],"type":"Point"}
}
