{
  "type": "Feature",
  "properties": {
    "iso:country":"GB",
    "wof:name":"CM6 1TG",
    "wof:placetype":"postalcode"
},
  "geometry": {"coordinates":[0.32275302187179,51.86122310778396],"type":"Point"}
}