{
  "type": "Feature",
  "properties": {
    "iso:country":"GB",
    "wof:name":"M38 9HF",
    "wof:placetype":"postalcode"
},
  "geometry": {"coordinates":[-2.42023843946305,53.53622141204005],"type":"Point"}
}