{
  "type": "Feature",
  "properties": {
    "date:inception_lower":"1994-05-01",
    "date:inception_upper":"1994-05-31",
    "iso:country":"GB",
    "wof:name":"M38 9HF",
    "wof:placetype":"postalcode"
},
  "geometry": {"coordinates":[-2.420238,53.536221],"type":"Point"}
}