{
  "type": "Feature",
  "properties": {
    "iso:country": "GB",
    "wof:name": "GU5 0LH",
    "wof:placetype": "postalcode"
  },
  "geometry": {"coordinates":[-0.539994,51.165637],"type":"Point"}
}
