{
  "type": "Feature",
  "properties": {
    "iso:country":"GB",
    "wof:name":"KY11 9PF",
    "wof:placetype":"postalcode"
},
  "geometry": {"coordinates":[-3.36445693262908,56.04013447646105],"type":"Point"}
}