{
  "type": "Feature",
  "properties": {
    "date:inception_lower": "1998-12-01",
    "date:inception_upper": "1998-12-01",
    "iso:country": "GB",
    "wof:name": "KY11 9PF",
    "wof:placetype": "postalcode"
  },
  "geometry": {"coordinates":[-3.364457,56.040134],"type":"Point"}
}
