{
  "type": "Feature",
  "properties": {
    "iso:country":"GB",
    "wof:name":"DA4 9JW",
    "wof:placetype":"postalcode"
},
  "geometry": {"coordinates":[0.24656843146981,51.38704421866571],"type":"Point"}
}