{
  "type": "Feature",
  "properties": {
    "iso:country":"GB",
    "wof:name":"RG6 5XE",
    "wof:placetype":"postalcode"
},
  "geometry": {"coordinates":[-0.9304499042457,51.4293252879325],"type":"Point"}
}