{
  "type": "Feature",
  "properties": {
    "iso:country": "GB",
    "wof:name": "RG6 5XE",
    "wof:placetype": "postalcode"
  },
  "geometry": {"coordinates":[-0.93045,51.429325],"type":"Point"}
}
