{
  "type": "Feature",
  "properties": {
    "iso:country":"GB",
    "wof:name":"WS3 2AT",
    "wof:placetype":"postalcode"
},
  "geometry": {"coordinates":[-1.99422752190641,52.60593705256448],"type":"Point"}
}