{
  "type": "Feature",
  "properties": {
    "iso:country":"GB",
    "wof:name":"WR7 4DE",
    "wof:placetype":"postalcode"
},
  "geometry": {"coordinates":[-2.02955584339356,52.20255778977924],"type":"Point"}
}