{
  "type": "Feature",
  "properties": {
    "date:inception_lower": "1980-01-01",
    "date:inception_upper": "1980-01-01",
    "iso:country": "GB",
    "wof:name": "OX9 3BQ",
    "wof:placetype": "postalcode"
  },
  "geometry": {"coordinates":[-0.97555,51.750056],"type":"Point"}
}
