{
  "type": "Feature",
  "properties": {
    "iso:country":"GB",
    "wof:name":"OX9 3BQ",
    "wof:placetype":"postalcode"
},
  "geometry": {"coordinates":[-0.97554990317169,51.75005558917934],"type":"Point"}
}