{
  "type": "Feature",
  "properties": {
    "iso:country": "GB",
    "wof:name": "SS0 9TE",
    "wof:placetype": "postalcode"
  },
  "geometry": {"coordinates":[0.675383,51.546136],"type":"Point"}
}
