{
  "type": "Feature",
  "properties": {
    "iso:country": "GB",
    "wof:name": "EX16 8HJ",
    "wof:placetype": "postalcode"
  },
  "geometry": {"coordinates":[-3.531757,50.874738],"type":"Point"}
}
