{
  "type": "Feature",
  "properties": {
    "iso:country":"GB",
    "wof:name":"EX16 8HJ",
    "wof:placetype":"postalcode"
},
  "geometry": {"coordinates":[-3.53014038306591,50.87185361154194],"type":"Point"}
}