{
  "type": "Feature",
  "properties": {
    "date:inception_lower": "1980-01-01",
    "date:inception_upper": "1980-01-01",
    "iso:country": "GB",
    "wof:name": "SG12 8PU",
    "wof:placetype": "postalcode"
  },
  "geometry": {"coordinates":[0.033156,51.797918],"type":"Point"}
}
