{
  "type": "Feature",
  "properties": {
    "iso:country":"GB",
    "wof:name":"SG12 8PU",
    "wof:placetype":"postalcode"
},
  "geometry": {"coordinates":[0.03417576231023,51.79829861686351],"type":"Point"}
}