{
  "type": "Feature",
  "properties": {
    "iso:country":"GB",
    "wof:name":"DL9 4PE",
    "wof:placetype":"postalcode"
},
  "geometry": {"coordinates":[-1.69827365331669,54.38802586243018],"type":"Point"}
}