{
  "type": "Feature",
  "properties": {
    "iso:country":"GB",
    "wof:name":"CR5 2NL",
    "wof:placetype":"postalcode"
},
  "geometry": {"coordinates":[-0.13967808452053,51.319102311753],"type":"Point"}
}