{
  "type": "Feature",
  "properties": {
    "date:inception_lower": "1980-01-01",
    "date:inception_upper": "1980-01-01",
    "iso:country": "GB",
    "wof:name": "SL8 5HB",
    "wof:placetype": "postalcode"
  },
  "geometry": {"coordinates":[-0.702333,51.578681],"type":"Point"}
}
