{
  "type": "Feature",
  "properties": {
    "iso:country":"GB",
    "wof:name":"LS6 3QL",
    "wof:placetype":"postalcode"
},
  "geometry": {"coordinates":[-1.59077403701485,53.82696674397948],"type":"Point"}
}