{
  "type": "Feature",
  "properties": {
    "iso:country":"GB",
    "wof:name":"WF3 3EB",
    "wof:placetype":"postalcode"
},
  "geometry": {"coordinates":[-1.53136478735646,53.73765078746245],"type":"Point"}
}