{
  "type": "Feature",
  "properties": {
    "date:inception_lower":"1980-01-01",
    "date:inception_upper":"1980-01-31",
    "iso:country":"GB",
    "wof:name":"WF3 3EB",
    "wof:placetype":"postalcode"
},
  "geometry": {"coordinates":[-1.531365,53.737651],"type":"Point"}
}