{
  "type": "Feature",
  "properties": {
    "iso:country":"GB",
    "wof:name":"TW7 7JE",
    "wof:placetype":"postalcode"
},
  "geometry": {"coordinates":[-0.32831192805869,51.46132121899785],"type":"Point"}
}