{
  "type": "Feature",
  "properties": {
    "iso:country":"GB",
    "wof:name":"CF15 9QD",
    "wof:placetype":"postalcode"
},
  "geometry": {"coordinates":[-3.29450272482728,51.5301268647769],"type":"Point"}
}