{
  "type": "Feature",
  "properties": {
    "iso:country": "GB",
    "wof:name": "HU5 3UN",
    "wof:placetype": "postalcode"
  },
  "geometry": {"coordinates":[-0.375522,53.753223],"type":"Point"}
}
