{
  "type": "Feature",
  "properties": {
    "iso:country":"GB",
    "wof:name":"RG5 3PX",
    "wof:placetype":"postalcode"
},
  "geometry": {"coordinates":[-0.9035421810243,51.44171040342679],"type":"Point"}
}