{
  "type": "Feature",
  "properties": {
    "date:inception_lower": "1994-06-01",
    "date:inception_upper": "1994-06-01",
    "iso:country": "GB",
    "wof:name": "FK7 7XA",
    "wof:placetype": "postalcode"
  },
  "geometry": {"coordinates":[-3.914971,56.100529],"type":"Point"}
}
