{
  "type": "Feature",
  "properties": {
    "iso:country":"GB",
    "wof:name":"BL6 4LZ",
    "wof:placetype":"postalcode"
},
  "geometry": {"coordinates":[-2.51924598976061,53.58667978676079],"type":"Point"}
}