{
  "type": "Feature",
  "properties": {
    "iso:country":"GB",
    "wof:name":"NE21 5GN",
    "wof:placetype":"postalcode"
},
  "geometry": {"coordinates":[-1.71716258600819,54.95610156043353],"type":"Point"}
}