{
  "type": "Feature",
  "properties": {
    "iso:country": "GB",
    "wof:name": "NE21 5GN",
    "wof:placetype": "postalcode"
  },
  "geometry": {"coordinates":[-1.717163,54.956102],"type":"Point"}
}
