{
  "type": "Feature",
  "properties": {
    "date:inception_lower":"2007-07-01",
    "date:inception_upper":"2007-07-31",
    "iso:country":"GB",
    "wof:name":"NE21 5GN",
    "wof:placetype":"postalcode"
},
  "geometry": {"coordinates":[-1.717163,54.956102],"type":"Point"}
}