{
  "type": "Feature",
  "properties": {
    "iso:country":"GB",
    "wof:name":"BN14 9BS",
    "wof:placetype":"postalcode"
},
  "geometry": {"coordinates":[-0.37457245125534,50.82816057458139],"type":"Point"}
}