{
  "type": "Feature",
  "properties": {
    "date:inception_lower":"1980-01-01",
    "date:inception_upper":"1980-01-31",
    "iso:country":"GB",
    "wof:name":"BN14 9BS",
    "wof:placetype":"postalcode"
},
  "geometry": {"coordinates":[-0.374547,50.828153],"type":"Point"}
}