{
  "type": "Feature",
  "properties": {
    "iso:country":"GB",
    "wof:name":"NN15 6LG",
    "wof:placetype":"postalcode"
},
  "geometry": {"coordinates":[-0.7158928260761,52.38100402690659],"type":"Point"}
}