{
  "type": "Feature",
  "properties": {
    "iso:country": "GB",
    "wof:name": "NN15 6LG",
    "wof:placetype": "postalcode"
  },
  "geometry": {"coordinates":[-0.715893,52.381004],"type":"Point"}
}
