{
  "type": "Feature",
  "properties": {
    "date:inception_lower":"1992-08-01",
    "date:inception_upper":"1992-08-31",
    "iso:country":"GB",
    "wof:name":"SW15 1JF",
    "wof:placetype":"postalcode"
},
  "geometry": {"coordinates":[-0.232127,51.46902],"type":"Point"}
}