{
  "type": "Feature",
  "properties": {
    "date:inception_lower": "2024-08-01",
    "date:inception_upper": "2024-08-01",
    "iso:country": "GB",
    "wof:name": "LS9 0FA",
    "wof:placetype": "postalcode"
  },
  "geometry": {"coordinates":[-1.454075,53.77447],"type":"Point"}
}
