{
  "type": "Feature",
  "properties": {
    "iso:country": "GB",
    "wof:name": "AL1 2BJ",
    "wof:placetype": "postalcode"
  },
  "geometry": {"coordinates":[-0.335422,51.742904],"type":"Point"}
}
