{
  "type": "Feature",
  "properties": {
    "iso:country":"GB",
    "wof:name":"AL1 2BJ",
    "wof:placetype":"postalcode"
},
  "geometry": {"coordinates":[-0.33542221627123,51.74290425942782],"type":"Point"}
}