{
  "type": "Feature",
  "properties": {
    "date:inception_lower": "2004-08-01",
    "date:inception_upper": "2004-08-01",
    "iso:country": "GB",
    "wof:name": "E10 7QA",
    "wof:placetype": "postalcode"
  },
  "geometry": {"coordinates":[-0.036008,51.568623],"type":"Point"}
}
