{
  "type": "Feature",
  "properties": {
    "date:inception_lower":"2004-08-01",
    "date:inception_upper":"2004-08-31",
    "iso:country":"GB",
    "wof:name":"E10 7QA",
    "wof:placetype":"postalcode"
},
  "geometry": {"coordinates":[-0.035951,51.568596],"type":"Point"}
}