{
  "type": "Feature",
  "properties": {
    "iso:country":"GB",
    "wof:name":"E10 7QA",
    "wof:placetype":"postalcode"
},
  "geometry": {"coordinates":[-0.03600756671271,51.5685852828334],"type":"Point"}
}