{
  "type": "Feature",
  "properties": {
    "iso:country":"GB",
    "wof:name":"PA16 7XF",
    "wof:placetype":"postalcode"
},
  "geometry": {"coordinates":[-4.77890901157923,55.95659532371483],"type":"Point"}
}