{
  "type": "Feature",
  "properties": {
    "date:inception_lower":"1980-01-01",
    "date:inception_upper":"1980-01-31",
    "iso:country":"GB",
    "wof:name":"PA16 7XF",
    "wof:placetype":"postalcode"
},
  "geometry": {"coordinates":[-4.778909,55.956595],"type":"Point"}
}