{
  "type": "Feature",
  "properties": {
    "iso:country":"GB",
    "wof:name":"OL15 0RA",
    "wof:placetype":"postalcode"
},
  "geometry": {"coordinates":[-2.1108200040415,53.63105238847118],"type":"Point"}
}