{
  "type": "Feature",
  "properties": {
    "iso:country":"GB",
    "wof:name":"TW18 2QG",
    "wof:placetype":"postalcode"
},
  "geometry": {"coordinates":[-0.50646047804957,51.42578753434188],"type":"Point"}
}