{
  "type": "Feature",
  "properties": {
    "iso:country": "GB",
    "wof:name": "PL7 5FG",
    "wof:placetype": "postalcode"
  },
  "geometry": {"coordinates":[-4.040271,50.428469],"type":"Point"}
}
