{
  "type": "Feature",
  "properties": {
    "iso:country":"GB",
    "wof:name":"TN35 5HR",
    "wof:placetype":"postalcode"
},
  "geometry": {"coordinates":[0.60949455878649,50.87210569592337],"type":"Point"}
}