{
  "type": "Feature",
  "properties": {
    "iso:country": "GB",
    "wof:name": "NP11 7NQ",
    "wof:placetype": "postalcode"
  },
  "geometry": {"coordinates":[-3.139196,51.639207],"type":"Point"}
}
