{
  "type": "Feature",
  "properties": {
    "date:inception_lower": "1994-05-01",
    "date:inception_upper": "1994-05-01",
    "iso:country": "GB",
    "wof:name": "LE8 8UQ",
    "wof:placetype": "postalcode"
  },
  "geometry": {"coordinates":[-1.047149,52.532442],"type":"Point"}
}
