{
  "type": "Feature",
  "properties": {
    "iso:country":"GB",
    "wof:name":"CA2 5BN",
    "wof:placetype":"postalcode"
},
  "geometry": {"coordinates":[-2.94200505960992,54.89419493907178],"type":"Point"}
}