{
  "type": "Feature",
  "properties": {
    "date:inception_lower": "1980-01-01",
    "date:inception_upper": "1980-01-01",
    "iso:country": "GB",
    "wof:name": "CA2 5BN",
    "wof:placetype": "postalcode"
  },
  "geometry": {"coordinates":[-2.942009,54.894201],"type":"Point"}
}
