{
  "type": "Feature",
  "properties": {
    "date:inception_lower": "1980-01-01",
    "date:inception_upper": "1980-01-01",
    "iso:country": "GB",
    "wof:name": "L1 9HB",
    "wof:placetype": "postalcode"
  },
  "geometry": {"coordinates":[-2.972964,53.40036],"type":"Point"}
}
