{
  "type": "Feature",
  "properties": {
    "iso:country":"GB",
    "wof:name":"DG2 9EP",
    "wof:placetype":"postalcode"
},
  "geometry": {"coordinates":[-3.63549711660092,55.07048587079854],"type":"Point"}
}