{
  "type": "Feature",
  "properties": {
    "date:inception_lower": "1999-12-01",
    "date:inception_upper": "1999-12-01",
    "iso:country": "GB",
    "wof:name": "DG2 9EP",
    "wof:placetype": "postalcode"
  },
  "geometry": {"coordinates":[-3.635497,55.070486],"type":"Point"}
}
