{
  "type": "Feature",
  "properties": {
    "date:inception_lower": "2019-06-01",
    "date:inception_upper": "2019-06-01",
    "iso:country": "GB",
    "wof:name": "OX15 4TN",
    "wof:placetype": "postalcode"
  },
  "geometry": {"coordinates":[-1.325125,52.042076],"type":"Point"}
}
