{
  "type": "Feature",
  "properties": {
    "iso:country":"GB",
    "wof:name":"TN14 7EA",
    "wof:placetype":"postalcode"
},
  "geometry": {"coordinates":[0.13604472869488,51.32940669146801],"type":"Point"}
}