{
  "type": "Feature",
  "properties": {
    "date:inception_lower": "1980-01-01",
    "date:inception_upper": "1980-01-01",
    "iso:country": "GB",
    "wof:name": "L31 4HT",
    "wof:placetype": "postalcode"
  },
  "geometry": {"coordinates":[-2.953289,53.54275],"type":"Point"}
}
