{
  "type": "Feature",
  "properties": {
    "iso:country": "GB",
    "wof:name": "L31 4HT",
    "wof:placetype": "postalcode"
  },
  "geometry": {"coordinates":[-2.953289,53.54275],"type":"Point"}
}
