{
  "type": "Feature",
  "properties": {
    "date:inception_lower": "2022-09-01",
    "date:inception_upper": "2022-09-01",
    "iso:country": "GB",
    "wof:name": "BN3 5GG",
    "wof:placetype": "postalcode"
  },
  "geometry": {"coordinates":[-0.189172,50.835389],"type":"Point"}
}
