{
  "type": "Feature",
  "properties": {
    "iso:country": "GB",
    "wof:name": "PO4 9RS",
    "wof:placetype": "postalcode"
  },
  "geometry": {"coordinates":[-1.066662,50.782734],"type":"Point"}
}
