{
  "type": "Feature",
  "properties": {
    "iso:country":"GB",
    "wof:name":"TN12 8AX",
    "wof:placetype":"postalcode"
},
  "geometry": {"coordinates":[0.43755767921394,51.13668422670916],"type":"Point"}
}