{
  "type": "Feature",
  "properties": {
    "iso:country":"GB",
    "wof:name":"WA10 5HA",
    "wof:placetype":"postalcode"
},
  "geometry": {"coordinates":[-2.78034766575689,53.45898913191223],"type":"Point"}
}