{
  "type": "Feature",
  "properties": {
    "iso:country": "GB",
    "wof:name": "EH12 5RW",
    "wof:placetype": "postalcode"
  },
  "geometry": {"coordinates":[-3.249052,55.941928],"type":"Point"}
}
