{
  "type": "Feature",
  "properties": {
    "iso:country":"GB",
    "wof:name":"HA9 8SW",
    "wof:placetype":"postalcode"
},
  "geometry": {"coordinates":[-0.3087133984663,51.5755033360009],"type":"Point"}
}