{
  "type": "Feature",
  "properties": {
    "date:inception_lower": "2015-10-01",
    "date:inception_upper": "2015-10-01",
    "iso:country": "GB",
    "wof:name": "CM1 1AP",
    "wof:placetype": "postalcode"
  },
  "geometry": {"coordinates":[0.471383,51.738236],"type":"Point"}
}
