{
  "type": "Feature",
  "properties": {
    "iso:country":"GB",
    "wof:name":"CW11 1JD",
    "wof:placetype":"postalcode"
},
  "geometry": {"coordinates":[-2.38003083867819,53.14480809859645],"type":"Point"}
}