{
  "type": "Feature",
  "properties": {
    "iso:country": "GB",
    "wof:name": "TS10 1SN",
    "wof:placetype": "postalcode"
  },
  "geometry": {"coordinates":[-1.073253,54.618238],"type":"Point"}
}
