{
  "type": "Feature",
  "properties": {
    "date:inception_lower": "2023-01-01",
    "date:inception_upper": "2023-01-01",
    "iso:country": "GB",
    "wof:name": "TN25 7LX",
    "wof:placetype": "postalcode"
  },
  "geometry": {"coordinates":[0.884132,51.107846],"type":"Point"}
}
