{
  "type": "Feature",
  "properties": {
    "iso:country":"GB",
    "wof:name":"TN12 9ET",
    "wof:placetype":"postalcode"
},
  "geometry": {"coordinates":[0.50066144807007,51.17270272715457],"type":"Point"}
}