{
  "type": "Feature",
  "properties": {
    "iso:country": "GB",
    "wof:name": "TN12 9ET",
    "wof:placetype": "postalcode"
  },
  "geometry": {"coordinates":[0.500661,51.172703],"type":"Point"}
}
