{
  "type": "Feature",
  "properties": {
    "date:inception_lower": "2019-01-01",
    "date:inception_upper": "2019-01-01",
    "iso:country": "GB",
    "wof:name": "CB10 1FF",
    "wof:placetype": "postalcode"
  },
  "geometry": {"coordinates":[0.205044,52.062762],"type":"Point"}
}
