{
  "type": "Feature",
  "properties": {
    "iso:country":"GB",
    "wof:name":"FY2 9NB",
    "wof:placetype":"postalcode"
},
  "geometry": {"coordinates":[-3.04348770839108,53.84883888946025],"type":"Point"}
}