{
  "type": "Feature",
  "properties": {
    "iso:country":"GB",
    "wof:name":"WA4 4AE",
    "wof:placetype":"postalcode"
},
  "geometry": {"coordinates":[-2.63186148650026,53.34021817203246],"type":"Point"}
}