{
  "type": "Feature",
  "properties": {
    "iso:country": "GB",
    "wof:name": "WA4 4AE",
    "wof:placetype": "postalcode"
  },
  "geometry": {"coordinates":[-2.631861,53.340218],"type":"Point"}
}
