{
  "type": "Feature",
  "properties": {
    "iso:country":"GB",
    "wof:name":"ME4 6JL",
    "wof:placetype":"postalcode"
},
  "geometry": {"coordinates":[0.51670835588471,51.36122617943842],"type":"Point"}
}