{
  "type": "Feature",
  "properties": {
    "iso:country":"GB",
    "wof:name":"DN4 6HQ",
    "wof:placetype":"postalcode"
},
  "geometry": {"coordinates":[-1.08530186625149,53.51661061009517],"type":"Point"}
}