{
  "type": "Feature",
  "properties": {
    "iso:country":"GB",
    "wof:name":"BR3 3XN",
    "wof:placetype":"postalcode"
},
  "geometry": {"coordinates":[-0.01615373019577,51.39332532384752],"type":"Point"}
}