{
  "type": "Feature",
  "properties": {
    "iso:country": "GB",
    "wof:name": "EH9 1LS",
    "wof:placetype": "postalcode"
  },
  "geometry": {"coordinates":[-3.185729,55.938749],"type":"Point"}
}
