{
  "type": "Feature",
  "properties": {
    "iso:country":"GB",
    "wof:name":"WC1X 9LS",
    "wof:placetype":"postalcode"
},
  "geometry": {"coordinates":[-0.11578637779763,51.52780864639974],"type":"Point"}
}