{
  "type": "Feature",
  "properties": {
    "iso:country":"GB",
    "wof:name":"DT1 1HR",
    "wof:placetype":"postalcode"
},
  "geometry": {"coordinates":[-2.43431825174055,50.71619854387079],"type":"Point"}
}