{
  "type": "Feature",
  "properties": {
    "iso:country":"GB",
    "wof:name":"LN4 2RW",
    "wof:placetype":"postalcode"
},
  "geometry": {"coordinates":[-0.52433363158665,53.21501605692671],"type":"Point"}
}