{
  "type": "Feature",
  "properties": {
    "iso:country":"GB",
    "wof:name":"W4 1HD",
    "wof:placetype":"postalcode"
},
  "geometry": {"coordinates":[-0.25685632417636,51.5001440511107],"type":"Point"}
}