{
  "type": "Feature",
  "properties": {
    "iso:country":"GB",
    "wof:name":"MK42 7HS",
    "wof:placetype":"postalcode"
},
  "geometry": {"coordinates":[-0.5048895414397,52.11149737414683],"type":"Point"}
}