{
  "type": "Feature",
  "properties": {
    "iso:country":"GB",
    "wof:name":"NW5 2NF",
    "wof:placetype":"postalcode"
},
  "geometry": {"coordinates":[-0.14187753565894,51.54700112510953],"type":"Point"}
}