{
  "type": "Feature",
  "properties": {
    "iso:country": "GB",
    "wof:name": "PE15 9NN",
    "wof:placetype": "postalcode"
  },
  "geometry": {"coordinates":[0.089372,52.54133],"type":"Point"}
}
