{
  "type": "Feature",
  "properties": {
    "iso:country": "GB",
    "wof:name": "WF3 4LF",
    "wof:placetype": "postalcode"
  },
  "geometry": {"coordinates":[-1.475738,53.700164],"type":"Point"}
}
