{
  "type": "Feature",
  "properties": {
    "iso:country":"GB",
    "wof:name":"LS23 6EQ",
    "wof:placetype":"postalcode"
},
  "geometry": {"coordinates":[-1.3581705785989,53.905941740884],"type":"Point"}
}