{
  "type": "Feature",
  "properties": {
    "iso:country":"GB",
    "wof:name":"LE4 0AF",
    "wof:placetype":"postalcode"
},
  "geometry": {"coordinates":[-1.1448690298815,52.64878230457868],"type":"Point"}
}