{
  "type": "Feature",
  "properties": {
    "date:inception_lower": "1994-05-01",
    "date:inception_upper": "1994-05-01",
    "iso:country": "GB",
    "wof:name": "WF2 6NZ",
    "wof:placetype": "postalcode"
  },
  "geometry": {"coordinates":[-1.466458,53.648225],"type":"Point"}
}
