{
  "type": "Feature",
  "properties": {
    "iso:country":"GB",
    "wof:name":"WF2 6NZ",
    "wof:placetype":"postalcode"
},
  "geometry": {"coordinates":[-1.4664582992466,53.64822530884391],"type":"Point"}
}