{
  "type": "Feature",
  "properties": {
    "iso:country": "GB",
    "wof:name": "WF2 6NZ",
    "wof:placetype": "postalcode"
  },
  "geometry": {"coordinates":[-1.466458,53.648225],"type":"Point"}
}
