{
  "type": "Feature",
  "properties": {
    "date:inception_lower":"2007-02-01",
    "date:inception_upper":"2007-02-28",
    "iso:country":"GB",
    "wof:name":"ME7 4JP",
    "wof:placetype":"postalcode"
},
  "geometry": {"coordinates":[0.551608,51.385095],"type":"Point"}
}