{
  "type": "Feature",
  "properties": {
    "iso:country":"GB",
    "wof:name":"ME7 4JP",
    "wof:placetype":"postalcode"
},
  "geometry": {"coordinates":[0.55160812082479,51.3850954785705],"type":"Point"}
}