{
  "type": "Feature",
  "properties": {
    "iso:country": "GB",
    "wof:name": "ME7 4JP",
    "wof:placetype": "postalcode"
  },
  "geometry": {"coordinates":[0.551608,51.385095],"type":"Point"}
}
