{
  "type": "Feature",
  "properties": {
    "iso:country":"GB",
    "wof:name":"ST9 0PL",
    "wof:placetype":"postalcode"
},
  "geometry": {"coordinates":[-2.10071556665892,53.01928315939099],"type":"Point"}
}