{
  "type": "Feature",
  "properties": {
    "iso:country": "GB",
    "wof:name": "ST9 0PL",
    "wof:placetype": "postalcode"
  },
  "geometry": {"coordinates":[-2.100716,53.019283],"type":"Point"}
}
