{
  "type": "Feature",
  "properties": {
    "iso:country":"GB",
    "wof:name":"NG34 9EL",
    "wof:placetype":"postalcode"
},
  "geometry": {"coordinates":[-0.38776380292942,53.04650093260867],"type":"Point"}
}