{
  "type": "Feature",
  "properties": {
    "iso:country":"GB",
    "wof:name":"TS25 5DL",
    "wof:placetype":"postalcode"
},
  "geometry": {"coordinates":[-1.22116867266479,54.66486175134011],"type":"Point"}
}