{
  "type": "Feature",
  "properties": {
    "iso:country": "GB",
    "wof:name": "RG12 7QQ",
    "wof:placetype": "postalcode"
  },
  "geometry": {"coordinates":[-0.769419,51.38952],"type":"Point"}
}
