{
  "type": "Feature",
  "properties": {
    "iso:country":"GB",
    "wof:name":"NG3 7GU",
    "wof:placetype":"postalcode"
},
  "geometry": {"coordinates":[-1.10603790247151,52.95919976895211],"type":"Point"}
}