{
  "type": "Feature",
  "properties": {
    "iso:country":"GB",
    "wof:name":"BH15 1ST",
    "wof:placetype":"postalcode"
},
  "geometry": {"coordinates":[-1.98014489284829,50.71833771698935],"type":"Point"}
}