{
  "type": "Feature",
  "properties": {
    "iso:country": "GB",
    "wof:name": "SY10 7NN",
    "wof:placetype": "postalcode"
  },
  "geometry": {"coordinates":[-3.093594,52.90522],"type":"Point"}
}
