{
  "type": "Feature",
  "properties": {
    "date:inception_lower": "1980-01-01",
    "date:inception_upper": "1980-01-01",
    "iso:country": "GB",
    "wof:name": "SY10 7NN",
    "wof:placetype": "postalcode"
  },
  "geometry": {"coordinates":[-3.09159,52.906506],"type":"Point"}
}
