{
  "type": "Feature",
  "properties": {
    "iso:country": "GB",
    "wof:name": "NN14 2UY",
    "wof:placetype": "postalcode"
  },
  "geometry": {"coordinates":[-0.834178,52.445145],"type":"Point"}
}
