{
  "type": "Feature",
  "properties": {
    "iso:country": "GB",
    "wof:name": "SE12 9SU",
    "wof:placetype": "postalcode"
  },
  "geometry": {"coordinates":[0.024651,51.432933],"type":"Point"}
}
