{
  "type": "Feature",
  "properties": {
    "iso:country":"GB",
    "wof:name":"SE12 9SU",
    "wof:placetype":"postalcode"
},
  "geometry": {"coordinates":[0.02465119865621,51.43293322278345],"type":"Point"}
}