{
  "type": "Feature",
  "properties": {
    "iso:country":"GB",
    "wof:name":"HA0 1LZ",
    "wof:placetype":"postalcode"
},
  "geometry": {"coordinates":[-0.28947967625391,51.53657574149757],"type":"Point"}
}