{
  "type": "Feature",
  "properties": {
    "iso:country":"GB",
    "wof:name":"BD18 4JZ",
    "wof:placetype":"postalcode"
},
  "geometry": {"coordinates":[-1.7983820476603,53.83226739740484],"type":"Point"}
}