{
  "type": "Feature",
  "properties": {
    "iso:country": "GB",
    "wof:name": "RH20 4NN",
    "wof:placetype": "postalcode"
  },
  "geometry": {"coordinates":[-0.453632,50.920596],"type":"Point"}
}
