{
  "type": "Feature",
  "properties": {
    "iso:country":"GB",
    "wof:name":"RG26 5DD",
    "wof:placetype":"postalcode"
},
  "geometry": {"coordinates":[-1.07258836535406,51.32589682385255],"type":"Point"}
}