{
  "type": "Feature",
  "properties": {
    "iso:country": "GB",
    "wof:name": "G33 1NX",
    "wof:placetype": "postalcode"
  },
  "geometry": {"coordinates":[-4.180714,55.87998],"type":"Point"}
}
