{
  "type": "Feature",
  "properties": {
    "iso:country": "GB",
    "wof:name": "LL68 0SD",
    "wof:placetype": "postalcode"
  },
  "geometry": {"coordinates":[-4.461601,53.386474],"type":"Point"}
}
