{
  "type": "Feature",
  "properties": {
    "date:inception_lower": "1980-01-01",
    "date:inception_upper": "1980-01-01",
    "iso:country": "GB",
    "wof:name": "LL68 0SD",
    "wof:placetype": "postalcode"
  },
  "geometry": {"coordinates":[-4.461601,53.386474],"type":"Point"}
}
