{
  "type": "Feature",
  "properties": {
    "iso:country":"GB",
    "wof:name":"LL68 0SD",
    "wof:placetype":"postalcode"
},
  "geometry": {"coordinates":[-4.46160138464958,53.38647449749794],"type":"Point"}
}