{
  "type": "Feature",
  "properties": {
    "iso:country":"GB",
    "wof:name":"SA32 7SL",
    "wof:placetype":"postalcode"
},
  "geometry": {"coordinates":[-4.06094461008818,51.98380966710363],"type":"Point"}
}