{
  "type": "Feature",
  "properties": {
    "date:inception_lower": "1980-01-01",
    "date:inception_upper": "1980-01-01",
    "iso:country": "GB",
    "wof:name": "DN4 0SR",
    "wof:placetype": "postalcode"
  },
  "geometry": {"coordinates":[-1.161972,53.50537],"type":"Point"}
}
