{
  "type": "Feature",
  "properties": {
    "iso:country":"GB",
    "wof:name":"DN4 0SR",
    "wof:placetype":"postalcode"
},
  "geometry": {"coordinates":[-1.16197184696018,53.50537032481566],"type":"Point"}
}