{
  "type": "Feature",
  "properties": {
    "date:inception_lower": "1980-01-01",
    "date:inception_upper": "1980-01-01",
    "iso:country": "GB",
    "wof:name": "TF11 9JZ",
    "wof:placetype": "postalcode"
  },
  "geometry": {"coordinates":[-2.356099,52.636047],"type":"Point"}
}
