{
  "type": "Feature",
  "properties": {
    "iso:country":"GB",
    "wof:name":"TF11 9JZ",
    "wof:placetype":"postalcode"
},
  "geometry": {"coordinates":[-2.35609917131953,52.63604733428471],"type":"Point"}
}