{
  "type": "Feature",
  "properties": {
    "iso:country":"GB",
    "wof:name":"RM3 8SU",
    "wof:placetype":"postalcode"
},
  "geometry": {"coordinates":[0.21981409758231,51.59951890456809],"type":"Point"}
}