{
  "type": "Feature",
  "properties": {
    "iso:country": "GB",
    "wof:name": "RM3 8SU",
    "wof:placetype": "postalcode"
  },
  "geometry": {"coordinates":[0.219563,51.599472],"type":"Point"}
}
