{
  "type": "Feature",
  "properties": {
    "iso:country":"GB",
    "wof:name":"LU4 8PP",
    "wof:placetype":"postalcode"
},
  "geometry": {"coordinates":[-0.44976044255675,51.89476505794093],"type":"Point"}
}