{
  "type": "Feature",
  "properties": {
    "iso:country":"GB",
    "wof:name":"S42 5BQ",
    "wof:placetype":"postalcode"
},
  "geometry": {"coordinates":[-1.3932594213758,53.20051101262732],"type":"Point"}
}