{
  "type": "Feature",
  "properties": {
    "iso:country":"GB",
    "wof:name":"PA33 1BS",
    "wof:placetype":"postalcode"
},
  "geometry": {"coordinates":[-5.27749973101408,56.23302218357995],"type":"Point"}
}