{
  "type": "Feature",
  "properties": {
    "date:inception_lower": "1980-01-01",
    "date:inception_upper": "1980-01-01",
    "iso:country": "GB",
    "wof:name": "PA33 1BS",
    "wof:placetype": "postalcode"
  },
  "geometry": {"coordinates":[-5.2775,56.233022],"type":"Point"}
}
