{
  "type": "Feature",
  "properties": {
    "iso:country": "GB",
    "wof:name": "PA33 1BS",
    "wof:placetype": "postalcode"
  },
  "geometry": {"coordinates":[-5.2775,56.233022],"type":"Point"}
}
