{
  "type": "Feature",
  "properties": {
    "date:inception_lower": "1980-01-01",
    "date:inception_upper": "1980-01-01",
    "iso:country": "GB",
    "wof:name": "HP1 3DU",
    "wof:placetype": "postalcode"
  },
  "geometry": {"coordinates":[-0.48493,51.759403],"type":"Point"}
}
