{
  "type": "Feature",
  "properties": {
    "iso:country":"GB",
    "wof:name":"SK11 9DE",
    "wof:placetype":"postalcode"
},
  "geometry": {"coordinates":[-2.25851148687331,53.2315624480447],"type":"Point"}
}