{
  "type": "Feature",
  "properties": {
    "iso:country": "GB",
    "wof:name": "SK11 9DE",
    "wof:placetype": "postalcode"
  },
  "geometry": {"coordinates":[-2.258511,53.231562],"type":"Point"}
}
