{
  "type": "Feature",
  "properties": {
    "date:inception_lower": "1999-06-01",
    "date:inception_upper": "1999-06-01",
    "iso:country": "GB",
    "wof:name": "CH61 6XY",
    "wof:placetype": "postalcode"
  },
  "geometry": {"coordinates":[-3.106927,53.340522],"type":"Point"}
}
