{
  "type": "Feature",
  "properties": {
    "date:inception_lower": "1980-01-01",
    "date:inception_upper": "1980-01-01",
    "iso:country": "GB",
    "wof:name": "AL2 1QH",
    "wof:placetype": "postalcode"
  },
  "geometry": {"coordinates":[-0.293987,51.722911],"type":"Point"}
}
