{
  "type": "Feature",
  "properties": {
    "iso:country": "GB",
    "wof:name": "LA2 9RX",
    "wof:placetype": "postalcode"
  },
  "geometry": {"coordinates":[-2.720372,54.076317],"type":"Point"}
}
