{
  "type": "Feature",
  "properties": {
    "iso:country":"GB",
    "wof:name":"M43 6NS",
    "wof:placetype":"postalcode"
},
  "geometry": {"coordinates":[-2.16250829927891,53.48211056170886],"type":"Point"}
}