{
  "type": "Feature",
  "properties": {
    "iso:country":"GB",
    "wof:name":"TR10 8PR",
    "wof:placetype":"postalcode"
},
  "geometry": {"coordinates":[-5.10570336837028,50.1675766480236],"type":"Point"}
}