{
  "type": "Feature",
  "properties": {
    "date:inception_lower": "1980-01-01",
    "date:inception_upper": "1980-01-01",
    "iso:country": "GB",
    "wof:name": "DH6 1BA",
    "wof:placetype": "postalcode"
  },
  "geometry": {"coordinates":[-1.488481,54.793185],"type":"Point"}
}
