{
  "type": "Feature",
  "properties": {
    "date:inception_lower": "1980-01-01",
    "date:inception_upper": "1980-01-01",
    "iso:country": "GB",
    "wof:name": "N14 7AD",
    "wof:placetype": "postalcode"
  },
  "geometry": {"coordinates":[-0.12555,51.623833],"type":"Point"}
}
