{
  "type": "Feature",
  "properties": {
    "iso:country": "GB",
    "wof:name": "EX19 8JP",
    "wof:placetype": "postalcode"
  },
  "geometry": {"coordinates":[-3.94526,50.852414],"type":"Point"}
}
