{
  "type": "Feature",
  "properties": {
    "iso:country":"GB",
    "wof:name":"SE7 8UJ",
    "wof:placetype":"postalcode"
},
  "geometry": {"coordinates":[0.03566671054247,51.48231968304507],"type":"Point"}
}