{
  "type": "Feature",
  "properties": {
    "iso:country":"GB",
    "wof:name":"AB43 7EG",
    "wof:placetype":"postalcode"
},
  "geometry": {"coordinates":[-2.06645002097604,57.69564302011206],"type":"Point"}
}