{
  "type": "Feature",
  "properties": {
    "date:inception_lower": "1996-06-01",
    "date:inception_upper": "1996-06-01",
    "iso:country": "GB",
    "wof:name": "AB43 7EG",
    "wof:placetype": "postalcode"
  },
  "geometry": {"coordinates":[-2.06645,57.695643],"type":"Point"}
}
