{
  "type": "Feature",
  "properties": {
    "date:inception_lower": "1980-01-01",
    "date:inception_upper": "1980-01-01",
    "iso:country": "GB",
    "wof:name": "L9 2AY",
    "wof:placetype": "postalcode"
  },
  "geometry": {"coordinates":[-2.957376,53.454322],"type":"Point"}
}
