{
  "type": "Feature",
  "properties": {
    "iso:country": "GB",
    "wof:name": "SO50 7FL",
    "wof:placetype": "postalcode"
  },
  "geometry": {"coordinates":[-1.303842,50.974227],"type":"Point"}
}
