{
  "type": "Feature",
  "properties": {
    "date:inception_lower": "1980-01-01",
    "date:inception_upper": "1980-01-01",
    "iso:country": "GB",
    "wof:name": "DH9 0UW",
    "wof:placetype": "postalcode"
  },
  "geometry": {"coordinates":[-1.674993,54.873861],"type":"Point"}
}
