{
  "type": "Feature",
  "properties": {
    "iso:country":"GB",
    "wof:name":"DH9 0UW",
    "wof:placetype":"postalcode"
},
  "geometry": {"coordinates":[-1.67499275740056,54.87386120632104],"type":"Point"}
}