{
  "type": "Feature",
  "properties": {
    "date:inception_lower":"1980-01-01",
    "date:inception_upper":"1980-01-31",
    "iso:country":"GB",
    "wof:name":"NP44 1LY",
    "wof:placetype":"postalcode"
},
  "geometry": {"coordinates":[-3.022803,51.656275],"type":"Point"}
}