{
  "type": "Feature",
  "properties": {
    "iso:country":"GB",
    "wof:name":"NP44 1LY",
    "wof:placetype":"postalcode"
},
  "geometry": {"coordinates":[-3.0228028641502,51.65627517724453],"type":"Point"}
}