{
  "type": "Feature",
  "properties": {
    "iso:country":"GB",
    "wof:name":"IG8 8NJ",
    "wof:placetype":"postalcode"
},
  "geometry": {"coordinates":[0.0544798628312,51.60021862222975],"type":"Point"}
}