{
  "type": "Feature",
  "properties": {
    "date:inception_lower":"1980-01-01",
    "date:inception_upper":"1980-01-31",
    "iso:country":"GB",
    "wof:name":"IG8 8NJ",
    "wof:placetype":"postalcode"
},
  "geometry": {"coordinates":[0.05448,51.600219],"type":"Point"}
}