{
  "type": "Feature",
  "properties": {
    "iso:country": "GB",
    "wof:name": "IG8 8NJ",
    "wof:placetype": "postalcode"
  },
  "geometry": {"coordinates":[0.05448,51.600219],"type":"Point"}
}
