{
  "type": "Feature",
  "properties": {
    "iso:country": "GB",
    "wof:name": "BB8 7NR",
    "wof:placetype": "postalcode"
  },
  "geometry": {"coordinates":[-2.167451,53.874598],"type":"Point"}
}
