{
  "type": "Feature",
  "properties": {
    "iso:country":"GB",
    "wof:name":"BB8 7NR",
    "wof:placetype":"postalcode"
},
  "geometry": {"coordinates":[-2.16745064321319,53.87459814188608],"type":"Point"}
}