{
  "type": "Feature",
  "properties": {
    "date:inception_lower":"1980-01-01",
    "date:inception_upper":"1980-01-31",
    "iso:country":"GB",
    "wof:name":"NE19 1BP",
    "wof:placetype":"postalcode"
},
  "geometry": {"coordinates":[-2.096986,55.220778],"type":"Point"}
}