{
  "type": "Feature",
  "properties": {
    "iso:country": "GB",
    "wof:name": "NE19 1BP",
    "wof:placetype": "postalcode"
  },
  "geometry": {"coordinates":[-2.096986,55.220778],"type":"Point"}
}
