{
  "type": "Feature",
  "properties": {
    "iso:country":"GB",
    "wof:name":"NE19 1BP",
    "wof:placetype":"postalcode"
},
  "geometry": {"coordinates":[-2.09698651527226,55.22077787277937],"type":"Point"}
}