{
  "type": "Feature",
  "properties": {
    "iso:country": "GB",
    "wof:name": "GU8 5TS",
    "wof:placetype": "postalcode"
  },
  "geometry": {"coordinates":[-0.634978,51.135342],"type":"Point"}
}
