{
  "type": "Feature",
  "properties": {
    "iso:country":"GB",
    "wof:name":"EH55 8ER",
    "wof:placetype":"postalcode"
},
  "geometry": {"coordinates":[-3.5818172084304,55.84769060347784],"type":"Point"}
}