{
  "type": "Feature",
  "properties": {
    "date:inception_lower": "1980-01-01",
    "date:inception_upper": "1980-01-01",
    "iso:country": "GB",
    "wof:name": "GL12 7LR",
    "wof:placetype": "postalcode"
  },
  "geometry": {"coordinates":[-2.347436,51.63335],"type":"Point"}
}
