{
  "type": "Feature",
  "properties": {
    "iso:country": "GB",
    "wof:name": "GL12 7LR",
    "wof:placetype": "postalcode"
  },
  "geometry": {"coordinates":[-2.347436,51.63335],"type":"Point"}
}
