{
  "type": "Feature",
  "properties": {
    "iso:country":"GB",
    "wof:name":"CF43 3LW",
    "wof:placetype":"postalcode"
},
  "geometry": {"coordinates":[-3.42948565312926,51.63360356737616],"type":"Point"}
}