{
  "type": "Feature",
  "properties": {
    "iso:country":"GB",
    "wof:name":"ML7 5HS",
    "wof:placetype":"postalcode"
},
  "geometry": {"coordinates":[-3.77472506741506,55.81052348903416],"type":"Point"}
}