{
  "type": "Feature",
  "properties": {
    "iso:country":"GB",
    "wof:name":"SW12 0PG",
    "wof:placetype":"postalcode"
},
  "geometry": {"coordinates":[-0.142878967078,51.44299140499777],"type":"Point"}
}