{
  "type": "Feature",
  "properties": {
    "date:inception_lower": "1994-12-01",
    "date:inception_upper": "1994-12-01",
    "iso:country": "GB",
    "wof:name": "SO53 2HP",
    "wof:placetype": "postalcode"
  },
  "geometry": {"coordinates":[-1.376001,50.983319],"type":"Point"}
}
