{
  "type": "Feature",
  "properties": {
    "iso:country":"GB",
    "wof:name":"DT11 9NT",
    "wof:placetype":"postalcode"
},
  "geometry": {"coordinates":[-2.14451190177686,50.83590850545306],"type":"Point"}
}