{
  "type": "Feature",
  "properties": {
    "date:inception_lower": "1980-01-01",
    "date:inception_upper": "1980-01-01",
    "iso:country": "GB",
    "wof:name": "DT11 9NT",
    "wof:placetype": "postalcode"
  },
  "geometry": {"coordinates":[-2.144512,50.835909],"type":"Point"}
}
