{
  "type": "Feature",
  "properties": {
    "iso:country":"GB",
    "wof:name":"RG6 1PQ",
    "wof:placetype":"postalcode"
},
  "geometry": {"coordinates":[-0.94277943966569,51.45977574374814],"type":"Point"}
}