{
  "type": "Feature",
  "properties": {
    "iso:country":"GB",
    "wof:name":"TN11 8NH",
    "wof:placetype":"postalcode"
},
  "geometry": {"coordinates":[0.22230988396057,51.22675286540554],"type":"Point"}
}