{
  "type": "Feature",
  "properties": {
    "iso:country": "GB",
    "wof:name": "TN11 8NH",
    "wof:placetype": "postalcode"
  },
  "geometry": {"coordinates":[0.22231,51.226753],"type":"Point"}
}
