{
  "type": "Feature",
  "properties": {
    "iso:country":"GB",
    "wof:name":"IP28 8JP",
    "wof:placetype":"postalcode"
},
  "geometry": {"coordinates":[0.49459383987191,52.30457516818714],"type":"Point"}
}