{
  "type": "Feature",
  "properties": {
    "iso:country": "GB",
    "wof:name": "TR14 7EU",
    "wof:placetype": "postalcode"
  },
  "geometry": {"coordinates":[-5.303399,50.213602],"type":"Point"}
}
