{
  "type": "Feature",
  "properties": {
    "date:inception_lower": "1980-01-01",
    "date:inception_upper": "1980-01-01",
    "iso:country": "GB",
    "wof:name": "TR14 7EU",
    "wof:placetype": "postalcode"
  },
  "geometry": {"coordinates":[-5.303469,50.2136],"type":"Point"}
}
