{
  "type": "Feature",
  "properties": {
    "date:inception_lower":"2011-10-01",
    "date:inception_upper":"2011-10-31",
    "iso:country":"GB",
    "wof:name":"LE67 6AJ",
    "wof:placetype":"postalcode"
},
  "geometry": {"coordinates":[-1.405612,52.693078],"type":"Point"}
}