{
  "type": "Feature",
  "properties": {
    "iso:country": "GB",
    "wof:name": "LE67 6AJ",
    "wof:placetype": "postalcode"
  },
  "geometry": {"coordinates":[-1.405574,52.693087],"type":"Point"}
}
