{
  "type": "Feature",
  "properties": {
    "iso:country":"GB",
    "wof:name":"LE67 6AJ",
    "wof:placetype":"postalcode"
},
  "geometry": {"coordinates":[-1.40561203146651,52.69307794509162],"type":"Point"}
}