{
  "type": "Feature",
  "properties": {
    "iso:country": "GB",
    "wof:name": "DN4 6QA",
    "wof:placetype": "postalcode"
  },
  "geometry": {"coordinates":[-1.073878,53.501709],"type":"Point"}
}
