{
  "type": "Feature",
  "properties": {
    "date:inception_lower": "1980-01-01",
    "date:inception_upper": "1980-01-01",
    "iso:country": "GB",
    "wof:name": "DN4 6QA",
    "wof:placetype": "postalcode"
  },
  "geometry": {"coordinates":[-1.073878,53.501709],"type":"Point"}
}
