{
  "type": "Feature",
  "properties": {
    "iso:country":"GB",
    "wof:name":"DN4 6QA",
    "wof:placetype":"postalcode"
},
  "geometry": {"coordinates":[-1.07387814966397,53.50170925378563],"type":"Point"}
}