{
  "type": "Feature",
  "properties": {
    "date:inception_lower":"1980-01-01",
    "date:inception_upper":"1980-01-31",
    "iso:country":"GB",
    "wof:name":"WF1 3LA",
    "wof:placetype":"postalcode"
},
  "geometry": {"coordinates":[-1.502625,53.692351],"type":"Point"}
}