{
  "type": "Feature",
  "properties": {
    "iso:country":"GB",
    "wof:name":"CR0 0XB",
    "wof:placetype":"postalcode"
},
  "geometry": {"coordinates":[-0.09960043226933,51.37521222775766],"type":"Point"}
}