{
  "type": "Feature",
  "properties": {
    "iso:country": "GB",
    "wof:name": "CV21 4BB",
    "wof:placetype": "postalcode"
  },
  "geometry": {"coordinates":[-1.20944,52.356763],"type":"Point"}
}
