{
  "type": "Feature",
  "properties": {
    "iso:country":"GB",
    "wof:name":"B68 0JE",
    "wof:placetype":"postalcode"
},
  "geometry": {"coordinates":[-2.00923015859451,52.46960542899011],"type":"Point"}
}