{
  "type": "Feature",
  "properties": {
    "date:inception_lower": "1980-01-01",
    "date:inception_upper": "1980-01-01",
    "iso:country": "GB",
    "wof:name": "RG7 3XB",
    "wof:placetype": "postalcode"
  },
  "geometry": {"coordinates":[-1.072176,51.377624],"type":"Point"}
}
