{
  "type": "Feature",
  "properties": {
    "iso:country":"GB",
    "wof:name":"RG7 3XB",
    "wof:placetype":"postalcode"
},
  "geometry": {"coordinates":[-1.07217590171938,51.37762424951779],"type":"Point"}
}