{
  "type": "Feature",
  "properties": {
    "iso:country": "GB",
    "wof:name": "KA7 1HE",
    "wof:placetype": "postalcode"
  },
  "geometry": {"coordinates":[-4.636465,55.466299],"type":"Point"}
}
