{
  "type": "Feature",
  "properties": {
    "date:inception_lower": "1999-12-01",
    "date:inception_upper": "1999-12-01",
    "iso:country": "GB",
    "wof:name": "KA7 1HE",
    "wof:placetype": "postalcode"
  },
  "geometry": {"coordinates":[-4.636465,55.466299],"type":"Point"}
}
