{
  "type": "Feature",
  "properties": {
    "iso:country":"GB",
    "wof:name":"DY5 2RG",
    "wof:placetype":"postalcode"
},
  "geometry": {"coordinates":[-2.12066619492383,52.48065560650399],"type":"Point"}
}