{
  "type": "Feature",
  "properties": {
    "iso:country":"GB",
    "wof:name":"CT15 7AH",
    "wof:placetype":"postalcode"
},
  "geometry": {"coordinates":[1.25444891010935,51.11371437557425],"type":"Point"}
}