{
  "type": "Feature",
  "properties": {
    "iso:country":"GB",
    "wof:name":"IP24 1TH",
    "wof:placetype":"postalcode"
},
  "geometry": {"coordinates":[0.75152220486685,52.42632071548007],"type":"Point"}
}