{
  "type": "Feature",
  "properties": {
    "date:inception_lower": "1985-10-01",
    "date:inception_upper": "1985-10-01",
    "iso:country": "GB",
    "wof:name": "NG16 6NR",
    "wof:placetype": "postalcode"
  },
  "geometry": {"coordinates":[-1.32293,53.091139],"type":"Point"}
}
