{
  "type": "Feature",
  "properties": {
    "iso:country":"GB",
    "wof:name":"EH6 7QB",
    "wof:placetype":"postalcode"
},
  "geometry": {"coordinates":[-3.15061181614598,55.96761925371133],"type":"Point"}
}