{
  "type": "Feature",
  "properties": {
    "iso:country":"GB",
    "wof:name":"SE23 3NH",
    "wof:placetype":"postalcode"
},
  "geometry": {"coordinates":[-0.05041712580104,51.44651696330111],"type":"Point"}
}