{
  "type": "Feature",
  "properties": {
    "iso:country": "GB",
    "wof:name": "PE28 5XT",
    "wof:placetype": "postalcode"
  },
  "geometry": {"coordinates":[-0.27136,52.420816],"type":"Point"}
}
