{
  "type": "Feature",
  "properties": {
    "iso:country":"GB",
    "wof:name":"TS3 7BA",
    "wof:placetype":"postalcode"
},
  "geometry": {"coordinates":[-1.21188174801525,54.56386862649251],"type":"Point"}
}