{
  "type": "Feature",
  "properties": {
    "iso:country":"GB",
    "wof:name":"DA15 9BS",
    "wof:placetype":"postalcode"
},
  "geometry": {"coordinates":[0.10381299264311,51.44053186104992],"type":"Point"}
}