{
  "type": "Feature",
  "properties": {
    "date:inception_lower": "1980-01-01",
    "date:inception_upper": "1980-01-01",
    "iso:country": "GB",
    "wof:name": "BN3 5BE",
    "wof:placetype": "postalcode"
  },
  "geometry": {"coordinates":[-0.180092,50.83404],"type":"Point"}
}
