{
  "type": "Feature",
  "properties": {
    "date:inception_lower":"1995-01-01",
    "date:inception_upper":"1995-01-31",
    "iso:country":"GB",
    "wof:name":"RM16 6PA",
    "wof:placetype":"postalcode"
},
  "geometry": {"coordinates":[0.312203,51.489737],"type":"Point"}
}