{
  "type": "Feature",
  "properties": {
    "iso:country": "GB",
    "wof:name": "BH2 5EX",
    "wof:placetype": "postalcode"
  },
  "geometry": {"coordinates":[-1.888647,50.716665],"type":"Point"}
}
