{
  "type": "Feature",
  "properties": {
    "iso:country":"GB",
    "wof:name":"KT10 8PB",
    "wof:placetype":"postalcode"
},
  "geometry": {"coordinates":[-0.37097015516156,51.36894026268975],"type":"Point"}
}