{
  "type": "Feature",
  "properties": {
    "iso:country":"GB",
    "wof:name":"PR1 3RU",
    "wof:placetype":"postalcode"
},
  "geometry": {"coordinates":[-2.69589693049589,53.75557221050164],"type":"Point"}
}