{
  "type": "Feature",
  "properties": {
    "iso:country": "GB",
    "wof:name": "DN19 7AJ",
    "wof:placetype": "postalcode"
  },
  "geometry": {"coordinates":[-0.376403,53.6792],"type":"Point"}
}
