{
  "type": "Feature",
  "properties": {
    "iso:country":"GB",
    "wof:name":"DN19 7AJ",
    "wof:placetype":"postalcode"
},
  "geometry": {"coordinates":[-0.37640349594271,53.67919976030373],"type":"Point"}
}