{
  "type": "Feature",
  "properties": {
    "iso:country": "GB",
    "wof:name": "NG7 3FL",
    "wof:placetype": "postalcode"
  },
  "geometry": {"coordinates":[-1.179331,52.957337],"type":"Point"}
}
