{
  "type": "Feature",
  "properties": {
    "iso:country":"GB",
    "wof:name":"SO50 6DA",
    "wof:placetype":"postalcode"
},
  "geometry": {"coordinates":[-1.33462535597864,50.97472775044366],"type":"Point"}
}