{
  "type": "Feature",
  "properties": {
    "date:inception_lower": "2021-07-01",
    "date:inception_upper": "2021-07-01",
    "iso:country": "GB",
    "wof:name": "S75 1DG",
    "wof:placetype": "postalcode"
  },
  "geometry": {"coordinates":[-1.497287,53.568353],"type":"Point"}
}
