{
  "type": "Feature",
  "properties": {
    "iso:country":"GB",
    "wof:name":"HP9 1TS",
    "wof:placetype":"postalcode"
},
  "geometry": {"coordinates":[-0.6531764051348,51.59972578331252],"type":"Point"}
}