{
  "type": "Feature",
  "properties": {
    "iso:country":"GB",
    "wof:name":"DY4 7NN",
    "wof:placetype":"postalcode"
},
  "geometry": {"coordinates":[-2.04276571637855,52.53197009595488],"type":"Point"}
}