{
  "type": "Feature",
  "properties": {
    "iso:country":"GB",
    "wof:name":"SA17 4SS",
    "wof:placetype":"postalcode"
},
  "geometry": {"coordinates":[-4.29465282926271,51.74035406718869],"type":"Point"}
}