{
  "type": "Feature",
  "properties": {
    "date:inception_lower":"2014-06-01",
    "date:inception_upper":"2014-06-30",
    "iso:country":"GB",
    "wof:name":"SA17 4SS",
    "wof:placetype":"postalcode"
},
  "geometry": {"coordinates":[-4.294911,51.740132],"type":"Point"}
}