{
  "type": "Feature",
  "properties": {
    "iso:country": "GB",
    "wof:name": "SA17 4SS",
    "wof:placetype": "postalcode"
  },
  "geometry": {"coordinates":[-4.294911,51.740132],"type":"Point"}
}
