{
  "type": "Feature",
  "properties": {
    "date:inception_lower":"1980-01-01",
    "date:inception_upper":"1980-01-31",
    "iso:country":"GB",
    "wof:name":"YO8 8HQ",
    "wof:placetype":"postalcode"
},
  "geometry": {"coordinates":[-1.012919,53.726881],"type":"Point"}
}