{
  "type": "Feature",
  "properties": {
    "iso:country":"GB",
    "wof:name":"YO8 8HQ",
    "wof:placetype":"postalcode"
},
  "geometry": {"coordinates":[-1.01291891527922,53.72688101486209],"type":"Point"}
}