{
  "type": "Feature",
  "properties": {
    "date:inception_lower":"1980-01-01",
    "date:inception_upper":"1980-01-31",
    "iso:country":"GB",
    "wof:name":"BD6 2PU",
    "wof:placetype":"postalcode"
},
  "geometry": {"coordinates":[-1.786797,53.755796],"type":"Point"}
}