{
  "type": "Feature",
  "properties": {
    "iso:country":"GB",
    "wof:name":"BD6 2PU",
    "wof:placetype":"postalcode"
},
  "geometry": {"coordinates":[-1.78679669706403,53.7557956397951],"type":"Point"}
}