{
  "type": "Feature",
  "properties": {
    "iso:country":"GB",
    "wof:name":"SN14 6EP",
    "wof:placetype":"postalcode"
},
  "geometry": {"coordinates":[-2.15168072176156,51.54006821546414],"type":"Point"}
}