{
  "type": "Feature",
  "properties": {
    "date:inception_lower": "1980-01-01",
    "date:inception_upper": "1980-01-01",
    "iso:country": "GB",
    "wof:name": "SN14 6EP",
    "wof:placetype": "postalcode"
  },
  "geometry": {"coordinates":[-2.151681,51.540068],"type":"Point"}
}
