{
  "type": "Feature",
  "properties": {
    "iso:country":"GB",
    "wof:name":"TR17 0BG",
    "wof:placetype":"postalcode"
},
  "geometry": {"coordinates":[-5.46360334983089,50.12529061429461],"type":"Point"}
}