{
  "type": "Feature",
  "properties": {
    "iso:country":"GB",
    "wof:name":"OX2 6QJ",
    "wof:placetype":"postalcode"
},
  "geometry": {"coordinates":[-1.25721853586817,51.76485912421557],"type":"Point"}
}