{
  "type": "Feature",
  "properties": {
    "date:inception_lower": "2010-03-01",
    "date:inception_upper": "2010-03-01",
    "iso:country": "GB",
    "wof:name": "SG15 6AE",
    "wof:placetype": "postalcode"
  },
  "geometry": {"coordinates":[-0.260721,52.020822],"type":"Point"}
}
