{
  "type": "Feature",
  "properties": {
    "date:inception_lower": "1980-01-01",
    "date:inception_upper": "1980-01-01",
    "iso:country": "GB",
    "wof:name": "LN8 3DY",
    "wof:placetype": "postalcode"
  },
  "geometry": {"coordinates":[-0.32743,53.383437],"type":"Point"}
}
