{
  "type": "Feature",
  "properties": {
    "iso:country": "GB",
    "wof:name": "LN8 3DY",
    "wof:placetype": "postalcode"
  },
  "geometry": {"coordinates":[-0.32743,53.383437],"type":"Point"}
}
