{
  "type": "Feature",
  "properties": {
    "date:inception_lower": "1980-01-01",
    "date:inception_upper": "1980-01-01",
    "iso:country": "GB",
    "wof:name": "E14 6BL",
    "wof:placetype": "postalcode"
  },
  "geometry": {"coordinates":[-0.018169,51.516551],"type":"Point"}
}
