{
  "type": "Feature",
  "properties": {
    "iso:country":"GB",
    "wof:name":"E14 6BL",
    "wof:placetype":"postalcode"
},
  "geometry": {"coordinates":[-0.0181690635851,51.51655084644189],"type":"Point"}
}