{
  "type": "Feature",
  "properties": {
    "date:inception_lower": "2021-06-01",
    "date:inception_upper": "2021-06-01",
    "iso:country": "GB",
    "wof:name": "IV30 4FD",
    "wof:placetype": "postalcode"
  },
  "geometry": {"coordinates":[-3.318899,57.658606],"type":"Point"}
}
