{
  "type": "Feature",
  "properties": {
    "iso:country":"GB",
    "wof:name":"CM1 2EH",
    "wof:placetype":"postalcode"
},
  "geometry": {"coordinates":[0.4518958955004,51.75126189882732],"type":"Point"}
}