{
  "type": "Feature",
  "properties": {
    "iso:country":"GB",
    "wof:name":"CR2 0DX",
    "wof:placetype":"postalcode"
},
  "geometry": {"coordinates":[-0.08516206400566,51.3527739653069],"type":"Point"}
}