{
  "type": "Feature",
  "properties": {
    "iso:country":"GB",
    "wof:name":"CB6 2PB",
    "wof:placetype":"postalcode"
},
  "geometry": {"coordinates":[0.10925268496959,52.38587333756034],"type":"Point"}
}