{
  "type": "Feature",
  "properties": {
    "iso:country":"GB",
    "wof:name":"AB25 2JT",
    "wof:placetype":"postalcode"
},
  "geometry": {"coordinates":[-2.11916004213317,57.14906564280125],"type":"Point"}
}