{
  "type": "Feature",
  "properties": {
    "iso:country": "GB",
    "wof:name": "AB25 2JT",
    "wof:placetype": "postalcode"
  },
  "geometry": {"coordinates":[-2.11916,57.149066],"type":"Point"}
}
