{
  "type": "Feature",
  "properties": {
    "iso:country": "GB",
    "wof:name": "L7 9LN",
    "wof:placetype": "postalcode"
  },
  "geometry": {"coordinates":[-2.93341,53.408713],"type":"Point"}
}
