{
  "type": "Feature",
  "properties": {
    "iso:country":"GB",
    "wof:name":"ST16 3BL",
    "wof:placetype":"postalcode"
},
  "geometry": {"coordinates":[-2.11401645278815,52.80603588499122],"type":"Point"}
}