{
  "type": "Feature",
  "properties": {
    "iso:country": "GB",
    "wof:name": "ST16 3BL",
    "wof:placetype": "postalcode"
  },
  "geometry": {"coordinates":[-2.114016,52.806036],"type":"Point"}
}
