{
  "type": "Feature",
  "properties": {
    "date:inception_lower":"1982-03-01",
    "date:inception_upper":"1982-03-31",
    "iso:country":"GB",
    "wof:name":"ST16 3BL",
    "wof:placetype":"postalcode"
},
  "geometry": {"coordinates":[-2.114016,52.806036],"type":"Point"}
}