{
  "type": "Feature",
  "properties": {
    "iso:country":"GB",
    "wof:name":"ML2 8RG",
    "wof:placetype":"postalcode"
},
  "geometry": {"coordinates":[-3.89413268725416,55.77780028425599],"type":"Point"}
}