{
  "type": "Feature",
  "properties": {
    "date:inception_lower": "1996-06-01",
    "date:inception_upper": "1996-06-01",
    "iso:country": "GB",
    "wof:name": "ML2 8RG",
    "wof:placetype": "postalcode"
  },
  "geometry": {"coordinates":[-3.894133,55.7778],"type":"Point"}
}
