{
  "type": "Feature",
  "properties": {
    "iso:country": "GB",
    "wof:name": "WA2 8BT",
    "wof:placetype": "postalcode"
  },
  "geometry": {"coordinates":[-2.59284,53.403861],"type":"Point"}
}
