{
  "type": "Feature",
  "properties": {
    "iso:country":"GB",
    "wof:name":"CB8 9LH",
    "wof:placetype":"postalcode"
},
  "geometry": {"coordinates":[0.43733112465122,52.15152509222343],"type":"Point"}
}