{
  "type": "Feature",
  "properties": {
    "date:inception_lower": "1995-01-01",
    "date:inception_upper": "1995-01-01",
    "iso:country": "GB",
    "wof:name": "CB8 9LH",
    "wof:placetype": "postalcode"
  },
  "geometry": {"coordinates":[0.437362,52.151539],"type":"Point"}
}
