{
  "type": "Feature",
  "properties": {
    "date:inception_lower": "1990-12-01",
    "date:inception_upper": "1990-12-01",
    "iso:country": "GB",
    "wof:name": "KY8 4NX",
    "wof:placetype": "postalcode"
  },
  "geometry": {"coordinates":[-2.997273,56.195793],"type":"Point"}
}
