{
  "type": "Feature",
  "properties": {
    "iso:country":"GB",
    "wof:name":"KY8 4NX",
    "wof:placetype":"postalcode"
},
  "geometry": {"coordinates":[-2.99727279811149,56.19579264581851],"type":"Point"}
}