{
  "type": "Feature",
  "properties": {
    "iso:country":"GB",
    "wof:name":"AB54 6DW",
    "wof:placetype":"postalcode"
},
  "geometry": {"coordinates":[-2.64637258890652,57.49183751104766],"type":"Point"}
}