{
  "type": "Feature",
  "properties": {
    "date:inception_lower":"2011-09-01",
    "date:inception_upper":"2011-09-30",
    "iso:country":"GB",
    "wof:name":"PE25 1GR",
    "wof:placetype":"postalcode"
},
  "geometry": {"coordinates":[0.330073,53.158142],"type":"Point"}
}