{
  "type": "Feature",
  "properties": {
    "iso:country": "GB",
    "wof:name": "RH19 2QS",
    "wof:placetype": "postalcode"
  },
  "geometry": {"coordinates":[-0.038453,51.14072],"type":"Point"}
}
