{
  "type": "Feature",
  "properties": {
    "date:inception_lower": "1995-12-01",
    "date:inception_upper": "1995-12-01",
    "iso:country": "GB",
    "wof:name": "CA28 9BE",
    "wof:placetype": "postalcode"
  },
  "geometry": {"coordinates":[-3.598018,54.535978],"type":"Point"}
}
