{
  "type": "Feature",
  "properties": {
    "iso:country":"GB",
    "wof:name":"CA28 9BE",
    "wof:placetype":"postalcode"
},
  "geometry": {"coordinates":[-3.5980180135912,54.5359776626289],"type":"Point"}
}