{
  "type": "Feature",
  "properties": {
    "iso:country": "GB",
    "wof:name": "CA28 9BE",
    "wof:placetype": "postalcode"
  },
  "geometry": {"coordinates":[-3.598018,54.535978],"type":"Point"}
}
