{
  "type": "Feature",
  "properties": {
    "date:inception_lower":"2007-04-01",
    "date:inception_upper":"2007-04-30",
    "iso:country":"GB",
    "wof:name":"NG17 8RG",
    "wof:placetype":"postalcode"
},
  "geometry": {"coordinates":[-1.251748,53.092008],"type":"Point"}
}