{
  "type": "Feature",
  "properties": {
    "iso:country": "GB",
    "wof:name": "NG17 8RG",
    "wof:placetype": "postalcode"
  },
  "geometry": {"coordinates":[-1.251748,53.092008],"type":"Point"}
}
