{
  "type": "Feature",
  "properties": {
    "iso:country": "GB",
    "wof:name": "PE21 7JE",
    "wof:placetype": "postalcode"
  },
  "geometry": {"coordinates":[-0.059665,52.969215],"type":"Point"}
}
