{
  "type": "Feature",
  "properties": {
    "iso:country":"GB",
    "wof:name":"PE21 7JE",
    "wof:placetype":"postalcode"
},
  "geometry": {"coordinates":[-0.05983586722074,52.9692121923141],"type":"Point"}
}