{
  "type": "Feature",
  "properties": {
    "iso:country": "GB",
    "wof:name": "SG19 1RH",
    "wof:placetype": "postalcode"
  },
  "geometry": {"coordinates":[-0.290038,52.135561],"type":"Point"}
}
