{
  "type": "Feature",
  "properties": {
    "date:inception_lower":"1980-01-01",
    "date:inception_upper":"1980-01-31",
    "iso:country":"GB",
    "wof:name":"LS7 3DQ",
    "wof:placetype":"postalcode"
},
  "geometry": {"coordinates":[-1.540089,53.823098],"type":"Point"}
}