{
  "type": "Feature",
  "properties": {
    "iso:country":"GB",
    "wof:name":"LS7 3DQ",
    "wof:placetype":"postalcode"
},
  "geometry": {"coordinates":[-1.54008901355613,53.82309817922985],"type":"Point"}
}