{
  "type": "Feature",
  "properties": {
    "iso:country":"GB",
    "wof:name":"NG2 4FF",
    "wof:placetype":"postalcode"
},
  "geometry": {"coordinates":[-1.12596315150027,52.95000780310864],"type":"Point"}
}