{
  "type": "Feature",
  "properties": {
    "iso:country": "GB",
    "wof:name": "NP19 4DJ",
    "wof:placetype": "postalcode"
  },
  "geometry": {"coordinates":[-2.937799,51.577465],"type":"Point"}
}
