{
  "type": "Feature",
  "properties": {
    "iso:country":"GB",
    "wof:name":"E12 6DR",
    "wof:placetype":"postalcode"
},
  "geometry": {"coordinates":[0.05545353488879,51.54981570058851],"type":"Point"}
}