{
  "type": "Feature",
  "properties": {
    "iso:country": "GB",
    "wof:name": "E12 6DR",
    "wof:placetype": "postalcode"
  },
  "geometry": {"coordinates":[0.055454,51.549816],"type":"Point"}
}
