{
  "type": "Feature",
  "properties": {
    "date:inception_lower": "1980-01-01",
    "date:inception_upper": "1980-01-01",
    "iso:country": "GB",
    "wof:name": "TW2 7DU",
    "wof:placetype": "postalcode"
  },
  "geometry": {"coordinates":[-0.350676,51.4551],"type":"Point"}
}
