{
  "type": "Feature",
  "properties": {
    "iso:country":"GB",
    "wof:name":"TW2 7DU",
    "wof:placetype":"postalcode"
},
  "geometry": {"coordinates":[-0.35067616879795,51.45510050162797],"type":"Point"}
}