{
  "type": "Feature",
  "properties": {
    "date:inception_lower":"1999-12-01",
    "date:inception_upper":"1999-12-31",
    "iso:country":"GB",
    "wof:name":"EH12 8GR",
    "wof:placetype":"postalcode"
},
  "geometry": {"coordinates":[-3.307802,55.946831],"type":"Point"}
}