{
  "type": "Feature",
  "properties": {
    "iso:country":"GB",
    "wof:name":"OX10 7BB",
    "wof:placetype":"postalcode"
},
  "geometry": {"coordinates":[-1.13909517933118,51.66321544587146],"type":"Point"}
}