{
  "type": "Feature",
  "properties": {
    "iso:country": "GB",
    "wof:name": "B90 4BE",
    "wof:placetype": "postalcode"
  },
  "geometry": {"coordinates":[-1.813088,52.39405],"type":"Point"}
}
