{
  "type": "Feature",
  "properties": {
    "iso:country":"GB",
    "wof:name":"B90 4BE",
    "wof:placetype":"postalcode"
},
  "geometry": {"coordinates":[-1.81308799746299,52.39405008642335],"type":"Point"}
}