{
  "type": "Feature",
  "properties": {
    "date:inception_lower": "1980-01-01",
    "date:inception_upper": "1980-01-01",
    "iso:country": "GB",
    "wof:name": "B90 4BE",
    "wof:placetype": "postalcode"
  },
  "geometry": {"coordinates":[-1.813088,52.39405],"type":"Point"}
}
