{
  "type": "Feature",
  "properties": {
    "iso:country":"GB",
    "wof:name":"LA23 2FE",
    "wof:placetype":"postalcode"
},
  "geometry": {"coordinates":[-2.89360176157526,54.37403916294738],"type":"Point"}
}