{
  "type": "Feature",
  "properties": {
    "iso:country": "GB",
    "wof:name": "LA23 2FE",
    "wof:placetype": "postalcode"
  },
  "geometry": {"coordinates":[-2.893602,54.374039],"type":"Point"}
}
