{
  "type": "Feature",
  "properties": {
    "date:inception_lower": "2000-12-01",
    "date:inception_upper": "2000-12-01",
    "iso:country": "GB",
    "wof:name": "LA23 2FE",
    "wof:placetype": "postalcode"
  },
  "geometry": {"coordinates":[-2.893602,54.374039],"type":"Point"}
}
