{
  "type": "Feature",
  "properties": {
    "iso:country":"GB",
    "wof:name":"LS12 1DS",
    "wof:placetype":"postalcode"
},
  "geometry": {"coordinates":[-1.57368867636947,53.79042493786559],"type":"Point"}
}