{
  "type": "Feature",
  "properties": {
    "iso:country":"GB",
    "wof:name":"L39 0EF",
    "wof:placetype":"postalcode"
},
  "geometry": {"coordinates":[-2.87103979156145,53.53004720973293],"type":"Point"}
}