{
  "type": "Feature",
  "properties": {
    "iso:country":"GB",
    "wof:name":"BH13 7LS",
    "wof:placetype":"postalcode"
},
  "geometry": {"coordinates":[-1.92145094598804,50.70589418520079],"type":"Point"}
}