{
  "type": "Feature",
  "properties": {
    "iso:country":"GB",
    "wof:name":"NR31 6DB",
    "wof:placetype":"postalcode"
},
  "geometry": {"coordinates":[1.72412687842904,52.56540928683562],"type":"Point"}
}