{
  "type": "Feature",
  "properties": {
    "date:inception_lower":"1980-01-01",
    "date:inception_upper":"1980-01-31",
    "iso:country":"GB",
    "wof:name":"NR31 6DB",
    "wof:placetype":"postalcode"
},
  "geometry": {"coordinates":[1.724127,52.565409],"type":"Point"}
}