{
  "type": "Feature",
  "properties": {
    "iso:country": "GB",
    "wof:name": "NP20 9HP",
    "wof:placetype": "postalcode"
  },
  "geometry": {"coordinates":[-2.997047,51.591272],"type":"Point"}
}
