{
  "type": "Feature",
  "properties": {
    "iso:country":"GB",
    "wof:name":"DD5 2RW",
    "wof:placetype":"postalcode"
},
  "geometry": {"coordinates":[-2.86443422641084,56.46848663369553],"type":"Point"}
}