{
  "type": "Feature",
  "properties": {
    "date:inception_lower": "1980-01-01",
    "date:inception_upper": "1980-01-01",
    "iso:country": "GB",
    "wof:name": "DD5 2RW",
    "wof:placetype": "postalcode"
  },
  "geometry": {"coordinates":[-2.864434,56.468487],"type":"Point"}
}
