{
  "type": "Feature",
  "properties": {
    "iso:country": "GB",
    "wof:name": "AL1 3TW",
    "wof:placetype": "postalcode"
  },
  "geometry": {"coordinates":[-0.331085,51.750927],"type":"Point"}
}
