{
  "type": "Feature",
  "properties": {
    "iso:country":"GB",
    "wof:name":"BB7 2QL",
    "wof:placetype":"postalcode"
},
  "geometry": {"coordinates":[-2.40591463543427,53.86290105548547],"type":"Point"}
}