{
  "type": "Feature",
  "properties": {
    "iso:country":"GB",
    "wof:name":"SW1V 2HJ",
    "wof:placetype":"postalcode"
},
  "geometry": {"coordinates":[-0.13154726321728,51.48932995702743],"type":"Point"}
}