{
  "type": "Feature",
  "properties": {
    "iso:country": "GB",
    "wof:name": "SW1V 2HJ",
    "wof:placetype": "postalcode"
  },
  "geometry": {"coordinates":[-0.131547,51.48933],"type":"Point"}
}
