{
  "type": "Feature",
  "properties": {
    "date:inception_lower":"1987-04-01",
    "date:inception_upper":"1987-04-30",
    "iso:country":"GB",
    "wof:name":"SW1V 2HJ",
    "wof:placetype":"postalcode"
},
  "geometry": {"coordinates":[-0.131547,51.48933],"type":"Point"}
}