{
  "type": "Feature",
  "properties": {
    "date:inception_lower": "1990-07-01",
    "date:inception_upper": "1990-07-01",
    "iso:country": "GB",
    "wof:name": "NR13 3RJ",
    "wof:placetype": "postalcode"
  },
  "geometry": {"coordinates":[1.554361,52.640798],"type":"Point"}
}
