{
  "type": "Feature",
  "properties": {
    "iso:country": "GB",
    "wof:name": "LE9 6TP",
    "wof:placetype": "postalcode"
  },
  "geometry": {"coordinates":[-1.237524,52.536375],"type":"Point"}
}
