{
  "type": "Feature",
  "properties": {
    "date:inception_lower": "2019-11-01",
    "date:inception_upper": "2019-11-01",
    "iso:country": "GB",
    "wof:name": "IP25 6FT",
    "wof:placetype": "postalcode"
  },
  "geometry": {"coordinates":[0.858951,52.567597],"type":"Point"}
}
