{
  "type": "Feature",
  "properties": {
    "iso:country": "GB",
    "wof:name": "IP25 6FT",
    "wof:placetype": "postalcode"
  },
  "geometry": {"coordinates":[0.858951,52.567597],"type":"Point"}
}
