{
  "type": "Feature",
  "properties": {
    "date:inception_lower": "1989-04-01",
    "date:inception_upper": "1989-04-01",
    "iso:country": "GB",
    "wof:name": "FK8 3AX",
    "wof:placetype": "postalcode"
  },
  "geometry": {"coordinates":[-4.080965,56.124883],"type":"Point"}
}
