{
  "type": "Feature",
  "properties": {
    "iso:country": "GB",
    "wof:name": "KY7 6LW",
    "wof:placetype": "postalcode"
  },
  "geometry": {"coordinates":[-3.077562,56.231382],"type":"Point"}
}
