{
  "type": "Feature",
  "properties": {
    "iso:country": "GB",
    "wof:name": "KY7 6LW",
    "wof:placetype": "postalcode"
  },
  "geometry": {"coordinates":[-3.07827,56.234127],"type":"Point"}
}
