{
  "type": "Feature",
  "properties": {
    "iso:country":"GB",
    "wof:name":"TS4 2TF",
    "wof:placetype":"postalcode"
},
  "geometry": {"coordinates":[-1.22739513536159,54.55560166844143],"type":"Point"}
}