{
  "type": "Feature",
  "properties": {
    "iso:country": "GB",
    "wof:name": "NW6 3BN",
    "wof:placetype": "postalcode"
  },
  "geometry": {"coordinates":[-0.18482,51.546837],"type":"Point"}
}
