{
  "type": "Feature",
  "properties": {
    "iso:country":"GB",
    "wof:name":"NW6 3BN",
    "wof:placetype":"postalcode"
},
  "geometry": {"coordinates":[-0.18482033720217,51.54683708860493],"type":"Point"}
}