{
  "type": "Feature",
  "properties": {
    "date:inception_lower": "1996-12-01",
    "date:inception_upper": "1996-12-01",
    "iso:country": "GB",
    "wof:name": "M28 2ED",
    "wof:placetype": "postalcode"
  },
  "geometry": {"coordinates":[-2.375733,53.497522],"type":"Point"}
}
