{
  "type": "Feature",
  "properties": {
    "iso:country":"GB",
    "wof:name":"SA70 8BB",
    "wof:placetype":"postalcode"
},
  "geometry": {"coordinates":[-4.70526021903635,51.67797661534524],"type":"Point"}
}