{
  "type": "Feature",
  "properties": {
    "date:inception_lower":"2014-10-01",
    "date:inception_upper":"2014-10-31",
    "iso:country":"GB",
    "wof:name":"SA70 8BB",
    "wof:placetype":"postalcode"
},
  "geometry": {"coordinates":[-4.70526,51.677977],"type":"Point"}
}