{
  "type": "Feature",
  "properties": {
    "iso:country": "GB",
    "wof:name": "SA70 8BB",
    "wof:placetype": "postalcode"
  },
  "geometry": {"coordinates":[-4.70526,51.677977],"type":"Point"}
}
