{
  "type": "Feature",
  "properties": {
    "iso:country": "GB",
    "wof:name": "OX29 8FT",
    "wof:placetype": "postalcode"
  },
  "geometry": {"coordinates":[-1.402957,51.822384],"type":"Point"}
}
