{
  "type": "Feature",
  "properties": {
    "iso:country":"GB",
    "wof:name":"TA2 6DN",
    "wof:placetype":"postalcode"
},
  "geometry": {"coordinates":[-3.11124783729617,51.03497337382019],"type":"Point"}
}