{
  "type": "Feature",
  "properties": {
    "iso:country":"GB",
    "wof:name":"RM1 4RT",
    "wof:placetype":"postalcode"
},
  "geometry": {"coordinates":[0.18293469235919,51.60193732558896],"type":"Point"}
}