{
  "type": "Feature",
  "properties": {
    "iso:country":"GB",
    "wof:name":"PA10 2JR",
    "wof:placetype":"postalcode"
},
  "geometry": {"coordinates":[-4.55597999471323,55.8377108562634],"type":"Point"}
}