{
  "type": "Feature",
  "properties": {
    "iso:country":"GB",
    "wof:name":"WF9 3QN",
    "wof:placetype":"postalcode"
},
  "geometry": {"coordinates":[-1.31474960137711,53.5895950543764],"type":"Point"}
}