{
  "type": "Feature",
  "properties": {
    "iso:country": "GB",
    "wof:name": "WF9 3QN",
    "wof:placetype": "postalcode"
  },
  "geometry": {"coordinates":[-1.314705,53.589541],"type":"Point"}
}
