{
  "type": "Feature",
  "properties": {
    "iso:country":"GB",
    "wof:name":"SS0 7LE",
    "wof:placetype":"postalcode"
},
  "geometry": {"coordinates":[0.69792453276171,51.53875729275381],"type":"Point"}
}