{
  "type": "Feature",
  "properties": {
    "iso:country": "GB",
    "wof:name": "SS0 7LE",
    "wof:placetype": "postalcode"
  },
  "geometry": {"coordinates":[0.697925,51.538757],"type":"Point"}
}
