{
  "type": "Feature",
  "properties": {
    "iso:country":"GB",
    "wof:name":"LD3 9EL",
    "wof:placetype":"postalcode"
},
  "geometry": {"coordinates":[-3.39354508259,51.9555944983276],"type":"Point"}
}