{
  "type": "Feature",
  "properties": {
    "iso:country": "GB",
    "wof:name": "LD3 9EL",
    "wof:placetype": "postalcode"
  },
  "geometry": {"coordinates":[-3.393545,51.955594],"type":"Point"}
}
