{
  "type": "Feature",
  "properties": {
    "iso:country": "GB",
    "wof:name": "WR8 0QE",
    "wof:placetype": "postalcode"
  },
  "geometry": {"coordinates":[-2.212703,52.060616],"type":"Point"}
}
