{
  "type": "Feature",
  "properties": {
    "iso:country":"GB",
    "wof:name":"CT1 2LU",
    "wof:placetype":"postalcode"
},
  "geometry": {"coordinates":[1.08515073117807,51.28096814024516],"type":"Point"}
}