{
  "type": "Feature",
  "properties": {
    "date:inception_lower": "1995-12-01",
    "date:inception_upper": "1995-12-01",
    "iso:country": "GB",
    "wof:name": "SE19 1SZ",
    "wof:placetype": "postalcode"
  },
  "geometry": {"coordinates":[-0.078259,51.421941],"type":"Point"}
}
