{
  "type": "Feature",
  "properties": {
    "iso:country":"GB",
    "wof:name":"SE19 1SZ",
    "wof:placetype":"postalcode"
},
  "geometry": {"coordinates":[-0.07825948208957,51.42194108176368],"type":"Point"}
}