{
  "type": "Feature",
  "properties": {
    "iso:country": "GB",
    "wof:name": "SE19 1SZ",
    "wof:placetype": "postalcode"
  },
  "geometry": {"coordinates":[-0.078259,51.421941],"type":"Point"}
}
