{
  "type": "Feature",
  "properties": {
    "iso:country": "GB",
    "wof:name": "EH20 9BW",
    "wof:placetype": "postalcode"
  },
  "geometry": {"coordinates":[-3.150964,55.876387],"type":"Point"}
}
