{
  "type": "Feature",
  "properties": {
    "iso:country":"GB",
    "wof:name":"SO30 3NE",
    "wof:placetype":"postalcode"
},
  "geometry": {"coordinates":[-1.34180186995805,50.92950048502548],"type":"Point"}
}