{
  "type": "Feature",
  "properties": {
    "date:inception_lower": "1995-01-01",
    "date:inception_upper": "1995-01-01",
    "iso:country": "GB",
    "wof:name": "SO30 3NE",
    "wof:placetype": "postalcode"
  },
  "geometry": {"coordinates":[-1.341802,50.9295],"type":"Point"}
}
