{
  "type": "Feature",
  "properties": {
    "date:inception_lower": "1990-02-01",
    "date:inception_upper": "1990-02-01",
    "iso:country": "GB",
    "wof:name": "M16 8GU",
    "wof:placetype": "postalcode"
  },
  "geometry": {"coordinates":[-2.246388,53.446957],"type":"Point"}
}
