{
  "type": "Feature",
  "properties": {
    "date:inception_lower": "2009-10-01",
    "date:inception_upper": "2009-10-01",
    "iso:country": "GB",
    "wof:name": "BS1 3ES",
    "wof:placetype": "postalcode"
  },
  "geometry": {"coordinates":[-2.592169,51.459419],"type":"Point"}
}
