{
  "type": "Feature",
  "properties": {
    "iso:country":"GB",
    "wof:name":"NW8 0PP",
    "wof:placetype":"postalcode"
},
  "geometry": {"coordinates":[-0.18394772222258,51.53325402252576],"type":"Point"}
}