{
  "type": "Feature",
  "properties": {
    "iso:country":"GB",
    "wof:name":"SO51 6AL",
    "wof:placetype":"postalcode"
},
  "geometry": {"coordinates":[-1.54745097530584,50.94790531225063],"type":"Point"}
}