{
  "type": "Feature",
  "properties": {
    "date:inception_lower": "1980-01-01",
    "date:inception_upper": "1980-01-01",
    "iso:country": "GB",
    "wof:name": "RH20 3JW",
    "wof:placetype": "postalcode"
  },
  "geometry": {"coordinates":[-0.426276,50.923441],"type":"Point"}
}
