{
  "type": "Feature",
  "properties": {
    "iso:country": "GB",
    "wof:name": "PH2 0RQ",
    "wof:placetype": "postalcode"
  },
  "geometry": {"coordinates":[-3.58834,56.312867],"type":"Point"}
}
