{
  "type": "Feature",
  "properties": {
    "iso:country":"GB",
    "wof:name":"SK2 6BA",
    "wof:placetype":"postalcode"
},
  "geometry": {"coordinates":[-2.12881968523497,53.39441489176759],"type":"Point"}
}