{
  "type": "Feature",
  "properties": {
    "iso:country":"GB",
    "wof:name":"SL1 2PA",
    "wof:placetype":"postalcode"
},
  "geometry": {"coordinates":[-0.61666516484674,51.50638716986617],"type":"Point"}
}