{
  "type": "Feature",
  "properties": {
    "iso:country": "GB",
    "wof:name": "DN4 9LU",
    "wof:placetype": "postalcode"
  },
  "geometry": {"coordinates":[-1.182092,53.498896],"type":"Point"}
}
