{
  "type": "Feature",
  "properties": {
    "date:inception_lower": "1994-05-01",
    "date:inception_upper": "1994-05-01",
    "iso:country": "GB",
    "wof:name": "TS9 5PW",
    "wof:placetype": "postalcode"
  },
  "geometry": {"coordinates":[-1.189486,54.476581],"type":"Point"}
}
