{
  "type": "Feature",
  "properties": {
    "iso:country":"GB",
    "wof:name":"TS9 5PW",
    "wof:placetype":"postalcode"
},
  "geometry": {"coordinates":[-1.18948555344246,54.47658120828454],"type":"Point"}
}