{
  "type": "Feature",
  "properties": {
    "iso:country":"GB",
    "wof:name":"NR2 3UE",
    "wof:placetype":"postalcode"
},
  "geometry": {"coordinates":[1.25999419880851,52.6346563585426],"type":"Point"}
}