{
  "type": "Feature",
  "properties": {
    "date:inception_lower": "1980-01-01",
    "date:inception_upper": "1980-01-01",
    "iso:country": "GB",
    "wof:name": "N14 4AB",
    "wof:placetype": "postalcode"
  },
  "geometry": {"coordinates":[-0.142985,51.642302],"type":"Point"}
}
