{
  "type": "Feature",
  "properties": {
    "iso:country":"GB",
    "wof:name":"N14 4AB",
    "wof:placetype":"postalcode"
},
  "geometry": {"coordinates":[-0.14298483328233,51.64230203485808],"type":"Point"}
}