{
  "type": "Feature",
  "properties": {
    "iso:country": "GB",
    "wof:name": "TR8 4JZ",
    "wof:placetype": "postalcode"
  },
  "geometry": {"coordinates":[-5.000766,50.435483],"type":"Point"}
}
