{
  "type": "Feature",
  "properties": {
    "iso:country":"GB",
    "wof:name":"TR8 4JZ",
    "wof:placetype":"postalcode"
},
  "geometry": {"coordinates":[-5.00076610891478,50.43548258823667],"type":"Point"}
}