{
  "type": "Feature",
  "properties": {
    "date:inception_lower": "1980-01-01",
    "date:inception_upper": "1980-01-01",
    "iso:country": "GB",
    "wof:name": "CV1 3EQ",
    "wof:placetype": "postalcode"
  },
  "geometry": {"coordinates":[-1.521061,52.407379],"type":"Point"}
}
