{
  "type": "Feature",
  "properties": {
    "iso:country":"GB",
    "wof:name":"CV1 3EQ",
    "wof:placetype":"postalcode"
},
  "geometry": {"coordinates":[-1.52106085490109,52.40737885206521],"type":"Point"}
}