{
  "type": "Feature",
  "properties": {
    "iso:country":"GB",
    "wof:name":"KT18 7RL",
    "wof:placetype":"postalcode"
},
  "geometry": {"coordinates":[-0.27161065228672,51.33273326666184],"type":"Point"}
}