{
  "type": "Feature",
  "properties": {
    "date:inception_lower":"1980-01-01",
    "date:inception_upper":"1980-01-31",
    "iso:country":"GB",
    "wof:name":"ML7 5NL",
    "wof:placetype":"postalcode"
},
  "geometry": {"coordinates":[-3.754664,55.85977],"type":"Point"}
}