{
  "type": "Feature",
  "properties": {
    "iso:country":"GB",
    "wof:name":"ML7 5NL",
    "wof:placetype":"postalcode"
},
  "geometry": {"coordinates":[-3.75466437424787,55.85976973841653],"type":"Point"}
}