{
  "type": "Feature",
  "properties": {
    "iso:country": "GB",
    "wof:name": "ML7 5NL",
    "wof:placetype": "postalcode"
  },
  "geometry": {"coordinates":[-3.754664,55.85977],"type":"Point"}
}
