{
  "type": "Feature",
  "properties": {
    "date:inception_lower": "2022-12-01",
    "date:inception_upper": "2022-12-01",
    "iso:country": "GB",
    "wof:name": "DN14 9GE",
    "wof:placetype": "postalcode"
  },
  "geometry": {"coordinates":[-1.022578,53.713785],"type":"Point"}
}
