{
  "type": "Feature",
  "properties": {
    "date:inception_lower": "1990-07-01",
    "date:inception_upper": "1990-07-01",
    "iso:country": "GB",
    "wof:name": "SW17 9SZ",
    "wof:placetype": "postalcode"
  },
  "geometry": {"coordinates":[-0.158607,51.425542],"type":"Point"}
}
