{
  "type": "Feature",
  "properties": {
    "iso:country": "GB",
    "wof:name": "RH13 0NH",
    "wof:placetype": "postalcode"
  },
  "geometry": {"coordinates":[-0.39833,51.037421],"type":"Point"}
}
