{
  "type": "Feature",
  "properties": {
    "iso:country":"GB",
    "wof:name":"PE3 7JX",
    "wof:placetype":"postalcode"
},
  "geometry": {"coordinates":[-0.27252051542947,52.59033951329618],"type":"Point"}
}