{
  "type": "Feature",
  "properties": {
    "date:inception_lower": "1980-01-01",
    "date:inception_upper": "1980-01-01",
    "iso:country": "GB",
    "wof:name": "PE3 7JX",
    "wof:placetype": "postalcode"
  },
  "geometry": {"coordinates":[-0.27252,52.59034],"type":"Point"}
}
