{
  "type": "Feature",
  "properties": {
    "date:inception_lower":"1992-01-01",
    "date:inception_upper":"1992-01-31",
    "iso:country":"GB",
    "wof:name":"HP7 9QQ",
    "wof:placetype":"postalcode"
},
  "geometry": {"coordinates":[-0.57038,51.664244],"type":"Point"}
}