{
  "type": "Feature",
  "properties": {
    "iso:country": "GB",
    "wof:name": "SP10 9JN",
    "wof:placetype": "postalcode"
  },
  "geometry": {"coordinates":[-1.481728,51.206324],"type":"Point"}
}
