{
  "type": "Feature",
  "properties": {
    "iso:country":"GB",
    "wof:name":"ML12 6AP",
    "wof:placetype":"postalcode"
},
  "geometry": {"coordinates":[-3.51794812736716,55.62632007371641],"type":"Point"}
}