{
  "type": "Feature",
  "properties": {
    "date:inception_lower":"2004-11-01",
    "date:inception_upper":"2004-11-30",
    "iso:country":"GB",
    "wof:name":"TN24 9RZ",
    "wof:placetype":"postalcode"
},
  "geometry": {"coordinates":[0.891238,51.159001],"type":"Point"}
}