{
  "type": "Feature",
  "properties": {
    "iso:country":"GB",
    "wof:name":"E14 6HQ",
    "wof:placetype":"postalcode"
},
  "geometry": {"coordinates":[-0.0234967865059,51.51167681157358],"type":"Point"}
}