{
  "type": "Feature",
  "properties": {
    "iso:country":"GB",
    "wof:name":"SK7 6DD",
    "wof:placetype":"postalcode"
},
  "geometry": {"coordinates":[-2.1117690856044,53.37236512554271],"type":"Point"}
}