{
  "type": "Feature",
  "properties": {
    "date:inception_lower": "1983-03-01",
    "date:inception_upper": "1983-03-01",
    "iso:country": "GB",
    "wof:name": "SK7 6DD",
    "wof:placetype": "postalcode"
  },
  "geometry": {"coordinates":[-2.111768,53.372382],"type":"Point"}
}
