{
  "type": "Feature",
  "properties": {
    "iso:country": "GB",
    "wof:name": "SK7 6DD",
    "wof:placetype": "postalcode"
  },
  "geometry": {"coordinates":[-2.111409,53.37276],"type":"Point"}
}
