{
  "type": "Feature",
  "properties": {
    "date:inception_lower":"1980-01-01",
    "date:inception_upper":"1980-01-31",
    "iso:country":"GB",
    "wof:name":"TN3 9SQ",
    "wof:placetype":"postalcode"
},
  "geometry": {"coordinates":[0.183438,51.110506],"type":"Point"}
}