{
  "type": "Feature",
  "properties": {
    "iso:country": "GB",
    "wof:name": "SK12 1GN",
    "wof:placetype": "postalcode"
  },
  "geometry": {"coordinates":[-2.135928,53.350793],"type":"Point"}
}
