{
  "type": "Feature",
  "properties": {
    "iso:country":"GB",
    "wof:name":"SK12 1GN",
    "wof:placetype":"postalcode"
},
  "geometry": {"coordinates":[-2.13592863367875,53.3507763030582],"type":"Point"}
}