{
  "type": "Feature",
  "properties": {
    "iso:country": "GB",
    "wof:name": "SS5 4HA",
    "wof:placetype": "postalcode"
  },
  "geometry": {"coordinates":[0.669459,51.596689],"type":"Point"}
}
