{
  "type": "Feature",
  "properties": {
    "iso:country":"GB",
    "wof:name":"IP22 4NP",
    "wof:placetype":"postalcode"
},
  "geometry": {"coordinates":[1.11920938932218,52.37856837879259],"type":"Point"}
}