{
  "type": "Feature",
  "properties": {
    "iso:country": "GB",
    "wof:name": "IP22 4NP",
    "wof:placetype": "postalcode"
  },
  "geometry": {"coordinates":[1.119502,52.37859],"type":"Point"}
}
