{
  "type": "Feature",
  "properties": {
    "date:inception_lower": "1980-01-01",
    "date:inception_upper": "1980-01-01",
    "iso:country": "GB",
    "wof:name": "BS2 8JJ",
    "wof:placetype": "postalcode"
  },
  "geometry": {"coordinates":[-2.592836,51.46205],"type":"Point"}
}
