{
  "type": "Feature",
  "properties": {
    "iso:country":"GB",
    "wof:name":"PA3 2JJ",
    "wof:placetype":"postalcode"
},
  "geometry": {"coordinates":[-4.43080203669884,55.85120544890778],"type":"Point"}
}