{
  "type": "Feature",
  "properties": {
    "iso:country": "GB",
    "wof:name": "PA3 2JJ",
    "wof:placetype": "postalcode"
  },
  "geometry": {"coordinates":[-4.430802,55.851205],"type":"Point"}
}
