{
  "type": "Feature",
  "properties": {
    "iso:country":"GB",
    "wof:name":"WV3 0DR",
    "wof:placetype":"postalcode"
},
  "geometry": {"coordinates":[-2.13677491430733,52.57547240555825],"type":"Point"}
}