{
  "type": "Feature",
  "properties": {
    "date:inception_lower": "1980-01-01",
    "date:inception_upper": "1980-01-01",
    "iso:country": "GB",
    "wof:name": "CM7 5EG",
    "wof:placetype": "postalcode"
  },
  "geometry": {"coordinates":[0.449955,51.915962],"type":"Point"}
}
