{
  "type": "Feature",
  "properties": {
    "iso:country":"GB",
    "wof:name":"CM7 5EG",
    "wof:placetype":"postalcode"
},
  "geometry": {"coordinates":[0.44995455077267,51.9159621579898],"type":"Point"}
}