{
  "type": "Feature",
  "properties": {
    "date:inception_lower": "1980-01-01",
    "date:inception_upper": "1980-01-01",
    "iso:country": "GB",
    "wof:name": "M1 3NF",
    "wof:placetype": "postalcode"
  },
  "geometry": {"coordinates":[-2.236993,53.476602],"type":"Point"}
}
