{
  "type": "Feature",
  "properties": {
    "iso:country":"GB",
    "wof:name":"NE63 8UL",
    "wof:placetype":"postalcode"
},
  "geometry": {"coordinates":[-1.56914368028725,55.17066110313272],"type":"Point"}
}