{
  "type": "Feature",
  "properties": {
    "iso:country": "GB",
    "wof:name": "NE63 8UL",
    "wof:placetype": "postalcode"
  },
  "geometry": {"coordinates":[-1.570125,55.171236],"type":"Point"}
}
