{
  "type": "Feature",
  "properties": {
    "date:inception_lower": "1986-04-01",
    "date:inception_upper": "1986-04-01",
    "iso:country": "GB",
    "wof:name": "SN5 6HX",
    "wof:placetype": "postalcode"
  },
  "geometry": {"coordinates":[-1.846843,51.555883],"type":"Point"}
}
