{
  "type": "Feature",
  "properties": {
    "iso:country": "GB",
    "wof:name": "SK16 5DE",
    "wof:placetype": "postalcode"
  },
  "geometry": {"coordinates":[-2.059482,53.470791],"type":"Point"}
}
