{
  "type": "Feature",
  "properties": {
    "iso:country": "GB",
    "wof:name": "TN4 9TN",
    "wof:placetype": "postalcode"
  },
  "geometry": {"coordinates":[0.261314,51.137661],"type":"Point"}
}
