{
  "type": "Feature",
  "properties": {
    "iso:country":"GB",
    "wof:name":"TN4 9TN",
    "wof:placetype":"postalcode"
},
  "geometry": {"coordinates":[0.26087158670583,51.1382379919603],"type":"Point"}
}