{
  "type": "Feature",
  "properties": {
    "iso:country":"GB",
    "wof:name":"B48 7TD",
    "wof:placetype":"postalcode"
},
  "geometry": {"coordinates":[-1.96458388453011,52.35690119036982],"type":"Point"}
}