{
  "type": "Feature",
  "properties": {
    "iso:country": "GB",
    "wof:name": "DL11 6SZ",
    "wof:placetype": "postalcode"
  },
  "geometry": {"coordinates":[-1.943504,54.388552],"type":"Point"}
}
