{
  "type": "Feature",
  "properties": {
    "iso:country":"GB",
    "wof:name":"DL11 6SZ",
    "wof:placetype":"postalcode"
},
  "geometry": {"coordinates":[-1.9434519707091,54.38868561530131],"type":"Point"}
}