{
  "type": "Feature",
  "properties": {
    "iso:country":"GB",
    "wof:name":"CV35 0EL",
    "wof:placetype":"postalcode"
},
  "geometry": {"coordinates":[-1.4764891095012,52.17478967753856],"type":"Point"}
}