{
  "type": "Feature",
  "properties": {
    "date:inception_lower": "1980-01-01",
    "date:inception_upper": "1980-01-01",
    "iso:country": "GB",
    "wof:name": "CV35 0EL",
    "wof:placetype": "postalcode"
  },
  "geometry": {"coordinates":[-1.476489,52.17479],"type":"Point"}
}
