{
  "type": "Feature",
  "properties": {
    "iso:country": "GB",
    "wof:name": "PE16 6BQ",
    "wof:placetype": "postalcode"
  },
  "geometry": {"coordinates":[0.049342,52.456315],"type":"Point"}
}
