{
  "type": "Feature",
  "properties": {
    "date:inception_lower": "1985-04-01",
    "date:inception_upper": "1985-04-01",
    "iso:country": "GB",
    "wof:name": "RH2 9RS",
    "wof:placetype": "postalcode"
  },
  "geometry": {"coordinates":[-0.216961,51.243111],"type":"Point"}
}
