{
  "type": "Feature",
  "properties": {
    "iso:country":"GB",
    "wof:name":"HA4 6RG",
    "wof:placetype":"postalcode"
},
  "geometry": {"coordinates":[-0.40317772234744,51.55129792140016],"type":"Point"}
}