{
  "type": "Feature",
  "properties": {
    "date:inception_lower": "1980-01-01",
    "date:inception_upper": "1980-01-01",
    "iso:country": "GB",
    "wof:name": "B38 0DG",
    "wof:placetype": "postalcode"
  },
  "geometry": {"coordinates":[-1.909512,52.390567],"type":"Point"}
}
