{
  "type": "Feature",
  "properties": {
    "iso:country":"GB",
    "wof:name":"B38 0DG",
    "wof:placetype":"postalcode"
},
  "geometry": {"coordinates":[-1.90951220873577,52.39056696027525],"type":"Point"}
}