{
  "type": "Feature",
  "properties": {
    "iso:country": "GB",
    "wof:name": "PE36 5PN",
    "wof:placetype": "postalcode"
  },
  "geometry": {"coordinates":[0.498232,52.937741],"type":"Point"}
}
