{
  "type": "Feature",
  "properties": {
    "date:inception_lower": "2005-05-01",
    "date:inception_upper": "2005-05-01",
    "iso:country": "GB",
    "wof:name": "PE36 5PN",
    "wof:placetype": "postalcode"
  },
  "geometry": {"coordinates":[0.498232,52.937741],"type":"Point"}
}
