{
  "type": "Feature",
  "properties": {
    "iso:country":"GB",
    "wof:name":"KA30 8PJ",
    "wof:placetype":"postalcode"
},
  "geometry": {"coordinates":[-4.87599701871809,55.80583100123221],"type":"Point"}
}