{
  "type": "Feature",
  "properties": {
    "iso:country": "GB",
    "wof:name": "KA30 8PJ",
    "wof:placetype": "postalcode"
  },
  "geometry": {"coordinates":[-4.875997,55.805831],"type":"Point"}
}
