{
  "type": "Feature",
  "properties": {
    "date:inception_lower": "2022-02-01",
    "date:inception_upper": "2022-02-01",
    "iso:country": "GB",
    "wof:name": "G84 7EH",
    "wof:placetype": "postalcode"
  },
  "geometry": {"coordinates":[-4.696263,55.993192],"type":"Point"}
}
