{
  "type": "Feature",
  "properties": {
    "iso:country":"GB",
    "wof:name":"BS40 8XD",
    "wof:placetype":"postalcode"
},
  "geometry": {"coordinates":[-2.6337905890826,51.35201115795023],"type":"Point"}
}