{
  "type": "Feature",
  "properties": {
    "iso:country":"GB",
    "wof:name":"LA1 2HY",
    "wof:placetype":"postalcode"
},
  "geometry": {"coordinates":[-2.80056701455996,54.06370326872788],"type":"Point"}
}