{
  "type": "Feature",
  "properties": {
    "date:inception_lower": "1980-01-01",
    "date:inception_upper": "1980-01-01",
    "iso:country": "GB",
    "wof:name": "CF48 3AY",
    "wof:placetype": "postalcode"
  },
  "geometry": {"coordinates":[-3.35861,51.763495],"type":"Point"}
}
