{
  "type": "Feature",
  "properties": {
    "iso:country":"GB",
    "wof:name":"CF48 3AY",
    "wof:placetype":"postalcode"
},
  "geometry": {"coordinates":[-3.35860997286875,51.76349474319347],"type":"Point"}
}