{
  "type": "Feature",
  "properties": {
    "date:inception_lower":"1995-01-01",
    "date:inception_upper":"1995-01-31",
    "iso:country":"GB",
    "wof:name":"SS15 6ES",
    "wof:placetype":"postalcode"
},
  "geometry": {"coordinates":[0.421326,51.580731],"type":"Point"}
}