{
  "type": "Feature",
  "properties": {
    "iso:country":"GB",
    "wof:name":"SS15 6ES",
    "wof:placetype":"postalcode"
},
  "geometry": {"coordinates":[0.42132565323605,51.58073110728438],"type":"Point"}
}