{
  "type": "Feature",
  "properties": {
    "iso:country": "GB",
    "wof:name": "BL3 6DG",
    "wof:placetype": "postalcode"
  },
  "geometry": {"coordinates":[-2.431852,53.571406],"type":"Point"}
}
