{
  "type": "Feature",
  "properties": {
    "iso:country":"GB",
    "wof:name":"CT19 5JU",
    "wof:placetype":"postalcode"
},
  "geometry": {"coordinates":[1.15916287730722,51.08589986072933],"type":"Point"}
}