{
  "type": "Feature",
  "properties": {
    "iso:country": "GB",
    "wof:name": "CT19 5JU",
    "wof:placetype": "postalcode"
  },
  "geometry": {"coordinates":[1.159163,51.0859],"type":"Point"}
}
