{
  "type": "Feature",
  "properties": {
    "iso:country": "GB",
    "wof:name": "NN17 1DQ",
    "wof:placetype": "postalcode"
  },
  "geometry": {"coordinates":[-0.688621,52.501035],"type":"Point"}
}
