{
  "type": "Feature",
  "properties": {
    "iso:country":"GB",
    "wof:name":"ME5 8YL",
    "wof:placetype":"postalcode"
},
  "geometry": {"coordinates":[0.53862552345313,51.34555387533532],"type":"Point"}
}