{
  "type": "Feature",
  "properties": {
    "iso:country": "GB",
    "wof:name": "ME5 8YL",
    "wof:placetype": "postalcode"
  },
  "geometry": {"coordinates":[0.538626,51.345554],"type":"Point"}
}
