{
  "type": "Feature",
  "properties": {
    "date:inception_lower": "2022-03-01",
    "date:inception_upper": "2022-03-01",
    "iso:country": "GB",
    "wof:name": "B90 1UX",
    "wof:placetype": "postalcode"
  },
  "geometry": {"coordinates":[-1.855659,52.383372],"type":"Point"}
}
