{
  "type": "Feature",
  "properties": {
    "iso:country": "GB",
    "wof:name": "WV12 4SG",
    "wof:placetype": "postalcode"
  },
  "geometry": {"coordinates":[-2.04728,52.603159],"type":"Point"}
}
