{
  "type": "Feature",
  "properties": {
    "iso:country":"GB",
    "wof:name":"WV12 4SG",
    "wof:placetype":"postalcode"
},
  "geometry": {"coordinates":[-2.04727981869358,52.60315879109315],"type":"Point"}
}