{
  "type": "Feature",
  "properties": {
    "iso:country":"GB",
    "wof:name":"AB21 0HH",
    "wof:placetype":"postalcode"
},
  "geometry": {"coordinates":[-2.22580718326538,57.21094637506231],"type":"Point"}
}