{
  "type": "Feature",
  "properties": {
    "iso:country": "GB",
    "wof:name": "AB21 0HH",
    "wof:placetype": "postalcode"
  },
  "geometry": {"coordinates":[-2.225807,57.210946],"type":"Point"}
}
