{
  "type": "Feature",
  "properties": {
    "iso:country": "GB",
    "wof:name": "GU7 3AZ",
    "wof:placetype": "postalcode"
  },
  "geometry": {"coordinates":[-0.604936,51.196186],"type":"Point"}
}
