{
  "type": "Feature",
  "properties": {
    "iso:country": "GB",
    "wof:name": "SA61 2TS",
    "wof:placetype": "postalcode"
  },
  "geometry": {"coordinates":[-4.984276,51.802057],"type":"Point"}
}
