{
  "type": "Feature",
  "properties": {
    "iso:country":"GB",
    "wof:name":"SA61 2TS",
    "wof:placetype":"postalcode"
},
  "geometry": {"coordinates":[-4.98427585237279,51.80205729920336],"type":"Point"}
}