{
  "type": "Feature",
  "properties": {
    "iso:country": "GB",
    "wof:name": "YO26 5QZ",
    "wof:placetype": "postalcode"
  },
  "geometry": {"coordinates":[-1.135898,53.96812],"type":"Point"}
}
