{
  "type": "Feature",
  "properties": {
    "iso:country": "GB",
    "wof:name": "OX15 6EZ",
    "wof:placetype": "postalcode"
  },
  "geometry": {"coordinates":[-1.420683,52.063578],"type":"Point"}
}
