{
  "type": "Feature",
  "properties": {
    "iso:country":"GB",
    "wof:name":"CR4 2EB",
    "wof:placetype":"postalcode"
},
  "geometry": {"coordinates":[-0.1495417235272,51.41450026267218],"type":"Point"}
}