{
  "type": "Feature",
  "properties": {
    "iso:country":"GB",
    "wof:name":"EX37 9BE",
    "wof:placetype":"postalcode"
},
  "geometry": {"coordinates":[-3.97609605297314,50.97880288733003],"type":"Point"}
}