{
  "type": "Feature",
  "properties": {
    "iso:country":"GB",
    "wof:name":"TA3 7DT",
    "wof:placetype":"postalcode"
},
  "geometry": {"coordinates":[-3.13819628563252,50.94092987870708],"type":"Point"}
}