{
  "type": "Feature",
  "properties": {
    "iso:country": "GB",
    "wof:name": "DG7 2LE",
    "wof:placetype": "postalcode"
  },
  "geometry": {"coordinates":[-4.189788,54.885144],"type":"Point"}
}
