{
  "type": "Feature",
  "properties": {
    "date:inception_lower": "1983-03-01",
    "date:inception_upper": "1983-03-01",
    "iso:country": "GB",
    "wof:name": "DG7 2LE",
    "wof:placetype": "postalcode"
  },
  "geometry": {"coordinates":[-4.189788,54.885144],"type":"Point"}
}
