{
  "type": "Feature",
  "properties": {
    "iso:country": "GB",
    "wof:name": "GU6 8PA",
    "wof:placetype": "postalcode"
  },
  "geometry": {"coordinates":[-0.503784,51.151331],"type":"Point"}
}
