{
  "type": "Feature",
  "properties": {
    "iso:country":"GB",
    "wof:name":"NG8 5PS",
    "wof:placetype":"postalcode"
},
  "geometry": {"coordinates":[-1.20696199771133,52.97756203060715],"type":"Point"}
}