{
  "type": "Feature",
  "properties": {
    "iso:country": "GB",
    "wof:name": "HA5 5LX",
    "wof:placetype": "postalcode"
  },
  "geometry": {"coordinates":[-0.381734,51.593639],"type":"Point"}
}
