{
  "type": "Feature",
  "properties": {
    "iso:country":"GB",
    "wof:name":"SG6 3QX",
    "wof:placetype":"postalcode"
},
  "geometry": {"coordinates":[-0.2376887918519,51.97604242123704],"type":"Point"}
}