{
  "type": "Feature",
  "properties": {
    "iso:country":"GB",
    "wof:name":"HU16 5EZ",
    "wof:placetype":"postalcode"
},
  "geometry": {"coordinates":[-0.42370936124819,53.7742709887479],"type":"Point"}
}