{
  "type": "Feature",
  "properties": {
    "iso:country":"GB",
    "wof:name":"WD3 1NB",
    "wof:placetype":"postalcode"
},
  "geometry": {"coordinates":[-0.47219335644694,51.63309128726532],"type":"Point"}
}