{
  "type": "Feature",
  "properties": {
    "iso:country":"GB",
    "wof:name":"L19 0PS",
    "wof:placetype":"postalcode"
},
  "geometry": {"coordinates":[-2.91862946683147,53.35875946721121],"type":"Point"}
}