{
  "type": "Feature",
  "properties": {
    "date:inception_lower": "1991-09-01",
    "date:inception_upper": "1991-09-01",
    "iso:country": "GB",
    "wof:name": "BN9 9YA",
    "wof:placetype": "postalcode"
  },
  "geometry": {"coordinates":[0.037514,50.794387],"type":"Point"}
}
