{
  "type": "Feature",
  "properties": {
    "iso:country":"GB",
    "wof:name":"BN9 9YA",
    "wof:placetype":"postalcode"
},
  "geometry": {"coordinates":[0.03751388885188,50.79438665681828],"type":"Point"}
}