{
  "type": "Feature",
  "properties": {
    "iso:country": "GB",
    "wof:name": "WR9 0QE",
    "wof:placetype": "postalcode"
  },
  "geometry": {"coordinates":[-2.167748,52.283279],"type":"Point"}
}
