{
  "type": "Feature",
  "properties": {
    "date:inception_lower":"1986-07-01",
    "date:inception_upper":"1986-07-31",
    "iso:country":"GB",
    "wof:name":"WR9 0QE",
    "wof:placetype":"postalcode"
},
  "geometry": {"coordinates":[-2.167748,52.283279],"type":"Point"}
}