{
  "type": "Feature",
  "properties": {
    "iso:country": "GB",
    "wof:name": "EX17 5AX",
    "wof:placetype": "postalcode"
  },
  "geometry": {"coordinates":[-3.867852,50.760462],"type":"Point"}
}
