{
  "type": "Feature",
  "properties": {
    "iso:country":"GB",
    "wof:name":"GU8 6EN",
    "wof:placetype":"postalcode"
},
  "geometry": {"coordinates":[-0.70578799961344,51.18358601990801],"type":"Point"}
}