{
  "type": "Feature",
  "properties": {
    "date:inception_lower": "1980-01-01",
    "date:inception_upper": "1980-01-01",
    "iso:country": "GB",
    "wof:name": "GU8 6EN",
    "wof:placetype": "postalcode"
  },
  "geometry": {"coordinates":[-0.705788,51.183586],"type":"Point"}
}
