{
  "type": "Feature",
  "properties": {
    "iso:country":"GB",
    "wof:name":"DE22 4ND",
    "wof:placetype":"postalcode"
},
  "geometry": {"coordinates":[-1.5463205903258,52.93973373589412],"type":"Point"}
}