{
  "type": "Feature",
  "properties": {
    "iso:country":"GB",
    "wof:name":"W1T 5HA",
    "wof:placetype":"postalcode"
},
  "geometry": {"coordinates":[-0.13751500314317,51.52279613370834],"type":"Point"}
}