{
  "type": "Feature",
  "properties": {
    "iso:country": "GB",
    "wof:name": "BA14 6FR",
    "wof:placetype": "postalcode"
  },
  "geometry": {"coordinates":[-2.150976,51.340367],"type":"Point"}
}
