{
  "type": "Feature",
  "properties": {
    "date:inception_lower": "1980-01-01",
    "date:inception_upper": "1980-01-01",
    "iso:country": "GB",
    "wof:name": "IV9 8RN",
    "wof:placetype": "postalcode"
  },
  "geometry": {"coordinates":[-4.188755,57.567218],"type":"Point"}
}
