{
  "type": "Feature",
  "properties": {
    "iso:country":"GB",
    "wof:name":"IV9 8RN",
    "wof:placetype":"postalcode"
},
  "geometry": {"coordinates":[-4.18875496718672,57.56721755776245],"type":"Point"}
}