{
  "type": "Feature",
  "properties": {
    "iso:country": "GB",
    "wof:name": "IV9 8RN",
    "wof:placetype": "postalcode"
  },
  "geometry": {"coordinates":[-4.188755,57.567218],"type":"Point"}
}
