{
  "type": "Feature",
  "properties": {
    "iso:country": "GB",
    "wof:name": "RG17 8YZ",
    "wof:placetype": "postalcode"
  },
  "geometry": {"coordinates":[-1.526278,51.509548],"type":"Point"}
}
