{
  "type": "Feature",
  "properties": {
    "date:inception_lower": "2010-10-01",
    "date:inception_upper": "2010-10-01",
    "iso:country": "GB",
    "wof:name": "DT11 7GF",
    "wof:placetype": "postalcode"
  },
  "geometry": {"coordinates":[-2.151223,50.864838],"type":"Point"}
}
