{
  "type": "Feature",
  "properties": {
    "iso:country":"GB",
    "wof:name":"DT11 7GF",
    "wof:placetype":"postalcode"
},
  "geometry": {"coordinates":[-2.1512231218278,50.86483777191895],"type":"Point"}
}