{
  "type": "Feature",
  "properties": {
    "date:inception_lower":"2001-12-01",
    "date:inception_upper":"2001-12-31",
    "iso:country":"GB",
    "wof:name":"MK10 9FU",
    "wof:placetype":"postalcode"
},
  "geometry": {"coordinates":[-0.703797,52.033624],"type":"Point"}
}