{
  "type": "Feature",
  "properties": {
    "iso:country":"GB",
    "wof:name":"MK10 9FU",
    "wof:placetype":"postalcode"
},
  "geometry": {"coordinates":[-0.70379678941866,52.0336236912246],"type":"Point"}
}