{
  "type": "Feature",
  "properties": {
    "iso:country":"GB",
    "wof:name":"LE14 3DS",
    "wof:placetype":"postalcode"
},
  "geometry": {"coordinates":[-0.99416676804403,52.7617810133948],"type":"Point"}
}