{
  "type": "Feature",
  "properties": {
    "iso:country": "GB",
    "wof:name": "LE14 3DS",
    "wof:placetype": "postalcode"
  },
  "geometry": {"coordinates":[-0.994167,52.761781],"type":"Point"}
}
