{
  "type": "Feature",
  "properties": {
    "iso:country":"GB",
    "wof:name":"SR8 4JZ",
    "wof:placetype":"postalcode"
},
  "geometry": {"coordinates":[-1.31332534706198,54.76302447711254],"type":"Point"}
}