{
  "type": "Feature",
  "properties": {
    "iso:country":"GB",
    "wof:name":"YO13 9QR",
    "wof:placetype":"postalcode"
},
  "geometry": {"coordinates":[-0.51869279078315,54.22022805439926],"type":"Point"}
}