{
  "type": "Feature",
  "properties": {
    "iso:country":"GB",
    "wof:name":"SO23 9BA",
    "wof:placetype":"postalcode"
},
  "geometry": {"coordinates":[-1.31043326573221,51.06174129646984],"type":"Point"}
}