{
  "type": "Feature",
  "properties": {
    "date:inception_lower":"1980-01-01",
    "date:inception_upper":"1980-01-31",
    "iso:country":"GB",
    "wof:name":"SO23 9BA",
    "wof:placetype":"postalcode"
},
  "geometry": {"coordinates":[-1.310179,51.061698],"type":"Point"}
}