{
  "type": "Feature",
  "properties": {
    "iso:country": "GB",
    "wof:name": "SA68 0TX",
    "wof:placetype": "postalcode"
  },
  "geometry": {"coordinates":[-4.820305,51.711603],"type":"Point"}
}
