{
  "type": "Feature",
  "properties": {
    "iso:country":"GB",
    "wof:name":"SA68 0TX",
    "wof:placetype":"postalcode"
},
  "geometry": {"coordinates":[-4.82030527709095,51.71160303167434],"type":"Point"}
}