{
  "type": "Feature",
  "properties": {
    "iso:country":"GB",
    "wof:name":"PO5 3LJ",
    "wof:placetype":"postalcode"
},
  "geometry": {"coordinates":[-1.0931284961562,50.78509366108186],"type":"Point"}
}