{
  "type": "Feature",
  "properties": {
    "iso:country": "GB",
    "wof:name": "SN4 0TJ",
    "wof:placetype": "postalcode"
  },
  "geometry": {"coordinates":[-1.766573,51.513887],"type":"Point"}
}
