{
  "type": "Feature",
  "properties": {
    "date:inception_lower": "2018-06-01",
    "date:inception_upper": "2018-06-01",
    "iso:country": "GB",
    "wof:name": "LA5 5BG",
    "wof:placetype": "postalcode"
  },
  "geometry": {"coordinates":[-2.770026,54.129874],"type":"Point"}
}
