{
  "type": "Feature",
  "properties": {
    "date:inception_lower": "1981-06-01",
    "date:inception_upper": "1981-06-01",
    "iso:country": "GB",
    "wof:name": "HG4 3BL",
    "wof:placetype": "postalcode"
  },
  "geometry": {"coordinates":[-1.647486,54.181289],"type":"Point"}
}
