{
  "type": "Feature",
  "properties": {
    "iso:country": "GB",
    "wof:name": "HG4 3BL",
    "wof:placetype": "postalcode"
  },
  "geometry": {"coordinates":[-1.647486,54.181289],"type":"Point"}
}
