{
  "type": "Feature",
  "properties": {
    "iso:country":"GB",
    "wof:name":"HG4 3BL",
    "wof:placetype":"postalcode"
},
  "geometry": {"coordinates":[-1.64748566384604,54.18128887088191],"type":"Point"}
}