{
  "type": "Feature",
  "properties": {
    "iso:country": "GB",
    "wof:name": "CF39 9HB",
    "wof:placetype": "postalcode"
  },
  "geometry": {"coordinates":[-3.410336,51.607986],"type":"Point"}
}
