{
  "type": "Feature",
  "properties": {
    "iso:country":"GB",
    "wof:name":"EX2 9DU",
    "wof:placetype":"postalcode"
},
  "geometry": {"coordinates":[-3.53914726331799,50.70977642651288],"type":"Point"}
}