{
  "type": "Feature",
  "properties": {
    "iso:country": "GB",
    "wof:name": "EX2 9DU",
    "wof:placetype": "postalcode"
  },
  "geometry": {"coordinates":[-3.539147,50.709776],"type":"Point"}
}
