{
  "type": "Feature",
  "properties": {
    "date:inception_lower": "1981-06-01",
    "date:inception_upper": "1981-06-01",
    "iso:country": "GB",
    "wof:name": "TN37 7JX",
    "wof:placetype": "postalcode"
  },
  "geometry": {"coordinates":[0.555961,50.879101],"type":"Point"}
}
