{
  "type": "Feature",
  "properties": {
    "iso:country":"GB",
    "wof:name":"IP17 2EZ",
    "wof:placetype":"postalcode"
},
  "geometry": {"coordinates":[1.42879126859873,52.257367241103],"type":"Point"}
}