{
  "type": "Feature",
  "properties": {
    "iso:country": "GB",
    "wof:name": "DY8 5RF",
    "wof:placetype": "postalcode"
  },
  "geometry": {"coordinates":[-2.15943,52.480876],"type":"Point"}
}
