{
  "type": "Feature",
  "properties": {
    "iso:country":"GB",
    "wof:name":"DY8 5RF",
    "wof:placetype":"postalcode"
},
  "geometry": {"coordinates":[-2.1594508222766,52.48086132747235],"type":"Point"}
}