{
  "type": "Feature",
  "properties": {
    "iso:country":"GB",
    "wof:name":"DD4 6HN",
    "wof:placetype":"postalcode"
},
  "geometry": {"coordinates":[-2.95128225033588,56.4683006593585],"type":"Point"}
}