{
  "type": "Feature",
  "properties": {
    "iso:country": "GB",
    "wof:name": "NG5 4PR",
    "wof:placetype": "postalcode"
  },
  "geometry": {"coordinates":[-1.11262,52.993283],"type":"Point"}
}
