{
  "type": "Feature",
  "properties": {
    "iso:country":"GB",
    "wof:name":"TF3 1NQ",
    "wof:placetype":"postalcode"
},
  "geometry": {"coordinates":[-2.44327664936017,52.65171892331633],"type":"Point"}
}