{
  "type": "Feature",
  "properties": {
    "iso:country":"GB",
    "wof:name":"E8 3EJ",
    "wof:placetype":"postalcode"
},
  "geometry": {"coordinates":[-0.06360233048403,51.54265082022201],"type":"Point"}
}