{
  "type": "Feature",
  "properties": {
    "iso:country":"GB",
    "wof:name":"TS4 2ES",
    "wof:placetype":"postalcode"
},
  "geometry": {"coordinates":[-1.2248383688117,54.56894011512384],"type":"Point"}
}