{
  "type": "Feature",
  "properties": {
    "iso:country":"GB",
    "wof:name":"RG12 9YU",
    "wof:placetype":"postalcode"
},
  "geometry": {"coordinates":[-0.72400122622387,51.40611978440155],"type":"Point"}
}