{
  "type": "Feature",
  "properties": {
    "date:inception_lower": "1980-01-01",
    "date:inception_upper": "1980-01-01",
    "iso:country": "GB",
    "wof:name": "PA16 7AX",
    "wof:placetype": "postalcode"
  },
  "geometry": {"coordinates":[-4.796503,55.951336],"type":"Point"}
}
