{
  "type": "Feature",
  "properties": {
    "date:inception_lower": "1980-01-01",
    "date:inception_upper": "1980-01-01",
    "iso:country": "GB",
    "wof:name": "RM10 7AN",
    "wof:placetype": "postalcode"
  },
  "geometry": {"coordinates":[0.152956,51.55125],"type":"Point"}
}
