{
  "type": "Feature",
  "properties": {
    "iso:country":"GB",
    "wof:name":"NE28 8HX",
    "wof:placetype":"postalcode"
},
  "geometry": {"coordinates":[-1.5352364248932,54.99063421467251],"type":"Point"}
}