{
  "type": "Feature",
  "properties": {
    "iso:country":"GB",
    "wof:name":"MK44 3DR",
    "wof:placetype":"postalcode"
},
  "geometry": {"coordinates":[-0.31328329097727,52.17775936702387],"type":"Point"}
}