{
  "type": "Feature",
  "properties": {
    "date:inception_lower": "1999-12-01",
    "date:inception_upper": "1999-12-01",
    "iso:country": "GB",
    "wof:name": "RG26 3PR",
    "wof:placetype": "postalcode"
  },
  "geometry": {"coordinates":[-1.138951,51.344351],"type":"Point"}
}
