{
  "type": "Feature",
  "properties": {
    "iso:country":"GB",
    "wof:name":"SA32 8AB",
    "wof:placetype":"postalcode"
},
  "geometry": {"coordinates":[-4.24881683836941,51.85796485206857],"type":"Point"}
}