{
  "type": "Feature",
  "properties": {
    "iso:country": "GB",
    "wof:name": "SA32 8AB",
    "wof:placetype": "postalcode"
  },
  "geometry": {"coordinates":[-4.248817,51.857965],"type":"Point"}
}
