{
  "type": "Feature",
  "properties": {
    "date:inception_lower": "1980-01-01",
    "date:inception_upper": "1980-01-01",
    "iso:country": "GB",
    "wof:name": "SA32 8AB",
    "wof:placetype": "postalcode"
  },
  "geometry": {"coordinates":[-4.248817,51.857965],"type":"Point"}
}
