{
  "type": "Feature",
  "properties": {
    "iso:country": "GB",
    "wof:name": "TF1 5SS",
    "wof:placetype": "postalcode"
  },
  "geometry": {"coordinates":[-2.465069,52.706419],"type":"Point"}
}
