{
  "type": "Feature",
  "properties": {
    "iso:country":"GB",
    "wof:name":"HA8 6EX",
    "wof:placetype":"postalcode"
},
  "geometry": {"coordinates":[-0.27998267995428,51.60601908552087],"type":"Point"}
}