{
  "type": "Feature",
  "properties": {
    "iso:country": "GB",
    "wof:name": "HA8 6EX",
    "wof:placetype": "postalcode"
  },
  "geometry": {"coordinates":[-0.279983,51.606019],"type":"Point"}
}
