{
  "type": "Feature",
  "properties": {
    "date:inception_lower": "2022-03-01",
    "date:inception_upper": "2022-03-01",
    "iso:country": "GB",
    "wof:name": "HP22 3AS",
    "wof:placetype": "postalcode"
  },
  "geometry": {"coordinates":[-0.767931,51.811542],"type":"Point"}
}
