{
  "type": "Feature",
  "properties": {
    "iso:country":"GB",
    "wof:name":"RM14 3UL",
    "wof:placetype":"postalcode"
},
  "geometry": {"coordinates":[0.24843000980825,51.54796627026173],"type":"Point"}
}