{
  "type": "Feature",
  "properties": {
    "iso:country": "GB",
    "wof:name": "BN21 3UX",
    "wof:placetype": "postalcode"
  },
  "geometry": {"coordinates":[0.2822,50.771174],"type":"Point"}
}
