{
  "type": "Feature",
  "properties": {
    "iso:country":"GB",
    "wof:name":"YO17 6NJ",
    "wof:placetype":"postalcode"
},
  "geometry": {"coordinates":[-0.81269692213957,54.13682985655838],"type":"Point"}
}