{
  "type": "Feature",
  "properties": {
    "iso:country": "GB",
    "wof:name": "YO17 6NJ",
    "wof:placetype": "postalcode"
  },
  "geometry": {"coordinates":[-0.812697,54.13683],"type":"Point"}
}
