{
  "type": "Feature",
  "properties": {
    "iso:country": "GB",
    "wof:name": "BD5 8LB",
    "wof:placetype": "postalcode"
  },
  "geometry": {"coordinates":[-1.740595,53.768773],"type":"Point"}
}
