{
  "type": "Feature",
  "properties": {
    "iso:country":"GB",
    "wof:name":"BD5 8LB",
    "wof:placetype":"postalcode"
},
  "geometry": {"coordinates":[-1.74059518977702,53.76877327323895],"type":"Point"}
}