{
  "type": "Feature",
  "properties": {
    "iso:country":"GB",
    "wof:name":"CO3 9UW",
    "wof:placetype":"postalcode"
},
  "geometry": {"coordinates":[0.81438581031171,51.90123368408856],"type":"Point"}
}