{
  "type": "Feature",
  "properties": {
    "iso:country":"GB",
    "wof:name":"NG23 7AT",
    "wof:placetype":"postalcode"
},
  "geometry": {"coordinates":[-0.76933634152588,53.24081954638491],"type":"Point"}
}