{
  "type": "Feature",
  "properties": {
    "date:inception_lower": "1980-01-01",
    "date:inception_upper": "1980-01-01",
    "iso:country": "GB",
    "wof:name": "LE5 5BT",
    "wof:placetype": "postalcode"
  },
  "geometry": {"coordinates":[-1.103106,52.628839],"type":"Point"}
}
