{
  "type": "Feature",
  "properties": {
    "iso:country":"GB",
    "wof:name":"LE5 5BT",
    "wof:placetype":"postalcode"
},
  "geometry": {"coordinates":[-1.10310620661998,52.62883949117403],"type":"Point"}
}