{
  "type": "Feature",
  "properties": {
    "iso:country":"GB",
    "wof:name":"AL5 5SJ",
    "wof:placetype":"postalcode"
},
  "geometry": {"coordinates":[-0.33744044111257,51.81415781234504],"type":"Point"}
}