{
  "type": "Feature",
  "properties": {
    "date:inception_lower":"1980-01-01",
    "date:inception_upper":"1980-01-31",
    "iso:country":"GB",
    "wof:name":"CM3 4BG",
    "wof:placetype":"postalcode"
},
  "geometry": {"coordinates":[0.538883,51.74166],"type":"Point"}
}