{
  "type": "Feature",
  "properties": {
    "iso:country": "GB",
    "wof:name": "CM3 4BG",
    "wof:placetype": "postalcode"
  },
  "geometry": {"coordinates":[0.538883,51.74166],"type":"Point"}
}
