{
  "type": "Feature",
  "properties": {
    "date:inception_lower": "1980-01-01",
    "date:inception_upper": "1980-01-01",
    "iso:country": "GB",
    "wof:name": "ML11 0NS",
    "wof:placetype": "postalcode"
  },
  "geometry": {"coordinates":[-3.843981,55.55497],"type":"Point"}
}
