{
  "type": "Feature",
  "properties": {
    "iso:country":"GB",
    "wof:name":"ML11 0NS",
    "wof:placetype":"postalcode"
},
  "geometry": {"coordinates":[-3.84398058264933,55.55497003189505],"type":"Point"}
}