{
  "type": "Feature",
  "properties": {
    "iso:country":"GB",
    "wof:name":"G69 6BG",
    "wof:placetype":"postalcode"
},
  "geometry": {"coordinates":[-4.10405702740522,55.85555724340649],"type":"Point"}
}