{
  "type": "Feature",
  "properties": {
    "iso:country":"GB",
    "wof:name":"GU15 2YA",
    "wof:placetype":"postalcode"
},
  "geometry": {"coordinates":[-0.75184424840729,51.32442924388418],"type":"Point"}
}