{
  "type": "Feature",
  "properties": {
    "iso:country":"GB",
    "wof:name":"SW8 2RB",
    "wof:placetype":"postalcode"
},
  "geometry": {"coordinates":[-0.13512841817822,51.47075438157299],"type":"Point"}
}