{
  "type": "Feature",
  "properties": {
    "iso:country": "GB",
    "wof:name": "NR18 9DN",
    "wof:placetype": "postalcode"
  },
  "geometry": {"coordinates":[1.006891,52.553476],"type":"Point"}
}
