{
  "type": "Feature",
  "properties": {
    "iso:country":"GB",
    "wof:name":"NR18 9DN",
    "wof:placetype":"postalcode"
},
  "geometry": {"coordinates":[1.00689120737648,52.55347567028755],"type":"Point"}
}