{
  "type": "Feature",
  "properties": {
    "iso:country": "GB",
    "wof:name": "SN2 8QE",
    "wof:placetype": "postalcode"
  },
  "geometry": {"coordinates":[-1.76947,51.57382],"type":"Point"}
}
