{
  "type": "Feature",
  "properties": {
    "date:inception_lower":"2000-06-01",
    "date:inception_upper":"2000-06-30",
    "iso:country":"GB",
    "wof:name":"SN2 8QE",
    "wof:placetype":"postalcode"
},
  "geometry": {"coordinates":[-1.76947,51.57382],"type":"Point"}
}