{
  "type": "Feature",
  "properties": {
    "iso:country":"GB",
    "wof:name":"SN2 8QE",
    "wof:placetype":"postalcode"
},
  "geometry": {"coordinates":[-1.76946961160792,51.5738202254969],"type":"Point"}
}