{
  "type": "Feature",
  "properties": {
    "date:inception_lower": "2016-05-01",
    "date:inception_upper": "2016-05-01",
    "iso:country": "GB",
    "wof:name": "NR16 1FA",
    "wof:placetype": "postalcode"
  },
  "geometry": {"coordinates":[1.166104,52.478273],"type":"Point"}
}
