{
  "type": "Feature",
  "properties": {
    "iso:country": "GB",
    "wof:name": "NR16 1FA",
    "wof:placetype": "postalcode"
  },
  "geometry": {"coordinates":[1.166104,52.478273],"type":"Point"}
}
