{
  "type": "Feature",
  "properties": {
    "iso:country": "GB",
    "wof:name": "B14 4DT",
    "wof:placetype": "postalcode"
  },
  "geometry": {"coordinates":[-1.861257,52.418524],"type":"Point"}
}
