{
  "type": "Feature",
  "properties": {
    "iso:country":"GB",
    "wof:name":"B14 4DT",
    "wof:placetype":"postalcode"
},
  "geometry": {"coordinates":[-1.86125668834078,52.41852438201561],"type":"Point"}
}