{
  "type": "Feature",
  "properties": {
    "iso:country":"GB",
    "wof:name":"NE4 5RE",
    "wof:placetype":"postalcode"
},
  "geometry": {"coordinates":[-1.62943212199586,54.97690290967719],"type":"Point"}
}