{
  "type": "Feature",
  "properties": {
    "iso:country": "GB",
    "wof:name": "NE4 5RE",
    "wof:placetype": "postalcode"
  },
  "geometry": {"coordinates":[-1.629432,54.976903],"type":"Point"}
}
