{
  "type": "Feature",
  "properties": {
    "iso:country":"GB",
    "wof:name":"N3 3TX",
    "wof:placetype":"postalcode"
},
  "geometry": {"coordinates":[-0.19651631970417,51.59826492488654],"type":"Point"}
}