{
  "type": "Feature",
  "properties": {
    "iso:country":"GB",
    "wof:name":"M20 1PH",
    "wof:placetype":"postalcode"
},
  "geometry": {"coordinates":[-2.24335906388236,53.43854072628604],"type":"Point"}
}