{
  "type": "Feature",
  "properties": {
    "iso:country":"GB",
    "wof:name":"TW15 3DR",
    "wof:placetype":"postalcode"
},
  "geometry": {"coordinates":[-0.47664535528282,51.44041196927554],"type":"Point"}
}