{
  "type": "Feature",
  "properties": {
    "iso:country": "GB",
    "wof:name": "TW15 3DR",
    "wof:placetype": "postalcode"
  },
  "geometry": {"coordinates":[-0.476645,51.440412],"type":"Point"}
}
