{
  "type": "Feature",
  "properties": {
    "date:inception_lower": "2001-12-01",
    "date:inception_upper": "2001-12-01",
    "iso:country": "GB",
    "wof:name": "TW15 3DR",
    "wof:placetype": "postalcode"
  },
  "geometry": {"coordinates":[-0.476645,51.440412],"type":"Point"}
}
