{
  "type": "Feature",
  "properties": {
    "iso:country":"GB",
    "wof:name":"B29 6NS",
    "wof:placetype":"postalcode"
},
  "geometry": {"coordinates":[-1.94521717229143,52.44007908664357],"type":"Point"}
}