{
  "type": "Feature",
  "properties": {
    "iso:country":"GB",
    "wof:name":"NW10 6QH",
    "wof:placetype":"postalcode"
},
  "geometry": {"coordinates":[-0.26021458206854,51.53037231345611],"type":"Point"}
}