{
  "type": "Feature",
  "properties": {
    "iso:country":"GB",
    "wof:name":"DA6 7JJ",
    "wof:placetype":"postalcode"
},
  "geometry": {"coordinates":[0.14614618713362,51.45585271706831],"type":"Point"}
}