{
  "type": "Feature",
  "properties": {
    "date:inception_lower": "1984-10-01",
    "date:inception_upper": "1984-10-01",
    "iso:country": "GB",
    "wof:name": "DA6 7JJ",
    "wof:placetype": "postalcode"
  },
  "geometry": {"coordinates":[0.146,51.455838],"type":"Point"}
}
