{
  "type": "Feature",
  "properties": {
    "date:inception_lower": "1993-08-01",
    "date:inception_upper": "1993-08-01",
    "iso:country": "GB",
    "wof:name": "SA71 4AS",
    "wof:placetype": "postalcode"
  },
  "geometry": {"coordinates":[-4.902,51.672009],"type":"Point"}
}
