{
  "type": "Feature",
  "properties": {
    "iso:country":"GB",
    "wof:name":"LE67 4DN",
    "wof:placetype":"postalcode"
},
  "geometry": {"coordinates":[-1.34354683282477,52.72539249540488],"type":"Point"}
}