{
  "type": "Feature",
  "properties": {
    "iso:country": "GB",
    "wof:name": "LE67 4DN",
    "wof:placetype": "postalcode"
  },
  "geometry": {"coordinates":[-1.343547,52.725392],"type":"Point"}
}
