{
  "type": "Feature",
  "properties": {
    "iso:country":"GB",
    "wof:name":"E15 2DA",
    "wof:placetype":"postalcode"
},
  "geometry": {"coordinates":[-0.00762715546306,51.55366469554846],"type":"Point"}
}