{
  "type": "Feature",
  "properties": {
    "iso:country":"GB",
    "wof:name":"NW3 6TX",
    "wof:placetype":"postalcode"
},
  "geometry": {"coordinates":[-0.17902839420708,51.55644115237242],"type":"Point"}
}