{
  "type": "Feature",
  "properties": {
    "iso:country": "GB",
    "wof:name": "SN15 3HT",
    "wof:placetype": "postalcode"
  },
  "geometry": {"coordinates":[-2.113146,51.457956],"type":"Point"}
}
