{
  "type": "Feature",
  "properties": {
    "iso:country":"GB",
    "wof:name":"S74 0LQ",
    "wof:placetype":"postalcode"
},
  "geometry": {"coordinates":[-1.42868677104571,53.50339145461046],"type":"Point"}
}