{
  "type": "Feature",
  "properties": {
    "iso:country": "GB",
    "wof:name": "S74 0LQ",
    "wof:placetype": "postalcode"
  },
  "geometry": {"coordinates":[-1.428687,53.503391],"type":"Point"}
}
