{
  "type": "Feature",
  "properties": {
    "iso:country": "GB",
    "wof:name": "TR26 1QA",
    "wof:placetype": "postalcode"
  },
  "geometry": {"coordinates":[-5.478536,50.216266],"type":"Point"}
}
