{
  "type": "Feature",
  "properties": {
    "date:inception_lower": "1980-01-01",
    "date:inception_upper": "1980-01-01",
    "iso:country": "GB",
    "wof:name": "HR6 0AR",
    "wof:placetype": "postalcode"
  },
  "geometry": {"coordinates":[-2.756055,52.268172],"type":"Point"}
}
