{
  "type": "Feature",
  "properties": {
    "iso:country": "GB",
    "wof:name": "HR6 0AR",
    "wof:placetype": "postalcode"
  },
  "geometry": {"coordinates":[-2.756055,52.268172],"type":"Point"}
}
