{
  "type": "Feature",
  "properties": {
    "iso:country":"GB",
    "wof:name":"HR6 0AR",
    "wof:placetype":"postalcode"
},
  "geometry": {"coordinates":[-2.75605376165323,52.26816027422107],"type":"Point"}
}