{
  "type": "Feature",
  "properties": {
    "iso:country":"GB",
    "wof:name":"NP22 5AG",
    "wof:placetype":"postalcode"
},
  "geometry": {"coordinates":[-3.26467956992611,51.74322411046534],"type":"Point"}
}