{
  "type": "Feature",
  "properties": {
    "iso:country": "GB",
    "wof:name": "EX5 2LH",
    "wof:placetype": "postalcode"
  },
  "geometry": {"coordinates":[-3.389786,50.746889],"type":"Point"}
}
