{
  "type": "Feature",
  "properties": {
    "date:inception_lower":"2012-05-01",
    "date:inception_upper":"2012-05-31",
    "iso:country":"GB",
    "wof:name":"S25 2AF",
    "wof:placetype":"postalcode"
},
  "geometry": {"coordinates":[-1.211888,53.368128],"type":"Point"}
}