{
  "type": "Feature",
  "properties": {
    "iso:country": "GB",
    "wof:name": "S25 2AF",
    "wof:placetype": "postalcode"
  },
  "geometry": {"coordinates":[-1.211888,53.368128],"type":"Point"}
}
