{
  "type": "Feature",
  "properties": {
    "date:inception_lower": "2005-06-01",
    "date:inception_upper": "2005-06-01",
    "iso:country": "GB",
    "wof:name": "YO61 3NN",
    "wof:placetype": "postalcode"
  },
  "geometry": {"coordinates":[-1.212261,54.102259],"type":"Point"}
}
