{
  "type": "Feature",
  "properties": {
    "iso:country": "GB",
    "wof:name": "YO61 3NN",
    "wof:placetype": "postalcode"
  },
  "geometry": {"coordinates":[-1.212261,54.102259],"type":"Point"}
}
