{
  "type": "Feature",
  "properties": {
    "date:inception_lower": "1986-07-01",
    "date:inception_upper": "1986-07-01",
    "iso:country": "GB",
    "wof:name": "MK8 9HH",
    "wof:placetype": "postalcode"
  },
  "geometry": {"coordinates":[-0.794267,52.036319],"type":"Point"}
}
