{
  "type": "Feature",
  "properties": {
    "date:inception_lower":"1980-01-01",
    "date:inception_upper":"1980-01-31",
    "iso:country":"GB",
    "wof:name":"WA15 6UJ",
    "wof:placetype":"postalcode"
},
  "geometry": {"coordinates":[-2.311302,53.400323],"type":"Point"}
}