{
  "type": "Feature",
  "properties": {
    "iso:country": "GB",
    "wof:name": "WA15 6UJ",
    "wof:placetype": "postalcode"
  },
  "geometry": {"coordinates":[-2.311302,53.400323],"type":"Point"}
}
