{
  "type": "Feature",
  "properties": {
    "iso:country":"GB",
    "wof:name":"ST6 8NL",
    "wof:placetype":"postalcode"
},
  "geometry": {"coordinates":[-2.15511504495033,53.06594093371332],"type":"Point"}
}