{
  "type": "Feature",
  "properties": {
    "date:inception_lower":"2013-02-01",
    "date:inception_upper":"2013-02-28",
    "iso:country":"GB",
    "wof:name":"TQ9 5RS",
    "wof:placetype":"postalcode"
},
  "geometry": {"coordinates":[-3.709111,50.431563],"type":"Point"}
}