{
  "type": "Feature",
  "properties": {
    "iso:country":"GB",
    "wof:name":"TQ9 5RS",
    "wof:placetype":"postalcode"
},
  "geometry": {"coordinates":[-3.70911102863228,50.43156277687322],"type":"Point"}
}