{
  "type": "Feature",
  "properties": {
    "iso:country": "GB",
    "wof:name": "TQ9 5RS",
    "wof:placetype": "postalcode"
  },
  "geometry": {"coordinates":[-3.709111,50.431563],"type":"Point"}
}
