{
  "type": "Feature",
  "properties": {
    "iso:country":"GB",
    "wof:name":"PE21 7QF",
    "wof:placetype":"postalcode"
},
  "geometry": {"coordinates":[-0.04876133690083,52.97669990598583],"type":"Point"}
}