{
  "type": "Feature",
  "properties": {
    "iso:country": "GB",
    "wof:name": "PE21 7QF",
    "wof:placetype": "postalcode"
  },
  "geometry": {"coordinates":[-0.048761,52.9767],"type":"Point"}
}
