{
  "type": "Feature",
  "properties": {
    "date:inception_lower": "1980-01-01",
    "date:inception_upper": "1980-01-01",
    "iso:country": "GB",
    "wof:name": "PE21 7QF",
    "wof:placetype": "postalcode"
  },
  "geometry": {"coordinates":[-0.048761,52.9767],"type":"Point"}
}
