{
  "type": "Feature",
  "properties": {
    "iso:country":"GB",
    "wof:name":"CO1 2UW",
    "wof:placetype":"postalcode"
},
  "geometry": {"coordinates":[0.9097042299908,51.88758213298817],"type":"Point"}
}