{
  "type": "Feature",
  "properties": {
    "date:inception_lower":"2004-10-01",
    "date:inception_upper":"2004-10-31",
    "iso:country":"GB",
    "wof:name":"CO1 2UW",
    "wof:placetype":"postalcode"
},
  "geometry": {"coordinates":[0.909704,51.887582],"type":"Point"}
}