{
  "type": "Feature",
  "properties": {
    "iso:country": "GB",
    "wof:name": "DL3 9EU",
    "wof:placetype": "postalcode"
  },
  "geometry": {"coordinates":[-1.580733,54.534595],"type":"Point"}
}
