{
  "type": "Feature",
  "properties": {
    "iso:country": "GB",
    "wof:name": "SA62 5TS",
    "wof:placetype": "postalcode"
  },
  "geometry": {"coordinates":[-4.918413,51.929857],"type":"Point"}
}
