{
  "type": "Feature",
  "properties": {
    "iso:country":"GB",
    "wof:name":"SK6 3DW",
    "wof:placetype":"postalcode"
},
  "geometry": {"coordinates":[-2.10394136181886,53.41050174631966],"type":"Point"}
}