{
  "type": "Feature",
  "properties": {
    "iso:country":"GB",
    "wof:name":"HP19 0GB",
    "wof:placetype":"postalcode"
},
  "geometry": {"coordinates":[-0.80367685375027,51.83314982964981],"type":"Point"}
}