{
  "type": "Feature",
  "properties": {
    "date:inception_lower": "2021-06-01",
    "date:inception_upper": "2021-06-01",
    "iso:country": "GB",
    "wof:name": "LE17 6BY",
    "wof:placetype": "postalcode"
  },
  "geometry": {"coordinates":[-1.168713,52.411396],"type":"Point"}
}
