{
  "type": "Feature",
  "properties": {
    "date:inception_lower": "1980-01-01",
    "date:inception_upper": "1980-01-01",
    "iso:country": "GB",
    "wof:name": "TS25 2QW",
    "wof:placetype": "postalcode"
  },
  "geometry": {"coordinates":[-1.231684,54.65481],"type":"Point"}
}
