{
  "type": "Feature",
  "properties": {
    "iso:country": "GB",
    "wof:name": "CB24 5HE",
    "wof:placetype": "postalcode"
  },
  "geometry": {"coordinates":[0.058701,52.30655],"type":"Point"}
}
