{
  "type": "Feature",
  "properties": {
    "iso:country":"GB",
    "wof:name":"CB24 5HE",
    "wof:placetype":"postalcode"
},
  "geometry": {"coordinates":[0.05870060660226,52.30655047325479],"type":"Point"}
}