{
  "type": "Feature",
  "properties": {
    "iso:country": "GB",
    "wof:name": "NE15 6AR",
    "wof:placetype": "postalcode"
  },
  "geometry": {"coordinates":[-1.690937,54.971368],"type":"Point"}
}
