{
  "type": "Feature",
  "properties": {
    "iso:country": "GB",
    "wof:name": "FK2 7TA",
    "wof:placetype": "postalcode"
  },
  "geometry": {"coordinates":[-3.792586,56.015829],"type":"Point"}
}
