{
  "type": "Feature",
  "properties": {
    "iso:country":"GB",
    "wof:name":"FK2 7TA",
    "wof:placetype":"postalcode"
},
  "geometry": {"coordinates":[-3.79258640422603,56.0158291440945],"type":"Point"}
}