{
  "type": "Feature",
  "properties": {
    "iso:country": "GB",
    "wof:name": "CF83 8EQ",
    "wof:placetype": "postalcode"
  },
  "geometry": {"coordinates":[-3.212308,51.604702],"type":"Point"}
}
