{
  "type": "Feature",
  "properties": {
    "date:inception_lower": "1999-06-01",
    "date:inception_upper": "1999-06-01",
    "iso:country": "GB",
    "wof:name": "CF83 8EQ",
    "wof:placetype": "postalcode"
  },
  "geometry": {"coordinates":[-3.212308,51.604702],"type":"Point"}
}
