{
  "type": "Feature",
  "properties": {
    "iso:country":"GB",
    "wof:name":"CF83 8EQ",
    "wof:placetype":"postalcode"
},
  "geometry": {"coordinates":[-3.21230759739842,51.60470217711093],"type":"Point"}
}