{
  "type": "Feature",
  "properties": {
    "date:inception_lower": "1980-01-01",
    "date:inception_upper": "1980-01-01",
    "iso:country": "GB",
    "wof:name": "TS12 2QX",
    "wof:placetype": "postalcode"
  },
  "geometry": {"coordinates":[-0.921537,54.573632],"type":"Point"}
}
