{
  "type": "Feature",
  "properties": {
    "iso:country":"GB",
    "wof:name":"TS12 2QX",
    "wof:placetype":"postalcode"
},
  "geometry": {"coordinates":[-0.92179852390869,54.5736391961745],"type":"Point"}
}