{
  "type": "Feature",
  "properties": {
    "iso:country": "GB",
    "wof:name": "BA14 7NY",
    "wof:placetype": "postalcode"
  },
  "geometry": {"coordinates":[-2.200257,51.336201],"type":"Point"}
}
