{
  "type": "Feature",
  "properties": {
    "date:inception_lower":"1980-01-01",
    "date:inception_upper":"1980-01-31",
    "iso:country":"GB",
    "wof:name":"BA14 7NY",
    "wof:placetype":"postalcode"
},
  "geometry": {"coordinates":[-2.200257,51.336201],"type":"Point"}
}