{
  "type": "Feature",
  "properties": {
    "iso:country":"GB",
    "wof:name":"S26 4SW",
    "wof:placetype":"postalcode"
},
  "geometry": {"coordinates":[-1.33569400677848,53.36340672848151],"type":"Point"}
}