{
  "type": "Feature",
  "properties": {
    "iso:country": "GB",
    "wof:name": "HU12 9BP",
    "wof:placetype": "postalcode"
  },
  "geometry": {"coordinates":[-0.134577,53.772161],"type":"Point"}
}
