{
  "type": "Feature",
  "properties": {
    "iso:country":"GB",
    "wof:name":"HU12 9BP",
    "wof:placetype":"postalcode"
},
  "geometry": {"coordinates":[-0.13457725111624,53.77216122003309],"type":"Point"}
}