{
  "type": "Feature",
  "properties": {
    "iso:country":"GB",
    "wof:name":"N16 9BT",
    "wof:placetype":"postalcode"
},
  "geometry": {"coordinates":[-0.08678833039666,51.55236547900873],"type":"Point"}
}