{
  "type": "Feature",
  "properties": {
    "iso:country": "GB",
    "wof:name": "TR9 6NQ",
    "wof:placetype": "postalcode"
  },
  "geometry": {"coordinates":[-4.933551,50.388479],"type":"Point"}
}
