{
  "type": "Feature",
  "properties": {
    "iso:country":"GB",
    "wof:name":"TR9 6NQ",
    "wof:placetype":"postalcode"
},
  "geometry": {"coordinates":[-4.93355127282363,50.38847925184937],"type":"Point"}
}