{
  "type": "Feature",
  "properties": {
    "date:inception_lower":"1980-01-01",
    "date:inception_upper":"1980-01-31",
    "iso:country":"GB",
    "wof:name":"TR9 6NQ",
    "wof:placetype":"postalcode"
},
  "geometry": {"coordinates":[-4.933551,50.388479],"type":"Point"}
}