{
  "type": "Feature",
  "properties": {
    "iso:country":"GB",
    "wof:name":"PR7 4DL",
    "wof:placetype":"postalcode"
},
  "geometry": {"coordinates":[-2.61667351788471,53.61003639142979],"type":"Point"}
}