{
  "type": "Feature",
  "properties": {
    "iso:country": "GB",
    "wof:name": "CF42 6UU",
    "wof:placetype": "postalcode"
  },
  "geometry": {"coordinates":[-3.51186,51.656544],"type":"Point"}
}
