{
  "type": "Feature",
  "properties": {
    "iso:country":"GB",
    "wof:name":"CF42 6UU",
    "wof:placetype":"postalcode"
},
  "geometry": {"coordinates":[-3.51185968841924,51.65654406991508],"type":"Point"}
}