{
  "type": "Feature",
  "properties": {
    "iso:country":"GB",
    "wof:name":"EX17 5LT",
    "wof:placetype":"postalcode"
},
  "geometry": {"coordinates":[-3.74808942254105,50.81244859137998],"type":"Point"}
}