{
  "type": "Feature",
  "properties": {
    "date:inception_lower": "1990-02-01",
    "date:inception_upper": "1990-02-01",
    "iso:country": "GB",
    "wof:name": "EX17 5LT",
    "wof:placetype": "postalcode"
  },
  "geometry": {"coordinates":[-3.748089,50.812449],"type":"Point"}
}
