{
  "type": "Feature",
  "properties": {
    "iso:country": "GB",
    "wof:name": "TR21 0JG",
    "wof:placetype": "postalcode"
  },
  "geometry": {"coordinates":[-6.316747,49.914187],"type":"Point"}
}
