{
  "type": "Feature",
  "properties": {
    "iso:country":"GB",
    "wof:name":"TR21 0JG",
    "wof:placetype":"postalcode"
},
  "geometry": {"coordinates":[-6.31674735967743,49.91418713001071],"type":"Point"}
}