{
  "type": "Feature",
  "properties": {
    "iso:country":"GB",
    "wof:name":"SS7 3RX",
    "wof:placetype":"postalcode"
},
  "geometry": {"coordinates":[0.58590022117053,51.57189479000606],"type":"Point"}
}