{
  "type": "Feature",
  "properties": {
    "date:inception_lower": "1980-01-01",
    "date:inception_upper": "1980-01-01",
    "iso:country": "GB",
    "wof:name": "SS7 3RX",
    "wof:placetype": "postalcode"
  },
  "geometry": {"coordinates":[0.5859,51.571895],"type":"Point"}
}
