{
  "type": "Feature",
  "properties": {
    "iso:country": "GB",
    "wof:name": "NG32 3NX",
    "wof:placetype": "postalcode"
  },
  "geometry": {"coordinates":[-0.512448,52.978286],"type":"Point"}
}
