{
  "type": "Feature",
  "properties": {
    "date:inception_lower":"1980-01-01",
    "date:inception_upper":"1980-01-31",
    "iso:country":"GB",
    "wof:name":"NG32 3NX",
    "wof:placetype":"postalcode"
},
  "geometry": {"coordinates":[-0.512448,52.978286],"type":"Point"}
}