{
  "type": "Feature",
  "properties": {
    "iso:country":"GB",
    "wof:name":"NG32 3NX",
    "wof:placetype":"postalcode"
},
  "geometry": {"coordinates":[-0.51245401368149,52.9782642510708],"type":"Point"}
}