{
  "type": "Feature",
  "properties": {
    "iso:country":"GB",
    "wof:name":"PR6 9BB",
    "wof:placetype":"postalcode"
},
  "geometry": {"coordinates":[-2.60175465436697,53.66840176187378],"type":"Point"}
}