{
  "type": "Feature",
  "properties": {
    "iso:country": "GB",
    "wof:name": "EH31 2HE",
    "wof:placetype": "postalcode"
  },
  "geometry": {"coordinates":[-2.82373,56.036619],"type":"Point"}
}
