{
  "type": "Feature",
  "properties": {
    "iso:country":"GB",
    "wof:name":"EH31 2HE",
    "wof:placetype":"postalcode"
},
  "geometry": {"coordinates":[-2.82372969674632,56.03661913169518],"type":"Point"}
}