{
  "type": "Feature",
  "properties": {
    "date:inception_lower":"1980-01-01",
    "date:inception_upper":"1980-01-31",
    "iso:country":"GB",
    "wof:name":"SR8 2LD",
    "wof:placetype":"postalcode"
},
  "geometry": {"coordinates":[-1.358893,54.75408],"type":"Point"}
}