{
  "type": "Feature",
  "properties": {
    "iso:country":"GB",
    "wof:name":"SR8 2LD",
    "wof:placetype":"postalcode"
},
  "geometry": {"coordinates":[-1.35889331495378,54.75408036928204],"type":"Point"}
}