{
  "type": "Feature",
  "properties": {
    "iso:country":"GB",
    "wof:name":"BH12 3DX",
    "wof:placetype":"postalcode"
},
  "geometry": {"coordinates":[-1.94583157846428,50.73526008490302],"type":"Point"}
}