{
  "type": "Feature",
  "properties": {
    "date:inception_lower": "1980-01-01",
    "date:inception_upper": "1980-01-01",
    "iso:country": "GB",
    "wof:name": "BL9 9JB",
    "wof:placetype": "postalcode"
  },
  "geometry": {"coordinates":[-2.29151,53.582742],"type":"Point"}
}
