{
  "type": "Feature",
  "properties": {
    "date:inception_lower": "1980-01-01",
    "date:inception_upper": "1980-01-01",
    "iso:country": "GB",
    "wof:name": "GU35 8NL",
    "wof:placetype": "postalcode"
  },
  "geometry": {"coordinates":[-0.807655,51.116137],"type":"Point"}
}
