{
  "type": "Feature",
  "properties": {
    "iso:country": "GB",
    "wof:name": "NP44 4UA",
    "wof:placetype": "postalcode"
  },
  "geometry": {"coordinates":[-3.042896,51.646489],"type":"Point"}
}
