{
  "type": "Feature",
  "properties": {
    "date:inception_lower": "1980-01-01",
    "date:inception_upper": "1980-01-01",
    "iso:country": "GB",
    "wof:name": "HU20 3UR",
    "wof:placetype": "postalcode"
  },
  "geometry": {"coordinates":[-0.552079,53.80407],"type":"Point"}
}
