{
  "type": "Feature",
  "properties": {
    "iso:country":"GB",
    "wof:name":"TR1 2PA",
    "wof:placetype":"postalcode"
},
  "geometry": {"coordinates":[-5.05167922449582,50.25948936293232],"type":"Point"}
}