{
  "type": "Feature",
  "properties": {
    "iso:country": "GB",
    "wof:name": "PE14 8DD",
    "wof:placetype": "postalcode"
  },
  "geometry": {"coordinates":[0.208001,52.641205],"type":"Point"}
}
