{
  "type": "Feature",
  "properties": {
    "date:inception_lower": "1983-07-01",
    "date:inception_upper": "1983-07-01",
    "iso:country": "GB",
    "wof:name": "PE14 8DD",
    "wof:placetype": "postalcode"
  },
  "geometry": {"coordinates":[0.208004,52.641267],"type":"Point"}
}
