{
  "type": "Feature",
  "properties": {
    "iso:country": "GB",
    "wof:name": "LL65 4LR",
    "wof:placetype": "postalcode"
  },
  "geometry": {"coordinates":[-4.544565,53.400387],"type":"Point"}
}
