{
  "type": "Feature",
  "properties": {
    "date:inception_lower": "1980-01-01",
    "date:inception_upper": "1980-01-01",
    "iso:country": "GB",
    "wof:name": "S41 8DX",
    "wof:placetype": "postalcode"
  },
  "geometry": {"coordinates":[-1.451429,53.257055],"type":"Point"}
}
