{
  "type": "Feature",
  "properties": {
    "iso:country":"GB",
    "wof:name":"S41 8DX",
    "wof:placetype":"postalcode"
},
  "geometry": {"coordinates":[-1.45144480617844,53.25704568574152],"type":"Point"}
}