{
  "type": "Feature",
  "properties": {
    "date:inception_lower": "1987-06-01",
    "date:inception_upper": "1987-06-01",
    "iso:country": "GB",
    "wof:name": "EH48 2SW",
    "wof:placetype": "postalcode"
  },
  "geometry": {"coordinates":[-3.651545,55.894878],"type":"Point"}
}
