{
  "type": "Feature",
  "properties": {
    "iso:country":"GB",
    "wof:name":"EH48 2SW",
    "wof:placetype":"postalcode"
},
  "geometry": {"coordinates":[-3.6515450355841,55.89487760377993],"type":"Point"}
}