{
  "type": "Feature",
  "properties": {
    "date:inception_lower":"1996-06-01",
    "date:inception_upper":"1996-06-30",
    "iso:country":"GB",
    "wof:name":"CB7 4GA",
    "wof:placetype":"postalcode"
},
  "geometry": {"coordinates":[0.262285,52.39092],"type":"Point"}
}