{
  "type": "Feature",
  "properties": {
    "iso:country":"GB",
    "wof:name":"CB7 4GA",
    "wof:placetype":"postalcode"
},
  "geometry": {"coordinates":[0.26228498593742,52.39091955528269],"type":"Point"}
}