{
  "type": "Feature",
  "properties": {
    "iso:country": "GB",
    "wof:name": "E18 2UA",
    "wof:placetype": "postalcode"
  },
  "geometry": {"coordinates":[0.017057,51.586641],"type":"Point"}
}
