{
  "type": "Feature",
  "properties": {
    "iso:country": "GB",
    "wof:name": "BS16 7JD",
    "wof:placetype": "postalcode"
  },
  "geometry": {"coordinates":[-2.475304,51.485342],"type":"Point"}
}
