{
  "type": "Feature",
  "properties": {
    "iso:country":"GB",
    "wof:name":"BS16 7JD",
    "wof:placetype":"postalcode"
},
  "geometry": {"coordinates":[-2.47527527929305,51.48534379654394],"type":"Point"}
}