{
  "type": "Feature",
  "properties": {
    "iso:country": "GB",
    "wof:name": "WA7 2DR",
    "wof:placetype": "postalcode"
  },
  "geometry": {"coordinates":[-2.692774,53.327823],"type":"Point"}
}
