{
  "type": "Feature",
  "properties": {
    "date:inception_lower": "2000-12-01",
    "date:inception_upper": "2000-12-01",
    "iso:country": "GB",
    "wof:name": "WN6 7EU",
    "wof:placetype": "postalcode"
  },
  "geometry": {"coordinates":[-2.650121,53.554877],"type":"Point"}
}
