{
  "type": "Feature",
  "properties": {
    "iso:country":"GB",
    "wof:name":"MK18 3BH",
    "wof:placetype":"postalcode"
},
  "geometry": {"coordinates":[-0.88508514609989,51.94276186952973],"type":"Point"}
}