{
  "type": "Feature",
  "properties": {
    "iso:country":"GB",
    "wof:name":"SN5 7BA",
    "wof:placetype":"postalcode"
},
  "geometry": {"coordinates":[-1.82193182745161,51.55620741040189],"type":"Point"}
}