{
  "type": "Feature",
  "properties": {
    "iso:country":"GB",
    "wof:name":"LE16 8JY",
    "wof:placetype":"postalcode"
},
  "geometry": {"coordinates":[-0.89389281511138,52.42481612009896],"type":"Point"}
}