{
  "type": "Feature",
  "properties": {
    "iso:country": "GB",
    "wof:name": "LE16 8JY",
    "wof:placetype": "postalcode"
  },
  "geometry": {"coordinates":[-0.893893,52.424816],"type":"Point"}
}
