{
  "type": "Feature",
  "properties": {
    "date:inception_lower": "1980-01-01",
    "date:inception_upper": "1980-01-01",
    "iso:country": "GB",
    "wof:name": "NR30 2BT",
    "wof:placetype": "postalcode"
  },
  "geometry": {"coordinates":[1.732053,52.60811],"type":"Point"}
}
