{
  "type": "Feature",
  "properties": {
    "iso:country": "GB",
    "wof:name": "DN18 5RQ",
    "wof:placetype": "postalcode"
  },
  "geometry": {"coordinates":[-0.462659,53.686711],"type":"Point"}
}
