{
  "type": "Feature",
  "properties": {
    "iso:country":"GB",
    "wof:name":"CB2 0AB",
    "wof:placetype":"postalcode"
},
  "geometry": {"coordinates":[0.13834517469984,52.17752227450989],"type":"Point"}
}