{
  "type": "Feature",
  "properties": {
    "date:inception_lower": "2010-07-01",
    "date:inception_upper": "2010-07-01",
    "iso:country": "GB",
    "wof:name": "CB2 0AB",
    "wof:placetype": "postalcode"
  },
  "geometry": {"coordinates":[0.138345,52.177522],"type":"Point"}
}
