{
  "type": "Feature",
  "properties": {
    "iso:country":"GB",
    "wof:name":"B32 4HE",
    "wof:placetype":"postalcode"
},
  "geometry": {"coordinates":[-2.00454512196473,52.43403227844961],"type":"Point"}
}