{
  "type": "Feature",
  "properties": {
    "iso:country":"GB",
    "wof:name":"LS18 5JJ",
    "wof:placetype":"postalcode"
},
  "geometry": {"coordinates":[-1.65574835280641,53.83850444225299],"type":"Point"}
}