{
  "type": "Feature",
  "properties": {
    "iso:country":"GB",
    "wof:name":"GL13 9EN",
    "wof:placetype":"postalcode"
},
  "geometry": {"coordinates":[-2.44492530931955,51.69003503322418],"type":"Point"}
}