{
  "type": "Feature",
  "properties": {
    "iso:country": "GB",
    "wof:name": "GL13 9EN",
    "wof:placetype": "postalcode"
  },
  "geometry": {"coordinates":[-2.444651,51.690093],"type":"Point"}
}
