{
  "type": "Feature",
  "properties": {
    "iso:country":"GB",
    "wof:name":"IV52 8TN",
    "wof:placetype":"postalcode"
},
  "geometry": {"coordinates":[-5.65089939539984,57.33954088325248],"type":"Point"}
}