{
  "type": "Feature",
  "properties": {
    "date:inception_lower": "2023-07-01",
    "date:inception_upper": "2023-07-01",
    "iso:country": "GB",
    "wof:name": "NR17 2FY",
    "wof:placetype": "postalcode"
  },
  "geometry": {"coordinates":[1.03115,52.52474],"type":"Point"}
}
