{
  "type": "Feature",
  "properties": {
    "iso:country":"GB",
    "wof:name":"CT11 7AF",
    "wof:placetype":"postalcode"
},
  "geometry": {"coordinates":[1.41494179202377,51.34313735908047],"type":"Point"}
}