{
  "type": "Feature",
  "properties": {
    "date:inception_lower": "1980-01-01",
    "date:inception_upper": "1980-01-01",
    "iso:country": "GB",
    "wof:name": "CT11 7AF",
    "wof:placetype": "postalcode"
  },
  "geometry": {"coordinates":[1.413829,51.343079],"type":"Point"}
}
