{
  "type": "Feature",
  "properties": {
    "iso:country": "GB",
    "wof:name": "M14 5QE",
    "wof:placetype": "postalcode"
  },
  "geometry": {"coordinates":[-2.213803,53.458192],"type":"Point"}
}
