{
  "type": "Feature",
  "properties": {
    "date:inception_lower":"2000-12-01",
    "date:inception_upper":"2000-12-31",
    "iso:country":"GB",
    "wof:name":"M14 5QE",
    "wof:placetype":"postalcode"
},
  "geometry": {"coordinates":[-2.213803,53.458192],"type":"Point"}
}