{
  "type": "Feature",
  "properties": {
    "date:inception_lower": "1980-01-01",
    "date:inception_upper": "1980-01-01",
    "iso:country": "GB",
    "wof:name": "HA5 5ET",
    "wof:placetype": "postalcode"
  },
  "geometry": {"coordinates":[-0.371635,51.577499],"type":"Point"}
}
