{
  "type": "Feature",
  "properties": {
    "iso:country":"GB",
    "wof:name":"HA5 5ET",
    "wof:placetype":"postalcode"
},
  "geometry": {"coordinates":[-0.37163376900171,51.57753523083053],"type":"Point"}
}