{
  "type": "Feature",
  "properties": {
    "iso:country":"GB",
    "wof:name":"LU7 4HQ",
    "wof:placetype":"postalcode"
},
  "geometry": {"coordinates":[-0.63843420435817,51.90904874388964],"type":"Point"}
}