{
  "type": "Feature",
  "properties": {
    "iso:country":"GB",
    "wof:name":"NG17 3EU",
    "wof:placetype":"postalcode"
},
  "geometry": {"coordinates":[-1.26741101657281,53.14484462206751],"type":"Point"}
}