{
  "type": "Feature",
  "properties": {
    "iso:country":"GB",
    "wof:name":"WF10 5SG",
    "wof:placetype":"postalcode"
},
  "geometry": {"coordinates":[-1.35695503043252,53.71620531007463],"type":"Point"}
}