{
  "type": "Feature",
  "properties": {
    "date:inception_lower": "1980-01-01",
    "date:inception_upper": "1980-01-01",
    "iso:country": "GB",
    "wof:name": "WF10 5SG",
    "wof:placetype": "postalcode"
  },
  "geometry": {"coordinates":[-1.356955,53.716205],"type":"Point"}
}
