{
  "type": "Feature",
  "properties": {
    "iso:country":"GB",
    "wof:name":"EX4 2HP",
    "wof:placetype":"postalcode"
},
  "geometry": {"coordinates":[-3.62587116338725,50.74046235865104],"type":"Point"}
}