{
  "type": "Feature",
  "properties": {
    "iso:country": "GB",
    "wof:name": "NG10 5QY",
    "wof:placetype": "postalcode"
  },
  "geometry": {"coordinates":[-1.307373,52.931759],"type":"Point"}
}
