{
  "type": "Feature",
  "properties": {
    "date:inception_lower":"2007-01-01",
    "date:inception_upper":"2007-01-31",
    "iso:country":"GB",
    "wof:name":"NG10 5QY",
    "wof:placetype":"postalcode"
},
  "geometry": {"coordinates":[-1.307373,52.931759],"type":"Point"}
}