{
  "type": "Feature",
  "properties": {
    "iso:country":"GB",
    "wof:name":"GU5 9QW",
    "wof:placetype":"postalcode"
},
  "geometry": {"coordinates":[-0.4528022893953,51.19090061109699],"type":"Point"}
}