{
  "type": "Feature",
  "properties": {
    "date:inception_lower": "1980-01-01",
    "date:inception_upper": "1980-01-01",
    "iso:country": "GB",
    "wof:name": "GU5 9QW",
    "wof:placetype": "postalcode"
  },
  "geometry": {"coordinates":[-0.452802,51.190901],"type":"Point"}
}
