{
  "type": "Feature",
  "properties": {
    "date:inception_lower":"1986-04-01",
    "date:inception_upper":"1986-04-30",
    "iso:country":"GB",
    "wof:name":"LU2 9UU",
    "wof:placetype":"postalcode"
},
  "geometry": {"coordinates":[-0.371214,51.891771],"type":"Point"}
}