{
  "type": "Feature",
  "properties": {
    "iso:country":"GB",
    "wof:name":"LU2 9UU",
    "wof:placetype":"postalcode"
},
  "geometry": {"coordinates":[-0.37121407883643,51.89177090509554],"type":"Point"}
}