{
  "type": "Feature",
  "properties": {
    "iso:country":"GB",
    "wof:name":"NW2 1NY",
    "wof:placetype":"postalcode"
},
  "geometry": {"coordinates":[-0.20864512204459,51.56816448505444],"type":"Point"}
}