{
  "type": "Feature",
  "properties": {
    "iso:country":"GB",
    "wof:name":"G13 3XA",
    "wof:placetype":"postalcode"
},
  "geometry": {"coordinates":[-4.34889457936312,55.89659388554659],"type":"Point"}
}