{
  "type": "Feature",
  "properties": {
    "iso:country":"GB",
    "wof:name":"SW17 9BU",
    "wof:placetype":"postalcode"
},
  "geometry": {"coordinates":[-0.15153303468226,51.42324554094393],"type":"Point"}
}