{
  "type": "Feature",
  "properties": {
    "date:inception_lower": "1992-08-01",
    "date:inception_upper": "1992-08-01",
    "iso:country": "GB",
    "wof:name": "SW17 9BU",
    "wof:placetype": "postalcode"
  },
  "geometry": {"coordinates":[-0.151533,51.423246],"type":"Point"}
}
