{
  "type": "Feature",
  "properties": {
    "iso:country":"GB",
    "wof:name":"CM16 9ZZ",
    "wof:placetype":"postalcode"
},
  "geometry": {"coordinates":[0.1130073861166,51.70004084867341],"type":"Point"}
}