{
  "type": "Feature",
  "properties": {
    "date:inception_lower": "2016-03-01",
    "date:inception_upper": "2016-03-01",
    "iso:country": "GB",
    "wof:name": "CM16 9ZZ",
    "wof:placetype": "postalcode"
  },
  "geometry": {"coordinates":[0.113007,51.700041],"type":"Point"}
}
