{
  "type": "Feature",
  "properties": {
    "iso:country":"GB",
    "wof:name":"S80 2LL",
    "wof:placetype":"postalcode"
},
  "geometry": {"coordinates":[-1.11865987940851,53.30051745304823],"type":"Point"}
}