{
  "type": "Feature",
  "properties": {
    "date:inception_lower":"1980-01-01",
    "date:inception_upper":"1980-01-31",
    "iso:country":"GB",
    "wof:name":"BN3 7LQ",
    "wof:placetype":"postalcode"
},
  "geometry": {"coordinates":[-0.186937,50.847232],"type":"Point"}
}