{
  "type": "Feature",
  "properties": {
    "iso:country":"GB",
    "wof:name":"BN3 7LQ",
    "wof:placetype":"postalcode"
},
  "geometry": {"coordinates":[-0.18693740952836,50.84723164155171],"type":"Point"}
}