{
  "type": "Feature",
  "properties": {
    "iso:country":"GB",
    "wof:name":"ST4 7PE",
    "wof:placetype":"postalcode"
},
  "geometry": {"coordinates":[-2.20492274408442,53.0113194859571],"type":"Point"}
}