{
  "type": "Feature",
  "properties": {
    "date:inception_lower": "2008-07-01",
    "date:inception_upper": "2008-07-01",
    "iso:country": "GB",
    "wof:name": "G1 1QA",
    "wof:placetype": "postalcode"
  },
  "geometry": {"coordinates":[-4.242587,55.859437],"type":"Point"}
}
