{
  "type": "Feature",
  "properties": {
    "iso:country":"GB",
    "wof:name":"BN12 6AZ",
    "wof:placetype":"postalcode"
},
  "geometry": {"coordinates":[-0.42788299496213,50.82080616242441],"type":"Point"}
}