{
  "type": "Feature",
  "properties": {
    "date:inception_lower":"1980-01-01",
    "date:inception_upper":"1980-01-31",
    "iso:country":"GB",
    "wof:name":"BH22 9LT",
    "wof:placetype":"postalcode"
},
  "geometry": {"coordinates":[-1.903891,50.809827],"type":"Point"}
}