{
  "type": "Feature",
  "properties": {
    "iso:country":"GB",
    "wof:name":"N20 8QP",
    "wof:placetype":"postalcode"
},
  "geometry": {"coordinates":[-0.18413248140554,51.63180416651461],"type":"Point"}
}