{
  "type": "Feature",
  "properties": {
    "date:inception_lower":"1980-01-01",
    "date:inception_upper":"1980-01-31",
    "iso:country":"GB",
    "wof:name":"N20 8QP",
    "wof:placetype":"postalcode"
},
  "geometry": {"coordinates":[-0.184132,51.631804],"type":"Point"}
}