{
  "type": "Feature",
  "properties": {
    "date:inception_lower": "1981-06-01",
    "date:inception_upper": "1981-06-01",
    "iso:country": "GB",
    "wof:name": "ME6 5RL",
    "wof:placetype": "postalcode"
  },
  "geometry": {"coordinates":[0.432439,51.331925],"type":"Point"}
}
