{
  "type": "Feature",
  "properties": {
    "iso:country":"GB",
    "wof:name":"ME6 5RL",
    "wof:placetype":"postalcode"
},
  "geometry": {"coordinates":[0.43243923220503,51.33192537835257],"type":"Point"}
}