{
  "type": "Feature",
  "properties": {
    "iso:country":"GB",
    "wof:name":"GU17 9HS",
    "wof:placetype":"postalcode"
},
  "geometry": {"coordinates":[-0.77882633688592,51.31683647896831],"type":"Point"}
}