{
  "type": "Feature",
  "properties": {
    "iso:country": "GB",
    "wof:name": "GU17 9HS",
    "wof:placetype": "postalcode"
  },
  "geometry": {"coordinates":[-0.77753,51.315816],"type":"Point"}
}
