{
  "type": "Feature",
  "properties": {
    "iso:country": "GB",
    "wof:name": "SK12 1RL",
    "wof:placetype": "postalcode"
  },
  "geometry": {"coordinates":[-2.108549,53.347425],"type":"Point"}
}
