{
  "type": "Feature",
  "properties": {
    "iso:country":"GB",
    "wof:name":"DL8 4LY",
    "wof:placetype":"postalcode"
},
  "geometry": {"coordinates":[-1.90573273610451,54.29066632360246],"type":"Point"}
}