{
  "type": "Feature",
  "properties": {
    "iso:country": "GB",
    "wof:name": "TS10 3QA",
    "wof:placetype": "postalcode"
  },
  "geometry": {"coordinates":[-1.047978,54.607015],"type":"Point"}
}
