{
  "type": "Feature",
  "properties": {
    "iso:country":"GB",
    "wof:name":"TS10 3QA",
    "wof:placetype":"postalcode"
},
  "geometry": {"coordinates":[-1.04797822386729,54.60701521091875],"type":"Point"}
}