{
  "type": "Feature",
  "properties": {
    "date:inception_lower":"1980-01-01",
    "date:inception_upper":"1980-01-31",
    "iso:country":"GB",
    "wof:name":"EH14 5BE",
    "wof:placetype":"postalcode"
},
  "geometry": {"coordinates":[-3.274751,55.908333],"type":"Point"}
}