{
  "type": "Feature",
  "properties": {
    "iso:country": "GB",
    "wof:name": "BS39 6UG",
    "wof:placetype": "postalcode"
  },
  "geometry": {"coordinates":[-2.530354,51.298147],"type":"Point"}
}
