{
  "type": "Feature",
  "properties": {
    "date:inception_lower": "2009-08-01",
    "date:inception_upper": "2009-08-01",
    "iso:country": "GB",
    "wof:name": "SO22 6EJ",
    "wof:placetype": "postalcode"
  },
  "geometry": {"coordinates":[-1.320574,51.067978],"type":"Point"}
}
