{
  "type": "Feature",
  "properties": {
    "iso:country":"GB",
    "wof:name":"SO22 6EJ",
    "wof:placetype":"postalcode"
},
  "geometry": {"coordinates":[-1.3205735403611,51.06797834240597],"type":"Point"}
}