{
  "type": "Feature",
  "properties": {
    "iso:country": "GB",
    "wof:name": "NR18 0GJ",
    "wof:placetype": "postalcode"
  },
  "geometry": {"coordinates":[1.143339,52.587015],"type":"Point"}
}
