{
  "type": "Feature",
  "properties": {
    "date:inception_lower": "1992-08-01",
    "date:inception_upper": "1992-08-01",
    "iso:country": "GB",
    "wof:name": "CO4 5YA",
    "wof:placetype": "postalcode"
  },
  "geometry": {"coordinates":[0.905617,51.916364],"type":"Point"}
}
