{
  "type": "Feature",
  "properties": {
    "iso:country":"GB",
    "wof:name":"W1K 5JH",
    "wof:placetype":"postalcode"
},
  "geometry": {"coordinates":[-0.14872570151067,51.51294697717091],"type":"Point"}
}