{
  "type": "Feature",
  "properties": {
    "iso:country":"GB",
    "wof:name":"NW10 5YB",
    "wof:placetype":"postalcode"
},
  "geometry": {"coordinates":[-0.23983247106714,51.53513096761083],"type":"Point"}
}