{
  "type": "Feature",
  "properties": {
    "iso:country": "GB",
    "wof:name": "NW10 5YB",
    "wof:placetype": "postalcode"
  },
  "geometry": {"coordinates":[-0.239832,51.535131],"type":"Point"}
}
