{
  "type": "Feature",
  "properties": {
    "date:inception_lower": "1995-07-01",
    "date:inception_upper": "1995-07-01",
    "iso:country": "GB",
    "wof:name": "OL15 9LS",
    "wof:placetype": "postalcode"
  },
  "geometry": {"coordinates":[-2.113122,53.649359],"type":"Point"}
}
