{
  "type": "Feature",
  "properties": {
    "iso:country":"GB",
    "wof:name":"OL15 9LS",
    "wof:placetype":"postalcode"
},
  "geometry": {"coordinates":[-2.11312223573961,53.64935919047267],"type":"Point"}
}