{
  "type": "Feature",
  "properties": {
    "iso:country":"GB",
    "wof:name":"BB3 1PG",
    "wof:placetype":"postalcode"
},
  "geometry": {"coordinates":[-2.48003641123652,53.70169585521545],"type":"Point"}
}