{
  "type": "Feature",
  "properties": {
    "iso:country": "GB",
    "wof:name": "BB3 1PG",
    "wof:placetype": "postalcode"
  },
  "geometry": {"coordinates":[-2.480036,53.701696],"type":"Point"}
}
