{
  "type": "Feature",
  "properties": {
    "iso:country": "GB",
    "wof:name": "BL4 9DB",
    "wof:placetype": "postalcode"
  },
  "geometry": {"coordinates":[-2.388812,53.543042],"type":"Point"}
}
