{
  "type": "Feature",
  "properties": {
    "iso:country":"GB",
    "wof:name":"BL4 9DB",
    "wof:placetype":"postalcode"
},
  "geometry": {"coordinates":[-2.38881212582809,53.54304212513332],"type":"Point"}
}