{
  "type": "Feature",
  "properties": {
    "iso:country":"GB",
    "wof:name":"IV30 6YH",
    "wof:placetype":"postalcode"
},
  "geometry": {"coordinates":[-3.31871824034028,57.63784457177521],"type":"Point"}
}