{
  "type": "Feature",
  "properties": {
    "date:inception_lower": "2023-09-01",
    "date:inception_upper": "2023-09-01",
    "iso:country": "GB",
    "wof:name": "TN23 3UW",
    "wof:placetype": "postalcode"
  },
  "geometry": {"coordinates":[0.819081,51.133933],"type":"Point"}
}
