{
  "type": "Feature",
  "properties": {
    "date:inception_lower": "1980-01-01",
    "date:inception_upper": "1980-01-01",
    "iso:country": "GB",
    "wof:name": "G84 9ED",
    "wof:placetype": "postalcode"
  },
  "geometry": {"coordinates":[-4.686051,56.032504],"type":"Point"}
}
