{
  "type": "Feature",
  "properties": {
    "iso:country": "GB",
    "wof:name": "SS3 9LF",
    "wof:placetype": "postalcode"
  },
  "geometry": {"coordinates":[0.779657,51.528619],"type":"Point"}
}
