{
  "type": "Feature",
  "properties": {
    "iso:country":"GB",
    "wof:name":"AB39 2JT",
    "wof:placetype":"postalcode"
},
  "geometry": {"coordinates":[-2.20431095656795,56.96073144638132],"type":"Point"}
}