{
  "type": "Feature",
  "properties": {
    "iso:country": "GB",
    "wof:name": "NE30 3ER",
    "wof:placetype": "postalcode"
  },
  "geometry": {"coordinates":[-1.442755,55.03266],"type":"Point"}
}
