{
  "type": "Feature",
  "properties": {
    "iso:country":"GB",
    "wof:name":"NE30 3ER",
    "wof:placetype":"postalcode"
},
  "geometry": {"coordinates":[-1.44277261545583,55.03266129350541],"type":"Point"}
}