{
  "type": "Feature",
  "properties": {
    "iso:country":"GB",
    "wof:name":"BH9 1QJ",
    "wof:placetype":"postalcode"
},
  "geometry": {"coordinates":[-1.86276236620358,50.74600125897028],"type":"Point"}
}