{
  "type": "Feature",
  "properties": {
    "iso:country":"GB",
    "wof:name":"SL4 2SJ",
    "wof:placetype":"postalcode"
},
  "geometry": {"coordinates":[-0.57422529756189,51.45158460561753],"type":"Point"}
}