{
  "type": "Feature",
  "properties": {
    "date:inception_lower": "1980-01-01",
    "date:inception_upper": "1980-01-01",
    "iso:country": "GB",
    "wof:name": "PE24 4AT",
    "wof:placetype": "postalcode"
  },
  "geometry": {"coordinates":[0.304602,53.112963],"type":"Point"}
}
