{
  "type": "Feature",
  "properties": {
    "iso:country":"GB",
    "wof:name":"HP2 5LG",
    "wof:placetype":"postalcode"
},
  "geometry": {"coordinates":[-0.45430089657432,51.7606232414713],"type":"Point"}
}