{
  "type": "Feature",
  "properties": {
    "iso:country":"GB",
    "wof:name":"NR15 1TP",
    "wof:placetype":"postalcode"
},
  "geometry": {"coordinates":[1.28553561335704,52.53224081105159],"type":"Point"}
}