{
  "type": "Feature",
  "properties": {
    "iso:country": "GB",
    "wof:name": "CW10 9LR",
    "wof:placetype": "postalcode"
  },
  "geometry": {"coordinates":[-2.385885,53.21244],"type":"Point"}
}
