{
  "type": "Feature",
  "properties": {
    "iso:country":"GB",
    "wof:name":"TF6 6PA",
    "wof:placetype":"postalcode"
},
  "geometry": {"coordinates":[-2.53681430678817,52.77089505886196],"type":"Point"}
}