{
  "type": "Feature",
  "properties": {
    "date:inception_lower":"1980-01-01",
    "date:inception_upper":"1980-01-31",
    "iso:country":"GB",
    "wof:name":"TF6 6PA",
    "wof:placetype":"postalcode"
},
  "geometry": {"coordinates":[-2.536814,52.770895],"type":"Point"}
}