{
  "type": "Feature",
  "properties": {
    "iso:country": "GB",
    "wof:name": "IP13 7PW",
    "wof:placetype": "postalcode"
  },
  "geometry": {"coordinates":[1.273357,52.15783],"type":"Point"}
}
