{
  "type": "Feature",
  "properties": {
    "date:inception_lower":"1980-01-01",
    "date:inception_upper":"1980-01-31",
    "iso:country":"GB",
    "wof:name":"SN12 7BZ",
    "wof:placetype":"postalcode"
},
  "geometry": {"coordinates":[-2.127004,51.377549],"type":"Point"}
}