{
  "type": "Feature",
  "properties": {
    "date:inception_lower":"1980-01-01",
    "date:inception_upper":"1980-01-31",
    "iso:country":"GB",
    "wof:name":"NW9 9LJ",
    "wof:placetype":"postalcode"
},
  "geometry": {"coordinates":[-0.281357,51.593342],"type":"Point"}
}