{
  "type": "Feature",
  "properties": {
    "iso:country":"GB",
    "wof:name":"M30 9BB",
    "wof:placetype":"postalcode"
},
  "geometry": {"coordinates":[-2.33433166190517,53.49087634626602],"type":"Point"}
}