{
  "type": "Feature",
  "properties": {
    "iso:country": "GB",
    "wof:name": "SN12 7EP",
    "wof:placetype": "postalcode"
  },
  "geometry": {"coordinates":[-2.137079,51.370503],"type":"Point"}
}
