{
  "type": "Feature",
  "properties": {
    "date:inception_lower": "1993-08-01",
    "date:inception_upper": "1993-08-01",
    "iso:country": "GB",
    "wof:name": "SN12 7EP",
    "wof:placetype": "postalcode"
  },
  "geometry": {"coordinates":[-2.137079,51.370503],"type":"Point"}
}
