{
  "type": "Feature",
  "properties": {
    "iso:country":"GB",
    "wof:name":"SN12 7EP",
    "wof:placetype":"postalcode"
},
  "geometry": {"coordinates":[-2.13702657687328,51.37060476809818],"type":"Point"}
}