{
  "type": "Feature",
  "properties": {
    "iso:country":"GB",
    "wof:name":"WF12 0EQ",
    "wof:placetype":"postalcode"
},
  "geometry": {"coordinates":[-1.62995322865024,53.66138943343746],"type":"Point"}
}