{
  "type": "Feature",
  "properties": {
    "iso:country":"GB",
    "wof:name":"BS16 5QE",
    "wof:placetype":"postalcode"
},
  "geometry": {"coordinates":[-2.49175379298837,51.48428675297731],"type":"Point"}
}