{
  "type": "Feature",
  "properties": {
    "iso:country":"GB",
    "wof:name":"TA6 6GA",
    "wof:placetype":"postalcode"
},
  "geometry": {"coordinates":[-2.99524018935284,51.11011665233445],"type":"Point"}
}