{
  "type": "Feature",
  "properties": {
    "iso:country":"GB",
    "wof:name":"ML3 7LL",
    "wof:placetype":"postalcode"
},
  "geometry": {"coordinates":[-4.04015303652098,55.76664634304572],"type":"Point"}
}