{
  "type": "Feature",
  "properties": {
    "iso:country":"GB",
    "wof:name":"CF14 5BN",
    "wof:placetype":"postalcode"
},
  "geometry": {"coordinates":[-3.19463540622436,51.53214872333274],"type":"Point"}
}