{
  "type": "Feature",
  "properties": {
    "iso:country":"GB",
    "wof:name":"BA2 8TP",
    "wof:placetype":"postalcode"
},
  "geometry": {"coordinates":[-2.41449248496749,51.31440906308213],"type":"Point"}
}