{
  "type": "Feature",
  "properties": {
    "date:inception_lower": "1995-12-01",
    "date:inception_upper": "1995-12-01",
    "iso:country": "GB",
    "wof:name": "BA2 8TP",
    "wof:placetype": "postalcode"
  },
  "geometry": {"coordinates":[-2.414492,51.314409],"type":"Point"}
}
