{
  "type": "Feature",
  "properties": {
    "date:inception_lower": "1980-01-01",
    "date:inception_upper": "1980-01-01",
    "iso:country": "GB",
    "wof:name": "EX39 6BU",
    "wof:placetype": "postalcode"
  },
  "geometry": {"coordinates":[-4.478984,50.996421],"type":"Point"}
}
