{
  "type": "Feature",
  "properties": {
    "iso:country":"GB",
    "wof:name":"EX39 6BU",
    "wof:placetype":"postalcode"
},
  "geometry": {"coordinates":[-4.47858152328743,50.99558648937836],"type":"Point"}
}