{
  "type": "Feature",
  "properties": {
    "iso:country": "GB",
    "wof:name": "EX39 6BU",
    "wof:placetype": "postalcode"
  },
  "geometry": {"coordinates":[-4.478984,50.996421],"type":"Point"}
}
