{
  "type": "Feature",
  "properties": {
    "iso:country":"GB",
    "wof:name":"LL65 2TW",
    "wof:placetype":"postalcode"
},
  "geometry": {"coordinates":[-4.61931167622181,53.28273680006036],"type":"Point"}
}