{
  "type": "Feature",
  "properties": {
    "date:inception_lower":"1995-07-01",
    "date:inception_upper":"1995-07-31",
    "iso:country":"GB",
    "wof:name":"LL65 2TW",
    "wof:placetype":"postalcode"
},
  "geometry": {"coordinates":[-4.619312,53.282737],"type":"Point"}
}