{
  "type": "Feature",
  "properties": {
    "iso:country":"GB",
    "wof:name":"L13 7EY",
    "wof:placetype":"postalcode"
},
  "geometry": {"coordinates":[-2.93112908137098,53.42411084587025],"type":"Point"}
}