{
  "type": "Feature",
  "properties": {
    "iso:country":"GB",
    "wof:name":"NR13 6NJ",
    "wof:placetype":"postalcode"
},
  "geometry": {"coordinates":[1.38990454639493,52.68987178022552],"type":"Point"}
}