{
  "type": "Feature",
  "properties": {
    "iso:country": "GB",
    "wof:name": "NR13 6NJ",
    "wof:placetype": "postalcode"
  },
  "geometry": {"coordinates":[1.389927,52.689898],"type":"Point"}
}
