{
  "type": "Feature",
  "properties": {
    "date:inception_lower": "1980-01-01",
    "date:inception_upper": "1980-01-01",
    "iso:country": "GB",
    "wof:name": "NR13 6NJ",
    "wof:placetype": "postalcode"
  },
  "geometry": {"coordinates":[1.388787,52.690848],"type":"Point"}
}
