{
  "type": "Feature",
  "properties": {
    "iso:country":"GB",
    "wof:name":"BN5 9XT",
    "wof:placetype":"postalcode"
},
  "geometry": {"coordinates":[-0.27476086349329,50.90291839349182],"type":"Point"}
}