{
  "type": "Feature",
  "properties": {
    "iso:country":"GB",
    "wof:name":"KT6 4NG",
    "wof:placetype":"postalcode"
},
  "geometry": {"coordinates":[-0.30847712189973,51.39114745335225],"type":"Point"}
}