{
  "type": "Feature",
  "properties": {
    "iso:country": "GB",
    "wof:name": "TS14 6RJ",
    "wof:placetype": "postalcode"
  },
  "geometry": {"coordinates":[-1.064014,54.561243],"type":"Point"}
}
