{
  "type": "Feature",
  "properties": {
    "iso:country": "GB",
    "wof:name": "N1 9HW",
    "wof:placetype": "postalcode"
  },
  "geometry": {"coordinates":[-0.115991,51.53158],"type":"Point"}
}
