{
  "type": "Feature",
  "properties": {
    "iso:country":"GB",
    "wof:name":"WF10 4BL",
    "wof:placetype":"postalcode"
},
  "geometry": {"coordinates":[-1.34020854130844,53.71832541315439],"type":"Point"}
}