{
  "type": "Feature",
  "properties": {
    "iso:country":"GB",
    "wof:name":"GU20 6DH",
    "wof:placetype":"postalcode"
},
  "geometry": {"coordinates":[-0.6553971174526,51.36327843571313],"type":"Point"}
}