{
  "type": "Feature",
  "properties": {
    "date:inception_lower": "1992-08-01",
    "date:inception_upper": "1992-08-01",
    "iso:country": "GB",
    "wof:name": "GU20 6DH",
    "wof:placetype": "postalcode"
  },
  "geometry": {"coordinates":[-0.655365,51.36326],"type":"Point"}
}
