{
  "type": "Feature",
  "properties": {
    "iso:country":"GB",
    "wof:name":"B78 3PF",
    "wof:placetype":"postalcode"
},
  "geometry": {"coordinates":[-1.73889493689552,52.61479260788945],"type":"Point"}
}