{
  "type": "Feature",
  "properties": {
    "iso:country":"GB",
    "wof:name":"SO53 1FG",
    "wof:placetype":"postalcode"
},
  "geometry": {"coordinates":[-1.36758262278453,50.99372279868516],"type":"Point"}
}