{
  "type": "Feature",
  "properties": {
    "iso:country":"GB",
    "wof:name":"BN16 1UA",
    "wof:placetype":"postalcode"
},
  "geometry": {"coordinates":[-0.48075146486465,50.8064250082235],"type":"Point"}
}