{
  "type": "Feature",
  "properties": {
    "date:inception_lower":"2000-06-01",
    "date:inception_upper":"2000-06-30",
    "iso:country":"GB",
    "wof:name":"BN16 1UA",
    "wof:placetype":"postalcode"
},
  "geometry": {"coordinates":[-0.480751,50.806425],"type":"Point"}
}