{
  "type": "Feature",
  "properties": {
    "date:inception_lower": "1980-01-01",
    "date:inception_upper": "1980-01-01",
    "iso:country": "GB",
    "wof:name": "BS16 6UJ",
    "wof:placetype": "postalcode"
  },
  "geometry": {"coordinates":[-2.491289,51.495942],"type":"Point"}
}
