{
  "type": "Feature",
  "properties": {
    "iso:country":"GB",
    "wof:name":"BS16 6UJ",
    "wof:placetype":"postalcode"
},
  "geometry": {"coordinates":[-2.49128865887713,51.49594175611461],"type":"Point"}
}