{
  "type": "Feature",
  "properties": {
    "iso:country":"GB",
    "wof:name":"IV30 1EQ",
    "wof:placetype":"postalcode"
},
  "geometry": {"coordinates":[-3.31034587667893,57.64907989477017],"type":"Point"}
}