{
  "type": "Feature",
  "properties": {
    "iso:country":"GB",
    "wof:name":"CM19 4BJ",
    "wof:placetype":"postalcode"
},
  "geometry": {"coordinates":[0.08103068248146,51.76668848597205],"type":"Point"}
}