{
  "type": "Feature",
  "properties": {
    "iso:country":"GB",
    "wof:name":"YO62 7HH",
    "wof:placetype":"postalcode"
},
  "geometry": {"coordinates":[-0.95577904956123,54.2512225392131],"type":"Point"}
}