{
  "type": "Feature",
  "properties": {
    "iso:country": "GB",
    "wof:name": "YO62 7HH",
    "wof:placetype": "postalcode"
  },
  "geometry": {"coordinates":[-0.955881,54.251311],"type":"Point"}
}
