{
  "type": "Feature",
  "properties": {
    "iso:country":"GB",
    "wof:name":"B49 6JN",
    "wof:placetype":"postalcode"
},
  "geometry": {"coordinates":[-1.82473106189311,52.26282894979919],"type":"Point"}
}