{
  "type": "Feature",
  "properties": {
    "iso:country": "GB",
    "wof:name": "GU34 1PN",
    "wof:placetype": "postalcode"
  },
  "geometry": {"coordinates":[-0.985663,51.142608],"type":"Point"}
}
