{
  "type": "Feature",
  "properties": {
    "iso:country":"GB",
    "wof:name":"GU34 1PN",
    "wof:placetype":"postalcode"
},
  "geometry": {"coordinates":[-0.98566288767626,51.14260829336789],"type":"Point"}
}