{
  "type": "Feature",
  "properties": {
    "date:inception_lower":"1980-01-01",
    "date:inception_upper":"1980-01-31",
    "iso:country":"GB",
    "wof:name":"GU34 1PN",
    "wof:placetype":"postalcode"
},
  "geometry": {"coordinates":[-0.985663,51.142608],"type":"Point"}
}