{
  "type": "Feature",
  "properties": {
    "iso:country":"GB",
    "wof:name":"IG8 8LQ",
    "wof:placetype":"postalcode"
},
  "geometry": {"coordinates":[0.0467955518962,51.59181889140747],"type":"Point"}
}