{
  "type": "Feature",
  "properties": {
    "iso:country":"GB",
    "wof:name":"NN16 0EW",
    "wof:placetype":"postalcode"
},
  "geometry": {"coordinates":[-0.7169065209699,52.39874463256555],"type":"Point"}
}