{
  "type": "Feature",
  "properties": {
    "iso:country":"GB",
    "wof:name":"PO19 8BN",
    "wof:placetype":"postalcode"
},
  "geometry": {"coordinates":[-0.77178390938374,50.82704612387888],"type":"Point"}
}