{
  "type": "Feature",
  "properties": {
    "date:inception_lower": "2002-06-01",
    "date:inception_upper": "2002-06-01",
    "iso:country": "GB",
    "wof:name": "PO19 8BN",
    "wof:placetype": "postalcode"
  },
  "geometry": {"coordinates":[-0.771784,50.827046],"type":"Point"}
}
