{
  "type": "Feature",
  "properties": {
    "iso:country":"GB",
    "wof:name":"TN38 9TE",
    "wof:placetype":"postalcode"
},
  "geometry": {"coordinates":[0.52672343543185,50.86870209115459],"type":"Point"}
}