{
  "type": "Feature",
  "properties": {
    "iso:country": "GB",
    "wof:name": "TN38 9TE",
    "wof:placetype": "postalcode"
  },
  "geometry": {"coordinates":[0.526723,50.868702],"type":"Point"}
}
