{
  "type": "Feature",
  "properties": {
    "date:inception_lower": "2007-08-01",
    "date:inception_upper": "2007-08-01",
    "iso:country": "GB",
    "wof:name": "ZE2 9EG",
    "wof:placetype": "postalcode"
  },
  "geometry": {"coordinates":[-1.233758,60.001543],"type":"Point"}
}
