{
  "type": "Feature",
  "properties": {
    "iso:country":"GB",
    "wof:name":"B92 0AL",
    "wof:placetype":"postalcode"
},
  "geometry": {"coordinates":[-1.6976943517084,52.42483641175938],"type":"Point"}
}