{
  "type": "Feature",
  "properties": {
    "iso:country": "GB",
    "wof:name": "B92 0AL",
    "wof:placetype": "postalcode"
  },
  "geometry": {"coordinates":[-1.697694,52.424836],"type":"Point"}
}
