{
  "type": "Feature",
  "properties": {
    "iso:country":"GB",
    "wof:name":"DA16 3QR",
    "wof:placetype":"postalcode"
},
  "geometry": {"coordinates":[0.09981888130072,51.46387706324956],"type":"Point"}
}