{
  "type": "Feature",
  "properties": {
    "iso:country": "GB",
    "wof:name": "SK10 2FA",
    "wof:placetype": "postalcode"
  },
  "geometry": {"coordinates":[-2.132661,53.280497],"type":"Point"}
}
