{
  "type": "Feature",
  "properties": {
    "date:inception_lower":"1995-12-01",
    "date:inception_upper":"1995-12-31",
    "iso:country":"GB",
    "wof:name":"SK10 2FA",
    "wof:placetype":"postalcode"
},
  "geometry": {"coordinates":[-2.132661,53.280497],"type":"Point"}
}