{
  "type": "Feature",
  "properties": {
    "iso:country":"GB",
    "wof:name":"SK10 2FA",
    "wof:placetype":"postalcode"
},
  "geometry": {"coordinates":[-2.13266056114078,53.28049740718517],"type":"Point"}
}