{
  "type": "Feature",
  "properties": {
    "iso:country":"GB",
    "wof:name":"M32 9PY",
    "wof:placetype":"postalcode"
},
  "geometry": {"coordinates":[-2.33094037885121,53.45216336697722],"type":"Point"}
}