{
  "type": "Feature",
  "properties": {
    "iso:country":"GB",
    "wof:name":"HD6 3HN",
    "wof:placetype":"postalcode"
},
  "geometry": {"coordinates":[-1.79176913988877,53.69173730127047],"type":"Point"}
}