{
  "type": "Feature",
  "properties": {
    "iso:country": "GB",
    "wof:name": "AB13 0HJ",
    "wof:placetype": "postalcode"
  },
  "geometry": {"coordinates":[-2.234009,57.104806],"type":"Point"}
}
