{
  "type": "Feature",
  "properties": {
    "iso:country":"GB",
    "wof:name":"AB13 0HJ",
    "wof:placetype":"postalcode"
},
  "geometry": {"coordinates":[-2.23400861230141,57.10480589603359],"type":"Point"}
}