{
  "type": "Feature",
  "properties": {
    "date:inception_lower": "1980-01-01",
    "date:inception_upper": "1980-01-01",
    "iso:country": "GB",
    "wof:name": "LE2 1SB",
    "wof:placetype": "postalcode"
  },
  "geometry": {"coordinates":[-1.10278,52.621663],"type":"Point"}
}
