{
  "type": "Feature",
  "properties": {
    "iso:country":"GB",
    "wof:name":"LE2 1SB",
    "wof:placetype":"postalcode"
},
  "geometry": {"coordinates":[-1.10278016026349,52.62166298364663],"type":"Point"}
}