{
  "type": "Feature",
  "properties": {
    "iso:country":"GB",
    "wof:name":"NR3 4HG",
    "wof:placetype":"postalcode"
},
  "geometry": {"coordinates":[1.30437575478311,52.65177278643325],"type":"Point"}
}