{
  "type": "Feature",
  "properties": {
    "iso:country": "GB",
    "wof:name": "HP16 0PT",
    "wof:placetype": "postalcode"
  },
  "geometry": {"coordinates":[-0.728429,51.691741],"type":"Point"}
}
