{
  "type": "Feature",
  "properties": {
    "iso:country":"GB",
    "wof:name":"CA8 1NL",
    "wof:placetype":"postalcode"
},
  "geometry": {"coordinates":[-2.73487287267584,54.9423815859275],"type":"Point"}
}