{
  "type": "Feature",
  "properties": {
    "iso:country":"GB",
    "wof:name":"SN6 7AA",
    "wof:placetype":"postalcode"
},
  "geometry": {"coordinates":[-1.70946777107418,51.63105187162667],"type":"Point"}
}