{
  "type": "Feature",
  "properties": {
    "date:inception_lower": "1980-01-01",
    "date:inception_upper": "1980-01-01",
    "iso:country": "GB",
    "wof:name": "SN6 7AA",
    "wof:placetype": "postalcode"
  },
  "geometry": {"coordinates":[-1.709468,51.631052],"type":"Point"}
}
