{
  "type": "Feature",
  "properties": {
    "iso:country":"GB",
    "wof:name":"DL8 4UL",
    "wof:placetype":"postalcode"
},
  "geometry": {"coordinates":[-1.95837250080914,54.29784968130774],"type":"Point"}
}