{
  "type": "Feature",
  "properties": {
    "iso:country": "GB",
    "wof:name": "DL8 4UL",
    "wof:placetype": "postalcode"
  },
  "geometry": {"coordinates":[-1.958372,54.29785],"type":"Point"}
}
