{
  "type": "Feature",
  "properties": {
    "iso:country":"GB",
    "wof:name":"NW8 0SF",
    "wof:placetype":"postalcode"
},
  "geometry": {"coordinates":[-0.18597895857932,51.53946324467328],"type":"Point"}
}