{
  "type": "Feature",
  "properties": {
    "date:inception_lower": "1986-07-01",
    "date:inception_upper": "1986-07-01",
    "iso:country": "GB",
    "wof:name": "NW8 0SF",
    "wof:placetype": "postalcode"
  },
  "geometry": {"coordinates":[-0.185979,51.539463],"type":"Point"}
}
