{
  "type": "Feature",
  "properties": {
    "iso:country":"GB",
    "wof:name":"W1K 1DB",
    "wof:placetype":"postalcode"
},
  "geometry": {"coordinates":[-0.15044176686549,51.5072278436122],"type":"Point"}
}