{
  "type": "Feature",
  "properties": {
    "date:inception_lower":"1990-02-01",
    "date:inception_upper":"1990-02-28",
    "iso:country":"GB",
    "wof:name":"CT7 9JJ",
    "wof:placetype":"postalcode"
},
  "geometry": {"coordinates":[1.301845,51.378756],"type":"Point"}
}