{
  "type": "Feature",
  "properties": {
    "iso:country": "GB",
    "wof:name": "CT7 9JJ",
    "wof:placetype": "postalcode"
  },
  "geometry": {"coordinates":[1.301845,51.378756],"type":"Point"}
}
