{
  "type": "Feature",
  "properties": {
    "iso:country":"GB",
    "wof:name":"SN10 5PZ",
    "wof:placetype":"postalcode"
},
  "geometry": {"coordinates":[-2.00873349470551,51.32451247699944],"type":"Point"}
}