{
  "type": "Feature",
  "properties": {
    "date:inception_lower": "1980-01-01",
    "date:inception_upper": "1980-01-01",
    "iso:country": "GB",
    "wof:name": "SN10 5PZ",
    "wof:placetype": "postalcode"
  },
  "geometry": {"coordinates":[-2.008454,51.324365],"type":"Point"}
}
