{
  "type": "Feature",
  "properties": {
    "iso:country":"GB",
    "wof:name":"EH7 6EN",
    "wof:placetype":"postalcode"
},
  "geometry": {"coordinates":[-3.14728122660762,55.96226805176654],"type":"Point"}
}