{
  "type": "Feature",
  "properties": {
    "iso:country": "GB",
    "wof:name": "EH7 6EN",
    "wof:placetype": "postalcode"
  },
  "geometry": {"coordinates":[-3.147281,55.962268],"type":"Point"}
}
