{
  "type": "Feature",
  "properties": {
    "iso:country":"GB",
    "wof:name":"GL12 8US",
    "wof:placetype":"postalcode"
},
  "geometry": {"coordinates":[-2.48058220540977,51.59547669232097],"type":"Point"}
}