{
  "type": "Feature",
  "properties": {
    "iso:country":"GB",
    "wof:name":"OX18 3AT",
    "wof:placetype":"postalcode"
},
  "geometry": {"coordinates":[-1.59884054817586,51.76219579385695],"type":"Point"}
}