{
  "type": "Feature",
  "properties": {
    "date:inception_lower": "2009-03-01",
    "date:inception_upper": "2009-03-01",
    "iso:country": "GB",
    "wof:name": "BS21 7GX",
    "wof:placetype": "postalcode"
  },
  "geometry": {"coordinates":[-2.823895,51.465742],"type":"Point"}
}
