{
  "type": "Feature",
  "properties": {
    "iso:country": "GB",
    "wof:name": "BS21 7GX",
    "wof:placetype": "postalcode"
  },
  "geometry": {"coordinates":[-2.823895,51.465742],"type":"Point"}
}
