{
  "type": "Feature",
  "properties": {
    "iso:country":"GB",
    "wof:name":"BS21 7GX",
    "wof:placetype":"postalcode"
},
  "geometry": {"coordinates":[-2.82417697991424,51.4656514779462],"type":"Point"}
}