{
  "type": "Feature",
  "properties": {
    "iso:country": "GB",
    "wof:name": "WD25 7EZ",
    "wof:placetype": "postalcode"
  },
  "geometry": {"coordinates":[-0.400519,51.695243],"type":"Point"}
}
