{
  "type": "Feature",
  "properties": {
    "date:inception_lower": "2018-11-01",
    "date:inception_upper": "2018-11-01",
    "iso:country": "GB",
    "wof:name": "WA12 9ZN",
    "wof:placetype": "postalcode"
  },
  "geometry": {"coordinates":[-2.650343,53.450283],"type":"Point"}
}
