{
  "type": "Feature",
  "properties": {
    "iso:country": "GB",
    "wof:name": "G21 4DA",
    "wof:placetype": "postalcode"
  },
  "geometry": {"coordinates":[-4.232064,55.879018],"type":"Point"}
}
