{
  "type": "Feature",
  "properties": {
    "iso:country":"GB",
    "wof:name":"G21 4DA",
    "wof:placetype":"postalcode"
},
  "geometry": {"coordinates":[-4.23207779390291,55.87902268854126],"type":"Point"}
}