{
  "type": "Feature",
  "properties": {
    "date:inception_lower":"1990-09-01",
    "date:inception_upper":"1990-09-30",
    "iso:country":"GB",
    "wof:name":"G21 4DA",
    "wof:placetype":"postalcode"
},
  "geometry": {"coordinates":[-4.232064,55.879018],"type":"Point"}
}