{
  "type": "Feature",
  "properties": {
    "date:inception_lower":"1980-01-01",
    "date:inception_upper":"1980-01-31",
    "iso:country":"GB",
    "wof:name":"CA1 3SX",
    "wof:placetype":"postalcode"
},
  "geometry": {"coordinates":[-2.883741,54.874932],"type":"Point"}
}