{
  "type": "Feature",
  "properties": {
    "iso:country":"GB",
    "wof:name":"CA1 3SX",
    "wof:placetype":"postalcode"
},
  "geometry": {"coordinates":[-2.88390836972488,54.87491480593066],"type":"Point"}
}