{
  "type": "Feature",
  "properties": {
    "iso:country":"GB",
    "wof:name":"EN4 8UA",
    "wof:placetype":"postalcode"
},
  "geometry": {"coordinates":[-0.15895921568494,51.64256258982533],"type":"Point"}
}