{
  "type": "Feature",
  "properties": {
    "iso:country":"GB",
    "wof:name":"B97 4DQ",
    "wof:placetype":"postalcode"
},
  "geometry": {"coordinates":[-1.93968721761339,52.30915328519364],"type":"Point"}
}