{
  "type": "Feature",
  "properties": {
    "iso:country":"GB",
    "wof:name":"LN9 6DF",
    "wof:placetype":"postalcode"
},
  "geometry": {"coordinates":[-0.1067471911226,53.20189397502356],"type":"Point"}
}