{
  "type": "Feature",
  "properties": {
    "iso:country": "GB",
    "wof:name": "LN9 6DF",
    "wof:placetype": "postalcode"
  },
  "geometry": {"coordinates":[-0.106716,53.201891],"type":"Point"}
}
