{
  "type": "Feature",
  "properties": {
    "date:inception_lower": "1980-01-01",
    "date:inception_upper": "1980-01-01",
    "iso:country": "GB",
    "wof:name": "S5 8UL",
    "wof:placetype": "postalcode"
  },
  "geometry": {"coordinates":[-1.483941,53.412822],"type":"Point"}
}
