{
  "type": "Feature",
  "properties": {
    "iso:country":"GB",
    "wof:name":"S5 8UL",
    "wof:placetype":"postalcode"
},
  "geometry": {"coordinates":[-1.48394070710589,53.4127951080893],"type":"Point"}
}