{
  "type": "Feature",
  "properties": {
    "iso:country":"GB",
    "wof:name":"PL30 5DE",
    "wof:placetype":"postalcode"
},
  "geometry": {"coordinates":[-4.72564890739772,50.40921911980078],"type":"Point"}
}