{
  "type": "Feature",
  "properties": {
    "date:inception_lower": "2017-10-01",
    "date:inception_upper": "2017-10-01",
    "iso:country": "GB",
    "wof:name": "CM14 4GQ",
    "wof:placetype": "postalcode"
  },
  "geometry": {"coordinates":[0.302069,51.620752],"type":"Point"}
}
