{
  "type": "Feature",
  "properties": {
    "date:inception_lower": "1980-01-01",
    "date:inception_upper": "1980-01-01",
    "iso:country": "GB",
    "wof:name": "SE24 9DQ",
    "wof:placetype": "postalcode"
  },
  "geometry": {"coordinates":[-0.099328,51.448022],"type":"Point"}
}
