{
  "type": "Feature",
  "properties": {
    "iso:country":"GB",
    "wof:name":"NE2 1AZ",
    "wof:placetype":"postalcode"
},
  "geometry": {"coordinates":[-1.59767010119936,54.97687395910115],"type":"Point"}
}