{
  "type": "Feature",
  "properties": {
    "iso:country": "GB",
    "wof:name": "NE2 1AZ",
    "wof:placetype": "postalcode"
  },
  "geometry": {"coordinates":[-1.59767,54.976874],"type":"Point"}
}
