{
  "type": "Feature",
  "properties": {
    "iso:country": "GB",
    "wof:name": "HG4 3PP",
    "wof:placetype": "postalcode"
  },
  "geometry": {"coordinates":[-1.663661,54.122139],"type":"Point"}
}
