{
  "type": "Feature",
  "properties": {
    "date:inception_lower":"1980-01-01",
    "date:inception_upper":"1980-01-31",
    "iso:country":"GB",
    "wof:name":"DA16 3QU",
    "wof:placetype":"postalcode"
},
  "geometry": {"coordinates":[0.090414,51.465997],"type":"Point"}
}