{
  "type": "Feature",
  "properties": {
    "iso:country":"GB",
    "wof:name":"LL54 7EE",
    "wof:placetype":"postalcode"
},
  "geometry": {"coordinates":[-4.27906141229299,53.08278558319047],"type":"Point"}
}