{
  "type": "Feature",
  "properties": {
    "date:inception_lower": "1980-01-01",
    "date:inception_upper": "1980-01-01",
    "iso:country": "GB",
    "wof:name": "SA14 6ST",
    "wof:placetype": "postalcode"
  },
  "geometry": {"coordinates":[-4.08816,51.797271],"type":"Point"}
}
