{
  "type": "Feature",
  "properties": {
    "iso:country": "GB",
    "wof:name": "OX10 7BQ",
    "wof:placetype": "postalcode"
  },
  "geometry": {"coordinates":[-1.137677,51.661775],"type":"Point"}
}
