{
  "type": "Feature",
  "properties": {
    "iso:country":"GB",
    "wof:name":"DE7 8NA",
    "wof:placetype":"postalcode"
},
  "geometry": {"coordinates":[-1.30870344543783,52.98550530002422],"type":"Point"}
}