{
  "type": "Feature",
  "properties": {
    "date:inception_lower": "2017-11-01",
    "date:inception_upper": "2017-11-01",
    "iso:country": "GB",
    "wof:name": "IP17 2RU",
    "wof:placetype": "postalcode"
  },
  "geometry": {"coordinates":[1.458136,52.273756],"type":"Point"}
}
