{
  "type": "Feature",
  "properties": {
    "date:inception_lower":"1987-10-01",
    "date:inception_upper":"1987-10-31",
    "iso:country":"GB",
    "wof:name":"TA18 7BY",
    "wof:placetype":"postalcode"
},
  "geometry": {"coordinates":[-2.79146,50.888761],"type":"Point"}
}