{
  "type": "Feature",
  "properties": {
    "iso:country":"GB",
    "wof:name":"TA18 7BY",
    "wof:placetype":"postalcode"
},
  "geometry": {"coordinates":[-2.79145993524315,50.88876105096087],"type":"Point"}
}