{
  "type": "Feature",
  "properties": {
    "iso:country": "GB",
    "wof:name": "PH33 6HU",
    "wof:placetype": "postalcode"
  },
  "geometry": {"coordinates":[-5.104278,56.815339],"type":"Point"}
}
