{
  "type": "Feature",
  "properties": {
    "date:inception_lower": "1980-01-01",
    "date:inception_upper": "1980-01-01",
    "iso:country": "GB",
    "wof:name": "PH33 6HU",
    "wof:placetype": "postalcode"
  },
  "geometry": {"coordinates":[-5.104278,56.815339],"type":"Point"}
}
