{
  "type": "Feature",
  "properties": {
    "iso:country":"GB",
    "wof:name":"SO15 1JE",
    "wof:placetype":"postalcode"
},
  "geometry": {"coordinates":[-1.42306993376941,50.90845610406868],"type":"Point"}
}