{
  "type": "Feature",
  "properties": {
    "iso:country":"GB",
    "wof:name":"AB11 5PW",
    "wof:placetype":"postalcode"
},
  "geometry": {"coordinates":[-2.09017794564561,57.14495769178026],"type":"Point"}
}