{
  "type": "Feature",
  "properties": {
    "date:inception_lower": "2019-04-01",
    "date:inception_upper": "2019-04-01",
    "iso:country": "GB",
    "wof:name": "AB11 5PW",
    "wof:placetype": "postalcode"
  },
  "geometry": {"coordinates":[-2.090185,57.144942],"type":"Point"}
}
