{
  "type": "Feature",
  "properties": {
    "iso:country":"GB",
    "wof:name":"BH6 3AG",
    "wof:placetype":"postalcode"
},
  "geometry": {"coordinates":[-1.79379137836195,50.72719513133178],"type":"Point"}
}