{
  "type": "Feature",
  "properties": {
    "iso:country": "GB",
    "wof:name": "PO19 8PP",
    "wof:placetype": "postalcode"
  },
  "geometry": {"coordinates":[-0.76507,50.831265],"type":"Point"}
}
