{
  "type": "Feature",
  "properties": {
    "iso:country":"GB",
    "wof:name":"S65 3HS",
    "wof:placetype":"postalcode"
},
  "geometry": {"coordinates":[-1.30444121573242,53.42223098046526],"type":"Point"}
}