{
  "type": "Feature",
  "properties": {
    "iso:country":"GB",
    "wof:name":"RM13 7AP",
    "wof:placetype":"postalcode"
},
  "geometry": {"coordinates":[0.19290103108035,51.53301915414577],"type":"Point"}
}