{
  "type": "Feature",
  "properties": {
    "iso:country": "GB",
    "wof:name": "M16 0WW",
    "wof:placetype": "postalcode"
  },
  "geometry": {"coordinates":[-2.277772,53.457054],"type":"Point"}
}
