{
  "type": "Feature",
  "properties": {
    "iso:country":"GB",
    "wof:name":"SO41 0UR",
    "wof:placetype":"postalcode"
},
  "geometry": {"coordinates":[-1.59293331964808,50.72390662921294],"type":"Point"}
}