{
  "type": "Feature",
  "properties": {
    "iso:country":"GB",
    "wof:name":"WN6 0LE",
    "wof:placetype":"postalcode"
},
  "geometry": {"coordinates":[-2.66497375299534,53.58946380482219],"type":"Point"}
}