{
  "type": "Feature",
  "properties": {
    "iso:country":"GB",
    "wof:name":"BD3 7AD",
    "wof:placetype":"postalcode"
},
  "geometry": {"coordinates":[-1.70890775650433,53.79872055418986],"type":"Point"}
}