{
  "type": "Feature",
  "properties": {
    "date:inception_lower": "1980-01-01",
    "date:inception_upper": "1980-01-01",
    "iso:country": "GB",
    "wof:name": "BD3 7AD",
    "wof:placetype": "postalcode"
  },
  "geometry": {"coordinates":[-1.708908,53.798721],"type":"Point"}
}
