{
  "type": "Feature",
  "properties": {
    "date:inception_lower": "1980-01-01",
    "date:inception_upper": "1980-01-01",
    "iso:country": "GB",
    "wof:name": "ST14 8DN",
    "wof:placetype": "postalcode"
  },
  "geometry": {"coordinates":[-1.87921,52.891609],"type":"Point"}
}
