{
  "type": "Feature",
  "properties": {
    "iso:country":"GB",
    "wof:name":"ST14 8DN",
    "wof:placetype":"postalcode"
},
  "geometry": {"coordinates":[-1.87920971208216,52.89160879412388],"type":"Point"}
}