{
  "type": "Feature",
  "properties": {
    "iso:country":"GB",
    "wof:name":"PO22 9PR",
    "wof:placetype":"postalcode"
},
  "geometry": {"coordinates":[-0.67644903555974,50.7935480021888],"type":"Point"}
}