{
  "type": "Feature",
  "properties": {
    "date:inception_lower": "2020-06-01",
    "date:inception_upper": "2020-06-01",
    "iso:country": "GB",
    "wof:name": "BD7 3AU",
    "wof:placetype": "postalcode"
  },
  "geometry": {"coordinates":[-1.776479,53.788643],"type":"Point"}
}
