{
  "type": "Feature",
  "properties": {
    "date:inception_lower": "1980-01-01",
    "date:inception_upper": "1980-01-01",
    "iso:country": "GB",
    "wof:name": "M34 2WW",
    "wof:placetype": "postalcode"
  },
  "geometry": {"coordinates":[-2.154974,53.453151],"type":"Point"}
}
