{
  "type": "Feature",
  "properties": {
    "iso:country":"GB",
    "wof:name":"SG19 3ES",
    "wof:placetype":"postalcode"
},
  "geometry": {"coordinates":[-0.17328450045934,52.15814099600729],"type":"Point"}
}