{
  "type": "Feature",
  "properties": {
    "date:inception_lower": "2023-07-01",
    "date:inception_upper": "2023-07-01",
    "iso:country": "GB",
    "wof:name": "PR26 6AS",
    "wof:placetype": "postalcode"
  },
  "geometry": {"coordinates":[-2.713902,53.71029],"type":"Point"}
}
