{
  "type": "Feature",
  "properties": {
    "iso:country": "GB",
    "wof:name": "CT20 1AN",
    "wof:placetype": "postalcode"
  },
  "geometry": {"coordinates":[1.179589,51.080956],"type":"Point"}
}
