{
  "type": "Feature",
  "properties": {
    "iso:country":"GB",
    "wof:name":"CT20 1AN",
    "wof:placetype":"postalcode"
},
  "geometry": {"coordinates":[1.17958929389041,51.08095604999028],"type":"Point"}
}