{
  "type": "Feature",
  "properties": {
    "date:inception_lower": "2014-01-01",
    "date:inception_upper": "2014-01-01",
    "iso:country": "GB",
    "wof:name": "CT20 1AN",
    "wof:placetype": "postalcode"
  },
  "geometry": {"coordinates":[1.179948,51.08051],"type":"Point"}
}
