{
  "type": "Feature",
  "properties": {
    "iso:country":"GB",
    "wof:name":"WD18 7QD",
    "wof:placetype":"postalcode"
},
  "geometry": {"coordinates":[-0.41910969130857,51.65209911666243],"type":"Point"}
}