{
  "type": "Feature",
  "properties": {
    "iso:country":"GB",
    "wof:name":"HU14 3HR",
    "wof:placetype":"postalcode"
},
  "geometry": {"coordinates":[-0.53192417473877,53.72633170133109],"type":"Point"}
}