{
  "type": "Feature",
  "properties": {
    "iso:country": "GB",
    "wof:name": "HU14 3HR",
    "wof:placetype": "postalcode"
  },
  "geometry": {"coordinates":[-0.531924,53.726332],"type":"Point"}
}
