{
  "type": "Feature",
  "properties": {
    "date:inception_lower":"1980-01-01",
    "date:inception_upper":"1980-01-31",
    "iso:country":"GB",
    "wof:name":"HU14 3HR",
    "wof:placetype":"postalcode"
},
  "geometry": {"coordinates":[-0.531924,53.726332],"type":"Point"}
}