{
  "type": "Feature",
  "properties": {
    "date:inception_lower": "2022-08-01",
    "date:inception_upper": "2022-08-01",
    "iso:country": "GB",
    "wof:name": "RG45 6UF",
    "wof:placetype": "postalcode"
  },
  "geometry": {"coordinates":[-0.790502,51.379642],"type":"Point"}
}
