{
  "type": "Feature",
  "properties": {
    "date:inception_lower": "2022-10-01",
    "date:inception_upper": "2022-10-01",
    "iso:country": "GB",
    "wof:name": "HX3 5FJ",
    "wof:placetype": "postalcode"
  },
  "geometry": {"coordinates":[-1.899023,53.740102],"type":"Point"}
}
