{
  "type": "Feature",
  "properties": {
    "iso:country":"GB",
    "wof:name":"RH10 3AH",
    "wof:placetype":"postalcode"
},
  "geometry": {"coordinates":[-0.15502453814291,51.12448707492008],"type":"Point"}
}