{
  "type": "Feature",
  "properties": {
    "iso:country":"GB",
    "wof:name":"RM6 4RR",
    "wof:placetype":"postalcode"
},
  "geometry": {"coordinates":[0.12101907918638,51.57045602920817],"type":"Point"}
}