{
  "type": "Feature",
  "properties": {
    "iso:country":"GB",
    "wof:name":"BD1 4HA",
    "wof:placetype":"postalcode"
},
  "geometry": {"coordinates":[-1.74696960898095,53.79866300299875],"type":"Point"}
}