{
  "type": "Feature",
  "properties": {
    "iso:country": "GB",
    "wof:name": "BD1 4HA",
    "wof:placetype": "postalcode"
  },
  "geometry": {"coordinates":[-1.746973,53.798678],"type":"Point"}
}
