{
  "type": "Feature",
  "properties": {
    "iso:country":"GB",
    "wof:name":"SA3 1DR",
    "wof:placetype":"postalcode"
},
  "geometry": {"coordinates":[-4.24381875105724,51.60567099592552],"type":"Point"}
}