{
  "type": "Feature",
  "properties": {
    "iso:country":"GB",
    "wof:name":"SS0 0EN",
    "wof:placetype":"postalcode"
},
  "geometry": {"coordinates":[0.67964090469874,51.56041044232143],"type":"Point"}
}