{
  "type": "Feature",
  "properties": {
    "iso:country": "GB",
    "wof:name": "SS0 0EN",
    "wof:placetype": "postalcode"
  },
  "geometry": {"coordinates":[0.679641,51.56041],"type":"Point"}
}
