{
  "type": "Feature",
  "properties": {
    "iso:country": "GB",
    "wof:name": "YO42 2NN",
    "wof:placetype": "postalcode"
  },
  "geometry": {"coordinates":[-0.77123,53.935967],"type":"Point"}
}
