{
  "type": "Feature",
  "properties": {
    "date:inception_lower":"1986-07-01",
    "date:inception_upper":"1986-07-31",
    "iso:country":"GB",
    "wof:name":"CT19 5TU",
    "wof:placetype":"postalcode"
},
  "geometry": {"coordinates":[1.160241,51.091232],"type":"Point"}
}