{
  "type": "Feature",
  "properties": {
    "iso:country":"GB",
    "wof:name":"CT19 5TU",
    "wof:placetype":"postalcode"
},
  "geometry": {"coordinates":[1.16024062973886,51.09123171575137],"type":"Point"}
}