{
  "type": "Feature",
  "properties": {
    "iso:country":"GB",
    "wof:name":"RH8 0AB",
    "wof:placetype":"postalcode"
},
  "geometry": {"coordinates":[-0.00160896627643,51.26021667826412],"type":"Point"}
}