{
  "type": "Feature",
  "properties": {
    "date:inception_lower": "1980-01-01",
    "date:inception_upper": "1980-01-01",
    "iso:country": "GB",
    "wof:name": "RH8 0AB",
    "wof:placetype": "postalcode"
  },
  "geometry": {"coordinates":[-0.001609,51.260217],"type":"Point"}
}
