{
  "type": "Feature",
  "properties": {
    "iso:country":"GB",
    "wof:name":"NE15 8BD",
    "wof:placetype":"postalcode"
},
  "geometry": {"coordinates":[-1.71858157845966,54.98098774194975],"type":"Point"}
}