{
  "type": "Feature",
  "properties": {
    "iso:country":"GB",
    "wof:name":"RH2 8BP",
    "wof:placetype":"postalcode"
},
  "geometry": {"coordinates":[-0.2022510111606,51.22353318962483],"type":"Point"}
}