{
  "type": "Feature",
  "properties": {
    "date:inception_lower":"2008-04-01",
    "date:inception_upper":"2008-04-30",
    "iso:country":"GB",
    "wof:name":"RH2 8BP",
    "wof:placetype":"postalcode"
},
  "geometry": {"coordinates":[-0.202251,51.223533],"type":"Point"}
}