{
  "type": "Feature",
  "properties": {
    "iso:country": "GB",
    "wof:name": "RH2 8BP",
    "wof:placetype": "postalcode"
  },
  "geometry": {"coordinates":[-0.202251,51.223533],"type":"Point"}
}
