{
  "type": "Feature",
  "properties": {
    "iso:country":"GB",
    "wof:name":"B10 0TX",
    "wof:placetype":"postalcode"
},
  "geometry": {"coordinates":[-1.84515195037148,52.46598074174217],"type":"Point"}
}