{
  "type": "Feature",
  "properties": {
    "iso:country":"GB",
    "wof:name":"TA4 1JZ",
    "wof:placetype":"postalcode"
},
  "geometry": {"coordinates":[-3.2531856202705,51.02338437321669],"type":"Point"}
}