{
  "type": "Feature",
  "properties": {
    "iso:country": "GB",
    "wof:name": "TA4 1JZ",
    "wof:placetype": "postalcode"
  },
  "geometry": {"coordinates":[-3.253186,51.023384],"type":"Point"}
}
