{
  "type": "Feature",
  "properties": {
    "iso:country":"GB",
    "wof:name":"CF72 8WL",
    "wof:placetype":"postalcode"
},
  "geometry": {"coordinates":[-3.3908630496285,51.53012973684623],"type":"Point"}
}