{
  "type": "Feature",
  "properties": {
    "iso:country": "GB",
    "wof:name": "MK11 4AX",
    "wof:placetype": "postalcode"
  },
  "geometry": {"coordinates":[-0.832752,52.044154],"type":"Point"}
}
