{
  "type": "Feature",
  "properties": {
    "iso:country":"GB",
    "wof:name":"CR2 0DF",
    "wof:placetype":"postalcode"
},
  "geometry": {"coordinates":[-0.08696004484537,51.35236269729175],"type":"Point"}
}