{
  "type": "Feature",
  "properties": {
    "date:inception_lower":"1997-06-01",
    "date:inception_upper":"1997-06-30",
    "iso:country":"GB",
    "wof:name":"S64 5UQ",
    "wof:placetype":"postalcode"
},
  "geometry": {"coordinates":[-1.310586,53.477691],"type":"Point"}
}