{
  "type": "Feature",
  "properties": {
    "date:inception_lower": "1992-01-01",
    "date:inception_upper": "1992-01-01",
    "iso:country": "GB",
    "wof:name": "OL7 0RE",
    "wof:placetype": "postalcode"
  },
  "geometry": {"coordinates":[-2.104215,53.479138],"type":"Point"}
}
