{
  "type": "Feature",
  "properties": {
    "iso:country": "GB",
    "wof:name": "NG3 5PL",
    "wof:placetype": "postalcode"
  },
  "geometry": {"coordinates":[-1.128871,52.97271],"type":"Point"}
}
