{
  "type": "Feature",
  "properties": {
    "iso:country":"GB",
    "wof:name":"HG3 5AB",
    "wof:placetype":"postalcode"
},
  "geometry": {"coordinates":[-1.78665126333189,54.10736109790388],"type":"Point"}
}