{
  "type": "Feature",
  "properties": {
    "iso:country":"GB",
    "wof:name":"BR1 5NT",
    "wof:placetype":"postalcode"
},
  "geometry": {"coordinates":[0.00481223543881,51.42572030881397],"type":"Point"}
}