{
  "type": "Feature",
  "properties": {
    "iso:country":"GB",
    "wof:name":"DG5 4JS",
    "wof:placetype":"postalcode"
},
  "geometry": {"coordinates":[-3.82231708181059,54.93467962201159],"type":"Point"}
}