{
  "type": "Feature",
  "properties": {
    "date:inception_lower":"1980-01-01",
    "date:inception_upper":"1980-01-31",
    "iso:country":"GB",
    "wof:name":"DG5 4JS",
    "wof:placetype":"postalcode"
},
  "geometry": {"coordinates":[-3.822317,54.93468],"type":"Point"}
}