{
  "type": "Feature",
  "properties": {
    "iso:country":"GB",
    "wof:name":"N20 8PD",
    "wof:placetype":"postalcode"
},
  "geometry": {"coordinates":[-0.19435488601845,51.62617978773373],"type":"Point"}
}