{
  "type": "Feature",
  "properties": {
    "iso:country":"GB",
    "wof:name":"KY15 4JB",
    "wof:placetype":"postalcode"
},
  "geometry": {"coordinates":[-3.0317916826413,56.31929376920345],"type":"Point"}
}