{
  "type": "Feature",
  "properties": {
    "iso:country":"GB",
    "wof:name":"CR8 1BE",
    "wof:placetype":"postalcode"
},
  "geometry": {"coordinates":[-0.11068685844082,51.33416872927251],"type":"Point"}
}