{
  "type": "Feature",
  "properties": {
    "iso:country":"GB",
    "wof:name":"S71 4LL",
    "wof:placetype":"postalcode"
},
  "geometry": {"coordinates":[-1.4644672233365,53.59757614266349],"type":"Point"}
}