{
  "type": "Feature",
  "properties": {
    "iso:country":"GB",
    "wof:name":"SS15 6GP",
    "wof:placetype":"postalcode"
},
  "geometry": {"coordinates":[0.42196468488819,51.58134743831383],"type":"Point"}
}