{
  "type": "Feature",
  "properties": {
    "date:inception_lower":"2009-09-01",
    "date:inception_upper":"2009-09-30",
    "iso:country":"GB",
    "wof:name":"SS15 6GP",
    "wof:placetype":"postalcode"
},
  "geometry": {"coordinates":[0.421965,51.581347],"type":"Point"}
}