{
  "type": "Feature",
  "properties": {
    "iso:country": "GB",
    "wof:name": "SS15 6GP",
    "wof:placetype": "postalcode"
  },
  "geometry": {"coordinates":[0.421965,51.581347],"type":"Point"}
}
