{
  "type": "Feature",
  "properties": {
    "iso:country":"GB",
    "wof:name":"DG7 1QZ",
    "wof:placetype":"postalcode"
},
  "geometry": {"coordinates":[-3.84444382551274,54.83523621928301],"type":"Point"}
}