{
  "type": "Feature",
  "properties": {
    "iso:country":"GB",
    "wof:name":"LU2 0FG",
    "wof:placetype":"postalcode"
},
  "geometry": {"coordinates":[-0.3977635622352,51.88853870943789],"type":"Point"}
}