{
  "type": "Feature",
  "properties": {
    "iso:country": "GB",
    "wof:name": "LU2 0FG",
    "wof:placetype": "postalcode"
  },
  "geometry": {"coordinates":[-0.397764,51.888539],"type":"Point"}
}
