{
  "type": "Feature",
  "properties": {
    "date:inception_lower":"2003-07-01",
    "date:inception_upper":"2003-07-31",
    "iso:country":"GB",
    "wof:name":"PE8 6DF",
    "wof:placetype":"postalcode"
},
  "geometry": {"coordinates":[-0.43983,52.612243],"type":"Point"}
}