{
  "type": "Feature",
  "properties": {
    "iso:country":"GB",
    "wof:name":"NE32 3NQ",
    "wof:placetype":"postalcode"
},
  "geometry": {"coordinates":[-1.48921451220167,54.98163423762042],"type":"Point"}
}