{
  "type": "Feature",
  "properties": {
    "iso:country":"GB",
    "wof:name":"BR5 1LD",
    "wof:placetype":"postalcode"
},
  "geometry": {"coordinates":[0.08505459276232,51.39103734624268],"type":"Point"}
}