{
  "type": "Feature",
  "properties": {
    "iso:country":"GB",
    "wof:name":"LE12 9QL",
    "wof:placetype":"postalcode"
},
  "geometry": {"coordinates":[-1.29889201197409,52.76676844303989],"type":"Point"}
}