{
  "type": "Feature",
  "properties": {
    "iso:country":"GB",
    "wof:name":"IP2 9AW",
    "wof:placetype":"postalcode"
},
  "geometry": {"coordinates":[1.14365158748332,52.04746342739674],"type":"Point"}
}