{
  "type": "Feature",
  "properties": {
    "date:inception_lower": "1990-07-01",
    "date:inception_upper": "1990-07-01",
    "iso:country": "GB",
    "wof:name": "BR8 7WL",
    "wof:placetype": "postalcode"
  },
  "geometry": {"coordinates":[0.175753,51.396142],"type":"Point"}
}
