{
  "type": "Feature",
  "properties": {
    "iso:country":"GB",
    "wof:name":"PH2 7NJ",
    "wof:placetype":"postalcode"
},
  "geometry": {"coordinates":[-3.29691692831226,56.37357790405803],"type":"Point"}
}