{
  "type": "Feature",
  "properties": {
    "iso:country": "GB",
    "wof:name": "NW10 1HG",
    "wof:placetype": "postalcode"
  },
  "geometry": {"coordinates":[-0.238455,51.555127],"type":"Point"}
}
