{
  "type": "Feature",
  "properties": {
    "date:inception_lower": "2001-12-01",
    "date:inception_upper": "2001-12-01",
    "iso:country": "GB",
    "wof:name": "PO1 3TY",
    "wof:placetype": "postalcode"
  },
  "geometry": {"coordinates":[-1.106357,50.795133],"type":"Point"}
}
