{
  "type": "Feature",
  "properties": {
    "iso:country":"GB",
    "wof:name":"IP21 4RN",
    "wof:placetype":"postalcode"
},
  "geometry": {"coordinates":[1.25271047644432,52.40695754363809],"type":"Point"}
}