{
  "type": "Feature",
  "properties": {
    "iso:country": "GB",
    "wof:name": "IP21 4RN",
    "wof:placetype": "postalcode"
  },
  "geometry": {"coordinates":[1.252691,52.406935],"type":"Point"}
}
