{
  "type": "Feature",
  "properties": {
    "iso:country": "GB",
    "wof:name": "RM12 4LL",
    "wof:placetype": "postalcode"
  },
  "geometry": {"coordinates":[0.215501,51.556913],"type":"Point"}
}
