{
  "type": "Feature",
  "properties": {
    "iso:country": "GB",
    "wof:name": "CO15 2PS",
    "wof:placetype": "postalcode"
  },
  "geometry": {"coordinates":[1.117286,51.783804],"type":"Point"}
}
