{
  "type": "Feature",
  "properties": {
    "iso:country":"GB",
    "wof:name":"DG13 0HJ",
    "wof:placetype":"postalcode"
},
  "geometry": {"coordinates":[-2.98846340848022,55.20778843219576],"type":"Point"}
}