{
  "type": "Feature",
  "properties": {
    "date:inception_lower": "1980-01-01",
    "date:inception_upper": "1980-01-01",
    "iso:country": "GB",
    "wof:name": "DG13 0HJ",
    "wof:placetype": "postalcode"
  },
  "geometry": {"coordinates":[-2.988463,55.207788],"type":"Point"}
}
