{
  "type": "Feature",
  "properties": {
    "date:inception_lower": "2022-07-01",
    "date:inception_upper": "2022-07-01",
    "iso:country": "GB",
    "wof:name": "RG7 3WB",
    "wof:placetype": "postalcode"
  },
  "geometry": {"coordinates":[-1.059265,51.374285],"type":"Point"}
}
