{
  "type": "Feature",
  "properties": {
    "iso:country":"GB",
    "wof:name":"HP4 3QN",
    "wof:placetype":"postalcode"
},
  "geometry": {"coordinates":[-0.58978472444504,51.76987068892914],"type":"Point"}
}