{
  "type": "Feature",
  "properties": {
    "date:inception_lower": "1980-01-01",
    "date:inception_upper": "1980-01-01",
    "iso:country": "GB",
    "wof:name": "DY8 5YG",
    "wof:placetype": "postalcode"
  },
  "geometry": {"coordinates":[-2.14922,52.472964],"type":"Point"}
}
