{
  "type": "Feature",
  "properties": {
    "iso:country":"GB",
    "wof:name":"SR7 9EZ",
    "wof:placetype":"postalcode"
},
  "geometry": {"coordinates":[-1.39791722911741,54.81945136449819],"type":"Point"}
}