{
  "type": "Feature",
  "properties": {
    "iso:country": "GB",
    "wof:name": "GL54 2LH",
    "wof:placetype": "postalcode"
  },
  "geometry": {"coordinates":[-1.71203,51.856473],"type":"Point"}
}
