{
  "type": "Feature",
  "properties": {
    "date:inception_lower":"1980-01-01",
    "date:inception_upper":"1980-01-31",
    "iso:country":"GB",
    "wof:name":"GL54 2LH",
    "wof:placetype":"postalcode"
},
  "geometry": {"coordinates":[-1.71203,51.856473],"type":"Point"}
}