{
  "type": "Feature",
  "properties": {
    "iso:country":"GB",
    "wof:name":"HD2 1ZG",
    "wof:placetype":"postalcode"
},
  "geometry": {"coordinates":[-1.76912245711949,53.67362966134177],"type":"Point"}
}