{
  "type": "Feature",
  "properties": {
    "iso:country": "GB",
    "wof:name": "SN8 3DX",
    "wof:placetype": "postalcode"
  },
  "geometry": {"coordinates":[-1.67001,51.350194],"type":"Point"}
}
