{
  "type": "Feature",
  "properties": {
    "date:inception_lower": "1995-12-01",
    "date:inception_upper": "1995-12-01",
    "iso:country": "GB",
    "wof:name": "SN8 3DX",
    "wof:placetype": "postalcode"
  },
  "geometry": {"coordinates":[-1.670253,51.350348],"type":"Point"}
}
