{
  "type": "Feature",
  "properties": {
    "iso:country":"GB",
    "wof:name":"WF17 7LH",
    "wof:placetype":"postalcode"
},
  "geometry": {"coordinates":[-1.63717683942052,53.7030807393031],"type":"Point"}
}