{
  "type": "Feature",
  "properties": {
    "iso:country": "GB",
    "wof:name": "WF17 7LH",
    "wof:placetype": "postalcode"
  },
  "geometry": {"coordinates":[-1.637177,53.703081],"type":"Point"}
}
