{
  "type": "Feature",
  "properties": {
    "iso:country":"GB",
    "wof:name":"SL9 8RP",
    "wof:placetype":"postalcode"
},
  "geometry": {"coordinates":[-0.56748062069211,51.59658925723458],"type":"Point"}
}