{
  "type": "Feature",
  "properties": {
    "iso:country":"GB",
    "wof:name":"PO16 0UH",
    "wof:placetype":"postalcode"
},
  "geometry": {"coordinates":[-1.18547685867448,50.84388572542221],"type":"Point"}
}