{
  "type": "Feature",
  "properties": {
    "iso:country":"GB",
    "wof:name":"PL14 5BH",
    "wof:placetype":"postalcode"
},
  "geometry": {"coordinates":[-4.44951190010082,50.52908401141558],"type":"Point"}
}