{
  "type": "Feature",
  "properties": {
    "date:inception_lower": "1980-01-01",
    "date:inception_upper": "1980-01-01",
    "iso:country": "GB",
    "wof:name": "PL14 5BH",
    "wof:placetype": "postalcode"
  },
  "geometry": {"coordinates":[-4.449512,50.529084],"type":"Point"}
}
