{
  "type": "Feature",
  "properties": {
    "date:inception_lower": "1980-01-01",
    "date:inception_upper": "1980-01-01",
    "iso:country": "GB",
    "wof:name": "SY4 1DJ",
    "wof:placetype": "postalcode"
  },
  "geometry": {"coordinates":[-2.911112,52.778877],"type":"Point"}
}
