{
  "type": "Feature",
  "properties": {
    "iso:country": "GB",
    "wof:name": "SY4 1DJ",
    "wof:placetype": "postalcode"
  },
  "geometry": {"coordinates":[-2.911112,52.778877],"type":"Point"}
}
