{
  "type": "Feature",
  "properties": {
    "iso:country": "GB",
    "wof:name": "OX28 3AE",
    "wof:placetype": "postalcode"
  },
  "geometry": {"coordinates":[-1.47175,51.787291],"type":"Point"}
}
