{
  "type": "Feature",
  "properties": {
    "iso:country":"GB",
    "wof:name":"G69 0JR",
    "wof:placetype":"postalcode"
},
  "geometry": {"coordinates":[-4.08289544643201,55.91839531796904],"type":"Point"}
}