{
  "type": "Feature",
  "properties": {
    "date:inception_lower": "1988-11-01",
    "date:inception_upper": "1988-11-01",
    "iso:country": "GB",
    "wof:name": "G69 0JR",
    "wof:placetype": "postalcode"
  },
  "geometry": {"coordinates":[-4.082895,55.918395],"type":"Point"}
}
