{
  "type": "Feature",
  "properties": {
    "iso:country":"GB",
    "wof:name":"SY23 2JN",
    "wof:placetype":"postalcode"
},
  "geometry": {"coordinates":[-4.08138023965945,52.41563484873381],"type":"Point"}
}