{
  "type": "Feature",
  "properties": {
    "iso:country":"GB",
    "wof:name":"M26 4EQ",
    "wof:placetype":"postalcode"
},
  "geometry": {"coordinates":[-2.32827454676908,53.56713279708825],"type":"Point"}
}