{
  "type": "Feature",
  "properties": {
    "iso:country": "GB",
    "wof:name": "EX6 6YB",
    "wof:placetype": "postalcode"
  },
  "geometry": {"coordinates":[-3.68219,50.736299],"type":"Point"}
}
