{
  "type": "Feature",
  "properties": {
    "date:inception_lower":"1984-10-01",
    "date:inception_upper":"1984-10-31",
    "iso:country":"GB",
    "wof:name":"GU14 8UQ",
    "wof:placetype":"postalcode"
},
  "geometry": {"coordinates":[-0.765794,51.306269],"type":"Point"}
}