{
  "type": "Feature",
  "properties": {
    "date:inception_lower": "1980-01-01",
    "date:inception_upper": "1980-01-01",
    "iso:country": "GB",
    "wof:name": "ST10 2HY",
    "wof:placetype": "postalcode"
  },
  "geometry": {"coordinates":[-1.927785,53.024788],"type":"Point"}
}
