{
  "type": "Feature",
  "properties": {
    "iso:country": "GB",
    "wof:name": "NE1 7RN",
    "wof:placetype": "postalcode"
  },
  "geometry": {"coordinates":[-1.616412,54.97582],"type":"Point"}
}
