{
  "type": "Feature",
  "properties": {
    "iso:country":"GB",
    "wof:name":"NE1 7RN",
    "wof:placetype":"postalcode"
},
  "geometry": {"coordinates":[-1.61641255035314,54.97582017124748],"type":"Point"}
}