{
  "type": "Feature",
  "properties": {
    "iso:country":"GB",
    "wof:name":"PL10 1NE",
    "wof:placetype":"postalcode"
},
  "geometry": {"coordinates":[-4.20117988198203,50.33394877868945],"type":"Point"}
}