{
  "type": "Feature",
  "properties": {
    "date:inception_lower":"1981-06-01",
    "date:inception_upper":"1981-06-30",
    "iso:country":"GB",
    "wof:name":"IP24 1UL",
    "wof:placetype":"postalcode"
},
  "geometry": {"coordinates":[0.761784,52.424813],"type":"Point"}
}