{
  "type": "Feature",
  "properties": {
    "iso:country":"GB",
    "wof:name":"IP24 1UL",
    "wof:placetype":"postalcode"
},
  "geometry": {"coordinates":[0.76178417782888,52.42481336637898],"type":"Point"}
}