{
  "type": "Feature",
  "properties": {
    "iso:country": "GB",
    "wof:name": "IP24 1UL",
    "wof:placetype": "postalcode"
  },
  "geometry": {"coordinates":[0.761784,52.424813],"type":"Point"}
}
