{
  "type": "Feature",
  "properties": {
    "iso:country":"GB",
    "wof:name":"WR11 8SU",
    "wof:placetype":"postalcode"
},
  "geometry": {"coordinates":[-1.92296408364859,52.1152392992535],"type":"Point"}
}