{
  "type": "Feature",
  "properties": {
    "date:inception_lower": "1980-01-01",
    "date:inception_upper": "1980-01-01",
    "iso:country": "GB",
    "wof:name": "CA11 0QW",
    "wof:placetype": "postalcode"
  },
  "geometry": {"coordinates":[-2.961866,54.545955],"type":"Point"}
}
