{
  "type": "Feature",
  "properties": {
    "iso:country":"GB",
    "wof:name":"SW17 0JU",
    "wof:placetype":"postalcode"
},
  "geometry": {"coordinates":[-0.18363138625054,51.43536578456954],"type":"Point"}
}