{
  "type": "Feature",
  "properties": {
    "iso:country":"GB",
    "wof:name":"BN23 5AR",
    "wof:placetype":"postalcode"
},
  "geometry": {"coordinates":[0.32915853755047,50.79710204020662],"type":"Point"}
}