{
  "type": "Feature",
  "properties": {
    "date:inception_lower":"2003-08-01",
    "date:inception_upper":"2003-08-31",
    "iso:country":"GB",
    "wof:name":"BN23 5AR",
    "wof:placetype":"postalcode"
},
  "geometry": {"coordinates":[0.329159,50.797102],"type":"Point"}
}