{
  "type": "Feature",
  "properties": {
    "iso:country":"GB",
    "wof:name":"SK6 6JY",
    "wof:placetype":"postalcode"
},
  "geometry": {"coordinates":[-2.08610466225206,53.39803986536563],"type":"Point"}
}