{
  "type": "Feature",
  "properties": {
    "date:inception_lower": "2022-04-01",
    "date:inception_upper": "2022-04-01",
    "iso:country": "GB",
    "wof:name": "EH32 9GS",
    "wof:placetype": "postalcode"
  },
  "geometry": {"coordinates":[-2.948988,55.955729],"type":"Point"}
}
