{
  "type": "Feature",
  "properties": {
    "iso:country":"GB",
    "wof:name":"IP24 1BE",
    "wof:placetype":"postalcode"
},
  "geometry": {"coordinates":[0.74524949862461,52.41652068450864],"type":"Point"}
}