{
  "type": "Feature",
  "properties": {
    "date:inception_lower":"1980-01-01",
    "date:inception_upper":"1980-01-31",
    "iso:country":"GB",
    "wof:name":"E6 1LF",
    "wof:placetype":"postalcode"
},
  "geometry": {"coordinates":[0.044409,51.532545],"type":"Point"}
}