{
  "type": "Feature",
  "properties": {
    "iso:country":"GB",
    "wof:name":"E6 1LF",
    "wof:placetype":"postalcode"
},
  "geometry": {"coordinates":[0.04440943837259,51.53254487868308],"type":"Point"}
}