{
  "type": "Feature",
  "properties": {
    "iso:country":"GB",
    "wof:name":"LN6 0NA",
    "wof:placetype":"postalcode"
},
  "geometry": {"coordinates":[-0.60014068747114,53.21968822731723],"type":"Point"}
}