{
  "type": "Feature",
  "properties": {
    "date:inception_lower":"1980-01-01",
    "date:inception_upper":"1980-01-31",
    "iso:country":"GB",
    "wof:name":"BD4 0PB",
    "wof:placetype":"postalcode"
},
  "geometry": {"coordinates":[-1.703023,53.774268],"type":"Point"}
}