{
  "type": "Feature",
  "properties": {
    "iso:country":"GB",
    "wof:name":"BD4 0PB",
    "wof:placetype":"postalcode"
},
  "geometry": {"coordinates":[-1.70302267911857,53.77426774359049],"type":"Point"}
}