{
  "type": "Feature",
  "properties": {
    "iso:country": "GB",
    "wof:name": "S10 4NL",
    "wof:placetype": "postalcode"
  },
  "geometry": {"coordinates":[-1.56976,53.370384],"type":"Point"}
}
