{
  "type": "Feature",
  "properties": {
    "iso:country": "GB",
    "wof:name": "AL5 1AU",
    "wof:placetype": "postalcode"
  },
  "geometry": {"coordinates":[-0.33571,51.812299],"type":"Point"}
}
