{
  "type": "Feature",
  "properties": {
    "date:inception_lower": "1980-01-01",
    "date:inception_upper": "1980-01-01",
    "iso:country": "GB",
    "wof:name": "MK18 4NA",
    "wof:placetype": "postalcode"
  },
  "geometry": {"coordinates":[-1.039565,51.964182],"type":"Point"}
}
