{
  "type": "Feature",
  "properties": {
    "iso:country":"GB",
    "wof:name":"M12 6FT",
    "wof:placetype":"postalcode"
},
  "geometry": {"coordinates":[-2.22184108456447,53.47189402428604],"type":"Point"}
}