{
  "type": "Feature",
  "properties": {
    "date:inception_lower": "1981-09-01",
    "date:inception_upper": "1981-09-01",
    "iso:country": "GB",
    "wof:name": "GU14 0LQ",
    "wof:placetype": "postalcode"
  },
  "geometry": {"coordinates":[-0.779805,51.292918],"type":"Point"}
}
