{
  "type": "Feature",
  "properties": {
    "iso:country":"GB",
    "wof:name":"SS4 1RW",
    "wof:placetype":"postalcode"
},
  "geometry": {"coordinates":[0.69811628972976,51.58999855046989],"type":"Point"}
}