{
  "type": "Feature",
  "properties": {
    "date:inception_lower": "1994-05-01",
    "date:inception_upper": "1994-05-01",
    "iso:country": "GB",
    "wof:name": "M40 7PG",
    "wof:placetype": "postalcode"
  },
  "geometry": {"coordinates":[-2.220597,53.491076],"type":"Point"}
}
