{
  "type": "Feature",
  "properties": {
    "iso:country":"GB",
    "wof:name":"SG13 8AY",
    "wof:placetype":"postalcode"
},
  "geometry": {"coordinates":[-0.07648360473661,51.79452315383308],"type":"Point"}
}