{
  "type": "Feature",
  "properties": {
    "iso:country":"GB",
    "wof:name":"DD11 3LH",
    "wof:placetype":"postalcode"
},
  "geometry": {"coordinates":[-2.61222011014936,56.5610050341753],"type":"Point"}
}