{
  "type": "Feature",
  "properties": {
    "iso:country":"GB",
    "wof:name":"B20 1LX",
    "wof:placetype":"postalcode"
},
  "geometry": {"coordinates":[-1.93930406336448,52.52558866296092],"type":"Point"}
}