{
  "type": "Feature",
  "properties": {
    "iso:country":"GB",
    "wof:name":"DY8 3DY",
    "wof:placetype":"postalcode"
},
  "geometry": {"coordinates":[-2.16933238149065,52.44294575423119],"type":"Point"}
}