{
  "type": "Feature",
  "properties": {
    "iso:country":"GB",
    "wof:name":"M9 6DH",
    "wof:placetype":"postalcode"
},
  "geometry": {"coordinates":[-2.20562593116638,53.52686929159523],"type":"Point"}
}