{
  "type": "Feature",
  "properties": {
    "iso:country": "GB",
    "wof:name": "DD3 8QP",
    "wof:placetype": "postalcode"
  },
  "geometry": {"coordinates":[-2.995807,56.486397],"type":"Point"}
}
