{
  "type": "Feature",
  "properties": {
    "iso:country":"GB",
    "wof:name":"WF7 7NT",
    "wof:placetype":"postalcode"
},
  "geometry": {"coordinates":[-1.32250385492568,53.65261197856402],"type":"Point"}
}