{
  "type": "Feature",
  "properties": {
    "iso:country": "GB",
    "wof:name": "WF7 7NT",
    "wof:placetype": "postalcode"
  },
  "geometry": {"coordinates":[-1.322504,53.652612],"type":"Point"}
}
