{
  "type": "Feature",
  "properties": {
    "iso:country":"GB",
    "wof:name":"M50 1AU",
    "wof:placetype":"postalcode"
},
  "geometry": {"coordinates":[-2.3274713017863,53.48271584724819],"type":"Point"}
}