{
  "type": "Feature",
  "properties": {
    "date:inception_lower":"2009-02-01",
    "date:inception_upper":"2009-02-28",
    "iso:country":"GB",
    "wof:name":"M50 1AU",
    "wof:placetype":"postalcode"
},
  "geometry": {"coordinates":[-2.327471,53.482716],"type":"Point"}
}