{
  "type": "Feature",
  "properties": {
    "iso:country":"GB",
    "wof:name":"GU6 8QT",
    "wof:placetype":"postalcode"
},
  "geometry": {"coordinates":[-0.48695624926949,51.16047555303571],"type":"Point"}
}