{
  "type": "Feature",
  "properties": {
    "iso:country": "GB",
    "wof:name": "TS24 0GE",
    "wof:placetype": "postalcode"
  },
  "geometry": {"coordinates":[-1.214185,54.708549],"type":"Point"}
}
