{
  "type": "Feature",
  "properties": {
    "date:inception_lower": "2017-04-01",
    "date:inception_upper": "2017-04-01",
    "iso:country": "GB",
    "wof:name": "TS24 0GE",
    "wof:placetype": "postalcode"
  },
  "geometry": {"coordinates":[-1.214185,54.708549],"type":"Point"}
}
