{
  "type": "Feature",
  "properties": {
    "iso:country": "GB",
    "wof:name": "PL12 5DY",
    "wof:placetype": "postalcode"
  },
  "geometry": {"coordinates":[-4.290084,50.422581],"type":"Point"}
}
