{
  "type": "Feature",
  "properties": {
    "iso:country":"GB",
    "wof:name":"PL12 5DY",
    "wof:placetype":"postalcode"
},
  "geometry": {"coordinates":[-4.29008443286781,50.4225810123909],"type":"Point"}
}