{
  "type": "Feature",
  "properties": {
    "iso:country":"GB",
    "wof:name":"TW20 9SJ",
    "wof:placetype":"postalcode"
},
  "geometry": {"coordinates":[-0.57016921890983,51.42201387918468],"type":"Point"}
}