{
  "type": "Feature",
  "properties": {
    "iso:country":"GB",
    "wof:name":"SA8 4NU",
    "wof:placetype":"postalcode"
},
  "geometry": {"coordinates":[-3.85719465279064,51.72854463691271],"type":"Point"}
}