{
  "type": "Feature",
  "properties": {
    "date:inception_lower": "1980-01-01",
    "date:inception_upper": "1980-01-01",
    "iso:country": "GB",
    "wof:name": "SA8 4NU",
    "wof:placetype": "postalcode"
  },
  "geometry": {"coordinates":[-3.857195,51.728545],"type":"Point"}
}
