{
  "type": "Feature",
  "properties": {
    "iso:country": "GB",
    "wof:name": "SA8 4NU",
    "wof:placetype": "postalcode"
  },
  "geometry": {"coordinates":[-3.857195,51.728545],"type":"Point"}
}
