{
  "type": "Feature",
  "properties": {
    "iso:country":"GB",
    "wof:name":"E16 4DF",
    "wof:placetype":"postalcode"
},
  "geometry": {"coordinates":[0.01633150027564,51.51774334271425],"type":"Point"}
}