{
  "type": "Feature",
  "properties": {
    "iso:country": "GB",
    "wof:name": "E16 4DF",
    "wof:placetype": "postalcode"
  },
  "geometry": {"coordinates":[0.016332,51.517743],"type":"Point"}
}
