{
  "type": "Feature",
  "properties": {
    "iso:country":"GB",
    "wof:name":"SR2 9LF",
    "wof:placetype":"postalcode"
},
  "geometry": {"coordinates":[-1.38070054349531,54.88280086235152],"type":"Point"}
}