{
  "type": "Feature",
  "properties": {
    "iso:country":"GB",
    "wof:name":"CW10 0PJ",
    "wof:placetype":"postalcode"
},
  "geometry": {"coordinates":[-2.45285448118545,53.18451835301705],"type":"Point"}
}