{
  "type": "Feature",
  "properties": {
    "date:inception_lower": "1985-10-01",
    "date:inception_upper": "1985-10-01",
    "iso:country": "GB",
    "wof:name": "SA7 9PH",
    "wof:placetype": "postalcode"
  },
  "geometry": {"coordinates":[-3.874963,51.664876],"type":"Point"}
}
