{
  "type": "Feature",
  "properties": {
    "iso:country": "GB",
    "wof:name": "HP5 1SA",
    "wof:placetype": "postalcode"
  },
  "geometry": {"coordinates":[-0.605544,51.69674],"type":"Point"}
}
