{
  "type": "Feature",
  "properties": {
    "iso:country":"GB",
    "wof:name":"EH28 8JU",
    "wof:placetype":"postalcode"
},
  "geometry": {"coordinates":[-3.37378225236931,55.92486166592302],"type":"Point"}
}