{
  "type": "Feature",
  "properties": {
    "iso:country": "GB",
    "wof:name": "EH28 8JU",
    "wof:placetype": "postalcode"
  },
  "geometry": {"coordinates":[-3.373782,55.924862],"type":"Point"}
}
