{
  "type": "Feature",
  "properties": {
    "iso:country":"GB",
    "wof:name":"SO41 3QE",
    "wof:placetype":"postalcode"
},
  "geometry": {"coordinates":[-1.52978070449132,50.7532821681196],"type":"Point"}
}