{
  "type": "Feature",
  "properties": {
    "date:inception_lower": "1994-12-01",
    "date:inception_upper": "1994-12-01",
    "iso:country": "GB",
    "wof:name": "SO41 3QE",
    "wof:placetype": "postalcode"
  },
  "geometry": {"coordinates":[-1.529781,50.753282],"type":"Point"}
}
