{
  "type": "Feature",
  "properties": {
    "iso:country":"GB",
    "wof:name":"YO21 2RG",
    "wof:placetype":"postalcode"
},
  "geometry": {"coordinates":[-1.06475973547988,54.47589649295806],"type":"Point"}
}