{
  "type": "Feature",
  "properties": {
    "iso:country": "GB",
    "wof:name": "YO21 2RG",
    "wof:placetype": "postalcode"
  },
  "geometry": {"coordinates":[-1.06476,54.475896],"type":"Point"}
}
