{
  "type": "Feature",
  "properties": {
    "date:inception_lower": "1980-01-01",
    "date:inception_upper": "1980-01-01",
    "iso:country": "GB",
    "wof:name": "YO21 2RG",
    "wof:placetype": "postalcode"
  },
  "geometry": {"coordinates":[-1.06476,54.475896],"type":"Point"}
}
