{
  "type": "Feature",
  "properties": {
    "date:inception_lower": "1994-05-01",
    "date:inception_upper": "1994-05-01",
    "iso:country": "GB",
    "wof:name": "M23 1PQ",
    "wof:placetype": "postalcode"
  },
  "geometry": {"coordinates":[-2.273745,53.39293],"type":"Point"}
}
