{
  "type": "Feature",
  "properties": {
    "iso:country":"GB",
    "wof:name":"M23 1PQ",
    "wof:placetype":"postalcode"
},
  "geometry": {"coordinates":[-2.27374456317578,53.39292984909865],"type":"Point"}
}