{
  "type": "Feature",
  "properties": {
    "date:inception_lower": "1980-01-01",
    "date:inception_upper": "1980-01-01",
    "iso:country": "GB",
    "wof:name": "SO24 9RE",
    "wof:placetype": "postalcode"
  },
  "geometry": {"coordinates":[-1.123145,51.106033],"type":"Point"}
}
