{
  "type": "Feature",
  "properties": {
    "iso:country":"GB",
    "wof:name":"SO24 9RE",
    "wof:placetype":"postalcode"
},
  "geometry": {"coordinates":[-1.12314476251976,51.10603292915476],"type":"Point"}
}