{
  "type": "Feature",
  "properties": {
    "iso:country":"GB",
    "wof:name":"ML11 9LS",
    "wof:placetype":"postalcode"
},
  "geometry": {"coordinates":[-3.78736611835851,55.60877768043593],"type":"Point"}
}