{
  "type": "Feature",
  "properties": {
    "iso:country": "GB",
    "wof:name": "ML11 9LS",
    "wof:placetype": "postalcode"
  },
  "geometry": {"coordinates":[-3.787366,55.608778],"type":"Point"}
}
