{
  "type": "Feature",
  "properties": {
    "iso:country":"GB",
    "wof:name":"AL5 4JY",
    "wof:placetype":"postalcode"
},
  "geometry": {"coordinates":[-0.3508642039446,51.82874277198254],"type":"Point"}
}