{
  "type": "Feature",
  "properties": {
    "iso:country":"GB",
    "wof:name":"CB2 8AP",
    "wof:placetype":"postalcode"
},
  "geometry": {"coordinates":[0.12273422379599,52.18479999491642],"type":"Point"}
}