{
  "type": "Feature",
  "properties": {
    "iso:country":"GB",
    "wof:name":"CF63 4AB",
    "wof:placetype":"postalcode"
},
  "geometry": {"coordinates":[-3.25596793404594,51.40276057966692],"type":"Point"}
}