{
  "type": "Feature",
  "properties": {
    "iso:country": "GB",
    "wof:name": "DH4 6RZ",
    "wof:placetype": "postalcode"
  },
  "geometry": {"coordinates":[-1.506828,54.812825],"type":"Point"}
}
