{
  "type": "Feature",
  "properties": {
    "iso:country":"GB",
    "wof:name":"NG16 3GD",
    "wof:placetype":"postalcode"
},
  "geometry": {"coordinates":[-1.30223597356201,53.01711003056219],"type":"Point"}
}