{
  "type": "Feature",
  "properties": {
    "date:inception_lower": "1980-01-01",
    "date:inception_upper": "1980-01-01",
    "iso:country": "GB",
    "wof:name": "NG16 3GD",
    "wof:placetype": "postalcode"
  },
  "geometry": {"coordinates":[-1.302236,53.01711],"type":"Point"}
}
