{
  "type": "Feature",
  "properties": {
    "date:inception_lower": "1997-06-01",
    "date:inception_upper": "1997-06-01",
    "iso:country": "GB",
    "wof:name": "DE12 7AU",
    "wof:placetype": "postalcode"
  },
  "geometry": {"coordinates":[-1.532882,52.683741],"type":"Point"}
}
