{
  "type": "Feature",
  "properties": {
    "iso:country":"GB",
    "wof:name":"DE12 7AU",
    "wof:placetype":"postalcode"
},
  "geometry": {"coordinates":[-1.53288193716065,52.68374075997126],"type":"Point"}
}