{
  "type": "Feature",
  "properties": {
    "date:inception_lower":"2010-02-01",
    "date:inception_upper":"2010-02-28",
    "iso:country":"GB",
    "wof:name":"ME3 8FH",
    "wof:placetype":"postalcode"
},
  "geometry": {"coordinates":[0.514112,51.414515],"type":"Point"}
}