{
  "type": "Feature",
  "properties": {
    "iso:country":"GB",
    "wof:name":"ME3 8FH",
    "wof:placetype":"postalcode"
},
  "geometry": {"coordinates":[0.51411198475538,51.41451474731418],"type":"Point"}
}