{
  "type": "Feature",
  "properties": {
    "iso:country": "GB",
    "wof:name": "ME3 8FH",
    "wof:placetype": "postalcode"
  },
  "geometry": {"coordinates":[0.514112,51.414515],"type":"Point"}
}
