{
  "type": "Feature",
  "properties": {
    "iso:country":"GB",
    "wof:name":"DN14 6JA",
    "wof:placetype":"postalcode"
},
  "geometry": {"coordinates":[-0.87246123223574,53.70755689915958],"type":"Point"}
}