{
  "type": "Feature",
  "properties": {
    "iso:country": "GB",
    "wof:name": "OX13 5GJ",
    "wof:placetype": "postalcode"
  },
  "geometry": {"coordinates":[-1.41017,51.680915],"type":"Point"}
}
