{
  "type": "Feature",
  "properties": {
    "iso:country": "GB",
    "wof:name": "PA4 0XQ",
    "wof:placetype": "postalcode"
  },
  "geometry": {"coordinates":[-4.375419,55.868915],"type":"Point"}
}
