{
  "type": "Feature",
  "properties": {
    "iso:country":"GB",
    "wof:name":"RM12 4LY",
    "wof:placetype":"postalcode"
},
  "geometry": {"coordinates":[0.20933158171399,51.55549882664715],"type":"Point"}
}