{
  "type": "Feature",
  "properties": {
    "date:inception_lower": "2015-07-01",
    "date:inception_upper": "2015-07-01",
    "iso:country": "GB",
    "wof:name": "L3 4GG",
    "wof:placetype": "postalcode"
  },
  "geometry": {"coordinates":[-2.989051,53.39293],"type":"Point"}
}
