{
  "type": "Feature",
  "properties": {
    "iso:country":"GB",
    "wof:name":"MK12 5AU",
    "wof:placetype":"postalcode"
},
  "geometry": {"coordinates":[-0.81432937766673,52.06105062395874],"type":"Point"}
}