{
  "type": "Feature",
  "properties": {
    "date:inception_lower": "1998-06-01",
    "date:inception_upper": "1998-06-01",
    "iso:country": "GB",
    "wof:name": "EX16 7LL",
    "wof:placetype": "postalcode"
  },
  "geometry": {"coordinates":[-3.304219,50.940066],"type":"Point"}
}
