{
  "type": "Feature",
  "properties": {
    "iso:country":"GB",
    "wof:name":"LL54 7LP",
    "wof:placetype":"postalcode"
},
  "geometry": {"coordinates":[-4.2457672725667,53.09692326764171],"type":"Point"}
}