{
  "type": "Feature",
  "properties": {
    "date:inception_lower": "2015-09-01",
    "date:inception_upper": "2015-09-01",
    "iso:country": "GB",
    "wof:name": "EH7 4QU",
    "wof:placetype": "postalcode"
  },
  "geometry": {"coordinates":[-3.186254,55.964248],"type":"Point"}
}
