{
  "type": "Feature",
  "properties": {
    "date:inception_lower": "1980-01-01",
    "date:inception_upper": "1980-01-01",
    "iso:country": "GB",
    "wof:name": "HU17 8TJ",
    "wof:placetype": "postalcode"
  },
  "geometry": {"coordinates":[-0.494597,53.822023],"type":"Point"}
}
