{
  "type": "Feature",
  "properties": {
    "date:inception_lower": "1992-08-01",
    "date:inception_upper": "1992-08-01",
    "iso:country": "GB",
    "wof:name": "HP27 9DB",
    "wof:placetype": "postalcode"
  },
  "geometry": {"coordinates":[-0.838744,51.718019],"type":"Point"}
}
