{
  "type": "Feature",
  "properties": {
    "iso:country": "GB",
    "wof:name": "DE56 1SJ",
    "wof:placetype": "postalcode"
  },
  "geometry": {"coordinates":[-1.470025,53.016835],"type":"Point"}
}
