{
  "type": "Feature",
  "properties": {
    "iso:country":"GB",
    "wof:name":"RG40 4QP",
    "wof:placetype":"postalcode"
},
  "geometry": {"coordinates":[-0.88702641647235,51.36224545957018],"type":"Point"}
}