{
  "type": "Feature",
  "properties": {
    "date:inception_lower":"1994-05-01",
    "date:inception_upper":"1994-05-31",
    "iso:country":"GB",
    "wof:name":"M12 5NE",
    "wof:placetype":"postalcode"
},
  "geometry": {"coordinates":[-2.205829,53.469199],"type":"Point"}
}