{
  "type": "Feature",
  "properties": {
    "iso:country":"GB",
    "wof:name":"M12 5NE",
    "wof:placetype":"postalcode"
},
  "geometry": {"coordinates":[-2.20582880154421,53.46919920518096],"type":"Point"}
}