{
  "type": "Feature",
  "properties": {
    "iso:country":"GB",
    "wof:name":"TF6 5EF",
    "wof:placetype":"postalcode"
},
  "geometry": {"coordinates":[-2.57069953893518,52.71888440062412],"type":"Point"}
}