{
  "type": "Feature",
  "properties": {
    "date:inception_lower": "1980-01-01",
    "date:inception_upper": "1980-01-01",
    "iso:country": "GB",
    "wof:name": "TF6 5EF",
    "wof:placetype": "postalcode"
  },
  "geometry": {"coordinates":[-2.570727,52.718846],"type":"Point"}
}
