{
  "type": "Feature",
  "properties": {
    "iso:country":"GB",
    "wof:name":"ME8 0HU",
    "wof:placetype":"postalcode"
},
  "geometry": {"coordinates":[0.59175196675757,51.35379738687817],"type":"Point"}
}