{
  "type": "Feature",
  "properties": {
    "date:inception_lower": "1980-01-01",
    "date:inception_upper": "1980-01-01",
    "iso:country": "GB",
    "wof:name": "BD20 8BY",
    "wof:placetype": "postalcode"
  },
  "geometry": {"coordinates":[-1.994226,53.897194],"type":"Point"}
}
