{
  "type": "Feature",
  "properties": {
    "iso:country": "GB",
    "wof:name": "BD20 8BY",
    "wof:placetype": "postalcode"
  },
  "geometry": {"coordinates":[-1.994226,53.897194],"type":"Point"}
}
