{
  "type": "Feature",
  "properties": {
    "date:inception_lower":"2015-06-01",
    "date:inception_upper":"2015-06-30",
    "iso:country":"GB",
    "wof:name":"MK43 0FB",
    "wof:placetype":"postalcode"
},
  "geometry": {"coordinates":[-0.542227,52.062587],"type":"Point"}
}