{
  "type": "Feature",
  "properties": {
    "iso:country": "GB",
    "wof:name": "MK43 0FB",
    "wof:placetype": "postalcode"
  },
  "geometry": {"coordinates":[-0.542227,52.062587],"type":"Point"}
}
