{
  "type": "Feature",
  "properties": {
    "iso:country":"GB",
    "wof:name":"MK43 0FB",
    "wof:placetype":"postalcode"
},
  "geometry": {"coordinates":[-0.54243242922081,52.06275822252815],"type":"Point"}
}