{
  "type": "Feature",
  "properties": {
    "iso:country": "GB",
    "wof:name": "NE64 6DS",
    "wof:placetype": "postalcode"
  },
  "geometry": {"coordinates":[-1.505662,55.186573],"type":"Point"}
}
