{
  "type": "Feature",
  "properties": {
    "iso:country":"GB",
    "wof:name":"NE64 6DS",
    "wof:placetype":"postalcode"
},
  "geometry": {"coordinates":[-1.5056640783467,55.18655030401806],"type":"Point"}
}