{
  "type": "Feature",
  "properties": {
    "iso:country":"GB",
    "wof:name":"BB12 9PQ",
    "wof:placetype":"postalcode"
},
  "geometry": {"coordinates":[-2.26282123049474,53.8344668086859],"type":"Point"}
}