{
  "type": "Feature",
  "properties": {
    "iso:country":"GB",
    "wof:name":"LL12 8PT",
    "wof:placetype":"postalcode"
},
  "geometry": {"coordinates":[-2.97414452585447,53.08666572497702],"type":"Point"}
}