{
  "type": "Feature",
  "properties": {
    "date:inception_lower": "1998-12-01",
    "date:inception_upper": "1998-12-01",
    "iso:country": "GB",
    "wof:name": "CV21 1HE",
    "wof:placetype": "postalcode"
  },
  "geometry": {"coordinates":[-1.273478,52.379127],"type":"Point"}
}
