{
  "type": "Feature",
  "properties": {
    "iso:country": "GB",
    "wof:name": "CV21 1HE",
    "wof:placetype": "postalcode"
  },
  "geometry": {"coordinates":[-1.273449,52.37893],"type":"Point"}
}
