{
  "type": "Feature",
  "properties": {
    "iso:country": "GB",
    "wof:name": "W9 1EA",
    "wof:placetype": "postalcode"
  },
  "geometry": {"coordinates":[-0.187474,51.53207],"type":"Point"}
}
