{
  "type": "Feature",
  "properties": {
    "date:inception_lower": "2020-04-01",
    "date:inception_upper": "2020-04-01",
    "iso:country": "GB",
    "wof:name": "W9 1EA",
    "wof:placetype": "postalcode"
  },
  "geometry": {"coordinates":[-0.187474,51.53207],"type":"Point"}
}
