{
  "type": "Feature",
  "properties": {
    "date:inception_lower": "2000-12-01",
    "date:inception_upper": "2000-12-01",
    "iso:country": "GB",
    "wof:name": "SE18 4ND",
    "wof:placetype": "postalcode"
  },
  "geometry": {"coordinates":[0.047974,51.470909],"type":"Point"}
}
