{
  "type": "Feature",
  "properties": {
    "iso:country":"GB",
    "wof:name":"SE18 4ND",
    "wof:placetype":"postalcode"
},
  "geometry": {"coordinates":[0.0479738649916,51.47090934613298],"type":"Point"}
}