{
  "type": "Feature",
  "properties": {
    "date:inception_lower": "1980-01-01",
    "date:inception_upper": "1980-01-01",
    "iso:country": "GB",
    "wof:name": "PR7 4DD",
    "wof:placetype": "postalcode"
  },
  "geometry": {"coordinates":[-2.614775,53.631428],"type":"Point"}
}
