{
  "type": "Feature",
  "properties": {
    "iso:country":"GB",
    "wof:name":"PH2 0JT",
    "wof:placetype":"postalcode"
},
  "geometry": {"coordinates":[-3.44594758214446,56.39114838031356],"type":"Point"}
}