{
  "type": "Feature",
  "properties": {
    "iso:country":"GB",
    "wof:name":"LL31 9YS",
    "wof:placetype":"postalcode"
},
  "geometry": {"coordinates":[-3.81753653311814,53.2967595417296],"type":"Point"}
}