{
  "type": "Feature",
  "properties": {
    "date:inception_lower": "1980-01-01",
    "date:inception_upper": "1980-01-01",
    "iso:country": "GB",
    "wof:name": "SP3 6DY",
    "wof:placetype": "postalcode"
  },
  "geometry": {"coordinates":[-2.127061,51.094001],"type":"Point"}
}
