{
  "type": "Feature",
  "properties": {
    "iso:country": "GB",
    "wof:name": "DE22 1JN",
    "wof:placetype": "postalcode"
  },
  "geometry": {"coordinates":[-1.483066,52.949723],"type":"Point"}
}
