{
  "type": "Feature",
  "properties": {
    "iso:country":"GB",
    "wof:name":"TR19 6BT",
    "wof:placetype":"postalcode"
},
  "geometry": {"coordinates":[-5.61897805031711,50.07557100683493],"type":"Point"}
}