{
  "type": "Feature",
  "properties": {
    "date:inception_lower":"1983-07-01",
    "date:inception_upper":"1983-07-31",
    "iso:country":"GB",
    "wof:name":"TR19 6BT",
    "wof:placetype":"postalcode"
},
  "geometry": {"coordinates":[-5.619024,50.075607],"type":"Point"}
}