{
  "type": "Feature",
  "properties": {
    "date:inception_lower": "1980-01-01",
    "date:inception_upper": "1980-01-01",
    "iso:country": "GB",
    "wof:name": "CV32 6BH",
    "wof:placetype": "postalcode"
  },
  "geometry": {"coordinates":[-1.557576,52.294358],"type":"Point"}
}
