{
  "type": "Feature",
  "properties": {
    "iso:country": "GB",
    "wof:name": "WV10 9NB",
    "wof:placetype": "postalcode"
  },
  "geometry": {"coordinates":[-2.117822,52.606031],"type":"Point"}
}
