{
  "type": "Feature",
  "properties": {
    "date:inception_lower":"1980-01-01",
    "date:inception_upper":"1980-01-31",
    "iso:country":"GB",
    "wof:name":"LA1 3DF",
    "wof:placetype":"postalcode"
},
  "geometry": {"coordinates":[-2.790712,54.046026],"type":"Point"}
}