{
  "type": "Feature",
  "properties": {
    "iso:country":"GB",
    "wof:name":"LA1 3DF",
    "wof:placetype":"postalcode"
},
  "geometry": {"coordinates":[-2.79071234394984,54.04602648924724],"type":"Point"}
}