{
  "type": "Feature",
  "properties": {
    "iso:country":"GB",
    "wof:name":"EX1 2EW",
    "wof:placetype":"postalcode"
},
  "geometry": {"coordinates":[-3.51698599591859,50.7257153306592],"type":"Point"}
}