{
  "type": "Feature",
  "properties": {
    "iso:country": "GB",
    "wof:name": "CO4 3HY",
    "wof:placetype": "postalcode"
  },
  "geometry": {"coordinates":[0.939846,51.902688],"type":"Point"}
}
