{
  "type": "Feature",
  "properties": {
    "iso:country":"GB",
    "wof:name":"NG31 9RU",
    "wof:placetype":"postalcode"
},
  "geometry": {"coordinates":[-0.58215431954161,52.9306149354086],"type":"Point"}
}