{
  "type": "Feature",
  "properties": {
    "iso:country":"GB",
    "wof:name":"S64 8AZ",
    "wof:placetype":"postalcode"
},
  "geometry": {"coordinates":[-1.30729029525662,53.48764905095847],"type":"Point"}
}