{
  "type": "Feature",
  "properties": {
    "iso:country": "GB",
    "wof:name": "S64 8AZ",
    "wof:placetype": "postalcode"
  },
  "geometry": {"coordinates":[-1.30729,53.487649],"type":"Point"}
}
