{
  "type": "Feature",
  "properties": {
    "date:inception_lower":"1980-01-01",
    "date:inception_upper":"1980-01-31",
    "iso:country":"GB",
    "wof:name":"S64 8AZ",
    "wof:placetype":"postalcode"
},
  "geometry": {"coordinates":[-1.30729,53.487649],"type":"Point"}
}