{
  "type": "Feature",
  "properties": {
    "iso:country":"GB",
    "wof:name":"RM8 2RJ",
    "wof:placetype":"postalcode"
},
  "geometry": {"coordinates":[0.12087878935612,51.5534892229599],"type":"Point"}
}