{
  "type": "Feature",
  "properties": {
    "iso:country":"GB",
    "wof:name":"BN21 4DG",
    "wof:placetype":"postalcode"
},
  "geometry": {"coordinates":[0.2863990650055,50.76276367648672],"type":"Point"}
}