{
  "type": "Feature",
  "properties": {
    "date:inception_lower":"2005-05-01",
    "date:inception_upper":"2005-05-31",
    "iso:country":"GB",
    "wof:name":"BN21 4DG",
    "wof:placetype":"postalcode"
},
  "geometry": {"coordinates":[0.286399,50.762764],"type":"Point"}
}