{
  "type": "Feature",
  "properties": {
    "iso:country": "GB",
    "wof:name": "BN21 4DG",
    "wof:placetype": "postalcode"
  },
  "geometry": {"coordinates":[0.286399,50.762764],"type":"Point"}
}
