{
  "type": "Feature",
  "properties": {
    "iso:country":"GB",
    "wof:name":"DE15 9FD",
    "wof:placetype":"postalcode"
},
  "geometry": {"coordinates":[-1.61536215973445,52.79189431868129],"type":"Point"}
}