{
  "type": "Feature",
  "properties": {
    "iso:country": "GB",
    "wof:name": "BR3 4XS",
    "wof:placetype": "postalcode"
  },
  "geometry": {"coordinates":[-0.049896,51.39962],"type":"Point"}
}
