{
  "type": "Feature",
  "properties": {
    "iso:country":"GB",
    "wof:name":"BR3 4XS",
    "wof:placetype":"postalcode"
},
  "geometry": {"coordinates":[-0.04989608528355,51.39962017017479],"type":"Point"}
}