{
  "type": "Feature",
  "properties": {
    "date:inception_lower": "1980-01-01",
    "date:inception_upper": "1980-01-01",
    "iso:country": "GB",
    "wof:name": "TW3 3UJ",
    "wof:placetype": "postalcode"
  },
  "geometry": {"coordinates":[-0.37074,51.456334],"type":"Point"}
}
