{
  "type": "Feature",
  "properties": {
    "iso:country": "GB",
    "wof:name": "PE22 8HD",
    "wof:placetype": "postalcode"
  },
  "geometry": {"coordinates":[0.035699,53.117641],"type":"Point"}
}
