{
  "type": "Feature",
  "properties": {
    "iso:country":"GB",
    "wof:name":"PE22 8HD",
    "wof:placetype":"postalcode"
},
  "geometry": {"coordinates":[0.03586774546927,53.11748578405543],"type":"Point"}
}