{
  "type": "Feature",
  "properties": {
    "iso:country":"GB",
    "wof:name":"WA3 5RT",
    "wof:placetype":"postalcode"
},
  "geometry": {"coordinates":[-2.5164205793886,53.44903337058796],"type":"Point"}
}