{
  "type": "Feature",
  "properties": {
    "iso:country":"GB",
    "wof:name":"BA5 2XD",
    "wof:placetype":"postalcode"
},
  "geometry": {"coordinates":[-2.63833289303936,51.21275558325799],"type":"Point"}
}