{
  "type": "Feature",
  "properties": {
    "iso:country": "GB",
    "wof:name": "BA5 2XD",
    "wof:placetype": "postalcode"
  },
  "geometry": {"coordinates":[-2.638333,51.212756],"type":"Point"}
}
