{
  "type": "Feature",
  "properties": {
    "iso:country":"GB",
    "wof:name":"ME14 5NT",
    "wof:placetype":"postalcode"
},
  "geometry": {"coordinates":[0.53853564568685,51.27582782798694],"type":"Point"}
}