{
  "type": "Feature",
  "properties": {
    "iso:country": "GB",
    "wof:name": "N9 0AJ",
    "wof:placetype": "postalcode"
  },
  "geometry": {"coordinates":[-0.042927,51.627521],"type":"Point"}
}
