{
  "type": "Feature",
  "properties": {
    "iso:country":"GB",
    "wof:name":"ME5 8YB",
    "wof:placetype":"postalcode"
},
  "geometry": {"coordinates":[0.55040157907462,51.33598952629977],"type":"Point"}
}