{
  "type": "Feature",
  "properties": {
    "iso:country":"GB",
    "wof:name":"FY8 1DL",
    "wof:placetype":"postalcode"
},
  "geometry": {"coordinates":[-3.01807846348224,53.7425808000111],"type":"Point"}
}