{
  "type": "Feature",
  "properties": {
    "iso:country": "GB",
    "wof:name": "BA21 3TH",
    "wof:placetype": "postalcode"
  },
  "geometry": {"coordinates":[-2.667403,50.948464],"type":"Point"}
}
