{
  "type": "Feature",
  "properties": {
    "date:inception_lower": "2022-05-01",
    "date:inception_upper": "2022-05-01",
    "iso:country": "GB",
    "wof:name": "PE37 8PG",
    "wof:placetype": "postalcode"
  },
  "geometry": {"coordinates":[0.698365,52.646562],"type":"Point"}
}
