{
  "type": "Feature",
  "properties": {
    "iso:country": "GB",
    "wof:name": "ML11 9GY",
    "wof:placetype": "postalcode"
  },
  "geometry": {"coordinates":[-3.925402,55.675924],"type":"Point"}
}
