{
  "type": "Feature",
  "properties": {
    "date:inception_lower": "2007-01-01",
    "date:inception_upper": "2007-01-01",
    "iso:country": "GB",
    "wof:name": "ML11 9GY",
    "wof:placetype": "postalcode"
  },
  "geometry": {"coordinates":[-3.925402,55.675924],"type":"Point"}
}
