{
  "type": "Feature",
  "properties": {
    "iso:country":"GB",
    "wof:name":"SS2 4LR",
    "wof:placetype":"postalcode"
},
  "geometry": {"coordinates":[0.73345291109848,51.54777359333504],"type":"Point"}
}