{
  "type": "Feature",
  "properties": {
    "date:inception_lower": "1980-01-01",
    "date:inception_upper": "1980-01-01",
    "iso:country": "GB",
    "wof:name": "KT22 7DU",
    "wof:placetype": "postalcode"
  },
  "geometry": {"coordinates":[-0.327102,51.306058],"type":"Point"}
}
