{
  "type": "Feature",
  "properties": {
    "iso:country":"GB",
    "wof:name":"KT22 7DU",
    "wof:placetype":"postalcode"
},
  "geometry": {"coordinates":[-0.32710184901494,51.30605766848279],"type":"Point"}
}