{
  "type": "Feature",
  "properties": {
    "date:inception_lower": "2004-01-01",
    "date:inception_upper": "2004-01-01",
    "iso:country": "GB",
    "wof:name": "PE26 2UU",
    "wof:placetype": "postalcode"
  },
  "geometry": {"coordinates":[-0.154215,52.478423],"type":"Point"}
}
