{
  "type": "Feature",
  "properties": {
    "iso:country":"GB",
    "wof:name":"GU7 2EX",
    "wof:placetype":"postalcode"
},
  "geometry": {"coordinates":[-0.61148768941052,51.19486066428875],"type":"Point"}
}