{
  "type": "Feature",
  "properties": {
    "iso:country":"GB",
    "wof:name":"EH3 6SS",
    "wof:placetype":"postalcode"
},
  "geometry": {"coordinates":[-3.20533257649906,55.9575715651868],"type":"Point"}
}