{
  "type": "Feature",
  "properties": {
    "iso:country":"GB",
    "wof:name":"HP19 8SZ",
    "wof:placetype":"postalcode"
},
  "geometry": {"coordinates":[-0.83771452521896,51.81942850903906],"type":"Point"}
}