{
  "type": "Feature",
  "properties": {
    "iso:country": "GB",
    "wof:name": "HP19 8SZ",
    "wof:placetype": "postalcode"
  },
  "geometry": {"coordinates":[-0.837714,51.819429],"type":"Point"}
}
