{
  "type": "Feature",
  "properties": {
    "date:inception_lower": "2009-02-01",
    "date:inception_upper": "2009-02-01",
    "iso:country": "GB",
    "wof:name": "HP19 8SZ",
    "wof:placetype": "postalcode"
  },
  "geometry": {"coordinates":[-0.83724,51.819503],"type":"Point"}
}
