{
  "type": "Feature",
  "properties": {
    "iso:country":"GB",
    "wof:name":"PE33 0LW",
    "wof:placetype":"postalcode"
},
  "geometry": {"coordinates":[0.41254200040424,52.72408306944019],"type":"Point"}
}