{
  "type": "Feature",
  "properties": {
    "iso:country":"GB",
    "wof:name":"NR28 9AH",
    "wof:placetype":"postalcode"
},
  "geometry": {"coordinates":[1.4805194679958,52.83215399438998],"type":"Point"}
}