{
  "type": "Feature",
  "properties": {
    "date:inception_lower": "1980-01-01",
    "date:inception_upper": "1980-01-01",
    "iso:country": "GB",
    "wof:name": "NR28 9AH",
    "wof:placetype": "postalcode"
  },
  "geometry": {"coordinates":[1.480541,52.832182],"type":"Point"}
}
