{
  "type": "Feature",
  "properties": {
    "date:inception_lower": "2017-03-01",
    "date:inception_upper": "2017-03-01",
    "iso:country": "GB",
    "wof:name": "WR5 3GT",
    "wof:placetype": "postalcode"
  },
  "geometry": {"coordinates":[-2.221611,52.181229],"type":"Point"}
}
