{
  "type": "Feature",
  "properties": {
    "date:inception_lower": "1980-01-01",
    "date:inception_upper": "1980-01-01",
    "iso:country": "GB",
    "wof:name": "N5 2UT",
    "wof:placetype": "postalcode"
  },
  "geometry": {"coordinates":[-0.093888,51.557121],"type":"Point"}
}
