{
  "type": "Feature",
  "properties": {
    "iso:country": "GB",
    "wof:name": "HD6 2BN",
    "wof:placetype": "postalcode"
  },
  "geometry": {"coordinates":[-1.78492,53.707517],"type":"Point"}
}
