{
  "type": "Feature",
  "properties": {
    "iso:country": "GB",
    "wof:name": "TS9 5BU",
    "wof:placetype": "postalcode"
  },
  "geometry": {"coordinates":[-1.199649,54.468115],"type":"Point"}
}
