{
  "type": "Feature",
  "properties": {
    "iso:country":"GB",
    "wof:name":"WS2 8RH",
    "wof:placetype":"postalcode"
},
  "geometry": {"coordinates":[-2.00491611164717,52.58721135647475],"type":"Point"}
}