{
  "type": "Feature",
  "properties": {
    "date:inception_lower": "2000-06-01",
    "date:inception_upper": "2000-06-01",
    "iso:country": "GB",
    "wof:name": "NN11 3DQ",
    "wof:placetype": "postalcode"
  },
  "geometry": {"coordinates":[-1.212504,52.155931],"type":"Point"}
}
