{
  "type": "Feature",
  "properties": {
    "iso:country": "GB",
    "wof:name": "NN11 3DQ",
    "wof:placetype": "postalcode"
  },
  "geometry": {"coordinates":[-1.210998,52.155997],"type":"Point"}
}
