{
  "type": "Feature",
  "properties": {
    "iso:country":"GB",
    "wof:name":"NN11 3DQ",
    "wof:placetype":"postalcode"
},
  "geometry": {"coordinates":[-1.2109980263611,52.15599746761089],"type":"Point"}
}