{
  "type": "Feature",
  "properties": {
    "iso:country": "GB",
    "wof:name": "CA15 7JT",
    "wof:placetype": "postalcode"
  },
  "geometry": {"coordinates":[-3.430931,54.712278],"type":"Point"}
}
