{
  "type": "Feature",
  "properties": {
    "iso:country":"GB",
    "wof:name":"DA5 1HZ",
    "wof:placetype":"postalcode"
},
  "geometry": {"coordinates":[0.14115001029412,51.44413635843942],"type":"Point"}
}