{
  "type": "Feature",
  "properties": {
    "date:inception_lower": "1980-01-01",
    "date:inception_upper": "1980-01-01",
    "iso:country": "GB",
    "wof:name": "DA5 1HZ",
    "wof:placetype": "postalcode"
  },
  "geometry": {"coordinates":[0.14115,51.444136],"type":"Point"}
}
