{
  "type": "Feature",
  "properties": {
    "iso:country":"GB",
    "wof:name":"ME13 8XB",
    "wof:placetype":"postalcode"
},
  "geometry": {"coordinates":[0.9030299094723,51.30560503832585],"type":"Point"}
}