{
  "type": "Feature",
  "properties": {
    "date:inception_lower": "1998-06-01",
    "date:inception_upper": "1998-06-01",
    "iso:country": "GB",
    "wof:name": "YO23 7DN",
    "wof:placetype": "postalcode"
  },
  "geometry": {"coordinates":[-1.157689,53.874251],"type":"Point"}
}
