{
  "type": "Feature",
  "properties": {
    "iso:country":"GB",
    "wof:name":"YO23 7DN",
    "wof:placetype":"postalcode"
},
  "geometry": {"coordinates":[-1.1576889889064,53.87425144377733],"type":"Point"}
}