{
  "type": "Feature",
  "properties": {
    "iso:country":"GB",
    "wof:name":"PR9 0DP",
    "wof:placetype":"postalcode"
},
  "geometry": {"coordinates":[-3.00516416544964,53.65060244143741],"type":"Point"}
}