{
  "type": "Feature",
  "properties": {
    "iso:country":"GB",
    "wof:name":"YO41 4HG",
    "wof:placetype":"postalcode"
},
  "geometry": {"coordinates":[-0.93438949821569,53.92035771258028],"type":"Point"}
}