{
  "type": "Feature",
  "properties": {
    "iso:country": "GB",
    "wof:name": "YO41 4HG",
    "wof:placetype": "postalcode"
  },
  "geometry": {"coordinates":[-0.934389,53.920358],"type":"Point"}
}
