{
  "type": "Feature",
  "properties": {
    "iso:country":"GB",
    "wof:name":"HG5 0DJ",
    "wof:placetype":"postalcode"
},
  "geometry": {"coordinates":[-1.45675266337043,54.01073184094259],"type":"Point"}
}