{
  "type": "Feature",
  "properties": {
    "iso:country":"GB",
    "wof:name":"SG18 9JS",
    "wof:placetype":"postalcode"
},
  "geometry": {"coordinates":[-0.27230751584593,52.05144695973333],"type":"Point"}
}