{
  "type": "Feature",
  "properties": {
    "iso:country": "GB",
    "wof:name": "SG18 9JS",
    "wof:placetype": "postalcode"
  },
  "geometry": {"coordinates":[-0.272307,52.051447],"type":"Point"}
}
