{
  "type": "Feature",
  "properties": {
    "iso:country": "GB",
    "wof:name": "CH1 5SY",
    "wof:placetype": "postalcode"
  },
  "geometry": {"coordinates":[-2.932106,53.202973],"type":"Point"}
}
