{
  "type": "Feature",
  "properties": {
    "iso:country":"GB",
    "wof:name":"TW15 2JB",
    "wof:placetype":"postalcode"
},
  "geometry": {"coordinates":[-0.45916499243761,51.43437451299981],"type":"Point"}
}