{
  "type": "Feature",
  "properties": {
    "iso:country":"GB",
    "wof:name":"LL31 9UH",
    "wof:placetype":"postalcode"
},
  "geometry": {"coordinates":[-3.82207104723766,53.291539052483],"type":"Point"}
}