{
  "type": "Feature",
  "properties": {
    "date:inception_lower": "1980-01-01",
    "date:inception_upper": "1980-01-01",
    "iso:country": "GB",
    "wof:name": "HP12 4DY",
    "wof:placetype": "postalcode"
  },
  "geometry": {"coordinates":[-0.788584,51.621837],"type":"Point"}
}
