{
  "type": "Feature",
  "properties": {
    "iso:country": "GB",
    "wof:name": "HP12 4DY",
    "wof:placetype": "postalcode"
  },
  "geometry": {"coordinates":[-0.788584,51.621837],"type":"Point"}
}
