{
  "type": "Feature",
  "properties": {
    "date:inception_lower": "1980-01-01",
    "date:inception_upper": "1980-01-01",
    "iso:country": "GB",
    "wof:name": "BA4 6TB",
    "wof:placetype": "postalcode"
  },
  "geometry": {"coordinates":[-2.547358,51.145599],"type":"Point"}
}
