{
  "type": "Feature",
  "properties": {
    "date:inception_lower":"1980-01-01",
    "date:inception_upper":"1980-01-31",
    "iso:country":"GB",
    "wof:name":"B42 2RA",
    "wof:placetype":"postalcode"
},
  "geometry": {"coordinates":[-1.915562,52.546916],"type":"Point"}
}