{
  "type": "Feature",
  "properties": {
    "iso:country":"GB",
    "wof:name":"B42 2RA",
    "wof:placetype":"postalcode"
},
  "geometry": {"coordinates":[-1.91556242829043,52.54691612243801],"type":"Point"}
}