{
  "type": "Feature",
  "properties": {
    "iso:country":"GB",
    "wof:name":"EX8 1SD",
    "wof:placetype":"postalcode"
},
  "geometry": {"coordinates":[-3.4123761301488,50.62512706000775],"type":"Point"}
}