{
  "type": "Feature",
  "properties": {
    "iso:country":"GB",
    "wof:name":"CM14 4RN",
    "wof:placetype":"postalcode"
},
  "geometry": {"coordinates":[0.30310007201637,51.62081892063459],"type":"Point"}
}