{
  "type": "Feature",
  "properties": {
    "date:inception_lower": "2004-01-01",
    "date:inception_upper": "2004-01-01",
    "iso:country": "GB",
    "wof:name": "SE28 0LR",
    "wof:placetype": "postalcode"
  },
  "geometry": {"coordinates":[0.092231,51.501],"type":"Point"}
}
