{
  "type": "Feature",
  "properties": {
    "iso:country":"GB",
    "wof:name":"ML7 5EP",
    "wof:placetype":"postalcode"
},
  "geometry": {"coordinates":[-3.78954473628826,55.82291681684853],"type":"Point"}
}