{
  "type": "Feature",
  "properties": {
    "iso:country": "GB",
    "wof:name": "S70 6JT",
    "wof:placetype": "postalcode"
  },
  "geometry": {"coordinates":[-1.49152,53.548087],"type":"Point"}
}
