{
  "type": "Feature",
  "properties": {
    "iso:country":"GB",
    "wof:name":"DL4 1AF",
    "wof:placetype":"postalcode"
},
  "geometry": {"coordinates":[-1.65138863829656,54.63258709538332],"type":"Point"}
}