{
  "type": "Feature",
  "properties": {
    "iso:country": "GB",
    "wof:name": "WF2 8JF",
    "wof:placetype": "postalcode"
  },
  "geometry": {"coordinates":[-1.53417,53.668929],"type":"Point"}
}
