{
  "type": "Feature",
  "properties": {
    "iso:country": "GB",
    "wof:name": "EX8 4EH",
    "wof:placetype": "postalcode"
  },
  "geometry": {"coordinates":[-3.384338,50.635149],"type":"Point"}
}
