{
  "type": "Feature",
  "properties": {
    "date:inception_lower":"2010-07-01",
    "date:inception_upper":"2010-07-31",
    "iso:country":"GB",
    "wof:name":"BB2 9HR",
    "wof:placetype":"postalcode"
},
  "geometry": {"coordinates":[-2.484903,53.742923],"type":"Point"}
}