{
  "type": "Feature",
  "properties": {
    "iso:country":"GB",
    "wof:name":"WF5 9RZ",
    "wof:placetype":"postalcode"
},
  "geometry": {"coordinates":[-1.59393623241309,53.69300116093882],"type":"Point"}
}