{
  "type": "Feature",
  "properties": {
    "iso:country":"GB",
    "wof:name":"SA73 1RR",
    "wof:placetype":"postalcode"
},
  "geometry": {"coordinates":[-4.95247421580912,51.71187899411816],"type":"Point"}
}