{
  "type": "Feature",
  "properties": {
    "date:inception_lower": "1980-01-01",
    "date:inception_upper": "1980-01-01",
    "iso:country": "GB",
    "wof:name": "SA73 1RR",
    "wof:placetype": "postalcode"
  },
  "geometry": {"coordinates":[-4.952596,51.711898],"type":"Point"}
}
