{
  "type": "Feature",
  "properties": {
    "iso:country":"GB",
    "wof:name":"NR21 9EG",
    "wof:placetype":"postalcode"
},
  "geometry": {"coordinates":[0.84573141469085,52.83317402249716],"type":"Point"}
}