{
  "type": "Feature",
  "properties": {
    "iso:country": "GB",
    "wof:name": "PR1 2EU",
    "wof:placetype": "postalcode"
  },
  "geometry": {"coordinates":[-2.70269,53.76113],"type":"Point"}
}
