{
  "type": "Feature",
  "properties": {
    "iso:country":"GB",
    "wof:name":"PR1 2EU",
    "wof:placetype":"postalcode"
},
  "geometry": {"coordinates":[-2.70269320473876,53.76111423167333],"type":"Point"}
}