{
  "type": "Feature",
  "properties": {
    "iso:country":"GB",
    "wof:name":"SE25 4DT",
    "wof:placetype":"postalcode"
},
  "geometry": {"coordinates":[-0.07425701109921,51.40560755248518],"type":"Point"}
}