{
  "type": "Feature",
  "properties": {
    "iso:country":"GB",
    "wof:name":"SE17 3DJ",
    "wof:placetype":"postalcode"
},
  "geometry": {"coordinates":[-0.1026471128439,51.49117700251822],"type":"Point"}
}