{
  "type": "Feature",
  "properties": {
    "iso:country":"GB",
    "wof:name":"BS6 7LH",
    "wof:placetype":"postalcode"
},
  "geometry": {"coordinates":[-2.60779331327034,51.47729555626253],"type":"Point"}
}