{
  "type": "Feature",
  "properties": {
    "date:inception_lower": "1980-01-01",
    "date:inception_upper": "1980-01-01",
    "iso:country": "GB",
    "wof:name": "CA11 0SQ",
    "wof:placetype": "postalcode"
  },
  "geometry": {"coordinates":[-2.936289,54.646812],"type":"Point"}
}
