{
  "type": "Feature",
  "properties": {
    "iso:country": "GB",
    "wof:name": "CA11 0SQ",
    "wof:placetype": "postalcode"
  },
  "geometry": {"coordinates":[-2.936289,54.646812],"type":"Point"}
}
