{
  "type": "Feature",
  "properties": {
    "iso:country":"GB",
    "wof:name":"LE7 4YU",
    "wof:placetype":"postalcode"
},
  "geometry": {"coordinates":[-1.03902455111533,52.72073633709792],"type":"Point"}
}