{
  "type": "Feature",
  "properties": {
    "iso:country": "GB",
    "wof:name": "LE7 4YU",
    "wof:placetype": "postalcode"
  },
  "geometry": {"coordinates":[-1.039025,52.720736],"type":"Point"}
}
