{
  "type": "Feature",
  "properties": {
    "iso:country":"GB",
    "wof:name":"HA2 9LN",
    "wof:placetype":"postalcode"
},
  "geometry": {"coordinates":[-0.37755152153361,51.57265351350045],"type":"Point"}
}