{
  "type": "Feature",
  "properties": {
    "iso:country":"GB",
    "wof:name":"KA6 7JL",
    "wof:placetype":"postalcode"
},
  "geometry": {"coordinates":[-4.48736244429937,55.35575264678854],"type":"Point"}
}