{
  "type": "Feature",
  "properties": {
    "iso:country": "GB",
    "wof:name": "KA6 7JL",
    "wof:placetype": "postalcode"
  },
  "geometry": {"coordinates":[-4.487362,55.355753],"type":"Point"}
}
