{
  "type": "Feature",
  "properties": {
    "iso:country": "GB",
    "wof:name": "SA44 6EH",
    "wof:placetype": "postalcode"
  },
  "geometry": {"coordinates":[-4.434999,52.147696],"type":"Point"}
}
