{
  "type": "Feature",
  "properties": {
    "iso:country": "GB",
    "wof:name": "BN11 2SQ",
    "wof:placetype": "postalcode"
  },
  "geometry": {"coordinates":[-0.348958,50.818043],"type":"Point"}
}
