{
  "type": "Feature",
  "properties": {
    "iso:country":"GB",
    "wof:name":"SY16 3JH",
    "wof:placetype":"postalcode"
},
  "geometry": {"coordinates":[-3.3734797217378,52.53327494573487],"type":"Point"}
}