{
  "type": "Feature",
  "properties": {
    "iso:country": "GB",
    "wof:name": "SY16 3JH",
    "wof:placetype": "postalcode"
  },
  "geometry": {"coordinates":[-3.37348,52.533275],"type":"Point"}
}
