{
  "type": "Feature",
  "properties": {
    "date:inception_lower":"2012-08-01",
    "date:inception_upper":"2012-08-31",
    "iso:country":"GB",
    "wof:name":"BN22 8QJ",
    "wof:placetype":"postalcode"
},
  "geometry": {"coordinates":[0.302174,50.785406],"type":"Point"}
}