{
  "type": "Feature",
  "properties": {
    "date:inception_lower": "1980-01-01",
    "date:inception_upper": "1980-01-01",
    "iso:country": "GB",
    "wof:name": "FY6 8EF",
    "wof:placetype": "postalcode"
  },
  "geometry": {"coordinates":[-2.989487,53.840173],"type":"Point"}
}
