{
  "type": "Feature",
  "properties": {
    "iso:country": "GB",
    "wof:name": "G46 7DG",
    "wof:placetype": "postalcode"
  },
  "geometry": {"coordinates":[-4.311425,55.808218],"type":"Point"}
}
