{
  "type": "Feature",
  "properties": {
    "iso:country": "GB",
    "wof:name": "PE12 7LZ",
    "wof:placetype": "postalcode"
  },
  "geometry": {"coordinates":[0.011719,52.808651],"type":"Point"}
}
