{
  "type": "Feature",
  "properties": {
    "iso:country": "GB",
    "wof:name": "SE6 3DD",
    "wof:placetype": "postalcode"
  },
  "geometry": {"coordinates":[-0.017014,51.43093],"type":"Point"}
}
