{
  "type": "Feature",
  "properties": {
    "iso:country": "GB",
    "wof:name": "LL16 5DT",
    "wof:placetype": "postalcode"
  },
  "geometry": {"coordinates":[-3.512808,53.235533],"type":"Point"}
}
