{
  "type": "Feature",
  "properties": {
    "iso:country":"GB",
    "wof:name":"LL16 5DT",
    "wof:placetype":"postalcode"
},
  "geometry": {"coordinates":[-3.51285022095786,53.23548917045753],"type":"Point"}
}