{
  "type": "Feature",
  "properties": {
    "iso:country": "GB",
    "wof:name": "DY2 0AN",
    "wof:placetype": "postalcode"
  },
  "geometry": {"coordinates":[-2.092604,52.481868],"type":"Point"}
}
