{
  "type": "Feature",
  "properties": {
    "iso:country": "GB",
    "wof:name": "SG19 3AB",
    "wof:placetype": "postalcode"
  },
  "geometry": {"coordinates":[-0.141696,52.186466],"type":"Point"}
}
