{
  "type": "Feature",
  "properties": {
    "iso:country":"GB",
    "wof:name":"EX20 1UE",
    "wof:placetype":"postalcode"
},
  "geometry": {"coordinates":[-3.98242353150591,50.74271406099413],"type":"Point"}
}