{
  "type": "Feature",
  "properties": {
    "iso:country": "GB",
    "wof:name": "SA61 2JD",
    "wof:placetype": "postalcode"
  },
  "geometry": {"coordinates":[-4.972134,51.802901],"type":"Point"}
}
