{
  "type": "Feature",
  "properties": {
    "iso:country":"GB",
    "wof:name":"SA61 2JD",
    "wof:placetype":"postalcode"
},
  "geometry": {"coordinates":[-4.9722907060034,51.80290076857952],"type":"Point"}
}