{
  "type": "Feature",
  "properties": {
    "iso:country":"GB",
    "wof:name":"PE31 7SB",
    "wof:placetype":"postalcode"
},
  "geometry": {"coordinates":[0.49768868174585,52.90867334085596],"type":"Point"}
}