{
  "type": "Feature",
  "properties": {
    "date:inception_lower":"1980-01-01",
    "date:inception_upper":"1980-01-31",
    "iso:country":"GB",
    "wof:name":"BR1 3DD",
    "wof:placetype":"postalcode"
},
  "geometry": {"coordinates":[0.022476,51.404589],"type":"Point"}
}