{
  "type": "Feature",
  "properties": {
    "iso:country":"GB",
    "wof:name":"BR1 3DD",
    "wof:placetype":"postalcode"
},
  "geometry": {"coordinates":[0.02222139511811,51.40462078218031],"type":"Point"}
}