{
  "type": "Feature",
  "properties": {
    "iso:country": "GB",
    "wof:name": "AB41 7DP",
    "wof:placetype": "postalcode"
  },
  "geometry": {"coordinates":[-2.202067,57.434407],"type":"Point"}
}
