{
  "type": "Feature",
  "properties": {
    "iso:country":"GB",
    "wof:name":"AB41 7DP",
    "wof:placetype":"postalcode"
},
  "geometry": {"coordinates":[-2.2020666080828,57.4344065556694],"type":"Point"}
}