{
  "type": "Feature",
  "properties": {
    "iso:country":"GB",
    "wof:name":"WA4 2LG",
    "wof:placetype":"postalcode"
},
  "geometry": {"coordinates":[-2.55425512685709,53.37583089849934],"type":"Point"}
}