{
  "type": "Feature",
  "properties": {
    "date:inception_lower": "1980-01-01",
    "date:inception_upper": "1980-01-01",
    "iso:country": "GB",
    "wof:name": "LL19 9RL",
    "wof:placetype": "postalcode"
  },
  "geometry": {"coordinates":[-3.400765,53.325064],"type":"Point"}
}
