{
  "type": "Feature",
  "properties": {
    "iso:country":"GB",
    "wof:name":"GU24 9JD",
    "wof:placetype":"postalcode"
},
  "geometry": {"coordinates":[-0.6424079355174,51.3405761084629],"type":"Point"}
}