{
  "type": "Feature",
  "properties": {
    "date:inception_lower": "1980-01-01",
    "date:inception_upper": "1980-01-01",
    "iso:country": "GB",
    "wof:name": "TN12 6RP",
    "wof:placetype": "postalcode"
  },
  "geometry": {"coordinates":[0.348868,51.184528],"type":"Point"}
}
