{
  "type": "Feature",
  "properties": {
    "iso:country":"GB",
    "wof:name":"TN12 6RP",
    "wof:placetype":"postalcode"
},
  "geometry": {"coordinates":[0.34889474256054,51.18449248843543],"type":"Point"}
}