{
  "type": "Feature",
  "properties": {
    "iso:country":"GB",
    "wof:name":"NG22 0HJ",
    "wof:placetype":"postalcode"
},
  "geometry": {"coordinates":[-0.88207874216903,53.20354563976728],"type":"Point"}
}