{
  "type": "Feature",
  "properties": {
    "iso:country":"GB",
    "wof:name":"UB6 9PH",
    "wof:placetype":"postalcode"
},
  "geometry": {"coordinates":[-0.35356503509741,51.52759212731983],"type":"Point"}
}