{
  "type": "Feature",
  "properties": {
    "iso:country":"GB",
    "wof:name":"EH28 8QP",
    "wof:placetype":"postalcode"
},
  "geometry": {"coordinates":[-3.38965588104634,55.93596968853815],"type":"Point"}
}