{
  "type": "Feature",
  "properties": {
    "iso:country":"GB",
    "wof:name":"BB2 6QZ",
    "wof:placetype":"postalcode"
},
  "geometry": {"coordinates":[-2.53979325667101,53.74434200283049],"type":"Point"}
}