{
  "type": "Feature",
  "properties": {
    "date:inception_lower":"2015-10-01",
    "date:inception_upper":"2015-10-31",
    "iso:country":"GB",
    "wof:name":"M34 5ZE",
    "wof:placetype":"postalcode"
},
  "geometry": {"coordinates":[-2.122134,53.464685],"type":"Point"}
}