{
  "type": "Feature",
  "properties": {
    "iso:country":"GB",
    "wof:name":"M34 5ZE",
    "wof:placetype":"postalcode"
},
  "geometry": {"coordinates":[-2.12213407258187,53.46468517732362],"type":"Point"}
}