{
  "type": "Feature",
  "properties": {
    "iso:country": "GB",
    "wof:name": "M34 5ZE",
    "wof:placetype": "postalcode"
  },
  "geometry": {"coordinates":[-2.122134,53.464685],"type":"Point"}
}
