{
  "type": "Feature",
  "properties": {
    "iso:country":"GB",
    "wof:name":"NG7 2NU",
    "wof:placetype":"postalcode"
},
  "geometry": {"coordinates":[-1.17769444103444,52.94316728625158],"type":"Point"}
}