{
  "type": "Feature",
  "properties": {
    "date:inception_lower": "1980-01-01",
    "date:inception_upper": "1980-01-01",
    "iso:country": "GB",
    "wof:name": "SP9 7YD",
    "wof:placetype": "postalcode"
  },
  "geometry": {"coordinates":[-1.668076,51.205755],"type":"Point"}
}
