{
  "type": "Feature",
  "properties": {
    "iso:country":"GB",
    "wof:name":"SP9 7YD",
    "wof:placetype":"postalcode"
},
  "geometry": {"coordinates":[-1.66807561397712,51.20575537267212],"type":"Point"}
}