{
  "type": "Feature",
  "properties": {
    "iso:country":"GB",
    "wof:name":"HG2 8NW",
    "wof:placetype":"postalcode"
},
  "geometry": {"coordinates":[-1.50967381652385,53.9884898339858],"type":"Point"}
}