{
  "type": "Feature",
  "properties": {
    "date:inception_lower":"1987-04-01",
    "date:inception_upper":"1987-04-30",
    "iso:country":"GB",
    "wof:name":"GU9 0QP",
    "wof:placetype":"postalcode"
},
  "geometry": {"coordinates":[-0.79426,51.236012],"type":"Point"}
}