{
  "type": "Feature",
  "properties": {
    "iso:country":"GB",
    "wof:name":"GU9 0QP",
    "wof:placetype":"postalcode"
},
  "geometry": {"coordinates":[-0.79425995316526,51.23601225317464],"type":"Point"}
}