{
  "type": "Feature",
  "properties": {
    "iso:country":"GB",
    "wof:name":"BL1 7HS",
    "wof:placetype":"postalcode"
},
  "geometry": {"coordinates":[-2.42627407239579,53.60978780714525],"type":"Point"}
}