{
  "type": "Feature",
  "properties": {
    "iso:country": "GB",
    "wof:name": "CO2 8FJ",
    "wof:placetype": "postalcode"
  },
  "geometry": {"coordinates":[0.910306,51.858878],"type":"Point"}
}
