{
  "type": "Feature",
  "properties": {
    "iso:country":"GB",
    "wof:name":"CO2 8FJ",
    "wof:placetype":"postalcode"
},
  "geometry": {"coordinates":[0.91030554773805,51.8588775384248],"type":"Point"}
}