{
  "type": "Feature",
  "properties": {
    "date:inception_lower":"2004-08-01",
    "date:inception_upper":"2004-08-31",
    "iso:country":"GB",
    "wof:name":"CO2 8FJ",
    "wof:placetype":"postalcode"
},
  "geometry": {"coordinates":[0.910306,51.858878],"type":"Point"}
}