{
  "type": "Feature",
  "properties": {
    "iso:country":"GB",
    "wof:name":"LL57 1LZ",
    "wof:placetype":"postalcode"
},
  "geometry": {"coordinates":[-4.13461526952563,53.22305883034031],"type":"Point"}
}