{
  "type": "Feature",
  "properties": {
    "iso:country":"GB",
    "wof:name":"TR3 7PU",
    "wof:placetype":"postalcode"
},
  "geometry": {"coordinates":[-5.11858442227992,50.21243553169658],"type":"Point"}
}