{
  "type": "Feature",
  "properties": {
    "iso:country":"GB",
    "wof:name":"L36 0RQ",
    "wof:placetype":"postalcode"
},
  "geometry": {"coordinates":[-2.83433700305061,53.40267800011563],"type":"Point"}
}