{
  "type": "Feature",
  "properties": {
    "iso:country":"GB",
    "wof:name":"HX2 7PP",
    "wof:placetype":"postalcode"
},
  "geometry": {"coordinates":[-1.88948638311937,53.71646752376085],"type":"Point"}
}