{
  "type": "Feature",
  "properties": {
    "iso:country": "GB",
    "wof:name": "PO6 4EB",
    "wof:placetype": "postalcode"
  },
  "geometry": {"coordinates":[-1.096687,50.850687],"type":"Point"}
}
