{
  "type": "Feature",
  "properties": {
    "date:inception_lower": "1980-01-01",
    "date:inception_upper": "1980-01-01",
    "iso:country": "GB",
    "wof:name": "PO6 4EB",
    "wof:placetype": "postalcode"
  },
  "geometry": {"coordinates":[-1.0966,50.85074],"type":"Point"}
}
