{
  "type": "Feature",
  "properties": {
    "iso:country": "GB",
    "wof:name": "CV33 9TX",
    "wof:placetype": "postalcode"
  },
  "geometry": {"coordinates":[-1.488056,52.201917],"type":"Point"}
}
