{
  "type": "Feature",
  "properties": {
    "iso:country": "GB",
    "wof:name": "DY10 2DN",
    "wof:placetype": "postalcode"
  },
  "geometry": {"coordinates":[-2.248515,52.388721],"type":"Point"}
}
