{
  "type": "Feature",
  "properties": {
    "iso:country": "GB",
    "wof:name": "TN18 4BF",
    "wof:placetype": "postalcode"
  },
  "geometry": {"coordinates":[0.509459,51.047938],"type":"Point"}
}
