{
  "type": "Feature",
  "properties": {
    "date:inception_lower":"2003-07-01",
    "date:inception_upper":"2003-07-31",
    "iso:country":"GB",
    "wof:name":"TN18 4BF",
    "wof:placetype":"postalcode"
},
  "geometry": {"coordinates":[0.50955,51.047774],"type":"Point"}
}