{
  "type": "Feature",
  "properties": {
    "iso:country": "GB",
    "wof:name": "TN18 4BF",
    "wof:placetype": "postalcode"
  },
  "geometry": {"coordinates":[0.50955,51.047774],"type":"Point"}
}
