{
  "type": "Feature",
  "properties": {
    "iso:country":"GB",
    "wof:name":"TN18 4BF",
    "wof:placetype":"postalcode"
},
  "geometry": {"coordinates":[0.50952047765387,51.0477767225935],"type":"Point"}
}