{
  "type": "Feature",
  "properties": {
    "iso:country": "GB",
    "wof:name": "ZE1 0NP",
    "wof:placetype": "postalcode"
  },
  "geometry": {"coordinates":[-1.153202,60.157148],"type":"Point"}
}
