{
  "type": "Feature",
  "properties": {
    "iso:country":"GB",
    "wof:name":"ZE1 0NP",
    "wof:placetype":"postalcode"
},
  "geometry": {"coordinates":[-1.15287883166878,60.15711947926444],"type":"Point"}
}