{
  "type": "Feature",
  "properties": {
    "iso:country":"GB",
    "wof:name":"SA1 7DJ",
    "wof:placetype":"postalcode"
},
  "geometry": {"coordinates":[-3.91156772429426,51.64542852051906],"type":"Point"}
}