{
  "type": "Feature",
  "properties": {
    "date:inception_lower": "1980-01-01",
    "date:inception_upper": "1980-01-01",
    "iso:country": "GB",
    "wof:name": "SA1 7DJ",
    "wof:placetype": "postalcode"
  },
  "geometry": {"coordinates":[-3.911568,51.645429],"type":"Point"}
}
