{
  "type": "Feature",
  "properties": {
    "iso:country":"GB",
    "wof:name":"WN1 3BL",
    "wof:placetype":"postalcode"
},
  "geometry": {"coordinates":[-2.61956621599201,53.54331820144197],"type":"Point"}
}