{
  "type": "Feature",
  "properties": {
    "iso:country":"GB",
    "wof:name":"TS24 8GY",
    "wof:placetype":"postalcode"
},
  "geometry": {"coordinates":[-1.22643957155854,54.69915356624141],"type":"Point"}
}