{
  "type": "Feature",
  "properties": {
    "date:inception_lower": "2011-08-01",
    "date:inception_upper": "2011-08-01",
    "iso:country": "GB",
    "wof:name": "TS24 8GY",
    "wof:placetype": "postalcode"
  },
  "geometry": {"coordinates":[-1.22644,54.699154],"type":"Point"}
}
