{
  "type": "Feature",
  "properties": {
    "date:inception_lower": "2019-05-01",
    "date:inception_upper": "2019-05-01",
    "iso:country": "GB",
    "wof:name": "YO61 3SB",
    "wof:placetype": "postalcode"
  },
  "geometry": {"coordinates":[-1.181997,54.11746],"type":"Point"}
}
