{
  "type": "Feature",
  "properties": {
    "iso:country": "GB",
    "wof:name": "SA46 0DW",
    "wof:placetype": "postalcode"
  },
  "geometry": {"coordinates":[-4.259661,52.23672],"type":"Point"}
}
