{
  "type": "Feature",
  "properties": {
    "iso:country":"GB",
    "wof:name":"MK17 0LP",
    "wof:placetype":"postalcode"
},
  "geometry": {"coordinates":[-0.82122605883654,51.99739980566117],"type":"Point"}
}