{
  "type": "Feature",
  "properties": {
    "iso:country":"GB",
    "wof:name":"WA7 2FX",
    "wof:placetype":"postalcode"
},
  "geometry": {"coordinates":[-2.70228734712569,53.32296124564475],"type":"Point"}
}