{
  "type": "Feature",
  "properties": {
    "iso:country":"GB",
    "wof:name":"DA3 8DZ",
    "wof:placetype":"postalcode"
},
  "geometry": {"coordinates":[0.31299123840023,51.37088567601057],"type":"Point"}
}