{
  "type": "Feature",
  "properties": {
    "date:inception_lower": "1980-01-01",
    "date:inception_upper": "1980-01-01",
    "iso:country": "GB",
    "wof:name": "DE11 0DX",
    "wof:placetype": "postalcode"
  },
  "geometry": {"coordinates":[-1.552036,52.780831],"type":"Point"}
}
