{
  "type": "Feature",
  "properties": {
    "date:inception_lower":"1994-12-01",
    "date:inception_upper":"1994-12-31",
    "iso:country":"GB",
    "wof:name":"LL18 2TX",
    "wof:placetype":"postalcode"
},
  "geometry": {"coordinates":[-3.464522,53.292772],"type":"Point"}
}