{
  "type": "Feature",
  "properties": {
    "iso:country": "GB",
    "wof:name": "LL18 2TX",
    "wof:placetype": "postalcode"
  },
  "geometry": {"coordinates":[-3.464522,53.292772],"type":"Point"}
}
