{
  "type": "Feature",
  "properties": {
    "iso:country":"GB",
    "wof:name":"S4 8GE",
    "wof:placetype":"postalcode"
},
  "geometry": {"coordinates":[-1.44125281821007,53.40756946172963],"type":"Point"}
}