{
  "type": "Feature",
  "properties": {
    "date:inception_lower": "1980-01-01",
    "date:inception_upper": "1980-01-01",
    "iso:country": "GB",
    "wof:name": "S4 8GE",
    "wof:placetype": "postalcode"
  },
  "geometry": {"coordinates":[-1.441253,53.407569],"type":"Point"}
}
