{
  "type": "Feature",
  "properties": {
    "iso:country": "GB",
    "wof:name": "BH8 8FH",
    "wof:placetype": "postalcode"
  },
  "geometry": {"coordinates":[-1.856286,50.736488],"type":"Point"}
}
