{
  "type": "Feature",
  "properties": {
    "iso:country":"GB",
    "wof:name":"BH8 8FH",
    "wof:placetype":"postalcode"
},
  "geometry": {"coordinates":[-1.8562857803851,50.73648824787428],"type":"Point"}
}