{
  "type": "Feature",
  "properties": {
    "iso:country":"GB",
    "wof:name":"S10 2TY",
    "wof:placetype":"postalcode"
},
  "geometry": {"coordinates":[-1.4966238515778,53.38213495893918],"type":"Point"}
}