{
  "type": "Feature",
  "properties": {
    "iso:country": "GB",
    "wof:name": "SL9 8PS",
    "wof:placetype": "postalcode"
  },
  "geometry": {"coordinates":[-0.557071,51.59068],"type":"Point"}
}
