{
  "type": "Feature",
  "properties": {
    "date:inception_lower": "1980-01-01",
    "date:inception_upper": "1980-01-01",
    "iso:country": "GB",
    "wof:name": "NG11 8BX",
    "wof:placetype": "postalcode"
  },
  "geometry": {"coordinates":[-1.179653,52.903916],"type":"Point"}
}
