{
  "type": "Feature",
  "properties": {
    "iso:country": "GB",
    "wof:name": "NG11 8BX",
    "wof:placetype": "postalcode"
  },
  "geometry": {"coordinates":[-1.179658,52.90387],"type":"Point"}
}
