{
  "type": "Feature",
  "properties": {
    "iso:country":"GB",
    "wof:name":"NG11 8BX",
    "wof:placetype":"postalcode"
},
  "geometry": {"coordinates":[-1.17965762374201,52.90386962877292],"type":"Point"}
}