{
  "type": "Feature",
  "properties": {
    "iso:country":"GB",
    "wof:name":"L9 1DX",
    "wof:placetype":"postalcode"
},
  "geometry": {"coordinates":[-2.96471865603972,53.45004673509019],"type":"Point"}
}