{
  "type": "Feature",
  "properties": {
    "iso:country":"GB",
    "wof:name":"DA2 8AU",
    "wof:placetype":"postalcode"
},
  "geometry": {"coordinates":[0.28427198068679,51.42604699191384],"type":"Point"}
}