{
  "type": "Feature",
  "properties": {
    "date:inception_lower":"1980-01-01",
    "date:inception_upper":"1980-01-31",
    "iso:country":"GB",
    "wof:name":"PL25 4QA",
    "wof:placetype":"postalcode"
},
  "geometry": {"coordinates":[-4.774272,50.337978],"type":"Point"}
}