{
  "type": "Feature",
  "properties": {
    "date:inception_lower": "2016-04-01",
    "date:inception_upper": "2016-04-01",
    "iso:country": "GB",
    "wof:name": "NE69 7AD",
    "wof:placetype": "postalcode"
  },
  "geometry": {"coordinates":[-1.745844,55.600624],"type":"Point"}
}
