{
  "type": "Feature",
  "properties": {
    "iso:country":"GB",
    "wof:name":"NE69 7AD",
    "wof:placetype":"postalcode"
},
  "geometry": {"coordinates":[-1.74584394381823,55.60062441093722],"type":"Point"}
}