{
  "type": "Feature",
  "properties": {
    "iso:country":"GB",
    "wof:name":"G66 7BU",
    "wof:placetype":"postalcode"
},
  "geometry": {"coordinates":[-4.18840097481217,55.97047936274755],"type":"Point"}
}