{
  "type": "Feature",
  "properties": {
    "date:inception_lower": "1998-12-01",
    "date:inception_upper": "1998-12-01",
    "iso:country": "GB",
    "wof:name": "G66 7BU",
    "wof:placetype": "postalcode"
  },
  "geometry": {"coordinates":[-4.188401,55.970479],"type":"Point"}
}
