{
  "type": "Feature",
  "properties": {
    "iso:country": "GB",
    "wof:name": "KY5 8JR",
    "wof:placetype": "postalcode"
  },
  "geometry": {"coordinates":[-3.330032,56.163377],"type":"Point"}
}
