{
  "type": "Feature",
  "properties": {
    "iso:country":"GB",
    "wof:name":"KY5 8JR",
    "wof:placetype":"postalcode"
},
  "geometry": {"coordinates":[-3.33003195553103,56.16337738552743],"type":"Point"}
}