{
  "type": "Feature",
  "properties": {
    "iso:country":"GB",
    "wof:name":"SK13 8SR",
    "wof:placetype":"postalcode"
},
  "geometry": {"coordinates":[-1.93098833528204,53.43749298655145],"type":"Point"}
}