{
  "type": "Feature",
  "properties": {
    "iso:country": "GB",
    "wof:name": "IP7 7DX",
    "wof:placetype": "postalcode"
  },
  "geometry": {"coordinates":[0.97751,52.115627],"type":"Point"}
}
