{
  "type": "Feature",
  "properties": {
    "date:inception_lower": "1997-06-01",
    "date:inception_upper": "1997-06-01",
    "iso:country": "GB",
    "wof:name": "IP7 7DX",
    "wof:placetype": "postalcode"
  },
  "geometry": {"coordinates":[0.977555,52.115633],"type":"Point"}
}
