{
  "type": "Feature",
  "properties": {
    "iso:country":"GB",
    "wof:name":"IP7 7DX",
    "wof:placetype":"postalcode"
},
  "geometry": {"coordinates":[0.97750991438061,52.11562694528812],"type":"Point"}
}