{
  "type": "Feature",
  "properties": {
    "iso:country":"GB",
    "wof:name":"B93 9JD",
    "wof:placetype":"postalcode"
},
  "geometry": {"coordinates":[-1.7483563835165,52.38850912595861],"type":"Point"}
}