{
  "type": "Feature",
  "properties": {
    "iso:country": "GB",
    "wof:name": "CA8 2AZ",
    "wof:placetype": "postalcode"
  },
  "geometry": {"coordinates":[-2.726761,54.986814],"type":"Point"}
}
