{
  "type": "Feature",
  "properties": {
    "iso:country":"GB",
    "wof:name":"CA8 2AZ",
    "wof:placetype":"postalcode"
},
  "geometry": {"coordinates":[-2.72676135368067,54.98681445293311],"type":"Point"}
}