{
  "type": "Feature",
  "properties": {
    "iso:country":"GB",
    "wof:name":"CA11 8PJ",
    "wof:placetype":"postalcode"
},
  "geometry": {"coordinates":[-2.75037289788753,54.65608707652774],"type":"Point"}
}