{
  "type": "Feature",
  "properties": {
    "iso:country":"GB",
    "wof:name":"CM2 6YP",
    "wof:placetype":"postalcode"
},
  "geometry": {"coordinates":[0.51315330319988,51.73947254048229],"type":"Point"}
}