{
  "type": "Feature",
  "properties": {
    "iso:country":"GB",
    "wof:name":"SA1 6PW",
    "wof:placetype":"postalcode"
},
  "geometry": {"coordinates":[-3.96807829740643,51.62662658929276],"type":"Point"}
}