{
  "type": "Feature",
  "properties": {
    "iso:country": "GB",
    "wof:name": "SA1 6PW",
    "wof:placetype": "postalcode"
  },
  "geometry": {"coordinates":[-3.968078,51.626627],"type":"Point"}
}
