{
  "type": "Feature",
  "properties": {
    "iso:country":"GB",
    "wof:name":"KT20 7TN",
    "wof:placetype":"postalcode"
},
  "geometry": {"coordinates":[-0.23918238490353,51.27913043149254],"type":"Point"}
}