{
  "type": "Feature",
  "properties": {
    "date:inception_lower": "2014-10-01",
    "date:inception_upper": "2014-10-01",
    "iso:country": "GB",
    "wof:name": "DN3 3FA",
    "wof:placetype": "postalcode"
  },
  "geometry": {"coordinates":[-1.04185,53.509996],"type":"Point"}
}
