{
  "type": "Feature",
  "properties": {
    "iso:country": "GB",
    "wof:name": "DN3 3FA",
    "wof:placetype": "postalcode"
  },
  "geometry": {"coordinates":[-1.04185,53.509996],"type":"Point"}
}
