{
  "type": "Feature",
  "properties": {
    "iso:country":"GB",
    "wof:name":"DN3 3FA",
    "wof:placetype":"postalcode"
},
  "geometry": {"coordinates":[-1.0418501424691,53.50999621309676],"type":"Point"}
}