{
  "type": "Feature",
  "properties": {
    "iso:country":"GB",
    "wof:name":"S75 3JN",
    "wof:placetype":"postalcode"
},
  "geometry": {"coordinates":[-1.52659126339262,53.54556144021589],"type":"Point"}
}