{
  "type": "Feature",
  "properties": {
    "iso:country":"GB",
    "wof:name":"GL54 4NX",
    "wof:placetype":"postalcode"
},
  "geometry": {"coordinates":[-1.95088811733954,51.81894618428708],"type":"Point"}
}