{
  "type": "Feature",
  "properties": {
    "iso:country": "GB",
    "wof:name": "LE12 8BG",
    "wof:placetype": "postalcode"
  },
  "geometry": {"coordinates":[-1.162676,52.747647],"type":"Point"}
}
