{
  "type": "Feature",
  "properties": {
    "iso:country":"GB",
    "wof:name":"GL19 4DG",
    "wof:placetype":"postalcode"
},
  "geometry": {"coordinates":[-2.20257985132387,51.95418408611461],"type":"Point"}
}