{
  "type": "Feature",
  "properties": {
    "iso:country": "GB",
    "wof:name": "NP44 1RR",
    "wof:placetype": "postalcode"
  },
  "geometry": {"coordinates":[-3.025463,51.66527],"type":"Point"}
}
