{
  "type": "Feature",
  "properties": {
    "iso:country": "GB",
    "wof:name": "NG17 4ET",
    "wof:placetype": "postalcode"
  },
  "geometry": {"coordinates":[-1.253691,53.132471],"type":"Point"}
}
