{
  "type": "Feature",
  "properties": {
    "iso:country":"GB",
    "wof:name":"NG17 4ET",
    "wof:placetype":"postalcode"
},
  "geometry": {"coordinates":[-1.25369126249168,53.13247127326948],"type":"Point"}
}