{
  "type": "Feature",
  "properties": {
    "iso:country":"GB",
    "wof:name":"CA1 3RS",
    "wof:placetype":"postalcode"
},
  "geometry": {"coordinates":[-2.88998706563439,54.88343473375752],"type":"Point"}
}