{
  "type": "Feature",
  "properties": {
    "iso:country": "GB",
    "wof:name": "CA1 3RS",
    "wof:placetype": "postalcode"
  },
  "geometry": {"coordinates":[-2.889987,54.883435],"type":"Point"}
}
