{
  "type": "Feature",
  "properties": {
    "iso:country": "GB",
    "wof:name": "LS9 8HB",
    "wof:placetype": "postalcode"
  },
  "geometry": {"coordinates":[-1.528631,53.796323],"type":"Point"}
}
