{
  "type": "Feature",
  "properties": {
    "iso:country":"GB",
    "wof:name":"PR4 6ND",
    "wof:placetype":"postalcode"
},
  "geometry": {"coordinates":[-2.82958143074325,53.67492259776794],"type":"Point"}
}