{
  "type": "Feature",
  "properties": {
    "iso:country":"GB",
    "wof:name":"WC1N 2JQ",
    "wof:placetype":"postalcode"
},
  "geometry": {"coordinates":[-0.11490604267184,51.5222461174589],"type":"Point"}
}