{
  "type": "Feature",
  "properties": {
    "iso:country":"GB",
    "wof:name":"CW8 3NW",
    "wof:placetype":"postalcode"
},
  "geometry": {"coordinates":[-2.5767907919303,53.26258194702992],"type":"Point"}
}