{
  "type": "Feature",
  "properties": {
    "iso:country":"GB",
    "wof:name":"HU5 2TA",
    "wof:placetype":"postalcode"
},
  "geometry": {"coordinates":[-0.35267443220493,53.75723445550343],"type":"Point"}
}