{
  "type": "Feature",
  "properties": {
    "iso:country":"GB",
    "wof:name":"EH32 9AU",
    "wof:placetype":"postalcode"
},
  "geometry": {"coordinates":[-2.98297403712077,55.95904295736933],"type":"Point"}
}