{
  "type": "Feature",
  "properties": {
    "iso:country": "GB",
    "wof:name": "NE42 6LQ",
    "wof:placetype": "postalcode"
  },
  "geometry": {"coordinates":[-1.865491,54.956185],"type":"Point"}
}
