{
  "type": "Feature",
  "properties": {
    "iso:country": "GB",
    "wof:name": "SO19 4DW",
    "wof:placetype": "postalcode"
  },
  "geometry": {"coordinates":[-1.364249,50.91432],"type":"Point"}
}
