{
  "type": "Feature",
  "properties": {
    "iso:country":"GB",
    "wof:name":"SO19 4DW",
    "wof:placetype":"postalcode"
},
  "geometry": {"coordinates":[-1.36424925979099,50.91431961597213],"type":"Point"}
}