{
  "type": "Feature",
  "properties": {
    "iso:country": "GB",
    "wof:name": "G46 7LL",
    "wof:placetype": "postalcode"
  },
  "geometry": {"coordinates":[-4.311015,55.794574],"type":"Point"}
}
