{
  "type": "Feature",
  "properties": {
    "iso:country":"GB",
    "wof:name":"G46 7LL",
    "wof:placetype":"postalcode"
},
  "geometry": {"coordinates":[-4.31101473088679,55.79457372266138],"type":"Point"}
}