{
  "type": "Feature",
  "properties": {
    "iso:country":"GB",
    "wof:name":"G32 9EQ",
    "wof:placetype":"postalcode"
},
  "geometry": {"coordinates":[-4.15061529895973,55.84974615896512],"type":"Point"}
}