{
  "type": "Feature",
  "properties": {
    "iso:country": "GB",
    "wof:name": "LS27 7NG",
    "wof:placetype": "postalcode"
  },
  "geometry": {"coordinates":[-1.60164,53.770889],"type":"Point"}
}
