{
  "type": "Feature",
  "properties": {
    "iso:country":"GB",
    "wof:name":"SA31 1PS",
    "wof:placetype":"postalcode"
},
  "geometry": {"coordinates":[-4.30837497471296,51.85654086103435],"type":"Point"}
}