{
  "type": "Feature",
  "properties": {
    "iso:country":"GB",
    "wof:name":"LS9 6PF",
    "wof:placetype":"postalcode"
},
  "geometry": {"coordinates":[-1.49036493535292,53.80964000494703],"type":"Point"}
}