{
  "type": "Feature",
  "properties": {
    "iso:country": "GB",
    "wof:name": "LS9 6PF",
    "wof:placetype": "postalcode"
  },
  "geometry": {"coordinates":[-1.490365,53.80964],"type":"Point"}
}
