{
  "type": "Feature",
  "properties": {
    "date:inception_lower":"1980-01-01",
    "date:inception_upper":"1980-01-31",
    "iso:country":"GB",
    "wof:name":"BD12 8AT",
    "wof:placetype":"postalcode"
},
  "geometry": {"coordinates":[-1.768128,53.744436],"type":"Point"}
}