{
  "type": "Feature",
  "properties": {
    "iso:country":"GB",
    "wof:name":"BD12 8AT",
    "wof:placetype":"postalcode"
},
  "geometry": {"coordinates":[-1.76812844332474,53.74443608338622],"type":"Point"}
}