{
  "type": "Feature",
  "properties": {
    "iso:country": "GB",
    "wof:name": "PE21 6JN",
    "wof:placetype": "postalcode"
  },
  "geometry": {"coordinates":[-0.017392,52.977377],"type":"Point"}
}
