{
  "type": "Feature",
  "properties": {
    "iso:country": "GB",
    "wof:name": "CO3 9TJ",
    "wof:placetype": "postalcode"
  },
  "geometry": {"coordinates":[0.82289,51.899366],"type":"Point"}
}
