{
  "type": "Feature",
  "properties": {
    "iso:country": "GB",
    "wof:name": "S81 9HQ",
    "wof:placetype": "postalcode"
  },
  "geometry": {"coordinates":[-1.126954,53.358836],"type":"Point"}
}
