{
  "type": "Feature",
  "properties": {
    "iso:country":"GB",
    "wof:name":"S81 9HQ",
    "wof:placetype":"postalcode"
},
  "geometry": {"coordinates":[-1.12695368304343,53.3588358872455],"type":"Point"}
}