{
  "type": "Feature",
  "properties": {
    "iso:country":"GB",
    "wof:name":"PE11 1GT",
    "wof:placetype":"postalcode"
},
  "geometry": {"coordinates":[-0.16289902140228,52.78226296065166],"type":"Point"}
}