{
  "type": "Feature",
  "properties": {
    "iso:country":"GB",
    "wof:name":"EX11 1SF",
    "wof:placetype":"postalcode"
},
  "geometry": {"coordinates":[-3.31038246069234,50.70786961574484],"type":"Point"}
}