{
  "type": "Feature",
  "properties": {
    "iso:country":"GB",
    "wof:name":"CM0 7LH",
    "wof:placetype":"postalcode"
},
  "geometry": {"coordinates":[0.82189494816135,51.69794315877446],"type":"Point"}
}