{
  "type": "Feature",
  "properties": {
    "date:inception_lower":"1980-01-01",
    "date:inception_upper":"1980-01-31",
    "iso:country":"GB",
    "wof:name":"CM0 7LH",
    "wof:placetype":"postalcode"
},
  "geometry": {"coordinates":[0.821895,51.697943],"type":"Point"}
}