{
  "type": "Feature",
  "properties": {
    "iso:country": "GB",
    "wof:name": "CM0 7LH",
    "wof:placetype": "postalcode"
  },
  "geometry": {"coordinates":[0.821895,51.697943],"type":"Point"}
}
