{
  "type": "Feature",
  "properties": {
    "iso:country": "GB",
    "wof:name": "KA15 2BX",
    "wof:placetype": "postalcode"
  },
  "geometry": {"coordinates":[-4.631806,55.754307],"type":"Point"}
}
