{
  "type": "Feature",
  "properties": {
    "iso:country": "GB",
    "wof:name": "WF17 9DU",
    "wof:placetype": "postalcode"
  },
  "geometry": {"coordinates":[-1.660865,53.730265],"type":"Point"}
}
