{
  "type": "Feature",
  "properties": {
    "iso:country":"GB",
    "wof:name":"OL6 8SL",
    "wof:placetype":"postalcode"
},
  "geometry": {"coordinates":[-2.08746123888596,53.50183789281143],"type":"Point"}
}