{
  "type": "Feature",
  "properties": {
    "iso:country": "GB",
    "wof:name": "GL53 0BB",
    "wof:placetype": "postalcode"
  },
  "geometry": {"coordinates":[-2.07966,51.885903],"type":"Point"}
}
