{
  "type": "Feature",
  "properties": {
    "date:inception_lower": "2015-12-01",
    "date:inception_upper": "2015-12-01",
    "iso:country": "GB",
    "wof:name": "NR7 8DQ",
    "wof:placetype": "postalcode"
  },
  "geometry": {"coordinates":[1.341868,52.660657],"type":"Point"}
}
