{
  "type": "Feature",
  "properties": {
    "iso:country":"GB",
    "wof:name":"NR7 8DQ",
    "wof:placetype":"postalcode"
},
  "geometry": {"coordinates":[1.33865993598878,52.6621159955271],"type":"Point"}
}