{
  "type": "Feature",
  "properties": {
    "iso:country": "GB",
    "wof:name": "SK13 6EF",
    "wof:placetype": "postalcode"
  },
  "geometry": {"coordinates":[-1.979045,53.452558],"type":"Point"}
}
