{
  "type": "Feature",
  "properties": {
    "iso:country":"GB",
    "wof:name":"RH10 7LD",
    "wof:placetype":"postalcode"
},
  "geometry": {"coordinates":[-0.1565571856417,51.09818860354184],"type":"Point"}
}