{
  "type": "Feature",
  "properties": {
    "date:inception_lower": "1995-01-01",
    "date:inception_upper": "1995-01-01",
    "iso:country": "GB",
    "wof:name": "RH10 7LD",
    "wof:placetype": "postalcode"
  },
  "geometry": {"coordinates":[-0.156557,51.098189],"type":"Point"}
}
