{
  "type": "Feature",
  "properties": {
    "iso:country": "GB",
    "wof:name": "LL20 8NS",
    "wof:placetype": "postalcode"
  },
  "geometry": {"coordinates":[-3.16994,52.96952],"type":"Point"}
}
