{
  "type": "Feature",
  "properties": {
    "iso:country":"GB",
    "wof:name":"LL20 8NS",
    "wof:placetype":"postalcode"
},
  "geometry": {"coordinates":[-3.16994012520871,52.96951952975467],"type":"Point"}
}