{
  "type": "Feature",
  "properties": {
    "date:inception_lower": "2001-06-01",
    "date:inception_upper": "2001-06-01",
    "iso:country": "GB",
    "wof:name": "PR25 3AE",
    "wof:placetype": "postalcode"
  },
  "geometry": {"coordinates":[-2.683458,53.688196],"type":"Point"}
}
