{
  "type": "Feature",
  "properties": {
    "iso:country":"GB",
    "wof:name":"PR25 3AE",
    "wof:placetype":"postalcode"
},
  "geometry": {"coordinates":[-2.6834584053126,53.68819588993744],"type":"Point"}
}