{
  "type": "Feature",
  "properties": {
    "iso:country":"GB",
    "wof:name":"AB45 2PN",
    "wof:placetype":"postalcode"
},
  "geometry": {"coordinates":[-2.69479802479944,57.68376398036573],"type":"Point"}
}