{
  "type": "Feature",
  "properties": {
    "iso:country": "GB",
    "wof:name": "EN8 7EY",
    "wof:placetype": "postalcode"
  },
  "geometry": {"coordinates":[-0.02549,51.696983],"type":"Point"}
}
