{
  "type": "Feature",
  "properties": {
    "iso:country":"GB",
    "wof:name":"EN8 7EY",
    "wof:placetype":"postalcode"
},
  "geometry": {"coordinates":[-0.02548979204179,51.69698324031341],"type":"Point"}
}