{
  "type": "Feature",
  "properties": {
    "iso:country":"GB",
    "wof:name":"FY8 2NE",
    "wof:placetype":"postalcode"
},
  "geometry": {"coordinates":[-3.03494577458258,53.75086747935656],"type":"Point"}
}