{
  "type": "Feature",
  "properties": {
    "iso:country":"GB",
    "wof:name":"EC4Y 7EQ",
    "wof:placetype":"postalcode"
},
  "geometry": {"coordinates":[-0.10857626578673,51.51184776243417],"type":"Point"}
}