{
  "type": "Feature",
  "properties": {
    "date:inception_lower":"1980-01-01",
    "date:inception_upper":"1980-01-31",
    "iso:country":"GB",
    "wof:name":"CF48 4EU",
    "wof:placetype":"postalcode"
},
  "geometry": {"coordinates":[-3.349304,51.708969],"type":"Point"}
}