{
  "type": "Feature",
  "properties": {
    "iso:country":"GB",
    "wof:name":"CF48 4EU",
    "wof:placetype":"postalcode"
},
  "geometry": {"coordinates":[-3.349304409198,51.70896852082122],"type":"Point"}
}