{
  "type": "Feature",
  "properties": {
    "iso:country":"GB",
    "wof:name":"PH9 0PN",
    "wof:placetype":"postalcode"
},
  "geometry": {"coordinates":[-3.66944058607372,56.65541359079354],"type":"Point"}
}