{
  "type": "Feature",
  "properties": {
    "date:inception_lower": "2021-01-01",
    "date:inception_upper": "2021-01-01",
    "iso:country": "GB",
    "wof:name": "G81 1BS",
    "wof:placetype": "postalcode"
  },
  "geometry": {"coordinates":[-4.398427,55.897763],"type":"Point"}
}
