{
  "type": "Feature",
  "properties": {
    "iso:country": "GB",
    "wof:name": "PE7 8NQ",
    "wof:placetype": "postalcode"
  },
  "geometry": {"coordinates":[-0.254891,52.534625],"type":"Point"}
}
