{
  "type": "Feature",
  "properties": {
    "iso:country": "GB",
    "wof:name": "PL8 1JZ",
    "wof:placetype": "postalcode"
  },
  "geometry": {"coordinates":[-3.964302,50.317995],"type":"Point"}
}
