{
  "type": "Feature",
  "properties": {
    "date:inception_lower": "1980-01-01",
    "date:inception_upper": "1980-01-01",
    "iso:country": "GB",
    "wof:name": "PL8 1JZ",
    "wof:placetype": "postalcode"
  },
  "geometry": {"coordinates":[-3.964241,50.317547],"type":"Point"}
}
