{
  "type": "Feature",
  "properties": {
    "iso:country": "GB",
    "wof:name": "BD6 3YP",
    "wof:placetype": "postalcode"
  },
  "geometry": {"coordinates":[-1.811346,53.767153],"type":"Point"}
}
