{
  "type": "Feature",
  "properties": {
    "date:inception_lower":"2004-03-01",
    "date:inception_upper":"2004-03-31",
    "iso:country":"GB",
    "wof:name":"BD6 3YP",
    "wof:placetype":"postalcode"
},
  "geometry": {"coordinates":[-1.811346,53.767153],"type":"Point"}
}