{
  "type": "Feature",
  "properties": {
    "iso:country":"GB",
    "wof:name":"BD6 3YP",
    "wof:placetype":"postalcode"
},
  "geometry": {"coordinates":[-1.8113460756039,53.7671526565449],"type":"Point"}
}