{
  "type": "Feature",
  "properties": {
    "date:inception_lower":"1980-01-01",
    "date:inception_upper":"1980-01-31",
    "iso:country":"GB",
    "wof:name":"CF5 6XE",
    "wof:placetype":"postalcode"
},
  "geometry": {"coordinates":[-3.255383,51.460658],"type":"Point"}
}