{
  "type": "Feature",
  "properties": {
    "iso:country": "GB",
    "wof:name": "CF5 6XE",
    "wof:placetype": "postalcode"
  },
  "geometry": {"coordinates":[-3.255383,51.460658],"type":"Point"}
}
