{
  "type": "Feature",
  "properties": {
    "iso:country":"GB",
    "wof:name":"S14 1QU",
    "wof:placetype":"postalcode"
},
  "geometry": {"coordinates":[-1.43897446126908,53.34859282256624],"type":"Point"}
}