{
  "type": "Feature",
  "properties": {
    "iso:country":"GB",
    "wof:name":"IP32 6RJ",
    "wof:placetype":"postalcode"
},
  "geometry": {"coordinates":[0.69985573227396,52.25763135957767],"type":"Point"}
}