{
  "type": "Feature",
  "properties": {
    "date:inception_lower":"2003-01-01",
    "date:inception_upper":"2003-01-31",
    "iso:country":"GB",
    "wof:name":"NR23 1GY",
    "wof:placetype":"postalcode"
},
  "geometry": {"coordinates":[0.854272,52.950382],"type":"Point"}
}