{
  "type": "Feature",
  "properties": {
    "iso:country": "GB",
    "wof:name": "NR23 1GY",
    "wof:placetype": "postalcode"
  },
  "geometry": {"coordinates":[0.854272,52.950382],"type":"Point"}
}
