{
  "type": "Feature",
  "properties": {
    "date:inception_lower": "2009-11-01",
    "date:inception_upper": "2009-11-01",
    "iso:country": "GB",
    "wof:name": "E14 9AF",
    "wof:placetype": "postalcode"
  },
  "geometry": {"coordinates":[-0.025445,51.502276],"type":"Point"}
}
