{
  "type": "Feature",
  "properties": {
    "date:inception_lower": "2020-10-01",
    "date:inception_upper": "2020-10-01",
    "iso:country": "GB",
    "wof:name": "IP7 7NX",
    "wof:placetype": "postalcode"
  },
  "geometry": {"coordinates":[0.89659,52.124549],"type":"Point"}
}
