{
  "type": "Feature",
  "properties": {
    "iso:country": "GB",
    "wof:name": "NE22 7BJ",
    "wof:placetype": "postalcode"
  },
  "geometry": {"coordinates":[-1.534107,55.144769],"type":"Point"}
}
