{
  "type": "Feature",
  "properties": {
    "iso:country": "GB",
    "wof:name": "NG24 3RJ",
    "wof:placetype": "postalcode"
  },
  "geometry": {"coordinates":[-0.813614,53.031286],"type":"Point"}
}
