{
  "type": "Feature",
  "properties": {
    "iso:country":"GB",
    "wof:name":"NG24 3RJ",
    "wof:placetype":"postalcode"
},
  "geometry": {"coordinates":[-0.81401456480447,53.03151149027187],"type":"Point"}
}