{
  "type": "Feature",
  "properties": {
    "date:inception_lower":"1980-01-01",
    "date:inception_upper":"1980-01-31",
    "iso:country":"GB",
    "wof:name":"TN1 2QU",
    "wof:placetype":"postalcode"
},
  "geometry": {"coordinates":[0.270806,51.136463],"type":"Point"}
}