{
  "type": "Feature",
  "properties": {
    "iso:country":"GB",
    "wof:name":"TN1 2QU",
    "wof:placetype":"postalcode"
},
  "geometry": {"coordinates":[0.27080571383746,51.13646260897228],"type":"Point"}
}