{
  "type": "Feature",
  "properties": {
    "iso:country":"GB",
    "wof:name":"BA2 4DL",
    "wof:placetype":"postalcode"
},
  "geometry": {"coordinates":[-2.3551980835683,51.38384937472014],"type":"Point"}
}