{
  "type": "Feature",
  "properties": {
    "date:inception_lower": "1997-06-01",
    "date:inception_upper": "1997-06-01",
    "iso:country": "GB",
    "wof:name": "ML1 5TR",
    "wof:placetype": "postalcode"
  },
  "geometry": {"coordinates":[-3.940721,55.799846],"type":"Point"}
}
