{
  "type": "Feature",
  "properties": {
    "iso:country":"GB",
    "wof:name":"WR12 7AX",
    "wof:placetype":"postalcode"
},
  "geometry": {"coordinates":[-1.85301749776819,52.0381057363051],"type":"Point"}
}