{
  "type": "Feature",
  "properties": {
    "date:inception_lower":"1980-01-01",
    "date:inception_upper":"1980-01-31",
    "iso:country":"GB",
    "wof:name":"WR12 7AX",
    "wof:placetype":"postalcode"
},
  "geometry": {"coordinates":[-1.853017,52.038106],"type":"Point"}
}