{
  "type": "Feature",
  "properties": {
    "iso:country":"GB",
    "wof:name":"S71 5DB",
    "wof:placetype":"postalcode"
},
  "geometry": {"coordinates":[-1.42604432017155,53.54388098937231],"type":"Point"}
}