{
  "type": "Feature",
  "properties": {
    "iso:country": "GB",
    "wof:name": "PO8 0WN",
    "wof:placetype": "postalcode"
  },
  "geometry": {"coordinates":[-0.990716,50.941942],"type":"Point"}
}
