{
  "type": "Feature",
  "properties": {
    "date:inception_lower": "1983-03-01",
    "date:inception_upper": "1983-03-01",
    "iso:country": "GB",
    "wof:name": "WV9 5AS",
    "wof:placetype": "postalcode"
  },
  "geometry": {"coordinates":[-2.136616,52.656983],"type":"Point"}
}
