{
  "type": "Feature",
  "properties": {
    "iso:country": "GB",
    "wof:name": "PE24 4PT",
    "wof:placetype": "postalcode"
  },
  "geometry": {"coordinates":[0.204198,53.127174],"type":"Point"}
}
