{
  "type": "Feature",
  "properties": {
    "date:inception_lower": "1983-07-01",
    "date:inception_upper": "1983-07-01",
    "iso:country": "GB",
    "wof:name": "PE24 4PT",
    "wof:placetype": "postalcode"
  },
  "geometry": {"coordinates":[0.204198,53.127174],"type":"Point"}
}
