{
  "type": "Feature",
  "properties": {
    "date:inception_lower": "1980-01-01",
    "date:inception_upper": "1980-01-01",
    "iso:country": "GB",
    "wof:name": "S4 7AL",
    "wof:placetype": "postalcode"
  },
  "geometry": {"coordinates":[-1.456671,53.404018],"type":"Point"}
}
