{
  "type": "Feature",
  "properties": {
    "iso:country":"GB",
    "wof:name":"HP9 2PL",
    "wof:placetype":"postalcode"
},
  "geometry": {"coordinates":[-0.64404568361062,51.61300058439226],"type":"Point"}
}