{
  "type": "Feature",
  "properties": {
    "iso:country":"GB",
    "wof:name":"NR7 0XJ",
    "wof:placetype":"postalcode"
},
  "geometry": {"coordinates":[1.34559779362366,52.63483099788672],"type":"Point"}
}