{
  "type": "Feature",
  "properties": {
    "iso:country":"GB",
    "wof:name":"TN2 5JJ",
    "wof:placetype":"postalcode"
},
  "geometry": {"coordinates":[0.27113128029891,51.11600498542537],"type":"Point"}
}