{
  "type": "Feature",
  "properties": {
    "iso:country": "GB",
    "wof:name": "AL1 3EE",
    "wof:placetype": "postalcode"
  },
  "geometry": {"coordinates":[-0.332411,51.753886],"type":"Point"}
}
