{
  "type": "Feature",
  "properties": {
    "iso:country":"GB",
    "wof:name":"SY4 4LU",
    "wof:placetype":"postalcode"
},
  "geometry": {"coordinates":[-2.65264447718846,52.83388878571512],"type":"Point"}
}