{
  "type": "Feature",
  "properties": {
    "date:inception_lower":"1980-01-01",
    "date:inception_upper":"1980-01-31",
    "iso:country":"GB",
    "wof:name":"CF48 4DQ",
    "wof:placetype":"postalcode"
},
  "geometry": {"coordinates":[-3.353782,51.722225],"type":"Point"}
}