{
  "type": "Feature",
  "properties": {
    "iso:country":"GB",
    "wof:name":"CH3 6QG",
    "wof:placetype":"postalcode"
},
  "geometry": {"coordinates":[-2.87962345063319,53.08476818870338],"type":"Point"}
}