{
  "type": "Feature",
  "properties": {
    "iso:country": "GB",
    "wof:name": "CH3 6QG",
    "wof:placetype": "postalcode"
  },
  "geometry": {"coordinates":[-2.879623,53.084768],"type":"Point"}
}
