{
  "type": "Feature",
  "properties": {
    "iso:country":"GB",
    "wof:name":"SY23 4EY",
    "wof:placetype":"postalcode"
},
  "geometry": {"coordinates":[-4.0697536369816,52.32150798860535],"type":"Point"}
}