{
  "type": "Feature",
  "properties": {
    "date:inception_lower": "1980-01-01",
    "date:inception_upper": "1980-01-01",
    "iso:country": "GB",
    "wof:name": "SY23 4EY",
    "wof:placetype": "postalcode"
  },
  "geometry": {"coordinates":[-4.069754,52.321508],"type":"Point"}
}
