{
  "type": "Feature",
  "properties": {
    "iso:country": "GB",
    "wof:name": "CB21 4LE",
    "wof:placetype": "postalcode"
  },
  "geometry": {"coordinates":[0.295605,52.108072],"type":"Point"}
}
