{
  "type": "Feature",
  "properties": {
    "iso:country": "GB",
    "wof:name": "DN6 7DE",
    "wof:placetype": "postalcode"
  },
  "geometry": {"coordinates":[-1.195124,53.571583],"type":"Point"}
}
