{
  "type": "Feature",
  "properties": {
    "iso:country":"GB",
    "wof:name":"DN6 7DE",
    "wof:placetype":"postalcode"
},
  "geometry": {"coordinates":[-1.19512415816617,53.57158342375838],"type":"Point"}
}