{
  "type": "Feature",
  "properties": {
    "date:inception_lower": "2002-07-01",
    "date:inception_upper": "2002-07-01",
    "iso:country": "GB",
    "wof:name": "NG1 1QX",
    "wof:placetype": "postalcode"
  },
  "geometry": {"coordinates":[-1.141952,52.951302],"type":"Point"}
}
