{
  "type": "Feature",
  "properties": {
    "iso:country": "GB",
    "wof:name": "HR7 4PJ",
    "wof:placetype": "postalcode"
  },
  "geometry": {"coordinates":[-2.478813,52.205518],"type":"Point"}
}
