{
  "type": "Feature",
  "properties": {
    "date:inception_lower": "1980-01-01",
    "date:inception_upper": "1980-01-01",
    "iso:country": "GB",
    "wof:name": "HR7 4PJ",
    "wof:placetype": "postalcode"
  },
  "geometry": {"coordinates":[-2.478813,52.205518],"type":"Point"}
}
