{
  "type": "Feature",
  "properties": {
    "iso:country":"GB",
    "wof:name":"HR7 4PJ",
    "wof:placetype":"postalcode"
},
  "geometry": {"coordinates":[-2.47881320592853,52.20551795816347],"type":"Point"}
}