{
  "type": "Feature",
  "properties": {
    "iso:country": "GB",
    "wof:name": "PE19 1BA",
    "wof:placetype": "postalcode"
  },
  "geometry": {"coordinates":[-0.267265,52.230196],"type":"Point"}
}
