{
  "type": "Feature",
  "properties": {
    "date:inception_lower":"1980-01-01",
    "date:inception_upper":"1980-01-31",
    "iso:country":"GB",
    "wof:name":"EX1 3PF",
    "wof:placetype":"postalcode"
},
  "geometry": {"coordinates":[-3.48195,50.732955],"type":"Point"}
}