{
  "type": "Feature",
  "properties": {
    "iso:country":"GB",
    "wof:name":"EX1 3PF",
    "wof:placetype":"postalcode"
},
  "geometry": {"coordinates":[-3.48188909635186,50.73283982061746],"type":"Point"}
}