{
  "type": "Feature",
  "properties": {
    "iso:country": "GB",
    "wof:name": "EX1 3PF",
    "wof:placetype": "postalcode"
  },
  "geometry": {"coordinates":[-3.48195,50.732955],"type":"Point"}
}
