{
  "type": "Feature",
  "properties": {
    "iso:country": "GB",
    "wof:name": "PO14 1RT",
    "wof:placetype": "postalcode"
  },
  "geometry": {"coordinates":[-1.208648,50.847768],"type":"Point"}
}
