{
  "type": "Feature",
  "properties": {
    "date:inception_lower":"1980-01-01",
    "date:inception_upper":"1980-01-31",
    "iso:country":"GB",
    "wof:name":"SE15 5LQ",
    "wof:placetype":"postalcode"
},
  "geometry": {"coordinates":[-0.068877,51.473631],"type":"Point"}
}