{
  "type": "Feature",
  "properties": {
    "iso:country":"GB",
    "wof:name":"CH6 5LL",
    "wof:placetype":"postalcode"
},
  "geometry": {"coordinates":[-3.13670530354933,53.23916743196702],"type":"Point"}
}