{
  "type": "Feature",
  "properties": {
    "iso:country": "GB",
    "wof:name": "CH6 5LL",
    "wof:placetype": "postalcode"
  },
  "geometry": {"coordinates":[-3.136705,53.239167],"type":"Point"}
}
