{
  "type": "Feature",
  "properties": {
    "iso:country": "GB",
    "wof:name": "TN38 0FD",
    "wof:placetype": "postalcode"
  },
  "geometry": {"coordinates":[0.534213,50.850335],"type":"Point"}
}
