{
  "type": "Feature",
  "properties": {
    "iso:country": "GB",
    "wof:name": "LL30 3HP",
    "wof:placetype": "postalcode"
  },
  "geometry": {"coordinates":[-3.769845,53.313713],"type":"Point"}
}
