{
  "type": "Feature",
  "properties": {
    "iso:country":"GB",
    "wof:name":"LL30 3HP",
    "wof:placetype":"postalcode"
},
  "geometry": {"coordinates":[-3.76984481805362,53.31371282602906],"type":"Point"}
}