{
  "type": "Feature",
  "properties": {
    "date:inception_lower": "2020-02-01",
    "date:inception_upper": "2020-02-01",
    "iso:country": "GB",
    "wof:name": "PO1 1FG",
    "wof:placetype": "postalcode"
  },
  "geometry": {"coordinates":[-1.08196,50.80129],"type":"Point"}
}
