{
  "type": "Feature",
  "properties": {
    "iso:country": "GB",
    "wof:name": "PO1 1FG",
    "wof:placetype": "postalcode"
  },
  "geometry": {"coordinates":[-1.091338,50.799179],"type":"Point"}
}
