{
  "type": "Feature",
  "properties": {
    "date:inception_lower": "2020-02-01",
    "date:inception_upper": "2020-02-01",
    "iso:country": "GB",
    "wof:name": "PO1 1FG",
    "wof:placetype": "postalcode"
  },
  "geometry": {"coordinates":[-1.091338,50.799179],"type":"Point"}
}
