{
  "type": "Feature",
  "properties": {
    "iso:country": "GB",
    "wof:name": "CH3 6EN",
    "wof:placetype": "postalcode"
  },
  "geometry": {"coordinates":[-2.833572,53.151575],"type":"Point"}
}
