{
  "type": "Feature",
  "properties": {
    "iso:country": "GB",
    "wof:name": "NP20 4LZ",
    "wof:placetype": "postalcode"
  },
  "geometry": {"coordinates":[-3.007025,51.586826],"type":"Point"}
}
