{
  "type": "Feature",
  "properties": {
    "iso:country":"GB",
    "wof:name":"LL28 5SY",
    "wof:placetype":"postalcode"
},
  "geometry": {"coordinates":[-3.79962426062749,53.26402896690979],"type":"Point"}
}