{
  "type": "Feature",
  "properties": {
    "date:inception_lower": "1980-01-01",
    "date:inception_upper": "1980-01-01",
    "iso:country": "GB",
    "wof:name": "PL19 9LZ",
    "wof:placetype": "postalcode"
  },
  "geometry": {"coordinates":[-4.089098,50.590958],"type":"Point"}
}
