{
  "type": "Feature",
  "properties": {
    "date:inception_lower": "2021-09-01",
    "date:inception_upper": "2021-09-01",
    "iso:country": "GB",
    "wof:name": "DG2 0DP",
    "wof:placetype": "postalcode"
  },
  "geometry": {"coordinates":[-3.624985,55.084409],"type":"Point"}
}
