{
  "type": "Feature",
  "properties": {
    "iso:country": "GB",
    "wof:name": "SK6 1HA",
    "wof:placetype": "postalcode"
  },
  "geometry": {"coordinates":[-2.09917,53.422245],"type":"Point"}
}
