{
  "type": "Feature",
  "properties": {
    "iso:country":"GB",
    "wof:name":"SK6 1HA",
    "wof:placetype":"postalcode"
},
  "geometry": {"coordinates":[-2.09916988512338,53.42224484222206],"type":"Point"}
}