{
  "type": "Feature",
  "properties": {
    "date:inception_lower": "2023-09-01",
    "date:inception_upper": "2023-09-01",
    "iso:country": "GB",
    "wof:name": "CA1 3BZ",
    "wof:placetype": "postalcode"
  },
  "geometry": {"coordinates":[-2.894931,54.870024],"type":"Point"}
}
