{
  "type": "Feature",
  "properties": {
    "date:inception_lower": "2006-05-01",
    "date:inception_upper": "2006-05-01",
    "iso:country": "GB",
    "wof:name": "KA1 5HN",
    "wof:placetype": "postalcode"
  },
  "geometry": {"coordinates":[-4.450554,55.599686],"type":"Point"}
}
