{
  "type": "Feature",
  "properties": {
    "iso:country":"GB",
    "wof:name":"LS29 6JG",
    "wof:placetype":"postalcode"
},
  "geometry": {"coordinates":[-1.73632418466696,53.89111673229854],"type":"Point"}
}