{
  "type": "Feature",
  "properties": {
    "iso:country":"GB",
    "wof:name":"SL1 3LW",
    "wof:placetype":"postalcode"
},
  "geometry": {"coordinates":[-0.5973657836298,51.52533802307298],"type":"Point"}
}