{
  "type": "Feature",
  "properties": {
    "iso:country": "GB",
    "wof:name": "SL1 3LW",
    "wof:placetype": "postalcode"
  },
  "geometry": {"coordinates":[-0.597451,51.525375],"type":"Point"}
}
