{
  "type": "Feature",
  "properties": {
    "iso:country":"GB",
    "wof:name":"RG12 9RY",
    "wof:placetype":"postalcode"
},
  "geometry": {"coordinates":[-0.72492860613894,51.40379192961611],"type":"Point"}
}