{
  "type": "Feature",
  "properties": {
    "date:inception_lower": "1980-01-01",
    "date:inception_upper": "1980-01-01",
    "iso:country": "GB",
    "wof:name": "CA16 6DE",
    "wof:placetype": "postalcode"
  },
  "geometry": {"coordinates":[-2.480666,54.61867],"type":"Point"}
}
