{
  "type": "Feature",
  "properties": {
    "iso:country": "GB",
    "wof:name": "CA16 6DE",
    "wof:placetype": "postalcode"
  },
  "geometry": {"coordinates":[-2.480666,54.61867],"type":"Point"}
}
