{
  "type": "Feature",
  "properties": {
    "iso:country":"GB",
    "wof:name":"PH33 6TZ",
    "wof:placetype":"postalcode"
},
  "geometry": {"coordinates":[-5.13798124300906,56.79777555550914],"type":"Point"}
}