{
  "type": "Feature",
  "properties": {
    "date:inception_lower":"2009-08-01",
    "date:inception_upper":"2009-08-31",
    "iso:country":"GB",
    "wof:name":"PH33 6TZ",
    "wof:placetype":"postalcode"
},
  "geometry": {"coordinates":[-5.137981,56.797776],"type":"Point"}
}