{
  "type": "Feature",
  "properties": {
    "iso:country": "GB",
    "wof:name": "WD7 8BD",
    "wof:placetype": "postalcode"
  },
  "geometry": {"coordinates":[-0.323524,51.691022],"type":"Point"}
}
