{
  "type": "Feature",
  "properties": {
    "date:inception_lower": "1980-01-01",
    "date:inception_upper": "1980-01-01",
    "iso:country": "GB",
    "wof:name": "EX13 5BE",
    "wof:placetype": "postalcode"
  },
  "geometry": {"coordinates":[-2.992085,50.780619],"type":"Point"}
}
