{
  "type": "Feature",
  "properties": {
    "iso:country":"GB",
    "wof:name":"SA19 7RU",
    "wof:placetype":"postalcode"
},
  "geometry": {"coordinates":[-4.03609051734205,52.04809466987489],"type":"Point"}
}