{
  "type": "Feature",
  "properties": {
    "iso:country": "GB",
    "wof:name": "SA19 7RU",
    "wof:placetype": "postalcode"
  },
  "geometry": {"coordinates":[-4.03609,52.048095],"type":"Point"}
}
