{
  "type": "Feature",
  "properties": {
    "date:inception_lower": "1985-10-01",
    "date:inception_upper": "1985-10-01",
    "iso:country": "GB",
    "wof:name": "CH4 8RQ",
    "wof:placetype": "postalcode"
  },
  "geometry": {"coordinates":[-2.93053,53.179926],"type":"Point"}
}
