{
  "type": "Feature",
  "properties": {
    "iso:country":"GB",
    "wof:name":"BL6 7TG",
    "wof:placetype":"postalcode"
},
  "geometry": {"coordinates":[-2.54557614213753,53.59958673788299],"type":"Point"}
}