{
  "type": "Feature",
  "properties": {
    "date:inception_lower": "1997-12-01",
    "date:inception_upper": "1997-12-01",
    "iso:country": "GB",
    "wof:name": "BL6 7TG",
    "wof:placetype": "postalcode"
  },
  "geometry": {"coordinates":[-2.545576,53.599587],"type":"Point"}
}
