{
  "type": "Feature",
  "properties": {
    "iso:country": "GB",
    "wof:name": "BL6 7TG",
    "wof:placetype": "postalcode"
  },
  "geometry": {"coordinates":[-2.545576,53.599587],"type":"Point"}
}
