{
  "type": "Feature",
  "properties": {
    "iso:country":"GB",
    "wof:name":"TN37 7JW",
    "wof:placetype":"postalcode"
},
  "geometry": {"coordinates":[0.55419458655156,50.87695421147561],"type":"Point"}
}