{
  "type": "Feature",
  "properties": {
    "iso:country": "GB",
    "wof:name": "TN37 7JW",
    "wof:placetype": "postalcode"
  },
  "geometry": {"coordinates":[0.554195,50.876954],"type":"Point"}
}
