{
  "type": "Feature",
  "properties": {
    "iso:country": "GB",
    "wof:name": "EX38 8QH",
    "wof:placetype": "postalcode"
  },
  "geometry": {"coordinates":[-4.169669,50.894936],"type":"Point"}
}
