{
  "type": "Feature",
  "properties": {
    "iso:country":"GB",
    "wof:name":"EX38 8QH",
    "wof:placetype":"postalcode"
},
  "geometry": {"coordinates":[-4.16966858111806,50.89493586176557],"type":"Point"}
}