{
  "type": "Feature",
  "properties": {
    "date:inception_lower": "1980-01-01",
    "date:inception_upper": "1980-01-01",
    "iso:country": "GB",
    "wof:name": "EX38 8QH",
    "wof:placetype": "postalcode"
  },
  "geometry": {"coordinates":[-4.169669,50.894936],"type":"Point"}
}
