{
  "type": "Feature",
  "properties": {
    "date:inception_lower":"2018-04-01",
    "date:inception_upper":"2018-04-30",
    "iso:country":"GB",
    "wof:name":"TS17 9DF",
    "wof:placetype":"postalcode"
},
  "geometry": {"coordinates":[-1.291889,54.54562],"type":"Point"}
}