{
  "type": "Feature",
  "properties": {
    "iso:country": "GB",
    "wof:name": "TS17 9DF",
    "wof:placetype": "postalcode"
  },
  "geometry": {"coordinates":[-1.291889,54.54562],"type":"Point"}
}
