{
  "type": "Feature",
  "properties": {
    "iso:country":"GB",
    "wof:name":"TN29 9LJ",
    "wof:placetype":"postalcode"
},
  "geometry": {"coordinates":[0.91416973668784,50.9552532232851],"type":"Point"}
}