{
  "type": "Feature",
  "properties": {
    "iso:country": "GB",
    "wof:name": "TN29 9LJ",
    "wof:placetype": "postalcode"
  },
  "geometry": {"coordinates":[0.914249,50.955252],"type":"Point"}
}
