{
  "type": "Feature",
  "properties": {
    "date:inception_lower":"1980-01-01",
    "date:inception_upper":"1980-01-31",
    "iso:country":"GB",
    "wof:name":"TN29 9LJ",
    "wof:placetype":"postalcode"
},
  "geometry": {"coordinates":[0.914249,50.955252],"type":"Point"}
}