{
  "type": "Feature",
  "properties": {
    "date:inception_lower":"1999-06-01",
    "date:inception_upper":"1999-06-30",
    "iso:country":"GB",
    "wof:name":"CF11 9QB",
    "wof:placetype":"postalcode"
},
  "geometry": {"coordinates":[-3.20399,51.486716],"type":"Point"}
}