{
  "type": "Feature",
  "properties": {
    "iso:country":"GB",
    "wof:name":"CF11 9QB",
    "wof:placetype":"postalcode"
},
  "geometry": {"coordinates":[-3.20399012126674,51.48671593381118],"type":"Point"}
}