{
  "type": "Feature",
  "properties": {
    "iso:country":"GB",
    "wof:name":"LA19 5SA",
    "wof:placetype":"postalcode"
},
  "geometry": {"coordinates":[-3.37817935713841,54.28177363071099],"type":"Point"}
}