{
  "type": "Feature",
  "properties": {
    "date:inception_lower": "2003-08-01",
    "date:inception_upper": "2003-08-01",
    "iso:country": "GB",
    "wof:name": "LA19 5SA",
    "wof:placetype": "postalcode"
  },
  "geometry": {"coordinates":[-3.378179,54.281774],"type":"Point"}
}
