{
  "type": "Feature",
  "properties": {
    "iso:country":"GB",
    "wof:name":"EH4 3RH",
    "wof:placetype":"postalcode"
},
  "geometry": {"coordinates":[-3.25919002538103,55.95878510796061],"type":"Point"}
}