{
  "type": "Feature",
  "properties": {
    "iso:country": "GB",
    "wof:name": "NG12 1EW",
    "wof:placetype": "postalcode"
  },
  "geometry": {"coordinates":[-1.015328,52.969846],"type":"Point"}
}
