{
  "type": "Feature",
  "properties": {
    "date:inception_lower": "1997-06-01",
    "date:inception_upper": "1997-06-01",
    "iso:country": "GB",
    "wof:name": "NG12 1EW",
    "wof:placetype": "postalcode"
  },
  "geometry": {"coordinates":[-1.015328,52.969846],"type":"Point"}
}
