{
  "type": "Feature",
  "properties": {
    "iso:country":"GB",
    "wof:name":"NG12 1EW",
    "wof:placetype":"postalcode"
},
  "geometry": {"coordinates":[-1.01532836598755,52.96984594836664],"type":"Point"}
}