{
  "type": "Feature",
  "properties": {
    "iso:country": "GB",
    "wof:name": "PL13 2JG",
    "wof:placetype": "postalcode"
  },
  "geometry": {"coordinates":[-4.510268,50.340834],"type":"Point"}
}
