{
  "type": "Feature",
  "properties": {
    "iso:country": "GB",
    "wof:name": "SW16 3HD",
    "wof:placetype": "postalcode"
  },
  "geometry": {"coordinates":[-0.128131,51.423603],"type":"Point"}
}
