{
  "type": "Feature",
  "properties": {
    "date:inception_lower": "1980-01-01",
    "date:inception_upper": "1980-01-01",
    "iso:country": "GB",
    "wof:name": "B63 1BT",
    "wof:placetype": "postalcode"
  },
  "geometry": {"coordinates":[-2.075577,52.439668],"type":"Point"}
}
