{
  "type": "Feature",
  "properties": {
    "iso:country":"GB",
    "wof:name":"B63 1BT",
    "wof:placetype":"postalcode"
},
  "geometry": {"coordinates":[-2.07558343303807,52.4396448006823],"type":"Point"}
}