{
  "type": "Feature",
  "properties": {
    "iso:country":"GB",
    "wof:name":"TS9 5AH",
    "wof:placetype":"postalcode"
},
  "geometry": {"coordinates":[-1.18613977862343,54.4686499685678],"type":"Point"}
}