{
  "type": "Feature",
  "properties": {
    "date:inception_lower": "1980-01-01",
    "date:inception_upper": "1980-01-01",
    "iso:country": "GB",
    "wof:name": "TS9 5AH",
    "wof:placetype": "postalcode"
  },
  "geometry": {"coordinates":[-1.18614,54.46865],"type":"Point"}
}
