{
  "type": "Feature",
  "properties": {
    "iso:country":"GB",
    "wof:name":"RG26 3US",
    "wof:placetype":"postalcode"
},
  "geometry": {"coordinates":[-1.14238567919958,51.34492494115185],"type":"Point"}
}