{
  "type": "Feature",
  "properties": {
    "date:inception_lower":"2007-01-01",
    "date:inception_upper":"2007-01-31",
    "iso:country":"GB",
    "wof:name":"DT2 8GZ",
    "wof:placetype":"postalcode"
},
  "geometry": {"coordinates":[-2.34714,50.749458],"type":"Point"}
}