{
  "type": "Feature",
  "properties": {
    "iso:country":"GB",
    "wof:name":"DD10 0DX",
    "wof:placetype":"postalcode"
},
  "geometry": {"coordinates":[-2.43183800749434,56.77390624447416],"type":"Point"}
}