{
  "type": "Feature",
  "properties": {
    "date:inception_lower": "1980-01-01",
    "date:inception_upper": "1980-01-01",
    "iso:country": "GB",
    "wof:name": "FK15 0BD",
    "wof:placetype": "postalcode"
  },
  "geometry": {"coordinates":[-3.959778,56.193096],"type":"Point"}
}
