{
  "type": "Feature",
  "properties": {
    "iso:country":"GB",
    "wof:name":"OX26 3ZB",
    "wof:placetype":"postalcode"
},
  "geometry": {"coordinates":[-1.15720591531999,51.91251220031279],"type":"Point"}
}