{
  "type": "Feature",
  "properties": {
    "iso:country": "GB",
    "wof:name": "TS5 4RD",
    "wof:placetype": "postalcode"
  },
  "geometry": {"coordinates":[-1.269121,54.549893],"type":"Point"}
}
