{
  "type": "Feature",
  "properties": {
    "iso:country": "GB",
    "wof:name": "S75 1PJ",
    "wof:placetype": "postalcode"
  },
  "geometry": {"coordinates":[-1.536029,53.557499],"type":"Point"}
}
