{
  "type": "Feature",
  "properties": {
    "iso:country":"GB",
    "wof:name":"S75 1PJ",
    "wof:placetype":"postalcode"
},
  "geometry": {"coordinates":[-1.53602875644329,53.55749906317649],"type":"Point"}
}