{
  "type": "Feature",
  "properties": {
    "date:inception_lower":"1999-06-01",
    "date:inception_upper":"1999-06-30",
    "iso:country":"GB",
    "wof:name":"NP11 7GE",
    "wof:placetype":"postalcode"
},
  "geometry": {"coordinates":[-3.126124,51.626035],"type":"Point"}
}