{
  "type": "Feature",
  "properties": {
    "iso:country":"GB",
    "wof:name":"NP11 7GE",
    "wof:placetype":"postalcode"
},
  "geometry": {"coordinates":[-3.12612369517267,51.62603486208211],"type":"Point"}
}