{
  "type": "Feature",
  "properties": {
    "iso:country":"GB",
    "wof:name":"SL6 9QR",
    "wof:placetype":"postalcode"
},
  "geometry": {"coordinates":[-0.70616607582979,51.55804199767856],"type":"Point"}
}