{
  "type": "Feature",
  "properties": {
    "iso:country":"GB",
    "wof:name":"EN2 7QE",
    "wof:placetype":"postalcode"
},
  "geometry": {"coordinates":[-0.10509796829564,51.6587282259109],"type":"Point"}
}