{
  "type": "Feature",
  "properties": {
    "iso:country": "GB",
    "wof:name": "BA20 1TZ",
    "wof:placetype": "postalcode"
  },
  "geometry": {"coordinates":[-2.637653,50.94132],"type":"Point"}
}
