{
  "type": "Feature",
  "properties": {
    "iso:country":"GB",
    "wof:name":"SA41 3QW",
    "wof:placetype":"postalcode"
},
  "geometry": {"coordinates":[-4.65062446311166,51.95282449816042],"type":"Point"}
}