{
  "type": "Feature",
  "properties": {
    "iso:country":"GB",
    "wof:name":"MK42 5TP",
    "wof:placetype":"postalcode"
},
  "geometry": {"coordinates":[-0.47028130746741,52.13275843520889],"type":"Point"}
}