{
  "type": "Feature",
  "properties": {
    "date:inception_lower": "1980-01-01",
    "date:inception_upper": "1980-01-01",
    "iso:country": "GB",
    "wof:name": "CW3 0AZ",
    "wof:placetype": "postalcode"
  },
  "geometry": {"coordinates":[-2.502801,52.989452],"type":"Point"}
}
