{
  "type": "Feature",
  "properties": {
    "iso:country":"GB",
    "wof:name":"W13 0AL",
    "wof:placetype":"postalcode"
},
  "geometry": {"coordinates":[-0.332393164116,51.52862393540287],"type":"Point"}
}