{
  "type": "Feature",
  "properties": {
    "iso:country": "GB",
    "wof:name": "GL51 7AQ",
    "wof:placetype": "postalcode"
  },
  "geometry": {"coordinates":[-2.103746,51.89679],"type":"Point"}
}
