{
  "type": "Feature",
  "properties": {
    "date:inception_lower": "2021-01-01",
    "date:inception_upper": "2021-01-01",
    "iso:country": "GB",
    "wof:name": "CO5 9GF",
    "wof:placetype": "postalcode"
  },
  "geometry": {"coordinates":[0.719086,51.844661],"type":"Point"}
}
