{
  "type": "Feature",
  "properties": {
    "iso:country":"GB",
    "wof:name":"TW9 3DN",
    "wof:placetype":"postalcode"
},
  "geometry": {"coordinates":[-0.30497356081131,51.46374681040769],"type":"Point"}
}