{
  "type": "Feature",
  "properties": {
    "date:inception_lower":"1980-01-01",
    "date:inception_upper":"1980-01-31",
    "iso:country":"GB",
    "wof:name":"BS14 0PA",
    "wof:placetype":"postalcode"
},
  "geometry": {"coordinates":[-2.558937,51.412511],"type":"Point"}
}