{
  "type": "Feature",
  "properties": {
    "date:inception_lower": "2014-12-01",
    "date:inception_upper": "2014-12-01",
    "iso:country": "GB",
    "wof:name": "KT15 1FF",
    "wof:placetype": "postalcode"
  },
  "geometry": {"coordinates":[-0.507158,51.357545],"type":"Point"}
}
