{
  "type": "Feature",
  "properties": {
    "iso:country":"GB",
    "wof:name":"BL2 4AN",
    "wof:placetype":"postalcode"
},
  "geometry": {"coordinates":[-2.39508057528347,53.60842981839834],"type":"Point"}
}