{
  "type": "Feature",
  "properties": {
    "iso:country": "GB",
    "wof:name": "LE9 6QY",
    "wof:placetype": "postalcode"
  },
  "geometry": {"coordinates":[-1.236023,52.533398],"type":"Point"}
}
