{
  "type": "Feature",
  "properties": {
    "iso:country":"GB",
    "wof:name":"LE9 6QY",
    "wof:placetype":"postalcode"
},
  "geometry": {"coordinates":[-1.23602264784052,52.5333979276695],"type":"Point"}
}