{
  "type": "Feature",
  "properties": {
    "date:inception_lower": "1980-01-01",
    "date:inception_upper": "1980-01-01",
    "iso:country": "GB",
    "wof:name": "LE9 6QY",
    "wof:placetype": "postalcode"
  },
  "geometry": {"coordinates":[-1.236023,52.533398],"type":"Point"}
}
