{
  "type": "Feature",
  "properties": {
    "date:inception_lower": "1980-01-01",
    "date:inception_upper": "1980-01-01",
    "iso:country": "GB",
    "wof:name": "DG2 8EF",
    "wof:placetype": "postalcode"
  },
  "geometry": {"coordinates":[-3.684478,55.000911],"type":"Point"}
}
