{
  "type": "Feature",
  "properties": {
    "iso:country":"GB",
    "wof:name":"DE7 4LS",
    "wof:placetype":"postalcode"
},
  "geometry": {"coordinates":[-1.30548610091177,52.96226697621724],"type":"Point"}
}