{
  "type": "Feature",
  "properties": {
    "iso:country": "GB",
    "wof:name": "DE7 4LS",
    "wof:placetype": "postalcode"
  },
  "geometry": {"coordinates":[-1.305486,52.962267],"type":"Point"}
}
