{
  "type": "Feature",
  "properties": {
    "iso:country":"GB",
    "wof:name":"WS2 8EJ",
    "wof:placetype":"postalcode"
},
  "geometry": {"coordinates":[-1.98428086972913,52.5893680115291],"type":"Point"}
}