{
  "type": "Feature",
  "properties": {
    "date:inception_lower": "2005-09-01",
    "date:inception_upper": "2005-09-01",
    "iso:country": "GB",
    "wof:name": "IP32 7GW",
    "wof:placetype": "postalcode"
  },
  "geometry": {"coordinates":[0.753774,52.251322],"type":"Point"}
}
