{
  "type": "Feature",
  "properties": {
    "date:inception_lower": "1995-12-01",
    "date:inception_upper": "1995-12-01",
    "iso:country": "GB",
    "wof:name": "CM17 9QF",
    "wof:placetype": "postalcode"
  },
  "geometry": {"coordinates":[0.143414,51.762807],"type":"Point"}
}
