{
  "type": "Feature",
  "properties": {
    "iso:country": "GB",
    "wof:name": "CM17 9QF",
    "wof:placetype": "postalcode"
  },
  "geometry": {"coordinates":[0.143414,51.762807],"type":"Point"}
}
