{
  "type": "Feature",
  "properties": {
    "date:inception_lower": "2023-03-01",
    "date:inception_upper": "2023-03-01",
    "iso:country": "GB",
    "wof:name": "AB15 8RW",
    "wof:placetype": "postalcode"
  },
  "geometry": {"coordinates":[-2.21487,57.139671],"type":"Point"}
}
