{
  "type": "Feature",
  "properties": {
    "date:inception_lower":"2000-12-01",
    "date:inception_upper":"2000-12-31",
    "iso:country":"GB",
    "wof:name":"W1U 2SH",
    "wof:placetype":"postalcode"
},
  "geometry": {"coordinates":[-0.150627,51.516187],"type":"Point"}
}