{
  "type": "Feature",
  "properties": {
    "iso:country":"GB",
    "wof:name":"W1U 2SH",
    "wof:placetype":"postalcode"
},
  "geometry": {"coordinates":[-0.15062654843331,51.51618728463067],"type":"Point"}
}