{
  "type": "Feature",
  "properties": {
    "date:inception_lower":"1980-01-01",
    "date:inception_upper":"1980-01-31",
    "iso:country":"GB",
    "wof:name":"CH8 7DJ",
    "wof:placetype":"postalcode"
},
  "geometry": {"coordinates":[-3.247144,53.280034],"type":"Point"}
}