{
  "type": "Feature",
  "properties": {
    "iso:country":"GB",
    "wof:name":"CH8 7DJ",
    "wof:placetype":"postalcode"
},
  "geometry": {"coordinates":[-3.24714398794469,53.28003421154446],"type":"Point"}
}