{
  "type": "Feature",
  "properties": {
    "iso:country": "GB",
    "wof:name": "CH8 7DJ",
    "wof:placetype": "postalcode"
  },
  "geometry": {"coordinates":[-3.247144,53.280034],"type":"Point"}
}
