{
  "type": "Feature",
  "properties": {
    "date:inception_lower": "2023-04-01",
    "date:inception_upper": "2023-04-01",
    "iso:country": "GB",
    "wof:name": "WS6 7FD",
    "wof:placetype": "postalcode"
  },
  "geometry": {"coordinates":[-2.043391,52.663453],"type":"Point"}
}
