{
  "type": "Feature",
  "properties": {
    "date:inception_lower": "1992-08-01",
    "date:inception_upper": "1992-08-01",
    "iso:country": "GB",
    "wof:name": "DE65 5PJ",
    "wof:placetype": "postalcode"
  },
  "geometry": {"coordinates":[-1.714161,52.886032],"type":"Point"}
}
