{
  "type": "Feature",
  "properties": {
    "iso:country":"GB",
    "wof:name":"CH44 8BG",
    "wof:placetype":"postalcode"
},
  "geometry": {"coordinates":[-3.02622386562897,53.4197717778022],"type":"Point"}
}