{
  "type": "Feature",
  "properties": {
    "date:inception_lower": "1992-01-01",
    "date:inception_upper": "1992-01-01",
    "iso:country": "GB",
    "wof:name": "B60 2DA",
    "wof:placetype": "postalcode"
  },
  "geometry": {"coordinates":[-2.06044,52.332981],"type":"Point"}
}
