{
  "type": "Feature",
  "properties": {
    "iso:country":"GB",
    "wof:name":"B65 0RL",
    "wof:placetype":"postalcode"
},
  "geometry": {"coordinates":[-2.02972914471766,52.4811810831116],"type":"Point"}
}