{
  "type": "Feature",
  "properties": {
    "date:inception_lower":"1980-01-01",
    "date:inception_upper":"1980-01-31",
    "iso:country":"GB",
    "wof:name":"B65 0RL",
    "wof:placetype":"postalcode"
},
  "geometry": {"coordinates":[-2.029729,52.481181],"type":"Point"}
}