{
  "type": "Feature",
  "properties": {
    "iso:country":"GB",
    "wof:name":"BN2 8FX",
    "wof:placetype":"postalcode"
},
  "geometry": {"coordinates":[-0.03835021772041,50.80816142587451],"type":"Point"}
}