{
  "type": "Feature",
  "properties": {
    "iso:country":"GB",
    "wof:name":"SA1 2NZ",
    "wof:placetype":"postalcode"
},
  "geometry": {"coordinates":[-3.94058015887729,51.64279427986975],"type":"Point"}
}