{
  "type": "Feature",
  "properties": {
    "date:inception_lower":"1980-01-01",
    "date:inception_upper":"1980-01-31",
    "iso:country":"GB",
    "wof:name":"B66 4AG",
    "wof:placetype":"postalcode"
},
  "geometry": {"coordinates":[-1.967316,52.47602],"type":"Point"}
}