{
  "type": "Feature",
  "properties": {
    "iso:country":"GB",
    "wof:name":"PE15 8LT",
    "wof:placetype":"postalcode"
},
  "geometry": {"coordinates":[0.09012261140605,52.55496590249976],"type":"Point"}
}