{
  "type": "Feature",
  "properties": {
    "iso:country":"GB",
    "wof:name":"WS12 3EX",
    "wof:placetype":"postalcode"
},
  "geometry": {"coordinates":[-1.98526652538423,52.68899215300501],"type":"Point"}
}