{
  "type": "Feature",
  "properties": {
    "iso:country":"GB",
    "wof:name":"PE21 0RN",
    "wof:placetype":"postalcode"
},
  "geometry": {"coordinates":[0.02297867014156,52.9666356698981],"type":"Point"}
}