{
  "type": "Feature",
  "properties": {
    "date:inception_lower": "1980-01-01",
    "date:inception_upper": "1980-01-01",
    "iso:country": "GB",
    "wof:name": "CV10 7DG",
    "wof:placetype": "postalcode"
  },
  "geometry": {"coordinates":[-1.492599,52.515231],"type":"Point"}
}
