{
  "type": "Feature",
  "properties": {
    "iso:country":"GB",
    "wof:name":"CV10 7DG",
    "wof:placetype":"postalcode"
},
  "geometry": {"coordinates":[-1.49259860777897,52.51523101743123],"type":"Point"}
}