{
  "type": "Feature",
  "properties": {
    "iso:country":"GB",
    "wof:name":"DN16 3FH",
    "wof:placetype":"postalcode"
},
  "geometry": {"coordinates":[-0.62974570345994,53.5570326536708],"type":"Point"}
}