{
  "type": "Feature",
  "properties": {
    "date:inception_lower": "2007-04-01",
    "date:inception_upper": "2007-04-01",
    "iso:country": "GB",
    "wof:name": "DN16 3FH",
    "wof:placetype": "postalcode"
  },
  "geometry": {"coordinates":[-0.629746,53.557033],"type":"Point"}
}
