{
  "type": "Feature",
  "properties": {
    "iso:country": "GB",
    "wof:name": "DN16 3FH",
    "wof:placetype": "postalcode"
  },
  "geometry": {"coordinates":[-0.629746,53.557033],"type":"Point"}
}
