{
  "type": "Feature",
  "properties": {
    "iso:country":"GB",
    "wof:name":"B68 9HQ",
    "wof:placetype":"postalcode"
},
  "geometry": {"coordinates":[-1.99312524150116,52.47326454343865],"type":"Point"}
}