{
  "type": "Feature",
  "properties": {
    "iso:country":"GB",
    "wof:name":"DT6 6EB",
    "wof:placetype":"postalcode"
},
  "geometry": {"coordinates":[-2.85182550101998,50.74599925841729],"type":"Point"}
}