{
  "type": "Feature",
  "properties": {
    "iso:country":"GB",
    "wof:name":"KW15 1GW",
    "wof:placetype":"postalcode"
},
  "geometry": {"coordinates":[-2.96693890055772,58.97922301207947],"type":"Point"}
}