{
  "type": "Feature",
  "properties": {
    "date:inception_lower": "2011-06-01",
    "date:inception_upper": "2011-06-01",
    "iso:country": "GB",
    "wof:name": "KW15 1GW",
    "wof:placetype": "postalcode"
  },
  "geometry": {"coordinates":[-2.966835,58.979233],"type":"Point"}
}
