{
  "type": "Feature",
  "properties": {
    "iso:country":"GB",
    "wof:name":"OX2 0AE",
    "wof:placetype":"postalcode"
},
  "geometry": {"coordinates":[-1.2718314398336,51.75364853752438],"type":"Point"}
}