{
  "type": "Feature",
  "properties": {
    "date:inception_lower": "2000-12-01",
    "date:inception_upper": "2000-12-01",
    "iso:country": "GB",
    "wof:name": "B93 8LW",
    "wof:placetype": "postalcode"
  },
  "geometry": {"coordinates":[-1.756485,52.379896],"type":"Point"}
}
