{
  "type": "Feature",
  "properties": {
    "iso:country":"GB",
    "wof:name":"B93 8LW",
    "wof:placetype":"postalcode"
},
  "geometry": {"coordinates":[-1.75648524805473,52.37989561227015],"type":"Point"}
}