{
  "type": "Feature",
  "properties": {
    "iso:country":"GB",
    "wof:name":"CO5 7EZ",
    "wof:placetype":"postalcode"
},
  "geometry": {"coordinates":[0.94879678212447,51.85443779150688],"type":"Point"}
}