{
  "type": "Feature",
  "properties": {
    "iso:country": "GB",
    "wof:name": "SA10 7NT",
    "wof:placetype": "postalcode"
  },
  "geometry": {"coordinates":[-3.833449,51.660945],"type":"Point"}
}
