{
  "type": "Feature",
  "properties": {
    "date:inception_lower": "2007-04-01",
    "date:inception_upper": "2007-04-01",
    "iso:country": "GB",
    "wof:name": "SA10 7NT",
    "wof:placetype": "postalcode"
  },
  "geometry": {"coordinates":[-3.833449,51.660945],"type":"Point"}
}
