{
  "type": "Feature",
  "properties": {
    "iso:country":"GB",
    "wof:name":"GU29 9DF",
    "wof:placetype":"postalcode"
},
  "geometry": {"coordinates":[-0.73850227336834,50.98598102007193],"type":"Point"}
}