{
  "type": "Feature",
  "properties": {
    "iso:country": "GB",
    "wof:name": "GU29 9DF",
    "wof:placetype": "postalcode"
  },
  "geometry": {"coordinates":[-0.738502,50.985981],"type":"Point"}
}
