{
  "type": "Feature",
  "properties": {
    "iso:country":"GB",
    "wof:name":"G41 5RH",
    "wof:placetype":"postalcode"
},
  "geometry": {"coordinates":[-4.28038374136497,55.84149479496958],"type":"Point"}
}