{
  "type": "Feature",
  "properties": {
    "iso:country":"GB",
    "wof:name":"OX20 1UH",
    "wof:placetype":"postalcode"
},
  "geometry": {"coordinates":[-1.35464024407088,51.84602157023422],"type":"Point"}
}