{
  "type": "Feature",
  "properties": {
    "iso:country": "GB",
    "wof:name": "OX20 1UH",
    "wof:placetype": "postalcode"
  },
  "geometry": {"coordinates":[-1.35464,51.846022],"type":"Point"}
}
