{
  "type": "Feature",
  "properties": {
    "iso:country": "GB",
    "wof:name": "EH21 8BX",
    "wof:placetype": "postalcode"
  },
  "geometry": {"coordinates":[-3.020064,55.9375],"type":"Point"}
}
