{
  "type": "Feature",
  "properties": {
    "iso:country":"GB",
    "wof:name":"CO15 5RS",
    "wof:placetype":"postalcode"
},
  "geometry": {"coordinates":[1.19492357031775,51.81000484274406],"type":"Point"}
}