{
  "type": "Feature",
  "properties": {
    "iso:country": "GB",
    "wof:name": "KT24 6PG",
    "wof:placetype": "postalcode"
  },
  "geometry": {"coordinates":[-0.442605,51.284486],"type":"Point"}
}
