{
  "type": "Feature",
  "properties": {
    "iso:country":"GB",
    "wof:name":"SN15 3BL",
    "wof:placetype":"postalcode"
},
  "geometry": {"coordinates":[-2.11004974521077,51.45492054866867],"type":"Point"}
}