{
  "type": "Feature",
  "properties": {
    "date:inception_lower": "1993-01-01",
    "date:inception_upper": "1993-01-01",
    "iso:country": "GB",
    "wof:name": "SN15 3BL",
    "wof:placetype": "postalcode"
  },
  "geometry": {"coordinates":[-2.11005,51.454921],"type":"Point"}
}
