{
  "type": "Feature",
  "properties": {
    "iso:country": "GB",
    "wof:name": "NN13 7FG",
    "wof:placetype": "postalcode"
  },
  "geometry": {"coordinates":[-1.136389,52.038821],"type":"Point"}
}
