{
  "type": "Feature",
  "properties": {
    "iso:country":"GB",
    "wof:name":"PA3 3ES",
    "wof:placetype":"postalcode"
},
  "geometry": {"coordinates":[-4.49943477529587,55.84562332652494],"type":"Point"}
}