{
  "type": "Feature",
  "properties": {
    "iso:country":"GB",
    "wof:name":"PE38 9LJ",
    "wof:placetype":"postalcode"
},
  "geometry": {"coordinates":[0.39231212308308,52.6027988044797],"type":"Point"}
}