{
  "type": "Feature",
  "properties": {
    "iso:country":"GB",
    "wof:name":"SG12 9RS",
    "wof:placetype":"postalcode"
},
  "geometry": {"coordinates":[-0.02245999496121,51.78766492824172],"type":"Point"}
}