{
  "type": "Feature",
  "properties": {
    "date:inception_lower": "2015-08-01",
    "date:inception_upper": "2015-08-01",
    "iso:country": "GB",
    "wof:name": "WA8 9DZ",
    "wof:placetype": "postalcode"
  },
  "geometry": {"coordinates":[-2.746711,53.380551],"type":"Point"}
}
