{
  "type": "Feature",
  "properties": {
    "iso:country": "GB",
    "wof:name": "WA8 9DZ",
    "wof:placetype": "postalcode"
  },
  "geometry": {"coordinates":[-2.746711,53.380551],"type":"Point"}
}
