{
  "type": "Feature",
  "properties": {
    "date:inception_lower": "2018-04-01",
    "date:inception_upper": "2018-04-01",
    "iso:country": "GB",
    "wof:name": "LS10 3TT",
    "wof:placetype": "postalcode"
  },
  "geometry": {"coordinates":[-1.531268,53.757656],"type":"Point"}
}
