{
  "type": "Feature",
  "properties": {
    "date:inception_lower":"1980-01-01",
    "date:inception_upper":"1980-01-31",
    "iso:country":"GB",
    "wof:name":"BN20 8QR",
    "wof:placetype":"postalcode"
},
  "geometry": {"coordinates":[0.254642,50.780911],"type":"Point"}
}