{
  "type": "Feature",
  "properties": {
    "iso:country":"GB",
    "wof:name":"SA12 8EE",
    "wof:placetype":"postalcode"
},
  "geometry": {"coordinates":[-3.80236203557675,51.61247287745317],"type":"Point"}
}