{
  "type": "Feature",
  "properties": {
    "iso:country":"GB",
    "wof:name":"GU22 7XG",
    "wof:placetype":"postalcode"
},
  "geometry": {"coordinates":[-0.56164552072723,51.3131748308918],"type":"Point"}
}