{
  "type": "Feature",
  "properties": {
    "date:inception_lower":"2008-04-01",
    "date:inception_upper":"2008-04-30",
    "iso:country":"GB",
    "wof:name":"WR5 3FJ",
    "wof:placetype":"postalcode"
},
  "geometry": {"coordinates":[-2.216799,52.168342],"type":"Point"}
}