{
  "type": "Feature",
  "properties": {
    "iso:country":"GB",
    "wof:name":"WR5 3FJ",
    "wof:placetype":"postalcode"
},
  "geometry": {"coordinates":[-2.21679893065356,52.16834216397005],"type":"Point"}
}