{
  "type": "Feature",
  "properties": {
    "iso:country":"GB",
    "wof:name":"BB9 7AW",
    "wof:placetype":"postalcode"
},
  "geometry": {"coordinates":[-2.22261338286405,53.83411681414826],"type":"Point"}
}