{
  "type": "Feature",
  "properties": {
    "iso:country":"GB",
    "wof:name":"SG4 8QE",
    "wof:placetype":"postalcode"
},
  "geometry": {"coordinates":[-0.30317622418028,51.85154218252194],"type":"Point"}
}