{
  "type": "Feature",
  "properties": {
    "iso:country":"GB",
    "wof:name":"WD18 6PH",
    "wof:placetype":"postalcode"
},
  "geometry": {"coordinates":[-0.4226680305876,51.64620324198949],"type":"Point"}
}