{
  "type": "Feature",
  "properties": {
    "date:inception_lower": "2000-10-01",
    "date:inception_upper": "2000-10-01",
    "iso:country": "GB",
    "wof:name": "WD18 6PH",
    "wof:placetype": "postalcode"
  },
  "geometry": {"coordinates":[-0.422668,51.646203],"type":"Point"}
}
