{
  "type": "Feature",
  "properties": {
    "iso:country": "GB",
    "wof:name": "GU7 3AG",
    "wof:placetype": "postalcode"
  },
  "geometry": {"coordinates":[-0.609117,51.191847],"type":"Point"}
}
