{
  "type": "Feature",
  "properties": {
    "iso:country":"GB",
    "wof:name":"CB24 5HX",
    "wof:placetype":"postalcode"
},
  "geometry": {"coordinates":[0.06295771134534,52.31482046345945],"type":"Point"}
}