{
  "type": "Feature",
  "properties": {
    "iso:country":"GB",
    "wof:name":"SN16 0HR",
    "wof:placetype":"postalcode"
},
  "geometry": {"coordinates":[-2.11079625563436,51.55490487903857],"type":"Point"}
}