{
  "type": "Feature",
  "properties": {
    "date:inception_lower": "2005-04-01",
    "date:inception_upper": "2005-04-01",
    "iso:country": "GB",
    "wof:name": "SN16 0HR",
    "wof:placetype": "postalcode"
  },
  "geometry": {"coordinates":[-2.110633,51.554968],"type":"Point"}
}
