{
  "type": "Feature",
  "properties": {
    "iso:country": "GB",
    "wof:name": "SN16 0HR",
    "wof:placetype": "postalcode"
  },
  "geometry": {"coordinates":[-2.110796,51.554905],"type":"Point"}
}
