{
  "type": "Feature",
  "properties": {
    "iso:country":"GB",
    "wof:name":"BS1 3BH",
    "wof:placetype":"postalcode"
},
  "geometry": {"coordinates":[-2.58527256508297,51.45814112442391],"type":"Point"}
}