{
  "type": "Feature",
  "properties": {
    "iso:country":"GB",
    "wof:name":"DL15 9DX",
    "wof:placetype":"postalcode"
},
  "geometry": {"coordinates":[-1.74349540899565,54.71681537905002],"type":"Point"}
}