{
  "type": "Feature",
  "properties": {
    "iso:country": "GB",
    "wof:name": "SK13 0BR",
    "wof:placetype": "postalcode"
  },
  "geometry": {"coordinates":[-1.989784,53.444928],"type":"Point"}
}
