{
  "type": "Feature",
  "properties": {
    "iso:country":"GB",
    "wof:name":"SK13 0BR",
    "wof:placetype":"postalcode"
},
  "geometry": {"coordinates":[-1.98978356706302,53.44492786160931],"type":"Point"}
}