{
  "type": "Feature",
  "properties": {
    "iso:country":"GB",
    "wof:name":"L13 0DE",
    "wof:placetype":"postalcode"
},
  "geometry": {"coordinates":[-2.92427516276243,53.42935066735492],"type":"Point"}
}