{
  "type": "Feature",
  "properties": {
    "iso:country":"GB",
    "wof:name":"NE7 7DN",
    "wof:placetype":"postalcode"
},
  "geometry": {"coordinates":[-1.59372177765336,55.00275920585941],"type":"Point"}
}