{
  "type": "Feature",
  "properties": {
    "date:inception_lower":"2000-10-01",
    "date:inception_upper":"2000-10-31",
    "iso:country":"GB",
    "wof:name":"WD25 9QU",
    "wof:placetype":"postalcode"
},
  "geometry": {"coordinates":[-0.380888,51.690244],"type":"Point"}
}