{
  "type": "Feature",
  "properties": {
    "iso:country":"GB",
    "wof:name":"WD25 9QU",
    "wof:placetype":"postalcode"
},
  "geometry": {"coordinates":[-0.38088836657927,51.69024408312095],"type":"Point"}
}