{
  "type": "Feature",
  "properties": {
    "iso:country": "GB",
    "wof:name": "SN25 2GN",
    "wof:placetype": "postalcode"
  },
  "geometry": {"coordinates":[-1.815561,51.60146],"type":"Point"}
}
