{
  "type": "Feature",
  "properties": {
    "date:inception_lower":"2006-07-01",
    "date:inception_upper":"2006-07-31",
    "iso:country":"GB",
    "wof:name":"SN25 2GN",
    "wof:placetype":"postalcode"
},
  "geometry": {"coordinates":[-1.815561,51.60146],"type":"Point"}
}