{
  "type": "Feature",
  "properties": {
    "iso:country": "GB",
    "wof:name": "SA4 8RW",
    "wof:placetype": "postalcode"
  },
  "geometry": {"coordinates":[-4.036765,51.715587],"type":"Point"}
}
