{
  "type": "Feature",
  "properties": {
    "iso:country": "GB",
    "wof:name": "TS14 6LN",
    "wof:placetype": "postalcode"
  },
  "geometry": {"coordinates":[-1.068218,54.535581],"type":"Point"}
}
