{
  "type": "Feature",
  "properties": {
    "date:inception_lower": "1980-01-01",
    "date:inception_upper": "1980-01-01",
    "iso:country": "GB",
    "wof:name": "TS14 6LN",
    "wof:placetype": "postalcode"
  },
  "geometry": {"coordinates":[-1.068218,54.535581],"type":"Point"}
}
