{
  "type": "Feature",
  "properties": {
    "iso:country": "GB",
    "wof:name": "LS9 8AR",
    "wof:placetype": "postalcode"
  },
  "geometry": {"coordinates":[-1.530674,53.792835],"type":"Point"}
}
