{
  "type": "Feature",
  "properties": {
    "date:inception_lower": "2006-02-01",
    "date:inception_upper": "2006-02-01",
    "iso:country": "GB",
    "wof:name": "LS9 8AR",
    "wof:placetype": "postalcode"
  },
  "geometry": {"coordinates":[-1.530674,53.792835],"type":"Point"}
}
