{
  "type": "Feature",
  "properties": {
    "date:inception_lower": "1980-01-01",
    "date:inception_upper": "1980-01-01",
    "iso:country": "GB",
    "wof:name": "KA8 9HS",
    "wof:placetype": "postalcode"
  },
  "geometry": {"coordinates":[-4.616738,55.476441],"type":"Point"}
}
