{
  "type": "Feature",
  "properties": {
    "iso:country":"GB",
    "wof:name":"KA8 9HS",
    "wof:placetype":"postalcode"
},
  "geometry": {"coordinates":[-4.61666146469705,55.47664818770443],"type":"Point"}
}