{
  "type": "Feature",
  "properties": {
    "date:inception_lower":"1990-02-01",
    "date:inception_upper":"1990-02-28",
    "iso:country":"GB",
    "wof:name":"WF6 1TF",
    "wof:placetype":"postalcode"
},
  "geometry": {"coordinates":[-1.396415,53.700411],"type":"Point"}
}