{
  "type": "Feature",
  "properties": {
    "iso:country":"GB",
    "wof:name":"WF6 1TF",
    "wof:placetype":"postalcode"
},
  "geometry": {"coordinates":[-1.39888612961535,53.70104403944786],"type":"Point"}
}