{
  "type": "Feature",
  "properties": {
    "iso:country":"GB",
    "wof:name":"HU9 5UR",
    "wof:placetype":"postalcode"
},
  "geometry": {"coordinates":[-0.2802164045557,53.7571246528715],"type":"Point"}
}