{
  "type": "Feature",
  "properties": {
    "iso:country": "GB",
    "wof:name": "CA8 1LW",
    "wof:placetype": "postalcode"
  },
  "geometry": {"coordinates":[-2.712842,54.902442],"type":"Point"}
}
