{
  "type": "Feature",
  "properties": {
    "iso:country":"GB",
    "wof:name":"CA8 1LW",
    "wof:placetype":"postalcode"
},
  "geometry": {"coordinates":[-2.7128425363118,54.90244196865336],"type":"Point"}
}