{
  "type": "Feature",
  "properties": {
    "iso:country":"GB",
    "wof:name":"W1W 7AS",
    "wof:placetype":"postalcode"
},
  "geometry": {"coordinates":[-0.1416537920908,51.51886011739649],"type":"Point"}
}