{
  "type": "Feature",
  "properties": {
    "iso:country":"GB",
    "wof:name":"ST10 1LT",
    "wof:placetype":"postalcode"
},
  "geometry": {"coordinates":[-1.98698728670707,52.97733694135489],"type":"Point"}
}