{
  "type": "Feature",
  "properties": {
    "date:inception_lower":"2017-02-01",
    "date:inception_upper":"2017-02-28",
    "iso:country":"GB",
    "wof:name":"W1J 0PZ",
    "wof:placetype":"postalcode"
},
  "geometry": {"coordinates":[-0.140784,51.509523],"type":"Point"}
}