{
  "type": "Feature",
  "properties": {
    "iso:country":"GB",
    "wof:name":"KY15 5HZ",
    "wof:placetype":"postalcode"
},
  "geometry": {"coordinates":[-3.01038058354216,56.31666704304757],"type":"Point"}
}