{
  "type": "Feature",
  "properties": {
    "date:inception_lower": "2011-05-01",
    "date:inception_upper": "2011-05-01",
    "iso:country": "GB",
    "wof:name": "PE6 8GJ",
    "wof:placetype": "postalcode"
  },
  "geometry": {"coordinates":[-0.313855,52.682218],"type":"Point"}
}
