{
  "type": "Feature",
  "properties": {
    "iso:country": "GB",
    "wof:name": "TQ9 5AZ",
    "wof:placetype": "postalcode"
  },
  "geometry": {"coordinates":[-3.678171,50.431033],"type":"Point"}
}
