{
  "type": "Feature",
  "properties": {
    "iso:country":"GB",
    "wof:name":"TQ9 5AZ",
    "wof:placetype":"postalcode"
},
  "geometry": {"coordinates":[-3.67817131373097,50.43103296211289],"type":"Point"}
}