{
  "type": "Feature",
  "properties": {
    "iso:country":"GB",
    "wof:name":"CM9 6QR",
    "wof:placetype":"postalcode"
},
  "geometry": {"coordinates":[0.62337926222964,51.75081330373955],"type":"Point"}
}