{
  "type": "Feature",
  "properties": {
    "iso:country": "GB",
    "wof:name": "CM9 6QR",
    "wof:placetype": "postalcode"
  },
  "geometry": {"coordinates":[0.623379,51.750813],"type":"Point"}
}
