{
  "type": "Feature",
  "properties": {
    "iso:country":"GB",
    "wof:name":"SL7 3PL",
    "wof:placetype":"postalcode"
},
  "geometry": {"coordinates":[-0.78431496268265,51.59077144918243],"type":"Point"}
}