{
  "type": "Feature",
  "properties": {
    "iso:country": "GB",
    "wof:name": "SL7 3PL",
    "wof:placetype": "postalcode"
  },
  "geometry": {"coordinates":[-0.784315,51.590771],"type":"Point"}
}
