{
  "type": "Feature",
  "properties": {
    "date:inception_lower": "1980-01-01",
    "date:inception_upper": "1980-01-01",
    "iso:country": "GB",
    "wof:name": "G76 7RQ",
    "wof:placetype": "postalcode"
  },
  "geometry": {"coordinates":[-4.28989,55.789639],"type":"Point"}
}
