{
  "type": "Feature",
  "properties": {
    "iso:country": "GB",
    "wof:name": "HU17 8GL",
    "wof:placetype": "postalcode"
  },
  "geometry": {"coordinates":[-0.480033,53.842667],"type":"Point"}
}
