{
  "type": "Feature",
  "properties": {
    "iso:country": "GB",
    "wof:name": "GL19 4HJ",
    "wof:placetype": "postalcode"
  },
  "geometry": {"coordinates":[-2.227336,51.949347],"type":"Point"}
}
