{
  "type": "Feature",
  "properties": {
    "iso:country":"GB",
    "wof:name":"GL19 4HJ",
    "wof:placetype":"postalcode"
},
  "geometry": {"coordinates":[-2.22733617726356,51.94934674886811],"type":"Point"}
}