{
  "type": "Feature",
  "properties": {
    "iso:country":"GB",
    "wof:name":"SW11 3HE",
    "wof:placetype":"postalcode"
},
  "geometry": {"coordinates":[-0.17159150043557,51.47060926404626],"type":"Point"}
}