{
  "type": "Feature",
  "properties": {
    "iso:country":"GB",
    "wof:name":"SK22 4HX",
    "wof:placetype":"postalcode"
},
  "geometry": {"coordinates":[-1.98634348912083,53.37267761206058],"type":"Point"}
}