{
  "type": "Feature",
  "properties": {
    "iso:country": "GB",
    "wof:name": "LS14 5LZ",
    "wof:placetype": "postalcode"
  },
  "geometry": {"coordinates":[-1.445114,53.822032],"type":"Point"}
}
