{
  "type": "Feature",
  "properties": {
    "iso:country":"GB",
    "wof:name":"PA5 8HN",
    "wof:placetype":"postalcode"
},
  "geometry": {"coordinates":[-4.49835556415426,55.83752004565446],"type":"Point"}
}