{
  "type": "Feature",
  "properties": {
    "date:inception_lower": "2008-12-01",
    "date:inception_upper": "2008-12-01",
    "iso:country": "GB",
    "wof:name": "BS10 7ES",
    "wof:placetype": "postalcode"
  },
  "geometry": {"coordinates":[-2.652902,51.542503],"type":"Point"}
}
