{
  "type": "Feature",
  "properties": {
    "iso:country":"GB",
    "wof:name":"BS10 7ES",
    "wof:placetype":"postalcode"
},
  "geometry": {"coordinates":[-2.65290183710572,51.54250270453058],"type":"Point"}
}