{
  "type": "Feature",
  "properties": {
    "iso:country":"GB",
    "wof:name":"G71 8RB",
    "wof:placetype":"postalcode"
},
  "geometry": {"coordinates":[-4.06744256529276,55.80273187505501],"type":"Point"}
}