{
  "type": "Feature",
  "properties": {
    "iso:country": "GB",
    "wof:name": "OX1 4LL",
    "wof:placetype": "postalcode"
  },
  "geometry": {"coordinates":[-1.258356,51.74585],"type":"Point"}
}
