{
  "type": "Feature",
  "properties": {
    "iso:country":"GB",
    "wof:name":"OX1 4LL",
    "wof:placetype":"postalcode"
},
  "geometry": {"coordinates":[-1.25835584865489,51.7458498189972],"type":"Point"}
}