{
  "type": "Feature",
  "properties": {
    "iso:country": "GB",
    "wof:name": "NG32 2LQ",
    "wof:placetype": "postalcode"
  },
  "geometry": {"coordinates":[-0.728907,52.977696],"type":"Point"}
}
