{
  "type": "Feature",
  "properties": {
    "iso:country": "GB",
    "wof:name": "NP19 9BL",
    "wof:placetype": "postalcode"
  },
  "geometry": {"coordinates":[-2.954923,51.589842],"type":"Point"}
}
