{
  "type": "Feature",
  "properties": {
    "iso:country":"GB",
    "wof:name":"NP19 9BL",
    "wof:placetype":"postalcode"
},
  "geometry": {"coordinates":[-2.95492305042858,51.58984179059912],"type":"Point"}
}