{
  "type": "Feature",
  "properties": {
    "iso:country":"GB",
    "wof:name":"ST16 1AQ",
    "wof:placetype":"postalcode"
},
  "geometry": {"coordinates":[-2.13487081909413,52.80531279479266],"type":"Point"}
}