{
  "type": "Feature",
  "properties": {
    "iso:country": "GB",
    "wof:name": "ST16 1AQ",
    "wof:placetype": "postalcode"
  },
  "geometry": {"coordinates":[-2.134871,52.805313],"type":"Point"}
}
