{
  "type": "Feature",
  "properties": {
    "date:inception_lower": "1993-08-01",
    "date:inception_upper": "1993-08-01",
    "iso:country": "GB",
    "wof:name": "ST16 1AQ",
    "wof:placetype": "postalcode"
  },
  "geometry": {"coordinates":[-2.134871,52.805313],"type":"Point"}
}
