{
  "type": "Feature",
  "properties": {
    "iso:country": "GB",
    "wof:name": "DY4 9SJ",
    "wof:placetype": "postalcode"
  },
  "geometry": {"coordinates":[-2.06178,52.530083],"type":"Point"}
}
