{
  "type": "Feature",
  "properties": {
    "iso:country":"GB",
    "wof:name":"DY4 9SJ",
    "wof:placetype":"postalcode"
},
  "geometry": {"coordinates":[-2.06177956059459,52.53008277214203],"type":"Point"}
}