{
  "type": "Feature",
  "properties": {
    "date:inception_lower": "2024-08-01",
    "date:inception_upper": "2024-08-01",
    "iso:country": "GB",
    "wof:name": "G5 0EN",
    "wof:placetype": "postalcode"
  },
  "geometry": {"coordinates":[-4.252856,55.844936],"type":"Point"}
}
