{
  "type": "Feature",
  "properties": {
    "date:inception_lower": "1980-01-01",
    "date:inception_upper": "1980-01-01",
    "iso:country": "GB",
    "wof:name": "TN18 5BA",
    "wof:placetype": "postalcode"
  },
  "geometry": {"coordinates":[0.531559,51.053417],"type":"Point"}
}
