{
  "type": "Feature",
  "properties": {
    "iso:country":"GB",
    "wof:name":"TN18 5BA",
    "wof:placetype":"postalcode"
},
  "geometry": {"coordinates":[0.53155875120727,51.05341713220982],"type":"Point"}
}