{
  "type": "Feature",
  "properties": {
    "iso:country": "GB",
    "wof:name": "TN18 5BA",
    "wof:placetype": "postalcode"
  },
  "geometry": {"coordinates":[0.531559,51.053417],"type":"Point"}
}
