{
  "type": "Feature",
  "properties": {
    "iso:country":"GB",
    "wof:name":"DL15 0RQ",
    "wof:placetype":"postalcode"
},
  "geometry": {"coordinates":[-1.70373759375424,54.6959207803361],"type":"Point"}
}