{
  "type": "Feature",
  "properties": {
    "iso:country":"GB",
    "wof:name":"NR5 9NR",
    "wof:placetype":"postalcode"
},
  "geometry": {"coordinates":[1.20755631191418,52.64205149281726],"type":"Point"}
}