{
  "type": "Feature",
  "properties": {
    "date:inception_lower":"1980-01-01",
    "date:inception_upper":"1980-01-31",
    "iso:country":"GB",
    "wof:name":"NP8 1AS",
    "wof:placetype":"postalcode"
},
  "geometry": {"coordinates":[-3.1398,51.857749],"type":"Point"}
}