{
  "type": "Feature",
  "properties": {
    "iso:country":"GB",
    "wof:name":"NP8 1AS",
    "wof:placetype":"postalcode"
},
  "geometry": {"coordinates":[-3.13980031073867,51.85774879529075],"type":"Point"}
}