{
  "type": "Feature",
  "properties": {
    "date:inception_lower": "1980-01-01",
    "date:inception_upper": "1980-01-01",
    "iso:country": "GB",
    "wof:name": "S72 9AH",
    "wof:placetype": "postalcode"
  },
  "geometry": {"coordinates":[-1.390256,53.607441],"type":"Point"}
}
