{
  "type": "Feature",
  "properties": {
    "iso:country":"GB",
    "wof:name":"S72 9AH",
    "wof:placetype":"postalcode"
},
  "geometry": {"coordinates":[-1.39025573841945,53.60744099012888],"type":"Point"}
}