{
  "type": "Feature",
  "properties": {
    "iso:country":"GB",
    "wof:name":"EH21 8NT",
    "wof:placetype":"postalcode"
},
  "geometry": {"coordinates":[-3.03533081498734,55.9192854300974],"type":"Point"}
}