{
  "type": "Feature",
  "properties": {
    "iso:country":"GB",
    "wof:name":"SS4 1NU",
    "wof:placetype":"postalcode"
},
  "geometry": {"coordinates":[0.69696885228808,51.58159793563523],"type":"Point"}
}