{
  "type": "Feature",
  "properties": {
    "date:inception_lower": "1980-01-01",
    "date:inception_upper": "1980-01-01",
    "iso:country": "GB",
    "wof:name": "HP1 3LZ",
    "wof:placetype": "postalcode"
  },
  "geometry": {"coordinates":[-0.492681,51.7664],"type":"Point"}
}
