{
  "type": "Feature",
  "properties": {
    "iso:country":"GB",
    "wof:name":"HP1 3LZ",
    "wof:placetype":"postalcode"
},
  "geometry": {"coordinates":[-0.49268128885715,51.76639983400367],"type":"Point"}
}