{
  "type": "Feature",
  "properties": {
    "iso:country":"GB",
    "wof:name":"YO22 4SN",
    "wof:placetype":"postalcode"
},
  "geometry": {"coordinates":[-0.53245180653609,54.43013376099342],"type":"Point"}
}