{
  "type": "Feature",
  "properties": {
    "date:inception_lower": "1980-01-01",
    "date:inception_upper": "1980-01-01",
    "iso:country": "GB",
    "wof:name": "YO22 4SN",
    "wof:placetype": "postalcode"
  },
  "geometry": {"coordinates":[-0.532533,54.430078],"type":"Point"}
}
