{
  "type": "Feature",
  "properties": {
    "iso:country":"GB",
    "wof:name":"RG19 8ED",
    "wof:placetype":"postalcode"
},
  "geometry": {"coordinates":[-1.22286094005669,51.37550109865374],"type":"Point"}
}