{
  "type": "Feature",
  "properties": {
    "iso:country": "GB",
    "wof:name": "BD15 0HF",
    "wof:placetype": "postalcode"
  },
  "geometry": {"coordinates":[-1.857508,53.817342],"type":"Point"}
}
