{
  "type": "Feature",
  "properties": {
    "date:inception_lower": "2007-07-01",
    "date:inception_upper": "2007-07-01",
    "iso:country": "GB",
    "wof:name": "BD15 0HF",
    "wof:placetype": "postalcode"
  },
  "geometry": {"coordinates":[-1.857508,53.817342],"type":"Point"}
}
