{
  "type": "Feature",
  "properties": {
    "iso:country": "GB",
    "wof:name": "CH61 3XY",
    "wof:placetype": "postalcode"
  },
  "geometry": {"coordinates":[-3.110462,53.35516],"type":"Point"}
}
