{
  "type": "Feature",
  "properties": {
    "iso:country": "GB",
    "wof:name": "BN12 6PG",
    "wof:placetype": "postalcode"
  },
  "geometry": {"coordinates":[-0.444549,50.822245],"type":"Point"}
}
