{
  "type": "Feature",
  "properties": {
    "iso:country":"GB",
    "wof:name":"BN12 6PG",
    "wof:placetype":"postalcode"
},
  "geometry": {"coordinates":[-0.44457344915508,50.82225293087183],"type":"Point"}
}