{
  "type": "Feature",
  "properties": {
    "date:inception_lower": "2020-05-01",
    "date:inception_upper": "2020-05-01",
    "iso:country": "GB",
    "wof:name": "HR9 7WP",
    "wof:placetype": "postalcode"
  },
  "geometry": {"coordinates":[-2.568767,51.923331],"type":"Point"}
}
