{
  "type": "Feature",
  "properties": {
    "date:inception_lower": "2009-10-01",
    "date:inception_upper": "2009-10-01",
    "iso:country": "GB",
    "wof:name": "NP20 2GA",
    "wof:placetype": "postalcode"
  },
  "geometry": {"coordinates":[-2.980865,51.579224],"type":"Point"}
}
