{
  "type": "Feature",
  "properties": {
    "iso:country":"GB",
    "wof:name":"KT13 0HN",
    "wof:placetype":"postalcode"
},
  "geometry": {"coordinates":[-0.43577874269263,51.35874476823955],"type":"Point"}
}