{
  "type": "Feature",
  "properties": {
    "iso:country":"GB",
    "wof:name":"S65 1DF",
    "wof:placetype":"postalcode"
},
  "geometry": {"coordinates":[-1.35294417538869,53.43091689352101],"type":"Point"}
}