{
  "type": "Feature",
  "properties": {
    "date:inception_lower":"2000-06-01",
    "date:inception_upper":"2000-06-30",
    "iso:country":"GB",
    "wof:name":"TR27 4RF",
    "wof:placetype":"postalcode"
},
  "geometry": {"coordinates":[-5.401016,50.195569],"type":"Point"}
}