{
  "type": "Feature",
  "properties": {
    "iso:country":"GB",
    "wof:name":"TR27 4RF",
    "wof:placetype":"postalcode"
},
  "geometry": {"coordinates":[-5.40101577638794,50.19556924223352],"type":"Point"}
}