{
  "type": "Feature",
  "properties": {
    "iso:country": "GB",
    "wof:name": "TR27 4RF",
    "wof:placetype": "postalcode"
  },
  "geometry": {"coordinates":[-5.401016,50.195569],"type":"Point"}
}
