{
  "type": "Feature",
  "properties": {
    "iso:country":"GB",
    "wof:name":"NG4 1PY",
    "wof:placetype":"postalcode"
},
  "geometry": {"coordinates":[-1.11215799181897,52.97075220353737],"type":"Point"}
}