{
  "type": "Feature",
  "properties": {
    "iso:country":"GB",
    "wof:name":"HP4 2PT",
    "wof:placetype":"postalcode"
},
  "geometry": {"coordinates":[-0.54768110665837,51.76495214908103],"type":"Point"}
}