{
  "type": "Feature",
  "properties": {
    "date:inception_lower": "1980-01-01",
    "date:inception_upper": "1980-01-01",
    "iso:country": "GB",
    "wof:name": "HP4 2PT",
    "wof:placetype": "postalcode"
  },
  "geometry": {"coordinates":[-0.547681,51.764952],"type":"Point"}
}
