{
  "type": "Feature",
  "properties": {
    "iso:country":"GB",
    "wof:name":"SO18 5QL",
    "wof:placetype":"postalcode"
},
  "geometry": {"coordinates":[-1.35007344629139,50.92306322576062],"type":"Point"}
}