{
  "type": "Feature",
  "properties": {
    "iso:country":"GB",
    "wof:name":"PR1 9HU",
    "wof:placetype":"postalcode"
},
  "geometry": {"coordinates":[-2.71961681018837,53.7377702076257],"type":"Point"}
}