{
  "type": "Feature",
  "properties": {
    "date:inception_lower": "1980-01-01",
    "date:inception_upper": "1980-01-01",
    "iso:country": "GB",
    "wof:name": "PR1 9HU",
    "wof:placetype": "postalcode"
  },
  "geometry": {"coordinates":[-2.719617,53.73777],"type":"Point"}
}
