{
  "type": "Feature",
  "properties": {
    "iso:country": "GB",
    "wof:name": "PR1 9HU",
    "wof:placetype": "postalcode"
  },
  "geometry": {"coordinates":[-2.719617,53.73777],"type":"Point"}
}
