{
  "type": "Feature",
  "properties": {
    "iso:country": "GB",
    "wof:name": "LL42 1NS",
    "wof:placetype": "postalcode"
  },
  "geometry": {"coordinates":[-4.060502,52.724709],"type":"Point"}
}
