{
  "type": "Feature",
  "properties": {
    "iso:country":"GB",
    "wof:name":"SR3 3AP",
    "wof:placetype":"postalcode"
},
  "geometry": {"coordinates":[-1.41801448110248,54.87533775697086],"type":"Point"}
}