{
  "type": "Feature",
  "properties": {
    "iso:country":"GB",
    "wof:name":"EH52 5LE",
    "wof:placetype":"postalcode"
},
  "geometry": {"coordinates":[-3.48100351389958,55.93306308616143],"type":"Point"}
}