{
  "type": "Feature",
  "properties": {
    "date:inception_lower": "1980-01-01",
    "date:inception_upper": "1980-01-01",
    "iso:country": "GB",
    "wof:name": "EH52 5LE",
    "wof:placetype": "postalcode"
  },
  "geometry": {"coordinates":[-3.480305,55.933292],"type":"Point"}
}
