{
  "type": "Feature",
  "properties": {
    "iso:country": "GB",
    "wof:name": "CV12 0HE",
    "wof:placetype": "postalcode"
  },
  "geometry": {"coordinates":[-1.505735,52.47128],"type":"Point"}
}
