{
  "type": "Feature",
  "properties": {
    "iso:country":"GB",
    "wof:name":"CV12 0HE",
    "wof:placetype":"postalcode"
},
  "geometry": {"coordinates":[-1.50573485878576,52.4712804113211],"type":"Point"}
}