{
  "type": "Feature",
  "properties": {
    "iso:country":"GB",
    "wof:name":"S80 2EQ",
    "wof:placetype":"postalcode"
},
  "geometry": {"coordinates":[-1.1162845656295,53.30727759510454],"type":"Point"}
}