{
  "type": "Feature",
  "properties": {
    "date:inception_lower":"1980-01-01",
    "date:inception_upper":"1980-01-31",
    "iso:country":"GB",
    "wof:name":"S80 2EQ",
    "wof:placetype":"postalcode"
},
  "geometry": {"coordinates":[-1.116406,53.307235],"type":"Point"}
}