{
  "type": "Feature",
  "properties": {
    "iso:country":"GB",
    "wof:name":"SY13 4RE",
    "wof:placetype":"postalcode"
},
  "geometry": {"coordinates":[-2.73145503844873,52.98419213397706],"type":"Point"}
}