{
  "type": "Feature",
  "properties": {
    "date:inception_lower": "1980-01-01",
    "date:inception_upper": "1980-01-01",
    "iso:country": "GB",
    "wof:name": "SY13 4RE",
    "wof:placetype": "postalcode"
  },
  "geometry": {"coordinates":[-2.731455,52.984192],"type":"Point"}
}
