{
  "type": "Feature",
  "properties": {
    "iso:country": "GB",
    "wof:name": "SY13 4RE",
    "wof:placetype": "postalcode"
  },
  "geometry": {"coordinates":[-2.731455,52.984192],"type":"Point"}
}
