{
  "type": "Feature",
  "properties": {
    "iso:country":"GB",
    "wof:name":"LS8 5BL",
    "wof:placetype":"postalcode"
},
  "geometry": {"coordinates":[-1.51614918104899,53.81639787117682],"type":"Point"}
}