{
  "type": "Feature",
  "properties": {
    "iso:country": "GB",
    "wof:name": "LS8 5BL",
    "wof:placetype": "postalcode"
  },
  "geometry": {"coordinates":[-1.516149,53.816398],"type":"Point"}
}
