{
  "type": "Feature",
  "properties": {
    "iso:country":"GB",
    "wof:name":"S63 9NH",
    "wof:placetype":"postalcode"
},
  "geometry": {"coordinates":[-1.3031450547552,53.53183082209256],"type":"Point"}
}