{
  "type": "Feature",
  "properties": {
    "date:inception_lower": "1980-01-01",
    "date:inception_upper": "1980-01-01",
    "iso:country": "GB",
    "wof:name": "S63 9NH",
    "wof:placetype": "postalcode"
  },
  "geometry": {"coordinates":[-1.303145,53.531831],"type":"Point"}
}
