{
  "type": "Feature",
  "properties": {
    "iso:country": "GB",
    "wof:name": "S63 9NH",
    "wof:placetype": "postalcode"
  },
  "geometry": {"coordinates":[-1.303145,53.531831],"type":"Point"}
}
