{
  "type": "Feature",
  "properties": {
    "iso:country": "GB",
    "wof:name": "TN23 1DU",
    "wof:placetype": "postalcode"
  },
  "geometry": {"coordinates":[0.866793,51.148127],"type":"Point"}
}
