{
  "type": "Feature",
  "properties": {
    "date:inception_lower":"1980-01-01",
    "date:inception_upper":"1980-01-31",
    "iso:country":"GB",
    "wof:name":"HX3 8RE",
    "wof:placetype":"postalcode"
},
  "geometry": {"coordinates":[-1.794543,53.73795],"type":"Point"}
}