{
  "type": "Feature",
  "properties": {
    "iso:country":"GB",
    "wof:name":"DA12 2BG",
    "wof:placetype":"postalcode"
},
  "geometry": {"coordinates":[0.37397160366761,51.44475073485006],"type":"Point"}
}