{
  "type": "Feature",
  "properties": {
    "iso:country":"GB",
    "wof:name":"DN14 7PW",
    "wof:placetype":"postalcode"
},
  "geometry": {"coordinates":[-0.7941713636693,53.75926136110003],"type":"Point"}
}