{
  "type": "Feature",
  "properties": {
    "iso:country": "GB",
    "wof:name": "DN14 7PW",
    "wof:placetype": "postalcode"
  },
  "geometry": {"coordinates":[-0.794171,53.759261],"type":"Point"}
}
