{
  "type": "Feature",
  "properties": {
    "iso:country":"GB",
    "wof:name":"TS3 6EG",
    "wof:placetype":"postalcode"
},
  "geometry": {"coordinates":[-1.21223793171538,54.5694609075005],"type":"Point"}
}