{
  "type": "Feature",
  "properties": {
    "iso:country": "GB",
    "wof:name": "CT6 5QJ",
    "wof:placetype": "postalcode"
  },
  "geometry": {"coordinates":[1.119909,51.365846],"type":"Point"}
}
