{
  "type": "Feature",
  "properties": {
    "date:inception_lower": "1988-03-01",
    "date:inception_upper": "1988-03-01",
    "iso:country": "GB",
    "wof:name": "TW3 1YS",
    "wof:placetype": "postalcode"
  },
  "geometry": {"coordinates":[-0.353837,51.466853],"type":"Point"}
}
