{
  "type": "Feature",
  "properties": {
    "iso:country":"GB",
    "wof:name":"TW3 1YS",
    "wof:placetype":"postalcode"
},
  "geometry": {"coordinates":[-0.35383732243433,51.46685296855701],"type":"Point"}
}