{
  "type": "Feature",
  "properties": {
    "iso:country":"GB",
    "wof:name":"NW4 1NX",
    "wof:placetype":"postalcode"
},
  "geometry": {"coordinates":[-0.21698537889819,51.59766043699733],"type":"Point"}
}