{
  "type": "Feature",
  "properties": {
    "iso:country":"GB",
    "wof:name":"TS14 8BJ",
    "wof:placetype":"postalcode"
},
  "geometry": {"coordinates":[-1.07377205258073,54.52781347834934],"type":"Point"}
}