{
  "type": "Feature",
  "properties": {
    "iso:country": "GB",
    "wof:name": "TS14 8BJ",
    "wof:placetype": "postalcode"
  },
  "geometry": {"coordinates":[-1.073772,54.527813],"type":"Point"}
}
