{
  "type": "Feature",
  "properties": {
    "date:inception_lower": "1980-01-01",
    "date:inception_upper": "1980-01-01",
    "iso:country": "GB",
    "wof:name": "NE6 2EB",
    "wof:placetype": "postalcode"
  },
  "geometry": {"coordinates":[-1.570495,54.971623],"type":"Point"}
}
