{
  "type": "Feature",
  "properties": {
    "iso:country":"GB",
    "wof:name":"NE6 2EB",
    "wof:placetype":"postalcode"
},
  "geometry": {"coordinates":[-1.57049456288355,54.97162297219045],"type":"Point"}
}