{
  "type": "Feature",
  "properties": {
    "date:inception_lower": "1980-01-01",
    "date:inception_upper": "1980-01-01",
    "iso:country": "GB",
    "wof:name": "HX6 1AX",
    "wof:placetype": "postalcode"
  },
  "geometry": {"coordinates":[-1.928961,53.705873],"type":"Point"}
}
