{
  "type": "Feature",
  "properties": {
    "iso:country":"GB",
    "wof:name":"HX6 1AX",
    "wof:placetype":"postalcode"
},
  "geometry": {"coordinates":[-1.92896104870486,53.70587342180875],"type":"Point"}
}