{
  "type": "Feature",
  "properties": {
    "date:inception_lower":"1980-01-01",
    "date:inception_upper":"1980-01-31",
    "iso:country":"GB",
    "wof:name":"MK42 7PD",
    "wof:placetype":"postalcode"
},
  "geometry": {"coordinates":[-0.485366,52.11489],"type":"Point"}
}