{
  "type": "Feature",
  "properties": {
    "iso:country": "GB",
    "wof:name": "SY5 7LQ",
    "wof:placetype": "postalcode"
  },
  "geometry": {"coordinates":[-2.753682,52.62417],"type":"Point"}
}
