{
  "type": "Feature",
  "properties": {
    "date:inception_lower":"2002-06-01",
    "date:inception_upper":"2002-06-30",
    "iso:country":"GB",
    "wof:name":"SY5 7LQ",
    "wof:placetype":"postalcode"
},
  "geometry": {"coordinates":[-2.753682,52.62417],"type":"Point"}
}