{
  "type": "Feature",
  "properties": {
    "date:inception_lower": "2002-06-01",
    "date:inception_upper": "2002-06-01",
    "iso:country": "GB",
    "wof:name": "SY5 7LQ",
    "wof:placetype": "postalcode"
  },
  "geometry": {"coordinates":[-2.753666,52.624158],"type":"Point"}
}
