{
  "type": "Feature",
  "properties": {
    "iso:country":"GB",
    "wof:name":"SE15 3SS",
    "wof:placetype":"postalcode"
},
  "geometry": {"coordinates":[-0.06278938869713,51.46939261178512],"type":"Point"}
}