{
  "type": "Feature",
  "properties": {
    "date:inception_lower": "2023-09-01",
    "date:inception_upper": "2023-09-01",
    "iso:country": "GB",
    "wof:name": "B46 1LW",
    "wof:placetype": "postalcode"
  },
  "geometry": {"coordinates":[-1.705787,52.498159],"type":"Point"}
}
