{
  "type": "Feature",
  "properties": {
    "iso:country":"GB",
    "wof:name":"FK2 8NT",
    "wof:placetype":"postalcode"
},
  "geometry": {"coordinates":[-3.75326349283201,56.02888540649009],"type":"Point"}
}