{
  "type": "Feature",
  "properties": {
    "iso:country":"GB",
    "wof:name":"BR5 3WF",
    "wof:placetype":"postalcode"
},
  "geometry": {"coordinates":[0.11961360897675,51.39640653551653],"type":"Point"}
}