{
  "type": "Feature",
  "properties": {
    "iso:country": "GB",
    "wof:name": "BR5 3WF",
    "wof:placetype": "postalcode"
  },
  "geometry": {"coordinates":[0.119614,51.396407],"type":"Point"}
}
