{
  "type": "Feature",
  "properties": {
    "date:inception_lower":"1990-02-01",
    "date:inception_upper":"1990-02-28",
    "iso:country":"GB",
    "wof:name":"GU31 4LF",
    "wof:placetype":"postalcode"
},
  "geometry": {"coordinates":[-0.93334,51.000494],"type":"Point"}
}