{
  "type": "Feature",
  "properties": {
    "iso:country": "GB",
    "wof:name": "GU31 4LF",
    "wof:placetype": "postalcode"
  },
  "geometry": {"coordinates":[-0.93334,51.000494],"type":"Point"}
}
