{
  "type": "Feature",
  "properties": {
    "iso:country":"GB",
    "wof:name":"PL13 2HB",
    "wof:placetype":"postalcode"
},
  "geometry": {"coordinates":[-4.45764818818305,50.35176256353945],"type":"Point"}
}