{
  "type": "Feature",
  "properties": {
    "iso:country": "GB",
    "wof:name": "CF45 4AH",
    "wof:placetype": "postalcode"
  },
  "geometry": {"coordinates":[-3.378749,51.685823],"type":"Point"}
}
