{
  "type": "Feature",
  "properties": {
    "iso:country": "GB",
    "wof:name": "MK42 7FS",
    "wof:placetype": "postalcode"
  },
  "geometry": {"coordinates":[-0.506921,52.106632],"type":"Point"}
}
