{
  "type": "Feature",
  "properties": {
    "iso:country":"GB",
    "wof:name":"MK42 7FS",
    "wof:placetype":"postalcode"
},
  "geometry": {"coordinates":[-0.5069213307816,52.10663186725991],"type":"Point"}
}