{
  "type": "Feature",
  "properties": {
    "iso:country":"GB",
    "wof:name":"SW16 6NN",
    "wof:placetype":"postalcode"
},
  "geometry": {"coordinates":[-0.13224871094446,51.42843431191164],"type":"Point"}
}