{
  "type": "Feature",
  "properties": {
    "iso:country": "GB",
    "wof:name": "SY23 4AJ",
    "wof:placetype": "postalcode"
  },
  "geometry": {"coordinates":[-3.989224,52.315353],"type":"Point"}
}
