{
  "type": "Feature",
  "properties": {
    "date:inception_lower":"1980-01-01",
    "date:inception_upper":"1980-01-31",
    "iso:country":"GB",
    "wof:name":"NE26 2PJ",
    "wof:placetype":"postalcode"
},
  "geometry": {"coordinates":[-1.434299,55.037789],"type":"Point"}
}