{
  "type": "Feature",
  "properties": {
    "iso:country": "GB",
    "wof:name": "SN3 6JG",
    "wof:placetype": "postalcode"
  },
  "geometry": {"coordinates":[-1.730537,51.552104],"type":"Point"}
}
