{
  "type": "Feature",
  "properties": {
    "iso:country":"GB",
    "wof:name":"SN3 6JG",
    "wof:placetype":"postalcode"
},
  "geometry": {"coordinates":[-1.73053718841421,51.55210410621594],"type":"Point"}
}