{
  "type": "Feature",
  "properties": {
    "iso:country": "GB",
    "wof:name": "SP4 7YT",
    "wof:placetype": "postalcode"
  },
  "geometry": {"coordinates":[-1.768497,51.161958],"type":"Point"}
}
