{
  "type": "Feature",
  "properties": {
    "iso:country": "GB",
    "wof:name": "N13 4EG",
    "wof:placetype": "postalcode"
  },
  "geometry": {"coordinates":[-0.118495,51.61287],"type":"Point"}
}
