{
  "type": "Feature",
  "properties": {
    "iso:country":"GB",
    "wof:name":"TR18 3PQ",
    "wof:placetype":"postalcode"
},
  "geometry": {"coordinates":[-5.53820591918959,50.12832863530561],"type":"Point"}
}