{
  "type": "Feature",
  "properties": {
    "iso:country":"GB",
    "wof:name":"WV4 6BA",
    "wof:placetype":"postalcode"
},
  "geometry": {"coordinates":[-2.11999804927522,52.55957863364483],"type":"Point"}
}