{
  "type": "Feature",
  "properties": {
    "date:inception_lower":"2004-09-01",
    "date:inception_upper":"2004-09-30",
    "iso:country":"GB",
    "wof:name":"NN11 2JT",
    "wof:placetype":"postalcode"
},
  "geometry": {"coordinates":[-1.149923,52.291142],"type":"Point"}
}