{
  "type": "Feature",
  "properties": {
    "iso:country":"GB",
    "wof:name":"NN11 2JT",
    "wof:placetype":"postalcode"
},
  "geometry": {"coordinates":[-1.14992339441081,52.29114247135946],"type":"Point"}
}