{
  "type": "Feature",
  "properties": {
    "iso:country":"GB",
    "wof:name":"CB1 2AB",
    "wof:placetype":"postalcode"
},
  "geometry": {"coordinates":[0.13379074971244,52.20154131965587],"type":"Point"}
}