{
  "type": "Feature",
  "properties": {
    "iso:country": "GB",
    "wof:name": "CB1 2AB",
    "wof:placetype": "postalcode"
  },
  "geometry": {"coordinates":[0.133791,52.201541],"type":"Point"}
}
