{
  "type": "Feature",
  "properties": {
    "iso:country":"GB",
    "wof:name":"EX1 3FS",
    "wof:placetype":"postalcode"
},
  "geometry": {"coordinates":[-3.46361632654941,50.73488732355352],"type":"Point"}
}