{
  "type": "Feature",
  "properties": {
    "iso:country": "GB",
    "wof:name": "EX1 3FS",
    "wof:placetype": "postalcode"
  },
  "geometry": {"coordinates":[-3.463817,50.734047],"type":"Point"}
}
