{
  "type": "Feature",
  "properties": {
    "iso:country": "GB",
    "wof:name": "IV36 3YB",
    "wof:placetype": "postalcode"
  },
  "geometry": {"coordinates":[-3.552823,57.634641],"type":"Point"}
}
