{
  "type": "Feature",
  "properties": {
    "iso:country":"GB",
    "wof:name":"IV36 3YB",
    "wof:placetype":"postalcode"
},
  "geometry": {"coordinates":[-3.55282562515545,57.63465588189228],"type":"Point"}
}