{
  "type": "Feature",
  "properties": {
    "iso:country": "GB",
    "wof:name": "NR9 5RZ",
    "wof:placetype": "postalcode"
  },
  "geometry": {"coordinates":[1.062031,52.717058],"type":"Point"}
}
