{
  "type": "Feature",
  "properties": {
    "iso:country":"GB",
    "wof:name":"NR9 5RZ",
    "wof:placetype":"postalcode"
},
  "geometry": {"coordinates":[1.06203135547129,52.71705767292815],"type":"Point"}
}