{
  "type": "Feature",
  "properties": {
    "iso:country":"GB",
    "wof:name":"CO9 4EN",
    "wof:placetype":"postalcode"
},
  "geometry": {"coordinates":[0.51567202822827,51.97630225161404],"type":"Point"}
}