{
  "type": "Feature",
  "properties": {
    "iso:country": "GB",
    "wof:name": "CO9 4EN",
    "wof:placetype": "postalcode"
  },
  "geometry": {"coordinates":[0.515672,51.976302],"type":"Point"}
}
