{
  "type": "Feature",
  "properties": {
    "date:inception_lower":"1980-01-01",
    "date:inception_upper":"1980-01-31",
    "iso:country":"GB",
    "wof:name":"CO9 4EN",
    "wof:placetype":"postalcode"
},
  "geometry": {"coordinates":[0.515672,51.976302],"type":"Point"}
}