{
  "type": "Feature",
  "properties": {
    "date:inception_lower": "1980-01-01",
    "date:inception_upper": "1980-01-01",
    "iso:country": "GB",
    "wof:name": "DA11 8LA",
    "wof:placetype": "postalcode"
  },
  "geometry": {"coordinates":[0.348372,51.426021],"type":"Point"}
}
