{
  "type": "Feature",
  "properties": {
    "iso:country":"GB",
    "wof:name":"BS15 3LF",
    "wof:placetype":"postalcode"
},
  "geometry": {"coordinates":[-2.52280750618076,51.44060602162703],"type":"Point"}
}