{
  "type": "Feature",
  "properties": {
    "iso:country":"GB",
    "wof:name":"EX31 1QD",
    "wof:placetype":"postalcode"
},
  "geometry": {"coordinates":[-4.06459623327434,51.09020164045574],"type":"Point"}
}