{
  "type": "Feature",
  "properties": {
    "date:inception_lower": "1980-01-01",
    "date:inception_upper": "1980-01-01",
    "iso:country": "GB",
    "wof:name": "EX31 1QD",
    "wof:placetype": "postalcode"
  },
  "geometry": {"coordinates":[-4.064596,51.090202],"type":"Point"}
}
