{
  "type": "Feature",
  "properties": {
    "date:inception_lower":"2003-05-01",
    "date:inception_upper":"2003-05-31",
    "iso:country":"GB",
    "wof:name":"TQ14 9EB",
    "wof:placetype":"postalcode"
},
  "geometry": {"coordinates":[-3.509324,50.553663],"type":"Point"}
}