{
  "type": "Feature",
  "properties": {
    "date:inception_lower": "1980-01-01",
    "date:inception_upper": "1980-01-01",
    "iso:country": "GB",
    "wof:name": "HP13 7XB",
    "wof:placetype": "postalcode"
  },
  "geometry": {"coordinates":[-0.718503,51.631617],"type":"Point"}
}
