{
  "type": "Feature",
  "properties": {
    "iso:country":"GB",
    "wof:name":"HP13 7XB",
    "wof:placetype":"postalcode"
},
  "geometry": {"coordinates":[-0.71852280638204,51.63161383348925],"type":"Point"}
}