{
  "type": "Feature",
  "properties": {
    "iso:country":"GB",
    "wof:name":"DN6 9HD",
    "wof:placetype":"postalcode"
},
  "geometry": {"coordinates":[-1.16954032072461,53.63260251872871],"type":"Point"}
}