{
  "type": "Feature",
  "properties": {
    "date:inception_lower": "1980-01-01",
    "date:inception_upper": "1980-01-01",
    "iso:country": "GB",
    "wof:name": "CM8 3PR",
    "wof:placetype": "postalcode"
  },
  "geometry": {"coordinates":[0.644745,51.837938],"type":"Point"}
}
