{
  "type": "Feature",
  "properties": {
    "iso:country": "GB",
    "wof:name": "CM8 3PR",
    "wof:placetype": "postalcode"
  },
  "geometry": {"coordinates":[0.644745,51.837938],"type":"Point"}
}
