{
  "type": "Feature",
  "properties": {
    "iso:country":"GB",
    "wof:name":"CV6 5GJ",
    "wof:placetype":"postalcode"
},
  "geometry": {"coordinates":[-1.49253945384001,52.42560882670205],"type":"Point"}
}