{
  "type": "Feature",
  "properties": {
    "iso:country":"GB",
    "wof:name":"ME2 3LR",
    "wof:placetype":"postalcode"
},
  "geometry": {"coordinates":[0.48273949858295,51.40248499585659],"type":"Point"}
}