{
  "type": "Feature",
  "properties": {
    "date:inception_lower": "1980-01-01",
    "date:inception_upper": "1980-01-01",
    "iso:country": "GB",
    "wof:name": "ME2 3LR",
    "wof:placetype": "postalcode"
  },
  "geometry": {"coordinates":[0.482621,51.402434],"type":"Point"}
}
