{
  "type": "Feature",
  "properties": {
    "date:inception_lower":"1980-01-01",
    "date:inception_upper":"1980-01-31",
    "iso:country":"GB",
    "wof:name":"ME2 3LR",
    "wof:placetype":"postalcode"
},
  "geometry": {"coordinates":[0.48274,51.402485],"type":"Point"}
}