{
  "type": "Feature",
  "properties": {
    "iso:country":"GB",
    "wof:name":"RM8 1NR",
    "wof:placetype":"postalcode"
},
  "geometry": {"coordinates":[0.14742670417441,51.56309618381578],"type":"Point"}
}