{
  "type": "Feature",
  "properties": {
    "iso:country":"GB",
    "wof:name":"DH3 2HH",
    "wof:placetype":"postalcode"
},
  "geometry": {"coordinates":[-1.5679650259338,54.88264017648645],"type":"Point"}
}