{
  "type": "Feature",
  "properties": {
    "date:inception_lower": "2001-06-01",
    "date:inception_upper": "2001-06-01",
    "iso:country": "GB",
    "wof:name": "EH39 4DE",
    "wof:placetype": "postalcode"
  },
  "geometry": {"coordinates":[-2.740429,56.05363],"type":"Point"}
}
