{
  "type": "Feature",
  "properties": {
    "iso:country":"GB",
    "wof:name":"EH39 4DE",
    "wof:placetype":"postalcode"
},
  "geometry": {"coordinates":[-2.74002322466848,56.05369990434539],"type":"Point"}
}