{
  "type": "Feature",
  "properties": {
    "date:inception_lower": "2009-05-01",
    "date:inception_upper": "2009-05-01",
    "iso:country": "GB",
    "wof:name": "HX7 5RJ",
    "wof:placetype": "postalcode"
  },
  "geometry": {"coordinates":[-1.9751,53.712926],"type":"Point"}
}
