{
  "type": "Feature",
  "properties": {
    "iso:country":"GB",
    "wof:name":"CM7 2AQ",
    "wof:placetype":"postalcode"
},
  "geometry": {"coordinates":[0.54276227515874,51.87606059899354],"type":"Point"}
}