{
  "type": "Feature",
  "properties": {
    "iso:country": "GB",
    "wof:name": "CM7 2AQ",
    "wof:placetype": "postalcode"
  },
  "geometry": {"coordinates":[0.542762,51.876061],"type":"Point"}
}
