{
  "type": "Feature",
  "properties": {
    "date:inception_lower": "1995-01-01",
    "date:inception_upper": "1995-01-01",
    "iso:country": "GB",
    "wof:name": "M32 0JU",
    "wof:placetype": "postalcode"
  },
  "geometry": {"coordinates":[-2.297574,53.450409],"type":"Point"}
}
