{
  "type": "Feature",
  "properties": {
    "iso:country":"GB",
    "wof:name":"M32 0JU",
    "wof:placetype":"postalcode"
},
  "geometry": {"coordinates":[-2.29757410301392,53.45040855504151],"type":"Point"}
}