{
  "type": "Feature",
  "properties": {
    "iso:country":"GB",
    "wof:name":"SN8 1UE",
    "wof:placetype":"postalcode"
},
  "geometry": {"coordinates":[-1.74191488278122,51.41962183252305],"type":"Point"}
}