{
  "type": "Feature",
  "properties": {
    "iso:country":"GB",
    "wof:name":"CM2 6DY",
    "wof:placetype":"postalcode"
},
  "geometry": {"coordinates":[0.49126720859909,51.73107155160286],"type":"Point"}
}