{
  "type": "Feature",
  "properties": {
    "iso:country":"GB",
    "wof:name":"SW4 0QX",
    "wof:placetype":"postalcode"
},
  "geometry": {"coordinates":[-0.1453424294855,51.46458562935638],"type":"Point"}
}