{
  "type": "Feature",
  "properties": {
    "iso:country": "GB",
    "wof:name": "WR9 7GG",
    "wof:placetype": "postalcode"
  },
  "geometry": {"coordinates":[-2.168988,52.250921],"type":"Point"}
}
