{
  "type": "Feature",
  "properties": {
    "iso:country":"GB",
    "wof:name":"EX8 3ND",
    "wof:placetype":"postalcode"
},
  "geometry": {"coordinates":[-3.40925153680748,50.63552523350442],"type":"Point"}
}