{
  "type": "Feature",
  "properties": {
    "date:inception_lower": "1980-01-01",
    "date:inception_upper": "1980-01-01",
    "iso:country": "GB",
    "wof:name": "EX8 3ND",
    "wof:placetype": "postalcode"
  },
  "geometry": {"coordinates":[-3.409251,50.635525],"type":"Point"}
}
