{
  "type": "Feature",
  "properties": {
    "iso:country": "GB",
    "wof:name": "SG19 3JE",
    "wof:placetype": "postalcode"
  },
  "geometry": {"coordinates":[-0.189868,52.156212],"type":"Point"}
}
