{
  "type": "Feature",
  "properties": {
    "date:inception_lower":"1980-01-01",
    "date:inception_upper":"1980-01-31",
    "iso:country":"GB",
    "wof:name":"ME17 1RE",
    "wof:placetype":"postalcode"
},
  "geometry": {"coordinates":[0.617052,51.258089],"type":"Point"}
}