{
  "type": "Feature",
  "properties": {
    "iso:country":"GB",
    "wof:name":"ME17 1RE",
    "wof:placetype":"postalcode"
},
  "geometry": {"coordinates":[0.61705191757811,51.25808917853065],"type":"Point"}
}