{
  "type": "Feature",
  "properties": {
    "iso:country": "GB",
    "wof:name": "ME17 1RE",
    "wof:placetype": "postalcode"
  },
  "geometry": {"coordinates":[0.617052,51.258089],"type":"Point"}
}
