{
  "type": "Feature",
  "properties": {
    "iso:country": "GB",
    "wof:name": "BA3 4LT",
    "wof:placetype": "postalcode"
  },
  "geometry": {"coordinates":[-2.512553,51.255735],"type":"Point"}
}
