{
  "type": "Feature",
  "properties": {
    "date:inception_lower": "1995-07-01",
    "date:inception_upper": "1995-07-01",
    "iso:country": "GB",
    "wof:name": "BA3 4LT",
    "wof:placetype": "postalcode"
  },
  "geometry": {"coordinates":[-2.512553,51.255735],"type":"Point"}
}
