{
  "type": "Feature",
  "properties": {
    "date:inception_lower": "2006-05-01",
    "date:inception_upper": "2006-05-01",
    "iso:country": "GB",
    "wof:name": "SY4 3RJ",
    "wof:placetype": "postalcode"
  },
  "geometry": {"coordinates":[-2.793061,52.807512],"type":"Point"}
}
