{
  "type": "Feature",
  "properties": {
    "iso:country":"GB",
    "wof:name":"AL9 7ED",
    "wof:placetype":"postalcode"
},
  "geometry": {"coordinates":[-0.21966436245889,51.73431067866275],"type":"Point"}
}