{
  "type": "Feature",
  "properties": {
    "date:inception_lower": "1980-01-01",
    "date:inception_upper": "1980-01-01",
    "iso:country": "GB",
    "wof:name": "NR25 6JB",
    "wof:placetype": "postalcode"
  },
  "geometry": {"coordinates":[1.08754,52.907605],"type":"Point"}
}
