{
  "type": "Feature",
  "properties": {
    "date:inception_lower": "1980-01-01",
    "date:inception_upper": "1980-01-01",
    "iso:country": "GB",
    "wof:name": "HP10 9BX",
    "wof:placetype": "postalcode"
  },
  "geometry": {"coordinates":[-0.709683,51.605531],"type":"Point"}
}
