{
  "type": "Feature",
  "properties": {
    "iso:country":"GB",
    "wof:name":"HP10 9BX",
    "wof:placetype":"postalcode"
},
  "geometry": {"coordinates":[-0.7096832238226,51.6055307352237],"type":"Point"}
}