{
  "type": "Feature",
  "properties": {
    "date:inception_lower": "1980-01-01",
    "date:inception_upper": "1980-01-01",
    "iso:country": "GB",
    "wof:name": "AL3 4AB",
    "wof:placetype": "postalcode"
  },
  "geometry": {"coordinates":[-0.352835,51.740047],"type":"Point"}
}
