{
  "type": "Feature",
  "properties": {
    "iso:country":"GB",
    "wof:name":"BA12 8FB",
    "wof:placetype":"postalcode"
},
  "geometry": {"coordinates":[-2.1920461192105,51.19195897918588],"type":"Point"}
}