{
  "type": "Feature",
  "properties": {
    "date:inception_lower":"2012-03-01",
    "date:inception_upper":"2012-03-31",
    "iso:country":"GB",
    "wof:name":"BA12 8FB",
    "wof:placetype":"postalcode"
},
  "geometry": {"coordinates":[-2.192046,51.191959],"type":"Point"}
}