{
  "type": "Feature",
  "properties": {
    "iso:country": "GB",
    "wof:name": "BA12 8FB",
    "wof:placetype": "postalcode"
  },
  "geometry": {"coordinates":[-2.192046,51.191959],"type":"Point"}
}
