{
  "type": "Feature",
  "properties": {
    "iso:country":"GB",
    "wof:name":"G67 3AA",
    "wof:placetype":"postalcode"
},
  "geometry": {"coordinates":[-3.96259111130809,55.9496055991313],"type":"Point"}
}