{
  "type": "Feature",
  "properties": {
    "date:inception_lower": "1980-01-01",
    "date:inception_upper": "1980-01-01",
    "iso:country": "GB",
    "wof:name": "OX9 7DX",
    "wof:placetype": "postalcode"
  },
  "geometry": {"coordinates":[-0.972985,51.694493],"type":"Point"}
}
