{
  "type": "Feature",
  "properties": {
    "iso:country":"GB",
    "wof:name":"OX9 7DX",
    "wof:placetype":"postalcode"
},
  "geometry": {"coordinates":[-0.97298498720394,51.69449299114063],"type":"Point"}
}