{
  "type": "Feature",
  "properties": {
    "iso:country":"GB",
    "wof:name":"GU7 1HT",
    "wof:placetype":"postalcode"
},
  "geometry": {"coordinates":[-0.60929903595339,51.18769462314084],"type":"Point"}
}