{
  "type": "Feature",
  "properties": {
    "iso:country": "GB",
    "wof:name": "GU7 1HT",
    "wof:placetype": "postalcode"
  },
  "geometry": {"coordinates":[-0.609279,51.187691],"type":"Point"}
}
