{
  "type": "Feature",
  "properties": {
    "iso:country": "GB",
    "wof:name": "DN17 3AG",
    "wof:placetype": "postalcode"
  },
  "geometry": {"coordinates":[-0.73612,53.546386],"type":"Point"}
}
