{
  "type": "Feature",
  "properties": {
    "iso:country":"GB",
    "wof:name":"DN17 3AG",
    "wof:placetype":"postalcode"
},
  "geometry": {"coordinates":[-0.73611686765631,53.54636537499685],"type":"Point"}
}