{
  "type": "Feature",
  "properties": {
    "iso:country":"GB",
    "wof:name":"SP4 7ER",
    "wof:placetype":"postalcode"
},
  "geometry": {"coordinates":[-1.77977591498106,51.17432198633929],"type":"Point"}
}