{
  "type": "Feature",
  "properties": {
    "iso:country":"GB",
    "wof:name":"FK4 2HP",
    "wof:placetype":"postalcode"
},
  "geometry": {"coordinates":[-3.93801477699218,55.97252425387693],"type":"Point"}
}