{
  "type": "Feature",
  "properties": {
    "iso:country":"GB",
    "wof:name":"SM5 1TF",
    "wof:placetype":"postalcode"
},
  "geometry": {"coordinates":[-0.17422989649801,51.38138094309171],"type":"Point"}
}