{
  "type": "Feature",
  "properties": {
    "iso:country": "GB",
    "wof:name": "SK17 8PF",
    "wof:placetype": "postalcode"
  },
  "geometry": {"coordinates":[-1.774176,53.27625],"type":"Point"}
}
