{
  "type": "Feature",
  "properties": {
    "iso:country":"GB",
    "wof:name":"SK17 8PF",
    "wof:placetype":"postalcode"
},
  "geometry": {"coordinates":[-1.77417614292735,53.27625031873],"type":"Point"}
}