{
  "type": "Feature",
  "properties": {
    "iso:country": "GB",
    "wof:name": "SP3 6EU",
    "wof:placetype": "postalcode"
  },
  "geometry": {"coordinates":[-2.154051,51.096817],"type":"Point"}
}
