{
  "type": "Feature",
  "properties": {
    "iso:country":"GB",
    "wof:name":"SP3 6EU",
    "wof:placetype":"postalcode"
},
  "geometry": {"coordinates":[-2.15405056578253,51.09681673830637],"type":"Point"}
}