{
  "type": "Feature",
  "properties": {
    "iso:country":"GB",
    "wof:name":"DN6 0RF",
    "wof:placetype":"postalcode"
},
  "geometry": {"coordinates":[-1.13975616929809,53.6165994290382],"type":"Point"}
}