{
  "type": "Feature",
  "properties": {
    "iso:country": "GB",
    "wof:name": "KT22 7UT",
    "wof:placetype": "postalcode"
  },
  "geometry": {"coordinates":[-0.33618,51.299398],"type":"Point"}
}
