{
  "type": "Feature",
  "properties": {
    "iso:country": "GB",
    "wof:name": "SO53 1EX",
    "wof:placetype": "postalcode"
  },
  "geometry": {"coordinates":[-1.37519,50.994107],"type":"Point"}
}
