{
  "type": "Feature",
  "properties": {
    "iso:country":"GB",
    "wof:name":"SE1 7DA",
    "wof:placetype":"postalcode"
},
  "geometry": {"coordinates":[-0.11373499232696,51.49685932874574],"type":"Point"}
}