{
  "type": "Feature",
  "properties": {
    "iso:country":"GB",
    "wof:name":"HD6 1SP",
    "wof:placetype":"postalcode"
},
  "geometry": {"coordinates":[-1.77952445878454,53.70500885505785],"type":"Point"}
}