{
  "type": "Feature",
  "properties": {
    "iso:country": "GB",
    "wof:name": "HD6 1SP",
    "wof:placetype": "postalcode"
  },
  "geometry": {"coordinates":[-1.779524,53.705009],"type":"Point"}
}
