{
  "type": "Feature",
  "properties": {
    "iso:country":"GB",
    "wof:name":"CF63 4LD",
    "wof:placetype":"postalcode"
},
  "geometry": {"coordinates":[-3.26799388369923,51.40510387468461],"type":"Point"}
}