{
  "type": "Feature",
  "properties": {
    "iso:country":"GB",
    "wof:name":"CM14 5AW",
    "wof:placetype":"postalcode"
},
  "geometry": {"coordinates":[0.30976469165236,51.60810680815533],"type":"Point"}
}