{
  "type": "Feature",
  "properties": {
    "date:inception_lower":"1986-07-01",
    "date:inception_upper":"1986-07-31",
    "iso:country":"GB",
    "wof:name":"CM14 5AW",
    "wof:placetype":"postalcode"
},
  "geometry": {"coordinates":[0.309765,51.608107],"type":"Point"}
}