{
  "type": "Feature",
  "properties": {
    "iso:country":"GB",
    "wof:name":"IV2 3RQ",
    "wof:placetype":"postalcode"
},
  "geometry": {"coordinates":[-4.20031555536641,57.47085616960254],"type":"Point"}
}