{
  "type": "Feature",
  "properties": {
    "iso:country":"GB",
    "wof:name":"SA17 4EG",
    "wof:placetype":"postalcode"
},
  "geometry": {"coordinates":[-4.26042322484966,51.72669235907878],"type":"Point"}
}