{
  "type": "Feature",
  "properties": {
    "iso:country": "GB",
    "wof:name": "BB7 4NX",
    "wof:placetype": "postalcode"
  },
  "geometry": {"coordinates":[-2.327461,53.957073],"type":"Point"}
}
