{
  "type": "Feature",
  "properties": {
    "iso:country":"GB",
    "wof:name":"BB7 4NX",
    "wof:placetype":"postalcode"
},
  "geometry": {"coordinates":[-2.3274615080947,53.95707273815509],"type":"Point"}
}