{
  "type": "Feature",
  "properties": {
    "iso:country":"GB",
    "wof:name":"L21 8HE",
    "wof:placetype":"postalcode"
},
  "geometry": {"coordinates":[-2.9990006980429,53.46073132751519],"type":"Point"}
}