{
  "type": "Feature",
  "properties": {
    "iso:country": "GB",
    "wof:name": "TA4 1HG",
    "wof:placetype": "postalcode"
  },
  "geometry": {"coordinates":[-3.178652,50.99961],"type":"Point"}
}
