{
  "type": "Feature",
  "properties": {
    "date:inception_lower": "1980-01-01",
    "date:inception_upper": "1980-01-01",
    "iso:country": "GB",
    "wof:name": "PO8 9JN",
    "wof:placetype": "postalcode"
  },
  "geometry": {"coordinates":[-1.006807,50.91028],"type":"Point"}
}
