{
  "type": "Feature",
  "properties": {
    "iso:country":"GB",
    "wof:name":"E18 2BB",
    "wof:placetype":"postalcode"
},
  "geometry": {"coordinates":[0.02350478804952,51.59076599516913],"type":"Point"}
}