{
  "type": "Feature",
  "properties": {
    "iso:country":"GB",
    "wof:name":"EX3 0QQ",
    "wof:placetype":"postalcode"
},
  "geometry": {"coordinates":[-3.45962990265765,50.68459302604032],"type":"Point"}
}