{
  "type": "Feature",
  "properties": {
    "date:inception_lower":"1980-01-01",
    "date:inception_upper":"1980-01-31",
    "iso:country":"GB",
    "wof:name":"EX3 0QQ",
    "wof:placetype":"postalcode"
},
  "geometry": {"coordinates":[-3.45963,50.684593],"type":"Point"}
}