{
  "type": "Feature",
  "properties": {
    "iso:country": "GB",
    "wof:name": "EX3 0QQ",
    "wof:placetype": "postalcode"
  },
  "geometry": {"coordinates":[-3.45963,50.684593],"type":"Point"}
}
