{
  "type": "Feature",
  "properties": {
    "iso:country":"GB",
    "wof:name":"CF64 2TH",
    "wof:placetype":"postalcode"
},
  "geometry": {"coordinates":[-3.19013801193249,51.43815694074694],"type":"Point"}
}