{
  "type": "Feature",
  "properties": {
    "iso:country":"GB",
    "wof:name":"BN3 1NA",
    "wof:placetype":"postalcode"
},
  "geometry": {"coordinates":[-0.15810376414439,50.82621209404451],"type":"Point"}
}