{
  "type": "Feature",
  "properties": {
    "iso:country":"GB",
    "wof:name":"NE26 4PX",
    "wof:placetype":"postalcode"
},
  "geometry": {"coordinates":[-1.51172829911457,55.08738655070336],"type":"Point"}
}