{
  "type": "Feature",
  "properties": {
    "iso:country":"GB",
    "wof:name":"B17 0HT",
    "wof:placetype":"postalcode"
},
  "geometry": {"coordinates":[-1.94403085700843,52.45923623521425],"type":"Point"}
}