{
  "type": "Feature",
  "properties": {
    "iso:country":"GB",
    "wof:name":"PR5 5LJ",
    "wof:placetype":"postalcode"
},
  "geometry": {"coordinates":[-2.68385197385373,53.72180983475647],"type":"Point"}
}