{
  "type": "Feature",
  "properties": {
    "iso:country":"GB",
    "wof:name":"EX34 0PE",
    "wof:placetype":"postalcode"
},
  "geometry": {"coordinates":[-3.97506579586038,51.20321014557564],"type":"Point"}
}