{
  "type": "Feature",
  "properties": {
    "iso:country":"GB",
    "wof:name":"SG5 4EJ",
    "wof:placetype":"postalcode"
},
  "geometry": {"coordinates":[-0.23233070662751,52.0196798935871],"type":"Point"}
}