{
  "type": "Feature",
  "properties": {
    "iso:country":"GB",
    "wof:name":"HR1 4DB",
    "wof:placetype":"postalcode"
},
  "geometry": {"coordinates":[-2.63684578596366,52.06671061315306],"type":"Point"}
}