{
  "type": "Feature",
  "properties": {
    "date:inception_lower": "2019-02-01",
    "date:inception_upper": "2019-02-01",
    "iso:country": "GB",
    "wof:name": "SG18 8XS",
    "wof:placetype": "postalcode"
  },
  "geometry": {"coordinates":[-0.241522,52.096465],"type":"Point"}
}
