{
  "type": "Feature",
  "properties": {
    "iso:country":"GB",
    "wof:name":"SE17 1HB",
    "wof:placetype":"postalcode"
},
  "geometry": {"coordinates":[-0.08603589541532,51.49329009376938],"type":"Point"}
}