{
  "type": "Feature",
  "properties": {
    "iso:country": "GB",
    "wof:name": "BN25 2SA",
    "wof:placetype": "postalcode"
  },
  "geometry": {"coordinates":[0.07858,50.784794],"type":"Point"}
}
