{
  "type": "Feature",
  "properties": {
    "date:inception_lower":"1996-06-01",
    "date:inception_upper":"1996-06-30",
    "iso:country":"GB",
    "wof:name":"NE26 2NX",
    "wof:placetype":"postalcode"
},
  "geometry": {"coordinates":[-1.435404,55.040427],"type":"Point"}
}