{
  "type": "Feature",
  "properties": {
    "date:inception_lower": "1980-01-01",
    "date:inception_upper": "1980-01-01",
    "iso:country": "GB",
    "wof:name": "GU15 4HD",
    "wof:placetype": "postalcode"
  },
  "geometry": {"coordinates":[-0.726174,51.34756],"type":"Point"}
}
