{
  "type": "Feature",
  "properties": {
    "iso:country":"GB",
    "wof:name":"GU15 4HD",
    "wof:placetype":"postalcode"
},
  "geometry": {"coordinates":[-0.72617381250906,51.34755960903412],"type":"Point"}
}