{
  "type": "Feature",
  "properties": {
    "iso:country":"GB",
    "wof:name":"NE61 2YD",
    "wof:placetype":"postalcode"
},
  "geometry": {"coordinates":[-1.70325899905253,55.16240745835843],"type":"Point"}
}