{
  "type": "Feature",
  "properties": {
    "iso:country":"GB",
    "wof:name":"CR4 4EJ",
    "wof:placetype":"postalcode"
},
  "geometry": {"coordinates":[-0.17004019621136,51.39779010544707],"type":"Point"}
}