{
  "type": "Feature",
  "properties": {
    "iso:country":"GB",
    "wof:name":"ST16 3BN",
    "wof:placetype":"postalcode"
},
  "geometry": {"coordinates":[-2.1198535880636,52.8140936659049],"type":"Point"}
}