{
  "type": "Feature",
  "properties": {
    "iso:country":"GB",
    "wof:name":"SK16 4HQ",
    "wof:placetype":"postalcode"
},
  "geometry": {"coordinates":[-2.09140085586456,53.48311205777647],"type":"Point"}
}