{
  "type": "Feature",
  "properties": {
    "date:inception_lower": "1994-12-01",
    "date:inception_upper": "1994-12-01",
    "iso:country": "GB",
    "wof:name": "SK16 4HQ",
    "wof:placetype": "postalcode"
  },
  "geometry": {"coordinates":[-2.091401,53.483112],"type":"Point"}
}
