{
  "type": "Feature",
  "properties": {
    "iso:country":"GB",
    "wof:name":"BA11 6PG",
    "wof:placetype":"postalcode"
},
  "geometry": {"coordinates":[-2.2890101693671,51.28103997295988],"type":"Point"}
}