{
  "type": "Feature",
  "properties": {
    "date:inception_lower": "2001-06-01",
    "date:inception_upper": "2001-06-01",
    "iso:country": "GB",
    "wof:name": "BA11 6PG",
    "wof:placetype": "postalcode"
  },
  "geometry": {"coordinates":[-2.28895,51.281072],"type":"Point"}
}
