{
  "type": "Feature",
  "properties": {
    "iso:country": "GB",
    "wof:name": "BA11 6PG",
    "wof:placetype": "postalcode"
  },
  "geometry": {"coordinates":[-2.289007,51.281035],"type":"Point"}
}
