{
  "type": "Feature",
  "properties": {
    "date:inception_lower": "1980-01-01",
    "date:inception_upper": "1980-01-01",
    "iso:country": "GB",
    "wof:name": "LS27 7TR",
    "wof:placetype": "postalcode"
  },
  "geometry": {"coordinates":[-1.631086,53.760451],"type":"Point"}
}
