{
  "type": "Feature",
  "properties": {
    "iso:country":"GB",
    "wof:name":"LS27 7TR",
    "wof:placetype":"postalcode"
},
  "geometry": {"coordinates":[-1.63108576497862,53.76045123799281],"type":"Point"}
}