{
  "type": "Feature",
  "properties": {
    "iso:country": "GB",
    "wof:name": "LS27 7TR",
    "wof:placetype": "postalcode"
  },
  "geometry": {"coordinates":[-1.631086,53.760451],"type":"Point"}
}
