{
  "type": "Feature",
  "properties": {
    "iso:country":"GB",
    "wof:name":"G81 3JG",
    "wof:placetype":"postalcode"
},
  "geometry": {"coordinates":[-4.40915135718768,55.91723335964573],"type":"Point"}
}