{
  "type": "Feature",
  "properties": {
    "iso:country": "GB",
    "wof:name": "G81 3JG",
    "wof:placetype": "postalcode"
  },
  "geometry": {"coordinates":[-4.409151,55.917233],"type":"Point"}
}
