{
  "type": "Feature",
  "properties": {
    "iso:country": "GB",
    "wof:name": "NR21 0HX",
    "wof:placetype": "postalcode"
  },
  "geometry": {"coordinates":[0.902067,52.850325],"type":"Point"}
}
