{
  "type": "Feature",
  "properties": {
    "date:inception_lower": "2013-09-01",
    "date:inception_upper": "2013-09-01",
    "iso:country": "GB",
    "wof:name": "RG40 1RF",
    "wof:placetype": "postalcode"
  },
  "geometry": {"coordinates":[-0.831894,51.412145],"type":"Point"}
}
