{
  "type": "Feature",
  "properties": {
    "date:inception_lower": "2006-04-01",
    "date:inception_upper": "2006-04-01",
    "iso:country": "GB",
    "wof:name": "MK10 9QG",
    "wof:placetype": "postalcode"
  },
  "geometry": {"coordinates":[-0.692128,52.041326],"type":"Point"}
}
