{
  "type": "Feature",
  "properties": {
    "iso:country":"GB",
    "wof:name":"DA15 9BU",
    "wof:placetype":"postalcode"
},
  "geometry": {"coordinates":[0.10370262724396,51.43938275047741],"type":"Point"}
}