{
  "type": "Feature",
  "properties": {
    "iso:country":"GB",
    "wof:name":"WA10 4PQ",
    "wof:placetype":"postalcode"
},
  "geometry": {"coordinates":[-2.75891186467183,53.45285314090232],"type":"Point"}
}