{
  "type": "Feature",
  "properties": {
    "date:inception_lower": "2010-06-01",
    "date:inception_upper": "2010-06-01",
    "iso:country": "GB",
    "wof:name": "WA10 4PQ",
    "wof:placetype": "postalcode"
  },
  "geometry": {"coordinates":[-2.759096,53.452284],"type":"Point"}
}
