{
  "type": "Feature",
  "properties": {
    "iso:country": "GB",
    "wof:name": "WA10 4PQ",
    "wof:placetype": "postalcode"
  },
  "geometry": {"coordinates":[-2.758912,53.452853],"type":"Point"}
}
