{
  "type": "Feature",
  "properties": {
    "date:inception_lower": "1995-12-01",
    "date:inception_upper": "1995-12-01",
    "iso:country": "GB",
    "wof:name": "BA20 1RX",
    "wof:placetype": "postalcode"
  },
  "geometry": {"coordinates":[-2.632307,50.941683],"type":"Point"}
}
