{
  "type": "Feature",
  "properties": {
    "iso:country": "GB",
    "wof:name": "DH9 6NR",
    "wof:placetype": "postalcode"
  },
  "geometry": {"coordinates":[-1.693488,54.859738],"type":"Point"}
}
