{
  "type": "Feature",
  "properties": {
    "iso:country":"GB",
    "wof:name":"G12 0LE",
    "wof:placetype":"postalcode"
},
  "geometry": {"coordinates":[-4.30992368520637,55.89112111730994],"type":"Point"}
}