{
  "type": "Feature",
  "properties": {
    "iso:country":"GB",
    "wof:name":"NG7 7HD",
    "wof:placetype":"postalcode"
},
  "geometry": {"coordinates":[-1.16706758853307,52.97579705345223],"type":"Point"}
}