{
  "type": "Feature",
  "properties": {
    "iso:country": "GB",
    "wof:name": "BR5 2NP",
    "wof:placetype": "postalcode"
  },
  "geometry": {"coordinates":[0.097031,51.396444],"type":"Point"}
}
