{
  "type": "Feature",
  "properties": {
    "iso:country":"GB",
    "wof:name":"HX7 5DL",
    "wof:placetype":"postalcode"
},
  "geometry": {"coordinates":[-1.98459249711275,53.73195878527238],"type":"Point"}
}