{
  "type": "Feature",
  "properties": {
    "iso:country":"GB",
    "wof:name":"WF1 1RG",
    "wof:placetype":"postalcode"
},
  "geometry": {"coordinates":[-1.49722258877934,53.67928698145951],"type":"Point"}
}