{
  "type": "Feature",
  "properties": {
    "date:inception_lower": "2003-07-01",
    "date:inception_upper": "2003-07-01",
    "iso:country": "GB",
    "wof:name": "WF1 1RG",
    "wof:placetype": "postalcode"
  },
  "geometry": {"coordinates":[-1.497223,53.679287],"type":"Point"}
}
