{
  "type": "Feature",
  "properties": {
    "iso:country": "GB",
    "wof:name": "KT1 2JJ",
    "wof:placetype": "postalcode"
  },
  "geometry": {"coordinates":[-0.305144,51.404903],"type":"Point"}
}
