{
  "type": "Feature",
  "properties": {
    "date:inception_lower": "2023-10-01",
    "date:inception_upper": "2023-10-01",
    "iso:country": "GB",
    "wof:name": "S1 4UH",
    "wof:placetype": "postalcode"
  },
  "geometry": {"coordinates":[-1.471364,53.373846],"type":"Point"}
}
