{
  "type": "Feature",
  "properties": {
    "date:inception_lower": "1980-01-01",
    "date:inception_upper": "1980-01-01",
    "iso:country": "GB",
    "wof:name": "NE21 4PZ",
    "wof:placetype": "postalcode"
  },
  "geometry": {"coordinates":[-1.713834,54.962986],"type":"Point"}
}
