{
  "type": "Feature",
  "properties": {
    "date:inception_lower":"1990-07-01",
    "date:inception_upper":"1990-07-31",
    "iso:country":"GB",
    "wof:name":"E7 9AT",
    "wof:placetype":"postalcode"
},
  "geometry": {"coordinates":[0.021563,51.547995],"type":"Point"}
}