{
  "type": "Feature",
  "properties": {
    "iso:country":"GB",
    "wof:name":"E7 9AT",
    "wof:placetype":"postalcode"
},
  "geometry": {"coordinates":[0.02156307494351,51.54799456715124],"type":"Point"}
}