{
  "type": "Feature",
  "properties": {
    "iso:country": "GB",
    "wof:name": "CT13 9AD",
    "wof:placetype": "postalcode"
  },
  "geometry": {"coordinates":[1.339162,51.273749],"type":"Point"}
}
