{
  "type": "Feature",
  "properties": {
    "date:inception_lower": "1980-01-01",
    "date:inception_upper": "1980-01-01",
    "iso:country": "GB",
    "wof:name": "CT13 9AD",
    "wof:placetype": "postalcode"
  },
  "geometry": {"coordinates":[1.339162,51.273749],"type":"Point"}
}
