{
  "type": "Feature",
  "properties": {
    "iso:country":"GB",
    "wof:name":"HP16 0BD",
    "wof:placetype":"postalcode"
},
  "geometry": {"coordinates":[-0.70267183719397,51.70049632922746],"type":"Point"}
}