{
  "type": "Feature",
  "properties": {
    "date:inception_lower": "1980-01-01",
    "date:inception_upper": "1980-01-01",
    "iso:country": "GB",
    "wof:name": "IP13 9EA",
    "wof:placetype": "postalcode"
  },
  "geometry": {"coordinates":[1.342329,52.22032],"type":"Point"}
}
