{
  "type": "Feature",
  "properties": {
    "iso:country":"GB",
    "wof:name":"IP13 9EA",
    "wof:placetype":"postalcode"
},
  "geometry": {"coordinates":[1.34232919892924,52.22031981539494],"type":"Point"}
}