{
  "type": "Feature",
  "properties": {
    "iso:country":"GB",
    "wof:name":"NG6 8GL",
    "wof:placetype":"postalcode"
},
  "geometry": {"coordinates":[-1.19641688750932,53.00650908835006],"type":"Point"}
}