{
  "type": "Feature",
  "properties": {
    "date:inception_lower":"1980-01-01",
    "date:inception_upper":"1980-01-31",
    "iso:country":"GB",
    "wof:name":"NG6 8GL",
    "wof:placetype":"postalcode"
},
  "geometry": {"coordinates":[-1.196417,53.006509],"type":"Point"}
}