{
  "type": "Feature",
  "properties": {
    "iso:country": "GB",
    "wof:name": "ST10 3DQ",
    "wof:placetype": "postalcode"
  },
  "geometry": {"coordinates":[-1.921563,53.002751],"type":"Point"}
}
