{
  "type": "Feature",
  "properties": {
    "iso:country":"GB",
    "wof:name":"OL6 8QA",
    "wof:placetype":"postalcode"
},
  "geometry": {"coordinates":[-2.09021458980283,53.49924717918889],"type":"Point"}
}