{
  "type": "Feature",
  "properties": {
    "date:inception_lower": "1980-01-01",
    "date:inception_upper": "1980-01-01",
    "iso:country": "GB",
    "wof:name": "ML9 3NG",
    "wof:placetype": "postalcode"
  },
  "geometry": {"coordinates":[-3.975271,55.700967],"type":"Point"}
}
