{
  "type": "Feature",
  "properties": {
    "iso:country":"GB",
    "wof:name":"DG12 6PD",
    "wof:placetype":"postalcode"
},
  "geometry": {"coordinates":[-3.17085685702128,54.98517384976301],"type":"Point"}
}