{
  "type": "Feature",
  "properties": {
    "iso:country": "GB",
    "wof:name": "CV37 7PN",
    "wof:placetype": "postalcode"
  },
  "geometry": {"coordinates":[-1.607196,52.151023],"type":"Point"}
}
