{
  "type": "Feature",
  "properties": {
    "date:inception_lower":"1980-01-01",
    "date:inception_upper":"1980-01-31",
    "iso:country":"GB",
    "wof:name":"CV37 7PN",
    "wof:placetype":"postalcode"
},
  "geometry": {"coordinates":[-1.607196,52.151023],"type":"Point"}
}