{
  "type": "Feature",
  "properties": {
    "date:inception_lower": "2020-04-01",
    "date:inception_upper": "2020-04-01",
    "iso:country": "GB",
    "wof:name": "S20 4AF",
    "wof:placetype": "postalcode"
  },
  "geometry": {"coordinates":[-1.339361,53.32065],"type":"Point"}
}
