{
  "type": "Feature",
  "properties": {
    "iso:country": "GB",
    "wof:name": "S20 4AF",
    "wof:placetype": "postalcode"
  },
  "geometry": {"coordinates":[-1.339378,53.320534],"type":"Point"}
}
