{
  "type": "Feature",
  "properties": {
    "iso:country": "GB",
    "wof:name": "ML3 9FN",
    "wof:placetype": "postalcode"
  },
  "geometry": {"coordinates":[-4.054059,55.775222],"type":"Point"}
}
