{
  "type": "Feature",
  "properties": {
    "date:inception_lower": "2010-05-01",
    "date:inception_upper": "2010-05-01",
    "iso:country": "GB",
    "wof:name": "ML3 9FN",
    "wof:placetype": "postalcode"
  },
  "geometry": {"coordinates":[-4.053068,55.775388],"type":"Point"}
}
