{
  "type": "Feature",
  "properties": {
    "iso:country":"GB",
    "wof:name":"ML3 9FN",
    "wof:placetype":"postalcode"
},
  "geometry": {"coordinates":[-4.05405859649516,55.77522203599502],"type":"Point"}
}