{
  "type": "Feature",
  "properties": {
    "iso:country":"GB",
    "wof:name":"PE22 0BZ",
    "wof:placetype":"postalcode"
},
  "geometry": {"coordinates":[0.08386227748387,52.99866093782157],"type":"Point"}
}