{
  "type": "Feature",
  "properties": {
    "iso:country":"GB",
    "wof:name":"ML11 9SS",
    "wof:placetype":"postalcode"
},
  "geometry": {"coordinates":[-3.92215563406053,55.67361105316258],"type":"Point"}
}