{
  "type": "Feature",
  "properties": {
    "date:inception_lower": "1980-01-01",
    "date:inception_upper": "1980-01-01",
    "iso:country": "GB",
    "wof:name": "DN9 2LR",
    "wof:placetype": "postalcode"
  },
  "geometry": {"coordinates":[-0.817177,53.489147],"type":"Point"}
}
