{
  "type": "Feature",
  "properties": {
    "iso:country":"GB",
    "wof:name":"DN9 2LR",
    "wof:placetype":"postalcode"
},
  "geometry": {"coordinates":[-0.8168166141206,53.48898750402856],"type":"Point"}
}