{
  "type": "Feature",
  "properties": {
    "date:inception_lower": "2017-08-01",
    "date:inception_upper": "2017-08-01",
    "iso:country": "GB",
    "wof:name": "PL8 2FL",
    "wof:placetype": "postalcode"
  },
  "geometry": {"coordinates":[-4.042691,50.35049],"type":"Point"}
}
