{
  "type": "Feature",
  "properties": {
    "iso:country": "GB",
    "wof:name": "PL8 2FL",
    "wof:placetype": "postalcode"
  },
  "geometry": {"coordinates":[-4.042691,50.35049],"type":"Point"}
}
