{
  "type": "Feature",
  "properties": {
    "iso:country":"GB",
    "wof:name":"NG12 2AJ",
    "wof:placetype":"postalcode"
},
  "geometry": {"coordinates":[-1.03767650092103,52.94783366117493],"type":"Point"}
}