{
  "type": "Feature",
  "properties": {
    "iso:country":"GB",
    "wof:name":"BA2 1DJ",
    "wof:placetype":"postalcode"
},
  "geometry": {"coordinates":[-2.39632299993623,51.37871803372678],"type":"Point"}
}