{
  "type": "Feature",
  "properties": {
    "date:inception_lower":"1980-01-01",
    "date:inception_upper":"1980-01-31",
    "iso:country":"GB",
    "wof:name":"BA2 1DJ",
    "wof:placetype":"postalcode"
},
  "geometry": {"coordinates":[-2.396323,51.378718],"type":"Point"}
}