{
  "type": "Feature",
  "properties": {
    "date:inception_lower": "1980-01-01",
    "date:inception_upper": "1980-01-01",
    "iso:country": "GB",
    "wof:name": "CM6 3SG",
    "wof:placetype": "postalcode"
  },
  "geometry": {"coordinates":[0.413283,51.89217],"type":"Point"}
}
