{
  "type": "Feature",
  "properties": {
    "iso:country": "GB",
    "wof:name": "NN1 4LE",
    "wof:placetype": "postalcode"
  },
  "geometry": {"coordinates":[-0.881329,52.24758],"type":"Point"}
}
