{
  "type": "Feature",
  "properties": {
    "iso:country":"GB",
    "wof:name":"SG18 9BS",
    "wof:placetype":"postalcode"
},
  "geometry": {"coordinates":[-0.30777594994102,52.09893342083375],"type":"Point"}
}