{
  "type": "Feature",
  "properties": {
    "iso:country":"GB",
    "wof:name":"PA14 5HP",
    "wof:placetype":"postalcode"
},
  "geometry": {"coordinates":[-4.6956792418266,55.93410451919901],"type":"Point"}
}