{
  "type": "Feature",
  "properties": {
    "iso:country": "GB",
    "wof:name": "M33 2XL",
    "wof:placetype": "postalcode"
  },
  "geometry": {"coordinates":[-2.299002,53.409363],"type":"Point"}
}
