{
  "type": "Feature",
  "properties": {
    "date:inception_lower": "1992-01-01",
    "date:inception_upper": "1992-01-01",
    "iso:country": "GB",
    "wof:name": "M33 2XL",
    "wof:placetype": "postalcode"
  },
  "geometry": {"coordinates":[-2.299002,53.409363],"type":"Point"}
}
