{
  "type": "Feature",
  "properties": {
    "iso:country":"GB",
    "wof:name":"M33 2XL",
    "wof:placetype":"postalcode"
},
  "geometry": {"coordinates":[-2.29900223400698,53.40936328057535],"type":"Point"}
}