{
  "type": "Feature",
  "properties": {
    "iso:country":"GB",
    "wof:name":"HD2 2BJ",
    "wof:placetype":"postalcode"
},
  "geometry": {"coordinates":[-1.79908108455043,53.65719929321235],"type":"Point"}
}