{
  "type": "Feature",
  "properties": {
    "iso:country":"GB",
    "wof:name":"OL2 7QU",
    "wof:placetype":"postalcode"
},
  "geometry": {"coordinates":[-2.10635141148145,53.58600736361585],"type":"Point"}
}