{
  "type": "Feature",
  "properties": {
    "date:inception_lower": "1980-01-01",
    "date:inception_upper": "1980-01-01",
    "iso:country": "GB",
    "wof:name": "TS5 6AU",
    "wof:placetype": "postalcode"
  },
  "geometry": {"coordinates":[-1.246076,54.563008],"type":"Point"}
}
