{
  "type": "Feature",
  "properties": {
    "iso:country":"GB",
    "wof:name":"DY8 5YN",
    "wof:placetype":"postalcode"
},
  "geometry": {"coordinates":[-2.15291781493452,52.47371394961379],"type":"Point"}
}