{
  "type": "Feature",
  "properties": {
    "date:inception_lower":"1980-01-01",
    "date:inception_upper":"1980-01-31",
    "iso:country":"GB",
    "wof:name":"EN9 3EQ",
    "wof:placetype":"postalcode"
},
  "geometry": {"coordinates":[0.022527,51.688298],"type":"Point"}
}