{
  "type": "Feature",
  "properties": {
    "iso:country":"GB",
    "wof:name":"EN9 3EQ",
    "wof:placetype":"postalcode"
},
  "geometry": {"coordinates":[0.02252726369296,51.6882978508999],"type":"Point"}
}