{
  "type": "Feature",
  "properties": {
    "iso:country":"GB",
    "wof:name":"SE5 0NP",
    "wof:placetype":"postalcode"
},
  "geometry": {"coordinates":[-0.09648136751056,51.48288482558459],"type":"Point"}
}