{
  "type": "Feature",
  "properties": {
    "date:inception_lower": "1980-01-01",
    "date:inception_upper": "1980-01-01",
    "iso:country": "GB",
    "wof:name": "G20 9AN",
    "wof:placetype": "postalcode"
  },
  "geometry": {"coordinates":[-4.288771,55.891196],"type":"Point"}
}
