{
  "type": "Feature",
  "properties": {
    "iso:country": "GB",
    "wof:name": "YO26 7QT",
    "wof:placetype": "postalcode"
  },
  "geometry": {"coordinates":[-1.294306,53.96805],"type":"Point"}
}
