{
  "type": "Feature",
  "properties": {
    "iso:country":"GB",
    "wof:name":"YO26 7QT",
    "wof:placetype":"postalcode"
},
  "geometry": {"coordinates":[-1.2943057420564,53.96804980446976],"type":"Point"}
}