{
  "type": "Feature",
  "properties": {
    "iso:country": "GB",
    "wof:name": "DE1 3QG",
    "wof:placetype": "postalcode"
  },
  "geometry": {"coordinates":[-1.470928,52.930909],"type":"Point"}
}
