{
  "type": "Feature",
  "properties": {
    "iso:country":"GB",
    "wof:name":"DE1 3QG",
    "wof:placetype":"postalcode"
},
  "geometry": {"coordinates":[-1.47092793847463,52.93090925298481],"type":"Point"}
}