{
  "type": "Feature",
  "properties": {
    "iso:country": "GB",
    "wof:name": "NN11 0XQ",
    "wof:placetype": "postalcode"
  },
  "geometry": {"coordinates":[-1.160823,52.267566],"type":"Point"}
}
