{
  "type": "Feature",
  "properties": {
    "iso:country": "GB",
    "wof:name": "DE7 8RH",
    "wof:placetype": "postalcode"
  },
  "geometry": {"coordinates":[-1.32309,52.988295],"type":"Point"}
}
