{
  "type": "Feature",
  "properties": {
    "date:inception_lower": "1980-01-01",
    "date:inception_upper": "1980-01-01",
    "iso:country": "GB",
    "wof:name": "NE65 7BU",
    "wof:placetype": "postalcode"
  },
  "geometry": {"coordinates":[-2.180046,55.424265],"type":"Point"}
}
