{
  "type": "Feature",
  "properties": {
    "iso:country": "GB",
    "wof:name": "NE65 7BU",
    "wof:placetype": "postalcode"
  },
  "geometry": {"coordinates":[-2.180046,55.424265],"type":"Point"}
}
