{
  "type": "Feature",
  "properties": {
    "iso:country":"GB",
    "wof:name":"NE65 7BU",
    "wof:placetype":"postalcode"
},
  "geometry": {"coordinates":[-2.18229467992436,55.42375671077642],"type":"Point"}
}