{
  "type": "Feature",
  "properties": {
    "iso:country":"GB",
    "wof:name":"FY4 5HL",
    "wof:placetype":"postalcode"
},
  "geometry": {"coordinates":[-3.0126697274585,53.78624747518683],"type":"Point"}
}