{
  "type": "Feature",
  "properties": {
    "date:inception_lower": "1980-01-01",
    "date:inception_upper": "1980-01-01",
    "iso:country": "GB",
    "wof:name": "FY4 5HL",
    "wof:placetype": "postalcode"
  },
  "geometry": {"coordinates":[-3.012542,53.786128],"type":"Point"}
}
