{
  "type": "Feature",
  "properties": {
    "date:inception_lower":"1980-01-01",
    "date:inception_upper":"1980-01-31",
    "iso:country":"GB",
    "wof:name":"PO8 8AB",
    "wof:placetype":"postalcode"
},
  "geometry": {"coordinates":[-1.017203,50.89277],"type":"Point"}
}