{
  "type": "Feature",
  "properties": {
    "iso:country":"GB",
    "wof:name":"G77 6EG",
    "wof:placetype":"postalcode"
},
  "geometry": {"coordinates":[-4.31934137902024,55.78033313930398],"type":"Point"}
}