{
  "type": "Feature",
  "properties": {
    "iso:country":"GB",
    "wof:name":"TD12 4NS",
    "wof:placetype":"postalcode"
},
  "geometry": {"coordinates":[-2.24863693140929,55.65477081860428],"type":"Point"}
}