{
  "type": "Feature",
  "properties": {
    "iso:country":"GB",
    "wof:name":"PL4 7AU",
    "wof:placetype":"postalcode"
},
  "geometry": {"coordinates":[-4.12504614155572,50.38309896794088],"type":"Point"}
}