{
  "type": "Feature",
  "properties": {
    "iso:country": "GB",
    "wof:name": "PO15 6RR",
    "wof:placetype": "postalcode"
  },
  "geometry": {"coordinates":[-1.228074,50.872223],"type":"Point"}
}
