{
  "type": "Feature",
  "properties": {
    "date:inception_lower": "1980-01-01",
    "date:inception_upper": "1980-01-01",
    "iso:country": "GB",
    "wof:name": "PO15 6RR",
    "wof:placetype": "postalcode"
  },
  "geometry": {"coordinates":[-1.228724,50.871679],"type":"Point"}
}
