{
  "type": "Feature",
  "properties": {
    "iso:country":"GB",
    "wof:name":"LS15 8AX",
    "wof:placetype":"postalcode"
},
  "geometry": {"coordinates":[-1.44914061335607,53.80801077709486],"type":"Point"}
}