{
  "type": "Feature",
  "properties": {
    "iso:country": "GB",
    "wof:name": "DE72 3AA",
    "wof:placetype": "postalcode"
  },
  "geometry": {"coordinates":[-1.310802,52.900065],"type":"Point"}
}
