{
  "type": "Feature",
  "properties": {
    "date:inception_lower": "2003-09-01",
    "date:inception_upper": "2003-09-01",
    "iso:country": "GB",
    "wof:name": "TA2 8ZQ",
    "wof:placetype": "postalcode"
  },
  "geometry": {"coordinates":[-3.109646,51.023442],"type":"Point"}
}
