{
  "type": "Feature",
  "properties": {
    "iso:country": "GB",
    "wof:name": "ME2 3EH",
    "wof:placetype": "postalcode"
  },
  "geometry": {"coordinates":[0.492493,51.398348],"type":"Point"}
}
