{
  "type": "Feature",
  "properties": {
    "iso:country": "GB",
    "wof:name": "BR6 9HQ",
    "wof:placetype": "postalcode"
  },
  "geometry": {"coordinates":[0.108944,51.362588],"type":"Point"}
}
