{
  "type": "Feature",
  "properties": {
    "iso:country":"GB",
    "wof:name":"BR6 9HQ",
    "wof:placetype":"postalcode"
},
  "geometry": {"coordinates":[0.10894419083878,51.36258758232799],"type":"Point"}
}