{
  "type": "Feature",
  "properties": {
    "date:inception_lower": "2007-10-01",
    "date:inception_upper": "2007-10-01",
    "iso:country": "GB",
    "wof:name": "CO8 5FL",
    "wof:placetype": "postalcode"
  },
  "geometry": {"coordinates":[0.779561,51.972384],"type":"Point"}
}
