{
  "type": "Feature",
  "properties": {
    "iso:country":"GB",
    "wof:name":"CO8 5FL",
    "wof:placetype":"postalcode"
},
  "geometry": {"coordinates":[0.77952683244176,51.97235445966681],"type":"Point"}
}