{
  "type": "Feature",
  "properties": {
    "iso:country": "GB",
    "wof:name": "NG16 6QD",
    "wof:placetype": "postalcode"
  },
  "geometry": {"coordinates":[-1.324121,53.095182],"type":"Point"}
}
