{
  "type": "Feature",
  "properties": {
    "iso:country":"GB",
    "wof:name":"NG16 6QD",
    "wof:placetype":"postalcode"
},
  "geometry": {"coordinates":[-1.32412101010922,53.09518216434938],"type":"Point"}
}