{
  "type": "Feature",
  "properties": {
    "iso:country":"GB",
    "wof:name":"NW3 1HG",
    "wof:placetype":"postalcode"
},
  "geometry": {"coordinates":[-0.17650519624958,51.55713035051502],"type":"Point"}
}