{
  "type": "Feature",
  "properties": {
    "iso:country":"GB",
    "wof:name":"LD1 5HE",
    "wof:placetype":"postalcode"
},
  "geometry": {"coordinates":[-3.37893691480264,52.23871001588468],"type":"Point"}
}