{
  "type": "Feature",
  "properties": {
    "iso:country":"GB",
    "wof:name":"BN16 2JP",
    "wof:placetype":"postalcode"
},
  "geometry": {"coordinates":[-0.50551015421342,50.8044425443488],"type":"Point"}
}