{
  "type": "Feature",
  "properties": {
    "iso:country":"GB",
    "wof:name":"TR1 1EZ",
    "wof:placetype":"postalcode"
},
  "geometry": {"coordinates":[-5.04974914006631,50.26529732596562],"type":"Point"}
}