{
  "type": "Feature",
  "properties": {
    "iso:country":"GB",
    "wof:name":"PA8 6BN",
    "wof:placetype":"postalcode"
},
  "geometry": {"coordinates":[-4.4652994412601,55.90922796387446],"type":"Point"}
}