{
  "type": "Feature",
  "properties": {
    "iso:country":"GB",
    "wof:name":"OX1 9SD",
    "wof:placetype":"postalcode"
},
  "geometry": {"coordinates":[-1.25803504119987,51.75128750460173],"type":"Point"}
}