{
  "type": "Feature",
  "properties": {
    "iso:country":"GB",
    "wof:name":"L25 9PF",
    "wof:placetype":"postalcode"
},
  "geometry": {"coordinates":[-2.85085152203198,53.37098355824385],"type":"Point"}
}