{
  "type": "Feature",
  "properties": {
    "iso:country":"GB",
    "wof:name":"OX27 7NZ",
    "wof:placetype":"postalcode"
},
  "geometry": {"coordinates":[-1.21599523233829,51.94774049187853],"type":"Point"}
}