{
  "type": "Feature",
  "properties": {
    "iso:country": "GB",
    "wof:name": "OX27 7NZ",
    "wof:placetype": "postalcode"
  },
  "geometry": {"coordinates":[-1.215995,51.94774],"type":"Point"}
}
