{
  "type": "Feature",
  "properties": {
    "date:inception_lower": "2000-10-01",
    "date:inception_upper": "2000-10-01",
    "iso:country": "GB",
    "wof:name": "OX27 7NZ",
    "wof:placetype": "postalcode"
  },
  "geometry": {"coordinates":[-1.215995,51.94774],"type":"Point"}
}
