{
  "type": "Feature",
  "properties": {
    "date:inception_lower": "2015-09-01",
    "date:inception_upper": "2015-09-01",
    "iso:country": "GB",
    "wof:name": "HU15 2FU",
    "wof:placetype": "postalcode"
  },
  "geometry": {"coordinates":[-0.652529,53.779937],"type":"Point"}
}
