{
  "type": "Feature",
  "properties": {
    "iso:country":"GB",
    "wof:name":"HU15 2FU",
    "wof:placetype":"postalcode"
},
  "geometry": {"coordinates":[-0.65232098965717,53.77980908359948],"type":"Point"}
}