{
  "type": "Feature",
  "properties": {
    "iso:country":"GB",
    "wof:name":"EX34 9NF",
    "wof:placetype":"postalcode"
},
  "geometry": {"coordinates":[-4.11084796728069,51.20448960392959],"type":"Point"}
}