{
  "type": "Feature",
  "properties": {
    "iso:country":"GB",
    "wof:name":"SG1 2QE",
    "wof:placetype":"postalcode"
},
  "geometry": {"coordinates":[-0.22221802622704,51.91111375595324],"type":"Point"}
}