{
  "type": "Feature",
  "properties": {
    "date:inception_lower":"1980-01-01",
    "date:inception_upper":"1980-01-31",
    "iso:country":"GB",
    "wof:name":"SN4 0NG",
    "wof:placetype":"postalcode"
},
  "geometry": {"coordinates":[-1.731151,51.516499],"type":"Point"}
}