{
  "type": "Feature",
  "properties": {
    "date:inception_lower": "1980-01-01",
    "date:inception_upper": "1980-01-01",
    "iso:country": "GB",
    "wof:name": "PA33 1BU",
    "wof:placetype": "postalcode"
  },
  "geometry": {"coordinates":[-5.298766,56.215939],"type":"Point"}
}
