{
  "type": "Feature",
  "properties": {
    "iso:country":"GB",
    "wof:name":"PA33 1BU",
    "wof:placetype":"postalcode"
},
  "geometry": {"coordinates":[-5.30149009902075,56.21602180161873],"type":"Point"}
}