{
  "type": "Feature",
  "properties": {
    "iso:country":"GB",
    "wof:name":"LE15 6RT",
    "wof:placetype":"postalcode"
},
  "geometry": {"coordinates":[-0.73772866480529,52.66629057887625],"type":"Point"}
}