{
  "type": "Feature",
  "properties": {
    "iso:country": "GB",
    "wof:name": "LE15 6RT",
    "wof:placetype": "postalcode"
  },
  "geometry": {"coordinates":[-0.737729,52.666291],"type":"Point"}
}
