{
  "type": "Feature",
  "properties": {
    "date:inception_lower": "2008-02-01",
    "date:inception_upper": "2008-02-01",
    "iso:country": "GB",
    "wof:name": "TD15 1TB",
    "wof:placetype": "postalcode"
  },
  "geometry": {"coordinates":[-2.018833,55.789327],"type":"Point"}
}
