{
  "type": "Feature",
  "properties": {
    "iso:country":"GB",
    "wof:name":"EC4N 6HL",
    "wof:placetype":"postalcode"
},
  "geometry": {"coordinates":[-0.08978967091535,51.51135444688776],"type":"Point"}
}