{
  "type": "Feature",
  "properties": {
    "iso:country":"GB",
    "wof:name":"DN22 6NP",
    "wof:placetype":"postalcode"
},
  "geometry": {"coordinates":[-0.9326023872284,53.32240567518826],"type":"Point"}
}