{
  "type": "Feature",
  "properties": {
    "date:inception_lower":"1992-05-01",
    "date:inception_upper":"1992-05-31",
    "iso:country":"GB",
    "wof:name":"DG12 5PW",
    "wof:placetype":"postalcode"
},
  "geometry": {"coordinates":[-3.33026,54.980452],"type":"Point"}
}