{
  "type": "Feature",
  "properties": {
    "date:inception_lower": "1998-06-01",
    "date:inception_upper": "1998-06-01",
    "iso:country": "GB",
    "wof:name": "TR4 8GG",
    "wof:placetype": "postalcode"
  },
  "geometry": {"coordinates":[-5.126154,50.261709],"type":"Point"}
}
