{
  "type": "Feature",
  "properties": {
    "iso:country":"GB",
    "wof:name":"TR4 8GG",
    "wof:placetype":"postalcode"
},
  "geometry": {"coordinates":[-5.12615412076016,50.26170908755579],"type":"Point"}
}