{
  "type": "Feature",
  "properties": {
    "iso:country":"GB",
    "wof:name":"DL12 9EY",
    "wof:placetype":"postalcode"
},
  "geometry": {"coordinates":[-2.03846715704272,54.58830994526911],"type":"Point"}
}