{
  "type": "Feature",
  "properties": {
    "iso:country":"GB",
    "wof:name":"TA7 0HW",
    "wof:placetype":"postalcode"
},
  "geometry": {"coordinates":[-2.93317426706253,51.11095232349555],"type":"Point"}
}