{
  "type": "Feature",
  "properties": {
    "date:inception_lower": "1985-10-01",
    "date:inception_upper": "1985-10-01",
    "iso:country": "GB",
    "wof:name": "TA7 0HW",
    "wof:placetype": "postalcode"
  },
  "geometry": {"coordinates":[-2.933168,51.110947],"type":"Point"}
}
