{
  "type": "Feature",
  "properties": {
    "iso:country": "GB",
    "wof:name": "TA7 0HW",
    "wof:placetype": "postalcode"
  },
  "geometry": {"coordinates":[-2.933174,51.110952],"type":"Point"}
}
