{
  "type": "Feature",
  "properties": {
    "iso:country":"GB",
    "wof:name":"SY8 2DJ",
    "wof:placetype":"postalcode"
},
  "geometry": {"coordinates":[-2.75858240150219,52.44693503946269],"type":"Point"}
}