{
  "type": "Feature",
  "properties": {
    "iso:country": "GB",
    "wof:name": "SY8 2DJ",
    "wof:placetype": "postalcode"
  },
  "geometry": {"coordinates":[-2.758582,52.446935],"type":"Point"}
}
