{
  "type": "Feature",
  "properties": {
    "date:inception_lower": "1980-01-01",
    "date:inception_upper": "1980-01-01",
    "iso:country": "GB",
    "wof:name": "L17 3BB",
    "wof:placetype": "postalcode"
  },
  "geometry": {"coordinates":[-2.939217,53.390294],"type":"Point"}
}
