{
  "type": "Feature",
  "properties": {
    "iso:country":"GB",
    "wof:name":"TR15 1EY",
    "wof:placetype":"postalcode"
},
  "geometry": {"coordinates":[-5.22795733623077,50.24209180716277],"type":"Point"}
}