{
  "type": "Feature",
  "properties": {
    "iso:country":"GB",
    "wof:name":"PA1 3TX",
    "wof:placetype":"postalcode"
},
  "geometry": {"coordinates":[-4.40000098956076,55.85229570883877],"type":"Point"}
}