{
  "type": "Feature",
  "properties": {
    "iso:country": "GB",
    "wof:name": "LS7 3LX",
    "wof:placetype": "postalcode"
  },
  "geometry": {"coordinates":[-1.534467,53.823229],"type":"Point"}
}
