{
  "type": "Feature",
  "properties": {
    "iso:country":"GB",
    "wof:name":"MK4 2HF",
    "wof:placetype":"postalcode"
},
  "geometry": {"coordinates":[-0.77849325820183,52.00903063119041],"type":"Point"}
}