{
  "type": "Feature",
  "properties": {
    "iso:country": "GB",
    "wof:name": "CB24 3ER",
    "wof:placetype": "postalcode"
  },
  "geometry": {"coordinates":[0.040611,52.286399],"type":"Point"}
}
