{
  "type": "Feature",
  "properties": {
    "iso:country":"GB",
    "wof:name":"RM8 1ND",
    "wof:placetype":"postalcode"
},
  "geometry": {"coordinates":[0.14792854101499,51.56609059054143],"type":"Point"}
}