{
  "type": "Feature",
  "properties": {
    "date:inception_lower": "1980-01-01",
    "date:inception_upper": "1980-01-01",
    "iso:country": "GB",
    "wof:name": "RM8 1ND",
    "wof:placetype": "postalcode"
  },
  "geometry": {"coordinates":[0.147929,51.566091],"type":"Point"}
}
