{
  "type": "Feature",
  "properties": {
    "iso:country":"GB",
    "wof:name":"KT22 7SJ",
    "wof:placetype":"postalcode"
},
  "geometry": {"coordinates":[-0.33174450405251,51.29830034044645],"type":"Point"}
}