{
  "type": "Feature",
  "properties": {
    "iso:country":"GB",
    "wof:name":"HP1 3QA",
    "wof:placetype":"postalcode"
},
  "geometry": {"coordinates":[-0.49982157248168,51.76434213792503],"type":"Point"}
}