{
  "type": "Feature",
  "properties": {
    "date:inception_lower": "1985-04-01",
    "date:inception_upper": "1985-04-01",
    "iso:country": "GB",
    "wof:name": "DH8 7TS",
    "wof:placetype": "postalcode"
  },
  "geometry": {"coordinates":[-1.79751,54.861249],"type":"Point"}
}
