{
  "type": "Feature",
  "properties": {
    "date:inception_lower": "2007-03-01",
    "date:inception_upper": "2007-03-01",
    "iso:country": "GB",
    "wof:name": "B31 1JU",
    "wof:placetype": "postalcode"
  },
  "geometry": {"coordinates":[-1.984265,52.423315],"type":"Point"}
}
