{
  "type": "Feature",
  "properties": {
    "iso:country":"GB",
    "wof:name":"CM11 2XJ",
    "wof:placetype":"postalcode"
},
  "geometry": {"coordinates":[0.46859966346711,51.60204009951759],"type":"Point"}
}