{
  "type": "Feature",
  "properties": {
    "iso:country":"GB",
    "wof:name":"SK4 2AE",
    "wof:placetype":"postalcode"
},
  "geometry": {"coordinates":[-2.1859651079091,53.41204691621972],"type":"Point"}
}