{
  "type": "Feature",
  "properties": {
    "iso:country":"GB",
    "wof:name":"SR3 1BF",
    "wof:placetype":"postalcode"
},
  "geometry": {"coordinates":[-1.40418421577146,54.8779307454303],"type":"Point"}
}