{
  "type": "Feature",
  "properties": {
    "date:inception_lower":"2009-09-01",
    "date:inception_upper":"2009-09-30",
    "iso:country":"GB",
    "wof:name":"SR3 1BF",
    "wof:placetype":"postalcode"
},
  "geometry": {"coordinates":[-1.404184,54.877931],"type":"Point"}
}