{
  "type": "Feature",
  "properties": {
    "iso:country":"GB",
    "wof:name":"TN26 2JB",
    "wof:placetype":"postalcode"
},
  "geometry": {"coordinates":[0.85791863637824,51.06189836055616],"type":"Point"}
}