{
  "type": "Feature",
  "properties": {
    "iso:country": "GB",
    "wof:name": "BH15 3NL",
    "wof:placetype": "postalcode"
  },
  "geometry": {"coordinates":[-1.958046,50.73576],"type":"Point"}
}
