{
  "type": "Feature",
  "properties": {
    "iso:country":"GB",
    "wof:name":"S18 1WL",
    "wof:placetype":"postalcode"
},
  "geometry": {"coordinates":[-1.46500392300091,53.2984290261557],"type":"Point"}
}