{
  "type": "Feature",
  "properties": {
    "iso:country":"GB",
    "wof:name":"NE4 7NL",
    "wof:placetype":"postalcode"
},
  "geometry": {"coordinates":[-1.63988229925939,54.96313138044776],"type":"Point"}
}