{
  "type": "Feature",
  "properties": {
    "date:inception_lower":"1995-12-01",
    "date:inception_upper":"1995-12-31",
    "iso:country":"GB",
    "wof:name":"SS6 9TQ",
    "wof:placetype":"postalcode"
},
  "geometry": {"coordinates":[0.583333,51.589992],"type":"Point"}
}