{
  "type": "Feature",
  "properties": {
    "iso:country": "GB",
    "wof:name": "SS6 9TQ",
    "wof:placetype": "postalcode"
  },
  "geometry": {"coordinates":[0.583333,51.589992],"type":"Point"}
}
