{
  "type": "Feature",
  "properties": {
    "iso:country":"GB",
    "wof:name":"NE65 8TQ",
    "wof:placetype":"postalcode"
},
  "geometry": {"coordinates":[-1.73849368633194,55.24914787922659],"type":"Point"}
}