{
  "type": "Feature",
  "properties": {
    "iso:country":"GB",
    "wof:name":"PO7 5ER",
    "wof:placetype":"postalcode"
},
  "geometry": {"coordinates":[-1.04461694514199,50.86354605527369],"type":"Point"}
}