{
  "type": "Feature",
  "properties": {
    "iso:country": "GB",
    "wof:name": "PO7 5ER",
    "wof:placetype": "postalcode"
  },
  "geometry": {"coordinates":[-1.044617,50.863546],"type":"Point"}
}
