{
  "type": "Feature",
  "properties": {
    "date:inception_lower": "1993-08-01",
    "date:inception_upper": "1993-08-01",
    "iso:country": "GB",
    "wof:name": "E13 9HD",
    "wof:placetype": "postalcode"
  },
  "geometry": {"coordinates":[0.029239,51.527351],"type":"Point"}
}
