{
  "type": "Feature",
  "properties": {
    "iso:country": "GB",
    "wof:name": "DE55 5LJ",
    "wof:placetype": "postalcode"
  },
  "geometry": {"coordinates":[-1.333478,53.146806],"type":"Point"}
}
