{
  "type": "Feature",
  "properties": {
    "iso:country": "GB",
    "wof:name": "HP22 4LU",
    "wof:placetype": "postalcode"
  },
  "geometry": {"coordinates":[-0.767756,51.871702],"type":"Point"}
}
