{
  "type": "Feature",
  "properties": {
    "iso:country": "GB",
    "wof:name": "WS14 9UA",
    "wof:placetype": "postalcode"
  },
  "geometry": {"coordinates":[-1.8059,52.682488],"type":"Point"}
}
