{
  "type": "Feature",
  "properties": {
    "iso:country":"GB",
    "wof:name":"PE1 4RF",
    "wof:placetype":"postalcode"
},
  "geometry": {"coordinates":[-0.22056779908818,52.58857226011326],"type":"Point"}
}