{
  "type": "Feature",
  "properties": {
    "date:inception_lower": "1999-06-01",
    "date:inception_upper": "1999-06-01",
    "iso:country": "GB",
    "wof:name": "CH63 2HB",
    "wof:placetype": "postalcode"
  },
  "geometry": {"coordinates":[-3.022086,53.350125],"type":"Point"}
}
