{
  "type": "Feature",
  "properties": {
    "iso:country":"GB",
    "wof:name":"B80 7DH",
    "wof:placetype":"postalcode"
},
  "geometry": {"coordinates":[-1.87550376826665,52.30359221158626],"type":"Point"}
}