{
  "type": "Feature",
  "properties": {
    "iso:country":"GB",
    "wof:name":"BL0 9YU",
    "wof:placetype":"postalcode"
},
  "geometry": {"coordinates":[-2.31772847585907,53.6346184384403],"type":"Point"}
}