{
  "type": "Feature",
  "properties": {
    "date:inception_lower":"1980-01-01",
    "date:inception_upper":"1980-01-31",
    "iso:country":"GB",
    "wof:name":"DN31 2SB",
    "wof:placetype":"postalcode"
},
  "geometry": {"coordinates":[-0.100881,53.572413],"type":"Point"}
}