{
  "type": "Feature",
  "properties": {
    "iso:country":"GB",
    "wof:name":"DT4 9AR",
    "wof:placetype":"postalcode"
},
  "geometry": {"coordinates":[-2.47502707522657,50.59140800852727],"type":"Point"}
}