{
  "type": "Feature",
  "properties": {
    "iso:country": "GB",
    "wof:name": "DT4 9AR",
    "wof:placetype": "postalcode"
  },
  "geometry": {"coordinates":[-2.475027,50.591408],"type":"Point"}
}
