{
  "type": "Feature",
  "properties": {
    "iso:country":"GB",
    "wof:name":"RG18 9RB",
    "wof:placetype":"postalcode"
},
  "geometry": {"coordinates":[-1.26819952965714,51.4550732369301],"type":"Point"}
}