{
  "type": "Feature",
  "properties": {
    "iso:country": "GB",
    "wof:name": "CR6 9PR",
    "wof:placetype": "postalcode"
  },
  "geometry": {"coordinates":[-0.055063,51.312674],"type":"Point"}
}
