{
  "type": "Feature",
  "properties": {
    "date:inception_lower": "1993-01-01",
    "date:inception_upper": "1993-01-01",
    "iso:country": "GB",
    "wof:name": "CR6 9PR",
    "wof:placetype": "postalcode"
  },
  "geometry": {"coordinates":[-0.055063,51.312674],"type":"Point"}
}
