{
  "type": "Feature",
  "properties": {
    "iso:country":"GB",
    "wof:name":"HP4 3RQ",
    "wof:placetype":"postalcode"
},
  "geometry": {"coordinates":[-0.59164623802826,51.76873307682208],"type":"Point"}
}