{
  "type": "Feature",
  "properties": {
    "iso:country": "GB",
    "wof:name": "HP4 3RQ",
    "wof:placetype": "postalcode"
  },
  "geometry": {"coordinates":[-0.591646,51.768733],"type":"Point"}
}
