{
  "type": "Feature",
  "properties": {
    "iso:country":"GB",
    "wof:name":"TW3 3RT",
    "wof:placetype":"postalcode"
},
  "geometry": {"coordinates":[-0.37026497666943,51.4631977612816],"type":"Point"}
}