{
  "type": "Feature",
  "properties": {
    "iso:country": "GB",
    "wof:name": "WV10 8LX",
    "wof:placetype": "postalcode"
  },
  "geometry": {"coordinates":[-2.097453,52.616451],"type":"Point"}
}
