{
  "type": "Feature",
  "properties": {
    "iso:country":"GB",
    "wof:name":"GL17 9TJ",
    "wof:placetype":"postalcode"
},
  "geometry": {"coordinates":[-2.55547798453442,51.85518992306823],"type":"Point"}
}