{
  "type": "Feature",
  "properties": {
    "iso:country":"GB",
    "wof:name":"EN8 9HD",
    "wof:placetype":"postalcode"
},
  "geometry": {"coordinates":[-0.02666368747468,51.70425982303444],"type":"Point"}
}