{
  "type": "Feature",
  "properties": {
    "iso:country":"GB",
    "wof:name":"WR2 4LX",
    "wof:placetype":"postalcode"
},
  "geometry": {"coordinates":[-2.23367741040439,52.18059983951133],"type":"Point"}
}