{
  "type": "Feature",
  "properties": {
    "date:inception_lower": "1980-01-01",
    "date:inception_upper": "1980-01-01",
    "iso:country": "GB",
    "wof:name": "WR2 4LX",
    "wof:placetype": "postalcode"
  },
  "geometry": {"coordinates":[-2.233677,52.1806],"type":"Point"}
}
