{
  "type": "Feature",
  "properties": {
    "iso:country": "GB",
    "wof:name": "NG2 3NG",
    "wof:placetype": "postalcode"
  },
  "geometry": {"coordinates":[-1.144604,52.948148],"type":"Point"}
}
