{
  "type": "Feature",
  "properties": {
    "iso:country":"GB",
    "wof:name":"NG2 3NG",
    "wof:placetype":"postalcode"
},
  "geometry": {"coordinates":[-1.14460441689552,52.94814771648826],"type":"Point"}
}