{
  "type": "Feature",
  "properties": {
    "date:inception_lower":"1990-07-01",
    "date:inception_upper":"1990-07-31",
    "iso:country":"GB",
    "wof:name":"SA12 6DG",
    "wof:placetype":"postalcode"
},
  "geometry": {"coordinates":[-3.798168,51.591144],"type":"Point"}
}