{
  "type": "Feature",
  "properties": {
    "iso:country": "GB",
    "wof:name": "SA12 6DG",
    "wof:placetype": "postalcode"
  },
  "geometry": {"coordinates":[-3.798168,51.591144],"type":"Point"}
}
