{
  "type": "Feature",
  "properties": {
    "iso:country":"GB",
    "wof:name":"SA12 6DG",
    "wof:placetype":"postalcode"
},
  "geometry": {"coordinates":[-3.79816818577165,51.59114449591734],"type":"Point"}
}