{
  "type": "Feature",
  "properties": {
    "iso:country":"GB",
    "wof:name":"ST6 6PH",
    "wof:placetype":"postalcode"
},
  "geometry": {"coordinates":[-2.17767634609133,53.06533403557048],"type":"Point"}
}