{
  "type": "Feature",
  "properties": {
    "iso:country": "GB",
    "wof:name": "ST6 6PH",
    "wof:placetype": "postalcode"
  },
  "geometry": {"coordinates":[-2.177676,53.065334],"type":"Point"}
}
