{
  "type": "Feature",
  "properties": {
    "date:inception_lower": "1980-01-01",
    "date:inception_upper": "1980-01-01",
    "iso:country": "GB",
    "wof:name": "SA48 8HB",
    "wof:placetype": "postalcode"
  },
  "geometry": {"coordinates":[-4.034319,52.077774],"type":"Point"}
}
