{
  "type": "Feature",
  "properties": {
    "iso:country": "GB",
    "wof:name": "SA48 8HB",
    "wof:placetype": "postalcode"
  },
  "geometry": {"coordinates":[-4.034319,52.077774],"type":"Point"}
}
