{
  "type": "Feature",
  "properties": {
    "iso:country":"GB",
    "wof:name":"SA48 8HB",
    "wof:placetype":"postalcode"
},
  "geometry": {"coordinates":[-4.03171085919649,52.07691763841429],"type":"Point"}
}