{
  "type": "Feature",
  "properties": {
    "iso:country":"GB",
    "wof:name":"TD6 9BE",
    "wof:placetype":"postalcode"
},
  "geometry": {"coordinates":[-2.76219789173595,55.59756465362513],"type":"Point"}
}