{
  "type": "Feature",
  "properties": {
    "iso:country": "GB",
    "wof:name": "PO14 3LD",
    "wof:placetype": "postalcode"
  },
  "geometry": {"coordinates":[-1.231296,50.818846],"type":"Point"}
}
