{
  "type": "Feature",
  "properties": {
    "iso:country":"GB",
    "wof:name":"PO14 3LD",
    "wof:placetype":"postalcode"
},
  "geometry": {"coordinates":[-1.23139776132983,50.81872988717898],"type":"Point"}
}