{
  "type": "Feature",
  "properties": {
    "iso:country":"GB",
    "wof:name":"NP26 5UN",
    "wof:placetype":"postalcode"
},
  "geometry": {"coordinates":[-2.73650309080837,51.59932850002426],"type":"Point"}
}