{
  "type": "Feature",
  "properties": {
    "date:inception_lower": "2015-11-01",
    "date:inception_upper": "2015-11-01",
    "iso:country": "GB",
    "wof:name": "PE28 2WN",
    "wof:placetype": "postalcode"
  },
  "geometry": {"coordinates":[-0.078745,52.402889],"type":"Point"}
}
