{
  "type": "Feature",
  "properties": {
    "iso:country":"GB",
    "wof:name":"BH12 5EW",
    "wof:placetype":"postalcode"
},
  "geometry": {"coordinates":[-1.90553248444717,50.74172718375499],"type":"Point"}
}