{
  "type": "Feature",
  "properties": {
    "iso:country": "GB",
    "wof:name": "BH12 5EW",
    "wof:placetype": "postalcode"
  },
  "geometry": {"coordinates":[-1.905532,50.741727],"type":"Point"}
}
