{
  "type": "Feature",
  "properties": {
    "iso:country": "GB",
    "wof:name": "ME20 7DL",
    "wof:placetype": "postalcode"
  },
  "geometry": {"coordinates":[0.455841,51.306947],"type":"Point"}
}
