{
  "type": "Feature",
  "properties": {
    "date:inception_lower": "2018-03-01",
    "date:inception_upper": "2018-03-01",
    "iso:country": "GB",
    "wof:name": "ME20 7DL",
    "wof:placetype": "postalcode"
  },
  "geometry": {"coordinates":[0.455841,51.306947],"type":"Point"}
}
