{
  "type": "Feature",
  "properties": {
    "iso:country": "GB",
    "wof:name": "BB7 9TD",
    "wof:placetype": "postalcode"
  },
  "geometry": {"coordinates":[-2.404916,53.820913],"type":"Point"}
}
