{
  "type": "Feature",
  "properties": {
    "iso:country":"GB",
    "wof:name":"BB7 9TD",
    "wof:placetype":"postalcode"
},
  "geometry": {"coordinates":[-2.40491604282444,53.82091269627776],"type":"Point"}
}