{
  "type": "Feature",
  "properties": {
    "iso:country": "GB",
    "wof:name": "SO45 4JH",
    "wof:placetype": "postalcode"
  },
  "geometry": {"coordinates":[-1.414341,50.853711],"type":"Point"}
}
