{
  "type": "Feature",
  "properties": {
    "date:inception_lower":"1994-12-01",
    "date:inception_upper":"1994-12-31",
    "iso:country":"GB",
    "wof:name":"SO45 4JH",
    "wof:placetype":"postalcode"
},
  "geometry": {"coordinates":[-1.414341,50.853711],"type":"Point"}
}