{
  "type": "Feature",
  "properties": {
    "iso:country":"GB",
    "wof:name":"TN29 0JW",
    "wof:placetype":"postalcode"
},
  "geometry": {"coordinates":[1.00909160978251,51.0520031781621],"type":"Point"}
}