{
  "type": "Feature",
  "properties": {
    "date:inception_lower":"1980-01-01",
    "date:inception_upper":"1980-01-31",
    "iso:country":"GB",
    "wof:name":"TN29 0JW",
    "wof:placetype":"postalcode"
},
  "geometry": {"coordinates":[1.009092,51.052003],"type":"Point"}
}