{
  "type": "Feature",
  "properties": {
    "date:inception_lower": "2022-02-01",
    "date:inception_upper": "2022-02-01",
    "iso:country": "GB",
    "wof:name": "SL5 8AT",
    "wof:placetype": "postalcode"
  },
  "geometry": {"coordinates":[-0.694215,51.404354],"type":"Point"}
}
