{
  "type": "Feature",
  "properties": {
    "iso:country": "GB",
    "wof:name": "L24 4AX",
    "wof:placetype": "postalcode"
  },
  "geometry": {"coordinates":[-2.797918,53.334126],"type":"Point"}
}
