{
  "type": "Feature",
  "properties": {
    "iso:country":"GB",
    "wof:name":"L24 4AX",
    "wof:placetype":"postalcode"
},
  "geometry": {"coordinates":[-2.79791846442219,53.3341262915735],"type":"Point"}
}