{
  "type": "Feature",
  "properties": {
    "iso:country":"GB",
    "wof:name":"G2 4EG",
    "wof:placetype":"postalcode"
},
  "geometry": {"coordinates":[-4.26195204621524,55.8640522500195],"type":"Point"}
}