{
  "type": "Feature",
  "properties": {
    "iso:country":"GB",
    "wof:name":"S2 3HN",
    "wof:placetype":"postalcode"
},
  "geometry": {"coordinates":[-1.46304807719202,53.36106302251271],"type":"Point"}
}