{
  "type": "Feature",
  "properties": {
    "iso:country": "GB",
    "wof:name": "EH4 5BH",
    "wof:placetype": "postalcode"
  },
  "geometry": {"coordinates":[-3.269336,55.965834],"type":"Point"}
}
