{
  "type": "Feature",
  "properties": {
    "iso:country":"GB",
    "wof:name":"EH4 5BH",
    "wof:placetype":"postalcode"
},
  "geometry": {"coordinates":[-3.269335824959,55.96583350630195],"type":"Point"}
}