{
  "type": "Feature",
  "properties": {
    "date:inception_lower": "2019-06-01",
    "date:inception_upper": "2019-06-01",
    "iso:country": "GB",
    "wof:name": "G41 1BF",
    "wof:placetype": "postalcode"
  },
  "geometry": {"coordinates":[-4.264153,55.841979],"type":"Point"}
}
