{
  "type": "Feature",
  "properties": {
    "iso:country": "GB",
    "wof:name": "G41 1BF",
    "wof:placetype": "postalcode"
  },
  "geometry": {"coordinates":[-4.26446,55.841757],"type":"Point"}
}
