{
  "type": "Feature",
  "properties": {
    "iso:country":"GB",
    "wof:name":"NR31 0LP",
    "wof:placetype":"postalcode"
},
  "geometry": {"coordinates":[1.72243462297101,52.60342048453153],"type":"Point"}
}