{
  "type": "Feature",
  "properties": {
    "date:inception_lower": "1994-05-01",
    "date:inception_upper": "1994-05-01",
    "iso:country": "GB",
    "wof:name": "NR31 0LP",
    "wof:placetype": "postalcode"
  },
  "geometry": {"coordinates":[1.722435,52.60342],"type":"Point"}
}
