{
  "type": "Feature",
  "properties": {
    "iso:country":"GB",
    "wof:name":"CW8 1NU",
    "wof:placetype":"postalcode"
},
  "geometry": {"coordinates":[-2.53796882721608,53.24519022514361],"type":"Point"}
}