{
  "type": "Feature",
  "properties": {
    "date:inception_lower": "1980-01-01",
    "date:inception_upper": "1980-01-01",
    "iso:country": "GB",
    "wof:name": "CW8 1NU",
    "wof:placetype": "postalcode"
  },
  "geometry": {"coordinates":[-2.539124,53.245407],"type":"Point"}
}
