{
  "type": "Feature",
  "properties": {
    "iso:country":"GB",
    "wof:name":"SW9 8RR",
    "wof:placetype":"postalcode"
},
  "geometry": {"coordinates":[-0.10295439054538,51.46503149784413],"type":"Point"}
}