{
  "type": "Feature",
  "properties": {
    "iso:country":"GB",
    "wof:name":"BD9 6RS",
    "wof:placetype":"postalcode"
},
  "geometry": {"coordinates":[-1.80598309023037,53.80836301303894],"type":"Point"}
}