{
  "type": "Feature",
  "properties": {
    "date:inception_lower": "1998-06-01",
    "date:inception_upper": "1998-06-01",
    "iso:country": "GB",
    "wof:name": "G83 8QU",
    "wof:placetype": "postalcode"
  },
  "geometry": {"coordinates":[-4.599163,56.000169],"type":"Point"}
}
