{
  "type": "Feature",
  "properties": {
    "iso:country":"GB",
    "wof:name":"G83 8QU",
    "wof:placetype":"postalcode"
},
  "geometry": {"coordinates":[-4.59918051968323,56.00017538009019],"type":"Point"}
}