{
  "type": "Feature",
  "properties": {
    "date:inception_lower": "2011-12-01",
    "date:inception_upper": "2011-12-01",
    "iso:country": "GB",
    "wof:name": "RH8 9EW",
    "wof:placetype": "postalcode"
  },
  "geometry": {"coordinates":[-0.006595,51.258987],"type":"Point"}
}
