{
  "type": "Feature",
  "properties": {
    "iso:country":"GB",
    "wof:name":"RH8 9EW",
    "wof:placetype":"postalcode"
},
  "geometry": {"coordinates":[-0.00675055974021,51.25898238025757],"type":"Point"}
}