{
  "type": "Feature",
  "properties": {
    "iso:country":"GB",
    "wof:name":"N19 4QD",
    "wof:placetype":"postalcode"
},
  "geometry": {"coordinates":[-0.12969494537349,51.55990057198024],"type":"Point"}
}