{
  "type": "Feature",
  "properties": {
    "iso:country":"GB",
    "wof:name":"BB5 0PR",
    "wof:placetype":"postalcode"
},
  "geometry": {"coordinates":[-2.36650508745586,53.74490763963927],"type":"Point"}
}