{
  "type": "Feature",
  "properties": {
    "iso:country":"GB",
    "wof:name":"DG13 0JN",
    "wof:placetype":"postalcode"
},
  "geometry": {"coordinates":[-2.99983393117548,55.152968802346],"type":"Point"}
}