{
  "type": "Feature",
  "properties": {
    "iso:country":"GB",
    "wof:name":"BS9 1HQ",
    "wof:placetype":"postalcode"
},
  "geometry": {"coordinates":[-2.62984099843696,51.48061396582543],"type":"Point"}
}