{
  "type": "Feature",
  "properties": {
    "iso:country":"GB",
    "wof:name":"N18 1RG",
    "wof:placetype":"postalcode"
},
  "geometry": {"coordinates":[-0.07493340003078,51.6161800732182],"type":"Point"}
}