{
  "type": "Feature",
  "properties": {
    "iso:country":"GB",
    "wof:name":"HG5 9JF",
    "wof:placetype":"postalcode"
},
  "geometry": {"coordinates":[-1.45012676065443,54.03992986307235],"type":"Point"}
}