{
  "type": "Feature",
  "properties": {
    "iso:country": "GB",
    "wof:name": "OX18 3TD",
    "wof:placetype": "postalcode"
  },
  "geometry": {"coordinates":[-1.594333,51.750992],"type":"Point"}
}
