{
  "type": "Feature",
  "properties": {
    "iso:country": "GB",
    "wof:name": "CH45 7LD",
    "wof:placetype": "postalcode"
  },
  "geometry": {"coordinates":[-3.042565,53.422228],"type":"Point"}
}
