{
  "type": "Feature",
  "properties": {
    "iso:country":"GB",
    "wof:name":"CH45 7LD",
    "wof:placetype":"postalcode"
},
  "geometry": {"coordinates":[-3.04256529406956,53.42222801160608],"type":"Point"}
}