{
  "type": "Feature",
  "properties": {
    "date:inception_lower": "2021-02-01",
    "date:inception_upper": "2021-02-01",
    "iso:country": "GB",
    "wof:name": "G72 6AN",
    "wof:placetype": "postalcode"
  },
  "geometry": {"coordinates":[-4.131179,55.826165],"type":"Point"}
}
