{
  "type": "Feature",
  "properties": {
    "iso:country":"GB",
    "wof:name":"SA5 5AF",
    "wof:placetype":"postalcode"
},
  "geometry": {"coordinates":[-3.96931386826565,51.64814282401255],"type":"Point"}
}