{
  "type": "Feature",
  "properties": {
    "date:inception_lower": "1991-01-01",
    "date:inception_upper": "1991-01-01",
    "iso:country": "GB",
    "wof:name": "HU18 1TR",
    "wof:placetype": "postalcode"
  },
  "geometry": {"coordinates":[-0.165476,53.901437],"type":"Point"}
}
