{
  "type": "Feature",
  "properties": {
    "iso:country":"GB",
    "wof:name":"HU18 1TR",
    "wof:placetype":"postalcode"
},
  "geometry": {"coordinates":[-0.16547595163632,53.90143663428127],"type":"Point"}
}