{
  "type": "Feature",
  "properties": {
    "iso:country":"GB",
    "wof:name":"WD3 6AE",
    "wof:placetype":"postalcode"
},
  "geometry": {"coordinates":[-0.49902612762975,51.68166105901275],"type":"Point"}
}