{
  "type": "Feature",
  "properties": {
    "iso:country":"GB",
    "wof:name":"WR3 8ED",
    "wof:placetype":"postalcode"
},
  "geometry": {"coordinates":[-2.21751429398299,52.21003841077108],"type":"Point"}
}