{
  "type": "Feature",
  "properties": {
    "date:inception_lower": "1980-01-01",
    "date:inception_upper": "1980-01-01",
    "iso:country": "GB",
    "wof:name": "WR3 8ED",
    "wof:placetype": "postalcode"
  },
  "geometry": {"coordinates":[-2.217514,52.210038],"type":"Point"}
}
