{
  "type": "Feature",
  "properties": {
    "iso:country":"GB",
    "wof:name":"ST3 6HJ",
    "wof:placetype":"postalcode"
},
  "geometry": {"coordinates":[-2.08673028464484,52.97356628904506],"type":"Point"}
}