{
  "type": "Feature",
  "properties": {
    "iso:country": "GB",
    "wof:name": "NG12 4HR",
    "wof:placetype": "postalcode"
  },
  "geometry": {"coordinates":[-1.121831,52.910588],"type":"Point"}
}
