{
  "type": "Feature",
  "properties": {
    "date:inception_lower": "2019-05-01",
    "date:inception_upper": "2019-05-01",
    "iso:country": "GB",
    "wof:name": "NG12 4HR",
    "wof:placetype": "postalcode"
  },
  "geometry": {"coordinates":[-1.121835,52.910417],"type":"Point"}
}
