{
  "type": "Feature",
  "properties": {
    "date:inception_lower":"1984-02-01",
    "date:inception_upper":"1984-02-29",
    "iso:country":"GB",
    "wof:name":"GL5 4BJ",
    "wof:placetype":"postalcode"
},
  "geometry": {"coordinates":[-2.217194,51.747294],"type":"Point"}
}