{
  "type": "Feature",
  "properties": {
    "iso:country": "GB",
    "wof:name": "GL5 4BJ",
    "wof:placetype": "postalcode"
  },
  "geometry": {"coordinates":[-2.217194,51.747294],"type":"Point"}
}
