{
  "type": "Feature",
  "properties": {
    "date:inception_lower": "1981-06-01",
    "date:inception_upper": "1981-06-01",
    "iso:country": "GB",
    "wof:name": "LL15 1ND",
    "wof:placetype": "postalcode"
  },
  "geometry": {"coordinates":[-3.309376,53.116585],"type":"Point"}
}
