{
  "type": "Feature",
  "properties": {
    "iso:country":"GB",
    "wof:name":"LL15 1ND",
    "wof:placetype":"postalcode"
},
  "geometry": {"coordinates":[-3.3093759454341,53.11658465190224],"type":"Point"}
}