{
  "type": "Feature",
  "properties": {
    "date:inception_lower": "2006-01-01",
    "date:inception_upper": "2006-01-01",
    "iso:country": "GB",
    "wof:name": "M3 2PD",
    "wof:placetype": "postalcode"
  },
  "geometry": {"coordinates":[-2.249527,53.48143],"type":"Point"}
}
