{
  "type": "Feature",
  "properties": {
    "iso:country":"GB",
    "wof:name":"LE2 9RE",
    "wof:placetype":"postalcode"
},
  "geometry": {"coordinates":[-1.15321184929719,52.58183966959714],"type":"Point"}
}