{
  "type": "Feature",
  "properties": {
    "date:inception_lower":"1980-01-01",
    "date:inception_upper":"1980-01-31",
    "iso:country":"GB",
    "wof:name":"LE2 9RE",
    "wof:placetype":"postalcode"
},
  "geometry": {"coordinates":[-1.153212,52.58184],"type":"Point"}
}