{
  "type": "Feature",
  "properties": {
    "iso:country": "GB",
    "wof:name": "LE2 9RE",
    "wof:placetype": "postalcode"
  },
  "geometry": {"coordinates":[-1.153212,52.58184],"type":"Point"}
}
