{
  "type": "Feature",
  "properties": {
    "iso:country":"GB",
    "wof:name":"E16 2HL",
    "wof:placetype":"postalcode"
},
  "geometry": {"coordinates":[0.05165982834031,51.50170810151845],"type":"Point"}
}