{
  "type": "Feature",
  "properties": {
    "iso:country": "GB",
    "wof:name": "RG1 3LT",
    "wof:placetype": "postalcode"
  },
  "geometry": {"coordinates":[-0.946927,51.457557],"type":"Point"}
}
