{
  "type": "Feature",
  "properties": {
    "iso:country":"GB",
    "wof:name":"RG1 3LT",
    "wof:placetype":"postalcode"
},
  "geometry": {"coordinates":[-0.94694719919993,51.45755628237748],"type":"Point"}
}