{
  "type": "Feature",
  "properties": {
    "iso:country": "GB",
    "wof:name": "RG1 3LT",
    "wof:placetype": "postalcode"
  },
  "geometry": {"coordinates":[-0.946911,51.457647],"type":"Point"}
}
