{
  "type": "Feature",
  "properties": {
    "date:inception_lower":"1980-01-01",
    "date:inception_upper":"1980-01-31",
    "iso:country":"GB",
    "wof:name":"RG1 3LT",
    "wof:placetype":"postalcode"
},
  "geometry": {"coordinates":[-0.946911,51.457647],"type":"Point"}
}