{
  "type": "Feature",
  "properties": {
    "iso:country":"GB",
    "wof:name":"NG23 7ET",
    "wof:placetype":"postalcode"
},
  "geometry": {"coordinates":[-0.71046437847055,53.2212475218311],"type":"Point"}
}