{
  "type": "Feature",
  "properties": {
    "iso:country": "GB",
    "wof:name": "NG23 7ET",
    "wof:placetype": "postalcode"
  },
  "geometry": {"coordinates":[-0.710464,53.221248],"type":"Point"}
}
