{
  "type": "Feature",
  "properties": {
    "iso:country": "GB",
    "wof:name": "TA11 7EU",
    "wof:placetype": "postalcode"
  },
  "geometry": {"coordinates":[-2.72931,51.053424],"type":"Point"}
}
