{
  "type": "Feature",
  "properties": {
    "iso:country":"GB",
    "wof:name":"BS9 4QX",
    "wof:placetype":"postalcode"
},
  "geometry": {"coordinates":[-2.59767407432042,51.49186901626527],"type":"Point"}
}