{
  "type": "Feature",
  "properties": {
    "iso:country":"GB",
    "wof:name":"BH1 4HW",
    "wof:placetype":"postalcode"
},
  "geometry": {"coordinates":[-1.84303342979297,50.72882743346105],"type":"Point"}
}