{
  "type": "Feature",
  "properties": {
    "iso:country": "GB",
    "wof:name": "DA12 4BH",
    "wof:placetype": "postalcode"
  },
  "geometry": {"coordinates":[0.388607,51.425163],"type":"Point"}
}
