{
  "type": "Feature",
  "properties": {
    "date:inception_lower": "2018-10-01",
    "date:inception_upper": "2018-10-01",
    "iso:country": "GB",
    "wof:name": "CM23 2GR",
    "wof:placetype": "postalcode"
  },
  "geometry": {"coordinates":[0.13904,51.878097],"type":"Point"}
}
