{
  "type": "Feature",
  "properties": {
    "date:inception_lower": "1993-01-01",
    "date:inception_upper": "1993-01-01",
    "iso:country": "GB",
    "wof:name": "GL53 9NR",
    "wof:placetype": "postalcode"
  },
  "geometry": {"coordinates":[-1.992502,51.82309],"type":"Point"}
}
