{
  "type": "Feature",
  "properties": {
    "iso:country":"GB",
    "wof:name":"GL53 9NR",
    "wof:placetype":"postalcode"
},
  "geometry": {"coordinates":[-1.99181322277713,51.82441357856577],"type":"Point"}
}