{
  "type": "Feature",
  "properties": {
    "iso:country": "GB",
    "wof:name": "GL53 9NR",
    "wof:placetype": "postalcode"
  },
  "geometry": {"coordinates":[-1.991805,51.82442],"type":"Point"}
}
