{
  "type": "Feature",
  "properties": {
    "date:inception_lower":"1980-01-01",
    "date:inception_upper":"1980-01-31",
    "iso:country":"GB",
    "wof:name":"KT12 5NX",
    "wof:placetype":"postalcode"
},
  "geometry": {"coordinates":[-0.408649,51.372776],"type":"Point"}
}