{
  "type": "Feature",
  "properties": {
    "iso:country":"GB",
    "wof:name":"KT12 5NX",
    "wof:placetype":"postalcode"
},
  "geometry": {"coordinates":[-0.4086491078343,51.37277628787379],"type":"Point"}
}