{
  "type": "Feature",
  "properties": {
    "date:inception_lower": "2020-08-01",
    "date:inception_upper": "2020-08-01",
    "iso:country": "GB",
    "wof:name": "IV17 0AJ",
    "wof:placetype": "postalcode"
  },
  "geometry": {"coordinates":[-4.232648,57.703062],"type":"Point"}
}
