{
  "type": "Feature",
  "properties": {
    "iso:country":"GB",
    "wof:name":"TW11 8EP",
    "wof:placetype":"postalcode"
},
  "geometry": {"coordinates":[-0.33317967609741,51.42687770803973],"type":"Point"}
}