{
  "type": "Feature",
  "properties": {
    "iso:country": "GB",
    "wof:name": "FK10 1RN",
    "wof:placetype": "postalcode"
  },
  "geometry": {"coordinates":[-3.777266,56.10833],"type":"Point"}
}
