{
  "type": "Feature",
  "properties": {
    "date:inception_lower":"2013-03-01",
    "date:inception_upper":"2013-03-31",
    "iso:country":"GB",
    "wof:name":"FK10 1RN",
    "wof:placetype":"postalcode"
},
  "geometry": {"coordinates":[-3.777266,56.10833],"type":"Point"}
}