{
  "type": "Feature",
  "properties": {
    "iso:country":"GB",
    "wof:name":"FK10 1RN",
    "wof:placetype":"postalcode"
},
  "geometry": {"coordinates":[-3.77731991367134,56.10845537472925],"type":"Point"}
}