{
  "type": "Feature",
  "properties": {
    "iso:country":"GB",
    "wof:name":"CO4 3JZ",
    "wof:placetype":"postalcode"
},
  "geometry": {"coordinates":[0.94101164877993,51.89337766915541],"type":"Point"}
}