{
  "type": "Feature",
  "properties": {
    "date:inception_lower":"1980-01-01",
    "date:inception_upper":"1980-01-31",
    "iso:country":"GB",
    "wof:name":"DH2 1BL",
    "wof:placetype":"postalcode"
},
  "geometry": {"coordinates":[-1.594279,54.867965],"type":"Point"}
}