{
  "type": "Feature",
  "properties": {
    "iso:country":"GB",
    "wof:name":"DH2 1BL",
    "wof:placetype":"postalcode"
},
  "geometry": {"coordinates":[-1.59254087837588,54.86764582442758],"type":"Point"}
}