{
  "type": "Feature",
  "properties": {
    "iso:country": "GB",
    "wof:name": "DH2 1BL",
    "wof:placetype": "postalcode"
  },
  "geometry": {"coordinates":[-1.592553,54.867654],"type":"Point"}
}
