{
  "type": "Feature",
  "properties": {
    "iso:country":"GB",
    "wof:name":"IP20 9AA",
    "wof:placetype":"postalcode"
},
  "geometry": {"coordinates":[1.29958812350752,52.40216767540853],"type":"Point"}
}