{
  "type": "Feature",
  "properties": {
    "date:inception_lower": "2000-12-01",
    "date:inception_upper": "2000-12-01",
    "iso:country": "GB",
    "wof:name": "IP20 9AA",
    "wof:placetype": "postalcode"
  },
  "geometry": {"coordinates":[1.299616,52.402189],"type":"Point"}
}
