{
  "type": "Feature",
  "properties": {
    "iso:country": "GB",
    "wof:name": "LU7 9NZ",
    "wof:placetype": "postalcode"
  },
  "geometry": {"coordinates":[-0.621933,51.927127],"type":"Point"}
}
