{
  "type": "Feature",
  "properties": {
    "iso:country":"GB",
    "wof:name":"LU7 9NZ",
    "wof:placetype":"postalcode"
},
  "geometry": {"coordinates":[-0.62193303165574,51.92712731384415],"type":"Point"}
}