{
  "type": "Feature",
  "properties": {
    "iso:country":"GB",
    "wof:name":"DG4 6AQ",
    "wof:placetype":"postalcode"
},
  "geometry": {"coordinates":[-3.92429486679595,55.36489406882491],"type":"Point"}
}