{
  "type": "Feature",
  "properties": {
    "iso:country":"GB",
    "wof:name":"PR3 3BD",
    "wof:placetype":"postalcode"
},
  "geometry": {"coordinates":[-2.60693914109294,53.81936815788585],"type":"Point"}
}