{
  "type": "Feature",
  "properties": {
    "iso:country": "GB",
    "wof:name": "PR3 3BD",
    "wof:placetype": "postalcode"
  },
  "geometry": {"coordinates":[-2.607103,53.819229],"type":"Point"}
}
