{
  "type": "Feature",
  "properties": {
    "iso:country":"GB",
    "wof:name":"KA5 5NL",
    "wof:placetype":"postalcode"
},
  "geometry": {"coordinates":[-4.49649920636363,55.50623237139659],"type":"Point"}
}