{
  "type": "Feature",
  "properties": {
    "iso:country": "GB",
    "wof:name": "KA5 5NL",
    "wof:placetype": "postalcode"
  },
  "geometry": {"coordinates":[-4.496499,55.506232],"type":"Point"}
}
