{
  "type": "Feature",
  "properties": {
    "iso:country":"GB",
    "wof:name":"ML6 9RQ",
    "wof:placetype":"postalcode"
},
  "geometry": {"coordinates":[-3.99470296441409,55.85176224801877],"type":"Point"}
}