{
  "type": "Feature",
  "properties": {
    "iso:country":"GB",
    "wof:name":"KW14 7GZ",
    "wof:placetype":"postalcode"
},
  "geometry": {"coordinates":[-3.52744936318971,58.59185621262549],"type":"Point"}
}