{
  "type": "Feature",
  "properties": {
    "iso:country":"GB",
    "wof:name":"FK10 2US",
    "wof:placetype":"postalcode"
},
  "geometry": {"coordinates":[-3.82221751145588,56.13936946032062],"type":"Point"}
}