{
  "type": "Feature",
  "properties": {
    "iso:country":"GB",
    "wof:name":"CV37 9DP",
    "wof:placetype":"postalcode"
},
  "geometry": {"coordinates":[-1.72522088388715,52.19525672454657],"type":"Point"}
}