{
  "type": "Feature",
  "properties": {
    "iso:country":"GB",
    "wof:name":"BS7 9EN",
    "wof:placetype":"postalcode"
},
  "geometry": {"coordinates":[-2.58758651670159,51.47804598154008],"type":"Point"}
}