{
  "type": "Feature",
  "properties": {
    "iso:country":"GB",
    "wof:name":"ST6 5LR",
    "wof:placetype":"postalcode"
},
  "geometry": {"coordinates":[-2.21171485951022,53.07126499475547],"type":"Point"}
}