{
  "type": "Feature",
  "properties": {
    "iso:country":"GB",
    "wof:name":"NW11 9NN",
    "wof:placetype":"postalcode"
},
  "geometry": {"coordinates":[-0.20736881642507,51.57823440873016],"type":"Point"}
}