{
  "type": "Feature",
  "properties": {
    "iso:country": "GB",
    "wof:name": "WR10 2BP",
    "wof:placetype": "postalcode"
  },
  "geometry": {"coordinates":[-2.103064,52.137704],"type":"Point"}
}
