{
  "type": "Feature",
  "properties": {
    "date:inception_lower":"1980-01-01",
    "date:inception_upper":"1980-01-31",
    "iso:country":"GB",
    "wof:name":"TR13 8JB",
    "wof:placetype":"postalcode"
},
  "geometry": {"coordinates":[-5.270784,50.096154],"type":"Point"}
}