{
  "type": "Feature",
  "properties": {
    "iso:country": "GB",
    "wof:name": "TR13 8JB",
    "wof:placetype": "postalcode"
  },
  "geometry": {"coordinates":[-5.270784,50.096154],"type":"Point"}
}
