{
  "type": "Feature",
  "properties": {
    "iso:country":"GB",
    "wof:name":"M14 6HX",
    "wof:placetype":"postalcode"
},
  "geometry": {"coordinates":[-2.21737107978701,53.44329188960067],"type":"Point"}
}