{
  "type": "Feature",
  "properties": {
    "iso:country":"GB",
    "wof:name":"NE6 5DE",
    "wof:placetype":"postalcode"
},
  "geometry": {"coordinates":[-1.56907187243813,54.98632847021316],"type":"Point"}
}