{
  "type": "Feature",
  "properties": {
    "iso:country": "GB",
    "wof:name": "SG13 7HE",
    "wof:placetype": "postalcode"
  },
  "geometry": {"coordinates":[-0.071205,51.796901],"type":"Point"}
}
