{
  "type": "Feature",
  "properties": {
    "iso:country": "GB",
    "wof:name": "HU17 9DF",
    "wof:placetype": "postalcode"
  },
  "geometry": {"coordinates":[-0.430128,53.841763],"type":"Point"}
}
