{
  "type": "Feature",
  "properties": {
    "iso:country":"GB",
    "wof:name":"TS17 0PU",
    "wof:placetype":"postalcode"
},
  "geometry": {"coordinates":[-1.30812078237677,54.51004930165164],"type":"Point"}
}