{
  "type": "Feature",
  "properties": {
    "date:inception_lower":"1994-05-01",
    "date:inception_upper":"1994-05-31",
    "iso:country":"GB",
    "wof:name":"TS17 0PU",
    "wof:placetype":"postalcode"
},
  "geometry": {"coordinates":[-1.308121,54.510049],"type":"Point"}
}