{
  "type": "Feature",
  "properties": {
    "iso:country":"GB",
    "wof:name":"OL16 3RY",
    "wof:placetype":"postalcode"
},
  "geometry": {"coordinates":[-2.09813751215873,53.60056640656691],"type":"Point"}
}