{
  "type": "Feature",
  "properties": {
    "date:inception_lower":"1980-01-01",
    "date:inception_upper":"1980-01-31",
    "iso:country":"GB",
    "wof:name":"OL16 3RY",
    "wof:placetype":"postalcode"
},
  "geometry": {"coordinates":[-2.098166,53.600619],"type":"Point"}
}