{
  "type": "Feature",
  "properties": {
    "iso:country": "GB",
    "wof:name": "OL16 3RY",
    "wof:placetype": "postalcode"
  },
  "geometry": {"coordinates":[-2.098166,53.600619],"type":"Point"}
}
