{
  "type": "Feature",
  "properties": {
    "iso:country": "GB",
    "wof:name": "NG1 3AN",
    "wof:placetype": "postalcode"
  },
  "geometry": {"coordinates":[-1.144194,52.954617],"type":"Point"}
}
