{
  "type": "Feature",
  "properties": {
    "iso:country": "GB",
    "wof:name": "SY6 7AA",
    "wof:placetype": "postalcode"
  },
  "geometry": {"coordinates":[-2.797672,52.537829],"type":"Point"}
}
