{
  "type": "Feature",
  "properties": {
    "iso:country":"GB",
    "wof:name":"SY6 7AA",
    "wof:placetype":"postalcode"
},
  "geometry": {"coordinates":[-2.7976715712291,52.53782905058672],"type":"Point"}
}