{
  "type": "Feature",
  "properties": {
    "iso:country":"GB",
    "wof:name":"EH33 1AL",
    "wof:placetype":"postalcode"
},
  "geometry": {"coordinates":[-2.95750634310842,55.94476831797974],"type":"Point"}
}