{
  "type": "Feature",
  "properties": {
    "iso:country": "GB",
    "wof:name": "RH5 5QP",
    "wof:placetype": "postalcode"
  },
  "geometry": {"coordinates":[-0.367877,51.1421],"type":"Point"}
}
