{
  "type": "Feature",
  "properties": {
    "date:inception_lower": "1980-01-01",
    "date:inception_upper": "1980-01-01",
    "iso:country": "GB",
    "wof:name": "PE19 2UB",
    "wof:placetype": "postalcode"
  },
  "geometry": {"coordinates":[-0.26973,52.221236],"type":"Point"}
}
