{
  "type": "Feature",
  "properties": {
    "date:inception_lower": "1983-01-01",
    "date:inception_upper": "1983-01-01",
    "iso:country": "GB",
    "wof:name": "TS6 6XG",
    "wof:placetype": "postalcode"
  },
  "geometry": {"coordinates":[-1.175825,54.578763],"type":"Point"}
}
