{
  "type": "Feature",
  "properties": {
    "iso:country":"GB",
    "wof:name":"TS6 6XG",
    "wof:placetype":"postalcode"
},
  "geometry": {"coordinates":[-1.17579493656755,54.57873559896533],"type":"Point"}
}