{
  "type": "Feature",
  "properties": {
    "iso:country":"GB",
    "wof:name":"B30 1LU",
    "wof:placetype":"postalcode"
},
  "geometry": {"coordinates":[-1.94321943901346,52.42628744199763],"type":"Point"}
}