{
  "type": "Feature",
  "properties": {
    "iso:country":"GB",
    "wof:name":"FK10 2ES",
    "wof:placetype":"postalcode"
},
  "geometry": {"coordinates":[-3.81462835760923,56.13337956815131],"type":"Point"}
}