{
  "type": "Feature",
  "properties": {
    "iso:country":"GB",
    "wof:name":"SY5 0PU",
    "wof:placetype":"postalcode"
},
  "geometry": {"coordinates":[-2.88447186133953,52.65304906138902],"type":"Point"}
}