{
  "type": "Feature",
  "properties": {
    "iso:country": "GB",
    "wof:name": "WF4 4RQ",
    "wof:placetype": "postalcode"
  },
  "geometry": {"coordinates":[-1.613134,53.648933],"type":"Point"}
}
