{
  "type": "Feature",
  "properties": {
    "iso:country":"GB",
    "wof:name":"WF4 4RQ",
    "wof:placetype":"postalcode"
},
  "geometry": {"coordinates":[-1.61313367356609,53.64893255529203],"type":"Point"}
}