{
  "type": "Feature",
  "properties": {
    "date:inception_lower": "2017-02-01",
    "date:inception_upper": "2017-02-01",
    "iso:country": "GB",
    "wof:name": "RG2 9GQ",
    "wof:placetype": "postalcode"
  },
  "geometry": {"coordinates":[-0.88677,51.385668],"type":"Point"}
}
