{
  "type": "Feature",
  "properties": {
    "date:inception_lower": "2019-08-01",
    "date:inception_upper": "2019-08-01",
    "iso:country": "GB",
    "wof:name": "SA43 2TZ",
    "wof:placetype": "postalcode"
  },
  "geometry": {"coordinates":[-4.640837,52.054509],"type":"Point"}
}
