{
  "type": "Feature",
  "properties": {
    "iso:country": "GB",
    "wof:name": "SA43 2TZ",
    "wof:placetype": "postalcode"
  },
  "geometry": {"coordinates":[-4.641173,52.05451],"type":"Point"}
}
