{
  "type": "Feature",
  "properties": {
    "iso:country":"GB",
    "wof:name":"NR7 9QT",
    "wof:placetype":"postalcode"
},
  "geometry": {"coordinates":[1.34085316547139,52.64569454073444],"type":"Point"}
}