{
  "type": "Feature",
  "properties": {
    "iso:country":"GB",
    "wof:name":"SS15 5HB",
    "wof:placetype":"postalcode"
},
  "geometry": {"coordinates":[0.43944126434102,51.57372784342212],"type":"Point"}
}