{
  "type": "Feature",
  "properties": {
    "iso:country": "GB",
    "wof:name": "RH12 1XB",
    "wof:placetype": "postalcode"
  },
  "geometry": {"coordinates":[-0.349567,51.060919],"type":"Point"}
}
