{
  "type": "Feature",
  "properties": {
    "date:inception_lower":"1982-03-01",
    "date:inception_upper":"1982-03-31",
    "iso:country":"GB",
    "wof:name":"RH12 1XB",
    "wof:placetype":"postalcode"
},
  "geometry": {"coordinates":[-0.349567,51.060919],"type":"Point"}
}