{
  "type": "Feature",
  "properties": {
    "iso:country":"GB",
    "wof:name":"RH12 1XB",
    "wof:placetype":"postalcode"
},
  "geometry": {"coordinates":[-0.34956699258644,51.06091938544598],"type":"Point"}
}