{
  "type": "Feature",
  "properties": {
    "iso:country":"GB",
    "wof:name":"NE6 3LG",
    "wof:placetype":"postalcode"
},
  "geometry": {"coordinates":[-1.56341331593723,54.96485805800827],"type":"Point"}
}