{
  "type": "Feature",
  "properties": {
    "date:inception_lower": "2008-05-01",
    "date:inception_upper": "2008-05-01",
    "iso:country": "GB",
    "wof:name": "NE6 3LG",
    "wof:placetype": "postalcode"
  },
  "geometry": {"coordinates":[-1.563413,54.964858],"type":"Point"}
}
