{
  "type": "Feature",
  "properties": {
    "date:inception_lower":"1980-01-01",
    "date:inception_upper":"1980-01-31",
    "iso:country":"GB",
    "wof:name":"CM3 3HR",
    "wof:placetype":"postalcode"
},
  "geometry": {"coordinates":[0.514837,51.76691],"type":"Point"}
}