{
  "type": "Feature",
  "properties": {
    "iso:country":"GB",
    "wof:name":"CM3 3HR",
    "wof:placetype":"postalcode"
},
  "geometry": {"coordinates":[0.51483688702775,51.76691040429296],"type":"Point"}
}