{
  "type": "Feature",
  "properties": {
    "iso:country":"GB",
    "wof:name":"WN5 9XJ",
    "wof:placetype":"postalcode"
},
  "geometry": {"coordinates":[-2.6797291371159,53.54400695963042],"type":"Point"}
}