{
  "type": "Feature",
  "properties": {
    "iso:country":"GB",
    "wof:name":"HX2 9HR",
    "wof:placetype":"postalcode"
},
  "geometry": {"coordinates":[-1.88698635453212,53.76173800077254],"type":"Point"}
}