{
  "type": "Feature",
  "properties": {
    "date:inception_lower": "2019-11-01",
    "date:inception_upper": "2019-11-01",
    "iso:country": "GB",
    "wof:name": "CT5 1FY",
    "wof:placetype": "postalcode"
  },
  "geometry": {"coordinates":[1.028714,51.355195],"type":"Point"}
}
