{
  "type": "Feature",
  "properties": {
    "iso:country":"GB",
    "wof:name":"TR26 2BG",
    "wof:placetype":"postalcode"
},
  "geometry": {"coordinates":[-5.47935496414177,50.20190121446781],"type":"Point"}
}