{
  "type": "Feature",
  "properties": {
    "date:inception_lower": "2001-12-01",
    "date:inception_upper": "2001-12-01",
    "iso:country": "GB",
    "wof:name": "S25 2PD",
    "wof:placetype": "postalcode"
  },
  "geometry": {"coordinates":[-1.21155,53.367694],"type":"Point"}
}
