{
  "type": "Feature",
  "properties": {
    "iso:country":"GB",
    "wof:name":"KT6 6DF",
    "wof:placetype":"postalcode"
},
  "geometry": {"coordinates":[-0.30128004444045,51.39181669671738],"type":"Point"}
}