{
  "type": "Feature",
  "properties": {
    "date:inception_lower": "1980-01-01",
    "date:inception_upper": "1980-01-01",
    "iso:country": "GB",
    "wof:name": "BL6 7DT",
    "wof:placetype": "postalcode"
  },
  "geometry": {"coordinates":[-2.543957,53.604133],"type":"Point"}
}
