{
  "type": "Feature",
  "properties": {
    "date:inception_lower":"2014-02-01",
    "date:inception_upper":"2014-02-28",
    "iso:country":"GB",
    "wof:name":"ZE2 9BY",
    "wof:placetype":"postalcode"
},
  "geometry": {"coordinates":[-1.351556,60.3874],"type":"Point"}
}