{
  "type": "Feature",
  "properties": {
    "iso:country":"GB",
    "wof:name":"ZE2 9BY",
    "wof:placetype":"postalcode"
},
  "geometry": {"coordinates":[-1.35155634503337,60.38740016834557],"type":"Point"}
}