{
  "type": "Feature",
  "properties": {
    "iso:country": "GB",
    "wof:name": "NR31 7LG",
    "wof:placetype": "postalcode"
  },
  "geometry": {"coordinates":[1.713437,52.57358],"type":"Point"}
}
