{
  "type": "Feature",
  "properties": {
    "iso:country":"GB",
    "wof:name":"WV14 9AT",
    "wof:placetype":"postalcode"
},
  "geometry": {"coordinates":[-2.09688384999973,52.53963338676493],"type":"Point"}
}