{
  "type": "Feature",
  "properties": {
    "iso:country": "GB",
    "wof:name": "WV14 9AT",
    "wof:placetype": "postalcode"
  },
  "geometry": {"coordinates":[-2.096863,52.539649],"type":"Point"}
}
