{
  "type": "Feature",
  "properties": {
    "iso:country":"GB",
    "wof:name":"AB51 0EN",
    "wof:placetype":"postalcode"
},
  "geometry": {"coordinates":[-2.32069755931865,57.33651810202116],"type":"Point"}
}