{
  "type": "Feature",
  "properties": {
    "iso:country": "GB",
    "wof:name": "AB51 0EN",
    "wof:placetype": "postalcode"
  },
  "geometry": {"coordinates":[-2.320698,57.336518],"type":"Point"}
}
