{
  "type": "Feature",
  "properties": {
    "iso:country": "GB",
    "wof:name": "TF9 3JR",
    "wof:placetype": "postalcode"
  },
  "geometry": {"coordinates":[-2.53766,52.819234],"type":"Point"}
}
