{
  "type": "Feature",
  "properties": {
    "iso:country":"GB",
    "wof:name":"TF9 3JR",
    "wof:placetype":"postalcode"
},
  "geometry": {"coordinates":[-2.53776542367758,52.81917379891394],"type":"Point"}
}