{
  "type": "Feature",
  "properties": {
    "iso:country":"GB",
    "wof:name":"DG1 1LS",
    "wof:placetype":"postalcode"
},
  "geometry": {"coordinates":[-3.60611733082585,55.07326765249294],"type":"Point"}
}