{
  "type": "Feature",
  "properties": {
    "iso:country":"GB",
    "wof:name":"SN1 5EP",
    "wof:placetype":"postalcode"
},
  "geometry": {"coordinates":[-1.799130920337,51.55873319519239],"type":"Point"}
}