{
  "type": "Feature",
  "properties": {
    "iso:country":"GB",
    "wof:name":"SM6 9LB",
    "wof:placetype":"postalcode"
},
  "geometry": {"coordinates":[-0.13445115904414,51.34747226011552],"type":"Point"}
}