{
  "type": "Feature",
  "properties": {
    "date:inception_lower":"1998-06-01",
    "date:inception_upper":"1998-06-30",
    "iso:country":"GB",
    "wof:name":"LN2 2FB",
    "wof:placetype":"postalcode"
},
  "geometry": {"coordinates":[-0.446371,53.271568],"type":"Point"}
}