{
  "type": "Feature",
  "properties": {
    "iso:country":"GB",
    "wof:name":"LN2 2FB",
    "wof:placetype":"postalcode"
},
  "geometry": {"coordinates":[-0.44637154347599,53.27156846473761],"type":"Point"}
}