{
  "type": "Feature",
  "properties": {
    "iso:country": "GB",
    "wof:name": "GL54 3JG",
    "wof:placetype": "postalcode"
  },
  "geometry": {"coordinates":[-1.839042,51.83298],"type":"Point"}
}
