{
  "type": "Feature",
  "properties": {
    "iso:country": "GB",
    "wof:name": "ST6 7JL",
    "wof:placetype": "postalcode"
  },
  "geometry": {"coordinates":[-2.189168,53.058682],"type":"Point"}
}
