{
  "type": "Feature",
  "properties": {
    "date:inception_lower": "1991-09-01",
    "date:inception_upper": "1991-09-01",
    "iso:country": "GB",
    "wof:name": "LE12 8XE",
    "wof:placetype": "postalcode"
  },
  "geometry": {"coordinates":[-1.146135,52.74919],"type":"Point"}
}
