{
  "type": "Feature",
  "properties": {
    "iso:country":"GB",
    "wof:name":"LE12 8XE",
    "wof:placetype":"postalcode"
},
  "geometry": {"coordinates":[-1.14613470677441,52.74919048780306],"type":"Point"}
}