{
  "type": "Feature",
  "properties": {
    "iso:country": "GB",
    "wof:name": "WF10 3DJ",
    "wof:placetype": "postalcode"
  },
  "geometry": {"coordinates":[-1.322226,53.728382],"type":"Point"}
}
