{
  "type": "Feature",
  "properties": {
    "date:inception_lower": "1980-01-01",
    "date:inception_upper": "1980-01-01",
    "iso:country": "GB",
    "wof:name": "WF10 3DJ",
    "wof:placetype": "postalcode"
  },
  "geometry": {"coordinates":[-1.322226,53.728382],"type":"Point"}
}
