{
  "type": "Feature",
  "properties": {
    "iso:country":"GB",
    "wof:name":"WF10 3DJ",
    "wof:placetype":"postalcode"
},
  "geometry": {"coordinates":[-1.3222265354591,53.72838181621156],"type":"Point"}
}