{
  "type": "Feature",
  "properties": {
    "iso:country":"GB",
    "wof:name":"TS5 4PT",
    "wof:placetype":"postalcode"
},
  "geometry": {"coordinates":[-1.26167532484319,54.55044136774917],"type":"Point"}
}