{
  "type": "Feature",
  "properties": {
    "date:inception_lower":"1980-01-01",
    "date:inception_upper":"1980-01-31",
    "iso:country":"GB",
    "wof:name":"TS5 4PT",
    "wof:placetype":"postalcode"
},
  "geometry": {"coordinates":[-1.261675,54.550441],"type":"Point"}
}