{
  "type": "Feature",
  "properties": {
    "date:inception_lower": "1980-01-01",
    "date:inception_upper": "1980-01-01",
    "iso:country": "GB",
    "wof:name": "CT3 4EZ",
    "wof:placetype": "postalcode"
  },
  "geometry": {"coordinates":[1.16418,51.315637],"type":"Point"}
}
