{
  "type": "Feature",
  "properties": {
    "iso:country":"GB",
    "wof:name":"CT3 4EZ",
    "wof:placetype":"postalcode"
},
  "geometry": {"coordinates":[1.16417993972117,51.31563688939227],"type":"Point"}
}