{
  "type": "Feature",
  "properties": {
    "iso:country":"GB",
    "wof:name":"GU29 9NJ",
    "wof:placetype":"postalcode"
},
  "geometry": {"coordinates":[-0.73753389126002,50.98543999024633],"type":"Point"}
}