{
  "type": "Feature",
  "properties": {
    "date:inception_lower": "1980-01-01",
    "date:inception_upper": "1980-01-01",
    "iso:country": "GB",
    "wof:name": "PA15 4BN",
    "wof:placetype": "postalcode"
  },
  "geometry": {"coordinates":[-4.759803,55.942358],"type":"Point"}
}
