{
  "type": "Feature",
  "properties": {
    "iso:country":"GB",
    "wof:name":"B71 1JE",
    "wof:placetype":"postalcode"
},
  "geometry": {"coordinates":[-1.99603477154861,52.5375605706346],"type":"Point"}
}