{
  "type": "Feature",
  "properties": {
    "iso:country":"GB",
    "wof:name":"SK17 7PG",
    "wof:placetype":"postalcode"
},
  "geometry": {"coordinates":[-1.89940824253164,53.25787760854379],"type":"Point"}
}