{
  "type": "Feature",
  "properties": {
    "iso:country":"GB",
    "wof:name":"TN30 6RL",
    "wof:placetype":"postalcode"
},
  "geometry": {"coordinates":[0.69540036612419,51.07118483617602],"type":"Point"}
}