{
  "type": "Feature",
  "properties": {
    "iso:country":"GB",
    "wof:name":"BS15 9TY",
    "wof:placetype":"postalcode"
},
  "geometry": {"coordinates":[-2.49598188233867,51.45985679376993],"type":"Point"}
}