{
  "type": "Feature",
  "properties": {
    "iso:country": "GB",
    "wof:name": "BS15 9TY",
    "wof:placetype": "postalcode"
  },
  "geometry": {"coordinates":[-2.495982,51.459857],"type":"Point"}
}
