{
  "type": "Feature",
  "properties": {
    "iso:country":"GB",
    "wof:name":"LE67 4DZ",
    "wof:placetype":"postalcode"
},
  "geometry": {"coordinates":[-1.35839290078585,52.72372970452625],"type":"Point"}
}