{
  "type": "Feature",
  "properties": {
    "iso:country":"GB",
    "wof:name":"HD3 3UA",
    "wof:placetype":"postalcode"
},
  "geometry": {"coordinates":[-1.84620887260556,53.66295850303169],"type":"Point"}
}