{
  "type": "Feature",
  "properties": {
    "date:inception_lower": "1980-01-01",
    "date:inception_upper": "1980-01-01",
    "iso:country": "GB",
    "wof:name": "PE25 1ND",
    "wof:placetype": "postalcode"
  },
  "geometry": {"coordinates":[0.333419,53.194714],"type":"Point"}
}
