{
  "type": "Feature",
  "properties": {
    "iso:country":"GB",
    "wof:name":"CF31 4RZ",
    "wof:placetype":"postalcode"
},
  "geometry": {"coordinates":[-3.59881921314721,51.51227330847206],"type":"Point"}
}