{
  "type": "Feature",
  "properties": {
    "iso:country": "GB",
    "wof:name": "CF31 4RZ",
    "wof:placetype": "postalcode"
  },
  "geometry": {"coordinates":[-3.598789,51.512238],"type":"Point"}
}
