{
  "type": "Feature",
  "properties": {
    "iso:country":"GB",
    "wof:name":"WS15 2BH",
    "wof:placetype":"postalcode"
},
  "geometry": {"coordinates":[-1.93564321595669,52.76189022920532],"type":"Point"}
}