{
  "type": "Feature",
  "properties": {
    "iso:country": "GB",
    "wof:name": "SA31 3DF",
    "wof:placetype": "postalcode"
  },
  "geometry": {"coordinates":[-4.316649,51.856189],"type":"Point"}
}
