{
  "type": "Feature",
  "properties": {
    "date:inception_lower": "1980-01-01",
    "date:inception_upper": "1980-01-01",
    "iso:country": "GB",
    "wof:name": "SA31 3DF",
    "wof:placetype": "postalcode"
  },
  "geometry": {"coordinates":[-4.316649,51.856189],"type":"Point"}
}
