{
  "type": "Feature",
  "properties": {
    "date:inception_lower": "1980-01-01",
    "date:inception_upper": "1980-01-01",
    "iso:country": "GB",
    "wof:name": "DN17 2PJ",
    "wof:placetype": "postalcode"
  },
  "geometry": {"coordinates":[-0.662188,53.556096],"type":"Point"}
}
