{
  "type": "Feature",
  "properties": {
    "iso:country":"GB",
    "wof:name":"DN17 2PJ",
    "wof:placetype":"postalcode"
},
  "geometry": {"coordinates":[-0.66218767824228,53.55609647526518],"type":"Point"}
}