{
  "type": "Feature",
  "properties": {
    "iso:country":"GB",
    "wof:name":"HA4 9EB",
    "wof:placetype":"postalcode"
},
  "geometry": {"coordinates":[-0.39498285593226,51.56816332912503],"type":"Point"}
}