{
  "type": "Feature",
  "properties": {
    "iso:country":"GB",
    "wof:name":"BD11 2EX",
    "wof:placetype":"postalcode"
},
  "geometry": {"coordinates":[-1.68558397448536,53.74846356702594],"type":"Point"}
}