{
  "type": "Feature",
  "properties": {
    "date:inception_lower": "1980-01-01",
    "date:inception_upper": "1980-01-01",
    "iso:country": "GB",
    "wof:name": "DN22 9DJ",
    "wof:placetype": "postalcode"
  },
  "geometry": {"coordinates":[-0.851958,53.361356],"type":"Point"}
}
