{
  "type": "Feature",
  "properties": {
    "iso:country":"GB",
    "wof:name":"DN22 9DJ",
    "wof:placetype":"postalcode"
},
  "geometry": {"coordinates":[-0.85213689621307,53.36135492391013],"type":"Point"}
}