{
  "type": "Feature",
  "properties": {
    "iso:country":"GB",
    "wof:name":"KY9 1LR",
    "wof:placetype":"postalcode"
},
  "geometry": {"coordinates":[-2.84556200854196,56.2208407074692],"type":"Point"}
}