{
  "type": "Feature",
  "properties": {
    "iso:country":"GB",
    "wof:name":"G33 3HL",
    "wof:placetype":"postalcode"
},
  "geometry": {"coordinates":[-4.17305676616445,55.86740715426732],"type":"Point"}
}