{
  "type": "Feature",
  "properties": {
    "date:inception_lower": "2007-01-01",
    "date:inception_upper": "2007-01-01",
    "iso:country": "GB",
    "wof:name": "TS18 4QG",
    "wof:placetype": "postalcode"
  },
  "geometry": {"coordinates":[-1.342291,54.569303],"type":"Point"}
}
