{
  "type": "Feature",
  "properties": {
    "iso:country":"GB",
    "wof:name":"SO23 8DU",
    "wof:placetype":"postalcode"
},
  "geometry": {"coordinates":[-1.3084171093903,51.06393249747624],"type":"Point"}
}