{
  "type": "Feature",
  "properties": {
    "iso:country": "GB",
    "wof:name": "SO23 8DU",
    "wof:placetype": "postalcode"
  },
  "geometry": {"coordinates":[-1.308532,51.064017],"type":"Point"}
}
