{
  "type": "Feature",
  "properties": {
    "iso:country": "GB",
    "wof:name": "CV9 3BY",
    "wof:placetype": "postalcode"
  },
  "geometry": {"coordinates":[-1.543551,52.583123],"type":"Point"}
}
