{
  "type": "Feature",
  "properties": {
    "iso:country": "GB",
    "wof:name": "RG9 5NU",
    "wof:placetype": "postalcode"
  },
  "geometry": {"coordinates":[-1.008301,51.544433],"type":"Point"}
}
