{
  "type": "Feature",
  "properties": {
    "date:inception_lower": "2009-10-01",
    "date:inception_upper": "2009-10-01",
    "iso:country": "GB",
    "wof:name": "TA6 6FQ",
    "wof:placetype": "postalcode"
  },
  "geometry": {"coordinates":[-2.996419,51.10981],"type":"Point"}
}
