{
  "type": "Feature",
  "properties": {
    "iso:country":"GB",
    "wof:name":"HP13 5XL",
    "wof:placetype":"postalcode"
},
  "geometry": {"coordinates":[-0.7765224837235,51.64868726032965],"type":"Point"}
}