{
  "type": "Feature",
  "properties": {
    "date:inception_lower": "2022-12-01",
    "date:inception_upper": "2022-12-01",
    "iso:country": "GB",
    "wof:name": "KY11 8WH",
    "wof:placetype": "postalcode"
  },
  "geometry": {"coordinates":[-3.395795,56.072343],"type":"Point"}
}
