{
  "type": "Feature",
  "properties": {
    "iso:country":"GB",
    "wof:name":"TN28 8RH",
    "wof:placetype":"postalcode"
},
  "geometry": {"coordinates":[0.9619983666789,50.96141588607149],"type":"Point"}
}