{
  "type": "Feature",
  "properties": {
    "iso:country": "GB",
    "wof:name": "TN28 8RH",
    "wof:placetype": "postalcode"
  },
  "geometry": {"coordinates":[0.962013,50.961758],"type":"Point"}
}
