{
  "type": "Feature",
  "properties": {
    "date:inception_lower": "1986-05-01",
    "date:inception_upper": "1986-05-01",
    "iso:country": "GB",
    "wof:name": "PA13 4PZ",
    "wof:placetype": "postalcode"
  },
  "geometry": {"coordinates":[-4.620607,55.89493],"type":"Point"}
}
