{
  "type": "Feature",
  "properties": {
    "iso:country": "GB",
    "wof:name": "PA13 4PZ",
    "wof:placetype": "postalcode"
  },
  "geometry": {"coordinates":[-4.620657,55.894944],"type":"Point"}
}
