{
  "type": "Feature",
  "properties": {
    "iso:country":"GB",
    "wof:name":"ST10 1TJ",
    "wof:placetype":"postalcode"
},
  "geometry": {"coordinates":[-2.00341462620066,52.98692004622783],"type":"Point"}
}