{
  "type": "Feature",
  "properties": {
    "date:inception_lower": "1980-01-01",
    "date:inception_upper": "1980-01-01",
    "iso:country": "GB",
    "wof:name": "ST10 1TJ",
    "wof:placetype": "postalcode"
  },
  "geometry": {"coordinates":[-2.003415,52.98692],"type":"Point"}
}
