{
  "type": "Feature",
  "properties": {
    "iso:country": "GB",
    "wof:name": "DL12 9HL",
    "wof:placetype": "postalcode"
  },
  "geometry": {"coordinates":[-2.01,54.517158],"type":"Point"}
}
