{
  "type": "Feature",
  "properties": {
    "iso:country":"GB",
    "wof:name":"DL12 9HL",
    "wof:placetype":"postalcode"
},
  "geometry": {"coordinates":[-2.01040934319147,54.51716700645867],"type":"Point"}
}