{
  "type": "Feature",
  "properties": {
    "iso:country": "GB",
    "wof:name": "DL12 9HL",
    "wof:placetype": "postalcode"
  },
  "geometry": {"coordinates":[-2.010409,54.517167],"type":"Point"}
}
