{
  "type": "Feature",
  "properties": {
    "iso:country": "GB",
    "wof:name": "PE22 9QA",
    "wof:placetype": "postalcode"
  },
  "geometry": {"coordinates":[0.08575,53.050163],"type":"Point"}
}
