{
  "type": "Feature",
  "properties": {
    "iso:country":"GB",
    "wof:name":"WR11 4QX",
    "wof:placetype":"postalcode"
},
  "geometry": {"coordinates":[-1.94197586795586,52.09429320950283],"type":"Point"}
}