{
  "type": "Feature",
  "properties": {
    "date:inception_lower": "1980-01-01",
    "date:inception_upper": "1980-01-01",
    "iso:country": "GB",
    "wof:name": "GL7 5HN",
    "wof:placetype": "postalcode"
  },
  "geometry": {"coordinates":[-1.859848,51.707762],"type":"Point"}
}
