{
  "type": "Feature",
  "properties": {
    "iso:country":"GB",
    "wof:name":"GL7 5HN",
    "wof:placetype":"postalcode"
},
  "geometry": {"coordinates":[-1.85984847651031,51.70776156920276],"type":"Point"}
}