{
  "type": "Feature",
  "properties": {
    "iso:country":"GB",
    "wof:name":"G73 4NE",
    "wof:placetype":"postalcode"
},
  "geometry": {"coordinates":[-4.20929026920685,55.81279259558617],"type":"Point"}
}