{
  "type": "Feature",
  "properties": {
    "iso:country":"GB",
    "wof:name":"CT21 4QH",
    "wof:placetype":"postalcode"
},
  "geometry": {"coordinates":[1.07534328588226,51.07964555158147],"type":"Point"}
}