{
  "type": "Feature",
  "properties": {
    "iso:country": "GB",
    "wof:name": "CT21 4QH",
    "wof:placetype": "postalcode"
  },
  "geometry": {"coordinates":[1.075343,51.079646],"type":"Point"}
}
