{
  "type": "Feature",
  "properties": {
    "date:inception_lower": "1980-01-01",
    "date:inception_upper": "1980-01-01",
    "iso:country": "GB",
    "wof:name": "HD2 2QZ",
    "wof:placetype": "postalcode"
  },
  "geometry": {"coordinates":[-1.778999,53.66653],"type":"Point"}
}
