{
  "type": "Feature",
  "properties": {
    "iso:country":"GB",
    "wof:name":"HD2 2QZ",
    "wof:placetype":"postalcode"
},
  "geometry": {"coordinates":[-1.77899866246802,53.66652964176897],"type":"Point"}
}