{
  "type": "Feature",
  "properties": {
    "iso:country":"GB",
    "wof:name":"BS16 6PS",
    "wof:placetype":"postalcode"
},
  "geometry": {"coordinates":[-2.49784812245853,51.49906112359773],"type":"Point"}
}