{
  "type": "Feature",
  "properties": {
    "iso:country":"GB",
    "wof:name":"GL7 3HD",
    "wof:placetype":"postalcode"
},
  "geometry": {"coordinates":[-1.64598590052559,51.69216217716831],"type":"Point"}
}