{
  "type": "Feature",
  "properties": {
    "date:inception_lower":"1980-01-01",
    "date:inception_upper":"1980-01-31",
    "iso:country":"GB",
    "wof:name":"NN11 4LX",
    "wof:placetype":"postalcode"
},
  "geometry": {"coordinates":[-1.150618,52.254799],"type":"Point"}
}