{
  "type": "Feature",
  "properties": {
    "iso:country":"GB",
    "wof:name":"NN11 4LX",
    "wof:placetype":"postalcode"
},
  "geometry": {"coordinates":[-1.1506181732457,52.25479878907041],"type":"Point"}
}