{
  "type": "Feature",
  "properties": {
    "iso:country":"GB",
    "wof:name":"PE16 6HX",
    "wof:placetype":"postalcode"
},
  "geometry": {"coordinates":[0.05605289036945,52.45313240903815],"type":"Point"}
}