{
  "type": "Feature",
  "properties": {
    "iso:country": "GB",
    "wof:name": "PE16 6HX",
    "wof:placetype": "postalcode"
  },
  "geometry": {"coordinates":[0.056053,52.453132],"type":"Point"}
}
