{
  "type": "Feature",
  "properties": {
    "iso:country":"GB",
    "wof:name":"L11 6LD",
    "wof:placetype":"postalcode"
},
  "geometry": {"coordinates":[-2.8926152427376,53.45695346362222],"type":"Point"}
}