{
  "type": "Feature",
  "properties": {
    "iso:country": "GB",
    "wof:name": "CA5 6AJ",
    "wof:placetype": "postalcode"
  },
  "geometry": {"coordinates":[-3.056967,54.84115],"type":"Point"}
}
