{
  "type": "Feature",
  "properties": {
    "iso:country":"GB",
    "wof:name":"WN6 0SE",
    "wof:placetype":"postalcode"
},
  "geometry": {"coordinates":[-2.69254005154099,53.59011633053184],"type":"Point"}
}