{
  "type": "Feature",
  "properties": {
    "iso:country": "GB",
    "wof:name": "WN6 0SE",
    "wof:placetype": "postalcode"
  },
  "geometry": {"coordinates":[-2.69254,53.590116],"type":"Point"}
}
