{
  "type": "Feature",
  "properties": {
    "iso:country": "GB",
    "wof:name": "NR16 1AW",
    "wof:placetype": "postalcode"
  },
  "geometry": {"coordinates":[1.179062,52.541069],"type":"Point"}
}
