{
  "type": "Feature",
  "properties": {
    "date:inception_lower": "1980-01-01",
    "date:inception_upper": "1980-01-01",
    "iso:country": "GB",
    "wof:name": "DY12 3LS",
    "wof:placetype": "postalcode"
  },
  "geometry": {"coordinates":[-2.357705,52.409213],"type":"Point"}
}
