{
  "type": "Feature",
  "properties": {
    "iso:country": "GB",
    "wof:name": "DY12 3LS",
    "wof:placetype": "postalcode"
  },
  "geometry": {"coordinates":[-2.357853,52.409393],"type":"Point"}
}
