{
  "type": "Feature",
  "properties": {
    "iso:country":"GB",
    "wof:name":"DY12 3LS",
    "wof:placetype":"postalcode"
},
  "geometry": {"coordinates":[-2.35770812633984,52.40919937703529],"type":"Point"}
}