{
  "type": "Feature",
  "properties": {
    "iso:country":"GB",
    "wof:name":"PE9 3AH",
    "wof:placetype":"postalcode"
},
  "geometry": {"coordinates":[-0.38204130625053,52.64172182112539],"type":"Point"}
}