{
  "type": "Feature",
  "properties": {
    "date:inception_lower": "1980-01-01",
    "date:inception_upper": "1980-01-01",
    "iso:country": "GB",
    "wof:name": "PE9 3AH",
    "wof:placetype": "postalcode"
  },
  "geometry": {"coordinates":[-0.382041,52.641722],"type":"Point"}
}
