{
  "type": "Feature",
  "properties": {
    "iso:country":"GB",
    "wof:name":"NE65 0ES",
    "wof:placetype":"postalcode"
},
  "geometry": {"coordinates":[-1.58380527869588,55.33198129225922],"type":"Point"}
}