{
  "type": "Feature",
  "properties": {
    "iso:country": "GB",
    "wof:name": "NE65 0ES",
    "wof:placetype": "postalcode"
  },
  "geometry": {"coordinates":[-1.583805,55.331981],"type":"Point"}
}
