{
  "type": "Feature",
  "properties": {
    "iso:country":"GB",
    "wof:name":"S10 5NQ",
    "wof:placetype":"postalcode"
},
  "geometry": {"coordinates":[-1.52022140810968,53.38126129138067],"type":"Point"}
}