{
  "type": "Feature",
  "properties": {
    "iso:country":"GB",
    "wof:name":"CR0 3SB",
    "wof:placetype":"postalcode"
},
  "geometry": {"coordinates":[-0.1100231259269,51.37961640756664],"type":"Point"}
}