{
  "type": "Feature",
  "properties": {
    "date:inception_lower":"1980-01-01",
    "date:inception_upper":"1980-01-31",
    "iso:country":"GB",
    "wof:name":"DD8 1RJ",
    "wof:placetype":"postalcode"
},
  "geometry": {"coordinates":[-3.005308,56.606693],"type":"Point"}
}