{
  "type": "Feature",
  "properties": {
    "date:inception_lower":"2010-09-01",
    "date:inception_upper":"2010-09-30",
    "iso:country":"GB",
    "wof:name":"PO12 1FQ",
    "wof:placetype":"postalcode"
},
  "geometry": {"coordinates":[-1.130257,50.797858],"type":"Point"}
}