{
  "type": "Feature",
  "properties": {
    "iso:country": "GB",
    "wof:name": "NG7 3QH",
    "wof:placetype": "postalcode"
  },
  "geometry": {"coordinates":[-1.166022,52.95737],"type":"Point"}
}
