{
  "type": "Feature",
  "properties": {
    "iso:country":"GB",
    "wof:name":"NG7 3QH",
    "wof:placetype":"postalcode"
},
  "geometry": {"coordinates":[-1.1660223139654,52.95737029215717],"type":"Point"}
}