{
  "type": "Feature",
  "properties": {
    "iso:country":"GB",
    "wof:name":"GU16 8HY",
    "wof:placetype":"postalcode"
},
  "geometry": {"coordinates":[-0.73835591674053,51.3144022994074],"type":"Point"}
}