{
  "type": "Feature",
  "properties": {
    "date:inception_lower": "2004-06-01",
    "date:inception_upper": "2004-06-01",
    "iso:country": "GB",
    "wof:name": "GU23 7DZ",
    "wof:placetype": "postalcode"
  },
  "geometry": {"coordinates":[-0.541338,51.2943],"type":"Point"}
}
