{
  "type": "Feature",
  "properties": {
    "iso:country":"GB",
    "wof:name":"TA21 8HX",
    "wof:placetype":"postalcode"
},
  "geometry": {"coordinates":[-3.23429709289449,50.97951241632875],"type":"Point"}
}