{
  "type": "Feature",
  "properties": {
    "iso:country":"GB",
    "wof:name":"LE2 0AH",
    "wof:placetype":"postalcode"
},
  "geometry": {"coordinates":[-1.11601227740475,52.63577785650258],"type":"Point"}
}