{
  "type": "Feature",
  "properties": {
    "iso:country":"GB",
    "wof:name":"SM2 6SD",
    "wof:placetype":"postalcode"
},
  "geometry": {"coordinates":[-0.19784186475335,51.35609948674448],"type":"Point"}
}