{
  "type": "Feature",
  "properties": {
    "date:inception_lower": "1980-01-01",
    "date:inception_upper": "1980-01-01",
    "iso:country": "GB",
    "wof:name": "CV22 5JZ",
    "wof:placetype": "postalcode"
  },
  "geometry": {"coordinates":[-1.242709,52.358814],"type":"Point"}
}
