{
  "type": "Feature",
  "properties": {
    "iso:country": "GB",
    "wof:name": "SG4 7NH",
    "wof:placetype": "postalcode"
  },
  "geometry": {"coordinates":[-0.271161,51.934448],"type":"Point"}
}
