{
  "type": "Feature",
  "properties": {
    "iso:country":"GB",
    "wof:name":"WS6 6DQ",
    "wof:placetype":"postalcode"
},
  "geometry": {"coordinates":[-2.01268735482938,52.66262565985986],"type":"Point"}
}