{
  "type": "Feature",
  "properties": {
    "iso:country":"GB",
    "wof:name":"EN6 4QQ",
    "wof:placetype":"postalcode"
},
  "geometry": {"coordinates":[-0.11566665799709,51.71691657986462],"type":"Point"}
}