{
  "type": "Feature",
  "properties": {
    "date:inception_lower":"2015-08-01",
    "date:inception_upper":"2015-08-31",
    "iso:country":"GB",
    "wof:name":"E8 3FP",
    "wof:placetype":"postalcode"
},
  "geometry": {"coordinates":[-0.058855,51.53734],"type":"Point"}
}