{
  "type": "Feature",
  "properties": {
    "iso:country":"GB",
    "wof:name":"ST7 4RF",
    "wof:placetype":"postalcode"
},
  "geometry": {"coordinates":[-2.21946776453902,53.09899115064682],"type":"Point"}
}