{
  "type": "Feature",
  "properties": {
    "date:inception_lower": "1980-01-01",
    "date:inception_upper": "1980-01-01",
    "iso:country": "GB",
    "wof:name": "ST7 4RF",
    "wof:placetype": "postalcode"
  },
  "geometry": {"coordinates":[-2.219467,53.099008],"type":"Point"}
}
