{
  "type": "Feature",
  "properties": {
    "iso:country":"GB",
    "wof:name":"OL14 8EZ",
    "wof:placetype":"postalcode"
},
  "geometry": {"coordinates":[-2.1172087519491,53.72619474923889],"type":"Point"}
}