{
  "type": "Feature",
  "properties": {
    "iso:country": "GB",
    "wof:name": "OL14 8EZ",
    "wof:placetype": "postalcode"
  },
  "geometry": {"coordinates":[-2.117209,53.726195],"type":"Point"}
}
