{
  "type": "Feature",
  "properties": {
    "iso:country":"GB",
    "wof:name":"GU12 4QE",
    "wof:placetype":"postalcode"
},
  "geometry": {"coordinates":[-0.74106077017054,51.2422683904884],"type":"Point"}
}