{
  "type": "Feature",
  "properties": {
    "date:inception_lower": "2019-09-01",
    "date:inception_upper": "2019-09-01",
    "iso:country": "GB",
    "wof:name": "BN27 4FB",
    "wof:placetype": "postalcode"
  },
  "geometry": {"coordinates":[0.25977,50.881917],"type":"Point"}
}
