{
  "type": "Feature",
  "properties": {
    "date:inception_lower": "1980-01-01",
    "date:inception_upper": "1980-01-01",
    "iso:country": "GB",
    "wof:name": "NE24 1LX",
    "wof:placetype": "postalcode"
  },
  "geometry": {"coordinates":[-1.512284,55.130558],"type":"Point"}
}
