{
  "type": "Feature",
  "properties": {
    "iso:country":"GB",
    "wof:name":"NE24 1LX",
    "wof:placetype":"postalcode"
},
  "geometry": {"coordinates":[-1.51228404382435,55.13055802161477],"type":"Point"}
}