{
  "type": "Feature",
  "properties": {
    "date:inception_lower":"2012-11-01",
    "date:inception_upper":"2012-11-30",
    "iso:country":"GB",
    "wof:name":"EH9 8AT",
    "wof:placetype":"postalcode"
},
  "geometry": {"coordinates":[-3.19582,55.934239],"type":"Point"}
}