{
  "type": "Feature",
  "properties": {
    "date:inception_lower":"2010-03-01",
    "date:inception_upper":"2010-03-31",
    "iso:country":"GB",
    "wof:name":"SL6 8BW",
    "wof:placetype":"postalcode"
},
  "geometry": {"coordinates":[-0.712364,51.523341],"type":"Point"}
}