{
  "type": "Feature",
  "properties": {
    "iso:country":"GB",
    "wof:name":"SL6 8BW",
    "wof:placetype":"postalcode"
},
  "geometry": {"coordinates":[-0.7123391559474,51.5233291727042],"type":"Point"}
}