{
  "type": "Feature",
  "properties": {
    "iso:country":"GB",
    "wof:name":"DY1 3HZ",
    "wof:placetype":"postalcode"
},
  "geometry": {"coordinates":[-2.09407198339439,52.51409538532594],"type":"Point"}
}