{
  "type": "Feature",
  "properties": {
    "iso:country": "GB",
    "wof:name": "GU11 2JH",
    "wof:placetype": "postalcode"
  },
  "geometry": {"coordinates":[-0.750832,51.27345],"type":"Point"}
}
