{
  "type": "Feature",
  "properties": {
    "iso:country":"GB",
    "wof:name":"HP1 3NP",
    "wof:placetype":"postalcode"
},
  "geometry": {"coordinates":[-0.4958064887698,51.76611616066374],"type":"Point"}
}