{
  "type": "Feature",
  "properties": {
    "date:inception_lower": "1980-01-01",
    "date:inception_upper": "1980-01-01",
    "iso:country": "GB",
    "wof:name": "HP1 3NP",
    "wof:placetype": "postalcode"
  },
  "geometry": {"coordinates":[-0.495806,51.766116],"type":"Point"}
}
