{
  "type": "Feature",
  "properties": {
    "iso:country": "GB",
    "wof:name": "WD25 8EJ",
    "wof:placetype": "postalcode"
  },
  "geometry": {"coordinates":[-0.334851,51.66659],"type":"Point"}
}
