{
  "type": "Feature",
  "properties": {
    "iso:country":"GB",
    "wof:name":"TQ13 7QZ",
    "wof:placetype":"postalcode"
},
  "geometry": {"coordinates":[-3.76699206838001,50.51080622797432],"type":"Point"}
}