{
  "type": "Feature",
  "properties": {
    "iso:country": "GB",
    "wof:name": "TQ13 7QZ",
    "wof:placetype": "postalcode"
  },
  "geometry": {"coordinates":[-3.766992,50.510806],"type":"Point"}
}
