{
  "type": "Feature",
  "properties": {
    "date:inception_lower": "1980-01-01",
    "date:inception_upper": "1980-01-01",
    "iso:country": "GB",
    "wof:name": "OL13 0NH",
    "wof:placetype": "postalcode"
  },
  "geometry": {"coordinates":[-2.23829,53.691402],"type":"Point"}
}
