{
  "type": "Feature",
  "properties": {
    "iso:country":"GB",
    "wof:name":"SR3 1DW",
    "wof:placetype":"postalcode"
},
  "geometry": {"coordinates":[-1.39477862245578,54.87532311715785],"type":"Point"}
}