{
  "type": "Feature",
  "properties": {
    "iso:country":"GB",
    "wof:name":"BN27 2DL",
    "wof:placetype":"postalcode"
},
  "geometry": {"coordinates":[0.25652235871139,50.86000350587118],"type":"Point"}
}