{
  "type": "Feature",
  "properties": {
    "date:inception_lower": "1981-06-01",
    "date:inception_upper": "1981-06-01",
    "iso:country": "GB",
    "wof:name": "BN27 2DL",
    "wof:placetype": "postalcode"
  },
  "geometry": {"coordinates":[0.256593,50.860007],"type":"Point"}
}
