{
  "type": "Feature",
  "properties": {
    "date:inception_lower": "1992-08-01",
    "date:inception_upper": "1992-08-01",
    "iso:country": "GB",
    "wof:name": "CO4 5EL",
    "wof:placetype": "postalcode"
  },
  "geometry": {"coordinates":[0.890111,51.912465],"type":"Point"}
}
