{
  "type": "Feature",
  "properties": {
    "iso:country":"GB",
    "wof:name":"CO4 5EL",
    "wof:placetype":"postalcode"
},
  "geometry": {"coordinates":[0.89011083049251,51.91246487242102],"type":"Point"}
}