{
  "type": "Feature",
  "properties": {
    "iso:country":"GB",
    "wof:name":"PE19 2GD",
    "wof:placetype":"postalcode"
},
  "geometry": {"coordinates":[-0.27477819125919,52.21392343149258],"type":"Point"}
}