{
  "type": "Feature",
  "properties": {
    "date:inception_lower": "2005-06-01",
    "date:inception_upper": "2005-06-01",
    "iso:country": "GB",
    "wof:name": "PE19 2GD",
    "wof:placetype": "postalcode"
  },
  "geometry": {"coordinates":[-0.274778,52.213923],"type":"Point"}
}
