{
  "type": "Feature",
  "properties": {
    "iso:country": "GB",
    "wof:name": "PE19 2GD",
    "wof:placetype": "postalcode"
  },
  "geometry": {"coordinates":[-0.274778,52.213923],"type":"Point"}
}
