{
  "type": "Feature",
  "properties": {
    "iso:country":"GB",
    "wof:name":"EX20 1EW",
    "wof:placetype":"postalcode"
},
  "geometry": {"coordinates":[-3.99530632749554,50.73134201551155],"type":"Point"}
}