{
  "type": "Feature",
  "properties": {
    "date:inception_lower": "1980-01-01",
    "date:inception_upper": "1980-01-01",
    "iso:country": "GB",
    "wof:name": "WN2 5JY",
    "wof:placetype": "postalcode"
  },
  "geometry": {"coordinates":[-2.622495,53.509503],"type":"Point"}
}
