{
  "type": "Feature",
  "properties": {
    "iso:country":"GB",
    "wof:name":"TF9 2SF",
    "wof:placetype":"postalcode"
},
  "geometry": {"coordinates":[-2.40850946771899,52.86377363516497],"type":"Point"}
}