{
  "type": "Feature",
  "properties": {
    "iso:country":"GB",
    "wof:name":"PO13 9LE",
    "wof:placetype":"postalcode"
},
  "geometry": {"coordinates":[-1.20244175893893,50.80185414438582],"type":"Point"}
}