{
  "type": "Feature",
  "properties": {
    "iso:country":"GB",
    "wof:name":"W1F 8RQ",
    "wof:placetype":"postalcode"
},
  "geometry": {"coordinates":[-0.13534272559117,51.51421874149462],"type":"Point"}
}