{
  "type": "Feature",
  "properties": {
    "iso:country":"GB",
    "wof:name":"SP7 9LE",
    "wof:placetype":"postalcode"
},
  "geometry": {"coordinates":[-2.19307494793993,51.02384134376712],"type":"Point"}
}