{
  "type": "Feature",
  "properties": {
    "iso:country":"GB",
    "wof:name":"IV41 8PL",
    "wof:placetype":"postalcode"
},
  "geometry": {"coordinates":[-5.72805382830365,57.27286639745666],"type":"Point"}
}