{
  "type": "Feature",
  "properties": {
    "iso:country": "GB",
    "wof:name": "IV41 8PL",
    "wof:placetype": "postalcode"
  },
  "geometry": {"coordinates":[-5.728054,57.272866],"type":"Point"}
}
