{
  "type": "Feature",
  "properties": {
    "iso:country":"GB",
    "wof:name":"DA3 8LX",
    "wof:placetype":"postalcode"
},
  "geometry": {"coordinates":[0.28754427097502,51.38181757321772],"type":"Point"}
}