{
  "type": "Feature",
  "properties": {
    "iso:country":"GB",
    "wof:name":"CT11 8HB",
    "wof:placetype":"postalcode"
},
  "geometry": {"coordinates":[1.42091442754838,51.33443543563801],"type":"Point"}
}