{
  "type": "Feature",
  "properties": {
    "date:inception_lower": "1997-12-01",
    "date:inception_upper": "1997-12-01",
    "iso:country": "GB",
    "wof:name": "CT11 8HB",
    "wof:placetype": "postalcode"
  },
  "geometry": {"coordinates":[1.420914,51.334435],"type":"Point"}
}
