{
  "type": "Feature",
  "properties": {
    "date:inception_lower": "1994-05-01",
    "date:inception_upper": "1994-05-01",
    "iso:country": "GB",
    "wof:name": "M28 2JP",
    "wof:placetype": "postalcode"
  },
  "geometry": {"coordinates":[-2.388081,53.507621],"type":"Point"}
}
