{
  "type": "Feature",
  "properties": {
    "iso:country":"GB",
    "wof:name":"E17 5JZ",
    "wof:placetype":"postalcode"
},
  "geometry": {"coordinates":[-0.02574580687394,51.59094840508335],"type":"Point"}
}