{
  "type": "Feature",
  "properties": {
    "iso:country": "GB",
    "wof:name": "WS13 7TA",
    "wof:placetype": "postalcode"
  },
  "geometry": {"coordinates":[-1.821182,52.701982],"type":"Point"}
}
