{
  "type": "Feature",
  "properties": {
    "date:inception_lower": "2008-10-01",
    "date:inception_upper": "2008-10-01",
    "iso:country": "GB",
    "wof:name": "DD1 5AZ",
    "wof:placetype": "postalcode"
  },
  "geometry": {"coordinates":[-2.986702,56.462651],"type":"Point"}
}
