{
  "type": "Feature",
  "properties": {
    "date:inception_lower": "1990-08-01",
    "date:inception_upper": "1990-08-01",
    "iso:country": "GB",
    "wof:name": "AB51 8XR",
    "wof:placetype": "postalcode"
  },
  "geometry": {"coordinates":[-2.505104,57.43714],"type":"Point"}
}
