{
  "type": "Feature",
  "properties": {
    "iso:country": "GB",
    "wof:name": "AB51 8XR",
    "wof:placetype": "postalcode"
  },
  "geometry": {"coordinates":[-2.505104,57.43714],"type":"Point"}
}
