{
  "type": "Feature",
  "properties": {
    "iso:country":"GB",
    "wof:name":"AB51 8XR",
    "wof:placetype":"postalcode"
},
  "geometry": {"coordinates":[-2.50510443660163,57.43714001694367],"type":"Point"}
}