{
  "type": "Feature",
  "properties": {
    "date:inception_lower": "2011-02-01",
    "date:inception_upper": "2011-02-01",
    "iso:country": "GB",
    "wof:name": "DL14 6ZG",
    "wof:placetype": "postalcode"
  },
  "geometry": {"coordinates":[-1.669042,54.648615],"type":"Point"}
}
