{
  "type": "Feature",
  "properties": {
    "iso:country":"GB",
    "wof:name":"WF11 0HY",
    "wof:placetype":"postalcode"
},
  "geometry": {"coordinates":[-1.24638766730348,53.70594364455049],"type":"Point"}
}