{
  "type": "Feature",
  "properties": {
    "iso:country": "GB",
    "wof:name": "TW5 9AG",
    "wof:placetype": "postalcode"
  },
  "geometry": {"coordinates":[-0.387615,51.477816],"type":"Point"}
}
