{
  "type": "Feature",
  "properties": {
    "iso:country":"GB",
    "wof:name":"S43 4QL",
    "wof:placetype":"postalcode"
},
  "geometry": {"coordinates":[-1.27266615892427,53.27707874424417],"type":"Point"}
}