{
  "type": "Feature",
  "properties": {
    "iso:country": "GB",
    "wof:name": "S43 4QL",
    "wof:placetype": "postalcode"
  },
  "geometry": {"coordinates":[-1.272666,53.277079],"type":"Point"}
}
