{
  "type": "Feature",
  "properties": {
    "iso:country":"GB",
    "wof:name":"G64 1GB",
    "wof:placetype":"postalcode"
},
  "geometry": {"coordinates":[-4.19413023346126,55.89955812466528],"type":"Point"}
}