{
  "type": "Feature",
  "properties": {
    "date:inception_lower":"2002-10-01",
    "date:inception_upper":"2002-10-31",
    "iso:country":"GB",
    "wof:name":"G64 1GB",
    "wof:placetype":"postalcode"
},
  "geometry": {"coordinates":[-4.19413,55.899558],"type":"Point"}
}