{
  "type": "Feature",
  "properties": {
    "iso:country":"GB",
    "wof:name":"BH8 0DQ",
    "wof:placetype":"postalcode"
},
  "geometry": {"coordinates":[-1.8410893650003,50.75907604874945],"type":"Point"}
}