{
  "type": "Feature",
  "properties": {
    "date:inception_lower": "2017-06-01",
    "date:inception_upper": "2017-06-01",
    "iso:country": "GB",
    "wof:name": "PE7 8PZ",
    "wof:placetype": "postalcode"
  },
  "geometry": {"coordinates":[-0.256099,52.535398],"type":"Point"}
}
