{
  "type": "Feature",
  "properties": {
    "iso:country":"GB",
    "wof:name":"EX10 0PN",
    "wof:placetype":"postalcode"
},
  "geometry": {"coordinates":[-3.19236795646329,50.69180706939978],"type":"Point"}
}