{
  "type": "Feature",
  "properties": {
    "date:inception_lower": "1980-01-01",
    "date:inception_upper": "1980-01-01",
    "iso:country": "GB",
    "wof:name": "EX10 0PN",
    "wof:placetype": "postalcode"
  },
  "geometry": {"coordinates":[-3.193391,50.691533],"type":"Point"}
}
