{
  "type": "Feature",
  "properties": {
    "date:inception_lower": "2018-04-01",
    "date:inception_upper": "2018-04-01",
    "iso:country": "GB",
    "wof:name": "EC1N 7AA",
    "wof:placetype": "postalcode"
  },
  "geometry": {"coordinates":[-0.111384,51.52069],"type":"Point"}
}
