{
  "type": "Feature",
  "properties": {
    "iso:country": "GB",
    "wof:name": "RH11 8QW",
    "wof:placetype": "postalcode"
  },
  "geometry": {"coordinates":[-0.196953,51.103198],"type":"Point"}
}
