{
  "type": "Feature",
  "properties": {
    "date:inception_lower":"1980-01-01",
    "date:inception_upper":"1980-01-31",
    "iso:country":"GB",
    "wof:name":"ST17 4NX",
    "wof:placetype":"postalcode"
},
  "geometry": {"coordinates":[-2.096291,52.793314],"type":"Point"}
}