{
  "type": "Feature",
  "properties": {
    "iso:country":"GB",
    "wof:name":"FK2 9GN",
    "wof:placetype":"postalcode"
},
  "geometry": {"coordinates":[-3.75497866805866,55.98463070766514],"type":"Point"}
}