{
  "type": "Feature",
  "properties": {
    "date:inception_lower":"2012-11-01",
    "date:inception_upper":"2012-11-30",
    "iso:country":"GB",
    "wof:name":"FK2 9GN",
    "wof:placetype":"postalcode"
},
  "geometry": {"coordinates":[-3.754979,55.984631],"type":"Point"}
}