{
  "type": "Feature",
  "properties": {
    "date:inception_lower": "1980-01-01",
    "date:inception_upper": "1980-01-01",
    "iso:country": "GB",
    "wof:name": "PO5 2RF",
    "wof:placetype": "postalcode"
  },
  "geometry": {"coordinates":[-1.07907,50.785836],"type":"Point"}
}
