{
  "type": "Feature",
  "properties": {
    "iso:country":"GB",
    "wof:name":"PO5 2RF",
    "wof:placetype":"postalcode"
},
  "geometry": {"coordinates":[-1.07875852445767,50.78580842546396],"type":"Point"}
}