{
  "type": "Feature",
  "properties": {
    "iso:country":"GB",
    "wof:name":"AL1 3DQ",
    "wof:placetype":"postalcode"
},
  "geometry": {"coordinates":[-0.33307162424422,51.75796844776196],"type":"Point"}
}