{
  "type": "Feature",
  "properties": {
    "iso:country":"GB",
    "wof:name":"W13 8PR",
    "wof:placetype":"postalcode"
},
  "geometry": {"coordinates":[-0.31648219916929,51.51480931166963],"type":"Point"}
}