{
  "type": "Feature",
  "properties": {
    "date:inception_lower": "1992-08-01",
    "date:inception_upper": "1992-08-01",
    "iso:country": "GB",
    "wof:name": "SS13 3QU",
    "wof:placetype": "postalcode"
  },
  "geometry": {"coordinates":[0.502763,51.574103],"type":"Point"}
}
