{
  "type": "Feature",
  "properties": {
    "iso:country":"GB",
    "wof:name":"SS13 3QU",
    "wof:placetype":"postalcode"
},
  "geometry": {"coordinates":[0.50276277627606,51.57410272423728],"type":"Point"}
}