{
  "type": "Feature",
  "properties": {
    "iso:country": "GB",
    "wof:name": "CW1 5TP",
    "wof:placetype": "postalcode"
  },
  "geometry": {"coordinates":[-2.385372,53.110228],"type":"Point"}
}
