{
  "type": "Feature",
  "properties": {
    "iso:country": "GB",
    "wof:name": "IP15 5QF",
    "wof:placetype": "postalcode"
  },
  "geometry": {"coordinates":[1.584146,52.173819],"type":"Point"}
}
