{
  "type": "Feature",
  "properties": {
    "iso:country":"GB",
    "wof:name":"TQ12 3DN",
    "wof:placetype":"postalcode"
},
  "geometry": {"coordinates":[-3.58628661436478,50.54898839986069],"type":"Point"}
}