{
  "type": "Feature",
  "properties": {
    "iso:country": "GB",
    "wof:name": "TQ12 3DN",
    "wof:placetype": "postalcode"
  },
  "geometry": {"coordinates":[-3.586287,50.548988],"type":"Point"}
}
