{
  "type": "Feature",
  "properties": {
    "iso:country":"GB",
    "wof:name":"TS25 3SA",
    "wof:placetype":"postalcode"
},
  "geometry": {"coordinates":[-1.24739673423082,54.66005769420291],"type":"Point"}
}