{
  "type": "Feature",
  "properties": {
    "iso:country":"GB",
    "wof:name":"IG1 3JR",
    "wof:placetype":"postalcode"
},
  "geometry": {"coordinates":[0.06342709523207,51.5682366390531],"type":"Point"}
}