{
  "type": "Feature",
  "properties": {
    "iso:country": "GB",
    "wof:name": "UB10 0GF",
    "wof:placetype": "postalcode"
  },
  "geometry": {"coordinates":[-0.468927,51.539495],"type":"Point"}
}
