{
  "type": "Feature",
  "properties": {
    "iso:country":"GB",
    "wof:name":"UB10 0GF",
    "wof:placetype":"postalcode"
},
  "geometry": {"coordinates":[-0.4689270808461,51.53949536034323],"type":"Point"}
}