{
  "type": "Feature",
  "properties": {
    "date:inception_lower": "2003-09-01",
    "date:inception_upper": "2003-09-01",
    "iso:country": "GB",
    "wof:name": "PO19 8EN",
    "wof:placetype": "postalcode"
  },
  "geometry": {"coordinates":[-0.772598,50.831209],"type":"Point"}
}
