{
  "type": "Feature",
  "properties": {
    "date:inception_lower": "1980-01-01",
    "date:inception_upper": "1980-01-01",
    "iso:country": "GB",
    "wof:name": "RH12 4ST",
    "wof:placetype": "postalcode"
  },
  "geometry": {"coordinates":[-0.239707,51.095995],"type":"Point"}
}
