{
  "type": "Feature",
  "properties": {
    "iso:country": "GB",
    "wof:name": "B65 0DT",
    "wof:placetype": "postalcode"
  },
  "geometry": {"coordinates":[-2.040128,52.475431],"type":"Point"}
}
