{
  "type": "Feature",
  "properties": {
    "iso:country":"GB",
    "wof:name":"B65 0DT",
    "wof:placetype":"postalcode"
},
  "geometry": {"coordinates":[-2.04019297106531,52.47541540285549],"type":"Point"}
}