{
  "type": "Feature",
  "properties": {
    "iso:country": "GB",
    "wof:name": "IP24 3AW",
    "wof:placetype": "postalcode"
  },
  "geometry": {"coordinates":[0.745836,52.411291],"type":"Point"}
}
