{
  "type": "Feature",
  "properties": {
    "date:inception_lower": "1980-01-01",
    "date:inception_upper": "1980-01-01",
    "iso:country": "GB",
    "wof:name": "IP24 3AW",
    "wof:placetype": "postalcode"
  },
  "geometry": {"coordinates":[0.745836,52.411291],"type":"Point"}
}
