{
  "type": "Feature",
  "properties": {
    "iso:country":"GB",
    "wof:name":"IP24 3AW",
    "wof:placetype":"postalcode"
},
  "geometry": {"coordinates":[0.74583633643625,52.41129128535408],"type":"Point"}
}