{
  "type": "Feature",
  "properties": {
    "date:inception_lower": "2021-09-01",
    "date:inception_upper": "2021-09-01",
    "iso:country": "GB",
    "wof:name": "SS11 8GL",
    "wof:placetype": "postalcode"
  },
  "geometry": {"coordinates":[0.523608,51.613537],"type":"Point"}
}
