{
  "type": "Feature",
  "properties": {
    "date:inception_lower":"1980-01-01",
    "date:inception_upper":"1980-01-31",
    "iso:country":"GB",
    "wof:name":"NP7 7EW",
    "wof:placetype":"postalcode"
},
  "geometry": {"coordinates":[-3.043895,51.830973],"type":"Point"}
}