{
  "type": "Feature",
  "properties": {
    "iso:country": "GB",
    "wof:name": "SK9 4AY",
    "wof:placetype": "postalcode"
  },
  "geometry": {"coordinates":[-2.228157,53.337969],"type":"Point"}
}
