{
  "type": "Feature",
  "properties": {
    "date:inception_lower": "2006-02-01",
    "date:inception_upper": "2006-02-01",
    "iso:country": "GB",
    "wof:name": "SK9 4AY",
    "wof:placetype": "postalcode"
  },
  "geometry": {"coordinates":[-2.228157,53.337969],"type":"Point"}
}
