{
  "type": "Feature",
  "properties": {
    "iso:country":"GB",
    "wof:name":"SK9 4AY",
    "wof:placetype":"postalcode"
},
  "geometry": {"coordinates":[-2.22787206303226,53.33784510664341],"type":"Point"}
}