{
  "type": "Feature",
  "properties": {
    "date:inception_lower": "1980-01-01",
    "date:inception_upper": "1980-01-01",
    "iso:country": "GB",
    "wof:name": "DN6 8RA",
    "wof:placetype": "postalcode"
  },
  "geometry": {"coordinates":[-1.209679,53.591132],"type":"Point"}
}
