{
  "type": "Feature",
  "properties": {
    "date:inception_lower": "1980-01-01",
    "date:inception_upper": "1980-01-01",
    "iso:country": "GB",
    "wof:name": "KA17 0LS",
    "wof:placetype": "postalcode"
  },
  "geometry": {"coordinates":[-4.266018,55.59894],"type":"Point"}
}
