{
  "type": "Feature",
  "properties": {
    "iso:country": "GB",
    "wof:name": "KA17 0LS",
    "wof:placetype": "postalcode"
  },
  "geometry": {"coordinates":[-4.266018,55.59894],"type":"Point"}
}
