{
  "type": "Feature",
  "properties": {
    "iso:country":"GB",
    "wof:name":"KA17 0LS",
    "wof:placetype":"postalcode"
},
  "geometry": {"coordinates":[-4.26603207480277,55.59894057744899],"type":"Point"}
}