{
  "type": "Feature",
  "properties": {
    "iso:country":"GB",
    "wof:name":"HR9 7UQ",
    "wof:placetype":"postalcode"
},
  "geometry": {"coordinates":[-2.50549308675857,51.93334888497888],"type":"Point"}
}