{
  "type": "Feature",
  "properties": {
    "iso:country": "GB",
    "wof:name": "HR9 7UQ",
    "wof:placetype": "postalcode"
  },
  "geometry": {"coordinates":[-2.505493,51.933349],"type":"Point"}
}
