{
  "type": "Feature",
  "properties": {
    "date:inception_lower": "2020-12-01",
    "date:inception_upper": "2020-12-01",
    "iso:country": "GB",
    "wof:name": "BN10 8FN",
    "wof:placetype": "postalcode"
  },
  "geometry": {"coordinates":[0.009827,50.798972],"type":"Point"}
}
