{
  "type": "Feature",
  "properties": {
    "iso:country": "GB",
    "wof:name": "CF47 8AX",
    "wof:placetype": "postalcode"
  },
  "geometry": {"coordinates":[-3.377576,51.755447],"type":"Point"}
}
