{
  "type": "Feature",
  "properties": {
    "iso:country":"GB",
    "wof:name":"S61 4QQ",
    "wof:placetype":"postalcode"
},
  "geometry": {"coordinates":[-1.35962400505451,53.44111905621884],"type":"Point"}
}