{
  "type": "Feature",
  "properties": {
    "date:inception_lower": "1980-01-01",
    "date:inception_upper": "1980-01-01",
    "iso:country": "GB",
    "wof:name": "SK11 7SD",
    "wof:placetype": "postalcode"
  },
  "geometry": {"coordinates":[-2.126309,53.247668],"type":"Point"}
}
