{
  "type": "Feature",
  "properties": {
    "date:inception_lower": "2024-08-01",
    "date:inception_upper": "2024-08-01",
    "iso:country": "GB",
    "wof:name": "L23 4AH",
    "wof:placetype": "postalcode"
  },
  "geometry": {"coordinates":[-2.99912,53.503075],"type":"Point"}
}
