{
  "type": "Feature",
  "properties": {
    "iso:country": "GB",
    "wof:name": "SO31 7PE",
    "wof:placetype": "postalcode"
  },
  "geometry": {"coordinates":[-1.276084,50.871397],"type":"Point"}
}
