{
  "type": "Feature",
  "properties": {
    "date:inception_lower":"1983-03-01",
    "date:inception_upper":"1983-03-31",
    "iso:country":"GB",
    "wof:name":"S3 8AA",
    "wof:placetype":"postalcode"
},
  "geometry": {"coordinates":[-1.484915,53.39564],"type":"Point"}
}