{
  "type": "Feature",
  "properties": {
    "date:inception_lower": "1983-03-01",
    "date:inception_upper": "1983-03-01",
    "iso:country": "GB",
    "wof:name": "S3 8AA",
    "wof:placetype": "postalcode"
  },
  "geometry": {"coordinates":[-1.484975,53.395676],"type":"Point"}
}
