{
  "type": "Feature",
  "properties": {
    "iso:country": "GB",
    "wof:name": "S3 8AA",
    "wof:placetype": "postalcode"
  },
  "geometry": {"coordinates":[-1.484915,53.39564],"type":"Point"}
}
