{
  "type": "Feature",
  "properties": {
    "date:inception_lower": "1980-01-01",
    "date:inception_upper": "1980-01-01",
    "iso:country": "GB",
    "wof:name": "WR14 3QT",
    "wof:placetype": "postalcode"
  },
  "geometry": {"coordinates":[-2.294649,52.106095],"type":"Point"}
}
