{
  "type": "Feature",
  "properties": {
    "iso:country": "GB",
    "wof:name": "SG10 6FF",
    "wof:placetype": "postalcode"
  },
  "geometry": {"coordinates":[0.108939,51.851789],"type":"Point"}
}
