{
  "type": "Feature",
  "properties": {
    "date:inception_lower": "2018-12-01",
    "date:inception_upper": "2018-12-01",
    "iso:country": "GB",
    "wof:name": "SG10 6FF",
    "wof:placetype": "postalcode"
  },
  "geometry": {"coordinates":[0.108939,51.851789],"type":"Point"}
}
