{
  "type": "Feature",
  "properties": {
    "iso:country":"GB",
    "wof:name":"WR3 7LR",
    "wof:placetype":"postalcode"
},
  "geometry": {"coordinates":[-2.22727811711956,52.21625032634483],"type":"Point"}
}