{
  "type": "Feature",
  "properties": {
    "date:inception_lower": "1980-01-01",
    "date:inception_upper": "1980-01-01",
    "iso:country": "GB",
    "wof:name": "WR3 7LR",
    "wof:placetype": "postalcode"
  },
  "geometry": {"coordinates":[-2.227278,52.21625],"type":"Point"}
}
