{
  "type": "Feature",
  "properties": {
    "iso:country": "GB",
    "wof:name": "GU5 0ES",
    "wof:placetype": "postalcode"
  },
  "geometry": {"coordinates":[-0.559102,51.194773],"type":"Point"}
}
