{
  "type": "Feature",
  "properties": {
    "date:inception_lower":"2003-09-01",
    "date:inception_upper":"2003-09-30",
    "iso:country":"GB",
    "wof:name":"GU5 0ES",
    "wof:placetype":"postalcode"
},
  "geometry": {"coordinates":[-0.559102,51.194773],"type":"Point"}
}