{
  "type": "Feature",
  "properties": {
    "iso:country": "GB",
    "wof:name": "DY5 1HT",
    "wof:placetype": "postalcode"
  },
  "geometry": {"coordinates":[-2.117586,52.493026],"type":"Point"}
}
