{
  "type": "Feature",
  "properties": {
    "date:inception_lower": "1980-01-01",
    "date:inception_upper": "1980-01-01",
    "iso:country": "GB",
    "wof:name": "LE13 0DJ",
    "wof:placetype": "postalcode"
  },
  "geometry": {"coordinates":[-0.888036,52.74983],"type":"Point"}
}
