{
  "type": "Feature",
  "properties": {
    "iso:country":"GB",
    "wof:name":"LE13 0DJ",
    "wof:placetype":"postalcode"
},
  "geometry": {"coordinates":[-0.88803653310863,52.74983012970877],"type":"Point"}
}