{
  "type": "Feature",
  "properties": {
    "iso:country": "GB",
    "wof:name": "SA12 9LR",
    "wof:placetype": "postalcode"
  },
  "geometry": {"coordinates":[-3.773102,51.616237],"type":"Point"}
}
