{
  "type": "Feature",
  "properties": {
    "iso:country": "GB",
    "wof:name": "DN22 0JB",
    "wof:placetype": "postalcode"
  },
  "geometry": {"coordinates":[-0.818267,53.293947],"type":"Point"}
}
