{
  "type": "Feature",
  "properties": {
    "date:inception_lower":"1980-01-01",
    "date:inception_upper":"1980-01-31",
    "iso:country":"GB",
    "wof:name":"TF6 6AW",
    "wof:placetype":"postalcode"
},
  "geometry": {"coordinates":[-2.605276,52.761312],"type":"Point"}
}