{
  "type": "Feature",
  "properties": {
    "iso:country":"GB",
    "wof:name":"TF6 6AW",
    "wof:placetype":"postalcode"
},
  "geometry": {"coordinates":[-2.60527848393127,52.76129704790031],"type":"Point"}
}