{
  "type": "Feature",
  "properties": {
    "iso:country":"GB",
    "wof:name":"RG41 5PG",
    "wof:placetype":"postalcode"
},
  "geometry": {"coordinates":[-0.88185394953456,51.42658795850434],"type":"Point"}
}