{
  "type": "Feature",
  "properties": {
    "iso:country":"GB",
    "wof:name":"SS17 0SA",
    "wof:placetype":"postalcode"
},
  "geometry": {"coordinates":[0.43442704316693,51.51579870495402],"type":"Point"}
}