{
  "type": "Feature",
  "properties": {
    "iso:country":"GB",
    "wof:name":"EC4M 7BG",
    "wof:placetype":"postalcode"
},
  "geometry": {"coordinates":[-0.10235458767399,51.51417525104594],"type":"Point"}
}