{
  "type": "Feature",
  "properties": {
    "date:inception_lower": "1998-12-01",
    "date:inception_upper": "1998-12-01",
    "iso:country": "GB",
    "wof:name": "EC4M 7BG",
    "wof:placetype": "postalcode"
  },
  "geometry": {"coordinates":[-0.102312,51.51424],"type":"Point"}
}
