{
  "type": "Feature",
  "properties": {
    "date:inception_lower": "1980-01-01",
    "date:inception_upper": "1980-01-01",
    "iso:country": "GB",
    "wof:name": "E8 1JW",
    "wof:placetype": "postalcode"
  },
  "geometry": {"coordinates":[-0.056255,51.54788],"type":"Point"}
}
