{
  "type": "Feature",
  "properties": {
    "iso:country": "GB",
    "wof:name": "FK1 2EB",
    "wof:placetype": "postalcode"
  },
  "geometry": {"coordinates":[-3.764479,55.973604],"type":"Point"}
}
