{
  "type": "Feature",
  "properties": {
    "iso:country":"GB",
    "wof:name":"G72 7LR",
    "wof:placetype":"postalcode"
},
  "geometry": {"coordinates":[-4.15311981136429,55.81819299937024],"type":"Point"}
}