{
  "type": "Feature",
  "properties": {
    "date:inception_lower":"1980-01-01",
    "date:inception_upper":"1980-01-31",
    "iso:country":"GB",
    "wof:name":"G72 7LR",
    "wof:placetype":"postalcode"
},
  "geometry": {"coordinates":[-4.15312,55.818193],"type":"Point"}
}