{
  "type": "Feature",
  "properties": {
    "iso:country": "GB",
    "wof:name": "SY11 1JL",
    "wof:placetype": "postalcode"
  },
  "geometry": {"coordinates":[-3.05683,52.860168],"type":"Point"}
}
