{
  "type": "Feature",
  "properties": {
    "date:inception_lower": "1980-01-01",
    "date:inception_upper": "1980-01-01",
    "iso:country": "GB",
    "wof:name": "CO9 4LN",
    "wof:placetype": "postalcode"
  },
  "geometry": {"coordinates":[0.581122,52.022785],"type":"Point"}
}
