{
  "type": "Feature",
  "properties": {
    "iso:country":"GB",
    "wof:name":"CA1 3HJ",
    "wof:placetype":"postalcode"
},
  "geometry": {"coordinates":[-2.89605301629683,54.87089860688068],"type":"Point"}
}