{
  "type": "Feature",
  "properties": {
    "iso:country":"GB",
    "wof:name":"EX3 0AW",
    "wof:placetype":"postalcode"
},
  "geometry": {"coordinates":[-3.46242318392147,50.68018725683159],"type":"Point"}
}