{
  "type": "Feature",
  "properties": {
    "iso:country":"GB",
    "wof:name":"N1 3BY",
    "wof:placetype":"postalcode"
},
  "geometry": {"coordinates":[-0.09243282811229,51.54053331177543],"type":"Point"}
}