{
  "type": "Feature",
  "properties": {
    "iso:country":"GB",
    "wof:name":"YO61 1ST",
    "wof:placetype":"postalcode"
},
  "geometry": {"coordinates":[-1.26985861964461,54.10118423679627],"type":"Point"}
}