{
  "type": "Feature",
  "properties": {
    "iso:country":"GB",
    "wof:name":"S66 7LW",
    "wof:placetype":"postalcode"
},
  "geometry": {"coordinates":[-1.19663394550696,53.42082663410086],"type":"Point"}
}