{
  "type": "Feature",
  "properties": {
    "date:inception_lower": "1992-08-01",
    "date:inception_upper": "1992-08-01",
    "iso:country": "GB",
    "wof:name": "LE7 4SP",
    "wof:placetype": "postalcode"
  },
  "geometry": {"coordinates":[-1.081798,52.724637],"type":"Point"}
}
