{
  "type": "Feature",
  "properties": {
    "iso:country":"GB",
    "wof:name":"LE7 4SP",
    "wof:placetype":"postalcode"
},
  "geometry": {"coordinates":[-1.08119358845211,52.72412704855812],"type":"Point"}
}