{
  "type": "Feature",
  "properties": {
    "date:inception_lower": "2022-07-01",
    "date:inception_upper": "2022-07-01",
    "iso:country": "GB",
    "wof:name": "PL25 5FQ",
    "wof:placetype": "postalcode"
  },
  "geometry": {"coordinates":[-4.803469,50.331599],"type":"Point"}
}
