{
  "type": "Feature",
  "properties": {
    "iso:country": "GB",
    "wof:name": "YO25 9LJ",
    "wof:placetype": "postalcode"
  },
  "geometry": {"coordinates":[-0.569107,53.942961],"type":"Point"}
}
