{
  "type": "Feature",
  "properties": {
    "iso:country":"GB",
    "wof:name":"YO25 9LJ",
    "wof:placetype":"postalcode"
},
  "geometry": {"coordinates":[-0.56910665596223,53.94296083201188],"type":"Point"}
}