{
  "type": "Feature",
  "properties": {
    "iso:country": "GB",
    "wof:name": "M16 0HZ",
    "wof:placetype": "postalcode"
  },
  "geometry": {"coordinates":[-2.284124,53.452176],"type":"Point"}
}
