{
  "type": "Feature",
  "properties": {
    "iso:country":"GB",
    "wof:name":"M16 0HZ",
    "wof:placetype":"postalcode"
},
  "geometry": {"coordinates":[-2.28412440768176,53.45217610831568],"type":"Point"}
}