{
  "type": "Feature",
  "properties": {
    "iso:country": "GB",
    "wof:name": "CM4 0RN",
    "wof:placetype": "postalcode"
  },
  "geometry": {"coordinates":[0.318131,51.691797],"type":"Point"}
}
