{
  "type": "Feature",
  "properties": {
    "iso:country":"GB",
    "wof:name":"CM4 0RN",
    "wof:placetype":"postalcode"
},
  "geometry": {"coordinates":[0.31808853077584,51.69177468930864],"type":"Point"}
}