{
  "type": "Feature",
  "properties": {
    "iso:country":"GB",
    "wof:name":"SO23 7JG",
    "wof:placetype":"postalcode"
},
  "geometry": {"coordinates":[-1.30439405341996,51.08861036647455],"type":"Point"}
}