{
  "type": "Feature",
  "properties": {
    "iso:country":"GB",
    "wof:name":"CM1 3BZ",
    "wof:placetype":"postalcode"
},
  "geometry": {"coordinates":[0.44513245156439,51.72851567513144],"type":"Point"}
}