{
  "type": "Feature",
  "properties": {
    "date:inception_lower":"2001-12-01",
    "date:inception_upper":"2001-12-31",
    "iso:country":"GB",
    "wof:name":"NG7 2GS",
    "wof:placetype":"postalcode"
},
  "geometry": {"coordinates":[-1.180885,52.949131],"type":"Point"}
}