{
  "type": "Feature",
  "properties": {
    "date:inception_lower": "2021-01-01",
    "date:inception_upper": "2021-01-01",
    "iso:country": "GB",
    "wof:name": "TS18 2GE",
    "wof:placetype": "postalcode"
  },
  "geometry": {"coordinates":[-1.309558,54.568504],"type":"Point"}
}
