{
  "type": "Feature",
  "properties": {
    "iso:country":"GB",
    "wof:name":"CF3 5PJ",
    "wof:placetype":"postalcode"
},
  "geometry": {"coordinates":[-3.12351200883426,51.52962352324217],"type":"Point"}
}