{
  "type": "Feature",
  "properties": {
    "iso:country":"GB",
    "wof:name":"BD12 0EN",
    "wof:placetype":"postalcode"
},
  "geometry": {"coordinates":[-1.77645561303298,53.75531843472548],"type":"Point"}
}