{
  "type": "Feature",
  "properties": {
    "iso:country":"GB",
    "wof:name":"NE11 0NS",
    "wof:placetype":"postalcode"
},
  "geometry": {"coordinates":[-1.6204215214941,54.93336353884563],"type":"Point"}
}