{
  "type": "Feature",
  "properties": {
    "iso:country":"GB",
    "wof:name":"CM11 2ED",
    "wof:placetype":"postalcode"
},
  "geometry": {"coordinates":[0.43191762246302,51.62688070423407],"type":"Point"}
}