{
  "type": "Feature",
  "properties": {
    "date:inception_lower":"1980-01-01",
    "date:inception_upper":"1980-01-31",
    "iso:country":"GB",
    "wof:name":"CM11 2ED",
    "wof:placetype":"postalcode"
},
  "geometry": {"coordinates":[0.431918,51.626881],"type":"Point"}
}