{
  "type": "Feature",
  "properties": {
    "iso:country": "GB",
    "wof:name": "BH21 7NT",
    "wof:placetype": "postalcode"
  },
  "geometry": {"coordinates":[-1.917161,50.802166],"type":"Point"}
}
