{
  "type": "Feature",
  "properties": {
    "iso:country":"GB",
    "wof:name":"SY25 6RU",
    "wof:placetype":"postalcode"
},
  "geometry": {"coordinates":[-3.95795607502233,52.17918914160497],"type":"Point"}
}