{
  "type": "Feature",
  "properties": {
    "date:inception_lower": "1980-01-01",
    "date:inception_upper": "1980-01-01",
    "iso:country": "GB",
    "wof:name": "SY25 6RU",
    "wof:placetype": "postalcode"
  },
  "geometry": {"coordinates":[-3.957956,52.179189],"type":"Point"}
}
