{
  "type": "Feature",
  "properties": {
    "iso:country":"GB",
    "wof:name":"PO19 6BU",
    "wof:placetype":"postalcode"
},
  "geometry": {"coordinates":[-0.77894054460571,50.85151895576632],"type":"Point"}
}