{
  "type": "Feature",
  "properties": {
    "iso:country":"GB",
    "wof:name":"BL9 0BL",
    "wof:placetype":"postalcode"
},
  "geometry": {"coordinates":[-2.29651459577196,53.59205952135549],"type":"Point"}
}