{
  "type": "Feature",
  "properties": {
    "date:inception_lower": "1980-01-01",
    "date:inception_upper": "1980-01-01",
    "iso:country": "GB",
    "wof:name": "BL9 0BL",
    "wof:placetype": "postalcode"
  },
  "geometry": {"coordinates":[-2.29671,53.592291],"type":"Point"}
}
