{
  "type": "Feature",
  "properties": {
    "iso:country":"GB",
    "wof:name":"NR30 1NN",
    "wof:placetype":"postalcode"
},
  "geometry": {"coordinates":[1.73020435297794,52.60983186783912],"type":"Point"}
}