{
  "type": "Feature",
  "properties": {
    "iso:country":"GB",
    "wof:name":"LA23 1JA",
    "wof:placetype":"postalcode"
},
  "geometry": {"coordinates":[-2.92390607515819,54.38676190679843],"type":"Point"}
}