{
  "type": "Feature",
  "properties": {
    "date:inception_lower": "1980-01-01",
    "date:inception_upper": "1980-01-01",
    "iso:country": "GB",
    "wof:name": "DG7 3TZ",
    "wof:placetype": "postalcode"
  },
  "geometry": {"coordinates":[-4.180551,55.13902],"type":"Point"}
}
