{
  "type": "Feature",
  "properties": {
    "iso:country":"GB",
    "wof:name":"GL50 4DF",
    "wof:placetype":"postalcode"
},
  "geometry": {"coordinates":[-2.07685983657295,51.90494705751772],"type":"Point"}
}