{
  "type": "Feature",
  "properties": {
    "date:inception_lower": "1993-01-01",
    "date:inception_upper": "1993-01-01",
    "iso:country": "GB",
    "wof:name": "CO10 8TB",
    "wof:placetype": "postalcode"
  },
  "geometry": {"coordinates":[0.505243,52.070652],"type":"Point"}
}
