{
  "type": "Feature",
  "properties": {
    "iso:country":"GB",
    "wof:name":"CO10 8TB",
    "wof:placetype":"postalcode"
},
  "geometry": {"coordinates":[0.5052429565742,52.07065167247387],"type":"Point"}
}