{
  "type": "Feature",
  "properties": {
    "iso:country": "GB",
    "wof:name": "M16 7GJ",
    "wof:placetype": "postalcode"
  },
  "geometry": {"coordinates":[-2.255484,53.454713],"type":"Point"}
}
