{
  "type": "Feature",
  "properties": {
    "iso:country": "GB",
    "wof:name": "PE27 5FY",
    "wof:placetype": "postalcode"
  },
  "geometry": {"coordinates":[-0.063512,52.329577],"type":"Point"}
}
