{
  "type": "Feature",
  "properties": {
    "iso:country":"GB",
    "wof:name":"DT6 4JG",
    "wof:placetype":"postalcode"
},
  "geometry": {"coordinates":[-2.75031326928525,50.71765904695584],"type":"Point"}
}