{
  "type": "Feature",
  "properties": {
    "iso:country":"GB",
    "wof:name":"LL20 8HS",
    "wof:placetype":"postalcode"
},
  "geometry": {"coordinates":[-3.16647077579685,52.96842092875748],"type":"Point"}
}