{
  "type": "Feature",
  "properties": {
    "iso:country":"GB",
    "wof:name":"LS13 2LX",
    "wof:placetype":"postalcode"
},
  "geometry": {"coordinates":[-1.62971530564375,53.81452797596952],"type":"Point"}
}