{
  "type": "Feature",
  "properties": {
    "iso:country":"GB",
    "wof:name":"S40 4DZ",
    "wof:placetype":"postalcode"
},
  "geometry": {"coordinates":[-1.44256391920535,53.24027616027445],"type":"Point"}
}