{
  "type": "Feature",
  "properties": {
    "iso:country": "GB",
    "wof:name": "S35 7AP",
    "wof:placetype": "postalcode"
  },
  "geometry": {"coordinates":[-1.543247,53.508135],"type":"Point"}
}
