{
  "type": "Feature",
  "properties": {
    "iso:country":"GB",
    "wof:name":"S35 7AP",
    "wof:placetype":"postalcode"
},
  "geometry": {"coordinates":[-1.54324734421708,53.50813535647666],"type":"Point"}
}