{
  "type": "Feature",
  "properties": {
    "iso:country":"GB",
    "wof:name":"LL29 7TY",
    "wof:placetype":"postalcode"
},
  "geometry": {"coordinates":[-3.72546215961597,53.29190657798069],"type":"Point"}
}