{
  "type": "Feature",
  "properties": {
    "iso:country":"GB",
    "wof:name":"FY7 8LQ",
    "wof:placetype":"postalcode"
},
  "geometry": {"coordinates":[-3.04340361476046,53.91203624906786],"type":"Point"}
}