{
  "type": "Feature",
  "properties": {
    "date:inception_lower": "1980-01-01",
    "date:inception_upper": "1980-01-01",
    "iso:country": "GB",
    "wof:name": "DD2 1AZ",
    "wof:placetype": "postalcode"
  },
  "geometry": {"coordinates":[-2.994683,56.45399],"type":"Point"}
}
