{
  "type": "Feature",
  "properties": {
    "iso:country": "GB",
    "wof:name": "NE42 5EH",
    "wof:placetype": "postalcode"
  },
  "geometry": {"coordinates":[-1.836302,54.964983],"type":"Point"}
}
