{
  "type": "Feature",
  "properties": {
    "iso:country":"GB",
    "wof:name":"NE42 5EH",
    "wof:placetype":"postalcode"
},
  "geometry": {"coordinates":[-1.83630189609948,54.96498276162955],"type":"Point"}
}