{
  "type": "Feature",
  "properties": {
    "iso:country":"GB",
    "wof:name":"RM3 8HL",
    "wof:placetype":"postalcode"
},
  "geometry": {"coordinates":[0.21891935974883,51.60574987903981],"type":"Point"}
}