{
  "type": "Feature",
  "properties": {
    "iso:country":"GB",
    "wof:name":"NG24 4SG",
    "wof:placetype":"postalcode"
},
  "geometry": {"coordinates":[-0.82124025435361,53.07058024220947],"type":"Point"}
}