{
  "type": "Feature",
  "properties": {
    "date:inception_lower": "2004-04-01",
    "date:inception_upper": "2004-04-01",
    "iso:country": "GB",
    "wof:name": "NG24 4SG",
    "wof:placetype": "postalcode"
  },
  "geometry": {"coordinates":[-0.82124,53.07058],"type":"Point"}
}
