{
  "type": "Feature",
  "properties": {
    "date:inception_lower":"1997-12-01",
    "date:inception_upper":"1997-12-31",
    "iso:country":"GB",
    "wof:name":"BH1 1PA",
    "wof:placetype":"postalcode"
},
  "geometry": {"coordinates":[-1.868282,50.723526],"type":"Point"}
}