{
  "type": "Feature",
  "properties": {
    "iso:country": "GB",
    "wof:name": "WS8 6DP",
    "wof:placetype": "postalcode"
  },
  "geometry": {"coordinates":[-1.92066,52.639604],"type":"Point"}
}
