{
  "type": "Feature",
  "properties": {
    "iso:country":"GB",
    "wof:name":"WS8 6DP",
    "wof:placetype":"postalcode"
},
  "geometry": {"coordinates":[-1.92066024082501,52.63960433987984],"type":"Point"}
}