{
  "type": "Feature",
  "properties": {
    "iso:country":"GB",
    "wof:name":"NW4 9TF",
    "wof:placetype":"postalcode"
},
  "geometry": {"coordinates":[-0.22176563144019,51.58802126691188],"type":"Point"}
}