{
  "type": "Feature",
  "properties": {
    "iso:country": "GB",
    "wof:name": "RH10 3ZL",
    "wof:placetype": "postalcode"
  },
  "geometry": {"coordinates":[-0.15126,51.138624],"type":"Point"}
}
