{
  "type": "Feature",
  "properties": {
    "iso:country":"GB",
    "wof:name":"EX5 4NL",
    "wof:placetype":"postalcode"
},
  "geometry": {"coordinates":[-3.4211600193557,50.82611737358442],"type":"Point"}
}