{
  "type": "Feature",
  "properties": {
    "date:inception_lower": "1980-01-01",
    "date:inception_upper": "1980-01-01",
    "iso:country": "GB",
    "wof:name": "EX5 4NL",
    "wof:placetype": "postalcode"
  },
  "geometry": {"coordinates":[-3.42116,50.826117],"type":"Point"}
}
