{
  "type": "Feature",
  "properties": {
    "date:inception_lower":"2007-04-01",
    "date:inception_upper":"2007-04-30",
    "iso:country":"GB",
    "wof:name":"NR11 6WE",
    "wof:placetype":"postalcode"
},
  "geometry": {"coordinates":[1.243718,52.791023],"type":"Point"}
}