{
  "type": "Feature",
  "properties": {
    "iso:country":"GB",
    "wof:name":"NR11 6WE",
    "wof:placetype":"postalcode"
},
  "geometry": {"coordinates":[1.2437176166214,52.79102263660768],"type":"Point"}
}