{
  "type": "Feature",
  "properties": {
    "date:inception_lower": "1980-01-01",
    "date:inception_upper": "1980-01-01",
    "iso:country": "GB",
    "wof:name": "SK13 8QT",
    "wof:placetype": "postalcode"
  },
  "geometry": {"coordinates":[-1.932634,53.444056],"type":"Point"}
}
