{
  "type": "Feature",
  "properties": {
    "iso:country":"GB",
    "wof:name":"CH44 4AF",
    "wof:placetype":"postalcode"
},
  "geometry": {"coordinates":[-3.04392174682617,53.41125861426206],"type":"Point"}
}