{
  "type": "Feature",
  "properties": {
    "iso:country": "GB",
    "wof:name": "G52 1RH",
    "wof:placetype": "postalcode"
  },
  "geometry": {"coordinates":[-4.332909,55.835467],"type":"Point"}
}
