{
  "type": "Feature",
  "properties": {
    "iso:country":"GB",
    "wof:name":"ML6 7FH",
    "wof:placetype":"postalcode"
},
  "geometry": {"coordinates":[-3.93949754385345,55.91536362886995],"type":"Point"}
}