{
  "type": "Feature",
  "properties": {
    "iso:country": "GB",
    "wof:name": "ML6 7FH",
    "wof:placetype": "postalcode"
  },
  "geometry": {"coordinates":[-3.939497,55.915364],"type":"Point"}
}
