{
  "type": "Feature",
  "properties": {
    "iso:country":"GB",
    "wof:name":"S63 7BQ",
    "wof:placetype":"postalcode"
},
  "geometry": {"coordinates":[-1.33826609223006,53.49605804527017],"type":"Point"}
}