{
  "type": "Feature",
  "properties": {
    "iso:country":"GB",
    "wof:name":"AL7 1PF",
    "wof:placetype":"postalcode"
},
  "geometry": {"coordinates":[-0.1829189069472,51.81091840389714],"type":"Point"}
}