{
  "type": "Feature",
  "properties": {
    "iso:country": "GB",
    "wof:name": "AL7 1PF",
    "wof:placetype": "postalcode"
  },
  "geometry": {"coordinates":[-0.183102,51.81082],"type":"Point"}
}
