{
  "type": "Feature",
  "properties": {
    "iso:country":"GB",
    "wof:name":"GU32 1AS",
    "wof:placetype":"postalcode"
},
  "geometry": {"coordinates":[-0.96300479528061,51.01360215042779],"type":"Point"}
}