{
  "type": "Feature",
  "properties": {
    "date:inception_lower":"1980-01-01",
    "date:inception_upper":"1980-01-31",
    "iso:country":"GB",
    "wof:name":"BB6 8BB",
    "wof:placetype":"postalcode"
},
  "geometry": {"coordinates":[-2.452924,53.828641],"type":"Point"}
}