{
  "type": "Feature",
  "properties": {
    "iso:country":"GB",
    "wof:name":"SE5 7QX",
    "wof:placetype":"postalcode"
},
  "geometry": {"coordinates":[-0.08749397701201,51.47703726465401],"type":"Point"}
}