{
  "type": "Feature",
  "properties": {
    "date:inception_lower": "2012-10-01",
    "date:inception_upper": "2012-10-01",
    "iso:country": "GB",
    "wof:name": "NN2 7EX",
    "wof:placetype": "postalcode"
  },
  "geometry": {"coordinates":[-0.886307,52.275124],"type":"Point"}
}
