{
  "type": "Feature",
  "properties": {
    "iso:country":"GB",
    "wof:name":"KT13 0HG",
    "wof:placetype":"postalcode"
},
  "geometry": {"coordinates":[-0.43590181161044,51.36314370128861],"type":"Point"}
}