{
  "type": "Feature",
  "properties": {
    "iso:country": "GB",
    "wof:name": "BH20 5RS",
    "wof:placetype": "postalcode"
  },
  "geometry": {"coordinates":[-2.254994,50.619535],"type":"Point"}
}
