{
  "type": "Feature",
  "properties": {
    "iso:country":"GB",
    "wof:name":"TR7 2QQ",
    "wof:placetype":"postalcode"
},
  "geometry": {"coordinates":[-5.06457689325164,50.41643850665093],"type":"Point"}
}