{
  "type": "Feature",
  "properties": {
    "iso:country": "GB",
    "wof:name": "TR7 2QQ",
    "wof:placetype": "postalcode"
  },
  "geometry": {"coordinates":[-5.064311,50.416419],"type":"Point"}
}
