{
  "type": "Feature",
  "properties": {
    "iso:country":"GB",
    "wof:name":"SA31 2NX",
    "wof:placetype":"postalcode"
},
  "geometry": {"coordinates":[-4.30035046438454,51.84812815378381],"type":"Point"}
}