{
  "type": "Feature",
  "properties": {
    "date:inception_lower":"2011-11-01",
    "date:inception_upper":"2011-11-30",
    "iso:country":"GB",
    "wof:name":"SA31 2NX",
    "wof:placetype":"postalcode"
},
  "geometry": {"coordinates":[-4.30035,51.848128],"type":"Point"}
}