{
  "type": "Feature",
  "properties": {
    "iso:country":"GB",
    "wof:name":"PE29 7AF",
    "wof:placetype":"postalcode"
},
  "geometry": {"coordinates":[-0.18203468329797,52.33998422046808],"type":"Point"}
}