{
  "type": "Feature",
  "properties": {
    "iso:country": "GB",
    "wof:name": "CO6 4SG",
    "wof:placetype": "postalcode"
  },
  "geometry": {"coordinates":[0.899945,51.980137],"type":"Point"}
}
