{
  "type": "Feature",
  "properties": {
    "iso:country": "GB",
    "wof:name": "G74 4TX",
    "wof:placetype": "postalcode"
  },
  "geometry": {"coordinates":[-4.204123,55.77503],"type":"Point"}
}
