{
  "type": "Feature",
  "properties": {
    "iso:country": "GB",
    "wof:name": "WA1 3GQ",
    "wof:placetype": "postalcode"
  },
  "geometry": {"coordinates":[-2.560145,53.399722],"type":"Point"}
}
