{
  "type": "Feature",
  "properties": {
    "iso:country":"GB",
    "wof:name":"WA1 3GQ",
    "wof:placetype":"postalcode"
},
  "geometry": {"coordinates":[-2.56014547186733,53.39972232120925],"type":"Point"}
}