{
  "type": "Feature",
  "properties": {
    "date:inception_lower": "2022-02-01",
    "date:inception_upper": "2022-02-01",
    "iso:country": "GB",
    "wof:name": "DN37 0FE",
    "wof:placetype": "postalcode"
  },
  "geometry": {"coordinates":[-0.139693,53.511702],"type":"Point"}
}
