{
  "type": "Feature",
  "properties": {
    "iso:country":"GB",
    "wof:name":"OX2 6XJ",
    "wof:placetype":"postalcode"
},
  "geometry": {"coordinates":[-1.26468463124883,51.77178433137267],"type":"Point"}
}