{
  "type": "Feature",
  "properties": {
    "iso:country":"GB",
    "wof:name":"TS19 8SZ",
    "wof:placetype":"postalcode"
},
  "geometry": {"coordinates":[-1.35992956120081,54.58373143910475],"type":"Point"}
}