{
  "type": "Feature",
  "properties": {
    "iso:country":"GB",
    "wof:name":"HU8 9TP",
    "wof:placetype":"postalcode"
},
  "geometry": {"coordinates":[-0.26823053555966,53.78261633682183],"type":"Point"}
}