{
  "type": "Feature",
  "properties": {
    "iso:country":"GB",
    "wof:name":"EN5 2LW",
    "wof:placetype":"postalcode"
},
  "geometry": {"coordinates":[-0.20512883364589,51.64860983610579],"type":"Point"}
}