{
  "type": "Feature",
  "properties": {
    "date:inception_lower": "1980-01-01",
    "date:inception_upper": "1980-01-01",
    "iso:country": "GB",
    "wof:name": "EN5 2LW",
    "wof:placetype": "postalcode"
  },
  "geometry": {"coordinates":[-0.205129,51.64861],"type":"Point"}
}
