{
  "type": "Feature",
  "properties": {
    "date:inception_lower": "1980-01-01",
    "date:inception_upper": "1980-01-01",
    "iso:country": "GB",
    "wof:name": "S6 4LT",
    "wof:placetype": "postalcode"
  },
  "geometry": {"coordinates":[-1.507949,53.40264],"type":"Point"}
}
