{
  "type": "Feature",
  "properties": {
    "iso:country":"GB",
    "wof:name":"NW1 7SU",
    "wof:placetype":"postalcode"
},
  "geometry": {"coordinates":[-0.15461735709516,51.53797595149177],"type":"Point"}
}