{
  "type": "Feature",
  "properties": {
    "iso:country":"GB",
    "wof:name":"KA7 4LZ",
    "wof:placetype":"postalcode"
},
  "geometry": {"coordinates":[-4.75914070331075,55.40634130720902],"type":"Point"}
}