{
  "type": "Feature",
  "properties": {
    "iso:country":"GB",
    "wof:name":"YO11 1NG",
    "wof:placetype":"postalcode"
},
  "geometry": {"coordinates":[-0.39584227242135,54.28333576169073],"type":"Point"}
}