{
  "type": "Feature",
  "properties": {
    "iso:country":"GB",
    "wof:name":"SW15 2TX",
    "wof:placetype":"postalcode"
},
  "geometry": {"coordinates":[-0.21659386477644,51.46045745462165],"type":"Point"}
}