{
  "type": "Feature",
  "properties": {
    "iso:country":"GB",
    "wof:name":"SN5 8JS",
    "wof:placetype":"postalcode"
},
  "geometry": {"coordinates":[-1.83214200613734,51.5528146994964],"type":"Point"}
}