{
  "type": "Feature",
  "properties": {
    "date:inception_lower": "2023-12-01",
    "date:inception_upper": "2023-12-01",
    "iso:country": "GB",
    "wof:name": "SA7 9GS",
    "wof:placetype": "postalcode"
  },
  "geometry": {"coordinates":[-3.870041,51.660131],"type":"Point"}
}
