{
  "type": "Feature",
  "properties": {
    "iso:country": "GB",
    "wof:name": "CV11 9TA",
    "wof:placetype": "postalcode"
  },
  "geometry": {"coordinates":[-1.467336,52.521782],"type":"Point"}
}
