{
  "type": "Feature",
  "properties": {
    "iso:country": "GB",
    "wof:name": "KT10 0EH",
    "wof:placetype": "postalcode"
  },
  "geometry": {"coordinates":[-0.339567,51.360964],"type":"Point"}
}
