{
  "type": "Feature",
  "properties": {
    "date:inception_lower":"1980-01-01",
    "date:inception_upper":"1980-01-31",
    "iso:country":"GB",
    "wof:name":"KT10 0EH",
    "wof:placetype":"postalcode"
},
  "geometry": {"coordinates":[-0.339567,51.360964],"type":"Point"}
}