{
  "type": "Feature",
  "properties": {
    "iso:country":"GB",
    "wof:name":"KT10 0EH",
    "wof:placetype":"postalcode"
},
  "geometry": {"coordinates":[-0.33956662516395,51.36096370282745],"type":"Point"}
}