{
  "type": "Feature",
  "properties": {
    "iso:country":"GB",
    "wof:name":"GL50 4AY",
    "wof:placetype":"postalcode"
},
  "geometry": {"coordinates":[-2.08047955003339,51.90517839190788],"type":"Point"}
}