{
  "type": "Feature",
  "properties": {
    "date:inception_lower": "1980-01-01",
    "date:inception_upper": "1980-01-01",
    "iso:country": "GB",
    "wof:name": "TR27 6DT",
    "wof:placetype": "postalcode"
  },
  "geometry": {"coordinates":[-5.347524,50.163803],"type":"Point"}
}
