{
  "type": "Feature",
  "properties": {
    "iso:country": "GB",
    "wof:name": "LL20 8ND",
    "wof:placetype": "postalcode"
  },
  "geometry": {"coordinates":[-3.17009,52.969015],"type":"Point"}
}
