{
  "type": "Feature",
  "properties": {
    "iso:country":"GB",
    "wof:name":"PO12 2PU",
    "wof:placetype":"postalcode"
},
  "geometry": {"coordinates":[-1.154456981967,50.79117467533738],"type":"Point"}
}