{
  "type": "Feature",
  "properties": {
    "date:inception_lower":"1980-01-01",
    "date:inception_upper":"1980-01-31",
    "iso:country":"GB",
    "wof:name":"LN12 2HP",
    "wof:placetype":"postalcode"
},
  "geometry": {"coordinates":[0.278123,53.309689],"type":"Point"}
}