{
  "type": "Feature",
  "properties": {
    "date:inception_lower": "1980-01-01",
    "date:inception_upper": "1980-01-01",
    "iso:country": "GB",
    "wof:name": "HP10 0BP",
    "wof:placetype": "postalcode"
  },
  "geometry": {"coordinates":[-0.681031,51.592174],"type":"Point"}
}
