{
  "type": "Feature",
  "properties": {
    "iso:country": "GB",
    "wof:name": "HP10 0BP",
    "wof:placetype": "postalcode"
  },
  "geometry": {"coordinates":[-0.681031,51.592174],"type":"Point"}
}
