{
  "type": "Feature",
  "properties": {
    "iso:country": "GB",
    "wof:name": "WV6 0DA",
    "wof:placetype": "postalcode"
  },
  "geometry": {"coordinates":[-2.154464,52.59139],"type":"Point"}
}
