{
  "type": "Feature",
  "properties": {
    "date:inception_lower": "1980-01-01",
    "date:inception_upper": "1980-01-01",
    "iso:country": "GB",
    "wof:name": "G63 0HA",
    "wof:placetype": "postalcode"
  },
  "geometry": {"coordinates":[-4.437775,56.039101],"type":"Point"}
}
