{
  "type": "Feature",
  "properties": {
    "iso:country":"GB",
    "wof:name":"G63 0HA",
    "wof:placetype":"postalcode"
},
  "geometry": {"coordinates":[-4.4377755142619,56.03910096566774],"type":"Point"}
}