{
  "type": "Feature",
  "properties": {
    "iso:country": "GB",
    "wof:name": "GL18 1TQ",
    "wof:placetype": "postalcode"
  },
  "geometry": {"coordinates":[-2.406468,51.93278],"type":"Point"}
}
