{
  "type": "Feature",
  "properties": {
    "date:inception_lower": "1981-06-01",
    "date:inception_upper": "1981-06-01",
    "iso:country": "GB",
    "wof:name": "GL18 1TQ",
    "wof:placetype": "postalcode"
  },
  "geometry": {"coordinates":[-2.406468,51.93278],"type":"Point"}
}
