{
  "type": "Feature",
  "properties": {
    "iso:country":"GB",
    "wof:name":"HP20 2XP",
    "wof:placetype":"postalcode"
},
  "geometry": {"coordinates":[-0.79831757359063,51.82511981506678],"type":"Point"}
}