{
  "type": "Feature",
  "properties": {
    "iso:country": "GB",
    "wof:name": "HP20 2XP",
    "wof:placetype": "postalcode"
  },
  "geometry": {"coordinates":[-0.798337,51.825163],"type":"Point"}
}
