{
  "type": "Feature",
  "properties": {
    "date:inception_lower": "1980-01-01",
    "date:inception_upper": "1980-01-01",
    "iso:country": "GB",
    "wof:name": "LE16 8PY",
    "wof:placetype": "postalcode"
  },
  "geometry": {"coordinates":[-0.815833,52.481258],"type":"Point"}
}
