{
  "type": "Feature",
  "properties": {
    "iso:country":"GB",
    "wof:name":"LE16 8PY",
    "wof:placetype":"postalcode"
},
  "geometry": {"coordinates":[-0.81583294691151,52.48125779755822],"type":"Point"}
}