{
  "type": "Feature",
  "properties": {
    "iso:country":"GB",
    "wof:name":"NE29 9LJ",
    "wof:placetype":"postalcode"
},
  "geometry": {"coordinates":[-1.45304770013935,55.02029785735133],"type":"Point"}
}