{
  "type": "Feature",
  "properties": {
    "iso:country": "GB",
    "wof:name": "NE29 9LJ",
    "wof:placetype": "postalcode"
  },
  "geometry": {"coordinates":[-1.453045,55.020306],"type":"Point"}
}
