{
  "type": "Feature",
  "properties": {
    "date:inception_lower":"2015-06-01",
    "date:inception_upper":"2015-06-30",
    "iso:country":"GB",
    "wof:name":"RM8 2FA",
    "wof:placetype":"postalcode"
},
  "geometry": {"coordinates":[0.107238,51.551415],"type":"Point"}
}