{
  "type": "Feature",
  "properties": {
    "iso:country":"GB",
    "wof:name":"PO4 9HN",
    "wof:placetype":"postalcode"
},
  "geometry": {"coordinates":[-1.06077651983115,50.78835391194279],"type":"Point"}
}