{
  "type": "Feature",
  "properties": {
    "iso:country":"GB",
    "wof:name":"SL5 9RL",
    "wof:placetype":"postalcode"
},
  "geometry": {"coordinates":[-0.63251596902913,51.38832672358707],"type":"Point"}
}