{
  "type": "Feature",
  "properties": {
    "iso:country":"GB",
    "wof:name":"CO4 3YJ",
    "wof:placetype":"postalcode"
},
  "geometry": {"coordinates":[0.9404682919643,51.88639417432502],"type":"Point"}
}