{
  "type": "Feature",
  "properties": {
    "date:inception_lower": "1990-02-01",
    "date:inception_upper": "1990-02-01",
    "iso:country": "GB",
    "wof:name": "PO31 7QX",
    "wof:placetype": "postalcode"
  },
  "geometry": {"coordinates":[-1.299572,50.76416],"type":"Point"}
}
