{
  "type": "Feature",
  "properties": {
    "iso:country": "GB",
    "wof:name": "PO31 7QX",
    "wof:placetype": "postalcode"
  },
  "geometry": {"coordinates":[-1.299572,50.76416],"type":"Point"}
}
