{
  "type": "Feature",
  "properties": {
    "iso:country":"GB",
    "wof:name":"TN8 5LB",
    "wof:placetype":"postalcode"
},
  "geometry": {"coordinates":[0.05885796895057,51.20300654749257],"type":"Point"}
}