{
  "type": "Feature",
  "properties": {
    "iso:country": "GB",
    "wof:name": "TN8 5LB",
    "wof:placetype": "postalcode"
  },
  "geometry": {"coordinates":[0.058858,51.203007],"type":"Point"}
}
