{
  "type": "Feature",
  "properties": {
    "date:inception_lower": "1980-01-01",
    "date:inception_upper": "1980-01-01",
    "iso:country": "GB",
    "wof:name": "TN8 5LB",
    "wof:placetype": "postalcode"
  },
  "geometry": {"coordinates":[0.058858,51.203007],"type":"Point"}
}
