{
  "type": "Feature",
  "properties": {
    "iso:country":"GB",
    "wof:name":"L21 7PN",
    "wof:placetype":"postalcode"
},
  "geometry": {"coordinates":[-2.9962361713108,53.47388712604261],"type":"Point"}
}