{
  "type": "Feature",
  "properties": {
    "date:inception_lower":"2015-06-01",
    "date:inception_upper":"2015-06-30",
    "iso:country":"GB",
    "wof:name":"DN5 0AH",
    "wof:placetype":"postalcode"
},
  "geometry": {"coordinates":[-1.138235,53.559306],"type":"Point"}
}