{
  "type": "Feature",
  "properties": {
    "date:inception_lower":"1980-01-01",
    "date:inception_upper":"1980-01-31",
    "iso:country":"GB",
    "wof:name":"BS3 3JF",
    "wof:placetype":"postalcode"
},
  "geometry": {"coordinates":[-2.608644,51.436244],"type":"Point"}
}