{
  "type": "Feature",
  "properties": {
    "iso:country":"GB",
    "wof:name":"PA3 4BZ",
    "wof:placetype":"postalcode"
},
  "geometry": {"coordinates":[-4.41344374059598,55.85624794818938],"type":"Point"}
}