{
  "type": "Feature",
  "properties": {
    "iso:country":"GB",
    "wof:name":"OL3 7DU",
    "wof:placetype":"postalcode"
},
  "geometry": {"coordinates":[-1.99973532465623,53.53426419402712],"type":"Point"}
}