{
  "type": "Feature",
  "properties": {
    "date:inception_lower": "1994-05-01",
    "date:inception_upper": "1994-05-01",
    "iso:country": "GB",
    "wof:name": "LE8 5SA",
    "wof:placetype": "postalcode"
  },
  "geometry": {"coordinates":[-1.143735,52.555386],"type":"Point"}
}
