{
  "type": "Feature",
  "properties": {
    "iso:country":"GB",
    "wof:name":"LE8 5SA",
    "wof:placetype":"postalcode"
},
  "geometry": {"coordinates":[-1.14373551451002,52.55538565565631],"type":"Point"}
}