{
  "type": "Feature",
  "properties": {
    "iso:country":"GB",
    "wof:name":"UB8 1NG",
    "wof:placetype":"postalcode"
},
  "geometry": {"coordinates":[-0.48049193990088,51.54641676125812],"type":"Point"}
}