{
  "type": "Feature",
  "properties": {
    "iso:country":"GB",
    "wof:name":"PR25 1YN",
    "wof:placetype":"postalcode"
},
  "geometry": {"coordinates":[-2.712491904281,53.69836321601259],"type":"Point"}
}