{
  "type": "Feature",
  "properties": {
    "iso:country":"GB",
    "wof:name":"SE4 2LP",
    "wof:placetype":"postalcode"
},
  "geometry": {"coordinates":[-0.04476820602528,51.46050544432937],"type":"Point"}
}