{
  "type": "Feature",
  "properties": {
    "date:inception_lower":"2018-06-01",
    "date:inception_upper":"2018-06-30",
    "iso:country":"GB",
    "wof:name":"SE24 4BN",
    "wof:placetype":"postalcode"
},
  "geometry": {"coordinates":[-0.096699,51.473915],"type":"Point"}
}