{
  "type": "Feature",
  "properties": {
    "iso:country":"GB",
    "wof:name":"IP26 5NR",
    "wof:placetype":"postalcode"
},
  "geometry": {"coordinates":[0.58833788849919,52.54089147345216],"type":"Point"}
}