{
  "type": "Feature",
  "properties": {
    "date:inception_lower": "1987-10-01",
    "date:inception_upper": "1987-10-01",
    "iso:country": "GB",
    "wof:name": "IP26 5NR",
    "wof:placetype": "postalcode"
  },
  "geometry": {"coordinates":[0.588338,52.540891],"type":"Point"}
}
