{
  "type": "Feature",
  "properties": {
    "iso:country":"GB",
    "wof:name":"M14 4GW",
    "wof:placetype":"postalcode"
},
  "geometry": {"coordinates":[-2.2413232165187,53.45912853949046],"type":"Point"}
}