{
  "type": "Feature",
  "properties": {
    "iso:country":"GB",
    "wof:name":"SR8 4NT",
    "wof:placetype":"postalcode"
},
  "geometry": {"coordinates":[-1.32068195606795,54.76639995279453],"type":"Point"}
}