{
  "type": "Feature",
  "properties": {
    "iso:country":"GB",
    "wof:name":"HP13 6BE",
    "wof:placetype":"postalcode"
},
  "geometry": {"coordinates":[-0.73879597862111,51.62686086838276],"type":"Point"}
}