{
  "type": "Feature",
  "properties": {
    "iso:country": "GB",
    "wof:name": "HP13 6BE",
    "wof:placetype": "postalcode"
  },
  "geometry": {"coordinates":[-0.738796,51.626861],"type":"Point"}
}
