{
  "type": "Feature",
  "properties": {
    "iso:country": "GB",
    "wof:name": "GU15 1DL",
    "wof:placetype": "postalcode"
  },
  "geometry": {"coordinates":[-0.705947,51.329542],"type":"Point"}
}
