{
  "type": "Feature",
  "properties": {
    "iso:country":"GB",
    "wof:name":"GU15 1DL",
    "wof:placetype":"postalcode"
},
  "geometry": {"coordinates":[-0.70594665531997,51.3295423517947],"type":"Point"}
}