{
  "type": "Feature",
  "properties": {
    "date:inception_lower": "2006-01-01",
    "date:inception_upper": "2006-01-01",
    "iso:country": "GB",
    "wof:name": "YO26 5NB",
    "wof:placetype": "postalcode"
  },
  "geometry": {"coordinates":[-1.120587,53.967237],"type":"Point"}
}
