{
  "type": "Feature",
  "properties": {
    "iso:country": "GB",
    "wof:name": "GU34 5DF",
    "wof:placetype": "postalcode"
  },
  "geometry": {"coordinates":[-1.042451,51.109042],"type":"Point"}
}
