{
  "type": "Feature",
  "properties": {
    "iso:country":"GB",
    "wof:name":"GU34 5DF",
    "wof:placetype":"postalcode"
},
  "geometry": {"coordinates":[-1.04245092401264,51.10904201439358],"type":"Point"}
}