{
  "type": "Feature",
  "properties": {
    "iso:country":"GB",
    "wof:name":"PE11 2UU",
    "wof:placetype":"postalcode"
},
  "geometry": {"coordinates":[-0.16435172665291,52.77734054313518],"type":"Point"}
}