{
  "type": "Feature",
  "properties": {
    "iso:country": "GB",
    "wof:name": "PE11 2UU",
    "wof:placetype": "postalcode"
  },
  "geometry": {"coordinates":[-0.164354,52.77737],"type":"Point"}
}
