{
  "type": "Feature",
  "properties": {
    "date:inception_lower":"1983-01-01",
    "date:inception_upper":"1983-01-31",
    "iso:country":"GB",
    "wof:name":"ME5 9LR",
    "wof:placetype":"postalcode"
},
  "geometry": {"coordinates":[0.526731,51.33948],"type":"Point"}
}