{
  "type": "Feature",
  "properties": {
    "iso:country": "GB",
    "wof:name": "ME5 9LR",
    "wof:placetype": "postalcode"
  },
  "geometry": {"coordinates":[0.526731,51.33948],"type":"Point"}
}
