{
  "type": "Feature",
  "properties": {
    "iso:country": "GB",
    "wof:name": "KT13 8TZ",
    "wof:placetype": "postalcode"
  },
  "geometry": {"coordinates":[-0.459215,51.361861],"type":"Point"}
}
