{
  "type": "Feature",
  "properties": {
    "iso:country":"GB",
    "wof:name":"KT13 8TZ",
    "wof:placetype":"postalcode"
},
  "geometry": {"coordinates":[-0.45921507624671,51.36186095805042],"type":"Point"}
}