{
  "type": "Feature",
  "properties": {
    "iso:country":"GB",
    "wof:name":"LL40 2AS",
    "wof:placetype":"postalcode"
},
  "geometry": {"coordinates":[-3.77488294636308,52.7825098967739],"type":"Point"}
}