{
  "type": "Feature",
  "properties": {
    "date:inception_lower":"1980-01-01",
    "date:inception_upper":"1980-01-31",
    "iso:country":"GB",
    "wof:name":"NR5 8QN",
    "wof:placetype":"postalcode"
},
  "geometry": {"coordinates":[1.247779,52.637573],"type":"Point"}
}