{
  "type": "Feature",
  "properties": {
    "iso:country":"GB",
    "wof:name":"NR5 8QN",
    "wof:placetype":"postalcode"
},
  "geometry": {"coordinates":[1.24777855212711,52.63757328703586],"type":"Point"}
}