{
  "type": "Feature",
  "properties": {
    "iso:country": "GB",
    "wof:name": "ML3 9TA",
    "wof:placetype": "postalcode"
  },
  "geometry": {"coordinates":[-4.074122,55.76961],"type":"Point"}
}
