{
  "type": "Feature",
  "properties": {
    "date:inception_lower": "1988-03-01",
    "date:inception_upper": "1988-03-01",
    "iso:country": "GB",
    "wof:name": "ME10 1BE",
    "wof:placetype": "postalcode"
  },
  "geometry": {"coordinates":[0.72862,51.342144],"type":"Point"}
}
