{
  "type": "Feature",
  "properties": {
    "iso:country":"GB",
    "wof:name":"TA23 0RN",
    "wof:placetype":"postalcode"
},
  "geometry": {"coordinates":[-3.38391996775035,51.12323817710458],"type":"Point"}
}