{
  "type": "Feature",
  "properties": {
    "date:inception_lower":"1980-01-01",
    "date:inception_upper":"1980-01-31",
    "iso:country":"GB",
    "wof:name":"TA23 0RN",
    "wof:placetype":"postalcode"
},
  "geometry": {"coordinates":[-3.38392,51.123238],"type":"Point"}
}