{
  "type": "Feature",
  "properties": {
    "iso:country":"GB",
    "wof:name":"TF12 5RZ",
    "wof:placetype":"postalcode"
},
  "geometry": {"coordinates":[-2.47150753744395,52.60753286693622],"type":"Point"}
}