{
  "type": "Feature",
  "properties": {
    "iso:country":"GB",
    "wof:name":"NW9 6RD",
    "wof:placetype":"postalcode"
},
  "geometry": {"coordinates":[-0.24413717976547,51.58886165897388],"type":"Point"}
}