{
  "type": "Feature",
  "properties": {
    "iso:country": "GB",
    "wof:name": "SE18 4PH",
    "wof:placetype": "postalcode"
  },
  "geometry": {"coordinates":[0.03958,51.474482],"type":"Point"}
}
