{
  "type": "Feature",
  "properties": {
    "iso:country":"GB",
    "wof:name":"LN5 7LX",
    "wof:placetype":"postalcode"
},
  "geometry": {"coordinates":[-0.53694940976708,53.22275887001712],"type":"Point"}
}