{
  "type": "Feature",
  "properties": {
    "iso:country":"GB",
    "wof:name":"PE6 8GN",
    "wof:placetype":"postalcode"
},
  "geometry": {"coordinates":[-0.29112101539074,52.67719951034896],"type":"Point"}
}