{
  "type": "Feature",
  "properties": {
    "date:inception_lower":"2012-02-01",
    "date:inception_upper":"2012-02-29",
    "iso:country":"GB",
    "wof:name":"PE6 8GN",
    "wof:placetype":"postalcode"
},
  "geometry": {"coordinates":[-0.291121,52.6772],"type":"Point"}
}