{
  "type": "Feature",
  "properties": {
    "iso:country": "GB",
    "wof:name": "PE6 8GN",
    "wof:placetype": "postalcode"
  },
  "geometry": {"coordinates":[-0.291121,52.6772],"type":"Point"}
}
