{
  "type": "Feature",
  "properties": {
    "iso:country":"GB",
    "wof:name":"SW16 2NQ",
    "wof:placetype":"postalcode"
},
  "geometry": {"coordinates":[-0.12409399721257,51.43682010570675],"type":"Point"}
}