{
  "type": "Feature",
  "properties": {
    "iso:country": "GB",
    "wof:name": "DH5 0GG",
    "wof:placetype": "postalcode"
  },
  "geometry": {"coordinates":[-1.436742,54.810571],"type":"Point"}
}
