{
  "type": "Feature",
  "properties": {
    "iso:country":"GB",
    "wof:name":"DH5 0GG",
    "wof:placetype":"postalcode"
},
  "geometry": {"coordinates":[-1.43589358055046,54.81026968405319],"type":"Point"}
}