{
  "type": "Feature",
  "properties": {
    "date:inception_lower":"2012-06-01",
    "date:inception_upper":"2012-06-30",
    "iso:country":"GB",
    "wof:name":"DH5 0GG",
    "wof:placetype":"postalcode"
},
  "geometry": {"coordinates":[-1.436742,54.810571],"type":"Point"}
}