{
  "type": "Feature",
  "properties": {
    "iso:country":"GB",
    "wof:name":"G11 7TW",
    "wof:placetype":"postalcode"
},
  "geometry": {"coordinates":[-4.31811069323659,55.87178767971],"type":"Point"}
}