{
  "type": "Feature",
  "properties": {
    "iso:country":"GB",
    "wof:name":"SR8 5RY",
    "wof:placetype":"postalcode"
},
  "geometry": {"coordinates":[-1.32543341372678,54.75638829370753],"type":"Point"}
}