{
  "type": "Feature",
  "properties": {
    "date:inception_lower": "1980-01-01",
    "date:inception_upper": "1980-01-01",
    "iso:country": "GB",
    "wof:name": "SR8 5RY",
    "wof:placetype": "postalcode"
  },
  "geometry": {"coordinates":[-1.325433,54.756388],"type":"Point"}
}
