{
  "type": "Feature",
  "properties": {
    "iso:country":"GB",
    "wof:name":"RG45 6QE",
    "wof:placetype":"postalcode"
},
  "geometry": {"coordinates":[-0.79731016700693,51.37656463555208],"type":"Point"}
}