{
  "type": "Feature",
  "properties": {
    "iso:country":"GB",
    "wof:name":"CV21 2SP",
    "wof:placetype":"postalcode"
},
  "geometry": {"coordinates":[-1.26046141138007,52.37985687391195],"type":"Point"}
}