{
  "type": "Feature",
  "properties": {
    "iso:country": "GB",
    "wof:name": "CV21 2SP",
    "wof:placetype": "postalcode"
  },
  "geometry": {"coordinates":[-1.260461,52.379857],"type":"Point"}
}
