{
  "type": "Feature",
  "properties": {
    "iso:country": "GB",
    "wof:name": "TN8 6EW",
    "wof:placetype": "postalcode"
  },
  "geometry": {"coordinates":[0.059786,51.207494],"type":"Point"}
}
