{
  "type": "Feature",
  "properties": {
    "iso:country":"GB",
    "wof:name":"TN8 6EW",
    "wof:placetype":"postalcode"
},
  "geometry": {"coordinates":[0.05957535327568,51.20753546734699],"type":"Point"}
}