{
  "type": "Feature",
  "properties": {
    "date:inception_lower": "1998-12-01",
    "date:inception_upper": "1998-12-01",
    "iso:country": "GB",
    "wof:name": "TN8 6EW",
    "wof:placetype": "postalcode"
  },
  "geometry": {"coordinates":[0.059786,51.207494],"type":"Point"}
}
