{
  "type": "Feature",
  "properties": {
    "iso:country":"GB",
    "wof:name":"CH7 6BA",
    "wof:placetype":"postalcode"
},
  "geometry": {"coordinates":[-3.14217099432961,53.20920767670757],"type":"Point"}
}