{
  "type": "Feature",
  "properties": {
    "iso:country": "GB",
    "wof:name": "CH7 6BA",
    "wof:placetype": "postalcode"
  },
  "geometry": {"coordinates":[-3.142171,53.209208],"type":"Point"}
}
