{
  "type": "Feature",
  "properties": {
    "iso:country":"GB",
    "wof:name":"M34 2DX",
    "wof:placetype":"postalcode"
},
  "geometry": {"coordinates":[-2.12450554658424,53.44640015867814],"type":"Point"}
}