{
  "type": "Feature",
  "properties": {
    "iso:country": "GB",
    "wof:name": "M34 2DX",
    "wof:placetype": "postalcode"
  },
  "geometry": {"coordinates":[-2.124506,53.4464],"type":"Point"}
}
