{
  "type": "Feature",
  "properties": {
    "iso:country":"GB",
    "wof:name":"FY7 6QW",
    "wof:placetype":"postalcode"
},
  "geometry": {"coordinates":[-3.01878477009477,53.92196396014237],"type":"Point"}
}