{
  "type": "Feature",
  "properties": {
    "iso:country":"GB",
    "wof:name":"SA1 8EL",
    "wof:placetype":"postalcode"
},
  "geometry": {"coordinates":[-3.92379597840912,51.62050858591186],"type":"Point"}
}