{
  "type": "Feature",
  "properties": {
    "iso:country": "GB",
    "wof:name": "SA1 8EL",
    "wof:placetype": "postalcode"
  },
  "geometry": {"coordinates":[-3.923796,51.620509],"type":"Point"}
}
