{
  "type": "Feature",
  "properties": {
    "iso:country":"GB",
    "wof:name":"TN2 4EZ",
    "wof:placetype":"postalcode"
},
  "geometry": {"coordinates":[0.32490719015211,51.14687508916399],"type":"Point"}
}