{
  "type": "Feature",
  "properties": {
    "iso:country": "GB",
    "wof:name": "EX20 3SD",
    "wof:placetype": "postalcode"
  },
  "geometry": {"coordinates":[-3.982272,50.796832],"type":"Point"}
}
