{
  "type": "Feature",
  "properties": {
    "date:inception_lower": "1987-06-01",
    "date:inception_upper": "1987-06-01",
    "iso:country": "GB",
    "wof:name": "EH20 9QT",
    "wof:placetype": "postalcode"
  },
  "geometry": {"coordinates":[-3.159124,55.888975],"type":"Point"}
}
