{
  "type": "Feature",
  "properties": {
    "iso:country": "GB",
    "wof:name": "L12 0NH",
    "wof:placetype": "postalcode"
  },
  "geometry": {"coordinates":[-2.886737,53.452404],"type":"Point"}
}
