{
  "type": "Feature",
  "properties": {
    "iso:country":"GB",
    "wof:name":"BS8 3ET",
    "wof:placetype":"postalcode"
},
  "geometry": {"coordinates":[-2.62117871095287,51.46202953764647],"type":"Point"}
}