{
  "type": "Feature",
  "properties": {
    "date:inception_lower": "2004-06-01",
    "date:inception_upper": "2004-06-01",
    "iso:country": "GB",
    "wof:name": "BS8 3ET",
    "wof:placetype": "postalcode"
  },
  "geometry": {"coordinates":[-2.621179,51.46203],"type":"Point"}
}
