{
  "type": "Feature",
  "properties": {
    "iso:country": "GB",
    "wof:name": "SE18 6EB",
    "wof:placetype": "postalcode"
  },
  "geometry": {"coordinates":[0.069351,51.487656],"type":"Point"}
}
