{
  "type": "Feature",
  "properties": {
    "date:inception_lower":"2004-05-01",
    "date:inception_upper":"2004-05-31",
    "iso:country":"GB",
    "wof:name":"SE18 6EB",
    "wof:placetype":"postalcode"
},
  "geometry": {"coordinates":[0.069351,51.487656],"type":"Point"}
}