{
  "type": "Feature",
  "properties": {
    "iso:country":"GB",
    "wof:name":"SE18 6EB",
    "wof:placetype":"postalcode"
},
  "geometry": {"coordinates":[0.06935126649793,51.48765626544625],"type":"Point"}
}