{
  "type": "Feature",
  "properties": {
    "iso:country":"GB",
    "wof:name":"RG5 4JY",
    "wof:placetype":"postalcode"
},
  "geometry": {"coordinates":[-0.90045164444694,51.45237284854205],"type":"Point"}
}