{
  "type": "Feature",
  "properties": {
    "iso:country":"GB",
    "wof:name":"TW5 0QL",
    "wof:placetype":"postalcode"
},
  "geometry": {"coordinates":[-0.36394424203784,51.48133717795714],"type":"Point"}
}