{
  "type": "Feature",
  "properties": {
    "iso:country": "GB",
    "wof:name": "NR17 1NP",
    "wof:placetype": "postalcode"
  },
  "geometry": {"coordinates":[1.016839,52.483427],"type":"Point"}
}
