{
  "type": "Feature",
  "properties": {
    "date:inception_lower":"1980-01-01",
    "date:inception_upper":"1980-01-31",
    "iso:country":"GB",
    "wof:name":"NR17 1NP",
    "wof:placetype":"postalcode"
},
  "geometry": {"coordinates":[1.016839,52.483427],"type":"Point"}
}