{
  "type": "Feature",
  "properties": {
    "iso:country":"GB",
    "wof:name":"TN25 4HA",
    "wof:placetype":"postalcode"
},
  "geometry": {"coordinates":[0.93703161260427,51.20412730902316],"type":"Point"}
}