{
  "type": "Feature",
  "properties": {
    "iso:country":"GB",
    "wof:name":"IP3 0RD",
    "wof:placetype":"postalcode"
},
  "geometry": {"coordinates":[1.17955551683825,52.04363921700778],"type":"Point"}
}