{
  "type": "Feature",
  "properties": {
    "iso:country":"GB",
    "wof:name":"NE31 1QD",
    "wof:placetype":"postalcode"
},
  "geometry": {"coordinates":[-1.51000937094125,54.97669639311487],"type":"Point"}
}