{
  "type": "Feature",
  "properties": {
    "iso:country": "GB",
    "wof:name": "NE31 1QD",
    "wof:placetype": "postalcode"
  },
  "geometry": {"coordinates":[-1.510009,54.976696],"type":"Point"}
}
