{
  "type": "Feature",
  "properties": {
    "iso:country":"GB",
    "wof:name":"DN18 5LB",
    "wof:placetype":"postalcode"
},
  "geometry": {"coordinates":[-0.43176676563495,53.68834232810112],"type":"Point"}
}