{
  "type": "Feature",
  "properties": {
    "iso:country": "GB",
    "wof:name": "GU24 8PN",
    "wof:placetype": "postalcode"
  },
  "geometry": {"coordinates":[-0.596615,51.351196],"type":"Point"}
}
