{
  "type": "Feature",
  "properties": {
    "date:inception_lower":"1999-12-01",
    "date:inception_upper":"1999-12-31",
    "iso:country":"GB",
    "wof:name":"OL5 9QG",
    "wof:placetype":"postalcode"
},
  "geometry": {"coordinates":[-2.041432,53.500262],"type":"Point"}
}