{
  "type": "Feature",
  "properties": {
    "iso:country":"GB",
    "wof:name":"OL5 9QG",
    "wof:placetype":"postalcode"
},
  "geometry": {"coordinates":[-2.04134447535809,53.50186283885473],"type":"Point"}
}