{
  "type": "Feature",
  "properties": {
    "iso:country": "GB",
    "wof:name": "OL5 9QG",
    "wof:placetype": "postalcode"
  },
  "geometry": {"coordinates":[-2.041343,53.50188],"type":"Point"}
}
