{
  "type": "Feature",
  "properties": {
    "iso:country":"GB",
    "wof:name":"SP7 8NT",
    "wof:placetype":"postalcode"
},
  "geometry": {"coordinates":[-2.18727833823547,51.00069580320545],"type":"Point"}
}