{
  "type": "Feature",
  "properties": {
    "iso:country":"GB",
    "wof:name":"GU2 9TQ",
    "wof:placetype":"postalcode"
},
  "geometry": {"coordinates":[-0.59742888792219,51.25297318268871],"type":"Point"}
}