{
  "type": "Feature",
  "properties": {
    "iso:country":"GB",
    "wof:name":"M8 4NG",
    "wof:placetype":"postalcode"
},
  "geometry": {"coordinates":[-2.24673471030098,53.52219837503128],"type":"Point"}
}