{
  "type": "Feature",
  "properties": {
    "iso:country":"GB",
    "wof:name":"BH8 0JU",
    "wof:placetype":"postalcode"
},
  "geometry": {"coordinates":[-1.82521618788937,50.74994384773503],"type":"Point"}
}