{
  "type": "Feature",
  "properties": {
    "iso:country":"GB",
    "wof:name":"AB51 0YB",
    "wof:placetype":"postalcode"
},
  "geometry": {"coordinates":[-2.40952354526688,57.20857695127807],"type":"Point"}
}