{
  "type": "Feature",
  "properties": {
    "iso:country":"GB",
    "wof:name":"BD21 4LW",
    "wof:placetype":"postalcode"
},
  "geometry": {"coordinates":[-1.88620686156798,53.87069797504575],"type":"Point"}
}