{
  "type": "Feature",
  "properties": {
    "iso:country":"GB",
    "wof:name":"WN6 9LN",
    "wof:placetype":"postalcode"
},
  "geometry": {"coordinates":[-2.71495142781832,53.58158023774113],"type":"Point"}
}