{
  "type": "Feature",
  "properties": {
    "date:inception_lower": "2002-06-01",
    "date:inception_upper": "2002-06-01",
    "iso:country": "GB",
    "wof:name": "WN6 9LN",
    "wof:placetype": "postalcode"
  },
  "geometry": {"coordinates":[-2.714951,53.58158],"type":"Point"}
}
