{
  "type": "Feature",
  "properties": {
    "iso:country":"GB",
    "wof:name":"LN4 4QB",
    "wof:placetype":"postalcode"
},
  "geometry": {"coordinates":[-0.19885953991914,53.06855002027869],"type":"Point"}
}