{
  "type": "Feature",
  "properties": {
    "iso:country":"GB",
    "wof:name":"NE24 3LB",
    "wof:placetype":"postalcode"
},
  "geometry": {"coordinates":[-1.51055336916404,55.11946226277764],"type":"Point"}
}