{
  "type": "Feature",
  "properties": {
    "iso:country": "GB",
    "wof:name": "DA2 6QF",
    "wof:placetype": "postalcode"
  },
  "geometry": {"coordinates":[0.245349,51.452835],"type":"Point"}
}
