{
  "type": "Feature",
  "properties": {
    "date:inception_lower": "1990-07-01",
    "date:inception_upper": "1990-07-01",
    "iso:country": "GB",
    "wof:name": "DA2 6QF",
    "wof:placetype": "postalcode"
  },
  "geometry": {"coordinates":[0.245349,51.452835],"type":"Point"}
}
