{
  "type": "Feature",
  "properties": {
    "iso:country":"GB",
    "wof:name":"ML4 3EG",
    "wof:placetype":"postalcode"
},
  "geometry": {"coordinates":[-4.02796998155536,55.82210940788678],"type":"Point"}
}