{
  "type": "Feature",
  "properties": {
    "date:inception_lower": "1980-01-01",
    "date:inception_upper": "1980-01-01",
    "iso:country": "GB",
    "wof:name": "ML4 3EG",
    "wof:placetype": "postalcode"
  },
  "geometry": {"coordinates":[-4.02797,55.822109],"type":"Point"}
}
