{
  "type": "Feature",
  "properties": {
    "iso:country":"GB",
    "wof:name":"IV30 4PH",
    "wof:placetype":"postalcode"
},
  "geometry": {"coordinates":[-3.31979000503995,57.6622949276134],"type":"Point"}
}