{
  "type": "Feature",
  "properties": {
    "date:inception_lower": "2022-02-01",
    "date:inception_upper": "2022-02-01",
    "iso:country": "GB",
    "wof:name": "CA4 8FZ",
    "wof:placetype": "postalcode"
  },
  "geometry": {"coordinates":[-2.864011,54.866141],"type":"Point"}
}
