{
  "type": "Feature",
  "properties": {
    "iso:country":"GB",
    "wof:name":"ME3 8GR",
    "wof:placetype":"postalcode"
},
  "geometry": {"coordinates":[0.49824809117395,51.40976378721942],"type":"Point"}
}