{
  "type": "Feature",
  "properties": {
    "iso:country":"GB",
    "wof:name":"PE12 6RB",
    "wof:placetype":"postalcode"
},
  "geometry": {"coordinates":[-0.08488819835125,52.80692286465106],"type":"Point"}
}