{
  "type": "Feature",
  "properties": {
    "iso:country":"GB",
    "wof:name":"TN27 9DD",
    "wof:placetype":"postalcode"
},
  "geometry": {"coordinates":[0.69561439318741,51.18602613872691],"type":"Point"}
}