{
  "type": "Feature",
  "properties": {
    "iso:country":"GB",
    "wof:name":"NR4 6PX",
    "wof:placetype":"postalcode"
},
  "geometry": {"coordinates":[1.26364496126618,52.61063285371692],"type":"Point"}
}