{
  "type": "Feature",
  "properties": {
    "iso:country": "GB",
    "wof:name": "NR4 6PX",
    "wof:placetype": "postalcode"
  },
  "geometry": {"coordinates":[1.263645,52.610633],"type":"Point"}
}
