{
  "type": "Feature",
  "properties": {
    "iso:country":"GB",
    "wof:name":"PR2 2LH",
    "wof:placetype":"postalcode"
},
  "geometry": {"coordinates":[-2.72957111709624,53.7724135920218],"type":"Point"}
}