{
  "type": "Feature",
  "properties": {
    "iso:country": "GB",
    "wof:name": "NP22 4EG",
    "wof:placetype": "postalcode"
  },
  "geometry": {"coordinates":[-3.248854,51.787011],"type":"Point"}
}
