{
  "type": "Feature",
  "properties": {
    "date:inception_lower": "2018-06-01",
    "date:inception_upper": "2018-06-01",
    "iso:country": "GB",
    "wof:name": "TF12 5FF",
    "wof:placetype": "postalcode"
  },
  "geometry": {"coordinates":[-2.49001,52.598411],"type":"Point"}
}
