{
  "type": "Feature",
  "properties": {
    "iso:country":"GB",
    "wof:name":"WF1 3SG",
    "wof:placetype":"postalcode"
},
  "geometry": {"coordinates":[-1.4919903366127,53.68886434689202],"type":"Point"}
}