{
  "type": "Feature",
  "properties": {
    "iso:country":"GB",
    "wof:name":"WC1B 3DG",
    "wof:placetype":"postalcode"
},
  "geometry": {"coordinates":[-0.12687343140335,51.51936239866416],"type":"Point"}
}