{
  "type": "Feature",
  "properties": {
    "date:inception_lower": "1980-01-01",
    "date:inception_upper": "1980-01-01",
    "iso:country": "GB",
    "wof:name": "EH19 3HY",
    "wof:placetype": "postalcode"
  },
  "geometry": {"coordinates":[-3.090156,55.861907],"type":"Point"}
}
