{
  "type": "Feature",
  "properties": {
    "iso:country":"GB",
    "wof:name":"DT1 2EZ",
    "wof:placetype":"postalcode"
},
  "geometry": {"coordinates":[-2.45038447311673,50.70622755404526],"type":"Point"}
}