{
  "type": "Feature",
  "properties": {
    "iso:country":"GB",
    "wof:name":"SG14 1BD",
    "wof:placetype":"postalcode"
},
  "geometry": {"coordinates":[-0.07640670110256,51.79667103007611],"type":"Point"}
}