{
  "type": "Feature",
  "properties": {
    "date:inception_lower": "1980-01-01",
    "date:inception_upper": "1980-01-01",
    "iso:country": "GB",
    "wof:name": "CT5 3LR",
    "wof:placetype": "postalcode"
  },
  "geometry": {"coordinates":[1.063228,51.346098],"type":"Point"}
}
