{
  "type": "Feature",
  "properties": {
    "iso:country":"GB",
    "wof:name":"CT5 3LR",
    "wof:placetype":"postalcode"
},
  "geometry": {"coordinates":[1.06322819018286,51.34609813023319],"type":"Point"}
}