{
  "type": "Feature",
  "properties": {
    "iso:country":"GB",
    "wof:name":"TN6 3EZ",
    "wof:placetype":"postalcode"
},
  "geometry": {"coordinates":[0.1853736310099,51.04336244251267],"type":"Point"}
}