{
  "type": "Feature",
  "properties": {
    "date:inception_lower": "2016-10-01",
    "date:inception_upper": "2016-10-01",
    "iso:country": "GB",
    "wof:name": "WF10 1ER",
    "wof:placetype": "postalcode"
  },
  "geometry": {"coordinates":[-1.360209,53.726676],"type":"Point"}
}
