{
  "type": "Feature",
  "properties": {
    "date:inception_lower": "2007-09-01",
    "date:inception_upper": "2007-09-01",
    "iso:country": "GB",
    "wof:name": "G68 0FR",
    "wof:placetype": "postalcode"
  },
  "geometry": {"coordinates":[-3.961521,55.974519],"type":"Point"}
}
