{
  "type": "Feature",
  "properties": {
    "iso:country": "GB",
    "wof:name": "G68 0FR",
    "wof:placetype": "postalcode"
  },
  "geometry": {"coordinates":[-3.96204,55.974322],"type":"Point"}
}
