{
  "type": "Feature",
  "properties": {
    "iso:country": "GB",
    "wof:name": "SM2 7HA",
    "wof:placetype": "postalcode"
  },
  "geometry": {"coordinates":[-0.214327,51.340291],"type":"Point"}
}
