{
  "type": "Feature",
  "properties": {
    "iso:country":"GB",
    "wof:name":"SM2 7HA",
    "wof:placetype":"postalcode"
},
  "geometry": {"coordinates":[-0.21432707150112,51.34029105951358],"type":"Point"}
}