{
  "type": "Feature",
  "properties": {
    "date:inception_lower": "1987-10-01",
    "date:inception_upper": "1987-10-01",
    "iso:country": "GB",
    "wof:name": "TS17 0TT",
    "wof:placetype": "postalcode"
  },
  "geometry": {"coordinates":[-1.30998,54.521599],"type":"Point"}
}
