{
  "type": "Feature",
  "properties": {
    "date:inception_lower":"1980-01-01",
    "date:inception_upper":"1980-01-31",
    "iso:country":"GB",
    "wof:name":"SG5 1AT",
    "wof:placetype":"postalcode"
},
  "geometry": {"coordinates":[-0.278124,51.948405],"type":"Point"}
}