{
  "type": "Feature",
  "properties": {
    "iso:country":"GB",
    "wof:name":"SG5 1AT",
    "wof:placetype":"postalcode"
},
  "geometry": {"coordinates":[-0.27823664245935,51.94835430208961],"type":"Point"}
}