{
  "type": "Feature",
  "properties": {
    "iso:country":"GB",
    "wof:name":"TQ12 1GA",
    "wof:placetype":"postalcode"
},
  "geometry": {"coordinates":[-3.61749395028173,50.52996011873428],"type":"Point"}
}