{
  "type": "Feature",
  "properties": {
    "date:inception_lower":"2000-06-01",
    "date:inception_upper":"2000-06-30",
    "iso:country":"GB",
    "wof:name":"TQ12 1GA",
    "wof:placetype":"postalcode"
},
  "geometry": {"coordinates":[-3.617494,50.52996],"type":"Point"}
}