{
  "type": "Feature",
  "properties": {
    "iso:country": "GB",
    "wof:name": "TQ12 1GA",
    "wof:placetype": "postalcode"
  },
  "geometry": {"coordinates":[-3.617494,50.52996],"type":"Point"}
}
