{
  "type": "Feature",
  "properties": {
    "iso:country": "GB",
    "wof:name": "TS8 9FG",
    "wof:placetype": "postalcode"
  },
  "geometry": {"coordinates":[-1.261478,54.524443],"type":"Point"}
}
