{
  "type": "Feature",
  "properties": {
    "iso:country":"GB",
    "wof:name":"TS8 9FG",
    "wof:placetype":"postalcode"
},
  "geometry": {"coordinates":[-1.2609984691706,54.52458138610453],"type":"Point"}
}