{
  "type": "Feature",
  "properties": {
    "date:inception_lower":"2014-02-01",
    "date:inception_upper":"2014-02-28",
    "iso:country":"GB",
    "wof:name":"TS8 9FG",
    "wof:placetype":"postalcode"
},
  "geometry": {"coordinates":[-1.261478,54.524443],"type":"Point"}
}