{
  "type": "Feature",
  "properties": {
    "iso:country": "GB",
    "wof:name": "LN13 0DH",
    "wof:placetype": "postalcode"
  },
  "geometry": {"coordinates":[0.116134,53.284399],"type":"Point"}
}
