{
  "type": "Feature",
  "properties": {
    "iso:country":"GB",
    "wof:name":"SN10 2NF",
    "wof:placetype":"postalcode"
},
  "geometry": {"coordinates":[-2.02026103319276,51.36471293210816],"type":"Point"}
}