{
  "type": "Feature",
  "properties": {
    "iso:country":"GB",
    "wof:name":"S12 4QN",
    "wof:placetype":"postalcode"
},
  "geometry": {"coordinates":[-1.39616591463919,53.34726040530247],"type":"Point"}
}