{
  "type": "Feature",
  "properties": {
    "date:inception_lower": "2017-07-01",
    "date:inception_upper": "2017-07-01",
    "iso:country": "GB",
    "wof:name": "BN17 5TJ",
    "wof:placetype": "postalcode"
  },
  "geometry": {"coordinates":[-0.531016,50.803166],"type":"Point"}
}
