{
  "type": "Feature",
  "properties": {
    "iso:country":"GB",
    "wof:name":"PL14 3DR",
    "wof:placetype":"postalcode"
},
  "geometry": {"coordinates":[-4.46440449216747,50.45687567379676],"type":"Point"}
}