{
  "type": "Feature",
  "properties": {
    "date:inception_lower": "1980-01-01",
    "date:inception_upper": "1980-01-01",
    "iso:country": "GB",
    "wof:name": "DT1 1UG",
    "wof:placetype": "postalcode"
  },
  "geometry": {"coordinates":[-2.436984,50.715244],"type":"Point"}
}
