{
  "type": "Feature",
  "properties": {
    "date:inception_lower": "2024-01-01",
    "date:inception_upper": "2024-01-01",
    "iso:country": "GB",
    "wof:name": "HU17 9FF",
    "wof:placetype": "postalcode"
  },
  "geometry": {"coordinates":[-0.379362,53.861665],"type":"Point"}
}
