{
  "type": "Feature",
  "properties": {
    "iso:country": "GB",
    "wof:name": "GL7 2QQ",
    "wof:placetype": "postalcode"
  },
  "geometry": {"coordinates":[-1.964864,51.717811],"type":"Point"}
}
