{
  "type": "Feature",
  "properties": {
    "iso:country":"GB",
    "wof:name":"GL7 2QQ",
    "wof:placetype":"postalcode"
},
  "geometry": {"coordinates":[-1.96486445599027,51.71781083201908],"type":"Point"}
}