{
  "type": "Feature",
  "properties": {
    "iso:country":"GB",
    "wof:name":"HU7 4HD",
    "wof:placetype":"postalcode"
},
  "geometry": {"coordinates":[-0.33658744428181,53.79350815343245],"type":"Point"}
}