{
  "type": "Feature",
  "properties": {
    "date:inception_lower": "2005-01-01",
    "date:inception_upper": "2005-01-01",
    "iso:country": "GB",
    "wof:name": "NG22 0LE",
    "wof:placetype": "postalcode"
  },
  "geometry": {"coordinates":[-0.899445,53.23455],"type":"Point"}
}
