{
  "type": "Feature",
  "properties": {
    "iso:country": "GB",
    "wof:name": "NG22 0LE",
    "wof:placetype": "postalcode"
  },
  "geometry": {"coordinates":[-0.899445,53.23455],"type":"Point"}
}
