{
  "type": "Feature",
  "properties": {
    "iso:country":"GB",
    "wof:name":"L39 2BD",
    "wof:placetype":"postalcode"
},
  "geometry": {"coordinates":[-2.86661613990799,53.56533278807642],"type":"Point"}
}