{
  "type": "Feature",
  "properties": {
    "date:inception_lower":"1980-01-01",
    "date:inception_upper":"1980-01-31",
    "iso:country":"GB",
    "wof:name":"L39 2BD",
    "wof:placetype":"postalcode"
},
  "geometry": {"coordinates":[-2.866616,53.565333],"type":"Point"}
}