{
  "type": "Feature",
  "properties": {
    "iso:country": "GB",
    "wof:name": "BB4 4NZ",
    "wof:placetype": "postalcode"
  },
  "geometry": {"coordinates":[-2.332442,53.686333],"type":"Point"}
}
