{
  "type": "Feature",
  "properties": {
    "date:inception_lower":"1995-01-01",
    "date:inception_upper":"1995-01-31",
    "iso:country":"GB",
    "wof:name":"BB4 4NZ",
    "wof:placetype":"postalcode"
},
  "geometry": {"coordinates":[-2.332442,53.686333],"type":"Point"}
}