{
  "type": "Feature",
  "properties": {
    "iso:country":"GB",
    "wof:name":"LE10 3EZ",
    "wof:placetype":"postalcode"
},
  "geometry": {"coordinates":[-1.38025468754507,52.5233447167216],"type":"Point"}
}