{
  "type": "Feature",
  "properties": {
    "date:inception_lower": "2018-11-01",
    "date:inception_upper": "2018-11-01",
    "iso:country": "GB",
    "wof:name": "SN13 8DS",
    "wof:placetype": "postalcode"
  },
  "geometry": {"coordinates":[-2.249134,51.421158],"type":"Point"}
}
