{
  "type": "Feature",
  "properties": {
    "iso:country": "GB",
    "wof:name": "SN13 8DS",
    "wof:placetype": "postalcode"
  },
  "geometry": {"coordinates":[-2.249134,51.421158],"type":"Point"}
}
