{
  "type": "Feature",
  "properties": {
    "iso:country": "GB",
    "wof:name": "ML9 2RZ",
    "wof:placetype": "postalcode"
  },
  "geometry": {"coordinates":[-3.954745,55.733606],"type":"Point"}
}
