{
  "type": "Feature",
  "properties": {
    "iso:country":"GB",
    "wof:name":"M43 7TX",
    "wof:placetype":"postalcode"
},
  "geometry": {"coordinates":[-2.13043922209305,53.49103949334638],"type":"Point"}
}