{
  "type": "Feature",
  "properties": {
    "date:inception_lower":"2001-06-01",
    "date:inception_upper":"2001-06-30",
    "iso:country":"GB",
    "wof:name":"WA5 7XF",
    "wof:placetype":"postalcode"
},
  "geometry": {"coordinates":[-2.639162,53.413554],"type":"Point"}
}