{
  "type": "Feature",
  "properties": {
    "iso:country":"GB",
    "wof:name":"WA5 7XF",
    "wof:placetype":"postalcode"
},
  "geometry": {"coordinates":[-2.63916188643173,53.41355446731818],"type":"Point"}
}