{
  "type": "Feature",
  "properties": {
    "iso:country":"GB",
    "wof:name":"HG3 3TX",
    "wof:placetype":"postalcode"
},
  "geometry": {"coordinates":[-1.50526578297688,54.06959485308818],"type":"Point"}
}