{
  "type": "Feature",
  "properties": {
    "date:inception_lower": "1996-12-01",
    "date:inception_upper": "1996-12-01",
    "iso:country": "GB",
    "wof:name": "HG3 3TX",
    "wof:placetype": "postalcode"
  },
  "geometry": {"coordinates":[-1.505266,54.069595],"type":"Point"}
}
