{
  "type": "Feature",
  "properties": {
    "iso:country":"GB",
    "wof:name":"IV19 1PU",
    "wof:placetype":"postalcode"
},
  "geometry": {"coordinates":[-4.0662005797122,57.80194240130353],"type":"Point"}
}