{
  "type": "Feature",
  "properties": {
    "iso:country":"GB",
    "wof:name":"YO7 4PD",
    "wof:placetype":"postalcode"
},
  "geometry": {"coordinates":[-1.4583178885211,54.20025179044987],"type":"Point"}
}