{
  "type": "Feature",
  "properties": {
    "date:inception_lower":"1980-01-01",
    "date:inception_upper":"1980-01-31",
    "iso:country":"GB",
    "wof:name":"PR4 3SU",
    "wof:placetype":"postalcode"
},
  "geometry": {"coordinates":[-2.838885,53.772804],"type":"Point"}
}