{
  "type": "Feature",
  "properties": {
    "iso:country": "GB",
    "wof:name": "PR4 3SU",
    "wof:placetype": "postalcode"
  },
  "geometry": {"coordinates":[-2.838885,53.772804],"type":"Point"}
}
