{
  "type": "Feature",
  "properties": {
    "iso:country": "GB",
    "wof:name": "ST17 0ND",
    "wof:placetype": "postalcode"
  },
  "geometry": {"coordinates":[-2.065623,52.783185],"type":"Point"}
}
