{
  "type": "Feature",
  "properties": {
    "date:inception_lower": "1988-03-01",
    "date:inception_upper": "1988-03-01",
    "iso:country": "GB",
    "wof:name": "S65 3BG",
    "wof:placetype": "postalcode"
  },
  "geometry": {"coordinates":[-1.324895,53.422978],"type":"Point"}
}
