{
  "type": "Feature",
  "properties": {
    "iso:country":"GB",
    "wof:name":"S65 3BG",
    "wof:placetype":"postalcode"
},
  "geometry": {"coordinates":[-1.32489454648584,53.42297750572535],"type":"Point"}
}