{
  "type": "Feature",
  "properties": {
    "iso:country":"GB",
    "wof:name":"SW16 2NA",
    "wof:placetype":"postalcode"
},
  "geometry": {"coordinates":[-0.11761046937954,51.43143748276824],"type":"Point"}
}