{
  "type": "Feature",
  "properties": {
    "date:inception_lower": "1980-01-01",
    "date:inception_upper": "1980-01-01",
    "iso:country": "GB",
    "wof:name": "NN16 9RJ",
    "wof:placetype": "postalcode"
  },
  "geometry": {"coordinates":[-0.723553,52.409848],"type":"Point"}
}
