{
  "type": "Feature",
  "properties": {
    "iso:country":"GB",
    "wof:name":"NN16 9RJ",
    "wof:placetype":"postalcode"
},
  "geometry": {"coordinates":[-0.72355295812304,52.40984809286846],"type":"Point"}
}