{
  "type": "Feature",
  "properties": {
    "iso:country": "GB",
    "wof:name": "WC1A 1LY",
    "wof:placetype": "postalcode"
  },
  "geometry": {"coordinates":[-0.125199,51.517654],"type":"Point"}
}
