{
  "type": "Feature",
  "properties": {
    "iso:country":"GB",
    "wof:name":"WC1A 1LY",
    "wof:placetype":"postalcode"
},
  "geometry": {"coordinates":[-0.12519949289181,51.51765405398794],"type":"Point"}
}