{
  "type": "Feature",
  "properties": {
    "iso:country": "GB",
    "wof:name": "BS9 3HG",
    "wof:placetype": "postalcode"
  },
  "geometry": {"coordinates":[-2.61977,51.495072],"type":"Point"}
}
