{
  "type": "Feature",
  "properties": {
    "iso:country":"GB",
    "wof:name":"BS9 3HG",
    "wof:placetype":"postalcode"
},
  "geometry": {"coordinates":[-2.61976970583306,51.49507218793006],"type":"Point"}
}