{
  "type": "Feature",
  "properties": {
    "iso:country": "GB",
    "wof:name": "CA20 1AZ",
    "wof:placetype": "postalcode"
  },
  "geometry": {"coordinates":[-3.429992,54.419136],"type":"Point"}
}
