{
  "type": "Feature",
  "properties": {
    "iso:country":"GB",
    "wof:name":"NP10 9AQ",
    "wof:placetype":"postalcode"
},
  "geometry": {"coordinates":[-3.04846892600178,51.59076065088246],"type":"Point"}
}