{
  "type": "Feature",
  "properties": {
    "iso:country":"GB",
    "wof:name":"NW10 5EL",
    "wof:placetype":"postalcode"
},
  "geometry": {"coordinates":[-0.225829838196,51.53184464337508],"type":"Point"}
}