{
  "type": "Feature",
  "properties": {
    "date:inception_lower": "2002-12-01",
    "date:inception_upper": "2002-12-01",
    "iso:country": "GB",
    "wof:name": "G67 4AE",
    "wof:placetype": "postalcode"
  },
  "geometry": {"coordinates":[-3.975415,55.925918],"type":"Point"}
}
