{
  "type": "Feature",
  "properties": {
    "date:inception_lower": "1980-01-01",
    "date:inception_upper": "1980-01-01",
    "iso:country": "GB",
    "wof:name": "BN27 4LD",
    "wof:placetype": "postalcode"
  },
  "geometry": {"coordinates":[0.323342,50.889771],"type":"Point"}
}
