{
  "type": "Feature",
  "properties": {
    "iso:country":"GB",
    "wof:name":"S36 1EQ",
    "wof:placetype":"postalcode"
},
  "geometry": {"coordinates":[-1.59831474885066,53.48397417260308],"type":"Point"}
}