{
  "type": "Feature",
  "properties": {
    "iso:country": "GB",
    "wof:name": "S36 1EQ",
    "wof:placetype": "postalcode"
  },
  "geometry": {"coordinates":[-1.598315,53.483974],"type":"Point"}
}
