{
  "type": "Feature",
  "properties": {
    "iso:country": "GB",
    "wof:name": "LN1 1EB",
    "wof:placetype": "postalcode"
  },
  "geometry": {"coordinates":[-0.554423,53.242965],"type":"Point"}
}
