{
  "type": "Feature",
  "properties": {
    "iso:country":"GB",
    "wof:name":"LN1 1EB",
    "wof:placetype":"postalcode"
},
  "geometry": {"coordinates":[-0.55442339877284,53.24296499647291],"type":"Point"}
}