{
  "type": "Feature",
  "properties": {
    "iso:country": "GB",
    "wof:name": "DE23 8HZ",
    "wof:placetype": "postalcode"
  },
  "geometry": {"coordinates":[-1.472777,52.904857],"type":"Point"}
}
