{
  "type": "Feature",
  "properties": {
    "iso:country": "GB",
    "wof:name": "DY14 8PE",
    "wof:placetype": "postalcode"
  },
  "geometry": {"coordinates":[-2.483449,52.38019],"type":"Point"}
}
