{
  "type": "Feature",
  "properties": {
    "iso:country":"GB",
    "wof:name":"DY14 8PE",
    "wof:placetype":"postalcode"
},
  "geometry": {"coordinates":[-2.48344862273699,52.38019005104788],"type":"Point"}
}