{
  "type": "Feature",
  "properties": {
    "iso:country":"GB",
    "wof:name":"W1J 8DS",
    "wof:placetype":"postalcode"
},
  "geometry": {"coordinates":[-0.14280975296215,51.50815936191151],"type":"Point"}
}