{
  "type": "Feature",
  "properties": {
    "iso:country":"GB",
    "wof:name":"CB6 1NR",
    "wof:placetype":"postalcode"
},
  "geometry": {"coordinates":[0.30480490121193,52.4554870093237],"type":"Point"}
}