{
  "type": "Feature",
  "properties": {
    "date:inception_lower":"2007-02-01",
    "date:inception_upper":"2007-02-28",
    "iso:country":"GB",
    "wof:name":"CB6 1NR",
    "wof:placetype":"postalcode"
},
  "geometry": {"coordinates":[0.304805,52.455487],"type":"Point"}
}