{
  "type": "Feature",
  "properties": {
    "iso:country": "GB",
    "wof:name": "CB6 1NR",
    "wof:placetype": "postalcode"
  },
  "geometry": {"coordinates":[0.304805,52.455487],"type":"Point"}
}
