{
  "type": "Feature",
  "properties": {
    "iso:country": "GB",
    "wof:name": "BD20 8PD",
    "wof:placetype": "postalcode"
  },
  "geometry": {"coordinates":[-2.03287,53.923613],"type":"Point"}
}
