{
  "type": "Feature",
  "properties": {
    "iso:country":"GB",
    "wof:name":"BD20 8PD",
    "wof:placetype":"postalcode"
},
  "geometry": {"coordinates":[-2.03286995718807,53.92361336689429],"type":"Point"}
}