{
  "type": "Feature",
  "properties": {
    "date:inception_lower": "2020-12-01",
    "date:inception_upper": "2020-12-01",
    "iso:country": "GB",
    "wof:name": "LE12 7XG",
    "wof:placetype": "postalcode"
  },
  "geometry": {"coordinates":[-1.137511,52.727895],"type":"Point"}
}
