{
  "type": "Feature",
  "properties": {
    "iso:country": "GB",
    "wof:name": "PO33 1FY",
    "wof:placetype": "postalcode"
  },
  "geometry": {"coordinates":[-1.115876,50.698829],"type":"Point"}
}
