{
  "type": "Feature",
  "properties": {
    "iso:country":"GB",
    "wof:name":"PO33 1FY",
    "wof:placetype":"postalcode"
},
  "geometry": {"coordinates":[-1.11587648489999,50.69882898403685],"type":"Point"}
}