{
  "type": "Feature",
  "properties": {
    "date:inception_lower": "2012-08-01",
    "date:inception_upper": "2012-08-01",
    "iso:country": "GB",
    "wof:name": "PO33 1FY",
    "wof:placetype": "postalcode"
  },
  "geometry": {"coordinates":[-1.115876,50.698829],"type":"Point"}
}
