{
  "type": "Feature",
  "properties": {
    "date:inception_lower": "2006-04-01",
    "date:inception_upper": "2006-04-01",
    "iso:country": "GB",
    "wof:name": "EH48 2ST",
    "wof:placetype": "postalcode"
  },
  "geometry": {"coordinates":[-3.654323,55.897392],"type":"Point"}
}
