{
  "type": "Feature",
  "properties": {
    "iso:country":"GB",
    "wof:name":"EH48 2ST",
    "wof:placetype":"postalcode"
},
  "geometry": {"coordinates":[-3.65432283340496,55.89739238916221],"type":"Point"}
}