{
  "type": "Feature",
  "properties": {
    "iso:country":"GB",
    "wof:name":"PE34 3EW",
    "wof:placetype":"postalcode"
},
  "geometry": {"coordinates":[0.33384158028839,52.68908987184372],"type":"Point"}
}