{
  "type": "Feature",
  "properties": {
    "date:inception_lower": "2022-08-01",
    "date:inception_upper": "2022-08-01",
    "iso:country": "GB",
    "wof:name": "M30 0EH",
    "wof:placetype": "postalcode"
  },
  "geometry": {"coordinates":[-2.335742,53.484552],"type":"Point"}
}
