{
  "type": "Feature",
  "properties": {
    "iso:country": "GB",
    "wof:name": "NG5 9QD",
    "wof:placetype": "postalcode"
  },
  "geometry": {"coordinates":[-1.16044,53.014261],"type":"Point"}
}
