{
  "type": "Feature",
  "properties": {
    "date:inception_lower": "1981-06-01",
    "date:inception_upper": "1981-06-01",
    "iso:country": "GB",
    "wof:name": "NG5 9QD",
    "wof:placetype": "postalcode"
  },
  "geometry": {"coordinates":[-1.16044,53.014261],"type":"Point"}
}
