{
  "type": "Feature",
  "properties": {
    "iso:country": "GB",
    "wof:name": "SA12 8PF",
    "wof:placetype": "postalcode"
  },
  "geometry": {"coordinates":[-3.807774,51.623261],"type":"Point"}
}
