{
  "type": "Feature",
  "properties": {
    "iso:country":"GB",
    "wof:name":"KA27 8BD",
    "wof:placetype":"postalcode"
},
  "geometry": {"coordinates":[-5.14333619018627,55.57413501162451],"type":"Point"}
}