{
  "type": "Feature",
  "properties": {
    "iso:country": "GB",
    "wof:name": "WD17 1UL",
    "wof:placetype": "postalcode"
  },
  "geometry": {"coordinates":[-0.400301,51.663651],"type":"Point"}
}
