{
  "type": "Feature",
  "properties": {
    "date:inception_lower": "2017-01-01",
    "date:inception_upper": "2017-01-01",
    "iso:country": "GB",
    "wof:name": "W6 0DB",
    "wof:placetype": "postalcode"
  },
  "geometry": {"coordinates":[-0.235813,51.493401],"type":"Point"}
}
