{
  "type": "Feature",
  "properties": {
    "iso:country":"GB",
    "wof:name":"CF62 3DQ",
    "wof:placetype":"postalcode"
},
  "geometry": {"coordinates":[-3.34640267445577,51.3907678008151],"type":"Point"}
}