{
  "type": "Feature",
  "properties": {
    "iso:country": "GB",
    "wof:name": "HX3 6LR",
    "wof:placetype": "postalcode"
  },
  "geometry": {"coordinates":[-1.866049,53.734411],"type":"Point"}
}
