{
  "type": "Feature",
  "properties": {
    "date:inception_lower":"1980-01-01",
    "date:inception_upper":"1980-01-31",
    "iso:country":"GB",
    "wof:name":"HX3 6LR",
    "wof:placetype":"postalcode"
},
  "geometry": {"coordinates":[-1.866049,53.734411],"type":"Point"}
}