{
  "type": "Feature",
  "properties": {
    "iso:country":"GB",
    "wof:name":"CF64 3LN",
    "wof:placetype":"postalcode"
},
  "geometry": {"coordinates":[-3.18590985611596,51.43266972657307],"type":"Point"}
}