{
  "type": "Feature",
  "properties": {
    "date:inception_lower":"1993-01-01",
    "date:inception_upper":"1993-01-31",
    "iso:country":"GB",
    "wof:name":"CF64 3LN",
    "wof:placetype":"postalcode"
},
  "geometry": {"coordinates":[-3.18591,51.43267],"type":"Point"}
}