{
  "type": "Feature",
  "properties": {
    "iso:country": "GB",
    "wof:name": "NE19 1LQ",
    "wof:placetype": "postalcode"
  },
  "geometry": {"coordinates":[-2.226048,55.24486],"type":"Point"}
}
