{
  "type": "Feature",
  "properties": {
    "date:inception_lower": "1980-01-01",
    "date:inception_upper": "1980-01-01",
    "iso:country": "GB",
    "wof:name": "NE19 1LQ",
    "wof:placetype": "postalcode"
  },
  "geometry": {"coordinates":[-2.226048,55.24486],"type":"Point"}
}
