{
  "type": "Feature",
  "properties": {
    "iso:country":"GB",
    "wof:name":"EX17 4LS",
    "wof:placetype":"postalcode"
},
  "geometry": {"coordinates":[-3.66691561137211,50.81024657218913],"type":"Point"}
}