{
  "type": "Feature",
  "properties": {
    "iso:country": "GB",
    "wof:name": "GU19 5AX",
    "wof:placetype": "postalcode"
  },
  "geometry": {"coordinates":[-0.691986,51.361642],"type":"Point"}
}
