{
  "type": "Feature",
  "properties": {
    "iso:country":"GB",
    "wof:name":"DD5 4EE",
    "wof:placetype":"postalcode"
},
  "geometry": {"coordinates":[-2.81170751390933,56.48558043778672],"type":"Point"}
}