{
  "type": "Feature",
  "properties": {
    "iso:country":"GB",
    "wof:name":"AB41 8BL",
    "wof:placetype":"postalcode"
},
  "geometry": {"coordinates":[-2.0734107657103,57.3722348010031],"type":"Point"}
}