{
  "type": "Feature",
  "properties": {
    "date:inception_lower": "1991-11-01",
    "date:inception_upper": "1991-11-01",
    "iso:country": "GB",
    "wof:name": "AB41 8BL",
    "wof:placetype": "postalcode"
  },
  "geometry": {"coordinates":[-2.073411,57.372235],"type":"Point"}
}
