{
  "type": "Feature",
  "properties": {
    "iso:country":"GB",
    "wof:name":"CR3 6DP",
    "wof:placetype":"postalcode"
},
  "geometry": {"coordinates":[-0.07915273637035,51.27355645615967],"type":"Point"}
}