{
  "type": "Feature",
  "properties": {
    "iso:country":"GB",
    "wof:name":"HA3 9AN",
    "wof:placetype":"postalcode"
},
  "geometry": {"coordinates":[-0.30258788695336,51.59388493600463],"type":"Point"}
}