{
  "type": "Feature",
  "properties": {
    "date:inception_lower":"1980-01-01",
    "date:inception_upper":"1980-01-31",
    "iso:country":"GB",
    "wof:name":"HA3 9AN",
    "wof:placetype":"postalcode"
},
  "geometry": {"coordinates":[-0.302588,51.593885],"type":"Point"}
}