{
  "type": "Feature",
  "properties": {
    "iso:country": "GB",
    "wof:name": "NE20 9BB",
    "wof:placetype": "postalcode"
  },
  "geometry": {"coordinates":[-1.74098,55.050222],"type":"Point"}
}
