{
  "type": "Feature",
  "properties": {
    "iso:country":"GB",
    "wof:name":"NE20 9BB",
    "wof:placetype":"postalcode"
},
  "geometry": {"coordinates":[-1.74097973697302,55.05022191187518],"type":"Point"}
}