{
  "type": "Feature",
  "properties": {
    "iso:country":"GB",
    "wof:name":"KA3 7TQ",
    "wof:placetype":"postalcode"
},
  "geometry": {"coordinates":[-4.47275796695695,55.62330197137466],"type":"Point"}
}