{
  "type": "Feature",
  "properties": {
    "iso:country": "GB",
    "wof:name": "CT14 6AX",
    "wof:placetype": "postalcode"
  },
  "geometry": {"coordinates":[1.398979,51.225027],"type":"Point"}
}
