{
  "type": "Feature",
  "properties": {
    "iso:country":"GB",
    "wof:name":"NN17 2PT",
    "wof:placetype":"postalcode"
},
  "geometry": {"coordinates":[-0.72440992600275,52.4947642936548],"type":"Point"}
}