{
  "type": "Feature",
  "properties": {
    "iso:country":"GB",
    "wof:name":"EX5 2SQ",
    "wof:placetype":"postalcode"
},
  "geometry": {"coordinates":[-3.35929087308657,50.76625952586916],"type":"Point"}
}