{
  "type": "Feature",
  "properties": {
    "iso:country": "GB",
    "wof:name": "WA9 2NJ",
    "wof:placetype": "postalcode"
  },
  "geometry": {"coordinates":[-2.689332,53.445814],"type":"Point"}
}
