{
  "type": "Feature",
  "properties": {
    "iso:country":"GB",
    "wof:name":"WA9 2NJ",
    "wof:placetype":"postalcode"
},
  "geometry": {"coordinates":[-2.68933175764618,53.44581440898032],"type":"Point"}
}