{
  "type": "Feature",
  "properties": {
    "date:inception_lower":"1980-01-01",
    "date:inception_upper":"1980-01-31",
    "iso:country":"GB",
    "wof:name":"DY12 1AG",
    "wof:placetype":"postalcode"
},
  "geometry": {"coordinates":[-2.311215,52.376463],"type":"Point"}
}