{
  "type": "Feature",
  "properties": {
    "iso:country": "GB",
    "wof:name": "KT17 1RW",
    "wof:placetype": "postalcode"
  },
  "geometry": {"coordinates":[-0.249328,51.349021],"type":"Point"}
}
