{
  "type": "Feature",
  "properties": {
    "date:inception_lower":"1980-01-01",
    "date:inception_upper":"1980-01-31",
    "iso:country":"GB",
    "wof:name":"KT17 1RW",
    "wof:placetype":"postalcode"
},
  "geometry": {"coordinates":[-0.249328,51.349021],"type":"Point"}
}