{
  "type": "Feature",
  "properties": {
    "iso:country":"GB",
    "wof:name":"KT17 1RW",
    "wof:placetype":"postalcode"
},
  "geometry": {"coordinates":[-0.24932833347981,51.34902070361392],"type":"Point"}
}