{
  "type": "Feature",
  "properties": {
    "iso:country": "GB",
    "wof:name": "PO3 5AB",
    "wof:placetype": "postalcode"
  },
  "geometry": {"coordinates":[-1.064218,50.810666],"type":"Point"}
}
