{
  "type": "Feature",
  "properties": {
    "iso:country": "GB",
    "wof:name": "SA33 6UT",
    "wof:placetype": "postalcode"
  },
  "geometry": {"coordinates":[-4.341798,51.948585],"type":"Point"}
}
