{
  "type": "Feature",
  "properties": {
    "iso:country":"GB",
    "wof:name":"SA33 6UT",
    "wof:placetype":"postalcode"
},
  "geometry": {"coordinates":[-4.34179779955986,51.94858495372065],"type":"Point"}
}