{
  "type": "Feature",
  "properties": {
    "iso:country": "GB",
    "wof:name": "DE21 5DA",
    "wof:placetype": "postalcode"
  },
  "geometry": {"coordinates":[-1.46089,52.95696],"type":"Point"}
}
