{
  "type": "Feature",
  "properties": {
    "iso:country":"GB",
    "wof:name":"B31 2QU",
    "wof:placetype":"postalcode"
},
  "geometry": {"coordinates":[-1.97525973616794,52.40786880263781],"type":"Point"}
}