{
  "type": "Feature",
  "properties": {
    "date:inception_lower":"1980-01-01",
    "date:inception_upper":"1980-01-31",
    "iso:country":"GB",
    "wof:name":"B31 2QU",
    "wof:placetype":"postalcode"
},
  "geometry": {"coordinates":[-1.974444,52.408441],"type":"Point"}
}