{
  "type": "Feature",
  "properties": {
    "iso:country":"GB",
    "wof:name":"RM13 9ES",
    "wof:placetype":"postalcode"
},
  "geometry": {"coordinates":[0.2254704822924,51.52438397858335],"type":"Point"}
}