{
  "type": "Feature",
  "properties": {
    "date:inception_lower":"1980-01-01",
    "date:inception_upper":"1980-01-31",
    "iso:country":"GB",
    "wof:name":"LN4 4UU",
    "wof:placetype":"postalcode"
},
  "geometry": {"coordinates":[-0.195031,53.083011],"type":"Point"}
}