{
  "type": "Feature",
  "properties": {
    "iso:country": "GB",
    "wof:name": "LN4 4UU",
    "wof:placetype": "postalcode"
  },
  "geometry": {"coordinates":[-0.195031,53.083011],"type":"Point"}
}
