{
  "type": "Feature",
  "properties": {
    "iso:country":"GB",
    "wof:name":"BH18 9AA",
    "wof:placetype":"postalcode"
},
  "geometry": {"coordinates":[-1.99647419431081,50.76374314925918],"type":"Point"}
}