{
  "type": "Feature",
  "properties": {
    "iso:country": "GB",
    "wof:name": "CW8 1LY",
    "wof:placetype": "postalcode"
  },
  "geometry": {"coordinates":[-2.54716,53.243216],"type":"Point"}
}
