{
  "type": "Feature",
  "properties": {
    "iso:country":"GB",
    "wof:name":"DG4 6DA",
    "wof:placetype":"postalcode"
},
  "geometry": {"coordinates":[-3.92548814351379,55.36802086354058],"type":"Point"}
}