{
  "type": "Feature",
  "properties": {
    "iso:country":"GB",
    "wof:name":"W1K 2AX",
    "wof:placetype":"postalcode"
},
  "geometry": {"coordinates":[-0.15230227355492,51.50932544405164],"type":"Point"}
}