{
  "type": "Feature",
  "properties": {
    "iso:country":"GB",
    "wof:name":"SP5 2PT",
    "wof:placetype":"postalcode"
},
  "geometry": {"coordinates":[-1.70578444274608,50.9751902650029],"type":"Point"}
}