{
  "type": "Feature",
  "properties": {
    "date:inception_lower": "1980-01-01",
    "date:inception_upper": "1980-01-01",
    "iso:country": "GB",
    "wof:name": "NW11 7LH",
    "wof:placetype": "postalcode"
  },
  "geometry": {"coordinates":[-0.189843,51.576545],"type":"Point"}
}
