{
  "type": "Feature",
  "properties": {
    "iso:country":"GB",
    "wof:name":"NW11 7LH",
    "wof:placetype":"postalcode"
},
  "geometry": {"coordinates":[-0.18984274948369,51.57654458925997],"type":"Point"}
}