{
  "type": "Feature",
  "properties": {
    "iso:country": "GB",
    "wof:name": "BA14 8TH",
    "wof:placetype": "postalcode"
  },
  "geometry": {"coordinates":[-2.207461,51.323079],"type":"Point"}
}
