{
  "type": "Feature",
  "properties": {
    "date:inception_lower":"2013-09-01",
    "date:inception_upper":"2013-09-30",
    "iso:country":"GB",
    "wof:name":"BA14 8TH",
    "wof:placetype":"postalcode"
},
  "geometry": {"coordinates":[-2.207461,51.323079],"type":"Point"}
}