{
  "type": "Feature",
  "properties": {
    "iso:country":"GB",
    "wof:name":"W4 1JQ",
    "wof:placetype":"postalcode"
},
  "geometry": {"coordinates":[-0.25968460443739,51.49662506471696],"type":"Point"}
}