{
  "type": "Feature",
  "properties": {
    "iso:country": "GB",
    "wof:name": "TR18 2TE",
    "wof:placetype": "postalcode"
  },
  "geometry": {"coordinates":[-5.533791,50.122355],"type":"Point"}
}
