{
  "type": "Feature",
  "properties": {
    "date:inception_lower":"2000-06-01",
    "date:inception_upper":"2000-06-30",
    "iso:country":"GB",
    "wof:name":"TR18 2TE",
    "wof:placetype":"postalcode"
},
  "geometry": {"coordinates":[-5.533791,50.122355],"type":"Point"}
}