{
  "type": "Feature",
  "properties": {
    "iso:country":"GB",
    "wof:name":"TR18 2TE",
    "wof:placetype":"postalcode"
},
  "geometry": {"coordinates":[-5.533790864711,50.12235452899139],"type":"Point"}
}