{
  "type": "Feature",
  "properties": {
    "iso:country":"GB",
    "wof:name":"WF3 1AW",
    "wof:placetype":"postalcode"
},
  "geometry": {"coordinates":[-1.57447722088566,53.72443717634131],"type":"Point"}
}