{
  "type": "Feature",
  "properties": {
    "iso:country":"GB",
    "wof:name":"RG41 3XA",
    "wof:placetype":"postalcode"
},
  "geometry": {"coordinates":[-0.85892289883516,51.41921839987327],"type":"Point"}
}