{
  "type": "Feature",
  "properties": {
    "iso:country": "GB",
    "wof:name": "RG9 2BS",
    "wof:placetype": "postalcode"
  },
  "geometry": {"coordinates":[-0.903369,51.539603],"type":"Point"}
}
