{
  "type": "Feature",
  "properties": {
    "iso:country":"GB",
    "wof:name":"RG9 2BS",
    "wof:placetype":"postalcode"
},
  "geometry": {"coordinates":[-0.90336906625495,51.53960301507981],"type":"Point"}
}