{
  "type": "Feature",
  "properties": {
    "iso:country":"GB",
    "wof:name":"DN7 6QF",
    "wof:placetype":"postalcode"
},
  "geometry": {"coordinates":[-1.00025267781771,53.58019028983163],"type":"Point"}
}