{
  "type": "Feature",
  "properties": {
    "iso:country": "GB",
    "wof:name": "DN7 6QF",
    "wof:placetype": "postalcode"
  },
  "geometry": {"coordinates":[-1.000253,53.58019],"type":"Point"}
}
