{
  "type": "Feature",
  "properties": {
    "iso:country":"GB",
    "wof:name":"B43 5DP",
    "wof:placetype":"postalcode"
},
  "geometry": {"coordinates":[-1.95590060432984,52.54034836165766],"type":"Point"}
}