{
  "type": "Feature",
  "properties": {
    "date:inception_lower":"2009-07-01",
    "date:inception_upper":"2009-07-31",
    "iso:country":"GB",
    "wof:name":"SO16 0AN",
    "wof:placetype":"postalcode"
},
  "geometry": {"coordinates":[-1.480587,50.949381],"type":"Point"}
}