{
  "type": "Feature",
  "properties": {
    "iso:country": "GB",
    "wof:name": "SO16 0AN",
    "wof:placetype": "postalcode"
  },
  "geometry": {"coordinates":[-1.480587,50.949381],"type":"Point"}
}
