{
  "type": "Feature",
  "properties": {
    "iso:country":"GB",
    "wof:name":"SO16 0AN",
    "wof:placetype":"postalcode"
},
  "geometry": {"coordinates":[-1.4806168345749,50.94928197123465],"type":"Point"}
}