{
  "type": "Feature",
  "properties": {
    "iso:country": "GB",
    "wof:name": "EX4 2BN",
    "wof:placetype": "postalcode"
  },
  "geometry": {"coordinates":[-3.550053,50.726072],"type":"Point"}
}
