{
  "type": "Feature",
  "properties": {
    "iso:country":"GB",
    "wof:name":"EX4 2BN",
    "wof:placetype":"postalcode"
},
  "geometry": {"coordinates":[-3.55005265263822,50.72607168955309],"type":"Point"}
}