{
  "type": "Feature",
  "properties": {
    "iso:country": "GB",
    "wof:name": "YO31 7UF",
    "wof:placetype": "postalcode"
  },
  "geometry": {"coordinates":[-1.065381,53.978235],"type":"Point"}
}
