{
  "type": "Feature",
  "properties": {
    "iso:country":"GB",
    "wof:name":"OX13 5ND",
    "wof:placetype":"postalcode"
},
  "geometry": {"coordinates":[-1.40359653334329,51.67059221898072],"type":"Point"}
}