{
  "type": "Feature",
  "properties": {
    "date:inception_lower":"1980-01-01",
    "date:inception_upper":"1980-01-31",
    "iso:country":"GB",
    "wof:name":"OX13 5ND",
    "wof:placetype":"postalcode"
},
  "geometry": {"coordinates":[-1.403596,51.670592],"type":"Point"}
}