{
  "type": "Feature",
  "properties": {
    "date:inception_lower": "2021-04-01",
    "date:inception_upper": "2021-04-01",
    "iso:country": "GB",
    "wof:name": "LE15 7WS",
    "wof:placetype": "postalcode"
  },
  "geometry": {"coordinates":[-0.600599,52.733637],"type":"Point"}
}
