{
  "type": "Feature",
  "properties": {
    "date:inception_lower": "1980-01-01",
    "date:inception_upper": "1980-01-01",
    "iso:country": "GB",
    "wof:name": "DL11 6RU",
    "wof:placetype": "postalcode"
  },
  "geometry": {"coordinates":[-2.009684,54.429626],"type":"Point"}
}
