{
  "type": "Feature",
  "properties": {
    "iso:country":"GB",
    "wof:name":"IV12 5RE",
    "wof:placetype":"postalcode"
},
  "geometry": {"coordinates":[-3.92664376481544,57.52707828074848],"type":"Point"}
}