{
  "type": "Feature",
  "properties": {
    "iso:country":"GB",
    "wof:name":"EH26 9DG",
    "wof:placetype":"postalcode"
},
  "geometry": {"coordinates":[-3.2229995752596,55.82593821302826],"type":"Point"}
}