{
  "type": "Feature",
  "properties": {
    "iso:country": "GB",
    "wof:name": "SA61 2UA",
    "wof:placetype": "postalcode"
  },
  "geometry": {"coordinates":[-4.987014,51.803054],"type":"Point"}
}
