{
  "type": "Feature",
  "properties": {
    "date:inception_lower":"1980-01-01",
    "date:inception_upper":"1980-01-31",
    "iso:country":"GB",
    "wof:name":"SA61 2UA",
    "wof:placetype":"postalcode"
},
  "geometry": {"coordinates":[-4.987014,51.803054],"type":"Point"}
}