{
  "type": "Feature",
  "properties": {
    "iso:country":"GB",
    "wof:name":"SA61 2UA",
    "wof:placetype":"postalcode"
},
  "geometry": {"coordinates":[-4.98698115890484,51.80304082934312],"type":"Point"}
}