{
  "type": "Feature",
  "properties": {
    "iso:country":"GB",
    "wof:name":"NE3 3PW",
    "wof:placetype":"postalcode"
},
  "geometry": {"coordinates":[-1.62418663103865,55.01162758738514],"type":"Point"}
}