{
  "type": "Feature",
  "properties": {
    "iso:country": "GB",
    "wof:name": "NE3 3PW",
    "wof:placetype": "postalcode"
  },
  "geometry": {"coordinates":[-1.624187,55.011628],"type":"Point"}
}
