{
  "type": "Feature",
  "properties": {
    "date:inception_lower": "2018-03-01",
    "date:inception_upper": "2018-03-01",
    "iso:country": "GB",
    "wof:name": "N19 4BS",
    "wof:placetype": "postalcode"
  },
  "geometry": {"coordinates":[-0.127915,51.560801],"type":"Point"}
}
