{
  "type": "Feature",
  "properties": {
    "iso:country": "GB",
    "wof:name": "CO15 2NX",
    "wof:placetype": "postalcode"
  },
  "geometry": {"coordinates":[1.112438,51.78458],"type":"Point"}
}
