{
  "type": "Feature",
  "properties": {
    "iso:country":"GB",
    "wof:name":"NG5 9RL",
    "wof:placetype":"postalcode"
},
  "geometry": {"coordinates":[-1.17890219723967,52.99962944547386],"type":"Point"}
}