{
  "type": "Feature",
  "properties": {
    "date:inception_lower":"1987-10-01",
    "date:inception_upper":"1987-10-31",
    "iso:country":"GB",
    "wof:name":"NG5 9RL",
    "wof:placetype":"postalcode"
},
  "geometry": {"coordinates":[-1.178902,52.999629],"type":"Point"}
}