{
  "type": "Feature",
  "properties": {
    "date:inception_lower": "2021-04-01",
    "date:inception_upper": "2021-04-01",
    "iso:country": "GB",
    "wof:name": "HD9 4FE",
    "wof:placetype": "postalcode"
  },
  "geometry": {"coordinates":[-1.836773,53.598372],"type":"Point"}
}
