{
  "type": "Feature",
  "properties": {
    "iso:country":"GB",
    "wof:name":"PE38 9AZ",
    "wof:placetype":"postalcode"
},
  "geometry": {"coordinates":[0.37921700074859,52.59280302305713],"type":"Point"}
}