{
  "type": "Feature",
  "properties": {
    "iso:country":"GB",
    "wof:name":"HR1 1QR",
    "wof:placetype":"postalcode"
},
  "geometry": {"coordinates":[-2.68490593442666,52.05955410931786],"type":"Point"}
}