{
  "type": "Feature",
  "properties": {
    "date:inception_lower": "2021-11-01",
    "date:inception_upper": "2021-11-01",
    "iso:country": "GB",
    "wof:name": "GL3 1GE",
    "wof:placetype": "postalcode"
  },
  "geometry": {"coordinates":[-2.195404,51.884453],"type":"Point"}
}
