{
  "type": "Feature",
  "properties": {
    "date:inception_lower": "1980-01-01",
    "date:inception_upper": "1980-01-01",
    "iso:country": "GB",
    "wof:name": "EH35 5JL",
    "wof:placetype": "postalcode"
  },
  "geometry": {"coordinates":[-2.946873,55.912558],"type":"Point"}
}
