{
  "type": "Feature",
  "properties": {
    "iso:country":"GB",
    "wof:name":"S6 2TL",
    "wof:placetype":"postalcode"
},
  "geometry": {"coordinates":[-1.4956013555325,53.39869676727462],"type":"Point"}
}