{
  "type": "Feature",
  "properties": {
    "iso:country": "GB",
    "wof:name": "S6 2TL",
    "wof:placetype": "postalcode"
  },
  "geometry": {"coordinates":[-1.495601,53.398697],"type":"Point"}
}
