{
  "type": "Feature",
  "properties": {
    "iso:country":"GB",
    "wof:name":"M6 5FB",
    "wof:placetype":"postalcode"
},
  "geometry": {"coordinates":[-2.28813442197021,53.48617892425247],"type":"Point"}
}