{
  "type": "Feature",
  "properties": {
    "iso:country":"GB",
    "wof:name":"LL14 3LN",
    "wof:placetype":"postalcode"
},
  "geometry": {"coordinates":[-3.07611226327612,52.97304914403651],"type":"Point"}
}