{
  "type": "Feature",
  "properties": {
    "date:inception_lower":"1985-10-01",
    "date:inception_upper":"1985-10-31",
    "iso:country":"GB",
    "wof:name":"LL14 3LN",
    "wof:placetype":"postalcode"
},
  "geometry": {"coordinates":[-3.076112,52.973049],"type":"Point"}
}