{
  "type": "Feature",
  "properties": {
    "iso:country": "GB",
    "wof:name": "LL14 3LN",
    "wof:placetype": "postalcode"
  },
  "geometry": {"coordinates":[-3.076112,52.973049],"type":"Point"}
}
