{
  "type": "Feature",
  "properties": {
    "iso:country":"GB",
    "wof:name":"TN6 1JU",
    "wof:placetype":"postalcode"
},
  "geometry": {"coordinates":[0.16233625629745,51.0461743505129],"type":"Point"}
}