{
  "type": "Feature",
  "properties": {
    "iso:country":"GB",
    "wof:name":"W5 1QQ",
    "wof:placetype":"postalcode"
},
  "geometry": {"coordinates":[-0.3105143135112,51.52691707909711],"type":"Point"}
}