{
  "type": "Feature",
  "properties": {
    "iso:country": "GB",
    "wof:name": "BS30 9DS",
    "wof:placetype": "postalcode"
  },
  "geometry": {"coordinates":[-2.490481,51.440827],"type":"Point"}
}
