{
  "type": "Feature",
  "properties": {
    "iso:country": "GB",
    "wof:name": "KA5 5LN",
    "wof:placetype": "postalcode"
  },
  "geometry": {"coordinates":[-4.415226,55.531125],"type":"Point"}
}
