{
  "type": "Feature",
  "properties": {
    "iso:country":"GB",
    "wof:name":"KA5 5LN",
    "wof:placetype":"postalcode"
},
  "geometry": {"coordinates":[-4.41522643923028,55.53112459911934],"type":"Point"}
}