{
  "type": "Feature",
  "properties": {
    "iso:country":"GB",
    "wof:name":"SN6 8BX",
    "wof:placetype":"postalcode"
},
  "geometry": {"coordinates":[-1.64772975709834,51.60531171592611],"type":"Point"}
}