{
  "type": "Feature",
  "properties": {
    "date:inception_lower": "2008-06-01",
    "date:inception_upper": "2008-06-01",
    "iso:country": "GB",
    "wof:name": "SN6 8BX",
    "wof:placetype": "postalcode"
  },
  "geometry": {"coordinates":[-1.64773,51.605312],"type":"Point"}
}
