{
  "type": "Feature",
  "properties": {
    "iso:country":"GB",
    "wof:name":"SG14 2AL",
    "wof:placetype":"postalcode"
},
  "geometry": {"coordinates":[-0.0953868119249,51.7943453454974],"type":"Point"}
}