{
  "type": "Feature",
  "properties": {
    "iso:country":"GB",
    "wof:name":"CF62 3BA",
    "wof:placetype":"postalcode"
},
  "geometry": {"coordinates":[-3.30451651078316,51.40779621753926],"type":"Point"}
}