{
  "type": "Feature",
  "properties": {
    "iso:country":"GB",
    "wof:name":"HA0 2FA",
    "wof:placetype":"postalcode"
},
  "geometry": {"coordinates":[-0.32193560604454,51.555433635561],"type":"Point"}
}