{
  "type": "Feature",
  "properties": {
    "date:inception_lower":"2012-10-01",
    "date:inception_upper":"2012-10-31",
    "iso:country":"GB",
    "wof:name":"S35 7ES",
    "wof:placetype":"postalcode"
},
  "geometry": {"coordinates":[-1.556179,53.520193],"type":"Point"}
}