{
  "type": "Feature",
  "properties": {
    "iso:country":"GB",
    "wof:name":"S35 7ES",
    "wof:placetype":"postalcode"
},
  "geometry": {"coordinates":[-1.55617911954648,53.52019262128439],"type":"Point"}
}