{
  "type": "Feature",
  "properties": {
    "iso:country": "GB",
    "wof:name": "S35 7ES",
    "wof:placetype": "postalcode"
  },
  "geometry": {"coordinates":[-1.556179,53.520193],"type":"Point"}
}
