{
  "type": "Feature",
  "properties": {
    "date:inception_lower": "1998-12-01",
    "date:inception_upper": "1998-12-01",
    "iso:country": "GB",
    "wof:name": "DA11 8RZ",
    "wof:placetype": "postalcode"
  },
  "geometry": {"coordinates":[0.349223,51.434197],"type":"Point"}
}
