{
  "type": "Feature",
  "properties": {
    "iso:country":"GB",
    "wof:name":"CB5 8RL",
    "wof:placetype":"postalcode"
},
  "geometry": {"coordinates":[0.16397421152335,52.21102655412829],"type":"Point"}
}