{
  "type": "Feature",
  "properties": {
    "iso:country": "GB",
    "wof:name": "DH3 3AR",
    "wof:placetype": "postalcode"
  },
  "geometry": {"coordinates":[-1.574457,54.857914],"type":"Point"}
}
