{
  "type": "Feature",
  "properties": {
    "date:inception_lower": "2019-06-01",
    "date:inception_upper": "2019-06-01",
    "iso:country": "GB",
    "wof:name": "DH3 3AR",
    "wof:placetype": "postalcode"
  },
  "geometry": {"coordinates":[-1.574274,54.857536],"type":"Point"}
}
