{
  "type": "Feature",
  "properties": {
    "iso:country": "GB",
    "wof:name": "KT23 3HR",
    "wof:placetype": "postalcode"
  },
  "geometry": {"coordinates":[-0.387407,51.287866],"type":"Point"}
}
