{
  "type": "Feature",
  "properties": {
    "iso:country":"GB",
    "wof:name":"ST3 3EY",
    "wof:placetype":"postalcode"
},
  "geometry": {"coordinates":[-2.16229419141756,52.97501514910087],"type":"Point"}
}