{
  "type": "Feature",
  "properties": {
    "iso:country":"GB",
    "wof:name":"WA11 0PZ",
    "wof:placetype":"postalcode"
},
  "geometry": {"coordinates":[-2.65966402845394,53.47061984043692],"type":"Point"}
}