{
  "type": "Feature",
  "properties": {
    "date:inception_lower":"1980-01-01",
    "date:inception_upper":"1980-01-31",
    "iso:country":"GB",
    "wof:name":"TD14 5JL",
    "wof:placetype":"postalcode"
},
  "geometry": {"coordinates":[-2.175563,55.851343],"type":"Point"}
}