{
  "type": "Feature",
  "properties": {
    "iso:country":"GB",
    "wof:name":"M30 0GN",
    "wof:placetype":"postalcode"
},
  "geometry": {"coordinates":[-2.35052960522222,53.48486156050461],"type":"Point"}
}