{
  "type": "Feature",
  "properties": {
    "date:inception_lower":"1994-05-01",
    "date:inception_upper":"1994-05-31",
    "iso:country":"GB",
    "wof:name":"M30 0GN",
    "wof:placetype":"postalcode"
},
  "geometry": {"coordinates":[-2.35053,53.484862],"type":"Point"}
}