{
  "type": "Feature",
  "properties": {
    "date:inception_lower": "1980-01-01",
    "date:inception_upper": "1980-01-01",
    "iso:country": "GB",
    "wof:name": "NG31 9SE",
    "wof:placetype": "postalcode"
  },
  "geometry": {"coordinates":[-0.604692,52.924512],"type":"Point"}
}
