{
  "type": "Feature",
  "properties": {
    "iso:country":"GB",
    "wof:name":"TR13 9QR",
    "wof:placetype":"postalcode"
},
  "geometry": {"coordinates":[-5.33802116019451,50.12264841920295],"type":"Point"}
}