{
  "type": "Feature",
  "properties": {
    "date:inception_lower":"1980-01-01",
    "date:inception_upper":"1980-01-31",
    "iso:country":"GB",
    "wof:name":"KY6 1AW",
    "wof:placetype":"postalcode"
},
  "geometry": {"coordinates":[-3.187785,56.195376],"type":"Point"}
}