{
  "type": "Feature",
  "properties": {
    "iso:country": "GB",
    "wof:name": "WA16 6RJ",
    "wof:placetype": "postalcode"
  },
  "geometry": {"coordinates":[-2.405461,53.34594],"type":"Point"}
}
