{
  "type": "Feature",
  "properties": {
    "iso:country": "GB",
    "wof:name": "CF23 6EG",
    "wof:placetype": "postalcode"
  },
  "geometry": {"coordinates":[-3.177197,51.518981],"type":"Point"}
}
