{
  "type": "Feature",
  "properties": {
    "date:inception_lower":"1999-06-01",
    "date:inception_upper":"1999-06-30",
    "iso:country":"GB",
    "wof:name":"CF23 6EG",
    "wof:placetype":"postalcode"
},
  "geometry": {"coordinates":[-3.177197,51.518981],"type":"Point"}
}