{
  "type": "Feature",
  "properties": {
    "date:inception_lower": "2020-04-01",
    "date:inception_upper": "2020-04-01",
    "iso:country": "GB",
    "wof:name": "HP6 6FZ",
    "wof:placetype": "postalcode"
  },
  "geometry": {"coordinates":[-0.594614,51.673334],"type":"Point"}
}
