{
  "type": "Feature",
  "properties": {
    "iso:country": "GB",
    "wof:name": "HP6 6FZ",
    "wof:placetype": "postalcode"
  },
  "geometry": {"coordinates":[-0.594718,51.673219],"type":"Point"}
}
