{
  "type": "Feature",
  "properties": {
    "iso:country":"GB",
    "wof:name":"DA5 3JE",
    "wof:placetype":"postalcode"
},
  "geometry": {"coordinates":[0.1212593996593,51.43724973586595],"type":"Point"}
}