{
  "type": "Feature",
  "properties": {
    "iso:country":"GB",
    "wof:name":"E17 6BW",
    "wof:placetype":"postalcode"
},
  "geometry": {"coordinates":[-0.03510450685907,51.59220255696503],"type":"Point"}
}