{
  "type": "Feature",
  "properties": {
    "iso:country":"GB",
    "wof:name":"CW7 3HZ",
    "wof:placetype":"postalcode"
},
  "geometry": {"coordinates":[-2.50560559272007,53.19991090648341],"type":"Point"}
}