{
  "type": "Feature",
  "properties": {
    "iso:country":"GB",
    "wof:name":"NG10 4BS",
    "wof:placetype":"postalcode"
},
  "geometry": {"coordinates":[-1.29082861459806,52.89992847789564],"type":"Point"}
}