{
  "type": "Feature",
  "properties": {
    "iso:country": "GB",
    "wof:name": "OX1 1BY",
    "wof:placetype": "postalcode"
  },
  "geometry": {"coordinates":[-1.263653,51.752312],"type":"Point"}
}
