{
  "type": "Feature",
  "properties": {
    "iso:country":"GB",
    "wof:name":"SR1 2LN",
    "wof:placetype":"postalcode"
},
  "geometry": {"coordinates":[-1.3722682242503,54.90484640667922],"type":"Point"}
}