{
  "type": "Feature",
  "properties": {
    "date:inception_lower": "2021-10-01",
    "date:inception_upper": "2021-10-01",
    "iso:country": "GB",
    "wof:name": "OX29 7BT",
    "wof:placetype": "postalcode"
  },
  "geometry": {"coordinates":[-1.526957,51.783028],"type":"Point"}
}
