{
  "type": "Feature",
  "properties": {
    "iso:country": "GB",
    "wof:name": "PO30 4PG",
    "wof:placetype": "postalcode"
  },
  "geometry": {"coordinates":[-1.376579,50.626368],"type":"Point"}
}
