{
  "type": "Feature",
  "properties": {
    "iso:country":"GB",
    "wof:name":"PO22 9HS",
    "wof:placetype":"postalcode"
},
  "geometry": {"coordinates":[-0.67803902697158,50.79804455949389],"type":"Point"}
}