{
  "type": "Feature",
  "properties": {
    "iso:country": "GB",
    "wof:name": "HP5 2TL",
    "wof:placetype": "postalcode"
  },
  "geometry": {"coordinates":[-0.65418,51.725379],"type":"Point"}
}
