{
  "type": "Feature",
  "properties": {
    "iso:country":"GB",
    "wof:name":"HP5 2TL",
    "wof:placetype":"postalcode"
},
  "geometry": {"coordinates":[-0.65418049249076,51.72537947061593],"type":"Point"}
}