{
  "type": "Feature",
  "properties": {
    "date:inception_lower": "1980-01-01",
    "date:inception_upper": "1980-01-01",
    "iso:country": "GB",
    "wof:name": "DN3 2QE",
    "wof:placetype": "postalcode"
  },
  "geometry": {"coordinates":[-1.078313,53.556002],"type":"Point"}
}
