{
  "type": "Feature",
  "properties": {
    "iso:country":"GB",
    "wof:name":"DN3 2QE",
    "wof:placetype":"postalcode"
},
  "geometry": {"coordinates":[-1.07830922674338,53.55598131835756],"type":"Point"}
}