{
  "type": "Feature",
  "properties": {
    "iso:country":"GB",
    "wof:name":"KA15 2JN",
    "wof:placetype":"postalcode"
},
  "geometry": {"coordinates":[-4.60288528129529,55.76973642677656],"type":"Point"}
}