{
  "type": "Feature",
  "properties": {
    "iso:country": "GB",
    "wof:name": "KA15 2JN",
    "wof:placetype": "postalcode"
  },
  "geometry": {"coordinates":[-4.602885,55.769736],"type":"Point"}
}
