{
  "type": "Feature",
  "properties": {
    "iso:country": "GB",
    "wof:name": "KY13 8FD",
    "wof:placetype": "postalcode"
  },
  "geometry": {"coordinates":[-3.429523,56.203824],"type":"Point"}
}
