{
  "type": "Feature",
  "properties": {
    "iso:country":"GB",
    "wof:name":"KY13 8FD",
    "wof:placetype":"postalcode"
},
  "geometry": {"coordinates":[-3.42952307653192,56.20382429759543],"type":"Point"}
}