{
  "type": "Feature",
  "properties": {
    "iso:country":"GB",
    "wof:name":"BS48 3EP",
    "wof:placetype":"postalcode"
},
  "geometry": {"coordinates":[-2.72143610758451,51.38534924758704],"type":"Point"}
}