{
  "type": "Feature",
  "properties": {
    "iso:country":"GB",
    "wof:name":"SA16 0DB",
    "wof:placetype":"postalcode"
},
  "geometry": {"coordinates":[-4.2493633116167,51.69117652210817],"type":"Point"}
}