{
  "type": "Feature",
  "properties": {
    "iso:country": "GB",
    "wof:name": "TW4 5PR",
    "wof:placetype": "postalcode"
  },
  "geometry": {"coordinates":[-0.382339,51.447844],"type":"Point"}
}
