{
  "type": "Feature",
  "properties": {
    "iso:country":"GB",
    "wof:name":"TW4 5PR",
    "wof:placetype":"postalcode"
},
  "geometry": {"coordinates":[-0.38233887437312,51.4478441976016],"type":"Point"}
}