{
  "type": "Feature",
  "properties": {
    "iso:country":"GB",
    "wof:name":"PO35 5SU",
    "wof:placetype":"postalcode"
},
  "geometry": {"coordinates":[-1.07813480155155,50.68686387774741],"type":"Point"}
}