{
  "type": "Feature",
  "properties": {
    "iso:country": "GB",
    "wof:name": "PO35 5SU",
    "wof:placetype": "postalcode"
  },
  "geometry": {"coordinates":[-1.078135,50.686864],"type":"Point"}
}
