{
  "type": "Feature",
  "properties": {
    "date:inception_lower": "1980-01-01",
    "date:inception_upper": "1980-01-01",
    "iso:country": "GB",
    "wof:name": "PO35 5SU",
    "wof:placetype": "postalcode"
  },
  "geometry": {"coordinates":[-1.078135,50.686864],"type":"Point"}
}
