{
  "type": "Feature",
  "properties": {
    "iso:country":"GB",
    "wof:name":"NN3 3DG",
    "wof:placetype":"postalcode"
},
  "geometry": {"coordinates":[-0.83830302463604,52.24945109890658],"type":"Point"}
}