{
  "type": "Feature",
  "properties": {
    "date:inception_lower":"1980-01-01",
    "date:inception_upper":"1980-01-31",
    "iso:country":"GB",
    "wof:name":"NN3 3DG",
    "wof:placetype":"postalcode"
},
  "geometry": {"coordinates":[-0.838303,52.249451],"type":"Point"}
}