{
  "type": "Feature",
  "properties": {
    "iso:country":"GB",
    "wof:name":"CV21 3LA",
    "wof:placetype":"postalcode"
},
  "geometry": {"coordinates":[-1.24894478261181,52.37892121265109],"type":"Point"}
}