{
  "type": "Feature",
  "properties": {
    "iso:country":"GB",
    "wof:name":"UB6 9RY",
    "wof:placetype":"postalcode"
},
  "geometry": {"coordinates":[-0.36496479466075,51.53090783997677],"type":"Point"}
}