{
  "type": "Feature",
  "properties": {
    "iso:country":"GB",
    "wof:name":"BD4 8EE",
    "wof:placetype":"postalcode"
},
  "geometry": {"coordinates":[-1.71743062571994,53.78882716083958],"type":"Point"}
}