{
  "type": "Feature",
  "properties": {
    "date:inception_lower": "1980-01-01",
    "date:inception_upper": "1980-01-01",
    "iso:country": "GB",
    "wof:name": "BD4 8EE",
    "wof:placetype": "postalcode"
  },
  "geometry": {"coordinates":[-1.717431,53.788827],"type":"Point"}
}
