{
  "type": "Feature",
  "properties": {
    "date:inception_lower": "1999-06-01",
    "date:inception_upper": "1999-06-01",
    "iso:country": "GB",
    "wof:name": "NP26 4AF",
    "wof:placetype": "postalcode"
  },
  "geometry": {"coordinates":[-2.763023,51.591112],"type":"Point"}
}
