{
  "type": "Feature",
  "properties": {
    "iso:country": "GB",
    "wof:name": "ME15 9PR",
    "wof:placetype": "postalcode"
  },
  "geometry": {"coordinates":[0.556503,51.237357],"type":"Point"}
}
