{
  "type": "Feature",
  "properties": {
    "iso:country":"GB",
    "wof:name":"SG1 1PX",
    "wof:placetype":"postalcode"
},
  "geometry": {"coordinates":[-0.18676795882429,51.90363115119704],"type":"Point"}
}