{
  "type": "Feature",
  "properties": {
    "iso:country":"GB",
    "wof:name":"WS7 0DG",
    "wof:placetype":"postalcode"
},
  "geometry": {"coordinates":[-1.9088487096362,52.67727165175989],"type":"Point"}
}