{
  "type": "Feature",
  "properties": {
    "date:inception_lower":"1983-07-01",
    "date:inception_upper":"1983-07-31",
    "iso:country":"GB",
    "wof:name":"SK13 8RP",
    "wof:placetype":"postalcode"
},
  "geometry": {"coordinates":[-1.931372,53.442374],"type":"Point"}
}