{
  "type": "Feature",
  "properties": {
    "iso:country": "GB",
    "wof:name": "SK13 8RP",
    "wof:placetype": "postalcode"
  },
  "geometry": {"coordinates":[-1.931372,53.442374],"type":"Point"}
}
