{
  "type": "Feature",
  "properties": {
    "date:inception_lower": "2000-06-01",
    "date:inception_upper": "2000-06-01",
    "iso:country": "GB",
    "wof:name": "CA7 2NR",
    "wof:placetype": "postalcode"
  },
  "geometry": {"coordinates":[-3.387302,54.760146],"type":"Point"}
}
