{
  "type": "Feature",
  "properties": {
    "iso:country": "GB",
    "wof:name": "CA7 2NR",
    "wof:placetype": "postalcode"
  },
  "geometry": {"coordinates":[-3.387179,54.760193],"type":"Point"}
}
