{
  "type": "Feature",
  "properties": {
    "iso:country":"GB",
    "wof:name":"CA7 2NR",
    "wof:placetype":"postalcode"
},
  "geometry": {"coordinates":[-3.38717828189585,54.76018599816858],"type":"Point"}
}