{
  "type": "Feature",
  "properties": {
    "iso:country":"GB",
    "wof:name":"IP19 9AT",
    "wof:placetype":"postalcode"
},
  "geometry": {"coordinates":[1.46583574023556,52.31902931047573],"type":"Point"}
}