{
  "type": "Feature",
  "properties": {
    "iso:country":"GB",
    "wof:name":"CA1 3SJ",
    "wof:placetype":"postalcode"
},
  "geometry": {"coordinates":[-2.89570011137518,54.88168526123729],"type":"Point"}
}