{
  "type": "Feature",
  "properties": {
    "iso:country":"GB",
    "wof:name":"NG16 1HH",
    "wof:placetype":"postalcode"
},
  "geometry": {"coordinates":[-1.24869552067675,53.00142116463734],"type":"Point"}
}