{
  "type": "Feature",
  "properties": {
    "iso:country":"GB",
    "wof:name":"TS1 2EJ",
    "wof:placetype":"postalcode"
},
  "geometry": {"coordinates":[-1.2300435215168,54.57261309284277],"type":"Point"}
}