{
  "type": "Feature",
  "properties": {
    "date:inception_lower":"1980-01-01",
    "date:inception_upper":"1980-01-31",
    "iso:country":"GB",
    "wof:name":"TS1 2EJ",
    "wof:placetype":"postalcode"
},
  "geometry": {"coordinates":[-1.230043,54.572613],"type":"Point"}
}