{
  "type": "Feature",
  "properties": {
    "iso:country":"GB",
    "wof:name":"PA3 3BT",
    "wof:placetype":"postalcode"
},
  "geometry": {"coordinates":[-4.46271532944448,55.84170839635492],"type":"Point"}
}