{
  "type": "Feature",
  "properties": {
    "iso:country": "GB",
    "wof:name": "PA3 3BT",
    "wof:placetype": "postalcode"
  },
  "geometry": {"coordinates":[-4.462715,55.841708],"type":"Point"}
}
