{
  "type": "Feature",
  "properties": {
    "iso:country":"GB",
    "wof:name":"S72 0AA",
    "wof:placetype":"postalcode"
},
  "geometry": {"coordinates":[-1.35243067156447,53.55475881233456],"type":"Point"}
}