{
  "type": "Feature",
  "properties": {
    "iso:country":"GB",
    "wof:name":"SY2 5RU",
    "wof:placetype":"postalcode"
},
  "geometry": {"coordinates":[-2.72930585948694,52.71645942338404],"type":"Point"}
}