{
  "type": "Feature",
  "properties": {
    "iso:country":"GB",
    "wof:name":"PO18 0PY",
    "wof:placetype":"postalcode"
},
  "geometry": {"coordinates":[-0.73964449230079,50.87214460666484],"type":"Point"}
}