{
  "type": "Feature",
  "properties": {
    "date:inception_lower":"1980-01-01",
    "date:inception_upper":"1980-01-31",
    "iso:country":"GB",
    "wof:name":"RG10 8HN",
    "wof:placetype":"postalcode"
},
  "geometry": {"coordinates":[-0.885768,51.493309],"type":"Point"}
}