{
  "type": "Feature",
  "properties": {
    "iso:country":"GB",
    "wof:name":"AB15 8TQ",
    "wof:placetype":"postalcode"
},
  "geometry": {"coordinates":[-2.22953912951953,57.15612542041473],"type":"Point"}
}