{
  "type": "Feature",
  "properties": {
    "iso:country":"GB",
    "wof:name":"DN18 5QE",
    "wof:placetype":"postalcode"
},
  "geometry": {"coordinates":[-0.44401126513675,53.68894248201192],"type":"Point"}
}