{
  "type": "Feature",
  "properties": {
    "iso:country": "GB",
    "wof:name": "DD2 3FX",
    "wof:placetype": "postalcode"
  },
  "geometry": {"coordinates":[-3.020122,56.490206],"type":"Point"}
}
