{
  "type": "Feature",
  "properties": {
    "date:inception_lower": "2004-01-01",
    "date:inception_upper": "2004-01-01",
    "iso:country": "GB",
    "wof:name": "DD2 3FX",
    "wof:placetype": "postalcode"
  },
  "geometry": {"coordinates":[-3.020122,56.490206],"type":"Point"}
}
