{
  "type": "Feature",
  "properties": {
    "iso:country":"GB",
    "wof:name":"DD2 3FX",
    "wof:placetype":"postalcode"
},
  "geometry": {"coordinates":[-3.02012195937134,56.49020634982529],"type":"Point"}
}