{
  "type": "Feature",
  "properties": {
    "iso:country": "GB",
    "wof:name": "NE65 9YW",
    "wof:placetype": "postalcode"
  },
  "geometry": {"coordinates":[-1.612962,55.308103],"type":"Point"}
}
