{
  "type": "Feature",
  "properties": {
    "iso:country":"GB",
    "wof:name":"GL8 8RP",
    "wof:placetype":"postalcode"
},
  "geometry": {"coordinates":[-2.12732991423833,51.61828597202311],"type":"Point"}
}