{
  "type": "Feature",
  "properties": {
    "iso:country": "GB",
    "wof:name": "TA5 2RU",
    "wof:placetype": "postalcode"
  },
  "geometry": {"coordinates":[-3.010552,51.109062],"type":"Point"}
}
