{
  "type": "Feature",
  "properties": {
    "iso:country":"GB",
    "wof:name":"EX15 3RQ",
    "wof:placetype":"postalcode"
},
  "geometry": {"coordinates":[-3.23262736378749,50.91105926360296],"type":"Point"}
}