{
  "type": "Feature",
  "properties": {
    "iso:country":"GB",
    "wof:name":"SL6 6BN",
    "wof:placetype":"postalcode"
},
  "geometry": {"coordinates":[-0.73404412495285,51.52551662146931],"type":"Point"}
}