{
  "type": "Feature",
  "properties": {
    "iso:country": "GB",
    "wof:name": "NG31 8PE",
    "wof:placetype": "postalcode"
  },
  "geometry": {"coordinates":[-0.661116,52.931872],"type":"Point"}
}
