{
  "type": "Feature",
  "properties": {
    "iso:country":"GB",
    "wof:name":"NG31 8PE",
    "wof:placetype":"postalcode"
},
  "geometry": {"coordinates":[-0.66111621610092,52.93187241479124],"type":"Point"}
}