{
  "type": "Feature",
  "properties": {
    "iso:country":"GB",
    "wof:name":"EX8 3QW",
    "wof:placetype":"postalcode"
},
  "geometry": {"coordinates":[-3.39609221473279,50.62809332548268],"type":"Point"}
}