{
  "type": "Feature",
  "properties": {
    "date:inception_lower":"1980-01-01",
    "date:inception_upper":"1980-01-31",
    "iso:country":"GB",
    "wof:name":"SP1 1JF",
    "wof:placetype":"postalcode"
},
  "geometry": {"coordinates":[-1.790988,51.070259],"type":"Point"}
}