{
  "type": "Feature",
  "properties": {
    "iso:country":"GB",
    "wof:name":"SP1 1JF",
    "wof:placetype":"postalcode"
},
  "geometry": {"coordinates":[-1.79098808110976,51.07025943246847],"type":"Point"}
}