{
  "type": "Feature",
  "properties": {
    "iso:country": "GB",
    "wof:name": "OX14 3DB",
    "wof:placetype": "postalcode"
  },
  "geometry": {"coordinates":[-1.228684,51.65776],"type":"Point"}
}
