{
  "type": "Feature",
  "properties": {
    "date:inception_lower": "1980-01-01",
    "date:inception_upper": "1980-01-01",
    "iso:country": "GB",
    "wof:name": "OX14 3DB",
    "wof:placetype": "postalcode"
  },
  "geometry": {"coordinates":[-1.228684,51.65776],"type":"Point"}
}
