{
  "type": "Feature",
  "properties": {
    "iso:country":"GB",
    "wof:name":"OX14 3DB",
    "wof:placetype":"postalcode"
},
  "geometry": {"coordinates":[-1.22868399420403,51.65775956404489],"type":"Point"}
}