{
  "type": "Feature",
  "properties": {
    "iso:country":"GB",
    "wof:name":"LE11 1SN",
    "wof:placetype":"postalcode"
},
  "geometry": {"coordinates":[-1.19793539456406,52.77058800403807],"type":"Point"}
}