{
  "type": "Feature",
  "properties": {
    "date:inception_lower": "1980-01-01",
    "date:inception_upper": "1980-01-01",
    "iso:country": "GB",
    "wof:name": "SN13 0JS",
    "wof:placetype": "postalcode"
  },
  "geometry": {"coordinates":[-2.22488,51.425048],"type":"Point"}
}
