{
  "type": "Feature",
  "properties": {
    "iso:country":"GB",
    "wof:name":"SN13 0JS",
    "wof:placetype":"postalcode"
},
  "geometry": {"coordinates":[-2.22488031378746,51.42504813530535],"type":"Point"}
}