{
  "type": "Feature",
  "properties": {
    "iso:country": "GB",
    "wof:name": "SN13 0JS",
    "wof:placetype": "postalcode"
  },
  "geometry": {"coordinates":[-2.22488,51.425048],"type":"Point"}
}
