{
  "type": "Feature",
  "properties": {
    "iso:country":"GB",
    "wof:name":"YO32 9TY",
    "wof:placetype":"postalcode"
},
  "geometry": {"coordinates":[-1.00389305120766,53.99228401311377],"type":"Point"}
}