{
  "type": "Feature",
  "properties": {
    "iso:country": "GB",
    "wof:name": "YO32 9TY",
    "wof:placetype": "postalcode"
  },
  "geometry": {"coordinates":[-1.003886,53.99232],"type":"Point"}
}
