{
  "type": "Feature",
  "properties": {
    "iso:country":"GB",
    "wof:name":"N2 9NN",
    "wof:placetype":"postalcode"
},
  "geometry": {"coordinates":[-0.15201252323468,51.59158373809888],"type":"Point"}
}