{
  "type": "Feature",
  "properties": {
    "iso:country": "GB",
    "wof:name": "N2 9NN",
    "wof:placetype": "postalcode"
  },
  "geometry": {"coordinates":[-0.152012,51.591584],"type":"Point"}
}
