{
  "type": "Feature",
  "properties": {
    "date:inception_lower": "1980-01-01",
    "date:inception_upper": "1980-01-01",
    "iso:country": "GB",
    "wof:name": "WA11 8QU",
    "wof:placetype": "postalcode"
  },
  "geometry": {"coordinates":[-2.755374,53.493612],"type":"Point"}
}
