{
  "type": "Feature",
  "properties": {
    "iso:country": "GB",
    "wof:name": "WA11 8QU",
    "wof:placetype": "postalcode"
  },
  "geometry": {"coordinates":[-2.755374,53.493612],"type":"Point"}
}
