{
  "type": "Feature",
  "properties": {
    "iso:country":"GB",
    "wof:name":"TN23 1LZ",
    "wof:placetype":"postalcode"
},
  "geometry": {"coordinates":[0.86306455684401,51.15122206862206],"type":"Point"}
}