{
  "type": "Feature",
  "properties": {
    "iso:country": "GB",
    "wof:name": "DE13 9UD",
    "wof:placetype": "postalcode"
  },
  "geometry": {"coordinates":[-1.688623,52.822395],"type":"Point"}
}
