{
  "type": "Feature",
  "properties": {
    "iso:country":"GB",
    "wof:name":"DE13 9UD",
    "wof:placetype":"postalcode"
},
  "geometry": {"coordinates":[-1.68862348874191,52.82239459984949],"type":"Point"}
}