{
  "type": "Feature",
  "properties": {
    "iso:country":"GB",
    "wof:name":"NR1 4NS",
    "wof:placetype":"postalcode"
},
  "geometry": {"coordinates":[1.32223485456682,52.63981500430781],"type":"Point"}
}