{
  "type": "Feature",
  "properties": {
    "date:inception_lower":"1980-01-01",
    "date:inception_upper":"1980-01-31",
    "iso:country":"GB",
    "wof:name":"NR1 4NS",
    "wof:placetype":"postalcode"
},
  "geometry": {"coordinates":[1.322235,52.639815],"type":"Point"}
}