{
  "type": "Feature",
  "properties": {
    "iso:country":"GB",
    "wof:name":"B27 6AA",
    "wof:placetype":"postalcode"
},
  "geometry": {"coordinates":[-1.82378648114095,52.44941827888705],"type":"Point"}
}