{
  "type": "Feature",
  "properties": {
    "date:inception_lower": "1980-01-01",
    "date:inception_upper": "1980-01-01",
    "iso:country": "GB",
    "wof:name": "PR6 0PZ",
    "wof:placetype": "postalcode"
  },
  "geometry": {"coordinates":[-2.618083,53.650666],"type":"Point"}
}
