{
  "type": "Feature",
  "properties": {
    "iso:country":"GB",
    "wof:name":"CT18 8NB",
    "wof:placetype":"postalcode"
},
  "geometry": {"coordinates":[1.09550630781538,51.1119261893241],"type":"Point"}
}