{
  "type": "Feature",
  "properties": {
    "date:inception_lower": "1998-06-01",
    "date:inception_upper": "1998-06-01",
    "iso:country": "GB",
    "wof:name": "CT18 8NB",
    "wof:placetype": "postalcode"
  },
  "geometry": {"coordinates":[1.095506,51.111926],"type":"Point"}
}
