{
  "type": "Feature",
  "properties": {
    "iso:country": "GB",
    "wof:name": "CT18 8NB",
    "wof:placetype": "postalcode"
  },
  "geometry": {"coordinates":[1.095506,51.111926],"type":"Point"}
}
