{
  "type": "Feature",
  "properties": {
    "iso:country":"GB",
    "wof:name":"WD23 4HW",
    "wof:placetype":"postalcode"
},
  "geometry": {"coordinates":[-0.35343487488518,51.64220456633796],"type":"Point"}
}