{
  "type": "Feature",
  "properties": {
    "iso:country":"GB",
    "wof:name":"BS16 7FE",
    "wof:placetype":"postalcode"
},
  "geometry": {"coordinates":[-2.48136746279276,51.50314017659254],"type":"Point"}
}