{
  "type": "Feature",
  "properties": {
    "date:inception_lower": "2005-02-01",
    "date:inception_upper": "2005-02-01",
    "iso:country": "GB",
    "wof:name": "BS16 7FE",
    "wof:placetype": "postalcode"
  },
  "geometry": {"coordinates":[-2.481367,51.503094],"type":"Point"}
}
