{
  "type": "Feature",
  "properties": {
    "iso:country": "GB",
    "wof:name": "BS16 7FE",
    "wof:placetype": "postalcode"
  },
  "geometry": {"coordinates":[-2.481367,51.50314],"type":"Point"}
}
