{
  "type": "Feature",
  "properties": {
    "iso:country": "GB",
    "wof:name": "SS17 8PL",
    "wof:placetype": "postalcode"
  },
  "geometry": {"coordinates":[0.406727,51.522981],"type":"Point"}
}
