{
  "type": "Feature",
  "properties": {
    "iso:country":"GB",
    "wof:name":"LN2 1QR",
    "wof:placetype":"postalcode"
},
  "geometry": {"coordinates":[-0.53430106599237,53.23802670748911],"type":"Point"}
}