{
  "type": "Feature",
  "properties": {
    "iso:country":"GB",
    "wof:name":"CR3 5DE",
    "wof:placetype":"postalcode"
},
  "geometry": {"coordinates":[-0.1045148016407,51.28017495817378],"type":"Point"}
}