{
  "type": "Feature",
  "properties": {
    "iso:country":"GB",
    "wof:name":"LS16 8JE",
    "wof:placetype":"postalcode"
},
  "geometry": {"coordinates":[-1.57835534981781,53.85334838512205],"type":"Point"}
}