{
  "type": "Feature",
  "properties": {
    "iso:country":"GB",
    "wof:name":"BD10 8QX",
    "wof:placetype":"postalcode"
},
  "geometry": {"coordinates":[-1.73964895783045,53.83102197409458],"type":"Point"}
}