{
  "type": "Feature",
  "properties": {
    "iso:country":"GB",
    "wof:name":"ML12 9AH",
    "wof:placetype":"postalcode"
},
  "geometry": {"coordinates":[-3.52371604201725,55.62393006126972],"type":"Point"}
}