{
  "type": "Feature",
  "properties": {
    "iso:country": "GB",
    "wof:name": "ML12 9AH",
    "wof:placetype": "postalcode"
  },
  "geometry": {"coordinates":[-3.523712,55.62393],"type":"Point"}
}
