{
  "type": "Feature",
  "properties": {
    "iso:country": "GB",
    "wof:name": "DT2 7QY",
    "wof:placetype": "postalcode"
  },
  "geometry": {"coordinates":[-2.423943,50.804895],"type":"Point"}
}
