{
  "type": "Feature",
  "properties": {
    "iso:country":"GB",
    "wof:name":"DT2 7QY",
    "wof:placetype":"postalcode"
},
  "geometry": {"coordinates":[-2.42394352029308,50.80489536017246],"type":"Point"}
}