{
  "type": "Feature",
  "properties": {
    "iso:country":"GB",
    "wof:name":"BL1 1PU",
    "wof:placetype":"postalcode"
},
  "geometry": {"coordinates":[-2.42517022330333,53.57815279246218],"type":"Point"}
}