{
  "type": "Feature",
  "properties": {
    "iso:country":"GB",
    "wof:name":"IP4 3HX",
    "wof:placetype":"postalcode"
},
  "geometry": {"coordinates":[1.19298721216071,52.0685578672262],"type":"Point"}
}