{
  "type": "Feature",
  "properties": {
    "iso:country":"GB",
    "wof:name":"LU7 2QA",
    "wof:placetype":"postalcode"
},
  "geometry": {"coordinates":[-0.68666068595712,51.91584573209458],"type":"Point"}
}