{
  "type": "Feature",
  "properties": {
    "date:inception_lower": "2001-06-01",
    "date:inception_upper": "2001-06-01",
    "iso:country": "GB",
    "wof:name": "LU7 2QA",
    "wof:placetype": "postalcode"
  },
  "geometry": {"coordinates":[-0.686661,51.915846],"type":"Point"}
}
