{
  "type": "Feature",
  "properties": {
    "iso:country":"GB",
    "wof:name":"CO16 8BQ",
    "wof:placetype":"postalcode"
},
  "geometry": {"coordinates":[1.12123463897951,51.79499554502036],"type":"Point"}
}