{
  "type": "Feature",
  "properties": {
    "iso:country": "GB",
    "wof:name": "CO16 8BQ",
    "wof:placetype": "postalcode"
  },
  "geometry": {"coordinates":[1.121235,51.794996],"type":"Point"}
}
