{
  "type": "Feature",
  "properties": {
    "date:inception_lower": "2005-11-01",
    "date:inception_upper": "2005-11-01",
    "iso:country": "GB",
    "wof:name": "CO16 8BQ",
    "wof:placetype": "postalcode"
  },
  "geometry": {"coordinates":[1.121235,51.794996],"type":"Point"}
}
