{
  "type": "Feature",
  "properties": {
    "iso:country": "GB",
    "wof:name": "EX14 9HQ",
    "wof:placetype": "postalcode"
  },
  "geometry": {"coordinates":[-3.133632,50.813672],"type":"Point"}
}
