{
  "type": "Feature",
  "properties": {
    "date:inception_lower": "1980-01-01",
    "date:inception_upper": "1980-01-01",
    "iso:country": "GB",
    "wof:name": "EX14 9HQ",
    "wof:placetype": "postalcode"
  },
  "geometry": {"coordinates":[-3.135563,50.811342],"type":"Point"}
}
