{
  "type": "Feature",
  "properties": {
    "iso:country":"GB",
    "wof:name":"BN41 1DJ",
    "wof:placetype":"postalcode"
},
  "geometry": {"coordinates":[-0.20922044827032,50.83030847096038],"type":"Point"}
}