{
  "type": "Feature",
  "properties": {
    "date:inception_lower": "1980-01-01",
    "date:inception_upper": "1980-01-01",
    "iso:country": "GB",
    "wof:name": "WC1E 7DH",
    "wof:placetype": "postalcode"
  },
  "geometry": {"coordinates":[-0.131938,51.519938],"type":"Point"}
}
