{
  "type": "Feature",
  "properties": {
    "date:inception_lower":"1980-01-01",
    "date:inception_upper":"1980-01-31",
    "iso:country":"GB",
    "wof:name":"DL8 3ET",
    "wof:placetype":"postalcode"
},
  "geometry": {"coordinates":[-2.069507,54.306285],"type":"Point"}
}