{
  "type": "Feature",
  "properties": {
    "iso:country":"GB",
    "wof:name":"DL8 3ET",
    "wof:placetype":"postalcode"
},
  "geometry": {"coordinates":[-2.06950699556609,54.3062845638554],"type":"Point"}
}