{
  "type": "Feature",
  "properties": {
    "iso:country": "GB",
    "wof:name": "DL8 3ET",
    "wof:placetype": "postalcode"
  },
  "geometry": {"coordinates":[-2.069507,54.306285],"type":"Point"}
}
