{
  "type": "Feature",
  "properties": {
    "date:inception_lower": "1980-01-01",
    "date:inception_upper": "1980-01-01",
    "iso:country": "GB",
    "wof:name": "GL2 8DQ",
    "wof:placetype": "postalcode"
  },
  "geometry": {"coordinates":[-2.302205,51.879535],"type":"Point"}
}
