{
  "type": "Feature",
  "properties": {
    "iso:country":"GB",
    "wof:name":"SO16 9FN",
    "wof:placetype":"postalcode"
},
  "geometry": {"coordinates":[-1.45531487232746,50.9314876861491],"type":"Point"}
}