{
  "type": "Feature",
  "properties": {
    "iso:country":"GB",
    "wof:name":"DG14 0YE",
    "wof:placetype":"postalcode"
},
  "geometry": {"coordinates":[-3.11355564193387,55.04120500931523],"type":"Point"}
}