{
  "type": "Feature",
  "properties": {
    "iso:country":"GB",
    "wof:name":"SS4 1RP",
    "wof:placetype":"postalcode"
},
  "geometry": {"coordinates":[0.69870855768547,51.58976008721991],"type":"Point"}
}