{
  "type": "Feature",
  "properties": {
    "iso:country": "GB",
    "wof:name": "SS4 1RP",
    "wof:placetype": "postalcode"
  },
  "geometry": {"coordinates":[0.698709,51.58976],"type":"Point"}
}
