{
  "type": "Feature",
  "properties": {
    "iso:country": "GB",
    "wof:name": "DE13 7DT",
    "wof:placetype": "postalcode"
  },
  "geometry": {"coordinates":[-1.752521,52.733674],"type":"Point"}
}
