{
  "type": "Feature",
  "properties": {
    "iso:country":"GB",
    "wof:name":"BN10 8AX",
    "wof:placetype":"postalcode"
},
  "geometry": {"coordinates":[0.00406295533226,50.80222411916251],"type":"Point"}
}