{
  "type": "Feature",
  "properties": {
    "iso:country":"GB",
    "wof:name":"G21 2LA",
    "wof:placetype":"postalcode"
},
  "geometry": {"coordinates":[-4.22820939176568,55.86899098870859],"type":"Point"}
}