{
  "type": "Feature",
  "properties": {
    "iso:country": "GB",
    "wof:name": "G21 2LA",
    "wof:placetype": "postalcode"
  },
  "geometry": {"coordinates":[-4.228209,55.868991],"type":"Point"}
}
