{
  "type": "Feature",
  "properties": {
    "iso:country":"GB",
    "wof:name":"PE28 4EB",
    "wof:placetype":"postalcode"
},
  "geometry": {"coordinates":[-0.25694283249357,52.36948039886671],"type":"Point"}
}