{
  "type": "Feature",
  "properties": {
    "iso:country": "GB",
    "wof:name": "WD7 9EF",
    "wof:placetype": "postalcode"
  },
  "geometry": {"coordinates":[-0.277572,51.69105],"type":"Point"}
}
