{
  "type": "Feature",
  "properties": {
    "iso:country":"GB",
    "wof:name":"WD7 9EF",
    "wof:placetype":"postalcode"
},
  "geometry": {"coordinates":[-0.27757157644004,51.69104961710052],"type":"Point"}
}