{
  "type": "Feature",
  "properties": {
    "iso:country":"GB",
    "wof:name":"NG12 5EL",
    "wof:placetype":"postalcode"
},
  "geometry": {"coordinates":[-1.07981666204059,52.87524356721168],"type":"Point"}
}