{
  "type": "Feature",
  "properties": {
    "iso:country": "GB",
    "wof:name": "NG12 5EL",
    "wof:placetype": "postalcode"
  },
  "geometry": {"coordinates":[-1.079817,52.875244],"type":"Point"}
}
