{
  "type": "Feature",
  "properties": {
    "iso:country":"GB",
    "wof:name":"SG18 9BP",
    "wof:placetype":"postalcode"
},
  "geometry": {"coordinates":[-0.29266254809005,52.09708803908307],"type":"Point"}
}