{
  "type": "Feature",
  "properties": {
    "iso:country": "GB",
    "wof:name": "SG18 9BP",
    "wof:placetype": "postalcode"
  },
  "geometry": {"coordinates":[-0.292639,52.097099],"type":"Point"}
}
