{
  "type": "Feature",
  "properties": {
    "date:inception_lower":"2016-02-01",
    "date:inception_upper":"2016-02-29",
    "iso:country":"GB",
    "wof:name":"GL54 5FJ",
    "wof:placetype":"postalcode"
},
  "geometry": {"coordinates":[-1.968596,51.961952],"type":"Point"}
}