{
  "type": "Feature",
  "properties": {
    "iso:country":"GB",
    "wof:name":"GL54 5FJ",
    "wof:placetype":"postalcode"
},
  "geometry": {"coordinates":[-1.96880851012711,51.9620957820017],"type":"Point"}
}