{
  "type": "Feature",
  "properties": {
    "date:inception_lower": "1980-01-01",
    "date:inception_upper": "1980-01-01",
    "iso:country": "GB",
    "wof:name": "SA34 0EY",
    "wof:placetype": "postalcode"
  },
  "geometry": {"coordinates":[-4.60061,51.891367],"type":"Point"}
}
