{
  "type": "Feature",
  "properties": {
    "iso:country":"GB",
    "wof:name":"SA34 0EY",
    "wof:placetype":"postalcode"
},
  "geometry": {"coordinates":[-4.60061004024541,51.89136714367068],"type":"Point"}
}