{
  "type": "Feature",
  "properties": {
    "iso:country": "GB",
    "wof:name": "LU6 1TU",
    "wof:placetype": "postalcode"
  },
  "geometry": {"coordinates":[-0.545175,51.89013],"type":"Point"}
}
