{
  "type": "Feature",
  "properties": {
    "iso:country":"GB",
    "wof:name":"LU6 1TU",
    "wof:placetype":"postalcode"
},
  "geometry": {"coordinates":[-0.54517548316322,51.89012975986542],"type":"Point"}
}