{
  "type": "Feature",
  "properties": {
    "iso:country":"GB",
    "wof:name":"GU30 7RG",
    "wof:placetype":"postalcode"
},
  "geometry": {"coordinates":[-0.81360143713436,51.09647714107472],"type":"Point"}
}