{
  "type": "Feature",
  "properties": {
    "iso:country": "GB",
    "wof:name": "GU30 7RG",
    "wof:placetype": "postalcode"
  },
  "geometry": {"coordinates":[-0.813601,51.096477],"type":"Point"}
}
