{
  "type": "Feature",
  "properties": {
    "date:inception_lower": "1980-01-01",
    "date:inception_upper": "1980-01-01",
    "iso:country": "GB",
    "wof:name": "CM1 3PN",
    "wof:placetype": "postalcode"
  },
  "geometry": {"coordinates":[0.417059,51.709915],"type":"Point"}
}
