{
  "type": "Feature",
  "properties": {
    "iso:country": "GB",
    "wof:name": "B94 5JZ",
    "wof:placetype": "postalcode"
  },
  "geometry": {"coordinates":[-1.869995,52.361771],"type":"Point"}
}
