{
  "type": "Feature",
  "properties": {
    "iso:country":"GB",
    "wof:name":"B94 5JZ",
    "wof:placetype":"postalcode"
},
  "geometry": {"coordinates":[-1.86999540704461,52.36177079409066],"type":"Point"}
}