{
  "type": "Feature",
  "properties": {
    "iso:country": "GB",
    "wof:name": "CM11 1NF",
    "wof:placetype": "postalcode"
  },
  "geometry": {"coordinates":[0.471089,51.6343],"type":"Point"}
}
