{
  "type": "Feature",
  "properties": {
    "iso:country":"GB",
    "wof:name":"DN6 9BT",
    "wof:placetype":"postalcode"
},
  "geometry": {"coordinates":[-1.18602758244451,53.65128588276872],"type":"Point"}
}