{
  "type": "Feature",
  "properties": {
    "iso:country": "GB",
    "wof:name": "DN6 9BT",
    "wof:placetype": "postalcode"
  },
  "geometry": {"coordinates":[-1.186028,53.651286],"type":"Point"}
}
