{
  "type": "Feature",
  "properties": {
    "iso:country":"GB",
    "wof:name":"BB1 1SS",
    "wof:placetype":"postalcode"
},
  "geometry": {"coordinates":[-2.46491751035795,53.74408973281331],"type":"Point"}
}