{
  "type": "Feature",
  "properties": {
    "date:inception_lower": "1985-04-01",
    "date:inception_upper": "1985-04-01",
    "iso:country": "GB",
    "wof:name": "SK10 5RJ",
    "wof:placetype": "postalcode"
  },
  "geometry": {"coordinates":[-2.092448,53.299672],"type":"Point"}
}
