{
  "type": "Feature",
  "properties": {
    "date:inception_lower": "2009-07-01",
    "date:inception_upper": "2009-07-01",
    "iso:country": "GB",
    "wof:name": "NN14 1UD",
    "wof:placetype": "postalcode"
  },
  "geometry": {"coordinates":[-0.727902,52.423756],"type":"Point"}
}
