{
  "type": "Feature",
  "properties": {
    "iso:country": "GB",
    "wof:name": "NN14 1UD",
    "wof:placetype": "postalcode"
  },
  "geometry": {"coordinates":[-0.72798,52.424101],"type":"Point"}
}
