{
  "type": "Feature",
  "properties": {
    "iso:country":"GB",
    "wof:name":"SA15 2AZ",
    "wof:placetype":"postalcode"
},
  "geometry": {"coordinates":[-4.16057512809432,51.66464291439374],"type":"Point"}
}