{
  "type": "Feature",
  "properties": {
    "date:inception_lower": "2011-05-01",
    "date:inception_upper": "2011-05-01",
    "iso:country": "GB",
    "wof:name": "SA15 2AZ",
    "wof:placetype": "postalcode"
  },
  "geometry": {"coordinates":[-4.160575,51.664643],"type":"Point"}
}
