{
  "type": "Feature",
  "properties": {
    "date:inception_lower": "2014-03-01",
    "date:inception_upper": "2014-03-01",
    "iso:country": "GB",
    "wof:name": "NG20 8AE",
    "wof:placetype": "postalcode"
  },
  "geometry": {"coordinates":[-1.210583,53.201842],"type":"Point"}
}
