{
  "type": "Feature",
  "properties": {
    "iso:country":"GB",
    "wof:name":"NG20 8AE",
    "wof:placetype":"postalcode"
},
  "geometry": {"coordinates":[-1.2108517137873,53.20195095646593],"type":"Point"}
}