{
  "type": "Feature",
  "properties": {
    "iso:country": "GB",
    "wof:name": "SG17 5ZS",
    "wof:placetype": "postalcode"
  },
  "geometry": {"coordinates":[-0.344651,52.034063],"type":"Point"}
}
