{
  "type": "Feature",
  "properties": {
    "date:inception_lower": "1980-01-01",
    "date:inception_upper": "1980-01-01",
    "iso:country": "GB",
    "wof:name": "CT14 0BH",
    "wof:placetype": "postalcode"
  },
  "geometry": {"coordinates":[1.336236,51.259108],"type":"Point"}
}
