{
  "type": "Feature",
  "properties": {
    "iso:country": "GB",
    "wof:name": "CT14 0BH",
    "wof:placetype": "postalcode"
  },
  "geometry": {"coordinates":[1.33619,51.259073],"type":"Point"}
}
