{
  "type": "Feature",
  "properties": {
    "iso:country": "GB",
    "wof:name": "G33 4ST",
    "wof:placetype": "postalcode"
  },
  "geometry": {"coordinates":[-4.133019,55.857197],"type":"Point"}
}
