{
  "type": "Feature",
  "properties": {
    "iso:country":"GB",
    "wof:name":"G33 4ST",
    "wof:placetype":"postalcode"
},
  "geometry": {"coordinates":[-4.13367280122045,55.85688048731698],"type":"Point"}
}