{
  "type": "Feature",
  "properties": {
    "iso:country":"GB",
    "wof:name":"CM6 1DA",
    "wof:placetype":"postalcode"
},
  "geometry": {"coordinates":[0.3608579241075,51.87302714988787],"type":"Point"}
}