{
  "type": "Feature",
  "properties": {
    "date:inception_lower": "1980-01-01",
    "date:inception_upper": "1980-01-01",
    "iso:country": "GB",
    "wof:name": "IP30 0QP",
    "wof:placetype": "postalcode"
  },
  "geometry": {"coordinates":[0.826804,52.172487],"type":"Point"}
}
