{
  "type": "Feature",
  "properties": {
    "iso:country":"GB",
    "wof:name":"IP30 0QP",
    "wof:placetype":"postalcode"
},
  "geometry": {"coordinates":[0.82819423368001,52.17229316761163],"type":"Point"}
}