{
  "type": "Feature",
  "properties": {
    "date:inception_lower":"1980-01-01",
    "date:inception_upper":"1980-01-31",
    "iso:country":"GB",
    "wof:name":"W14 9XA",
    "wof:placetype":"postalcode"
},
  "geometry": {"coordinates":[-0.207339,51.487249],"type":"Point"}
}