{
  "type": "Feature",
  "properties": {
    "iso:country":"GB",
    "wof:name":"W14 9XA",
    "wof:placetype":"postalcode"
},
  "geometry": {"coordinates":[-0.20733860874786,51.48724880102407],"type":"Point"}
}