{
  "type": "Feature",
  "properties": {
    "iso:country": "GB",
    "wof:name": "W14 9XA",
    "wof:placetype": "postalcode"
  },
  "geometry": {"coordinates":[-0.207339,51.487249],"type":"Point"}
}
