{
  "type": "Feature",
  "properties": {
    "date:inception_lower": "1984-10-01",
    "date:inception_upper": "1984-10-01",
    "iso:country": "GB",
    "wof:name": "RH16 3TP",
    "wof:placetype": "postalcode"
  },
  "geometry": {"coordinates":[-0.104864,51.002178],"type":"Point"}
}
