{
  "type": "Feature",
  "properties": {
    "iso:country": "GB",
    "wof:name": "EX10 0PQ",
    "wof:placetype": "postalcode"
  },
  "geometry": {"coordinates":[-3.179651,50.694632],"type":"Point"}
}
