{
  "type": "Feature",
  "properties": {
    "iso:country":"GB",
    "wof:name":"EX10 0PQ",
    "wof:placetype":"postalcode"
},
  "geometry": {"coordinates":[-3.17954162258131,50.69465351400235],"type":"Point"}
}