{
  "type": "Feature",
  "properties": {
    "iso:country":"GB",
    "wof:name":"PA1 2BB",
    "wof:placetype":"postalcode"
},
  "geometry": {"coordinates":[-4.42986185190463,55.84510327710847],"type":"Point"}
}