{
  "type": "Feature",
  "properties": {
    "iso:country":"GB",
    "wof:name":"IP3 9PH",
    "wof:placetype":"postalcode"
},
  "geometry": {"coordinates":[1.18361062838483,52.03482343409247],"type":"Point"}
}