{
  "type": "Feature",
  "properties": {
    "iso:country":"GB",
    "wof:name":"NE25 9AL",
    "wof:placetype":"postalcode"
},
  "geometry": {"coordinates":[-1.46930621349828,55.04455176977734],"type":"Point"}
}