{
  "type": "Feature",
  "properties": {
    "iso:country": "GB",
    "wof:name": "NE25 9AL",
    "wof:placetype": "postalcode"
  },
  "geometry": {"coordinates":[-1.469306,55.044552],"type":"Point"}
}
