{
  "type": "Feature",
  "properties": {
    "date:inception_lower":"1980-01-01",
    "date:inception_upper":"1980-01-31",
    "iso:country":"GB",
    "wof:name":"NE25 9AL",
    "wof:placetype":"postalcode"
},
  "geometry": {"coordinates":[-1.469306,55.044552],"type":"Point"}
}