{
  "type": "Feature",
  "properties": {
    "iso:country":"GB",
    "wof:name":"GU17 0JA",
    "wof:placetype":"postalcode"
},
  "geometry": {"coordinates":[-0.77900065880522,51.33189120527273],"type":"Point"}
}