{
  "type": "Feature",
  "properties": {
    "date:inception_lower": "1980-01-01",
    "date:inception_upper": "1980-01-01",
    "iso:country": "GB",
    "wof:name": "GU17 0JA",
    "wof:placetype": "postalcode"
  },
  "geometry": {"coordinates":[-0.779001,51.331891],"type":"Point"}
}
