{
  "type": "Feature",
  "properties": {
    "iso:country":"GB",
    "wof:name":"ST5 2NP",
    "wof:placetype":"postalcode"
},
  "geometry": {"coordinates":[-2.24107827910896,53.01090103617117],"type":"Point"}
}