{
  "type": "Feature",
  "properties": {
    "iso:country":"GB",
    "wof:name":"RH6 8RR",
    "wof:placetype":"postalcode"
},
  "geometry": {"coordinates":[-0.18103701851268,51.17712576067388],"type":"Point"}
}