{
  "type": "Feature",
  "properties": {
    "iso:country": "GB",
    "wof:name": "RH6 8RR",
    "wof:placetype": "postalcode"
  },
  "geometry": {"coordinates":[-0.181037,51.177126],"type":"Point"}
}
