{
  "type": "Feature",
  "properties": {
    "iso:country": "GB",
    "wof:name": "PR6 7YH",
    "wof:placetype": "postalcode"
  },
  "geometry": {"coordinates":[-2.630733,53.67634],"type":"Point"}
}
