{
  "type": "Feature",
  "properties": {
    "iso:country":"GB",
    "wof:name":"SL1 4EQ",
    "wof:placetype":"postalcode"
},
  "geometry": {"coordinates":[-0.62868070959537,51.51988139913139],"type":"Point"}
}