{
  "type": "Feature",
  "properties": {
    "date:inception_lower":"1991-03-01",
    "date:inception_upper":"1991-03-31",
    "iso:country":"GB",
    "wof:name":"G74 4SX",
    "wof:placetype":"postalcode"
},
  "geometry": {"coordinates":[-4.18585,55.772998],"type":"Point"}
}