{
  "type": "Feature",
  "properties": {
    "date:inception_lower": "1991-03-01",
    "date:inception_upper": "1991-03-01",
    "iso:country": "GB",
    "wof:name": "G74 4SX",
    "wof:placetype": "postalcode"
  },
  "geometry": {"coordinates":[-4.186083,55.773452],"type":"Point"}
}
