{
  "type": "Feature",
  "properties": {
    "iso:country": "GB",
    "wof:name": "E5 9FU",
    "wof:placetype": "postalcode"
  },
  "geometry": {"coordinates":[-0.064877,51.572095],"type":"Point"}
}
