{
  "type": "Feature",
  "properties": {
    "date:inception_lower":"2015-01-01",
    "date:inception_upper":"2015-01-31",
    "iso:country":"GB",
    "wof:name":"E5 9FU",
    "wof:placetype":"postalcode"
},
  "geometry": {"coordinates":[-0.064877,51.572095],"type":"Point"}
}