{
  "type": "Feature",
  "properties": {
    "iso:country": "GB",
    "wof:name": "AB51 5HH",
    "wof:placetype": "postalcode"
  },
  "geometry": {"coordinates":[-2.46694,57.308689],"type":"Point"}
}
