{
  "type": "Feature",
  "properties": {
    "date:inception_lower": "1980-01-01",
    "date:inception_upper": "1980-01-01",
    "iso:country": "GB",
    "wof:name": "GL54 3AA",
    "wof:placetype": "postalcode"
  },
  "geometry": {"coordinates":[-1.830322,51.909876],"type":"Point"}
}
