{
  "type": "Feature",
  "properties": {
    "iso:country":"GB",
    "wof:name":"SN7 8JP",
    "wof:placetype":"postalcode"
},
  "geometry": {"coordinates":[-1.54740715944801,51.6877599599984],"type":"Point"}
}