{
  "type": "Feature",
  "properties": {
    "iso:country": "GB",
    "wof:name": "DE13 7HN",
    "wof:placetype": "postalcode"
  },
  "geometry": {"coordinates":[-1.812686,52.745462],"type":"Point"}
}
