{
  "type": "Feature",
  "properties": {
    "iso:country":"GB",
    "wof:name":"CM13 3LB",
    "wof:placetype":"postalcode"
},
  "geometry": {"coordinates":[0.29947706238194,51.5765816460975],"type":"Point"}
}