{
  "type": "Feature",
  "properties": {
    "iso:country": "GB",
    "wof:name": "CM13 3LB",
    "wof:placetype": "postalcode"
  },
  "geometry": {"coordinates":[0.299477,51.576582],"type":"Point"}
}
