{
  "type": "Feature",
  "properties": {
    "iso:country":"GB",
    "wof:name":"LU4 8QT",
    "wof:placetype":"postalcode"
},
  "geometry": {"coordinates":[-0.46197550829784,51.89072624349537],"type":"Point"}
}