{
  "type": "Feature",
  "properties": {
    "date:inception_lower":"1980-01-01",
    "date:inception_upper":"1980-01-31",
    "iso:country":"GB",
    "wof:name":"LU4 8QT",
    "wof:placetype":"postalcode"
},
  "geometry": {"coordinates":[-0.461975,51.890726],"type":"Point"}
}