{
  "type": "Feature",
  "properties": {
    "iso:country":"GB",
    "wof:name":"DH1 3NR",
    "wof:placetype":"postalcode"
},
  "geometry": {"coordinates":[-1.57503221576214,54.77674132249283],"type":"Point"}
}