{
  "type": "Feature",
  "properties": {
    "iso:country":"GB",
    "wof:name":"WC1R 5EU",
    "wof:placetype":"postalcode"
},
  "geometry": {"coordinates":[-0.11311605457643,51.51916886939917],"type":"Point"}
}