{
  "type": "Feature",
  "properties": {
    "iso:country":"GB",
    "wof:name":"B65 8HE",
    "wof:placetype":"postalcode"
},
  "geometry": {"coordinates":[-2.05630097475276,52.48807564652994],"type":"Point"}
}