{
  "type": "Feature",
  "properties": {
    "iso:country":"GB",
    "wof:name":"EX14 3EZ",
    "wof:placetype":"postalcode"
},
  "geometry": {"coordinates":[-3.29420852719145,50.80755864811958],"type":"Point"}
}