{
  "type": "Feature",
  "properties": {
    "iso:country": "GB",
    "wof:name": "WS12 0PW",
    "wof:placetype": "postalcode"
  },
  "geometry": {"coordinates":[-1.964153,52.709889],"type":"Point"}
}
