{
  "type": "Feature",
  "properties": {
    "date:inception_lower":"1980-01-01",
    "date:inception_upper":"1980-01-31",
    "iso:country":"GB",
    "wof:name":"DL11 7JG",
    "wof:placetype":"postalcode"
},
  "geometry": {"coordinates":[-1.807253,54.45992],"type":"Point"}
}