{
  "type": "Feature",
  "properties": {
    "iso:country": "GB",
    "wof:name": "DL11 7JG",
    "wof:placetype": "postalcode"
  },
  "geometry": {"coordinates":[-1.807253,54.45992],"type":"Point"}
}
