{
  "type": "Feature",
  "properties": {
    "iso:country":"GB",
    "wof:name":"AB56 1NU",
    "wof:placetype":"postalcode"
},
  "geometry": {"coordinates":[-2.95727857424626,57.67315738190568],"type":"Point"}
}