{
  "type": "Feature",
  "properties": {
    "iso:country": "GB",
    "wof:name": "TR9 6AN",
    "wof:placetype": "postalcode"
  },
  "geometry": {"coordinates":[-4.939753,50.435251],"type":"Point"}
}
