{
  "type": "Feature",
  "properties": {
    "iso:country": "GB",
    "wof:name": "SA4 8TL",
    "wof:placetype": "postalcode"
  },
  "geometry": {"coordinates":[-4.045318,51.716326],"type":"Point"}
}
