{
  "type": "Feature",
  "properties": {
    "date:inception_lower":"2002-06-01",
    "date:inception_upper":"2002-06-30",
    "iso:country":"GB",
    "wof:name":"SA4 8TL",
    "wof:placetype":"postalcode"
},
  "geometry": {"coordinates":[-4.045318,51.716326],"type":"Point"}
}