{
  "type": "Feature",
  "properties": {
    "iso:country": "GB",
    "wof:name": "CF62 5BY",
    "wof:placetype": "postalcode"
  },
  "geometry": {"coordinates":[-3.276005,51.395547],"type":"Point"}
}
