{
  "type": "Feature",
  "properties": {
    "iso:country":"GB",
    "wof:name":"ME15 7LS",
    "wof:placetype":"postalcode"
},
  "geometry": {"coordinates":[0.54993055379957,51.25399508169696],"type":"Point"}
}