{
  "type": "Feature",
  "properties": {
    "date:inception_lower": "1993-08-01",
    "date:inception_upper": "1993-08-01",
    "iso:country": "GB",
    "wof:name": "NG7 2FN",
    "wof:placetype": "postalcode"
  },
  "geometry": {"coordinates":[-1.180373,52.952607],"type":"Point"}
}
