{
  "type": "Feature",
  "properties": {
    "iso:country":"GB",
    "wof:name":"NG7 2FN",
    "wof:placetype":"postalcode"
},
  "geometry": {"coordinates":[-1.18037328984879,52.95260677596933],"type":"Point"}
}