{
  "type": "Feature",
  "properties": {
    "date:inception_lower": "1998-12-01",
    "date:inception_upper": "1998-12-01",
    "iso:country": "GB",
    "wof:name": "IV30 5SX",
    "wof:placetype": "postalcode"
  },
  "geometry": {"coordinates":[-3.433184,57.704427],"type":"Point"}
}
