{
  "type": "Feature",
  "properties": {
    "iso:country": "GB",
    "wof:name": "SO23 7TF",
    "wof:placetype": "postalcode"
  },
  "geometry": {"coordinates":[-1.294967,51.096332],"type":"Point"}
}
