{
  "type": "Feature",
  "properties": {
    "iso:country": "GB",
    "wof:name": "OX2 7QY",
    "wof:placetype": "postalcode"
  },
  "geometry": {"coordinates":[-1.272005,51.784328],"type":"Point"}
}
