{
  "type": "Feature",
  "properties": {
    "iso:country":"GB",
    "wof:name":"OX2 7QY",
    "wof:placetype":"postalcode"
},
  "geometry": {"coordinates":[-1.27200463457943,51.78432764610088],"type":"Point"}
}