{
  "type": "Feature",
  "properties": {
    "iso:country":"GB",
    "wof:name":"PE22 0LL",
    "wof:placetype":"postalcode"
},
  "geometry": {"coordinates":[0.05323594363619,52.9634465102216],"type":"Point"}
}