{
  "type": "Feature",
  "properties": {
    "iso:country":"GB",
    "wof:name":"L39 7HG",
    "wof:placetype":"postalcode"
},
  "geometry": {"coordinates":[-2.92556220475625,53.55012270313132],"type":"Point"}
}