{
  "type": "Feature",
  "properties": {
    "iso:country":"GB",
    "wof:name":"ME2 1FE",
    "wof:placetype":"postalcode"
},
  "geometry": {"coordinates":[0.44652454476298,51.36592409632853],"type":"Point"}
}