{
  "type": "Feature",
  "properties": {
    "date:inception_lower": "2013-01-01",
    "date:inception_upper": "2013-01-01",
    "iso:country": "GB",
    "wof:name": "ME2 1FE",
    "wof:placetype": "postalcode"
  },
  "geometry": {"coordinates":[0.446525,51.365924],"type":"Point"}
}
