{
  "type": "Feature",
  "properties": {
    "iso:country":"GB",
    "wof:name":"HA2 7BA",
    "wof:placetype":"postalcode"
},
  "geometry": {"coordinates":[-0.35712754388254,51.58239566103936],"type":"Point"}
}