{
  "type": "Feature",
  "properties": {
    "iso:country": "GB",
    "wof:name": "HA2 7BA",
    "wof:placetype": "postalcode"
  },
  "geometry": {"coordinates":[-0.357128,51.582396],"type":"Point"}
}
