{
  "type": "Feature",
  "properties": {
    "iso:country":"GB",
    "wof:name":"CF43 4PT",
    "wof:placetype":"postalcode"
},
  "geometry": {"coordinates":[-3.44824055212661,51.66351449958309],"type":"Point"}
}