{
  "type": "Feature",
  "properties": {
    "iso:country": "GB",
    "wof:name": "CF43 4PT",
    "wof:placetype": "postalcode"
  },
  "geometry": {"coordinates":[-3.448241,51.663514],"type":"Point"}
}
