{
  "type": "Feature",
  "properties": {
    "date:inception_lower": "1980-01-01",
    "date:inception_upper": "1980-01-01",
    "iso:country": "GB",
    "wof:name": "S43 2JW",
    "wof:placetype": "postalcode"
  },
  "geometry": {"coordinates":[-1.377477,53.263802],"type":"Point"}
}
