{
  "type": "Feature",
  "properties": {
    "iso:country":"GB",
    "wof:name":"EX31 1TZ",
    "wof:placetype":"postalcode"
},
  "geometry": {"coordinates":[-4.06021782150176,51.08294036317675],"type":"Point"}
}