{
  "type": "Feature",
  "properties": {
    "iso:country":"GB",
    "wof:name":"WD6 4AS",
    "wof:placetype":"postalcode"
},
  "geometry": {"coordinates":[-0.28219072293218,51.65845786301385],"type":"Point"}
}