{
  "type": "Feature",
  "properties": {
    "iso:country":"GB",
    "wof:name":"SA70 8QT",
    "wof:placetype":"postalcode"
},
  "geometry": {"coordinates":[-4.80701594948191,51.65738390651623],"type":"Point"}
}