{
  "type": "Feature",
  "properties": {
    "date:inception_lower":"2002-05-01",
    "date:inception_upper":"2002-05-31",
    "iso:country":"GB",
    "wof:name":"SA70 8QT",
    "wof:placetype":"postalcode"
},
  "geometry": {"coordinates":[-4.807016,51.657384],"type":"Point"}
}