{
  "type": "Feature",
  "properties": {
    "date:inception_lower": "1980-01-01",
    "date:inception_upper": "1980-01-01",
    "iso:country": "GB",
    "wof:name": "PA37 1QY",
    "wof:placetype": "postalcode"
  },
  "geometry": {"coordinates":[-5.378436,56.459204],"type":"Point"}
}
