{
  "type": "Feature",
  "properties": {
    "iso:country":"GB",
    "wof:name":"E1 2NJ",
    "wof:placetype":"postalcode"
},
  "geometry": {"coordinates":[-0.05991286057989,51.51241075941615],"type":"Point"}
}