{
  "type": "Feature",
  "properties": {
    "iso:country":"GB",
    "wof:name":"ST15 8TN",
    "wof:placetype":"postalcode"
},
  "geometry": {"coordinates":[-2.13488533836145,52.93427427217479],"type":"Point"}
}