{
  "type": "Feature",
  "properties": {
    "date:inception_lower":"1980-01-01",
    "date:inception_upper":"1980-01-31",
    "iso:country":"GB",
    "wof:name":"CT10 2DL",
    "wof:placetype":"postalcode"
},
  "geometry": {"coordinates":[1.432481,51.35608],"type":"Point"}
}