{
  "type": "Feature",
  "properties": {
    "iso:country":"GB",
    "wof:name":"WC1E 7HU",
    "wof:placetype":"postalcode"
},
  "geometry": {"coordinates":[-0.12872363245248,51.52064188993692],"type":"Point"}
}