{
  "type": "Feature",
  "properties": {
    "date:inception_lower":"1993-08-01",
    "date:inception_upper":"1993-08-31",
    "iso:country":"GB",
    "wof:name":"NN4 7AD",
    "wof:placetype":"postalcode"
},
  "geometry": {"coordinates":[-0.873215,52.23247],"type":"Point"}
}