{
  "type": "Feature",
  "properties": {
    "iso:country": "GB",
    "wof:name": "NN4 7AD",
    "wof:placetype": "postalcode"
  },
  "geometry": {"coordinates":[-0.873083,52.232496],"type":"Point"}
}
