{
  "type": "Feature",
  "properties": {
    "iso:country":"GB",
    "wof:name":"NN4 7AD",
    "wof:placetype":"postalcode"
},
  "geometry": {"coordinates":[-0.87309800600159,52.23248109984335],"type":"Point"}
}