{
  "type": "Feature",
  "properties": {
    "date:inception_lower": "1980-01-01",
    "date:inception_upper": "1980-01-01",
    "iso:country": "GB",
    "wof:name": "MK14 6BZ",
    "wof:placetype": "postalcode"
  },
  "geometry": {"coordinates":[-0.76346,52.063342],"type":"Point"}
}
