{
  "type": "Feature",
  "properties": {
    "iso:country":"GB",
    "wof:name":"MK14 6BZ",
    "wof:placetype":"postalcode"
},
  "geometry": {"coordinates":[-0.76346048726131,52.06334217140689],"type":"Point"}
}