{
  "type": "Feature",
  "properties": {
    "iso:country":"GB",
    "wof:name":"NG17 4BE",
    "wof:placetype":"postalcode"
},
  "geometry": {"coordinates":[-1.25697221963954,53.12942647553233],"type":"Point"}
}