{
  "type": "Feature",
  "properties": {
    "date:inception_lower": "1980-01-01",
    "date:inception_upper": "1980-01-01",
    "iso:country": "GB",
    "wof:name": "KT9 1RN",
    "wof:placetype": "postalcode"
  },
  "geometry": {"coordinates":[-0.296053,51.370411],"type":"Point"}
}
