{
  "type": "Feature",
  "properties": {
    "iso:country":"GB",
    "wof:name":"KT9 1RN",
    "wof:placetype":"postalcode"
},
  "geometry": {"coordinates":[-0.29605265719528,51.37041053889627],"type":"Point"}
}