{
  "type": "Feature",
  "properties": {
    "iso:country":"GB",
    "wof:name":"WA4 2TY",
    "wof:placetype":"postalcode"
},
  "geometry": {"coordinates":[-2.53782887196736,53.3760768531687],"type":"Point"}
}