{
  "type": "Feature",
  "properties": {
    "date:inception_lower":"2018-05-01",
    "date:inception_upper":"2018-05-31",
    "iso:country":"GB",
    "wof:name":"DN22 7XH",
    "wof:placetype":"postalcode"
},
  "geometry": {"coordinates":[-0.93029,53.306198],"type":"Point"}
}