{
  "type": "Feature",
  "properties": {
    "iso:country":"GB",
    "wof:name":"YO30 4SW",
    "wof:placetype":"postalcode"
},
  "geometry": {"coordinates":[-1.1098987401084,53.98954736182382],"type":"Point"}
}