{
  "type": "Feature",
  "properties": {
    "date:inception_lower":"2003-04-01",
    "date:inception_upper":"2003-04-30",
    "iso:country":"GB",
    "wof:name":"YO30 4SW",
    "wof:placetype":"postalcode"
},
  "geometry": {"coordinates":[-1.109899,53.989547],"type":"Point"}
}