{
  "type": "Feature",
  "properties": {
    "iso:country": "GB",
    "wof:name": "PO8 9DQ",
    "wof:placetype": "postalcode"
  },
  "geometry": {"coordinates":[-1.008701,50.904163],"type":"Point"}
}
