{
  "type": "Feature",
  "properties": {
    "date:inception_lower": "1980-01-01",
    "date:inception_upper": "1980-01-01",
    "iso:country": "GB",
    "wof:name": "DE13 9RR",
    "wof:placetype": "postalcode"
  },
  "geometry": {"coordinates":[-1.730447,52.804707],"type":"Point"}
}
