{
  "type": "Feature",
  "properties": {
    "iso:country":"GB",
    "wof:name":"DE13 9RR",
    "wof:placetype":"postalcode"
},
  "geometry": {"coordinates":[-1.73044697629943,52.80470667344191],"type":"Point"}
}