{
  "type": "Feature",
  "properties": {
    "iso:country": "GB",
    "wof:name": "KA16 9LH",
    "wof:placetype": "postalcode"
  },
  "geometry": {"coordinates":[-4.370452,55.623137],"type":"Point"}
}
