{
  "type": "Feature",
  "properties": {
    "iso:country":"GB",
    "wof:name":"SK8 1HL",
    "wof:placetype":"postalcode"
},
  "geometry": {"coordinates":[-2.21516401376938,53.3879174235293],"type":"Point"}
}