{
  "type": "Feature",
  "properties": {
    "iso:country":"GB",
    "wof:name":"G74 4BN",
    "wof:placetype":"postalcode"
},
  "geometry": {"coordinates":[-4.17086347284325,55.77163206225486],"type":"Point"}
}