{
  "type": "Feature",
  "properties": {
    "date:inception_lower": "2002-06-01",
    "date:inception_upper": "2002-06-01",
    "iso:country": "GB",
    "wof:name": "OX2 0EW",
    "wof:placetype": "postalcode"
  },
  "geometry": {"coordinates":[-1.27027,51.747183],"type":"Point"}
}
