{
  "type": "Feature",
  "properties": {
    "iso:country":"GB",
    "wof:name":"OX2 0EW",
    "wof:placetype":"postalcode"
},
  "geometry": {"coordinates":[-1.2702695971165,51.74718313973865],"type":"Point"}
}