{
  "type": "Feature",
  "properties": {
    "iso:country":"GB",
    "wof:name":"SA39 9HN",
    "wof:placetype":"postalcode"
},
  "geometry": {"coordinates":[-4.26705050496045,51.978150164434],"type":"Point"}
}