{
  "type": "Feature",
  "properties": {
    "iso:country": "GB",
    "wof:name": "SA39 9HN",
    "wof:placetype": "postalcode"
  },
  "geometry": {"coordinates":[-4.26705,51.97815],"type":"Point"}
}
