{
  "type": "Feature",
  "properties": {
    "iso:country":"GB",
    "wof:name":"WF8 3BQ",
    "wof:placetype":"postalcode"
},
  "geometry": {"coordinates":[-1.2640359105059,53.67469300698303],"type":"Point"}
}