{
  "type": "Feature",
  "properties": {
    "date:inception_lower": "1980-01-01",
    "date:inception_upper": "1980-01-01",
    "iso:country": "GB",
    "wof:name": "WF8 3BQ",
    "wof:placetype": "postalcode"
  },
  "geometry": {"coordinates":[-1.264036,53.674693],"type":"Point"}
}
