{
  "type": "Feature",
  "properties": {
    "iso:country": "GB",
    "wof:name": "G33 6NN",
    "wof:placetype": "postalcode"
  },
  "geometry": {"coordinates":[-4.167157,55.884299],"type":"Point"}
}
