{
  "type": "Feature",
  "properties": {
    "iso:country":"GB",
    "wof:name":"EX38 8EQ",
    "wof:placetype":"postalcode"
},
  "geometry": {"coordinates":[-4.14140100166472,50.95355698690415],"type":"Point"}
}