{
  "type": "Feature",
  "properties": {
    "iso:country":"GB",
    "wof:name":"PO36 8QN",
    "wof:placetype":"postalcode"
},
  "geometry": {"coordinates":[-1.13283112595901,50.66549360220223],"type":"Point"}
}