{
  "type": "Feature",
  "properties": {
    "iso:country":"GB",
    "wof:name":"KA15 1EY",
    "wof:placetype":"postalcode"
},
  "geometry": {"coordinates":[-4.63662181108345,55.74726468461974],"type":"Point"}
}