{
  "type": "Feature",
  "properties": {
    "iso:country": "GB",
    "wof:name": "KA15 1EY",
    "wof:placetype": "postalcode"
  },
  "geometry": {"coordinates":[-4.636622,55.747265],"type":"Point"}
}
