{
  "type": "Feature",
  "properties": {
    "iso:country": "GB",
    "wof:name": "WF9 2NN",
    "wof:placetype": "postalcode"
  },
  "geometry": {"coordinates":[-1.289151,53.603504],"type":"Point"}
}
