{
  "type": "Feature",
  "properties": {
    "iso:country":"GB",
    "wof:name":"WF9 2NN",
    "wof:placetype":"postalcode"
},
  "geometry": {"coordinates":[-1.28915106218307,53.60350372637269],"type":"Point"}
}