{
  "type": "Feature",
  "properties": {
    "iso:country": "GB",
    "wof:name": "NE40 4FD",
    "wof:placetype": "postalcode"
  },
  "geometry": {"coordinates":[-1.784036,54.962482],"type":"Point"}
}
