{
  "type": "Feature",
  "properties": {
    "iso:country":"GB",
    "wof:name":"CM15 0BU",
    "wof:placetype":"postalcode"
},
  "geometry": {"coordinates":[0.28227737197148,51.66389688170258],"type":"Point"}
}