{
  "type": "Feature",
  "properties": {
    "iso:country": "GB",
    "wof:name": "DL7 9RS",
    "wof:placetype": "postalcode"
  },
  "geometry": {"coordinates":[-1.554103,54.30186],"type":"Point"}
}
