{
  "type": "Feature",
  "properties": {
    "iso:country":"GB",
    "wof:name":"EN2 0HJ",
    "wof:placetype":"postalcode"
},
  "geometry": {"coordinates":[-0.08367550766107,51.67026848863256],"type":"Point"}
}