{
  "type": "Feature",
  "properties": {
    "iso:country":"GB",
    "wof:name":"B62 8JW",
    "wof:placetype":"postalcode"
},
  "geometry": {"coordinates":[-2.03403269054494,52.46738031457839],"type":"Point"}
}