{
  "type": "Feature",
  "properties": {
    "iso:country":"GB",
    "wof:name":"HR6 0ES",
    "wof:placetype":"postalcode"
},
  "geometry": {"coordinates":[-2.66508102335636,52.24465847487885],"type":"Point"}
}