{
  "type": "Feature",
  "properties": {
    "iso:country": "GB",
    "wof:name": "HR6 0ES",
    "wof:placetype": "postalcode"
  },
  "geometry": {"coordinates":[-2.665081,52.244658],"type":"Point"}
}
