{
  "type": "Feature",
  "properties": {
    "date:inception_lower": "2018-09-01",
    "date:inception_upper": "2018-09-01",
    "iso:country": "GB",
    "wof:name": "YO51 9FW",
    "wof:placetype": "postalcode"
  },
  "geometry": {"coordinates":[-1.399448,54.09637],"type":"Point"}
}
