{
  "type": "Feature",
  "properties": {
    "date:inception_lower": "2019-11-01",
    "date:inception_upper": "2019-11-01",
    "iso:country": "GB",
    "wof:name": "PE29 2FD",
    "wof:placetype": "postalcode"
  },
  "geometry": {"coordinates":[-0.177286,52.326807],"type":"Point"}
}
