{
  "type": "Feature",
  "properties": {
    "iso:country": "GB",
    "wof:name": "CB6 1TA",
    "wof:placetype": "postalcode"
  },
  "geometry": {"coordinates":[0.260065,52.400107],"type":"Point"}
}
