{
  "type": "Feature",
  "properties": {
    "iso:country":"GB",
    "wof:name":"CB6 1TA",
    "wof:placetype":"postalcode"
},
  "geometry": {"coordinates":[0.26006483377319,52.40010676778427],"type":"Point"}
}