{
  "type": "Feature",
  "properties": {
    "iso:country":"GB",
    "wof:name":"CW1 4LH",
    "wof:placetype":"postalcode"
},
  "geometry": {"coordinates":[-2.44128680643405,53.10578202918633],"type":"Point"}
}