{
  "type": "Feature",
  "properties": {
    "iso:country":"GB",
    "wof:name":"E4 8YH",
    "wof:placetype":"postalcode"
},
  "geometry": {"coordinates":[-0.02618426234777,51.60747504786941],"type":"Point"}
}