{
  "type": "Feature",
  "properties": {
    "iso:country":"GB",
    "wof:name":"HG5 0AT",
    "wof:placetype":"postalcode"
},
  "geometry": {"coordinates":[-1.45429797999997,54.00824010682494],"type":"Point"}
}