{
  "type": "Feature",
  "properties": {
    "date:inception_lower":"2002-07-01",
    "date:inception_upper":"2002-07-31",
    "iso:country":"GB",
    "wof:name":"LL23 7EQ",
    "wof:placetype":"postalcode"
},
  "geometry": {"coordinates":[-3.596026,52.909478],"type":"Point"}
}