{
  "type": "Feature",
  "properties": {
    "date:inception_lower": "2021-03-01",
    "date:inception_upper": "2021-03-01",
    "iso:country": "GB",
    "wof:name": "IP16 4WS",
    "wof:placetype": "postalcode"
  },
  "geometry": {"coordinates":[1.561696,52.209573],"type":"Point"}
}
