{
  "type": "Feature",
  "properties": {
    "date:inception_lower": "1980-01-01",
    "date:inception_upper": "1980-01-01",
    "iso:country": "GB",
    "wof:name": "SN15 5LU",
    "wof:placetype": "postalcode"
  },
  "geometry": {"coordinates":[-2.121032,51.482388],"type":"Point"}
}
