{
  "type": "Feature",
  "properties": {
    "iso:country":"GB",
    "wof:name":"SN15 5LU",
    "wof:placetype":"postalcode"
},
  "geometry": {"coordinates":[-2.1210316647308,51.4823877775714],"type":"Point"}
}