{
  "type": "Feature",
  "properties": {
    "iso:country": "GB",
    "wof:name": "CB10 1JZ",
    "wof:placetype": "postalcode"
  },
  "geometry": {"coordinates":[0.240854,52.023014],"type":"Point"}
}
