{
  "type": "Feature",
  "properties": {
    "date:inception_lower": "1996-06-01",
    "date:inception_upper": "1996-06-01",
    "iso:country": "GB",
    "wof:name": "AB31 5ZN",
    "wof:placetype": "postalcode"
  },
  "geometry": {"coordinates":[-2.484315,57.059397],"type":"Point"}
}
