{
  "type": "Feature",
  "properties": {
    "iso:country":"GB",
    "wof:name":"AB31 5ZN",
    "wof:placetype":"postalcode"
},
  "geometry": {"coordinates":[-2.48431461854359,57.05939681830693],"type":"Point"}
}