{
  "type": "Feature",
  "properties": {
    "date:inception_lower": "1987-04-01",
    "date:inception_upper": "1987-04-01",
    "iso:country": "GB",
    "wof:name": "YO21 1LW",
    "wof:placetype": "postalcode"
  },
  "geometry": {"coordinates":[-0.630269,54.481395],"type":"Point"}
}
