{
  "type": "Feature",
  "properties": {
    "iso:country":"GB",
    "wof:name":"FY6 7TG",
    "wof:placetype":"postalcode"
},
  "geometry": {"coordinates":[-3.00273389002205,53.85709616484007],"type":"Point"}
}