{
  "type": "Feature",
  "properties": {
    "date:inception_lower": "1980-01-01",
    "date:inception_upper": "1980-01-01",
    "iso:country": "GB",
    "wof:name": "FY6 7TG",
    "wof:placetype": "postalcode"
  },
  "geometry": {"coordinates":[-3.002734,53.857096],"type":"Point"}
}
