{
  "type": "Feature",
  "properties": {
    "iso:country":"GB",
    "wof:name":"B29 6ST",
    "wof:placetype":"postalcode"
},
  "geometry": {"coordinates":[-1.94588824576369,52.44469127248462],"type":"Point"}
}