{
  "type": "Feature",
  "properties": {
    "date:inception_lower":"1980-01-01",
    "date:inception_upper":"1980-01-31",
    "iso:country":"GB",
    "wof:name":"B29 6ST",
    "wof:placetype":"postalcode"
},
  "geometry": {"coordinates":[-1.945765,52.444715],"type":"Point"}
}