{
  "type": "Feature",
  "properties": {
    "date:inception_lower":"2017-01-01",
    "date:inception_upper":"2017-01-31",
    "iso:country":"GB",
    "wof:name":"CV21 1YR",
    "wof:placetype":"postalcode"
},
  "geometry": {"coordinates":[-1.25043,52.37982],"type":"Point"}
}