{
  "type": "Feature",
  "properties": {
    "date:inception_lower": "1980-01-01",
    "date:inception_upper": "1980-01-01",
    "iso:country": "GB",
    "wof:name": "HP8 4QY",
    "wof:placetype": "postalcode"
  },
  "geometry": {"coordinates":[-0.570257,51.632753],"type":"Point"}
}
