{
  "type": "Feature",
  "properties": {
    "date:inception_lower": "1994-05-01",
    "date:inception_upper": "1994-05-01",
    "iso:country": "GB",
    "wof:name": "M33 7RF",
    "wof:placetype": "postalcode"
  },
  "geometry": {"coordinates":[-2.329398,53.422144],"type":"Point"}
}
