{
  "type": "Feature",
  "properties": {
    "date:inception_lower":"1980-01-01",
    "date:inception_upper":"1980-01-31",
    "iso:country":"GB",
    "wof:name":"L9 2AW",
    "wof:placetype":"postalcode"
},
  "geometry": {"coordinates":[-2.954903,53.455519],"type":"Point"}
}