{
  "type": "Feature",
  "properties": {
    "iso:country":"GB",
    "wof:name":"L9 2AW",
    "wof:placetype":"postalcode"
},
  "geometry": {"coordinates":[-2.95490313316458,53.45551891877686],"type":"Point"}
}