{
  "type": "Feature",
  "properties": {
    "iso:country": "GB",
    "wof:name": "EC1V 2AG",
    "wof:placetype": "postalcode"
  },
  "geometry": {"coordinates":[-0.096727,51.529257],"type":"Point"}
}
