{
  "type": "Feature",
  "properties": {
    "iso:country":"GB",
    "wof:name":"SO50 7NX",
    "wof:placetype":"postalcode"
},
  "geometry": {"coordinates":[-1.29429948135964,50.94955515785725],"type":"Point"}
}