{
  "type": "Feature",
  "properties": {
    "iso:country":"GB",
    "wof:name":"WN5 0EH",
    "wof:placetype":"postalcode"
},
  "geometry": {"coordinates":[-2.67882757486337,53.54896475694641],"type":"Point"}
}