{
  "type": "Feature",
  "properties": {
    "iso:country": "GB",
    "wof:name": "RM3 8AJ",
    "wof:placetype": "postalcode"
  },
  "geometry": {"coordinates":[0.212345,51.600994],"type":"Point"}
}
