{
  "type": "Feature",
  "properties": {
    "iso:country":"GB",
    "wof:name":"RM3 8AJ",
    "wof:placetype":"postalcode"
},
  "geometry": {"coordinates":[0.21233349778103,51.60099110780606],"type":"Point"}
}