{
  "type": "Feature",
  "properties": {
    "iso:country":"GB",
    "wof:name":"BH10 7JP",
    "wof:placetype":"postalcode"
},
  "geometry": {"coordinates":[-1.89781488448034,50.77147726483931],"type":"Point"}
}