{
  "type": "Feature",
  "properties": {
    "iso:country":"GB",
    "wof:name":"CM1 3NY",
    "wof:placetype":"postalcode"
},
  "geometry": {"coordinates":[0.41114958898922,51.72889438810233],"type":"Point"}
}