{
  "type": "Feature",
  "properties": {
    "date:inception_lower": "1980-01-01",
    "date:inception_upper": "1980-01-01",
    "iso:country": "GB",
    "wof:name": "CM1 3NY",
    "wof:placetype": "postalcode"
  },
  "geometry": {"coordinates":[0.411531,51.729046],"type":"Point"}
}
