{
  "type": "Feature",
  "properties": {
    "iso:country":"GB",
    "wof:name":"BL2 6LX",
    "wof:placetype":"postalcode"
},
  "geometry": {"coordinates":[-2.38031805273687,53.57689270365304],"type":"Point"}
}