{
  "type": "Feature",
  "properties": {
    "date:inception_lower":"1980-01-01",
    "date:inception_upper":"1980-01-31",
    "iso:country":"GB",
    "wof:name":"NE65 8AN",
    "wof:placetype":"postalcode"
},
  "geometry": {"coordinates":[-1.805699,55.302541],"type":"Point"}
}