{
  "type": "Feature",
  "properties": {
    "iso:country": "GB",
    "wof:name": "PA18 6ED",
    "wof:placetype": "postalcode"
  },
  "geometry": {"coordinates":[-4.8906,55.893573],"type":"Point"}
}
