{
  "type": "Feature",
  "properties": {
    "iso:country":"GB",
    "wof:name":"PA18 6ED",
    "wof:placetype":"postalcode"
},
  "geometry": {"coordinates":[-4.8905999144878,55.89357281497012],"type":"Point"}
}