{
  "type": "Feature",
  "properties": {
    "iso:country": "GB",
    "wof:name": "DE11 9QT",
    "wof:placetype": "postalcode"
  },
  "geometry": {"coordinates":[-1.563527,52.764414],"type":"Point"}
}
