{
  "type": "Feature",
  "properties": {
    "iso:country":"GB",
    "wof:name":"DE11 9QT",
    "wof:placetype":"postalcode"
},
  "geometry": {"coordinates":[-1.56352688188346,52.76441377339204],"type":"Point"}
}