{
  "type": "Feature",
  "properties": {
    "iso:country": "GB",
    "wof:name": "PE25 2BD",
    "wof:placetype": "postalcode"
  },
  "geometry": {"coordinates":[0.338507,53.143798],"type":"Point"}
}
