{
  "type": "Feature",
  "properties": {
    "date:inception_lower": "1980-01-01",
    "date:inception_upper": "1980-01-01",
    "iso:country": "GB",
    "wof:name": "PE25 2BD",
    "wof:placetype": "postalcode"
  },
  "geometry": {"coordinates":[0.338507,53.143798],"type":"Point"}
}
