{
  "type": "Feature",
  "properties": {
    "iso:country":"GB",
    "wof:name":"PE25 2BD",
    "wof:placetype":"postalcode"
},
  "geometry": {"coordinates":[0.33844719697134,53.14378056991264],"type":"Point"}
}