{
  "type": "Feature",
  "properties": {
    "iso:country":"GB",
    "wof:name":"G64 1FJ",
    "wof:placetype":"postalcode"
},
  "geometry": {"coordinates":[-4.19370861837827,55.90059018857976],"type":"Point"}
}