{
  "type": "Feature",
  "properties": {
    "date:inception_lower":"2005-01-01",
    "date:inception_upper":"2005-01-31",
    "iso:country":"GB",
    "wof:name":"G64 1FJ",
    "wof:placetype":"postalcode"
},
  "geometry": {"coordinates":[-4.193709,55.90059],"type":"Point"}
}