{
  "type": "Feature",
  "properties": {
    "iso:country": "GB",
    "wof:name": "G64 1FJ",
    "wof:placetype": "postalcode"
  },
  "geometry": {"coordinates":[-4.193709,55.90059],"type":"Point"}
}
