{
  "type": "Feature",
  "properties": {
    "date:inception_lower": "2015-03-01",
    "date:inception_upper": "2015-03-01",
    "iso:country": "GB",
    "wof:name": "PE7 8PE",
    "wof:placetype": "postalcode"
  },
  "geometry": {"coordinates":[-0.282044,52.529502],"type":"Point"}
}
