{
  "type": "Feature",
  "properties": {
    "iso:country":"GB",
    "wof:name":"PE7 8PE",
    "wof:placetype":"postalcode"
},
  "geometry": {"coordinates":[-0.28215190890505,52.52938654607534],"type":"Point"}
}