{
  "type": "Feature",
  "properties": {
    "date:inception_lower": "1980-01-01",
    "date:inception_upper": "1980-01-01",
    "iso:country": "GB",
    "wof:name": "BS24 9QR",
    "wof:placetype": "postalcode"
  },
  "geometry": {"coordinates":[-2.935611,51.325743],"type":"Point"}
}
