{
  "type": "Feature",
  "properties": {
    "date:inception_lower": "1998-12-01",
    "date:inception_upper": "1998-12-01",
    "iso:country": "GB",
    "wof:name": "TS27 3JS",
    "wof:placetype": "postalcode"
  },
  "geometry": {"coordinates":[-1.281579,54.673188],"type":"Point"}
}
