{
  "type": "Feature",
  "properties": {
    "iso:country": "GB",
    "wof:name": "TS27 3JS",
    "wof:placetype": "postalcode"
  },
  "geometry": {"coordinates":[-1.281579,54.673188],"type":"Point"}
}
