{
  "type": "Feature",
  "properties": {
    "iso:country":"GB",
    "wof:name":"TS27 3JS",
    "wof:placetype":"postalcode"
},
  "geometry": {"coordinates":[-1.28157925362071,54.67318828372774],"type":"Point"}
}