{
  "type": "Feature",
  "properties": {
    "date:inception_lower": "2022-10-01",
    "date:inception_upper": "2022-10-01",
    "iso:country": "GB",
    "wof:name": "TS24 0AN",
    "wof:placetype": "postalcode"
  },
  "geometry": {"coordinates":[-1.222013,54.704204],"type":"Point"}
}
