{
  "type": "Feature",
  "properties": {
    "date:inception_lower": "2022-10-01",
    "date:inception_upper": "2022-10-01",
    "iso:country": "GB",
    "wof:name": "TS24 0AN",
    "wof:placetype": "postalcode"
  },
  "geometry": {"coordinates":[-1.22199,54.711888],"type":"Point"}
}
