{
  "type": "Feature",
  "properties": {
    "iso:country": "GB",
    "wof:name": "CV3 6FJ",
    "wof:placetype": "postalcode"
  },
  "geometry": {"coordinates":[-1.511777,52.3761],"type":"Point"}
}
