{
  "type": "Feature",
  "properties": {
    "iso:country":"GB",
    "wof:name":"CV3 6FJ",
    "wof:placetype":"postalcode"
},
  "geometry": {"coordinates":[-1.5117773961818,52.37610004211309],"type":"Point"}
}