{
  "type": "Feature",
  "properties": {
    "date:inception_lower": "1980-01-01",
    "date:inception_upper": "1980-01-01",
    "iso:country": "GB",
    "wof:name": "CV3 6FJ",
    "wof:placetype": "postalcode"
  },
  "geometry": {"coordinates":[-1.511777,52.3761],"type":"Point"}
}
