{
  "type": "Feature",
  "properties": {
    "iso:country":"GB",
    "wof:name":"CW8 4BL",
    "wof:placetype":"postalcode"
},
  "geometry": {"coordinates":[-2.52890440130698,53.26234564541285],"type":"Point"}
}