{
  "type": "Feature",
  "properties": {
    "date:inception_lower":"1980-01-01",
    "date:inception_upper":"1980-01-31",
    "iso:country":"GB",
    "wof:name":"CW8 4BL",
    "wof:placetype":"postalcode"
},
  "geometry": {"coordinates":[-2.528904,53.262346],"type":"Point"}
}