{
  "type": "Feature",
  "properties": {
    "date:inception_lower":"1990-07-01",
    "date:inception_upper":"1990-07-31",
    "iso:country":"GB",
    "wof:name":"DL1 5PJ",
    "wof:placetype":"postalcode"
},
  "geometry": {"coordinates":[-1.559155,54.520652],"type":"Point"}
}