{
  "type": "Feature",
  "properties": {
    "iso:country":"GB",
    "wof:name":"DL1 5PJ",
    "wof:placetype":"postalcode"
},
  "geometry": {"coordinates":[-1.5591553226636,54.52065176022084],"type":"Point"}
}