{
  "type": "Feature",
  "properties": {
    "iso:country":"GB",
    "wof:name":"OL9 0JN",
    "wof:placetype":"postalcode"
},
  "geometry": {"coordinates":[-2.1435436562371,53.54652772481793],"type":"Point"}
}