{
  "type": "Feature",
  "properties": {
    "iso:country": "GB",
    "wof:name": "OL9 0JN",
    "wof:placetype": "postalcode"
  },
  "geometry": {"coordinates":[-2.143544,53.546528],"type":"Point"}
}
