{
  "type": "Feature",
  "properties": {
    "iso:country":"GB",
    "wof:name":"LL18 4LZ",
    "wof:placetype":"postalcode"
},
  "geometry": {"coordinates":[-3.45925074347987,53.32121692063188],"type":"Point"}
}