{
  "type": "Feature",
  "properties": {
    "iso:country": "GB",
    "wof:name": "LL18 4LZ",
    "wof:placetype": "postalcode"
  },
  "geometry": {"coordinates":[-3.459251,53.321217],"type":"Point"}
}
