{
  "type": "Feature",
  "properties": {
    "iso:country":"GB",
    "wof:name":"WR3 7NF",
    "wof:placetype":"postalcode"
},
  "geometry": {"coordinates":[-2.23585040064215,52.21809449722346],"type":"Point"}
}