{
  "type": "Feature",
  "properties": {
    "iso:country":"GB",
    "wof:name":"RM14 1LP",
    "wof:placetype":"postalcode"
},
  "geometry": {"coordinates":[0.26977907354222,51.56712380656822],"type":"Point"}
}