{
  "type": "Feature",
  "properties": {
    "iso:country": "GB",
    "wof:name": "DL15 8HH",
    "wof:placetype": "postalcode"
  },
  "geometry": {"coordinates":[-1.750909,54.695119],"type":"Point"}
}
