{
  "type": "Feature",
  "properties": {
    "iso:country":"GB",
    "wof:name":"EX7 9QZ",
    "wof:placetype":"postalcode"
},
  "geometry": {"coordinates":[-3.47940189145177,50.57863535012498],"type":"Point"}
}