{
  "type": "Feature",
  "properties": {
    "date:inception_lower": "1980-01-01",
    "date:inception_upper": "1980-01-01",
    "iso:country": "GB",
    "wof:name": "HA8 5RY",
    "wof:placetype": "postalcode"
  },
  "geometry": {"coordinates":[-0.280671,51.601164],"type":"Point"}
}
