{
  "type": "Feature",
  "properties": {
    "iso:country": "GB",
    "wof:name": "LN5 9JF",
    "wof:placetype": "postalcode"
  },
  "geometry": {"coordinates":[-0.629639,53.117948],"type":"Point"}
}
