{
  "type": "Feature",
  "properties": {
    "iso:country": "GB",
    "wof:name": "GU52 7TP",
    "wof:placetype": "postalcode"
  },
  "geometry": {"coordinates":[-0.835482,51.270186],"type":"Point"}
}
