{
  "type": "Feature",
  "properties": {
    "iso:country":"GB",
    "wof:name":"CM9 6BD",
    "wof:placetype":"postalcode"
},
  "geometry": {"coordinates":[0.68280424542105,51.72349829044988],"type":"Point"}
}