{
  "type": "Feature",
  "properties": {
    "iso:country":"GB",
    "wof:name":"KY7 6LB",
    "wof:placetype":"postalcode"
},
  "geometry": {"coordinates":[-3.10938298690845,56.21668904973784],"type":"Point"}
}