{
  "type": "Feature",
  "properties": {
    "iso:country": "GB",
    "wof:name": "KY11 4TT",
    "wof:placetype": "postalcode"
  },
  "geometry": {"coordinates":[-3.447999,56.065636],"type":"Point"}
}
