{
  "type": "Feature",
  "properties": {
    "iso:country":"GB",
    "wof:name":"S9 3SA",
    "wof:placetype":"postalcode"
},
  "geometry": {"coordinates":[-1.43313181074462,53.39269987935136],"type":"Point"}
}