{
  "type": "Feature",
  "properties": {
    "iso:country": "GB",
    "wof:name": "S9 3SA",
    "wof:placetype": "postalcode"
  },
  "geometry": {"coordinates":[-1.433132,53.3927],"type":"Point"}
}
