{
  "type": "Feature",
  "properties": {
    "iso:country": "GB",
    "wof:name": "SY16 2HS",
    "wof:placetype": "postalcode"
  },
  "geometry": {"coordinates":[-3.323687,52.516904],"type":"Point"}
}
