{
  "type": "Feature",
  "properties": {
    "iso:country":"GB",
    "wof:name":"BA7 7PR",
    "wof:placetype":"postalcode"
},
  "geometry": {"coordinates":[-2.58173134300022,51.08364536901497],"type":"Point"}
}