{
  "type": "Feature",
  "properties": {
    "iso:country":"GB",
    "wof:name":"BD9 5JU",
    "wof:placetype":"postalcode"
},
  "geometry": {"coordinates":[-1.79549308572288,53.81082628516975],"type":"Point"}
}