{
  "type": "Feature",
  "properties": {
    "date:inception_lower":"1980-01-01",
    "date:inception_upper":"1980-01-31",
    "iso:country":"GB",
    "wof:name":"BD9 5JU",
    "wof:placetype":"postalcode"
},
  "geometry": {"coordinates":[-1.795493,53.810826],"type":"Point"}
}