{
  "type": "Feature",
  "properties": {
    "iso:country":"GB",
    "wof:name":"PE21 8XB",
    "wof:placetype":"postalcode"
},
  "geometry": {"coordinates":[-0.03039200554557,52.97547988639664],"type":"Point"}
}