{
  "type": "Feature",
  "properties": {
    "iso:country": "GB",
    "wof:name": "PE21 8XB",
    "wof:placetype": "postalcode"
  },
  "geometry": {"coordinates":[-0.030392,52.97548],"type":"Point"}
}
