{
  "type": "Feature",
  "properties": {
    "iso:country":"GB",
    "wof:name":"TS13 5DU",
    "wof:placetype":"postalcode"
},
  "geometry": {"coordinates":[-0.80928525118287,54.55143720293476],"type":"Point"}
}