{
  "type": "Feature",
  "properties": {
    "iso:country":"GB",
    "wof:name":"SN6 7EL",
    "wof:placetype":"postalcode"
},
  "geometry": {"coordinates":[-1.71635465961318,51.63411673882845],"type":"Point"}
}