{
  "type": "Feature",
  "properties": {
    "iso:country": "GB",
    "wof:name": "PE28 0PE",
    "wof:placetype": "postalcode"
  },
  "geometry": {"coordinates":[-0.404805,52.344083],"type":"Point"}
}
