{
  "type": "Feature",
  "properties": {
    "iso:country":"GB",
    "wof:name":"RG14 7AQ",
    "wof:placetype":"postalcode"
},
  "geometry": {"coordinates":[-1.32833428580538,51.3910073323222],"type":"Point"}
}