{
  "type": "Feature",
  "properties": {
    "iso:country": "GB",
    "wof:name": "RM4 1DJ",
    "wof:placetype": "postalcode"
  },
  "geometry": {"coordinates":[0.121163,51.648834],"type":"Point"}
}
