{
  "type": "Feature",
  "properties": {
    "date:inception_lower": "1980-01-01",
    "date:inception_upper": "1980-01-01",
    "iso:country": "GB",
    "wof:name": "B11 4JJ",
    "wof:placetype": "postalcode"
  },
  "geometry": {"coordinates":[-1.867957,52.449584],"type":"Point"}
}
