{
  "type": "Feature",
  "properties": {
    "iso:country":"GB",
    "wof:name":"B11 4JJ",
    "wof:placetype":"postalcode"
},
  "geometry": {"coordinates":[-1.8679571526609,52.44958361710876],"type":"Point"}
}