{
  "type": "Feature",
  "properties": {
    "iso:country": "GB",
    "wof:name": "B11 4JJ",
    "wof:placetype": "postalcode"
  },
  "geometry": {"coordinates":[-1.867957,52.449584],"type":"Point"}
}
