{
  "type": "Feature",
  "properties": {
    "iso:country": "GB",
    "wof:name": "OL9 8JE",
    "wof:placetype": "postalcode"
  },
  "geometry": {"coordinates":[-2.148828,53.525848],"type":"Point"}
}
