{
  "type": "Feature",
  "properties": {
    "iso:country":"GB",
    "wof:name":"B8 1AR",
    "wof:placetype":"postalcode"
},
  "geometry": {"coordinates":[-1.86506372164352,52.48645726644063],"type":"Point"}
}