{
  "type": "Feature",
  "properties": {
    "iso:country": "GB",
    "wof:name": "N17 9DF",
    "wof:placetype": "postalcode"
  },
  "geometry": {"coordinates":[-0.054888,51.586354],"type":"Point"}
}
