{
  "type": "Feature",
  "properties": {
    "iso:country":"GB",
    "wof:name":"N17 9DF",
    "wof:placetype":"postalcode"
},
  "geometry": {"coordinates":[-0.05488788049208,51.58635426314366],"type":"Point"}
}