{
  "type": "Feature",
  "properties": {
    "iso:country":"GB",
    "wof:name":"NP20 4HE",
    "wof:placetype":"postalcode"
},
  "geometry": {"coordinates":[-3.00881059350691,51.58144227217686],"type":"Point"}
}