{
  "type": "Feature",
  "properties": {
    "iso:country": "GB",
    "wof:name": "HU8 9FD",
    "wof:placetype": "postalcode"
  },
  "geometry": {"coordinates":[-0.300784,53.784601],"type":"Point"}
}
