{
  "type": "Feature",
  "properties": {
    "date:inception_lower": "1995-12-01",
    "date:inception_upper": "1995-12-01",
    "iso:country": "GB",
    "wof:name": "PL6 7NN",
    "wof:placetype": "postalcode"
  },
  "geometry": {"coordinates":[-4.099182,50.426837],"type":"Point"}
}
