{
  "type": "Feature",
  "properties": {
    "iso:country":"GB",
    "wof:name":"PL6 7NN",
    "wof:placetype":"postalcode"
},
  "geometry": {"coordinates":[-4.09867878136577,50.42691241017755],"type":"Point"}
}