{
  "type": "Feature",
  "properties": {
    "iso:country":"GB",
    "wof:name":"TW12 1HT",
    "wof:placetype":"postalcode"
},
  "geometry": {"coordinates":[-0.36611239033654,51.43112717585622],"type":"Point"}
}