{
  "type": "Feature",
  "properties": {
    "iso:country":"GB",
    "wof:name":"B78 1PJ",
    "wof:placetype":"postalcode"
},
  "geometry": {"coordinates":[-1.61711074046572,52.60419550058685],"type":"Point"}
}