{
  "type": "Feature",
  "properties": {
    "iso:country": "GB",
    "wof:name": "TN34 3HE",
    "wof:placetype": "postalcode"
  },
  "geometry": {"coordinates":[0.59077,50.858708],"type":"Point"}
}
