{
  "type": "Feature",
  "properties": {
    "iso:country":"GB",
    "wof:name":"KT22 0AA",
    "wof:placetype":"postalcode"
},
  "geometry": {"coordinates":[-0.34096798557911,51.30147987178466],"type":"Point"}
}