{
  "type": "Feature",
  "properties": {
    "iso:country": "GB",
    "wof:name": "KT22 0AA",
    "wof:placetype": "postalcode"
  },
  "geometry": {"coordinates":[-0.340968,51.30148],"type":"Point"}
}
