{
  "type": "Feature",
  "properties": {
    "iso:country":"GB",
    "wof:name":"SY1 1TT",
    "wof:placetype":"postalcode"
},
  "geometry": {"coordinates":[-2.75174187986237,52.70573825405213],"type":"Point"}
}