{
  "type": "Feature",
  "properties": {
    "iso:country":"GB",
    "wof:name":"GL2 5HS",
    "wof:placetype":"postalcode"
},
  "geometry": {"coordinates":[-2.26106516908869,51.86215527778457],"type":"Point"}
}