{
  "type": "Feature",
  "properties": {
    "date:inception_lower":"1995-12-01",
    "date:inception_upper":"1995-12-31",
    "iso:country":"GB",
    "wof:name":"GL2 5HS",
    "wof:placetype":"postalcode"
},
  "geometry": {"coordinates":[-2.261065,51.862155],"type":"Point"}
}