{
  "type": "Feature",
  "properties": {
    "date:inception_lower": "2024-06-01",
    "date:inception_upper": "2024-06-01",
    "iso:country": "GB",
    "wof:name": "SS6 9XJ",
    "wof:placetype": "postalcode"
  },
  "geometry": {"coordinates":[0.596587,51.605723],"type":"Point"}
}
