{
  "type": "Feature",
  "properties": {
    "iso:country":"GB",
    "wof:name":"BS14 0BS",
    "wof:placetype":"postalcode"
},
  "geometry": {"coordinates":[-2.5603197051094,51.4056438561495],"type":"Point"}
}