{
  "type": "Feature",
  "properties": {
    "iso:country":"GB",
    "wof:name":"LL53 5GA",
    "wof:placetype":"postalcode"
},
  "geometry": {"coordinates":[-4.42270533602723,52.88867239290974],"type":"Point"}
}