{
  "type": "Feature",
  "properties": {
    "iso:country": "GB",
    "wof:name": "LL53 5GA",
    "wof:placetype": "postalcode"
  },
  "geometry": {"coordinates":[-4.422705,52.888672],"type":"Point"}
}
