{
  "type": "Feature",
  "properties": {
    "iso:country":"GB",
    "wof:name":"PA2 6XR",
    "wof:placetype":"postalcode"
},
  "geometry": {"coordinates":[-4.40557992792865,55.83269210229506],"type":"Point"}
}