{
  "type": "Feature",
  "properties": {
    "iso:country":"GB",
    "wof:name":"MK15 9DE",
    "wof:placetype":"postalcode"
},
  "geometry": {"coordinates":[-0.73377990630384,52.06161546077998],"type":"Point"}
}