{
  "type": "Feature",
  "properties": {
    "iso:country":"GB",
    "wof:name":"LS27 7SF",
    "wof:placetype":"postalcode"
},
  "geometry": {"coordinates":[-1.58592060497357,53.7629103857347],"type":"Point"}
}