{
  "type": "Feature",
  "properties": {
    "date:inception_lower": "1980-01-01",
    "date:inception_upper": "1980-01-01",
    "iso:country": "GB",
    "wof:name": "LS27 7SF",
    "wof:placetype": "postalcode"
  },
  "geometry": {"coordinates":[-1.585921,53.76291],"type":"Point"}
}
