{
  "type": "Feature",
  "properties": {
    "iso:country":"GB",
    "wof:name":"WV2 4AG",
    "wof:placetype":"postalcode"
},
  "geometry": {"coordinates":[-2.12603564976685,52.58170529641927],"type":"Point"}
}