{
  "type": "Feature",
  "properties": {
    "iso:country":"GB",
    "wof:name":"SW14 7EW",
    "wof:placetype":"postalcode"
},
  "geometry": {"coordinates":[-0.27330769751568,51.45940002021975],"type":"Point"}
}