{
  "type": "Feature",
  "properties": {
    "iso:country": "GB",
    "wof:name": "WA3 3YR",
    "wof:placetype": "postalcode"
  },
  "geometry": {"coordinates":[-2.586753,53.484031],"type":"Point"}
}
