{
  "type": "Feature",
  "properties": {
    "iso:country":"GB",
    "wof:name":"DY12 3BA",
    "wof:placetype":"postalcode"
},
  "geometry": {"coordinates":[-2.4306127815384,52.43076619205353],"type":"Point"}
}