{
  "type": "Feature",
  "properties": {
    "date:inception_lower": "2000-12-01",
    "date:inception_upper": "2000-12-01",
    "iso:country": "GB",
    "wof:name": "W1F 7ND",
    "wof:placetype": "postalcode"
  },
  "geometry": {"coordinates":[-0.137223,51.514401],"type":"Point"}
}
