{
  "type": "Feature",
  "properties": {
    "iso:country":"GB",
    "wof:name":"W1F 7ND",
    "wof:placetype":"postalcode"
},
  "geometry": {"coordinates":[-0.13722328802672,51.51440149615046],"type":"Point"}
}