{
  "type": "Feature",
  "properties": {
    "iso:country":"GB",
    "wof:name":"SP10 3NT",
    "wof:placetype":"postalcode"
},
  "geometry": {"coordinates":[-1.50582583439446,51.20688254204009],"type":"Point"}
}