{
  "type": "Feature",
  "properties": {
    "iso:country": "GB",
    "wof:name": "CH44 8EH",
    "wof:placetype": "postalcode"
  },
  "geometry": {"coordinates":[-3.026349,53.416238],"type":"Point"}
}
