{
  "type": "Feature",
  "properties": {
    "iso:country":"GB",
    "wof:name":"CH44 8EH",
    "wof:placetype":"postalcode"
},
  "geometry": {"coordinates":[-3.02634940907457,53.4162380427428],"type":"Point"}
}