{
  "type": "Feature",
  "properties": {
    "iso:country":"GB",
    "wof:name":"B21 0LS",
    "wof:placetype":"postalcode"
},
  "geometry": {"coordinates":[-1.94843490965153,52.50675912481817],"type":"Point"}
}