{
  "type": "Feature",
  "properties": {
    "iso:country": "GB",
    "wof:name": "DD8 1BQ",
    "wof:placetype": "postalcode"
  },
  "geometry": {"coordinates":[-2.890261,56.645959],"type":"Point"}
}
