{
  "type": "Feature",
  "properties": {
    "iso:country": "GB",
    "wof:name": "MK45 9AU",
    "wof:placetype": "postalcode"
  },
  "geometry": {"coordinates":[-0.507445,52.024163],"type":"Point"}
}
