{
  "type": "Feature",
  "properties": {
    "iso:country":"GB",
    "wof:name":"TQ7 3SE",
    "wof:placetype":"postalcode"
},
  "geometry": {"coordinates":[-3.81311725893963,50.24352233618923],"type":"Point"}
}