{
  "type": "Feature",
  "properties": {
    "iso:country":"GB",
    "wof:name":"LS8 1LS",
    "wof:placetype":"postalcode"
},
  "geometry": {"coordinates":[-1.52420534550482,53.8346307921839],"type":"Point"}
}