{
  "type": "Feature",
  "properties": {
    "iso:country":"GB",
    "wof:name":"KY8 2EF",
    "wof:placetype":"postalcode"
},
  "geometry": {"coordinates":[-3.03698816529718,56.18644501012294],"type":"Point"}
}