{
  "type": "Feature",
  "properties": {
    "date:inception_lower":"1980-01-01",
    "date:inception_upper":"1980-01-31",
    "iso:country":"GB",
    "wof:name":"SA67 8JD",
    "wof:placetype":"postalcode"
},
  "geometry": {"coordinates":[-4.672733,51.772568],"type":"Point"}
}