{
  "type": "Feature",
  "properties": {
    "iso:country":"GB",
    "wof:name":"SA67 8JD",
    "wof:placetype":"postalcode"
},
  "geometry": {"coordinates":[-4.67273276170288,51.77256780151419],"type":"Point"}
}