{
  "type": "Feature",
  "properties": {
    "iso:country": "GB",
    "wof:name": "CV35 9BG",
    "wof:placetype": "postalcode"
  },
  "geometry": {"coordinates":[-1.544415,52.200478],"type":"Point"}
}
