{
  "type": "Feature",
  "properties": {
    "iso:country":"GB",
    "wof:name":"PO7 5TR",
    "wof:placetype":"postalcode"
},
  "geometry": {"coordinates":[-1.03516406463104,50.8712919631264],"type":"Point"}
}