{
  "type": "Feature",
  "properties": {
    "iso:country":"GB",
    "wof:name":"BS29 6AX",
    "wof:placetype":"postalcode"
},
  "geometry": {"coordinates":[-2.8745988031402,51.32818731988579],"type":"Point"}
}