{
  "type": "Feature",
  "properties": {
    "iso:country": "GB",
    "wof:name": "BS29 6AX",
    "wof:placetype": "postalcode"
  },
  "geometry": {"coordinates":[-2.874604,51.328166],"type":"Point"}
}
