{
  "type": "Feature",
  "properties": {
    "iso:country": "GB",
    "wof:name": "CV3 3FA",
    "wof:placetype": "postalcode"
  },
  "geometry": {"coordinates":[-1.454892,52.386693],"type":"Point"}
}
