{
  "type": "Feature",
  "properties": {
    "iso:country": "GB",
    "wof:name": "PR4 6JZ",
    "wof:placetype": "postalcode"
  },
  "geometry": {"coordinates":[-2.885711,53.661889],"type":"Point"}
}
