{
  "type": "Feature",
  "properties": {
    "iso:country":"GB",
    "wof:name":"E8 2NP",
    "wof:placetype":"postalcode"
},
  "geometry": {"coordinates":[-0.07286596676524,51.54833377527238],"type":"Point"}
}