{
  "type": "Feature",
  "properties": {
    "iso:country": "GB",
    "wof:name": "E8 2NP",
    "wof:placetype": "postalcode"
  },
  "geometry": {"coordinates":[-0.072866,51.548334],"type":"Point"}
}
