{
  "type": "Feature",
  "properties": {
    "iso:country":"GB",
    "wof:name":"CV9 1EE",
    "wof:placetype":"postalcode"
},
  "geometry": {"coordinates":[-1.54157784226043,52.57219320369287],"type":"Point"}
}