{
  "type": "Feature",
  "properties": {
    "date:inception_lower":"2006-08-01",
    "date:inception_upper":"2006-08-31",
    "iso:country":"GB",
    "wof:name":"IV2 6GJ",
    "wof:placetype":"postalcode"
},
  "geometry": {"coordinates":[-4.177233,57.453745],"type":"Point"}
}