{
  "type": "Feature",
  "properties": {
    "iso:country": "GB",
    "wof:name": "IV2 6GJ",
    "wof:placetype": "postalcode"
  },
  "geometry": {"coordinates":[-4.177233,57.453745],"type":"Point"}
}
