{
  "type": "Feature",
  "properties": {
    "iso:country":"GB",
    "wof:name":"S36 2RA",
    "wof:placetype":"postalcode"
},
  "geometry": {"coordinates":[-1.57833985757994,53.48019316362151],"type":"Point"}
}