{
  "type": "Feature",
  "properties": {
    "iso:country":"GB",
    "wof:name":"KY2 5NB",
    "wof:placetype":"postalcode"
},
  "geometry": {"coordinates":[-3.18088337323546,56.10657869218089],"type":"Point"}
}