{
  "type": "Feature",
  "properties": {
    "iso:country":"GB",
    "wof:name":"PE1 3PL",
    "wof:placetype":"postalcode"
},
  "geometry": {"coordinates":[-0.24065514537267,52.59420400055722],"type":"Point"}
}