{
  "type": "Feature",
  "properties": {
    "iso:country":"GB",
    "wof:name":"DL8 3AW",
    "wof:placetype":"postalcode"
},
  "geometry": {"coordinates":[-2.04363072660258,54.29542224255612],"type":"Point"}
}