{
  "type": "Feature",
  "properties": {
    "iso:country": "GB",
    "wof:name": "DL8 3AW",
    "wof:placetype": "postalcode"
  },
  "geometry": {"coordinates":[-2.043631,54.295422],"type":"Point"}
}
