{
  "type": "Feature",
  "properties": {
    "date:inception_lower": "1980-01-01",
    "date:inception_upper": "1980-01-01",
    "iso:country": "GB",
    "wof:name": "DL8 3AW",
    "wof:placetype": "postalcode"
  },
  "geometry": {"coordinates":[-2.043497,54.295335],"type":"Point"}
}
