{
  "type": "Feature",
  "properties": {
    "iso:country":"GB",
    "wof:name":"SY12 9DN",
    "wof:placetype":"postalcode"
},
  "geometry": {"coordinates":[-2.90567659584241,52.92319380087447],"type":"Point"}
}