{
  "type": "Feature",
  "properties": {
    "date:inception_lower": "1988-03-01",
    "date:inception_upper": "1988-03-01",
    "iso:country": "GB",
    "wof:name": "DY5 3RF",
    "wof:placetype": "postalcode"
  },
  "geometry": {"coordinates":[-2.131701,52.470131],"type":"Point"}
}
