{
  "type": "Feature",
  "properties": {
    "iso:country":"GB",
    "wof:name":"TS4 3JX",
    "wof:placetype":"postalcode"
},
  "geometry": {"coordinates":[-1.22537687726371,54.54868668329682],"type":"Point"}
}