{
  "type": "Feature",
  "properties": {
    "iso:country":"GB",
    "wof:name":"N11 3JG",
    "wof:placetype":"postalcode"
},
  "geometry": {"coordinates":[-0.15637161071263,51.61442096000017],"type":"Point"}
}