{
  "type": "Feature",
  "properties": {
    "date:inception_lower": "1980-01-01",
    "date:inception_upper": "1980-01-01",
    "iso:country": "GB",
    "wof:name": "EN6 3PA",
    "wof:placetype": "postalcode"
  },
  "geometry": {"coordinates":[-0.233177,51.692683],"type":"Point"}
}
