{
  "type": "Feature",
  "properties": {
    "iso:country":"GB",
    "wof:name":"EN6 3PA",
    "wof:placetype":"postalcode"
},
  "geometry": {"coordinates":[-0.23317719151729,51.69268327135036],"type":"Point"}
}