{
  "type": "Feature",
  "properties": {
    "iso:country": "GB",
    "wof:name": "LN4 1PQ",
    "wof:placetype": "postalcode"
  },
  "geometry": {"coordinates":[-0.473978,53.194928],"type":"Point"}
}
