{
  "type": "Feature",
  "properties": {
    "iso:country":"GB",
    "wof:name":"NR19 2QH",
    "wof:placetype":"postalcode"
},
  "geometry": {"coordinates":[0.89967707118337,52.69939770692052],"type":"Point"}
}