{
  "type": "Feature",
  "properties": {
    "date:inception_lower": "2018-09-01",
    "date:inception_upper": "2018-09-01",
    "iso:country": "GB",
    "wof:name": "G77 6GP",
    "wof:placetype": "postalcode"
  },
  "geometry": {"coordinates":[-4.332442,55.791621],"type":"Point"}
}
