{
  "type": "Feature",
  "properties": {
    "iso:country": "GB",
    "wof:name": "G77 6GP",
    "wof:placetype": "postalcode"
  },
  "geometry": {"coordinates":[-4.332442,55.791621],"type":"Point"}
}
