{
  "type": "Feature",
  "properties": {
    "iso:country": "GB",
    "wof:name": "G77 6GP",
    "wof:placetype": "postalcode"
  },
  "geometry": {"coordinates":[-4.341816,55.767338],"type":"Point"}
}
