{
  "type": "Feature",
  "properties": {
    "iso:country":"GB",
    "wof:name":"M40 0FE",
    "wof:placetype":"postalcode"
},
  "geometry": {"coordinates":[-2.17392799179225,53.51829082005504],"type":"Point"}
}