{
  "type": "Feature",
  "properties": {
    "iso:country":"GB",
    "wof:name":"LE13 0JA",
    "wof:placetype":"postalcode"
},
  "geometry": {"coordinates":[-0.9030484168653,52.76561243485855],"type":"Point"}
}