{
  "type": "Feature",
  "properties": {
    "date:inception_lower":"2018-02-01",
    "date:inception_upper":"2018-02-28",
    "iso:country":"GB",
    "wof:name":"RG24 4GH",
    "wof:placetype":"postalcode"
},
  "geometry": {"coordinates":[-1.107856,51.277326],"type":"Point"}
}