{
  "type": "Feature",
  "properties": {
    "iso:country": "GB",
    "wof:name": "B11 3DD",
    "wof:placetype": "postalcode"
  },
  "geometry": {"coordinates":[-1.847174,52.447464],"type":"Point"}
}
