{
  "type": "Feature",
  "properties": {
    "iso:country":"GB",
    "wof:name":"NW3 3RE",
    "wof:placetype":"postalcode"
},
  "geometry": {"coordinates":[-0.16153728790463,51.54195135215821],"type":"Point"}
}