{
  "type": "Feature",
  "properties": {
    "iso:country": "GB",
    "wof:name": "CM13 2QT",
    "wof:placetype": "postalcode"
  },
  "geometry": {"coordinates":[0.351908,51.625987],"type":"Point"}
}
