{
  "type": "Feature",
  "properties": {
    "iso:country": "GB",
    "wof:name": "MK10 9AL",
    "wof:placetype": "postalcode"
  },
  "geometry": {"coordinates":[-0.705592,52.044649],"type":"Point"}
}
