{
  "type": "Feature",
  "properties": {
    "date:inception_lower": "1993-08-01",
    "date:inception_upper": "1993-08-01",
    "iso:country": "GB",
    "wof:name": "NN3 6NA",
    "wof:placetype": "postalcode"
  },
  "geometry": {"coordinates":[-0.861248,52.26869],"type":"Point"}
}
