{
  "type": "Feature",
  "properties": {
    "iso:country":"GB",
    "wof:name":"NN3 6NA",
    "wof:placetype":"postalcode"
},
  "geometry": {"coordinates":[-0.86124784801244,52.26869002894395],"type":"Point"}
}