{
  "type": "Feature",
  "properties": {
    "iso:country": "GB",
    "wof:name": "HX3 8TB",
    "wof:placetype": "postalcode"
  },
  "geometry": {"coordinates":[-1.80253,53.725353],"type":"Point"}
}
