{
  "type": "Feature",
  "properties": {
    "iso:country":"GB",
    "wof:name":"CF45 3DU",
    "wof:placetype":"postalcode"
},
  "geometry": {"coordinates":[-3.40227363316808,51.6826495748744],"type":"Point"}
}