{
  "type": "Feature",
  "properties": {
    "iso:country": "GB",
    "wof:name": "CF45 3DU",
    "wof:placetype": "postalcode"
  },
  "geometry": {"coordinates":[-3.402274,51.68265],"type":"Point"}
}
