{
  "type": "Feature",
  "properties": {
    "date:inception_lower": "1980-01-01",
    "date:inception_upper": "1980-01-01",
    "iso:country": "GB",
    "wof:name": "TN40 1EY",
    "wof:placetype": "postalcode"
  },
  "geometry": {"coordinates":[0.474889,50.840555],"type":"Point"}
}
