{
  "type": "Feature",
  "properties": {
    "iso:country": "GB",
    "wof:name": "G22 7AU",
    "wof:placetype": "postalcode"
  },
  "geometry": {"coordinates":[-4.247417,55.894346],"type":"Point"}
}
