{
  "type": "Feature",
  "properties": {
    "date:inception_lower": "1980-01-01",
    "date:inception_upper": "1980-01-01",
    "iso:country": "GB",
    "wof:name": "G22 7AU",
    "wof:placetype": "postalcode"
  },
  "geometry": {"coordinates":[-4.247417,55.894346],"type":"Point"}
}
