{
  "type": "Feature",
  "properties": {
    "iso:country":"GB",
    "wof:name":"KA22 8AS",
    "wof:placetype":"postalcode"
},
  "geometry": {"coordinates":[-4.80025675780866,55.64340508677458],"type":"Point"}
}