{
  "type": "Feature",
  "properties": {
    "date:inception_lower":"2001-06-01",
    "date:inception_upper":"2001-06-30",
    "iso:country":"GB",
    "wof:name":"BD6 3YF",
    "wof:placetype":"postalcode"
},
  "geometry": {"coordinates":[-1.812828,53.768269],"type":"Point"}
}