{
  "type": "Feature",
  "properties": {
    "iso:country":"GB",
    "wof:name":"BD6 3YF",
    "wof:placetype":"postalcode"
},
  "geometry": {"coordinates":[-1.8128278414059,53.76826948959562],"type":"Point"}
}