{
  "type": "Feature",
  "properties": {
    "iso:country":"GB",
    "wof:name":"TN8 7AU",
    "wof:placetype":"postalcode"
},
  "geometry": {"coordinates":[0.16146324529547,51.19978876027878],"type":"Point"}
}