{
  "type": "Feature",
  "properties": {
    "iso:country": "GB",
    "wof:name": "TN8 7AU",
    "wof:placetype": "postalcode"
  },
  "geometry": {"coordinates":[0.161463,51.199789],"type":"Point"}
}
