{
  "type": "Feature",
  "properties": {
    "iso:country":"GB",
    "wof:name":"HD3 4EN",
    "wof:placetype":"postalcode"
},
  "geometry": {"coordinates":[-1.8207328567393,53.64313114482282],"type":"Point"}
}