{
  "type": "Feature",
  "properties": {
    "iso:country": "GB",
    "wof:name": "HD3 4EN",
    "wof:placetype": "postalcode"
  },
  "geometry": {"coordinates":[-1.820598,53.643074],"type":"Point"}
}
