{
  "type": "Feature",
  "properties": {
    "iso:country": "GB",
    "wof:name": "KT16 0EJ",
    "wof:placetype": "postalcode"
  },
  "geometry": {"coordinates":[-0.563462,51.370757],"type":"Point"}
}
