{
  "type": "Feature",
  "properties": {
    "date:inception_lower":"1980-01-01",
    "date:inception_upper":"1980-01-31",
    "iso:country":"GB",
    "wof:name":"KT16 0EJ",
    "wof:placetype":"postalcode"
},
  "geometry": {"coordinates":[-0.563462,51.370757],"type":"Point"}
}