{
  "type": "Feature",
  "properties": {
    "date:inception_lower": "2023-12-01",
    "date:inception_upper": "2023-12-01",
    "iso:country": "GB",
    "wof:name": "S72 8XX",
    "wof:placetype": "postalcode"
  },
  "geometry": {"coordinates":[-1.41829,53.57709],"type":"Point"}
}
