{
  "type": "Feature",
  "properties": {
    "date:inception_lower": "1980-01-01",
    "date:inception_upper": "1980-01-01",
    "iso:country": "GB",
    "wof:name": "L35 9JX",
    "wof:placetype": "postalcode"
  },
  "geometry": {"coordinates":[-2.777425,53.416148],"type":"Point"}
}
