{
  "type": "Feature",
  "properties": {
    "iso:country":"GB",
    "wof:name":"L35 9JX",
    "wof:placetype":"postalcode"
},
  "geometry": {"coordinates":[-2.77730704772135,53.41620458070183],"type":"Point"}
}