{
  "type": "Feature",
  "properties": {
    "date:inception_lower": "2021-04-01",
    "date:inception_upper": "2021-04-01",
    "iso:country": "GB",
    "wof:name": "IP30 9UQ",
    "wof:placetype": "postalcode"
  },
  "geometry": {"coordinates":[0.908109,52.214973],"type":"Point"}
}
