{
  "type": "Feature",
  "properties": {
    "date:inception_lower": "2005-01-01",
    "date:inception_upper": "2005-01-01",
    "iso:country": "GB",
    "wof:name": "CW11 2SA",
    "wof:placetype": "postalcode"
  },
  "geometry": {"coordinates":[-2.316212,53.157759],"type":"Point"}
}
