{
  "type": "Feature",
  "properties": {
    "iso:country": "GB",
    "wof:name": "CW11 2SA",
    "wof:placetype": "postalcode"
  },
  "geometry": {"coordinates":[-2.316212,53.157759],"type":"Point"}
}
