{
  "type": "Feature",
  "properties": {
    "iso:country":"GB",
    "wof:name":"CW11 2SA",
    "wof:placetype":"postalcode"
},
  "geometry": {"coordinates":[-2.31621252268228,53.1577591261618],"type":"Point"}
}