{
  "type": "Feature",
  "properties": {
    "iso:country": "GB",
    "wof:name": "HP7 9AP",
    "wof:placetype": "postalcode"
  },
  "geometry": {"coordinates":[-0.595963,51.671557],"type":"Point"}
}
