{
  "type": "Feature",
  "properties": {
    "iso:country":"GB",
    "wof:name":"CT3 4HT",
    "wof:placetype":"postalcode"
},
  "geometry": {"coordinates":[1.15989783138336,51.314313443098],"type":"Point"}
}