{
  "type": "Feature",
  "properties": {
    "iso:country":"GB",
    "wof:name":"SK12 1JP",
    "wof:placetype":"postalcode"
},
  "geometry": {"coordinates":[-2.14555177896446,53.34894922869357],"type":"Point"}
}