{
  "type": "Feature",
  "properties": {
    "iso:country": "GB",
    "wof:name": "SK12 1JP",
    "wof:placetype": "postalcode"
  },
  "geometry": {"coordinates":[-2.145552,53.348949],"type":"Point"}
}
