{
  "type": "Feature",
  "properties": {
    "iso:country":"GB",
    "wof:name":"N17 7BW",
    "wof:placetype":"postalcode"
},
  "geometry": {"coordinates":[-0.0831638210606,51.60493932408171],"type":"Point"}
}