{
  "type": "Feature",
  "properties": {
    "date:inception_lower": "2003-04-01",
    "date:inception_upper": "2003-04-01",
    "iso:country": "GB",
    "wof:name": "N17 7BW",
    "wof:placetype": "postalcode"
  },
  "geometry": {"coordinates":[-0.083139,51.604941],"type":"Point"}
}
