{
  "type": "Feature",
  "properties": {
    "date:inception_lower": "1980-01-01",
    "date:inception_upper": "1980-01-01",
    "iso:country": "GB",
    "wof:name": "NR13 4AT",
    "wof:placetype": "postalcode"
  },
  "geometry": {"coordinates":[1.489252,52.622687],"type":"Point"}
}
