{
  "type": "Feature",
  "properties": {
    "iso:country":"GB",
    "wof:name":"SS0 0RH",
    "wof:placetype":"postalcode"
},
  "geometry": {"coordinates":[0.69434806350965,51.55438053255654],"type":"Point"}
}