{
  "type": "Feature",
  "properties": {
    "iso:country":"GB",
    "wof:name":"PL23 1DY",
    "wof:placetype":"postalcode"
},
  "geometry": {"coordinates":[-4.63755948943033,50.33944417590093],"type":"Point"}
}