{
  "type": "Feature",
  "properties": {
    "iso:country": "GB",
    "wof:name": "TS10 1QG",
    "wof:placetype": "postalcode"
  },
  "geometry": {"coordinates":[-1.077135,54.612969],"type":"Point"}
}
