{
  "type": "Feature",
  "properties": {
    "iso:country": "GB",
    "wof:name": "TS10 1QG",
    "wof:placetype": "postalcode"
  },
  "geometry": {"coordinates":[-1.077107,54.612843],"type":"Point"}
}
