{
  "type": "Feature",
  "properties": {
    "iso:country":"GB",
    "wof:name":"TS10 1QG",
    "wof:placetype":"postalcode"
},
  "geometry": {"coordinates":[-1.07709212137102,54.61283057431226],"type":"Point"}
}