{
  "type": "Feature",
  "properties": {
    "iso:country":"GB",
    "wof:name":"SW6 2UF",
    "wof:placetype":"postalcode"
},
  "geometry": {"coordinates":[-0.19150914253068,51.47049552219768],"type":"Point"}
}