{
  "type": "Feature",
  "properties": {
    "iso:country":"GB",
    "wof:name":"DE45 1FW",
    "wof:placetype":"postalcode"
},
  "geometry": {"coordinates":[-1.68041336534175,53.20656139798522],"type":"Point"}
}