{
  "type": "Feature",
  "properties": {
    "date:inception_lower":"1992-08-01",
    "date:inception_upper":"1992-08-31",
    "iso:country":"GB",
    "wof:name":"DE45 1FW",
    "wof:placetype":"postalcode"
},
  "geometry": {"coordinates":[-1.680413,53.206561],"type":"Point"}
}