{
  "type": "Feature",
  "properties": {
    "iso:country": "GB",
    "wof:name": "NR1 1TL",
    "wof:placetype": "postalcode"
  },
  "geometry": {"coordinates":[1.319702,52.625901],"type":"Point"}
}
