{
  "type": "Feature",
  "properties": {
    "date:inception_lower": "2022-12-01",
    "date:inception_upper": "2022-12-01",
    "iso:country": "GB",
    "wof:name": "CV6 6QJ",
    "wof:placetype": "postalcode"
  },
  "geometry": {"coordinates":[-1.47146,52.462294],"type":"Point"}
}
