{
  "type": "Feature",
  "properties": {
    "date:inception_lower": "1993-08-01",
    "date:inception_upper": "1993-08-01",
    "iso:country": "GB",
    "wof:name": "NN4 7NX",
    "wof:placetype": "postalcode"
  },
  "geometry": {"coordinates":[-0.837745,52.218652],"type":"Point"}
}
