{
  "type": "Feature",
  "properties": {
    "iso:country":"GB",
    "wof:name":"NN4 7NX",
    "wof:placetype":"postalcode"
},
  "geometry": {"coordinates":[-0.83774531836866,52.21865213860189],"type":"Point"}
}