{
  "type": "Feature",
  "properties": {
    "date:inception_lower": "1980-01-01",
    "date:inception_upper": "1980-01-01",
    "iso:country": "GB",
    "wof:name": "EC2Y 9BH",
    "wof:placetype": "postalcode"
  },
  "geometry": {"coordinates":[-0.090865,51.519827],"type":"Point"}
}
