{
  "type": "Feature",
  "properties": {
    "iso:country": "GB",
    "wof:name": "TS4 3GG",
    "wof:placetype": "postalcode"
  },
  "geometry": {"coordinates":[-1.219058,54.555764],"type":"Point"}
}
