{
  "type": "Feature",
  "properties": {
    "iso:country": "GB",
    "wof:name": "HU12 0AL",
    "wof:placetype": "postalcode"
  },
  "geometry": {"coordinates":[-0.081939,53.702497],"type":"Point"}
}
