{
  "type": "Feature",
  "properties": {
    "date:inception_lower": "1980-01-01",
    "date:inception_upper": "1980-01-01",
    "iso:country": "GB",
    "wof:name": "GL11 4DW",
    "wof:placetype": "postalcode"
  },
  "geometry": {"coordinates":[-2.3608,51.691529],"type":"Point"}
}
