{
  "type": "Feature",
  "properties": {
    "iso:country":"GB",
    "wof:name":"GL11 4DW",
    "wof:placetype":"postalcode"
},
  "geometry": {"coordinates":[-2.36080014095352,51.69152851876319],"type":"Point"}
}