{
  "type": "Feature",
  "properties": {
    "iso:country": "GB",
    "wof:name": "LL41 3SR",
    "wof:placetype": "postalcode"
  },
  "geometry": {"coordinates":[-3.961503,52.987437],"type":"Point"}
}
