{
  "type": "Feature",
  "properties": {
    "iso:country":"GB",
    "wof:name":"LL41 3SR",
    "wof:placetype":"postalcode"
},
  "geometry": {"coordinates":[-3.96140085650721,52.98748353666705],"type":"Point"}
}