{
  "type": "Feature",
  "properties": {
    "iso:country":"GB",
    "wof:name":"DT9 4JZ",
    "wof:placetype":"postalcode"
},
  "geometry": {"coordinates":[-2.49309846728647,50.96238757812024],"type":"Point"}
}