{
  "type": "Feature",
  "properties": {
    "date:inception_lower": "1980-01-01",
    "date:inception_upper": "1980-01-01",
    "iso:country": "GB",
    "wof:name": "BL0 9DB",
    "wof:placetype": "postalcode"
  },
  "geometry": {"coordinates":[-2.317185,53.644822],"type":"Point"}
}
