{
  "type": "Feature",
  "properties": {
    "iso:country": "GB",
    "wof:name": "NG16 3JJ",
    "wof:placetype": "postalcode"
  },
  "geometry": {"coordinates":[-1.306792,53.010017],"type":"Point"}
}
