{
  "type": "Feature",
  "properties": {
    "date:inception_lower": "1990-07-01",
    "date:inception_upper": "1990-07-01",
    "iso:country": "GB",
    "wof:name": "HR6 8PY",
    "wof:placetype": "postalcode"
  },
  "geometry": {"coordinates":[-2.744176,52.22919],"type":"Point"}
}
