{
  "type": "Feature",
  "properties": {
    "iso:country":"GB",
    "wof:name":"HR6 8PY",
    "wof:placetype":"postalcode"
},
  "geometry": {"coordinates":[-2.7441761106503,52.2291900093144],"type":"Point"}
}