{
  "type": "Feature",
  "properties": {
    "iso:country": "GB",
    "wof:name": "NE17 7RE",
    "wof:placetype": "postalcode"
  },
  "geometry": {"coordinates":[-1.819371,54.894091],"type":"Point"}
}
