{
  "type": "Feature",
  "properties": {
    "date:inception_lower":"1985-10-01",
    "date:inception_upper":"1985-10-31",
    "iso:country":"GB",
    "wof:name":"L16 3GA",
    "wof:placetype":"postalcode"
},
  "geometry": {"coordinates":[-2.879706,53.406568],"type":"Point"}
}