{
  "type": "Feature",
  "properties": {
    "iso:country":"GB",
    "wof:name":"L16 3GA",
    "wof:placetype":"postalcode"
},
  "geometry": {"coordinates":[-2.87970626978712,53.40656804980178],"type":"Point"}
}