{
  "type": "Feature",
  "properties": {
    "iso:country": "GB",
    "wof:name": "L16 3GA",
    "wof:placetype": "postalcode"
  },
  "geometry": {"coordinates":[-2.879706,53.406568],"type":"Point"}
}
