{
  "type": "Feature",
  "properties": {
    "date:inception_lower": "1996-06-01",
    "date:inception_upper": "1996-06-01",
    "iso:country": "GB",
    "wof:name": "PL7 1NQ",
    "wof:placetype": "postalcode"
  },
  "geometry": {"coordinates":[-4.048141,50.383382],"type":"Point"}
}
