{
  "type": "Feature",
  "properties": {
    "iso:country": "GB",
    "wof:name": "PL7 1NQ",
    "wof:placetype": "postalcode"
  },
  "geometry": {"coordinates":[-4.048141,50.383382],"type":"Point"}
}
