{
  "type": "Feature",
  "properties": {
    "iso:country":"GB",
    "wof:name":"PL7 1NQ",
    "wof:placetype":"postalcode"
},
  "geometry": {"coordinates":[-4.04814096039087,50.38338192040318],"type":"Point"}
}