{
  "type": "Feature",
  "properties": {
    "iso:country":"GB",
    "wof:name":"SN3 4BA",
    "wof:placetype":"postalcode"
},
  "geometry": {"coordinates":[-1.74028003758555,51.57358849387273],"type":"Point"}
}