{
  "type": "Feature",
  "properties": {
    "iso:country":"GB",
    "wof:name":"WA4 2UT",
    "wof:placetype":"postalcode"
},
  "geometry": {"coordinates":[-2.57781403539475,53.37284275057159],"type":"Point"}
}