{
  "type": "Feature",
  "properties": {
    "date:inception_lower": "2024-03-01",
    "date:inception_upper": "2024-03-01",
    "iso:country": "GB",
    "wof:name": "HU10 7PN",
    "wof:placetype": "postalcode"
  },
  "geometry": {"coordinates":[-0.427258,53.742408],"type":"Point"}
}
