{
  "type": "Feature",
  "properties": {
    "iso:country":"GB",
    "wof:name":"ME13 8NL",
    "wof:placetype":"postalcode"
},
  "geometry": {"coordinates":[0.8995956801994,51.30848739735858],"type":"Point"}
}