{
  "type": "Feature",
  "properties": {
    "iso:country": "GB",
    "wof:name": "W1K 1QG",
    "wof:placetype": "postalcode"
  },
  "geometry": {"coordinates":[-0.152694,51.50783],"type":"Point"}
}
