{
  "type": "Feature",
  "properties": {
    "date:inception_lower": "1980-01-01",
    "date:inception_upper": "1980-01-01",
    "iso:country": "GB",
    "wof:name": "NN13 5HN",
    "wof:placetype": "postalcode"
  },
  "geometry": {"coordinates":[-1.084986,52.070907],"type":"Point"}
}
