{
  "type": "Feature",
  "properties": {
    "iso:country":"GB",
    "wof:name":"CT3 3HJ",
    "wof:placetype":"postalcode"
},
  "geometry": {"coordinates":[1.20718762028384,51.2317581797265],"type":"Point"}
}