{
  "type": "Feature",
  "properties": {
    "date:inception_lower": "1980-01-01",
    "date:inception_upper": "1980-01-01",
    "iso:country": "GB",
    "wof:name": "CT3 3HJ",
    "wof:placetype": "postalcode"
  },
  "geometry": {"coordinates":[1.207111,51.231676],"type":"Point"}
}
