{
  "type": "Feature",
  "properties": {
    "iso:country":"GB",
    "wof:name":"IP3 9UR",
    "wof:placetype":"postalcode"
},
  "geometry": {"coordinates":[1.19522725146473,52.02860862039002],"type":"Point"}
}