{
  "type": "Feature",
  "properties": {
    "date:inception_lower":"2006-05-01",
    "date:inception_upper":"2006-05-31",
    "iso:country":"GB",
    "wof:name":"IP3 9UR",
    "wof:placetype":"postalcode"
},
  "geometry": {"coordinates":[1.195227,52.028609],"type":"Point"}
}