{
  "type": "Feature",
  "properties": {
    "date:inception_lower": "2001-12-01",
    "date:inception_upper": "2001-12-01",
    "iso:country": "GB",
    "wof:name": "NP26 3TJ",
    "wof:placetype": "postalcode"
  },
  "geometry": {"coordinates":[-2.772735,51.58702],"type":"Point"}
}
