{
  "type": "Feature",
  "properties": {
    "iso:country":"GB",
    "wof:name":"NP26 3TJ",
    "wof:placetype":"postalcode"
},
  "geometry": {"coordinates":[-2.77273525116836,51.5870199127755],"type":"Point"}
}