{
  "type": "Feature",
  "properties": {
    "date:inception_lower":"1980-01-01",
    "date:inception_upper":"1980-01-31",
    "iso:country":"GB",
    "wof:name":"LL38 2SZ",
    "wof:placetype":"postalcode"
},
  "geometry": {"coordinates":[-4.05225,52.689147],"type":"Point"}
}