{
  "type": "Feature",
  "properties": {
    "iso:country":"GB",
    "wof:name":"GU21 2NJ",
    "wof:placetype":"postalcode"
},
  "geometry": {"coordinates":[-0.611670404345,51.32010908598087],"type":"Point"}
}