{
  "type": "Feature",
  "properties": {
    "iso:country": "GB",
    "wof:name": "M18 7SJ",
    "wof:placetype": "postalcode"
  },
  "geometry": {"coordinates":[-2.1819,53.457077],"type":"Point"}
}
