{
  "type": "Feature",
  "properties": {
    "iso:country":"GB",
    "wof:name":"M18 7SJ",
    "wof:placetype":"postalcode"
},
  "geometry": {"coordinates":[-2.18190010220947,53.45707667054248],"type":"Point"}
}