{
  "type": "Feature",
  "properties": {
    "iso:country":"GB",
    "wof:name":"LE4 4EA",
    "wof:placetype":"postalcode"
},
  "geometry": {"coordinates":[-1.12331466764727,52.67408440724565],"type":"Point"}
}