{
  "type": "Feature",
  "properties": {
    "iso:country":"GB",
    "wof:name":"SO53 4RJ",
    "wof:placetype":"postalcode"
},
  "geometry": {"coordinates":[-1.40066518998592,50.9796172530212],"type":"Point"}
}