{
  "type": "Feature",
  "properties": {
    "date:inception_lower": "1994-12-01",
    "date:inception_upper": "1994-12-01",
    "iso:country": "GB",
    "wof:name": "SO53 4RJ",
    "wof:placetype": "postalcode"
  },
  "geometry": {"coordinates":[-1.400665,50.979617],"type":"Point"}
}
