{
  "type": "Feature",
  "properties": {
    "iso:country": "GB",
    "wof:name": "SO53 4RJ",
    "wof:placetype": "postalcode"
  },
  "geometry": {"coordinates":[-1.400665,50.979617],"type":"Point"}
}
