{
  "type": "Feature",
  "properties": {
    "iso:country":"GB",
    "wof:name":"CH49 1RJ",
    "wof:placetype":"postalcode"
},
  "geometry": {"coordinates":[-3.12011622573398,53.37667928325202],"type":"Point"}
}