{
  "type": "Feature",
  "properties": {
    "iso:country": "GB",
    "wof:name": "CH49 1RJ",
    "wof:placetype": "postalcode"
  },
  "geometry": {"coordinates":[-3.120116,53.376679],"type":"Point"}
}
