{
  "type": "Feature",
  "properties": {
    "date:inception_lower": "1990-07-01",
    "date:inception_upper": "1990-07-01",
    "iso:country": "GB",
    "wof:name": "BN43 5AY",
    "wof:placetype": "postalcode"
  },
  "geometry": {"coordinates":[-0.276502,50.835315],"type":"Point"}
}
