{
  "type": "Feature",
  "properties": {
    "iso:country": "GB",
    "wof:name": "MK5 6FR",
    "wof:placetype": "postalcode"
  },
  "geometry": {"coordinates":[-0.806728,52.01894],"type":"Point"}
}
