{
  "type": "Feature",
  "properties": {
    "iso:country":"GB",
    "wof:name":"YO25 8ND",
    "wof:placetype":"postalcode"
},
  "geometry": {"coordinates":[-0.31620091016782,53.96267554819345],"type":"Point"}
}