{
  "type": "Feature",
  "properties": {
    "date:inception_lower": "2023-02-01",
    "date:inception_upper": "2023-02-01",
    "iso:country": "GB",
    "wof:name": "TR14 0GP",
    "wof:placetype": "postalcode"
  },
  "geometry": {"coordinates":[-5.313978,50.194094],"type":"Point"}
}
