{
  "type": "Feature",
  "properties": {
    "iso:country":"GB",
    "wof:name":"CV1 1DG",
    "wof:placetype":"postalcode"
},
  "geometry": {"coordinates":[-1.51369461044791,52.40618008007314],"type":"Point"}
}