{
  "type": "Feature",
  "properties": {
    "iso:country":"GB",
    "wof:name":"IG1 3QP",
    "wof:placetype":"postalcode"
},
  "geometry": {"coordinates":[0.06219135879744,51.5715406912834],"type":"Point"}
}