{
  "type": "Feature",
  "properties": {
    "date:inception_lower": "1980-01-01",
    "date:inception_upper": "1980-01-01",
    "iso:country": "GB",
    "wof:name": "N19 4PX",
    "wof:placetype": "postalcode"
  },
  "geometry": {"coordinates":[-0.131474,51.558023],"type":"Point"}
}
