{
  "type": "Feature",
  "properties": {
    "iso:country":"GB",
    "wof:name":"BA3 3QA",
    "wof:placetype":"postalcode"
},
  "geometry": {"coordinates":[-2.44224722747129,51.29112655956899],"type":"Point"}
}