{
  "type": "Feature",
  "properties": {
    "iso:country":"GB",
    "wof:name":"W10 6QY",
    "wof:placetype":"postalcode"
},
  "geometry": {"coordinates":[-0.22343847259624,51.51734867694307],"type":"Point"}
}