{
  "type": "Feature",
  "properties": {
    "date:inception_lower":"1980-01-01",
    "date:inception_upper":"1980-01-31",
    "iso:country":"GB",
    "wof:name":"W10 6QY",
    "wof:placetype":"postalcode"
},
  "geometry": {"coordinates":[-0.223411,51.517303],"type":"Point"}
}