{
  "type": "Feature",
  "properties": {
    "iso:country":"GB",
    "wof:name":"ML9 2SB",
    "wof:placetype":"postalcode"
},
  "geometry": {"coordinates":[-3.95426906843336,55.73396389747217],"type":"Point"}
}