{
  "type": "Feature",
  "properties": {
    "date:inception_lower": "1990-02-01",
    "date:inception_upper": "1990-02-01",
    "iso:country": "GB",
    "wof:name": "WS3 3XG",
    "wof:placetype": "postalcode"
  },
  "geometry": {"coordinates":[-2.007891,52.628906],"type":"Point"}
}
