{
  "type": "Feature",
  "properties": {
    "iso:country": "GB",
    "wof:name": "WS3 3XG",
    "wof:placetype": "postalcode"
  },
  "geometry": {"coordinates":[-2.007891,52.628906],"type":"Point"}
}
