{
  "type": "Feature",
  "properties": {
    "iso:country":"GB",
    "wof:name":"WS3 3XG",
    "wof:placetype":"postalcode"
},
  "geometry": {"coordinates":[-2.00789061290544,52.62890570549677],"type":"Point"}
}