{
  "type": "Feature",
  "properties": {
    "iso:country":"GB",
    "wof:name":"PE8 5NH",
    "wof:placetype":"postalcode"
},
  "geometry": {"coordinates":[-0.35249573212264,52.46413275385274],"type":"Point"}
}