{
  "type": "Feature",
  "properties": {
    "iso:country": "GB",
    "wof:name": "PE8 5NH",
    "wof:placetype": "postalcode"
  },
  "geometry": {"coordinates":[-0.352496,52.464133],"type":"Point"}
}
