{
  "type": "Feature",
  "properties": {
    "date:inception_lower": "2024-07-01",
    "date:inception_upper": "2024-07-01",
    "iso:country": "GB",
    "wof:name": "IP8 3GE",
    "wof:placetype": "postalcode"
  },
  "geometry": {"coordinates":[1.101272,52.045068],"type":"Point"}
}
