{
  "type": "Feature",
  "properties": {
    "date:inception_lower": "1980-01-01",
    "date:inception_upper": "1980-01-01",
    "iso:country": "GB",
    "wof:name": "SA44 5AA",
    "wof:placetype": "postalcode"
  },
  "geometry": {"coordinates":[-4.329699,52.017492],"type":"Point"}
}
