{
  "type": "Feature",
  "properties": {
    "iso:country": "GB",
    "wof:name": "TD5 7AZ",
    "wof:placetype": "postalcode"
  },
  "geometry": {"coordinates":[-2.43137,55.598906],"type":"Point"}
}
