{
  "type": "Feature",
  "properties": {
    "iso:country":"GB",
    "wof:name":"EN2 8DG",
    "wof:placetype":"postalcode"
},
  "geometry": {"coordinates":[-0.09114831021828,51.65557078318164],"type":"Point"}
}