{
  "type": "Feature",
  "properties": {
    "iso:country":"GB",
    "wof:name":"TQ9 6AT",
    "wof:placetype":"postalcode"
},
  "geometry": {"coordinates":[-3.69213451763174,50.47551198325368],"type":"Point"}
}