{
  "type": "Feature",
  "properties": {
    "iso:country": "GB",
    "wof:name": "TQ9 6AT",
    "wof:placetype": "postalcode"
  },
  "geometry": {"coordinates":[-3.692408,50.47554],"type":"Point"}
}
