{
  "type": "Feature",
  "properties": {
    "iso:country":"GB",
    "wof:name":"LN6 9AZ",
    "wof:placetype":"postalcode"
},
  "geometry": {"coordinates":[-0.5916224449275,53.18256860751705],"type":"Point"}
}