{
  "type": "Feature",
  "properties": {
    "date:inception_lower": "1990-07-01",
    "date:inception_upper": "1990-07-01",
    "iso:country": "GB",
    "wof:name": "LN6 9AZ",
    "wof:placetype": "postalcode"
  },
  "geometry": {"coordinates":[-0.591622,53.182569],"type":"Point"}
}
