{
  "type": "Feature",
  "properties": {
    "iso:country":"GB",
    "wof:name":"SY6 7HD",
    "wof:placetype":"postalcode"
},
  "geometry": {"coordinates":[-2.77209283622944,52.51944315220499],"type":"Point"}
}