{
  "type": "Feature",
  "properties": {
    "iso:country":"GB",
    "wof:name":"WF8 4DY",
    "wof:placetype":"postalcode"
},
  "geometry": {"coordinates":[-1.32065696496526,53.68844699846243],"type":"Point"}
}