{
  "type": "Feature",
  "properties": {
    "date:inception_lower": "1980-01-01",
    "date:inception_upper": "1980-01-01",
    "iso:country": "GB",
    "wof:name": "TF9 4PT",
    "wof:placetype": "postalcode"
  },
  "geometry": {"coordinates":[-2.377872,52.9226],"type":"Point"}
}
