{
  "type": "Feature",
  "properties": {
    "iso:country":"GB",
    "wof:name":"TF9 4PT",
    "wof:placetype":"postalcode"
},
  "geometry": {"coordinates":[-2.37784292619232,52.92259386444164],"type":"Point"}
}