{
  "type": "Feature",
  "properties": {
    "iso:country": "GB",
    "wof:name": "B66 3QR",
    "wof:placetype": "postalcode"
  },
  "geometry": {"coordinates":[-1.959983,52.493297],"type":"Point"}
}
