{
  "type": "Feature",
  "properties": {
    "iso:country": "GB",
    "wof:name": "DL12 0DN",
    "wof:placetype": "postalcode"
  },
  "geometry": {"coordinates":[-1.965788,54.603715],"type":"Point"}
}
