{
  "type": "Feature",
  "properties": {
    "iso:country":"GB",
    "wof:name":"DL12 0DN",
    "wof:placetype":"postalcode"
},
  "geometry": {"coordinates":[-1.96578756308499,54.60371468133721],"type":"Point"}
}