{
  "type": "Feature",
  "properties": {
    "iso:country":"GB",
    "wof:name":"HS7 5LH",
    "wof:placetype":"postalcode"
},
  "geometry": {"coordinates":[-7.38845938739065,57.4730641014233],"type":"Point"}
}