{
  "type": "Feature",
  "properties": {
    "iso:country":"GB",
    "wof:name":"S9 3TW",
    "wof:placetype":"postalcode"
},
  "geometry": {"coordinates":[-1.43039730472278,53.39478123751902],"type":"Point"}
}