{
  "type": "Feature",
  "properties": {
    "iso:country": "GB",
    "wof:name": "DL1 2YA",
    "wof:placetype": "postalcode"
  },
  "geometry": {"coordinates":[-1.54296,54.544659],"type":"Point"}
}
