{
  "type": "Feature",
  "properties": {
    "iso:country":"GB",
    "wof:name":"B16 8DJ",
    "wof:placetype":"postalcode"
},
  "geometry": {"coordinates":[-1.92593996618006,52.47892337117351],"type":"Point"}
}