{
  "type": "Feature",
  "properties": {
    "date:inception_lower":"1980-01-01",
    "date:inception_upper":"1980-01-31",
    "iso:country":"GB",
    "wof:name":"B16 8DJ",
    "wof:placetype":"postalcode"
},
  "geometry": {"coordinates":[-1.92594,52.478923],"type":"Point"}
}