{
  "type": "Feature",
  "properties": {
    "iso:country": "GB",
    "wof:name": "HP2 5YS",
    "wof:placetype": "postalcode"
  },
  "geometry": {"coordinates":[-0.47047,51.764117],"type":"Point"}
}
