{
  "type": "Feature",
  "properties": {
    "date:inception_lower": "1991-01-01",
    "date:inception_upper": "1991-01-01",
    "iso:country": "GB",
    "wof:name": "HP2 5YS",
    "wof:placetype": "postalcode"
  },
  "geometry": {"coordinates":[-0.47047,51.764117],"type":"Point"}
}
