{
  "type": "Feature",
  "properties": {
    "iso:country":"GB",
    "wof:name":"DA3 7NP",
    "wof:placetype":"postalcode"
},
  "geometry": {"coordinates":[0.32331092924011,51.39677091292311],"type":"Point"}
}