{
  "type": "Feature",
  "properties": {
    "iso:country":"GB",
    "wof:name":"KA21 6DY",
    "wof:placetype":"postalcode"
},
  "geometry": {"coordinates":[-4.77781900474306,55.64975835239143],"type":"Point"}
}