{
  "type": "Feature",
  "properties": {
    "date:inception_lower": "1980-01-01",
    "date:inception_upper": "1980-01-01",
    "iso:country": "GB",
    "wof:name": "TS7 9DA",
    "wof:placetype": "postalcode"
  },
  "geometry": {"coordinates":[-1.176325,54.544013],"type":"Point"}
}
