{
  "type": "Feature",
  "properties": {
    "iso:country": "GB",
    "wof:name": "BN8 6BN",
    "wof:placetype": "postalcode"
  },
  "geometry": {"coordinates":[0.150509,50.893843],"type":"Point"}
}
