{
  "type": "Feature",
  "properties": {
    "iso:country":"GB",
    "wof:name":"BN8 6BN",
    "wof:placetype":"postalcode"
},
  "geometry": {"coordinates":[0.15050868120619,50.89384339023446],"type":"Point"}
}