{
  "type": "Feature",
  "properties": {
    "iso:country": "GB",
    "wof:name": "SO21 2JW",
    "wof:placetype": "postalcode"
  },
  "geometry": {"coordinates":[-1.39268,51.027199],"type":"Point"}
}
