{
  "type": "Feature",
  "properties": {
    "iso:country":"GB",
    "wof:name":"SO21 2JW",
    "wof:placetype":"postalcode"
},
  "geometry": {"coordinates":[-1.39268000721681,51.02719944251455],"type":"Point"}
}