{
  "type": "Feature",
  "properties": {
    "date:inception_lower":"2009-11-01",
    "date:inception_upper":"2009-11-30",
    "iso:country":"GB",
    "wof:name":"HS2 9NG",
    "wof:placetype":"postalcode"
},
  "geometry": {"coordinates":[-6.45543,58.142926],"type":"Point"}
}