{
  "type": "Feature",
  "properties": {
    "iso:country": "GB",
    "wof:name": "HS2 9NG",
    "wof:placetype": "postalcode"
  },
  "geometry": {"coordinates":[-6.45543,58.142926],"type":"Point"}
}
