{
  "type": "Feature",
  "properties": {
    "iso:country":"GB",
    "wof:name":"CM6 1RD",
    "wof:placetype":"postalcode"
},
  "geometry": {"coordinates":[0.29865314399953,51.79387395773393],"type":"Point"}
}