{
  "type": "Feature",
  "properties": {
    "iso:country": "GB",
    "wof:name": "PE25 2HN",
    "wof:placetype": "postalcode"
  },
  "geometry": {"coordinates":[0.325166,53.147899],"type":"Point"}
}
