{
  "type": "Feature",
  "properties": {
    "date:inception_lower": "2006-07-01",
    "date:inception_upper": "2006-07-01",
    "iso:country": "GB",
    "wof:name": "OL11 5HG",
    "wof:placetype": "postalcode"
  },
  "geometry": {"coordinates":[-2.200276,53.611027],"type":"Point"}
}
