{
  "type": "Feature",
  "properties": {
    "iso:country": "GB",
    "wof:name": "OL11 5HG",
    "wof:placetype": "postalcode"
  },
  "geometry": {"coordinates":[-2.200276,53.611027],"type":"Point"}
}
