{
  "type": "Feature",
  "properties": {
    "iso:country":"GB",
    "wof:name":"TN15 8FJ",
    "wof:placetype":"postalcode"
},
  "geometry": {"coordinates":[0.2998464078733,51.28774056383001],"type":"Point"}
}