{
  "type": "Feature",
  "properties": {
    "date:inception_lower": "2014-11-01",
    "date:inception_upper": "2014-11-01",
    "iso:country": "GB",
    "wof:name": "TN15 8FJ",
    "wof:placetype": "postalcode"
  },
  "geometry": {"coordinates":[0.299989,51.287729],"type":"Point"}
}
