{
  "type": "Feature",
  "properties": {
    "iso:country":"GB",
    "wof:name":"NG34 9BS",
    "wof:placetype":"postalcode"
},
  "geometry": {"coordinates":[-0.38620152169775,53.04159813502198],"type":"Point"}
}