{
  "type": "Feature",
  "properties": {
    "iso:country":"GB",
    "wof:name":"MK16 8NP",
    "wof:placetype":"postalcode"
},
  "geometry": {"coordinates":[-0.7778110327205,52.13025034625095],"type":"Point"}
}