{
  "type": "Feature",
  "properties": {
    "date:inception_lower":"1980-01-01",
    "date:inception_upper":"1980-01-31",
    "iso:country":"GB",
    "wof:name":"MK16 8NP",
    "wof:placetype":"postalcode"
},
  "geometry": {"coordinates":[-0.777375,52.129997],"type":"Point"}
}