{
  "type": "Feature",
  "properties": {
    "iso:country": "GB",
    "wof:name": "TN21 0FW",
    "wof:placetype": "postalcode"
  },
  "geometry": {"coordinates":[0.224572,50.967576],"type":"Point"}
}
