{
  "type": "Feature",
  "properties": {
    "date:inception_lower":"1980-01-01",
    "date:inception_upper":"1980-01-31",
    "iso:country":"GB",
    "wof:name":"SY15 6LN",
    "wof:placetype":"postalcode"
},
  "geometry": {"coordinates":[-3.192081,52.544079],"type":"Point"}
}