{
  "type": "Feature",
  "properties": {
    "iso:country": "GB",
    "wof:name": "SY15 6LN",
    "wof:placetype": "postalcode"
  },
  "geometry": {"coordinates":[-3.192081,52.544079],"type":"Point"}
}
