{
  "type": "Feature",
  "properties": {
    "iso:country": "GB",
    "wof:name": "NR21 8BB",
    "wof:placetype": "postalcode"
  },
  "geometry": {"coordinates":[0.854611,52.830226],"type":"Point"}
}
