{
  "type": "Feature",
  "properties": {
    "iso:country": "GB",
    "wof:name": "NR19 2TU",
    "wof:placetype": "postalcode"
  },
  "geometry": {"coordinates":[0.927274,52.677568],"type":"Point"}
}
