{
  "type": "Feature",
  "properties": {
    "iso:country":"GB",
    "wof:name":"ST5 9LY",
    "wof:placetype":"postalcode"
},
  "geometry": {"coordinates":[-2.21780590671233,53.02430386940279],"type":"Point"}
}