{
  "type": "Feature",
  "properties": {
    "iso:country": "GB",
    "wof:name": "ST5 9LY",
    "wof:placetype": "postalcode"
  },
  "geometry": {"coordinates":[-2.217806,53.024304],"type":"Point"}
}
