{
  "type": "Feature",
  "properties": {
    "iso:country": "GB",
    "wof:name": "DN3 3AH",
    "wof:placetype": "postalcode"
  },
  "geometry": {"coordinates":[-1.05856,53.53643],"type":"Point"}
}
