{
  "type": "Feature",
  "properties": {
    "iso:country":"GB",
    "wof:name":"DN3 3AH",
    "wof:placetype":"postalcode"
},
  "geometry": {"coordinates":[-1.0585602824565,53.53642994804408],"type":"Point"}
}