{
  "type": "Feature",
  "properties": {
    "iso:country":"GB",
    "wof:name":"NR7 8AZ",
    "wof:placetype":"postalcode"
},
  "geometry": {"coordinates":[1.32448802119134,52.66248779324818],"type":"Point"}
}