{
  "type": "Feature",
  "properties": {
    "iso:country": "GB",
    "wof:name": "BA20 2FQ",
    "wof:placetype": "postalcode"
  },
  "geometry": {"coordinates":[-2.644812,50.941289],"type":"Point"}
}
