{
  "type": "Feature",
  "properties": {
    "date:inception_lower":"2007-07-01",
    "date:inception_upper":"2007-07-31",
    "iso:country":"GB",
    "wof:name":"BA20 2FQ",
    "wof:placetype":"postalcode"
},
  "geometry": {"coordinates":[-2.644812,50.941289],"type":"Point"}
}