{
  "type": "Feature",
  "properties": {
    "date:inception_lower": "1980-01-01",
    "date:inception_upper": "1980-01-01",
    "iso:country": "GB",
    "wof:name": "SA16 0LG",
    "wof:placetype": "postalcode"
  },
  "geometry": {"coordinates":[-4.250861,51.6855],"type":"Point"}
}
