{
  "type": "Feature",
  "properties": {
    "iso:country":"GB",
    "wof:name":"SA16 0LG",
    "wof:placetype":"postalcode"
},
  "geometry": {"coordinates":[-4.25085955830024,51.68546441395827],"type":"Point"}
}