{
  "type": "Feature",
  "properties": {
    "iso:country": "GB",
    "wof:name": "SA16 0LG",
    "wof:placetype": "postalcode"
  },
  "geometry": {"coordinates":[-4.250861,51.6855],"type":"Point"}
}
