{
  "type": "Feature",
  "properties": {
    "iso:country": "GB",
    "wof:name": "CT2 9BT",
    "wof:placetype": "postalcode"
  },
  "geometry": {"coordinates":[1.04754,51.288448],"type":"Point"}
}
