{
  "type": "Feature",
  "properties": {
    "date:inception_lower": "1980-01-01",
    "date:inception_upper": "1980-01-01",
    "iso:country": "GB",
    "wof:name": "CT2 9BT",
    "wof:placetype": "postalcode"
  },
  "geometry": {"coordinates":[1.04754,51.288448],"type":"Point"}
}
