{
  "type": "Feature",
  "properties": {
    "iso:country":"GB",
    "wof:name":"CT2 9BT",
    "wof:placetype":"postalcode"
},
  "geometry": {"coordinates":[1.0475394583629,51.28844799366449],"type":"Point"}
}