{
  "type": "Feature",
  "properties": {
    "iso:country":"GB",
    "wof:name":"CV6 3GG",
    "wof:placetype":"postalcode"
},
  "geometry": {"coordinates":[-1.51649533862572,52.42429769921845],"type":"Point"}
}