{
  "type": "Feature",
  "properties": {
    "iso:country":"GB",
    "wof:name":"IV22 2HE",
    "wof:placetype":"postalcode"
},
  "geometry": {"coordinates":[-5.68816087469388,57.57959390061328],"type":"Point"}
}