{
  "type": "Feature",
  "properties": {
    "date:inception_lower":"1980-01-01",
    "date:inception_upper":"1980-01-31",
    "iso:country":"GB",
    "wof:name":"CO4 3YP",
    "wof:placetype":"postalcode"
},
  "geometry": {"coordinates":[0.938172,51.885058],"type":"Point"}
}