{
  "type": "Feature",
  "properties": {
    "iso:country":"GB",
    "wof:name":"CO4 3YP",
    "wof:placetype":"postalcode"
},
  "geometry": {"coordinates":[0.93817192330487,51.88505755497238],"type":"Point"}
}