{
  "type": "Feature",
  "properties": {
    "iso:country": "GB",
    "wof:name": "KY16 8XP",
    "wof:placetype": "postalcode"
  },
  "geometry": {"coordinates":[-2.821156,56.327491],"type":"Point"}
}
