{
  "type": "Feature",
  "properties": {
    "date:inception_lower":"1983-07-01",
    "date:inception_upper":"1983-07-31",
    "iso:country":"GB",
    "wof:name":"TN11 9RX",
    "wof:placetype":"postalcode"
},
  "geometry": {"coordinates":[0.30199,51.242839],"type":"Point"}
}