{
  "type": "Feature",
  "properties": {
    "iso:country":"GB",
    "wof:name":"TN11 9RX",
    "wof:placetype":"postalcode"
},
  "geometry": {"coordinates":[0.30199001816252,51.24283936762323],"type":"Point"}
}