{
  "type": "Feature",
  "properties": {
    "date:inception_lower":"2004-01-01",
    "date:inception_upper":"2004-01-31",
    "iso:country":"GB",
    "wof:name":"WA3 3GS",
    "wof:placetype":"postalcode"
},
  "geometry": {"coordinates":[-2.595867,53.478431],"type":"Point"}
}