{
  "type": "Feature",
  "properties": {
    "date:inception_lower":"2008-10-01",
    "date:inception_upper":"2008-10-31",
    "iso:country":"GB",
    "wof:name":"M29 8QT",
    "wof:placetype":"postalcode"
},
  "geometry": {"coordinates":[-2.438173,53.513776],"type":"Point"}
}