{
  "type": "Feature",
  "properties": {
    "iso:country": "GB",
    "wof:name": "NE19 2DP",
    "wof:placetype": "postalcode"
  },
  "geometry": {"coordinates":[-1.925951,55.099112],"type":"Point"}
}
