{
  "type": "Feature",
  "properties": {
    "iso:country":"GB",
    "wof:name":"DY7 6LJ",
    "wof:placetype":"postalcode"
},
  "geometry": {"coordinates":[-2.22366933166901,52.45001141926343],"type":"Point"}
}