{
  "type": "Feature",
  "properties": {
    "iso:country":"GB",
    "wof:name":"M20 6LB",
    "wof:placetype":"postalcode"
},
  "geometry": {"coordinates":[-2.2213978300546,53.41571665982214],"type":"Point"}
}