{
  "type": "Feature",
  "properties": {
    "iso:country": "GB",
    "wof:name": "TS22 5FA",
    "wof:placetype": "postalcode"
  },
  "geometry": {"coordinates":[-1.325505,54.63976],"type":"Point"}
}
