{
  "type": "Feature",
  "properties": {
    "iso:country":"GB",
    "wof:name":"CM4 9NS",
    "wof:placetype":"postalcode"
},
  "geometry": {"coordinates":[0.38914560057051,51.66147405238264],"type":"Point"}
}