{
  "type": "Feature",
  "properties": {
    "date:inception_lower": "1980-01-01",
    "date:inception_upper": "1980-01-01",
    "iso:country": "GB",
    "wof:name": "CM4 9NS",
    "wof:placetype": "postalcode"
  },
  "geometry": {"coordinates":[0.389155,51.661415],"type":"Point"}
}
