{
  "type": "Feature",
  "properties": {
    "date:inception_lower": "1991-07-01",
    "date:inception_upper": "1991-07-01",
    "iso:country": "GB",
    "wof:name": "PA5 8JR",
    "wof:placetype": "postalcode"
  },
  "geometry": {"coordinates":[-4.505483,55.832611],"type":"Point"}
}
