{
  "type": "Feature",
  "properties": {
    "iso:country": "GB",
    "wof:name": "YO7 4LX",
    "wof:placetype": "postalcode"
  },
  "geometry": {"coordinates":[-1.376872,54.227935],"type":"Point"}
}
