{
  "type": "Feature",
  "properties": {
    "iso:country":"GB",
    "wof:name":"CO5 9EZ",
    "wof:placetype":"postalcode"
},
  "geometry": {"coordinates":[0.76070232799409,51.85771009187879],"type":"Point"}
}