{
  "type": "Feature",
  "properties": {
    "iso:country":"GB",
    "wof:name":"WF7 6DN",
    "wof:placetype":"postalcode"
},
  "geometry": {"coordinates":[-1.40466544183139,53.6768315376852],"type":"Point"}
}