{
  "type": "Feature",
  "properties": {
    "iso:country":"GB",
    "wof:name":"BN13 2LT",
    "wof:placetype":"postalcode"
},
  "geometry": {"coordinates":[-0.40665036963242,50.83604939594652],"type":"Point"}
}