{
  "type": "Feature",
  "properties": {
    "iso:country": "GB",
    "wof:name": "NE43 7BX",
    "wof:placetype": "postalcode"
  },
  "geometry": {"coordinates":[-1.884233,54.955099],"type":"Point"}
}
