{
  "type": "Feature",
  "properties": {
    "iso:country":"GB",
    "wof:name":"PL5 4BL",
    "wof:placetype":"postalcode"
},
  "geometry": {"coordinates":[-4.14788196792943,50.4155806477473],"type":"Point"}
}