{
  "type": "Feature",
  "properties": {
    "iso:country":"GB",
    "wof:name":"W3 8RJ",
    "wof:placetype":"postalcode"
},
  "geometry": {"coordinates":[-0.27675560890957,51.50122945003375],"type":"Point"}
}