{
  "type": "Feature",
  "properties": {
    "iso:country":"GB",
    "wof:name":"DL1 5BG",
    "wof:placetype":"postalcode"
},
  "geometry": {"coordinates":[-1.54908356232792,54.51215791693824],"type":"Point"}
}