{
  "type": "Feature",
  "properties": {
    "iso:country": "GB",
    "wof:name": "DL1 5BG",
    "wof:placetype": "postalcode"
  },
  "geometry": {"coordinates":[-1.549084,54.512158],"type":"Point"}
}
