{
  "type": "Feature",
  "properties": {
    "iso:country":"GB",
    "wof:name":"NE47 9QP",
    "wof:placetype":"postalcode"
},
  "geometry": {"coordinates":[-2.26883055048126,54.91381573092401],"type":"Point"}
}