{
  "type": "Feature",
  "properties": {
    "date:inception_lower":"1980-01-01",
    "date:inception_upper":"1980-01-31",
    "iso:country":"GB",
    "wof:name":"NE47 9QP",
    "wof:placetype":"postalcode"
},
  "geometry": {"coordinates":[-2.26883,54.913816],"type":"Point"}
}