{
  "type": "Feature",
  "properties": {
    "iso:country": "GB",
    "wof:name": "IV11 8XJ",
    "wof:placetype": "postalcode"
  },
  "geometry": {"coordinates":[-4.025695,57.678537],"type":"Point"}
}
