{
  "type": "Feature",
  "properties": {
    "iso:country":"GB",
    "wof:name":"EN10 7HA",
    "wof:placetype":"postalcode"
},
  "geometry": {"coordinates":[-0.02637036299571,51.74324574651986],"type":"Point"}
}