{
  "type": "Feature",
  "properties": {
    "iso:country":"GB",
    "wof:name":"TA23 0BE",
    "wof:placetype":"postalcode"
},
  "geometry": {"coordinates":[-3.33320801292317,51.18132565842125],"type":"Point"}
}