{
  "type": "Feature",
  "properties": {
    "iso:country":"GB",
    "wof:name":"CF43 4SX",
    "wof:placetype":"postalcode"
},
  "geometry": {"coordinates":[-3.46101237270717,51.66680015944632],"type":"Point"}
}