{
  "type": "Feature",
  "properties": {
    "iso:country": "GB",
    "wof:name": "CF43 4SX",
    "wof:placetype": "postalcode"
  },
  "geometry": {"coordinates":[-3.462004,51.667169],"type":"Point"}
}
