{
  "type": "Feature",
  "properties": {
    "date:inception_lower":"1990-02-01",
    "date:inception_upper":"1990-02-28",
    "iso:country":"GB",
    "wof:name":"CF43 4SX",
    "wof:placetype":"postalcode"
},
  "geometry": {"coordinates":[-3.462004,51.667169],"type":"Point"}
}