{
  "type": "Feature",
  "properties": {
    "date:inception_lower": "2016-05-01",
    "date:inception_upper": "2016-05-01",
    "iso:country": "GB",
    "wof:name": "NW10 0UP",
    "wof:placetype": "postalcode"
  },
  "geometry": {"coordinates":[-0.265011,51.557025],"type":"Point"}
}
