{
  "type": "Feature",
  "properties": {
    "iso:country": "GB",
    "wof:name": "NW10 0UP",
    "wof:placetype": "postalcode"
  },
  "geometry": {"coordinates":[-0.265011,51.557025],"type":"Point"}
}
