{
  "type": "Feature",
  "properties": {
    "iso:country":"GB",
    "wof:name":"LU3 1LE",
    "wof:placetype":"postalcode"
},
  "geometry": {"coordinates":[-0.4215812897833,51.88975976540552],"type":"Point"}
}