{
  "type": "Feature",
  "properties": {
    "iso:country":"GB",
    "wof:name":"DY9 8EH",
    "wof:placetype":"postalcode"
},
  "geometry": {"coordinates":[-2.11333845226623,52.45971622186912],"type":"Point"}
}