{
  "type": "Feature",
  "properties": {
    "date:inception_lower": "1980-01-01",
    "date:inception_upper": "1980-01-01",
    "iso:country": "GB",
    "wof:name": "DY9 8EH",
    "wof:placetype": "postalcode"
  },
  "geometry": {"coordinates":[-2.115039,52.459702],"type":"Point"}
}
