{
  "type": "Feature",
  "properties": {
    "iso:country":"GB",
    "wof:name":"S8 7LN",
    "wof:placetype":"postalcode"
},
  "geometry": {"coordinates":[-1.48129390900687,53.32110776816548],"type":"Point"}
}