{
  "type": "Feature",
  "properties": {
    "iso:country": "GB",
    "wof:name": "S8 7LN",
    "wof:placetype": "postalcode"
  },
  "geometry": {"coordinates":[-1.480885,53.321322],"type":"Point"}
}
