{
  "type": "Feature",
  "properties": {
    "iso:country":"GB",
    "wof:name":"AL10 8JX",
    "wof:placetype":"postalcode"
},
  "geometry": {"coordinates":[-0.23110018591667,51.7477916709814],"type":"Point"}
}