{
  "type": "Feature",
  "properties": {
    "iso:country": "GB",
    "wof:name": "AL10 8JX",
    "wof:placetype": "postalcode"
  },
  "geometry": {"coordinates":[-0.2311,51.747792],"type":"Point"}
}
