{
  "type": "Feature",
  "properties": {
    "iso:country":"GB",
    "wof:name":"AL5 2EE",
    "wof:placetype":"postalcode"
},
  "geometry": {"coordinates":[-0.36888064194098,51.81609974391754],"type":"Point"}
}