{
  "type": "Feature",
  "properties": {
    "iso:country": "GB",
    "wof:name": "NN6 9HR",
    "wof:placetype": "postalcode"
  },
  "geometry": {"coordinates":[-0.849359,52.350893],"type":"Point"}
}
