{
  "type": "Feature",
  "properties": {
    "iso:country":"GB",
    "wof:name":"NN6 9HR",
    "wof:placetype":"postalcode"
},
  "geometry": {"coordinates":[-0.84935865754398,52.35089340047771],"type":"Point"}
}