{
  "type": "Feature",
  "properties": {
    "date:inception_lower": "1993-08-01",
    "date:inception_upper": "1993-08-01",
    "iso:country": "GB",
    "wof:name": "NN6 9HR",
    "wof:placetype": "postalcode"
  },
  "geometry": {"coordinates":[-0.849359,52.350893],"type":"Point"}
}
