{
  "type": "Feature",
  "properties": {
    "iso:country":"GB",
    "wof:name":"S71 1QP",
    "wof:placetype":"postalcode"
},
  "geometry": {"coordinates":[-1.4795847107411,53.56497899473913],"type":"Point"}
}