{
  "type": "Feature",
  "properties": {
    "iso:country": "GB",
    "wof:name": "ST16 2ND",
    "wof:placetype": "postalcode"
  },
  "geometry": {"coordinates":[-2.113796,52.806791],"type":"Point"}
}
