{
  "type": "Feature",
  "properties": {
    "date:inception_lower": "2002-06-01",
    "date:inception_upper": "2002-06-01",
    "iso:country": "GB",
    "wof:name": "PO19 7EZ",
    "wof:placetype": "postalcode"
  },
  "geometry": {"coordinates":[-0.758515,50.835899],"type":"Point"}
}
