{
  "type": "Feature",
  "properties": {
    "iso:country":"GB",
    "wof:name":"PO19 7EZ",
    "wof:placetype":"postalcode"
},
  "geometry": {"coordinates":[-0.75851470673229,50.8358986370578],"type":"Point"}
}