{
  "type": "Feature",
  "properties": {
    "date:inception_lower": "2009-11-01",
    "date:inception_upper": "2009-11-01",
    "iso:country": "GB",
    "wof:name": "PO21 3DN",
    "wof:placetype": "postalcode"
  },
  "geometry": {"coordinates":[-0.723033,50.787197],"type":"Point"}
}
