{
  "type": "Feature",
  "properties": {
    "iso:country":"GB",
    "wof:name":"SA48 7PG",
    "wof:placetype":"postalcode"
},
  "geometry": {"coordinates":[-4.1597676180709,52.18169019099074],"type":"Point"}
}