{
  "type": "Feature",
  "properties": {
    "iso:country": "GB",
    "wof:name": "SA48 7PG",
    "wof:placetype": "postalcode"
  },
  "geometry": {"coordinates":[-4.159768,52.18169],"type":"Point"}
}
