{
  "type": "Feature",
  "properties": {
    "date:inception_lower": "1980-01-01",
    "date:inception_upper": "1980-01-01",
    "iso:country": "GB",
    "wof:name": "OX12 7JE",
    "wof:placetype": "postalcode"
  },
  "geometry": {"coordinates":[-1.421316,51.605404],"type":"Point"}
}
