{
  "type": "Feature",
  "properties": {
    "iso:country": "GB",
    "wof:name": "OX12 7JE",
    "wof:placetype": "postalcode"
  },
  "geometry": {"coordinates":[-1.421316,51.605404],"type":"Point"}
}
