{
  "type": "Feature",
  "properties": {
    "date:inception_lower": "1980-01-01",
    "date:inception_upper": "1980-01-01",
    "iso:country": "GB",
    "wof:name": "ME10 1XP",
    "wof:placetype": "postalcode"
  },
  "geometry": {"coordinates":[0.720451,51.344332],"type":"Point"}
}
