{
  "type": "Feature",
  "properties": {
    "iso:country": "GB",
    "wof:name": "HU17 0QF",
    "wof:placetype": "postalcode"
  },
  "geometry": {"coordinates":[-0.415774,53.840694],"type":"Point"}
}
