{
  "type": "Feature",
  "properties": {
    "date:inception_lower":"1987-04-01",
    "date:inception_upper":"1987-04-30",
    "iso:country":"GB",
    "wof:name":"HU17 0QF",
    "wof:placetype":"postalcode"
},
  "geometry": {"coordinates":[-0.415774,53.840694],"type":"Point"}
}