{
  "type": "Feature",
  "properties": {
    "date:inception_lower": "2017-09-01",
    "date:inception_upper": "2017-09-01",
    "iso:country": "GB",
    "wof:name": "HP9 2FQ",
    "wof:placetype": "postalcode"
  },
  "geometry": {"coordinates":[-0.633578,51.601651],"type":"Point"}
}
