{
  "type": "Feature",
  "properties": {
    "iso:country":"GB",
    "wof:name":"NW7 2HP",
    "wof:placetype":"postalcode"
},
  "geometry": {"coordinates":[-0.21916662294138,51.61055252875754],"type":"Point"}
}