{
  "type": "Feature",
  "properties": {
    "date:inception_lower": "1980-01-01",
    "date:inception_upper": "1980-01-01",
    "iso:country": "GB",
    "wof:name": "CT15 4ES",
    "wof:placetype": "postalcode"
  },
  "geometry": {"coordinates":[1.258258,51.20776],"type":"Point"}
}
