{
  "type": "Feature",
  "properties": {
    "iso:country":"GB",
    "wof:name":"CT15 4ES",
    "wof:placetype":"postalcode"
},
  "geometry": {"coordinates":[1.25825830853585,51.20775977456137],"type":"Point"}
}