{
  "type": "Feature",
  "properties": {
    "iso:country":"GB",
    "wof:name":"SA70 8SU",
    "wof:placetype":"postalcode"
},
  "geometry": {"coordinates":[-4.82480283678056,51.68969421060752],"type":"Point"}
}