{
  "type": "Feature",
  "properties": {
    "iso:country": "GB",
    "wof:name": "SA70 8SU",
    "wof:placetype": "postalcode"
  },
  "geometry": {"coordinates":[-4.824803,51.689694],"type":"Point"}
}
