{
  "type": "Feature",
  "properties": {
    "iso:country":"GB",
    "wof:name":"DN37 8JT",
    "wof:placetype":"postalcode"
},
  "geometry": {"coordinates":[-0.27386669369069,53.56438210932475],"type":"Point"}
}