{
  "type": "Feature",
  "properties": {
    "iso:country": "GB",
    "wof:name": "DN37 8JT",
    "wof:placetype": "postalcode"
  },
  "geometry": {"coordinates":[-0.273867,53.564382],"type":"Point"}
}
