{
  "type": "Feature",
  "properties": {
    "date:inception_lower": "1980-01-01",
    "date:inception_upper": "1980-01-01",
    "iso:country": "GB",
    "wof:name": "TD9 9BL",
    "wof:placetype": "postalcode"
  },
  "geometry": {"coordinates":[-2.785476,55.424173],"type":"Point"}
}
