{
  "type": "Feature",
  "properties": {
    "date:inception_lower":"1980-01-01",
    "date:inception_upper":"1980-01-31",
    "iso:country":"GB",
    "wof:name":"SW9 9LQ",
    "wof:placetype":"postalcode"
},
  "geometry": {"coordinates":[-0.124659,51.46665],"type":"Point"}
}