{
  "type": "Feature",
  "properties": {
    "iso:country":"GB",
    "wof:name":"SW9 9LQ",
    "wof:placetype":"postalcode"
},
  "geometry": {"coordinates":[-0.12468494944065,51.46664905532851],"type":"Point"}
}