{
  "type": "Feature",
  "properties": {
    "iso:country": "GB",
    "wof:name": "SW9 9LQ",
    "wof:placetype": "postalcode"
  },
  "geometry": {"coordinates":[-0.124659,51.46665],"type":"Point"}
}
