{
  "type": "Feature",
  "properties": {
    "date:inception_lower": "2002-10-01",
    "date:inception_upper": "2002-10-01",
    "iso:country": "GB",
    "wof:name": "B33 8QJ",
    "wof:placetype": "postalcode"
  },
  "geometry": {"coordinates":[-1.813163,52.477262],"type":"Point"}
}
