{
  "type": "Feature",
  "properties": {
    "iso:country":"GB",
    "wof:name":"B33 8QJ",
    "wof:placetype":"postalcode"
},
  "geometry": {"coordinates":[-1.81316307176271,52.47726199526359],"type":"Point"}
}