{
  "type": "Feature",
  "properties": {
    "iso:country":"GB",
    "wof:name":"ME9 7UB",
    "wof:placetype":"postalcode"
},
  "geometry": {"coordinates":[0.64283063782056,51.32787771620544],"type":"Point"}
}