{
  "type": "Feature",
  "properties": {
    "iso:country": "GB",
    "wof:name": "NG22 8UW",
    "wof:placetype": "postalcode"
  },
  "geometry": {"coordinates":[-1.029115,53.140552],"type":"Point"}
}
