{
  "type": "Feature",
  "properties": {
    "iso:country":"GB",
    "wof:name":"NG22 8UW",
    "wof:placetype":"postalcode"
},
  "geometry": {"coordinates":[-1.02911518980543,53.14055186783902],"type":"Point"}
}