{
  "type": "Feature",
  "properties": {
    "date:inception_lower":"2013-09-01",
    "date:inception_upper":"2013-09-30",
    "iso:country":"GB",
    "wof:name":"NG22 8UW",
    "wof:placetype":"postalcode"
},
  "geometry": {"coordinates":[-1.029115,53.140552],"type":"Point"}
}