{
  "type": "Feature",
  "properties": {
    "iso:country":"GB",
    "wof:name":"BD11 1HU",
    "wof:placetype":"postalcode"
},
  "geometry": {"coordinates":[-1.65923540114558,53.74954208939014],"type":"Point"}
}