{
  "type": "Feature",
  "properties": {
    "date:inception_lower":"1980-01-01",
    "date:inception_upper":"1980-01-31",
    "iso:country":"GB",
    "wof:name":"BD11 1HU",
    "wof:placetype":"postalcode"
},
  "geometry": {"coordinates":[-1.659235,53.749542],"type":"Point"}
}