{
  "type": "Feature",
  "properties": {
    "iso:country": "GB",
    "wof:name": "BD11 1HU",
    "wof:placetype": "postalcode"
  },
  "geometry": {"coordinates":[-1.659235,53.749542],"type":"Point"}
}
