{
  "type": "Feature",
  "properties": {
    "iso:country":"GB",
    "wof:name":"PA34 4SZ",
    "wof:placetype":"postalcode"
},
  "geometry": {"coordinates":[-5.61497599027489,56.20733680827231],"type":"Point"}
}