{
  "type": "Feature",
  "properties": {
    "date:inception_lower":"1992-08-01",
    "date:inception_upper":"1992-08-31",
    "iso:country":"GB",
    "wof:name":"B63 3HR",
    "wof:placetype":"postalcode"
},
  "geometry": {"coordinates":[-2.050486,52.451588],"type":"Point"}
}