{
  "type": "Feature",
  "properties": {
    "iso:country":"GB",
    "wof:name":"NG23 6LN",
    "wof:placetype":"postalcode"
},
  "geometry": {"coordinates":[-0.87389823737681,53.17120578654923],"type":"Point"}
}