{
  "type": "Feature",
  "properties": {
    "iso:country": "GB",
    "wof:name": "N7 9FA",
    "wof:placetype": "postalcode"
  },
  "geometry": {"coordinates":[-0.121456,51.548091],"type":"Point"}
}
