{
  "type": "Feature",
  "properties": {
    "date:inception_lower": "2018-08-01",
    "date:inception_upper": "2018-08-01",
    "iso:country": "GB",
    "wof:name": "N7 9FA",
    "wof:placetype": "postalcode"
  },
  "geometry": {"coordinates":[-0.121456,51.548091],"type":"Point"}
}
