{
  "type": "Feature",
  "properties": {
    "iso:country":"GB",
    "wof:name":"TF1 7YU",
    "wof:placetype":"postalcode"
},
  "geometry": {"coordinates":[-2.46862945647161,52.72095905026578],"type":"Point"}
}