{
  "type": "Feature",
  "properties": {
    "date:inception_lower":"1995-07-01",
    "date:inception_upper":"1995-07-31",
    "iso:country":"GB",
    "wof:name":"LS12 6HL",
    "wof:placetype":"postalcode"
},
  "geometry": {"coordinates":[-1.56924,53.787926],"type":"Point"}
}