{
  "type": "Feature",
  "properties": {
    "iso:country": "GB",
    "wof:name": "HP9 2XE",
    "wof:placetype": "postalcode"
  },
  "geometry": {"coordinates":[-0.597345,51.595421],"type":"Point"}
}
