{
  "type": "Feature",
  "properties": {
    "iso:country":"GB",
    "wof:name":"HP9 2XE",
    "wof:placetype":"postalcode"
},
  "geometry": {"coordinates":[-0.59734487758035,51.59542126124806],"type":"Point"}
}