{
  "type": "Feature",
  "properties": {
    "date:inception_lower":"1980-01-01",
    "date:inception_upper":"1980-01-31",
    "iso:country":"GB",
    "wof:name":"CB8 0EU",
    "wof:placetype":"postalcode"
},
  "geometry": {"coordinates":[0.39323,52.251524],"type":"Point"}
}