{
  "type": "Feature",
  "properties": {
    "date:inception_lower": "2019-06-01",
    "date:inception_upper": "2019-06-01",
    "iso:country": "GB",
    "wof:name": "LE7 9NG",
    "wof:placetype": "postalcode"
  },
  "geometry": {"coordinates":[-0.903724,52.643246],"type":"Point"}
}
