{
  "type": "Feature",
  "properties": {
    "date:inception_lower": "1980-01-01",
    "date:inception_upper": "1980-01-01",
    "iso:country": "GB",
    "wof:name": "TN21 8ED",
    "wof:placetype": "postalcode"
  },
  "geometry": {"coordinates":[0.257016,50.965482],"type":"Point"}
}
