{
  "type": "Feature",
  "properties": {
    "iso:country": "GB",
    "wof:name": "TN21 8ED",
    "wof:placetype": "postalcode"
  },
  "geometry": {"coordinates":[0.257016,50.965482],"type":"Point"}
}
