{
  "type": "Feature",
  "properties": {
    "iso:country": "GB",
    "wof:name": "ML2 8AF",
    "wof:placetype": "postalcode"
  },
  "geometry": {"coordinates":[-3.91685,55.772514],"type":"Point"}
}
