{
  "type": "Feature",
  "properties": {
    "date:inception_lower": "1980-01-01",
    "date:inception_upper": "1980-01-01",
    "iso:country": "GB",
    "wof:name": "ML2 8AF",
    "wof:placetype": "postalcode"
  },
  "geometry": {"coordinates":[-3.91685,55.772514],"type":"Point"}
}
