{
  "type": "Feature",
  "properties": {
    "iso:country":"GB",
    "wof:name":"ML2 8AF",
    "wof:placetype":"postalcode"
},
  "geometry": {"coordinates":[-3.91685032647521,55.77251423236601],"type":"Point"}
}