{
  "type": "Feature",
  "properties": {
    "date:inception_lower": "1980-01-01",
    "date:inception_upper": "1980-01-01",
    "iso:country": "GB",
    "wof:name": "EX12 2EH",
    "wof:placetype": "postalcode"
  },
  "geometry": {"coordinates":[-3.075714,50.714355],"type":"Point"}
}
