{
  "type": "Feature",
  "properties": {
    "iso:country":"GB",
    "wof:name":"EX12 2EH",
    "wof:placetype":"postalcode"
},
  "geometry": {"coordinates":[-3.07571447792828,50.71435462054869],"type":"Point"}
}