{
  "type": "Feature",
  "properties": {
    "iso:country":"GB",
    "wof:name":"IG3 9PP",
    "wof:placetype":"postalcode"
},
  "geometry": {"coordinates":[0.1075235592219,51.55292056080253],"type":"Point"}
}