{
  "type": "Feature",
  "properties": {
    "iso:country": "GB",
    "wof:name": "IG3 9PP",
    "wof:placetype": "postalcode"
  },
  "geometry": {"coordinates":[0.107524,51.552921],"type":"Point"}
}
