{
  "type": "Feature",
  "properties": {
    "iso:country":"GB",
    "wof:name":"LE65 2GB",
    "wof:placetype":"postalcode"
},
  "geometry": {"coordinates":[-1.48345118540276,52.74589730550838],"type":"Point"}
}