{
  "type": "Feature",
  "properties": {
    "iso:country":"GB",
    "wof:name":"BB2 7BB",
    "wof:placetype":"postalcode"
},
  "geometry": {"coordinates":[-2.51117621538001,53.75390507024419],"type":"Point"}
}