{
  "type": "Feature",
  "properties": {
    "iso:country": "GB",
    "wof:name": "HP17 8AT",
    "wof:placetype": "postalcode"
  },
  "geometry": {"coordinates":[-0.928001,51.769862],"type":"Point"}
}
