{
  "type": "Feature",
  "properties": {
    "date:inception_lower": "1996-06-01",
    "date:inception_upper": "1996-06-01",
    "iso:country": "GB",
    "wof:name": "RG4 7XJ",
    "wof:placetype": "postalcode"
  },
  "geometry": {"coordinates":[-0.989522,51.479468],"type":"Point"}
}
