{
  "type": "Feature",
  "properties": {
    "date:inception_lower": "1980-01-01",
    "date:inception_upper": "1980-01-01",
    "iso:country": "GB",
    "wof:name": "SY8 4LL",
    "wof:placetype": "postalcode"
  },
  "geometry": {"coordinates":[-2.657394,52.310179],"type":"Point"}
}
