{
  "type": "Feature",
  "properties": {
    "iso:country":"GB",
    "wof:name":"SY8 4LL",
    "wof:placetype":"postalcode"
},
  "geometry": {"coordinates":[-2.65739418623547,52.31017874953833],"type":"Point"}
}