{
  "type": "Feature",
  "properties": {
    "iso:country":"GB",
    "wof:name":"SN4 7FF",
    "wof:placetype":"postalcode"
},
  "geometry": {"coordinates":[-1.89791576446907,51.53738004013766],"type":"Point"}
}