{
  "type": "Feature",
  "properties": {
    "iso:country":"GB",
    "wof:name":"HX3 8QL",
    "wof:placetype":"postalcode"
},
  "geometry": {"coordinates":[-1.79018140072624,53.74004555513623],"type":"Point"}
}