{
  "type": "Feature",
  "properties": {
    "date:inception_lower": "1980-01-01",
    "date:inception_upper": "1980-01-01",
    "iso:country": "GB",
    "wof:name": "IP29 5EL",
    "wof:placetype": "postalcode"
  },
  "geometry": {"coordinates":[0.571031,52.22622],"type":"Point"}
}
