{
  "type": "Feature",
  "properties": {
    "iso:country": "GB",
    "wof:name": "SS11 7FX",
    "wof:placetype": "postalcode"
  },
  "geometry": {"coordinates":[0.545763,51.634121],"type":"Point"}
}
