{
  "type": "Feature",
  "properties": {
    "iso:country":"GB",
    "wof:name":"EH33 2AT",
    "wof:placetype":"postalcode"
},
  "geometry": {"coordinates":[-2.94107674336999,55.94139069078778],"type":"Point"}
}