{
  "type": "Feature",
  "properties": {
    "iso:country": "GB",
    "wof:name": "SA14 7AN",
    "wof:placetype": "postalcode"
  },
  "geometry": {"coordinates":[-4.129038,51.802077],"type":"Point"}
}
