{
  "type": "Feature",
  "properties": {
    "iso:country":"GB",
    "wof:name":"SA14 7AN",
    "wof:placetype":"postalcode"
},
  "geometry": {"coordinates":[-4.12903845804808,51.80207666192783],"type":"Point"}
}