{
  "type": "Feature",
  "properties": {
    "iso:country": "GB",
    "wof:name": "SK13 8QJ",
    "wof:placetype": "postalcode"
  },
  "geometry": {"coordinates":[-1.936923,53.445029],"type":"Point"}
}
