{
  "type": "Feature",
  "properties": {
    "iso:country": "GB",
    "wof:name": "BN17 5RD",
    "wof:placetype": "postalcode"
  },
  "geometry": {"coordinates":[-0.590457,50.794312],"type":"Point"}
}
