{
  "type": "Feature",
  "properties": {
    "iso:country":"GB",
    "wof:name":"BN17 5RD",
    "wof:placetype":"postalcode"
},
  "geometry": {"coordinates":[-0.59045667886453,50.79431235554421],"type":"Point"}
}