{
  "type": "Feature",
  "properties": {
    "iso:country": "GB",
    "wof:name": "OX25 4AL",
    "wof:placetype": "postalcode"
  },
  "geometry": {"coordinates":[-1.244061,51.914855],"type":"Point"}
}
