{
  "type": "Feature",
  "properties": {
    "iso:country":"GB",
    "wof:name":"OX25 4AL",
    "wof:placetype":"postalcode"
},
  "geometry": {"coordinates":[-1.24406088066377,51.91485512354153],"type":"Point"}
}