{
  "type": "Feature",
  "properties": {
    "iso:country":"GB",
    "wof:name":"B70 0AW",
    "wof:placetype":"postalcode"
},
  "geometry": {"coordinates":[-2.02399416487878,52.52170898086154],"type":"Point"}
}