{
  "type": "Feature",
  "properties": {
    "iso:country": "GB",
    "wof:name": "B70 0AW",
    "wof:placetype": "postalcode"
  },
  "geometry": {"coordinates":[-2.023988,52.521724],"type":"Point"}
}
