{
  "type": "Feature",
  "properties": {
    "date:inception_lower":"1980-01-01",
    "date:inception_upper":"1980-01-31",
    "iso:country":"GB",
    "wof:name":"B70 0AW",
    "wof:placetype":"postalcode"
},
  "geometry": {"coordinates":[-2.023988,52.521724],"type":"Point"}
}