{
  "type": "Feature",
  "properties": {
    "date:inception_lower":"1980-01-01",
    "date:inception_upper":"1980-01-31",
    "iso:country":"GB",
    "wof:name":"NR10 5HJ",
    "wof:placetype":"postalcode"
},
  "geometry": {"coordinates":[1.298268,52.759479],"type":"Point"}
}