{
  "type": "Feature",
  "properties": {
    "iso:country": "GB",
    "wof:name": "NR10 5HJ",
    "wof:placetype": "postalcode"
  },
  "geometry": {"coordinates":[1.298268,52.759479],"type":"Point"}
}
