{
  "type": "Feature",
  "properties": {
    "iso:country":"GB",
    "wof:name":"RH20 4TB",
    "wof:placetype":"postalcode"
},
  "geometry": {"coordinates":[-0.447465639093,50.91692591948333],"type":"Point"}
}