{
  "type": "Feature",
  "properties": {
    "date:inception_lower":"1992-01-01",
    "date:inception_upper":"1992-01-31",
    "iso:country":"GB",
    "wof:name":"RH20 4TB",
    "wof:placetype":"postalcode"
},
  "geometry": {"coordinates":[-0.447466,50.916926],"type":"Point"}
}