{
  "type": "Feature",
  "properties": {
    "iso:country": "GB",
    "wof:name": "RH20 4TB",
    "wof:placetype": "postalcode"
  },
  "geometry": {"coordinates":[-0.447466,50.916926],"type":"Point"}
}
