{
  "type": "Feature",
  "properties": {
    "iso:country":"GB",
    "wof:name":"M27 9GE",
    "wof:placetype":"postalcode"
},
  "geometry": {"coordinates":[-2.35599807684294,53.51700607645404],"type":"Point"}
}