{
  "type": "Feature",
  "properties": {
    "iso:country":"GB",
    "wof:name":"EH49 6NF",
    "wof:placetype":"postalcode"
},
  "geometry": {"coordinates":[-3.50528294974043,55.96513598174717],"type":"Point"}
}