{
  "type": "Feature",
  "properties": {
    "iso:country":"GB",
    "wof:name":"ST1 3BH",
    "wof:placetype":"postalcode"
},
  "geometry": {"coordinates":[-2.17557519134123,53.01841399245984],"type":"Point"}
}