{
  "type": "Feature",
  "properties": {
    "iso:country": "GB",
    "wof:name": "TN2 4QU",
    "wof:placetype": "postalcode"
  },
  "geometry": {"coordinates":[0.309468,51.13691],"type":"Point"}
}
