{
  "type": "Feature",
  "properties": {
    "iso:country":"GB",
    "wof:name":"DL11 6LF",
    "wof:placetype":"postalcode"
},
  "geometry": {"coordinates":[-2.05812513893767,54.3756443673401],"type":"Point"}
}