{
  "type": "Feature",
  "properties": {
    "date:inception_lower":"1980-01-01",
    "date:inception_upper":"1980-01-31",
    "iso:country":"GB",
    "wof:name":"DL11 6LF",
    "wof:placetype":"postalcode"
},
  "geometry": {"coordinates":[-2.058125,54.375644],"type":"Point"}
}