{
  "type": "Feature",
  "properties": {
    "iso:country":"GB",
    "wof:name":"M5 4TR",
    "wof:placetype":"postalcode"
},
  "geometry": {"coordinates":[-2.26860072361543,53.4762292900934],"type":"Point"}
}