{
  "type": "Feature",
  "properties": {
    "iso:country":"GB",
    "wof:name":"AL4 8AF",
    "wof:placetype":"postalcode"
},
  "geometry": {"coordinates":[-0.29691946759372,51.81111415345922],"type":"Point"}
}