{
  "type": "Feature",
  "properties": {
    "date:inception_lower": "1980-01-01",
    "date:inception_upper": "1980-01-01",
    "iso:country": "GB",
    "wof:name": "AL4 8AF",
    "wof:placetype": "postalcode"
  },
  "geometry": {"coordinates":[-0.296919,51.811114],"type":"Point"}
}
