{
  "type": "Feature",
  "properties": {
    "iso:country":"GB",
    "wof:name":"HA5 3AP",
    "wof:placetype":"postalcode"
},
  "geometry": {"coordinates":[-0.37434978194758,51.59606074608784],"type":"Point"}
}