{
  "type": "Feature",
  "properties": {
    "iso:country":"GB",
    "wof:name":"CM8 1RT",
    "wof:placetype":"postalcode"
},
  "geometry": {"coordinates":[0.57668431780006,51.84244363819951],"type":"Point"}
}