{
  "type": "Feature",
  "properties": {
    "iso:country":"GB",
    "wof:name":"BR5 2EW",
    "wof:placetype":"postalcode"
},
  "geometry": {"coordinates":[0.10403205772343,51.3926855175352],"type":"Point"}
}