{
  "type": "Feature",
  "properties": {
    "iso:country": "GB",
    "wof:name": "DN3 3FU",
    "wof:placetype": "postalcode"
  },
  "geometry": {"coordinates":[-1.033172,53.509812],"type":"Point"}
}
