{
  "type": "Feature",
  "properties": {
    "iso:country":"GB",
    "wof:name":"NP11 4SP",
    "wof:placetype":"postalcode"
},
  "geometry": {"coordinates":[-3.13984189893876,51.64999110211533],"type":"Point"}
}