{
  "type": "Feature",
  "properties": {
    "iso:country":"GB",
    "wof:name":"LS18 5TQ",
    "wof:placetype":"postalcode"
},
  "geometry": {"coordinates":[-1.62908428310681,53.83956650674849],"type":"Point"}
}