{
  "type": "Feature",
  "properties": {
    "iso:country": "GB",
    "wof:name": "LS18 5TQ",
    "wof:placetype": "postalcode"
  },
  "geometry": {"coordinates":[-1.629084,53.839567],"type":"Point"}
}
