{
  "type": "Feature",
  "properties": {
    "date:inception_lower":"2000-12-01",
    "date:inception_upper":"2000-12-31",
    "iso:country":"GB",
    "wof:name":"BS24 0BT",
    "wof:placetype":"postalcode"
},
  "geometry": {"coordinates":[-2.947396,51.294437],"type":"Point"}
}