{
  "type": "Feature",
  "properties": {
    "iso:country": "GB",
    "wof:name": "BS24 0BT",
    "wof:placetype": "postalcode"
  },
  "geometry": {"coordinates":[-2.947396,51.294437],"type":"Point"}
}
