{
  "type": "Feature",
  "properties": {
    "date:inception_lower":"1980-01-01",
    "date:inception_upper":"1980-01-31",
    "iso:country":"GB",
    "wof:name":"TS13 4DD",
    "wof:placetype":"postalcode"
},
  "geometry": {"coordinates":[-0.908156,54.562579],"type":"Point"}
}