{
  "type": "Feature",
  "properties": {
    "iso:country":"GB",
    "wof:name":"G53 7NW",
    "wof:placetype":"postalcode"
},
  "geometry": {"coordinates":[-4.36684696573317,55.8289049754171],"type":"Point"}
}