{
  "type": "Feature",
  "properties": {
    "iso:country":"GB",
    "wof:name":"LD2 3BH",
    "wof:placetype":"postalcode"
},
  "geometry": {"coordinates":[-3.40337593005607,52.14941936247719],"type":"Point"}
}