{
  "type": "Feature",
  "properties": {
    "iso:country":"GB",
    "wof:name":"AL10 8PS",
    "wof:placetype":"postalcode"
},
  "geometry": {"coordinates":[-0.22654421725477,51.75315422423139],"type":"Point"}
}