{
  "type": "Feature",
  "properties": {
    "iso:country":"GB",
    "wof:name":"BS14 9SA",
    "wof:placetype":"postalcode"
},
  "geometry": {"coordinates":[-2.57263499632333,51.42015984853592],"type":"Point"}
}