{
  "type": "Feature",
  "properties": {
    "iso:country": "GB",
    "wof:name": "SA19 9SS",
    "wof:placetype": "postalcode"
  },
  "geometry": {"coordinates":[-3.823307,51.917081],"type":"Point"}
}
