{
  "type": "Feature",
  "properties": {
    "iso:country":"GB",
    "wof:name":"SA19 9SS",
    "wof:placetype":"postalcode"
},
  "geometry": {"coordinates":[-3.82330699413027,51.91708103706217],"type":"Point"}
}