{
  "type": "Feature",
  "properties": {
    "date:inception_lower": "1980-01-01",
    "date:inception_upper": "1980-01-01",
    "iso:country": "GB",
    "wof:name": "L18 1HP",
    "wof:placetype": "postalcode"
  },
  "geometry": {"coordinates":[-2.927125,53.388771],"type":"Point"}
}
