{
  "type": "Feature",
  "properties": {
    "iso:country":"GB",
    "wof:name":"L18 1HP",
    "wof:placetype":"postalcode"
},
  "geometry": {"coordinates":[-2.9271246422172,53.38877073722729],"type":"Point"}
}