{
  "type": "Feature",
  "properties": {
    "iso:country":"GB",
    "wof:name":"YO10 5GE",
    "wof:placetype":"postalcode"
},
  "geometry": {"coordinates":[-1.02995506606649,53.94721512733923],"type":"Point"}
}