{
  "type": "Feature",
  "properties": {
    "date:inception_lower":"2010-11-01",
    "date:inception_upper":"2010-11-30",
    "iso:country":"GB",
    "wof:name":"YO10 5GE",
    "wof:placetype":"postalcode"
},
  "geometry": {"coordinates":[-1.029955,53.947215],"type":"Point"}
}