{
  "type": "Feature",
  "properties": {
    "iso:country":"GB",
    "wof:name":"GL2 0DD",
    "wof:placetype":"postalcode"
},
  "geometry": {"coordinates":[-2.21532962590155,51.87889014286758],"type":"Point"}
}