{
  "type": "Feature",
  "properties": {
    "date:inception_lower": "1980-01-01",
    "date:inception_upper": "1980-01-01",
    "iso:country": "GB",
    "wof:name": "CM16 6RS",
    "wof:placetype": "postalcode"
  },
  "geometry": {"coordinates":[0.111147,51.706702],"type":"Point"}
}
