{
  "type": "Feature",
  "properties": {
    "iso:country":"GB",
    "wof:name":"S81 0DG",
    "wof:placetype":"postalcode"
},
  "geometry": {"coordinates":[-1.10622175663383,53.31195782904205],"type":"Point"}
}