{
  "type": "Feature",
  "properties": {
    "iso:country": "GB",
    "wof:name": "SO31 8DE",
    "wof:placetype": "postalcode"
  },
  "geometry": {"coordinates":[-1.318391,50.882245],"type":"Point"}
}
