{
  "type": "Feature",
  "properties": {
    "date:inception_lower":"1994-12-01",
    "date:inception_upper":"1994-12-31",
    "iso:country":"GB",
    "wof:name":"SO31 8DE",
    "wof:placetype":"postalcode"
},
  "geometry": {"coordinates":[-1.318391,50.882245],"type":"Point"}
}