{
  "type": "Feature",
  "properties": {
    "iso:country":"GB",
    "wof:name":"IG8 8EB",
    "wof:placetype":"postalcode"
},
  "geometry": {"coordinates":[0.05206131756989,51.60742805064584],"type":"Point"}
}