{
  "type": "Feature",
  "properties": {
    "iso:country": "GB",
    "wof:name": "PL25 3SU",
    "wof:placetype": "postalcode"
  },
  "geometry": {"coordinates":[-4.780985,50.353038],"type":"Point"}
}
