{
  "type": "Feature",
  "properties": {
    "iso:country":"GB",
    "wof:name":"PL25 3SU",
    "wof:placetype":"postalcode"
},
  "geometry": {"coordinates":[-4.78098502098972,50.35303791954308],"type":"Point"}
}