{
  "type": "Feature",
  "properties": {
    "date:inception_lower":"2006-03-01",
    "date:inception_upper":"2006-03-31",
    "iso:country":"GB",
    "wof:name":"PL25 3SU",
    "wof:placetype":"postalcode"
},
  "geometry": {"coordinates":[-4.780985,50.353038],"type":"Point"}
}