{
  "type": "Feature",
  "properties": {
    "iso:country": "GB",
    "wof:name": "DN6 7QE",
    "wof:placetype": "postalcode"
  },
  "geometry": {"coordinates":[-1.184888,53.561258],"type":"Point"}
}
