{
  "type": "Feature",
  "properties": {
    "iso:country":"GB",
    "wof:name":"SO20 6PJ",
    "wof:placetype":"postalcode"
},
  "geometry": {"coordinates":[-1.48685414082594,51.07960779873179],"type":"Point"}
}