{
  "type": "Feature",
  "properties": {
    "date:inception_lower": "1980-01-01",
    "date:inception_upper": "1980-01-01",
    "iso:country": "GB",
    "wof:name": "BL9 5HS",
    "wof:placetype": "postalcode"
  },
  "geometry": {"coordinates":[-2.294985,53.613168],"type":"Point"}
}
