{
  "type": "Feature",
  "properties": {
    "date:inception_lower": "2006-11-01",
    "date:inception_upper": "2006-11-01",
    "iso:country": "GB",
    "wof:name": "CO10 2SR",
    "wof:placetype": "postalcode"
  },
  "geometry": {"coordinates":[0.745532,52.036442],"type":"Point"}
}
