{
  "type": "Feature",
  "properties": {
    "iso:country":"GB",
    "wof:name":"CO10 2SR",
    "wof:placetype":"postalcode"
},
  "geometry": {"coordinates":[0.74547258826055,52.03644780352532],"type":"Point"}
}