{
  "type": "Feature",
  "properties": {
    "iso:country": "GB",
    "wof:name": "BA16 9NA",
    "wof:placetype": "postalcode"
  },
  "geometry": {"coordinates":[-2.746454,51.130566],"type":"Point"}
}
