{
  "type": "Feature",
  "properties": {
    "iso:country": "GB",
    "wof:name": "B7 4QG",
    "wof:placetype": "postalcode"
  },
  "geometry": {"coordinates":[-1.873461,52.490485],"type":"Point"}
}
