{
  "type": "Feature",
  "properties": {
    "date:inception_lower": "1980-01-01",
    "date:inception_upper": "1980-01-01",
    "iso:country": "GB",
    "wof:name": "B7 4QG",
    "wof:placetype": "postalcode"
  },
  "geometry": {"coordinates":[-1.873461,52.490485],"type":"Point"}
}
