{
  "type": "Feature",
  "properties": {
    "iso:country":"GB",
    "wof:name":"BA1 0ZZ",
    "wof:placetype":"postalcode"
},
  "geometry": {"coordinates":[-2.35556172925545,51.37885788588602],"type":"Point"}
}