{
  "type": "Feature",
  "properties": {
    "date:inception_lower":"2016-03-01",
    "date:inception_upper":"2016-03-31",
    "iso:country":"GB",
    "wof:name":"BA1 0ZZ",
    "wof:placetype":"postalcode"
},
  "geometry": {"coordinates":[-2.355562,51.378858],"type":"Point"}
}