{
  "type": "Feature",
  "properties": {
    "date:inception_lower": "1980-01-01",
    "date:inception_upper": "1980-01-01",
    "iso:country": "GB",
    "wof:name": "TN27 8RD",
    "wof:placetype": "postalcode"
  },
  "geometry": {"coordinates":[0.72097,51.155794],"type":"Point"}
}
