{
  "type": "Feature",
  "properties": {
    "iso:country":"GB",
    "wof:name":"TN27 8RD",
    "wof:placetype":"postalcode"
},
  "geometry": {"coordinates":[0.72036508574396,51.15575431076533],"type":"Point"}
}