{
  "type": "Feature",
  "properties": {
    "date:inception_lower": "1991-09-01",
    "date:inception_upper": "1991-09-01",
    "iso:country": "GB",
    "wof:name": "MK13 8NB",
    "wof:placetype": "postalcode"
  },
  "geometry": {"coordinates":[-0.776081,52.045096],"type":"Point"}
}
