{
  "type": "Feature",
  "properties": {
    "date:inception_lower": "1997-06-01",
    "date:inception_upper": "1997-06-01",
    "iso:country": "GB",
    "wof:name": "WF7 5NY",
    "wof:placetype": "postalcode"
  },
  "geometry": {"coordinates":[-1.357927,53.669292],"type":"Point"}
}
