{
  "type": "Feature",
  "properties": {
    "iso:country": "GB",
    "wof:name": "WF7 5NY",
    "wof:placetype": "postalcode"
  },
  "geometry": {"coordinates":[-1.357927,53.669292],"type":"Point"}
}
