{
  "type": "Feature",
  "properties": {
    "iso:country":"GB",
    "wof:name":"BH15 4LU",
    "wof:placetype":"postalcode"
},
  "geometry": {"coordinates":[-2.02091033473952,50.71402095438089],"type":"Point"}
}