{
  "type": "Feature",
  "properties": {
    "iso:country":"GB",
    "wof:name":"HG3 2BS",
    "wof:placetype":"postalcode"
},
  "geometry": {"coordinates":[-1.59241734976492,54.01129499269339],"type":"Point"}
}