{
  "type": "Feature",
  "properties": {
    "iso:country": "GB",
    "wof:name": "HG3 2BS",
    "wof:placetype": "postalcode"
  },
  "geometry": {"coordinates":[-1.592179,54.011247],"type":"Point"}
}
