{
  "type": "Feature",
  "properties": {
    "iso:country":"GB",
    "wof:name":"WF4 1TA",
    "wof:placetype":"postalcode"
},
  "geometry": {"coordinates":[-1.42008909636439,53.65494878172736],"type":"Point"}
}