{
  "type": "Feature",
  "properties": {
    "iso:country": "GB",
    "wof:name": "WF4 1TA",
    "wof:placetype": "postalcode"
  },
  "geometry": {"coordinates":[-1.420089,53.654949],"type":"Point"}
}
