{
  "type": "Feature",
  "properties": {
    "iso:country":"GB",
    "wof:name":"BB3 3SG",
    "wof:placetype":"postalcode"
},
  "geometry": {"coordinates":[-2.44760790720457,53.69330067098539],"type":"Point"}
}