{
  "type": "Feature",
  "properties": {
    "iso:country": "GB",
    "wof:name": "BB3 3SG",
    "wof:placetype": "postalcode"
  },
  "geometry": {"coordinates":[-2.447608,53.693301],"type":"Point"}
}
