{
  "type": "Feature",
  "properties": {
    "iso:country": "GB",
    "wof:name": "SK4 2DF",
    "wof:placetype": "postalcode"
  },
  "geometry": {"coordinates":[-2.193537,53.409869],"type":"Point"}
}
