{
  "type": "Feature",
  "properties": {
    "iso:country":"GB",
    "wof:name":"AB32 6AW",
    "wof:placetype":"postalcode"
},
  "geometry": {"coordinates":[-2.31048179576791,57.15732550367443],"type":"Point"}
}