{
  "type": "Feature",
  "properties": {
    "date:inception_lower": "2010-07-01",
    "date:inception_upper": "2010-07-01",
    "iso:country": "GB",
    "wof:name": "AB32 6AW",
    "wof:placetype": "postalcode"
  },
  "geometry": {"coordinates":[-2.310482,57.157326],"type":"Point"}
}
