{
  "type": "Feature",
  "properties": {
    "iso:country":"GB",
    "wof:name":"LA1 4NT",
    "wof:placetype":"postalcode"
},
  "geometry": {"coordinates":[-2.79618224203405,54.02458129247146],"type":"Point"}
}