{
  "type": "Feature",
  "properties": {
    "iso:country": "GB",
    "wof:name": "SN26 7BL",
    "wof:placetype": "postalcode"
  },
  "geometry": {"coordinates":[-1.78681,51.614782],"type":"Point"}
}
