{
  "type": "Feature",
  "properties": {
    "date:inception_lower": "1980-01-01",
    "date:inception_upper": "1980-01-01",
    "iso:country": "GB",
    "wof:name": "SW15 4AS",
    "wof:placetype": "postalcode"
  },
  "geometry": {"coordinates":[-0.237838,51.44559],"type":"Point"}
}
