{
  "type": "Feature",
  "properties": {
    "iso:country":"GB",
    "wof:name":"SW15 4AS",
    "wof:placetype":"postalcode"
},
  "geometry": {"coordinates":[-0.23783797962036,51.44559037691344],"type":"Point"}
}