{
  "type": "Feature",
  "properties": {
    "iso:country":"GB",
    "wof:name":"TN22 3NF",
    "wof:placetype":"postalcode"
},
  "geometry": {"coordinates":[0.05507028164467,51.03150841353741],"type":"Point"}
}