{
  "type": "Feature",
  "properties": {
    "date:inception_lower": "1980-01-01",
    "date:inception_upper": "1980-01-01",
    "iso:country": "GB",
    "wof:name": "TN22 3NF",
    "wof:placetype": "postalcode"
  },
  "geometry": {"coordinates":[0.055112,51.031523],"type":"Point"}
}
