{
  "type": "Feature",
  "properties": {
    "iso:country": "GB",
    "wof:name": "TN22 3NF",
    "wof:placetype": "postalcode"
  },
  "geometry": {"coordinates":[0.05507,51.031508],"type":"Point"}
}
