{
  "type": "Feature",
  "properties": {
    "iso:country": "GB",
    "wof:name": "NG12 4BH",
    "wof:placetype": "postalcode"
  },
  "geometry": {"coordinates":[-1.115781,52.912104],"type":"Point"}
}
