{
  "type": "Feature",
  "properties": {
    "iso:country":"GB",
    "wof:name":"IP27 9JR",
    "wof:placetype":"postalcode"
},
  "geometry": {"coordinates":[0.52483474661467,52.42214575741927],"type":"Point"}
}