{
  "type": "Feature",
  "properties": {
    "iso:country": "GB",
    "wof:name": "RG6 1NU",
    "wof:placetype": "postalcode"
  },
  "geometry": {"coordinates":[-0.933761,51.447753],"type":"Point"}
}
