{
  "type": "Feature",
  "properties": {
    "iso:country":"GB",
    "wof:name":"RG6 1NU",
    "wof:placetype":"postalcode"
},
  "geometry": {"coordinates":[-0.93376096778542,51.44775288016309],"type":"Point"}
}