{
  "type": "Feature",
  "properties": {
    "date:inception_lower": "1980-01-01",
    "date:inception_upper": "1980-01-01",
    "iso:country": "GB",
    "wof:name": "CT12 4EG",
    "wof:placetype": "postalcode"
  },
  "geometry": {"coordinates":[1.308686,51.336322],"type":"Point"}
}
