{
  "type": "Feature",
  "properties": {
    "iso:country": "GB",
    "wof:name": "CT12 4EG",
    "wof:placetype": "postalcode"
  },
  "geometry": {"coordinates":[1.308686,51.336322],"type":"Point"}
}
