{
  "type": "Feature",
  "properties": {
    "iso:country":"GB",
    "wof:name":"CT12 4EG",
    "wof:placetype":"postalcode"
},
  "geometry": {"coordinates":[1.30868626810301,51.33632221234216],"type":"Point"}
}