{
  "type": "Feature",
  "properties": {
    "iso:country": "GB",
    "wof:name": "NG9 3TB",
    "wof:placetype": "postalcode"
  },
  "geometry": {"coordinates":[-1.235906,52.93384],"type":"Point"}
}
