{
  "type": "Feature",
  "properties": {
    "date:inception_lower": "2001-06-01",
    "date:inception_upper": "2001-06-01",
    "iso:country": "GB",
    "wof:name": "HD9 3XE",
    "wof:placetype": "postalcode"
  },
  "geometry": {"coordinates":[-1.806861,53.570314],"type":"Point"}
}
