{
  "type": "Feature",
  "properties": {
    "date:inception_lower": "2019-03-01",
    "date:inception_upper": "2019-03-01",
    "iso:country": "GB",
    "wof:name": "M15 4RZ",
    "wof:placetype": "postalcode"
  },
  "geometry": {"coordinates":[-2.26424,53.470566],"type":"Point"}
}
