{
  "type": "Feature",
  "properties": {
    "iso:country": "GB",
    "wof:name": "SA5 5DD",
    "wof:placetype": "postalcode"
  },
  "geometry": {"coordinates":[-3.981053,51.647846],"type":"Point"}
}
