{
  "type": "Feature",
  "properties": {
    "date:inception_lower": "1990-07-01",
    "date:inception_upper": "1990-07-01",
    "iso:country": "GB",
    "wof:name": "SA5 5DD",
    "wof:placetype": "postalcode"
  },
  "geometry": {"coordinates":[-3.980982,51.648114],"type":"Point"}
}
