{
  "type": "Feature",
  "properties": {
    "iso:country":"GB",
    "wof:name":"CM2 9RQ",
    "wof:placetype":"postalcode"
},
  "geometry": {"coordinates":[0.49537559527826,51.71941922562527],"type":"Point"}
}