{
  "type": "Feature",
  "properties": {
    "date:inception_lower":"1990-07-01",
    "date:inception_upper":"1990-07-31",
    "iso:country":"GB",
    "wof:name":"CM2 9RQ",
    "wof:placetype":"postalcode"
},
  "geometry": {"coordinates":[0.495376,51.719419],"type":"Point"}
}