{
  "type": "Feature",
  "properties": {
    "iso:country": "GB",
    "wof:name": "CA15 7NA",
    "wof:placetype": "postalcode"
  },
  "geometry": {"coordinates":[-3.491269,54.709735],"type":"Point"}
}
