{
  "type": "Feature",
  "properties": {
    "date:inception_lower": "1980-01-01",
    "date:inception_upper": "1980-01-01",
    "iso:country": "GB",
    "wof:name": "TN6 2SH",
    "wof:placetype": "postalcode"
  },
  "geometry": {"coordinates":[0.162531,51.060776],"type":"Point"}
}
