{
  "type": "Feature",
  "properties": {
    "iso:country": "GB",
    "wof:name": "G81 2EH",
    "wof:placetype": "postalcode"
  },
  "geometry": {"coordinates":[-4.393534,55.908982],"type":"Point"}
}
