{
  "type": "Feature",
  "properties": {
    "iso:country":"GB",
    "wof:name":"NE2 1JW",
    "wof:placetype":"postalcode"
},
  "geometry": {"coordinates":[-1.59238746284404,54.9847822643229],"type":"Point"}
}