{
  "type": "Feature",
  "properties": {
    "iso:country": "GB",
    "wof:name": "NE2 1JW",
    "wof:placetype": "postalcode"
  },
  "geometry": {"coordinates":[-1.592387,54.984782],"type":"Point"}
}
