{
  "type": "Feature",
  "properties": {
    "iso:country":"GB",
    "wof:name":"IG4 5BS",
    "wof:placetype":"postalcode"
},
  "geometry": {"coordinates":[0.04929619394131,51.57841218993161],"type":"Point"}
}