{
  "type": "Feature",
  "properties": {
    "iso:country": "GB",
    "wof:name": "DD8 5PY",
    "wof:placetype": "postalcode"
  },
  "geometry": {"coordinates":[-2.889617,56.644022],"type":"Point"}
}
