{
  "type": "Feature",
  "properties": {
    "iso:country": "GB",
    "wof:name": "SA32 7JH",
    "wof:placetype": "postalcode"
  },
  "geometry": {"coordinates":[-4.227078,51.931748],"type":"Point"}
}
