{
  "type": "Feature",
  "properties": {
    "iso:country":"GB",
    "wof:name":"SA32 7JH",
    "wof:placetype":"postalcode"
},
  "geometry": {"coordinates":[-4.22707782638673,51.93174818760967],"type":"Point"}
}