{
  "type": "Feature",
  "properties": {
    "date:inception_lower": "1980-01-01",
    "date:inception_upper": "1980-01-01",
    "iso:country": "GB",
    "wof:name": "EX20 2PH",
    "wof:placetype": "postalcode"
  },
  "geometry": {"coordinates":[-3.901628,50.72235],"type":"Point"}
}
