{
  "type": "Feature",
  "properties": {
    "iso:country":"GB",
    "wof:name":"OX3 9SL",
    "wof:placetype":"postalcode"
},
  "geometry": {"coordinates":[-1.19171658891371,51.76997474092824],"type":"Point"}
}