{
  "type": "Feature",
  "properties": {
    "iso:country": "GB",
    "wof:name": "OX3 9SL",
    "wof:placetype": "postalcode"
  },
  "geometry": {"coordinates":[-1.191717,51.769975],"type":"Point"}
}
