{
  "type": "Feature",
  "properties": {
    "iso:country":"GB",
    "wof:name":"CR0 7SX",
    "wof:placetype":"postalcode"
},
  "geometry": {"coordinates":[-0.04639416431852,51.39104567578054],"type":"Point"}
}