{
  "type": "Feature",
  "properties": {
    "iso:country":"GB",
    "wof:name":"DH4 7JA",
    "wof:placetype":"postalcode"
},
  "geometry": {"coordinates":[-1.49822675039778,54.87780719967004],"type":"Point"}
}