{
  "type": "Feature",
  "properties": {
    "iso:country":"GB",
    "wof:name":"HA1 4PN",
    "wof:placetype":"postalcode"
},
  "geometry": {"coordinates":[-0.35804959035577,51.58484544273153],"type":"Point"}
}