{
  "type": "Feature",
  "properties": {
    "date:inception_lower": "1980-01-01",
    "date:inception_upper": "1980-01-01",
    "iso:country": "GB",
    "wof:name": "DY14 0ES",
    "wof:placetype": "postalcode"
  },
  "geometry": {"coordinates":[-2.556195,52.404652],"type":"Point"}
}
