{
  "type": "Feature",
  "properties": {
    "iso:country": "GB",
    "wof:name": "DY14 0ES",
    "wof:placetype": "postalcode"
  },
  "geometry": {"coordinates":[-2.555942,52.405507],"type":"Point"}
}
