{
  "type": "Feature",
  "properties": {
    "date:inception_lower": "1980-01-01",
    "date:inception_upper": "1980-01-01",
    "iso:country": "GB",
    "wof:name": "DY14 0ES",
    "wof:placetype": "postalcode"
  },
  "geometry": {"coordinates":[-2.555942,52.405507],"type":"Point"}
}
