{
  "type": "Feature",
  "properties": {
    "iso:country":"GB",
    "wof:name":"TW18 2SW",
    "wof:placetype":"postalcode"
},
  "geometry": {"coordinates":[-0.4955993168618,51.41487590703132],"type":"Point"}
}