{
  "type": "Feature",
  "properties": {
    "iso:country": "GB",
    "wof:name": "TW18 2SW",
    "wof:placetype": "postalcode"
  },
  "geometry": {"coordinates":[-0.495599,51.414876],"type":"Point"}
}
