{
  "type": "Feature",
  "properties": {
    "iso:country": "GB",
    "wof:name": "CV13 0LQ",
    "wof:placetype": "postalcode"
  },
  "geometry": {"coordinates":[-1.401588,52.627001],"type":"Point"}
}
