{
  "type": "Feature",
  "properties": {
    "iso:country": "GB",
    "wof:name": "WA10 3PG",
    "wof:placetype": "postalcode"
  },
  "geometry": {"coordinates":[-2.768793,53.434642],"type":"Point"}
}
