{
  "type": "Feature",
  "properties": {
    "date:inception_lower": "1980-01-01",
    "date:inception_upper": "1980-01-01",
    "iso:country": "GB",
    "wof:name": "WA10 3PG",
    "wof:placetype": "postalcode"
  },
  "geometry": {"coordinates":[-2.768793,53.434642],"type":"Point"}
}
