{
  "type": "Feature",
  "properties": {
    "iso:country":"GB",
    "wof:name":"EX16 7NQ",
    "wof:placetype":"postalcode"
},
  "geometry": {"coordinates":[-3.42378883805141,50.9734888858119],"type":"Point"}
}