{
  "type": "Feature",
  "properties": {
    "iso:country":"GB",
    "wof:name":"CF5 4JP",
    "wof:placetype":"postalcode"
},
  "geometry": {"coordinates":[-3.25674166290791,51.48022765334679],"type":"Point"}
}