{
  "type": "Feature",
  "properties": {
    "iso:country": "GB",
    "wof:name": "CF5 4JP",
    "wof:placetype": "postalcode"
  },
  "geometry": {"coordinates":[-3.256742,51.480228],"type":"Point"}
}
