{
  "type": "Feature",
  "properties": {
    "iso:country": "GB",
    "wof:name": "BA5 2BA",
    "wof:placetype": "postalcode"
  },
  "geometry": {"coordinates":[-2.65315,51.20869],"type":"Point"}
}
