{
  "type": "Feature",
  "properties": {
    "iso:country":"GB",
    "wof:name":"BA5 2BA",
    "wof:placetype":"postalcode"
},
  "geometry": {"coordinates":[-2.65315023764582,51.20869031693908],"type":"Point"}
}