{
  "type": "Feature",
  "properties": {
    "iso:country":"GB",
    "wof:name":"DE4 4DW",
    "wof:placetype":"postalcode"
},
  "geometry": {"coordinates":[-1.57220557665546,53.08059183162464],"type":"Point"}
}