{
  "type": "Feature",
  "properties": {
    "date:inception_lower": "1980-01-01",
    "date:inception_upper": "1980-01-01",
    "iso:country": "GB",
    "wof:name": "DE4 4DW",
    "wof:placetype": "postalcode"
  },
  "geometry": {"coordinates":[-1.572206,53.080592],"type":"Point"}
}
