{
  "type": "Feature",
  "properties": {
    "iso:country":"GB",
    "wof:name":"WF2 0EX",
    "wof:placetype":"postalcode"
},
  "geometry": {"coordinates":[-1.51828903270484,53.68922460397408],"type":"Point"}
}