{
  "type": "Feature",
  "properties": {
    "date:inception_lower": "1993-08-01",
    "date:inception_upper": "1993-08-01",
    "iso:country": "GB",
    "wof:name": "RH1 1YB",
    "wof:placetype": "postalcode"
  },
  "geometry": {"coordinates":[-0.169177,51.241375],"type":"Point"}
}
