{
  "type": "Feature",
  "properties": {
    "iso:country":"GB",
    "wof:name":"E10 5BH",
    "wof:placetype":"postalcode"
},
  "geometry": {"coordinates":[-0.01335161101462,51.57126135116442],"type":"Point"}
}