{
  "type": "Feature",
  "properties": {
    "iso:country":"GB",
    "wof:name":"PO22 9RR",
    "wof:placetype":"postalcode"
},
  "geometry": {"coordinates":[-0.67243274663401,50.79458153329746],"type":"Point"}
}