{
  "type": "Feature",
  "properties": {
    "date:inception_lower":"1982-03-01",
    "date:inception_upper":"1982-03-31",
    "iso:country":"GB",
    "wof:name":"PO22 9RR",
    "wof:placetype":"postalcode"
},
  "geometry": {"coordinates":[-0.672433,50.794582],"type":"Point"}
}