{
  "type": "Feature",
  "properties": {
    "iso:country":"GB",
    "wof:name":"ME5 7EG",
    "wof:placetype":"postalcode"
},
  "geometry": {"coordinates":[0.54069277785755,51.37538584487304],"type":"Point"}
}