{
  "type": "Feature",
  "properties": {
    "iso:country":"GB",
    "wof:name":"ML2 9NG",
    "wof:placetype":"postalcode"
},
  "geometry": {"coordinates":[-3.87188303183454,55.78665168178435],"type":"Point"}
}