{
  "type": "Feature",
  "properties": {
    "iso:country":"GB",
    "wof:name":"LE18 1EF",
    "wof:placetype":"postalcode"
},
  "geometry": {"coordinates":[-1.11016577962937,52.59690615253911],"type":"Point"}
}