{
  "type": "Feature",
  "properties": {
    "date:inception_lower":"2010-10-01",
    "date:inception_upper":"2010-10-31",
    "iso:country":"GB",
    "wof:name":"RM10 7FA",
    "wof:placetype":"postalcode"
},
  "geometry": {"coordinates":[0.158673,51.555012],"type":"Point"}
}