{
  "type": "Feature",
  "properties": {
    "iso:country":"GB",
    "wof:name":"RM10 7FA",
    "wof:placetype":"postalcode"
},
  "geometry": {"coordinates":[0.15867310104944,51.55501208352339],"type":"Point"}
}