{
  "type": "Feature",
  "properties": {
    "iso:country":"GB",
    "wof:name":"MK45 4EF",
    "wof:placetype":"postalcode"
},
  "geometry": {"coordinates":[-0.426834042705,52.00807841407167],"type":"Point"}
}