{
  "type": "Feature",
  "properties": {
    "iso:country": "GB",
    "wof:name": "YO21 2DZ",
    "wof:placetype": "postalcode"
  },
  "geometry": {"coordinates":[-0.944884,54.451196],"type":"Point"}
}
