{
  "type": "Feature",
  "properties": {
    "iso:country":"GB",
    "wof:name":"YO21 2DZ",
    "wof:placetype":"postalcode"
},
  "geometry": {"coordinates":[-0.94685209077737,54.45379745226668],"type":"Point"}
}