{
  "type": "Feature",
  "properties": {
    "iso:country": "GB",
    "wof:name": "BH21 4FA",
    "wof:placetype": "postalcode"
  },
  "geometry": {"coordinates":[-1.984769,50.809865],"type":"Point"}
}
