{
  "type": "Feature",
  "properties": {
    "iso:country": "GB",
    "wof:name": "TW2 5SH",
    "wof:placetype": "postalcode"
  },
  "geometry": {"coordinates":[-0.340803,51.438793],"type":"Point"}
}
