{
  "type": "Feature",
  "properties": {
    "iso:country":"GB",
    "wof:name":"TW2 5SH",
    "wof:placetype":"postalcode"
},
  "geometry": {"coordinates":[-0.34080339021542,51.43879289505568],"type":"Point"}
}