{
  "type": "Feature",
  "properties": {
    "date:inception_lower":"1980-01-01",
    "date:inception_upper":"1980-01-31",
    "iso:country":"GB",
    "wof:name":"TW2 5SH",
    "wof:placetype":"postalcode"
},
  "geometry": {"coordinates":[-0.340803,51.438793],"type":"Point"}
}