{
  "type": "Feature",
  "properties": {
    "iso:country":"GB",
    "wof:name":"M3 2GR",
    "wof:placetype":"postalcode"
},
  "geometry": {"coordinates":[-2.24816912452132,53.48119918562681],"type":"Point"}
}