{
  "type": "Feature",
  "properties": {
    "iso:country":"GB",
    "wof:name":"BD23 4NA",
    "wof:placetype":"postalcode"
},
  "geometry": {"coordinates":[-2.25500877933728,54.01879626047798],"type":"Point"}
}