{
  "type": "Feature",
  "properties": {
    "date:inception_lower":"1980-01-01",
    "date:inception_upper":"1980-01-31",
    "iso:country":"GB",
    "wof:name":"HR1 1SL",
    "wof:placetype":"postalcode"
},
  "geometry": {"coordinates":[-2.690548,52.052778],"type":"Point"}
}