{
  "type": "Feature",
  "properties": {
    "iso:country": "GB",
    "wof:name": "HR1 1SL",
    "wof:placetype": "postalcode"
  },
  "geometry": {"coordinates":[-2.690548,52.052778],"type":"Point"}
}
