{
  "type": "Feature",
  "properties": {
    "iso:country":"GB",
    "wof:name":"PR4 5WH",
    "wof:placetype":"postalcode"
},
  "geometry": {"coordinates":[-2.78460819929385,53.72792448369603],"type":"Point"}
}