{
  "type": "Feature",
  "properties": {
    "date:inception_lower": "1992-05-01",
    "date:inception_upper": "1992-05-01",
    "iso:country": "GB",
    "wof:name": "G81 2QR",
    "wof:placetype": "postalcode"
  },
  "geometry": {"coordinates":[-4.415066,55.907836],"type":"Point"}
}
