{
  "type": "Feature",
  "properties": {
    "iso:country": "GB",
    "wof:name": "G81 2QR",
    "wof:placetype": "postalcode"
  },
  "geometry": {"coordinates":[-4.415243,55.907859],"type":"Point"}
}
