{
  "type": "Feature",
  "properties": {
    "iso:country":"GB",
    "wof:name":"G81 2QR",
    "wof:placetype":"postalcode"
},
  "geometry": {"coordinates":[-4.41525845909512,55.9078652697965],"type":"Point"}
}