{
  "type": "Feature",
  "properties": {
    "iso:country":"GB",
    "wof:name":"LE9 4FE",
    "wof:placetype":"postalcode"
},
  "geometry": {"coordinates":[-1.27883778094467,52.53407996670896],"type":"Point"}
}