{
  "type": "Feature",
  "properties": {
    "iso:country": "GB",
    "wof:name": "LE9 4FE",
    "wof:placetype": "postalcode"
  },
  "geometry": {"coordinates":[-1.278838,52.53408],"type":"Point"}
}
