{
  "type": "Feature",
  "properties": {
    "iso:country": "GB",
    "wof:name": "DN21 1BQ",
    "wof:placetype": "postalcode"
  },
  "geometry": {"coordinates":[-0.770608,53.394468],"type":"Point"}
}
