{
  "type": "Feature",
  "properties": {
    "date:inception_lower": "1980-01-01",
    "date:inception_upper": "1980-01-01",
    "iso:country": "GB",
    "wof:name": "IP21 5EE",
    "wof:placetype": "postalcode"
  },
  "geometry": {"coordinates":[1.243477,52.304349],"type":"Point"}
}
