{
  "type": "Feature",
  "properties": {
    "iso:country":"GB",
    "wof:name":"IP21 5EE",
    "wof:placetype":"postalcode"
},
  "geometry": {"coordinates":[1.24347680389218,52.30434931396265],"type":"Point"}
}