{
  "type": "Feature",
  "properties": {
    "iso:country": "GB",
    "wof:name": "LN7 6UB",
    "wof:placetype": "postalcode"
  },
  "geometry": {"coordinates":[-0.31462,53.4964],"type":"Point"}
}
