{
  "type": "Feature",
  "properties": {
    "iso:country":"GB",
    "wof:name":"LN7 6UB",
    "wof:placetype":"postalcode"
},
  "geometry": {"coordinates":[-0.31462015595191,53.49640040262161],"type":"Point"}
}