{
  "type": "Feature",
  "properties": {
    "iso:country": "GB",
    "wof:name": "S66 1WS",
    "wof:placetype": "postalcode"
  },
  "geometry": {"coordinates":[-1.256863,53.41861],"type":"Point"}
}
