{
  "type": "Feature",
  "properties": {
    "iso:country":"GB",
    "wof:name":"S66 1WS",
    "wof:placetype":"postalcode"
},
  "geometry": {"coordinates":[-1.25686256799135,53.41860970254154],"type":"Point"}
}