{
  "type": "Feature",
  "properties": {
    "iso:country":"GB",
    "wof:name":"AB11 6FF",
    "wof:placetype":"postalcode"
},
  "geometry": {"coordinates":[-2.10249783085367,57.14207364061124],"type":"Point"}
}