{
  "type": "Feature",
  "properties": {
    "date:inception_lower": "2017-06-01",
    "date:inception_upper": "2017-06-01",
    "iso:country": "GB",
    "wof:name": "PE12 6FY",
    "wof:placetype": "postalcode"
  },
  "geometry": {"coordinates":[-0.158629,52.760909],"type":"Point"}
}
