{
  "type": "Feature",
  "properties": {
    "iso:country": "GB",
    "wof:name": "PE12 6FY",
    "wof:placetype": "postalcode"
  },
  "geometry": {"coordinates":[-0.158629,52.760909],"type":"Point"}
}
