{
  "type": "Feature",
  "properties": {
    "iso:country":"GB",
    "wof:name":"PE12 6FY",
    "wof:placetype":"postalcode"
},
  "geometry": {"coordinates":[-0.15789139477319,52.76004108378806],"type":"Point"}
}