{
  "type": "Feature",
  "properties": {
    "iso:country":"GB",
    "wof:name":"BD9 4JT",
    "wof:placetype":"postalcode"
},
  "geometry": {"coordinates":[-1.77447588467611,53.81633422406814],"type":"Point"}
}