{
  "type": "Feature",
  "properties": {
    "iso:country":"GB",
    "wof:name":"WA12 9PY",
    "wof:placetype":"postalcode"
},
  "geometry": {"coordinates":[-2.64052473952989,53.45416695446532],"type":"Point"}
}