{
  "type": "Feature",
  "properties": {
    "iso:country":"GB",
    "wof:name":"NR11 7QN",
    "wof:placetype":"postalcode"
},
  "geometry": {"coordinates":[1.24508434340994,52.83943230132007],"type":"Point"}
}