{
  "type": "Feature",
  "properties": {
    "date:inception_lower":"1980-01-01",
    "date:inception_upper":"1980-01-31",
    "iso:country":"GB",
    "wof:name":"HU16 4DT",
    "wof:placetype":"postalcode"
},
  "geometry": {"coordinates":[-0.41138,53.77969],"type":"Point"}
}