{
  "type": "Feature",
  "properties": {
    "iso:country":"GB",
    "wof:name":"HU16 4DT",
    "wof:placetype":"postalcode"
},
  "geometry": {"coordinates":[-0.41137991164631,53.77969043776469],"type":"Point"}
}