{
  "type": "Feature",
  "properties": {
    "iso:country":"GB",
    "wof:name":"CV36 4HF",
    "wof:placetype":"postalcode"
},
  "geometry": {"coordinates":[-1.62590015007328,52.06065615128633],"type":"Point"}
}