{
  "type": "Feature",
  "properties": {
    "iso:country":"GB",
    "wof:name":"DE4 3FH",
    "wof:placetype":"postalcode"
},
  "geometry": {"coordinates":[-1.55104956007794,53.14111828061704],"type":"Point"}
}