{
  "type": "Feature",
  "properties": {
    "date:inception_lower": "1980-01-01",
    "date:inception_upper": "1980-01-01",
    "iso:country": "GB",
    "wof:name": "DE4 3FH",
    "wof:placetype": "postalcode"
  },
  "geometry": {"coordinates":[-1.55105,53.141118],"type":"Point"}
}
