{
  "type": "Feature",
  "properties": {
    "iso:country":"GB",
    "wof:name":"AL3 8HG",
    "wof:placetype":"postalcode"
},
  "geometry": {"coordinates":[-0.43023093971559,51.82415505557646],"type":"Point"}
}