{
  "type": "Feature",
  "properties": {
    "date:inception_lower": "1980-01-01",
    "date:inception_upper": "1980-01-01",
    "iso:country": "GB",
    "wof:name": "AL3 8HG",
    "wof:placetype": "postalcode"
  },
  "geometry": {"coordinates":[-0.430394,51.824201],"type":"Point"}
}
