{
  "type": "Feature",
  "properties": {
    "iso:country": "GB",
    "wof:name": "CB8 7HE",
    "wof:placetype": "postalcode"
  },
  "geometry": {"coordinates":[0.369837,52.26427],"type":"Point"}
}
