{
  "type": "Feature",
  "properties": {
    "iso:country":"GB",
    "wof:name":"CB8 7HE",
    "wof:placetype":"postalcode"
},
  "geometry": {"coordinates":[0.36983669575613,52.26427047599974],"type":"Point"}
}