{
  "type": "Feature",
  "properties": {
    "iso:country":"GB",
    "wof:name":"TR3 7QX",
    "wof:placetype":"postalcode"
},
  "geometry": {"coordinates":[-5.11780394583559,50.21143097017436],"type":"Point"}
}