{
  "type": "Feature",
  "properties": {
    "iso:country":"GB",
    "wof:name":"ZE1 0AT",
    "wof:placetype":"postalcode"
},
  "geometry": {"coordinates":[-1.14288730551789,60.15064403137753],"type":"Point"}
}