{
  "type": "Feature",
  "properties": {
    "date:inception_lower": "1980-01-01",
    "date:inception_upper": "1980-01-01",
    "iso:country": "GB",
    "wof:name": "ZE1 0AT",
    "wof:placetype": "postalcode"
  },
  "geometry": {"coordinates":[-1.142895,60.150609],"type":"Point"}
}
