{
  "type": "Feature",
  "properties": {
    "iso:country":"GB",
    "wof:name":"SS9 5QR",
    "wof:placetype":"postalcode"
},
  "geometry": {"coordinates":[0.65954686354996,51.57162410865333],"type":"Point"}
}