{
  "type": "Feature",
  "properties": {
    "iso:country":"GB",
    "wof:name":"CR0 4PE",
    "wof:placetype":"postalcode"
},
  "geometry": {"coordinates":[-0.12566363629655,51.36786239303397],"type":"Point"}
}