{
  "type": "Feature",
  "properties": {
    "date:inception_lower": "1980-01-01",
    "date:inception_upper": "1980-01-01",
    "iso:country": "GB",
    "wof:name": "CR0 4PE",
    "wof:placetype": "postalcode"
  },
  "geometry": {"coordinates":[-0.125664,51.367862],"type":"Point"}
}
