{
  "type": "Feature",
  "properties": {
    "date:inception_lower": "2008-06-01",
    "date:inception_upper": "2008-06-01",
    "iso:country": "GB",
    "wof:name": "CF3 4JG",
    "wof:placetype": "postalcode"
  },
  "geometry": {"coordinates":[-3.131992,51.52278],"type":"Point"}
}
