{
  "type": "Feature",
  "properties": {
    "iso:country":"GB",
    "wof:name":"CF3 4JG",
    "wof:placetype":"postalcode"
},
  "geometry": {"coordinates":[-3.13199192134418,51.52278013808775],"type":"Point"}
}