{
  "type": "Feature",
  "properties": {
    "iso:country":"GB",
    "wof:name":"SR6 8DU",
    "wof:placetype":"postalcode"
},
  "geometry": {"coordinates":[-1.3770195861204,54.9344901972296],"type":"Point"}
}