{
  "type": "Feature",
  "properties": {
    "date:inception_lower": "2000-06-01",
    "date:inception_upper": "2000-06-01",
    "iso:country": "GB",
    "wof:name": "PE28 2ER",
    "wof:placetype": "postalcode"
  },
  "geometry": {"coordinates":[-0.108856,52.347575],"type":"Point"}
}
