{
  "type": "Feature",
  "properties": {
    "iso:country":"GB",
    "wof:name":"NR17 2EE",
    "wof:placetype":"postalcode"
},
  "geometry": {"coordinates":[1.013360154743,52.51762643650217],"type":"Point"}
}