{
  "type": "Feature",
  "properties": {
    "iso:country":"GB",
    "wof:name":"S61 3BJ",
    "wof:placetype":"postalcode"
},
  "geometry": {"coordinates":[-1.40614550898232,53.44738165395118],"type":"Point"}
}