{
  "type": "Feature",
  "properties": {
    "iso:country":"GB",
    "wof:name":"ST4 8PS",
    "wof:placetype":"postalcode"
},
  "geometry": {"coordinates":[-2.19132038866579,52.97211334677672],"type":"Point"}
}