{
  "type": "Feature",
  "properties": {
    "date:inception_lower": "1980-01-01",
    "date:inception_upper": "1980-01-01",
    "iso:country": "GB",
    "wof:name": "NE6 1DD",
    "wof:placetype": "postalcode"
  },
  "geometry": {"coordinates":[-1.585212,54.974424],"type":"Point"}
}
