{
  "type": "Feature",
  "properties": {
    "iso:country":"GB",
    "wof:name":"YO26 4UR",
    "wof:placetype":"postalcode"
},
  "geometry": {"coordinates":[-1.11276210110188,53.96102258015523],"type":"Point"}
}