{
  "type": "Feature",
  "properties": {
    "date:inception_lower": "2011-05-01",
    "date:inception_upper": "2011-05-01",
    "iso:country": "GB",
    "wof:name": "KY11 8ST",
    "wof:placetype": "postalcode"
  },
  "geometry": {"coordinates":[-3.390704,56.063851],"type":"Point"}
}
