{
  "type": "Feature",
  "properties": {
    "iso:country":"GB",
    "wof:name":"KY11 8ST",
    "wof:placetype":"postalcode"
},
  "geometry": {"coordinates":[-3.39070428587449,56.0638508673981],"type":"Point"}
}