{
  "type": "Feature",
  "properties": {
    "iso:country":"GB",
    "wof:name":"NP18 1RE",
    "wof:placetype":"postalcode"
},
  "geometry": {"coordinates":[-2.95437660456754,51.61197454410124],"type":"Point"}
}