{
  "type": "Feature",
  "properties": {
    "iso:country":"GB",
    "wof:name":"NW5 9ES",
    "wof:placetype":"postalcode"
},
  "geometry": {"coordinates":[-0.14672635144816,51.55083666414147],"type":"Point"}
}