{
  "type": "Feature",
  "properties": {
    "iso:country":"GB",
    "wof:name":"SE28 8LX",
    "wof:placetype":"postalcode"
},
  "geometry": {"coordinates":[0.11907385461,51.50998769488058],"type":"Point"}
}