{
  "type": "Feature",
  "properties": {
    "iso:country":"GB",
    "wof:name":"LE4 1BN",
    "wof:placetype":"postalcode"
},
  "geometry": {"coordinates":[-1.17040270210931,52.67498959725672],"type":"Point"}
}