{
  "type": "Feature",
  "properties": {
    "iso:country": "GB",
    "wof:name": "BN10 7HY",
    "wof:placetype": "postalcode"
  },
  "geometry": {"coordinates":[-0.007686,50.791921],"type":"Point"}
}
