{
  "type": "Feature",
  "properties": {
    "iso:country":"GB",
    "wof:name":"NW6 1XR",
    "wof:placetype":"postalcode"
},
  "geometry": {"coordinates":[-0.18501881191444,51.55018533464584],"type":"Point"}
}