{
  "type": "Feature",
  "properties": {
    "date:inception_lower":"1990-02-01",
    "date:inception_upper":"1990-02-28",
    "iso:country":"GB",
    "wof:name":"CF48 1TL",
    "wof:placetype":"postalcode"
},
  "geometry": {"coordinates":[-3.408998,51.744999],"type":"Point"}
}