{
  "type": "Feature",
  "properties": {
    "iso:country":"GB",
    "wof:name":"BA22 8ZB",
    "wof:placetype":"postalcode"
},
  "geometry": {"coordinates":[-2.68210602102554,50.94542077068879],"type":"Point"}
}