{
  "type": "Feature",
  "properties": {
    "iso:country":"GB",
    "wof:name":"S35 0AN",
    "wof:placetype":"postalcode"
},
  "geometry": {"coordinates":[-1.54014341499282,53.4242603811934],"type":"Point"}
}