{
  "type": "Feature",
  "properties": {
    "date:inception_lower": "1980-01-01",
    "date:inception_upper": "1980-01-01",
    "iso:country": "GB",
    "wof:name": "DY4 7NQ",
    "wof:placetype": "postalcode"
  },
  "geometry": {"coordinates":[-2.040585,52.533643],"type":"Point"}
}
