{
  "type": "Feature",
  "properties": {
    "iso:country":"GB",
    "wof:name":"LE13 1TD",
    "wof:placetype":"postalcode"
},
  "geometry": {"coordinates":[-0.88522546924876,52.7723146638885],"type":"Point"}
}