{
  "type": "Feature",
  "properties": {
    "date:inception_lower": "1980-01-01",
    "date:inception_upper": "1980-01-01",
    "iso:country": "GB",
    "wof:name": "LE13 1TD",
    "wof:placetype": "postalcode"
  },
  "geometry": {"coordinates":[-0.885225,52.772315],"type":"Point"}
}
