{
  "type": "Feature",
  "properties": {
    "iso:country": "GB",
    "wof:name": "ME8 8QS",
    "wof:placetype": "postalcode"
  },
  "geometry": {"coordinates":[0.617863,51.360313],"type":"Point"}
}
