{
  "type": "Feature",
  "properties": {
    "iso:country": "GB",
    "wof:name": "DN12 2AD",
    "wof:placetype": "postalcode"
  },
  "geometry": {"coordinates":[-1.21796,53.4821],"type":"Point"}
}
