{
  "type": "Feature",
  "properties": {
    "date:inception_lower":"1980-01-01",
    "date:inception_upper":"1980-01-31",
    "iso:country":"GB",
    "wof:name":"GL11 4BN",
    "wof:placetype":"postalcode"
},
  "geometry": {"coordinates":[-2.354122,51.681128],"type":"Point"}
}