{
  "type": "Feature",
  "properties": {
    "iso:country": "GB",
    "wof:name": "ST1 6EJ",
    "wof:placetype": "postalcode"
  },
  "geometry": {"coordinates":[-2.164919,53.04634],"type":"Point"}
}
