{
  "type": "Feature",
  "properties": {
    "date:inception_lower":"1980-01-01",
    "date:inception_upper":"1980-01-31",
    "iso:country":"GB",
    "wof:name":"ST1 6EJ",
    "wof:placetype":"postalcode"
},
  "geometry": {"coordinates":[-2.164919,53.04634],"type":"Point"}
}