{
  "type": "Feature",
  "properties": {
    "date:inception_lower":"1981-06-01",
    "date:inception_upper":"1981-06-30",
    "iso:country":"GB",
    "wof:name":"NE37 1PL",
    "wof:placetype":"postalcode"
},
  "geometry": {"coordinates":[-1.533319,54.921414],"type":"Point"}
}