{
  "type": "Feature",
  "properties": {
    "date:inception_lower":"2011-05-01",
    "date:inception_upper":"2011-05-31",
    "iso:country":"GB",
    "wof:name":"SK7 1YJ",
    "wof:placetype":"postalcode"
},
  "geometry": {"coordinates":[-2.165514,53.356375],"type":"Point"}
}