{
  "type": "Feature",
  "properties": {
    "iso:country":"GB",
    "wof:name":"LS2 7ES",
    "wof:placetype":"postalcode"
},
  "geometry": {"coordinates":[-1.53769575899345,53.79484860596695],"type":"Point"}
}