{
  "type": "Feature",
  "properties": {
    "date:inception_lower":"2016-03-01",
    "date:inception_upper":"2016-03-31",
    "iso:country":"GB",
    "wof:name":"HR2 6NX",
    "wof:placetype":"postalcode"
},
  "geometry": {"coordinates":[-2.688815,52.034816],"type":"Point"}
}