{
  "type": "Feature",
  "properties": {
    "iso:country":"GB",
    "wof:name":"HR2 6NX",
    "wof:placetype":"postalcode"
},
  "geometry": {"coordinates":[-2.68887169409226,52.03480634462152],"type":"Point"}
}