{
  "type": "Feature",
  "properties": {
    "iso:country": "GB",
    "wof:name": "HR2 6NX",
    "wof:placetype": "postalcode"
  },
  "geometry": {"coordinates":[-2.688815,52.034816],"type":"Point"}
}
