{
  "type": "Feature",
  "properties": {
    "date:inception_lower": "2016-03-01",
    "date:inception_upper": "2016-03-01",
    "iso:country": "GB",
    "wof:name": "HR2 6NX",
    "wof:placetype": "postalcode"
  },
  "geometry": {"coordinates":[-2.688816,52.034843],"type":"Point"}
}
