{
  "type": "Feature",
  "properties": {
    "date:inception_lower":"1980-01-01",
    "date:inception_upper":"1980-01-31",
    "iso:country":"GB",
    "wof:name":"IP17 3NP",
    "wof:placetype":"postalcode"
},
  "geometry": {"coordinates":[1.560781,52.254661],"type":"Point"}
}