{
  "type": "Feature",
  "properties": {
    "iso:country":"GB",
    "wof:name":"IP17 3NP",
    "wof:placetype":"postalcode"
},
  "geometry": {"coordinates":[1.56078128788972,52.25466114492793],"type":"Point"}
}