{
  "type": "Feature",
  "properties": {
    "iso:country":"GB",
    "wof:name":"HA8 8FB",
    "wof:placetype":"postalcode"
},
  "geometry": {"coordinates":[-0.28483495705128,51.61981219296733],"type":"Point"}
}