{
  "type": "Feature",
  "properties": {
    "date:inception_lower": "1980-01-01",
    "date:inception_upper": "1980-01-01",
    "iso:country": "GB",
    "wof:name": "PO9 3SA",
    "wof:placetype": "postalcode"
  },
  "geometry": {"coordinates":[-0.994882,50.864297],"type":"Point"}
}
