{
  "type": "Feature",
  "properties": {
    "iso:country":"GB",
    "wof:name":"M24 1EY",
    "wof:placetype":"postalcode"
},
  "geometry": {"coordinates":[-2.18575103899193,53.54217309617231],"type":"Point"}
}