{
  "type": "Feature",
  "properties": {
    "date:inception_lower": "1980-01-01",
    "date:inception_upper": "1980-01-01",
    "iso:country": "GB",
    "wof:name": "M24 1EY",
    "wof:placetype": "postalcode"
  },
  "geometry": {"coordinates":[-2.185751,53.542173],"type":"Point"}
}
