{
  "type": "Feature",
  "properties": {
    "date:inception_lower": "2005-09-01",
    "date:inception_upper": "2005-09-01",
    "iso:country": "GB",
    "wof:name": "DL15 9GR",
    "wof:placetype": "postalcode"
  },
  "geometry": {"coordinates":[-1.752179,54.710624],"type":"Point"}
}
