{
  "type": "Feature",
  "properties": {
    "iso:country":"GB",
    "wof:name":"DL15 9GR",
    "wof:placetype":"postalcode"
},
  "geometry": {"coordinates":[-1.75217951652377,54.71062367535264],"type":"Point"}
}