{
  "type": "Feature",
  "properties": {
    "iso:country":"GB",
    "wof:name":"LA4 4JP",
    "wof:placetype":"postalcode"
},
  "geometry": {"coordinates":[-2.87374816317526,54.06562951307559],"type":"Point"}
}