{
  "type": "Feature",
  "properties": {
    "iso:country":"GB",
    "wof:name":"IG6 3XQ",
    "wof:placetype":"postalcode"
},
  "geometry": {"coordinates":[0.12149898240165,51.61298293436164],"type":"Point"}
}