{
  "type": "Feature",
  "properties": {
    "date:inception_lower": "1981-06-01",
    "date:inception_upper": "1981-06-01",
    "iso:country": "GB",
    "wof:name": "SR4 0NL",
    "wof:placetype": "postalcode"
  },
  "geometry": {"coordinates":[-1.446186,54.901818],"type":"Point"}
}
