{
  "type": "Feature",
  "properties": {
    "iso:country":"GB",
    "wof:name":"SR4 0NL",
    "wof:placetype":"postalcode"
},
  "geometry": {"coordinates":[-1.44618621260079,54.90181770041261],"type":"Point"}
}