{
  "type": "Feature",
  "properties": {
    "date:inception_lower": "1980-01-01",
    "date:inception_upper": "1980-01-01",
    "iso:country": "GB",
    "wof:name": "NE38 9EL",
    "wof:placetype": "postalcode"
  },
  "geometry": {"coordinates":[-1.548079,54.882397],"type":"Point"}
}
