{
  "type": "Feature",
  "properties": {
    "iso:country":"GB",
    "wof:name":"WN5 0HS",
    "wof:placetype":"postalcode"
},
  "geometry": {"coordinates":[-2.68526219064694,53.54927860044025],"type":"Point"}
}