{
  "type": "Feature",
  "properties": {
    "iso:country": "GB",
    "wof:name": "WN5 0HS",
    "wof:placetype": "postalcode"
  },
  "geometry": {"coordinates":[-2.685262,53.549279],"type":"Point"}
}
