{
  "type": "Feature",
  "properties": {
    "iso:country":"GB",
    "wof:name":"IP32 7AF",
    "wof:placetype":"postalcode"
},
  "geometry": {"coordinates":[0.72922843968709,52.2503188961177],"type":"Point"}
}