{
  "type": "Feature",
  "properties": {
    "iso:country":"GB",
    "wof:name":"B14 5HR",
    "wof:placetype":"postalcode"
},
  "geometry": {"coordinates":[-1.88685225008508,52.4083568538556],"type":"Point"}
}