{
  "type": "Feature",
  "properties": {
    "iso:country": "GB",
    "wof:name": "B14 5HR",
    "wof:placetype": "postalcode"
  },
  "geometry": {"coordinates":[-1.886852,52.408357],"type":"Point"}
}
