{
  "type": "Feature",
  "properties": {
    "date:inception_lower":"2004-08-01",
    "date:inception_upper":"2004-08-31",
    "iso:country":"GB",
    "wof:name":"RG14 7RB",
    "wof:placetype":"postalcode"
},
  "geometry": {"coordinates":[-1.31763,51.395621],"type":"Point"}
}