{
  "type": "Feature",
  "properties": {
    "iso:country":"GB",
    "wof:name":"RG14 7RB",
    "wof:placetype":"postalcode"
},
  "geometry": {"coordinates":[-1.31763030606989,51.3956212391381],"type":"Point"}
}