{
  "type": "Feature",
  "properties": {
    "iso:country":"GB",
    "wof:name":"GU22 8DP",
    "wof:placetype":"postalcode"
},
  "geometry": {"coordinates":[-0.53417832542113,51.32005517231806],"type":"Point"}
}