{
  "type": "Feature",
  "properties": {
    "iso:country":"GB",
    "wof:name":"B70 9LZ",
    "wof:placetype":"postalcode"
},
  "geometry": {"coordinates":[-2.01017042522185,52.52399443940352],"type":"Point"}
}