{
  "type": "Feature",
  "properties": {
    "iso:country": "GB",
    "wof:name": "B70 9LZ",
    "wof:placetype": "postalcode"
  },
  "geometry": {"coordinates":[-2.010002,52.523947],"type":"Point"}
}
