{
  "type": "Feature",
  "properties": {
    "iso:country":"GB",
    "wof:name":"B77 1BB",
    "wof:placetype":"postalcode"
},
  "geometry": {"coordinates":[-1.68482524231606,52.62497249591843],"type":"Point"}
}