{
  "type": "Feature",
  "properties": {
    "date:inception_lower": "1981-09-01",
    "date:inception_upper": "1981-09-01",
    "iso:country": "GB",
    "wof:name": "B77 1BB",
    "wof:placetype": "postalcode"
  },
  "geometry": {"coordinates":[-1.684847,52.625071],"type":"Point"}
}
