{
  "type": "Feature",
  "properties": {
    "iso:country": "GB",
    "wof:name": "GL12 8LW",
    "wof:placetype": "postalcode"
  },
  "geometry": {"coordinates":[-2.397712,51.589934],"type":"Point"}
}
