{
  "type": "Feature",
  "properties": {
    "date:inception_lower": "1988-03-01",
    "date:inception_upper": "1988-03-01",
    "iso:country": "GB",
    "wof:name": "GL12 8LW",
    "wof:placetype": "postalcode"
  },
  "geometry": {"coordinates":[-2.397739,51.589979],"type":"Point"}
}
