{
  "type": "Feature",
  "properties": {
    "iso:country":"GB",
    "wof:name":"GL12 8LW",
    "wof:placetype":"postalcode"
},
  "geometry": {"coordinates":[-2.39771193174846,51.58993350806507],"type":"Point"}
}