{
  "type": "Feature",
  "properties": {
    "iso:country":"GB",
    "wof:name":"WA2 9TD",
    "wof:placetype":"postalcode"
},
  "geometry": {"coordinates":[-2.59745952632475,53.4190468154052],"type":"Point"}
}