{
  "type": "Feature",
  "properties": {
    "date:inception_lower": "1998-06-01",
    "date:inception_upper": "1998-06-01",
    "iso:country": "GB",
    "wof:name": "B31 5EA",
    "wof:placetype": "postalcode"
  },
  "geometry": {"coordinates":[-2.001161,52.402396],"type":"Point"}
}
