{
  "type": "Feature",
  "properties": {
    "iso:country":"GB",
    "wof:name":"B31 5EA",
    "wof:placetype":"postalcode"
},
  "geometry": {"coordinates":[-2.00116108359586,52.40239637334799],"type":"Point"}
}