{
  "type": "Feature",
  "properties": {
    "iso:country":"GB",
    "wof:name":"M25 9GZ",
    "wof:placetype":"postalcode"
},
  "geometry": {"coordinates":[-2.28413703418299,53.52165685439124],"type":"Point"}
}