{
  "type": "Feature",
  "properties": {
    "date:inception_lower":"1994-05-01",
    "date:inception_upper":"1994-05-31",
    "iso:country":"GB",
    "wof:name":"M25 9GZ",
    "wof:placetype":"postalcode"
},
  "geometry": {"coordinates":[-2.284137,53.521657],"type":"Point"}
}