{
  "type": "Feature",
  "properties": {
    "iso:country":"GB",
    "wof:name":"RG40 3HE",
    "wof:placetype":"postalcode"
},
  "geometry": {"coordinates":[-0.84684054466633,51.39357185956198],"type":"Point"}
}