{
  "type": "Feature",
  "properties": {
    "iso:country": "GB",
    "wof:name": "RG40 3HE",
    "wof:placetype": "postalcode"
  },
  "geometry": {"coordinates":[-0.846841,51.393572],"type":"Point"}
}
