{
  "type": "Feature",
  "properties": {
    "iso:country":"GB",
    "wof:name":"ST3 5RY",
    "wof:placetype":"postalcode"
},
  "geometry": {"coordinates":[-2.11157472286446,52.99309701164203],"type":"Point"}
}