{
  "type": "Feature",
  "properties": {
    "iso:country": "GB",
    "wof:name": "ST3 5RY",
    "wof:placetype": "postalcode"
  },
  "geometry": {"coordinates":[-2.111575,52.993097],"type":"Point"}
}
