{
  "type": "Feature",
  "properties": {
    "iso:country":"GB",
    "wof:name":"AB53 4BD",
    "wof:placetype":"postalcode"
},
  "geometry": {"coordinates":[-2.46543137754772,57.53836553463157],"type":"Point"}
}