{
  "type": "Feature",
  "properties": {
    "iso:country":"GB",
    "wof:name":"SS8 8DY",
    "wof:placetype":"postalcode"
},
  "geometry": {"coordinates":[0.59888975609036,51.5268651588381],"type":"Point"}
}