{
  "type": "Feature",
  "properties": {
    "date:inception_lower": "1980-01-01",
    "date:inception_upper": "1980-01-01",
    "iso:country": "GB",
    "wof:name": "HD7 5HX",
    "wof:placetype": "postalcode"
  },
  "geometry": {"coordinates":[-1.888126,53.617794],"type":"Point"}
}
