{
  "type": "Feature",
  "properties": {
    "iso:country":"GB",
    "wof:name":"HD7 5HX",
    "wof:placetype":"postalcode"
},
  "geometry": {"coordinates":[-1.88812611483659,53.61779426949609],"type":"Point"}
}