{
  "type": "Feature",
  "properties": {
    "date:inception_lower": "1980-01-01",
    "date:inception_upper": "1980-01-01",
    "iso:country": "GB",
    "wof:name": "CO4 3PY",
    "wof:placetype": "postalcode"
  },
  "geometry": {"coordinates":[0.936416,51.890453],"type":"Point"}
}
