{
  "type": "Feature",
  "properties": {
    "iso:country":"GB",
    "wof:name":"SK8 6NS",
    "wof:placetype":"postalcode"
},
  "geometry": {"coordinates":[-2.19666073772812,53.35977007672764],"type":"Point"}
}