{
  "type": "Feature",
  "properties": {
    "date:inception_lower": "1980-01-01",
    "date:inception_upper": "1980-01-01",
    "iso:country": "GB",
    "wof:name": "SK8 6NS",
    "wof:placetype": "postalcode"
  },
  "geometry": {"coordinates":[-2.196661,53.35977],"type":"Point"}
}
