{
  "type": "Feature",
  "properties": {
    "date:inception_lower":"1980-01-01",
    "date:inception_upper":"1980-01-31",
    "iso:country":"GB",
    "wof:name":"CA2 4BB",
    "wof:placetype":"postalcode"
},
  "geometry": {"coordinates":[-2.931942,54.882309],"type":"Point"}
}