{
  "type": "Feature",
  "properties": {
    "iso:country":"GB",
    "wof:name":"CA2 4BB",
    "wof:placetype":"postalcode"
},
  "geometry": {"coordinates":[-2.93193847735186,54.88229328962277],"type":"Point"}
}