{
  "type": "Feature",
  "properties": {
    "date:inception_lower":"1990-07-01",
    "date:inception_upper":"1990-07-31",
    "iso:country":"GB",
    "wof:name":"CR5 2HA",
    "wof:placetype":"postalcode"
},
  "geometry": {"coordinates":[-0.135494,51.313991],"type":"Point"}
}