{
  "type": "Feature",
  "properties": {
    "iso:country":"GB",
    "wof:name":"CR5 2HA",
    "wof:placetype":"postalcode"
},
  "geometry": {"coordinates":[-0.13549391046847,51.31399081544915],"type":"Point"}
}