{
  "type": "Feature",
  "properties": {
    "iso:country": "GB",
    "wof:name": "CB4 2NN",
    "wof:placetype": "postalcode"
  },
  "geometry": {"coordinates":[0.138543,52.227963],"type":"Point"}
}
