{
  "type": "Feature",
  "properties": {
    "date:inception_lower": "1980-01-01",
    "date:inception_upper": "1980-01-01",
    "iso:country": "GB",
    "wof:name": "CB4 2NN",
    "wof:placetype": "postalcode"
  },
  "geometry": {"coordinates":[0.138543,52.227963],"type":"Point"}
}
