{
  "type": "Feature",
  "properties": {
    "iso:country":"GB",
    "wof:name":"CB4 2NN",
    "wof:placetype":"postalcode"
},
  "geometry": {"coordinates":[0.13854265268196,52.22796345614591],"type":"Point"}
}