{
  "type": "Feature",
  "properties": {
    "iso:country": "GB",
    "wof:name": "ST20 0FG",
    "wof:placetype": "postalcode"
  },
  "geometry": {"coordinates":[-2.249255,52.782516],"type":"Point"}
}
