{
  "type": "Feature",
  "properties": {
    "iso:country":"GB",
    "wof:name":"CH1 4LT",
    "wof:placetype":"postalcode"
},
  "geometry": {"coordinates":[-2.91628365961331,53.19253360330799],"type":"Point"}
}