{
  "type": "Feature",
  "properties": {
    "iso:country": "GB",
    "wof:name": "CH1 4LT",
    "wof:placetype": "postalcode"
  },
  "geometry": {"coordinates":[-2.916284,53.192534],"type":"Point"}
}
