{
  "type": "Feature",
  "properties": {
    "iso:country": "GB",
    "wof:name": "CA7 4SP",
    "wof:placetype": "postalcode"
  },
  "geometry": {"coordinates":[-3.291939,54.847354],"type":"Point"}
}
