{
  "type": "Feature",
  "properties": {
    "iso:country":"GB",
    "wof:name":"CF5 1GB",
    "wof:placetype":"postalcode"
},
  "geometry": {"coordinates":[-3.21431180093383,51.48706807420415],"type":"Point"}
}