{
  "type": "Feature",
  "properties": {
    "iso:country": "GB",
    "wof:name": "S40 4AT",
    "wof:placetype": "postalcode"
  },
  "geometry": {"coordinates":[-1.44466,53.240367],"type":"Point"}
}
