{
  "type": "Feature",
  "properties": {
    "iso:country":"GB",
    "wof:name":"S40 4AT",
    "wof:placetype":"postalcode"
},
  "geometry": {"coordinates":[-1.44466049207682,53.24036684121059],"type":"Point"}
}