{
  "type": "Feature",
  "properties": {
    "iso:country":"GB",
    "wof:name":"CA15 6EH",
    "wof:placetype":"postalcode"
},
  "geometry": {"coordinates":[-3.49861783795278,54.71624089333981],"type":"Point"}
}