{
  "type": "Feature",
  "properties": {
    "iso:country": "GB",
    "wof:name": "CA15 6EH",
    "wof:placetype": "postalcode"
  },
  "geometry": {"coordinates":[-3.498215,54.716262],"type":"Point"}
}
