{
  "type": "Feature",
  "properties": {
    "iso:country":"GB",
    "wof:name":"WV6 7NR",
    "wof:placetype":"postalcode"
},
  "geometry": {"coordinates":[-2.19306283314217,52.59747286207904],"type":"Point"}
}