{
  "type": "Feature",
  "properties": {
    "iso:country":"GB",
    "wof:name":"SA71 5HU",
    "wof:placetype":"postalcode"
},
  "geometry": {"coordinates":[-4.97052153243056,51.63887825035835],"type":"Point"}
}