{
  "type": "Feature",
  "properties": {
    "iso:country": "GB",
    "wof:name": "SA71 5HU",
    "wof:placetype": "postalcode"
  },
  "geometry": {"coordinates":[-4.970601,51.638879],"type":"Point"}
}
