{
  "type": "Feature",
  "properties": {
    "iso:country":"GB",
    "wof:name":"RH5 6BT",
    "wof:placetype":"postalcode"
},
  "geometry": {"coordinates":[-0.32774354219057,51.25364877611333],"type":"Point"}
}