{
  "type": "Feature",
  "properties": {
    "iso:country":"GB",
    "wof:name":"M6 7GU",
    "wof:placetype":"postalcode"
},
  "geometry": {"coordinates":[-2.30650967632228,53.49934620170893],"type":"Point"}
}