{
  "type": "Feature",
  "properties": {
    "iso:country":"GB",
    "wof:name":"NP25 3DU",
    "wof:placetype":"postalcode"
},
  "geometry": {"coordinates":[-2.71597465764789,51.82671059629398],"type":"Point"}
}