{
  "type": "Feature",
  "properties": {
    "iso:country":"GB",
    "wof:name":"BS1 4JP",
    "wof:placetype":"postalcode"
},
  "geometry": {"coordinates":[-2.59508690810119,51.45136595622574],"type":"Point"}
}