{
  "type": "Feature",
  "properties": {
    "iso:country":"GB",
    "wof:name":"WF10 2NT",
    "wof:placetype":"postalcode"
},
  "geometry": {"coordinates":[-1.30842135052595,53.73005568101915],"type":"Point"}
}