{
  "type": "Feature",
  "properties": {
    "iso:country":"GB",
    "wof:name":"B65 9EE",
    "wof:placetype":"postalcode"
},
  "geometry": {"coordinates":[-2.0421207345447,52.48980764504379],"type":"Point"}
}