{
  "type": "Feature",
  "properties": {
    "date:inception_lower": "1993-01-01",
    "date:inception_upper": "1993-01-01",
    "iso:country": "GB",
    "wof:name": "SY1 4DL",
    "wof:placetype": "postalcode"
  },
  "geometry": {"coordinates":[-2.735869,52.729041],"type":"Point"}
}
