{
  "type": "Feature",
  "properties": {
    "date:inception_lower":"2000-06-01",
    "date:inception_upper":"2000-06-30",
    "iso:country":"GB",
    "wof:name":"CA7 1DD",
    "wof:placetype":"postalcode"
},
  "geometry": {"coordinates":[-3.183543,54.753122],"type":"Point"}
}