{
  "type": "Feature",
  "properties": {
    "date:inception_lower": "2000-06-01",
    "date:inception_upper": "2000-06-01",
    "iso:country": "GB",
    "wof:name": "CA7 1DD",
    "wof:placetype": "postalcode"
  },
  "geometry": {"coordinates":[-3.186319,54.752376],"type":"Point"}
}
