{
  "type": "Feature",
  "properties": {
    "iso:country":"GB",
    "wof:name":"WF1 5RD",
    "wof:placetype":"postalcode"
},
  "geometry": {"coordinates":[-1.49095774628748,53.67402937547794],"type":"Point"}
}