{
  "type": "Feature",
  "properties": {
    "iso:country": "GB",
    "wof:name": "WF1 5RD",
    "wof:placetype": "postalcode"
  },
  "geometry": {"coordinates":[-1.490958,53.674029],"type":"Point"}
}
