{
  "type": "Feature",
  "properties": {
    "iso:country":"GB",
    "wof:name":"NN5 7JT",
    "wof:placetype":"postalcode"
},
  "geometry": {"coordinates":[-0.91555883011308,52.25484309338614],"type":"Point"}
}