{
  "type": "Feature",
  "properties": {
    "date:inception_lower": "2000-12-01",
    "date:inception_upper": "2000-12-01",
    "iso:country": "GB",
    "wof:name": "NN5 7JT",
    "wof:placetype": "postalcode"
  },
  "geometry": {"coordinates":[-0.915559,52.254843],"type":"Point"}
}
