{
  "type": "Feature",
  "properties": {
    "iso:country": "GB",
    "wof:name": "SG4 8LE",
    "wof:placetype": "postalcode"
  },
  "geometry": {"coordinates":[-0.314801,51.904687],"type":"Point"}
}
