{
  "type": "Feature",
  "properties": {
    "iso:country":"GB",
    "wof:name":"EX19 8BH",
    "wof:placetype":"postalcode"
},
  "geometry": {"coordinates":[-4.02786843398839,50.85616095020663],"type":"Point"}
}