{
  "type": "Feature",
  "properties": {
    "iso:country": "GB",
    "wof:name": "EX19 8BH",
    "wof:placetype": "postalcode"
  },
  "geometry": {"coordinates":[-4.027868,50.856161],"type":"Point"}
}
