{
  "type": "Feature",
  "properties": {
    "date:inception_lower": "2016-06-01",
    "date:inception_upper": "2016-06-01",
    "iso:country": "GB",
    "wof:name": "PA7 5FF",
    "wof:placetype": "postalcode"
  },
  "geometry": {"coordinates":[-4.497505,55.897203],"type":"Point"}
}
