{
  "type": "Feature",
  "properties": {
    "iso:country": "GB",
    "wof:name": "PA7 5FF",
    "wof:placetype": "postalcode"
  },
  "geometry": {"coordinates":[-4.497505,55.897203],"type":"Point"}
}
