{
  "type": "Feature",
  "properties": {
    "iso:country":"GB",
    "wof:name":"LL11 2RL",
    "wof:placetype":"postalcode"
},
  "geometry": {"coordinates":[-2.99789994758671,53.05957247945761],"type":"Point"}
}