{
  "type": "Feature",
  "properties": {
    "iso:country": "GB",
    "wof:name": "PR4 1BS",
    "wof:placetype": "postalcode"
  },
  "geometry": {"coordinates":[-2.898119,53.751396],"type":"Point"}
}
