{
  "type": "Feature",
  "properties": {
    "iso:country":"GB",
    "wof:name":"PR4 1BS",
    "wof:placetype":"postalcode"
},
  "geometry": {"coordinates":[-2.89811936025585,53.7513958624245],"type":"Point"}
}