{
  "type": "Feature",
  "properties": {
    "date:inception_lower": "2024-09-01",
    "date:inception_upper": "2024-09-01",
    "iso:country": "GB",
    "wof:name": "HU10 6FG",
    "wof:placetype": "postalcode"
  },
  "geometry": {"coordinates":[-0.445829,53.760602],"type":"Point"}
}
