{
  "type": "Feature",
  "properties": {
    "date:inception_lower":"1980-01-01",
    "date:inception_upper":"1980-01-31",
    "iso:country":"GB",
    "wof:name":"BB9 9BW",
    "wof:placetype":"postalcode"
},
  "geometry": {"coordinates":[-2.211762,53.833732],"type":"Point"}
}