{
  "type": "Feature",
  "properties": {
    "iso:country": "GB",
    "wof:name": "BB9 9BW",
    "wof:placetype": "postalcode"
  },
  "geometry": {"coordinates":[-2.211703,53.833773],"type":"Point"}
}
