{
  "type": "Feature",
  "properties": {
    "iso:country":"GB",
    "wof:name":"NR4 6JB",
    "wof:placetype":"postalcode"
},
  "geometry": {"coordinates":[1.26687485083529,52.60877199949334],"type":"Point"}
}