{
  "type": "Feature",
  "properties": {
    "iso:country":"GB",
    "wof:name":"DE74 2DQ",
    "wof:placetype":"postalcode"
},
  "geometry": {"coordinates":[-1.28439268253343,52.83483248253587],"type":"Point"}
}