{
  "type": "Feature",
  "properties": {
    "date:inception_lower": "2023-05-01",
    "date:inception_upper": "2023-05-01",
    "iso:country": "GB",
    "wof:name": "MK10 9XH",
    "wof:placetype": "postalcode"
  },
  "geometry": {"coordinates":[-0.703579,52.047497],"type":"Point"}
}
