{
  "type": "Feature",
  "properties": {
    "iso:country":"GB",
    "wof:name":"RG6 5XP",
    "wof:placetype":"postalcode"
},
  "geometry": {"coordinates":[-0.93644955402514,51.42616974888362],"type":"Point"}
}