{
  "type": "Feature",
  "properties": {
    "iso:country": "GB",
    "wof:name": "CH1 1XS",
    "wof:placetype": "postalcode"
  },
  "geometry": {"coordinates":[-2.893549,53.188976],"type":"Point"}
}
