{
  "type": "Feature",
  "properties": {
    "date:inception_lower":"1980-01-01",
    "date:inception_upper":"1980-01-31",
    "iso:country":"GB",
    "wof:name":"CH1 1XS",
    "wof:placetype":"postalcode"
},
  "geometry": {"coordinates":[-2.893549,53.188976],"type":"Point"}
}