{
  "type": "Feature",
  "properties": {
    "iso:country":"GB",
    "wof:name":"CV13 0DU",
    "wof:placetype":"postalcode"
},
  "geometry": {"coordinates":[-1.41085894471926,52.64289611517913],"type":"Point"}
}