{
  "type": "Feature",
  "properties": {
    "date:inception_lower":"2012-06-01",
    "date:inception_upper":"2012-06-30",
    "iso:country":"GB",
    "wof:name":"CV13 0DU",
    "wof:placetype":"postalcode"
},
  "geometry": {"coordinates":[-1.410859,52.642896],"type":"Point"}
}