{
  "type": "Feature",
  "properties": {
    "iso:country": "GB",
    "wof:name": "CV13 0DU",
    "wof:placetype": "postalcode"
  },
  "geometry": {"coordinates":[-1.410859,52.642896],"type":"Point"}
}
