{
  "type": "Feature",
  "properties": {
    "iso:country":"GB",
    "wof:name":"B37 5RS",
    "wof:placetype":"postalcode"
},
  "geometry": {"coordinates":[-1.74400737802354,52.47739343894108],"type":"Point"}
}