{
  "type": "Feature",
  "properties": {
    "iso:country":"GB",
    "wof:name":"LL77 7NP",
    "wof:placetype":"postalcode"
},
  "geometry": {"coordinates":[-4.32495312631737,53.25991887894892],"type":"Point"}
}