{
  "type": "Feature",
  "properties": {
    "iso:country":"GB",
    "wof:name":"SK17 9TQ",
    "wof:placetype":"postalcode"
},
  "geometry": {"coordinates":[-1.81267070941815,53.24554831463607],"type":"Point"}
}