{
  "type": "Feature",
  "properties": {
    "iso:country": "GB",
    "wof:name": "SK17 9TQ",
    "wof:placetype": "postalcode"
  },
  "geometry": {"coordinates":[-1.812671,53.245548],"type":"Point"}
}
