{
  "type": "Feature",
  "properties": {
    "iso:country":"GB",
    "wof:name":"DH7 0PF",
    "wof:placetype":"postalcode"
},
  "geometry": {"coordinates":[-1.74705690023964,54.82300764552739],"type":"Point"}
}