{
  "type": "Feature",
  "properties": {
    "iso:country":"GB",
    "wof:name":"KT6 6PD",
    "wof:placetype":"postalcode"
},
  "geometry": {"coordinates":[-0.30668722648494,51.38901735769318],"type":"Point"}
}