{
  "type": "Feature",
  "properties": {
    "date:inception_lower": "1980-01-01",
    "date:inception_upper": "1980-01-01",
    "iso:country": "GB",
    "wof:name": "WR6 5BB",
    "wof:placetype": "postalcode"
  },
  "geometry": {"coordinates":[-2.474917,52.139301],"type":"Point"}
}
