{
  "type": "Feature",
  "properties": {
    "iso:country":"GB",
    "wof:name":"WR6 5BB",
    "wof:placetype":"postalcode"
},
  "geometry": {"coordinates":[-2.47491710762624,52.13930065692376],"type":"Point"}
}