{
  "type": "Feature",
  "properties": {
    "iso:country":"GB",
    "wof:name":"ME9 7AF",
    "wof:placetype":"postalcode"
},
  "geometry": {"coordinates":[0.6450091855907,51.37643097709032],"type":"Point"}
}