{
  "type": "Feature",
  "properties": {
    "date:inception_lower":"2004-01-01",
    "date:inception_upper":"2004-01-31",
    "iso:country":"GB",
    "wof:name":"ME9 7AF",
    "wof:placetype":"postalcode"
},
  "geometry": {"coordinates":[0.645009,51.376431],"type":"Point"}
}