{
  "type": "Feature",
  "properties": {
    "iso:country":"GB",
    "wof:name":"SA64 0HD",
    "wof:placetype":"postalcode"
},
  "geometry": {"coordinates":[-5.00237637807949,52.00483768707607],"type":"Point"}
}