{
  "type": "Feature",
  "properties": {
    "date:inception_lower": "1980-01-01",
    "date:inception_upper": "1980-01-01",
    "iso:country": "GB",
    "wof:name": "SA64 0HD",
    "wof:placetype": "postalcode"
  },
  "geometry": {"coordinates":[-5.002403,52.004827],"type":"Point"}
}
