{
  "type": "Feature",
  "properties": {
    "date:inception_lower":"1980-01-01",
    "date:inception_upper":"1980-01-31",
    "iso:country":"GB",
    "wof:name":"TR15 1QE",
    "wof:placetype":"postalcode"
},
  "geometry": {"coordinates":[-5.217821,50.239989],"type":"Point"}
}