{
  "type": "Feature",
  "properties": {
    "iso:country": "GB",
    "wof:name": "DE15 9PR",
    "wof:placetype": "postalcode"
  },
  "geometry": {"coordinates":[-1.633629,52.782755],"type":"Point"}
}
