{
  "type": "Feature",
  "properties": {
    "date:inception_lower": "2019-11-01",
    "date:inception_upper": "2019-11-01",
    "iso:country": "GB",
    "wof:name": "DE15 9PR",
    "wof:placetype": "postalcode"
  },
  "geometry": {"coordinates":[-1.634365,52.783432],"type":"Point"}
}
