{
  "type": "Feature",
  "properties": {
    "iso:country": "GB",
    "wof:name": "BA4 4SN",
    "wof:placetype": "postalcode"
  },
  "geometry": {"coordinates":[-2.436174,51.182971],"type":"Point"}
}
