{
  "type": "Feature",
  "properties": {
    "iso:country":"GB",
    "wof:name":"BA4 4SN",
    "wof:placetype":"postalcode"
},
  "geometry": {"coordinates":[-2.436174784375,51.18297647824028],"type":"Point"}
}