{
  "type": "Feature",
  "properties": {
    "iso:country": "GB",
    "wof:name": "NN11 3YU",
    "wof:placetype": "postalcode"
  },
  "geometry": {"coordinates":[-1.221714,52.19863],"type":"Point"}
}
