{
  "type": "Feature",
  "properties": {
    "iso:country":"GB",
    "wof:name":"NN11 3YU",
    "wof:placetype":"postalcode"
},
  "geometry": {"coordinates":[-1.22171446744657,52.19863026251927],"type":"Point"}
}