{
  "type": "Feature",
  "properties": {
    "iso:country":"GB",
    "wof:name":"HR1 3JT",
    "wof:placetype":"postalcode"
},
  "geometry": {"coordinates":[-2.68877490392618,52.15736820151715],"type":"Point"}
}