{
  "type": "Feature",
  "properties": {
    "iso:country": "GB",
    "wof:name": "MK4 2JD",
    "wof:placetype": "postalcode"
  },
  "geometry": {"coordinates":[-0.783362,52.0057],"type":"Point"}
}
