{
  "type": "Feature",
  "properties": {
    "iso:country":"GB",
    "wof:name":"MK4 2JD",
    "wof:placetype":"postalcode"
},
  "geometry": {"coordinates":[-0.7833624641612,52.00570033346318],"type":"Point"}
}