{
  "type": "Feature",
  "properties": {
    "date:inception_lower": "1980-01-01",
    "date:inception_upper": "1980-01-01",
    "iso:country": "GB",
    "wof:name": "LL14 3AY",
    "wof:placetype": "postalcode"
  },
  "geometry": {"coordinates":[-3.073958,52.972071],"type":"Point"}
}
