{
  "type": "Feature",
  "properties": {
    "iso:country": "GB",
    "wof:name": "LL14 3AY",
    "wof:placetype": "postalcode"
  },
  "geometry": {"coordinates":[-3.073958,52.972071],"type":"Point"}
}
