{
  "type": "Feature",
  "properties": {
    "iso:country":"GB",
    "wof:name":"LL14 3AY",
    "wof:placetype":"postalcode"
},
  "geometry": {"coordinates":[-3.07395846946335,52.97207077677968],"type":"Point"}
}