{
  "type": "Feature",
  "properties": {
    "iso:country":"GB",
    "wof:name":"NN3 3PE",
    "wof:placetype":"postalcode"
},
  "geometry": {"coordinates":[-0.83872054430645,52.25309646730215],"type":"Point"}
}