{
  "type": "Feature",
  "properties": {
    "iso:country": "GB",
    "wof:name": "NN3 3PE",
    "wof:placetype": "postalcode"
  },
  "geometry": {"coordinates":[-0.838721,52.253096],"type":"Point"}
}
