{
  "type": "Feature",
  "properties": {
    "iso:country":"GB",
    "wof:name":"LU5 5EA",
    "wof:placetype":"postalcode"
},
  "geometry": {"coordinates":[-0.5182548212986,51.90539424294082],"type":"Point"}
}