{
  "type": "Feature",
  "properties": {
    "iso:country":"GB",
    "wof:name":"RG9 5QT",
    "wof:placetype":"postalcode"
},
  "geometry": {"coordinates":[-1.02432801824648,51.54988745641523],"type":"Point"}
}