{
  "type": "Feature",
  "properties": {
    "iso:country": "GB",
    "wof:name": "RG9 5QT",
    "wof:placetype": "postalcode"
  },
  "geometry": {"coordinates":[-1.024248,51.549935],"type":"Point"}
}
