{
  "type": "Feature",
  "properties": {
    "date:inception_lower": "1980-01-01",
    "date:inception_upper": "1980-01-01",
    "iso:country": "GB",
    "wof:name": "RG9 5QT",
    "wof:placetype": "postalcode"
  },
  "geometry": {"coordinates":[-1.024248,51.549935],"type":"Point"}
}
