{
  "type": "Feature",
  "properties": {
    "date:inception_lower": "1980-01-01",
    "date:inception_upper": "1980-01-01",
    "iso:country": "GB",
    "wof:name": "BN20 9EJ",
    "wof:placetype": "postalcode"
  },
  "geometry": {"coordinates":[0.250059,50.797149],"type":"Point"}
}
