{
  "type": "Feature",
  "properties": {
    "iso:country": "GB",
    "wof:name": "RG31 6NH",
    "wof:placetype": "postalcode"
  },
  "geometry": {"coordinates":[-1.029948,51.469748],"type":"Point"}
}
