{
  "type": "Feature",
  "properties": {
    "iso:country":"GB",
    "wof:name":"RG31 6NH",
    "wof:placetype":"postalcode"
},
  "geometry": {"coordinates":[-1.02982523183254,51.46970874328446],"type":"Point"}
}