{
  "type": "Feature",
  "properties": {
    "date:inception_lower": "2002-06-01",
    "date:inception_upper": "2002-06-01",
    "iso:country": "GB",
    "wof:name": "RG31 6NH",
    "wof:placetype": "postalcode"
  },
  "geometry": {"coordinates":[-1.029805,51.46971],"type":"Point"}
}
