{
  "type": "Feature",
  "properties": {
    "iso:country":"GB",
    "wof:name":"HP7 0LZ",
    "wof:placetype":"postalcode"
},
  "geometry": {"coordinates":[-0.6315023785015,51.64444342553902],"type":"Point"}
}