{
  "type": "Feature",
  "properties": {
    "iso:country": "GB",
    "wof:name": "HP7 0LZ",
    "wof:placetype": "postalcode"
  },
  "geometry": {"coordinates":[-0.631392,51.644262],"type":"Point"}
}
