{
  "type": "Feature",
  "properties": {
    "iso:country":"GB",
    "wof:name":"CA10 3PE",
    "wof:placetype":"postalcode"
},
  "geometry": {"coordinates":[-2.67259214277995,54.52651163184842],"type":"Point"}
}