{
  "type": "Feature",
  "properties": {
    "iso:country": "GB",
    "wof:name": "NE24 1PD",
    "wof:placetype": "postalcode"
  },
  "geometry": {"coordinates":[-1.51635,55.132665],"type":"Point"}
}
