{
  "type": "Feature",
  "properties": {
    "iso:country":"GB",
    "wof:name":"EX13 5GA",
    "wof:placetype":"postalcode"
},
  "geometry": {"coordinates":[-2.9892155610365,50.78443805902383],"type":"Point"}
}