{
  "type": "Feature",
  "properties": {
    "iso:country": "GB",
    "wof:name": "EX13 5GA",
    "wof:placetype": "postalcode"
  },
  "geometry": {"coordinates":[-2.989216,50.784438],"type":"Point"}
}
