{
  "type": "Feature",
  "properties": {
    "iso:country":"GB",
    "wof:name":"M30 7PA",
    "wof:placetype":"postalcode"
},
  "geometry": {"coordinates":[-2.37583605076693,53.4785196305851],"type":"Point"}
}