{
  "type": "Feature",
  "properties": {
    "date:inception_lower": "1980-01-01",
    "date:inception_upper": "1980-01-01",
    "iso:country": "GB",
    "wof:name": "B77 3BP",
    "wof:placetype": "postalcode"
  },
  "geometry": {"coordinates":[-1.671034,52.633889],"type":"Point"}
}
