{
  "type": "Feature",
  "properties": {
    "iso:country":"GB",
    "wof:name":"LN1 1EL",
    "wof:placetype":"postalcode"
},
  "geometry": {"coordinates":[-0.54103774490971,53.23248183893987],"type":"Point"}
}