{
  "type": "Feature",
  "properties": {
    "iso:country":"GB",
    "wof:name":"CV7 7QZ",
    "wof:placetype":"postalcode"
},
  "geometry": {"coordinates":[-1.64256120768206,52.38312142079089],"type":"Point"}
}