{
  "type": "Feature",
  "properties": {
    "date:inception_lower": "2009-05-01",
    "date:inception_upper": "2009-05-01",
    "iso:country": "GB",
    "wof:name": "CV7 7QZ",
    "wof:placetype": "postalcode"
  },
  "geometry": {"coordinates":[-1.642561,52.383121],"type":"Point"}
}
