{
  "type": "Feature",
  "properties": {
    "iso:country":"GB",
    "wof:name":"BD23 2LH",
    "wof:placetype":"postalcode"
},
  "geometry": {"coordinates":[-2.00313379372254,53.95803194415137],"type":"Point"}
}