{
  "type": "Feature",
  "properties": {
    "iso:country": "GB",
    "wof:name": "BD23 2LH",
    "wof:placetype": "postalcode"
  },
  "geometry": {"coordinates":[-2.003134,53.958032],"type":"Point"}
}
