{
  "type": "Feature",
  "properties": {
    "iso:country":"GB",
    "wof:name":"IG11 7TA",
    "wof:placetype":"postalcode"
},
  "geometry": {"coordinates":[0.08466882779334,51.53355388140967],"type":"Point"}
}