{
  "type": "Feature",
  "properties": {
    "iso:country": "GB",
    "wof:name": "IG11 7TA",
    "wof:placetype": "postalcode"
  },
  "geometry": {"coordinates":[0.084669,51.533554],"type":"Point"}
}
