{
  "type": "Feature",
  "properties": {
    "date:inception_lower":"1980-02-01",
    "date:inception_upper":"1980-02-29",
    "iso:country":"GB",
    "wof:name":"G62 6AY",
    "wof:placetype":"postalcode"
},
  "geometry": {"coordinates":[-4.301919,55.936074],"type":"Point"}
}