{
  "type": "Feature",
  "properties": {
    "iso:country":"GB",
    "wof:name":"G62 6AY",
    "wof:placetype":"postalcode"
},
  "geometry": {"coordinates":[-4.30191954996191,55.93607378341068],"type":"Point"}
}