{
  "type": "Feature",
  "properties": {
    "date:inception_lower":"1980-01-01",
    "date:inception_upper":"1980-01-31",
    "iso:country":"GB",
    "wof:name":"NG2 5HG",
    "wof:placetype":"postalcode"
},
  "geometry": {"coordinates":[-1.123565,52.936083],"type":"Point"}
}