{
  "type": "Feature",
  "properties": {
    "iso:country": "GB",
    "wof:name": "G42 0DW",
    "wof:placetype": "postalcode"
  },
  "geometry": {"coordinates":[-4.233979,55.825279],"type":"Point"}
}
