{
  "type": "Feature",
  "properties": {
    "iso:country":"GB",
    "wof:name":"G42 0DW",
    "wof:placetype":"postalcode"
},
  "geometry": {"coordinates":[-4.23397912011249,55.82527936558138],"type":"Point"}
}