{
  "type": "Feature",
  "properties": {
    "iso:country": "GB",
    "wof:name": "TQ1 4HN",
    "wof:placetype": "postalcode"
  },
  "geometry": {"coordinates":[-3.535998,50.477867],"type":"Point"}
}
