{
  "type": "Feature",
  "properties": {
    "iso:country":"GB",
    "wof:name":"TQ1 4HN",
    "wof:placetype":"postalcode"
},
  "geometry": {"coordinates":[-3.53599799962411,50.47786683510486],"type":"Point"}
}