{
  "type": "Feature",
  "properties": {
    "date:inception_lower":"1980-01-01",
    "date:inception_upper":"1980-01-31",
    "iso:country":"GB",
    "wof:name":"TQ1 4HN",
    "wof:placetype":"postalcode"
},
  "geometry": {"coordinates":[-3.535998,50.477867],"type":"Point"}
}