{
  "type": "Feature",
  "properties": {
    "iso:country": "GB",
    "wof:name": "HP13 5YP",
    "wof:placetype": "postalcode"
  },
  "geometry": {"coordinates":[-0.775075,51.649841],"type":"Point"}
}
