{
  "type": "Feature",
  "properties": {
    "iso:country":"GB",
    "wof:name":"HP13 5YP",
    "wof:placetype":"postalcode"
},
  "geometry": {"coordinates":[-0.7750748981034,51.64984109369039],"type":"Point"}
}