{
  "type": "Feature",
  "properties": {
    "iso:country":"GB",
    "wof:name":"KT6 4HX",
    "wof:placetype":"postalcode"
},
  "geometry": {"coordinates":[-0.31319837953006,51.39447978312563],"type":"Point"}
}