{
  "type": "Feature",
  "properties": {
    "iso:country": "GB",
    "wof:name": "S2 5FE",
    "wof:placetype": "postalcode"
  },
  "geometry": {"coordinates":[-1.440537,53.374937],"type":"Point"}
}
