{
  "type": "Feature",
  "properties": {
    "iso:country": "GB",
    "wof:name": "CT19 5BE",
    "wof:placetype": "postalcode"
  },
  "geometry": {"coordinates":[1.176644,51.085075],"type":"Point"}
}
