{
  "type": "Feature",
  "properties": {
    "iso:country":"GB",
    "wof:name":"CT19 5BE",
    "wof:placetype":"postalcode"
},
  "geometry": {"coordinates":[1.17664430212987,51.08507494420747],"type":"Point"}
}