{
  "type": "Feature",
  "properties": {
    "iso:country":"GB",
    "wof:name":"M34 3LA",
    "wof:placetype":"postalcode"
},
  "geometry": {"coordinates":[-2.12473902559716,53.45413001337139],"type":"Point"}
}