{
  "type": "Feature",
  "properties": {
    "iso:country":"GB",
    "wof:name":"WA6 7LN",
    "wof:placetype":"postalcode"
},
  "geometry": {"coordinates":[-2.71374280802915,53.29331078729764],"type":"Point"}
}