{
  "type": "Feature",
  "properties": {
    "iso:country": "GB",
    "wof:name": "HP22 5AY",
    "wof:placetype": "postalcode"
  },
  "geometry": {"coordinates":[-0.779728,51.834539],"type":"Point"}
}
