{
  "type": "Feature",
  "properties": {
    "date:inception_lower": "1992-08-01",
    "date:inception_upper": "1992-08-01",
    "iso:country": "GB",
    "wof:name": "DE72 3BN",
    "wof:placetype": "postalcode"
  },
  "geometry": {"coordinates":[-1.304038,52.899413],"type":"Point"}
}
