{
  "type": "Feature",
  "properties": {
    "iso:country":"GB",
    "wof:name":"HG4 1JU",
    "wof:placetype":"postalcode"
},
  "geometry": {"coordinates":[-1.51397273749152,54.13529370954411],"type":"Point"}
}