{
  "type": "Feature",
  "properties": {
    "iso:country": "GB",
    "wof:name": "RH13 0QA",
    "wof:placetype": "postalcode"
  },
  "geometry": {"coordinates":[-0.384636,51.02917],"type":"Point"}
}
