{
  "type": "Feature",
  "properties": {
    "iso:country":"GB",
    "wof:name":"RH13 0QA",
    "wof:placetype":"postalcode"
},
  "geometry": {"coordinates":[-0.38463591154592,51.02916972588977],"type":"Point"}
}