{
  "type": "Feature",
  "properties": {
    "iso:country":"GB",
    "wof:name":"NG6 8FS",
    "wof:placetype":"postalcode"
},
  "geometry": {"coordinates":[-1.1990227733055,53.00259829567955],"type":"Point"}
}