{
  "type": "Feature",
  "properties": {
    "iso:country":"GB",
    "wof:name":"SM1 4EF",
    "wof:placetype":"postalcode"
},
  "geometry": {"coordinates":[-0.19341601697397,51.36856707814515],"type":"Point"}
}