{
  "type": "Feature",
  "properties": {
    "date:inception_lower": "2021-03-01",
    "date:inception_upper": "2021-03-01",
    "iso:country": "GB",
    "wof:name": "SG16 6GU",
    "wof:placetype": "postalcode"
  },
  "geometry": {"coordinates":[-0.298733,52.000472],"type":"Point"}
}
