{
  "type": "Feature",
  "properties": {
    "iso:country":"GB",
    "wof:name":"NE12 6FR",
    "wof:placetype":"postalcode"
},
  "geometry": {"coordinates":[-1.57168770015478,55.03567206961906],"type":"Point"}
}