{
  "type": "Feature",
  "properties": {
    "date:inception_lower": "1994-05-01",
    "date:inception_upper": "1994-05-01",
    "iso:country": "GB",
    "wof:name": "M26 1EW",
    "wof:placetype": "postalcode"
  },
  "geometry": {"coordinates":[-2.342313,53.537089],"type":"Point"}
}
