{
  "type": "Feature",
  "properties": {
    "iso:country":"GB",
    "wof:name":"M26 1EW",
    "wof:placetype":"postalcode"
},
  "geometry": {"coordinates":[-2.34576394851122,53.53810496976602],"type":"Point"}
}