{
  "type": "Feature",
  "properties": {
    "iso:country":"GB",
    "wof:name":"PA6 7JT",
    "wof:placetype":"postalcode"
},
  "geometry": {"coordinates":[-4.53767825750483,55.86176475004314],"type":"Point"}
}