{
  "type": "Feature",
  "properties": {
    "iso:country":"GB",
    "wof:name":"CT10 2SE",
    "wof:placetype":"postalcode"
},
  "geometry": {"coordinates":[1.41703239177223,51.36369334385417],"type":"Point"}
}