{
  "type": "Feature",
  "properties": {
    "iso:country": "GB",
    "wof:name": "DA14 6LF",
    "wof:placetype": "postalcode"
  },
  "geometry": {"coordinates":[0.100057,51.419241],"type":"Point"}
}
