{
  "type": "Feature",
  "properties": {
    "iso:country":"GB",
    "wof:name":"B44 8RW",
    "wof:placetype":"postalcode"
},
  "geometry": {"coordinates":[-1.89015594723674,52.5403057620736],"type":"Point"}
}