{
  "type": "Feature",
  "properties": {
    "iso:country":"GB",
    "wof:name":"M35 0FP",
    "wof:placetype":"postalcode"
},
  "geometry": {"coordinates":[-2.162166661358,53.50707188026155],"type":"Point"}
}