{
  "type": "Feature",
  "properties": {
    "iso:country": "GB",
    "wof:name": "M35 0FP",
    "wof:placetype": "postalcode"
  },
  "geometry": {"coordinates":[-2.162167,53.507072],"type":"Point"}
}
