{
  "type": "Feature",
  "properties": {
    "iso:country":"GB",
    "wof:name":"DE4 5EF",
    "wof:placetype":"postalcode"
},
  "geometry": {"coordinates":[-1.49905310187672,53.08476517800104],"type":"Point"}
}