{
  "type": "Feature",
  "properties": {
    "iso:country": "GB",
    "wof:name": "DE4 5EF",
    "wof:placetype": "postalcode"
  },
  "geometry": {"coordinates":[-1.499053,53.084765],"type":"Point"}
}
