{
  "type": "Feature",
  "properties": {
    "iso:country": "GB",
    "wof:name": "DN40 1QT",
    "wof:placetype": "postalcode"
  },
  "geometry": {"coordinates":[-0.191846,53.618097],"type":"Point"}
}
