{
  "type": "Feature",
  "properties": {
    "iso:country":"GB",
    "wof:name":"DN40 1QT",
    "wof:placetype":"postalcode"
},
  "geometry": {"coordinates":[-0.19184611464539,53.61809664929517],"type":"Point"}
}