{
  "type": "Feature",
  "properties": {
    "iso:country":"GB",
    "wof:name":"ST2 9DU",
    "wof:placetype":"postalcode"
},
  "geometry": {"coordinates":[-2.11440429173463,53.02081688224715],"type":"Point"}
}