{
  "type": "Feature",
  "properties": {
    "iso:country":"GB",
    "wof:name":"DN11 0PX",
    "wof:placetype":"postalcode"
},
  "geometry": {"coordinates":[-1.08638625990004,53.48020551108819],"type":"Point"}
}