{
  "type": "Feature",
  "properties": {
    "date:inception_lower": "2009-02-01",
    "date:inception_upper": "2009-02-01",
    "iso:country": "GB",
    "wof:name": "TR15 1BH",
    "wof:placetype": "postalcode"
  },
  "geometry": {"coordinates":[-5.225405,50.234318],"type":"Point"}
}
