{
  "type": "Feature",
  "properties": {
    "iso:country":"GB",
    "wof:name":"LE67 3ES",
    "wof:placetype":"postalcode"
},
  "geometry": {"coordinates":[-1.36034286063322,52.7209983646468],"type":"Point"}
}