{
  "type": "Feature",
  "properties": {
    "iso:country": "GB",
    "wof:name": "LE67 3ES",
    "wof:placetype": "postalcode"
  },
  "geometry": {"coordinates":[-1.360343,52.720998],"type":"Point"}
}
