{
  "type": "Feature",
  "properties": {
    "iso:country":"GB",
    "wof:name":"DD11 1TG",
    "wof:placetype":"postalcode"
},
  "geometry": {"coordinates":[-2.58069646080244,56.56790332605386],"type":"Point"}
}