{
  "type": "Feature",
  "properties": {
    "date:inception_lower": "1980-01-01",
    "date:inception_upper": "1980-01-01",
    "iso:country": "GB",
    "wof:name": "DD11 1TG",
    "wof:placetype": "postalcode"
  },
  "geometry": {"coordinates":[-2.580696,56.567903],"type":"Point"}
}
