{
  "type": "Feature",
  "properties": {
    "iso:country":"GB",
    "wof:name":"CW1 5FX",
    "wof:placetype":"postalcode"
},
  "geometry": {"coordinates":[-2.39887093873319,53.09667305320463],"type":"Point"}
}