{
  "type": "Feature",
  "properties": {
    "date:inception_lower": "1980-01-01",
    "date:inception_upper": "1980-01-01",
    "iso:country": "GB",
    "wof:name": "DE4 2BQ",
    "wof:placetype": "postalcode"
  },
  "geometry": {"coordinates":[-1.649174,53.157897],"type":"Point"}
}
