{
  "type": "Feature",
  "properties": {
    "iso:country":"GB",
    "wof:name":"DE4 2BQ",
    "wof:placetype":"postalcode"
},
  "geometry": {"coordinates":[-1.64917452610839,53.15789739522342],"type":"Point"}
}