{
  "type": "Feature",
  "properties": {
    "iso:country":"GB",
    "wof:name":"TR12 7BW",
    "wof:placetype":"postalcode"
},
  "geometry": {"coordinates":[-5.24346815622883,50.04601145786112],"type":"Point"}
}