{
  "type": "Feature",
  "properties": {
    "iso:country":"GB",
    "wof:name":"N13 6AD",
    "wof:placetype":"postalcode"
},
  "geometry": {"coordinates":[-0.10422391614222,51.60863553748182],"type":"Point"}
}