{
  "type": "Feature",
  "properties": {
    "iso:country": "GB",
    "wof:name": "TN31 6DL",
    "wof:placetype": "postalcode"
  },
  "geometry": {"coordinates":[0.604419,50.950559],"type":"Point"}
}
