{
  "type": "Feature",
  "properties": {
    "date:inception_lower":"1980-01-01",
    "date:inception_upper":"1980-01-31",
    "iso:country":"GB",
    "wof:name":"S65 3HR",
    "wof:placetype":"postalcode"
},
  "geometry": {"coordinates":[-1.305836,53.421601],"type":"Point"}
}