{
  "type": "Feature",
  "properties": {
    "iso:country": "GB",
    "wof:name": "S65 3HR",
    "wof:placetype": "postalcode"
  },
  "geometry": {"coordinates":[-1.305836,53.421601],"type":"Point"}
}
