{
  "type": "Feature",
  "properties": {
    "iso:country":"GB",
    "wof:name":"S65 3HR",
    "wof:placetype":"postalcode"
},
  "geometry": {"coordinates":[-1.30583588309719,53.42160089258162],"type":"Point"}
}