{
  "type": "Feature",
  "properties": {
    "iso:country":"GB",
    "wof:name":"SA66 7HW",
    "wof:placetype":"postalcode"
},
  "geometry": {"coordinates":[-4.77668988315234,51.84101602143581],"type":"Point"}
}