{
  "type": "Feature",
  "properties": {
    "iso:country":"GB",
    "wof:name":"G69 0QN",
    "wof:placetype":"postalcode"
},
  "geometry": {"coordinates":[-4.07741476943285,55.91586371421513],"type":"Point"}
}