{
  "type": "Feature",
  "properties": {
    "date:inception_lower":"1987-04-01",
    "date:inception_upper":"1987-04-30",
    "iso:country":"GB",
    "wof:name":"NW10 0EG",
    "wof:placetype":"postalcode"
},
  "geometry": {"coordinates":[-0.255474,51.563493],"type":"Point"}
}