{
  "type": "Feature",
  "properties": {
    "iso:country": "GB",
    "wof:name": "NW10 0EG",
    "wof:placetype": "postalcode"
  },
  "geometry": {"coordinates":[-0.255474,51.563493],"type":"Point"}
}
