{
  "type": "Feature",
  "properties": {
    "iso:country":"GB",
    "wof:name":"NW10 0EG",
    "wof:placetype":"postalcode"
},
  "geometry": {"coordinates":[-0.25547368513937,51.56349260448494],"type":"Point"}
}