{
  "type": "Feature",
  "properties": {
    "date:inception_lower": "2020-07-01",
    "date:inception_upper": "2020-07-01",
    "iso:country": "GB",
    "wof:name": "OX13 5PN",
    "wof:placetype": "postalcode"
  },
  "geometry": {"coordinates":[-1.346178,51.706364],"type":"Point"}
}
