{
  "type": "Feature",
  "properties": {
    "iso:country":"GB",
    "wof:name":"PH21 1JE",
    "wof:placetype":"postalcode"
},
  "geometry": {"coordinates":[-4.04096854096656,57.08341785341415],"type":"Point"}
}