{
  "type": "Feature",
  "properties": {
    "date:inception_lower": "2009-06-01",
    "date:inception_upper": "2009-06-01",
    "iso:country": "GB",
    "wof:name": "M20 2SL",
    "wof:placetype": "postalcode"
  },
  "geometry": {"coordinates":[-2.226157,53.408103],"type":"Point"}
}
