{
  "type": "Feature",
  "properties": {
    "iso:country": "GB",
    "wof:name": "OX26 4LN",
    "wof:placetype": "postalcode"
  },
  "geometry": {"coordinates":[-1.130237,51.904287],"type":"Point"}
}
