{
  "type": "Feature",
  "properties": {
    "date:inception_lower":"2012-02-01",
    "date:inception_upper":"2012-02-29",
    "iso:country":"GB",
    "wof:name":"OX26 4LN",
    "wof:placetype":"postalcode"
},
  "geometry": {"coordinates":[-1.130237,51.904287],"type":"Point"}
}