{
  "type": "Feature",
  "properties": {
    "date:inception_lower": "2012-02-01",
    "date:inception_upper": "2012-02-01",
    "iso:country": "GB",
    "wof:name": "OX26 4LN",
    "wof:placetype": "postalcode"
  },
  "geometry": {"coordinates":[-1.13013,51.904276],"type":"Point"}
}
