{
  "type": "Feature",
  "properties": {
    "iso:country": "GB",
    "wof:name": "NR30 4AL",
    "wof:placetype": "postalcode"
  },
  "geometry": {"coordinates":[1.73081,52.62684],"type":"Point"}
}
