{
  "type": "Feature",
  "properties": {
    "iso:country":"GB",
    "wof:name":"NR30 4AL",
    "wof:placetype":"postalcode"
},
  "geometry": {"coordinates":[1.73080967600355,52.62683985949388],"type":"Point"}
}