{
  "type": "Feature",
  "properties": {
    "date:inception_lower": "2022-10-01",
    "date:inception_upper": "2022-10-01",
    "iso:country": "GB",
    "wof:name": "HU9 5FA",
    "wof:placetype": "postalcode"
  },
  "geometry": {"coordinates":[-0.277505,53.755731],"type":"Point"}
}
