{
  "type": "Feature",
  "properties": {
    "iso:country":"GB",
    "wof:name":"RH7 6AL",
    "wof:placetype":"postalcode"
},
  "geometry": {"coordinates":[-0.01859504458352,51.17480166643021],"type":"Point"}
}