{
  "type": "Feature",
  "properties": {
    "iso:country": "GB",
    "wof:name": "RH7 6AL",
    "wof:placetype": "postalcode"
  },
  "geometry": {"coordinates":[-0.018595,51.174802],"type":"Point"}
}
