{
  "type": "Feature",
  "properties": {
    "date:inception_lower": "1980-01-01",
    "date:inception_upper": "1980-01-01",
    "iso:country": "GB",
    "wof:name": "HU12 9BL",
    "wof:placetype": "postalcode"
  },
  "geometry": {"coordinates":[-0.108568,53.763253],"type":"Point"}
}
