{
  "type": "Feature",
  "properties": {
    "iso:country":"GB",
    "wof:name":"HU12 9BL",
    "wof:placetype":"postalcode"
},
  "geometry": {"coordinates":[-0.10963703332143,53.76287992865432],"type":"Point"}
}