{
  "type": "Feature",
  "properties": {
    "iso:country": "GB",
    "wof:name": "AL7 1BH",
    "wof:placetype": "postalcode"
  },
  "geometry": {"coordinates":[-0.195448,51.801722],"type":"Point"}
}
