{
  "type": "Feature",
  "properties": {
    "iso:country":"GB",
    "wof:name":"AL7 1BH",
    "wof:placetype":"postalcode"
},
  "geometry": {"coordinates":[-0.19545768075173,51.80171482395269],"type":"Point"}
}