{
  "type": "Feature",
  "properties": {
    "date:inception_lower":"1985-10-01",
    "date:inception_upper":"1985-10-31",
    "iso:country":"GB",
    "wof:name":"AL7 1BH",
    "wof:placetype":"postalcode"
},
  "geometry": {"coordinates":[-0.195448,51.801722],"type":"Point"}
}