{
  "type": "Feature",
  "properties": {
    "iso:country":"GB",
    "wof:name":"DN35 7LF",
    "wof:placetype":"postalcode"
},
  "geometry": {"coordinates":[-0.03641200972781,53.56410846618455],"type":"Point"}
}