{
  "type": "Feature",
  "properties": {
    "iso:country":"GB",
    "wof:name":"DL3 6RU",
    "wof:placetype":"postalcode"
},
  "geometry": {"coordinates":[-1.56934999763906,54.53107737435724],"type":"Point"}
}