{
  "type": "Feature",
  "properties": {
    "iso:country":"GB",
    "wof:name":"LS19 7RB",
    "wof:placetype":"postalcode"
},
  "geometry": {"coordinates":[-1.68746890162745,53.86636383989843],"type":"Point"}
}