{
  "type": "Feature",
  "properties": {
    "iso:country": "GB",
    "wof:name": "NR7 8BF",
    "wof:placetype": "postalcode"
  },
  "geometry": {"coordinates":[1.336994,52.661523],"type":"Point"}
}
