{
  "type": "Feature",
  "properties": {
    "iso:country":"GB",
    "wof:name":"NR7 8BF",
    "wof:placetype":"postalcode"
},
  "geometry": {"coordinates":[1.33573275067119,52.66174881678222],"type":"Point"}
}