{
  "type": "Feature",
  "properties": {
    "date:inception_lower": "2016-02-01",
    "date:inception_upper": "2016-02-01",
    "iso:country": "GB",
    "wof:name": "NR7 8BF",
    "wof:placetype": "postalcode"
  },
  "geometry": {"coordinates":[1.336572,52.661616],"type":"Point"}
}
