{
  "type": "Feature",
  "properties": {
    "iso:country": "GB",
    "wof:name": "CT7 9XD",
    "wof:placetype": "postalcode"
  },
  "geometry": {"coordinates":[1.312576,51.37311],"type":"Point"}
}
