{
  "type": "Feature",
  "properties": {
    "date:inception_lower": "2021-10-01",
    "date:inception_upper": "2021-10-01",
    "iso:country": "GB",
    "wof:name": "CF64 5WA",
    "wof:placetype": "postalcode"
  },
  "geometry": {"coordinates":[-3.232513,51.405887],"type":"Point"}
}
