{
  "type": "Feature",
  "properties": {
    "iso:country":"GB",
    "wof:name":"BS36 1DH",
    "wof:placetype":"postalcode"
},
  "geometry": {"coordinates":[-2.49759966696505,51.51327778793785],"type":"Point"}
}