{
  "type": "Feature",
  "properties": {
    "date:inception_lower": "1997-12-01",
    "date:inception_upper": "1997-12-01",
    "iso:country": "GB",
    "wof:name": "BS36 1DH",
    "wof:placetype": "postalcode"
  },
  "geometry": {"coordinates":[-2.4976,51.513278],"type":"Point"}
}
