{
  "type": "Feature",
  "properties": {
    "iso:country":"GB",
    "wof:name":"BH12 4BL",
    "wof:placetype":"postalcode"
},
  "geometry": {"coordinates":[-1.91540998788718,50.74203150133546],"type":"Point"}
}