{
  "type": "Feature",
  "properties": {
    "iso:country": "GB",
    "wof:name": "CA27 0AS",
    "wof:placetype": "postalcode"
  },
  "geometry": {"coordinates":[-3.587975,54.484708],"type":"Point"}
}
