{
  "type": "Feature",
  "properties": {
    "date:inception_lower": "1980-01-01",
    "date:inception_upper": "1980-01-01",
    "iso:country": "GB",
    "wof:name": "CA27 0AS",
    "wof:placetype": "postalcode"
  },
  "geometry": {"coordinates":[-3.587975,54.484708],"type":"Point"}
}
