{
  "type": "Feature",
  "properties": {
    "iso:country": "GB",
    "wof:name": "IP4 5PD",
    "wof:placetype": "postalcode"
  },
  "geometry": {"coordinates":[1.197915,52.056849],"type":"Point"}
}
