{
  "type": "Feature",
  "properties": {
    "iso:country":"GB",
    "wof:name":"TN22 1RD",
    "wof:placetype":"postalcode"
},
  "geometry": {"coordinates":[0.09726519352541,50.97319130870647],"type":"Point"}
}