{
  "type": "Feature",
  "properties": {
    "date:inception_lower": "1997-06-01",
    "date:inception_upper": "1997-06-01",
    "iso:country": "GB",
    "wof:name": "SN1 1GH",
    "wof:placetype": "postalcode"
  },
  "geometry": {"coordinates":[-1.725769,51.551194],"type":"Point"}
}
