{
  "type": "Feature",
  "properties": {
    "date:inception_lower":"2011-10-01",
    "date:inception_upper":"2011-10-31",
    "iso:country":"GB",
    "wof:name":"NE5 3TF",
    "wof:placetype":"postalcode"
},
  "geometry": {"coordinates":[-1.672815,54.994622],"type":"Point"}
}