{
  "type": "Feature",
  "properties": {
    "iso:country":"GB",
    "wof:name":"NE5 3TF",
    "wof:placetype":"postalcode"
},
  "geometry": {"coordinates":[-1.67281480052522,54.99462227262135],"type":"Point"}
}