{
  "type": "Feature",
  "properties": {
    "iso:country": "GB",
    "wof:name": "DE74 2LB",
    "wof:placetype": "postalcode"
  },
  "geometry": {"coordinates":[-1.337386,52.842673],"type":"Point"}
}
