{
  "type": "Feature",
  "properties": {
    "date:inception_lower":"1980-01-01",
    "date:inception_upper":"1980-01-31",
    "iso:country":"GB",
    "wof:name":"CO5 9BD",
    "wof:placetype":"postalcode"
},
  "geometry": {"coordinates":[0.699056,51.83164],"type":"Point"}
}