{
  "type": "Feature",
  "properties": {
    "iso:country":"GB",
    "wof:name":"CO5 9BD",
    "wof:placetype":"postalcode"
},
  "geometry": {"coordinates":[0.69905592381395,51.83163992059893],"type":"Point"}
}