{
  "type": "Feature",
  "properties": {
    "iso:country": "GB",
    "wof:name": "S75 4PG",
    "wof:placetype": "postalcode"
  },
  "geometry": {"coordinates":[-1.556172,53.536713],"type":"Point"}
}
