{
  "type": "Feature",
  "properties": {
    "iso:country":"GB",
    "wof:name":"WN5 8HE",
    "wof:placetype":"postalcode"
},
  "geometry": {"coordinates":[-2.68531583684338,53.53672131810282],"type":"Point"}
}