{
  "type": "Feature",
  "properties": {
    "iso:country": "GB",
    "wof:name": "OL4 4NQ",
    "wof:placetype": "postalcode"
  },
  "geometry": {"coordinates":[-2.066809,53.542567],"type":"Point"}
}
