{
  "type": "Feature",
  "properties": {
    "date:inception_lower": "1980-01-01",
    "date:inception_upper": "1980-01-01",
    "iso:country": "GB",
    "wof:name": "NW9 7HX",
    "wof:placetype": "postalcode"
  },
  "geometry": {"coordinates":[-0.2529,51.582179],"type":"Point"}
}
