{
  "type": "Feature",
  "properties": {
    "iso:country":"GB",
    "wof:name":"NW9 7HX",
    "wof:placetype":"postalcode"
},
  "geometry": {"coordinates":[-0.25292516193101,51.58217665321727],"type":"Point"}
}