{
  "type": "Feature",
  "properties": {
    "date:inception_lower": "2002-07-01",
    "date:inception_upper": "2002-07-01",
    "iso:country": "GB",
    "wof:name": "PE7 8EP",
    "wof:placetype": "postalcode"
  },
  "geometry": {"coordinates":[-0.270546,52.531726],"type":"Point"}
}
