{
  "type": "Feature",
  "properties": {
    "iso:country":"GB",
    "wof:name":"PE7 8EP",
    "wof:placetype":"postalcode"
},
  "geometry": {"coordinates":[-0.27054623241256,52.53172599960315],"type":"Point"}
}