{
  "type": "Feature",
  "properties": {
    "date:inception_lower":"1980-01-01",
    "date:inception_upper":"1980-01-31",
    "iso:country":"GB",
    "wof:name":"B44 8AP",
    "wof:placetype":"postalcode"
},
  "geometry": {"coordinates":[-1.891843,52.531551],"type":"Point"}
}