{
  "type": "Feature",
  "properties": {
    "iso:country": "GB",
    "wof:name": "B44 8AP",
    "wof:placetype": "postalcode"
  },
  "geometry": {"coordinates":[-1.891843,52.531551],"type":"Point"}
}
