{
  "type": "Feature",
  "properties": {
    "iso:country":"GB",
    "wof:name":"WV3 9QU",
    "wof:placetype":"postalcode"
},
  "geometry": {"coordinates":[-2.14642775921138,52.58502600218794],"type":"Point"}
}