{
  "type": "Feature",
  "properties": {
    "date:inception_lower": "1980-01-01",
    "date:inception_upper": "1980-01-01",
    "iso:country": "GB",
    "wof:name": "WV3 9QU",
    "wof:placetype": "postalcode"
  },
  "geometry": {"coordinates":[-2.146407,52.585023],"type":"Point"}
}
