{
  "type": "Feature",
  "properties": {
    "iso:country":"GB",
    "wof:name":"CF37 4NP",
    "wof:placetype":"postalcode"
},
  "geometry": {"coordinates":[-3.31925058233952,51.62312394205698],"type":"Point"}
}