{
  "type": "Feature",
  "properties": {
    "date:inception_lower":"1995-07-01",
    "date:inception_upper":"1995-07-31",
    "iso:country":"GB",
    "wof:name":"RG20 8QP",
    "wof:placetype":"postalcode"
},
  "geometry": {"coordinates":[-1.377081,51.484367],"type":"Point"}
}