{
  "type": "Feature",
  "properties": {
    "iso:country":"GB",
    "wof:name":"PE8 5XD",
    "wof:placetype":"postalcode"
},
  "geometry": {"coordinates":[-0.51146879019369,52.43941156875739],"type":"Point"}
}