{
  "type": "Feature",
  "properties": {
    "iso:country": "GB",
    "wof:name": "PE8 5XD",
    "wof:placetype": "postalcode"
  },
  "geometry": {"coordinates":[-0.511469,52.439412],"type":"Point"}
}
