{
  "type": "Feature",
  "properties": {
    "date:inception_lower":"1999-06-01",
    "date:inception_upper":"1999-06-30",
    "iso:country":"GB",
    "wof:name":"PE8 5XD",
    "wof:placetype":"postalcode"
},
  "geometry": {"coordinates":[-0.511469,52.439412],"type":"Point"}
}