{
  "type": "Feature",
  "properties": {
    "iso:country": "GB",
    "wof:name": "PO30 5FY",
    "wof:placetype": "postalcode"
  },
  "geometry": {"coordinates":[-1.29664,50.701507],"type":"Point"}
}
