{
  "type": "Feature",
  "properties": {
    "date:inception_lower": "1980-01-01",
    "date:inception_upper": "1980-01-01",
    "iso:country": "GB",
    "wof:name": "CO11 1PL",
    "wof:placetype": "postalcode"
  },
  "geometry": {"coordinates":[1.087061,51.96946],"type":"Point"}
}
