{
  "type": "Feature",
  "properties": {
    "iso:country":"GB",
    "wof:name":"CO11 1PL",
    "wof:placetype":"postalcode"
},
  "geometry": {"coordinates":[1.0870143612198,51.96942047467297],"type":"Point"}
}