{
  "type": "Feature",
  "properties": {
    "date:inception_lower": "1980-01-01",
    "date:inception_upper": "1980-01-01",
    "iso:country": "GB",
    "wof:name": "CW8 4SR",
    "wof:placetype": "postalcode"
  },
  "geometry": {"coordinates":[-2.546349,53.273665],"type":"Point"}
}
