{
  "type": "Feature",
  "properties": {
    "iso:country":"GB",
    "wof:name":"SR5 5UD",
    "wof:placetype":"postalcode"
},
  "geometry": {"coordinates":[-1.43357981215911,54.92559163677102],"type":"Point"}
}