{
  "type": "Feature",
  "properties": {
    "iso:country": "GB",
    "wof:name": "SA11 1AY",
    "wof:placetype": "postalcode"
  },
  "geometry": {"coordinates":[-3.810405,51.654865],"type":"Point"}
}
