{
  "type": "Feature",
  "properties": {
    "date:inception_lower": "1980-01-01",
    "date:inception_upper": "1980-01-01",
    "iso:country": "GB",
    "wof:name": "SA11 1AY",
    "wof:placetype": "postalcode"
  },
  "geometry": {"coordinates":[-3.810405,51.654865],"type":"Point"}
}
