{
  "type": "Feature",
  "properties": {
    "iso:country":"GB",
    "wof:name":"SA11 1AY",
    "wof:placetype":"postalcode"
},
  "geometry": {"coordinates":[-3.81040478196411,51.6548645998074],"type":"Point"}
}