{
  "type": "Feature",
  "properties": {
    "date:inception_lower":"1980-01-01",
    "date:inception_upper":"1980-01-31",
    "iso:country":"GB",
    "wof:name":"WA7 2UB",
    "wof:placetype":"postalcode"
},
  "geometry": {"coordinates":[-2.691172,53.326316],"type":"Point"}
}