{
  "type": "Feature",
  "properties": {
    "iso:country":"GB",
    "wof:name":"WA7 2UB",
    "wof:placetype":"postalcode"
},
  "geometry": {"coordinates":[-2.69117193391386,53.32631610160569],"type":"Point"}
}