{
  "type": "Feature",
  "properties": {
    "iso:country":"GB",
    "wof:name":"KY12 8XA",
    "wof:placetype":"postalcode"
},
  "geometry": {"coordinates":[-3.53601515764431,56.06180408688247],"type":"Point"}
}