{
  "type": "Feature",
  "properties": {
    "date:inception_lower": "1980-01-01",
    "date:inception_upper": "1980-01-01",
    "iso:country": "GB",
    "wof:name": "KY12 8XA",
    "wof:placetype": "postalcode"
  },
  "geometry": {"coordinates":[-3.536015,56.061804],"type":"Point"}
}
