{
  "type": "Feature",
  "properties": {
    "iso:country": "GB",
    "wof:name": "KY12 8XA",
    "wof:placetype": "postalcode"
  },
  "geometry": {"coordinates":[-3.536015,56.061804],"type":"Point"}
}
