{
  "type": "Feature",
  "properties": {
    "iso:country":"GB",
    "wof:name":"LL54 5NW",
    "wof:placetype":"postalcode"
},
  "geometry": {"coordinates":[-4.36957191729328,53.00893419167419],"type":"Point"}
}