{
  "type": "Feature",
  "properties": {
    "iso:country": "GB",
    "wof:name": "LL54 5NW",
    "wof:placetype": "postalcode"
  },
  "geometry": {"coordinates":[-4.36958,53.008951],"type":"Point"}
}
