{
  "type": "Feature",
  "properties": {
    "iso:country":"GB",
    "wof:name":"UB8 2EX",
    "wof:placetype":"postalcode"
},
  "geometry": {"coordinates":[-0.48447335745606,51.52468035256466],"type":"Point"}
}