{
  "type": "Feature",
  "properties": {
    "iso:country":"GB",
    "wof:name":"CT13 0AB",
    "wof:placetype":"postalcode"
},
  "geometry": {"coordinates":[1.3329257483524,51.27278570406881],"type":"Point"}
}