{
  "type": "Feature",
  "properties": {
    "iso:country":"GB",
    "wof:name":"ST13 6LS",
    "wof:placetype":"postalcode"
},
  "geometry": {"coordinates":[-2.01978099315791,53.10644638974603],"type":"Point"}
}