{
  "type": "Feature",
  "properties": {
    "date:inception_lower": "1980-01-01",
    "date:inception_upper": "1980-01-01",
    "iso:country": "GB",
    "wof:name": "HD4 6XB",
    "wof:placetype": "postalcode"
  },
  "geometry": {"coordinates":[-1.75124,53.597347],"type":"Point"}
}
