{
  "type": "Feature",
  "properties": {
    "iso:country":"GB",
    "wof:name":"HD4 6XB",
    "wof:placetype":"postalcode"
},
  "geometry": {"coordinates":[-1.75124013861937,53.59734677725391],"type":"Point"}
}