{
  "type": "Feature",
  "properties": {
    "iso:country":"GB",
    "wof:name":"M8 9JT",
    "wof:placetype":"postalcode"
},
  "geometry": {"coordinates":[-2.24201897874924,53.51254549056252],"type":"Point"}
}