{
  "type": "Feature",
  "properties": {
    "iso:country":"GB",
    "wof:name":"CF40 2DZ",
    "wof:placetype":"postalcode"
},
  "geometry": {"coordinates":[-3.4725907299004,51.62787337834153],"type":"Point"}
}