{
  "type": "Feature",
  "properties": {
    "date:inception_lower": "2005-05-01",
    "date:inception_upper": "2005-05-01",
    "iso:country": "GB",
    "wof:name": "DD7 7JU",
    "wof:placetype": "postalcode"
  },
  "geometry": {"coordinates":[-2.735901,56.497005],"type":"Point"}
}
