{
  "type": "Feature",
  "properties": {
    "iso:country":"GB",
    "wof:name":"EH4 2AT",
    "wof:placetype":"postalcode"
},
  "geometry": {"coordinates":[-3.25459365656207,55.9622734563281],"type":"Point"}
}