{
  "type": "Feature",
  "properties": {
    "date:inception_lower": "1980-01-01",
    "date:inception_upper": "1980-01-01",
    "iso:country": "GB",
    "wof:name": "BN6 8PL",
    "wof:placetype": "postalcode"
  },
  "geometry": {"coordinates":[-0.147816,50.927495],"type":"Point"}
}
