{
  "type": "Feature",
  "properties": {
    "iso:country":"GB",
    "wof:name":"BN6 8PL",
    "wof:placetype":"postalcode"
},
  "geometry": {"coordinates":[-0.14781652615241,50.92749456349028],"type":"Point"}
}