{
  "type": "Feature",
  "properties": {
    "iso:country": "GB",
    "wof:name": "S71 1LS",
    "wof:placetype": "postalcode"
  },
  "geometry": {"coordinates":[-1.469778,53.561979],"type":"Point"}
}
