{
  "type": "Feature",
  "properties": {
    "iso:country":"GB",
    "wof:name":"SK5 6TP",
    "wof:placetype":"postalcode"
},
  "geometry": {"coordinates":[-2.15180983814628,53.44428319289811],"type":"Point"}
}