{
  "type": "Feature",
  "properties": {
    "iso:country":"GB",
    "wof:name":"B44 8SA",
    "wof:placetype":"postalcode"
},
  "geometry": {"coordinates":[-1.8910929873734,52.54297661643508],"type":"Point"}
}