{
  "type": "Feature",
  "properties": {
    "iso:country": "GB",
    "wof:name": "NG22 9PW",
    "wof:placetype": "postalcode"
  },
  "geometry": {"coordinates":[-1.009725,53.203517],"type":"Point"}
}
