{
  "type": "Feature",
  "properties": {
    "iso:country":"GB",
    "wof:name":"NG22 9PW",
    "wof:placetype":"postalcode"
},
  "geometry": {"coordinates":[-1.00972773744167,53.20349700178546],"type":"Point"}
}