{
  "type": "Feature",
  "properties": {
    "iso:country":"GB",
    "wof:name":"NE4 5TB",
    "wof:placetype":"postalcode"
},
  "geometry": {"coordinates":[-1.62629547202512,54.97482648160073],"type":"Point"}
}