{
  "type": "Feature",
  "properties": {
    "iso:country":"GB",
    "wof:name":"DH4 5PL",
    "wof:placetype":"postalcode"
},
  "geometry": {"coordinates":[-1.49530244271733,54.85114121274044],"type":"Point"}
}