{
  "type": "Feature",
  "properties": {
    "iso:country":"GB",
    "wof:name":"LE7 7PT",
    "wof:placetype":"postalcode"
},
  "geometry": {"coordinates":[-1.1371519666389,52.7134178414352],"type":"Point"}
}