{
  "type": "Feature",
  "properties": {
    "iso:country": "GB",
    "wof:name": "LE7 7PT",
    "wof:placetype": "postalcode"
  },
  "geometry": {"coordinates":[-1.137144,52.7135],"type":"Point"}
}
