{
  "type": "Feature",
  "properties": {
    "date:inception_lower": "1980-01-01",
    "date:inception_upper": "1980-01-01",
    "iso:country": "GB",
    "wof:name": "LE7 7PT",
    "wof:placetype": "postalcode"
  },
  "geometry": {"coordinates":[-1.137158,52.713545],"type":"Point"}
}
