{
  "type": "Feature",
  "properties": {
    "date:inception_lower": "1988-03-01",
    "date:inception_upper": "1988-03-01",
    "iso:country": "GB",
    "wof:name": "EN7 6ES",
    "wof:placetype": "postalcode"
  },
  "geometry": {"coordinates":[-0.057143,51.715082],"type":"Point"}
}
