{
  "type": "Feature",
  "properties": {
    "iso:country": "GB",
    "wof:name": "EN7 6ES",
    "wof:placetype": "postalcode"
  },
  "geometry": {"coordinates":[-0.057143,51.715082],"type":"Point"}
}
