{
  "type": "Feature",
  "properties": {
    "iso:country":"GB",
    "wof:name":"EN7 6ES",
    "wof:placetype":"postalcode"
},
  "geometry": {"coordinates":[-0.05714302950379,51.71508209059708],"type":"Point"}
}