{
  "type": "Feature",
  "properties": {
    "iso:country": "GB",
    "wof:name": "SE1 3LL",
    "wof:placetype": "postalcode"
  },
  "geometry": {"coordinates":[-0.079915,51.500456],"type":"Point"}
}
