{
  "type": "Feature",
  "properties": {
    "iso:country":"GB",
    "wof:name":"SE1 3LL",
    "wof:placetype":"postalcode"
},
  "geometry": {"coordinates":[-0.07991480662417,51.50045604895919],"type":"Point"}
}