{
  "type": "Feature",
  "properties": {
    "iso:country": "GB",
    "wof:name": "EN1 3LU",
    "wof:placetype": "postalcode"
  },
  "geometry": {"coordinates":[-0.069153,51.660139],"type":"Point"}
}
