{
  "type": "Feature",
  "properties": {
    "iso:country":"GB",
    "wof:name":"ME1 1XP",
    "wof:placetype":"postalcode"
},
  "geometry": {"coordinates":[0.50627197559952,51.38450947009918],"type":"Point"}
}