{
  "type": "Feature",
  "properties": {
    "iso:country":"GB",
    "wof:name":"MK13 9AW",
    "wof:placetype":"postalcode"
},
  "geometry": {"coordinates":[-0.79129081808837,52.05046787904717],"type":"Point"}
}