{
  "type": "Feature",
  "properties": {
    "iso:country":"GB",
    "wof:name":"ML5 4DA",
    "wof:placetype":"postalcode"
},
  "geometry": {"coordinates":[-4.02289391128372,55.85317115524892],"type":"Point"}
}