{
  "type": "Feature",
  "properties": {
    "iso:country":"GB",
    "wof:name":"CO11 2BG",
    "wof:placetype":"postalcode"
},
  "geometry": {"coordinates":[1.14087174780191,51.91209725810389],"type":"Point"}
}