{
  "type": "Feature",
  "properties": {
    "date:inception_lower":"2010-09-01",
    "date:inception_upper":"2010-09-30",
    "iso:country":"GB",
    "wof:name":"CO11 2BG",
    "wof:placetype":"postalcode"
},
  "geometry": {"coordinates":[1.140872,51.912097],"type":"Point"}
}