{
  "type": "Feature",
  "properties": {
    "iso:country": "GB",
    "wof:name": "CO11 2BG",
    "wof:placetype": "postalcode"
  },
  "geometry": {"coordinates":[1.140872,51.912097],"type":"Point"}
}
