{
  "type": "Feature",
  "properties": {
    "iso:country": "GB",
    "wof:name": "KY12 8LR",
    "wof:placetype": "postalcode"
  },
  "geometry": {"coordinates":[-3.572053,56.058299],"type":"Point"}
}
