{
  "type": "Feature",
  "properties": {
    "iso:country":"GB",
    "wof:name":"KY12 8LR",
    "wof:placetype":"postalcode"
},
  "geometry": {"coordinates":[-3.57188075727649,56.05827024654651],"type":"Point"}
}