{
  "type": "Feature",
  "properties": {
    "iso:country":"GB",
    "wof:name":"WA6 6JH",
    "wof:placetype":"postalcode"
},
  "geometry": {"coordinates":[-2.71053883072457,53.25845283075941],"type":"Point"}
}