{
  "type": "Feature",
  "properties": {
    "date:inception_lower": "2023-06-01",
    "date:inception_upper": "2023-06-01",
    "iso:country": "GB",
    "wof:name": "WA6 6JH",
    "wof:placetype": "postalcode"
  },
  "geometry": {"coordinates":[-2.710567,53.258423],"type":"Point"}
}
