{
  "type": "Feature",
  "properties": {
    "iso:country":"GB",
    "wof:name":"YO41 4BT",
    "wof:placetype":"postalcode"
},
  "geometry": {"coordinates":[-0.92549788036129,53.90905216247626],"type":"Point"}
}