{
  "type": "Feature",
  "properties": {
    "date:inception_lower":"1986-07-01",
    "date:inception_upper":"1986-07-31",
    "iso:country":"GB",
    "wof:name":"MK15 8QJ",
    "wof:placetype":"postalcode"
},
  "geometry": {"coordinates":[-0.736912,52.064346],"type":"Point"}
}