{
  "type": "Feature",
  "properties": {
    "iso:country": "GB",
    "wof:name": "MK15 8QJ",
    "wof:placetype": "postalcode"
  },
  "geometry": {"coordinates":[-0.736912,52.064346],"type":"Point"}
}
