{
  "type": "Feature",
  "properties": {
    "date:inception_lower": "1981-06-01",
    "date:inception_upper": "1981-06-01",
    "iso:country": "GB",
    "wof:name": "NR17 2PL",
    "wof:placetype": "postalcode"
  },
  "geometry": {"coordinates":[1.006003,52.516096],"type":"Point"}
}
