{
  "type": "Feature",
  "properties": {
    "iso:country":"GB",
    "wof:name":"SP2 7LE",
    "wof:placetype":"postalcode"
},
  "geometry": {"coordinates":[-1.81251819397615,51.07903624662594],"type":"Point"}
}