{
  "type": "Feature",
  "properties": {
    "date:inception_lower": "1990-02-01",
    "date:inception_upper": "1990-02-01",
    "iso:country": "GB",
    "wof:name": "SP2 7LE",
    "wof:placetype": "postalcode"
  },
  "geometry": {"coordinates":[-1.812518,51.079036],"type":"Point"}
}
