{
  "type": "Feature",
  "properties": {
    "iso:country": "GB",
    "wof:name": "SP2 7LE",
    "wof:placetype": "postalcode"
  },
  "geometry": {"coordinates":[-1.812518,51.079036],"type":"Point"}
}
