{
  "type": "Feature",
  "properties": {
    "iso:country": "GB",
    "wof:name": "AL3 5EW",
    "wof:placetype": "postalcode"
  },
  "geometry": {"coordinates":[-0.340565,51.754747],"type":"Point"}
}
