{
  "type": "Feature",
  "properties": {
    "iso:country":"GB",
    "wof:name":"AL3 5EW",
    "wof:placetype":"postalcode"
},
  "geometry": {"coordinates":[-0.34056486328584,51.75474745773088],"type":"Point"}
}