{
  "type": "Feature",
  "properties": {
    "iso:country":"GB",
    "wof:name":"IP4 5TX",
    "wof:placetype":"postalcode"
},
  "geometry": {"coordinates":[1.21231470140157,52.05176198665196],"type":"Point"}
}