{
  "type": "Feature",
  "properties": {
    "iso:country":"GB",
    "wof:name":"LS12 3SE",
    "wof:placetype":"postalcode"
},
  "geometry": {"coordinates":[-1.60412317682166,53.80007448160175],"type":"Point"}
}