{
  "type": "Feature",
  "properties": {
    "iso:country":"GB",
    "wof:name":"WN2 3NY",
    "wof:placetype":"postalcode"
},
  "geometry": {"coordinates":[-2.58240396251554,53.53168517311116],"type":"Point"}
}