{
  "type": "Feature",
  "properties": {
    "iso:country":"GB",
    "wof:name":"EH51 0LE",
    "wof:placetype":"postalcode"
},
  "geometry": {"coordinates":[-3.61542219156477,56.00725162153232],"type":"Point"}
}