{
  "type": "Feature",
  "properties": {
    "iso:country": "GB",
    "wof:name": "PO20 8JF",
    "wof:placetype": "postalcode"
  },
  "geometry": {"coordinates":[-0.852012,50.77162],"type":"Point"}
}
