{
  "type": "Feature",
  "properties": {
    "iso:country":"GB",
    "wof:name":"PO20 8JF",
    "wof:placetype":"postalcode"
},
  "geometry": {"coordinates":[-0.85178722769386,50.77169998393553],"type":"Point"}
}