{
  "type": "Feature",
  "properties": {
    "iso:country": "GB",
    "wof:name": "RH9 8FD",
    "wof:placetype": "postalcode"
  },
  "geometry": {"coordinates":[-0.07507,51.247111],"type":"Point"}
}
