{
  "type": "Feature",
  "properties": {
    "date:inception_lower":"2012-03-01",
    "date:inception_upper":"2012-03-31",
    "iso:country":"GB",
    "wof:name":"NG24 1XF",
    "wof:placetype":"postalcode"
},
  "geometry": {"coordinates":[-0.811777,53.074813],"type":"Point"}
}