{
  "type": "Feature",
  "properties": {
    "iso:country": "GB",
    "wof:name": "S66 8JP",
    "wof:placetype": "postalcode"
  },
  "geometry": {"coordinates":[-1.204869,53.429493],"type":"Point"}
}
