{
  "type": "Feature",
  "properties": {
    "iso:country":"GB",
    "wof:name":"BH18 9DE",
    "wof:placetype":"postalcode"
},
  "geometry": {"coordinates":[-2.00825670650325,50.76296951948866],"type":"Point"}
}