{
  "type": "Feature",
  "properties": {
    "iso:country":"GB",
    "wof:name":"WA9 4SW",
    "wof:placetype":"postalcode"
},
  "geometry": {"coordinates":[-2.68540991957201,53.42666411033422],"type":"Point"}
}