{
  "type": "Feature",
  "properties": {
    "iso:country": "GB",
    "wof:name": "WA9 4SW",
    "wof:placetype": "postalcode"
  },
  "geometry": {"coordinates":[-2.686929,53.426671],"type":"Point"}
}
