{
  "type": "Feature",
  "properties": {
    "iso:country":"GB",
    "wof:name":"AB42 0RP",
    "wof:placetype":"postalcode"
},
  "geometry": {"coordinates":[-1.86363204700176,57.41477859241465],"type":"Point"}
}