{
  "type": "Feature",
  "properties": {
    "iso:country": "GB",
    "wof:name": "AB42 0RP",
    "wof:placetype": "postalcode"
  },
  "geometry": {"coordinates":[-1.863632,57.414779],"type":"Point"}
}
