{
  "type": "Feature",
  "properties": {
    "date:inception_lower":"1980-01-01",
    "date:inception_upper":"1980-01-31",
    "iso:country":"GB",
    "wof:name":"PE21 7PN",
    "wof:placetype":"postalcode"
},
  "geometry": {"coordinates":[-0.047027,52.97273],"type":"Point"}
}