{
  "type": "Feature",
  "properties": {
    "iso:country": "GB",
    "wof:name": "PE21 7PN",
    "wof:placetype": "postalcode"
  },
  "geometry": {"coordinates":[-0.047027,52.97273],"type":"Point"}
}
