{
  "type": "Feature",
  "properties": {
    "date:inception_lower":"2005-08-01",
    "date:inception_upper":"2005-08-31",
    "iso:country":"GB",
    "wof:name":"DN22 8LD",
    "wof:placetype":"postalcode"
},
  "geometry": {"coordinates":[-1.006367,53.38291],"type":"Point"}
}