{
  "type": "Feature",
  "properties": {
    "iso:country":"GB",
    "wof:name":"CH44 5UE",
    "wof:placetype":"postalcode"
},
  "geometry": {"coordinates":[-3.04604637202866,53.41691205642511],"type":"Point"}
}