{
  "type": "Feature",
  "properties": {
    "date:inception_lower": "2013-12-01",
    "date:inception_upper": "2013-12-01",
    "iso:country": "GB",
    "wof:name": "GU17 0SE",
    "wof:placetype": "postalcode"
  },
  "geometry": {"coordinates":[-0.806146,51.337809],"type":"Point"}
}
