{
  "type": "Feature",
  "properties": {
    "iso:country": "GB",
    "wof:name": "BH23 8EE",
    "wof:placetype": "postalcode"
  },
  "geometry": {"coordinates":[-1.73572,50.803541],"type":"Point"}
}
