{
  "type": "Feature",
  "properties": {
    "iso:country": "GB",
    "wof:name": "BN1 4EZ",
    "wof:placetype": "postalcode"
  },
  "geometry": {"coordinates":[-0.137334,50.827888],"type":"Point"}
}
