{
  "type": "Feature",
  "properties": {
    "date:inception_lower": "2005-06-01",
    "date:inception_upper": "2005-06-01",
    "iso:country": "GB",
    "wof:name": "BN1 4EZ",
    "wof:placetype": "postalcode"
  },
  "geometry": {"coordinates":[-0.137334,50.827888],"type":"Point"}
}
