{
  "type": "Feature",
  "properties": {
    "iso:country":"GB",
    "wof:name":"BN1 4EZ",
    "wof:placetype":"postalcode"
},
  "geometry": {"coordinates":[-0.13733450570569,50.82788788672138],"type":"Point"}
}