{
  "type": "Feature",
  "properties": {
    "date:inception_lower":"2005-09-01",
    "date:inception_upper":"2005-09-30",
    "iso:country":"GB",
    "wof:name":"MK10 9PJ",
    "wof:placetype":"postalcode"
},
  "geometry": {"coordinates":[-0.713851,52.0343],"type":"Point"}
}