{
  "type": "Feature",
  "properties": {
    "date:inception_lower": "1980-01-01",
    "date:inception_upper": "1980-01-01",
    "iso:country": "GB",
    "wof:name": "HR6 9PR",
    "wof:placetype": "postalcode"
  },
  "geometry": {"coordinates":[-2.780336,52.271509],"type":"Point"}
}
