{
  "type": "Feature",
  "properties": {
    "iso:country": "GB",
    "wof:name": "HR6 9PR",
    "wof:placetype": "postalcode"
  },
  "geometry": {"coordinates":[-2.780336,52.271509],"type":"Point"}
}
