{
  "type": "Feature",
  "properties": {
    "date:inception_lower": "1980-01-01",
    "date:inception_upper": "1980-01-01",
    "iso:country": "GB",
    "wof:name": "DN20 8PW",
    "wof:placetype": "postalcode"
  },
  "geometry": {"coordinates":[-0.486277,53.559672],"type":"Point"}
}
