{
  "type": "Feature",
  "properties": {
    "iso:country":"GB",
    "wof:name":"W2 3JJ",
    "wof:placetype":"postalcode"
},
  "geometry": {"coordinates":[-0.18611299205317,51.5106985062295],"type":"Point"}
}