{
  "type": "Feature",
  "properties": {
    "date:inception_lower": "1980-01-01",
    "date:inception_upper": "1980-01-01",
    "iso:country": "GB",
    "wof:name": "W2 3JJ",
    "wof:placetype": "postalcode"
  },
  "geometry": {"coordinates":[-0.186113,51.510699],"type":"Point"}
}
