{
  "type": "Feature",
  "properties": {
    "iso:country": "GB",
    "wof:name": "SP11 6PX",
    "wof:placetype": "postalcode"
  },
  "geometry": {"coordinates":[-1.38269,51.198417],"type":"Point"}
}
