{
  "type": "Feature",
  "properties": {
    "iso:country":"GB",
    "wof:name":"SP11 6PX",
    "wof:placetype":"postalcode"
},
  "geometry": {"coordinates":[-1.3826147159276,51.19867240277341],"type":"Point"}
}