{
  "type": "Feature",
  "properties": {
    "iso:country":"GB",
    "wof:name":"WA9 5FY",
    "wof:placetype":"postalcode"
},
  "geometry": {"coordinates":[-2.72397676762835,53.44319144592529],"type":"Point"}
}