{
  "type": "Feature",
  "properties": {
    "date:inception_lower":"1999-06-01",
    "date:inception_upper":"1999-06-30",
    "iso:country":"GB",
    "wof:name":"WA9 5FY",
    "wof:placetype":"postalcode"
},
  "geometry": {"coordinates":[-2.723977,53.443191],"type":"Point"}
}