{
  "type": "Feature",
  "properties": {
    "iso:country":"GB",
    "wof:name":"E15 1JQ",
    "wof:placetype":"postalcode"
},
  "geometry": {"coordinates":[0.00192562101575,51.54782773097253],"type":"Point"}
}