{
  "type": "Feature",
  "properties": {
    "iso:country": "GB",
    "wof:name": "BL8 4EF",
    "wof:placetype": "postalcode"
  },
  "geometry": {"coordinates":[-2.330787,53.623941],"type":"Point"}
}
