{
  "type": "Feature",
  "properties": {
    "iso:country":"GB",
    "wof:name":"BL8 4EF",
    "wof:placetype":"postalcode"
},
  "geometry": {"coordinates":[-2.33078689933985,53.6239409474379],"type":"Point"}
}