{
  "type": "Feature",
  "properties": {
    "iso:country":"GB",
    "wof:name":"LS12 2AZ",
    "wof:placetype":"postalcode"
},
  "geometry": {"coordinates":[-1.58841657248263,53.80086651798639],"type":"Point"}
}