{
  "type": "Feature",
  "properties": {
    "date:inception_lower": "2020-10-01",
    "date:inception_upper": "2020-10-01",
    "iso:country": "GB",
    "wof:name": "WR11 7WE",
    "wof:placetype": "postalcode"
  },
  "geometry": {"coordinates":[-2.002731,52.046766],"type":"Point"}
}
