{
  "type": "Feature",
  "properties": {
    "iso:country": "GB",
    "wof:name": "LL36 9BY",
    "wof:placetype": "postalcode"
  },
  "geometry": {"coordinates":[-4.086949,52.587353],"type":"Point"}
}
