{
  "type": "Feature",
  "properties": {
    "iso:country":"GB",
    "wof:name":"LL36 9BY",
    "wof:placetype":"postalcode"
},
  "geometry": {"coordinates":[-4.08628780812468,52.58757301663881],"type":"Point"}
}