{
  "type": "Feature",
  "properties": {
    "date:inception_lower": "1999-06-01",
    "date:inception_upper": "1999-06-01",
    "iso:country": "GB",
    "wof:name": "NE12 6HB",
    "wof:placetype": "postalcode"
  },
  "geometry": {"coordinates":[-1.554782,55.033518],"type":"Point"}
}
