{
  "type": "Feature",
  "properties": {
    "date:inception_lower": "1999-06-01",
    "date:inception_upper": "1999-06-01",
    "iso:country": "GB",
    "wof:name": "CF11 0JL",
    "wof:placetype": "postalcode"
  },
  "geometry": {"coordinates":[-3.185622,51.461771],"type":"Point"}
}
