{
  "type": "Feature",
  "properties": {
    "iso:country":"GB",
    "wof:name":"IV20 1RG",
    "wof:placetype":"postalcode"
},
  "geometry": {"coordinates":[-3.84745593129465,57.81798666892573],"type":"Point"}
}