{
  "type": "Feature",
  "properties": {
    "date:inception_lower": "1990-08-01",
    "date:inception_upper": "1990-08-01",
    "iso:country": "GB",
    "wof:name": "AB51 0AA",
    "wof:placetype": "postalcode"
  },
  "geometry": {"coordinates":[-2.319789,57.335236],"type":"Point"}
}
