{
  "type": "Feature",
  "properties": {
    "iso:country":"GB",
    "wof:name":"AB51 0AA",
    "wof:placetype":"postalcode"
},
  "geometry": {"coordinates":[-2.31978939743471,57.33523587494483],"type":"Point"}
}