{
  "type": "Feature",
  "properties": {
    "date:inception_lower": "1991-07-01",
    "date:inception_upper": "1991-07-01",
    "iso:country": "GB",
    "wof:name": "G77 5DH",
    "wof:placetype": "postalcode"
  },
  "geometry": {"coordinates":[-4.318713,55.76547],"type":"Point"}
}
