{
  "type": "Feature",
  "properties": {
    "iso:country":"GB",
    "wof:name":"G77 5DH",
    "wof:placetype":"postalcode"
},
  "geometry": {"coordinates":[-4.31871351701555,55.76547032578513],"type":"Point"}
}