{
  "type": "Feature",
  "properties": {
    "iso:country": "GB",
    "wof:name": "MK18 4EL",
    "wof:placetype": "postalcode"
  },
  "geometry": {"coordinates":[-1.040528,51.929708],"type":"Point"}
}
