{
  "type": "Feature",
  "properties": {
    "date:inception_lower": "1980-01-01",
    "date:inception_upper": "1980-01-01",
    "iso:country": "GB",
    "wof:name": "MK18 4EL",
    "wof:placetype": "postalcode"
  },
  "geometry": {"coordinates":[-1.040443,51.929609],"type":"Point"}
}
