{
  "type": "Feature",
  "properties": {
    "iso:country":"GB",
    "wof:name":"MK18 4EL",
    "wof:placetype":"postalcode"
},
  "geometry": {"coordinates":[-1.0405485492265,51.92970044915911],"type":"Point"}
}