{
  "type": "Feature",
  "properties": {
    "date:inception_lower":"1980-01-01",
    "date:inception_upper":"1980-01-31",
    "iso:country":"GB",
    "wof:name":"SY6 6JW",
    "wof:placetype":"postalcode"
},
  "geometry": {"coordinates":[-2.804632,52.554845],"type":"Point"}
}