{
  "type": "Feature",
  "properties": {
    "iso:country":"GB",
    "wof:name":"SY6 6JW",
    "wof:placetype":"postalcode"
},
  "geometry": {"coordinates":[-2.80463226175446,52.55484510964824],"type":"Point"}
}