{
  "type": "Feature",
  "properties": {
    "date:inception_lower": "2019-06-01",
    "date:inception_upper": "2019-06-01",
    "iso:country": "GB",
    "wof:name": "LN2 2GP",
    "wof:placetype": "postalcode"
  },
  "geometry": {"coordinates":[-0.493129,53.269935],"type":"Point"}
}
