{
  "type": "Feature",
  "properties": {
    "iso:country":"GB",
    "wof:name":"PE23 4HQ",
    "wof:placetype":"postalcode"
},
  "geometry": {"coordinates":[0.01392624503726,53.16756752926174],"type":"Point"}
}