{
  "type": "Feature",
  "properties": {
    "iso:country":"GB",
    "wof:name":"NW10 8HG",
    "wof:placetype":"postalcode"
},
  "geometry": {"coordinates":[-0.2632218577262,51.54454383525844],"type":"Point"}
}