{
  "type": "Feature",
  "properties": {
    "iso:country":"GB",
    "wof:name":"DY1 3LE",
    "wof:placetype":"postalcode"
},
  "geometry": {"coordinates":[-2.09768004844943,52.52639063723881],"type":"Point"}
}