{
  "type": "Feature",
  "properties": {
    "iso:country":"GB",
    "wof:name":"LL65 2YX",
    "wof:placetype":"postalcode"
},
  "geometry": {"coordinates":[-4.62179684439639,53.2863236743364],"type":"Point"}
}