{
  "type": "Feature",
  "properties": {
    "date:inception_lower": "2006-09-01",
    "date:inception_upper": "2006-09-01",
    "iso:country": "GB",
    "wof:name": "LL65 2YX",
    "wof:placetype": "postalcode"
  },
  "geometry": {"coordinates":[-4.621797,53.286324],"type":"Point"}
}
