{
  "type": "Feature",
  "properties": {
    "iso:country":"GB",
    "wof:name":"BB10 2RS",
    "wof:placetype":"postalcode"
},
  "geometry": {"coordinates":[-2.19976040603941,53.8118130850696],"type":"Point"}
}