{
  "type": "Feature",
  "properties": {
    "iso:country":"GB",
    "wof:name":"M40 7SP",
    "wof:placetype":"postalcode"
},
  "geometry": {"coordinates":[-2.22116645337536,53.49857298777925],"type":"Point"}
}