{
  "type": "Feature",
  "properties": {
    "iso:country":"GB",
    "wof:name":"N6 4RH",
    "wof:placetype":"postalcode"
},
  "geometry": {"coordinates":[-0.15380977184094,51.57930143927551],"type":"Point"}
}