{
  "type": "Feature",
  "properties": {
    "iso:country": "GB",
    "wof:name": "SM2 5BB",
    "wof:placetype": "postalcode"
  },
  "geometry": {"coordinates":[-0.197883,51.347719],"type":"Point"}
}
