{
  "type": "Feature",
  "properties": {
    "iso:country":"GB",
    "wof:name":"SM2 5BB",
    "wof:placetype":"postalcode"
},
  "geometry": {"coordinates":[-0.19788346525922,51.34771896151265],"type":"Point"}
}