{
  "type": "Feature",
  "properties": {
    "date:inception_lower":"1980-01-01",
    "date:inception_upper":"1980-01-31",
    "iso:country":"GB",
    "wof:name":"SM4 5NB",
    "wof:placetype":"postalcode"
},
  "geometry": {"coordinates":[-0.19104,51.397145],"type":"Point"}
}