{
  "type": "Feature",
  "properties": {
    "iso:country":"GB",
    "wof:name":"SM4 5NB",
    "wof:placetype":"postalcode"
},
  "geometry": {"coordinates":[-0.19103968301967,51.39714496110631],"type":"Point"}
}