{
  "type": "Feature",
  "properties": {
    "iso:country":"GB",
    "wof:name":"CV35 9DP",
    "wof:placetype":"postalcode"
},
  "geometry": {"coordinates":[-1.56855096898034,52.21170827324489],"type":"Point"}
}