{
  "type": "Feature",
  "properties": {
    "date:inception_lower": "1980-01-01",
    "date:inception_upper": "1980-01-01",
    "iso:country": "GB",
    "wof:name": "CV35 9DP",
    "wof:placetype": "postalcode"
  },
  "geometry": {"coordinates":[-1.568551,52.211708],"type":"Point"}
}
