{
  "type": "Feature",
  "properties": {
    "date:inception_lower": "1998-06-01",
    "date:inception_upper": "1998-06-01",
    "iso:country": "GB",
    "wof:name": "YO32 2RE",
    "wof:placetype": "postalcode"
  },
  "geometry": {"coordinates":[-1.12056,54.021407],"type":"Point"}
}
