{
  "type": "Feature",
  "properties": {
    "iso:country":"GB",
    "wof:name":"YO32 2RE",
    "wof:placetype":"postalcode"
},
  "geometry": {"coordinates":[-1.12055967189791,54.02140727808735],"type":"Point"}
}