{
  "type": "Feature",
  "properties": {
    "iso:country":"GB",
    "wof:name":"LL15 2RG",
    "wof:placetype":"postalcode"
},
  "geometry": {"coordinates":[-3.35299055104448,53.02945362496366],"type":"Point"}
}