{
  "type": "Feature",
  "properties": {
    "date:inception_lower": "2007-03-01",
    "date:inception_upper": "2007-03-01",
    "iso:country": "GB",
    "wof:name": "OX18 3AN",
    "wof:placetype": "postalcode"
  },
  "geometry": {"coordinates":[-1.581593,51.76584],"type":"Point"}
}
