{
  "type": "Feature",
  "properties": {
    "date:inception_lower": "2021-06-01",
    "date:inception_upper": "2021-06-01",
    "iso:country": "GB",
    "wof:name": "DN22 8FR",
    "wof:placetype": "postalcode"
  },
  "geometry": {"coordinates":[-1.010693,53.389627],"type":"Point"}
}
