{
  "type": "Feature",
  "properties": {
    "iso:country": "GB",
    "wof:name": "GU15 1RY",
    "wof:placetype": "postalcode"
  },
  "geometry": {"coordinates":[-0.703748,51.331173],"type":"Point"}
}
