{
  "type": "Feature",
  "properties": {
    "iso:country":"GB",
    "wof:name":"CB7 4FF",
    "wof:placetype":"postalcode"
},
  "geometry": {"coordinates":[0.2744959437746,52.41373134796316],"type":"Point"}
}