{
  "type": "Feature",
  "properties": {
    "date:inception_lower":"1995-12-01",
    "date:inception_upper":"1995-12-31",
    "iso:country":"GB",
    "wof:name":"CB7 4FF",
    "wof:placetype":"postalcode"
},
  "geometry": {"coordinates":[0.274496,52.413731],"type":"Point"}
}