{
  "type": "Feature",
  "properties": {
    "iso:country":"GB",
    "wof:name":"WF11 8QG",
    "wof:placetype":"postalcode"
},
  "geometry": {"coordinates":[-1.27844283601659,53.70949355969358],"type":"Point"}
}