{
  "type": "Feature",
  "properties": {
    "iso:country":"GB",
    "wof:name":"EX10 0HJ",
    "wof:placetype":"postalcode"
},
  "geometry": {"coordinates":[-3.30691401942961,50.68041643675507],"type":"Point"}
}