{
  "type": "Feature",
  "properties": {
    "date:inception_lower":"1980-01-01",
    "date:inception_upper":"1980-01-31",
    "iso:country":"GB",
    "wof:name":"EX10 0HJ",
    "wof:placetype":"postalcode"
},
  "geometry": {"coordinates":[-3.306914,50.680416],"type":"Point"}
}