{
  "type": "Feature",
  "properties": {
    "iso:country": "GB",
    "wof:name": "EX10 0HJ",
    "wof:placetype": "postalcode"
  },
  "geometry": {"coordinates":[-3.306914,50.680416],"type":"Point"}
}
