{
  "type": "Feature",
  "properties": {
    "iso:country":"GB",
    "wof:name":"B78 3HW",
    "wof:placetype":"postalcode"
},
  "geometry": {"coordinates":[-1.71784097472575,52.62058773494698],"type":"Point"}
}