{
  "type": "Feature",
  "properties": {
    "date:inception_lower": "1980-01-01",
    "date:inception_upper": "1980-01-01",
    "iso:country": "GB",
    "wof:name": "W13 8DA",
    "wof:placetype": "postalcode"
  },
  "geometry": {"coordinates":[-0.316359,51.522838],"type":"Point"}
}
