{
  "type": "Feature",
  "properties": {
    "iso:country":"GB",
    "wof:name":"NG19 6SB",
    "wof:placetype":"postalcode"
},
  "geometry": {"coordinates":[-1.21075509248988,53.14850090790975],"type":"Point"}
}