{
  "type": "Feature",
  "properties": {
    "date:inception_lower": "1980-01-01",
    "date:inception_upper": "1980-01-01",
    "iso:country": "GB",
    "wof:name": "NG19 6SB",
    "wof:placetype": "postalcode"
  },
  "geometry": {"coordinates":[-1.210755,53.148501],"type":"Point"}
}
