{
  "type": "Feature",
  "properties": {
    "iso:country":"GB",
    "wof:name":"S61 4AT",
    "wof:placetype":"postalcode"
},
  "geometry": {"coordinates":[-1.38175752543607,53.45022424223762],"type":"Point"}
}