{
  "type": "Feature",
  "properties": {
    "iso:country":"GB",
    "wof:name":"LS11 8SX",
    "wof:placetype":"postalcode"
},
  "geometry": {"coordinates":[-1.55910852321617,53.77961355116444],"type":"Point"}
}