{
  "type": "Feature",
  "properties": {
    "date:inception_lower": "1980-01-01",
    "date:inception_upper": "1980-01-01",
    "iso:country": "GB",
    "wof:name": "LS11 8SX",
    "wof:placetype": "postalcode"
  },
  "geometry": {"coordinates":[-1.558993,53.779494],"type":"Point"}
}
