{
  "type": "Feature",
  "properties": {
    "iso:country":"GB",
    "wof:name":"B38 9NN",
    "wof:placetype":"postalcode"
},
  "geometry": {"coordinates":[-1.9253469325007,52.40273258287355],"type":"Point"}
}