{
  "type": "Feature",
  "properties": {
    "iso:country":"GB",
    "wof:name":"IP4 4LH",
    "wof:placetype":"postalcode"
},
  "geometry": {"coordinates":[1.18981687135688,52.06359815797002],"type":"Point"}
}