{
  "type": "Feature",
  "properties": {
    "iso:country":"GB",
    "wof:name":"L39 4SW",
    "wof:placetype":"postalcode"
},
  "geometry": {"coordinates":[-2.89761081582457,53.55804807234159],"type":"Point"}
}