{
  "type": "Feature",
  "properties": {
    "iso:country": "GB",
    "wof:name": "L39 4SW",
    "wof:placetype": "postalcode"
  },
  "geometry": {"coordinates":[-2.897611,53.558048],"type":"Point"}
}
