{
  "type": "Feature",
  "properties": {
    "iso:country": "GB",
    "wof:name": "MK44 2HR",
    "wof:placetype": "postalcode"
  },
  "geometry": {"coordinates":[-0.423187,52.258555],"type":"Point"}
}
