{
  "type": "Feature",
  "properties": {
    "iso:country":"GB",
    "wof:name":"MK44 2HR",
    "wof:placetype":"postalcode"
},
  "geometry": {"coordinates":[-0.42318748860345,52.25855494778236],"type":"Point"}
}