{
  "type": "Feature",
  "properties": {
    "iso:country":"GB",
    "wof:name":"SS16 6LG",
    "wof:placetype":"postalcode"
},
  "geometry": {"coordinates":[0.42435564660578,51.56253828573697],"type":"Point"}
}