{
  "type": "Feature",
  "properties": {
    "iso:country": "GB",
    "wof:name": "DT6 4SD",
    "wof:placetype": "postalcode"
  },
  "geometry": {"coordinates":[-2.725722,50.70571],"type":"Point"}
}
