{
  "type": "Feature",
  "properties": {
    "iso:country":"GB",
    "wof:name":"DT6 4SD",
    "wof:placetype":"postalcode"
},
  "geometry": {"coordinates":[-2.72572203329562,50.70571041930489],"type":"Point"}
}