{
  "type": "Feature",
  "properties": {
    "iso:country":"GB",
    "wof:name":"DL8 5LX",
    "wof:placetype":"postalcode"
},
  "geometry": {"coordinates":[-1.72821884075517,54.31184087921669],"type":"Point"}
}