{
  "type": "Feature",
  "properties": {
    "iso:country": "GB",
    "wof:name": "DL8 5LX",
    "wof:placetype": "postalcode"
  },
  "geometry": {"coordinates":[-1.728219,54.311841],"type":"Point"}
}
