{
  "type": "Feature",
  "properties": {
    "iso:country":"GB",
    "wof:name":"PO7 6ES",
    "wof:placetype":"postalcode"
},
  "geometry": {"coordinates":[-1.07845057263541,50.9103549835135],"type":"Point"}
}