{
  "type": "Feature",
  "properties": {
    "iso:country":"GB",
    "wof:name":"TR7 1RE",
    "wof:placetype":"postalcode"
},
  "geometry": {"coordinates":[-5.08766844066236,50.41236407010527],"type":"Point"}
}