{
  "type": "Feature",
  "properties": {
    "iso:country":"GB",
    "wof:name":"CA6 5TY",
    "wof:placetype":"postalcode"
},
  "geometry": {"coordinates":[-2.83917358903326,55.0326226262527],"type":"Point"}
}