{
  "type": "Feature",
  "properties": {
    "date:inception_lower": "1998-12-01",
    "date:inception_upper": "1998-12-01",
    "iso:country": "GB",
    "wof:name": "IV2 5FP",
    "wof:placetype": "postalcode"
  },
  "geometry": {"coordinates":[-4.005807,57.521541],"type":"Point"}
}
