{
  "type": "Feature",
  "properties": {
    "iso:country":"GB",
    "wof:name":"B71 2EJ",
    "wof:placetype":"postalcode"
},
  "geometry": {"coordinates":[-1.99747913134054,52.54708087138609],"type":"Point"}
}