{
  "type": "Feature",
  "properties": {
    "iso:country":"GB",
    "wof:name":"PO9 5BJ",
    "wof:placetype":"postalcode"
},
  "geometry": {"coordinates":[-0.98955410402444,50.87081619550143],"type":"Point"}
}