{
  "type": "Feature",
  "properties": {
    "iso:country":"GB",
    "wof:name":"CO12 4WE",
    "wof:placetype":"postalcode"
},
  "geometry": {"coordinates":[1.24708980560514,51.92674211249914],"type":"Point"}
}