{
  "type": "Feature",
  "properties": {
    "iso:country":"GB",
    "wof:name":"ST5 8QJ",
    "wof:placetype":"postalcode"
},
  "geometry": {"coordinates":[-2.22505839042315,53.03705492661805],"type":"Point"}
}