{
  "type": "Feature",
  "properties": {
    "iso:country": "GB",
    "wof:name": "ST5 8QJ",
    "wof:placetype": "postalcode"
  },
  "geometry": {"coordinates":[-2.225058,53.037055],"type":"Point"}
}
