{
  "type": "Feature",
  "properties": {
    "iso:country":"GB",
    "wof:name":"DH7 7NH",
    "wof:placetype":"postalcode"
},
  "geometry": {"coordinates":[-1.64330431800925,54.78102301013158],"type":"Point"}
}