{
  "type": "Feature",
  "properties": {
    "iso:country": "GB",
    "wof:name": "DH7 7NH",
    "wof:placetype": "postalcode"
  },
  "geometry": {"coordinates":[-1.643304,54.781023],"type":"Point"}
}
