{
  "type": "Feature",
  "properties": {
    "iso:country":"GB",
    "wof:name":"GU12 5LF",
    "wof:placetype":"postalcode"
},
  "geometry": {"coordinates":[-0.72525557905365,51.26830097496268],"type":"Point"}
}