{
  "type": "Feature",
  "properties": {
    "iso:country": "GB",
    "wof:name": "PE24 5QH",
    "wof:placetype": "postalcode"
  },
  "geometry": {"coordinates":[0.31338,53.234054],"type":"Point"}
}
