{
  "type": "Feature",
  "properties": {
    "iso:country":"GB",
    "wof:name":"PE24 5QH",
    "wof:placetype":"postalcode"
},
  "geometry": {"coordinates":[0.31418703250394,53.23400222623956],"type":"Point"}
}