{
  "type": "Feature",
  "properties": {
    "iso:country": "GB",
    "wof:name": "EH54 0HN",
    "wof:placetype": "postalcode"
  },
  "geometry": {"coordinates":[-3.52951,55.891391],"type":"Point"}
}
