{
  "type": "Feature",
  "properties": {
    "iso:country":"GB",
    "wof:name":"RG6 5TG",
    "wof:placetype":"postalcode"
},
  "geometry": {"coordinates":[-0.94264418979615,51.43198060123892],"type":"Point"}
}