{
  "type": "Feature",
  "properties": {
    "iso:country":"GB",
    "wof:name":"L37 3LU",
    "wof:placetype":"postalcode"
},
  "geometry": {"coordinates":[-3.05367825753597,53.56233870141524],"type":"Point"}
}