{
  "type": "Feature",
  "properties": {
    "iso:country":"GB",
    "wof:name":"NN6 6JF",
    "wof:placetype":"postalcode"
},
  "geometry": {"coordinates":[-1.02687651116529,52.39500414327478],"type":"Point"}
}