{
  "type": "Feature",
  "properties": {
    "date:inception_lower":"1993-08-01",
    "date:inception_upper":"1993-08-31",
    "iso:country":"GB",
    "wof:name":"NN6 6JF",
    "wof:placetype":"postalcode"
},
  "geometry": {"coordinates":[-1.026876,52.395004],"type":"Point"}
}