{
  "type": "Feature",
  "properties": {
    "iso:country": "GB",
    "wof:name": "NN6 6JF",
    "wof:placetype": "postalcode"
  },
  "geometry": {"coordinates":[-1.026876,52.395004],"type":"Point"}
}
