{
  "type": "Feature",
  "properties": {
    "iso:country":"GB",
    "wof:name":"PL31 1FN",
    "wof:placetype":"postalcode"
},
  "geometry": {"coordinates":[-4.71510201760737,50.46425454547827],"type":"Point"}
}