{
  "type": "Feature",
  "properties": {
    "date:inception_lower":"2012-03-01",
    "date:inception_upper":"2012-03-31",
    "iso:country":"GB",
    "wof:name":"PL31 1FN",
    "wof:placetype":"postalcode"
},
  "geometry": {"coordinates":[-4.715159,50.464298],"type":"Point"}
}