{
  "type": "Feature",
  "properties": {
    "iso:country":"GB",
    "wof:name":"IG6 1LF",
    "wof:placetype":"postalcode"
},
  "geometry": {"coordinates":[0.07263438995597,51.58602374096806],"type":"Point"}
}