{
  "type": "Feature",
  "properties": {
    "iso:country":"GB",
    "wof:name":"NP8 1PS",
    "wof:placetype":"postalcode"
},
  "geometry": {"coordinates":[-3.15214722567358,51.85848266675097],"type":"Point"}
}