{
  "type": "Feature",
  "properties": {
    "iso:country":"GB",
    "wof:name":"SL6 7NL",
    "wof:placetype":"postalcode"
},
  "geometry": {"coordinates":[-0.73629727763584,51.53473064173937],"type":"Point"}
}