{
  "type": "Feature",
  "properties": {
    "date:inception_lower": "2020-04-01",
    "date:inception_upper": "2020-04-01",
    "iso:country": "GB",
    "wof:name": "DE15 9PW",
    "wof:placetype": "postalcode"
  },
  "geometry": {"coordinates":[-1.633629,52.782755],"type":"Point"}
}
