{
  "type": "Feature",
  "properties": {
    "iso:country": "GB",
    "wof:name": "HA5 3AY",
    "wof:placetype": "postalcode"
  },
  "geometry": {"coordinates":[-0.376026,51.599654],"type":"Point"}
}
