{
  "type": "Feature",
  "properties": {
    "iso:country": "GB",
    "wof:name": "LE10 3LS",
    "wof:placetype": "postalcode"
  },
  "geometry": {"coordinates":[-1.372676,52.485609],"type":"Point"}
}
