{
  "type": "Feature",
  "properties": {
    "date:inception_lower": "1980-01-01",
    "date:inception_upper": "1980-01-01",
    "iso:country": "GB",
    "wof:name": "LE10 3LS",
    "wof:placetype": "postalcode"
  },
  "geometry": {"coordinates":[-1.372676,52.485609],"type":"Point"}
}
