{
  "type": "Feature",
  "properties": {
    "iso:country": "GB",
    "wof:name": "RH13 8LQ",
    "wof:placetype": "postalcode"
  },
  "geometry": {"coordinates":[-0.342228,50.977882],"type":"Point"}
}
