{
  "type": "Feature",
  "properties": {
    "iso:country":"GB",
    "wof:name":"SE17 2SX",
    "wof:placetype":"postalcode"
},
  "geometry": {"coordinates":[-0.08245183446139,51.49012909339291],"type":"Point"}
}