{
  "type": "Feature",
  "properties": {
    "iso:country":"GB",
    "wof:name":"SN3 3DF",
    "wof:placetype":"postalcode"
},
  "geometry": {"coordinates":[-1.75279558138372,51.56197165840703],"type":"Point"}
}