{
  "type": "Feature",
  "properties": {
    "iso:country": "GB",
    "wof:name": "TN39 3QE",
    "wof:placetype": "postalcode"
  },
  "geometry": {"coordinates":[0.459977,50.842238],"type":"Point"}
}
