{
  "type": "Feature",
  "properties": {
    "date:inception_lower":"2008-05-01",
    "date:inception_upper":"2008-05-31",
    "iso:country":"GB",
    "wof:name":"YO13 9EG",
    "wof:placetype":"postalcode"
},
  "geometry": {"coordinates":[-0.587973,54.268769],"type":"Point"}
}