{
  "type": "Feature",
  "properties": {
    "iso:country": "GB",
    "wof:name": "YO13 9EG",
    "wof:placetype": "postalcode"
  },
  "geometry": {"coordinates":[-0.587973,54.268769],"type":"Point"}
}
