{
  "type": "Feature",
  "properties": {
    "iso:country":"GB",
    "wof:name":"PE9 2TU",
    "wof:placetype":"postalcode"
},
  "geometry": {"coordinates":[-0.50634444771659,52.65805340746012],"type":"Point"}
}