{
  "type": "Feature",
  "properties": {
    "iso:country":"GB",
    "wof:name":"LE4 2PP",
    "wof:placetype":"postalcode"
},
  "geometry": {"coordinates":[-1.14191817223889,52.66663300321812],"type":"Point"}
}