{
  "type": "Feature",
  "properties": {
    "date:inception_lower":"2001-06-01",
    "date:inception_upper":"2001-06-30",
    "iso:country":"GB",
    "wof:name":"OX5 2PL",
    "wof:placetype":"postalcode"
},
  "geometry": {"coordinates":[-1.288432,51.82193],"type":"Point"}
}