{
  "type": "Feature",
  "properties": {
    "iso:country":"GB",
    "wof:name":"OX5 2PL",
    "wof:placetype":"postalcode"
},
  "geometry": {"coordinates":[-1.2884323364111,51.82193030234904],"type":"Point"}
}