{
  "type": "Feature",
  "properties": {
    "iso:country":"GB",
    "wof:name":"UB8 3PW",
    "wof:placetype":"postalcode"
},
  "geometry": {"coordinates":[-0.46590347915644,51.52992420166009],"type":"Point"}
}