{
  "type": "Feature",
  "properties": {
    "date:inception_lower": "2000-12-01",
    "date:inception_upper": "2000-12-01",
    "iso:country": "GB",
    "wof:name": "WD18 0QL",
    "wof:placetype": "postalcode"
  },
  "geometry": {"coordinates":[-0.403679,51.657822],"type":"Point"}
}
