{
  "type": "Feature",
  "properties": {
    "iso:country":"GB",
    "wof:name":"TQ3 2PZ",
    "wof:placetype":"postalcode"
},
  "geometry": {"coordinates":[-3.58091228917012,50.44479791860945],"type":"Point"}
}