{
  "type": "Feature",
  "properties": {
    "iso:country":"GB",
    "wof:name":"BN3 5BP",
    "wof:placetype":"postalcode"
},
  "geometry": {"coordinates":[-0.17851883481298,50.8332327066988],"type":"Point"}
}