{
  "type": "Feature",
  "properties": {
    "date:inception_lower": "2010-11-01",
    "date:inception_upper": "2010-11-01",
    "iso:country": "GB",
    "wof:name": "MK18 1YA",
    "wof:placetype": "postalcode"
  },
  "geometry": {"coordinates":[-0.983446,52.009008],"type":"Point"}
}
