{
  "type": "Feature",
  "properties": {
    "iso:country":"GB",
    "wof:name":"PO21 3FG",
    "wof:placetype":"postalcode"
},
  "geometry": {"coordinates":[-0.69657294713013,50.78012314694678],"type":"Point"}
}