{
  "type": "Feature",
  "properties": {
    "iso:country":"GB",
    "wof:name":"DE21 4BD",
    "wof:placetype":"postalcode"
},
  "geometry": {"coordinates":[-1.46714720631637,52.93228572164198],"type":"Point"}
}