{
  "type": "Feature",
  "properties": {
    "date:inception_lower": "1992-08-01",
    "date:inception_upper": "1992-08-01",
    "iso:country": "GB",
    "wof:name": "DE21 4BD",
    "wof:placetype": "postalcode"
  },
  "geometry": {"coordinates":[-1.467216,52.932448],"type":"Point"}
}
