{
  "type": "Feature",
  "properties": {
    "iso:country":"GB",
    "wof:name":"NE65 0NZ",
    "wof:placetype":"postalcode"
},
  "geometry": {"coordinates":[-1.5891170565686,55.33200824200668],"type":"Point"}
}