{
  "type": "Feature",
  "properties": {
    "iso:country":"GB",
    "wof:name":"NE46 2BX",
    "wof:placetype":"postalcode"
},
  "geometry": {"coordinates":[-2.10996942406703,54.96422487690354],"type":"Point"}
}