{
  "type": "Feature",
  "properties": {
    "date:inception_lower": "1981-06-01",
    "date:inception_upper": "1981-06-01",
    "iso:country": "GB",
    "wof:name": "NE46 2BX",
    "wof:placetype": "postalcode"
  },
  "geometry": {"coordinates":[-2.109969,54.964225],"type":"Point"}
}
