{
  "type": "Feature",
  "properties": {
    "iso:country":"GB",
    "wof:name":"SL8 5NX",
    "wof:placetype":"postalcode"
},
  "geometry": {"coordinates":[-0.71756303039647,51.58365003196807],"type":"Point"}
}