{
  "type": "Feature",
  "properties": {
    "iso:country": "GB",
    "wof:name": "BS16 2AB",
    "wof:placetype": "postalcode"
  },
  "geometry": {"coordinates":[-2.541683,51.477017],"type":"Point"}
}
