{
  "type": "Feature",
  "properties": {
    "iso:country":"GB",
    "wof:name":"CO9 2BG",
    "wof:placetype":"postalcode"
},
  "geometry": {"coordinates":[0.64767031904319,51.95051976093346],"type":"Point"}
}