{
  "type": "Feature",
  "properties": {
    "iso:country":"GB",
    "wof:name":"DL5 6BH",
    "wof:placetype":"postalcode"
},
  "geometry": {"coordinates":[-1.56635032759775,54.60270111747175],"type":"Point"}
}