{
  "type": "Feature",
  "properties": {
    "iso:country": "GB",
    "wof:name": "OX29 8HT",
    "wof:placetype": "postalcode"
  },
  "geometry": {"coordinates":[-1.400404,51.813725],"type":"Point"}
}
