{
  "type": "Feature",
  "properties": {
    "date:inception_lower": "1980-01-01",
    "date:inception_upper": "1980-01-01",
    "iso:country": "GB",
    "wof:name": "NE65 0TJ",
    "wof:placetype": "postalcode"
  },
  "geometry": {"coordinates":[-1.612685,55.341394],"type":"Point"}
}
