{
  "type": "Feature",
  "properties": {
    "iso:country":"GB",
    "wof:name":"NE65 0TJ",
    "wof:placetype":"postalcode"
},
  "geometry": {"coordinates":[-1.61268550176119,55.34139437645317],"type":"Point"}
}