{
  "type": "Feature",
  "properties": {
    "iso:country": "GB",
    "wof:name": "KT15 2BU",
    "wof:placetype": "postalcode"
  },
  "geometry": {"coordinates":[-0.484987,51.364382],"type":"Point"}
}
