{
  "type": "Feature",
  "properties": {
    "iso:country":"GB",
    "wof:name":"BH3 7EL",
    "wof:placetype":"postalcode"
},
  "geometry": {"coordinates":[-1.8937618712777,50.73883943602912],"type":"Point"}
}