{
  "type": "Feature",
  "properties": {
    "date:inception_lower":"1991-01-01",
    "date:inception_upper":"1991-01-31",
    "iso:country":"GB",
    "wof:name":"BH3 7EL",
    "wof:placetype":"postalcode"
},
  "geometry": {"coordinates":[-1.893412,50.739062],"type":"Point"}
}