{
  "type": "Feature",
  "properties": {
    "iso:country":"GB",
    "wof:name":"SL5 7BB",
    "wof:placetype":"postalcode"
},
  "geometry": {"coordinates":[-0.65255829053285,51.405185396154],"type":"Point"}
}