{
  "type": "Feature",
  "properties": {
    "iso:country": "GB",
    "wof:name": "BH7 6LN",
    "wof:placetype": "postalcode"
  },
  "geometry": {"coordinates":[-1.826302,50.732185],"type":"Point"}
}
