{
  "type": "Feature",
  "properties": {
    "date:inception_lower": "1998-12-01",
    "date:inception_upper": "1998-12-01",
    "iso:country": "GB",
    "wof:name": "B24 0GB",
    "wof:placetype": "postalcode"
  },
  "geometry": {"coordinates":[-1.81581,52.520292],"type":"Point"}
}
