{
  "type": "Feature",
  "properties": {
    "iso:country": "GB",
    "wof:name": "CH66 2WW",
    "wof:placetype": "postalcode"
  },
  "geometry": {"coordinates":[-2.923444,53.265192],"type":"Point"}
}
