{
  "type": "Feature",
  "properties": {
    "iso:country":"GB",
    "wof:name":"CF32 8RJ",
    "wof:placetype":"postalcode"
},
  "geometry": {"coordinates":[-3.55735198005452,51.57206263831579],"type":"Point"}
}