{
  "type": "Feature",
  "properties": {
    "iso:country": "GB",
    "wof:name": "CF32 8RJ",
    "wof:placetype": "postalcode"
  },
  "geometry": {"coordinates":[-3.557352,51.572063],"type":"Point"}
}
