{
  "type": "Feature",
  "properties": {
    "iso:country": "GB",
    "wof:name": "GL52 3HB",
    "wof:placetype": "postalcode"
  },
  "geometry": {"coordinates":[-2.05771,51.910973],"type":"Point"}
}
