{
  "type": "Feature",
  "properties": {
    "iso:country":"GB",
    "wof:name":"B42 2BY",
    "wof:placetype":"postalcode"
},
  "geometry": {"coordinates":[-1.92070093237919,52.54317089241991],"type":"Point"}
}