{
  "type": "Feature",
  "properties": {
    "iso:country":"GB",
    "wof:name":"BS16 9RZ",
    "wof:placetype":"postalcode"
},
  "geometry": {"coordinates":[-2.43152329369954,51.47926390719756],"type":"Point"}
}