{
  "type": "Feature",
  "properties": {
    "date:inception_lower":"1997-12-01",
    "date:inception_upper":"1997-12-31",
    "iso:country":"GB",
    "wof:name":"BS16 9RZ",
    "wof:placetype":"postalcode"
},
  "geometry": {"coordinates":[-2.431523,51.479264],"type":"Point"}
}