{
  "type": "Feature",
  "properties": {
    "iso:country": "GB",
    "wof:name": "BS16 9RZ",
    "wof:placetype": "postalcode"
  },
  "geometry": {"coordinates":[-2.431523,51.479264],"type":"Point"}
}
