{
  "type": "Feature",
  "properties": {
    "iso:country":"GB",
    "wof:name":"SN10 1SW",
    "wof:placetype":"postalcode"
},
  "geometry": {"coordinates":[-2.07928409054089,51.32482749646486],"type":"Point"}
}