{
  "type": "Feature",
  "properties": {
    "iso:country":"GB",
    "wof:name":"KT15 2RF",
    "wof:placetype":"postalcode"
},
  "geometry": {"coordinates":[-0.47439656346844,51.37486475482317],"type":"Point"}
}