{
  "type": "Feature",
  "properties": {
    "iso:country": "GB",
    "wof:name": "KT15 2RF",
    "wof:placetype": "postalcode"
  },
  "geometry": {"coordinates":[-0.474397,51.374865],"type":"Point"}
}
