{
  "type": "Feature",
  "properties": {
    "date:inception_lower":"1980-01-01",
    "date:inception_upper":"1980-01-31",
    "iso:country":"GB",
    "wof:name":"PE33 9QA",
    "wof:placetype":"postalcode"
},
  "geometry": {"coordinates":[0.552935,52.592844],"type":"Point"}
}