{
  "type": "Feature",
  "properties": {
    "iso:country":"GB",
    "wof:name":"W1J 8NL",
    "wof:placetype":"postalcode"
},
  "geometry": {"coordinates":[-0.14276698263959,51.5074392837131],"type":"Point"}
}