{
  "type": "Feature",
  "properties": {
    "iso:country":"GB",
    "wof:name":"PL24 2RF",
    "wof:placetype":"postalcode"
},
  "geometry": {"coordinates":[-4.70756964702501,50.36788654782601],"type":"Point"}
}