{
  "type": "Feature",
  "properties": {
    "date:inception_lower": "2000-06-01",
    "date:inception_upper": "2000-06-01",
    "iso:country": "GB",
    "wof:name": "PL24 2RF",
    "wof:placetype": "postalcode"
  },
  "geometry": {"coordinates":[-4.70757,50.367887],"type":"Point"}
}
