{
  "type": "Feature",
  "properties": {
    "iso:country":"GB",
    "wof:name":"W4 5JU",
    "wof:placetype":"postalcode"
},
  "geometry": {"coordinates":[-0.26141387177061,51.50115590153608],"type":"Point"}
}