{
  "type": "Feature",
  "properties": {
    "iso:country":"GB",
    "wof:name":"WR7 4JL",
    "wof:placetype":"postalcode"
},
  "geometry": {"coordinates":[-1.98871549325327,52.20979829655068],"type":"Point"}
}