{
  "type": "Feature",
  "properties": {
    "iso:country": "GB",
    "wof:name": "WR7 4JL",
    "wof:placetype": "postalcode"
  },
  "geometry": {"coordinates":[-1.988715,52.209798],"type":"Point"}
}
