{
  "type": "Feature",
  "properties": {
    "iso:country": "GB",
    "wof:name": "FY1 2HL",
    "wof:placetype": "postalcode"
  },
  "geometry": {"coordinates":[-3.053143,53.82836],"type":"Point"}
}
