{
  "type": "Feature",
  "properties": {
    "iso:country":"GB",
    "wof:name":"FY1 2HL",
    "wof:placetype":"postalcode"
},
  "geometry": {"coordinates":[-3.05314299481394,53.82835993758084],"type":"Point"}
}