{
  "type": "Feature",
  "properties": {
    "date:inception_lower": "1980-01-01",
    "date:inception_upper": "1980-01-01",
    "iso:country": "GB",
    "wof:name": "DD8 5DY",
    "wof:placetype": "postalcode"
  },
  "geometry": {"coordinates":[-3.005453,56.668495],"type":"Point"}
}
