{
  "type": "Feature",
  "properties": {
    "iso:country":"GB",
    "wof:name":"CH4 0NH",
    "wof:placetype":"postalcode"
},
  "geometry": {"coordinates":[-3.04048226606716,53.15284137585132],"type":"Point"}
}