{
  "type": "Feature",
  "properties": {
    "iso:country": "GB",
    "wof:name": "DN10 6ED",
    "wof:placetype": "postalcode"
  },
  "geometry": {"coordinates":[-0.962889,53.445957],"type":"Point"}
}
