{
  "type": "Feature",
  "properties": {
    "iso:country":"GB",
    "wof:name":"DN10 6ED",
    "wof:placetype":"postalcode"
},
  "geometry": {"coordinates":[-0.96288900063131,53.44595692569875],"type":"Point"}
}