{
  "type": "Feature",
  "properties": {
    "date:inception_lower": "1980-01-01",
    "date:inception_upper": "1980-01-01",
    "iso:country": "GB",
    "wof:name": "DN10 6ED",
    "wof:placetype": "postalcode"
  },
  "geometry": {"coordinates":[-0.962889,53.445957],"type":"Point"}
}
