{
  "type": "Feature",
  "properties": {
    "iso:country": "GB",
    "wof:name": "LE15 6AN",
    "wof:placetype": "postalcode"
  },
  "geometry": {"coordinates":[-0.727313,52.669515],"type":"Point"}
}
