{
  "type": "Feature",
  "properties": {
    "iso:country":"GB",
    "wof:name":"FK2 9EA",
    "wof:placetype":"postalcode"
},
  "geometry": {"coordinates":[-3.75822158315506,56.00274573764729],"type":"Point"}
}