{
  "type": "Feature",
  "properties": {
    "date:inception_lower":"1991-07-01",
    "date:inception_upper":"1991-07-31",
    "iso:country":"GB",
    "wof:name":"EH47 0JU",
    "wof:placetype":"postalcode"
},
  "geometry": {"coordinates":[-3.671733,55.867476],"type":"Point"}
}