{
  "type": "Feature",
  "properties": {
    "date:inception_lower": "2023-06-01",
    "date:inception_upper": "2023-06-01",
    "iso:country": "GB",
    "wof:name": "IV15 9AS",
    "wof:placetype": "postalcode"
  },
  "geometry": {"coordinates":[-4.441291,57.606942],"type":"Point"}
}
