{
  "type": "Feature",
  "properties": {
    "iso:country":"GB",
    "wof:name":"WD3 5TE",
    "wof:placetype":"postalcode"
},
  "geometry": {"coordinates":[-0.49700533627824,51.65837314390205],"type":"Point"}
}