{
  "type": "Feature",
  "properties": {
    "iso:country": "GB",
    "wof:name": "TR6 0EN",
    "wof:placetype": "postalcode"
  },
  "geometry": {"coordinates":[-5.170703,50.337318],"type":"Point"}
}
