{
  "type": "Feature",
  "properties": {
    "date:inception_lower":"1999-06-01",
    "date:inception_upper":"1999-06-30",
    "iso:country":"GB",
    "wof:name":"YO25 9SE",
    "wof:placetype":"postalcode"
},
  "geometry": {"coordinates":[-0.666707,54.020172],"type":"Point"}
}