{
  "type": "Feature",
  "properties": {
    "iso:country":"GB",
    "wof:name":"BA14 8RE",
    "wof:placetype":"postalcode"
},
  "geometry": {"coordinates":[-2.21104910380113,51.32311731863663],"type":"Point"}
}