{
  "type": "Feature",
  "properties": {
    "iso:country":"GB",
    "wof:name":"EH10 6UW",
    "wof:placetype":"postalcode"
},
  "geometry": {"coordinates":[-3.20081739431772,55.90744056244107],"type":"Point"}
}