{
  "type": "Feature",
  "properties": {
    "date:inception_lower": "1980-01-01",
    "date:inception_upper": "1980-01-01",
    "iso:country": "GB",
    "wof:name": "G76 0AS",
    "wof:placetype": "postalcode"
  },
  "geometry": {"coordinates":[-4.275297,55.738766],"type":"Point"}
}
