{
  "type": "Feature",
  "properties": {
    "iso:country": "GB",
    "wof:name": "G76 0AS",
    "wof:placetype": "postalcode"
  },
  "geometry": {"coordinates":[-4.275297,55.738766],"type":"Point"}
}
