{
  "type": "Feature",
  "properties": {
    "iso:country":"GB",
    "wof:name":"G76 0AS",
    "wof:placetype":"postalcode"
},
  "geometry": {"coordinates":[-4.27531082348404,55.73877072348165],"type":"Point"}
}