{
  "type": "Feature",
  "properties": {
    "iso:country":"GB",
    "wof:name":"NW8 6BN",
    "wof:placetype":"postalcode"
},
  "geometry": {"coordinates":[-0.17192244120116,51.53398447379111],"type":"Point"}
}