{
  "type": "Feature",
  "properties": {
    "iso:country":"GB",
    "wof:name":"CF48 2BA",
    "wof:placetype":"postalcode"
},
  "geometry": {"coordinates":[-3.350177867738,51.77325793174531],"type":"Point"}
}