{
  "type": "Feature",
  "properties": {
    "iso:country":"GB",
    "wof:name":"TF3 5GS",
    "wof:placetype":"postalcode"
},
  "geometry": {"coordinates":[-2.48001162515617,52.68023508694565],"type":"Point"}
}