{
  "type": "Feature",
  "properties": {
    "date:inception_lower": "2013-12-01",
    "date:inception_upper": "2013-12-01",
    "iso:country": "GB",
    "wof:name": "TF3 5GS",
    "wof:placetype": "postalcode"
  },
  "geometry": {"coordinates":[-2.480012,52.680235],"type":"Point"}
}
