{
  "type": "Feature",
  "properties": {
    "iso:country":"GB",
    "wof:name":"NE13 6PG",
    "wof:placetype":"postalcode"
},
  "geometry": {"coordinates":[-1.62173547922645,55.04280204521631],"type":"Point"}
}