{
  "type": "Feature",
  "properties": {
    "iso:country":"GB",
    "wof:name":"SE15 3AX",
    "wof:placetype":"postalcode"
},
  "geometry": {"coordinates":[-0.05001371180357,51.45801191136533],"type":"Point"}
}