{
  "type": "Feature",
  "properties": {
    "iso:country": "GB",
    "wof:name": "PA2 6RZ",
    "wof:placetype": "postalcode"
  },
  "geometry": {"coordinates":[-4.413875,55.832539],"type":"Point"}
}
