{
  "type": "Feature",
  "properties": {
    "date:inception_lower": "1980-01-01",
    "date:inception_upper": "1980-01-01",
    "iso:country": "GB",
    "wof:name": "PA2 6RZ",
    "wof:placetype": "postalcode"
  },
  "geometry": {"coordinates":[-4.413875,55.832539],"type":"Point"}
}
