{
  "type": "Feature",
  "properties": {
    "date:inception_lower":"1994-05-01",
    "date:inception_upper":"1994-05-31",
    "iso:country":"GB",
    "wof:name":"M7 3NB",
    "wof:placetype":"postalcode"
},
  "geometry": {"coordinates":[-2.269172,53.514069],"type":"Point"}
}