{
  "type": "Feature",
  "properties": {
    "iso:country": "GB",
    "wof:name": "RH6 7JX",
    "wof:placetype": "postalcode"
  },
  "geometry": {"coordinates":[-0.162618,51.172971],"type":"Point"}
}
