{
  "type": "Feature",
  "properties": {
    "date:inception_lower": "1980-01-01",
    "date:inception_upper": "1980-01-01",
    "iso:country": "GB",
    "wof:name": "CA1 1EA",
    "wof:placetype": "postalcode"
  },
  "geometry": {"coordinates":[-2.927333,54.8942],"type":"Point"}
}
