{
  "type": "Feature",
  "properties": {
    "iso:country":"GB",
    "wof:name":"CA1 1EA",
    "wof:placetype":"postalcode"
},
  "geometry": {"coordinates":[-2.92733317647102,54.89419999579806],"type":"Point"}
}