{
  "type": "Feature",
  "properties": {
    "iso:country":"GB",
    "wof:name":"RG6 7JX",
    "wof:placetype":"postalcode"
},
  "geometry": {"coordinates":[-0.91579474094037,51.43772402093538],"type":"Point"}
}