{
  "type": "Feature",
  "properties": {
    "iso:country":"GB",
    "wof:name":"NW2 4NL",
    "wof:placetype":"postalcode"
},
  "geometry": {"coordinates":[-0.22154736106438,51.54998036988899],"type":"Point"}
}