{
  "type": "Feature",
  "properties": {
    "iso:country":"GB",
    "wof:name":"GL54 2HN",
    "wof:placetype":"postalcode"
},
  "geometry": {"coordinates":[-1.75796847333243,51.89421369827063],"type":"Point"}
}