{
  "type": "Feature",
  "properties": {
    "iso:country": "GB",
    "wof:name": "WV7 3AN",
    "wof:placetype": "postalcode"
  },
  "geometry": {"coordinates":[-2.23764,52.620343],"type":"Point"}
}
