{
  "type": "Feature",
  "properties": {
    "iso:country":"GB",
    "wof:name":"WV7 3AN",
    "wof:placetype":"postalcode"
},
  "geometry": {"coordinates":[-2.23763956771592,52.62034262883606],"type":"Point"}
}