{
  "type": "Feature",
  "properties": {
    "iso:country":"GB",
    "wof:name":"LN1 1SD",
    "wof:placetype":"postalcode"
},
  "geometry": {"coordinates":[-0.5575950169725,53.23421157734747],"type":"Point"}
}