{
  "type": "Feature",
  "properties": {
    "iso:country":"GB",
    "wof:name":"NG23 6EW",
    "wof:placetype":"postalcode"
},
  "geometry": {"coordinates":[-0.81306789611943,53.125685875222],"type":"Point"}
}