{
  "type": "Feature",
  "properties": {
    "iso:country":"GB",
    "wof:name":"AB53 4LL",
    "wof:placetype":"postalcode"
},
  "geometry": {"coordinates":[-2.5746743432074,57.54073592419159],"type":"Point"}
}