{
  "type": "Feature",
  "properties": {
    "iso:country": "GB",
    "wof:name": "YO23 1HH",
    "wof:placetype": "postalcode"
  },
  "geometry": {"coordinates":[-1.089169,53.944892],"type":"Point"}
}
