{
  "type": "Feature",
  "properties": {
    "iso:country":"GB",
    "wof:name":"YO23 1HH",
    "wof:placetype":"postalcode"
},
  "geometry": {"coordinates":[-1.08916916677054,53.9448922654256],"type":"Point"}
}