{
  "type": "Feature",
  "properties": {
    "iso:country": "GB",
    "wof:name": "EH22 4JL",
    "wof:placetype": "postalcode"
  },
  "geometry": {"coordinates":[-3.061449,55.869095],"type":"Point"}
}
