{
  "type": "Feature",
  "properties": {
    "iso:country":"GB",
    "wof:name":"OL11 2QQ",
    "wof:placetype":"postalcode"
},
  "geometry": {"coordinates":[-2.1726982310304,53.59401930611511],"type":"Point"}
}