{
  "type": "Feature",
  "properties": {
    "iso:country": "GB",
    "wof:name": "N11 1NR",
    "wof:placetype": "postalcode"
  },
  "geometry": {"coordinates":[-0.144534,51.618155],"type":"Point"}
}
