{
  "type": "Feature",
  "properties": {
    "iso:country":"GB",
    "wof:name":"TA20 2PW",
    "wof:placetype":"postalcode"
},
  "geometry": {"coordinates":[-2.9523063891672,50.84104009784985],"type":"Point"}
}