{
  "type": "Feature",
  "properties": {
    "iso:country":"GB",
    "wof:name":"KY7 5RE",
    "wof:placetype":"postalcode"
},
  "geometry": {"coordinates":[-3.14971340895085,56.19790131209491],"type":"Point"}
}