{
  "type": "Feature",
  "properties": {
    "iso:country":"GB",
    "wof:name":"M7 4DS",
    "wof:placetype":"postalcode"
},
  "geometry": {"coordinates":[-2.2470052702065,53.50649506681764],"type":"Point"}
}