{
  "type": "Feature",
  "properties": {
    "date:inception_lower":"1980-01-01",
    "date:inception_upper":"1980-01-31",
    "iso:country":"GB",
    "wof:name":"KA26 9RL",
    "wof:placetype":"postalcode"
},
  "geometry": {"coordinates":[-4.711575,55.275813],"type":"Point"}
}