{
  "type": "Feature",
  "properties": {
    "iso:country": "GB",
    "wof:name": "KA26 9RL",
    "wof:placetype": "postalcode"
  },
  "geometry": {"coordinates":[-4.711575,55.275813],"type":"Point"}
}
