{
  "type": "Feature",
  "properties": {
    "iso:country":"GB",
    "wof:name":"KA26 9RL",
    "wof:placetype":"postalcode"
},
  "geometry": {"coordinates":[-4.71157527304663,55.27581291012323],"type":"Point"}
}