{
  "type": "Feature",
  "properties": {
    "date:inception_lower":"1980-01-01",
    "date:inception_upper":"1980-01-31",
    "iso:country":"GB",
    "wof:name":"GL53 8AZ",
    "wof:placetype":"postalcode"
},
  "geometry": {"coordinates":[-2.052307,51.884325],"type":"Point"}
}