{
  "type": "Feature",
  "properties": {
    "iso:country":"GB",
    "wof:name":"GL53 8AZ",
    "wof:placetype":"postalcode"
},
  "geometry": {"coordinates":[-2.0523146434772,51.88431757471368],"type":"Point"}
}