{
  "type": "Feature",
  "properties": {
    "iso:country":"GB",
    "wof:name":"SN14 6QU",
    "wof:placetype":"postalcode"
},
  "geometry": {"coordinates":[-2.13824225304111,51.46873759006076],"type":"Point"}
}