{
  "type": "Feature",
  "properties": {
    "iso:country":"GB",
    "wof:name":"LE15 9BN",
    "wof:placetype":"postalcode"
},
  "geometry": {"coordinates":[-0.67743393205585,52.59492399714798],"type":"Point"}
}