{
  "type": "Feature",
  "properties": {
    "iso:country": "GB",
    "wof:name": "LE15 9BN",
    "wof:placetype": "postalcode"
  },
  "geometry": {"coordinates":[-0.677434,52.594924],"type":"Point"}
}
