{
  "type": "Feature",
  "properties": {
    "iso:country":"GB",
    "wof:name":"CB25 9LD",
    "wof:placetype":"postalcode"
},
  "geometry": {"coordinates":[0.18806557182603,52.26933568026973],"type":"Point"}
}