{
  "type": "Feature",
  "properties": {
    "iso:country":"GB",
    "wof:name":"SE10 9NR",
    "wof:placetype":"postalcode"
},
  "geometry": {"coordinates":[-0.00305903167777,51.48436151622376],"type":"Point"}
}