{
  "type": "Feature",
  "properties": {
    "iso:country": "GB",
    "wof:name": "RH4 1RL",
    "wof:placetype": "postalcode"
  },
  "geometry": {"coordinates":[-0.327336,51.234471],"type":"Point"}
}
