{
  "type": "Feature",
  "properties": {
    "date:inception_lower":"1980-01-01",
    "date:inception_upper":"1980-01-31",
    "iso:country":"GB",
    "wof:name":"SK9 4EB",
    "wof:placetype":"postalcode"
},
  "geometry": {"coordinates":[-2.236317,53.336103],"type":"Point"}
}