{
  "type": "Feature",
  "properties": {
    "iso:country": "GB",
    "wof:name": "GU7 1XY",
    "wof:placetype": "postalcode"
  },
  "geometry": {"coordinates":[-0.621397,51.177397],"type":"Point"}
}
