{
  "type": "Feature",
  "properties": {
    "date:inception_lower": "2003-07-01",
    "date:inception_upper": "2003-07-01",
    "iso:country": "GB",
    "wof:name": "LE3 9RY",
    "wof:placetype": "postalcode"
  },
  "geometry": {"coordinates":[-1.177665,52.658427],"type":"Point"}
}
