{
  "type": "Feature",
  "properties": {
    "iso:country":"GB",
    "wof:name":"LE3 9RY",
    "wof:placetype":"postalcode"
},
  "geometry": {"coordinates":[-1.1776648691084,52.65842682201087],"type":"Point"}
}