{
  "type": "Feature",
  "properties": {
    "iso:country": "GB",
    "wof:name": "DT6 4JZ",
    "wof:placetype": "postalcode"
  },
  "geometry": {"coordinates":[-2.742906,50.737435],"type":"Point"}
}
