{
  "type": "Feature",
  "properties": {
    "iso:country":"GB",
    "wof:name":"DT6 4JZ",
    "wof:placetype":"postalcode"
},
  "geometry": {"coordinates":[-2.74292065796458,50.73746360506765],"type":"Point"}
}