{
  "type": "Feature",
  "properties": {
    "iso:country": "GB",
    "wof:name": "GL1 5AX",
    "wof:placetype": "postalcode"
  },
  "geometry": {"coordinates":[-2.246197,51.857161],"type":"Point"}
}
