{
  "type": "Feature",
  "properties": {
    "date:inception_lower": "1980-01-01",
    "date:inception_upper": "1980-01-01",
    "iso:country": "GB",
    "wof:name": "WV10 0JP",
    "wof:placetype": "postalcode"
  },
  "geometry": {"coordinates":[-2.121112,52.5913],"type":"Point"}
}
