{
  "type": "Feature",
  "properties": {
    "iso:country":"GB",
    "wof:name":"WV10 0JP",
    "wof:placetype":"postalcode"
},
  "geometry": {"coordinates":[-2.11986301994794,52.59114201877949],"type":"Point"}
}