{
  "type": "Feature",
  "properties": {
    "iso:country":"GB",
    "wof:name":"NG34 7NU",
    "wof:placetype":"postalcode"
},
  "geometry": {"coordinates":[-0.42492545874707,52.99203345972625],"type":"Point"}
}