{
  "type": "Feature",
  "properties": {
    "iso:country":"GB",
    "wof:name":"SG4 9JW",
    "wof:placetype":"postalcode"
},
  "geometry": {"coordinates":[-0.27050511696337,51.94280995419016],"type":"Point"}
}