{
  "type": "Feature",
  "properties": {
    "iso:country": "GB",
    "wof:name": "BN7 1SZ",
    "wof:placetype": "postalcode"
  },
  "geometry": {"coordinates":[-0.000468,50.873913],"type":"Point"}
}
