{
  "type": "Feature",
  "properties": {
    "iso:country":"GB",
    "wof:name":"S2 1JW",
    "wof:placetype":"postalcode"
},
  "geometry": {"coordinates":[-1.42544558865271,53.36492397191059],"type":"Point"}
}