{
  "type": "Feature",
  "properties": {
    "date:inception_lower": "2019-12-01",
    "date:inception_upper": "2019-12-01",
    "iso:country": "GB",
    "wof:name": "PL19 8FR",
    "wof:placetype": "postalcode"
  },
  "geometry": {"coordinates":[-4.15894,50.549659],"type":"Point"}
}
