{
  "type": "Feature",
  "properties": {
    "iso:country":"GB",
    "wof:name":"NG6 0EG",
    "wof:placetype":"postalcode"
},
  "geometry": {"coordinates":[-1.17696321916317,52.98953889735363],"type":"Point"}
}