{
  "type": "Feature",
  "properties": {
    "date:inception_lower": "1980-01-01",
    "date:inception_upper": "1980-01-01",
    "iso:country": "GB",
    "wof:name": "NG6 0EG",
    "wof:placetype": "postalcode"
  },
  "geometry": {"coordinates":[-1.176963,52.989539],"type":"Point"}
}
