{
  "type": "Feature",
  "properties": {
    "iso:country": "GB",
    "wof:name": "WF7 7GD",
    "wof:placetype": "postalcode"
  },
  "geometry": {"coordinates":[-1.355112,53.642635],"type":"Point"}
}
