{
  "type": "Feature",
  "properties": {
    "iso:country":"GB",
    "wof:name":"RH20 1SG",
    "wof:placetype":"postalcode"
},
  "geometry": {"coordinates":[-0.51534656045213,50.95738675532162],"type":"Point"}
}