{
  "type": "Feature",
  "properties": {
    "iso:country": "GB",
    "wof:name": "RH20 1SG",
    "wof:placetype": "postalcode"
  },
  "geometry": {"coordinates":[-0.515347,50.957387],"type":"Point"}
}
