{
  "type": "Feature",
  "properties": {
    "iso:country":"GB",
    "wof:name":"DL15 9TQ",
    "wof:placetype":"postalcode"
},
  "geometry": {"coordinates":[-1.74885296985796,54.72904835380575],"type":"Point"}
}