{
  "type": "Feature",
  "properties": {
    "date:inception_lower":"1980-01-01",
    "date:inception_upper":"1980-01-31",
    "iso:country":"GB",
    "wof:name":"DL15 9TQ",
    "wof:placetype":"postalcode"
},
  "geometry": {"coordinates":[-1.748853,54.729048],"type":"Point"}
}