{
  "type": "Feature",
  "properties": {
    "date:inception_lower": "1990-07-01",
    "date:inception_upper": "1990-07-01",
    "iso:country": "GB",
    "wof:name": "ST5 1UP",
    "wof:placetype": "postalcode"
  },
  "geometry": {"coordinates":[-2.223716,53.011312],"type":"Point"}
}
