{
  "type": "Feature",
  "properties": {
    "iso:country":"GB",
    "wof:name":"ST5 1UP",
    "wof:placetype":"postalcode"
},
  "geometry": {"coordinates":[-2.22368686630639,53.01124068754158],"type":"Point"}
}