{
  "type": "Feature",
  "properties": {
    "iso:country":"GB",
    "wof:name":"BS3 4NT",
    "wof:placetype":"postalcode"
},
  "geometry": {"coordinates":[-2.59702721465727,51.43794053463796],"type":"Point"}
}