{
  "type": "Feature",
  "properties": {
    "iso:country": "GB",
    "wof:name": "PE7 8QP",
    "wof:placetype": "postalcode"
  },
  "geometry": {"coordinates":[-0.25982,52.529285],"type":"Point"}
}
