{
  "type": "Feature",
  "properties": {
    "iso:country":"GB",
    "wof:name":"WN6 8DU",
    "wof:placetype":"postalcode"
},
  "geometry": {"coordinates":[-2.71551347999003,53.57729835451785],"type":"Point"}
}