{
  "type": "Feature",
  "properties": {
    "date:inception_lower":"1990-02-01",
    "date:inception_upper":"1990-02-28",
    "iso:country":"GB",
    "wof:name":"WN6 8DU",
    "wof:placetype":"postalcode"
},
  "geometry": {"coordinates":[-2.715513,53.577298],"type":"Point"}
}