{
  "type": "Feature",
  "properties": {
    "iso:country": "GB",
    "wof:name": "SK14 2QY",
    "wof:placetype": "postalcode"
  },
  "geometry": {"coordinates":[-2.076921,53.451131],"type":"Point"}
}
