{
  "type": "Feature",
  "properties": {
    "iso:country":"GB",
    "wof:name":"NR8 6HU",
    "wof:placetype":"postalcode"
},
  "geometry": {"coordinates":[1.18206429833471,52.68066434985176],"type":"Point"}
}