{
  "type": "Feature",
  "properties": {
    "iso:country":"GB",
    "wof:name":"HD5 9NN",
    "wof:placetype":"postalcode"
},
  "geometry": {"coordinates":[-1.76437094305065,53.65162633687747],"type":"Point"}
}