{
  "type": "Feature",
  "properties": {
    "iso:country": "GB",
    "wof:name": "TN4 0BU",
    "wof:placetype": "postalcode"
  },
  "geometry": {"coordinates":[0.267439,51.152357],"type":"Point"}
}
