{
  "type": "Feature",
  "properties": {
    "iso:country":"GB",
    "wof:name":"TN4 0BU",
    "wof:placetype":"postalcode"
},
  "geometry": {"coordinates":[0.26743899664778,51.15235652342442],"type":"Point"}
}