{
  "type": "Feature",
  "properties": {
    "date:inception_lower": "1983-07-01",
    "date:inception_upper": "1983-07-01",
    "iso:country": "GB",
    "wof:name": "NG3 7DF",
    "wof:placetype": "postalcode"
  },
  "geometry": {"coordinates":[-1.116622,52.965086],"type":"Point"}
}
