{
  "type": "Feature",
  "properties": {
    "date:inception_lower": "2021-12-01",
    "date:inception_upper": "2021-12-01",
    "iso:country": "GB",
    "wof:name": "ML11 8JT",
    "wof:placetype": "postalcode"
  },
  "geometry": {"coordinates":[-3.623941,55.69076],"type":"Point"}
}
