{
  "type": "Feature",
  "properties": {
    "iso:country":"GB",
    "wof:name":"G22 6DN",
    "wof:placetype":"postalcode"
},
  "geometry": {"coordinates":[-4.24286897869023,55.88981804618957],"type":"Point"}
}