{
  "type": "Feature",
  "properties": {
    "date:inception_lower":"2019-03-01",
    "date:inception_upper":"2019-03-31",
    "iso:country":"GB",
    "wof:name":"NR3 2RH",
    "wof:placetype":"postalcode"
},
  "geometry": {"coordinates":[1.276317,52.653199],"type":"Point"}
}