{
  "type": "Feature",
  "properties": {
    "date:inception_lower":"1980-01-01",
    "date:inception_upper":"1980-01-31",
    "iso:country":"GB",
    "wof:name":"SE26 4BU",
    "wof:placetype":"postalcode"
},
  "geometry": {"coordinates":[-0.061046,51.436478],"type":"Point"}
}