{
  "type": "Feature",
  "properties": {
    "iso:country": "GB",
    "wof:name": "SE26 4BU",
    "wof:placetype": "postalcode"
  },
  "geometry": {"coordinates":[-0.061046,51.436478],"type":"Point"}
}
