{
  "type": "Feature",
  "properties": {
    "iso:country":"GB",
    "wof:name":"CO1 2AW",
    "wof:placetype":"postalcode"
},
  "geometry": {"coordinates":[0.9080414890471,51.88389091063606],"type":"Point"}
}