{
  "type": "Feature",
  "properties": {
    "iso:country":"GB",
    "wof:name":"CF32 9TB",
    "wof:placetype":"postalcode"
},
  "geometry": {"coordinates":[-3.57515508811978,51.545657830489],"type":"Point"}
}