{
  "type": "Feature",
  "properties": {
    "iso:country":"GB",
    "wof:name":"BS10 5RJ",
    "wof:placetype":"postalcode"
},
  "geometry": {"coordinates":[-2.59488564987502,51.50338342435462],"type":"Point"}
}