{
  "type": "Feature",
  "properties": {
    "date:inception_lower": "2011-12-01",
    "date:inception_upper": "2011-12-01",
    "iso:country": "GB",
    "wof:name": "BS36 2FJ",
    "wof:placetype": "postalcode"
  },
  "geometry": {"coordinates":[-2.481717,51.526732],"type":"Point"}
}
