{
  "type": "Feature",
  "properties": {
    "iso:country":"GB",
    "wof:name":"LL19 7TP",
    "wof:placetype":"postalcode"
},
  "geometry": {"coordinates":[-3.41579919499312,53.33745419153824],"type":"Point"}
}