{
  "type": "Feature",
  "properties": {
    "iso:country":"GB",
    "wof:name":"AB51 7JE",
    "wof:placetype":"postalcode"
},
  "geometry": {"coordinates":[-2.54617850222426,57.26136216955828],"type":"Point"}
}