{
  "type": "Feature",
  "properties": {
    "date:inception_lower": "1996-06-01",
    "date:inception_upper": "1996-06-01",
    "iso:country": "GB",
    "wof:name": "AB51 7JE",
    "wof:placetype": "postalcode"
  },
  "geometry": {"coordinates":[-2.546015,57.26116],"type":"Point"}
}
