{
  "type": "Feature",
  "properties": {
    "iso:country":"GB",
    "wof:name":"NP26 3GU",
    "wof:placetype":"postalcode"
},
  "geometry": {"coordinates":[-2.83244538175502,51.58131547240184],"type":"Point"}
}