{
  "type": "Feature",
  "properties": {
    "date:inception_lower":"2000-06-01",
    "date:inception_upper":"2000-06-30",
    "iso:country":"GB",
    "wof:name":"NP26 3GU",
    "wof:placetype":"postalcode"
},
  "geometry": {"coordinates":[-2.832445,51.581315],"type":"Point"}
}