{
  "type": "Feature",
  "properties": {
    "iso:country":"GB",
    "wof:name":"LS10 4NN",
    "wof:placetype":"postalcode"
},
  "geometry": {"coordinates":[-1.55666677690917,53.74633064977444],"type":"Point"}
}