{
  "type": "Feature",
  "properties": {
    "date:inception_lower":"1980-01-01",
    "date:inception_upper":"1980-01-31",
    "iso:country":"GB",
    "wof:name":"B30 3PL",
    "wof:placetype":"postalcode"
},
  "geometry": {"coordinates":[-1.918721,52.408877],"type":"Point"}
}