{
  "type": "Feature",
  "properties": {
    "date:inception_lower": "1980-01-01",
    "date:inception_upper": "1980-01-01",
    "iso:country": "GB",
    "wof:name": "EH4 6DA",
    "wof:placetype": "postalcode"
  },
  "geometry": {"coordinates":[-3.307298,55.962786],"type":"Point"}
}
