{
  "type": "Feature",
  "properties": {
    "iso:country":"GB",
    "wof:name":"EH4 6DA",
    "wof:placetype":"postalcode"
},
  "geometry": {"coordinates":[-3.30729850371527,55.96278585464555],"type":"Point"}
}