{
  "type": "Feature",
  "properties": {
    "date:inception_lower": "1980-01-01",
    "date:inception_upper": "1980-01-01",
    "iso:country": "GB",
    "wof:name": "CW9 7EW",
    "wof:placetype": "postalcode"
  },
  "geometry": {"coordinates":[-2.48521,53.253651],"type":"Point"}
}
