{
  "type": "Feature",
  "properties": {
    "iso:country":"GB",
    "wof:name":"CW9 7EW",
    "wof:placetype":"postalcode"
},
  "geometry": {"coordinates":[-2.48521041882273,53.25365055188692],"type":"Point"}
}