{
  "type": "Feature",
  "properties": {
    "iso:country":"GB",
    "wof:name":"SG8 7RU",
    "wof:placetype":"postalcode"
},
  "geometry": {"coordinates":[0.07382508827438,52.08685767623777],"type":"Point"}
}