{
  "type": "Feature",
  "properties": {
    "iso:country": "GB",
    "wof:name": "SG8 7RU",
    "wof:placetype": "postalcode"
  },
  "geometry": {"coordinates":[0.073812,52.0866],"type":"Point"}
}
