{
  "type": "Feature",
  "properties": {
    "iso:country":"GB",
    "wof:name":"NR29 3ER",
    "wof:placetype":"postalcode"
},
  "geometry": {"coordinates":[1.59537449141177,52.63645603494322],"type":"Point"}
}