{
  "type": "Feature",
  "properties": {
    "iso:country": "GB",
    "wof:name": "HD9 6QH",
    "wof:placetype": "postalcode"
  },
  "geometry": {"coordinates":[-1.782525,53.607742],"type":"Point"}
}
