{
  "type": "Feature",
  "properties": {
    "date:inception_lower": "2017-01-01",
    "date:inception_upper": "2017-01-01",
    "iso:country": "GB",
    "wof:name": "HR3 5FG",
    "wof:placetype": "postalcode"
  },
  "geometry": {"coordinates":[-3.090965,52.044452],"type":"Point"}
}
