{
  "type": "Feature",
  "properties": {
    "date:inception_lower": "1980-01-01",
    "date:inception_upper": "1980-01-01",
    "iso:country": "GB",
    "wof:name": "SR4 0QJ",
    "wof:placetype": "postalcode"
  },
  "geometry": {"coordinates":[-1.450328,54.906733],"type":"Point"}
}
