{
  "type": "Feature",
  "properties": {
    "iso:country":"GB",
    "wof:name":"SR4 0QJ",
    "wof:placetype":"postalcode"
},
  "geometry": {"coordinates":[-1.45031429273837,54.90672505598982],"type":"Point"}
}