{
  "type": "Feature",
  "properties": {
    "iso:country":"GB",
    "wof:name":"BN2 9ST",
    "wof:placetype":"postalcode"
},
  "geometry": {"coordinates":[-0.12994654731414,50.83047673199857],"type":"Point"}
}