{
  "type": "Feature",
  "properties": {
    "iso:country": "GB",
    "wof:name": "BN2 9ST",
    "wof:placetype": "postalcode"
  },
  "geometry": {"coordinates":[-0.129947,50.830477],"type":"Point"}
}
