{
  "type": "Feature",
  "properties": {
    "iso:country":"GB",
    "wof:name":"PO7 7BZ",
    "wof:placetype":"postalcode"
},
  "geometry": {"coordinates":[-1.03397816497773,50.87297278310435],"type":"Point"}
}