{
  "type": "Feature",
  "properties": {
    "iso:country":"GB",
    "wof:name":"NR30 2EA",
    "wof:placetype":"postalcode"
},
  "geometry": {"coordinates":[1.73014129662303,52.60943808636669],"type":"Point"}
}