{
  "type": "Feature",
  "properties": {
    "date:inception_lower": "2007-08-01",
    "date:inception_upper": "2007-08-01",
    "iso:country": "GB",
    "wof:name": "PE3 7EZ",
    "wof:placetype": "postalcode"
  },
  "geometry": {"coordinates":[-0.263364,52.590439],"type":"Point"}
}
