{
  "type": "Feature",
  "properties": {
    "date:inception_lower": "2005-12-01",
    "date:inception_upper": "2005-12-01",
    "iso:country": "GB",
    "wof:name": "DH4 5NJ",
    "wof:placetype": "postalcode"
  },
  "geometry": {"coordinates":[-1.495801,54.844844],"type":"Point"}
}
