{
  "type": "Feature",
  "properties": {
    "iso:country":"GB",
    "wof:name":"DH4 5NJ",
    "wof:placetype":"postalcode"
},
  "geometry": {"coordinates":[-1.49580145336199,54.84484374981088],"type":"Point"}
}