{
  "type": "Feature",
  "properties": {
    "iso:country":"GB",
    "wof:name":"LL15 2EP",
    "wof:placetype":"postalcode"
},
  "geometry": {"coordinates":[-3.28465405168537,53.09275285507761],"type":"Point"}
}