{
  "type": "Feature",
  "properties": {
    "iso:country": "GB",
    "wof:name": "BL8 4BW",
    "wof:placetype": "postalcode"
  },
  "geometry": {"coordinates":[-2.349841,53.617074],"type":"Point"}
}
