{
  "type": "Feature",
  "properties": {
    "iso:country":"GB",
    "wof:name":"BL8 4BW",
    "wof:placetype":"postalcode"
},
  "geometry": {"coordinates":[-2.34984089789756,53.61707362440338],"type":"Point"}
}