{
  "type": "Feature",
  "properties": {
    "iso:country": "GB",
    "wof:name": "OX17 2ST",
    "wof:placetype": "postalcode"
  },
  "geometry": {"coordinates":[-1.275192,52.078865],"type":"Point"}
}
