{
  "type": "Feature",
  "properties": {
    "iso:country":"GB",
    "wof:name":"SY13 1QP",
    "wof:placetype":"postalcode"
},
  "geometry": {"coordinates":[-2.6785723102063,52.96964639859478],"type":"Point"}
}