{
  "type": "Feature",
  "properties": {
    "iso:country":"GB",
    "wof:name":"W12 9TB",
    "wof:placetype":"postalcode"
},
  "geometry": {"coordinates":[-0.2517195610644,51.50222576762512],"type":"Point"}
}