{
  "type": "Feature",
  "properties": {
    "date:inception_lower": "1980-01-01",
    "date:inception_upper": "1980-01-01",
    "iso:country": "GB",
    "wof:name": "SY11 1DT",
    "wof:placetype": "postalcode"
  },
  "geometry": {"coordinates":[-3.052687,52.865751],"type":"Point"}
}
