{
  "type": "Feature",
  "properties": {
    "date:inception_lower": "1980-01-01",
    "date:inception_upper": "1980-01-01",
    "iso:country": "GB",
    "wof:name": "MK3 7LL",
    "wof:placetype": "postalcode"
  },
  "geometry": {"coordinates":[-0.75316,51.998416],"type":"Point"}
}
