{
  "type": "Feature",
  "properties": {
    "iso:country": "GB",
    "wof:name": "CW5 6QA",
    "wof:placetype": "postalcode"
  },
  "geometry": {"coordinates":[-2.480434,53.069457],"type":"Point"}
}
