{
  "type": "Feature",
  "properties": {
    "date:inception_lower": "1980-01-01",
    "date:inception_upper": "1980-01-01",
    "iso:country": "GB",
    "wof:name": "CW5 6QA",
    "wof:placetype": "postalcode"
  },
  "geometry": {"coordinates":[-2.480434,53.069457],"type":"Point"}
}
