{
  "type": "Feature",
  "properties": {
    "iso:country":"GB",
    "wof:name":"NG2 6NH",
    "wof:placetype":"postalcode"
},
  "geometry": {"coordinates":[-1.10429491874757,52.92970992158943],"type":"Point"}
}