{
  "type": "Feature",
  "properties": {
    "iso:country": "GB",
    "wof:name": "NG2 6NH",
    "wof:placetype": "postalcode"
  },
  "geometry": {"coordinates":[-1.104295,52.92971],"type":"Point"}
}
