{
  "type": "Feature",
  "properties": {
    "date:inception_lower":"1987-04-01",
    "date:inception_upper":"1987-04-30",
    "iso:country":"GB",
    "wof:name":"PR5 5LZ",
    "wof:placetype":"postalcode"
},
  "geometry": {"coordinates":[-2.683113,53.724816],"type":"Point"}
}