{
  "type": "Feature",
  "properties": {
    "iso:country": "GB",
    "wof:name": "PR5 5LZ",
    "wof:placetype": "postalcode"
  },
  "geometry": {"coordinates":[-2.683113,53.724816],"type":"Point"}
}
