{
  "type": "Feature",
  "properties": {
    "iso:country":"GB",
    "wof:name":"G69 9HR",
    "wof:placetype":"postalcode"
},
  "geometry": {"coordinates":[-4.11449114225274,55.91729953208136],"type":"Point"}
}