{
  "type": "Feature",
  "properties": {
    "date:inception_lower":"2002-12-01",
    "date:inception_upper":"2002-12-31",
    "iso:country":"GB",
    "wof:name":"G69 9HR",
    "wof:placetype":"postalcode"
},
  "geometry": {"coordinates":[-4.114491,55.9173],"type":"Point"}
}