{
  "type": "Feature",
  "properties": {
    "date:inception_lower": "2001-06-01",
    "date:inception_upper": "2001-06-01",
    "iso:country": "GB",
    "wof:name": "PR25 1TN",
    "wof:placetype": "postalcode"
  },
  "geometry": {"coordinates":[-2.720931,53.688767],"type":"Point"}
}
