{
  "type": "Feature",
  "properties": {
    "date:inception_lower":"1980-01-01",
    "date:inception_upper":"1980-01-31",
    "iso:country":"GB",
    "wof:name":"CW12 3QF",
    "wof:placetype":"postalcode"
},
  "geometry": {"coordinates":[-2.131619,53.171123],"type":"Point"}
}