{
  "type": "Feature",
  "properties": {
    "date:inception_lower": "2013-07-01",
    "date:inception_upper": "2013-07-01",
    "iso:country": "GB",
    "wof:name": "PL13 1QU",
    "wof:placetype": "postalcode"
  },
  "geometry": {"coordinates":[-4.449567,50.367098],"type":"Point"}
}
