{
  "type": "Feature",
  "properties": {
    "iso:country":"GB",
    "wof:name":"PL13 1QU",
    "wof:placetype":"postalcode"
},
  "geometry": {"coordinates":[-4.44956712934443,50.36709832849748],"type":"Point"}
}