{
  "type": "Feature",
  "properties": {
    "iso:country":"GB",
    "wof:name":"CF24 3EY",
    "wof:placetype":"postalcode"
},
  "geometry": {"coordinates":[-3.16320165934959,51.49123699276993],"type":"Point"}
}