{
  "type": "Feature",
  "properties": {
    "date:inception_lower": "1999-06-01",
    "date:inception_upper": "1999-06-01",
    "iso:country": "GB",
    "wof:name": "CF24 3EY",
    "wof:placetype": "postalcode"
  },
  "geometry": {"coordinates":[-3.16324,51.491273],"type":"Point"}
}
