{
  "type": "Feature",
  "properties": {
    "iso:country":"GB",
    "wof:name":"B91 3ST",
    "wof:placetype":"postalcode"
},
  "geometry": {"coordinates":[-1.77631654069002,52.41216428056499],"type":"Point"}
}