{
  "type": "Feature",
  "properties": {
    "iso:country":"GB",
    "wof:name":"M34 3YJ",
    "wof:placetype":"postalcode"
},
  "geometry": {"coordinates":[-2.11703482147634,53.46175106295276],"type":"Point"}
}