{
  "type": "Feature",
  "properties": {
    "iso:country":"GB",
    "wof:name":"EX23 8EQ",
    "wof:placetype":"postalcode"
},
  "geometry": {"coordinates":[-4.54089966451385,50.82992315944738],"type":"Point"}
}