{
  "type": "Feature",
  "properties": {
    "date:inception_lower": "1980-01-01",
    "date:inception_upper": "1980-01-01",
    "iso:country": "GB",
    "wof:name": "EX23 8EQ",
    "wof:placetype": "postalcode"
  },
  "geometry": {"coordinates":[-4.540606,50.829907],"type":"Point"}
}
