{
  "type": "Feature",
  "properties": {
    "iso:country": "GB",
    "wof:name": "CH1 5BL",
    "wof:placetype": "postalcode"
  },
  "geometry": {"coordinates":[-2.910121,53.203332],"type":"Point"}
}
