{
  "type": "Feature",
  "properties": {
    "iso:country": "GB",
    "wof:name": "SW6 5DP",
    "wof:placetype": "postalcode"
  },
  "geometry": {"coordinates":[-0.20514,51.477575],"type":"Point"}
}
