{
  "type": "Feature",
  "properties": {
    "iso:country":"GB",
    "wof:name":"WS14 9QB",
    "wof:placetype":"postalcode"
},
  "geometry": {"coordinates":[-1.78323768023898,52.64964527411826],"type":"Point"}
}