{
  "type": "Feature",
  "properties": {
    "iso:country": "GB",
    "wof:name": "NN8 6XD",
    "wof:placetype": "postalcode"
  },
  "geometry": {"coordinates":[-0.738551,52.310743],"type":"Point"}
}
