{
  "type": "Feature",
  "properties": {
    "iso:country":"GB",
    "wof:name":"NN8 6XD",
    "wof:placetype":"postalcode"
},
  "geometry": {"coordinates":[-0.73855109680686,52.31074281194966],"type":"Point"}
}