{
  "type": "Feature",
  "properties": {
    "iso:country": "GB",
    "wof:name": "WS4 1AX",
    "wof:placetype": "postalcode"
  },
  "geometry": {"coordinates":[-1.953634,52.620671],"type":"Point"}
}
