{
  "type": "Feature",
  "properties": {
    "date:inception_lower":"1983-07-01",
    "date:inception_upper":"1983-07-31",
    "iso:country":"GB",
    "wof:name":"DE55 1RY",
    "wof:placetype":"postalcode"
},
  "geometry": {"coordinates":[-1.389075,53.07875],"type":"Point"}
}