{
  "type": "Feature",
  "properties": {
    "iso:country":"GB",
    "wof:name":"WN5 8AR",
    "wof:placetype":"postalcode"
},
  "geometry": {"coordinates":[-2.67676377789562,53.53597006169459],"type":"Point"}
}