{
  "type": "Feature",
  "properties": {
    "iso:country":"GB",
    "wof:name":"WA3 2HZ",
    "wof:placetype":"postalcode"
},
  "geometry": {"coordinates":[-2.57728672012398,53.4771226435276],"type":"Point"}
}