{
  "type": "Feature",
  "properties": {
    "iso:country":"GB",
    "wof:name":"BD18 3NA",
    "wof:placetype":"postalcode"
},
  "geometry": {"coordinates":[-1.78282626103219,53.83461309383001],"type":"Point"}
}