{
  "type": "Feature",
  "properties": {
    "iso:country": "GB",
    "wof:name": "BD18 3NA",
    "wof:placetype": "postalcode"
  },
  "geometry": {"coordinates":[-1.782826,53.834613],"type":"Point"}
}
