{
  "type": "Feature",
  "properties": {
    "iso:country":"GB",
    "wof:name":"ST5 6JZ",
    "wof:placetype":"postalcode"
},
  "geometry": {"coordinates":[-2.27726542039206,53.01551444699021],"type":"Point"}
}