{
  "type": "Feature",
  "properties": {
    "iso:country": "GB",
    "wof:name": "OX25 5QQ",
    "wof:placetype": "postalcode"
  },
  "geometry": {"coordinates":[-1.324149,51.923946],"type":"Point"}
}
