{
  "type": "Feature",
  "properties": {
    "iso:country":"GB",
    "wof:name":"OX25 5QQ",
    "wof:placetype":"postalcode"
},
  "geometry": {"coordinates":[-1.32414953832606,51.92394640290883],"type":"Point"}
}