{
  "type": "Feature",
  "properties": {
    "date:inception_lower":"2000-10-01",
    "date:inception_upper":"2000-10-31",
    "iso:country":"GB",
    "wof:name":"OX25 5QQ",
    "wof:placetype":"postalcode"
},
  "geometry": {"coordinates":[-1.324149,51.923946],"type":"Point"}
}