{
  "type": "Feature",
  "properties": {
    "iso:country": "GB",
    "wof:name": "YO25 3TB",
    "wof:placetype": "postalcode"
  },
  "geometry": {"coordinates":[-0.455489,54.086028],"type":"Point"}
}
