{
  "type": "Feature",
  "properties": {
    "iso:country":"GB",
    "wof:name":"LL28 5HQ",
    "wof:placetype":"postalcode"
},
  "geometry": {"coordinates":[-3.76660198313919,53.28789689368668],"type":"Point"}
}