{
  "type": "Feature",
  "properties": {
    "iso:country": "GB",
    "wof:name": "LL28 5HQ",
    "wof:placetype": "postalcode"
  },
  "geometry": {"coordinates":[-3.766602,53.287897],"type":"Point"}
}
