{
  "type": "Feature",
  "properties": {
    "iso:country": "GB",
    "wof:name": "SO31 4JN",
    "wof:placetype": "postalcode"
  },
  "geometry": {"coordinates":[-1.325001,50.861654],"type":"Point"}
}
