{
  "type": "Feature",
  "properties": {
    "date:inception_lower":"2018-04-01",
    "date:inception_upper":"2018-04-30",
    "iso:country":"GB",
    "wof:name":"UB8 9BU",
    "wof:placetype":"postalcode"
},
  "geometry": {"coordinates":[-0.487335,51.537326],"type":"Point"}
}