{
  "type": "Feature",
  "properties": {
    "iso:country":"GB",
    "wof:name":"M20 1BG",
    "wof:placetype":"postalcode"
},
  "geometry": {"coordinates":[-2.24258193361523,53.43953104588573],"type":"Point"}
}