{
  "type": "Feature",
  "properties": {
    "iso:country": "GB",
    "wof:name": "MK40 2FN",
    "wof:placetype": "postalcode"
  },
  "geometry": {"coordinates":[-0.475162,52.141106],"type":"Point"}
}
