{
  "type": "Feature",
  "properties": {
    "iso:country":"GB",
    "wof:name":"S75 1JX",
    "wof:placetype":"postalcode"
},
  "geometry": {"coordinates":[-1.52859611578757,53.56751006103994],"type":"Point"}
}