{
  "type": "Feature",
  "properties": {
    "iso:country":"GB",
    "wof:name":"WD6 3AU",
    "wof:placetype":"postalcode"
},
  "geometry": {"coordinates":[-0.32005714757501,51.65294496137324],"type":"Point"}
}