{
  "type": "Feature",
  "properties": {
    "iso:country":"GB",
    "wof:name":"SN4 9DN",
    "wof:placetype":"postalcode"
},
  "geometry": {"coordinates":[-1.79032184021368,51.52949572671276],"type":"Point"}
}