{
  "type": "Feature",
  "properties": {
    "iso:country":"GB",
    "wof:name":"DH9 8RQ",
    "wof:placetype":"postalcode"
},
  "geometry": {"coordinates":[-1.69000783153559,54.8788878596467],"type":"Point"}
}