{
  "type": "Feature",
  "properties": {
    "iso:country": "GB",
    "wof:name": "DH9 8RQ",
    "wof:placetype": "postalcode"
  },
  "geometry": {"coordinates":[-1.690008,54.878888],"type":"Point"}
}
