{
  "type": "Feature",
  "properties": {
    "date:inception_lower": "2023-07-01",
    "date:inception_upper": "2023-07-01",
    "iso:country": "GB",
    "wof:name": "S81 9GD",
    "wof:placetype": "postalcode"
  },
  "geometry": {"coordinates":[-1.125371,53.369406],"type":"Point"}
}
