{
  "type": "Feature",
  "properties": {
    "iso:country":"GB",
    "wof:name":"BS5 0DS",
    "wof:placetype":"postalcode"
},
  "geometry": {"coordinates":[-2.56938423440821,51.45943325833685],"type":"Point"}
}