{
  "type": "Feature",
  "properties": {
    "iso:country":"GB",
    "wof:name":"B76 1BE",
    "wof:placetype":"postalcode"
},
  "geometry": {"coordinates":[-1.78957859872036,52.52933712269917],"type":"Point"}
}