{
  "type": "Feature",
  "properties": {
    "date:inception_lower":"2006-10-01",
    "date:inception_upper":"2006-10-31",
    "iso:country":"GB",
    "wof:name":"B76 1BE",
    "wof:placetype":"postalcode"
},
  "geometry": {"coordinates":[-1.789579,52.529337],"type":"Point"}
}