{
  "type": "Feature",
  "properties": {
    "iso:country": "GB",
    "wof:name": "DY1 4EU",
    "wof:placetype": "postalcode"
  },
  "geometry": {"coordinates":[-2.086424,52.516822],"type":"Point"}
}
