{
  "type": "Feature",
  "properties": {
    "iso:country":"GB",
    "wof:name":"DY1 4EU",
    "wof:placetype":"postalcode"
},
  "geometry": {"coordinates":[-2.0865328406471,52.51685206567618],"type":"Point"}
}