{
  "type": "Feature",
  "properties": {
    "iso:country":"GB",
    "wof:name":"NP7 7RB",
    "wof:placetype":"postalcode"
},
  "geometry": {"coordinates":[-3.02939035561209,51.82491481676263],"type":"Point"}
}