{
  "type": "Feature",
  "properties": {
    "iso:country":"GB",
    "wof:name":"WD25 0JW",
    "wof:placetype":"postalcode"
},
  "geometry": {"coordinates":[-0.39510780578812,51.70299200125491],"type":"Point"}
}