{
  "type": "Feature",
  "properties": {
    "iso:country": "GB",
    "wof:name": "LE3 3QL",
    "wof:placetype": "postalcode"
  },
  "geometry": {"coordinates":[-1.209999,52.6272],"type":"Point"}
}
