{
  "type": "Feature",
  "properties": {
    "iso:country":"GB",
    "wof:name":"LE3 3QL",
    "wof:placetype":"postalcode"
},
  "geometry": {"coordinates":[-1.2099991354515,52.62719991740691],"type":"Point"}
}