{
  "type": "Feature",
  "properties": {
    "iso:country":"GB",
    "wof:name":"WA13 0RH",
    "wof:placetype":"postalcode"
},
  "geometry": {"coordinates":[-2.45306543586259,53.3717457168494],"type":"Point"}
}