{
  "type": "Feature",
  "properties": {
    "date:inception_lower": "2024-01-01",
    "date:inception_upper": "2024-01-01",
    "iso:country": "GB",
    "wof:name": "TA21 9FZ",
    "wof:placetype": "postalcode"
  },
  "geometry": {"coordinates":[-3.214835,50.9757],"type":"Point"}
}
