{
  "type": "Feature",
  "properties": {
    "iso:country":"GB",
    "wof:name":"IP12 4FB",
    "wof:placetype":"postalcode"
},
  "geometry": {"coordinates":[1.30311991994452,52.09194502773596],"type":"Point"}
}