{
  "type": "Feature",
  "properties": {
    "iso:country": "GB",
    "wof:name": "IP12 4FB",
    "wof:placetype": "postalcode"
  },
  "geometry": {"coordinates":[1.30315,52.09196],"type":"Point"}
}
