{
  "type": "Feature",
  "properties": {
    "iso:country": "GB",
    "wof:name": "WS7 2ER",
    "wof:placetype": "postalcode"
  },
  "geometry": {"coordinates":[-1.926095,52.685833],"type":"Point"}
}
