{
  "type": "Feature",
  "properties": {
    "iso:country":"GB",
    "wof:name":"WS7 2ER",
    "wof:placetype":"postalcode"
},
  "geometry": {"coordinates":[-1.92609464192201,52.6858327788873],"type":"Point"}
}