{
  "type": "Feature",
  "properties": {
    "iso:country":"GB",
    "wof:name":"TF11 8QN",
    "wof:placetype":"postalcode"
},
  "geometry": {"coordinates":[-2.37567802304562,52.68774071371524],"type":"Point"}
}