{
  "type": "Feature",
  "properties": {
    "iso:country":"GB",
    "wof:name":"MK4 4HR",
    "wof:placetype":"postalcode"
},
  "geometry": {"coordinates":[-0.80638311451063,52.00014550669027],"type":"Point"}
}