{
  "type": "Feature",
  "properties": {
    "iso:country": "GB",
    "wof:name": "MK4 4HR",
    "wof:placetype": "postalcode"
  },
  "geometry": {"coordinates":[-0.806383,52.000146],"type":"Point"}
}
