{
  "type": "Feature",
  "properties": {
    "iso:country":"GB",
    "wof:name":"BL9 6QU",
    "wof:placetype":"postalcode"
},
  "geometry": {"coordinates":[-2.29274698984102,53.61524958875486],"type":"Point"}
}