{
  "type": "Feature",
  "properties": {
    "date:inception_lower": "1988-03-01",
    "date:inception_upper": "1988-03-01",
    "iso:country": "GB",
    "wof:name": "ME8 9NQ",
    "wof:placetype": "postalcode"
  },
  "geometry": {"coordinates":[0.601128,51.348661],"type":"Point"}
}
