{
  "type": "Feature",
  "properties": {
    "iso:country":"GB",
    "wof:name":"LU7 2RQ",
    "wof:placetype":"postalcode"
},
  "geometry": {"coordinates":[-0.67406980112563,51.91878863160894],"type":"Point"}
}