{
  "type": "Feature",
  "properties": {
    "iso:country":"GB",
    "wof:name":"CM6 1ZF",
    "wof:placetype":"postalcode"
},
  "geometry": {"coordinates":[0.36064761252432,51.87261770712133],"type":"Point"}
}