{
  "type": "Feature",
  "properties": {
    "iso:country": "GB",
    "wof:name": "CM6 1ZF",
    "wof:placetype": "postalcode"
  },
  "geometry": {"coordinates":[0.360648,51.872618],"type":"Point"}
}
