{
  "type": "Feature",
  "properties": {
    "iso:country":"GB",
    "wof:name":"BS7 8NT",
    "wof:placetype":"postalcode"
},
  "geometry": {"coordinates":[-2.5905105634567,51.47700624506601],"type":"Point"}
}