{
  "type": "Feature",
  "properties": {
    "iso:country": "GB",
    "wof:name": "BS7 8NT",
    "wof:placetype": "postalcode"
  },
  "geometry": {"coordinates":[-2.590541,51.476969],"type":"Point"}
}
