{
  "type": "Feature",
  "properties": {
    "iso:country":"GB",
    "wof:name":"SP10 5PJ",
    "wof:placetype":"postalcode"
},
  "geometry": {"coordinates":[-1.47501139788571,51.22029935380345],"type":"Point"}
}