{
  "type": "Feature",
  "properties": {
    "iso:country":"GB",
    "wof:name":"PR6 0BU",
    "wof:placetype":"postalcode"
},
  "geometry": {"coordinates":[-2.6127323403717,53.64576741319757],"type":"Point"}
}