{
  "type": "Feature",
  "properties": {
    "iso:country": "GB",
    "wof:name": "PR6 0BU",
    "wof:placetype": "postalcode"
  },
  "geometry": {"coordinates":[-2.612673,53.646018],"type":"Point"}
}
