{
  "type": "Feature",
  "properties": {
    "date:inception_lower": "2009-11-01",
    "date:inception_upper": "2009-11-01",
    "iso:country": "GB",
    "wof:name": "PR6 0BU",
    "wof:placetype": "postalcode"
  },
  "geometry": {"coordinates":[-2.61273,53.645784],"type":"Point"}
}
