{
  "type": "Feature",
  "properties": {
    "iso:country": "GB",
    "wof:name": "LN1 2NH",
    "wof:placetype": "postalcode"
  },
  "geometry": {"coordinates":[-0.734305,53.293508],"type":"Point"}
}
