{
  "type": "Feature",
  "properties": {
    "date:inception_lower": "1991-01-01",
    "date:inception_upper": "1991-01-01",
    "iso:country": "GB",
    "wof:name": "LN1 2NH",
    "wof:placetype": "postalcode"
  },
  "geometry": {"coordinates":[-0.734305,53.293508],"type":"Point"}
}
