{
  "type": "Feature",
  "properties": {
    "iso:country":"GB",
    "wof:name":"SP11 9BG",
    "wof:placetype":"postalcode"
},
  "geometry": {"coordinates":[-1.56558543018744,51.23774607875682],"type":"Point"}
}