{
  "type": "Feature",
  "properties": {
    "iso:country": "GB",
    "wof:name": "SP11 9BG",
    "wof:placetype": "postalcode"
  },
  "geometry": {"coordinates":[-1.565574,51.237742],"type":"Point"}
}
