{
  "type": "Feature",
  "properties": {
    "iso:country": "GB",
    "wof:name": "GL54 5PZ",
    "wof:placetype": "postalcode"
  },
  "geometry": {"coordinates":[-1.96732,51.954678],"type":"Point"}
}
