{
  "type": "Feature",
  "properties": {
    "iso:country":"GB",
    "wof:name":"WR9 0EE",
    "wof:placetype":"postalcode"
},
  "geometry": {"coordinates":[-2.23012537706823,52.27712733979106],"type":"Point"}
}