{
  "type": "Feature",
  "properties": {
    "iso:country": "GB",
    "wof:name": "WR9 0EE",
    "wof:placetype": "postalcode"
  },
  "geometry": {"coordinates":[-2.230125,52.277127],"type":"Point"}
}
