{
  "type": "Feature",
  "properties": {
    "date:inception_lower": "2009-08-01",
    "date:inception_upper": "2009-08-01",
    "iso:country": "GB",
    "wof:name": "ME16 8FD",
    "wof:placetype": "postalcode"
  },
  "geometry": {"coordinates":[0.516906,51.26758],"type":"Point"}
}
