{
  "type": "Feature",
  "properties": {
    "iso:country": "GB",
    "wof:name": "DH2 3QH",
    "wof:placetype": "postalcode"
  },
  "geometry": {"coordinates":[-1.597939,54.819874],"type":"Point"}
}
