{
  "type": "Feature",
  "properties": {
    "iso:country":"GB",
    "wof:name":"DH2 3QH",
    "wof:placetype":"postalcode"
},
  "geometry": {"coordinates":[-1.59793941493711,54.81987380198792],"type":"Point"}
}