{
  "type": "Feature",
  "properties": {
    "iso:country": "GB",
    "wof:name": "NN4 0SE",
    "wof:placetype": "postalcode"
  },
  "geometry": {"coordinates":[-0.896543,52.203456],"type":"Point"}
}
