{
  "type": "Feature",
  "properties": {
    "iso:country":"GB",
    "wof:name":"BD13 3LY",
    "wof:placetype":"postalcode"
},
  "geometry": {"coordinates":[-1.85328986213922,53.78548382390819],"type":"Point"}
}