{
  "type": "Feature",
  "properties": {
    "iso:country":"GB",
    "wof:name":"SN4 0RT",
    "wof:placetype":"postalcode"
},
  "geometry": {"coordinates":[-1.79075905872541,51.52215949339907],"type":"Point"}
}