{
  "type": "Feature",
  "properties": {
    "iso:country": "GB",
    "wof:name": "TQ12 3PW",
    "wof:placetype": "postalcode"
  },
  "geometry": {"coordinates":[-3.605953,50.556963],"type":"Point"}
}
