{
  "type": "Feature",
  "properties": {
    "iso:country":"GB",
    "wof:name":"TQ12 3PW",
    "wof:placetype":"postalcode"
},
  "geometry": {"coordinates":[-3.60828427778106,50.55786904032337],"type":"Point"}
}