{
  "type": "Feature",
  "properties": {
    "date:inception_lower": "2000-06-01",
    "date:inception_upper": "2000-06-01",
    "iso:country": "GB",
    "wof:name": "YO11 2JP",
    "wof:placetype": "postalcode"
  },
  "geometry": {"coordinates":[-0.407742,54.276294],"type":"Point"}
}
