{
  "type": "Feature",
  "properties": {
    "iso:country":"GB",
    "wof:name":"BD22 7LY",
    "wof:placetype":"postalcode"
},
  "geometry": {"coordinates":[-1.93385577802905,53.8501064405586],"type":"Point"}
}