{
  "type": "Feature",
  "properties": {
    "date:inception_lower":"1980-01-01",
    "date:inception_upper":"1980-01-31",
    "iso:country":"GB",
    "wof:name":"NG23 6SA",
    "wof:placetype":"postalcode"
},
  "geometry": {"coordinates":[-0.824117,53.22236],"type":"Point"}
}