{
  "type": "Feature",
  "properties": {
    "iso:country":"GB",
    "wof:name":"NG23 6SA",
    "wof:placetype":"postalcode"
},
  "geometry": {"coordinates":[-0.82411722146423,53.22235995924182],"type":"Point"}
}