{
  "type": "Feature",
  "properties": {
    "iso:country": "GB",
    "wof:name": "NG23 6SA",
    "wof:placetype": "postalcode"
  },
  "geometry": {"coordinates":[-0.824117,53.22236],"type":"Point"}
}
