{
  "type": "Feature",
  "properties": {
    "iso:country": "GB",
    "wof:name": "DA3 7JH",
    "wof:placetype": "postalcode"
  },
  "geometry": {"coordinates":[0.326318,51.399085],"type":"Point"}
}
