{
  "type": "Feature",
  "properties": {
    "iso:country":"GB",
    "wof:name":"YO60 7TE",
    "wof:placetype":"postalcode"
},
  "geometry": {"coordinates":[-0.95639904915846,54.078094560007],"type":"Point"}
}