{
  "type": "Feature",
  "properties": {
    "iso:country": "GB",
    "wof:name": "YO60 7TE",
    "wof:placetype": "postalcode"
  },
  "geometry": {"coordinates":[-0.956399,54.078095],"type":"Point"}
}
