{
  "type": "Feature",
  "properties": {
    "iso:country":"GB",
    "wof:name":"LL20 8BS",
    "wof:placetype":"postalcode"
},
  "geometry": {"coordinates":[-3.19314850331355,52.98172158918131],"type":"Point"}
}