{
  "type": "Feature",
  "properties": {
    "date:inception_lower": "1980-01-01",
    "date:inception_upper": "1980-01-01",
    "iso:country": "GB",
    "wof:name": "NG3 6HA",
    "wof:placetype": "postalcode"
  },
  "geometry": {"coordinates":[-1.120153,52.977428],"type":"Point"}
}
