{
  "type": "Feature",
  "properties": {
    "date:inception_lower": "2024-08-01",
    "date:inception_upper": "2024-08-01",
    "iso:country": "GB",
    "wof:name": "NE6 5BZ",
    "wof:placetype": "postalcode"
  },
  "geometry": {"coordinates":[-1.573612,54.983853],"type":"Point"}
}
