{
  "type": "Feature",
  "properties": {
    "iso:country":"GB",
    "wof:name":"B60 2NU",
    "wof:placetype":"postalcode"
},
  "geometry": {"coordinates":[-2.0513936984857,52.33429385453585],"type":"Point"}
}