{
  "type": "Feature",
  "properties": {
    "date:inception_lower": "1980-01-01",
    "date:inception_upper": "1980-01-01",
    "iso:country": "GB",
    "wof:name": "WS4 1AY",
    "wof:placetype": "postalcode"
  },
  "geometry": {"coordinates":[-1.953249,52.622011],"type":"Point"}
}
