{
  "type": "Feature",
  "properties": {
    "iso:country":"GB",
    "wof:name":"WS4 1AY",
    "wof:placetype":"postalcode"
},
  "geometry": {"coordinates":[-1.95324879310324,52.62201072856026],"type":"Point"}
}