{
  "type": "Feature",
  "properties": {
    "date:inception_lower": "2022-02-01",
    "date:inception_upper": "2022-02-01",
    "iso:country": "GB",
    "wof:name": "CF64 5WL",
    "wof:placetype": "postalcode"
  },
  "geometry": {"coordinates":[-3.209459,51.409409],"type":"Point"}
}
