{
  "type": "Feature",
  "properties": {
    "iso:country": "GB",
    "wof:name": "OL4 4NT",
    "wof:placetype": "postalcode"
  },
  "geometry": {"coordinates":[-2.064381,53.541779],"type":"Point"}
}
