{
  "type": "Feature",
  "properties": {
    "iso:country":"GB",
    "wof:name":"CT14 6AQ",
    "wof:placetype":"postalcode"
},
  "geometry": {"coordinates":[1.40158403727625,51.2242224839324],"type":"Point"}
}