{
  "type": "Feature",
  "properties": {
    "iso:country": "GB",
    "wof:name": "CT14 6AQ",
    "wof:placetype": "postalcode"
  },
  "geometry": {"coordinates":[1.401584,51.224222],"type":"Point"}
}
