{
  "type": "Feature",
  "properties": {
    "iso:country":"GB",
    "wof:name":"SN12 6SJ",
    "wof:placetype":"postalcode"
},
  "geometry": {"coordinates":[-2.1278971119261,51.35767608372093],"type":"Point"}
}