{
  "type": "Feature",
  "properties": {
    "iso:country":"GB",
    "wof:name":"KA16 9AP",
    "wof:placetype":"postalcode"
},
  "geometry": {"coordinates":[-4.32969437307561,55.60682483983827],"type":"Point"}
}