{
  "type": "Feature",
  "properties": {
    "iso:country":"GB",
    "wof:name":"SL4 2PF",
    "wof:placetype":"postalcode"
},
  "geometry": {"coordinates":[-0.57916079859264,51.46274082394295],"type":"Point"}
}