{
  "type": "Feature",
  "properties": {
    "iso:country": "GB",
    "wof:name": "SL4 2PF",
    "wof:placetype": "postalcode"
  },
  "geometry": {"coordinates":[-0.578523,51.462779],"type":"Point"}
}
