{
  "type": "Feature",
  "properties": {
    "iso:country":"GB",
    "wof:name":"NE31 2UG",
    "wof:placetype":"postalcode"
},
  "geometry": {"coordinates":[-1.51672057860978,54.97205933809528],"type":"Point"}
}