{
  "type": "Feature",
  "properties": {
    "iso:country": "GB",
    "wof:name": "NE31 2UG",
    "wof:placetype": "postalcode"
  },
  "geometry": {"coordinates":[-1.516721,54.972059],"type":"Point"}
}
