{
  "type": "Feature",
  "properties": {
    "iso:country": "GB",
    "wof:name": "FY5 2LA",
    "wof:placetype": "postalcode"
  },
  "geometry": {"coordinates":[-3.02524,53.887125],"type":"Point"}
}
