{
  "type": "Feature",
  "properties": {
    "iso:country":"GB",
    "wof:name":"SE13 5BP",
    "wof:placetype":"postalcode"
},
  "geometry": {"coordinates":[0.00244460429383,51.4613811528961],"type":"Point"}
}