{
  "type": "Feature",
  "properties": {
    "iso:country":"GB",
    "wof:name":"ST10 1QE",
    "wof:placetype":"postalcode"
},
  "geometry": {"coordinates":[-1.98307081608483,52.976608331715],"type":"Point"}
}