{
  "type": "Feature",
  "properties": {
    "date:inception_lower": "1980-01-01",
    "date:inception_upper": "1980-01-01",
    "iso:country": "GB",
    "wof:name": "CV6 7JZ",
    "wof:placetype": "postalcode"
  },
  "geometry": {"coordinates":[-1.476597,52.430628],"type":"Point"}
}
