{
  "type": "Feature",
  "properties": {
    "iso:country":"GB",
    "wof:name":"CV6 7JZ",
    "wof:placetype":"postalcode"
},
  "geometry": {"coordinates":[-1.47659742685683,52.43062779071493],"type":"Point"}
}