{
  "type": "Feature",
  "properties": {
    "iso:country":"GB",
    "wof:name":"AB24 4FE",
    "wof:placetype":"postalcode"
},
  "geometry": {"coordinates":[-2.12555657180905,57.16869623221702],"type":"Point"}
}