{
  "type": "Feature",
  "properties": {
    "iso:country":"GB",
    "wof:name":"DL11 7BP",
    "wof:placetype":"postalcode"
},
  "geometry": {"coordinates":[-1.79925773073075,54.52715649720578],"type":"Point"}
}