{
  "type": "Feature",
  "properties": {
    "iso:country": "GB",
    "wof:name": "DL11 7BP",
    "wof:placetype": "postalcode"
  },
  "geometry": {"coordinates":[-1.799258,54.527156],"type":"Point"}
}
