{
  "type": "Feature",
  "properties": {
    "date:inception_lower": "2023-03-01",
    "date:inception_upper": "2023-03-01",
    "iso:country": "GB",
    "wof:name": "WA4 5RW",
    "wof:placetype": "postalcode"
  },
  "geometry": {"coordinates":[-2.553228,53.350045],"type":"Point"}
}
