{
  "type": "Feature",
  "properties": {
    "date:inception_lower": "2020-09-01",
    "date:inception_upper": "2020-09-01",
    "iso:country": "GB",
    "wof:name": "CW11 5EH",
    "wof:placetype": "postalcode"
  },
  "geometry": {"coordinates":[-2.361844,53.143974],"type":"Point"}
}
