{
  "type": "Feature",
  "properties": {
    "iso:country": "GB",
    "wof:name": "WF1 1UN",
    "wof:placetype": "postalcode"
  },
  "geometry": {"coordinates":[-1.493517,53.678957],"type":"Point"}
}
