{
  "type": "Feature",
  "properties": {
    "iso:country":"GB",
    "wof:name":"WF1 1UN",
    "wof:placetype":"postalcode"
},
  "geometry": {"coordinates":[-1.49351743551108,53.67895679069191],"type":"Point"}
}