{
  "type": "Feature",
  "properties": {
    "date:inception_lower": "1980-01-01",
    "date:inception_upper": "1980-01-01",
    "iso:country": "GB",
    "wof:name": "GL6 6UF",
    "wof:placetype": "postalcode"
  },
  "geometry": {"coordinates":[-2.185056,51.80821],"type":"Point"}
}
