{
  "type": "Feature",
  "properties": {
    "iso:country":"GB",
    "wof:name":"GL6 6UF",
    "wof:placetype":"postalcode"
},
  "geometry": {"coordinates":[-2.18505555307075,51.80820994694608],"type":"Point"}
}