{
  "type": "Feature",
  "properties": {
    "date:inception_lower": "1980-01-01",
    "date:inception_upper": "1980-01-01",
    "iso:country": "GB",
    "wof:name": "B61 9HB",
    "wof:placetype": "postalcode"
  },
  "geometry": {"coordinates":[-2.125876,52.314936],"type":"Point"}
}
