{
  "type": "Feature",
  "properties": {
    "iso:country":"GB",
    "wof:name":"B61 9HB",
    "wof:placetype":"postalcode"
},
  "geometry": {"coordinates":[-2.12587636460167,52.31493585229485],"type":"Point"}
}