{
  "type": "Feature",
  "properties": {
    "date:inception_lower": "1992-01-01",
    "date:inception_upper": "1992-01-01",
    "iso:country": "GB",
    "wof:name": "LA3 2JQ",
    "wof:placetype": "postalcode"
  },
  "geometry": {"coordinates":[-2.888457,54.04407],"type":"Point"}
}
