{
  "type": "Feature",
  "properties": {
    "iso:country": "GB",
    "wof:name": "SE18 3BE",
    "wof:placetype": "postalcode"
  },
  "geometry": {"coordinates":[0.067527,51.467761],"type":"Point"}
}
