{
  "type": "Feature",
  "properties": {
    "iso:country":"GB",
    "wof:name":"CF39 9PX",
    "wof:placetype":"postalcode"
},
  "geometry": {"coordinates":[-3.41743946493088,51.60038066456858],"type":"Point"}
}