{
  "type": "Feature",
  "properties": {
    "date:inception_lower": "1980-01-01",
    "date:inception_upper": "1980-01-01",
    "iso:country": "GB",
    "wof:name": "AL1 2JL",
    "wof:placetype": "postalcode"
  },
  "geometry": {"coordinates":[-0.336383,51.739222],"type":"Point"}
}
