{
  "type": "Feature",
  "properties": {
    "iso:country": "GB",
    "wof:name": "AL1 2JL",
    "wof:placetype": "postalcode"
  },
  "geometry": {"coordinates":[-0.336383,51.739222],"type":"Point"}
}
