{
  "type": "Feature",
  "properties": {
    "date:inception_lower": "2019-06-01",
    "date:inception_upper": "2019-06-01",
    "iso:country": "GB",
    "wof:name": "ME1 1GF",
    "wof:placetype": "postalcode"
  },
  "geometry": {"coordinates":[0.50826,51.390115],"type":"Point"}
}
