{
  "type": "Feature",
  "properties": {
    "iso:country": "GB",
    "wof:name": "ME1 1GF",
    "wof:placetype": "postalcode"
  },
  "geometry": {"coordinates":[0.507923,51.389996],"type":"Point"}
}
