{
  "type": "Feature",
  "properties": {
    "iso:country":"GB",
    "wof:name":"N3 2DS",
    "wof:placetype":"postalcode"
},
  "geometry": {"coordinates":[-0.18291366614976,51.60661582951591],"type":"Point"}
}