{
  "type": "Feature",
  "properties": {
    "iso:country":"GB",
    "wof:name":"SN8 3JP",
    "wof:placetype":"postalcode"
},
  "geometry": {"coordinates":[-1.58172962563652,51.39080935755814],"type":"Point"}
}