{
  "type": "Feature",
  "properties": {
    "date:inception_lower": "1980-01-01",
    "date:inception_upper": "1980-01-01",
    "iso:country": "GB",
    "wof:name": "SN8 3JP",
    "wof:placetype": "postalcode"
  },
  "geometry": {"coordinates":[-1.58173,51.390809],"type":"Point"}
}
