{
  "type": "Feature",
  "properties": {
    "iso:country": "GB",
    "wof:name": "SN8 3JP",
    "wof:placetype": "postalcode"
  },
  "geometry": {"coordinates":[-1.58173,51.390809],"type":"Point"}
}
