{
  "type": "Feature",
  "properties": {
    "iso:country":"GB",
    "wof:name":"SY1 3PX",
    "wof:placetype":"postalcode"
},
  "geometry": {"coordinates":[-2.74198064831111,52.74015872803604],"type":"Point"}
}