{
  "type": "Feature",
  "properties": {
    "iso:country": "GB",
    "wof:name": "HG3 1NQ",
    "wof:placetype": "postalcode"
  },
  "geometry": {"coordinates":[-1.540846,53.965556],"type":"Point"}
}
