{
  "type": "Feature",
  "properties": {
    "iso:country":"GB",
    "wof:name":"HG3 1NQ",
    "wof:placetype":"postalcode"
},
  "geometry": {"coordinates":[-1.54126680772928,53.96555187176635],"type":"Point"}
}