{
  "type": "Feature",
  "properties": {
    "iso:country": "GB",
    "wof:name": "BL3 1BS",
    "wof:placetype": "postalcode"
  },
  "geometry": {"coordinates":[-2.38327,53.561028],"type":"Point"}
}
