{
  "type": "Feature",
  "properties": {
    "date:inception_lower": "1980-01-01",
    "date:inception_upper": "1980-01-01",
    "iso:country": "GB",
    "wof:name": "BL3 1BS",
    "wof:placetype": "postalcode"
  },
  "geometry": {"coordinates":[-2.38327,53.561028],"type":"Point"}
}
