{
  "type": "Feature",
  "properties": {
    "iso:country":"GB",
    "wof:name":"LE67 2QD",
    "wof:placetype":"postalcode"
},
  "geometry": {"coordinates":[-1.42209590821352,52.69410333055426],"type":"Point"}
}