{
  "type": "Feature",
  "properties": {
    "iso:country": "GB",
    "wof:name": "TN15 8EJ",
    "wof:placetype": "postalcode"
  },
  "geometry": {"coordinates":[0.311839,51.296066],"type":"Point"}
}
