{
  "type": "Feature",
  "properties": {
    "iso:country":"GB",
    "wof:name":"TN15 8EJ",
    "wof:placetype":"postalcode"
},
  "geometry": {"coordinates":[0.311838751932,51.29606601273419],"type":"Point"}
}