{
  "type": "Feature",
  "properties": {
    "iso:country":"GB",
    "wof:name":"KT14 7PW",
    "wof:placetype":"postalcode"
},
  "geometry": {"coordinates":[-0.47104309333105,51.3396608168472],"type":"Point"}
}