{
  "type": "Feature",
  "properties": {
    "iso:country":"GB",
    "wof:name":"TN21 0NB",
    "wof:placetype":"postalcode"
},
  "geometry": {"coordinates":[0.22603390626643,50.96061778980433],"type":"Point"}
}