{
  "type": "Feature",
  "properties": {
    "iso:country":"GB",
    "wof:name":"WN2 3NQ",
    "wof:placetype":"postalcode"
},
  "geometry": {"coordinates":[-2.58263788740498,53.52784594507155],"type":"Point"}
}