{
  "type": "Feature",
  "properties": {
    "iso:country":"GB",
    "wof:name":"BN6 9UY",
    "wof:placetype":"postalcode"
},
  "geometry": {"coordinates":[-0.17450283015169,50.93391338045502],"type":"Point"}
}