{
  "type": "Feature",
  "properties": {
    "iso:country": "GB",
    "wof:name": "EH39 4QT",
    "wof:placetype": "postalcode"
  },
  "geometry": {"coordinates":[-2.72431,56.053155],"type":"Point"}
}
