{
  "type": "Feature",
  "properties": {
    "date:inception_lower":"1980-01-01",
    "date:inception_upper":"1980-01-31",
    "iso:country":"GB",
    "wof:name":"EH39 4QT",
    "wof:placetype":"postalcode"
},
  "geometry": {"coordinates":[-2.72431,56.053155],"type":"Point"}
}