{
  "type": "Feature",
  "properties": {
    "iso:country":"GB",
    "wof:name":"SY3 7NN",
    "wof:placetype":"postalcode"
},
  "geometry": {"coordinates":[-2.74984674336458,52.69792911295913],"type":"Point"}
}