{
  "type": "Feature",
  "properties": {
    "iso:country":"GB",
    "wof:name":"M16 0NF",
    "wof:placetype":"postalcode"
},
  "geometry": {"coordinates":[-2.275686456659,53.45599803205094],"type":"Point"}
}