{
  "type": "Feature",
  "properties": {
    "date:inception_lower": "1994-05-01",
    "date:inception_upper": "1994-05-01",
    "iso:country": "GB",
    "wof:name": "M16 0NF",
    "wof:placetype": "postalcode"
  },
  "geometry": {"coordinates":[-2.275686,53.455998],"type":"Point"}
}
