{
  "type": "Feature",
  "properties": {
    "iso:country": "GB",
    "wof:name": "SN1 5BY",
    "wof:placetype": "postalcode"
  },
  "geometry": {"coordinates":[-1.788496,51.562644],"type":"Point"}
}
