{
  "type": "Feature",
  "properties": {
    "iso:country":"GB",
    "wof:name":"SN1 5BY",
    "wof:placetype":"postalcode"
},
  "geometry": {"coordinates":[-1.7884962069002,51.56264376959925],"type":"Point"}
}