{
  "type": "Feature",
  "properties": {
    "date:inception_lower": "2008-04-01",
    "date:inception_upper": "2008-04-01",
    "iso:country": "GB",
    "wof:name": "SN1 5BY",
    "wof:placetype": "postalcode"
  },
  "geometry": {"coordinates":[-1.788496,51.562644],"type":"Point"}
}
