{
  "type": "Feature",
  "properties": {
    "iso:country": "GB",
    "wof:name": "WV2 2HJ",
    "wof:placetype": "postalcode"
  },
  "geometry": {"coordinates":[-2.106201,52.56984],"type":"Point"}
}
