{
  "type": "Feature",
  "properties": {
    "date:inception_lower":"1980-01-01",
    "date:inception_upper":"1980-01-31",
    "iso:country":"GB",
    "wof:name":"BD2 2HA",
    "wof:placetype":"postalcode"
},
  "geometry": {"coordinates":[-1.725157,53.81891],"type":"Point"}
}