{
  "type": "Feature",
  "properties": {
    "iso:country": "GB",
    "wof:name": "BD2 2HA",
    "wof:placetype": "postalcode"
  },
  "geometry": {"coordinates":[-1.725157,53.81891],"type":"Point"}
}
