{
  "type": "Feature",
  "properties": {
    "iso:country":"GB",
    "wof:name":"NR29 4NW",
    "wof:placetype":"postalcode"
},
  "geometry": {"coordinates":[1.70565201868196,52.69026019987328],"type":"Point"}
}