{
  "type": "Feature",
  "properties": {
    "iso:country":"GB",
    "wof:name":"IG5 0XL",
    "wof:placetype":"postalcode"
},
  "geometry": {"coordinates":[0.07526193722544,51.59616599062781],"type":"Point"}
}