{
  "type": "Feature",
  "properties": {
    "date:inception_lower": "1995-01-01",
    "date:inception_upper": "1995-01-01",
    "iso:country": "GB",
    "wof:name": "SG5 3PL",
    "wof:placetype": "postalcode"
  },
  "geometry": {"coordinates":[-0.367142,52.001619],"type":"Point"}
}
