{
  "type": "Feature",
  "properties": {
    "iso:country": "GB",
    "wof:name": "BA14 7TQ",
    "wof:placetype": "postalcode"
  },
  "geometry": {"coordinates":[-2.199336,51.338891],"type":"Point"}
}
