{
  "type": "Feature",
  "properties": {
    "iso:country":"GB",
    "wof:name":"BR2 8ER",
    "wof:placetype":"postalcode"
},
  "geometry": {"coordinates":[0.04751999331577,51.38611472542057],"type":"Point"}
}