{
  "type": "Feature",
  "properties": {
    "iso:country":"GB",
    "wof:name":"B19 3XG",
    "wof:placetype":"postalcode"
},
  "geometry": {"coordinates":[-1.9034443459072,52.49137626669226],"type":"Point"}
}