{
  "type": "Feature",
  "properties": {
    "iso:country":"GB",
    "wof:name":"NW2 3XE",
    "wof:placetype":"postalcode"
},
  "geometry": {"coordinates":[-0.21228076566214,51.55309478001094],"type":"Point"}
}