{
  "type": "Feature",
  "properties": {
    "date:inception_lower":"1980-01-01",
    "date:inception_upper":"1980-01-31",
    "iso:country":"GB",
    "wof:name":"NW2 3XE",
    "wof:placetype":"postalcode"
},
  "geometry": {"coordinates":[-0.212281,51.553095],"type":"Point"}
}