{
  "type": "Feature",
  "properties": {
    "iso:country": "GB",
    "wof:name": "NW2 3XE",
    "wof:placetype": "postalcode"
  },
  "geometry": {"coordinates":[-0.212281,51.553095],"type":"Point"}
}
