{
  "type": "Feature",
  "properties": {
    "iso:country":"GB",
    "wof:name":"TN40 1LR",
    "wof:placetype":"postalcode"
},
  "geometry": {"coordinates":[0.48021399983483,50.83892208100637],"type":"Point"}
}