{
  "type": "Feature",
  "properties": {
    "iso:country": "GB",
    "wof:name": "TN40 1LR",
    "wof:placetype": "postalcode"
  },
  "geometry": {"coordinates":[0.480214,50.838922],"type":"Point"}
}
