{
  "type": "Feature",
  "properties": {
    "date:inception_lower": "1980-01-01",
    "date:inception_upper": "1980-01-01",
    "iso:country": "GB",
    "wof:name": "TN40 1LR",
    "wof:placetype": "postalcode"
  },
  "geometry": {"coordinates":[0.480214,50.838922],"type":"Point"}
}
