{
  "type": "Feature",
  "properties": {
    "date:inception_lower": "1980-01-01",
    "date:inception_upper": "1980-01-01",
    "iso:country": "GB",
    "wof:name": "WR6 5BT",
    "wof:placetype": "postalcode"
  },
  "geometry": {"coordinates":[-2.494263,52.122348],"type":"Point"}
}
