{
  "type": "Feature",
  "properties": {
    "iso:country":"GB",
    "wof:name":"WR6 5BT",
    "wof:placetype":"postalcode"
},
  "geometry": {"coordinates":[-2.49415997157373,52.12208552278008],"type":"Point"}
}