{
  "type": "Feature",
  "properties": {
    "date:inception_lower": "1994-06-01",
    "date:inception_upper": "1994-06-01",
    "iso:country": "GB",
    "wof:name": "G68 9NX",
    "wof:placetype": "postalcode"
  },
  "geometry": {"coordinates":[-4.047518,55.944008],"type":"Point"}
}
