{
  "type": "Feature",
  "properties": {
    "iso:country": "GB",
    "wof:name": "TR1 2FQ",
    "wof:placetype": "postalcode"
  },
  "geometry": {"coordinates":[-5.051201,50.264647],"type":"Point"}
}
