{
  "type": "Feature",
  "properties": {
    "iso:country":"GB",
    "wof:name":"GU46 7GA",
    "wof:placetype":"postalcode"
},
  "geometry": {"coordinates":[-0.82843563308898,51.34148704922382],"type":"Point"}
}