{
  "type": "Feature",
  "properties": {
    "iso:country": "GB",
    "wof:name": "M3 2PJ",
    "wof:placetype": "postalcode"
  },
  "geometry": {"coordinates":[-2.24983,53.481834],"type":"Point"}
}
