{
  "type": "Feature",
  "properties": {
    "date:inception_lower": "1995-12-01",
    "date:inception_upper": "1995-12-01",
    "iso:country": "GB",
    "wof:name": "GL51 9NA",
    "wof:placetype": "postalcode"
  },
  "geometry": {"coordinates":[-2.093443,51.918125],"type":"Point"}
}
