{
  "type": "Feature",
  "properties": {
    "iso:country":"GB",
    "wof:name":"IP7 6EF",
    "wof:placetype":"postalcode"
},
  "geometry": {"coordinates":[0.91773094352335,52.05835046331281],"type":"Point"}
}