{
  "type": "Feature",
  "properties": {
    "iso:country": "GB",
    "wof:name": "NR20 5LP",
    "wof:placetype": "postalcode"
  },
  "geometry": {"coordinates":[0.896134,52.761192],"type":"Point"}
}
