{
  "type": "Feature",
  "properties": {
    "iso:country":"GB",
    "wof:name":"SO18 5DW",
    "wof:placetype":"postalcode"
},
  "geometry": {"coordinates":[-1.34401959053834,50.92053847068082],"type":"Point"}
}