{
  "type": "Feature",
  "properties": {
    "iso:country": "GB",
    "wof:name": "ST16 2TB",
    "wof:placetype": "postalcode"
  },
  "geometry": {"coordinates":[-2.126014,52.804864],"type":"Point"}
}
