{
  "type": "Feature",
  "properties": {
    "iso:country":"GB",
    "wof:name":"BD4 6PH",
    "wof:placetype":"postalcode"
},
  "geometry": {"coordinates":[-1.70010700056737,53.75969088210392],"type":"Point"}
}