{
  "type": "Feature",
  "properties": {
    "iso:country":"GB",
    "wof:name":"HX3 7QZ",
    "wof:placetype":"postalcode"
},
  "geometry": {"coordinates":[-1.8105703339468,53.75748032175142],"type":"Point"}
}