{
  "type": "Feature",
  "properties": {
    "iso:country": "GB",
    "wof:name": "OX28 4YQ",
    "wof:placetype": "postalcode"
  },
  "geometry": {"coordinates":[-1.484215,51.775915],"type":"Point"}
}
