{
  "type": "Feature",
  "properties": {
    "iso:country":"GB",
    "wof:name":"EN10 6QZ",
    "wof:placetype":"postalcode"
},
  "geometry": {"coordinates":[-0.01266229583689,51.7400562254837],"type":"Point"}
}