{
  "type": "Feature",
  "properties": {
    "iso:country": "GB",
    "wof:name": "EN10 6QZ",
    "wof:placetype": "postalcode"
  },
  "geometry": {"coordinates":[-0.012662,51.740056],"type":"Point"}
}
