{
  "type": "Feature",
  "properties": {
    "date:inception_lower":"1980-01-01",
    "date:inception_upper":"1980-01-31",
    "iso:country":"GB",
    "wof:name":"EN10 6QZ",
    "wof:placetype":"postalcode"
},
  "geometry": {"coordinates":[-0.012662,51.740056],"type":"Point"}
}