{
  "type": "Feature",
  "properties": {
    "iso:country":"GB",
    "wof:name":"WD25 9RW",
    "wof:placetype":"postalcode"
},
  "geometry": {"coordinates":[-0.38477579142051,51.68670979177205],"type":"Point"}
}