{
  "type": "Feature",
  "properties": {
    "date:inception_lower":"1980-01-01",
    "date:inception_upper":"1980-01-31",
    "iso:country":"GB",
    "wof:name":"PE9 1XH",
    "wof:placetype":"postalcode"
},
  "geometry": {"coordinates":[-0.46508,52.664359],"type":"Point"}
}