{
  "type": "Feature",
  "properties": {
    "iso:country": "GB",
    "wof:name": "IP18 6XF",
    "wof:placetype": "postalcode"
  },
  "geometry": {"coordinates":[1.675381,52.33979],"type":"Point"}
}
