{
  "type": "Feature",
  "properties": {
    "date:inception_lower": "1980-01-01",
    "date:inception_upper": "1980-01-01",
    "iso:country": "GB",
    "wof:name": "IP18 6XF",
    "wof:placetype": "postalcode"
  },
  "geometry": {"coordinates":[1.675381,52.33979],"type":"Point"}
}
