{
  "type": "Feature",
  "properties": {
    "iso:country":"GB",
    "wof:name":"PO35 5YH",
    "wof:placetype":"postalcode"
},
  "geometry": {"coordinates":[-1.08791749015757,50.69193189653128],"type":"Point"}
}