{
  "type": "Feature",
  "properties": {
    "iso:country":"GB",
    "wof:name":"PO30 1XZ",
    "wof:placetype":"postalcode"
},
  "geometry": {"coordinates":[-1.31062989823465,50.68994501344478],"type":"Point"}
}