{
  "type": "Feature",
  "properties": {
    "iso:country":"GB",
    "wof:name":"DA8 3SP",
    "wof:placetype":"postalcode"
},
  "geometry": {"coordinates":[0.16704118649583,51.48003701920187],"type":"Point"}
}