{
  "type": "Feature",
  "properties": {
    "iso:country":"GB",
    "wof:name":"HD6 3SP",
    "wof:placetype":"postalcode"
},
  "geometry": {"coordinates":[-1.77843292865351,53.69073369953001],"type":"Point"}
}