{
  "type": "Feature",
  "properties": {
    "date:inception_lower": "1980-01-01",
    "date:inception_upper": "1980-01-01",
    "iso:country": "GB",
    "wof:name": "NR3 4QB",
    "wof:placetype": "postalcode"
  },
  "geometry": {"coordinates":[1.301289,52.641426],"type":"Point"}
}
