{
  "type": "Feature",
  "properties": {
    "iso:country":"GB",
    "wof:name":"NR3 4QB",
    "wof:placetype":"postalcode"
},
  "geometry": {"coordinates":[1.30128878945095,52.64142628663802],"type":"Point"}
}