{
  "type": "Feature",
  "properties": {
    "iso:country": "GB",
    "wof:name": "BL9 9RE",
    "wof:placetype": "postalcode"
  },
  "geometry": {"coordinates":[-2.293442,53.576005],"type":"Point"}
}
