{
  "type": "Feature",
  "properties": {
    "date:inception_lower": "2014-06-01",
    "date:inception_upper": "2014-06-01",
    "iso:country": "GB",
    "wof:name": "SY21 7GY",
    "wof:placetype": "postalcode"
  },
  "geometry": {"coordinates":[-3.14531,52.667024],"type":"Point"}
}
