{
  "type": "Feature",
  "properties": {
    "iso:country":"GB",
    "wof:name":"SY21 7GY",
    "wof:placetype":"postalcode"
},
  "geometry": {"coordinates":[-3.14530972506511,52.66702376557235],"type":"Point"}
}