{
  "type": "Feature",
  "properties": {
    "date:inception_lower": "1980-01-01",
    "date:inception_upper": "1980-01-01",
    "iso:country": "GB",
    "wof:name": "GU7 3BP",
    "wof:placetype": "postalcode"
  },
  "geometry": {"coordinates":[-0.590869,51.20411],"type":"Point"}
}
