{
  "type": "Feature",
  "properties": {
    "iso:country":"GB",
    "wof:name":"GU7 3BP",
    "wof:placetype":"postalcode"
},
  "geometry": {"coordinates":[-0.59086860101504,51.20411026712138],"type":"Point"}
}