{
  "type": "Feature",
  "properties": {
    "iso:country":"GB",
    "wof:name":"B90 3JT",
    "wof:placetype":"postalcode"
},
  "geometry": {"coordinates":[-1.82230036701944,52.41645856918085],"type":"Point"}
}