{
  "type": "Feature",
  "properties": {
    "date:inception_lower":"1996-12-01",
    "date:inception_upper":"1996-12-31",
    "iso:country":"GB",
    "wof:name":"LN8 2AX",
    "wof:placetype":"postalcode"
},
  "geometry": {"coordinates":[-0.5419,53.407087],"type":"Point"}
}