{
  "type": "Feature",
  "properties": {
    "iso:country":"GB",
    "wof:name":"FK10 2AG",
    "wof:placetype":"postalcode"
},
  "geometry": {"coordinates":[-3.79052754423793,56.11859863361936],"type":"Point"}
}