{
  "type": "Feature",
  "properties": {
    "date:inception_lower": "2020-11-01",
    "date:inception_upper": "2020-11-01",
    "iso:country": "GB",
    "wof:name": "LS27 0GH",
    "wof:placetype": "postalcode"
  },
  "geometry": {"coordinates":[-1.619834,53.73868],"type":"Point"}
}
