{
  "type": "Feature",
  "properties": {
    "date:inception_lower": "1995-12-01",
    "date:inception_upper": "1995-12-01",
    "iso:country": "GB",
    "wof:name": "S5 0DQ",
    "wof:placetype": "postalcode"
  },
  "geometry": {"coordinates":[-1.435268,53.436979],"type":"Point"}
}
