{
  "type": "Feature",
  "properties": {
    "iso:country":"GB",
    "wof:name":"S36 9QG",
    "wof:placetype":"postalcode"
},
  "geometry": {"coordinates":[-1.6488920018095,53.52914747005588],"type":"Point"}
}