{
  "type": "Feature",
  "properties": {
    "iso:country":"GB",
    "wof:name":"HG3 5SE",
    "wof:placetype":"postalcode"
},
  "geometry": {"coordinates":[-1.83526924689223,54.15847715124701],"type":"Point"}
}