{
  "type": "Feature",
  "properties": {
    "iso:country": "GB",
    "wof:name": "BA16 0SA",
    "wof:placetype": "postalcode"
  },
  "geometry": {"coordinates":[-2.731746,51.121325],"type":"Point"}
}
