{
  "type": "Feature",
  "properties": {
    "iso:country":"GB",
    "wof:name":"IP2 9JA",
    "wof:placetype":"postalcode"
},
  "geometry": {"coordinates":[1.12407203584488,52.04071751470931],"type":"Point"}
}