{
  "type": "Feature",
  "properties": {
    "date:inception_lower": "2005-06-01",
    "date:inception_upper": "2005-06-01",
    "iso:country": "GB",
    "wof:name": "CV8 3LJ",
    "wof:placetype": "postalcode"
  },
  "geometry": {"coordinates":[-1.396352,52.37999],"type":"Point"}
}
