{
  "type": "Feature",
  "properties": {
    "iso:country":"GB",
    "wof:name":"CV8 3LJ",
    "wof:placetype":"postalcode"
},
  "geometry": {"coordinates":[-1.396351554192,52.37999036542627],"type":"Point"}
}