{
  "type": "Feature",
  "properties": {
    "iso:country":"GB",
    "wof:name":"EX2 5NQ",
    "wof:placetype":"postalcode"
},
  "geometry": {"coordinates":[-3.49212017325948,50.71723189154455],"type":"Point"}
}