{
  "type": "Feature",
  "properties": {
    "iso:country":"GB",
    "wof:name":"CF11 8XB",
    "wof:placetype":"postalcode"
},
  "geometry": {"coordinates":[-3.21208019374276,51.47623789211056],"type":"Point"}
}