{
  "type": "Feature",
  "properties": {
    "date:inception_lower": "1980-01-01",
    "date:inception_upper": "1980-01-01",
    "iso:country": "GB",
    "wof:name": "PO11 0LE",
    "wof:placetype": "postalcode"
  },
  "geometry": {"coordinates":[-0.9795,50.816339],"type":"Point"}
}
