{
  "type": "Feature",
  "properties": {
    "iso:country": "GB",
    "wof:name": "LL57 1RP",
    "wof:placetype": "postalcode"
  },
  "geometry": {"coordinates":[-4.125557,53.22679],"type":"Point"}
}
