{
  "type": "Feature",
  "properties": {
    "date:inception_lower":"1980-01-01",
    "date:inception_upper":"1980-01-31",
    "iso:country":"GB",
    "wof:name":"LL57 1RP",
    "wof:placetype":"postalcode"
},
  "geometry": {"coordinates":[-4.125557,53.22679],"type":"Point"}
}