{
  "type": "Feature",
  "properties": {
    "date:inception_lower":"2015-11-01",
    "date:inception_upper":"2015-11-30",
    "iso:country":"GB",
    "wof:name":"HU12 8FR",
    "wof:placetype":"postalcode"
},
  "geometry": {"coordinates":[-0.210123,53.741706],"type":"Point"}
}