{
  "type": "Feature",
  "properties": {
    "iso:country":"GB",
    "wof:name":"HU12 8FR",
    "wof:placetype":"postalcode"
},
  "geometry": {"coordinates":[-0.2101229467156,53.74170649485093],"type":"Point"}
}