{
  "type": "Feature",
  "properties": {
    "iso:country":"GB",
    "wof:name":"S41 7BA",
    "wof:placetype":"postalcode"
},
  "geometry": {"coordinates":[-1.44052544499134,53.247224035451],"type":"Point"}
}