{
  "type": "Feature",
  "properties": {
    "date:inception_lower": "1985-11-01",
    "date:inception_upper": "1985-11-01",
    "iso:country": "GB",
    "wof:name": "KA7 3JE",
    "wof:placetype": "postalcode"
  },
  "geometry": {"coordinates":[-4.608432,55.451502],"type":"Point"}
}
