{
  "type": "Feature",
  "properties": {
    "iso:country":"GB",
    "wof:name":"KA7 3JE",
    "wof:placetype":"postalcode"
},
  "geometry": {"coordinates":[-4.60843191773743,55.45150249483639],"type":"Point"}
}