{
  "type": "Feature",
  "properties": {
    "date:inception_lower":"1980-01-01",
    "date:inception_upper":"1980-01-31",
    "iso:country":"GB",
    "wof:name":"BD2 4PU",
    "wof:placetype":"postalcode"
},
  "geometry": {"coordinates":[-1.74298,53.810528],"type":"Point"}
}