{
  "type": "Feature",
  "properties": {
    "iso:country":"GB",
    "wof:name":"BD2 4PU",
    "wof:placetype":"postalcode"
},
  "geometry": {"coordinates":[-1.74298015867138,53.81052764007096],"type":"Point"}
}