{
  "type": "Feature",
  "properties": {
    "iso:country":"GB",
    "wof:name":"DH5 8AX",
    "wof:placetype":"postalcode"
},
  "geometry": {"coordinates":[-1.46661958273058,54.84478204682706],"type":"Point"}
}