{
  "type": "Feature",
  "properties": {
    "iso:country":"GB",
    "wof:name":"BS13 0BW",
    "wof:placetype":"postalcode"
},
  "geometry": {"coordinates":[-2.60357827980855,51.40449383344928],"type":"Point"}
}