{
  "type": "Feature",
  "properties": {
    "iso:country":"GB",
    "wof:name":"OL4 2PN",
    "wof:placetype":"postalcode"
},
  "geometry": {"coordinates":[-2.07852810516371,53.55427324979647],"type":"Point"}
}