{
  "type": "Feature",
  "properties": {
    "iso:country": "GB",
    "wof:name": "OL4 2PN",
    "wof:placetype": "postalcode"
  },
  "geometry": {"coordinates":[-2.078528,53.554273],"type":"Point"}
}
