{
  "type": "Feature",
  "properties": {
    "date:inception_lower": "1980-01-01",
    "date:inception_upper": "1980-01-01",
    "iso:country": "GB",
    "wof:name": "ML2 9NA",
    "wof:placetype": "postalcode"
  },
  "geometry": {"coordinates":[-3.870883,55.78974],"type":"Point"}
}
