{
  "type": "Feature",
  "properties": {
    "iso:country": "GB",
    "wof:name": "ML2 9NA",
    "wof:placetype": "postalcode"
  },
  "geometry": {"coordinates":[-3.870883,55.78974],"type":"Point"}
}
