{
  "type": "Feature",
  "properties": {
    "iso:country":"GB",
    "wof:name":"SS8 9RE",
    "wof:placetype":"postalcode"
},
  "geometry": {"coordinates":[0.57767039887863,51.53203712469823],"type":"Point"}
}