{
  "type": "Feature",
  "properties": {
    "iso:country": "GB",
    "wof:name": "ST7 3NZ",
    "wof:placetype": "postalcode"
  },
  "geometry": {"coordinates":[-2.21632,53.111501],"type":"Point"}
}
