{
  "type": "Feature",
  "properties": {
    "iso:country":"GB",
    "wof:name":"NR29 3HY",
    "wof:placetype":"postalcode"
},
  "geometry": {"coordinates":[1.67120123867722,52.66005937674562],"type":"Point"}
}