{
  "type": "Feature",
  "properties": {
    "iso:country":"GB",
    "wof:name":"BN2 5RP",
    "wof:placetype":"postalcode"
},
  "geometry": {"coordinates":[-0.0919618841354,50.81475259149517],"type":"Point"}
}