{
  "type": "Feature",
  "properties": {
    "iso:country": "GB",
    "wof:name": "BN2 5RP",
    "wof:placetype": "postalcode"
  },
  "geometry": {"coordinates":[-0.091962,50.814753],"type":"Point"}
}
