{
  "type": "Feature",
  "properties": {
    "iso:country":"GB",
    "wof:name":"CV37 0PZ",
    "wof:placetype":"postalcode"
},
  "geometry": {"coordinates":[-1.67299103104663,52.2233445560343],"type":"Point"}
}