{
  "type": "Feature",
  "properties": {
    "date:inception_lower":"2002-06-01",
    "date:inception_upper":"2002-06-30",
    "iso:country":"GB",
    "wof:name":"DL17 0RR",
    "wof:placetype":"postalcode"
},
  "geometry": {"coordinates":[-1.562731,54.660186],"type":"Point"}
}