{
  "type": "Feature",
  "properties": {
    "iso:country":"GB",
    "wof:name":"DL17 0RR",
    "wof:placetype":"postalcode"
},
  "geometry": {"coordinates":[-1.56273139257666,54.66018558855152],"type":"Point"}
}