{
  "type": "Feature",
  "properties": {
    "iso:country": "GB",
    "wof:name": "IG8 9JT",
    "wof:placetype": "postalcode"
  },
  "geometry": {"coordinates":[0.022313,51.604572],"type":"Point"}
}
