{
  "type": "Feature",
  "properties": {
    "date:inception_lower":"1995-07-01",
    "date:inception_upper":"1995-07-31",
    "iso:country":"GB",
    "wof:name":"PE7 1HP",
    "wof:placetype":"postalcode"
},
  "geometry": {"coordinates":[-0.132686,52.559077],"type":"Point"}
}