{
  "type": "Feature",
  "properties": {
    "iso:country":"GB",
    "wof:name":"NW2 2PG",
    "wof:placetype":"postalcode"
},
  "geometry": {"coordinates":[-0.19789313573321,51.55982578974016],"type":"Point"}
}