{
  "type": "Feature",
  "properties": {
    "iso:country":"GB",
    "wof:name":"TQ12 5SX",
    "wof:placetype":"postalcode"
},
  "geometry": {"coordinates":[-3.63873558048965,50.48941619053397],"type":"Point"}
}