{
  "type": "Feature",
  "properties": {
    "iso:country":"GB",
    "wof:name":"NW9 5PT",
    "wof:placetype":"postalcode"
},
  "geometry": {"coordinates":[-0.2438645175853,51.59967529014801],"type":"Point"}
}