{
  "type": "Feature",
  "properties": {
    "date:inception_lower": "1980-01-01",
    "date:inception_upper": "1980-01-01",
    "iso:country": "GB",
    "wof:name": "B49 5LS",
    "wof:placetype": "postalcode"
  },
  "geometry": {"coordinates":[-1.936831,52.21866],"type":"Point"}
}
