{
  "type": "Feature",
  "properties": {
    "iso:country":"GB",
    "wof:name":"B49 5LS",
    "wof:placetype":"postalcode"
},
  "geometry": {"coordinates":[-1.93834551235199,52.21871027822202],"type":"Point"}
}