{
  "type": "Feature",
  "properties": {
    "iso:country":"GB",
    "wof:name":"MK6 5BU",
    "wof:placetype":"postalcode"
},
  "geometry": {"coordinates":[-0.73548758692607,52.03057834801564],"type":"Point"}
}