{
  "type": "Feature",
  "properties": {
    "iso:country":"GB",
    "wof:name":"CM0 7RH",
    "wof:placetype":"postalcode"
},
  "geometry": {"coordinates":[0.79999221883585,51.69223494242404],"type":"Point"}
}