{
  "type": "Feature",
  "properties": {
    "date:inception_lower": "1996-06-01",
    "date:inception_upper": "1996-06-01",
    "iso:country": "GB",
    "wof:name": "HS6 5BF",
    "wof:placetype": "postalcode"
  },
  "geometry": {"coordinates":[-7.174033,57.719219],"type":"Point"}
}
