{
  "type": "Feature",
  "properties": {
    "iso:country":"GB",
    "wof:name":"HS6 5BF",
    "wof:placetype":"postalcode"
},
  "geometry": {"coordinates":[-7.17403343588867,57.71921938366616],"type":"Point"}
}