{
  "type": "Feature",
  "properties": {
    "date:inception_lower":"1980-01-01",
    "date:inception_upper":"1980-01-31",
    "iso:country":"GB",
    "wof:name":"CT21 6DP",
    "wof:placetype":"postalcode"
},
  "geometry": {"coordinates":[1.082903,51.065774],"type":"Point"}
}