{
  "type": "Feature",
  "properties": {
    "iso:country": "GB",
    "wof:name": "CT21 6DP",
    "wof:placetype": "postalcode"
  },
  "geometry": {"coordinates":[1.082903,51.065774],"type":"Point"}
}
