{
  "type": "Feature",
  "properties": {
    "iso:country":"GB",
    "wof:name":"RG12 7RD",
    "wof:placetype":"postalcode"
},
  "geometry": {"coordinates":[-0.76540340051375,51.39080904214943],"type":"Point"}
}