{
  "type": "Feature",
  "properties": {
    "iso:country":"GB",
    "wof:name":"PA14 6QX",
    "wof:placetype":"postalcode"
},
  "geometry": {"coordinates":[-4.65543106464418,55.93117711836113],"type":"Point"}
}