{
  "type": "Feature",
  "properties": {
    "iso:country":"GB",
    "wof:name":"BL9 0NU",
    "wof:placetype":"postalcode"
},
  "geometry": {"coordinates":[-2.29592103742355,53.59359799135318],"type":"Point"}
}