{
  "type": "Feature",
  "properties": {
    "iso:country":"GB",
    "wof:name":"CF23 5LU",
    "wof:placetype":"postalcode"
},
  "geometry": {"coordinates":[-3.16601585201783,51.50273663736665],"type":"Point"}
}