{
  "type": "Feature",
  "properties": {
    "date:inception_lower":"2007-04-01",
    "date:inception_upper":"2007-04-30",
    "iso:country":"GB",
    "wof:name":"SO51 7UT",
    "wof:placetype":"postalcode"
},
  "geometry": {"coordinates":[-1.482706,50.993183],"type":"Point"}
}