{
  "type": "Feature",
  "properties": {
    "date:inception_lower": "2023-11-01",
    "date:inception_upper": "2023-11-01",
    "iso:country": "GB",
    "wof:name": "SO51 7UT",
    "wof:placetype": "postalcode"
  },
  "geometry": {"coordinates":[-1.471767,50.998217],"type":"Point"}
}
