{
  "type": "Feature",
  "properties": {
    "iso:country":"GB",
    "wof:name":"G32 6EQ",
    "wof:placetype":"postalcode"
},
  "geometry": {"coordinates":[-4.18774787819339,55.85864479431587],"type":"Point"}
}