{
  "type": "Feature",
  "properties": {
    "iso:country":"GB",
    "wof:name":"WV10 9JY",
    "wof:placetype":"postalcode"
},
  "geometry": {"coordinates":[-2.12298414568707,52.60923523827749],"type":"Point"}
}