{
  "type": "Feature",
  "properties": {
    "date:inception_lower":"1995-01-01",
    "date:inception_upper":"1995-01-31",
    "iso:country":"GB",
    "wof:name":"WV10 9JY",
    "wof:placetype":"postalcode"
},
  "geometry": {"coordinates":[-2.122984,52.609235],"type":"Point"}
}