{
  "type": "Feature",
  "properties": {
    "iso:country":"GB",
    "wof:name":"HU16 4JW",
    "wof:placetype":"postalcode"
},
  "geometry": {"coordinates":[-0.39903813026199,53.79810659429941],"type":"Point"}
}