{
  "type": "Feature",
  "properties": {
    "iso:country": "GB",
    "wof:name": "CH41 6JA",
    "wof:placetype": "postalcode"
  },
  "geometry": {"coordinates":[-3.019515,53.394094],"type":"Point"}
}
