{
  "type": "Feature",
  "properties": {
    "iso:country":"GB",
    "wof:name":"CH65 6TW",
    "wof:placetype":"postalcode"
},
  "geometry": {"coordinates":[-2.90388155899777,53.26606058267814],"type":"Point"}
}