{
  "type": "Feature",
  "properties": {
    "iso:country":"GB",
    "wof:name":"SE18 7AF",
    "wof:placetype":"postalcode"
},
  "geometry": {"coordinates":[0.08411137428326,51.48913944434769],"type":"Point"}
}