{
  "type": "Feature",
  "properties": {
    "date:inception_lower": "2010-06-01",
    "date:inception_upper": "2010-06-01",
    "iso:country": "GB",
    "wof:name": "SE18 7AF",
    "wof:placetype": "postalcode"
  },
  "geometry": {"coordinates":[0.084111,51.489139],"type":"Point"}
}
