{
  "type": "Feature",
  "properties": {
    "iso:country": "GB",
    "wof:name": "CF5 1NZ",
    "wof:placetype": "postalcode"
  },
  "geometry": {"coordinates":[-3.201262,51.480459],"type":"Point"}
}
