{
  "type": "Feature",
  "properties": {
    "iso:country":"GB",
    "wof:name":"CF5 1NZ",
    "wof:placetype":"postalcode"
},
  "geometry": {"coordinates":[-3.20126196984979,51.4804585578694],"type":"Point"}
}