{
  "type": "Feature",
  "properties": {
    "iso:country":"GB",
    "wof:name":"YO26 4ZP",
    "wof:placetype":"postalcode"
},
  "geometry": {"coordinates":[-1.09097124759462,53.96011372438956],"type":"Point"}
}