{
  "type": "Feature",
  "properties": {
    "iso:country": "GB",
    "wof:name": "YO26 4ZP",
    "wof:placetype": "postalcode"
  },
  "geometry": {"coordinates":[-1.090971,53.960114],"type":"Point"}
}
