{
  "type": "Feature",
  "properties": {
    "iso:country": "GB",
    "wof:name": "LN1 1NA",
    "wof:placetype": "postalcode"
  },
  "geometry": {"coordinates":[-0.552396,53.23511],"type":"Point"}
}
