{
  "type": "Feature",
  "properties": {
    "iso:country":"GB",
    "wof:name":"PL10 1EA",
    "wof:placetype":"postalcode"
},
  "geometry": {"coordinates":[-4.20955468100895,50.34695779871803],"type":"Point"}
}