{
  "type": "Feature",
  "properties": {
    "iso:country":"GB",
    "wof:name":"PR8 2DF",
    "wof:placetype":"postalcode"
},
  "geometry": {"coordinates":[-3.02397553333393,53.63896453331439],"type":"Point"}
}