{
  "type": "Feature",
  "properties": {
    "iso:country":"GB",
    "wof:name":"B78 2LS",
    "wof:placetype":"postalcode"
},
  "geometry": {"coordinates":[-1.68239339288366,52.56289130289879],"type":"Point"}
}