{
  "type": "Feature",
  "properties": {
    "date:inception_lower": "2018-01-01",
    "date:inception_upper": "2018-01-01",
    "iso:country": "GB",
    "wof:name": "PE29 2PA",
    "wof:placetype": "postalcode"
  },
  "geometry": {"coordinates":[-0.163467,52.312144],"type":"Point"}
}
