{
  "type": "Feature",
  "properties": {
    "iso:country":"GB",
    "wof:name":"L69 3GS",
    "wof:placetype":"postalcode"
},
  "geometry": {"coordinates":[-2.96912641929158,53.40686439849028],"type":"Point"}
}