{
  "type": "Feature",
  "properties": {
    "iso:country":"GB",
    "wof:name":"CW9 7DD",
    "wof:placetype":"postalcode"
},
  "geometry": {"coordinates":[-2.49054168964839,53.2584827137918],"type":"Point"}
}