{
  "type": "Feature",
  "properties": {
    "iso:country":"GB",
    "wof:name":"LA8 9BY",
    "wof:placetype":"postalcode"
},
  "geometry": {"coordinates":[-2.62612327313883,54.36335673907743],"type":"Point"}
}