{
  "type": "Feature",
  "properties": {
    "iso:country": "GB",
    "wof:name": "LA8 9BY",
    "wof:placetype": "postalcode"
  },
  "geometry": {"coordinates":[-2.626123,54.363357],"type":"Point"}
}
