{
  "type": "Feature",
  "properties": {
    "iso:country":"GB",
    "wof:name":"PE30 4JJ",
    "wof:placetype":"postalcode"
},
  "geometry": {"coordinates":[0.41530493352521,52.74245079091589],"type":"Point"}
}