{
  "type": "Feature",
  "properties": {
    "date:inception_lower": "1981-06-01",
    "date:inception_upper": "1981-06-01",
    "iso:country": "GB",
    "wof:name": "PE30 5NF",
    "wof:placetype": "postalcode"
  },
  "geometry": {"coordinates":[0.403727,52.748513],"type":"Point"}
}
