{
  "type": "Feature",
  "properties": {
    "iso:country": "GB",
    "wof:name": "PE30 5NF",
    "wof:placetype": "postalcode"
  },
  "geometry": {"coordinates":[0.403727,52.748513],"type":"Point"}
}
