{
  "type": "Feature",
  "properties": {
    "iso:country":"GB",
    "wof:name":"PE30 5NF",
    "wof:placetype":"postalcode"
},
  "geometry": {"coordinates":[0.40372665971352,52.74851269750188],"type":"Point"}
}