{
  "type": "Feature",
  "properties": {
    "date:inception_lower": "2011-12-01",
    "date:inception_upper": "2011-12-01",
    "iso:country": "GB",
    "wof:name": "BN7 9HX",
    "wof:placetype": "postalcode"
  },
  "geometry": {"coordinates":[0.016199,50.879369],"type":"Point"}
}
