{
  "type": "Feature",
  "properties": {
    "iso:country":"GB",
    "wof:name":"NP26 4GT",
    "wof:placetype":"postalcode"
},
  "geometry": {"coordinates":[-2.75062121550411,51.59219870409538],"type":"Point"}
}