{
  "type": "Feature",
  "properties": {
    "date:inception_lower": "2001-06-01",
    "date:inception_upper": "2001-06-01",
    "iso:country": "GB",
    "wof:name": "BA2 7LN",
    "wof:placetype": "postalcode"
  },
  "geometry": {"coordinates":[-2.324285,51.301997],"type":"Point"}
}
