{
  "type": "Feature",
  "properties": {
    "iso:country":"GB",
    "wof:name":"BA2 7LN",
    "wof:placetype":"postalcode"
},
  "geometry": {"coordinates":[-2.324285003597,51.3019973579521],"type":"Point"}
}