{
  "type": "Feature",
  "properties": {
    "iso:country":"GB",
    "wof:name":"AB11 8BP",
    "wof:placetype":"postalcode"
},
  "geometry": {"coordinates":[-2.09065174454507,57.13600127526567],"type":"Point"}
}