{
  "type": "Feature",
  "properties": {
    "iso:country":"GB",
    "wof:name":"HA3 7PP",
    "wof:placetype":"postalcode"
},
  "geometry": {"coordinates":[-0.32375529917901,51.59578075507585],"type":"Point"}
}