{
  "type": "Feature",
  "properties": {
    "iso:country":"GB",
    "wof:name":"DE1 3AZ",
    "wof:placetype":"postalcode"
},
  "geometry": {"coordinates":[-1.48075070538374,52.92932548198482],"type":"Point"}
}