{
  "type": "Feature",
  "properties": {
    "iso:country":"GB",
    "wof:name":"RG2 8DH",
    "wof:placetype":"postalcode"
},
  "geometry": {"coordinates":[-0.96116585309105,51.42783005135667],"type":"Point"}
}