{
  "type": "Feature",
  "properties": {
    "iso:country":"GB",
    "wof:name":"LS27 0HP",
    "wof:placetype":"postalcode"
},
  "geometry": {"coordinates":[-1.58995987430852,53.73442300045254],"type":"Point"}
}