{
  "type": "Feature",
  "properties": {
    "iso:country":"GB",
    "wof:name":"NE4 9BD",
    "wof:placetype":"postalcode"
},
  "geometry": {"coordinates":[-1.64709814640502,54.98270660276054],"type":"Point"}
}