{
  "type": "Feature",
  "properties": {
    "iso:country": "GB",
    "wof:name": "HP6 5QQ",
    "wof:placetype": "postalcode"
  },
  "geometry": {"coordinates":[-0.61922,51.682884],"type":"Point"}
}
