{
  "type": "Feature",
  "properties": {
    "iso:country":"GB",
    "wof:name":"HP6 5QQ",
    "wof:placetype":"postalcode"
},
  "geometry": {"coordinates":[-0.61922021402073,51.68288352247546],"type":"Point"}
}