{
  "type": "Feature",
  "properties": {
    "date:inception_lower":"2012-05-01",
    "date:inception_upper":"2012-05-31",
    "iso:country":"GB",
    "wof:name":"NE13 9BN",
    "wof:placetype":"postalcode"
},
  "geometry": {"coordinates":[-1.65162,55.0289],"type":"Point"}
}