{
  "type": "Feature",
  "properties": {
    "iso:country":"GB",
    "wof:name":"NE13 9BN",
    "wof:placetype":"postalcode"
},
  "geometry": {"coordinates":[-1.65162041183037,55.02889972132626],"type":"Point"}
}