{
  "type": "Feature",
  "properties": {
    "iso:country":"GB",
    "wof:name":"GL5 1EB",
    "wof:placetype":"postalcode"
},
  "geometry": {"coordinates":[-2.20597655551892,51.74273823638605],"type":"Point"}
}