{
  "type": "Feature",
  "properties": {
    "iso:country": "GB",
    "wof:name": "GL5 1EB",
    "wof:placetype": "postalcode"
  },
  "geometry": {"coordinates":[-2.205977,51.742738],"type":"Point"}
}
