{
  "type": "Feature",
  "properties": {
    "iso:country":"GB",
    "wof:name":"PO30 5AJ",
    "wof:placetype":"postalcode"
},
  "geometry": {"coordinates":[-1.32172924378311,50.70072056320765],"type":"Point"}
}