{
  "type": "Feature",
  "properties": {
    "date:inception_lower": "1983-07-01",
    "date:inception_upper": "1983-07-01",
    "iso:country": "GB",
    "wof:name": "PO30 5AJ",
    "wof:placetype": "postalcode"
  },
  "geometry": {"coordinates":[-1.321791,50.700656],"type":"Point"}
}
