{
  "type": "Feature",
  "properties": {
    "date:inception_lower": "2019-04-01",
    "date:inception_upper": "2019-04-01",
    "iso:country": "GB",
    "wof:name": "M14 6NJ",
    "wof:placetype": "postalcode"
  },
  "geometry": {"coordinates":[-2.219348,53.441507],"type":"Point"}
}
