{
  "type": "Feature",
  "properties": {
    "iso:country":"GB",
    "wof:name":"EX13 5UN",
    "wof:placetype":"postalcode"
},
  "geometry": {"coordinates":[-2.92306811949021,50.7837034485196],"type":"Point"}
}