{
  "type": "Feature",
  "properties": {
    "iso:country": "GB",
    "wof:name": "EX13 5UN",
    "wof:placetype": "postalcode"
  },
  "geometry": {"coordinates":[-2.923068,50.783703],"type":"Point"}
}
