{
  "type": "Feature",
  "properties": {
    "date:inception_lower": "1980-01-01",
    "date:inception_upper": "1980-01-01",
    "iso:country": "GB",
    "wof:name": "EX13 5UN",
    "wof:placetype": "postalcode"
  },
  "geometry": {"coordinates":[-2.923068,50.783703],"type":"Point"}
}
