{
  "type": "Feature",
  "properties": {
    "date:inception_lower": "2020-11-01",
    "date:inception_upper": "2020-11-01",
    "iso:country": "GB",
    "wof:name": "M16 8QS",
    "wof:placetype": "postalcode"
  },
  "geometry": {"coordinates":[-2.253628,53.446617],"type":"Point"}
}
