{
  "type": "Feature",
  "properties": {
    "date:inception_lower": "1980-01-01",
    "date:inception_upper": "1980-01-01",
    "iso:country": "GB",
    "wof:name": "NP4 9AP",
    "wof:placetype": "postalcode"
  },
  "geometry": {"coordinates":[-3.084499,51.771712],"type":"Point"}
}
