{
  "type": "Feature",
  "properties": {
    "iso:country":"GB",
    "wof:name":"BH18 0BH",
    "wof:placetype":"postalcode"
},
  "geometry": {"coordinates":[-1.97393915775618,50.74666336319211],"type":"Point"}
}