{
  "type": "Feature",
  "properties": {
    "date:inception_lower":"2018-11-01",
    "date:inception_upper":"2018-11-30",
    "iso:country":"GB",
    "wof:name":"BH18 0BH",
    "wof:placetype":"postalcode"
},
  "geometry": {"coordinates":[-1.973932,50.746653],"type":"Point"}
}