{
  "type": "Feature",
  "properties": {
    "iso:country":"GB",
    "wof:name":"SL1 3PD",
    "wof:placetype":"postalcode"
},
  "geometry": {"coordinates":[-0.60004863852686,51.51776280635985],"type":"Point"}
}