{
  "type": "Feature",
  "properties": {
    "iso:country":"GB",
    "wof:name":"OX15 4NX",
    "wof:placetype":"postalcode"
},
  "geometry": {"coordinates":[-1.36818988457352,52.02587758038723],"type":"Point"}
}