{
  "type": "Feature",
  "properties": {
    "iso:country": "GB",
    "wof:name": "OX15 4NX",
    "wof:placetype": "postalcode"
  },
  "geometry": {"coordinates":[-1.36819,52.025878],"type":"Point"}
}
