{
  "type": "Feature",
  "properties": {
    "date:inception_lower": "2000-12-01",
    "date:inception_upper": "2000-12-01",
    "iso:country": "GB",
    "wof:name": "KT18 5UX",
    "wof:placetype": "postalcode"
  },
  "geometry": {"coordinates":[-0.232362,51.315592],"type":"Point"}
}
