{
  "type": "Feature",
  "properties": {
    "iso:country":"GB",
    "wof:name":"DT3 6AX",
    "wof:placetype":"postalcode"
},
  "geometry": {"coordinates":[-2.45375365103924,50.64447893832864],"type":"Point"}
}