{
  "type": "Feature",
  "properties": {
    "iso:country":"GB",
    "wof:name":"GU21 2HY",
    "wof:placetype":"postalcode"
},
  "geometry": {"coordinates":[-0.61546169610004,51.32192544787028],"type":"Point"}
}