{
  "type": "Feature",
  "properties": {
    "iso:country":"GB",
    "wof:name":"M35 0SL",
    "wof:placetype":"postalcode"
},
  "geometry": {"coordinates":[-2.15666640289759,53.50790615985401],"type":"Point"}
}