{
  "type": "Feature",
  "properties": {
    "iso:country":"GB",
    "wof:name":"RG17 0AJ",
    "wof:placetype":"postalcode"
},
  "geometry": {"coordinates":[-1.51777060609841,51.40759403736656],"type":"Point"}
}