{
  "type": "Feature",
  "properties": {
    "iso:country":"GB",
    "wof:name":"LU1 3EU",
    "wof:placetype":"postalcode"
},
  "geometry": {"coordinates":[-0.41013517593826,51.87644183830479],"type":"Point"}
}