{
  "type": "Feature",
  "properties": {
    "iso:country": "GB",
    "wof:name": "LU1 3EU",
    "wof:placetype": "postalcode"
  },
  "geometry": {"coordinates":[-0.410135,51.876442],"type":"Point"}
}
