{
  "type": "Feature",
  "properties": {
    "date:inception_lower": "1980-01-01",
    "date:inception_upper": "1980-01-01",
    "iso:country": "GB",
    "wof:name": "M33 3PA",
    "wof:placetype": "postalcode"
  },
  "geometry": {"coordinates":[-2.319556,53.409957],"type":"Point"}
}
