{
  "type": "Feature",
  "properties": {
    "iso:country":"GB",
    "wof:name":"M33 3PA",
    "wof:placetype":"postalcode"
},
  "geometry": {"coordinates":[-2.31955558674703,53.40995718579939],"type":"Point"}
}