{
  "type": "Feature",
  "properties": {
    "date:inception_lower": "1997-06-01",
    "date:inception_upper": "1997-06-01",
    "iso:country": "GB",
    "wof:name": "DA2 7DU",
    "wof:placetype": "postalcode"
  },
  "geometry": {"coordinates":[0.19977,51.428086],"type":"Point"}
}
