{
  "type": "Feature",
  "properties": {
    "iso:country":"GB",
    "wof:name":"DA2 7DU",
    "wof:placetype":"postalcode"
},
  "geometry": {"coordinates":[0.19976980782075,51.42808639476946],"type":"Point"}
}