{
  "type": "Feature",
  "properties": {
    "iso:country": "GB",
    "wof:name": "AB44 1XE",
    "wof:placetype": "postalcode"
  },
  "geometry": {"coordinates":[-2.499692,57.667576],"type":"Point"}
}
