{
  "type": "Feature",
  "properties": {
    "iso:country":"GB",
    "wof:name":"AB44 1XE",
    "wof:placetype":"postalcode"
},
  "geometry": {"coordinates":[-2.49968953968583,57.66759152074278],"type":"Point"}
}