{
  "type": "Feature",
  "properties": {
    "iso:country":"GB",
    "wof:name":"KA17 0HF",
    "wof:placetype":"postalcode"
},
  "geometry": {"coordinates":[-4.28967639069632,55.60888212293573],"type":"Point"}
}