{
  "type": "Feature",
  "properties": {
    "iso:country":"GB",
    "wof:name":"SS6 8PF",
    "wof:placetype":"postalcode"
},
  "geometry": {"coordinates":[0.61710837487275,51.58203978855784],"type":"Point"}
}