{
  "type": "Feature",
  "properties": {
    "iso:country":"GB",
    "wof:name":"EX8 4JY",
    "wof:placetype":"postalcode"
},
  "geometry": {"coordinates":[-3.38900962782829,50.63771991360631],"type":"Point"}
}