{
  "type": "Feature",
  "properties": {
    "date:inception_lower": "2021-01-01",
    "date:inception_upper": "2021-01-01",
    "iso:country": "GB",
    "wof:name": "TA14 6AG",
    "wof:placetype": "postalcode"
  },
  "geometry": {"coordinates":[-2.757816,50.94161],"type":"Point"}
}
