{
  "type": "Feature",
  "properties": {
    "date:inception_lower": "2022-02-01",
    "date:inception_upper": "2022-02-01",
    "iso:country": "GB",
    "wof:name": "HA0 1NT",
    "wof:placetype": "postalcode"
  },
  "geometry": {"coordinates":[-0.285871,51.541057],"type":"Point"}
}
