{
  "type": "Feature",
  "properties": {
    "date:inception_lower": "1980-01-01",
    "date:inception_upper": "1980-01-01",
    "iso:country": "GB",
    "wof:name": "LL18 5HH",
    "wof:placetype": "postalcode"
  },
  "geometry": {"coordinates":[-3.514078,53.300351],"type":"Point"}
}
