{
  "type": "Feature",
  "properties": {
    "date:inception_lower": "2024-08-01",
    "date:inception_upper": "2024-08-01",
    "iso:country": "GB",
    "wof:name": "SO51 0AA",
    "wof:placetype": "postalcode"
  },
  "geometry": {"coordinates":[-1.471202,51.005309],"type":"Point"}
}
