{
  "type": "Feature",
  "properties": {
    "date:inception_lower": "1992-08-01",
    "date:inception_upper": "1992-08-01",
    "iso:country": "GB",
    "wof:name": "L33 1ZS",
    "wof:placetype": "postalcode"
  },
  "geometry": {"coordinates":[-2.893159,53.495035],"type":"Point"}
}
