{
  "type": "Feature",
  "properties": {
    "date:inception_lower":"1980-01-01",
    "date:inception_upper":"1980-01-31",
    "iso:country":"GB",
    "wof:name":"TN6 1DF",
    "wof:placetype":"postalcode"
},
  "geometry": {"coordinates":[0.162607,51.05874],"type":"Point"}
}