{
  "type": "Feature",
  "properties": {
    "iso:country": "GB",
    "wof:name": "TN6 1DF",
    "wof:placetype": "postalcode"
  },
  "geometry": {"coordinates":[0.162607,51.05874],"type":"Point"}
}
