{
  "type": "Feature",
  "properties": {
    "date:inception_lower": "1980-01-01",
    "date:inception_upper": "1980-01-01",
    "iso:country": "GB",
    "wof:name": "OL6 9LY",
    "wof:placetype": "postalcode"
  },
  "geometry": {"coordinates":[-2.084087,53.495486],"type":"Point"}
}
