{
  "type": "Feature",
  "properties": {
    "iso:country":"GB",
    "wof:name":"W1T 5HF",
    "wof:placetype":"postalcode"
},
  "geometry": {"coordinates":[-0.13903138631407,51.52308098383838],"type":"Point"}
}