{
  "type": "Feature",
  "properties": {
    "iso:country":"GB",
    "wof:name":"M34 3LE",
    "wof:placetype":"postalcode"
},
  "geometry": {"coordinates":[-2.1156193896799,53.4563503718759],"type":"Point"}
}