{
  "type": "Feature",
  "properties": {
    "iso:country":"GB",
    "wof:name":"RG4 8LN",
    "wof:placetype":"postalcode"
},
  "geometry": {"coordinates":[-0.96997508413464,51.48319868937749],"type":"Point"}
}