{
  "type": "Feature",
  "properties": {
    "iso:country":"GB",
    "wof:name":"DN7 6LA",
    "wof:placetype":"postalcode"
},
  "geometry": {"coordinates":[-1.01115019990418,53.5792291610529],"type":"Point"}
}