{
  "type": "Feature",
  "properties": {
    "iso:country":"GB",
    "wof:name":"CH5 4NY",
    "wof:placetype":"postalcode"
},
  "geometry": {"coordinates":[-3.052761243972,53.21400458897997],"type":"Point"}
}