{
  "type": "Feature",
  "properties": {
    "iso:country": "GB",
    "wof:name": "RM18 8FN",
    "wof:placetype": "postalcode"
  },
  "geometry": {"coordinates":[0.364151,51.46774],"type":"Point"}
}
