{
  "type": "Feature",
  "properties": {
    "iso:country":"GB",
    "wof:name":"BR3 6RT",
    "wof:placetype":"postalcode"
},
  "geometry": {"coordinates":[-0.00362962717589,51.39407483250774],"type":"Point"}
}