{
  "type": "Feature",
  "properties": {
    "iso:country":"GB",
    "wof:name":"BB1 8ED",
    "wof:placetype":"postalcode"
},
  "geometry": {"coordinates":[-2.48692066815817,53.75609134611641],"type":"Point"}
}