{
  "type": "Feature",
  "properties": {
    "iso:country": "GB",
    "wof:name": "BB1 8ED",
    "wof:placetype": "postalcode"
  },
  "geometry": {"coordinates":[-2.486921,53.756091],"type":"Point"}
}
