{
  "type": "Feature",
  "properties": {
    "date:inception_lower": "1996-06-01",
    "date:inception_upper": "1996-06-01",
    "iso:country": "GB",
    "wof:name": "FK10 2UW",
    "wof:placetype": "postalcode"
  },
  "geometry": {"coordinates":[-3.827982,56.130604],"type":"Point"}
}
