{
  "type": "Feature",
  "properties": {
    "iso:country":"GB",
    "wof:name":"E11 1PP",
    "wof:placetype":"postalcode"
},
  "geometry": {"coordinates":[0.01772403172618,51.57401339226519],"type":"Point"}
}