{
  "type": "Feature",
  "properties": {
    "date:inception_lower": "2017-01-01",
    "date:inception_upper": "2017-01-01",
    "iso:country": "GB",
    "wof:name": "PA3 9UW",
    "wof:placetype": "postalcode"
  },
  "geometry": {"coordinates":[-4.418295,55.844032],"type":"Point"}
}
