{
  "type": "Feature",
  "properties": {
    "iso:country":"GB",
    "wof:name":"EX21 5AD",
    "wof:placetype":"postalcode"
},
  "geometry": {"coordinates":[-4.18939746670162,50.76578477750967],"type":"Point"}
}