{
  "type": "Feature",
  "properties": {
    "iso:country": "GB",
    "wof:name": "EX21 5AD",
    "wof:placetype": "postalcode"
  },
  "geometry": {"coordinates":[-4.189632,50.765645],"type":"Point"}
}
