{
  "type": "Feature",
  "properties": {
    "iso:country":"GB",
    "wof:name":"OL11 2RN",
    "wof:placetype":"postalcode"
},
  "geometry": {"coordinates":[-2.15635772746173,53.59182170489331],"type":"Point"}
}