{
  "type": "Feature",
  "properties": {
    "iso:country": "GB",
    "wof:name": "OL11 2RN",
    "wof:placetype": "postalcode"
  },
  "geometry": {"coordinates":[-2.156358,53.591822],"type":"Point"}
}
