{
  "type": "Feature",
  "properties": {
    "iso:country": "GB",
    "wof:name": "OX7 5XD",
    "wof:placetype": "postalcode"
  },
  "geometry": {"coordinates":[-1.540545,51.920988],"type":"Point"}
}
