{
  "type": "Feature",
  "properties": {
    "iso:country":"GB",
    "wof:name":"OX7 5XD",
    "wof:placetype":"postalcode"
},
  "geometry": {"coordinates":[-1.54054478919627,51.92098846697916],"type":"Point"}
}