{
  "type": "Feature",
  "properties": {
    "iso:country": "GB",
    "wof:name": "EX39 2LN",
    "wof:placetype": "postalcode"
  },
  "geometry": {"coordinates":[-4.211728,51.025526],"type":"Point"}
}
