{
  "type": "Feature",
  "properties": {
    "date:inception_lower":"1980-01-01",
    "date:inception_upper":"1980-01-31",
    "iso:country":"GB",
    "wof:name":"EX39 2LN",
    "wof:placetype":"postalcode"
},
  "geometry": {"coordinates":[-4.211728,51.025526],"type":"Point"}
}