{
  "type": "Feature",
  "properties": {
    "date:inception_lower": "2007-08-01",
    "date:inception_upper": "2007-08-01",
    "iso:country": "GB",
    "wof:name": "KA3 7FB",
    "wof:placetype": "postalcode"
  },
  "geometry": {"coordinates":[-4.471319,55.61206],"type":"Point"}
}
