{
  "type": "Feature",
  "properties": {
    "iso:country":"GB",
    "wof:name":"KA3 7FB",
    "wof:placetype":"postalcode"
},
  "geometry": {"coordinates":[-4.47131951434361,55.61205969041394],"type":"Point"}
}