{
  "type": "Feature",
  "properties": {
    "iso:country": "GB",
    "wof:name": "OX5 3JP",
    "wof:placetype": "postalcode"
  },
  "geometry": {"coordinates":[-1.26321,51.874769],"type":"Point"}
}
