{
  "type": "Feature",
  "properties": {
    "iso:country":"GB",
    "wof:name":"OX5 3JP",
    "wof:placetype":"postalcode"
},
  "geometry": {"coordinates":[-1.2632099765639,51.8747686107621],"type":"Point"}
}