{
  "type": "Feature",
  "properties": {
    "date:inception_lower": "1980-01-01",
    "date:inception_upper": "1980-01-01",
    "iso:country": "GB",
    "wof:name": "SP11 6PT",
    "wof:placetype": "postalcode"
  },
  "geometry": {"coordinates":[-1.383248,51.197336],"type":"Point"}
}
