{
  "type": "Feature",
  "properties": {
    "iso:country": "GB",
    "wof:name": "L39 3LU",
    "wof:placetype": "postalcode"
  },
  "geometry": {"coordinates":[-2.893151,53.565632],"type":"Point"}
}
