{
  "type": "Feature",
  "properties": {
    "date:inception_lower": "1994-12-01",
    "date:inception_upper": "1994-12-01",
    "iso:country": "GB",
    "wof:name": "SO50 9GH",
    "wof:placetype": "postalcode"
  },
  "geometry": {"coordinates":[-1.367828,50.96753],"type":"Point"}
}
