{
  "type": "Feature",
  "properties": {
    "iso:country":"GB",
    "wof:name":"SO50 9GH",
    "wof:placetype":"postalcode"
},
  "geometry": {"coordinates":[-1.3678384077597,50.96753837281823],"type":"Point"}
}