{
  "type": "Feature",
  "properties": {
    "date:inception_lower": "2017-08-01",
    "date:inception_upper": "2017-08-01",
    "iso:country": "GB",
    "wof:name": "PR2 2FS",
    "wof:placetype": "postalcode"
  },
  "geometry": {"coordinates":[-2.744299,53.758614],"type":"Point"}
}
