{
  "type": "Feature",
  "properties": {
    "iso:country": "GB",
    "wof:name": "PR2 2FS",
    "wof:placetype": "postalcode"
  },
  "geometry": {"coordinates":[-2.744299,53.758614],"type":"Point"}
}
