{
  "type": "Feature",
  "properties": {
    "iso:country":"GB",
    "wof:name":"MK6 3AT",
    "wof:placetype":"postalcode"
},
  "geometry": {"coordinates":[-0.72078014072677,52.02238147491194],"type":"Point"}
}