{
  "type": "Feature",
  "properties": {
    "iso:country": "GB",
    "wof:name": "SO24 0HP",
    "wof:placetype": "postalcode"
  },
  "geometry": {"coordinates":[-1.082995,51.044523],"type":"Point"}
}
