{
  "type": "Feature",
  "properties": {
    "iso:country":"GB",
    "wof:name":"SO24 0HP",
    "wof:placetype":"postalcode"
},
  "geometry": {"coordinates":[-1.08299539749151,51.0445230228294],"type":"Point"}
}