{
  "type": "Feature",
  "properties": {
    "iso:country":"GB",
    "wof:name":"CB23 3WF",
    "wof:placetype":"postalcode"
},
  "geometry": {"coordinates":[-0.11862732140755,52.25086617074314],"type":"Point"}
}