{
  "type": "Feature",
  "properties": {
    "iso:country":"GB",
    "wof:name":"ME9 8RH",
    "wof:placetype":"postalcode"
},
  "geometry": {"coordinates":[0.72936565906756,51.3744953064046],"type":"Point"}
}