{
  "type": "Feature",
  "properties": {
    "iso:country":"GB",
    "wof:name":"BH1 1HZ",
    "wof:placetype":"postalcode"
},
  "geometry": {"coordinates":[-1.87303374588286,50.72663370898002],"type":"Point"}
}