{
  "type": "Feature",
  "properties": {
    "iso:country":"GB",
    "wof:name":"BS23 3YE",
    "wof:placetype":"postalcode"
},
  "geometry": {"coordinates":[-2.96280561775182,51.34098325644263],"type":"Point"}
}