{
  "type": "Feature",
  "properties": {
    "iso:country": "GB",
    "wof:name": "BS23 3YE",
    "wof:placetype": "postalcode"
  },
  "geometry": {"coordinates":[-2.961758,51.342121],"type":"Point"}
}
