{
  "type": "Feature",
  "properties": {
    "iso:country":"GB",
    "wof:name":"SE9 4BT",
    "wof:placetype":"postalcode"
},
  "geometry": {"coordinates":[0.03720032197851,51.42622294152991],"type":"Point"}
}