{
  "type": "Feature",
  "properties": {
    "date:inception_lower": "1980-01-01",
    "date:inception_upper": "1980-01-01",
    "iso:country": "GB",
    "wof:name": "SE9 4BT",
    "wof:placetype": "postalcode"
  },
  "geometry": {"coordinates":[0.0372,51.426223],"type":"Point"}
}
