{
  "type": "Feature",
  "properties": {
    "iso:country":"GB",
    "wof:name":"S65 1ER",
    "wof:placetype":"postalcode"
},
  "geometry": {"coordinates":[-1.35070846784033,53.43145307595556],"type":"Point"}
}