{
  "type": "Feature",
  "properties": {
    "iso:country": "GB",
    "wof:name": "S65 1ER",
    "wof:placetype": "postalcode"
  },
  "geometry": {"coordinates":[-1.350708,53.431453],"type":"Point"}
}
