{
  "type": "Feature",
  "properties": {
    "date:inception_lower":"1997-06-01",
    "date:inception_upper":"1997-06-30",
    "iso:country":"GB",
    "wof:name":"S65 1ER",
    "wof:placetype":"postalcode"
},
  "geometry": {"coordinates":[-1.350708,53.431453],"type":"Point"}
}