{
  "type": "Feature",
  "properties": {
    "iso:country":"GB",
    "wof:name":"HX4 9LP",
    "wof:placetype":"postalcode"
},
  "geometry": {"coordinates":[-1.8819510454235,53.66385286694018],"type":"Point"}
}