{
  "type": "Feature",
  "properties": {
    "iso:country":"GB",
    "wof:name":"BH6 3NW",
    "wof:placetype":"postalcode"
},
  "geometry": {"coordinates":[-1.8037891897562,50.72152898976769],"type":"Point"}
}