{
  "type": "Feature",
  "properties": {
    "date:inception_lower": "1980-01-01",
    "date:inception_upper": "1980-01-01",
    "iso:country": "GB",
    "wof:name": "BH6 3NW",
    "wof:placetype": "postalcode"
  },
  "geometry": {"coordinates":[-1.803789,50.721529],"type":"Point"}
}
