{
  "type": "Feature",
  "properties": {
    "iso:country": "GB",
    "wof:name": "DH3 1FH",
    "wof:placetype": "postalcode"
  },
  "geometry": {"coordinates":[-1.568073,54.901358],"type":"Point"}
}
