{
  "type": "Feature",
  "properties": {
    "iso:country":"GB",
    "wof:name":"B68 8RP",
    "wof:placetype":"postalcode"
},
  "geometry": {"coordinates":[-2.00614168767413,52.48931162593261],"type":"Point"}
}