{
  "type": "Feature",
  "properties": {
    "iso:country": "GB",
    "wof:name": "OL12 7ET",
    "wof:placetype": "postalcode"
  },
  "geometry": {"coordinates":[-2.175303,53.624719],"type":"Point"}
}
