{
  "type": "Feature",
  "properties": {
    "iso:country": "GB",
    "wof:name": "IV6 7PU",
    "wof:placetype": "postalcode"
  },
  "geometry": {"coordinates":[-4.472361,57.523827],"type":"Point"}
}
