{
  "type": "Feature",
  "properties": {
    "date:inception_lower": "2014-02-01",
    "date:inception_upper": "2014-02-01",
    "iso:country": "GB",
    "wof:name": "IV6 7PU",
    "wof:placetype": "postalcode"
  },
  "geometry": {"coordinates":[-4.472361,57.523827],"type":"Point"}
}
