{
  "type": "Feature",
  "properties": {
    "date:inception_lower":"1980-01-01",
    "date:inception_upper":"1980-01-31",
    "iso:country":"GB",
    "wof:name":"LA4 4RD",
    "wof:placetype":"postalcode"
},
  "geometry": {"coordinates":[-2.84762,54.062662],"type":"Point"}
}