{
  "type": "Feature",
  "properties": {
    "iso:country":"GB",
    "wof:name":"LA4 4RD",
    "wof:placetype":"postalcode"
},
  "geometry": {"coordinates":[-2.84762043218676,54.06266177584963],"type":"Point"}
}