{
  "type": "Feature",
  "properties": {
    "iso:country":"GB",
    "wof:name":"S73 9DS",
    "wof:placetype":"postalcode"
},
  "geometry": {"coordinates":[-1.38028102232514,53.53923036881772],"type":"Point"}
}