{
  "type": "Feature",
  "properties": {
    "iso:country": "GB",
    "wof:name": "S73 9DS",
    "wof:placetype": "postalcode"
  },
  "geometry": {"coordinates":[-1.380281,53.53923],"type":"Point"}
}
