{
  "type": "Feature",
  "properties": {
    "iso:country": "GB",
    "wof:name": "SS15 6FU",
    "wof:placetype": "postalcode"
  },
  "geometry": {"coordinates":[0.414112,51.582975],"type":"Point"}
}
