{
  "type": "Feature",
  "properties": {
    "iso:country": "GB",
    "wof:name": "BA12 9QL",
    "wof:placetype": "postalcode"
  },
  "geometry": {"coordinates":[-2.189398,51.195164],"type":"Point"}
}
