{
  "type": "Feature",
  "properties": {
    "iso:country":"GB",
    "wof:name":"BA12 9QL",
    "wof:placetype":"postalcode"
},
  "geometry": {"coordinates":[-2.18939763422258,51.19516443546679],"type":"Point"}
}