{
  "type": "Feature",
  "properties": {
    "iso:country":"GB",
    "wof:name":"YO30 1AS",
    "wof:placetype":"postalcode"
},
  "geometry": {"coordinates":[-1.18225891665471,54.03209780533847],"type":"Point"}
}