{
  "type": "Feature",
  "properties": {
    "date:inception_lower":"2003-01-01",
    "date:inception_upper":"2003-01-31",
    "iso:country":"GB",
    "wof:name":"CH3 5AD",
    "wof:placetype":"postalcode"
},
  "geometry": {"coordinates":[-2.88056,53.192704],"type":"Point"}
}