{
  "type": "Feature",
  "properties": {
    "iso:country":"GB",
    "wof:name":"CH3 5AD",
    "wof:placetype":"postalcode"
},
  "geometry": {"coordinates":[-2.88055956769862,53.19270418135481],"type":"Point"}
}