{
  "type": "Feature",
  "properties": {
    "iso:country":"GB",
    "wof:name":"DN22 7BT",
    "wof:placetype":"postalcode"
},
  "geometry": {"coordinates":[-0.95307505349899,53.32016897187816],"type":"Point"}
}