{
  "type": "Feature",
  "properties": {
    "iso:country":"GB",
    "wof:name":"LA2 7DE",
    "wof:placetype":"postalcode"
},
  "geometry": {"coordinates":[-2.56034490561854,54.12435412837361],"type":"Point"}
}