{
  "type": "Feature",
  "properties": {
    "iso:country": "GB",
    "wof:name": "LA2 7DE",
    "wof:placetype": "postalcode"
  },
  "geometry": {"coordinates":[-2.560345,54.124354],"type":"Point"}
}
