{
  "type": "Feature",
  "properties": {
    "iso:country":"GB",
    "wof:name":"DH8 0HR",
    "wof:placetype":"postalcode"
},
  "geometry": {"coordinates":[-1.85897672268559,54.87210192226568],"type":"Point"}
}