{
  "type": "Feature",
  "properties": {
    "iso:country":"GB",
    "wof:name":"E4 6QP",
    "wof:placetype":"postalcode"
},
  "geometry": {"coordinates":[-0.00486876995866,51.62885858383498],"type":"Point"}
}