{
  "type": "Feature",
  "properties": {
    "iso:country":"GB",
    "wof:name":"W1D 4RT",
    "wof:placetype":"postalcode"
},
  "geometry": {"coordinates":[-0.1312133674486,51.51334369388259],"type":"Point"}
}