{
  "type": "Feature",
  "properties": {
    "iso:country":"GB",
    "wof:name":"SS0 8AJ",
    "wof:placetype":"postalcode"
},
  "geometry": {"coordinates":[0.69085268702515,51.54233736888323],"type":"Point"}
}