{
  "type": "Feature",
  "properties": {
    "iso:country":"GB",
    "wof:name":"N17 6AT",
    "wof:placetype":"postalcode"
},
  "geometry": {"coordinates":[-0.09283792701727,51.5898097541015],"type":"Point"}
}