{
  "type": "Feature",
  "properties": {
    "date:inception_lower": "2000-10-01",
    "date:inception_upper": "2000-10-01",
    "iso:country": "GB",
    "wof:name": "WD25 9UE",
    "wof:placetype": "postalcode"
  },
  "geometry": {"coordinates":[-0.381092,51.681695],"type":"Point"}
}
