{
  "type": "Feature",
  "properties": {
    "date:inception_lower": "1990-08-01",
    "date:inception_upper": "1990-08-01",
    "iso:country": "GB",
    "wof:name": "AB31 4AH",
    "wof:placetype": "postalcode"
  },
  "geometry": {"coordinates":[-2.52298,57.05484],"type":"Point"}
}
