{
  "type": "Feature",
  "properties": {
    "iso:country": "GB",
    "wof:name": "SN14 8ER",
    "wof:placetype": "postalcode"
  },
  "geometry": {"coordinates":[-2.373225,51.480245],"type":"Point"}
}
