{
  "type": "Feature",
  "properties": {
    "date:inception_lower":"1980-01-01",
    "date:inception_upper":"1980-01-31",
    "iso:country":"GB",
    "wof:name":"SN14 8ER",
    "wof:placetype":"postalcode"
},
  "geometry": {"coordinates":[-2.373225,51.480245],"type":"Point"}
}