{
  "type": "Feature",
  "properties": {
    "iso:country":"GB",
    "wof:name":"DG11 2HP",
    "wof:placetype":"postalcode"
},
  "geometry": {"coordinates":[-3.35141601565962,55.12073853721141],"type":"Point"}
}