{
  "type": "Feature",
  "properties": {
    "iso:country":"GB",
    "wof:name":"CR6 9HS",
    "wof:placetype":"postalcode"
},
  "geometry": {"coordinates":[-0.06345484893623,51.30250676969654],"type":"Point"}
}