{
  "type": "Feature",
  "properties": {
    "date:inception_lower": "1993-08-01",
    "date:inception_upper": "1993-08-01",
    "iso:country": "GB",
    "wof:name": "NP44 1QZ",
    "wof:placetype": "postalcode"
  },
  "geometry": {"coordinates":[-3.025269,51.665632],"type":"Point"}
}
