{
  "type": "Feature",
  "properties": {
    "iso:country":"GB",
    "wof:name":"NP44 1QZ",
    "wof:placetype":"postalcode"
},
  "geometry": {"coordinates":[-3.02526924200762,51.66563184824022],"type":"Point"}
}