{
  "type": "Feature",
  "properties": {
    "iso:country": "GB",
    "wof:name": "NP44 1QZ",
    "wof:placetype": "postalcode"
  },
  "geometry": {"coordinates":[-3.025269,51.665632],"type":"Point"}
}
