{
  "type": "Feature",
  "properties": {
    "iso:country": "GB",
    "wof:name": "SG11 1RA",
    "wof:placetype": "postalcode"
  },
  "geometry": {"coordinates":[0.015943,51.86198],"type":"Point"}
}
