{
  "type": "Feature",
  "properties": {
    "iso:country":"GB",
    "wof:name":"SG11 1RA",
    "wof:placetype":"postalcode"
},
  "geometry": {"coordinates":[0.01673271726594,51.86206655760397],"type":"Point"}
}