{
  "type": "Feature",
  "properties": {
    "iso:country":"GB",
    "wof:name":"BD16 4AE",
    "wof:placetype":"postalcode"
},
  "geometry": {"coordinates":[-1.82514921179891,53.855390256446],"type":"Point"}
}