{
  "type": "Feature",
  "properties": {
    "date:inception_lower": "2010-05-01",
    "date:inception_upper": "2010-05-01",
    "iso:country": "GB",
    "wof:name": "CM0 8GZ",
    "wof:placetype": "postalcode"
  },
  "geometry": {"coordinates":[0.821799,51.625906],"type":"Point"}
}
