{
  "type": "Feature",
  "properties": {
    "iso:country":"GB",
    "wof:name":"CM0 8GZ",
    "wof:placetype":"postalcode"
},
  "geometry": {"coordinates":[0.82179893902629,51.62590574951155],"type":"Point"}
}