{
  "type": "Feature",
  "properties": {
    "date:inception_lower": "1980-01-01",
    "date:inception_upper": "1980-01-01",
    "iso:country": "GB",
    "wof:name": "DY11 5TU",
    "wof:placetype": "postalcode"
  },
  "geometry": {"coordinates":[-2.259253,52.408243],"type":"Point"}
}
