{
  "type": "Feature",
  "properties": {
    "iso:country":"GB",
    "wof:name":"B76 2SH",
    "wof:placetype":"postalcode"
},
  "geometry": {"coordinates":[-1.79689452365766,52.55073681125791],"type":"Point"}
}