{
  "type": "Feature",
  "properties": {
    "iso:country": "GB",
    "wof:name": "RH14 0DR",
    "wof:placetype": "postalcode"
  },
  "geometry": {"coordinates":[-0.505385,51.022863],"type":"Point"}
}
