{
  "type": "Feature",
  "properties": {
    "date:inception_lower":"1980-01-01",
    "date:inception_upper":"1980-01-31",
    "iso:country":"GB",
    "wof:name":"RH14 0DR",
    "wof:placetype":"postalcode"
},
  "geometry": {"coordinates":[-0.505385,51.022863],"type":"Point"}
}