{
  "type": "Feature",
  "properties": {
    "iso:country":"GB",
    "wof:name":"NW7 4JJ",
    "wof:placetype":"postalcode"
},
  "geometry": {"coordinates":[-0.24456793197105,51.61999931757021],"type":"Point"}
}