{
  "type": "Feature",
  "properties": {
    "iso:country":"GB",
    "wof:name":"DN16 2BB",
    "wof:placetype":"postalcode"
},
  "geometry": {"coordinates":[-0.65295454337446,53.57159782459473],"type":"Point"}
}