{
  "type": "Feature",
  "properties": {
    "iso:country": "GB",
    "wof:name": "DN16 2BB",
    "wof:placetype": "postalcode"
  },
  "geometry": {"coordinates":[-0.652954,53.571598],"type":"Point"}
}
