{
  "type": "Feature",
  "properties": {
    "date:inception_lower": "2016-11-01",
    "date:inception_upper": "2016-11-01",
    "iso:country": "GB",
    "wof:name": "CV1 2LY",
    "wof:placetype": "postalcode"
  },
  "geometry": {"coordinates":[-1.506791,52.40223],"type":"Point"}
}
