{
  "type": "Feature",
  "properties": {
    "iso:country": "GB",
    "wof:name": "CV1 2LY",
    "wof:placetype": "postalcode"
  },
  "geometry": {"coordinates":[-1.506791,52.40223],"type":"Point"}
}
