{
  "type": "Feature",
  "properties": {
    "date:inception_lower": "2019-09-01",
    "date:inception_upper": "2019-09-01",
    "iso:country": "GB",
    "wof:name": "G81 2AB",
    "wof:placetype": "postalcode"
  },
  "geometry": {"coordinates":[-4.391966,55.907406],"type":"Point"}
}
