{
  "type": "Feature",
  "properties": {
    "date:inception_lower": "1997-12-01",
    "date:inception_upper": "1997-12-01",
    "iso:country": "GB",
    "wof:name": "BS22 6FU",
    "wof:placetype": "postalcode"
  },
  "geometry": {"coordinates":[-2.910858,51.360282],"type":"Point"}
}
