{
  "type": "Feature",
  "properties": {
    "date:inception_lower": "2020-08-01",
    "date:inception_upper": "2020-08-01",
    "iso:country": "GB",
    "wof:name": "HP4 9EP",
    "wof:placetype": "postalcode"
  },
  "geometry": {"coordinates":[-0.569452,51.762241],"type":"Point"}
}
