{
  "type": "Feature",
  "properties": {
    "iso:country": "GB",
    "wof:name": "SO51 7JQ",
    "wof:placetype": "postalcode"
  },
  "geometry": {"coordinates":[-1.483919,50.998152],"type":"Point"}
}
