{
  "type": "Feature",
  "properties": {
    "iso:country":"GB",
    "wof:name":"TS29 6AT",
    "wof:placetype":"postalcode"
},
  "geometry": {"coordinates":[-1.40357646131589,54.71938587100364],"type":"Point"}
}