{
  "type": "Feature",
  "properties": {
    "iso:country": "GB",
    "wof:name": "TS29 6AT",
    "wof:placetype": "postalcode"
  },
  "geometry": {"coordinates":[-1.403576,54.719386],"type":"Point"}
}
