{
  "type": "Feature",
  "properties": {
    "date:inception_lower": "1980-01-01",
    "date:inception_upper": "1980-01-01",
    "iso:country": "GB",
    "wof:name": "TS29 6AT",
    "wof:placetype": "postalcode"
  },
  "geometry": {"coordinates":[-1.403576,54.719386],"type":"Point"}
}
