{
  "type": "Feature",
  "properties": {
    "iso:country":"GB",
    "wof:name":"SG14 3JW",
    "wof:placetype":"postalcode"
},
  "geometry": {"coordinates":[-0.07361496917759,51.80534774327089],"type":"Point"}
}