{
  "type": "Feature",
  "properties": {
    "iso:country":"GB",
    "wof:name":"NG6 8ET",
    "wof:placetype":"postalcode"
},
  "geometry": {"coordinates":[-1.19549706277901,53.00307790967866],"type":"Point"}
}