{
  "type": "Feature",
  "properties": {
    "iso:country":"GB",
    "wof:name":"PR8 3PT",
    "wof:placetype":"postalcode"
},
  "geometry": {"coordinates":[-3.04352486869931,53.59698039072116],"type":"Point"}
}