{
  "type": "Feature",
  "properties": {
    "iso:country": "GB",
    "wof:name": "B8 1NG",
    "wof:placetype": "postalcode"
  },
  "geometry": {"coordinates":[-1.854734,52.488576],"type":"Point"}
}
