{
  "type": "Feature",
  "properties": {
    "iso:country":"GB",
    "wof:name":"B23 5QZ",
    "wof:placetype":"postalcode"
},
  "geometry": {"coordinates":[-1.84386295505151,52.53916608571718],"type":"Point"}
}