{
  "type": "Feature",
  "properties": {
    "date:inception_lower":"1986-04-01",
    "date:inception_upper":"1986-04-30",
    "iso:country":"GB",
    "wof:name":"B23 5QZ",
    "wof:placetype":"postalcode"
},
  "geometry": {"coordinates":[-1.843863,52.539166],"type":"Point"}
}