{
  "type": "Feature",
  "properties": {
    "iso:country":"GB",
    "wof:name":"BL8 1QF",
    "wof:placetype":"postalcode"
},
  "geometry": {"coordinates":[-2.32494434276084,53.5975224297408],"type":"Point"}
}