{
  "type": "Feature",
  "properties": {
    "iso:country":"GB",
    "wof:name":"PL15 8TN",
    "wof:placetype":"postalcode"
},
  "geometry": {"coordinates":[-4.37760977807259,50.66880967129428],"type":"Point"}
}