{
  "type": "Feature",
  "properties": {
    "date:inception_lower": "1980-01-01",
    "date:inception_upper": "1980-01-01",
    "iso:country": "GB",
    "wof:name": "PL15 8TN",
    "wof:placetype": "postalcode"
  },
  "geometry": {"coordinates":[-4.37761,50.66881],"type":"Point"}
}
