{
  "type": "Feature",
  "properties": {
    "date:inception_lower":"2013-08-01",
    "date:inception_upper":"2013-08-31",
    "iso:country":"GB",
    "wof:name":"LS1 4DA",
    "wof:placetype":"postalcode"
},
  "geometry": {"coordinates":[-1.545362,53.793431],"type":"Point"}
}