{
  "type": "Feature",
  "properties": {
    "iso:country": "GB",
    "wof:name": "LS1 4DA",
    "wof:placetype": "postalcode"
  },
  "geometry": {"coordinates":[-1.545362,53.793431],"type":"Point"}
}
