{
  "type": "Feature",
  "properties": {
    "iso:country":"GB",
    "wof:name":"CB6 3PH",
    "wof:placetype":"postalcode"
},
  "geometry": {"coordinates":[0.11867869031037,52.33873209777875],"type":"Point"}
}