{
  "type": "Feature",
  "properties": {
    "date:inception_lower": "2018-07-01",
    "date:inception_upper": "2018-07-01",
    "iso:country": "GB",
    "wof:name": "KT15 2GE",
    "wof:placetype": "postalcode"
  },
  "geometry": {"coordinates":[-0.489151,51.370388],"type":"Point"}
}
