{
  "type": "Feature",
  "properties": {
    "date:inception_lower": "2021-07-01",
    "date:inception_upper": "2021-07-01",
    "iso:country": "GB",
    "wof:name": "GL54 1FZ",
    "wof:placetype": "postalcode"
  },
  "geometry": {"coordinates":[-1.724021,51.925868],"type":"Point"}
}
