{
  "type": "Feature",
  "properties": {
    "iso:country":"GB",
    "wof:name":"FY1 2AX",
    "wof:placetype":"postalcode"
},
  "geometry": {"coordinates":[-3.05145525862166,53.8210312454661],"type":"Point"}
}