{
  "type": "Feature",
  "properties": {
    "iso:country":"GB",
    "wof:name":"LE5 1NR",
    "wof:placetype":"postalcode"
},
  "geometry": {"coordinates":[-1.05992514958028,52.66032950769297],"type":"Point"}
}