{
  "type": "Feature",
  "properties": {
    "date:inception_lower":"2007-01-01",
    "date:inception_upper":"2007-01-31",
    "iso:country":"GB",
    "wof:name":"LE5 1NR",
    "wof:placetype":"postalcode"
},
  "geometry": {"coordinates":[-1.059925,52.66033],"type":"Point"}
}