{
  "type": "Feature",
  "properties": {
    "iso:country": "GB",
    "wof:name": "SA3 1NB",
    "wof:placetype": "postalcode"
  },
  "geometry": {"coordinates":[-4.179677,51.553112],"type":"Point"}
}
