{
  "type": "Feature",
  "properties": {
    "iso:country":"GB",
    "wof:name":"SA3 1NB",
    "wof:placetype":"postalcode"
},
  "geometry": {"coordinates":[-4.17967735720038,51.5531120394592],"type":"Point"}
}