{
  "type": "Feature",
  "properties": {
    "date:inception_lower":"1980-01-01",
    "date:inception_upper":"1980-01-31",
    "iso:country":"GB",
    "wof:name":"SA3 1NB",
    "wof:placetype":"postalcode"
},
  "geometry": {"coordinates":[-4.179677,51.553112],"type":"Point"}
}