{
  "type": "Feature",
  "properties": {
    "iso:country":"GB",
    "wof:name":"KA9 1AR",
    "wof:placetype":"postalcode"
},
  "geometry": {"coordinates":[-4.60863351169952,55.50339939464624],"type":"Point"}
}