{
  "type": "Feature",
  "properties": {
    "date:inception_lower": "1980-01-01",
    "date:inception_upper": "1980-01-01",
    "iso:country": "GB",
    "wof:name": "KA9 1AR",
    "wof:placetype": "postalcode"
  },
  "geometry": {"coordinates":[-4.608633,55.503399],"type":"Point"}
}
