{
  "type": "Feature",
  "properties": {
    "iso:country": "GB",
    "wof:name": "NE21 4PU",
    "wof:placetype": "postalcode"
  },
  "geometry": {"coordinates":[-1.715135,54.962396],"type":"Point"}
}
