{
  "type": "Feature",
  "properties": {
    "iso:country":"GB",
    "wof:name":"B92 8QE",
    "wof:placetype":"postalcode"
},
  "geometry": {"coordinates":[-1.79578107286327,52.44090470010573],"type":"Point"}
}