{
  "type": "Feature",
  "properties": {
    "iso:country": "GB",
    "wof:name": "CF62 9XS",
    "wof:placetype": "postalcode"
  },
  "geometry": {"coordinates":[-3.269831,51.426251],"type":"Point"}
}
