{
  "type": "Feature",
  "properties": {
    "date:inception_lower":"1993-01-01",
    "date:inception_upper":"1993-01-31",
    "iso:country":"GB",
    "wof:name":"CF62 9XS",
    "wof:placetype":"postalcode"
},
  "geometry": {"coordinates":[-3.269831,51.426251],"type":"Point"}
}