{
  "type": "Feature",
  "properties": {
    "iso:country":"GB",
    "wof:name":"BS10 6DP",
    "wof:placetype":"postalcode"
},
  "geometry": {"coordinates":[-2.60525207673814,51.50286280757288],"type":"Point"}
}