{
  "type": "Feature",
  "properties": {
    "iso:country":"GB",
    "wof:name":"N1C 4AU",
    "wof:placetype":"postalcode"
},
  "geometry": {"coordinates":[-0.12492889712682,51.54038277540432],"type":"Point"}
}