{
  "type": "Feature",
  "properties": {
    "iso:country": "GB",
    "wof:name": "ML8 4DS",
    "wof:placetype": "postalcode"
  },
  "geometry": {"coordinates":[-3.828098,55.732393],"type":"Point"}
}
