{
  "type": "Feature",
  "properties": {
    "date:inception_lower":"1980-01-01",
    "date:inception_upper":"1980-01-31",
    "iso:country":"GB",
    "wof:name":"ML8 4DS",
    "wof:placetype":"postalcode"
},
  "geometry": {"coordinates":[-3.828098,55.732393],"type":"Point"}
}