{
  "type": "Feature",
  "properties": {
    "iso:country":"GB",
    "wof:name":"IP21 5LA",
    "wof:placetype":"postalcode"
},
  "geometry": {"coordinates":[1.26242882153346,52.30629120728567],"type":"Point"}
}