{
  "type": "Feature",
  "properties": {
    "iso:country": "GB",
    "wof:name": "L3 2AL",
    "wof:placetype": "postalcode"
  },
  "geometry": {"coordinates":[-2.983768,53.410348],"type":"Point"}
}
