{
  "type": "Feature",
  "properties": {
    "iso:country":"GB",
    "wof:name":"BA3 5YP",
    "wof:placetype":"postalcode"
},
  "geometry": {"coordinates":[-2.41607401873622,51.29257131561452],"type":"Point"}
}