{
  "type": "Feature",
  "properties": {
    "date:inception_lower":"2001-06-01",
    "date:inception_upper":"2001-06-30",
    "iso:country":"GB",
    "wof:name":"BA3 5YP",
    "wof:placetype":"postalcode"
},
  "geometry": {"coordinates":[-2.415772,51.292577],"type":"Point"}
}