{
  "type": "Feature",
  "properties": {
    "iso:country": "GB",
    "wof:name": "BA3 5YP",
    "wof:placetype": "postalcode"
  },
  "geometry": {"coordinates":[-2.415772,51.292577],"type":"Point"}
}
