{
  "type": "Feature",
  "properties": {
    "date:inception_lower": "2001-06-01",
    "date:inception_upper": "2001-06-01",
    "iso:country": "GB",
    "wof:name": "BA3 5YP",
    "wof:placetype": "postalcode"
  },
  "geometry": {"coordinates":[-2.416073,51.292567],"type":"Point"}
}
