{
  "type": "Feature",
  "properties": {
    "iso:country":"GB",
    "wof:name":"CW2 8AF",
    "wof:placetype":"postalcode"
},
  "geometry": {"coordinates":[-2.46254720436744,53.08815455388512],"type":"Point"}
}