{
  "type": "Feature",
  "properties": {
    "iso:country": "GB",
    "wof:name": "CW2 8AF",
    "wof:placetype": "postalcode"
  },
  "geometry": {"coordinates":[-2.462547,53.088155],"type":"Point"}
}
