{
  "type": "Feature",
  "properties": {
    "iso:country":"GB",
    "wof:name":"MK3 6JX",
    "wof:placetype":"postalcode"
},
  "geometry": {"coordinates":[-0.74345365624741,52.00691783770335],"type":"Point"}
}