{
  "type": "Feature",
  "properties": {
    "iso:country":"GB",
    "wof:name":"BD23 6LR",
    "wof:placetype":"postalcode"
},
  "geometry": {"coordinates":[-2.06007505304287,54.02489405708075],"type":"Point"}
}