{
  "type": "Feature",
  "properties": {
    "iso:country":"GB",
    "wof:name":"RG10 8JX",
    "wof:placetype":"postalcode"
},
  "geometry": {"coordinates":[-0.86495630842019,51.50074374629411],"type":"Point"}
}