{
  "type": "Feature",
  "properties": {
    "iso:country":"GB",
    "wof:name":"MK4 3EY",
    "wof:placetype":"postalcode"
},
  "geometry": {"coordinates":[-0.78774457106877,51.99556749220505],"type":"Point"}
}