{
  "type": "Feature",
  "properties": {
    "date:inception_lower": "2002-07-01",
    "date:inception_upper": "2002-07-01",
    "iso:country": "GB",
    "wof:name": "MK4 3EY",
    "wof:placetype": "postalcode"
  },
  "geometry": {"coordinates":[-0.787745,51.995567],"type":"Point"}
}
