{
  "type": "Feature",
  "properties": {
    "iso:country":"GB",
    "wof:name":"M14 5AW",
    "wof:placetype":"postalcode"
},
  "geometry": {"coordinates":[-2.22426435533225,53.45434398054834],"type":"Point"}
}