{
  "type": "Feature",
  "properties": {
    "iso:country": "GB",
    "wof:name": "WV16 4EZ",
    "wof:placetype": "postalcode"
  },
  "geometry": {"coordinates":[-2.419452,52.537787],"type":"Point"}
}
