{
  "type": "Feature",
  "properties": {
    "iso:country":"GB",
    "wof:name":"B62 0HA",
    "wof:placetype":"postalcode"
},
  "geometry": {"coordinates":[-2.04966299917253,52.40034509219757],"type":"Point"}
}