{
  "type": "Feature",
  "properties": {
    "date:inception_lower": "1980-01-01",
    "date:inception_upper": "1980-01-01",
    "iso:country": "GB",
    "wof:name": "B62 0HA",
    "wof:placetype": "postalcode"
  },
  "geometry": {"coordinates":[-2.049663,52.400345],"type":"Point"}
}
