{
  "type": "Feature",
  "properties": {
    "iso:country": "GB",
    "wof:name": "B62 0HA",
    "wof:placetype": "postalcode"
  },
  "geometry": {"coordinates":[-2.049663,52.400345],"type":"Point"}
}
