{
  "type": "Feature",
  "properties": {
    "date:inception_lower": "1983-07-01",
    "date:inception_upper": "1983-07-01",
    "iso:country": "GB",
    "wof:name": "NR14 6DP",
    "wof:placetype": "postalcode"
  },
  "geometry": {"coordinates":[1.478172,52.528071],"type":"Point"}
}
