{
  "type": "Feature",
  "properties": {
    "iso:country":"GB",
    "wof:name":"NR14 6DP",
    "wof:placetype":"postalcode"
},
  "geometry": {"coordinates":[1.4781718169783,52.52807139888173],"type":"Point"}
}