{
  "type": "Feature",
  "properties": {
    "iso:country":"GB",
    "wof:name":"B75 5HX",
    "wof:placetype":"postalcode"
},
  "geometry": {"coordinates":[-1.83274380066505,52.59414174529194],"type":"Point"}
}