{
  "type": "Feature",
  "properties": {
    "date:inception_lower": "1980-01-01",
    "date:inception_upper": "1980-01-01",
    "iso:country": "GB",
    "wof:name": "DL2 2SY",
    "wof:placetype": "postalcode"
  },
  "geometry": {"coordinates":[-1.555489,54.476407],"type":"Point"}
}
