{
  "type": "Feature",
  "properties": {
    "iso:country":"GB",
    "wof:name":"M28 1WB",
    "wof:placetype":"postalcode"
},
  "geometry": {"coordinates":[-2.41902157611232,53.50620428290583],"type":"Point"}
}