{
  "type": "Feature",
  "properties": {
    "date:inception_lower": "1980-01-01",
    "date:inception_upper": "1980-01-01",
    "iso:country": "GB",
    "wof:name": "YO16 4TJ",
    "wof:placetype": "postalcode"
  },
  "geometry": {"coordinates":[-0.213217,54.082989],"type":"Point"}
}
