{
  "type": "Feature",
  "properties": {
    "iso:country":"GB",
    "wof:name":"YO16 4TJ",
    "wof:placetype":"postalcode"
},
  "geometry": {"coordinates":[-0.21321690914943,54.08298855238508],"type":"Point"}
}