{
  "type": "Feature",
  "properties": {
    "date:inception_lower":"2012-04-01",
    "date:inception_upper":"2012-04-30",
    "iso:country":"GB",
    "wof:name":"G73 4DH",
    "wof:placetype":"postalcode"
},
  "geometry": {"coordinates":[-4.208229,55.80759],"type":"Point"}
}