{
  "type": "Feature",
  "properties": {
    "date:inception_lower":"1993-01-01",
    "date:inception_upper":"1993-01-31",
    "iso:country":"GB",
    "wof:name":"LS15 4PD",
    "wof:placetype":"postalcode"
},
  "geometry": {"coordinates":[-1.397324,53.827597],"type":"Point"}
}