{
  "type": "Feature",
  "properties": {
    "iso:country":"GB",
    "wof:name":"CH4 0LS",
    "wof:placetype":"postalcode"
},
  "geometry": {"coordinates":[-3.04329837614694,53.14933785345829],"type":"Point"}
}