{
  "type": "Feature",
  "properties": {
    "date:inception_lower": "2002-11-01",
    "date:inception_upper": "2002-11-01",
    "iso:country": "GB",
    "wof:name": "LN5 7BW",
    "wof:placetype": "postalcode"
  },
  "geometry": {"coordinates":[-0.536399,53.227921],"type":"Point"}
}
