{
  "type": "Feature",
  "properties": {
    "date:inception_lower":"1980-01-01",
    "date:inception_upper":"1980-01-31",
    "iso:country":"GB",
    "wof:name":"TD15 2NS",
    "wof:placetype":"postalcode"
},
  "geometry": {"coordinates":[-2.032718,55.757269],"type":"Point"}
}