{
  "type": "Feature",
  "properties": {
    "iso:country": "GB",
    "wof:name": "CO11 1SB",
    "wof:placetype": "postalcode"
  },
  "geometry": {"coordinates":[1.05945,51.960013],"type":"Point"}
}
