{
  "type": "Feature",
  "properties": {
    "iso:country":"GB",
    "wof:name":"WA15 7PE",
    "wof:placetype":"postalcode"
},
  "geometry": {"coordinates":[-2.32330974273263,53.3872688347768],"type":"Point"}
}