{
  "type": "Feature",
  "properties": {
    "date:inception_lower": "1995-01-01",
    "date:inception_upper": "1995-01-01",
    "iso:country": "GB",
    "wof:name": "WA15 7PE",
    "wof:placetype": "postalcode"
  },
  "geometry": {"coordinates":[-2.32331,53.387269],"type":"Point"}
}
