{
  "type": "Feature",
  "properties": {
    "iso:country": "GB",
    "wof:name": "CT3 2EZ",
    "wof:placetype": "postalcode"
  },
  "geometry": {"coordinates":[1.277391,51.279905],"type":"Point"}
}
