{
  "type": "Feature",
  "properties": {
    "iso:country": "GB",
    "wof:name": "CT3 2EZ",
    "wof:placetype": "postalcode"
  },
  "geometry": {"coordinates":[1.277408,51.279938],"type":"Point"}
}
