{
  "type": "Feature",
  "properties": {
    "date:inception_lower": "1980-01-01",
    "date:inception_upper": "1980-01-01",
    "iso:country": "GB",
    "wof:name": "CT3 2EZ",
    "wof:placetype": "postalcode"
  },
  "geometry": {"coordinates":[1.277408,51.279938],"type":"Point"}
}
