{
  "type": "Feature",
  "properties": {
    "iso:country":"GB",
    "wof:name":"CT3 2EZ",
    "wof:placetype":"postalcode"
},
  "geometry": {"coordinates":[1.2773913932526,51.27990487292307],"type":"Point"}
}