{
  "type": "Feature",
  "properties": {
    "iso:country":"GB",
    "wof:name":"DH3 2JS",
    "wof:placetype":"postalcode"
},
  "geometry": {"coordinates":[-1.56113332166662,54.88880734373819],"type":"Point"}
}