{
  "type": "Feature",
  "properties": {
    "iso:country": "GB",
    "wof:name": "HP23 4LY",
    "wof:placetype": "postalcode"
  },
  "geometry": {"coordinates":[-0.670469,51.820561],"type":"Point"}
}
