{
  "type": "Feature",
  "properties": {
    "iso:country":"GB",
    "wof:name":"KY7 5NW",
    "wof:placetype":"postalcode"
},
  "geometry": {"coordinates":[-3.17086526293344,56.19651677593932],"type":"Point"}
}