{
  "type": "Feature",
  "properties": {
    "iso:country":"GB",
    "wof:name":"BB12 6LJ",
    "wof:placetype":"postalcode"
},
  "geometry": {"coordinates":[-2.29065533413184,53.79672500576837],"type":"Point"}
}