{
  "type": "Feature",
  "properties": {
    "date:inception_lower": "2020-02-01",
    "date:inception_upper": "2020-02-01",
    "iso:country": "GB",
    "wof:name": "RG2 9TY",
    "wof:placetype": "postalcode"
  },
  "geometry": {"coordinates":[-0.905529,51.380584],"type":"Point"}
}
