{
  "type": "Feature",
  "properties": {
    "date:inception_lower": "1980-01-01",
    "date:inception_upper": "1980-01-01",
    "iso:country": "GB",
    "wof:name": "CA20 1PD",
    "wof:placetype": "postalcode"
  },
  "geometry": {"coordinates":[-3.479446,54.392107],"type":"Point"}
}
