{
  "type": "Feature",
  "properties": {
    "iso:country":"GB",
    "wof:name":"SK2 5UH",
    "wof:placetype":"postalcode"
},
  "geometry": {"coordinates":[-2.10119571105042,53.39460335297442],"type":"Point"}
}