{
  "type": "Feature",
  "properties": {
    "iso:country":"GB",
    "wof:name":"GL8 8LG",
    "wof:placetype":"postalcode"
},
  "geometry": {"coordinates":[-2.16160090695044,51.64162103411698],"type":"Point"}
}