{
  "type": "Feature",
  "properties": {
    "iso:country":"GB",
    "wof:name":"IG11 7DZ",
    "wof:placetype":"postalcode"
},
  "geometry": {"coordinates":[0.08402015049679,51.53008521243418],"type":"Point"}
}