{
  "type": "Feature",
  "properties": {
    "iso:country":"GB",
    "wof:name":"HP7 0QZ",
    "wof:placetype":"postalcode"
},
  "geometry": {"coordinates":[-0.66724701724724,51.68180168532891],"type":"Point"}
}