{
  "type": "Feature",
  "properties": {
    "iso:country":"GB",
    "wof:name":"M46 0NG",
    "wof:placetype":"postalcode"
},
  "geometry": {"coordinates":[-2.49754470114687,53.52548000584733],"type":"Point"}
}