{
  "type": "Feature",
  "properties": {
    "iso:country":"GB",
    "wof:name":"CF23 7HB",
    "wof:placetype":"postalcode"
},
  "geometry": {"coordinates":[-3.14229034300138,51.52938818654355],"type":"Point"}
}