{
  "type": "Feature",
  "properties": {
    "iso:country":"GB",
    "wof:name":"G71 6DN",
    "wof:placetype":"postalcode"
},
  "geometry": {"coordinates":[-4.08874041027397,55.83334151277651],"type":"Point"}
}