{
  "type": "Feature",
  "properties": {
    "iso:country": "GB",
    "wof:name": "G71 6DN",
    "wof:placetype": "postalcode"
  },
  "geometry": {"coordinates":[-4.08874,55.833342],"type":"Point"}
}
