{
  "type": "Feature",
  "properties": {
    "date:inception_lower": "2005-06-01",
    "date:inception_upper": "2005-06-01",
    "iso:country": "GB",
    "wof:name": "TW1 1NN",
    "wof:placetype": "postalcode"
  },
  "geometry": {"coordinates":[-0.323269,51.460647],"type":"Point"}
}
