{
  "type": "Feature",
  "properties": {
    "iso:country":"GB",
    "wof:name":"TW1 1NN",
    "wof:placetype":"postalcode"
},
  "geometry": {"coordinates":[-0.32326948631997,51.46064672761413],"type":"Point"}
}