{
  "type": "Feature",
  "properties": {
    "iso:country": "GB",
    "wof:name": "RG41 2PF",
    "wof:placetype": "postalcode"
  },
  "geometry": {"coordinates":[-0.841252,51.401987],"type":"Point"}
}
