{
  "type": "Feature",
  "properties": {
    "date:inception_lower": "2020-05-01",
    "date:inception_upper": "2020-05-01",
    "iso:country": "GB",
    "wof:name": "RG27 0FS",
    "wof:placetype": "postalcode"
  },
  "geometry": {"coordinates":[-1.031227,51.314044],"type":"Point"}
}
