{
  "type": "Feature",
  "properties": {
    "iso:country": "GB",
    "wof:name": "OL12 0QX",
    "wof:placetype": "postalcode"
  },
  "geometry": {"coordinates":[-2.15605,53.6232],"type":"Point"}
}
