{
  "type": "Feature",
  "properties": {
    "date:inception_lower": "1983-07-01",
    "date:inception_upper": "1983-07-01",
    "iso:country": "GB",
    "wof:name": "OL12 0QX",
    "wof:placetype": "postalcode"
  },
  "geometry": {"coordinates":[-2.15605,53.6232],"type":"Point"}
}
