{
  "type": "Feature",
  "properties": {
    "iso:country":"GB",
    "wof:name":"LS29 9QW",
    "wof:placetype":"postalcode"
},
  "geometry": {"coordinates":[-1.83570473538879,53.92018943229866],"type":"Point"}
}