{
  "type": "Feature",
  "properties": {
    "date:inception_lower": "1980-01-01",
    "date:inception_upper": "1980-01-01",
    "iso:country": "GB",
    "wof:name": "LS29 9QW",
    "wof:placetype": "postalcode"
  },
  "geometry": {"coordinates":[-1.835705,53.920189],"type":"Point"}
}
