{
  "type": "Feature",
  "properties": {
    "iso:country":"GB",
    "wof:name":"ST1 2JA",
    "wof:placetype":"postalcode"
},
  "geometry": {"coordinates":[-2.17114779821673,53.02967485719775],"type":"Point"}
}