{
  "type": "Feature",
  "properties": {
    "iso:country":"GB",
    "wof:name":"BS16 9PP",
    "wof:placetype":"postalcode"
},
  "geometry": {"coordinates":[-2.43864321343138,51.48743776952251],"type":"Point"}
}