{
  "type": "Feature",
  "properties": {
    "date:inception_lower": "1997-12-01",
    "date:inception_upper": "1997-12-01",
    "iso:country": "GB",
    "wof:name": "BS16 9PP",
    "wof:placetype": "postalcode"
  },
  "geometry": {"coordinates":[-2.438793,51.48811],"type":"Point"}
}
