{
  "type": "Feature",
  "properties": {
    "iso:country": "GB",
    "wof:name": "BS16 9PP",
    "wof:placetype": "postalcode"
  },
  "geometry": {"coordinates":[-2.438793,51.48811],"type":"Point"}
}
