{
  "type": "Feature",
  "properties": {
    "iso:country":"GB",
    "wof:name":"PO8 9RT",
    "wof:placetype":"postalcode"
},
  "geometry": {"coordinates":[-1.02726932083753,50.91123483553467],"type":"Point"}
}