{
  "type": "Feature",
  "properties": {
    "iso:country":"GB",
    "wof:name":"CO10 9LW",
    "wof:placetype":"postalcode"
},
  "geometry": {"coordinates":[0.71791884217003,52.07210599374373],"type":"Point"}
}