{
  "type": "Feature",
  "properties": {
    "date:inception_lower": "1999-06-01",
    "date:inception_upper": "1999-06-01",
    "iso:country": "GB",
    "wof:name": "CH45 9JE",
    "wof:placetype": "postalcode"
  },
  "geometry": {"coordinates":[-3.049412,53.435058],"type":"Point"}
}
