{
  "type": "Feature",
  "properties": {
    "date:inception_lower": "1980-01-01",
    "date:inception_upper": "1980-01-01",
    "iso:country": "GB",
    "wof:name": "DL11 6RH",
    "wof:placetype": "postalcode"
  },
  "geometry": {"coordinates":[-2.003095,54.424907],"type":"Point"}
}
