{
  "type": "Feature",
  "properties": {
    "iso:country": "GB",
    "wof:name": "DL11 6RH",
    "wof:placetype": "postalcode"
  },
  "geometry": {"coordinates":[-2.003095,54.424907],"type":"Point"}
}
