{
  "type": "Feature",
  "properties": {
    "iso:country": "GB",
    "wof:name": "TR24 0QJ",
    "wof:placetype": "postalcode"
  },
  "geometry": {"coordinates":[-6.337445,49.952826],"type":"Point"}
}
