{
  "type": "Feature",
  "properties": {
    "date:inception_lower": "1987-04-01",
    "date:inception_upper": "1987-04-01",
    "iso:country": "GB",
    "wof:name": "TR24 0QJ",
    "wof:placetype": "postalcode"
  },
  "geometry": {"coordinates":[-6.337445,49.952826],"type":"Point"}
}
