{
  "type": "Feature",
  "properties": {
    "iso:country":"GB",
    "wof:name":"SS12 0RB",
    "wof:placetype":"postalcode"
},
  "geometry": {"coordinates":[0.51987212087996,51.61360374149952],"type":"Point"}
}