{
  "type": "Feature",
  "properties": {
    "iso:country":"GB",
    "wof:name":"HR2 0QS",
    "wof:placetype":"postalcode"
},
  "geometry": {"coordinates":[-2.9635191771973,51.9847241783016],"type":"Point"}
}