{
  "type": "Feature",
  "properties": {
    "date:inception_lower": "1980-01-01",
    "date:inception_upper": "1980-01-01",
    "iso:country": "GB",
    "wof:name": "NE61 2RH",
    "wof:placetype": "postalcode"
  },
  "geometry": {"coordinates":[-1.700583,55.159211],"type":"Point"}
}
