{
  "type": "Feature",
  "properties": {
    "iso:country":"GB",
    "wof:name":"NE61 2RH",
    "wof:placetype":"postalcode"
},
  "geometry": {"coordinates":[-1.7005832561102,55.15921090780086],"type":"Point"}
}