{
  "type": "Feature",
  "properties": {
    "date:inception_lower":"1980-01-01",
    "date:inception_upper":"1980-01-31",
    "iso:country":"GB",
    "wof:name":"PO38 2RB",
    "wof:placetype":"postalcode"
},
  "geometry": {"coordinates":[-1.267313,50.60057],"type":"Point"}
}