{
  "type": "Feature",
  "properties": {
    "iso:country":"GB",
    "wof:name":"G46 6QJ",
    "wof:placetype":"postalcode"
},
  "geometry": {"coordinates":[-4.29564966352807,55.79318999890045],"type":"Point"}
}