{
  "type": "Feature",
  "properties": {
    "iso:country": "GB",
    "wof:name": "CB21 5NU",
    "wof:placetype": "postalcode"
  },
  "geometry": {"coordinates":[0.377557,52.145242],"type":"Point"}
}
