{
  "type": "Feature",
  "properties": {
    "iso:country":"GB",
    "wof:name":"CB21 5NU",
    "wof:placetype":"postalcode"
},
  "geometry": {"coordinates":[0.37749521688816,52.14518427561485],"type":"Point"}
}