{
  "type": "Feature",
  "properties": {
    "iso:country":"GB",
    "wof:name":"SS0 7HB",
    "wof:placetype":"postalcode"
},
  "geometry": {"coordinates":[0.69218873347371,51.538583335426],"type":"Point"}
}