{
  "type": "Feature",
  "properties": {
    "iso:country":"GB",
    "wof:name":"CA25 5LR",
    "wof:placetype":"postalcode"
},
  "geometry": {"coordinates":[-3.50407474898977,54.51705880261807],"type":"Point"}
}