{
  "type": "Feature",
  "properties": {
    "iso:country":"GB",
    "wof:name":"DH6 2NB",
    "wof:placetype":"postalcode"
},
  "geometry": {"coordinates":[-1.38341353291405,54.76316716819083],"type":"Point"}
}