{
  "type": "Feature",
  "properties": {
    "iso:country":"GB",
    "wof:name":"BR3 3GL",
    "wof:placetype":"postalcode"
},
  "geometry": {"coordinates":[-0.02023734339404,51.39196453779819],"type":"Point"}
}