{
  "type": "Feature",
  "properties": {
    "date:inception_lower": "2007-08-01",
    "date:inception_upper": "2007-08-01",
    "iso:country": "GB",
    "wof:name": "NW9 5XG",
    "wof:placetype": "postalcode"
  },
  "geometry": {"coordinates":[-0.242235,51.60085],"type":"Point"}
}
