{
  "type": "Feature",
  "properties": {
    "date:inception_lower": "1980-01-01",
    "date:inception_upper": "1980-01-01",
    "iso:country": "GB",
    "wof:name": "OX7 3JN",
    "wof:placetype": "postalcode"
  },
  "geometry": {"coordinates":[-1.480566,51.895582],"type":"Point"}
}
