{
  "type": "Feature",
  "properties": {
    "iso:country":"GB",
    "wof:name":"OX7 3JN",
    "wof:placetype":"postalcode"
},
  "geometry": {"coordinates":[-1.48089798151425,51.89585380786148],"type":"Point"}
}