{
  "type": "Feature",
  "properties": {
    "iso:country": "GB",
    "wof:name": "OX7 3JN",
    "wof:placetype": "postalcode"
  },
  "geometry": {"coordinates":[-1.480882,51.895862],"type":"Point"}
}
