{
  "type": "Feature",
  "properties": {
    "iso:country": "GB",
    "wof:name": "S61 2UT",
    "wof:placetype": "postalcode"
  },
  "geometry": {"coordinates":[-1.430839,53.460841],"type":"Point"}
}
