{
  "type": "Feature",
  "properties": {
    "iso:country":"GB",
    "wof:name":"S61 2UT",
    "wof:placetype":"postalcode"
},
  "geometry": {"coordinates":[-1.43083934102712,53.46084088009584],"type":"Point"}
}