{
  "type": "Feature",
  "properties": {
    "iso:country":"GB",
    "wof:name":"N22 5AR",
    "wof:placetype":"postalcode"
},
  "geometry": {"coordinates":[-0.10780960624566,51.60749740379247],"type":"Point"}
}