{
  "type": "Feature",
  "properties": {
    "date:inception_lower": "1984-10-01",
    "date:inception_upper": "1984-10-01",
    "iso:country": "GB",
    "wof:name": "SK14 3AG",
    "wof:placetype": "postalcode"
  },
  "geometry": {"coordinates":[-2.053602,53.431227],"type":"Point"}
}
