{
  "type": "Feature",
  "properties": {
    "iso:country": "GB",
    "wof:name": "SK14 3AG",
    "wof:placetype": "postalcode"
  },
  "geometry": {"coordinates":[-2.053602,53.431227],"type":"Point"}
}
