{
  "type": "Feature",
  "properties": {
    "iso:country": "GB",
    "wof:name": "NN10 0XE",
    "wof:placetype": "postalcode"
  },
  "geometry": {"coordinates":[-0.595588,52.277356],"type":"Point"}
}
