{
  "type": "Feature",
  "properties": {
    "iso:country":"GB",
    "wof:name":"NN10 0XE",
    "wof:placetype":"postalcode"
},
  "geometry": {"coordinates":[-0.59558843522939,52.27735577961853],"type":"Point"}
}