{
  "type": "Feature",
  "properties": {
    "iso:country":"GB",
    "wof:name":"SW6 2RW",
    "wof:placetype":"postalcode"
},
  "geometry": {"coordinates":[-0.18476432494649,51.47029237694215],"type":"Point"}
}