{
  "type": "Feature",
  "properties": {
    "iso:country": "GB",
    "wof:name": "EH20 9EP",
    "wof:placetype": "postalcode"
  },
  "geometry": {"coordinates":[-3.157882,55.882171],"type":"Point"}
}
