{
  "type": "Feature",
  "properties": {
    "iso:country":"GB",
    "wof:name":"KA3 1JL",
    "wof:placetype":"postalcode"
},
  "geometry": {"coordinates":[-4.50152278862849,55.61827816449735],"type":"Point"}
}