{
  "type": "Feature",
  "properties": {
    "iso:country":"GB",
    "wof:name":"CT9 1DL",
    "wof:placetype":"postalcode"
},
  "geometry": {"coordinates":[1.38030292360767,51.3890016983558],"type":"Point"}
}