{
  "type": "Feature",
  "properties": {
    "date:inception_lower": "1994-05-01",
    "date:inception_upper": "1994-05-01",
    "iso:country": "GB",
    "wof:name": "NG1 2JP",
    "wof:placetype": "postalcode"
  },
  "geometry": {"coordinates":[-1.147907,52.952765],"type":"Point"}
}
