{
  "type": "Feature",
  "properties": {
    "iso:country":"GB",
    "wof:name":"NG1 2JP",
    "wof:placetype":"postalcode"
},
  "geometry": {"coordinates":[-1.14790703002414,52.95276507342528],"type":"Point"}
}