{
  "type": "Feature",
  "properties": {
    "iso:country":"GB",
    "wof:name":"BB1 9NS",
    "wof:placetype":"postalcode"
},
  "geometry": {"coordinates":[-2.46957642577951,53.77842408379779],"type":"Point"}
}