{
  "type": "Feature",
  "properties": {
    "iso:country":"GB",
    "wof:name":"TN9 1HW",
    "wof:placetype":"postalcode"
},
  "geometry": {"coordinates":[0.27354065317943,51.19821268585952],"type":"Point"}
}