{
  "type": "Feature",
  "properties": {
    "iso:country":"GB",
    "wof:name":"L2 2UA",
    "wof:placetype":"postalcode"
},
  "geometry": {"coordinates":[-2.98616356756809,53.40854063876043],"type":"Point"}
}