{
  "type": "Feature",
  "properties": {
    "date:inception_lower":"1980-01-01",
    "date:inception_upper":"1980-01-31",
    "iso:country":"GB",
    "wof:name":"TN11 9SF",
    "wof:placetype":"postalcode"
},
  "geometry": {"coordinates":[0.306579,51.253252],"type":"Point"}
}