{
  "type": "Feature",
  "properties": {
    "iso:country":"GB",
    "wof:name":"TR11 2DH",
    "wof:placetype":"postalcode"
},
  "geometry": {"coordinates":[-5.07734607185501,50.15368688772244],"type":"Point"}
}