{
  "type": "Feature",
  "properties": {
    "iso:country": "GB",
    "wof:name": "TR11 2DH",
    "wof:placetype": "postalcode"
  },
  "geometry": {"coordinates":[-5.077346,50.153687],"type":"Point"}
}
