{
  "type": "Feature",
  "properties": {
    "date:inception_lower": "1980-01-01",
    "date:inception_upper": "1980-01-01",
    "iso:country": "GB",
    "wof:name": "TR11 2DH",
    "wof:placetype": "postalcode"
  },
  "geometry": {"coordinates":[-5.077346,50.153687],"type":"Point"}
}
