{
  "type": "Feature",
  "properties": {
    "iso:country": "GB",
    "wof:name": "NE4 9PB",
    "wof:placetype": "postalcode"
  },
  "geometry": {"coordinates":[-1.66136,54.981381],"type":"Point"}
}
