{
  "type": "Feature",
  "properties": {
    "iso:country":"GB",
    "wof:name":"NE4 9PB",
    "wof:placetype":"postalcode"
},
  "geometry": {"coordinates":[-1.66135983964386,54.98138120183922],"type":"Point"}
}