{
  "type": "Feature",
  "properties": {
    "iso:country":"GB",
    "wof:name":"LL24 0DS",
    "wof:placetype":"postalcode"
},
  "geometry": {"coordinates":[-3.86910494517957,53.10122530881821],"type":"Point"}
}