{
  "type": "Feature",
  "properties": {
    "date:inception_lower": "1980-01-01",
    "date:inception_upper": "1980-01-01",
    "iso:country": "GB",
    "wof:name": "LL24 0DS",
    "wof:placetype": "postalcode"
  },
  "geometry": {"coordinates":[-3.869105,53.101225],"type":"Point"}
}
