{
  "type": "Feature",
  "properties": {
    "iso:country":"GB",
    "wof:name":"RG21 5PN",
    "wof:placetype":"postalcode"
},
  "geometry": {"coordinates":[-1.08315197093251,51.27401506949764],"type":"Point"}
}