{
  "type": "Feature",
  "properties": {
    "date:inception_lower":"2017-12-01",
    "date:inception_upper":"2017-12-31",
    "iso:country":"GB",
    "wof:name":"SG13 7AS",
    "wof:placetype":"postalcode"
},
  "geometry": {"coordinates":[-0.047999,51.803008],"type":"Point"}
}