{
  "type": "Feature",
  "properties": {
    "iso:country": "GB",
    "wof:name": "SG13 7AS",
    "wof:placetype": "postalcode"
  },
  "geometry": {"coordinates":[-0.047999,51.803008],"type":"Point"}
}
