{
  "type": "Feature",
  "properties": {
    "iso:country": "GB",
    "wof:name": "TS1 4RY",
    "wof:placetype": "postalcode"
  },
  "geometry": {"coordinates":[-1.253316,54.56627],"type":"Point"}
}
