{
  "type": "Feature",
  "properties": {
    "iso:country":"GB",
    "wof:name":"ME8 6YE",
    "wof:placetype":"postalcode"
},
  "geometry": {"coordinates":[0.59213321988506,51.37174036786312],"type":"Point"}
}