{
  "type": "Feature",
  "properties": {
    "iso:country":"GB",
    "wof:name":"W1F 0PZ",
    "wof:placetype":"postalcode"
},
  "geometry": {"coordinates":[-0.13497109627784,51.51379018470038],"type":"Point"}
}