{
  "type": "Feature",
  "properties": {
    "iso:country":"GB",
    "wof:name":"CA10 2AE",
    "wof:placetype":"postalcode"
},
  "geometry": {"coordinates":[-2.66048716649433,54.65325857530952],"type":"Point"}
}