{
  "type": "Feature",
  "properties": {
    "iso:country": "GB",
    "wof:name": "CA10 2AE",
    "wof:placetype": "postalcode"
  },
  "geometry": {"coordinates":[-2.660493,54.653284],"type":"Point"}
}
