{
  "type": "Feature",
  "properties": {
    "iso:country":"GB",
    "wof:name":"OL14 8AP",
    "wof:placetype":"postalcode"
},
  "geometry": {"coordinates":[-2.08495557482647,53.7180069267221],"type":"Point"}
}