{
  "type": "Feature",
  "properties": {
    "iso:country":"GB",
    "wof:name":"LE15 7QL",
    "wof:placetype":"postalcode"
},
  "geometry": {"coordinates":[-0.7429947008645,52.68323918379016],"type":"Point"}
}