{
  "type": "Feature",
  "properties": {
    "date:inception_lower":"2014-04-01",
    "date:inception_upper":"2014-04-30",
    "iso:country":"GB",
    "wof:name":"LE15 7QL",
    "wof:placetype":"postalcode"
},
  "geometry": {"coordinates":[-0.743235,52.683297],"type":"Point"}
}