{
  "type": "Feature",
  "properties": {
    "iso:country":"GB",
    "wof:name":"DY9 0RF",
    "wof:placetype":"postalcode"
},
  "geometry": {"coordinates":[-2.13177999158567,52.43535211727255],"type":"Point"}
}