{
  "type": "Feature",
  "properties": {
    "iso:country": "GB",
    "wof:name": "DY9 0RF",
    "wof:placetype": "postalcode"
  },
  "geometry": {"coordinates":[-2.13176,52.435384],"type":"Point"}
}
