{
  "type": "Feature",
  "properties": {
    "date:inception_lower": "2021-07-01",
    "date:inception_upper": "2021-07-01",
    "iso:country": "GB",
    "wof:name": "MK17 8YT",
    "wof:placetype": "postalcode"
  },
  "geometry": {"coordinates":[-0.6724,52.029814],"type":"Point"}
}
