{
  "type": "Feature",
  "properties": {
    "iso:country":"GB",
    "wof:name":"WR11 3BF",
    "wof:placetype":"postalcode"
},
  "geometry": {"coordinates":[-1.93458016055649,52.09095385916114],"type":"Point"}
}