{
  "type": "Feature",
  "properties": {
    "iso:country": "GB",
    "wof:name": "SK14 5NL",
    "wof:placetype": "postalcode"
  },
  "geometry": {"coordinates":[-2.064454,53.441675],"type":"Point"}
}
