{
  "type": "Feature",
  "properties": {
    "date:inception_lower": "1980-01-01",
    "date:inception_upper": "1980-01-01",
    "iso:country": "GB",
    "wof:name": "SK14 5NL",
    "wof:placetype": "postalcode"
  },
  "geometry": {"coordinates":[-2.064454,53.441675],"type":"Point"}
}
