{
  "type": "Feature",
  "properties": {
    "iso:country":"GB",
    "wof:name":"OX5 1GB",
    "wof:placetype":"postalcode"
},
  "geometry": {"coordinates":[-1.31018891976824,51.83282223311488],"type":"Point"}
}