{
  "type": "Feature",
  "properties": {
    "date:inception_lower": "1994-05-01",
    "date:inception_upper": "1994-05-01",
    "iso:country": "GB",
    "wof:name": "OX5 1GB",
    "wof:placetype": "postalcode"
  },
  "geometry": {"coordinates":[-1.310189,51.832822],"type":"Point"}
}
