{
  "type": "Feature",
  "properties": {
    "date:inception_lower": "2016-11-01",
    "date:inception_upper": "2016-11-01",
    "iso:country": "GB",
    "wof:name": "TQ12 4FL",
    "wof:placetype": "postalcode"
  },
  "geometry": {"coordinates":[-3.582949,50.53232],"type":"Point"}
}
