{
  "type": "Feature",
  "properties": {
    "iso:country":"GB",
    "wof:name":"G81 2JA",
    "wof:placetype":"postalcode"
},
  "geometry": {"coordinates":[-4.40375523425385,55.90917797491893],"type":"Point"}
}