{
  "type": "Feature",
  "properties": {
    "date:inception_lower": "1998-06-01",
    "date:inception_upper": "1998-06-01",
    "iso:country": "GB",
    "wof:name": "PO32 6EW",
    "wof:placetype": "postalcode"
  },
  "geometry": {"coordinates":[-1.290789,50.752693],"type":"Point"}
}
