{
  "type": "Feature",
  "properties": {
    "iso:country": "GB",
    "wof:name": "PO32 6EW",
    "wof:placetype": "postalcode"
  },
  "geometry": {"coordinates":[-1.290789,50.752693],"type":"Point"}
}
