{
  "type": "Feature",
  "properties": {
    "iso:country":"GB",
    "wof:name":"WS4 2BB",
    "wof:placetype":"postalcode"
},
  "geometry": {"coordinates":[-1.9793346864044,52.59225298494815],"type":"Point"}
}