{
  "type": "Feature",
  "properties": {
    "iso:country": "GB",
    "wof:name": "KW14 8QX",
    "wof:placetype": "postalcode"
  },
  "geometry": {"coordinates":[-3.519842,58.587437],"type":"Point"}
}
