{
  "type": "Feature",
  "properties": {
    "iso:country":"GB",
    "wof:name":"KW14 8QX",
    "wof:placetype":"postalcode"
},
  "geometry": {"coordinates":[-3.51984236549821,58.58743722373739],"type":"Point"}
}