{
  "type": "Feature",
  "properties": {
    "date:inception_lower": "1980-01-01",
    "date:inception_upper": "1980-01-01",
    "iso:country": "GB",
    "wof:name": "SG4 0AA",
    "wof:placetype": "postalcode"
  },
  "geometry": {"coordinates":[-0.26704,51.960337],"type":"Point"}
}
