{
  "type": "Feature",
  "properties": {
    "iso:country":"GB",
    "wof:name":"G73 5DQ",
    "wof:placetype":"postalcode"
},
  "geometry": {"coordinates":[-4.19521741907851,55.81400635324997],"type":"Point"}
}