{
  "type": "Feature",
  "properties": {
    "date:inception_lower":"2015-02-01",
    "date:inception_upper":"2015-02-28",
    "iso:country":"GB",
    "wof:name":"CA2 7TS",
    "wof:placetype":"postalcode"
},
  "geometry": {"coordinates":[-2.967019,54.895697],"type":"Point"}
}