{
  "type": "Feature",
  "properties": {
    "iso:country":"GB",
    "wof:name":"CA2 7TS",
    "wof:placetype":"postalcode"
},
  "geometry": {"coordinates":[-2.96701936164627,54.89569686711607],"type":"Point"}
}