{
  "type": "Feature",
  "properties": {
    "iso:country":"GB",
    "wof:name":"G75 9NS",
    "wof:placetype":"postalcode"
},
  "geometry": {"coordinates":[-4.19679029649799,55.73993081902956],"type":"Point"}
}