{
  "type": "Feature",
  "properties": {
    "iso:country": "GB",
    "wof:name": "NR33 0DG",
    "wof:placetype": "postalcode"
  },
  "geometry": {"coordinates":[1.741436,52.461152],"type":"Point"}
}
