{
  "type": "Feature",
  "properties": {
    "iso:country": "GB",
    "wof:name": "TW11 8AJ",
    "wof:placetype": "postalcode"
  },
  "geometry": {"coordinates":[-0.32748,51.430915],"type":"Point"}
}
