{
  "type": "Feature",
  "properties": {
    "iso:country":"GB",
    "wof:name":"SK12 1PY",
    "wof:placetype":"postalcode"
},
  "geometry": {"coordinates":[-2.10905556033337,53.34570738345524],"type":"Point"}
}