{
  "type": "Feature",
  "properties": {
    "date:inception_lower":"1980-01-01",
    "date:inception_upper":"1980-01-31",
    "iso:country":"GB",
    "wof:name":"SK12 1PY",
    "wof:placetype":"postalcode"
},
  "geometry": {"coordinates":[-2.109056,53.345707],"type":"Point"}
}