{
  "type": "Feature",
  "properties": {
    "date:inception_lower": "2005-02-01",
    "date:inception_upper": "2005-02-01",
    "iso:country": "GB",
    "wof:name": "NN16 8QZ",
    "wof:placetype": "postalcode"
  },
  "geometry": {"coordinates":[-0.720073,52.405135],"type":"Point"}
}
