{
  "type": "Feature",
  "properties": {
    "date:inception_lower":"2008-01-01",
    "date:inception_upper":"2008-01-31",
    "iso:country":"GB",
    "wof:name":"DE24 1AJ",
    "wof:placetype":"postalcode"
},
  "geometry": {"coordinates":[-1.446139,52.907595],"type":"Point"}
}