{
  "type": "Feature",
  "properties": {
    "iso:country":"GB",
    "wof:name":"DE24 1AJ",
    "wof:placetype":"postalcode"
},
  "geometry": {"coordinates":[-1.44562218767307,52.90762825997265],"type":"Point"}
}