{
  "type": "Feature",
  "properties": {
    "iso:country":"GB",
    "wof:name":"CF64 2RD",
    "wof:placetype":"postalcode"
},
  "geometry": {"coordinates":[-3.19583947854386,51.44326929863831],"type":"Point"}
}