{
  "type": "Feature",
  "properties": {
    "iso:country":"GB",
    "wof:name":"G51 3AG",
    "wof:placetype":"postalcode"
},
  "geometry": {"coordinates":[-4.315785515626,55.86441670928154],"type":"Point"}
}