{
  "type": "Feature",
  "properties": {
    "iso:country": "GB",
    "wof:name": "WR8 0DU",
    "wof:placetype": "postalcode"
  },
  "geometry": {"coordinates":[-2.273865,52.082661],"type":"Point"}
}
