{
  "type": "Feature",
  "properties": {
    "iso:country":"GB",
    "wof:name":"WR8 0DU",
    "wof:placetype":"postalcode"
},
  "geometry": {"coordinates":[-2.27386495735696,52.08266052702557],"type":"Point"}
}