{
  "type": "Feature",
  "properties": {
    "date:inception_lower": "1980-01-01",
    "date:inception_upper": "1980-01-01",
    "iso:country": "GB",
    "wof:name": "FK17 8LW",
    "wof:placetype": "postalcode"
  },
  "geometry": {"coordinates":[-4.107629,56.207407],"type":"Point"}
}
