{
  "type": "Feature",
  "properties": {
    "iso:country": "GB",
    "wof:name": "FK17 8LW",
    "wof:placetype": "postalcode"
  },
  "geometry": {"coordinates":[-4.107629,56.207407],"type":"Point"}
}
