{
  "type": "Feature",
  "properties": {
    "iso:country":"GB",
    "wof:name":"FK17 8LW",
    "wof:placetype":"postalcode"
},
  "geometry": {"coordinates":[-4.10790652144524,56.20731105731017],"type":"Point"}
}