{
  "type": "Feature",
  "properties": {
    "iso:country":"GB",
    "wof:name":"CF23 6DS",
    "wof:placetype":"postalcode"
},
  "geometry": {"coordinates":[-3.16964164194304,51.51098204259957],"type":"Point"}
}