{
  "type": "Feature",
  "properties": {
    "iso:country":"GB",
    "wof:name":"M44 6ZG",
    "wof:placetype":"postalcode"
},
  "geometry": {"coordinates":[-2.4282383892903,53.44084304900728],"type":"Point"}
}