{
  "type": "Feature",
  "properties": {
    "iso:country":"GB",
    "wof:name":"BB11 4DJ",
    "wof:placetype":"postalcode"
},
  "geometry": {"coordinates":[-2.26192905087966,53.7791837575154],"type":"Point"}
}