{
  "type": "Feature",
  "properties": {
    "date:inception_lower": "1980-01-01",
    "date:inception_upper": "1980-01-01",
    "iso:country": "GB",
    "wof:name": "BB11 4DJ",
    "wof:placetype": "postalcode"
  },
  "geometry": {"coordinates":[-2.261929,53.779184],"type":"Point"}
}
