{
  "type": "Feature",
  "properties": {
    "iso:country":"GB",
    "wof:name":"DG16 5AP",
    "wof:placetype":"postalcode"
},
  "geometry": {"coordinates":[-3.07144565636083,54.99379195247041],"type":"Point"}
}