{
  "type": "Feature",
  "properties": {
    "date:inception_lower":"2009-04-01",
    "date:inception_upper":"2009-04-30",
    "iso:country":"GB",
    "wof:name":"SN15 9WG",
    "wof:placetype":"postalcode"
},
  "geometry": {"coordinates":[-2.115246,51.460931],"type":"Point"}
}