{
  "type": "Feature",
  "properties": {
    "iso:country":"GB",
    "wof:name":"TN15 0NN",
    "wof:placetype":"postalcode"
},
  "geometry": {"coordinates":[0.27429924655979,51.2658912721134],"type":"Point"}
}