{
  "type": "Feature",
  "properties": {
    "iso:country": "GB",
    "wof:name": "MK9 3AP",
    "wof:placetype": "postalcode"
  },
  "geometry": {"coordinates":[-0.758161,52.045387],"type":"Point"}
}
