{
  "type": "Feature",
  "properties": {
    "iso:country":"GB",
    "wof:name":"EN3 4AH",
    "wof:placetype":"postalcode"
},
  "geometry": {"coordinates":[-0.04818535340184,51.64369590930722],"type":"Point"}
}