{
  "type": "Feature",
  "properties": {
    "date:inception_lower": "1980-01-01",
    "date:inception_upper": "1980-01-01",
    "iso:country": "GB",
    "wof:name": "EN3 4AH",
    "wof:placetype": "postalcode"
  },
  "geometry": {"coordinates":[-0.047943,51.643677],"type":"Point"}
}
