{
  "type": "Feature",
  "properties": {
    "iso:country":"GB",
    "wof:name":"ML5 2PX",
    "wof:placetype":"postalcode"
},
  "geometry": {"coordinates":[-4.03823195477194,55.88978251715494],"type":"Point"}
}