{
  "type": "Feature",
  "properties": {
    "date:inception_lower": "1995-07-01",
    "date:inception_upper": "1995-07-01",
    "iso:country": "GB",
    "wof:name": "CF83 1LZ",
    "wof:placetype": "postalcode"
  },
  "geometry": {"coordinates":[-3.215242,51.557386],"type":"Point"}
}
