{
  "type": "Feature",
  "properties": {
    "iso:country":"GB",
    "wof:name":"LN2 2QJ",
    "wof:placetype":"postalcode"
},
  "geometry": {"coordinates":[-0.45011351177928,53.2705204183919],"type":"Point"}
}