{
  "type": "Feature",
  "properties": {
    "iso:country": "GB",
    "wof:name": "LN2 2QJ",
    "wof:placetype": "postalcode"
  },
  "geometry": {"coordinates":[-0.450113,53.27052],"type":"Point"}
}
