{
  "type": "Feature",
  "properties": {
    "iso:country": "GB",
    "wof:name": "BH17 8QE",
    "wof:placetype": "postalcode"
  },
  "geometry": {"coordinates":[-1.967409,50.740951],"type":"Point"}
}
