{
  "type": "Feature",
  "properties": {
    "iso:country":"GB",
    "wof:name":"BH17 8QE",
    "wof:placetype":"postalcode"
},
  "geometry": {"coordinates":[-1.96740900335714,50.74095141305365],"type":"Point"}
}