{
  "type": "Feature",
  "properties": {
    "date:inception_lower": "1980-01-01",
    "date:inception_upper": "1980-01-01",
    "iso:country": "GB",
    "wof:name": "ME19 5JZ",
    "wof:placetype": "postalcode"
  },
  "geometry": {"coordinates":[0.39309,51.324786],"type":"Point"}
}
