{
  "type": "Feature",
  "properties": {
    "iso:country":"GB",
    "wof:name":"ME19 5JZ",
    "wof:placetype":"postalcode"
},
  "geometry": {"coordinates":[0.39309033365536,51.32478603487971],"type":"Point"}
}