{
  "type": "Feature",
  "properties": {
    "iso:country":"GB",
    "wof:name":"W1K 2PU",
    "wof:placetype":"postalcode"
},
  "geometry": {"coordinates":[-0.15182236551815,51.51014519252428],"type":"Point"}
}