{
  "type": "Feature",
  "properties": {
    "iso:country":"GB",
    "wof:name":"SW11 1BL",
    "wof:placetype":"postalcode"
},
  "geometry": {"coordinates":[-0.16492877840396,51.45903068607803],"type":"Point"}
}