{
  "type": "Feature",
  "properties": {
    "iso:country": "GB",
    "wof:name": "B16 0EZ",
    "wof:placetype": "postalcode"
  },
  "geometry": {"coordinates":[-1.937964,52.482931],"type":"Point"}
}
