{
  "type": "Feature",
  "properties": {
    "date:inception_lower": "1980-01-01",
    "date:inception_upper": "1980-01-01",
    "iso:country": "GB",
    "wof:name": "LS14 5BQ",
    "wof:placetype": "postalcode"
  },
  "geometry": {"coordinates":[-1.448141,53.822845],"type":"Point"}
}
