{
  "type": "Feature",
  "properties": {
    "iso:country": "GB",
    "wof:name": "AL10 8DF",
    "wof:placetype": "postalcode"
  },
  "geometry": {"coordinates":[-0.233561,51.760454],"type":"Point"}
}
