{
  "type": "Feature",
  "properties": {
    "iso:country":"GB",
    "wof:name":"AL10 8DF",
    "wof:placetype":"postalcode"
},
  "geometry": {"coordinates":[-0.23356143284885,51.76045355189038],"type":"Point"}
}