{
  "type": "Feature",
  "properties": {
    "iso:country":"GB",
    "wof:name":"BB1 6DZ",
    "wof:placetype":"postalcode"
},
  "geometry": {"coordinates":[-2.47843313389382,53.75394142784155],"type":"Point"}
}