{
  "type": "Feature",
  "properties": {
    "iso:country": "GB",
    "wof:name": "BB1 6DZ",
    "wof:placetype": "postalcode"
  },
  "geometry": {"coordinates":[-2.478431,53.753956],"type":"Point"}
}
