{
  "type": "Feature",
  "properties": {
    "iso:country":"GB",
    "wof:name":"KY8 3BA",
    "wof:placetype":"postalcode"
},
  "geometry": {"coordinates":[-3.00409415697379,56.19164031114041],"type":"Point"}
}