{
  "type": "Feature",
  "properties": {
    "iso:country": "GB",
    "wof:name": "M15 6GZ",
    "wof:placetype": "postalcode"
  },
  "geometry": {"coordinates":[-2.236768,53.463532],"type":"Point"}
}
