{
  "type": "Feature",
  "properties": {
    "iso:country":"GB",
    "wof:name":"GU24 0DE",
    "wof:placetype":"postalcode"
},
  "geometry": {"coordinates":[-0.6272982339141,51.2797108795563],"type":"Point"}
}