{
  "type": "Feature",
  "properties": {
    "iso:country": "GB",
    "wof:name": "TR8 4ES",
    "wof:placetype": "postalcode"
  },
  "geometry": {"coordinates":[-4.999638,50.453494],"type":"Point"}
}
