{
  "type": "Feature",
  "properties": {
    "iso:country":"GB",
    "wof:name":"TR8 4ES",
    "wof:placetype":"postalcode"
},
  "geometry": {"coordinates":[-4.99963797416927,50.4534935545467],"type":"Point"}
}