{
  "type": "Feature",
  "properties": {
    "iso:country": "GB",
    "wof:name": "LA14 4DA",
    "wof:placetype": "postalcode"
  },
  "geometry": {"coordinates":[-3.234048,54.131033],"type":"Point"}
}
