{
  "type": "Feature",
  "properties": {
    "date:inception_lower":"2009-04-01",
    "date:inception_upper":"2009-04-30",
    "iso:country":"GB",
    "wof:name":"LA14 4DA",
    "wof:placetype":"postalcode"
},
  "geometry": {"coordinates":[-3.234048,54.131033],"type":"Point"}
}