{
  "type": "Feature",
  "properties": {
    "iso:country": "GB",
    "wof:name": "TN17 4LX",
    "wof:placetype": "postalcode"
  },
  "geometry": {"coordinates":[0.631486,51.053296],"type":"Point"}
}
