{
  "type": "Feature",
  "properties": {
    "iso:country": "GB",
    "wof:name": "RH5 6AL",
    "wof:placetype": "postalcode"
  },
  "geometry": {"coordinates":[-0.334043,51.25382],"type":"Point"}
}
