{
  "type": "Feature",
  "properties": {
    "iso:country": "GB",
    "wof:name": "IP12 3LR",
    "wof:placetype": "postalcode"
  },
  "geometry": {"coordinates":[1.474916,52.076927],"type":"Point"}
}
