{
  "type": "Feature",
  "properties": {
    "iso:country":"GB",
    "wof:name":"KA12 0UD",
    "wof:placetype":"postalcode"
},
  "geometry": {"coordinates":[-4.66447533699231,55.62470504352451],"type":"Point"}
}