{
  "type": "Feature",
  "properties": {
    "date:inception_lower": "1985-10-01",
    "date:inception_upper": "1985-10-01",
    "iso:country": "GB",
    "wof:name": "ME15 0JR",
    "wof:placetype": "postalcode"
  },
  "geometry": {"coordinates":[0.479161,51.253771],"type":"Point"}
}
