{
  "type": "Feature",
  "properties": {
    "iso:country":"GB",
    "wof:name":"CW11 3ZE",
    "wof:placetype":"postalcode"
},
  "geometry": {"coordinates":[-2.39656932450036,53.14028660219714],"type":"Point"}
}