{
  "type": "Feature",
  "properties": {
    "date:inception_lower": "1980-01-01",
    "date:inception_upper": "1980-01-01",
    "iso:country": "GB",
    "wof:name": "SW1W 8HH",
    "wof:placetype": "postalcode"
  },
  "geometry": {"coordinates":[-0.155655,51.492319],"type":"Point"}
}
