{
  "type": "Feature",
  "properties": {
    "iso:country": "GB",
    "wof:name": "SW1W 8HH",
    "wof:placetype": "postalcode"
  },
  "geometry": {"coordinates":[-0.155655,51.492319],"type":"Point"}
}
