{
  "type": "Feature",
  "properties": {
    "iso:country":"GB",
    "wof:name":"SW1W 8HH",
    "wof:placetype":"postalcode"
},
  "geometry": {"coordinates":[-0.155654959664,51.49231942909967],"type":"Point"}
}