{
  "type": "Feature",
  "properties": {
    "iso:country":"GB",
    "wof:name":"NG1 7LL",
    "wof:placetype":"postalcode"
},
  "geometry": {"coordinates":[-1.14721363245722,52.95018011246541],"type":"Point"}
}