{
  "type": "Feature",
  "properties": {
    "iso:country":"GB",
    "wof:name":"CH5 1QU",
    "wof:placetype":"postalcode"
},
  "geometry": {"coordinates":[-3.03560205393688,53.20913897477426],"type":"Point"}
}