{
  "type": "Feature",
  "properties": {
    "date:inception_lower": "1980-01-01",
    "date:inception_upper": "1980-01-01",
    "iso:country": "GB",
    "wof:name": "CH5 1QU",
    "wof:placetype": "postalcode"
  },
  "geometry": {"coordinates":[-3.035602,53.209139],"type":"Point"}
}
