{
  "type": "Feature",
  "properties": {
    "iso:country":"GB",
    "wof:name":"CO14 8SL",
    "wof:placetype":"postalcode"
},
  "geometry": {"coordinates":[1.25825664852559,51.86300533310599],"type":"Point"}
}