{
  "type": "Feature",
  "properties": {
    "date:inception_lower":"1980-01-01",
    "date:inception_upper":"1980-01-31",
    "iso:country":"GB",
    "wof:name":"TR19 6LU",
    "wof:placetype":"postalcode"
},
  "geometry": {"coordinates":[-5.666887,50.057963],"type":"Point"}
}