{
  "type": "Feature",
  "properties": {
    "iso:country":"GB",
    "wof:name":"PO12 4NX",
    "wof:placetype":"postalcode"
},
  "geometry": {"coordinates":[-1.14999732728234,50.81099825169365],"type":"Point"}
}