{
  "type": "Feature",
  "properties": {
    "date:inception_lower": "1980-01-01",
    "date:inception_upper": "1980-01-01",
    "iso:country": "GB",
    "wof:name": "PO12 4NX",
    "wof:placetype": "postalcode"
  },
  "geometry": {"coordinates":[-1.149997,50.810998],"type":"Point"}
}
