{
  "type": "Feature",
  "properties": {
    "iso:country": "GB",
    "wof:name": "MK45 4GY",
    "wof:placetype": "postalcode"
  },
  "geometry": {"coordinates":[-0.426312,52.005922],"type":"Point"}
}
