{
  "type": "Feature",
  "properties": {
    "iso:country":"GB",
    "wof:name":"B93 9LL",
    "wof:placetype":"postalcode"
},
  "geometry": {"coordinates":[-1.74768691876064,52.40027575568429],"type":"Point"}
}