{
  "type": "Feature",
  "properties": {
    "iso:country":"GB",
    "wof:name":"HG5 8NQ",
    "wof:placetype":"postalcode"
},
  "geometry": {"coordinates":[-1.44747813074925,54.0035802690739],"type":"Point"}
}