{
  "type": "Feature",
  "properties": {
    "date:inception_lower": "1993-01-01",
    "date:inception_upper": "1993-01-01",
    "iso:country": "GB",
    "wof:name": "HG5 8NQ",
    "wof:placetype": "postalcode"
  },
  "geometry": {"coordinates":[-1.447478,54.00358],"type":"Point"}
}
