{
  "type": "Feature",
  "properties": {
    "date:inception_lower": "2005-05-01",
    "date:inception_upper": "2005-05-01",
    "iso:country": "GB",
    "wof:name": "CT6 5SN",
    "wof:placetype": "postalcode"
  },
  "geometry": {"coordinates":[1.126652,51.368847],"type":"Point"}
}
