{
  "type": "Feature",
  "properties": {
    "iso:country":"GB",
    "wof:name":"CM23 3XY",
    "wof:placetype":"postalcode"
},
  "geometry": {"coordinates":[0.16374951890366,51.86886894213791],"type":"Point"}
}