{
  "type": "Feature",
  "properties": {
    "date:inception_lower":"1995-12-01",
    "date:inception_upper":"1995-12-31",
    "iso:country":"GB",
    "wof:name":"CM23 3XY",
    "wof:placetype":"postalcode"
},
  "geometry": {"coordinates":[0.16375,51.868869],"type":"Point"}
}