{
  "type": "Feature",
  "properties": {
    "iso:country": "GB",
    "wof:name": "AB53 8AW",
    "wof:placetype": "postalcode"
  },
  "geometry": {"coordinates":[-2.513492,57.498404],"type":"Point"}
}
