{
  "type": "Feature",
  "properties": {
    "iso:country":"GB",
    "wof:name":"BB18 6JR",
    "wof:placetype":"postalcode"
},
  "geometry": {"coordinates":[-2.11874185301763,53.92537450928974],"type":"Point"}
}