{
  "type": "Feature",
  "properties": {
    "date:inception_lower": "1997-12-01",
    "date:inception_upper": "1997-12-01",
    "iso:country": "GB",
    "wof:name": "BB18 6JR",
    "wof:placetype": "postalcode"
  },
  "geometry": {"coordinates":[-2.122499,53.922805],"type":"Point"}
}
