{
  "type": "Feature",
  "properties": {
    "iso:country": "GB",
    "wof:name": "BB18 6JR",
    "wof:placetype": "postalcode"
  },
  "geometry": {"coordinates":[-2.118742,53.925375],"type":"Point"}
}
