{
  "type": "Feature",
  "properties": {
    "iso:country":"GB",
    "wof:name":"SL1 3PR",
    "wof:placetype":"postalcode"
},
  "geometry": {"coordinates":[-0.60012547817713,51.51666669442788],"type":"Point"}
}