{
  "type": "Feature",
  "properties": {
    "date:inception_lower":"1980-01-01",
    "date:inception_upper":"1980-01-31",
    "iso:country":"GB",
    "wof:name":"L3 9LU",
    "wof:placetype":"postalcode"
},
  "geometry": {"coordinates":[-2.991984,53.409113],"type":"Point"}
}