{
  "type": "Feature",
  "properties": {
    "iso:country":"GB",
    "wof:name":"KT10 8JN",
    "wof:placetype":"postalcode"
},
  "geometry": {"coordinates":[-0.34809711416708,51.38376333355941],"type":"Point"}
}