{
  "type": "Feature",
  "properties": {
    "iso:country":"GB",
    "wof:name":"N2 9PX",
    "wof:placetype":"postalcode"
},
  "geometry": {"coordinates":[-0.16220775105553,51.58722066024296],"type":"Point"}
}