{
  "type": "Feature",
  "properties": {
    "iso:country":"GB",
    "wof:name":"FK9 4TE",
    "wof:placetype":"postalcode"
},
  "geometry": {"coordinates":[-3.94490789271427,56.14670954779583],"type":"Point"}
}