{
  "type": "Feature",
  "properties": {
    "date:inception_lower": "2004-07-01",
    "date:inception_upper": "2004-07-01",
    "iso:country": "GB",
    "wof:name": "ME19 4HG",
    "wof:placetype": "postalcode"
  },
  "geometry": {"coordinates":[0.401116,51.270679],"type":"Point"}
}
