{
  "type": "Feature",
  "properties": {
    "iso:country":"GB",
    "wof:name":"E1 3HA",
    "wof:placetype":"postalcode"
},
  "geometry": {"coordinates":[-0.05136942440446,51.51639673116353],"type":"Point"}
}