{
  "type": "Feature",
  "properties": {
    "date:inception_lower": "1980-01-01",
    "date:inception_upper": "1980-01-01",
    "iso:country": "GB",
    "wof:name": "E1 3HA",
    "wof:placetype": "postalcode"
  },
  "geometry": {"coordinates":[-0.051369,51.516397],"type":"Point"}
}
