{
  "type": "Feature",
  "properties": {
    "iso:country":"GB",
    "wof:name":"SL6 3DZ",
    "wof:placetype":"postalcode"
},
  "geometry": {"coordinates":[-0.73941894406491,51.50626882234205],"type":"Point"}
}