{
  "type": "Feature",
  "properties": {
    "iso:country": "GB",
    "wof:name": "BA2 8QG",
    "wof:placetype": "postalcode"
  },
  "geometry": {"coordinates":[-2.374154,51.32244],"type":"Point"}
}
