{
  "type": "Feature",
  "properties": {
    "date:inception_lower":"1980-01-01",
    "date:inception_upper":"1980-01-31",
    "iso:country":"GB",
    "wof:name":"BA2 8QG",
    "wof:placetype":"postalcode"
},
  "geometry": {"coordinates":[-2.374154,51.32244],"type":"Point"}
}