{
  "type": "Feature",
  "properties": {
    "iso:country":"GB",
    "wof:name":"BA2 8QG",
    "wof:placetype":"postalcode"
},
  "geometry": {"coordinates":[-2.37415380456121,51.32243975210421],"type":"Point"}
}