{
  "type": "Feature",
  "properties": {
    "iso:country": "GB",
    "wof:name": "DE55 7EH",
    "wof:placetype": "postalcode"
  },
  "geometry": {"coordinates":[-1.381386,53.096563],"type":"Point"}
}
