{
  "type": "Feature",
  "properties": {
    "iso:country":"GB",
    "wof:name":"DE55 7EH",
    "wof:placetype":"postalcode"
},
  "geometry": {"coordinates":[-1.38138616334881,53.09656313663185],"type":"Point"}
}