{
  "type": "Feature",
  "properties": {
    "iso:country": "GB",
    "wof:name": "PO21 9LP",
    "wof:placetype": "postalcode"
  },
  "geometry": {"coordinates":[-0.671195,50.783937],"type":"Point"}
}
