{
  "type": "Feature",
  "properties": {
    "iso:country": "GB",
    "wof:name": "IP6 0JT",
    "wof:placetype": "postalcode"
  },
  "geometry": {"coordinates":[1.100918,52.106695],"type":"Point"}
}
