{
  "type": "Feature",
  "properties": {
    "iso:country":"GB",
    "wof:name":"N1 0TU",
    "wof:placetype":"postalcode"
},
  "geometry": {"coordinates":[-0.11387809776023,51.53561045592967],"type":"Point"}
}