{
  "type": "Feature",
  "properties": {
    "iso:country":"GB",
    "wof:name":"TS4 2NX",
    "wof:placetype":"postalcode"
},
  "geometry": {"coordinates":[-1.22473542126299,54.5621362432451],"type":"Point"}
}