{
  "type": "Feature",
  "properties": {
    "iso:country":"GB",
    "wof:name":"LA15 8NT",
    "wof:placetype":"postalcode"
},
  "geometry": {"coordinates":[-3.1792913483923,54.14876765312251],"type":"Point"}
}