{
  "type": "Feature",
  "properties": {
    "iso:country": "GB",
    "wof:name": "LA15 8NT",
    "wof:placetype": "postalcode"
  },
  "geometry": {"coordinates":[-3.179291,54.148768],"type":"Point"}
}
