{
  "type": "Feature",
  "properties": {
    "iso:country":"GB",
    "wof:name":"OL4 2JA",
    "wof:placetype":"postalcode"
},
  "geometry": {"coordinates":[-2.07618376077491,53.55165916775358],"type":"Point"}
}