{
  "type": "Feature",
  "properties": {
    "date:inception_lower":"2016-03-01",
    "date:inception_upper":"2016-03-31",
    "iso:country":"GB",
    "wof:name":"IP7 7FG",
    "wof:placetype":"postalcode"
},
  "geometry": {"coordinates":[0.909469,52.109401],"type":"Point"}
}