{
  "type": "Feature",
  "properties": {
    "iso:country": "GB",
    "wof:name": "IP7 7FG",
    "wof:placetype": "postalcode"
  },
  "geometry": {"coordinates":[0.909469,52.109401],"type":"Point"}
}
