{
  "type": "Feature",
  "properties": {
    "iso:country":"GB",
    "wof:name":"IP7 7FG",
    "wof:placetype":"postalcode"
},
  "geometry": {"coordinates":[0.90906175218821,52.10923372463634],"type":"Point"}
}