{
  "type": "Feature",
  "properties": {
    "iso:country": "GB",
    "wof:name": "WV15 6HU",
    "wof:placetype": "postalcode"
  },
  "geometry": {"coordinates":[-2.327609,52.447953],"type":"Point"}
}
