{
  "type": "Feature",
  "properties": {
    "iso:country":"GB",
    "wof:name":"LA2 8DT",
    "wof:placetype":"postalcode"
},
  "geometry": {"coordinates":[-2.39101958682611,54.12061970054013],"type":"Point"}
}