{
  "type": "Feature",
  "properties": {
    "date:inception_lower": "1973-08-01",
    "date:inception_upper": "1973-08-01",
    "iso:country": "GB",
    "wof:name": "PH2 6LJ",
    "wof:placetype": "postalcode"
  },
  "geometry": {"coordinates":[-3.405296,56.418652],"type":"Point"}
}
