{
  "type": "Feature",
  "properties": {
    "iso:country":"GB",
    "wof:name":"HU1 1HT",
    "wof:placetype":"postalcode"
},
  "geometry": {"coordinates":[-0.33377102178139,53.74274332081449],"type":"Point"}
}