{
  "type": "Feature",
  "properties": {
    "iso:country":"GB",
    "wof:name":"NP19 9TG",
    "wof:placetype":"postalcode"
},
  "geometry": {"coordinates":[-2.93645276110888,51.59507089580501],"type":"Point"}
}