{
  "type": "Feature",
  "properties": {
    "date:inception_lower": "2005-10-01",
    "date:inception_upper": "2005-10-01",
    "iso:country": "GB",
    "wof:name": "NP19 9TG",
    "wof:placetype": "postalcode"
  },
  "geometry": {"coordinates":[-2.936453,51.595071],"type":"Point"}
}
