{
  "type": "Feature",
  "properties": {
    "iso:country":"GB",
    "wof:name":"B31 5BD",
    "wof:placetype":"postalcode"
},
  "geometry": {"coordinates":[-1.98033123638275,52.40792368413041],"type":"Point"}
}