{
  "type": "Feature",
  "properties": {
    "iso:country":"GB",
    "wof:name":"SO53 2JQ",
    "wof:placetype":"postalcode"
},
  "geometry": {"coordinates":[-1.3722869206632,50.98194118026323],"type":"Point"}
}