{
  "type": "Feature",
  "properties": {
    "iso:country":"GB",
    "wof:name":"CA2 6HJ",
    "wof:placetype":"postalcode"
},
  "geometry": {"coordinates":[-2.95713032106724,54.88043481809554],"type":"Point"}
}