{
  "type": "Feature",
  "properties": {
    "date:inception_lower": "2015-07-01",
    "date:inception_upper": "2015-07-01",
    "iso:country": "GB",
    "wof:name": "OL3 6YW",
    "wof:placetype": "postalcode"
  },
  "geometry": {"coordinates":[-2.006376,53.547342],"type":"Point"}
}
