{
  "type": "Feature",
  "properties": {
    "iso:country":"GB",
    "wof:name":"BN26 5AJ",
    "wof:placetype":"postalcode"
},
  "geometry": {"coordinates":[0.24620241907338,50.81971220147513],"type":"Point"}
}