{
  "type": "Feature",
  "properties": {
    "date:inception_lower": "1980-01-01",
    "date:inception_upper": "1980-01-01",
    "iso:country": "GB",
    "wof:name": "TR1 2DA",
    "wof:placetype": "postalcode"
  },
  "geometry": {"coordinates":[-5.059119,50.258439],"type":"Point"}
}
