{
  "type": "Feature",
  "properties": {
    "iso:country":"GB",
    "wof:name":"TR1 2DA",
    "wof:placetype":"postalcode"
},
  "geometry": {"coordinates":[-5.05911916318994,50.25843899019834],"type":"Point"}
}