{
  "type": "Feature",
  "properties": {
    "iso:country":"GB",
    "wof:name":"FY8 3QY",
    "wof:placetype":"postalcode"
},
  "geometry": {"coordinates":[-2.99886482476264,53.75396907780929],"type":"Point"}
}