{
  "type": "Feature",
  "properties": {
    "iso:country":"GB",
    "wof:name":"LN6 0BY",
    "wof:placetype":"postalcode"
},
  "geometry": {"coordinates":[-0.58188503238251,53.21417753322456],"type":"Point"}
}