{
  "type": "Feature",
  "properties": {
    "iso:country": "GB",
    "wof:name": "MK46 4HU",
    "wof:placetype": "postalcode"
  },
  "geometry": {"coordinates":[-0.656146,52.172884],"type":"Point"}
}
