{
  "type": "Feature",
  "properties": {
    "date:inception_lower": "1980-01-01",
    "date:inception_upper": "1980-01-01",
    "iso:country": "GB",
    "wof:name": "RH11 9NL",
    "wof:placetype": "postalcode"
  },
  "geometry": {"coordinates":[-0.199226,51.098728],"type":"Point"}
}
