{
  "type": "Feature",
  "properties": {
    "iso:country": "GB",
    "wof:name": "RH11 9NL",
    "wof:placetype": "postalcode"
  },
  "geometry": {"coordinates":[-0.199226,51.098728],"type":"Point"}
}
