{
  "type": "Feature",
  "properties": {
    "iso:country":"GB",
    "wof:name":"SP5 3QZ",
    "wof:placetype":"postalcode"
},
  "geometry": {"coordinates":[-1.73884020127008,50.99346914198968],"type":"Point"}
}