{
  "type": "Feature",
  "properties": {
    "date:inception_lower": "2018-09-01",
    "date:inception_upper": "2018-09-01",
    "iso:country": "GB",
    "wof:name": "DG1 3LF",
    "wof:placetype": "postalcode"
  },
  "geometry": {"coordinates":[-3.59703,55.080357],"type":"Point"}
}
