{
  "type": "Feature",
  "properties": {
    "iso:country":"GB",
    "wof:name":"BN7 3LG",
    "wof:placetype":"postalcode"
},
  "geometry": {"coordinates":[-0.02550934407788,50.85819184970063],"type":"Point"}
}