{
  "type": "Feature",
  "properties": {
    "iso:country": "GB",
    "wof:name": "BN7 3LG",
    "wof:placetype": "postalcode"
  },
  "geometry": {"coordinates":[-0.025509,50.858192],"type":"Point"}
}
