{
  "type": "Feature",
  "properties": {
    "date:inception_lower": "1980-01-01",
    "date:inception_upper": "1980-01-01",
    "iso:country": "GB",
    "wof:name": "NP4 6PG",
    "wof:placetype": "postalcode"
  },
  "geometry": {"coordinates":[-3.056472,51.709737],"type":"Point"}
}
