{
  "type": "Feature",
  "properties": {
    "iso:country":"GB",
    "wof:name":"NP4 6PG",
    "wof:placetype":"postalcode"
},
  "geometry": {"coordinates":[-3.05647205251183,51.70973742356687],"type":"Point"}
}