{
  "type": "Feature",
  "properties": {
    "iso:country":"GB",
    "wof:name":"NN9 6AD",
    "wof:placetype":"postalcode"
},
  "geometry": {"coordinates":[-0.54869666267815,52.31641197463943],"type":"Point"}
}