{
  "type": "Feature",
  "properties": {
    "date:inception_lower": "1980-01-01",
    "date:inception_upper": "1980-01-01",
    "iso:country": "GB",
    "wof:name": "NN9 6AD",
    "wof:placetype": "postalcode"
  },
  "geometry": {"coordinates":[-0.548697,52.316412],"type":"Point"}
}
