{
  "type": "Feature",
  "properties": {
    "iso:country": "GB",
    "wof:name": "AB32 6JE",
    "wof:placetype": "postalcode"
  },
  "geometry": {"coordinates":[-2.299735,57.150992],"type":"Point"}
}
