{
  "type": "Feature",
  "properties": {
    "iso:country": "GB",
    "wof:name": "PR1 2LA",
    "wof:placetype": "postalcode"
  },
  "geometry": {"coordinates":[-2.699737,53.760491],"type":"Point"}
}
