{
  "type": "Feature",
  "properties": {
    "iso:country":"GB",
    "wof:name":"BS48 4NY",
    "wof:placetype":"postalcode"
},
  "geometry": {"coordinates":[-2.76749956736233,51.42779446599201],"type":"Point"}
}