{
  "type": "Feature",
  "properties": {
    "iso:country":"GB",
    "wof:name":"AB39 2RN",
    "wof:placetype":"postalcode"
},
  "geometry": {"coordinates":[-2.20096339462917,56.97117546172822],"type":"Point"}
}