{
  "type": "Feature",
  "properties": {
    "date:inception_lower":"1994-12-01",
    "date:inception_upper":"1994-12-31",
    "iso:country":"GB",
    "wof:name":"OX44 9EJ",
    "wof:placetype":"postalcode"
},
  "geometry": {"coordinates":[-1.153138,51.727062],"type":"Point"}
}