{
  "type": "Feature",
  "properties": {
    "iso:country":"GB",
    "wof:name":"SK9 3PF",
    "wof:placetype":"postalcode"
},
  "geometry": {"coordinates":[-2.20702385298982,53.34954143207944],"type":"Point"}
}