{
  "type": "Feature",
  "properties": {
    "iso:country":"GB",
    "wof:name":"G71 5LZ",
    "wof:placetype":"postalcode"
},
  "geometry": {"coordinates":[-4.05968948274349,55.83266320385844],"type":"Point"}
}