{
  "type": "Feature",
  "properties": {
    "iso:country": "GB",
    "wof:name": "ST5 0EF",
    "wof:placetype": "postalcode"
  },
  "geometry": {"coordinates":[-2.213786,53.028518],"type":"Point"}
}
