{
  "type": "Feature",
  "properties": {
    "date:inception_lower":"1980-01-01",
    "date:inception_upper":"1980-01-31",
    "iso:country":"GB",
    "wof:name":"ST5 0EF",
    "wof:placetype":"postalcode"
},
  "geometry": {"coordinates":[-2.213786,53.028518],"type":"Point"}
}