{
  "type": "Feature",
  "properties": {
    "date:inception_lower": "2008-02-01",
    "date:inception_upper": "2008-02-01",
    "iso:country": "GB",
    "wof:name": "DY4 9NS",
    "wof:placetype": "postalcode"
  },
  "geometry": {"coordinates":[-2.06469,52.544753],"type":"Point"}
}
