{
  "type": "Feature",
  "properties": {
    "date:inception_lower":"1980-01-01",
    "date:inception_upper":"1980-01-31",
    "iso:country":"GB",
    "wof:name":"M24 2NS",
    "wof:placetype":"postalcode"
},
  "geometry": {"coordinates":[-2.185558,53.560087],"type":"Point"}
}