{
  "type": "Feature",
  "properties": {
    "iso:country": "GB",
    "wof:name": "SO22 4FD",
    "wof:placetype": "postalcode"
  },
  "geometry": {"coordinates":[-1.325914,51.058112],"type":"Point"}
}
