{
  "type": "Feature",
  "properties": {
    "date:inception_lower": "2013-10-01",
    "date:inception_upper": "2013-10-01",
    "iso:country": "GB",
    "wof:name": "SO22 4FD",
    "wof:placetype": "postalcode"
  },
  "geometry": {"coordinates":[-1.325914,51.058112],"type":"Point"}
}
