{
  "type": "Feature",
  "properties": {
    "iso:country":"GB",
    "wof:name":"SO22 4FD",
    "wof:placetype":"postalcode"
},
  "geometry": {"coordinates":[-1.32589817295821,51.05806370739482],"type":"Point"}
}