{
  "type": "Feature",
  "properties": {
    "iso:country":"GB",
    "wof:name":"BH23 1RH",
    "wof:placetype":"postalcode"
},
  "geometry": {"coordinates":[-1.78118013427718,50.73977089734905],"type":"Point"}
}