{
  "type": "Feature",
  "properties": {
    "date:inception_lower":"2018-04-01",
    "date:inception_upper":"2018-04-30",
    "iso:country":"GB",
    "wof:name":"EH22 1EY",
    "wof:placetype":"postalcode"
},
  "geometry": {"coordinates":[-3.067729,55.894528],"type":"Point"}
}