{
  "type": "Feature",
  "properties": {
    "iso:country": "GB",
    "wof:name": "EH22 1EY",
    "wof:placetype": "postalcode"
  },
  "geometry": {"coordinates":[-3.067729,55.894528],"type":"Point"}
}
