{
  "type": "Feature",
  "properties": {
    "iso:country":"GB",
    "wof:name":"B26 3BL",
    "wof:placetype":"postalcode"
},
  "geometry": {"coordinates":[-1.78910592411596,52.45863929954139],"type":"Point"}
}