{
  "type": "Feature",
  "properties": {
    "date:inception_lower": "1980-01-01",
    "date:inception_upper": "1980-01-01",
    "iso:country": "GB",
    "wof:name": "SA5 5AD",
    "wof:placetype": "postalcode"
  },
  "geometry": {"coordinates":[-3.981273,51.641203],"type":"Point"}
}
