{
  "type": "Feature",
  "properties": {
    "iso:country":"GB",
    "wof:name":"SA5 5AD",
    "wof:placetype":"postalcode"
},
  "geometry": {"coordinates":[-3.98120988292735,51.64117130914782],"type":"Point"}
}