{
  "type": "Feature",
  "properties": {
    "iso:country":"GB",
    "wof:name":"BN22 9ER",
    "wof:placetype":"postalcode"
},
  "geometry": {"coordinates":[0.280335954951,50.80254594606208],"type":"Point"}
}