{
  "type": "Feature",
  "properties": {
    "iso:country":"GB",
    "wof:name":"TQ5 9UA",
    "wof:placetype":"postalcode"
},
  "geometry": {"coordinates":[-3.50966572636457,50.39540649417114],"type":"Point"}
}