{
  "type": "Feature",
  "properties": {
    "iso:country":"GB",
    "wof:name":"WF8 3SP",
    "wof:placetype":"postalcode"
},
  "geometry": {"coordinates":[-1.21720290052706,53.64264907750499],"type":"Point"}
}