{
  "type": "Feature",
  "properties": {
    "iso:country":"GB",
    "wof:name":"PE15 0SZ",
    "wof:placetype":"postalcode"
},
  "geometry": {"coordinates":[0.06189498690702,52.49279994077521],"type":"Point"}
}