{
  "type": "Feature",
  "properties": {
    "iso:country": "GB",
    "wof:name": "PE15 0SZ",
    "wof:placetype": "postalcode"
  },
  "geometry": {"coordinates":[0.061895,52.4928],"type":"Point"}
}
