{
  "type": "Feature",
  "properties": {
    "iso:country": "GB",
    "wof:name": "LS27 7EG",
    "wof:placetype": "postalcode"
  },
  "geometry": {"coordinates":[-1.626347,53.755996],"type":"Point"}
}
