{
  "type": "Feature",
  "properties": {
    "iso:country":"GB",
    "wof:name":"DL3 6JW",
    "wof:placetype":"postalcode"
},
  "geometry": {"coordinates":[-1.55590727661252,54.5281260152837],"type":"Point"}
}