{
  "type": "Feature",
  "properties": {
    "iso:country": "GB",
    "wof:name": "DL3 6JW",
    "wof:placetype": "postalcode"
  },
  "geometry": {"coordinates":[-1.555907,54.528126],"type":"Point"}
}
