{
  "type": "Feature",
  "properties": {
    "iso:country": "GB",
    "wof:name": "SK14 4TZ",
    "wof:placetype": "postalcode"
  },
  "geometry": {"coordinates":[-2.086258,53.459036],"type":"Point"}
}
