{
  "type": "Feature",
  "properties": {
    "date:inception_lower":"2016-01-01",
    "date:inception_upper":"2016-01-31",
    "iso:country":"GB",
    "wof:name":"SK14 4TZ",
    "wof:placetype":"postalcode"
},
  "geometry": {"coordinates":[-2.086258,53.459036],"type":"Point"}
}