{
  "type": "Feature",
  "properties": {
    "iso:country":"GB",
    "wof:name":"PO22 9TD",
    "wof:placetype":"postalcode"
},
  "geometry": {"coordinates":[-0.68181262246781,50.7980782635528],"type":"Point"}
}