{
  "type": "Feature",
  "properties": {
    "date:inception_lower": "1987-04-01",
    "date:inception_upper": "1987-04-01",
    "iso:country": "GB",
    "wof:name": "PO22 9TD",
    "wof:placetype": "postalcode"
  },
  "geometry": {"coordinates":[-0.681813,50.798078],"type":"Point"}
}
