{
  "type": "Feature",
  "properties": {
    "iso:country": "GB",
    "wof:name": "CV5 9EW",
    "wof:placetype": "postalcode"
  },
  "geometry": {"coordinates":[-1.559317,52.425939],"type":"Point"}
}
