{
  "type": "Feature",
  "properties": {
    "iso:country":"GB",
    "wof:name":"CV5 9EW",
    "wof:placetype":"postalcode"
},
  "geometry": {"coordinates":[-1.5593165549774,52.42593931388728],"type":"Point"}
}