{
  "type": "Feature",
  "properties": {
    "iso:country":"GB",
    "wof:name":"PL23 1PH",
    "wof:placetype":"postalcode"
},
  "geometry": {"coordinates":[-4.63306185421699,50.32750184053153],"type":"Point"}
}