{
  "type": "Feature",
  "properties": {
    "iso:country": "GB",
    "wof:name": "GL56 9HX",
    "wof:placetype": "postalcode"
  },
  "geometry": {"coordinates":[-1.761539,52.010364],"type":"Point"}
}
