{
  "type": "Feature",
  "properties": {
    "iso:country": "GB",
    "wof:name": "PE28 5PD",
    "wof:placetype": "postalcode"
  },
  "geometry": {"coordinates":[-0.368463,52.423229],"type":"Point"}
}
