{
  "type": "Feature",
  "properties": {
    "date:inception_lower":"2000-06-01",
    "date:inception_upper":"2000-06-30",
    "iso:country":"GB",
    "wof:name":"PE28 5PD",
    "wof:placetype":"postalcode"
},
  "geometry": {"coordinates":[-0.368463,52.423229],"type":"Point"}
}