{
  "type": "Feature",
  "properties": {
    "iso:country": "GB",
    "wof:name": "PL8 1DB",
    "wof:placetype": "postalcode"
  },
  "geometry": {"coordinates":[-4.047697,50.317843],"type":"Point"}
}
