{
  "type": "Feature",
  "properties": {
    "iso:country":"GB",
    "wof:name":"PL8 1DB",
    "wof:placetype":"postalcode"
},
  "geometry": {"coordinates":[-4.04712391763414,50.3179302709349],"type":"Point"}
}