{
  "type": "Feature",
  "properties": {
    "iso:country": "GB",
    "wof:name": "TD8 6BH",
    "wof:placetype": "postalcode"
  },
  "geometry": {"coordinates":[-2.556065,55.478141],"type":"Point"}
}
