{
  "type": "Feature",
  "properties": {
    "date:inception_lower": "1980-01-01",
    "date:inception_upper": "1980-01-01",
    "iso:country": "GB",
    "wof:name": "RH19 1LZ",
    "wof:placetype": "postalcode"
  },
  "geometry": {"coordinates":[-0.023243,51.129339],"type":"Point"}
}
