{
  "type": "Feature",
  "properties": {
    "iso:country": "GB",
    "wof:name": "RH19 1LZ",
    "wof:placetype": "postalcode"
  },
  "geometry": {"coordinates":[-0.023243,51.129339],"type":"Point"}
}
