{
  "type": "Feature",
  "properties": {
    "date:inception_lower": "1980-01-01",
    "date:inception_upper": "1980-01-01",
    "iso:country": "GB",
    "wof:name": "CW7 2JY",
    "wof:placetype": "postalcode"
  },
  "geometry": {"coordinates":[-2.541503,53.18804],"type":"Point"}
}
