{
  "type": "Feature",
  "properties": {
    "iso:country":"GB",
    "wof:name":"CW7 2JY",
    "wof:placetype":"postalcode"
},
  "geometry": {"coordinates":[-2.54150319775875,53.18804045969977],"type":"Point"}
}