{
  "type": "Feature",
  "properties": {
    "iso:country": "GB",
    "wof:name": "CW7 2JY",
    "wof:placetype": "postalcode"
  },
  "geometry": {"coordinates":[-2.541503,53.18804],"type":"Point"}
}
