{
  "type": "Feature",
  "properties": {
    "iso:country":"GB",
    "wof:name":"UB4 8AH",
    "wof:placetype":"postalcode"
},
  "geometry": {"coordinates":[-0.42392510899019,51.52481772812467],"type":"Point"}
}