{
  "type": "Feature",
  "properties": {
    "iso:country":"GB",
    "wof:name":"SE15 3BW",
    "wof:placetype":"postalcode"
},
  "geometry": {"coordinates":[-0.05086037985716,51.4661823537873],"type":"Point"}
}