{
  "type": "Feature",
  "properties": {
    "iso:country":"GB",
    "wof:name":"N1 0QB",
    "wof:placetype":"postalcode"
},
  "geometry": {"coordinates":[-0.10602015306165,51.53629317645188],"type":"Point"}
}