{
  "type": "Feature",
  "properties": {
    "date:inception_lower": "1984-10-01",
    "date:inception_upper": "1984-10-01",
    "iso:country": "GB",
    "wof:name": "ME14 3AZ",
    "wof:placetype": "postalcode"
  },
  "geometry": {"coordinates":[0.510962,51.304744],"type":"Point"}
}
