{
  "type": "Feature",
  "properties": {
    "iso:country":"GB",
    "wof:name":"TR19 7AN",
    "wof:placetype":"postalcode"
},
  "geometry": {"coordinates":[-5.67677919508759,50.12130087339594],"type":"Point"}
}