{
  "type": "Feature",
  "properties": {
    "date:inception_lower": "2017-04-01",
    "date:inception_upper": "2017-04-01",
    "iso:country": "GB",
    "wof:name": "ST16 1FX",
    "wof:placetype": "postalcode"
  },
  "geometry": {"coordinates":[-2.143916,52.809624],"type":"Point"}
}
