{
  "type": "Feature",
  "properties": {
    "iso:country":"GB",
    "wof:name":"LE4 2EZ",
    "wof:placetype":"postalcode"
},
  "geometry": {"coordinates":[-1.14575776255535,52.66310071565759],"type":"Point"}
}