{
  "type": "Feature",
  "properties": {
    "iso:country": "GB",
    "wof:name": "LE12 6LR",
    "wof:placetype": "postalcode"
  },
  "geometry": {"coordinates":[-1.183656,52.831908],"type":"Point"}
}
