{
  "type": "Feature",
  "properties": {
    "iso:country":"GB",
    "wof:name":"LE12 6LR",
    "wof:placetype":"postalcode"
},
  "geometry": {"coordinates":[-1.18365564868829,52.83190834813022],"type":"Point"}
}