{
  "type": "Feature",
  "properties": {
    "iso:country":"GB",
    "wof:name":"WA14 3JZ",
    "wof:placetype":"postalcode"
},
  "geometry": {"coordinates":[-2.37209217550952,53.37609760558735],"type":"Point"}
}