{
  "type": "Feature",
  "properties": {
    "iso:country": "GB",
    "wof:name": "WA14 3JZ",
    "wof:placetype": "postalcode"
  },
  "geometry": {"coordinates":[-2.372092,53.376098],"type":"Point"}
}
