{
  "type": "Feature",
  "properties": {
    "date:inception_lower": "1980-01-01",
    "date:inception_upper": "1980-01-01",
    "iso:country": "GB",
    "wof:name": "BN18 9RJ",
    "wof:placetype": "postalcode"
  },
  "geometry": {"coordinates":[-0.520629,50.871229],"type":"Point"}
}
