{
  "type": "Feature",
  "properties": {
    "iso:country":"GB",
    "wof:name":"AB42 3GT",
    "wof:placetype":"postalcode"
},
  "geometry": {"coordinates":[-1.80732365941754,57.48637731128801],"type":"Point"}
}