{
  "type": "Feature",
  "properties": {
    "iso:country": "GB",
    "wof:name": "CT15 7NQ",
    "wof:placetype": "postalcode"
  },
  "geometry": {"coordinates":[1.22675,51.183736],"type":"Point"}
}
