{
  "type": "Feature",
  "properties": {
    "iso:country":"GB",
    "wof:name":"BH15 3BY",
    "wof:placetype":"postalcode"
},
  "geometry": {"coordinates":[-1.98359529394867,50.73552321998312],"type":"Point"}
}