{
  "type": "Feature",
  "properties": {
    "date:inception_lower":"1995-01-01",
    "date:inception_upper":"1995-01-31",
    "iso:country":"GB",
    "wof:name":"S43 4UU",
    "wof:placetype":"postalcode"
},
  "geometry": {"coordinates":[-1.285219,53.286962],"type":"Point"}
}