{
  "type": "Feature",
  "properties": {
    "iso:country":"GB",
    "wof:name":"TD5 7TA",
    "wof:placetype":"postalcode"
},
  "geometry": {"coordinates":[-2.45821116306826,55.63880202751147],"type":"Point"}
}