{
  "type": "Feature",
  "properties": {
    "date:inception_lower": "1980-01-01",
    "date:inception_upper": "1980-01-01",
    "iso:country": "GB",
    "wof:name": "PO33 2QH",
    "wof:placetype": "postalcode"
  },
  "geometry": {"coordinates":[-1.164289,50.726837],"type":"Point"}
}
