{
  "type": "Feature",
  "properties": {
    "iso:country":"GB",
    "wof:name":"BD8 7NA",
    "wof:placetype":"postalcode"
},
  "geometry": {"coordinates":[-1.76777437165706,53.80869966648716],"type":"Point"}
}