{
  "type": "Feature",
  "properties": {
    "iso:country": "GB",
    "wof:name": "S40 4FE",
    "wof:placetype": "postalcode"
  },
  "geometry": {"coordinates":[-1.454165,53.250613],"type":"Point"}
}
