{
  "type": "Feature",
  "properties": {
    "iso:country":"GB",
    "wof:name":"DY8 4NN",
    "wof:placetype":"postalcode"
},
  "geometry": {"coordinates":[-2.16377013826817,52.46242595886036],"type":"Point"}
}