{
  "type": "Feature",
  "properties": {
    "iso:country": "GB",
    "wof:name": "GL5 4BP",
    "wof:placetype": "postalcode"
  },
  "geometry": {"coordinates":[-2.251379,51.739638],"type":"Point"}
}
