{
  "type": "Feature",
  "properties": {
    "iso:country":"GB",
    "wof:name":"GL5 4BP",
    "wof:placetype":"postalcode"
},
  "geometry": {"coordinates":[-2.25137880377262,51.73963777776088],"type":"Point"}
}