{
  "type": "Feature",
  "properties": {
    "date:inception_lower":"2007-04-01",
    "date:inception_upper":"2007-04-30",
    "iso:country":"GB",
    "wof:name":"GL5 4BP",
    "wof:placetype":"postalcode"
},
  "geometry": {"coordinates":[-2.251379,51.739638],"type":"Point"}
}