{
  "type": "Feature",
  "properties": {
    "iso:country": "GB",
    "wof:name": "DN16 1UG",
    "wof:placetype": "postalcode"
  },
  "geometry": {"coordinates":[-0.643795,53.585068],"type":"Point"}
}
