{
  "type": "Feature",
  "properties": {
    "iso:country":"GB",
    "wof:name":"L12 0NX",
    "wof:placetype":"postalcode"
},
  "geometry": {"coordinates":[-2.87826573247277,53.44250699060592],"type":"Point"}
}