{
  "type": "Feature",
  "properties": {
    "iso:country": "GB",
    "wof:name": "L12 0NX",
    "wof:placetype": "postalcode"
  },
  "geometry": {"coordinates":[-2.878266,53.442507],"type":"Point"}
}
