{
  "type": "Feature",
  "properties": {
    "iso:country": "GB",
    "wof:name": "BL9 0HH",
    "wof:placetype": "postalcode"
  },
  "geometry": {"coordinates":[-2.303593,53.591026],"type":"Point"}
}
