{
  "type": "Feature",
  "properties": {
    "iso:country":"GB",
    "wof:name":"BL9 0HH",
    "wof:placetype":"postalcode"
},
  "geometry": {"coordinates":[-2.30359279873373,53.59102607864673],"type":"Point"}
}