{
  "type": "Feature",
  "properties": {
    "iso:country":"GB",
    "wof:name":"KW15 1PX",
    "wof:placetype":"postalcode"
},
  "geometry": {"coordinates":[-2.95295999703968,58.97823098988439],"type":"Point"}
}