{
  "type": "Feature",
  "properties": {
    "date:inception_lower":"2015-07-01",
    "date:inception_upper":"2015-07-31",
    "iso:country":"GB",
    "wof:name":"KW15 1PX",
    "wof:placetype":"postalcode"
},
  "geometry": {"coordinates":[-2.952909,58.978062],"type":"Point"}
}