{
  "type": "Feature",
  "properties": {
    "iso:country":"GB",
    "wof:name":"SW9 9NX",
    "wof:placetype":"postalcode"
},
  "geometry": {"coordinates":[-0.1243078842662,51.46601354222884],"type":"Point"}
}