{
  "type": "Feature",
  "properties": {
    "iso:country":"GB",
    "wof:name":"MK45 3DD",
    "wof:placetype":"postalcode"
},
  "geometry": {"coordinates":[-0.43727049514283,52.08153349570541],"type":"Point"}
}