{
  "type": "Feature",
  "properties": {
    "iso:country": "GB",
    "wof:name": "MK45 3DD",
    "wof:placetype": "postalcode"
  },
  "geometry": {"coordinates":[-0.43727,52.081533],"type":"Point"}
}
