{
  "type": "Feature",
  "properties": {
    "date:inception_lower": "2021-04-01",
    "date:inception_upper": "2021-04-01",
    "iso:country": "GB",
    "wof:name": "MK45 1GX",
    "wof:placetype": "postalcode"
  },
  "geometry": {"coordinates":[-0.502447,52.015809],"type":"Point"}
}
