{
  "type": "Feature",
  "properties": {
    "iso:country":"GB",
    "wof:name":"TA19 0QR",
    "wof:placetype":"postalcode"
},
  "geometry": {"coordinates":[-2.85382145265181,50.92868914689415],"type":"Point"}
}