{
  "type": "Feature",
  "properties": {
    "date:inception_lower": "1980-01-01",
    "date:inception_upper": "1980-01-01",
    "iso:country": "GB",
    "wof:name": "TA19 0QR",
    "wof:placetype": "postalcode"
  },
  "geometry": {"coordinates":[-2.853821,50.928689],"type":"Point"}
}
