{
  "type": "Feature",
  "properties": {
    "date:inception_lower":"1980-01-01",
    "date:inception_upper":"1980-01-31",
    "iso:country":"GB",
    "wof:name":"LS27 8EG",
    "wof:placetype":"postalcode"
},
  "geometry": {"coordinates":[-1.602271,53.748648],"type":"Point"}
}