{
  "type": "Feature",
  "properties": {
    "iso:country":"GB",
    "wof:name":"LS27 8EG",
    "wof:placetype":"postalcode"
},
  "geometry": {"coordinates":[-1.60227119287331,53.74864769192385],"type":"Point"}
}