{
  "type": "Feature",
  "properties": {
    "date:inception_lower": "1980-01-01",
    "date:inception_upper": "1980-01-01",
    "iso:country": "GB",
    "wof:name": "WS4 1PS",
    "wof:placetype": "postalcode"
  },
  "geometry": {"coordinates":[-1.950949,52.61747],"type":"Point"}
}
