{
  "type": "Feature",
  "properties": {
    "iso:country": "GB",
    "wof:name": "GU32 1RT",
    "wof:placetype": "postalcode"
  },
  "geometry": {"coordinates":[-0.985081,50.988278],"type":"Point"}
}
