{
  "type": "Feature",
  "properties": {
    "iso:country":"GB",
    "wof:name":"GU32 1RT",
    "wof:placetype":"postalcode"
},
  "geometry": {"coordinates":[-0.98143260971997,50.99297348890576],"type":"Point"}
}