{
  "type": "Feature",
  "properties": {
    "iso:country": "GB",
    "wof:name": "BA2 3PU",
    "wof:placetype": "postalcode"
  },
  "geometry": {"coordinates":[-2.380276,51.377297],"type":"Point"}
}
