{
  "type": "Feature",
  "properties": {
    "iso:country":"GB",
    "wof:name":"CH7 3LP",
    "wof:placetype":"postalcode"
},
  "geometry": {"coordinates":[-3.07278602227735,53.18175210847232],"type":"Point"}
}