{
  "type": "Feature",
  "properties": {
    "iso:country": "GB",
    "wof:name": "GU9 8TD",
    "wof:placetype": "postalcode"
  },
  "geometry": {"coordinates":[-0.81039,51.199309],"type":"Point"}
}
