{
  "type": "Feature",
  "properties": {
    "iso:country":"GB",
    "wof:name":"CT12 6QU",
    "wof:placetype":"postalcode"
},
  "geometry": {"coordinates":[1.39770777400254,51.3538215436486],"type":"Point"}
}