{
  "type": "Feature",
  "properties": {
    "iso:country": "GB",
    "wof:name": "DN31 2BH",
    "wof:placetype": "postalcode"
  },
  "geometry": {"coordinates":[-0.108523,53.567689],"type":"Point"}
}
