{
  "type": "Feature",
  "properties": {
    "date:inception_lower":"1980-01-01",
    "date:inception_upper":"1980-01-31",
    "iso:country":"GB",
    "wof:name":"DN31 2BH",
    "wof:placetype":"postalcode"
},
  "geometry": {"coordinates":[-0.108523,53.567689],"type":"Point"}
}