{
  "type": "Feature",
  "properties": {
    "iso:country":"GB",
    "wof:name":"IV40 8JD",
    "wof:placetype":"postalcode"
},
  "geometry": {"coordinates":[-5.61963288652708,57.21361028803574],"type":"Point"}
}