{
  "type": "Feature",
  "properties": {
    "iso:country": "GB",
    "wof:name": "IV40 8JD",
    "wof:placetype": "postalcode"
  },
  "geometry": {"coordinates":[-5.619633,57.21361],"type":"Point"}
}
