{
  "type": "Feature",
  "properties": {
    "date:inception_lower": "1997-06-01",
    "date:inception_upper": "1997-06-01",
    "iso:country": "GB",
    "wof:name": "IV40 8JD",
    "wof:placetype": "postalcode"
  },
  "geometry": {"coordinates":[-5.619633,57.21361],"type":"Point"}
}
