{
  "type": "Feature",
  "properties": {
    "iso:country": "GB",
    "wof:name": "KY8 5JD",
    "wof:placetype": "postalcode"
  },
  "geometry": {"coordinates":[-3.042053,56.211012],"type":"Point"}
}
