{
  "type": "Feature",
  "properties": {
    "iso:country":"GB",
    "wof:name":"ST5 0QD",
    "wof:placetype":"postalcode"
},
  "geometry": {"coordinates":[-2.21083771674029,53.02006457341054],"type":"Point"}
}