{
  "type": "Feature",
  "properties": {
    "iso:country":"GB",
    "wof:name":"FY6 0QP",
    "wof:placetype":"postalcode"
},
  "geometry": {"coordinates":[-2.95855935801248,53.89998948891722],"type":"Point"}
}