{
  "type": "Feature",
  "properties": {
    "iso:country": "GB",
    "wof:name": "NN6 0PT",
    "wof:placetype": "postalcode"
  },
  "geometry": {"coordinates":[-0.740656,52.263959],"type":"Point"}
}
