{
  "type": "Feature",
  "properties": {
    "iso:country":"GB",
    "wof:name":"NN6 0PT",
    "wof:placetype":"postalcode"
},
  "geometry": {"coordinates":[-0.74065566889465,52.26395917620673],"type":"Point"}
}