{
  "type": "Feature",
  "properties": {
    "date:inception_lower":"1980-01-01",
    "date:inception_upper":"1980-01-31",
    "iso:country":"GB",
    "wof:name":"NN6 0PT",
    "wof:placetype":"postalcode"
},
  "geometry": {"coordinates":[-0.740656,52.263959],"type":"Point"}
}