{
  "type": "Feature",
  "properties": {
    "iso:country": "GB",
    "wof:name": "CF63 1RP",
    "wof:placetype": "postalcode"
  },
  "geometry": {"coordinates":[-3.262414,51.418634],"type":"Point"}
}
