{
  "type": "Feature",
  "properties": {
    "iso:country":"GB",
    "wof:name":"CF63 1RP",
    "wof:placetype":"postalcode"
},
  "geometry": {"coordinates":[-3.26241447724933,51.41863426260934],"type":"Point"}
}