{
  "type": "Feature",
  "properties": {
    "iso:country":"GB",
    "wof:name":"BR3 5EY",
    "wof:placetype":"postalcode"
},
  "geometry": {"coordinates":[-0.00956799035398,51.41026400506726],"type":"Point"}
}