{
  "type": "Feature",
  "properties": {
    "iso:country": "GB",
    "wof:name": "CM14 5NB",
    "wof:placetype": "postalcode"
  },
  "geometry": {"coordinates":[0.270592,51.61097],"type":"Point"}
}
