{
  "type": "Feature",
  "properties": {
    "date:inception_lower": "2016-04-01",
    "date:inception_upper": "2016-04-01",
    "iso:country": "GB",
    "wof:name": "BD7 1AE",
    "wof:placetype": "postalcode"
  },
  "geometry": {"coordinates":[-1.769645,53.788705],"type":"Point"}
}
