{
  "type": "Feature",
  "properties": {
    "iso:country":"GB",
    "wof:name":"HA6 2TD",
    "wof:placetype":"postalcode"
},
  "geometry": {"coordinates":[-0.44548859195353,51.60609738766484],"type":"Point"}
}