{
  "type": "Feature",
  "properties": {
    "iso:country":"GB",
    "wof:name":"SL4 3AH",
    "wof:placetype":"postalcode"
},
  "geometry": {"coordinates":[-0.60893643092831,51.47674783348963],"type":"Point"}
}