{
  "type": "Feature",
  "properties": {
    "iso:country":"GB",
    "wof:name":"PL3 6SP",
    "wof:placetype":"postalcode"
},
  "geometry": {"coordinates":[-4.10512883663892,50.39424550523189],"type":"Point"}
}