{
  "type": "Feature",
  "properties": {
    "iso:country":"GB",
    "wof:name":"SK9 1LS",
    "wof:placetype":"postalcode"
},
  "geometry": {"coordinates":[-2.23141560155361,53.32386087817094],"type":"Point"}
}