{
  "type": "Feature",
  "properties": {
    "iso:country":"GB",
    "wof:name":"WV11 2EG",
    "wof:placetype":"postalcode"
},
  "geometry": {"coordinates":[-2.06203700521156,52.62861092506778],"type":"Point"}
}