{
  "type": "Feature",
  "properties": {
    "iso:country":"GB",
    "wof:name":"HA4 0UL",
    "wof:placetype":"postalcode"
},
  "geometry": {"coordinates":[-0.39760951790052,51.56486313346937],"type":"Point"}
}