{
  "type": "Feature",
  "properties": {
    "iso:country":"GB",
    "wof:name":"FK2 7AQ",
    "wof:placetype":"postalcode"
},
  "geometry": {"coordinates":[-3.7750843448594,56.00255800185458],"type":"Point"}
}