{
  "type": "Feature",
  "properties": {
    "iso:country":"GB",
    "wof:name":"TW8 9NR",
    "wof:placetype":"postalcode"
},
  "geometry": {"coordinates":[-0.30937911737758,51.49255902812423],"type":"Point"}
}