{
  "type": "Feature",
  "properties": {
    "iso:country":"GB",
    "wof:name":"PA2 0NQ",
    "wof:placetype":"postalcode"
},
  "geometry": {"coordinates":[-4.46403266263721,55.83223563428012],"type":"Point"}
}