{
  "type": "Feature",
  "properties": {
    "iso:country": "GB",
    "wof:name": "SW1W 8EL",
    "wof:placetype": "postalcode"
  },
  "geometry": {"coordinates":[-0.159,51.492246],"type":"Point"}
}
