{
  "type": "Feature",
  "properties": {
    "iso:country": "GB",
    "wof:name": "SO31 5EY",
    "wof:placetype": "postalcode"
  },
  "geometry": {"coordinates":[-1.351097,50.871217],"type":"Point"}
}
