{
  "type": "Feature",
  "properties": {
    "iso:country":"GB",
    "wof:name":"SW15 3BD",
    "wof:placetype":"postalcode"
},
  "geometry": {"coordinates":[-0.22905062179387,51.45512489019843],"type":"Point"}
}