{
  "type": "Feature",
  "properties": {
    "iso:country":"GB",
    "wof:name":"M15 5EU",
    "wof:placetype":"postalcode"
},
  "geometry": {"coordinates":[-2.24948616010241,53.46427114890353],"type":"Point"}
}