{
  "type": "Feature",
  "properties": {
    "date:inception_lower":"2012-07-01",
    "date:inception_upper":"2012-07-31",
    "iso:country":"GB",
    "wof:name":"M15 5EU",
    "wof:placetype":"postalcode"
},
  "geometry": {"coordinates":[-2.249486,53.46419],"type":"Point"}
}