{
  "type": "Feature",
  "properties": {
    "iso:country": "GB",
    "wof:name": "M15 5EU",
    "wof:placetype": "postalcode"
  },
  "geometry": {"coordinates":[-2.249486,53.46419],"type":"Point"}
}
