{
  "type": "Feature",
  "properties": {
    "iso:country":"GB",
    "wof:name":"EH55 8EF",
    "wof:placetype":"postalcode"
},
  "geometry": {"coordinates":[-3.57507990520798,55.85014041042474],"type":"Point"}
}