{
  "type": "Feature",
  "properties": {
    "iso:country":"GB",
    "wof:name":"DL2 2PB",
    "wof:placetype":"postalcode"
},
  "geometry": {"coordinates":[-1.52305885028407,54.45632959836079],"type":"Point"}
}