{
  "type": "Feature",
  "properties": {
    "iso:country":"GB",
    "wof:name":"L11 8NE",
    "wof:placetype":"postalcode"
},
  "geometry": {"coordinates":[-2.93225531269783,53.43981457271696],"type":"Point"}
}