{
  "type": "Feature",
  "properties": {
    "date:inception_lower": "2005-08-01",
    "date:inception_upper": "2005-08-01",
    "iso:country": "GB",
    "wof:name": "SW8 1AP",
    "wof:placetype": "postalcode"
  },
  "geometry": {"coordinates":[-0.116139,51.479093],"type":"Point"}
}
