{
  "type": "Feature",
  "properties": {
    "iso:country":"GB",
    "wof:name":"SW8 1AP",
    "wof:placetype":"postalcode"
},
  "geometry": {"coordinates":[-0.11613865286938,51.4790926785294],"type":"Point"}
}