{
  "type": "Feature",
  "properties": {
    "iso:country":"GB",
    "wof:name":"ST4 3JX",
    "wof:placetype":"postalcode"
},
  "geometry": {"coordinates":[-2.15330869213133,52.99859676025697],"type":"Point"}
}