{
  "type": "Feature",
  "properties": {
    "iso:country":"GB",
    "wof:name":"S35 2ES",
    "wof:placetype":"postalcode"
},
  "geometry": {"coordinates":[-1.47369063184661,53.46559442055105],"type":"Point"}
}