{
  "type": "Feature",
  "properties": {
    "iso:country":"GB",
    "wof:name":"WS12 2NE",
    "wof:placetype":"postalcode"
},
  "geometry": {"coordinates":[-1.99547349770237,52.70022100709154],"type":"Point"}
}