{
  "type": "Feature",
  "properties": {
    "iso:country":"GB",
    "wof:name":"OL12 7TN",
    "wof:placetype":"postalcode"
},
  "geometry": {"coordinates":[-2.22595130413161,53.62990148909664],"type":"Point"}
}