{
  "type": "Feature",
  "properties": {
    "iso:country":"GB",
    "wof:name":"PA1 1XG",
    "wof:placetype":"postalcode"
},
  "geometry": {"coordinates":[-4.4235598317888,55.84215378318162],"type":"Point"}
}