{
  "type": "Feature",
  "properties": {
    "iso:country": "GB",
    "wof:name": "PA1 1XG",
    "wof:placetype": "postalcode"
  },
  "geometry": {"coordinates":[-4.42356,55.842154],"type":"Point"}
}
