{
  "type": "Feature",
  "properties": {
    "iso:country":"GB",
    "wof:name":"DN36 4BB",
    "wof:placetype":"postalcode"
},
  "geometry": {"coordinates":[-0.0357167363611,53.53479003914183],"type":"Point"}
}