{
  "type": "Feature",
  "properties": {
    "iso:country": "GB",
    "wof:name": "DN36 4BB",
    "wof:placetype": "postalcode"
  },
  "geometry": {"coordinates":[-0.035717,53.53479],"type":"Point"}
}
