{
  "type": "Feature",
  "properties": {
    "iso:country":"GB",
    "wof:name":"RG7 4UX",
    "wof:placetype":"postalcode"
},
  "geometry": {"coordinates":[-1.13801433206045,51.40037278926672],"type":"Point"}
}