{
  "type": "Feature",
  "properties": {
    "iso:country": "GB",
    "wof:name": "RG7 4UX",
    "wof:placetype": "postalcode"
  },
  "geometry": {"coordinates":[-1.138014,51.400373],"type":"Point"}
}
