{
  "type": "Feature",
  "properties": {
    "iso:country":"GB",
    "wof:name":"RG27 8HU",
    "wof:placetype":"postalcode"
},
  "geometry": {"coordinates":[-0.91603688811487,51.29603896634362],"type":"Point"}
}