{
  "type": "Feature",
  "properties": {
    "iso:country": "GB",
    "wof:name": "HX6 2QN",
    "wof:placetype": "postalcode"
  },
  "geometry": {"coordinates":[-1.912684,53.70944],"type":"Point"}
}
