{
  "type": "Feature",
  "properties": {
    "iso:country": "GB",
    "wof:name": "BS14 8HE",
    "wof:placetype": "postalcode"
  },
  "geometry": {"coordinates":[-2.552789,51.41067],"type":"Point"}
}
