{
  "type": "Feature",
  "properties": {
    "date:inception_lower": "1995-07-01",
    "date:inception_upper": "1995-07-01",
    "iso:country": "GB",
    "wof:name": "L2 8SZ",
    "wof:placetype": "postalcode"
  },
  "geometry": {"coordinates":[-2.993255,53.407502],"type":"Point"}
}
