{
  "type": "Feature",
  "properties": {
    "iso:country": "GB",
    "wof:name": "CV37 8TB",
    "wof:placetype": "postalcode"
  },
  "geometry": {"coordinates":[-1.742457,52.114349],"type":"Point"}
}
