{
  "type": "Feature",
  "properties": {
    "iso:country":"GB",
    "wof:name":"MK40 4AA",
    "wof:placetype":"postalcode"
},
  "geometry": {"coordinates":[-0.49590629460692,52.14149485119852],"type":"Point"}
}