{
  "type": "Feature",
  "properties": {
    "iso:country":"GB",
    "wof:name":"LL57 4RB",
    "wof:placetype":"postalcode"
},
  "geometry": {"coordinates":[-4.09663996048901,53.18565828569638],"type":"Point"}
}