{
  "type": "Feature",
  "properties": {
    "date:inception_lower": "1980-01-01",
    "date:inception_upper": "1980-01-01",
    "iso:country": "GB",
    "wof:name": "LL57 4RB",
    "wof:placetype": "postalcode"
  },
  "geometry": {"coordinates":[-4.09664,53.185658],"type":"Point"}
}
