{
  "type": "Feature",
  "properties": {
    "iso:country":"GB",
    "wof:name":"TN12 7ES",
    "wof:placetype":"postalcode"
},
  "geometry": {"coordinates":[0.36224274650815,51.1533575969674],"type":"Point"}
}