{
  "type": "Feature",
  "properties": {
    "iso:country":"GB",
    "wof:name":"TS23 4BU",
    "wof:placetype":"postalcode"
},
  "geometry": {"coordinates":[-1.26674328711956,54.61180858615582],"type":"Point"}
}