{
  "type": "Feature",
  "properties": {
    "iso:country": "GB",
    "wof:name": "TS23 4BU",
    "wof:placetype": "postalcode"
  },
  "geometry": {"coordinates":[-1.266743,54.611809],"type":"Point"}
}
