{
  "type": "Feature",
  "properties": {
    "date:inception_lower": "1980-01-01",
    "date:inception_upper": "1980-01-01",
    "iso:country": "GB",
    "wof:name": "TS23 4BU",
    "wof:placetype": "postalcode"
  },
  "geometry": {"coordinates":[-1.266743,54.611809],"type":"Point"}
}
