{
  "type": "Feature",
  "properties": {
    "iso:country":"GB",
    "wof:name":"MK18 4BS",
    "wof:placetype":"postalcode"
},
  "geometry": {"coordinates":[-0.99293186399176,51.97778281715468],"type":"Point"}
}