{
  "type": "Feature",
  "properties": {
    "iso:country": "GB",
    "wof:name": "MK18 4BS",
    "wof:placetype": "postalcode"
  },
  "geometry": {"coordinates":[-0.992157,51.977732],"type":"Point"}
}
