{
  "type": "Feature",
  "properties": {
    "date:inception_lower": "1980-01-01",
    "date:inception_upper": "1980-01-01",
    "iso:country": "GB",
    "wof:name": "MK18 4BS",
    "wof:placetype": "postalcode"
  },
  "geometry": {"coordinates":[-0.992157,51.977732],"type":"Point"}
}
