{
  "type": "Feature",
  "properties": {
    "iso:country":"GB",
    "wof:name":"B90 1HR",
    "wof:placetype":"postalcode"
},
  "geometry": {"coordinates":[-1.85762142904365,52.40588003245061],"type":"Point"}
}