{
  "type": "Feature",
  "properties": {
    "iso:country": "GB",
    "wof:name": "HP14 3AN",
    "wof:placetype": "postalcode"
  },
  "geometry": {"coordinates":[-0.894605,51.659047],"type":"Point"}
}
