{
  "type": "Feature",
  "properties": {
    "iso:country":"GB",
    "wof:name":"B11 1TY",
    "wof:placetype":"postalcode"
},
  "geometry": {"coordinates":[-1.86224734862346,52.45928632184818],"type":"Point"}
}