{
  "type": "Feature",
  "properties": {
    "iso:country":"GB",
    "wof:name":"N22 5RQ",
    "wof:placetype":"postalcode"
},
  "geometry": {"coordinates":[-0.1060779585185,51.59844108328722],"type":"Point"}
}