{
  "type": "Feature",
  "properties": {
    "iso:country":"GB",
    "wof:name":"PE15 9LQ",
    "wof:placetype":"postalcode"
},
  "geometry": {"coordinates":[0.08888904269555,52.54607719930146],"type":"Point"}
}