{
  "type": "Feature",
  "properties": {
    "iso:country": "GB",
    "wof:name": "DN16 3NZ",
    "wof:placetype": "postalcode"
  },
  "geometry": {"coordinates":[-0.655835,53.546581],"type":"Point"}
}
