{
  "type": "Feature",
  "properties": {
    "iso:country":"GB",
    "wof:name":"SA20 0EA",
    "wof:placetype":"postalcode"
},
  "geometry": {"coordinates":[-3.79845471665909,51.99702318013212],"type":"Point"}
}