{
  "type": "Feature",
  "properties": {
    "iso:country": "GB",
    "wof:name": "SL6 0HS",
    "wof:placetype": "postalcode"
  },
  "geometry": {"coordinates":[-0.6834,51.54951],"type":"Point"}
}
