{
  "type": "Feature",
  "properties": {
    "date:inception_lower": "1980-01-01",
    "date:inception_upper": "1980-01-01",
    "iso:country": "GB",
    "wof:name": "SL6 0HS",
    "wof:placetype": "postalcode"
  },
  "geometry": {"coordinates":[-0.6834,51.54951],"type":"Point"}
}
