{
  "type": "Feature",
  "properties": {
    "iso:country":"GB",
    "wof:name":"SL6 0HS",
    "wof:placetype":"postalcode"
},
  "geometry": {"coordinates":[-0.68340148379073,51.54959718480621],"type":"Point"}
}