{
  "type": "Feature",
  "properties": {
    "iso:country":"GB",
    "wof:name":"LL13 0TY",
    "wof:placetype":"postalcode"
},
  "geometry": {"coordinates":[-2.92653970993515,53.0189781556078],"type":"Point"}
}