{
  "type": "Feature",
  "properties": {
    "iso:country": "GB",
    "wof:name": "LL13 0TY",
    "wof:placetype": "postalcode"
  },
  "geometry": {"coordinates":[-2.92654,53.018978],"type":"Point"}
}
