{
  "type": "Feature",
  "properties": {
    "iso:country": "GB",
    "wof:name": "L7 4JF",
    "wof:placetype": "postalcode"
  },
  "geometry": {"coordinates":[-2.941951,53.396277],"type":"Point"}
}
