{
  "type": "Feature",
  "properties": {
    "iso:country":"GB",
    "wof:name":"W10 4AL",
    "wof:placetype":"postalcode"
},
  "geometry": {"coordinates":[-0.21549490881854,51.52993436806356],"type":"Point"}
}