{
  "type": "Feature",
  "properties": {
    "date:inception_lower":"1980-01-01",
    "date:inception_upper":"1980-01-31",
    "iso:country":"GB",
    "wof:name":"W10 4AL",
    "wof:placetype":"postalcode"
},
  "geometry": {"coordinates":[-0.215495,51.529943],"type":"Point"}
}