{
  "type": "Feature",
  "properties": {
    "iso:country": "GB",
    "wof:name": "S5 8RD",
    "wof:placetype": "postalcode"
  },
  "geometry": {"coordinates":[-1.479377,53.416937],"type":"Point"}
}
