{
  "type": "Feature",
  "properties": {
    "iso:country":"GB",
    "wof:name":"NP26 3BY",
    "wof:placetype":"postalcode"
},
  "geometry": {"coordinates":[-2.82725773403794,51.58493079882577],"type":"Point"}
}