{
  "type": "Feature",
  "properties": {
    "iso:country":"GB",
    "wof:name":"N5 2QL",
    "wof:placetype":"postalcode"
},
  "geometry": {"coordinates":[-0.09669787775711,51.55616861967429],"type":"Point"}
}