{
  "type": "Feature",
  "properties": {
    "iso:country": "GB",
    "wof:name": "LE4 8JQ",
    "wof:placetype": "postalcode"
  },
  "geometry": {"coordinates":[-1.0925,52.673034],"type":"Point"}
}
