{
  "type": "Feature",
  "properties": {
    "iso:country": "GB",
    "wof:name": "RG23 8HL",
    "wof:placetype": "postalcode"
  },
  "geometry": {"coordinates":[-1.120394,51.275614],"type":"Point"}
}
