{
  "type": "Feature",
  "properties": {
    "iso:country":"GB",
    "wof:name":"RG23 8HL",
    "wof:placetype":"postalcode"
},
  "geometry": {"coordinates":[-1.12039440917784,51.27561354766516],"type":"Point"}
}