{
  "type": "Feature",
  "properties": {
    "iso:country":"GB",
    "wof:name":"EC3V 3LA",
    "wof:placetype":"postalcode"
},
  "geometry": {"coordinates":[-0.08900012317103,51.51334692739724],"type":"Point"}
}