{
  "type": "Feature",
  "properties": {
    "iso:country":"GB",
    "wof:name":"PO13 9HJ",
    "wof:placetype":"postalcode"
},
  "geometry": {"coordinates":[-1.19709505833069,50.80663757768111],"type":"Point"}
}