{
  "type": "Feature",
  "properties": {
    "iso:country": "GB",
    "wof:name": "MK18 3JJ",
    "wof:placetype": "postalcode"
  },
  "geometry": {"coordinates":[-0.870165,51.94021],"type":"Point"}
}
