{
  "type": "Feature",
  "properties": {
    "iso:country":"GB",
    "wof:name":"MK18 3JJ",
    "wof:placetype":"postalcode"
},
  "geometry": {"coordinates":[-0.8701645840353,51.94021001056451],"type":"Point"}
}