{
  "type": "Feature",
  "properties": {
    "iso:country": "GB",
    "wof:name": "B61 0BW",
    "wof:placetype": "postalcode"
  },
  "geometry": {"coordinates":[-2.063638,52.357707],"type":"Point"}
}
