{
  "type": "Feature",
  "properties": {
    "iso:country":"GB",
    "wof:name":"WD23 2FQ",
    "wof:placetype":"postalcode"
},
  "geometry": {"coordinates":[-0.38048647200447,51.64919893030112],"type":"Point"}
}