{
  "type": "Feature",
  "properties": {
    "iso:country": "GB",
    "wof:name": "WD23 2FQ",
    "wof:placetype": "postalcode"
  },
  "geometry": {"coordinates":[-0.380486,51.649199],"type":"Point"}
}
