{
  "type": "Feature",
  "properties": {
    "iso:country":"GB",
    "wof:name":"KT16 8RW",
    "wof:placetype":"postalcode"
},
  "geometry": {"coordinates":[-0.49187655235849,51.40302118728007],"type":"Point"}
}