{
  "type": "Feature",
  "properties": {
    "iso:country": "GB",
    "wof:name": "KT16 8RW",
    "wof:placetype": "postalcode"
  },
  "geometry": {"coordinates":[-0.491794,51.402759],"type":"Point"}
}
