{
  "type": "Feature",
  "properties": {
    "iso:country":"GB",
    "wof:name":"CO7 7RU",
    "wof:placetype":"postalcode"
},
  "geometry": {"coordinates":[0.98184777164528,51.91735188173314],"type":"Point"}
}