{
  "type": "Feature",
  "properties": {
    "iso:country": "GB",
    "wof:name": "DA10 0HG",
    "wof:placetype": "postalcode"
  },
  "geometry": {"coordinates":[0.310518,51.446136],"type":"Point"}
}
