{
  "type": "Feature",
  "properties": {
    "iso:country":"GB",
    "wof:name":"DA10 0HG",
    "wof:placetype":"postalcode"
},
  "geometry": {"coordinates":[0.31051772566682,51.4461358168571],"type":"Point"}
}