{
  "type": "Feature",
  "properties": {
    "iso:country":"GB",
    "wof:name":"TQ1 2ET",
    "wof:placetype":"postalcode"
},
  "geometry": {"coordinates":[-3.51427494432967,50.46098268876833],"type":"Point"}
}