{
  "type": "Feature",
  "properties": {
    "date:inception_lower": "1996-06-01",
    "date:inception_upper": "1996-06-01",
    "iso:country": "GB",
    "wof:name": "G72 9UL",
    "wof:placetype": "postalcode"
  },
  "geometry": {"coordinates":[-4.113499,55.792845],"type":"Point"}
}
