{
  "type": "Feature",
  "properties": {
    "date:inception_lower":"1980-01-01",
    "date:inception_upper":"1980-01-31",
    "iso:country":"GB",
    "wof:name":"WV16 6PD",
    "wof:placetype":"postalcode"
},
  "geometry": {"coordinates":[-2.400233,52.434739],"type":"Point"}
}