{
  "type": "Feature",
  "properties": {
    "iso:country":"GB",
    "wof:name":"WV16 6PD",
    "wof:placetype":"postalcode"
},
  "geometry": {"coordinates":[-2.40023308926245,52.43473871467707],"type":"Point"}
}