{
  "type": "Feature",
  "properties": {
    "iso:country":"GB",
    "wof:name":"BR2 0DJ",
    "wof:placetype":"postalcode"
},
  "geometry": {"coordinates":[0.00772182064406,51.40710033844641],"type":"Point"}
}