{
  "type": "Feature",
  "properties": {
    "iso:country": "GB",
    "wof:name": "BR2 0DJ",
    "wof:placetype": "postalcode"
  },
  "geometry": {"coordinates":[0.007722,51.4071],"type":"Point"}
}
