{
  "type": "Feature",
  "properties": {
    "iso:country":"GB",
    "wof:name":"CM2 7AE",
    "wof:placetype":"postalcode"
},
  "geometry": {"coordinates":[0.51535944135243,51.71138475274946],"type":"Point"}
}