{
  "type": "Feature",
  "properties": {
    "date:inception_lower": "1980-01-01",
    "date:inception_upper": "1980-01-01",
    "iso:country": "GB",
    "wof:name": "CM2 7AE",
    "wof:placetype": "postalcode"
  },
  "geometry": {"coordinates":[0.515359,51.711385],"type":"Point"}
}
