{
  "type": "Feature",
  "properties": {
    "iso:country":"GB",
    "wof:name":"SA14 8EH",
    "wof:placetype":"postalcode"
},
  "geometry": {"coordinates":[-4.13392816750552,51.70409533799612],"type":"Point"}
}