{
  "type": "Feature",
  "properties": {
    "iso:country": "GB",
    "wof:name": "E17 3SZ",
    "wof:placetype": "postalcode"
  },
  "geometry": {"coordinates":[-0.018673,51.583608],"type":"Point"}
}
