{
  "type": "Feature",
  "properties": {
    "iso:country":"GB",
    "wof:name":"E17 3SZ",
    "wof:placetype":"postalcode"
},
  "geometry": {"coordinates":[-0.01867352006534,51.58360819977666],"type":"Point"}
}