{
  "type": "Feature",
  "properties": {
    "iso:country": "GB",
    "wof:name": "PL15 7PN",
    "wof:placetype": "postalcode"
  },
  "geometry": {"coordinates":[-4.430349,50.580934],"type":"Point"}
}
