{
  "type": "Feature",
  "properties": {
    "iso:country":"GB",
    "wof:name":"DE7 4BW",
    "wof:placetype":"postalcode"
},
  "geometry": {"coordinates":[-1.30387788251746,52.95950681460396],"type":"Point"}
}