{
  "type": "Feature",
  "properties": {
    "date:inception_lower": "1985-04-01",
    "date:inception_upper": "1985-04-01",
    "iso:country": "GB",
    "wof:name": "L12 0JY",
    "wof:placetype": "postalcode"
  },
  "geometry": {"coordinates":[-2.88535,53.448684],"type":"Point"}
}
