{
  "type": "Feature",
  "properties": {
    "iso:country":"GB",
    "wof:name":"L12 0JY",
    "wof:placetype":"postalcode"
},
  "geometry": {"coordinates":[-2.8853497353499,53.44868392113199],"type":"Point"}
}