{
  "type": "Feature",
  "properties": {
    "date:inception_lower": "1996-06-01",
    "date:inception_upper": "1996-06-01",
    "iso:country": "GB",
    "wof:name": "AB25 3AF",
    "wof:placetype": "postalcode"
  },
  "geometry": {"coordinates":[-2.121178,57.159789],"type":"Point"}
}
