{
  "type": "Feature",
  "properties": {
    "iso:country":"GB",
    "wof:name":"TN11 8LW",
    "wof:placetype":"postalcode"
},
  "geometry": {"coordinates":[0.17042424394394,51.19918216797503],"type":"Point"}
}