{
  "type": "Feature",
  "properties": {
    "date:inception_lower": "1980-01-01",
    "date:inception_upper": "1980-01-01",
    "iso:country": "GB",
    "wof:name": "LA2 0BD",
    "wof:placetype": "postalcode"
  },
  "geometry": {"coordinates":[-2.823137,53.992999],"type":"Point"}
}
