{
  "type": "Feature",
  "properties": {
    "iso:country":"GB",
    "wof:name":"LA2 0BD",
    "wof:placetype":"postalcode"
},
  "geometry": {"coordinates":[-2.82363041584425,53.99302848533833],"type":"Point"}
}