{
  "type": "Feature",
  "properties": {
    "iso:country": "GB",
    "wof:name": "GL6 0RY",
    "wof:placetype": "postalcode"
  },
  "geometry": {"coordinates":[-2.228259,51.692553],"type":"Point"}
}
