{
  "type": "Feature",
  "properties": {
    "iso:country":"GB",
    "wof:name":"GL6 0RY",
    "wof:placetype":"postalcode"
},
  "geometry": {"coordinates":[-2.22825939326036,51.69255341018222],"type":"Point"}
}