{
  "type": "Feature",
  "properties": {
    "iso:country":"GB",
    "wof:name":"BA16 0HD",
    "wof:placetype":"postalcode"
},
  "geometry": {"coordinates":[-2.73909970563179,51.12194420843595],"type":"Point"}
}