{
  "type": "Feature",
  "properties": {
    "date:inception_lower": "1980-01-01",
    "date:inception_upper": "1980-01-01",
    "iso:country": "GB",
    "wof:name": "BA16 0HD",
    "wof:placetype": "postalcode"
  },
  "geometry": {"coordinates":[-2.7391,51.121944],"type":"Point"}
}
