{
  "type": "Feature",
  "properties": {
    "iso:country": "GB",
    "wof:name": "BA16 0HD",
    "wof:placetype": "postalcode"
  },
  "geometry": {"coordinates":[-2.7391,51.121944],"type":"Point"}
}
