{
  "type": "Feature",
  "properties": {
    "date:inception_lower": "1980-01-01",
    "date:inception_upper": "1980-01-01",
    "iso:country": "GB",
    "wof:name": "B69 3JD",
    "wof:placetype": "postalcode"
  },
  "geometry": {"coordinates":[-2.04188,52.515438],"type":"Point"}
}
