{
  "type": "Feature",
  "properties": {
    "iso:country":"GB",
    "wof:name":"NE5 1DT",
    "wof:placetype":"postalcode"
},
  "geometry": {"coordinates":[-1.71713730910393,54.99529942639025],"type":"Point"}
}