{
  "type": "Feature",
  "properties": {
    "date:inception_lower": "1980-01-01",
    "date:inception_upper": "1980-01-01",
    "iso:country": "GB",
    "wof:name": "PE22 7DS",
    "wof:placetype": "postalcode"
  },
  "geometry": {"coordinates":[-0.091456,53.030165],"type":"Point"}
}
