{
  "type": "Feature",
  "properties": {
    "iso:country":"GB",
    "wof:name":"S64 8AE",
    "wof:placetype":"postalcode"
},
  "geometry": {"coordinates":[-1.29965746860277,53.48989668388045],"type":"Point"}
}