{
  "type": "Feature",
  "properties": {
    "iso:country": "GB",
    "wof:name": "S64 8AE",
    "wof:placetype": "postalcode"
  },
  "geometry": {"coordinates":[-1.299657,53.489897],"type":"Point"}
}
