{
  "type": "Feature",
  "properties": {
    "iso:country":"GB",
    "wof:name":"SS9 4TE",
    "wof:placetype":"postalcode"
},
  "geometry": {"coordinates":[0.63309646774397,51.56570055362925],"type":"Point"}
}