{
  "type": "Feature",
  "properties": {
    "iso:country":"GB",
    "wof:name":"ST17 0XQ",
    "wof:placetype":"postalcode"
},
  "geometry": {"coordinates":[-1.97842849049009,52.78641102905891],"type":"Point"}
}