{
  "type": "Feature",
  "properties": {
    "iso:country": "GB",
    "wof:name": "ST17 0XQ",
    "wof:placetype": "postalcode"
  },
  "geometry": {"coordinates":[-1.978675,52.78641],"type":"Point"}
}
