{
  "type": "Feature",
  "properties": {
    "iso:country": "GB",
    "wof:name": "LE5 4QH",
    "wof:placetype": "postalcode"
  },
  "geometry": {"coordinates":[-1.093962,52.637715],"type":"Point"}
}
