{
  "type": "Feature",
  "properties": {
    "iso:country":"GB",
    "wof:name":"BL6 7EF",
    "wof:placetype":"postalcode"
},
  "geometry": {"coordinates":[-2.54156150324243,53.6035059350568],"type":"Point"}
}