{
  "type": "Feature",
  "properties": {
    "date:inception_lower": "2008-09-01",
    "date:inception_upper": "2008-09-01",
    "iso:country": "GB",
    "wof:name": "DA6 8AE",
    "wof:placetype": "postalcode"
  },
  "geometry": {"coordinates":[0.125421,51.459018],"type":"Point"}
}
