{
  "type": "Feature",
  "properties": {
    "iso:country": "GB",
    "wof:name": "NG22 9UP",
    "wof:placetype": "postalcode"
  },
  "geometry": {"coordinates":[-1.007647,53.206716],"type":"Point"}
}
