{
  "type": "Feature",
  "properties": {
    "iso:country": "GB",
    "wof:name": "SS0 8FL",
    "wof:placetype": "postalcode"
  },
  "geometry": {"coordinates":[0.685767,51.543655],"type":"Point"}
}
