{
  "type": "Feature",
  "properties": {
    "iso:country":"GB",
    "wof:name":"EH4 7BE",
    "wof:placetype":"postalcode"
},
  "geometry": {"coordinates":[-3.26993716776299,55.96169395573651],"type":"Point"}
}