{
  "type": "Feature",
  "properties": {
    "iso:country":"GB",
    "wof:name":"BH1 4HT",
    "wof:placetype":"postalcode"
},
  "geometry": {"coordinates":[-1.84262197794575,50.72899774043216],"type":"Point"}
}