{
  "type": "Feature",
  "properties": {
    "iso:country": "GB",
    "wof:name": "PL3 4AW",
    "wof:placetype": "postalcode"
  },
  "geometry": {"coordinates":[-4.160047,50.379441],"type":"Point"}
}
