{
  "type": "Feature",
  "properties": {
    "iso:country": "GB",
    "wof:name": "CA9 3JT",
    "wof:placetype": "postalcode"
  },
  "geometry": {"coordinates":[-2.428936,54.815386],"type":"Point"}
}
