{
  "type": "Feature",
  "properties": {
    "iso:country":"GB",
    "wof:name":"CA9 3JT",
    "wof:placetype":"postalcode"
},
  "geometry": {"coordinates":[-2.42893613309628,54.81538562155889],"type":"Point"}
}