{
  "type": "Feature",
  "properties": {
    "date:inception_lower": "2016-06-01",
    "date:inception_upper": "2016-06-01",
    "iso:country": "GB",
    "wof:name": "ST7 2GW",
    "wof:placetype": "postalcode"
  },
  "geometry": {"coordinates":[-2.333271,53.09726],"type":"Point"}
}
