{
  "type": "Feature",
  "properties": {
    "date:inception_lower": "2008-03-01",
    "date:inception_upper": "2008-03-01",
    "iso:country": "GB",
    "wof:name": "WR14 2FE",
    "wof:placetype": "postalcode"
  },
  "geometry": {"coordinates":[-2.306864,52.11376],"type":"Point"}
}
