{
  "type": "Feature",
  "properties": {
    "date:inception_lower":"2008-10-01",
    "date:inception_upper":"2008-10-31",
    "iso:country":"GB",
    "wof:name":"SA1 1PG",
    "wof:placetype":"postalcode"
},
  "geometry": {"coordinates":[-3.943479,51.613584],"type":"Point"}
}