{
  "type": "Feature",
  "properties": {
    "iso:country":"GB",
    "wof:name":"SA1 1PG",
    "wof:placetype":"postalcode"
},
  "geometry": {"coordinates":[-3.94347907271525,51.61358380505456],"type":"Point"}
}