{
  "type": "Feature",
  "properties": {
    "iso:country": "GB",
    "wof:name": "SA1 1PG",
    "wof:placetype": "postalcode"
  },
  "geometry": {"coordinates":[-3.943479,51.613584],"type":"Point"}
}
