{
  "type": "Feature",
  "properties": {
    "date:inception_lower": "1999-06-01",
    "date:inception_upper": "1999-06-01",
    "iso:country": "GB",
    "wof:name": "CF24 1QX",
    "wof:placetype": "postalcode"
  },
  "geometry": {"coordinates":[-3.148118,51.489992],"type":"Point"}
}
