{
  "type": "Feature",
  "properties": {
    "iso:country":"GB",
    "wof:name":"CF24 1QX",
    "wof:placetype":"postalcode"
},
  "geometry": {"coordinates":[-3.14811814403335,51.48999192088417],"type":"Point"}
}