{
  "type": "Feature",
  "properties": {
    "iso:country":"GB",
    "wof:name":"EX24 6RX",
    "wof:placetype":"postalcode"
},
  "geometry": {"coordinates":[-3.1057749556783,50.73796768607396],"type":"Point"}
}