{
  "type": "Feature",
  "properties": {
    "iso:country": "GB",
    "wof:name": "EX24 6RX",
    "wof:placetype": "postalcode"
  },
  "geometry": {"coordinates":[-3.105783,50.737957],"type":"Point"}
}
