{
  "type": "Feature",
  "properties": {
    "iso:country":"GB",
    "wof:name":"SY11 2PZ",
    "wof:placetype":"postalcode"
},
  "geometry": {"coordinates":[-3.0418067328516,52.85555380667233],"type":"Point"}
}