{
  "type": "Feature",
  "properties": {
    "iso:country":"GB",
    "wof:name":"NE65 9QR",
    "wof:placetype":"postalcode"
},
  "geometry": {"coordinates":[-1.73100399223777,55.25880933978799],"type":"Point"}
}