{
  "type": "Feature",
  "properties": {
    "date:inception_lower":"1980-01-01",
    "date:inception_upper":"1980-01-31",
    "iso:country":"GB",
    "wof:name":"BS7 0AJ",
    "wof:placetype":"postalcode"
},
  "geometry": {"coordinates":[-2.581568,51.48936],"type":"Point"}
}