{
  "type": "Feature",
  "properties": {
    "date:inception_lower":"1980-01-01",
    "date:inception_upper":"1980-01-31",
    "iso:country":"GB",
    "wof:name":"ML5 1NS",
    "wof:placetype":"postalcode"
},
  "geometry": {"coordinates":[-4.039605,55.863527],"type":"Point"}
}