{
  "type": "Feature",
  "properties": {
    "iso:country":"GB",
    "wof:name":"SW1Y 6BU",
    "wof:placetype":"postalcode"
},
  "geometry": {"coordinates":[-0.13718320932604,51.50761151193988],"type":"Point"}
}