{
  "type": "Feature",
  "properties": {
    "iso:country":"GB",
    "wof:name":"TW16 7HD",
    "wof:placetype":"postalcode"
},
  "geometry": {"coordinates":[-0.43329455074027,51.4168023304461],"type":"Point"}
}