{
  "type": "Feature",
  "properties": {
    "iso:country":"GB",
    "wof:name":"BH8 8JW",
    "wof:placetype":"postalcode"
},
  "geometry": {"coordinates":[-1.86666539265319,50.72912657596484],"type":"Point"}
}