{
  "type": "Feature",
  "properties": {
    "iso:country":"GB",
    "wof:name":"HD4 7JE",
    "wof:placetype":"postalcode"
},
  "geometry": {"coordinates":[-1.80651478493387,53.61323217820748],"type":"Point"}
}