{
  "type": "Feature",
  "properties": {
    "date:inception_lower":"1980-01-01",
    "date:inception_upper":"1980-01-31",
    "iso:country":"GB",
    "wof:name":"NE46 3JE",
    "wof:placetype":"postalcode"
},
  "geometry": {"coordinates":[-2.11497,54.970744],"type":"Point"}
}