{
  "type": "Feature",
  "properties": {
    "iso:country": "GB",
    "wof:name": "NE46 3JE",
    "wof:placetype": "postalcode"
  },
  "geometry": {"coordinates":[-2.11497,54.970744],"type":"Point"}
}
