{
  "type": "Feature",
  "properties": {
    "iso:country":"GB",
    "wof:name":"TD7 4QB",
    "wof:placetype":"postalcode"
},
  "geometry": {"coordinates":[-2.75099518464413,55.53863440441983],"type":"Point"}
}