{
  "type": "Feature",
  "properties": {
    "iso:country":"GB",
    "wof:name":"MK3 5HW",
    "wof:placetype":"postalcode"
},
  "geometry": {"coordinates":[-0.74572747515592,51.99176489882019],"type":"Point"}
}