{
  "type": "Feature",
  "properties": {
    "iso:country": "GB",
    "wof:name": "M35 9PR",
    "wof:placetype": "postalcode"
  },
  "geometry": {"coordinates":[-2.149845,53.510369],"type":"Point"}
}
