{
  "type": "Feature",
  "properties": {
    "iso:country":"GB",
    "wof:name":"M35 9PR",
    "wof:placetype":"postalcode"
},
  "geometry": {"coordinates":[-2.14984479759006,53.51036875288008],"type":"Point"}
}