{
  "type": "Feature",
  "properties": {
    "iso:country":"GB",
    "wof:name":"LU3 2DR",
    "wof:placetype":"postalcode"
},
  "geometry": {"coordinates":[-0.43031960759754,51.91506224960694],"type":"Point"}
}