{
  "type": "Feature",
  "properties": {
    "date:inception_lower":"1980-01-01",
    "date:inception_upper":"1980-01-31",
    "iso:country":"GB",
    "wof:name":"LU3 2DR",
    "wof:placetype":"postalcode"
},
  "geometry": {"coordinates":[-0.43032,51.915062],"type":"Point"}
}