{
  "type": "Feature",
  "properties": {
    "iso:country": "GB",
    "wof:name": "DL8 1JS",
    "wof:placetype": "postalcode"
  },
  "geometry": {"coordinates":[-1.660078,54.313252],"type":"Point"}
}
