{
  "type": "Feature",
  "properties": {
    "date:inception_lower": "1980-01-01",
    "date:inception_upper": "1980-01-01",
    "iso:country": "GB",
    "wof:name": "DL8 1JS",
    "wof:placetype": "postalcode"
  },
  "geometry": {"coordinates":[-1.660031,54.313306],"type":"Point"}
}
