{
  "type": "Feature",
  "properties": {
    "iso:country": "GB",
    "wof:name": "B49 5DU",
    "wof:placetype": "postalcode"
  },
  "geometry": {"coordinates":[-1.876007,52.220149],"type":"Point"}
}
