{
  "type": "Feature",
  "properties": {
    "iso:country":"GB",
    "wof:name":"B49 5DU",
    "wof:placetype":"postalcode"
},
  "geometry": {"coordinates":[-1.87607311565421,52.22025275576348],"type":"Point"}
}