{
  "type": "Feature",
  "properties": {
    "iso:country": "GB",
    "wof:name": "GL4 3AU",
    "wof:placetype": "postalcode"
  },
  "geometry": {"coordinates":[-2.213285,51.858224],"type":"Point"}
}
