{
  "type": "Feature",
  "properties": {
    "iso:country":"GB",
    "wof:name":"GL4 3AU",
    "wof:placetype":"postalcode"
},
  "geometry": {"coordinates":[-2.21328511870528,51.85822376730705],"type":"Point"}
}