{
  "type": "Feature",
  "properties": {
    "date:inception_lower": "1980-01-01",
    "date:inception_upper": "1980-01-01",
    "iso:country": "GB",
    "wof:name": "MK3 7RB",
    "wof:placetype": "postalcode"
  },
  "geometry": {"coordinates":[-0.771674,51.996795],"type":"Point"}
}
