{
  "type": "Feature",
  "properties": {
    "date:inception_lower":"1987-10-01",
    "date:inception_upper":"1987-10-31",
    "iso:country":"GB",
    "wof:name":"TQ1 3QG",
    "wof:placetype":"postalcode"
},
  "geometry": {"coordinates":[-3.524575,50.478085],"type":"Point"}
}