{
  "type": "Feature",
  "properties": {
    "iso:country":"GB",
    "wof:name":"TQ1 3QG",
    "wof:placetype":"postalcode"
},
  "geometry": {"coordinates":[-3.52461620015703,50.47806149828507],"type":"Point"}
}