{
  "type": "Feature",
  "properties": {
    "date:inception_lower": "1996-06-01",
    "date:inception_upper": "1996-06-01",
    "iso:country": "GB",
    "wof:name": "AB15 4UG",
    "wof:placetype": "postalcode"
  },
  "geometry": {"coordinates":[-2.131319,57.138364],"type":"Point"}
}
