{
  "type": "Feature",
  "properties": {
    "iso:country": "GB",
    "wof:name": "CV2 2EE",
    "wof:placetype": "postalcode"
  },
  "geometry": {"coordinates":[-1.44472,52.426365],"type":"Point"}
}
