{
  "type": "Feature",
  "properties": {
    "iso:country": "GB",
    "wof:name": "DE13 8TU",
    "wof:placetype": "postalcode"
  },
  "geometry": {"coordinates":[-1.739626,52.836783],"type":"Point"}
}
