{
  "type": "Feature",
  "properties": {
    "date:inception_lower": "1980-01-01",
    "date:inception_upper": "1980-01-01",
    "iso:country": "GB",
    "wof:name": "TN18 4ND",
    "wof:placetype": "postalcode"
  },
  "geometry": {"coordinates":[0.504048,51.040994],"type":"Point"}
}
