{
  "type": "Feature",
  "properties": {
    "date:inception_lower": "2021-09-01",
    "date:inception_upper": "2021-09-01",
    "iso:country": "GB",
    "wof:name": "ST17 4FQ",
    "wof:placetype": "postalcode"
  },
  "geometry": {"coordinates":[-2.116585,52.802876],"type":"Point"}
}
