{
  "type": "Feature",
  "properties": {
    "iso:country":"GB",
    "wof:name":"SW15 1PL",
    "wof:placetype":"postalcode"
},
  "geometry": {"coordinates":[-0.22227928247606,51.4634393800175],"type":"Point"}
}