{
  "type": "Feature",
  "properties": {
    "date:inception_lower": "1990-02-01",
    "date:inception_upper": "1990-02-01",
    "iso:country": "GB",
    "wof:name": "B92 8RU",
    "wof:placetype": "postalcode"
  },
  "geometry": {"coordinates":[-1.786462,52.43624],"type":"Point"}
}
