{
  "type": "Feature",
  "properties": {
    "iso:country":"GB",
    "wof:name":"B92 8RU",
    "wof:placetype":"postalcode"
},
  "geometry": {"coordinates":[-1.78646205359017,52.43624041362145],"type":"Point"}
}