{
  "type": "Feature",
  "properties": {
    "iso:country":"GB",
    "wof:name":"NE25 9QB",
    "wof:placetype":"postalcode"
},
  "geometry": {"coordinates":[-1.48507564941147,55.04254364055866],"type":"Point"}
}