{
  "type": "Feature",
  "properties": {
    "iso:country":"GB",
    "wof:name":"OL3 7NX",
    "wof:placetype":"postalcode"
},
  "geometry": {"coordinates":[-1.99436379281867,53.53788637868639],"type":"Point"}
}