{
  "type": "Feature",
  "properties": {
    "iso:country": "GB",
    "wof:name": "CW2 7DR",
    "wof:placetype": "postalcode"
  },
  "geometry": {"coordinates":[-2.440132,53.089236],"type":"Point"}
}
