{
  "type": "Feature",
  "properties": {
    "iso:country":"GB",
    "wof:name":"PE26 2XB",
    "wof:placetype":"postalcode"
},
  "geometry": {"coordinates":[-0.09386177871751,52.45373770788269],"type":"Point"}
}