{
  "type": "Feature",
  "properties": {
    "iso:country": "GB",
    "wof:name": "PE26 2XB",
    "wof:placetype": "postalcode"
  },
  "geometry": {"coordinates":[-0.093862,52.453738],"type":"Point"}
}
