{
  "type": "Feature",
  "properties": {
    "iso:country": "GB",
    "wof:name": "HP19 8BY",
    "wof:placetype": "postalcode"
  },
  "geometry": {"coordinates":[-0.828538,51.823042],"type":"Point"}
}
