{
  "type": "Feature",
  "properties": {
    "iso:country":"GB",
    "wof:name":"HP19 8BY",
    "wof:placetype":"postalcode"
},
  "geometry": {"coordinates":[-0.82853849903969,51.8230419411282],"type":"Point"}
}