{
  "type": "Feature",
  "properties": {
    "date:inception_lower":"1995-12-01",
    "date:inception_upper":"1995-12-31",
    "iso:country":"GB",
    "wof:name":"IP6 9QT",
    "wof:placetype":"postalcode"
},
  "geometry": {"coordinates":[1.141329,52.143992],"type":"Point"}
}