{
  "type": "Feature",
  "properties": {
    "iso:country":"GB",
    "wof:name":"IP6 9QT",
    "wof:placetype":"postalcode"
},
  "geometry": {"coordinates":[1.14120337353946,52.14408681266819],"type":"Point"}
}