{
  "type": "Feature",
  "properties": {
    "iso:country":"GB",
    "wof:name":"NN8 3LE",
    "wof:placetype":"postalcode"
},
  "geometry": {"coordinates":[-0.71487665304306,52.29956382857928],"type":"Point"}
}