{
  "type": "Feature",
  "properties": {
    "iso:country": "GB",
    "wof:name": "GU17 0PD",
    "wof:placetype": "postalcode"
  },
  "geometry": {"coordinates":[-0.791928,51.332088],"type":"Point"}
}
