{
  "type": "Feature",
  "properties": {
    "iso:country":"GB",
    "wof:name":"GU17 0PD",
    "wof:placetype":"postalcode"
},
  "geometry": {"coordinates":[-0.79192854000165,51.33208817886138],"type":"Point"}
}