{
  "type": "Feature",
  "properties": {
    "iso:country":"GB",
    "wof:name":"LE9 7LB",
    "wof:placetype":"postalcode"
},
  "geometry": {"coordinates":[-1.32279794483433,52.574452938014],"type":"Point"}
}