{
  "type": "Feature",
  "properties": {
    "date:inception_lower": "2004-06-01",
    "date:inception_upper": "2004-06-01",
    "iso:country": "GB",
    "wof:name": "RG2 6UP",
    "wof:placetype": "postalcode"
  },
  "geometry": {"coordinates":[-0.987118,51.419865],"type":"Point"}
}
