{
  "type": "Feature",
  "properties": {
    "iso:country":"GB",
    "wof:name":"RG2 6UP",
    "wof:placetype":"postalcode"
},
  "geometry": {"coordinates":[-0.9871179581324,51.41986550223031],"type":"Point"}
}