{
  "type": "Feature",
  "properties": {
    "iso:country": "GB",
    "wof:name": "RG2 6UP",
    "wof:placetype": "postalcode"
  },
  "geometry": {"coordinates":[-0.987118,51.419865],"type":"Point"}
}
