{
  "type": "Feature",
  "properties": {
    "iso:country": "GB",
    "wof:name": "YO8 9PX",
    "wof:placetype": "postalcode"
  },
  "geometry": {"coordinates":[-1.12035,53.768983],"type":"Point"}
}
