{
  "type": "Feature",
  "properties": {
    "iso:country":"GB",
    "wof:name":"BS37 6QT",
    "wof:placetype":"postalcode"
},
  "geometry": {"coordinates":[-2.34315407490691,51.5561453283885],"type":"Point"}
}