{
  "type": "Feature",
  "properties": {
    "date:inception_lower": "1997-12-01",
    "date:inception_upper": "1997-12-01",
    "iso:country": "GB",
    "wof:name": "BS37 6QT",
    "wof:placetype": "postalcode"
  },
  "geometry": {"coordinates":[-2.343154,51.556145],"type":"Point"}
}
