{
  "type": "Feature",
  "properties": {
    "iso:country":"GB",
    "wof:name":"NP20 6LJ",
    "wof:placetype":"postalcode"
},
  "geometry": {"coordinates":[-3.00013938604591,51.61441685678494],"type":"Point"}
}