{
  "type": "Feature",
  "properties": {
    "iso:country": "GB",
    "wof:name": "PE25 2RB",
    "wof:placetype": "postalcode"
  },
  "geometry": {"coordinates":[0.339452,53.150702],"type":"Point"}
}
