{
  "type": "Feature",
  "properties": {
    "date:inception_lower":"1986-07-01",
    "date:inception_upper":"1986-07-31",
    "iso:country":"GB",
    "wof:name":"PE25 2RB",
    "wof:placetype":"postalcode"
},
  "geometry": {"coordinates":[0.339452,53.150702],"type":"Point"}
}