{
  "type": "Feature",
  "properties": {
    "date:inception_lower": "1992-08-01",
    "date:inception_upper": "1992-08-01",
    "iso:country": "GB",
    "wof:name": "OX44 7TN",
    "wof:placetype": "postalcode"
  },
  "geometry": {"coordinates":[-1.086341,51.669489],"type":"Point"}
}
