{
  "type": "Feature",
  "properties": {
    "iso:country": "GB",
    "wof:name": "OX44 7TN",
    "wof:placetype": "postalcode"
  },
  "geometry": {"coordinates":[-1.086341,51.669489],"type":"Point"}
}
