{
  "type": "Feature",
  "properties": {
    "iso:country":"GB",
    "wof:name":"RM3 0PE",
    "wof:placetype":"postalcode"
},
  "geometry": {"coordinates":[0.23423972859081,51.59275228963696],"type":"Point"}
}