{
  "type": "Feature",
  "properties": {
    "date:inception_lower": "1980-01-01",
    "date:inception_upper": "1980-01-01",
    "iso:country": "GB",
    "wof:name": "PL2 2QG",
    "wof:placetype": "postalcode"
  },
  "geometry": {"coordinates":[-4.163346,50.394405],"type":"Point"}
}
