{
  "type": "Feature",
  "properties": {
    "iso:country":"GB",
    "wof:name":"PL2 2QG",
    "wof:placetype":"postalcode"
},
  "geometry": {"coordinates":[-4.16312468862358,50.3945211299375],"type":"Point"}
}