{
  "type": "Feature",
  "properties": {
    "iso:country": "GB",
    "wof:name": "EH8 9BY",
    "wof:placetype": "postalcode"
  },
  "geometry": {"coordinates":[-3.18407,55.944731],"type":"Point"}
}
