{
  "type": "Feature",
  "properties": {
    "date:inception_lower":"1994-02-01",
    "date:inception_upper":"1994-02-28",
    "iso:country":"GB",
    "wof:name":"EH8 9BY",
    "wof:placetype":"postalcode"
},
  "geometry": {"coordinates":[-3.18407,55.944731],"type":"Point"}
}