{
  "type": "Feature",
  "properties": {
    "iso:country":"GB",
    "wof:name":"SW19 1ND",
    "wof:placetype":"postalcode"
},
  "geometry": {"coordinates":[-0.19785827471461,51.41714163162505],"type":"Point"}
}