{
  "type": "Feature",
  "properties": {
    "date:inception_lower": "1990-02-01",
    "date:inception_upper": "1990-02-01",
    "iso:country": "GB",
    "wof:name": "SW19 1ND",
    "wof:placetype": "postalcode"
  },
  "geometry": {"coordinates":[-0.197858,51.417142],"type":"Point"}
}
