{
  "type": "Feature",
  "properties": {
    "iso:country": "GB",
    "wof:name": "SW19 1ND",
    "wof:placetype": "postalcode"
  },
  "geometry": {"coordinates":[-0.197858,51.417142],"type":"Point"}
}
