{
  "type": "Feature",
  "properties": {
    "date:inception_lower": "2021-03-01",
    "date:inception_upper": "2021-03-01",
    "iso:country": "GB",
    "wof:name": "FY1 9PL",
    "wof:placetype": "postalcode"
  },
  "geometry": {"coordinates":[-3.051848,53.818696],"type":"Point"}
}
