{
  "type": "Feature",
  "properties": {
    "iso:country":"GB",
    "wof:name":"CM7 4QN",
    "wof:placetype":"postalcode"
},
  "geometry": {"coordinates":[0.4709225614523,51.94955240074908],"type":"Point"}
}