{
  "type": "Feature",
  "properties": {
    "date:inception_lower": "1993-08-01",
    "date:inception_upper": "1993-08-01",
    "iso:country": "GB",
    "wof:name": "DL12 8AY",
    "wof:placetype": "postalcode"
  },
  "geometry": {"coordinates":[-1.921974,54.549585],"type":"Point"}
}
