{
  "type": "Feature",
  "properties": {
    "iso:country":"GB",
    "wof:name":"S65 2UA",
    "wof:placetype":"postalcode"
},
  "geometry": {"coordinates":[-1.33123016124362,53.43830289173438],"type":"Point"}
}