{
  "type": "Feature",
  "properties": {
    "date:inception_lower": "1980-01-01",
    "date:inception_upper": "1980-01-01",
    "iso:country": "GB",
    "wof:name": "DN15 8AT",
    "wof:placetype": "postalcode"
  },
  "geometry": {"coordinates":[-0.683335,53.592776],"type":"Point"}
}
