{
  "type": "Feature",
  "properties": {
    "iso:country":"GB",
    "wof:name":"DN15 8AT",
    "wof:placetype":"postalcode"
},
  "geometry": {"coordinates":[-0.68325197488644,53.59287943917482],"type":"Point"}
}