{
  "type": "Feature",
  "properties": {
    "iso:country":"GB",
    "wof:name":"SP10 4DD",
    "wof:placetype":"postalcode"
},
  "geometry": {"coordinates":[-1.48180740569007,51.22588666379841],"type":"Point"}
}