{
  "type": "Feature",
  "properties": {
    "iso:country":"GB",
    "wof:name":"DY9 0PF",
    "wof:placetype":"postalcode"
},
  "geometry": {"coordinates":[-2.13099087014763,52.43214355332442],"type":"Point"}
}