{
  "type": "Feature",
  "properties": {
    "iso:country":"GB",
    "wof:name":"PA30 8HL",
    "wof:placetype":"postalcode"
},
  "geometry": {"coordinates":[-5.45087589797188,56.02117560008563],"type":"Point"}
}