{
  "type": "Feature",
  "properties": {
    "iso:country":"GB",
    "wof:name":"EX8 4GA",
    "wof:placetype":"postalcode"
},
  "geometry": {"coordinates":[-3.38811360037637,50.63418722828683],"type":"Point"}
}