{
  "type": "Feature",
  "properties": {
    "iso:country":"GB",
    "wof:name":"CH45 4RH",
    "wof:placetype":"postalcode"
},
  "geometry": {"coordinates":[-3.04823066381552,53.42129749081685],"type":"Point"}
}