{
  "type": "Feature",
  "properties": {
    "iso:country": "GB",
    "wof:name": "CH45 4RH",
    "wof:placetype": "postalcode"
  },
  "geometry": {"coordinates":[-3.048231,53.421297],"type":"Point"}
}
