{
  "type": "Feature",
  "properties": {
    "date:inception_lower": "1980-01-01",
    "date:inception_upper": "1980-01-01",
    "iso:country": "GB",
    "wof:name": "SK8 2AY",
    "wof:placetype": "postalcode"
  },
  "geometry": {"coordinates":[-2.20886,53.396369],"type":"Point"}
}
