{
  "type": "Feature",
  "properties": {
    "iso:country":"GB",
    "wof:name":"SK8 2AY",
    "wof:placetype":"postalcode"
},
  "geometry": {"coordinates":[-2.2088604436811,53.39636891269909],"type":"Point"}
}