{
  "type": "Feature",
  "properties": {
    "iso:country":"GB",
    "wof:name":"BD17 5BX",
    "wof:placetype":"postalcode"
},
  "geometry": {"coordinates":[-1.78021656046038,53.84840478835434],"type":"Point"}
}