{
  "type": "Feature",
  "properties": {
    "iso:country":"GB",
    "wof:name":"NP23 6YG",
    "wof:placetype":"postalcode"
},
  "geometry": {"coordinates":[-3.20720419034634,51.78007353776371],"type":"Point"}
}