{
  "type": "Feature",
  "properties": {
    "iso:country": "GB",
    "wof:name": "N19 4QN",
    "wof:placetype": "postalcode"
  },
  "geometry": {"coordinates":[-0.121921,51.570352],"type":"Point"}
}
