{
  "type": "Feature",
  "properties": {
    "date:inception_lower":"1980-01-01",
    "date:inception_upper":"1980-01-31",
    "iso:country":"GB",
    "wof:name":"N19 4QN",
    "wof:placetype":"postalcode"
},
  "geometry": {"coordinates":[-0.121921,51.570352],"type":"Point"}
}