{
  "type": "Feature",
  "properties": {
    "iso:country":"GB",
    "wof:name":"N19 4QN",
    "wof:placetype":"postalcode"
},
  "geometry": {"coordinates":[-0.1219211020419,51.57035152674013],"type":"Point"}
}