{
  "type": "Feature",
  "properties": {
    "iso:country":"GB",
    "wof:name":"NE26 4DE",
    "wof:placetype":"postalcode"
},
  "geometry": {"coordinates":[-1.475643233225,55.07939171973316],"type":"Point"}
}