{
  "type": "Feature",
  "properties": {
    "date:inception_lower": "2018-01-01",
    "date:inception_upper": "2018-01-01",
    "iso:country": "GB",
    "wof:name": "TS6 0BE",
    "wof:placetype": "postalcode"
  },
  "geometry": {"coordinates":[-1.166478,54.563667],"type":"Point"}
}
