{
  "type": "Feature",
  "properties": {
    "iso:country":"GB",
    "wof:name":"BR5 1DX",
    "wof:placetype":"postalcode"
},
  "geometry": {"coordinates":[0.07380290901818,51.38602114616165],"type":"Point"}
}