{
  "type": "Feature",
  "properties": {
    "iso:country": "GB",
    "wof:name": "BR5 1DX",
    "wof:placetype": "postalcode"
  },
  "geometry": {"coordinates":[0.073803,51.386021],"type":"Point"}
}
