{
  "type": "Feature",
  "properties": {
    "iso:country":"GB",
    "wof:name":"SA12 9NP",
    "wof:placetype":"postalcode"
},
  "geometry": {"coordinates":[-3.75923370923862,51.61768640368018],"type":"Point"}
}