{
  "type": "Feature",
  "properties": {
    "iso:country": "GB",
    "wof:name": "SA12 9NP",
    "wof:placetype": "postalcode"
  },
  "geometry": {"coordinates":[-3.759234,51.617686],"type":"Point"}
}
