{
  "type": "Feature",
  "properties": {
    "iso:country":"GB",
    "wof:name":"SM6 0PH",
    "wof:placetype":"postalcode"
},
  "geometry": {"coordinates":[-0.14886171743303,51.34799764980745],"type":"Point"}
}