{
  "type": "Feature",
  "properties": {
    "iso:country":"GB",
    "wof:name":"SA33 6PD",
    "wof:placetype":"postalcode"
},
  "geometry": {"coordinates":[-4.43684680212419,51.90066591196254],"type":"Point"}
}