{
  "type": "Feature",
  "properties": {
    "iso:country": "GB",
    "wof:name": "SA33 6PD",
    "wof:placetype": "postalcode"
  },
  "geometry": {"coordinates":[-4.436847,51.900666],"type":"Point"}
}
