{
  "type": "Feature",
  "properties": {
    "iso:country":"GB",
    "wof:name":"CT1 1EN",
    "wof:placetype":"postalcode"
},
  "geometry": {"coordinates":[1.10705486589954,51.2901566628884],"type":"Point"}
}