{
  "type": "Feature",
  "properties": {
    "iso:country":"GB",
    "wof:name":"SS8 9AY",
    "wof:placetype":"postalcode"
},
  "geometry": {"coordinates":[0.58636597186626,51.52619774944413],"type":"Point"}
}