{
  "type": "Feature",
  "properties": {
    "date:inception_lower":"2016-02-01",
    "date:inception_upper":"2016-02-29",
    "iso:country":"GB",
    "wof:name":"NR16 2BS",
    "wof:placetype":"postalcode"
},
  "geometry": {"coordinates":[1.0113,52.447631],"type":"Point"}
}