{
  "type": "Feature",
  "properties": {
    "iso:country":"GB",
    "wof:name":"NR16 2BS",
    "wof:placetype":"postalcode"
},
  "geometry": {"coordinates":[1.011300356112,52.44763120254478],"type":"Point"}
}