{
  "type": "Feature",
  "properties": {
    "iso:country": "GB",
    "wof:name": "NR16 2BS",
    "wof:placetype": "postalcode"
  },
  "geometry": {"coordinates":[1.0113,52.447631],"type":"Point"}
}
