{
  "type": "Feature",
  "properties": {
    "date:inception_lower": "2019-10-01",
    "date:inception_upper": "2019-10-01",
    "iso:country": "GB",
    "wof:name": "B33 9FD",
    "wof:placetype": "postalcode"
  },
  "geometry": {"coordinates":[-1.81199,52.488611],"type":"Point"}
}
