{
  "type": "Feature",
  "properties": {
    "iso:country": "GB",
    "wof:name": "B33 9FD",
    "wof:placetype": "postalcode"
  },
  "geometry": {"coordinates":[-1.81199,52.488611],"type":"Point"}
}
