{
  "type": "Feature",
  "properties": {
    "iso:country":"GB",
    "wof:name":"LD7 1PP",
    "wof:placetype":"postalcode"
},
  "geometry": {"coordinates":[-3.1005930936182,52.36165034935286],"type":"Point"}
}