{
  "type": "Feature",
  "properties": {
    "date:inception_lower":"1980-01-01",
    "date:inception_upper":"1980-01-31",
    "iso:country":"GB",
    "wof:name":"LD7 1PP",
    "wof:placetype":"postalcode"
},
  "geometry": {"coordinates":[-3.100833,52.36185],"type":"Point"}
}