{
  "type": "Feature",
  "properties": {
    "iso:country": "GB",
    "wof:name": "LD7 1PP",
    "wof:placetype": "postalcode"
  },
  "geometry": {"coordinates":[-3.100593,52.361663],"type":"Point"}
}
