{
  "type": "Feature",
  "properties": {
    "iso:country":"GB",
    "wof:name":"CF40 2RP",
    "wof:placetype":"postalcode"
},
  "geometry": {"coordinates":[-3.4690669696086,51.62657773434524],"type":"Point"}
}