{
  "type": "Feature",
  "properties": {
    "iso:country": "GB",
    "wof:name": "FY5 2HP",
    "wof:placetype": "postalcode"
  },
  "geometry": {"coordinates":[-3.018933,53.883673],"type":"Point"}
}
