{
  "type": "Feature",
  "properties": {
    "iso:country": "GB",
    "wof:name": "IP4 3EN",
    "wof:placetype": "postalcode"
  },
  "geometry": {"coordinates":[1.181929,52.069628],"type":"Point"}
}
