{
  "type": "Feature",
  "properties": {
    "iso:country":"GB",
    "wof:name":"TR10 9HU",
    "wof:placetype":"postalcode"
},
  "geometry": {"coordinates":[-5.13375262000015,50.1621716170024],"type":"Point"}
}