{
  "type": "Feature",
  "properties": {
    "iso:country": "GB",
    "wof:name": "TR10 9HU",
    "wof:placetype": "postalcode"
  },
  "geometry": {"coordinates":[-5.133753,50.162172],"type":"Point"}
}
