{
  "type": "Feature",
  "properties": {
    "iso:country":"GB",
    "wof:name":"DL5 4RB",
    "wof:placetype":"postalcode"
},
  "geometry": {"coordinates":[-1.57023982883446,54.62731187998315],"type":"Point"}
}