{
  "type": "Feature",
  "properties": {
    "date:inception_lower": "1983-03-01",
    "date:inception_upper": "1983-03-01",
    "iso:country": "GB",
    "wof:name": "DL5 4RB",
    "wof:placetype": "postalcode"
  },
  "geometry": {"coordinates":[-1.57024,54.627312],"type":"Point"}
}
