{
  "type": "Feature",
  "properties": {
    "iso:country":"GB",
    "wof:name":"W14 8BT",
    "wof:placetype":"postalcode"
},
  "geometry": {"coordinates":[-0.21150899853217,51.50287841412762],"type":"Point"}
}