{
  "type": "Feature",
  "properties": {
    "iso:country":"GB",
    "wof:name":"ML3 7PX",
    "wof:placetype":"postalcode"
},
  "geometry": {"coordinates":[-4.03254113528874,55.76649390680533],"type":"Point"}
}