{
  "type": "Feature",
  "properties": {
    "date:inception_lower": "1980-01-01",
    "date:inception_upper": "1980-01-01",
    "iso:country": "GB",
    "wof:name": "L25 8RN",
    "wof:placetype": "postalcode"
  },
  "geometry": {"coordinates":[-2.857616,53.37852],"type":"Point"}
}
