{
  "type": "Feature",
  "properties": {
    "iso:country":"GB",
    "wof:name":"HA1 2FL",
    "wof:placetype":"postalcode"
},
  "geometry": {"coordinates":[-0.33073759789812,51.58411847330263],"type":"Point"}
}