{
  "type": "Feature",
  "properties": {
    "date:inception_lower": "2002-07-01",
    "date:inception_upper": "2002-07-01",
    "iso:country": "GB",
    "wof:name": "HA1 2FL",
    "wof:placetype": "postalcode"
  },
  "geometry": {"coordinates":[-0.330738,51.584118],"type":"Point"}
}
