{
  "type": "Feature",
  "properties": {
    "iso:country":"GB",
    "wof:name":"SE13 5AZ",
    "wof:placetype":"postalcode"
},
  "geometry": {"coordinates":[-0.00532857929453,51.46238596544326],"type":"Point"}
}