{
  "type": "Feature",
  "properties": {
    "iso:country":"GB",
    "wof:name":"WN6 9AJ",
    "wof:placetype":"postalcode"
},
  "geometry": {"coordinates":[-2.72205015718816,53.58421616147199],"type":"Point"}
}