{
  "type": "Feature",
  "properties": {
    "date:inception_lower": "1980-01-01",
    "date:inception_upper": "1980-01-01",
    "iso:country": "GB",
    "wof:name": "RM13 7JH",
    "wof:placetype": "postalcode"
  },
  "geometry": {"coordinates":[0.196068,51.541305],"type":"Point"}
}
