{
  "type": "Feature",
  "properties": {
    "iso:country":"GB",
    "wof:name":"RM13 7JH",
    "wof:placetype":"postalcode"
},
  "geometry": {"coordinates":[0.19606834511663,51.54130530056843],"type":"Point"}
}