{
  "type": "Feature",
  "properties": {
    "iso:country":"GB",
    "wof:name":"W1D 6BW",
    "wof:placetype":"postalcode"
},
  "geometry": {"coordinates":[-0.13212314772771,51.51048058038758],"type":"Point"}
}