{
  "type": "Feature",
  "properties": {
    "iso:country": "GB",
    "wof:name": "W1D 6BW",
    "wof:placetype": "postalcode"
  },
  "geometry": {"coordinates":[-0.132123,51.510481],"type":"Point"}
}
