{
  "type": "Feature",
  "properties": {
    "iso:country": "GB",
    "wof:name": "DH8 9QB",
    "wof:placetype": "postalcode"
  },
  "geometry": {"coordinates":[-1.867902,54.834926],"type":"Point"}
}
