{
  "type": "Feature",
  "properties": {
    "iso:country": "GB",
    "wof:name": "CH5 3AN",
    "wof:placetype": "postalcode"
  },
  "geometry": {"coordinates":[-3.051599,53.194111],"type":"Point"}
}
