{
  "type": "Feature",
  "properties": {
    "iso:country": "GB",
    "wof:name": "G13 2JB",
    "wof:placetype": "postalcode"
  },
  "geometry": {"coordinates":[-4.337437,55.901045],"type":"Point"}
}
