{
  "type": "Feature",
  "properties": {
    "iso:country":"GB",
    "wof:name":"G13 2JB",
    "wof:placetype":"postalcode"
},
  "geometry": {"coordinates":[-4.33743751039764,55.90104518275106],"type":"Point"}
}