{
  "type": "Feature",
  "properties": {
    "iso:country":"GB",
    "wof:name":"G69 6HF",
    "wof:placetype":"postalcode"
},
  "geometry": {"coordinates":[-4.1026024120137,55.85850293122315],"type":"Point"}
}