{
  "type": "Feature",
  "properties": {
    "date:inception_lower":"1993-08-01",
    "date:inception_upper":"1993-08-31",
    "iso:country":"GB",
    "wof:name":"G69 6HF",
    "wof:placetype":"postalcode"
},
  "geometry": {"coordinates":[-4.102602,55.858503],"type":"Point"}
}