{
  "type": "Feature",
  "properties": {
    "iso:country": "GB",
    "wof:name": "G69 6HF",
    "wof:placetype": "postalcode"
  },
  "geometry": {"coordinates":[-4.102602,55.858503],"type":"Point"}
}
