{
  "type": "Feature",
  "properties": {
    "iso:country": "GB",
    "wof:name": "KT6 4BY",
    "wof:placetype": "postalcode"
  },
  "geometry": {"coordinates":[-0.308897,51.397313],"type":"Point"}
}
