{
  "type": "Feature",
  "properties": {
    "iso:country":"GB",
    "wof:name":"KT6 4BY",
    "wof:placetype":"postalcode"
},
  "geometry": {"coordinates":[-0.30889657807209,51.39731336337736],"type":"Point"}
}