{
  "type": "Feature",
  "properties": {
    "iso:country": "GB",
    "wof:name": "YO43 3LY",
    "wof:placetype": "postalcode"
  },
  "geometry": {"coordinates":[-0.587854,53.883166],"type":"Point"}
}
