{
  "type": "Feature",
  "properties": {
    "date:inception_lower": "1981-06-01",
    "date:inception_upper": "1981-06-01",
    "iso:country": "GB",
    "wof:name": "CV11 6TD",
    "wof:placetype": "postalcode"
  },
  "geometry": {"coordinates":[-1.426542,52.505769],"type":"Point"}
}
