{
  "type": "Feature",
  "properties": {
    "iso:country":"GB",
    "wof:name":"BA5 2HT",
    "wof:placetype":"postalcode"
},
  "geometry": {"coordinates":[-2.65427723140104,51.20841425756452],"type":"Point"}
}