{
  "type": "Feature",
  "properties": {
    "iso:country":"GB",
    "wof:name":"WA6 0LJ",
    "wof:placetype":"postalcode"
},
  "geometry": {"coordinates":[-2.77440936327885,53.2524458093878],"type":"Point"}
}