{
  "type": "Feature",
  "properties": {
    "date:inception_lower": "2007-01-01",
    "date:inception_upper": "2007-01-01",
    "iso:country": "GB",
    "wof:name": "WA6 0LJ",
    "wof:placetype": "postalcode"
  },
  "geometry": {"coordinates":[-2.774408,53.252461],"type":"Point"}
}
