{
  "type": "Feature",
  "properties": {
    "iso:country": "GB",
    "wof:name": "WA6 0LJ",
    "wof:placetype": "postalcode"
  },
  "geometry": {"coordinates":[-2.774409,53.252446],"type":"Point"}
}
