{
  "type": "Feature",
  "properties": {
    "iso:country":"GB",
    "wof:name":"SN8 2NA",
    "wof:placetype":"postalcode"
},
  "geometry": {"coordinates":[-1.68910055969868,51.42710966985728],"type":"Point"}
}