{
  "type": "Feature",
  "properties": {
    "date:inception_lower": "1980-01-01",
    "date:inception_upper": "1980-01-01",
    "iso:country": "GB",
    "wof:name": "SN8 2NA",
    "wof:placetype": "postalcode"
  },
  "geometry": {"coordinates":[-1.689101,51.42711],"type":"Point"}
}
