{
  "type": "Feature",
  "properties": {
    "iso:country":"GB",
    "wof:name":"OL13 0NU",
    "wof:placetype":"postalcode"
},
  "geometry": {"coordinates":[-2.23406446667086,53.69138304315318],"type":"Point"}
}