{
  "type": "Feature",
  "properties": {
    "iso:country":"GB",
    "wof:name":"GU29 9BL",
    "wof:placetype":"postalcode"
},
  "geometry": {"coordinates":[-0.72705376702524,50.99617148276817],"type":"Point"}
}