{
  "type": "Feature",
  "properties": {
    "iso:country": "GB",
    "wof:name": "EN6 5EL",
    "wof:placetype": "postalcode"
  },
  "geometry": {"coordinates":[-0.16852,51.691144],"type":"Point"}
}
