{
  "type": "Feature",
  "properties": {
    "iso:country":"GB",
    "wof:name":"EN6 5EL",
    "wof:placetype":"postalcode"
},
  "geometry": {"coordinates":[-0.16851997818657,51.69114443270939],"type":"Point"}
}