{
  "type": "Feature",
  "properties": {
    "date:inception_lower":"2007-11-01",
    "date:inception_upper":"2007-11-30",
    "iso:country":"GB",
    "wof:name":"M44 6GN",
    "wof:placetype":"postalcode"
},
  "geometry": {"coordinates":[-2.428136,53.439621],"type":"Point"}
}