{
  "type": "Feature",
  "properties": {
    "iso:country": "GB",
    "wof:name": "M44 6GN",
    "wof:placetype": "postalcode"
  },
  "geometry": {"coordinates":[-2.428136,53.439621],"type":"Point"}
}
