{
  "type": "Feature",
  "properties": {
    "date:inception_lower": "1999-06-01",
    "date:inception_upper": "1999-06-01",
    "iso:country": "GB",
    "wof:name": "DL2 3XD",
    "wof:placetype": "postalcode"
  },
  "geometry": {"coordinates":[-1.810485,54.57707],"type":"Point"}
}
