{
  "type": "Feature",
  "properties": {
    "iso:country":"GB",
    "wof:name":"CH46 2RH",
    "wof:placetype":"postalcode"
},
  "geometry": {"coordinates":[-3.09101644986961,53.41970068238393],"type":"Point"}
}