{
  "type": "Feature",
  "properties": {
    "iso:country": "GB",
    "wof:name": "CH46 2RH",
    "wof:placetype": "postalcode"
  },
  "geometry": {"coordinates":[-3.091016,53.419701],"type":"Point"}
}
