{
  "type": "Feature",
  "properties": {
    "iso:country":"GB",
    "wof:name":"GU21 8AS",
    "wof:placetype":"postalcode"
},
  "geometry": {"coordinates":[-0.60139839572967,51.31764887707519],"type":"Point"}
}