{
  "type": "Feature",
  "properties": {
    "date:inception_lower":"2002-06-01",
    "date:inception_upper":"2002-06-30",
    "iso:country":"GB",
    "wof:name":"GU21 8AS",
    "wof:placetype":"postalcode"
},
  "geometry": {"coordinates":[-0.601398,51.317649],"type":"Point"}
}