{
  "type": "Feature",
  "properties": {
    "iso:country":"GB",
    "wof:name":"DN14 8JY",
    "wof:placetype":"postalcode"
},
  "geometry": {"coordinates":[-0.92596877183957,53.70824618656124],"type":"Point"}
}