{
  "type": "Feature",
  "properties": {
    "iso:country":"GB",
    "wof:name":"HD1 4JR",
    "wof:placetype":"postalcode"
},
  "geometry": {"coordinates":[-1.81141262034823,53.64370108072386],"type":"Point"}
}