{
  "type": "Feature",
  "properties": {
    "iso:country":"GB",
    "wof:name":"DE13 9BH",
    "wof:placetype":"postalcode"
},
  "geometry": {"coordinates":[-1.65335496811048,52.84785396166295],"type":"Point"}
}