{
  "type": "Feature",
  "properties": {
    "date:inception_lower": "1981-06-01",
    "date:inception_upper": "1981-06-01",
    "iso:country": "GB",
    "wof:name": "MK14 7PR",
    "wof:placetype": "postalcode"
  },
  "geometry": {"coordinates":[-0.743414,52.056162],"type":"Point"}
}
