{
  "type": "Feature",
  "properties": {
    "iso:country":"GB",
    "wof:name":"MK14 7PR",
    "wof:placetype":"postalcode"
},
  "geometry": {"coordinates":[-0.74341446950349,52.05616204955325],"type":"Point"}
}