{
  "type": "Feature",
  "properties": {
    "iso:country":"GB",
    "wof:name":"EH9 1EP",
    "wof:placetype":"postalcode"
},
  "geometry": {"coordinates":[-3.19842751259831,55.93885925651202],"type":"Point"}
}