{
  "type": "Feature",
  "properties": {
    "iso:country":"GB",
    "wof:name":"TR20 8QR",
    "wof:placetype":"postalcode"
},
  "geometry": {"coordinates":[-5.61097955074957,50.10973837524664],"type":"Point"}
}