{
  "type": "Feature",
  "properties": {
    "iso:country":"GB",
    "wof:name":"G81 1HF",
    "wof:placetype":"postalcode"
},
  "geometry": {"coordinates":[-4.38850779987694,55.89385413596749],"type":"Point"}
}