{
  "type": "Feature",
  "properties": {
    "iso:country":"GB",
    "wof:name":"PL4 6QL",
    "wof:placetype":"postalcode"
},
  "geometry": {"coordinates":[-4.13680452592571,50.38181311772261],"type":"Point"}
}