{
  "type": "Feature",
  "properties": {
    "date:inception_lower": "1980-01-01",
    "date:inception_upper": "1980-01-01",
    "iso:country": "GB",
    "wof:name": "PL4 6QL",
    "wof:placetype": "postalcode"
  },
  "geometry": {"coordinates":[-4.136804,50.381813],"type":"Point"}
}
