{
  "type": "Feature",
  "properties": {
    "iso:country":"GB",
    "wof:name":"CB22 4QF",
    "wof:placetype":"postalcode"
},
  "geometry": {"coordinates":[0.13084821135273,52.08182098804267],"type":"Point"}
}