{
  "type": "Feature",
  "properties": {
    "iso:country":"GB",
    "wof:name":"YO12 5EZ",
    "wof:placetype":"postalcode"
},
  "geometry": {"coordinates":[-0.41596717337054,54.27689649707519],"type":"Point"}
}