{
  "type": "Feature",
  "properties": {
    "iso:country": "GB",
    "wof:name": "YO12 5EZ",
    "wof:placetype": "postalcode"
  },
  "geometry": {"coordinates":[-0.415967,54.276932],"type":"Point"}
}
