{
  "type": "Feature",
  "properties": {
    "date:inception_lower":"1998-12-01",
    "date:inception_upper":"1998-12-31",
    "iso:country":"GB",
    "wof:name":"CO10 2HA",
    "wof:placetype":"postalcode"
},
  "geometry": {"coordinates":[0.72588,52.037497],"type":"Point"}
}