{
  "type": "Feature",
  "properties": {
    "iso:country": "GB",
    "wof:name": "CO10 2HA",
    "wof:placetype": "postalcode"
  },
  "geometry": {"coordinates":[0.72588,52.037497],"type":"Point"}
}
