{
  "type": "Feature",
  "properties": {
    "iso:country":"GB",
    "wof:name":"CO10 1UE",
    "wof:placetype":"postalcode"
},
  "geometry": {"coordinates":[0.73316445294493,52.04336204328985],"type":"Point"}
}