{
  "type": "Feature",
  "properties": {
    "iso:country":"GB",
    "wof:name":"B74 2QB",
    "wof:placetype":"postalcode"
},
  "geometry": {"coordinates":[-1.8391345863169,52.57431007759919],"type":"Point"}
}