{
  "type": "Feature",
  "properties": {
    "date:inception_lower": "2006-09-01",
    "date:inception_upper": "2006-09-01",
    "iso:country": "GB",
    "wof:name": "CB23 2UR",
    "wof:placetype": "postalcode"
  },
  "geometry": {"coordinates":[-0.109218,52.1641],"type":"Point"}
}
