{
  "type": "Feature",
  "properties": {
    "iso:country":"GB",
    "wof:name":"CB23 2UR",
    "wof:placetype":"postalcode"
},
  "geometry": {"coordinates":[-0.10921757285289,52.16409982938313],"type":"Point"}
}