{
  "type": "Feature",
  "properties": {
    "date:inception_lower": "2022-02-01",
    "date:inception_upper": "2022-02-01",
    "iso:country": "GB",
    "wof:name": "CO8 5FE",
    "wof:placetype": "postalcode"
  },
  "geometry": {"coordinates":[0.77931,51.967866],"type":"Point"}
}
