{
  "type": "Feature",
  "properties": {
    "iso:country":"GB",
    "wof:name":"AL7 1BY",
    "wof:placetype":"postalcode"
},
  "geometry": {"coordinates":[-0.19026867582508,51.81539289016148],"type":"Point"}
}