{
  "type": "Feature",
  "properties": {
    "date:inception_lower": "1980-01-01",
    "date:inception_upper": "1980-01-01",
    "iso:country": "GB",
    "wof:name": "ST10 4HH",
    "wof:placetype": "postalcode"
  },
  "geometry": {"coordinates":[-1.913462,52.9465],"type":"Point"}
}
