{
  "type": "Feature",
  "properties": {
    "iso:country": "GB",
    "wof:name": "HD5 8TS",
    "wof:placetype": "postalcode"
  },
  "geometry": {"coordinates":[-1.738763,53.636024],"type":"Point"}
}
