{
  "type": "Feature",
  "properties": {
    "iso:country":"GB",
    "wof:name":"N21 1NH",
    "wof:placetype":"postalcode"
},
  "geometry": {"coordinates":[-0.1151876554785,51.63996171322691],"type":"Point"}
}