{
  "type": "Feature",
  "properties": {
    "iso:country":"GB",
    "wof:name":"LN3 4JJ",
    "wof:placetype":"postalcode"
},
  "geometry": {"coordinates":[-0.45375967988848,53.24094668251345],"type":"Point"}
}