{
  "type": "Feature",
  "properties": {
    "iso:country":"GB",
    "wof:name":"CH5 4RQ",
    "wof:placetype":"postalcode"
},
  "geometry": {"coordinates":[-3.05963795200361,53.21958888537615],"type":"Point"}
}