{
  "type": "Feature",
  "properties": {
    "iso:country": "GB",
    "wof:name": "CH5 4RQ",
    "wof:placetype": "postalcode"
  },
  "geometry": {"coordinates":[-3.059638,53.219589],"type":"Point"}
}
