{
  "type": "Feature",
  "properties": {
    "iso:country": "GB",
    "wof:name": "HP22 5YZ",
    "wof:placetype": "postalcode"
  },
  "geometry": {"coordinates":[-0.768893,51.80711],"type":"Point"}
}
