{
  "type": "Feature",
  "properties": {
    "date:inception_lower": "2019-11-01",
    "date:inception_upper": "2019-11-01",
    "iso:country": "GB",
    "wof:name": "HP22 5YZ",
    "wof:placetype": "postalcode"
  },
  "geometry": {"coordinates":[-0.768907,51.807155],"type":"Point"}
}
