{
  "type": "Feature",
  "properties": {
    "iso:country":"GB",
    "wof:name":"IG7 4JH",
    "wof:placetype":"postalcode"
},
  "geometry": {"coordinates":[0.09554236798662,51.61265787803823],"type":"Point"}
}