{
  "type": "Feature",
  "properties": {
    "iso:country":"GB",
    "wof:name":"NP8 1DJ",
    "wof:placetype":"postalcode"
},
  "geometry": {"coordinates":[-3.14236679394747,51.86333448508258],"type":"Point"}
}