{
  "type": "Feature",
  "properties": {
    "date:inception_lower":"1981-06-01",
    "date:inception_upper":"1981-06-30",
    "iso:country":"GB",
    "wof:name":"NP8 1DJ",
    "wof:placetype":"postalcode"
},
  "geometry": {"coordinates":[-3.142367,51.863334],"type":"Point"}
}