{
  "type": "Feature",
  "properties": {
    "iso:country": "GB",
    "wof:name": "AB30 1DH",
    "wof:placetype": "postalcode"
  },
  "geometry": {"coordinates":[-2.565952,56.856055],"type":"Point"}
}
