{
  "type": "Feature",
  "properties": {
    "iso:country":"GB",
    "wof:name":"AB30 1DH",
    "wof:placetype":"postalcode"
},
  "geometry": {"coordinates":[-2.56595247423828,56.85605524879256],"type":"Point"}
}