{
  "type": "Feature",
  "properties": {
    "iso:country":"GB",
    "wof:name":"TW7 7HS",
    "wof:placetype":"postalcode"
},
  "geometry": {"coordinates":[-0.3262428917142,51.46357576473844],"type":"Point"}
}