{
  "type": "Feature",
  "properties": {
    "iso:country": "GB",
    "wof:name": "BS22 8QX",
    "wof:placetype": "postalcode"
  },
  "geometry": {"coordinates":[-2.936398,51.353837],"type":"Point"}
}
