{
  "type": "Feature",
  "properties": {
    "iso:country":"GB",
    "wof:name":"BS22 8QX",
    "wof:placetype":"postalcode"
},
  "geometry": {"coordinates":[-2.93626450127525,51.35387712632146],"type":"Point"}
}