{
  "type": "Feature",
  "properties": {
    "iso:country": "GB",
    "wof:name": "EH52 5EX",
    "wof:placetype": "postalcode"
  },
  "geometry": {"coordinates":[-3.466684,55.935477],"type":"Point"}
}
