{
  "type": "Feature",
  "properties": {
    "iso:country":"GB",
    "wof:name":"EH52 5EX",
    "wof:placetype":"postalcode"
},
  "geometry": {"coordinates":[-3.4666879088185,55.93548085964248],"type":"Point"}
}