{
  "type": "Feature",
  "properties": {
    "date:inception_lower": "1980-01-01",
    "date:inception_upper": "1980-01-01",
    "iso:country": "GB",
    "wof:name": "CV3 5AA",
    "wof:placetype": "postalcode"
  },
  "geometry": {"coordinates":[-1.506145,52.379689],"type":"Point"}
}
