{
  "type": "Feature",
  "properties": {
    "iso:country": "GB",
    "wof:name": "CV3 5AA",
    "wof:placetype": "postalcode"
  },
  "geometry": {"coordinates":[-1.506145,52.379689],"type":"Point"}
}
