{
  "type": "Feature",
  "properties": {
    "iso:country":"GB",
    "wof:name":"CV3 5AA",
    "wof:placetype":"postalcode"
},
  "geometry": {"coordinates":[-1.50582910069023,52.37995910194739],"type":"Point"}
}