{
  "type": "Feature",
  "properties": {
    "iso:country":"GB",
    "wof:name":"LL11 6PP",
    "wof:placetype":"postalcode"
},
  "geometry": {"coordinates":[-3.03677447369534,53.05662405485866],"type":"Point"}
}