{
  "type": "Feature",
  "properties": {
    "iso:country":"GB",
    "wof:name":"MK44 3TW",
    "wof:placetype":"postalcode"
},
  "geometry": {"coordinates":[-0.38972006299746,52.12905144135958],"type":"Point"}
}