{
  "type": "Feature",
  "properties": {
    "date:inception_lower": "1980-01-01",
    "date:inception_upper": "1980-01-01",
    "iso:country": "GB",
    "wof:name": "WA15 6HT",
    "wof:placetype": "postalcode"
  },
  "geometry": {"coordinates":[-2.328799,53.40302],"type":"Point"}
}
