{
  "type": "Feature",
  "properties": {
    "iso:country": "GB",
    "wof:name": "YO25 3HE",
    "wof:placetype": "postalcode"
  },
  "geometry": {"coordinates":[-0.643993,54.048392],"type":"Point"}
}
