{
  "type": "Feature",
  "properties": {
    "iso:country": "GB",
    "wof:name": "YO25 3HE",
    "wof:placetype": "postalcode"
  },
  "geometry": {"coordinates":[-0.642864,54.048344],"type":"Point"}
}
