{
  "type": "Feature",
  "properties": {
    "iso:country":"GB",
    "wof:name":"L7 8SF",
    "wof:placetype":"postalcode"
},
  "geometry": {"coordinates":[-2.95627732643057,53.40809162946442],"type":"Point"}
}