{
  "type": "Feature",
  "properties": {
    "iso:country":"GB",
    "wof:name":"LL55 2ED",
    "wof:placetype":"postalcode"
},
  "geometry": {"coordinates":[-4.25430152189988,53.14013408360915],"type":"Point"}
}