{
  "type": "Feature",
  "properties": {
    "date:inception_lower": "1980-01-01",
    "date:inception_upper": "1980-01-01",
    "iso:country": "GB",
    "wof:name": "LL55 2ED",
    "wof:placetype": "postalcode"
  },
  "geometry": {"coordinates":[-4.254301,53.140134],"type":"Point"}
}
