{
  "type": "Feature",
  "properties": {
    "date:inception_lower": "2018-09-01",
    "date:inception_upper": "2018-09-01",
    "iso:country": "GB",
    "wof:name": "RG40 1LH",
    "wof:placetype": "postalcode"
  },
  "geometry": {"coordinates":[-0.803072,51.413375],"type":"Point"}
}
