{
  "type": "Feature",
  "properties": {
    "date:inception_lower": "2022-02-01",
    "date:inception_upper": "2022-02-01",
    "iso:country": "GB",
    "wof:name": "HU13 0SZ",
    "wof:placetype": "postalcode"
  },
  "geometry": {"coordinates":[-0.459045,53.726936],"type":"Point"}
}
