{
  "type": "Feature",
  "properties": {
    "iso:country":"GB",
    "wof:name":"LE5 6GH",
    "wof:placetype":"postalcode"
},
  "geometry": {"coordinates":[-1.07151739612274,52.62678921361527],"type":"Point"}
}