{
  "type": "Feature",
  "properties": {
    "iso:country":"GB",
    "wof:name":"L7 9LP",
    "wof:placetype":"postalcode"
},
  "geometry": {"coordinates":[-2.93429191973934,53.41050394747506],"type":"Point"}
}