{
  "type": "Feature",
  "properties": {
    "iso:country": "GB",
    "wof:name": "L12 4ZL",
    "wof:placetype": "postalcode"
  },
  "geometry": {"coordinates":[-2.893573,53.434429],"type":"Point"}
}
