{
  "type": "Feature",
  "properties": {
    "iso:country":"GB",
    "wof:name":"LE8 8TW",
    "wof:placetype":"postalcode"
},
  "geometry": {"coordinates":[-1.03932724461498,52.53351171582722],"type":"Point"}
}