{
  "type": "Feature",
  "properties": {
    "iso:country":"GB",
    "wof:name":"PH16 5NX",
    "wof:placetype":"postalcode"
},
  "geometry": {"coordinates":[-4.01779838680431,56.70773604282061],"type":"Point"}
}