{
  "type": "Feature",
  "properties": {
    "iso:country": "GB",
    "wof:name": "PH16 5NX",
    "wof:placetype": "postalcode"
  },
  "geometry": {"coordinates":[-4.017798,56.707736],"type":"Point"}
}
