{
  "type": "Feature",
  "properties": {
    "iso:country":"GB",
    "wof:name":"CO12 4SR",
    "wof:placetype":"postalcode"
},
  "geometry": {"coordinates":[1.25410582610951,51.94769371072356],"type":"Point"}
}