{
  "type": "Feature",
  "properties": {
    "iso:country":"GB",
    "wof:name":"RM16 2HX",
    "wof:placetype":"postalcode"
},
  "geometry": {"coordinates":[0.32903644712402,51.50033978631937],"type":"Point"}
}