{
  "type": "Feature",
  "properties": {
    "iso:country": "GB",
    "wof:name": "PR25 1BU",
    "wof:placetype": "postalcode"
  },
  "geometry": {"coordinates":[-2.705213,53.686955],"type":"Point"}
}
