{
  "type": "Feature",
  "properties": {
    "date:inception_lower":"2001-06-01",
    "date:inception_upper":"2001-06-30",
    "iso:country":"GB",
    "wof:name":"PR25 1BU",
    "wof:placetype":"postalcode"
},
  "geometry": {"coordinates":[-2.705213,53.686955],"type":"Point"}
}