{
  "type": "Feature",
  "properties": {
    "iso:country":"GB",
    "wof:name":"NP4 8JU",
    "wof:placetype":"postalcode"
},
  "geometry": {"coordinates":[-3.03701925233382,51.70970397018834],"type":"Point"}
}