{
  "type": "Feature",
  "properties": {
    "date:inception_lower":"1980-01-01",
    "date:inception_upper":"1980-01-31",
    "iso:country":"GB",
    "wof:name":"NP4 8JU",
    "wof:placetype":"postalcode"
},
  "geometry": {"coordinates":[-3.037019,51.709704],"type":"Point"}
}