{
  "type": "Feature",
  "properties": {
    "iso:country": "GB",
    "wof:name": "ME13 9SH",
    "wof:placetype": "postalcode"
  },
  "geometry": {"coordinates":[0.954271,51.294888],"type":"Point"}
}
