{
  "type": "Feature",
  "properties": {
    "date:inception_lower": "1999-12-01",
    "date:inception_upper": "1999-12-01",
    "iso:country": "GB",
    "wof:name": "WS2 7PW",
    "wof:placetype": "postalcode"
  },
  "geometry": {"coordinates":[-1.981286,52.585996],"type":"Point"}
}
