{
  "type": "Feature",
  "properties": {
    "iso:country":"GB",
    "wof:name":"OL6 9EL",
    "wof:placetype":"postalcode"
},
  "geometry": {"coordinates":[-2.07666485027475,53.50065885828382],"type":"Point"}
}