{
  "type": "Feature",
  "properties": {
    "date:inception_lower": "1980-01-01",
    "date:inception_upper": "1980-01-01",
    "iso:country": "GB",
    "wof:name": "OL6 9EL",
    "wof:placetype": "postalcode"
  },
  "geometry": {"coordinates":[-2.076694,53.500837],"type":"Point"}
}
