{
  "type": "Feature",
  "properties": {
    "iso:country":"GB",
    "wof:name":"NN5 7DY",
    "wof:placetype":"postalcode"
},
  "geometry": {"coordinates":[-0.91193831431913,52.24354442191836],"type":"Point"}
}