{
  "type": "Feature",
  "properties": {
    "iso:country":"GB",
    "wof:name":"PA15 2EL",
    "wof:placetype":"postalcode"
},
  "geometry": {"coordinates":[-4.73514256362507,55.93875308408534],"type":"Point"}
}