{
  "type": "Feature",
  "properties": {
    "date:inception_lower": "1980-01-01",
    "date:inception_upper": "1980-01-01",
    "iso:country": "GB",
    "wof:name": "PA15 2EL",
    "wof:placetype": "postalcode"
  },
  "geometry": {"coordinates":[-4.735124,55.938756],"type":"Point"}
}
