{
  "type": "Feature",
  "properties": {
    "date:inception_lower":"1980-01-01",
    "date:inception_upper":"1980-01-31",
    "iso:country":"GB",
    "wof:name":"OX17 1BY",
    "wof:placetype":"postalcode"
},
  "geometry": {"coordinates":[-1.401584,52.124932],"type":"Point"}
}