{
  "type": "Feature",
  "properties": {
    "iso:country":"GB",
    "wof:name":"OX17 1BY",
    "wof:placetype":"postalcode"
},
  "geometry": {"coordinates":[-1.40158445130387,52.12493153462788],"type":"Point"}
}