{
  "type": "Feature",
  "properties": {
    "iso:country": "GB",
    "wof:name": "OX17 1BY",
    "wof:placetype": "postalcode"
  },
  "geometry": {"coordinates":[-1.401584,52.124932],"type":"Point"}
}
