{
  "type": "Feature",
  "properties": {
    "date:inception_lower":"2006-07-01",
    "date:inception_upper":"2006-07-31",
    "iso:country":"GB",
    "wof:name":"NE34 8BY",
    "wof:placetype":"postalcode"
},
  "geometry": {"coordinates":[-1.412507,54.968977],"type":"Point"}
}