{
  "type": "Feature",
  "properties": {
    "iso:country": "GB",
    "wof:name": "NE34 8BY",
    "wof:placetype": "postalcode"
  },
  "geometry": {"coordinates":[-1.412507,54.968977],"type":"Point"}
}
