{
  "type": "Feature",
  "properties": {
    "iso:country":"GB",
    "wof:name":"NE34 8BY",
    "wof:placetype":"postalcode"
},
  "geometry": {"coordinates":[-1.41250698703748,54.9689768174097],"type":"Point"}
}