{
  "type": "Feature",
  "properties": {
    "iso:country":"GB",
    "wof:name":"CV4 9YP",
    "wof:placetype":"postalcode"
},
  "geometry": {"coordinates":[-1.5744507480418,52.39979749013989],"type":"Point"}
}