{
  "type": "Feature",
  "properties": {
    "iso:country": "GB",
    "wof:name": "CV4 9YP",
    "wof:placetype": "postalcode"
  },
  "geometry": {"coordinates":[-1.574451,52.399797],"type":"Point"}
}
