{
  "type": "Feature",
  "properties": {
    "date:inception_lower":"2012-07-01",
    "date:inception_upper":"2012-07-31",
    "iso:country":"GB",
    "wof:name":"CV4 9YP",
    "wof:placetype":"postalcode"
},
  "geometry": {"coordinates":[-1.574451,52.399797],"type":"Point"}
}