{
  "type": "Feature",
  "properties": {
    "iso:country": "GB",
    "wof:name": "BN11 5SL",
    "wof:placetype": "postalcode"
  },
  "geometry": {"coordinates":[-0.402047,50.80907],"type":"Point"}
}
