{
  "type": "Feature",
  "properties": {
    "date:inception_lower": "2017-10-01",
    "date:inception_upper": "2017-10-01",
    "iso:country": "GB",
    "wof:name": "BS11 9BP",
    "wof:placetype": "postalcode"
  },
  "geometry": {"coordinates":[-2.691926,51.521551],"type":"Point"}
}
