{
  "type": "Feature",
  "properties": {
    "iso:country": "GB",
    "wof:name": "BS11 9BP",
    "wof:placetype": "postalcode"
  },
  "geometry": {"coordinates":[-2.691926,51.521551],"type":"Point"}
}
