{
  "type": "Feature",
  "properties": {
    "iso:country":"GB",
    "wof:name":"BS11 9BP",
    "wof:placetype":"postalcode"
},
  "geometry": {"coordinates":[-2.69216788024824,51.52165990177593],"type":"Point"}
}