{
  "type": "Feature",
  "properties": {
    "iso:country":"GB",
    "wof:name":"DG9 7QE",
    "wof:placetype":"postalcode"
},
  "geometry": {"coordinates":[-5.03340253436437,54.89991744948912],"type":"Point"}
}