{
  "type": "Feature",
  "properties": {
    "date:inception_lower": "1995-01-01",
    "date:inception_upper": "1995-01-01",
    "iso:country": "GB",
    "wof:name": "TS25 2EB",
    "wof:placetype": "postalcode"
  },
  "geometry": {"coordinates":[-1.239002,54.64471],"type":"Point"}
}
