{
  "type": "Feature",
  "properties": {
    "iso:country":"GB",
    "wof:name":"E16 2FS",
    "wof:placetype":"postalcode"
},
  "geometry": {"coordinates":[0.03834293766716,51.50228205606975],"type":"Point"}
}