{
  "type": "Feature",
  "properties": {
    "iso:country":"GB",
    "wof:name":"WS5 3QS",
    "wof:placetype":"postalcode"
},
  "geometry": {"coordinates":[-1.9505955722414,52.57734845208811],"type":"Point"}
}