{
  "type": "Feature",
  "properties": {
    "iso:country":"GB",
    "wof:name":"WS2 9TE",
    "wof:placetype":"postalcode"
},
  "geometry": {"coordinates":[-2.00634676602432,52.58012732339186],"type":"Point"}
}