{
  "type": "Feature",
  "properties": {
    "iso:country":"GB",
    "wof:name":"LE9 4NS",
    "wof:placetype":"postalcode"
},
  "geometry": {"coordinates":[-1.28262929519497,52.53662920249059],"type":"Point"}
}