{
  "type": "Feature",
  "properties": {
    "iso:country":"GB",
    "wof:name":"B65 9EA",
    "wof:placetype":"postalcode"
},
  "geometry": {"coordinates":[-2.04237363841383,52.49243261708937],"type":"Point"}
}