{
  "type": "Feature",
  "properties": {
    "iso:country":"GB",
    "wof:name":"SY8 3LH",
    "wof:placetype":"postalcode"
},
  "geometry": {"coordinates":[-2.62112285932514,52.36689718609816],"type":"Point"}
}