{
  "type": "Feature",
  "properties": {
    "iso:country":"GB",
    "wof:name":"KY6 2SG",
    "wof:placetype":"postalcode"
},
  "geometry": {"coordinates":[-3.17681225718949,56.18809516909394],"type":"Point"}
}