{
  "type": "Feature",
  "properties": {
    "date:inception_lower": "1980-01-01",
    "date:inception_upper": "1980-01-01",
    "iso:country": "GB",
    "wof:name": "LL68 0RU",
    "wof:placetype": "postalcode"
  },
  "geometry": {"coordinates":[-4.45175,53.390022],"type":"Point"}
}
