{
  "type": "Feature",
  "properties": {
    "iso:country":"GB",
    "wof:name":"LL68 0RU",
    "wof:placetype":"postalcode"
},
  "geometry": {"coordinates":[-4.45159302446728,53.39000721768441],"type":"Point"}
}