{
  "type": "Feature",
  "properties": {
    "iso:country":"GB",
    "wof:name":"BA20 1BN",
    "wof:placetype":"postalcode"
},
  "geometry": {"coordinates":[-2.64181574274712,50.94179147353604],"type":"Point"}
}