{
  "type": "Feature",
  "properties": {
    "iso:country":"GB",
    "wof:name":"LL11 6TS",
    "wof:placetype":"postalcode"
},
  "geometry": {"coordinates":[-3.02584531095532,53.05317696089597],"type":"Point"}
}