{
  "type": "Feature",
  "properties": {
    "iso:country": "GB",
    "wof:name": "TS27 4QN",
    "wof:placetype": "postalcode"
  },
  "geometry": {"coordinates":[-1.293616,54.745324],"type":"Point"}
}
