{
  "type": "Feature",
  "properties": {
    "date:inception_lower": "1987-04-01",
    "date:inception_upper": "1987-04-01",
    "iso:country": "GB",
    "wof:name": "TS27 4QN",
    "wof:placetype": "postalcode"
  },
  "geometry": {"coordinates":[-1.293616,54.745324],"type":"Point"}
}
