{
  "type": "Feature",
  "properties": {
    "iso:country": "GB",
    "wof:name": "IP17 1BX",
    "wof:placetype": "postalcode"
  },
  "geometry": {"coordinates":[1.480031,52.213754],"type":"Point"}
}
