{
  "type": "Feature",
  "properties": {
    "iso:country":"GB",
    "wof:name":"IP17 1BX",
    "wof:placetype":"postalcode"
},
  "geometry": {"coordinates":[1.48003061267008,52.21375427994771],"type":"Point"}
}