{
  "type": "Feature",
  "properties": {
    "iso:country":"GB",
    "wof:name":"LL22 8UN",
    "wof:placetype":"postalcode"
},
  "geometry": {"coordinates":[-3.69673444640578,53.16245929136871],"type":"Point"}
}