{
  "type": "Feature",
  "properties": {
    "iso:country": "GB",
    "wof:name": "LL22 8UN",
    "wof:placetype": "postalcode"
  },
  "geometry": {"coordinates":[-3.696734,53.162459],"type":"Point"}
}
