{
  "type": "Feature",
  "properties": {
    "iso:country": "GB",
    "wof:name": "OX29 8QN",
    "wof:placetype": "postalcode"
  },
  "geometry": {"coordinates":[-1.428625,51.853354],"type":"Point"}
}
