{
  "type": "Feature",
  "properties": {
    "iso:country":"GB",
    "wof:name":"RH12 3HF",
    "wof:placetype":"postalcode"
},
  "geometry": {"coordinates":[-0.44433807535285,51.0937029881268],"type":"Point"}
}