{
  "type": "Feature",
  "properties": {
    "date:inception_lower": "2023-07-01",
    "date:inception_upper": "2023-07-01",
    "iso:country": "GB",
    "wof:name": "CM20 2UH",
    "wof:placetype": "postalcode"
  },
  "geometry": {"coordinates":[0.09888,51.781278],"type":"Point"}
}
