{
  "type": "Feature",
  "properties": {
    "iso:country": "GB",
    "wof:name": "GL3 4JH",
    "wof:placetype": "postalcode"
  },
  "geometry": {"coordinates":[-2.154536,51.845657],"type":"Point"}
}
