{
  "type": "Feature",
  "properties": {
    "date:inception_lower": "1980-01-01",
    "date:inception_upper": "1980-01-01",
    "iso:country": "GB",
    "wof:name": "GL3 4JH",
    "wof:placetype": "postalcode"
  },
  "geometry": {"coordinates":[-2.154536,51.845657],"type":"Point"}
}
