{
  "type": "Feature",
  "properties": {
    "iso:country":"GB",
    "wof:name":"DN39 6GB",
    "wof:placetype":"postalcode"
},
  "geometry": {"coordinates":[-0.35419150961945,53.58477857003142],"type":"Point"}
}