{
  "type": "Feature",
  "properties": {
    "date:inception_lower": "2002-06-01",
    "date:inception_upper": "2002-06-01",
    "iso:country": "GB",
    "wof:name": "DN39 6GB",
    "wof:placetype": "postalcode"
  },
  "geometry": {"coordinates":[-0.354191,53.584779],"type":"Point"}
}
