{
  "type": "Feature",
  "properties": {
    "iso:country":"GB",
    "wof:name":"WR10 3GZ",
    "wof:placetype":"postalcode"
},
  "geometry": {"coordinates":[-2.02393780160746,52.06911330104499],"type":"Point"}
}