{
  "type": "Feature",
  "properties": {
    "iso:country": "GB",
    "wof:name": "WR10 3GZ",
    "wof:placetype": "postalcode"
  },
  "geometry": {"coordinates":[-2.023938,52.069113],"type":"Point"}
}
