{
  "type": "Feature",
  "properties": {
    "iso:country":"GB",
    "wof:name":"HD2 1JT",
    "wof:placetype":"postalcode"
},
  "geometry": {"coordinates":[-1.75857486653685,53.67046302839435],"type":"Point"}
}