{
  "type": "Feature",
  "properties": {
    "iso:country":"GB",
    "wof:name":"BS27 3QJ",
    "wof:placetype":"postalcode"
},
  "geometry": {"coordinates":[-2.77117810111107,51.28136473893466],"type":"Point"}
}