{
  "type": "Feature",
  "properties": {
    "iso:country":"GB",
    "wof:name":"S12 4AN",
    "wof:placetype":"postalcode"
},
  "geometry": {"coordinates":[-1.37086067422441,53.34481962291513],"type":"Point"}
}