{
  "type": "Feature",
  "properties": {
    "date:inception_lower": "2016-11-01",
    "date:inception_upper": "2016-11-01",
    "iso:country": "GB",
    "wof:name": "MK3 6FP",
    "wof:placetype": "postalcode"
  },
  "geometry": {"coordinates":[-0.739646,52.002751],"type":"Point"}
}
