{
  "type": "Feature",
  "properties": {
    "iso:country": "GB",
    "wof:name": "RG26 5DP",
    "wof:placetype": "postalcode"
  },
  "geometry": {"coordinates":[-1.058361,51.306973],"type":"Point"}
}
