{
  "type": "Feature",
  "properties": {
    "iso:country":"GB",
    "wof:name":"RG26 5DP",
    "wof:placetype":"postalcode"
},
  "geometry": {"coordinates":[-1.05837984637133,51.30697220162506],"type":"Point"}
}