{
  "type": "Feature",
  "properties": {
    "iso:country": "GB",
    "wof:name": "TS2 1LF",
    "wof:placetype": "postalcode"
  },
  "geometry": {"coordinates":[-1.241045,54.583219],"type":"Point"}
}
