{
  "type": "Feature",
  "properties": {
    "date:inception_lower":"2017-01-01",
    "date:inception_upper":"2017-01-31",
    "iso:country":"GB",
    "wof:name":"TS2 1LF",
    "wof:placetype":"postalcode"
},
  "geometry": {"coordinates":[-1.241045,54.583219],"type":"Point"}
}