{
  "type": "Feature",
  "properties": {
    "iso:country":"GB",
    "wof:name":"BL6 7DL",
    "wof:placetype":"postalcode"
},
  "geometry": {"coordinates":[-2.54589360413187,53.60194024326417],"type":"Point"}
}