{
  "type": "Feature",
  "properties": {
    "iso:country":"GB",
    "wof:name":"SO50 5HH",
    "wof:placetype":"postalcode"
},
  "geometry": {"coordinates":[-1.35695394146405,50.96578841159645],"type":"Point"}
}