{
  "type": "Feature",
  "properties": {
    "iso:country":"GB",
    "wof:name":"BR3 1AF",
    "wof:placetype":"postalcode"
},
  "geometry": {"coordinates":[-0.02848928630498,51.40631229454559],"type":"Point"}
}