{
  "type": "Feature",
  "properties": {
    "date:inception_lower":"1980-01-01",
    "date:inception_upper":"1980-01-31",
    "iso:country":"GB",
    "wof:name":"BR3 1AF",
    "wof:placetype":"postalcode"
},
  "geometry": {"coordinates":[-0.028489,51.406312],"type":"Point"}
}