{
  "type": "Feature",
  "properties": {
    "iso:country":"GB",
    "wof:name":"SS15 5SR",
    "wof:placetype":"postalcode"
},
  "geometry": {"coordinates":[0.43219978488853,51.58001155217416],"type":"Point"}
}