{
  "type": "Feature",
  "properties": {
    "iso:country":"GB",
    "wof:name":"M20 3JH",
    "wof:placetype":"postalcode"
},
  "geometry": {"coordinates":[-2.23197501514516,53.43234334044931],"type":"Point"}
}