{
  "type": "Feature",
  "properties": {
    "iso:country": "GB",
    "wof:name": "M20 3JH",
    "wof:placetype": "postalcode"
  },
  "geometry": {"coordinates":[-2.231975,53.432343],"type":"Point"}
}
