{
  "type": "Feature",
  "properties": {
    "iso:country":"GB",
    "wof:name":"RG1 8AR",
    "wof:placetype":"postalcode"
},
  "geometry": {"coordinates":[-0.9752623885776,51.46189840154435],"type":"Point"}
}