{
  "type": "Feature",
  "properties": {
    "iso:country": "GB",
    "wof:name": "RG1 8AR",
    "wof:placetype": "postalcode"
  },
  "geometry": {"coordinates":[-0.975262,51.461898],"type":"Point"}
}
