{
  "type": "Feature",
  "properties": {
    "iso:country":"GB",
    "wof:name":"LE14 2DT",
    "wof:placetype":"postalcode"
},
  "geometry": {"coordinates":[-0.93893851955334,52.75184256986514],"type":"Point"}
}