{
  "type": "Feature",
  "properties": {
    "iso:country": "GB",
    "wof:name": "LE14 2DT",
    "wof:placetype": "postalcode"
  },
  "geometry": {"coordinates":[-0.938938,52.751843],"type":"Point"}
}
