{
  "type": "Feature",
  "properties": {
    "date:inception_lower":"1980-01-01",
    "date:inception_upper":"1980-01-31",
    "iso:country":"GB",
    "wof:name":"M24 4HT",
    "wof:placetype":"postalcode"
},
  "geometry": {"coordinates":[-2.216463,53.557698],"type":"Point"}
}