{
  "type": "Feature",
  "properties": {
    "iso:country":"GB",
    "wof:name":"M24 4HT",
    "wof:placetype":"postalcode"
},
  "geometry": {"coordinates":[-2.2164632943107,53.55769819303833],"type":"Point"}
}