{
  "type": "Feature",
  "properties": {
    "iso:country": "GB",
    "wof:name": "SA71 5JJ",
    "wof:placetype": "postalcode"
  },
  "geometry": {"coordinates":[-4.897654,51.672506],"type":"Point"}
}
