{
  "type": "Feature",
  "properties": {
    "iso:country":"GB",
    "wof:name":"SA71 5JJ",
    "wof:placetype":"postalcode"
},
  "geometry": {"coordinates":[-4.89764434790697,51.67244017491358],"type":"Point"}
}