{
  "type": "Feature",
  "properties": {
    "date:inception_lower": "1988-03-01",
    "date:inception_upper": "1988-03-01",
    "iso:country": "GB",
    "wof:name": "DN14 0JX",
    "wof:placetype": "postalcode"
  },
  "geometry": {"coordinates":[-1.148116,53.70667],"type":"Point"}
}
