{
  "type": "Feature",
  "properties": {
    "date:inception_lower": "1999-12-01",
    "date:inception_upper": "1999-12-01",
    "iso:country": "GB",
    "wof:name": "GL15 5EU",
    "wof:placetype": "postalcode"
  },
  "geometry": {"coordinates":[-2.537542,51.713299],"type":"Point"}
}
