{
  "type": "Feature",
  "properties": {
    "iso:country":"GB",
    "wof:name":"GL15 5EU",
    "wof:placetype":"postalcode"
},
  "geometry": {"coordinates":[-2.53469021526899,51.71336150033502],"type":"Point"}
}