{
  "type": "Feature",
  "properties": {
    "iso:country": "GB",
    "wof:name": "PE20 2BP",
    "wof:placetype": "postalcode"
  },
  "geometry": {"coordinates":[-0.092552,52.902083],"type":"Point"}
}
