{
  "type": "Feature",
  "properties": {
    "iso:country": "GB",
    "wof:name": "PA16 9NT",
    "wof:placetype": "postalcode"
  },
  "geometry": {"coordinates":[-4.778988,55.936908],"type":"Point"}
}
