{
  "type": "Feature",
  "properties": {
    "iso:country":"GB",
    "wof:name":"PA16 9NT",
    "wof:placetype":"postalcode"
},
  "geometry": {"coordinates":[-4.77898766786921,55.93690830138506],"type":"Point"}
}