{
  "type": "Feature",
  "properties": {
    "iso:country":"GB",
    "wof:name":"EX23 8QN",
    "wof:placetype":"postalcode"
},
  "geometry": {"coordinates":[-4.53152047833847,50.82089004034005],"type":"Point"}
}