{
  "type": "Feature",
  "properties": {
    "iso:country":"GB",
    "wof:name":"PL18 9EG",
    "wof:placetype":"postalcode"
},
  "geometry": {"coordinates":[-4.22347482372264,50.51592181100022],"type":"Point"}
}