{
  "type": "Feature",
  "properties": {
    "iso:country":"GB",
    "wof:name":"DH9 6JS",
    "wof:placetype":"postalcode"
},
  "geometry": {"coordinates":[-1.69088953254153,54.8654913991764],"type":"Point"}
}