{
  "type": "Feature",
  "properties": {
    "iso:country": "GB",
    "wof:name": "EH54 5NW",
    "wof:placetype": "postalcode"
  },
  "geometry": {"coordinates":[-3.486306,55.896364],"type":"Point"}
}
