{
  "type": "Feature",
  "properties": {
    "iso:country":"GB",
    "wof:name":"RH10 6PP",
    "wof:placetype":"postalcode"
},
  "geometry": {"coordinates":[-0.16409410126961,51.10334331786115],"type":"Point"}
}