{
  "type": "Feature",
  "properties": {
    "date:inception_lower":"1990-02-01",
    "date:inception_upper":"1990-02-28",
    "iso:country":"GB",
    "wof:name":"M35 0WL",
    "wof:placetype":"postalcode"
},
  "geometry": {"coordinates":[-2.158716,53.50358],"type":"Point"}
}