{
  "type": "Feature",
  "properties": {
    "iso:country":"GB",
    "wof:name":"AL5 5RE",
    "wof:placetype":"postalcode"
},
  "geometry": {"coordinates":[-0.33696969537674,51.81748713834018],"type":"Point"}
}