{
  "type": "Feature",
  "properties": {
    "date:inception_lower": "1998-12-01",
    "date:inception_upper": "1998-12-01",
    "iso:country": "GB",
    "wof:name": "DA2 6RU",
    "wof:placetype": "postalcode"
  },
  "geometry": {"coordinates":[0.237002,51.446087],"type":"Point"}
}
