{
  "type": "Feature",
  "properties": {
    "iso:country": "GB",
    "wof:name": "DA2 6RU",
    "wof:placetype": "postalcode"
  },
  "geometry": {"coordinates":[0.237002,51.446087],"type":"Point"}
}
