{
  "type": "Feature",
  "properties": {
    "iso:country":"GB",
    "wof:name":"DA2 6RU",
    "wof:placetype":"postalcode"
},
  "geometry": {"coordinates":[0.23700244637817,51.4460871813051],"type":"Point"}
}