{
  "type": "Feature",
  "properties": {
    "iso:country":"GB",
    "wof:name":"DE24 9NU",
    "wof:placetype":"postalcode"
},
  "geometry": {"coordinates":[-1.49884412475103,52.88129184747427],"type":"Point"}
}