{
  "type": "Feature",
  "properties": {
    "date:inception_lower":"1983-01-01",
    "date:inception_upper":"1983-01-31",
    "iso:country":"GB",
    "wof:name":"GU9 0SF",
    "wof:placetype":"postalcode"
},
  "geometry": {"coordinates":[-0.805081,51.233021],"type":"Point"}
}