{
  "type": "Feature",
  "properties": {
    "iso:country":"GB",
    "wof:name":"GU9 0SF",
    "wof:placetype":"postalcode"
},
  "geometry": {"coordinates":[-0.80508060772509,51.23302086496501],"type":"Point"}
}