{
  "type": "Feature",
  "properties": {
    "iso:country":"GB",
    "wof:name":"TS2 1LX",
    "wof:placetype":"postalcode"
},
  "geometry": {"coordinates":[-1.23161233129556,54.58378497341099],"type":"Point"}
}