{
  "type": "Feature",
  "properties": {
    "date:inception_lower":"1980-01-01",
    "date:inception_upper":"1980-01-31",
    "iso:country":"GB",
    "wof:name":"YO12 7ST",
    "wof:placetype":"postalcode"
},
  "geometry": {"coordinates":[-0.406706,54.283255],"type":"Point"}
}