{
  "type": "Feature",
  "properties": {
    "iso:country":"GB",
    "wof:name":"SE8 4JL",
    "wof:placetype":"postalcode"
},
  "geometry": {"coordinates":[-0.01776987330105,51.4679656410336],"type":"Point"}
}