{
  "type": "Feature",
  "properties": {
    "date:inception_lower":"1980-01-01",
    "date:inception_upper":"1980-01-31",
    "iso:country":"GB",
    "wof:name":"B28 0UD",
    "wof:placetype":"postalcode"
},
  "geometry": {"coordinates":[-1.848926,52.41245],"type":"Point"}
}