{
  "type": "Feature",
  "properties": {
    "iso:country":"GB",
    "wof:name":"B28 0UD",
    "wof:placetype":"postalcode"
},
  "geometry": {"coordinates":[-1.84892636563853,52.41244999576245],"type":"Point"}
}