{
  "type": "Feature",
  "properties": {
    "date:inception_lower": "2023-04-01",
    "date:inception_upper": "2023-04-01",
    "iso:country": "GB",
    "wof:name": "DN2 4FJ",
    "wof:placetype": "postalcode"
  },
  "geometry": {"coordinates":[-1.110857,53.543798],"type":"Point"}
}
