{
  "type": "Feature",
  "properties": {
    "iso:country":"GB",
    "wof:name":"DN21 3GA",
    "wof:placetype":"postalcode"
},
  "geometry": {"coordinates":[-0.67112157399913,53.49787496432006],"type":"Point"}
}