{
  "type": "Feature",
  "properties": {
    "iso:country":"GB",
    "wof:name":"WA7 6JB",
    "wof:placetype":"postalcode"
},
  "geometry": {"coordinates":[-2.65896280563903,53.32314556788424],"type":"Point"}
}