{
  "type": "Feature",
  "properties": {
    "date:inception_lower": "1980-01-01",
    "date:inception_upper": "1980-01-01",
    "iso:country": "GB",
    "wof:name": "WA7 6JB",
    "wof:placetype": "postalcode"
  },
  "geometry": {"coordinates":[-2.658963,53.323146],"type":"Point"}
}
