{
  "type": "Feature",
  "properties": {
    "date:inception_lower": "1980-01-01",
    "date:inception_upper": "1980-01-01",
    "iso:country": "GB",
    "wof:name": "B33 0EN",
    "wof:placetype": "postalcode"
  },
  "geometry": {"coordinates":[-1.763536,52.481767],"type":"Point"}
}
