{
  "type": "Feature",
  "properties": {
    "iso:country": "GB",
    "wof:name": "B33 0EN",
    "wof:placetype": "postalcode"
  },
  "geometry": {"coordinates":[-1.763536,52.481767],"type":"Point"}
}
