{
  "type": "Feature",
  "properties": {
    "date:inception_lower": "2021-10-01",
    "date:inception_upper": "2021-10-01",
    "iso:country": "GB",
    "wof:name": "LE12 6AS",
    "wof:placetype": "postalcode"
  },
  "geometry": {"coordinates":[-1.180513,52.821982],"type":"Point"}
}
