{
  "type": "Feature",
  "properties": {
    "iso:country":"GB",
    "wof:name":"PO16 0HY",
    "wof:placetype":"postalcode"
},
  "geometry": {"coordinates":[-1.18934733798461,50.85249165908596],"type":"Point"}
}