{
  "type": "Feature",
  "properties": {
    "iso:country":"GB",
    "wof:name":"TW13 7EW",
    "wof:placetype":"postalcode"
},
  "geometry": {"coordinates":[-0.4083325007255,51.44401854665806],"type":"Point"}
}