{
  "type": "Feature",
  "properties": {
    "iso:country":"GB",
    "wof:name":"TN1 1UD",
    "wof:placetype":"postalcode"
},
  "geometry": {"coordinates":[0.26122432214916,51.12702525188664],"type":"Point"}
}