{
  "type": "Feature",
  "properties": {
    "iso:country":"GB",
    "wof:name":"HP2 4UA",
    "wof:placetype":"postalcode"
},
  "geometry": {"coordinates":[-0.42828476205463,51.75537769756118],"type":"Point"}
}