{
  "type": "Feature",
  "properties": {
    "date:inception_lower":"1980-01-01",
    "date:inception_upper":"1980-01-31",
    "iso:country":"GB",
    "wof:name":"PO9 3HS",
    "wof:placetype":"postalcode"
},
  "geometry": {"coordinates":[-0.999895,50.85845],"type":"Point"}
}