{
  "type": "Feature",
  "properties": {
    "iso:country":"GB",
    "wof:name":"SW15 3PR",
    "wof:placetype":"postalcode"
},
  "geometry": {"coordinates":[-0.25739002777345,51.43512764239497],"type":"Point"}
}