{
  "type": "Feature",
  "properties": {
    "iso:country": "GB",
    "wof:name": "SW15 3PR",
    "wof:placetype": "postalcode"
  },
  "geometry": {"coordinates":[-0.25739,51.435128],"type":"Point"}
}
