{
  "type": "Feature",
  "properties": {
    "iso:country":"GB",
    "wof:name":"RH12 5HU",
    "wof:placetype":"postalcode"
},
  "geometry": {"coordinates":[-0.3215488312104,51.08590743643641],"type":"Point"}
}