{
  "type": "Feature",
  "properties": {
    "iso:country":"GB",
    "wof:name":"PL25 5RH",
    "wof:placetype":"postalcode"
},
  "geometry": {"coordinates":[-4.8103617014056,50.35243908227012],"type":"Point"}
}