{
  "type": "Feature",
  "properties": {
    "iso:country":"GB",
    "wof:name":"PO6 1JN",
    "wof:placetype":"postalcode"
},
  "geometry": {"coordinates":[-1.03371595548578,50.84577664868584],"type":"Point"}
}