{
  "type": "Feature",
  "properties": {
    "date:inception_lower": "1998-06-01",
    "date:inception_upper": "1998-06-01",
    "iso:country": "GB",
    "wof:name": "YO23 7BE",
    "wof:placetype": "postalcode"
  },
  "geometry": {"coordinates":[-1.154373,53.860207],"type":"Point"}
}
