{
  "type": "Feature",
  "properties": {
    "iso:country":"GB",
    "wof:name":"YO23 7BE",
    "wof:placetype":"postalcode"
},
  "geometry": {"coordinates":[-1.16388753128359,53.86163946774109],"type":"Point"}
}