{
  "type": "Feature",
  "properties": {
    "iso:country": "GB",
    "wof:name": "SW12 9AZ",
    "wof:placetype": "postalcode"
  },
  "geometry": {"coordinates":[-0.153385,51.442322],"type":"Point"}
}
