{
  "type": "Feature",
  "properties": {
    "iso:country":"GB",
    "wof:name":"SW12 9AZ",
    "wof:placetype":"postalcode"
},
  "geometry": {"coordinates":[-0.15336673613935,51.44233876566455],"type":"Point"}
}