{
  "type": "Feature",
  "properties": {
    "iso:country":"GB",
    "wof:name":"CW9 6JA",
    "wof:placetype":"postalcode"
},
  "geometry": {"coordinates":[-2.52712028185673,53.30132018992705],"type":"Point"}
}