{
  "type": "Feature",
  "properties": {
    "date:inception_lower":"2004-05-01",
    "date:inception_upper":"2004-05-31",
    "iso:country":"GB",
    "wof:name":"BA2 3LU",
    "wof:placetype":"postalcode"
},
  "geometry": {"coordinates":[-2.377493,51.376074],"type":"Point"}
}