{
  "type": "Feature",
  "properties": {
    "iso:country":"GB",
    "wof:name":"BA2 3LU",
    "wof:placetype":"postalcode"
},
  "geometry": {"coordinates":[-2.37749336098242,51.37607374623829],"type":"Point"}
}