{
  "type": "Feature",
  "properties": {
    "iso:country":"GB",
    "wof:name":"CF3 5UE",
    "wof:placetype":"postalcode"
},
  "geometry": {"coordinates":[-3.1129837990622,51.52412200907992],"type":"Point"}
}