{
  "type": "Feature",
  "properties": {
    "iso:country": "GB",
    "wof:name": "CF3 5UE",
    "wof:placetype": "postalcode"
  },
  "geometry": {"coordinates":[-3.112984,51.524122],"type":"Point"}
}
