{
  "type": "Feature",
  "properties": {
    "date:inception_lower": "1980-01-01",
    "date:inception_upper": "1980-01-01",
    "iso:country": "GB",
    "wof:name": "WN6 7HS",
    "wof:placetype": "postalcode"
  },
  "geometry": {"coordinates":[-2.643863,53.559297],"type":"Point"}
}
