{
  "type": "Feature",
  "properties": {
    "iso:country":"GB",
    "wof:name":"NG34 9AJ",
    "wof:placetype":"postalcode"
},
  "geometry": {"coordinates":[-0.39733109698278,53.04355560337786],"type":"Point"}
}