{
  "type": "Feature",
  "properties": {
    "iso:country":"GB",
    "wof:name":"BN3 7GU",
    "wof:placetype":"postalcode"
},
  "geometry": {"coordinates":[-0.19955694640913,50.83676988868775],"type":"Point"}
}