{
  "type": "Feature",
  "properties": {
    "date:inception_lower": "1980-01-01",
    "date:inception_upper": "1980-01-01",
    "iso:country": "GB",
    "wof:name": "CF41 7HQ",
    "wof:placetype": "postalcode"
  },
  "geometry": {"coordinates":[-3.491195,51.647115],"type":"Point"}
}
