{
  "type": "Feature",
  "properties": {
    "iso:country": "GB",
    "wof:name": "CF10 2GD",
    "wof:placetype": "postalcode"
  },
  "geometry": {"coordinates":[-3.172843,51.480432],"type":"Point"}
}
