{
  "type": "Feature",
  "properties": {
    "iso:country": "GB",
    "wof:name": "DY1 2NR",
    "wof:placetype": "postalcode"
  },
  "geometry": {"coordinates":[-2.11847,52.509279],"type":"Point"}
}
