{
  "type": "Feature",
  "properties": {
    "iso:country":"GB",
    "wof:name":"DY1 2NR",
    "wof:placetype":"postalcode"
},
  "geometry": {"coordinates":[-2.11859352850984,52.50925470574146],"type":"Point"}
}