{
  "type": "Feature",
  "properties": {
    "iso:country":"GB",
    "wof:name":"LN11 0GD",
    "wof:placetype":"postalcode"
},
  "geometry": {"coordinates":[-0.00036983679498,53.3736774907924],"type":"Point"}
}