{
  "type": "Feature",
  "properties": {
    "date:inception_lower":"1996-12-01",
    "date:inception_upper":"1996-12-31",
    "iso:country":"GB",
    "wof:name":"LN11 0GD",
    "wof:placetype":"postalcode"
},
  "geometry": {"coordinates":[-0.000339,53.373729],"type":"Point"}
}