{
  "type": "Feature",
  "properties": {
    "date:inception_lower": "1998-06-01",
    "date:inception_upper": "1998-06-01",
    "iso:country": "GB",
    "wof:name": "WA1 2NJ",
    "wof:placetype": "postalcode"
  },
  "geometry": {"coordinates":[-2.590423,53.390138],"type":"Point"}
}
