{
  "type": "Feature",
  "properties": {
    "date:inception_lower": "2015-07-01",
    "date:inception_upper": "2015-07-01",
    "iso:country": "GB",
    "wof:name": "YO25 5AA",
    "wof:placetype": "postalcode"
  },
  "geometry": {"coordinates":[-0.432764,54.010688],"type":"Point"}
}
