{
  "type": "Feature",
  "properties": {
    "iso:country": "GB",
    "wof:name": "YO25 5AA",
    "wof:placetype": "postalcode"
  },
  "geometry": {"coordinates":[-0.432764,54.010688],"type":"Point"}
}
