{
  "type": "Feature",
  "properties": {
    "iso:country":"GB",
    "wof:name":"YO25 5AA",
    "wof:placetype":"postalcode"
},
  "geometry": {"coordinates":[-0.43276454303447,54.01068824417808],"type":"Point"}
}