{
  "type": "Feature",
  "properties": {
    "date:inception_lower": "2003-11-01",
    "date:inception_upper": "2003-11-01",
    "iso:country": "GB",
    "wof:name": "PE31 8LA",
    "wof:placetype": "postalcode"
  },
  "geometry": {"coordinates":[0.622648,52.902688],"type":"Point"}
}
