{
  "type": "Feature",
  "properties": {
    "iso:country":"GB",
    "wof:name":"PE31 8LA",
    "wof:placetype":"postalcode"
},
  "geometry": {"coordinates":[0.6226475013385,52.90268810699499],"type":"Point"}
}