{
  "type": "Feature",
  "properties": {
    "iso:country":"GB",
    "wof:name":"KA8 9RB",
    "wof:placetype":"postalcode"
},
  "geometry": {"coordinates":[-4.60312421158298,55.47104033869036],"type":"Point"}
}