{
  "type": "Feature",
  "properties": {
    "date:inception_lower": "2005-07-01",
    "date:inception_upper": "2005-07-01",
    "iso:country": "GB",
    "wof:name": "MK44 3EQ",
    "wof:placetype": "postalcode"
  },
  "geometry": {"coordinates":[-0.423372,52.112315],"type":"Point"}
}
