{
  "type": "Feature",
  "properties": {
    "iso:country":"GB",
    "wof:name":"EH22 4QF",
    "wof:placetype":"postalcode"
},
  "geometry": {"coordinates":[-3.06264547600107,55.86433161507844],"type":"Point"}
}