{
  "type": "Feature",
  "properties": {
    "iso:country": "GB",
    "wof:name": "KY11 1JW",
    "wof:placetype": "postalcode"
  },
  "geometry": {"coordinates":[-3.395438,56.011307],"type":"Point"}
}
