{
  "type": "Feature",
  "properties": {
    "iso:country": "GB",
    "wof:name": "CW3 0BF",
    "wof:placetype": "postalcode"
  },
  "geometry": {"coordinates":[-2.501354,52.985473],"type":"Point"}
}
