{
  "type": "Feature",
  "properties": {
    "iso:country":"GB",
    "wof:name":"CW3 0BF",
    "wof:placetype":"postalcode"
},
  "geometry": {"coordinates":[-2.50111565422462,52.98545849153059],"type":"Point"}
}