{
  "type": "Feature",
  "properties": {
    "date:inception_lower": "1980-01-01",
    "date:inception_upper": "1980-01-01",
    "iso:country": "GB",
    "wof:name": "TF9 3QZ",
    "wof:placetype": "postalcode"
  },
  "geometry": {"coordinates":[-2.502429,52.90605],"type":"Point"}
}
