{
  "type": "Feature",
  "properties": {
    "iso:country":"GB",
    "wof:name":"RH14 0BN",
    "wof:placetype":"postalcode"
},
  "geometry": {"coordinates":[-0.50633585004178,51.02390013764895],"type":"Point"}
}