{
  "type": "Feature",
  "properties": {
    "iso:country":"GB",
    "wof:name":"CM13 1ER",
    "wof:placetype":"postalcode"
},
  "geometry": {"coordinates":[0.34356926560211,51.63853436048988],"type":"Point"}
}