{
  "type": "Feature",
  "properties": {
    "date:inception_lower": "1980-01-01",
    "date:inception_upper": "1980-01-01",
    "iso:country": "GB",
    "wof:name": "WA15 6RP",
    "wof:placetype": "postalcode"
  },
  "geometry": {"coordinates":[-2.33855,53.39599],"type":"Point"}
}
