{
  "type": "Feature",
  "properties": {
    "iso:country":"GB",
    "wof:name":"RG20 4ST",
    "wof:placetype":"postalcode"
},
  "geometry": {"coordinates":[-1.24238400628573,51.34079446515242],"type":"Point"}
}