{
  "type": "Feature",
  "properties": {
    "iso:country": "GB",
    "wof:name": "RG20 4ST",
    "wof:placetype": "postalcode"
  },
  "geometry": {"coordinates":[-1.242384,51.340794],"type":"Point"}
}
