{
  "type": "Feature",
  "properties": {
    "iso:country":"GB",
    "wof:name":"SN7 8BB",
    "wof:placetype":"postalcode"
},
  "geometry": {"coordinates":[-1.59078791795694,51.65587415674838],"type":"Point"}
}