{
  "type": "Feature",
  "properties": {
    "iso:country":"GB",
    "wof:name":"DT8 3ND",
    "wof:placetype":"postalcode"
},
  "geometry": {"coordinates":[-2.77393043055294,50.84244077781237],"type":"Point"}
}