{
  "type": "Feature",
  "properties": {
    "iso:country": "GB",
    "wof:name": "DT8 3ND",
    "wof:placetype": "postalcode"
  },
  "geometry": {"coordinates":[-2.773987,50.842378],"type":"Point"}
}
