{
  "type": "Feature",
  "properties": {
    "date:inception_lower":"2007-01-01",
    "date:inception_upper":"2007-01-31",
    "iso:country":"GB",
    "wof:name":"SA7 0HY",
    "wof:placetype":"postalcode"
},
  "geometry": {"coordinates":[-3.893267,51.676587],"type":"Point"}
}