{
  "type": "Feature",
  "properties": {
    "iso:country":"GB",
    "wof:name":"SA7 0HY",
    "wof:placetype":"postalcode"
},
  "geometry": {"coordinates":[-3.89326676491925,51.67658684737707],"type":"Point"}
}