{
  "type": "Feature",
  "properties": {
    "iso:country": "GB",
    "wof:name": "HU7 3LS",
    "wof:placetype": "postalcode"
  },
  "geometry": {"coordinates":[-0.336979,53.804545],"type":"Point"}
}
