{
  "type": "Feature",
  "properties": {
    "date:inception_lower": "1980-01-01",
    "date:inception_upper": "1980-01-01",
    "iso:country": "GB",
    "wof:name": "PE13 1DY",
    "wof:placetype": "postalcode"
  },
  "geometry": {"coordinates":[0.160734,52.664941],"type":"Point"}
}
