{
  "type": "Feature",
  "properties": {
    "iso:country":"GB",
    "wof:name":"PE13 1DY",
    "wof:placetype":"postalcode"
},
  "geometry": {"coordinates":[0.16070149625377,52.6648865824397],"type":"Point"}
}