{
  "type": "Feature",
  "properties": {
    "iso:country":"GB",
    "wof:name":"NE49 0PF",
    "wof:placetype":"postalcode"
},
  "geometry": {"coordinates":[-2.46937275332343,54.93278758195429],"type":"Point"}
}