{
  "type": "Feature",
  "properties": {
    "iso:country": "GB",
    "wof:name": "BD9 4SA",
    "wof:placetype": "postalcode"
  },
  "geometry": {"coordinates":[-1.779258,53.80811],"type":"Point"}
}
