{
  "type": "Feature",
  "properties": {
    "date:inception_lower":"2008-07-01",
    "date:inception_upper":"2008-07-31",
    "iso:country":"GB",
    "wof:name":"BD9 4SA",
    "wof:placetype":"postalcode"
},
  "geometry": {"coordinates":[-1.779258,53.80811],"type":"Point"}
}