{
  "type": "Feature",
  "properties": {
    "iso:country":"GB",
    "wof:name":"BD9 4SA",
    "wof:placetype":"postalcode"
},
  "geometry": {"coordinates":[-1.77925784066025,53.80811014291937],"type":"Point"}
}