{
  "type": "Feature",
  "properties": {
    "iso:country":"GB",
    "wof:name":"DL12 8UR",
    "wof:placetype":"postalcode"
},
  "geometry": {"coordinates":[-1.89208721912119,54.53911042250535],"type":"Point"}
}