{
  "type": "Feature",
  "properties": {
    "date:inception_lower": "1985-04-01",
    "date:inception_upper": "1985-04-01",
    "iso:country": "GB",
    "wof:name": "L7 5QX",
    "wof:placetype": "postalcode"
  },
  "geometry": {"coordinates":[-2.94615,53.404541],"type":"Point"}
}
