{
  "type": "Feature",
  "properties": {
    "iso:country":"GB",
    "wof:name":"L7 5QX",
    "wof:placetype":"postalcode"
},
  "geometry": {"coordinates":[-2.94614965110735,53.4045408094492],"type":"Point"}
}