{
  "type": "Feature",
  "properties": {
    "iso:country": "GB",
    "wof:name": "BD6 1TT",
    "wof:placetype": "postalcode"
  },
  "geometry": {"coordinates":[-1.778148,53.765074],"type":"Point"}
}
