{
  "type": "Feature",
  "properties": {
    "date:inception_lower": "1980-01-01",
    "date:inception_upper": "1980-01-01",
    "iso:country": "GB",
    "wof:name": "IG8 9BN",
    "wof:placetype": "postalcode"
  },
  "geometry": {"coordinates":[0.017825,51.603336],"type":"Point"}
}
