{
  "type": "Feature",
  "properties": {
    "iso:country":"GB",
    "wof:name":"PL5 1TR",
    "wof:placetype":"postalcode"
},
  "geometry": {"coordinates":[-4.18392685954835,50.40291976380092],"type":"Point"}
}