{
  "type": "Feature",
  "properties": {
    "iso:country":"GB",
    "wof:name":"WA3 3XQ",
    "wof:placetype":"postalcode"
},
  "geometry": {"coordinates":[-2.60962550572334,53.48373937674741],"type":"Point"}
}