{
  "type": "Feature",
  "properties": {
    "iso:country":"GB",
    "wof:name":"B38 8QP",
    "wof:placetype":"postalcode"
},
  "geometry": {"coordinates":[-1.92853091707966,52.40618673218304],"type":"Point"}
}