{
  "type": "Feature",
  "properties": {
    "date:inception_lower": "1980-01-01",
    "date:inception_upper": "1980-01-01",
    "iso:country": "GB",
    "wof:name": "B38 8QP",
    "wof:placetype": "postalcode"
  },
  "geometry": {"coordinates":[-1.928531,52.406187],"type":"Point"}
}
