{
  "type": "Feature",
  "properties": {
    "iso:country": "GB",
    "wof:name": "SG3 6SP",
    "wof:placetype": "postalcode"
  },
  "geometry": {"coordinates":[-0.15913,51.849655],"type":"Point"}
}
