{
  "type": "Feature",
  "properties": {
    "date:inception_lower": "1991-01-01",
    "date:inception_upper": "1991-01-01",
    "iso:country": "GB",
    "wof:name": "SG3 6SP",
    "wof:placetype": "postalcode"
  },
  "geometry": {"coordinates":[-0.15913,51.849655],"type":"Point"}
}
