{
  "type": "Feature",
  "properties": {
    "iso:country":"GB",
    "wof:name":"SG3 6SP",
    "wof:placetype":"postalcode"
},
  "geometry": {"coordinates":[-0.15913014524923,51.84965478758369],"type":"Point"}
}