{
  "type": "Feature",
  "properties": {
    "iso:country":"GB",
    "wof:name":"SS4 3BL",
    "wof:placetype":"postalcode"
},
  "geometry": {"coordinates":[0.69338955297915,51.59991016918163],"type":"Point"}
}