{
  "type": "Feature",
  "properties": {
    "date:inception_lower":"1994-05-01",
    "date:inception_upper":"1994-05-31",
    "iso:country":"GB",
    "wof:name":"M26 2TG",
    "wof:placetype":"postalcode"
},
  "geometry": {"coordinates":[-2.327302,53.562479],"type":"Point"}
}