{
  "type": "Feature",
  "properties": {
    "iso:country":"GB",
    "wof:name":"M26 2TG",
    "wof:placetype":"postalcode"
},
  "geometry": {"coordinates":[-2.32730245123004,53.56247949726989],"type":"Point"}
}