{
  "type": "Feature",
  "properties": {
    "iso:country":"GB",
    "wof:name":"HD9 6QQ",
    "wof:placetype":"postalcode"
},
  "geometry": {"coordinates":[-1.78233435938217,53.60062510836715],"type":"Point"}
}