{
  "type": "Feature",
  "properties": {
    "iso:country":"GB",
    "wof:name":"WR11 7SP",
    "wof:placetype":"postalcode"
},
  "geometry": {"coordinates":[-2.00628212654125,52.0451826107798],"type":"Point"}
}