{
  "type": "Feature",
  "properties": {
    "iso:country":"GB",
    "wof:name":"SL2 1BH",
    "wof:placetype":"postalcode"
},
  "geometry": {"coordinates":[-0.61146390139247,51.53149440349399],"type":"Point"}
}