{
  "type": "Feature",
  "properties": {
    "date:inception_lower":"1999-06-01",
    "date:inception_upper":"1999-06-30",
    "iso:country":"GB",
    "wof:name":"NP20 2PA",
    "wof:placetype":"postalcode"
},
  "geometry": {"coordinates":[-2.991858,51.582083],"type":"Point"}
}