{
  "type": "Feature",
  "properties": {
    "iso:country":"GB",
    "wof:name":"NP20 2PA",
    "wof:placetype":"postalcode"
},
  "geometry": {"coordinates":[-2.9916724020503,51.58178618450418],"type":"Point"}
}