{
  "type": "Feature",
  "properties": {
    "iso:country": "GB",
    "wof:name": "CO4 3ZT",
    "wof:placetype": "postalcode"
  },
  "geometry": {"coordinates":[0.940155,51.878931],"type":"Point"}
}
