{
  "type": "Feature",
  "properties": {
    "date:inception_lower": "2018-10-01",
    "date:inception_upper": "2018-10-01",
    "iso:country": "GB",
    "wof:name": "CO4 3ZT",
    "wof:placetype": "postalcode"
  },
  "geometry": {"coordinates":[0.93964,51.878827],"type":"Point"}
}
