{
  "type": "Feature",
  "properties": {
    "date:inception_lower": "1987-04-01",
    "date:inception_upper": "1987-04-01",
    "iso:country": "GB",
    "wof:name": "PE30 3QN",
    "wof:placetype": "postalcode"
  },
  "geometry": {"coordinates":[0.432699,52.788187],"type":"Point"}
}
