{
  "type": "Feature",
  "properties": {
    "iso:country": "GB",
    "wof:name": "PE30 3QN",
    "wof:placetype": "postalcode"
  },
  "geometry": {"coordinates":[0.432699,52.788187],"type":"Point"}
}
