{
  "type": "Feature",
  "properties": {
    "iso:country":"GB",
    "wof:name":"PE30 3QN",
    "wof:placetype":"postalcode"
},
  "geometry": {"coordinates":[0.43269922308371,52.78818654093651],"type":"Point"}
}