{
  "type": "Feature",
  "properties": {
    "date:inception_lower": "1980-01-01",
    "date:inception_upper": "1980-01-01",
    "iso:country": "GB",
    "wof:name": "PO6 4JE",
    "wof:placetype": "postalcode"
  },
  "geometry": {"coordinates":[-1.106408,50.850456],"type":"Point"}
}
