{
  "type": "Feature",
  "properties": {
    "iso:country":"GB",
    "wof:name":"SM1 2RA",
    "wof:placetype":"postalcode"
},
  "geometry": {"coordinates":[-0.20033478233436,51.37128143032677],"type":"Point"}
}