{
  "type": "Feature",
  "properties": {
    "date:inception_lower": "1980-01-01",
    "date:inception_upper": "1980-01-01",
    "iso:country": "GB",
    "wof:name": "SM1 2RA",
    "wof:placetype": "postalcode"
  },
  "geometry": {"coordinates":[-0.200335,51.371281],"type":"Point"}
}
