{
  "type": "Feature",
  "properties": {
    "iso:country": "GB",
    "wof:name": "DN14 7PP",
    "wof:placetype": "postalcode"
  },
  "geometry": {"coordinates":[-0.795792,53.75901],"type":"Point"}
}
