{
  "type": "Feature",
  "properties": {
    "date:inception_lower":"1980-01-01",
    "date:inception_upper":"1980-01-31",
    "iso:country":"GB",
    "wof:name":"EX31 4HA",
    "wof:placetype":"postalcode"
},
  "geometry": {"coordinates":[-4.05598,51.12753],"type":"Point"}
}