{
  "type": "Feature",
  "properties": {
    "iso:country": "GB",
    "wof:name": "EX31 4HA",
    "wof:placetype": "postalcode"
  },
  "geometry": {"coordinates":[-4.05598,51.12753],"type":"Point"}
}
