{
  "type": "Feature",
  "properties": {
    "date:inception_lower":"2010-09-01",
    "date:inception_upper":"2010-09-30",
    "iso:country":"GB",
    "wof:name":"DN16 1UP",
    "wof:placetype":"postalcode"
},
  "geometry": {"coordinates":[-0.636938,53.585017],"type":"Point"}
}