{
  "type": "Feature",
  "properties": {
    "iso:country": "GB",
    "wof:name": "DN16 1UP",
    "wof:placetype": "postalcode"
  },
  "geometry": {"coordinates":[-0.636938,53.585017],"type":"Point"}
}
