{
  "type": "Feature",
  "properties": {
    "iso:country":"GB",
    "wof:name":"G46 7TY",
    "wof:placetype":"postalcode"
},
  "geometry": {"coordinates":[-4.30573819348559,55.80840595784728],"type":"Point"}
}