{
  "type": "Feature",
  "properties": {
    "iso:country":"GB",
    "wof:name":"SW19 6PG",
    "wof:placetype":"postalcode"
},
  "geometry": {"coordinates":[-0.20972796616492,51.44241274653329],"type":"Point"}
}