{
  "type": "Feature",
  "properties": {
    "iso:country": "GB",
    "wof:name": "DG7 1LJ",
    "wof:placetype": "postalcode"
  },
  "geometry": {"coordinates":[-3.92785,54.950892],"type":"Point"}
}
