{
  "type": "Feature",
  "properties": {
    "iso:country":"GB",
    "wof:name":"E4 7PQ",
    "wof:placetype":"postalcode"
},
  "geometry": {"coordinates":[-0.00530783173841,51.63927037115824],"type":"Point"}
}