{
  "type": "Feature",
  "properties": {
    "iso:country":"GB",
    "wof:name":"BS15 8SF",
    "wof:placetype":"postalcode"
},
  "geometry": {"coordinates":[-2.51417953011048,51.44997750878245],"type":"Point"}
}