{
  "type": "Feature",
  "properties": {
    "iso:country": "GB",
    "wof:name": "CT19 5TZ",
    "wof:placetype": "postalcode"
  },
  "geometry": {"coordinates":[1.164574,51.092356],"type":"Point"}
}
