{
  "type": "Feature",
  "properties": {
    "date:inception_lower": "1983-07-01",
    "date:inception_upper": "1983-07-01",
    "iso:country": "GB",
    "wof:name": "CT19 5TZ",
    "wof:placetype": "postalcode"
  },
  "geometry": {"coordinates":[1.164574,51.092356],"type":"Point"}
}
