{
  "type": "Feature",
  "properties": {
    "iso:country":"GB",
    "wof:name":"L35 9JZ",
    "wof:placetype":"postalcode"
},
  "geometry": {"coordinates":[-2.77811319137827,53.41585775601735],"type":"Point"}
}