{
  "type": "Feature",
  "properties": {
    "iso:country": "GB",
    "wof:name": "L35 9JZ",
    "wof:placetype": "postalcode"
  },
  "geometry": {"coordinates":[-2.778113,53.415858],"type":"Point"}
}
