{
  "type": "Feature",
  "properties": {
    "iso:country":"GB",
    "wof:name":"SG6 4LU",
    "wof:placetype":"postalcode"
},
  "geometry": {"coordinates":[-0.22725039761439,51.99150441462997],"type":"Point"}
}