{
  "type": "Feature",
  "properties": {
    "iso:country":"GB",
    "wof:name":"RM17 6DT",
    "wof:placetype":"postalcode"
},
  "geometry": {"coordinates":[0.32643651214025,51.47418538513503],"type":"Point"}
}