{
  "type": "Feature",
  "properties": {
    "iso:country":"GB",
    "wof:name":"WA10 5NJ",
    "wof:placetype":"postalcode"
},
  "geometry": {"coordinates":[-2.77693383914307,53.44936649571002],"type":"Point"}
}