{
  "type": "Feature",
  "properties": {
    "date:inception_lower":"1980-01-01",
    "date:inception_upper":"1980-01-31",
    "iso:country":"GB",
    "wof:name":"WA10 5NJ",
    "wof:placetype":"postalcode"
},
  "geometry": {"coordinates":[-2.776934,53.449366],"type":"Point"}
}