{
  "type": "Feature",
  "properties": {
    "iso:country":"GB",
    "wof:name":"DN32 9EP",
    "wof:placetype":"postalcode"
},
  "geometry": {"coordinates":[-0.07337057988298,53.56526692594818],"type":"Point"}
}