{
  "type": "Feature",
  "properties": {
    "iso:country":"GB",
    "wof:name":"BS26 2RG",
    "wof:placetype":"postalcode"
},
  "geometry": {"coordinates":[-2.88463776961135,51.27183094276356],"type":"Point"}
}