{
  "type": "Feature",
  "properties": {
    "date:inception_lower":"2003-03-01",
    "date:inception_upper":"2003-03-31",
    "iso:country":"GB",
    "wof:name":"WS12 3HF",
    "wof:placetype":"postalcode"
},
  "geometry": {"coordinates":[-1.985666,52.688057],"type":"Point"}
}