{
  "type": "Feature",
  "properties": {
    "iso:country":"GB",
    "wof:name":"WS12 3HF",
    "wof:placetype":"postalcode"
},
  "geometry": {"coordinates":[-1.98566627193102,52.68805727864201],"type":"Point"}
}