{
  "type": "Feature",
  "properties": {
    "iso:country": "GB",
    "wof:name": "WS12 3HF",
    "wof:placetype": "postalcode"
  },
  "geometry": {"coordinates":[-1.985666,52.688057],"type":"Point"}
}
