{
  "type": "Feature",
  "properties": {
    "iso:country":"GB",
    "wof:name":"IP28 8PA",
    "wof:placetype":"postalcode"
},
  "geometry": {"coordinates":[0.45791217285822,52.35524267318097],"type":"Point"}
}