{
  "type": "Feature",
  "properties": {
    "date:inception_lower": "1980-01-01",
    "date:inception_upper": "1980-01-01",
    "iso:country": "GB",
    "wof:name": "IP28 8PA",
    "wof:placetype": "postalcode"
  },
  "geometry": {"coordinates":[0.457228,52.354896],"type":"Point"}
}
