{
  "type": "Feature",
  "properties": {
    "iso:country": "GB",
    "wof:name": "TS13 4GB",
    "wof:placetype": "postalcode"
  },
  "geometry": {"coordinates":[-0.879046,54.554261],"type":"Point"}
}
