{
  "type": "Feature",
  "properties": {
    "iso:country":"GB",
    "wof:name":"TS13 4GB",
    "wof:placetype":"postalcode"
},
  "geometry": {"coordinates":[-0.87904633449815,54.55426051810809],"type":"Point"}
}