{
  "type": "Feature",
  "properties": {
    "date:inception_lower":"2005-03-01",
    "date:inception_upper":"2005-03-31",
    "iso:country":"GB",
    "wof:name":"TS13 4GB",
    "wof:placetype":"postalcode"
},
  "geometry": {"coordinates":[-0.879046,54.554261],"type":"Point"}
}