{
  "type": "Feature",
  "properties": {
    "iso:country":"GB",
    "wof:name":"RG12 7GP",
    "wof:placetype":"postalcode"
},
  "geometry": {"coordinates":[-0.75803541969313,51.39752022760145],"type":"Point"}
}