{
  "type": "Feature",
  "properties": {
    "date:inception_lower": "2002-06-01",
    "date:inception_upper": "2002-06-01",
    "iso:country": "GB",
    "wof:name": "RG12 7GP",
    "wof:placetype": "postalcode"
  },
  "geometry": {"coordinates":[-0.758035,51.39752],"type":"Point"}
}
