{
  "type": "Feature",
  "properties": {
    "iso:country":"GB",
    "wof:name":"KT8 0DU",
    "wof:placetype":"postalcode"
},
  "geometry": {"coordinates":[-0.35839226195462,51.40087675778527],"type":"Point"}
}