{
  "type": "Feature",
  "properties": {
    "iso:country": "GB",
    "wof:name": "KT8 0DU",
    "wof:placetype": "postalcode"
  },
  "geometry": {"coordinates":[-0.358392,51.400877],"type":"Point"}
}
