{
  "type": "Feature",
  "properties": {
    "date:inception_lower": "1980-01-01",
    "date:inception_upper": "1980-01-01",
    "iso:country": "GB",
    "wof:name": "HR4 0RP",
    "wof:placetype": "postalcode"
  },
  "geometry": {"coordinates":[-2.743303,52.063687],"type":"Point"}
}
