{
  "type": "Feature",
  "properties": {
    "iso:country":"GB",
    "wof:name":"HR4 0RP",
    "wof:placetype":"postalcode"
},
  "geometry": {"coordinates":[-2.74330291523909,52.06368654239033],"type":"Point"}
}