{
  "type": "Feature",
  "properties": {
    "date:inception_lower": "1980-01-01",
    "date:inception_upper": "1980-01-01",
    "iso:country": "GB",
    "wof:name": "GU11 3DD",
    "wof:placetype": "postalcode"
  },
  "geometry": {"coordinates":[-0.764073,51.241048],"type":"Point"}
}
