{
  "type": "Feature",
  "properties": {
    "date:inception_lower": "2009-08-01",
    "date:inception_upper": "2009-08-01",
    "iso:country": "GB",
    "wof:name": "DE11 9TU",
    "wof:placetype": "postalcode"
  },
  "geometry": {"coordinates":[-1.580055,52.762514],"type":"Point"}
}
