{
  "type": "Feature",
  "properties": {
    "iso:country":"GB",
    "wof:name":"DE11 9TU",
    "wof:placetype":"postalcode"
},
  "geometry": {"coordinates":[-1.58005458053483,52.76251366051976],"type":"Point"}
}