{
  "type": "Feature",
  "properties": {
    "iso:country": "GB",
    "wof:name": "DE11 9TU",
    "wof:placetype": "postalcode"
  },
  "geometry": {"coordinates":[-1.580055,52.762514],"type":"Point"}
}
