{
  "type": "Feature",
  "properties": {
    "iso:country":"GB",
    "wof:name":"HU7 0AN",
    "wof:placetype":"postalcode"
},
  "geometry": {"coordinates":[-0.32805931556757,53.77278646495016],"type":"Point"}
}