{
  "type": "Feature",
  "properties": {
    "iso:country": "GB",
    "wof:name": "HU7 0AN",
    "wof:placetype": "postalcode"
  },
  "geometry": {"coordinates":[-0.328059,53.772786],"type":"Point"}
}
