{
  "type": "Feature",
  "properties": {
    "iso:country": "GB",
    "wof:name": "CT1 1DP",
    "wof:placetype": "postalcode"
  },
  "geometry": {"coordinates":[1.098886,51.289627],"type":"Point"}
}
