{
  "type": "Feature",
  "properties": {
    "date:inception_lower": "1980-01-01",
    "date:inception_upper": "1980-01-01",
    "iso:country": "GB",
    "wof:name": "S9 3SP",
    "wof:placetype": "postalcode"
  },
  "geometry": {"coordinates":[-1.430668,53.392517],"type":"Point"}
}
