{
  "type": "Feature",
  "properties": {
    "iso:country":"GB",
    "wof:name":"TQ5 0JA",
    "wof:placetype":"postalcode"
},
  "geometry": {"coordinates":[-3.54527258054531,50.39443514089918],"type":"Point"}
}