{
  "type": "Feature",
  "properties": {
    "iso:country":"GB",
    "wof:name":"AB42 1WU",
    "wof:placetype":"postalcode"
},
  "geometry": {"coordinates":[-1.80766355410909,57.50741490862382],"type":"Point"}
}