{
  "type": "Feature",
  "properties": {
    "date:inception_lower": "1996-06-01",
    "date:inception_upper": "1996-06-01",
    "iso:country": "GB",
    "wof:name": "AB42 1WU",
    "wof:placetype": "postalcode"
  },
  "geometry": {"coordinates":[-1.807618,57.507284],"type":"Point"}
}
