{
  "type": "Feature",
  "properties": {
    "date:inception_lower": "1980-01-01",
    "date:inception_upper": "1980-01-01",
    "iso:country": "GB",
    "wof:name": "CF48 4QD",
    "wof:placetype": "postalcode"
  },
  "geometry": {"coordinates":[-3.343834,51.702742],"type":"Point"}
}
