{
  "type": "Feature",
  "properties": {
    "iso:country": "GB",
    "wof:name": "CF48 4QD",
    "wof:placetype": "postalcode"
  },
  "geometry": {"coordinates":[-3.343822,51.702737],"type":"Point"}
}
