{
  "type": "Feature",
  "properties": {
    "iso:country": "GB",
    "wof:name": "BD14 6AG",
    "wof:placetype": "postalcode"
  },
  "geometry": {"coordinates":[-1.818375,53.783594],"type":"Point"}
}
