{
  "type": "Feature",
  "properties": {
    "date:inception_lower": "1980-01-01",
    "date:inception_upper": "1980-01-01",
    "iso:country": "GB",
    "wof:name": "BD14 6AG",
    "wof:placetype": "postalcode"
  },
  "geometry": {"coordinates":[-1.818375,53.783594],"type":"Point"}
}
