{
  "type": "Feature",
  "properties": {
    "iso:country":"GB",
    "wof:name":"BD14 6AG",
    "wof:placetype":"postalcode"
},
  "geometry": {"coordinates":[-1.81837509014848,53.78359356425307],"type":"Point"}
}