{
  "type": "Feature",
  "properties": {
    "iso:country":"GB",
    "wof:name":"M30 9HA",
    "wof:placetype":"postalcode"
},
  "geometry": {"coordinates":[-2.34209639818985,53.48746570591436],"type":"Point"}
}