{
  "type": "Feature",
  "properties": {
    "date:inception_lower": "1980-01-01",
    "date:inception_upper": "1980-01-01",
    "iso:country": "GB",
    "wof:name": "M30 9HA",
    "wof:placetype": "postalcode"
  },
  "geometry": {"coordinates":[-2.342096,53.487466],"type":"Point"}
}
