{
  "type": "Feature",
  "properties": {
    "iso:country":"GB",
    "wof:name":"HX2 0QR",
    "wof:placetype":"postalcode"
},
  "geometry": {"coordinates":[-1.90470942033715,53.73219170952993],"type":"Point"}
}