{
  "type": "Feature",
  "properties": {
    "iso:country": "GB",
    "wof:name": "B69 1TN",
    "wof:placetype": "postalcode"
  },
  "geometry": {"coordinates":[-2.054883,52.508654],"type":"Point"}
}
