{
  "type": "Feature",
  "properties": {
    "iso:country":"GB",
    "wof:name":"B69 1TN",
    "wof:placetype":"postalcode"
},
  "geometry": {"coordinates":[-2.0548834897257,52.50865426728544],"type":"Point"}
}