{
  "type": "Feature",
  "properties": {
    "iso:country":"GB",
    "wof:name":"IP17 3QW",
    "wof:placetype":"postalcode"
},
  "geometry": {"coordinates":[1.53214153929394,52.29204936845971],"type":"Point"}
}