{
  "type": "Feature",
  "properties": {
    "iso:country": "GB",
    "wof:name": "IP17 3QW",
    "wof:placetype": "postalcode"
  },
  "geometry": {"coordinates":[1.532216,52.292061],"type":"Point"}
}
