{
  "type": "Feature",
  "properties": {
    "date:inception_lower": "1980-01-01",
    "date:inception_upper": "1980-01-01",
    "iso:country": "GB",
    "wof:name": "DA12 4HF",
    "wof:placetype": "postalcode"
  },
  "geometry": {"coordinates":[0.39705,51.427059],"type":"Point"}
}
