{
  "type": "Feature",
  "properties": {
    "iso:country":"GB",
    "wof:name":"DG11 1TH",
    "wof:placetype":"postalcode"
},
  "geometry": {"coordinates":[-3.45673136947816,55.17805660745234],"type":"Point"}
}