{
  "type": "Feature",
  "properties": {
    "iso:country":"GB",
    "wof:name":"BR4 0JE",
    "wof:placetype":"postalcode"
},
  "geometry": {"coordinates":[-0.00452094104112,51.38548387203893],"type":"Point"}
}