{
  "type": "Feature",
  "properties": {
    "iso:country":"GB",
    "wof:name":"ME3 9QH",
    "wof:placetype":"postalcode"
},
  "geometry": {"coordinates":[0.65042662095922,51.47559009315034],"type":"Point"}
}