{
  "type": "Feature",
  "properties": {
    "iso:country": "GB",
    "wof:name": "DT3 4HS",
    "wof:placetype": "postalcode"
  },
  "geometry": {"coordinates":[-2.546355,50.641544],"type":"Point"}
}
