{
  "type": "Feature",
  "properties": {
    "iso:country": "GB",
    "wof:name": "AB31 4HY",
    "wof:placetype": "postalcode"
  },
  "geometry": {"coordinates":[-2.628451,57.102451],"type":"Point"}
}
