{
  "type": "Feature",
  "properties": {
    "iso:country":"GB",
    "wof:name":"CF14 3QD",
    "wof:placetype":"postalcode"
},
  "geometry": {"coordinates":[-3.18792882644908,51.50213903078053],"type":"Point"}
}