{
  "type": "Feature",
  "properties": {
    "iso:country":"GB",
    "wof:name":"ST3 4AE",
    "wof:placetype":"postalcode"
},
  "geometry": {"coordinates":[-2.13044058374838,52.96513034054845],"type":"Point"}
}