{
  "type": "Feature",
  "properties": {
    "iso:country": "GB",
    "wof:name": "HU4 6XY",
    "wof:placetype": "postalcode"
  },
  "geometry": {"coordinates":[-0.411008,53.736907],"type":"Point"}
}
