{
  "type": "Feature",
  "properties": {
    "iso:country":"GB",
    "wof:name":"HU4 6XY",
    "wof:placetype":"postalcode"
},
  "geometry": {"coordinates":[-0.41100760879617,53.73690660308279],"type":"Point"}
}