{
  "type": "Feature",
  "properties": {
    "date:inception_lower":"1993-08-01",
    "date:inception_upper":"1993-08-31",
    "iso:country":"GB",
    "wof:name":"LL30 1SR",
    "wof:placetype":"postalcode"
},
  "geometry": {"coordinates":[-3.818074,53.303053],"type":"Point"}
}