{
  "type": "Feature",
  "properties": {
    "iso:country": "GB",
    "wof:name": "LL30 1SR",
    "wof:placetype": "postalcode"
  },
  "geometry": {"coordinates":[-3.818074,53.303053],"type":"Point"}
}
