{
  "type": "Feature",
  "properties": {
    "iso:country":"GB",
    "wof:name":"M23 2TJ",
    "wof:placetype":"postalcode"
},
  "geometry": {"coordinates":[-2.28772838931715,53.38166117944063],"type":"Point"}
}