{
  "type": "Feature",
  "properties": {
    "iso:country":"GB",
    "wof:name":"WV11 2EJ",
    "wof:placetype":"postalcode"
},
  "geometry": {"coordinates":[-2.06340362851212,52.61336359319602],"type":"Point"}
}