{
  "type": "Feature",
  "properties": {
    "iso:country":"GB",
    "wof:name":"LL14 3EY",
    "wof:placetype":"postalcode"
},
  "geometry": {"coordinates":[-3.05862282742448,52.98375104229717],"type":"Point"}
}