{
  "type": "Feature",
  "properties": {
    "iso:country": "GB",
    "wof:name": "GL4 0UU",
    "wof:placetype": "postalcode"
  },
  "geometry": {"coordinates":[-2.234042,51.806423],"type":"Point"}
}
