{
  "type": "Feature",
  "properties": {
    "iso:country": "GB",
    "wof:name": "TW11 9FL",
    "wof:placetype": "postalcode"
  },
  "geometry": {"coordinates":[-0.321278,51.428389],"type":"Point"}
}
