{
  "type": "Feature",
  "properties": {
    "iso:country":"GB",
    "wof:name":"ME2 3EZ",
    "wof:placetype":"postalcode"
},
  "geometry": {"coordinates":[0.48816006860939,51.39745054978923],"type":"Point"}
}