{
  "type": "Feature",
  "properties": {
    "iso:country": "GB",
    "wof:name": "GU47 8JQ",
    "wof:placetype": "postalcode"
  },
  "geometry": {"coordinates":[-0.813894,51.345774],"type":"Point"}
}
