{
  "type": "Feature",
  "properties": {
    "iso:country": "GB",
    "wof:name": "GU47 8JQ",
    "wof:placetype": "postalcode"
  },
  "geometry": {"coordinates":[-0.812779,51.346141],"type":"Point"}
}
