{
  "type": "Feature",
  "properties": {
    "iso:country":"GB",
    "wof:name":"LL15 1DP",
    "wof:placetype":"postalcode"
},
  "geometry": {"coordinates":[-3.31082474600516,53.11362010023873],"type":"Point"}
}