{
  "type": "Feature",
  "properties": {
    "date:inception_lower": "2006-01-01",
    "date:inception_upper": "2006-01-01",
    "iso:country": "GB",
    "wof:name": "HR9 5HU",
    "wof:placetype": "postalcode"
  },
  "geometry": {"coordinates":[-2.590659,51.901727],"type":"Point"}
}
