{
  "type": "Feature",
  "properties": {
    "iso:country":"GB",
    "wof:name":"HR9 5HU",
    "wof:placetype":"postalcode"
},
  "geometry": {"coordinates":[-2.59065861380632,51.90172668993133],"type":"Point"}
}