{
  "type": "Feature",
  "properties": {
    "date:inception_lower": "2018-03-01",
    "date:inception_upper": "2018-03-01",
    "iso:country": "GB",
    "wof:name": "ML6 8GW",
    "wof:placetype": "postalcode"
  },
  "geometry": {"coordinates":[-3.945923,55.84003],"type":"Point"}
}
