{
  "type": "Feature",
  "properties": {
    "iso:country": "GB",
    "wof:name": "ML6 8GW",
    "wof:placetype": "postalcode"
  },
  "geometry": {"coordinates":[-3.945923,55.84003],"type":"Point"}
}
