{
  "type": "Feature",
  "properties": {
    "iso:country":"GB",
    "wof:name":"S5 6DF",
    "wof:placetype":"postalcode"
},
  "geometry": {"coordinates":[-1.43452044993625,53.41613993976085],"type":"Point"}
}