{
  "type": "Feature",
  "properties": {
    "date:inception_lower":"2006-10-01",
    "date:inception_upper":"2006-10-31",
    "iso:country":"GB",
    "wof:name":"WA14 5WE",
    "wof:placetype":"postalcode"
},
  "geometry": {"coordinates":[-2.357144,53.407576],"type":"Point"}
}