{
  "type": "Feature",
  "properties": {
    "iso:country":"GB",
    "wof:name":"ML4 2RS",
    "wof:placetype":"postalcode"
},
  "geometry": {"coordinates":[-3.9889646653063,55.81668036820902],"type":"Point"}
}