{
  "type": "Feature",
  "properties": {
    "date:inception_lower": "2021-07-01",
    "date:inception_upper": "2021-07-01",
    "iso:country": "GB",
    "wof:name": "DE55 3BY",
    "wof:placetype": "postalcode"
  },
  "geometry": {"coordinates":[-1.354744,53.098401],"type":"Point"}
}
