{
  "type": "Feature",
  "properties": {
    "iso:country": "GB",
    "wof:name": "GU21 3QA",
    "wof:placetype": "postalcode"
  },
  "geometry": {"coordinates":[-0.597054,51.317534],"type":"Point"}
}
