{
  "type": "Feature",
  "properties": {
    "iso:country": "GB",
    "wof:name": "SN4 0PF",
    "wof:placetype": "postalcode"
  },
  "geometry": {"coordinates":[-1.728188,51.515549],"type":"Point"}
}
