{
  "type": "Feature",
  "properties": {
    "iso:country":"GB",
    "wof:name":"TW10 6NF",
    "wof:placetype":"postalcode"
},
  "geometry": {"coordinates":[-0.2982775730912,51.45334451551727],"type":"Point"}
}