{
  "type": "Feature",
  "properties": {
    "date:inception_lower":"1980-01-01",
    "date:inception_upper":"1980-01-31",
    "iso:country":"GB",
    "wof:name":"DN6 9DH",
    "wof:placetype":"postalcode"
},
  "geometry": {"coordinates":[-1.181117,53.631442],"type":"Point"}
}