{
  "type": "Feature",
  "properties": {
    "iso:country":"GB",
    "wof:name":"DN6 9DH",
    "wof:placetype":"postalcode"
},
  "geometry": {"coordinates":[-1.18111661303651,53.63144183344849],"type":"Point"}
}