{
  "type": "Feature",
  "properties": {
    "iso:country": "GB",
    "wof:name": "LS13 3NS",
    "wof:placetype": "postalcode"
  },
  "geometry": {"coordinates":[-1.632997,53.810925],"type":"Point"}
}
