{
  "type": "Feature",
  "properties": {
    "iso:country":"GB",
    "wof:name":"LS12 3AZ",
    "wof:placetype":"postalcode"
},
  "geometry": {"coordinates":[-1.58978032726249,53.79803097221369],"type":"Point"}
}