{
  "type": "Feature",
  "properties": {
    "iso:country":"GB",
    "wof:name":"DN4 9DJ",
    "wof:placetype":"postalcode"
},
  "geometry": {"coordinates":[-1.15967590240523,53.49719248632681],"type":"Point"}
}