{
  "type": "Feature",
  "properties": {
    "iso:country":"GB",
    "wof:name":"TS10 1QL",
    "wof:placetype":"postalcode"
},
  "geometry": {"coordinates":[-1.07792185817002,54.61653958401693],"type":"Point"}
}