{
  "type": "Feature",
  "properties": {
    "iso:country":"GB",
    "wof:name":"BA2 8LJ",
    "wof:placetype":"postalcode"
},
  "geometry": {"coordinates":[-2.42329222860935,51.31176994700385],"type":"Point"}
}