{
  "type": "Feature",
  "properties": {
    "iso:country":"GB",
    "wof:name":"EX8 1XZ",
    "wof:placetype":"postalcode"
},
  "geometry": {"coordinates":[-3.42471381375735,50.6188882939709],"type":"Point"}
}