{
  "type": "Feature",
  "properties": {
    "iso:country": "GB",
    "wof:name": "EX8 1XZ",
    "wof:placetype": "postalcode"
  },
  "geometry": {"coordinates":[-3.424714,50.618888],"type":"Point"}
}
