{
  "type": "Feature",
  "properties": {
    "iso:country":"GB",
    "wof:name":"MK42 9UG",
    "wof:placetype":"postalcode"
},
  "geometry": {"coordinates":[-0.46429303009462,52.11824958193733],"type":"Point"}
}