{
  "type": "Feature",
  "properties": {
    "iso:country":"GB",
    "wof:name":"CA13 9JX",
    "wof:placetype":"postalcode"
},
  "geometry": {"coordinates":[-3.36523497808829,54.66320900836552],"type":"Point"}
}