{
  "type": "Feature",
  "properties": {
    "iso:country": "GB",
    "wof:name": "CA13 9JX",
    "wof:placetype": "postalcode"
  },
  "geometry": {"coordinates":[-3.365235,54.663209],"type":"Point"}
}
