{
  "type": "Feature",
  "properties": {
    "date:inception_lower": "1999-12-01",
    "date:inception_upper": "1999-12-01",
    "iso:country": "GB",
    "wof:name": "CA13 9JX",
    "wof:placetype": "postalcode"
  },
  "geometry": {"coordinates":[-3.365235,54.663209],"type":"Point"}
}
