{
  "type": "Feature",
  "properties": {
    "iso:country": "GB",
    "wof:name": "OX29 9TJ",
    "wof:placetype": "postalcode"
  },
  "geometry": {"coordinates":[-1.510503,51.803173],"type":"Point"}
}
