{
  "type": "Feature",
  "properties": {
    "iso:country":"GB",
    "wof:name":"OX29 9TJ",
    "wof:placetype":"postalcode"
},
  "geometry": {"coordinates":[-1.51051849042296,51.80316654640751],"type":"Point"}
}