{
  "type": "Feature",
  "properties": {
    "date:inception_lower": "1980-01-01",
    "date:inception_upper": "1980-01-01",
    "iso:country": "GB",
    "wof:name": "TN34 2JR",
    "wof:placetype": "postalcode"
  },
  "geometry": {"coordinates":[0.580264,50.875616],"type":"Point"}
}
