{
  "type": "Feature",
  "properties": {
    "iso:country":"GB",
    "wof:name":"TN34 2JR",
    "wof:placetype":"postalcode"
},
  "geometry": {"coordinates":[0.58026407129994,50.87561604533852],"type":"Point"}
}