{
  "type": "Feature",
  "properties": {
    "iso:country":"GB",
    "wof:name":"EH3 6RA",
    "wof:placetype":"postalcode"
},
  "geometry": {"coordinates":[-3.20098151040792,55.95826999268716],"type":"Point"}
}