{
  "type": "Feature",
  "properties": {
    "iso:country": "GB",
    "wof:name": "DL10 6AS",
    "wof:placetype": "postalcode"
  },
  "geometry": {"coordinates":[-1.58154,54.374739],"type":"Point"}
}
