{
  "type": "Feature",
  "properties": {
    "date:inception_lower": "1996-12-01",
    "date:inception_upper": "1996-12-01",
    "iso:country": "GB",
    "wof:name": "DL10 6AS",
    "wof:placetype": "postalcode"
  },
  "geometry": {"coordinates":[-1.58154,54.374739],"type":"Point"}
}
