{
  "type": "Feature",
  "properties": {
    "iso:country":"GB",
    "wof:name":"EN6 5ED",
    "wof:placetype":"postalcode"
},
  "geometry": {"coordinates":[-0.173755750694,51.69011091607544],"type":"Point"}
}