{
  "type": "Feature",
  "properties": {
    "date:inception_lower": "1980-01-01",
    "date:inception_upper": "1980-01-01",
    "iso:country": "GB",
    "wof:name": "EN6 5ED",
    "wof:placetype": "postalcode"
  },
  "geometry": {"coordinates":[-0.173756,51.690111],"type":"Point"}
}
