{
  "type": "Feature",
  "properties": {
    "iso:country":"GB",
    "wof:name":"CF10 2HL",
    "wof:placetype":"postalcode"
},
  "geometry": {"coordinates":[-3.17108019472345,51.48053912620402],"type":"Point"}
}