{
  "type": "Feature",
  "properties": {
    "date:inception_lower": "2020-11-01",
    "date:inception_upper": "2020-11-01",
    "iso:country": "GB",
    "wof:name": "PA2 7GH",
    "wof:placetype": "postalcode"
  },
  "geometry": {"coordinates":[-4.400058,55.839203],"type":"Point"}
}
