{
  "type": "Feature",
  "properties": {
    "iso:country":"GB",
    "wof:name":"SG1 5JG",
    "wof:placetype":"postalcode"
},
  "geometry": {"coordinates":[-0.18833797598663,51.91771866534856],"type":"Point"}
}