{
  "type": "Feature",
  "properties": {
    "iso:country":"GB",
    "wof:name":"CT10 3PR",
    "wof:placetype":"postalcode"
},
  "geometry": {"coordinates":[1.43957358885887,51.38107751062358],"type":"Point"}
}