{
  "type": "Feature",
  "properties": {
    "date:inception_lower": "1980-01-01",
    "date:inception_upper": "1980-01-01",
    "iso:country": "GB",
    "wof:name": "EH49 6HY",
    "wof:placetype": "postalcode"
  },
  "geometry": {"coordinates":[-3.603291,55.967225],"type":"Point"}
}
