{
  "type": "Feature",
  "properties": {
    "iso:country":"GB",
    "wof:name":"AL4 8GD",
    "wof:placetype":"postalcode"
},
  "geometry": {"coordinates":[-0.28986101306462,51.81593029273174],"type":"Point"}
}