{
  "type": "Feature",
  "properties": {
    "date:inception_lower": "2000-06-01",
    "date:inception_upper": "2000-06-01",
    "iso:country": "GB",
    "wof:name": "AL4 8GD",
    "wof:placetype": "postalcode"
  },
  "geometry": {"coordinates":[-0.289861,51.81593],"type":"Point"}
}
