{
  "type": "Feature",
  "properties": {
    "iso:country": "GB",
    "wof:name": "PO16 8HW",
    "wof:placetype": "postalcode"
  },
  "geometry": {"coordinates":[-1.119842,50.851449],"type":"Point"}
}
