{
  "type": "Feature",
  "properties": {
    "iso:country": "GB",
    "wof:name": "G62 7PU",
    "wof:placetype": "postalcode"
  },
  "geometry": {"coordinates":[-4.331312,55.939718],"type":"Point"}
}
