{
  "type": "Feature",
  "properties": {
    "iso:country":"GB",
    "wof:name":"W1W 7RA",
    "wof:placetype":"postalcode"
},
  "geometry": {"coordinates":[-0.14270071548379,51.51757278755789],"type":"Point"}
}