{
  "type": "Feature",
  "properties": {
    "iso:country": "GB",
    "wof:name": "EH11 4FS",
    "wof:placetype": "postalcode"
  },
  "geometry": {"coordinates":[-3.284544,55.9244],"type":"Point"}
}
