{
  "type": "Feature",
  "properties": {
    "date:inception_lower": "2018-07-01",
    "date:inception_upper": "2018-07-01",
    "iso:country": "GB",
    "wof:name": "EH11 4FS",
    "wof:placetype": "postalcode"
  },
  "geometry": {"coordinates":[-3.286949,55.924537],"type":"Point"}
}
