{
  "type": "Feature",
  "properties": {
    "iso:country":"GB",
    "wof:name":"W1B 1NX",
    "wof:placetype":"postalcode"
},
  "geometry": {"coordinates":[-0.14561562897714,51.52245686851948],"type":"Point"}
}