{
  "type": "Feature",
  "properties": {
    "iso:country":"GB",
    "wof:name":"HA0 4UB",
    "wof:placetype":"postalcode"
},
  "geometry": {"coordinates":[-0.30172929708737,51.55147407521623],"type":"Point"}
}