{
  "type": "Feature",
  "properties": {
    "iso:country": "GB",
    "wof:name": "HA0 4UB",
    "wof:placetype": "postalcode"
  },
  "geometry": {"coordinates":[-0.301729,51.551474],"type":"Point"}
}
