{
  "type": "Feature",
  "properties": {
    "date:inception_lower": "2020-01-01",
    "date:inception_upper": "2020-01-01",
    "iso:country": "GB",
    "wof:name": "NG18 6BF",
    "wof:placetype": "postalcode"
  },
  "geometry": {"coordinates":[-1.176166,53.11969],"type":"Point"}
}
