{
  "type": "Feature",
  "properties": {
    "iso:country":"GB",
    "wof:name":"TS19 8GP",
    "wof:placetype":"postalcode"
},
  "geometry": {"coordinates":[-1.35606439538572,54.58844707251655],"type":"Point"}
}