{
  "type": "Feature",
  "properties": {
    "date:inception_lower": "1980-01-01",
    "date:inception_upper": "1980-01-01",
    "iso:country": "GB",
    "wof:name": "ME16 8UE",
    "wof:placetype": "postalcode"
  },
  "geometry": {"coordinates":[0.493718,51.265351],"type":"Point"}
}
