{
  "type": "Feature",
  "properties": {
    "iso:country":"GB",
    "wof:name":"CW7 4AF",
    "wof:placetype":"postalcode"
},
  "geometry": {"coordinates":[-2.52116950123165,53.19089080087308],"type":"Point"}
}