{
  "type": "Feature",
  "properties": {
    "iso:country": "GB",
    "wof:name": "AB35 5XG",
    "wof:placetype": "postalcode"
  },
  "geometry": {"coordinates":[-3.397241,57.003788],"type":"Point"}
}
