{
  "type": "Feature",
  "properties": {
    "date:inception_lower": "2013-07-01",
    "date:inception_upper": "2013-07-01",
    "iso:country": "GB",
    "wof:name": "AB35 5XG",
    "wof:placetype": "postalcode"
  },
  "geometry": {"coordinates":[-3.397241,57.003788],"type":"Point"}
}
