{
  "type": "Feature",
  "properties": {
    "iso:country":"GB",
    "wof:name":"AB35 5XG",
    "wof:placetype":"postalcode"
},
  "geometry": {"coordinates":[-3.39669431263623,57.0036981235039],"type":"Point"}
}