{
  "type": "Feature",
  "properties": {
    "date:inception_lower":"1980-01-01",
    "date:inception_upper":"1980-01-31",
    "iso:country":"GB",
    "wof:name":"SG11 1NR",
    "wof:placetype":"postalcode"
},
  "geometry": {"coordinates":[0.046339,51.879206],"type":"Point"}
}