{
  "type": "Feature",
  "properties": {
    "iso:country": "GB",
    "wof:name": "SG11 1NR",
    "wof:placetype": "postalcode"
  },
  "geometry": {"coordinates":[0.046339,51.879206],"type":"Point"}
}
