{
  "type": "Feature",
  "properties": {
    "iso:country": "GB",
    "wof:name": "WR5 1HG",
    "wof:placetype": "postalcode"
  },
  "geometry": {"coordinates":[-2.202942,52.194889],"type":"Point"}
}
