{
  "type": "Feature",
  "properties": {
    "iso:country":"GB",
    "wof:name":"WR5 1HG",
    "wof:placetype":"postalcode"
},
  "geometry": {"coordinates":[-2.20294218077704,52.19488861040723],"type":"Point"}
}