{
  "type": "Feature",
  "properties": {
    "date:inception_lower":"1980-01-01",
    "date:inception_upper":"1980-01-31",
    "iso:country":"GB",
    "wof:name":"WR5 1HG",
    "wof:placetype":"postalcode"
},
  "geometry": {"coordinates":[-2.202942,52.194889],"type":"Point"}
}