{
  "type": "Feature",
  "properties": {
    "iso:country":"GB",
    "wof:name":"LE2 5AQ",
    "wof:placetype":"postalcode"
},
  "geometry": {"coordinates":[-1.07611962507421,52.59624998039523],"type":"Point"}
}