{
  "type": "Feature",
  "properties": {
    "date:inception_lower": "2008-08-01",
    "date:inception_upper": "2008-08-01",
    "iso:country": "GB",
    "wof:name": "LE2 5AQ",
    "wof:placetype": "postalcode"
  },
  "geometry": {"coordinates":[-1.07612,52.59625],"type":"Point"}
}
