{
  "type": "Feature",
  "properties": {
    "iso:country":"GB",
    "wof:name":"SG1 4LR",
    "wof:placetype":"postalcode"
},
  "geometry": {"coordinates":[-0.18657057624314,51.92657543072859],"type":"Point"}
}