{
  "type": "Feature",
  "properties": {
    "iso:country":"GB",
    "wof:name":"BN16 1BL",
    "wof:placetype":"postalcode"
},
  "geometry": {"coordinates":[-0.47980572728876,50.81632315536114],"type":"Point"}
}