{
  "type": "Feature",
  "properties": {
    "iso:country":"GB",
    "wof:name":"E3 2FU",
    "wof:placetype":"postalcode"
},
  "geometry": {"coordinates":[-0.02934378271643,51.53013814854315],"type":"Point"}
}