{
  "type": "Feature",
  "properties": {
    "date:inception_lower": "2015-03-01",
    "date:inception_upper": "2015-03-01",
    "iso:country": "GB",
    "wof:name": "E3 2FU",
    "wof:placetype": "postalcode"
  },
  "geometry": {"coordinates":[-0.029344,51.530138],"type":"Point"}
}
