{
  "type": "Feature",
  "properties": {
    "iso:country":"GB",
    "wof:name":"NG15 8BQ",
    "wof:placetype":"postalcode"
},
  "geometry": {"coordinates":[-1.19388309181964,53.04812170773386],"type":"Point"}
}