{
  "type": "Feature",
  "properties": {
    "iso:country": "GB",
    "wof:name": "NG15 8BQ",
    "wof:placetype": "postalcode"
  },
  "geometry": {"coordinates":[-1.193883,53.048122],"type":"Point"}
}
