{
  "type": "Feature",
  "properties": {
    "iso:country":"GB",
    "wof:name":"HP18 9PE",
    "wof:placetype":"postalcode"
},
  "geometry": {"coordinates":[-1.04361880048529,51.85225760646098],"type":"Point"}
}