{
  "type": "Feature",
  "properties": {
    "iso:country":"GB",
    "wof:name":"CM7 4DG",
    "wof:placetype":"postalcode"
},
  "geometry": {"coordinates":[0.53110493013619,51.94861513879279],"type":"Point"}
}