{
  "type": "Feature",
  "properties": {
    "iso:country": "GB",
    "wof:name": "HU10 7NB",
    "wof:placetype": "postalcode"
  },
  "geometry": {"coordinates":[-0.455667,53.746587],"type":"Point"}
}
