{
  "type": "Feature",
  "properties": {
    "iso:country":"GB",
    "wof:name":"S40 2QW",
    "wof:placetype":"postalcode"
},
  "geometry": {"coordinates":[-1.42975763306359,53.21847136840142],"type":"Point"}
}