{
  "type": "Feature",
  "properties": {
    "iso:country": "GB",
    "wof:name": "WR2 5ED",
    "wof:placetype": "postalcode"
  },
  "geometry": {"coordinates":[-2.246667,52.186291],"type":"Point"}
}
