{
  "type": "Feature",
  "properties": {
    "iso:country":"GB",
    "wof:name":"CV10 7HS",
    "wof:placetype":"postalcode"
},
  "geometry": {"coordinates":[-1.48645647249018,52.5124625895085],"type":"Point"}
}