{
  "type": "Feature",
  "properties": {
    "iso:country": "GB",
    "wof:name": "W5 5BW",
    "wof:placetype": "postalcode"
  },
  "geometry": {"coordinates":[-0.311585,51.511773],"type":"Point"}
}
