{
  "type": "Feature",
  "properties": {
    "date:inception_lower": "1980-01-01",
    "date:inception_upper": "1980-01-01",
    "iso:country": "GB",
    "wof:name": "WD6 5EE",
    "wof:placetype": "postalcode"
  },
  "geometry": {"coordinates":[-0.28058,51.666644],"type":"Point"}
}
