{
  "type": "Feature",
  "properties": {
    "iso:country":"GB",
    "wof:name":"BS41 9NB",
    "wof:placetype":"postalcode"
},
  "geometry": {"coordinates":[-2.65467939907206,51.43018750995915],"type":"Point"}
}