{
  "type": "Feature",
  "properties": {
    "date:inception_lower":"1997-12-01",
    "date:inception_upper":"1997-12-31",
    "iso:country":"GB",
    "wof:name":"BS41 9NB",
    "wof:placetype":"postalcode"
},
  "geometry": {"coordinates":[-2.654679,51.430188],"type":"Point"}
}