{
  "type": "Feature",
  "properties": {
    "iso:country":"GB",
    "wof:name":"DE7 5DE",
    "wof:placetype":"postalcode"
},
  "geometry": {"coordinates":[-1.30460683228177,52.97067591260755],"type":"Point"}
}