{
  "type": "Feature",
  "properties": {
    "date:inception_lower":"1980-01-01",
    "date:inception_upper":"1980-01-31",
    "iso:country":"GB",
    "wof:name":"DE7 5DE",
    "wof:placetype":"postalcode"
},
  "geometry": {"coordinates":[-1.304607,52.970676],"type":"Point"}
}