{
  "type": "Feature",
  "properties": {
    "date:inception_lower": "1990-02-01",
    "date:inception_upper": "1990-02-01",
    "iso:country": "GB",
    "wof:name": "SE22 8QT",
    "wof:placetype": "postalcode"
  },
  "geometry": {"coordinates":[-0.077912,51.455577],"type":"Point"}
}
