{
  "type": "Feature",
  "properties": {
    "iso:country":"GB",
    "wof:name":"SE22 8QT",
    "wof:placetype":"postalcode"
},
  "geometry": {"coordinates":[-0.07808451931797,51.45558882655786],"type":"Point"}
}