{
  "type": "Feature",
  "properties": {
    "iso:country":"GB",
    "wof:name":"TD14 5TX",
    "wof:placetype":"postalcode"
},
  "geometry": {"coordinates":[-2.23646637709728,55.89720214119384],"type":"Point"}
}