{
  "type": "Feature",
  "properties": {
    "date:inception_lower": "1996-06-01",
    "date:inception_upper": "1996-06-01",
    "iso:country": "GB",
    "wof:name": "GL20 8TW",
    "wof:placetype": "postalcode"
  },
  "geometry": {"coordinates":[-2.110872,52.004717],"type":"Point"}
}
