{
  "type": "Feature",
  "properties": {
    "iso:country":"GB",
    "wof:name":"TN12 0BD",
    "wof:placetype":"postalcode"
},
  "geometry": {"coordinates":[0.54986874588451,51.1575106529446],"type":"Point"}
}