{
  "type": "Feature",
  "properties": {
    "iso:country":"GB",
    "wof:name":"KT11 1HY",
    "wof:placetype":"postalcode"
},
  "geometry": {"coordinates":[-0.41623781657107,51.33229621151206],"type":"Point"}
}