{
  "type": "Feature",
  "properties": {
    "iso:country": "GB",
    "wof:name": "KT11 1HY",
    "wof:placetype": "postalcode"
  },
  "geometry": {"coordinates":[-0.41639,51.332207],"type":"Point"}
}
