{
  "type": "Feature",
  "properties": {
    "date:inception_lower": "2004-11-01",
    "date:inception_upper": "2004-11-01",
    "iso:country": "GB",
    "wof:name": "PO11 9FJ",
    "wof:placetype": "postalcode"
  },
  "geometry": {"coordinates":[-0.97735,50.787428],"type":"Point"}
}
