{
  "type": "Feature",
  "properties": {
    "iso:country":"GB",
    "wof:name":"PR1 4TE",
    "wof:placetype":"postalcode"
},
  "geometry": {"coordinates":[-2.65661819522139,53.76550113031972],"type":"Point"}
}