{
  "type": "Feature",
  "properties": {
    "iso:country":"GB",
    "wof:name":"CT6 6SW",
    "wof:placetype":"postalcode"
},
  "geometry": {"coordinates":[1.15532523448293,51.36664206856509],"type":"Point"}
}