{
  "type": "Feature",
  "properties": {
    "date:inception_lower":"1984-02-01",
    "date:inception_upper":"1984-02-29",
    "iso:country":"GB",
    "wof:name":"CT6 6SW",
    "wof:placetype":"postalcode"
},
  "geometry": {"coordinates":[1.155325,51.366642],"type":"Point"}
}