{
  "type": "Feature",
  "properties": {
    "iso:country": "GB",
    "wof:name": "L22 1RB",
    "wof:placetype": "postalcode"
  },
  "geometry": {"coordinates":[-3.024959,53.472278],"type":"Point"}
}
