{
  "type": "Feature",
  "properties": {
    "iso:country":"GB",
    "wof:name":"TA21 0AQ",
    "wof:placetype":"postalcode"
},
  "geometry": {"coordinates":[-3.2448132918796,50.9870895515846],"type":"Point"}
}