{
  "type": "Feature",
  "properties": {
    "date:inception_lower": "2014-01-01",
    "date:inception_upper": "2014-01-01",
    "iso:country": "GB",
    "wof:name": "PE37 8GQ",
    "wof:placetype": "postalcode"
  },
  "geometry": {"coordinates":[0.689329,52.63229],"type":"Point"}
}
