{
  "type": "Feature",
  "properties": {
    "iso:country":"GB",
    "wof:name":"CM6 2LA",
    "wof:placetype":"postalcode"
},
  "geometry": {"coordinates":[0.34419416201953,51.95369153269272],"type":"Point"}
}