{
  "type": "Feature",
  "properties": {
    "iso:country": "GB",
    "wof:name": "CM6 2LA",
    "wof:placetype": "postalcode"
  },
  "geometry": {"coordinates":[0.344194,51.953692],"type":"Point"}
}
