{
  "type": "Feature",
  "properties": {
    "iso:country": "GB",
    "wof:name": "FK10 3HX",
    "wof:placetype": "postalcode"
  },
  "geometry": {"coordinates":[-3.77172,56.136375],"type":"Point"}
}
