{
  "type": "Feature",
  "properties": {
    "iso:country":"GB",
    "wof:name":"LS17 8HL",
    "wof:placetype":"postalcode"
},
  "geometry": {"coordinates":[-1.48191889017778,53.85419338214861],"type":"Point"}
}