{
  "type": "Feature",
  "properties": {
    "iso:country":"GB",
    "wof:name":"SE6 3TF",
    "wof:placetype":"postalcode"
},
  "geometry": {"coordinates":[-0.02023458506542,51.43363705923455],"type":"Point"}
}