{
  "type": "Feature",
  "properties": {
    "date:inception_lower": "1980-01-01",
    "date:inception_upper": "1980-01-01",
    "iso:country": "GB",
    "wof:name": "SY13 2LN",
    "wof:placetype": "postalcode"
  },
  "geometry": {"coordinates":[-2.801788,52.912452],"type":"Point"}
}
