{
  "type": "Feature",
  "properties": {
    "iso:country":"GB",
    "wof:name":"SY13 2LN",
    "wof:placetype":"postalcode"
},
  "geometry": {"coordinates":[-2.80178826801231,52.91245186402177],"type":"Point"}
}