{
  "type": "Feature",
  "properties": {
    "iso:country":"GB",
    "wof:name":"GU14 0RL",
    "wof:placetype":"postalcode"
},
  "geometry": {"coordinates":[-0.78518228350807,51.28915261897401],"type":"Point"}
}