{
  "type": "Feature",
  "properties": {
    "iso:country": "GB",
    "wof:name": "SA48 7LW",
    "wof:placetype": "postalcode"
  },
  "geometry": {"coordinates":[-4.182077,52.111789],"type":"Point"}
}
