{
  "type": "Feature",
  "properties": {
    "iso:country":"GB",
    "wof:name":"SA48 7LW",
    "wof:placetype":"postalcode"
},
  "geometry": {"coordinates":[-4.18207672966536,52.11178871904895],"type":"Point"}
}