{
  "type": "Feature",
  "properties": {
    "iso:country": "GB",
    "wof:name": "BD17 6AT",
    "wof:placetype": "postalcode"
  },
  "geometry": {"coordinates":[-1.762259,53.84411],"type":"Point"}
}
