{
  "type": "Feature",
  "properties": {
    "iso:country":"GB",
    "wof:name":"CV21 3XP",
    "wof:placetype":"postalcode"
},
  "geometry": {"coordinates":[-1.2398780166859,52.37907005008438],"type":"Point"}
}