{
  "type": "Feature",
  "properties": {
    "iso:country": "GB",
    "wof:name": "CV21 3XP",
    "wof:placetype": "postalcode"
  },
  "geometry": {"coordinates":[-1.23985,52.379096],"type":"Point"}
}
