{
  "type": "Feature",
  "properties": {
    "iso:country": "GB",
    "wof:name": "SE21 9BS",
    "wof:placetype": "postalcode"
  },
  "geometry": {"coordinates":[-0.087137,51.436412],"type":"Point"}
}
