{
  "type": "Feature",
  "properties": {
    "iso:country":"GB",
    "wof:name":"NG19 6NL",
    "wof:placetype":"postalcode"
},
  "geometry": {"coordinates":[-1.223171536945,53.15313103650524],"type":"Point"}
}