{
  "type": "Feature",
  "properties": {
    "iso:country":"GB",
    "wof:name":"TS6 0AT",
    "wof:placetype":"postalcode"
},
  "geometry": {"coordinates":[-1.16940983365809,54.56786250677374],"type":"Point"}
}