{
  "type": "Feature",
  "properties": {
    "iso:country": "GB",
    "wof:name": "NR4 7DZ",
    "wof:placetype": "postalcode"
  },
  "geometry": {"coordinates":[1.249821,52.622057],"type":"Point"}
}
