{
  "type": "Feature",
  "properties": {
    "iso:country": "GB",
    "wof:name": "M20 1AL",
    "wof:placetype": "postalcode"
  },
  "geometry": {"coordinates":[-2.234604,53.436994],"type":"Point"}
}
