{
  "type": "Feature",
  "properties": {
    "iso:country":"GB",
    "wof:name":"M20 1AL",
    "wof:placetype":"postalcode"
},
  "geometry": {"coordinates":[-2.23440907690729,53.43703958265928],"type":"Point"}
}