{
  "type": "Feature",
  "properties": {
    "iso:country":"GB",
    "wof:name":"AB12 3NB",
    "wof:placetype":"postalcode"
},
  "geometry": {"coordinates":[-2.07836481298571,57.09934973040318],"type":"Point"}
}