{
  "type": "Feature",
  "properties": {
    "date:inception_lower":"2001-12-01",
    "date:inception_upper":"2001-12-31",
    "iso:country":"GB",
    "wof:name":"LN1 2WX",
    "wof:placetype":"postalcode"
},
  "geometry": {"coordinates":[-0.649851,53.26636],"type":"Point"}
}