{
  "type": "Feature",
  "properties": {
    "iso:country":"GB",
    "wof:name":"PE29 1NA",
    "wof:placetype":"postalcode"
},
  "geometry": {"coordinates":[-0.17505709629104,52.34224135875233],"type":"Point"}
}