{
  "type": "Feature",
  "properties": {
    "date:inception_lower": "2015-09-01",
    "date:inception_upper": "2015-09-01",
    "iso:country": "GB",
    "wof:name": "SW19 9HL",
    "wof:placetype": "postalcode"
  },
  "geometry": {"coordinates":[-0.213374,51.416938],"type":"Point"}
}
