{
  "type": "Feature",
  "properties": {
    "iso:country":"GB",
    "wof:name":"M5 3EZ",
    "wof:placetype":"postalcode"
},
  "geometry": {"coordinates":[-2.27686385964493,53.46798595736245],"type":"Point"}
}