{
  "type": "Feature",
  "properties": {
    "date:inception_lower":"1991-01-01",
    "date:inception_upper":"1991-01-31",
    "iso:country":"GB",
    "wof:name":"M5 3EZ",
    "wof:placetype":"postalcode"
},
  "geometry": {"coordinates":[-2.276864,53.467986],"type":"Point"}
}