{
  "type": "Feature",
  "properties": {
    "date:inception_lower": "1980-01-01",
    "date:inception_upper": "1980-01-01",
    "iso:country": "GB",
    "wof:name": "BA2 6XE",
    "wof:placetype": "postalcode"
  },
  "geometry": {"coordinates":[-2.319854,51.391151],"type":"Point"}
}
