{
  "type": "Feature",
  "properties": {
    "date:inception_lower": "1997-12-01",
    "date:inception_upper": "1997-12-01",
    "iso:country": "GB",
    "wof:name": "BS49 5BD",
    "wof:placetype": "postalcode"
  },
  "geometry": {"coordinates":[-2.806069,51.374232],"type":"Point"}
}
