{
  "type": "Feature",
  "properties": {
    "iso:country":"GB",
    "wof:name":"BS49 5BD",
    "wof:placetype":"postalcode"
},
  "geometry": {"coordinates":[-2.80606926588248,51.37423203757084],"type":"Point"}
}