{
  "type": "Feature",
  "properties": {
    "date:inception_lower": "2017-08-01",
    "date:inception_upper": "2017-08-01",
    "iso:country": "GB",
    "wof:name": "AB15 9EH",
    "wof:placetype": "postalcode"
  },
  "geometry": {"coordinates":[-2.182156,57.122951],"type":"Point"}
}
