{
  "type": "Feature",
  "properties": {
    "iso:country":"GB",
    "wof:name":"SW3 1AP",
    "wof:placetype":"postalcode"
},
  "geometry": {"coordinates":[-0.16088756281848,51.50010818612539],"type":"Point"}
}