{
  "type": "Feature",
  "properties": {
    "iso:country":"GB",
    "wof:name":"BL7 9NH",
    "wof:placetype":"postalcode"
},
  "geometry": {"coordinates":[-2.40918818277555,53.61846725976979],"type":"Point"}
}