{
  "type": "Feature",
  "properties": {
    "iso:country": "GB",
    "wof:name": "BL7 9NH",
    "wof:placetype": "postalcode"
  },
  "geometry": {"coordinates":[-2.409188,53.618467],"type":"Point"}
}
