{
  "type": "Feature",
  "properties": {
    "iso:country":"GB",
    "wof:name":"PE38 9AA",
    "wof:placetype":"postalcode"
},
  "geometry": {"coordinates":[0.37798496955448,52.60140595723166],"type":"Point"}
}