{
  "type": "Feature",
  "properties": {
    "date:inception_lower":"1995-07-01",
    "date:inception_upper":"1995-07-31",
    "iso:country":"GB",
    "wof:name":"RG42 5JA",
    "wof:placetype":"postalcode"
},
  "geometry": {"coordinates":[-0.789727,51.43471],"type":"Point"}
}