{
  "type": "Feature",
  "properties": {
    "iso:country":"GB",
    "wof:name":"RG42 5JA",
    "wof:placetype":"postalcode"
},
  "geometry": {"coordinates":[-0.78972744846223,51.43471010931081],"type":"Point"}
}