{
  "type": "Feature",
  "properties": {
    "iso:country":"GB",
    "wof:name":"CV9 3SJ",
    "wof:placetype":"postalcode"
},
  "geometry": {"coordinates":[-1.54745356093228,52.58622202260703],"type":"Point"}
}