{
  "type": "Feature",
  "properties": {
    "date:inception_lower": "1982-03-01",
    "date:inception_upper": "1982-03-01",
    "iso:country": "GB",
    "wof:name": "PA14 5DL",
    "wof:placetype": "postalcode"
  },
  "geometry": {"coordinates":[-4.684268,55.927516],"type":"Point"}
}
