{
  "type": "Feature",
  "properties": {
    "iso:country": "GB",
    "wof:name": "UB4 9UR",
    "wof:placetype": "postalcode"
  },
  "geometry": {"coordinates":[-0.396203,51.529783],"type":"Point"}
}
