{
  "type": "Feature",
  "properties": {
    "iso:country":"GB",
    "wof:name":"UB4 9UR",
    "wof:placetype":"postalcode"
},
  "geometry": {"coordinates":[-0.39620313629816,51.52978339031007],"type":"Point"}
}