{
  "type": "Feature",
  "properties": {
    "date:inception_lower":"1995-01-01",
    "date:inception_upper":"1995-01-31",
    "iso:country":"GB",
    "wof:name":"UB4 9UR",
    "wof:placetype":"postalcode"
},
  "geometry": {"coordinates":[-0.396203,51.529783],"type":"Point"}
}