{
  "type": "Feature",
  "properties": {
    "iso:country":"GB",
    "wof:name":"CH3 7AP",
    "wof:placetype":"postalcode"
},
  "geometry": {"coordinates":[-2.83572296999196,53.18533250384708],"type":"Point"}
}