{
  "type": "Feature",
  "properties": {
    "iso:country":"GB",
    "wof:name":"NR17 2HB",
    "wof:placetype":"postalcode"
},
  "geometry": {"coordinates":[1.00703320703969,52.51111459322822],"type":"Point"}
}