{
  "type": "Feature",
  "properties": {
    "iso:country":"GB",
    "wof:name":"LA3 1HY",
    "wof:placetype":"postalcode"
},
  "geometry": {"coordinates":[-2.88132692796561,54.05985791251791],"type":"Point"}
}