{
  "type": "Feature",
  "properties": {
    "iso:country": "GB",
    "wof:name": "LA3 1HY",
    "wof:placetype": "postalcode"
  },
  "geometry": {"coordinates":[-2.881327,54.059858],"type":"Point"}
}
