{
  "type": "Feature",
  "properties": {
    "date:inception_lower": "1994-05-01",
    "date:inception_upper": "1994-05-01",
    "iso:country": "GB",
    "wof:name": "LS6 1RQ",
    "wof:placetype": "postalcode"
  },
  "geometry": {"coordinates":[-1.570792,53.808067],"type":"Point"}
}
