{
  "type": "Feature",
  "properties": {
    "iso:country":"GB",
    "wof:name":"LS6 1RQ",
    "wof:placetype":"postalcode"
},
  "geometry": {"coordinates":[-1.57079160558504,53.80806709946457],"type":"Point"}
}