{
  "type": "Feature",
  "properties": {
    "date:inception_lower": "1980-01-01",
    "date:inception_upper": "1980-01-01",
    "iso:country": "GB",
    "wof:name": "BA3 5JY",
    "wof:placetype": "postalcode"
  },
  "geometry": {"coordinates":[-2.474005,51.218064],"type":"Point"}
}
