{
  "type": "Feature",
  "properties": {
    "iso:country":"GB",
    "wof:name":"BA3 5JY",
    "wof:placetype":"postalcode"
},
  "geometry": {"coordinates":[-2.47400557679211,51.21806886436207],"type":"Point"}
}