{
  "type": "Feature",
  "properties": {
    "iso:country":"GB",
    "wof:name":"NN9 5YR",
    "wof:placetype":"postalcode"
},
  "geometry": {"coordinates":[-0.70524621321715,52.32153106084242],"type":"Point"}
}