{
  "type": "Feature",
  "properties": {
    "iso:country": "GB",
    "wof:name": "CA7 8BN",
    "wof:placetype": "postalcode"
  },
  "geometry": {"coordinates":[-3.051996,54.822583],"type":"Point"}
}
