{
  "type": "Feature",
  "properties": {
    "iso:country":"GB",
    "wof:name":"B25 8RJ",
    "wof:placetype":"postalcode"
},
  "geometry": {"coordinates":[-1.80871150160839,52.47165413465888],"type":"Point"}
}