{
  "type": "Feature",
  "properties": {
    "iso:country":"GB",
    "wof:name":"SE1 8SU",
    "wof:placetype":"postalcode"
},
  "geometry": {"coordinates":[-0.10712714053976,51.50473825293368],"type":"Point"}
}