{
  "type": "Feature",
  "properties": {
    "date:inception_lower": "1980-01-01",
    "date:inception_upper": "1980-01-01",
    "iso:country": "GB",
    "wof:name": "DE55 4BP",
    "wof:placetype": "postalcode"
  },
  "geometry": {"coordinates":[-1.359085,53.067689],"type":"Point"}
}
