{
  "type": "Feature",
  "properties": {
    "iso:country":"GB",
    "wof:name":"DE55 4BP",
    "wof:placetype":"postalcode"
},
  "geometry": {"coordinates":[-1.35908549559084,53.06768876346464],"type":"Point"}
}