{
  "type": "Feature",
  "properties": {
    "iso:country":"GB",
    "wof:name":"OX20 1LH",
    "wof:placetype":"postalcode"
},
  "geometry": {"coordinates":[-1.34608830754958,51.85014621655085],"type":"Point"}
}