{
  "type": "Feature",
  "properties": {
    "iso:country":"GB",
    "wof:name":"L20 6DN",
    "wof:placetype":"postalcode"
},
  "geometry": {"coordinates":[-2.976896021979,53.46821308991762],"type":"Point"}
}