{
  "type": "Feature",
  "properties": {
    "date:inception_lower":"2006-10-01",
    "date:inception_upper":"2006-10-31",
    "iso:country":"GB",
    "wof:name":"CV47 1RB",
    "wof:placetype":"postalcode"
},
  "geometry": {"coordinates":[-1.395669,52.247919],"type":"Point"}
}