{
  "type": "Feature",
  "properties": {
    "date:inception_lower": "1980-01-01",
    "date:inception_upper": "1980-01-01",
    "iso:country": "GB",
    "wof:name": "NG15 7HN",
    "wof:placetype": "postalcode"
  },
  "geometry": {"coordinates":[-1.202033,53.036553],"type":"Point"}
}
