{
  "type": "Feature",
  "properties": {
    "iso:country":"GB",
    "wof:name":"OX2 0AJ",
    "wof:placetype":"postalcode"
},
  "geometry": {"coordinates":[-1.27083654398628,51.75155640373605],"type":"Point"}
}