{
  "type": "Feature",
  "properties": {
    "iso:country":"GB",
    "wof:name":"RG42 7PY",
    "wof:placetype":"postalcode"
},
  "geometry": {"coordinates":[-0.7118098996036,51.43116429420416],"type":"Point"}
}