{
  "type": "Feature",
  "properties": {
    "iso:country":"GB",
    "wof:name":"SS6 8YW",
    "wof:placetype":"postalcode"
},
  "geometry": {"coordinates":[0.62647271619557,51.58621931980471],"type":"Point"}
}