{
  "type": "Feature",
  "properties": {
    "date:inception_lower": "1980-01-01",
    "date:inception_upper": "1980-01-01",
    "iso:country": "GB",
    "wof:name": "SS6 8YW",
    "wof:placetype": "postalcode"
  },
  "geometry": {"coordinates":[0.62647,51.586207],"type":"Point"}
}
