{
  "type": "Feature",
  "properties": {
    "date:inception_lower": "2004-02-01",
    "date:inception_upper": "2004-02-01",
    "iso:country": "GB",
    "wof:name": "NE4 8SX",
    "wof:placetype": "postalcode"
  },
  "geometry": {"coordinates":[-1.646876,54.974169],"type":"Point"}
}
