{
  "type": "Feature",
  "properties": {
    "iso:country":"GB",
    "wof:name":"DN4 0UH",
    "wof:placetype":"postalcode"
},
  "geometry": {"coordinates":[-1.17111404570692,53.50355541261381],"type":"Point"}
}