{
  "type": "Feature",
  "properties": {
    "date:inception_lower":"1980-01-01",
    "date:inception_upper":"1980-01-31",
    "iso:country":"GB",
    "wof:name":"DN7 6QT",
    "wof:placetype":"postalcode"
},
  "geometry": {"coordinates":[-1.006809,53.578834],"type":"Point"}
}