{
  "type": "Feature",
  "properties": {
    "iso:country":"GB",
    "wof:name":"B66 4QN",
    "wof:placetype":"postalcode"
},
  "geometry": {"coordinates":[-1.9582670575907,52.48556471477503],"type":"Point"}
}