{
  "type": "Feature",
  "properties": {
    "date:inception_lower": "2017-02-01",
    "date:inception_upper": "2017-02-01",
    "iso:country": "GB",
    "wof:name": "PO14 4GB",
    "wof:placetype": "postalcode"
  },
  "geometry": {"coordinates":[-1.252416,50.84865],"type":"Point"}
}
