{
  "type": "Feature",
  "properties": {
    "iso:country":"GB",
    "wof:name":"AL10 9JT",
    "wof:placetype":"postalcode"
},
  "geometry": {"coordinates":[-0.23325062559372,51.772498226704],"type":"Point"}
}