{
  "type": "Feature",
  "properties": {
    "iso:country": "GB",
    "wof:name": "CF48 2HG",
    "wof:placetype": "postalcode"
  },
  "geometry": {"coordinates":[-3.411683,51.766987],"type":"Point"}
}
