{
  "type": "Feature",
  "properties": {
    "date:inception_lower": "2008-03-01",
    "date:inception_upper": "2008-03-01",
    "iso:country": "GB",
    "wof:name": "CF48 2HG",
    "wof:placetype": "postalcode"
  },
  "geometry": {"coordinates":[-3.411694,51.766992],"type":"Point"}
}
