{
  "type": "Feature",
  "properties": {
    "iso:country":"GB",
    "wof:name":"HA7 1HN",
    "wof:placetype":"postalcode"
},
  "geometry": {"coordinates":[-0.29947103127302,51.60234645369862],"type":"Point"}
}