{
  "type": "Feature",
  "properties": {
    "iso:country":"GB",
    "wof:name":"NE3 3UE",
    "wof:placetype":"postalcode"
},
  "geometry": {"coordinates":[-1.63007238972429,55.00414212660151],"type":"Point"}
}