{
  "type": "Feature",
  "properties": {
    "date:inception_lower": "2009-03-01",
    "date:inception_upper": "2009-03-01",
    "iso:country": "GB",
    "wof:name": "M4 4BR",
    "wof:placetype": "postalcode"
  },
  "geometry": {"coordinates":[-2.235226,53.487165],"type":"Point"}
}
