{
  "type": "Feature",
  "properties": {
    "iso:country":"GB",
    "wof:name":"M4 4BR",
    "wof:placetype":"postalcode"
},
  "geometry": {"coordinates":[-2.2352281003895,53.48714877395583],"type":"Point"}
}