{
  "type": "Feature",
  "properties": {
    "iso:country":"GB",
    "wof:name":"B30 3PJ",
    "wof:placetype":"postalcode"
},
  "geometry": {"coordinates":[-1.92027926565496,52.40909425774073],"type":"Point"}
}