{
  "type": "Feature",
  "properties": {
    "iso:country":"GB",
    "wof:name":"BH10 4BL",
    "wof:placetype":"postalcode"
},
  "geometry": {"coordinates":[-1.89700865486728,50.75109031063297],"type":"Point"}
}