{
  "type": "Feature",
  "properties": {
    "iso:country":"GB",
    "wof:name":"BL2 3JZ",
    "wof:placetype":"postalcode"
},
  "geometry": {"coordinates":[-2.39473586961534,53.60388287280205],"type":"Point"}
}