{
  "type": "Feature",
  "properties": {
    "iso:country":"GB",
    "wof:name":"SM5 3AY",
    "wof:placetype":"postalcode"
},
  "geometry": {"coordinates":[-0.1653130521757,51.36322932729457],"type":"Point"}
}