{
  "type": "Feature",
  "properties": {
    "iso:country": "GB",
    "wof:name": "SM5 3AY",
    "wof:placetype": "postalcode"
  },
  "geometry": {"coordinates":[-0.165244,51.363245],"type":"Point"}
}
