{
  "type": "Feature",
  "properties": {
    "date:inception_lower":"2016-02-01",
    "date:inception_upper":"2016-02-29",
    "iso:country":"GB",
    "wof:name":"SM5 3AY",
    "wof:placetype":"postalcode"
},
  "geometry": {"coordinates":[-0.165244,51.363245],"type":"Point"}
}