{
  "type": "Feature",
  "properties": {
    "iso:country":"GB",
    "wof:name":"NN11 9XL",
    "wof:placetype":"postalcode"
},
  "geometry": {"coordinates":[-1.16849214901745,52.26648781068275],"type":"Point"}
}