{
  "type": "Feature",
  "properties": {
    "date:inception_lower": "2016-07-01",
    "date:inception_upper": "2016-07-01",
    "iso:country": "GB",
    "wof:name": "KY1 4PY",
    "wof:placetype": "postalcode"
  },
  "geometry": {"coordinates":[-3.097901,56.150565],"type":"Point"}
}
