{
  "type": "Feature",
  "properties": {
    "iso:country": "GB",
    "wof:name": "DA7 4AS",
    "wof:placetype": "postalcode"
  },
  "geometry": {"coordinates":[0.135863,51.461904],"type":"Point"}
}
