{
  "type": "Feature",
  "properties": {
    "iso:country":"GB",
    "wof:name":"DA7 4AS",
    "wof:placetype":"postalcode"
},
  "geometry": {"coordinates":[0.13586313733873,51.46190392166901],"type":"Point"}
}