{
  "type": "Feature",
  "properties": {
    "iso:country":"GB",
    "wof:name":"BS15 9ZF",
    "wof:placetype":"postalcode"
},
  "geometry": {"coordinates":[-2.49835081047544,51.45402018369584],"type":"Point"}
}