{
  "type": "Feature",
  "properties": {
    "iso:country": "GB",
    "wof:name": "CH34 9DP",
    "wof:placetype": "postalcode"
  },
  "geometry": {"coordinates":[-2.912829,53.286281],"type":"Point"}
}
