{
  "type": "Feature",
  "properties": {
    "date:inception_lower": "2024-08-01",
    "date:inception_upper": "2024-08-01",
    "iso:country": "GB",
    "wof:name": "ST55 9LJ",
    "wof:placetype": "postalcode"
  },
  "geometry": {"coordinates":[-2.254182,53.016599],"type":"Point"}
}
