{
  "type": "Feature",
  "properties": {
    "iso:country":"GB",
    "wof:name":"LL26 0BA",
    "wof:placetype":"postalcode"
},
  "geometry": {"coordinates":[-3.79293095036928,53.14088459967952],"type":"Point"}
}