{
  "type": "Feature",
  "properties": {
    "iso:country":"GB",
    "wof:name":"BS22 9JB",
    "wof:placetype":"postalcode"
},
  "geometry": {"coordinates":[-2.92764863638342,51.36243407867097],"type":"Point"}
}