{
  "type": "Feature",
  "properties": {
    "date:inception_lower":"1983-07-01",
    "date:inception_upper":"1983-07-31",
    "iso:country":"GB",
    "wof:name":"BS22 9JB",
    "wof:placetype":"postalcode"
},
  "geometry": {"coordinates":[-2.927649,51.362434],"type":"Point"}
}