{
  "type": "Feature",
  "properties": {
    "date:inception_lower": "1980-01-01",
    "date:inception_upper": "1980-01-01",
    "iso:country": "GB",
    "wof:name": "BB5 2DS",
    "wof:placetype": "postalcode"
  },
  "geometry": {"coordinates":[-2.324688,53.725566],"type":"Point"}
}
