{
  "type": "Feature",
  "properties": {
    "iso:country":"GB",
    "wof:name":"BB5 2DS",
    "wof:placetype":"postalcode"
},
  "geometry": {"coordinates":[-2.32468861014276,53.72555110247729],"type":"Point"}
}