{
  "type": "Feature",
  "properties": {
    "iso:country":"GB",
    "wof:name":"EN4 0JU",
    "wof:placetype":"postalcode"
},
  "geometry": {"coordinates":[-0.15595143906883,51.65862958969288],"type":"Point"}
}