{
  "type": "Feature",
  "properties": {
    "iso:country": "GB",
    "wof:name": "EN4 0JU",
    "wof:placetype": "postalcode"
  },
  "geometry": {"coordinates":[-0.155179,51.658864],"type":"Point"}
}
