{
  "type": "Feature",
  "properties": {
    "iso:country":"GB",
    "wof:name":"ME20 7EU",
    "wof:placetype":"postalcode"
},
  "geometry": {"coordinates":[0.50462919848011,51.32361314742172],"type":"Point"}
}