{
  "type": "Feature",
  "properties": {
    "date:inception_lower": "1987-04-01",
    "date:inception_upper": "1987-04-01",
    "iso:country": "GB",
    "wof:name": "MK46 5PH",
    "wof:placetype": "postalcode"
  },
  "geometry": {"coordinates":[-0.709911,52.157399],"type":"Point"}
}
