{
  "type": "Feature",
  "properties": {
    "iso:country": "GB",
    "wof:name": "MK46 5PH",
    "wof:placetype": "postalcode"
  },
  "geometry": {"coordinates":[-0.709911,52.157399],"type":"Point"}
}
