{
  "type": "Feature",
  "properties": {
    "date:inception_lower":"1980-01-01",
    "date:inception_upper":"1980-01-31",
    "iso:country":"GB",
    "wof:name":"DD4 9EJ",
    "wof:placetype":"postalcode"
},
  "geometry": {"coordinates":[-2.945254,56.488948],"type":"Point"}
}