{
  "type": "Feature",
  "properties": {
    "iso:country":"GB",
    "wof:name":"WS15 1HJ",
    "wof:placetype":"postalcode"
},
  "geometry": {"coordinates":[-1.91916296241654,52.74666088806445],"type":"Point"}
}