{
  "type": "Feature",
  "properties": {
    "iso:country": "GB",
    "wof:name": "EH16 5EW",
    "wof:placetype": "postalcode"
  },
  "geometry": {"coordinates":[-3.161485,55.931611],"type":"Point"}
}
