{
  "type": "Feature",
  "properties": {
    "iso:country": "GB",
    "wof:name": "GL50 1PQ",
    "wof:placetype": "postalcode"
  },
  "geometry": {"coordinates":[-2.07708,51.897934],"type":"Point"}
}
