{
  "type": "Feature",
  "properties": {
    "date:inception_lower": "2019-02-01",
    "date:inception_upper": "2019-02-01",
    "iso:country": "GB",
    "wof:name": "RH16 1AN",
    "wof:placetype": "postalcode"
  },
  "geometry": {"coordinates":[-0.100907,51.016401],"type":"Point"}
}
