{
  "type": "Feature",
  "properties": {
    "iso:country":"GB",
    "wof:name":"CT10 2LZ",
    "wof:placetype":"postalcode"
},
  "geometry": {"coordinates":[1.40750376313312,51.3574766259441],"type":"Point"}
}