{
  "type": "Feature",
  "properties": {
    "iso:country":"GB",
    "wof:name":"S70 3EW",
    "wof:placetype":"postalcode"
},
  "geometry": {"coordinates":[-1.44655505161401,53.5471864990156],"type":"Point"}
}