{
  "type": "Feature",
  "properties": {
    "date:inception_lower": "1980-01-01",
    "date:inception_upper": "1980-01-01",
    "iso:country": "GB",
    "wof:name": "BB12 8EX",
    "wof:placetype": "postalcode"
  },
  "geometry": {"coordinates":[-2.315422,53.801548],"type":"Point"}
}
