{
  "type": "Feature",
  "properties": {
    "iso:country":"GB",
    "wof:name":"BB12 8EX",
    "wof:placetype":"postalcode"
},
  "geometry": {"coordinates":[-2.3151804147118,53.8017232486176],"type":"Point"}
}