{
  "type": "Feature",
  "properties": {
    "iso:country":"GB",
    "wof:name":"DL14 9NA",
    "wof:placetype":"postalcode"
},
  "geometry": {"coordinates":[-1.72786508145463,54.63070697507224],"type":"Point"}
}