{
  "type": "Feature",
  "properties": {
    "iso:country": "GB",
    "wof:name": "DL14 9NA",
    "wof:placetype": "postalcode"
  },
  "geometry": {"coordinates":[-1.727865,54.630707],"type":"Point"}
}
