{
  "type": "Feature",
  "properties": {
    "date:inception_lower":"1999-12-01",
    "date:inception_upper":"1999-12-31",
    "iso:country":"GB",
    "wof:name":"DL14 9NA",
    "wof:placetype":"postalcode"
},
  "geometry": {"coordinates":[-1.727865,54.630707],"type":"Point"}
}