{
  "type": "Feature",
  "properties": {
    "iso:country": "GB",
    "wof:name": "E7 0DS",
    "wof:placetype": "postalcode"
  },
  "geometry": {"coordinates":[0.024,51.552863],"type":"Point"}
}
