{
  "type": "Feature",
  "properties": {
    "iso:country":"GB",
    "wof:name":"E7 0DS",
    "wof:placetype":"postalcode"
},
  "geometry": {"coordinates":[0.02400033263528,51.55286253109612],"type":"Point"}
}