{
  "type": "Feature",
  "properties": {
    "iso:country":"GB",
    "wof:name":"RH11 6DG",
    "wof:placetype":"postalcode"
},
  "geometry": {"coordinates":[-0.23032306715283,51.10611820815588],"type":"Point"}
}