{
  "type": "Feature",
  "properties": {
    "iso:country": "GB",
    "wof:name": "S7 2HJ",
    "wof:placetype": "postalcode"
  },
  "geometry": {"coordinates":[-1.495718,53.348037],"type":"Point"}
}
