{
  "type": "Feature",
  "properties": {
    "iso:country":"GB",
    "wof:name":"AB21 9TS",
    "wof:placetype":"postalcode"
},
  "geometry": {"coordinates":[-2.20546082133182,57.19002411123327],"type":"Point"}
}