{
  "type": "Feature",
  "properties": {
    "date:inception_lower": "1997-12-01",
    "date:inception_upper": "1997-12-01",
    "iso:country": "GB",
    "wof:name": "BS32 4NZ",
    "wof:placetype": "postalcode"
  },
  "geometry": {"coordinates":[-2.554055,51.57931],"type":"Point"}
}
