{
  "type": "Feature",
  "properties": {
    "iso:country":"GB",
    "wof:name":"BS32 4NZ",
    "wof:placetype":"postalcode"
},
  "geometry": {"coordinates":[-2.554054748099,51.57930985239945],"type":"Point"}
}