{
  "type": "Feature",
  "properties": {
    "date:inception_lower":"2004-05-01",
    "date:inception_upper":"2004-05-31",
    "iso:country":"GB",
    "wof:name":"AL1 3WA",
    "wof:placetype":"postalcode"
},
  "geometry": {"coordinates":[-0.335502,51.75018],"type":"Point"}
}