{
  "type": "Feature",
  "properties": {
    "iso:country": "GB",
    "wof:name": "BS37 8SU",
    "wof:placetype": "postalcode"
  },
  "geometry": {"coordinates":[-2.428467,51.528063],"type":"Point"}
}
