{
  "type": "Feature",
  "properties": {
    "iso:country":"GB",
    "wof:name":"TF11 9BG",
    "wof:placetype":"postalcode"
},
  "geometry": {"coordinates":[-2.3728049807295,52.66481704429314],"type":"Point"}
}