{
  "type": "Feature",
  "properties": {
    "iso:country":"GB",
    "wof:name":"EX8 5LZ",
    "wof:placetype":"postalcode"
},
  "geometry": {"coordinates":[-3.41529466993224,50.64792571086139],"type":"Point"}
}