{
  "type": "Feature",
  "properties": {
    "iso:country": "GB",
    "wof:name": "EX8 5LZ",
    "wof:placetype": "postalcode"
  },
  "geometry": {"coordinates":[-3.415295,50.647926],"type":"Point"}
}
