{
  "type": "Feature",
  "properties": {
    "iso:country": "GB",
    "wof:name": "IV30 6BX",
    "wof:placetype": "postalcode"
  },
  "geometry": {"coordinates":[-3.307206,57.636778],"type":"Point"}
}
