{
  "type": "Feature",
  "properties": {
    "iso:country":"GB",
    "wof:name":"RG7 1UP",
    "wof:placetype":"postalcode"
},
  "geometry": {"coordinates":[-0.91343610012365,51.37701542588496],"type":"Point"}
}