{
  "type": "Feature",
  "properties": {
    "iso:country": "GB",
    "wof:name": "OL9 9DQ",
    "wof:placetype": "postalcode"
  },
  "geometry": {"coordinates":[-2.147207,53.536744],"type":"Point"}
}
