{
  "type": "Feature",
  "properties": {
    "iso:country":"GB",
    "wof:name":"OL9 9DQ",
    "wof:placetype":"postalcode"
},
  "geometry": {"coordinates":[-2.14720710676146,53.53674393788591],"type":"Point"}
}