{
  "type": "Feature",
  "properties": {
    "iso:country":"GB",
    "wof:name":"TR7 2PD",
    "wof:placetype":"postalcode"
},
  "geometry": {"coordinates":[-5.06807869988463,50.41877492650531],"type":"Point"}
}