{
  "type": "Feature",
  "properties": {
    "date:inception_lower":"2014-08-01",
    "date:inception_upper":"2014-08-31",
    "iso:country":"GB",
    "wof:name":"TR7 2PD",
    "wof:placetype":"postalcode"
},
  "geometry": {"coordinates":[-5.068079,50.418775],"type":"Point"}
}