{
  "type": "Feature",
  "properties": {
    "date:inception_lower": "2008-08-01",
    "date:inception_upper": "2008-08-01",
    "iso:country": "GB",
    "wof:name": "LU6 2QS",
    "wof:placetype": "postalcode"
  },
  "geometry": {"coordinates":[-0.62169,51.873311],"type":"Point"}
}
