{
  "type": "Feature",
  "properties": {
    "iso:country":"GB",
    "wof:name":"LU6 2QS",
    "wof:placetype":"postalcode"
},
  "geometry": {"coordinates":[-0.62169022775427,51.87331055256488],"type":"Point"}
}