{
  "type": "Feature",
  "properties": {
    "date:inception_lower":"1985-04-01",
    "date:inception_upper":"1985-04-30",
    "iso:country":"GB",
    "wof:name":"NE9 5EF",
    "wof:placetype":"postalcode"
},
  "geometry": {"coordinates":[-1.598743,54.949128],"type":"Point"}
}