{
  "type": "Feature",
  "properties": {
    "iso:country": "GB",
    "wof:name": "S21 4LH",
    "wof:placetype": "postalcode"
  },
  "geometry": {"coordinates":[-1.356409,53.303997],"type":"Point"}
}
