{
  "type": "Feature",
  "properties": {
    "iso:country":"GB",
    "wof:name":"PR1 1TR",
    "wof:placetype":"postalcode"
},
  "geometry": {"coordinates":[-2.69584557622377,53.76347314731034],"type":"Point"}
}