{
  "type": "Feature",
  "properties": {
    "iso:country": "GB",
    "wof:name": "PR1 1TR",
    "wof:placetype": "postalcode"
  },
  "geometry": {"coordinates":[-2.695846,53.763473],"type":"Point"}
}
