{
  "type": "Feature",
  "properties": {
    "iso:country":"GB",
    "wof:name":"SE28 8EF",
    "wof:placetype":"postalcode"
},
  "geometry": {"coordinates":[0.1126529054658,51.505769003819],"type":"Point"}
}