{
  "type": "Feature",
  "properties": {
    "date:inception_lower": "2012-07-01",
    "date:inception_upper": "2012-07-01",
    "iso:country": "GB",
    "wof:name": "DE12 6DY",
    "wof:placetype": "postalcode"
  },
  "geometry": {"coordinates":[-1.521778,52.742849],"type":"Point"}
}
