{
  "type": "Feature",
  "properties": {
    "iso:country": "GB",
    "wof:name": "NG20 0EU",
    "wof:placetype": "postalcode"
  },
  "geometry": {"coordinates":[-1.126695,53.220637],"type":"Point"}
}
