{
  "type": "Feature",
  "properties": {
    "date:inception_lower": "2016-11-01",
    "date:inception_upper": "2016-11-01",
    "iso:country": "GB",
    "wof:name": "G5 0AP",
    "wof:placetype": "postalcode"
  },
  "geometry": {"coordinates":[-4.237227,55.838697],"type":"Point"}
}
