{
  "type": "Feature",
  "properties": {
    "iso:country":"GB",
    "wof:name":"RH1 5NJ",
    "wof:placetype":"postalcode"
},
  "geometry": {"coordinates":[-0.13604143995234,51.22288397466031],"type":"Point"}
}