{
  "type": "Feature",
  "properties": {
    "iso:country": "GB",
    "wof:name": "PH1 0AF",
    "wof:placetype": "postalcode"
  },
  "geometry": {"coordinates":[-3.491855,56.423464],"type":"Point"}
}
