{
  "type": "Feature",
  "properties": {
    "iso:country":"GB",
    "wof:name":"S70 2RF",
    "wof:placetype":"postalcode"
},
  "geometry": {"coordinates":[-1.48763329120159,53.55363438018303],"type":"Point"}
}