{
  "type": "Feature",
  "properties": {
    "date:inception_lower": "2010-08-01",
    "date:inception_upper": "2010-08-01",
    "iso:country": "GB",
    "wof:name": "S70 2RF",
    "wof:placetype": "postalcode"
  },
  "geometry": {"coordinates":[-1.487633,53.553634],"type":"Point"}
}
