{
  "type": "Feature",
  "properties": {
    "iso:country":"GB",
    "wof:name":"BS22 8EF",
    "wof:placetype":"postalcode"
},
  "geometry": {"coordinates":[-2.94579917188272,51.35383648421166],"type":"Point"}
}