{
  "type": "Feature",
  "properties": {
    "iso:country": "GB",
    "wof:name": "GU23 6JX",
    "wof:placetype": "postalcode"
  },
  "geometry": {"coordinates":[-0.513463,51.292736],"type":"Point"}
}
