{
  "type": "Feature",
  "properties": {
    "iso:country":"GB",
    "wof:name":"IP22 2NE",
    "wof:placetype":"postalcode"
},
  "geometry": {"coordinates":[0.99228543890041,52.4107475267412],"type":"Point"}
}