{
  "type": "Feature",
  "properties": {
    "iso:country": "GB",
    "wof:name": "IP22 2NE",
    "wof:placetype": "postalcode"
  },
  "geometry": {"coordinates":[0.992285,52.410748],"type":"Point"}
}
