{
  "type": "Feature",
  "properties": {
    "iso:country": "GB",
    "wof:name": "AL3 7QE",
    "wof:placetype": "postalcode"
  },
  "geometry": {"coordinates":[-0.390983,51.800586],"type":"Point"}
}
