{
  "type": "Feature",
  "properties": {
    "iso:country":"GB",
    "wof:name":"EN4 0JF",
    "wof:placetype":"postalcode"
},
  "geometry": {"coordinates":[-0.15449236546238,51.65966775841486],"type":"Point"}
}