{
  "type": "Feature",
  "properties": {
    "iso:country":"GB",
    "wof:name":"CM14 4HL",
    "wof:placetype":"postalcode"
},
  "geometry": {"coordinates":[0.30057636083434,51.61433954403643],"type":"Point"}
}