{
  "type": "Feature",
  "properties": {
    "date:inception_lower": "2000-12-01",
    "date:inception_upper": "2000-12-01",
    "iso:country": "GB",
    "wof:name": "TA11 7JW",
    "wof:placetype": "postalcode"
  },
  "geometry": {"coordinates":[-2.721547,51.044478],"type":"Point"}
}
