{
  "type": "Feature",
  "properties": {
    "iso:country": "GB",
    "wof:name": "PL24 2QA",
    "wof:placetype": "postalcode"
  },
  "geometry": {"coordinates":[-4.695626,50.358653],"type":"Point"}
}
