{
  "type": "Feature",
  "properties": {
    "date:inception_lower":"2012-06-01",
    "date:inception_upper":"2012-06-30",
    "iso:country":"GB",
    "wof:name":"PL24 2QA",
    "wof:placetype":"postalcode"
},
  "geometry": {"coordinates":[-4.695626,50.358653],"type":"Point"}
}