{
  "type": "Feature",
  "properties": {
    "iso:country":"GB",
    "wof:name":"PL24 2QA",
    "wof:placetype":"postalcode"
},
  "geometry": {"coordinates":[-4.6955851808512,50.35866634020606],"type":"Point"}
}