{
  "type": "Feature",
  "properties": {
    "iso:country":"GB",
    "wof:name":"BD18 2NN",
    "wof:placetype":"postalcode"
},
  "geometry": {"coordinates":[-1.76449196696919,53.83351797250372],"type":"Point"}
}