{
  "type": "Feature",
  "properties": {
    "date:inception_lower": "1980-01-01",
    "date:inception_upper": "1980-01-01",
    "iso:country": "GB",
    "wof:name": "G68 9AD",
    "wof:placetype": "postalcode"
  },
  "geometry": {"coordinates":[-4.033915,55.947541],"type":"Point"}
}
