{
  "type": "Feature",
  "properties": {
    "iso:country": "GB",
    "wof:name": "G68 9AD",
    "wof:placetype": "postalcode"
  },
  "geometry": {"coordinates":[-4.033915,55.947541],"type":"Point"}
}
