{
  "type": "Feature",
  "properties": {
    "date:inception_lower": "2000-12-01",
    "date:inception_upper": "2000-12-01",
    "iso:country": "GB",
    "wof:name": "SY5 0DR",
    "wof:placetype": "postalcode"
  },
  "geometry": {"coordinates":[-2.923176,52.639889],"type":"Point"}
}
