{
  "type": "Feature",
  "properties": {
    "iso:country":"GB",
    "wof:name":"SY5 0DR",
    "wof:placetype":"postalcode"
},
  "geometry": {"coordinates":[-2.92317644443771,52.6398890680453],"type":"Point"}
}