{
  "type": "Feature",
  "properties": {
    "date:inception_lower": "2009-04-01",
    "date:inception_upper": "2009-04-01",
    "iso:country": "GB",
    "wof:name": "B77 2TQ",
    "wof:placetype": "postalcode"
  },
  "geometry": {"coordinates":[-1.677438,52.61305],"type":"Point"}
}
