{
  "type": "Feature",
  "properties": {
    "iso:country":"GB",
    "wof:name":"B77 2TQ",
    "wof:placetype":"postalcode"
},
  "geometry": {"coordinates":[-1.67743779744206,52.61305015810185],"type":"Point"}
}