{
  "type": "Feature",
  "properties": {
    "iso:country":"GB",
    "wof:name":"BB4 8LY",
    "wof:placetype":"postalcode"
},
  "geometry": {"coordinates":[-2.28817863488338,53.72115049090615],"type":"Point"}
}