{
  "type": "Feature",
  "properties": {
    "iso:country": "GB",
    "wof:name": "LL72 8LB",
    "wof:placetype": "postalcode"
  },
  "geometry": {"coordinates":[-4.23376,53.354761],"type":"Point"}
}
