{
  "type": "Feature",
  "properties": {
    "date:inception_lower":"1980-01-01",
    "date:inception_upper":"1980-01-31",
    "iso:country":"GB",
    "wof:name":"LL72 8LB",
    "wof:placetype":"postalcode"
},
  "geometry": {"coordinates":[-4.23376,53.354761],"type":"Point"}
}