{
  "type": "Feature",
  "properties": {
    "iso:country":"GB",
    "wof:name":"LE11 3NN",
    "wof:placetype":"postalcode"
},
  "geometry": {"coordinates":[-1.21248490294054,52.76434767060238],"type":"Point"}
}