{
  "type": "Feature",
  "properties": {
    "iso:country":"GB",
    "wof:name":"EH31 2ED",
    "wof:placetype":"postalcode"
},
  "geometry": {"coordinates":[-2.82145613507079,56.03989583715106],"type":"Point"}
}