{
  "type": "Feature",
  "properties": {
    "date:inception_lower": "1980-01-01",
    "date:inception_upper": "1980-01-01",
    "iso:country": "GB",
    "wof:name": "EH31 2ED",
    "wof:placetype": "postalcode"
  },
  "geometry": {"coordinates":[-2.821456,56.039896],"type":"Point"}
}
