{
  "type": "Feature",
  "properties": {
    "iso:country": "GB",
    "wof:name": "EH31 2ED",
    "wof:placetype": "postalcode"
  },
  "geometry": {"coordinates":[-2.821456,56.039896],"type":"Point"}
}
