{
  "type": "Feature",
  "properties": {
    "iso:country":"GB",
    "wof:name":"HP5 3FE",
    "wof:placetype":"postalcode"
},
  "geometry": {"coordinates":[-0.60252603172134,51.71722351838604],"type":"Point"}
}