{
  "type": "Feature",
  "properties": {
    "date:inception_lower": "2007-11-01",
    "date:inception_upper": "2007-11-01",
    "iso:country": "GB",
    "wof:name": "CV12 0PG",
    "wof:placetype": "postalcode"
  },
  "geometry": {"coordinates":[-1.512912,52.468477],"type":"Point"}
}
