{
  "type": "Feature",
  "properties": {
    "iso:country":"GB",
    "wof:name":"CV12 0PG",
    "wof:placetype":"postalcode"
},
  "geometry": {"coordinates":[-1.51277314412046,52.46847772380815],"type":"Point"}
}