{
  "type": "Feature",
  "properties": {
    "iso:country": "GB",
    "wof:name": "LS17 7PH",
    "wof:placetype": "postalcode"
  },
  "geometry": {"coordinates":[-1.550802,53.864016],"type":"Point"}
}
