{
  "type": "Feature",
  "properties": {
    "iso:country":"GB",
    "wof:name":"LS17 7PH",
    "wof:placetype":"postalcode"
},
  "geometry": {"coordinates":[-1.55080168297033,53.8640160330924],"type":"Point"}
}