{
  "type": "Feature",
  "properties": {
    "date:inception_lower": "1980-01-01",
    "date:inception_upper": "1980-01-01",
    "iso:country": "GB",
    "wof:name": "MK15 0AL",
    "wof:placetype": "postalcode"
  },
  "geometry": {"coordinates":[-0.725751,52.044383],"type":"Point"}
}
