{
  "type": "Feature",
  "properties": {
    "iso:country":"GB",
    "wof:name":"DG3 4HB",
    "wof:placetype":"postalcode"
},
  "geometry": {"coordinates":[-3.86478294168083,55.19173959075076],"type":"Point"}
}