{
  "type": "Feature",
  "properties": {
    "iso:country": "GB",
    "wof:name": "PL2 1RG",
    "wof:placetype": "postalcode"
  },
  "geometry": {"coordinates":[-4.17895,50.381238],"type":"Point"}
}
