{
  "type": "Feature",
  "properties": {
    "iso:country":"GB",
    "wof:name":"PL2 1RG",
    "wof:placetype":"postalcode"
},
  "geometry": {"coordinates":[-4.17894969618102,50.38123771657845],"type":"Point"}
}