{
  "type": "Feature",
  "properties": {
    "date:inception_lower":"1991-09-01",
    "date:inception_upper":"1991-09-30",
    "iso:country":"GB",
    "wof:name":"PO22 7SR",
    "wof:placetype":"postalcode"
},
  "geometry": {"coordinates":[-0.617758,50.794747],"type":"Point"}
}