{
  "type": "Feature",
  "properties": {
    "iso:country": "GB",
    "wof:name": "PO22 7SR",
    "wof:placetype": "postalcode"
  },
  "geometry": {"coordinates":[-0.617758,50.794747],"type":"Point"}
}
