{
  "type": "Feature",
  "properties": {
    "iso:country":"GB",
    "wof:name":"SO40 8FX",
    "wof:placetype":"postalcode"
},
  "geometry": {"coordinates":[-1.51759493210326,50.91814690755393],"type":"Point"}
}