{
  "type": "Feature",
  "properties": {
    "date:inception_lower": "1994-12-01",
    "date:inception_upper": "1994-12-01",
    "iso:country": "GB",
    "wof:name": "SO40 8FX",
    "wof:placetype": "postalcode"
  },
  "geometry": {"coordinates":[-1.517595,50.918147],"type":"Point"}
}
