{
  "type": "Feature",
  "properties": {
    "iso:country": "GB",
    "wof:name": "SO40 8FX",
    "wof:placetype": "postalcode"
  },
  "geometry": {"coordinates":[-1.517595,50.918147],"type":"Point"}
}
