{
  "type": "Feature",
  "properties": {
    "iso:country":"GB",
    "wof:name":"LN6 8TA",
    "wof:placetype":"postalcode"
},
  "geometry": {"coordinates":[-0.58396277471069,53.19839847923416],"type":"Point"}
}