{
  "type": "Feature",
  "properties": {
    "iso:country": "GB",
    "wof:name": "LN6 8TA",
    "wof:placetype": "postalcode"
  },
  "geometry": {"coordinates":[-0.583963,53.198398],"type":"Point"}
}
