{
  "type": "Feature",
  "properties": {
    "iso:country":"GB",
    "wof:name":"SN10 5FJ",
    "wof:placetype":"postalcode"
},
  "geometry": {"coordinates":[-1.98869592679859,51.33876418477266],"type":"Point"}
}