{
  "type": "Feature",
  "properties": {
    "iso:country":"GB",
    "wof:name":"NE29 0HE",
    "wof:placetype":"postalcode"
},
  "geometry": {"coordinates":[-1.44965159710427,55.01017299754228],"type":"Point"}
}