{
  "type": "Feature",
  "properties": {
    "iso:country": "GB",
    "wof:name": "ML11 7PW",
    "wof:placetype": "postalcode"
  },
  "geometry": {"coordinates":[-3.787532,55.67659],"type":"Point"}
}
