{
  "type": "Feature",
  "properties": {
    "iso:country":"GB",
    "wof:name":"ML11 7PW",
    "wof:placetype":"postalcode"
},
  "geometry": {"coordinates":[-3.7875317680774,55.67658957374087],"type":"Point"}
}