{
  "type": "Feature",
  "properties": {
    "iso:country":"GB",
    "wof:name":"SG11 1AF",
    "wof:placetype":"postalcode"
},
  "geometry": {"coordinates":[-0.02405431629127,51.84737317258447],"type":"Point"}
}