{
  "type": "Feature",
  "properties": {
    "date:inception_lower":"2002-06-01",
    "date:inception_upper":"2002-06-30",
    "iso:country":"GB",
    "wof:name":"CV6 6BS",
    "wof:placetype":"postalcode"
},
  "geometry": {"coordinates":[-1.491517,52.450579],"type":"Point"}
}