{
  "type": "Feature",
  "properties": {
    "date:inception_lower":"2000-06-01",
    "date:inception_upper":"2000-06-30",
    "iso:country":"GB",
    "wof:name":"TN9 2DQ",
    "wof:placetype":"postalcode"
},
  "geometry": {"coordinates":[0.280408,51.188573],"type":"Point"}
}