{
  "type": "Feature",
  "properties": {
    "iso:country":"GB",
    "wof:name":"TN9 2DQ",
    "wof:placetype":"postalcode"
},
  "geometry": {"coordinates":[0.28040780633472,51.18857292031363],"type":"Point"}
}