{
  "type": "Feature",
  "properties": {
    "iso:country": "GB",
    "wof:name": "PE23 4LF",
    "wof:placetype": "postalcode"
  },
  "geometry": {"coordinates":[0.03876,53.198098],"type":"Point"}
}
