{
  "type": "Feature",
  "properties": {
    "iso:country":"GB",
    "wof:name":"PE23 4LF",
    "wof:placetype":"postalcode"
},
  "geometry": {"coordinates":[0.0387567179647,53.19807230447971],"type":"Point"}
}