{
  "type": "Feature",
  "properties": {
    "date:inception_lower":"1980-01-01",
    "date:inception_upper":"1980-01-31",
    "iso:country":"GB",
    "wof:name":"UB10 0LF",
    "wof:placetype":"postalcode"
},
  "geometry": {"coordinates":[-0.456753,51.534903],"type":"Point"}
}