{
  "type": "Feature",
  "properties": {
    "iso:country":"GB",
    "wof:name":"UB10 0LF",
    "wof:placetype":"postalcode"
},
  "geometry": {"coordinates":[-0.45675349403475,51.53490274693639],"type":"Point"}
}