{
  "type": "Feature",
  "properties": {
    "iso:country":"GB",
    "wof:name":"CF32 8EL",
    "wof:placetype":"postalcode"
},
  "geometry": {"coordinates":[-3.58639609062681,51.61131070501319],"type":"Point"}
}