{
  "type": "Feature",
  "properties": {
    "iso:country": "GB",
    "wof:name": "KT12 5PW",
    "wof:placetype": "postalcode"
  },
  "geometry": {"coordinates":[-0.417235,51.37211],"type":"Point"}
}
