{
  "type": "Feature",
  "properties": {
    "iso:country":"GB",
    "wof:name":"EH44 6HJ",
    "wof:placetype":"postalcode"
},
  "geometry": {"coordinates":[-3.05821054476634,55.62098543679898],"type":"Point"}
}