{
  "type": "Feature",
  "properties": {
    "iso:country":"GB",
    "wof:name":"W1H 7JR",
    "wof:placetype":"postalcode"
},
  "geometry": {"coordinates":[-0.15866288376121,51.51455119355744],"type":"Point"}
}