{
  "type": "Feature",
  "properties": {
    "iso:country":"GB",
    "wof:name":"NE3 5DL",
    "wof:placetype":"postalcode"
},
  "geometry": {"coordinates":[-1.61197030602542,55.01365610106948],"type":"Point"}
}