{
  "type": "Feature",
  "properties": {
    "date:inception_lower":"1980-01-01",
    "date:inception_upper":"1980-01-31",
    "iso:country":"GB",
    "wof:name":"NE3 5DL",
    "wof:placetype":"postalcode"
},
  "geometry": {"coordinates":[-1.61197,55.013656],"type":"Point"}
}