{
  "type": "Feature",
  "properties": {
    "iso:country":"GB",
    "wof:name":"G20 2BU",
    "wof:placetype":"postalcode"
},
  "geometry": {"coordinates":[-4.28878529053628,55.89120151701729],"type":"Point"}
}