{
  "type": "Feature",
  "properties": {
    "iso:country":"GB",
    "wof:name":"PE6 7SP",
    "wof:placetype":"postalcode"
},
  "geometry": {"coordinates":[-0.19720393586399,52.60535560734648],"type":"Point"}
}