{
  "type": "Feature",
  "properties": {
    "date:inception_lower": "1995-12-01",
    "date:inception_upper": "1995-12-01",
    "iso:country": "GB",
    "wof:name": "PE6 7SP",
    "wof:placetype": "postalcode"
  },
  "geometry": {"coordinates":[-0.197204,52.605356],"type":"Point"}
}
