{
  "type": "Feature",
  "properties": {
    "iso:country": "GB",
    "wof:name": "PE6 7SP",
    "wof:placetype": "postalcode"
  },
  "geometry": {"coordinates":[-0.197204,52.605356],"type":"Point"}
}
