{
  "type": "Feature",
  "properties": {
    "iso:country":"GB",
    "wof:name":"BL1 2TJ",
    "wof:placetype":"postalcode"
},
  "geometry": {"coordinates":[-2.42245297649883,53.58736649644931],"type":"Point"}
}