{
  "type": "Feature",
  "properties": {
    "date:inception_lower":"1980-01-01",
    "date:inception_upper":"1980-01-31",
    "iso:country":"GB",
    "wof:name":"BL1 2TJ",
    "wof:placetype":"postalcode"
},
  "geometry": {"coordinates":[-2.422453,53.587366],"type":"Point"}
}