{
  "type": "Feature",
  "properties": {
    "iso:country":"GB",
    "wof:name":"B21 0RD",
    "wof:placetype":"postalcode"
},
  "geometry": {"coordinates":[-1.93777567879207,52.50143199020028],"type":"Point"}
}