{
  "type": "Feature",
  "properties": {
    "iso:country":"GB",
    "wof:name":"SA14 8DL",
    "wof:placetype":"postalcode"
},
  "geometry": {"coordinates":[-4.13885091673643,51.70321443033739],"type":"Point"}
}