{
  "type": "Feature",
  "properties": {
    "iso:country":"GB",
    "wof:name":"TW9 1YS",
    "wof:placetype":"postalcode"
},
  "geometry": {"coordinates":[-0.29243209091265,51.46188325183973],"type":"Point"}
}