{
  "type": "Feature",
  "properties": {
    "date:inception_lower": "2009-08-01",
    "date:inception_upper": "2009-08-01",
    "iso:country": "GB",
    "wof:name": "PA16 0GG",
    "wof:placetype": "postalcode"
  },
  "geometry": {"coordinates":[-4.857055,55.904939],"type":"Point"}
}
