{
  "type": "Feature",
  "properties": {
    "iso:country": "GB",
    "wof:name": "PA16 0GG",
    "wof:placetype": "postalcode"
  },
  "geometry": {"coordinates":[-4.857079,55.904999],"type":"Point"}
}
