{
  "type": "Feature",
  "properties": {
    "iso:country":"GB",
    "wof:name":"PA16 0GG",
    "wof:placetype":"postalcode"
},
  "geometry": {"coordinates":[-4.85707876424048,55.90499876555005],"type":"Point"}
}