{
  "type": "Feature",
  "properties": {
    "iso:country": "GB",
    "wof:name": "OL8 3HX",
    "wof:placetype": "postalcode"
  },
  "geometry": {"coordinates":[-2.107098,53.5116],"type":"Point"}
}
