{
  "type": "Feature",
  "properties": {
    "iso:country":"GB",
    "wof:name":"UB3 1LU",
    "wof:placetype":"postalcode"
},
  "geometry": {"coordinates":[-0.43022455541853,51.49966107839914],"type":"Point"}
}