{
  "type": "Feature",
  "properties": {
    "iso:country":"GB",
    "wof:name":"UB4 8NU",
    "wof:placetype":"postalcode"
},
  "geometry": {"coordinates":[-0.42061985188352,51.53327089377346],"type":"Point"}
}