{
  "type": "Feature",
  "properties": {
    "date:inception_lower": "1980-01-01",
    "date:inception_upper": "1980-01-01",
    "iso:country": "GB",
    "wof:name": "LS28 8DS",
    "wof:placetype": "postalcode"
  },
  "geometry": {"coordinates":[-1.663176,53.783995],"type":"Point"}
}
