{
  "type": "Feature",
  "properties": {
    "iso:country": "GB",
    "wof:name": "BL2 5AE",
    "wof:placetype": "postalcode"
  },
  "geometry": {"coordinates":[-2.395295,53.587756],"type":"Point"}
}
