{
  "type": "Feature",
  "properties": {
    "iso:country":"GB",
    "wof:name":"BB9 8EA",
    "wof:placetype":"postalcode"
},
  "geometry": {"coordinates":[-2.20586659330323,53.83989003060951],"type":"Point"}
}