{
  "type": "Feature",
  "properties": {
    "iso:country":"GB",
    "wof:name":"EH39 5HJ",
    "wof:placetype":"postalcode"
},
  "geometry": {"coordinates":[-2.75664529159785,56.0563574447491],"type":"Point"}
}