{
  "type": "Feature",
  "properties": {
    "iso:country": "GB",
    "wof:name": "HU3 4AR",
    "wof:placetype": "postalcode"
  },
  "geometry": {"coordinates":[-0.358131,53.733623],"type":"Point"}
}
