{
  "type": "Feature",
  "properties": {
    "iso:country":"GB",
    "wof:name":"AB13 0DS",
    "wof:placetype":"postalcode"
},
  "geometry": {"coordinates":[-2.2349699043887,57.10541494721135],"type":"Point"}
}