{
  "type": "Feature",
  "properties": {
    "iso:country": "GB",
    "wof:name": "BR6 8BS",
    "wof:placetype": "postalcode"
  },
  "geometry": {"coordinates":[0.082691,51.374748],"type":"Point"}
}
