{
  "type": "Feature",
  "properties": {
    "iso:country":"GB",
    "wof:name":"BR6 8BS",
    "wof:placetype":"postalcode"
},
  "geometry": {"coordinates":[0.08269064634189,51.37474819097613],"type":"Point"}
}