{
  "type": "Feature",
  "properties": {
    "iso:country":"GB",
    "wof:name":"KA6 7PQ",
    "wof:placetype":"postalcode"
},
  "geometry": {"coordinates":[-4.49900082990952,55.35742069602814],"type":"Point"}
}