{
  "type": "Feature",
  "properties": {
    "iso:country": "GB",
    "wof:name": "TS10 3JA",
    "wof:placetype": "postalcode"
  },
  "geometry": {"coordinates":[-1.061795,54.616802],"type":"Point"}
}
