{
  "type": "Feature",
  "properties": {
    "date:inception_lower":"1980-01-01",
    "date:inception_upper":"1980-01-31",
    "iso:country":"GB",
    "wof:name":"TS10 3JA",
    "wof:placetype":"postalcode"
},
  "geometry": {"coordinates":[-1.061795,54.616802],"type":"Point"}
}