{
  "type": "Feature",
  "properties": {
    "iso:country":"GB",
    "wof:name":"TS10 3JA",
    "wof:placetype":"postalcode"
},
  "geometry": {"coordinates":[-1.0617953447964,54.61680218193006],"type":"Point"}
}