{
  "type": "Feature",
  "properties": {
    "iso:country":"GB",
    "wof:name":"SW18 4FR",
    "wof:placetype":"postalcode"
},
  "geometry": {"coordinates":[-0.18970780067624,51.44324733765292],"type":"Point"}
}