{
  "type": "Feature",
  "properties": {
    "iso:country":"GB",
    "wof:name":"TN15 0RX",
    "wof:placetype":"postalcode"
},
  "geometry": {"coordinates":[0.21988576681052,51.25137762816539],"type":"Point"}
}