{
  "type": "Feature",
  "properties": {
    "date:inception_lower":"1980-01-01",
    "date:inception_upper":"1980-01-31",
    "iso:country":"GB",
    "wof:name":"GU34 2RD",
    "wof:placetype":"postalcode"
},
  "geometry": {"coordinates":[-0.967925,51.153388],"type":"Point"}
}