{
  "type": "Feature",
  "properties": {
    "iso:country":"GB",
    "wof:name":"GU34 2RD",
    "wof:placetype":"postalcode"
},
  "geometry": {"coordinates":[-0.96792531666893,51.15338781039773],"type":"Point"}
}