{
  "type": "Feature",
  "properties": {
    "date:inception_lower": "2021-05-01",
    "date:inception_upper": "2021-05-01",
    "iso:country": "GB",
    "wof:name": "DE65 5RB",
    "wof:placetype": "postalcode"
  },
  "geometry": {"coordinates":[-1.624368,52.863237],"type":"Point"}
}
