{
  "type": "Feature",
  "properties": {
    "date:inception_lower":"1980-01-01",
    "date:inception_upper":"1980-01-31",
    "iso:country":"GB",
    "wof:name":"SN10 5JH",
    "wof:placetype":"postalcode"
},
  "geometry": {"coordinates":[-2.000468,51.34478],"type":"Point"}
}