{
  "type": "Feature",
  "properties": {
    "iso:country": "GB",
    "wof:name": "SN10 5JH",
    "wof:placetype": "postalcode"
  },
  "geometry": {"coordinates":[-2.000468,51.34478],"type":"Point"}
}
