{
  "type": "Feature",
  "properties": {
    "iso:country": "GB",
    "wof:name": "PA19 1NA",
    "wof:placetype": "postalcode"
  },
  "geometry": {"coordinates":[-4.819241,55.961982],"type":"Point"}
}
