{
  "type": "Feature",
  "properties": {
    "date:inception_lower": "1980-01-01",
    "date:inception_upper": "1980-01-01",
    "iso:country": "GB",
    "wof:name": "PA19 1NA",
    "wof:placetype": "postalcode"
  },
  "geometry": {"coordinates":[-4.819241,55.961982],"type":"Point"}
}
