{
  "type": "Feature",
  "properties": {
    "iso:country": "GB",
    "wof:name": "RG40 3NH",
    "wof:placetype": "postalcode"
  },
  "geometry": {"coordinates":[-0.836064,51.379276],"type":"Point"}
}
