{
  "type": "Feature",
  "properties": {
    "iso:country": "GB",
    "wof:name": "PO14 3SZ",
    "wof:placetype": "postalcode"
  },
  "geometry": {"coordinates":[-1.223692,50.824542],"type":"Point"}
}
