{
  "type": "Feature",
  "properties": {
    "iso:country":"GB",
    "wof:name":"B15 3XA",
    "wof:placetype":"postalcode"
},
  "geometry": {"coordinates":[-1.94934573354054,52.47039518620794],"type":"Point"}
}