{
  "type": "Feature",
  "properties": {
    "iso:country": "GB",
    "wof:name": "TD8 6HQ",
    "wof:placetype": "postalcode"
  },
  "geometry": {"coordinates":[-2.548001,55.480739],"type":"Point"}
}
