{
  "type": "Feature",
  "properties": {
    "iso:country":"GB",
    "wof:name":"TD8 6HQ",
    "wof:placetype":"postalcode"
},
  "geometry": {"coordinates":[-2.54800056939394,55.48073864130741],"type":"Point"}
}