{
  "type": "Feature",
  "properties": {
    "iso:country":"GB",
    "wof:name":"W8 4RR",
    "wof:placetype":"postalcode"
},
  "geometry": {"coordinates":[-0.19251761860363,51.5069036473292],"type":"Point"}
}