{
  "type": "Feature",
  "properties": {
    "iso:country": "GB",
    "wof:name": "LN7 6RB",
    "wof:placetype": "postalcode"
  },
  "geometry": {"coordinates":[-0.309916,53.49868],"type":"Point"}
}
