{
  "type": "Feature",
  "properties": {
    "iso:country":"GB",
    "wof:name":"LS6 1LL",
    "wof:placetype":"postalcode"
},
  "geometry": {"coordinates":[-1.57534758489548,53.80953936394934],"type":"Point"}
}