{
  "type": "Feature",
  "properties": {
    "iso:country":"GB",
    "wof:name":"W1K 7QW",
    "wof:placetype":"postalcode"
},
  "geometry": {"coordinates":[-0.15560111621339,51.51113989586848],"type":"Point"}
}