{
  "type": "Feature",
  "properties": {
    "date:inception_lower": "2000-12-01",
    "date:inception_upper": "2000-12-01",
    "iso:country": "GB",
    "wof:name": "W1K 7QW",
    "wof:placetype": "postalcode"
  },
  "geometry": {"coordinates":[-0.155719,51.511162],"type":"Point"}
}
