{
  "type": "Feature",
  "properties": {
    "iso:country":"GB",
    "wof:name":"BD10 8PF",
    "wof:placetype":"postalcode"
},
  "geometry": {"coordinates":[-1.72906257434238,53.83987863163677],"type":"Point"}
}