{
  "type": "Feature",
  "properties": {
    "iso:country": "GB",
    "wof:name": "BD10 8PF",
    "wof:placetype": "postalcode"
  },
  "geometry": {"coordinates":[-1.729063,53.839879],"type":"Point"}
}
