{
  "type": "Feature",
  "properties": {
    "iso:country":"GB",
    "wof:name":"HD2 1AJ",
    "wof:placetype":"postalcode"
},
  "geometry": {"coordinates":[-1.77760761433892,53.66339918450863],"type":"Point"}
}