{
  "type": "Feature",
  "properties": {
    "iso:country":"GB",
    "wof:name":"LL12 0RE",
    "wof:placetype":"postalcode"
},
  "geometry": {"coordinates":[-3.0019910813393,53.09375185506435],"type":"Point"}
}