{
  "type": "Feature",
  "properties": {
    "iso:country": "GB",
    "wof:name": "LL12 0RE",
    "wof:placetype": "postalcode"
  },
  "geometry": {"coordinates":[-3.001991,53.093752],"type":"Point"}
}
