{
  "type": "Feature",
  "properties": {
    "iso:country":"GB",
    "wof:name":"TR12 6DT",
    "wof:placetype":"postalcode"
},
  "geometry": {"coordinates":[-5.13198416485478,50.06312845383225],"type":"Point"}
}