{
  "type": "Feature",
  "properties": {
    "iso:country":"GB",
    "wof:name":"YO8 8BP",
    "wof:placetype":"postalcode"
},
  "geometry": {"coordinates":[-1.05911107631915,53.78008624371815],"type":"Point"}
}