{
  "type": "Feature",
  "properties": {
    "iso:country":"GB",
    "wof:name":"SY20 9TG",
    "wof:placetype":"postalcode"
},
  "geometry": {"coordinates":[-3.83868648568716,52.65190821406951],"type":"Point"}
}