{
  "type": "Feature",
  "properties": {
    "date:inception_lower": "1983-01-01",
    "date:inception_upper": "1983-01-01",
    "iso:country": "GB",
    "wof:name": "SY20 9TG",
    "wof:placetype": "postalcode"
  },
  "geometry": {"coordinates":[-3.838686,52.651908],"type":"Point"}
}
