{
  "type": "Feature",
  "properties": {
    "iso:country": "GB",
    "wof:name": "SP7 8GS",
    "wof:placetype": "postalcode"
  },
  "geometry": {"coordinates":[-2.180412,51.004987],"type":"Point"}
}
