{
  "type": "Feature",
  "properties": {
    "iso:country":"GB",
    "wof:name":"SP7 8GS",
    "wof:placetype":"postalcode"
},
  "geometry": {"coordinates":[-2.18041177313124,51.00498693022384],"type":"Point"}
}