{
  "type": "Feature",
  "properties": {
    "iso:country":"GB",
    "wof:name":"ST4 2HB",
    "wof:placetype":"postalcode"
},
  "geometry": {"coordinates":[-2.16323871139368,53.00036337858746],"type":"Point"}
}