{
  "type": "Feature",
  "properties": {
    "date:inception_lower":"1980-01-01",
    "date:inception_upper":"1980-01-31",
    "iso:country":"GB",
    "wof:name":"ST4 2HB",
    "wof:placetype":"postalcode"
},
  "geometry": {"coordinates":[-2.163239,53.000363],"type":"Point"}
}