{
  "type": "Feature",
  "properties": {
    "iso:country": "GB",
    "wof:name": "ML9 2JD",
    "wof:placetype": "postalcode"
  },
  "geometry": {"coordinates":[-3.962995,55.737096],"type":"Point"}
}
