{
  "type": "Feature",
  "properties": {
    "iso:country":"GB",
    "wof:name":"LL49 9NL",
    "wof:placetype":"postalcode"
},
  "geometry": {"coordinates":[-4.12864788997206,52.92555300892942],"type":"Point"}
}