{
  "type": "Feature",
  "properties": {
    "iso:country":"GB",
    "wof:name":"W1U 6DG",
    "wof:placetype":"postalcode"
},
  "geometry": {"coordinates":[-0.15766749561359,51.52136085551095],"type":"Point"}
}