{
  "type": "Feature",
  "properties": {
    "iso:country":"GB",
    "wof:name":"RM10 9JJ",
    "wof:placetype":"postalcode"
},
  "geometry": {"coordinates":[0.1496752336139,51.53367546746066],"type":"Point"}
}