{
  "type": "Feature",
  "properties": {
    "date:inception_lower": "1995-07-01",
    "date:inception_upper": "1995-07-01",
    "iso:country": "GB",
    "wof:name": "KT22 7LQ",
    "wof:placetype": "postalcode"
  },
  "geometry": {"coordinates":[-0.328432,51.297093],"type":"Point"}
}
