{
  "type": "Feature",
  "properties": {
    "iso:country": "GB",
    "wof:name": "KT22 7LQ",
    "wof:placetype": "postalcode"
  },
  "geometry": {"coordinates":[-0.328432,51.297093],"type":"Point"}
}
