{
  "type": "Feature",
  "properties": {
    "iso:country": "GB",
    "wof:name": "PR7 6LE",
    "wof:placetype": "postalcode"
  },
  "geometry": {"coordinates":[-2.680276,53.669285],"type":"Point"}
}
