{
  "type": "Feature",
  "properties": {
    "date:inception_lower": "1986-07-01",
    "date:inception_upper": "1986-07-01",
    "iso:country": "GB",
    "wof:name": "PR7 6LE",
    "wof:placetype": "postalcode"
  },
  "geometry": {"coordinates":[-2.680276,53.669285],"type":"Point"}
}
