{
  "type": "Feature",
  "properties": {
    "iso:country":"GB",
    "wof:name":"PR7 6LE",
    "wof:placetype":"postalcode"
},
  "geometry": {"coordinates":[-2.68027640760945,53.66928460075616],"type":"Point"}
}