{
  "type": "Feature",
  "properties": {
    "iso:country": "GB",
    "wof:name": "YO8 5RF",
    "wof:placetype": "postalcode"
  },
  "geometry": {"coordinates":[-0.965339,53.826341],"type":"Point"}
}
