{
  "type": "Feature",
  "properties": {
    "iso:country":"GB",
    "wof:name":"YO8 5RF",
    "wof:placetype":"postalcode"
},
  "geometry": {"coordinates":[-0.96533888672021,53.82634116659354],"type":"Point"}
}