{
  "type": "Feature",
  "properties": {
    "iso:country":"GB",
    "wof:name":"DH9 7NQ",
    "wof:placetype":"postalcode"
},
  "geometry": {"coordinates":[-1.69704374312952,54.8613282154373],"type":"Point"}
}