{
  "type": "Feature",
  "properties": {
    "iso:country": "GB",
    "wof:name": "NE23 6HZ",
    "wof:placetype": "postalcode"
  },
  "geometry": {"coordinates":[-1.573768,55.075524],"type":"Point"}
}
