{
  "type": "Feature",
  "properties": {
    "iso:country":"GB",
    "wof:name":"NE23 6HZ",
    "wof:placetype":"postalcode"
},
  "geometry": {"coordinates":[-1.5737682288504,55.07552398694176],"type":"Point"}
}