{
  "type": "Feature",
  "properties": {
    "iso:country":"GB",
    "wof:name":"NP15 1AG",
    "wof:placetype":"postalcode"
},
  "geometry": {"coordinates":[-2.90160535699831,51.70227060033633],"type":"Point"}
}