{
  "type": "Feature",
  "properties": {
    "iso:country": "GB",
    "wof:name": "KT18 7BE",
    "wof:placetype": "postalcode"
  },
  "geometry": {"coordinates":[-0.275762,51.331131],"type":"Point"}
}
