{
  "type": "Feature",
  "properties": {
    "iso:country":"GB",
    "wof:name":"KT18 7BE",
    "wof:placetype":"postalcode"
},
  "geometry": {"coordinates":[-0.27576196763571,51.3311308201069],"type":"Point"}
}