{
  "type": "Feature",
  "properties": {
    "iso:country":"GB",
    "wof:name":"ML12 6FJ",
    "wof:placetype":"postalcode"
},
  "geometry": {"coordinates":[-3.47546751790863,55.65941377978616],"type":"Point"}
}