{
  "type": "Feature",
  "properties": {
    "iso:country": "GB",
    "wof:name": "CA7 9BL",
    "wof:placetype": "postalcode"
  },
  "geometry": {"coordinates":[-3.1686,54.82938],"type":"Point"}
}
