{
  "type": "Feature",
  "properties": {
    "date:inception_lower": "1980-01-01",
    "date:inception_upper": "1980-01-01",
    "iso:country": "GB",
    "wof:name": "CA7 9BL",
    "wof:placetype": "postalcode"
  },
  "geometry": {"coordinates":[-3.1686,54.82938],"type":"Point"}
}
