{
  "type": "Feature",
  "properties": {
    "iso:country": "GB",
    "wof:name": "RH10 1BU",
    "wof:placetype": "postalcode"
  },
  "geometry": {"coordinates":[-0.190511,51.11528],"type":"Point"}
}
