{
  "type": "Feature",
  "properties": {
    "iso:country":"GB",
    "wof:name":"LU7 0DE",
    "wof:placetype":"postalcode"
},
  "geometry": {"coordinates":[-0.71766444981466,51.93965495282484],"type":"Point"}
}