{
  "type": "Feature",
  "properties": {
    "date:inception_lower":"1980-01-01",
    "date:inception_upper":"1980-01-31",
    "iso:country":"GB",
    "wof:name":"SN16 0JE",
    "wof:placetype":"postalcode"
},
  "geometry": {"coordinates":[-2.10877,51.582241],"type":"Point"}
}