{
  "type": "Feature",
  "properties": {
    "iso:country": "GB",
    "wof:name": "WA6 6QF",
    "wof:placetype": "postalcode"
  },
  "geometry": {"coordinates":[-2.713741,53.288699],"type":"Point"}
}
