{
  "type": "Feature",
  "properties": {
    "date:inception_lower":"1980-01-01",
    "date:inception_upper":"1980-01-31",
    "iso:country":"GB",
    "wof:name":"HR9 5UE",
    "wof:placetype":"postalcode"
},
  "geometry": {"coordinates":[-2.591925,51.905209],"type":"Point"}
}