{
  "type": "Feature",
  "properties": {
    "iso:country":"GB",
    "wof:name":"HR9 5UE",
    "wof:placetype":"postalcode"
},
  "geometry": {"coordinates":[-2.59192529756218,51.90520881435982],"type":"Point"}
}