{
  "type": "Feature",
  "properties": {
    "iso:country":"GB",
    "wof:name":"DT10 1JR",
    "wof:placetype":"postalcode"
},
  "geometry": {"coordinates":[-2.32575676474601,50.97648097968077],"type":"Point"}
}