{
  "type": "Feature",
  "properties": {
    "iso:country":"GB",
    "wof:name":"SK7 4RY",
    "wof:placetype":"postalcode"
},
  "geometry": {"coordinates":[-2.10370940713486,53.37706446601758],"type":"Point"}
}