{
  "type": "Feature",
  "properties": {
    "iso:country":"GB",
    "wof:name":"NP22 4DA",
    "wof:placetype":"postalcode"
},
  "geometry": {"coordinates":[-3.22289121679071,51.75442936955475],"type":"Point"}
}