{
  "type": "Feature",
  "properties": {
    "iso:country": "GB",
    "wof:name": "NP22 4DA",
    "wof:placetype": "postalcode"
  },
  "geometry": {"coordinates":[-3.222891,51.754429],"type":"Point"}
}
