{
  "type": "Feature",
  "properties": {
    "iso:country":"GB",
    "wof:name":"CR0 1BQ",
    "wof:placetype":"postalcode"
},
  "geometry": {"coordinates":[-0.09501568672729,51.36727810032391],"type":"Point"}
}