{
  "type": "Feature",
  "properties": {
    "iso:country": "GB",
    "wof:name": "NE30 3AH",
    "wof:placetype": "postalcode"
  },
  "geometry": {"coordinates":[-1.444189,55.029792],"type":"Point"}
}
