{
  "type": "Feature",
  "properties": {
    "iso:country":"GB",
    "wof:name":"NE30 3AH",
    "wof:placetype":"postalcode"
},
  "geometry": {"coordinates":[-1.44418908305455,55.02979216579156],"type":"Point"}
}