{
  "type": "Feature",
  "properties": {
    "iso:country":"GB",
    "wof:name":"ME4 5BS",
    "wof:placetype":"postalcode"
},
  "geometry": {"coordinates":[0.54110598485853,51.37350621058064],"type":"Point"}
}