{
  "type": "Feature",
  "properties": {
    "iso:country":"GB",
    "wof:name":"CH49 1RA",
    "wof:placetype":"postalcode"
},
  "geometry": {"coordinates":[-3.11724716142819,53.37676011164217],"type":"Point"}
}