{
  "type": "Feature",
  "properties": {
    "date:inception_lower":"1999-06-01",
    "date:inception_upper":"1999-06-30",
    "iso:country":"GB",
    "wof:name":"CH49 1RA",
    "wof:placetype":"postalcode"
},
  "geometry": {"coordinates":[-3.117247,53.37676],"type":"Point"}
}