{
  "type": "Feature",
  "properties": {
    "iso:country":"GB",
    "wof:name":"CV3 6PH",
    "wof:placetype":"postalcode"
},
  "geometry": {"coordinates":[-1.53257370176356,52.38763755981459],"type":"Point"}
}