{
  "type": "Feature",
  "properties": {
    "iso:country":"GB",
    "wof:name":"SW4 9EW",
    "wof:placetype":"postalcode"
},
  "geometry": {"coordinates":[-0.13773338403145,51.4548699275609],"type":"Point"}
}