{
  "type": "Feature",
  "properties": {
    "date:inception_lower": "1980-01-01",
    "date:inception_upper": "1980-01-01",
    "iso:country": "GB",
    "wof:name": "B79 0HB",
    "wof:placetype": "postalcode"
  },
  "geometry": {"coordinates":[-1.580974,52.645803],"type":"Point"}
}
