{
  "type": "Feature",
  "properties": {
    "iso:country":"GB",
    "wof:name":"SO16 4LP",
    "wof:placetype":"postalcode"
},
  "geometry": {"coordinates":[-1.44330262985976,50.92331988945752],"type":"Point"}
}