{
  "type": "Feature",
  "properties": {
    "iso:country": "GB",
    "wof:name": "SO16 4LP",
    "wof:placetype": "postalcode"
  },
  "geometry": {"coordinates":[-1.443303,50.92332],"type":"Point"}
}
