{
  "type": "Feature",
  "properties": {
    "iso:country": "GB",
    "wof:name": "SO15 1AS",
    "wof:placetype": "postalcode"
  },
  "geometry": {"coordinates":[-1.42269,50.909264],"type":"Point"}
}
