{
  "type": "Feature",
  "properties": {
    "iso:country":"GB",
    "wof:name":"SO15 1AS",
    "wof:placetype":"postalcode"
},
  "geometry": {"coordinates":[-1.42269015409776,50.9092635501101],"type":"Point"}
}