{
  "type": "Feature",
  "properties": {
    "iso:country":"GB",
    "wof:name":"NW11 7NU",
    "wof:placetype":"postalcode"
},
  "geometry": {"coordinates":[-0.19548426626536,51.57293561436736],"type":"Point"}
}