{
  "type": "Feature",
  "properties": {
    "iso:country":"GB",
    "wof:name":"CR4 1XD",
    "wof:placetype":"postalcode"
},
  "geometry": {"coordinates":[-0.13093746742014,51.40098581571082],"type":"Point"}
}