{
  "type": "Feature",
  "properties": {
    "iso:country":"GB",
    "wof:name":"RH1 1TU",
    "wof:placetype":"postalcode"
},
  "geometry": {"coordinates":[-0.15820251884753,51.24640051905303],"type":"Point"}
}