{
  "type": "Feature",
  "properties": {
    "iso:country": "GB",
    "wof:name": "RH1 1TU",
    "wof:placetype": "postalcode"
  },
  "geometry": {"coordinates":[-0.158202,51.246401],"type":"Point"}
}
