{
  "type": "Feature",
  "properties": {
    "date:inception_lower":"2014-07-01",
    "date:inception_upper":"2014-07-31",
    "iso:country":"GB",
    "wof:name":"EX14 3FD",
    "wof:placetype":"postalcode"
},
  "geometry": {"coordinates":[-3.277207,50.786289],"type":"Point"}
}