{
  "type": "Feature",
  "properties": {
    "iso:country":"GB",
    "wof:name":"EX14 3FD",
    "wof:placetype":"postalcode"
},
  "geometry": {"coordinates":[-3.27720732086176,50.78628877025164],"type":"Point"}
}