{
  "type": "Feature",
  "properties": {
    "iso:country":"GB",
    "wof:name":"NR10 4QE",
    "wof:placetype":"postalcode"
},
  "geometry": {"coordinates":[1.19419597233349,52.73897421338163],"type":"Point"}
}