{
  "type": "Feature",
  "properties": {
    "date:inception_lower": "1980-01-01",
    "date:inception_upper": "1980-01-01",
    "iso:country": "GB",
    "wof:name": "S42 5SA",
    "wof:placetype": "postalcode"
  },
  "geometry": {"coordinates":[-1.350518,53.186766],"type":"Point"}
}
