{
  "type": "Feature",
  "properties": {
    "iso:country":"GB",
    "wof:name":"S42 5SA",
    "wof:placetype":"postalcode"
},
  "geometry": {"coordinates":[-1.35051792703284,53.1867663045286],"type":"Point"}
}