{
  "type": "Feature",
  "properties": {
    "iso:country":"GB",
    "wof:name":"B63 3QL",
    "wof:placetype":"postalcode"
},
  "geometry": {"coordinates":[-2.0552936270402,52.45999146363584],"type":"Point"}
}