{
  "type": "Feature",
  "properties": {
    "iso:country":"GB",
    "wof:name":"RM17 5YG",
    "wof:placetype":"postalcode"
},
  "geometry": {"coordinates":[0.31663676596919,51.47858825147836],"type":"Point"}
}