{
  "type": "Feature",
  "properties": {
    "date:inception_lower": "2021-11-01",
    "date:inception_upper": "2021-11-01",
    "iso:country": "GB",
    "wof:name": "S63 0FP",
    "wof:placetype": "postalcode"
  },
  "geometry": {"coordinates":[-1.308336,53.549569],"type":"Point"}
}
