{
  "type": "Feature",
  "properties": {
    "iso:country":"GB",
    "wof:name":"BS16 9SW",
    "wof:placetype":"postalcode"
},
  "geometry": {"coordinates":[-2.4305856595053,51.48367321466763],"type":"Point"}
}