{
  "type": "Feature",
  "properties": {
    "iso:country":"GB",
    "wof:name":"CA3 9RZ",
    "wof:placetype":"postalcode"
},
  "geometry": {"coordinates":[-2.94947925966963,54.90967478011708],"type":"Point"}
}