{
  "type": "Feature",
  "properties": {
    "date:inception_lower": "1980-01-01",
    "date:inception_upper": "1980-01-01",
    "iso:country": "GB",
    "wof:name": "CA3 9RZ",
    "wof:placetype": "postalcode"
  },
  "geometry": {"coordinates":[-2.949561,54.909707],"type":"Point"}
}
