{
  "type": "Feature",
  "properties": {
    "iso:country":"GB",
    "wof:name":"LL12 7BT",
    "wof:placetype":"postalcode"
},
  "geometry": {"coordinates":[-2.98579745765309,53.05168177652828],"type":"Point"}
}