{
  "type": "Feature",
  "properties": {
    "date:inception_lower":"1980-01-01",
    "date:inception_upper":"1980-01-31",
    "iso:country":"GB",
    "wof:name":"L3 5SD",
    "wof:placetype":"postalcode"
},
  "geometry": {"coordinates":[-2.975063,53.403994],"type":"Point"}
}