{
  "type": "Feature",
  "properties": {
    "iso:country":"GB",
    "wof:name":"KA30 8DQ",
    "wof:placetype":"postalcode"
},
  "geometry": {"coordinates":[-4.87008436266397,55.79272826540911],"type":"Point"}
}