{
  "type": "Feature",
  "properties": {
    "date:inception_lower":"1987-04-01",
    "date:inception_upper":"1987-04-30",
    "iso:country":"GB",
    "wof:name":"E13 9HJ",
    "wof:placetype":"postalcode"
},
  "geometry": {"coordinates":[0.025082,51.529472],"type":"Point"}
}