{
  "type": "Feature",
  "properties": {
    "iso:country":"GB",
    "wof:name":"BH16 5SB",
    "wof:placetype":"postalcode"
},
  "geometry": {"coordinates":[-2.02633107431002,50.73193323619066],"type":"Point"}
}