{
  "type": "Feature",
  "properties": {
    "iso:country": "GB",
    "wof:name": "BH16 5SB",
    "wof:placetype": "postalcode"
  },
  "geometry": {"coordinates":[-2.026331,50.731933],"type":"Point"}
}
