{
  "type": "Feature",
  "properties": {
    "date:inception_lower": "1995-12-01",
    "date:inception_upper": "1995-12-01",
    "iso:country": "GB",
    "wof:name": "PH2 6ES",
    "wof:placetype": "postalcode"
  },
  "geometry": {"coordinates":[-3.319785,56.476709],"type":"Point"}
}
