{
  "type": "Feature",
  "properties": {
    "iso:country":"GB",
    "wof:name":"PH2 6ES",
    "wof:placetype":"postalcode"
},
  "geometry": {"coordinates":[-3.31978537565108,56.47670872455357],"type":"Point"}
}