{
  "type": "Feature",
  "properties": {
    "iso:country": "GB",
    "wof:name": "PE4 7XQ",
    "wof:placetype": "postalcode"
  },
  "geometry": {"coordinates":[-0.245941,52.60713],"type":"Point"}
}
