{
  "type": "Feature",
  "properties": {
    "iso:country":"GB",
    "wof:name":"PE4 7XQ",
    "wof:placetype":"postalcode"
},
  "geometry": {"coordinates":[-0.24594113544156,52.60713037134019],"type":"Point"}
}