{
  "type": "Feature",
  "properties": {
    "iso:country":"GB",
    "wof:name":"W1T 1NQ",
    "wof:placetype":"postalcode"
},
  "geometry": {"coordinates":[-0.13534041463333,51.51815742345203],"type":"Point"}
}