{
  "type": "Feature",
  "properties": {
    "iso:country":"GB",
    "wof:name":"NE9 6SR",
    "wof:placetype":"postalcode"
},
  "geometry": {"coordinates":[-1.58369733735488,54.93961471494796],"type":"Point"}
}