{
  "type": "Feature",
  "properties": {
    "date:inception_lower": "1980-01-01",
    "date:inception_upper": "1980-01-01",
    "iso:country": "GB",
    "wof:name": "NP44 2DF",
    "wof:placetype": "postalcode"
  },
  "geometry": {"coordinates":[-2.991683,51.655148],"type":"Point"}
}
