{
  "type": "Feature",
  "properties": {
    "iso:country":"GB",
    "wof:name":"NP44 2DF",
    "wof:placetype":"postalcode"
},
  "geometry": {"coordinates":[-2.99168306587055,51.65514846376286],"type":"Point"}
}