{
  "type": "Feature",
  "properties": {
    "iso:country":"GB",
    "wof:name":"GU51 1BQ",
    "wof:placetype":"postalcode"
},
  "geometry": {"coordinates":[-0.86289162509843,51.29102097842322],"type":"Point"}
}