{
  "type": "Feature",
  "properties": {
    "iso:country":"GB",
    "wof:name":"WA2 8ED",
    "wof:placetype":"postalcode"
},
  "geometry": {"coordinates":[-2.57805009280818,53.40468859154837],"type":"Point"}
}