{
  "type": "Feature",
  "properties": {
    "iso:country":"GB",
    "wof:name":"DE21 4JX",
    "wof:placetype":"postalcode"
},
  "geometry": {"coordinates":[-1.44427434194964,52.93859942571271],"type":"Point"}
}