{
  "type": "Feature",
  "properties": {
    "iso:country":"GB",
    "wof:name":"NG23 5EQ",
    "wof:placetype":"postalcode"
},
  "geometry": {"coordinates":[-0.75332381658755,52.99213623787761],"type":"Point"}
}