{
  "type": "Feature",
  "properties": {
    "iso:country":"GB",
    "wof:name":"S70 1LP",
    "wof:placetype":"postalcode"
},
  "geometry": {"coordinates":[-1.48095455277034,53.549273172897],"type":"Point"}
}