{
  "type": "Feature",
  "properties": {
    "iso:country":"GB",
    "wof:name":"KT3 5NX",
    "wof:placetype":"postalcode"
},
  "geometry": {"coordinates":[-0.26384438574485,51.38668182779028],"type":"Point"}
}