{
  "type": "Feature",
  "properties": {
    "iso:country":"GB",
    "wof:name":"CB10 2PP",
    "wof:placetype":"postalcode"
},
  "geometry": {"coordinates":[0.41732419604927,52.03202188943352],"type":"Point"}
}