{
  "type": "Feature",
  "properties": {
    "date:inception_lower": "1980-01-01",
    "date:inception_upper": "1980-01-01",
    "iso:country": "GB",
    "wof:name": "CB10 2PP",
    "wof:placetype": "postalcode"
  },
  "geometry": {"coordinates":[0.417324,52.032022],"type":"Point"}
}
