{
  "type": "Feature",
  "properties": {
    "iso:country":"GB",
    "wof:name":"EX2 7LB",
    "wof:placetype":"postalcode"
},
  "geometry": {"coordinates":[-3.47186766435902,50.71647317160013],"type":"Point"}
}