{
  "type": "Feature",
  "properties": {
    "iso:country":"GB",
    "wof:name":"BL2 1AY",
    "wof:placetype":"postalcode"
},
  "geometry": {"coordinates":[-2.42574096842444,53.57633511255231],"type":"Point"}
}