{
  "type": "Feature",
  "properties": {
    "date:inception_lower":"1999-06-01",
    "date:inception_upper":"1999-06-30",
    "iso:country":"GB",
    "wof:name":"CF10 5HN",
    "wof:placetype":"postalcode"
},
  "geometry": {"coordinates":[-3.17068,51.471659],"type":"Point"}
}