{
  "type": "Feature",
  "properties": {
    "iso:country":"GB",
    "wof:name":"CF10 5HN",
    "wof:placetype":"postalcode"
},
  "geometry": {"coordinates":[-3.17067997282476,51.47165910647904],"type":"Point"}
}