{
  "type": "Feature",
  "properties": {
    "date:inception_lower": "2009-02-01",
    "date:inception_upper": "2009-02-01",
    "iso:country": "GB",
    "wof:name": "WA11 0AD",
    "wof:placetype": "postalcode"
  },
  "geometry": {"coordinates":[-2.701533,53.463541],"type":"Point"}
}
