{
  "type": "Feature",
  "properties": {
    "date:inception_lower": "1980-01-01",
    "date:inception_upper": "1980-01-01",
    "iso:country": "GB",
    "wof:name": "NE30 1PW",
    "wof:placetype": "postalcode"
  },
  "geometry": {"coordinates":[-1.444736,55.0106],"type":"Point"}
}
