{
  "type": "Feature",
  "properties": {
    "iso:country":"GB",
    "wof:name":"SP10 4LW",
    "wof:placetype":"postalcode"
},
  "geometry": {"coordinates":[-1.48822478384695,51.22185051687951],"type":"Point"}
}