{
  "type": "Feature",
  "properties": {
    "iso:country":"GB",
    "wof:name":"SA18 1UF",
    "wof:placetype":"postalcode"
},
  "geometry": {"coordinates":[-3.89416855517559,51.8016992828267],"type":"Point"}
}