{
  "type": "Feature",
  "properties": {
    "iso:country": "GB",
    "wof:name": "SA18 1UF",
    "wof:placetype": "postalcode"
  },
  "geometry": {"coordinates":[-3.894169,51.801699],"type":"Point"}
}
