{
  "type": "Feature",
  "properties": {
    "date:inception_lower": "1980-01-01",
    "date:inception_upper": "1980-01-01",
    "iso:country": "GB",
    "wof:name": "SS4 1RA",
    "wof:placetype": "postalcode"
  },
  "geometry": {"coordinates":[0.70355,51.585473],"type":"Point"}
}
