{
  "type": "Feature",
  "properties": {
    "iso:country": "GB",
    "wof:name": "SS4 1RA",
    "wof:placetype": "postalcode"
  },
  "geometry": {"coordinates":[0.70355,51.585473],"type":"Point"}
}
