{
  "type": "Feature",
  "properties": {
    "iso:country":"GB",
    "wof:name":"PO14 4JE",
    "wof:placetype":"postalcode"
},
  "geometry": {"coordinates":[-1.23713298917847,50.84486420666315],"type":"Point"}
}