{
  "type": "Feature",
  "properties": {
    "date:inception_lower":"2001-06-01",
    "date:inception_upper":"2001-06-30",
    "iso:country":"GB",
    "wof:name":"BA2 7WS",
    "wof:placetype":"postalcode"
},
  "geometry": {"coordinates":[-2.301888,51.340452],"type":"Point"}
}