{
  "type": "Feature",
  "properties": {
    "iso:country":"GB",
    "wof:name":"BA2 7WS",
    "wof:placetype":"postalcode"
},
  "geometry": {"coordinates":[-2.3018881695135,51.34045212946447],"type":"Point"}
}