{
  "type": "Feature",
  "properties": {
    "iso:country":"GB",
    "wof:name":"BD13 2EX",
    "wof:placetype":"postalcode"
},
  "geometry": {"coordinates":[-1.85089441746126,53.76760374956292],"type":"Point"}
}