{
  "type": "Feature",
  "properties": {
    "date:inception_lower":"1980-01-01",
    "date:inception_upper":"1980-01-31",
    "iso:country":"GB",
    "wof:name":"ST2 0LQ",
    "wof:placetype":"postalcode"
},
  "geometry": {"coordinates":[-2.122474,53.011928],"type":"Point"}
}