{
  "type": "Feature",
  "properties": {
    "iso:country":"GB",
    "wof:name":"ST2 0LQ",
    "wof:placetype":"postalcode"
},
  "geometry": {"coordinates":[-2.12247387378559,53.01192755369944],"type":"Point"}
}