{
  "type": "Feature",
  "properties": {
    "iso:country": "GB",
    "wof:name": "ST2 0LQ",
    "wof:placetype": "postalcode"
  },
  "geometry": {"coordinates":[-2.122474,53.011928],"type":"Point"}
}
