{
  "type": "Feature",
  "properties": {
    "iso:country":"GB",
    "wof:name":"BN3 5QT",
    "wof:placetype":"postalcode"
},
  "geometry": {"coordinates":[-0.18955215076941,50.83362926880996],"type":"Point"}
}