{
  "type": "Feature",
  "properties": {
    "date:inception_lower": "1999-12-01",
    "date:inception_upper": "1999-12-01",
    "iso:country": "GB",
    "wof:name": "PO30 2EH",
    "wof:placetype": "postalcode"
  },
  "geometry": {"coordinates":[-1.291091,50.706051],"type":"Point"}
}
