{
  "type": "Feature",
  "properties": {
    "date:inception_lower":"1980-01-01",
    "date:inception_upper":"1980-01-31",
    "iso:country":"GB",
    "wof:name":"KA8 0BW",
    "wof:placetype":"postalcode"
},
  "geometry": {"coordinates":[-4.625378,55.465405],"type":"Point"}
}