{
  "type": "Feature",
  "properties": {
    "iso:country": "GB",
    "wof:name": "KA8 0BW",
    "wof:placetype": "postalcode"
  },
  "geometry": {"coordinates":[-4.625378,55.465405],"type":"Point"}
}
