{
  "type": "Feature",
  "properties": {
    "iso:country":"GB",
    "wof:name":"CM14 4SS",
    "wof:placetype":"postalcode"
},
  "geometry": {"coordinates":[0.29929084174994,51.62119936688883],"type":"Point"}
}