{
  "type": "Feature",
  "properties": {
    "iso:country":"GB",
    "wof:name":"PA1 2UL",
    "wof:placetype":"postalcode"
},
  "geometry": {"coordinates":[-4.44424650517157,55.83987484665259],"type":"Point"}
}