{
  "type": "Feature",
  "properties": {
    "iso:country":"GB",
    "wof:name":"DN5 9DE",
    "wof:placetype":"postalcode"
},
  "geometry": {"coordinates":[-1.17143674628268,53.54731435568828],"type":"Point"}
}