{
  "type": "Feature",
  "properties": {
    "iso:country": "GB",
    "wof:name": "DN5 9DE",
    "wof:placetype": "postalcode"
  },
  "geometry": {"coordinates":[-1.171121,53.547386],"type":"Point"}
}
