{
  "type": "Feature",
  "properties": {
    "iso:country": "GB",
    "wof:name": "CT11 7BE",
    "wof:placetype": "postalcode"
  },
  "geometry": {"coordinates":[1.416954,51.347981],"type":"Point"}
}
