{
  "type": "Feature",
  "properties": {
    "iso:country":"GB",
    "wof:name":"CT11 7BE",
    "wof:placetype":"postalcode"
},
  "geometry": {"coordinates":[1.41695406011755,51.34798101086349],"type":"Point"}
}