{
  "type": "Feature",
  "properties": {
    "iso:country":"GB",
    "wof:name":"NG31 7FP",
    "wof:placetype":"postalcode"
},
  "geometry": {"coordinates":[-0.64868049094761,52.89930482779567],"type":"Point"}
}