{
  "type": "Feature",
  "properties": {
    "date:inception_lower": "2004-09-01",
    "date:inception_upper": "2004-09-01",
    "iso:country": "GB",
    "wof:name": "DE73 7JG",
    "wof:placetype": "postalcode"
  },
  "geometry": {"coordinates":[-1.481829,52.811451],"type":"Point"}
}
