{
  "type": "Feature",
  "properties": {
    "iso:country": "GB",
    "wof:name": "LE6 0FZ",
    "wof:placetype": "postalcode"
  },
  "geometry": {"coordinates":[-1.238909,52.644803],"type":"Point"}
}
