{
  "type": "Feature",
  "properties": {
    "date:inception_lower": "2012-07-01",
    "date:inception_upper": "2012-07-01",
    "iso:country": "GB",
    "wof:name": "NP4 5YL",
    "wof:placetype": "postalcode"
  },
  "geometry": {"coordinates":[-3.019073,51.678193],"type":"Point"}
}
