{
  "type": "Feature",
  "properties": {
    "iso:country":"GB",
    "wof:name":"NP4 5YL",
    "wof:placetype":"postalcode"
},
  "geometry": {"coordinates":[-3.01907348033818,51.67819299699168],"type":"Point"}
}