{
  "type": "Feature",
  "properties": {
    "iso:country": "GB",
    "wof:name": "NP4 5YL",
    "wof:placetype": "postalcode"
  },
  "geometry": {"coordinates":[-3.019073,51.678193],"type":"Point"}
}
