{
  "type": "Feature",
  "properties": {
    "date:inception_lower": "1980-01-01",
    "date:inception_upper": "1980-01-01",
    "iso:country": "GB",
    "wof:name": "CM3 6BE",
    "wof:placetype": "postalcode"
  },
  "geometry": {"coordinates":[0.77026,51.679306],"type":"Point"}
}
