{
  "type": "Feature",
  "properties": {
    "iso:country":"GB",
    "wof:name":"CM3 6BE",
    "wof:placetype":"postalcode"
},
  "geometry": {"coordinates":[0.77026038150431,51.67930594334899],"type":"Point"}
}