{
  "type": "Feature",
  "properties": {
    "iso:country":"GB",
    "wof:name":"NG16 4JB",
    "wof:placetype":"postalcode"
},
  "geometry": {"coordinates":[-1.32912789868542,53.02477076668106],"type":"Point"}
}