{
  "type": "Feature",
  "properties": {
    "iso:country":"GB",
    "wof:name":"AB41 7DR",
    "wof:placetype":"postalcode"
},
  "geometry": {"coordinates":[-2.18511311964051,57.43148632805078],"type":"Point"}
}