{
  "type": "Feature",
  "properties": {
    "iso:country":"GB",
    "wof:name":"LS19 7XE",
    "wof:placetype":"postalcode"
},
  "geometry": {"coordinates":[-1.68032484088465,53.87195348413007],"type":"Point"}
}