{
  "type": "Feature",
  "properties": {
    "iso:country":"GB",
    "wof:name":"HU11 4UA",
    "wof:placetype":"postalcode"
},
  "geometry": {"coordinates":[-0.18541844653884,53.84833482660119],"type":"Point"}
}