{
  "type": "Feature",
  "properties": {
    "date:inception_lower":"1980-01-01",
    "date:inception_upper":"1980-01-31",
    "iso:country":"GB",
    "wof:name":"HU11 4UA",
    "wof:placetype":"postalcode"
},
  "geometry": {"coordinates":[-0.185418,53.848335],"type":"Point"}
}