{
  "type": "Feature",
  "properties": {
    "iso:country":"GB",
    "wof:name":"SS9 2AR",
    "wof:placetype":"postalcode"
},
  "geometry": {"coordinates":[0.65308873133306,51.54449290308379],"type":"Point"}
}