{
  "type": "Feature",
  "properties": {
    "iso:country":"GB",
    "wof:name":"PR7 7DF",
    "wof:placetype":"postalcode"
},
  "geometry": {"coordinates":[-2.65416615268695,53.6819148970848],"type":"Point"}
}