{
  "type": "Feature",
  "properties": {
    "date:inception_lower":"2007-10-01",
    "date:inception_upper":"2007-10-31",
    "iso:country":"GB",
    "wof:name":"PR7 7DF",
    "wof:placetype":"postalcode"
},
  "geometry": {"coordinates":[-2.654166,53.681915],"type":"Point"}
}