{
  "type": "Feature",
  "properties": {
    "iso:country":"GB",
    "wof:name":"PL11 2JL",
    "wof:placetype":"postalcode"
},
  "geometry": {"coordinates":[-4.20383164284385,50.37816930053035],"type":"Point"}
}