{
  "type": "Feature",
  "properties": {
    "iso:country":"GB",
    "wof:name":"W1J 6JH",
    "wof:placetype":"postalcode"
},
  "geometry": {"coordinates":[-0.143800875892,51.51071993195467],"type":"Point"}
}