{
  "type": "Feature",
  "properties": {
    "iso:country": "GB",
    "wof:name": "W1J 6JH",
    "wof:placetype": "postalcode"
  },
  "geometry": {"coordinates":[-0.143801,51.51072],"type":"Point"}
}
