{
  "type": "Feature",
  "properties": {
    "iso:country":"GB",
    "wof:name":"L6 9JG",
    "wof:placetype":"postalcode"
},
  "geometry": {"coordinates":[-2.95051573721912,53.41281186946136],"type":"Point"}
}