{
  "type": "Feature",
  "properties": {
    "iso:country": "GB",
    "wof:name": "L6 9JG",
    "wof:placetype": "postalcode"
  },
  "geometry": {"coordinates":[-2.950516,53.412812],"type":"Point"}
}
