{
  "type": "Feature",
  "properties": {
    "iso:country":"GB",
    "wof:name":"GL54 1AS",
    "wof:placetype":"postalcode"
},
  "geometry": {"coordinates":[-1.71215819952032,51.93152162217958],"type":"Point"}
}