{
  "type": "Feature",
  "properties": {
    "iso:country": "GB",
    "wof:name": "GL54 1AS",
    "wof:placetype": "postalcode"
  },
  "geometry": {"coordinates":[-1.712158,51.931522],"type":"Point"}
}
