{
  "type": "Feature",
  "properties": {
    "iso:country":"GB",
    "wof:name":"TQ12 2TL",
    "wof:placetype":"postalcode"
},
  "geometry": {"coordinates":[-3.6127727885768,50.53674388225938],"type":"Point"}
}