{
  "type": "Feature",
  "properties": {
    "date:inception_lower":"1999-12-01",
    "date:inception_upper":"1999-12-31",
    "iso:country":"GB",
    "wof:name":"TQ12 2TL",
    "wof:placetype":"postalcode"
},
  "geometry": {"coordinates":[-3.612773,50.536744],"type":"Point"}
}