{
  "type": "Feature",
  "properties": {
    "iso:country": "GB",
    "wof:name": "TQ12 2TL",
    "wof:placetype": "postalcode"
  },
  "geometry": {"coordinates":[-3.612773,50.536744],"type":"Point"}
}
