{
  "type": "Feature",
  "properties": {
    "iso:country":"GB",
    "wof:name":"LN8 6AX",
    "wof:placetype":"postalcode"
},
  "geometry": {"coordinates":[-0.17130227112702,53.37277791780536],"type":"Point"}
}