{
  "type": "Feature",
  "properties": {
    "date:inception_lower": "1981-06-01",
    "date:inception_upper": "1981-06-01",
    "iso:country": "GB",
    "wof:name": "DN21 3UU",
    "wof:placetype": "postalcode"
  },
  "geometry": {"coordinates":[-0.674933,53.497],"type":"Point"}
}
