{
  "type": "Feature",
  "properties": {
    "iso:country":"GB",
    "wof:name":"DN21 3UU",
    "wof:placetype":"postalcode"
},
  "geometry": {"coordinates":[-0.67493280133376,53.49700038140216],"type":"Point"}
}