{
  "type": "Feature",
  "properties": {
    "iso:country": "GB",
    "wof:name": "SN7 8JU",
    "wof:placetype": "postalcode"
  },
  "geometry": {"coordinates":[-1.574956,51.680943],"type":"Point"}
}
