{
  "type": "Feature",
  "properties": {
    "iso:country":"GB",
    "wof:name":"SN7 8JU",
    "wof:placetype":"postalcode"
},
  "geometry": {"coordinates":[-1.57497041648819,51.68093959943477],"type":"Point"}
}