{
  "type": "Feature",
  "properties": {
    "iso:country": "GB",
    "wof:name": "SN7 8JU",
    "wof:placetype": "postalcode"
  },
  "geometry": {"coordinates":[-1.574999,51.681007],"type":"Point"}
}
