{
  "type": "Feature",
  "properties": {
    "iso:country": "GB",
    "wof:name": "SO18 2PE",
    "wof:placetype": "postalcode"
  },
  "geometry": {"coordinates":[-1.367425,50.930847],"type":"Point"}
}
