{
  "type": "Feature",
  "properties": {
    "iso:country": "GB",
    "wof:name": "AB22 8LX",
    "wof:placetype": "postalcode"
  },
  "geometry": {"coordinates":[-2.119241,57.184306],"type":"Point"}
}
