{
  "type": "Feature",
  "properties": {
    "iso:country": "GB",
    "wof:name": "TS21 3HG",
    "wof:placetype": "postalcode"
  },
  "geometry": {"coordinates":[-1.401621,54.64113],"type":"Point"}
}
