{
  "type": "Feature",
  "properties": {
    "iso:country":"GB",
    "wof:name":"TS21 3HG",
    "wof:placetype":"postalcode"
},
  "geometry": {"coordinates":[-1.40160774552351,54.64111918456555],"type":"Point"}
}