{
  "type": "Feature",
  "properties": {
    "iso:country": "GB",
    "wof:name": "OX28 6RB",
    "wof:placetype": "postalcode"
  },
  "geometry": {"coordinates":[-1.484858,51.785821],"type":"Point"}
}
