{
  "type": "Feature",
  "properties": {
    "date:inception_lower":"2006-08-01",
    "date:inception_upper":"2006-08-31",
    "iso:country":"GB",
    "wof:name":"OX28 6RB",
    "wof:placetype":"postalcode"
},
  "geometry": {"coordinates":[-1.484858,51.785821],"type":"Point"}
}