{
  "type": "Feature",
  "properties": {
    "iso:country":"GB",
    "wof:name":"PL21 9GB",
    "wof:placetype":"postalcode"
},
  "geometry": {"coordinates":[-3.95327650021764,50.38719095143481],"type":"Point"}
}