{
  "type": "Feature",
  "properties": {
    "date:inception_lower":"1997-06-01",
    "date:inception_upper":"1997-06-30",
    "iso:country":"GB",
    "wof:name":"PL21 9GB",
    "wof:placetype":"postalcode"
},
  "geometry": {"coordinates":[-3.953276,50.387191],"type":"Point"}
}