{
  "type": "Feature",
  "properties": {
    "iso:country": "GB",
    "wof:name": "PL21 9GB",
    "wof:placetype": "postalcode"
  },
  "geometry": {"coordinates":[-3.953276,50.387191],"type":"Point"}
}
