{
  "type": "Feature",
  "properties": {
    "iso:country":"GB",
    "wof:name":"WN1 2TA",
    "wof:placetype":"postalcode"
},
  "geometry": {"coordinates":[-2.63636852370443,53.57691875178433],"type":"Point"}
}