{
  "type": "Feature",
  "properties": {
    "iso:country":"GB",
    "wof:name":"NE66 3JA",
    "wof:placetype":"postalcode"
},
  "geometry": {"coordinates":[-1.75177254054062,55.42539381407246],"type":"Point"}
}