{
  "type": "Feature",
  "properties": {
    "iso:country":"GB",
    "wof:name":"EH6 6DR",
    "wof:placetype":"postalcode"
},
  "geometry": {"coordinates":[-3.17039555558491,55.97390244474122],"type":"Point"}
}