{
  "type": "Feature",
  "properties": {
    "date:inception_lower": "1980-01-01",
    "date:inception_upper": "1980-01-01",
    "iso:country": "GB",
    "wof:name": "WS2 8RE",
    "wof:placetype": "postalcode"
  },
  "geometry": {"coordinates":[-1.996311,52.585998],"type":"Point"}
}
