{
  "type": "Feature",
  "properties": {
    "iso:country":"GB",
    "wof:name":"WS2 8RE",
    "wof:placetype":"postalcode"
},
  "geometry": {"coordinates":[-1.99631112490469,52.58599779793483],"type":"Point"}
}