{
  "type": "Feature",
  "properties": {
    "date:inception_lower":"1995-07-01",
    "date:inception_upper":"1995-07-31",
    "iso:country":"GB",
    "wof:name":"HS4 3XY",
    "wof:placetype":"postalcode"
},
  "geometry": {"coordinates":[-6.692177,57.873774],"type":"Point"}
}