{
  "type": "Feature",
  "properties": {
    "iso:country":"GB",
    "wof:name":"HS4 3XY",
    "wof:placetype":"postalcode"
},
  "geometry": {"coordinates":[-6.69218304520028,57.87380501212709],"type":"Point"}
}