{
  "type": "Feature",
  "properties": {
    "iso:country":"GB",
    "wof:name":"LL12 8RU",
    "wof:placetype":"postalcode"
},
  "geometry": {"coordinates":[-2.99289611645292,53.08075749703327],"type":"Point"}
}