{
  "type": "Feature",
  "properties": {
    "iso:country": "GB",
    "wof:name": "LL12 8RU",
    "wof:placetype": "postalcode"
  },
  "geometry": {"coordinates":[-2.992896,53.080757],"type":"Point"}
}
