{
  "type": "Feature",
  "properties": {
    "date:inception_lower": "1980-01-01",
    "date:inception_upper": "1980-01-01",
    "iso:country": "GB",
    "wof:name": "LL12 8RU",
    "wof:placetype": "postalcode"
  },
  "geometry": {"coordinates":[-2.992896,53.080757],"type":"Point"}
}
