{
  "type": "Feature",
  "properties": {
    "iso:country":"GB",
    "wof:name":"BN24 6NE",
    "wof:placetype":"postalcode"
},
  "geometry": {"coordinates":[0.3596217949241,50.81586282668508],"type":"Point"}
}