{
  "type": "Feature",
  "properties": {
    "iso:country":"GB",
    "wof:name":"DY1 2RG",
    "wof:placetype":"postalcode"
},
  "geometry": {"coordinates":[-2.09660454715922,52.51321232847148],"type":"Point"}
}