{
  "type": "Feature",
  "properties": {
    "date:inception_lower": "1980-01-01",
    "date:inception_upper": "1980-01-01",
    "iso:country": "GB",
    "wof:name": "DY1 2RG",
    "wof:placetype": "postalcode"
  },
  "geometry": {"coordinates":[-2.096628,52.5132],"type":"Point"}
}
