{
  "type": "Feature",
  "properties": {
    "iso:country":"GB",
    "wof:name":"ST2 0QN",
    "wof:placetype":"postalcode"
},
  "geometry": {"coordinates":[-2.11733508378385,53.00764491902342],"type":"Point"}
}