{
  "type": "Feature",
  "properties": {
    "iso:country":"GB",
    "wof:name":"CO2 0HU",
    "wof:placetype":"postalcode"
},
  "geometry": {"coordinates":[0.86504162383577,51.85126554920869],"type":"Point"}
}