{
  "type": "Feature",
  "properties": {
    "iso:country":"GB",
    "wof:name":"NW4 1TA",
    "wof:placetype":"postalcode"
},
  "geometry": {"coordinates":[-0.2167710732409,51.59059821933543],"type":"Point"}
}