{
  "type": "Feature",
  "properties": {
    "date:inception_lower": "2003-05-01",
    "date:inception_upper": "2003-05-01",
    "iso:country": "GB",
    "wof:name": "G15 7SB",
    "wof:placetype": "postalcode"
  },
  "geometry": {"coordinates":[-4.35999,55.912308],"type":"Point"}
}
