{
  "type": "Feature",
  "properties": {
    "iso:country":"GB",
    "wof:name":"G15 7SB",
    "wof:placetype":"postalcode"
},
  "geometry": {"coordinates":[-4.35999047142418,55.91230772027296],"type":"Point"}
}