{
  "type": "Feature",
  "properties": {
    "iso:country": "GB",
    "wof:name": "LE8 0PX",
    "wof:placetype": "postalcode"
  },
  "geometry": {"coordinates":[-0.999701,52.545096],"type":"Point"}
}
