{
  "type": "Feature",
  "properties": {
    "iso:country":"GB",
    "wof:name":"LE8 0PX",
    "wof:placetype":"postalcode"
},
  "geometry": {"coordinates":[-0.99970143770548,52.54509560504587],"type":"Point"}
}