{
  "type": "Feature",
  "properties": {
    "date:inception_lower": "2002-08-01",
    "date:inception_upper": "2002-08-01",
    "iso:country": "GB",
    "wof:name": "LE8 0PX",
    "wof:placetype": "postalcode"
  },
  "geometry": {"coordinates":[-0.999701,52.545096],"type":"Point"}
}
