{
  "type": "Feature",
  "properties": {
    "iso:country":"GB",
    "wof:name":"G71 7BX",
    "wof:placetype":"postalcode"
},
  "geometry": {"coordinates":[-4.08463222346832,55.82222225484254],"type":"Point"}
}