{
  "type": "Feature",
  "properties": {
    "iso:country": "GB",
    "wof:name": "N7 7RQ",
    "wof:placetype": "postalcode"
  },
  "geometry": {"coordinates":[-0.113348,51.562723],"type":"Point"}
}
