{
  "type": "Feature",
  "properties": {
    "date:inception_lower": "1981-06-01",
    "date:inception_upper": "1981-06-01",
    "iso:country": "GB",
    "wof:name": "N7 7RQ",
    "wof:placetype": "postalcode"
  },
  "geometry": {"coordinates":[-0.113348,51.562723],"type":"Point"}
}
