{
  "type": "Feature",
  "properties": {
    "iso:country":"GB",
    "wof:name":"BS30 5RT",
    "wof:placetype":"postalcode"
},
  "geometry": {"coordinates":[-2.38962827895817,51.45150085746218],"type":"Point"}
}