{
  "type": "Feature",
  "properties": {
    "date:inception_lower": "1997-12-01",
    "date:inception_upper": "1997-12-01",
    "iso:country": "GB",
    "wof:name": "BS30 5RT",
    "wof:placetype": "postalcode"
  },
  "geometry": {"coordinates":[-2.389379,51.45114],"type":"Point"}
}
