{
  "type": "Feature",
  "properties": {
    "iso:country":"GB",
    "wof:name":"SG5 3BH",
    "wof:placetype":"postalcode"
},
  "geometry": {"coordinates":[-0.31653423800795,51.95108415467176],"type":"Point"}
}