{
  "type": "Feature",
  "properties": {
    "iso:country": "GB",
    "wof:name": "SG5 3BH",
    "wof:placetype": "postalcode"
  },
  "geometry": {"coordinates":[-0.316534,51.951084],"type":"Point"}
}
