{
  "type": "Feature",
  "properties": {
    "iso:country":"GB",
    "wof:name":"NN1 4BW",
    "wof:placetype":"postalcode"
},
  "geometry": {"coordinates":[-0.88246879738752,52.24358384883323],"type":"Point"}
}