{
  "type": "Feature",
  "properties": {
    "iso:country":"GB",
    "wof:name":"OL4 5AB",
    "wof:placetype":"postalcode"
},
  "geometry": {"coordinates":[-2.07220509105822,53.53750500894269],"type":"Point"}
}