{
  "type": "Feature",
  "properties": {
    "iso:country": "GB",
    "wof:name": "OX39 4HR",
    "wof:placetype": "postalcode"
  },
  "geometry": {"coordinates":[-0.915909,51.696831],"type":"Point"}
}
