{
  "type": "Feature",
  "properties": {
    "date:inception_lower": "2000-10-01",
    "date:inception_upper": "2000-10-01",
    "iso:country": "GB",
    "wof:name": "OX39 4HR",
    "wof:placetype": "postalcode"
  },
  "geometry": {"coordinates":[-0.916427,51.696624],"type":"Point"}
}
