{
  "type": "Feature",
  "properties": {
    "iso:country": "GB",
    "wof:name": "SK9 2PQ",
    "wof:placetype": "postalcode"
  },
  "geometry": {"coordinates":[-2.214429,53.340441],"type":"Point"}
}
