{
  "type": "Feature",
  "properties": {
    "iso:country":"GB",
    "wof:name":"SK9 2PQ",
    "wof:placetype":"postalcode"
},
  "geometry": {"coordinates":[-2.2144290528866,53.34044080745046],"type":"Point"}
}