{
  "type": "Feature",
  "properties": {
    "iso:country":"GB",
    "wof:name":"SO18 3PB",
    "wof:placetype":"postalcode"
},
  "geometry": {"coordinates":[-1.3481973062327,50.9259843185545],"type":"Point"}
}