{
  "type": "Feature",
  "properties": {
    "iso:country":"GB",
    "wof:name":"TA22 9PS",
    "wof:placetype":"postalcode"
},
  "geometry": {"coordinates":[-3.55815534874009,51.0612705847989],"type":"Point"}
}