{
  "type": "Feature",
  "properties": {
    "date:inception_lower":"1980-01-01",
    "date:inception_upper":"1980-01-31",
    "iso:country":"GB",
    "wof:name":"TA22 9PS",
    "wof:placetype":"postalcode"
},
  "geometry": {"coordinates":[-3.558155,51.061271],"type":"Point"}
}