{
  "type": "Feature",
  "properties": {
    "iso:country":"GB",
    "wof:name":"N11 2LB",
    "wof:placetype":"postalcode"
},
  "geometry": {"coordinates":[-0.12781605490148,51.61230541221258],"type":"Point"}
}