{
  "type": "Feature",
  "properties": {
    "iso:country": "GB",
    "wof:name": "G46 8JW",
    "wof:placetype": "postalcode"
  },
  "geometry": {"coordinates":[-4.328041,55.802117],"type":"Point"}
}
