{
  "type": "Feature",
  "properties": {
    "iso:country":"GB",
    "wof:name":"ME19 4HZ",
    "wof:placetype":"postalcode"
},
  "geometry": {"coordinates":[0.40026814857864,51.27146058749143],"type":"Point"}
}