{
  "type": "Feature",
  "properties": {
    "iso:country": "GB",
    "wof:name": "ME19 4HZ",
    "wof:placetype": "postalcode"
  },
  "geometry": {"coordinates":[0.400268,51.271461],"type":"Point"}
}
