{
  "type": "Feature",
  "properties": {
    "iso:country":"GB",
    "wof:name":"NP44 2LG",
    "wof:placetype":"postalcode"
},
  "geometry": {"coordinates":[-3.0104686048307,51.66003254408568],"type":"Point"}
}