{
  "type": "Feature",
  "properties": {
    "iso:country":"GB",
    "wof:name":"TQ5 9TH",
    "wof:placetype":"postalcode"
},
  "geometry": {"coordinates":[-3.51091443483305,50.39618172745678],"type":"Point"}
}