{
  "type": "Feature",
  "properties": {
    "date:inception_lower": "1987-04-01",
    "date:inception_upper": "1987-04-01",
    "iso:country": "GB",
    "wof:name": "HR6 9RJ",
    "wof:placetype": "postalcode"
  },
  "geometry": {"coordinates":[-2.822629,52.235765],"type":"Point"}
}
