{
  "type": "Feature",
  "properties": {
    "iso:country": "GB",
    "wof:name": "HR6 9RJ",
    "wof:placetype": "postalcode"
  },
  "geometry": {"coordinates":[-2.823453,52.235991],"type":"Point"}
}
