{
  "type": "Feature",
  "properties": {
    "date:inception_lower":"1987-04-01",
    "date:inception_upper":"1987-04-30",
    "iso:country":"GB",
    "wof:name":"HR6 9RJ",
    "wof:placetype":"postalcode"
},
  "geometry": {"coordinates":[-2.823453,52.235991],"type":"Point"}
}