{
  "type": "Feature",
  "properties": {
    "iso:country":"GB",
    "wof:name":"HR6 9RJ",
    "wof:placetype":"postalcode"
},
  "geometry": {"coordinates":[-2.82345299645415,52.23599070054802],"type":"Point"}
}