{
  "type": "Feature",
  "properties": {
    "iso:country": "GB",
    "wof:name": "OX28 4EX",
    "wof:placetype": "postalcode"
  },
  "geometry": {"coordinates":[-1.489689,51.77392],"type":"Point"}
}
