{
  "type": "Feature",
  "properties": {
    "iso:country": "GB",
    "wof:name": "KY11 2YL",
    "wof:placetype": "postalcode"
  },
  "geometry": {"coordinates":[-3.441494,56.028628],"type":"Point"}
}
