{
  "type": "Feature",
  "properties": {
    "iso:country":"GB",
    "wof:name":"KY11 2YL",
    "wof:placetype":"postalcode"
},
  "geometry": {"coordinates":[-3.44149423929787,56.02862820443291],"type":"Point"}
}