{
  "type": "Feature",
  "properties": {
    "iso:country":"GB",
    "wof:name":"CR7 8RJ",
    "wof:placetype":"postalcode"
},
  "geometry": {"coordinates":[-0.09353073621353,51.39645337561341],"type":"Point"}
}