{
  "type": "Feature",
  "properties": {
    "iso:country":"GB",
    "wof:name":"CM0 7LX",
    "wof:placetype":"postalcode"
},
  "geometry": {"coordinates":[0.79505319216516,51.69216376291691],"type":"Point"}
}