{
  "type": "Feature",
  "properties": {
    "iso:country":"GB",
    "wof:name":"PL3 4NL",
    "wof:placetype":"postalcode"
},
  "geometry": {"coordinates":[-4.14070734249705,50.3906997001901],"type":"Point"}
}