{
  "type": "Feature",
  "properties": {
    "iso:country":"GB",
    "wof:name":"SO45 6AZ",
    "wof:placetype":"postalcode"
},
  "geometry": {"coordinates":[-1.40543934130016,50.87335987568172],"type":"Point"}
}