{
  "type": "Feature",
  "properties": {
    "iso:country":"GB",
    "wof:name":"PL6 7HZ",
    "wof:placetype":"postalcode"
},
  "geometry": {"coordinates":[-4.10157303051123,50.42836218544528],"type":"Point"}
}