{
  "type": "Feature",
  "properties": {
    "iso:country": "GB",
    "wof:name": "PL6 7HZ",
    "wof:placetype": "postalcode"
  },
  "geometry": {"coordinates":[-4.101573,50.428362],"type":"Point"}
}
