{
  "type": "Feature",
  "properties": {
    "date:inception_lower": "1980-01-01",
    "date:inception_upper": "1980-01-01",
    "iso:country": "GB",
    "wof:name": "LN11 0UG",
    "wof:placetype": "postalcode"
  },
  "geometry": {"coordinates":[-0.022085,53.405701],"type":"Point"}
}
