{
  "type": "Feature",
  "properties": {
    "iso:country":"GB",
    "wof:name":"RG22 4JS",
    "wof:placetype":"postalcode"
},
  "geometry": {"coordinates":[-1.10283338684356,51.24684958462237],"type":"Point"}
}