{
  "type": "Feature",
  "properties": {
    "iso:country":"GB",
    "wof:name":"DG3 5WX",
    "wof:placetype":"postalcode"
},
  "geometry": {"coordinates":[-3.7658621991155,55.24188777552588],"type":"Point"}
}