{
  "type": "Feature",
  "properties": {
    "iso:country":"GB",
    "wof:name":"CF62 8BJ",
    "wof:placetype":"postalcode"
},
  "geometry": {"coordinates":[-3.27398889960278,51.41078479234732],"type":"Point"}
}