{
  "type": "Feature",
  "properties": {
    "iso:country":"GB",
    "wof:name":"SK16 5JF",
    "wof:placetype":"postalcode"
},
  "geometry": {"coordinates":[-2.07346904290664,53.47468432030612],"type":"Point"}
}