{
  "type": "Feature",
  "properties": {
    "date:inception_lower":"1991-09-01",
    "date:inception_upper":"1991-09-30",
    "iso:country":"GB",
    "wof:name":"NG22 0UA",
    "wof:placetype":"postalcode"
},
  "geometry": {"coordinates":[-0.783484,53.261371],"type":"Point"}
}