{
  "type": "Feature",
  "properties": {
    "iso:country":"GB",
    "wof:name":"NG22 0UA",
    "wof:placetype":"postalcode"
},
  "geometry": {"coordinates":[-0.78348368409894,53.26137058064646],"type":"Point"}
}