{
  "type": "Feature",
  "properties": {
    "iso:country": "GB",
    "wof:name": "TS1 4QB",
    "wof:placetype": "postalcode"
  },
  "geometry": {"coordinates":[-1.250322,54.566746],"type":"Point"}
}
