{
  "type": "Feature",
  "properties": {
    "iso:country":"GB",
    "wof:name":"TS1 4QB",
    "wof:placetype":"postalcode"
},
  "geometry": {"coordinates":[-1.2503223197481,54.56674600789099],"type":"Point"}
}