{
  "type": "Feature",
  "properties": {
    "iso:country":"GB",
    "wof:name":"ME17 1HT",
    "wof:placetype":"postalcode"
},
  "geometry": {"coordinates":[0.68161811875973,51.23678643329457],"type":"Point"}
}