{
  "type": "Feature",
  "properties": {
    "iso:country":"GB",
    "wof:name":"BB12 6RE",
    "wof:placetype":"postalcode"
},
  "geometry": {"coordinates":[-2.26940332019087,53.79228966648716],"type":"Point"}
}