{
  "type": "Feature",
  "properties": {
    "date:inception_lower":"1980-01-01",
    "date:inception_upper":"1980-01-31",
    "iso:country":"GB",
    "wof:name":"BB12 6RE",
    "wof:placetype":"postalcode"
},
  "geometry": {"coordinates":[-2.269403,53.79229],"type":"Point"}
}