{
  "type": "Feature",
  "properties": {
    "iso:country": "GB",
    "wof:name": "PL13 1JA",
    "wof:placetype": "postalcode"
  },
  "geometry": {"coordinates":[-4.453804,50.358176],"type":"Point"}
}
