{
  "type": "Feature",
  "properties": {
    "date:inception_lower": "1980-01-01",
    "date:inception_upper": "1980-01-01",
    "iso:country": "GB",
    "wof:name": "PL13 1JA",
    "wof:placetype": "postalcode"
  },
  "geometry": {"coordinates":[-4.453804,50.358176],"type":"Point"}
}
