{
  "type": "Feature",
  "properties": {
    "iso:country": "GB",
    "wof:name": "B63 2BU",
    "wof:placetype": "postalcode"
  },
  "geometry": {"coordinates":[-2.086812,52.459906],"type":"Point"}
}
