{
  "type": "Feature",
  "properties": {
    "iso:country": "GB",
    "wof:name": "BN8 6BB",
    "wof:placetype": "postalcode"
  },
  "geometry": {"coordinates":[0.134099,50.867105],"type":"Point"}
}
