{
  "type": "Feature",
  "properties": {
    "date:inception_lower": "2008-03-01",
    "date:inception_upper": "2008-03-01",
    "iso:country": "GB",
    "wof:name": "BN8 6BB",
    "wof:placetype": "postalcode"
  },
  "geometry": {"coordinates":[0.133592,50.867213],"type":"Point"}
}
