{
  "type": "Feature",
  "properties": {
    "iso:country":"GB",
    "wof:name":"BN8 6BB",
    "wof:placetype":"postalcode"
},
  "geometry": {"coordinates":[0.13433360415403,50.86725818205121],"type":"Point"}
}