{
  "type": "Feature",
  "properties": {
    "iso:country":"GB",
    "wof:name":"GU34 5NE",
    "wof:placetype":"postalcode"
},
  "geometry": {"coordinates":[-1.08572319942258,51.12404572184543],"type":"Point"}
}