{
  "type": "Feature",
  "properties": {
    "date:inception_lower":"2007-07-01",
    "date:inception_upper":"2007-07-31",
    "iso:country":"GB",
    "wof:name":"GU34 5NE",
    "wof:placetype":"postalcode"
},
  "geometry": {"coordinates":[-1.085723,51.124046],"type":"Point"}
}