{
  "type": "Feature",
  "properties": {
    "iso:country":"GB",
    "wof:name":"YO1 8RR",
    "wof:placetype":"postalcode"
},
  "geometry": {"coordinates":[-1.08151810745519,53.95958345795444],"type":"Point"}
}