{
  "type": "Feature",
  "properties": {
    "date:inception_lower": "1998-06-01",
    "date:inception_upper": "1998-06-01",
    "iso:country": "GB",
    "wof:name": "YO1 8RR",
    "wof:placetype": "postalcode"
  },
  "geometry": {"coordinates":[-1.081518,53.959583],"type":"Point"}
}
