{
  "type": "Feature",
  "properties": {
    "iso:country":"GB",
    "wof:name":"SK14 4HF",
    "wof:placetype":"postalcode"
},
  "geometry": {"coordinates":[-2.06489651314576,53.46491885348698],"type":"Point"}
}