{
  "type": "Feature",
  "properties": {
    "date:inception_lower": "1980-01-01",
    "date:inception_upper": "1980-01-01",
    "iso:country": "GB",
    "wof:name": "SK14 4HF",
    "wof:placetype": "postalcode"
  },
  "geometry": {"coordinates":[-2.064896,53.464919],"type":"Point"}
}
