{
  "type": "Feature",
  "properties": {
    "iso:country":"GB",
    "wof:name":"DN33 3SG",
    "wof:placetype":"postalcode"
},
  "geometry": {"coordinates":[-0.10412957908434,53.54030843027193],"type":"Point"}
}