{
  "type": "Feature",
  "properties": {
    "date:inception_lower": "1980-01-01",
    "date:inception_upper": "1980-01-01",
    "iso:country": "GB",
    "wof:name": "CA12 4LH",
    "wof:placetype": "postalcode"
  },
  "geometry": {"coordinates":[-3.118321,54.60451],"type":"Point"}
}
