{
  "type": "Feature",
  "properties": {
    "iso:country":"GB",
    "wof:name":"CA12 4LH",
    "wof:placetype":"postalcode"
},
  "geometry": {"coordinates":[-3.11832079927983,54.60451029268211],"type":"Point"}
}