{
  "type": "Feature",
  "properties": {
    "iso:country":"GB",
    "wof:name":"S36 2PR",
    "wof:placetype":"postalcode"
},
  "geometry": {"coordinates":[-1.57913390854604,53.47456016493197],"type":"Point"}
}