{
  "type": "Feature",
  "properties": {
    "iso:country": "GB",
    "wof:name": "S36 2PR",
    "wof:placetype": "postalcode"
  },
  "geometry": {"coordinates":[-1.57912,53.474586],"type":"Point"}
}
