{
  "type": "Feature",
  "properties": {
    "iso:country":"GB",
    "wof:name":"NR2 3DS",
    "wof:placetype":"postalcode"
},
  "geometry": {"coordinates":[1.27738465832322,52.62703522569413],"type":"Point"}
}