{
  "type": "Feature",
  "properties": {
    "iso:country":"GB",
    "wof:name":"GL52 9TX",
    "wof:placetype":"postalcode"
},
  "geometry": {"coordinates":[-2.04109389740725,51.94260059618896],"type":"Point"}
}