{
  "type": "Feature",
  "properties": {
    "iso:country": "GB",
    "wof:name": "NN16 0PW",
    "wof:placetype": "postalcode"
  },
  "geometry": {"coordinates":[-0.704427,52.406808],"type":"Point"}
}
