{
  "type": "Feature",
  "properties": {
    "iso:country":"GB",
    "wof:name":"NN16 0PW",
    "wof:placetype":"postalcode"
},
  "geometry": {"coordinates":[-0.70442693973934,52.40680802270469],"type":"Point"}
}