{
  "type": "Feature",
  "properties": {
    "iso:country":"GB",
    "wof:name":"HU17 8BU",
    "wof:placetype":"postalcode"
},
  "geometry": {"coordinates":[-0.44020399566445,53.84178694840718],"type":"Point"}
}