{
  "type": "Feature",
  "properties": {
    "date:inception_lower":"1981-06-01",
    "date:inception_upper":"1981-06-30",
    "iso:country":"GB",
    "wof:name":"SP6 3AQ",
    "wof:placetype":"postalcode"
},
  "geometry": {"coordinates":[-1.8277,50.911165],"type":"Point"}
}