{
  "type": "Feature",
  "properties": {
    "date:inception_lower": "2019-06-01",
    "date:inception_upper": "2019-06-01",
    "iso:country": "GB",
    "wof:name": "L32 1BS",
    "wof:placetype": "postalcode"
  },
  "geometry": {"coordinates":[-2.878895,53.492001],"type":"Point"}
}
