{
  "type": "Feature",
  "properties": {
    "iso:country":"GB",
    "wof:name":"PL32 9UQ",
    "wof:placetype":"postalcode"
},
  "geometry": {"coordinates":[-4.68105090815929,50.62312874491003],"type":"Point"}
}