{
  "type": "Feature",
  "properties": {
    "iso:country": "GB",
    "wof:name": "OX11 7QL",
    "wof:placetype": "postalcode"
  },
  "geometry": {"coordinates":[-1.228265,51.611766],"type":"Point"}
}
