{
  "type": "Feature",
  "properties": {
    "iso:country":"GB",
    "wof:name":"OX11 7QL",
    "wof:placetype":"postalcode"
},
  "geometry": {"coordinates":[-1.22826485219005,51.6117655851895],"type":"Point"}
}