{
  "type": "Feature",
  "properties": {
    "iso:country":"GB",
    "wof:name":"ML3 9HR",
    "wof:placetype":"postalcode"
},
  "geometry": {"coordinates":[-4.08596607244596,55.77883657919345],"type":"Point"}
}