{
  "type": "Feature",
  "properties": {
    "date:inception_lower": "2007-11-01",
    "date:inception_upper": "2007-11-01",
    "iso:country": "GB",
    "wof:name": "BB11 1BH",
    "wof:placetype": "postalcode"
  },
  "geometry": {"coordinates":[-2.244285,53.787769],"type":"Point"}
}
