{
  "type": "Feature",
  "properties": {
    "iso:country":"GB",
    "wof:name":"SW4 6LR",
    "wof:placetype":"postalcode"
},
  "geometry": {"coordinates":[-0.13340029257495,51.46793918388679],"type":"Point"}
}