{
  "type": "Feature",
  "properties": {
    "iso:country":"GB",
    "wof:name":"BB8 7BZ",
    "wof:placetype":"postalcode"
},
  "geometry": {"coordinates":[-2.14873286710868,53.85893003002594],"type":"Point"}
}