{
  "type": "Feature",
  "properties": {
    "date:inception_lower": "1998-12-01",
    "date:inception_upper": "1998-12-01",
    "iso:country": "GB",
    "wof:name": "IV2 7RQ",
    "wof:placetype": "postalcode"
  },
  "geometry": {"coordinates":[-4.124543,57.48938],"type":"Point"}
}
