{
  "type": "Feature",
  "properties": {
    "iso:country":"GB",
    "wof:name":"IV2 7RQ",
    "wof:placetype":"postalcode"
},
  "geometry": {"coordinates":[-4.12454300746891,57.48938049315891],"type":"Point"}
}