{
  "type": "Feature",
  "properties": {
    "iso:country":"GB",
    "wof:name":"CM24 1QX",
    "wof:placetype":"postalcode"
},
  "geometry": {"coordinates":[0.26174067578514,51.88993845106022],"type":"Point"}
}