{
  "type": "Feature",
  "properties": {
    "iso:country": "GB",
    "wof:name": "CB6 3HP",
    "wof:placetype": "postalcode"
  },
  "geometry": {"coordinates":[0.232987,52.360509],"type":"Point"}
}
