{
  "type": "Feature",
  "properties": {
    "iso:country":"GB",
    "wof:name":"CB6 3HP",
    "wof:placetype":"postalcode"
},
  "geometry": {"coordinates":[0.23298682976802,52.36050887527977],"type":"Point"}
}