{
  "type": "Feature",
  "properties": {
    "iso:country":"GB",
    "wof:name":"KT2 5LF",
    "wof:placetype":"postalcode"
},
  "geometry": {"coordinates":[-0.28906272263588,51.42340043274092],"type":"Point"}
}