{
  "type": "Feature",
  "properties": {
    "iso:country":"GB",
    "wof:name":"LE5 2AN",
    "wof:placetype":"postalcode"
},
  "geometry": {"coordinates":[-1.07704352416494,52.64150410719397],"type":"Point"}
}