{
  "type": "Feature",
  "properties": {
    "iso:country":"GB",
    "wof:name":"RG24 7HR",
    "wof:placetype":"postalcode"
},
  "geometry": {"coordinates":[-1.04294675905253,51.26541168901076],"type":"Point"}
}