{
  "type": "Feature",
  "properties": {
    "iso:country": "GB",
    "wof:name": "RG24 7HR",
    "wof:placetype": "postalcode"
  },
  "geometry": {"coordinates":[-1.042947,51.265412],"type":"Point"}
}
