{
  "type": "Feature",
  "properties": {
    "date:inception_lower":"1993-08-01",
    "date:inception_upper":"1993-08-31",
    "iso:country":"GB",
    "wof:name":"RG24 7HR",
    "wof:placetype":"postalcode"
},
  "geometry": {"coordinates":[-1.042947,51.265412],"type":"Point"}
}