{
  "type": "Feature",
  "properties": {
    "date:inception_lower":"2011-09-01",
    "date:inception_upper":"2011-09-30",
    "iso:country":"GB",
    "wof:name":"HP13 5HF",
    "wof:placetype":"postalcode"
},
  "geometry": {"coordinates":[-0.736241,51.647074],"type":"Point"}
}