{
  "type": "Feature",
  "properties": {
    "iso:country":"GB",
    "wof:name":"HP13 5HF",
    "wof:placetype":"postalcode"
},
  "geometry": {"coordinates":[-0.736240646401,51.64707383052995],"type":"Point"}
}