{
  "type": "Feature",
  "properties": {
    "iso:country": "GB",
    "wof:name": "SP10 5DZ",
    "wof:placetype": "postalcode"
  },
  "geometry": {"coordinates":[-1.467701,51.222191],"type":"Point"}
}
