{
  "type": "Feature",
  "properties": {
    "iso:country": "GB",
    "wof:name": "LS28 5RT",
    "wof:placetype": "postalcode"
  },
  "geometry": {"coordinates":[-1.700646,53.829026],"type":"Point"}
}
