{
  "type": "Feature",
  "properties": {
    "iso:country":"GB",
    "wof:name":"LS28 5RT",
    "wof:placetype":"postalcode"
},
  "geometry": {"coordinates":[-1.70064556786488,53.82902563873869],"type":"Point"}
}