{
  "type": "Feature",
  "properties": {
    "iso:country":"GB",
    "wof:name":"PA8 6DP",
    "wof:placetype":"postalcode"
},
  "geometry": {"coordinates":[-4.46675549605794,55.90821910952143],"type":"Point"}
}