{
  "type": "Feature",
  "properties": {
    "iso:country":"GB",
    "wof:name":"DN15 0BB",
    "wof:placetype":"postalcode"
},
  "geometry": {"coordinates":[-0.60485521052187,53.64222171835846],"type":"Point"}
}