{
  "type": "Feature",
  "properties": {
    "iso:country": "GB",
    "wof:name": "LU5 5AU",
    "wof:placetype": "postalcode"
  },
  "geometry": {"coordinates":[-0.525956,51.896742],"type":"Point"}
}
