{
  "type": "Feature",
  "properties": {
    "iso:country":"GB",
    "wof:name":"G44 5AP",
    "wof:placetype":"postalcode"
},
  "geometry": {"coordinates":[-4.24786857913904,55.8164072103926],"type":"Point"}
}