{
  "type": "Feature",
  "properties": {
    "date:inception_lower": "1980-01-01",
    "date:inception_upper": "1980-01-01",
    "iso:country": "GB",
    "wof:name": "NE44 6AQ",
    "wof:placetype": "postalcode"
  },
  "geometry": {"coordinates":[-2.015165,54.938679],"type":"Point"}
}
