{
  "type": "Feature",
  "properties": {
    "date:inception_lower": "1980-01-01",
    "date:inception_upper": "1980-01-01",
    "iso:country": "GB",
    "wof:name": "G65 0AE",
    "wof:placetype": "postalcode"
  },
  "geometry": {"coordinates":[-4.052578,55.978365],"type":"Point"}
}
