{
  "type": "Feature",
  "properties": {
    "iso:country":"GB",
    "wof:name":"G65 0AE",
    "wof:placetype":"postalcode"
},
  "geometry": {"coordinates":[-4.05258773000357,55.97837065024416],"type":"Point"}
}