{
  "type": "Feature",
  "properties": {
    "iso:country": "GB",
    "wof:name": "G65 0AE",
    "wof:placetype": "postalcode"
  },
  "geometry": {"coordinates":[-4.052608,55.978311],"type":"Point"}
}
