{
  "type": "Feature",
  "properties": {
    "date:inception_lower":"1990-02-01",
    "date:inception_upper":"1990-02-28",
    "iso:country":"GB",
    "wof:name":"WN2 3UH",
    "wof:placetype":"postalcode"
},
  "geometry": {"coordinates":[-2.598114,53.524516],"type":"Point"}
}