{
  "type": "Feature",
  "properties": {
    "iso:country":"GB",
    "wof:name":"WN2 3UH",
    "wof:placetype":"postalcode"
},
  "geometry": {"coordinates":[-2.59811365794743,53.52451566214526],"type":"Point"}
}