{
  "type": "Feature",
  "properties": {
    "iso:country":"GB",
    "wof:name":"IV19 1DD",
    "wof:placetype":"postalcode"
},
  "geometry": {"coordinates":[-4.05543798306541,57.80740928978621],"type":"Point"}
}