{
  "type": "Feature",
  "properties": {
    "iso:country": "GB",
    "wof:name": "IV19 1DD",
    "wof:placetype": "postalcode"
  },
  "geometry": {"coordinates":[-4.055438,57.807409],"type":"Point"}
}
