{
  "type": "Feature",
  "properties": {
    "iso:country": "GB",
    "wof:name": "TW13 7JP",
    "wof:placetype": "postalcode"
  },
  "geometry": {"coordinates":[-0.417014,51.437635],"type":"Point"}
}
