{
  "type": "Feature",
  "properties": {
    "iso:country":"GB",
    "wof:name":"TW13 7JP",
    "wof:placetype":"postalcode"
},
  "geometry": {"coordinates":[-0.41701440063849,51.43763465044965],"type":"Point"}
}