{
  "type": "Feature",
  "properties": {
    "date:inception_lower": "1980-01-01",
    "date:inception_upper": "1980-01-01",
    "iso:country": "GB",
    "wof:name": "TW13 7JP",
    "wof:placetype": "postalcode"
  },
  "geometry": {"coordinates":[-0.417014,51.437635],"type":"Point"}
}
