{
  "type": "Feature",
  "properties": {
    "iso:country":"GB",
    "wof:name":"SL6 4RN",
    "wof:placetype":"postalcode"
},
  "geometry": {"coordinates":[-0.74464672570443,51.5189495485221],"type":"Point"}
}