{
  "type": "Feature",
  "properties": {
    "iso:country": "GB",
    "wof:name": "DN41 7LW",
    "wof:placetype": "postalcode"
  },
  "geometry": {"coordinates":[-0.164356,53.577737],"type":"Point"}
}
