{
  "type": "Feature",
  "properties": {
    "date:inception_lower":"2011-05-01",
    "date:inception_upper":"2011-05-31",
    "iso:country":"GB",
    "wof:name":"DN41 7LW",
    "wof:placetype":"postalcode"
},
  "geometry": {"coordinates":[-0.164356,53.577737],"type":"Point"}
}