{
  "type": "Feature",
  "properties": {
    "iso:country":"GB",
    "wof:name":"RG7 2HF",
    "wof:placetype":"postalcode"
},
  "geometry": {"coordinates":[-1.05891455983344,51.36919199802229],"type":"Point"}
}