{
  "type": "Feature",
  "properties": {
    "date:inception_lower": "1980-01-01",
    "date:inception_upper": "1980-01-01",
    "iso:country": "GB",
    "wof:name": "RG7 2HF",
    "wof:placetype": "postalcode"
  },
  "geometry": {"coordinates":[-1.058915,51.369192],"type":"Point"}
}
