{
  "type": "Feature",
  "properties": {
    "iso:country":"GB",
    "wof:name":"LN5 7TF",
    "wof:placetype":"postalcode"
},
  "geometry": {"coordinates":[-0.54306417592278,53.2195705306604],"type":"Point"}
}