{
  "type": "Feature",
  "properties": {
    "date:inception_lower": "1983-01-01",
    "date:inception_upper": "1983-01-01",
    "iso:country": "GB",
    "wof:name": "LL11 5BQ",
    "wof:placetype": "postalcode"
  },
  "geometry": {"coordinates":[-3.055387,53.07764],"type":"Point"}
}
