{
  "type": "Feature",
  "properties": {
    "iso:country":"GB",
    "wof:name":"LL11 5BQ",
    "wof:placetype":"postalcode"
},
  "geometry": {"coordinates":[-3.05538693266154,53.07763959158213],"type":"Point"}
}