{
  "type": "Feature",
  "properties": {
    "date:inception_lower":"2017-01-01",
    "date:inception_upper":"2017-01-31",
    "iso:country":"GB",
    "wof:name":"ME16 0XU",
    "wof:placetype":"postalcode"
},
  "geometry": {"coordinates":[0.488502,51.287119],"type":"Point"}
}