{
  "type": "Feature",
  "properties": {
    "iso:country":"GB",
    "wof:name":"DH9 9XS",
    "wof:placetype":"postalcode"
},
  "geometry": {"coordinates":[-1.70866361180309,54.88320251571821],"type":"Point"}
}