{
  "type": "Feature",
  "properties": {
    "date:inception_lower":"1996-06-01",
    "date:inception_upper":"1996-06-30",
    "iso:country":"GB",
    "wof:name":"DH9 9XS",
    "wof:placetype":"postalcode"
},
  "geometry": {"coordinates":[-1.708664,54.883203],"type":"Point"}
}