{
  "type": "Feature",
  "properties": {
    "iso:country": "GB",
    "wof:name": "DL4 2BF",
    "wof:placetype": "postalcode"
  },
  "geometry": {"coordinates":[-1.628905,54.627578],"type":"Point"}
}
