{
  "type": "Feature",
  "properties": {
    "iso:country":"GB",
    "wof:name":"G69 9HG",
    "wof:placetype":"postalcode"
},
  "geometry": {"coordinates":[-4.10091085187416,55.90588480306173],"type":"Point"}
}