{
  "type": "Feature",
  "properties": {
    "iso:country":"GB",
    "wof:name":"TN34 3BN",
    "wof:placetype":"postalcode"
},
  "geometry": {"coordinates":[0.59381905979092,50.85731784440532],"type":"Point"}
}