{
  "type": "Feature",
  "properties": {
    "date:inception_lower":"1980-01-01",
    "date:inception_upper":"1980-01-31",
    "iso:country":"GB",
    "wof:name":"BD19 3HA",
    "wof:placetype":"postalcode"
},
  "geometry": {"coordinates":[-1.720352,53.723698],"type":"Point"}
}