{
  "type": "Feature",
  "properties": {
    "iso:country": "GB",
    "wof:name": "BD19 3HA",
    "wof:placetype": "postalcode"
  },
  "geometry": {"coordinates":[-1.720352,53.723698],"type":"Point"}
}
