{
  "type": "Feature",
  "properties": {
    "iso:country": "GB",
    "wof:name": "SL6 3QZ",
    "wof:placetype": "postalcode"
  },
  "geometry": {"coordinates":[-0.794746,51.514556],"type":"Point"}
}
