{
  "type": "Feature",
  "properties": {
    "date:inception_lower":"1980-01-01",
    "date:inception_upper":"1980-01-31",
    "iso:country":"GB",
    "wof:name":"SL6 3QZ",
    "wof:placetype":"postalcode"
},
  "geometry": {"coordinates":[-0.794746,51.514556],"type":"Point"}
}