{
  "type": "Feature",
  "properties": {
    "iso:country":"GB",
    "wof:name":"SL6 3QZ",
    "wof:placetype":"postalcode"
},
  "geometry": {"coordinates":[-0.79474653018651,51.51455634440583],"type":"Point"}
}