{
  "type": "Feature",
  "properties": {
    "iso:country":"GB",
    "wof:name":"E5 9DU",
    "wof:placetype":"postalcode"
},
  "geometry": {"coordinates":[-0.05839594396143,51.56738419241753],"type":"Point"}
}