{
  "type": "Feature",
  "properties": {
    "date:inception_lower": "1980-01-01",
    "date:inception_upper": "1980-01-01",
    "iso:country": "GB",
    "wof:name": "E5 9DU",
    "wof:placetype": "postalcode"
  },
  "geometry": {"coordinates":[-0.058309,51.567392],"type":"Point"}
}
