{
  "type": "Feature",
  "properties": {
    "iso:country": "GB",
    "wof:name": "PL21 0TG",
    "wof:placetype": "postalcode"
  },
  "geometry": {"coordinates":[-3.918203,50.332787],"type":"Point"}
}
