{
  "type": "Feature",
  "properties": {
    "iso:country":"GB",
    "wof:name":"SA1 6RR",
    "wof:placetype":"postalcode"
},
  "geometry": {"coordinates":[-3.96581461264464,51.63141255508482],"type":"Point"}
}