{
  "type": "Feature",
  "properties": {
    "iso:country": "GB",
    "wof:name": "BB8 7BP",
    "wof:placetype": "postalcode"
  },
  "geometry": {"coordinates":[-2.144729,53.857416],"type":"Point"}
}
