{
  "type": "Feature",
  "properties": {
    "iso:country":"GB",
    "wof:name":"BB8 7BP",
    "wof:placetype":"postalcode"
},
  "geometry": {"coordinates":[-2.14472902261741,53.85741598331261],"type":"Point"}
}