{
  "type": "Feature",
  "properties": {
    "iso:country":"GB",
    "wof:name":"WF3 4ED",
    "wof:placetype":"postalcode"
},
  "geometry": {"coordinates":[-1.4821780810421,53.71724306584904],"type":"Point"}
}