{
  "type": "Feature",
  "properties": {
    "iso:country":"GB",
    "wof:name":"NW4 1QY",
    "wof:placetype":"postalcode"
},
  "geometry": {"coordinates":[-0.2179208118581,51.59478811370288],"type":"Point"}
}