{
  "type": "Feature",
  "properties": {
    "date:inception_lower": "1980-01-01",
    "date:inception_upper": "1980-01-01",
    "iso:country": "GB",
    "wof:name": "NW4 1QY",
    "wof:placetype": "postalcode"
  },
  "geometry": {"coordinates":[-0.217921,51.594788],"type":"Point"}
}
