{
  "type": "Feature",
  "properties": {
    "iso:country": "GB",
    "wof:name": "NW4 1QY",
    "wof:placetype": "postalcode"
  },
  "geometry": {"coordinates":[-0.217921,51.594788],"type":"Point"}
}
