{
  "type": "Feature",
  "properties": {
    "iso:country": "GB",
    "wof:name": "GU9 8BD",
    "wof:placetype": "postalcode"
  },
  "geometry": {"coordinates":[-0.790782,51.212408],"type":"Point"}
}
