{
  "type": "Feature",
  "properties": {
    "iso:country":"GB",
    "wof:name":"NE26 4AB",
    "wof:placetype":"postalcode"
},
  "geometry": {"coordinates":[-1.45884801399219,55.05879383555842],"type":"Point"}
}