{
  "type": "Feature",
  "properties": {
    "iso:country":"GB",
    "wof:name":"NG18 1AE",
    "wof:placetype":"postalcode"
},
  "geometry": {"coordinates":[-1.19445669507299,53.1437354161265],"type":"Point"}
}