{
  "type": "Feature",
  "properties": {
    "iso:country":"GB",
    "wof:name":"SA16 0HX",
    "wof:placetype":"postalcode"
},
  "geometry": {"coordinates":[-4.29593816895824,51.69456458026106],"type":"Point"}
}