{
  "type": "Feature",
  "properties": {
    "date:inception_lower": "1980-01-01",
    "date:inception_upper": "1980-01-01",
    "iso:country": "GB",
    "wof:name": "SA16 0HX",
    "wof:placetype": "postalcode"
  },
  "geometry": {"coordinates":[-4.296199,51.694091],"type":"Point"}
}
