{
  "type": "Feature",
  "properties": {
    "iso:country":"GB",
    "wof:name":"SS0 0RG",
    "wof:placetype":"postalcode"
},
  "geometry": {"coordinates":[0.69532524061664,51.55382745440905],"type":"Point"}
}