{
  "type": "Feature",
  "properties": {
    "iso:country": "GB",
    "wof:name": "LL18 1PR",
    "wof:placetype": "postalcode"
  },
  "geometry": {"coordinates":[-3.496723,53.31731],"type":"Point"}
}
