{
  "type": "Feature",
  "properties": {
    "iso:country":"GB",
    "wof:name":"ME4 5DP",
    "wof:placetype":"postalcode"
},
  "geometry": {"coordinates":[0.53985451491951,51.37036760855255],"type":"Point"}
}