{
  "type": "Feature",
  "properties": {
    "iso:country":"GB",
    "wof:name":"CV5 9DP",
    "wof:placetype":"postalcode"
},
  "geometry": {"coordinates":[-1.55885323600252,52.42668376637701],"type":"Point"}
}