{
  "type": "Feature",
  "properties": {
    "iso:country": "GB",
    "wof:name": "CV5 9DP",
    "wof:placetype": "postalcode"
  },
  "geometry": {"coordinates":[-1.558853,52.426684],"type":"Point"}
}
