{
  "type": "Feature",
  "properties": {
    "iso:country":"GB",
    "wof:name":"NG19 7PT",
    "wof:placetype":"postalcode"
},
  "geometry": {"coordinates":[-1.25114597375679,53.17055131063078],"type":"Point"}
}