{
  "type": "Feature",
  "properties": {
    "iso:country":"GB",
    "wof:name":"SW15 3HX",
    "wof:placetype":"postalcode"
},
  "geometry": {"coordinates":[-0.21833218098896,51.45019646368237],"type":"Point"}
}