{
  "type": "Feature",
  "properties": {
    "iso:country": "GB",
    "wof:name": "PO33 4BT",
    "wof:placetype": "postalcode"
  },
  "geometry": {"coordinates":[-1.177766,50.699954],"type":"Point"}
}
