{
  "type": "Feature",
  "properties": {
    "iso:country":"GB",
    "wof:name":"PO33 4BT",
    "wof:placetype":"postalcode"
},
  "geometry": {"coordinates":[-1.17777659822066,50.69996533112945],"type":"Point"}
}