{
  "type": "Feature",
  "properties": {
    "iso:country":"GB",
    "wof:name":"KA26 9LB",
    "wof:placetype":"postalcode"
},
  "geometry": {"coordinates":[-4.7577369865303,55.28728249924514],"type":"Point"}
}