{
  "type": "Feature",
  "properties": {
    "date:inception_lower":"2004-05-01",
    "date:inception_upper":"2004-05-31",
    "iso:country":"GB",
    "wof:name":"CH2 1JL",
    "wof:placetype":"postalcode"
},
  "geometry": {"coordinates":[-2.878514,53.220783],"type":"Point"}
}