{
  "type": "Feature",
  "properties": {
    "iso:country": "GB",
    "wof:name": "BS7 9LD",
    "wof:placetype": "postalcode"
  },
  "geometry": {"coordinates":[-2.578938,51.478521],"type":"Point"}
}
