{
  "type": "Feature",
  "properties": {
    "iso:country":"GB",
    "wof:name":"GL6 0RB",
    "wof:placetype":"postalcode"
},
  "geometry": {"coordinates":[-2.22274193467882,51.69438922240415],"type":"Point"}
}