{
  "type": "Feature",
  "properties": {
    "iso:country": "GB",
    "wof:name": "GL6 0RB",
    "wof:placetype": "postalcode"
  },
  "geometry": {"coordinates":[-2.222742,51.694389],"type":"Point"}
}
