{
  "type": "Feature",
  "properties": {
    "date:inception_lower": "1991-01-01",
    "date:inception_upper": "1991-01-01",
    "iso:country": "GB",
    "wof:name": "GL6 0RB",
    "wof:placetype": "postalcode"
  },
  "geometry": {"coordinates":[-2.222742,51.694389],"type":"Point"}
}
