{
  "type": "Feature",
  "properties": {
    "iso:country":"GB",
    "wof:name":"CH46 9RR",
    "wof:placetype":"postalcode"
},
  "geometry": {"coordinates":[-3.09768265457801,53.39867718923369],"type":"Point"}
}