{
  "type": "Feature",
  "properties": {
    "iso:country": "GB",
    "wof:name": "G3 7BQ",
    "wof:placetype": "postalcode"
  },
  "geometry": {"coordinates":[-4.276601,55.863387],"type":"Point"}
}
