{
  "type": "Feature",
  "properties": {
    "iso:country":"GB",
    "wof:name":"CA22 2AX",
    "wof:placetype":"postalcode"
},
  "geometry": {"coordinates":[-3.52767199062929,54.47957082292015],"type":"Point"}
}