{
  "type": "Feature",
  "properties": {
    "iso:country": "GB",
    "wof:name": "SW11 3YS",
    "wof:placetype": "postalcode"
  },
  "geometry": {"coordinates":[-0.179579,51.46818],"type":"Point"}
}
