{
  "type": "Feature",
  "properties": {
    "iso:country":"GB",
    "wof:name":"BS23 2PE",
    "wof:placetype":"postalcode"
},
  "geometry": {"coordinates":[-2.97029579434811,51.35506582136548],"type":"Point"}
}