{
  "type": "Feature",
  "properties": {
    "date:inception_lower": "1980-01-01",
    "date:inception_upper": "1980-01-01",
    "iso:country": "GB",
    "wof:name": "SA32 7JQ",
    "wof:placetype": "postalcode"
  },
  "geometry": {"coordinates":[-4.203854,51.940207],"type":"Point"}
}
