{
  "type": "Feature",
  "properties": {
    "iso:country":"GB",
    "wof:name":"PL27 7SN",
    "wof:placetype":"postalcode"
},
  "geometry": {"coordinates":[-4.85145167529264,50.51913569785594],"type":"Point"}
}