{
  "type": "Feature",
  "properties": {
    "date:inception_lower": "2013-07-01",
    "date:inception_upper": "2013-07-01",
    "iso:country": "GB",
    "wof:name": "PL27 7SN",
    "wof:placetype": "postalcode"
  },
  "geometry": {"coordinates":[-4.851452,50.519136],"type":"Point"}
}
