{
  "type": "Feature",
  "properties": {
    "iso:country":"GB",
    "wof:name":"WN7 5RZ",
    "wof:placetype":"postalcode"
},
  "geometry": {"coordinates":[-2.5250473089547,53.50384388954595],"type":"Point"}
}