{
  "type": "Feature",
  "properties": {
    "iso:country":"GB",
    "wof:name":"LU1 5SA",
    "wof:placetype":"postalcode"
},
  "geometry": {"coordinates":[-0.41839228815853,51.87504251489343],"type":"Point"}
}