{
  "type": "Feature",
  "properties": {
    "date:inception_lower":"1990-07-01",
    "date:inception_upper":"1990-07-31",
    "iso:country":"GB",
    "wof:name":"LU1 5SA",
    "wof:placetype":"postalcode"
},
  "geometry": {"coordinates":[-0.418392,51.875043],"type":"Point"}
}