{
  "type": "Feature",
  "properties": {
    "iso:country":"GB",
    "wof:name":"CF3 4DF",
    "wof:placetype":"postalcode"
},
  "geometry": {"coordinates":[-3.13624497288673,51.50428775433112],"type":"Point"}
}