{
  "type": "Feature",
  "properties": {
    "date:inception_lower": "1980-01-01",
    "date:inception_upper": "1980-01-01",
    "iso:country": "GB",
    "wof:name": "LA14 5NX",
    "wof:placetype": "postalcode"
  },
  "geometry": {"coordinates":[-3.223181,54.124125],"type":"Point"}
}
