{
  "type": "Feature",
  "properties": {
    "iso:country": "GB",
    "wof:name": "CF83 8SX",
    "wof:placetype": "postalcode"
  },
  "geometry": {"coordinates":[-3.130855,51.595535],"type":"Point"}
}
