{
  "type": "Feature",
  "properties": {
    "iso:country":"GB",
    "wof:name":"CF83 8SX",
    "wof:placetype":"postalcode"
},
  "geometry": {"coordinates":[-3.13085506062658,51.59553451354093],"type":"Point"}
}