{
  "type": "Feature",
  "properties": {
    "date:inception_lower": "2008-04-01",
    "date:inception_upper": "2008-04-01",
    "iso:country": "GB",
    "wof:name": "DL14 8NH",
    "wof:placetype": "postalcode"
  },
  "geometry": {"coordinates":[-1.634603,54.659543],"type":"Point"}
}
