{
  "type": "Feature",
  "properties": {
    "iso:country": "GB",
    "wof:name": "DL14 8NH",
    "wof:placetype": "postalcode"
  },
  "geometry": {"coordinates":[-1.634603,54.659543],"type":"Point"}
}
