{
  "type": "Feature",
  "properties": {
    "iso:country":"GB",
    "wof:name":"DL14 8NH",
    "wof:placetype":"postalcode"
},
  "geometry": {"coordinates":[-1.63460264111184,54.65954281157839],"type":"Point"}
}