{
  "type": "Feature",
  "properties": {
    "iso:country":"GB",
    "wof:name":"WA15 9BZ",
    "wof:placetype":"postalcode"
},
  "geometry": {"coordinates":[-2.33613766628906,53.3761773674681],"type":"Point"}
}