{
  "type": "Feature",
  "properties": {
    "iso:country":"GB",
    "wof:name":"SS8 9HD",
    "wof:placetype":"postalcode"
},
  "geometry": {"coordinates":[0.57886284975131,51.52048127123425],"type":"Point"}
}