{
  "type": "Feature",
  "properties": {
    "iso:country":"GB",
    "wof:name":"NW9 5NY",
    "wof:placetype":"postalcode"
},
  "geometry": {"coordinates":[-0.24343129823804,51.59855376605464],"type":"Point"}
}