{
  "type": "Feature",
  "properties": {
    "iso:country": "GB",
    "wof:name": "LD2 3LT",
    "wof:placetype": "postalcode"
  },
  "geometry": {"coordinates":[-3.543178,52.169701],"type":"Point"}
}
