{
  "type": "Feature",
  "properties": {
    "iso:country": "GB",
    "wof:name": "CV11 4XE",
    "wof:placetype": "postalcode"
  },
  "geometry": {"coordinates":[-1.450482,52.503518],"type":"Point"}
}
