{
  "type": "Feature",
  "properties": {
    "iso:country":"GB",
    "wof:name":"CV11 4XE",
    "wof:placetype":"postalcode"
},
  "geometry": {"coordinates":[-1.4504817046617,52.5035178488215],"type":"Point"}
}