{
  "type": "Feature",
  "properties": {
    "date:inception_lower": "2023-04-01",
    "date:inception_upper": "2023-04-01",
    "iso:country": "GB",
    "wof:name": "PR2 9ZZ",
    "wof:placetype": "postalcode"
  },
  "geometry": {"coordinates":[-2.690019,53.796859],"type":"Point"}
}
