{
  "type": "Feature",
  "properties": {
    "iso:country": "GB",
    "wof:name": "PR2 9ZZ",
    "wof:placetype": "postalcode"
  },
  "geometry": {"coordinates":[-2.690022,53.796844],"type":"Point"}
}
