{
  "type": "Feature",
  "properties": {
    "iso:country":"GB",
    "wof:name":"KY8 1AT",
    "wof:placetype":"postalcode"
},
  "geometry": {"coordinates":[-3.03504775171855,56.17002775646201],"type":"Point"}
}