{
  "type": "Feature",
  "properties": {
    "iso:country": "GB",
    "wof:name": "KY8 1AT",
    "wof:placetype": "postalcode"
  },
  "geometry": {"coordinates":[-3.035149,56.170074],"type":"Point"}
}
