{
  "type": "Feature",
  "properties": {
    "date:inception_lower": "1980-01-01",
    "date:inception_upper": "1980-01-01",
    "iso:country": "GB",
    "wof:name": "KY8 1AT",
    "wof:placetype": "postalcode"
  },
  "geometry": {"coordinates":[-3.035149,56.170074],"type":"Point"}
}
