{
  "type": "Feature",
  "properties": {
    "iso:country": "GB",
    "wof:name": "SW15 1BF",
    "wof:placetype": "postalcode"
  },
  "geometry": {"coordinates":[-0.221787,51.466229],"type":"Point"}
}
