{
  "type": "Feature",
  "properties": {
    "iso:country":"GB",
    "wof:name":"SW15 1BF",
    "wof:placetype":"postalcode"
},
  "geometry": {"coordinates":[-0.22179655597846,51.46622872196226],"type":"Point"}
}