{
  "type": "Feature",
  "properties": {
    "iso:country":"GB",
    "wof:name":"GL54 1AG",
    "wof:placetype":"postalcode"
},
  "geometry": {"coordinates":[-1.72060974589092,51.92893462398325],"type":"Point"}
}