{
  "type": "Feature",
  "properties": {
    "iso:country":"GB",
    "wof:name":"AL2 1HE",
    "wof:placetype":"postalcode"
},
  "geometry": {"coordinates":[-0.29703150035952,51.72419033332009],"type":"Point"}
}