{
  "type": "Feature",
  "properties": {
    "date:inception_lower":"2001-06-01",
    "date:inception_upper":"2001-06-30",
    "iso:country":"GB",
    "wof:name":"AL2 1HE",
    "wof:placetype":"postalcode"
},
  "geometry": {"coordinates":[-0.297031,51.72419],"type":"Point"}
}