{
  "type": "Feature",
  "properties": {
    "iso:country":"GB",
    "wof:name":"RG23 8ED",
    "wof:placetype":"postalcode"
},
  "geometry": {"coordinates":[-1.12057256426181,51.27078615854523],"type":"Point"}
}