{
  "type": "Feature",
  "properties": {
    "iso:country":"GB",
    "wof:name":"OL3 6BU",
    "wof:placetype":"postalcode"
},
  "geometry": {"coordinates":[-2.00343325151062,53.55197116698163],"type":"Point"}
}