{
  "type": "Feature",
  "properties": {
    "date:inception_lower":"1980-01-01",
    "date:inception_upper":"1980-01-31",
    "iso:country":"GB",
    "wof:name":"RH14 0RQ",
    "wof:placetype":"postalcode"
},
  "geometry": {"coordinates":[-0.515508,51.064404],"type":"Point"}
}