{
  "type": "Feature",
  "properties": {
    "iso:country":"GB",
    "wof:name":"RH14 0RQ",
    "wof:placetype":"postalcode"
},
  "geometry": {"coordinates":[-0.51550802479035,51.06440367008717],"type":"Point"}
}