{
  "type": "Feature",
  "properties": {
    "iso:country": "GB",
    "wof:name": "AL2 1FH",
    "wof:placetype": "postalcode"
  },
  "geometry": {"coordinates":[-0.296738,51.725832],"type":"Point"}
}
