{
  "type": "Feature",
  "properties": {
    "iso:country":"GB",
    "wof:name":"CA28 7PQ",
    "wof:placetype":"postalcode"
},
  "geometry": {"coordinates":[-3.583615258276,54.54881319769446],"type":"Point"}
}