{
  "type": "Feature",
  "properties": {
    "iso:country":"GB",
    "wof:name":"G5 8PN",
    "wof:placetype":"postalcode"
},
  "geometry": {"coordinates":[-4.27007373725488,55.85314461485032],"type":"Point"}
}