{
  "type": "Feature",
  "properties": {
    "iso:country":"GB",
    "wof:name":"SN10 1JL",
    "wof:placetype":"postalcode"
},
  "geometry": {"coordinates":[-1.99791160890922,51.3535290642979],"type":"Point"}
}