{
  "type": "Feature",
  "properties": {
    "iso:country": "GB",
    "wof:name": "NE31 2BH",
    "wof:placetype": "postalcode"
  },
  "geometry": {"coordinates":[-1.504931,54.958801],"type":"Point"}
}
