{
  "type": "Feature",
  "properties": {
    "iso:country": "GB",
    "wof:name": "G83 0PW",
    "wof:placetype": "postalcode"
  },
  "geometry": {"coordinates":[-4.578653,55.988428],"type":"Point"}
}
