{
  "type": "Feature",
  "properties": {
    "iso:country":"GB",
    "wof:name":"G83 0PW",
    "wof:placetype":"postalcode"
},
  "geometry": {"coordinates":[-4.57865296096298,55.98842775588231],"type":"Point"}
}