{
  "type": "Feature",
  "properties": {
    "date:inception_lower": "1983-03-01",
    "date:inception_upper": "1983-03-01",
    "iso:country": "GB",
    "wof:name": "TN34 1UR",
    "wof:placetype": "postalcode"
  },
  "geometry": {"coordinates":[0.57298,50.857186],"type":"Point"}
}
