{
  "type": "Feature",
  "properties": {
    "date:inception_lower":"1993-01-01",
    "date:inception_upper":"1993-01-31",
    "iso:country":"GB",
    "wof:name":"HA9 7NQ",
    "wof:placetype":"postalcode"
},
  "geometry": {"coordinates":[-0.29894,51.565329],"type":"Point"}
}