{
  "type": "Feature",
  "properties": {
    "iso:country": "GB",
    "wof:name": "HA9 7NQ",
    "wof:placetype": "postalcode"
  },
  "geometry": {"coordinates":[-0.29894,51.565329],"type":"Point"}
}
