{
  "type": "Feature",
  "properties": {
    "iso:country":"GB",
    "wof:name":"HA9 7NQ",
    "wof:placetype":"postalcode"
},
  "geometry": {"coordinates":[-0.29914987158032,51.56532976840094],"type":"Point"}
}