{
  "type": "Feature",
  "properties": {
    "iso:country":"GB",
    "wof:name":"BD5 7NL",
    "wof:placetype":"postalcode"
},
  "geometry": {"coordinates":[-1.7614138113972,53.77884708790332],"type":"Point"}
}