{
  "type": "Feature",
  "properties": {
    "iso:country":"GB",
    "wof:name":"WD18 0SH",
    "wof:placetype":"postalcode"
},
  "geometry": {"coordinates":[-0.40727696700539,51.6502667166436],"type":"Point"}
}