{
  "type": "Feature",
  "properties": {
    "date:inception_lower":"2005-12-01",
    "date:inception_upper":"2005-12-31",
    "iso:country":"GB",
    "wof:name":"SN10 5LY",
    "wof:placetype":"postalcode"
},
  "geometry": {"coordinates":[-2.00473,51.328379],"type":"Point"}
}