{
  "type": "Feature",
  "properties": {
    "iso:country":"GB",
    "wof:name":"RH2 9PN",
    "wof:placetype":"postalcode"
},
  "geometry": {"coordinates":[-0.19788164278445,51.25106496666813],"type":"Point"}
}