{
  "type": "Feature",
  "properties": {
    "date:inception_lower": "2018-12-01",
    "date:inception_upper": "2018-12-01",
    "iso:country": "GB",
    "wof:name": "BA13 3ZG",
    "wof:placetype": "postalcode"
  },
  "geometry": {"coordinates":[-2.177683,51.26849],"type":"Point"}
}
