{
  "type": "Feature",
  "properties": {
    "iso:country":"GB",
    "wof:name":"G84 8DB",
    "wof:placetype":"postalcode"
},
  "geometry": {"coordinates":[-4.74333409226283,56.00766594529542],"type":"Point"}
}