{
  "type": "Feature",
  "properties": {
    "iso:country":"GB",
    "wof:name":"SE19 3LQ",
    "wof:placetype":"postalcode"
},
  "geometry": {"coordinates":[-0.08736182734986,51.41028256523126],"type":"Point"}
}