{
  "type": "Feature",
  "properties": {
    "iso:country": "GB",
    "wof:name": "NN16 8RJ",
    "wof:placetype": "postalcode"
  },
  "geometry": {"coordinates":[-0.722528,52.404604],"type":"Point"}
}
