{
  "type": "Feature",
  "properties": {
    "date:inception_lower":"2010-04-01",
    "date:inception_upper":"2010-04-30",
    "iso:country":"GB",
    "wof:name":"IP20 0PY",
    "wof:placetype":"postalcode"
},
  "geometry": {"coordinates":[1.390789,52.399908],"type":"Point"}
}