{
  "type": "Feature",
  "properties": {
    "date:inception_lower": "2023-06-01",
    "date:inception_upper": "2023-06-01",
    "iso:country": "GB",
    "wof:name": "LE3 5BQ",
    "wof:placetype": "postalcode"
  },
  "geometry": {"coordinates":[-1.142792,52.638213],"type":"Point"}
}
