{
  "type": "Feature",
  "properties": {
    "date:inception_lower": "2023-06-01",
    "date:inception_upper": "2023-06-01",
    "iso:country": "GB",
    "wof:name": "LE3 5BQ",
    "wof:placetype": "postalcode"
  },
  "geometry": {"coordinates":[-1.142791,52.638267],"type":"Point"}
}
