{
  "type": "Feature",
  "properties": {
    "iso:country": "GB",
    "wof:name": "EN5 4RL",
    "wof:placetype": "postalcode"
  },
  "geometry": {"coordinates":[-0.202959,51.672397],"type":"Point"}
}
