{
  "type": "Feature",
  "properties": {
    "iso:country":"GB",
    "wof:name":"EN5 4RL",
    "wof:placetype":"postalcode"
},
  "geometry": {"coordinates":[-0.20295934534773,51.67239707524089],"type":"Point"}
}