{
  "type": "Feature",
  "properties": {
    "iso:country":"GB",
    "wof:name":"YO24 1BG",
    "wof:placetype":"postalcode"
},
  "geometry": {"coordinates":[-1.09524942612452,53.95187699268166],"type":"Point"}
}