{
  "type": "Feature",
  "properties": {
    "date:inception_lower":"2006-07-01",
    "date:inception_upper":"2006-07-31",
    "iso:country":"GB",
    "wof:name":"YO24 1BG",
    "wof:placetype":"postalcode"
},
  "geometry": {"coordinates":[-1.095249,53.951877],"type":"Point"}
}