{
  "type": "Feature",
  "properties": {
    "iso:country":"GB",
    "wof:name":"E5 8EG",
    "wof:placetype":"postalcode"
},
  "geometry": {"coordinates":[-0.05609492421173,51.55671691318461],"type":"Point"}
}