{
  "type": "Feature",
  "properties": {
    "iso:country":"GB",
    "wof:name":"GL2 0SD",
    "wof:placetype":"postalcode"
},
  "geometry": {"coordinates":[-2.21910419803774,51.86644874499397],"type":"Point"}
}