{
  "type": "Feature",
  "properties": {
    "date:inception_lower":"1980-01-01",
    "date:inception_upper":"1980-01-31",
    "iso:country":"GB",
    "wof:name":"GL2 0SD",
    "wof:placetype":"postalcode"
},
  "geometry": {"coordinates":[-2.219104,51.866449],"type":"Point"}
}