{
  "type": "Feature",
  "properties": {
    "iso:country":"GB",
    "wof:name":"NE46 2BB",
    "wof:placetype":"postalcode"
},
  "geometry": {"coordinates":[-2.1099741481026,54.96595022529431],"type":"Point"}
}