{
  "type": "Feature",
  "properties": {
    "date:inception_lower": "1980-01-01",
    "date:inception_upper": "1980-01-01",
    "iso:country": "GB",
    "wof:name": "UB1 3NX",
    "wof:placetype": "postalcode"
  },
  "geometry": {"coordinates":[-0.356837,51.51638],"type":"Point"}
}
