{
  "type": "Feature",
  "properties": {
    "iso:country":"GB",
    "wof:name":"CW1 3RA",
    "wof:placetype":"postalcode"
},
  "geometry": {"coordinates":[-2.44723539847623,53.11332861714381],"type":"Point"}
}