{
  "type": "Feature",
  "properties": {
    "date:inception_lower": "1980-01-01",
    "date:inception_upper": "1980-01-01",
    "iso:country": "GB",
    "wof:name": "CW1 3RA",
    "wof:placetype": "postalcode"
  },
  "geometry": {"coordinates":[-2.447235,53.113329],"type":"Point"}
}
