{
  "type": "Feature",
  "properties": {
    "iso:country":"GB",
    "wof:name":"WF9 1EJ",
    "wof:placetype":"postalcode"
},
  "geometry": {"coordinates":[-1.26554483412849,53.61836296025251],"type":"Point"}
}