{
  "type": "Feature",
  "properties": {
    "date:inception_lower":"1980-01-01",
    "date:inception_upper":"1980-01-31",
    "iso:country":"GB",
    "wof:name":"WF9 1EJ",
    "wof:placetype":"postalcode"
},
  "geometry": {"coordinates":[-1.265545,53.618363],"type":"Point"}
}