{
  "type": "Feature",
  "properties": {
    "iso:country": "GB",
    "wof:name": "WF9 1EJ",
    "wof:placetype": "postalcode"
  },
  "geometry": {"coordinates":[-1.265545,53.618363],"type":"Point"}
}
