{
  "type": "Feature",
  "properties": {
    "iso:country":"GB",
    "wof:name":"PE31 7PU",
    "wof:placetype":"postalcode"
},
  "geometry": {"coordinates":[0.50355935579727,52.8768810937139],"type":"Point"}
}