{
  "type": "Feature",
  "properties": {
    "iso:country":"GB",
    "wof:name":"DE14 3HD",
    "wof:placetype":"postalcode"
},
  "geometry": {"coordinates":[-1.6812328615137,52.78185931002801],"type":"Point"}
}