{
  "type": "Feature",
  "properties": {
    "date:inception_lower":"2016-12-01",
    "date:inception_upper":"2016-12-31",
    "iso:country":"GB",
    "wof:name":"CO4 9TG",
    "wof:placetype":"postalcode"
},
  "geometry": {"coordinates":[0.925744,51.920563],"type":"Point"}
}