{
  "type": "Feature",
  "properties": {
    "date:inception_lower": "1999-06-01",
    "date:inception_upper": "1999-06-01",
    "iso:country": "GB",
    "wof:name": "NP23 6TP",
    "wof:placetype": "postalcode"
  },
  "geometry": {"coordinates":[-3.192577,51.753671],"type":"Point"}
}
