{
  "type": "Feature",
  "properties": {
    "date:inception_lower": "2019-02-01",
    "date:inception_upper": "2019-02-01",
    "iso:country": "GB",
    "wof:name": "EH17 8GR",
    "wof:placetype": "postalcode"
  },
  "geometry": {"coordinates":[-3.128345,55.902128],"type":"Point"}
}
