{
  "type": "Feature",
  "properties": {
    "iso:country":"GB",
    "wof:name":"GU51 1GJ",
    "wof:placetype":"postalcode"
},
  "geometry": {"coordinates":[-0.84497921556561,51.2938850478732],"type":"Point"}
}