{
  "type": "Feature",
  "properties": {
    "date:inception_lower": "2007-07-01",
    "date:inception_upper": "2007-07-01",
    "iso:country": "GB",
    "wof:name": "GU51 1GJ",
    "wof:placetype": "postalcode"
  },
  "geometry": {"coordinates":[-0.844979,51.293885],"type":"Point"}
}
