{
  "type": "Feature",
  "properties": {
    "date:inception_lower": "1980-01-01",
    "date:inception_upper": "1980-01-01",
    "iso:country": "GB",
    "wof:name": "KY3 0DH",
    "wof:placetype": "postalcode"
  },
  "geometry": {"coordinates":[-3.245678,56.05867],"type":"Point"}
}
