{
  "type": "Feature",
  "properties": {
    "iso:country": "GB",
    "wof:name": "CH6 6EL",
    "wof:placetype": "postalcode"
  },
  "geometry": {"coordinates":[-3.17333,53.267758],"type":"Point"}
}
