{
  "type": "Feature",
  "properties": {
    "iso:country":"GB",
    "wof:name":"BB3 0PN",
    "wof:placetype":"postalcode"
},
  "geometry": {"coordinates":[-2.48058284003782,53.71906781873297],"type":"Point"}
}