{
  "type": "Feature",
  "properties": {
    "iso:country":"GB",
    "wof:name":"YO14 9AA",
    "wof:placetype":"postalcode"
},
  "geometry": {"coordinates":[-0.28884637085988,54.20921053278575],"type":"Point"}
}