{
  "type": "Feature",
  "properties": {
    "iso:country": "GB",
    "wof:name": "NE2 2AG",
    "wof:placetype": "postalcode"
  },
  "geometry": {"coordinates":[-1.606032,54.987685],"type":"Point"}
}
