{
  "type": "Feature",
  "properties": {
    "iso:country":"GB",
    "wof:name":"NE2 2AG",
    "wof:placetype":"postalcode"
},
  "geometry": {"coordinates":[-1.60603219049312,54.98768481547469],"type":"Point"}
}