{
  "type": "Feature",
  "properties": {
    "iso:country":"GB",
    "wof:name":"WN6 8AD",
    "wof:placetype":"postalcode"
},
  "geometry": {"coordinates":[-2.68538546912244,53.58024326406849],"type":"Point"}
}