{
  "type": "Feature",
  "properties": {
    "iso:country":"GB",
    "wof:name":"TR1 2HP",
    "wof:placetype":"postalcode"
},
  "geometry": {"coordinates":[-5.05710900088112,50.25531644390562],"type":"Point"}
}