{
  "type": "Feature",
  "properties": {
    "iso:country": "GB",
    "wof:name": "CB5 8QT",
    "wof:placetype": "postalcode"
  },
  "geometry": {"coordinates":[0.167604,52.217632],"type":"Point"}
}
