{
  "type": "Feature",
  "properties": {
    "iso:country":"GB",
    "wof:name":"CB5 8QT",
    "wof:placetype":"postalcode"
},
  "geometry": {"coordinates":[0.16760391529506,52.2176319598398],"type":"Point"}
}