{
  "type": "Feature",
  "properties": {
    "iso:country":"GB",
    "wof:name":"SW16 1LH",
    "wof:placetype":"postalcode"
},
  "geometry": {"coordinates":[-0.13375405255615,51.43773867958227],"type":"Point"}
}