{
  "type": "Feature",
  "properties": {
    "date:inception_lower": "1980-01-01",
    "date:inception_upper": "1980-01-01",
    "iso:country": "GB",
    "wof:name": "RG2 8JJ",
    "wof:placetype": "postalcode"
  },
  "geometry": {"coordinates":[-0.956049,51.421364],"type":"Point"}
}
