{
  "type": "Feature",
  "properties": {
    "iso:country":"GB",
    "wof:name":"NR19 1RD",
    "wof:placetype":"postalcode"
},
  "geometry": {"coordinates":[0.95977341051535,52.65319021614896],"type":"Point"}
}