{
  "type": "Feature",
  "properties": {
    "iso:country":"GB",
    "wof:name":"YO25 3HF",
    "wof:placetype":"postalcode"
},
  "geometry": {"coordinates":[-0.61223131253866,54.04411966865292],"type":"Point"}
}