{
  "type": "Feature",
  "properties": {
    "iso:country": "GB",
    "wof:name": "YO25 3HF",
    "wof:placetype": "postalcode"
  },
  "geometry": {"coordinates":[-0.612231,54.04412],"type":"Point"}
}
