{
  "type": "Feature",
  "properties": {
    "iso:country":"GB",
    "wof:name":"NN6 9EW",
    "wof:placetype":"postalcode"
},
  "geometry": {"coordinates":[-0.90729910959167,52.32921856926458],"type":"Point"}
}