{
  "type": "Feature",
  "properties": {
    "iso:country": "GB",
    "wof:name": "TN21 0UD",
    "wof:placetype": "postalcode"
  },
  "geometry": {"coordinates":[0.220614,50.97687],"type":"Point"}
}
