{
  "type": "Feature",
  "properties": {
    "iso:country": "GB",
    "wof:name": "SS3 0AD",
    "wof:placetype": "postalcode"
  },
  "geometry": {"coordinates":[0.808319,51.554333],"type":"Point"}
}
