{
  "type": "Feature",
  "properties": {
    "date:inception_lower": "1990-02-01",
    "date:inception_upper": "1990-02-01",
    "iso:country": "GB",
    "wof:name": "SL2 3SN",
    "wof:placetype": "postalcode"
  },
  "geometry": {"coordinates":[-0.638044,51.550509],"type":"Point"}
}
