{
  "type": "Feature",
  "properties": {
    "iso:country":"GB",
    "wof:name":"SL2 3SN",
    "wof:placetype":"postalcode"
},
  "geometry": {"coordinates":[-0.63804369742163,51.5505092510797],"type":"Point"}
}