{
  "type": "Feature",
  "properties": {
    "iso:country":"GB",
    "wof:name":"DE13 8TJ",
    "wof:placetype":"postalcode"
},
  "geometry": {"coordinates":[-1.7444992538727,52.84186418412514],"type":"Point"}
}