{
  "type": "Feature",
  "properties": {
    "iso:country":"GB",
    "wof:name":"DG11 1NR",
    "wof:placetype":"postalcode"
},
  "geometry": {"coordinates":[-3.43873393659241,55.12833008547086],"type":"Point"}
}