{
  "type": "Feature",
  "properties": {
    "date:inception_lower": "1980-01-01",
    "date:inception_upper": "1980-01-01",
    "iso:country": "GB",
    "wof:name": "DG11 1NR",
    "wof:placetype": "postalcode"
  },
  "geometry": {"coordinates":[-3.438731,55.128335],"type":"Point"}
}
