{
  "type": "Feature",
  "properties": {
    "date:inception_lower": "2012-10-01",
    "date:inception_upper": "2012-10-01",
    "iso:country": "GB",
    "wof:name": "G42 7AU",
    "wof:placetype": "postalcode"
  },
  "geometry": {"coordinates":[-4.256915,55.839753],"type":"Point"}
}
