{
  "type": "Feature",
  "properties": {
    "iso:country":"GB",
    "wof:name":"WN6 8ND",
    "wof:placetype":"postalcode"
},
  "geometry": {"coordinates":[-2.66642019395633,53.56329931008762],"type":"Point"}
}