{
  "type": "Feature",
  "properties": {
    "date:inception_lower": "1991-01-01",
    "date:inception_upper": "1991-01-01",
    "iso:country": "GB",
    "wof:name": "WN6 8ND",
    "wof:placetype": "postalcode"
  },
  "geometry": {"coordinates":[-2.66642,53.563299],"type":"Point"}
}
