{
  "type": "Feature",
  "properties": {
    "iso:country": "GB",
    "wof:name": "MK41 7QD",
    "wof:placetype": "postalcode"
  },
  "geometry": {"coordinates":[-0.461633,52.15222],"type":"Point"}
}
