{
  "type": "Feature",
  "properties": {
    "iso:country":"GB",
    "wof:name":"BH20 5AR",
    "wof:placetype":"postalcode"
},
  "geometry": {"coordinates":[-2.09862885632557,50.65403539977675],"type":"Point"}
}