{
  "type": "Feature",
  "properties": {
    "iso:country": "GB",
    "wof:name": "BH20 5AR",
    "wof:placetype": "postalcode"
  },
  "geometry": {"coordinates":[-2.098629,50.654035],"type":"Point"}
}
