{
  "type": "Feature",
  "properties": {
    "iso:country": "GB",
    "wof:name": "B61 8AS",
    "wof:placetype": "postalcode"
  },
  "geometry": {"coordinates":[-2.06001,52.335773],"type":"Point"}
}
