{
  "type": "Feature",
  "properties": {
    "iso:country":"GB",
    "wof:name":"OL9 8PD",
    "wof:placetype":"postalcode"
},
  "geometry": {"coordinates":[-2.14274356779284,53.53750438073079],"type":"Point"}
}