{
  "type": "Feature",
  "properties": {
    "iso:country": "GB",
    "wof:name": "OL9 8PD",
    "wof:placetype": "postalcode"
  },
  "geometry": {"coordinates":[-2.142744,53.537504],"type":"Point"}
}
