{
  "type": "Feature",
  "properties": {
    "iso:country":"GB",
    "wof:name":"SR3 3PL",
    "wof:placetype":"postalcode"
},
  "geometry": {"coordinates":[-1.4381738462113,54.87244910692814],"type":"Point"}
}