{
  "type": "Feature",
  "properties": {
    "date:inception_lower":"1980-01-01",
    "date:inception_upper":"1980-01-31",
    "iso:country":"GB",
    "wof:name":"DY4 9NH",
    "wof:placetype":"postalcode"
},
  "geometry": {"coordinates":[-2.064536,52.540096],"type":"Point"}
}