{
  "type": "Feature",
  "properties": {
    "date:inception_lower": "1980-01-01",
    "date:inception_upper": "1980-01-01",
    "iso:country": "GB",
    "wof:name": "GL6 6ER",
    "wof:placetype": "postalcode"
  },
  "geometry": {"coordinates":[-2.2497,51.752921],"type":"Point"}
}
