{
  "type": "Feature",
  "properties": {
    "iso:country":"GB",
    "wof:name":"RM10 7AX",
    "wof:placetype":"postalcode"
},
  "geometry": {"coordinates":[0.1635646481127,51.55625290989567],"type":"Point"}
}