{
  "type": "Feature",
  "properties": {
    "date:inception_lower": "1980-01-01",
    "date:inception_upper": "1980-01-01",
    "iso:country": "GB",
    "wof:name": "RM10 7AX",
    "wof:placetype": "postalcode"
  },
  "geometry": {"coordinates":[0.163565,51.556253],"type":"Point"}
}
