{
  "type": "Feature",
  "properties": {
    "iso:country":"GB",
    "wof:name":"PL17 7NU",
    "wof:placetype":"postalcode"
},
  "geometry": {"coordinates":[-4.31505701745353,50.50933271704049],"type":"Point"}
}