{
  "type": "Feature",
  "properties": {
    "date:inception_lower": "1999-06-01",
    "date:inception_upper": "1999-06-01",
    "iso:country": "GB",
    "wof:name": "CH41 9HD",
    "wof:placetype": "postalcode"
  },
  "geometry": {"coordinates":[-3.01481,53.379635],"type":"Point"}
}
