{
  "type": "Feature",
  "properties": {
    "iso:country": "GB",
    "wof:name": "CH41 9HD",
    "wof:placetype": "postalcode"
  },
  "geometry": {"coordinates":[-3.01481,53.379635],"type":"Point"}
}
