{
  "type": "Feature",
  "properties": {
    "iso:country":"GB",
    "wof:name":"SR1 2QT",
    "wof:placetype":"postalcode"
},
  "geometry": {"coordinates":[-1.37746836123276,54.90238389146858],"type":"Point"}
}