{
  "type": "Feature",
  "properties": {
    "iso:country": "GB",
    "wof:name": "CO9 3EJ",
    "wof:placetype": "postalcode"
  },
  "geometry": {"coordinates":[0.598993,51.989827],"type":"Point"}
}
