{
  "type": "Feature",
  "properties": {
    "iso:country":"GB",
    "wof:name":"WV6 7PZ",
    "wof:placetype":"postalcode"
},
  "geometry": {"coordinates":[-2.19610884107935,52.5952293927051],"type":"Point"}
}