{
  "type": "Feature",
  "properties": {
    "date:inception_lower": "2022-05-01",
    "date:inception_upper": "2022-05-01",
    "iso:country": "GB",
    "wof:name": "BN23 5BS",
    "wof:placetype": "postalcode"
  },
  "geometry": {"coordinates":[0.331988,50.801178],"type":"Point"}
}
