{
  "type": "Feature",
  "properties": {
    "date:inception_lower": "1980-01-01",
    "date:inception_upper": "1980-01-01",
    "iso:country": "GB",
    "wof:name": "TQ6 0JG",
    "wof:placetype": "postalcode"
  },
  "geometry": {"coordinates":[-3.599056,50.371322],"type":"Point"}
}
