{
  "type": "Feature",
  "properties": {
    "iso:country":"GB",
    "wof:name":"TQ6 0JG",
    "wof:placetype":"postalcode"
},
  "geometry": {"coordinates":[-3.59905617095458,50.37132231644794],"type":"Point"}
}