{
  "type": "Feature",
  "properties": {
    "date:inception_lower":"1980-01-01",
    "date:inception_upper":"1980-01-31",
    "iso:country":"GB",
    "wof:name":"GU24 8DD",
    "wof:placetype":"postalcode"
},
  "geometry": {"coordinates":[-0.616138,51.347966],"type":"Point"}
}