{
  "type": "Feature",
  "properties": {
    "iso:country": "GB",
    "wof:name": "GU24 8DD",
    "wof:placetype": "postalcode"
  },
  "geometry": {"coordinates":[-0.616138,51.347966],"type":"Point"}
}
