{
  "type": "Feature",
  "properties": {
    "iso:country":"GB",
    "wof:name":"GU24 8DD",
    "wof:placetype":"postalcode"
},
  "geometry": {"coordinates":[-0.61403221024077,51.34839983615043],"type":"Point"}
}