{
  "type": "Feature",
  "properties": {
    "iso:country":"GB",
    "wof:name":"HA7 1EB",
    "wof:placetype":"postalcode"
},
  "geometry": {"coordinates":[-0.28980249173497,51.59487732550622],"type":"Point"}
}