{
  "type": "Feature",
  "properties": {
    "iso:country": "GB",
    "wof:name": "BN6 8SE",
    "wof:placetype": "postalcode"
  },
  "geometry": {"coordinates":[-0.094381,50.948097],"type":"Point"}
}
