{
  "type": "Feature",
  "properties": {
    "iso:country":"GB",
    "wof:name":"BN6 8SE",
    "wof:placetype":"postalcode"
},
  "geometry": {"coordinates":[-0.09429337219767,50.94846904706041],"type":"Point"}
}