{
  "type": "Feature",
  "properties": {
    "iso:country":"GB",
    "wof:name":"GU3 3LX",
    "wof:placetype":"postalcode"
},
  "geometry": {"coordinates":[-0.61831460409364,51.2632480755486],"type":"Point"}
}