{
  "type": "Feature",
  "properties": {
    "iso:country":"GB",
    "wof:name":"TN31 6BQ",
    "wof:placetype":"postalcode"
},
  "geometry": {"coordinates":[0.60310852103377,50.99970573944293],"type":"Point"}
}