{
  "type": "Feature",
  "properties": {
    "iso:country": "GB",
    "wof:name": "TN31 6BQ",
    "wof:placetype": "postalcode"
  },
  "geometry": {"coordinates":[0.603109,50.999706],"type":"Point"}
}
