{
  "type": "Feature",
  "properties": {
    "date:inception_lower": "2011-08-01",
    "date:inception_upper": "2011-08-01",
    "iso:country": "GB",
    "wof:name": "TN31 6BQ",
    "wof:placetype": "postalcode"
  },
  "geometry": {"coordinates":[0.603109,50.999706],"type":"Point"}
}
