{
  "type": "Feature",
  "properties": {
    "iso:country": "GB",
    "wof:name": "SA63 4UN",
    "wof:placetype": "postalcode"
  },
  "geometry": {"coordinates":[-4.883694,51.850765],"type":"Point"}
}
