{
  "type": "Feature",
  "properties": {
    "iso:country":"GB",
    "wof:name":"YO24 3EP",
    "wof:placetype":"postalcode"
},
  "geometry": {"coordinates":[-1.1360673238892,53.94622729403435],"type":"Point"}
}