{
  "type": "Feature",
  "properties": {
    "date:inception_lower": "1986-07-01",
    "date:inception_upper": "1986-07-01",
    "iso:country": "GB",
    "wof:name": "NN9 5RQ",
    "wof:placetype": "postalcode"
  },
  "geometry": {"coordinates":[-0.620175,52.319642],"type":"Point"}
}
