{
  "type": "Feature",
  "properties": {
    "iso:country":"GB",
    "wof:name":"NN9 5RQ",
    "wof:placetype":"postalcode"
},
  "geometry": {"coordinates":[-0.62017541672818,52.31964206597875],"type":"Point"}
}