{
  "type": "Feature",
  "properties": {
    "iso:country": "GB",
    "wof:name": "TQ9 5AL",
    "wof:placetype": "postalcode"
  },
  "geometry": {"coordinates":[-3.680283,50.42745],"type":"Point"}
}
