{
  "type": "Feature",
  "properties": {
    "iso:country":"GB",
    "wof:name":"WV14 0NE",
    "wof:placetype":"postalcode"
},
  "geometry": {"coordinates":[-2.09271627613372,52.5699055467818],"type":"Point"}
}