{
  "type": "Feature",
  "properties": {
    "date:inception_lower": "2019-06-01",
    "date:inception_upper": "2019-06-01",
    "iso:country": "GB",
    "wof:name": "OX25 5BY",
    "wof:placetype": "postalcode"
  },
  "geometry": {"coordinates":[-1.270196,51.930269],"type":"Point"}
}
