{
  "type": "Feature",
  "properties": {
    "iso:country":"GB",
    "wof:name":"BB4 8EN",
    "wof:placetype":"postalcode"
},
  "geometry": {"coordinates":[-2.28712870337216,53.70940554899326],"type":"Point"}
}