{
  "type": "Feature",
  "properties": {
    "date:inception_lower": "1987-04-01",
    "date:inception_upper": "1987-04-01",
    "iso:country": "GB",
    "wof:name": "BB4 8EN",
    "wof:placetype": "postalcode"
  },
  "geometry": {"coordinates":[-2.286961,53.709331],"type":"Point"}
}
