{
  "type": "Feature",
  "properties": {
    "iso:country": "GB",
    "wof:name": "DT7 3JW",
    "wof:placetype": "postalcode"
  },
  "geometry": {"coordinates":[-2.94027,50.723359],"type":"Point"}
}
