{
  "type": "Feature",
  "properties": {
    "iso:country":"GB",
    "wof:name":"DT7 3JW",
    "wof:placetype":"postalcode"
},
  "geometry": {"coordinates":[-2.94027045015468,50.7233588124311],"type":"Point"}
}