{
  "type": "Feature",
  "properties": {
    "iso:country":"GB",
    "wof:name":"CT14 0AW",
    "wof:placetype":"postalcode"
},
  "geometry": {"coordinates":[1.35447302203882,51.23609904691601],"type":"Point"}
}