{
  "type": "Feature",
  "properties": {
    "iso:country": "GB",
    "wof:name": "CT14 0AW",
    "wof:placetype": "postalcode"
  },
  "geometry": {"coordinates":[1.354283,51.23605],"type":"Point"}
}
