{
  "type": "Feature",
  "properties": {
    "iso:country":"GB",
    "wof:name":"HG4 4LJ",
    "wof:placetype":"postalcode"
},
  "geometry": {"coordinates":[-1.75660211347413,54.22149841526785],"type":"Point"}
}