{
  "type": "Feature",
  "properties": {
    "date:inception_lower":"1980-01-01",
    "date:inception_upper":"1980-01-31",
    "iso:country":"GB",
    "wof:name":"TA7 8BD",
    "wof:placetype":"postalcode"
},
  "geometry": {"coordinates":[-2.966791,51.169564],"type":"Point"}
}