{
  "type": "Feature",
  "properties": {
    "iso:country":"GB",
    "wof:name":"TA7 8BD",
    "wof:placetype":"postalcode"
},
  "geometry": {"coordinates":[-2.96679763833459,51.16958757323583],"type":"Point"}
}