{
  "type": "Feature",
  "properties": {
    "iso:country":"GB",
    "wof:name":"SA12 9BT",
    "wof:placetype":"postalcode"
},
  "geometry": {"coordinates":[-3.76771235681073,51.61358442141571],"type":"Point"}
}