{
  "type": "Feature",
  "properties": {
    "iso:country": "GB",
    "wof:name": "SA12 9BT",
    "wof:placetype": "postalcode"
  },
  "geometry": {"coordinates":[-3.767712,51.613584],"type":"Point"}
}
