{
  "type": "Feature",
  "properties": {
    "iso:country": "GB",
    "wof:name": "TS5 4JF",
    "wof:placetype": "postalcode"
  },
  "geometry": {"coordinates":[-1.267114,54.554923],"type":"Point"}
}
