{
  "type": "Feature",
  "properties": {
    "iso:country": "GB",
    "wof:name": "DN19 7QR",
    "wof:placetype": "postalcode"
  },
  "geometry": {"coordinates":[-0.360428,53.698141],"type":"Point"}
}
