{
  "type": "Feature",
  "properties": {
    "date:inception_lower": "1980-01-01",
    "date:inception_upper": "1980-01-01",
    "iso:country": "GB",
    "wof:name": "DN19 7QR",
    "wof:placetype": "postalcode"
  },
  "geometry": {"coordinates":[-0.360429,53.698096],"type":"Point"}
}
