{
  "type": "Feature",
  "properties": {
    "date:inception_lower": "2024-06-01",
    "date:inception_upper": "2024-06-01",
    "iso:country": "GB",
    "wof:name": "LU7 3SJ",
    "wof:placetype": "postalcode"
  },
  "geometry": {"coordinates":[-0.636044,51.929531],"type":"Point"}
}
