{
  "type": "Feature",
  "properties": {
    "iso:country":"GB",
    "wof:name":"W1G 7JU",
    "wof:placetype":"postalcode"
},
  "geometry": {"coordinates":[-0.14825697615001,51.5223727016177],"type":"Point"}
}