{
  "type": "Feature",
  "properties": {
    "iso:country": "GB",
    "wof:name": "SR8 1NB",
    "wof:placetype": "postalcode"
  },
  "geometry": {"coordinates":[-1.353453,54.746413],"type":"Point"}
}
