{
  "type": "Feature",
  "properties": {
    "iso:country":"GB",
    "wof:name":"SR8 1NB",
    "wof:placetype":"postalcode"
},
  "geometry": {"coordinates":[-1.35345295344066,54.74641279438132],"type":"Point"}
}