{
  "type": "Feature",
  "properties": {
    "iso:country":"GB",
    "wof:name":"SE18 5BE",
    "wof:placetype":"postalcode"
},
  "geometry": {"coordinates":[0.06162752727572,51.48918620613898],"type":"Point"}
}