{
  "type": "Feature",
  "properties": {
    "date:inception_lower": "1980-01-01",
    "date:inception_upper": "1980-01-01",
    "iso:country": "GB",
    "wof:name": "B45 0JP",
    "wof:placetype": "postalcode"
  },
  "geometry": {"coordinates":[-2.002293,52.406694],"type":"Point"}
}
