{
  "type": "Feature",
  "properties": {
    "iso:country":"GB",
    "wof:name":"B45 0JP",
    "wof:placetype":"postalcode"
},
  "geometry": {"coordinates":[-2.00229309740728,52.40669360931891],"type":"Point"}
}