{
  "type": "Feature",
  "properties": {
    "date:inception_lower":"1980-01-01",
    "date:inception_upper":"1980-01-31",
    "iso:country":"GB",
    "wof:name":"CM8 3SE",
    "wof:placetype":"postalcode"
},
  "geometry": {"coordinates":[0.632849,51.843052],"type":"Point"}
}