{
  "type": "Feature",
  "properties": {
    "iso:country":"GB",
    "wof:name":"DN6 8LB",
    "wof:placetype":"postalcode"
},
  "geometry": {"coordinates":[-1.21271760937825,53.58861688296761],"type":"Point"}
}