{
  "type": "Feature",
  "properties": {
    "date:inception_lower": "1980-01-01",
    "date:inception_upper": "1980-01-01",
    "iso:country": "GB",
    "wof:name": "SP5 5PB",
    "wof:placetype": "postalcode"
  },
  "geometry": {"coordinates":[-1.99651,50.964916],"type":"Point"}
}
