{
  "type": "Feature",
  "properties": {
    "iso:country":"GB",
    "wof:name":"SP5 5PB",
    "wof:placetype":"postalcode"
},
  "geometry": {"coordinates":[-1.99651709519611,50.96492218158257],"type":"Point"}
}