{
  "type": "Feature",
  "properties": {
    "date:inception_lower": "1989-07-01",
    "date:inception_upper": "1989-07-01",
    "iso:country": "GB",
    "wof:name": "EH54 7BZ",
    "wof:placetype": "postalcode"
  },
  "geometry": {"coordinates":[-3.530647,55.887679],"type":"Point"}
}
