{
  "type": "Feature",
  "properties": {
    "iso:country":"GB",
    "wof:name":"OL12 0RR",
    "wof:placetype":"postalcode"
},
  "geometry": {"coordinates":[-2.15732735611749,53.62503202075682],"type":"Point"}
}