{
  "type": "Feature",
  "properties": {
    "iso:country":"GB",
    "wof:name":"DE1 1LD",
    "wof:placetype":"postalcode"
},
  "geometry": {"coordinates":[-1.49096765111566,52.92070390671638],"type":"Point"}
}