{
  "type": "Feature",
  "properties": {
    "date:inception_lower": "2021-02-01",
    "date:inception_upper": "2021-02-01",
    "iso:country": "GB",
    "wof:name": "NN3 6FU",
    "wof:placetype": "postalcode"
  },
  "geometry": {"coordinates":[-0.876355,52.271107],"type":"Point"}
}
