{
  "type": "Feature",
  "properties": {
    "iso:country":"GB",
    "wof:name":"EH48 4LR",
    "wof:placetype":"postalcode"
},
  "geometry": {"coordinates":[-3.65473895248614,55.93194770100016],"type":"Point"}
}