{
  "type": "Feature",
  "properties": {
    "iso:country":"GB",
    "wof:name":"N15 6NH",
    "wof:placetype":"postalcode"
},
  "geometry": {"coordinates":[-0.07559278365122,51.57701969422415],"type":"Point"}
}