{
  "type": "Feature",
  "properties": {
    "iso:country": "GB",
    "wof:name": "B4 7LR",
    "wof:placetype": "postalcode"
  },
  "geometry": {"coordinates":[-1.892318,52.48199],"type":"Point"}
}
