{
  "type": "Feature",
  "properties": {
    "date:inception_lower": "1980-01-01",
    "date:inception_upper": "1980-01-01",
    "iso:country": "GB",
    "wof:name": "GL54 5JN",
    "wof:placetype": "postalcode"
  },
  "geometry": {"coordinates":[-1.962269,51.95705],"type":"Point"}
}
