{
  "type": "Feature",
  "properties": {
    "iso:country":"GB",
    "wof:name":"GL54 5JN",
    "wof:placetype":"postalcode"
},
  "geometry": {"coordinates":[-1.96336980237134,51.95663683877446],"type":"Point"}
}