{
  "type": "Feature",
  "properties": {
    "iso:country": "GB",
    "wof:name": "NE71 6BE",
    "wof:placetype": "postalcode"
  },
  "geometry": {"coordinates":[-2.016265,55.545923],"type":"Point"}
}
