{
  "type": "Feature",
  "properties": {
    "iso:country": "GB",
    "wof:name": "DA1 1JW",
    "wof:placetype": "postalcode"
  },
  "geometry": {"coordinates":[0.22539,51.432504],"type":"Point"}
}
