{
  "type": "Feature",
  "properties": {
    "iso:country":"GB",
    "wof:name":"DA1 1JW",
    "wof:placetype":"postalcode"
},
  "geometry": {"coordinates":[0.22538999319974,51.43250389353801],"type":"Point"}
}