{
  "type": "Feature",
  "properties": {
    "date:inception_lower": "1996-06-01",
    "date:inception_upper": "1996-06-01",
    "iso:country": "GB",
    "wof:name": "DA1 1JW",
    "wof:placetype": "postalcode"
  },
  "geometry": {"coordinates":[0.22539,51.432504],"type":"Point"}
}
