{
  "type": "Feature",
  "properties": {
    "iso:country":"GB",
    "wof:name":"W1F 8ZR",
    "wof:placetype":"postalcode"
},
  "geometry": {"coordinates":[-0.13451074030876,51.51447528703392],"type":"Point"}
}