{
  "type": "Feature",
  "properties": {
    "iso:country": "GB",
    "wof:name": "SA20 0DU",
    "wof:placetype": "postalcode"
  },
  "geometry": {"coordinates":[-3.798653,51.999079],"type":"Point"}
}
