{
  "type": "Feature",
  "properties": {
    "iso:country":"GB",
    "wof:name":"SA20 0DU",
    "wof:placetype":"postalcode"
},
  "geometry": {"coordinates":[-3.79869123663683,51.99892582140954],"type":"Point"}
}