{
  "type": "Feature",
  "properties": {
    "date:inception_lower": "1985-04-01",
    "date:inception_upper": "1985-04-01",
    "iso:country": "GB",
    "wof:name": "CB6 1PA",
    "wof:placetype": "postalcode"
  },
  "geometry": {"coordinates":[0.308238,52.456958],"type":"Point"}
}
