{
  "type": "Feature",
  "properties": {
    "iso:country":"GB",
    "wof:name":"CB6 1PA",
    "wof:placetype":"postalcode"
},
  "geometry": {"coordinates":[0.30823775795043,52.45695765281545],"type":"Point"}
}