{
  "type": "Feature",
  "properties": {
    "iso:country":"GB",
    "wof:name":"BS16 1JP",
    "wof:placetype":"postalcode"
},
  "geometry": {"coordinates":[-2.53142800078767,51.49406726706199],"type":"Point"}
}