{
  "type": "Feature",
  "properties": {
    "date:inception_lower":"1980-01-01",
    "date:inception_upper":"1980-01-31",
    "iso:country":"GB",
    "wof:name":"BS16 1JP",
    "wof:placetype":"postalcode"
},
  "geometry": {"coordinates":[-2.531428,51.494067],"type":"Point"}
}