{
  "type": "Feature",
  "properties": {
    "iso:country":"GB",
    "wof:name":"BS2 9EB",
    "wof:placetype":"postalcode"
},
  "geometry": {"coordinates":[-2.57921509604013,51.45943903667234],"type":"Point"}
}