{
  "type": "Feature",
  "properties": {
    "iso:country":"GB",
    "wof:name":"EH26 8BF",
    "wof:placetype":"postalcode"
},
  "geometry": {"coordinates":[-3.21561451649736,55.83328982614665],"type":"Point"}
}