{
  "type": "Feature",
  "properties": {
    "date:inception_lower": "2013-09-01",
    "date:inception_upper": "2013-09-01",
    "iso:country": "GB",
    "wof:name": "EH26 8BF",
    "wof:placetype": "postalcode"
  },
  "geometry": {"coordinates":[-3.215369,55.833082],"type":"Point"}
}
