{
  "type": "Feature",
  "properties": {
    "date:inception_lower": "1995-01-01",
    "date:inception_upper": "1995-01-01",
    "iso:country": "GB",
    "wof:name": "CO3 3UF",
    "wof:placetype": "postalcode"
  },
  "geometry": {"coordinates":[0.864678,51.890109],"type":"Point"}
}
