{
  "type": "Feature",
  "properties": {
    "iso:country":"GB",
    "wof:name":"CO3 3UF",
    "wof:placetype":"postalcode"
},
  "geometry": {"coordinates":[0.86467839765652,51.89010858350852],"type":"Point"}
}