{
  "type": "Feature",
  "properties": {
    "iso:country":"GB",
    "wof:name":"M33 6GQ",
    "wof:placetype":"postalcode"
},
  "geometry": {"coordinates":[-2.3392309515699,53.42490480864794],"type":"Point"}
}