{
  "type": "Feature",
  "properties": {
    "date:inception_lower": "1994-05-01",
    "date:inception_upper": "1994-05-01",
    "iso:country": "GB",
    "wof:name": "M33 6GQ",
    "wof:placetype": "postalcode"
  },
  "geometry": {"coordinates":[-2.339231,53.424905],"type":"Point"}
}
