{
  "type": "Feature",
  "properties": {
    "iso:country":"GB",
    "wof:name":"NP20 7TR",
    "wof:placetype":"postalcode"
},
  "geometry": {"coordinates":[-3.02449509226069,51.6101515650337],"type":"Point"}
}