{
  "type": "Feature",
  "properties": {
    "date:inception_lower": "2020-06-01",
    "date:inception_upper": "2020-06-01",
    "iso:country": "GB",
    "wof:name": "WV11 3BH",
    "wof:placetype": "postalcode"
  },
  "geometry": {"coordinates":[-2.073536,52.608726],"type":"Point"}
}
