{
  "type": "Feature",
  "properties": {
    "iso:country":"GB",
    "wof:name":"NE5 2RE",
    "wof:placetype":"postalcode"
},
  "geometry": {"coordinates":[-1.68824380531919,54.9943662079062],"type":"Point"}
}