{
  "type": "Feature",
  "properties": {
    "iso:country":"GB",
    "wof:name":"DD8 3TJ",
    "wof:placetype":"postalcode"
},
  "geometry": {"coordinates":[-2.91048564994899,56.65963076058883],"type":"Point"}
}