{
  "type": "Feature",
  "properties": {
    "iso:country": "GB",
    "wof:name": "BB12 7AZ",
    "wof:placetype": "postalcode"
  },
  "geometry": {"coordinates":[-2.315807,53.79619],"type":"Point"}
}
