{
  "type": "Feature",
  "properties": {
    "iso:country":"GB",
    "wof:name":"BB12 7AZ",
    "wof:placetype":"postalcode"
},
  "geometry": {"coordinates":[-2.31580676085611,53.7961760068589],"type":"Point"}
}