{
  "type": "Feature",
  "properties": {
    "iso:country": "GB",
    "wof:name": "TQ6 0JF",
    "wof:placetype": "postalcode"
  },
  "geometry": {"coordinates":[-3.608876,50.366764],"type":"Point"}
}
