{
  "type": "Feature",
  "properties": {
    "date:inception_lower":"1980-01-01",
    "date:inception_upper":"1980-01-31",
    "iso:country":"GB",
    "wof:name":"TQ6 0JF",
    "wof:placetype":"postalcode"
},
  "geometry": {"coordinates":[-3.608876,50.366764],"type":"Point"}
}