{
  "type": "Feature",
  "properties": {
    "iso:country":"GB",
    "wof:name":"TQ6 0JF",
    "wof:placetype":"postalcode"
},
  "geometry": {"coordinates":[-3.60637988200688,50.36748890460247],"type":"Point"}
}