{
  "type": "Feature",
  "properties": {
    "date:inception_lower":"2014-03-01",
    "date:inception_upper":"2014-03-31",
    "iso:country":"GB",
    "wof:name":"E1 8NS",
    "wof:placetype":"postalcode"
},
  "geometry": {"coordinates":[-0.063202,51.510981],"type":"Point"}
}