{
  "type": "Feature",
  "properties": {
    "iso:country":"GB",
    "wof:name":"E1 8NS",
    "wof:placetype":"postalcode"
},
  "geometry": {"coordinates":[-0.06320175915813,51.51098133898928],"type":"Point"}
}