{
  "type": "Feature",
  "properties": {
    "iso:country":"GB",
    "wof:name":"DD11 2JG",
    "wof:placetype":"postalcode"
},
  "geometry": {"coordinates":[-2.61570027677026,56.5599007713663],"type":"Point"}
}