{
  "type": "Feature",
  "properties": {
    "iso:country":"GB",
    "wof:name":"SO43 7EE",
    "wof:placetype":"postalcode"
},
  "geometry": {"coordinates":[-1.57796283215497,50.86849943711067],"type":"Point"}
}