{
  "type": "Feature",
  "properties": {
    "iso:country": "GB",
    "wof:name": "SO43 7EE",
    "wof:placetype": "postalcode"
  },
  "geometry": {"coordinates":[-1.577963,50.868499],"type":"Point"}
}
