{
  "type": "Feature",
  "properties": {
    "date:inception_lower": "1987-04-01",
    "date:inception_upper": "1987-04-01",
    "iso:country": "GB",
    "wof:name": "CT3 1DQ",
    "wof:placetype": "postalcode"
  },
  "geometry": {"coordinates":[1.213735,51.270373],"type":"Point"}
}
