{
  "type": "Feature",
  "properties": {
    "iso:country": "GB",
    "wof:name": "CT3 1DQ",
    "wof:placetype": "postalcode"
  },
  "geometry": {"coordinates":[1.213735,51.270373],"type":"Point"}
}
