{
  "type": "Feature",
  "properties": {
    "iso:country":"GB",
    "wof:name":"W1U 3JD",
    "wof:placetype":"postalcode"
},
  "geometry": {"coordinates":[-0.15177374578273,51.51811177471832],"type":"Point"}
}