{
  "type": "Feature",
  "properties": {
    "date:inception_lower": "2000-12-01",
    "date:inception_upper": "2000-12-01",
    "iso:country": "GB",
    "wof:name": "W1U 3JD",
    "wof:placetype": "postalcode"
  },
  "geometry": {"coordinates":[-0.15179,51.518168],"type":"Point"}
}
