{
  "type": "Feature",
  "properties": {
    "iso:country": "GB",
    "wof:name": "CT18 8EB",
    "wof:placetype": "postalcode"
  },
  "geometry": {"coordinates":[1.09482,51.125144],"type":"Point"}
}
