{
  "type": "Feature",
  "properties": {
    "iso:country":"GB",
    "wof:name":"CT18 8EB",
    "wof:placetype":"postalcode"
},
  "geometry": {"coordinates":[1.09451073105812,51.12546279510519],"type":"Point"}
}