{
  "type": "Feature",
  "properties": {
    "date:inception_lower": "2004-04-01",
    "date:inception_upper": "2004-04-01",
    "iso:country": "GB",
    "wof:name": "CV32 4NP",
    "wof:placetype": "postalcode"
  },
  "geometry": {"coordinates":[-1.53431,52.289944],"type":"Point"}
}
