{
  "type": "Feature",
  "properties": {
    "iso:country":"GB",
    "wof:name":"BL2 2PF",
    "wof:placetype":"postalcode"
},
  "geometry": {"coordinates":[-2.41058812584024,53.58670673387678],"type":"Point"}
}