{
  "type": "Feature",
  "properties": {
    "date:inception_lower": "2003-08-01",
    "date:inception_upper": "2003-08-01",
    "iso:country": "GB",
    "wof:name": "BL2 2PF",
    "wof:placetype": "postalcode"
  },
  "geometry": {"coordinates":[-2.410588,53.586707],"type":"Point"}
}
