{
  "type": "Feature",
  "properties": {
    "date:inception_lower":"1999-06-01",
    "date:inception_upper":"1999-06-30",
    "iso:country":"GB",
    "wof:name":"CH49 4LD",
    "wof:placetype":"postalcode"
},
  "geometry": {"coordinates":[-3.113892,53.388251],"type":"Point"}
}