{
  "type": "Feature",
  "properties": {
    "iso:country":"GB",
    "wof:name":"HR1 4PN",
    "wof:placetype":"postalcode"
},
  "geometry": {"coordinates":[-2.61178802021471,52.00832253891846],"type":"Point"}
}