{
  "type": "Feature",
  "properties": {
    "iso:country":"GB",
    "wof:name":"SY4 1AX",
    "wof:placetype":"postalcode"
},
  "geometry": {"coordinates":[-2.90064794333672,52.76031161435274],"type":"Point"}
}