{
  "type": "Feature",
  "properties": {
    "iso:country": "GB",
    "wof:name": "ST5 9FP",
    "wof:placetype": "postalcode"
  },
  "geometry": {"coordinates":[-2.243157,53.022852],"type":"Point"}
}
