{
  "type": "Feature",
  "properties": {
    "iso:country":"GB",
    "wof:name":"BB9 8AG",
    "wof:placetype":"postalcode"
},
  "geometry": {"coordinates":[-2.20314949649476,53.84054179690079],"type":"Point"}
}