{
  "type": "Feature",
  "properties": {
    "iso:country": "GB",
    "wof:name": "PA5 8FB",
    "wof:placetype": "postalcode"
  },
  "geometry": {"coordinates":[-4.518287,55.837009],"type":"Point"}
}
