{
  "type": "Feature",
  "properties": {
    "iso:country":"GB",
    "wof:name":"TW11 9EP",
    "wof:placetype":"postalcode"
},
  "geometry": {"coordinates":[-0.32512082145261,51.42303996717284],"type":"Point"}
}