{
  "type": "Feature",
  "properties": {
    "iso:country": "GB",
    "wof:name": "TW11 9EP",
    "wof:placetype": "postalcode"
  },
  "geometry": {"coordinates":[-0.325121,51.42304],"type":"Point"}
}
