{
  "type": "Feature",
  "properties": {
    "date:inception_lower":"1987-04-01",
    "date:inception_upper":"1987-04-30",
    "iso:country":"GB",
    "wof:name":"TW11 9EP",
    "wof:placetype":"postalcode"
},
  "geometry": {"coordinates":[-0.325121,51.42304],"type":"Point"}
}