{
  "type": "Feature",
  "properties": {
    "date:inception_lower":"1981-09-01",
    "date:inception_upper":"1981-09-30",
    "iso:country":"GB",
    "wof:name":"SA44 4SF",
    "wof:placetype":"postalcode"
},
  "geometry": {"coordinates":[-4.32289,52.032617],"type":"Point"}
}