{
  "type": "Feature",
  "properties": {
    "iso:country": "GB",
    "wof:name": "SA44 4SF",
    "wof:placetype": "postalcode"
  },
  "geometry": {"coordinates":[-4.32289,52.032617],"type":"Point"}
}
