{
  "type": "Feature",
  "properties": {
    "iso:country":"GB",
    "wof:name":"SA33 5LG",
    "wof:placetype":"postalcode"
},
  "geometry": {"coordinates":[-4.39264624258717,51.77516171017552],"type":"Point"}
}