{
  "type": "Feature",
  "properties": {
    "iso:country": "GB",
    "wof:name": "SA33 5LG",
    "wof:placetype": "postalcode"
  },
  "geometry": {"coordinates":[-4.392647,51.77518],"type":"Point"}
}
