{
  "type": "Feature",
  "properties": {
    "date:inception_lower": "2018-03-01",
    "date:inception_upper": "2018-03-01",
    "iso:country": "GB",
    "wof:name": "DE4 5PF",
    "wof:placetype": "postalcode"
  },
  "geometry": {"coordinates":[-1.473386,53.087235],"type":"Point"}
}
