{
  "type": "Feature",
  "properties": {
    "iso:country": "GB",
    "wof:name": "DE4 5PF",
    "wof:placetype": "postalcode"
  },
  "geometry": {"coordinates":[-1.473815,53.08632],"type":"Point"}
}
