{
  "type": "Feature",
  "properties": {
    "date:inception_lower": "1980-01-01",
    "date:inception_upper": "1980-01-01",
    "iso:country": "GB",
    "wof:name": "NE5 5DX",
    "wof:placetype": "postalcode"
  },
  "geometry": {"coordinates":[-1.703718,54.9901],"type":"Point"}
}
