{
  "type": "Feature",
  "properties": {
    "iso:country":"GB",
    "wof:name":"NE5 5DX",
    "wof:placetype":"postalcode"
},
  "geometry": {"coordinates":[-1.70371774933582,54.99010044788923],"type":"Point"}
}