{
  "type": "Feature",
  "properties": {
    "iso:country":"GB",
    "wof:name":"KT2 7BY",
    "wof:placetype":"postalcode"
},
  "geometry": {"coordinates":[-0.27421580041871,51.41317412505894],"type":"Point"}
}