{
  "type": "Feature",
  "properties": {
    "iso:country": "GB",
    "wof:name": "KT2 7BY",
    "wof:placetype": "postalcode"
  },
  "geometry": {"coordinates":[-0.274216,51.413174],"type":"Point"}
}
