{
  "type": "Feature",
  "properties": {
    "iso:country": "GB",
    "wof:name": "S80 3PL",
    "wof:placetype": "postalcode"
  },
  "geometry": {"coordinates":[-1.146954,53.303069],"type":"Point"}
}
