{
  "type": "Feature",
  "properties": {
    "iso:country":"GB",
    "wof:name":"S80 3PL",
    "wof:placetype":"postalcode"
},
  "geometry": {"coordinates":[-1.14695399202041,53.30306922117629],"type":"Point"}
}