{
  "type": "Feature",
  "properties": {
    "iso:country": "GB",
    "wof:name": "HU15 2UN",
    "wof:placetype": "postalcode"
  },
  "geometry": {"coordinates":[-0.732619,53.753611],"type":"Point"}
}
