{
  "type": "Feature",
  "properties": {
    "iso:country": "GB",
    "wof:name": "WS8 7LW",
    "wof:placetype": "postalcode"
  },
  "geometry": {"coordinates":[-1.938807,52.656091],"type":"Point"}
}
