{
  "type": "Feature",
  "properties": {
    "iso:country":"GB",
    "wof:name":"WS8 7LW",
    "wof:placetype":"postalcode"
},
  "geometry": {"coordinates":[-1.93881384530628,52.65607520910411],"type":"Point"}
}