{
  "type": "Feature",
  "properties": {
    "iso:country": "GB",
    "wof:name": "PA7 5GB",
    "wof:placetype": "postalcode"
  },
  "geometry": {"coordinates":[-4.502961,55.89995],"type":"Point"}
}
