{
  "type": "Feature",
  "properties": {
    "iso:country": "GB",
    "wof:name": "DY1 4JY",
    "wof:placetype": "postalcode"
  },
  "geometry": {"coordinates":[-2.092825,52.533242],"type":"Point"}
}
