{
  "type": "Feature",
  "properties": {
    "iso:country":"GB",
    "wof:name":"YO14 0JT",
    "wof:placetype":"postalcode"
},
  "geometry": {"coordinates":[-0.32235192613757,54.18006438858318],"type":"Point"}
}