{
  "type": "Feature",
  "properties": {
    "date:inception_lower": "1980-01-01",
    "date:inception_upper": "1980-01-01",
    "iso:country": "GB",
    "wof:name": "YO14 0JT",
    "wof:placetype": "postalcode"
  },
  "geometry": {"coordinates":[-0.322931,54.180532],"type":"Point"}
}
