{
  "type": "Feature",
  "properties": {
    "iso:country":"GB",
    "wof:name":"CA2 7XX",
    "wof:placetype":"postalcode"
},
  "geometry": {"coordinates":[-2.98539113990465,54.89010324240059],"type":"Point"}
}