{
  "type": "Feature",
  "properties": {
    "iso:country":"GB",
    "wof:name":"HR2 9DA",
    "wof:placetype":"postalcode"
},
  "geometry": {"coordinates":[-2.80002669620117,51.98580474855198],"type":"Point"}
}