{
  "type": "Feature",
  "properties": {
    "date:inception_lower":"1980-01-01",
    "date:inception_upper":"1980-01-31",
    "iso:country":"GB",
    "wof:name":"HR2 9DA",
    "wof:placetype":"postalcode"
},
  "geometry": {"coordinates":[-2.800027,51.985805],"type":"Point"}
}