{
  "type": "Feature",
  "properties": {
    "iso:country": "GB",
    "wof:name": "HR2 9DA",
    "wof:placetype": "postalcode"
  },
  "geometry": {"coordinates":[-2.800027,51.985805],"type":"Point"}
}
