{
  "type": "Feature",
  "properties": {
    "iso:country":"GB",
    "wof:name":"GL7 5XH",
    "wof:placetype":"postalcode"
},
  "geometry": {"coordinates":[-1.92241025024644,51.67434526429722],"type":"Point"}
}