{
  "type": "Feature",
  "properties": {
    "iso:country":"GB",
    "wof:name":"EH4 7QF",
    "wof:placetype":"postalcode"
},
  "geometry": {"coordinates":[-3.2993104388413,55.95913233672869],"type":"Point"}
}