{
  "type": "Feature",
  "properties": {
    "date:inception_lower":"2006-07-01",
    "date:inception_upper":"2006-07-31",
    "iso:country":"GB",
    "wof:name":"WN3 4NZ",
    "wof:placetype":"postalcode"
},
  "geometry": {"coordinates":[-2.613768,53.531609],"type":"Point"}
}