{
  "type": "Feature",
  "properties": {
    "iso:country": "GB",
    "wof:name": "WN3 4NZ",
    "wof:placetype": "postalcode"
  },
  "geometry": {"coordinates":[-2.613768,53.531609],"type":"Point"}
}
