{
  "type": "Feature",
  "properties": {
    "iso:country":"GB",
    "wof:name":"SM1 4LF",
    "wof:placetype":"postalcode"
},
  "geometry": {"coordinates":[-0.18827201478895,51.3623996119676],"type":"Point"}
}