{
  "type": "Feature",
  "properties": {
    "iso:country":"GB",
    "wof:name":"N7 7JZ",
    "wof:placetype":"postalcode"
},
  "geometry": {"coordinates":[-0.11129475819717,51.56108958407194],"type":"Point"}
}