{
  "type": "Feature",
  "properties": {
    "date:inception_lower": "1980-01-01",
    "date:inception_upper": "1980-01-01",
    "iso:country": "GB",
    "wof:name": "TN29 9JF",
    "wof:placetype": "postalcode"
  },
  "geometry": {"coordinates":[0.907916,50.944832],"type":"Point"}
}
