{
  "type": "Feature",
  "properties": {
    "iso:country":"GB",
    "wof:name":"TN29 9JF",
    "wof:placetype":"postalcode"
},
  "geometry": {"coordinates":[0.90779484208611,50.94484345495859],"type":"Point"}
}