{
  "type": "Feature",
  "properties": {
    "iso:country": "GB",
    "wof:name": "SG12 0UD",
    "wof:placetype": "postalcode"
  },
  "geometry": {"coordinates":[-0.038821,51.831309],"type":"Point"}
}
