{
  "type": "Feature",
  "properties": {
    "iso:country": "GB",
    "wof:name": "WS14 0BN",
    "wof:placetype": "postalcode"
  },
  "geometry": {"coordinates":[-1.883706,52.654722],"type":"Point"}
}
