{
  "type": "Feature",
  "properties": {
    "date:inception_lower":"1980-01-01",
    "date:inception_upper":"1980-01-31",
    "iso:country":"GB",
    "wof:name":"WS14 0BN",
    "wof:placetype":"postalcode"
},
  "geometry": {"coordinates":[-1.883706,52.654722],"type":"Point"}
}