{
  "type": "Feature",
  "properties": {
    "iso:country":"GB",
    "wof:name":"WS14 0BN",
    "wof:placetype":"postalcode"
},
  "geometry": {"coordinates":[-1.88370570118312,52.65472157345909],"type":"Point"}
}