{
  "type": "Feature",
  "properties": {
    "date:inception_lower": "1997-12-01",
    "date:inception_upper": "1997-12-01",
    "iso:country": "GB",
    "wof:name": "BS48 3JN",
    "wof:placetype": "postalcode"
  },
  "geometry": {"coordinates":[-2.73896,51.41224],"type":"Point"}
}
