{
  "type": "Feature",
  "properties": {
    "iso:country": "GB",
    "wof:name": "BS48 3JN",
    "wof:placetype": "postalcode"
  },
  "geometry": {"coordinates":[-2.73896,51.41224],"type":"Point"}
}
