{
  "type": "Feature",
  "properties": {
    "iso:country":"GB",
    "wof:name":"AB30 1BJ",
    "wof:placetype":"postalcode"
},
  "geometry": {"coordinates":[-2.46723521148763,56.83227998426031],"type":"Point"}
}