{
  "type": "Feature",
  "properties": {
    "iso:country":"GB",
    "wof:name":"LA7 7JY",
    "wof:placetype":"postalcode"
},
  "geometry": {"coordinates":[-2.81116820870102,54.20766057261656],"type":"Point"}
}