{
  "type": "Feature",
  "properties": {
    "iso:country": "GB",
    "wof:name": "LA7 7JY",
    "wof:placetype": "postalcode"
  },
  "geometry": {"coordinates":[-2.811183,54.207644],"type":"Point"}
}
