{
  "type": "Feature",
  "properties": {
    "date:inception_lower": "1980-01-01",
    "date:inception_upper": "1980-01-01",
    "iso:country": "GB",
    "wof:name": "LA7 7JY",
    "wof:placetype": "postalcode"
  },
  "geometry": {"coordinates":[-2.811183,54.207644],"type":"Point"}
}
