{
  "type": "Feature",
  "properties": {
    "iso:country":"GB",
    "wof:name":"W1H 4HE",
    "wof:placetype":"postalcode"
},
  "geometry": {"coordinates":[-0.16520354041829,51.51999522109829],"type":"Point"}
}