{
  "type": "Feature",
  "properties": {
    "date:inception_lower": "2020-11-01",
    "date:inception_upper": "2020-11-01",
    "iso:country": "GB",
    "wof:name": "NR18 9GH",
    "wof:placetype": "postalcode"
  },
  "geometry": {"coordinates":[1.098861,52.561648],"type":"Point"}
}
