{
  "type": "Feature",
  "properties": {
    "date:inception_lower": "2019-11-01",
    "date:inception_upper": "2019-11-01",
    "iso:country": "GB",
    "wof:name": "FY6 9EX",
    "wof:placetype": "postalcode"
  },
  "geometry": {"coordinates":[-2.945488,53.871327],"type":"Point"}
}
