{
  "type": "Feature",
  "properties": {
    "iso:country":"GB",
    "wof:name":"GL15 6PZ",
    "wof:placetype":"postalcode"
},
  "geometry": {"coordinates":[-2.56843204464158,51.70782627938995],"type":"Point"}
}