{
  "type": "Feature",
  "properties": {
    "iso:country": "GB",
    "wof:name": "GL15 6PZ",
    "wof:placetype": "postalcode"
  },
  "geometry": {"coordinates":[-2.568432,51.707826],"type":"Point"}
}
