{
  "type": "Feature",
  "properties": {
    "date:inception_lower": "1981-06-01",
    "date:inception_upper": "1981-06-01",
    "iso:country": "GB",
    "wof:name": "WR9 7RS",
    "wof:placetype": "postalcode"
  },
  "geometry": {"coordinates":[-2.144874,52.257053],"type":"Point"}
}
