{
  "type": "Feature",
  "properties": {
    "iso:country": "GB",
    "wof:name": "BD23 6EJ",
    "wof:placetype": "postalcode"
  },
  "geometry": {"coordinates":[-1.938678,53.983434],"type":"Point"}
}
