{
  "type": "Feature",
  "properties": {
    "iso:country": "GB",
    "wof:name": "SR8 3UX",
    "wof:placetype": "postalcode"
  },
  "geometry": {"coordinates":[-1.318625,54.795388],"type":"Point"}
}
