{
  "type": "Feature",
  "properties": {
    "iso:country":"GB",
    "wof:name":"SR8 3UX",
    "wof:placetype":"postalcode"
},
  "geometry": {"coordinates":[-1.31862525100618,54.79538847969364],"type":"Point"}
}