{
  "type": "Feature",
  "properties": {
    "iso:country": "GB",
    "wof:name": "EH12 1PZ",
    "wof:placetype": "postalcode"
  },
  "geometry": {"coordinates":[-3.30222,55.928941],"type":"Point"}
}
