{
  "type": "Feature",
  "properties": {
    "date:inception_lower": "2023-04-01",
    "date:inception_upper": "2023-04-01",
    "iso:country": "GB",
    "wof:name": "NR23 1YY",
    "wof:placetype": "postalcode"
  },
  "geometry": {"coordinates":[0.853348,52.954468],"type":"Point"}
}
