{
  "type": "Feature",
  "properties": {
    "iso:country":"GB",
    "wof:name":"SE6 4DA",
    "wof:placetype":"postalcode"
},
  "geometry": {"coordinates":[-0.03373148683344,51.4346016665456],"type":"Point"}
}