{
  "type": "Feature",
  "properties": {
    "iso:country":"GB",
    "wof:name":"NP18 2DP",
    "wof:placetype":"postalcode"
},
  "geometry": {"coordinates":[-2.91971817430086,51.59280249391782],"type":"Point"}
}