{
  "type": "Feature",
  "properties": {
    "iso:country": "GB",
    "wof:name": "NP18 2DP",
    "wof:placetype": "postalcode"
  },
  "geometry": {"coordinates":[-2.919718,51.592802],"type":"Point"}
}
