{
  "type": "Feature",
  "properties": {
    "iso:country":"GB",
    "wof:name":"SG13 8QU",
    "wof:placetype":"postalcode"
},
  "geometry": {"coordinates":[-0.11426406737032,51.73740538081785],"type":"Point"}
}