{
  "type": "Feature",
  "properties": {
    "iso:country":"GB",
    "wof:name":"E18 1DE",
    "wof:placetype":"postalcode"
},
  "geometry": {"coordinates":[0.02863140826806,51.59436445323111],"type":"Point"}
}