{
  "type": "Feature",
  "properties": {
    "iso:country":"GB",
    "wof:name":"DA2 6JD",
    "wof:placetype":"postalcode"
},
  "geometry": {"coordinates":[0.2430339010476,51.43671802109096],"type":"Point"}
}