{
  "type": "Feature",
  "properties": {
    "iso:country": "GB",
    "wof:name": "SL9 7QU",
    "wof:placetype": "postalcode"
  },
  "geometry": {"coordinates":[-0.557699,51.589069],"type":"Point"}
}
