{
  "type": "Feature",
  "properties": {
    "iso:country": "GB",
    "wof:name": "W1S 3BE",
    "wof:placetype": "postalcode"
  },
  "geometry": {"coordinates":[-0.140301,51.511735],"type":"Point"}
}
