{
  "type": "Feature",
  "properties": {
    "iso:country":"GB",
    "wof:name":"W1S 3BE",
    "wof:placetype":"postalcode"
},
  "geometry": {"coordinates":[-0.14030085915899,51.51173459623775],"type":"Point"}
}