{
  "type": "Feature",
  "properties": {
    "iso:country":"GB",
    "wof:name":"WA8 7BG",
    "wof:placetype":"postalcode"
},
  "geometry": {"coordinates":[-2.74060417004744,53.36389843764565],"type":"Point"}
}