{
  "type": "Feature",
  "properties": {
    "date:inception_lower": "1980-01-01",
    "date:inception_upper": "1980-01-01",
    "iso:country": "GB",
    "wof:name": "HR9 7SW",
    "wof:placetype": "postalcode"
  },
  "geometry": {"coordinates":[-2.471798,51.932455],"type":"Point"}
}
