{
  "type": "Feature",
  "properties": {
    "iso:country":"GB",
    "wof:name":"HR9 7SW",
    "wof:placetype":"postalcode"
},
  "geometry": {"coordinates":[-2.47179833282859,51.93245486546302],"type":"Point"}
}