{
  "type": "Feature",
  "properties": {
    "iso:country":"GB",
    "wof:name":"WV1 4QB",
    "wof:placetype":"postalcode"
},
  "geometry": {"coordinates":[-2.13949867033276,52.59210935344166],"type":"Point"}
}