{
  "type": "Feature",
  "properties": {
    "iso:country":"GB",
    "wof:name":"WV16 6HE",
    "wof:placetype":"postalcode"
},
  "geometry": {"coordinates":[-2.39426303981773,52.45470773858676],"type":"Point"}
}