{
  "type": "Feature",
  "properties": {
    "iso:country": "GB",
    "wof:name": "RG17 9UU",
    "wof:placetype": "postalcode"
  },
  "geometry": {"coordinates":[-1.44686,51.399413],"type":"Point"}
}
