{
  "type": "Feature",
  "properties": {
    "iso:country":"GB",
    "wof:name":"BH25 5HL",
    "wof:placetype":"postalcode"
},
  "geometry": {"coordinates":[-1.65215061321784,50.7603386473076],"type":"Point"}
}