{
  "type": "Feature",
  "properties": {
    "iso:country":"GB",
    "wof:name":"N7 6NE",
    "wof:placetype":"postalcode"
},
  "geometry": {"coordinates":[-0.11338267478268,51.5538662456887],"type":"Point"}
}