{
  "type": "Feature",
  "properties": {
    "date:inception_lower": "1996-12-01",
    "date:inception_upper": "1996-12-01",
    "iso:country": "GB",
    "wof:name": "IP17 2BZ",
    "wof:placetype": "postalcode"
  },
  "geometry": {"coordinates":[1.425596,52.223722],"type":"Point"}
}
