{
  "type": "Feature",
  "properties": {
    "iso:country":"GB",
    "wof:name":"S73 0RR",
    "wof:placetype":"postalcode"
},
  "geometry": {"coordinates":[-1.39019417665133,53.51405054884384],"type":"Point"}
}