{
  "type": "Feature",
  "properties": {
    "iso:country": "GB",
    "wof:name": "SG13 7PH",
    "wof:placetype": "postalcode"
  },
  "geometry": {"coordinates":[-0.043721,51.780512],"type":"Point"}
}
