{
  "type": "Feature",
  "properties": {
    "iso:country": "GB",
    "wof:name": "EH11 1SU",
    "wof:placetype": "postalcode"
  },
  "geometry": {"coordinates":[-3.232285,55.931705],"type":"Point"}
}
