{
  "type": "Feature",
  "properties": {
    "date:inception_lower": "1980-01-01",
    "date:inception_upper": "1980-01-01",
    "iso:country": "GB",
    "wof:name": "SW12 8AY",
    "wof:placetype": "postalcode"
  },
  "geometry": {"coordinates":[-0.151255,51.445903],"type":"Point"}
}
