{
  "type": "Feature",
  "properties": {
    "iso:country":"GB",
    "wof:name":"DH9 0LS",
    "wof:placetype":"postalcode"
},
  "geometry": {"coordinates":[-1.68501837539761,54.883161538484],"type":"Point"}
}