{
  "type": "Feature",
  "properties": {
    "iso:country":"GB",
    "wof:name":"ML2 0BS",
    "wof:placetype":"postalcode"
},
  "geometry": {"coordinates":[-3.9497763538273,55.76906643254632],"type":"Point"}
}