{
  "type": "Feature",
  "properties": {
    "iso:country":"GB",
    "wof:name":"FY4 4DW",
    "wof:placetype":"postalcode"
},
  "geometry": {"coordinates":[-3.02465716927097,53.80229775401607],"type":"Point"}
}