{
  "type": "Feature",
  "properties": {
    "iso:country":"GB",
    "wof:name":"W1F 9TJ",
    "wof:placetype":"postalcode"
},
  "geometry": {"coordinates":[-0.13604733584758,51.51143326992433],"type":"Point"}
}