{
  "type": "Feature",
  "properties": {
    "date:inception_lower": "2022-02-01",
    "date:inception_upper": "2022-02-01",
    "iso:country": "GB",
    "wof:name": "LU7 3EZ",
    "wof:placetype": "postalcode"
  },
  "geometry": {"coordinates":[-0.632909,51.920701],"type":"Point"}
}
