{
  "type": "Feature",
  "properties": {
    "iso:country":"GB",
    "wof:name":"CO4 5BD",
    "wof:placetype":"postalcode"
},
  "geometry": {"coordinates":[0.91878868748405,51.92300770804045],"type":"Point"}
}