{
  "type": "Feature",
  "properties": {
    "iso:country":"GB",
    "wof:name":"PE25 2ND",
    "wof:placetype":"postalcode"
},
  "geometry": {"coordinates":[0.32431290833131,53.15396547484235],"type":"Point"}
}