{
  "type": "Feature",
  "properties": {
    "iso:country":"GB",
    "wof:name":"M33 5LS",
    "wof:placetype":"postalcode"
},
  "geometry": {"coordinates":[-2.35744473429743,53.42728755358054],"type":"Point"}
}