{
  "type": "Feature",
  "properties": {
    "iso:country":"GB",
    "wof:name":"B32 3QN",
    "wof:placetype":"postalcode"
},
  "geometry": {"coordinates":[-2.00353065904146,52.43918359923219],"type":"Point"}
}