{
  "type": "Feature",
  "properties": {
    "iso:country": "GB",
    "wof:name": "B32 3QN",
    "wof:placetype": "postalcode"
  },
  "geometry": {"coordinates":[-2.003531,52.439184],"type":"Point"}
}
