{
  "type": "Feature",
  "properties": {
    "iso:country":"GB",
    "wof:name":"TR26 2DN",
    "wof:placetype":"postalcode"
},
  "geometry": {"coordinates":[-5.48277701630623,50.21020125708704],"type":"Point"}
}