{
  "type": "Feature",
  "properties": {
    "iso:country":"GB",
    "wof:name":"CT20 2QT",
    "wof:placetype":"postalcode"
},
  "geometry": {"coordinates":[1.17156333142029,51.07886253901412],"type":"Point"}
}