{
  "type": "Feature",
  "properties": {
    "date:inception_lower": "1980-01-01",
    "date:inception_upper": "1980-01-01",
    "iso:country": "GB",
    "wof:name": "SG3 6TQ",
    "wof:placetype": "postalcode"
  },
  "geometry": {"coordinates":[-0.157268,51.851865],"type":"Point"}
}
