{
  "type": "Feature",
  "properties": {
    "iso:country":"GB",
    "wof:name":"TS23 2QR",
    "wof:placetype":"postalcode"
},
  "geometry": {"coordinates":[-1.28394560117924,54.6038591805698],"type":"Point"}
}