{
  "type": "Feature",
  "properties": {
    "date:inception_lower": "2020-01-01",
    "date:inception_upper": "2020-01-01",
    "iso:country": "GB",
    "wof:name": "KA21 6BS",
    "wof:placetype": "postalcode"
  },
  "geometry": {"coordinates":[-4.782751,55.654156],"type":"Point"}
}
