{
  "type": "Feature",
  "properties": {
    "iso:country": "GB",
    "wof:name": "KA21 6BS",
    "wof:placetype": "postalcode"
  },
  "geometry": {"coordinates":[-4.78558,55.644968],"type":"Point"}
}
