{
  "type": "Feature",
  "properties": {
    "iso:country":"GB",
    "wof:name":"EH13 9PB",
    "wof:placetype":"postalcode"
},
  "geometry": {"coordinates":[-3.22476197150008,55.90280177252656],"type":"Point"}
}