{
  "type": "Feature",
  "properties": {
    "iso:country":"GB",
    "wof:name":"L39 5DE",
    "wof:placetype":"postalcode"
},
  "geometry": {"coordinates":[-2.91082824083927,53.54859092823035],"type":"Point"}
}