{
  "type": "Feature",
  "properties": {
    "iso:country": "GB",
    "wof:name": "L39 5DE",
    "wof:placetype": "postalcode"
  },
  "geometry": {"coordinates":[-2.910828,53.548591],"type":"Point"}
}
