{
  "type": "Feature",
  "properties": {
    "iso:country":"GB",
    "wof:name":"L11 6LH",
    "wof:placetype":"postalcode"
},
  "geometry": {"coordinates":[-2.89490438058766,53.45838352941991],"type":"Point"}
}