{
  "type": "Feature",
  "properties": {
    "iso:country":"GB",
    "wof:name":"KT22 8NX",
    "wof:placetype":"postalcode"
},
  "geometry": {"coordinates":[-0.31884949672854,51.29004054098586],"type":"Point"}
}