{
  "type": "Feature",
  "properties": {
    "date:inception_lower": "1980-01-01",
    "date:inception_upper": "1980-01-01",
    "iso:country": "GB",
    "wof:name": "RH16 4HJ",
    "wof:placetype": "postalcode"
  },
  "geometry": {"coordinates":[-0.099189,50.992112],"type":"Point"}
}
