{
  "type": "Feature",
  "properties": {
    "iso:country":"GB",
    "wof:name":"SW19 8LL",
    "wof:placetype":"postalcode"
},
  "geometry": {"coordinates":[-0.18986866301711,51.42898762466278],"type":"Point"}
}