{
  "type": "Feature",
  "properties": {
    "iso:country": "GB",
    "wof:name": "SW19 8LL",
    "wof:placetype": "postalcode"
  },
  "geometry": {"coordinates":[-0.189771,51.429013],"type":"Point"}
}
