{
  "type": "Feature",
  "properties": {
    "iso:country":"GB",
    "wof:name":"TA9 3TH",
    "wof:placetype":"postalcode"
},
  "geometry": {"coordinates":[-2.97581207939663,51.21918569926387],"type":"Point"}
}