{
  "type": "Feature",
  "properties": {
    "iso:country":"GB",
    "wof:name":"NP23 4BQ",
    "wof:placetype":"postalcode"
},
  "geometry": {"coordinates":[-3.18263864578005,51.79190430450628],"type":"Point"}
}