{
  "type": "Feature",
  "properties": {
    "iso:country": "GB",
    "wof:name": "NP23 4BQ",
    "wof:placetype": "postalcode"
  },
  "geometry": {"coordinates":[-3.182639,51.791904],"type":"Point"}
}
