{
  "type": "Feature",
  "properties": {
    "date:inception_lower": "2009-02-01",
    "date:inception_upper": "2009-02-01",
    "iso:country": "GB",
    "wof:name": "RG19 6HD",
    "wof:placetype": "postalcode"
  },
  "geometry": {"coordinates":[-1.278497,51.37333],"type":"Point"}
}
