{
  "type": "Feature",
  "properties": {
    "iso:country":"GB",
    "wof:name":"UB8 2LW",
    "wof:placetype":"postalcode"
},
  "geometry": {"coordinates":[-0.48255833347501,51.52374739258893],"type":"Point"}
}