{
  "type": "Feature",
  "properties": {
    "date:inception_lower": "1995-07-01",
    "date:inception_upper": "1995-07-01",
    "iso:country": "GB",
    "wof:name": "BB3 1PJ",
    "wof:placetype": "postalcode"
  },
  "geometry": {"coordinates":[-2.477369,53.700223],"type":"Point"}
}
