{
  "type": "Feature",
  "properties": {
    "iso:country":"GB",
    "wof:name":"BB3 1PJ",
    "wof:placetype":"postalcode"
},
  "geometry": {"coordinates":[-2.47736896987395,53.70022346731714],"type":"Point"}
}