{
  "type": "Feature",
  "properties": {
    "iso:country": "GB",
    "wof:name": "BB3 1PJ",
    "wof:placetype": "postalcode"
  },
  "geometry": {"coordinates":[-2.477369,53.700223],"type":"Point"}
}
