{
  "type": "Feature",
  "properties": {
    "iso:country":"GB",
    "wof:name":"KA23 9JF",
    "wof:placetype":"postalcode"
},
  "geometry": {"coordinates":[-4.85759672527013,55.6923678406794],"type":"Point"}
}