{
  "type": "Feature",
  "properties": {
    "date:inception_lower": "1980-01-01",
    "date:inception_upper": "1980-01-01",
    "iso:country": "GB",
    "wof:name": "WA10 2SE",
    "wof:placetype": "postalcode"
  },
  "geometry": {"coordinates":[-2.73909,53.459557],"type":"Point"}
}
