{
  "type": "Feature",
  "properties": {
    "iso:country":"GB",
    "wof:name":"WA10 2SE",
    "wof:placetype":"postalcode"
},
  "geometry": {"coordinates":[-2.73909046928859,53.45955716650652],"type":"Point"}
}