{
  "type": "Feature",
  "properties": {
    "iso:country":"GB",
    "wof:name":"OX3 7JG",
    "wof:placetype":"postalcode"
},
  "geometry": {"coordinates":[-1.20053003080385,51.74359165996187],"type":"Point"}
}