{
  "type": "Feature",
  "properties": {
    "iso:country": "GB",
    "wof:name": "OX3 7JG",
    "wof:placetype": "postalcode"
  },
  "geometry": {"coordinates":[-1.20053,51.743592],"type":"Point"}
}
