{
  "type": "Feature",
  "properties": {
    "iso:country":"GB",
    "wof:name":"PR5 5RQ",
    "wof:placetype":"postalcode"
},
  "geometry": {"coordinates":[-2.69170225664093,53.72551286476871],"type":"Point"}
}