{
  "type": "Feature",
  "properties": {
    "iso:country": "GB",
    "wof:name": "EH11 1BT",
    "wof:placetype": "postalcode"
  },
  "geometry": {"coordinates":[-3.218631,55.938859],"type":"Point"}
}
