{
  "type": "Feature",
  "properties": {
    "iso:country":"GB",
    "wof:name":"LL13 7NZ",
    "wof:placetype":"postalcode"
},
  "geometry": {"coordinates":[-3.00398441377745,53.04466169010261],"type":"Point"}
}