{
  "type": "Feature",
  "properties": {
    "date:inception_lower": "1996-06-01",
    "date:inception_upper": "1996-06-01",
    "iso:country": "GB",
    "wof:name": "LL13 7NZ",
    "wof:placetype": "postalcode"
  },
  "geometry": {"coordinates":[-3.003984,53.044662],"type":"Point"}
}
