{
  "type": "Feature",
  "properties": {
    "iso:country":"GB",
    "wof:name":"LN4 1BF",
    "wof:placetype":"postalcode"
},
  "geometry": {"coordinates":[-0.43050244254073,53.22004718218668],"type":"Point"}
}