{
  "type": "Feature",
  "properties": {
    "date:inception_lower":"2010-05-01",
    "date:inception_upper":"2010-05-31",
    "iso:country":"GB",
    "wof:name":"LN4 1BF",
    "wof:placetype":"postalcode"
},
  "geometry": {"coordinates":[-0.430322,53.220463],"type":"Point"}
}