{
  "type": "Feature",
  "properties": {
    "iso:country":"GB",
    "wof:name":"PA2 6EW",
    "wof:placetype":"postalcode"
},
  "geometry": {"coordinates":[-4.42321200041742,55.83220206272553],"type":"Point"}
}