{
  "type": "Feature",
  "properties": {
    "date:inception_lower": "2012-02-01",
    "date:inception_upper": "2012-02-01",
    "iso:country": "GB",
    "wof:name": "WA8 5AF",
    "wof:placetype": "postalcode"
  },
  "geometry": {"coordinates":[-2.738003,53.390791],"type":"Point"}
}
