{
  "type": "Feature",
  "properties": {
    "iso:country":"GB",
    "wof:name":"WA8 5AF",
    "wof:placetype":"postalcode"
},
  "geometry": {"coordinates":[-2.73800354325291,53.39079108016496],"type":"Point"}
}