{
  "type": "Feature",
  "properties": {
    "date:inception_lower": "2018-09-01",
    "date:inception_upper": "2018-09-01",
    "iso:country": "GB",
    "wof:name": "HU13 0GJ",
    "wof:placetype": "postalcode"
  },
  "geometry": {"coordinates":[-0.461882,53.731027],"type":"Point"}
}
