{
  "type": "Feature",
  "properties": {
    "iso:country": "GB",
    "wof:name": "NE13 6QE",
    "wof:placetype": "postalcode"
  },
  "geometry": {"coordinates":[-1.623614,55.042736],"type":"Point"}
}
