{
  "type": "Feature",
  "properties": {
    "iso:country":"GB",
    "wof:name":"NE13 6QE",
    "wof:placetype":"postalcode"
},
  "geometry": {"coordinates":[-1.62361397839103,55.04273597414846],"type":"Point"}
}