{
  "type": "Feature",
  "properties": {
    "date:inception_lower": "1980-01-01",
    "date:inception_upper": "1980-01-01",
    "iso:country": "GB",
    "wof:name": "NE13 6QE",
    "wof:placetype": "postalcode"
  },
  "geometry": {"coordinates":[-1.623614,55.042736],"type":"Point"}
}
