{
  "type": "Feature",
  "properties": {
    "iso:country":"GB",
    "wof:name":"BD7 4HT",
    "wof:placetype":"postalcode"
},
  "geometry": {"coordinates":[-1.78965919969589,53.77482833387055],"type":"Point"}
}