{
  "type": "Feature",
  "properties": {
    "date:inception_lower":"1980-01-01",
    "date:inception_upper":"1980-01-31",
    "iso:country":"GB",
    "wof:name":"BD7 4HT",
    "wof:placetype":"postalcode"
},
  "geometry": {"coordinates":[-1.789659,53.774828],"type":"Point"}
}