{
  "type": "Feature",
  "properties": {
    "iso:country":"GB",
    "wof:name":"FK2 8NB",
    "wof:placetype":"postalcode"
},
  "geometry": {"coordinates":[-3.78693679426202,56.0254995172137],"type":"Point"}
}