{
  "type": "Feature",
  "properties": {
    "date:inception_lower": "1995-12-01",
    "date:inception_upper": "1995-12-01",
    "iso:country": "GB",
    "wof:name": "FK2 8NB",
    "wof:placetype": "postalcode"
  },
  "geometry": {"coordinates":[-3.786937,56.0255],"type":"Point"}
}
