{
  "type": "Feature",
  "properties": {
    "iso:country":"GB",
    "wof:name":"PO7 8DR",
    "wof:placetype":"postalcode"
},
  "geometry": {"coordinates":[-1.02109240454478,50.87138165680406],"type":"Point"}
}