{
  "type": "Feature",
  "properties": {
    "date:inception_lower": "2017-02-01",
    "date:inception_upper": "2017-02-01",
    "iso:country": "GB",
    "wof:name": "SN3 3FW",
    "wof:placetype": "postalcode"
  },
  "geometry": {"coordinates":[-1.762759,51.560591],"type":"Point"}
}
