{
  "type": "Feature",
  "properties": {
    "iso:country": "GB",
    "wof:name": "SN3 3FW",
    "wof:placetype": "postalcode"
  },
  "geometry": {"coordinates":[-1.762759,51.560591],"type":"Point"}
}
