{
  "type": "Feature",
  "properties": {
    "iso:country":"GB",
    "wof:name":"IV55 8GB",
    "wof:placetype":"postalcode"
},
  "geometry": {"coordinates":[-6.5782533623975,57.52105989378444],"type":"Point"}
}