{
  "type": "Feature",
  "properties": {
    "date:inception_lower": "2004-02-01",
    "date:inception_upper": "2004-02-01",
    "iso:country": "GB",
    "wof:name": "IV55 8GB",
    "wof:placetype": "postalcode"
  },
  "geometry": {"coordinates":[-6.57842,57.521007],"type":"Point"}
}
