{
  "type": "Feature",
  "properties": {
    "date:inception_lower": "2004-11-01",
    "date:inception_upper": "2004-11-01",
    "iso:country": "GB",
    "wof:name": "CA1 3TL",
    "wof:placetype": "postalcode"
  },
  "geometry": {"coordinates":[-2.893654,54.877261],"type":"Point"}
}
