{
  "type": "Feature",
  "properties": {
    "iso:country":"GB",
    "wof:name":"CA1 3TL",
    "wof:placetype":"postalcode"
},
  "geometry": {"coordinates":[-2.89365379566855,54.87726090487294],"type":"Point"}
}