{
  "type": "Feature",
  "properties": {
    "iso:country":"GB",
    "wof:name":"LL65 1PA",
    "wof:placetype":"postalcode"
},
  "geometry": {"coordinates":[-4.64834534980603,53.31066096603448],"type":"Point"}
}