{
  "type": "Feature",
  "properties": {
    "iso:country": "GB",
    "wof:name": "LL65 1PA",
    "wof:placetype": "postalcode"
  },
  "geometry": {"coordinates":[-4.648345,53.310661],"type":"Point"}
}
