{
  "type": "Feature",
  "properties": {
    "iso:country": "GB",
    "wof:name": "S9 3BG",
    "wof:placetype": "postalcode"
  },
  "geometry": {"coordinates":[-1.421848,53.387585],"type":"Point"}
}
