{
  "type": "Feature",
  "properties": {
    "iso:country":"GB",
    "wof:name":"ME5 0JL",
    "wof:placetype":"postalcode"
},
  "geometry": {"coordinates":[0.52330690182378,51.35504048701246],"type":"Point"}
}