{
  "type": "Feature",
  "properties": {
    "date:inception_lower": "1984-10-01",
    "date:inception_upper": "1984-10-01",
    "iso:country": "GB",
    "wof:name": "ST18 0UT",
    "wof:placetype": "postalcode"
  },
  "geometry": {"coordinates":[-1.986996,52.794287],"type":"Point"}
}
