{
  "type": "Feature",
  "properties": {
    "iso:country":"GB",
    "wof:name":"ST18 0UT",
    "wof:placetype":"postalcode"
},
  "geometry": {"coordinates":[-1.98699638018878,52.79428704603242],"type":"Point"}
}