{
  "type": "Feature",
  "properties": {
    "date:inception_lower":"1980-01-01",
    "date:inception_upper":"1980-01-31",
    "iso:country":"GB",
    "wof:name":"BH25 5SB",
    "wof:placetype":"postalcode"
},
  "geometry": {"coordinates":[-1.657735,50.77424],"type":"Point"}
}