{
  "type": "Feature",
  "properties": {
    "iso:country":"GB",
    "wof:name":"AB41 6BD",
    "wof:placetype":"postalcode"
},
  "geometry": {"coordinates":[-2.07659480789654,57.288657406159],"type":"Point"}
}