{
  "type": "Feature",
  "properties": {
    "iso:country": "GB",
    "wof:name": "WA7 1NU",
    "wof:placetype": "postalcode"
  },
  "geometry": {"coordinates":[-2.692389,53.343055],"type":"Point"}
}
