{
  "type": "Feature",
  "properties": {
    "iso:country":"GB",
    "wof:name":"WA7 1NU",
    "wof:placetype":"postalcode"
},
  "geometry": {"coordinates":[-2.69238896301992,53.34305525868692],"type":"Point"}
}