{
  "type": "Feature",
  "properties": {
    "iso:country":"GB",
    "wof:name":"NN16 0TB",
    "wof:placetype":"postalcode"
},
  "geometry": {"coordinates":[-0.71990032628025,52.39890295383189],"type":"Point"}
}