{
  "type": "Feature",
  "properties": {
    "iso:country":"GB",
    "wof:name":"DD11 4EY",
    "wof:placetype":"postalcode"
},
  "geometry": {"coordinates":[-2.60499179713892,56.56786830671776],"type":"Point"}
}