{
  "type": "Feature",
  "properties": {
    "date:inception_lower":"1987-04-01",
    "date:inception_upper":"1987-04-30",
    "iso:country":"GB",
    "wof:name":"SA7 9EQ",
    "wof:placetype":"postalcode"
},
  "geometry": {"coordinates":[-3.910283,51.654757],"type":"Point"}
}