{
  "type": "Feature",
  "properties": {
    "iso:country": "GB",
    "wof:name": "SA7 9EQ",
    "wof:placetype": "postalcode"
  },
  "geometry": {"coordinates":[-3.910283,51.654757],"type":"Point"}
}
