{
  "type": "Feature",
  "properties": {
    "iso:country":"GB",
    "wof:name":"SA7 9EQ",
    "wof:placetype":"postalcode"
},
  "geometry": {"coordinates":[-3.91028328925241,51.65475654262635],"type":"Point"}
}