{
  "type": "Feature",
  "properties": {
    "date:inception_lower": "1987-04-01",
    "date:inception_upper": "1987-04-01",
    "iso:country": "GB",
    "wof:name": "SA7 9EQ",
    "wof:placetype": "postalcode"
  },
  "geometry": {"coordinates":[-3.910253,51.654654],"type":"Point"}
}
