{
  "type": "Feature",
  "properties": {
    "date:inception_lower": "1980-01-01",
    "date:inception_upper": "1980-01-01",
    "iso:country": "GB",
    "wof:name": "CT19 4DN",
    "wof:placetype": "postalcode"
  },
  "geometry": {"coordinates":[1.154221,51.086271],"type":"Point"}
}
