{
  "type": "Feature",
  "properties": {
    "iso:country": "GB",
    "wof:name": "IP19 0NG",
    "wof:placetype": "postalcode"
  },
  "geometry": {"coordinates":[1.449296,52.370903],"type":"Point"}
}
