{
  "type": "Feature",
  "properties": {
    "iso:country":"GB",
    "wof:name":"CF35 5AA",
    "wof:placetype":"postalcode"
},
  "geometry": {"coordinates":[-3.58512743813098,51.48525767356964],"type":"Point"}
}