{
  "type": "Feature",
  "properties": {
    "iso:country": "GB",
    "wof:name": "CF35 5AA",
    "wof:placetype": "postalcode"
  },
  "geometry": {"coordinates":[-3.585127,51.485258],"type":"Point"}
}
