{
  "type": "Feature",
  "properties": {
    "date:inception_lower": "2009-05-01",
    "date:inception_upper": "2009-05-01",
    "iso:country": "GB",
    "wof:name": "NN14 1UA",
    "wof:placetype": "postalcode"
  },
  "geometry": {"coordinates":[-0.733547,52.4228],"type":"Point"}
}
