{
  "type": "Feature",
  "properties": {
    "iso:country":"GB",
    "wof:name":"NN14 1UA",
    "wof:placetype":"postalcode"
},
  "geometry": {"coordinates":[-0.73745484368634,52.42292584634966],"type":"Point"}
}