{
  "type": "Feature",
  "properties": {
    "date:inception_lower": "1997-12-01",
    "date:inception_upper": "1997-12-01",
    "iso:country": "GB",
    "wof:name": "BS40 5DZ",
    "wof:placetype": "postalcode"
  },
  "geometry": {"coordinates":[-2.784156,51.337874],"type":"Point"}
}
