{
  "type": "Feature",
  "properties": {
    "iso:country":"GB",
    "wof:name":"SO52 9EJ",
    "wof:placetype":"postalcode"
},
  "geometry": {"coordinates":[-1.4375645826342,50.97678821175666],"type":"Point"}
}