{
  "type": "Feature",
  "properties": {
    "date:inception_lower": "2020-12-01",
    "date:inception_upper": "2020-12-01",
    "iso:country": "GB",
    "wof:name": "ML3 6NR",
    "wof:placetype": "postalcode"
  },
  "geometry": {"coordinates":[-4.048731,55.775703],"type":"Point"}
}
