{
  "type": "Feature",
  "properties": {
    "date:inception_lower": "1991-09-01",
    "date:inception_upper": "1991-09-01",
    "iso:country": "GB",
    "wof:name": "NG6 0NZ",
    "wof:placetype": "postalcode"
  },
  "geometry": {"coordinates":[-1.175548,52.987956],"type":"Point"}
}
