{
  "type": "Feature",
  "properties": {
    "iso:country": "GB",
    "wof:name": "NG6 0NZ",
    "wof:placetype": "postalcode"
  },
  "geometry": {"coordinates":[-1.175548,52.987956],"type":"Point"}
}
