{
  "type": "Feature",
  "properties": {
    "iso:country": "GB",
    "wof:name": "LN10 6YW",
    "wof:placetype": "postalcode"
  },
  "geometry": {"coordinates":[-0.144806,53.144713],"type":"Point"}
}
