{
  "type": "Feature",
  "properties": {
    "date:inception_lower": "1998-12-01",
    "date:inception_upper": "1998-12-01",
    "iso:country": "GB",
    "wof:name": "IV30 6JL",
    "wof:placetype": "postalcode"
  },
  "geometry": {"coordinates":[-3.30878,57.639098],"type":"Point"}
}
