{
  "type": "Feature",
  "properties": {
    "iso:country": "GB",
    "wof:name": "IV30 6JL",
    "wof:placetype": "postalcode"
  },
  "geometry": {"coordinates":[-3.30878,57.639098],"type":"Point"}
}
