{
  "type": "Feature",
  "properties": {
    "iso:country": "GB",
    "wof:name": "M35 9LJ",
    "wof:placetype": "postalcode"
  },
  "geometry": {"coordinates":[-2.144378,53.512443],"type":"Point"}
}
