{
  "type": "Feature",
  "properties": {
    "iso:country":"GB",
    "wof:name":"M35 9LJ",
    "wof:placetype":"postalcode"
},
  "geometry": {"coordinates":[-2.14437825094078,53.51244282258638],"type":"Point"}
}