{
  "type": "Feature",
  "properties": {
    "iso:country":"GB",
    "wof:name":"PE19 6RR",
    "wof:placetype":"postalcode"
},
  "geometry": {"coordinates":[-0.22536473782226,52.25863323665467],"type":"Point"}
}