{
  "type": "Feature",
  "properties": {
    "date:inception_lower": "2020-04-01",
    "date:inception_upper": "2020-04-01",
    "iso:country": "GB",
    "wof:name": "WD25 9DX",
    "wof:placetype": "postalcode"
  },
  "geometry": {"coordinates":[-0.38088,51.680889],"type":"Point"}
}
