{
  "type": "Feature",
  "properties": {
    "date:inception_lower":"1992-01-01",
    "date:inception_upper":"1992-01-31",
    "iso:country":"GB",
    "wof:name":"PO7 4TH",
    "wof:placetype":"postalcode"
},
  "geometry": {"coordinates":[-1.072231,50.942023],"type":"Point"}
}