{
  "type": "Feature",
  "properties": {
    "iso:country":"GB",
    "wof:name":"LE4 5BF",
    "wof:placetype":"postalcode"
},
  "geometry": {"coordinates":[-1.1229243211814,52.65147178178849],"type":"Point"}
}