{
  "type": "Feature",
  "properties": {
    "iso:country":"GB",
    "wof:name":"S20 5EF",
    "wof:placetype":"postalcode"
},
  "geometry": {"coordinates":[-1.35976515312796,53.32042790408614],"type":"Point"}
}