{
  "type": "Feature",
  "properties": {
    "iso:country":"GB",
    "wof:name":"BH3 7HB",
    "wof:placetype":"postalcode"
},
  "geometry": {"coordinates":[-1.89756924002619,50.73449938464867],"type":"Point"}
}