{
  "type": "Feature",
  "properties": {
    "date:inception_lower": "1999-06-01",
    "date:inception_upper": "1999-06-01",
    "iso:country": "GB",
    "wof:name": "NP18 3SH",
    "wof:placetype": "postalcode"
  },
  "geometry": {"coordinates":[-2.972782,51.612264],"type":"Point"}
}
