{
  "type": "Feature",
  "properties": {
    "iso:country":"GB",
    "wof:name":"NP18 3SH",
    "wof:placetype":"postalcode"
},
  "geometry": {"coordinates":[-2.97278194936303,51.61226402221584],"type":"Point"}
}