{
  "type": "Feature",
  "properties": {
    "iso:country":"GB",
    "wof:name":"BH1 1SD",
    "wof:placetype":"postalcode"
},
  "geometry": {"coordinates":[-1.86712271280967,50.72271532550193],"type":"Point"}
}