{
  "type": "Feature",
  "properties": {
    "iso:country":"GB",
    "wof:name":"SY7 8BD",
    "wof:placetype":"postalcode"
},
  "geometry": {"coordinates":[-2.97891468392643,52.44881334350433],"type":"Point"}
}