{
  "type": "Feature",
  "properties": {
    "iso:country": "GB",
    "wof:name": "SY7 8BD",
    "wof:placetype": "postalcode"
  },
  "geometry": {"coordinates":[-2.978915,52.448813],"type":"Point"}
}
