{
  "type": "Feature",
  "properties": {
    "iso:country": "GB",
    "wof:name": "G76 7RG",
    "wof:placetype": "postalcode"
  },
  "geometry": {"coordinates":[-4.293243,55.789972],"type":"Point"}
}
