{
  "type": "Feature",
  "properties": {
    "iso:country":"GB",
    "wof:name":"TR3 7NN",
    "wof:placetype":"postalcode"
},
  "geometry": {"coordinates":[-5.10996101469307,50.21628323732708],"type":"Point"}
}