{
  "type": "Feature",
  "properties": {
    "iso:country":"GB",
    "wof:name":"CR8 3BB",
    "wof:placetype":"postalcode"
},
  "geometry": {"coordinates":[-0.12604204417557,51.33747296920843],"type":"Point"}
}