{
  "type": "Feature",
  "properties": {
    "iso:country":"GB",
    "wof:name":"CV22 7LA",
    "wof:placetype":"postalcode"
},
  "geometry": {"coordinates":[-1.29470367301026,52.36341605263392],"type":"Point"}
}