{
  "type": "Feature",
  "properties": {
    "iso:country": "GB",
    "wof:name": "CV22 7LA",
    "wof:placetype": "postalcode"
  },
  "geometry": {"coordinates":[-1.294663,52.363415],"type":"Point"}
}
