{
  "type": "Feature",
  "properties": {
    "iso:country":"GB",
    "wof:name":"ZE1 0ND",
    "wof:placetype":"postalcode"
},
  "geometry": {"coordinates":[-1.14772540258672,60.15786764130202],"type":"Point"}
}