{
  "type": "Feature",
  "properties": {
    "iso:country": "GB",
    "wof:name": "ZE1 0ND",
    "wof:placetype": "postalcode"
  },
  "geometry": {"coordinates":[-1.147725,60.157868],"type":"Point"}
}
