{
  "type": "Feature",
  "properties": {
    "date:inception_lower": "2013-05-01",
    "date:inception_upper": "2013-05-01",
    "iso:country": "GB",
    "wof:name": "WS11 8LA",
    "wof:placetype": "postalcode"
  },
  "geometry": {"coordinates":[-2.022628,52.671254],"type":"Point"}
}
