{
  "type": "Feature",
  "properties": {
    "date:inception_lower": "1980-01-01",
    "date:inception_upper": "1980-01-01",
    "iso:country": "GB",
    "wof:name": "IP17 1QJ",
    "wof:placetype": "postalcode"
  },
  "geometry": {"coordinates":[1.501143,52.183009],"type":"Point"}
}
