{
  "type": "Feature",
  "properties": {
    "iso:country":"GB",
    "wof:name":"IP17 1QJ",
    "wof:placetype":"postalcode"
},
  "geometry": {"coordinates":[1.50111113912004,52.18298931648827],"type":"Point"}
}