{
  "type": "Feature",
  "properties": {
    "date:inception_lower": "2016-12-01",
    "date:inception_upper": "2016-12-01",
    "iso:country": "GB",
    "wof:name": "GU21 7AB",
    "wof:placetype": "postalcode"
  },
  "geometry": {"coordinates":[-0.594467,51.312843],"type":"Point"}
}
