{
  "type": "Feature",
  "properties": {
    "iso:country": "GB",
    "wof:name": "CF83 8BP",
    "wof:placetype": "postalcode"
  },
  "geometry": {"coordinates":[-3.186185,51.592507],"type":"Point"}
}
