{
  "type": "Feature",
  "properties": {
    "iso:country": "GB",
    "wof:name": "EX12 2QT",
    "wof:placetype": "postalcode"
  },
  "geometry": {"coordinates":[-3.072237,50.704728],"type":"Point"}
}
