{
  "type": "Feature",
  "properties": {
    "date:inception_lower":"2012-08-01",
    "date:inception_upper":"2012-08-31",
    "iso:country":"GB",
    "wof:name":"PA8 6FD",
    "wof:placetype":"postalcode"
},
  "geometry": {"coordinates":[-4.457249,55.910216],"type":"Point"}
}