{
  "type": "Feature",
  "properties": {
    "iso:country":"GB",
    "wof:name":"PA8 6FD",
    "wof:placetype":"postalcode"
},
  "geometry": {"coordinates":[-4.45724921728582,55.91021582683127],"type":"Point"}
}