{
  "type": "Feature",
  "properties": {
    "iso:country": "GB",
    "wof:name": "PA8 6FD",
    "wof:placetype": "postalcode"
  },
  "geometry": {"coordinates":[-4.457249,55.910216],"type":"Point"}
}
