{
  "type": "Feature",
  "properties": {
    "iso:country": "GB",
    "wof:name": "CT11 9PS",
    "wof:placetype": "postalcode"
  },
  "geometry": {"coordinates":[1.411241,51.330256],"type":"Point"}
}
