{
  "type": "Feature",
  "properties": {
    "iso:country":"GB",
    "wof:name":"CT11 9PS",
    "wof:placetype":"postalcode"
},
  "geometry": {"coordinates":[1.41124136078906,51.33025620281211],"type":"Point"}
}