{
  "type": "Feature",
  "properties": {
    "date:inception_lower":"1980-01-01",
    "date:inception_upper":"1980-01-31",
    "iso:country":"GB",
    "wof:name":"SG12 0TF",
    "wof:placetype":"postalcode"
},
  "geometry": {"coordinates":[-0.031604,51.83938],"type":"Point"}
}