{
  "type": "Feature",
  "properties": {
    "iso:country":"GB",
    "wof:name":"SG12 0TF",
    "wof:placetype":"postalcode"
},
  "geometry": {"coordinates":[-0.0316043812078,51.83937983154036],"type":"Point"}
}