{
  "type": "Feature",
  "properties": {
    "iso:country": "GB",
    "wof:name": "NE34 7NE",
    "wof:placetype": "postalcode"
  },
  "geometry": {"coordinates":[-1.402715,54.973036],"type":"Point"}
}
