{
  "type": "Feature",
  "properties": {
    "iso:country":"GB",
    "wof:name":"NE34 7NE",
    "wof:placetype":"postalcode"
},
  "geometry": {"coordinates":[-1.40271523787096,54.9730359140963],"type":"Point"}
}