{
  "type": "Feature",
  "properties": {
    "date:inception_lower":"1980-01-01",
    "date:inception_upper":"1980-01-31",
    "iso:country":"GB",
    "wof:name":"NE34 7NE",
    "wof:placetype":"postalcode"
},
  "geometry": {"coordinates":[-1.402715,54.973036],"type":"Point"}
}