{
  "type": "Feature",
  "properties": {
    "iso:country": "GB",
    "wof:name": "HX2 6JB",
    "wof:placetype": "postalcode"
  },
  "geometry": {"coordinates":[-1.960404,53.729856],"type":"Point"}
}
