{
  "type": "Feature",
  "properties": {
    "iso:country":"GB",
    "wof:name":"HX2 6JB",
    "wof:placetype":"postalcode"
},
  "geometry": {"coordinates":[-1.9604023418166,53.72984109373567],"type":"Point"}
}