{
  "type": "Feature",
  "properties": {
    "date:inception_lower": "1994-05-01",
    "date:inception_upper": "1994-05-01",
    "iso:country": "GB",
    "wof:name": "DH9 0QQ",
    "wof:placetype": "postalcode"
  },
  "geometry": {"coordinates":[-1.66079,54.87455],"type":"Point"}
}
