{
  "type": "Feature",
  "properties": {
    "iso:country": "GB",
    "wof:name": "LD2 3AX",
    "wof:placetype": "postalcode"
  },
  "geometry": {"coordinates":[-3.345439,52.042883],"type":"Point"}
}
