{
  "type": "Feature",
  "properties": {
    "iso:country":"GB",
    "wof:name":"B74 3BA",
    "wof:placetype":"postalcode"
},
  "geometry": {"coordinates":[-1.86094784194422,52.60096543904361],"type":"Point"}
}