{
  "type": "Feature",
  "properties": {
    "iso:country": "GB",
    "wof:name": "B74 3BA",
    "wof:placetype": "postalcode"
  },
  "geometry": {"coordinates":[-1.860948,52.600965],"type":"Point"}
}
