{
  "type": "Feature",
  "properties": {
    "iso:country":"GB",
    "wof:name":"TS26 9NN",
    "wof:placetype":"postalcode"
},
  "geometry": {"coordinates":[-1.23240377008152,54.68240397550868],"type":"Point"}
}