{
  "type": "Feature",
  "properties": {
    "date:inception_lower":"1980-01-01",
    "date:inception_upper":"1980-01-31",
    "iso:country":"GB",
    "wof:name":"TS26 9NN",
    "wof:placetype":"postalcode"
},
  "geometry": {"coordinates":[-1.232404,54.682404],"type":"Point"}
}