{
  "type": "Feature",
  "properties": {
    "iso:country":"GB",
    "wof:name":"LL54 6PW",
    "wof:placetype":"postalcode"
},
  "geometry": {"coordinates":[-4.28251684686429,53.05694201685471],"type":"Point"}
}