{
  "type": "Feature",
  "properties": {
    "date:inception_lower": "1980-01-01",
    "date:inception_upper": "1980-01-01",
    "iso:country": "GB",
    "wof:name": "ME3 8QH",
    "wof:placetype": "postalcode"
  },
  "geometry": {"coordinates":[0.562475,51.442715],"type":"Point"}
}
