{
  "type": "Feature",
  "properties": {
    "iso:country":"GB",
    "wof:name":"PA3 4QA",
    "wof:placetype":"postalcode"
},
  "geometry": {"coordinates":[-4.40280636124629,55.85839758402678],"type":"Point"}
}