{
  "type": "Feature",
  "properties": {
    "iso:country":"GB",
    "wof:name":"KY12 7ST",
    "wof:placetype":"postalcode"
},
  "geometry": {"coordinates":[-3.43212711404011,56.07380040061685],"type":"Point"}
}