{
  "type": "Feature",
  "properties": {
    "iso:country":"GB",
    "wof:name":"HA3 7QT",
    "wof:placetype":"postalcode"
},
  "geometry": {"coordinates":[-0.33195199413947,51.59391924332319],"type":"Point"}
}