{
  "type": "Feature",
  "properties": {
    "date:inception_lower": "2003-05-01",
    "date:inception_upper": "2003-05-01",
    "iso:country": "GB",
    "wof:name": "GU10 5ZQ",
    "wof:placetype": "postalcode"
  },
  "geometry": {"coordinates":[-0.801697,51.214399],"type":"Point"}
}
