{
  "type": "Feature",
  "properties": {
    "date:inception_lower":"2012-08-01",
    "date:inception_upper":"2012-08-31",
    "iso:country":"GB",
    "wof:name":"DD1 1DH",
    "wof:placetype":"postalcode"
},
  "geometry": {"coordinates":[-2.971177,56.461777],"type":"Point"}
}