{
  "type": "Feature",
  "properties": {
    "iso:country":"GB",
    "wof:name":"DD1 1DH",
    "wof:placetype":"postalcode"
},
  "geometry": {"coordinates":[-2.97117733744896,56.46177658482885],"type":"Point"}
}