{
  "type": "Feature",
  "properties": {
    "iso:country":"GB",
    "wof:name":"SN3 3BX",
    "wof:placetype":"postalcode"
},
  "geometry": {"coordinates":[-1.75481772455975,51.5614993523244],"type":"Point"}
}