{
  "type": "Feature",
  "properties": {
    "iso:country":"GB",
    "wof:name":"TA6 3LQ",
    "wof:placetype":"postalcode"
},
  "geometry": {"coordinates":[-3.00290203183088,51.12816174839636],"type":"Point"}
}