{
  "type": "Feature",
  "properties": {
    "iso:country":"GB",
    "wof:name":"B12 8NX",
    "wof:placetype":"postalcode"
},
  "geometry": {"coordinates":[-1.87759093090242,52.45630050109629],"type":"Point"}
}