{
  "type": "Feature",
  "properties": {
    "iso:country": "GB",
    "wof:name": "E15 2GW",
    "wof:placetype": "postalcode"
  },
  "geometry": {"coordinates":[-0.023555,51.546985],"type":"Point"}
}
