{
  "type": "Feature",
  "properties": {
    "iso:country": "GB",
    "wof:name": "YO25 3HQ",
    "wof:placetype": "postalcode"
  },
  "geometry": {"coordinates":[-0.451104,54.140954],"type":"Point"}
}
