{
  "type": "Feature",
  "properties": {
    "iso:country":"GB",
    "wof:name":"YO25 3HQ",
    "wof:placetype":"postalcode"
},
  "geometry": {"coordinates":[-0.45110374561948,54.14095439720114],"type":"Point"}
}