{
  "type": "Feature",
  "properties": {
    "date:inception_lower":"2007-10-01",
    "date:inception_upper":"2007-10-31",
    "iso:country":"GB",
    "wof:name":"PO36 8DN",
    "wof:placetype":"postalcode"
},
  "geometry": {"coordinates":[-1.157098,50.654385],"type":"Point"}
}