{
  "type": "Feature",
  "properties": {
    "iso:country":"GB",
    "wof:name":"CO9 4RH",
    "wof:placetype":"postalcode"
},
  "geometry": {"coordinates":[0.54626393370823,52.0319485962796],"type":"Point"}
}