{
  "type": "Feature",
  "properties": {
    "iso:country":"GB",
    "wof:name":"DE56 0JT",
    "wof:placetype":"postalcode"
},
  "geometry": {"coordinates":[-1.43129703821306,53.00574227704484],"type":"Point"}
}