{
  "type": "Feature",
  "properties": {
    "iso:country":"GB",
    "wof:name":"DL8 3JG",
    "wof:placetype":"postalcode"
},
  "geometry": {"coordinates":[-2.11618367422149,54.31837225501352],"type":"Point"}
}