{
  "type": "Feature",
  "properties": {
    "iso:country":"GB",
    "wof:name":"CV34 4JD",
    "wof:placetype":"postalcode"
},
  "geometry": {"coordinates":[-1.58233222183662,52.28250307014191],"type":"Point"}
}