{
  "type": "Feature",
  "properties": {
    "iso:country": "GB",
    "wof:name": "BH8 9NQ",
    "wof:placetype": "postalcode"
  },
  "geometry": {"coordinates":[-1.839472,50.746835],"type":"Point"}
}
