{
  "type": "Feature",
  "properties": {
    "iso:country": "GB",
    "wof:name": "DD8 4TS",
    "wof:placetype": "postalcode"
  },
  "geometry": {"coordinates":[-3.005418,56.684344],"type":"Point"}
}
