{
  "type": "Feature",
  "properties": {
    "iso:country":"GB",
    "wof:name":"DD8 4TS",
    "wof:placetype":"postalcode"
},
  "geometry": {"coordinates":[-3.00541815881311,56.68434360586433],"type":"Point"}
}