{
  "type": "Feature",
  "properties": {
    "date:inception_lower":"2017-02-01",
    "date:inception_upper":"2017-02-28",
    "iso:country":"GB",
    "wof:name":"E3 3JH",
    "wof:placetype":"postalcode"
},
  "geometry": {"coordinates":[-0.007854,51.523743],"type":"Point"}
}