{
  "type": "Feature",
  "properties": {
    "iso:country": "GB",
    "wof:name": "IP2 9RB",
    "wof:placetype": "postalcode"
  },
  "geometry": {"coordinates":[1.113697,52.040848],"type":"Point"}
}
