{
  "type": "Feature",
  "properties": {
    "iso:country":"GB",
    "wof:name":"IP2 9RB",
    "wof:placetype":"postalcode"
},
  "geometry": {"coordinates":[1.11369692119683,52.04084845649056],"type":"Point"}
}