{
  "type": "Feature",
  "properties": {
    "iso:country":"GB",
    "wof:name":"CH3 8LA",
    "wof:placetype":"postalcode"
},
  "geometry": {"coordinates":[-2.76682316391773,53.19616946873624],"type":"Point"}
}