{
  "type": "Feature",
  "properties": {
    "iso:country": "GB",
    "wof:name": "CA22 2LR",
    "wof:placetype": "postalcode"
  },
  "geometry": {"coordinates":[-3.533224,54.480282],"type":"Point"}
}
