{
  "type": "Feature",
  "properties": {
    "date:inception_lower": "1980-01-01",
    "date:inception_upper": "1980-01-01",
    "iso:country": "GB",
    "wof:name": "BA21 4NP",
    "wof:placetype": "postalcode"
  },
  "geometry": {"coordinates":[-2.62797,50.95783],"type":"Point"}
}
