{
  "type": "Feature",
  "properties": {
    "iso:country":"GB",
    "wof:name":"BA21 4NP",
    "wof:placetype":"postalcode"
},
  "geometry": {"coordinates":[-2.62779930331655,50.95787421193277],"type":"Point"}
}