{
  "type": "Feature",
  "properties": {
    "iso:country":"GB",
    "wof:name":"HP22 5EH",
    "wof:placetype":"postalcode"
},
  "geometry": {"coordinates":[-0.73561896485556,51.80175904976496],"type":"Point"}
}