{
  "type": "Feature",
  "properties": {
    "date:inception_lower":"2003-02-01",
    "date:inception_upper":"2003-02-28",
    "iso:country":"GB",
    "wof:name":"HP22 5EH",
    "wof:placetype":"postalcode"
},
  "geometry": {"coordinates":[-0.735619,51.801759],"type":"Point"}
}