{
  "type": "Feature",
  "properties": {
    "date:inception_lower": "2006-02-01",
    "date:inception_upper": "2006-02-01",
    "iso:country": "GB",
    "wof:name": "NN10 0FJ",
    "wof:placetype": "postalcode"
  },
  "geometry": {"coordinates":[-0.589508,52.290185],"type":"Point"}
}
