{
  "type": "Feature",
  "properties": {
    "iso:country":"GB",
    "wof:name":"PE34 4PJ",
    "wof:placetype":"postalcode"
},
  "geometry": {"coordinates":[0.28688852639712,52.7541685549625],"type":"Point"}
}