{
  "type": "Feature",
  "properties": {
    "date:inception_lower":"2004-04-01",
    "date:inception_upper":"2004-04-30",
    "iso:country":"GB",
    "wof:name":"GU51 1HN",
    "wof:placetype":"postalcode"
},
  "geometry": {"coordinates":[-0.850735,51.290273],"type":"Point"}
}