{
  "type": "Feature",
  "properties": {
    "iso:country": "GB",
    "wof:name": "GU51 1HN",
    "wof:placetype": "postalcode"
  },
  "geometry": {"coordinates":[-0.850735,51.290273],"type":"Point"}
}
