{
  "type": "Feature",
  "properties": {
    "iso:country":"GB",
    "wof:name":"IV22 2NH",
    "wof:placetype":"postalcode"
},
  "geometry": {"coordinates":[-5.4297133391117,57.88077230760862],"type":"Point"}
}