{
  "type": "Feature",
  "properties": {
    "date:inception_lower": "1980-01-01",
    "date:inception_upper": "1980-01-01",
    "iso:country": "GB",
    "wof:name": "EX20 2SX",
    "wof:placetype": "postalcode"
  },
  "geometry": {"coordinates":[-3.943102,50.793983],"type":"Point"}
}
