{
  "type": "Feature",
  "properties": {
    "iso:country":"GB",
    "wof:name":"EX20 2SX",
    "wof:placetype":"postalcode"
},
  "geometry": {"coordinates":[-3.943101910271,50.79398334630041],"type":"Point"}
}