{
  "type": "Feature",
  "properties": {
    "date:inception_lower": "1992-01-01",
    "date:inception_upper": "1992-01-01",
    "iso:country": "GB",
    "wof:name": "WV14 9JQ",
    "wof:placetype": "postalcode"
  },
  "geometry": {"coordinates":[-2.092304,52.542064],"type":"Point"}
}
