{
  "type": "Feature",
  "properties": {
    "iso:country":"GB",
    "wof:name":"NG10 2DE",
    "wof:placetype":"postalcode"
},
  "geometry": {"coordinates":[-1.25992764887438,52.89520034639035],"type":"Point"}
}