{
  "type": "Feature",
  "properties": {
    "iso:country":"GB",
    "wof:name":"IV2 6UN",
    "wof:placetype":"postalcode"
},
  "geometry": {"coordinates":[-4.50616663487783,57.20836156817199],"type":"Point"}
}