{
  "type": "Feature",
  "properties": {
    "iso:country":"GB",
    "wof:name":"ME19 4PA",
    "wof:placetype":"postalcode"
},
  "geometry": {"coordinates":[0.39554667846519,51.26641303471629],"type":"Point"}
}