{
  "type": "Feature",
  "properties": {
    "iso:country":"GB",
    "wof:name":"DD5 2JF",
    "wof:placetype":"postalcode"
},
  "geometry": {"coordinates":[-2.86945374087418,56.4693769685449],"type":"Point"}
}