{
  "type": "Feature",
  "properties": {
    "date:inception_lower": "1980-01-01",
    "date:inception_upper": "1980-01-01",
    "iso:country": "GB",
    "wof:name": "DD5 2JF",
    "wof:placetype": "postalcode"
  },
  "geometry": {"coordinates":[-2.869454,56.469377],"type":"Point"}
}
