{
  "type": "Feature",
  "properties": {
    "iso:country": "GB",
    "wof:name": "DD5 2JF",
    "wof:placetype": "postalcode"
  },
  "geometry": {"coordinates":[-2.869454,56.469377],"type":"Point"}
}
