{
  "type": "Feature",
  "properties": {
    "iso:country":"GB",
    "wof:name":"WS2 8QD",
    "wof:placetype":"postalcode"
},
  "geometry": {"coordinates":[-1.99386020264259,52.59220065750716],"type":"Point"}
}