{
  "type": "Feature",
  "properties": {
    "iso:country":"GB",
    "wof:name":"WF4 1RT",
    "wof:placetype":"postalcode"
},
  "geometry": {"coordinates":[-1.45109365279072,53.66527858353994],"type":"Point"}
}