{
  "type": "Feature",
  "properties": {
    "iso:country":"GB",
    "wof:name":"RG21 5SN",
    "wof:placetype":"postalcode"
},
  "geometry": {"coordinates":[-1.09410693032383,51.27607857333568],"type":"Point"}
}