{
  "type": "Feature",
  "properties": {
    "date:inception_lower": "1984-10-01",
    "date:inception_upper": "1984-10-01",
    "iso:country": "GB",
    "wof:name": "CB9 0EB",
    "wof:placetype": "postalcode"
  },
  "geometry": {"coordinates":[0.441158,52.091331],"type":"Point"}
}
