{
  "type": "Feature",
  "properties": {
    "iso:country": "GB",
    "wof:name": "BH31 6DJ",
    "wof:placetype": "postalcode"
  },
  "geometry": {"coordinates":[-1.877025,50.874323],"type":"Point"}
}
