{
  "type": "Feature",
  "properties": {
    "iso:country":"GB",
    "wof:name":"SW2 4JW",
    "wof:placetype":"postalcode"
},
  "geometry": {"coordinates":[-0.12778568946538,51.44857852611776],"type":"Point"}
}