{
  "type": "Feature",
  "properties": {
    "date:inception_lower": "1980-01-01",
    "date:inception_upper": "1980-01-01",
    "iso:country": "GB",
    "wof:name": "TR10 9JG",
    "wof:placetype": "postalcode"
  },
  "geometry": {"coordinates":[-5.142588,50.150317],"type":"Point"}
}
