{
  "type": "Feature",
  "properties": {
    "iso:country": "GB",
    "wof:name": "TR10 9JG",
    "wof:placetype": "postalcode"
  },
  "geometry": {"coordinates":[-5.13843,50.155233],"type":"Point"}
}
