{
  "type": "Feature",
  "properties": {
    "iso:country":"GB",
    "wof:name":"SN25 3HH",
    "wof:placetype":"postalcode"
},
  "geometry": {"coordinates":[-1.81075739522837,51.58653580395203],"type":"Point"}
}