{
  "type": "Feature",
  "properties": {
    "date:inception_lower": "1990-02-01",
    "date:inception_upper": "1990-02-01",
    "iso:country": "GB",
    "wof:name": "CA14 4NB",
    "wof:placetype": "postalcode"
  },
  "geometry": {"coordinates":[-3.535947,54.614563],"type":"Point"}
}
