{
  "type": "Feature",
  "properties": {
    "date:inception_lower": "1980-01-01",
    "date:inception_upper": "1980-01-01",
    "iso:country": "GB",
    "wof:name": "NW6 6NN",
    "wof:placetype": "postalcode"
  },
  "geometry": {"coordinates":[-0.205516,51.535483],"type":"Point"}
}
