{
  "type": "Feature",
  "properties": {
    "date:inception_lower":"1980-01-01",
    "date:inception_upper":"1980-01-31",
    "iso:country":"GB",
    "wof:name":"PE13 5BE",
    "wof:placetype":"postalcode"
},
  "geometry": {"coordinates":[0.122502,52.686563],"type":"Point"}
}