{
  "type": "Feature",
  "properties": {
    "iso:country":"GB",
    "wof:name":"PE13 5BE",
    "wof:placetype":"postalcode"
},
  "geometry": {"coordinates":[0.12250243258433,52.68656268657073],"type":"Point"}
}