{
  "type": "Feature",
  "properties": {
    "iso:country":"GB",
    "wof:name":"M13 9FB",
    "wof:placetype":"postalcode"
},
  "geometry": {"coordinates":[-2.22299565729766,53.46511456433473],"type":"Point"}
}