{
  "type": "Feature",
  "properties": {
    "iso:country":"GB",
    "wof:name":"SO15 3NN",
    "wof:placetype":"postalcode"
},
  "geometry": {"coordinates":[-1.43278912389177,50.92210029919607],"type":"Point"}
}