{
  "type": "Feature",
  "properties": {
    "date:inception_lower": "2024-01-01",
    "date:inception_upper": "2024-01-01",
    "iso:country": "GB",
    "wof:name": "IG11 0SZ",
    "wof:placetype": "postalcode"
  },
  "geometry": {"coordinates":[0.124677,51.522343],"type":"Point"}
}
