{
  "type": "Feature",
  "properties": {
    "iso:country":"GB",
    "wof:name":"TN2 5TP",
    "wof:placetype":"postalcode"
},
  "geometry": {"coordinates":[0.25661947797271,51.12608896778642],"type":"Point"}
}