{
  "type": "Feature",
  "properties": {
    "iso:country": "GB",
    "wof:name": "AB55 5JF",
    "wof:placetype": "postalcode"
  },
  "geometry": {"coordinates":[-3.034651,57.483959],"type":"Point"}
}
