{
  "type": "Feature",
  "properties": {
    "date:inception_lower": "1996-06-01",
    "date:inception_upper": "1996-06-01",
    "iso:country": "GB",
    "wof:name": "AB55 5JF",
    "wof:placetype": "postalcode"
  },
  "geometry": {"coordinates":[-3.034651,57.483959],"type":"Point"}
}
