{
  "type": "Feature",
  "properties": {
    "date:inception_lower": "2015-09-01",
    "date:inception_upper": "2015-09-01",
    "iso:country": "GB",
    "wof:name": "HU17 7SZ",
    "wof:placetype": "postalcode"
  },
  "geometry": {"coordinates":[-0.44948,53.855229],"type":"Point"}
}
