{
  "type": "Feature",
  "properties": {
    "iso:country": "GB",
    "wof:name": "TD12 4WB",
    "wof:placetype": "postalcode"
  },
  "geometry": {"coordinates":[-2.222851,55.647632],"type":"Point"}
}
