{
  "type": "Feature",
  "properties": {
    "date:inception_lower":"2008-03-01",
    "date:inception_upper":"2008-03-31",
    "iso:country":"GB",
    "wof:name":"TD12 4WB",
    "wof:placetype":"postalcode"
},
  "geometry": {"coordinates":[-2.222851,55.647632],"type":"Point"}
}