{
  "type": "Feature",
  "properties": {
    "iso:country":"GB",
    "wof:name":"TD12 4WB",
    "wof:placetype":"postalcode"
},
  "geometry": {"coordinates":[-2.22285111924519,55.64763222894151],"type":"Point"}
}