{
  "type": "Feature",
  "properties": {
    "iso:country":"GB",
    "wof:name":"W1K 6JS",
    "wof:placetype":"postalcode"
},
  "geometry": {"coordinates":[-0.151333386185,51.51368052968561],"type":"Point"}
}