{
  "type": "Feature",
  "properties": {
    "iso:country": "GB",
    "wof:name": "ST3 1EX",
    "wof:placetype": "postalcode"
  },
  "geometry": {"coordinates":[-2.133245,52.986324],"type":"Point"}
}
