{
  "type": "Feature",
  "properties": {
    "iso:country":"GB",
    "wof:name":"ST3 1EX",
    "wof:placetype":"postalcode"
},
  "geometry": {"coordinates":[-2.13324535187132,52.98632377613315],"type":"Point"}
}