{
  "type": "Feature",
  "properties": {
    "date:inception_lower": "1980-01-01",
    "date:inception_upper": "1980-01-01",
    "iso:country": "GB",
    "wof:name": "SG4 9AE",
    "wof:placetype": "postalcode"
  },
  "geometry": {"coordinates":[-0.276139,51.943646],"type":"Point"}
}
