{
  "type": "Feature",
  "properties": {
    "iso:country":"GB",
    "wof:name":"SG4 9AE",
    "wof:placetype":"postalcode"
},
  "geometry": {"coordinates":[-0.27616204052752,51.94363924118225],"type":"Point"}
}