{
  "type": "Feature",
  "properties": {
    "iso:country":"GB",
    "wof:name":"G66 3DD",
    "wof:placetype":"postalcode"
},
  "geometry": {"coordinates":[-4.15149659648964,55.93155009985183],"type":"Point"}
}