{
  "type": "Feature",
  "properties": {
    "iso:country": "GB",
    "wof:name": "FK2 8SR",
    "wof:placetype": "postalcode"
  },
  "geometry": {"coordinates":[-3.812851,56.041355],"type":"Point"}
}
