{
  "type": "Feature",
  "properties": {
    "iso:country": "GB",
    "wof:name": "SA70 7HJ",
    "wof:placetype": "postalcode"
  },
  "geometry": {"coordinates":[-4.69866,51.671105],"type":"Point"}
}
