{
  "type": "Feature",
  "properties": {
    "iso:country":"GB",
    "wof:name":"SA70 7HJ",
    "wof:placetype":"postalcode"
},
  "geometry": {"coordinates":[-4.69865987689604,51.6711046363644],"type":"Point"}
}