{
  "type": "Feature",
  "properties": {
    "iso:country":"GB",
    "wof:name":"CB23 5EG",
    "wof:placetype":"postalcode"
},
  "geometry": {"coordinates":[-0.07048458446848,52.21411359706934],"type":"Point"}
}