{
  "type": "Feature",
  "properties": {
    "iso:country": "GB",
    "wof:name": "CB23 5EG",
    "wof:placetype": "postalcode"
  },
  "geometry": {"coordinates":[-0.070485,52.214114],"type":"Point"}
}
