{
  "type": "Feature",
  "properties": {
    "iso:country":"GB",
    "wof:name":"BN14 0BA",
    "wof:placetype":"postalcode"
},
  "geometry": {"coordinates":[-0.39529967771365,50.84318733398616],"type":"Point"}
}