{
  "type": "Feature",
  "properties": {
    "iso:country": "GB",
    "wof:name": "AB24 5HA",
    "wof:placetype": "postalcode"
  },
  "geometry": {"coordinates":[-2.088606,57.151094],"type":"Point"}
}
