{
  "type": "Feature",
  "properties": {
    "iso:country": "GB",
    "wof:name": "NW1 0QA",
    "wof:placetype": "postalcode"
  },
  "geometry": {"coordinates":[-0.135171,51.538181],"type":"Point"}
}
