{
  "type": "Feature",
  "properties": {
    "iso:country":"GB",
    "wof:name":"KY16 9DF",
    "wof:placetype":"postalcode"
},
  "geometry": {"coordinates":[-2.80949313500448,56.33649838458648],"type":"Point"}
}