{
  "type": "Feature",
  "properties": {
    "iso:country":"GB",
    "wof:name":"SE15 5HQ",
    "wof:placetype":"postalcode"
},
  "geometry": {"coordinates":[-0.0683483822315,51.47140875883123],"type":"Point"}
}