{
  "type": "Feature",
  "properties": {
    "date:inception_lower": "1980-01-01",
    "date:inception_upper": "1980-01-01",
    "iso:country": "GB",
    "wof:name": "SL5 7LS",
    "wof:placetype": "postalcode"
  },
  "geometry": {"coordinates":[-0.677163,51.426939],"type":"Point"}
}
