{
  "type": "Feature",
  "properties": {
    "iso:country":"GB",
    "wof:name":"SL5 7LS",
    "wof:placetype":"postalcode"
},
  "geometry": {"coordinates":[-0.67716259054858,51.42693884766324],"type":"Point"}
}