{
  "type": "Feature",
  "properties": {
    "date:inception_lower": "1980-01-01",
    "date:inception_upper": "1980-01-01",
    "iso:country": "GB",
    "wof:name": "BN1 3RQ",
    "wof:placetype": "postalcode"
  },
  "geometry": {"coordinates":[-0.143506,50.829812],"type":"Point"}
}
