{
  "type": "Feature",
  "properties": {
    "iso:country":"GB",
    "wof:name":"BN1 3RQ",
    "wof:placetype":"postalcode"
},
  "geometry": {"coordinates":[-0.14348976419516,50.82986562834414],"type":"Point"}
}