{
  "type": "Feature",
  "properties": {
    "iso:country": "GB",
    "wof:name": "BN1 3RQ",
    "wof:placetype": "postalcode"
  },
  "geometry": {"coordinates":[-0.143506,50.829812],"type":"Point"}
}
