{
  "type": "Feature",
  "properties": {
    "iso:country":"GB",
    "wof:name":"M44 6ZR",
    "wof:placetype":"postalcode"
},
  "geometry": {"coordinates":[-2.42579045800795,53.43842489070834],"type":"Point"}
}