{
  "type": "Feature",
  "properties": {
    "date:inception_lower": "1995-12-01",
    "date:inception_upper": "1995-12-01",
    "iso:country": "GB",
    "wof:name": "SO40 9PJ",
    "wof:placetype": "postalcode"
  },
  "geometry": {"coordinates":[-1.482399,50.911827],"type":"Point"}
}
