{
  "type": "Feature",
  "properties": {
    "date:inception_lower": "1999-06-01",
    "date:inception_upper": "1999-06-01",
    "iso:country": "GB",
    "wof:name": "NP12 3NN",
    "wof:placetype": "postalcode"
  },
  "geometry": {"coordinates":[-3.211847,51.669258],"type":"Point"}
}
