{
  "type": "Feature",
  "properties": {
    "iso:country":"GB",
    "wof:name":"NP12 3NN",
    "wof:placetype":"postalcode"
},
  "geometry": {"coordinates":[-3.21189022705668,51.66924900184034],"type":"Point"}
}