{
  "type": "Feature",
  "properties": {
    "date:inception_lower":"2012-06-01",
    "date:inception_upper":"2012-06-30",
    "iso:country":"GB",
    "wof:name":"PO19 7SZ",
    "wof:placetype":"postalcode"
},
  "geometry": {"coordinates":[-0.772491,50.839958],"type":"Point"}
}