{
  "type": "Feature",
  "properties": {
    "iso:country":"GB",
    "wof:name":"PO19 7SZ",
    "wof:placetype":"postalcode"
},
  "geometry": {"coordinates":[-0.77250996683342,50.83996758201948],"type":"Point"}
}