{
  "type": "Feature",
  "properties": {
    "iso:country": "GB",
    "wof:name": "PO19 7SZ",
    "wof:placetype": "postalcode"
  },
  "geometry": {"coordinates":[-0.772491,50.839958],"type":"Point"}
}
