{
  "type": "Feature",
  "properties": {
    "iso:country":"GB",
    "wof:name":"CV33 9DQ",
    "wof:placetype":"postalcode"
},
  "geometry": {"coordinates":[-1.42491276437088,52.31759637310017],"type":"Point"}
}