{
  "type": "Feature",
  "properties": {
    "date:inception_lower": "1980-01-01",
    "date:inception_upper": "1980-01-01",
    "iso:country": "GB",
    "wof:name": "CV33 9DQ",
    "wof:placetype": "postalcode"
  },
  "geometry": {"coordinates":[-1.42496,52.317613],"type":"Point"}
}
