{
  "type": "Feature",
  "properties": {
    "iso:country":"GB",
    "wof:name":"HU10 7HW",
    "wof:placetype":"postalcode"
},
  "geometry": {"coordinates":[-0.44824703296807,53.74464871734246],"type":"Point"}
}