{
  "type": "Feature",
  "properties": {
    "iso:country":"GB",
    "wof:name":"DE7 4GJ",
    "wof:placetype":"postalcode"
},
  "geometry": {"coordinates":[-1.33136995007124,52.95588903198252],"type":"Point"}
}