{
  "type": "Feature",
  "properties": {
    "iso:country":"GB",
    "wof:name":"CO5 7EP",
    "wof:placetype":"postalcode"
},
  "geometry": {"coordinates":[0.9461514523285,51.85529556562436],"type":"Point"}
}