{
  "type": "Feature",
  "properties": {
    "iso:country": "GB",
    "wof:name": "CO5 7EP",
    "wof:placetype": "postalcode"
  },
  "geometry": {"coordinates":[0.946151,51.855296],"type":"Point"}
}
