{
  "type": "Feature",
  "properties": {
    "iso:country":"GB",
    "wof:name":"PL3 4RX",
    "wof:placetype":"postalcode"
},
  "geometry": {"coordinates":[-4.13484941564272,50.38588750175759],"type":"Point"}
}