{
  "type": "Feature",
  "properties": {
    "iso:country": "GB",
    "wof:name": "PL3 4RX",
    "wof:placetype": "postalcode"
  },
  "geometry": {"coordinates":[-4.134849,50.385887],"type":"Point"}
}
