{
  "type": "Feature",
  "properties": {
    "iso:country":"GB",
    "wof:name":"NG20 0AN",
    "wof:placetype":"postalcode"
},
  "geometry": {"coordinates":[-1.15309427282582,53.20576148900778],"type":"Point"}
}