{
  "type": "Feature",
  "properties": {
    "iso:country":"GB",
    "wof:name":"DT6 3ET",
    "wof:placetype":"postalcode"
},
  "geometry": {"coordinates":[-2.73869365417437,50.74531419259708],"type":"Point"}
}