{
  "type": "Feature",
  "properties": {
    "iso:country":"GB",
    "wof:name":"SW9 9DL",
    "wof:placetype":"postalcode"
},
  "geometry": {"coordinates":[-0.12340670925773,51.46973104576341],"type":"Point"}
}