{
  "type": "Feature",
  "properties": {
    "iso:country": "GB",
    "wof:name": "SW9 9DL",
    "wof:placetype": "postalcode"
  },
  "geometry": {"coordinates":[-0.123521,51.469491],"type":"Point"}
}
