{
  "type": "Feature",
  "properties": {
    "iso:country": "GB",
    "wof:name": "EX37 9PR",
    "wof:placetype": "postalcode"
  },
  "geometry": {"coordinates":[-3.947723,51.012276],"type":"Point"}
}
