{
  "type": "Feature",
  "properties": {
    "iso:country":"GB",
    "wof:name":"EX37 9PR",
    "wof:placetype":"postalcode"
},
  "geometry": {"coordinates":[-3.94763824142263,51.01228653038026],"type":"Point"}
}