{
  "type": "Feature",
  "properties": {
    "iso:country":"GB",
    "wof:name":"TR13 9TU",
    "wof:placetype":"postalcode"
},
  "geometry": {"coordinates":[-5.37451105290565,50.09953337176435],"type":"Point"}
}