{
  "type": "Feature",
  "properties": {
    "iso:country":"GB",
    "wof:name":"IV36 3ED",
    "wof:placetype":"postalcode"
},
  "geometry": {"coordinates":[-3.62171143678063,57.61310114705267],"type":"Point"}
}