{
  "type": "Feature",
  "properties": {
    "date:inception_lower":"1998-12-01",
    "date:inception_upper":"1998-12-31",
    "iso:country":"GB",
    "wof:name":"IV36 3ED",
    "wof:placetype":"postalcode"
},
  "geometry": {"coordinates":[-3.621541,57.613061],"type":"Point"}
}