{
  "type": "Feature",
  "properties": {
    "iso:country":"GB",
    "wof:name":"SS14 1DT",
    "wof:placetype":"postalcode"
},
  "geometry": {"coordinates":[0.45703414085084,51.56970943993837],"type":"Point"}
}