{
  "type": "Feature",
  "properties": {
    "iso:country": "GB",
    "wof:name": "L13 9AE",
    "wof:placetype": "postalcode"
  },
  "geometry": {"coordinates":[-2.929664,53.426621],"type":"Point"}
}
