{
  "type": "Feature",
  "properties": {
    "date:inception_lower":"1980-01-01",
    "date:inception_upper":"1980-01-31",
    "iso:country":"GB",
    "wof:name":"L13 9AE",
    "wof:placetype":"postalcode"
},
  "geometry": {"coordinates":[-2.929664,53.426621],"type":"Point"}
}