{
  "type": "Feature",
  "properties": {
    "date:inception_lower": "1980-01-01",
    "date:inception_upper": "1980-01-01",
    "iso:country": "GB",
    "wof:name": "LN12 1NJ",
    "wof:placetype": "postalcode"
  },
  "geometry": {"coordinates":[0.218755,53.364096],"type":"Point"}
}
