{
  "type": "Feature",
  "properties": {
    "iso:country": "GB",
    "wof:name": "LN12 1NJ",
    "wof:placetype": "postalcode"
  },
  "geometry": {"coordinates":[0.218755,53.364096],"type":"Point"}
}
