{
  "type": "Feature",
  "properties": {
    "iso:country": "GB",
    "wof:name": "S60 5DG",
    "wof:placetype": "postalcode"
  },
  "geometry": {"coordinates":[-1.366593,53.404716],"type":"Point"}
}
