{
  "type": "Feature",
  "properties": {
    "date:inception_lower":"2009-12-01",
    "date:inception_upper":"2009-12-31",
    "iso:country":"GB",
    "wof:name":"S60 5DG",
    "wof:placetype":"postalcode"
},
  "geometry": {"coordinates":[-1.366593,53.404716],"type":"Point"}
}