{
  "type": "Feature",
  "properties": {
    "iso:country": "GB",
    "wof:name": "MK42 0FU",
    "wof:placetype": "postalcode"
  },
  "geometry": {"coordinates":[-0.426837,52.114054],"type":"Point"}
}
