{
  "type": "Feature",
  "properties": {
    "iso:country": "GB",
    "wof:name": "NE46 1SF",
    "wof:placetype": "postalcode"
  },
  "geometry": {"coordinates":[-2.081734,54.945958],"type":"Point"}
}
