{
  "type": "Feature",
  "properties": {
    "iso:country":"GB",
    "wof:name":"BH23 5QT",
    "wof:placetype":"postalcode"
},
  "geometry": {"coordinates":[-1.69318031502589,50.7496625341219],"type":"Point"}
}