{
  "type": "Feature",
  "properties": {
    "iso:country": "GB",
    "wof:name": "RG18 3AU",
    "wof:placetype": "postalcode"
  },
  "geometry": {"coordinates":[-1.268955,51.410479],"type":"Point"}
}
