{
  "type": "Feature",
  "properties": {
    "iso:country":"GB",
    "wof:name":"RG18 3AU",
    "wof:placetype":"postalcode"
},
  "geometry": {"coordinates":[-1.26895455570226,51.4104789664705],"type":"Point"}
}