{
  "type": "Feature",
  "properties": {
    "iso:country":"GB",
    "wof:name":"WN2 4HF",
    "wof:placetype":"postalcode"
},
  "geometry": {"coordinates":[-2.5483742179867,53.52511377112018],"type":"Point"}
}