{
  "type": "Feature",
  "properties": {
    "iso:country":"GB",
    "wof:name":"WV4 6RU",
    "wof:placetype":"postalcode"
},
  "geometry": {"coordinates":[-2.11664925397627,52.56498487954106],"type":"Point"}
}