{
  "type": "Feature",
  "properties": {
    "iso:country": "GB",
    "wof:name": "WV4 6RU",
    "wof:placetype": "postalcode"
  },
  "geometry": {"coordinates":[-2.116649,52.564985],"type":"Point"}
}
