{
  "type": "Feature",
  "properties": {
    "iso:country":"GB",
    "wof:name":"DA1 1RB",
    "wof:placetype":"postalcode"
},
  "geometry": {"coordinates":[0.23339194921781,51.43816119712556],"type":"Point"}
}