{
  "type": "Feature",
  "properties": {
    "iso:country": "GB",
    "wof:name": "DD6 8SD",
    "wof:placetype": "postalcode"
  },
  "geometry": {"coordinates":[-3.041805,56.409084],"type":"Point"}
}
