{
  "type": "Feature",
  "properties": {
    "iso:country":"GB",
    "wof:name":"SP4 6LT",
    "wof:placetype":"postalcode"
},
  "geometry": {"coordinates":[-1.73138529527597,51.11984619558847],"type":"Point"}
}