{
  "type": "Feature",
  "properties": {
    "iso:country":"GB",
    "wof:name":"BB10 3RG",
    "wof:placetype":"postalcode"
},
  "geometry": {"coordinates":[-2.15876571912614,53.8384337561095],"type":"Point"}
}