{
  "type": "Feature",
  "properties": {
    "date:inception_lower": "1991-01-01",
    "date:inception_upper": "1991-01-01",
    "iso:country": "GB",
    "wof:name": "ST20 0AR",
    "wof:placetype": "postalcode"
  },
  "geometry": {"coordinates":[-2.265166,52.778148],"type":"Point"}
}
