{
  "type": "Feature",
  "properties": {
    "iso:country":"GB",
    "wof:name":"CV4 9SB",
    "wof:placetype":"postalcode"
},
  "geometry": {"coordinates":[-1.57991090377489,52.40366478500766],"type":"Point"}
}