{
  "type": "Feature",
  "properties": {
    "iso:country":"GB",
    "wof:name":"L35 3JX",
    "wof:placetype":"postalcode"
},
  "geometry": {"coordinates":[-2.80188350334159,53.41175438675892],"type":"Point"}
}