{
  "type": "Feature",
  "properties": {
    "iso:country":"GB",
    "wof:name":"NE23 3QP",
    "wof:placetype":"postalcode"
},
  "geometry": {"coordinates":[-1.59091423219419,55.09891965857816],"type":"Point"}
}