{
  "type": "Feature",
  "properties": {
    "iso:country":"GB",
    "wof:name":"N16 6TD",
    "wof:placetype":"postalcode"
},
  "geometry": {"coordinates":[-0.06638655162946,51.57630182851401],"type":"Point"}
}