{
  "type": "Feature",
  "properties": {
    "iso:country": "GB",
    "wof:name": "TS20 2EN",
    "wof:placetype": "postalcode"
  },
  "geometry": {"coordinates":[-1.309182,54.5817],"type":"Point"}
}
