{
  "type": "Feature",
  "properties": {
    "iso:country":"GB",
    "wof:name":"TS20 2EN",
    "wof:placetype":"postalcode"
},
  "geometry": {"coordinates":[-1.30918220666467,54.58170008563773],"type":"Point"}
}