{
  "type": "Feature",
  "properties": {
    "iso:country": "GB",
    "wof:name": "CH4 9LZ",
    "wof:placetype": "postalcode"
  },
  "geometry": {"coordinates":[-2.957724,53.143962],"type":"Point"}
}
