{
  "type": "Feature",
  "properties": {
    "iso:country":"GB",
    "wof:name":"CH4 9LZ",
    "wof:placetype":"postalcode"
},
  "geometry": {"coordinates":[-2.95772424438559,53.14396223833452],"type":"Point"}
}