{
  "type": "Feature",
  "properties": {
    "iso:country":"GB",
    "wof:name":"M11 1LL",
    "wof:placetype":"postalcode"
},
  "geometry": {"coordinates":[-2.16294403549251,53.47000252230134],"type":"Point"}
}