{
  "type": "Feature",
  "properties": {
    "iso:country":"GB",
    "wof:name":"LE10 2FL",
    "wof:placetype":"postalcode"
},
  "geometry": {"coordinates":[-1.34960236435071,52.52404336155406],"type":"Point"}
}