{
  "type": "Feature",
  "properties": {
    "iso:country":"GB",
    "wof:name":"RH19 2PS",
    "wof:placetype":"postalcode"
},
  "geometry": {"coordinates":[-0.05519454057056,51.13696145478148],"type":"Point"}
}