{
  "type": "Feature",
  "properties": {
    "date:inception_lower": "1983-07-01",
    "date:inception_upper": "1983-07-01",
    "iso:country": "GB",
    "wof:name": "RH19 2PS",
    "wof:placetype": "postalcode"
  },
  "geometry": {"coordinates":[-0.055167,51.136958],"type":"Point"}
}
