{
  "type": "Feature",
  "properties": {
    "date:inception_lower":"1998-06-01",
    "date:inception_upper":"1998-06-30",
    "iso:country":"GB",
    "wof:name":"HU14 3PS",
    "wof:placetype":"postalcode"
},
  "geometry": {"coordinates":[-0.495659,53.737758],"type":"Point"}
}