{
  "type": "Feature",
  "properties": {
    "iso:country":"GB",
    "wof:name":"HU14 3PS",
    "wof:placetype":"postalcode"
},
  "geometry": {"coordinates":[-0.4956543919977,53.73773833832888],"type":"Point"}
}