{
  "type": "Feature",
  "properties": {
    "date:inception_lower": "1980-01-01",
    "date:inception_upper": "1980-01-01",
    "iso:country": "GB",
    "wof:name": "LE1 6PT",
    "wof:placetype": "postalcode"
  },
  "geometry": {"coordinates":[-1.128851,52.631792],"type":"Point"}
}
