{
  "type": "Feature",
  "properties": {
    "iso:country":"GB",
    "wof:name":"LE1 6PT",
    "wof:placetype":"postalcode"
},
  "geometry": {"coordinates":[-1.12885894572436,52.63177354079721],"type":"Point"}
}