{
  "type": "Feature",
  "properties": {
    "iso:country":"GB",
    "wof:name":"DG9 0RT",
    "wof:placetype":"postalcode"
},
  "geometry": {"coordinates":[-5.16354128914094,54.92766831891235],"type":"Point"}
}