{
  "type": "Feature",
  "properties": {
    "iso:country":"GB",
    "wof:name":"RH12 4RL",
    "wof:placetype":"postalcode"
},
  "geometry": {"coordinates":[-0.2511420018404,51.13207033793862],"type":"Point"}
}