{
  "type": "Feature",
  "properties": {
    "date:inception_lower": "1980-01-01",
    "date:inception_upper": "1980-01-01",
    "iso:country": "GB",
    "wof:name": "RH12 4RL",
    "wof:placetype": "postalcode"
  },
  "geometry": {"coordinates":[-0.251156,51.132112],"type":"Point"}
}
