{
  "type": "Feature",
  "properties": {
    "date:inception_lower": "2008-03-01",
    "date:inception_upper": "2008-03-01",
    "iso:country": "GB",
    "wof:name": "CM2 7HD",
    "wof:placetype": "postalcode"
  },
  "geometry": {"coordinates":[0.499416,51.717598],"type":"Point"}
}
