{
  "type": "Feature",
  "properties": {
    "iso:country":"GB",
    "wof:name":"CM2 7HD",
    "wof:placetype":"postalcode"
},
  "geometry": {"coordinates":[0.49941609863643,51.7175976418719],"type":"Point"}
}