{
  "type": "Feature",
  "properties": {
    "date:inception_lower": "1990-07-01",
    "date:inception_upper": "1990-07-01",
    "iso:country": "GB",
    "wof:name": "B60 3QH",
    "wof:placetype": "postalcode"
  },
  "geometry": {"coordinates":[-2.073392,52.316491],"type":"Point"}
}
