{
  "type": "Feature",
  "properties": {
    "iso:country":"GB",
    "wof:name":"G72 9EL",
    "wof:placetype":"postalcode"
},
  "geometry": {"coordinates":[-4.09668884388664,55.7979585872657],"type":"Point"}
}