{
  "type": "Feature",
  "properties": {
    "iso:country":"GB",
    "wof:name":"LA11 7RA",
    "wof:placetype":"postalcode"
},
  "geometry": {"coordinates":[-2.94156340103694,54.18520421184196],"type":"Point"}
}