{
  "type": "Feature",
  "properties": {
    "date:inception_lower": "1980-01-01",
    "date:inception_upper": "1980-01-01",
    "iso:country": "GB",
    "wof:name": "SP10 3BS",
    "wof:placetype": "postalcode"
  },
  "geometry": {"coordinates":[-1.511881,51.209588],"type":"Point"}
}
