{
  "type": "Feature",
  "properties": {
    "iso:country":"GB",
    "wof:name":"SP10 3BS",
    "wof:placetype":"postalcode"
},
  "geometry": {"coordinates":[-1.51188097446159,51.20958755302047],"type":"Point"}
}