{
  "type": "Feature",
  "properties": {
    "iso:country":"GB",
    "wof:name":"CH44 7BE",
    "wof:placetype":"postalcode"
},
  "geometry": {"coordinates":[-3.01965618783347,53.40816039385815],"type":"Point"}
}