{
  "type": "Feature",
  "properties": {
    "iso:country":"GB",
    "wof:name":"TQ9 5GT",
    "wof:placetype":"postalcode"
},
  "geometry": {"coordinates":[-3.68708094002844,50.43014858853877],"type":"Point"}
}