{
  "type": "Feature",
  "properties": {
    "date:inception_lower": "2003-09-01",
    "date:inception_upper": "2003-09-01",
    "iso:country": "GB",
    "wof:name": "TQ9 5GT",
    "wof:placetype": "postalcode"
  },
  "geometry": {"coordinates":[-3.687099,50.430089],"type":"Point"}
}
