{
  "type": "Feature",
  "properties": {
    "iso:country": "GB",
    "wof:name": "TQ9 5GT",
    "wof:placetype": "postalcode"
  },
  "geometry": {"coordinates":[-3.687099,50.430089],"type":"Point"}
}
