{
  "type": "Feature",
  "properties": {
    "iso:country": "GB",
    "wof:name": "BH21 5RJ",
    "wof:placetype": "postalcode"
  },
  "geometry": {"coordinates":[-1.888249,50.89409],"type":"Point"}
}
