{
  "type": "Feature",
  "properties": {
    "iso:country":"GB",
    "wof:name":"W7 1BL",
    "wof:placetype":"postalcode"
},
  "geometry": {"coordinates":[-0.33814456062979,51.52389468382837],"type":"Point"}
}