{
  "type": "Feature",
  "properties": {
    "iso:country":"GB",
    "wof:name":"RG25 3LD",
    "wof:placetype":"postalcode"
},
  "geometry": {"coordinates":[-1.26810650275987,51.23999636883073],"type":"Point"}
}