{
  "type": "Feature",
  "properties": {
    "iso:country": "GB",
    "wof:name": "RG25 3LD",
    "wof:placetype": "postalcode"
  },
  "geometry": {"coordinates":[-1.268106,51.239996],"type":"Point"}
}
