{
  "type": "Feature",
  "properties": {
    "iso:country":"GB",
    "wof:name":"PH7 3SQ",
    "wof:placetype":"postalcode"
},
  "geometry": {"coordinates":[-3.82164792063589,56.37229602550242],"type":"Point"}
}