{
  "type": "Feature",
  "properties": {
    "date:inception_lower": "2002-05-01",
    "date:inception_upper": "2002-05-01",
    "iso:country": "GB",
    "wof:name": "PH7 3SQ",
    "wof:placetype": "postalcode"
  },
  "geometry": {"coordinates":[-3.821648,56.372296],"type":"Point"}
}
