{
  "type": "Feature",
  "properties": {
    "iso:country":"GB",
    "wof:name":"LS25 5LH",
    "wof:placetype":"postalcode"
},
  "geometry": {"coordinates":[-1.30229664701908,53.77497928589677],"type":"Point"}
}