{
  "type": "Feature",
  "properties": {
    "date:inception_lower": "1980-01-01",
    "date:inception_upper": "1980-01-01",
    "iso:country": "GB",
    "wof:name": "LS14 5LU",
    "wof:placetype": "postalcode"
  },
  "geometry": {"coordinates":[-1.441943,53.82057],"type":"Point"}
}
