{
  "type": "Feature",
  "properties": {
    "iso:country":"GB",
    "wof:name":"LS14 5LU",
    "wof:placetype":"postalcode"
},
  "geometry": {"coordinates":[-1.44194294380702,53.82056979142718],"type":"Point"}
}