{
  "type": "Feature",
  "properties": {
    "iso:country": "GB",
    "wof:name": "LA1 3RL",
    "wof:placetype": "postalcode"
  },
  "geometry": {"coordinates":[-2.774363,54.048065],"type":"Point"}
}
