{
  "type": "Feature",
  "properties": {
    "iso:country":"GB",
    "wof:name":"BN6 9AQ",
    "wof:placetype":"postalcode"
},
  "geometry": {"coordinates":[-0.16410754416399,50.93261723740752],"type":"Point"}
}