{
  "type": "Feature",
  "properties": {
    "iso:country":"GB",
    "wof:name":"BL9 7HU",
    "wof:placetype":"postalcode"
},
  "geometry": {"coordinates":[-2.25792763147638,53.58688185910238],"type":"Point"}
}