{
  "type": "Feature",
  "properties": {
    "date:inception_lower": "1995-12-01",
    "date:inception_upper": "1995-12-01",
    "iso:country": "GB",
    "wof:name": "BL9 7HU",
    "wof:placetype": "postalcode"
  },
  "geometry": {"coordinates":[-2.257928,53.586882],"type":"Point"}
}
