{
  "type": "Feature",
  "properties": {
    "iso:country":"GB",
    "wof:name":"LU5 6FL",
    "wof:placetype":"postalcode"
},
  "geometry": {"coordinates":[-0.5309655617965,51.95065498815373],"type":"Point"}
}