{
  "type": "Feature",
  "properties": {
    "date:inception_lower":"2007-03-01",
    "date:inception_upper":"2007-03-31",
    "iso:country":"GB",
    "wof:name":"LU5 6FL",
    "wof:placetype":"postalcode"
},
  "geometry": {"coordinates":[-0.53082,51.950788],"type":"Point"}
}