{
  "type": "Feature",
  "properties": {
    "iso:country": "GB",
    "wof:name": "RH20 4QB",
    "wof:placetype": "postalcode"
  },
  "geometry": {"coordinates":[-0.460079,50.922687],"type":"Point"}
}
