{
  "type": "Feature",
  "properties": {
    "date:inception_lower": "2011-02-01",
    "date:inception_upper": "2011-02-01",
    "iso:country": "GB",
    "wof:name": "PA23 8FJ",
    "wof:placetype": "postalcode"
  },
  "geometry": {"coordinates":[-4.925259,55.950185],"type":"Point"}
}
