{
  "type": "Feature",
  "properties": {
    "iso:country":"GB",
    "wof:name":"SO22 4ET",
    "wof:placetype":"postalcode"
},
  "geometry": {"coordinates":[-1.34533245714436,51.04893905981536],"type":"Point"}
}