{
  "type": "Feature",
  "properties": {
    "iso:country": "GB",
    "wof:name": "SO22 4ET",
    "wof:placetype": "postalcode"
  },
  "geometry": {"coordinates":[-1.345332,51.048939],"type":"Point"}
}
