{
  "type": "Feature",
  "properties": {
    "date:inception_lower":"1980-01-01",
    "date:inception_upper":"1980-01-31",
    "iso:country":"GB",
    "wof:name":"SO22 4ET",
    "wof:placetype":"postalcode"
},
  "geometry": {"coordinates":[-1.345332,51.048939],"type":"Point"}
}