{
  "type": "Feature",
  "properties": {
    "iso:country": "GB",
    "wof:name": "PE8 4EA",
    "wof:placetype": "postalcode"
  },
  "geometry": {"coordinates":[-0.468576,52.48121],"type":"Point"}
}
