{
  "type": "Feature",
  "properties": {
    "date:inception_lower": "1998-06-01",
    "date:inception_upper": "1998-06-01",
    "iso:country": "GB",
    "wof:name": "YO25 6SE",
    "wof:placetype": "postalcode"
  },
  "geometry": {"coordinates":[-0.4451,53.997455],"type":"Point"}
}
