{
  "type": "Feature",
  "properties": {
    "iso:country":"GB",
    "wof:name":"B27 7UL",
    "wof:placetype":"postalcode"
},
  "geometry": {"coordinates":[-1.82927550512836,52.44541676870044],"type":"Point"}
}