{
  "type": "Feature",
  "properties": {
    "iso:country":"GB",
    "wof:name":"NE66 3BP",
    "wof:placetype":"postalcode"
},
  "geometry": {"coordinates":[-1.58073059996205,55.42165686312284],"type":"Point"}
}