{
  "type": "Feature",
  "properties": {
    "date:inception_lower":"1980-01-01",
    "date:inception_upper":"1980-01-31",
    "iso:country":"GB",
    "wof:name":"NE66 3BP",
    "wof:placetype":"postalcode"
},
  "geometry": {"coordinates":[-1.580731,55.421657],"type":"Point"}
}