{
  "type": "Feature",
  "properties": {
    "date:inception_lower": "2020-10-01",
    "date:inception_upper": "2020-10-01",
    "iso:country": "GB",
    "wof:name": "GU3 3EN",
    "wof:placetype": "postalcode"
  },
  "geometry": {"coordinates":[-0.600847,51.262462],"type":"Point"}
}
