{
  "type": "Feature",
  "properties": {
    "iso:country":"GB",
    "wof:name":"TF2 7BW",
    "wof:placetype":"postalcode"
},
  "geometry": {"coordinates":[-2.43849675313713,52.70580091454367],"type":"Point"}
}