{
  "type": "Feature",
  "properties": {
    "iso:country": "GB",
    "wof:name": "LN6 8BN",
    "wof:placetype": "postalcode"
  },
  "geometry": {"coordinates":[-0.572038,53.194588],"type":"Point"}
}
