{
  "type": "Feature",
  "properties": {
    "iso:country": "GB",
    "wof:name": "ME17 1PY",
    "wof:placetype": "postalcode"
  },
  "geometry": {"coordinates":[0.697412,51.262821],"type":"Point"}
}
