{
  "type": "Feature",
  "properties": {
    "iso:country":"GB",
    "wof:name":"DL11 6PH",
    "wof:placetype":"postalcode"
},
  "geometry": {"coordinates":[-2.01634811977116,54.38207411859944],"type":"Point"}
}