{
  "type": "Feature",
  "properties": {
    "iso:country": "GB",
    "wof:name": "DL11 6PH",
    "wof:placetype": "postalcode"
  },
  "geometry": {"coordinates":[-2.016348,54.382074],"type":"Point"}
}
