{
  "type": "Feature",
  "properties": {
    "iso:country":"GB",
    "wof:name":"HX6 4AP",
    "wof:placetype":"postalcode"
},
  "geometry": {"coordinates":[-1.93946744160197,53.67877999777478],"type":"Point"}
}