{
  "type": "Feature",
  "properties": {
    "date:inception_lower": "1980-01-01",
    "date:inception_upper": "1980-01-01",
    "iso:country": "GB",
    "wof:name": "TA8 1HU",
    "wof:placetype": "postalcode"
  },
  "geometry": {"coordinates":[-2.988628,51.232814],"type":"Point"}
}
