{
  "type": "Feature",
  "properties": {
    "iso:country": "GB",
    "wof:name": "TA8 1HU",
    "wof:placetype": "postalcode"
  },
  "geometry": {"coordinates":[-2.988628,51.232814],"type":"Point"}
}
