{
  "type": "Feature",
  "properties": {
    "iso:country":"GB",
    "wof:name":"NR25 7AG",
    "wof:placetype":"postalcode"
},
  "geometry": {"coordinates":[0.98189911082035,52.93374842619863],"type":"Point"}
}