{
  "type": "Feature",
  "properties": {
    "iso:country":"GB",
    "wof:name":"KA11 5AW",
    "wof:placetype":"postalcode"
},
  "geometry": {"coordinates":[-4.65052822482074,55.59789738724032],"type":"Point"}
}