{
  "type": "Feature",
  "properties": {
    "date:inception_lower": "1980-01-01",
    "date:inception_upper": "1980-01-01",
    "iso:country": "GB",
    "wof:name": "KA11 5AW",
    "wof:placetype": "postalcode"
  },
  "geometry": {"coordinates":[-4.650508,55.597896],"type":"Point"}
}
