{
  "type": "Feature",
  "properties": {
    "iso:country":"GB",
    "wof:name":"CV13 6HA",
    "wof:placetype":"postalcode"
},
  "geometry": {"coordinates":[-1.41492193906778,52.5720399808291],"type":"Point"}
}