{
  "type": "Feature",
  "properties": {
    "iso:country": "GB",
    "wof:name": "CV13 6HA",
    "wof:placetype": "postalcode"
  },
  "geometry": {"coordinates":[-1.414922,52.57204],"type":"Point"}
}
