{
  "type": "Feature",
  "properties": {
    "iso:country": "GB",
    "wof:name": "IP13 6AL",
    "wof:placetype": "postalcode"
  },
  "geometry": {"coordinates":[1.303213,52.122037],"type":"Point"}
}
