{
  "type": "Feature",
  "properties": {
    "iso:country":"GB",
    "wof:name":"OX17 1GY",
    "wof:placetype":"postalcode"
},
  "geometry": {"coordinates":[-1.3683735356568,52.08836419755217],"type":"Point"}
}