{
  "type": "Feature",
  "properties": {
    "date:inception_lower": "2010-08-01",
    "date:inception_upper": "2010-08-01",
    "iso:country": "GB",
    "wof:name": "OX17 1GY",
    "wof:placetype": "postalcode"
  },
  "geometry": {"coordinates":[-1.368373,52.088364],"type":"Point"}
}
