{
  "type": "Feature",
  "properties": {
    "date:inception_lower": "2022-05-01",
    "date:inception_upper": "2022-05-01",
    "iso:country": "GB",
    "wof:name": "DN36 4ZL",
    "wof:placetype": "postalcode"
  },
  "geometry": {"coordinates":[-0.051841,53.520938],"type":"Point"}
}
