{
  "type": "Feature",
  "properties": {
    "date:inception_lower": "2022-05-01",
    "date:inception_upper": "2022-05-01",
    "iso:country": "GB",
    "wof:name": "DN36 4ZL",
    "wof:placetype": "postalcode"
  },
  "geometry": {"coordinates":[-0.051142,53.521062],"type":"Point"}
}
