{
  "type": "Feature",
  "properties": {
    "iso:country":"GB",
    "wof:name":"WD25 7AD",
    "wof:placetype":"postalcode"
},
  "geometry": {"coordinates":[-0.41336364610135,51.68624515841993],"type":"Point"}
}