{
  "type": "Feature",
  "properties": {
    "iso:country": "GB",
    "wof:name": "SR4 9BW",
    "wof:placetype": "postalcode"
  },
  "geometry": {"coordinates":[-1.447982,54.894825],"type":"Point"}
}
