{
  "type": "Feature",
  "properties": {
    "iso:country":"GB",
    "wof:name":"EH18 1LQ",
    "wof:placetype":"postalcode"
},
  "geometry": {"coordinates":[-3.11648987903913,55.8809182988777],"type":"Point"}
}