{
  "type": "Feature",
  "properties": {
    "date:inception_lower":"2010-11-01",
    "date:inception_upper":"2010-11-30",
    "iso:country":"GB",
    "wof:name":"EH18 1LQ",
    "wof:placetype":"postalcode"
},
  "geometry": {"coordinates":[-3.11649,55.880918],"type":"Point"}
}