{
  "type": "Feature",
  "properties": {
    "iso:country": "GB",
    "wof:name": "EH18 1LQ",
    "wof:placetype": "postalcode"
  },
  "geometry": {"coordinates":[-3.11649,55.880918],"type":"Point"}
}
