{
  "type": "Feature",
  "properties": {
    "iso:country":"GB",
    "wof:name":"CT2 0QJ",
    "wof:placetype":"postalcode"
},
  "geometry": {"coordinates":[1.10640146670318,51.31255270262179],"type":"Point"}
}