{
  "type": "Feature",
  "properties": {
    "date:inception_lower": "2000-12-01",
    "date:inception_upper": "2000-12-01",
    "iso:country": "GB",
    "wof:name": "SN7 7YP",
    "wof:placetype": "postalcode"
  },
  "geometry": {"coordinates":[-1.580946,51.65257],"type":"Point"}
}
