{
  "type": "Feature",
  "properties": {
    "iso:country":"GB",
    "wof:name":"DD9 6DZ",
    "wof:placetype":"postalcode"
},
  "geometry": {"coordinates":[-2.65431858612305,56.73087498121977],"type":"Point"}
}