{
  "type": "Feature",
  "properties": {
    "iso:country": "GB",
    "wof:name": "DD9 6DZ",
    "wof:placetype": "postalcode"
  },
  "geometry": {"coordinates":[-2.654319,56.730875],"type":"Point"}
}
