{
  "type": "Feature",
  "properties": {
    "iso:country":"GB",
    "wof:name":"WS13 7QP",
    "wof:placetype":"postalcode"
},
  "geometry": {"coordinates":[-1.83982441049328,52.68880428014642],"type":"Point"}
}