{
  "type": "Feature",
  "properties": {
    "date:inception_lower": "2000-06-01",
    "date:inception_upper": "2000-06-01",
    "iso:country": "GB",
    "wof:name": "WS13 7QP",
    "wof:placetype": "postalcode"
  },
  "geometry": {"coordinates":[-1.839824,52.688804],"type":"Point"}
}
