{
  "type": "Feature",
  "properties": {
    "date:inception_lower": "2019-01-01",
    "date:inception_upper": "2019-01-01",
    "iso:country": "GB",
    "wof:name": "DL3 6DB",
    "wof:placetype": "postalcode"
  },
  "geometry": {"coordinates":[-1.554228,54.531357],"type":"Point"}
}
