{
  "type": "Feature",
  "properties": {
    "iso:country": "GB",
    "wof:name": "NG34 9TS",
    "wof:placetype": "postalcode"
  },
  "geometry": {"coordinates":[-0.304438,52.979777],"type":"Point"}
}
