{
  "type": "Feature",
  "properties": {
    "date:inception_lower":"1997-06-01",
    "date:inception_upper":"1997-06-30",
    "iso:country":"GB",
    "wof:name":"NG34 9TS",
    "wof:placetype":"postalcode"
},
  "geometry": {"coordinates":[-0.304438,52.979777],"type":"Point"}
}