{
  "type": "Feature",
  "properties": {
    "iso:country":"GB",
    "wof:name":"NG2 2LB",
    "wof:placetype":"postalcode"
},
  "geometry": {"coordinates":[-1.14123219679205,52.93730900433479],"type":"Point"}
}