{
  "type": "Feature",
  "properties": {
    "iso:country":"GB",
    "wof:name":"LS15 7SZ",
    "wof:placetype":"postalcode"
},
  "geometry": {"coordinates":[-1.46360261897057,53.79807257453913],"type":"Point"}
}