{
  "type": "Feature",
  "properties": {
    "iso:country":"GB",
    "wof:name":"HU10 7LA",
    "wof:placetype":"postalcode"
},
  "geometry": {"coordinates":[-0.45263244315337,53.74333009500805],"type":"Point"}
}