{
  "type": "Feature",
  "properties": {
    "iso:country": "GB",
    "wof:name": "HU10 7LA",
    "wof:placetype": "postalcode"
  },
  "geometry": {"coordinates":[-0.452632,53.74333],"type":"Point"}
}
