{
  "type": "Feature",
  "properties": {
    "iso:country":"GB",
    "wof:name":"SS6 7DF",
    "wof:placetype":"postalcode"
},
  "geometry": {"coordinates":[0.59959172563861,51.58369733952205],"type":"Point"}
}