{
  "type": "Feature",
  "properties": {
    "date:inception_lower": "2007-09-01",
    "date:inception_upper": "2007-09-01",
    "iso:country": "GB",
    "wof:name": "MK41 0GE",
    "wof:placetype": "postalcode"
  },
  "geometry": {"coordinates":[-0.422312,52.155558],"type":"Point"}
}
