{
  "type": "Feature",
  "properties": {
    "iso:country":"GB",
    "wof:name":"MK41 0GE",
    "wof:placetype":"postalcode"
},
  "geometry": {"coordinates":[-0.42231251607561,52.15555781023567],"type":"Point"}
}