{
  "type": "Feature",
  "properties": {
    "iso:country": "GB",
    "wof:name": "IV2 5BA",
    "wof:placetype": "postalcode"
  },
  "geometry": {"coordinates":[-4.178251,57.469444],"type":"Point"}
}
