{
  "type": "Feature",
  "properties": {
    "date:inception_lower": "1998-12-01",
    "date:inception_upper": "1998-12-01",
    "iso:country": "GB",
    "wof:name": "IV2 5BA",
    "wof:placetype": "postalcode"
  },
  "geometry": {"coordinates":[-4.178251,57.469444],"type":"Point"}
}
