{
  "type": "Feature",
  "properties": {
    "date:inception_lower": "2021-07-01",
    "date:inception_upper": "2021-07-01",
    "iso:country": "GB",
    "wof:name": "UB6 8GN",
    "wof:placetype": "postalcode"
  },
  "geometry": {"coordinates":[-0.324981,51.533178],"type":"Point"}
}
