{
  "type": "Feature",
  "properties": {
    "date:inception_lower": "1981-06-01",
    "date:inception_upper": "1981-06-01",
    "iso:country": "GB",
    "wof:name": "PE33 0NL",
    "wof:placetype": "postalcode"
  },
  "geometry": {"coordinates":[0.413206,52.711427],"type":"Point"}
}
