{
  "type": "Feature",
  "properties": {
    "iso:country":"GB",
    "wof:name":"PE33 0NL",
    "wof:placetype":"postalcode"
},
  "geometry": {"coordinates":[0.4132056104575,52.71142721341741],"type":"Point"}
}