{
  "type": "Feature",
  "properties": {
    "iso:country":"GB",
    "wof:name":"SW6 7RA",
    "wof:placetype":"postalcode"
},
  "geometry": {"coordinates":[-0.21144125020085,51.4810526889274],"type":"Point"}
}