{
  "type": "Feature",
  "properties": {
    "iso:country": "GB",
    "wof:name": "RG14 6TL",
    "wof:placetype": "postalcode"
  },
  "geometry": {"coordinates":[-1.34823,51.379312],"type":"Point"}
}
