{
  "type": "Feature",
  "properties": {
    "iso:country":"GB",
    "wof:name":"RG22 5EE",
    "wof:placetype":"postalcode"
},
  "geometry": {"coordinates":[-1.13050641316954,51.26243478516362],"type":"Point"}
}