{
  "type": "Feature",
  "properties": {
    "date:inception_lower": "1991-09-01",
    "date:inception_upper": "1991-09-01",
    "iso:country": "GB",
    "wof:name": "GU20 6QG",
    "wof:placetype": "postalcode"
  },
  "geometry": {"coordinates":[-0.65956,51.364342],"type":"Point"}
}
