{
  "type": "Feature",
  "properties": {
    "iso:country":"GB",
    "wof:name":"GU20 6QG",
    "wof:placetype":"postalcode"
},
  "geometry": {"coordinates":[-0.65956037616057,51.36434225701971],"type":"Point"}
}