{
  "type": "Feature",
  "properties": {
    "iso:country": "GB",
    "wof:name": "NE65 0GR",
    "wof:placetype": "postalcode"
  },
  "geometry": {"coordinates":[-1.586678,55.326998],"type":"Point"}
}
