{
  "type": "Feature",
  "properties": {
    "iso:country":"GB",
    "wof:name":"TN38 0YQ",
    "wof:placetype":"postalcode"
},
  "geometry": {"coordinates":[0.53944589915116,50.85617569450284],"type":"Point"}
}