{
  "type": "Feature",
  "properties": {
    "date:inception_lower":"1985-10-01",
    "date:inception_upper":"1985-10-31",
    "iso:country":"GB",
    "wof:name":"TN38 0YQ",
    "wof:placetype":"postalcode"
},
  "geometry": {"coordinates":[0.539446,50.856176],"type":"Point"}
}