{
  "type": "Feature",
  "properties": {
    "iso:country":"GB",
    "wof:name":"BA14 6ND",
    "wof:placetype":"postalcode"
},
  "geometry": {"coordinates":[-2.1126311588641,51.32273200260687],"type":"Point"}
}