{
  "type": "Feature",
  "properties": {
    "date:inception_lower": "2008-01-01",
    "date:inception_upper": "2008-01-01",
    "iso:country": "GB",
    "wof:name": "NP7 0LE",
    "wof:placetype": "postalcode"
  },
  "geometry": {"coordinates":[-3.130445,51.804269],"type":"Point"}
}
