{
  "type": "Feature",
  "properties": {
    "iso:country": "GB",
    "wof:name": "YO26 8BX",
    "wof:placetype": "postalcode"
  },
  "geometry": {"coordinates":[-1.29565,53.993573],"type":"Point"}
}
