{
  "type": "Feature",
  "properties": {
    "date:inception_lower":"1998-06-01",
    "date:inception_upper":"1998-06-30",
    "iso:country":"GB",
    "wof:name":"YO26 8BX",
    "wof:placetype":"postalcode"
},
  "geometry": {"coordinates":[-1.29565,53.993573],"type":"Point"}
}