{
  "type": "Feature",
  "properties": {
    "iso:country":"GB",
    "wof:name":"HD1 3JR",
    "wof:placetype":"postalcode"
},
  "geometry": {"coordinates":[-1.79762627167312,53.63868115835424],"type":"Point"}
}