{
  "type": "Feature",
  "properties": {
    "iso:country": "GB",
    "wof:name": "HD1 3JR",
    "wof:placetype": "postalcode"
  },
  "geometry": {"coordinates":[-1.797627,53.638705],"type":"Point"}
}
