{
  "type": "Feature",
  "properties": {
    "iso:country":"GB",
    "wof:name":"NE24 4EB",
    "wof:placetype":"postalcode"
},
  "geometry": {"coordinates":[-1.54459439111057,55.12205634244391],"type":"Point"}
}