{
  "type": "Feature",
  "properties": {
    "iso:country":"GB",
    "wof:name":"BR6 6HP",
    "wof:placetype":"postalcode"
},
  "geometry": {"coordinates":[0.10978607490191,51.35339954071603],"type":"Point"}
}