{
  "type": "Feature",
  "properties": {
    "date:inception_lower": "1980-01-01",
    "date:inception_upper": "1980-01-01",
    "iso:country": "GB",
    "wof:name": "BR6 6HP",
    "wof:placetype": "postalcode"
  },
  "geometry": {"coordinates":[0.109786,51.3534],"type":"Point"}
}
