{
  "type": "Feature",
  "properties": {
    "iso:country":"GB",
    "wof:name":"DL13 3LT",
    "wof:placetype":"postalcode"
},
  "geometry": {"coordinates":[-1.89894622886977,54.74714024845311],"type":"Point"}
}