{
  "type": "Feature",
  "properties": {
    "iso:country": "GB",
    "wof:name": "DL13 3LT",
    "wof:placetype": "postalcode"
  },
  "geometry": {"coordinates":[-1.898946,54.74714],"type":"Point"}
}
