{
  "type": "Feature",
  "properties": {
    "iso:country": "GB",
    "wof:name": "NG15 8EU",
    "wof:placetype": "postalcode"
  },
  "geometry": {"coordinates":[-1.197491,53.041027],"type":"Point"}
}
