{
  "type": "Feature",
  "properties": {
    "iso:country":"GB",
    "wof:name":"NN7 2HW",
    "wof:placetype":"postalcode"
},
  "geometry": {"coordinates":[-0.85554328623821,52.14693515295033],"type":"Point"}
}