{
  "type": "Feature",
  "properties": {
    "iso:country": "GB",
    "wof:name": "NN7 2HW",
    "wof:placetype": "postalcode"
  },
  "geometry": {"coordinates":[-0.855543,52.146935],"type":"Point"}
}
