{
  "type": "Feature",
  "properties": {
    "iso:country": "GB",
    "wof:name": "NE30 2HB",
    "wof:placetype": "postalcode"
  },
  "geometry": {"coordinates":[-1.439005,55.016629],"type":"Point"}
}
