{
  "type": "Feature",
  "properties": {
    "iso:country":"GB",
    "wof:name":"LL23 7BY",
    "wof:placetype":"postalcode"
},
  "geometry": {"coordinates":[-3.63192784217633,52.87118552066397],"type":"Point"}
}