{
  "type": "Feature",
  "properties": {
    "date:inception_lower": "1980-01-01",
    "date:inception_upper": "1980-01-01",
    "iso:country": "GB",
    "wof:name": "CH1 1HA",
    "wof:placetype": "postalcode"
  },
  "geometry": {"coordinates":[-2.886918,53.191045],"type":"Point"}
}
