{
  "type": "Feature",
  "properties": {
    "date:inception_lower": "1980-01-01",
    "date:inception_upper": "1980-01-01",
    "iso:country": "GB",
    "wof:name": "DY10 3EJ",
    "wof:placetype": "postalcode"
  },
  "geometry": {"coordinates":[-2.2238,52.382972],"type":"Point"}
}
