{
  "type": "Feature",
  "properties": {
    "iso:country":"GB",
    "wof:name":"NP15 2HL",
    "wof:placetype":"postalcode"
},
  "geometry": {"coordinates":[-2.85807224728824,51.76238012158029],"type":"Point"}
}