{
  "type": "Feature",
  "properties": {
    "iso:country":"GB",
    "wof:name":"DY13 0JS",
    "wof:placetype":"postalcode"
},
  "geometry": {"coordinates":[-2.29356250475425,52.32402359279065],"type":"Point"}
}