{
  "type": "Feature",
  "properties": {
    "iso:country":"GB",
    "wof:name":"E18 2FQ",
    "wof:placetype":"postalcode"
},
  "geometry": {"coordinates":[0.02598742746557,51.59691906084732],"type":"Point"}
}