{
  "type": "Feature",
  "properties": {
    "iso:country": "GB",
    "wof:name": "E18 2FQ",
    "wof:placetype": "postalcode"
  },
  "geometry": {"coordinates":[0.025987,51.596919],"type":"Point"}
}
