{
  "type": "Feature",
  "properties": {
    "iso:country": "GB",
    "wof:name": "IV36 1HE",
    "wof:placetype": "postalcode"
  },
  "geometry": {"coordinates":[-3.63056,57.605099],"type":"Point"}
}
