{
  "type": "Feature",
  "properties": {
    "iso:country":"GB",
    "wof:name":"CT5 4EJ",
    "wof:placetype":"postalcode"
},
  "geometry": {"coordinates":[1.00970266522893,51.34789135179813],"type":"Point"}
}