{
  "type": "Feature",
  "properties": {
    "iso:country": "GB",
    "wof:name": "EX16 7PX",
    "wof:placetype": "postalcode"
  },
  "geometry": {"coordinates":[-3.454017,50.938485],"type":"Point"}
}
