{
  "type": "Feature",
  "properties": {
    "iso:country":"GB",
    "wof:name":"LD1 6UN",
    "wof:placetype":"postalcode"
},
  "geometry": {"coordinates":[-3.29361386546859,52.37099583176052],"type":"Point"}
}