{
  "type": "Feature",
  "properties": {
    "iso:country": "GB",
    "wof:name": "LD1 6UN",
    "wof:placetype": "postalcode"
  },
  "geometry": {"coordinates":[-3.299442,52.379792],"type":"Point"}
}
