{
  "type": "Feature",
  "properties": {
    "iso:country":"GB",
    "wof:name":"SL3 9PF",
    "wof:placetype":"postalcode"
},
  "geometry": {"coordinates":[-0.5326315967138,51.47136679557976],"type":"Point"}
}