{
  "type": "Feature",
  "properties": {
    "date:inception_lower":"1990-07-01",
    "date:inception_upper":"1990-07-31",
    "iso:country":"GB",
    "wof:name":"SA14 8QF",
    "wof:placetype":"postalcode"
},
  "geometry": {"coordinates":[-4.134758,51.691895],"type":"Point"}
}