{
  "type": "Feature",
  "properties": {
    "iso:country":"GB",
    "wof:name":"SA14 8QF",
    "wof:placetype":"postalcode"
},
  "geometry": {"coordinates":[-4.13475761696789,51.69189528828328],"type":"Point"}
}