{
  "type": "Feature",
  "properties": {
    "iso:country": "GB",
    "wof:name": "DD2 5PX",
    "wof:placetype": "postalcode"
  },
  "geometry": {"coordinates":[-3.054194,56.496633],"type":"Point"}
}
