{
  "type": "Feature",
  "properties": {
    "iso:country":"GB",
    "wof:name":"DD2 5PX",
    "wof:placetype":"postalcode"
},
  "geometry": {"coordinates":[-3.0541944405188,56.49663320907849],"type":"Point"}
}