{
  "type": "Feature",
  "properties": {
    "date:inception_lower": "2019-07-01",
    "date:inception_upper": "2019-07-01",
    "iso:country": "GB",
    "wof:name": "MK17 7AF",
    "wof:placetype": "postalcode"
  },
  "geometry": {"coordinates":[-0.64879,52.035453],"type":"Point"}
}
