{
  "type": "Feature",
  "properties": {
    "date:inception_lower": "2018-11-01",
    "date:inception_upper": "2018-11-01",
    "iso:country": "GB",
    "wof:name": "CB25 9AR",
    "wof:placetype": "postalcode"
  },
  "geometry": {"coordinates":[0.236013,52.220794],"type":"Point"}
}
