{
  "type": "Feature",
  "properties": {
    "iso:country":"GB",
    "wof:name":"CB25 9AR",
    "wof:placetype":"postalcode"
},
  "geometry": {"coordinates":[0.23635107535403,52.22051223717789],"type":"Point"}
}