{
  "type": "Feature",
  "properties": {
    "iso:country":"GB",
    "wof:name":"OX4 2NZ",
    "wof:placetype":"postalcode"
},
  "geometry": {"coordinates":[-1.21454240902797,51.73903761241043],"type":"Point"}
}