{
  "type": "Feature",
  "properties": {
    "date:inception_lower": "1980-01-01",
    "date:inception_upper": "1980-01-01",
    "iso:country": "GB",
    "wof:name": "G69 8BQ",
    "wof:placetype": "postalcode"
  },
  "geometry": {"coordinates":[-4.089795,55.896719],"type":"Point"}
}
