{
  "type": "Feature",
  "properties": {
    "iso:country":"GB",
    "wof:name":"G69 8BQ",
    "wof:placetype":"postalcode"
},
  "geometry": {"coordinates":[-4.08979468654255,55.89671851292029],"type":"Point"}
}