{
  "type": "Feature",
  "properties": {
    "iso:country":"GB",
    "wof:name":"LL18 1NW",
    "wof:placetype":"postalcode"
},
  "geometry": {"coordinates":[-3.50232359812256,53.31563899434799],"type":"Point"}
}