{
  "type": "Feature",
  "properties": {
    "iso:country":"GB",
    "wof:name":"SG1 3LQ",
    "wof:placetype":"postalcode"
},
  "geometry": {"coordinates":[-0.19251172272279,51.90865606759282],"type":"Point"}
}