{
  "type": "Feature",
  "properties": {
    "iso:country":"GB",
    "wof:name":"NW1 4HN",
    "wof:placetype":"postalcode"
},
  "geometry": {"coordinates":[-0.14535387956731,51.53138226492711],"type":"Point"}
}