{
  "type": "Feature",
  "properties": {
    "date:inception_lower": "1980-01-01",
    "date:inception_upper": "1980-01-01",
    "iso:country": "GB",
    "wof:name": "NW1 4HN",
    "wof:placetype": "postalcode"
  },
  "geometry": {"coordinates":[-0.145354,51.531382],"type":"Point"}
}
