{
  "type": "Feature",
  "properties": {
    "iso:country":"GB",
    "wof:name":"LL11 5BY",
    "wof:placetype":"postalcode"
},
  "geometry": {"coordinates":[-3.05428402649426,53.07648972876714],"type":"Point"}
}