{
  "type": "Feature",
  "properties": {
    "iso:country":"GB",
    "wof:name":"EH52 5AG",
    "wof:placetype":"postalcode"
},
  "geometry": {"coordinates":[-3.46934691631,55.93467638280001],"type":"Point"}
}