{
  "type": "Feature",
  "properties": {
    "iso:country":"GB",
    "wof:name":"PE19 5JE",
    "wof:placetype":"postalcode"
},
  "geometry": {"coordinates":[-0.32916312286016,52.22701506827456],"type":"Point"}
}