{
  "type": "Feature",
  "properties": {
    "iso:country":"GB",
    "wof:name":"HP27 0LE",
    "wof:placetype":"postalcode"
},
  "geometry": {"coordinates":[-0.81410710640353,51.71497238315189],"type":"Point"}
}