{
  "type": "Feature",
  "properties": {
    "date:inception_lower":"1992-08-01",
    "date:inception_upper":"1992-08-31",
    "iso:country":"GB",
    "wof:name":"HP27 0LE",
    "wof:placetype":"postalcode"
},
  "geometry": {"coordinates":[-0.814107,51.714972],"type":"Point"}
}