{
  "type": "Feature",
  "properties": {
    "iso:country": "GB",
    "wof:name": "HP27 0LE",
    "wof:placetype": "postalcode"
  },
  "geometry": {"coordinates":[-0.814107,51.714972],"type":"Point"}
}
