{
  "type": "Feature",
  "properties": {
    "date:inception_lower": "2012-07-01",
    "date:inception_upper": "2012-07-01",
    "iso:country": "GB",
    "wof:name": "LL16 5DB",
    "wof:placetype": "postalcode"
  },
  "geometry": {"coordinates":[-3.460755,53.203426],"type":"Point"}
}
