{
  "type": "Feature",
  "properties": {
    "iso:country":"GB",
    "wof:name":"LL16 5DB",
    "wof:placetype":"postalcode"
},
  "geometry": {"coordinates":[-3.46075484011571,53.20342582543343],"type":"Point"}
}