{
  "type": "Feature",
  "properties": {
    "iso:country":"GB",
    "wof:name":"SO31 6LD",
    "wof:placetype":"postalcode"
},
  "geometry": {"coordinates":[-1.26935147874849,50.87004276353024],"type":"Point"}
}