{
  "type": "Feature",
  "properties": {
    "iso:country":"GB",
    "wof:name":"NE65 7LP",
    "wof:placetype":"postalcode"
},
  "geometry": {"coordinates":[-1.96007642801726,55.31618499672233],"type":"Point"}
}