{
  "type": "Feature",
  "properties": {
    "iso:country": "GB",
    "wof:name": "NE65 7LP",
    "wof:placetype": "postalcode"
  },
  "geometry": {"coordinates":[-1.960076,55.316185],"type":"Point"}
}
