{
  "type": "Feature",
  "properties": {
    "iso:country":"GB",
    "wof:name":"OX2 7HN",
    "wof:placetype":"postalcode"
},
  "geometry": {"coordinates":[-1.26535490388871,51.77781263267928],"type":"Point"}
}