{
  "type": "Feature",
  "properties": {
    "iso:country": "GB",
    "wof:name": "SO50 8GE",
    "wof:placetype": "postalcode"
  },
  "geometry": {"coordinates":[-1.304952,50.969494],"type":"Point"}
}
