{
  "type": "Feature",
  "properties": {
    "date:inception_lower": "1980-01-01",
    "date:inception_upper": "1980-01-01",
    "iso:country": "GB",
    "wof:name": "S13 9QS",
    "wof:placetype": "postalcode"
  },
  "geometry": {"coordinates":[-1.370618,53.36739],"type":"Point"}
}
