{
  "type": "Feature",
  "properties": {
    "date:inception_lower": "1980-01-01",
    "date:inception_upper": "1980-01-01",
    "iso:country": "GB",
    "wof:name": "S70 6PP",
    "wof:placetype": "postalcode"
  },
  "geometry": {"coordinates":[-1.510364,53.551132],"type":"Point"}
}
