{
  "type": "Feature",
  "properties": {
    "iso:country":"GB",
    "wof:name":"M24 2NJ",
    "wof:placetype":"postalcode"
},
  "geometry": {"coordinates":[-2.17509031084367,53.55870977357008],"type":"Point"}
}