{
  "type": "Feature",
  "properties": {
    "iso:country":"GB",
    "wof:name":"BB4 8LW",
    "wof:placetype":"postalcode"
},
  "geometry": {"coordinates":[-2.29115419070511,53.71753906009653],"type":"Point"}
}