{
  "type": "Feature",
  "properties": {
    "date:inception_lower": "1980-01-01",
    "date:inception_upper": "1980-01-01",
    "iso:country": "GB",
    "wof:name": "BB4 8LW",
    "wof:placetype": "postalcode"
  },
  "geometry": {"coordinates":[-2.291154,53.717539],"type":"Point"}
}
