{
  "type": "Feature",
  "properties": {
    "iso:country":"GB",
    "wof:name":"CV12 0QE",
    "wof:placetype":"postalcode"
},
  "geometry": {"coordinates":[-1.50535643034625,52.47877653338539],"type":"Point"}
}