{
  "type": "Feature",
  "properties": {
    "iso:country":"GB",
    "wof:name":"RH8 0RY",
    "wof:placetype":"postalcode"
},
  "geometry": {"coordinates":[0.01363358344961,51.23839010321396],"type":"Point"}
}