{
  "type": "Feature",
  "properties": {
    "iso:country":"GB",
    "wof:name":"SA1 6NR",
    "wof:placetype":"postalcode"
},
  "geometry": {"coordinates":[-3.9659753564951,51.62510613665304],"type":"Point"}
}