{
  "type": "Feature",
  "properties": {
    "iso:country":"GB",
    "wof:name":"PO9 2RX",
    "wof:placetype":"postalcode"
},
  "geometry": {"coordinates":[-0.96587458526645,50.85294709100887],"type":"Point"}
}