{
  "type": "Feature",
  "properties": {
    "iso:country":"GB",
    "wof:name":"PE37 8JB",
    "wof:placetype":"postalcode"
},
  "geometry": {"coordinates":[0.80380190770614,52.65000745789567],"type":"Point"}
}