{
  "type": "Feature",
  "properties": {
    "iso:country":"GB",
    "wof:name":"SK3 8RH",
    "wof:placetype":"postalcode"
},
  "geometry": {"coordinates":[-2.16407073400508,53.38724363596548],"type":"Point"}
}