{
  "type": "Feature",
  "properties": {
    "iso:country": "GB",
    "wof:name": "RH17 7AD",
    "wof:placetype": "postalcode"
  },
  "geometry": {"coordinates":[-0.027216,51.037037],"type":"Point"}
}
