{
  "type": "Feature",
  "properties": {
    "date:inception_lower": "2018-05-01",
    "date:inception_upper": "2018-05-01",
    "iso:country": "GB",
    "wof:name": "NP7 8AL",
    "wof:placetype": "postalcode"
  },
  "geometry": {"coordinates":[-2.877377,51.857208],"type":"Point"}
}
