{
  "type": "Feature",
  "properties": {
    "date:inception_lower": "1980-01-01",
    "date:inception_upper": "1980-01-01",
    "iso:country": "GB",
    "wof:name": "SW16 6DB",
    "wof:placetype": "postalcode"
  },
  "geometry": {"coordinates":[-0.139078,51.4225],"type":"Point"}
}
