{
  "type": "Feature",
  "properties": {
    "iso:country":"GB",
    "wof:name":"KT8 9EW",
    "wof:placetype":"postalcode"
},
  "geometry": {"coordinates":[-0.35314273471736,51.40333897263109],"type":"Point"}
}