{
  "type": "Feature",
  "properties": {
    "date:inception_lower": "1980-01-01",
    "date:inception_upper": "1980-01-01",
    "iso:country": "GB",
    "wof:name": "KT8 9EW",
    "wof:placetype": "postalcode"
  },
  "geometry": {"coordinates":[-0.353143,51.403339],"type":"Point"}
}
