{
  "type": "Feature",
  "properties": {
    "date:inception_lower":"1980-01-01",
    "date:inception_upper":"1980-01-31",
    "iso:country":"GB",
    "wof:name":"ST15 8RR",
    "wof:placetype":"postalcode"
},
  "geometry": {"coordinates":[-2.102598,52.933255],"type":"Point"}
}