{
  "type": "Feature",
  "properties": {
    "iso:country":"GB",
    "wof:name":"ST15 8RR",
    "wof:placetype":"postalcode"
},
  "geometry": {"coordinates":[-2.10259807034945,52.93325485960722],"type":"Point"}
}