{
  "type": "Feature",
  "properties": {
    "iso:country":"GB",
    "wof:name":"SO53 2ET",
    "wof:placetype":"postalcode"
},
  "geometry": {"coordinates":[-1.38269016838769,50.98700534262879],"type":"Point"}
}