{
  "type": "Feature",
  "properties": {
    "iso:country":"GB",
    "wof:name":"BR1 1BW",
    "wof:placetype":"postalcode"
},
  "geometry": {"coordinates":[0.01616526601744,51.39899669995949],"type":"Point"}
}