{
  "type": "Feature",
  "properties": {
    "iso:country": "GB",
    "wof:name": "DA11 7PA",
    "wof:placetype": "postalcode"
  },
  "geometry": {"coordinates":[0.365153,51.416663],"type":"Point"}
}
