{
  "type": "Feature",
  "properties": {
    "iso:country":"GB",
    "wof:name":"BD7 4AT",
    "wof:placetype":"postalcode"
},
  "geometry": {"coordinates":[-1.80579570758275,53.77657222902261],"type":"Point"}
}