{
  "type": "Feature",
  "properties": {
    "iso:country": "GB",
    "wof:name": "AB51 5GG",
    "wof:placetype": "postalcode"
  },
  "geometry": {"coordinates":[-2.448889,57.239964],"type":"Point"}
}
