{
  "type": "Feature",
  "properties": {
    "iso:country":"GB",
    "wof:name":"AB51 5GG",
    "wof:placetype":"postalcode"
},
  "geometry": {"coordinates":[-2.44888922336724,57.23996373307941],"type":"Point"}
}