{
  "type": "Feature",
  "properties": {
    "iso:country":"GB",
    "wof:name":"GL7 1EF",
    "wof:placetype":"postalcode"
},
  "geometry": {"coordinates":[-1.96438975148924,51.71398945940632],"type":"Point"}
}