{
  "type": "Feature",
  "properties": {
    "date:inception_lower": "1980-01-01",
    "date:inception_upper": "1980-01-01",
    "iso:country": "GB",
    "wof:name": "GL7 1EF",
    "wof:placetype": "postalcode"
  },
  "geometry": {"coordinates":[-1.96439,51.713989],"type":"Point"}
}
