{
  "type": "Feature",
  "properties": {
    "iso:country": "GB",
    "wof:name": "LN11 7AA",
    "wof:placetype": "postalcode"
  },
  "geometry": {"coordinates":[0.006783,53.370454],"type":"Point"}
}
