{
  "type": "Feature",
  "properties": {
    "iso:country":"GB",
    "wof:name":"NR8 6JW",
    "wof:placetype":"postalcode"
},
  "geometry": {"coordinates":[1.14964276131256,52.6878532621811],"type":"Point"}
}