{
  "type": "Feature",
  "properties": {
    "date:inception_lower": "1980-01-01",
    "date:inception_upper": "1980-01-01",
    "iso:country": "GB",
    "wof:name": "NR8 6JW",
    "wof:placetype": "postalcode"
  },
  "geometry": {"coordinates":[1.149664,52.68786],"type":"Point"}
}
