{
  "type": "Feature",
  "properties": {
    "iso:country":"GB",
    "wof:name":"SO53 2NN",
    "wof:placetype":"postalcode"
},
  "geometry": {"coordinates":[-1.37775754242154,50.98084638827687],"type":"Point"}
}