{
  "type": "Feature",
  "properties": {
    "iso:country":"GB",
    "wof:name":"OX9 2HA",
    "wof:placetype":"postalcode"
},
  "geometry": {"coordinates":[-1.01884739039915,51.74811412285189],"type":"Point"}
}