{
  "type": "Feature",
  "properties": {
    "iso:country": "GB",
    "wof:name": "OX9 2HA",
    "wof:placetype": "postalcode"
  },
  "geometry": {"coordinates":[-1.018906,51.748471],"type":"Point"}
}
