{
  "type": "Feature",
  "properties": {
    "iso:country":"GB",
    "wof:name":"KT3 6HT",
    "wof:placetype":"postalcode"
},
  "geometry": {"coordinates":[-0.2364025779716,51.39878966626969],"type":"Point"}
}