{
  "type": "Feature",
  "properties": {
    "date:inception_lower":"2002-10-01",
    "date:inception_upper":"2002-10-31",
    "iso:country":"GB",
    "wof:name":"LE10 1RW",
    "wof:placetype":"postalcode"
},
  "geometry": {"coordinates":[-1.373355,52.545253],"type":"Point"}
}