{
  "type": "Feature",
  "properties": {
    "iso:country":"GB",
    "wof:name":"WA3 4DF",
    "wof:placetype":"postalcode"
},
  "geometry": {"coordinates":[-2.5269286699694,53.45617833469895],"type":"Point"}
}