{
  "type": "Feature",
  "properties": {
    "iso:country":"GB",
    "wof:name":"IV2 4HW",
    "wof:placetype":"postalcode"
},
  "geometry": {"coordinates":[-4.21337546210304,57.46150737212093],"type":"Point"}
}