{
  "type": "Feature",
  "properties": {
    "iso:country":"GB",
    "wof:name":"W1J 8PE",
    "wof:placetype":"postalcode"
},
  "geometry": {"coordinates":[-0.14463561706564,51.50790949250442],"type":"Point"}
}