{
  "type": "Feature",
  "properties": {
    "iso:country":"GB",
    "wof:name":"BS48 2QH",
    "wof:placetype":"postalcode"
},
  "geometry": {"coordinates":[-2.76430668336,51.42608891763187],"type":"Point"}
}