{
  "type": "Feature",
  "properties": {
    "iso:country":"GB",
    "wof:name":"BS14 8SL",
    "wof:placetype":"postalcode"
},
  "geometry": {"coordinates":[-2.54563954000607,51.40912999483061],"type":"Point"}
}