{
  "type": "Feature",
  "properties": {
    "date:inception_lower": "2012-02-01",
    "date:inception_upper": "2012-02-01",
    "iso:country": "GB",
    "wof:name": "SE15 4BG",
    "wof:placetype": "postalcode"
  },
  "geometry": {"coordinates":[-0.067712,51.468062],"type":"Point"}
}
