{
  "type": "Feature",
  "properties": {
    "iso:country":"GB",
    "wof:name":"SE15 4BG",
    "wof:placetype":"postalcode"
},
  "geometry": {"coordinates":[-0.06771224791456,51.46806200294345],"type":"Point"}
}