{
  "type": "Feature",
  "properties": {
    "iso:country":"GB",
    "wof:name":"IP2 9QJ",
    "wof:placetype":"postalcode"
},
  "geometry": {"coordinates":[1.11537327195222,52.03978780447114],"type":"Point"}
}