{
  "type": "Feature",
  "properties": {
    "iso:country":"GB",
    "wof:name":"IP20 0JH",
    "wof:placetype":"postalcode"
},
  "geometry": {"coordinates":[1.32242794225784,52.38285594961258],"type":"Point"}
}