{
  "type": "Feature",
  "properties": {
    "date:inception_lower":"1980-01-01",
    "date:inception_upper":"1980-01-31",
    "iso:country":"GB",
    "wof:name":"IP20 0JH",
    "wof:placetype":"postalcode"
},
  "geometry": {"coordinates":[1.322414,52.382887],"type":"Point"}
}