{
  "type": "Feature",
  "properties": {
    "date:inception_lower":"1980-01-01",
    "date:inception_upper":"1980-01-31",
    "iso:country":"GB",
    "wof:name":"NR13 5EQ",
    "wof:placetype":"postalcode"
},
  "geometry": {"coordinates":[1.38408,52.644817],"type":"Point"}
}