{
  "type": "Feature",
  "properties": {
    "iso:country":"GB",
    "wof:name":"NR13 5EQ",
    "wof:placetype":"postalcode"
},
  "geometry": {"coordinates":[1.38407995814737,52.64481744620405],"type":"Point"}
}