{
  "type": "Feature",
  "properties": {
    "iso:country":"GB",
    "wof:name":"IV30 1QX",
    "wof:placetype":"postalcode"
},
  "geometry": {"coordinates":[-3.30846576866955,57.64665590765449],"type":"Point"}
}