{
  "type": "Feature",
  "properties": {
    "iso:country":"GB",
    "wof:name":"EH41 3NS",
    "wof:placetype":"postalcode"
},
  "geometry": {"coordinates":[-2.78032405435492,55.95584772892305],"type":"Point"}
}