{
  "type": "Feature",
  "properties": {
    "date:inception_lower": "1980-01-01",
    "date:inception_upper": "1980-01-01",
    "iso:country": "GB",
    "wof:name": "LA23 3NL",
    "wof:placetype": "postalcode"
  },
  "geometry": {"coordinates":[-2.898341,54.343527],"type":"Point"}
}
