{
  "type": "Feature",
  "properties": {
    "date:inception_lower": "1980-01-01",
    "date:inception_upper": "1980-01-01",
    "iso:country": "GB",
    "wof:name": "DL5 4AR",
    "wof:placetype": "postalcode"
  },
  "geometry": {"coordinates":[-1.55963,54.625809],"type":"Point"}
}
