{
  "type": "Feature",
  "properties": {
    "iso:country":"GB",
    "wof:name":"SL0 9ET",
    "wof:placetype":"postalcode"
},
  "geometry": {"coordinates":[-0.50889354170576,51.50655042964404],"type":"Point"}
}