{
  "type": "Feature",
  "properties": {
    "iso:country":"GB",
    "wof:name":"M12 6AN",
    "wof:placetype":"postalcode"
},
  "geometry": {"coordinates":[-2.22292541276628,53.46895277443311],"type":"Point"}
}