{
  "type": "Feature",
  "properties": {
    "date:inception_lower": "1992-08-01",
    "date:inception_upper": "1992-08-01",
    "iso:country": "GB",
    "wof:name": "PO33 1HB",
    "wof:placetype": "postalcode"
  },
  "geometry": {"coordinates":[-1.157625,50.720017],"type":"Point"}
}
