{
  "type": "Feature",
  "properties": {
    "date:inception_lower":"1992-08-01",
    "date:inception_upper":"1992-08-31",
    "iso:country":"GB",
    "wof:name":"PO33 1HB",
    "wof:placetype":"postalcode"
},
  "geometry": {"coordinates":[-1.15765,50.720029],"type":"Point"}
}