{
  "type": "Feature",
  "properties": {
    "iso:country":"GB",
    "wof:name":"PO33 1HB",
    "wof:placetype":"postalcode"
},
  "geometry": {"coordinates":[-1.15764995695452,50.72002868053076],"type":"Point"}
}