{
  "type": "Feature",
  "properties": {
    "iso:country":"GB",
    "wof:name":"RH17 5PX",
    "wof:placetype":"postalcode"
},
  "geometry": {"coordinates":[-0.19651640873158,50.99468084493507],"type":"Point"}
}