{
  "type": "Feature",
  "properties": {
    "iso:country": "GB",
    "wof:name": "RH17 5PX",
    "wof:placetype": "postalcode"
  },
  "geometry": {"coordinates":[-0.196516,50.994681],"type":"Point"}
}
