{
  "type": "Feature",
  "properties": {
    "iso:country": "GB",
    "wof:name": "CV2 4WA",
    "wof:placetype": "postalcode"
  },
  "geometry": {"coordinates":[-1.489751,52.416687],"type":"Point"}
}
