{
  "type": "Feature",
  "properties": {
    "date:inception_lower": "1995-01-01",
    "date:inception_upper": "1995-01-01",
    "iso:country": "GB",
    "wof:name": "CV2 4WA",
    "wof:placetype": "postalcode"
  },
  "geometry": {"coordinates":[-1.489563,52.416452],"type":"Point"}
}
