{
  "type": "Feature",
  "properties": {
    "iso:country":"GB",
    "wof:name":"RH6 9LU",
    "wof:placetype":"postalcode"
},
  "geometry": {"coordinates":[-0.13032698272995,51.17445568641534],"type":"Point"}
}