{
  "type": "Feature",
  "properties": {
    "date:inception_lower":"1980-01-01",
    "date:inception_upper":"1980-01-31",
    "iso:country":"GB",
    "wof:name":"RH6 9LU",
    "wof:placetype":"postalcode"
},
  "geometry": {"coordinates":[-0.130327,51.174456],"type":"Point"}
}