{
  "type": "Feature",
  "properties": {
    "iso:country":"GB",
    "wof:name":"M45 7GZ",
    "wof:placetype":"postalcode"
},
  "geometry": {"coordinates":[-2.29826069335692,53.55469967755919],"type":"Point"}
}