{
  "type": "Feature",
  "properties": {
    "iso:country": "GB",
    "wof:name": "OX18 1FJ",
    "wof:placetype": "postalcode"
  },
  "geometry": {"coordinates":[-1.58584,51.772032],"type":"Point"}
}
