{
  "type": "Feature",
  "properties": {
    "iso:country":"GB",
    "wof:name":"BA15 1DA",
    "wof:placetype":"postalcode"
},
  "geometry": {"coordinates":[-2.25180010645223,51.34576782751701],"type":"Point"}
}