{
  "type": "Feature",
  "properties": {
    "iso:country":"GB",
    "wof:name":"DY6 8PD",
    "wof:placetype":"postalcode"
},
  "geometry": {"coordinates":[-2.14737574515618,52.48494047367762],"type":"Point"}
}