{
  "type": "Feature",
  "properties": {
    "iso:country": "GB",
    "wof:name": "DY6 8PD",
    "wof:placetype": "postalcode"
  },
  "geometry": {"coordinates":[-2.147376,52.48494],"type":"Point"}
}
