{
  "type": "Feature",
  "properties": {
    "iso:country":"GB",
    "wof:name":"SA6 5PY",
    "wof:placetype":"postalcode"
},
  "geometry": {"coordinates":[-3.88547390710801,51.69894120623162],"type":"Point"}
}