{
  "type": "Feature",
  "properties": {
    "iso:country":"GB",
    "wof:name":"LA12 8RA",
    "wof:placetype":"postalcode"
},
  "geometry": {"coordinates":[-2.98794020879762,54.25420006601856],"type":"Point"}
}