{
  "type": "Feature",
  "properties": {
    "date:inception_lower": "2000-12-01",
    "date:inception_upper": "2000-12-01",
    "iso:country": "GB",
    "wof:name": "LA12 8RA",
    "wof:placetype": "postalcode"
  },
  "geometry": {"coordinates":[-2.987925,54.254209],"type":"Point"}
}
