{
  "type": "Feature",
  "properties": {
    "iso:country":"GB",
    "wof:name":"G76 7XR",
    "wof:placetype":"postalcode"
},
  "geometry": {"coordinates":[-4.28568353860068,55.78401066607655],"type":"Point"}
}