{
  "type": "Feature",
  "properties": {
    "date:inception_lower": "1980-01-01",
    "date:inception_upper": "1980-01-01",
    "iso:country": "GB",
    "wof:name": "SK6 4QB",
    "wof:placetype": "postalcode"
  },
  "geometry": {"coordinates":[-2.086076,53.421293],"type":"Point"}
}
