{
  "type": "Feature",
  "properties": {
    "iso:country":"GB",
    "wof:name":"BA11 2EX",
    "wof:placetype":"postalcode"
},
  "geometry": {"coordinates":[-2.29780394283531,51.23524933190044],"type":"Point"}
}