{
  "type": "Feature",
  "properties": {
    "iso:country":"GB",
    "wof:name":"B77 4EP",
    "wof:placetype":"postalcode"
},
  "geometry": {"coordinates":[-1.65095619575745,52.62992988694128],"type":"Point"}
}