{
  "type": "Feature",
  "properties": {
    "iso:country":"GB",
    "wof:name":"HU6 9ER",
    "wof:placetype":"postalcode"
},
  "geometry": {"coordinates":[-0.37250565397561,53.79082787969439],"type":"Point"}
}