{
  "type": "Feature",
  "properties": {
    "iso:country":"GB",
    "wof:name":"HR1 1EG",
    "wof:placetype":"postalcode"
},
  "geometry": {"coordinates":[-2.71053866140664,52.06358300932624],"type":"Point"}
}