{
  "type": "Feature",
  "properties": {
    "iso:country":"GB",
    "wof:name":"DG8 9EW",
    "wof:placetype":"postalcode"
},
  "geometry": {"coordinates":[-4.43980284203865,54.86625569335982],"type":"Point"}
}