{
  "type": "Feature",
  "properties": {
    "iso:country":"GB",
    "wof:name":"S36 2PP",
    "wof:placetype":"postalcode"
},
  "geometry": {"coordinates":[-1.57225192352195,53.47723230030989],"type":"Point"}
}