{
  "type": "Feature",
  "properties": {
    "date:inception_lower": "1980-01-01",
    "date:inception_upper": "1980-01-01",
    "iso:country": "GB",
    "wof:name": "G51 4DA",
    "wof:placetype": "postalcode"
  },
  "geometry": {"coordinates":[-4.329878,55.85261],"type":"Point"}
}
