{
  "type": "Feature",
  "properties": {
    "iso:country":"GB",
    "wof:name":"G51 4DA",
    "wof:placetype":"postalcode"
},
  "geometry": {"coordinates":[-4.32987816204679,55.85261048082987],"type":"Point"}
}