{
  "type": "Feature",
  "properties": {
    "iso:country": "GB",
    "wof:name": "RG27 9SW",
    "wof:placetype": "postalcode"
  },
  "geometry": {"coordinates":[-0.949383,51.287764],"type":"Point"}
}
