{
  "type": "Feature",
  "properties": {
    "iso:country":"GB",
    "wof:name":"CW1 5TG",
    "wof:placetype":"postalcode"
},
  "geometry": {"coordinates":[-2.39316743292763,53.09844491048616],"type":"Point"}
}