{
  "type": "Feature",
  "properties": {
    "iso:country": "GB",
    "wof:name": "CT10 1QH",
    "wof:placetype": "postalcode"
  },
  "geometry": {"coordinates":[1.439207,51.356314],"type":"Point"}
}
