{
  "type": "Feature",
  "properties": {
    "date:inception_lower": "2000-10-01",
    "date:inception_upper": "2000-10-01",
    "iso:country": "GB",
    "wof:name": "GL51 3JX",
    "wof:placetype": "postalcode"
  },
  "geometry": {"coordinates":[-2.115519,51.88599],"type":"Point"}
}
