{
  "type": "Feature",
  "properties": {
    "iso:country":"GB",
    "wof:name":"FY5 3EY",
    "wof:placetype":"postalcode"
},
  "geometry": {"coordinates":[-3.02578827260207,53.86290544114909],"type":"Point"}
}