{
  "type": "Feature",
  "properties": {
    "iso:country":"GB",
    "wof:name":"KT20 5BX",
    "wof:placetype":"postalcode"
},
  "geometry": {"coordinates":[-0.24028178584536,51.30288770678306],"type":"Point"}
}