{
  "type": "Feature",
  "properties": {
    "iso:country":"GB",
    "wof:name":"TA8 1ES",
    "wof:placetype":"postalcode"
},
  "geometry": {"coordinates":[-2.9941300036355,51.23732156421653],"type":"Point"}
}