{
  "type": "Feature",
  "properties": {
    "date:inception_lower": "1980-01-01",
    "date:inception_upper": "1980-01-01",
    "iso:country": "GB",
    "wof:name": "G44 3NF",
    "wof:placetype": "postalcode"
  },
  "geometry": {"coordinates":[-4.265342,55.812981],"type":"Point"}
}
