{
  "type": "Feature",
  "properties": {
    "iso:country": "GB",
    "wof:name": "G44 3NF",
    "wof:placetype": "postalcode"
  },
  "geometry": {"coordinates":[-4.264425,55.813411],"type":"Point"}
}
