{
  "type": "Feature",
  "properties": {
    "iso:country":"GB",
    "wof:name":"IV17 0UG",
    "wof:placetype":"postalcode"
},
  "geometry": {"coordinates":[-4.24367220928255,57.69515600401547],"type":"Point"}
}