{
  "type": "Feature",
  "properties": {
    "date:inception_lower": "1980-01-01",
    "date:inception_upper": "1980-01-01",
    "iso:country": "GB",
    "wof:name": "BB11 3DH",
    "wof:placetype": "postalcode"
  },
  "geometry": {"coordinates":[-2.234489,53.792156],"type":"Point"}
}
