{
  "type": "Feature",
  "properties": {
    "iso:country":"GB",
    "wof:name":"BB11 3DH",
    "wof:placetype":"postalcode"
},
  "geometry": {"coordinates":[-2.23459422236158,53.79194943899736],"type":"Point"}
}