{
  "type": "Feature",
  "properties": {
    "iso:country":"GB",
    "wof:name":"LS17 8BL",
    "wof:placetype":"postalcode"
},
  "geometry": {"coordinates":[-1.53246159155469,53.85190217110021],"type":"Point"}
}