{
  "type": "Feature",
  "properties": {
    "iso:country":"GB",
    "wof:name":"G72 9JX",
    "wof:placetype":"postalcode"
},
  "geometry": {"coordinates":[-4.10079465581168,55.80013527771547],"type":"Point"}
}