{
  "type": "Feature",
  "properties": {
    "date:inception_lower": "2022-10-01",
    "date:inception_upper": "2022-10-01",
    "iso:country": "GB",
    "wof:name": "YO10 5FZ",
    "wof:placetype": "postalcode"
  },
  "geometry": {"coordinates":[-1.034082,53.947671],"type":"Point"}
}
