{
  "type": "Feature",
  "properties": {
    "iso:country":"GB",
    "wof:name":"NP23 5QP",
    "wof:placetype":"postalcode"
},
  "geometry": {"coordinates":[-3.20440346907589,51.79846287918901],"type":"Point"}
}