{
  "type": "Feature",
  "properties": {
    "iso:country": "GB",
    "wof:name": "NP23 5QP",
    "wof:placetype": "postalcode"
  },
  "geometry": {"coordinates":[-3.204403,51.798463],"type":"Point"}
}
