{
  "type": "Feature",
  "properties": {
    "iso:country":"GB",
    "wof:name":"PR2 5HZ",
    "wof:placetype":"postalcode"
},
  "geometry": {"coordinates":[-2.62864366867602,53.80403948147296],"type":"Point"}
}