{
  "type": "Feature",
  "properties": {
    "date:inception_lower":"2005-07-01",
    "date:inception_upper":"2005-07-31",
    "iso:country":"GB",
    "wof:name":"PR2 5HZ",
    "wof:placetype":"postalcode"
},
  "geometry": {"coordinates":[-2.628644,53.804039],"type":"Point"}
}