{
  "type": "Feature",
  "properties": {
    "iso:country": "GB",
    "wof:name": "PR2 5HZ",
    "wof:placetype": "postalcode"
  },
  "geometry": {"coordinates":[-2.628644,53.804039],"type":"Point"}
}
