{
  "type": "Feature",
  "properties": {
    "iso:country": "GB",
    "wof:name": "HU3 1UR",
    "wof:placetype": "postalcode"
  },
  "geometry": {"coordinates":[-0.347368,53.755615],"type":"Point"}
}
