{
  "type": "Feature",
  "properties": {
    "iso:country":"GB",
    "wof:name":"HU3 1UR",
    "wof:placetype":"postalcode"
},
  "geometry": {"coordinates":[-0.34736818787726,53.75561528194827],"type":"Point"}
}