{
  "type": "Feature",
  "properties": {
    "iso:country":"GB",
    "wof:name":"DE21 6TZ",
    "wof:placetype":"postalcode"
},
  "geometry": {"coordinates":[-1.43179789007792,52.91870985515023],"type":"Point"}
}