{
  "type": "Feature",
  "properties": {
    "iso:country": "GB",
    "wof:name": "DE21 6TZ",
    "wof:placetype": "postalcode"
  },
  "geometry": {"coordinates":[-1.431798,52.91871],"type":"Point"}
}
