{
  "type": "Feature",
  "properties": {
    "date:inception_lower": "1990-02-01",
    "date:inception_upper": "1990-02-01",
    "iso:country": "GB",
    "wof:name": "PL11 2QY",
    "wof:placetype": "postalcode"
  },
  "geometry": {"coordinates":[-4.213569,50.377651],"type":"Point"}
}
