{
  "type": "Feature",
  "properties": {
    "iso:country":"GB",
    "wof:name":"PL11 2QY",
    "wof:placetype":"postalcode"
},
  "geometry": {"coordinates":[-4.21356903709747,50.37765150167981],"type":"Point"}
}