{
  "type": "Feature",
  "properties": {
    "iso:country":"GB",
    "wof:name":"LL57 1SN",
    "wof:placetype":"postalcode"
},
  "geometry": {"coordinates":[-4.11556219735819,53.22644652437742],"type":"Point"}
}