{
  "type": "Feature",
  "properties": {
    "iso:country": "GB",
    "wof:name": "LL57 1SN",
    "wof:placetype": "postalcode"
  },
  "geometry": {"coordinates":[-4.11566,53.226489],"type":"Point"}
}
