{
  "type": "Feature",
  "properties": {
    "date:inception_lower": "1980-01-01",
    "date:inception_upper": "1980-01-01",
    "iso:country": "GB",
    "wof:name": "LL57 1SN",
    "wof:placetype": "postalcode"
  },
  "geometry": {"coordinates":[-4.11566,53.226489],"type":"Point"}
}
