{
  "type": "Feature",
  "properties": {
    "iso:country":"GB",
    "wof:name":"BN3 8AB",
    "wof:placetype":"postalcode"
},
  "geometry": {"coordinates":[-0.20048512565628,50.84402387703574],"type":"Point"}
}