{
  "type": "Feature",
  "properties": {
    "iso:country":"GB",
    "wof:name":"TS21 3DQ",
    "wof:placetype":"postalcode"
},
  "geometry": {"coordinates":[-1.44820351328267,54.65686054676579],"type":"Point"}
}