{
  "type": "Feature",
  "properties": {
    "date:inception_lower":"1993-01-01",
    "date:inception_upper":"1993-01-31",
    "iso:country":"GB",
    "wof:name":"BL8 2NN",
    "wof:placetype":"postalcode"
},
  "geometry": {"coordinates":[-2.332988,53.592449],"type":"Point"}
}