{
  "type": "Feature",
  "properties": {
    "iso:country": "GB",
    "wof:name": "BL8 2NN",
    "wof:placetype": "postalcode"
  },
  "geometry": {"coordinates":[-2.332988,53.592449],"type":"Point"}
}
