{
  "type": "Feature",
  "properties": {
    "iso:country":"GB",
    "wof:name":"SA10 8LR",
    "wof:placetype":"postalcode"
},
  "geometry": {"coordinates":[-3.7791844284879,51.68897272498864],"type":"Point"}
}