{
  "type": "Feature",
  "properties": {
    "iso:country":"GB",
    "wof:name":"PA21 2DX",
    "wof:placetype":"postalcode"
},
  "geometry": {"coordinates":[-5.23011976750023,55.90812269471302],"type":"Point"}
}