{
  "type": "Feature",
  "properties": {
    "iso:country": "GB",
    "wof:name": "PR25 2EL",
    "wof:placetype": "postalcode"
  },
  "geometry": {"coordinates":[-2.693267,53.68982],"type":"Point"}
}
