{
  "type": "Feature",
  "properties": {
    "iso:country":"GB",
    "wof:name":"PR25 2EL",
    "wof:placetype":"postalcode"
},
  "geometry": {"coordinates":[-2.6932672069995,53.68982031461795],"type":"Point"}
}