{
  "type": "Feature",
  "properties": {
    "iso:country": "GB",
    "wof:name": "EX4 1HB",
    "wof:placetype": "postalcode"
  },
  "geometry": {"coordinates":[-3.546519,50.71556],"type":"Point"}
}
