{
  "type": "Feature",
  "properties": {
    "date:inception_lower": "1980-01-01",
    "date:inception_upper": "1980-01-01",
    "iso:country": "GB",
    "wof:name": "CM3 6AX",
    "wof:placetype": "postalcode"
  },
  "geometry": {"coordinates":[0.771586,51.680406],"type":"Point"}
}
