{
  "type": "Feature",
  "properties": {
    "date:inception_lower": "2021-03-01",
    "date:inception_upper": "2021-03-01",
    "iso:country": "GB",
    "wof:name": "TA11 6FR",
    "wof:placetype": "postalcode"
  },
  "geometry": {"coordinates":[-2.737024,51.055867],"type":"Point"}
}
