{
  "type": "Feature",
  "properties": {
    "date:inception_lower": "2002-06-01",
    "date:inception_upper": "2002-06-01",
    "iso:country": "GB",
    "wof:name": "S43 1GA",
    "wof:placetype": "postalcode"
  },
  "geometry": {"coordinates":[-1.39761,53.257514],"type":"Point"}
}
