{
  "type": "Feature",
  "properties": {
    "iso:country": "GB",
    "wof:name": "ST1 2AP",
    "wof:placetype": "postalcode"
  },
  "geometry": {"coordinates":[-2.164156,53.026062],"type":"Point"}
}
