{
  "type": "Feature",
  "properties": {
    "iso:country":"GB",
    "wof:name":"OL11 1DT",
    "wof:placetype":"postalcode"
},
  "geometry": {"coordinates":[-2.153391188903,53.61115031288386],"type":"Point"}
}