{
  "type": "Feature",
  "properties": {
    "iso:country": "GB",
    "wof:name": "DE4 2PS",
    "wof:placetype": "postalcode"
  },
  "geometry": {"coordinates":[-1.605458,53.20062],"type":"Point"}
}
