{
  "type": "Feature",
  "properties": {
    "iso:country":"GB",
    "wof:name":"S60 5UE",
    "wof:placetype":"postalcode"
},
  "geometry": {"coordinates":[-1.37062302662746,53.39564080549613],"type":"Point"}
}