{
  "type": "Feature",
  "properties": {
    "iso:country":"GB",
    "wof:name":"SA2 8HQ",
    "wof:placetype":"postalcode"
},
  "geometry": {"coordinates":[-3.9956661068647,51.61722214390491],"type":"Point"}
}