{
  "type": "Feature",
  "properties": {
    "iso:country": "GB",
    "wof:name": "SA2 8HQ",
    "wof:placetype": "postalcode"
  },
  "geometry": {"coordinates":[-3.995666,51.617222],"type":"Point"}
}
