{
  "type": "Feature",
  "properties": {
    "iso:country":"GB",
    "wof:name":"DH4 7NA",
    "wof:placetype":"postalcode"
},
  "geometry": {"coordinates":[-1.49505071989115,54.87005670531591],"type":"Point"}
}