{
  "type": "Feature",
  "properties": {
    "date:inception_lower":"2015-09-01",
    "date:inception_upper":"2015-09-30",
    "iso:country":"GB",
    "wof:name":"DH4 7NA",
    "wof:placetype":"postalcode"
},
  "geometry": {"coordinates":[-1.50017,54.87041],"type":"Point"}
}