{
  "type": "Feature",
  "properties": {
    "iso:country":"GB",
    "wof:name":"PE11 4BE",
    "wof:placetype":"postalcode"
},
  "geometry": {"coordinates":[-0.15546954812045,52.84956891645818],"type":"Point"}
}