{
  "type": "Feature",
  "properties": {
    "iso:country": "GB",
    "wof:name": "PE11 4BE",
    "wof:placetype": "postalcode"
  },
  "geometry": {"coordinates":[-0.15546,52.849591],"type":"Point"}
}
