{
  "type": "Feature",
  "properties": {
    "date:inception_lower": "1980-01-01",
    "date:inception_upper": "1980-01-01",
    "iso:country": "GB",
    "wof:name": "PE11 4BE",
    "wof:placetype": "postalcode"
  },
  "geometry": {"coordinates":[-0.15546,52.849591],"type":"Point"}
}
