{
  "type": "Feature",
  "properties": {
    "iso:country":"GB",
    "wof:name":"BN1 5EP",
    "wof:placetype":"postalcode"
},
  "geometry": {"coordinates":[-0.15848563655769,50.86160721247735],"type":"Point"}
}