{
  "type": "Feature",
  "properties": {
    "date:inception_lower": "1984-10-01",
    "date:inception_upper": "1984-10-01",
    "iso:country": "GB",
    "wof:name": "SA5 5BZ",
    "wof:placetype": "postalcode"
  },
  "geometry": {"coordinates":[-3.984258,51.637402],"type":"Point"}
}
