{
  "type": "Feature",
  "properties": {
    "iso:country": "GB",
    "wof:name": "SA5 5BZ",
    "wof:placetype": "postalcode"
  },
  "geometry": {"coordinates":[-3.98424,51.637406],"type":"Point"}
}
