{
  "type": "Feature",
  "properties": {
    "iso:country":"GB",
    "wof:name":"SA5 5BZ",
    "wof:placetype":"postalcode"
},
  "geometry": {"coordinates":[-3.9842395472092,51.63740623523744],"type":"Point"}
}