{
  "type": "Feature",
  "properties": {
    "date:inception_lower": "1980-01-01",
    "date:inception_upper": "1980-01-01",
    "iso:country": "GB",
    "wof:name": "NE28 0LN",
    "wof:placetype": "postalcode"
  },
  "geometry": {"coordinates":[-1.495828,54.998781],"type":"Point"}
}
