{
  "type": "Feature",
  "properties": {
    "iso:country":"GB",
    "wof:name":"NE28 0LN",
    "wof:placetype":"postalcode"
},
  "geometry": {"coordinates":[-1.49582799456755,54.99878069086119],"type":"Point"}
}