{
  "type": "Feature",
  "properties": {
    "iso:country":"GB",
    "wof:name":"ST1 3HP",
    "wof:placetype":"postalcode"
},
  "geometry": {"coordinates":[-2.16545796776149,53.01568682870305],"type":"Point"}
}