{
  "type": "Feature",
  "properties": {
    "iso:country": "GB",
    "wof:name": "ST4 4EJ",
    "wof:placetype": "postalcode"
  },
  "geometry": {"coordinates":[-2.18343,52.997089],"type":"Point"}
}
