{
  "type": "Feature",
  "properties": {
    "iso:country":"GB",
    "wof:name":"RG30 3NS",
    "wof:placetype":"postalcode"
},
  "geometry": {"coordinates":[-1.01991400129023,51.44377485297601],"type":"Point"}
}