{
  "type": "Feature",
  "properties": {
    "iso:country":"GB",
    "wof:name":"PO6 4LL",
    "wof:placetype":"postalcode"
},
  "geometry": {"coordinates":[-1.11147377757031,50.85526121142351],"type":"Point"}
}