{
  "type": "Feature",
  "properties": {
    "iso:country": "GB",
    "wof:name": "DE56 0HZ",
    "wof:placetype": "postalcode"
  },
  "geometry": {"coordinates":[-1.460536,53.032055],"type":"Point"}
}
