{
  "type": "Feature",
  "properties": {
    "date:inception_lower":"1994-05-01",
    "date:inception_upper":"1994-05-31",
    "iso:country":"GB",
    "wof:name":"DE56 0HZ",
    "wof:placetype":"postalcode"
},
  "geometry": {"coordinates":[-1.460536,53.032055],"type":"Point"}
}