{
  "type": "Feature",
  "properties": {
    "date:inception_lower": "2024-10-01",
    "date:inception_upper": "2024-10-01",
    "iso:country": "GB",
    "wof:name": "HR4 7FN",
    "wof:placetype": "postalcode"
  },
  "geometry": {"coordinates":[-2.786772,52.08598],"type":"Point"}
}
