{
  "type": "Feature",
  "properties": {
    "date:inception_lower": "1980-01-01",
    "date:inception_upper": "1980-01-01",
    "iso:country": "GB",
    "wof:name": "LE7 9SH",
    "wof:placetype": "postalcode"
  },
  "geometry": {"coordinates":[-1.041809,52.64563],"type":"Point"}
}
