{
  "type": "Feature",
  "properties": {
    "iso:country":"GB",
    "wof:name":"LE7 9SH",
    "wof:placetype":"postalcode"
},
  "geometry": {"coordinates":[-1.0418094157199,52.64562961213645],"type":"Point"}
}