{
  "type": "Feature",
  "properties": {
    "iso:country": "GB",
    "wof:name": "EH54 6RF",
    "wof:placetype": "postalcode"
  },
  "geometry": {"coordinates":[-3.534927,55.894033],"type":"Point"}
}
