{
  "type": "Feature",
  "properties": {
    "iso:country":"GB",
    "wof:name":"BN9 9TH",
    "wof:placetype":"postalcode"
},
  "geometry": {"coordinates":[0.03635772230959,50.79161880431446],"type":"Point"}
}