{
  "type": "Feature",
  "properties": {
    "iso:country": "GB",
    "wof:name": "BN9 9TH",
    "wof:placetype": "postalcode"
  },
  "geometry": {"coordinates":[0.036358,50.791619],"type":"Point"}
}
