{
  "type": "Feature",
  "properties": {
    "date:inception_lower":"1980-01-01",
    "date:inception_upper":"1980-01-31",
    "iso:country":"GB",
    "wof:name":"BN9 9TH",
    "wof:placetype":"postalcode"
},
  "geometry": {"coordinates":[0.036358,50.791619],"type":"Point"}
}