{
  "type": "Feature",
  "properties": {
    "iso:country":"GB",
    "wof:name":"LE9 8NF",
    "wof:placetype":"postalcode"
},
  "geometry": {"coordinates":[-1.3405575691702,52.5670195317252],"type":"Point"}
}