{
  "type": "Feature",
  "properties": {
    "iso:country":"GB",
    "wof:name":"SK3 9EH",
    "wof:placetype":"postalcode"
},
  "geometry": {"coordinates":[-2.16720596588672,53.40457823913145],"type":"Point"}
}