{
  "type": "Feature",
  "properties": {
    "iso:country":"GB",
    "wof:name":"EH14 2TW",
    "wof:placetype":"postalcode"
},
  "geometry": {"coordinates":[-3.29485010644528,55.91573380351507],"type":"Point"}
}