{
  "type": "Feature",
  "properties": {
    "date:inception_lower": "2021-10-01",
    "date:inception_upper": "2021-10-01",
    "iso:country": "GB",
    "wof:name": "DY11 7FX",
    "wof:placetype": "postalcode"
  },
  "geometry": {"coordinates":[-2.259545,52.368583],"type":"Point"}
}
