{
  "type": "Feature",
  "properties": {
    "iso:country":"GB",
    "wof:name":"NW3 1QJ",
    "wof:placetype":"postalcode"
},
  "geometry": {"coordinates":[-0.1763659445482,51.55592320390587],"type":"Point"}
}