{
  "type": "Feature",
  "properties": {
    "iso:country": "GB",
    "wof:name": "LE16 8YP",
    "wof:placetype": "postalcode"
  },
  "geometry": {"coordinates":[-0.765982,52.502046],"type":"Point"}
}
