{
  "type": "Feature",
  "properties": {
    "date:inception_lower": "1980-01-01",
    "date:inception_upper": "1980-01-01",
    "iso:country": "GB",
    "wof:name": "LE16 8YP",
    "wof:placetype": "postalcode"
  },
  "geometry": {"coordinates":[-0.766594,52.502295],"type":"Point"}
}
