{
  "type": "Feature",
  "properties": {
    "iso:country":"GB",
    "wof:name":"LE16 8YP",
    "wof:placetype":"postalcode"
},
  "geometry": {"coordinates":[-0.76599540721875,52.50202900464884],"type":"Point"}
}