{
  "type": "Feature",
  "properties": {
    "iso:country":"GB",
    "wof:name":"BS37 9TT",
    "wof:placetype":"postalcode"
},
  "geometry": {"coordinates":[-2.48864446420068,51.55844370091292],"type":"Point"}
}