{
  "type": "Feature",
  "properties": {
    "date:inception_lower": "1997-12-01",
    "date:inception_upper": "1997-12-01",
    "iso:country": "GB",
    "wof:name": "BS37 9TT",
    "wof:placetype": "postalcode"
  },
  "geometry": {"coordinates":[-2.488587,51.558444],"type":"Point"}
}
