{
  "type": "Feature",
  "properties": {
    "iso:country":"GB",
    "wof:name":"DY9 0JD",
    "wof:placetype":"postalcode"
},
  "geometry": {"coordinates":[-2.15526378801455,52.41251580400104],"type":"Point"}
}