{
  "type": "Feature",
  "properties": {
    "iso:country":"GB",
    "wof:name":"SK8 7NN",
    "wof:placetype":"postalcode"
},
  "geometry": {"coordinates":[-2.19071424958368,53.35386521611904],"type":"Point"}
}