{
  "type": "Feature",
  "properties": {
    "iso:country":"GB",
    "wof:name":"CM2 9XQ",
    "wof:placetype":"postalcode"
},
  "geometry": {"coordinates":[0.4601821335124,51.72350707050818],"type":"Point"}
}