{
  "type": "Feature",
  "properties": {
    "date:inception_lower":"1992-08-01",
    "date:inception_upper":"1992-08-31",
    "iso:country":"GB",
    "wof:name":"CM2 9XQ",
    "wof:placetype":"postalcode"
},
  "geometry": {"coordinates":[0.460182,51.723507],"type":"Point"}
}