{
  "type": "Feature",
  "properties": {
    "iso:country": "GB",
    "wof:name": "SN10 3FU",
    "wof:placetype": "postalcode"
  },
  "geometry": {"coordinates":[-1.901601,51.354842],"type":"Point"}
}
