{
  "type": "Feature",
  "properties": {
    "iso:country":"GB",
    "wof:name":"SP1 1BL",
    "wof:placetype":"postalcode"
},
  "geometry": {"coordinates":[-1.7970985256987,51.06982956898425],"type":"Point"}
}