{
  "type": "Feature",
  "properties": {
    "iso:country": "GB",
    "wof:name": "SP1 1BL",
    "wof:placetype": "postalcode"
  },
  "geometry": {"coordinates":[-1.797098,51.06983],"type":"Point"}
}
