{
  "type": "Feature",
  "properties": {
    "date:inception_lower":"1980-01-01",
    "date:inception_upper":"1980-01-31",
    "iso:country":"GB",
    "wof:name":"SP1 1BL",
    "wof:placetype":"postalcode"
},
  "geometry": {"coordinates":[-1.797098,51.06983],"type":"Point"}
}