{
  "type": "Feature",
  "properties": {
    "date:inception_lower": "2022-08-01",
    "date:inception_upper": "2022-08-01",
    "iso:country": "GB",
    "wof:name": "EH24 9DF",
    "wof:placetype": "postalcode"
  },
  "geometry": {"coordinates":[-3.140657,55.850241],"type":"Point"}
}
