{
  "type": "Feature",
  "properties": {
    "iso:country":"GB",
    "wof:name":"G75 0JA",
    "wof:placetype":"postalcode"
},
  "geometry": {"coordinates":[-4.17469694542298,55.75744506729168],"type":"Point"}
}