{
  "type": "Feature",
  "properties": {
    "iso:country": "GB",
    "wof:name": "HP21 8AY",
    "wof:placetype": "postalcode"
  },
  "geometry": {"coordinates":[-0.809637,51.79834],"type":"Point"}
}
