{
  "type": "Feature",
  "properties": {
    "date:inception_lower": "1980-01-01",
    "date:inception_upper": "1980-01-01",
    "iso:country": "GB",
    "wof:name": "HP21 8AY",
    "wof:placetype": "postalcode"
  },
  "geometry": {"coordinates":[-0.809811,51.798341],"type":"Point"}
}
