{
  "type": "Feature",
  "properties": {
    "iso:country": "GB",
    "wof:name": "S20 3GB",
    "wof:placetype": "postalcode"
  },
  "geometry": {"coordinates":[-1.336494,53.328319],"type":"Point"}
}
