{
  "type": "Feature",
  "properties": {
    "iso:country":"GB",
    "wof:name":"CH65 9HR",
    "wof:placetype":"postalcode"
},
  "geometry": {"coordinates":[-2.89954835231172,53.25891108701582],"type":"Point"}
}