{
  "type": "Feature",
  "properties": {
    "iso:country": "GB",
    "wof:name": "NE63 8TL",
    "wof:placetype": "postalcode"
  },
  "geometry": {"coordinates":[-1.582702,55.17574],"type":"Point"}
}
