{
  "type": "Feature",
  "properties": {
    "iso:country":"GB",
    "wof:name":"NE63 8TL",
    "wof:placetype":"postalcode"
},
  "geometry": {"coordinates":[-1.58270175679742,55.17574037315705],"type":"Point"}
}