{
  "type": "Feature",
  "properties": {
    "iso:country":"GB",
    "wof:name":"LS25 6NH",
    "wof:placetype":"postalcode"
},
  "geometry": {"coordinates":[-1.24127073777601,53.79499403285299],"type":"Point"}
}