{
  "type": "Feature",
  "properties": {
    "iso:country": "GB",
    "wof:name": "LS25 6NH",
    "wof:placetype": "postalcode"
  },
  "geometry": {"coordinates":[-1.241271,53.794994],"type":"Point"}
}
