{
  "type": "Feature",
  "properties": {
    "iso:country": "GB",
    "wof:name": "BS37 7LY",
    "wof:placetype": "postalcode"
  },
  "geometry": {"coordinates":[-2.4449,51.567861],"type":"Point"}
}
