{
  "type": "Feature",
  "properties": {
    "iso:country":"GB",
    "wof:name":"BS37 7LY",
    "wof:placetype":"postalcode"
},
  "geometry": {"coordinates":[-2.44489968750496,51.56786098071507],"type":"Point"}
}