{
  "type": "Feature",
  "properties": {
    "date:inception_lower": "1980-01-01",
    "date:inception_upper": "1980-01-01",
    "iso:country": "GB",
    "wof:name": "SN15 3DW",
    "wof:placetype": "postalcode"
  },
  "geometry": {"coordinates":[-2.112899,51.454675],"type":"Point"}
}
