{
  "type": "Feature",
  "properties": {
    "iso:country": "GB",
    "wof:name": "BH21 4EY",
    "wof:placetype": "postalcode"
  },
  "geometry": {"coordinates":[-1.984456,50.810539],"type":"Point"}
}
