{
  "type": "Feature",
  "properties": {
    "iso:country":"GB",
    "wof:name":"B29 5DD",
    "wof:placetype":"postalcode"
},
  "geometry": {"coordinates":[-1.96524154746875,52.43624788242857],"type":"Point"}
}