{
  "type": "Feature",
  "properties": {
    "date:inception_lower": "1986-07-01",
    "date:inception_upper": "1986-07-01",
    "iso:country": "GB",
    "wof:name": "BN21 3UW",
    "wof:placetype": "postalcode"
  },
  "geometry": {"coordinates":[0.282054,50.771681],"type":"Point"}
}
