{
  "type": "Feature",
  "properties": {
    "iso:country": "GB",
    "wof:name": "BN21 3UW",
    "wof:placetype": "postalcode"
  },
  "geometry": {"coordinates":[0.282054,50.771681],"type":"Point"}
}
