{
  "type": "Feature",
  "properties": {
    "iso:country":"GB",
    "wof:name":"NG9 2SH",
    "wof:placetype":"postalcode"
},
  "geometry": {"coordinates":[-1.21068833841525,52.93895910775256],"type":"Point"}
}