{
  "type": "Feature",
  "properties": {
    "date:inception_lower": "2023-08-01",
    "date:inception_upper": "2023-08-01",
    "iso:country": "GB",
    "wof:name": "TF2 9XX",
    "wof:placetype": "postalcode"
  },
  "geometry": {"coordinates":[-2.408022,52.693132],"type":"Point"}
}
