{
  "type": "Feature",
  "properties": {
    "iso:country":"GB",
    "wof:name":"WV11 3PR",
    "wof:placetype":"postalcode"
},
  "geometry": {"coordinates":[-2.0786472225794,52.59815272277527],"type":"Point"}
}