{
  "type": "Feature",
  "properties": {
    "iso:country":"GB",
    "wof:name":"WA5 0JL",
    "wof:placetype":"postalcode"
},
  "geometry": {"coordinates":[-2.60656674831069,53.41192679980441],"type":"Point"}
}