{
  "type": "Feature",
  "properties": {
    "iso:country": "GB",
    "wof:name": "EH16 4XW",
    "wof:placetype": "postalcode"
  },
  "geometry": {"coordinates":[-3.126428,55.914914],"type":"Point"}
}
