{
  "type": "Feature",
  "properties": {
    "date:inception_lower": "2018-12-01",
    "date:inception_upper": "2018-12-01",
    "iso:country": "GB",
    "wof:name": "EH16 4XW",
    "wof:placetype": "postalcode"
  },
  "geometry": {"coordinates":[-3.126428,55.914914],"type":"Point"}
}
