{
  "type": "Feature",
  "properties": {
    "iso:country": "GB",
    "wof:name": "BN3 6AH",
    "wof:placetype": "postalcode"
  },
  "geometry": {"coordinates":[-0.163741,50.833451],"type":"Point"}
}
