{
  "type": "Feature",
  "properties": {
    "iso:country":"GB",
    "wof:name":"BN3 6AH",
    "wof:placetype":"postalcode"
},
  "geometry": {"coordinates":[-0.16374084054282,50.83345073074148],"type":"Point"}
}