{
  "type": "Feature",
  "properties": {
    "date:inception_lower":"2012-08-01",
    "date:inception_upper":"2012-08-31",
    "iso:country":"GB",
    "wof:name":"BN3 6AH",
    "wof:placetype":"postalcode"
},
  "geometry": {"coordinates":[-0.163741,50.833451],"type":"Point"}
}