{
  "type": "Feature",
  "properties": {
    "date:inception_lower": "2021-04-01",
    "date:inception_upper": "2021-04-01",
    "iso:country": "GB",
    "wof:name": "BN3 6AH",
    "wof:placetype": "postalcode"
  },
  "geometry": {"coordinates":[-0.163713,50.833445],"type":"Point"}
}
