{
  "type": "Feature",
  "properties": {
    "iso:country":"GB",
    "wof:name":"OX18 1HG",
    "wof:placetype":"postalcode"
},
  "geometry": {"coordinates":[-1.58964992662278,51.77226110355048],"type":"Point"}
}