{
  "type": "Feature",
  "properties": {
    "iso:country":"GB",
    "wof:name":"NE24 2BX",
    "wof:placetype":"postalcode"
},
  "geometry": {"coordinates":[-1.5165973393023,55.12403333346229],"type":"Point"}
}