{
  "type": "Feature",
  "properties": {
    "iso:country":"GB",
    "wof:name":"TN2 5RW",
    "wof:placetype":"postalcode"
},
  "geometry": {"coordinates":[0.24997864723549,51.11736734849104],"type":"Point"}
}