{
  "type": "Feature",
  "properties": {
    "iso:country":"GB",
    "wof:name":"TS25 2PZ",
    "wof:placetype":"postalcode"
},
  "geometry": {"coordinates":[-1.22645823208881,54.65492013368552],"type":"Point"}
}