{
  "type": "Feature",
  "properties": {
    "iso:country": "GB",
    "wof:name": "HU7 5AX",
    "wof:placetype": "postalcode"
  },
  "geometry": {"coordinates":[-0.324617,53.803958],"type":"Point"}
}
