{
  "type": "Feature",
  "properties": {
    "iso:country":"GB",
    "wof:name":"ST6 6PR",
    "wof:placetype":"postalcode"
},
  "geometry": {"coordinates":[-2.2015055190306,53.07432104753804],"type":"Point"}
}