{
  "type": "Feature",
  "properties": {
    "date:inception_lower":"2006-11-01",
    "date:inception_upper":"2006-11-30",
    "iso:country":"GB",
    "wof:name":"TQ2 8AZ",
    "wof:placetype":"postalcode"
},
  "geometry": {"coordinates":[-3.531585,50.492648],"type":"Point"}
}