{
  "type": "Feature",
  "properties": {
    "iso:country":"GB",
    "wof:name":"TQ2 8AZ",
    "wof:placetype":"postalcode"
},
  "geometry": {"coordinates":[-3.53158519964518,50.49264760145025],"type":"Point"}
}