{
  "type": "Feature",
  "properties": {
    "iso:country": "GB",
    "wof:name": "BN2 9YG",
    "wof:placetype": "postalcode"
  },
  "geometry": {"coordinates":[-0.11653,50.827923],"type":"Point"}
}
