{
  "type": "Feature",
  "properties": {
    "iso:country":"GB",
    "wof:name":"BN2 9YG",
    "wof:placetype":"postalcode"
},
  "geometry": {"coordinates":[-0.11653035563911,50.8279226105719],"type":"Point"}
}