{
  "type": "Feature",
  "properties": {
    "date:inception_lower":"2001-12-01",
    "date:inception_upper":"2001-12-31",
    "iso:country":"GB",
    "wof:name":"BN2 9YG",
    "wof:placetype":"postalcode"
},
  "geometry": {"coordinates":[-0.11653,50.827923],"type":"Point"}
}