{
  "type": "Feature",
  "properties": {
    "iso:country": "GB",
    "wof:name": "NP20 7SE",
    "wof:placetype": "postalcode"
  },
  "geometry": {"coordinates":[-3.035276,51.606694],"type":"Point"}
}
