{
  "type": "Feature",
  "properties": {
    "iso:country":"GB",
    "wof:name":"NP20 7SE",
    "wof:placetype":"postalcode"
},
  "geometry": {"coordinates":[-3.03527644678067,51.60669408706333],"type":"Point"}
}