{
  "type": "Feature",
  "properties": {
    "iso:country":"GB",
    "wof:name":"DE73 7JR",
    "wof:placetype":"postalcode"
},
  "geometry": {"coordinates":[-1.48220907736934,52.8106979199337],"type":"Point"}
}