{
  "type": "Feature",
  "properties": {
    "iso:country": "GB",
    "wof:name": "DE73 7JR",
    "wof:placetype": "postalcode"
  },
  "geometry": {"coordinates":[-1.482209,52.810698],"type":"Point"}
}
