{
  "type": "Feature",
  "properties": {
    "date:inception_lower": "1999-06-01",
    "date:inception_upper": "1999-06-01",
    "iso:country": "GB",
    "wof:name": "CH64 1RH",
    "wof:placetype": "postalcode"
  },
  "geometry": {"coordinates":[-3.009132,53.293972],"type":"Point"}
}
