{
  "type": "Feature",
  "properties": {
    "iso:country":"GB",
    "wof:name":"WS11 8JP",
    "wof:placetype":"postalcode"
},
  "geometry": {"coordinates":[-2.00954032305764,52.67271237285179],"type":"Point"}
}