{
  "type": "Feature",
  "properties": {
    "date:inception_lower":"2011-05-01",
    "date:inception_upper":"2011-05-31",
    "iso:country":"GB",
    "wof:name":"WS11 8JP",
    "wof:placetype":"postalcode"
},
  "geometry": {"coordinates":[-2.00954,52.672712],"type":"Point"}
}