{
  "type": "Feature",
  "properties": {
    "iso:country":"GB",
    "wof:name":"TR4 8ES",
    "wof:placetype":"postalcode"
},
  "geometry": {"coordinates":[-5.18045334418009,50.27125435379278],"type":"Point"}
}