{
  "type": "Feature",
  "properties": {
    "iso:country": "GB",
    "wof:name": "BN41 2GY",
    "wof:placetype": "postalcode"
  },
  "geometry": {"coordinates":[-0.211263,50.848947],"type":"Point"}
}
