{
  "type": "Feature",
  "properties": {
    "iso:country":"GB",
    "wof:name":"BN41 2GY",
    "wof:placetype":"postalcode"
},
  "geometry": {"coordinates":[-0.21126279910048,50.84894708003431],"type":"Point"}
}