{
  "type": "Feature",
  "properties": {
    "iso:country":"GB",
    "wof:name":"LL71 7AB",
    "wof:placetype":"postalcode"
},
  "geometry": {"coordinates":[-4.3798842869254,53.33020440862377],"type":"Point"}
}