{
  "type": "Feature",
  "properties": {
    "date:inception_lower": "1980-01-01",
    "date:inception_upper": "1980-01-01",
    "iso:country": "GB",
    "wof:name": "LL71 7AB",
    "wof:placetype": "postalcode"
  },
  "geometry": {"coordinates":[-4.379816,53.330223],"type":"Point"}
}
