{
  "type": "Feature",
  "properties": {
    "iso:country": "GB",
    "wof:name": "TS17 8HN",
    "wof:placetype": "postalcode"
  },
  "geometry": {"coordinates":[-1.296201,54.543098],"type":"Point"}
}
