{
  "type": "Feature",
  "properties": {
    "iso:country":"GB",
    "wof:name":"TS17 8HN",
    "wof:placetype":"postalcode"
},
  "geometry": {"coordinates":[-1.29620074551699,54.54309793432399],"type":"Point"}
}