{
  "type": "Feature",
  "properties": {
    "iso:country":"GB",
    "wof:name":"DN10 6LJ",
    "wof:placetype":"postalcode"
},
  "geometry": {"coordinates":[-1.02785676656449,53.43349624156514],"type":"Point"}
}