{
  "type": "Feature",
  "properties": {
    "date:inception_lower": "1980-01-01",
    "date:inception_upper": "1980-01-01",
    "iso:country": "GB",
    "wof:name": "DN10 6LJ",
    "wof:placetype": "postalcode"
  },
  "geometry": {"coordinates":[-1.027857,53.433496],"type":"Point"}
}
