{
  "type": "Feature",
  "properties": {
    "iso:country": "GB",
    "wof:name": "AL3 4HJ",
    "wof:placetype": "postalcode"
  },
  "geometry": {"coordinates":[-0.346918,51.748756],"type":"Point"}
}
