{
  "type": "Feature",
  "properties": {
    "iso:country":"GB",
    "wof:name":"OL4 3JT",
    "wof:placetype":"postalcode"
},
  "geometry": {"coordinates":[-2.06947252714149,53.54573995698585],"type":"Point"}
}