{
  "type": "Feature",
  "properties": {
    "iso:country":"GB",
    "wof:name":"BD20 6BQ",
    "wof:placetype":"postalcode"
},
  "geometry": {"coordinates":[-1.91988675029218,53.8818610386419],"type":"Point"}
}