{
  "type": "Feature",
  "properties": {
    "iso:country": "GB",
    "wof:name": "BD23 5JY",
    "wof:placetype": "postalcode"
  },
  "geometry": {"coordinates":[-1.96125,54.062309],"type":"Point"}
}
