{
  "type": "Feature",
  "properties": {
    "iso:country":"GB",
    "wof:name":"BD23 5JY",
    "wof:placetype":"postalcode"
},
  "geometry": {"coordinates":[-1.96124999563635,54.06230936716381],"type":"Point"}
}