{
  "type": "Feature",
  "properties": {
    "date:inception_lower":"1997-12-01",
    "date:inception_upper":"1997-12-31",
    "iso:country":"GB",
    "wof:name":"BD23 5JY",
    "wof:placetype":"postalcode"
},
  "geometry": {"coordinates":[-1.96125,54.062309],"type":"Point"}
}