{
  "type": "Feature",
  "properties": {
    "iso:country":"GB",
    "wof:name":"S3 7TY",
    "wof:placetype":"postalcode"
},
  "geometry": {"coordinates":[-1.48182782009794,53.37494365553758],"type":"Point"}
}