{
  "type": "Feature",
  "properties": {
    "iso:country":"GB",
    "wof:name":"HD7 5TJ",
    "wof:placetype":"postalcode"
},
  "geometry": {"coordinates":[-1.84970025264806,53.61731184753995],"type":"Point"}
}