{
  "type": "Feature",
  "properties": {
    "iso:country":"GB",
    "wof:name":"S7 2GF",
    "wof:placetype":"postalcode"
},
  "geometry": {"coordinates":[-1.50077740604325,53.34961327298998],"type":"Point"}
}