{
  "type": "Feature",
  "properties": {
    "date:inception_lower":"1997-12-01",
    "date:inception_upper":"1997-12-31",
    "iso:country":"GB",
    "wof:name":"BS48 1DP",
    "wof:placetype":"postalcode"
},
  "geometry": {"coordinates":[-2.758357,51.434848],"type":"Point"}
}