{
  "type": "Feature",
  "properties": {
    "iso:country":"GB",
    "wof:name":"BS48 1DP",
    "wof:placetype":"postalcode"
},
  "geometry": {"coordinates":[-2.75832452092195,51.43484977624465],"type":"Point"}
}