{
  "type": "Feature",
  "properties": {
    "date:inception_lower": "1980-01-01",
    "date:inception_upper": "1980-01-01",
    "iso:country": "GB",
    "wof:name": "TS24 8JQ",
    "wof:placetype": "postalcode"
  },
  "geometry": {"coordinates":[-1.225641,54.697047],"type":"Point"}
}
