{
  "type": "Feature",
  "properties": {
    "iso:country":"GB",
    "wof:name":"TS24 8JQ",
    "wof:placetype":"postalcode"
},
  "geometry": {"coordinates":[-1.22515418489739,54.69739291797222],"type":"Point"}
}