{
  "type": "Feature",
  "properties": {
    "date:inception_lower":"1980-01-01",
    "date:inception_upper":"1980-01-31",
    "iso:country":"GB",
    "wof:name":"SS15 4EE",
    "wof:placetype":"postalcode"
},
  "geometry": {"coordinates":[0.438222,51.584923],"type":"Point"}
}