{
  "type": "Feature",
  "properties": {
    "iso:country": "GB",
    "wof:name": "SS15 4EE",
    "wof:placetype": "postalcode"
  },
  "geometry": {"coordinates":[0.438222,51.584923],"type":"Point"}
}
