{
  "type": "Feature",
  "properties": {
    "iso:country":"GB",
    "wof:name":"NR2 4QB",
    "wof:placetype":"postalcode"
},
  "geometry": {"coordinates":[1.28135933604464,52.63333754484984],"type":"Point"}
}