{
  "type": "Feature",
  "properties": {
    "iso:country":"GB",
    "wof:name":"AL7 4EA",
    "wof:placetype":"postalcode"
},
  "geometry": {"coordinates":[-0.19501519644306,51.7830135448737],"type":"Point"}
}