{
  "type": "Feature",
  "properties": {
    "iso:country":"GB",
    "wof:name":"SW2 4FA",
    "wof:placetype":"postalcode"
},
  "geometry": {"coordinates":[-0.1263698685996,51.44765664424133],"type":"Point"}
}