{
  "type": "Feature",
  "properties": {
    "date:inception_lower": "2019-10-01",
    "date:inception_upper": "2019-10-01",
    "iso:country": "GB",
    "wof:name": "SA5 7DU",
    "wof:placetype": "postalcode"
  },
  "geometry": {"coordinates":[-3.950282,51.655255],"type":"Point"}
}
