{
  "type": "Feature",
  "properties": {
    "date:inception_lower": "2019-10-01",
    "date:inception_upper": "2019-10-01",
    "iso:country": "GB",
    "wof:name": "SA5 7DU",
    "wof:placetype": "postalcode"
  },
  "geometry": {"coordinates":[-3.97021,51.681333],"type":"Point"}
}
