{
  "type": "Feature",
  "properties": {
    "iso:country": "GB",
    "wof:name": "WV10 6UX",
    "wof:placetype": "postalcode"
  },
  "geometry": {"coordinates":[-2.138619,52.617228],"type":"Point"}
}
