{
  "type": "Feature",
  "properties": {
    "iso:country": "GB",
    "wof:name": "LS16 6AJ",
    "wof:placetype": "postalcode"
  },
  "geometry": {"coordinates":[-1.592369,53.852594],"type":"Point"}
}
