{
  "type": "Feature",
  "properties": {
    "iso:country":"GB",
    "wof:name":"N13 4HE",
    "wof:placetype":"postalcode"
},
  "geometry": {"coordinates":[-0.11738758548602,51.61685063635473],"type":"Point"}
}