{
  "type": "Feature",
  "properties": {
    "iso:country": "GB",
    "wof:name": "BS15 8AR",
    "wof:placetype": "postalcode"
  },
  "geometry": {"coordinates":[-2.52359,51.459997],"type":"Point"}
}
