{
  "type": "Feature",
  "properties": {
    "iso:country":"GB",
    "wof:name":"NR14 7BH",
    "wof:placetype":"postalcode"
},
  "geometry": {"coordinates":[1.44212388463594,52.56943779282982],"type":"Point"}
}