{
  "type": "Feature",
  "properties": {
    "iso:country":"GB",
    "wof:name":"SS7 5RE",
    "wof:placetype":"postalcode"
},
  "geometry": {"coordinates":[0.55108916153015,51.56054293526439],"type":"Point"}
}