{
  "type": "Feature",
  "properties": {
    "iso:country":"GB",
    "wof:name":"IG10 3SP",
    "wof:placetype":"postalcode"
},
  "geometry": {"coordinates":[0.08417887825442,51.64836308283303],"type":"Point"}
}