{
  "type": "Feature",
  "properties": {
    "iso:country":"GB",
    "wof:name":"CW6 9TQ",
    "wof:placetype":"postalcode"
},
  "geometry": {"coordinates":[-2.66526596614285,53.10849802399094],"type":"Point"}
}