{
  "type": "Feature",
  "properties": {
    "iso:country":"GB",
    "wof:name":"WR10 1AA",
    "wof:placetype":"postalcode"
},
  "geometry": {"coordinates":[-2.07470254060362,52.11056538859111],"type":"Point"}
}