{
  "type": "Feature",
  "properties": {
    "iso:country": "GB",
    "wof:name": "GL12 8EJ",
    "wof:placetype": "postalcode"
  },
  "geometry": {"coordinates":[-2.393362,51.629647],"type":"Point"}
}
