{
  "type": "Feature",
  "properties": {
    "iso:country": "GB",
    "wof:name": "G60 5HY",
    "wof:placetype": "postalcode"
  },
  "geometry": {"coordinates":[-4.451103,55.918553],"type":"Point"}
}
