{
  "type": "Feature",
  "properties": {
    "iso:country":"GB",
    "wof:name":"G60 5HY",
    "wof:placetype":"postalcode"
},
  "geometry": {"coordinates":[-4.45110275652494,55.91855328295652],"type":"Point"}
}