{
  "type": "Feature",
  "properties": {
    "iso:country":"GB",
    "wof:name":"PL6 8RU",
    "wof:placetype":"postalcode"
},
  "geometry": {"coordinates":[-4.09123942448647,50.41049698299226],"type":"Point"}
}