{
  "type": "Feature",
  "properties": {
    "iso:country": "GB",
    "wof:name": "PL6 8RU",
    "wof:placetype": "postalcode"
  },
  "geometry": {"coordinates":[-4.091239,50.410497],"type":"Point"}
}
