{
  "type": "Feature",
  "properties": {
    "iso:country":"GB",
    "wof:name":"NR32 3NH",
    "wof:placetype":"postalcode"
},
  "geometry": {"coordinates":[1.71467219392775,52.47819623440343],"type":"Point"}
}