{
  "type": "Feature",
  "properties": {
    "iso:country":"GB",
    "wof:name":"SE16 6PE",
    "wof:placetype":"postalcode"
},
  "geometry": {"coordinates":[-0.04697084368987,51.50162962468801],"type":"Point"}
}