{
  "type": "Feature",
  "properties": {
    "iso:country": "GB",
    "wof:name": "SE16 6PE",
    "wof:placetype": "postalcode"
  },
  "geometry": {"coordinates":[-0.046971,51.50163],"type":"Point"}
}
