{
  "type": "Feature",
  "properties": {
    "date:inception_lower":"1980-01-01",
    "date:inception_upper":"1980-01-31",
    "iso:country":"GB",
    "wof:name":"SS6 9NR",
    "wof:placetype":"postalcode"
},
  "geometry": {"coordinates":[0.614339,51.601437],"type":"Point"}
}