{
  "type": "Feature",
  "properties": {
    "iso:country":"GB",
    "wof:name":"SS6 9NR",
    "wof:placetype":"postalcode"
},
  "geometry": {"coordinates":[0.61433912515672,51.60143745795877],"type":"Point"}
}