{
  "type": "Feature",
  "properties": {
    "iso:country":"GB",
    "wof:name":"BB4 5PW",
    "wof:placetype":"postalcode"
},
  "geometry": {"coordinates":[-2.31896094332508,53.70169403935372],"type":"Point"}
}