{
  "type": "Feature",
  "properties": {
    "date:inception_lower":"2005-07-01",
    "date:inception_upper":"2005-07-31",
    "iso:country":"GB",
    "wof:name":"BB4 5PW",
    "wof:placetype":"postalcode"
},
  "geometry": {"coordinates":[-2.318961,53.701694],"type":"Point"}
}