{
  "type": "Feature",
  "properties": {
    "iso:country":"GB",
    "wof:name":"NR9 3AD",
    "wof:placetype":"postalcode"
},
  "geometry": {"coordinates":[1.19255293279753,52.61591751743405],"type":"Point"}
}