{
  "type": "Feature",
  "properties": {
    "date:inception_lower": "1980-01-01",
    "date:inception_upper": "1980-01-01",
    "iso:country": "GB",
    "wof:name": "NR9 3AD",
    "wof:placetype": "postalcode"
  },
  "geometry": {"coordinates":[1.192407,52.615865],"type":"Point"}
}
