{
  "type": "Feature",
  "properties": {
    "date:inception_lower": "2008-01-01",
    "date:inception_upper": "2008-01-01",
    "iso:country": "GB",
    "wof:name": "CV4 9AH",
    "wof:placetype": "postalcode"
  },
  "geometry": {"coordinates":[-1.599833,52.409613],"type":"Point"}
}
