{
  "type": "Feature",
  "properties": {
    "iso:country":"GB",
    "wof:name":"CV4 9AH",
    "wof:placetype":"postalcode"
},
  "geometry": {"coordinates":[-1.59983274172278,52.4096133896798],"type":"Point"}
}