{
  "type": "Feature",
  "properties": {
    "iso:country": "GB",
    "wof:name": "EX4 0AN",
    "wof:placetype": "postalcode"
  },
  "geometry": {"coordinates":[-3.477814,50.76094],"type":"Point"}
}
