{
  "type": "Feature",
  "properties": {
    "iso:country": "GB",
    "wof:name": "L18 1JN",
    "wof:placetype": "postalcode"
  },
  "geometry": {"coordinates":[-2.91467,53.385739],"type":"Point"}
}
