{
  "type": "Feature",
  "properties": {
    "iso:country": "GB",
    "wof:name": "LE67 6PH",
    "wof:placetype": "postalcode"
  },
  "geometry": {"coordinates":[-1.407862,52.68863],"type":"Point"}
}
