{
  "type": "Feature",
  "properties": {
    "iso:country":"GB",
    "wof:name":"SW9 6BN",
    "wof:placetype":"postalcode"
},
  "geometry": {"coordinates":[-0.11029293357104,51.47383686485922],"type":"Point"}
}