{
  "type": "Feature",
  "properties": {
    "date:inception_lower":"2015-02-01",
    "date:inception_upper":"2015-02-28",
    "iso:country":"GB",
    "wof:name":"SW9 6BN",
    "wof:placetype":"postalcode"
},
  "geometry": {"coordinates":[-0.110293,51.473837],"type":"Point"}
}