{
  "type": "Feature",
  "properties": {
    "iso:country":"GB",
    "wof:name":"YO24 1NE",
    "wof:placetype":"postalcode"
},
  "geometry": {"coordinates":[-1.10627704958928,53.93427997842231],"type":"Point"}
}