{
  "type": "Feature",
  "properties": {
    "iso:country":"GB",
    "wof:name":"SG16 6GA",
    "wof:placetype":"postalcode"
},
  "geometry": {"coordinates":[-0.28692685564158,52.0314652563796],"type":"Point"}
}