{
  "type": "Feature",
  "properties": {
    "date:inception_lower": "2015-01-01",
    "date:inception_upper": "2015-01-01",
    "iso:country": "GB",
    "wof:name": "SG16 6GA",
    "wof:placetype": "postalcode"
  },
  "geometry": {"coordinates":[-0.287019,52.03145],"type":"Point"}
}
