{
  "type": "Feature",
  "properties": {
    "iso:country":"GB",
    "wof:name":"B64 5RG",
    "wof:placetype":"postalcode"
},
  "geometry": {"coordinates":[-2.06082381074283,52.47867889606002],"type":"Point"}
}