{
  "type": "Feature",
  "properties": {
    "iso:country": "GB",
    "wof:name": "B64 5RG",
    "wof:placetype": "postalcode"
  },
  "geometry": {"coordinates":[-2.060229,52.478506],"type":"Point"}
}
