{
  "type": "Feature",
  "properties": {
    "iso:country":"GB",
    "wof:name":"S66 8LW",
    "wof:placetype":"postalcode"
},
  "geometry": {"coordinates":[-1.21446486591326,53.42166430415254],"type":"Point"}
}