{
  "type": "Feature",
  "properties": {
    "iso:country":"GB",
    "wof:name":"M1 2FF",
    "wof:placetype":"postalcode"
},
  "geometry": {"coordinates":[-2.23257444182776,53.48141934116428],"type":"Point"}
}