{
  "type": "Feature",
  "properties": {
    "iso:country":"GB",
    "wof:name":"CM11 2QW",
    "wof:placetype":"postalcode"
},
  "geometry": {"coordinates":[0.43416955538078,51.61118596838585],"type":"Point"}
}