{
  "type": "Feature",
  "properties": {
    "date:inception_lower": "1980-01-01",
    "date:inception_upper": "1980-01-01",
    "iso:country": "GB",
    "wof:name": "CM11 2QW",
    "wof:placetype": "postalcode"
  },
  "geometry": {"coordinates":[0.43417,51.611186],"type":"Point"}
}
