{
  "type": "Feature",
  "properties": {
    "iso:country":"GB",
    "wof:name":"W1W 6XT",
    "wof:placetype":"postalcode"
},
  "geometry": {"coordinates":[-0.14223822262827,51.52008336232181],"type":"Point"}
}