{
  "type": "Feature",
  "properties": {
    "date:inception_lower": "1994-05-01",
    "date:inception_upper": "1994-05-01",
    "iso:country": "GB",
    "wof:name": "M22 8EG",
    "wof:placetype": "postalcode"
  },
  "geometry": {"coordinates":[-2.266255,53.39274],"type":"Point"}
}
