{
  "type": "Feature",
  "properties": {
    "iso:country":"GB",
    "wof:name":"M22 8EG",
    "wof:placetype":"postalcode"
},
  "geometry": {"coordinates":[-2.26625479867175,53.39274006382641],"type":"Point"}
}