{
  "type": "Feature",
  "properties": {
    "iso:country":"GB",
    "wof:name":"ML8 5SS",
    "wof:placetype":"postalcode"
},
  "geometry": {"coordinates":[-3.83274143185554,55.71150145168889],"type":"Point"}
}