{
  "type": "Feature",
  "properties": {
    "date:inception_lower": "2003-11-01",
    "date:inception_upper": "2003-11-01",
    "iso:country": "GB",
    "wof:name": "ML8 5SS",
    "wof:placetype": "postalcode"
  },
  "geometry": {"coordinates":[-3.832741,55.711501],"type":"Point"}
}
