{
  "type": "Feature",
  "properties": {
    "iso:country":"GB",
    "wof:name":"ME12 3PR",
    "wof:placetype":"postalcode"
},
  "geometry": {"coordinates":[0.81021072492133,51.41993654612019],"type":"Point"}
}