{
  "type": "Feature",
  "properties": {
    "iso:country": "GB",
    "wof:name": "ME12 3PR",
    "wof:placetype": "postalcode"
  },
  "geometry": {"coordinates":[0.810211,51.419937],"type":"Point"}
}
