{
  "type": "Feature",
  "properties": {
    "iso:country": "GB",
    "wof:name": "CM19 4AQ",
    "wof:placetype": "postalcode"
  },
  "geometry": {"coordinates":[0.087428,51.768391],"type":"Point"}
}
