{
  "type": "Feature",
  "properties": {
    "iso:country":"GB",
    "wof:name":"CM19 4AQ",
    "wof:placetype":"postalcode"
},
  "geometry": {"coordinates":[0.08742825748214,51.76839150221985],"type":"Point"}
}