{
  "type": "Feature",
  "properties": {
    "iso:country": "GB",
    "wof:name": "YO61 3NA",
    "wof:placetype": "postalcode"
  },
  "geometry": {"coordinates":[-1.198602,54.121939],"type":"Point"}
}
