{
  "type": "Feature",
  "properties": {
    "iso:country": "GB",
    "wof:name": "YO61 3NA",
    "wof:placetype": "postalcode"
  },
  "geometry": {"coordinates":[-1.199327,54.122447],"type":"Point"}
}
