{
  "type": "Feature",
  "properties": {
    "iso:country":"GB",
    "wof:name":"WN6 8RR",
    "wof:placetype":"postalcode"
},
  "geometry": {"coordinates":[-2.6962714257134,53.58918683246481],"type":"Point"}
}