{
  "type": "Feature",
  "properties": {
    "iso:country": "GB",
    "wof:name": "WN6 8RR",
    "wof:placetype": "postalcode"
  },
  "geometry": {"coordinates":[-2.695941,53.589385],"type":"Point"}
}
