{
  "type": "Feature",
  "properties": {
    "iso:country":"GB",
    "wof:name":"BH24 2NN",
    "wof:placetype":"postalcode"
},
  "geometry": {"coordinates":[-1.81011421086935,50.84257064531758],"type":"Point"}
}