{
  "type": "Feature",
  "properties": {
    "date:inception_lower":"1980-01-01",
    "date:inception_upper":"1980-01-31",
    "iso:country":"GB",
    "wof:name":"WN6 8RG",
    "wof:placetype":"postalcode"
},
  "geometry": {"coordinates":[-2.645738,53.561453],"type":"Point"}
}