{
  "type": "Feature",
  "properties": {
    "iso:country":"GB",
    "wof:name":"IP28 7RH",
    "wof:placetype":"postalcode"
},
  "geometry": {"coordinates":[0.52365723143454,52.34304743808972],"type":"Point"}
}