{
  "type": "Feature",
  "properties": {
    "iso:country":"GB",
    "wof:name":"LA9 7HL",
    "wof:placetype":"postalcode"
},
  "geometry": {"coordinates":[-2.72950903067414,54.308456282881],"type":"Point"}
}