{
  "type": "Feature",
  "properties": {
    "date:inception_lower": "2005-06-01",
    "date:inception_upper": "2005-06-01",
    "iso:country": "GB",
    "wof:name": "PE10 0DB",
    "wof:placetype": "postalcode"
  },
  "geometry": {"coordinates":[-0.367468,52.755945],"type":"Point"}
}
