{
  "type": "Feature",
  "properties": {
    "iso:country": "GB",
    "wof:name": "BN14 9PR",
    "wof:placetype": "postalcode"
  },
  "geometry": {"coordinates":[-0.39006,50.834068],"type":"Point"}
}
