{
  "type": "Feature",
  "properties": {
    "iso:country": "GB",
    "wof:name": "CM15 0SX",
    "wof:placetype": "postalcode"
  },
  "geometry": {"coordinates":[0.339153,51.661432],"type":"Point"}
}
