{
  "type": "Feature",
  "properties": {
    "date:inception_lower":"1980-01-01",
    "date:inception_upper":"1980-01-31",
    "iso:country":"GB",
    "wof:name":"SA13 1YT",
    "wof:placetype":"postalcode"
},
  "geometry": {"coordinates":[-3.77759,51.599119],"type":"Point"}
}