{
  "type": "Feature",
  "properties": {
    "iso:country":"GB",
    "wof:name":"SA13 1YT",
    "wof:placetype":"postalcode"
},
  "geometry": {"coordinates":[-3.77758990190095,51.59911950157768],"type":"Point"}
}