{
  "type": "Feature",
  "properties": {
    "iso:country": "GB",
    "wof:name": "SA13 1YT",
    "wof:placetype": "postalcode"
  },
  "geometry": {"coordinates":[-3.77759,51.599119],"type":"Point"}
}
