{
  "type": "Feature",
  "properties": {
    "iso:country": "GB",
    "wof:name": "PO14 4GE",
    "wof:placetype": "postalcode"
  },
  "geometry": {"coordinates":[-1.251909,50.849231],"type":"Point"}
}
