{
  "type": "Feature",
  "properties": {
    "date:inception_lower": "2020-06-01",
    "date:inception_upper": "2020-06-01",
    "iso:country": "GB",
    "wof:name": "RG28 7FZ",
    "wof:placetype": "postalcode"
  },
  "geometry": {"coordinates":[-1.345735,51.229707],"type":"Point"}
}
