{
  "type": "Feature",
  "properties": {
    "iso:country":"GB",
    "wof:name":"GL7 2LB",
    "wof:placetype":"postalcode"
},
  "geometry": {"coordinates":[-1.98034794461452,51.72959277237494],"type":"Point"}
}