{
  "type": "Feature",
  "properties": {
    "iso:country":"GB",
    "wof:name":"EX38 7EW",
    "wof:placetype":"postalcode"
},
  "geometry": {"coordinates":[-4.13042231224687,50.94544779167083],"type":"Point"}
}