{
  "type": "Feature",
  "properties": {
    "iso:country":"GB",
    "wof:name":"PE21 9ES",
    "wof:placetype":"postalcode"
},
  "geometry": {"coordinates":[-0.02555160502471,52.98494765721141],"type":"Point"}
}