{
  "type": "Feature",
  "properties": {
    "date:inception_lower": "1980-01-01",
    "date:inception_upper": "1980-01-01",
    "iso:country": "GB",
    "wof:name": "EN7 6PJ",
    "wof:placetype": "postalcode"
  },
  "geometry": {"coordinates":[-0.08944,51.724685],"type":"Point"}
}
