{
  "type": "Feature",
  "properties": {
    "iso:country": "GB",
    "wof:name": "EN7 6PJ",
    "wof:placetype": "postalcode"
  },
  "geometry": {"coordinates":[-0.08944,51.724685],"type":"Point"}
}
