{
  "type": "Feature",
  "properties": {
    "iso:country":"GB",
    "wof:name":"LS15 7UU",
    "wof:placetype":"postalcode"
},
  "geometry": {"coordinates":[-1.46038261223298,53.80764840505244],"type":"Point"}
}