{
  "type": "Feature",
  "properties": {
    "iso:country": "GB",
    "wof:name": "LS15 7UU",
    "wof:placetype": "postalcode"
  },
  "geometry": {"coordinates":[-1.460383,53.807648],"type":"Point"}
}
