{
  "type": "Feature",
  "properties": {
    "iso:country": "GB",
    "wof:name": "SA15 5YG",
    "wof:placetype": "postalcode"
  },
  "geometry": {"coordinates":[-4.186057,51.746625],"type":"Point"}
}
