{
  "type": "Feature",
  "properties": {
    "iso:country":"GB",
    "wof:name":"WV8 1AT",
    "wof:placetype":"postalcode"
},
  "geometry": {"coordinates":[-2.19519162661359,52.63127987871594],"type":"Point"}
}