{
  "type": "Feature",
  "properties": {
    "iso:country": "GB",
    "wof:name": "WV8 1AT",
    "wof:placetype": "postalcode"
  },
  "geometry": {"coordinates":[-2.195192,52.63128],"type":"Point"}
}
