{
  "type": "Feature",
  "properties": {
    "date:inception_lower": "1980-01-01",
    "date:inception_upper": "1980-01-01",
    "iso:country": "GB",
    "wof:name": "BD20 5RR",
    "wof:placetype": "postalcode"
  },
  "geometry": {"coordinates":[-1.853388,53.870707],"type":"Point"}
}
