{
  "type": "Feature",
  "properties": {
    "iso:country": "GB",
    "wof:name": "CF32 0EA",
    "wof:placetype": "postalcode"
  },
  "geometry": {"coordinates":[-3.601422,51.558512],"type":"Point"}
}
