{
  "type": "Feature",
  "properties": {
    "iso:country": "GB",
    "wof:name": "M12 4JD",
    "wof:placetype": "postalcode"
  },
  "geometry": {"coordinates":[-2.220867,53.472849],"type":"Point"}
}
