{
  "type": "Feature",
  "properties": {
    "iso:country":"GB",
    "wof:name":"M12 4JD",
    "wof:placetype":"postalcode"
},
  "geometry": {"coordinates":[-2.2208027642522,53.47212066119154],"type":"Point"}
}