{
  "type": "Feature",
  "properties": {
    "date:inception_lower": "2020-12-01",
    "date:inception_upper": "2020-12-01",
    "iso:country": "GB",
    "wof:name": "OX7 6SZ",
    "wof:placetype": "postalcode"
  },
  "geometry": {"coordinates":[-1.614047,51.861722],"type":"Point"}
}
