{
  "type": "Feature",
  "properties": {
    "iso:country":"GB",
    "wof:name":"ST5 6BZ",
    "wof:placetype":"postalcode"
},
  "geometry": {"coordinates":[-2.25220834434878,53.020541281655],"type":"Point"}
}