{
  "type": "Feature",
  "properties": {
    "date:inception_lower": "1980-01-01",
    "date:inception_upper": "1980-01-01",
    "iso:country": "GB",
    "wof:name": "KY11 2TL",
    "wof:placetype": "postalcode"
  },
  "geometry": {"coordinates":[-3.428468,56.041773],"type":"Point"}
}
