{
  "type": "Feature",
  "properties": {
    "iso:country":"GB",
    "wof:name":"KY11 2TL",
    "wof:placetype":"postalcode"
},
  "geometry": {"coordinates":[-3.4284681048968,56.0417730476776],"type":"Point"}
}