{
  "type": "Feature",
  "properties": {
    "date:inception_lower": "1980-01-01",
    "date:inception_upper": "1980-01-01",
    "iso:country": "GB",
    "wof:name": "BB9 0JB",
    "wof:placetype": "postalcode"
  },
  "geometry": {"coordinates":[-2.202433,53.827466],"type":"Point"}
}
