{
  "type": "Feature",
  "properties": {
    "iso:country":"GB",
    "wof:name":"BS22 8SU",
    "wof:placetype":"postalcode"
},
  "geometry": {"coordinates":[-2.92933974138405,51.35302409249837],"type":"Point"}
}