{
  "type": "Feature",
  "properties": {
    "iso:country":"GB",
    "wof:name":"UB7 7JA",
    "wof:placetype":"postalcode"
},
  "geometry": {"coordinates":[-0.47030333768669,51.50617941603046],"type":"Point"}
}