{
  "type": "Feature",
  "properties": {
    "iso:country":"GB",
    "wof:name":"PE30 9ET",
    "wof:placetype":"postalcode"
},
  "geometry": {"coordinates":[0.40060159988859,52.75743278310136],"type":"Point"}
}