{
  "type": "Feature",
  "properties": {
    "iso:country": "GB",
    "wof:name": "PE30 9ET",
    "wof:placetype": "postalcode"
  },
  "geometry": {"coordinates":[0.400602,52.757433],"type":"Point"}
}
