{
  "type": "Feature",
  "properties": {
    "iso:country":"GB",
    "wof:name":"DH3 1GH",
    "wof:placetype":"postalcode"
},
  "geometry": {"coordinates":[-1.58630564633521,54.90597872439603],"type":"Point"}
}