{
  "type": "Feature",
  "properties": {
    "date:inception_lower": "2012-05-01",
    "date:inception_upper": "2012-05-01",
    "iso:country": "GB",
    "wof:name": "DH3 1GH",
    "wof:placetype": "postalcode"
  },
  "geometry": {"coordinates":[-1.586306,54.905979],"type":"Point"}
}
