{
  "type": "Feature",
  "properties": {
    "iso:country": "GB",
    "wof:name": "DH3 1GH",
    "wof:placetype": "postalcode"
  },
  "geometry": {"coordinates":[-1.586306,54.905979],"type":"Point"}
}
