{
  "type": "Feature",
  "properties": {
    "iso:country": "GB",
    "wof:name": "KT4 8PT",
    "wof:placetype": "postalcode"
  },
  "geometry": {"coordinates":[-0.224607,51.381166],"type":"Point"}
}
