{
  "type": "Feature",
  "properties": {
    "date:inception_lower": "2002-05-01",
    "date:inception_upper": "2002-05-01",
    "iso:country": "GB",
    "wof:name": "EC3R 7LU",
    "wof:placetype": "postalcode"
  },
  "geometry": {"coordinates":[-0.080114,51.511817],"type":"Point"}
}
