{
  "type": "Feature",
  "properties": {
    "iso:country":"GB",
    "wof:name":"CW3 9QH",
    "wof:placetype":"postalcode"
},
  "geometry": {"coordinates":[-2.36361787126,52.98221926725521],"type":"Point"}
}