{
  "type": "Feature",
  "properties": {
    "iso:country": "GB",
    "wof:name": "CV23 9JS",
    "wof:placetype": "postalcode"
  },
  "geometry": {"coordinates":[-1.314552,52.335366],"type":"Point"}
}
