{
  "type": "Feature",
  "properties": {
    "date:inception_lower":"1980-01-01",
    "date:inception_upper":"1980-01-31",
    "iso:country":"GB",
    "wof:name":"CV23 9JS",
    "wof:placetype":"postalcode"
},
  "geometry": {"coordinates":[-1.314552,52.335366],"type":"Point"}
}