{
  "type": "Feature",
  "properties": {
    "iso:country":"GB",
    "wof:name":"SY3 5AP",
    "wof:placetype":"postalcode"
},
  "geometry": {"coordinates":[-2.81041534468606,52.7147909346081],"type":"Point"}
}