{
  "type": "Feature",
  "properties": {
    "iso:country":"GB",
    "wof:name":"PA4 9BL",
    "wof:placetype":"postalcode"
},
  "geometry": {"coordinates":[-4.39940310112101,55.87887528522894],"type":"Point"}
}