{
  "type": "Feature",
  "properties": {
    "date:inception_lower":"1980-01-01",
    "date:inception_upper":"1980-01-31",
    "iso:country":"GB",
    "wof:name":"PA4 9BL",
    "wof:placetype":"postalcode"
},
  "geometry": {"coordinates":[-4.399403,55.878875],"type":"Point"}
}