{
  "type": "Feature",
  "properties": {
    "date:inception_lower":"1980-01-01",
    "date:inception_upper":"1980-01-31",
    "iso:country":"GB",
    "wof:name":"SP10 2LS",
    "wof:placetype":"postalcode"
},
  "geometry": {"coordinates":[-1.492371,51.202922],"type":"Point"}
}