{
  "type": "Feature",
  "properties": {
    "iso:country":"GB",
    "wof:name":"SP10 2LS",
    "wof:placetype":"postalcode"
},
  "geometry": {"coordinates":[-1.49237064169236,51.20292245355505],"type":"Point"}
}