{
  "type": "Feature",
  "properties": {
    "iso:country":"GB",
    "wof:name":"SW6 4LP",
    "wof:placetype":"postalcode"
},
  "geometry": {"coordinates":[-0.20431395838255,51.47221205755449],"type":"Point"}
}