{
  "type": "Feature",
  "properties": {
    "iso:country":"GB",
    "wof:name":"NG9 8BB",
    "wof:placetype":"postalcode"
},
  "geometry": {"coordinates":[-1.26192685041568,52.93414629135801],"type":"Point"}
}