{
  "type": "Feature",
  "properties": {
    "iso:country":"GB",
    "wof:name":"PE25 2JT",
    "wof:placetype":"postalcode"
},
  "geometry": {"coordinates":[0.31707374737219,53.15257811598204],"type":"Point"}
}