{
  "type": "Feature",
  "properties": {
    "iso:country":"GB",
    "wof:name":"MK3 7QN",
    "wof:placetype":"postalcode"
},
  "geometry": {"coordinates":[-0.76100266834962,52.00030635807603],"type":"Point"}
}