{
  "type": "Feature",
  "properties": {
    "iso:country":"GB",
    "wof:name":"IP4 4DU",
    "wof:placetype":"postalcode"
},
  "geometry": {"coordinates":[1.17967103585052,52.0610754335957],"type":"Point"}
}