{
  "type": "Feature",
  "properties": {
    "iso:country": "GB",
    "wof:name": "SA20 0AG",
    "wof:placetype": "postalcode"
  },
  "geometry": {"coordinates":[-3.804745,51.989725],"type":"Point"}
}
