{
  "type": "Feature",
  "properties": {
    "date:inception_lower": "2003-01-01",
    "date:inception_upper": "2003-01-01",
    "iso:country": "GB",
    "wof:name": "SA20 0AG",
    "wof:placetype": "postalcode"
  },
  "geometry": {"coordinates":[-3.804745,51.989725],"type":"Point"}
}
