{
  "type": "Feature",
  "properties": {
    "iso:country":"GB",
    "wof:name":"G52 3PH",
    "wof:placetype":"postalcode"
},
  "geometry": {"coordinates":[-4.3582134640901,55.84507801137354],"type":"Point"}
}