{
  "type": "Feature",
  "properties": {
    "iso:country": "GB",
    "wof:name": "LD6 5BU",
    "wof:placetype": "postalcode"
  },
  "geometry": {"coordinates":[-3.511103,52.301183],"type":"Point"}
}
