{
  "type": "Feature",
  "properties": {
    "iso:country":"GB",
    "wof:name":"LD6 5BU",
    "wof:placetype":"postalcode"
},
  "geometry": {"coordinates":[-3.51115588700998,52.30122415802574],"type":"Point"}
}