{
  "type": "Feature",
  "properties": {
    "date:inception_lower": "1984-10-01",
    "date:inception_upper": "1984-10-01",
    "iso:country": "GB",
    "wof:name": "LD6 5BU",
    "wof:placetype": "postalcode"
  },
  "geometry": {"coordinates":[-3.511103,52.301183],"type":"Point"}
}
