{
  "type": "Feature",
  "properties": {
    "iso:country":"GB",
    "wof:name":"TS6 0NW",
    "wof:placetype":"postalcode"
},
  "geometry": {"coordinates":[-1.14950464195613,54.54998368322516],"type":"Point"}
}