{
  "type": "Feature",
  "properties": {
    "iso:country":"GB",
    "wof:name":"SO19 9JN",
    "wof:placetype":"postalcode"
},
  "geometry": {"coordinates":[-1.36180076126608,50.88531442609669],"type":"Point"}
}