{
  "type": "Feature",
  "properties": {
    "iso:country":"GB",
    "wof:name":"MK2 2JA",
    "wof:placetype":"postalcode"
},
  "geometry": {"coordinates":[-0.71619149860199,51.99582543894991],"type":"Point"}
}