{
  "type": "Feature",
  "properties": {
    "iso:country":"GB",
    "wof:name":"TN29 0UD",
    "wof:placetype":"postalcode"
},
  "geometry": {"coordinates":[1.02924981065281,51.0484058370793],"type":"Point"}
}