{
  "type": "Feature",
  "properties": {
    "iso:country": "GB",
    "wof:name": "TN29 0UD",
    "wof:placetype": "postalcode"
  },
  "geometry": {"coordinates":[1.029721,51.048324],"type":"Point"}
}
