{
  "type": "Feature",
  "properties": {
    "date:inception_lower": "2019-03-01",
    "date:inception_upper": "2019-03-01",
    "iso:country": "GB",
    "wof:name": "BH21 3BZ",
    "wof:placetype": "postalcode"
  },
  "geometry": {"coordinates":[-2.020644,50.764478],"type":"Point"}
}
