{
  "type": "Feature",
  "properties": {
    "iso:country": "GB",
    "wof:name": "BH21 3BZ",
    "wof:placetype": "postalcode"
  },
  "geometry": {"coordinates":[-2.020644,50.764478],"type":"Point"}
}
