{
  "type": "Feature",
  "properties": {
    "iso:country":"GB",
    "wof:name":"SY5 8PP",
    "wof:placetype":"postalcode"
},
  "geometry": {"coordinates":[-2.84197020299691,52.6868012680407],"type":"Point"}
}