{
  "type": "Feature",
  "properties": {
    "iso:country":"GB",
    "wof:name":"SO21 2LD",
    "wof:placetype":"postalcode"
},
  "geometry": {"coordinates":[-1.40749233373533,51.00953362543778],"type":"Point"}
}