{
  "type": "Feature",
  "properties": {
    "iso:country": "GB",
    "wof:name": "CH62 5AS",
    "wof:placetype": "postalcode"
  },
  "geometry": {"coordinates":[-3.002447,53.364026],"type":"Point"}
}
