{
  "type": "Feature",
  "properties": {
    "iso:country":"GB",
    "wof:name":"CH62 5AS",
    "wof:placetype":"postalcode"
},
  "geometry": {"coordinates":[-3.00234225959525,53.36404531140936],"type":"Point"}
}