{
  "type": "Feature",
  "properties": {
    "iso:country":"GB",
    "wof:name":"DH5 0LQ",
    "wof:placetype":"postalcode"
},
  "geometry": {"coordinates":[-1.42861101524434,54.8048167219717],"type":"Point"}
}