{
  "type": "Feature",
  "properties": {
    "iso:country":"GB",
    "wof:name":"L11 2YE",
    "wof:placetype":"postalcode"
},
  "geometry": {"coordinates":[-2.90652517914814,53.44253852015176],"type":"Point"}
}