{
  "type": "Feature",
  "properties": {
    "iso:country":"GB",
    "wof:name":"CT17 0HF",
    "wof:placetype":"postalcode"
},
  "geometry": {"coordinates":[1.28922058775681,51.13184631331092],"type":"Point"}
}