{
  "type": "Feature",
  "properties": {
    "date:inception_lower": "2006-02-01",
    "date:inception_upper": "2006-02-01",
    "iso:country": "GB",
    "wof:name": "WS13 6UA",
    "wof:placetype": "postalcode"
  },
  "geometry": {"coordinates":[-1.840317,52.6755],"type":"Point"}
}
