{
  "type": "Feature",
  "properties": {
    "iso:country":"GB",
    "wof:name":"PO2 8BW",
    "wof:placetype":"postalcode"
},
  "geometry": {"coordinates":[-1.08231771922681,50.81921764893715],"type":"Point"}
}