{
  "type": "Feature",
  "properties": {
    "iso:country":"GB",
    "wof:name":"PE36 6DG",
    "wof:placetype":"postalcode"
},
  "geometry": {"coordinates":[0.49021782428947,52.94150569424743],"type":"Point"}
}