{
  "type": "Feature",
  "properties": {
    "iso:country": "GB",
    "wof:name": "CV21 2AF",
    "wof:placetype": "postalcode"
  },
  "geometry": {"coordinates":[-1.262921,52.374342],"type":"Point"}
}
