{
  "type": "Feature",
  "properties": {
    "iso:country": "GB",
    "wof:name": "B69 1UL",
    "wof:placetype": "postalcode"
  },
  "geometry": {"coordinates":[-2.053191,52.510642],"type":"Point"}
}
