{
  "type": "Feature",
  "properties": {
    "iso:country":"GB",
    "wof:name":"B69 1UL",
    "wof:placetype":"postalcode"
},
  "geometry": {"coordinates":[-2.05319152857972,52.51064181448398],"type":"Point"}
}