{
  "type": "Feature",
  "properties": {
    "iso:country": "GB",
    "wof:name": "SA43 2SL",
    "wof:placetype": "postalcode"
  },
  "geometry": {"coordinates":[-4.63164,52.054634],"type":"Point"}
}
