{
  "type": "Feature",
  "properties": {
    "iso:country":"GB",
    "wof:name":"NG7 6HQ",
    "wof:placetype":"postalcode"
},
  "geometry": {"coordinates":[-1.16583782790033,52.96928005970144],"type":"Point"}
}