{
  "type": "Feature",
  "properties": {
    "iso:country":"GB",
    "wof:name":"E9 6DE",
    "wof:placetype":"postalcode"
},
  "geometry": {"coordinates":[-0.04349843015578,51.55139975501015],"type":"Point"}
}