{
  "type": "Feature",
  "properties": {
    "iso:country":"GB",
    "wof:name":"PA2 8TB",
    "wof:placetype":"postalcode"
},
  "geometry": {"coordinates":[-4.42819738162421,55.81687818563302],"type":"Point"}
}