{
  "type": "Feature",
  "properties": {
    "iso:country": "GB",
    "wof:name": "PA2 8TB",
    "wof:placetype": "postalcode"
  },
  "geometry": {"coordinates":[-4.428197,55.816878],"type":"Point"}
}
