{
  "type": "Feature",
  "properties": {
    "date:inception_lower": "1980-01-01",
    "date:inception_upper": "1980-01-01",
    "iso:country": "GB",
    "wof:name": "HU10 7TH",
    "wof:placetype": "postalcode"
  },
  "geometry": {"coordinates":[-0.455695,53.754084],"type":"Point"}
}
