{
  "type": "Feature",
  "properties": {
    "iso:country":"GB",
    "wof:name":"HU10 7TH",
    "wof:placetype":"postalcode"
},
  "geometry": {"coordinates":[-0.4556954163585,53.7540844985403],"type":"Point"}
}