{
  "type": "Feature",
  "properties": {
    "iso:country":"GB",
    "wof:name":"BD22 9EZ",
    "wof:placetype":"postalcode"
},
  "geometry": {"coordinates":[-1.93945469187106,53.83598941079016],"type":"Point"}
}