{
  "type": "Feature",
  "properties": {
    "iso:country":"GB",
    "wof:name":"CF5 1DX",
    "wof:placetype":"postalcode"
},
  "geometry": {"coordinates":[-3.21805904436665,51.48824311540549],"type":"Point"}
}