{
  "type": "Feature",
  "properties": {
    "date:inception_lower":"2018-11-01",
    "date:inception_upper":"2018-11-30",
    "iso:country":"GB",
    "wof:name":"TF10 8PG",
    "wof:placetype":"postalcode"
},
  "geometry": {"coordinates":[-2.476189,52.774944],"type":"Point"}
}