{
  "type": "Feature",
  "properties": {
    "date:inception_lower": "2018-11-01",
    "date:inception_upper": "2018-11-01",
    "iso:country": "GB",
    "wof:name": "TF10 8PG",
    "wof:placetype": "postalcode"
  },
  "geometry": {"coordinates":[-2.476145,52.774971],"type":"Point"}
}
