{
  "type": "Feature",
  "properties": {
    "iso:country": "GB",
    "wof:name": "TF10 8PG",
    "wof:placetype": "postalcode"
  },
  "geometry": {"coordinates":[-2.476189,52.774944],"type":"Point"}
}
