{
  "type": "Feature",
  "properties": {
    "iso:country":"GB",
    "wof:name":"ST7 3LX",
    "wof:placetype":"postalcode"
},
  "geometry": {"coordinates":[-2.22971080056214,53.11259916241627],"type":"Point"}
}