{
  "type": "Feature",
  "properties": {
    "date:inception_lower":"2015-02-01",
    "date:inception_upper":"2015-02-28",
    "iso:country":"GB",
    "wof:name":"ST7 3LX",
    "wof:placetype":"postalcode"
},
  "geometry": {"coordinates":[-2.229711,53.112599],"type":"Point"}
}