{
  "type": "Feature",
  "properties": {
    "date:inception_lower":"2008-02-01",
    "date:inception_upper":"2008-02-29",
    "iso:country":"GB",
    "wof:name":"IG10 3FL",
    "wof:placetype":"postalcode"
},
  "geometry": {"coordinates":[0.085241,51.644729],"type":"Point"}
}