{
  "type": "Feature",
  "properties": {
    "iso:country":"GB",
    "wof:name":"EX13 8JT",
    "wof:placetype":"postalcode"
},
  "geometry": {"coordinates":[-3.00477336974243,50.7736754892172],"type":"Point"}
}