{
  "type": "Feature",
  "properties": {
    "iso:country":"GB",
    "wof:name":"NE34 7TD",
    "wof:placetype":"postalcode"
},
  "geometry": {"coordinates":[-1.40015254160384,54.98461570376636],"type":"Point"}
}