{
  "type": "Feature",
  "properties": {
    "iso:country":"GB",
    "wof:name":"BD23 6QL",
    "wof:placetype":"postalcode"
},
  "geometry": {"coordinates":[-1.99444481976598,53.97582752231601],"type":"Point"}
}