{
  "type": "Feature",
  "properties": {
    "iso:country":"GB",
    "wof:name":"CF37 3EN",
    "wof:placetype":"postalcode"
},
  "geometry": {"coordinates":[-3.3585923140633,51.63683731154965],"type":"Point"}
}