{
  "type": "Feature",
  "properties": {
    "iso:country": "GB",
    "wof:name": "NP20 2QX",
    "wof:placetype": "postalcode"
  },
  "geometry": {"coordinates":[-3.005927,51.574752],"type":"Point"}
}
