{
  "type": "Feature",
  "properties": {
    "iso:country": "GB",
    "wof:name": "SP5 3EQ",
    "wof:placetype": "postalcode"
  },
  "geometry": {"coordinates":[-1.72293,51.035633],"type":"Point"}
}
