{
  "type": "Feature",
  "properties": {
    "date:inception_lower": "2009-05-01",
    "date:inception_upper": "2009-05-01",
    "iso:country": "GB",
    "wof:name": "LN2 3HX",
    "wof:placetype": "postalcode"
  },
  "geometry": {"coordinates":[-0.475579,53.308803],"type":"Point"}
}
