{
  "type": "Feature",
  "properties": {
    "date:inception_lower": "1995-01-01",
    "date:inception_upper": "1995-01-01",
    "iso:country": "GB",
    "wof:name": "RH12 3DX",
    "wof:placetype": "postalcode"
  },
  "geometry": {"coordinates":[-0.45033,51.090896],"type":"Point"}
}
