{
  "type": "Feature",
  "properties": {
    "iso:country":"GB",
    "wof:name":"RH12 3DX",
    "wof:placetype":"postalcode"
},
  "geometry": {"coordinates":[-0.45032981115654,51.09089587608329],"type":"Point"}
}