{
  "type": "Feature",
  "properties": {
    "date:inception_lower": "2007-01-01",
    "date:inception_upper": "2007-01-01",
    "iso:country": "GB",
    "wof:name": "BB3 3BF",
    "wof:placetype": "postalcode"
  },
  "geometry": {"coordinates":[-2.458037,53.698358],"type":"Point"}
}
