{
  "type": "Feature",
  "properties": {
    "iso:country":"GB",
    "wof:name":"BB3 3BF",
    "wof:placetype":"postalcode"
},
  "geometry": {"coordinates":[-2.45803662764678,53.69835753363021],"type":"Point"}
}