{
  "type": "Feature",
  "properties": {
    "date:inception_lower":"1980-01-01",
    "date:inception_upper":"1980-01-31",
    "iso:country":"GB",
    "wof:name":"DN14 6QU",
    "wof:placetype":"postalcode"
},
  "geometry": {"coordinates":[-0.874871,53.714339],"type":"Point"}
}