{
  "type": "Feature",
  "properties": {
    "iso:country":"GB",
    "wof:name":"DN14 6QU",
    "wof:placetype":"postalcode"
},
  "geometry": {"coordinates":[-0.87487098032021,53.71433897997381],"type":"Point"}
}