{
  "type": "Feature",
  "properties": {
    "iso:country":"GB",
    "wof:name":"KY3 9SQ",
    "wof:placetype":"postalcode"
},
  "geometry": {"coordinates":[-3.17920006431238,56.0636182338555],"type":"Point"}
}