{
  "type": "Feature",
  "properties": {
    "iso:country": "GB",
    "wof:name": "KY3 9SQ",
    "wof:placetype": "postalcode"
  },
  "geometry": {"coordinates":[-3.178819,56.063185],"type":"Point"}
}
