{
  "type": "Feature",
  "properties": {
    "iso:country":"GB",
    "wof:name":"LD3 8NH",
    "wof:placetype":"postalcode"
},
  "geometry": {"coordinates":[-3.49086427553351,51.89869054831577],"type":"Point"}
}