{
  "type": "Feature",
  "properties": {
    "iso:country":"GB",
    "wof:name":"DN2 4ES",
    "wof:placetype":"postalcode"
},
  "geometry": {"coordinates":[-1.11991058553224,53.5364296682892],"type":"Point"}
}