{
  "type": "Feature",
  "properties": {
    "iso:country":"GB",
    "wof:name":"BD4 6QH",
    "wof:placetype":"postalcode"
},
  "geometry": {"coordinates":[-1.73288068286288,53.75320704141236],"type":"Point"}
}