{
  "type": "Feature",
  "properties": {
    "iso:country": "GB",
    "wof:name": "ML1 2QW",
    "wof:placetype": "postalcode"
  },
  "geometry": {"coordinates":[-3.98717,55.775531],"type":"Point"}
}
