{
  "type": "Feature",
  "properties": {
    "date:inception_lower": "1985-05-01",
    "date:inception_upper": "1985-05-01",
    "iso:country": "GB",
    "wof:name": "ML1 2QW",
    "wof:placetype": "postalcode"
  },
  "geometry": {"coordinates":[-3.98717,55.775531],"type":"Point"}
}
