{
  "type": "Feature",
  "properties": {
    "iso:country":"GB",
    "wof:name":"ML1 2QW",
    "wof:placetype":"postalcode"
},
  "geometry": {"coordinates":[-3.98717046899581,55.77553111044708],"type":"Point"}
}