{
  "type": "Feature",
  "properties": {
    "date:inception_lower": "2012-12-01",
    "date:inception_upper": "2012-12-01",
    "iso:country": "GB",
    "wof:name": "TA9 3GB",
    "wof:placetype": "postalcode"
  },
  "geometry": {"coordinates":[-2.973226,51.223744],"type":"Point"}
}
