{
  "type": "Feature",
  "properties": {
    "iso:country":"GB",
    "wof:name":"TA9 3GB",
    "wof:placetype":"postalcode"
},
  "geometry": {"coordinates":[-2.97321620020961,51.2237393768304],"type":"Point"}
}