{
  "type": "Feature",
  "properties": {
    "iso:country":"GB",
    "wof:name":"BH17 9DR",
    "wof:placetype":"postalcode"
},
  "geometry": {"coordinates":[-1.9721230064915,50.74991827852598],"type":"Point"}
}