{
  "type": "Feature",
  "properties": {
    "iso:country":"GB",
    "wof:name":"SW2 2NU",
    "wof:placetype":"postalcode"
},
  "geometry": {"coordinates":[-0.11391402821725,51.44538859298638],"type":"Point"}
}