{
  "type": "Feature",
  "properties": {
    "date:inception_lower":"1990-02-01",
    "date:inception_upper":"1990-02-28",
    "iso:country":"GB",
    "wof:name":"WD6 4PR",
    "wof:placetype":"postalcode"
},
  "geometry": {"coordinates":[-0.277805,51.656694],"type":"Point"}
}