{
  "type": "Feature",
  "properties": {
    "iso:country": "GB",
    "wof:name": "WD6 4PR",
    "wof:placetype": "postalcode"
  },
  "geometry": {"coordinates":[-0.277805,51.656694],"type":"Point"}
}
