{
  "type": "Feature",
  "properties": {
    "date:inception_lower": "1980-01-01",
    "date:inception_upper": "1980-01-01",
    "iso:country": "GB",
    "wof:name": "W3 7TU",
    "wof:placetype": "postalcode"
  },
  "geometry": {"coordinates":[-0.256932,51.5159],"type":"Point"}
}
