{
  "type": "Feature",
  "properties": {
    "iso:country":"GB",
    "wof:name":"TF9 1GA",
    "wof:placetype":"postalcode"
},
  "geometry": {"coordinates":[-2.47547760560495,52.90652065024137],"type":"Point"}
}