{
  "type": "Feature",
  "properties": {
    "iso:country":"GB",
    "wof:name":"SS3 9HG",
    "wof:placetype":"postalcode"
},
  "geometry": {"coordinates":[0.77406386575825,51.52390375878188],"type":"Point"}
}