{
  "type": "Feature",
  "properties": {
    "iso:country": "GB",
    "wof:name": "B46 2AG",
    "wof:placetype": "postalcode"
  },
  "geometry": {"coordinates":[-1.683352,52.514625],"type":"Point"}
}
