{
  "type": "Feature",
  "properties": {
    "iso:country":"GB",
    "wof:name":"B46 2AG",
    "wof:placetype":"postalcode"
},
  "geometry": {"coordinates":[-1.68337503197337,52.51460016825276],"type":"Point"}
}