{
  "type": "Feature",
  "properties": {
    "date:inception_lower": "1980-01-01",
    "date:inception_upper": "1980-01-01",
    "iso:country": "GB",
    "wof:name": "B46 2AG",
    "wof:placetype": "postalcode"
  },
  "geometry": {"coordinates":[-1.683352,52.514625],"type":"Point"}
}
