{
  "type": "Feature",
  "properties": {
    "iso:country":"GB",
    "wof:name":"PR26 6QX",
    "wof:placetype":"postalcode"
},
  "geometry": {"coordinates":[-2.71034541482575,53.70221397567109],"type":"Point"}
}