{
  "type": "Feature",
  "properties": {
    "date:inception_lower":"1980-01-01",
    "date:inception_upper":"1980-01-31",
    "iso:country":"GB",
    "wof:name":"GL53 8QH",
    "wof:placetype":"postalcode"
},
  "geometry": {"coordinates":[-2.042114,51.882964],"type":"Point"}
}