{
  "type": "Feature",
  "properties": {
    "date:inception_lower":"1980-01-01",
    "date:inception_upper":"1980-01-31",
    "iso:country":"GB",
    "wof:name":"B70 7NN",
    "wof:placetype":"postalcode"
},
  "geometry": {"coordinates":[-1.993186,52.517582],"type":"Point"}
}