{
  "type": "Feature",
  "properties": {
    "iso:country":"GB",
    "wof:name":"B70 7NN",
    "wof:placetype":"postalcode"
},
  "geometry": {"coordinates":[-1.99322175765008,52.51752199531557],"type":"Point"}
}