{
  "type": "Feature",
  "properties": {
    "iso:country": "GB",
    "wof:name": "WA13 9TY",
    "wof:placetype": "postalcode"
  },
  "geometry": {"coordinates":[-2.417933,53.410991],"type":"Point"}
}
