{
  "type": "Feature",
  "properties": {
    "date:inception_lower": "1980-01-01",
    "date:inception_upper": "1980-01-01",
    "iso:country": "GB",
    "wof:name": "WA13 9TY",
    "wof:placetype": "postalcode"
  },
  "geometry": {"coordinates":[-2.421421,53.41079],"type":"Point"}
}
