{
  "type": "Feature",
  "properties": {
    "iso:country":"GB",
    "wof:name":"WA13 9TY",
    "wof:placetype":"postalcode"
},
  "geometry": {"coordinates":[-2.42142221543539,53.41077351005607],"type":"Point"}
}