{
  "type": "Feature",
  "properties": {
    "date:inception_lower": "1986-07-01",
    "date:inception_upper": "1986-07-01",
    "iso:country": "GB",
    "wof:name": "BN17 6SH",
    "wof:placetype": "postalcode"
  },
  "geometry": {"coordinates":[-0.51821,50.817977],"type":"Point"}
}
