{
  "type": "Feature",
  "properties": {
    "iso:country": "GB",
    "wof:name": "NE27 9BY",
    "wof:placetype": "postalcode"
  },
  "geometry": {"coordinates":[-1.490343,55.018212],"type":"Point"}
}
