{
  "type": "Feature",
  "properties": {
    "iso:country":"GB",
    "wof:name":"PH16 5PR",
    "wof:placetype":"postalcode"
},
  "geometry": {"coordinates":[-4.19138049222467,56.70007610585144],"type":"Point"}
}