{
  "type": "Feature",
  "properties": {
    "date:inception_lower": "1980-01-01",
    "date:inception_upper": "1980-01-01",
    "iso:country": "GB",
    "wof:name": "PH16 5PR",
    "wof:placetype": "postalcode"
  },
  "geometry": {"coordinates":[-4.19138,56.700076],"type":"Point"}
}
