{
  "type": "Feature",
  "properties": {
    "iso:country":"GB",
    "wof:name":"CV4 9PS",
    "wof:placetype":"postalcode"
},
  "geometry": {"coordinates":[-1.58551548324926,52.41104746906891],"type":"Point"}
}