{
  "type": "Feature",
  "properties": {
    "iso:country":"GB",
    "wof:name":"BB5 0LU",
    "wof:placetype":"postalcode"
},
  "geometry": {"coordinates":[-2.37705322478346,53.74433561345694],"type":"Point"}
}