{
  "type": "Feature",
  "properties": {
    "iso:country":"GB",
    "wof:name":"CR2 6FL",
    "wof:placetype":"postalcode"
},
  "geometry": {"coordinates":[-0.10728292307146,51.36313344230307],"type":"Point"}
}