{
  "type": "Feature",
  "properties": {
    "iso:country":"GB",
    "wof:name":"CA20 1HP",
    "wof:placetype":"postalcode"
},
  "geometry": {"coordinates":[-3.44620633179199,54.41304710826657],"type":"Point"}
}