{
  "type": "Feature",
  "properties": {
    "iso:country":"GB",
    "wof:name":"BD12 9HR",
    "wof:placetype":"postalcode"
},
  "geometry": {"coordinates":[-1.75970950554235,53.74509362433082],"type":"Point"}
}