{
  "type": "Feature",
  "properties": {
    "iso:country": "GB",
    "wof:name": "BD12 9HR",
    "wof:placetype": "postalcode"
  },
  "geometry": {"coordinates":[-1.759709,53.745094],"type":"Point"}
}
