{
  "type": "Feature",
  "properties": {
    "iso:country": "GB",
    "wof:name": "LS10 1SD",
    "wof:placetype": "postalcode"
  },
  "geometry": {"coordinates":[-1.504111,53.7672],"type":"Point"}
}
