{
  "type": "Feature",
  "properties": {
    "date:inception_lower": "2023-08-01",
    "date:inception_upper": "2023-08-01",
    "iso:country": "GB",
    "wof:name": "LA1 5XW",
    "wof:placetype": "postalcode"
  },
  "geometry": {"coordinates":[-2.826017,54.048226],"type":"Point"}
}
