{
  "type": "Feature",
  "properties": {
    "iso:country":"GB",
    "wof:name":"SA19 9YE",
    "wof:placetype":"postalcode"
},
  "geometry": {"coordinates":[-3.79668462491892,51.91604289234837],"type":"Point"}
}