{
  "type": "Feature",
  "properties": {
    "iso:country":"GB",
    "wof:name":"TA4 1LW",
    "wof:placetype":"postalcode"
},
  "geometry": {"coordinates":[-3.25704283896301,51.02629251920109],"type":"Point"}
}