{
  "type": "Feature",
  "properties": {
    "date:inception_lower":"1980-01-01",
    "date:inception_upper":"1980-01-31",
    "iso:country":"GB",
    "wof:name":"B79 7HE",
    "wof:placetype":"postalcode"
},
  "geometry": {"coordinates":[-1.692446,52.633758],"type":"Point"}
}