{
  "type": "Feature",
  "properties": {
    "date:inception_lower": "1980-01-01",
    "date:inception_upper": "1980-01-01",
    "iso:country": "GB",
    "wof:name": "B79 7HE",
    "wof:placetype": "postalcode"
  },
  "geometry": {"coordinates":[-1.692483,52.633757],"type":"Point"}
}
