{
  "type": "Feature",
  "properties": {
    "iso:country":"GB",
    "wof:name":"B79 7HE",
    "wof:placetype":"postalcode"
},
  "geometry": {"coordinates":[-1.69244554496309,52.63375752445587],"type":"Point"}
}