{
  "type": "Feature",
  "properties": {
    "iso:country":"GB",
    "wof:name":"IG1 4AN",
    "wof:placetype":"postalcode"
},
  "geometry": {"coordinates":[0.09035929999867,51.56490921012875],"type":"Point"}
}