{
  "type": "Feature",
  "properties": {
    "iso:country":"GB",
    "wof:name":"TN28 8TW",
    "wof:placetype":"postalcode"
},
  "geometry": {"coordinates":[0.944242023083,50.9925551678182],"type":"Point"}
}