{
  "type": "Feature",
  "properties": {
    "iso:country":"GB",
    "wof:name":"DD5 3PY",
    "wof:placetype":"postalcode"
},
  "geometry": {"coordinates":[-2.81563718939501,56.51886846436964],"type":"Point"}
}