{
  "type": "Feature",
  "properties": {
    "date:inception_lower": "1980-01-01",
    "date:inception_upper": "1980-01-01",
    "iso:country": "GB",
    "wof:name": "DD5 3PY",
    "wof:placetype": "postalcode"
  },
  "geometry": {"coordinates":[-2.811735,56.520115],"type":"Point"}
}
