{
  "type": "Feature",
  "properties": {
    "iso:country": "GB",
    "wof:name": "DD5 3PY",
    "wof:placetype": "postalcode"
  },
  "geometry": {"coordinates":[-2.811735,56.520115],"type":"Point"}
}
