{
  "type": "Feature",
  "properties": {
    "date:inception_lower": "2016-10-01",
    "date:inception_upper": "2016-10-01",
    "iso:country": "GB",
    "wof:name": "TF11 8FW",
    "wof:placetype": "postalcode"
  },
  "geometry": {"coordinates":[-2.373942,52.675292],"type":"Point"}
}
