{
  "type": "Feature",
  "properties": {
    "iso:country":"GB",
    "wof:name":"W1H 5BD",
    "wof:placetype":"postalcode"
},
  "geometry": {"coordinates":[-0.16141746440481,51.51486417953931],"type":"Point"}
}