{
  "type": "Feature",
  "properties": {
    "iso:country":"GB",
    "wof:name":"NE28 9AU",
    "wof:placetype":"postalcode"
},
  "geometry": {"coordinates":[-1.52415219187716,55.00678463310073],"type":"Point"}
}