{
  "type": "Feature",
  "properties": {
    "iso:country":"GB",
    "wof:name":"L19 2RU",
    "wof:placetype":"postalcode"
},
  "geometry": {"coordinates":[-2.88752894700761,53.35238799080341],"type":"Point"}
}