{
  "type": "Feature",
  "properties": {
    "iso:country":"GB",
    "wof:name":"RH13 9XW",
    "wof:placetype":"postalcode"
},
  "geometry": {"coordinates":[-0.34611337713167,51.02727290765783],"type":"Point"}
}