{
  "type": "Feature",
  "properties": {
    "iso:country":"GB",
    "wof:name":"CF15 7QF",
    "wof:placetype":"postalcode"
},
  "geometry": {"coordinates":[-3.27153579101014,51.5486946111465],"type":"Point"}
}