{
  "type": "Feature",
  "properties": {
    "date:inception_lower": "1999-06-01",
    "date:inception_upper": "1999-06-01",
    "iso:country": "GB",
    "wof:name": "CF15 7QF",
    "wof:placetype": "postalcode"
  },
  "geometry": {"coordinates":[-3.271536,51.548695],"type":"Point"}
}
