{
  "type": "Feature",
  "properties": {
    "iso:country":"GB",
    "wof:name":"SK23 7DY",
    "wof:placetype":"postalcode"
},
  "geometry": {"coordinates":[-1.99218529128076,53.31547440896695],"type":"Point"}
}