{
  "type": "Feature",
  "properties": {
    "iso:country":"GB",
    "wof:name":"GU17 0DY",
    "wof:placetype":"postalcode"
},
  "geometry": {"coordinates":[-0.79905443012117,51.33514683980788],"type":"Point"}
}