{
  "type": "Feature",
  "properties": {
    "iso:country":"GB",
    "wof:name":"HR5 3ET",
    "wof:placetype":"postalcode"
},
  "geometry": {"coordinates":[-3.04630316826305,52.17317797504428],"type":"Point"}
}