{
  "type": "Feature",
  "properties": {
    "iso:country":"GB",
    "wof:name":"NE5 2TL",
    "wof:placetype":"postalcode"
},
  "geometry": {"coordinates":[-1.67994622820615,54.98821608259374],"type":"Point"}
}