{
  "type": "Feature",
  "properties": {
    "iso:country": "GB",
    "wof:name": "TA4 1PW",
    "wof:placetype": "postalcode"
  },
  "geometry": {"coordinates":[-3.248885,51.024635],"type":"Point"}
}
