{
  "type": "Feature",
  "properties": {
    "date:inception_lower": "1999-06-01",
    "date:inception_upper": "1999-06-01",
    "iso:country": "GB",
    "wof:name": "SW4 6EL",
    "wof:placetype": "postalcode"
  },
  "geometry": {"coordinates":[-0.132771,51.464396],"type":"Point"}
}
