{
  "type": "Feature",
  "properties": {
    "iso:country":"GB",
    "wof:name":"SW4 6EL",
    "wof:placetype":"postalcode"
},
  "geometry": {"coordinates":[-0.13272397169269,51.4644033229775],"type":"Point"}
}