{
  "type": "Feature",
  "properties": {
    "date:inception_lower":"1993-08-01",
    "date:inception_upper":"1993-08-31",
    "iso:country":"GB",
    "wof:name":"SY21 8JF",
    "wof:placetype":"postalcode"
},
  "geometry": {"coordinates":[-3.1081,52.668732],"type":"Point"}
}