{
  "type": "Feature",
  "properties": {
    "iso:country": "GB",
    "wof:name": "SY21 8JF",
    "wof:placetype": "postalcode"
  },
  "geometry": {"coordinates":[-3.1081,52.668732],"type":"Point"}
}
