{
  "type": "Feature",
  "properties": {
    "iso:country":"GB",
    "wof:name":"SY21 8JF",
    "wof:placetype":"postalcode"
},
  "geometry": {"coordinates":[-3.10793784836958,52.66863773325125],"type":"Point"}
}