{
  "type": "Feature",
  "properties": {
    "iso:country":"GB",
    "wof:name":"OL2 7YQ",
    "wof:placetype":"postalcode"
},
  "geometry": {"coordinates":[-2.10088251091436,53.58574246314708],"type":"Point"}
}