{
  "type": "Feature",
  "properties": {
    "iso:country":"GB",
    "wof:name":"NR16 2SQ",
    "wof:placetype":"postalcode"
},
  "geometry": {"coordinates":[0.91898559741343,52.43248283167329],"type":"Point"}
}