{
  "type": "Feature",
  "properties": {
    "iso:country": "GB",
    "wof:name": "NR16 2SQ",
    "wof:placetype": "postalcode"
  },
  "geometry": {"coordinates":[0.918872,52.432549],"type":"Point"}
}
