{
  "type": "Feature",
  "properties": {
    "iso:country":"GB",
    "wof:name":"BA1 8HA",
    "wof:placetype":"postalcode"
},
  "geometry": {"coordinates":[-2.32096466082466,51.4303630503127],"type":"Point"}
}