{
  "type": "Feature",
  "properties": {
    "date:inception_lower": "2013-03-01",
    "date:inception_upper": "2013-03-01",
    "iso:country": "GB",
    "wof:name": "WS3 1EB",
    "wof:placetype": "postalcode"
  },
  "geometry": {"coordinates":[-1.985543,52.613137],"type":"Point"}
}
