{
  "type": "Feature",
  "properties": {
    "iso:country": "GB",
    "wof:name": "WS3 1EB",
    "wof:placetype": "postalcode"
  },
  "geometry": {"coordinates":[-1.985543,52.613137],"type":"Point"}
}
