{
  "type": "Feature",
  "properties": {
    "iso:country":"GB",
    "wof:name":"WS3 1EB",
    "wof:placetype":"postalcode"
},
  "geometry": {"coordinates":[-1.98554261176559,52.61313712797477],"type":"Point"}
}