{
  "type": "Feature",
  "properties": {
    "iso:country": "GB",
    "wof:name": "TW13 4PA",
    "wof:placetype": "postalcode"
  },
  "geometry": {"coordinates":[-0.418752,51.438989],"type":"Point"}
}
