{
  "type": "Feature",
  "properties": {
    "iso:country":"GB",
    "wof:name":"TR13 8SW",
    "wof:placetype":"postalcode"
},
  "geometry": {"coordinates":[-5.27001087702699,50.09855966996682],"type":"Point"}
}