{
  "type": "Feature",
  "properties": {
    "iso:country": "GB",
    "wof:name": "TR13 8SW",
    "wof:placetype": "postalcode"
  },
  "geometry": {"coordinates":[-5.270062,50.098548],"type":"Point"}
}
