{
  "type": "Feature",
  "properties": {
    "iso:country":"GB",
    "wof:name":"BN8 6JA",
    "wof:placetype":"postalcode"
},
  "geometry": {"coordinates":[0.17729120680716,50.89487573856415],"type":"Point"}
}