{
  "type": "Feature",
  "properties": {
    "iso:country": "GB",
    "wof:name": "BN8 6JA",
    "wof:placetype": "postalcode"
  },
  "geometry": {"coordinates":[0.177291,50.894876],"type":"Point"}
}
