{
  "type": "Feature",
  "properties": {
    "iso:country":"GB",
    "wof:name":"CH1 5RS",
    "wof:placetype":"postalcode"
},
  "geometry": {"coordinates":[-2.93451972356238,53.20035635561075],"type":"Point"}
}