{
  "type": "Feature",
  "properties": {
    "iso:country": "GB",
    "wof:name": "CH1 5RS",
    "wof:placetype": "postalcode"
  },
  "geometry": {"coordinates":[-2.93452,53.200356],"type":"Point"}
}
