{
  "type": "Feature",
  "properties": {
    "date:inception_lower": "1995-07-01",
    "date:inception_upper": "1995-07-01",
    "iso:country": "GB",
    "wof:name": "SS14 1TY",
    "wof:placetype": "postalcode"
  },
  "geometry": {"coordinates":[0.493254,51.566769],"type":"Point"}
}
