{
  "type": "Feature",
  "properties": {
    "iso:country":"GB",
    "wof:name":"SS14 1TY",
    "wof:placetype":"postalcode"
},
  "geometry": {"coordinates":[0.49325433385016,51.56676882506219],"type":"Point"}
}