{
  "type": "Feature",
  "properties": {
    "iso:country": "GB",
    "wof:name": "CM77 6BY",
    "wof:placetype": "postalcode"
  },
  "geometry": {"coordinates":[0.508618,51.879186],"type":"Point"}
}
