{
  "type": "Feature",
  "properties": {
    "iso:country":"GB",
    "wof:name":"CM77 6BY",
    "wof:placetype":"postalcode"
},
  "geometry": {"coordinates":[0.50861793529439,51.87918598207484],"type":"Point"}
}