{
  "type": "Feature",
  "properties": {
    "date:inception_lower":"2015-02-01",
    "date:inception_upper":"2015-02-28",
    "iso:country":"GB",
    "wof:name":"DH1 1NS",
    "wof:placetype":"postalcode"
},
  "geometry": {"coordinates":[-1.517662,54.791211],"type":"Point"}
}