{
  "type": "Feature",
  "properties": {
    "iso:country":"GB",
    "wof:name":"DH1 1NS",
    "wof:placetype":"postalcode"
},
  "geometry": {"coordinates":[-1.51722849095805,54.79136206344376],"type":"Point"}
}