{
  "type": "Feature",
  "properties": {
    "iso:country":"GB",
    "wof:name":"BB8 7QE",
    "wof:placetype":"postalcode"
},
  "geometry": {"coordinates":[-2.16600804159702,53.87901318198653],"type":"Point"}
}