{
  "type": "Feature",
  "properties": {
    "iso:country":"GB",
    "wof:name":"ML6 7AE",
    "wof:placetype":"postalcode"
},
  "geometry": {"coordinates":[-3.95424966545372,55.8679408006584],"type":"Point"}
}