{
  "type": "Feature",
  "properties": {
    "iso:country":"GB",
    "wof:name":"DA12 2DL",
    "wof:placetype":"postalcode"
},
  "geometry": {"coordinates":[0.37511254745124,51.44344157998866],"type":"Point"}
}