{
  "type": "Feature",
  "properties": {
    "iso:country": "GB",
    "wof:name": "NG31 0AG",
    "wof:placetype": "postalcode"
  },
  "geometry": {"coordinates":[-0.64064,52.909668],"type":"Point"}
}
