{
  "type": "Feature",
  "properties": {
    "iso:country":"GB",
    "wof:name":"DD3 9EU",
    "wof:placetype":"postalcode"
},
  "geometry": {"coordinates":[-3.00139913400678,56.4946174060409],"type":"Point"}
}