{
  "type": "Feature",
  "properties": {
    "iso:country":"GB",
    "wof:name":"GU8 6LQ",
    "wof:placetype":"postalcode"
},
  "geometry": {"coordinates":[-0.70984196061862,51.18290240209215],"type":"Point"}
}