{
  "type": "Feature",
  "properties": {
    "date:inception_lower": "1980-01-01",
    "date:inception_upper": "1980-01-01",
    "iso:country": "GB",
    "wof:name": "GU8 6LQ",
    "wof:placetype": "postalcode"
  },
  "geometry": {"coordinates":[-0.709842,51.182902],"type":"Point"}
}
