{
  "type": "Feature",
  "properties": {
    "iso:country": "GB",
    "wof:name": "NW10 7XT",
    "wof:placetype": "postalcode"
  },
  "geometry": {"coordinates":[-0.271047,51.532529],"type":"Point"}
}
