{
  "type": "Feature",
  "properties": {
    "iso:country":"GB",
    "wof:name":"GL2 4RA",
    "wof:placetype":"postalcode"
},
  "geometry": {"coordinates":[-2.28433463742738,51.8124441644214],"type":"Point"}
}