{
  "type": "Feature",
  "properties": {
    "date:inception_lower": "2011-07-01",
    "date:inception_upper": "2011-07-01",
    "iso:country": "GB",
    "wof:name": "SS14 3SN",
    "wof:placetype": "postalcode"
  },
  "geometry": {"coordinates":[0.487635,51.574317],"type":"Point"}
}
