{
  "type": "Feature",
  "properties": {
    "iso:country":"GB",
    "wof:name":"OX16 0NU",
    "wof:placetype":"postalcode"
},
  "geometry": {"coordinates":[-1.36749770178884,52.06771683995397],"type":"Point"}
}