{
  "type": "Feature",
  "properties": {
    "date:inception_lower": "1980-01-01",
    "date:inception_upper": "1980-01-01",
    "iso:country": "GB",
    "wof:name": "IP7 6BY",
    "wof:placetype": "postalcode"
  },
  "geometry": {"coordinates":[0.95095,52.046799],"type":"Point"}
}
