{
  "type": "Feature",
  "properties": {
    "iso:country": "GB",
    "wof:name": "AB38 7RT",
    "wof:placetype": "postalcode"
  },
  "geometry": {"coordinates":[-3.34409,57.457144],"type":"Point"}
}
