{
  "type": "Feature",
  "properties": {
    "date:inception_lower": "1990-09-01",
    "date:inception_upper": "1990-09-01",
    "iso:country": "GB",
    "wof:name": "AB38 7RT",
    "wof:placetype": "postalcode"
  },
  "geometry": {"coordinates":[-3.34409,57.457144],"type":"Point"}
}
