{
  "type": "Feature",
  "properties": {
    "iso:country": "GB",
    "wof:name": "CV12 9JD",
    "wof:placetype": "postalcode"
  },
  "geometry": {"coordinates":[-1.423598,52.47624],"type":"Point"}
}
