{
  "type": "Feature",
  "properties": {
    "iso:country":"GB",
    "wof:name":"CV12 9JD",
    "wof:placetype":"postalcode"
},
  "geometry": {"coordinates":[-1.42359854381642,52.47624004027507],"type":"Point"}
}