{
  "type": "Feature",
  "properties": {
    "iso:country": "GB",
    "wof:name": "ME13 0SQ",
    "wof:placetype": "postalcode"
  },
  "geometry": {"coordinates":[0.82261,51.303339],"type":"Point"}
}
