{
  "type": "Feature",
  "properties": {
    "iso:country":"GB",
    "wof:name":"ME13 0SQ",
    "wof:placetype":"postalcode"
},
  "geometry": {"coordinates":[0.82262332861309,51.30336269625202],"type":"Point"}
}