{
  "type": "Feature",
  "properties": {
    "iso:country":"GB",
    "wof:name":"CV10 0EA",
    "wof:placetype":"postalcode"
},
  "geometry": {"coordinates":[-1.46353494122622,52.53494382173773],"type":"Point"}
}