{
  "type": "Feature",
  "properties": {
    "iso:country":"GB",
    "wof:name":"BR5 3DT",
    "wof:placetype":"postalcode"
},
  "geometry": {"coordinates":[0.10513143518295,51.41287293751701],"type":"Point"}
}