{
  "type": "Feature",
  "properties": {
    "iso:country": "GB",
    "wof:name": "OX2 8PY",
    "wof:placetype": "postalcode"
  },
  "geometry": {"coordinates":[-1.307003,51.788846],"type":"Point"}
}
