{
  "type": "Feature",
  "properties": {
    "date:inception_lower": "1995-01-01",
    "date:inception_upper": "1995-01-01",
    "iso:country": "GB",
    "wof:name": "BD8 8BX",
    "wof:placetype": "postalcode"
  },
  "geometry": {"coordinates":[-1.773293,53.805345],"type":"Point"}
}
