{
  "type": "Feature",
  "properties": {
    "iso:country": "GB",
    "wof:name": "NG23 5LR",
    "wof:placetype": "postalcode"
  },
  "geometry": {"coordinates":[-0.893736,53.006389],"type":"Point"}
}
