{
  "type": "Feature",
  "properties": {
    "iso:country": "GB",
    "wof:name": "OL9 6AE",
    "wof:placetype": "postalcode"
  },
  "geometry": {"coordinates":[-2.124896,53.544237],"type":"Point"}
}
