{
  "type": "Feature",
  "properties": {
    "date:inception_lower": "2013-02-01",
    "date:inception_upper": "2013-02-01",
    "iso:country": "GB",
    "wof:name": "OL9 6AE",
    "wof:placetype": "postalcode"
  },
  "geometry": {"coordinates":[-2.124896,53.544237],"type":"Point"}
}
