{
  "type": "Feature",
  "properties": {
    "iso:country":"GB",
    "wof:name":"OL9 6AE",
    "wof:placetype":"postalcode"
},
  "geometry": {"coordinates":[-2.12480805557502,53.54420282692643],"type":"Point"}
}