{
  "type": "Feature",
  "properties": {
    "iso:country": "GB",
    "wof:name": "SK4 3AT",
    "wof:placetype": "postalcode"
  },
  "geometry": {"coordinates":[-2.211329,53.415025],"type":"Point"}
}
