{
  "type": "Feature",
  "properties": {
    "iso:country":"GB",
    "wof:name":"SK4 3AT",
    "wof:placetype":"postalcode"
},
  "geometry": {"coordinates":[-2.21132907251933,53.41502482669806],"type":"Point"}
}