{
  "type": "Feature",
  "properties": {
    "iso:country":"GB",
    "wof:name":"CH62 6AS",
    "wof:placetype":"postalcode"
},
  "geometry": {"coordinates":[-2.96967456269764,53.32444899034184],"type":"Point"}
}