{
  "type": "Feature",
  "properties": {
    "iso:country": "GB",
    "wof:name": "CH62 6AS",
    "wof:placetype": "postalcode"
  },
  "geometry": {"coordinates":[-2.969675,53.324449],"type":"Point"}
}
