{
  "type": "Feature",
  "properties": {
    "iso:country":"GB",
    "wof:name":"SE5 8SN",
    "wof:placetype":"postalcode"
},
  "geometry": {"coordinates":[-0.08708535191208,51.46959369916178],"type":"Point"}
}