{
  "type": "Feature",
  "properties": {
    "date:inception_lower": "2007-01-01",
    "date:inception_upper": "2007-01-01",
    "iso:country": "GB",
    "wof:name": "SE1 3TN",
    "wof:placetype": "postalcode"
  },
  "geometry": {"coordinates":[-0.080136,51.499318],"type":"Point"}
}
