{
  "type": "Feature",
  "properties": {
    "iso:country":"GB",
    "wof:name":"IV12 4TB",
    "wof:placetype":"postalcode"
},
  "geometry": {"coordinates":[-3.88470655561041,57.57885132602023],"type":"Point"}
}