{
  "type": "Feature",
  "properties": {
    "date:inception_lower": "1980-01-01",
    "date:inception_upper": "1980-01-01",
    "iso:country": "GB",
    "wof:name": "IV12 4TB",
    "wof:placetype": "postalcode"
  },
  "geometry": {"coordinates":[-3.884706,57.578851],"type":"Point"}
}
