{
  "type": "Feature",
  "properties": {
    "iso:country": "GB",
    "wof:name": "IV12 4TB",
    "wof:placetype": "postalcode"
  },
  "geometry": {"coordinates":[-3.884706,57.578851],"type":"Point"}
}
