{
  "type": "Feature",
  "properties": {
    "iso:country":"GB",
    "wof:name":"OX7 3LE",
    "wof:placetype":"postalcode"
},
  "geometry": {"coordinates":[-1.48055683290546,51.88762558621572],"type":"Point"}
}