{
  "type": "Feature",
  "properties": {
    "date:inception_lower": "1980-01-01",
    "date:inception_upper": "1980-01-01",
    "iso:country": "GB",
    "wof:name": "DH1 3QW",
    "wof:placetype": "postalcode"
  },
  "geometry": {"coordinates":[-1.597608,54.767032],"type":"Point"}
}
