{
  "type": "Feature",
  "properties": {
    "iso:country":"GB",
    "wof:name":"DH1 3QW",
    "wof:placetype":"postalcode"
},
  "geometry": {"coordinates":[-1.59760825620174,54.76703187504744],"type":"Point"}
}