{
  "type": "Feature",
  "properties": {
    "iso:country":"GB",
    "wof:name":"SW6 7RG",
    "wof:placetype":"postalcode"
},
  "geometry": {"coordinates":[-0.21285316461094,51.48177562863422],"type":"Point"}
}