{
  "type": "Feature",
  "properties": {
    "iso:country":"GB",
    "wof:name":"EN6 2PY",
    "wof:placetype":"postalcode"
},
  "geometry": {"coordinates":[-0.1838421060194,51.69222760161606],"type":"Point"}
}