{
  "type": "Feature",
  "properties": {
    "iso:country": "GB",
    "wof:name": "EN6 2PY",
    "wof:placetype": "postalcode"
  },
  "geometry": {"coordinates":[-0.183842,51.692228],"type":"Point"}
}
