{
  "type": "Feature",
  "properties": {
    "iso:country":"GB",
    "wof:name":"SS4 3PE",
    "wof:placetype":"postalcode"
},
  "geometry": {"coordinates":[0.74383086028131,51.61710633899519],"type":"Point"}
}