{
  "type": "Feature",
  "properties": {
    "date:inception_lower": "1980-01-01",
    "date:inception_upper": "1980-01-01",
    "iso:country": "GB",
    "wof:name": "SS4 3PE",
    "wof:placetype": "postalcode"
  },
  "geometry": {"coordinates":[0.743831,51.617106],"type":"Point"}
}
