{
  "type": "Feature",
  "properties": {
    "iso:country": "GB",
    "wof:name": "SS4 3PE",
    "wof:placetype": "postalcode"
  },
  "geometry": {"coordinates":[0.743831,51.617106],"type":"Point"}
}
