{
  "type": "Feature",
  "properties": {
    "date:inception_lower":"2004-09-01",
    "date:inception_upper":"2004-09-30",
    "iso:country":"GB",
    "wof:name":"SK8 7GJ",
    "wof:placetype":"postalcode"
},
  "geometry": {"coordinates":[-2.183762,53.37215],"type":"Point"}
}