{
  "type": "Feature",
  "properties": {
    "iso:country":"GB",
    "wof:name":"TS25 1UP",
    "wof:placetype":"postalcode"
},
  "geometry": {"coordinates":[-1.21000316050995,54.67699373209506],"type":"Point"}
}