{
  "type": "Feature",
  "properties": {
    "iso:country": "GB",
    "wof:name": "IP8 4DG",
    "wof:placetype": "postalcode"
  },
  "geometry": {"coordinates":[1.106327,52.092063],"type":"Point"}
}
