{
  "type": "Feature",
  "properties": {
    "iso:country":"GB",
    "wof:name":"IP8 4DG",
    "wof:placetype":"postalcode"
},
  "geometry": {"coordinates":[1.10629732213874,52.09204784129012],"type":"Point"}
}