{
  "type": "Feature",
  "properties": {
    "iso:country":"GB",
    "wof:name":"E14 9PU",
    "wof:placetype":"postalcode"
},
  "geometry": {"coordinates":[-0.00515453944096,51.50894722918162],"type":"Point"}
}