{
  "type": "Feature",
  "properties": {
    "iso:country":"GB",
    "wof:name":"EC1M 4DE",
    "wof:placetype":"postalcode"
},
  "geometry": {"coordinates":[-0.10331858996474,51.52219420720745],"type":"Point"}
}