{
  "type": "Feature",
  "properties": {
    "iso:country": "GB",
    "wof:name": "HA2 6FA",
    "wof:placetype": "postalcode"
  },
  "geometry": {"coordinates":[-0.351238,51.59495],"type":"Point"}
}
