{
  "type": "Feature",
  "properties": {
    "iso:country": "GB",
    "wof:name": "CH43 5RT",
    "wof:placetype": "postalcode"
  },
  "geometry": {"coordinates":[-3.038093,53.380728],"type":"Point"}
}
