{
  "type": "Feature",
  "properties": {
    "iso:country":"GB",
    "wof:name":"BN1 8WT",
    "wof:placetype":"postalcode"
},
  "geometry": {"coordinates":[-0.14930218121663,50.86457364881786],"type":"Point"}
}