{
  "type": "Feature",
  "properties": {
    "date:inception_lower": "1998-06-01",
    "date:inception_upper": "1998-06-01",
    "iso:country": "GB",
    "wof:name": "S36 6NA",
    "wof:placetype": "postalcode"
  },
  "geometry": {"coordinates":[-1.630846,53.526109],"type":"Point"}
}
