{
  "type": "Feature",
  "properties": {
    "iso:country": "GB",
    "wof:name": "S36 6NA",
    "wof:placetype": "postalcode"
  },
  "geometry": {"coordinates":[-1.630846,53.526109],"type":"Point"}
}
