{
  "type": "Feature",
  "properties": {
    "iso:country": "GB",
    "wof:name": "DL2 2JE",
    "wof:placetype": "postalcode"
  },
  "geometry": {"coordinates":[-1.534824,54.485278],"type":"Point"}
}
