{
  "type": "Feature",
  "properties": {
    "iso:country":"GB",
    "wof:name":"DL2 2JE",
    "wof:placetype":"postalcode"
},
  "geometry": {"coordinates":[-1.53482358853264,54.4852777482801],"type":"Point"}
}