{
  "type": "Feature",
  "properties": {
    "iso:country":"GB",
    "wof:name":"LS8 4DX",
    "wof:placetype":"postalcode"
},
  "geometry": {"coordinates":[-1.51989594987045,53.82080805857567],"type":"Point"}
}