{
  "type": "Feature",
  "properties": {
    "iso:country":"GB",
    "wof:name":"TQ1 1SR",
    "wof:placetype":"postalcode"
},
  "geometry": {"coordinates":[-3.51702213322726,50.47286349863018],"type":"Point"}
}