{
  "type": "Feature",
  "properties": {
    "date:inception_lower": "1980-01-01",
    "date:inception_upper": "1980-01-01",
    "iso:country": "GB",
    "wof:name": "G12 8NP",
    "wof:placetype": "postalcode"
  },
  "geometry": {"coordinates":[-4.283932,55.871999],"type":"Point"}
}
