{
  "type": "Feature",
  "properties": {
    "iso:country":"GB",
    "wof:name":"G12 8NP",
    "wof:placetype":"postalcode"
},
  "geometry": {"coordinates":[-4.28394674860519,55.87200424346857],"type":"Point"}
}