{
  "type": "Feature",
  "properties": {
    "iso:country":"GB",
    "wof:name":"S5 8XL",
    "wof:placetype":"postalcode"
},
  "geometry": {"coordinates":[-1.47216752172744,53.41104482601867],"type":"Point"}
}