{
  "type": "Feature",
  "properties": {
    "iso:country": "GB",
    "wof:name": "BN2 1GA",
    "wof:placetype": "postalcode"
  },
  "geometry": {"coordinates":[-0.108914,50.815047],"type":"Point"}
}
