{
  "type": "Feature",
  "properties": {
    "iso:country": "GB",
    "wof:name": "CO1 2QR",
    "wof:placetype": "postalcode"
  },
  "geometry": {"coordinates":[0.912102,51.890041],"type":"Point"}
}
