{
  "type": "Feature",
  "properties": {
    "iso:country":"GB",
    "wof:name":"CO1 2QR",
    "wof:placetype":"postalcode"
},
  "geometry": {"coordinates":[0.91210152583147,51.89004100554451],"type":"Point"}
}