{
  "type": "Feature",
  "properties": {
    "date:inception_lower": "1980-01-01",
    "date:inception_upper": "1980-01-01",
    "iso:country": "GB",
    "wof:name": "DE4 4DP",
    "wof:placetype": "postalcode"
  },
  "geometry": {"coordinates":[-1.572433,53.081716],"type":"Point"}
}
