{
  "type": "Feature",
  "properties": {
    "iso:country":"GB",
    "wof:name":"DE4 4DP",
    "wof:placetype":"postalcode"
},
  "geometry": {"coordinates":[-1.57243329524324,53.08171628820413],"type":"Point"}
}