{
  "type": "Feature",
  "properties": {
    "iso:country": "GB",
    "wof:name": "DY14 0TU",
    "wof:placetype": "postalcode"
  },
  "geometry": {"coordinates":[-2.523904,52.411075],"type":"Point"}
}
