{
  "type": "Feature",
  "properties": {
    "iso:country": "GB",
    "wof:name": "DY14 0TU",
    "wof:placetype": "postalcode"
  },
  "geometry": {"coordinates":[-2.524252,52.411954],"type":"Point"}
}
