{
  "type": "Feature",
  "properties": {
    "iso:country":"GB",
    "wof:name":"SN2 2ET",
    "wof:placetype":"postalcode"
},
  "geometry": {"coordinates":[-1.80887384435187,51.56413528164573],"type":"Point"}
}