{
  "type": "Feature",
  "properties": {
    "date:inception_lower":"2018-05-01",
    "date:inception_upper":"2018-05-31",
    "iso:country":"GB",
    "wof:name":"NP20 9NZ",
    "wof:placetype":"postalcode"
},
  "geometry": {"coordinates":[-2.997053,51.591274],"type":"Point"}
}