{
  "type": "Feature",
  "properties": {
    "date:inception_lower":"1988-02-01",
    "date:inception_upper":"1988-02-29",
    "iso:country":"GB",
    "wof:name":"G82 1LB",
    "wof:placetype":"postalcode"
},
  "geometry": {"coordinates":[-4.57301,55.943571],"type":"Point"}
}