{
  "type": "Feature",
  "properties": {
    "iso:country": "GB",
    "wof:name": "G82 1LB",
    "wof:placetype": "postalcode"
  },
  "geometry": {"coordinates":[-4.57301,55.943571],"type":"Point"}
}
