{
  "type": "Feature",
  "properties": {
    "date:inception_lower":"2016-11-01",
    "date:inception_upper":"2016-11-30",
    "iso:country":"GB",
    "wof:name":"NR32 1PZ",
    "wof:placetype":"postalcode"
},
  "geometry": {"coordinates":[1.75058,52.477835],"type":"Point"}
}