{
  "type": "Feature",
  "properties": {
    "iso:country": "GB",
    "wof:name": "BB5 0EP",
    "wof:placetype": "postalcode"
  },
  "geometry": {"coordinates":[-2.388715,53.747768],"type":"Point"}
}
