{
  "type": "Feature",
  "properties": {
    "iso:country":"GB",
    "wof:name":"WA8 6DQ",
    "wof:placetype":"postalcode"
},
  "geometry": {"coordinates":[-2.72979643454895,53.36284142780316],"type":"Point"}
}