{
  "type": "Feature",
  "properties": {
    "iso:country":"GB",
    "wof:name":"IP8 3LL",
    "wof:placetype":"postalcode"
},
  "geometry": {"coordinates":[1.1145819738383,52.03323422518429],"type":"Point"}
}