{
  "type": "Feature",
  "properties": {
    "iso:country": "GB",
    "wof:name": "IP8 3LL",
    "wof:placetype": "postalcode"
  },
  "geometry": {"coordinates":[1.114656,52.033238],"type":"Point"}
}
