{
  "type": "Feature",
  "properties": {
    "iso:country":"GB",
    "wof:name":"NG34 7YQ",
    "wof:placetype":"postalcode"
},
  "geometry": {"coordinates":[-0.41103057090231,52.99958008449659],"type":"Point"}
}