{
  "type": "Feature",
  "properties": {
    "date:inception_lower": "2005-07-01",
    "date:inception_upper": "2005-07-01",
    "iso:country": "GB",
    "wof:name": "NG34 7YQ",
    "wof:placetype": "postalcode"
  },
  "geometry": {"coordinates":[-0.410935,52.99961],"type":"Point"}
}
