{
  "type": "Feature",
  "properties": {
    "iso:country": "GB",
    "wof:name": "B37 7HQ",
    "wof:placetype": "postalcode"
  },
  "geometry": {"coordinates":[-1.728625,52.454207],"type":"Point"}
}
