{
  "type": "Feature",
  "properties": {
    "date:inception_lower":"2017-07-01",
    "date:inception_upper":"2017-07-31",
    "iso:country":"GB",
    "wof:name":"B37 7HQ",
    "wof:placetype":"postalcode"
},
  "geometry": {"coordinates":[-1.728625,52.454207],"type":"Point"}
}