{
  "type": "Feature",
  "properties": {
    "date:inception_lower":"2008-01-01",
    "date:inception_upper":"2008-01-31",
    "iso:country":"GB",
    "wof:name":"KA3 1SQ",
    "wof:placetype":"postalcode"
},
  "geometry": {"coordinates":[-4.495622,55.623206],"type":"Point"}
}