{
  "type": "Feature",
  "properties": {
    "iso:country":"GB",
    "wof:name":"KA3 1SQ",
    "wof:placetype":"postalcode"
},
  "geometry": {"coordinates":[-4.49557550960608,55.62316319308849],"type":"Point"}
}