{
  "type": "Feature",
  "properties": {
    "date:inception_lower": "2024-10-01",
    "date:inception_upper": "2024-10-01",
    "iso:country": "GB",
    "wof:name": "CA26 3AA",
    "wof:placetype": "postalcode"
  },
  "geometry": {"coordinates":[-3.474705,54.559833],"type":"Point"}
}
