{
  "type": "Feature",
  "properties": {
    "iso:country":"GB",
    "wof:name":"PE4 6PL",
    "wof:placetype":"postalcode"
},
  "geometry": {"coordinates":[-0.2759217229236,52.61425974567077],"type":"Point"}
}