{
  "type": "Feature",
  "properties": {
    "iso:country":"GB",
    "wof:name":"PH1 1JT",
    "wof:placetype":"postalcode"
},
  "geometry": {"coordinates":[-3.46643316214004,56.39645166856057],"type":"Point"}
}