{
  "type": "Feature",
  "properties": {
    "date:inception_lower":"2000-12-01",
    "date:inception_upper":"2000-12-31",
    "iso:country":"GB",
    "wof:name":"BB2 4FW",
    "wof:placetype":"postalcode"
},
  "geometry": {"coordinates":[-2.490777,53.722631],"type":"Point"}
}