{
  "type": "Feature",
  "properties": {
    "iso:country":"GB",
    "wof:name":"BB2 4FW",
    "wof:placetype":"postalcode"
},
  "geometry": {"coordinates":[-2.49077718948347,53.72263073295915],"type":"Point"}
}