{
  "type": "Feature",
  "properties": {
    "iso:country": "GB",
    "wof:name": "BB2 4FW",
    "wof:placetype": "postalcode"
  },
  "geometry": {"coordinates":[-2.490777,53.722631],"type":"Point"}
}
