{
  "type": "Feature",
  "properties": {
    "iso:country": "GB",
    "wof:name": "W1C 2QW",
    "wof:placetype": "postalcode"
  },
  "geometry": {"coordinates":[-0.157732,51.512963],"type":"Point"}
}
