{
  "type": "Feature",
  "properties": {
    "date:inception_lower":"2000-12-01",
    "date:inception_upper":"2000-12-31",
    "iso:country":"GB",
    "wof:name":"W1C 2QW",
    "wof:placetype":"postalcode"
},
  "geometry": {"coordinates":[-0.157732,51.512963],"type":"Point"}
}