{
  "type": "Feature",
  "properties": {
    "date:inception_lower":"2002-12-01",
    "date:inception_upper":"2002-12-31",
    "iso:country":"GB",
    "wof:name":"LE10 0RN",
    "wof:placetype":"postalcode"
},
  "geometry": {"coordinates":[-1.370513,52.554237],"type":"Point"}
}