{
  "type": "Feature",
  "properties": {
    "iso:country":"GB",
    "wof:name":"NG5 1LA",
    "wof:placetype":"postalcode"
},
  "geometry": {"coordinates":[-1.16916937944559,52.98346178158695],"type":"Point"}
}