{
  "type": "Feature",
  "properties": {
    "iso:country":"GB",
    "wof:name":"LL13 9JT",
    "wof:placetype":"postalcode"
},
  "geometry": {"coordinates":[-2.93061569242496,53.04765859768804],"type":"Point"}
}