{
  "type": "Feature",
  "properties": {
    "iso:country":"GB",
    "wof:name":"B94 6AB",
    "wof:placetype":"postalcode"
},
  "geometry": {"coordinates":[-1.83083134605103,52.36940788409868],"type":"Point"}
}