{
  "type": "Feature",
  "properties": {
    "iso:country": "GB",
    "wof:name": "B94 6AB",
    "wof:placetype": "postalcode"
  },
  "geometry": {"coordinates":[-1.830735,52.369548],"type":"Point"}
}
