{
  "type": "Feature",
  "properties": {
    "date:inception_lower": "1990-07-01",
    "date:inception_upper": "1990-07-01",
    "iso:country": "GB",
    "wof:name": "LA3 3RH",
    "wof:placetype": "postalcode"
  },
  "geometry": {"coordinates":[-2.855618,54.058516],"type":"Point"}
}
