{
  "type": "Feature",
  "properties": {
    "iso:country":"GB",
    "wof:name":"WV3 0RA",
    "wof:placetype":"postalcode"
},
  "geometry": {"coordinates":[-2.13389928144234,52.58089655621441],"type":"Point"}
}