{
  "type": "Feature",
  "properties": {
    "iso:country":"GB",
    "wof:name":"N5 1UT",
    "wof:placetype":"postalcode"
},
  "geometry": {"coordinates":[-0.10286352111292,51.55152044042438],"type":"Point"}
}