{
  "type": "Feature",
  "properties": {
    "iso:country":"GB",
    "wof:name":"DH1 1SN",
    "wof:placetype":"postalcode"
},
  "geometry": {"coordinates":[-1.53285068153511,54.79605125240338],"type":"Point"}
}