{
  "type": "Feature",
  "properties": {
    "iso:country":"GB",
    "wof:name":"SO51 7JR",
    "wof:placetype":"postalcode"
},
  "geometry": {"coordinates":[-1.48137919231558,50.999750437774],"type":"Point"}
}