{
  "type": "Feature",
  "properties": {
    "iso:country":"GB",
    "wof:name":"LN5 8AB",
    "wof:placetype":"postalcode"
},
  "geometry": {"coordinates":[-0.54733900200161,53.21938897972417],"type":"Point"}
}