{
  "type": "Feature",
  "properties": {
    "iso:country":"GB",
    "wof:name":"SW13 0HY",
    "wof:placetype":"postalcode"
},
  "geometry": {"coordinates":[-0.23942035264469,51.46543357156098],"type":"Point"}
}