{
  "type": "Feature",
  "properties": {
    "iso:country":"GB",
    "wof:name":"OX4 3HU",
    "wof:placetype":"postalcode"
},
  "geometry": {"coordinates":[-1.21136057088953,51.73130177737005],"type":"Point"}
}