{
  "type": "Feature",
  "properties": {
    "iso:country": "GB",
    "wof:name": "DD2 3AY",
    "wof:placetype": "postalcode"
  },
  "geometry": {"coordinates":[-3.009817,56.471558],"type":"Point"}
}
