{
  "type": "Feature",
  "properties": {
    "date:inception_lower": "1980-01-01",
    "date:inception_upper": "1980-01-01",
    "iso:country": "GB",
    "wof:name": "SA48 7AB",
    "wof:placetype": "postalcode"
  },
  "geometry": {"coordinates":[-4.075844,52.110929],"type":"Point"}
}
