{
  "type": "Feature",
  "properties": {
    "iso:country":"GB",
    "wof:name":"SA48 7AB",
    "wof:placetype":"postalcode"
},
  "geometry": {"coordinates":[-4.0758440471753,52.11092931908835],"type":"Point"}
}