{
  "type": "Feature",
  "properties": {
    "date:inception_lower":"2011-02-01",
    "date:inception_upper":"2011-02-28",
    "iso:country":"GB",
    "wof:name":"DG9 7TU",
    "wof:placetype":"postalcode"
},
  "geometry": {"coordinates":[-5.03214,54.900767],"type":"Point"}
}