{
  "type": "Feature",
  "properties": {
    "iso:country": "GB",
    "wof:name": "DG9 7TU",
    "wof:placetype": "postalcode"
  },
  "geometry": {"coordinates":[-5.03214,54.900767],"type":"Point"}
}
