{
  "type": "Feature",
  "properties": {
    "date:inception_lower": "2010-10-01",
    "date:inception_upper": "2010-10-01",
    "iso:country": "GB",
    "wof:name": "G45 0HJ",
    "wof:placetype": "postalcode"
  },
  "geometry": {"coordinates":[-4.215087,55.806379],"type":"Point"}
}
