{
  "type": "Feature",
  "properties": {
    "iso:country":"GB",
    "wof:name":"BD4 8NJ",
    "wof:placetype":"postalcode"
},
  "geometry": {"coordinates":[-1.71428923642288,53.78427179360268],"type":"Point"}
}