{
  "type": "Feature",
  "properties": {
    "iso:country":"GB",
    "wof:name":"CF83 4EP",
    "wof:placetype":"postalcode"
},
  "geometry": {"coordinates":[-3.27988217045244,51.59580211895986],"type":"Point"}
}