{
  "type": "Feature",
  "properties": {
    "iso:country": "GB",
    "wof:name": "CF83 4EP",
    "wof:placetype": "postalcode"
  },
  "geometry": {"coordinates":[-3.279882,51.595802],"type":"Point"}
}
