{
  "type": "Feature",
  "properties": {
    "iso:country":"GB",
    "wof:name":"SE9 4AW",
    "wof:placetype":"postalcode"
},
  "geometry": {"coordinates":[0.04817941140414,51.42436790068237],"type":"Point"}
}