{
  "type": "Feature",
  "properties": {
    "iso:country":"GB",
    "wof:name":"RG7 5QE",
    "wof:placetype":"postalcode"
},
  "geometry": {"coordinates":[-1.13826600369932,51.40304521585253],"type":"Point"}
}