{
  "type": "Feature",
  "properties": {
    "iso:country": "GB",
    "wof:name": "L40 4BP",
    "wof:placetype": "postalcode"
  },
  "geometry": {"coordinates":[-2.81235,53.600758],"type":"Point"}
}
