{
  "type": "Feature",
  "properties": {
    "iso:country":"GB",
    "wof:name":"L40 4BP",
    "wof:placetype":"postalcode"
},
  "geometry": {"coordinates":[-2.80857136797804,53.60305079029369],"type":"Point"}
}