{
  "type": "Feature",
  "properties": {
    "iso:country":"GB",
    "wof:name":"NG19 6RA",
    "wof:placetype":"postalcode"
},
  "geometry": {"coordinates":[-1.22310383175094,53.13782203172655],"type":"Point"}
}