{
  "type": "Feature",
  "properties": {
    "iso:country": "GB",
    "wof:name": "SS5 4FN",
    "wof:placetype": "postalcode"
  },
  "geometry": {"coordinates":[0.671591,51.592195],"type":"Point"}
}
