{
  "type": "Feature",
  "properties": {
    "date:inception_lower": "1980-01-01",
    "date:inception_upper": "1980-01-01",
    "iso:country": "GB",
    "wof:name": "BH23 8BN",
    "wof:placetype": "postalcode"
  },
  "geometry": {"coordinates":[-1.742107,50.778854],"type":"Point"}
}
