{
  "type": "Feature",
  "properties": {
    "iso:country":"GB",
    "wof:name":"PO16 8BZ",
    "wof:placetype":"postalcode"
},
  "geometry": {"coordinates":[-1.1264702805946,50.85254169552779],"type":"Point"}
}