{
  "type": "Feature",
  "properties": {
    "iso:country": "GB",
    "wof:name": "YO8 9FE",
    "wof:placetype": "postalcode"
  },
  "geometry": {"coordinates":[-1.128596,53.769358],"type":"Point"}
}
