{
  "type": "Feature",
  "properties": {
    "iso:country":"GB",
    "wof:name":"YO8 9FE",
    "wof:placetype":"postalcode"
},
  "geometry": {"coordinates":[-1.12859600585365,53.76935786626327],"type":"Point"}
}