{
  "type": "Feature",
  "properties": {
    "iso:country":"GB",
    "wof:name":"IG7 4BL",
    "wof:placetype":"postalcode"
},
  "geometry": {"coordinates":[0.09836087608496,51.60956800132458],"type":"Point"}
}