{
  "type": "Feature",
  "properties": {
    "iso:country":"GB",
    "wof:name":"GU31 4HY",
    "wof:placetype":"postalcode"
},
  "geometry": {"coordinates":[-0.91698860109177,51.00073008734071],"type":"Point"}
}