{
  "type": "Feature",
  "properties": {
    "date:inception_lower": "1983-03-01",
    "date:inception_upper": "1983-03-01",
    "iso:country": "GB",
    "wof:name": "GU31 4HY",
    "wof:placetype": "postalcode"
  },
  "geometry": {"coordinates":[-0.916985,51.00076],"type":"Point"}
}
