{
  "type": "Feature",
  "properties": {
    "date:inception_lower": "1980-01-01",
    "date:inception_upper": "1980-01-01",
    "iso:country": "GB",
    "wof:name": "N5 1BZ",
    "wof:placetype": "postalcode"
  },
  "geometry": {"coordinates":[-0.100712,51.557798],"type":"Point"}
}
