{
  "type": "Feature",
  "properties": {
    "iso:country":"GB",
    "wof:name":"TD1 2QF",
    "wof:placetype":"postalcode"
},
  "geometry": {"coordinates":[-2.72075097807675,55.68427346113039],"type":"Point"}
}