{
  "type": "Feature",
  "properties": {
    "iso:country":"GB",
    "wof:name":"RM12 6DX",
    "wof:placetype":"postalcode"
},
  "geometry": {"coordinates":[0.23116717593261,51.55184810192981],"type":"Point"}
}