{
  "type": "Feature",
  "properties": {
    "iso:country":"GB",
    "wof:name":"SY8 3QT",
    "wof:placetype":"postalcode"
},
  "geometry": {"coordinates":[-2.57319597005652,52.37223691784455],"type":"Point"}
}