{
  "type": "Feature",
  "properties": {
    "iso:country":"GB",
    "wof:name":"CM6 2HG",
    "wof:placetype":"postalcode"
},
  "geometry": {"coordinates":[0.33402239285792,51.90438950269812],"type":"Point"}
}