{
  "type": "Feature",
  "properties": {
    "date:inception_lower": "1980-01-01",
    "date:inception_upper": "1980-01-01",
    "iso:country": "GB",
    "wof:name": "CM6 2HG",
    "wof:placetype": "postalcode"
  },
  "geometry": {"coordinates":[0.333697,51.904305],"type":"Point"}
}
