{
  "type": "Feature",
  "properties": {
    "iso:country": "GB",
    "wof:name": "CM6 2HG",
    "wof:placetype": "postalcode"
  },
  "geometry": {"coordinates":[0.333697,51.904305],"type":"Point"}
}
