{
  "type": "Feature",
  "properties": {
    "iso:country": "GB",
    "wof:name": "IV36 1PD",
    "wof:placetype": "postalcode"
  },
  "geometry": {"coordinates":[-3.613489,57.609661],"type":"Point"}
}
