{
  "type": "Feature",
  "properties": {
    "iso:country": "GB",
    "wof:name": "BA11 3HD",
    "wof:placetype": "postalcode"
  },
  "geometry": {"coordinates":[-2.333662,51.232176],"type":"Point"}
}
