{
  "type": "Feature",
  "properties": {
    "iso:country":"GB",
    "wof:name":"BA11 3HD",
    "wof:placetype":"postalcode"
},
  "geometry": {"coordinates":[-2.33366173365084,51.23217620624292],"type":"Point"}
}