{
  "type": "Feature",
  "properties": {
    "iso:country":"GB",
    "wof:name":"SG8 8SQ",
    "wof:placetype":"postalcode"
},
  "geometry": {"coordinates":[0.07359454971629,52.02928572444231],"type":"Point"}
}