{
  "type": "Feature",
  "properties": {
    "date:inception_lower": "1980-01-01",
    "date:inception_upper": "1980-01-01",
    "iso:country": "GB",
    "wof:name": "SG8 8SQ",
    "wof:placetype": "postalcode"
  },
  "geometry": {"coordinates":[0.073595,52.029286],"type":"Point"}
}
