{
  "type": "Feature",
  "properties": {
    "date:inception_lower":"1980-01-01",
    "date:inception_upper":"1980-01-31",
    "iso:country":"GB",
    "wof:name":"FK3 8TY",
    "wof:placetype":"postalcode"
},
  "geometry": {"coordinates":[-3.722789,56.020634],"type":"Point"}
}