{
  "type": "Feature",
  "properties": {
    "iso:country":"GB",
    "wof:name":"FK3 8TY",
    "wof:placetype":"postalcode"
},
  "geometry": {"coordinates":[-3.71937624759159,56.02000791798844],"type":"Point"}
}