{
  "type": "Feature",
  "properties": {
    "iso:country":"GB",
    "wof:name":"PO15 6NT",
    "wof:placetype":"postalcode"
},
  "geometry": {"coordinates":[-1.21702693787552,50.8640022966132],"type":"Point"}
}