{
  "type": "Feature",
  "properties": {
    "date:inception_lower": "1980-01-01",
    "date:inception_upper": "1980-01-01",
    "iso:country": "GB",
    "wof:name": "EN2 9AE",
    "wof:placetype": "postalcode"
  },
  "geometry": {"coordinates":[-0.079962,51.669497],"type":"Point"}
}
