{
  "type": "Feature",
  "properties": {
    "date:inception_lower": "2021-10-01",
    "date:inception_upper": "2021-10-01",
    "iso:country": "GB",
    "wof:name": "EX1 3ZD",
    "wof:placetype": "postalcode"
  },
  "geometry": {"coordinates":[-3.489114,50.724742],"type":"Point"}
}
