{
  "type": "Feature",
  "properties": {
    "date:inception_lower": "1980-01-01",
    "date:inception_upper": "1980-01-01",
    "iso:country": "GB",
    "wof:name": "CF48 1TB",
    "wof:placetype": "postalcode"
  },
  "geometry": {"coordinates":[-3.408644,51.743861],"type":"Point"}
}
