{
  "type": "Feature",
  "properties": {
    "iso:country":"GB",
    "wof:name":"CF48 1TB",
    "wof:placetype":"postalcode"
},
  "geometry": {"coordinates":[-3.40864431922972,51.74386119193502],"type":"Point"}
}