{
  "type": "Feature",
  "properties": {
    "date:inception_lower": "1980-01-01",
    "date:inception_upper": "1980-01-01",
    "iso:country": "GB",
    "wof:name": "EN5 3AA",
    "wof:placetype": "postalcode"
  },
  "geometry": {"coordinates":[-0.22147,51.646197],"type":"Point"}
}
