{
  "type": "Feature",
  "properties": {
    "iso:country":"GB",
    "wof:name":"EN5 3AA",
    "wof:placetype":"postalcode"
},
  "geometry": {"coordinates":[-0.22147048936604,51.64619678807505],"type":"Point"}
}