{
  "type": "Feature",
  "properties": {
    "date:inception_lower":"1980-01-01",
    "date:inception_upper":"1980-01-31",
    "iso:country":"GB",
    "wof:name":"BD22 6JG",
    "wof:placetype":"postalcode"
},
  "geometry": {"coordinates":[-1.929236,53.867244],"type":"Point"}
}