{
  "type": "Feature",
  "properties": {
    "iso:country": "GB",
    "wof:name": "EX16 9PG",
    "wof:placetype": "postalcode"
  },
  "geometry": {"coordinates":[-3.510362,50.945845],"type":"Point"}
}
