{
  "type": "Feature",
  "properties": {
    "iso:country": "GB",
    "wof:name": "EX31 3EB",
    "wof:placetype": "postalcode"
  },
  "geometry": {"coordinates":[-4.148158,51.067543],"type":"Point"}
}
