{
  "type": "Feature",
  "properties": {
    "iso:country": "GB",
    "wof:name": "CA8 7NP",
    "wof:placetype": "postalcode"
  },
  "geometry": {"coordinates":[-2.520695,54.871848],"type":"Point"}
}
