{
  "type": "Feature",
  "properties": {
    "iso:country": "GB",
    "wof:name": "NE9 6QG",
    "wof:placetype": "postalcode"
  },
  "geometry": {"coordinates":[-1.59861,54.920173],"type":"Point"}
}
