{
  "type": "Feature",
  "properties": {
    "iso:country":"GB",
    "wof:name":"EN5 3DL",
    "wof:placetype":"postalcode"
},
  "geometry": {"coordinates":[-0.2130832923196,51.65254386112352],"type":"Point"}
}