{
  "type": "Feature",
  "properties": {
    "date:inception_lower": "1992-08-01",
    "date:inception_upper": "1992-08-01",
    "iso:country": "GB",
    "wof:name": "OX44 7UT",
    "wof:placetype": "postalcode"
  },
  "geometry": {"coordinates":[-1.129739,51.678387],"type":"Point"}
}
