{
  "type": "Feature",
  "properties": {
    "iso:country": "GB",
    "wof:name": "CM2 7US",
    "wof:placetype": "postalcode"
  },
  "geometry": {"coordinates":[0.536786,51.697242],"type":"Point"}
}
