{
  "type": "Feature",
  "properties": {
    "date:inception_lower": "2010-06-01",
    "date:inception_upper": "2010-06-01",
    "iso:country": "GB",
    "wof:name": "CM2 7US",
    "wof:placetype": "postalcode"
  },
  "geometry": {"coordinates":[0.536786,51.697242],"type":"Point"}
}
