{
  "type": "Feature",
  "properties": {
    "iso:country":"GB",
    "wof:name":"CM2 7US",
    "wof:placetype":"postalcode"
},
  "geometry": {"coordinates":[0.53676007789849,51.69723681568558],"type":"Point"}
}