{
  "type": "Feature",
  "properties": {
    "iso:country": "GB",
    "wof:name": "CT18 8AU",
    "wof:placetype": "postalcode"
  },
  "geometry": {"coordinates":[1.115826,51.094893],"type":"Point"}
}
