{
  "type": "Feature",
  "properties": {
    "iso:country":"GB",
    "wof:name":"TS2 1UX",
    "wof:placetype":"postalcode"
},
  "geometry": {"coordinates":[-1.25692691359788,54.58118396203927],"type":"Point"}
}