{
  "type": "Feature",
  "properties": {
    "iso:country": "GB",
    "wof:name": "M24 5QR",
    "wof:placetype": "postalcode"
  },
  "geometry": {"coordinates":[-2.209761,53.557665],"type":"Point"}
}
