{
  "type": "Feature",
  "properties": {
    "iso:country":"GB",
    "wof:name":"M24 5QR",
    "wof:placetype":"postalcode"
},
  "geometry": {"coordinates":[-2.20976066194601,53.55766520763299],"type":"Point"}
}