{
  "type": "Feature",
  "properties": {
    "iso:country":"GB",
    "wof:name":"PL4 8SU",
    "wof:placetype":"postalcode"
},
  "geometry": {"coordinates":[-4.12102585801565,50.37717315473313],"type":"Point"}
}