{
  "type": "Feature",
  "properties": {
    "date:inception_lower": "1980-01-01",
    "date:inception_upper": "1980-01-01",
    "iso:country": "GB",
    "wof:name": "PL4 8SU",
    "wof:placetype": "postalcode"
  },
  "geometry": {"coordinates":[-4.121026,50.377173],"type":"Point"}
}
