{
  "type": "Feature",
  "properties": {
    "date:inception_lower": "1980-01-01",
    "date:inception_upper": "1980-01-01",
    "iso:country": "GB",
    "wof:name": "GL14 1BJ",
    "wof:placetype": "postalcode"
  },
  "geometry": {"coordinates":[-2.447627,51.806808],"type":"Point"}
}
