{
  "type": "Feature",
  "properties": {
    "iso:country": "GB",
    "wof:name": "RG30 6AU",
    "wof:placetype": "postalcode"
  },
  "geometry": {"coordinates":[-1.01703,51.463488],"type":"Point"}
}
