{
  "type": "Feature",
  "properties": {
    "iso:country": "GB",
    "wof:name": "DH6 2ED",
    "wof:placetype": "postalcode"
  },
  "geometry": {"coordinates":[-1.422338,54.78091],"type":"Point"}
}
