{
  "type": "Feature",
  "properties": {
    "iso:country":"GB",
    "wof:name":"DH6 2ED",
    "wof:placetype":"postalcode"
},
  "geometry": {"coordinates":[-1.42232463652948,54.78090055446813],"type":"Point"}
}