{
  "type": "Feature",
  "properties": {
    "iso:country": "GB",
    "wof:name": "DE5 9RG",
    "wof:placetype": "postalcode"
  },
  "geometry": {"coordinates":[-1.372244,53.041268],"type":"Point"}
}
