{
  "type": "Feature",
  "properties": {
    "date:inception_lower": "2019-04-01",
    "date:inception_upper": "2019-04-01",
    "iso:country": "GB",
    "wof:name": "PL25 4GA",
    "wof:placetype": "postalcode"
  },
  "geometry": {"coordinates":[-4.772434,50.330787],"type":"Point"}
}
