{
  "type": "Feature",
  "properties": {
    "iso:country": "GB",
    "wof:name": "SG8 0DZ",
    "wof:placetype": "postalcode"
  },
  "geometry": {"coordinates":[-0.093407,52.124866],"type":"Point"}
}
