{
  "type": "Feature",
  "properties": {
    "iso:country":"GB",
    "wof:name":"SG8 0DZ",
    "wof:placetype":"postalcode"
},
  "geometry": {"coordinates":[-0.09340674370081,52.12486630035581],"type":"Point"}
}