{
  "type": "Feature",
  "properties": {
    "date:inception_lower": "2009-04-01",
    "date:inception_upper": "2009-04-01",
    "iso:country": "GB",
    "wof:name": "GU14 7FY",
    "wof:placetype": "postalcode"
  },
  "geometry": {"coordinates":[-0.751567,51.294986],"type":"Point"}
}
