{
  "type": "Feature",
  "properties": {
    "date:inception_lower": "1980-01-01",
    "date:inception_upper": "1980-01-01",
    "iso:country": "GB",
    "wof:name": "SA18 3BX",
    "wof:placetype": "postalcode"
  },
  "geometry": {"coordinates":[-4.025074,51.80377],"type":"Point"}
}
