{
  "type": "Feature",
  "properties": {
    "iso:country":"GB",
    "wof:name":"B17 9BJ",
    "wof:placetype":"postalcode"
},
  "geometry": {"coordinates":[-1.96193994868357,52.46123010049156],"type":"Point"}
}