{
  "type": "Feature",
  "properties": {
    "date:inception_lower": "2014-01-01",
    "date:inception_upper": "2014-01-01",
    "iso:country": "GB",
    "wof:name": "SA4 6AA",
    "wof:placetype": "postalcode"
  },
  "geometry": {"coordinates":[-4.044235,51.660998],"type":"Point"}
}
