{
  "type": "Feature",
  "properties": {
    "iso:country": "GB",
    "wof:name": "GU33 7QJ",
    "wof:placetype": "postalcode"
  },
  "geometry": {"coordinates":[-0.878579,51.03034],"type":"Point"}
}
