{
  "type": "Feature",
  "properties": {
    "iso:country":"GB",
    "wof:name":"GU33 7QJ",
    "wof:placetype":"postalcode"
},
  "geometry": {"coordinates":[-0.87857943106299,51.03034003529249],"type":"Point"}
}