{
  "type": "Feature",
  "properties": {
    "date:inception_lower": "2004-08-01",
    "date:inception_upper": "2004-08-01",
    "iso:country": "GB",
    "wof:name": "E6 6JL",
    "wof:placetype": "postalcode"
  },
  "geometry": {"coordinates":[0.059173,51.525497],"type":"Point"}
}
