{
  "type": "Feature",
  "properties": {
    "iso:country":"GB",
    "wof:name":"E6 6JL",
    "wof:placetype":"postalcode"
},
  "geometry": {"coordinates":[0.05917314468141,51.52549711786055],"type":"Point"}
}