{
  "type": "Feature",
  "properties": {
    "date:inception_lower": "2000-12-01",
    "date:inception_upper": "2000-12-01",
    "iso:country": "GB",
    "wof:name": "W1W 6YJ",
    "wof:placetype": "postalcode"
  },
  "geometry": {"coordinates":[-0.139698,51.52052],"type":"Point"}
}
