{
  "type": "Feature",
  "properties": {
    "iso:country":"GB",
    "wof:name":"W1W 6YJ",
    "wof:placetype":"postalcode"
},
  "geometry": {"coordinates":[-0.13969795769969,51.52051970355165],"type":"Point"}
}