{
  "type": "Feature",
  "properties": {
    "iso:country": "GB",
    "wof:name": "TS12 3BY",
    "wof:placetype": "postalcode"
  },
  "geometry": {"coordinates":[-0.988075,54.532187],"type":"Point"}
}
