{
  "type": "Feature",
  "properties": {
    "iso:country":"GB",
    "wof:name":"G69 7LR",
    "wof:placetype":"postalcode"
},
  "geometry": {"coordinates":[-4.13046824327703,55.84825440476466],"type":"Point"}
}