{
  "type": "Feature",
  "properties": {
    "iso:country":"GB",
    "wof:name":"PO30 5JS",
    "wof:placetype":"postalcode"
},
  "geometry": {"coordinates":[-1.31516735042372,50.69236384432273],"type":"Point"}
}