{
  "type": "Feature",
  "properties": {
    "iso:country":"GB",
    "wof:name":"WF17 7TR",
    "wof:placetype":"postalcode"
},
  "geometry": {"coordinates":[-1.64261596069,53.71368510746904],"type":"Point"}
}