{
  "type": "Feature",
  "properties": {
    "iso:country":"GB",
    "wof:name":"TR2 5SR",
    "wof:placetype":"postalcode"
},
  "geometry": {"coordinates":[-4.87254429759329,50.24594214525029],"type":"Point"}
}