{
  "type": "Feature",
  "properties": {
    "iso:country":"GB",
    "wof:name":"CV10 9PJ",
    "wof:placetype":"postalcode"
},
  "geometry": {"coordinates":[-1.555335520827,52.51904324168946],"type":"Point"}
}