{
  "type": "Feature",
  "properties": {
    "date:inception_lower": "1980-01-01",
    "date:inception_upper": "1980-01-01",
    "iso:country": "GB",
    "wof:name": "CV10 9PJ",
    "wof:placetype": "postalcode"
  },
  "geometry": {"coordinates":[-1.555335,52.519043],"type":"Point"}
}
