{
  "type": "Feature",
  "properties": {
    "iso:country":"GB",
    "wof:name":"NG24 3UE",
    "wof:placetype":"postalcode"
},
  "geometry": {"coordinates":[-0.84551129173271,53.06380629093728],"type":"Point"}
}