{
  "type": "Feature",
  "properties": {
    "iso:country": "GB",
    "wof:name": "BB9 7EB",
    "wof:placetype": "postalcode"
  },
  "geometry": {"coordinates":[-2.219064,53.840833],"type":"Point"}
}
