{
  "type": "Feature",
  "properties": {
    "iso:country": "GB",
    "wof:name": "CV22 7GF",
    "wof:placetype": "postalcode"
  },
  "geometry": {"coordinates":[-1.303584,52.359962],"type":"Point"}
}
