{
  "type": "Feature",
  "properties": {
    "iso:country": "GB",
    "wof:name": "HP22 7AP",
    "wof:placetype": "postalcode"
  },
  "geometry": {"coordinates":[-0.778859,51.82321],"type":"Point"}
}
