{
  "type": "Feature",
  "properties": {
    "iso:country": "GB",
    "wof:name": "KA7 4QB",
    "wof:placetype": "postalcode"
  },
  "geometry": {"coordinates":[-4.628656,55.432885],"type":"Point"}
}
