{
  "type": "Feature",
  "properties": {
    "iso:country":"GB",
    "wof:name":"SN14 0XT",
    "wof:placetype":"postalcode"
},
  "geometry": {"coordinates":[-2.15033009982994,51.44970559648934],"type":"Point"}
}