{
  "type": "Feature",
  "properties": {
    "date:inception_lower":"1994-12-01",
    "date:inception_upper":"1994-12-31",
    "iso:country":"GB",
    "wof:name":"SN14 0XT",
    "wof:placetype":"postalcode"
},
  "geometry": {"coordinates":[-2.15033,51.449706],"type":"Point"}
}