{
  "type": "Feature",
  "properties": {
    "iso:country":"GB",
    "wof:name":"ML6 9NB",
    "wof:placetype":"postalcode"
},
  "geometry": {"coordinates":[-3.9697694535794,55.86195970941877],"type":"Point"}
}