{
  "type": "Feature",
  "properties": {
    "iso:country":"GB",
    "wof:name":"LA5 9QD",
    "wof:placetype":"postalcode"
},
  "geometry": {"coordinates":[-2.7632428718254,54.14958113867595],"type":"Point"}
}