{
  "type": "Feature",
  "properties": {
    "iso:country":"GB",
    "wof:name":"TS10 4FJ",
    "wof:placetype":"postalcode"
},
  "geometry": {"coordinates":[-1.07369258947271,54.60433875079493],"type":"Point"}
}