{
  "type": "Feature",
  "properties": {
    "date:inception_lower":"1987-04-01",
    "date:inception_upper":"1987-04-30",
    "iso:country":"GB",
    "wof:name":"LS9 6SX",
    "wof:placetype":"postalcode"
},
  "geometry": {"coordinates":[-1.49359,53.811676],"type":"Point"}
}