{
  "type": "Feature",
  "properties": {
    "iso:country": "GB",
    "wof:name": "BS41 9LL",
    "wof:placetype": "postalcode"
  },
  "geometry": {"coordinates":[-2.646365,51.433219],"type":"Point"}
}
