{
  "type": "Feature",
  "properties": {
    "iso:country":"GB",
    "wof:name":"BS41 9LL",
    "wof:placetype":"postalcode"
},
  "geometry": {"coordinates":[-2.64636485898376,51.43321891065867],"type":"Point"}
}