{
  "type": "Feature",
  "properties": {
    "iso:country": "GB",
    "wof:name": "GU21 6AP",
    "wof:placetype": "postalcode"
  },
  "geometry": {"coordinates":[-0.555387,51.322692],"type":"Point"}
}
