{
  "type": "Feature",
  "properties": {
    "date:inception_lower": "2005-11-01",
    "date:inception_upper": "2005-11-01",
    "iso:country": "GB",
    "wof:name": "GU21 6AP",
    "wof:placetype": "postalcode"
  },
  "geometry": {"coordinates":[-0.555387,51.322692],"type":"Point"}
}
