{
  "type": "Feature",
  "properties": {
    "date:inception_lower": "1995-07-01",
    "date:inception_upper": "1995-07-01",
    "iso:country": "GB",
    "wof:name": "BD12 0TW",
    "wof:placetype": "postalcode"
  },
  "geometry": {"coordinates":[-1.76119,53.7567],"type":"Point"}
}
