{
  "type": "Feature",
  "properties": {
    "iso:country": "GB",
    "wof:name": "BD12 0TW",
    "wof:placetype": "postalcode"
  },
  "geometry": {"coordinates":[-1.76119,53.7567],"type":"Point"}
}
