{
  "type": "Feature",
  "properties": {
    "iso:country": "GB",
    "wof:name": "CV35 9HT",
    "wof:placetype": "postalcode"
  },
  "geometry": {"coordinates":[-1.592808,52.16486],"type":"Point"}
}
