{
  "type": "Feature",
  "properties": {
    "iso:country":"GB",
    "wof:name":"CV35 9HT",
    "wof:placetype":"postalcode"
},
  "geometry": {"coordinates":[-1.59151528479595,52.16522834200197],"type":"Point"}
}