{
  "type": "Feature",
  "properties": {
    "iso:country":"GB",
    "wof:name":"HP10 8AP",
    "wof:placetype":"postalcode"
},
  "geometry": {"coordinates":[-0.69959224899972,51.64434489986848],"type":"Point"}
}