{
  "type": "Feature",
  "properties": {
    "date:inception_lower": "2024-07-01",
    "date:inception_upper": "2024-07-01",
    "iso:country": "GB",
    "wof:name": "B16 8WW",
    "wof:placetype": "postalcode"
  },
  "geometry": {"coordinates":[-1.915516,52.476144],"type":"Point"}
}
