{
  "type": "Feature",
  "properties": {
    "iso:country":"GB",
    "wof:name":"SE7 8EE",
    "wof:placetype":"postalcode"
},
  "geometry": {"coordinates":[0.04667496366114,51.48499673584504],"type":"Point"}
}