{
  "type": "Feature",
  "properties": {
    "date:inception_lower": "2023-09-01",
    "date:inception_upper": "2023-09-01",
    "iso:country": "GB",
    "wof:name": "RG7 3ZP",
    "wof:placetype": "postalcode"
  },
  "geometry": {"coordinates":[-1.05827,51.403852],"type":"Point"}
}
