{
  "type": "Feature",
  "properties": {
    "iso:country":"GB",
    "wof:name":"EX19 8BD",
    "wof:placetype":"postalcode"
},
  "geometry": {"coordinates":[-4.0364702886422,50.84259261958515],"type":"Point"}
}