{
  "type": "Feature",
  "properties": {
    "iso:country": "GB",
    "wof:name": "EX19 8BD",
    "wof:placetype": "postalcode"
  },
  "geometry": {"coordinates":[-4.03647,50.842593],"type":"Point"}
}
