{
  "type": "Feature",
  "properties": {
    "iso:country": "GB",
    "wof:name": "DE56 1PQ",
    "wof:placetype": "postalcode"
  },
  "geometry": {"coordinates":[-1.481202,53.017216],"type":"Point"}
}
