{
  "type": "Feature",
  "properties": {
    "iso:country":"GB",
    "wof:name":"DE56 1PQ",
    "wof:placetype":"postalcode"
},
  "geometry": {"coordinates":[-1.4812022886641,53.01721589625591],"type":"Point"}
}