{
  "type": "Feature",
  "properties": {
    "date:inception_lower":"2002-12-01",
    "date:inception_upper":"2002-12-31",
    "iso:country":"GB",
    "wof:name":"NE29 9JA",
    "wof:placetype":"postalcode"
},
  "geometry": {"coordinates":[-1.457901,55.025756],"type":"Point"}
}