{
  "type": "Feature",
  "properties": {
    "date:inception_lower":"1980-01-01",
    "date:inception_upper":"1980-01-31",
    "iso:country":"GB",
    "wof:name":"WR3 8NB",
    "wof:placetype":"postalcode"
},
  "geometry": {"coordinates":[-2.211284,52.198479],"type":"Point"}
}