{
  "type": "Feature",
  "properties": {
    "iso:country":"GB",
    "wof:name":"CH66 4TE",
    "wof:placetype":"postalcode"
},
  "geometry": {"coordinates":[-2.94429686062796,53.2820894448227],"type":"Point"}
}