{
  "type": "Feature",
  "properties": {
    "iso:country":"GB",
    "wof:name":"SW10 0QF",
    "wof:placetype":"postalcode"
},
  "geometry": {"coordinates":[-0.17936384339799,51.47972272491617],"type":"Point"}
}