{
  "type": "Feature",
  "properties": {
    "iso:country": "GB",
    "wof:name": "SW10 0QF",
    "wof:placetype": "postalcode"
  },
  "geometry": {"coordinates":[-0.179364,51.479723],"type":"Point"}
}
