{
  "type": "Feature",
  "properties": {
    "date:inception_lower": "1986-09-01",
    "date:inception_upper": "1986-09-01",
    "iso:country": "GB",
    "wof:name": "KY11 2BU",
    "wof:placetype": "postalcode"
  },
  "geometry": {"coordinates":[-3.423392,56.036],"type":"Point"}
}
