{
  "type": "Feature",
  "properties": {
    "iso:country":"GB",
    "wof:name":"SO15 5HG",
    "wof:placetype":"postalcode"
},
  "geometry": {"coordinates":[-1.4238246256244,50.92452036084637],"type":"Point"}
}