{
  "type": "Feature",
  "properties": {
    "iso:country":"GB",
    "wof:name":"DD3 8PG",
    "wof:placetype":"postalcode"
},
  "geometry": {"coordinates":[-2.99840011961521,56.48556721667615],"type":"Point"}
}