{
  "type": "Feature",
  "properties": {
    "date:inception_lower": "1980-01-01",
    "date:inception_upper": "1980-01-01",
    "iso:country": "GB",
    "wof:name": "SY23 3JW",
    "wof:placetype": "postalcode"
  },
  "geometry": {"coordinates":[-3.846892,52.378348],"type":"Point"}
}
