{
  "type": "Feature",
  "properties": {
    "iso:country":"GB",
    "wof:name":"SY23 3JW",
    "wof:placetype":"postalcode"
},
  "geometry": {"coordinates":[-3.84372967183727,52.37814047366658],"type":"Point"}
}