{
  "type": "Feature",
  "properties": {
    "date:inception_lower":"1999-06-01",
    "date:inception_upper":"1999-06-30",
    "iso:country":"GB",
    "wof:name":"NP25 4DQ",
    "wof:placetype":"postalcode"
},
  "geometry": {"coordinates":[-2.73825,51.801092],"type":"Point"}
}