{
  "type": "Feature",
  "properties": {
    "iso:country": "GB",
    "wof:name": "NP25 4DQ",
    "wof:placetype": "postalcode"
  },
  "geometry": {"coordinates":[-2.73825,51.801092],"type":"Point"}
}
