{
  "type": "Feature",
  "properties": {
    "iso:country":"GB",
    "wof:name":"NP25 4DQ",
    "wof:placetype":"postalcode"
},
  "geometry": {"coordinates":[-2.73825004824707,51.80109190287982],"type":"Point"}
}