{
  "type": "Feature",
  "properties": {
    "iso:country":"GB",
    "wof:name":"AB42 5SU",
    "wof:placetype":"postalcode"
},
  "geometry": {"coordinates":[-2.19127233766711,57.48194128201915],"type":"Point"}
}