{
  "type": "Feature",
  "properties": {
    "iso:country":"GB",
    "wof:name":"SN7 8LT",
    "wof:placetype":"postalcode"
},
  "geometry": {"coordinates":[-1.50789063860691,51.6366475270323],"type":"Point"}
}