{
  "type": "Feature",
  "properties": {
    "iso:country":"GB",
    "wof:name":"HP18 9SL",
    "wof:placetype":"postalcode"
},
  "geometry": {"coordinates":[-1.05573968210679,51.81766731344383],"type":"Point"}
}