{
  "type": "Feature",
  "properties": {
    "iso:country": "GB",
    "wof:name": "CB6 3DS",
    "wof:placetype": "postalcode"
  },
  "geometry": {"coordinates":[0.25001,52.3952],"type":"Point"}
}
