{
  "type": "Feature",
  "properties": {
    "date:inception_lower": "1980-01-01",
    "date:inception_upper": "1980-01-01",
    "iso:country": "GB",
    "wof:name": "CB6 3DS",
    "wof:placetype": "postalcode"
  },
  "geometry": {"coordinates":[0.25001,52.3952],"type":"Point"}
}
