{
  "type": "Feature",
  "properties": {
    "date:inception_lower": "1997-12-01",
    "date:inception_upper": "1997-12-01",
    "iso:country": "GB",
    "wof:name": "B78 1NQ",
    "wof:placetype": "postalcode"
  },
  "geometry": {"coordinates":[-1.610982,52.614343],"type":"Point"}
}
