{
  "type": "Feature",
  "properties": {
    "iso:country":"GB",
    "wof:name":"B78 1NQ",
    "wof:placetype":"postalcode"
},
  "geometry": {"coordinates":[-1.61098167770591,52.61434302428346],"type":"Point"}
}