{
  "type": "Feature",
  "properties": {
    "iso:country": "GB",
    "wof:name": "B78 1NQ",
    "wof:placetype": "postalcode"
  },
  "geometry": {"coordinates":[-1.610982,52.614343],"type":"Point"}
}
