{
  "type": "Feature",
  "properties": {
    "iso:country":"GB",
    "wof:name":"PE13 2BT",
    "wof:placetype":"postalcode"
},
  "geometry": {"coordinates":[0.16595152017488,52.66309135635766],"type":"Point"}
}