{
  "type": "Feature",
  "properties": {
    "iso:country":"GB",
    "wof:name":"W14 9BP",
    "wof:placetype":"postalcode"
},
  "geometry": {"coordinates":[-0.20828774062682,51.49169659104933],"type":"Point"}
}