{
  "type": "Feature",
  "properties": {
    "iso:country": "GB",
    "wof:name": "SO22 4NH",
    "wof:placetype": "postalcode"
  },
  "geometry": {"coordinates":[-1.324488,51.057867],"type":"Point"}
}
