{
  "type": "Feature",
  "properties": {
    "iso:country":"GB",
    "wof:name":"IP8 3QJ",
    "wof:placetype":"postalcode"
},
  "geometry": {"coordinates":[1.01695805817163,52.03586629592366],"type":"Point"}
}