{
  "type": "Feature",
  "properties": {
    "iso:country": "GB",
    "wof:name": "IP8 3QJ",
    "wof:placetype": "postalcode"
  },
  "geometry": {"coordinates":[1.016958,52.035866],"type":"Point"}
}
