{
  "type": "Feature",
  "properties": {
    "iso:country":"GB",
    "wof:name":"BB4 8LQ",
    "wof:placetype":"postalcode"
},
  "geometry": {"coordinates":[-2.29127459125278,53.71522882218488],"type":"Point"}
}