{
  "type": "Feature",
  "properties": {
    "date:inception_lower": "1980-01-01",
    "date:inception_upper": "1980-01-01",
    "iso:country": "GB",
    "wof:name": "BN12 4RU",
    "wof:placetype": "postalcode"
  },
  "geometry": {"coordinates":[-0.418924,50.814516],"type":"Point"}
}
