{
  "type": "Feature",
  "properties": {
    "iso:country": "GB",
    "wof:name": "BN12 4RU",
    "wof:placetype": "postalcode"
  },
  "geometry": {"coordinates":[-0.418924,50.814516],"type":"Point"}
}
