{
  "type": "Feature",
  "properties": {
    "iso:country":"GB",
    "wof:name":"BN12 4RU",
    "wof:placetype":"postalcode"
},
  "geometry": {"coordinates":[-0.41892400770241,50.81451576294212],"type":"Point"}
}