{
  "type": "Feature",
  "properties": {
    "iso:country":"GB",
    "wof:name":"TA3 6QL",
    "wof:placetype":"postalcode"
},
  "geometry": {"coordinates":[-2.90628123511747,50.98630449402484],"type":"Point"}
}