{
  "type": "Feature",
  "properties": {
    "iso:country":"GB",
    "wof:name":"SY5 0NB",
    "wof:placetype":"postalcode"
},
  "geometry": {"coordinates":[-2.95292689700312,52.58965065677334],"type":"Point"}
}