{
  "type": "Feature",
  "properties": {
    "iso:country": "GB",
    "wof:name": "SY5 0NB",
    "wof:placetype": "postalcode"
  },
  "geometry": {"coordinates":[-2.953423,52.589446],"type":"Point"}
}
