{
  "type": "Feature",
  "properties": {
    "date:inception_lower":"1980-01-01",
    "date:inception_upper":"1980-01-31",
    "iso:country":"GB",
    "wof:name":"NG20 0PF",
    "wof:placetype":"postalcode"
},
  "geometry": {"coordinates":[-1.150566,53.207155],"type":"Point"}
}