{
  "type": "Feature",
  "properties": {
    "iso:country": "GB",
    "wof:name": "SA14 6DF",
    "wof:placetype": "postalcode"
  },
  "geometry": {"coordinates":[-4.090378,51.770281],"type":"Point"}
}
