{
  "type": "Feature",
  "properties": {
    "iso:country":"GB",
    "wof:name":"YO42 1YH",
    "wof:placetype":"postalcode"
},
  "geometry": {"coordinates":[-0.65655014606259,53.98355575051193],"type":"Point"}
}