{
  "type": "Feature",
  "properties": {
    "iso:country": "GB",
    "wof:name": "YO42 1YH",
    "wof:placetype": "postalcode"
  },
  "geometry": {"coordinates":[-0.656559,53.983574],"type":"Point"}
}
