{
  "type": "Feature",
  "properties": {
    "date:inception_lower": "2021-03-01",
    "date:inception_upper": "2021-03-01",
    "iso:country": "GB",
    "wof:name": "WF3 2GP",
    "wof:placetype": "postalcode"
  },
  "geometry": {"coordinates":[-1.547608,53.724661],"type":"Point"}
}
