{
  "type": "Feature",
  "properties": {
    "date:inception_lower":"1981-09-01",
    "date:inception_upper":"1981-09-30",
    "iso:country":"GB",
    "wof:name":"FY8 2RZ",
    "wof:placetype":"postalcode"
},
  "geometry": {"coordinates":[-3.035669,53.76607],"type":"Point"}
}