{
  "type": "Feature",
  "properties": {
    "iso:country":"GB",
    "wof:name":"FY8 2RZ",
    "wof:placetype":"postalcode"
},
  "geometry": {"coordinates":[-3.03566865370939,53.766069700939],"type":"Point"}
}