{
  "type": "Feature",
  "properties": {
    "date:inception_lower":"2010-08-01",
    "date:inception_upper":"2010-08-31",
    "iso:country":"GB",
    "wof:name":"BL3 3RQ",
    "wof:placetype":"postalcode"
},
  "geometry": {"coordinates":[-2.469252,53.555984],"type":"Point"}
}