{
  "type": "Feature",
  "properties": {
    "date:inception_lower":"2005-01-01",
    "date:inception_upper":"2005-01-31",
    "iso:country":"GB",
    "wof:name":"G69 8LB",
    "wof:placetype":"postalcode"
},
  "geometry": {"coordinates":[-4.086221,55.886462],"type":"Point"}
}