{
  "type": "Feature",
  "properties": {
    "iso:country":"GB",
    "wof:name":"G69 8LB",
    "wof:placetype":"postalcode"
},
  "geometry": {"coordinates":[-4.08622104371111,55.88646200960427],"type":"Point"}
}