{
  "type": "Feature",
  "properties": {
    "iso:country":"GB",
    "wof:name":"OL6 7HA",
    "wof:placetype":"postalcode"
},
  "geometry": {"coordinates":[-2.10422448237934,53.48915973738326],"type":"Point"}
}