{
  "type": "Feature",
  "properties": {
    "iso:country":"GB",
    "wof:name":"FY6 7PG",
    "wof:placetype":"postalcode"
},
  "geometry": {"coordinates":[-3.00971532433287,53.85279513544841],"type":"Point"}
}