{
  "type": "Feature",
  "properties": {
    "date:inception_lower":"1980-01-01",
    "date:inception_upper":"1980-01-31",
    "iso:country":"GB",
    "wof:name":"FY6 7PG",
    "wof:placetype":"postalcode"
},
  "geometry": {"coordinates":[-3.009715,53.852795],"type":"Point"}
}