{
  "type": "Feature",
  "properties": {
    "iso:country": "GB",
    "wof:name": "FY6 7PG",
    "wof:placetype": "postalcode"
  },
  "geometry": {"coordinates":[-3.009715,53.852795],"type":"Point"}
}
