{
  "type": "Feature",
  "properties": {
    "iso:country":"GB",
    "wof:name":"SN14 0BW",
    "wof:placetype":"postalcode"
},
  "geometry": {"coordinates":[-2.12855430358259,51.45878602285365],"type":"Point"}
}