{
  "type": "Feature",
  "properties": {
    "iso:country":"GB",
    "wof:name":"SY24 5DJ",
    "wof:placetype":"postalcode"
},
  "geometry": {"coordinates":[-3.95398352538481,52.47961637294761],"type":"Point"}
}