{
  "type": "Feature",
  "properties": {
    "iso:country": "GB",
    "wof:name": "SY24 5DJ",
    "wof:placetype": "postalcode"
  },
  "geometry": {"coordinates":[-3.953983,52.479616],"type":"Point"}
}
