{
  "type": "Feature",
  "properties": {
    "iso:country":"GB",
    "wof:name":"HA5 4BP",
    "wof:placetype":"postalcode"
},
  "geometry": {"coordinates":[-0.36087546287572,51.61260773399848],"type":"Point"}
}