{
  "type": "Feature",
  "properties": {
    "date:inception_lower": "1980-01-01",
    "date:inception_upper": "1980-01-01",
    "iso:country": "GB",
    "wof:name": "HA5 4BP",
    "wof:placetype": "postalcode"
  },
  "geometry": {"coordinates":[-0.360853,51.612611],"type":"Point"}
}
