{
  "type": "Feature",
  "properties": {
    "date:inception_lower": "1980-01-01",
    "date:inception_upper": "1980-01-01",
    "iso:country": "GB",
    "wof:name": "LL55 1HD",
    "wof:placetype": "postalcode"
  },
  "geometry": {"coordinates":[-4.265132,53.144208],"type":"Point"}
}
