{
  "type": "Feature",
  "properties": {
    "iso:country": "GB",
    "wof:name": "LL55 1HD",
    "wof:placetype": "postalcode"
  },
  "geometry": {"coordinates":[-4.265132,53.144208],"type":"Point"}
}
