{
  "type": "Feature",
  "properties": {
    "iso:country":"GB",
    "wof:name":"LL55 1HD",
    "wof:placetype":"postalcode"
},
  "geometry": {"coordinates":[-4.26513195459839,53.14420812253509],"type":"Point"}
}