{
  "type": "Feature",
  "properties": {
    "date:inception_lower": "2016-08-01",
    "date:inception_upper": "2016-08-01",
    "iso:country": "GB",
    "wof:name": "EX16 6FF",
    "wof:placetype": "postalcode"
  },
  "geometry": {"coordinates":[-3.48476,50.901795],"type":"Point"}
}
