{
  "type": "Feature",
  "properties": {
    "date:inception_lower": "1980-01-01",
    "date:inception_upper": "1980-01-01",
    "iso:country": "GB",
    "wof:name": "CF42 6TH",
    "wof:placetype": "postalcode"
  },
  "geometry": {"coordinates":[-3.51116,51.663849],"type":"Point"}
}
