{
  "type": "Feature",
  "properties": {
    "date:inception_lower":"1995-12-01",
    "date:inception_upper":"1995-12-31",
    "iso:country":"GB",
    "wof:name":"RM15 5XB",
    "wof:placetype":"postalcode"
},
  "geometry": {"coordinates":[0.287624,51.506056],"type":"Point"}
}