{
  "type": "Feature",
  "properties": {
    "iso:country":"GB",
    "wof:name":"B61 0SZ",
    "wof:placetype":"postalcode"
},
  "geometry": {"coordinates":[-2.05856456684605,52.35224386797817],"type":"Point"}
}