{
  "type": "Feature",
  "properties": {
    "date:inception_lower":"2002-12-01",
    "date:inception_upper":"2002-12-31",
    "iso:country":"GB",
    "wof:name":"B61 0SZ",
    "wof:placetype":"postalcode"
},
  "geometry": {"coordinates":[-2.058588,52.352276],"type":"Point"}
}