{
  "type": "Feature",
  "properties": {
    "iso:country": "GB",
    "wof:name": "TA24 8AP",
    "wof:placetype": "postalcode"
  },
  "geometry": {"coordinates":[-3.49125,51.203958],"type":"Point"}
}
