{
  "type": "Feature",
  "properties": {
    "iso:country":"GB",
    "wof:name":"M28 1BL",
    "wof:placetype":"postalcode"
},
  "geometry": {"coordinates":[-2.42786805183378,53.50730547600018],"type":"Point"}
}