{
  "type": "Feature",
  "properties": {
    "iso:country":"GB",
    "wof:name":"CF5 5JN",
    "wof:placetype":"postalcode"
},
  "geometry": {"coordinates":[-3.25108243509118,51.4718177366859],"type":"Point"}
}