{
  "type": "Feature",
  "properties": {
    "iso:country":"GB",
    "wof:name":"NG5 3GG",
    "wof:placetype":"postalcode"
},
  "geometry": {"coordinates":[-1.13801385731735,52.9944319266971],"type":"Point"}
}