{
  "type": "Feature",
  "properties": {
    "iso:country":"GB",
    "wof:name":"DN35 0RS",
    "wof:placetype":"postalcode"
},
  "geometry": {"coordinates":[-0.03970191046359,53.5432520030829],"type":"Point"}
}