{
  "type": "Feature",
  "properties": {
    "date:inception_lower":"1983-01-01",
    "date:inception_upper":"1983-01-31",
    "iso:country":"GB",
    "wof:name":"DN35 0RS",
    "wof:placetype":"postalcode"
},
  "geometry": {"coordinates":[-0.039702,53.543252],"type":"Point"}
}