{
  "type": "Feature",
  "properties": {
    "iso:country":"GB",
    "wof:name":"EC4V 3PT",
    "wof:placetype":"postalcode"
},
  "geometry": {"coordinates":[-0.0960986487465,51.51039590948605],"type":"Point"}
}