{
  "type": "Feature",
  "properties": {
    "date:inception_lower": "1980-01-01",
    "date:inception_upper": "1980-01-01",
    "iso:country": "GB",
    "wof:name": "WA4 3HG",
    "wof:placetype": "postalcode"
  },
  "geometry": {"coordinates":[-2.567827,53.370156],"type":"Point"}
}
