{
  "type": "Feature",
  "properties": {
    "iso:country":"GB",
    "wof:name":"WA4 3HG",
    "wof:placetype":"postalcode"
},
  "geometry": {"coordinates":[-2.56782795090866,53.37014013978798],"type":"Point"}
}