{
  "type": "Feature",
  "properties": {
    "iso:country": "GB",
    "wof:name": "TN33 0DU",
    "wof:placetype": "postalcode"
  },
  "geometry": {"coordinates":[0.501088,50.91445],"type":"Point"}
}
