{
  "type": "Feature",
  "properties": {
    "date:inception_lower": "1986-07-01",
    "date:inception_upper": "1986-07-01",
    "iso:country": "GB",
    "wof:name": "TN33 0DU",
    "wof:placetype": "postalcode"
  },
  "geometry": {"coordinates":[0.501088,50.91445],"type":"Point"}
}
