{
  "type": "Feature",
  "properties": {
    "date:inception_lower":"1994-12-01",
    "date:inception_upper":"1994-12-31",
    "iso:country":"GB",
    "wof:name":"EX20 1UA",
    "wof:placetype":"postalcode"
},
  "geometry": {"coordinates":[-3.981279,50.741611],"type":"Point"}
}