{
  "type": "Feature",
  "properties": {
    "iso:country":"GB",
    "wof:name":"OX4 3RW",
    "wof:placetype":"postalcode"
},
  "geometry": {"coordinates":[-1.21423953605715,51.73228312495674],"type":"Point"}
}