{
  "type": "Feature",
  "properties": {
    "iso:country":"GB",
    "wof:name":"HR1 2JY",
    "wof:placetype":"postalcode"
},
  "geometry": {"coordinates":[-2.70578600825715,52.05542997725757],"type":"Point"}
}