{
  "type": "Feature",
  "properties": {
    "iso:country": "GB",
    "wof:name": "HR1 2JY",
    "wof:placetype": "postalcode"
  },
  "geometry": {"coordinates":[-2.705786,52.05543],"type":"Point"}
}
