{
  "type": "Feature",
  "properties": {
    "iso:country":"GB",
    "wof:name":"BS34 5EG",
    "wof:placetype":"postalcode"
},
  "geometry": {"coordinates":[-2.58319015932528,51.53071352882209],"type":"Point"}
}