{
  "type": "Feature",
  "properties": {
    "iso:country": "GB",
    "wof:name": "BS34 5EG",
    "wof:placetype": "postalcode"
  },
  "geometry": {"coordinates":[-2.58319,51.530714],"type":"Point"}
}
