{
  "type": "Feature",
  "properties": {
    "date:inception_lower":"1980-01-01",
    "date:inception_upper":"1980-01-31",
    "iso:country":"GB",
    "wof:name":"OL13 0SH",
    "wof:placetype":"postalcode"
},
  "geometry": {"coordinates":[-2.22518,53.692254],"type":"Point"}
}