{
  "type": "Feature",
  "properties": {
    "date:inception_lower":"1996-06-01",
    "date:inception_upper":"1996-06-30",
    "iso:country":"GB",
    "wof:name":"IP28 7EU",
    "wof:placetype":"postalcode"
},
  "geometry": {"coordinates":[0.502669,52.346101],"type":"Point"}
}