{
  "type": "Feature",
  "properties": {
    "iso:country": "GB",
    "wof:name": "BS37 6JZ",
    "wof:placetype": "postalcode"
  },
  "geometry": {"coordinates":[-2.404841,51.532913],"type":"Point"}
}
