{
  "type": "Feature",
  "properties": {
    "date:inception_lower": "1998-06-01",
    "date:inception_upper": "1998-06-01",
    "iso:country": "GB",
    "wof:name": "BS37 6JZ",
    "wof:placetype": "postalcode"
  },
  "geometry": {"coordinates":[-2.404767,51.532903],"type":"Point"}
}
