{
  "type": "Feature",
  "properties": {
    "date:inception_lower": "1980-01-01",
    "date:inception_upper": "1980-01-01",
    "iso:country": "GB",
    "wof:name": "SL5 7AS",
    "wof:placetype": "postalcode"
  },
  "geometry": {"coordinates":[-0.663055,51.403165],"type":"Point"}
}
