{
  "type": "Feature",
  "properties": {
    "iso:country": "GB",
    "wof:name": "EX5 4DU",
    "wof:placetype": "postalcode"
  },
  "geometry": {"coordinates":[-3.488171,50.802241],"type":"Point"}
}
