{
  "type": "Feature",
  "properties": {
    "iso:country":"GB",
    "wof:name":"EX5 4DU",
    "wof:placetype":"postalcode"
},
  "geometry": {"coordinates":[-3.48817115271586,50.80224126224774],"type":"Point"}
}