{
  "type": "Feature",
  "properties": {
    "iso:country":"GB",
    "wof:name":"SK17 8RL",
    "wof:placetype":"postalcode"
},
  "geometry": {"coordinates":[-1.73779029112887,53.2843916803432],"type":"Point"}
}