{
  "type": "Feature",
  "properties": {
    "iso:country":"GB",
    "wof:name":"LS27 8BP",
    "wof:placetype":"postalcode"
},
  "geometry": {"coordinates":[-1.59935824869078,53.74560900863466],"type":"Point"}
}