{
  "type": "Feature",
  "properties": {
    "date:inception_lower": "1999-12-01",
    "date:inception_upper": "1999-12-01",
    "iso:country": "GB",
    "wof:name": "LS27 8BP",
    "wof:placetype": "postalcode"
  },
  "geometry": {"coordinates":[-1.599358,53.745609],"type":"Point"}
}
