{
  "type": "Feature",
  "properties": {
    "iso:country":"GB",
    "wof:name":"YO32 9SN",
    "wof:placetype":"postalcode"
},
  "geometry": {"coordinates":[-1.05240963649881,54.00788396266813],"type":"Point"}
}