{
  "type": "Feature",
  "properties": {
    "iso:country":"GB",
    "wof:name":"CV5 7EW",
    "wof:placetype":"postalcode"
},
  "geometry": {"coordinates":[-1.5894535887371,52.41599677468241],"type":"Point"}
}