{
  "type": "Feature",
  "properties": {
    "date:inception_lower":"1983-07-01",
    "date:inception_upper":"1983-07-31",
    "iso:country":"GB",
    "wof:name":"PR6 7UL",
    "wof:placetype":"postalcode"
},
  "geometry": {"coordinates":[-2.646832,53.701244],"type":"Point"}
}