{
  "type": "Feature",
  "properties": {
    "iso:country":"GB",
    "wof:name":"PR6 7UL",
    "wof:placetype":"postalcode"
},
  "geometry": {"coordinates":[-2.6468317723951,53.70124360898868],"type":"Point"}
}