{
  "type": "Feature",
  "properties": {
    "iso:country":"GB",
    "wof:name":"NG6 0EW",
    "wof:placetype":"postalcode"
},
  "geometry": {"coordinates":[-1.17767313487739,52.99373288263683],"type":"Point"}
}