{
  "type": "Feature",
  "properties": {
    "date:inception_lower": "1985-04-01",
    "date:inception_upper": "1985-04-01",
    "iso:country": "GB",
    "wof:name": "NG6 0EW",
    "wof:placetype": "postalcode"
  },
  "geometry": {"coordinates":[-1.177673,52.993733],"type":"Point"}
}
