{
  "type": "Feature",
  "properties": {
    "iso:country":"GB",
    "wof:name":"PL14 6AZ",
    "wof:placetype":"postalcode"
},
  "geometry": {"coordinates":[-4.46560046420149,50.45603181173654],"type":"Point"}
}