{
  "type": "Feature",
  "properties": {
    "date:inception_lower": "1980-01-01",
    "date:inception_upper": "1980-01-01",
    "iso:country": "GB",
    "wof:name": "PL14 6AZ",
    "wof:placetype": "postalcode"
  },
  "geometry": {"coordinates":[-4.4656,50.456032],"type":"Point"}
}
