{
  "type": "Feature",
  "properties": {
    "iso:country": "GB",
    "wof:name": "SO22 4JL",
    "wof:placetype": "postalcode"
  },
  "geometry": {"coordinates":[-1.350786,51.046604],"type":"Point"}
}
