{
  "type": "Feature",
  "properties": {
    "iso:country":"GB",
    "wof:name":"BN22 0PU",
    "wof:placetype":"postalcode"
},
  "geometry": {"coordinates":[0.25427751343266,50.80637131986481],"type":"Point"}
}