{
  "type": "Feature",
  "properties": {
    "date:inception_lower": "1980-01-01",
    "date:inception_upper": "1980-01-01",
    "iso:country": "GB",
    "wof:name": "EN6 3HF",
    "wof:placetype": "postalcode"
  },
  "geometry": {"coordinates":[-0.206671,51.695721],"type":"Point"}
}
