{
  "type": "Feature",
  "properties": {
    "iso:country": "GB",
    "wof:name": "EN6 3HF",
    "wof:placetype": "postalcode"
  },
  "geometry": {"coordinates":[-0.206595,51.695679],"type":"Point"}
}
