{
  "type": "Feature",
  "properties": {
    "iso:country":"GB",
    "wof:name":"EN6 3HF",
    "wof:placetype":"postalcode"
},
  "geometry": {"coordinates":[-0.20659522469171,51.69567948941215],"type":"Point"}
}