{
  "type": "Feature",
  "properties": {
    "iso:country":"GB",
    "wof:name":"LA11 7GS",
    "wof:placetype":"postalcode"
},
  "geometry": {"coordinates":[-3.31091193406248,53.11501253512498],"type":"Point"}
}