{
  "type": "Feature",
  "properties": {
    "date:inception_lower": "2024-06-01",
    "date:inception_upper": "2024-06-01",
    "iso:country": "GB",
    "wof:name": "GU11 1GA",
    "wof:placetype": "postalcode"
  },
  "geometry": {"coordinates":[-0.770448,51.250034],"type":"Point"}
}
