{
  "type": "Feature",
  "properties": {
    "iso:country": "GB",
    "wof:name": "GL5 3TU",
    "wof:placetype": "postalcode"
  },
  "geometry": {"coordinates":[-2.230137,51.738194],"type":"Point"}
}
