{
  "type": "Feature",
  "properties": {
    "iso:country":"GB",
    "wof:name":"GL5 3TU",
    "wof:placetype":"postalcode"
},
  "geometry": {"coordinates":[-2.2296452793664,51.73764131793417],"type":"Point"}
}