{
  "type": "Feature",
  "properties": {
    "date:inception_lower":"1980-01-01",
    "date:inception_upper":"1980-01-31",
    "iso:country":"GB",
    "wof:name":"GL5 3TU",
    "wof:placetype":"postalcode"
},
  "geometry": {"coordinates":[-2.230137,51.738194],"type":"Point"}
}