{
  "type": "Feature",
  "properties": {
    "iso:country":"GB",
    "wof:name":"TN30 6LN",
    "wof:placetype":"postalcode"
},
  "geometry": {"coordinates":[0.69019158822692,51.07097210783214],"type":"Point"}
}