{
  "type": "Feature",
  "properties": {
    "iso:country":"GB",
    "wof:name":"SY1 1UB",
    "wof:placetype":"postalcode"
},
  "geometry": {"coordinates":[-2.75232227608096,52.70592335765059],"type":"Point"}
}