{
  "type": "Feature",
  "properties": {
    "iso:country": "GB",
    "wof:name": "YO8 9AY",
    "wof:placetype": "postalcode"
  },
  "geometry": {"coordinates":[-1.077936,53.770777],"type":"Point"}
}
