{
  "type": "Feature",
  "properties": {
    "date:inception_lower": "1980-01-01",
    "date:inception_upper": "1980-01-01",
    "iso:country": "GB",
    "wof:name": "NR25 6HA",
    "wof:placetype": "postalcode"
  },
  "geometry": {"coordinates":[1.09115,52.907339],"type":"Point"}
}
