{
  "type": "Feature",
  "properties": {
    "iso:country":"GB",
    "wof:name":"B62 8ST",
    "wof:placetype":"postalcode"
},
  "geometry": {"coordinates":[-2.03647645904644,52.45001990846357],"type":"Point"}
}