{
  "type": "Feature",
  "properties": {
    "iso:country":"GB",
    "wof:name":"B74 3HU",
    "wof:placetype":"postalcode"
},
  "geometry": {"coordinates":[-1.88419523574759,52.58114093375342],"type":"Point"}
}