{
  "type": "Feature",
  "properties": {
    "iso:country": "GB",
    "wof:name": "B74 3HU",
    "wof:placetype": "postalcode"
  },
  "geometry": {"coordinates":[-1.884195,52.581141],"type":"Point"}
}
