{
  "type": "Feature",
  "properties": {
    "iso:country":"GB",
    "wof:name":"GU14 9SQ",
    "wof:placetype":"postalcode"
},
  "geometry": {"coordinates":[-0.78962608516486,51.29522341877497],"type":"Point"}
}