{
  "type": "Feature",
  "properties": {
    "iso:country": "GB",
    "wof:name": "TS21 3BS",
    "wof:placetype": "postalcode"
  },
  "geometry": {"coordinates":[-1.451263,54.654133],"type":"Point"}
}
