{
  "type": "Feature",
  "properties": {
    "iso:country":"GB",
    "wof:name":"TS21 3BS",
    "wof:placetype":"postalcode"
},
  "geometry": {"coordinates":[-1.45126283174562,54.65413346079296],"type":"Point"}
}