{
  "type": "Feature",
  "properties": {
    "iso:country":"GB",
    "wof:name":"L36 8EJ",
    "wof:placetype":"postalcode"
},
  "geometry": {"coordinates":[-2.85071847422646,53.43139850642798],"type":"Point"}
}