{
  "type": "Feature",
  "properties": {
    "iso:country":"GB",
    "wof:name":"SE23 3NA",
    "wof:placetype":"postalcode"
},
  "geometry": {"coordinates":[-0.052004998116,51.44505057316163],"type":"Point"}
}