{
  "type": "Feature",
  "properties": {
    "iso:country": "GB",
    "wof:name": "SK2 5QG",
    "wof:placetype": "postalcode"
  },
  "geometry": {"coordinates":[-2.129273,53.399996],"type":"Point"}
}
