{
  "type": "Feature",
  "properties": {
    "iso:country":"GB",
    "wof:name":"SK14 6AZ",
    "wof:placetype":"postalcode"
},
  "geometry": {"coordinates":[-2.01089058725326,53.44129640498011],"type":"Point"}
}