{
  "type": "Feature",
  "properties": {
    "date:inception_lower": "1980-01-01",
    "date:inception_upper": "1980-01-01",
    "iso:country": "GB",
    "wof:name": "SK14 6AZ",
    "wof:placetype": "postalcode"
  },
  "geometry": {"coordinates":[-2.010814,53.441313],"type":"Point"}
}
