{
  "type": "Feature",
  "properties": {
    "date:inception_lower": "1994-12-01",
    "date:inception_upper": "1994-12-01",
    "iso:country": "GB",
    "wof:name": "RH10 1YD",
    "wof:placetype": "postalcode"
  },
  "geometry": {"coordinates":[-0.186885,51.118483],"type":"Point"}
}
