{
  "type": "Feature",
  "properties": {
    "iso:country": "GB",
    "wof:name": "RH10 1YD",
    "wof:placetype": "postalcode"
  },
  "geometry": {"coordinates":[-0.186885,51.118483],"type":"Point"}
}
