{
  "type": "Feature",
  "properties": {
    "iso:country":"GB",
    "wof:name":"SN15 2JE",
    "wof:placetype":"postalcode"
},
  "geometry": {"coordinates":[-2.05370905307385,51.38492453730952],"type":"Point"}
}