{
  "type": "Feature",
  "properties": {
    "date:inception_lower": "1980-01-01",
    "date:inception_upper": "1980-01-01",
    "iso:country": "GB",
    "wof:name": "DG11 2JB",
    "wof:placetype": "postalcode"
  },
  "geometry": {"coordinates":[-3.351939,55.123213],"type":"Point"}
}
