{
  "type": "Feature",
  "properties": {
    "iso:country": "GB",
    "wof:name": "NR13 6QX",
    "wof:placetype": "postalcode"
  },
  "geometry": {"coordinates":[1.376056,52.674609],"type":"Point"}
}
