{
  "type": "Feature",
  "properties": {
    "iso:country":"GB",
    "wof:name":"NG12 3NG",
    "wof:placetype":"postalcode"
},
  "geometry": {"coordinates":[-1.03060653286619,52.90456308315363],"type":"Point"}
}