{
  "type": "Feature",
  "properties": {
    "date:inception_lower": "1980-01-01",
    "date:inception_upper": "1980-01-01",
    "iso:country": "GB",
    "wof:name": "NG12 3NG",
    "wof:placetype": "postalcode"
  },
  "geometry": {"coordinates":[-1.030606,52.904563],"type":"Point"}
}
