{
  "type": "Feature",
  "properties": {
    "iso:country": "GB",
    "wof:name": "NE6 3SR",
    "wof:placetype": "postalcode"
  },
  "geometry": {"coordinates":[-1.560103,54.964783],"type":"Point"}
}
