{
  "type": "Feature",
  "properties": {
    "iso:country": "GB",
    "wof:name": "B32 2LB",
    "wof:placetype": "postalcode"
  },
  "geometry": {"coordinates":[-1.972818,52.458941],"type":"Point"}
}
