{
  "type": "Feature",
  "properties": {
    "iso:country":"GB",
    "wof:name":"B32 2LB",
    "wof:placetype":"postalcode"
},
  "geometry": {"coordinates":[-1.97281782630863,52.4589406287982],"type":"Point"}
}