{
  "type": "Feature",
  "properties": {
    "date:inception_lower":"1992-01-01",
    "date:inception_upper":"1992-01-31",
    "iso:country":"GB",
    "wof:name":"ST5 3TF",
    "wof:placetype":"postalcode"
},
  "geometry": {"coordinates":[-2.22375,53.006305],"type":"Point"}
}