{
  "type": "Feature",
  "properties": {
    "iso:country":"GB",
    "wof:name":"DH9 8ES",
    "wof:placetype":"postalcode"
},
  "geometry": {"coordinates":[-1.74722257013807,54.86379733541702],"type":"Point"}
}