{
  "type": "Feature",
  "properties": {
    "date:inception_lower":"1980-01-01",
    "date:inception_upper":"1980-01-31",
    "iso:country":"GB",
    "wof:name":"DH9 8ES",
    "wof:placetype":"postalcode"
},
  "geometry": {"coordinates":[-1.747223,54.863797],"type":"Point"}
}