{
  "type": "Feature",
  "properties": {
    "iso:country": "GB",
    "wof:name": "DH9 8ES",
    "wof:placetype": "postalcode"
  },
  "geometry": {"coordinates":[-1.747223,54.863797],"type":"Point"}
}
