{
  "type": "Feature",
  "properties": {
    "iso:country":"GB",
    "wof:name":"B60 1EE",
    "wof:placetype":"postalcode"
},
  "geometry": {"coordinates":[-2.0447477564334,52.36530362761237],"type":"Point"}
}