{
  "type": "Feature",
  "properties": {
    "date:inception_lower": "2013-01-01",
    "date:inception_upper": "2013-01-01",
    "iso:country": "GB",
    "wof:name": "PO21 1FY",
    "wof:placetype": "postalcode"
  },
  "geometry": {"coordinates":[-0.67307,50.790128],"type":"Point"}
}
