{
  "type": "Feature",
  "properties": {
    "iso:country":"GB",
    "wof:name":"PO21 1FY",
    "wof:placetype":"postalcode"
},
  "geometry": {"coordinates":[-0.67306963433249,50.79012823074561],"type":"Point"}
}