{
  "type": "Feature",
  "properties": {
    "iso:country":"GB",
    "wof:name":"TN16 1FA",
    "wof:placetype":"postalcode"
},
  "geometry": {"coordinates":[0.10397622182086,51.27545318821774],"type":"Point"}
}