{
  "type": "Feature",
  "properties": {
    "date:inception_lower": "2014-11-01",
    "date:inception_upper": "2014-11-01",
    "iso:country": "GB",
    "wof:name": "TN16 1FA",
    "wof:placetype": "postalcode"
  },
  "geometry": {"coordinates":[0.103976,51.275453],"type":"Point"}
}
