{
  "type": "Feature",
  "properties": {
    "date:inception_lower":"1995-07-01",
    "date:inception_upper":"1995-07-31",
    "iso:country":"GB",
    "wof:name":"WA6 7NQ",
    "wof:placetype":"postalcode"
},
  "geometry": {"coordinates":[-2.711281,53.302251],"type":"Point"}
}