{
  "type": "Feature",
  "properties": {
    "iso:country":"GB",
    "wof:name":"WA6 7NQ",
    "wof:placetype":"postalcode"
},
  "geometry": {"coordinates":[-2.71128094202737,53.30225148619591],"type":"Point"}
}