{
  "type": "Feature",
  "properties": {
    "iso:country":"GB",
    "wof:name":"M32 8HX",
    "wof:placetype":"postalcode"
},
  "geometry": {"coordinates":[-2.30380621840093,53.44384022430819],"type":"Point"}
}