{
  "type": "Feature",
  "properties": {
    "iso:country": "GB",
    "wof:name": "M32 8HX",
    "wof:placetype": "postalcode"
  },
  "geometry": {"coordinates":[-2.303806,53.44384],"type":"Point"}
}
