{
  "type": "Feature",
  "properties": {
    "iso:country": "GB",
    "wof:name": "NN8 1EU",
    "wof:placetype": "postalcode"
  },
  "geometry": {"coordinates":[-0.691191,52.301614],"type":"Point"}
}
