{
  "type": "Feature",
  "properties": {
    "iso:country":"GB",
    "wof:name":"NN8 1EU",
    "wof:placetype":"postalcode"
},
  "geometry": {"coordinates":[-0.69115279640404,52.30140719081407],"type":"Point"}
}