{
  "type": "Feature",
  "properties": {
    "iso:country":"GB",
    "wof:name":"BD23 3JQ",
    "wof:placetype":"postalcode"
},
  "geometry": {"coordinates":[-2.12793768209409,53.93967355828613],"type":"Point"}
}