{
  "type": "Feature",
  "properties": {
    "iso:country":"GB",
    "wof:name":"SW19 7DX",
    "wof:placetype":"postalcode"
},
  "geometry": {"coordinates":[-0.20670130770467,51.42967801023265],"type":"Point"}
}