{
  "type": "Feature",
  "properties": {
    "iso:country":"GB",
    "wof:name":"BR3 4TD",
    "wof:placetype":"postalcode"
},
  "geometry": {"coordinates":[-0.05490578189342,51.40285090330448],"type":"Point"}
}