{
  "type": "Feature",
  "properties": {
    "iso:country": "GB",
    "wof:name": "EH37 5SQ",
    "wof:placetype": "postalcode"
  },
  "geometry": {"coordinates":[-2.96357,55.86446],"type":"Point"}
}
