{
  "type": "Feature",
  "properties": {
    "iso:country":"GB",
    "wof:name":"DY4 0DG",
    "wof:placetype":"postalcode"
},
  "geometry": {"coordinates":[-2.04918402468561,52.55022600521195],"type":"Point"}
}