{
  "type": "Feature",
  "properties": {
    "date:inception_lower": "1980-01-01",
    "date:inception_upper": "1980-01-01",
    "iso:country": "GB",
    "wof:name": "WF7 5HR",
    "wof:placetype": "postalcode"
  },
  "geometry": {"coordinates":[-1.35835,53.675307],"type":"Point"}
}
