{
  "type": "Feature",
  "properties": {
    "iso:country":"GB",
    "wof:name":"WF7 5HR",
    "wof:placetype":"postalcode"
},
  "geometry": {"coordinates":[-1.35834982896265,53.67530713502973],"type":"Point"}
}