{
  "type": "Feature",
  "properties": {
    "iso:country": "GB",
    "wof:name": "WF7 5HR",
    "wof:placetype": "postalcode"
  },
  "geometry": {"coordinates":[-1.35835,53.675307],"type":"Point"}
}
