{
  "type": "Feature",
  "properties": {
    "iso:country":"GB",
    "wof:name":"AB12 3SU",
    "wof:placetype":"postalcode"
},
  "geometry": {"coordinates":[-2.0933794789485,57.10395671881412],"type":"Point"}
}