{
  "type": "Feature",
  "properties": {
    "iso:country": "GB",
    "wof:name": "AB12 3SU",
    "wof:placetype": "postalcode"
  },
  "geometry": {"coordinates":[-2.093322,57.103636],"type":"Point"}
}
