{
  "type": "Feature",
  "properties": {
    "iso:country": "GB",
    "wof:name": "HD5 8AN",
    "wof:placetype": "postalcode"
  },
  "geometry": {"coordinates":[-1.761389,53.64381],"type":"Point"}
}
