{
  "type": "Feature",
  "properties": {
    "iso:country":"GB",
    "wof:name":"HD5 8AN",
    "wof:placetype":"postalcode"
},
  "geometry": {"coordinates":[-1.76138918712076,53.6438096885289],"type":"Point"}
}