{
  "type": "Feature",
  "properties": {
    "iso:country":"GB",
    "wof:name":"BA2 7BU",
    "wof:placetype":"postalcode"
},
  "geometry": {"coordinates":[-2.34665513176294,51.35056070934373],"type":"Point"}
}