{
  "type": "Feature",
  "properties": {
    "iso:country":"GB",
    "wof:name":"SO18 2JX",
    "wof:placetype":"postalcode"
},
  "geometry": {"coordinates":[-1.37642340800432,50.94004072430869],"type":"Point"}
}