{
  "type": "Feature",
  "properties": {
    "iso:country":"GB",
    "wof:name":"N11 2EZ",
    "wof:placetype":"postalcode"
},
  "geometry": {"coordinates":[-0.12890949311233,51.60327650282619],"type":"Point"}
}