{
  "type": "Feature",
  "properties": {
    "iso:country": "GB",
    "wof:name": "DH4 5HZ",
    "wof:placetype": "postalcode"
  },
  "geometry": {"coordinates":[-1.480706,54.850181],"type":"Point"}
}
