{
  "type": "Feature",
  "properties": {
    "date:inception_lower":"1993-08-01",
    "date:inception_upper":"1993-08-31",
    "iso:country":"GB",
    "wof:name":"DH4 5HZ",
    "wof:placetype":"postalcode"
},
  "geometry": {"coordinates":[-1.480706,54.850181],"type":"Point"}
}