{
  "type": "Feature",
  "properties": {
    "iso:country":"GB",
    "wof:name":"ME20 7XE",
    "wof:placetype":"postalcode"
},
  "geometry": {"coordinates":[0.5015215738053,51.30501783149079],"type":"Point"}
}