{
  "type": "Feature",
  "properties": {
    "date:inception_lower": "1997-06-01",
    "date:inception_upper": "1997-06-01",
    "iso:country": "GB",
    "wof:name": "ME20 7XE",
    "wof:placetype": "postalcode"
  },
  "geometry": {"coordinates":[0.501522,51.305018],"type":"Point"}
}
