{
  "type": "Feature",
  "properties": {
    "iso:country": "GB",
    "wof:name": "BN6 9QX",
    "wof:placetype": "postalcode"
  },
  "geometry": {"coordinates":[-0.169725,50.932364],"type":"Point"}
}
