{
  "type": "Feature",
  "properties": {
    "date:inception_lower": "1980-01-01",
    "date:inception_upper": "1980-01-01",
    "iso:country": "GB",
    "wof:name": "BN6 9QX",
    "wof:placetype": "postalcode"
  },
  "geometry": {"coordinates":[-0.169725,50.932364],"type":"Point"}
}
