{
  "type": "Feature",
  "properties": {
    "iso:country": "GB",
    "wof:name": "EN4 9AY",
    "wof:placetype": "postalcode"
  },
  "geometry": {"coordinates":[-0.171971,51.65504],"type":"Point"}
}
