{
  "type": "Feature",
  "properties": {
    "iso:country":"GB",
    "wof:name":"BH12 1HY",
    "wof:placetype":"postalcode"
},
  "geometry": {"coordinates":[-1.90515822997121,50.73052204062272],"type":"Point"}
}