{
  "type": "Feature",
  "properties": {
    "iso:country":"GB",
    "wof:name":"TW5 9LD",
    "wof:placetype":"postalcode"
},
  "geometry": {"coordinates":[-0.39716823142644,51.48299195625859],"type":"Point"}
}