{
  "type": "Feature",
  "properties": {
    "date:inception_lower":"1988-03-01",
    "date:inception_upper":"1988-03-31",
    "iso:country":"GB",
    "wof:name":"M19 2NU",
    "wof:placetype":"postalcode"
},
  "geometry": {"coordinates":[-2.199376,53.435899],"type":"Point"}
}