{
  "type": "Feature",
  "properties": {
    "date:inception_lower": "1995-01-01",
    "date:inception_upper": "1995-01-01",
    "iso:country": "GB",
    "wof:name": "LS2 8AA",
    "wof:placetype": "postalcode"
  },
  "geometry": {"coordinates":[-1.544508,53.804022],"type":"Point"}
}
