{
  "type": "Feature",
  "properties": {
    "iso:country": "GB",
    "wof:name": "MK19 6BJ",
    "wof:placetype": "postalcode"
  },
  "geometry": {"coordinates":[-0.917936,52.059943],"type":"Point"}
}
