{
  "type": "Feature",
  "properties": {
    "iso:country":"GB",
    "wof:name":"SG2 7QL",
    "wof:placetype":"postalcode"
},
  "geometry": {"coordinates":[-0.16180624119963,51.91009573702789],"type":"Point"}
}