{
  "type": "Feature",
  "properties": {
    "iso:country": "GB",
    "wof:name": "SG2 7QL",
    "wof:placetype": "postalcode"
  },
  "geometry": {"coordinates":[-0.161806,51.910096],"type":"Point"}
}
