{
  "type": "Feature",
  "properties": {
    "iso:country": "GB",
    "wof:name": "DN2 5BF",
    "wof:placetype": "postalcode"
  },
  "geometry": {"coordinates":[-1.116892,53.528634],"type":"Point"}
}
