{
  "type": "Feature",
  "properties": {
    "iso:country":"GB",
    "wof:name":"BA21 5XB",
    "wof:placetype":"postalcode"
},
  "geometry": {"coordinates":[-2.61068391016999,50.95886423320913],"type":"Point"}
}