{
  "type": "Feature",
  "properties": {
    "date:inception_lower": "1995-12-01",
    "date:inception_upper": "1995-12-01",
    "iso:country": "GB",
    "wof:name": "GL4 6EF",
    "wof:placetype": "postalcode"
  },
  "geometry": {"coordinates":[-2.220465,51.826949],"type":"Point"}
}
