{
  "type": "Feature",
  "properties": {
    "iso:country":"GB",
    "wof:name":"GL4 6EF",
    "wof:placetype":"postalcode"
},
  "geometry": {"coordinates":[-2.22046486616933,51.82694897780132],"type":"Point"}
}