{
  "type": "Feature",
  "properties": {
    "iso:country":"GB",
    "wof:name":"M14 6UZ",
    "wof:placetype":"postalcode"
},
  "geometry": {"coordinates":[-2.21556426064503,53.43730881686039],"type":"Point"}
}