{
  "type": "Feature",
  "properties": {
    "date:inception_lower": "1980-01-01",
    "date:inception_upper": "1980-01-01",
    "iso:country": "GB",
    "wof:name": "PR4 2PN",
    "wof:placetype": "postalcode"
  },
  "geometry": {"coordinates":[-2.913651,53.775241],"type":"Point"}
}
