{
  "type": "Feature",
  "properties": {
    "iso:country":"GB",
    "wof:name":"PR4 2PN",
    "wof:placetype":"postalcode"
},
  "geometry": {"coordinates":[-2.91365091475019,53.77524138891467],"type":"Point"}
}