{
  "type": "Feature",
  "properties": {
    "date:inception_lower": "2002-07-01",
    "date:inception_upper": "2002-07-01",
    "iso:country": "GB",
    "wof:name": "HD9 6RX",
    "wof:placetype": "postalcode"
  },
  "geometry": {"coordinates":[-1.800316,53.603937],"type":"Point"}
}
