{
  "type": "Feature",
  "properties": {
    "iso:country":"GB",
    "wof:name":"HD9 6RX",
    "wof:placetype":"postalcode"
},
  "geometry": {"coordinates":[-1.80031590094208,53.6039371407774],"type":"Point"}
}