{
  "type": "Feature",
  "properties": {
    "iso:country":"GB",
    "wof:name":"HU6 9LH",
    "wof:placetype":"postalcode"
},
  "geometry": {"coordinates":[-0.36987895505998,53.78378971728016],"type":"Point"}
}