{
  "type": "Feature",
  "properties": {
    "iso:country":"GB",
    "wof:name":"SN16 9LU",
    "wof:placetype":"postalcode"
},
  "geometry": {"coordinates":[-2.0906790839274,51.57840763479786],"type":"Point"}
}