{
  "type": "Feature",
  "properties": {
    "iso:country": "GB",
    "wof:name": "SN7 8AB",
    "wof:placetype": "postalcode"
  },
  "geometry": {"coordinates":[-1.58047,51.65867],"type":"Point"}
}
