{
  "type": "Feature",
  "properties": {
    "iso:country": "GB",
    "wof:name": "ME12 1RR",
    "wof:placetype": "postalcode"
  },
  "geometry": {"coordinates":[0.753749,51.442629],"type":"Point"}
}
