{
  "type": "Feature",
  "properties": {
    "iso:country":"GB",
    "wof:name":"CV23 0NG",
    "wof:placetype":"postalcode"
},
  "geometry": {"coordinates":[-1.37305148534611,52.4131958826495],"type":"Point"}
}