{
  "type": "Feature",
  "properties": {
    "date:inception_lower":"1980-01-01",
    "date:inception_upper":"1980-01-31",
    "iso:country":"GB",
    "wof:name":"CV23 0NG",
    "wof:placetype":"postalcode"
},
  "geometry": {"coordinates":[-1.373051,52.413196],"type":"Point"}
}