{
  "type": "Feature",
  "properties": {
    "iso:country": "GB",
    "wof:name": "RG7 2BE",
    "wof:placetype": "postalcode"
  },
  "geometry": {"coordinates":[-0.99563,51.374008],"type":"Point"}
}
