{
  "type": "Feature",
  "properties": {
    "date:inception_lower":"1980-01-01",
    "date:inception_upper":"1980-01-31",
    "iso:country":"GB",
    "wof:name":"RG7 2BE",
    "wof:placetype":"postalcode"
},
  "geometry": {"coordinates":[-0.99563,51.374008],"type":"Point"}
}