{
  "type": "Feature",
  "properties": {
    "iso:country":"GB",
    "wof:name":"BN1 3YE",
    "wof:placetype":"postalcode"
},
  "geometry": {"coordinates":[-0.1425283833282,50.82618099706715],"type":"Point"}
}