{
  "type": "Feature",
  "properties": {
    "iso:country": "GB",
    "wof:name": "TN12 9RT",
    "wof:placetype": "postalcode"
  },
  "geometry": {"coordinates":[0.454775,51.185808],"type":"Point"}
}
