{
  "type": "Feature",
  "properties": {
    "iso:country":"GB",
    "wof:name":"DA15 7LT",
    "wof:placetype":"postalcode"
},
  "geometry": {"coordinates":[0.08740494967238,51.43097801997759],"type":"Point"}
}