{
  "type": "Feature",
  "properties": {
    "date:inception_lower":"1995-07-01",
    "date:inception_upper":"1995-07-31",
    "iso:country":"GB",
    "wof:name":"UB7 7GN",
    "wof:placetype":"postalcode"
},
  "geometry": {"coordinates":[-0.477846,51.516602],"type":"Point"}
}