{
  "type": "Feature",
  "properties": {
    "iso:country":"GB",
    "wof:name":"UB7 7GN",
    "wof:placetype":"postalcode"
},
  "geometry": {"coordinates":[-0.47786734243726,51.51658282751491],"type":"Point"}
}