{
  "type": "Feature",
  "properties": {
    "iso:country": "GB",
    "wof:name": "GL50 1LR",
    "wof:placetype": "postalcode"
  },
  "geometry": {"coordinates":[-2.075036,51.900705],"type":"Point"}
}
