{
  "type": "Feature",
  "properties": {
    "iso:country":"GB",
    "wof:name":"RM6 5DU",
    "wof:placetype":"postalcode"
},
  "geometry": {"coordinates":[0.1242628499656,51.57998361549136],"type":"Point"}
}