{
  "type": "Feature",
  "properties": {
    "iso:country": "GB",
    "wof:name": "LS17 5ND",
    "wof:placetype": "postalcode"
  },
  "geometry": {"coordinates":[-1.559745,53.844941],"type":"Point"}
}
