{
  "type": "Feature",
  "properties": {
    "iso:country":"GB",
    "wof:name":"LS17 5ND",
    "wof:placetype":"postalcode"
},
  "geometry": {"coordinates":[-1.55974514941444,53.84494077063014],"type":"Point"}
}