{
  "type": "Feature",
  "properties": {
    "iso:country":"GB",
    "wof:name":"NE24 2AS",
    "wof:placetype":"postalcode"
},
  "geometry": {"coordinates":[-1.50426434891619,55.12846787101158],"type":"Point"}
}