{
  "type": "Feature",
  "properties": {
    "date:inception_lower": "1980-01-01",
    "date:inception_upper": "1980-01-01",
    "iso:country": "GB",
    "wof:name": "NE24 2AS",
    "wof:placetype": "postalcode"
  },
  "geometry": {"coordinates":[-1.504117,55.128824],"type":"Point"}
}
