{
  "type": "Feature",
  "properties": {
    "date:inception_lower": "1980-01-01",
    "date:inception_upper": "1980-01-01",
    "iso:country": "GB",
    "wof:name": "CF46 6BT",
    "wof:placetype": "postalcode"
  },
  "geometry": {"coordinates":[-3.293193,51.663337],"type":"Point"}
}
