{
  "type": "Feature",
  "properties": {
    "iso:country":"GB",
    "wof:name":"HR2 6PJ",
    "wof:placetype":"postalcode"
},
  "geometry": {"coordinates":[-2.68247702829875,51.98343398308419],"type":"Point"}
}