{
  "type": "Feature",
  "properties": {
    "iso:country":"GB",
    "wof:name":"RG24 8SJ",
    "wof:placetype":"postalcode"
},
  "geometry": {"coordinates":[-1.0616116036538,51.28778214938729],"type":"Point"}
}