{
  "type": "Feature",
  "properties": {
    "iso:country":"GB",
    "wof:name":"WR15 8PW",
    "wof:placetype":"postalcode"
},
  "geometry": {"coordinates":[-2.59549088811284,52.28141436487626],"type":"Point"}
}