{
  "type": "Feature",
  "properties": {
    "date:inception_lower": "1980-01-01",
    "date:inception_upper": "1980-01-01",
    "iso:country": "GB",
    "wof:name": "CW7 2HW",
    "wof:placetype": "postalcode"
  },
  "geometry": {"coordinates":[-2.543608,53.194728],"type":"Point"}
}
