{
  "type": "Feature",
  "properties": {
    "iso:country":"GB",
    "wof:name":"CW7 2HW",
    "wof:placetype":"postalcode"
},
  "geometry": {"coordinates":[-2.54360818006805,53.19472766507631],"type":"Point"}
}