{
  "type": "Feature",
  "properties": {
    "date:inception_lower": "1973-08-01",
    "date:inception_upper": "1973-08-01",
    "iso:country": "GB",
    "wof:name": "G63 0NQ",
    "wof:placetype": "postalcode"
  },
  "geometry": {"coordinates":[-4.411698,56.081469],"type":"Point"}
}
