{
  "type": "Feature",
  "properties": {
    "iso:country":"GB",
    "wof:name":"G63 0NQ",
    "wof:placetype":"postalcode"
},
  "geometry": {"coordinates":[-4.42385840797482,56.08239003532491],"type":"Point"}
}