{
  "type": "Feature",
  "properties": {
    "iso:country": "GB",
    "wof:name": "CM77 8JJ",
    "wof:placetype": "postalcode"
  },
  "geometry": {"coordinates":[0.586758,51.856575],"type":"Point"}
}
