{
  "type": "Feature",
  "properties": {
    "date:inception_lower": "1980-01-01",
    "date:inception_upper": "1980-01-01",
    "iso:country": "GB",
    "wof:name": "OX10 0JY",
    "wof:placetype": "postalcode"
  },
  "geometry": {"coordinates":[-1.133635,51.603022],"type":"Point"}
}
