{
  "type": "Feature",
  "properties": {
    "iso:country": "GB",
    "wof:name": "OX10 0JY",
    "wof:placetype": "postalcode"
  },
  "geometry": {"coordinates":[-1.133635,51.603022],"type":"Point"}
}
