{
  "type": "Feature",
  "properties": {
    "date:inception_lower":"1980-01-01",
    "date:inception_upper":"1980-01-31",
    "iso:country":"GB",
    "wof:name":"TQ13 9XS",
    "wof:placetype":"postalcode"
},
  "geometry": {"coordinates":[-3.74113,50.582588],"type":"Point"}
}