{
  "type": "Feature",
  "properties": {
    "iso:country":"GB",
    "wof:name":"NW10 9NG",
    "wof:placetype":"postalcode"
},
  "geometry": {"coordinates":[-0.25133697056666,51.54608483584995],"type":"Point"}
}