{
  "type": "Feature",
  "properties": {
    "iso:country":"GB",
    "wof:name":"LL53 8TP",
    "wof:placetype":"postalcode"
},
  "geometry": {"coordinates":[-4.46862664813781,52.89339095731565],"type":"Point"}
}