{
  "type": "Feature",
  "properties": {
    "date:inception_lower": "1982-03-01",
    "date:inception_upper": "1982-03-01",
    "iso:country": "GB",
    "wof:name": "CW5 7PJ",
    "wof:placetype": "postalcode"
  },
  "geometry": {"coordinates":[-2.480905,53.01115],"type":"Point"}
}
