{
  "type": "Feature",
  "properties": {
    "iso:country":"GB",
    "wof:name":"EN2 7EU",
    "wof:placetype":"postalcode"
},
  "geometry": {"coordinates":[-0.11151559565093,51.65599002983258],"type":"Point"}
}