{
  "type": "Feature",
  "properties": {
    "iso:country":"GB",
    "wof:name":"FK8 3BZ",
    "wof:placetype":"postalcode"
},
  "geometry": {"coordinates":[-4.08964040688586,56.12434136929429],"type":"Point"}
}