{
  "type": "Feature",
  "properties": {
    "iso:country":"GB",
    "wof:name":"G69 7TU",
    "wof:placetype":"postalcode"
},
  "geometry": {"coordinates":[-4.07009208479326,55.84992345477777],"type":"Point"}
}