{
  "type": "Feature",
  "properties": {
    "iso:country":"GB",
    "wof:name":"NG3 3ED",
    "wof:placetype":"postalcode"
},
  "geometry": {"coordinates":[-1.12588215601998,52.96436346343441],"type":"Point"}
}