{
  "type": "Feature",
  "properties": {
    "iso:country":"GB",
    "wof:name":"SW1P 3AL",
    "wof:placetype":"postalcode"
},
  "geometry": {"coordinates":[-0.12804271151443,51.50033489653976],"type":"Point"}
}