{
  "type": "Feature",
  "properties": {
    "date:inception_lower":"1980-01-01",
    "date:inception_upper":"1980-01-31",
    "iso:country":"GB",
    "wof:name":"LS28 9NE",
    "wof:placetype":"postalcode"
},
  "geometry": {"coordinates":[-1.643174,53.782014],"type":"Point"}
}