{
  "type": "Feature",
  "properties": {
    "iso:country":"GB",
    "wof:name":"LS28 9NE",
    "wof:placetype":"postalcode"
},
  "geometry": {"coordinates":[-1.64317426118798,53.78201417592967],"type":"Point"}
}