{
  "type": "Feature",
  "properties": {
    "iso:country": "GB",
    "wof:name": "LS28 9NE",
    "wof:placetype": "postalcode"
  },
  "geometry": {"coordinates":[-1.643174,53.782014],"type":"Point"}
}
