{
  "type": "Feature",
  "properties": {
    "iso:country":"GB",
    "wof:name":"WF12 0AL",
    "wof:placetype":"postalcode"
},
  "geometry": {"coordinates":[-1.63131272973486,53.67208060352206],"type":"Point"}
}