{
  "type": "Feature",
  "properties": {
    "iso:country":"GB",
    "wof:name":"LS29 7JX",
    "wof:placetype":"postalcode"
},
  "geometry": {"coordinates":[-1.75018560719334,53.91409225704534],"type":"Point"}
}