{
  "type": "Feature",
  "properties": {
    "iso:country":"GB",
    "wof:name":"MK18 2GD",
    "wof:placetype":"postalcode"
},
  "geometry": {"coordinates":[-0.99993239517563,51.91246813200436],"type":"Point"}
}