{
  "type": "Feature",
  "properties": {
    "iso:country": "GB",
    "wof:name": "MK18 2GD",
    "wof:placetype": "postalcode"
  },
  "geometry": {"coordinates":[-0.999932,51.912468],"type":"Point"}
}
