{
  "type": "Feature",
  "properties": {
    "date:inception_lower":"2012-09-01",
    "date:inception_upper":"2012-09-30",
    "iso:country":"GB",
    "wof:name":"MK18 2GD",
    "wof:placetype":"postalcode"
},
  "geometry": {"coordinates":[-0.999932,51.912468],"type":"Point"}
}