{
  "type": "Feature",
  "properties": {
    "iso:country": "GB",
    "wof:name": "LL14 3DT",
    "wof:placetype": "postalcode"
  },
  "geometry": {"coordinates":[-3.072909,52.971816],"type":"Point"}
}
