{
  "type": "Feature",
  "properties": {
    "iso:country":"GB",
    "wof:name":"ST6 6DF",
    "wof:placetype":"postalcode"
},
  "geometry": {"coordinates":[-2.21021972714991,53.06154146384672],"type":"Point"}
}