{
  "type": "Feature",
  "properties": {
    "iso:country": "GB",
    "wof:name": "BA12 6HX",
    "wof:placetype": "postalcode"
  },
  "geometry": {"coordinates":[-2.269279,51.094135],"type":"Point"}
}
