{
  "type": "Feature",
  "properties": {
    "iso:country":"GB",
    "wof:name":"BA12 6HX",
    "wof:placetype":"postalcode"
},
  "geometry": {"coordinates":[-2.2692788521502,51.09413505482581],"type":"Point"}
}