{
  "type": "Feature",
  "properties": {
    "date:inception_lower": "2000-12-01",
    "date:inception_upper": "2000-12-01",
    "iso:country": "GB",
    "wof:name": "LS6 2SJ",
    "wof:placetype": "postalcode"
  },
  "geometry": {"coordinates":[-1.565183,53.821772],"type":"Point"}
}
