{
  "type": "Feature",
  "properties": {
    "date:inception_lower":"1980-01-01",
    "date:inception_upper":"1980-01-31",
    "iso:country":"GB",
    "wof:name":"HP22 5TZ",
    "wof:placetype":"postalcode"
},
  "geometry": {"coordinates":[-0.789163,51.787172],"type":"Point"}
}