{
  "type": "Feature",
  "properties": {
    "iso:country": "GB",
    "wof:name": "HP22 5TZ",
    "wof:placetype": "postalcode"
  },
  "geometry": {"coordinates":[-0.789163,51.787172],"type":"Point"}
}
