{
  "type": "Feature",
  "properties": {
    "iso:country": "GB",
    "wof:name": "KT13 9QU",
    "wof:placetype": "postalcode"
  },
  "geometry": {"coordinates":[-0.435824,51.375112],"type":"Point"}
}
