{
  "type": "Feature",
  "properties": {
    "date:inception_lower": "1993-08-01",
    "date:inception_upper": "1993-08-01",
    "iso:country": "GB",
    "wof:name": "NN17 4BA",
    "wof:placetype": "postalcode"
  },
  "geometry": {"coordinates":[-0.683824,52.511239],"type":"Point"}
}
