{
  "type": "Feature",
  "properties": {
    "iso:country":"GB",
    "wof:name":"NN17 4BA",
    "wof:placetype":"postalcode"
},
  "geometry": {"coordinates":[-0.68405538025514,52.51135049085183],"type":"Point"}
}