{
  "type": "Feature",
  "properties": {
    "date:inception_lower": "2017-09-01",
    "date:inception_upper": "2017-09-01",
    "iso:country": "GB",
    "wof:name": "BH8 0FD",
    "wof:placetype": "postalcode"
  },
  "geometry": {"coordinates":[-1.825247,50.751049],"type":"Point"}
}
