{
  "type": "Feature",
  "properties": {
    "iso:country":"GB",
    "wof:name":"NG8 6HL",
    "wof:placetype":"postalcode"
},
  "geometry": {"coordinates":[-1.21212145296453,52.97966389273397],"type":"Point"}
}