{
  "type": "Feature",
  "properties": {
    "date:inception_lower": "1980-01-01",
    "date:inception_upper": "1980-01-01",
    "iso:country": "GB",
    "wof:name": "M16 0LX",
    "wof:placetype": "postalcode"
  },
  "geometry": {"coordinates":[-2.278246,53.455911],"type":"Point"}
}
