{
  "type": "Feature",
  "properties": {
    "iso:country":"GB",
    "wof:name":"EH11 4JT",
    "wof:placetype":"postalcode"
},
  "geometry": {"coordinates":[-3.29471618157701,55.92131529990591],"type":"Point"}
}