{
  "type": "Feature",
  "properties": {
    "iso:country": "GB",
    "wof:name": "BA11 1BS",
    "wof:placetype": "postalcode"
  },
  "geometry": {"coordinates":[-2.321615,51.231931],"type":"Point"}
}
