{
  "type": "Feature",
  "properties": {
    "iso:country":"GB",
    "wof:name":"SN4 8HA",
    "wof:placetype":"postalcode"
},
  "geometry": {"coordinates":[-1.89188446870984,51.54542195754402],"type":"Point"}
}