{
  "type": "Feature",
  "properties": {
    "iso:country":"GB",
    "wof:name":"M4 6AG",
    "wof:placetype":"postalcode"
},
  "geometry": {"coordinates":[-2.22776485828028,53.48653405390784],"type":"Point"}
}