{
  "type": "Feature",
  "properties": {
    "date:inception_lower": "1980-01-01",
    "date:inception_upper": "1980-01-01",
    "iso:country": "GB",
    "wof:name": "M4 6AG",
    "wof:placetype": "postalcode"
  },
  "geometry": {"coordinates":[-2.227644,53.486579],"type":"Point"}
}
