{
  "type": "Feature",
  "properties": {
    "iso:country": "GB",
    "wof:name": "HX7 8JZ",
    "wof:placetype": "postalcode"
  },
  "geometry": {"coordinates":[-2.011608,53.74581],"type":"Point"}
}
