{
  "type": "Feature",
  "properties": {
    "iso:country":"GB",
    "wof:name":"YO30 2BQ",
    "wof:placetype":"postalcode"
},
  "geometry": {"coordinates":[-1.22959411153001,54.05901427774872],"type":"Point"}
}