{
  "type": "Feature",
  "properties": {
    "date:inception_lower": "1998-06-01",
    "date:inception_upper": "1998-06-01",
    "iso:country": "GB",
    "wof:name": "YO30 2BQ",
    "wof:placetype": "postalcode"
  },
  "geometry": {"coordinates":[-1.230055,54.059285],"type":"Point"}
}
