{
  "type": "Feature",
  "properties": {
    "iso:country": "GB",
    "wof:name": "YO30 2BQ",
    "wof:placetype": "postalcode"
  },
  "geometry": {"coordinates":[-1.230055,54.059285],"type":"Point"}
}
