{
  "type": "Feature",
  "properties": {
    "iso:country":"GB",
    "wof:name":"DN36 4LA",
    "wof:placetype":"postalcode"
},
  "geometry": {"coordinates":[-0.01861178703952,53.53592819321462],"type":"Point"}
}