{
  "type": "Feature",
  "properties": {
    "iso:country": "GB",
    "wof:name": "DN36 4LA",
    "wof:placetype": "postalcode"
  },
  "geometry": {"coordinates":[-0.018612,53.535928],"type":"Point"}
}
