{
  "type": "Feature",
  "properties": {
    "iso:country": "GB",
    "wof:name": "PL21 9BP",
    "wof:placetype": "postalcode"
  },
  "geometry": {"coordinates":[-3.930565,50.389819],"type":"Point"}
}
