{
  "type": "Feature",
  "properties": {
    "date:inception_lower": "1980-01-01",
    "date:inception_upper": "1980-01-01",
    "iso:country": "GB",
    "wof:name": "LE7 7EA",
    "wof:placetype": "postalcode"
  },
  "geometry": {"coordinates":[-1.185863,52.67631],"type":"Point"}
}
