{
  "type": "Feature",
  "properties": {
    "date:inception_lower": "1980-01-01",
    "date:inception_upper": "1980-01-01",
    "iso:country": "GB",
    "wof:name": "CR3 5JT",
    "wof:placetype": "postalcode"
  },
  "geometry": {"coordinates":[-0.098495,51.293315],"type":"Point"}
}
