{
  "type": "Feature",
  "properties": {
    "iso:country":"GB",
    "wof:name":"CR3 5JT",
    "wof:placetype":"postalcode"
},
  "geometry": {"coordinates":[-0.09849463627857,51.29331482805965],"type":"Point"}
}