{
  "type": "Feature",
  "properties": {
    "date:inception_lower": "1988-03-01",
    "date:inception_upper": "1988-03-01",
    "iso:country": "GB",
    "wof:name": "HA0 1XQ",
    "wof:placetype": "postalcode"
  },
  "geometry": {"coordinates":[-0.296223,51.53671],"type":"Point"}
}
