{
  "type": "Feature",
  "properties": {
    "iso:country":"GB",
    "wof:name":"SS13 2HW",
    "wof:placetype":"postalcode"
},
  "geometry": {"coordinates":[0.5326127163268,51.57104286945985],"type":"Point"}
}