{
  "type": "Feature",
  "properties": {
    "iso:country":"GB",
    "wof:name":"SP1 1EJ",
    "wof:placetype":"postalcode"
},
  "geometry": {"coordinates":[-1.79447603682809,51.06901570106434],"type":"Point"}
}