{
  "type": "Feature",
  "properties": {
    "date:inception_lower":"2015-12-01",
    "date:inception_upper":"2015-12-31",
    "iso:country":"GB",
    "wof:name":"PR4 3JT",
    "wof:placetype":"postalcode"
},
  "geometry": {"coordinates":[-2.884788,53.794798],"type":"Point"}
}