{
  "type": "Feature",
  "properties": {
    "iso:country":"GB",
    "wof:name":"PR4 3JT",
    "wof:placetype":"postalcode"
},
  "geometry": {"coordinates":[-2.90632001132467,53.80683700638051],"type":"Point"}
}