{
  "type": "Feature",
  "properties": {
    "iso:country":"GB",
    "wof:name":"ZE1 0RJ",
    "wof:placetype":"postalcode"
},
  "geometry": {"coordinates":[-1.16339183523955,60.1460609314604],"type":"Point"}
}