{
  "type": "Feature",
  "properties": {
    "iso:country": "GB",
    "wof:name": "TA18 8FG",
    "wof:placetype": "postalcode"
  },
  "geometry": {"coordinates":[-2.772483,50.869924],"type":"Point"}
}
