{
  "type": "Feature",
  "properties": {
    "date:inception_lower": "2018-03-01",
    "date:inception_upper": "2018-03-01",
    "iso:country": "GB",
    "wof:name": "TA18 8FG",
    "wof:placetype": "postalcode"
  },
  "geometry": {"coordinates":[-2.772412,50.869978],"type":"Point"}
}
