{
  "type": "Feature",
  "properties": {
    "date:inception_lower": "2007-03-01",
    "date:inception_upper": "2007-03-01",
    "iso:country": "GB",
    "wof:name": "WV16 4EN",
    "wof:placetype": "postalcode"
  },
  "geometry": {"coordinates":[-2.422947,52.537874],"type":"Point"}
}
