{
  "type": "Feature",
  "properties": {
    "iso:country":"GB",
    "wof:name":"OX9 2AP",
    "wof:placetype":"postalcode"
},
  "geometry": {"coordinates":[-0.98792395558094,51.74668309157128],"type":"Point"}
}