{
  "type": "Feature",
  "properties": {
    "iso:country":"GB",
    "wof:name":"CH61 6XD",
    "wof:placetype":"postalcode"
},
  "geometry": {"coordinates":[-3.10195281989882,53.3357502124539],"type":"Point"}
}