{
  "type": "Feature",
  "properties": {
    "iso:country":"GB",
    "wof:name":"CM5 0DL",
    "wof:placetype":"postalcode"
},
  "geometry": {"coordinates":[0.21924058011443,51.7454551021769],"type":"Point"}
}