{
  "type": "Feature",
  "properties": {
    "iso:country": "GB",
    "wof:name": "CM5 0DL",
    "wof:placetype": "postalcode"
  },
  "geometry": {"coordinates":[0.219284,51.745793],"type":"Point"}
}
