{
  "type": "Feature",
  "properties": {
    "iso:country":"GB",
    "wof:name":"HU3 4AN",
    "wof:placetype":"postalcode"
},
  "geometry": {"coordinates":[-0.35931437427096,53.7347627873469],"type":"Point"}
}