{
  "type": "Feature",
  "properties": {
    "iso:country":"GB",
    "wof:name":"AB25 3XS",
    "wof:placetype":"postalcode"
},
  "geometry": {"coordinates":[-2.10918074768701,57.15571318627304],"type":"Point"}
}