{
  "type": "Feature",
  "properties": {
    "date:inception_lower":"2003-03-01",
    "date:inception_upper":"2003-03-31",
    "iso:country":"GB",
    "wof:name":"WS12 2LR",
    "wof:placetype":"postalcode"
},
  "geometry": {"coordinates":[-1.985306,52.70245],"type":"Point"}
}