{
  "type": "Feature",
  "properties": {
    "date:inception_lower": "2011-05-01",
    "date:inception_upper": "2011-05-01",
    "iso:country": "GB",
    "wof:name": "AB24 1WJ",
    "wof:placetype": "postalcode"
  },
  "geometry": {"coordinates":[-2.099944,57.175448],"type":"Point"}
}
