{
  "type": "Feature",
  "properties": {
    "iso:country":"GB",
    "wof:name":"AB24 1WJ",
    "wof:placetype":"postalcode"
},
  "geometry": {"coordinates":[-2.09994419290502,57.17544754304511],"type":"Point"}
}