{
  "type": "Feature",
  "properties": {
    "iso:country":"GB",
    "wof:name":"MK13 8NA",
    "wof:placetype":"postalcode"
},
  "geometry": {"coordinates":[-0.77540702318583,52.0446934547677],"type":"Point"}
}