{
  "type": "Feature",
  "properties": {
    "iso:country": "GB",
    "wof:name": "WA3 3QW",
    "wof:placetype": "postalcode"
  },
  "geometry": {"coordinates":[-2.610385,53.477893],"type":"Point"}
}
