{
  "type": "Feature",
  "properties": {
    "iso:country": "GB",
    "wof:name": "NG23 6QD",
    "wof:placetype": "postalcode"
  },
  "geometry": {"coordinates":[-0.812351,53.186385],"type":"Point"}
}
