{
  "type": "Feature",
  "properties": {
    "iso:country": "GB",
    "wof:name": "B69 2JU",
    "wof:placetype": "postalcode"
  },
  "geometry": {"coordinates":[-2.054268,52.511558],"type":"Point"}
}
