{
  "type": "Feature",
  "properties": {
    "date:inception_lower": "2001-06-01",
    "date:inception_upper": "2001-06-01",
    "iso:country": "GB",
    "wof:name": "B69 2JU",
    "wof:placetype": "postalcode"
  },
  "geometry": {"coordinates":[-2.054268,52.511558],"type":"Point"}
}
