{
  "type": "Feature",
  "properties": {
    "iso:country":"GB",
    "wof:name":"GL50 2RD",
    "wof:placetype":"postalcode"
},
  "geometry": {"coordinates":[-2.09495694997457,51.88461446780482],"type":"Point"}
}