{
  "type": "Feature",
  "properties": {
    "date:inception_lower": "1993-08-01",
    "date:inception_upper": "1993-08-01",
    "iso:country": "GB",
    "wof:name": "GL50 2RD",
    "wof:placetype": "postalcode"
  },
  "geometry": {"coordinates":[-2.094957,51.884614],"type":"Point"}
}
