{
  "type": "Feature",
  "properties": {
    "iso:country": "GB",
    "wof:name": "GL50 2RD",
    "wof:placetype": "postalcode"
  },
  "geometry": {"coordinates":[-2.094957,51.884614],"type":"Point"}
}
