{
  "type": "Feature",
  "properties": {
    "iso:country":"GB",
    "wof:name":"GL2 7DQ",
    "wof:placetype":"postalcode"
},
  "geometry": {"coordinates":[-2.38861862097451,51.72680207831782],"type":"Point"}
}