{
  "type": "Feature",
  "properties": {
    "iso:country": "GB",
    "wof:name": "GL2 7DQ",
    "wof:placetype": "postalcode"
  },
  "geometry": {"coordinates":[-2.388618,51.726806],"type":"Point"}
}
