{
  "type": "Feature",
  "properties": {
    "iso:country":"GB",
    "wof:name":"DL5 4QP",
    "wof:placetype":"postalcode"
},
  "geometry": {"coordinates":[-1.5767646491561,54.63141484568774],"type":"Point"}
}