{
  "type": "Feature",
  "properties": {
    "iso:country":"GB",
    "wof:name":"PL27 7RL",
    "wof:placetype":"postalcode"
},
  "geometry": {"coordinates":[-4.91170576449916,50.50645306061236],"type":"Point"}
}