{
  "type": "Feature",
  "properties": {
    "date:inception_lower": "1980-01-01",
    "date:inception_upper": "1980-01-01",
    "iso:country": "GB",
    "wof:name": "CM13 3LU",
    "wof:placetype": "postalcode"
  },
  "geometry": {"coordinates":[0.358264,51.56992],"type":"Point"}
}
