{
  "type": "Feature",
  "properties": {
    "iso:country": "GB",
    "wof:name": "GU34 2DN",
    "wof:placetype": "postalcode"
  },
  "geometry": {"coordinates":[-0.969014,51.153919],"type":"Point"}
}
