{
  "type": "Feature",
  "properties": {
    "iso:country":"GB",
    "wof:name":"GU34 2DN",
    "wof:placetype":"postalcode"
},
  "geometry": {"coordinates":[-0.96901446327347,51.15391896710382],"type":"Point"}
}