{
  "type": "Feature",
  "properties": {
    "iso:country":"GB",
    "wof:name":"AB43 7HD",
    "wof:placetype":"postalcode"
},
  "geometry": {"coordinates":[-2.1091745343278,57.68383758524356],"type":"Point"}
}