{
  "type": "Feature",
  "properties": {
    "iso:country":"GB",
    "wof:name":"PA20 0LY",
    "wof:placetype":"postalcode"
},
  "geometry": {"coordinates":[-5.08427696920435,55.85964400845363],"type":"Point"}
}