{
  "type": "Feature",
  "properties": {
    "date:inception_lower":"1980-01-01",
    "date:inception_upper":"1980-01-31",
    "iso:country":"GB",
    "wof:name":"LS22 5EG",
    "wof:placetype":"postalcode"
},
  "geometry": {"coordinates":[-1.361385,53.935718],"type":"Point"}
}