{
  "type": "Feature",
  "properties": {
    "date:inception_lower": "1994-12-01",
    "date:inception_upper": "1994-12-01",
    "iso:country": "GB",
    "wof:name": "SO31 5DU",
    "wof:placetype": "postalcode"
  },
  "geometry": {"coordinates":[-1.352675,50.873285],"type":"Point"}
}
