{
  "type": "Feature",
  "properties": {
    "iso:country":"GB",
    "wof:name":"SO31 5DU",
    "wof:placetype":"postalcode"
},
  "geometry": {"coordinates":[-1.35268423560885,50.87329517941456],"type":"Point"}
}