{
  "type": "Feature",
  "properties": {
    "date:inception_lower": "1980-01-01",
    "date:inception_upper": "1980-01-01",
    "iso:country": "GB",
    "wof:name": "E7 9PJ",
    "wof:placetype": "postalcode"
  },
  "geometry": {"coordinates":[0.024066,51.541675],"type":"Point"}
}
