{
  "type": "Feature",
  "properties": {
    "iso:country":"GB",
    "wof:name":"E7 9PJ",
    "wof:placetype":"postalcode"
},
  "geometry": {"coordinates":[0.02406627744732,51.54167452747113],"type":"Point"}
}