{
  "type": "Feature",
  "properties": {
    "iso:country":"GB",
    "wof:name":"RH20 1JS",
    "wof:placetype":"postalcode"
},
  "geometry": {"coordinates":[-0.57434187383085,50.96794196116087],"type":"Point"}
}