{
  "type": "Feature",
  "properties": {
    "date:inception_lower": "1994-12-01",
    "date:inception_upper": "1994-12-01",
    "iso:country": "GB",
    "wof:name": "RH20 1JS",
    "wof:placetype": "postalcode"
  },
  "geometry": {"coordinates":[-0.574342,50.967942],"type":"Point"}
}
