{
  "type": "Feature",
  "properties": {
    "iso:country":"GB",
    "wof:name":"E1 6NH",
    "wof:placetype":"postalcode"
},
  "geometry": {"coordinates":[-0.0744205267129,51.52073417368878],"type":"Point"}
}