{
  "type": "Feature",
  "properties": {
    "iso:country": "GB",
    "wof:name": "BR7 5HH",
    "wof:placetype": "postalcode"
  },
  "geometry": {"coordinates":[0.062846,51.41019],"type":"Point"}
}
