{
  "type": "Feature",
  "properties": {
    "iso:country":"GB",
    "wof:name":"BR7 5HH",
    "wof:placetype":"postalcode"
},
  "geometry": {"coordinates":[0.06284596714951,51.41018967487901],"type":"Point"}
}