{
  "type": "Feature",
  "properties": {
    "date:inception_lower": "1980-01-01",
    "date:inception_upper": "1980-01-01",
    "iso:country": "GB",
    "wof:name": "BR7 5HH",
    "wof:placetype": "postalcode"
  },
  "geometry": {"coordinates":[0.062846,51.41019],"type":"Point"}
}
