{
  "type": "Feature",
  "properties": {
    "iso:country":"GB",
    "wof:name":"B11 1UH",
    "wof:placetype":"postalcode"
},
  "geometry": {"coordinates":[-1.86779979797234,52.45792616547769],"type":"Point"}
}