{
  "type": "Feature",
  "properties": {
    "iso:country":"GB",
    "wof:name":"SW11 3DE",
    "wof:placetype":"postalcode"
},
  "geometry": {"coordinates":[-0.16792891962242,51.47325884414063],"type":"Point"}
}