{
  "type": "Feature",
  "properties": {
    "iso:country": "GB",
    "wof:name": "ME3 7DW",
    "wof:placetype": "postalcode"
  },
  "geometry": {"coordinates":[0.503745,51.46244],"type":"Point"}
}
