{
  "type": "Feature",
  "properties": {
    "date:inception_lower": "2019-10-01",
    "date:inception_upper": "2019-10-01",
    "iso:country": "GB",
    "wof:name": "ME3 7DW",
    "wof:placetype": "postalcode"
  },
  "geometry": {"coordinates":[0.503745,51.46244],"type":"Point"}
}
