{
  "type": "Feature",
  "properties": {
    "iso:country": "GB",
    "wof:name": "WA1 3TZ",
    "wof:placetype": "postalcode"
  },
  "geometry": {"coordinates":[-2.552165,53.397854],"type":"Point"}
}
