{
  "type": "Feature",
  "properties": {
    "iso:country":"GB",
    "wof:name":"WA1 3TZ",
    "wof:placetype":"postalcode"
},
  "geometry": {"coordinates":[-2.55216518814213,53.39785390697704],"type":"Point"}
}