{
  "type": "Feature",
  "properties": {
    "date:inception_lower": "1993-08-01",
    "date:inception_upper": "1993-08-01",
    "iso:country": "GB",
    "wof:name": "BN25 1LR",
    "wof:placetype": "postalcode"
  },
  "geometry": {"coordinates":[0.10087,50.771565],"type":"Point"}
}
