{
  "type": "Feature",
  "properties": {
    "date:inception_lower": "1980-01-01",
    "date:inception_upper": "1980-01-01",
    "iso:country": "GB",
    "wof:name": "TA21 8DH",
    "wof:placetype": "postalcode"
  },
  "geometry": {"coordinates":[-3.22944,50.975742],"type":"Point"}
}
