{
  "type": "Feature",
  "properties": {
    "iso:country":"GB",
    "wof:name":"PO4 8PY",
    "wof:placetype":"postalcode"
},
  "geometry": {"coordinates":[-1.05307685143327,50.79870534414066],"type":"Point"}
}