{
  "type": "Feature",
  "properties": {
    "date:inception_lower":"1980-01-01",
    "date:inception_upper":"1980-01-31",
    "iso:country":"GB",
    "wof:name":"LL21 0HW",
    "wof:placetype":"postalcode"
},
  "geometry": {"coordinates":[-3.391902,52.969399],"type":"Point"}
}