{
  "type": "Feature",
  "properties": {
    "iso:country":"GB",
    "wof:name":"LL21 0HW",
    "wof:placetype":"postalcode"
},
  "geometry": {"coordinates":[-3.39188498345588,52.96938372666268],"type":"Point"}
}