{
  "type": "Feature",
  "properties": {
    "iso:country":"GB",
    "wof:name":"M16 7BE",
    "wof:placetype":"postalcode"
},
  "geometry": {"coordinates":[-2.25589454352525,53.45539493001109],"type":"Point"}
}