{
  "type": "Feature",
  "properties": {
    "iso:country":"GB",
    "wof:name":"FK1 3AX",
    "wof:placetype":"postalcode"
},
  "geometry": {"coordinates":[-3.83024737279572,55.89553138454093],"type":"Point"}
}