{
  "type": "Feature",
  "properties": {
    "iso:country": "GB",
    "wof:name": "FK1 3AX",
    "wof:placetype": "postalcode"
  },
  "geometry": {"coordinates":[-3.830247,55.895531],"type":"Point"}
}
