{
  "type": "Feature",
  "properties": {
    "iso:country": "GB",
    "wof:name": "PL14 4NU",
    "wof:placetype": "postalcode"
  },
  "geometry": {"coordinates":[-4.464931,50.451018],"type":"Point"}
}
