{
  "type": "Feature",
  "properties": {
    "iso:country": "GB",
    "wof:name": "M18 8HD",
    "wof:placetype": "postalcode"
  },
  "geometry": {"coordinates":[-2.178039,53.46297],"type":"Point"}
}
