{
  "type": "Feature",
  "properties": {
    "iso:country":"GB",
    "wof:name":"M18 8HD",
    "wof:placetype":"postalcode"
},
  "geometry": {"coordinates":[-2.17803932733223,53.46296994753246],"type":"Point"}
}