{
  "type": "Feature",
  "properties": {
    "iso:country": "GB",
    "wof:name": "L40 5BR",
    "wof:placetype": "postalcode"
  },
  "geometry": {"coordinates":[-2.831869,53.59666],"type":"Point"}
}
