{
  "type": "Feature",
  "properties": {
    "date:inception_lower":"2003-10-01",
    "date:inception_upper":"2003-10-31",
    "iso:country":"GB",
    "wof:name":"L40 5BR",
    "wof:placetype":"postalcode"
},
  "geometry": {"coordinates":[-2.831869,53.59666],"type":"Point"}
}