{
  "type": "Feature",
  "properties": {
    "iso:country":"GB",
    "wof:name":"SL6 5EG",
    "wof:placetype":"postalcode"
},
  "geometry": {"coordinates":[-0.74610757655725,51.52663527147774],"type":"Point"}
}