{
  "type": "Feature",
  "properties": {
    "iso:country":"GB",
    "wof:name":"NR12 8NG",
    "wof:placetype":"postalcode"
},
  "geometry": {"coordinates":[1.49077964253707,52.69953281693611],"type":"Point"}
}