{
  "type": "Feature",
  "properties": {
    "iso:country":"GB",
    "wof:name":"GL20 7EA",
    "wof:placetype":"postalcode"
},
  "geometry": {"coordinates":[-2.14144521055371,52.00342586616789],"type":"Point"}
}