{
  "type": "Feature",
  "properties": {
    "date:inception_lower": "2023-07-01",
    "date:inception_upper": "2023-07-01",
    "iso:country": "GB",
    "wof:name": "RG2 6BJ",
    "wof:placetype": "postalcode"
  },
  "geometry": {"coordinates":[-0.991021,51.427139],"type":"Point"}
}
