{
  "type": "Feature",
  "properties": {
    "iso:country":"GB",
    "wof:name":"SG17 5GJ",
    "wof:placetype":"postalcode"
},
  "geometry": {"coordinates":[-0.32941010176522,52.04232569152959],"type":"Point"}
}