{
  "type": "Feature",
  "properties": {
    "iso:country":"GB",
    "wof:name":"CV5 9ER",
    "wof:placetype":"postalcode"
},
  "geometry": {"coordinates":[-1.55780577703882,52.42407272476467],"type":"Point"}
}