{
  "type": "Feature",
  "properties": {
    "date:inception_lower": "2010-04-01",
    "date:inception_upper": "2010-04-01",
    "iso:country": "GB",
    "wof:name": "TN24 0FP",
    "wof:placetype": "postalcode"
  },
  "geometry": {"coordinates":[0.89048,51.131731],"type":"Point"}
}
