{
  "type": "Feature",
  "properties": {
    "iso:country": "GB",
    "wof:name": "WF4 3PD",
    "wof:placetype": "postalcode"
  },
  "geometry": {"coordinates":[-1.525544,53.641939],"type":"Point"}
}
