{
  "type": "Feature",
  "properties": {
    "iso:country":"GB",
    "wof:name":"WF4 3PD",
    "wof:placetype":"postalcode"
},
  "geometry": {"coordinates":[-1.5255435587006,53.64193941299251],"type":"Point"}
}