{
  "type": "Feature",
  "properties": {
    "iso:country": "GB",
    "wof:name": "PE6 7YD",
    "wof:placetype": "postalcode"
  },
  "geometry": {"coordinates":[-0.20376,52.603207],"type":"Point"}
}
