{
  "type": "Feature",
  "properties": {
    "date:inception_lower": "1980-01-01",
    "date:inception_upper": "1980-01-01",
    "iso:country": "GB",
    "wof:name": "PE6 7YD",
    "wof:placetype": "postalcode"
  },
  "geometry": {"coordinates":[-0.20376,52.603207],"type":"Point"}
}
