{
  "type": "Feature",
  "properties": {
    "iso:country":"GB",
    "wof:name":"SM6 7NX",
    "wof:placetype":"postalcode"
},
  "geometry": {"coordinates":[-0.15491205715638,51.36682491828689],"type":"Point"}
}