{
  "type": "Feature",
  "properties": {
    "iso:country":"GB",
    "wof:name":"NE42 5EG",
    "wof:placetype":"postalcode"
},
  "geometry": {"coordinates":[-1.83377376425214,54.96447610971994],"type":"Point"}
}