{
  "type": "Feature",
  "properties": {
    "iso:country":"GB",
    "wof:name":"M13 0XY",
    "wof:placetype":"postalcode"
},
  "geometry": {"coordinates":[-2.20759615282947,53.45168658032052],"type":"Point"}
}