{
  "type": "Feature",
  "properties": {
    "iso:country": "GB",
    "wof:name": "CV21 4LE",
    "wof:placetype": "postalcode"
  },
  "geometry": {"coordinates":[-1.221697,52.362005],"type":"Point"}
}
