{
  "type": "Feature",
  "properties": {
    "date:inception_lower": "1980-01-01",
    "date:inception_upper": "1980-01-01",
    "iso:country": "GB",
    "wof:name": "KY12 7LB",
    "wof:placetype": "postalcode"
  },
  "geometry": {"coordinates":[-3.454903,56.070348],"type":"Point"}
}
