{
  "type": "Feature",
  "properties": {
    "date:inception_lower": "1996-12-01",
    "date:inception_upper": "1996-12-01",
    "iso:country": "GB",
    "wof:name": "SK11 8BE",
    "wof:placetype": "postalcode"
  },
  "geometry": {"coordinates":[-2.125302,53.251535],"type":"Point"}
}
