{
  "type": "Feature",
  "properties": {
    "iso:country":"GB",
    "wof:name":"SK11 8BE",
    "wof:placetype":"postalcode"
},
  "geometry": {"coordinates":[-2.12530176604797,53.25153458836162],"type":"Point"}
}