{
  "type": "Feature",
  "properties": {
    "iso:country": "GB",
    "wof:name": "PL8 2EY",
    "wof:placetype": "postalcode"
  },
  "geometry": {"coordinates":[-3.994701,50.343486],"type":"Point"}
}
