{
  "type": "Feature",
  "properties": {
    "iso:country":"GB",
    "wof:name":"PL8 2EY",
    "wof:placetype":"postalcode"
},
  "geometry": {"coordinates":[-3.99470138804832,50.34348621253208],"type":"Point"}
}