{
  "type": "Feature",
  "properties": {
    "date:inception_lower": "1980-01-01",
    "date:inception_upper": "1980-01-01",
    "iso:country": "GB",
    "wof:name": "PL8 2EY",
    "wof:placetype": "postalcode"
  },
  "geometry": {"coordinates":[-3.994701,50.343486],"type":"Point"}
}
