{
  "type": "Feature",
  "properties": {
    "iso:country":"GB",
    "wof:name":"MK4 1DQ",
    "wof:placetype":"postalcode"
},
  "geometry": {"coordinates":[-0.76307701810165,52.00749413678189],"type":"Point"}
}