{
  "type": "Feature",
  "properties": {
    "date:inception_lower": "1983-03-01",
    "date:inception_upper": "1983-03-01",
    "iso:country": "GB",
    "wof:name": "MK4 1DQ",
    "wof:placetype": "postalcode"
  },
  "geometry": {"coordinates":[-0.763077,52.007494],"type":"Point"}
}
