{
  "type": "Feature",
  "properties": {
    "iso:country": "GB",
    "wof:name": "PO15 5SX",
    "wof:placetype": "postalcode"
  },
  "geometry": {"coordinates":[-1.257615,50.870013],"type":"Point"}
}
