{
  "type": "Feature",
  "properties": {
    "iso:country":"GB",
    "wof:name":"PO15 5SX",
    "wof:placetype":"postalcode"
},
  "geometry": {"coordinates":[-1.25749969053391,50.87001296224497],"type":"Point"}
}