{
  "type": "Feature",
  "properties": {
    "iso:country":"GB",
    "wof:name":"NR27 0FD",
    "wof:placetype":"postalcode"
},
  "geometry": {"coordinates":[1.2985917690256,52.92079443233158],"type":"Point"}
}