{
  "type": "Feature",
  "properties": {
    "iso:country":"GB",
    "wof:name":"WR6 5RY",
    "wof:placetype":"postalcode"
},
  "geometry": {"coordinates":[-2.4137843791525,52.22143433546601],"type":"Point"}
}