{
  "type": "Feature",
  "properties": {
    "iso:country":"GB",
    "wof:name":"CH47 9RG",
    "wof:placetype":"postalcode"
},
  "geometry": {"coordinates":[-3.1550128259133,53.39801937462634],"type":"Point"}
}