{
  "type": "Feature",
  "properties": {
    "iso:country":"GB",
    "wof:name":"E11 2AL",
    "wof:placetype":"postalcode"
},
  "geometry": {"coordinates":[0.02437181557941,51.58006782577208],"type":"Point"}
}