{
  "type": "Feature",
  "properties": {
    "iso:country":"GB",
    "wof:name":"BD2 3AU",
    "wof:placetype":"postalcode"
},
  "geometry": {"coordinates":[-1.72810560665105,53.81162736217289],"type":"Point"}
}