{
  "type": "Feature",
  "properties": {
    "date:inception_lower": "1981-03-01",
    "date:inception_upper": "1981-03-01",
    "iso:country": "GB",
    "wof:name": "G67 2NH",
    "wof:placetype": "postalcode"
  },
  "geometry": {"coordinates":[-3.985209,55.938396],"type":"Point"}
}
