{
  "type": "Feature",
  "properties": {
    "iso:country": "GB",
    "wof:name": "G67 2NH",
    "wof:placetype": "postalcode"
  },
  "geometry": {"coordinates":[-3.985209,55.938396],"type":"Point"}
}
