{
  "type": "Feature",
  "properties": {
    "date:inception_lower": "2002-07-01",
    "date:inception_upper": "2002-07-01",
    "iso:country": "GB",
    "wof:name": "CA7 9XX",
    "wof:placetype": "postalcode"
  },
  "geometry": {"coordinates":[-3.163169,54.826727],"type":"Point"}
}
