{
  "type": "Feature",
  "properties": {
    "iso:country": "GB",
    "wof:name": "DD4 7PD",
    "wof:placetype": "postalcode"
  },
  "geometry": {"coordinates":[-2.918552,56.469284],"type":"Point"}
}
