{
  "type": "Feature",
  "properties": {
    "iso:country":"GB",
    "wof:name":"DD4 7PD",
    "wof:placetype":"postalcode"
},
  "geometry": {"coordinates":[-2.91855167950013,56.46928390500128],"type":"Point"}
}