{
  "type": "Feature",
  "properties": {
    "date:inception_lower": "1999-06-01",
    "date:inception_upper": "1999-06-01",
    "iso:country": "GB",
    "wof:name": "CH64 6TW",
    "wof:placetype": "postalcode"
  },
  "geometry": {"coordinates":[-3.071841,53.289578],"type":"Point"}
}
