{
  "type": "Feature",
  "properties": {
    "iso:country":"GB",
    "wof:name":"YO42 4EE",
    "wof:placetype":"postalcode"
},
  "geometry": {"coordinates":[-0.82095965410214,53.9307579656879],"type":"Point"}
}