{
  "type": "Feature",
  "properties": {
    "iso:country": "GB",
    "wof:name": "SY13 1JL",
    "wof:placetype": "postalcode"
  },
  "geometry": {"coordinates":[-2.695958,52.968332],"type":"Point"}
}
