{
  "type": "Feature",
  "properties": {
    "iso:country":"GB",
    "wof:name":"PE13 1SP",
    "wof:placetype":"postalcode"
},
  "geometry": {"coordinates":[0.15911285248699,52.6641602684554],"type":"Point"}
}