{
  "type": "Feature",
  "properties": {
    "iso:country": "GB",
    "wof:name": "MK45 3JF",
    "wof:placetype": "postalcode"
  },
  "geometry": {"coordinates":[-0.437633,52.12024],"type":"Point"}
}
