{
  "type": "Feature",
  "properties": {
    "iso:country":"GB",
    "wof:name":"WF4 3FE",
    "wof:placetype":"postalcode"
},
  "geometry": {"coordinates":[-1.5348518832302,53.64690149299783],"type":"Point"}
}