{
  "type": "Feature",
  "properties": {
    "date:inception_lower":"2005-02-01",
    "date:inception_upper":"2005-02-28",
    "iso:country":"GB",
    "wof:name":"WF4 3FE",
    "wof:placetype":"postalcode"
},
  "geometry": {"coordinates":[-1.534852,53.646901],"type":"Point"}
}