{
  "type": "Feature",
  "properties": {
    "iso:country":"GB",
    "wof:name":"IV1 3YF",
    "wof:placetype":"postalcode"
},
  "geometry": {"coordinates":[-4.24802450522814,57.50469815298949],"type":"Point"}
}