{
  "type": "Feature",
  "properties": {
    "date:inception_lower": "2022-12-01",
    "date:inception_upper": "2022-12-01",
    "iso:country": "GB",
    "wof:name": "BS30 5AE",
    "wof:placetype": "postalcode"
  },
  "geometry": {"coordinates":[-2.472234,51.458532],"type":"Point"}
}
