{
  "type": "Feature",
  "properties": {
    "iso:country":"GB",
    "wof:name":"EX33 2NW",
    "wof:placetype":"postalcode"
},
  "geometry": {"coordinates":[-4.15095231903486,51.11454499160681],"type":"Point"}
}