{
  "type": "Feature",
  "properties": {
    "date:inception_lower":"1993-01-01",
    "date:inception_upper":"1993-01-31",
    "iso:country":"GB",
    "wof:name":"LL11 4TF",
    "wof:placetype":"postalcode"
},
  "geometry": {"coordinates":[-3.025811,53.068064],"type":"Point"}
}