{
  "type": "Feature",
  "properties": {
    "iso:country":"GB",
    "wof:name":"S13 8HN",
    "wof:placetype":"postalcode"
},
  "geometry": {"coordinates":[-1.39723315423519,53.37064556682511],"type":"Point"}
}