{
  "type": "Feature",
  "properties": {
    "iso:country":"GB",
    "wof:name":"ML1 5LU",
    "wof:placetype":"postalcode"
},
  "geometry": {"coordinates":[-3.91356285458695,55.81049886375187],"type":"Point"}
}