{
  "type": "Feature",
  "properties": {
    "date:inception_lower": "2016-09-01",
    "date:inception_upper": "2016-09-01",
    "iso:country": "GB",
    "wof:name": "HX3 8UG",
    "wof:placetype": "postalcode"
  },
  "geometry": {"coordinates":[-1.79436,53.726154],"type":"Point"}
}
