{
  "type": "Feature",
  "properties": {
    "iso:country":"GB",
    "wof:name":"SG1 5DQ",
    "wof:placetype":"postalcode"
},
  "geometry": {"coordinates":[-0.19009083081124,51.90884365795537],"type":"Point"}
}