{
  "type": "Feature",
  "properties": {
    "iso:country":"GB",
    "wof:name":"L18 7HS",
    "wof:placetype":"postalcode"
},
  "geometry": {"coordinates":[-2.90433073794822,53.37180376809302],"type":"Point"}
}