{
  "type": "Feature",
  "properties": {
    "date:inception_lower": "2021-02-01",
    "date:inception_upper": "2021-02-01",
    "iso:country": "GB",
    "wof:name": "EX21 5DR",
    "wof:placetype": "postalcode"
  },
  "geometry": {"coordinates":[-4.264109,50.793159],"type":"Point"}
}
