{
  "type": "Feature",
  "properties": {
    "iso:country":"GB",
    "wof:name":"BL5 3LB",
    "wof:placetype":"postalcode"
},
  "geometry": {"coordinates":[-2.51808099336724,53.56060049634966],"type":"Point"}
}