{
  "type": "Feature",
  "properties": {
    "iso:country":"GB",
    "wof:name":"BH21 5NR",
    "wof:placetype":"postalcode"
},
  "geometry": {"coordinates":[-1.95082177203691,50.90975300380404],"type":"Point"}
}