{
  "type": "Feature",
  "properties": {
    "iso:country":"GB",
    "wof:name":"PO9 5BG",
    "wof:placetype":"postalcode"
},
  "geometry": {"coordinates":[-0.98697959774782,50.86763743861499],"type":"Point"}
}