{
  "type": "Feature",
  "properties": {
    "date:inception_lower": "1980-01-01",
    "date:inception_upper": "1980-01-01",
    "iso:country": "GB",
    "wof:name": "WV12 5XW",
    "wof:placetype": "postalcode"
  },
  "geometry": {"coordinates":[-2.03692,52.616879],"type":"Point"}
}
