{
  "type": "Feature",
  "properties": {
    "iso:country": "GB",
    "wof:name": "KT11 2DQ",
    "wof:placetype": "postalcode"
  },
  "geometry": {"coordinates":[-0.388469,51.328392],"type":"Point"}
}
