{
  "type": "Feature",
  "properties": {
    "iso:country":"GB",
    "wof:name":"PR3 2EF",
    "wof:placetype":"postalcode"
},
  "geometry": {"coordinates":[-2.65233742537532,53.85723020466746],"type":"Point"}
}