{
  "type": "Feature",
  "properties": {
    "iso:country":"GB",
    "wof:name":"SA20 0AB",
    "wof:placetype":"postalcode"
},
  "geometry": {"coordinates":[-3.79694233396339,51.99417789809968],"type":"Point"}
}