{
  "type": "Feature",
  "properties": {
    "iso:country": "GB",
    "wof:name": "B49 6FP",
    "wof:placetype": "postalcode"
  },
  "geometry": {"coordinates":[-1.82496,52.236025],"type":"Point"}
}
