{
  "type": "Feature",
  "properties": {
    "date:inception_lower": "2024-05-01",
    "date:inception_upper": "2024-05-01",
    "iso:country": "GB",
    "wof:name": "CM3 9BY",
    "wof:placetype": "postalcode"
  },
  "geometry": {"coordinates":[0.616316,51.64338],"type":"Point"}
}
