{
  "type": "Feature",
  "properties": {
    "iso:country":"GB",
    "wof:name":"KT22 0UF",
    "wof:placetype":"postalcode"
},
  "geometry": {"coordinates":[-0.34962951007229,51.3395508419244],"type":"Point"}
}