{
  "type": "Feature",
  "properties": {
    "date:inception_lower":"1980-01-01",
    "date:inception_upper":"1980-01-31",
    "iso:country":"GB",
    "wof:name":"N4 3NL",
    "wof:placetype":"postalcode"
},
  "geometry": {"coordinates":[-0.111526,51.565608],"type":"Point"}
}