{
  "type": "Feature",
  "properties": {
    "date:inception_lower": "1980-01-01",
    "date:inception_upper": "1980-01-01",
    "iso:country": "GB",
    "wof:name": "PR6 8DY",
    "wof:placetype": "postalcode"
  },
  "geometry": {"coordinates":[-2.522942,53.68307],"type":"Point"}
}
