{
  "type": "Feature",
  "properties": {
    "iso:country":"GB",
    "wof:name":"PR6 8DY",
    "wof:placetype":"postalcode"
},
  "geometry": {"coordinates":[-2.52337326030911,53.68342996552461],"type":"Point"}
}