{
  "type": "Feature",
  "properties": {
    "iso:country": "GB",
    "wof:name": "PR6 8DY",
    "wof:placetype": "postalcode"
  },
  "geometry": {"coordinates":[-2.523371,53.683446],"type":"Point"}
}
