{
  "type": "Feature",
  "properties": {
    "iso:country": "GB",
    "wof:name": "N2 8LA",
    "wof:placetype": "postalcode"
  },
  "geometry": {"coordinates":[-0.173341,51.597565],"type":"Point"}
}
