{
  "type": "Feature",
  "properties": {
    "iso:country":"GB",
    "wof:name":"TN3 0EA",
    "wof:placetype":"postalcode"
},
  "geometry": {"coordinates":[0.21406558152065,51.12594032253401],"type":"Point"}
}