{
  "type": "Feature",
  "properties": {
    "iso:country": "GB",
    "wof:name": "UB4 8QB",
    "wof:placetype": "postalcode"
  },
  "geometry": {"coordinates":[-0.439432,51.536301],"type":"Point"}
}
