{
  "type": "Feature",
  "properties": {
    "iso:country":"GB",
    "wof:name":"UB4 8QB",
    "wof:placetype":"postalcode"
},
  "geometry": {"coordinates":[-0.43943247377071,51.53630121559324],"type":"Point"}
}