{
  "type": "Feature",
  "properties": {
    "iso:country":"GB",
    "wof:name":"OL2 5UN",
    "wof:placetype":"postalcode"
},
  "geometry": {"coordinates":[-2.13760899471909,53.58255089292203],"type":"Point"}
}