{
  "type": "Feature",
  "properties": {
    "iso:country": "GB",
    "wof:name": "OL2 5UN",
    "wof:placetype": "postalcode"
  },
  "geometry": {"coordinates":[-2.137609,53.582551],"type":"Point"}
}
