{
  "type": "Feature",
  "properties": {
    "iso:country":"GB",
    "wof:name":"NE65 7AR",
    "wof:placetype":"postalcode"
},
  "geometry": {"coordinates":[-2.05009817681819,55.28331132650712],"type":"Point"}
}