{
  "type": "Feature",
  "properties": {
    "iso:country": "GB",
    "wof:name": "NE65 7AR",
    "wof:placetype": "postalcode"
  },
  "geometry": {"coordinates":[-2.050098,55.283311],"type":"Point"}
}
