{
  "type": "Feature",
  "properties": {
    "iso:country": "GB",
    "wof:name": "BS39 6EF",
    "wof:placetype": "postalcode"
  },
  "geometry": {"coordinates":[-2.519115,51.315413],"type":"Point"}
}
