{
  "type": "Feature",
  "properties": {
    "iso:country":"GB",
    "wof:name":"CT2 0EN",
    "wof:placetype":"postalcode"
},
  "geometry": {"coordinates":[1.13431260164685,51.30618674417226],"type":"Point"}
}