{
  "type": "Feature",
  "properties": {
    "date:inception_lower": "1980-01-01",
    "date:inception_upper": "1980-01-01",
    "iso:country": "GB",
    "wof:name": "FK10 2AU",
    "wof:placetype": "postalcode"
  },
  "geometry": {"coordinates":[-3.792875,56.119625],"type":"Point"}
}
