{
  "type": "Feature",
  "properties": {
    "date:inception_lower": "1980-01-01",
    "date:inception_upper": "1980-01-01",
    "iso:country": "GB",
    "wof:name": "S42 7AQ",
    "wof:placetype": "postalcode"
  },
  "geometry": {"coordinates":[-1.484,53.257182],"type":"Point"}
}
