{
  "type": "Feature",
  "properties": {
    "iso:country":"GB",
    "wof:name":"S42 7AQ",
    "wof:placetype":"postalcode"
},
  "geometry": {"coordinates":[-1.48404629035264,53.25714620381645],"type":"Point"}
}