{
  "type": "Feature",
  "properties": {
    "date:inception_lower": "1980-01-01",
    "date:inception_upper": "1980-01-01",
    "iso:country": "GB",
    "wof:name": "L3 2BE",
    "wof:placetype": "postalcode"
  },
  "geometry": {"coordinates":[-2.983513,53.412347],"type":"Point"}
}
