{
  "type": "Feature",
  "properties": {
    "iso:country":"GB",
    "wof:name":"DT9 4NQ",
    "wof:placetype":"postalcode"
},
  "geometry": {"coordinates":[-2.47936633902586,51.00334188307204],"type":"Point"}
}