{
  "type": "Feature",
  "properties": {
    "iso:country": "GB",
    "wof:name": "DT9 4NQ",
    "wof:placetype": "postalcode"
  },
  "geometry": {"coordinates":[-2.479366,51.003342],"type":"Point"}
}
