{
  "type": "Feature",
  "properties": {
    "iso:country":"GB",
    "wof:name":"EH29 9BU",
    "wof:placetype":"postalcode"
},
  "geometry": {"coordinates":[-3.40684899157862,55.95583074028989],"type":"Point"}
}