{
  "type": "Feature",
  "properties": {
    "iso:country":"GB",
    "wof:name":"RG24 9LR",
    "wof:placetype":"postalcode"
},
  "geometry": {"coordinates":[-1.09647003124841,51.28716603318008],"type":"Point"}
}