{
  "type": "Feature",
  "properties": {
    "iso:country":"GB",
    "wof:name":"HR9 5SG",
    "wof:placetype":"postalcode"
},
  "geometry": {"coordinates":[-2.56818264883946,51.89206422132846],"type":"Point"}
}