{
  "type": "Feature",
  "properties": {
    "date:inception_lower": "1980-01-01",
    "date:inception_upper": "1980-01-01",
    "iso:country": "GB",
    "wof:name": "NG9 1LE",
    "wof:placetype": "postalcode"
  },
  "geometry": {"coordinates":[-1.207227,52.9181],"type":"Point"}
}
