{
  "type": "Feature",
  "properties": {
    "iso:country":"GB",
    "wof:name":"NG9 1LE",
    "wof:placetype":"postalcode"
},
  "geometry": {"coordinates":[-1.20718567100445,52.91810711119488],"type":"Point"}
}