{
  "type": "Feature",
  "properties": {
    "date:inception_lower": "1995-01-01",
    "date:inception_upper": "1995-01-01",
    "iso:country": "GB",
    "wof:name": "B15 1TR",
    "wof:placetype": "postalcode"
  },
  "geometry": {"coordinates":[-1.919632,52.471463],"type":"Point"}
}
