{
  "type": "Feature",
  "properties": {
    "iso:country":"GB",
    "wof:name":"KA20 3AL",
    "wof:placetype":"postalcode"
},
  "geometry": {"coordinates":[-4.75284801347504,55.64164713600672],"type":"Point"}
}