{
  "type": "Feature",
  "properties": {
    "iso:country":"GB",
    "wof:name":"SW3 5BZ",
    "wof:placetype":"postalcode"
},
  "geometry": {"coordinates":[-0.17184868564723,51.48398515287214],"type":"Point"}
}