{
  "type": "Feature",
  "properties": {
    "iso:country":"GB",
    "wof:name":"SO32 1HG",
    "wof:placetype":"postalcode"
},
  "geometry": {"coordinates":[-1.26791289048526,50.97726038291392],"type":"Point"}
}