{
  "type": "Feature",
  "properties": {
    "date:inception_lower": "1994-12-01",
    "date:inception_upper": "1994-12-01",
    "iso:country": "GB",
    "wof:name": "SO32 1HG",
    "wof:placetype": "postalcode"
  },
  "geometry": {"coordinates":[-1.270599,50.975966],"type":"Point"}
}
