{
  "type": "Feature",
  "properties": {
    "iso:country": "GB",
    "wof:name": "PL18 9RZ",
    "wof:placetype": "postalcode"
  },
  "geometry": {"coordinates":[-4.224802,50.502144],"type":"Point"}
}
