{
  "type": "Feature",
  "properties": {
    "date:inception_lower": "2023-06-01",
    "date:inception_upper": "2023-06-01",
    "iso:country": "GB",
    "wof:name": "PE7 8TG",
    "wof:placetype": "postalcode"
  },
  "geometry": {"coordinates":[-0.254259,52.532701],"type":"Point"}
}
