{
  "type": "Feature",
  "properties": {
    "iso:country":"GB",
    "wof:name":"SK8 2AL",
    "wof:placetype":"postalcode"
},
  "geometry": {"coordinates":[-2.20724040751395,53.3941245936328],"type":"Point"}
}