{
  "type": "Feature",
  "properties": {
    "date:inception_lower":"1980-01-01",
    "date:inception_upper":"1980-01-31",
    "iso:country":"GB",
    "wof:name":"SK8 2AL",
    "wof:placetype":"postalcode"
},
  "geometry": {"coordinates":[-2.20724,53.394125],"type":"Point"}
}