{
  "type": "Feature",
  "properties": {
    "iso:country": "GB",
    "wof:name": "WA7 2SS",
    "wof:placetype": "postalcode"
  },
  "geometry": {"coordinates":[-2.705509,53.331623],"type":"Point"}
}
