{
  "type": "Feature",
  "properties": {
    "iso:country":"GB",
    "wof:name":"AB41 8HW",
    "wof:placetype":"postalcode"
},
  "geometry": {"coordinates":[-1.99818727128251,57.40373158932005],"type":"Point"}
}