{
  "type": "Feature",
  "properties": {
    "date:inception_lower": "1990-08-01",
    "date:inception_upper": "1990-08-01",
    "iso:country": "GB",
    "wof:name": "AB41 8HW",
    "wof:placetype": "postalcode"
  },
  "geometry": {"coordinates":[-1.998187,57.403732],"type":"Point"}
}
