{
  "type": "Feature",
  "properties": {
    "iso:country":"GB",
    "wof:name":"WA1 4HQ",
    "wof:placetype":"postalcode"
},
  "geometry": {"coordinates":[-2.53056840498168,53.39902152038043],"type":"Point"}
}