{
  "type": "Feature",
  "properties": {
    "iso:country": "GB",
    "wof:name": "NG16 2HB",
    "wof:placetype": "postalcode"
  },
  "geometry": {"coordinates":[-1.271666,53.001861],"type":"Point"}
}
