{
  "type": "Feature",
  "properties": {
    "iso:country":"GB",
    "wof:name":"PE19 8GA",
    "wof:placetype":"postalcode"
},
  "geometry": {"coordinates":[-0.28748435899382,52.21124026032282],"type":"Point"}
}