{
  "type": "Feature",
  "properties": {
    "iso:country":"GB",
    "wof:name":"YO10 5EB",
    "wof:placetype":"postalcode"
},
  "geometry": {"coordinates":[-1.04460812731227,53.94407883129298],"type":"Point"}
}