{
  "type": "Feature",
  "properties": {
    "date:inception_lower": "1980-01-01",
    "date:inception_upper": "1980-01-01",
    "iso:country": "GB",
    "wof:name": "NR26 8TB",
    "wof:placetype": "postalcode"
  },
  "geometry": {"coordinates":[1.178181,52.933927],"type":"Point"}
}
