{
  "type": "Feature",
  "properties": {
    "date:inception_lower": "2021-08-01",
    "date:inception_upper": "2021-08-01",
    "iso:country": "GB",
    "wof:name": "UB8 1GZ",
    "wof:placetype": "postalcode"
  },
  "geometry": {"coordinates":[-0.477351,51.544418],"type":"Point"}
}
