{
  "type": "Feature",
  "properties": {
    "date:inception_lower": "1980-01-01",
    "date:inception_upper": "1980-01-01",
    "iso:country": "GB",
    "wof:name": "S11 7PZ",
    "wof:placetype": "postalcode"
  },
  "geometry": {"coordinates":[-1.531578,53.353207],"type":"Point"}
}
