{
  "type": "Feature",
  "properties": {
    "iso:country":"GB",
    "wof:name":"S11 7PZ",
    "wof:placetype":"postalcode"
},
  "geometry": {"coordinates":[-1.53175929526658,53.35316347863308],"type":"Point"}
}