{
  "type": "Feature",
  "properties": {
    "iso:country":"GB",
    "wof:name":"SW8 2RD",
    "wof:placetype":"postalcode"
},
  "geometry": {"coordinates":[-0.13550787037318,51.47133594082479],"type":"Point"}
}