{
  "type": "Feature",
  "properties": {
    "iso:country":"GB",
    "wof:name":"ME17 3EA",
    "wof:placetype":"postalcode"
},
  "geometry": {"coordinates":[0.61647104728709,51.20418375631066],"type":"Point"}
}