{
  "type": "Feature",
  "properties": {
    "iso:country": "GB",
    "wof:name": "PL9 7PT",
    "wof:placetype": "postalcode"
  },
  "geometry": {"coordinates":[-4.108031,50.358476],"type":"Point"}
}
