{
  "type": "Feature",
  "properties": {
    "iso:country":"GB",
    "wof:name":"PL9 7PT",
    "wof:placetype":"postalcode"
},
  "geometry": {"coordinates":[-4.10803060313135,50.3584764189686],"type":"Point"}
}