{
  "type": "Feature",
  "properties": {
    "iso:country":"GB",
    "wof:name":"BS11 0YS",
    "wof:placetype":"postalcode"
},
  "geometry": {"coordinates":[-2.6734973770008,51.5115272081853],"type":"Point"}
}