{
  "type": "Feature",
  "properties": {
    "iso:country": "GB",
    "wof:name": "BS11 0YS",
    "wof:placetype": "postalcode"
  },
  "geometry": {"coordinates":[-2.673501,51.511525],"type":"Point"}
}
