{
  "type": "Feature",
  "properties": {
    "iso:country":"GB",
    "wof:name":"CR7 8HH",
    "wof:placetype":"postalcode"
},
  "geometry": {"coordinates":[-0.10490019217358,51.40657474281908],"type":"Point"}
}