{
  "type": "Feature",
  "properties": {
    "date:inception_lower": "1990-07-01",
    "date:inception_upper": "1990-07-01",
    "iso:country": "GB",
    "wof:name": "CR7 8HH",
    "wof:placetype": "postalcode"
  },
  "geometry": {"coordinates":[-0.1049,51.406575],"type":"Point"}
}
