{
  "type": "Feature",
  "properties": {
    "date:inception_lower": "1980-01-01",
    "date:inception_upper": "1980-01-01",
    "iso:country": "GB",
    "wof:name": "G84 7NW",
    "wof:placetype": "postalcode"
  },
  "geometry": {"coordinates":[-4.711224,56.003217],"type":"Point"}
}
