{
  "type": "Feature",
  "properties": {
    "date:inception_lower": "2023-09-01",
    "date:inception_upper": "2023-09-01",
    "iso:country": "GB",
    "wof:name": "RH6 8UD",
    "wof:placetype": "postalcode"
  },
  "geometry": {"coordinates":[-0.176346,51.186538],"type":"Point"}
}
