{
  "type": "Feature",
  "properties": {
    "iso:country":"GB",
    "wof:name":"DL8 2NP",
    "wof:placetype":"postalcode"
},
  "geometry": {"coordinates":[-1.49523442566977,54.21123291611778],"type":"Point"}
}