{
  "type": "Feature",
  "properties": {
    "date:inception_lower": "1980-01-01",
    "date:inception_upper": "1980-01-01",
    "iso:country": "GB",
    "wof:name": "DL8 2NP",
    "wof:placetype": "postalcode"
  },
  "geometry": {"coordinates":[-1.495257,54.211246],"type":"Point"}
}
