{
  "type": "Feature",
  "properties": {
    "iso:country":"GB",
    "wof:name":"W1K 5JE",
    "wof:placetype":"postalcode"
},
  "geometry": {"coordinates":[-0.14917748216686,51.51317891959307],"type":"Point"}
}