{
  "type": "Feature",
  "properties": {
    "iso:country": "GB",
    "wof:name": "TN17 2JY",
    "wof:placetype": "postalcode"
  },
  "geometry": {"coordinates":[0.55921,51.10998],"type":"Point"}
}
