{
  "type": "Feature",
  "properties": {
    "iso:country":"GB",
    "wof:name":"TN16 2JS",
    "wof:placetype":"postalcode"
},
  "geometry": {"coordinates":[0.0228989359359,51.29347452987137],"type":"Point"}
}