{
  "type": "Feature",
  "properties": {
    "date:inception_lower": "2023-12-01",
    "date:inception_upper": "2023-12-01",
    "iso:country": "GB",
    "wof:name": "CA13 9FT",
    "wof:placetype": "postalcode"
  },
  "geometry": {"coordinates":[-3.347021,54.660454],"type":"Point"}
}
