{
  "type": "Feature",
  "properties": {
    "iso:country":"GB",
    "wof:name":"PE29 6JX",
    "wof:placetype":"postalcode"
},
  "geometry": {"coordinates":[-0.21374975757052,52.33396730530405],"type":"Point"}
}