{
  "type": "Feature",
  "properties": {
    "date:inception_lower": "2007-01-01",
    "date:inception_upper": "2007-01-01",
    "iso:country": "GB",
    "wof:name": "PE29 6JX",
    "wof:placetype": "postalcode"
  },
  "geometry": {"coordinates":[-0.21375,52.333967],"type":"Point"}
}
