{
  "type": "Feature",
  "properties": {
    "iso:country": "GB",
    "wof:name": "PE29 6JX",
    "wof:placetype": "postalcode"
  },
  "geometry": {"coordinates":[-0.21375,52.333967],"type":"Point"}
}
