{
  "type": "Feature",
  "properties": {
    "iso:country":"GB",
    "wof:name":"LL11 6EU",
    "wof:placetype":"postalcode"
},
  "geometry": {"coordinates":[-3.03670248621904,53.07785781052625],"type":"Point"}
}