{
  "type": "Feature",
  "properties": {
    "iso:country":"GB",
    "wof:name":"OX16 2EY",
    "wof:placetype":"postalcode"
},
  "geometry": {"coordinates":[-1.34238400074963,52.06522387985915],"type":"Point"}
}