{
  "type": "Feature",
  "properties": {
    "iso:country":"GB",
    "wof:name":"HD2 2EH",
    "wof:placetype":"postalcode"
},
  "geometry": {"coordinates":[-1.82307446645472,53.67278662578925],"type":"Point"}
}