{
  "type": "Feature",
  "properties": {
    "iso:country":"GB",
    "wof:name":"DE65 6AN",
    "wof:placetype":"postalcode"
},
  "geometry": {"coordinates":[-1.54532222869934,52.87166230191936],"type":"Point"}
}