{
  "type": "Feature",
  "properties": {
    "date:inception_lower": "1992-01-01",
    "date:inception_upper": "1992-01-01",
    "iso:country": "GB",
    "wof:name": "B90 4UB",
    "wof:placetype": "postalcode"
  },
  "geometry": {"coordinates":[-1.793543,52.384605],"type":"Point"}
}
