{
  "type": "Feature",
  "properties": {
    "iso:country":"GB",
    "wof:name":"B90 4UB",
    "wof:placetype":"postalcode"
},
  "geometry": {"coordinates":[-1.79354291021034,52.38460496621665],"type":"Point"}
}