{
  "type": "Feature",
  "properties": {
    "iso:country":"GB",
    "wof:name":"CO9 2QW",
    "wof:placetype":"postalcode"
},
  "geometry": {"coordinates":[0.63212199214341,51.95962778342656],"type":"Point"}
}