{
  "type": "Feature",
  "properties": {
    "iso:country": "GB",
    "wof:name": "CO9 2QW",
    "wof:placetype": "postalcode"
  },
  "geometry": {"coordinates":[0.632122,51.959628],"type":"Point"}
}
