{
  "type": "Feature",
  "properties": {
    "date:inception_lower": "1993-01-01",
    "date:inception_upper": "1993-01-01",
    "iso:country": "GB",
    "wof:name": "CF62 3EH",
    "wof:placetype": "postalcode"
  },
  "geometry": {"coordinates":[-3.357323,51.38923],"type":"Point"}
}
