{
  "type": "Feature",
  "properties": {
    "iso:country": "GB",
    "wof:name": "CF62 3EH",
    "wof:placetype": "postalcode"
  },
  "geometry": {"coordinates":[-3.357323,51.38923],"type":"Point"}
}
