{
  "type": "Feature",
  "properties": {
    "iso:country":"GB",
    "wof:name":"S81 7JJ",
    "wof:placetype":"postalcode"
},
  "geometry": {"coordinates":[-1.12665842444831,53.31592946801983],"type":"Point"}
}