{
  "type": "Feature",
  "properties": {
    "iso:country": "GB",
    "wof:name": "UB6 9HL",
    "wof:placetype": "postalcode"
  },
  "geometry": {"coordinates":[-0.362448,51.526314],"type":"Point"}
}
