{
  "type": "Feature",
  "properties": {
    "date:inception_lower": "1980-01-01",
    "date:inception_upper": "1980-01-01",
    "iso:country": "GB",
    "wof:name": "UB6 9HL",
    "wof:placetype": "postalcode"
  },
  "geometry": {"coordinates":[-0.362448,51.526314],"type":"Point"}
}
