{
  "type": "Feature",
  "properties": {
    "iso:country":"GB",
    "wof:name":"UB6 9HL",
    "wof:placetype":"postalcode"
},
  "geometry": {"coordinates":[-0.36244802694266,51.52631366840852],"type":"Point"}
}