{
  "type": "Feature",
  "properties": {
    "date:inception_lower": "1994-06-01",
    "date:inception_upper": "1994-06-01",
    "iso:country": "GB",
    "wof:name": "ML6 8HX",
    "wof:placetype": "postalcode"
  },
  "geometry": {"coordinates":[-3.945264,55.837825],"type":"Point"}
}
