{
  "type": "Feature",
  "properties": {
    "date:inception_lower": "2023-04-01",
    "date:inception_upper": "2023-04-01",
    "iso:country": "GB",
    "wof:name": "W2 4BD",
    "wof:placetype": "postalcode"
  },
  "geometry": {"coordinates":[-0.190341,51.514309],"type":"Point"}
}
