{
  "type": "Feature",
  "properties": {
    "iso:country":"GB",
    "wof:name":"BS15 8BE",
    "wof:placetype":"postalcode"
},
  "geometry": {"coordinates":[-2.51515750683523,51.46270533649088],"type":"Point"}
}