{
  "type": "Feature",
  "properties": {
    "iso:country":"GB",
    "wof:name":"WA13 0DU",
    "wof:placetype":"postalcode"
},
  "geometry": {"coordinates":[-2.49333948710697,53.37510955100614],"type":"Point"}
}