{
  "type": "Feature",
  "properties": {
    "date:inception_lower": "1980-01-01",
    "date:inception_upper": "1980-01-01",
    "iso:country": "GB",
    "wof:name": "SS17 8HJ",
    "wof:placetype": "postalcode"
  },
  "geometry": {"coordinates":[0.44084,51.529524],"type":"Point"}
}
