{
  "type": "Feature",
  "properties": {
    "iso:country":"GB",
    "wof:name":"B65 9AN",
    "wof:placetype":"postalcode"
},
  "geometry": {"coordinates":[-2.04634069543407,52.48337824502516],"type":"Point"}
}