{
  "type": "Feature",
  "properties": {
    "iso:country": "GB",
    "wof:name": "ST11 9HY",
    "wof:placetype": "postalcode"
  },
  "geometry": {"coordinates":[-2.083899,52.972346],"type":"Point"}
}
