{
  "type": "Feature",
  "properties": {
    "iso:country":"GB",
    "wof:name":"ST11 9HY",
    "wof:placetype":"postalcode"
},
  "geometry": {"coordinates":[-2.08389856714165,52.97234579505962],"type":"Point"}
}