{
  "type": "Feature",
  "properties": {
    "iso:country": "GB",
    "wof:name": "WS14 9RE",
    "wof:placetype": "postalcode"
  },
  "geometry": {"coordinates":[-1.802534,52.651252],"type":"Point"}
}
