{
  "type": "Feature",
  "properties": {
    "iso:country":"GB",
    "wof:name":"WS14 9RE",
    "wof:placetype":"postalcode"
},
  "geometry": {"coordinates":[-1.80253449071808,52.65125215523493],"type":"Point"}
}