{
  "type": "Feature",
  "properties": {
    "date:inception_lower":"1997-12-01",
    "date:inception_upper":"1997-12-31",
    "iso:country":"GB",
    "wof:name":"BS36 2BS",
    "wof:placetype":"postalcode"
},
  "geometry": {"coordinates":[-2.486272,51.533439],"type":"Point"}
}