{
  "type": "Feature",
  "properties": {
    "date:inception_lower": "2006-03-01",
    "date:inception_upper": "2006-03-01",
    "iso:country": "GB",
    "wof:name": "LS17 0BF",
    "wof:placetype": "postalcode"
  },
  "geometry": {"coordinates":[-1.573191,53.94107],"type":"Point"}
}
