{
  "type": "Feature",
  "properties": {
    "iso:country":"GB",
    "wof:name":"LS17 0BF",
    "wof:placetype":"postalcode"
},
  "geometry": {"coordinates":[-1.57319114950413,53.94106983800283],"type":"Point"}
}