{
  "type": "Feature",
  "properties": {
    "iso:country":"GB",
    "wof:name":"NP12 1BZ",
    "wof:placetype":"postalcode"
},
  "geometry": {"coordinates":[-3.19147349190195,51.6770199170462],"type":"Point"}
}