{
  "type": "Feature",
  "properties": {
    "date:inception_lower": "1999-06-01",
    "date:inception_upper": "1999-06-01",
    "iso:country": "GB",
    "wof:name": "NP12 1BZ",
    "wof:placetype": "postalcode"
  },
  "geometry": {"coordinates":[-3.191743,51.677029],"type":"Point"}
}
