{
  "type": "Feature",
  "properties": {
    "iso:country":"GB",
    "wof:name":"BS5 0UY",
    "wof:placetype":"postalcode"
},
  "geometry": {"coordinates":[-2.57548336352309,51.46256852156029],"type":"Point"}
}