{
  "type": "Feature",
  "properties": {
    "iso:country":"GB",
    "wof:name":"EH17 8FG",
    "wof:placetype":"postalcode"
},
  "geometry": {"coordinates":[-3.15460274150585,55.90041566481739],"type":"Point"}
}