{
  "type": "Feature",
  "properties": {
    "iso:country":"GB",
    "wof:name":"SS7 3QU",
    "wof:placetype":"postalcode"
},
  "geometry": {"coordinates":[0.58752787255262,51.56904395231307],"type":"Point"}
}