{
  "type": "Feature",
  "properties": {
    "date:inception_lower":"2003-07-01",
    "date:inception_upper":"2003-07-31",
    "iso:country":"GB",
    "wof:name":"LU7 4HY",
    "wof:placetype":"postalcode"
},
  "geometry": {"coordinates":[-0.637498,51.909712],"type":"Point"}
}