{
  "type": "Feature",
  "properties": {
    "iso:country":"GB",
    "wof:name":"LU7 4HY",
    "wof:placetype":"postalcode"
},
  "geometry": {"coordinates":[-0.63749825512004,51.90971227142533],"type":"Point"}
}