{
  "type": "Feature",
  "properties": {
    "iso:country":"GB",
    "wof:name":"NN14 4UE",
    "wof:placetype":"postalcode"
},
  "geometry": {"coordinates":[-0.53199126218616,52.39293386933122],"type":"Point"}
}