{
  "type": "Feature",
  "properties": {
    "date:inception_lower": "1994-12-01",
    "date:inception_upper": "1994-12-01",
    "iso:country": "GB",
    "wof:name": "NN14 4UE",
    "wof:placetype": "postalcode"
  },
  "geometry": {"coordinates":[-0.531991,52.392934],"type":"Point"}
}
