{
  "type": "Feature",
  "properties": {
    "iso:country":"GB",
    "wof:name":"TS5 7NE",
    "wof:placetype":"postalcode"
},
  "geometry": {"coordinates":[-1.24133731514054,54.54585799532307],"type":"Point"}
}