{
  "type": "Feature",
  "properties": {
    "iso:country":"GB",
    "wof:name":"TN15 8AY",
    "wof:placetype":"postalcode"
},
  "geometry": {"coordinates":[0.30262425612708,51.29223659342131],"type":"Point"}
}