{
  "type": "Feature",
  "properties": {
    "iso:country":"GB",
    "wof:name":"DE73 5QB",
    "wof:placetype":"postalcode"
},
  "geometry": {"coordinates":[-1.44695263854111,52.87084964331908],"type":"Point"}
}