{
  "type": "Feature",
  "properties": {
    "date:inception_lower":"2005-11-01",
    "date:inception_upper":"2005-11-30",
    "iso:country":"GB",
    "wof:name":"DE73 5QB",
    "wof:placetype":"postalcode"
},
  "geometry": {"coordinates":[-1.446948,52.870886],"type":"Point"}
}