{
  "type": "Feature",
  "properties": {
    "date:inception_lower": "2005-05-01",
    "date:inception_upper": "2005-05-01",
    "iso:country": "GB",
    "wof:name": "RG30 4AW",
    "wof:placetype": "postalcode"
  },
  "geometry": {"coordinates":[-1.016949,51.450539],"type":"Point"}
}
