{
  "type": "Feature",
  "properties": {
    "date:inception_lower": "2012-02-01",
    "date:inception_upper": "2012-02-01",
    "iso:country": "GB",
    "wof:name": "NP22 4FA",
    "wof:placetype": "postalcode"
  },
  "geometry": {"coordinates":[-3.225571,51.755682],"type":"Point"}
}
