{
  "type": "Feature",
  "properties": {
    "iso:country":"GB",
    "wof:name":"SM1 3TZ",
    "wof:placetype":"postalcode"
},
  "geometry": {"coordinates":[-0.1914232171445,51.38341015766557],"type":"Point"}
}