{
  "type": "Feature",
  "properties": {
    "iso:country":"GB",
    "wof:name":"HA8 8SS",
    "wof:placetype":"postalcode"
},
  "geometry": {"coordinates":[-0.27295323039099,51.62571673474655],"type":"Point"}
}