{
  "type": "Feature",
  "properties": {
    "iso:country":"GB",
    "wof:name":"SL3 8GS",
    "wof:placetype":"postalcode"
},
  "geometry": {"coordinates":[-0.53875730439766,51.49549726697229],"type":"Point"}
}