{
  "type": "Feature",
  "properties": {
    "iso:country": "GB",
    "wof:name": "SL3 8GS",
    "wof:placetype": "postalcode"
  },
  "geometry": {"coordinates":[-0.538769,51.495463],"type":"Point"}
}
