{
  "type": "Feature",
  "properties": {
    "iso:country": "GB",
    "wof:name": "SL3 8GS",
    "wof:placetype": "postalcode"
  },
  "geometry": {"coordinates":[-0.538739,51.495499],"type":"Point"}
}
