{
  "type": "Feature",
  "properties": {
    "date:inception_lower": "2005-10-01",
    "date:inception_upper": "2005-10-01",
    "iso:country": "GB",
    "wof:name": "SL3 8GS",
    "wof:placetype": "postalcode"
  },
  "geometry": {"coordinates":[-0.538739,51.495499],"type":"Point"}
}
