{
  "type": "Feature",
  "properties": {
    "iso:country": "GB",
    "wof:name": "E3 3AU",
    "wof:placetype": "postalcode"
  },
  "geometry": {"coordinates":[-0.015839,51.528714],"type":"Point"}
}
