{
  "type": "Feature",
  "properties": {
    "iso:country":"GB",
    "wof:name":"E3 3AU",
    "wof:placetype":"postalcode"
},
  "geometry": {"coordinates":[-0.01583872631242,51.52871446068717],"type":"Point"}
}