{
  "type": "Feature",
  "properties": {
    "date:inception_lower":"2003-11-01",
    "date:inception_upper":"2003-11-30",
    "iso:country":"GB",
    "wof:name":"NG17 4JQ",
    "wof:placetype":"postalcode"
},
  "geometry": {"coordinates":[-1.238817,53.133474],"type":"Point"}
}