{
  "type": "Feature",
  "properties": {
    "iso:country":"GB",
    "wof:name":"BL4 8BA",
    "wof:placetype":"postalcode"
},
  "geometry": {"coordinates":[-2.38776938450301,53.54452859878482],"type":"Point"}
}