{
  "type": "Feature",
  "properties": {
    "iso:country": "GB",
    "wof:name": "BL4 8BA",
    "wof:placetype": "postalcode"
  },
  "geometry": {"coordinates":[-2.387769,53.544529],"type":"Point"}
}
