{
  "type": "Feature",
  "properties": {
    "iso:country":"GB",
    "wof:name":"BS8 3EZ",
    "wof:placetype":"postalcode"
},
  "geometry": {"coordinates":[-2.61916787149127,51.46341589798519],"type":"Point"}
}