{
  "type": "Feature",
  "properties": {
    "iso:country": "GB",
    "wof:name": "SO16 4FE",
    "wof:placetype": "postalcode"
  },
  "geometry": {"coordinates":[-1.444309,50.927209],"type":"Point"}
}
