{
  "type": "Feature",
  "properties": {
    "date:inception_lower": "1980-01-01",
    "date:inception_upper": "1980-01-01",
    "iso:country": "GB",
    "wof:name": "NE25 0QG",
    "wof:placetype": "postalcode"
  },
  "geometry": {"coordinates":[-1.543673,55.083161],"type":"Point"}
}
