{
  "type": "Feature",
  "properties": {
    "iso:country":"GB",
    "wof:name":"NE34 7PD",
    "wof:placetype":"postalcode"
},
  "geometry": {"coordinates":[-1.40699521877812,54.9698846620017],"type":"Point"}
}