{
  "type": "Feature",
  "properties": {
    "iso:country":"GB",
    "wof:name":"AL3 7HE",
    "wof:placetype":"postalcode"
},
  "geometry": {"coordinates":[-0.40380624466711,51.79872124955256],"type":"Point"}
}