{
  "type": "Feature",
  "properties": {
    "iso:country": "GB",
    "wof:name": "NR9 3FE",
    "wof:placetype": "postalcode"
  },
  "geometry": {"coordinates":[1.181738,52.597799],"type":"Point"}
}
