{
  "type": "Feature",
  "properties": {
    "iso:country":"GB",
    "wof:name":"NR9 3FE",
    "wof:placetype":"postalcode"
},
  "geometry": {"coordinates":[1.18173763600538,52.5977992644497],"type":"Point"}
}