{
  "type": "Feature",
  "properties": {
    "date:inception_lower": "1980-01-01",
    "date:inception_upper": "1980-01-01",
    "iso:country": "GB",
    "wof:name": "LL16 3SF",
    "wof:placetype": "postalcode"
  },
  "geometry": {"coordinates":[-3.419955,53.183036],"type":"Point"}
}
