{
  "type": "Feature",
  "properties": {
    "iso:country":"GB",
    "wof:name":"N16 5QD",
    "wof:placetype":"postalcode"
},
  "geometry": {"coordinates":[-0.07592523033939,51.56880600058155],"type":"Point"}
}