{
  "type": "Feature",
  "properties": {
    "iso:country": "GB",
    "wof:name": "W12 0RF",
    "wof:placetype": "postalcode"
  },
  "geometry": {"coordinates":[-0.241057,51.514943],"type":"Point"}
}
