{
  "type": "Feature",
  "properties": {
    "iso:country": "GB",
    "wof:name": "TR16 5DP",
    "wof:placetype": "postalcode"
  },
  "geometry": {"coordinates":[-5.207527,50.247957],"type":"Point"}
}
