{
  "type": "Feature",
  "properties": {
    "iso:country":"GB",
    "wof:name":"M40 7HF",
    "wof:placetype":"postalcode"
},
  "geometry": {"coordinates":[-2.21588864617979,53.48638534069531],"type":"Point"}
}