{
  "type": "Feature",
  "properties": {
    "date:inception_lower": "2020-11-01",
    "date:inception_upper": "2020-11-01",
    "iso:country": "GB",
    "wof:name": "HP17 8FT",
    "wof:placetype": "postalcode"
  },
  "geometry": {"coordinates":[-0.92299,51.769426],"type":"Point"}
}
