{
  "type": "Feature",
  "properties": {
    "date:inception_lower": "1980-01-01",
    "date:inception_upper": "1980-01-01",
    "iso:country": "GB",
    "wof:name": "G73 2SP",
    "wof:placetype": "postalcode"
  },
  "geometry": {"coordinates":[-4.215671,55.82677],"type":"Point"}
}
