{
  "type": "Feature",
  "properties": {
    "date:inception_lower": "1980-01-01",
    "date:inception_upper": "1980-01-01",
    "iso:country": "GB",
    "wof:name": "NP4 8JW",
    "wof:placetype": "postalcode"
  },
  "geometry": {"coordinates":[-3.034246,51.713145],"type":"Point"}
}
