{
  "type": "Feature",
  "properties": {
    "iso:country":"GB",
    "wof:name":"NP4 8JW",
    "wof:placetype":"postalcode"
},
  "geometry": {"coordinates":[-3.03424653682236,51.713145177664],"type":"Point"}
}