{
  "type": "Feature",
  "properties": {
    "iso:country":"GB",
    "wof:name":"UB7 0JG",
    "wof:placetype":"postalcode"
},
  "geometry": {"coordinates":[-0.45560075799252,51.49013351155268],"type":"Point"}
}