{
  "type": "Feature",
  "properties": {
    "iso:country":"GB",
    "wof:name":"NN4 7EQ",
    "wof:placetype":"postalcode"
},
  "geometry": {"coordinates":[-0.8808742677813,52.21264049730502],"type":"Point"}
}