{
  "type": "Feature",
  "properties": {
    "iso:country": "GB",
    "wof:name": "NN4 7EQ",
    "wof:placetype": "postalcode"
  },
  "geometry": {"coordinates":[-0.880874,52.21264],"type":"Point"}
}
