{
  "type": "Feature",
  "properties": {
    "iso:country":"GB",
    "wof:name":"NR31 8LJ",
    "wof:placetype":"postalcode"
},
  "geometry": {"coordinates":[1.71667809412918,52.57942360880532],"type":"Point"}
}