{
  "type": "Feature",
  "properties": {
    "iso:country": "GB",
    "wof:name": "BL4 0RD",
    "wof:placetype": "postalcode"
  },
  "geometry": {"coordinates":[-2.425944,53.545477],"type":"Point"}
}
