{
  "type": "Feature",
  "properties": {
    "iso:country":"GB",
    "wof:name":"GL51 0BX",
    "wof:placetype":"postalcode"
},
  "geometry": {"coordinates":[-2.11355617981984,51.90856757310389],"type":"Point"}
}