{
  "type": "Feature",
  "properties": {
    "date:inception_lower": "1980-01-01",
    "date:inception_upper": "1980-01-01",
    "iso:country": "GB",
    "wof:name": "SG1 5HH",
    "wof:placetype": "postalcode"
  },
  "geometry": {"coordinates":[-0.183959,51.906969],"type":"Point"}
}
