{
  "type": "Feature",
  "properties": {
    "iso:country": "GB",
    "wof:name": "SA72 6EU",
    "wof:placetype": "postalcode"
  },
  "geometry": {"coordinates":[-4.933472,51.698802],"type":"Point"}
}
