{
  "type": "Feature",
  "properties": {
    "date:inception_lower":"2014-11-01",
    "date:inception_upper":"2014-11-30",
    "iso:country":"GB",
    "wof:name":"S12 9ED",
    "wof:placetype":"postalcode"
},
  "geometry": {"coordinates":[-1.425085,53.360464],"type":"Point"}
}