{
  "type": "Feature",
  "properties": {
    "iso:country": "GB",
    "wof:name": "DT6 6DR",
    "wof:placetype": "postalcode"
  },
  "geometry": {"coordinates":[-2.844914,50.739069],"type":"Point"}
}
