{
  "type": "Feature",
  "properties": {
    "date:inception_lower": "1992-08-01",
    "date:inception_upper": "1992-08-01",
    "iso:country": "GB",
    "wof:name": "B98 8LT",
    "wof:placetype": "postalcode"
  },
  "geometry": {"coordinates":[-1.932263,52.30546],"type":"Point"}
}
