{
  "type": "Feature",
  "properties": {
    "iso:country":"GB",
    "wof:name":"B98 8LT",
    "wof:placetype":"postalcode"
},
  "geometry": {"coordinates":[-1.93296081906745,52.30522094657507],"type":"Point"}
}