{
  "type": "Feature",
  "properties": {
    "date:inception_lower": "2011-07-01",
    "date:inception_upper": "2011-07-01",
    "iso:country": "GB",
    "wof:name": "KT10 9EW",
    "wof:placetype": "postalcode"
  },
  "geometry": {"coordinates":[-0.363334,51.361496],"type":"Point"}
}
