{
  "type": "Feature",
  "properties": {
    "iso:country":"GB",
    "wof:name":"RG24 8XB",
    "wof:placetype":"postalcode"
},
  "geometry": {"coordinates":[-1.05851006508113,51.29709999609867],"type":"Point"}
}