{
  "type": "Feature",
  "properties": {
    "iso:country": "GB",
    "wof:name": "RG24 8XB",
    "wof:placetype": "postalcode"
  },
  "geometry": {"coordinates":[-1.05851,51.2971],"type":"Point"}
}
