{
  "type": "Feature",
  "properties": {
    "iso:country":"GB",
    "wof:name":"DT4 9JL",
    "wof:placetype":"postalcode"
},
  "geometry": {"coordinates":[-2.47152907710959,50.59196180385717],"type":"Point"}
}