{
  "type": "Feature",
  "properties": {
    "iso:country": "GB",
    "wof:name": "DT4 9JL",
    "wof:placetype": "postalcode"
  },
  "geometry": {"coordinates":[-2.471529,50.591962],"type":"Point"}
}
