{
  "type": "Feature",
  "properties": {
    "iso:country": "GB",
    "wof:name": "RG30 4UE",
    "wof:placetype": "postalcode"
  },
  "geometry": {"coordinates":[-1.035638,51.460306],"type":"Point"}
}
