{
  "type": "Feature",
  "properties": {
    "iso:country": "GB",
    "wof:name": "B65 0QL",
    "wof:placetype": "postalcode"
  },
  "geometry": {"coordinates":[-2.026327,52.479213],"type":"Point"}
}
