{
  "type": "Feature",
  "properties": {
    "iso:country":"GB",
    "wof:name":"B65 0QL",
    "wof:placetype":"postalcode"
},
  "geometry": {"coordinates":[-2.02632660026696,52.47921309596941],"type":"Point"}
}