{
  "type": "Feature",
  "properties": {
    "date:inception_lower": "1994-12-01",
    "date:inception_upper": "1994-12-01",
    "iso:country": "GB",
    "wof:name": "B65 0QL",
    "wof:placetype": "postalcode"
  },
  "geometry": {"coordinates":[-2.026327,52.479213],"type":"Point"}
}
