{
  "type": "Feature",
  "properties": {
    "date:inception_lower": "2024-10-01",
    "date:inception_upper": "2024-10-01",
    "iso:country": "GB",
    "wof:name": "CO6 1ZT",
    "wof:placetype": "postalcode"
  },
  "geometry": {"coordinates":[0.698393,51.87299],"type":"Point"}
}
