{
  "type": "Feature",
  "properties": {
    "iso:country":"GB",
    "wof:name":"DA1 4NQ",
    "wof:placetype":"postalcode"
},
  "geometry": {"coordinates":[0.19132190863866,51.45597013174086],"type":"Point"}
}