{
  "type": "Feature",
  "properties": {
    "iso:country":"GB",
    "wof:name":"E13 0LU",
    "wof:placetype":"postalcode"
},
  "geometry": {"coordinates":[0.02388561727324,51.53565255637467],"type":"Point"}
}