{
  "type": "Feature",
  "properties": {
    "date:inception_lower":"1980-01-01",
    "date:inception_upper":"1980-01-31",
    "iso:country":"GB",
    "wof:name":"E13 0LU",
    "wof:placetype":"postalcode"
},
  "geometry": {"coordinates":[0.023886,51.535653],"type":"Point"}
}