{
  "type": "Feature",
  "properties": {
    "iso:country":"GB",
    "wof:name":"WC2B 5LT",
    "wof:placetype":"postalcode"
},
  "geometry": {"coordinates":[-0.12269063434138,51.51662474798807],"type":"Point"}
}