{
  "type": "Feature",
  "properties": {
    "iso:country":"GB",
    "wof:name":"OL11 2UE",
    "wof:placetype":"postalcode"
},
  "geometry": {"coordinates":[-2.16587296369712,53.58728776708205],"type":"Point"}
}