{
  "type": "Feature",
  "properties": {
    "iso:country":"GB",
    "wof:name":"LN9 5EU",
    "wof:placetype":"postalcode"
},
  "geometry": {"coordinates":[-0.11152391371913,53.21414255038482],"type":"Point"}
}