{
  "type": "Feature",
  "properties": {
    "iso:country":"GB",
    "wof:name":"CB23 1JH",
    "wof:placetype":"postalcode"
},
  "geometry": {"coordinates":[0.04797192976411,52.14989352713447],"type":"Point"}
}