{
  "type": "Feature",
  "properties": {
    "iso:country":"GB",
    "wof:name":"CM1 4JX",
    "wof:placetype":"postalcode"
},
  "geometry": {"coordinates":[0.46519848429444,51.74703559099419],"type":"Point"}
}