{
  "type": "Feature",
  "properties": {
    "date:inception_lower":"1980-01-01",
    "date:inception_upper":"1980-01-31",
    "iso:country":"GB",
    "wof:name":"CM1 4JX",
    "wof:placetype":"postalcode"
},
  "geometry": {"coordinates":[0.465199,51.747036],"type":"Point"}
}