{
  "type": "Feature",
  "properties": {
    "iso:country":"GB",
    "wof:name":"LS10 4HZ",
    "wof:placetype":"postalcode"
},
  "geometry": {"coordinates":[-1.54822493754374,53.73887495856307],"type":"Point"}
}