{
  "type": "Feature",
  "properties": {
    "date:inception_lower":"1980-01-01",
    "date:inception_upper":"1980-01-31",
    "iso:country":"GB",
    "wof:name":"TN34 1JE",
    "wof:placetype":"postalcode"
},
  "geometry": {"coordinates":[0.578073,50.854969],"type":"Point"}
}