{
  "type": "Feature",
  "properties": {
    "date:inception_lower": "2004-02-01",
    "date:inception_upper": "2004-02-01",
    "iso:country": "GB",
    "wof:name": "TW19 7TH",
    "wof:placetype": "postalcode"
  },
  "geometry": {"coordinates":[-0.470508,51.447112],"type":"Point"}
}
