{
  "type": "Feature",
  "properties": {
    "iso:country": "GB",
    "wof:name": "BS34 9GZ",
    "wof:placetype": "postalcode"
  },
  "geometry": {"coordinates":[-2.570713,51.533462],"type":"Point"}
}
