{
  "type": "Feature",
  "properties": {
    "date:inception_lower": "2017-06-01",
    "date:inception_upper": "2017-06-01",
    "iso:country": "GB",
    "wof:name": "SE17 1FQ",
    "wof:placetype": "postalcode"
  },
  "geometry": {"coordinates":[-0.09469,51.492434],"type":"Point"}
}
