{
  "type": "Feature",
  "properties": {
    "iso:country": "GB",
    "wof:name": "HS1 2AD",
    "wof:placetype": "postalcode"
  },
  "geometry": {"coordinates":[-6.386334,58.208782],"type":"Point"}
}
