{
  "type": "Feature",
  "properties": {
    "iso:country":"GB",
    "wof:name":"HS1 2AD",
    "wof:placetype":"postalcode"
},
  "geometry": {"coordinates":[-6.38633367811901,58.20878192113501],"type":"Point"}
}