{
  "type": "Feature",
  "properties": {
    "iso:country": "GB",
    "wof:name": "CW4 7AH",
    "wof:placetype": "postalcode"
  },
  "geometry": {"coordinates":[-2.357254,53.201509],"type":"Point"}
}
