{
  "type": "Feature",
  "properties": {
    "date:inception_lower": "1980-01-01",
    "date:inception_upper": "1980-01-01",
    "iso:country": "GB",
    "wof:name": "CW4 7AH",
    "wof:placetype": "postalcode"
  },
  "geometry": {"coordinates":[-2.357282,53.201544],"type":"Point"}
}
