{
  "type": "Feature",
  "properties": {
    "iso:country": "GB",
    "wof:name": "PE3 8DE",
    "wof:placetype": "postalcode"
  },
  "geometry": {"coordinates":[-0.284958,52.588678],"type":"Point"}
}
