{
  "type": "Feature",
  "properties": {
    "date:inception_lower": "1980-01-01",
    "date:inception_upper": "1980-01-01",
    "iso:country": "GB",
    "wof:name": "PE3 8DE",
    "wof:placetype": "postalcode"
  },
  "geometry": {"coordinates":[-0.284958,52.588678],"type":"Point"}
}
