{
  "type": "Feature",
  "properties": {
    "iso:country":"GB",
    "wof:name":"PE3 8DE",
    "wof:placetype":"postalcode"
},
  "geometry": {"coordinates":[-0.28509258478006,52.58859819857346],"type":"Point"}
}