{
  "type": "Feature",
  "properties": {
    "iso:country":"GB",
    "wof:name":"NE61 2YF",
    "wof:placetype":"postalcode"
},
  "geometry": {"coordinates":[-1.70573306698869,55.16320421295191],"type":"Point"}
}