{
  "type": "Feature",
  "properties": {
    "date:inception_lower": "1980-01-01",
    "date:inception_upper": "1980-01-01",
    "iso:country": "GB",
    "wof:name": "NE61 2YF",
    "wof:placetype": "postalcode"
  },
  "geometry": {"coordinates":[-1.705733,55.163204],"type":"Point"}
}
