{
  "type": "Feature",
  "properties": {
    "iso:country":"GB",
    "wof:name":"L11 3EF",
    "wof:placetype":"postalcode"
},
  "geometry": {"coordinates":[-2.91989586679425,53.45166779743197],"type":"Point"}
}