{
  "type": "Feature",
  "properties": {
    "date:inception_lower": "2015-03-01",
    "date:inception_upper": "2015-03-01",
    "iso:country": "GB",
    "wof:name": "TF1 5TJ",
    "wof:placetype": "postalcode"
  },
  "geometry": {"coordinates":[-2.468869,52.706062],"type":"Point"}
}
