{
  "type": "Feature",
  "properties": {
    "date:inception_lower":"1999-06-01",
    "date:inception_upper":"1999-06-30",
    "iso:country":"GB",
    "wof:name":"CH49 8EJ",
    "wof:placetype":"postalcode"
},
  "geometry": {"coordinates":[-3.087182,53.377316],"type":"Point"}
}