{
  "type": "Feature",
  "properties": {
    "iso:country":"GB",
    "wof:name":"M15 4DT",
    "wof:placetype":"postalcode"
},
  "geometry": {"coordinates":[-2.25859789970923,53.46657078678535],"type":"Point"}
}