{
  "type": "Feature",
  "properties": {
    "date:inception_lower":"1980-01-01",
    "date:inception_upper":"1980-01-31",
    "iso:country":"GB",
    "wof:name":"M15 4DT",
    "wof:placetype":"postalcode"
},
  "geometry": {"coordinates":[-2.258598,53.466571],"type":"Point"}
}