{
  "type": "Feature",
  "properties": {
    "iso:country":"GB",
    "wof:name":"NP44 3NR",
    "wof:placetype":"postalcode"
},
  "geometry": {"coordinates":[-3.02530268165783,51.65622639895404],"type":"Point"}
}