{
  "type": "Feature",
  "properties": {
    "iso:country":"GB",
    "wof:name":"DY3 3RT",
    "wof:placetype":"postalcode"
},
  "geometry": {"coordinates":[-2.12806579411703,52.55421221629216],"type":"Point"}
}