{
  "type": "Feature",
  "properties": {
    "iso:country":"GB",
    "wof:name":"CF24 1DH",
    "wof:placetype":"postalcode"
},
  "geometry": {"coordinates":[-3.15824448435127,51.48830975117436],"type":"Point"}
}