{
  "type": "Feature",
  "properties": {
    "date:inception_lower": "1980-01-01",
    "date:inception_upper": "1980-01-01",
    "iso:country": "GB",
    "wof:name": "ME7 4ET",
    "wof:placetype": "postalcode"
  },
  "geometry": {"coordinates":[0.552975,51.382026],"type":"Point"}
}
