{
  "type": "Feature",
  "properties": {
    "iso:country":"GB",
    "wof:name":"ME7 4ET",
    "wof:placetype":"postalcode"
},
  "geometry": {"coordinates":[0.55297516502254,51.38202584873118],"type":"Point"}
}