{
  "type": "Feature",
  "properties": {
    "date:inception_lower": "1980-01-01",
    "date:inception_upper": "1980-01-01",
    "iso:country": "GB",
    "wof:name": "ST2 9BP",
    "wof:placetype": "postalcode"
  },
  "geometry": {"coordinates":[-2.14476,53.022446],"type":"Point"}
}
