{
  "type": "Feature",
  "properties": {
    "iso:country": "GB",
    "wof:name": "ST2 9BP",
    "wof:placetype": "postalcode"
  },
  "geometry": {"coordinates":[-2.14476,53.022446],"type":"Point"}
}
