{
  "type": "Feature",
  "properties": {
    "iso:country": "GB",
    "wof:name": "B13 9AW",
    "wof:placetype": "postalcode"
  },
  "geometry": {"coordinates":[-1.882681,52.451451],"type":"Point"}
}
