{
  "type": "Feature",
  "properties": {
    "iso:country":"GB",
    "wof:name":"B13 9AW",
    "wof:placetype":"postalcode"
},
  "geometry": {"coordinates":[-1.8826808787184,52.45145104600967],"type":"Point"}
}