{
  "type": "Feature",
  "properties": {
    "iso:country":"GB",
    "wof:name":"SN8 1DR",
    "wof:placetype":"postalcode"
},
  "geometry": {"coordinates":[-1.72937241854083,51.4273263551507],"type":"Point"}
}