{
  "type": "Feature",
  "properties": {
    "iso:country": "GB",
    "wof:name": "L31 7BT",
    "wof:placetype": "postalcode"
  },
  "geometry": {"coordinates":[-2.948809,53.515181],"type":"Point"}
}
