{
  "type": "Feature",
  "properties": {
    "date:inception_lower": "1980-01-01",
    "date:inception_upper": "1980-01-01",
    "iso:country": "GB",
    "wof:name": "L31 7BT",
    "wof:placetype": "postalcode"
  },
  "geometry": {"coordinates":[-2.948809,53.515181],"type":"Point"}
}
