{
  "type": "Feature",
  "properties": {
    "iso:country": "GB",
    "wof:name": "TD11 3UH",
    "wof:placetype": "postalcode"
  },
  "geometry": {"coordinates":[-2.210524,55.801856],"type":"Point"}
}
