{
  "type": "Feature",
  "properties": {
    "date:inception_lower": "2018-05-01",
    "date:inception_upper": "2018-05-01",
    "iso:country": "GB",
    "wof:name": "S20 1DG",
    "wof:placetype": "postalcode"
  },
  "geometry": {"coordinates":[-1.339181,53.342024],"type":"Point"}
}
