{
  "type": "Feature",
  "properties": {
    "iso:country":"GB",
    "wof:name":"EX2 4HE",
    "wof:placetype":"postalcode"
},
  "geometry": {"coordinates":[-3.52390623492067,50.71891605974427],"type":"Point"}
}