{
  "type": "Feature",
  "properties": {
    "iso:country":"GB",
    "wof:name":"PO16 9HJ",
    "wof:placetype":"postalcode"
},
  "geometry": {"coordinates":[-1.13205712038843,50.84008353732738],"type":"Point"}
}