{
  "type": "Feature",
  "properties": {
    "iso:country": "GB",
    "wof:name": "BN14 9FJ",
    "wof:placetype": "postalcode"
  },
  "geometry": {"coordinates":[-0.374659,50.838747],"type":"Point"}
}
