{
  "type": "Feature",
  "properties": {
    "date:inception_lower": "2000-06-01",
    "date:inception_upper": "2000-06-01",
    "iso:country": "GB",
    "wof:name": "CW1 6NF",
    "wof:placetype": "postalcode"
  },
  "geometry": {"coordinates":[-2.416671,53.079614],"type":"Point"}
}
