{
  "type": "Feature",
  "properties": {
    "iso:country": "GB",
    "wof:name": "CW1 6NF",
    "wof:placetype": "postalcode"
  },
  "geometry": {"coordinates":[-2.416671,53.079614],"type":"Point"}
}
