{
  "type": "Feature",
  "properties": {
    "iso:country": "GB",
    "wof:name": "ST5 6PJ",
    "wof:placetype": "postalcode"
  },
  "geometry": {"coordinates":[-2.253704,53.008618],"type":"Point"}
}
