{
  "type": "Feature",
  "properties": {
    "iso:country": "GB",
    "wof:name": "RH2 7LL",
    "wof:placetype": "postalcode"
  },
  "geometry": {"coordinates":[-0.197713,51.224596],"type":"Point"}
}
