{
  "type": "Feature",
  "properties": {
    "iso:country": "GB",
    "wof:name": "ME16 8HB",
    "wof:placetype": "postalcode"
  },
  "geometry": {"coordinates":[0.513112,51.270027],"type":"Point"}
}
