{
  "type": "Feature",
  "properties": {
    "iso:country":"GB",
    "wof:name":"HA7 4UA",
    "wof:placetype":"postalcode"
},
  "geometry": {"coordinates":[-0.30432187013438,51.61671421217537],"type":"Point"}
}