{
  "type": "Feature",
  "properties": {
    "iso:country":"GB",
    "wof:name":"KY8 4EJ",
    "wof:placetype":"postalcode"
},
  "geometry": {"coordinates":[-3.00307247101288,56.19880059763479],"type":"Point"}
}