{
  "type": "Feature",
  "properties": {
    "iso:country":"GB",
    "wof:name":"WA7 1BU",
    "wof:placetype":"postalcode"
},
  "geometry": {"coordinates":[-2.728194018369,53.34289600085719],"type":"Point"}
}