{
  "type": "Feature",
  "properties": {
    "iso:country": "GB",
    "wof:name": "DL7 9PZ",
    "wof:placetype": "postalcode"
  },
  "geometry": {"coordinates":[-1.487613,54.323474],"type":"Point"}
}
