{
  "type": "Feature",
  "properties": {
    "iso:country":"GB",
    "wof:name":"DL7 9PZ",
    "wof:placetype":"postalcode"
},
  "geometry": {"coordinates":[-1.48760455285468,54.32346187627039],"type":"Point"}
}