{
  "type": "Feature",
  "properties": {
    "date:inception_lower":"2011-03-01",
    "date:inception_upper":"2011-03-31",
    "iso:country":"GB",
    "wof:name":"WF6 1GU",
    "wof:placetype":"postalcode"
},
  "geometry": {"coordinates":[-1.412938,53.696997],"type":"Point"}
}