{
  "type": "Feature",
  "properties": {
    "iso:country":"GB",
    "wof:name":"WF6 1GU",
    "wof:placetype":"postalcode"
},
  "geometry": {"coordinates":[-1.41293835159543,53.69699707663602],"type":"Point"}
}