{
  "type": "Feature",
  "properties": {
    "date:inception_lower":"2005-12-01",
    "date:inception_upper":"2005-12-31",
    "iso:country":"GB",
    "wof:name":"SN16 9TT",
    "wof:placetype":"postalcode"
},
  "geometry": {"coordinates":[-2.019533,51.641371],"type":"Point"}
}