{
  "type": "Feature",
  "properties": {
    "iso:country": "GB",
    "wof:name": "DA3 7RR",
    "wof:placetype": "postalcode"
  },
  "geometry": {"coordinates":[0.30014,51.394557],"type":"Point"}
}
