{
  "type": "Feature",
  "properties": {
    "iso:country":"GB",
    "wof:name":"DA3 7RR",
    "wof:placetype":"postalcode"
},
  "geometry": {"coordinates":[0.30014029383975,51.39455714434023],"type":"Point"}
}