{
  "type": "Feature",
  "properties": {
    "date:inception_lower":"1984-10-01",
    "date:inception_upper":"1984-10-31",
    "iso:country":"GB",
    "wof:name":"DA3 7RR",
    "wof:placetype":"postalcode"
},
  "geometry": {"coordinates":[0.30014,51.394557],"type":"Point"}
}