{
  "type": "Feature",
  "properties": {
    "iso:country":"GB",
    "wof:name":"EH27 8AF",
    "wof:placetype":"postalcode"
},
  "geometry": {"coordinates":[-3.41957406062478,55.88688037248944],"type":"Point"}
}