{
  "type": "Feature",
  "properties": {
    "iso:country":"GB",
    "wof:name":"CW5 5BH",
    "wof:placetype":"postalcode"
},
  "geometry": {"coordinates":[-2.52204074572936,53.06542648304652],"type":"Point"}
}