{
  "type": "Feature",
  "properties": {
    "date:inception_lower": "1980-01-01",
    "date:inception_upper": "1980-01-01",
    "iso:country": "GB",
    "wof:name": "CW5 5BH",
    "wof:placetype": "postalcode"
  },
  "geometry": {"coordinates":[-2.522041,53.065426],"type":"Point"}
}
