{
  "type": "Feature",
  "properties": {
    "iso:country":"GB",
    "wof:name":"NW7 3AA",
    "wof:placetype":"postalcode"
},
  "geometry": {"coordinates":[-0.25180154598666,51.6249810466718],"type":"Point"}
}