{
  "type": "Feature",
  "properties": {
    "iso:country":"GB",
    "wof:name":"SL5 8NA",
    "wof:placetype":"postalcode"
},
  "geometry": {"coordinates":[-0.69109162581866,51.41869656881974],"type":"Point"}
}