{
  "type": "Feature",
  "properties": {
    "date:inception_lower": "1980-01-01",
    "date:inception_upper": "1980-01-01",
    "iso:country": "GB",
    "wof:name": "SS9 3SW",
    "wof:placetype": "postalcode"
  },
  "geometry": {"coordinates":[0.633667,51.553106],"type":"Point"}
}
