{
  "type": "Feature",
  "properties": {
    "iso:country":"GB",
    "wof:name":"CV10 8QR",
    "wof:placetype":"postalcode"
},
  "geometry": {"coordinates":[-1.52584847664592,52.52020542966269],"type":"Point"}
}