{
  "type": "Feature",
  "properties": {
    "iso:country":"GB",
    "wof:name":"NE24 1LW",
    "wof:placetype":"postalcode"
},
  "geometry": {"coordinates":[-1.51390194365999,55.13164281021832],"type":"Point"}
}