{
  "type": "Feature",
  "properties": {
    "iso:country": "GB",
    "wof:name": "N7 9GP",
    "wof:placetype": "postalcode"
  },
  "geometry": {"coordinates":[-0.124539,51.5474],"type":"Point"}
}
