{
  "type": "Feature",
  "properties": {
    "iso:country":"GB",
    "wof:name":"LU7 0RZ",
    "wof:placetype":"postalcode"
},
  "geometry": {"coordinates":[-0.66218041715515,51.84862867412245],"type":"Point"}
}