{
  "type": "Feature",
  "properties": {
    "iso:country": "GB",
    "wof:name": "LU7 0RZ",
    "wof:placetype": "postalcode"
  },
  "geometry": {"coordinates":[-0.66218,51.848629],"type":"Point"}
}
