{
  "type": "Feature",
  "properties": {
    "date:inception_lower":"1980-01-01",
    "date:inception_upper":"1980-01-31",
    "iso:country":"GB",
    "wof:name":"NR25 6DB",
    "wof:placetype":"postalcode"
},
  "geometry": {"coordinates":[1.094721,52.901914],"type":"Point"}
}