{
  "type": "Feature",
  "properties": {
    "iso:country": "GB",
    "wof:name": "NR25 6DB",
    "wof:placetype": "postalcode"
  },
  "geometry": {"coordinates":[1.094721,52.901914],"type":"Point"}
}
