{
  "type": "Feature",
  "properties": {
    "iso:country":"GB",
    "wof:name":"IP7 6RE",
    "wof:placetype":"postalcode"
},
  "geometry": {"coordinates":[0.96186207963186,52.05367838951781],"type":"Point"}
}