{
  "type": "Feature",
  "properties": {
    "iso:country": "GB",
    "wof:name": "ML1 1UF",
    "wof:placetype": "postalcode"
  },
  "geometry": {"coordinates":[-3.986409,55.783119],"type":"Point"}
}
