{
  "type": "Feature",
  "properties": {
    "iso:country": "GB",
    "wof:name": "BL6 5JT",
    "wof:placetype": "postalcode"
  },
  "geometry": {"coordinates":[-2.587816,53.596726],"type":"Point"}
}
