{
  "type": "Feature",
  "properties": {
    "iso:country":"GB",
    "wof:name":"BL6 5JT",
    "wof:placetype":"postalcode"
},
  "geometry": {"coordinates":[-2.58781633977137,53.59672604835625],"type":"Point"}
}