{
  "type": "Feature",
  "properties": {
    "iso:country":"GB",
    "wof:name":"SA48 7PR",
    "wof:placetype":"postalcode"
},
  "geometry": {"coordinates":[-4.21743839675936,52.19300189085732],"type":"Point"}
}