{
  "type": "Feature",
  "properties": {
    "iso:country":"GB",
    "wof:name":"BB10 1TA",
    "wof:placetype":"postalcode"
},
  "geometry": {"coordinates":[-2.23218755284374,53.80417777696736],"type":"Point"}
}