{
  "type": "Feature",
  "properties": {
    "iso:country": "GB",
    "wof:name": "N4 1RG",
    "wof:placetype": "postalcode"
  },
  "geometry": {"coordinates":[-0.104419,51.577606],"type":"Point"}
}
