{
  "type": "Feature",
  "properties": {
    "date:inception_lower":"1980-01-01",
    "date:inception_upper":"1980-01-31",
    "iso:country":"GB",
    "wof:name":"N4 1RG",
    "wof:placetype":"postalcode"
},
  "geometry": {"coordinates":[-0.104419,51.577606],"type":"Point"}
}