{
  "type": "Feature",
  "properties": {
    "iso:country":"GB",
    "wof:name":"PO9 2AA",
    "wof:placetype":"postalcode"
},
  "geometry": {"coordinates":[-0.98218170951853,50.85498788791229],"type":"Point"}
}