{
  "type": "Feature",
  "properties": {
    "iso:country":"GB",
    "wof:name":"S5 6TA",
    "wof:placetype":"postalcode"
},
  "geometry": {"coordinates":[-1.45688548261873,53.41675604224779],"type":"Point"}
}