{
  "type": "Feature",
  "properties": {
    "date:inception_lower": "1981-06-01",
    "date:inception_upper": "1981-06-01",
    "iso:country": "GB",
    "wof:name": "PO22 9LR",
    "wof:placetype": "postalcode"
  },
  "geometry": {"coordinates":[-0.683174,50.801646],"type":"Point"}
}
