{
  "type": "Feature",
  "properties": {
    "iso:country":"GB",
    "wof:name":"M12 6BF",
    "wof:placetype":"postalcode"
},
  "geometry": {"coordinates":[-2.20904282080441,53.47334629057913],"type":"Point"}
}