{
  "type": "Feature",
  "properties": {
    "iso:country": "GB",
    "wof:name": "SO45 4HP",
    "wof:placetype": "postalcode"
  },
  "geometry": {"coordinates":[-1.407078,50.850599],"type":"Point"}
}
