{
  "type": "Feature",
  "properties": {
    "iso:country":"GB",
    "wof:name":"SO45 4HP",
    "wof:placetype":"postalcode"
},
  "geometry": {"coordinates":[-1.40707811822195,50.85059907598003],"type":"Point"}
}