{
  "type": "Feature",
  "properties": {
    "date:inception_lower": "1980-01-01",
    "date:inception_upper": "1980-01-01",
    "iso:country": "GB",
    "wof:name": "NN17 2TD",
    "wof:placetype": "postalcode"
  },
  "geometry": {"coordinates":[-0.719936,52.491136],"type":"Point"}
}
