{
  "type": "Feature",
  "properties": {
    "iso:country":"GB",
    "wof:name":"NN17 2TD",
    "wof:placetype":"postalcode"
},
  "geometry": {"coordinates":[-0.71945274504733,52.49097969093874],"type":"Point"}
}