{
  "type": "Feature",
  "properties": {
    "iso:country":"GB",
    "wof:name":"EX12 2PE",
    "wof:placetype":"postalcode"
},
  "geometry": {"coordinates":[-3.07392802100812,50.70560292154023],"type":"Point"}
}