{
  "type": "Feature",
  "properties": {
    "iso:country": "GB",
    "wof:name": "NP18 3EW",
    "wof:placetype": "postalcode"
  },
  "geometry": {"coordinates":[-2.967317,51.620159],"type":"Point"}
}
