{
  "type": "Feature",
  "properties": {
    "iso:country":"GB",
    "wof:name":"NP18 3EW",
    "wof:placetype":"postalcode"
},
  "geometry": {"coordinates":[-2.96731739109193,51.62015883437778],"type":"Point"}
}