{
  "type": "Feature",
  "properties": {
    "date:inception_lower": "2022-02-01",
    "date:inception_upper": "2022-02-01",
    "iso:country": "GB",
    "wof:name": "BA11 2FR",
    "wof:placetype": "postalcode"
  },
  "geometry": {"coordinates":[-2.311302,51.2344],"type":"Point"}
}
