{
  "type": "Feature",
  "properties": {
    "iso:country":"GB",
    "wof:name":"LS5 3NS",
    "wof:placetype":"postalcode"
},
  "geometry": {"coordinates":[-1.61193095007926,53.82433161818296],"type":"Point"}
}