{
  "type": "Feature",
  "properties": {
    "iso:country":"GB",
    "wof:name":"SG12 8EN",
    "wof:placetype":"postalcode"
},
  "geometry": {"coordinates":[-0.0052025724182,51.78017051006151],"type":"Point"}
}