{
  "type": "Feature",
  "properties": {
    "iso:country": "GB",
    "wof:name": "EH53 0ET",
    "wof:placetype": "postalcode"
  },
  "geometry": {"coordinates":[-3.450195,55.898106],"type":"Point"}
}
