{
  "type": "Feature",
  "properties": {
    "iso:country":"GB",
    "wof:name":"EH6 6AX",
    "wof:placetype":"postalcode"
},
  "geometry": {"coordinates":[-3.16847242681592,55.97389373709671],"type":"Point"}
}