{
  "type": "Feature",
  "properties": {
    "iso:country":"GB",
    "wof:name":"ME13 7NR",
    "wof:placetype":"postalcode"
},
  "geometry": {"coordinates":[0.87085769693622,51.31546485563457],"type":"Point"}
}