{
  "type": "Feature",
  "properties": {
    "date:inception_lower":"2003-07-01",
    "date:inception_upper":"2003-07-31",
    "iso:country":"GB",
    "wof:name":"ME13 7NR",
    "wof:placetype":"postalcode"
},
  "geometry": {"coordinates":[0.870858,51.315465],"type":"Point"}
}