{
  "type": "Feature",
  "properties": {
    "iso:country": "GB",
    "wof:name": "RG6 6HE",
    "wof:placetype": "postalcode"
  },
  "geometry": {"coordinates":[-0.949273,51.445267],"type":"Point"}
}
