{
  "type": "Feature",
  "properties": {
    "date:inception_lower":"2010-09-01",
    "date:inception_upper":"2010-09-30",
    "iso:country":"GB",
    "wof:name":"RG6 6HE",
    "wof:placetype":"postalcode"
},
  "geometry": {"coordinates":[-0.949273,51.445267],"type":"Point"}
}