{
  "type": "Feature",
  "properties": {
    "iso:country":"GB",
    "wof:name":"RG6 6HE",
    "wof:placetype":"postalcode"
},
  "geometry": {"coordinates":[-0.94927313833198,51.44526726814782],"type":"Point"}
}