{
  "type": "Feature",
  "properties": {
    "iso:country": "GB",
    "wof:name": "DN6 9BD",
    "wof:placetype": "postalcode"
  },
  "geometry": {"coordinates":[-1.199106,53.666906],"type":"Point"}
}
