{
  "type": "Feature",
  "properties": {
    "iso:country":"GB",
    "wof:name":"DN6 9BD",
    "wof:placetype":"postalcode"
},
  "geometry": {"coordinates":[-1.199106078005,53.66690604974217],"type":"Point"}
}