{
  "type": "Feature",
  "properties": {
    "iso:country":"GB",
    "wof:name":"DY8 3JE",
    "wof:placetype":"postalcode"
},
  "geometry": {"coordinates":[-2.17023985488446,52.44173978607283],"type":"Point"}
}