{
  "type": "Feature",
  "properties": {
    "date:inception_lower": "1980-01-01",
    "date:inception_upper": "1980-01-01",
    "iso:country": "GB",
    "wof:name": "DY8 3JE",
    "wof:placetype": "postalcode"
  },
  "geometry": {"coordinates":[-2.17024,52.44174],"type":"Point"}
}
