{
  "type": "Feature",
  "properties": {
    "iso:country": "GB",
    "wof:name": "BS48 3AH",
    "wof:placetype": "postalcode"
  },
  "geometry": {"coordinates":[-2.768554,51.39976],"type":"Point"}
}
