{
  "type": "Feature",
  "properties": {
    "date:inception_lower":"2002-06-01",
    "date:inception_upper":"2002-06-30",
    "iso:country":"GB",
    "wof:name":"BS48 3AH",
    "wof:placetype":"postalcode"
},
  "geometry": {"coordinates":[-2.768554,51.39976],"type":"Point"}
}