{
  "type": "Feature",
  "properties": {
    "iso:country": "GB",
    "wof:name": "NG34 7JE",
    "wof:placetype": "postalcode"
  },
  "geometry": {"coordinates":[-0.397385,53.000269],"type":"Point"}
}
