{
  "type": "Feature",
  "properties": {
    "iso:country": "GB",
    "wof:name": "DE22 2DH",
    "wof:placetype": "postalcode"
  },
  "geometry": {"coordinates":[-1.478756,52.952959],"type":"Point"}
}
