{
  "type": "Feature",
  "properties": {
    "date:inception_lower": "1992-08-01",
    "date:inception_upper": "1992-08-01",
    "iso:country": "GB",
    "wof:name": "DE22 2DH",
    "wof:placetype": "postalcode"
  },
  "geometry": {"coordinates":[-1.478756,52.952959],"type":"Point"}
}
