{
  "type": "Feature",
  "properties": {
    "date:inception_lower":"1980-01-01",
    "date:inception_upper":"1980-01-31",
    "iso:country":"GB",
    "wof:name":"W13 8HG",
    "wof:placetype":"postalcode"
},
  "geometry": {"coordinates":[-0.317453,51.518573],"type":"Point"}
}