{
  "type": "Feature",
  "properties": {
    "iso:country":"GB",
    "wof:name":"W13 8HG",
    "wof:placetype":"postalcode"
},
  "geometry": {"coordinates":[-0.31745325804141,51.51857303735424],"type":"Point"}
}