{
  "type": "Feature",
  "properties": {
    "iso:country": "GB",
    "wof:name": "W13 8HG",
    "wof:placetype": "postalcode"
  },
  "geometry": {"coordinates":[-0.317453,51.518573],"type":"Point"}
}
