{
  "type": "Feature",
  "properties": {
    "date:inception_lower": "1980-01-01",
    "date:inception_upper": "1980-01-01",
    "iso:country": "GB",
    "wof:name": "BB3 0JT",
    "wof:placetype": "postalcode"
  },
  "geometry": {"coordinates":[-2.48583,53.710193],"type":"Point"}
}
