{
  "type": "Feature",
  "properties": {
    "iso:country":"GB",
    "wof:name":"M18 8TA",
    "wof:placetype":"postalcode"
},
  "geometry": {"coordinates":[-2.15790399550238,53.46771724128576],"type":"Point"}
}