{
  "type": "Feature",
  "properties": {
    "iso:country":"GB",
    "wof:name":"EN8 0RU",
    "wof:placetype":"postalcode"
},
  "geometry": {"coordinates":[-0.0306752598158,51.71019916315788],"type":"Point"}
}