{
  "type": "Feature",
  "properties": {
    "iso:country":"GB",
    "wof:name":"RG6 7DT",
    "wof:placetype":"postalcode"
},
  "geometry": {"coordinates":[-0.92994619133134,51.44226904291892],"type":"Point"}
}