{
  "type": "Feature",
  "properties": {
    "iso:country": "GB",
    "wof:name": "NG2 7JX",
    "wof:placetype": "postalcode"
  },
  "geometry": {"coordinates":[-1.137163,52.930915],"type":"Point"}
}
