{
  "type": "Feature",
  "properties": {
    "iso:country":"GB",
    "wof:name":"BD17 7LU",
    "wof:placetype":"postalcode"
},
  "geometry": {"coordinates":[-1.78917787472653,53.84065529843069],"type":"Point"}
}