{
  "type": "Feature",
  "properties": {
    "iso:country":"GB",
    "wof:name":"WS5 4LJ",
    "wof:placetype":"postalcode"
},
  "geometry": {"coordinates":[-1.96169203559275,52.56095510130908],"type":"Point"}
}