{
  "type": "Feature",
  "properties": {
    "iso:country": "GB",
    "wof:name": "NG32 3NE",
    "wof:placetype": "postalcode"
  },
  "geometry": {"coordinates":[-0.497818,52.937742],"type":"Point"}
}
