{
  "type": "Feature",
  "properties": {
    "iso:country": "GB",
    "wof:name": "SL2 4LL",
    "wof:placetype": "postalcode"
  },
  "geometry": {"coordinates":[-0.589766,51.547376],"type":"Point"}
}
