{
  "type": "Feature",
  "properties": {
    "iso:country":"GB",
    "wof:name":"SL2 4LL",
    "wof:placetype":"postalcode"
},
  "geometry": {"coordinates":[-0.58976563936361,51.54737627847335],"type":"Point"}
}