{
  "type": "Feature",
  "properties": {
    "date:inception_lower": "1980-01-01",
    "date:inception_upper": "1980-01-01",
    "iso:country": "GB",
    "wof:name": "ST5 3LE",
    "wof:placetype": "postalcode"
  },
  "geometry": {"coordinates":[-2.2418,52.988148],"type":"Point"}
}
