{
  "type": "Feature",
  "properties": {
    "iso:country": "GB",
    "wof:name": "ST5 3LE",
    "wof:placetype": "postalcode"
  },
  "geometry": {"coordinates":[-2.2418,52.988148],"type":"Point"}
}
