{
  "type": "Feature",
  "properties": {
    "iso:country":"GB",
    "wof:name":"ST5 3LE",
    "wof:placetype":"postalcode"
},
  "geometry": {"coordinates":[-2.24180053072707,52.98814793570661],"type":"Point"}
}