{
  "type": "Feature",
  "properties": {
    "iso:country": "GB",
    "wof:name": "CM24 8UF",
    "wof:placetype": "postalcode"
  },
  "geometry": {"coordinates":[0.220041,51.893089],"type":"Point"}
}
