{
  "type": "Feature",
  "properties": {
    "iso:country":"GB",
    "wof:name":"CM24 8UF",
    "wof:placetype":"postalcode"
},
  "geometry": {"coordinates":[0.22004054582306,51.89308880822883],"type":"Point"}
}