{
  "type": "Feature",
  "properties": {
    "date:inception_lower":"1980-01-01",
    "date:inception_upper":"1980-01-31",
    "iso:country":"GB",
    "wof:name":"BL9 0HE",
    "wof:placetype":"postalcode"
},
  "geometry": {"coordinates":[-2.302959,53.593203],"type":"Point"}
}