{
  "type": "Feature",
  "properties": {
    "iso:country":"GB",
    "wof:name":"BL9 0HE",
    "wof:placetype":"postalcode"
},
  "geometry": {"coordinates":[-2.30295875724399,53.59320285636093],"type":"Point"}
}