{
  "type": "Feature",
  "properties": {
    "iso:country": "GB",
    "wof:name": "NG11 6JY",
    "wof:placetype": "postalcode"
  },
  "geometry": {"coordinates":[-1.139422,52.883745],"type":"Point"}
}
