{
  "type": "Feature",
  "properties": {
    "iso:country":"GB",
    "wof:name":"NG11 6JY",
    "wof:placetype":"postalcode"
},
  "geometry": {"coordinates":[-1.13942247537924,52.88374501284535],"type":"Point"}
}