{
  "type": "Feature",
  "properties": {
    "iso:country":"GB",
    "wof:name":"GL15 6PG",
    "wof:placetype":"postalcode"
},
  "geometry": {"coordinates":[-2.59311422654554,51.70283096250702],"type":"Point"}
}