{
  "type": "Feature",
  "properties": {
    "iso:country": "GB",
    "wof:name": "OL14 6DE",
    "wof:placetype": "postalcode"
  },
  "geometry": {"coordinates":[-2.060743,53.718992],"type":"Point"}
}
