{
  "type": "Feature",
  "properties": {
    "date:inception_lower": "1987-04-01",
    "date:inception_upper": "1987-04-01",
    "iso:country": "GB",
    "wof:name": "CT20 1TZ",
    "wof:placetype": "postalcode"
  },
  "geometry": {"coordinates":[1.182552,51.08334],"type":"Point"}
}
