{
  "type": "Feature",
  "properties": {
    "iso:country":"GB",
    "wof:name":"BD6 1AF",
    "wof:placetype":"postalcode"
},
  "geometry": {"coordinates":[-1.76399012116078,53.76591842500544],"type":"Point"}
}