{
  "type": "Feature",
  "properties": {
    "iso:country": "GB",
    "wof:name": "ST15 8RY",
    "wof:placetype": "postalcode"
  },
  "geometry": {"coordinates":[-2.071209,52.889707],"type":"Point"}
}
