{
  "type": "Feature",
  "properties": {
    "date:inception_lower": "1980-01-01",
    "date:inception_upper": "1980-01-01",
    "iso:country": "GB",
    "wof:name": "ST15 8RY",
    "wof:placetype": "postalcode"
  },
  "geometry": {"coordinates":[-2.071209,52.889707],"type":"Point"}
}
