{
  "type": "Feature",
  "properties": {
    "date:inception_lower": "1991-01-01",
    "date:inception_upper": "1991-01-01",
    "iso:country": "GB",
    "wof:name": "WA16 0LS",
    "wof:placetype": "postalcode"
  },
  "geometry": {"coordinates":[-2.470262,53.288731],"type":"Point"}
}
