{
  "type": "Feature",
  "properties": {
    "iso:country": "GB",
    "wof:name": "CF3 5JZ",
    "wof:placetype": "postalcode"
  },
  "geometry": {"coordinates":[-3.13035,51.525143],"type":"Point"}
}
