{
  "type": "Feature",
  "properties": {
    "iso:country":"GB",
    "wof:name":"WS11 7EY",
    "wof:placetype":"postalcode"
},
  "geometry": {"coordinates":[-2.00688263336088,52.69902524858533],"type":"Point"}
}