{
  "type": "Feature",
  "properties": {
    "iso:country":"GB",
    "wof:name":"S18 2FA",
    "wof:placetype":"postalcode"
},
  "geometry": {"coordinates":[-1.4601952592708,53.30734225724719],"type":"Point"}
}