{
  "type": "Feature",
  "properties": {
    "iso:country":"GB",
    "wof:name":"NP11 7HD",
    "wof:placetype":"postalcode"
},
  "geometry": {"coordinates":[-3.18041510623104,51.61715713151079],"type":"Point"}
}