{
  "type": "Feature",
  "properties": {
    "iso:country": "GB",
    "wof:name": "NP11 7HD",
    "wof:placetype": "postalcode"
  },
  "geometry": {"coordinates":[-3.180415,51.617157],"type":"Point"}
}
