{
  "type": "Feature",
  "properties": {
    "iso:country":"GB",
    "wof:name":"NP25 5RF",
    "wof:placetype":"postalcode"
},
  "geometry": {"coordinates":[-2.71708672047243,51.84190779350521],"type":"Point"}
}