{
  "type": "Feature",
  "properties": {
    "date:inception_lower": "1999-06-01",
    "date:inception_upper": "1999-06-01",
    "iso:country": "GB",
    "wof:name": "NP25 5RF",
    "wof:placetype": "postalcode"
  },
  "geometry": {"coordinates":[-2.717132,51.841859],"type":"Point"}
}
