{
  "type": "Feature",
  "properties": {
    "iso:country": "GB",
    "wof:name": "RG7 6NP",
    "wof:placetype": "postalcode"
  },
  "geometry": {"coordinates":[-1.162814,51.430136],"type":"Point"}
}
