{
  "type": "Feature",
  "properties": {
    "date:inception_lower": "1980-01-01",
    "date:inception_upper": "1980-01-01",
    "iso:country": "GB",
    "wof:name": "LN1 1LR",
    "wof:placetype": "postalcode"
  },
  "geometry": {"coordinates":[-0.549631,53.236708],"type":"Point"}
}
