{
  "type": "Feature",
  "properties": {
    "iso:country":"GB",
    "wof:name":"LN1 1LR",
    "wof:placetype":"postalcode"
},
  "geometry": {"coordinates":[-0.54977284827994,53.23690345126091],"type":"Point"}
}