{
  "type": "Feature",
  "properties": {
    "iso:country": "GB",
    "wof:name": "WV5 9BE",
    "wof:placetype": "postalcode"
  },
  "geometry": {"coordinates":[-2.190487,52.544896],"type":"Point"}
}
