{
  "type": "Feature",
  "properties": {
    "date:inception_lower":"1980-01-01",
    "date:inception_upper":"1980-01-31",
    "iso:country":"GB",
    "wof:name":"WV5 9BE",
    "wof:placetype":"postalcode"
},
  "geometry": {"coordinates":[-2.190487,52.544896],"type":"Point"}
}