{
  "type": "Feature",
  "properties": {
    "iso:country":"GB",
    "wof:name":"WV5 9BE",
    "wof:placetype":"postalcode"
},
  "geometry": {"coordinates":[-2.19048716545489,52.54489551427588],"type":"Point"}
}