{
  "type": "Feature",
  "properties": {
    "iso:country":"GB",
    "wof:name":"L9 7HJ",
    "wof:placetype":"postalcode"
},
  "geometry": {"coordinates":[-2.94799660263646,53.45984362754898],"type":"Point"}
}