{
  "type": "Feature",
  "properties": {
    "date:inception_lower": "1983-07-01",
    "date:inception_upper": "1983-07-01",
    "iso:country": "GB",
    "wof:name": "L9 7HJ",
    "wof:placetype": "postalcode"
  },
  "geometry": {"coordinates":[-2.94778,53.459655],"type":"Point"}
}
