{
  "type": "Feature",
  "properties": {
    "iso:country": "GB",
    "wof:name": "L9 7HJ",
    "wof:placetype": "postalcode"
  },
  "geometry": {"coordinates":[-2.947997,53.459844],"type":"Point"}
}
