{
  "type": "Feature",
  "properties": {
    "iso:country": "GB",
    "wof:name": "WN7 4BQ",
    "wof:placetype": "postalcode"
  },
  "geometry": {"coordinates":[-2.553823,53.491963],"type":"Point"}
}
