{
  "type": "Feature",
  "properties": {
    "iso:country":"GB",
    "wof:name":"WN7 4BQ",
    "wof:placetype":"postalcode"
},
  "geometry": {"coordinates":[-2.55381488960172,53.49237947803407],"type":"Point"}
}