{
  "type": "Feature",
  "properties": {
    "date:inception_lower": "1986-07-01",
    "date:inception_upper": "1986-07-01",
    "iso:country": "GB",
    "wof:name": "PO33 4BL",
    "wof:placetype": "postalcode"
  },
  "geometry": {"coordinates":[-1.201824,50.697219],"type":"Point"}
}
