{
  "type": "Feature",
  "properties": {
    "date:inception_lower": "2022-11-01",
    "date:inception_upper": "2022-11-01",
    "iso:country": "GB",
    "wof:name": "CF48 1DP",
    "wof:placetype": "postalcode"
  },
  "geometry": {"coordinates":[-3.393107,51.746937],"type":"Point"}
}
