{
  "type": "Feature",
  "properties": {
    "iso:country":"GB",
    "wof:name":"SA3 4HN",
    "wof:placetype":"postalcode"
},
  "geometry": {"coordinates":[-3.99598609799937,51.56986187678292],"type":"Point"}
}