{
  "type": "Feature",
  "properties": {
    "iso:country":"GB",
    "wof:name":"SN1 4JE",
    "wof:placetype":"postalcode"
},
  "geometry": {"coordinates":[-1.78704759248853,51.54847071944828],"type":"Point"}
}