{
  "type": "Feature",
  "properties": {
    "iso:country":"GB",
    "wof:name":"EX1 2DS",
    "wof:placetype":"postalcode"
},
  "geometry": {"coordinates":[-3.51273931374988,50.72627414729463],"type":"Point"}
}