{
  "type": "Feature",
  "properties": {
    "date:inception_lower":"1980-01-01",
    "date:inception_upper":"1980-01-31",
    "iso:country":"GB",
    "wof:name":"EX1 2DS",
    "wof:placetype":"postalcode"
},
  "geometry": {"coordinates":[-3.512739,50.726274],"type":"Point"}
}