{
  "type": "Feature",
  "properties": {
    "iso:country":"GB",
    "wof:name":"LA14 3RU",
    "wof:placetype":"postalcode"
},
  "geometry": {"coordinates":[-3.2518004472066,54.11973184320685],"type":"Point"}
}