{
  "type": "Feature",
  "properties": {
    "date:inception_lower": "2005-03-01",
    "date:inception_upper": "2005-03-01",
    "iso:country": "GB",
    "wof:name": "CR0 1JX",
    "wof:placetype": "postalcode"
  },
  "geometry": {"coordinates":[-0.097023,51.36919],"type":"Point"}
}
