{
  "type": "Feature",
  "properties": {
    "iso:country":"GB",
    "wof:name":"PA3 1LR",
    "wof:placetype":"postalcode"
},
  "geometry": {"coordinates":[-4.44744260621783,55.84574331258623],"type":"Point"}
}