{
  "type": "Feature",
  "properties": {
    "iso:country": "GB",
    "wof:name": "AL3 4JT",
    "wof:placetype": "postalcode"
  },
  "geometry": {"coordinates":[-0.360282,51.744396],"type":"Point"}
}
