{
  "type": "Feature",
  "properties": {
    "iso:country":"GB",
    "wof:name":"KA1 5JX",
    "wof:placetype":"postalcode"
},
  "geometry": {"coordinates":[-4.41913045967511,55.56475337211777],"type":"Point"}
}