{
  "type": "Feature",
  "properties": {
    "iso:country": "GB",
    "wof:name": "KA1 5JX",
    "wof:placetype": "postalcode"
  },
  "geometry": {"coordinates":[-4.412894,55.563402],"type":"Point"}
}
