{
  "type": "Feature",
  "properties": {
    "iso:country":"GB",
    "wof:name":"EX5 4AU",
    "wof:placetype":"postalcode"
},
  "geometry": {"coordinates":[-3.50553593846104,50.77336609186315],"type":"Point"}
}