{
  "type": "Feature",
  "properties": {
    "iso:country": "GB",
    "wof:name": "EX5 4AU",
    "wof:placetype": "postalcode"
  },
  "geometry": {"coordinates":[-3.505536,50.773366],"type":"Point"}
}
