{
  "type": "Feature",
  "properties": {
    "iso:country":"GB",
    "wof:name":"BD16 1PH",
    "wof:placetype":"postalcode"
},
  "geometry": {"coordinates":[-1.82299867459187,53.83178488541438],"type":"Point"}
}