{
  "type": "Feature",
  "properties": {
    "iso:country": "GB",
    "wof:name": "CW7 3SN",
    "wof:placetype": "postalcode"
  },
  "geometry": {"coordinates":[-2.512913,53.201372],"type":"Point"}
}
