{
  "type": "Feature",
  "properties": {
    "iso:country":"GB",
    "wof:name":"WR13 5DW",
    "wof:placetype":"postalcode"
},
  "geometry": {"coordinates":[-2.3386153707991,52.16560973278428],"type":"Point"}
}