{
  "type": "Feature",
  "properties": {
    "iso:country":"GB",
    "wof:name":"NN2 8NP",
    "wof:placetype":"postalcode"
},
  "geometry": {"coordinates":[-0.89160141379992,52.27265600836918],"type":"Point"}
}