{
  "type": "Feature",
  "properties": {
    "date:inception_lower":"2014-06-01",
    "date:inception_upper":"2014-06-30",
    "iso:country":"GB",
    "wof:name":"RG40 1GJ",
    "wof:placetype":"postalcode"
},
  "geometry": {"coordinates":[-0.810579,51.409423],"type":"Point"}
}