{
  "type": "Feature",
  "properties": {
    "iso:country":"GB",
    "wof:name":"RG40 1GJ",
    "wof:placetype":"postalcode"
},
  "geometry": {"coordinates":[-0.81123449350762,51.40977948473265],"type":"Point"}
}