{
  "type": "Feature",
  "properties": {
    "date:inception_lower":"1984-10-01",
    "date:inception_upper":"1984-10-31",
    "iso:country":"GB",
    "wof:name":"IG11 8HE",
    "wof:placetype":"postalcode"
},
  "geometry": {"coordinates":[0.078199,51.539028],"type":"Point"}
}