{
  "type": "Feature",
  "properties": {
    "date:inception_lower":"1991-03-01",
    "date:inception_upper":"1991-03-31",
    "iso:country":"GB",
    "wof:name":"G33 4DR",
    "wof:placetype":"postalcode"
},
  "geometry": {"coordinates":[-4.151038,55.863125],"type":"Point"}
}