{
  "type": "Feature",
  "properties": {
    "iso:country":"GB",
    "wof:name":"G33 4DR",
    "wof:placetype":"postalcode"
},
  "geometry": {"coordinates":[-4.15294523008216,55.86356371186481],"type":"Point"}
}