{
  "type": "Feature",
  "properties": {
    "date:inception_lower":"2018-12-01",
    "date:inception_upper":"2018-12-31",
    "iso:country":"GB",
    "wof:name":"B2 2ES",
    "wof:placetype":"postalcode"
},
  "geometry": {"coordinates":[-1.894209,52.495968],"type":"Point"}
}