{
  "type": "Feature",
  "properties": {
    "iso:country":"GB",
    "wof:name":"KA2 0JZ",
    "wof:placetype":"postalcode"
},
  "geometry": {"coordinates":[-4.54539508482701,55.60780231933916],"type":"Point"}
}