{
  "type": "Feature",
  "properties": {
    "iso:country":"GB",
    "wof:name":"SP2 9JA",
    "wof:placetype":"postalcode"
},
  "geometry": {"coordinates":[-1.82996228962947,51.08684106054109],"type":"Point"}
}