{
  "type": "Feature",
  "properties": {
    "iso:country":"GB",
    "wof:name":"EN9 1BZ",
    "wof:placetype":"postalcode"
},
  "geometry": {"coordinates":[-0.00528213041396,51.68726271275656],"type":"Point"}
}