{
  "type": "Feature",
  "properties": {
    "date:inception_lower": "1981-09-01",
    "date:inception_upper": "1981-09-01",
    "iso:country": "GB",
    "wof:name": "L33 1EN",
    "wof:placetype": "postalcode"
  },
  "geometry": {"coordinates":[-2.895852,53.500525],"type":"Point"}
}
