{
  "type": "Feature",
  "properties": {
    "iso:country": "GB",
    "wof:name": "L33 1EN",
    "wof:placetype": "postalcode"
  },
  "geometry": {"coordinates":[-2.895852,53.500525],"type":"Point"}
}
