{
  "type": "Feature",
  "properties": {
    "date:inception_lower": "1980-01-01",
    "date:inception_upper": "1980-01-01",
    "iso:country": "GB",
    "wof:name": "SL6 8DT",
    "wof:placetype": "postalcode"
  },
  "geometry": {"coordinates":[-0.704831,51.526189],"type":"Point"}
}
