{
  "type": "Feature",
  "properties": {
    "iso:country":"GB",
    "wof:name":"SL6 8DT",
    "wof:placetype":"postalcode"
},
  "geometry": {"coordinates":[-0.70476545686044,51.5260872606824],"type":"Point"}
}