{
  "type": "Feature",
  "properties": {
    "iso:country": "GB",
    "wof:name": "BR6 9PN",
    "wof:placetype": "postalcode"
  },
  "geometry": {"coordinates":[0.087864,51.370339],"type":"Point"}
}
