{
  "type": "Feature",
  "properties": {
    "iso:country":"GB",
    "wof:name":"DN18 5AN",
    "wof:placetype":"postalcode"
},
  "geometry": {"coordinates":[-0.44843116087209,53.68735481069426],"type":"Point"}
}