{
  "type": "Feature",
  "properties": {
    "iso:country":"GB",
    "wof:name":"S25 4GA",
    "wof:placetype":"postalcode"
},
  "geometry": {"coordinates":[-1.21491135878272,53.36062420996407],"type":"Point"}
}