{
  "type": "Feature",
  "properties": {
    "date:inception_lower": "1980-01-01",
    "date:inception_upper": "1980-01-01",
    "iso:country": "GB",
    "wof:name": "CT8 8EE",
    "wof:placetype": "postalcode"
  },
  "geometry": {"coordinates":[1.336138,51.376965],"type":"Point"}
}
