{
  "type": "Feature",
  "properties": {
    "iso:country":"GB",
    "wof:name":"NW8 0AS",
    "wof:placetype":"postalcode"
},
  "geometry": {"coordinates":[-0.18023011115865,51.5350038909407],"type":"Point"}
}