{
  "type": "Feature",
  "properties": {
    "iso:country": "GB",
    "wof:name": "G76 8RH",
    "wof:placetype": "postalcode"
  },
  "geometry": {"coordinates":[-4.280339,55.773612],"type":"Point"}
}
