{
  "type": "Feature",
  "properties": {
    "date:inception_lower":"2014-04-01",
    "date:inception_upper":"2014-04-30",
    "iso:country":"GB",
    "wof:name":"NR34 8BF",
    "wof:placetype":"postalcode"
},
  "geometry": {"coordinates":[1.625973,52.359415],"type":"Point"}
}