{
  "type": "Feature",
  "properties": {
    "iso:country": "GB",
    "wof:name": "NR34 8BF",
    "wof:placetype": "postalcode"
  },
  "geometry": {"coordinates":[1.625973,52.359415],"type":"Point"}
}
