{
  "type": "Feature",
  "properties": {
    "date:inception_lower": "2018-05-01",
    "date:inception_upper": "2018-05-01",
    "iso:country": "GB",
    "wof:name": "LS14 6XR",
    "wof:placetype": "postalcode"
  },
  "geometry": {"coordinates":[-1.475298,53.81866],"type":"Point"}
}
