{
  "type": "Feature",
  "properties": {
    "iso:country":"GB",
    "wof:name":"OL2 6SF",
    "wof:placetype":"postalcode"
},
  "geometry": {"coordinates":[-2.13151984816538,53.57703894341176],"type":"Point"}
}