{
  "type": "Feature",
  "properties": {
    "iso:country":"GB",
    "wof:name":"BA4 4JQ",
    "wof:placetype":"postalcode"
},
  "geometry": {"coordinates":[-2.55581689527362,51.21073993584736],"type":"Point"}
}