{
  "type": "Feature",
  "properties": {
    "iso:country": "GB",
    "wof:name": "BA4 4JQ",
    "wof:placetype": "postalcode"
  },
  "geometry": {"coordinates":[-2.555817,51.21074],"type":"Point"}
}
