{
  "type": "Feature",
  "properties": {
    "iso:country": "GB",
    "wof:name": "LE5 6LP",
    "wof:placetype": "postalcode"
  },
  "geometry": {"coordinates":[-1.063173,52.625294],"type":"Point"}
}
