{
  "type": "Feature",
  "properties": {
    "iso:country":"GB",
    "wof:name":"LE5 6LP",
    "wof:placetype":"postalcode"
},
  "geometry": {"coordinates":[-1.06317255530546,52.62529412062399],"type":"Point"}
}