{
  "type": "Feature",
  "properties": {
    "iso:country": "GB",
    "wof:name": "E1 1FH",
    "wof:placetype": "postalcode"
  },
  "geometry": {"coordinates":[-0.066355,51.514451],"type":"Point"}
}
