{
  "type": "Feature",
  "properties": {
    "iso:country": "GB",
    "wof:name": "NN5 6NW",
    "wof:placetype": "postalcode"
  },
  "geometry": {"coordinates":[-0.952533,52.260544],"type":"Point"}
}
