{
  "type": "Feature",
  "properties": {
    "date:inception_lower": "1980-01-01",
    "date:inception_upper": "1980-01-01",
    "iso:country": "GB",
    "wof:name": "SL6 3ND",
    "wof:placetype": "postalcode"
  },
  "geometry": {"coordinates":[-0.759569,51.500198],"type":"Point"}
}
