{
  "type": "Feature",
  "properties": {
    "iso:country":"GB",
    "wof:name":"CM14 4NJ",
    "wof:placetype":"postalcode"
},
  "geometry": {"coordinates":[0.2842158885303,51.6147400447943],"type":"Point"}
}