{
  "type": "Feature",
  "properties": {
    "iso:country": "GB",
    "wof:name": "RG22 4BJ",
    "wof:placetype": "postalcode"
  },
  "geometry": {"coordinates":[-1.096906,51.247901],"type":"Point"}
}
