{
  "type": "Feature",
  "properties": {
    "iso:country":"GB",
    "wof:name":"RG22 4BJ",
    "wof:placetype":"postalcode"
},
  "geometry": {"coordinates":[-1.09698122363173,51.24791961672705],"type":"Point"}
}