{
  "type": "Feature",
  "properties": {
    "iso:country":"GB",
    "wof:name":"CW8 2PL",
    "wof:placetype":"postalcode"
},
  "geometry": {"coordinates":[-2.60193232026451,53.23379193228872],"type":"Point"}
}