{
  "type": "Feature",
  "properties": {
    "iso:country":"GB",
    "wof:name":"BR1 1AB",
    "wof:placetype":"postalcode"
},
  "geometry": {"coordinates":[0.01520826366516,51.40633333672923],"type":"Point"}
}