{
  "type": "Feature",
  "properties": {
    "date:inception_lower":"2012-03-01",
    "date:inception_upper":"2012-03-31",
    "iso:country":"GB",
    "wof:name":"BR1 1AB",
    "wof:placetype":"postalcode"
},
  "geometry": {"coordinates":[0.015208,51.406333],"type":"Point"}
}