{
  "type": "Feature",
  "properties": {
    "date:inception_lower":"2000-06-01",
    "date:inception_upper":"2000-06-30",
    "iso:country":"GB",
    "wof:name":"NE37 3HF",
    "wof:placetype":"postalcode"
},
  "geometry": {"coordinates":[-1.512084,54.922778],"type":"Point"}
}