{
  "type": "Feature",
  "properties": {
    "iso:country":"GB",
    "wof:name":"NE37 3HF",
    "wof:placetype":"postalcode"
},
  "geometry": {"coordinates":[-1.51208426887075,54.92277770588952],"type":"Point"}
}