{
  "type": "Feature",
  "properties": {
    "iso:country": "GB",
    "wof:name": "NE37 3HF",
    "wof:placetype": "postalcode"
  },
  "geometry": {"coordinates":[-1.512084,54.922778],"type":"Point"}
}
