{
  "type": "Feature",
  "properties": {
    "iso:country":"GB",
    "wof:name":"TR13 8NS",
    "wof:placetype":"postalcode"
},
  "geometry": {"coordinates":[-5.27265695262548,50.10639271511181],"type":"Point"}
}