{
  "type": "Feature",
  "properties": {
    "date:inception_lower": "1996-12-01",
    "date:inception_upper": "1996-12-01",
    "iso:country": "GB",
    "wof:name": "HD8 0WX",
    "wof:placetype": "postalcode"
  },
  "geometry": {"coordinates":[-1.726425,53.61215],"type":"Point"}
}
