{
  "type": "Feature",
  "properties": {
    "date:inception_lower":"1999-06-01",
    "date:inception_upper":"1999-06-30",
    "iso:country":"GB",
    "wof:name":"S41 9AJ",
    "wof:placetype":"postalcode"
},
  "geometry": {"coordinates":[-1.429538,53.262076],"type":"Point"}
}