{
  "type": "Feature",
  "properties": {
    "iso:country":"GB",
    "wof:name":"S41 9AJ",
    "wof:placetype":"postalcode"
},
  "geometry": {"coordinates":[-1.42953782698078,53.26207559206063],"type":"Point"}
}