{
  "type": "Feature",
  "properties": {
    "iso:country": "GB",
    "wof:name": "WA11 7QJ",
    "wof:placetype": "postalcode"
  },
  "geometry": {"coordinates":[-2.769521,53.477414],"type":"Point"}
}
