{
  "type": "Feature",
  "properties": {
    "date:inception_lower":"1980-01-01",
    "date:inception_upper":"1980-01-31",
    "iso:country":"GB",
    "wof:name":"HD4 5DX",
    "wof:placetype":"postalcode"
},
  "geometry": {"coordinates":[-1.809082,53.633792],"type":"Point"}
}