{
  "type": "Feature",
  "properties": {
    "iso:country": "GB",
    "wof:name": "HD4 5DX",
    "wof:placetype": "postalcode"
  },
  "geometry": {"coordinates":[-1.809082,53.633792],"type":"Point"}
}
