{
  "type": "Feature",
  "properties": {
    "iso:country":"GB",
    "wof:name":"HD4 5DX",
    "wof:placetype":"postalcode"
},
  "geometry": {"coordinates":[-1.80908246981602,53.63379238524],"type":"Point"}
}