{
  "type": "Feature",
  "properties": {
    "iso:country":"GB",
    "wof:name":"SW6 6EU",
    "wof:placetype":"postalcode"
},
  "geometry": {"coordinates":[-0.21826617833743,51.47443921481511],"type":"Point"}
}