{
  "type": "Feature",
  "properties": {
    "iso:country":"GB",
    "wof:name":"B60 2RP",
    "wof:placetype":"postalcode"
},
  "geometry": {"coordinates":[-2.04171868386669,52.33033301699015],"type":"Point"}
}