{
  "type": "Feature",
  "properties": {
    "date:inception_lower": "1980-01-01",
    "date:inception_upper": "1980-01-01",
    "iso:country": "GB",
    "wof:name": "TN32 5UZ",
    "wof:placetype": "postalcode"
  },
  "geometry": {"coordinates":[0.517045,51.019446],"type":"Point"}
}
