{
  "type": "Feature",
  "properties": {
    "iso:country":"GB",
    "wof:name":"TN32 5UZ",
    "wof:placetype":"postalcode"
},
  "geometry": {"coordinates":[0.51704484622502,51.01944565451617],"type":"Point"}
}