{
  "type": "Feature",
  "properties": {
    "iso:country":"GB",
    "wof:name":"SA19 9LL",
    "wof:placetype":"postalcode"
},
  "geometry": {"coordinates":[-3.87975109215486,51.93820510549739],"type":"Point"}
}