{
  "type": "Feature",
  "properties": {
    "date:inception_lower": "1980-01-01",
    "date:inception_upper": "1980-01-01",
    "iso:country": "GB",
    "wof:name": "MK41 9DF",
    "wof:placetype": "postalcode"
  },
  "geometry": {"coordinates":[-0.442519,52.148723],"type":"Point"}
}
