{
  "type": "Feature",
  "properties": {
    "iso:country":"GB",
    "wof:name":"MK41 9DF",
    "wof:placetype":"postalcode"
},
  "geometry": {"coordinates":[-0.44251945829996,52.14872324805943],"type":"Point"}
}