{
  "type": "Feature",
  "properties": {
    "iso:country":"GB",
    "wof:name":"LA2 9QZ",
    "wof:placetype":"postalcode"
},
  "geometry": {"coordinates":[-2.71897497784001,54.07416825033057],"type":"Point"}
}