{
  "type": "Feature",
  "properties": {
    "date:inception_lower": "1994-05-01",
    "date:inception_upper": "1994-05-01",
    "iso:country": "GB",
    "wof:name": "L26 0SY",
    "wof:placetype": "postalcode"
  },
  "geometry": {"coordinates":[-2.832365,53.363321],"type":"Point"}
}
