{
  "type": "Feature",
  "properties": {
    "iso:country":"GB",
    "wof:name":"SW15 3EF",
    "wof:placetype":"postalcode"
},
  "geometry": {"coordinates":[-0.2443854092006,51.43846764358665],"type":"Point"}
}