{
  "type": "Feature",
  "properties": {
    "iso:country":"GB",
    "wof:name":"TR8 5BT",
    "wof:placetype":"postalcode"
},
  "geometry": {"coordinates":[-4.94026188369581,50.37732628400677],"type":"Point"}
}