{
  "type": "Feature",
  "properties": {
    "iso:country": "GB",
    "wof:name": "TR8 5BT",
    "wof:placetype": "postalcode"
  },
  "geometry": {"coordinates":[-4.940262,50.377326],"type":"Point"}
}
