{
  "type": "Feature",
  "properties": {
    "iso:country": "GB",
    "wof:name": "DL12 8EZ",
    "wof:placetype": "postalcode"
  },
  "geometry": {"coordinates":[-1.922383,54.545604],"type":"Point"}
}
