{
  "type": "Feature",
  "properties": {
    "iso:country":"GB",
    "wof:name":"BR3 3JT",
    "wof:placetype":"postalcode"
},
  "geometry": {"coordinates":[-0.03244487901378,51.39857304141405],"type":"Point"}
}