{
  "type": "Feature",
  "properties": {
    "iso:country":"GB",
    "wof:name":"HU15 1GQ",
    "wof:placetype":"postalcode"
},
  "geometry": {"coordinates":[-0.55844113015896,53.72525135069657],"type":"Point"}
}