{
  "type": "Feature",
  "properties": {
    "date:inception_lower": "2005-05-01",
    "date:inception_upper": "2005-05-01",
    "iso:country": "GB",
    "wof:name": "HU15 1GQ",
    "wof:placetype": "postalcode"
  },
  "geometry": {"coordinates":[-0.558441,53.725251],"type":"Point"}
}
