{
  "type": "Feature",
  "properties": {
    "iso:country": "GB",
    "wof:name": "CF83 1PL",
    "wof:placetype": "postalcode"
  },
  "geometry": {"coordinates":[-3.210582,51.575128],"type":"Point"}
}
