{
  "type": "Feature",
  "properties": {
    "date:inception_lower":"1995-07-01",
    "date:inception_upper":"1995-07-31",
    "iso:country":"GB",
    "wof:name":"CF83 1PL",
    "wof:placetype":"postalcode"
},
  "geometry": {"coordinates":[-3.210582,51.575128],"type":"Point"}
}