{
  "type": "Feature",
  "properties": {
    "iso:country":"GB",
    "wof:name":"CF83 1PL",
    "wof:placetype":"postalcode"
},
  "geometry": {"coordinates":[-3.2105824088743,51.57512803404305],"type":"Point"}
}