{
  "type": "Feature",
  "properties": {
    "iso:country":"GB",
    "wof:name":"LU7 4QG",
    "wof:placetype":"postalcode"
},
  "geometry": {"coordinates":[-0.63087757996917,51.91182036868841],"type":"Point"}
}