{
  "type": "Feature",
  "properties": {
    "iso:country":"GB",
    "wof:name":"WN8 6DA",
    "wof:placetype":"postalcode"
},
  "geometry": {"coordinates":[-2.7625477838165,53.54729157464356],"type":"Point"}
}