{
  "type": "Feature",
  "properties": {
    "iso:country": "GB",
    "wof:name": "LE14 3DW",
    "wof:placetype": "postalcode"
  },
  "geometry": {"coordinates":[-1.009943,52.751611],"type":"Point"}
}
