{
  "type": "Feature",
  "properties": {
    "iso:country":"GB",
    "wof:name":"LE14 3DW",
    "wof:placetype":"postalcode"
},
  "geometry": {"coordinates":[-1.0099430488992,52.7516112799713],"type":"Point"}
}