{
  "type": "Feature",
  "properties": {
    "iso:country":"GB",
    "wof:name":"BR5 2PL",
    "wof:placetype":"postalcode"
},
  "geometry": {"coordinates":[0.10610284689358,51.40240567520249],"type":"Point"}
}