{
  "type": "Feature",
  "properties": {
    "iso:country":"GB",
    "wof:name":"CM2 9PL",
    "wof:placetype":"postalcode"
},
  "geometry": {"coordinates":[0.469002021175,51.72619078980072],"type":"Point"}
}