{
  "type": "Feature",
  "properties": {
    "iso:country": "GB",
    "wof:name": "M7 4UQ",
    "wof:placetype": "postalcode"
  },
  "geometry": {"coordinates":[-2.256385,53.50181],"type":"Point"}
}
