{
  "type": "Feature",
  "properties": {
    "iso:country":"GB",
    "wof:name":"M7 4UQ",
    "wof:placetype":"postalcode"
},
  "geometry": {"coordinates":[-2.2563853103773,53.50181030513679],"type":"Point"}
}