{
  "type": "Feature",
  "properties": {
    "iso:country":"GB",
    "wof:name":"BB12 0JR",
    "wof:placetype":"postalcode"
},
  "geometry": {"coordinates":[-2.26286145305029,53.797238603761],"type":"Point"}
}