{
  "type": "Feature",
  "properties": {
    "iso:country": "GB",
    "wof:name": "BB12 0JR",
    "wof:placetype": "postalcode"
  },
  "geometry": {"coordinates":[-2.262861,53.797239],"type":"Point"}
}
