{
  "type": "Feature",
  "properties": {
    "iso:country":"GB",
    "wof:name":"LA12 9BX",
    "wof:placetype":"postalcode"
},
  "geometry": {"coordinates":[-3.08740478597425,54.18997050487656],"type":"Point"}
}