{
  "type": "Feature",
  "properties": {
    "iso:country": "GB",
    "wof:name": "LA12 9BX",
    "wof:placetype": "postalcode"
  },
  "geometry": {"coordinates":[-3.087375,54.190007],"type":"Point"}
}
