{
  "type": "Feature",
  "properties": {
    "iso:country":"GB",
    "wof:name":"G23 5AW",
    "wof:placetype":"postalcode"
},
  "geometry": {"coordinates":[-4.281063015223,55.8975103057256],"type":"Point"}
}