{
  "type": "Feature",
  "properties": {
    "iso:country":"GB",
    "wof:name":"NG5 6FD",
    "wof:placetype":"postalcode"
},
  "geometry": {"coordinates":[-1.14205060791281,53.00199426709864],"type":"Point"}
}