{
  "type": "Feature",
  "properties": {
    "iso:country":"GB",
    "wof:name":"NE6 1AW",
    "wof:placetype":"postalcode"
},
  "geometry": {"coordinates":[-1.58722840841335,54.97434081345958],"type":"Point"}
}