{
  "type": "Feature",
  "properties": {
    "iso:country": "GB",
    "wof:name": "GU29 0EX",
    "wof:placetype": "postalcode"
  },
  "geometry": {"coordinates":[-0.747369,51.017329],"type":"Point"}
}
