{
  "type": "Feature",
  "properties": {
    "iso:country":"GB",
    "wof:name":"GU29 0EX",
    "wof:placetype":"postalcode"
},
  "geometry": {"coordinates":[-0.74739351270289,51.01717336708415],"type":"Point"}
}