{
  "type": "Feature",
  "properties": {
    "iso:country": "GB",
    "wof:name": "RG2 8JT",
    "wof:placetype": "postalcode"
  },
  "geometry": {"coordinates":[-0.955515,51.419931],"type":"Point"}
}
