{
  "type": "Feature",
  "properties": {
    "iso:country":"GB",
    "wof:name":"RG2 8JT",
    "wof:placetype":"postalcode"
},
  "geometry": {"coordinates":[-0.95559272190563,51.41991261755268],"type":"Point"}
}