{
  "type": "Feature",
  "properties": {
    "iso:country":"GB",
    "wof:name":"SW6 2NZ",
    "wof:placetype":"postalcode"
},
  "geometry": {"coordinates":[-0.18874779491682,51.46714365299201],"type":"Point"}
}