{
  "type": "Feature",
  "properties": {
    "iso:country":"GB",
    "wof:name":"NG24 3AA",
    "wof:placetype":"postalcode"
},
  "geometry": {"coordinates":[-0.78646009756819,53.06008139916021],"type":"Point"}
}