{
  "type": "Feature",
  "properties": {
    "date:inception_lower": "1980-01-01",
    "date:inception_upper": "1980-01-01",
    "iso:country": "GB",
    "wof:name": "DN21 1DB",
    "wof:placetype": "postalcode"
  },
  "geometry": {"coordinates":[-0.769069,53.389967],"type":"Point"}
}
