{
  "type": "Feature",
  "properties": {
    "iso:country":"GB",
    "wof:name":"UB5 5AN",
    "wof:placetype":"postalcode"
},
  "geometry": {"coordinates":[-0.37331282619365,51.54343315551289],"type":"Point"}
}