{
  "type": "Feature",
  "properties": {
    "iso:country":"GB",
    "wof:name":"LL36 9NY",
    "wof:placetype":"postalcode"
},
  "geometry": {"coordinates":[-4.05591131209409,52.60880245522493],"type":"Point"}
}