{
  "type": "Feature",
  "properties": {
    "date:inception_lower": "1980-01-01",
    "date:inception_upper": "1980-01-01",
    "iso:country": "GB",
    "wof:name": "PO21 3NP",
    "wof:placetype": "postalcode"
  },
  "geometry": {"coordinates":[-0.729381,50.782769],"type":"Point"}
}
