{
  "type": "Feature",
  "properties": {
    "iso:country":"GB",
    "wof:name":"PO21 3NP",
    "wof:placetype":"postalcode"
},
  "geometry": {"coordinates":[-0.72938102766009,50.78276933399874],"type":"Point"}
}