{
  "type": "Feature",
  "properties": {
    "iso:country":"GB",
    "wof:name":"G53 6PU",
    "wof:placetype":"postalcode"
},
  "geometry": {"coordinates":[-4.34447456619689,55.81667891712654],"type":"Point"}
}