{
  "type": "Feature",
  "properties": {
    "iso:country":"GB",
    "wof:name":"TF1 5DU",
    "wof:placetype":"postalcode"
},
  "geometry": {"coordinates":[-2.47503817161402,52.6976232724586],"type":"Point"}
}