{
  "type": "Feature",
  "properties": {
    "date:inception_lower":"2012-10-01",
    "date:inception_upper":"2012-10-31",
    "iso:country":"GB",
    "wof:name":"TF1 5DU",
    "wof:placetype":"postalcode"
},
  "geometry": {"coordinates":[-2.475038,52.697623],"type":"Point"}
}