{
  "type": "Feature",
  "properties": {
    "iso:country":"GB",
    "wof:name":"NN7 4AW",
    "wof:placetype":"postalcode"
},
  "geometry": {"coordinates":[-0.97618532700209,52.23491252605211],"type":"Point"}
}