{
  "type": "Feature",
  "properties": {
    "iso:country": "GB",
    "wof:name": "NN7 4AW",
    "wof:placetype": "postalcode"
  },
  "geometry": {"coordinates":[-0.976185,52.234913],"type":"Point"}
}
