{
  "type": "Feature",
  "properties": {
    "date:inception_lower": "1999-12-01",
    "date:inception_upper": "1999-12-01",
    "iso:country": "GB",
    "wof:name": "M26 3DX",
    "wof:placetype": "postalcode"
  },
  "geometry": {"coordinates":[-2.331686,53.563142],"type":"Point"}
}
