{
  "type": "Feature",
  "properties": {
    "iso:country":"GB",
    "wof:name":"M26 3DX",
    "wof:placetype":"postalcode"
},
  "geometry": {"coordinates":[-2.33168587912606,53.56314154029581],"type":"Point"}
}