{
  "type": "Feature",
  "properties": {
    "iso:country": "GB",
    "wof:name": "CA4 8AF",
    "wof:placetype": "postalcode"
  },
  "geometry": {"coordinates":[-2.863034,54.901585],"type":"Point"}
}
