{
  "type": "Feature",
  "properties": {
    "iso:country":"GB",
    "wof:name":"BA1 2PD",
    "wof:placetype":"postalcode"
},
  "geometry": {"coordinates":[-2.36351341724416,51.38506470925182],"type":"Point"}
}