{
  "type": "Feature",
  "properties": {
    "iso:country":"GB",
    "wof:name":"N9 8NY",
    "wof:placetype":"postalcode"
},
  "geometry": {"coordinates":[-0.05045461165164,51.63392285837693],"type":"Point"}
}