{
  "type": "Feature",
  "properties": {
    "date:inception_lower":"2018-01-01",
    "date:inception_upper":"2018-01-31",
    "iso:country":"GB",
    "wof:name":"LE15 6QJ",
    "wof:placetype":"postalcode"
},
  "geometry": {"coordinates":[-0.738282,52.674964],"type":"Point"}
}