{
  "type": "Feature",
  "properties": {
    "iso:country":"GB",
    "wof:name":"N14 4XD",
    "wof:placetype":"postalcode"
},
  "geometry": {"coordinates":[-0.12654993225416,51.64795790966884],"type":"Point"}
}