{
  "type": "Feature",
  "properties": {
    "iso:country":"GB",
    "wof:name":"CA15 6HZ",
    "wof:placetype":"postalcode"
},
  "geometry": {"coordinates":[-3.49583701226012,54.71787503963645],"type":"Point"}
}