{
  "type": "Feature",
  "properties": {
    "iso:country":"GB",
    "wof:name":"CF5 4UJ",
    "wof:placetype":"postalcode"
},
  "geometry": {"coordinates":[-3.27517424111288,51.47040717496043],"type":"Point"}
}