{
  "type": "Feature",
  "properties": {
    "date:inception_lower": "1980-01-01",
    "date:inception_upper": "1980-01-01",
    "iso:country": "GB",
    "wof:name": "KT24 5SW",
    "wof:placetype": "postalcode"
  },
  "geometry": {"coordinates":[-0.40126,51.272767],"type":"Point"}
}
