{
  "type": "Feature",
  "properties": {
    "date:inception_lower": "1980-01-01",
    "date:inception_upper": "1980-01-01",
    "iso:country": "GB",
    "wof:name": "LL61 5BJ",
    "wof:placetype": "postalcode"
  },
  "geometry": {"coordinates":[-4.205007,53.236422],"type":"Point"}
}
