{
  "type": "Feature",
  "properties": {
    "iso:country":"GB",
    "wof:name":"LL61 5BJ",
    "wof:placetype":"postalcode"
},
  "geometry": {"coordinates":[-4.20500746346588,53.23642246320073],"type":"Point"}
}