{
  "type": "Feature",
  "properties": {
    "date:inception_lower": "2010-09-01",
    "date:inception_upper": "2010-09-01",
    "iso:country": "GB",
    "wof:name": "HG1 9PG",
    "wof:placetype": "postalcode"
  },
  "geometry": {"coordinates":[-1.522386,54.002427],"type":"Point"}
}
