{
  "type": "Feature",
  "properties": {
    "date:inception_lower":"1980-01-01",
    "date:inception_upper":"1980-01-31",
    "iso:country":"GB",
    "wof:name":"OX16 0JN",
    "wof:placetype":"postalcode"
},
  "geometry": {"coordinates":[-1.364765,52.059781],"type":"Point"}
}