{
  "type": "Feature",
  "properties": {
    "iso:country":"GB",
    "wof:name":"OX16 0JN",
    "wof:placetype":"postalcode"
},
  "geometry": {"coordinates":[-1.36476552491068,52.05978131955781],"type":"Point"}
}