{
  "type": "Feature",
  "properties": {
    "iso:country":"GB",
    "wof:name":"CF42 5BL",
    "wof:placetype":"postalcode"
},
  "geometry": {"coordinates":[-3.54154920584369,51.67556263241677],"type":"Point"}
}