{
  "type": "Feature",
  "properties": {
    "date:inception_lower": "1980-01-01",
    "date:inception_upper": "1980-01-01",
    "iso:country": "GB",
    "wof:name": "WF14 9PZ",
    "wof:placetype": "postalcode"
  },
  "geometry": {"coordinates":[-1.708383,53.679349],"type":"Point"}
}
