{
  "type": "Feature",
  "properties": {
    "iso:country":"GB",
    "wof:name":"WF14 9PZ",
    "wof:placetype":"postalcode"
},
  "geometry": {"coordinates":[-1.70838331284241,53.6793486068819],"type":"Point"}
}