{
  "type": "Feature",
  "properties": {
    "date:inception_lower": "1980-01-01",
    "date:inception_upper": "1980-01-01",
    "iso:country": "GB",
    "wof:name": "KY7 6DB",
    "wof:placetype": "postalcode"
  },
  "geometry": {"coordinates":[-3.135172,56.203716],"type":"Point"}
}
