{
  "type": "Feature",
  "properties": {
    "iso:country": "GB",
    "wof:name": "KY7 6DB",
    "wof:placetype": "postalcode"
  },
  "geometry": {"coordinates":[-3.134399,56.203811],"type":"Point"}
}
