{
  "type": "Feature",
  "properties": {
    "iso:country":"GB",
    "wof:name":"BS8 3BX",
    "wof:placetype":"postalcode"
},
  "geometry": {"coordinates":[-2.61694682506256,51.45883288167092],"type":"Point"}
}