{
  "type": "Feature",
  "properties": {
    "iso:country": "GB",
    "wof:name": "SK8 1JB",
    "wof:placetype": "postalcode"
  },
  "geometry": {"coordinates":[-2.214801,53.384457],"type":"Point"}
}
