{
  "type": "Feature",
  "properties": {
    "date:inception_lower": "1980-01-01",
    "date:inception_upper": "1980-01-01",
    "iso:country": "GB",
    "wof:name": "SK8 1JB",
    "wof:placetype": "postalcode"
  },
  "geometry": {"coordinates":[-2.214801,53.384457],"type":"Point"}
}
