{
  "type": "Feature",
  "properties": {
    "iso:country":"GB",
    "wof:name":"SK8 1JB",
    "wof:placetype":"postalcode"
},
  "geometry": {"coordinates":[-2.21480075936166,53.38445746891185],"type":"Point"}
}