{
  "type": "Feature",
  "properties": {
    "iso:country": "GB",
    "wof:name": "DN21 3TU",
    "wof:placetype": "postalcode"
  },
  "geometry": {"coordinates":[-0.672772,53.496662],"type":"Point"}
}
