{
  "type": "Feature",
  "properties": {
    "iso:country":"GB",
    "wof:name":"DN21 3TU",
    "wof:placetype":"postalcode"
},
  "geometry": {"coordinates":[-0.67277254093307,53.49666179731992],"type":"Point"}
}