{
  "type": "Feature",
  "properties": {
    "date:inception_lower": "1980-01-01",
    "date:inception_upper": "1980-01-01",
    "iso:country": "GB",
    "wof:name": "ST5 8QQ",
    "wof:placetype": "postalcode"
  },
  "geometry": {"coordinates":[-2.232456,53.039935],"type":"Point"}
}
