{
  "type": "Feature",
  "properties": {
    "iso:country":"GB",
    "wof:name":"ST5 8QQ",
    "wof:placetype":"postalcode"
},
  "geometry": {"coordinates":[-2.23245592766719,53.03993518408122],"type":"Point"}
}