{
  "type": "Feature",
  "properties": {
    "date:inception_lower": "2004-01-01",
    "date:inception_upper": "2004-01-01",
    "iso:country": "GB",
    "wof:name": "CF46 5PQ",
    "wof:placetype": "postalcode"
  },
  "geometry": {"coordinates":[-3.323863,51.662465],"type":"Point"}
}
