{
  "type": "Feature",
  "properties": {
    "iso:country":"GB",
    "wof:name":"CF46 5PQ",
    "wof:placetype":"postalcode"
},
  "geometry": {"coordinates":[-3.3238632179219,51.66246505359998],"type":"Point"}
}