{
  "type": "Feature",
  "properties": {
    "iso:country":"GB",
    "wof:name":"WA8 5PZ",
    "wof:placetype":"postalcode"
},
  "geometry": {"coordinates":[-2.77158736858264,53.38865509190285],"type":"Point"}
}