{
  "type": "Feature",
  "properties": {
    "iso:country": "GB",
    "wof:name": "WA8 5PZ",
    "wof:placetype": "postalcode"
  },
  "geometry": {"coordinates":[-2.771587,53.388655],"type":"Point"}
}
