{
  "type": "Feature",
  "properties": {
    "date:inception_lower": "2004-05-01",
    "date:inception_upper": "2004-05-01",
    "iso:country": "GB",
    "wof:name": "CV34 4LD",
    "wof:placetype": "postalcode"
  },
  "geometry": {"coordinates":[-1.580163,52.285534],"type":"Point"}
}
