{
  "type": "Feature",
  "properties": {
    "iso:country":"GB",
    "wof:name":"CV34 4LD",
    "wof:placetype":"postalcode"
},
  "geometry": {"coordinates":[-1.58016343029822,52.28553411241725],"type":"Point"}
}