{
  "type": "Feature",
  "properties": {
    "iso:country": "GB",
    "wof:name": "CV34 4LD",
    "wof:placetype": "postalcode"
  },
  "geometry": {"coordinates":[-1.580163,52.285534],"type":"Point"}
}
