{
  "type": "Feature",
  "properties": {
    "iso:country": "GB",
    "wof:name": "SL6 3UU",
    "wof:placetype": "postalcode"
  },
  "geometry": {"coordinates":[-0.761432,51.506413],"type":"Point"}
}
