{
  "type": "Feature",
  "properties": {
    "iso:country":"GB",
    "wof:name":"NN8 2AY",
    "wof:placetype":"postalcode"
},
  "geometry": {"coordinates":[-0.70245872453433,52.29693761757575],"type":"Point"}
}