{
  "type": "Feature",
  "properties": {
    "iso:country":"GB",
    "wof:name":"NR30 1QY",
    "wof:placetype":"postalcode"
},
  "geometry": {"coordinates":[1.72509391939401,52.61681091223955],"type":"Point"}
}