{
  "type": "Feature",
  "properties": {
    "date:inception_lower":"1980-01-01",
    "date:inception_upper":"1980-01-31",
    "iso:country":"GB",
    "wof:name":"SG1 5RP",
    "wof:placetype":"postalcode"
},
  "geometry": {"coordinates":[-0.171735,51.92051],"type":"Point"}
}