{
  "type": "Feature",
  "properties": {
    "iso:country":"GB",
    "wof:name":"SG1 5RP",
    "wof:placetype":"postalcode"
},
  "geometry": {"coordinates":[-0.17173484347458,51.92051017509353],"type":"Point"}
}