{
  "type": "Feature",
  "properties": {
    "iso:country": "GB",
    "wof:name": "SG1 5RP",
    "wof:placetype": "postalcode"
  },
  "geometry": {"coordinates":[-0.171735,51.92051],"type":"Point"}
}
