{
  "type": "Feature",
  "properties": {
    "iso:country":"GB",
    "wof:name":"N1 1RR",
    "wof:placetype":"postalcode"
},
  "geometry": {"coordinates":[-0.10360367880305,51.54378086987398],"type":"Point"}
}