{
  "type": "Feature",
  "properties": {
    "iso:country": "GB",
    "wof:name": "N1 1RR",
    "wof:placetype": "postalcode"
  },
  "geometry": {"coordinates":[-0.103604,51.543781],"type":"Point"}
}
