{
  "type": "Feature",
  "properties": {
    "iso:country":"GB",
    "wof:name":"LS2 8JP",
    "wof:placetype":"postalcode"
},
  "geometry": {"coordinates":[-1.5409997476634,53.8009102418543],"type":"Point"}
}