{
  "type": "Feature",
  "properties": {
    "iso:country":"GB",
    "wof:name":"SL8 5NE",
    "wof:placetype":"postalcode"
},
  "geometry": {"coordinates":[-0.70862967150991,51.5825989585336],"type":"Point"}
}