{
  "type": "Feature",
  "properties": {
    "iso:country":"GB",
    "wof:name":"LE14 2JU",
    "wof:placetype":"postalcode"
},
  "geometry": {"coordinates":[-0.72704306499128,52.75001888117694],"type":"Point"}
}