{
  "type": "Feature",
  "properties": {
    "iso:country": "GB",
    "wof:name": "LE14 2JU",
    "wof:placetype": "postalcode"
  },
  "geometry": {"coordinates":[-0.727043,52.750019],"type":"Point"}
}
