{
  "type": "Feature",
  "properties": {
    "iso:country":"GB",
    "wof:name":"SM1 2LA",
    "wof:placetype":"postalcode"
},
  "geometry": {"coordinates":[-0.20923415429106,51.36854914793287],"type":"Point"}
}