{
  "type": "Feature",
  "properties": {
    "iso:country": "GB",
    "wof:name": "LL65 3HR",
    "wof:placetype": "postalcode"
  },
  "geometry": {"coordinates":[-4.547403,53.279215],"type":"Point"}
}
