{
  "type": "Feature",
  "properties": {
    "iso:country":"GB",
    "wof:name":"LL65 3HR",
    "wof:placetype":"postalcode"
},
  "geometry": {"coordinates":[-4.54740329155457,53.27921549733245],"type":"Point"}
}