{
  "type": "Feature",
  "properties": {
    "iso:country":"GB",
    "wof:name":"GU2 8LS",
    "wof:placetype":"postalcode"
},
  "geometry": {"coordinates":[-0.61602730065934,51.24586571155933],"type":"Point"}
}