{
  "type": "Feature",
  "properties": {
    "date:inception_lower": "2000-06-01",
    "date:inception_upper": "2000-06-01",
    "iso:country": "GB",
    "wof:name": "GU2 8LS",
    "wof:placetype": "postalcode"
  },
  "geometry": {"coordinates":[-0.616027,51.245866],"type":"Point"}
}
