{
  "type": "Feature",
  "properties": {
    "date:inception_lower": "1980-01-01",
    "date:inception_upper": "1980-01-01",
    "iso:country": "GB",
    "wof:name": "BH21 2PB",
    "wof:placetype": "postalcode"
  },
  "geometry": {"coordinates":[-1.971082,50.805933],"type":"Point"}
}
