{
  "type": "Feature",
  "properties": {
    "iso:country":"GB",
    "wof:name":"IG8 0NP",
    "wof:placetype":"postalcode"
},
  "geometry": {"coordinates":[0.03779043105739,51.61770342578777],"type":"Point"}
}