{
  "type": "Feature",
  "properties": {
    "iso:country":"GB",
    "wof:name":"BH10 5EP",
    "wof:placetype":"postalcode"
},
  "geometry": {"coordinates":[-1.90065203304111,50.75762210538405],"type":"Point"}
}