{
  "type": "Feature",
  "properties": {
    "iso:country":"GB",
    "wof:name":"L22 7RF",
    "wof:placetype":"postalcode"
},
  "geometry": {"coordinates":[-3.03569251605337,53.47995165364997],"type":"Point"}
}