{
  "type": "Feature",
  "properties": {
    "iso:country":"GB",
    "wof:name":"PR3 1LB",
    "wof:placetype":"postalcode"
},
  "geometry": {"coordinates":[-2.77523142629882,53.91249469254166],"type":"Point"}
}