{
  "type": "Feature",
  "properties": {
    "date:inception_lower": "1981-06-01",
    "date:inception_upper": "1981-06-01",
    "iso:country": "GB",
    "wof:name": "IP14 1TN",
    "wof:placetype": "postalcode"
  },
  "geometry": {"coordinates":[0.982438,52.196784],"type":"Point"}
}
