{
  "type": "Feature",
  "properties": {
    "iso:country":"GB",
    "wof:name":"M40 8DZ",
    "wof:placetype":"postalcode"
},
  "geometry": {"coordinates":[-2.2110565366757,53.49354877848832],"type":"Point"}
}