{
  "type": "Feature",
  "properties": {
    "date:inception_lower": "1994-05-01",
    "date:inception_upper": "1994-05-01",
    "iso:country": "GB",
    "wof:name": "M40 8DZ",
    "wof:placetype": "postalcode"
  },
  "geometry": {"coordinates":[-2.211056,53.493549],"type":"Point"}
}
