{
  "type": "Feature",
  "properties": {
    "iso:country":"GB",
    "wof:name":"NG34 0SL",
    "wof:placetype":"postalcode"
},
  "geometry": {"coordinates":[-0.40855913964849,52.88880580200671],"type":"Point"}
}