{
  "type": "Feature",
  "properties": {
    "iso:country": "GB",
    "wof:name": "NG34 0SL",
    "wof:placetype": "postalcode"
  },
  "geometry": {"coordinates":[-0.408559,52.888806],"type":"Point"}
}
