{
  "type": "Feature",
  "properties": {
    "iso:country": "GB",
    "wof:name": "DH2 1LU",
    "wof:placetype": "postalcode"
  },
  "geometry": {"coordinates":[-1.611554,54.872084],"type":"Point"}
}
