{
  "type": "Feature",
  "properties": {
    "iso:country":"GB",
    "wof:name":"DH2 1LU",
    "wof:placetype":"postalcode"
},
  "geometry": {"coordinates":[-1.61155392234187,54.87208445831109],"type":"Point"}
}