{
  "type": "Feature",
  "properties": {
    "iso:country":"GB",
    "wof:name":"LE2 6BE",
    "wof:placetype":"postalcode"
},
  "geometry": {"coordinates":[-1.13213379590083,52.62307726471701],"type":"Point"}
}