{
  "type": "Feature",
  "properties": {
    "iso:country":"GB",
    "wof:name":"BS10 6JR",
    "wof:placetype":"postalcode"
},
  "geometry": {"coordinates":[-2.60346097718493,51.51014621649249],"type":"Point"}
}