{
  "type": "Feature",
  "properties": {
    "date:inception_lower": "1980-01-01",
    "date:inception_upper": "1980-01-01",
    "iso:country": "GB",
    "wof:name": "TQ12 6LF",
    "wof:placetype": "postalcode"
  },
  "geometry": {"coordinates":[-3.728337,50.551094],"type":"Point"}
}
