{
  "type": "Feature",
  "properties": {
    "date:inception_lower": "2003-02-01",
    "date:inception_upper": "2003-02-01",
    "iso:country": "GB",
    "wof:name": "GU51 1HF",
    "wof:placetype": "postalcode"
  },
  "geometry": {"coordinates":[-0.863904,51.294169],"type":"Point"}
}
