{
  "type": "Feature",
  "properties": {
    "iso:country": "GB",
    "wof:name": "GL5 4EB",
    "wof:placetype": "postalcode"
  },
  "geometry": {"coordinates":[-2.234006,51.74915],"type":"Point"}
}
