{
  "type": "Feature",
  "properties": {
    "iso:country":"GB",
    "wof:name":"BS37 8UP",
    "wof:placetype":"postalcode"
},
  "geometry": {"coordinates":[-2.41904165545394,51.52667648828402],"type":"Point"}
}