{
  "type": "Feature",
  "properties": {
    "iso:country":"GB",
    "wof:name":"SG1 4AW",
    "wof:placetype":"postalcode"
},
  "geometry": {"coordinates":[-0.20800283735674,51.92416116834858],"type":"Point"}
}