{
  "type": "Feature",
  "properties": {
    "iso:country":"GB",
    "wof:name":"WR9 7BS",
    "wof:placetype":"postalcode"
},
  "geometry": {"coordinates":[-2.15298447879581,52.25949681751568],"type":"Point"}
}