{
  "type": "Feature",
  "properties": {
    "iso:country":"GB",
    "wof:name":"G61 3JF",
    "wof:placetype":"postalcode"
},
  "geometry": {"coordinates":[-4.33570354053219,55.9325975281845],"type":"Point"}
}