{
  "type": "Feature",
  "properties": {
    "date:inception_lower":"1986-11-01",
    "date:inception_upper":"1986-11-30",
    "iso:country":"GB",
    "wof:name":"DG6 4RX",
    "wof:placetype":"postalcode"
},
  "geometry": {"coordinates":[-4.051805,54.841588],"type":"Point"}
}