{
  "type": "Feature",
  "properties": {
    "iso:country":"GB",
    "wof:name":"DG6 4RX",
    "wof:placetype":"postalcode"
},
  "geometry": {"coordinates":[-4.0518050840434,54.84158789187214],"type":"Point"}
}