{
  "type": "Feature",
  "properties": {
    "date:inception_lower": "2020-06-01",
    "date:inception_upper": "2020-06-01",
    "iso:country": "GB",
    "wof:name": "CH8 7FE",
    "wof:placetype": "postalcode"
  },
  "geometry": {"coordinates":[-3.221688,53.272521],"type":"Point"}
}
