{
  "type": "Feature",
  "properties": {
    "iso:country":"GB",
    "wof:name":"PA7 5HN",
    "wof:placetype":"postalcode"
},
  "geometry": {"coordinates":[-4.50014005138276,55.9080667973362],"type":"Point"}
}