{
  "type": "Feature",
  "properties": {
    "iso:country": "GB",
    "wof:name": "EH26 8LS",
    "wof:placetype": "postalcode"
  },
  "geometry": {"coordinates":[-3.219255,55.823612],"type":"Point"}
}
