{
  "type": "Feature",
  "properties": {
    "iso:country":"GB",
    "wof:name":"EH26 8LS",
    "wof:placetype":"postalcode"
},
  "geometry": {"coordinates":[-3.21925528430291,55.82361215565498],"type":"Point"}
}