{
  "type": "Feature",
  "properties": {
    "date:inception_lower": "2019-11-01",
    "date:inception_upper": "2019-11-01",
    "iso:country": "GB",
    "wof:name": "HP22 7BW",
    "wof:placetype": "postalcode"
  },
  "geometry": {"coordinates":[-0.769675,51.825308],"type":"Point"}
}
