{
  "type": "Feature",
  "properties": {
    "iso:country": "GB",
    "wof:name": "HP22 7BW",
    "wof:placetype": "postalcode"
  },
  "geometry": {"coordinates":[-0.769675,51.825308],"type":"Point"}
}
