{
  "type": "Feature",
  "properties": {
    "date:inception_lower":"2000-12-01",
    "date:inception_upper":"2000-12-31",
    "iso:country":"GB",
    "wof:name":"B75 7HD",
    "wof:placetype":"postalcode"
},
  "geometry": {"coordinates":[-1.7915,52.568761],"type":"Point"}
}