{
  "type": "Feature",
  "properties": {
    "iso:country":"GB",
    "wof:name":"B75 7HD",
    "wof:placetype":"postalcode"
},
  "geometry": {"coordinates":[-1.7914999950508,52.56876108786229],"type":"Point"}
}