{
  "type": "Feature",
  "properties": {
    "iso:country":"GB",
    "wof:name":"BA5 1NA",
    "wof:placetype":"postalcode"
},
  "geometry": {"coordinates":[-2.67423779397093,51.20778836267464],"type":"Point"}
}