{
  "type": "Feature",
  "properties": {
    "iso:country": "GB",
    "wof:name": "LS29 6GA",
    "wof:placetype": "postalcode"
  },
  "geometry": {"coordinates":[-1.73465,53.888713],"type":"Point"}
}
