{
  "type": "Feature",
  "properties": {
    "iso:country":"GB",
    "wof:name":"SY23 3JN",
    "wof:placetype":"postalcode"
},
  "geometry": {"coordinates":[-3.8444219440981,52.37148509613699],"type":"Point"}
}