{
  "type": "Feature",
  "properties": {
    "date:inception_lower": "1980-01-01",
    "date:inception_upper": "1980-01-01",
    "iso:country": "GB",
    "wof:name": "G52 4DW",
    "wof:placetype": "postalcode"
  },
  "geometry": {"coordinates":[-4.373272,55.852581],"type":"Point"}
}
