{
  "type": "Feature",
  "properties": {
    "iso:country": "GB",
    "wof:name": "G52 4DW",
    "wof:placetype": "postalcode"
  },
  "geometry": {"coordinates":[-4.373272,55.852581],"type":"Point"}
}
