{
  "type": "Feature",
  "properties": {
    "iso:country":"GB",
    "wof:name":"SO31 6XB",
    "wof:placetype":"postalcode"
},
  "geometry": {"coordinates":[-1.28799390948677,50.85716363895561],"type":"Point"}
}