{
  "type": "Feature",
  "properties": {
    "iso:country":"GB",
    "wof:name":"CW5 6JN",
    "wof:placetype":"postalcode"
},
  "geometry": {"coordinates":[-2.5057946476201,53.06714169887211],"type":"Point"}
}