{
  "type": "Feature",
  "properties": {
    "date:inception_lower": "1980-01-01",
    "date:inception_upper": "1980-01-01",
    "iso:country": "GB",
    "wof:name": "CW5 6JN",
    "wof:placetype": "postalcode"
  },
  "geometry": {"coordinates":[-2.505795,53.067142],"type":"Point"}
}
