{
  "type": "Feature",
  "properties": {
    "iso:country":"GB",
    "wof:name":"CA2 7AX",
    "wof:placetype":"postalcode"
},
  "geometry": {"coordinates":[-2.95303753414937,54.8919340894963],"type":"Point"}
}