{
  "type": "Feature",
  "properties": {
    "iso:country":"GB",
    "wof:name":"SO17 1XB",
    "wof:placetype":"postalcode"
},
  "geometry": {"coordinates":[-1.40043953085196,50.92741515606654],"type":"Point"}
}