{
  "type": "Feature",
  "properties": {
    "iso:country":"GB",
    "wof:name":"L14 6TH",
    "wof:placetype":"postalcode"
},
  "geometry": {"coordinates":[-2.87635294934401,53.4110152263546],"type":"Point"}
}