{
  "type": "Feature",
  "properties": {
    "iso:country": "GB",
    "wof:name": "L14 6TH",
    "wof:placetype": "postalcode"
  },
  "geometry": {"coordinates":[-2.876353,53.411015],"type":"Point"}
}
