{
  "type": "Feature",
  "properties": {
    "iso:country":"GB",
    "wof:name":"CH62 0BZ",
    "wof:placetype":"postalcode"
},
  "geometry": {"coordinates":[-2.96388585047186,53.31475178868934],"type":"Point"}
}