{
  "type": "Feature",
  "properties": {
    "iso:country":"GB",
    "wof:name":"WR14 1AR",
    "wof:placetype":"postalcode"
},
  "geometry": {"coordinates":[-2.30846645513266,52.13149263076383],"type":"Point"}
}