{
  "type": "Feature",
  "properties": {
    "iso:country": "GB",
    "wof:name": "WR14 1AR",
    "wof:placetype": "postalcode"
  },
  "geometry": {"coordinates":[-2.308725,52.131386],"type":"Point"}
}
