{
  "type": "Feature",
  "properties": {
    "iso:country":"GB",
    "wof:name":"SK6 7LJ",
    "wof:placetype":"postalcode"
},
  "geometry": {"coordinates":[-2.06103098111444,53.38509384851564],"type":"Point"}
}