{
  "type": "Feature",
  "properties": {
    "iso:country": "GB",
    "wof:name": "NN11 3TQ",
    "wof:placetype": "postalcode"
  },
  "geometry": {"coordinates":[-1.157459,52.178172],"type":"Point"}
}
