{
  "type": "Feature",
  "properties": {
    "iso:country":"GB",
    "wof:name":"HP10 9XD",
    "wof:placetype":"postalcode"
},
  "geometry": {"coordinates":[-0.7008554026257,51.6087333835755],"type":"Point"}
}