{
  "type": "Feature",
  "properties": {
    "date:inception_lower": "2001-06-01",
    "date:inception_upper": "2001-06-01",
    "iso:country": "GB",
    "wof:name": "LS3 1BT",
    "wof:placetype": "postalcode"
  },
  "geometry": {"coordinates":[-1.561879,53.803604],"type":"Point"}
}
