{
  "type": "Feature",
  "properties": {
    "iso:country": "GB",
    "wof:name": "LS3 1BT",
    "wof:placetype": "postalcode"
  },
  "geometry": {"coordinates":[-1.561879,53.803604],"type":"Point"}
}
