{
  "type": "Feature",
  "properties": {
    "date:inception_lower":"1980-01-01",
    "date:inception_upper":"1980-01-31",
    "iso:country":"GB",
    "wof:name":"GL19 4DY",
    "wof:placetype":"postalcode"
},
  "geometry": {"coordinates":[-2.207946,51.944078],"type":"Point"}
}