{
  "type": "Feature",
  "properties": {
    "date:inception_lower": "1995-01-01",
    "date:inception_upper": "1995-01-01",
    "iso:country": "GB",
    "wof:name": "LL18 4XB",
    "wof:placetype": "postalcode"
  },
  "geometry": {"coordinates":[-3.46162,53.317591],"type":"Point"}
}
