{
  "type": "Feature",
  "properties": {
    "date:inception_lower":"1995-01-01",
    "date:inception_upper":"1995-01-31",
    "iso:country":"GB",
    "wof:name":"LL18 4XB",
    "wof:placetype":"postalcode"
},
  "geometry": {"coordinates":[-3.461573,53.317566],"type":"Point"}
}