{
  "type": "Feature",
  "properties": {
    "date:inception_lower":"2006-11-01",
    "date:inception_upper":"2006-11-30",
    "iso:country":"GB",
    "wof:name":"DY11 6SZ",
    "wof:placetype":"postalcode"
},
  "geometry": {"coordinates":[-2.255517,52.385003],"type":"Point"}
}