{
  "type": "Feature",
  "properties": {
    "date:inception_lower":"1980-01-01",
    "date:inception_upper":"1980-01-31",
    "iso:country":"GB",
    "wof:name":"NR33 9ND",
    "wof:placetype":"postalcode"
},
  "geometry": {"coordinates":[1.716286,52.472002],"type":"Point"}
}