{
  "type": "Feature",
  "properties": {
    "iso:country":"GB",
    "wof:name":"NR33 9ND",
    "wof:placetype":"postalcode"
},
  "geometry": {"coordinates":[1.71628571311737,52.47200201568809],"type":"Point"}
}