{
  "type": "Feature",
  "properties": {
    "iso:country":"GB",
    "wof:name":"SA10 6LJ",
    "wof:placetype":"postalcode"
},
  "geometry": {"coordinates":[-3.86017283871752,51.63245099738821],"type":"Point"}
}