{
  "type": "Feature",
  "properties": {
    "date:inception_lower": "1994-05-01",
    "date:inception_upper": "1994-05-01",
    "iso:country": "GB",
    "wof:name": "SA10 6LJ",
    "wof:placetype": "postalcode"
  },
  "geometry": {"coordinates":[-3.859773,51.632224],"type":"Point"}
}
