{
  "type": "Feature",
  "properties": {
    "date:inception_lower": "1980-01-01",
    "date:inception_upper": "1980-01-01",
    "iso:country": "GB",
    "wof:name": "BD9 6JL",
    "wof:placetype": "postalcode"
  },
  "geometry": {"coordinates":[-1.80814,53.814847],"type":"Point"}
}
