{
  "type": "Feature",
  "properties": {
    "iso:country":"GB",
    "wof:name":"BD9 6JL",
    "wof:placetype":"postalcode"
},
  "geometry": {"coordinates":[-1.80814024432976,53.81484678981109],"type":"Point"}
}