{
  "type": "Feature",
  "properties": {
    "iso:country":"GB",
    "wof:name":"M15 6SX",
    "wof:placetype":"postalcode"
},
  "geometry": {"coordinates":[-2.2363663242022,53.46419897605369],"type":"Point"}
}