{
  "type": "Feature",
  "properties": {
    "date:inception_lower": "1999-06-01",
    "date:inception_upper": "1999-06-01",
    "iso:country": "GB",
    "wof:name": "M15 6SX",
    "wof:placetype": "postalcode"
  },
  "geometry": {"coordinates":[-2.236366,53.464199],"type":"Point"}
}
