{
  "type": "Feature",
  "properties": {
    "iso:country": "GB",
    "wof:name": "CR3 0AX",
    "wof:placetype": "postalcode"
  },
  "geometry": {"coordinates":[-0.076464,51.305337],"type":"Point"}
}
