{
  "type": "Feature",
  "properties": {
    "iso:country": "GB",
    "wof:name": "KT1 3SL",
    "wof:placetype": "postalcode"
  },
  "geometry": {"coordinates":[-0.277792,51.412139],"type":"Point"}
}
