{
  "type": "Feature",
  "properties": {
    "iso:country":"GB",
    "wof:name":"CF83 1JW",
    "wof:placetype":"postalcode"
},
  "geometry": {"coordinates":[-3.21293476205683,51.57242418097488],"type":"Point"}
}