{
  "type": "Feature",
  "properties": {
    "date:inception_lower": "2000-06-01",
    "date:inception_upper": "2000-06-01",
    "iso:country": "GB",
    "wof:name": "ME19 4SZ",
    "wof:placetype": "postalcode"
  },
  "geometry": {"coordinates":[0.402228,51.272473],"type":"Point"}
}
