{
  "type": "Feature",
  "properties": {
    "iso:country":"GB",
    "wof:name":"ME19 4SZ",
    "wof:placetype":"postalcode"
},
  "geometry": {"coordinates":[0.40222780452572,51.27247262137206],"type":"Point"}
}