{
  "type": "Feature",
  "properties": {
    "iso:country":"GB",
    "wof:name":"CO15 1AG",
    "wof:placetype":"postalcode"
},
  "geometry": {"coordinates":[1.13632413494063,51.78273036269454],"type":"Point"}
}