{
  "type": "Feature",
  "properties": {
    "iso:country":"GB",
    "wof:name":"DN12 4AB",
    "wof:placetype":"postalcode"
},
  "geometry": {"coordinates":[-1.2457919745413,53.49066565641855],"type":"Point"}
}