{
  "type": "Feature",
  "properties": {
    "iso:country":"GB",
    "wof:name":"PR5 6SE",
    "wof:placetype":"postalcode"
},
  "geometry": {"coordinates":[-2.66106461456459,53.72890365348704],"type":"Point"}
}