{
  "type": "Feature",
  "properties": {
    "iso:country": "GB",
    "wof:name": "SA70 8LD",
    "wof:placetype": "postalcode"
  },
  "geometry": {"coordinates":[-4.774754,51.661137],"type":"Point"}
}
