{
  "type": "Feature",
  "properties": {
    "iso:country":"GB",
    "wof:name":"SR8 4JD",
    "wof:placetype":"postalcode"
},
  "geometry": {"coordinates":[-1.31768886454718,54.76138654633881],"type":"Point"}
}