{
  "type": "Feature",
  "properties": {
    "iso:country": "GB",
    "wof:name": "TR19 7TU",
    "wof:placetype": "postalcode"
  },
  "geometry": {"coordinates":[-5.650685,50.162485],"type":"Point"}
}
