{
  "type": "Feature",
  "properties": {
    "iso:country":"GB",
    "wof:name":"TR19 7TU",
    "wof:placetype":"postalcode"
},
  "geometry": {"coordinates":[-5.65068467338899,50.16248510230337],"type":"Point"}
}