{
  "type": "Feature",
  "properties": {
    "iso:country":"GB",
    "wof:name":"IP7 7LY",
    "wof:placetype":"postalcode"
},
  "geometry": {"coordinates":[0.9245228835243,52.14236030577499],"type":"Point"}
}