{
  "type": "Feature",
  "properties": {
    "iso:country": "GB",
    "wof:name": "IP7 7LY",
    "wof:placetype": "postalcode"
  },
  "geometry": {"coordinates":[0.924616,52.14241],"type":"Point"}
}
