{
  "type": "Feature",
  "properties": {
    "date:inception_lower": "1980-01-01",
    "date:inception_upper": "1980-01-01",
    "iso:country": "GB",
    "wof:name": "FK6 5JH",
    "wof:placetype": "postalcode"
  },
  "geometry": {"coordinates":[-4.028583,56.028216],"type":"Point"}
}
