{
  "type": "Feature",
  "properties": {
    "iso:country":"GB",
    "wof:name":"FK6 5JH",
    "wof:placetype":"postalcode"
},
  "geometry": {"coordinates":[-4.02859211481272,56.02822226988954],"type":"Point"}
}