{
  "type": "Feature",
  "properties": {
    "iso:country": "GB",
    "wof:name": "PL26 7ZA",
    "wof:placetype": "postalcode"
  },
  "geometry": {"coordinates":[-4.868551,50.369655],"type":"Point"}
}
