{
  "type": "Feature",
  "properties": {
    "date:inception_lower":"2007-03-01",
    "date:inception_upper":"2007-03-31",
    "iso:country":"GB",
    "wof:name":"PL26 7ZA",
    "wof:placetype":"postalcode"
},
  "geometry": {"coordinates":[-4.868551,50.369655],"type":"Point"}
}