{
  "type": "Feature",
  "properties": {
    "iso:country":"GB",
    "wof:name":"PL26 7ZA",
    "wof:placetype":"postalcode"
},
  "geometry": {"coordinates":[-4.86855083971585,50.36965543663643],"type":"Point"}
}