{
  "type": "Feature",
  "properties": {
    "date:inception_lower": "2005-02-01",
    "date:inception_upper": "2005-02-01",
    "iso:country": "GB",
    "wof:name": "CB7 9SB",
    "wof:placetype": "postalcode"
  },
  "geometry": {"coordinates":[0.263774,52.400907],"type":"Point"}
}
