{
  "type": "Feature",
  "properties": {
    "iso:country": "GB",
    "wof:name": "CB7 9SB",
    "wof:placetype": "postalcode"
  },
  "geometry": {"coordinates":[0.263489,52.400795],"type":"Point"}
}
