{
  "type": "Feature",
  "properties": {
    "iso:country":"GB",
    "wof:name":"CB7 9SB",
    "wof:placetype":"postalcode"
},
  "geometry": {"coordinates":[0.26375065754433,52.40089045044213],"type":"Point"}
}