{
  "type": "Feature",
  "properties": {
    "date:inception_lower":"1999-12-01",
    "date:inception_upper":"1999-12-31",
    "iso:country":"GB",
    "wof:name":"PR6 0HJ",
    "wof:placetype":"postalcode"
},
  "geometry": {"coordinates":[-2.62537,53.658456],"type":"Point"}
}