{
  "type": "Feature",
  "properties": {
    "iso:country":"GB",
    "wof:name":"PR6 0HJ",
    "wof:placetype":"postalcode"
},
  "geometry": {"coordinates":[-2.62536994583936,53.65845648935041],"type":"Point"}
}