{
  "type": "Feature",
  "properties": {
    "date:inception_lower": "1980-01-01",
    "date:inception_upper": "1980-01-01",
    "iso:country": "GB",
    "wof:name": "OL4 5DB",
    "wof:placetype": "postalcode"
  },
  "geometry": {"coordinates":[-2.071479,53.536562],"type":"Point"}
}
