{
  "type": "Feature",
  "properties": {
    "iso:country":"GB",
    "wof:name":"HD9 6NB",
    "wof:placetype":"postalcode"
},
  "geometry": {"coordinates":[-1.78924708490651,53.60833142165318],"type":"Point"}
}