{
  "type": "Feature",
  "properties": {
    "date:inception_lower": "2022-10-01",
    "date:inception_upper": "2022-10-01",
    "iso:country": "GB",
    "wof:name": "DL14 0BZ",
    "wof:placetype": "postalcode"
  },
  "geometry": {"coordinates":[-1.711201,54.655607],"type":"Point"}
}
