{
  "type": "Feature",
  "properties": {
    "iso:country": "GB",
    "wof:name": "RM5 3BY",
    "wof:placetype": "postalcode"
  },
  "geometry": {"coordinates":[0.173025,51.607043],"type":"Point"}
}
