{
  "type": "Feature",
  "properties": {
    "iso:country":"GB",
    "wof:name":"BB5 2BS",
    "wof:placetype":"postalcode"
},
  "geometry": {"coordinates":[-2.35535078015476,53.74735005866082],"type":"Point"}
}