{
  "type": "Feature",
  "properties": {
    "iso:country":"GB",
    "wof:name":"E14 6FE",
    "wof:placetype":"postalcode"
},
  "geometry": {"coordinates":[-0.01546203235905,51.51715254370794],"type":"Point"}
}