{
  "type": "Feature",
  "properties": {
    "iso:country":"GB",
    "wof:name":"NE35 9DP",
    "wof:placetype":"postalcode"
},
  "geometry": {"coordinates":[-1.45522577924778,54.94841709574769],"type":"Point"}
}