{
  "type": "Feature",
  "properties": {
    "iso:country":"GB",
    "wof:name":"NN3 2DA",
    "wof:placetype":"postalcode"
},
  "geometry": {"coordinates":[-0.85777720008347,52.25319244015808],"type":"Point"}
}