{
  "type": "Feature",
  "properties": {
    "iso:country":"GB",
    "wof:name":"BD20 7DY",
    "wof:placetype":"postalcode"
},
  "geometry": {"coordinates":[-1.98809154797693,53.9051384974938],"type":"Point"}
}