{
  "type": "Feature",
  "properties": {
    "iso:country":"GB",
    "wof:name":"ML6 6AS",
    "wof:placetype":"postalcode"
},
  "geometry": {"coordinates":[-3.97252229676873,55.86929380248539],"type":"Point"}
}