{
  "type": "Feature",
  "properties": {
    "date:inception_lower": "2000-10-01",
    "date:inception_upper": "2000-10-01",
    "iso:country": "GB",
    "wof:name": "GL52 9HZ",
    "wof:placetype": "postalcode"
  },
  "geometry": {"coordinates":[-2.046611,51.946123],"type":"Point"}
}
