{
  "type": "Feature",
  "properties": {
    "iso:country": "GB",
    "wof:name": "GL52 9HZ",
    "wof:placetype": "postalcode"
  },
  "geometry": {"coordinates":[-2.046611,51.946123],"type":"Point"}
}
