{
  "type": "Feature",
  "properties": {
    "iso:country": "GB",
    "wof:name": "CR3 5HR",
    "wof:placetype": "postalcode"
  },
  "geometry": {"coordinates":[-0.092411,51.291984],"type":"Point"}
}
