{
  "type": "Feature",
  "properties": {
    "iso:country":"GB",
    "wof:name":"WF14 0JB",
    "wof:placetype":"postalcode"
},
  "geometry": {"coordinates":[-1.692271076822,53.6840810480286],"type":"Point"}
}