{
  "type": "Feature",
  "properties": {
    "date:inception_lower":"2002-06-01",
    "date:inception_upper":"2002-06-30",
    "iso:country":"GB",
    "wof:name":"WF14 0JB",
    "wof:placetype":"postalcode"
},
  "geometry": {"coordinates":[-1.692271,53.684081],"type":"Point"}
}