{
  "type": "Feature",
  "properties": {
    "iso:country": "GB",
    "wof:name": "WF14 0JB",
    "wof:placetype": "postalcode"
  },
  "geometry": {"coordinates":[-1.692271,53.684081],"type":"Point"}
}
