{
  "type": "Feature",
  "properties": {
    "date:inception_lower": "1993-01-01",
    "date:inception_upper": "1993-01-01",
    "iso:country": "GB",
    "wof:name": "CR4 2NQ",
    "wof:placetype": "postalcode"
  },
  "geometry": {"coordinates":[-0.154801,51.41175],"type":"Point"}
}
