{
  "type": "Feature",
  "properties": {
    "iso:country": "GB",
    "wof:name": "DH4 4SF",
    "wof:placetype": "postalcode"
  },
  "geometry": {"coordinates":[-1.479395,54.859827],"type":"Point"}
}
