{
  "type": "Feature",
  "properties": {
    "iso:country": "GB",
    "wof:name": "N12 8PL",
    "wof:placetype": "postalcode"
  },
  "geometry": {"coordinates":[-0.184415,51.610245],"type":"Point"}
}
