{
  "type": "Feature",
  "properties": {
    "iso:country": "GB",
    "wof:name": "PR4 1UH",
    "wof:placetype": "postalcode"
  },
  "geometry": {"coordinates":[-2.869545,53.744063],"type":"Point"}
}
