{
  "type": "Feature",
  "properties": {
    "iso:country": "GB",
    "wof:name": "NN12 8PW",
    "wof:placetype": "postalcode"
  },
  "geometry": {"coordinates":[-1.124398,52.118354],"type":"Point"}
}
