{
  "type": "Feature",
  "properties": {
    "iso:country":"GB",
    "wof:name":"BR5 2AT",
    "wof:placetype":"postalcode"
},
  "geometry": {"coordinates":[0.10104391021688,51.3880178352418],"type":"Point"}
}