{
  "type": "Feature",
  "properties": {
    "iso:country":"GB",
    "wof:name":"PR5 8JE",
    "wof:placetype":"postalcode"
},
  "geometry": {"coordinates":[-2.64717205733741,53.71255799464721],"type":"Point"}
}