{
  "type": "Feature",
  "properties": {
    "date:inception_lower":"2009-08-01",
    "date:inception_upper":"2009-08-31",
    "iso:country":"GB",
    "wof:name":"PA16 7NY",
    "wof:placetype":"postalcode"
},
  "geometry": {"coordinates":[-4.794244,55.947053],"type":"Point"}
}