{
  "type": "Feature",
  "properties": {
    "iso:country":"GB",
    "wof:name":"PA16 7NY",
    "wof:placetype":"postalcode"
},
  "geometry": {"coordinates":[-4.7942436347524,55.94705285195419],"type":"Point"}
}