{
  "type": "Feature",
  "properties": {
    "date:inception_lower":"1980-01-01",
    "date:inception_upper":"1980-01-31",
    "iso:country":"GB",
    "wof:name":"SA9 2WB",
    "wof:placetype":"postalcode"
},
  "geometry": {"coordinates":[-3.825536,51.804575],"type":"Point"}
}