{
  "type": "Feature",
  "properties": {
    "iso:country":"GB",
    "wof:name":"SA9 2WB",
    "wof:placetype":"postalcode"
},
  "geometry": {"coordinates":[-3.82549313410382,51.80458435294589],"type":"Point"}
}