{
  "type": "Feature",
  "properties": {
    "iso:country": "GB",
    "wof:name": "M28 2SW",
    "wof:placetype": "postalcode"
  },
  "geometry": {"coordinates":[-2.363418,53.506395],"type":"Point"}
}
