{
  "type": "Feature",
  "properties": {
    "iso:country":"GB",
    "wof:name":"M28 2SW",
    "wof:placetype":"postalcode"
},
  "geometry": {"coordinates":[-2.36341768051627,53.50639535514026],"type":"Point"}
}