{
  "type": "Feature",
  "properties": {
    "date:inception_lower": "1980-01-01",
    "date:inception_upper": "1980-01-01",
    "iso:country": "GB",
    "wof:name": "ML1 3JD",
    "wof:placetype": "postalcode"
  },
  "geometry": {"coordinates":[-3.9971,55.790414],"type":"Point"}
}
