{
  "type": "Feature",
  "properties": {
    "iso:country":"GB",
    "wof:name":"LS12 2BA",
    "wof:placetype":"postalcode"
},
  "geometry": {"coordinates":[-1.58860937246169,53.80133455608005],"type":"Point"}
}