{
  "type": "Feature",
  "properties": {
    "date:inception_lower": "1996-06-01",
    "date:inception_upper": "1996-06-01",
    "iso:country": "GB",
    "wof:name": "AB43 8QA",
    "wof:placetype": "postalcode"
  },
  "geometry": {"coordinates":[-1.978248,57.587812],"type":"Point"}
}
