{
  "type": "Feature",
  "properties": {
    "iso:country":"GB",
    "wof:name":"DA2 7RL",
    "wof:placetype":"postalcode"
},
  "geometry": {"coordinates":[0.2319579933138,51.42055307313786],"type":"Point"}
}