{
  "type": "Feature",
  "properties": {
    "iso:country": "GB",
    "wof:name": "E6 1LS",
    "wof:placetype": "postalcode"
  },
  "geometry": {"coordinates":[0.047938,51.535658],"type":"Point"}
}
