{
  "type": "Feature",
  "properties": {
    "iso:country":"GB",
    "wof:name":"E6 1LS",
    "wof:placetype":"postalcode"
},
  "geometry": {"coordinates":[0.04793750584868,51.53565775860033],"type":"Point"}
}