{
  "type": "Feature",
  "properties": {
    "iso:country": "GB",
    "wof:name": "LE65 1BJ",
    "wof:placetype": "postalcode"
  },
  "geometry": {"coordinates":[-1.46907,52.745654],"type":"Point"}
}
