{
  "type": "Feature",
  "properties": {
    "date:inception_lower": "1980-01-01",
    "date:inception_upper": "1980-01-01",
    "iso:country": "GB",
    "wof:name": "DT9 6SD",
    "wof:placetype": "postalcode"
  },
  "geometry": {"coordinates":[-2.585557,50.929698],"type":"Point"}
}
