{
  "type": "Feature",
  "properties": {
    "iso:country":"GB",
    "wof:name":"DT9 6SD",
    "wof:placetype":"postalcode"
},
  "geometry": {"coordinates":[-2.58554363172816,50.92978565057621],"type":"Point"}
}