{
  "type": "Feature",
  "properties": {
    "iso:country":"GB",
    "wof:name":"N16 0NH",
    "wof:placetype":"postalcode"
},
  "geometry": {"coordinates":[-0.07736085937393,51.56179739083165],"type":"Point"}
}