{
  "type": "Feature",
  "properties": {
    "iso:country":"GB",
    "wof:name":"SS3 0DD",
    "wof:placetype":"postalcode"
},
  "geometry": {"coordinates":[0.80700783530342,51.55248452999926],"type":"Point"}
}