{
  "type": "Feature",
  "properties": {
    "iso:country":"GB",
    "wof:name":"KT9 2NF",
    "wof:placetype":"postalcode"
},
  "geometry": {"coordinates":[-0.30727937573224,51.34764229680854],"type":"Point"}
}