{
  "type": "Feature",
  "properties": {
    "date:inception_lower": "1981-06-01",
    "date:inception_upper": "1981-06-01",
    "iso:country": "GB",
    "wof:name": "RH11 8JR",
    "wof:placetype": "postalcode"
  },
  "geometry": {"coordinates":[-0.217397,51.105337],"type":"Point"}
}
