{
  "type": "Feature",
  "properties": {
    "iso:country":"GB",
    "wof:name":"RH11 8JR",
    "wof:placetype":"postalcode"
},
  "geometry": {"coordinates":[-0.21739677725229,51.10533729097195],"type":"Point"}
}