{
  "type": "Feature",
  "properties": {
    "date:inception_lower": "1980-01-01",
    "date:inception_upper": "1980-01-01",
    "iso:country": "GB",
    "wof:name": "SA43 1SJ",
    "wof:placetype": "postalcode"
  },
  "geometry": {"coordinates":[-4.583328,52.107856],"type":"Point"}
}
