{
  "type": "Feature",
  "properties": {
    "iso:country": "GB",
    "wof:name": "SA43 1SJ",
    "wof:placetype": "postalcode"
  },
  "geometry": {"coordinates":[-4.583328,52.107856],"type":"Point"}
}
