{
  "type": "Feature",
  "properties": {
    "iso:country":"GB",
    "wof:name":"CF72 8SX",
    "wof:placetype":"postalcode"
},
  "geometry": {"coordinates":[-3.37808245323547,51.52606335400107],"type":"Point"}
}