{
  "type": "Feature",
  "properties": {
    "iso:country": "GB",
    "wof:name": "CF72 8SX",
    "wof:placetype": "postalcode"
  },
  "geometry": {"coordinates":[-3.378082,51.526063],"type":"Point"}
}
