{
  "type": "Feature",
  "properties": {
    "date:inception_lower":"2004-06-01",
    "date:inception_upper":"2004-06-30",
    "iso:country":"GB",
    "wof:name":"CF72 8SX",
    "wof:placetype":"postalcode"
},
  "geometry": {"coordinates":[-3.378082,51.526063],"type":"Point"}
}