{
  "type": "Feature",
  "properties": {
    "iso:country":"GB",
    "wof:name":"WF8 1SY",
    "wof:placetype":"postalcode"
},
  "geometry": {"coordinates":[-1.30327117360768,53.70508339772778],"type":"Point"}
}