{
  "type": "Feature",
  "properties": {
    "iso:country": "GB",
    "wof:name": "BD18 2BT",
    "wof:placetype": "postalcode"
  },
  "geometry": {"coordinates":[-1.773279,53.82994],"type":"Point"}
}
