{
  "type": "Feature",
  "properties": {
    "iso:country":"GB",
    "wof:name":"BD18 2BT",
    "wof:placetype":"postalcode"
},
  "geometry": {"coordinates":[-1.7732785874998,53.82993970834388],"type":"Point"}
}