{
  "type": "Feature",
  "properties": {
    "iso:country":"GB",
    "wof:name":"DY8 3XX",
    "wof:placetype":"postalcode"
},
  "geometry": {"coordinates":[-2.15312608743935,52.45316255933145],"type":"Point"}
}