{
  "type": "Feature",
  "properties": {
    "iso:country": "GB",
    "wof:name": "CT19 6QH",
    "wof:placetype": "postalcode"
  },
  "geometry": {"coordinates":[1.194774,51.085786],"type":"Point"}
}
