{
  "type": "Feature",
  "properties": {
    "iso:country":"GB",
    "wof:name":"CT19 6QH",
    "wof:placetype":"postalcode"
},
  "geometry": {"coordinates":[1.19477374555953,51.0857858222607],"type":"Point"}
}