{
  "type": "Feature",
  "properties": {
    "date:inception_lower": "1981-06-01",
    "date:inception_upper": "1981-06-01",
    "iso:country": "GB",
    "wof:name": "RG6 4XA",
    "wof:placetype": "postalcode"
  },
  "geometry": {"coordinates":[-0.927177,51.422705],"type":"Point"}
}
