{
  "type": "Feature",
  "properties": {
    "iso:country":"GB",
    "wof:name":"DT1 1RS",
    "wof:placetype":"postalcode"
},
  "geometry": {"coordinates":[-2.44396066628854,50.71430970218792],"type":"Point"}
}