{
  "type": "Feature",
  "properties": {
    "iso:country":"GB",
    "wof:name":"UB9 6DJ",
    "wof:placetype":"postalcode"
},
  "geometry": {"coordinates":[-0.4854766353837,51.59998397614491],"type":"Point"}
}