{
  "type": "Feature",
  "properties": {
    "iso:country":"GB",
    "wof:name":"B45 9EL",
    "wof:placetype":"postalcode"
},
  "geometry": {"coordinates":[-2.03071115614366,52.39081309380497],"type":"Point"}
}