{
  "type": "Feature",
  "properties": {
    "iso:country": "GB",
    "wof:name": "CA7 9ND",
    "wof:placetype": "postalcode"
  },
  "geometry": {"coordinates":[-3.147689,54.81716],"type":"Point"}
}
