{
  "type": "Feature",
  "properties": {
    "iso:country":"GB",
    "wof:name":"LL11 2AY",
    "wof:placetype":"postalcode"
},
  "geometry": {"coordinates":[-3.00571671059258,53.04923168654067],"type":"Point"}
}