{
  "type": "Feature",
  "properties": {
    "date:inception_lower": "2013-09-01",
    "date:inception_upper": "2013-09-01",
    "iso:country": "GB",
    "wof:name": "LL11 2AY",
    "wof:placetype": "postalcode"
  },
  "geometry": {"coordinates":[-3.005717,53.049232],"type":"Point"}
}
