{
  "type": "Feature",
  "properties": {
    "iso:country": "GB",
    "wof:name": "LL11 2AY",
    "wof:placetype": "postalcode"
  },
  "geometry": {"coordinates":[-3.005717,53.049232],"type":"Point"}
}
