{
  "type": "Feature",
  "properties": {
    "iso:country":"GB",
    "wof:name":"W13 9QX",
    "wof:placetype":"postalcode"
},
  "geometry": {"coordinates":[-0.31467954231557,51.50820104798842],"type":"Point"}
}