{
  "type": "Feature",
  "properties": {
    "iso:country":"GB",
    "wof:name":"LA2 8SB",
    "wof:placetype":"postalcode"
},
  "geometry": {"coordinates":[-2.63483784868331,54.11282150375953],"type":"Point"}
}