{
  "type": "Feature",
  "properties": {
    "iso:country":"GB",
    "wof:name":"SO50 5GB",
    "wof:placetype":"postalcode"
},
  "geometry": {"coordinates":[-1.3618550721504,50.96977193623705],"type":"Point"}
}