{
  "type": "Feature",
  "properties": {
    "date:inception_lower":"1980-01-01",
    "date:inception_upper":"1980-01-31",
    "iso:country":"GB",
    "wof:name":"PR8 1DH",
    "wof:placetype":"postalcode"
},
  "geometry": {"coordinates":[-3.00635,53.647042],"type":"Point"}
}