{
  "type": "Feature",
  "properties": {
    "iso:country": "GB",
    "wof:name": "NR29 3PF",
    "wof:placetype": "postalcode"
  },
  "geometry": {"coordinates":[1.716126,52.680083],"type":"Point"}
}
