{
  "type": "Feature",
  "properties": {
    "iso:country": "GB",
    "wof:name": "G66 8DE",
    "wof:placetype": "postalcode"
  },
  "geometry": {"coordinates":[-4.159611,55.964867],"type":"Point"}
}
