{
  "type": "Feature",
  "properties": {
    "iso:country":"GB",
    "wof:name":"HS1 2HT",
    "wof:placetype":"postalcode"
},
  "geometry": {"coordinates":[-6.38364015934012,58.21498098687427],"type":"Point"}
}