{
  "type": "Feature",
  "properties": {
    "iso:country":"GB",
    "wof:name":"SE1 7TP",
    "wof:placetype":"postalcode"
},
  "geometry": {"coordinates":[-0.12373883389503,51.48795531468117],"type":"Point"}
}