{
  "type": "Feature",
  "properties": {
    "date:inception_lower": "1986-01-01",
    "date:inception_upper": "1986-01-01",
    "iso:country": "GB",
    "wof:name": "SO41 6FU",
    "wof:placetype": "postalcode"
  },
  "geometry": {"coordinates":[-1.638791,50.779246],"type":"Point"}
}
