{
  "type": "Feature",
  "properties": {
    "iso:country":"GB",
    "wof:name":"SO41 6FU",
    "wof:placetype":"postalcode"
},
  "geometry": {"coordinates":[-1.63879134084766,50.77924553983925],"type":"Point"}
}