{
  "type": "Feature",
  "properties": {
    "iso:country":"GB",
    "wof:name":"WS15 4HN",
    "wof:placetype":"postalcode"
},
  "geometry": {"coordinates":[-1.85352988582246,52.73128891134203],"type":"Point"}
}