{
  "type": "Feature",
  "properties": {
    "date:inception_lower": "1980-01-01",
    "date:inception_upper": "1980-01-01",
    "iso:country": "GB",
    "wof:name": "WS15 4HN",
    "wof:placetype": "postalcode"
  },
  "geometry": {"coordinates":[-1.85353,52.731289],"type":"Point"}
}
