{
  "type": "Feature",
  "properties": {
    "date:inception_lower": "2020-06-01",
    "date:inception_upper": "2020-06-01",
    "iso:country": "GB",
    "wof:name": "M3 6GJ",
    "wof:placetype": "postalcode"
  },
  "geometry": {"coordinates":[-2.265054,53.485233],"type":"Point"}
}
