{
  "type": "Feature",
  "properties": {
    "iso:country":"GB",
    "wof:name":"PR9 9FS",
    "wof:placetype":"postalcode"
},
  "geometry": {"coordinates":[-2.95999151608709,53.67473894706436],"type":"Point"}
}