{
  "type": "Feature",
  "properties": {
    "iso:country": "GB",
    "wof:name": "PR9 9FS",
    "wof:placetype": "postalcode"
  },
  "geometry": {"coordinates":[-2.959991,53.674739],"type":"Point"}
}
