{
  "type": "Feature",
  "properties": {
    "date:inception_lower": "1980-01-01",
    "date:inception_upper": "1980-01-01",
    "iso:country": "GB",
    "wof:name": "DL15 9AT",
    "wof:placetype": "postalcode"
  },
  "geometry": {"coordinates":[-1.678165,54.742847],"type":"Point"}
}
