{
  "type": "Feature",
  "properties": {
    "iso:country":"GB",
    "wof:name":"DL15 9AT",
    "wof:placetype":"postalcode"
},
  "geometry": {"coordinates":[-1.67815428670999,54.742837650214],"type":"Point"}
}