{
  "type": "Feature",
  "properties": {
    "iso:country": "GB",
    "wof:name": "PL4 9HU",
    "wof:placetype": "postalcode"
  },
  "geometry": {"coordinates":[-4.126131,50.370865],"type":"Point"}
}
