{
  "type": "Feature",
  "properties": {
    "iso:country":"GB",
    "wof:name":"PL4 9HU",
    "wof:placetype":"postalcode"
},
  "geometry": {"coordinates":[-4.12613068844155,50.37086480418704],"type":"Point"}
}