{
  "type": "Feature",
  "properties": {
    "iso:country":"GB",
    "wof:name":"SE26 5LD",
    "wof:placetype":"postalcode"
},
  "geometry": {"coordinates":[-0.0443541843725,51.42370933448426],"type":"Point"}
}