{
  "type": "Feature",
  "properties": {
    "date:inception_lower":"1980-01-01",
    "date:inception_upper":"1980-01-31",
    "iso:country":"GB",
    "wof:name":"SE26 5LD",
    "wof:placetype":"postalcode"
},
  "geometry": {"coordinates":[-0.044354,51.423709],"type":"Point"}
}