{
  "type": "Feature",
  "properties": {
    "iso:country": "GB",
    "wof:name": "N1P 1DQ",
    "wof:placetype": "postalcode"
  },
  "geometry": {"coordinates":[-0.103385,51.53905],"type":"Point"}
}
