{
  "type": "Feature",
  "properties": {
    "iso:country":"GB",
    "wof:name":"DL8 4NS",
    "wof:placetype":"postalcode"
},
  "geometry": {"coordinates":[-1.80443133236109,54.28451439776092],"type":"Point"}
}