{
  "type": "Feature",
  "properties": {
    "iso:country":"GB",
    "wof:name":"WF15 8DH",
    "wof:placetype":"postalcode"
},
  "geometry": {"coordinates":[-1.72427049536927,53.71087165746195],"type":"Point"}
}