{
  "type": "Feature",
  "properties": {
    "iso:country": "GB",
    "wof:name": "NE61 3SJ",
    "wof:placetype": "postalcode"
  },
  "geometry": {"coordinates":[-1.819202,55.180004],"type":"Point"}
}
