{
  "type": "Feature",
  "properties": {
    "iso:country": "GB",
    "wof:name": "HX4 8PW",
    "wof:placetype": "postalcode"
  },
  "geometry": {"coordinates":[-1.89123,53.686665],"type":"Point"}
}
