{
  "type": "Feature",
  "properties": {
    "iso:country":"GB",
    "wof:name":"HX4 8PW",
    "wof:placetype":"postalcode"
},
  "geometry": {"coordinates":[-1.89122983439769,53.68666455775688],"type":"Point"}
}