{
  "type": "Feature",
  "properties": {
    "date:inception_lower": "2019-05-01",
    "date:inception_upper": "2019-05-01",
    "iso:country": "GB",
    "wof:name": "M3 6JP",
    "wof:placetype": "postalcode"
  },
  "geometry": {"coordinates":[-2.265061,53.486464],"type":"Point"}
}
