{
  "type": "Feature",
  "properties": {
    "iso:country":"GB",
    "wof:name":"EH19 3BJ",
    "wof:placetype":"postalcode"
},
  "geometry": {"coordinates":[-3.09860337883382,55.87586768168285],"type":"Point"}
}