{
  "type": "Feature",
  "properties": {
    "iso:country": "GB",
    "wof:name": "EH19 3BJ",
    "wof:placetype": "postalcode"
  },
  "geometry": {"coordinates":[-3.098603,55.875868],"type":"Point"}
}
