{
  "type": "Feature",
  "properties": {
    "date:inception_lower": "2021-10-01",
    "date:inception_upper": "2021-10-01",
    "iso:country": "GB",
    "wof:name": "CH41 8AW",
    "wof:placetype": "postalcode"
  },
  "geometry": {"coordinates":[-3.053666,53.403828],"type":"Point"}
}
