{
  "type": "Feature",
  "properties": {
    "iso:country":"GB",
    "wof:name":"OX18 3PR",
    "wof:placetype":"postalcode"
},
  "geometry": {"coordinates":[-1.56583435232555,51.76511759777928],"type":"Point"}
}