{
  "type": "Feature",
  "properties": {
    "iso:country":"GB",
    "wof:name":"S26 6SD",
    "wof:placetype":"postalcode"
},
  "geometry": {"coordinates":[-1.25763444613788,53.3422636065055],"type":"Point"}
}