{
  "type": "Feature",
  "properties": {
    "iso:country": "GB",
    "wof:name": "PE28 5AL",
    "wof:placetype": "postalcode"
  },
  "geometry": {"coordinates":[-0.313256,52.377302],"type":"Point"}
}
