{
  "type": "Feature",
  "properties": {
    "iso:country":"GB",
    "wof:name":"SO50 5PF",
    "wof:placetype":"postalcode"
},
  "geometry": {"coordinates":[-1.35839112183829,50.95966348759437],"type":"Point"}
}