{
  "type": "Feature",
  "properties": {
    "iso:country": "GB",
    "wof:name": "SO50 5PF",
    "wof:placetype": "postalcode"
  },
  "geometry": {"coordinates":[-1.358352,50.959646],"type":"Point"}
}
