{
  "type": "Feature",
  "properties": {
    "date:inception_lower":"2013-05-01",
    "date:inception_upper":"2013-05-31",
    "iso:country":"GB",
    "wof:name":"SO50 5PF",
    "wof:placetype":"postalcode"
},
  "geometry": {"coordinates":[-1.358352,50.959646],"type":"Point"}
}