{
  "type": "Feature",
  "properties": {
    "date:inception_lower":"1980-01-01",
    "date:inception_upper":"1980-01-31",
    "iso:country":"GB",
    "wof:name":"EH14 7DF",
    "wof:placetype":"postalcode"
},
  "geometry": {"coordinates":[-3.34513,55.890538],"type":"Point"}
}