{
  "type": "Feature",
  "properties": {
    "iso:country":"GB",
    "wof:name":"NE6 4NY",
    "wof:placetype":"postalcode"
},
  "geometry": {"coordinates":[-1.55756547367441,54.98677245015366],"type":"Point"}
}