{
  "type": "Feature",
  "properties": {
    "iso:country":"GB",
    "wof:name":"BL3 5DN",
    "wof:placetype":"postalcode"
},
  "geometry": {"coordinates":[-2.44302056871559,53.57368368582742],"type":"Point"}
}