{
  "type": "Feature",
  "properties": {
    "iso:country":"GB",
    "wof:name":"B45 8UX",
    "wof:placetype":"postalcode"
},
  "geometry": {"coordinates":[-2.00136609543118,52.38167420760279],"type":"Point"}
}