{
  "type": "Feature",
  "properties": {
    "iso:country": "GB",
    "wof:name": "TS27 4AU",
    "wof:placetype": "postalcode"
  },
  "geometry": {"coordinates":[-1.276762,54.740956],"type":"Point"}
}
