{
  "type": "Feature",
  "properties": {
    "date:inception_lower": "1980-01-01",
    "date:inception_upper": "1980-01-01",
    "iso:country": "GB",
    "wof:name": "TS27 4AU",
    "wof:placetype": "postalcode"
  },
  "geometry": {"coordinates":[-1.276762,54.740956],"type":"Point"}
}
