{
  "type": "Feature",
  "properties": {
    "date:inception_lower":"2012-06-01",
    "date:inception_upper":"2012-06-30",
    "iso:country":"GB",
    "wof:name":"GU7 1AE",
    "wof:placetype":"postalcode"
},
  "geometry": {"coordinates":[-0.609825,51.185893],"type":"Point"}
}