{
  "type": "Feature",
  "properties": {
    "iso:country":"GB",
    "wof:name":"PR1 8TY",
    "wof:placetype":"postalcode"
},
  "geometry": {"coordinates":[-2.72061406671051,53.76326385044438],"type":"Point"}
}