{
  "type": "Feature",
  "properties": {
    "date:inception_lower":"1980-01-01",
    "date:inception_upper":"1980-01-31",
    "iso:country":"GB",
    "wof:name":"L36 8BG",
    "wof:placetype":"postalcode"
},
  "geometry": {"coordinates":[-2.841247,53.422818],"type":"Point"}
}