{
  "type": "Feature",
  "properties": {
    "date:inception_lower": "1980-01-01",
    "date:inception_upper": "1980-01-01",
    "iso:country": "GB",
    "wof:name": "IP3 8PJ",
    "wof:placetype": "postalcode"
  },
  "geometry": {"coordinates":[1.20135,52.049803],"type":"Point"}
}
