{
  "type": "Feature",
  "properties": {
    "iso:country": "GB",
    "wof:name": "IP3 8PJ",
    "wof:placetype": "postalcode"
  },
  "geometry": {"coordinates":[1.20135,52.049803],"type":"Point"}
}
