{
  "type": "Feature",
  "properties": {
    "iso:country":"GB",
    "wof:name":"PR4 4GA",
    "wof:placetype":"postalcode"
},
  "geometry": {"coordinates":[-2.79964701532901,53.70253184686882],"type":"Point"}
}