{
  "type": "Feature",
  "properties": {
    "date:inception_lower": "1980-01-01",
    "date:inception_upper": "1980-01-01",
    "iso:country": "GB",
    "wof:name": "PR4 4GA",
    "wof:placetype": "postalcode"
  },
  "geometry": {"coordinates":[-2.799572,53.70255],"type":"Point"}
}
