{
  "type": "Feature",
  "properties": {
    "iso:country":"GB",
    "wof:name":"SS7 4EQ",
    "wof:placetype":"postalcode"
},
  "geometry": {"coordinates":[0.54481215459617,51.56776606879559],"type":"Point"}
}