{
  "type": "Feature",
  "properties": {
    "date:inception_lower":"2007-11-01",
    "date:inception_upper":"2007-11-30",
    "iso:country":"GB",
    "wof:name":"SS7 4EQ",
    "wof:placetype":"postalcode"
},
  "geometry": {"coordinates":[0.544812,51.567766],"type":"Point"}
}