{
  "type": "Feature",
  "properties": {
    "iso:country": "GB",
    "wof:name": "SS7 4EQ",
    "wof:placetype": "postalcode"
  },
  "geometry": {"coordinates":[0.544812,51.567766],"type":"Point"}
}
