{
  "type": "Feature",
  "properties": {
    "iso:country": "GB",
    "wof:name": "SG18 8NG",
    "wof:placetype": "postalcode"
  },
  "geometry": {"coordinates":[-0.244203,52.087306],"type":"Point"}
}
