{
  "type": "Feature",
  "properties": {
    "date:inception_lower": "1980-01-01",
    "date:inception_upper": "1980-01-01",
    "iso:country": "GB",
    "wof:name": "BS23 1QP",
    "wof:placetype": "postalcode"
  },
  "geometry": {"coordinates":[-2.976872,51.347958],"type":"Point"}
}
