{
  "type": "Feature",
  "properties": {
    "iso:country":"GB",
    "wof:name":"BS23 1QP",
    "wof:placetype":"postalcode"
},
  "geometry": {"coordinates":[-2.9768666109797,51.34800644823687],"type":"Point"}
}