{
  "type": "Feature",
  "properties": {
    "date:inception_lower": "1986-04-01",
    "date:inception_upper": "1986-04-01",
    "iso:country": "GB",
    "wof:name": "SA20 0BR",
    "wof:placetype": "postalcode"
  },
  "geometry": {"coordinates":[-3.802502,51.994426],"type":"Point"}
}
