{
  "type": "Feature",
  "properties": {
    "iso:country": "GB",
    "wof:name": "RG10 0JY",
    "wof:placetype": "postalcode"
  },
  "geometry": {"coordinates":[-0.809879,51.485633],"type":"Point"}
}
