{
  "type": "Feature",
  "properties": {
    "iso:country":"GB",
    "wof:name":"BA3 3DL",
    "wof:placetype":"postalcode"
},
  "geometry": {"coordinates":[-2.45863760165093,51.30395777236782],"type":"Point"}
}