{
  "type": "Feature",
  "properties": {
    "iso:country":"GB",
    "wof:name":"E4 9SA",
    "wof:placetype":"postalcode"
},
  "geometry": {"coordinates":[0.00511132959948,51.61500190945193],"type":"Point"}
}