{
  "type": "Feature",
  "properties": {
    "iso:country":"GB",
    "wof:name":"WF8 2NJ",
    "wof:placetype":"postalcode"
},
  "geometry": {"coordinates":[-1.29689765542541,53.70483944596053],"type":"Point"}
}