{
  "type": "Feature",
  "properties": {
    "iso:country": "GB",
    "wof:name": "EH30 9XB",
    "wof:placetype": "postalcode"
  },
  "geometry": {"coordinates":[-3.412203,55.986734],"type":"Point"}
}
