{
  "type": "Feature",
  "properties": {
    "iso:country":"GB",
    "wof:name":"EH30 9XB",
    "wof:placetype":"postalcode"
},
  "geometry": {"coordinates":[-3.41220313112829,55.98673434101443],"type":"Point"}
}