{
  "type": "Feature",
  "properties": {
    "iso:country":"GB",
    "wof:name":"B44 0UX",
    "wof:placetype":"postalcode"
},
  "geometry": {"coordinates":[-1.88181632708979,52.55470849373476],"type":"Point"}
}