{
  "type": "Feature",
  "properties": {
    "iso:country":"GB",
    "wof:name":"WF2 6JP",
    "wof:placetype":"postalcode"
},
  "geometry": {"coordinates":[-1.47927411680494,53.65172421803064],"type":"Point"}
}