{
  "type": "Feature",
  "properties": {
    "iso:country":"GB",
    "wof:name":"PR6 7NA",
    "wof:placetype":"postalcode"
},
  "geometry": {"coordinates":[-2.63396128437677,53.69349264068975],"type":"Point"}
}