{
  "type": "Feature",
  "properties": {
    "date:inception_lower": "2021-12-01",
    "date:inception_upper": "2021-12-01",
    "iso:country": "GB",
    "wof:name": "MK3 5RF",
    "wof:placetype": "postalcode"
  },
  "geometry": {"coordinates":[-0.731456,51.971859],"type":"Point"}
}
