{
  "type": "Feature",
  "properties": {
    "iso:country":"GB",
    "wof:name":"BR6 0RQ",
    "wof:placetype":"postalcode"
},
  "geometry": {"coordinates":[0.10384510193016,51.37544933656316],"type":"Point"}
}