{
  "type": "Feature",
  "properties": {
    "iso:country":"GB",
    "wof:name":"SW18 5EU",
    "wof:placetype":"postalcode"
},
  "geometry": {"coordinates":[-0.20354094050613,51.44423350335713],"type":"Point"}
}