{
  "type": "Feature",
  "properties": {
    "date:inception_lower":"1980-01-01",
    "date:inception_upper":"1980-01-31",
    "iso:country":"GB",
    "wof:name":"SW18 5EU",
    "wof:placetype":"postalcode"
},
  "geometry": {"coordinates":[-0.203541,51.444233],"type":"Point"}
}