{
  "type": "Feature",
  "properties": {
    "iso:country":"GB",
    "wof:name":"N15 6JU",
    "wof:placetype":"postalcode"
},
  "geometry": {"coordinates":[-0.07280960851427,51.57764845624354],"type":"Point"}
}