{
  "type": "Feature",
  "properties": {
    "iso:country":"GB",
    "wof:name":"RG4 7TY",
    "wof:placetype":"postalcode"
},
  "geometry": {"coordinates":[-1.02343350124223,51.49058857766569],"type":"Point"}
}