{
  "type": "Feature",
  "properties": {
    "iso:country": "GB",
    "wof:name": "RG4 7TY",
    "wof:placetype": "postalcode"
  },
  "geometry": {"coordinates":[-1.023413,51.49059],"type":"Point"}
}
