{
  "type": "Feature",
  "properties": {
    "iso:country":"GB",
    "wof:name":"PO30 1SS",
    "wof:placetype":"postalcode"
},
  "geometry": {"coordinates":[-1.29183071433498,50.70021910134437],"type":"Point"}
}