{
  "type": "Feature",
  "properties": {
    "date:inception_lower": "1980-01-01",
    "date:inception_upper": "1980-01-01",
    "iso:country": "GB",
    "wof:name": "SN3 6EU",
    "wof:placetype": "postalcode"
  },
  "geometry": {"coordinates":[-1.733575,51.548119],"type":"Point"}
}
