{
  "type": "Feature",
  "properties": {
    "iso:country": "GB",
    "wof:name": "DL2 2QD",
    "wof:placetype": "postalcode"
  },
  "geometry": {"coordinates":[-1.593758,54.505324],"type":"Point"}
}
