{
  "type": "Feature",
  "properties": {
    "date:inception_lower":"1980-01-01",
    "date:inception_upper":"1980-01-31",
    "iso:country":"GB",
    "wof:name":"DL2 2QD",
    "wof:placetype":"postalcode"
},
  "geometry": {"coordinates":[-1.593758,54.505324],"type":"Point"}
}