{
  "type": "Feature",
  "properties": {
    "iso:country":"GB",
    "wof:name":"DL2 2QD",
    "wof:placetype":"postalcode"
},
  "geometry": {"coordinates":[-1.59375801802501,54.50532428529068],"type":"Point"}
}