{
  "type": "Feature",
  "properties": {
    "iso:country":"GB",
    "wof:name":"WA4 4GE",
    "wof:placetype":"postalcode"
},
  "geometry": {"coordinates":[-2.6421466956782,53.33203735793663],"type":"Point"}
}