{
  "type": "Feature",
  "properties": {
    "iso:country":"GB",
    "wof:name":"CT4 6BX",
    "wof:placetype":"postalcode"
},
  "geometry": {"coordinates":[1.04864391365512,51.18317321258249],"type":"Point"}
}