{
  "type": "Feature",
  "properties": {
    "iso:country": "GB",
    "wof:name": "CT4 6BX",
    "wof:placetype": "postalcode"
  },
  "geometry": {"coordinates":[1.048644,51.183173],"type":"Point"}
}
