{
  "type": "Feature",
  "properties": {
    "iso:country": "GB",
    "wof:name": "HR5 3HW",
    "wof:placetype": "postalcode"
  },
  "geometry": {"coordinates":[-2.971568,52.1934],"type":"Point"}
}
