{
  "type": "Feature",
  "properties": {
    "iso:country":"GB",
    "wof:name":"PL17 7NS",
    "wof:placetype":"postalcode"
},
  "geometry": {"coordinates":[-4.39639070932802,50.54284534317448],"type":"Point"}
}