{
  "type": "Feature",
  "properties": {
    "date:inception_lower": "1980-01-01",
    "date:inception_upper": "1980-01-01",
    "iso:country": "GB",
    "wof:name": "LU7 0DN",
    "wof:placetype": "postalcode"
  },
  "geometry": {"coordinates":[-0.73373,51.938417],"type":"Point"}
}
