{
  "type": "Feature",
  "properties": {
    "iso:country":"GB",
    "wof:name":"LU7 0DN",
    "wof:placetype":"postalcode"
},
  "geometry": {"coordinates":[-0.7337305369449,51.93841719721713],"type":"Point"}
}