{
  "type": "Feature",
  "properties": {
    "iso:country": "GB",
    "wof:name": "CB11 3LP",
    "wof:placetype": "postalcode"
  },
  "geometry": {"coordinates":[0.270387,51.973186],"type":"Point"}
}
