{
  "type": "Feature",
  "properties": {
    "iso:country":"GB",
    "wof:name":"CB11 3LP",
    "wof:placetype":"postalcode"
},
  "geometry": {"coordinates":[0.27038669408295,51.97318620073719],"type":"Point"}
}