{
  "type": "Feature",
  "properties": {
    "iso:country":"GB",
    "wof:name":"TR18 3LA",
    "wof:placetype":"postalcode"
},
  "geometry": {"coordinates":[-5.55627215242342,50.1249151097342],"type":"Point"}
}