{
  "type": "Feature",
  "properties": {
    "iso:country":"GB",
    "wof:name":"IG11 9SD",
    "wof:placetype":"postalcode"
},
  "geometry": {"coordinates":[0.10052440001164,51.53312712631649],"type":"Point"}
}