{
  "type": "Feature",
  "properties": {
    "date:inception_lower": "1995-07-01",
    "date:inception_upper": "1995-07-01",
    "iso:country": "GB",
    "wof:name": "LN1 2TX",
    "wof:placetype": "postalcode"
  },
  "geometry": {"coordinates":[-0.663502,53.273867],"type":"Point"}
}
