{
  "type": "Feature",
  "properties": {
    "iso:country":"GB",
    "wof:name":"LN1 2TX",
    "wof:placetype":"postalcode"
},
  "geometry": {"coordinates":[-0.66350187169224,53.27386700754081],"type":"Point"}
}