{
  "type": "Feature",
  "properties": {
    "iso:country": "GB",
    "wof:name": "LN1 2TX",
    "wof:placetype": "postalcode"
  },
  "geometry": {"coordinates":[-0.663502,53.273867],"type":"Point"}
}
