{
  "type": "Feature",
  "properties": {
    "iso:country": "GB",
    "wof:name": "WA13 0SP",
    "wof:placetype": "postalcode"
  },
  "geometry": {"coordinates":[-2.504454,53.359117],"type":"Point"}
}
