{
  "type": "Feature",
  "properties": {
    "iso:country":"GB",
    "wof:name":"CV7 8FR",
    "wof:placetype":"postalcode"
},
  "geometry": {"coordinates":[-1.58419904311967,52.51351138933012],"type":"Point"}
}