{
  "type": "Feature",
  "properties": {
    "iso:country":"GB",
    "wof:name":"PO15 5BY",
    "wof:placetype":"postalcode"
},
  "geometry": {"coordinates":[-1.21104515794342,50.85555392299652],"type":"Point"}
}