{
  "type": "Feature",
  "properties": {
    "date:inception_lower":"1980-01-01",
    "date:inception_upper":"1980-01-31",
    "iso:country":"GB",
    "wof:name":"PO15 5BY",
    "wof:placetype":"postalcode"
},
  "geometry": {"coordinates":[-1.211045,50.855554],"type":"Point"}
}