{
  "type": "Feature",
  "properties": {
    "iso:country": "GB",
    "wof:name": "BS10 7JQ",
    "wof:placetype": "postalcode"
  },
  "geometry": {"coordinates":[-2.618437,51.512577],"type":"Point"}
}
