{
  "type": "Feature",
  "properties": {
    "iso:country":"GB",
    "wof:name":"TQ8 8JX",
    "wof:placetype":"postalcode"
},
  "geometry": {"coordinates":[-3.77137595156523,50.23324738971616],"type":"Point"}
}