{
  "type": "Feature",
  "properties": {
    "iso:country":"GB",
    "wof:name":"BS48 3HP",
    "wof:placetype":"postalcode"
},
  "geometry": {"coordinates":[-2.74464056700223,51.41343825265435],"type":"Point"}
}