{
  "type": "Feature",
  "properties": {
    "date:inception_lower":"2003-03-01",
    "date:inception_upper":"2003-03-31",
    "iso:country":"GB",
    "wof:name":"CM11 2PZ",
    "wof:placetype":"postalcode"
},
  "geometry": {"coordinates":[0.442607,51.606649],"type":"Point"}
}