{
  "type": "Feature",
  "properties": {
    "iso:country": "GB",
    "wof:name": "CM11 2PZ",
    "wof:placetype": "postalcode"
  },
  "geometry": {"coordinates":[0.442607,51.606649],"type":"Point"}
}
