{
  "type": "Feature",
  "properties": {
    "iso:country":"GB",
    "wof:name":"EX8 4AU",
    "wof:placetype":"postalcode"
},
  "geometry": {"coordinates":[-3.39115152626369,50.62979821780109],"type":"Point"}
}