{
  "type": "Feature",
  "properties": {
    "iso:country":"GB",
    "wof:name":"SK9 6JF",
    "wof:placetype":"postalcode"
},
  "geometry": {"coordinates":[-2.24660480787778,53.3153720494262],"type":"Point"}
}