{
  "type": "Feature",
  "properties": {
    "iso:country":"GB",
    "wof:name":"WA1 3BT",
    "wof:placetype":"postalcode"
},
  "geometry": {"coordinates":[-2.56592102005445,53.39860744534506],"type":"Point"}
}