{
  "type": "Feature",
  "properties": {
    "iso:country":"GB",
    "wof:name":"LN1 3SP",
    "wof:placetype":"postalcode"
},
  "geometry": {"coordinates":[-0.53860390879857,53.24763550385772],"type":"Point"}
}