{
  "type": "Feature",
  "properties": {
    "iso:country": "GB",
    "wof:name": "LN1 3SP",
    "wof:placetype": "postalcode"
  },
  "geometry": {"coordinates":[-0.538604,53.247635],"type":"Point"}
}
