{
  "type": "Feature",
  "properties": {
    "date:inception_lower":"1984-02-01",
    "date:inception_upper":"1984-02-29",
    "iso:country":"GB",
    "wof:name":"PO9 5NP",
    "wof:placetype":"postalcode"
},
  "geometry": {"coordinates":[-0.95514,50.868589],"type":"Point"}
}