{
  "type": "Feature",
  "properties": {
    "iso:country": "GB",
    "wof:name": "PO9 5NP",
    "wof:placetype": "postalcode"
  },
  "geometry": {"coordinates":[-0.95514,50.868589],"type":"Point"}
}
