{
  "type": "Feature",
  "properties": {
    "iso:country":"GB",
    "wof:name":"PO9 5NP",
    "wof:placetype":"postalcode"
},
  "geometry": {"coordinates":[-0.95514026451211,50.86858882178269],"type":"Point"}
}