{
  "type": "Feature",
  "properties": {
    "iso:country":"GB",
    "wof:name":"SY20 9EP",
    "wof:placetype":"postalcode"
},
  "geometry": {"coordinates":[-3.69212041926806,52.69358866846496],"type":"Point"}
}