{
  "type": "Feature",
  "properties": {
    "iso:country": "GB",
    "wof:name": "SY20 9EP",
    "wof:placetype": "postalcode"
  },
  "geometry": {"coordinates":[-3.69212,52.693589],"type":"Point"}
}
