{
  "type": "Feature",
  "properties": {
    "iso:country":"GB",
    "wof:name":"CV23 9LG",
    "wof:placetype":"postalcode"
},
  "geometry": {"coordinates":[-1.33982321316647,52.34432048766099],"type":"Point"}
}