{
  "type": "Feature",
  "properties": {
    "iso:country":"GB",
    "wof:name":"GL5 3AR",
    "wof:placetype":"postalcode"
},
  "geometry": {"coordinates":[-2.21915251211234,51.74494417171339],"type":"Point"}
}