{
  "type": "Feature",
  "properties": {
    "iso:country": "GB",
    "wof:name": "GL5 3AR",
    "wof:placetype": "postalcode"
  },
  "geometry": {"coordinates":[-2.21938,51.744895],"type":"Point"}
}
