{
  "type": "Feature",
  "properties": {
    "iso:country": "GB",
    "wof:name": "EX39 6EG",
    "wof:placetype": "postalcode"
  },
  "geometry": {"coordinates":[-4.467185,50.973118],"type":"Point"}
}
