{
  "type": "Feature",
  "properties": {
    "iso:country":"GB",
    "wof:name":"RG31 5AT",
    "wof:placetype":"postalcode"
},
  "geometry": {"coordinates":[-1.03980958412832,51.45838930038274],"type":"Point"}
}