{
  "type": "Feature",
  "properties": {
    "iso:country":"GB",
    "wof:name":"LE9 4DA",
    "wof:placetype":"postalcode"
},
  "geometry": {"coordinates":[-1.27860479453531,52.54919980850246],"type":"Point"}
}