{
  "type": "Feature",
  "properties": {
    "iso:country": "GB",
    "wof:name": "EX37 9RT",
    "wof:placetype": "postalcode"
  },
  "geometry": {"coordinates":[-3.949406,51.019231],"type":"Point"}
}
