{
  "type": "Feature",
  "properties": {
    "iso:country":"GB",
    "wof:name":"EX37 9RT",
    "wof:placetype":"postalcode"
},
  "geometry": {"coordinates":[-3.94942738437947,51.01925346293802],"type":"Point"}
}