{
  "type": "Feature",
  "properties": {
    "date:inception_lower": "1980-01-01",
    "date:inception_upper": "1980-01-01",
    "iso:country": "GB",
    "wof:name": "EX37 9RT",
    "wof:placetype": "postalcode"
  },
  "geometry": {"coordinates":[-3.949406,51.019231],"type":"Point"}
}
