{
  "type": "Feature",
  "properties": {
    "iso:country":"GB",
    "wof:name":"PL4 0BW",
    "wof:placetype":"postalcode"
},
  "geometry": {"coordinates":[-4.13359308185907,50.37137567655439],"type":"Point"}
}