{
  "type": "Feature",
  "properties": {
    "iso:country": "GB",
    "wof:name": "PL4 0BW",
    "wof:placetype": "postalcode"
  },
  "geometry": {"coordinates":[-4.133593,50.371376],"type":"Point"}
}
