{
  "type": "Feature",
  "properties": {
    "iso:country":"GB",
    "wof:name":"LE67 6LE",
    "wof:placetype":"postalcode"
},
  "geometry": {"coordinates":[-1.39519970527438,52.68743367113667],"type":"Point"}
}