{
  "type": "Feature",
  "properties": {
    "date:inception_lower": "1992-08-01",
    "date:inception_upper": "1992-08-01",
    "iso:country": "GB",
    "wof:name": "LE67 6LE",
    "wof:placetype": "postalcode"
  },
  "geometry": {"coordinates":[-1.3952,52.687434],"type":"Point"}
}
