{
  "type": "Feature",
  "properties": {
    "iso:country":"GB",
    "wof:name":"LS9 8AX",
    "wof:placetype":"postalcode"
},
  "geometry": {"coordinates":[-1.53237961282426,53.79510663636236],"type":"Point"}
}