{
  "type": "Feature",
  "properties": {
    "iso:country": "GB",
    "wof:name": "LS9 8AX",
    "wof:placetype": "postalcode"
  },
  "geometry": {"coordinates":[-1.53238,53.795107],"type":"Point"}
}
