{
  "type": "Feature",
  "properties": {
    "date:inception_lower": "2008-01-01",
    "date:inception_upper": "2008-01-01",
    "iso:country": "GB",
    "wof:name": "LS9 8AX",
    "wof:placetype": "postalcode"
  },
  "geometry": {"coordinates":[-1.532384,53.795123],"type":"Point"}
}
