{
  "type": "Feature",
  "properties": {
    "iso:country":"GB",
    "wof:name":"NG34 8TN",
    "wof:placetype":"postalcode"
},
  "geometry": {"coordinates":[-0.41628384771965,53.00995282371737],"type":"Point"}
}