{
  "type": "Feature",
  "properties": {
    "iso:country":"GB",
    "wof:name":"SO21 2PY",
    "wof:placetype":"postalcode"
},
  "geometry": {"coordinates":[-1.39405901021457,51.11390071386737],"type":"Point"}
}