{
  "type": "Feature",
  "properties": {
    "iso:country": "GB",
    "wof:name": "SO21 2PY",
    "wof:placetype": "postalcode"
  },
  "geometry": {"coordinates":[-1.394035,51.113697],"type":"Point"}
}
