{
  "type": "Feature",
  "properties": {
    "date:inception_lower":"1980-01-01",
    "date:inception_upper":"1980-01-31",
    "iso:country":"GB",
    "wof:name":"SO21 2PY",
    "wof:placetype":"postalcode"
},
  "geometry": {"coordinates":[-1.394035,51.113697],"type":"Point"}
}