{
  "type": "Feature",
  "properties": {
    "date:inception_lower":"1980-01-01",
    "date:inception_upper":"1980-01-31",
    "iso:country":"GB",
    "wof:name":"EX23 0AA",
    "wof:placetype":"postalcode"
},
  "geometry": {"coordinates":[-4.551558,50.788388],"type":"Point"}
}