{
  "type": "Feature",
  "properties": {
    "date:inception_lower": "1980-01-01",
    "date:inception_upper": "1980-01-01",
    "iso:country": "GB",
    "wof:name": "EX23 0AA",
    "wof:placetype": "postalcode"
  },
  "geometry": {"coordinates":[-4.551056,50.788457],"type":"Point"}
}
