{
  "type": "Feature",
  "properties": {
    "date:inception_lower": "1980-01-01",
    "date:inception_upper": "1980-01-01",
    "iso:country": "GB",
    "wof:name": "L8 0RS",
    "wof:placetype": "postalcode"
  },
  "geometry": {"coordinates":[-2.947036,53.394313],"type":"Point"}
}
