{
  "type": "Feature",
  "properties": {
    "iso:country":"GB",
    "wof:name":"ML1 4BW",
    "wof:placetype":"postalcode"
},
  "geometry": {"coordinates":[-3.97703256014837,55.79699372935086],"type":"Point"}
}