{
  "type": "Feature",
  "properties": {
    "iso:country": "GB",
    "wof:name": "SE8 5DR",
    "wof:placetype": "postalcode"
  },
  "geometry": {"coordinates":[-0.042433,51.490511],"type":"Point"}
}
