{
  "type": "Feature",
  "properties": {
    "iso:country":"GB",
    "wof:name":"DE72 3QP",
    "wof:placetype":"postalcode"
},
  "geometry": {"coordinates":[-1.33624760055479,52.89393415198911],"type":"Point"}
}