{
  "type": "Feature",
  "properties": {
    "iso:country": "GB",
    "wof:name": "DE72 3QP",
    "wof:placetype": "postalcode"
  },
  "geometry": {"coordinates":[-1.336248,52.893934],"type":"Point"}
}
