{
  "type": "Feature",
  "properties": {
    "iso:country":"GB",
    "wof:name":"RG17 0PF",
    "wof:placetype":"postalcode"
},
  "geometry": {"coordinates":[-1.51135056672808,51.41777300869989],"type":"Point"}
}