{
  "type": "Feature",
  "properties": {
    "date:inception_lower":"2013-11-01",
    "date:inception_upper":"2013-11-30",
    "iso:country":"GB",
    "wof:name":"RG17 0PF",
    "wof:placetype":"postalcode"
},
  "geometry": {"coordinates":[-1.511164,51.417618],"type":"Point"}
}