{
  "type": "Feature",
  "properties": {
    "iso:country": "GB",
    "wof:name": "WS11 0DB",
    "wof:placetype": "postalcode"
  },
  "geometry": {"coordinates":[-2.031253,52.675882],"type":"Point"}
}
