{
  "type": "Feature",
  "properties": {
    "iso:country": "GB",
    "wof:name": "PO19 8GS",
    "wof:placetype": "postalcode"
  },
  "geometry": {"coordinates":[-0.7915,50.83093],"type":"Point"}
}
