{
  "type": "Feature",
  "properties": {
    "iso:country":"GB",
    "wof:name":"B23 6LL",
    "wof:placetype":"postalcode"
},
  "geometry": {"coordinates":[-1.8443393259725,52.52952056724976],"type":"Point"}
}