{
  "type": "Feature",
  "properties": {
    "date:inception_lower": "1994-12-01",
    "date:inception_upper": "1994-12-01",
    "iso:country": "GB",
    "wof:name": "NE24 3HP",
    "wof:placetype": "postalcode"
  },
  "geometry": {"coordinates":[-1.520371,55.111351],"type":"Point"}
}
