{
  "type": "Feature",
  "properties": {
    "iso:country":"GB",
    "wof:name":"NE24 3HP",
    "wof:placetype":"postalcode"
},
  "geometry": {"coordinates":[-1.52037150420798,55.11135089537404],"type":"Point"}
}