{
  "type": "Feature",
  "properties": {
    "iso:country":"GB",
    "wof:name":"N13 4UP",
    "wof:placetype":"postalcode"
},
  "geometry": {"coordinates":[-0.1103190064514,51.61279838843815],"type":"Point"}
}