{
  "type": "Feature",
  "properties": {
    "date:inception_lower": "2021-08-01",
    "date:inception_upper": "2021-08-01",
    "iso:country": "GB",
    "wof:name": "IP6 8FD",
    "wof:placetype": "postalcode"
  },
  "geometry": {"coordinates":[1.061128,52.144772],"type":"Point"}
}
