{
  "type": "Feature",
  "properties": {
    "iso:country": "GB",
    "wof:name": "TA21 8BJ",
    "wof:placetype": "postalcode"
  },
  "geometry": {"coordinates":[-3.231453,50.973239],"type":"Point"}
}
