{
  "type": "Feature",
  "properties": {
    "iso:country":"GB",
    "wof:name":"TA21 8BJ",
    "wof:placetype":"postalcode"
},
  "geometry": {"coordinates":[-3.23145299418362,50.97323855824206],"type":"Point"}
}