{
  "type": "Feature",
  "properties": {
    "iso:country":"GB",
    "wof:name":"G42 0QJ",
    "wof:placetype":"postalcode"
},
  "geometry": {"coordinates":[-4.25040921095859,55.83801158627286],"type":"Point"}
}