{
  "type": "Feature",
  "properties": {
    "iso:country":"GB",
    "wof:name":"EN1 3UN",
    "wof:placetype":"postalcode"
},
  "geometry": {"coordinates":[-0.07751916622178,51.65684117109069],"type":"Point"}
}