{
  "type": "Feature",
  "properties": {
    "iso:country":"GB",
    "wof:name":"S71 4HR",
    "wof:placetype":"postalcode"
},
  "geometry": {"coordinates":[-1.46561484944063,53.60242600152531],"type":"Point"}
}