{
  "type": "Feature",
  "properties": {
    "iso:country":"GB",
    "wof:name":"AB51 0PJ",
    "wof:placetype":"postalcode"
},
  "geometry": {"coordinates":[-2.31850526317834,57.34231757338422],"type":"Point"}
}