{
  "type": "Feature",
  "properties": {
    "iso:country":"GB",
    "wof:name":"OL5 9QD",
    "wof:placetype":"postalcode"
},
  "geometry": {"coordinates":[-2.04220442327371,53.5024917246561],"type":"Point"}
}