{
  "type": "Feature",
  "properties": {
    "iso:country":"GB",
    "wof:name":"LU3 2BB",
    "wof:placetype":"postalcode"
},
  "geometry": {"coordinates":[-0.42524632898999,51.91336699697881],"type":"Point"}
}