{
  "type": "Feature",
  "properties": {
    "iso:country":"GB",
    "wof:name":"LS27 9RB",
    "wof:placetype":"postalcode"
},
  "geometry": {"coordinates":[-1.60829495359238,53.75315257111162],"type":"Point"}
}