{
  "type": "Feature",
  "properties": {
    "date:inception_lower": "1980-01-01",
    "date:inception_upper": "1980-01-01",
    "iso:country": "GB",
    "wof:name": "RM10 8EU",
    "wof:placetype": "postalcode"
  },
  "geometry": {"coordinates":[0.161961,51.546157],"type":"Point"}
}
