{
  "type": "Feature",
  "properties": {
    "iso:country":"GB",
    "wof:name":"RM10 8EU",
    "wof:placetype":"postalcode"
},
  "geometry": {"coordinates":[0.16196060625324,51.54615655394998],"type":"Point"}
}