{
  "type": "Feature",
  "properties": {
    "iso:country":"GB",
    "wof:name":"BH9 3DU",
    "wof:placetype":"postalcode"
},
  "geometry": {"coordinates":[-1.86639721026565,50.75372114772223],"type":"Point"}
}