{
  "type": "Feature",
  "properties": {
    "iso:country": "GB",
    "wof:name": "BH9 3DU",
    "wof:placetype": "postalcode"
  },
  "geometry": {"coordinates":[-1.866397,50.753721],"type":"Point"}
}
