{
  "type": "Feature",
  "properties": {
    "iso:country":"GB",
    "wof:name":"N1 2TU",
    "wof:placetype":"postalcode"
},
  "geometry": {"coordinates":[-0.10212967448598,51.53899999449859],"type":"Point"}
}