{
  "type": "Feature",
  "properties": {
    "date:inception_lower": "1980-01-01",
    "date:inception_upper": "1980-01-01",
    "iso:country": "GB",
    "wof:name": "N1 2TU",
    "wof:placetype": "postalcode"
  },
  "geometry": {"coordinates":[-0.102091,51.538957],"type":"Point"}
}
