{
  "type": "Feature",
  "properties": {
    "iso:country":"GB",
    "wof:name":"L31 3EZ",
    "wof:placetype":"postalcode"
},
  "geometry": {"coordinates":[-2.9253398053041,53.51225502537275],"type":"Point"}
}