{
  "type": "Feature",
  "properties": {
    "iso:country": "GB",
    "wof:name": "BN17 5HF",
    "wof:placetype": "postalcode"
  },
  "geometry": {"coordinates":[-0.528473,50.806713],"type":"Point"}
}
