{
  "type": "Feature",
  "properties": {
    "iso:country": "GB",
    "wof:name": "RG22 6HE",
    "wof:placetype": "postalcode"
  },
  "geometry": {"coordinates":[-1.114791,51.252381],"type":"Point"}
}
