{
  "type": "Feature",
  "properties": {
    "iso:country":"GB",
    "wof:name":"EN10 6NG",
    "wof:placetype":"postalcode"
},
  "geometry": {"coordinates":[-0.03244335532517,51.72082178829388],"type":"Point"}
}