{
  "type": "Feature",
  "properties": {
    "date:inception_lower":"1992-08-01",
    "date:inception_upper":"1992-08-31",
    "iso:country":"GB",
    "wof:name":"EN10 6NG",
    "wof:placetype":"postalcode"
},
  "geometry": {"coordinates":[-0.032443,51.720822],"type":"Point"}
}