{
  "type": "Feature",
  "properties": {
    "iso:country": "GB",
    "wof:name": "SY21 8ER",
    "wof:placetype": "postalcode"
  },
  "geometry": {"coordinates":[-3.015087,52.717908],"type":"Point"}
}
