{
  "type": "Feature",
  "properties": {
    "date:inception_lower":"1980-01-01",
    "date:inception_upper":"1980-01-31",
    "iso:country":"GB",
    "wof:name":"SY21 8ER",
    "wof:placetype":"postalcode"
},
  "geometry": {"coordinates":[-3.015087,52.717908],"type":"Point"}
}