{
  "type": "Feature",
  "properties": {
    "iso:country":"GB",
    "wof:name":"SY21 8ER",
    "wof:placetype":"postalcode"
},
  "geometry": {"coordinates":[-3.01508723371502,52.71790771257768],"type":"Point"}
}