{
  "type": "Feature",
  "properties": {
    "iso:country":"GB",
    "wof:name":"SE20 8NR",
    "wof:placetype":"postalcode"
},
  "geometry": {"coordinates":[-0.06207452183655,51.41692641232681],"type":"Point"}
}