{
  "type": "Feature",
  "properties": {
    "iso:country": "GB",
    "wof:name": "SK11 8QE",
    "wof:placetype": "postalcode"
  },
  "geometry": {"coordinates":[-2.146758,53.258539],"type":"Point"}
}
