{
  "type": "Feature",
  "properties": {
    "date:inception_lower":"1980-01-01",
    "date:inception_upper":"1980-01-31",
    "iso:country":"GB",
    "wof:name":"PL15 8DU",
    "wof:placetype":"postalcode"
},
  "geometry": {"coordinates":[-4.365141,50.642549],"type":"Point"}
}