{
  "type": "Feature",
  "properties": {
    "iso:country": "GB",
    "wof:name": "PR9 7LA",
    "wof:placetype": "postalcode"
  },
  "geometry": {"coordinates":[-2.964909,53.659419],"type":"Point"}
}
