{
  "type": "Feature",
  "properties": {
    "date:inception_lower":"2001-06-01",
    "date:inception_upper":"2001-06-30",
    "iso:country":"GB",
    "wof:name":"PR9 7LA",
    "wof:placetype":"postalcode"
},
  "geometry": {"coordinates":[-2.964909,53.659419],"type":"Point"}
}