{
  "type": "Feature",
  "properties": {
    "iso:country": "GB",
    "wof:name": "WV15 5NH",
    "wof:placetype": "postalcode"
  },
  "geometry": {"coordinates":[-2.421742,52.584667],"type":"Point"}
}
