{
  "type": "Feature",
  "properties": {
    "iso:country":"GB",
    "wof:name":"RM1 4RB",
    "wof:placetype":"postalcode"
},
  "geometry": {"coordinates":[0.17315826633924,51.5910486487619],"type":"Point"}
}