{
  "type": "Feature",
  "properties": {
    "date:inception_lower": "2005-11-01",
    "date:inception_upper": "2005-11-01",
    "iso:country": "GB",
    "wof:name": "WF8 1NS",
    "wof:placetype": "postalcode"
  },
  "geometry": {"coordinates":[-1.306581,53.697274],"type":"Point"}
}
