{
  "type": "Feature",
  "properties": {
    "iso:country":"GB",
    "wof:name":"WF8 1NS",
    "wof:placetype":"postalcode"
},
  "geometry": {"coordinates":[-1.3065807285556,53.6972737846238],"type":"Point"}
}