{
  "type": "Feature",
  "properties": {
    "iso:country": "GB",
    "wof:name": "IP27 0ED",
    "wof:placetype": "postalcode"
  },
  "geometry": {"coordinates":[0.630077,52.447719],"type":"Point"}
}
