{
  "type": "Feature",
  "properties": {
    "iso:country":"GB",
    "wof:name":"IP27 0ED",
    "wof:placetype":"postalcode"
},
  "geometry": {"coordinates":[0.63000343353709,52.44762086670118],"type":"Point"}
}