{
  "type": "Feature",
  "properties": {
    "iso:country":"GB",
    "wof:name":"S40 3BB",
    "wof:placetype":"postalcode"
},
  "geometry": {"coordinates":[-1.4599821097361,53.2301988190767],"type":"Point"}
}