{
  "type": "Feature",
  "properties": {
    "iso:country":"GB",
    "wof:name":"RG27 8SE",
    "wof:placetype":"postalcode"
},
  "geometry": {"coordinates":[-0.90583036255056,51.30968402659371],"type":"Point"}
}