{
  "type": "Feature",
  "properties": {
    "date:inception_lower":"1980-01-01",
    "date:inception_upper":"1980-01-31",
    "iso:country":"GB",
    "wof:name":"RG27 8SE",
    "wof:placetype":"postalcode"
},
  "geometry": {"coordinates":[-0.90583,51.309684],"type":"Point"}
}