{
  "type": "Feature",
  "properties": {
    "iso:country":"GB",
    "wof:name":"PE31 8BW",
    "wof:placetype":"postalcode"
},
  "geometry": {"coordinates":[0.66656670967572,52.96664052160676],"type":"Point"}
}