{
  "type": "Feature",
  "properties": {
    "date:inception_lower":"2014-10-01",
    "date:inception_upper":"2014-10-31",
    "iso:country":"GB",
    "wof:name":"SY2 6AN",
    "wof:placetype":"postalcode"
},
  "geometry": {"coordinates":[-2.747689,52.70936],"type":"Point"}
}