{
  "type": "Feature",
  "properties": {
    "iso:country": "GB",
    "wof:name": "SY2 6AN",
    "wof:placetype": "postalcode"
  },
  "geometry": {"coordinates":[-2.747689,52.70936],"type":"Point"}
}
