{
  "type": "Feature",
  "properties": {
    "iso:country": "GB",
    "wof:name": "DD9 7BX",
    "wof:placetype": "postalcode"
  },
  "geometry": {"coordinates":[-2.652375,56.729052],"type":"Point"}
}
