{
  "type": "Feature",
  "properties": {
    "iso:country":"GB",
    "wof:name":"WF1 3LE",
    "wof:placetype":"postalcode"
},
  "geometry": {"coordinates":[-1.49598081163485,53.68819809013635],"type":"Point"}
}