{
  "type": "Feature",
  "properties": {
    "date:inception_lower": "1990-02-01",
    "date:inception_upper": "1990-02-01",
    "iso:country": "GB",
    "wof:name": "WF1 3LE",
    "wof:placetype": "postalcode"
  },
  "geometry": {"coordinates":[-1.495981,53.688198],"type":"Point"}
}
