{
  "type": "Feature",
  "properties": {
    "date:inception_lower": "2009-07-01",
    "date:inception_upper": "2009-07-01",
    "iso:country": "GB",
    "wof:name": "IV7 8LW",
    "wof:placetype": "postalcode"
  },
  "geometry": {"coordinates":[-4.231572,57.640021],"type":"Point"}
}
