{
  "type": "Feature",
  "properties": {
    "iso:country": "GB",
    "wof:name": "IV7 8LW",
    "wof:placetype": "postalcode"
  },
  "geometry": {"coordinates":[-4.231572,57.640021],"type":"Point"}
}
