{
  "type": "Feature",
  "properties": {
    "iso:country":"GB",
    "wof:name":"IV7 8LW",
    "wof:placetype":"postalcode"
},
  "geometry": {"coordinates":[-4.23157235766686,57.64002130723127],"type":"Point"}
}