{
  "type": "Feature",
  "properties": {
    "iso:country": "GB",
    "wof:name": "GL17 9DQ",
    "wof:placetype": "postalcode"
  },
  "geometry": {"coordinates":[-2.544494,51.834166],"type":"Point"}
}
