{
  "type": "Feature",
  "properties": {
    "iso:country":"GB",
    "wof:name":"WA4 6SF",
    "wof:placetype":"postalcode"
},
  "geometry": {"coordinates":[-2.59069306381462,53.36509431557626],"type":"Point"}
}