{
  "type": "Feature",
  "properties": {
    "iso:country": "GB",
    "wof:name": "LE5 2FE",
    "wof:placetype": "postalcode"
  },
  "geometry": {"coordinates":[-1.07489,52.642998],"type":"Point"}
}
