{
  "type": "Feature",
  "properties": {
    "iso:country":"GB",
    "wof:name":"LE5 2FE",
    "wof:placetype":"postalcode"
},
  "geometry": {"coordinates":[-1.07504774955842,52.64293594175574],"type":"Point"}
}