{
  "type": "Feature",
  "properties": {
    "iso:country":"GB",
    "wof:name":"B10 9JA",
    "wof:placetype":"postalcode"
},
  "geometry": {"coordinates":[-1.83840834584729,52.46655608686579],"type":"Point"}
}