{
  "type": "Feature",
  "properties": {
    "iso:country":"GB",
    "wof:name":"B45 0DF",
    "wof:placetype":"postalcode"
},
  "geometry": {"coordinates":[-2.01233244061745,52.40480505094347],"type":"Point"}
}