{
  "type": "Feature",
  "properties": {
    "date:inception_lower": "2019-07-01",
    "date:inception_upper": "2019-07-01",
    "iso:country": "GB",
    "wof:name": "NR7 7ES",
    "wof:placetype": "postalcode"
  },
  "geometry": {"coordinates":[1.32296,52.647735],"type":"Point"}
}
