{
  "type": "Feature",
  "properties": {
    "iso:country": "GB",
    "wof:name": "ME13 8GL",
    "wof:placetype": "postalcode"
  },
  "geometry": {"coordinates":[0.879008,51.307389],"type":"Point"}
}
