{
  "type": "Feature",
  "properties": {
    "date:inception_lower": "2019-03-01",
    "date:inception_upper": "2019-03-01",
    "iso:country": "GB",
    "wof:name": "ME13 8GL",
    "wof:placetype": "postalcode"
  },
  "geometry": {"coordinates":[0.879024,51.307416],"type":"Point"}
}
