{
  "type": "Feature",
  "properties": {
    "iso:country": "GB",
    "wof:name": "M33 5AW",
    "wof:placetype": "postalcode"
  },
  "geometry": {"coordinates":[-2.340131,53.42261],"type":"Point"}
}
