{
  "type": "Feature",
  "properties": {
    "date:inception_lower": "1980-01-01",
    "date:inception_upper": "1980-01-01",
    "iso:country": "GB",
    "wof:name": "M33 5AW",
    "wof:placetype": "postalcode"
  },
  "geometry": {"coordinates":[-2.340131,53.42261],"type":"Point"}
}
