{
  "type": "Feature",
  "properties": {
    "iso:country":"GB",
    "wof:name":"BB12 9LQ",
    "wof:placetype":"postalcode"
},
  "geometry": {"coordinates":[-2.2535508068473,53.85683970939406],"type":"Point"}
}