{
  "type": "Feature",
  "properties": {
    "iso:country": "GB",
    "wof:name": "BB12 9LQ",
    "wof:placetype": "postalcode"
  },
  "geometry": {"coordinates":[-2.253551,53.85684],"type":"Point"}
}
