{
  "type": "Feature",
  "properties": {
    "iso:country":"GB",
    "wof:name":"IP20 9FB",
    "wof:placetype":"postalcode"
},
  "geometry": {"coordinates":[1.30271923186139,52.39802391391176],"type":"Point"}
}