{
  "type": "Feature",
  "properties": {
    "iso:country": "GB",
    "wof:name": "IP20 9FB",
    "wof:placetype": "postalcode"
  },
  "geometry": {"coordinates":[1.302719,52.398024],"type":"Point"}
}
