{
  "type": "Feature",
  "properties": {
    "iso:country":"GB",
    "wof:name":"DG8 6RW",
    "wof:placetype":"postalcode"
},
  "geometry": {"coordinates":[-4.59880731565667,55.07304553028943],"type":"Point"}
}