{
  "type": "Feature",
  "properties": {
    "iso:country":"GB",
    "wof:name":"HX1 3AG",
    "wof:placetype":"postalcode"
},
  "geometry": {"coordinates":[-1.8713930021514,53.71692587862366],"type":"Point"}
}