{
  "type": "Feature",
  "properties": {
    "iso:country":"GB",
    "wof:name":"CH49 5LG",
    "wof:placetype":"postalcode"
},
  "geometry": {"coordinates":[-3.07671976424294,53.37079535351569],"type":"Point"}
}