{
  "type": "Feature",
  "properties": {
    "iso:country": "GB",
    "wof:name": "B78 2LE",
    "wof:placetype": "postalcode"
  },
  "geometry": {"coordinates":[-1.68159,52.565838],"type":"Point"}
}
