{
  "type": "Feature",
  "properties": {
    "iso:country":"GB",
    "wof:name":"B78 2LE",
    "wof:placetype":"postalcode"
},
  "geometry": {"coordinates":[-1.68159022416566,52.56583782329491],"type":"Point"}
}