{
  "type": "Feature",
  "properties": {
    "date:inception_lower":"1980-01-01",
    "date:inception_upper":"1980-01-31",
    "iso:country":"GB",
    "wof:name":"CB8 9HP",
    "wof:placetype":"postalcode"
},
  "geometry": {"coordinates":[0.521166,52.175499],"type":"Point"}
}