{
  "type": "Feature",
  "properties": {
    "iso:country":"GB",
    "wof:name":"CB8 9HP",
    "wof:placetype":"postalcode"
},
  "geometry": {"coordinates":[0.52116589883079,52.17549892994749],"type":"Point"}
}