{
  "type": "Feature",
  "properties": {
    "date:inception_lower": "1986-07-01",
    "date:inception_upper": "1986-07-01",
    "iso:country": "GB",
    "wof:name": "NN4 9YW",
    "wof:placetype": "postalcode"
  },
  "geometry": {"coordinates":[-0.932699,52.218236],"type":"Point"}
}
