{
  "type": "Feature",
  "properties": {
    "iso:country":"GB",
    "wof:name":"NN4 9YW",
    "wof:placetype":"postalcode"
},
  "geometry": {"coordinates":[-0.93269870624041,52.21823620627352],"type":"Point"}
}