{
  "type": "Feature",
  "properties": {
    "iso:country":"GB",
    "wof:name":"LS11 9BA",
    "wof:placetype":"postalcode"
},
  "geometry": {"coordinates":[-1.55114365964141,53.78510268763623],"type":"Point"}
}