{
  "type": "Feature",
  "properties": {
    "iso:country":"GB",
    "wof:name":"W1F 9DF",
    "wof:placetype":"postalcode"
},
  "geometry": {"coordinates":[-0.13719458516011,51.51227880787355],"type":"Point"}
}