{
  "type": "Feature",
  "properties": {
    "iso:country": "GB",
    "wof:name": "SA2 9FH",
    "wof:placetype": "postalcode"
  },
  "geometry": {"coordinates":[-3.979545,51.61679],"type":"Point"}
}
