{
  "type": "Feature",
  "properties": {
    "iso:country":"GB",
    "wof:name":"SA2 9FH",
    "wof:placetype":"postalcode"
},
  "geometry": {"coordinates":[-3.97952621709226,51.61678510011069],"type":"Point"}
}