{
  "type": "Feature",
  "properties": {
    "iso:country": "GB",
    "wof:name": "SA6 5JR",
    "wof:placetype": "postalcode"
  },
  "geometry": {"coordinates":[-3.89752,51.702884],"type":"Point"}
}
