{
  "type": "Feature",
  "properties": {
    "iso:country":"GB",
    "wof:name":"WD3 3PE",
    "wof:placetype":"postalcode"
},
  "geometry": {"coordinates":[-0.44412882939763,51.65219945319313],"type":"Point"}
}