{
  "type": "Feature",
  "properties": {
    "date:inception_lower":"2001-06-01",
    "date:inception_upper":"2001-06-30",
    "iso:country":"GB",
    "wof:name":"IV32 7PY",
    "wof:placetype":"postalcode"
},
  "geometry": {"coordinates":[-3.076187,57.66029],"type":"Point"}
}