{
  "type": "Feature",
  "properties": {
    "iso:country":"GB",
    "wof:name":"NP7 0LH",
    "wof:placetype":"postalcode"
},
  "geometry": {"coordinates":[-3.12102465272039,51.81333215143061],"type":"Point"}
}