{
  "type": "Feature",
  "properties": {
    "iso:country": "GB",
    "wof:name": "GL17 0EU",
    "wof:placetype": "postalcode"
  },
  "geometry": {"coordinates":[-2.488351,51.853501],"type":"Point"}
}
