{
  "type": "Feature",
  "properties": {
    "iso:country": "GB",
    "wof:name": "NP18 3QX",
    "wof:placetype": "postalcode"
  },
  "geometry": {"coordinates":[-2.968886,51.614463],"type":"Point"}
}
