{
  "type": "Feature",
  "properties": {
    "iso:country":"GB",
    "wof:name":"KT19 7LG",
    "wof:placetype":"postalcode"
},
  "geometry": {"coordinates":[-0.28714950629331,51.35027226897948],"type":"Point"}
}