{
  "type": "Feature",
  "properties": {
    "iso:country": "GB",
    "wof:name": "NN17 2QT",
    "wof:placetype": "postalcode"
  },
  "geometry": {"coordinates":[-0.720107,52.5004],"type":"Point"}
}
