{
  "type": "Feature",
  "properties": {
    "iso:country":"GB",
    "wof:name":"NN17 2QT",
    "wof:placetype":"postalcode"
},
  "geometry": {"coordinates":[-0.72010718319694,52.50039983699548],"type":"Point"}
}