{
  "type": "Feature",
  "properties": {
    "iso:country":"GB",
    "wof:name":"TS10 5BQ",
    "wof:placetype":"postalcode"
},
  "geometry": {"coordinates":[-1.09835460289595,54.61690910796339],"type":"Point"}
}