{
  "type": "Feature",
  "properties": {
    "iso:country": "GB",
    "wof:name": "TS10 5BQ",
    "wof:placetype": "postalcode"
  },
  "geometry": {"coordinates":[-1.096701,54.616738],"type":"Point"}
}
