{
  "type": "Feature",
  "properties": {
    "iso:country":"GB",
    "wof:name":"CM1 2RX",
    "wof:placetype":"postalcode"
},
  "geometry": {"coordinates":[0.45022305688316,51.73588279481019],"type":"Point"}
}