{
  "type": "Feature",
  "properties": {
    "date:inception_lower":"1980-01-01",
    "date:inception_upper":"1980-01-31",
    "iso:country":"GB",
    "wof:name":"G64 3LL",
    "wof:placetype":"postalcode"
},
  "geometry": {"coordinates":[-4.2197,55.91649],"type":"Point"}
}