{
  "type": "Feature",
  "properties": {
    "iso:country": "GB",
    "wof:name": "NE16 5JE",
    "wof:placetype": "postalcode"
  },
  "geometry": {"coordinates":[-1.682418,54.938385],"type":"Point"}
}
