{
  "type": "Feature",
  "properties": {
    "date:inception_lower": "2001-06-01",
    "date:inception_upper": "2001-06-01",
    "iso:country": "GB",
    "wof:name": "G43 1TF",
    "wof:placetype": "postalcode"
  },
  "geometry": {"coordinates":[-4.290416,55.825221],"type":"Point"}
}
