{
  "type": "Feature",
  "properties": {
    "iso:country":"GB",
    "wof:name":"WF12 9DJ",
    "wof:placetype":"postalcode"
},
  "geometry": {"coordinates":[-1.63386745184276,53.6759623478959],"type":"Point"}
}