{
  "type": "Feature",
  "properties": {
    "iso:country":"GB",
    "wof:name":"NG17 8BP",
    "wof:placetype":"postalcode"
},
  "geometry": {"coordinates":[-1.26249581961215,53.09922114271783],"type":"Point"}
}