{
  "type": "Feature",
  "properties": {
    "iso:country":"GB",
    "wof:name":"N21 1DP",
    "wof:placetype":"postalcode"
},
  "geometry": {"coordinates":[-0.09980310224656,51.64394014939852],"type":"Point"}
}