{
  "type": "Feature",
  "properties": {
    "iso:country":"GB",
    "wof:name":"BR5 2DD",
    "wof:placetype":"postalcode"
},
  "geometry": {"coordinates":[0.10644630413295,51.3898543150688],"type":"Point"}
}