{
  "type": "Feature",
  "properties": {
    "date:inception_lower":"1990-07-01",
    "date:inception_upper":"1990-07-31",
    "iso:country":"GB",
    "wof:name":"BN17 5QN",
    "wof:placetype":"postalcode"
},
  "geometry": {"coordinates":[-0.584637,50.810358],"type":"Point"}
}