{
  "type": "Feature",
  "properties": {
    "iso:country": "GB",
    "wof:name": "BN17 5QN",
    "wof:placetype": "postalcode"
  },
  "geometry": {"coordinates":[-0.584637,50.810358],"type":"Point"}
}
