{
  "type": "Feature",
  "properties": {
    "iso:country":"GB",
    "wof:name":"CV6 4FG",
    "wof:placetype":"postalcode"
},
  "geometry": {"coordinates":[-1.51781740528053,52.44195967207161],"type":"Point"}
}