{
  "type": "Feature",
  "properties": {
    "iso:country":"GB",
    "wof:name":"NE37 2JN",
    "wof:placetype":"postalcode"
},
  "geometry": {"coordinates":[-1.52798417602963,54.91468980893197],"type":"Point"}
}