{
  "type": "Feature",
  "properties": {
    "iso:country":"GB",
    "wof:name":"WA8 4PP",
    "wof:placetype":"postalcode"
},
  "geometry": {"coordinates":[-2.76692580572401,53.37943564841118],"type":"Point"}
}