{
  "type": "Feature",
  "properties": {
    "iso:country": "GB",
    "wof:name": "WA8 4PP",
    "wof:placetype": "postalcode"
  },
  "geometry": {"coordinates":[-2.766926,53.379436],"type":"Point"}
}
