{
  "type": "Feature",
  "properties": {
    "date:inception_lower":"1997-06-01",
    "date:inception_upper":"1997-06-30",
    "iso:country":"GB",
    "wof:name":"WA8 4PP",
    "wof:placetype":"postalcode"
},
  "geometry": {"coordinates":[-2.766926,53.379436],"type":"Point"}
}