{
  "type": "Feature",
  "properties": {
    "iso:country":"GB",
    "wof:name":"PL9 7DQ",
    "wof:placetype":"postalcode"
},
  "geometry": {"coordinates":[-4.09487679063355,50.36276167405395],"type":"Point"}
}