{
  "type": "Feature",
  "properties": {
    "date:inception_lower": "1980-01-01",
    "date:inception_upper": "1980-01-01",
    "iso:country": "GB",
    "wof:name": "PL9 7DQ",
    "wof:placetype": "postalcode"
  },
  "geometry": {"coordinates":[-4.094877,50.362762],"type":"Point"}
}
