{
  "type": "Feature",
  "properties": {
    "iso:country":"GB",
    "wof:name":"WS5 3NG",
    "wof:placetype":"postalcode"
},
  "geometry": {"coordinates":[-1.95380812451559,52.56744296289856],"type":"Point"}
}