{
  "type": "Feature",
  "properties": {
    "iso:country": "GB",
    "wof:name": "FY5 2BU",
    "wof:placetype": "postalcode"
  },
  "geometry": {"coordinates":[-3.021536,53.888082],"type":"Point"}
}
