{
  "type": "Feature",
  "properties": {
    "iso:country":"GB",
    "wof:name":"WF7 6AF",
    "wof:placetype":"postalcode"
},
  "geometry": {"coordinates":[-1.35378075951686,53.68800102444132],"type":"Point"}
}