{
  "type": "Feature",
  "properties": {
    "iso:country": "GB",
    "wof:name": "WF7 6AF",
    "wof:placetype": "postalcode"
  },
  "geometry": {"coordinates":[-1.353781,53.688001],"type":"Point"}
}
