{
  "type": "Feature",
  "properties": {
    "date:inception_lower":"1992-01-01",
    "date:inception_upper":"1992-01-31",
    "iso:country":"GB",
    "wof:name":"LN5 0HF",
    "wof:placetype":"postalcode"
},
  "geometry": {"coordinates":[-0.524512,53.108643],"type":"Point"}
}