{
  "type": "Feature",
  "properties": {
    "iso:country": "GB",
    "wof:name": "LN5 0HF",
    "wof:placetype": "postalcode"
  },
  "geometry": {"coordinates":[-0.524512,53.108643],"type":"Point"}
}
