{
  "type": "Feature",
  "properties": {
    "iso:country":"GB",
    "wof:name":"NN15 5LR",
    "wof:placetype":"postalcode"
},
  "geometry": {"coordinates":[-0.67633643121623,52.36692877521386],"type":"Point"}
}