{
  "type": "Feature",
  "properties": {
    "date:inception_lower":"1985-10-01",
    "date:inception_upper":"1985-10-31",
    "iso:country":"GB",
    "wof:name":"NN15 5LR",
    "wof:placetype":"postalcode"
},
  "geometry": {"coordinates":[-0.676336,52.366929],"type":"Point"}
}