{
  "type": "Feature",
  "properties": {
    "iso:country":"GB",
    "wof:name":"ST18 9FB",
    "wof:placetype":"postalcode"
},
  "geometry": {"coordinates":[-2.13364583193642,52.75903622271428],"type":"Point"}
}