{
  "type": "Feature",
  "properties": {
    "date:inception_lower": "2014-01-01",
    "date:inception_upper": "2014-01-01",
    "iso:country": "GB",
    "wof:name": "ST18 9FB",
    "wof:placetype": "postalcode"
  },
  "geometry": {"coordinates":[-2.133646,52.759036],"type":"Point"}
}
