{
  "type": "Feature",
  "properties": {
    "iso:country": "GB",
    "wof:name": "TN17 2RY",
    "wof:placetype": "postalcode"
  },
  "geometry": {"coordinates":[0.425663,51.09029],"type":"Point"}
}
