{
  "type": "Feature",
  "properties": {
    "date:inception_lower":"1980-01-01",
    "date:inception_upper":"1980-01-31",
    "iso:country":"GB",
    "wof:name":"TN17 2RY",
    "wof:placetype":"postalcode"
},
  "geometry": {"coordinates":[0.425663,51.09029],"type":"Point"}
}