{
  "type": "Feature",
  "properties": {
    "iso:country":"GB",
    "wof:name":"TN17 2RY",
    "wof:placetype":"postalcode"
},
  "geometry": {"coordinates":[0.42566274273904,51.09028998870701],"type":"Point"}
}