{
  "type": "Feature",
  "properties": {
    "iso:country":"GB",
    "wof:name":"CO7 7JQ",
    "wof:placetype":"postalcode"
},
  "geometry": {"coordinates":[1.01741900206895,51.88195339339128],"type":"Point"}
}