{
  "type": "Feature",
  "properties": {
    "iso:country": "GB",
    "wof:name": "LL55 4SH",
    "wof:placetype": "postalcode"
  },
  "geometry": {"coordinates":[-4.127476,53.11858],"type":"Point"}
}
