{
  "type": "Feature",
  "properties": {
    "iso:country": "GB",
    "wof:name": "WD3 3EP",
    "wof:placetype": "postalcode"
  },
  "geometry": {"coordinates":[-0.450432,51.648353],"type":"Point"}
}
