{
  "type": "Feature",
  "properties": {
    "iso:country":"GB",
    "wof:name":"WD3 3EP",
    "wof:placetype":"postalcode"
},
  "geometry": {"coordinates":[-0.45043250712414,51.6483532994669],"type":"Point"}
}