{
  "type": "Feature",
  "properties": {
    "iso:country": "GB",
    "wof:name": "PE28 3XQ",
    "wof:placetype": "postalcode"
  },
  "geometry": {"coordinates":[0.010778,52.351867],"type":"Point"}
}
