{
  "type": "Feature",
  "properties": {
    "iso:country":"GB",
    "wof:name":"WV11 2DH",
    "wof:placetype":"postalcode"
},
  "geometry": {"coordinates":[-2.05379321298415,52.62865992165076],"type":"Point"}
}