{
  "type": "Feature",
  "properties": {
    "iso:country": "GB",
    "wof:name": "WV11 2DH",
    "wof:placetype": "postalcode"
  },
  "geometry": {"coordinates":[-2.053793,52.62866],"type":"Point"}
}
