{
  "type": "Feature",
  "properties": {
    "iso:country":"GB",
    "wof:name":"BA6 8ER",
    "wof:placetype":"postalcode"
},
  "geometry": {"coordinates":[-2.70592455718311,51.15023179924606],"type":"Point"}
}