{
  "type": "Feature",
  "properties": {
    "date:inception_lower":"1981-06-01",
    "date:inception_upper":"1981-06-30",
    "iso:country":"GB",
    "wof:name":"BA6 8ER",
    "wof:placetype":"postalcode"
},
  "geometry": {"coordinates":[-2.705925,51.150232],"type":"Point"}
}