{
  "type": "Feature",
  "properties": {
    "iso:country": "GB",
    "wof:name": "BA6 8ER",
    "wof:placetype": "postalcode"
  },
  "geometry": {"coordinates":[-2.705925,51.150232],"type":"Point"}
}
