{
  "type": "Feature",
  "properties": {
    "date:inception_lower": "1994-05-01",
    "date:inception_upper": "1994-05-01",
    "iso:country": "GB",
    "wof:name": "M20 1PB",
    "wof:placetype": "postalcode"
  },
  "geometry": {"coordinates":[-2.239778,53.438854],"type":"Point"}
}
