{
  "type": "Feature",
  "properties": {
    "iso:country":"GB",
    "wof:name":"HX2 6EY",
    "wof:placetype":"postalcode"
},
  "geometry": {"coordinates":[-1.94792683399721,53.71842150384863],"type":"Point"}
}