{
  "type": "Feature",
  "properties": {
    "iso:country": "GB",
    "wof:name": "LE3 0DW",
    "wof:placetype": "postalcode"
  },
  "geometry": {"coordinates":[-1.14946,52.623958],"type":"Point"}
}
