{
  "type": "Feature",
  "properties": {
    "iso:country": "GB",
    "wof:name": "HU11 4RD",
    "wof:placetype": "postalcode"
  },
  "geometry": {"coordinates":[-0.14648,53.819067],"type":"Point"}
}
