{
  "type": "Feature",
  "properties": {
    "iso:country":"GB",
    "wof:name":"HU11 4RD",
    "wof:placetype":"postalcode"
},
  "geometry": {"coordinates":[-0.14644214536928,53.81902710091285],"type":"Point"}
}