{
  "type": "Feature",
  "properties": {
    "date:inception_lower": "1980-01-01",
    "date:inception_upper": "1980-01-01",
    "iso:country": "GB",
    "wof:name": "HU15 2EP",
    "wof:placetype": "postalcode"
  },
  "geometry": {"coordinates":[-0.604484,53.767669],"type":"Point"}
}
