{
  "type": "Feature",
  "properties": {
    "iso:country":"GB",
    "wof:name":"HU15 2EP",
    "wof:placetype":"postalcode"
},
  "geometry": {"coordinates":[-0.60472328573121,53.76757925072648],"type":"Point"}
}