{
  "type": "Feature",
  "properties": {
    "date:inception_lower": "1980-01-01",
    "date:inception_upper": "1980-01-01",
    "iso:country": "GB",
    "wof:name": "LD7 1TS",
    "wof:placetype": "postalcode"
  },
  "geometry": {"coordinates":[-3.104047,52.376471],"type":"Point"}
}
