{
  "type": "Feature",
  "properties": {
    "date:inception_lower": "2007-09-01",
    "date:inception_upper": "2007-09-01",
    "iso:country": "GB",
    "wof:name": "ME5 9PE",
    "wof:placetype": "postalcode"
  },
  "geometry": {"coordinates":[0.506438,51.336498],"type":"Point"}
}
