{
  "type": "Feature",
  "properties": {
    "iso:country":"GB",
    "wof:name":"ME5 9PE",
    "wof:placetype":"postalcode"
},
  "geometry": {"coordinates":[0.50648413810012,51.33656920969768],"type":"Point"}
}