{
  "type": "Feature",
  "properties": {
    "iso:country": "GB",
    "wof:name": "M11 1GF",
    "wof:placetype": "postalcode"
  },
  "geometry": {"coordinates":[-2.17454,53.476512],"type":"Point"}
}
