{
  "type": "Feature",
  "properties": {
    "iso:country":"GB",
    "wof:name":"M11 1GF",
    "wof:placetype":"postalcode"
},
  "geometry": {"coordinates":[-2.17454032128055,53.47651174312473],"type":"Point"}
}