{
  "type": "Feature",
  "properties": {
    "iso:country":"GB",
    "wof:name":"TQ9 7NW",
    "wof:placetype":"postalcode"
},
  "geometry": {"coordinates":[-3.80635416157204,50.36833137520119],"type":"Point"}
}