{
  "type": "Feature",
  "properties": {
    "date:inception_lower": "1980-01-01",
    "date:inception_upper": "1980-01-01",
    "iso:country": "GB",
    "wof:name": "BH14 0AS",
    "wof:placetype": "postalcode"
  },
  "geometry": {"coordinates":[-1.941588,50.728855],"type":"Point"}
}
