{
  "type": "Feature",
  "properties": {
    "iso:country":"GB",
    "wof:name":"BH14 0AS",
    "wof:placetype":"postalcode"
},
  "geometry": {"coordinates":[-1.941588422477,50.72885527711765],"type":"Point"}
}