{
  "type": "Feature",
  "properties": {
    "date:inception_lower": "2024-01-01",
    "date:inception_upper": "2024-01-01",
    "iso:country": "GB",
    "wof:name": "NE3 9HN",
    "wof:placetype": "postalcode"
  },
  "geometry": {"coordinates":[-1.632352,55.007795],"type":"Point"}
}
