{
  "type": "Feature",
  "properties": {
    "date:inception_lower":"2013-07-01",
    "date:inception_upper":"2013-07-31",
    "iso:country":"GB",
    "wof:name":"EH14 4BB",
    "wof:placetype":"postalcode"
},
  "geometry": {"coordinates":[-3.319981,55.917938],"type":"Point"}
}