{
  "type": "Feature",
  "properties": {
    "iso:country": "GB",
    "wof:name": "EH14 4BB",
    "wof:placetype": "postalcode"
  },
  "geometry": {"coordinates":[-3.319981,55.917938],"type":"Point"}
}
