{
  "type": "Feature",
  "properties": {
    "date:inception_lower": "1998-06-01",
    "date:inception_upper": "1998-06-01",
    "iso:country": "GB",
    "wof:name": "YO30 4TE",
    "wof:placetype": "postalcode"
  },
  "geometry": {"coordinates":[-1.102069,53.981741],"type":"Point"}
}
