{
  "type": "Feature",
  "properties": {
    "iso:country": "GB",
    "wof:name": "L20 8HB",
    "wof:placetype": "postalcode"
  },
  "geometry": {"coordinates":[-2.990225,53.437002],"type":"Point"}
}
