{
  "type": "Feature",
  "properties": {
    "date:inception_lower": "2022-06-01",
    "date:inception_upper": "2022-06-01",
    "iso:country": "GB",
    "wof:name": "S70 4FG",
    "wof:placetype": "postalcode"
  },
  "geometry": {"coordinates":[-1.471121,53.539092],"type":"Point"}
}
