{
  "type": "Feature",
  "properties": {
    "date:inception_lower": "1980-01-01",
    "date:inception_upper": "1980-01-01",
    "iso:country": "GB",
    "wof:name": "B70 9AE",
    "wof:placetype": "postalcode"
  },
  "geometry": {"coordinates":[-1.999735,52.522727],"type":"Point"}
}
