{
  "type": "Feature",
  "properties": {
    "iso:country": "GB",
    "wof:name": "YO26 7RB",
    "wof:placetype": "postalcode"
  },
  "geometry": {"coordinates":[-1.244193,53.958245],"type":"Point"}
}
