{
  "type": "Feature",
  "properties": {
    "iso:country": "GB",
    "wof:name": "TA5 2SU",
    "wof:placetype": "postalcode"
  },
  "geometry": {"coordinates":[-3.06032,51.155168],"type":"Point"}
}
