{
  "type": "Feature",
  "properties": {
    "iso:country":"GB",
    "wof:name":"BL3 5PL",
    "wof:placetype":"postalcode"
},
  "geometry": {"coordinates":[-2.45273532945858,53.57269452756725],"type":"Point"}
}