{
  "type": "Feature",
  "properties": {
    "iso:country":"GB",
    "wof:name":"AL1 2QF",
    "wof:placetype":"postalcode"
},
  "geometry": {"coordinates":[-0.34507636184507,51.73596392524354],"type":"Point"}
}