{
  "type": "Feature",
  "properties": {
    "iso:country":"GB",
    "wof:name":"BL9 7PS",
    "wof:placetype":"postalcode"
},
  "geometry": {"coordinates":[-2.27536292705314,53.59661324609363],"type":"Point"}
}