{
  "type": "Feature",
  "properties": {
    "iso:country": "GB",
    "wof:name": "LL28 5RH",
    "wof:placetype": "postalcode"
  },
  "geometry": {"coordinates":[-3.794686,53.228467],"type":"Point"}
}
