{
  "type": "Feature",
  "properties": {
    "date:inception_lower":"1980-01-01",
    "date:inception_upper":"1980-01-31",
    "iso:country":"GB",
    "wof:name":"LL28 5RH",
    "wof:placetype":"postalcode"
},
  "geometry": {"coordinates":[-3.794686,53.228467],"type":"Point"}
}