{
  "type": "Feature",
  "properties": {
    "iso:country":"GB",
    "wof:name":"KA7 1HG",
    "wof:placetype":"postalcode"
},
  "geometry": {"coordinates":[-4.63584087091349,55.46073968448115],"type":"Point"}
}