{
  "type": "Feature",
  "properties": {
    "iso:country":"GB",
    "wof:name":"LU3 2ET",
    "wof:placetype":"postalcode"
},
  "geometry": {"coordinates":[-0.43626664368059,51.91087038743164],"type":"Point"}
}