{
  "type": "Feature",
  "properties": {
    "iso:country":"GB",
    "wof:name":"FK2 8JD",
    "wof:placetype":"postalcode"
},
  "geometry": {"coordinates":[-3.78606240579825,56.02498199404023],"type":"Point"}
}