{
  "type": "Feature",
  "properties": {
    "iso:country": "GB",
    "wof:name": "FK2 8JD",
    "wof:placetype": "postalcode"
  },
  "geometry": {"coordinates":[-3.786062,56.024982],"type":"Point"}
}
