{
  "type": "Feature",
  "properties": {
    "date:inception_lower":"2006-09-01",
    "date:inception_upper":"2006-09-30",
    "iso:country":"GB",
    "wof:name":"M27 8BG",
    "wof:placetype":"postalcode"
},
  "geometry": {"coordinates":[-2.302417,53.511042],"type":"Point"}
}