{
  "type": "Feature",
  "properties": {
    "iso:country":"GB",
    "wof:name":"TR9 6DN",
    "wof:placetype":"postalcode"
},
  "geometry": {"coordinates":[-4.92279792118822,50.4439635698489],"type":"Point"}
}