{
  "type": "Feature",
  "properties": {
    "iso:country":"GB",
    "wof:name":"FY1 2ND",
    "wof:placetype":"postalcode"
},
  "geometry": {"coordinates":[-3.05035515132472,53.83109887174382],"type":"Point"}
}