{
  "type": "Feature",
  "properties": {
    "iso:country":"GB",
    "wof:name":"BS21 6AP",
    "wof:placetype":"postalcode"
},
  "geometry": {"coordinates":[-2.8372088383427,51.44698218242414],"type":"Point"}
}