{
  "type": "Feature",
  "properties": {
    "iso:country":"GB",
    "wof:name":"NR34 8NH",
    "wof:placetype":"postalcode"
},
  "geometry": {"coordinates":[1.48447163961108,52.41261547035738],"type":"Point"}
}