{
  "type": "Feature",
  "properties": {
    "date:inception_lower":"1980-01-01",
    "date:inception_upper":"1980-01-31",
    "iso:country":"GB",
    "wof:name":"NR34 8NH",
    "wof:placetype":"postalcode"
},
  "geometry": {"coordinates":[1.484472,52.412615],"type":"Point"}
}