{
  "type": "Feature",
  "properties": {
    "iso:country": "GB",
    "wof:name": "NR34 8NH",
    "wof:placetype": "postalcode"
  },
  "geometry": {"coordinates":[1.484472,52.412615],"type":"Point"}
}
