{
  "type": "Feature",
  "properties": {
    "date:inception_lower":"1980-01-01",
    "date:inception_upper":"1980-01-31",
    "iso:country":"GB",
    "wof:name":"BH1 3JE",
    "wof:placetype":"postalcode"
},
  "geometry": {"coordinates":[-1.850935,50.721248],"type":"Point"}
}