{
  "type": "Feature",
  "properties": {
    "iso:country": "GB",
    "wof:name": "BH1 3JE",
    "wof:placetype": "postalcode"
  },
  "geometry": {"coordinates":[-1.850935,50.721248],"type":"Point"}
}
