{
  "type": "Feature",
  "properties": {
    "iso:country":"GB",
    "wof:name":"BH1 3JE",
    "wof:placetype":"postalcode"
},
  "geometry": {"coordinates":[-1.85093504141446,50.72124797117067],"type":"Point"}
}