{
  "type": "Feature",
  "properties": {
    "date:inception_lower": "2017-12-01",
    "date:inception_upper": "2017-12-01",
    "iso:country": "GB",
    "wof:name": "DE55 7QQ",
    "wof:placetype": "postalcode"
  },
  "geometry": {"coordinates":[-1.369097,53.09632],"type":"Point"}
}
