{
  "type": "Feature",
  "properties": {
    "iso:country": "GB",
    "wof:name": "DE55 7QQ",
    "wof:placetype": "postalcode"
  },
  "geometry": {"coordinates":[-1.369708,53.097393],"type":"Point"}
}
