{
  "type": "Feature",
  "properties": {
    "iso:country":"GB",
    "wof:name":"WA3 2AH",
    "wof:placetype":"postalcode"
},
  "geometry": {"coordinates":[-2.55928810187637,53.47419709960604],"type":"Point"}
}