{
  "type": "Feature",
  "properties": {
    "iso:country":"GB",
    "wof:name":"B71 1QA",
    "wof:placetype":"postalcode"
},
  "geometry": {"coordinates":[-1.99432573668856,52.52785143746205],"type":"Point"}
}