{
  "type": "Feature",
  "properties": {
    "iso:country": "GB",
    "wof:name": "OX49 5AJ",
    "wof:placetype": "postalcode"
  },
  "geometry": {"coordinates":[-1.011151,51.646086],"type":"Point"}
}
