{
  "type": "Feature",
  "properties": {
    "date:inception_lower": "1986-04-01",
    "date:inception_upper": "1986-04-01",
    "iso:country": "GB",
    "wof:name": "SY10 9PZ",
    "wof:placetype": "postalcode"
  },
  "geometry": {"coordinates":[-3.056831,52.848625],"type":"Point"}
}
