{
  "type": "Feature",
  "properties": {
    "iso:country":"GB",
    "wof:name":"SY10 9PZ",
    "wof:placetype":"postalcode"
},
  "geometry": {"coordinates":[-3.05683150162933,52.84862470059375],"type":"Point"}
}