{
  "type": "Feature",
  "properties": {
    "date:inception_lower": "2008-02-01",
    "date:inception_upper": "2008-02-01",
    "iso:country": "GB",
    "wof:name": "SL3 0FB",
    "wof:placetype": "postalcode"
  },
  "geometry": {"coordinates":[-0.514293,51.480074],"type":"Point"}
}
