{
  "type": "Feature",
  "properties": {
    "iso:country":"GB",
    "wof:name":"SL3 0FB",
    "wof:placetype":"postalcode"
},
  "geometry": {"coordinates":[-0.51429340516486,51.48007411948254],"type":"Point"}
}