{
  "type": "Feature",
  "properties": {
    "iso:country": "GB",
    "wof:name": "SL3 0FB",
    "wof:placetype": "postalcode"
  },
  "geometry": {"coordinates":[-0.514293,51.480074],"type":"Point"}
}
