{
  "type": "Feature",
  "properties": {
    "iso:country":"GB",
    "wof:name":"WF8 4EN",
    "wof:placetype":"postalcode"
},
  "geometry": {"coordinates":[-1.3278562362113,53.68803818126174],"type":"Point"}
}