{
  "type": "Feature",
  "properties": {
    "iso:country":"GB",
    "wof:name":"OX16 9BS",
    "wof:placetype":"postalcode"
},
  "geometry": {"coordinates":[-1.33159709296211,52.05394276764439],"type":"Point"}
}