{
  "type": "Feature",
  "properties": {
    "iso:country":"GB",
    "wof:name":"S33 9AA",
    "wof:placetype":"postalcode"
},
  "geometry": {"coordinates":[-1.74136547460857,53.32824647907646],"type":"Point"}
}