{
  "type": "Feature",
  "properties": {
    "date:inception_lower": "1997-06-01",
    "date:inception_upper": "1997-06-01",
    "iso:country": "GB",
    "wof:name": "S33 9AA",
    "wof:placetype": "postalcode"
  },
  "geometry": {"coordinates":[-1.741365,53.328246],"type":"Point"}
}
