{
  "type": "Feature",
  "properties": {
    "iso:country": "GB",
    "wof:name": "G20 8NP",
    "wof:placetype": "postalcode"
  },
  "geometry": {"coordinates":[-4.285481,55.881242],"type":"Point"}
}
