{
  "type": "Feature",
  "properties": {
    "iso:country":"GB",
    "wof:name":"HA4 9ST",
    "wof:placetype":"postalcode"
},
  "geometry": {"coordinates":[-0.39949866224506,51.57433966392331],"type":"Point"}
}