{
  "type": "Feature",
  "properties": {
    "iso:country":"GB",
    "wof:name":"DN15 7PL",
    "wof:placetype":"postalcode"
},
  "geometry": {"coordinates":[-0.65982123174843,53.58750458598284],"type":"Point"}
}