{
  "type": "Feature",
  "properties": {
    "iso:country": "GB",
    "wof:name": "SP10 1BX",
    "wof:placetype": "postalcode"
  },
  "geometry": {"coordinates":[-1.475047,51.212108],"type":"Point"}
}
