{
  "type": "Feature",
  "properties": {
    "date:inception_lower": "2017-05-01",
    "date:inception_upper": "2017-05-01",
    "iso:country": "GB",
    "wof:name": "BS15 1FF",
    "wof:placetype": "postalcode"
  },
  "geometry": {"coordinates":[-2.506096,51.464586],"type":"Point"}
}
