{
  "type": "Feature",
  "properties": {
    "iso:country": "GB",
    "wof:name": "BS15 1FF",
    "wof:placetype": "postalcode"
  },
  "geometry": {"coordinates":[-2.506282,51.464496],"type":"Point"}
}
