{
  "type": "Feature",
  "properties": {
    "iso:country": "GB",
    "wof:name": "S20 4HW",
    "wof:placetype": "postalcode"
  },
  "geometry": {"coordinates":[-1.348254,53.319233],"type":"Point"}
}
