{
  "type": "Feature",
  "properties": {
    "iso:country":"GB",
    "wof:name":"S20 4HW",
    "wof:placetype":"postalcode"
},
  "geometry": {"coordinates":[-1.34825410987006,53.31923300940175],"type":"Point"}
}