{
  "type": "Feature",
  "properties": {
    "iso:country":"GB",
    "wof:name":"SA34 0UT",
    "wof:placetype":"postalcode"
},
  "geometry": {"coordinates":[-4.67896789565598,51.85621627114776],"type":"Point"}
}