{
  "type": "Feature",
  "properties": {
    "iso:country":"GB",
    "wof:name":"YO7 3RP",
    "wof:placetype":"postalcode"
},
  "geometry": {"coordinates":[-1.3848115034577,54.17776276683809],"type":"Point"}
}