{
  "type": "Feature",
  "properties": {
    "iso:country":"GB",
    "wof:name":"NE8 1BA",
    "wof:placetype":"postalcode"
},
  "geometry": {"coordinates":[-1.60419603622399,54.96303852411877],"type":"Point"}
}