{
  "type": "Feature",
  "properties": {
    "date:inception_lower": "2019-04-01",
    "date:inception_upper": "2019-04-01",
    "iso:country": "GB",
    "wof:name": "N22 9LJ",
    "wof:placetype": "postalcode"
  },
  "geometry": {"coordinates":[-0.119662,51.598609],"type":"Point"}
}
