{
  "type": "Feature",
  "properties": {
    "iso:country": "GB",
    "wof:name": "TS14 8PJ",
    "wof:placetype": "postalcode"
  },
  "geometry": {"coordinates":[-1.076475,54.531959],"type":"Point"}
}
