{
  "type": "Feature",
  "properties": {
    "iso:country": "GB",
    "wof:name": "HR1 2GY",
    "wof:placetype": "postalcode"
  },
  "geometry": {"coordinates":[-2.709738,52.055379],"type":"Point"}
}
