{
  "type": "Feature",
  "properties": {
    "iso:country":"GB",
    "wof:name":"HR1 2GY",
    "wof:placetype":"postalcode"
},
  "geometry": {"coordinates":[-2.70973757355123,52.05537926473292],"type":"Point"}
}