{
  "type": "Feature",
  "properties": {
    "date:inception_lower": "2008-09-01",
    "date:inception_upper": "2008-09-01",
    "iso:country": "GB",
    "wof:name": "HR1 2GY",
    "wof:placetype": "postalcode"
  },
  "geometry": {"coordinates":[-2.709739,52.055379],"type":"Point"}
}
