{
  "type": "Feature",
  "properties": {
    "iso:country":"GB",
    "wof:name":"B71 4ES",
    "wof:placetype":"postalcode"
},
  "geometry": {"coordinates":[-1.98812086332986,52.52517200498953],"type":"Point"}
}