{
  "type": "Feature",
  "properties": {
    "iso:country":"GB",
    "wof:name":"EN11 8JL",
    "wof:placetype":"postalcode"
},
  "geometry": {"coordinates":[-0.0088396446227,51.7650621492811],"type":"Point"}
}