{
  "type": "Feature",
  "properties": {
    "iso:country": "GB",
    "wof:name": "EN11 8JL",
    "wof:placetype": "postalcode"
  },
  "geometry": {"coordinates":[-0.00884,51.765062],"type":"Point"}
}
