{
  "type": "Feature",
  "properties": {
    "iso:country": "GB",
    "wof:name": "PL5 2DB",
    "wof:placetype": "postalcode"
  },
  "geometry": {"coordinates":[-4.183466,50.416456],"type":"Point"}
}
