{
  "type": "Feature",
  "properties": {
    "iso:country":"GB",
    "wof:name":"BH18 8EJ",
    "wof:placetype":"postalcode"
},
  "geometry": {"coordinates":[-1.99455989421318,50.76510995559991],"type":"Point"}
}