{
  "type": "Feature",
  "properties": {
    "date:inception_lower":"1986-07-01",
    "date:inception_upper":"1986-07-31",
    "iso:country":"GB",
    "wof:name":"BH18 8EJ",
    "wof:placetype":"postalcode"
},
  "geometry": {"coordinates":[-1.99456,50.76511],"type":"Point"}
}