{
  "type": "Feature",
  "properties": {
    "iso:country":"GB",
    "wof:name":"KY2 5HP",
    "wof:placetype":"postalcode"
},
  "geometry": {"coordinates":[-3.16547691682377,56.11872033637683],"type":"Point"}
}