{
  "type": "Feature",
  "properties": {
    "iso:country":"GB",
    "wof:name":"WF10 4JQ",
    "wof:placetype":"postalcode"
},
  "geometry": {"coordinates":[-1.34558453410134,53.72538369057524],"type":"Point"}
}