{
  "type": "Feature",
  "properties": {
    "iso:country":"GB",
    "wof:name":"BN2 4BN",
    "wof:placetype":"postalcode"
},
  "geometry": {"coordinates":[-0.11754735589797,50.84217568771563],"type":"Point"}
}