{
  "type": "Feature",
  "properties": {
    "iso:country": "GB",
    "wof:name": "BN2 4BN",
    "wof:placetype": "postalcode"
  },
  "geometry": {"coordinates":[-0.117547,50.842176],"type":"Point"}
}
