{
  "type": "Feature",
  "properties": {
    "iso:country":"GB",
    "wof:name":"IP27 0QB",
    "wof:placetype":"postalcode"
},
  "geometry": {"coordinates":[0.61429206806052,52.46412871845853],"type":"Point"}
}