{
  "type": "Feature",
  "properties": {
    "iso:country":"GB",
    "wof:name":"W2 4NH",
    "wof:placetype":"postalcode"
},
  "geometry": {"coordinates":[-0.19162274236816,51.51494709002499],"type":"Point"}
}