{
  "type": "Feature",
  "properties": {
    "iso:country":"GB",
    "wof:name":"B64 5HL",
    "wof:placetype":"postalcode"
},
  "geometry": {"coordinates":[-2.08260193457306,52.47181529208705],"type":"Point"}
}