{
  "type": "Feature",
  "properties": {
    "iso:country": "GB",
    "wof:name": "B64 5HL",
    "wof:placetype": "postalcode"
  },
  "geometry": {"coordinates":[-2.082552,52.471803],"type":"Point"}
}
