{
  "type": "Feature",
  "properties": {
    "date:inception_lower": "2022-11-01",
    "date:inception_upper": "2022-11-01",
    "iso:country": "GB",
    "wof:name": "CO4 5JD",
    "wof:placetype": "postalcode"
  },
  "geometry": {"coordinates":[0.948442,51.94731],"type":"Point"}
}
