{
  "type": "Feature",
  "properties": {
    "date:inception_lower":"2001-06-01",
    "date:inception_upper":"2001-06-30",
    "iso:country":"GB",
    "wof:name":"HD9 2QT",
    "wof:placetype":"postalcode"
},
  "geometry": {"coordinates":[-1.810534,53.566293],"type":"Point"}
}