{
  "type": "Feature",
  "properties": {
    "iso:country": "GB",
    "wof:name": "HD9 2QT",
    "wof:placetype": "postalcode"
  },
  "geometry": {"coordinates":[-1.810534,53.566293],"type":"Point"}
}
