{
  "type": "Feature",
  "properties": {
    "iso:country":"GB",
    "wof:name":"HD9 2QT",
    "wof:placetype":"postalcode"
},
  "geometry": {"coordinates":[-1.81053365978265,53.56629279140527],"type":"Point"}
}