{
  "type": "Feature",
  "properties": {
    "iso:country":"GB",
    "wof:name":"CF32 9LH",
    "wof:placetype":"postalcode"
},
  "geometry": {"coordinates":[-3.57325687367729,51.55292198976803],"type":"Point"}
}