{
  "type": "Feature",
  "properties": {
    "date:inception_lower": "2005-03-01",
    "date:inception_upper": "2005-03-01",
    "iso:country": "GB",
    "wof:name": "CF32 9LH",
    "wof:placetype": "postalcode"
  },
  "geometry": {"coordinates":[-3.573257,51.552922],"type":"Point"}
}
