{
  "type": "Feature",
  "properties": {
    "iso:country":"GB",
    "wof:name":"PE9 3PG",
    "wof:placetype":"postalcode"
},
  "geometry": {"coordinates":[-0.52453158080237,52.61892082980869],"type":"Point"}
}