{
  "type": "Feature",
  "properties": {
    "date:inception_lower": "1994-05-01",
    "date:inception_upper": "1994-05-01",
    "iso:country": "GB",
    "wof:name": "PE9 3PG",
    "wof:placetype": "postalcode"
  },
  "geometry": {"coordinates":[-0.52395,52.618329],"type":"Point"}
}
