{
  "type": "Feature",
  "properties": {
    "iso:country":"GB",
    "wof:name":"DT4 0DJ",
    "wof:placetype":"postalcode"
},
  "geometry": {"coordinates":[-2.46607242082476,50.60590481096759],"type":"Point"}
}