{
  "type": "Feature",
  "properties": {
    "iso:country": "GB",
    "wof:name": "DT4 0DJ",
    "wof:placetype": "postalcode"
  },
  "geometry": {"coordinates":[-2.466072,50.605905],"type":"Point"}
}
