{
  "type": "Feature",
  "properties": {
    "iso:country": "GB",
    "wof:name": "EX4 6QN",
    "wof:placetype": "postalcode"
  },
  "geometry": {"coordinates":[-3.523393,50.729742],"type":"Point"}
}
