{
  "type": "Feature",
  "properties": {
    "iso:country":"GB",
    "wof:name":"EX4 6QN",
    "wof:placetype":"postalcode"
},
  "geometry": {"coordinates":[-3.52339321048503,50.72974169765124],"type":"Point"}
}