{
  "type": "Feature",
  "properties": {
    "iso:country":"GB",
    "wof:name":"GU8 4BW",
    "wof:placetype":"postalcode"
},
  "geometry": {"coordinates":[-0.54325553735709,51.12200929662642],"type":"Point"}
}