{
  "type": "Feature",
  "properties": {
    "iso:country": "GB",
    "wof:name": "GU8 4BW",
    "wof:placetype": "postalcode"
  },
  "geometry": {"coordinates":[-0.543255,51.122009],"type":"Point"}
}
