{
  "type": "Feature",
  "properties": {
    "date:inception_lower": "1980-01-01",
    "date:inception_upper": "1980-01-01",
    "iso:country": "GB",
    "wof:name": "LE1 2JU",
    "wof:placetype": "postalcode"
  },
  "geometry": {"coordinates":[-1.124564,52.644517],"type":"Point"}
}
