{
  "type": "Feature",
  "properties": {
    "iso:country":"GB",
    "wof:name":"LE1 2JU",
    "wof:placetype":"postalcode"
},
  "geometry": {"coordinates":[-1.12470395990007,52.64451770442745],"type":"Point"}
}