{
  "type": "Feature",
  "properties": {
    "date:inception_lower": "2012-07-01",
    "date:inception_upper": "2012-07-01",
    "iso:country": "GB",
    "wof:name": "CF72 9WG",
    "wof:placetype": "postalcode"
  },
  "geometry": {"coordinates":[-3.44251,51.535809],"type":"Point"}
}
