{
  "type": "Feature",
  "properties": {
    "iso:country":"GB",
    "wof:name":"SM6 0HR",
    "wof:placetype":"postalcode"
},
  "geometry": {"coordinates":[-0.15225875571146,51.35922023766733],"type":"Point"}
}