{
  "type": "Feature",
  "properties": {
    "date:inception_lower": "1995-07-01",
    "date:inception_upper": "1995-07-01",
    "iso:country": "GB",
    "wof:name": "B66 1BL",
    "wof:placetype": "postalcode"
  },
  "geometry": {"coordinates":[-1.970551,52.5046],"type":"Point"}
}
