{
  "type": "Feature",
  "properties": {
    "iso:country":"GB",
    "wof:name":"B66 1BL",
    "wof:placetype":"postalcode"
},
  "geometry": {"coordinates":[-1.97055063210359,52.50460007471588],"type":"Point"}
}