{
  "type": "Feature",
  "properties": {
    "iso:country":"GB",
    "wof:name":"PE14 0LB",
    "wof:placetype":"postalcode"
},
  "geometry": {"coordinates":[0.1826969079575,52.61539921766781],"type":"Point"}
}