{
  "type": "Feature",
  "properties": {
    "iso:country": "GB",
    "wof:name": "SK8 3RH",
    "wof:placetype": "postalcode"
  },
  "geometry": {"coordinates":[-2.229101,53.373734],"type":"Point"}
}
