{
  "type": "Feature",
  "properties": {
    "iso:country": "GB",
    "wof:name": "LE1 9TG",
    "wof:placetype": "postalcode"
  },
  "geometry": {"coordinates":[-1.13299,52.633575],"type":"Point"}
}
