{
  "type": "Feature",
  "properties": {
    "iso:country":"GB",
    "wof:name":"B43 7BU",
    "wof:placetype":"postalcode"
},
  "geometry": {"coordinates":[-1.90939487840537,52.55581152988649],"type":"Point"}
}