{
  "type": "Feature",
  "properties": {
    "iso:country": "GB",
    "wof:name": "CV23 9DQ",
    "wof:placetype": "postalcode"
  },
  "geometry": {"coordinates":[-1.29519,52.377183],"type":"Point"}
}
