{
  "type": "Feature",
  "properties": {
    "date:inception_lower": "1980-01-01",
    "date:inception_upper": "1980-01-01",
    "iso:country": "GB",
    "wof:name": "IP14 1AQ",
    "wof:placetype": "postalcode"
  },
  "geometry": {"coordinates":[0.99585,52.187307],"type":"Point"}
}
