{
  "type": "Feature",
  "properties": {
    "iso:country":"GB",
    "wof:name":"OX15 4HJ",
    "wof:placetype":"postalcode"
},
  "geometry": {"coordinates":[-1.38155919684431,52.0139367889543],"type":"Point"}
}