{
  "type": "Feature",
  "properties": {
    "iso:country":"GB",
    "wof:name":"CV37 9UU",
    "wof:placetype":"postalcode"
},
  "geometry": {"coordinates":[-1.76111887881093,52.22053484803632],"type":"Point"}
}