{
  "type": "Feature",
  "properties": {
    "iso:country":"GB",
    "wof:name":"TR8 4HF",
    "wof:placetype":"postalcode"
},
  "geometry": {"coordinates":[-4.98080589881774,50.46747095416493],"type":"Point"}
}