{
  "type": "Feature",
  "properties": {
    "date:inception_lower": "1980-01-01",
    "date:inception_upper": "1980-01-01",
    "iso:country": "GB",
    "wof:name": "TR8 4HF",
    "wof:placetype": "postalcode"
  },
  "geometry": {"coordinates":[-4.985255,50.468266],"type":"Point"}
}
