{
  "type": "Feature",
  "properties": {
    "date:inception_lower":"1991-08-01",
    "date:inception_upper":"1991-08-31",
    "iso:country":"GB",
    "wof:name":"EH4 3UA",
    "wof:placetype":"postalcode"
},
  "geometry": {"coordinates":[-3.225054,55.952624],"type":"Point"}
}