{
  "type": "Feature",
  "properties": {
    "date:inception_lower":"2009-06-01",
    "date:inception_upper":"2009-06-30",
    "iso:country":"GB",
    "wof:name":"TN8 6ER",
    "wof:placetype":"postalcode"
},
  "geometry": {"coordinates":[0.064811,51.207119],"type":"Point"}
}