{
  "type": "Feature",
  "properties": {
    "iso:country":"GB",
    "wof:name":"TN8 6ER",
    "wof:placetype":"postalcode"
},
  "geometry": {"coordinates":[0.06481097620688,51.20711942541811],"type":"Point"}
}