{
  "type": "Feature",
  "properties": {
    "iso:country": "GB",
    "wof:name": "TN8 6ER",
    "wof:placetype": "postalcode"
  },
  "geometry": {"coordinates":[0.064811,51.207119],"type":"Point"}
}
