{
  "type": "Feature",
  "properties": {
    "iso:country":"GB",
    "wof:name":"B6 5HY",
    "wof:placetype":"postalcode"
},
  "geometry": {"coordinates":[-1.89380481679929,52.5006186752908],"type":"Point"}
}