{
  "type": "Feature",
  "properties": {
    "iso:country":"GB",
    "wof:name":"CV32 7PT",
    "wof:placetype":"postalcode"
},
  "geometry": {"coordinates":[-1.51076554917842,52.3000922224453],"type":"Point"}
}