{
  "type": "Feature",
  "properties": {
    "iso:country":"GB",
    "wof:name":"B98 8QR",
    "wof:placetype":"postalcode"
},
  "geometry": {"coordinates":[-1.90928968391022,52.31247828378822],"type":"Point"}
}