{
  "type": "Feature",
  "properties": {
    "date:inception_lower": "1980-01-01",
    "date:inception_upper": "1980-01-01",
    "iso:country": "GB",
    "wof:name": "RH20 3HU",
    "wof:placetype": "postalcode"
  },
  "geometry": {"coordinates":[-0.423454,50.922324],"type":"Point"}
}
