{
  "type": "Feature",
  "properties": {
    "iso:country": "GB",
    "wof:name": "TA19 0JJ",
    "wof:placetype": "postalcode"
  },
  "geometry": {"coordinates":[-2.877239,50.961493],"type":"Point"}
}
