{
  "type": "Feature",
  "properties": {
    "iso:country":"GB",
    "wof:name":"TA19 0JJ",
    "wof:placetype":"postalcode"
},
  "geometry": {"coordinates":[-2.87709107961089,50.96145629527939],"type":"Point"}
}