{
  "type": "Feature",
  "properties": {
    "iso:country":"GB",
    "wof:name":"DH1 2TY",
    "wof:placetype":"postalcode"
},
  "geometry": {"coordinates":[-1.53444070769173,54.75374850113502],"type":"Point"}
}