{
  "type": "Feature",
  "properties": {
    "iso:country": "GB",
    "wof:name": "TA4 2QL",
    "wof:placetype": "postalcode"
  },
  "geometry": {"coordinates":[-3.408724,51.033851],"type":"Point"}
}
