{
  "type": "Feature",
  "properties": {
    "iso:country":"GB",
    "wof:name":"TA4 2QL",
    "wof:placetype":"postalcode"
},
  "geometry": {"coordinates":[-3.40872360282203,51.03385138303237],"type":"Point"}
}