{
  "type": "Feature",
  "properties": {
    "date:inception_lower": "2022-12-01",
    "date:inception_upper": "2022-12-01",
    "iso:country": "GB",
    "wof:name": "CB9 7PG",
    "wof:placetype": "postalcode"
  },
  "geometry": {"coordinates":[0.49172,52.092201],"type":"Point"}
}
