{
  "type": "Feature",
  "properties": {
    "iso:country":"GB",
    "wof:name":"PE12 0AB",
    "wof:placetype":"postalcode"
},
  "geometry": {"coordinates":[0.10271959256653,52.7964098086546],"type":"Point"}
}