{
  "type": "Feature",
  "properties": {
    "date:inception_lower":"1985-04-01",
    "date:inception_upper":"1985-04-30",
    "iso:country":"GB",
    "wof:name":"IG7 6PJ",
    "wof:placetype":"postalcode"
},
  "geometry": {"coordinates":[0.077408,51.621038],"type":"Point"}
}