{
  "type": "Feature",
  "properties": {
    "iso:country":"GB",
    "wof:name":"IG7 6PJ",
    "wof:placetype":"postalcode"
},
  "geometry": {"coordinates":[0.07740785422699,51.62103764512954],"type":"Point"}
}