{
  "type": "Feature",
  "properties": {
    "date:inception_lower":"1980-01-01",
    "date:inception_upper":"1980-01-31",
    "iso:country":"GB",
    "wof:name":"NG5 5FP",
    "wof:placetype":"postalcode"
},
  "geometry": {"coordinates":[-1.169928,52.995171],"type":"Point"}
}