{
  "type": "Feature",
  "properties": {
    "date:inception_lower": "1980-01-01",
    "date:inception_upper": "1980-01-01",
    "iso:country": "GB",
    "wof:name": "AL6 9RB",
    "wof:placetype": "postalcode"
  },
  "geometry": {"coordinates":[-0.210547,51.835261],"type":"Point"}
}
