{
  "type": "Feature",
  "properties": {
    "iso:country":"GB",
    "wof:name":"SE1 0XN",
    "wof:placetype":"postalcode"
},
  "geometry": {"coordinates":[-0.10365918846156,51.50427756366655],"type":"Point"}
}