{
  "type": "Feature",
  "properties": {
    "iso:country":"GB",
    "wof:name":"CA4 8DY",
    "wof:placetype":"postalcode"
},
  "geometry": {"coordinates":[-2.85348968843573,54.86763751317112],"type":"Point"}
}