{
  "type": "Feature",
  "properties": {
    "date:inception_lower": "1980-01-01",
    "date:inception_upper": "1980-01-01",
    "iso:country": "GB",
    "wof:name": "B4 7BA",
    "wof:placetype": "postalcode"
  },
  "geometry": {"coordinates":[-1.893194,52.489063],"type":"Point"}
}
