{
  "type": "Feature",
  "properties": {
    "iso:country": "GB",
    "wof:name": "SL7 2NH",
    "wof:placetype": "postalcode"
  },
  "geometry": {"coordinates":[-0.779305,51.570884],"type":"Point"}
}
