{
  "type": "Feature",
  "properties": {
    "iso:country":"GB",
    "wof:name":"SL7 2NH",
    "wof:placetype":"postalcode"
},
  "geometry": {"coordinates":[-0.7793046154807,51.5708835436843],"type":"Point"}
}