{
  "type": "Feature",
  "properties": {
    "iso:country":"GB",
    "wof:name":"N1 9PD",
    "wof:placetype":"postalcode"
},
  "geometry": {"coordinates":[-0.10778721996655,51.53262576912885],"type":"Point"}
}