{
  "type": "Feature",
  "properties": {
    "iso:country":"GB",
    "wof:name":"SL5 0AH",
    "wof:placetype":"postalcode"
},
  "geometry": {"coordinates":[-0.64684659765684,51.39947251504235],"type":"Point"}
}