{
  "type": "Feature",
  "properties": {
    "date:inception_lower": "1980-01-01",
    "date:inception_upper": "1980-01-01",
    "iso:country": "GB",
    "wof:name": "SL5 0AH",
    "wof:placetype": "postalcode"
  },
  "geometry": {"coordinates":[-0.647333,51.399425],"type":"Point"}
}
