{
  "type": "Feature",
  "properties": {
    "iso:country":"GB",
    "wof:name":"TS6 9DD",
    "wof:placetype":"postalcode"
},
  "geometry": {"coordinates":[-1.15137847144381,54.56175201413606],"type":"Point"}
}