{
  "type": "Feature",
  "properties": {
    "date:inception_lower": "1997-06-01",
    "date:inception_upper": "1997-06-01",
    "iso:country": "GB",
    "wof:name": "DN41 8ES",
    "wof:placetype": "postalcode"
  },
  "geometry": {"coordinates":[-0.243824,53.570795],"type":"Point"}
}
