{
  "type": "Feature",
  "properties": {
    "iso:country":"GB",
    "wof:name":"DE22 2JY",
    "wof:placetype":"postalcode"
},
  "geometry": {"coordinates":[-1.49922178904123,52.94783288689928],"type":"Point"}
}