{
  "type": "Feature",
  "properties": {
    "iso:country": "GB",
    "wof:name": "DE22 2JY",
    "wof:placetype": "postalcode"
  },
  "geometry": {"coordinates":[-1.499222,52.947833],"type":"Point"}
}
