{
  "type": "Feature",
  "properties": {
    "iso:country":"GB",
    "wof:name":"SE15 1LE",
    "wof:placetype":"postalcode"
},
  "geometry": {"coordinates":[-0.06267813115504,51.4839138993911],"type":"Point"}
}