{
  "type": "Feature",
  "properties": {
    "iso:country": "GB",
    "wof:name": "SE15 1LE",
    "wof:placetype": "postalcode"
  },
  "geometry": {"coordinates":[-0.062678,51.483914],"type":"Point"}
}
