{
  "type": "Feature",
  "properties": {
    "date:inception_lower":"1980-01-01",
    "date:inception_upper":"1980-01-31",
    "iso:country":"GB",
    "wof:name":"KA8 0LQ",
    "wof:placetype":"postalcode"
},
  "geometry": {"coordinates":[-4.595223,55.472404],"type":"Point"}
}