{
  "type": "Feature",
  "properties": {
    "iso:country":"GB",
    "wof:name":"KA8 0LQ",
    "wof:placetype":"postalcode"
},
  "geometry": {"coordinates":[-4.59522278148305,55.47240371858702],"type":"Point"}
}