{
  "type": "Feature",
  "properties": {
    "iso:country":"GB",
    "wof:name":"CM3 3EX",
    "wof:placetype":"postalcode"
},
  "geometry": {"coordinates":[0.53882774953253,51.75792295250625],"type":"Point"}
}