{
  "type": "Feature",
  "properties": {
    "date:inception_lower":"1992-08-01",
    "date:inception_upper":"1992-08-31",
    "iso:country":"GB",
    "wof:name":"CM3 3EX",
    "wof:placetype":"postalcode"
},
  "geometry": {"coordinates":[0.538828,51.757923],"type":"Point"}
}