{
  "type": "Feature",
  "properties": {
    "iso:country":"GB",
    "wof:name":"LL48 6HB",
    "wof:placetype":"postalcode"
},
  "geometry": {"coordinates":[-4.07711353135666,52.92620476903424],"type":"Point"}
}