{
  "type": "Feature",
  "properties": {
    "iso:country": "GB",
    "wof:name": "LL48 6HB",
    "wof:placetype": "postalcode"
  },
  "geometry": {"coordinates":[-4.077113,52.926205],"type":"Point"}
}
