{
  "type": "Feature",
  "properties": {
    "date:inception_lower": "2002-06-01",
    "date:inception_upper": "2002-06-01",
    "iso:country": "GB",
    "wof:name": "RG18 4BG",
    "wof:placetype": "postalcode"
  },
  "geometry": {"coordinates":[-1.257042,51.409163],"type":"Point"}
}
