{
  "type": "Feature",
  "properties": {
    "iso:country": "GB",
    "wof:name": "CV7 7PB",
    "wof:placetype": "postalcode"
  },
  "geometry": {"coordinates":[-1.643587,52.436373],"type":"Point"}
}
