{
  "type": "Feature",
  "properties": {
    "iso:country":"GB",
    "wof:name":"CV7 7PB",
    "wof:placetype":"postalcode"
},
  "geometry": {"coordinates":[-1.64358706247435,52.43637293494151],"type":"Point"}
}