{
  "type": "Feature",
  "properties": {
    "iso:country": "GB",
    "wof:name": "SK14 4RP",
    "wof:placetype": "postalcode"
  },
  "geometry": {"coordinates":[-2.0787,53.451877],"type":"Point"}
}
