{
  "type": "Feature",
  "properties": {
    "iso:country":"GB",
    "wof:name":"NG31 9GD",
    "wof:placetype":"postalcode"
},
  "geometry": {"coordinates":[-0.61481388912626,52.92493187105525],"type":"Point"}
}