{
  "type": "Feature",
  "properties": {
    "iso:country": "GB",
    "wof:name": "EN2 7DG",
    "wof:placetype": "postalcode"
  },
  "geometry": {"coordinates":[-0.095385,51.653481],"type":"Point"}
}
