{
  "type": "Feature",
  "properties": {
    "date:inception_lower": "1980-01-01",
    "date:inception_upper": "1980-01-01",
    "iso:country": "GB",
    "wof:name": "CW7 3JJ",
    "wof:placetype": "postalcode"
  },
  "geometry": {"coordinates":[-2.506344,53.197831],"type":"Point"}
}
