{
  "type": "Feature",
  "properties": {
    "iso:country":"GB",
    "wof:name":"DL6 1QZ",
    "wof:placetype":"postalcode"
},
  "geometry": {"coordinates":[-1.42285722532483,54.34461337269788],"type":"Point"}
}