{
  "type": "Feature",
  "properties": {
    "iso:country":"GB",
    "wof:name":"M41 6HG",
    "wof:placetype":"postalcode"
},
  "geometry": {"coordinates":[-2.36976167945081,53.44536197388931],"type":"Point"}
}