{
  "type": "Feature",
  "properties": {
    "iso:country":"GB",
    "wof:name":"LL12 7AH",
    "wof:placetype":"postalcode"
},
  "geometry": {"coordinates":[-2.98748965941184,53.05130816082779],"type":"Point"}
}