{
  "type": "Feature",
  "properties": {
    "iso:country":"GB",
    "wof:name":"CW4 8HG",
    "wof:placetype":"postalcode"
},
  "geometry": {"coordinates":[-2.37968442625843,53.21902192012181],"type":"Point"}
}