{
  "type": "Feature",
  "properties": {
    "iso:country": "GB",
    "wof:name": "CW4 8HG",
    "wof:placetype": "postalcode"
  },
  "geometry": {"coordinates":[-2.379684,53.219022],"type":"Point"}
}
