{
  "type": "Feature",
  "properties": {
    "iso:country":"GB",
    "wof:name":"HA2 0GN",
    "wof:placetype":"postalcode"
},
  "geometry": {"coordinates":[-0.36081220505456,51.56944448742674],"type":"Point"}
}