{
  "type": "Feature",
  "properties": {
    "date:inception_lower":"2011-07-01",
    "date:inception_upper":"2011-07-31",
    "iso:country":"GB",
    "wof:name":"HA2 0GN",
    "wof:placetype":"postalcode"
},
  "geometry": {"coordinates":[-0.360812,51.569444],"type":"Point"}
}