{
  "type": "Feature",
  "properties": {
    "iso:country":"GB",
    "wof:name":"SY4 3NF",
    "wof:placetype":"postalcode"
},
  "geometry": {"coordinates":[-2.77654319796228,52.77049358297466],"type":"Point"}
}