{
  "type": "Feature",
  "properties": {
    "iso:country":"GB",
    "wof:name":"SL5 9QA",
    "wof:placetype":"postalcode"
},
  "geometry": {"coordinates":[-0.64557523394434,51.39433228943999],"type":"Point"}
}