{
  "type": "Feature",
  "properties": {
    "iso:country": "GB",
    "wof:name": "SW6 1FX",
    "wof:placetype": "postalcode"
  },
  "geometry": {"coordinates":[-0.19505,51.486342],"type":"Point"}
}
