{
  "type": "Feature",
  "properties": {
    "iso:country":"GB",
    "wof:name":"PO7 6AZ",
    "wof:placetype":"postalcode"
},
  "geometry": {"coordinates":[-1.03746414322656,50.89003370635586],"type":"Point"}
}