{
  "type": "Feature",
  "properties": {
    "iso:country":"GB",
    "wof:name":"NG23 5LF",
    "wof:placetype":"postalcode"
},
  "geometry": {"coordinates":[-0.89747742844619,53.00752993162657],"type":"Point"}
}