{
  "type": "Feature",
  "properties": {
    "iso:country":"GB",
    "wof:name":"TA2 6HS",
    "wof:placetype":"postalcode"
},
  "geometry": {"coordinates":[-3.10806966935405,51.02490493756711],"type":"Point"}
}