{
  "type": "Feature",
  "properties": {
    "iso:country":"GB",
    "wof:name":"CA28 9AR",
    "wof:placetype":"postalcode"
},
  "geometry": {"coordinates":[-3.59848149156401,54.53873983631511],"type":"Point"}
}