{
  "type": "Feature",
  "properties": {
    "date:inception_lower": "1980-01-01",
    "date:inception_upper": "1980-01-01",
    "iso:country": "GB",
    "wof:name": "BH25 5EJ",
    "wof:placetype": "postalcode"
  },
  "geometry": {"coordinates":[-1.647455,50.75885],"type":"Point"}
}
