{
  "type": "Feature",
  "properties": {
    "iso:country":"GB",
    "wof:name":"M32 8QN",
    "wof:placetype":"postalcode"
},
  "geometry": {"coordinates":[-2.29567156623013,53.44964925872561],"type":"Point"}
}