{
  "type": "Feature",
  "properties": {
    "date:inception_lower": "1980-01-01",
    "date:inception_upper": "1980-01-01",
    "iso:country": "GB",
    "wof:name": "M32 8QN",
    "wof:placetype": "postalcode"
  },
  "geometry": {"coordinates":[-2.295672,53.449649],"type":"Point"}
}
