{
  "type": "Feature",
  "properties": {
    "iso:country":"GB",
    "wof:name":"SG7 6HR",
    "wof:placetype":"postalcode"
},
  "geometry": {"coordinates":[-0.19220566187701,51.98394010200058],"type":"Point"}
}