{
  "type": "Feature",
  "properties": {
    "iso:country":"GB",
    "wof:name":"HG2 7NG",
    "wof:placetype":"postalcode"
},
  "geometry": {"coordinates":[-1.50620012873897,53.99592647732902],"type":"Point"}
}