{
  "type": "Feature",
  "properties": {
    "iso:country":"GB",
    "wof:name":"DD10 9JD",
    "wof:placetype":"postalcode"
},
  "geometry": {"coordinates":[-2.46809059052597,56.72875807870776],"type":"Point"}
}