{
  "type": "Feature",
  "properties": {
    "iso:country": "GB",
    "wof:name": "WR11 3GF",
    "wof:placetype": "postalcode"
  },
  "geometry": {"coordinates":[-1.923821,52.092035],"type":"Point"}
}
