{
  "type": "Feature",
  "properties": {
    "iso:country":"GB",
    "wof:name":"BR2 8QQ",
    "wof:placetype":"postalcode"
},
  "geometry": {"coordinates":[0.04518315201024,51.36948268231183],"type":"Point"}
}