{
  "type": "Feature",
  "properties": {
    "iso:country": "GB",
    "wof:name": "BR2 8QQ",
    "wof:placetype": "postalcode"
  },
  "geometry": {"coordinates":[0.045183,51.369483],"type":"Point"}
}
