{
  "type": "Feature",
  "properties": {
    "iso:country": "GB",
    "wof:name": "RG2 9NT",
    "wof:placetype": "postalcode"
  },
  "geometry": {"coordinates":[-0.906558,51.382266],"type":"Point"}
}
