{
  "type": "Feature",
  "properties": {
    "date:inception_lower": "1997-06-01",
    "date:inception_upper": "1997-06-01",
    "iso:country": "GB",
    "wof:name": "DE22 5JZ",
    "wof:placetype": "postalcode"
  },
  "geometry": {"coordinates":[-1.50115,52.966557],"type":"Point"}
}
