{
  "type": "Feature",
  "properties": {
    "iso:country":"GB",
    "wof:name":"DE22 5JZ",
    "wof:placetype":"postalcode"
},
  "geometry": {"coordinates":[-1.50114956749607,52.96655675886512],"type":"Point"}
}