{
  "type": "Feature",
  "properties": {
    "iso:country": "GB",
    "wof:name": "RH13 5DF",
    "wof:placetype": "postalcode"
  },
  "geometry": {"coordinates":[-0.315397,51.058732],"type":"Point"}
}
