{
  "type": "Feature",
  "properties": {
    "date:inception_lower":"1986-07-01",
    "date:inception_upper":"1986-07-31",
    "iso:country":"GB",
    "wof:name":"CM23 3EE",
    "wof:placetype":"postalcode"
},
  "geometry": {"coordinates":[0.165974,51.86801],"type":"Point"}
}