{
  "type": "Feature",
  "properties": {
    "iso:country": "GB",
    "wof:name": "CM23 3EE",
    "wof:placetype": "postalcode"
  },
  "geometry": {"coordinates":[0.165974,51.86801],"type":"Point"}
}
