{
  "type": "Feature",
  "properties": {
    "iso:country":"GB",
    "wof:name":"CM23 3EE",
    "wof:placetype":"postalcode"
},
  "geometry": {"coordinates":[0.16597431037987,51.86800968466747],"type":"Point"}
}