{
  "type": "Feature",
  "properties": {
    "date:inception_lower": "2019-04-01",
    "date:inception_upper": "2019-04-01",
    "iso:country": "GB",
    "wof:name": "LN8 9DE",
    "wof:placetype": "postalcode"
  },
  "geometry": {"coordinates":[-0.343485,53.390939],"type":"Point"}
}
