{
  "type": "Feature",
  "properties": {
    "iso:country": "GB",
    "wof:name": "SP2 7JW",
    "wof:placetype": "postalcode"
  },
  "geometry": {"coordinates":[-1.816137,51.077091],"type":"Point"}
}
