{
  "type": "Feature",
  "properties": {
    "iso:country":"GB",
    "wof:name":"SP2 7JW",
    "wof:placetype":"postalcode"
},
  "geometry": {"coordinates":[-1.81613748154864,51.07709069512526],"type":"Point"}
}