{
  "type": "Feature",
  "properties": {
    "iso:country": "GB",
    "wof:name": "WD25 7SU",
    "wof:placetype": "postalcode"
  },
  "geometry": {"coordinates":[-0.3939,51.700077],"type":"Point"}
}
