{
  "type": "Feature",
  "properties": {
    "iso:country":"GB",
    "wof:name":"WD25 7SU",
    "wof:placetype":"postalcode"
},
  "geometry": {"coordinates":[-0.39385217899084,51.70003446868999],"type":"Point"}
}