{
  "type": "Feature",
  "properties": {
    "date:inception_lower": "2000-10-01",
    "date:inception_upper": "2000-10-01",
    "iso:country": "GB",
    "wof:name": "WD25 7SU",
    "wof:placetype": "postalcode"
  },
  "geometry": {"coordinates":[-0.3939,51.700077],"type":"Point"}
}
