{
  "type": "Feature",
  "properties": {
    "date:inception_lower": "1987-04-01",
    "date:inception_upper": "1987-04-01",
    "iso:country": "GB",
    "wof:name": "LL12 7TX",
    "wof:placetype": "postalcode"
  },
  "geometry": {"coordinates":[-2.967488,53.062817],"type":"Point"}
}
