{
  "type": "Feature",
  "properties": {
    "iso:country":"GB",
    "wof:name":"DN8 5HT",
    "wof:placetype":"postalcode"
},
  "geometry": {"coordinates":[-0.95267920833017,53.60931127137857],"type":"Point"}
}