{
  "type": "Feature",
  "properties": {
    "date:inception_lower": "2000-10-01",
    "date:inception_upper": "2000-10-01",
    "iso:country": "GB",
    "wof:name": "W1G 9LQ",
    "wof:placetype": "postalcode"
  },
  "geometry": {"coordinates":[-0.145511,51.518725],"type":"Point"}
}
