{
  "type": "Feature",
  "properties": {
    "iso:country":"GB",
    "wof:name":"EN8 9HL",
    "wof:placetype":"postalcode"
},
  "geometry": {"coordinates":[-0.03049407591264,51.70737252144118],"type":"Point"}
}