{
  "type": "Feature",
  "properties": {
    "iso:country":"GB",
    "wof:name":"SR6 8BD",
    "wof:placetype":"postalcode"
},
  "geometry": {"coordinates":[-1.37058180112574,54.94197869218078],"type":"Point"}
}