{
  "type": "Feature",
  "properties": {
    "date:inception_lower": "1980-01-01",
    "date:inception_upper": "1980-01-01",
    "iso:country": "GB",
    "wof:name": "NW4 2QP",
    "wof:placetype": "postalcode"
  },
  "geometry": {"coordinates":[-0.214769,51.581279],"type":"Point"}
}
