{
  "type": "Feature",
  "properties": {
    "iso:country":"GB",
    "wof:name":"SK23 0EX",
    "wof:placetype":"postalcode"
},
  "geometry": {"coordinates":[-1.91468732538024,53.32363302290529],"type":"Point"}
}