{
  "type": "Feature",
  "properties": {
    "iso:country": "GB",
    "wof:name": "SK23 0EX",
    "wof:placetype": "postalcode"
  },
  "geometry": {"coordinates":[-1.914687,53.323633],"type":"Point"}
}
