{
  "type": "Feature",
  "properties": {
    "date:inception_lower": "2019-11-01",
    "date:inception_upper": "2019-11-01",
    "iso:country": "GB",
    "wof:name": "BA21 3GA",
    "wof:placetype": "postalcode"
  },
  "geometry": {"coordinates":[-2.665681,50.956344],"type":"Point"}
}
