{
  "type": "Feature",
  "properties": {
    "iso:country":"GB",
    "wof:name":"RG21 3EL",
    "wof:placetype":"postalcode"
},
  "geometry": {"coordinates":[-1.07636155780781,51.25446688198529],"type":"Point"}
}