{
  "type": "Feature",
  "properties": {
    "date:inception_lower": "1980-01-01",
    "date:inception_upper": "1980-01-01",
    "iso:country": "GB",
    "wof:name": "RG21 3EL",
    "wof:placetype": "postalcode"
  },
  "geometry": {"coordinates":[-1.076362,51.254467],"type":"Point"}
}
