{
  "type": "Feature",
  "properties": {
    "iso:country":"GB",
    "wof:name":"CH48 0RR",
    "wof:placetype":"postalcode"
},
  "geometry": {"coordinates":[-3.18407487547335,53.36731539629895],"type":"Point"}
}