{
  "type": "Feature",
  "properties": {
    "iso:country": "GB",
    "wof:name": "KY8 4PQ",
    "wof:placetype": "postalcode"
  },
  "geometry": {"coordinates":[-2.994576,56.19435],"type":"Point"}
}
