{
  "type": "Feature",
  "properties": {
    "iso:country":"GB",
    "wof:name":"KY8 4PQ",
    "wof:placetype":"postalcode"
},
  "geometry": {"coordinates":[-2.99457632848166,56.19434982737058],"type":"Point"}
}