{
  "type": "Feature",
  "properties": {
    "iso:country":"GB",
    "wof:name":"DH6 5EP",
    "wof:placetype":"postalcode"
},
  "geometry": {"coordinates":[-1.52780212079545,54.74341518851103],"type":"Point"}
}