{
  "type": "Feature",
  "properties": {
    "date:inception_lower": "1980-01-01",
    "date:inception_upper": "1980-01-01",
    "iso:country": "GB",
    "wof:name": "DH6 5EP",
    "wof:placetype": "postalcode"
  },
  "geometry": {"coordinates":[-1.527802,54.743415],"type":"Point"}
}
