{
  "type": "Feature",
  "properties": {
    "iso:country":"GB",
    "wof:name":"TN17 4EL",
    "wof:placetype":"postalcode"
},
  "geometry": {"coordinates":[0.57983976432891,51.07275939766897],"type":"Point"}
}