{
  "type": "Feature",
  "properties": {
    "iso:country":"GB",
    "wof:name":"NG34 8AD",
    "wof:placetype":"postalcode"
},
  "geometry": {"coordinates":[-0.41720482859771,53.00718714586226],"type":"Point"}
}