{
  "type": "Feature",
  "properties": {
    "iso:country": "GB",
    "wof:name": "NR32 3JR",
    "wof:placetype": "postalcode"
  },
  "geometry": {"coordinates":[1.713714,52.49269],"type":"Point"}
}
