{
  "type": "Feature",
  "properties": {
    "date:inception_lower": "1980-01-01",
    "date:inception_upper": "1980-01-01",
    "iso:country": "GB",
    "wof:name": "RG25 2HP",
    "wof:placetype": "postalcode"
  },
  "geometry": {"coordinates":[-1.12053,51.215771],"type":"Point"}
}
