{
  "type": "Feature",
  "properties": {
    "iso:country": "GB",
    "wof:name": "RG25 2HP",
    "wof:placetype": "postalcode"
  },
  "geometry": {"coordinates":[-1.12063,51.215799],"type":"Point"}
}
