{
  "type": "Feature",
  "properties": {
    "iso:country":"GB",
    "wof:name":"RG25 2HP",
    "wof:placetype":"postalcode"
},
  "geometry": {"coordinates":[-1.1205469522639,51.21577237124303],"type":"Point"}
}