{
  "type": "Feature",
  "properties": {
    "iso:country": "GB",
    "wof:name": "WA13 9UU",
    "wof:placetype": "postalcode"
  },
  "geometry": {"coordinates":[-2.430559,53.397896],"type":"Point"}
}
