{
  "type": "Feature",
  "properties": {
    "iso:country":"GB",
    "wof:name":"WA13 9UU",
    "wof:placetype":"postalcode"
},
  "geometry": {"coordinates":[-2.43055900721643,53.39789615609457],"type":"Point"}
}