{
  "type": "Feature",
  "properties": {
    "iso:country":"GB",
    "wof:name":"SP11 9QQ",
    "wof:placetype":"postalcode"
},
  "geometry": {"coordinates":[-1.62504361227493,51.25732005038183],"type":"Point"}
}