{
  "type": "Feature",
  "properties": {
    "iso:country": "GB",
    "wof:name": "SW15 5BU",
    "wof:placetype": "postalcode"
  },
  "geometry": {"coordinates":[-0.236057,51.454844],"type":"Point"}
}
