{
  "type": "Feature",
  "properties": {
    "iso:country":"GB",
    "wof:name":"LN2 2HF",
    "wof:placetype":"postalcode"
},
  "geometry": {"coordinates":[-0.52727620354572,53.24842204062596],"type":"Point"}
}