{
  "type": "Feature",
  "properties": {
    "iso:country":"GB",
    "wof:name":"CB1 3JR",
    "wof:placetype":"postalcode"
},
  "geometry": {"coordinates":[0.17658886198029,52.19210014814183],"type":"Point"}
}