{
  "type": "Feature",
  "properties": {
    "iso:country": "GB",
    "wof:name": "CB1 3JR",
    "wof:placetype": "postalcode"
  },
  "geometry": {"coordinates":[0.176589,52.1921],"type":"Point"}
}
