{
  "type": "Feature",
  "properties": {
    "iso:country":"GB",
    "wof:name":"OX16 9JX",
    "wof:placetype":"postalcode"
},
  "geometry": {"coordinates":[-1.35262181325365,52.05026599140035],"type":"Point"}
}