{
  "type": "Feature",
  "properties": {
    "date:inception_lower":"2010-11-01",
    "date:inception_upper":"2010-11-30",
    "iso:country":"GB",
    "wof:name":"L20 0WX",
    "wof:placetype":"postalcode"
},
  "geometry": {"coordinates":[-2.969084,53.469219],"type":"Point"}
}