{
  "type": "Feature",
  "properties": {
    "iso:country": "GB",
    "wof:name": "SL5 9BL",
    "wof:placetype": "postalcode"
  },
  "geometry": {"coordinates":[-0.668633,51.403166],"type":"Point"}
}
