{
  "type": "Feature",
  "properties": {
    "date:inception_lower":"1980-01-01",
    "date:inception_upper":"1980-01-31",
    "iso:country":"GB",
    "wof:name":"SA12 8HN",
    "wof:placetype":"postalcode"
},
  "geometry": {"coordinates":[-3.786691,51.599224],"type":"Point"}
}