{
  "type": "Feature",
  "properties": {
    "iso:country":"GB",
    "wof:name":"DY9 8UE",
    "wof:placetype":"postalcode"
},
  "geometry": {"coordinates":[-2.10896107282521,52.45715819608092],"type":"Point"}
}