{
  "type": "Feature",
  "properties": {
    "iso:country":"GB",
    "wof:name":"KT9 2ED",
    "wof:placetype":"postalcode"
},
  "geometry": {"coordinates":[-0.29438400801387,51.35848012625352],"type":"Point"}
}