{
  "type": "Feature",
  "properties": {
    "date:inception_lower": "1980-01-01",
    "date:inception_upper": "1980-01-01",
    "iso:country": "GB",
    "wof:name": "CT21 4DY",
    "wof:placetype": "postalcode"
  },
  "geometry": {"coordinates":[1.069641,51.071376],"type":"Point"}
}
