{
  "type": "Feature",
  "properties": {
    "date:inception_lower":"2009-04-01",
    "date:inception_upper":"2009-04-30",
    "iso:country":"GB",
    "wof:name":"S60 1FF",
    "wof:placetype":"postalcode"
},
  "geometry": {"coordinates":[-1.356988,53.430211],"type":"Point"}
}