{
  "type": "Feature",
  "properties": {
    "iso:country": "GB",
    "wof:name": "S60 1FF",
    "wof:placetype": "postalcode"
  },
  "geometry": {"coordinates":[-1.356988,53.430211],"type":"Point"}
}
