{
  "type": "Feature",
  "properties": {
    "iso:country":"GB",
    "wof:name":"S60 1FF",
    "wof:placetype":"postalcode"
},
  "geometry": {"coordinates":[-1.35698848180042,53.43021064153853],"type":"Point"}
}