{
  "type": "Feature",
  "properties": {
    "date:inception_lower":"1980-01-01",
    "date:inception_upper":"1980-01-31",
    "iso:country":"GB",
    "wof:name":"HU12 0TJ",
    "wof:placetype":"postalcode"
},
  "geometry": {"coordinates":[0.116081,53.652496],"type":"Point"}
}