{
  "type": "Feature",
  "properties": {
    "iso:country":"GB",
    "wof:name":"RH20 2AH",
    "wof:placetype":"postalcode"
},
  "geometry": {"coordinates":[-0.5012471131627,50.95792611635911],"type":"Point"}
}