{
  "type": "Feature",
  "properties": {
    "iso:country": "GB",
    "wof:name": "HU4 7RH",
    "wof:placetype": "postalcode"
  },
  "geometry": {"coordinates":[-0.41635,53.746425],"type":"Point"}
}
