{
  "type": "Feature",
  "properties": {
    "iso:country":"GB",
    "wof:name":"HU4 7RH",
    "wof:placetype":"postalcode"
},
  "geometry": {"coordinates":[-0.41635049446411,53.74642483669765],"type":"Point"}
}