{
  "type": "Feature",
  "properties": {
    "date:inception_lower": "1980-01-01",
    "date:inception_upper": "1980-01-01",
    "iso:country": "GB",
    "wof:name": "NG5 5BY",
    "wof:placetype": "postalcode"
  },
  "geometry": {"coordinates":[-1.181671,53.010608],"type":"Point"}
}
