{
  "type": "Feature",
  "properties": {
    "iso:country":"GB",
    "wof:name":"NG5 5BY",
    "wof:placetype":"postalcode"
},
  "geometry": {"coordinates":[-1.18186872723696,53.01059898545661],"type":"Point"}
}