{
  "type": "Feature",
  "properties": {
    "date:inception_lower":"1980-01-01",
    "date:inception_upper":"1980-01-31",
    "iso:country":"GB",
    "wof:name":"SS8 9EN",
    "wof:placetype":"postalcode"
},
  "geometry": {"coordinates":[0.581286,51.522029],"type":"Point"}
}