{
  "type": "Feature",
  "properties": {
    "date:inception_lower": "1980-01-01",
    "date:inception_upper": "1980-01-01",
    "iso:country": "GB",
    "wof:name": "WF9 5JP",
    "wof:placetype": "postalcode"
  },
  "geometry": {"coordinates":[-1.3768,53.62827],"type":"Point"}
}
