{
  "type": "Feature",
  "properties": {
    "iso:country":"GB",
    "wof:name":"WF9 5JP",
    "wof:placetype":"postalcode"
},
  "geometry": {"coordinates":[-1.37680033069096,53.62826970243799],"type":"Point"}
}