{
  "type": "Feature",
  "properties": {
    "date:inception_lower":"2008-05-01",
    "date:inception_upper":"2008-05-31",
    "iso:country":"GB",
    "wof:name":"LS10 2BD",
    "wof:placetype":"postalcode"
},
  "geometry": {"coordinates":[-1.531541,53.77497],"type":"Point"}
}