{
  "type": "Feature",
  "properties": {
    "iso:country": "GB",
    "wof:name": "LS10 2BD",
    "wof:placetype": "postalcode"
  },
  "geometry": {"coordinates":[-1.531541,53.77497],"type":"Point"}
}
