{
  "type": "Feature",
  "properties": {
    "iso:country": "GB",
    "wof:name": "ST21 6RU",
    "wof:placetype": "postalcode"
  },
  "geometry": {"coordinates":[-2.250228,52.912791],"type":"Point"}
}
