{
  "type": "Feature",
  "properties": {
    "iso:country":"GB",
    "wof:name":"ST21 6RU",
    "wof:placetype":"postalcode"
},
  "geometry": {"coordinates":[-2.25022813050015,52.91279146499392],"type":"Point"}
}