{
  "type": "Feature",
  "properties": {
    "iso:country":"GB",
    "wof:name":"L36 2LW",
    "wof:placetype":"postalcode"
},
  "geometry": {"coordinates":[-2.85762214778739,53.41919625140889],"type":"Point"}
}