{
  "type": "Feature",
  "properties": {
    "iso:country":"GB",
    "wof:name":"SN3 4JT",
    "wof:placetype":"postalcode"
},
  "geometry": {"coordinates":[-1.74781666661777,51.57800169029795],"type":"Point"}
}