{
  "type": "Feature",
  "properties": {
    "iso:country":"GB",
    "wof:name":"NP19 7LE",
    "wof:placetype":"postalcode"
},
  "geometry": {"coordinates":[-2.97351381380295,51.59854576883409],"type":"Point"}
}