{
  "type": "Feature",
  "properties": {
    "iso:country":"GB",
    "wof:name":"YO12 6EA",
    "wof:placetype":"postalcode"
},
  "geometry": {"coordinates":[-0.43454493751371,54.28841940914828],"type":"Point"}
}