{
  "type": "Feature",
  "properties": {
    "iso:country":"GB",
    "wof:name":"OL7 9EZ",
    "wof:placetype":"postalcode"
},
  "geometry": {"coordinates":[-2.10677403595008,53.49614148466308],"type":"Point"}
}