{
  "type": "Feature",
  "properties": {
    "iso:country": "GB",
    "wof:name": "OL7 9EZ",
    "wof:placetype": "postalcode"
  },
  "geometry": {"coordinates":[-2.106774,53.496141],"type":"Point"}
}
