{
  "type": "Feature",
  "properties": {
    "date:inception_lower": "1995-07-01",
    "date:inception_upper": "1995-07-01",
    "iso:country": "GB",
    "wof:name": "HS9 5UU",
    "wof:placetype": "postalcode"
  },
  "geometry": {"coordinates":[-7.412962,56.98194],"type":"Point"}
}
