{
  "type": "Feature",
  "properties": {
    "iso:country":"GB",
    "wof:name":"HS9 5UU",
    "wof:placetype":"postalcode"
},
  "geometry": {"coordinates":[-7.41296229548851,56.98193959136885],"type":"Point"}
}