{
  "type": "Feature",
  "properties": {
    "iso:country":"GB",
    "wof:name":"DH5 9PS",
    "wof:placetype":"postalcode"
},
  "geometry": {"coordinates":[-1.45799133302989,54.82975432586797],"type":"Point"}
}