{
  "type": "Feature",
  "properties": {
    "iso:country":"GB",
    "wof:name":"PA2 7JN",
    "wof:placetype":"postalcode"
},
  "geometry": {"coordinates":[-4.40346509588963,55.83516916470209],"type":"Point"}
}