{
  "type": "Feature",
  "properties": {
    "date:inception_lower":"1980-01-01",
    "date:inception_upper":"1980-01-31",
    "iso:country":"GB",
    "wof:name":"LS17 6LQ",
    "wof:placetype":"postalcode"
},
  "geometry": {"coordinates":[-1.537275,53.837208],"type":"Point"}
}