{
  "type": "Feature",
  "properties": {
    "iso:country": "GB",
    "wof:name": "LS17 6LQ",
    "wof:placetype": "postalcode"
  },
  "geometry": {"coordinates":[-1.537275,53.837208],"type":"Point"}
}
