{
  "type": "Feature",
  "properties": {
    "date:inception_lower": "1980-01-01",
    "date:inception_upper": "1980-01-01",
    "iso:country": "GB",
    "wof:name": "GU6 7EW",
    "wof:placetype": "postalcode"
  },
  "geometry": {"coordinates":[-0.476026,51.143221],"type":"Point"}
}
