{
  "type": "Feature",
  "properties": {
    "iso:country":"GB",
    "wof:name":"GU6 7EW",
    "wof:placetype":"postalcode"
},
  "geometry": {"coordinates":[-0.47602653864495,51.14322060815726],"type":"Point"}
}