{
  "type": "Feature",
  "properties": {
    "iso:country":"GB",
    "wof:name":"HP6 6UT",
    "wof:placetype":"postalcode"
},
  "geometry": {"coordinates":[-0.5883755787923,51.67560223138412],"type":"Point"}
}