{
  "type": "Feature",
  "properties": {
    "iso:country":"GB",
    "wof:name":"BS36 2RN",
    "wof:placetype":"postalcode"
},
  "geometry": {"coordinates":[-2.47664859486829,51.52586302326219],"type":"Point"}
}