{
  "type": "Feature",
  "properties": {
    "iso:country": "GB",
    "wof:name": "BD12 9JH",
    "wof:placetype": "postalcode"
  },
  "geometry": {"coordinates":[-1.769389,53.73856],"type":"Point"}
}
