{
  "type": "Feature",
  "properties": {
    "iso:country": "GB",
    "wof:name": "DD6 8TA",
    "wof:placetype": "postalcode"
  },
  "geometry": {"coordinates":[-2.964669,56.431019],"type":"Point"}
}
