{
  "type": "Feature",
  "properties": {
    "iso:country":"GB",
    "wof:name":"DD6 8TA",
    "wof:placetype":"postalcode"
},
  "geometry": {"coordinates":[-2.9646689382528,56.43101942316271],"type":"Point"}
}