{
  "type": "Feature",
  "properties": {
    "date:inception_lower": "1993-02-01",
    "date:inception_upper": "1993-02-01",
    "iso:country": "GB",
    "wof:name": "DD6 8TA",
    "wof:placetype": "postalcode"
  },
  "geometry": {"coordinates":[-2.964669,56.431019],"type":"Point"}
}
