{
  "type": "Feature",
  "properties": {
    "iso:country":"GB",
    "wof:name":"TS4 2LR",
    "wof:placetype":"postalcode"
},
  "geometry": {"coordinates":[-1.22201547009782,54.56366456918459],"type":"Point"}
}