{
  "type": "Feature",
  "properties": {
    "iso:country": "GB",
    "wof:name": "CB23 7PX",
    "wof:placetype": "postalcode"
  },
  "geometry": {"coordinates":[0.069655,52.20927],"type":"Point"}
}
