{
  "type": "Feature",
  "properties": {
    "date:inception_lower": "2006-09-01",
    "date:inception_upper": "2006-09-01",
    "iso:country": "GB",
    "wof:name": "CB23 7PX",
    "wof:placetype": "postalcode"
  },
  "geometry": {"coordinates":[0.06937,52.209437],"type":"Point"}
}
