{
  "type": "Feature",
  "properties": {
    "iso:country":"GB",
    "wof:name":"CB23 7PX",
    "wof:placetype":"postalcode"
},
  "geometry": {"coordinates":[0.06934152898221,52.20942428397205],"type":"Point"}
}