{
  "type": "Feature",
  "properties": {
    "iso:country":"GB",
    "wof:name":"CV5 8NY",
    "wof:placetype":"postalcode"
},
  "geometry": {"coordinates":[-1.54342444246876,52.40690988855535],"type":"Point"}
}