{
  "type": "Feature",
  "properties": {
    "iso:country": "GB",
    "wof:name": "CM17 0LJ",
    "wof:placetype": "postalcode"
  },
  "geometry": {"coordinates":[0.157272,51.789324],"type":"Point"}
}
