{
  "type": "Feature",
  "properties": {
    "date:inception_lower":"1981-06-01",
    "date:inception_upper":"1981-06-30",
    "iso:country":"GB",
    "wof:name":"CH5 2NU",
    "wof:placetype":"postalcode"
},
  "geometry": {"coordinates":[-3.002517,53.229349],"type":"Point"}
}