{
  "type": "Feature",
  "properties": {
    "iso:country":"GB",
    "wof:name":"CH5 2NU",
    "wof:placetype":"postalcode"
},
  "geometry": {"coordinates":[-3.00176366637574,53.22910572283542],"type":"Point"}
}