{
  "type": "Feature",
  "properties": {
    "iso:country":"GB",
    "wof:name":"TS20 1DQ",
    "wof:placetype":"postalcode"
},
  "geometry": {"coordinates":[-1.31109657979423,54.59020369289661],"type":"Point"}
}