{
  "type": "Feature",
  "properties": {
    "date:inception_lower": "1980-01-01",
    "date:inception_upper": "1980-01-01",
    "iso:country": "GB",
    "wof:name": "WS3 2AD",
    "wof:placetype": "postalcode"
  },
  "geometry": {"coordinates":[-1.999263,52.606063],"type":"Point"}
}
