{
  "type": "Feature",
  "properties": {
    "iso:country": "GB",
    "wof:name": "WS3 2AD",
    "wof:placetype": "postalcode"
  },
  "geometry": {"coordinates":[-1.999263,52.606063],"type":"Point"}
}
