{
  "type": "Feature",
  "properties": {
    "iso:country": "GB",
    "wof:name": "PR4 2UA",
    "wof:placetype": "postalcode"
  },
  "geometry": {"coordinates":[-2.874664,53.780862],"type":"Point"}
}
