{
  "type": "Feature",
  "properties": {
    "iso:country":"GB",
    "wof:name":"PR4 2UA",
    "wof:placetype":"postalcode"
},
  "geometry": {"coordinates":[-2.87466410698747,53.78086229444527],"type":"Point"}
}