{
  "type": "Feature",
  "properties": {
    "iso:country": "GB",
    "wof:name": "CH47 0JY",
    "wof:placetype": "postalcode"
  },
  "geometry": {"coordinates":[-3.162439,53.397354],"type":"Point"}
}
