{
  "type": "Feature",
  "properties": {
    "iso:country":"GB",
    "wof:name":"CH47 0JY",
    "wof:placetype":"postalcode"
},
  "geometry": {"coordinates":[-3.16243945762635,53.39735400333151],"type":"Point"}
}