{
  "type": "Feature",
  "properties": {
    "date:inception_lower":"2005-10-01",
    "date:inception_upper":"2005-10-31",
    "iso:country":"GB",
    "wof:name":"CH47 0JY",
    "wof:placetype":"postalcode"
},
  "geometry": {"coordinates":[-3.162439,53.397354],"type":"Point"}
}