{
  "type": "Feature",
  "properties": {
    "date:inception_lower": "1980-01-01",
    "date:inception_upper": "1980-01-01",
    "iso:country": "GB",
    "wof:name": "EX34 7HF",
    "wof:placetype": "postalcode"
  },
  "geometry": {"coordinates":[-4.157375,51.175788],"type":"Point"}
}
