{
  "type": "Feature",
  "properties": {
    "iso:country": "GB",
    "wof:name": "EX34 7HF",
    "wof:placetype": "postalcode"
  },
  "geometry": {"coordinates":[-4.157375,51.175788],"type":"Point"}
}
