{
  "type": "Feature",
  "properties": {
    "iso:country":"GB",
    "wof:name":"EX34 7HF",
    "wof:placetype":"postalcode"
},
  "geometry": {"coordinates":[-4.1575505908782,51.1757851016195],"type":"Point"}
}