{
  "type": "Feature",
  "properties": {
    "iso:country":"GB",
    "wof:name":"IP14 4DA",
    "wof:placetype":"postalcode"
},
  "geometry": {"coordinates":[1.01657926881785,52.19589869729998],"type":"Point"}
}