{
  "type": "Feature",
  "properties": {
    "date:inception_lower": "1980-01-01",
    "date:inception_upper": "1980-01-01",
    "iso:country": "GB",
    "wof:name": "IP14 4DA",
    "wof:placetype": "postalcode"
  },
  "geometry": {"coordinates":[1.016683,52.195904],"type":"Point"}
}
