{
  "type": "Feature",
  "properties": {
    "date:inception_lower":"1995-12-01",
    "date:inception_upper":"1995-12-31",
    "iso:country":"GB",
    "wof:name":"SE1 2EH",
    "wof:placetype":"postalcode"
},
  "geometry": {"coordinates":[-0.078352,51.501303],"type":"Point"}
}