{
  "type": "Feature",
  "properties": {
    "iso:country":"GB",
    "wof:name":"SE1 2EH",
    "wof:placetype":"postalcode"
},
  "geometry": {"coordinates":[-0.07835193080343,51.50130273170005],"type":"Point"}
}