{
  "type": "Feature",
  "properties": {
    "iso:country":"GB",
    "wof:name":"EX5 2QG",
    "wof:placetype":"postalcode"
},
  "geometry": {"coordinates":[-3.34949866639152,50.77436813179086],"type":"Point"}
}