{
  "type": "Feature",
  "properties": {
    "iso:country": "GB",
    "wof:name": "L25 5JN",
    "wof:placetype": "postalcode"
  },
  "geometry": {"coordinates":[-2.866005,53.380762],"type":"Point"}
}
