{
  "type": "Feature",
  "properties": {
    "iso:country":"GB",
    "wof:name":"L25 5JN",
    "wof:placetype":"postalcode"
},
  "geometry": {"coordinates":[-2.86600608011414,53.38082524241666],"type":"Point"}
}