{
  "type": "Feature",
  "properties": {
    "iso:country":"GB",
    "wof:name":"BL6 7LP",
    "wof:placetype":"postalcode"
},
  "geometry": {"coordinates":[-2.55040918575346,53.60404979405158],"type":"Point"}
}