{
  "type": "Feature",
  "properties": {
    "iso:country":"GB",
    "wof:name":"CV1 2PY",
    "wof:placetype":"postalcode"
},
  "geometry": {"coordinates":[-1.50674280079495,52.40607937613056],"type":"Point"}
}