{
  "type": "Feature",
  "properties": {
    "iso:country": "GB",
    "wof:name": "CO9 1FP",
    "wof:placetype": "postalcode"
  },
  "geometry": {"coordinates":[0.623181,51.936879],"type":"Point"}
}
