{
  "type": "Feature",
  "properties": {
    "date:inception_lower": "2008-02-01",
    "date:inception_upper": "2008-02-01",
    "iso:country": "GB",
    "wof:name": "DT3 5FJ",
    "wof:placetype": "postalcode"
  },
  "geometry": {"coordinates":[-2.468644,50.655822],"type":"Point"}
}
