{
  "type": "Feature",
  "properties": {
    "iso:country": "GB",
    "wof:name": "DT3 5FJ",
    "wof:placetype": "postalcode"
  },
  "geometry": {"coordinates":[-2.468658,50.655822],"type":"Point"}
}
