{
  "type": "Feature",
  "properties": {
    "iso:country":"GB",
    "wof:name":"DT3 5FJ",
    "wof:placetype":"postalcode"
},
  "geometry": {"coordinates":[-2.46874524944193,50.65584047180545],"type":"Point"}
}