{
  "type": "Feature",
  "properties": {
    "iso:country":"GB",
    "wof:name":"M20 4NG",
    "wof:placetype":"postalcode"
},
  "geometry": {"coordinates":[-2.22256156635868,53.43398819385946],"type":"Point"}
}