{
  "type": "Feature",
  "properties": {
    "iso:country":"GB",
    "wof:name":"WS14 0BL",
    "wof:placetype":"postalcode"
},
  "geometry": {"coordinates":[-1.88231422500765,52.65543038889533],"type":"Point"}
}