{
  "type": "Feature",
  "properties": {
    "date:inception_lower": "2023-05-01",
    "date:inception_upper": "2023-05-01",
    "iso:country": "GB",
    "wof:name": "SN1 3HL",
    "wof:placetype": "postalcode"
  },
  "geometry": {"coordinates":[-1.775848,51.553738],"type":"Point"}
}
