{
  "type": "Feature",
  "properties": {
    "iso:country":"GB",
    "wof:name":"SY11 1BD",
    "wof:placetype":"postalcode"
},
  "geometry": {"coordinates":[-3.06166741650058,52.86241684901444],"type":"Point"}
}