{
  "type": "Feature",
  "properties": {
    "iso:country": "GB",
    "wof:name": "SY11 1BD",
    "wof:placetype": "postalcode"
  },
  "geometry": {"coordinates":[-3.061667,52.862417],"type":"Point"}
}
