{
  "type": "Feature",
  "properties": {
    "iso:country": "GB",
    "wof:name": "OL14 6BD",
    "wof:placetype": "postalcode"
  },
  "geometry": {"coordinates":[-2.093547,53.683555],"type":"Point"}
}
