{
  "type": "Feature",
  "properties": {
    "date:inception_lower": "2003-02-01",
    "date:inception_upper": "2003-02-01",
    "iso:country": "GB",
    "wof:name": "OL14 6BD",
    "wof:placetype": "postalcode"
  },
  "geometry": {"coordinates":[-2.093547,53.683555],"type":"Point"}
}
