{
  "type": "Feature",
  "properties": {
    "date:inception_lower": "1980-01-01",
    "date:inception_upper": "1980-01-01",
    "iso:country": "GB",
    "wof:name": "TS24 9NG",
    "wof:placetype": "postalcode"
  },
  "geometry": {"coordinates":[-1.226599,54.709552],"type":"Point"}
}
