{
  "type": "Feature",
  "properties": {
    "iso:country":"GB",
    "wof:name":"TS24 9NG",
    "wof:placetype":"postalcode"
},
  "geometry": {"coordinates":[-1.22659870400416,54.70955238525036],"type":"Point"}
}