{
  "type": "Feature",
  "properties": {
    "iso:country":"GB",
    "wof:name":"SO51 8AP",
    "wof:placetype":"postalcode"
},
  "geometry": {"coordinates":[-1.49607397073731,50.99164968545749],"type":"Point"}
}