{
  "type": "Feature",
  "properties": {
    "iso:country":"GB",
    "wof:name":"CR8 4AG",
    "wof:placetype":"postalcode"
},
  "geometry": {"coordinates":[-0.11681756239043,51.32469014941189],"type":"Point"}
}