{
  "type": "Feature",
  "properties": {
    "iso:country": "GB",
    "wof:name": "NG11 6AB",
    "wof:placetype": "postalcode"
  },
  "geometry": {"coordinates":[-1.164286,52.896823],"type":"Point"}
}
