{
  "type": "Feature",
  "properties": {
    "iso:country":"GB",
    "wof:name":"NG11 6AB",
    "wof:placetype":"postalcode"
},
  "geometry": {"coordinates":[-1.16428605787453,52.89682256873767],"type":"Point"}
}