{
  "type": "Feature",
  "properties": {
    "date:inception_lower": "1980-01-01",
    "date:inception_upper": "1980-01-01",
    "iso:country": "GB",
    "wof:name": "CA22 2NX",
    "wof:placetype": "postalcode"
  },
  "geometry": {"coordinates":[-3.514287,54.456101],"type":"Point"}
}
