{
  "type": "Feature",
  "properties": {
    "iso:country":"GB",
    "wof:name":"TN8 7LL",
    "wof:placetype":"postalcode"
},
  "geometry": {"coordinates":[0.11029103870172,51.17320374096013],"type":"Point"}
}