{
  "type": "Feature",
  "properties": {
    "date:inception_lower":"1980-01-01",
    "date:inception_upper":"1980-01-31",
    "iso:country":"GB",
    "wof:name":"TN8 7LL",
    "wof:placetype":"postalcode"
},
  "geometry": {"coordinates":[0.110291,51.173204],"type":"Point"}
}