{
  "type": "Feature",
  "properties": {
    "iso:country":"GB",
    "wof:name":"CM20 2QQ",
    "wof:placetype":"postalcode"
},
  "geometry": {"coordinates":[0.09978521665314,51.77700196381507],"type":"Point"}
}