{
  "type": "Feature",
  "properties": {
    "iso:country":"GB",
    "wof:name":"IP21 4BY",
    "wof:placetype":"postalcode"
},
  "geometry": {"coordinates":[1.10778926425503,52.34465819156521],"type":"Point"}
}