{
  "type": "Feature",
  "properties": {
    "iso:country":"GB",
    "wof:name":"HP21 7AX",
    "wof:placetype":"postalcode"
},
  "geometry": {"coordinates":[-0.78651938351353,51.81274335384958],"type":"Point"}
}