{
  "type": "Feature",
  "properties": {
    "date:inception_lower": "2005-01-01",
    "date:inception_upper": "2005-01-01",
    "iso:country": "GB",
    "wof:name": "HP21 7AX",
    "wof:placetype": "postalcode"
  },
  "geometry": {"coordinates":[-0.786519,51.812743],"type":"Point"}
}
