{
  "type": "Feature",
  "properties": {
    "date:inception_lower": "1980-01-01",
    "date:inception_upper": "1980-01-01",
    "iso:country": "GB",
    "wof:name": "ML1 4HL",
    "wof:placetype": "postalcode"
  },
  "geometry": {"coordinates":[-3.962729,55.804098],"type":"Point"}
}
