{
  "type": "Feature",
  "properties": {
    "iso:country": "GB",
    "wof:name": "EH5 2FF",
    "wof:placetype": "postalcode"
  },
  "geometry": {"coordinates":[-3.23306,55.968182],"type":"Point"}
}
