{
  "type": "Feature",
  "properties": {
    "date:inception_lower": "2018-10-01",
    "date:inception_upper": "2018-10-01",
    "iso:country": "GB",
    "wof:name": "EH5 2FF",
    "wof:placetype": "postalcode"
  },
  "geometry": {"coordinates":[-3.23306,55.968182],"type":"Point"}
}
