{
  "type": "Feature",
  "properties": {
    "iso:country":"GB",
    "wof:name":"OX25 2NW",
    "wof:placetype":"postalcode"
},
  "geometry": {"coordinates":[-1.16472755879901,51.85419558505298],"type":"Point"}
}