{
  "type": "Feature",
  "properties": {
    "iso:country": "GB",
    "wof:name": "OX25 2NW",
    "wof:placetype": "postalcode"
  },
  "geometry": {"coordinates":[-1.164728,51.854196],"type":"Point"}
}
