{
  "type": "Feature",
  "properties": {
    "date:inception_lower":"2000-10-01",
    "date:inception_upper":"2000-10-31",
    "iso:country":"GB",
    "wof:name":"OX25 2NW",
    "wof:placetype":"postalcode"
},
  "geometry": {"coordinates":[-1.164728,51.854196],"type":"Point"}
}