{
  "type": "Feature",
  "properties": {
    "iso:country":"GB",
    "wof:name":"ST13 5RS",
    "wof:placetype":"postalcode"
},
  "geometry": {"coordinates":[-2.03687711855486,53.09842408760242],"type":"Point"}
}