{
  "type": "Feature",
  "properties": {
    "iso:country": "GB",
    "wof:name": "NE64 6AN",
    "wof:placetype": "postalcode"
  },
  "geometry": {"coordinates":[-1.517294,55.18839],"type":"Point"}
}
