{
  "type": "Feature",
  "properties": {
    "iso:country":"GB",
    "wof:name":"TN13 2AS",
    "wof:placetype":"postalcode"
},
  "geometry": {"coordinates":[0.16758545270639,51.28289001326506],"type":"Point"}
}