{
  "type": "Feature",
  "properties": {
    "date:inception_lower": "1980-01-01",
    "date:inception_upper": "1980-01-01",
    "iso:country": "GB",
    "wof:name": "TN13 2AS",
    "wof:placetype": "postalcode"
  },
  "geometry": {"coordinates":[0.167585,51.28289],"type":"Point"}
}
