{
  "type": "Feature",
  "properties": {
    "iso:country": "GB",
    "wof:name": "SG7 5FF",
    "wof:placetype": "postalcode"
  },
  "geometry": {"coordinates":[-0.153945,52.03827],"type":"Point"}
}
