{
  "type": "Feature",
  "properties": {
    "iso:country":"GB",
    "wof:name":"SS16 6BJ",
    "wof:placetype":"postalcode"
},
  "geometry": {"coordinates":[0.4172028466195,51.56288374725482],"type":"Point"}
}