{
  "type": "Feature",
  "properties": {
    "date:inception_lower": "1983-03-01",
    "date:inception_upper": "1983-03-01",
    "iso:country": "GB",
    "wof:name": "SS16 6BJ",
    "wof:placetype": "postalcode"
  },
  "geometry": {"coordinates":[0.417203,51.562884],"type":"Point"}
}
