{
  "type": "Feature",
  "properties": {
    "iso:country": "GB",
    "wof:name": "BS10 7FS",
    "wof:placetype": "postalcode"
  },
  "geometry": {"coordinates":[-2.626386,51.510978],"type":"Point"}
}
