{
  "type": "Feature",
  "properties": {
    "date:inception_lower": "2015-09-01",
    "date:inception_upper": "2015-09-01",
    "iso:country": "GB",
    "wof:name": "YO25 5AD",
    "wof:placetype": "postalcode"
  },
  "geometry": {"coordinates":[-0.44752,54.008176],"type":"Point"}
}
