{
  "type": "Feature",
  "properties": {
    "iso:country":"GB",
    "wof:name":"YO25 5AD",
    "wof:placetype":"postalcode"
},
  "geometry": {"coordinates":[-0.44710240793314,54.00801591951175],"type":"Point"}
}