{
  "type": "Feature",
  "properties": {
    "iso:country":"GB",
    "wof:name":"DA11 8AR",
    "wof:placetype":"postalcode"
},
  "geometry": {"coordinates":[0.33552140945947,51.43044166903324],"type":"Point"}
}