{
  "type": "Feature",
  "properties": {
    "iso:country": "GB",
    "wof:name": "NR13 5JQ",
    "wof:placetype": "postalcode"
  },
  "geometry": {"coordinates":[1.415121,52.661859],"type":"Point"}
}
