{
  "type": "Feature",
  "properties": {
    "iso:country":"GB",
    "wof:name":"NR13 5JQ",
    "wof:placetype":"postalcode"
},
  "geometry": {"coordinates":[1.41576753906788,52.66188613319686],"type":"Point"}
}