{
  "type": "Feature",
  "properties": {
    "iso:country": "GB",
    "wof:name": "B90 2EJ",
    "wof:placetype": "postalcode"
  },
  "geometry": {"coordinates":[-1.833343,52.412267],"type":"Point"}
}
