{
  "type": "Feature",
  "properties": {
    "iso:country":"GB",
    "wof:name":"B90 2EJ",
    "wof:placetype":"postalcode"
},
  "geometry": {"coordinates":[-1.83334334926551,52.41226727246988],"type":"Point"}
}