{
  "type": "Feature",
  "properties": {
    "iso:country":"GB",
    "wof:name":"SL0 0SD",
    "wof:placetype":"postalcode"
},
  "geometry": {"coordinates":[-0.52313337184353,51.53763642881153],"type":"Point"}
}