{
  "type": "Feature",
  "properties": {
    "iso:country": "GB",
    "wof:name": "SL0 0SD",
    "wof:placetype": "postalcode"
  },
  "geometry": {"coordinates":[-0.523133,51.537636],"type":"Point"}
}
