{
  "type": "Feature",
  "properties": {
    "iso:country":"GB",
    "wof:name":"TR12 7NZ",
    "wof:placetype":"postalcode"
},
  "geometry": {"coordinates":[-5.20400535356382,49.97012807995566],"type":"Point"}
}