{
  "type": "Feature",
  "properties": {
    "date:inception_lower": "1980-01-01",
    "date:inception_upper": "1980-01-01",
    "iso:country": "GB",
    "wof:name": "TR12 7NZ",
    "wof:placetype": "postalcode"
  },
  "geometry": {"coordinates":[-5.203849,49.969905],"type":"Point"}
}
