{
  "type": "Feature",
  "properties": {
    "date:inception_lower": "2005-01-01",
    "date:inception_upper": "2005-01-01",
    "iso:country": "GB",
    "wof:name": "CV23 0GB",
    "wof:placetype": "postalcode"
  },
  "geometry": {"coordinates":[-1.239858,52.399055],"type":"Point"}
}
