{
  "type": "Feature",
  "properties": {
    "iso:country":"GB",
    "wof:name":"CV23 0GB",
    "wof:placetype":"postalcode"
},
  "geometry": {"coordinates":[-1.23985809408435,52.39905535416588],"type":"Point"}
}