{
  "type": "Feature",
  "properties": {
    "iso:country": "GB",
    "wof:name": "CV23 0GB",
    "wof:placetype": "postalcode"
  },
  "geometry": {"coordinates":[-1.239858,52.399055],"type":"Point"}
}
