{
  "type": "Feature",
  "properties": {
    "iso:country":"GB",
    "wof:name":"WV10 8QY",
    "wof:placetype":"postalcode"
},
  "geometry": {"coordinates":[-2.09375354986485,52.63406474835281],"type":"Point"}
}