{
  "type": "Feature",
  "properties": {
    "date:inception_lower":"1996-06-01",
    "date:inception_upper":"1996-06-30",
    "iso:country":"GB",
    "wof:name":"WV10 8QY",
    "wof:placetype":"postalcode"
},
  "geometry": {"coordinates":[-2.093747,52.634081],"type":"Point"}
}