{
  "type": "Feature",
  "properties": {
    "iso:country":"GB",
    "wof:name":"G72 0HH",
    "wof:placetype":"postalcode"
},
  "geometry": {"coordinates":[-4.09658655046859,55.78418296111128],"type":"Point"}
}