{
  "type": "Feature",
  "properties": {
    "iso:country":"GB",
    "wof:name":"HP17 8AY",
    "wof:placetype":"postalcode"
},
  "geometry": {"coordinates":[-0.93231917356711,51.76804939936101],"type":"Point"}
}