{
  "type": "Feature",
  "properties": {
    "iso:country": "GB",
    "wof:name": "HP17 8AY",
    "wof:placetype": "postalcode"
  },
  "geometry": {"coordinates":[-0.932319,51.768049],"type":"Point"}
}
