{
  "type": "Feature",
  "properties": {
    "date:inception_lower":"1980-01-01",
    "date:inception_upper":"1980-01-31",
    "iso:country":"GB",
    "wof:name":"HP17 8AY",
    "wof:placetype":"postalcode"
},
  "geometry": {"coordinates":[-0.932319,51.768049],"type":"Point"}
}