{
  "type": "Feature",
  "properties": {
    "iso:country":"GB",
    "wof:name":"HP18 9RE",
    "wof:placetype":"postalcode"
},
  "geometry": {"coordinates":[-1.07709243956939,51.8042959395292],"type":"Point"}
}