{
  "type": "Feature",
  "properties": {
    "iso:country":"GB",
    "wof:name":"CF83 3JH",
    "wof:placetype":"postalcode"
},
  "geometry": {"coordinates":[-3.21321162260027,51.58823788971443],"type":"Point"}
}