{
  "type": "Feature",
  "properties": {
    "iso:country":"GB",
    "wof:name":"W3 6AH",
    "wof:placetype":"postalcode"
},
  "geometry": {"coordinates":[-0.26886727095808,51.50826222132356],"type":"Point"}
}