{
  "type": "Feature",
  "properties": {
    "iso:country": "GB",
    "wof:name": "W3 6AH",
    "wof:placetype": "postalcode"
  },
  "geometry": {"coordinates":[-0.268931,51.508247],"type":"Point"}
}
