{
  "type": "Feature",
  "properties": {
    "date:inception_lower": "1980-01-01",
    "date:inception_upper": "1980-01-01",
    "iso:country": "GB",
    "wof:name": "BN14 7SH",
    "wof:placetype": "postalcode"
  },
  "geometry": {"coordinates":[-0.38795,50.829344],"type":"Point"}
}
