{
  "type": "Feature",
  "properties": {
    "iso:country":"GB",
    "wof:name":"AB56 4TW",
    "wof:placetype":"postalcode"
},
  "geometry": {"coordinates":[-2.81321170816747,57.69266073022269],"type":"Point"}
}