{
  "type": "Feature",
  "properties": {
    "iso:country": "GB",
    "wof:name": "AB56 4TW",
    "wof:placetype": "postalcode"
  },
  "geometry": {"coordinates":[-2.813212,57.692661],"type":"Point"}
}
