{
  "type": "Feature",
  "properties": {
    "date:inception_lower":"1991-09-01",
    "date:inception_upper":"1991-09-30",
    "iso:country":"GB",
    "wof:name":"B97 4LF",
    "wof:placetype":"postalcode"
},
  "geometry": {"coordinates":[-1.950075,52.293281],"type":"Point"}
}