{
  "type": "Feature",
  "properties": {
    "iso:country": "GB",
    "wof:name": "RH19 1QS",
    "wof:placetype": "postalcode"
  },
  "geometry": {"coordinates":[-0.018939,51.130705],"type":"Point"}
}
