{
  "type": "Feature",
  "properties": {
    "iso:country":"GB",
    "wof:name":"TR18 5AE",
    "wof:placetype":"postalcode"
},
  "geometry": {"coordinates":[-5.55123689607779,50.10454798087839],"type":"Point"}
}