{
  "type": "Feature",
  "properties": {
    "date:inception_lower": "1980-01-01",
    "date:inception_upper": "1980-01-01",
    "iso:country": "GB",
    "wof:name": "S63 7ST",
    "wof:placetype": "postalcode"
  },
  "geometry": {"coordinates":[-1.346477,53.493416],"type":"Point"}
}
