{
  "type": "Feature",
  "properties": {
    "iso:country":"GB",
    "wof:name":"IP14 4LX",
    "wof:placetype":"postalcode"
},
  "geometry": {"coordinates":[1.01759710346656,52.26465456383562],"type":"Point"}
}