{
  "type": "Feature",
  "properties": {
    "date:inception_lower":"1980-01-01",
    "date:inception_upper":"1980-01-31",
    "iso:country":"GB",
    "wof:name":"IP14 4LX",
    "wof:placetype":"postalcode"
},
  "geometry": {"coordinates":[1.017597,52.264655],"type":"Point"}
}