{
  "type": "Feature",
  "properties": {
    "date:inception_lower":"1980-01-01",
    "date:inception_upper":"1980-01-31",
    "iso:country":"GB",
    "wof:name":"WV15 6NB",
    "wof:placetype":"postalcode"
},
  "geometry": {"coordinates":[-2.355434,52.457222],"type":"Point"}
}