{
  "type": "Feature",
  "properties": {
    "iso:country": "GB",
    "wof:name": "WV15 6NB",
    "wof:placetype": "postalcode"
  },
  "geometry": {"coordinates":[-2.355434,52.457222],"type":"Point"}
}
