{
  "type": "Feature",
  "properties": {
    "iso:country":"GB",
    "wof:name":"WV15 6NB",
    "wof:placetype":"postalcode"
},
  "geometry": {"coordinates":[-2.35543373958157,52.45722222483413],"type":"Point"}
}