{
  "type": "Feature",
  "properties": {
    "iso:country":"GB",
    "wof:name":"M43 6JA",
    "wof:placetype":"postalcode"
},
  "geometry": {"coordinates":[-2.16321220976085,53.48098604549597],"type":"Point"}
}