{
  "type": "Feature",
  "properties": {
    "iso:country":"GB",
    "wof:name":"B92 7JL",
    "wof:placetype":"postalcode"
},
  "geometry": {"coordinates":[-1.80977859876214,52.43921091374729],"type":"Point"}
}