{
  "type": "Feature",
  "properties": {
    "iso:country": "GB",
    "wof:name": "B92 7JL",
    "wof:placetype": "postalcode"
  },
  "geometry": {"coordinates":[-1.809779,52.439211],"type":"Point"}
}
