{
  "type": "Feature",
  "properties": {
    "iso:country":"GB",
    "wof:name":"AL7 4FN",
    "wof:placetype":"postalcode"
},
  "geometry": {"coordinates":[-0.20089050300112,51.78802226544877],"type":"Point"}
}