{
  "type": "Feature",
  "properties": {
    "iso:country":"GB",
    "wof:name":"SA18 3BQ",
    "wof:placetype":"postalcode"
},
  "geometry": {"coordinates":[-4.02255750471505,51.80588164459533],"type":"Point"}
}