{
  "type": "Feature",
  "properties": {
    "date:inception_lower": "1980-01-01",
    "date:inception_upper": "1980-01-01",
    "iso:country": "GB",
    "wof:name": "SA18 3BQ",
    "wof:placetype": "postalcode"
  },
  "geometry": {"coordinates":[-4.022557,51.805882],"type":"Point"}
}
