{
  "type": "Feature",
  "properties": {
    "iso:country":"GB",
    "wof:name":"PL28 8RS",
    "wof:placetype":"postalcode"
},
  "geometry": {"coordinates":[-4.95232611468595,50.53872055995362],"type":"Point"}
}