{
  "type": "Feature",
  "properties": {
    "iso:country": "GB",
    "wof:name": "SA18 2RE",
    "wof:placetype": "postalcode"
  },
  "geometry": {"coordinates":[-3.992969,51.775696],"type":"Point"}
}
