{
  "type": "Feature",
  "properties": {
    "iso:country":"GB",
    "wof:name":"SA18 2RE",
    "wof:placetype":"postalcode"
},
  "geometry": {"coordinates":[-3.99296916936784,51.7756963866682],"type":"Point"}
}