{
  "type": "Feature",
  "properties": {
    "iso:country":"GB",
    "wof:name":"SL1 7AN",
    "wof:placetype":"postalcode"
},
  "geometry": {"coordinates":[-0.66489503816095,51.53291484192189],"type":"Point"}
}