{
  "type": "Feature",
  "properties": {
    "iso:country":"GB",
    "wof:name":"RG42 1RU",
    "wof:placetype":"postalcode"
},
  "geometry": {"coordinates":[-0.77336385607822,51.42044054783685],"type":"Point"}
}