{
  "type": "Feature",
  "properties": {
    "date:inception_lower": "1995-07-01",
    "date:inception_upper": "1995-07-01",
    "iso:country": "GB",
    "wof:name": "RG42 1RU",
    "wof:placetype": "postalcode"
  },
  "geometry": {"coordinates":[-0.773364,51.420441],"type":"Point"}
}
