{
  "type": "Feature",
  "properties": {
    "iso:country":"GB",
    "wof:name":"W1F 9NA",
    "wof:placetype":"postalcode"
},
  "geometry": {"coordinates":[-0.13559362493539,51.51195661688066],"type":"Point"}
}