{
  "type": "Feature",
  "properties": {
    "date:inception_lower": "1997-12-01",
    "date:inception_upper": "1997-12-01",
    "iso:country": "GB",
    "wof:name": "SK13 5RR",
    "wof:placetype": "postalcode"
  },
  "geometry": {"coordinates":[-2.012557,53.425899],"type":"Point"}
}
