{
  "type": "Feature",
  "properties": {
    "iso:country":"GB",
    "wof:name":"SK13 5RR",
    "wof:placetype":"postalcode"
},
  "geometry": {"coordinates":[-2.01255698354303,53.425898926968],"type":"Point"}
}