{
  "type": "Feature",
  "properties": {
    "date:inception_lower":"1980-01-01",
    "date:inception_upper":"1980-01-31",
    "iso:country":"GB",
    "wof:name":"LS11 8QW",
    "wof:placetype":"postalcode"
},
  "geometry": {"coordinates":[-1.562693,53.776391],"type":"Point"}
}