{
  "type": "Feature",
  "properties": {
    "date:inception_lower":"1985-10-01",
    "date:inception_upper":"1985-10-31",
    "iso:country":"GB",
    "wof:name":"PE32 2JD",
    "wof:placetype":"postalcode"
},
  "geometry": {"coordinates":[0.665064,52.772319],"type":"Point"}
}