{
  "type": "Feature",
  "properties": {
    "iso:country":"GB",
    "wof:name":"PE32 2JD",
    "wof:placetype":"postalcode"
},
  "geometry": {"coordinates":[0.66507947368544,52.77232985557627],"type":"Point"}
}