{
  "type": "Feature",
  "properties": {
    "iso:country": "GB",
    "wof:name": "PE32 2JD",
    "wof:placetype": "postalcode"
  },
  "geometry": {"coordinates":[0.665064,52.772319],"type":"Point"}
}
