{
  "type": "Feature",
  "properties": {
    "iso:country": "GB",
    "wof:name": "PE32 2JD",
    "wof:placetype": "postalcode"
  },
  "geometry": {"coordinates":[0.66506,52.772499],"type":"Point"}
}
