{
  "type": "Feature",
  "properties": {
    "date:inception_lower": "1993-01-01",
    "date:inception_upper": "1993-01-01",
    "iso:country": "GB",
    "wof:name": "LE14 2RE",
    "wof:placetype": "postalcode"
  },
  "geometry": {"coordinates":[-0.906818,52.680423],"type":"Point"}
}
