{
  "type": "Feature",
  "properties": {
    "date:inception_lower": "1980-01-01",
    "date:inception_upper": "1980-01-01",
    "iso:country": "GB",
    "wof:name": "NE2 4NJ",
    "wof:placetype": "postalcode"
  },
  "geometry": {"coordinates":[-1.628509,54.983837],"type":"Point"}
}
