{
  "type": "Feature",
  "properties": {
    "iso:country":"GB",
    "wof:name":"NE2 4NJ",
    "wof:placetype":"postalcode"
},
  "geometry": {"coordinates":[-1.62850886353989,54.98383747867366],"type":"Point"}
}