{
  "type": "Feature",
  "properties": {
    "iso:country":"GB",
    "wof:name":"B15 2PA",
    "wof:placetype":"postalcode"
},
  "geometry": {"coordinates":[-1.93595949957542,52.4534426019397],"type":"Point"}
}