{
  "type": "Feature",
  "properties": {
    "iso:country": "GB",
    "wof:name": "BB7 1JG",
    "wof:placetype": "postalcode"
  },
  "geometry": {"coordinates":[-2.384155,53.87108],"type":"Point"}
}
