{
  "type": "Feature",
  "properties": {
    "iso:country":"GB",
    "wof:name":"RM11 1EJ",
    "wof:placetype":"postalcode"
},
  "geometry": {"coordinates":[0.19383396554195,51.56680592808738],"type":"Point"}
}