{
  "type": "Feature",
  "properties": {
    "iso:country":"GB",
    "wof:name":"CB25 0EU",
    "wof:placetype":"postalcode"
},
  "geometry": {"coordinates":[0.32705779204641,52.28079495834478],"type":"Point"}
}