{
  "type": "Feature",
  "properties": {
    "iso:country": "GB",
    "wof:name": "CB25 0EU",
    "wof:placetype": "postalcode"
  },
  "geometry": {"coordinates":[0.327058,52.280795],"type":"Point"}
}
