{
  "type": "Feature",
  "properties": {
    "iso:country":"GB",
    "wof:name":"SN6 8LH",
    "wof:placetype":"postalcode"
},
  "geometry": {"coordinates":[-1.63136581947716,51.55760719585562],"type":"Point"}
}