{
  "type": "Feature",
  "properties": {
    "date:inception_lower": "1980-01-01",
    "date:inception_upper": "1980-01-01",
    "iso:country": "GB",
    "wof:name": "HA3 9QZ",
    "wof:placetype": "postalcode"
  },
  "geometry": {"coordinates":[-0.286598,51.58449],"type":"Point"}
}
