{
  "type": "Feature",
  "properties": {
    "iso:country":"GB",
    "wof:name":"HA3 9QZ",
    "wof:placetype":"postalcode"
},
  "geometry": {"coordinates":[-0.28659839530785,51.58448952273857],"type":"Point"}
}