{
  "type": "Feature",
  "properties": {
    "iso:country":"GB",
    "wof:name":"S72 0EJ",
    "wof:placetype":"postalcode"
},
  "geometry": {"coordinates":[-1.3501667279264,53.55276907018614],"type":"Point"}
}