{
  "type": "Feature",
  "properties": {
    "iso:country": "GB",
    "wof:name": "S72 0EJ",
    "wof:placetype": "postalcode"
  },
  "geometry": {"coordinates":[-1.350167,53.552769],"type":"Point"}
}
