{
  "type": "Feature",
  "properties": {
    "iso:country": "GB",
    "wof:name": "TA3 6EE",
    "wof:placetype": "postalcode"
  },
  "geometry": {"coordinates":[-2.956213,51.02631],"type":"Point"}
}
