{
  "type": "Feature",
  "properties": {
    "iso:country":"GB",
    "wof:name":"TA3 6EE",
    "wof:placetype":"postalcode"
},
  "geometry": {"coordinates":[-2.9562129307336,51.02630958111183],"type":"Point"}
}