{
  "type": "Feature",
  "properties": {
    "date:inception_lower": "1980-01-01",
    "date:inception_upper": "1980-01-01",
    "iso:country": "GB",
    "wof:name": "CV23 8DH",
    "wof:placetype": "postalcode"
  },
  "geometry": {"coordinates":[-1.279719,52.297777],"type":"Point"}
}
