{
  "type": "Feature",
  "properties": {
    "iso:country": "GB",
    "wof:name": "PA16 0LT",
    "wof:placetype": "postalcode"
  },
  "geometry": {"coordinates":[-4.855237,55.912808],"type":"Point"}
}
