{
  "type": "Feature",
  "properties": {
    "date:inception_lower": "1980-01-01",
    "date:inception_upper": "1980-01-01",
    "iso:country": "GB",
    "wof:name": "DL11 7ER",
    "wof:placetype": "postalcode"
  },
  "geometry": {"coordinates":[-1.780504,54.465806],"type":"Point"}
}
