{
  "type": "Feature",
  "properties": {
    "iso:country":"GB",
    "wof:name":"IP9 2LB",
    "wof:placetype":"postalcode"
},
  "geometry": {"coordinates":[1.03536563825339,52.00816918501955],"type":"Point"}
}