{
  "type": "Feature",
  "properties": {
    "iso:country":"GB",
    "wof:name":"CW1 3JS",
    "wof:placetype":"postalcode"
},
  "geometry": {"coordinates":[-2.4576107717977,53.10697883457555],"type":"Point"}
}