{
  "type": "Feature",
  "properties": {
    "iso:country": "GB",
    "wof:name": "CT9 2UB",
    "wof:placetype": "postalcode"
  },
  "geometry": {"coordinates":[1.39926,51.38194],"type":"Point"}
}
