{
  "type": "Feature",
  "properties": {
    "iso:country":"GB",
    "wof:name":"CT9 2UB",
    "wof:placetype":"postalcode"
},
  "geometry": {"coordinates":[1.39925976818328,51.38194030475897],"type":"Point"}
}