{
  "type": "Feature",
  "properties": {
    "iso:country":"GB",
    "wof:name":"AL1 1JQ",
    "wof:placetype":"postalcode"
},
  "geometry": {"coordinates":[-0.32283347571143,51.74255443245352],"type":"Point"}
}