{
  "type": "Feature",
  "properties": {
    "iso:country":"GB",
    "wof:name":"AB42 4NB",
    "wof:placetype":"postalcode"
},
  "geometry": {"coordinates":[-2.13269065776244,57.52012043009491],"type":"Point"}
}