{
  "type": "Feature",
  "properties": {
    "iso:country": "GB",
    "wof:name": "AB42 4NB",
    "wof:placetype": "postalcode"
  },
  "geometry": {"coordinates":[-2.132691,57.52012],"type":"Point"}
}
