{
  "type": "Feature",
  "properties": {
    "date:inception_lower": "1980-01-01",
    "date:inception_upper": "1980-01-01",
    "iso:country": "GB",
    "wof:name": "LS21 3BY",
    "wof:placetype": "postalcode"
  },
  "geometry": {"coordinates":[-1.6412,53.892416],"type":"Point"}
}
