{
  "type": "Feature",
  "properties": {
    "iso:country":"GB",
    "wof:name":"TN3 9RL",
    "wof:placetype":"postalcode"
},
  "geometry": {"coordinates":[0.18580034262122,51.11330581412324],"type":"Point"}
}