{
  "type": "Feature",
  "properties": {
    "iso:country":"GB",
    "wof:name":"M30 0HG",
    "wof:placetype":"postalcode"
},
  "geometry": {"coordinates":[-2.3488903356016,53.47792725225704],"type":"Point"}
}