{
  "type": "Feature",
  "properties": {
    "iso:country": "GB",
    "wof:name": "TW19 7EU",
    "wof:placetype": "postalcode"
  },
  "geometry": {"coordinates":[-0.474751,51.455368],"type":"Point"}
}
