{
  "type": "Feature",
  "properties": {
    "iso:country":"GB",
    "wof:name":"CM20 3RE",
    "wof:placetype":"postalcode"
},
  "geometry": {"coordinates":[0.10382514299292,51.76786532100649],"type":"Point"}
}