{
  "type": "Feature",
  "properties": {
    "iso:country":"GB",
    "wof:name":"SG17 5RJ",
    "wof:placetype":"postalcode"
},
  "geometry": {"coordinates":[-0.30301747919042,52.03578929621607],"type":"Point"}
}