{
  "type": "Feature",
  "properties": {
    "iso:country": "GB",
    "wof:name": "SG17 5RJ",
    "wof:placetype": "postalcode"
  },
  "geometry": {"coordinates":[-0.303017,52.035789],"type":"Point"}
}
