{
  "type": "Feature",
  "properties": {
    "iso:country":"GB",
    "wof:name":"FK2 8FE",
    "wof:placetype":"postalcode"
},
  "geometry": {"coordinates":[-3.77780797142071,56.02519113339438],"type":"Point"}
}