{
  "type": "Feature",
  "properties": {
    "date:inception_lower": "1996-12-01",
    "date:inception_upper": "1996-12-01",
    "iso:country": "GB",
    "wof:name": "FK2 8FE",
    "wof:placetype": "postalcode"
  },
  "geometry": {"coordinates":[-3.777808,56.025191],"type":"Point"}
}
