{
  "type": "Feature",
  "properties": {
    "iso:country":"GB",
    "wof:name":"NG5 5JE",
    "wof:placetype":"postalcode"
},
  "geometry": {"coordinates":[-1.16678652388875,52.99041193096733],"type":"Point"}
}