{
  "type": "Feature",
  "properties": {
    "iso:country":"GB",
    "wof:name":"CF14 5JW",
    "wof:placetype":"postalcode"
},
  "geometry": {"coordinates":[-3.20200125965264,51.53264894629494],"type":"Point"}
}