{
  "type": "Feature",
  "properties": {
    "iso:country": "GB",
    "wof:name": "CF14 5JW",
    "wof:placetype": "postalcode"
  },
  "geometry": {"coordinates":[-3.202001,51.532649],"type":"Point"}
}
