{
  "type": "Feature",
  "properties": {
    "iso:country": "GB",
    "wof:name": "PE28 3GY",
    "wof:placetype": "postalcode"
  },
  "geometry": {"coordinates":[0.002592,52.380284],"type":"Point"}
}
