{
  "type": "Feature",
  "properties": {
    "iso:country":"GB",
    "wof:name":"PE28 3GY",
    "wof:placetype":"postalcode"
},
  "geometry": {"coordinates":[0.00259199105213,52.38028393930647],"type":"Point"}
}