{
  "type": "Feature",
  "properties": {
    "iso:country":"GB",
    "wof:name":"B61 9DZ",
    "wof:placetype":"postalcode"
},
  "geometry": {"coordinates":[-2.12044302454757,52.34518453615181],"type":"Point"}
}