{
  "type": "Feature",
  "properties": {
    "date:inception_lower":"2007-05-01",
    "date:inception_upper":"2007-05-31",
    "iso:country":"GB",
    "wof:name":"TN1 1DR",
    "wof:placetype":"postalcode"
},
  "geometry": {"coordinates":[0.259139,51.130573],"type":"Point"}
}