{
  "type": "Feature",
  "properties": {
    "iso:country":"GB",
    "wof:name":"PR2 2BQ",
    "wof:placetype":"postalcode"
},
  "geometry": {"coordinates":[-2.72228588084423,53.77051626492207],"type":"Point"}
}