{
  "type": "Feature",
  "properties": {
    "iso:country":"GB",
    "wof:name":"CO12 3EX",
    "wof:placetype":"postalcode"
},
  "geometry": {"coordinates":[1.28769797118957,51.94729025872563],"type":"Point"}
}