{
  "type": "Feature",
  "properties": {
    "iso:country": "GB",
    "wof:name": "NE37 2AS",
    "wof:placetype": "postalcode"
  },
  "geometry": {"coordinates":[-1.520214,54.912016],"type":"Point"}
}
