{
  "type": "Feature",
  "properties": {
    "date:inception_lower": "2007-10-01",
    "date:inception_upper": "2007-10-01",
    "iso:country": "GB",
    "wof:name": "FY8 5TR",
    "wof:placetype": "postalcode"
  },
  "geometry": {"coordinates":[-2.943386,53.73912],"type":"Point"}
}
