{
  "type": "Feature",
  "properties": {
    "iso:country":"GB",
    "wof:name":"FY8 5TR",
    "wof:placetype":"postalcode"
},
  "geometry": {"coordinates":[-2.94338644210892,53.73912042393634],"type":"Point"}
}