{
  "type": "Feature",
  "properties": {
    "date:inception_lower": "1980-01-01",
    "date:inception_upper": "1980-01-01",
    "iso:country": "GB",
    "wof:name": "BS1 3HB",
    "wof:placetype": "postalcode"
  },
  "geometry": {"coordinates":[-2.58874,51.45796],"type":"Point"}
}
