{
  "type": "Feature",
  "properties": {
    "iso:country":"GB",
    "wof:name":"BS1 3HB",
    "wof:placetype":"postalcode"
},
  "geometry": {"coordinates":[-2.58873900558809,51.45796191354035],"type":"Point"}
}