{
  "type": "Feature",
  "properties": {
    "iso:country":"GB",
    "wof:name":"SG18 9BG",
    "wof:placetype":"postalcode"
},
  "geometry": {"coordinates":[-0.28867438092306,52.09906229455216],"type":"Point"}
}