{
  "type": "Feature",
  "properties": {
    "iso:country":"GB",
    "wof:name":"DL13 5QP",
    "wof:placetype":"postalcode"
},
  "geometry": {"coordinates":[-1.83931208158044,54.61643724424982],"type":"Point"}
}