{
  "type": "Feature",
  "properties": {
    "iso:country":"GB",
    "wof:name":"TR16 6EY",
    "wof:placetype":"postalcode"
},
  "geometry": {"coordinates":[-5.2072771278437,50.21279832397902],"type":"Point"}
}