{
  "type": "Feature",
  "properties": {
    "iso:country":"GB",
    "wof:name":"CH7 1GN",
    "wof:placetype":"postalcode"
},
  "geometry": {"coordinates":[-3.14429774094572,53.16876201942949],"type":"Point"}
}