{
  "type": "Feature",
  "properties": {
    "iso:country": "GB",
    "wof:name": "CH7 1GN",
    "wof:placetype": "postalcode"
  },
  "geometry": {"coordinates":[-3.144298,53.168762],"type":"Point"}
}
