{
  "type": "Feature",
  "properties": {
    "iso:country": "GB",
    "wof:name": "CW8 1SQ",
    "wof:placetype": "postalcode"
  },
  "geometry": {"coordinates":[-2.534423,53.240988],"type":"Point"}
}
