{
  "type": "Feature",
  "properties": {
    "iso:country":"GB",
    "wof:name":"NP11 6PJ",
    "wof:placetype":"postalcode"
},
  "geometry": {"coordinates":[-3.08766358881034,51.60838726196797],"type":"Point"}
}