{
  "type": "Feature",
  "properties": {
    "date:inception_lower":"1999-06-01",
    "date:inception_upper":"1999-06-30",
    "iso:country":"GB",
    "wof:name":"NP11 6PJ",
    "wof:placetype":"postalcode"
},
  "geometry": {"coordinates":[-3.087664,51.608387],"type":"Point"}
}