{
  "type": "Feature",
  "properties": {
    "iso:country": "GB",
    "wof:name": "DE73 5BY",
    "wof:placetype": "postalcode"
  },
  "geometry": {"coordinates":[-1.445596,52.874709],"type":"Point"}
}
