{
  "type": "Feature",
  "properties": {
    "iso:country":"GB",
    "wof:name":"DE73 5BY",
    "wof:placetype":"postalcode"
},
  "geometry": {"coordinates":[-1.44559610492596,52.87470879438394],"type":"Point"}
}