{
  "type": "Feature",
  "properties": {
    "iso:country":"GB",
    "wof:name":"S75 5GS",
    "wof:placetype":"postalcode"
},
  "geometry": {"coordinates":[-1.53314886492389,53.59559858327476],"type":"Point"}
}