{
  "type": "Feature",
  "properties": {
    "iso:country":"GB",
    "wof:name":"YO31 0RX",
    "wof:placetype":"postalcode"
},
  "geometry": {"coordinates":[-1.06114203158424,53.96427956368227],"type":"Point"}
}