{
  "type": "Feature",
  "properties": {
    "iso:country":"GB",
    "wof:name":"DL1 5YL",
    "wof:placetype":"postalcode"
},
  "geometry": {"coordinates":[-1.55807410831281,54.52349668119948],"type":"Point"}
}