{
  "type": "Feature",
  "properties": {
    "iso:country": "GB",
    "wof:name": "DL1 5YL",
    "wof:placetype": "postalcode"
  },
  "geometry": {"coordinates":[-1.558074,54.523497],"type":"Point"}
}
