{
  "type": "Feature",
  "properties": {
    "date:inception_lower": "1997-12-01",
    "date:inception_upper": "1997-12-01",
    "iso:country": "GB",
    "wof:name": "DL1 5YL",
    "wof:placetype": "postalcode"
  },
  "geometry": {"coordinates":[-1.558074,54.523497],"type":"Point"}
}
