{
  "type": "Feature",
  "properties": {
    "date:inception_lower": "2021-06-01",
    "date:inception_upper": "2021-06-01",
    "iso:country": "GB",
    "wof:name": "BS34 4AD",
    "wof:placetype": "postalcode"
  },
  "geometry": {"coordinates":[-2.582531,51.520744],"type":"Point"}
}
