{
  "type": "Feature",
  "properties": {
    "iso:country": "GB",
    "wof:name": "CH66 1HT",
    "wof:placetype": "postalcode"
  },
  "geometry": {"coordinates":[-2.939747,53.288705],"type":"Point"}
}
