{
  "type": "Feature",
  "properties": {
    "date:inception_lower": "2023-03-01",
    "date:inception_upper": "2023-03-01",
    "iso:country": "GB",
    "wof:name": "NG34 8US",
    "wof:placetype": "postalcode"
  },
  "geometry": {"coordinates":[-0.42409,52.985374],"type":"Point"}
}
