{
  "type": "Feature",
  "properties": {
    "iso:country":"GB",
    "wof:name":"LA2 6LN",
    "wof:placetype":"postalcode"
},
  "geometry": {"coordinates":[-2.76232939722022,54.07735255513365],"type":"Point"}
}