{
  "type": "Feature",
  "properties": {
    "iso:country":"GB",
    "wof:name":"LE11 5AG",
    "wof:placetype":"postalcode"
},
  "geometry": {"coordinates":[-1.21461796444683,52.77594059136725],"type":"Point"}
}