{
  "type": "Feature",
  "properties": {
    "date:inception_lower": "2023-01-01",
    "date:inception_upper": "2023-01-01",
    "iso:country": "GB",
    "wof:name": "EX1 4BF",
    "wof:placetype": "postalcode"
  },
  "geometry": {"coordinates":[-3.471133,50.732831],"type":"Point"}
}
