{
  "type": "Feature",
  "properties": {
    "iso:country": "GB",
    "wof:name": "PO20 8NY",
    "wof:placetype": "postalcode"
  },
  "geometry": {"coordinates":[-0.859737,50.764961],"type":"Point"}
}
