{
  "type": "Feature",
  "properties": {
    "iso:country":"GB",
    "wof:name":"PO20 8NY",
    "wof:placetype":"postalcode"
},
  "geometry": {"coordinates":[-0.85973686483588,50.7649613032233],"type":"Point"}
}