{
  "type": "Feature",
  "properties": {
    "iso:country":"GB",
    "wof:name":"BB12 7PW",
    "wof:placetype":"postalcode"
},
  "geometry": {"coordinates":[-2.35625448370597,53.80571570435929],"type":"Point"}
}