{
  "type": "Feature",
  "properties": {
    "date:inception_lower": "1980-01-01",
    "date:inception_upper": "1980-01-01",
    "iso:country": "GB",
    "wof:name": "BB12 7PW",
    "wof:placetype": "postalcode"
  },
  "geometry": {"coordinates":[-2.356255,53.805712],"type":"Point"}
}
