{
  "type": "Feature",
  "properties": {
    "date:inception_lower": "1980-01-01",
    "date:inception_upper": "1980-01-01",
    "iso:country": "GB",
    "wof:name": "NG25 0TU",
    "wof:placetype": "postalcode"
  },
  "geometry": {"coordinates":[-0.920481,53.068018],"type":"Point"}
}
