{
  "type": "Feature",
  "properties": {
    "iso:country": "GB",
    "wof:name": "NW8 8SS",
    "wof:placetype": "postalcode"
  },
  "geometry": {"coordinates":[-0.16759,51.525268],"type":"Point"}
}
