{
  "type": "Feature",
  "properties": {
    "iso:country": "GB",
    "wof:name": "NG7 2FJ",
    "wof:placetype": "postalcode"
  },
  "geometry": {"coordinates":[-1.173881,52.946467],"type":"Point"}
}
