{
  "type": "Feature",
  "properties": {
    "date:inception_lower": "1985-04-01",
    "date:inception_upper": "1985-04-01",
    "iso:country": "GB",
    "wof:name": "NG7 2FJ",
    "wof:placetype": "postalcode"
  },
  "geometry": {"coordinates":[-1.173881,52.946467],"type":"Point"}
}
