{
  "type": "Feature",
  "properties": {
    "date:inception_lower": "1998-06-01",
    "date:inception_upper": "1998-06-01",
    "iso:country": "GB",
    "wof:name": "DE5 8PG",
    "wof:placetype": "postalcode"
  },
  "geometry": {"coordinates":[-1.408167,53.01435],"type":"Point"}
}
