{
  "type": "Feature",
  "properties": {
    "iso:country":"GB",
    "wof:name":"DE5 8PG",
    "wof:placetype":"postalcode"
},
  "geometry": {"coordinates":[-1.40821671795283,53.01418751101325],"type":"Point"}
}