{
  "type": "Feature",
  "properties": {
    "iso:country": "GB",
    "wof:name": "DE5 8PG",
    "wof:placetype": "postalcode"
  },
  "geometry": {"coordinates":[-1.408213,53.014206],"type":"Point"}
}
