{
  "type": "Feature",
  "properties": {
    "iso:country": "GB",
    "wof:name": "HG4 1RS",
    "wof:placetype": "postalcode"
  },
  "geometry": {"coordinates":[-1.523677,54.127199],"type":"Point"}
}
