{
  "type": "Feature",
  "properties": {
    "date:inception_lower":"1980-01-01",
    "date:inception_upper":"1980-01-31",
    "iso:country":"GB",
    "wof:name":"HG4 1RS",
    "wof:placetype":"postalcode"
},
  "geometry": {"coordinates":[-1.523677,54.127199],"type":"Point"}
}