{
  "type": "Feature",
  "properties": {
    "iso:country":"GB",
    "wof:name":"DE3 0EE",
    "wof:placetype":"postalcode"
},
  "geometry": {"coordinates":[-1.54866276992071,52.90909793672765],"type":"Point"}
}