{
  "type": "Feature",
  "properties": {
    "date:inception_lower":"1995-07-01",
    "date:inception_upper":"1995-07-31",
    "iso:country":"GB",
    "wof:name":"WA14 3SE",
    "wof:placetype":"postalcode"
},
  "geometry": {"coordinates":[-2.374863,53.373222],"type":"Point"}
}