{
  "type": "Feature",
  "properties": {
    "iso:country": "GB",
    "wof:name": "WA14 3SE",
    "wof:placetype": "postalcode"
  },
  "geometry": {"coordinates":[-2.374863,53.373222],"type":"Point"}
}
