{
  "type": "Feature",
  "properties": {
    "iso:country":"GB",
    "wof:name":"W3 0HT",
    "wof:placetype":"postalcode"
},
  "geometry": {"coordinates":[-0.28675962348635,51.51800286744587],"type":"Point"}
}