{
  "type": "Feature",
  "properties": {
    "date:inception_lower":"2002-06-01",
    "date:inception_upper":"2002-06-30",
    "iso:country":"GB",
    "wof:name":"CH43 9RB",
    "wof:placetype":"postalcode"
},
  "geometry": {"coordinates":[-3.070125,53.384716],"type":"Point"}
}