{
  "type": "Feature",
  "properties": {
    "date:inception_lower": "2023-04-01",
    "date:inception_upper": "2023-04-01",
    "iso:country": "GB",
    "wof:name": "CM20 2UE",
    "wof:placetype": "postalcode"
  },
  "geometry": {"coordinates":[0.098105,51.78113],"type":"Point"}
}
