{
  "type": "Feature",
  "properties": {
    "date:inception_lower": "1980-01-01",
    "date:inception_upper": "1980-01-01",
    "iso:country": "GB",
    "wof:name": "NG2 5AX",
    "wof:placetype": "postalcode"
  },
  "geometry": {"coordinates":[-1.102038,52.937397],"type":"Point"}
}
