{
  "type": "Feature",
  "properties": {
    "iso:country":"GB",
    "wof:name":"NG2 5AX",
    "wof:placetype":"postalcode"
},
  "geometry": {"coordinates":[-1.10203824798284,52.93739695267497],"type":"Point"}
}