{
  "type": "Feature",
  "properties": {
    "iso:country":"GB",
    "wof:name":"BR1 2JA",
    "wof:placetype":"postalcode"
},
  "geometry": {"coordinates":[0.05924753037702,51.39955142383645],"type":"Point"}
}