{
  "type": "Feature",
  "properties": {
    "date:inception_lower": "1980-01-01",
    "date:inception_upper": "1980-01-01",
    "iso:country": "GB",
    "wof:name": "BD4 8EU",
    "wof:placetype": "postalcode"
  },
  "geometry": {"coordinates":[-1.70295,53.791012],"type":"Point"}
}
