{
  "type": "Feature",
  "properties": {
    "iso:country":"GB",
    "wof:name":"NR28 0NF",
    "wof:placetype":"postalcode"
},
  "geometry": {"coordinates":[1.35995240494321,52.84042483435573],"type":"Point"}
}