{
  "type": "Feature",
  "properties": {
    "iso:country":"GB",
    "wof:name":"PE32 2LD",
    "wof:placetype":"postalcode"
},
  "geometry": {"coordinates":[0.66556431671988,52.77371273503677],"type":"Point"}
}