{
  "type": "Feature",
  "properties": {
    "iso:country": "GB",
    "wof:name": "PE32 2LD",
    "wof:placetype": "postalcode"
  },
  "geometry": {"coordinates":[0.665564,52.773713],"type":"Point"}
}
