{
  "type": "Feature",
  "properties": {
    "date:inception_lower": "1987-10-01",
    "date:inception_upper": "1987-10-01",
    "iso:country": "GB",
    "wof:name": "WF3 1TF",
    "wof:placetype": "postalcode"
  },
  "geometry": {"coordinates":[-1.567629,53.728637],"type":"Point"}
}
