{
  "type": "Feature",
  "properties": {
    "iso:country":"GB",
    "wof:name":"WF3 1TF",
    "wof:placetype":"postalcode"
},
  "geometry": {"coordinates":[-1.56762938830649,53.7286371050233],"type":"Point"}
}