{
  "type": "Feature",
  "properties": {
    "iso:country":"GB",
    "wof:name":"DN14 6HN",
    "wof:placetype":"postalcode"
},
  "geometry": {"coordinates":[-0.86744259144444,53.70939717878854],"type":"Point"}
}