{
  "type": "Feature",
  "properties": {
    "iso:country":"GB",
    "wof:name":"NG9 1LR",
    "wof:placetype":"postalcode"
},
  "geometry": {"coordinates":[-1.20181746747201,52.91563501921543],"type":"Point"}
}