{
  "type": "Feature",
  "properties": {
    "iso:country": "GB",
    "wof:name": "NG9 1LR",
    "wof:placetype": "postalcode"
  },
  "geometry": {"coordinates":[-1.201817,52.915635],"type":"Point"}
}
