{
  "type": "Feature",
  "properties": {
    "date:inception_lower":"1995-12-01",
    "date:inception_upper":"1995-12-31",
    "iso:country":"GB",
    "wof:name":"CF82 8FP",
    "wof:placetype":"postalcode"
},
  "geometry": {"coordinates":[-3.246535,51.665469],"type":"Point"}
}