{
  "type": "Feature",
  "properties": {
    "iso:country":"GB",
    "wof:name":"CV5 9BD",
    "wof:placetype":"postalcode"
},
  "geometry": {"coordinates":[-1.56843181708335,52.42469631580425],"type":"Point"}
}