{
  "type": "Feature",
  "properties": {
    "iso:country": "GB",
    "wof:name": "SO23 8AP",
    "wof:placetype": "postalcode"
  },
  "geometry": {"coordinates":[-1.312764,51.062514],"type":"Point"}
}
