{
  "type": "Feature",
  "properties": {
    "date:inception_lower":"2001-12-01",
    "date:inception_upper":"2001-12-31",
    "iso:country":"GB",
    "wof:name":"SO23 8AP",
    "wof:placetype":"postalcode"
},
  "geometry": {"coordinates":[-1.312764,51.062514],"type":"Point"}
}