{
  "type": "Feature",
  "properties": {
    "iso:country":"GB",
    "wof:name":"SO23 8AP",
    "wof:placetype":"postalcode"
},
  "geometry": {"coordinates":[-1.31270534249667,51.06249203947871],"type":"Point"}
}