{
  "type": "Feature",
  "properties": {
    "iso:country":"GB",
    "wof:name":"DE7 5EA",
    "wof:placetype":"postalcode"
},
  "geometry": {"coordinates":[-1.29233420736018,52.96902138229721],"type":"Point"}
}