{
  "type": "Feature",
  "properties": {
    "iso:country":"GB",
    "wof:name":"WA9 4WH",
    "wof:placetype":"postalcode"
},
  "geometry": {"coordinates":[-2.69998214967903,53.43242222732204],"type":"Point"}
}