{
  "type": "Feature",
  "properties": {
    "iso:country":"GB",
    "wof:name":"BN27 1UR",
    "wof:placetype":"postalcode"
},
  "geometry": {"coordinates":[0.26124412468519,50.87799873938859],"type":"Point"}
}