{
  "type": "Feature",
  "properties": {
    "date:inception_lower": "1980-01-01",
    "date:inception_upper": "1980-01-01",
    "iso:country": "GB",
    "wof:name": "BN27 1UR",
    "wof:placetype": "postalcode"
  },
  "geometry": {"coordinates":[0.261494,50.877576],"type":"Point"}
}
