{
  "type": "Feature",
  "properties": {
    "iso:country":"GB",
    "wof:name":"DA17 5AF",
    "wof:placetype":"postalcode"
},
  "geometry": {"coordinates":[0.14434274473504,51.48892568218822],"type":"Point"}
}