{
  "type": "Feature",
  "properties": {
    "date:inception_lower":"1980-01-01",
    "date:inception_upper":"1980-01-31",
    "iso:country":"GB",
    "wof:name":"IP11 7DR",
    "wof:placetype":"postalcode"
},
  "geometry": {"coordinates":[1.352186,51.965753],"type":"Point"}
}