{
  "type": "Feature",
  "properties": {
    "iso:country":"GB",
    "wof:name":"IP11 7DR",
    "wof:placetype":"postalcode"
},
  "geometry": {"coordinates":[1.3521859599327,51.96575254779753],"type":"Point"}
}