{
  "type": "Feature",
  "properties": {
    "iso:country":"GB",
    "wof:name":"PE28 4SR",
    "wof:placetype":"postalcode"
},
  "geometry": {"coordinates":[-0.23930949990614,52.32641173255146],"type":"Point"}
}