{
  "type": "Feature",
  "properties": {
    "iso:country":"GB",
    "wof:name":"ME13 8PE",
    "wof:placetype":"postalcode"
},
  "geometry": {"coordinates":[0.89067806767663,51.312953290855],"type":"Point"}
}