{
  "type": "Feature",
  "properties": {
    "date:inception_lower": "1994-05-01",
    "date:inception_upper": "1994-05-01",
    "iso:country": "GB",
    "wof:name": "M27 5NZ",
    "wof:placetype": "postalcode"
  },
  "geometry": {"coordinates":[-2.329352,53.503663],"type":"Point"}
}
