{
  "type": "Feature",
  "properties": {
    "date:inception_lower": "1980-01-01",
    "date:inception_upper": "1980-01-01",
    "iso:country": "GB",
    "wof:name": "PE14 7BE",
    "wof:placetype": "postalcode"
  },
  "geometry": {"coordinates":[0.201631,52.659459],"type":"Point"}
}
