{
  "type": "Feature",
  "properties": {
    "date:inception_lower":"1994-12-01",
    "date:inception_upper":"1994-12-31",
    "iso:country":"GB",
    "wof:name":"SO50 5RF",
    "wof:placetype":"postalcode"
},
  "geometry": {"coordinates":[-1.352485,50.967643],"type":"Point"}
}