{
  "type": "Feature",
  "properties": {
    "iso:country": "GB",
    "wof:name": "SO50 5RF",
    "wof:placetype": "postalcode"
  },
  "geometry": {"coordinates":[-1.352485,50.967643],"type":"Point"}
}
