{
  "type": "Feature",
  "properties": {
    "iso:country":"GB",
    "wof:name":"SO50 5RF",
    "wof:placetype":"postalcode"
},
  "geometry": {"coordinates":[-1.35248513556234,50.96764314730956],"type":"Point"}
}