{
  "type": "Feature",
  "properties": {
    "iso:country":"GB",
    "wof:name":"E14 9EX",
    "wof:placetype":"postalcode"
},
  "geometry": {"coordinates":[-0.00920707713465,51.50821574400197],"type":"Point"}
}