{
  "type": "Feature",
  "properties": {
    "iso:country":"GB",
    "wof:name":"CR8 5DZ",
    "wof:placetype":"postalcode"
},
  "geometry": {"coordinates":[-0.10605210788714,51.32401294185546],"type":"Point"}
}