{
  "type": "Feature",
  "properties": {
    "iso:country":"GB",
    "wof:name":"IV52 8TP",
    "wof:placetype":"postalcode"
},
  "geometry": {"coordinates":[-5.65304650268147,57.33638580735006],"type":"Point"}
}