{
  "type": "Feature",
  "properties": {
    "iso:country": "GB",
    "wof:name": "IV52 8TP",
    "wof:placetype": "postalcode"
  },
  "geometry": {"coordinates":[-5.653046,57.336386],"type":"Point"}
}
