{
  "type": "Feature",
  "properties": {
    "date:inception_lower": "1980-01-01",
    "date:inception_upper": "1980-01-01",
    "iso:country": "GB",
    "wof:name": "G42 9UQ",
    "wof:placetype": "postalcode"
  },
  "geometry": {"coordinates":[-4.272075,55.826109],"type":"Point"}
}
