{
  "type": "Feature",
  "properties": {
    "date:inception_lower": "1997-06-01",
    "date:inception_upper": "1997-06-01",
    "iso:country": "GB",
    "wof:name": "WR8 0SP",
    "wof:placetype": "postalcode"
  },
  "geometry": {"coordinates":[-2.26832,52.056961],"type":"Point"}
}
