{
  "type": "Feature",
  "properties": {
    "iso:country": "GB",
    "wof:name": "WR8 0SP",
    "wof:placetype": "postalcode"
  },
  "geometry": {"coordinates":[-2.268443,52.05696],"type":"Point"}
}
