{
  "type": "Feature",
  "properties": {
    "iso:country":"GB",
    "wof:name":"NE18 0PU",
    "wof:placetype":"postalcode"
},
  "geometry": {"coordinates":[-1.85189675179297,55.03097915967783],"type":"Point"}
}