{
  "type": "Feature",
  "properties": {
    "date:inception_lower": "1992-08-01",
    "date:inception_upper": "1992-08-01",
    "iso:country": "GB",
    "wof:name": "WF13 2RP",
    "wof:placetype": "postalcode"
  },
  "geometry": {"coordinates":[-1.643886,53.68525],"type":"Point"}
}
