{
  "type": "Feature",
  "properties": {
    "date:inception_lower":"1993-08-01",
    "date:inception_upper":"1993-08-31",
    "iso:country":"GB",
    "wof:name":"LE15 6HB",
    "wof:placetype":"postalcode"
},
  "geometry": {"coordinates":[-0.720215,52.678114],"type":"Point"}
}