{
  "type": "Feature",
  "properties": {
    "iso:country": "GB",
    "wof:name": "LE15 6HB",
    "wof:placetype": "postalcode"
  },
  "geometry": {"coordinates":[-0.720215,52.678114],"type":"Point"}
}
