{
  "type": "Feature",
  "properties": {
    "iso:country": "GB",
    "wof:name": "CM11 2HL",
    "wof:placetype": "postalcode"
  },
  "geometry": {"coordinates":[0.432628,51.624513],"type":"Point"}
}
