{
  "type": "Feature",
  "properties": {
    "iso:country":"GB",
    "wof:name":"CM11 2HL",
    "wof:placetype":"postalcode"
},
  "geometry": {"coordinates":[0.43274187881886,51.62446245819875],"type":"Point"}
}