{
  "type": "Feature",
  "properties": {
    "iso:country":"GB",
    "wof:name":"RH6 9PY",
    "wof:placetype":"postalcode"
},
  "geometry": {"coordinates":[-0.11564085773372,51.17184586741734],"type":"Point"}
}