{
  "type": "Feature",
  "properties": {
    "iso:country": "GB",
    "wof:name": "DN37 7JS",
    "wof:placetype": "postalcode"
  },
  "geometry": {"coordinates":[-0.192045,53.524931],"type":"Point"}
}
