{
  "type": "Feature",
  "properties": {
    "iso:country": "GB",
    "wof:name": "CF40 1TL",
    "wof:placetype": "postalcode"
  },
  "geometry": {"coordinates":[-3.439845,51.614423],"type":"Point"}
}
