{
  "type": "Feature",
  "properties": {
    "date:inception_lower": "2014-10-01",
    "date:inception_upper": "2014-10-01",
    "iso:country": "GB",
    "wof:name": "S72 0JQ",
    "wof:placetype": "postalcode"
  },
  "geometry": {"coordinates":[-1.361298,53.546321],"type":"Point"}
}
