{
  "type": "Feature",
  "properties": {
    "iso:country": "GB",
    "wof:name": "S72 0JQ",
    "wof:placetype": "postalcode"
  },
  "geometry": {"coordinates":[-1.361298,53.546321],"type":"Point"}
}
