{
  "type": "Feature",
  "properties": {
    "iso:country":"GB",
    "wof:name":"S72 0JQ",
    "wof:placetype":"postalcode"
},
  "geometry": {"coordinates":[-1.3612975989052,53.54632133343502],"type":"Point"}
}