{
  "type": "Feature",
  "properties": {
    "iso:country":"GB",
    "wof:name":"PR7 4JZ",
    "wof:placetype":"postalcode"
},
  "geometry": {"coordinates":[-2.61210286591808,53.61066208722633],"type":"Point"}
}