{
  "type": "Feature",
  "properties": {
    "iso:country": "GB",
    "wof:name": "AB22 8YF",
    "wof:placetype": "postalcode"
  },
  "geometry": {"coordinates":[-2.12566,57.184686],"type":"Point"}
}
