{
  "type": "Feature",
  "properties": {
    "iso:country":"GB",
    "wof:name":"AB22 8YF",
    "wof:placetype":"postalcode"
},
  "geometry": {"coordinates":[-2.12566053907729,57.18468582397934],"type":"Point"}
}