{
  "type": "Feature",
  "properties": {
    "iso:country":"GB",
    "wof:name":"BA14 6LJ",
    "wof:placetype":"postalcode"
},
  "geometry": {"coordinates":[-2.12117804107077,51.33674156184887],"type":"Point"}
}