{
  "type": "Feature",
  "properties": {
    "date:inception_lower":"1980-01-01",
    "date:inception_upper":"1980-01-31",
    "iso:country":"GB",
    "wof:name":"PE6 7UE",
    "wof:placetype":"postalcode"
},
  "geometry": {"coordinates":[-0.178572,52.609863],"type":"Point"}
}