{
  "type": "Feature",
  "properties": {
    "iso:country": "GB",
    "wof:name": "PE6 7UE",
    "wof:placetype": "postalcode"
  },
  "geometry": {"coordinates":[-0.178572,52.609863],"type":"Point"}
}
