{
  "type": "Feature",
  "properties": {
    "iso:country":"GB",
    "wof:name":"PE6 7UE",
    "wof:placetype":"postalcode"
},
  "geometry": {"coordinates":[-0.17857164799119,52.609862702687],"type":"Point"}
}