{
  "type": "Feature",
  "properties": {
    "date:inception_lower": "1980-01-01",
    "date:inception_upper": "1980-01-01",
    "iso:country": "GB",
    "wof:name": "LS17 8HX",
    "wof:placetype": "postalcode"
  },
  "geometry": {"coordinates":[-1.485368,53.855556],"type":"Point"}
}
