{
  "type": "Feature",
  "properties": {
    "iso:country":"GB",
    "wof:name":"ST2 0NS",
    "wof:placetype":"postalcode"
},
  "geometry": {"coordinates":[-2.12633316573823,53.01668775715419],"type":"Point"}
}