{
  "type": "Feature",
  "properties": {
    "iso:country": "GB",
    "wof:name": "NE61 5RU",
    "wof:placetype": "postalcode"
  },
  "geometry": {"coordinates":[-1.557265,55.226785],"type":"Point"}
}
