{
  "type": "Feature",
  "properties": {
    "date:inception_lower":"2013-11-01",
    "date:inception_upper":"2013-11-30",
    "iso:country":"GB",
    "wof:name":"NE61 5RU",
    "wof:placetype":"postalcode"
},
  "geometry": {"coordinates":[-1.557265,55.226785],"type":"Point"}
}