{
  "type": "Feature",
  "properties": {
    "iso:country":"GB",
    "wof:name":"NE61 5RU",
    "wof:placetype":"postalcode"
},
  "geometry": {"coordinates":[-1.5572499707649,55.22678072698617],"type":"Point"}
}