{
  "type": "Feature",
  "properties": {
    "iso:country":"GB",
    "wof:name":"BD13 2PD",
    "wof:placetype":"postalcode"
},
  "geometry": {"coordinates":[-1.84822358701317,53.76781611633903],"type":"Point"}
}