{
  "type": "Feature",
  "properties": {
    "iso:country":"GB",
    "wof:name":"N13 5AF",
    "wof:placetype":"postalcode"
},
  "geometry": {"coordinates":[-0.0933533671442,51.62369262384291],"type":"Point"}
}