{
  "type": "Feature",
  "properties": {
    "iso:country": "GB",
    "wof:name": "EX20 2HS",
    "wof:placetype": "postalcode"
  },
  "geometry": {"coordinates":[-3.886687,50.700639],"type":"Point"}
}
