{
  "type": "Feature",
  "properties": {
    "iso:country":"GB",
    "wof:name":"PE8 4GD",
    "wof:placetype":"postalcode"
},
  "geometry": {"coordinates":[-0.48080464785598,52.48358902394735],"type":"Point"}
}