{
  "type": "Feature",
  "properties": {
    "date:inception_lower": "2013-11-01",
    "date:inception_upper": "2013-11-01",
    "iso:country": "GB",
    "wof:name": "PE8 4GD",
    "wof:placetype": "postalcode"
  },
  "geometry": {"coordinates":[-0.480805,52.483589],"type":"Point"}
}
