{
  "type": "Feature",
  "properties": {
    "iso:country":"GB",
    "wof:name":"SW17 9HG",
    "wof:placetype":"postalcode"
},
  "geometry": {"coordinates":[-0.16125504944311,51.42256215514048],"type":"Point"}
}