{
  "type": "Feature",
  "properties": {
    "iso:country":"GB",
    "wof:name":"CT11 0HX",
    "wof:placetype":"postalcode"
},
  "geometry": {"coordinates":[1.40060417428411,51.329513389805],"type":"Point"}
}