{
  "type": "Feature",
  "properties": {
    "iso:country":"GB",
    "wof:name":"LE18 4LA",
    "wof:placetype":"postalcode"
},
  "geometry": {"coordinates":[-1.12795129777684,52.58003819062782],"type":"Point"}
}