{
  "type": "Feature",
  "properties": {
    "iso:country": "GB",
    "wof:name": "PR4 0WA",
    "wof:placetype": "postalcode"
  },
  "geometry": {"coordinates":[-2.764619,53.781498],"type":"Point"}
}
