{
  "type": "Feature",
  "properties": {
    "iso:country":"GB",
    "wof:name":"PR4 0WA",
    "wof:placetype":"postalcode"
},
  "geometry": {"coordinates":[-2.76461885739111,53.78149793734988],"type":"Point"}
}