{
  "type": "Feature",
  "properties": {
    "iso:country":"GB",
    "wof:name":"BB7 1QD",
    "wof:placetype":"postalcode"
},
  "geometry": {"coordinates":[-2.37797151437324,53.87686969573313],"type":"Point"}
}