{
  "type": "Feature",
  "properties": {
    "date:inception_lower": "1987-04-01",
    "date:inception_upper": "1987-04-01",
    "iso:country": "GB",
    "wof:name": "BB7 1QD",
    "wof:placetype": "postalcode"
  },
  "geometry": {"coordinates":[-2.377971,53.87687],"type":"Point"}
}
