{
  "type": "Feature",
  "properties": {
    "iso:country":"GB",
    "wof:name":"AL3 4EL",
    "wof:placetype":"postalcode"
},
  "geometry": {"coordinates":[-0.34018916707093,51.75116335614841],"type":"Point"}
}