{
  "type": "Feature",
  "properties": {
    "iso:country": "GB",
    "wof:name": "AL3 4EL",
    "wof:placetype": "postalcode"
  },
  "geometry": {"coordinates":[-0.340311,51.751171],"type":"Point"}
}
