{
  "type": "Feature",
  "properties": {
    "iso:country":"GB",
    "wof:name":"NG21 9FQ",
    "wof:placetype":"postalcode"
},
  "geometry": {"coordinates":[-1.12222537707308,53.15939669171424],"type":"Point"}
}