{
  "type": "Feature",
  "properties": {
    "date:inception_lower":"2010-11-01",
    "date:inception_upper":"2010-11-30",
    "iso:country":"GB",
    "wof:name":"NG21 9FQ",
    "wof:placetype":"postalcode"
},
  "geometry": {"coordinates":[-1.122225,53.159397],"type":"Point"}
}