{
  "type": "Feature",
  "properties": {
    "date:inception_lower": "2015-06-01",
    "date:inception_upper": "2015-06-01",
    "iso:country": "GB",
    "wof:name": "KT16 9FL",
    "wof:placetype": "postalcode"
  },
  "geometry": {"coordinates":[-0.504632,51.391746],"type":"Point"}
}
