{
  "type": "Feature",
  "properties": {
    "date:inception_lower": "2022-10-01",
    "date:inception_upper": "2022-10-01",
    "iso:country": "GB",
    "wof:name": "M15 4YT",
    "wof:placetype": "postalcode"
  },
  "geometry": {"coordinates":[-2.265915,53.468594],"type":"Point"}
}
