{
  "type": "Feature",
  "properties": {
    "iso:country":"GB",
    "wof:name":"LL69 9UN",
    "wof:placetype":"postalcode"
},
  "geometry": {"coordinates":[-4.31669121152208,53.3904100409955],"type":"Point"}
}