{
  "type": "Feature",
  "properties": {
    "date:inception_lower": "1986-04-01",
    "date:inception_upper": "1986-04-01",
    "iso:country": "GB",
    "wof:name": "LL69 9UN",
    "wof:placetype": "postalcode"
  },
  "geometry": {"coordinates":[-4.316691,53.39041],"type":"Point"}
}
