{
  "type": "Feature",
  "properties": {
    "date:inception_lower": "2011-05-01",
    "date:inception_upper": "2011-05-01",
    "iso:country": "GB",
    "wof:name": "RM13 8FH",
    "wof:placetype": "postalcode"
  },
  "geometry": {"coordinates":[0.170554,51.529138],"type":"Point"}
}
