{
  "type": "Feature",
  "properties": {
    "iso:country":"GB",
    "wof:name":"RM13 8FH",
    "wof:placetype":"postalcode"
},
  "geometry": {"coordinates":[0.17016718619246,51.52917937362601],"type":"Point"}
}