{
  "type": "Feature",
  "properties": {
    "iso:country": "GB",
    "wof:name": "RM13 8FH",
    "wof:placetype": "postalcode"
  },
  "geometry": {"coordinates":[0.170554,51.529138],"type":"Point"}
}
