{
  "type": "Feature",
  "properties": {
    "date:inception_lower": "2023-04-01",
    "date:inception_upper": "2023-04-01",
    "iso:country": "GB",
    "wof:name": "KY12 2GE",
    "wof:placetype": "postalcode"
  },
  "geometry": {"coordinates":[-3.449589,56.068281],"type":"Point"}
}
