{
  "type": "Feature",
  "properties": {
    "iso:country":"GB",
    "wof:name":"HD5 9TH",
    "wof:placetype":"postalcode"
},
  "geometry": {"coordinates":[-1.74109434236999,53.6504458070676],"type":"Point"}
}