{
  "type": "Feature",
  "properties": {
    "iso:country": "GB",
    "wof:name": "DN11 0ZG",
    "wof:placetype": "postalcode"
  },
  "geometry": {"coordinates":[-1.091883,53.47971],"type":"Point"}
}
