{
  "type": "Feature",
  "properties": {
    "date:inception_lower": "2020-01-01",
    "date:inception_upper": "2020-01-01",
    "iso:country": "GB",
    "wof:name": "DN11 0ZG",
    "wof:placetype": "postalcode"
  },
  "geometry": {"coordinates":[-1.091777,53.479745],"type":"Point"}
}
