{
  "type": "Feature",
  "properties": {
    "iso:country":"GB",
    "wof:name":"SK3 9AR",
    "wof:placetype":"postalcode"
},
  "geometry": {"coordinates":[-2.16826121803849,53.40136783743908],"type":"Point"}
}