{
  "type": "Feature",
  "properties": {
    "date:inception_lower":"1980-01-01",
    "date:inception_upper":"1980-01-31",
    "iso:country":"GB",
    "wof:name":"EN1 2HB",
    "wof:placetype":"postalcode"
},
  "geometry": {"coordinates":[-0.080982,51.636809],"type":"Point"}
}