{
  "type": "Feature",
  "properties": {
    "iso:country":"GB",
    "wof:name":"EX1 3TP",
    "wof:placetype":"postalcode"
},
  "geometry": {"coordinates":[-3.4589652809128,50.74847142584387],"type":"Point"}
}