{
  "type": "Feature",
  "properties": {
    "iso:country":"GB",
    "wof:name":"DT4 9XW",
    "wof:placetype":"postalcode"
},
  "geometry": {"coordinates":[-2.46880029154728,50.59173900741152],"type":"Point"}
}