{
  "type": "Feature",
  "properties": {
    "date:inception_lower": "1999-06-01",
    "date:inception_upper": "1999-06-01",
    "iso:country": "GB",
    "wof:name": "DT4 9XW",
    "wof:placetype": "postalcode"
  },
  "geometry": {"coordinates":[-2.4688,50.591739],"type":"Point"}
}
