{
  "type": "Feature",
  "properties": {
    "date:inception_lower": "1980-01-01",
    "date:inception_upper": "1980-01-01",
    "iso:country": "GB",
    "wof:name": "TQ12 2EX",
    "wof:placetype": "postalcode"
  },
  "geometry": {"coordinates":[-3.602342,50.5304],"type":"Point"}
}
