{
  "type": "Feature",
  "properties": {
    "iso:country": "GB",
    "wof:name": "TQ12 2EX",
    "wof:placetype": "postalcode"
  },
  "geometry": {"coordinates":[-3.602215,50.530402],"type":"Point"}
}
