{
  "type": "Feature",
  "properties": {
    "iso:country":"GB",
    "wof:name":"EX15 3FE",
    "wof:placetype":"postalcode"
},
  "geometry": {"coordinates":[-3.32659130649527,50.90849133998535],"type":"Point"}
}