{
  "type": "Feature",
  "properties": {
    "date:inception_lower": "1980-01-01",
    "date:inception_upper": "1980-01-01",
    "iso:country": "GB",
    "wof:name": "TD6 9PW",
    "wof:placetype": "postalcode"
  },
  "geometry": {"coordinates":[-2.719658,55.596797],"type":"Point"}
}
