{
  "type": "Feature",
  "properties": {
    "iso:country":"GB",
    "wof:name":"DH9 7AX",
    "wof:placetype":"postalcode"
},
  "geometry": {"coordinates":[-1.70657442451193,54.85965316323959],"type":"Point"}
}