{
  "type": "Feature",
  "properties": {
    "iso:country": "GB",
    "wof:name": "PO2 7EY",
    "wof:placetype": "postalcode"
  },
  "geometry": {"coordinates":[-1.08022,50.81109],"type":"Point"}
}
