{
  "type": "Feature",
  "properties": {
    "iso:country": "GB",
    "wof:name": "WD18 0LA",
    "wof:placetype": "postalcode"
  },
  "geometry": {"coordinates":[-0.40763,51.651315],"type":"Point"}
}
