{
  "type": "Feature",
  "properties": {
    "iso:country":"GB",
    "wof:name":"KA10 6PR",
    "wof:placetype":"postalcode"
},
  "geometry": {"coordinates":[-4.65045726058124,55.54788538344675],"type":"Point"}
}