{
  "type": "Feature",
  "properties": {
    "iso:country": "GB",
    "wof:name": "BD19 6EH",
    "wof:placetype": "postalcode"
  },
  "geometry": {"coordinates":[-1.749152,53.730466],"type":"Point"}
}
