{
  "type": "Feature",
  "properties": {
    "iso:country": "GB",
    "wof:name": "CT18 8FA",
    "wof:placetype": "postalcode"
  },
  "geometry": {"coordinates":[1.092299,51.118038],"type":"Point"}
}
