{
  "type": "Feature",
  "properties": {
    "date:inception_lower":"1995-07-01",
    "date:inception_upper":"1995-07-31",
    "iso:country":"GB",
    "wof:name":"CT18 8FA",
    "wof:placetype":"postalcode"
},
  "geometry": {"coordinates":[1.092299,51.118038],"type":"Point"}
}