{
  "type": "Feature",
  "properties": {
    "iso:country":"GB",
    "wof:name":"CT18 8FA",
    "wof:placetype":"postalcode"
},
  "geometry": {"coordinates":[1.09229929051466,51.11803764860726],"type":"Point"}
}