{
  "type": "Feature",
  "properties": {
    "date:inception_lower":"1980-01-01",
    "date:inception_upper":"1980-01-31",
    "iso:country":"GB",
    "wof:name":"DY9 9EU",
    "wof:placetype":"postalcode"
},
  "geometry": {"coordinates":[-2.114726,52.44454],"type":"Point"}
}