{
  "type": "Feature",
  "properties": {
    "iso:country": "GB",
    "wof:name": "DY9 9EU",
    "wof:placetype": "postalcode"
  },
  "geometry": {"coordinates":[-2.114726,52.44454],"type":"Point"}
}
