{
  "type": "Feature",
  "properties": {
    "iso:country":"GB",
    "wof:name":"DY9 9EU",
    "wof:placetype":"postalcode"
},
  "geometry": {"coordinates":[-2.1147265005767,52.44453975208591],"type":"Point"}
}