{
  "type": "Feature",
  "properties": {
    "iso:country":"GB",
    "wof:name":"PA48 7TX",
    "wof:placetype":"postalcode"
},
  "geometry": {"coordinates":[-6.37840582190889,55.739542901053],"type":"Point"}
}