{
  "type": "Feature",
  "properties": {
    "iso:country":"GB",
    "wof:name":"SE18 3QW",
    "wof:placetype":"postalcode"
},
  "geometry": {"coordinates":[0.06582167677143,51.47904045651379],"type":"Point"}
}