{
  "type": "Feature",
  "properties": {
    "iso:country": "GB",
    "wof:name": "GL15 4SF",
    "wof:placetype": "postalcode"
  },
  "geometry": {"coordinates":[-2.521536,51.761321],"type":"Point"}
}
