{
  "type": "Feature",
  "properties": {
    "iso:country":"GB",
    "wof:name":"GL15 4SF",
    "wof:placetype":"postalcode"
},
  "geometry": {"coordinates":[-2.52153549421136,51.76132568254373],"type":"Point"}
}