{
  "type": "Feature",
  "properties": {
    "iso:country":"GB",
    "wof:name":"AB41 9GZ",
    "wof:placetype":"postalcode"
},
  "geometry": {"coordinates":[-2.0601719280361,57.37013091809834],"type":"Point"}
}