{
  "type": "Feature",
  "properties": {
    "iso:country":"GB",
    "wof:name":"SO41 0RZ",
    "wof:placetype":"postalcode"
},
  "geometry": {"coordinates":[-1.59661952829717,50.72853268933305],"type":"Point"}
}