{
  "type": "Feature",
  "properties": {
    "iso:country":"GB",
    "wof:name":"NN8 3JD",
    "wof:placetype":"postalcode"
},
  "geometry": {"coordinates":[-0.71037675211392,52.30049478344707],"type":"Point"}
}