{
  "type": "Feature",
  "properties": {
    "iso:country": "GB",
    "wof:name": "NN8 3JD",
    "wof:placetype": "postalcode"
  },
  "geometry": {"coordinates":[-0.710377,52.300495],"type":"Point"}
}
