{
  "type": "Feature",
  "properties": {
    "iso:country":"GB",
    "wof:name":"TN6 1BZ",
    "wof:placetype":"postalcode"
},
  "geometry": {"coordinates":[0.158630751882,51.05730486116035],"type":"Point"}
}