{
  "type": "Feature",
  "properties": {
    "date:inception_lower": "1980-01-01",
    "date:inception_upper": "1980-01-01",
    "iso:country": "GB",
    "wof:name": "CA4 8JG",
    "wof:placetype": "postalcode"
  },
  "geometry": {"coordinates":[-2.837244,54.882774],"type":"Point"}
}
