{
  "type": "Feature",
  "properties": {
    "iso:country": "GB",
    "wof:name": "AB15 8TP",
    "wof:placetype": "postalcode"
  },
  "geometry": {"coordinates":[-2.222369,57.162382],"type":"Point"}
}
