{
  "type": "Feature",
  "properties": {
    "iso:country":"GB",
    "wof:name":"TQ1 3BY",
    "wof:placetype":"postalcode"
},
  "geometry": {"coordinates":[-3.52765696853777,50.46920782944675],"type":"Point"}
}