{
  "type": "Feature",
  "properties": {
    "iso:country": "GB",
    "wof:name": "DN20 0QB",
    "wof:placetype": "postalcode"
  },
  "geometry": {"coordinates":[-0.503493,53.637806],"type":"Point"}
}
