{
  "type": "Feature",
  "properties": {
    "iso:country":"GB",
    "wof:name":"SR8 1WY",
    "wof:placetype":"postalcode"
},
  "geometry": {"coordinates":[-1.33328595851445,54.75794146168941],"type":"Point"}
}