{
  "type": "Feature",
  "properties": {
    "iso:country":"GB",
    "wof:name":"IP9 1NE",
    "wof:placetype":"postalcode"
},
  "geometry": {"coordinates":[1.25020652749511,51.96822742579744],"type":"Point"}
}