{
  "type": "Feature",
  "properties": {
    "date:inception_lower": "2007-08-01",
    "date:inception_upper": "2007-08-01",
    "iso:country": "GB",
    "wof:name": "SG13 8RE",
    "wof:placetype": "postalcode"
  },
  "geometry": {"coordinates":[-0.094546,51.777471],"type":"Point"}
}
