{
  "type": "Feature",
  "properties": {
    "iso:country":"GB",
    "wof:name":"SG13 8RE",
    "wof:placetype":"postalcode"
},
  "geometry": {"coordinates":[-0.09454635299052,51.77747137802986],"type":"Point"}
}