{
  "type": "Feature",
  "properties": {
    "iso:country":"GB",
    "wof:name":"M33 2AB",
    "wof:placetype":"postalcode"
},
  "geometry": {"coordinates":[-2.31871931028273,53.42485348408454],"type":"Point"}
}