{
  "type": "Feature",
  "properties": {
    "iso:country":"GB",
    "wof:name":"IP13 7QJ",
    "wof:placetype":"postalcode"
},
  "geometry": {"coordinates":[1.2963557885843,52.1712291489861],"type":"Point"}
}