{
  "type": "Feature",
  "properties": {
    "date:inception_lower":"1980-01-01",
    "date:inception_upper":"1980-01-31",
    "iso:country":"GB",
    "wof:name":"IP13 7QJ",
    "wof:placetype":"postalcode"
},
  "geometry": {"coordinates":[1.296386,52.171246],"type":"Point"}
}