{
  "type": "Feature",
  "properties": {
    "iso:country": "GB",
    "wof:name": "WV11 3DU",
    "wof:placetype": "postalcode"
  },
  "geometry": {"coordinates":[-2.062289,52.608483],"type":"Point"}
}
