{
  "type": "Feature",
  "properties": {
    "date:inception_lower": "2010-04-01",
    "date:inception_upper": "2010-04-01",
    "iso:country": "GB",
    "wof:name": "S72 7DB",
    "wof:placetype": "postalcode"
  },
  "geometry": {"coordinates":[-1.385222,53.578347],"type":"Point"}
}
