{
  "type": "Feature",
  "properties": {
    "iso:country":"GB",
    "wof:name":"S72 7DB",
    "wof:placetype":"postalcode"
},
  "geometry": {"coordinates":[-1.38522202146816,53.57834670817734],"type":"Point"}
}