{
  "type": "Feature",
  "properties": {
    "iso:country":"GB",
    "wof:name":"BS22 8DZ",
    "wof:placetype":"postalcode"
},
  "geometry": {"coordinates":[-2.94841801954754,51.35547881848683],"type":"Point"}
}