{
  "type": "Feature",
  "properties": {
    "iso:country":"GB",
    "wof:name":"UB6 8LX",
    "wof:placetype":"postalcode"
},
  "geometry": {"coordinates":[-0.35288495938938,51.54204211356998],"type":"Point"}
}