{
  "type": "Feature",
  "properties": {
    "iso:country":"GB",
    "wof:name":"SW8 4BU",
    "wof:placetype":"postalcode"
},
  "geometry": {"coordinates":[-0.14650918165446,51.47700481848493],"type":"Point"}
}