{
  "type": "Feature",
  "properties": {
    "date:inception_lower": "1980-01-01",
    "date:inception_upper": "1980-01-01",
    "iso:country": "GB",
    "wof:name": "SW8 4BU",
    "wof:placetype": "postalcode"
  },
  "geometry": {"coordinates":[-0.146457,51.476978],"type":"Point"}
}
