{
  "type": "Feature",
  "properties": {
    "iso:country":"GB",
    "wof:name":"DN8 4NJ",
    "wof:placetype":"postalcode"
},
  "geometry": {"coordinates":[-0.94652961933385,53.63351772985698],"type":"Point"}
}