{
  "type": "Feature",
  "properties": {
    "date:inception_lower":"1980-01-01",
    "date:inception_upper":"1980-01-31",
    "iso:country":"GB",
    "wof:name":"DN8 4NJ",
    "wof:placetype":"postalcode"
},
  "geometry": {"coordinates":[-0.94653,53.633518],"type":"Point"}
}