{
  "type": "Feature",
  "properties": {
    "iso:country": "GB",
    "wof:name": "PE28 0RA",
    "wof:placetype": "postalcode"
  },
  "geometry": {"coordinates":[-0.45932,52.373818],"type":"Point"}
}
