{
  "type": "Feature",
  "properties": {
    "iso:country":"GB",
    "wof:name":"PE28 0RA",
    "wof:placetype":"postalcode"
},
  "geometry": {"coordinates":[-0.47170636009515,52.37719998720829],"type":"Point"}
}