{
  "type": "Feature",
  "properties": {
    "iso:country": "GB",
    "wof:name": "PO2 8JA",
    "wof:placetype": "postalcode"
  },
  "geometry": {"coordinates":[-1.084749,50.81903],"type":"Point"}
}
