{
  "type": "Feature",
  "properties": {
    "iso:country":"GB",
    "wof:name":"PO2 8JA",
    "wof:placetype":"postalcode"
},
  "geometry": {"coordinates":[-1.08474891109818,50.81902990702431],"type":"Point"}
}