{
  "type": "Feature",
  "properties": {
    "iso:country":"GB",
    "wof:name":"CM1 7NT",
    "wof:placetype":"postalcode"
},
  "geometry": {"coordinates":[0.48776531745646,51.74641599613031],"type":"Point"}
}