{
  "type": "Feature",
  "properties": {
    "date:inception_lower": "1995-07-01",
    "date:inception_upper": "1995-07-01",
    "iso:country": "GB",
    "wof:name": "CM1 7NT",
    "wof:placetype": "postalcode"
  },
  "geometry": {"coordinates":[0.487765,51.746416],"type":"Point"}
}
