{
  "type": "Feature",
  "properties": {
    "iso:country": "GB",
    "wof:name": "TF2 6ND",
    "wof:placetype": "postalcode"
  },
  "geometry": {"coordinates":[-2.454515,52.69631],"type":"Point"}
}
