{
  "type": "Feature",
  "properties": {
    "date:inception_lower":"1992-08-01",
    "date:inception_upper":"1992-08-31",
    "iso:country":"GB",
    "wof:name":"TF2 6ND",
    "wof:placetype":"postalcode"
},
  "geometry": {"coordinates":[-2.454515,52.69631],"type":"Point"}
}