{
  "type": "Feature",
  "properties": {
    "iso:country":"GB",
    "wof:name":"TF2 6ND",
    "wof:placetype":"postalcode"
},
  "geometry": {"coordinates":[-2.45451540649362,52.69631036671471],"type":"Point"}
}