{
  "type": "Feature",
  "properties": {
    "iso:country":"GB",
    "wof:name":"GU34 3JE",
    "wof:placetype":"postalcode"
},
  "geometry": {"coordinates":[-0.94844499566664,51.098882494198],"type":"Point"}
}