{
  "type": "Feature",
  "properties": {
    "date:inception_lower": "1980-01-01",
    "date:inception_upper": "1980-01-01",
    "iso:country": "GB",
    "wof:name": "GL7 2LW",
    "wof:placetype": "postalcode"
  },
  "geometry": {"coordinates":[-1.983958,51.733761],"type":"Point"}
}
