{
  "type": "Feature",
  "properties": {
    "iso:country":"GB",
    "wof:name":"GL7 2LW",
    "wof:placetype":"postalcode"
},
  "geometry": {"coordinates":[-1.98396625133428,51.73375619594253],"type":"Point"}
}