{
  "type": "Feature",
  "properties": {
    "iso:country":"GB",
    "wof:name":"CW9 8DU",
    "wof:placetype":"postalcode"
},
  "geometry": {"coordinates":[-2.51176258016641,53.24674388179886],"type":"Point"}
}