{
  "type": "Feature",
  "properties": {
    "date:inception_lower": "1992-08-01",
    "date:inception_upper": "1992-08-01",
    "iso:country": "GB",
    "wof:name": "TS1 4AT",
    "wof:placetype": "postalcode"
  },
  "geometry": {"coordinates":[-1.23965,54.569218],"type":"Point"}
}
