{
  "type": "Feature",
  "properties": {
    "iso:country": "GB",
    "wof:name": "TS1 4AT",
    "wof:placetype": "postalcode"
  },
  "geometry": {"coordinates":[-1.23965,54.569218],"type":"Point"}
}
