{
  "type": "Feature",
  "properties": {
    "iso:country":"GB",
    "wof:name":"TS1 4AT",
    "wof:placetype":"postalcode"
},
  "geometry": {"coordinates":[-1.23963565544091,54.56920471707789],"type":"Point"}
}