{
  "type": "Feature",
  "properties": {
    "iso:country": "GB",
    "wof:name": "E9 5BT",
    "wof:placetype": "postalcode"
  },
  "geometry": {"coordinates":[-0.039099,51.544366],"type":"Point"}
}
