{
  "type": "Feature",
  "properties": {
    "iso:country":"GB",
    "wof:name":"WA6 9JG",
    "wof:placetype":"postalcode"
},
  "geometry": {"coordinates":[-2.74275067437553,53.23754578563931],"type":"Point"}
}