{
  "type": "Feature",
  "properties": {
    "date:inception_lower": "1980-01-01",
    "date:inception_upper": "1980-01-01",
    "iso:country": "GB",
    "wof:name": "WA6 9JG",
    "wof:placetype": "postalcode"
  },
  "geometry": {"coordinates":[-2.742751,53.237546],"type":"Point"}
}
