{
  "type": "Feature",
  "properties": {
    "iso:country":"GB",
    "wof:name":"LD8 2NL",
    "wof:placetype":"postalcode"
},
  "geometry": {"coordinates":[-3.03355001029562,52.27521814450566],"type":"Point"}
}