{
  "type": "Feature",
  "properties": {
    "date:inception_lower": "1980-01-01",
    "date:inception_upper": "1980-01-01",
    "iso:country": "GB",
    "wof:name": "LD8 2NL",
    "wof:placetype": "postalcode"
  },
  "geometry": {"coordinates":[-3.020147,52.273701],"type":"Point"}
}
