{
  "type": "Feature",
  "properties": {
    "date:inception_lower":"1980-01-01",
    "date:inception_upper":"1980-01-31",
    "iso:country":"GB",
    "wof:name":"LD8 2NL",
    "wof:placetype":"postalcode"
},
  "geometry": {"coordinates":[-3.03355,52.275218],"type":"Point"}
}