{
  "type": "Feature",
  "properties": {
    "iso:country":"GB",
    "wof:name":"SS16 6ES",
    "wof:placetype":"postalcode"
},
  "geometry": {"coordinates":[0.39894107253816,51.56681991822023],"type":"Point"}
}