{
  "type": "Feature",
  "properties": {
    "iso:country": "GB",
    "wof:name": "N20 8BF",
    "wof:placetype": "postalcode"
  },
  "geometry": {"coordinates":[-0.196028,51.63253],"type":"Point"}
}
