{
  "type": "Feature",
  "properties": {
    "iso:country":"GB",
    "wof:name":"N20 8BF",
    "wof:placetype":"postalcode"
},
  "geometry": {"coordinates":[-0.19605353395034,51.63252747548838],"type":"Point"}
}