{
  "type": "Feature",
  "properties": {
    "iso:country": "GB",
    "wof:name": "L13 6AA",
    "wof:placetype": "postalcode"
  },
  "geometry": {"coordinates":[-2.914807,53.414626],"type":"Point"}
}
