{
  "type": "Feature",
  "properties": {
    "iso:country":"GB",
    "wof:name":"PE2 7JE",
    "wof:placetype":"postalcode"
},
  "geometry": {"coordinates":[-0.2603611887994,52.55739869878343],"type":"Point"}
}