{
  "type": "Feature",
  "properties": {
    "iso:country": "GB",
    "wof:name": "TR11 3QY",
    "wof:placetype": "postalcode"
  },
  "geometry": {"coordinates":[-5.061596,50.151513],"type":"Point"}
}
