{
  "type": "Feature",
  "properties": {
    "iso:country":"GB",
    "wof:name":"TN13 1NR",
    "wof:placetype":"postalcode"
},
  "geometry": {"coordinates":[0.17875357508928,51.25251938134017],"type":"Point"}
}