{
  "type": "Feature",
  "properties": {
    "iso:country":"GB",
    "wof:name":"LL48 6SN",
    "wof:placetype":"postalcode"
},
  "geometry": {"coordinates":[-4.06596815582766,52.99172651856509],"type":"Point"}
}