{
  "type": "Feature",
  "properties": {
    "date:inception_lower": "2018-07-01",
    "date:inception_upper": "2018-07-01",
    "iso:country": "GB",
    "wof:name": "TS9 5FT",
    "wof:placetype": "postalcode"
  },
  "geometry": {"coordinates":[-1.190223,54.478217],"type":"Point"}
}
