{
  "type": "Feature",
  "properties": {
    "iso:country":"GB",
    "wof:name":"NP20 3GT",
    "wof:placetype":"postalcode"
},
  "geometry": {"coordinates":[-3.01827701725125,51.57815946953051],"type":"Point"}
}