{
  "type": "Feature",
  "properties": {
    "iso:country":"GB",
    "wof:name":"G64 3BZ",
    "wof:placetype":"postalcode"
},
  "geometry": {"coordinates":[-4.22380995414365,55.91252441802172],"type":"Point"}
}