{
  "type": "Feature",
  "properties": {
    "date:inception_lower": "1980-01-01",
    "date:inception_upper": "1980-01-01",
    "iso:country": "GB",
    "wof:name": "M6 7HG",
    "wof:placetype": "postalcode"
  },
  "geometry": {"coordinates":[-2.302682,53.499482],"type":"Point"}
}
