{
  "type": "Feature",
  "properties": {
    "iso:country":"GB",
    "wof:name":"KA7 1HU",
    "wof:placetype":"postalcode"
},
  "geometry": {"coordinates":[-4.63385952240121,55.4644767865331],"type":"Point"}
}