{
  "type": "Feature",
  "properties": {
    "iso:country":"GB",
    "wof:name":"HA8 7TB",
    "wof:placetype":"postalcode"
},
  "geometry": {"coordinates":[-0.28742490752842,51.61663079603218],"type":"Point"}
}