{
  "type": "Feature",
  "properties": {
    "iso:country":"GB",
    "wof:name":"BA3 4JX",
    "wof:placetype":"postalcode"
},
  "geometry": {"coordinates":[-2.5116818522336,51.26242922581118],"type":"Point"}
}