{
  "type": "Feature",
  "properties": {
    "date:inception_lower": "1980-01-01",
    "date:inception_upper": "1980-01-01",
    "iso:country": "GB",
    "wof:name": "LL29 9HD",
    "wof:placetype": "postalcode"
  },
  "geometry": {"coordinates":[-3.686531,53.288193],"type":"Point"}
}
