{
  "type": "Feature",
  "properties": {
    "iso:country":"GB",
    "wof:name":"WN2 5RQ",
    "wof:placetype":"postalcode"
},
  "geometry": {"coordinates":[-2.59403806668823,53.51029817238189],"type":"Point"}
}