{
  "type": "Feature",
  "properties": {
    "iso:country": "GB",
    "wof:name": "ME10 4FF",
    "wof:placetype": "postalcode"
  },
  "geometry": {"coordinates":[0.743505,51.338623],"type":"Point"}
}
