{
  "type": "Feature",
  "properties": {
    "iso:country":"GB",
    "wof:name":"ME10 4FF",
    "wof:placetype":"postalcode"
},
  "geometry": {"coordinates":[0.74348780471023,51.33862121870187],"type":"Point"}
}