{
  "type": "Feature",
  "properties": {
    "date:inception_lower":"2010-04-01",
    "date:inception_upper":"2010-04-30",
    "iso:country":"GB",
    "wof:name":"ME10 4FF",
    "wof:placetype":"postalcode"
},
  "geometry": {"coordinates":[0.743505,51.338623],"type":"Point"}
}