{
  "type": "Feature",
  "properties": {
    "iso:country":"GB",
    "wof:name":"G78 2QQ",
    "wof:placetype":"postalcode"
},
  "geometry": {"coordinates":[-4.3913435672826,55.79927442621122],"type":"Point"}
}