{
  "type": "Feature",
  "properties": {
    "date:inception_lower": "1980-01-01",
    "date:inception_upper": "1980-01-01",
    "iso:country": "GB",
    "wof:name": "L20 3BB",
    "wof:placetype": "postalcode"
  },
  "geometry": {"coordinates":[-2.985227,53.447416],"type":"Point"}
}
