{
  "type": "Feature",
  "properties": {
    "iso:country":"GB",
    "wof:name":"L20 3BB",
    "wof:placetype":"postalcode"
},
  "geometry": {"coordinates":[-2.9852270723635,53.44741637034636],"type":"Point"}
}