{
  "type": "Feature",
  "properties": {
    "iso:country": "GB",
    "wof:name": "SK11 7YW",
    "wof:placetype": "postalcode"
  },
  "geometry": {"coordinates":[-2.152317,53.249391],"type":"Point"}
}
