{
  "type": "Feature",
  "properties": {
    "iso:country":"GB",
    "wof:name":"DL4 1PG",
    "wof:placetype":"postalcode"
},
  "geometry": {"coordinates":[-1.64296722030435,54.62662233013154],"type":"Point"}
}