{
  "type": "Feature",
  "properties": {
    "date:inception_lower":"1981-06-01",
    "date:inception_upper":"1981-06-30",
    "iso:country":"GB",
    "wof:name":"WN6 0BT",
    "wof:placetype":"postalcode"
},
  "geometry": {"coordinates":[-2.644486,53.576435],"type":"Point"}
}