{
  "type": "Feature",
  "properties": {
    "iso:country":"GB",
    "wof:name":"WN6 0BT",
    "wof:placetype":"postalcode"
},
  "geometry": {"coordinates":[-2.64448643726854,53.57643484383843],"type":"Point"}
}