{
  "type": "Feature",
  "properties": {
    "iso:country": "GB",
    "wof:name": "WN6 0BT",
    "wof:placetype": "postalcode"
  },
  "geometry": {"coordinates":[-2.644486,53.576435],"type":"Point"}
}
