{
  "type": "Feature",
  "properties": {
    "date:inception_lower": "1980-01-01",
    "date:inception_upper": "1980-01-01",
    "iso:country": "GB",
    "wof:name": "LE2 5AP",
    "wof:placetype": "postalcode"
  },
  "geometry": {"coordinates":[-1.083354,52.597961],"type":"Point"}
}
