{
  "type": "Feature",
  "properties": {
    "iso:country": "GB",
    "wof:name": "G46 6BJ",
    "wof:placetype": "postalcode"
  },
  "geometry": {"coordinates":[-4.285311,55.809515],"type":"Point"}
}
