{
  "type": "Feature",
  "properties": {
    "iso:country":"GB",
    "wof:name":"G46 6BJ",
    "wof:placetype":"postalcode"
},
  "geometry": {"coordinates":[-4.28531147882837,55.80951542247839],"type":"Point"}
}