{
  "type": "Feature",
  "properties": {
    "date:inception_lower": "1980-01-01",
    "date:inception_upper": "1980-01-01",
    "iso:country": "GB",
    "wof:name": "SW3 3AJ",
    "wof:placetype": "postalcode"
  },
  "geometry": {"coordinates":[-0.167931,51.493431],"type":"Point"}
}
