{
  "type": "Feature",
  "properties": {
    "iso:country":"GB",
    "wof:name":"SW3 3AJ",
    "wof:placetype":"postalcode"
},
  "geometry": {"coordinates":[-0.16799870838953,51.49343914223297],"type":"Point"}
}