{
  "type": "Feature",
  "properties": {
    "iso:country":"GB",
    "wof:name":"BH12 3BQ",
    "wof:placetype":"postalcode"
},
  "geometry": {"coordinates":[-1.94718241359599,50.73109710380997],"type":"Point"}
}