{
  "type": "Feature",
  "properties": {
    "date:inception_lower": "1980-01-01",
    "date:inception_upper": "1980-01-01",
    "iso:country": "GB",
    "wof:name": "BH12 3BQ",
    "wof:placetype": "postalcode"
  },
  "geometry": {"coordinates":[-1.947182,50.731097],"type":"Point"}
}
