{
  "type": "Feature",
  "properties": {
    "iso:country":"GB",
    "wof:name":"BA12 9LP",
    "wof:placetype":"postalcode"
},
  "geometry": {"coordinates":[-2.17653286698816,51.19909607435118],"type":"Point"}
}