{
  "type": "Feature",
  "properties": {
    "iso:country":"GB",
    "wof:name":"CA9 3UH",
    "wof:placetype":"postalcode"
},
  "geometry": {"coordinates":[-2.43776137527422,54.79976246983318],"type":"Point"}
}