{
  "type": "Feature",
  "properties": {
    "date:inception_lower":"1980-01-01",
    "date:inception_upper":"1980-01-31",
    "iso:country":"GB",
    "wof:name":"CA9 3UH",
    "wof:placetype":"postalcode"
},
  "geometry": {"coordinates":[-2.437761,54.799762],"type":"Point"}
}