{
  "type": "Feature",
  "properties": {
    "iso:country":"GB",
    "wof:name":"MK40 3EN",
    "wof:placetype":"postalcode"
},
  "geometry": {"coordinates":[-0.44866392404089,52.14014562049396],"type":"Point"}
}