{
  "type": "Feature",
  "properties": {
    "date:inception_lower": "1980-01-01",
    "date:inception_upper": "1980-01-01",
    "iso:country": "GB",
    "wof:name": "MK40 3EN",
    "wof:placetype": "postalcode"
  },
  "geometry": {"coordinates":[-0.448664,52.140146],"type":"Point"}
}
