{
  "type": "Feature",
  "properties": {
    "iso:country":"GB",
    "wof:name":"TS3 6JD",
    "wof:placetype":"postalcode"
},
  "geometry": {"coordinates":[-1.21024740800578,54.57081397311363],"type":"Point"}
}