{
  "type": "Feature",
  "properties": {
    "iso:country":"GB",
    "wof:name":"B65 8LL",
    "wof:placetype":"postalcode"
},
  "geometry": {"coordinates":[-2.05847338135317,52.49375623164207],"type":"Point"}
}