{
  "type": "Feature",
  "properties": {
    "iso:country": "GB",
    "wof:name": "B65 8LL",
    "wof:placetype": "postalcode"
  },
  "geometry": {"coordinates":[-2.058473,52.493756],"type":"Point"}
}
