{
  "type": "Feature",
  "properties": {
    "iso:country":"GB",
    "wof:name":"ME5 0TQ",
    "wof:placetype":"postalcode"
},
  "geometry": {"coordinates":[0.52099140820554,51.35341755000645],"type":"Point"}
}