{
  "type": "Feature",
  "properties": {
    "date:inception_lower": "2004-01-01",
    "date:inception_upper": "2004-01-01",
    "iso:country": "GB",
    "wof:name": "ME5 0TQ",
    "wof:placetype": "postalcode"
  },
  "geometry": {"coordinates":[0.520991,51.353418],"type":"Point"}
}
