{
  "type": "Feature",
  "properties": {
    "iso:country":"GB",
    "wof:name":"DY9 7DG",
    "wof:placetype":"postalcode"
},
  "geometry": {"coordinates":[-2.11924952471613,52.45775956853402],"type":"Point"}
}