{
  "type": "Feature",
  "properties": {
    "iso:country": "GB",
    "wof:name": "CV35 9LZ",
    "wof:placetype": "postalcode"
  },
  "geometry": {"coordinates":[-1.594858,52.188692],"type":"Point"}
}
