{
  "type": "Feature",
  "properties": {
    "iso:country":"GB",
    "wof:name":"ME15 0AA",
    "wof:placetype":"postalcode"
},
  "geometry": {"coordinates":[0.51911030591152,51.24261110246223],"type":"Point"}
}