{
  "type": "Feature",
  "properties": {
    "iso:country":"GB",
    "wof:name":"PR6 8AE",
    "wof:placetype":"postalcode"
},
  "geometry": {"coordinates":[-2.62003513513484,53.67952586862193],"type":"Point"}
}