{
  "type": "Feature",
  "properties": {
    "iso:country": "GB",
    "wof:name": "PR6 8AE",
    "wof:placetype": "postalcode"
  },
  "geometry": {"coordinates":[-2.620035,53.679526],"type":"Point"}
}
