{
  "type": "Feature",
  "properties": {
    "date:inception_lower": "2000-06-01",
    "date:inception_upper": "2000-06-01",
    "iso:country": "GB",
    "wof:name": "DN33 3SF",
    "wof:placetype": "postalcode"
  },
  "geometry": {"coordinates":[-0.104774,53.540741],"type":"Point"}
}
