{
  "type": "Feature",
  "properties": {
    "date:inception_lower": "1980-01-01",
    "date:inception_upper": "1980-01-01",
    "iso:country": "GB",
    "wof:name": "SK17 7AB",
    "wof:placetype": "postalcode"
  },
  "geometry": {"coordinates":[-1.907298,53.269578],"type":"Point"}
}
