{
  "type": "Feature",
  "properties": {
    "iso:country": "GB",
    "wof:name": "SK17 7AB",
    "wof:placetype": "postalcode"
  },
  "geometry": {"coordinates":[-1.907298,53.269578],"type":"Point"}
}
