{
  "type": "Feature",
  "properties": {
    "iso:country":"GB",
    "wof:name":"DD7 7NN",
    "wof:placetype":"postalcode"
},
  "geometry": {"coordinates":[-2.74259462694439,56.49871677649102],"type":"Point"}
}