{
  "type": "Feature",
  "properties": {
    "iso:country": "GB",
    "wof:name": "KY7 4TL",
    "wof:placetype": "postalcode"
  },
  "geometry": {"coordinates":[-3.176535,56.177972],"type":"Point"}
}
