{
  "type": "Feature",
  "properties": {
    "date:inception_lower": "2003-06-01",
    "date:inception_upper": "2003-06-01",
    "iso:country": "GB",
    "wof:name": "SN4 9NU",
    "wof:placetype": "postalcode"
  },
  "geometry": {"coordinates":[-1.799159,51.514065],"type":"Point"}
}
