{
  "type": "Feature",
  "properties": {
    "iso:country":"GB",
    "wof:name":"TS10 4LF",
    "wof:placetype":"postalcode"
},
  "geometry": {"coordinates":[-1.0713046278801,54.60246911174978],"type":"Point"}
}