{
  "type": "Feature",
  "properties": {
    "iso:country":"GB",
    "wof:name":"E10 5ED",
    "wof:placetype":"postalcode"
},
  "geometry": {"coordinates":[-0.01617842073131,51.56599456407673],"type":"Point"}
}