{
  "type": "Feature",
  "properties": {
    "iso:country":"GB",
    "wof:name":"LE7 7SF",
    "wof:placetype":"postalcode"
},
  "geometry": {"coordinates":[-1.15803398224686,52.71752344927619],"type":"Point"}
}