{
  "type": "Feature",
  "properties": {
    "iso:country": "GB",
    "wof:name": "LE7 7SF",
    "wof:placetype": "postalcode"
  },
  "geometry": {"coordinates":[-1.158034,52.717523],"type":"Point"}
}
