{
  "type": "Feature",
  "properties": {
    "iso:country":"GB",
    "wof:name":"CF38 2LB",
    "wof:placetype":"postalcode"
},
  "geometry": {"coordinates":[-3.35769247353648,51.55393349798141],"type":"Point"}
}