{
  "type": "Feature",
  "properties": {
    "iso:country":"GB",
    "wof:name":"EX6 8RG",
    "wof:placetype":"postalcode"
},
  "geometry": {"coordinates":[-3.44769062321553,50.61492666988615],"type":"Point"}
}