{
  "type": "Feature",
  "properties": {
    "date:inception_lower": "1994-12-01",
    "date:inception_upper": "1994-12-01",
    "iso:country": "GB",
    "wof:name": "LL22 8HD",
    "wof:placetype": "postalcode"
  },
  "geometry": {"coordinates":[-3.640472,53.29049],"type":"Point"}
}
