{
  "type": "Feature",
  "properties": {
    "iso:country":"GB",
    "wof:name":"LL22 8HD",
    "wof:placetype":"postalcode"
},
  "geometry": {"coordinates":[-3.64047247147213,53.29049024928705],"type":"Point"}
}