{
  "type": "Feature",
  "properties": {
    "iso:country": "GB",
    "wof:name": "RG30 2HB",
    "wof:placetype": "postalcode"
  },
  "geometry": {"coordinates":[-1.023834,51.443854],"type":"Point"}
}
