{
  "type": "Feature",
  "properties": {
    "date:inception_lower":"1985-10-01",
    "date:inception_upper":"1985-10-31",
    "iso:country":"GB",
    "wof:name":"NE25 9XP",
    "wof:placetype":"postalcode"
},
  "geometry": {"coordinates":[-1.477305,55.048019],"type":"Point"}
}