{
  "type": "Feature",
  "properties": {
    "iso:country":"GB",
    "wof:name":"NE25 9XP",
    "wof:placetype":"postalcode"
},
  "geometry": {"coordinates":[-1.4773050782411,55.04801909161763],"type":"Point"}
}