{
  "type": "Feature",
  "properties": {
    "date:inception_lower": "2000-06-01",
    "date:inception_upper": "2000-06-01",
    "iso:country": "GB",
    "wof:name": "BN13 3TB",
    "wof:placetype": "postalcode"
  },
  "geometry": {"coordinates":[-0.424326,50.825255],"type":"Point"}
}
