{
  "type": "Feature",
  "properties": {
    "date:inception_lower": "1980-01-01",
    "date:inception_upper": "1980-01-01",
    "iso:country": "GB",
    "wof:name": "BD3 8QP",
    "wof:placetype": "postalcode"
  },
  "geometry": {"coordinates":[-1.724573,53.79737],"type":"Point"}
}
