{
  "type": "Feature",
  "properties": {
    "iso:country":"GB",
    "wof:name":"B68 8DH",
    "wof:placetype":"postalcode"
},
  "geometry": {"coordinates":[-2.01472561123897,52.48331455439389],"type":"Point"}
}