{
  "type": "Feature",
  "properties": {
    "date:inception_lower": "1993-01-01",
    "date:inception_upper": "1993-01-01",
    "iso:country": "GB",
    "wof:name": "LN11 9AS",
    "wof:placetype": "postalcode"
  },
  "geometry": {"coordinates":[0.005318,53.367397],"type":"Point"}
}
