{
  "type": "Feature",
  "properties": {
    "iso:country": "GB",
    "wof:name": "LN11 9AS",
    "wof:placetype": "postalcode"
  },
  "geometry": {"coordinates":[0.005318,53.367397],"type":"Point"}
}
