{
  "type": "Feature",
  "properties": {
    "iso:country":"GB",
    "wof:name":"LN11 9AS",
    "wof:placetype":"postalcode"
},
  "geometry": {"coordinates":[0.00531827848014,53.36739680682788],"type":"Point"}
}