{
  "type": "Feature",
  "properties": {
    "date:inception_lower": "2017-05-01",
    "date:inception_upper": "2017-05-01",
    "iso:country": "GB",
    "wof:name": "CF44 6HQ",
    "wof:placetype": "postalcode"
  },
  "geometry": {"coordinates":[-3.437612,51.708771],"type":"Point"}
}
