{
  "type": "Feature",
  "properties": {
    "iso:country": "GB",
    "wof:name": "CF44 6HQ",
    "wof:placetype": "postalcode"
  },
  "geometry": {"coordinates":[-3.437612,51.708771],"type":"Point"}
}
