{
  "type": "Feature",
  "properties": {
    "iso:country": "GB",
    "wof:name": "BD20 9LB",
    "wof:placetype": "postalcode"
  },
  "geometry": {"coordinates":[-1.940849,53.914706],"type":"Point"}
}
