{
  "type": "Feature",
  "properties": {
    "iso:country":"GB",
    "wof:name":"BS8 4AZ",
    "wof:placetype":"postalcode"
},
  "geometry": {"coordinates":[-2.62370928678043,51.4554881638656],"type":"Point"}
}