{
  "type": "Feature",
  "properties": {
    "iso:country": "GB",
    "wof:name": "ME10 1YZ",
    "wof:placetype": "postalcode"
  },
  "geometry": {"coordinates":[0.715204,51.323579],"type":"Point"}
}
