{
  "type": "Feature",
  "properties": {
    "date:inception_lower":"1995-01-01",
    "date:inception_upper":"1995-01-31",
    "iso:country":"GB",
    "wof:name":"CF48 4PU",
    "wof:placetype":"postalcode"
},
  "geometry": {"coordinates":[-3.343378,51.683842],"type":"Point"}
}