{
  "type": "Feature",
  "properties": {
    "iso:country":"GB",
    "wof:name":"G66 2DE",
    "wof:placetype":"postalcode"
},
  "geometry": {"coordinates":[-4.14374939541883,55.93794923490965],"type":"Point"}
}