{
  "type": "Feature",
  "properties": {
    "date:inception_lower": "1980-01-01",
    "date:inception_upper": "1980-01-01",
    "iso:country": "GB",
    "wof:name": "HA1 3NX",
    "wof:placetype": "postalcode"
  },
  "geometry": {"coordinates":[-0.339497,51.563192],"type":"Point"}
}
