{
  "type": "Feature",
  "properties": {
    "iso:country": "GB",
    "wof:name": "HA1 3NX",
    "wof:placetype": "postalcode"
  },
  "geometry": {"coordinates":[-0.339497,51.563192],"type":"Point"}
}
