{
  "type": "Feature",
  "properties": {
    "iso:country":"GB",
    "wof:name":"HA1 3NX",
    "wof:placetype":"postalcode"
},
  "geometry": {"coordinates":[-0.33949683860103,51.56319197252418],"type":"Point"}
}