{
  "type": "Feature",
  "properties": {
    "iso:country":"GB",
    "wof:name":"W1K 6NT",
    "wof:placetype":"postalcode"
},
  "geometry": {"coordinates":[-0.15534382604976,51.51287140040797],"type":"Point"}
}