{
  "type": "Feature",
  "properties": {
    "iso:country":"GB",
    "wof:name":"CA14 4RW",
    "wof:placetype":"postalcode"
},
  "geometry": {"coordinates":[-3.43797042281613,54.58389612050864],"type":"Point"}
}