{
  "type": "Feature",
  "properties": {
    "date:inception_lower": "1980-01-01",
    "date:inception_upper": "1980-01-01",
    "iso:country": "GB",
    "wof:name": "CA14 4RW",
    "wof:placetype": "postalcode"
  },
  "geometry": {"coordinates":[-3.43797,54.583896],"type":"Point"}
}
