{
  "type": "Feature",
  "properties": {
    "date:inception_lower":"2013-01-01",
    "date:inception_upper":"2013-01-31",
    "iso:country":"GB",
    "wof:name":"WV15 6AT",
    "wof:placetype":"postalcode"
},
  "geometry": {"coordinates":[-2.40684,52.529093],"type":"Point"}
}