{
  "type": "Feature",
  "properties": {
    "iso:country":"GB",
    "wof:name":"IP33 3JZ",
    "wof:placetype":"postalcode"
},
  "geometry": {"coordinates":[0.70111390421979,52.24023745148308],"type":"Point"}
}