{
  "type": "Feature",
  "properties": {
    "iso:country": "GB",
    "wof:name": "WC1B 3LE",
    "wof:placetype": "postalcode"
  },
  "geometry": {"coordinates":[-0.128351,51.517776],"type":"Point"}
}
