{
  "type": "Feature",
  "properties": {
    "iso:country":"GB",
    "wof:name":"PE11 4RD",
    "wof:placetype":"postalcode"
},
  "geometry": {"coordinates":[-0.20762566075546,52.87588302411278],"type":"Point"}
}