{
  "type": "Feature",
  "properties": {
    "date:inception_lower":"1980-01-01",
    "date:inception_upper":"1980-01-31",
    "iso:country":"GB",
    "wof:name":"PE11 4RD",
    "wof:placetype":"postalcode"
},
  "geometry": {"coordinates":[-0.207631,52.875915],"type":"Point"}
}