{
  "type": "Feature",
  "properties": {
    "iso:country":"GB",
    "wof:name":"KT9 2ER",
    "wof:placetype":"postalcode"
},
  "geometry": {"coordinates":[-0.30455131571638,51.36164021512832],"type":"Point"}
}