{
  "type": "Feature",
  "properties": {
    "date:inception_lower": "2014-07-01",
    "date:inception_upper": "2014-07-01",
    "iso:country": "GB",
    "wof:name": "MK41 0FP",
    "wof:placetype": "postalcode"
  },
  "geometry": {"coordinates":[-0.414772,52.157138],"type":"Point"}
}
