{
  "type": "Feature",
  "properties": {
    "iso:country":"GB",
    "wof:name":"MK41 0FP",
    "wof:placetype":"postalcode"
},
  "geometry": {"coordinates":[-0.41477186505556,52.15713808179569],"type":"Point"}
}