{
  "type": "Feature",
  "properties": {
    "iso:country": "GB",
    "wof:name": "DE3 0HA",
    "wof:placetype": "postalcode"
  },
  "geometry": {"coordinates":[-1.54633,52.907111],"type":"Point"}
}
