{
  "type": "Feature",
  "properties": {
    "iso:country": "GB",
    "wof:name": "SA48 7SF",
    "wof:placetype": "postalcode"
  },
  "geometry": {"coordinates":[-4.196678,52.207868],"type":"Point"}
}
