{
  "type": "Feature",
  "properties": {
    "date:inception_lower": "1980-01-01",
    "date:inception_upper": "1980-01-01",
    "iso:country": "GB",
    "wof:name": "M6 7LP",
    "wof:placetype": "postalcode"
  },
  "geometry": {"coordinates":[-2.304629,53.502056],"type":"Point"}
}
