{
  "type": "Feature",
  "properties": {
    "iso:country":"GB",
    "wof:name":"M6 7LP",
    "wof:placetype":"postalcode"
},
  "geometry": {"coordinates":[-2.3047795951723,53.50193930019588],"type":"Point"}
}