{
  "type": "Feature",
  "properties": {
    "iso:country":"GB",
    "wof:name":"SG4 8QR",
    "wof:placetype":"postalcode"
},
  "geometry": {"coordinates":[-0.30627800918331,51.84936589764839],"type":"Point"}
}