{
  "type": "Feature",
  "properties": {
    "date:inception_lower": "1980-01-01",
    "date:inception_upper": "1980-01-01",
    "iso:country": "GB",
    "wof:name": "SG4 8QR",
    "wof:placetype": "postalcode"
  },
  "geometry": {"coordinates":[-0.306209,51.8494],"type":"Point"}
}
