{
  "type": "Feature",
  "properties": {
    "iso:country":"GB",
    "wof:name":"S43 1BE",
    "wof:placetype":"postalcode"
},
  "geometry": {"coordinates":[-1.40820415246271,53.25669517672976],"type":"Point"}
}