{
  "type": "Feature",
  "properties": {
    "iso:country": "GB",
    "wof:name": "S43 1BE",
    "wof:placetype": "postalcode"
  },
  "geometry": {"coordinates":[-1.408204,53.256695],"type":"Point"}
}
