{
  "type": "Feature",
  "properties": {
    "iso:country": "GB",
    "wof:name": "DE55 3BJ",
    "wof:placetype": "postalcode"
  },
  "geometry": {"coordinates":[-1.334612,53.09854],"type":"Point"}
}
