{
  "type": "Feature",
  "properties": {
    "iso:country":"GB",
    "wof:name":"B90 1BY",
    "wof:placetype":"postalcode"
},
  "geometry": {"coordinates":[-1.8532738418585,52.40484086768414],"type":"Point"}
}