{
  "type": "Feature",
  "properties": {
    "iso:country": "GB",
    "wof:name": "B90 1BY",
    "wof:placetype": "postalcode"
  },
  "geometry": {"coordinates":[-1.853274,52.404841],"type":"Point"}
}
