{
  "type": "Feature",
  "properties": {
    "date:inception_lower":"2014-12-01",
    "date:inception_upper":"2014-12-31",
    "iso:country":"GB",
    "wof:name":"B90 1BY",
    "wof:placetype":"postalcode"
},
  "geometry": {"coordinates":[-1.853274,52.404841],"type":"Point"}
}