{
  "type": "Feature",
  "properties": {
    "iso:country":"GB",
    "wof:name":"B44 0BH",
    "wof:placetype":"postalcode"
},
  "geometry": {"coordinates":[-1.88072211626069,52.53937968707181],"type":"Point"}
}