{
  "type": "Feature",
  "properties": {
    "date:inception_lower": "2015-10-01",
    "date:inception_upper": "2015-10-01",
    "iso:country": "GB",
    "wof:name": "TN12 0FD",
    "wof:placetype": "postalcode"
  },
  "geometry": {"coordinates":[0.551338,51.157955],"type":"Point"}
}
