{
  "type": "Feature",
  "properties": {
    "iso:country": "GB",
    "wof:name": "TR7 2QH",
    "wof:placetype": "postalcode"
  },
  "geometry": {"coordinates":[-5.067342,50.418489],"type":"Point"}
}
