{
  "type": "Feature",
  "properties": {
    "iso:country":"GB",
    "wof:name":"TR7 2QH",
    "wof:placetype":"postalcode"
},
  "geometry": {"coordinates":[-5.06734213348706,50.41848851743156],"type":"Point"}
}