{
  "type": "Feature",
  "properties": {
    "iso:country":"GB",
    "wof:name":"EX32 8DE",
    "wof:placetype":"postalcode"
},
  "geometry": {"coordinates":[-4.04755277743018,51.07970055295257],"type":"Point"}
}