{
  "type": "Feature",
  "properties": {
    "iso:country": "GB",
    "wof:name": "EX32 8DE",
    "wof:placetype": "postalcode"
  },
  "geometry": {"coordinates":[-4.047553,51.079701],"type":"Point"}
}
