{
  "type": "Feature",
  "properties": {
    "iso:country":"GB",
    "wof:name":"EH22 2LD",
    "wof:placetype":"postalcode"
},
  "geometry": {"coordinates":[-3.05871110303366,55.89062094062906],"type":"Point"}
}