{
  "type": "Feature",
  "properties": {
    "iso:country":"GB",
    "wof:name":"TS18 3EH",
    "wof:placetype":"postalcode"
},
  "geometry": {"coordinates":[-1.31956611036362,54.55927340663706],"type":"Point"}
}