{
  "type": "Feature",
  "properties": {
    "iso:country":"GB",
    "wof:name":"WF7 6DW",
    "wof:placetype":"postalcode"
},
  "geometry": {"coordinates":[-1.40269733114236,53.67683971954784],"type":"Point"}
}