{
  "type": "Feature",
  "properties": {
    "date:inception_lower": "2024-09-01",
    "date:inception_upper": "2024-09-01",
    "iso:country": "GB",
    "wof:name": "CB6 1TW",
    "wof:placetype": "postalcode"
  },
  "geometry": {"coordinates":[0.262845,52.402561],"type":"Point"}
}
