{
  "type": "Feature",
  "properties": {
    "iso:country": "GB",
    "wof:name": "ML11 9DL",
    "wof:placetype": "postalcode"
  },
  "geometry": {"coordinates":[-3.761282,55.670382],"type":"Point"}
}
