{
  "type": "Feature",
  "properties": {
    "date:inception_lower": "2001-12-01",
    "date:inception_upper": "2001-12-01",
    "iso:country": "GB",
    "wof:name": "ML11 9DL",
    "wof:placetype": "postalcode"
  },
  "geometry": {"coordinates":[-3.761282,55.670382],"type":"Point"}
}
