{
  "type": "Feature",
  "properties": {
    "iso:country":"GB",
    "wof:name":"ML11 9DL",
    "wof:placetype":"postalcode"
},
  "geometry": {"coordinates":[-3.76128204206036,55.67038187370011],"type":"Point"}
}