{
  "type": "Feature",
  "properties": {
    "iso:country": "GB",
    "wof:name": "DH1 4PY",
    "wof:placetype": "postalcode"
  },
  "geometry": {"coordinates":[-1.5815,54.776153],"type":"Point"}
}
