{
  "type": "Feature",
  "properties": {
    "iso:country":"GB",
    "wof:name":"DH1 4PY",
    "wof:placetype":"postalcode"
},
  "geometry": {"coordinates":[-1.58149003799918,54.77614368249191],"type":"Point"}
}