{
  "type": "Feature",
  "properties": {
    "date:inception_lower": "2003-11-01",
    "date:inception_upper": "2003-11-01",
    "iso:country": "GB",
    "wof:name": "DH1 4PY",
    "wof:placetype": "postalcode"
  },
  "geometry": {"coordinates":[-1.5815,54.776153],"type":"Point"}
}
