{
  "type": "Feature",
  "properties": {
    "date:inception_lower": "1980-01-01",
    "date:inception_upper": "1980-01-01",
    "iso:country": "GB",
    "wof:name": "L21 8ND",
    "wof:placetype": "postalcode"
  },
  "geometry": {"coordinates":[-2.998782,53.467439],"type":"Point"}
}
