{
  "type": "Feature",
  "properties": {
    "iso:country": "GB",
    "wof:name": "M11 2GL",
    "wof:placetype": "postalcode"
  },
  "geometry": {"coordinates":[-2.178066,53.476525],"type":"Point"}
}
