{
  "type": "Feature",
  "properties": {
    "iso:country":"GB",
    "wof:name":"NN7 2DL",
    "wof:placetype":"postalcode"
},
  "geometry": {"coordinates":[-0.82637932872831,52.18390691742493],"type":"Point"}
}