{
  "type": "Feature",
  "properties": {
    "iso:country": "GB",
    "wof:name": "NN7 2DL",
    "wof:placetype": "postalcode"
  },
  "geometry": {"coordinates":[-0.826379,52.183907],"type":"Point"}
}
