{
  "type": "Feature",
  "properties": {
    "iso:country":"GB",
    "wof:name":"DA8 3BH",
    "wof:placetype":"postalcode"
},
  "geometry": {"coordinates":[0.16932580016262,51.47537239809316],"type":"Point"}
}