{
  "type": "Feature",
  "properties": {
    "iso:country": "GB",
    "wof:name": "DA8 3BH",
    "wof:placetype": "postalcode"
  },
  "geometry": {"coordinates":[0.169326,51.475372],"type":"Point"}
}
