{
  "type": "Feature",
  "properties": {
    "date:inception_lower": "2022-07-01",
    "date:inception_upper": "2022-07-01",
    "iso:country": "GB",
    "wof:name": "OL11 3DW",
    "wof:placetype": "postalcode"
  },
  "geometry": {"coordinates":[-2.17331,53.599949],"type":"Point"}
}
