{
  "type": "Feature",
  "properties": {
    "iso:country":"GB",
    "wof:name":"SO16 0XH",
    "wof:placetype":"postalcode"
},
  "geometry": {"coordinates":[-1.46496400150733,50.945029883545],"type":"Point"}
}