{
  "type": "Feature",
  "properties": {
    "iso:country":"GB",
    "wof:name":"OX3 7XB",
    "wof:placetype":"postalcode"
},
  "geometry": {"coordinates":[-1.21819298498827,51.7515688153338],"type":"Point"}
}