{
  "type": "Feature",
  "properties": {
    "iso:country":"GB",
    "wof:name":"GL20 7RQ",
    "wof:placetype":"postalcode"
},
  "geometry": {"coordinates":[-2.14491523310372,51.98634828519819],"type":"Point"}
}