{
  "type": "Feature",
  "properties": {
    "iso:country": "GB",
    "wof:name": "PA23 8JJ",
    "wof:placetype": "postalcode"
  },
  "geometry": {"coordinates":[-4.921005,55.957514],"type":"Point"}
}
