{
  "type": "Feature",
  "properties": {
    "iso:country":"GB",
    "wof:name":"IV36 3UH",
    "wof:placetype":"postalcode"
},
  "geometry": {"coordinates":[-3.55730796013042,57.63958671114014],"type":"Point"}
}