{
  "type": "Feature",
  "properties": {
    "date:inception_lower": "1998-12-01",
    "date:inception_upper": "1998-12-01",
    "iso:country": "GB",
    "wof:name": "IV36 3UH",
    "wof:placetype": "postalcode"
  },
  "geometry": {"coordinates":[-3.558303,57.640952],"type":"Point"}
}
