{
  "type": "Feature",
  "properties": {
    "iso:country": "GB",
    "wof:name": "CF42 6AB",
    "wof:placetype": "postalcode"
  },
  "geometry": {"coordinates":[-3.506188,51.657826],"type":"Point"}
}
