{
  "type": "Feature",
  "properties": {
    "date:inception_lower": "2018-09-01",
    "date:inception_upper": "2018-09-01",
    "iso:country": "GB",
    "wof:name": "CF42 6AB",
    "wof:placetype": "postalcode"
  },
  "geometry": {"coordinates":[-3.506204,51.65787],"type":"Point"}
}
