{
  "type": "Feature",
  "properties": {
    "date:inception_lower":"1980-01-01",
    "date:inception_upper":"1980-01-31",
    "iso:country":"GB",
    "wof:name":"SA10 9BG",
    "wof:placetype":"postalcode"
},
  "geometry": {"coordinates":[-3.705489,51.770218],"type":"Point"}
}