{
  "type": "Feature",
  "properties": {
    "iso:country":"GB",
    "wof:name":"PO19 5UF",
    "wof:placetype":"postalcode"
},
  "geometry": {"coordinates":[-0.78099093998496,50.85624366110937],"type":"Point"}
}