{
  "type": "Feature",
  "properties": {
    "iso:country":"GB",
    "wof:name":"SL1 5UP",
    "wof:placetype":"postalcode"
},
  "geometry": {"coordinates":[-0.64001336550894,51.50959157707187],"type":"Point"}
}