{
  "type": "Feature",
  "properties": {
    "iso:country":"GB",
    "wof:name":"W12 0QG",
    "wof:placetype":"postalcode"
},
  "geometry": {"coordinates":[-0.24279194677816,51.51256849585864],"type":"Point"}
}