{
  "type": "Feature",
  "properties": {
    "iso:country": "GB",
    "wof:name": "MK44 3BH",
    "wof:placetype": "postalcode"
  },
  "geometry": {"coordinates":[-0.307178,52.191226],"type":"Point"}
}
