{
  "type": "Feature",
  "properties": {
    "iso:country":"GB",
    "wof:name":"SA41 3UB",
    "wof:placetype":"postalcode"
},
  "geometry": {"coordinates":[-4.75833089132681,51.99573749968581],"type":"Point"}
}