{
  "type": "Feature",
  "properties": {
    "iso:country":"GB",
    "wof:name":"M16 8FA",
    "wof:placetype":"postalcode"
},
  "geometry": {"coordinates":[-2.25770292123647,53.45311694865453],"type":"Point"}
}