{
  "type": "Feature",
  "properties": {
    "date:inception_lower":"1980-01-01",
    "date:inception_upper":"1980-01-31",
    "iso:country":"GB",
    "wof:name":"TN34 3RY",
    "wof:placetype":"postalcode"
},
  "geometry": {"coordinates":[0.585921,50.860965],"type":"Point"}
}