{
  "type": "Feature",
  "properties": {
    "iso:country":"GB",
    "wof:name":"AB15 8JT",
    "wof:placetype":"postalcode"
},
  "geometry": {"coordinates":[-2.16340578348832,57.1384157590883],"type":"Point"}
}