{
  "type": "Feature",
  "properties": {
    "iso:country": "GB",
    "wof:name": "TF13 6EE",
    "wof:placetype": "postalcode"
  },
  "geometry": {"coordinates":[-2.663048,52.552585],"type":"Point"}
}
