{
  "type": "Feature",
  "properties": {
    "iso:country":"GB",
    "wof:name":"TF13 6EE",
    "wof:placetype":"postalcode"
},
  "geometry": {"coordinates":[-2.66304766805157,52.55258549207598],"type":"Point"}
}