{
  "type": "Feature",
  "properties": {
    "iso:country": "GB",
    "wof:name": "GL14 1DZ",
    "wof:placetype": "postalcode"
  },
  "geometry": {"coordinates":[-2.456582,51.787356],"type":"Point"}
}
