{
  "type": "Feature",
  "properties": {
    "date:inception_lower": "1990-02-01",
    "date:inception_upper": "1990-02-01",
    "iso:country": "GB",
    "wof:name": "B69 3LA",
    "wof:placetype": "postalcode"
  },
  "geometry": {"coordinates":[-2.03516,52.514667],"type":"Point"}
}
