{
  "type": "Feature",
  "properties": {
    "iso:country":"GB",
    "wof:name":"B69 3LA",
    "wof:placetype":"postalcode"
},
  "geometry": {"coordinates":[-2.03515993521215,52.51466707421677],"type":"Point"}
}