{
  "type": "Feature",
  "properties": {
    "date:inception_lower": "2022-04-01",
    "date:inception_upper": "2022-04-01",
    "iso:country": "GB",
    "wof:name": "CR3 0FL",
    "wof:placetype": "postalcode"
  },
  "geometry": {"coordinates":[-0.074111,51.301908],"type":"Point"}
}
