{
  "type": "Feature",
  "properties": {
    "iso:country":"GB",
    "wof:name":"GL1 2QW",
    "wof:placetype":"postalcode"
},
  "geometry": {"coordinates":[-2.24439834655427,51.87091230703123],"type":"Point"}
}