{
  "type": "Feature",
  "properties": {
    "iso:country":"GB",
    "wof:name":"B79 7DQ",
    "wof:placetype":"postalcode"
},
  "geometry": {"coordinates":[-1.69693703448186,52.63380504660094],"type":"Point"}
}