{
  "type": "Feature",
  "properties": {
    "iso:country":"GB",
    "wof:name":"GL5 4PN",
    "wof:placetype":"postalcode"
},
  "geometry": {"coordinates":[-2.2565171181512,51.74679257865601],"type":"Point"}
}