{
  "type": "Feature",
  "properties": {
    "iso:country":"GB",
    "wof:name":"TN2 5PE",
    "wof:placetype":"postalcode"
},
  "geometry": {"coordinates":[0.244839044621,51.11657580083344],"type":"Point"}
}