{
  "type": "Feature",
  "properties": {
    "date:inception_lower": "1980-01-01",
    "date:inception_upper": "1980-01-01",
    "iso:country": "GB",
    "wof:name": "TN2 5PE",
    "wof:placetype": "postalcode"
  },
  "geometry": {"coordinates":[0.244174,51.11674],"type":"Point"}
}
