{
  "type": "Feature",
  "properties": {
    "iso:country":"GB",
    "wof:name":"IP5 1AG",
    "wof:placetype":"postalcode"
},
  "geometry": {"coordinates":[1.22584111033582,52.0645504983885],"type":"Point"}
}