{
  "type": "Feature",
  "properties": {
    "iso:country": "GB",
    "wof:name": "PL31 1PL",
    "wof:placetype": "postalcode"
  },
  "geometry": {"coordinates":[-4.732741,50.46466],"type":"Point"}
}
