{
  "type": "Feature",
  "properties": {
    "date:inception_lower": "1980-01-01",
    "date:inception_upper": "1980-01-01",
    "iso:country": "GB",
    "wof:name": "CV13 6LT",
    "wof:placetype": "postalcode"
  },
  "geometry": {"coordinates":[-1.469445,52.628564],"type":"Point"}
}
