{
  "type": "Feature",
  "properties": {
    "date:inception_lower": "1980-01-01",
    "date:inception_upper": "1980-01-01",
    "iso:country": "GB",
    "wof:name": "WR9 8AN",
    "wof:placetype": "postalcode"
  },
  "geometry": {"coordinates":[-2.153363,52.261057],"type":"Point"}
}
