{
  "type": "Feature",
  "properties": {
    "date:inception_lower": "1980-01-01",
    "date:inception_upper": "1980-01-01",
    "iso:country": "GB",
    "wof:name": "EX2 5HJ",
    "wof:placetype": "postalcode"
  },
  "geometry": {"coordinates":[-3.496464,50.718867],"type":"Point"}
}
