{
  "type": "Feature",
  "properties": {
    "date:inception_lower":"1980-01-01",
    "date:inception_upper":"1980-01-31",
    "iso:country":"GB",
    "wof:name":"NG19 7HP",
    "wof:placetype":"postalcode"
},
  "geometry": {"coordinates":[-1.215564,53.159481],"type":"Point"}
}