{
  "type": "Feature",
  "properties": {
    "date:inception_lower": "2001-12-01",
    "date:inception_upper": "2001-12-01",
    "iso:country": "GB",
    "wof:name": "SL5 0HN",
    "wof:placetype": "postalcode"
  },
  "geometry": {"coordinates":[-0.624484,51.391614],"type":"Point"}
}
