{
  "type": "Feature",
  "properties": {
    "iso:country": "GB",
    "wof:name": "SL5 0HN",
    "wof:placetype": "postalcode"
  },
  "geometry": {"coordinates":[-0.624484,51.391614],"type":"Point"}
}
