{
  "type": "Feature",
  "properties": {
    "iso:country":"GB",
    "wof:name":"SL5 0HN",
    "wof:placetype":"postalcode"
},
  "geometry": {"coordinates":[-0.62448408851274,51.39161379710684],"type":"Point"}
}