{
  "type": "Feature",
  "properties": {
    "iso:country": "GB",
    "wof:name": "ST13 5SX",
    "wof:placetype": "postalcode"
  },
  "geometry": {"coordinates":[-2.013118,53.102142],"type":"Point"}
}
