{
  "type": "Feature",
  "properties": {
    "iso:country":"GB",
    "wof:name":"ML7 5NE",
    "wof:placetype":"postalcode"
},
  "geometry": {"coordinates":[-3.77872258493399,55.81874232668132],"type":"Point"}
}