{
  "type": "Feature",
  "properties": {
    "date:inception_lower": "1980-01-01",
    "date:inception_upper": "1980-01-01",
    "iso:country": "GB",
    "wof:name": "ML7 5NE",
    "wof:placetype": "postalcode"
  },
  "geometry": {"coordinates":[-3.778723,55.818742],"type":"Point"}
}
