{
  "type": "Feature",
  "properties": {
    "iso:country": "GB",
    "wof:name": "DD1 4ER",
    "wof:placetype": "postalcode"
  },
  "geometry": {"coordinates":[-2.971966,56.458985],"type":"Point"}
}
