{
  "type": "Feature",
  "properties": {
    "iso:country":"GB",
    "wof:name":"DD1 4ER",
    "wof:placetype":"postalcode"
},
  "geometry": {"coordinates":[-2.97196612381587,56.45898521305072],"type":"Point"}
}