{
  "type": "Feature",
  "properties": {
    "iso:country":"GB",
    "wof:name":"B30 1RH",
    "wof:placetype":"postalcode"
},
  "geometry": {"coordinates":[-1.94929471679235,52.42486976275856],"type":"Point"}
}