{
  "type": "Feature",
  "properties": {
    "iso:country":"GB",
    "wof:name":"S43 3BN",
    "wof:placetype":"postalcode"
},
  "geometry": {"coordinates":[-1.33046871839333,53.27102602411355],"type":"Point"}
}