{
  "type": "Feature",
  "properties": {
    "date:inception_lower": "1980-01-01",
    "date:inception_upper": "1980-01-01",
    "iso:country": "GB",
    "wof:name": "S43 3BN",
    "wof:placetype": "postalcode"
  },
  "geometry": {"coordinates":[-1.330469,53.271017],"type":"Point"}
}
