{
  "type": "Feature",
  "properties": {
    "date:inception_lower": "1980-01-01",
    "date:inception_upper": "1980-01-01",
    "iso:country": "GB",
    "wof:name": "TW20 0JS",
    "wof:placetype": "postalcode"
  },
  "geometry": {"coordinates":[-0.570041,51.432435],"type":"Point"}
}
