{
  "type": "Feature",
  "properties": {
    "date:inception_lower":"1980-01-01",
    "date:inception_upper":"1980-01-31",
    "iso:country":"GB",
    "wof:name":"TW20 0JS",
    "wof:placetype":"postalcode"
},
  "geometry": {"coordinates":[-0.569366,51.431932],"type":"Point"}
}