{
  "type": "Feature",
  "properties": {
    "iso:country":"GB",
    "wof:name":"TW20 0JS",
    "wof:placetype":"postalcode"
},
  "geometry": {"coordinates":[-0.56969258759651,51.43221420778371],"type":"Point"}
}