{
  "type": "Feature",
  "properties": {
    "iso:country": "GB",
    "wof:name": "TW20 0JS",
    "wof:placetype": "postalcode"
  },
  "geometry": {"coordinates":[-0.569928,51.432379],"type":"Point"}
}
