{
  "type": "Feature",
  "properties": {
    "iso:country":"GB",
    "wof:name":"SP11 7LE",
    "wof:placetype":"postalcode"
},
  "geometry": {"coordinates":[-1.48245953113956,51.16513051956888],"type":"Point"}
}