{
  "type": "Feature",
  "properties": {
    "iso:country":"GB",
    "wof:name":"KA8 9LG",
    "wof:placetype":"postalcode"
},
  "geometry": {"coordinates":[-4.61290815110678,55.47063400396802],"type":"Point"}
}