{
  "type": "Feature",
  "properties": {
    "iso:country": "GB",
    "wof:name": "AL6 9FG",
    "wof:placetype": "postalcode"
  },
  "geometry": {"coordinates":[-0.210162,51.828502],"type":"Point"}
}
