{
  "type": "Feature",
  "properties": {
    "date:inception_lower":"2008-04-01",
    "date:inception_upper":"2008-04-30",
    "iso:country":"GB",
    "wof:name":"AL6 9FG",
    "wof:placetype":"postalcode"
},
  "geometry": {"coordinates":[-0.210162,51.828502],"type":"Point"}
}