{
  "type": "Feature",
  "properties": {
    "iso:country":"GB",
    "wof:name":"AL6 9FG",
    "wof:placetype":"postalcode"
},
  "geometry": {"coordinates":[-0.2101622092611,51.82850198026648],"type":"Point"}
}