{
  "type": "Feature",
  "properties": {
    "iso:country":"GB",
    "wof:name":"PE30 3XX",
    "wof:placetype":"postalcode"
},
  "geometry": {"coordinates":[0.44628258208413,52.76858401245963],"type":"Point"}
}