{
  "type": "Feature",
  "properties": {
    "iso:country":"GB",
    "wof:name":"CM6 3FR",
    "wof:placetype":"postalcode"
},
  "geometry": {"coordinates":[0.41642267947051,51.86209652452239],"type":"Point"}
}