{
  "type": "Feature",
  "properties": {
    "iso:country": "GB",
    "wof:name": "NN6 7BY",
    "wof:placetype": "postalcode"
  },
  "geometry": {"coordinates":[-1.073733,52.342112],"type":"Point"}
}
