{
  "type": "Feature",
  "properties": {
    "date:inception_lower": "1996-06-01",
    "date:inception_upper": "1996-06-01",
    "iso:country": "GB",
    "wof:name": "CT4 5QW",
    "wof:placetype": "postalcode"
  },
  "geometry": {"coordinates":[1.049979,51.235658],"type":"Point"}
}
