{
  "type": "Feature",
  "properties": {
    "iso:country": "GB",
    "wof:name": "M16 9BR",
    "wof:placetype": "postalcode"
  },
  "geometry": {"coordinates":[-2.260686,53.460751],"type":"Point"}
}
