{
  "type": "Feature",
  "properties": {
    "date:inception_lower":"1994-05-01",
    "date:inception_upper":"1994-05-31",
    "iso:country":"GB",
    "wof:name":"M16 9BR",
    "wof:placetype":"postalcode"
},
  "geometry": {"coordinates":[-2.260686,53.460751],"type":"Point"}
}