{
  "type": "Feature",
  "properties": {
    "iso:country":"GB",
    "wof:name":"M6 8LD",
    "wof:placetype":"postalcode"
},
  "geometry": {"coordinates":[-2.32316167667986,53.49461932519333],"type":"Point"}
}