{
  "type": "Feature",
  "properties": {
    "iso:country": "GB",
    "wof:name": "GU32 1PL",
    "wof:placetype": "postalcode"
  },
  "geometry": {"coordinates":[-1.04196,51.02076],"type":"Point"}
}
