{
  "type": "Feature",
  "properties": {
    "iso:country":"GB",
    "wof:name":"GU32 1PL",
    "wof:placetype":"postalcode"
},
  "geometry": {"coordinates":[-1.04196047741252,51.02075961655964],"type":"Point"}
}