{
  "type": "Feature",
  "properties": {
    "date:inception_lower":"1980-01-01",
    "date:inception_upper":"1980-01-31",
    "iso:country":"GB",
    "wof:name":"NE32 4BB",
    "wof:placetype":"postalcode"
},
  "geometry": {"coordinates":[-1.465734,54.96366],"type":"Point"}
}