{
  "type": "Feature",
  "properties": {
    "iso:country":"GB",
    "wof:name":"NE32 4BB",
    "wof:placetype":"postalcode"
},
  "geometry": {"coordinates":[-1.46573383557613,54.96365962019261],"type":"Point"}
}