{
  "type": "Feature",
  "properties": {
    "date:inception_lower": "2010-12-01",
    "date:inception_upper": "2010-12-01",
    "iso:country": "GB",
    "wof:name": "DG9 7TY",
    "wof:placetype": "postalcode"
  },
  "geometry": {"coordinates":[-5.031842,54.90128],"type":"Point"}
}
