{
  "type": "Feature",
  "properties": {
    "iso:country":"GB",
    "wof:name":"BD21 2TA",
    "wof:placetype":"postalcode"
},
  "geometry": {"coordinates":[-1.90901193123912,53.87397097877174],"type":"Point"}
}