{
  "type": "Feature",
  "properties": {
    "iso:country":"GB",
    "wof:name":"OL14 7SJ",
    "wof:placetype":"postalcode"
},
  "geometry": {"coordinates":[-2.10417941127138,53.69140491247791],"type":"Point"}
}