{
  "type": "Feature",
  "properties": {
    "iso:country": "GB",
    "wof:name": "OL14 7SJ",
    "wof:placetype": "postalcode"
  },
  "geometry": {"coordinates":[-2.104179,53.691405],"type":"Point"}
}
