{
  "type": "Feature",
  "properties": {
    "iso:country":"GB",
    "wof:name":"LA23 3NE",
    "wof:placetype":"postalcode"
},
  "geometry": {"coordinates":[-2.91278980658614,54.35423098616462],"type":"Point"}
}