{
  "type": "Feature",
  "properties": {
    "iso:country":"GB",
    "wof:name":"CA7 0HE",
    "wof:placetype":"postalcode"
},
  "geometry": {"coordinates":[-3.12682367057413,54.84692246163273],"type":"Point"}
}