{
  "type": "Feature",
  "properties": {
    "date:inception_lower": "1980-01-01",
    "date:inception_upper": "1980-01-01",
    "iso:country": "GB",
    "wof:name": "CA7 0HE",
    "wof:placetype": "postalcode"
  },
  "geometry": {"coordinates":[-3.126811,54.84692],"type":"Point"}
}
