{
  "type": "Feature",
  "properties": {
    "date:inception_lower": "1980-01-01",
    "date:inception_upper": "1980-01-01",
    "iso:country": "GB",
    "wof:name": "SE19 2QF",
    "wof:placetype": "postalcode"
  },
  "geometry": {"coordinates":[-0.082642,51.41249],"type":"Point"}
}
