{
  "type": "Feature",
  "properties": {
    "iso:country":"GB",
    "wof:name":"SE19 2QF",
    "wof:placetype":"postalcode"
},
  "geometry": {"coordinates":[-0.08379234791464,51.41276919027279],"type":"Point"}
}