{
  "type": "Feature",
  "properties": {
    "iso:country": "GB",
    "wof:name": "FY5 4QD",
    "wof:placetype": "postalcode"
  },
  "geometry": {"coordinates":[-3.000861,53.883097],"type":"Point"}
}
