{
  "type": "Feature",
  "properties": {
    "iso:country":"GB",
    "wof:name":"EH21 8PW",
    "wof:placetype":"postalcode"
},
  "geometry": {"coordinates":[-3.01894471161573,55.91680737390315],"type":"Point"}
}