{
  "type": "Feature",
  "properties": {
    "date:inception_lower": "1999-06-01",
    "date:inception_upper": "1999-06-01",
    "iso:country": "GB",
    "wof:name": "EH21 8PW",
    "wof:placetype": "postalcode"
  },
  "geometry": {"coordinates":[-3.018945,55.916807],"type":"Point"}
}
