{
  "type": "Feature",
  "properties": {
    "iso:country":"GB",
    "wof:name":"CR4 2DW",
    "wof:placetype":"postalcode"
},
  "geometry": {"coordinates":[-0.15550842727565,51.41632090635397],"type":"Point"}
}