{
  "type": "Feature",
  "properties": {
    "date:inception_lower":"1991-09-01",
    "date:inception_upper":"1991-09-30",
    "iso:country":"GB",
    "wof:name":"LN11 8NU",
    "wof:placetype":"postalcode"
},
  "geometry": {"coordinates":[0.062304,53.312052],"type":"Point"}
}