{
  "type": "Feature",
  "properties": {
    "iso:country": "GB",
    "wof:name": "LN11 8NU",
    "wof:placetype": "postalcode"
  },
  "geometry": {"coordinates":[0.062304,53.312052],"type":"Point"}
}
