{
  "type": "Feature",
  "properties": {
    "iso:country":"GB",
    "wof:name":"LN11 8NU",
    "wof:placetype":"postalcode"
},
  "geometry": {"coordinates":[0.06230371713059,53.31205220198892],"type":"Point"}
}