{
  "type": "Feature",
  "properties": {
    "iso:country":"GB",
    "wof:name":"SP5 2RJ",
    "wof:placetype":"postalcode"
},
  "geometry": {"coordinates":[-1.65033892671932,51.01269726135178],"type":"Point"}
}