{
  "type": "Feature",
  "properties": {
    "date:inception_lower":"1980-01-01",
    "date:inception_upper":"1980-01-31",
    "iso:country":"GB",
    "wof:name":"SP5 2RJ",
    "wof:placetype":"postalcode"
},
  "geometry": {"coordinates":[-1.650339,51.012697],"type":"Point"}
}