{
  "type": "Feature",
  "properties": {
    "iso:country": "GB",
    "wof:name": "CF48 1PW",
    "wof:placetype": "postalcode"
  },
  "geometry": {"coordinates":[-3.415038,51.750079],"type":"Point"}
}
