{
  "type": "Feature",
  "properties": {
    "iso:country":"GB",
    "wof:name":"CF48 1PW",
    "wof:placetype":"postalcode"
},
  "geometry": {"coordinates":[-3.41503804660562,51.75007856695882],"type":"Point"}
}