{
  "type": "Feature",
  "properties": {
    "iso:country":"GB",
    "wof:name":"SA17 4PF",
    "wof:placetype":"postalcode"
},
  "geometry": {"coordinates":[-4.28185163788411,51.74933540678303],"type":"Point"}
}