{
  "type": "Feature",
  "properties": {
    "iso:country": "GB",
    "wof:name": "SA17 4PF",
    "wof:placetype": "postalcode"
  },
  "geometry": {"coordinates":[-4.281838,51.749354],"type":"Point"}
}
