{
  "type": "Feature",
  "properties": {
    "date:inception_lower":"1985-10-01",
    "date:inception_upper":"1985-10-31",
    "iso:country":"GB",
    "wof:name":"DL5 4TL",
    "wof:placetype":"postalcode"
},
  "geometry": {"coordinates":[-1.56146,54.631432],"type":"Point"}
}