{
  "type": "Feature",
  "properties": {
    "iso:country":"GB",
    "wof:name":"DL5 4TL",
    "wof:placetype":"postalcode"
},
  "geometry": {"coordinates":[-1.56145965986677,54.63143232151149],"type":"Point"}
}