{
  "type": "Feature",
  "properties": {
    "date:inception_lower": "1997-12-01",
    "date:inception_upper": "1997-12-01",
    "iso:country": "GB",
    "wof:name": "BS40 5RU",
    "wof:placetype": "postalcode"
  },
  "geometry": {"coordinates":[-2.720245,51.357704],"type":"Point"}
}
