{
  "type": "Feature",
  "properties": {
    "iso:country":"GB",
    "wof:name":"BS40 5RU",
    "wof:placetype":"postalcode"
},
  "geometry": {"coordinates":[-2.71860986166232,51.35813040488497],"type":"Point"}
}