{
  "type": "Feature",
  "properties": {
    "iso:country":"GB",
    "wof:name":"NW1 9EE",
    "wof:placetype":"postalcode"
},
  "geometry": {"coordinates":[-0.13780564270191,51.54217055680676],"type":"Point"}
}