{
  "type": "Feature",
  "properties": {
    "iso:country":"GB",
    "wof:name":"RG25 2JB",
    "wof:placetype":"postalcode"
},
  "geometry": {"coordinates":[-1.09845810502196,51.23613336027372],"type":"Point"}
}