{
  "type": "Feature",
  "properties": {
    "iso:country":"GB",
    "wof:name":"EX13 5QD",
    "wof:placetype":"postalcode"
},
  "geometry": {"coordinates":[-2.99758546257656,50.78379121483469],"type":"Point"}
}