{
  "type": "Feature",
  "properties": {
    "iso:country":"GB",
    "wof:name":"TN28 8EU",
    "wof:placetype":"postalcode"
},
  "geometry": {"coordinates":[0.94203445372155,50.98469547764898],"type":"Point"}
}