{
  "type": "Feature",
  "properties": {
    "date:inception_lower": "1985-10-01",
    "date:inception_upper": "1985-10-01",
    "iso:country": "GB",
    "wof:name": "OX3 9DN",
    "wof:placetype": "postalcode"
  },
  "geometry": {"coordinates":[-1.212765,51.763797],"type":"Point"}
}
