{
  "type": "Feature",
  "properties": {
    "iso:country":"GB",
    "wof:name":"OX3 9DN",
    "wof:placetype":"postalcode"
},
  "geometry": {"coordinates":[-1.21276535477236,51.76379668446625],"type":"Point"}
}