{
  "type": "Feature",
  "properties": {
    "date:inception_lower": "1983-01-01",
    "date:inception_upper": "1983-01-01",
    "iso:country": "GB",
    "wof:name": "KT17 1UW",
    "wof:placetype": "postalcode"
  },
  "geometry": {"coordinates":[-0.251279,51.349086],"type":"Point"}
}
