{
  "type": "Feature",
  "properties": {
    "iso:country":"GB",
    "wof:name":"KT17 1UW",
    "wof:placetype":"postalcode"
},
  "geometry": {"coordinates":[-0.25127884592707,51.34908580880538],"type":"Point"}
}