{
  "type": "Feature",
  "properties": {
    "date:inception_lower": "1980-01-01",
    "date:inception_upper": "1980-01-01",
    "iso:country": "GB",
    "wof:name": "YO15 1HL",
    "wof:placetype": "postalcode"
  },
  "geometry": {"coordinates":[-0.178824,54.13033],"type":"Point"}
}
