{
  "type": "Feature",
  "properties": {
    "iso:country":"GB",
    "wof:name":"YO15 1HL",
    "wof:placetype":"postalcode"
},
  "geometry": {"coordinates":[-0.17882450186014,54.13032975913952],"type":"Point"}
}