{
  "type": "Feature",
  "properties": {
    "iso:country":"GB",
    "wof:name":"B11 1LR",
    "wof:placetype":"postalcode"
},
  "geometry": {"coordinates":[-1.87346382982309,52.46373988252261],"type":"Point"}
}