{
  "type": "Feature",
  "properties": {
    "iso:country": "GB",
    "wof:name": "G33 1PR",
    "wof:placetype": "postalcode"
  },
  "geometry": {"coordinates":[-4.181592,55.891917],"type":"Point"}
}
