{
  "type": "Feature",
  "properties": {
    "iso:country": "GB",
    "wof:name": "WA11 0HZ",
    "wof:placetype": "postalcode"
  },
  "geometry": {"coordinates":[-2.682771,53.465762],"type":"Point"}
}
