{
  "type": "Feature",
  "properties": {
    "iso:country":"GB",
    "wof:name":"CR4 4BY",
    "wof:placetype":"postalcode"
},
  "geometry": {"coordinates":[-0.17447631813583,51.39577300857066],"type":"Point"}
}