{
  "type": "Feature",
  "properties": {
    "iso:country":"GB",
    "wof:name":"M24 6FL",
    "wof:placetype":"postalcode"
},
  "geometry": {"coordinates":[-2.19309531704024,53.5610279783705],"type":"Point"}
}