{
  "type": "Feature",
  "properties": {
    "iso:country":"GB",
    "wof:name":"WF2 0HP",
    "wof:placetype":"postalcode"
},
  "geometry": {"coordinates":[-1.51823768928866,53.69637901145143],"type":"Point"}
}