{
  "type": "Feature",
  "properties": {
    "iso:country": "GB",
    "wof:name": "ML6 8PD",
    "wof:placetype": "postalcode"
  },
  "geometry": {"coordinates":[-3.937374,55.861566],"type":"Point"}
}
