{
  "type": "Feature",
  "properties": {
    "date:inception_lower": "1993-02-01",
    "date:inception_upper": "1993-02-01",
    "iso:country": "GB",
    "wof:name": "ML6 8PD",
    "wof:placetype": "postalcode"
  },
  "geometry": {"coordinates":[-3.937374,55.861566],"type":"Point"}
}
