{
  "type": "Feature",
  "properties": {
    "iso:country":"GB",
    "wof:name":"SO30 2AT",
    "wof:placetype":"postalcode"
},
  "geometry": {"coordinates":[-1.30023373404684,50.92502341951105],"type":"Point"}
}