{
  "type": "Feature",
  "properties": {
    "iso:country": "GB",
    "wof:name": "G34 9BL",
    "wof:placetype": "postalcode"
  },
  "geometry": {"coordinates":[-4.123789,55.867836],"type":"Point"}
}
