{
  "type": "Feature",
  "properties": {
    "iso:country":"GB",
    "wof:name":"ME14 5QE",
    "wof:placetype":"postalcode"
},
  "geometry": {"coordinates":[0.55968477627936,51.27374826424248],"type":"Point"}
}