{
  "type": "Feature",
  "properties": {
    "iso:country":"GB",
    "wof:name":"LS10 4PQ",
    "wof:placetype":"postalcode"
},
  "geometry": {"coordinates":[-1.56053373946404,53.75211524666339],"type":"Point"}
}