{
  "type": "Feature",
  "properties": {
    "iso:country":"GB",
    "wof:name":"SW11 5NN",
    "wof:placetype":"postalcode"
},
  "geometry": {"coordinates":[-0.15413319880475,51.46472436087917],"type":"Point"}
}