{
  "type": "Feature",
  "properties": {
    "date:inception_lower": "1980-01-01",
    "date:inception_upper": "1980-01-01",
    "iso:country": "GB",
    "wof:name": "SW11 5NN",
    "wof:placetype": "postalcode"
  },
  "geometry": {"coordinates":[-0.154209,51.464709],"type":"Point"}
}
