{
  "type": "Feature",
  "properties": {
    "iso:country":"GB",
    "wof:name":"RG8 0DN",
    "wof:placetype":"postalcode"
},
  "geometry": {"coordinates":[-1.12865739561862,51.52958698740269],"type":"Point"}
}