{
  "type": "Feature",
  "properties": {
    "iso:country": "GB",
    "wof:name": "EX31 4PT",
    "wof:placetype": "postalcode"
  },
  "geometry": {"coordinates":[-3.926593,51.196312],"type":"Point"}
}
