{
  "type": "Feature",
  "properties": {
    "iso:country":"GB",
    "wof:name":"EX31 4PT",
    "wof:placetype":"postalcode"
},
  "geometry": {"coordinates":[-3.9265930588464,51.19631161756305],"type":"Point"}
}