{
  "type": "Feature",
  "properties": {
    "date:inception_lower": "2012-02-01",
    "date:inception_upper": "2012-02-01",
    "iso:country": "GB",
    "wof:name": "B17 0DA",
    "wof:placetype": "postalcode"
  },
  "geometry": {"coordinates":[-1.946539,52.449093],"type":"Point"}
}
