{
  "type": "Feature",
  "properties": {
    "iso:country":"GB",
    "wof:name":"IG11 0LB",
    "wof:placetype":"postalcode"
},
  "geometry": {"coordinates":[0.10097099433146,51.52779540307304],"type":"Point"}
}