{
  "type": "Feature",
  "properties": {
    "date:inception_lower":"1980-01-01",
    "date:inception_upper":"1980-01-31",
    "iso:country":"GB",
    "wof:name":"IG11 0LB",
    "wof:placetype":"postalcode"
},
  "geometry": {"coordinates":[0.100971,51.527795],"type":"Point"}
}