{
  "type": "Feature",
  "properties": {
    "iso:country": "GB",
    "wof:name": "DY14 9AA",
    "wof:placetype": "postalcode"
  },
  "geometry": {"coordinates":[-2.494488,52.348171],"type":"Point"}
}
