{
  "type": "Feature",
  "properties": {
    "iso:country":"GB",
    "wof:name":"DY14 9AA",
    "wof:placetype":"postalcode"
},
  "geometry": {"coordinates":[-2.49449089378295,52.34815714487281],"type":"Point"}
}