{
  "type": "Feature",
  "properties": {
    "iso:country":"GB",
    "wof:name":"SS1 2QN",
    "wof:placetype":"postalcode"
},
  "geometry": {"coordinates":[0.73663343063029,51.54044148744038],"type":"Point"}
}