{
  "type": "Feature",
  "properties": {
    "iso:country":"GB",
    "wof:name":"LA18 4DX",
    "wof:placetype":"postalcode"
},
  "geometry": {"coordinates":[-3.26228010164057,54.20823593412395],"type":"Point"}
}