{
  "type": "Feature",
  "properties": {
    "iso:country":"GB",
    "wof:name":"BS4 1AP",
    "wof:placetype":"postalcode"
},
  "geometry": {"coordinates":[-2.58045520244023,51.43466091096766],"type":"Point"}
}