{
  "type": "Feature",
  "properties": {
    "iso:country":"GB",
    "wof:name":"E8 4JR",
    "wof:placetype":"postalcode"
},
  "geometry": {"coordinates":[-0.06733508538897,51.53692116889447],"type":"Point"}
}