{
  "type": "Feature",
  "properties": {
    "date:inception_lower": "2017-01-01",
    "date:inception_upper": "2017-01-01",
    "iso:country": "GB",
    "wof:name": "TF2 9YU",
    "wof:placetype": "postalcode"
  },
  "geometry": {"coordinates":[-2.427571,52.681412],"type":"Point"}
}
