{
  "type": "Feature",
  "properties": {
    "iso:country": "GB",
    "wof:name": "CH3 5YF",
    "wof:placetype": "postalcode"
  },
  "geometry": {"coordinates":[-2.856179,53.181502],"type":"Point"}
}
