{
  "type": "Feature",
  "properties": {
    "iso:country":"GB",
    "wof:name":"CH3 5YF",
    "wof:placetype":"postalcode"
},
  "geometry": {"coordinates":[-2.85617863174403,53.18150165128287],"type":"Point"}
}