{
  "type": "Feature",
  "properties": {
    "iso:country":"GB",
    "wof:name":"TN24 0UN",
    "wof:placetype":"postalcode"
},
  "geometry": {"coordinates":[0.90726958491211,51.13575776664054],"type":"Point"}
}