{
  "type": "Feature",
  "properties": {
    "iso:country": "GB",
    "wof:name": "TN24 0UN",
    "wof:placetype": "postalcode"
  },
  "geometry": {"coordinates":[0.90727,51.135758],"type":"Point"}
}
