{
  "type": "Feature",
  "properties": {
    "iso:country":"GB",
    "wof:name":"MK9 2DS",
    "wof:placetype":"postalcode"
},
  "geometry": {"coordinates":[-0.7666889497013,52.04145564797101],"type":"Point"}
}