{
  "type": "Feature",
  "properties": {
    "iso:country":"GB",
    "wof:name":"SW5 0TG",
    "wof:placetype":"postalcode"
},
  "geometry": {"coordinates":[-0.19084527539492,51.49418949142223],"type":"Point"}
}