{
  "type": "Feature",
  "properties": {
    "date:inception_lower":"1980-01-01",
    "date:inception_upper":"1980-01-31",
    "iso:country":"GB",
    "wof:name":"KA11 2AZ",
    "wof:placetype":"postalcode"
},
  "geometry": {"coordinates":[-4.616694,55.62977],"type":"Point"}
}