{
  "type": "Feature",
  "properties": {
    "iso:country":"GB",
    "wof:name":"KA11 2AZ",
    "wof:placetype":"postalcode"
},
  "geometry": {"coordinates":[-4.61669432589608,55.62977014487871],"type":"Point"}
}