{
  "type": "Feature",
  "properties": {
    "iso:country":"GB",
    "wof:name":"SP5 2QB",
    "wof:placetype":"postalcode"
},
  "geometry": {"coordinates":[-1.71799257159653,50.97961757840594],"type":"Point"}
}