{
  "type": "Feature",
  "properties": {
    "date:inception_lower": "1997-06-01",
    "date:inception_upper": "1997-06-01",
    "iso:country": "GB",
    "wof:name": "SP5 2QB",
    "wof:placetype": "postalcode"
  },
  "geometry": {"coordinates":[-1.717993,50.979618],"type":"Point"}
}
