{
  "type": "Feature",
  "properties": {
    "date:inception_lower": "1994-12-01",
    "date:inception_upper": "1994-12-01",
    "iso:country": "GB",
    "wof:name": "PE19 1AG",
    "wof:placetype": "postalcode"
  },
  "geometry": {"coordinates":[-0.267116,52.228966],"type":"Point"}
}
