{
  "type": "Feature",
  "properties": {
    "iso:country":"GB",
    "wof:name":"PE19 1AG",
    "wof:placetype":"postalcode"
},
  "geometry": {"coordinates":[-0.26713788862323,52.22895296310714],"type":"Point"}
}