{
  "type": "Feature",
  "properties": {
    "iso:country": "GB",
    "wof:name": "OX1 5PR",
    "wof:placetype": "postalcode"
  },
  "geometry": {"coordinates":[-1.243723,51.712219],"type":"Point"}
}
