{
  "type": "Feature",
  "properties": {
    "iso:country":"GB",
    "wof:name":"WD23 3LU",
    "wof:placetype":"postalcode"
},
  "geometry": {"coordinates":[-0.35994490342403,51.6448314394246],"type":"Point"}
}