{
  "type": "Feature",
  "properties": {
    "iso:country": "GB",
    "wof:name": "WD23 3LU",
    "wof:placetype": "postalcode"
  },
  "geometry": {"coordinates":[-0.359945,51.644831],"type":"Point"}
}
