{
  "type": "Feature",
  "properties": {
    "iso:country": "GB",
    "wof:name": "CT17 9SE",
    "wof:placetype": "postalcode"
  },
  "geometry": {"coordinates":[1.304037,51.125321],"type":"Point"}
}
