{
  "type": "Feature",
  "properties": {
    "iso:country":"GB",
    "wof:name":"B23 7YA",
    "wof:placetype":"postalcode"
},
  "geometry": {"coordinates":[-1.86961985744779,52.51944641270117],"type":"Point"}
}