{
  "type": "Feature",
  "properties": {
    "date:inception_lower": "1980-01-01",
    "date:inception_upper": "1980-01-01",
    "iso:country": "GB",
    "wof:name": "B23 7YA",
    "wof:placetype": "postalcode"
  },
  "geometry": {"coordinates":[-1.86962,52.519446],"type":"Point"}
}
