{
  "type": "Feature",
  "properties": {
    "iso:country": "GB",
    "wof:name": "G75 8RL",
    "wof:placetype": "postalcode"
  },
  "geometry": {"coordinates":[-4.226486,55.751394],"type":"Point"}
}
