{
  "type": "Feature",
  "properties": {
    "date:inception_lower":"2015-11-01",
    "date:inception_upper":"2015-11-30",
    "iso:country":"GB",
    "wof:name":"BD1 5AY",
    "wof:placetype":"postalcode"
},
  "geometry": {"coordinates":[-1.746977,53.792317],"type":"Point"}
}