{
  "type": "Feature",
  "properties": {
    "iso:country":"GB",
    "wof:name":"LU7 9EN",
    "wof:placetype":"postalcode"
},
  "geometry": {"coordinates":[-0.62557062007175,51.82796668002042],"type":"Point"}
}