{
  "type": "Feature",
  "properties": {
    "iso:country": "GB",
    "wof:name": "LU7 9EN",
    "wof:placetype": "postalcode"
  },
  "geometry": {"coordinates":[-0.625571,51.827967],"type":"Point"}
}
