{
  "type": "Feature",
  "properties": {
    "date:inception_lower": "2007-09-01",
    "date:inception_upper": "2007-09-01",
    "iso:country": "GB",
    "wof:name": "IP25 6GY",
    "wof:placetype": "postalcode"
  },
  "geometry": {"coordinates":[0.854091,52.568537],"type":"Point"}
}
