{
  "type": "Feature",
  "properties": {
    "date:inception_lower":"1992-08-01",
    "date:inception_upper":"1992-08-31",
    "iso:country":"GB",
    "wof:name":"NR30 1HU",
    "wof:placetype":"postalcode"
},
  "geometry": {"coordinates":[1.722635,52.608046],"type":"Point"}
}