{
  "type": "Feature",
  "properties": {
    "iso:country": "GB",
    "wof:name": "NR30 1HU",
    "wof:placetype": "postalcode"
  },
  "geometry": {"coordinates":[1.722635,52.608046],"type":"Point"}
}
