{
  "type": "Feature",
  "properties": {
    "date:inception_lower": "1995-12-01",
    "date:inception_upper": "1995-12-01",
    "iso:country": "GB",
    "wof:name": "NN4 6AX",
    "wof:placetype": "postalcode"
  },
  "geometry": {"coordinates":[-0.878319,52.206017],"type":"Point"}
}
