{
  "type": "Feature",
  "properties": {
    "iso:country": "GB",
    "wof:name": "NN4 6AX",
    "wof:placetype": "postalcode"
  },
  "geometry": {"coordinates":[-0.878319,52.206017],"type":"Point"}
}
