{
  "type": "Feature",
  "properties": {
    "iso:country":"GB",
    "wof:name":"NN4 6AX",
    "wof:placetype":"postalcode"
},
  "geometry": {"coordinates":[-0.87831872261397,52.20601699318833],"type":"Point"}
}