{
  "type": "Feature",
  "properties": {
    "iso:country":"GB",
    "wof:name":"HR4 8AY",
    "wof:placetype":"postalcode"
},
  "geometry": {"coordinates":[-2.74298522677042,52.13063351712002],"type":"Point"}
}