{
  "type": "Feature",
  "properties": {
    "iso:country":"GB",
    "wof:name":"FY8 1NZ",
    "wof:placetype":"postalcode"
},
  "geometry": {"coordinates":[-3.02770799832814,53.74698383756123],"type":"Point"}
}