{
  "type": "Feature",
  "properties": {
    "date:inception_lower": "1990-07-01",
    "date:inception_upper": "1990-07-01",
    "iso:country": "GB",
    "wof:name": "FY8 1NZ",
    "wof:placetype": "postalcode"
  },
  "geometry": {"coordinates":[-3.027708,53.746984],"type":"Point"}
}
