{
  "type": "Feature",
  "properties": {
    "iso:country":"GB",
    "wof:name":"NW5 1DD",
    "wof:placetype":"postalcode"
},
  "geometry": {"coordinates":[-0.1407956480286,51.55903387000952],"type":"Point"}
}