{
  "type": "Feature",
  "properties": {
    "iso:country":"GB",
    "wof:name":"LL19 8AF",
    "wof:placetype":"postalcode"
},
  "geometry": {"coordinates":[-3.42625518599758,53.33078531221469],"type":"Point"}
}