{
  "type": "Feature",
  "properties": {
    "iso:country":"GB",
    "wof:name":"DN14 7SE",
    "wof:placetype":"postalcode"
},
  "geometry": {"coordinates":[-0.88042794687104,53.73560406938927],"type":"Point"}
}