{
  "type": "Feature",
  "properties": {
    "date:inception_lower": "2008-07-01",
    "date:inception_upper": "2008-07-01",
    "iso:country": "GB",
    "wof:name": "DN14 7SE",
    "wof:placetype": "postalcode"
  },
  "geometry": {"coordinates":[-0.882036,53.736889],"type":"Point"}
}
