{
  "type": "Feature",
  "properties": {
    "iso:country": "GB",
    "wof:name": "CO6 3AW",
    "wof:placetype": "postalcode"
  },
  "geometry": {"coordinates":[0.821739,51.949172],"type":"Point"}
}
