{
  "type": "Feature",
  "properties": {
    "date:inception_lower": "1980-01-01",
    "date:inception_upper": "1980-01-01",
    "iso:country": "GB",
    "wof:name": "CO6 3AW",
    "wof:placetype": "postalcode"
  },
  "geometry": {"coordinates":[0.821739,51.949172],"type":"Point"}
}
