{
  "type": "Feature",
  "properties": {
    "iso:country":"GB",
    "wof:name":"CO6 3AW",
    "wof:placetype":"postalcode"
},
  "geometry": {"coordinates":[0.82173930296787,51.94917226044838],"type":"Point"}
}