{
  "type": "Feature",
  "properties": {
    "date:inception_lower": "1980-01-01",
    "date:inception_upper": "1980-01-01",
    "iso:country": "GB",
    "wof:name": "B92 7HX",
    "wof:placetype": "postalcode"
  },
  "geometry": {"coordinates":[-1.811954,52.441737],"type":"Point"}
}
