{
  "type": "Feature",
  "properties": {
    "iso:country":"GB",
    "wof:name":"LS25 6EZ",
    "wof:placetype":"postalcode"
},
  "geometry": {"coordinates":[-1.2290069871877,53.80147722850856],"type":"Point"}
}