{
  "type": "Feature",
  "properties": {
    "iso:country": "GB",
    "wof:name": "SO19 9RT",
    "wof:placetype": "postalcode"
  },
  "geometry": {"coordinates":[-1.356974,50.888966],"type":"Point"}
}
