{
  "type": "Feature",
  "properties": {
    "iso:country": "GB",
    "wof:name": "SK9 7JP",
    "wof:placetype": "postalcode"
  },
  "geometry": {"coordinates":[-2.236121,53.303572],"type":"Point"}
}
