{
  "type": "Feature",
  "properties": {
    "date:inception_lower":"1993-01-01",
    "date:inception_upper":"1993-01-31",
    "iso:country":"GB",
    "wof:name":"SK9 7JP",
    "wof:placetype":"postalcode"
},
  "geometry": {"coordinates":[-2.236121,53.303572],"type":"Point"}
}