{
  "type": "Feature",
  "properties": {
    "date:inception_lower": "1980-01-01",
    "date:inception_upper": "1980-01-01",
    "iso:country": "GB",
    "wof:name": "TR8 5HZ",
    "wof:placetype": "postalcode"
  },
  "geometry": {"coordinates":[-5.038827,50.367783],"type":"Point"}
}
