{
  "type": "Feature",
  "properties": {
    "date:inception_lower": "2024-03-01",
    "date:inception_upper": "2024-03-01",
    "iso:country": "GB",
    "wof:name": "BS16 1YX",
    "wof:placetype": "postalcode"
  },
  "geometry": {"coordinates":[-2.519567,51.501061],"type":"Point"}
}
