{
  "type": "Feature",
  "properties": {
    "iso:country": "GB",
    "wof:name": "SO50 6JP",
    "wof:placetype": "postalcode"
  },
  "geometry": {"coordinates":[-1.301038,50.922825],"type":"Point"}
}
