{
  "type": "Feature",
  "properties": {
    "iso:country":"GB",
    "wof:name":"CV23 8DU",
    "wof:placetype":"postalcode"
},
  "geometry": {"coordinates":[-1.28241257406944,52.29805406549217],"type":"Point"}
}