{
  "type": "Feature",
  "properties": {
    "date:inception_lower": "1997-12-01",
    "date:inception_upper": "1997-12-01",
    "iso:country": "GB",
    "wof:name": "CV23 8DU",
    "wof:placetype": "postalcode"
  },
  "geometry": {"coordinates":[-1.282413,52.298054],"type":"Point"}
}
