{
  "type": "Feature",
  "properties": {
    "iso:country":"GB",
    "wof:name":"B21 0BJ",
    "wof:placetype":"postalcode"
},
  "geometry": {"coordinates":[-1.96089853419984,52.50735720578259],"type":"Point"}
}