{
  "type": "Feature",
  "properties": {
    "iso:country":"GB",
    "wof:name":"TN13 1HE",
    "wof:placetype":"postalcode"
},
  "geometry": {"coordinates":[0.18757298723481,51.27286844705554],"type":"Point"}
}