{
  "type": "Feature",
  "properties": {
    "iso:country": "GB",
    "wof:name": "HU14 3RD",
    "wof:placetype": "postalcode"
  },
  "geometry": {"coordinates":[-0.490972,53.741464],"type":"Point"}
}
