{
  "type": "Feature",
  "properties": {
    "iso:country": "GB",
    "wof:name": "SN16 0FP",
    "wof:placetype": "postalcode"
  },
  "geometry": {"coordinates":[-2.221099,51.577983],"type":"Point"}
}
