{
  "type": "Feature",
  "properties": {
    "iso:country":"GB",
    "wof:name":"BD6 1EQ",
    "wof:placetype":"postalcode"
},
  "geometry": {"coordinates":[-1.7693897471493,53.76055407943768],"type":"Point"}
}