{
  "type": "Feature",
  "properties": {
    "iso:country":"GB",
    "wof:name":"NP19 9PF",
    "wof:placetype":"postalcode"
},
  "geometry": {"coordinates":[-2.93996439597579,51.58685147388648],"type":"Point"}
}