{
  "type": "Feature",
  "properties": {
    "iso:country": "GB",
    "wof:name": "NP19 9PF",
    "wof:placetype": "postalcode"
  },
  "geometry": {"coordinates":[-2.939964,51.586851],"type":"Point"}
}
