{
  "type": "Feature",
  "properties": {
    "date:inception_lower": "1986-04-01",
    "date:inception_upper": "1986-04-01",
    "iso:country": "GB",
    "wof:name": "NP44 5EG",
    "wof:placetype": "postalcode"
  },
  "geometry": {"coordinates":[-3.056288,51.651501],"type":"Point"}
}
