{
  "type": "Feature",
  "properties": {
    "iso:country":"GB",
    "wof:name":"NP44 5EG",
    "wof:placetype":"postalcode"
},
  "geometry": {"coordinates":[-3.05628803406922,51.65150089248846],"type":"Point"}
}