{
  "type": "Feature",
  "properties": {
    "iso:country":"GB",
    "wof:name":"PH11 8DN",
    "wof:placetype":"postalcode"
},
  "geometry": {"coordinates":[-3.23372901910978,56.62540985647127],"type":"Point"}
}