{
  "type": "Feature",
  "properties": {
    "iso:country":"GB",
    "wof:name":"HP19 0XT",
    "wof:placetype":"postalcode"
},
  "geometry": {"coordinates":[-0.80263075208365,51.82936279231435],"type":"Point"}
}