{
  "type": "Feature",
  "properties": {
    "iso:country": "GB",
    "wof:name": "HP19 0XT",
    "wof:placetype": "postalcode"
  },
  "geometry": {"coordinates":[-0.802631,51.829363],"type":"Point"}
}
