{
  "type": "Feature",
  "properties": {
    "iso:country":"GB",
    "wof:name":"HA6 3AE",
    "wof:placetype":"postalcode"
},
  "geometry": {"coordinates":[-0.42495425691778,51.61192030121802],"type":"Point"}
}