{
  "type": "Feature",
  "properties": {
    "date:inception_lower": "1980-01-01",
    "date:inception_upper": "1980-01-01",
    "iso:country": "GB",
    "wof:name": "BS5 7NF",
    "wof:placetype": "postalcode"
  },
  "geometry": {"coordinates":[-2.530077,51.460831],"type":"Point"}
}
