{
  "type": "Feature",
  "properties": {
    "date:inception_lower": "1984-10-01",
    "date:inception_upper": "1984-10-01",
    "iso:country": "GB",
    "wof:name": "SA2 8EG",
    "wof:placetype": "postalcode"
  },
  "geometry": {"coordinates":[-4.002312,51.601822],"type":"Point"}
}
