{
  "type": "Feature",
  "properties": {
    "iso:country":"GB",
    "wof:name":"SA2 8EG",
    "wof:placetype":"postalcode"
},
  "geometry": {"coordinates":[-4.00231185719414,51.60182160776439],"type":"Point"}
}