{
  "type": "Feature",
  "properties": {
    "iso:country":"GB",
    "wof:name":"SS9 2SH",
    "wof:placetype":"postalcode"
},
  "geometry": {"coordinates":[0.63484874477122,51.54833966879998],"type":"Point"}
}