{
  "type": "Feature",
  "properties": {
    "iso:country": "GB",
    "wof:name": "SS9 2SH",
    "wof:placetype": "postalcode"
  },
  "geometry": {"coordinates":[0.634849,51.54834],"type":"Point"}
}
