{
  "type": "Feature",
  "properties": {
    "iso:country": "GB",
    "wof:name": "LE2 9UP",
    "wof:placetype": "postalcode"
  },
  "geometry": {"coordinates":[-1.147958,52.580301],"type":"Point"}
}
