{
  "type": "Feature",
  "properties": {
    "iso:country":"GB",
    "wof:name":"LE2 9UP",
    "wof:placetype":"postalcode"
},
  "geometry": {"coordinates":[-1.14795809615164,52.58030065708201],"type":"Point"}
}