{
  "type": "Feature",
  "properties": {
    "iso:country":"GB",
    "wof:name":"EN5 2EF",
    "wof:placetype":"postalcode"
},
  "geometry": {"coordinates":[-0.19413669855508,51.64731726874714],"type":"Point"}
}