{
  "type": "Feature",
  "properties": {
    "date:inception_lower":"1980-01-01",
    "date:inception_upper":"1980-01-31",
    "iso:country":"GB",
    "wof:name":"EN5 2EF",
    "wof:placetype":"postalcode"
},
  "geometry": {"coordinates":[-0.194137,51.647317],"type":"Point"}
}