{
  "type": "Feature",
  "properties": {
    "iso:country":"GB",
    "wof:name":"KT2 5PB",
    "wof:placetype":"postalcode"
},
  "geometry": {"coordinates":[-0.29390284010426,51.4266812935231],"type":"Point"}
}