{
  "type": "Feature",
  "properties": {
    "date:inception_lower": "2004-10-01",
    "date:inception_upper": "2004-10-01",
    "iso:country": "GB",
    "wof:name": "KT2 5PB",
    "wof:placetype": "postalcode"
  },
  "geometry": {"coordinates":[-0.293581,51.426605],"type":"Point"}
}
