{
  "type": "Feature",
  "properties": {
    "iso:country": "GB",
    "wof:name": "SY22 6XJ",
    "wof:placetype": "postalcode"
  },
  "geometry": {"coordinates":[-3.20687,52.77317],"type":"Point"}
}
