{
  "type": "Feature",
  "properties": {
    "iso:country": "GB",
    "wof:name": "LE15 6QA",
    "wof:placetype": "postalcode"
  },
  "geometry": {"coordinates":[-0.725179,52.678302],"type":"Point"}
}
