{
  "type": "Feature",
  "properties": {
    "date:inception_lower":"1993-01-01",
    "date:inception_upper":"1993-01-31",
    "iso:country":"GB",
    "wof:name":"LE15 6QA",
    "wof:placetype":"postalcode"
},
  "geometry": {"coordinates":[-0.725179,52.678302],"type":"Point"}
}