{
  "type": "Feature",
  "properties": {
    "iso:country":"GB",
    "wof:name":"LE15 6QA",
    "wof:placetype":"postalcode"
},
  "geometry": {"coordinates":[-0.72517936793416,52.67830210408707],"type":"Point"}
}