{
  "type": "Feature",
  "properties": {
    "date:inception_lower": "1980-01-01",
    "date:inception_upper": "1980-01-01",
    "iso:country": "GB",
    "wof:name": "PE14 7JF",
    "wof:placetype": "postalcode"
  },
  "geometry": {"coordinates":[0.196033,52.732113],"type":"Point"}
}
