{
  "type": "Feature",
  "properties": {
    "iso:country":"GB",
    "wof:name":"PE14 7JF",
    "wof:placetype":"postalcode"
},
  "geometry": {"coordinates":[0.19603290440042,52.73211287358922],"type":"Point"}
}