{
  "type": "Feature",
  "properties": {
    "iso:country":"GB",
    "wof:name":"SW20 0PJ",
    "wof:placetype":"postalcode"
},
  "geometry": {"coordinates":[-0.23976158306456,51.41314731090421],"type":"Point"}
}