{
  "type": "Feature",
  "properties": {
    "iso:country":"GB",
    "wof:name":"B47 5PP",
    "wof:placetype":"postalcode"
},
  "geometry": {"coordinates":[-1.88012157305176,52.3967350512583],"type":"Point"}
}