{
  "type": "Feature",
  "properties": {
    "iso:country": "GB",
    "wof:name": "B47 5PP",
    "wof:placetype": "postalcode"
  },
  "geometry": {"coordinates":[-1.880276,52.396776],"type":"Point"}
}
