{
  "type": "Feature",
  "properties": {
    "iso:country":"GB",
    "wof:name":"SW15 3DB",
    "wof:placetype":"postalcode"
},
  "geometry": {"coordinates":[-0.22826058502546,51.45322453041347],"type":"Point"}
}