{
  "type": "Feature",
  "properties": {
    "iso:country":"GB",
    "wof:name":"SW3 5DB",
    "wof:placetype":"postalcode"
},
  "geometry": {"coordinates":[-0.17252600149734,51.48541652702244],"type":"Point"}
}