{
  "type": "Feature",
  "properties": {
    "iso:country":"GB",
    "wof:name":"BR6 8JY",
    "wof:placetype":"postalcode"
},
  "geometry": {"coordinates":[0.06314256597136,51.37300773698931],"type":"Point"}
}