{
  "type": "Feature",
  "properties": {
    "iso:country":"GB",
    "wof:name":"LA5 9JX",
    "wof:placetype":"postalcode"
},
  "geometry": {"coordinates":[-2.7686471052287,54.12890201573227],"type":"Point"}
}