{
  "type": "Feature",
  "properties": {
    "date:inception_lower": "1980-01-01",
    "date:inception_upper": "1980-01-01",
    "iso:country": "GB",
    "wof:name": "LA5 9JX",
    "wof:placetype": "postalcode"
  },
  "geometry": {"coordinates":[-2.768647,54.128902],"type":"Point"}
}
