{
  "type": "Feature",
  "properties": {
    "iso:country":"GB",
    "wof:name":"SY2 6BU",
    "wof:placetype":"postalcode"
},
  "geometry": {"coordinates":[-2.74488427002364,52.70804698284058],"type":"Point"}
}