{
  "type": "Feature",
  "properties": {
    "iso:country": "GB",
    "wof:name": "SY2 6BU",
    "wof:placetype": "postalcode"
  },
  "geometry": {"coordinates":[-2.744884,52.708047],"type":"Point"}
}
