{
  "type": "Feature",
  "properties": {
    "iso:country": "GB",
    "wof:name": "WS11 0XL",
    "wof:placetype": "postalcode"
  },
  "geometry": {"coordinates":[-2.030358,52.67509],"type":"Point"}
}
