{
  "type": "Feature",
  "properties": {
    "iso:country": "GB",
    "wof:name": "WS9 8RW",
    "wof:placetype": "postalcode"
  },
  "geometry": {"coordinates":[-1.913245,52.61539],"type":"Point"}
}
