{
  "type": "Feature",
  "properties": {
    "iso:country":"GB",
    "wof:name":"W1T 5LJ",
    "wof:placetype":"postalcode"
},
  "geometry": {"coordinates":[-0.13882260737868,51.52395893574926],"type":"Point"}
}