{
  "type": "Feature",
  "properties": {
    "date:inception_lower":"1995-01-01",
    "date:inception_upper":"1995-01-31",
    "iso:country":"GB",
    "wof:name":"BN7 1ED",
    "wof:placetype":"postalcode"
},
  "geometry": {"coordinates":[-0.006308,50.871302],"type":"Point"}
}