{
  "type": "Feature",
  "properties": {
    "iso:country":"GB",
    "wof:name":"BN7 1ED",
    "wof:placetype":"postalcode"
},
  "geometry": {"coordinates":[-0.0063076499127,50.87130171276641],"type":"Point"}
}