{
  "type": "Feature",
  "properties": {
    "date:inception_lower": "1985-10-01",
    "date:inception_upper": "1985-10-01",
    "iso:country": "GB",
    "wof:name": "L28 6YW",
    "wof:placetype": "postalcode"
  },
  "geometry": {"coordinates":[-2.860019,53.431341],"type":"Point"}
}
