{
  "type": "Feature",
  "properties": {
    "iso:country":"GB",
    "wof:name":"LD3 0BX",
    "wof:placetype":"postalcode"
},
  "geometry": {"coordinates":[-3.26036871441281,52.04666630408742],"type":"Point"}
}