{
  "type": "Feature",
  "properties": {
    "date:inception_lower": "2015-11-01",
    "date:inception_upper": "2015-11-01",
    "iso:country": "GB",
    "wof:name": "SW19 3ES",
    "wof:placetype": "postalcode"
  },
  "geometry": {"coordinates":[-0.203862,51.417809],"type":"Point"}
}
