{
  "type": "Feature",
  "properties": {
    "iso:country":"GB",
    "wof:name":"SW19 3ES",
    "wof:placetype":"postalcode"
},
  "geometry": {"coordinates":[-0.20421840910282,51.41778780305269],"type":"Point"}
}