{
  "type": "Feature",
  "properties": {
    "iso:country": "GB",
    "wof:name": "PL10 1HJ",
    "wof:placetype": "postalcode"
  },
  "geometry": {"coordinates":[-4.216911,50.349174],"type":"Point"}
}
