{
  "type": "Feature",
  "properties": {
    "date:inception_lower": "1987-04-01",
    "date:inception_upper": "1987-04-01",
    "iso:country": "GB",
    "wof:name": "PL10 1HJ",
    "wof:placetype": "postalcode"
  },
  "geometry": {"coordinates":[-4.216911,50.349174],"type":"Point"}
}
