{
  "type": "Feature",
  "properties": {
    "iso:country": "GB",
    "wof:name": "EH48 2DH",
    "wof:placetype": "postalcode"
  },
  "geometry": {"coordinates":[-3.662092,55.896173],"type":"Point"}
}
