{
  "type": "Feature",
  "properties": {
    "iso:country":"GB",
    "wof:name":"EH48 2DH",
    "wof:placetype":"postalcode"
},
  "geometry": {"coordinates":[-3.66209155898086,55.89617344724696],"type":"Point"}
}