{
  "type": "Feature",
  "properties": {
    "iso:country":"GB",
    "wof:name":"AL7 2QJ",
    "wof:placetype":"postalcode"
},
  "geometry": {"coordinates":[-0.15978539099987,51.80153957575315],"type":"Point"}
}