{
  "type": "Feature",
  "properties": {
    "date:inception_lower": "1980-01-01",
    "date:inception_upper": "1980-01-01",
    "iso:country": "GB",
    "wof:name": "WF7 6HQ",
    "wof:placetype": "postalcode"
  },
  "geometry": {"coordinates":[-1.376253,53.689963],"type":"Point"}
}
