{
  "type": "Feature",
  "properties": {
    "date:inception_lower": "2005-03-01",
    "date:inception_upper": "2005-03-01",
    "iso:country": "GB",
    "wof:name": "CO7 9DQ",
    "wof:placetype": "postalcode"
  },
  "geometry": {"coordinates":[0.960773,51.854353],"type":"Point"}
}
