{
  "type": "Feature",
  "properties": {
    "iso:country":"GB",
    "wof:name":"CO7 9DQ",
    "wof:placetype":"postalcode"
},
  "geometry": {"coordinates":[0.96077317672325,51.85435261305843],"type":"Point"}
}