{
  "type": "Feature",
  "properties": {
    "iso:country":"GB",
    "wof:name":"HP6 5RG",
    "wof:placetype":"postalcode"
},
  "geometry": {"coordinates":[-0.62292124486421,51.68962583625537],"type":"Point"}
}