{
  "type": "Feature",
  "properties": {
    "iso:country":"GB",
    "wof:name":"B28 9DT",
    "wof:placetype":"postalcode"
},
  "geometry": {"coordinates":[-1.83808715815425,52.42966062370938],"type":"Point"}
}