{
  "type": "Feature",
  "properties": {
    "iso:country": "GB",
    "wof:name": "CT1 2TN",
    "wof:placetype": "postalcode"
  },
  "geometry": {"coordinates":[1.080218,51.276255],"type":"Point"}
}
