{
  "type": "Feature",
  "properties": {
    "date:inception_lower": "2005-07-01",
    "date:inception_upper": "2005-07-01",
    "iso:country": "GB",
    "wof:name": "CT1 2TN",
    "wof:placetype": "postalcode"
  },
  "geometry": {"coordinates":[1.079766,51.276564],"type":"Point"}
}
