{
  "type": "Feature",
  "properties": {
    "iso:country":"GB",
    "wof:name":"CT1 2TN",
    "wof:placetype":"postalcode"
},
  "geometry": {"coordinates":[1.08018814542197,51.27625079886048],"type":"Point"}
}