{
  "type": "Feature",
  "properties": {
    "date:inception_lower":"1999-06-01",
    "date:inception_upper":"1999-06-30",
    "iso:country":"GB",
    "wof:name":"NP20 2AL",
    "wof:placetype":"postalcode"
},
  "geometry": {"coordinates":[-2.987845,51.583644],"type":"Point"}
}