{
  "type": "Feature",
  "properties": {
    "iso:country": "GB",
    "wof:name": "CH61 0HG",
    "wof:placetype": "postalcode"
  },
  "geometry": {"coordinates":[-3.129451,53.353948],"type":"Point"}
}
