{
  "type": "Feature",
  "properties": {
    "iso:country":"GB",
    "wof:name":"DL2 2TG",
    "wof:placetype":"postalcode"
},
  "geometry": {"coordinates":[-1.5960169975161,54.4751175975949],"type":"Point"}
}