{
  "type": "Feature",
  "properties": {
    "iso:country":"GB",
    "wof:name":"TS26 9JZ",
    "wof:placetype":"postalcode"
},
  "geometry": {"coordinates":[-1.21909800451581,54.67986556737391],"type":"Point"}
}