{
  "type": "Feature",
  "properties": {
    "date:inception_lower":"2005-08-01",
    "date:inception_upper":"2005-08-31",
    "iso:country":"GB",
    "wof:name":"TS26 9JZ",
    "wof:placetype":"postalcode"
},
  "geometry": {"coordinates":[-1.219098,54.679866],"type":"Point"}
}