{
  "type": "Feature",
  "properties": {
    "iso:country": "GB",
    "wof:name": "TS26 9JZ",
    "wof:placetype": "postalcode"
  },
  "geometry": {"coordinates":[-1.219098,54.679866],"type":"Point"}
}
