{
  "type": "Feature",
  "properties": {
    "date:inception_lower": "1980-01-01",
    "date:inception_upper": "1980-01-01",
    "iso:country": "GB",
    "wof:name": "B28 0TL",
    "wof:placetype": "postalcode"
  },
  "geometry": {"coordinates":[-1.843692,52.412695],"type":"Point"}
}
