{
  "type": "Feature",
  "properties": {
    "iso:country":"GB",
    "wof:name":"B28 0TL",
    "wof:placetype":"postalcode"
},
  "geometry": {"coordinates":[-1.84369172926103,52.41269492538482],"type":"Point"}
}