{
  "type": "Feature",
  "properties": {
    "date:inception_lower": "1980-01-01",
    "date:inception_upper": "1980-01-01",
    "iso:country": "GB",
    "wof:name": "PR7 2SW",
    "wof:placetype": "postalcode"
  },
  "geometry": {"coordinates":[-2.632214,53.652927],"type":"Point"}
}
