{
  "type": "Feature",
  "properties": {
    "iso:country": "GB",
    "wof:name": "LL58 8PA",
    "wof:placetype": "postalcode"
  },
  "geometry": {"coordinates":[-4.096617,53.2992],"type":"Point"}
}
