{
  "type": "Feature",
  "properties": {
    "iso:country":"GB",
    "wof:name":"LL58 8PA",
    "wof:placetype":"postalcode"
},
  "geometry": {"coordinates":[-4.09661690853929,53.29919973002035],"type":"Point"}
}