{
  "type": "Feature",
  "properties": {
    "date:inception_lower": "1980-01-01",
    "date:inception_upper": "1980-01-01",
    "iso:country": "GB",
    "wof:name": "LL58 8PA",
    "wof:placetype": "postalcode"
  },
  "geometry": {"coordinates":[-4.096617,53.2992],"type":"Point"}
}
