{
  "type": "Feature",
  "properties": {
    "iso:country":"GB",
    "wof:name":"E1 2NP",
    "wof:placetype":"postalcode"
},
  "geometry": {"coordinates":[-0.05732780338977,51.51219710967177],"type":"Point"}
}