{
  "type": "Feature",
  "properties": {
    "date:inception_lower":"1980-01-01",
    "date:inception_upper":"1980-01-31",
    "iso:country":"GB",
    "wof:name":"E1 2NP",
    "wof:placetype":"postalcode"
},
  "geometry": {"coordinates":[-0.057328,51.512197],"type":"Point"}
}