{
  "type": "Feature",
  "properties": {
    "date:inception_lower": "1990-02-01",
    "date:inception_upper": "1990-02-01",
    "iso:country": "GB",
    "wof:name": "CH3 8JW",
    "wof:placetype": "postalcode"
  },
  "geometry": {"coordinates":[-2.763436,53.198483],"type":"Point"}
}
