{
  "type": "Feature",
  "properties": {
    "iso:country": "GB",
    "wof:name": "CH3 8JW",
    "wof:placetype": "postalcode"
  },
  "geometry": {"coordinates":[-2.763436,53.198483],"type":"Point"}
}
