{
  "type": "Feature",
  "properties": {
    "date:inception_lower": "2003-03-01",
    "date:inception_upper": "2003-03-01",
    "iso:country": "GB",
    "wof:name": "L15 2HE",
    "wof:placetype": "postalcode"
  },
  "geometry": {"coordinates":[-2.936659,53.39158],"type":"Point"}
}
