{
  "type": "Feature",
  "properties": {
    "iso:country":"GB",
    "wof:name":"KY4 0HX",
    "wof:placetype":"postalcode"
},
  "geometry": {"coordinates":[-3.39816685699344,56.15901309995756],"type":"Point"}
}