{
  "type": "Feature",
  "properties": {
    "date:inception_lower":"2009-02-01",
    "date:inception_upper":"2009-02-28",
    "iso:country":"GB",
    "wof:name":"BN26 6RZ",
    "wof:placetype":"postalcode"
},
  "geometry": {"coordinates":[0.205811,50.842653],"type":"Point"}
}