{
  "type": "Feature",
  "properties": {
    "iso:country": "GB",
    "wof:name": "BN26 6RZ",
    "wof:placetype": "postalcode"
  },
  "geometry": {"coordinates":[0.205811,50.842653],"type":"Point"}
}
