{
  "type": "Feature",
  "properties": {
    "iso:country":"GB",
    "wof:name":"BN26 6RZ",
    "wof:placetype":"postalcode"
},
  "geometry": {"coordinates":[0.20581144438837,50.84265285581678],"type":"Point"}
}