{
  "type": "Feature",
  "properties": {
    "iso:country":"GB",
    "wof:name":"CH4 9QB",
    "wof:placetype":"postalcode"
},
  "geometry": {"coordinates":[-2.90287713090599,53.16353791806372],"type":"Point"}
}