{
  "type": "Feature",
  "properties": {
    "date:inception_lower": "1981-06-01",
    "date:inception_upper": "1981-06-01",
    "iso:country": "GB",
    "wof:name": "HR9 5UU",
    "wof:placetype": "postalcode"
  },
  "geometry": {"coordinates":[-2.589568,51.906129],"type":"Point"}
}
