{
  "type": "Feature",
  "properties": {
    "iso:country":"GB",
    "wof:name":"HR9 5UU",
    "wof:placetype":"postalcode"
},
  "geometry": {"coordinates":[-2.58956804410021,51.90612873732579],"type":"Point"}
}