{
  "type": "Feature",
  "properties": {
    "iso:country":"GB",
    "wof:name":"TF7 4PA",
    "wof:placetype":"postalcode"
},
  "geometry": {"coordinates":[-2.42824725422296,52.64302717628184],"type":"Point"}
}