{
  "type": "Feature",
  "properties": {
    "iso:country": "GB",
    "wof:name": "TF7 4PA",
    "wof:placetype": "postalcode"
  },
  "geometry": {"coordinates":[-2.428247,52.643027],"type":"Point"}
}
