{
  "type": "Feature",
  "properties": {
    "iso:country":"GB",
    "wof:name":"BA1 1HU",
    "wof:placetype":"postalcode"
},
  "geometry": {"coordinates":[-2.36530287228985,51.38240659413034],"type":"Point"}
}