{
  "type": "Feature",
  "properties": {
    "iso:country":"GB",
    "wof:name":"W13 9YQ",
    "wof:placetype":"postalcode"
},
  "geometry": {"coordinates":[-0.32103442896146,51.50898459421892],"type":"Point"}
}