{
  "type": "Feature",
  "properties": {
    "date:inception_lower": "1990-02-01",
    "date:inception_upper": "1990-02-01",
    "iso:country": "GB",
    "wof:name": "CH2 2EA",
    "wof:placetype": "postalcode"
  },
  "geometry": {"coordinates":[-2.888424,53.199549],"type":"Point"}
}
