{
  "type": "Feature",
  "properties": {
    "iso:country":"GB",
    "wof:name":"WV4 4RU",
    "wof:placetype":"postalcode"
},
  "geometry": {"coordinates":[-2.17214766826633,52.56480919968288],"type":"Point"}
}