{
  "type": "Feature",
  "properties": {
    "iso:country":"GB",
    "wof:name":"MK42 8JE",
    "wof:placetype":"postalcode"
},
  "geometry": {"coordinates":[-0.48980504207398,52.11838127507954],"type":"Point"}
}