{
  "type": "Feature",
  "properties": {
    "date:inception_lower": "1997-12-01",
    "date:inception_upper": "1997-12-01",
    "iso:country": "GB",
    "wof:name": "BS39 4EF",
    "wof:placetype": "postalcode"
  },
  "geometry": {"coordinates":[-2.570558,51.364176],"type":"Point"}
}
