{
  "type": "Feature",
  "properties": {
    "iso:country":"GB",
    "wof:name":"EH12 5DR",
    "wof:placetype":"postalcode"
},
  "geometry": {"coordinates":[-3.21833179016428,55.94613994811173],"type":"Point"}
}