{
  "type": "Feature",
  "properties": {
    "iso:country":"GB",
    "wof:name":"BA22 8RU",
    "wof:placetype":"postalcode"
},
  "geometry": {"coordinates":[-2.67385285448117,50.94659275711646],"type":"Point"}
}