{
  "type": "Feature",
  "properties": {
    "iso:country":"GB",
    "wof:name":"PL4 8DR",
    "wof:placetype":"postalcode"
},
  "geometry": {"coordinates":[-4.13367997431703,50.37425227990239],"type":"Point"}
}