{
  "type": "Feature",
  "properties": {
    "iso:country":"GB",
    "wof:name":"NG2 4LQ",
    "wof:placetype":"postalcode"
},
  "geometry": {"coordinates":[-1.12597449378745,52.95239909989665],"type":"Point"}
}