{
  "type": "Feature",
  "properties": {
    "iso:country": "GB",
    "wof:name": "NG2 4LQ",
    "wof:placetype": "postalcode"
  },
  "geometry": {"coordinates":[-1.125974,52.952399],"type":"Point"}
}
