{
  "type": "Feature",
  "properties": {
    "iso:country": "GB",
    "wof:name": "EH12 9EB",
    "wof:placetype": "postalcode"
  },
  "geometry": {"coordinates":[-3.300506,55.93077],"type":"Point"}
}
