{
  "type": "Feature",
  "properties": {
    "iso:country":"GB",
    "wof:name":"EH12 9EB",
    "wof:placetype":"postalcode"
},
  "geometry": {"coordinates":[-3.30050571629634,55.93077009512908],"type":"Point"}
}