{
  "type": "Feature",
  "properties": {
    "iso:country":"GB",
    "wof:name":"EN6 4EN",
    "wof:placetype":"postalcode"
},
  "geometry": {"coordinates":[-0.11913363168564,51.7150028315129],"type":"Point"}
}