{
  "type": "Feature",
  "properties": {
    "iso:country":"GB",
    "wof:name":"SL4 2AH",
    "wof:placetype":"postalcode"
},
  "geometry": {"coordinates":[-0.60612384009884,51.47548252179475],"type":"Point"}
}