{
  "type": "Feature",
  "properties": {
    "iso:country":"GB",
    "wof:name":"UB3 1NZ",
    "wof:placetype":"postalcode"
},
  "geometry": {"coordinates":[-0.43829730767101,51.49868078560312],"type":"Point"}
}