{
  "type": "Feature",
  "properties": {
    "iso:country": "GB",
    "wof:name": "TN29 9SF",
    "wof:placetype": "postalcode"
  },
  "geometry": {"coordinates":[0.914715,50.98557],"type":"Point"}
}
