{
  "type": "Feature",
  "properties": {
    "iso:country": "GB",
    "wof:name": "FK13 6JP",
    "wof:placetype": "postalcode"
  },
  "geometry": {"coordinates":[-3.739137,56.142185],"type":"Point"}
}
