{
  "type": "Feature",
  "properties": {
    "date:inception_lower": "2004-08-01",
    "date:inception_upper": "2004-08-01",
    "iso:country": "GB",
    "wof:name": "TF7 4GR",
    "wof:placetype": "postalcode"
  },
  "geometry": {"coordinates":[-2.438524,52.64361],"type":"Point"}
}
