{
  "type": "Feature",
  "properties": {
    "date:inception_lower": "1980-01-01",
    "date:inception_upper": "1980-01-01",
    "iso:country": "GB",
    "wof:name": "LE17 4EZ",
    "wof:placetype": "postalcode"
  },
  "geometry": {"coordinates":[-1.201452,52.457751],"type":"Point"}
}
