{
  "type": "Feature",
  "properties": {
    "iso:country":"GB",
    "wof:name":"LE17 4EZ",
    "wof:placetype":"postalcode"
},
  "geometry": {"coordinates":[-1.20145206373753,52.45775138717369],"type":"Point"}
}