{
  "type": "Feature",
  "properties": {
    "iso:country":"GB",
    "wof:name":"NE37 2LJ",
    "wof:placetype":"postalcode"
},
  "geometry": {"coordinates":[-1.52457662443058,54.91659962120914],"type":"Point"}
}