{
  "type": "Feature",
  "properties": {
    "iso:country": "GB",
    "wof:name": "NE37 2LJ",
    "wof:placetype": "postalcode"
  },
  "geometry": {"coordinates":[-1.524577,54.9166],"type":"Point"}
}
