{
  "type": "Feature",
  "properties": {
    "iso:country":"GB",
    "wof:name":"UB1 1RJ",
    "wof:placetype":"postalcode"
},
  "geometry": {"coordinates":[-0.37802466789522,51.50905813274703],"type":"Point"}
}