{
  "type": "Feature",
  "properties": {
    "iso:country": "GB",
    "wof:name": "LE14 3AD",
    "wof:placetype": "postalcode"
  },
  "geometry": {"coordinates":[-0.973266,52.849346],"type":"Point"}
}
