{
  "type": "Feature",
  "properties": {
    "iso:country":"GB",
    "wof:name":"LE14 3AD",
    "wof:placetype":"postalcode"
},
  "geometry": {"coordinates":[-0.97365376693818,52.84948111061244],"type":"Point"}
}