{
  "type": "Feature",
  "properties": {
    "date:inception_lower": "1980-01-01",
    "date:inception_upper": "1980-01-01",
    "iso:country": "GB",
    "wof:name": "G67 2DA",
    "wof:placetype": "postalcode"
  },
  "geometry": {"coordinates":[-3.964896,55.956525],"type":"Point"}
}
