{
  "type": "Feature",
  "properties": {
    "iso:country": "GB",
    "wof:name": "G67 2DA",
    "wof:placetype": "postalcode"
  },
  "geometry": {"coordinates":[-3.964896,55.956525],"type":"Point"}
}
