{
  "type": "Feature",
  "properties": {
    "iso:country":"GB",
    "wof:name":"WV16 4DN",
    "wof:placetype":"postalcode"
},
  "geometry": {"coordinates":[-2.42060577794988,52.53663268066686],"type":"Point"}
}