{
  "type": "Feature",
  "properties": {
    "iso:country": "GB",
    "wof:name": "N20 0BH",
    "wof:placetype": "postalcode"
  },
  "geometry": {"coordinates":[-0.175564,51.628293],"type":"Point"}
}
