{
  "type": "Feature",
  "properties": {
    "iso:country":"GB",
    "wof:name":"SW6 2HG",
    "wof:placetype":"postalcode"
},
  "geometry": {"coordinates":[-0.18335777627609,51.47271655697527],"type":"Point"}
}