{
  "type": "Feature",
  "properties": {
    "date:inception_lower": "1980-01-01",
    "date:inception_upper": "1980-01-01",
    "iso:country": "GB",
    "wof:name": "IP14 1BU",
    "wof:placetype": "postalcode"
  },
  "geometry": {"coordinates":[1.0008,52.183674],"type":"Point"}
}
