{
  "type": "Feature",
  "properties": {
    "iso:country":"GB",
    "wof:name":"IP14 1BU",
    "wof:placetype":"postalcode"
},
  "geometry": {"coordinates":[1.00079837722865,52.18389040684246],"type":"Point"}
}