{
  "type": "Feature",
  "properties": {
    "iso:country": "GB",
    "wof:name": "IP14 1BU",
    "wof:placetype": "postalcode"
  },
  "geometry": {"coordinates":[1.000798,52.18389],"type":"Point"}
}
