{
  "type": "Feature",
  "properties": {
    "iso:country":"GB",
    "wof:name":"SW16 2XR",
    "wof:placetype":"postalcode"
},
  "geometry": {"coordinates":[-0.11941095376498,51.42998259848608],"type":"Point"}
}