{
  "type": "Feature",
  "properties": {
    "date:inception_lower": "1984-02-01",
    "date:inception_upper": "1984-02-01",
    "iso:country": "GB",
    "wof:name": "YO18 7TT",
    "wof:placetype": "postalcode"
  },
  "geometry": {"coordinates":[-0.726566,54.233632],"type":"Point"}
}
