{
  "type": "Feature",
  "properties": {
    "iso:country": "GB",
    "wof:name": "YO18 7TT",
    "wof:placetype": "postalcode"
  },
  "geometry": {"coordinates":[-0.726566,54.233632],"type":"Point"}
}
