{
  "type": "Feature",
  "properties": {
    "iso:country": "GB",
    "wof:name": "LA5 0DS",
    "wof:placetype": "postalcode"
  },
  "geometry": {"coordinates":[-2.832584,54.19913],"type":"Point"}
}
