{
  "type": "Feature",
  "properties": {
    "date:inception_lower": "1980-01-01",
    "date:inception_upper": "1980-01-01",
    "iso:country": "GB",
    "wof:name": "LA5 0DS",
    "wof:placetype": "postalcode"
  },
  "geometry": {"coordinates":[-2.832658,54.199004],"type":"Point"}
}
