{
  "type": "Feature",
  "properties": {
    "iso:country":"GB",
    "wof:name":"LA5 0DS",
    "wof:placetype":"postalcode"
},
  "geometry": {"coordinates":[-2.83265810482285,54.19899364815607],"type":"Point"}
}