{
  "type": "Feature",
  "properties": {
    "date:inception_lower": "2018-08-01",
    "date:inception_upper": "2018-08-01",
    "iso:country": "GB",
    "wof:name": "S75 2SZ",
    "wof:placetype": "postalcode"
  },
  "geometry": {"coordinates":[-1.496518,53.559389],"type":"Point"}
}
