{
  "type": "Feature",
  "properties": {
    "iso:country": "GB",
    "wof:name": "EH7 4RB",
    "wof:placetype": "postalcode"
  },
  "geometry": {"coordinates":[-3.180713,55.962756],"type":"Point"}
}
