{
  "type": "Feature",
  "properties": {
    "iso:country":"GB",
    "wof:name":"NG20 8XQ",
    "wof:placetype":"postalcode"
},
  "geometry": {"coordinates":[-1.18359045490463,53.20586639037404],"type":"Point"}
}