{
  "type": "Feature",
  "properties": {
    "date:inception_lower": "1980-01-01",
    "date:inception_upper": "1980-01-01",
    "iso:country": "GB",
    "wof:name": "NG20 8XQ",
    "wof:placetype": "postalcode"
  },
  "geometry": {"coordinates":[-1.18359,53.205866],"type":"Point"}
}
