{
  "type": "Feature",
  "properties": {
    "iso:country": "GB",
    "wof:name": "GL18 1UD",
    "wof:placetype": "postalcode"
  },
  "geometry": {"coordinates":[-2.397755,51.927703],"type":"Point"}
}
