{
  "type": "Feature",
  "properties": {
    "iso:country":"GB",
    "wof:name":"GL18 1UD",
    "wof:placetype":"postalcode"
},
  "geometry": {"coordinates":[-2.39775479488502,51.92770259341576],"type":"Point"}
}