{
  "type": "Feature",
  "properties": {
    "date:inception_lower": "2010-09-01",
    "date:inception_upper": "2010-09-01",
    "iso:country": "GB",
    "wof:name": "GL18 1UD",
    "wof:placetype": "postalcode"
  },
  "geometry": {"coordinates":[-2.397755,51.927703],"type":"Point"}
}
