{
  "type": "Feature",
  "properties": {
    "iso:country": "GB",
    "wof:name": "G64 3BU",
    "wof:placetype": "postalcode"
  },
  "geometry": {"coordinates":[-4.227582,55.908538],"type":"Point"}
}
