{
  "type": "Feature",
  "properties": {
    "iso:country":"GB",
    "wof:name":"G64 3BU",
    "wof:placetype":"postalcode"
},
  "geometry": {"coordinates":[-4.22758171638317,55.90853774750266],"type":"Point"}
}