{
  "type": "Feature",
  "properties": {
    "date:inception_lower": "1980-01-01",
    "date:inception_upper": "1980-01-01",
    "iso:country": "GB",
    "wof:name": "BD22 9SA",
    "wof:placetype": "postalcode"
  },
  "geometry": {"coordinates":[-1.953183,53.816213],"type":"Point"}
}
