{
  "type": "Feature",
  "properties": {
    "iso:country":"GB",
    "wof:name":"BD22 9SA",
    "wof:placetype":"postalcode"
},
  "geometry": {"coordinates":[-1.9531829798232,53.81621312511071],"type":"Point"}
}