{
  "type": "Feature",
  "properties": {
    "iso:country":"GB",
    "wof:name":"CB9 8JS",
    "wof:placetype":"postalcode"
},
  "geometry": {"coordinates":[0.42648372536352,52.08079807041793],"type":"Point"}
}