{
  "type": "Feature",
  "properties": {
    "iso:country":"GB",
    "wof:name":"SY7 9DE",
    "wof:placetype":"postalcode"
},
  "geometry": {"coordinates":[-2.74278893971949,52.45969350758835],"type":"Point"}
}