{
  "type": "Feature",
  "properties": {
    "date:inception_lower":"1980-01-01",
    "date:inception_upper":"1980-01-31",
    "iso:country":"GB",
    "wof:name":"SY7 9DE",
    "wof:placetype":"postalcode"
},
  "geometry": {"coordinates":[-2.742789,52.459694],"type":"Point"}
}