{
  "type": "Feature",
  "properties": {
    "iso:country": "GB",
    "wof:name": "SN8 2NH",
    "wof:placetype": "postalcode"
  },
  "geometry": {"coordinates":[-1.693481,51.4389],"type":"Point"}
}
