{
  "type": "Feature",
  "properties": {
    "iso:country":"GB",
    "wof:name":"SN8 2NH",
    "wof:placetype":"postalcode"
},
  "geometry": {"coordinates":[-1.69348054981866,51.438900184344],"type":"Point"}
}