{
  "type": "Feature",
  "properties": {
    "iso:country":"GB",
    "wof:name":"FK17 8EL",
    "wof:placetype":"postalcode"
},
  "geometry": {"coordinates":[-4.21320447510119,56.245192899995],"type":"Point"}
}