{
  "type": "Feature",
  "properties": {
    "iso:country":"GB",
    "wof:name":"LL12 7YH",
    "wof:placetype":"postalcode"
},
  "geometry": {"coordinates":[-2.98617678584746,53.06045233293264],"type":"Point"}
}