{
  "type": "Feature",
  "properties": {
    "iso:country":"GB",
    "wof:name":"ST13 7QG",
    "wof:placetype":"postalcode"
},
  "geometry": {"coordinates":[-2.01872437306767,53.0814211268064],"type":"Point"}
}