{
  "type": "Feature",
  "properties": {
    "date:inception_lower": "1991-09-01",
    "date:inception_upper": "1991-09-01",
    "iso:country": "GB",
    "wof:name": "ST13 7QG",
    "wof:placetype": "postalcode"
  },
  "geometry": {"coordinates":[-2.018724,53.081421],"type":"Point"}
}
