{
  "type": "Feature",
  "properties": {
    "iso:country":"GB",
    "wof:name":"G64 1PX",
    "wof:placetype":"postalcode"
},
  "geometry": {"coordinates":[-4.21898116285742,55.90278841784723],"type":"Point"}
}