{
  "type": "Feature",
  "properties": {
    "iso:country":"GB",
    "wof:name":"HU2 8RR",
    "wof:placetype":"postalcode"
},
  "geometry": {"coordinates":[-0.35226777045207,53.74553399441267],"type":"Point"}
}