{
  "type": "Feature",
  "properties": {
    "iso:country":"GB",
    "wof:name":"WV2 4HD",
    "wof:placetype":"postalcode"
},
  "geometry": {"coordinates":[-2.1336903972648,52.58015063839034],"type":"Point"}
}