{
  "type": "Feature",
  "properties": {
    "iso:country":"GB",
    "wof:name":"CM15 8FF",
    "wof:placetype":"postalcode"
},
  "geometry": {"coordinates":[0.32319509741461,51.62956871341876],"type":"Point"}
}