{
  "type": "Feature",
  "properties": {
    "date:inception_lower": "2013-07-01",
    "date:inception_upper": "2013-07-01",
    "iso:country": "GB",
    "wof:name": "CM15 8FF",
    "wof:placetype": "postalcode"
  },
  "geometry": {"coordinates":[0.323195,51.629569],"type":"Point"}
}
