{
  "type": "Feature",
  "properties": {
    "iso:country":"GB",
    "wof:name":"LU2 9JD",
    "wof:placetype":"postalcode"
},
  "geometry": {"coordinates":[-0.38087839181701,51.88448610826585],"type":"Point"}
}