{
  "type": "Feature",
  "properties": {
    "iso:country": "GB",
    "wof:name": "LU2 9JD",
    "wof:placetype": "postalcode"
  },
  "geometry": {"coordinates":[-0.380878,51.884486],"type":"Point"}
}
