{
  "type": "Feature",
  "properties": {
    "date:inception_lower": "2008-03-01",
    "date:inception_upper": "2008-03-01",
    "iso:country": "GB",
    "wof:name": "L25 1AD",
    "wof:placetype": "postalcode"
  },
  "geometry": {"coordinates":[-2.87173,53.398276],"type":"Point"}
}
