{
  "type": "Feature",
  "properties": {
    "iso:country": "GB",
    "wof:name": "L25 1AD",
    "wof:placetype": "postalcode"
  },
  "geometry": {"coordinates":[-2.87173,53.398276],"type":"Point"}
}
