{
  "type": "Feature",
  "properties": {
    "date:inception_lower":"2003-10-01",
    "date:inception_upper":"2003-10-31",
    "iso:country":"GB",
    "wof:name":"YO43 3EZ",
    "wof:placetype":"postalcode"
},
  "geometry": {"coordinates":[-0.680014,53.862103],"type":"Point"}
}