{
  "type": "Feature",
  "properties": {
    "iso:country":"GB",
    "wof:name":"YO43 3EZ",
    "wof:placetype":"postalcode"
},
  "geometry": {"coordinates":[-0.68001429134104,53.86210252090834],"type":"Point"}
}