{
  "type": "Feature",
  "properties": {
    "date:inception_lower": "1980-01-01",
    "date:inception_upper": "1980-01-01",
    "iso:country": "GB",
    "wof:name": "ME9 7LT",
    "wof:placetype": "postalcode"
  },
  "geometry": {"coordinates":[0.666645,51.350605],"type":"Point"}
}
