{
  "type": "Feature",
  "properties": {
    "iso:country": "GB",
    "wof:name": "SG19 2UB",
    "wof:placetype": "postalcode"
  },
  "geometry": {"coordinates":[-0.299682,52.138236],"type":"Point"}
}
