{
  "type": "Feature",
  "properties": {
    "date:inception_lower":"2000-12-01",
    "date:inception_upper":"2000-12-31",
    "iso:country":"GB",
    "wof:name":"SG19 2UB",
    "wof:placetype":"postalcode"
},
  "geometry": {"coordinates":[-0.299682,52.138236],"type":"Point"}
}