{
  "type": "Feature",
  "properties": {
    "iso:country":"GB",
    "wof:name":"HX5 9JU",
    "wof:placetype":"postalcode"
},
  "geometry": {"coordinates":[-1.81756476648817,53.68329450708019],"type":"Point"}
}