{
  "type": "Feature",
  "properties": {
    "iso:country":"GB",
    "wof:name":"WN4 9HS",
    "wof:placetype":"postalcode"
},
  "geometry": {"coordinates":[-2.62918485513605,53.48468963090406],"type":"Point"}
}