{
  "type": "Feature",
  "properties": {
    "iso:country":"GB",
    "wof:name":"SK12 1XF",
    "wof:placetype":"postalcode"
},
  "geometry": {"coordinates":[-2.13198765130452,53.34912682532704],"type":"Point"}
}