{
  "type": "Feature",
  "properties": {
    "iso:country": "GB",
    "wof:name": "DN1 2AL",
    "wof:placetype": "postalcode"
  },
  "geometry": {"coordinates":[-1.12596,53.519038],"type":"Point"}
}
