{
  "type": "Feature",
  "properties": {
    "date:inception_lower": "1980-01-01",
    "date:inception_upper": "1980-01-01",
    "iso:country": "GB",
    "wof:name": "PR2 1DJ",
    "wof:placetype": "postalcode"
  },
  "geometry": {"coordinates":[-2.728835,53.765839],"type":"Point"}
}
