{
  "type": "Feature",
  "properties": {
    "iso:country":"GB",
    "wof:name":"YO22 4RE",
    "wof:placetype":"postalcode"
},
  "geometry": {"coordinates":[-0.53448356597466,54.43627022917855],"type":"Point"}
}