{
  "type": "Feature",
  "properties": {
    "date:inception_lower": "2005-08-01",
    "date:inception_upper": "2005-08-01",
    "iso:country": "GB",
    "wof:name": "PE33 0SR",
    "wof:placetype": "postalcode"
  },
  "geometry": {"coordinates":[0.418537,52.672334],"type":"Point"}
}
