{
  "type": "Feature",
  "properties": {
    "iso:country":"GB",
    "wof:name":"PE33 0SR",
    "wof:placetype":"postalcode"
},
  "geometry": {"coordinates":[0.41870322435695,52.67243480217643],"type":"Point"}
}