{
  "type": "Feature",
  "properties": {
    "iso:country":"GB",
    "wof:name":"NG3 2NZ",
    "wof:placetype":"postalcode"
},
  "geometry": {"coordinates":[-1.12146399720553,52.96417807968003],"type":"Point"}
}