{
  "type": "Feature",
  "properties": {
    "date:inception_lower":"1997-12-01",
    "date:inception_upper":"1997-12-31",
    "iso:country":"GB",
    "wof:name":"NG3 2NZ",
    "wof:placetype":"postalcode"
},
  "geometry": {"coordinates":[-1.121464,52.964178],"type":"Point"}
}