{
  "type": "Feature",
  "properties": {
    "date:inception_lower": "1995-01-01",
    "date:inception_upper": "1995-01-01",
    "iso:country": "GB",
    "wof:name": "B37 7TZ",
    "wof:placetype": "postalcode"
  },
  "geometry": {"coordinates":[-1.740744,52.480332],"type":"Point"}
}
