{
  "type": "Feature",
  "properties": {
    "iso:country": "GB",
    "wof:name": "NN12 6FW",
    "wof:placetype": "postalcode"
  },
  "geometry": {"coordinates":[-0.989351,52.134127],"type":"Point"}
}
