{
  "type": "Feature",
  "properties": {
    "date:inception_lower": "2019-12-01",
    "date:inception_upper": "2019-12-01",
    "iso:country": "GB",
    "wof:name": "NN12 6FW",
    "wof:placetype": "postalcode"
  },
  "geometry": {"coordinates":[-0.989542,52.134074],"type":"Point"}
}
