{
  "type": "Feature",
  "properties": {
    "iso:country":"GB",
    "wof:name":"WA3 7AG",
    "wof:placetype":"postalcode"
},
  "geometry": {"coordinates":[-2.52569002628264,53.41564515306776],"type":"Point"}
}