{
  "type": "Feature",
  "properties": {
    "iso:country":"GB",
    "wof:name":"CM20 3RD",
    "wof:placetype":"postalcode"
},
  "geometry": {"coordinates":[0.10502242441139,51.76930066162142],"type":"Point"}
}