{
  "type": "Feature",
  "properties": {
    "iso:country": "GB",
    "wof:name": "LL14 5DU",
    "wof:placetype": "postalcode"
  },
  "geometry": {"coordinates":[-3.055537,52.9262],"type":"Point"}
}
