{
  "type": "Feature",
  "properties": {
    "iso:country":"GB",
    "wof:name":"RH6 7JA",
    "wof:placetype":"postalcode"
},
  "geometry": {"coordinates":[-0.16444797746289,51.17406982028452],"type":"Point"}
}