{
  "type": "Feature",
  "properties": {
    "iso:country":"GB",
    "wof:name":"G46 8PB",
    "wof:placetype":"postalcode"
},
  "geometry": {"coordinates":[-4.32087683036475,55.80668302158735],"type":"Point"}
}