{
  "type": "Feature",
  "properties": {
    "iso:country": "GB",
    "wof:name": "G46 8PB",
    "wof:placetype": "postalcode"
  },
  "geometry": {"coordinates":[-4.320877,55.806683],"type":"Point"}
}
