{
  "type": "Feature",
  "properties": {
    "iso:country":"GB",
    "wof:name":"NN14 3EN",
    "wof:placetype":"postalcode"
},
  "geometry": {"coordinates":[-0.53928302448495,52.42223534514324],"type":"Point"}
}