{
  "type": "Feature",
  "properties": {
    "iso:country":"GB",
    "wof:name":"B44 9UY",
    "wof:placetype":"postalcode"
},
  "geometry": {"coordinates":[-1.8944783047537,52.54551481621696],"type":"Point"}
}