{
  "type": "Feature",
  "properties": {
    "iso:country": "GB",
    "wof:name": "B44 9UY",
    "wof:placetype": "postalcode"
  },
  "geometry": {"coordinates":[-1.894478,52.545515],"type":"Point"}
}
