{
  "type": "Feature",
  "properties": {
    "iso:country":"GB",
    "wof:name":"BN17 6AW",
    "wof:placetype":"postalcode"
},
  "geometry": {"coordinates":[-0.5392632717511,50.81067959133421],"type":"Point"}
}