{
  "type": "Feature",
  "properties": {
    "date:inception_lower": "2018-09-01",
    "date:inception_upper": "2018-09-01",
    "iso:country": "GB",
    "wof:name": "NE2 4DF",
    "wof:placetype": "postalcode"
  },
  "geometry": {"coordinates":[-1.607076,54.984604],"type":"Point"}
}
