{
  "type": "Feature",
  "properties": {
    "iso:country":"GB",
    "wof:name":"M6 8LX",
    "wof:placetype":"postalcode"
},
  "geometry": {"coordinates":[-2.3211315298479,53.49724044067419],"type":"Point"}
}