{
  "type": "Feature",
  "properties": {
    "date:inception_lower":"1982-03-01",
    "date:inception_upper":"1982-03-31",
    "iso:country":"GB",
    "wof:name":"SW9 0ST",
    "wof:placetype":"postalcode"
},
  "geometry": {"coordinates":[-0.11968,51.470022],"type":"Point"}
}