{
  "type": "Feature",
  "properties": {
    "iso:country": "GB",
    "wof:name": "L39 0EP",
    "wof:placetype": "postalcode"
  },
  "geometry": {"coordinates":[-2.882538,53.530257],"type":"Point"}
}
