{
  "type": "Feature",
  "properties": {
    "iso:country":"GB",
    "wof:name":"WD6 1AX",
    "wof:placetype":"postalcode"
},
  "geometry": {"coordinates":[-0.27556823171206,51.65619369622362],"type":"Point"}
}