{
  "type": "Feature",
  "properties": {
    "iso:country":"GB",
    "wof:name":"W1U 6DP",
    "wof:placetype":"postalcode"
},
  "geometry": {"coordinates":[-0.15646081729458,51.52090126516322],"type":"Point"}
}