{
  "type": "Feature",
  "properties": {
    "iso:country": "GB",
    "wof:name": "SA18 1YT",
    "wof:placetype": "postalcode"
  },
  "geometry": {"coordinates":[-3.896022,51.791265],"type":"Point"}
}
