{
  "type": "Feature",
  "properties": {
    "iso:country":"GB",
    "wof:name":"SA18 1YT",
    "wof:placetype":"postalcode"
},
  "geometry": {"coordinates":[-3.89602233148359,51.79126546377838],"type":"Point"}
}