{
  "type": "Feature",
  "properties": {
    "iso:country":"GB",
    "wof:name":"GL20 7LW",
    "wof:placetype":"postalcode"
},
  "geometry": {"coordinates":[-2.11223305922024,52.0305282976886],"type":"Point"}
}