{
  "type": "Feature",
  "properties": {
    "iso:country": "GB",
    "wof:name": "BS21 7SZ",
    "wof:placetype": "postalcode"
  },
  "geometry": {"coordinates":[-2.855235,51.438785],"type":"Point"}
}
