{
  "type": "Feature",
  "properties": {
    "iso:country":"GB",
    "wof:name":"BS21 7SZ",
    "wof:placetype":"postalcode"
},
  "geometry": {"coordinates":[-2.85514287035042,51.43874212411484],"type":"Point"}
}