{
  "type": "Feature",
  "properties": {
    "iso:country": "GB",
    "wof:name": "SP7 0HS",
    "wof:placetype": "postalcode"
  },
  "geometry": {"coordinates":[-2.078239,50.9977],"type":"Point"}
}
