{
  "type": "Feature",
  "properties": {
    "iso:country":"GB",
    "wof:name":"SP7 0HS",
    "wof:placetype":"postalcode"
},
  "geometry": {"coordinates":[-2.07823895352656,50.99769963798874],"type":"Point"}
}