{
  "type": "Feature",
  "properties": {
    "iso:country": "GB",
    "wof:name": "BB8 7EJ",
    "wof:placetype": "postalcode"
  },
  "geometry": {"coordinates":[-2.102519,53.867328],"type":"Point"}
}
