{
  "type": "Feature",
  "properties": {
    "iso:country":"GB",
    "wof:name":"BB8 7EJ",
    "wof:placetype":"postalcode"
},
  "geometry": {"coordinates":[-2.10276237130279,53.86752575211245],"type":"Point"}
}