{
  "type": "Feature",
  "properties": {
    "iso:country":"GB",
    "wof:name":"NN15 5SD",
    "wof:placetype":"postalcode"
},
  "geometry": {"coordinates":[-0.67261205719383,52.36917065503092],"type":"Point"}
}