{
  "type": "Feature",
  "properties": {
    "iso:country": "GB",
    "wof:name": "DG1 3QW",
    "wof:placetype": "postalcode"
  },
  "geometry": {"coordinates":[-3.579229,55.100806],"type":"Point"}
}
