{
  "type": "Feature",
  "properties": {
    "date:inception_lower": "2014-09-01",
    "date:inception_upper": "2014-09-01",
    "iso:country": "GB",
    "wof:name": "OX12 9WE",
    "wof:placetype": "postalcode"
  },
  "geometry": {"coordinates":[-1.45202,51.594168],"type":"Point"}
}
