{
  "type": "Feature",
  "properties": {
    "iso:country":"GB",
    "wof:name":"IP32 7DG",
    "wof:placetype":"postalcode"
},
  "geometry": {"coordinates":[0.73742124360854,52.24083945192127],"type":"Point"}
}