{
  "type": "Feature",
  "properties": {
    "date:inception_lower": "1981-06-01",
    "date:inception_upper": "1981-06-01",
    "iso:country": "GB",
    "wof:name": "IP32 7DG",
    "wof:placetype": "postalcode"
  },
  "geometry": {"coordinates":[0.737421,52.240839],"type":"Point"}
}
