{
  "type": "Feature",
  "properties": {
    "iso:country":"GB",
    "wof:name":"RG22 5LW",
    "wof:placetype":"postalcode"
},
  "geometry": {"coordinates":[-1.14095310827647,51.23712727819556],"type":"Point"}
}