{
  "type": "Feature",
  "properties": {
    "date:inception_lower": "1980-01-01",
    "date:inception_upper": "1980-01-01",
    "iso:country": "GB",
    "wof:name": "RG22 5LW",
    "wof:placetype": "postalcode"
  },
  "geometry": {"coordinates":[-1.140953,51.237127],"type":"Point"}
}
