{
  "type": "Feature",
  "properties": {
    "iso:country":"GB",
    "wof:name":"TA6 5HE",
    "wof:placetype":"postalcode"
},
  "geometry": {"coordinates":[-2.9924579978374,51.13027414614418],"type":"Point"}
}