{
  "type": "Feature",
  "properties": {
    "iso:country":"GB",
    "wof:name":"CO7 0QH",
    "wof:placetype":"postalcode"
},
  "geometry": {"coordinates":[1.02288778994694,51.81855893322163],"type":"Point"}
}