{
  "type": "Feature",
  "properties": {
    "iso:country":"GB",
    "wof:name":"WD6 1PA",
    "wof:placetype":"postalcode"
},
  "geometry": {"coordinates":[-0.2765695038657,51.66066850255428],"type":"Point"}
}