{
  "type": "Feature",
  "properties": {
    "iso:country": "GB",
    "wof:name": "SR8 3UZ",
    "wof:placetype": "postalcode"
  },
  "geometry": {"coordinates":[-1.344377,54.779256],"type":"Point"}
}
