{
  "type": "Feature",
  "properties": {
    "date:inception_lower": "2019-11-01",
    "date:inception_upper": "2019-11-01",
    "iso:country": "GB",
    "wof:name": "SR8 3UZ",
    "wof:placetype": "postalcode"
  },
  "geometry": {"coordinates":[-1.344377,54.779256],"type":"Point"}
}
