{
  "type": "Feature",
  "properties": {
    "iso:country": "GB",
    "wof:name": "YO25 6BD",
    "wof:placetype": "postalcode"
  },
  "geometry": {"coordinates":[-0.429811,54.001483],"type":"Point"}
}
