{
  "type": "Feature",
  "properties": {
    "iso:country":"GB",
    "wof:name":"WF13 2AF",
    "wof:placetype":"postalcode"
},
  "geometry": {"coordinates":[-1.63344644272718,53.6965709540443],"type":"Point"}
}