{
  "type": "Feature",
  "properties": {
    "date:inception_lower":"1980-01-01",
    "date:inception_upper":"1980-01-31",
    "iso:country":"GB",
    "wof:name":"CT2 7LB",
    "wof:placetype":"postalcode"
},
  "geometry": {"coordinates":[1.072175,51.292387],"type":"Point"}
}