{
  "type": "Feature",
  "properties": {
    "iso:country":"GB",
    "wof:name":"CV21 1EG",
    "wof:placetype":"postalcode"
},
  "geometry": {"coordinates":[-1.27523292603417,52.38661014261059],"type":"Point"}
}