{
  "type": "Feature",
  "properties": {
    "iso:country":"GB",
    "wof:name":"UB4 0XT",
    "wof:placetype":"postalcode"
},
  "geometry": {"coordinates":[-0.40039793240253,51.52362704291142],"type":"Point"}
}