{
  "type": "Feature",
  "properties": {
    "iso:country": "GB",
    "wof:name": "S66 9JL",
    "wof:placetype": "postalcode"
  },
  "geometry": {"coordinates":[-1.282186,53.399834],"type":"Point"}
}
