{
  "type": "Feature",
  "properties": {
    "iso:country":"GB",
    "wof:name":"S66 9JL",
    "wof:placetype":"postalcode"
},
  "geometry": {"coordinates":[-1.28218617993571,53.39983423279843],"type":"Point"}
}