{
  "type": "Feature",
  "properties": {
    "date:inception_lower": "1980-01-01",
    "date:inception_upper": "1980-01-01",
    "iso:country": "GB",
    "wof:name": "GU15 2LG",
    "wof:placetype": "postalcode"
  },
  "geometry": {"coordinates":[-0.739167,51.32513],"type":"Point"}
}
