{
  "type": "Feature",
  "properties": {
    "iso:country":"GB",
    "wof:name":"BL8 2EX",
    "wof:placetype":"postalcode"
},
  "geometry": {"coordinates":[-2.34278358898348,53.59124372160628],"type":"Point"}
}