{
  "type": "Feature",
  "properties": {
    "date:inception_lower":"1980-01-01",
    "date:inception_upper":"1980-01-31",
    "iso:country":"GB",
    "wof:name":"SA12 9UN",
    "wof:placetype":"postalcode"
},
  "geometry": {"coordinates":[-3.737834,51.652275],"type":"Point"}
}