{
  "type": "Feature",
  "properties": {
    "iso:country":"GB",
    "wof:name":"SA12 9UN",
    "wof:placetype":"postalcode"
},
  "geometry": {"coordinates":[-3.73783379933951,51.65227451977475],"type":"Point"}
}