{
  "type": "Feature",
  "properties": {
    "iso:country":"GB",
    "wof:name":"CM14 4GT",
    "wof:placetype":"postalcode"
},
  "geometry": {"coordinates":[0.28885329266632,51.62278828706847],"type":"Point"}
}