{
  "type": "Feature",
  "properties": {
    "iso:country":"GB",
    "wof:name":"CF37 1XG",
    "wof:placetype":"postalcode"
},
  "geometry": {"coordinates":[-3.34828233106389,51.58884974501618],"type":"Point"}
}