{
  "type": "Feature",
  "properties": {
    "iso:country":"GB",
    "wof:name":"TS17 0FJ",
    "wof:placetype":"postalcode"
},
  "geometry": {"coordinates":[-1.3150834588059,54.50838137418768],"type":"Point"}
}