{
  "type": "Feature",
  "properties": {
    "date:inception_lower": "1995-07-01",
    "date:inception_upper": "1995-07-01",
    "iso:country": "GB",
    "wof:name": "TS17 0FJ",
    "wof:placetype": "postalcode"
  },
  "geometry": {"coordinates":[-1.315083,54.508381],"type":"Point"}
}
