{
  "type": "Feature",
  "properties": {
    "iso:country":"GB",
    "wof:name":"GL13 9UD",
    "wof:placetype":"postalcode"
},
  "geometry": {"coordinates":[-2.47895626192566,51.71797174207013],"type":"Point"}
}