{
  "type": "Feature",
  "properties": {
    "iso:country": "GB",
    "wof:name": "GL13 9UD",
    "wof:placetype": "postalcode"
  },
  "geometry": {"coordinates":[-2.478957,51.717976],"type":"Point"}
}
