{
  "type": "Feature",
  "properties": {
    "date:inception_lower":"1980-01-01",
    "date:inception_upper":"1980-01-31",
    "iso:country":"GB",
    "wof:name":"GL13 9UD",
    "wof:placetype":"postalcode"
},
  "geometry": {"coordinates":[-2.478957,51.717976],"type":"Point"}
}