{
  "type": "Feature",
  "properties": {
    "date:inception_lower": "1983-03-01",
    "date:inception_upper": "1983-03-01",
    "iso:country": "GB",
    "wof:name": "RH12 1PB",
    "wof:placetype": "postalcode"
  },
  "geometry": {"coordinates":[-0.331019,51.062838],"type":"Point"}
}
