{
  "type": "Feature",
  "properties": {
    "iso:country": "GB",
    "wof:name": "ME19 5SQ",
    "wof:placetype": "postalcode"
  },
  "geometry": {"coordinates":[0.405018,51.309684],"type":"Point"}
}
