{
  "type": "Feature",
  "properties": {
    "date:inception_lower":"2011-02-01",
    "date:inception_upper":"2011-02-28",
    "iso:country":"GB",
    "wof:name":"NE24 9DN",
    "wof:placetype":"postalcode"
},
  "geometry": {"coordinates":[-1.506863,55.127544],"type":"Point"}
}