{
  "type": "Feature",
  "properties": {
    "date:inception_lower": "1980-01-01",
    "date:inception_upper": "1980-01-01",
    "iso:country": "GB",
    "wof:name": "EC1R 1UB",
    "wof:placetype": "postalcode"
  },
  "geometry": {"coordinates":[-0.106847,51.526451],"type":"Point"}
}
