{
  "type": "Feature",
  "properties": {
    "date:inception_lower": "1999-06-01",
    "date:inception_upper": "1999-06-01",
    "iso:country": "GB",
    "wof:name": "KT9 2SN",
    "wof:placetype": "postalcode"
  },
  "geometry": {"coordinates":[-0.313837,51.356765],"type":"Point"}
}
