{
  "type": "Feature",
  "properties": {
    "iso:country":"GB",
    "wof:name":"KT9 2SN",
    "wof:placetype":"postalcode"
},
  "geometry": {"coordinates":[-0.3138371523629,51.35676539011608],"type":"Point"}
}