{
  "type": "Feature",
  "properties": {
    "iso:country": "GB",
    "wof:name": "WR15 8RJ",
    "wof:placetype": "postalcode"
  },
  "geometry": {"coordinates":[-2.569291,52.290111],"type":"Point"}
}
