{
  "type": "Feature",
  "properties": {
    "iso:country":"GB",
    "wof:name":"WR15 8RJ",
    "wof:placetype":"postalcode"
},
  "geometry": {"coordinates":[-2.56929060719148,52.2901114516041],"type":"Point"}
}