{
  "type": "Feature",
  "properties": {
    "date:inception_lower":"1980-01-01",
    "date:inception_upper":"1980-01-31",
    "iso:country":"GB",
    "wof:name":"WR15 8RJ",
    "wof:placetype":"postalcode"
},
  "geometry": {"coordinates":[-2.569291,52.290111],"type":"Point"}
}