{
  "type": "Feature",
  "properties": {
    "iso:country":"GB",
    "wof:name":"TS10 2LE",
    "wof:placetype":"postalcode"
},
  "geometry": {"coordinates":[-1.0516318788642,54.60568681990249],"type":"Point"}
}