{
  "type": "Feature",
  "properties": {
    "iso:country": "GB",
    "wof:name": "RM1 2EE",
    "wof:placetype": "postalcode"
  },
  "geometry": {"coordinates":[0.18809,51.575531],"type":"Point"}
}
