{
  "type": "Feature",
  "properties": {
    "iso:country":"GB",
    "wof:name":"SY10 9LS",
    "wof:placetype":"postalcode"
},
  "geometry": {"coordinates":[-3.15654575834505,52.80845399430332],"type":"Point"}
}