{
  "type": "Feature",
  "properties": {
    "date:inception_lower": "1980-01-01",
    "date:inception_upper": "1980-01-01",
    "iso:country": "GB",
    "wof:name": "WA12 9TE",
    "wof:placetype": "postalcode"
  },
  "geometry": {"coordinates":[-2.616572,53.455659],"type":"Point"}
}
