{
  "type": "Feature",
  "properties": {
    "iso:country":"GB",
    "wof:name":"SW9 6UX",
    "wof:placetype":"postalcode"
},
  "geometry": {"coordinates":[-0.10358736180474,51.47684903174692],"type":"Point"}
}