{
  "type": "Feature",
  "properties": {
    "iso:country": "GB",
    "wof:name": "LL22 7HP",
    "wof:placetype": "postalcode"
  },
  "geometry": {"coordinates":[-3.575747,53.28267],"type":"Point"}
}
