{
  "type": "Feature",
  "properties": {
    "iso:country":"GB",
    "wof:name":"ST2 7LE",
    "wof:placetype":"postalcode"
},
  "geometry": {"coordinates":[-2.13174892180524,53.05733064587423],"type":"Point"}
}