{
  "type": "Feature",
  "properties": {
    "iso:country": "GB",
    "wof:name": "TW11 0LT",
    "wof:placetype": "postalcode"
  },
  "geometry": {"coordinates":[-0.340812,51.424666],"type":"Point"}
}
