{
  "type": "Feature",
  "properties": {
    "iso:country":"GB",
    "wof:name":"NE25 9JJ",
    "wof:placetype":"postalcode"
},
  "geometry": {"coordinates":[-1.49204390055835,55.04466668692966],"type":"Point"}
}