{
  "type": "Feature",
  "properties": {
    "date:inception_lower":"1980-01-01",
    "date:inception_upper":"1980-01-31",
    "iso:country":"GB",
    "wof:name":"NE25 9JJ",
    "wof:placetype":"postalcode"
},
  "geometry": {"coordinates":[-1.49195,55.04463],"type":"Point"}
}