{
  "type": "Feature",
  "properties": {
    "iso:country": "GB",
    "wof:name": "NE25 9JJ",
    "wof:placetype": "postalcode"
  },
  "geometry": {"coordinates":[-1.49195,55.04463],"type":"Point"}
}
