{
  "type": "Feature",
  "properties": {
    "iso:country":"GB",
    "wof:name":"SK10 4SW",
    "wof:placetype":"postalcode"
},
  "geometry": {"coordinates":[-2.1777163633661,53.27748138055047],"type":"Point"}
}