{
  "type": "Feature",
  "properties": {
    "date:inception_lower": "1994-05-01",
    "date:inception_upper": "1994-05-01",
    "iso:country": "GB",
    "wof:name": "M28 1GA",
    "wof:placetype": "postalcode"
  },
  "geometry": {"coordinates":[-2.414937,53.504762],"type":"Point"}
}
