{
  "type": "Feature",
  "properties": {
    "iso:country":"GB",
    "wof:name":"M28 1GA",
    "wof:placetype":"postalcode"
},
  "geometry": {"coordinates":[-2.41493657828374,53.50476240863886],"type":"Point"}
}