{
  "type": "Feature",
  "properties": {
    "iso:country":"GB",
    "wof:name":"TS14 8ER",
    "wof:placetype":"postalcode"
},
  "geometry": {"coordinates":[-1.07363982313018,54.51727042343926],"type":"Point"}
}