{
  "type": "Feature",
  "properties": {
    "iso:country":"GB",
    "wof:name":"KA10 6PU",
    "wof:placetype":"postalcode"
},
  "geometry": {"coordinates":[-4.65496681054573,55.54963040425561],"type":"Point"}
}