{
  "type": "Feature",
  "properties": {
    "date:inception_lower": "1993-07-01",
    "date:inception_upper": "1993-07-01",
    "iso:country": "GB",
    "wof:name": "AB51 5BD",
    "wof:placetype": "postalcode"
  },
  "geometry": {"coordinates":[-2.465481,57.372791],"type":"Point"}
}
