{
  "type": "Feature",
  "properties": {
    "iso:country": "GB",
    "wof:name": "AB51 5BD",
    "wof:placetype": "postalcode"
  },
  "geometry": {"coordinates":[-2.465481,57.372791],"type":"Point"}
}
