{
  "type": "Feature",
  "properties": {
    "iso:country":"GB",
    "wof:name":"AB51 5BD",
    "wof:placetype":"postalcode"
},
  "geometry": {"coordinates":[-2.4654177784104,57.37210496079678],"type":"Point"}
}