{
  "type": "Feature",
  "properties": {
    "date:inception_lower":"1986-07-01",
    "date:inception_upper":"1986-07-31",
    "iso:country":"GB",
    "wof:name":"NE44 6ET",
    "wof:placetype":"postalcode"
},
  "geometry": {"coordinates":[-1.968464,54.948141],"type":"Point"}
}