{
  "type": "Feature",
  "properties": {
    "iso:country":"GB",
    "wof:name":"DY10 4BU",
    "wof:placetype":"postalcode"
},
  "geometry": {"coordinates":[-2.20499560445318,52.36100748166309],"type":"Point"}
}