{
  "type": "Feature",
  "properties": {
    "iso:country":"GB",
    "wof:name":"BL7 9SJ",
    "wof:placetype":"postalcode"
},
  "geometry": {"coordinates":[-2.44060157853845,53.62856638440243],"type":"Point"}
}