{
  "type": "Feature",
  "properties": {
    "iso:country": "GB",
    "wof:name": "RH20 3FU",
    "wof:placetype": "postalcode"
  },
  "geometry": {"coordinates":[-0.389752,50.929295],"type":"Point"}
}
