{
  "type": "Feature",
  "properties": {
    "iso:country":"GB",
    "wof:name":"NG24 3WE",
    "wof:placetype":"postalcode"
},
  "geometry": {"coordinates":[-0.76730181786127,53.04852155757509],"type":"Point"}
}