{
  "type": "Feature",
  "properties": {
    "date:inception_lower": "2012-10-01",
    "date:inception_upper": "2012-10-01",
    "iso:country": "GB",
    "wof:name": "NG24 3WE",
    "wof:placetype": "postalcode"
  },
  "geometry": {"coordinates":[-0.767302,53.048522],"type":"Point"}
}
