{
  "type": "Feature",
  "properties": {
    "date:inception_lower": "1980-01-01",
    "date:inception_upper": "1980-01-01",
    "iso:country": "GB",
    "wof:name": "DY1 4LP",
    "wof:placetype": "postalcode"
  },
  "geometry": {"coordinates":[-2.089209,52.531438],"type":"Point"}
}
