{
  "type": "Feature",
  "properties": {
    "iso:country":"GB",
    "wof:name":"NW11 9NE",
    "wof:placetype":"postalcode"
},
  "geometry": {"coordinates":[-0.20307006609904,51.57854634364917],"type":"Point"}
}