{
  "type": "Feature",
  "properties": {
    "date:inception_lower": "1980-01-01",
    "date:inception_upper": "1980-01-01",
    "iso:country": "GB",
    "wof:name": "NW11 9NE",
    "wof:placetype": "postalcode"
  },
  "geometry": {"coordinates":[-0.20307,51.578546],"type":"Point"}
}
