{
  "type": "Feature",
  "properties": {
    "date:inception_lower": "1991-09-01",
    "date:inception_upper": "1991-09-01",
    "iso:country": "GB",
    "wof:name": "SN15 3XW",
    "wof:placetype": "postalcode"
  },
  "geometry": {"coordinates":[-2.103781,51.45748],"type":"Point"}
}
