{
  "type": "Feature",
  "properties": {
    "iso:country": "GB",
    "wof:name": "EX6 7RS",
    "wof:placetype": "postalcode"
  },
  "geometry": {"coordinates":[-3.613019,50.706249],"type":"Point"}
}
