{
  "type": "Feature",
  "properties": {
    "iso:country": "GB",
    "wof:name": "EX6 7RS",
    "wof:placetype": "postalcode"
  },
  "geometry": {"coordinates":[-3.613716,50.705915],"type":"Point"}
}
