{
  "type": "Feature",
  "properties": {
    "date:inception_lower": "1980-01-01",
    "date:inception_upper": "1980-01-01",
    "iso:country": "GB",
    "wof:name": "S6 5QL",
    "wof:placetype": "postalcode"
  },
  "geometry": {"coordinates":[-1.532639,53.390839],"type":"Point"}
}
