{
  "type": "Feature",
  "properties": {
    "iso:country": "GB",
    "wof:name": "CV23 1BA",
    "wof:placetype": "postalcode"
  },
  "geometry": {"coordinates":[-1.190763,52.359998],"type":"Point"}
}
