{
  "type": "Feature",
  "properties": {
    "iso:country":"GB",
    "wof:name":"EX8 4JG",
    "wof:placetype":"postalcode"
},
  "geometry": {"coordinates":[-3.39489831897357,50.63648041546993],"type":"Point"}
}