{
  "type": "Feature",
  "properties": {
    "iso:country":"GB",
    "wof:name":"N4 4JP",
    "wof:placetype":"postalcode"
},
  "geometry": {"coordinates":[-0.11127458617395,51.57654730469623],"type":"Point"}
}