{
  "type": "Feature",
  "properties": {
    "iso:country": "GB",
    "wof:name": "PE10 0FS",
    "wof:placetype": "postalcode"
  },
  "geometry": {"coordinates":[-0.38195,52.757843],"type":"Point"}
}
