{
  "type": "Feature",
  "properties": {
    "iso:country":"GB",
    "wof:name":"PE10 0FS",
    "wof:placetype":"postalcode"
},
  "geometry": {"coordinates":[-0.38195004436696,52.7578427877384],"type":"Point"}
}