{
  "type": "Feature",
  "properties": {
    "iso:country":"GB",
    "wof:name":"AB25 3DH",
    "wof:placetype":"postalcode"
},
  "geometry": {"coordinates":[-2.11579255661866,57.16091738631206],"type":"Point"}
}