{
  "type": "Feature",
  "properties": {
    "iso:country": "GB",
    "wof:name": "LL14 3BN",
    "wof:placetype": "postalcode"
  },
  "geometry": {"coordinates":[-3.075215,52.974753],"type":"Point"}
}
