{
  "type": "Feature",
  "properties": {
    "iso:country":"GB",
    "wof:name":"LL14 3BN",
    "wof:placetype":"postalcode"
},
  "geometry": {"coordinates":[-3.07521534632413,52.97471135544951],"type":"Point"}
}