{
  "type": "Feature",
  "properties": {
    "date:inception_lower": "2018-08-01",
    "date:inception_upper": "2018-08-01",
    "iso:country": "GB",
    "wof:name": "NN13 5HA",
    "wof:placetype": "postalcode"
  },
  "geometry": {"coordinates":[-1.085331,52.066758],"type":"Point"}
}
