{
  "type": "Feature",
  "properties": {
    "date:inception_lower": "2022-12-01",
    "date:inception_upper": "2022-12-01",
    "iso:country": "GB",
    "wof:name": "B79 7BU",
    "wof:placetype": "postalcode"
  },
  "geometry": {"coordinates":[-1.727462,52.644873],"type":"Point"}
}
