{
  "type": "Feature",
  "properties": {
    "iso:country": "GB",
    "wof:name": "SA43 2RP",
    "wof:placetype": "postalcode"
  },
  "geometry": {"coordinates":[-4.577042,52.071295],"type":"Point"}
}
