{
  "type": "Feature",
  "properties": {
    "iso:country":"GB",
    "wof:name":"SA43 2RP",
    "wof:placetype":"postalcode"
},
  "geometry": {"coordinates":[-4.57704239298329,52.07129459598696],"type":"Point"}
}