{
  "type": "Feature",
  "properties": {
    "iso:country":"GB",
    "wof:name":"NE62 5ST",
    "wof:placetype":"postalcode"
},
  "geometry": {"coordinates":[-1.60251025707994,55.14952249037724],"type":"Point"}
}