{
  "type": "Feature",
  "properties": {
    "iso:country": "GB",
    "wof:name": "IG11 7XW",
    "wof:placetype": "postalcode"
  },
  "geometry": {"coordinates":[0.097836,51.531413],"type":"Point"}
}
