{
  "type": "Feature",
  "properties": {
    "date:inception_lower": "1980-01-01",
    "date:inception_upper": "1980-01-01",
    "iso:country": "GB",
    "wof:name": "NR5 0EA",
    "wof:placetype": "postalcode"
  },
  "geometry": {"coordinates":[1.235251,52.642494],"type":"Point"}
}
