{
  "type": "Feature",
  "properties": {
    "iso:country":"GB",
    "wof:name":"OX15 4RT",
    "wof:placetype":"postalcode"
},
  "geometry": {"coordinates":[-1.42221799508994,52.0066627836885],"type":"Point"}
}