{
  "type": "Feature",
  "properties": {
    "date:inception_lower": "1980-01-01",
    "date:inception_upper": "1980-01-01",
    "iso:country": "GB",
    "wof:name": "OX15 4RT",
    "wof:placetype": "postalcode"
  },
  "geometry": {"coordinates":[-1.422203,52.006673],"type":"Point"}
}
