{
  "type": "Feature",
  "properties": {
    "iso:country": "GB",
    "wof:name": "OX15 4RT",
    "wof:placetype": "postalcode"
  },
  "geometry": {"coordinates":[-1.422218,52.006663],"type":"Point"}
}
