{
  "type": "Feature",
  "properties": {
    "iso:country":"GB",
    "wof:name":"M21 0XG",
    "wof:placetype":"postalcode"
},
  "geometry": {"coordinates":[-2.26428588044607,53.4413815334003],"type":"Point"}
}