{
  "type": "Feature",
  "properties": {
    "date:inception_lower": "1994-12-01",
    "date:inception_upper": "1994-12-01",
    "iso:country": "GB",
    "wof:name": "SO14 3BL",
    "wof:placetype": "postalcode"
  },
  "geometry": {"coordinates":[-1.40115,50.90126],"type":"Point"}
}
