{
  "type": "Feature",
  "properties": {
    "iso:country":"GB",
    "wof:name":"HR1 3AT",
    "wof:placetype":"postalcode"
},
  "geometry": {"coordinates":[-2.68524326657199,52.10539584936586],"type":"Point"}
}