{
  "type": "Feature",
  "properties": {
    "date:inception_lower": "1994-05-01",
    "date:inception_upper": "1994-05-01",
    "iso:country": "GB",
    "wof:name": "BB7 9DZ",
    "wof:placetype": "postalcode"
  },
  "geometry": {"coordinates":[-2.33854,53.832794],"type":"Point"}
}
