{
  "type": "Feature",
  "properties": {
    "iso:country": "GB",
    "wof:name": "CB4 3BE",
    "wof:placetype": "postalcode"
  },
  "geometry": {"coordinates":[0.121638,52.214313],"type":"Point"}
}
