{
  "type": "Feature",
  "properties": {
    "date:inception_lower": "1980-01-01",
    "date:inception_upper": "1980-01-01",
    "iso:country": "GB",
    "wof:name": "LA14 3QL",
    "wof:placetype": "postalcode"
  },
  "geometry": {"coordinates":[-3.250497,54.111512],"type":"Point"}
}
