{
  "type": "Feature",
  "properties": {
    "iso:country":"GB",
    "wof:name":"EX10 8AJ",
    "wof:placetype":"postalcode"
},
  "geometry": {"coordinates":[-3.23717629216568,50.67884851016431],"type":"Point"}
}