{
  "type": "Feature",
  "properties": {
    "date:inception_lower": "1998-06-01",
    "date:inception_upper": "1998-06-01",
    "iso:country": "GB",
    "wof:name": "YO25 4ST",
    "wof:placetype": "postalcode"
  },
  "geometry": {"coordinates":[-0.38703,54.06309],"type":"Point"}
}
