{
  "type": "Feature",
  "properties": {
    "iso:country":"GB",
    "wof:name":"N20 9QD",
    "wof:placetype":"postalcode"
},
  "geometry": {"coordinates":[-0.17704436513178,51.63668504831157],"type":"Point"}
}