{
  "type": "Feature",
  "properties": {
    "iso:country": "GB",
    "wof:name": "TF9 3ND",
    "wof:placetype": "postalcode"
  },
  "geometry": {"coordinates":[-2.560078,52.866077],"type":"Point"}
}
