{
  "type": "Feature",
  "properties": {
    "iso:country":"GB",
    "wof:name":"TF9 3ND",
    "wof:placetype":"postalcode"
},
  "geometry": {"coordinates":[-2.56007782611982,52.86607676812071],"type":"Point"}
}