{
  "type": "Feature",
  "properties": {
    "date:inception_lower": "1980-01-01",
    "date:inception_upper": "1980-01-01",
    "iso:country": "GB",
    "wof:name": "DY2 0TX",
    "wof:placetype": "postalcode"
  },
  "geometry": {"coordinates":[-2.104099,52.498301],"type":"Point"}
}
