{
  "type": "Feature",
  "properties": {
    "iso:country":"GB",
    "wof:name":"DE13 0DX",
    "wof:placetype":"postalcode"
},
  "geometry": {"coordinates":[-1.62761926437387,52.83090287949457],"type":"Point"}
}