{
  "type": "Feature",
  "properties": {
    "iso:country": "GB",
    "wof:name": "DE13 0DX",
    "wof:placetype": "postalcode"
  },
  "geometry": {"coordinates":[-1.627619,52.830903],"type":"Point"}
}
