{
  "type": "Feature",
  "properties": {
    "iso:country": "GB",
    "wof:name": "SP10 4NQ",
    "wof:placetype": "postalcode"
  },
  "geometry": {"coordinates":[-1.487512,51.226694],"type":"Point"}
}
