{
  "type": "Feature",
  "properties": {
    "date:inception_lower":"1999-06-01",
    "date:inception_upper":"1999-06-30",
    "iso:country":"GB",
    "wof:name":"SP10 4NQ",
    "wof:placetype":"postalcode"
},
  "geometry": {"coordinates":[-1.487512,51.226694],"type":"Point"}
}