{
  "type": "Feature",
  "properties": {
    "iso:country":"GB",
    "wof:name":"SP10 4NQ",
    "wof:placetype":"postalcode"
},
  "geometry": {"coordinates":[-1.48751233811793,51.22669407106819],"type":"Point"}
}