{
  "type": "Feature",
  "properties": {
    "date:inception_lower": "2007-09-01",
    "date:inception_upper": "2007-09-01",
    "iso:country": "GB",
    "wof:name": "BS5 9BY",
    "wof:placetype": "postalcode"
  },
  "geometry": {"coordinates":[-2.560708,51.457335],"type":"Point"}
}
