{
  "type": "Feature",
  "properties": {
    "iso:country":"GB",
    "wof:name":"BS5 9BY",
    "wof:placetype":"postalcode"
},
  "geometry": {"coordinates":[-2.56070799798376,51.45733508083831],"type":"Point"}
}