{
  "type": "Feature",
  "properties": {
    "iso:country": "GB",
    "wof:name": "NG20 0PY",
    "wof:placetype": "postalcode"
  },
  "geometry": {"coordinates":[-1.147292,53.20314],"type":"Point"}
}
