{
  "type": "Feature",
  "properties": {
    "date:inception_lower":"2007-05-01",
    "date:inception_upper":"2007-05-31",
    "iso:country":"GB",
    "wof:name":"PE13 5RN",
    "wof:placetype":"postalcode"
},
  "geometry": {"coordinates":[0.128872,52.744172],"type":"Point"}
}