{
  "type": "Feature",
  "properties": {
    "iso:country": "GB",
    "wof:name": "BL1 7AB",
    "wof:placetype": "postalcode"
  },
  "geometry": {"coordinates":[-2.432339,53.604247],"type":"Point"}
}
