{
  "type": "Feature",
  "properties": {
    "iso:country":"GB",
    "wof:name":"SG13 9SP",
    "wof:placetype":"postalcode"
},
  "geometry": {"coordinates":[-0.08197135792016,51.79301220524361],"type":"Point"}
}