{
  "type": "Feature",
  "properties": {
    "iso:country":"GB",
    "wof:name":"L13 9BB",
    "wof:placetype":"postalcode"
},
  "geometry": {"coordinates":[-2.93723884385578,53.4316316660454],"type":"Point"}
}