{
  "type": "Feature",
  "properties": {
    "iso:country":"GB",
    "wof:name":"SW19 7QH",
    "wof:placetype":"postalcode"
},
  "geometry": {"coordinates":[-0.20621841133218,51.42511139711442],"type":"Point"}
}