{
  "type": "Feature",
  "properties": {
    "iso:country":"GB",
    "wof:name":"MK16 9JY",
    "wof:placetype":"postalcode"
},
  "geometry": {"coordinates":[-0.63153830358687,52.1274839780286],"type":"Point"}
}