{
  "type": "Feature",
  "properties": {
    "iso:country":"GB",
    "wof:name":"SN15 1UB",
    "wof:placetype":"postalcode"
},
  "geometry": {"coordinates":[-2.11130749794503,51.46904504638033],"type":"Point"}
}