{
  "type": "Feature",
  "properties": {
    "iso:country": "GB",
    "wof:name": "SN15 1UB",
    "wof:placetype": "postalcode"
  },
  "geometry": {"coordinates":[-2.111317,51.46908],"type":"Point"}
}
