{
  "type": "Feature",
  "properties": {
    "date:inception_lower":"1997-06-01",
    "date:inception_upper":"1997-06-30",
    "iso:country":"GB",
    "wof:name":"SN15 1UB",
    "wof:placetype":"postalcode"
},
  "geometry": {"coordinates":[-2.111307,51.469045],"type":"Point"}
}