{
  "type": "Feature",
  "properties": {
    "date:inception_lower": "1980-01-01",
    "date:inception_upper": "1980-01-01",
    "iso:country": "GB",
    "wof:name": "WS3 3DL",
    "wof:placetype": "postalcode"
  },
  "geometry": {"coordinates":[-1.98932,52.627117],"type":"Point"}
}
