{
  "type": "Feature",
  "properties": {
    "iso:country":"GB",
    "wof:name":"WS3 3DL",
    "wof:placetype":"postalcode"
},
  "geometry": {"coordinates":[-1.9893200861665,52.62711657168932],"type":"Point"}
}