{
  "type": "Feature",
  "properties": {
    "date:inception_lower":"1994-05-01",
    "date:inception_upper":"1994-05-31",
    "iso:country":"GB",
    "wof:name":"SY21 0AS",
    "wof:placetype":"postalcode"
},
  "geometry": {"coordinates":[-3.432076,52.674711],"type":"Point"}
}