{
  "type": "Feature",
  "properties": {
    "iso:country":"GB",
    "wof:name":"SY21 0AS",
    "wof:placetype":"postalcode"
},
  "geometry": {"coordinates":[-3.4320036396822,52.67475699627955],"type":"Point"}
}