{
  "type": "Feature",
  "properties": {
    "iso:country":"GB",
    "wof:name":"LL11 4AX",
    "wof:placetype":"postalcode"
},
  "geometry": {"coordinates":[-3.01341266170837,53.06695651301474],"type":"Point"}
}