{
  "type": "Feature",
  "properties": {
    "date:inception_lower": "2006-05-01",
    "date:inception_upper": "2006-05-01",
    "iso:country": "GB",
    "wof:name": "LL11 4AX",
    "wof:placetype": "postalcode"
  },
  "geometry": {"coordinates":[-3.013413,53.066957],"type":"Point"}
}
