{
  "type": "Feature",
  "properties": {
    "iso:country": "GB",
    "wof:name": "LL11 4AX",
    "wof:placetype": "postalcode"
  },
  "geometry": {"coordinates":[-3.013413,53.066957],"type":"Point"}
}
