{
  "type": "Feature",
  "properties": {
    "iso:country":"GB",
    "wof:name":"DG16 5BT",
    "wof:placetype":"postalcode"
},
  "geometry": {"coordinates":[-3.06517599757948,54.99136669607532],"type":"Point"}
}