{
  "type": "Feature",
  "properties": {
    "iso:country":"GB",
    "wof:name":"PA29 6XN",
    "wof:placetype":"postalcode"
},
  "geometry": {"coordinates":[-5.56443680606187,55.76421695837759],"type":"Point"}
}