{
  "type": "Feature",
  "properties": {
    "date:inception_lower": "1980-01-01",
    "date:inception_upper": "1980-01-01",
    "iso:country": "GB",
    "wof:name": "PA29 6XN",
    "wof:placetype": "postalcode"
  },
  "geometry": {"coordinates":[-5.564437,55.764217],"type":"Point"}
}
