{
  "type": "Feature",
  "properties": {
    "iso:country":"GB",
    "wof:name":"DL14 8HH",
    "wof:placetype":"postalcode"
},
  "geometry": {"coordinates":[-1.62482206123444,54.66450955717179],"type":"Point"}
}