{
  "type": "Feature",
  "properties": {
    "iso:country": "GB",
    "wof:name": "DL14 8HH",
    "wof:placetype": "postalcode"
  },
  "geometry": {"coordinates":[-1.624822,54.66451],"type":"Point"}
}
