{
  "type": "Feature",
  "properties": {
    "iso:country":"GB",
    "wof:name":"PR26 7XB",
    "wof:placetype":"postalcode"
},
  "geometry": {"coordinates":[-2.7334382220819,53.68872710345747],"type":"Point"}
}