{
  "type": "Feature",
  "properties": {
    "iso:country":"GB",
    "wof:name":"YO42 2BQ",
    "wof:placetype":"postalcode"
},
  "geometry": {"coordinates":[-0.77758591601944,53.93270632909064],"type":"Point"}
}