{
  "type": "Feature",
  "properties": {
    "iso:country": "GB",
    "wof:name": "YO42 2BQ",
    "wof:placetype": "postalcode"
  },
  "geometry": {"coordinates":[-0.777586,53.932706],"type":"Point"}
}
