{
  "type": "Feature",
  "properties": {
    "iso:country":"GB",
    "wof:name":"EH21 7TA",
    "wof:placetype":"postalcode"
},
  "geometry": {"coordinates":[-3.04893330232543,55.93592798347268],"type":"Point"}
}