{
  "type": "Feature",
  "properties": {
    "iso:country":"GB",
    "wof:name":"IP11 0XP",
    "wof:placetype":"postalcode"
},
  "geometry": {"coordinates":[1.31903237669201,51.98211793480297],"type":"Point"}
}