{
  "type": "Feature",
  "properties": {
    "iso:country": "GB",
    "wof:name": "MK41 7JS",
    "wof:placetype": "postalcode"
  },
  "geometry": {"coordinates":[-0.457785,52.151064],"type":"Point"}
}
