{
  "type": "Feature",
  "properties": {
    "iso:country":"GB",
    "wof:name":"MK41 7JS",
    "wof:placetype":"postalcode"
},
  "geometry": {"coordinates":[-0.45778527775848,52.15106376488848],"type":"Point"}
}