{
  "type": "Feature",
  "properties": {
    "iso:country": "GB",
    "wof:name": "GU27 3QJ",
    "wof:placetype": "postalcode"
  },
  "geometry": {"coordinates":[-0.748014,51.084616],"type":"Point"}
}
