{
  "type": "Feature",
  "properties": {
    "iso:country":"GB",
    "wof:name":"GU27 3QJ",
    "wof:placetype":"postalcode"
},
  "geometry": {"coordinates":[-0.74801451433697,51.08461557260802],"type":"Point"}
}