{
  "type": "Feature",
  "properties": {
    "iso:country":"GB",
    "wof:name":"OX4 6BQ",
    "wof:placetype":"postalcode"
},
  "geometry": {"coordinates":[-1.19980012664464,51.72341020167342],"type":"Point"}
}