{
  "type": "Feature",
  "properties": {
    "iso:country": "GB",
    "wof:name": "OX4 6BQ",
    "wof:placetype": "postalcode"
  },
  "geometry": {"coordinates":[-1.1998,51.72341],"type":"Point"}
}
