{
  "type": "Feature",
  "properties": {
    "iso:country":"GB",
    "wof:name":"BH22 9AG",
    "wof:placetype":"postalcode"
},
  "geometry": {"coordinates":[-1.89214720838802,50.80028437612362],"type":"Point"}
}