{
  "type": "Feature",
  "properties": {
    "iso:country":"GB",
    "wof:name":"HP20 2FF",
    "wof:placetype":"postalcode"
},
  "geometry": {"coordinates":[-0.81196489838326,51.82869316234516],"type":"Point"}
}