{
  "type": "Feature",
  "properties": {
    "iso:country": "GB",
    "wof:name": "GU33 6HL",
    "wof:placetype": "postalcode"
  },
  "geometry": {"coordinates":[-0.912547,51.077193],"type":"Point"}
}
