{
  "type": "Feature",
  "properties": {
    "iso:country":"GB",
    "wof:name":"GU33 6HL",
    "wof:placetype":"postalcode"
},
  "geometry": {"coordinates":[-0.91274812202692,51.07725296961227],"type":"Point"}
}