{
  "type": "Feature",
  "properties": {
    "date:inception_lower":"1992-08-01",
    "date:inception_upper":"1992-08-31",
    "iso:country":"GB",
    "wof:name":"GU33 6HL",
    "wof:placetype":"postalcode"
},
  "geometry": {"coordinates":[-0.912547,51.077193],"type":"Point"}
}