{
  "type": "Feature",
  "properties": {
    "iso:country":"GB",
    "wof:name":"NR12 8SU",
    "wof:placetype":"postalcode"
},
  "geometry": {"coordinates":[1.37545325934786,52.69900851839709],"type":"Point"}
}