{
  "type": "Feature",
  "properties": {
    "iso:country":"GB",
    "wof:name":"PO21 3RX",
    "wof:placetype":"postalcode"
},
  "geometry": {"coordinates":[-0.70998734322424,50.78749365975261],"type":"Point"}
}