{
  "type": "Feature",
  "properties": {
    "date:inception_lower":"1980-01-01",
    "date:inception_upper":"1980-01-31",
    "iso:country":"GB",
    "wof:name":"PO21 3RX",
    "wof:placetype":"postalcode"
},
  "geometry": {"coordinates":[-0.709987,50.787494],"type":"Point"}
}