{
  "type": "Feature",
  "properties": {
    "iso:country":"GB",
    "wof:name":"CF44 6AN",
    "wof:placetype":"postalcode"
},
  "geometry": {"coordinates":[-3.41533920832637,51.68972224473367],"type":"Point"}
}