{
  "type": "Feature",
  "properties": {
    "date:inception_lower":"2003-06-01",
    "date:inception_upper":"2003-06-30",
    "iso:country":"GB",
    "wof:name":"IP4 1JF",
    "wof:placetype":"postalcode"
},
  "geometry": {"coordinates":[1.161408,52.054543],"type":"Point"}
}