{
  "type": "Feature",
  "properties": {
    "iso:country":"GB",
    "wof:name":"SA44 4AR",
    "wof:placetype":"postalcode"
},
  "geometry": {"coordinates":[-4.31816338317614,52.03622604784473],"type":"Point"}
}