{
  "type": "Feature",
  "properties": {
    "date:inception_lower": "2024-01-01",
    "date:inception_upper": "2024-01-01",
    "iso:country": "GB",
    "wof:name": "SA44 4AR",
    "wof:placetype": "postalcode"
  },
  "geometry": {"coordinates":[-4.317873,52.036442],"type":"Point"}
}
