{
  "type": "Feature",
  "properties": {
    "iso:country":"GB",
    "wof:name":"EH7 5NE",
    "wof:placetype":"postalcode"
},
  "geometry": {"coordinates":[-3.17833964760735,55.9611303267684],"type":"Point"}
}