{
  "type": "Feature",
  "properties": {
    "date:inception_lower":"2001-12-01",
    "date:inception_upper":"2001-12-31",
    "iso:country":"GB",
    "wof:name":"EH7 5NE",
    "wof:placetype":"postalcode"
},
  "geometry": {"coordinates":[-3.17834,55.96113],"type":"Point"}
}