{
  "type": "Feature",
  "properties": {
    "date:inception_lower": "2001-12-01",
    "date:inception_upper": "2001-12-01",
    "iso:country": "GB",
    "wof:name": "EH7 5NE",
    "wof:placetype": "postalcode"
  },
  "geometry": {"coordinates":[-3.178807,55.961175],"type":"Point"}
}
