{
  "type": "Feature",
  "properties": {
    "iso:country": "GB",
    "wof:name": "EH7 5NE",
    "wof:placetype": "postalcode"
  },
  "geometry": {"coordinates":[-3.17834,55.96113],"type":"Point"}
}
