{
  "type": "Feature",
  "properties": {
    "date:inception_lower": "1982-03-01",
    "date:inception_upper": "1982-03-01",
    "iso:country": "GB",
    "wof:name": "OL16 1DY",
    "wof:placetype": "postalcode"
  },
  "geometry": {"coordinates":[-2.155342,53.619588],"type":"Point"}
}
