{
  "type": "Feature",
  "properties": {
    "iso:country": "GB",
    "wof:name": "HP20 2TF",
    "wof:placetype": "postalcode"
  },
  "geometry": {"coordinates":[-0.820604,51.815734],"type":"Point"}
}
