{
  "type": "Feature",
  "properties": {
    "iso:country":"GB",
    "wof:name":"HP20 2TF",
    "wof:placetype":"postalcode"
},
  "geometry": {"coordinates":[-0.82060389342901,51.81573355198176],"type":"Point"}
}