{
  "type": "Feature",
  "properties": {
    "iso:country":"GB",
    "wof:name":"GL56 0YJ",
    "wof:placetype":"postalcode"
},
  "geometry": {"coordinates":[-1.63775499878138,51.94009141879715],"type":"Point"}
}