{
  "type": "Feature",
  "properties": {
    "date:inception_lower": "1980-01-01",
    "date:inception_upper": "1980-01-01",
    "iso:country": "GB",
    "wof:name": "GL56 0YJ",
    "wof:placetype": "postalcode"
  },
  "geometry": {"coordinates":[-1.637755,51.940091],"type":"Point"}
}
