{
  "type": "Feature",
  "properties": {
    "iso:country":"GB",
    "wof:name":"CM1 6LY",
    "wof:placetype":"postalcode"
},
  "geometry": {"coordinates":[0.49036865150546,51.74896882586237],"type":"Point"}
}