{
  "type": "Feature",
  "properties": {
    "iso:country":"GB",
    "wof:name":"ME17 4LU",
    "wof:placetype":"postalcode"
},
  "geometry": {"coordinates":[0.53117524271805,51.23400449291377],"type":"Point"}
}