{
  "type": "Feature",
  "properties": {
    "iso:country":"GB",
    "wof:name":"BD5 8HH",
    "wof:placetype":"postalcode"
},
  "geometry": {"coordinates":[-1.74896814342302,53.77158635337084],"type":"Point"}
}