{
  "type": "Feature",
  "properties": {
    "date:inception_lower":"2008-03-01",
    "date:inception_upper":"2008-03-31",
    "iso:country":"GB",
    "wof:name":"BD5 8HH",
    "wof:placetype":"postalcode"
},
  "geometry": {"coordinates":[-1.748968,53.771586],"type":"Point"}
}