{
  "type": "Feature",
  "properties": {
    "date:inception_lower": "1980-01-01",
    "date:inception_upper": "1980-01-01",
    "iso:country": "GB",
    "wof:name": "NN7 3PB",
    "wof:placetype": "postalcode"
  },
  "geometry": {"coordinates":[-1.012637,52.210975],"type":"Point"}
}
