{
  "type": "Feature",
  "properties": {
    "iso:country":"GB",
    "wof:name":"G62 7QU",
    "wof:placetype":"postalcode"
},
  "geometry": {"coordinates":[-4.33503467839371,55.94143598721487],"type":"Point"}
}