{
  "type": "Feature",
  "properties": {
    "iso:country": "GB",
    "wof:name": "G62 7QU",
    "wof:placetype": "postalcode"
  },
  "geometry": {"coordinates":[-4.335035,55.941436],"type":"Point"}
}
