{
  "type": "Feature",
  "properties": {
    "iso:country":"GB",
    "wof:name":"PO12 1LD",
    "wof:placetype":"postalcode"
},
  "geometry": {"coordinates":[-1.1331278426837,50.79760087214665],"type":"Point"}
}