{
  "type": "Feature",
  "properties": {
    "date:inception_lower": "1984-10-01",
    "date:inception_upper": "1984-10-01",
    "iso:country": "GB",
    "wof:name": "PO12 1LD",
    "wof:placetype": "postalcode"
  },
  "geometry": {"coordinates":[-1.133128,50.797601],"type":"Point"}
}
