{
  "type": "Feature",
  "properties": {
    "iso:country":"GB",
    "wof:name":"DA4 0JS",
    "wof:placetype":"postalcode"
},
  "geometry": {"coordinates":[0.20415425620851,51.38705852955066],"type":"Point"}
}