{
  "type": "Feature",
  "properties": {
    "iso:country":"GB",
    "wof:name":"SA7 9NR",
    "wof:placetype":"postalcode"
},
  "geometry": {"coordinates":[-3.8762394686653,51.67580807552695],"type":"Point"}
}