{
  "type": "Feature",
  "properties": {
    "iso:country": "GB",
    "wof:name": "SW11 6RS",
    "wof:placetype": "postalcode"
  },
  "geometry": {"coordinates":[-0.162157,51.45923],"type":"Point"}
}
