{
  "type": "Feature",
  "properties": {
    "iso:country":"GB",
    "wof:name":"SW11 6RS",
    "wof:placetype":"postalcode"
},
  "geometry": {"coordinates":[-0.16215694876909,51.45923006614535],"type":"Point"}
}