{
  "type": "Feature",
  "properties": {
    "iso:country": "GB",
    "wof:name": "ST5 6PD",
    "wof:placetype": "postalcode"
  },
  "geometry": {"coordinates":[-2.264313,53.013207],"type":"Point"}
}
