{
  "type": "Feature",
  "properties": {
    "iso:country":"GB",
    "wof:name":"RH2 7RE",
    "wof:placetype":"postalcode"
},
  "geometry": {"coordinates":[-0.19654802580864,51.22031592553973],"type":"Point"}
}