{
  "type": "Feature",
  "properties": {
    "iso:country": "GB",
    "wof:name": "KY6 3AN",
    "wof:placetype": "postalcode"
  },
  "geometry": {"coordinates":[-3.211445,56.20105],"type":"Point"}
}
