{
  "type": "Feature",
  "properties": {
    "iso:country":"GB",
    "wof:name":"LL55 4HA",
    "wof:placetype":"postalcode"
},
  "geometry": {"coordinates":[-4.12665679888864,53.12045610845981],"type":"Point"}
}