{
  "type": "Feature",
  "properties": {
    "date:inception_lower": "1980-01-01",
    "date:inception_upper": "1980-01-01",
    "iso:country": "GB",
    "wof:name": "LL55 4HA",
    "wof:placetype": "postalcode"
  },
  "geometry": {"coordinates":[-4.126657,53.120456],"type":"Point"}
}
