{
  "type": "Feature",
  "properties": {
    "iso:country":"GB",
    "wof:name":"RH10 0ZY",
    "wof:placetype":"postalcode"
},
  "geometry": {"coordinates":[-0.1841560707042,51.11701127289477],"type":"Point"}
}