{
  "type": "Feature",
  "properties": {
    "iso:country": "GB",
    "wof:name": "RH10 0ZY",
    "wof:placetype": "postalcode"
  },
  "geometry": {"coordinates":[-0.184156,51.117011],"type":"Point"}
}
