{
  "type": "Feature",
  "properties": {
    "iso:country":"GB",
    "wof:name":"NE15 7HT",
    "wof:placetype":"postalcode"
},
  "geometry": {"coordinates":[-1.69072576201757,54.97851186059051],"type":"Point"}
}