{
  "type": "Feature",
  "properties": {
    "iso:country":"GB",
    "wof:name":"N6 4ED",
    "wof:placetype":"postalcode"
},
  "geometry": {"coordinates":[-0.15504316242551,51.5798513879123],"type":"Point"}
}