{
  "type": "Feature",
  "properties": {
    "date:inception_lower": "1980-01-01",
    "date:inception_upper": "1980-01-01",
    "iso:country": "GB",
    "wof:name": "PO16 8QG",
    "wof:placetype": "postalcode"
  },
  "geometry": {"coordinates":[-1.143688,50.850232],"type":"Point"}
}
