{
  "type": "Feature",
  "properties": {
    "iso:country":"GB",
    "wof:name":"PO16 8QG",
    "wof:placetype":"postalcode"
},
  "geometry": {"coordinates":[-1.14368774890334,50.85023224573268],"type":"Point"}
}