{
  "type": "Feature",
  "properties": {
    "iso:country": "GB",
    "wof:name": "NR11 8NA",
    "wof:placetype": "postalcode"
  },
  "geometry": {"coordinates":[1.297301,52.88851],"type":"Point"}
}
