{
  "type": "Feature",
  "properties": {
    "iso:country":"GB",
    "wof:name":"YO17 8JS",
    "wof:placetype":"postalcode"
},
  "geometry": {"coordinates":[-0.69860592516829,54.15818406442733],"type":"Point"}
}