{
  "type": "Feature",
  "properties": {
    "iso:country":"GB",
    "wof:name":"LE3 8EJ",
    "wof:placetype":"postalcode"
},
  "geometry": {"coordinates":[-1.18885754275264,52.65198623666119],"type":"Point"}
}