{
  "type": "Feature",
  "properties": {
    "iso:country":"GB",
    "wof:name":"WF3 3EH",
    "wof:placetype":"postalcode"
},
  "geometry": {"coordinates":[-1.53297560346117,53.73867273082124],"type":"Point"}
}