{
  "type": "Feature",
  "properties": {
    "date:inception_lower":"1980-01-01",
    "date:inception_upper":"1980-01-31",
    "iso:country":"GB",
    "wof:name":"EH3 8AA",
    "wof:placetype":"postalcode"
},
  "geometry": {"coordinates":[-3.210991,55.943346],"type":"Point"}
}