{
  "type": "Feature",
  "properties": {
    "iso:country": "GB",
    "wof:name": "EH3 8AA",
    "wof:placetype": "postalcode"
  },
  "geometry": {"coordinates":[-3.210991,55.943346],"type":"Point"}
}
