{
  "type": "Feature",
  "properties": {
    "iso:country": "GB",
    "wof:name": "DN20 0JH",
    "wof:placetype": "postalcode"
  },
  "geometry": {"coordinates":[-0.54212,53.56726],"type":"Point"}
}
