{
  "type": "Feature",
  "properties": {
    "date:inception_lower": "1980-01-01",
    "date:inception_upper": "1980-01-01",
    "iso:country": "GB",
    "wof:name": "DN20 0JH",
    "wof:placetype": "postalcode"
  },
  "geometry": {"coordinates":[-0.54212,53.56726],"type":"Point"}
}
