{
  "type": "Feature",
  "properties": {
    "date:inception_lower":"1983-03-01",
    "date:inception_upper":"1983-03-31",
    "iso:country":"GB",
    "wof:name":"RH11 9PS",
    "wof:placetype":"postalcode"
},
  "geometry": {"coordinates":[-0.200245,51.093105],"type":"Point"}
}