{
  "type": "Feature",
  "properties": {
    "iso:country":"GB",
    "wof:name":"RH11 9PS",
    "wof:placetype":"postalcode"
},
  "geometry": {"coordinates":[-0.20024464241943,51.09310480515405],"type":"Point"}
}