{
  "type": "Feature",
  "properties": {
    "iso:country":"GB",
    "wof:name":"SN4 0SH",
    "wof:placetype":"postalcode"
},
  "geometry": {"coordinates":[-1.77996736567609,51.51538719589565],"type":"Point"}
}