{
  "type": "Feature",
  "properties": {
    "iso:country":"GB",
    "wof:name":"GU21 4HX",
    "wof:placetype":"postalcode"
},
  "geometry": {"coordinates":[-0.5622863123437,51.32710286898251],"type":"Point"}
}