{
  "type": "Feature",
  "properties": {
    "date:inception_lower": "1980-01-01",
    "date:inception_upper": "1980-01-01",
    "iso:country": "GB",
    "wof:name": "GU21 4HX",
    "wof:placetype": "postalcode"
  },
  "geometry": {"coordinates":[-0.561569,51.326949],"type":"Point"}
}
