{
  "type": "Feature",
  "properties": {
    "iso:country":"GB",
    "wof:name":"CR0 7JZ",
    "wof:placetype":"postalcode"
},
  "geometry": {"coordinates":[-0.06690076465771,51.37581032134403],"type":"Point"}
}