{
  "type": "Feature",
  "properties": {
    "date:inception_lower": "1980-01-01",
    "date:inception_upper": "1980-01-01",
    "iso:country": "GB",
    "wof:name": "BL3 6SD",
    "wof:placetype": "postalcode"
  },
  "geometry": {"coordinates":[-2.43617,53.568397],"type":"Point"}
}
