{
  "type": "Feature",
  "properties": {
    "iso:country":"GB",
    "wof:name":"LU3 3DP",
    "wof:placetype":"postalcode"
},
  "geometry": {"coordinates":[-0.46234919447519,51.91426217857016],"type":"Point"}
}