{
  "type": "Feature",
  "properties": {
    "iso:country":"GB",
    "wof:name":"IP3 9AG",
    "wof:placetype":"postalcode"
},
  "geometry": {"coordinates":[1.18176337765308,52.04494665755267],"type":"Point"}
}