{
  "type": "Feature",
  "properties": {
    "iso:country": "GB",
    "wof:name": "LL18 5BE",
    "wof:placetype": "postalcode"
  },
  "geometry": {"coordinates":[-3.511766,53.311789],"type":"Point"}
}
