{
  "type": "Feature",
  "properties": {
    "iso:country": "GB",
    "wof:name": "WS8 6AP",
    "wof:placetype": "postalcode"
  },
  "geometry": {"coordinates":[-1.924193,52.647347],"type":"Point"}
}
