{
  "type": "Feature",
  "properties": {
    "iso:country":"GB",
    "wof:name":"OX20 1NB",
    "wof:placetype":"postalcode"
},
  "geometry": {"coordinates":[-1.34330698545436,51.84773011539895],"type":"Point"}
}