{
  "type": "Feature",
  "properties": {
    "iso:country": "GB",
    "wof:name": "OX20 1NB",
    "wof:placetype": "postalcode"
  },
  "geometry": {"coordinates":[-1.343307,51.84773],"type":"Point"}
}
