{
  "type": "Feature",
  "properties": {
    "iso:country": "GB",
    "wof:name": "NE8 1UT",
    "wof:placetype": "postalcode"
  },
  "geometry": {"coordinates":[-1.615033,54.953377],"type":"Point"}
}
