{
  "type": "Feature",
  "properties": {
    "iso:country":"GB",
    "wof:name":"TR18 4AD",
    "wof:placetype":"postalcode"
},
  "geometry": {"coordinates":[-5.5365678439754,50.11807743895444],"type":"Point"}
}