{
  "type": "Feature",
  "properties": {
    "iso:country":"GB",
    "wof:name":"SW4 8QL",
    "wof:placetype":"postalcode"
},
  "geometry": {"coordinates":[-0.14013052551764,51.4514907979903],"type":"Point"}
}