{
  "type": "Feature",
  "properties": {
    "iso:country": "GB",
    "wof:name": "ML12 6EP",
    "wof:placetype": "postalcode"
  },
  "geometry": {"coordinates":[-3.53144,55.620814],"type":"Point"}
}
