{
  "type": "Feature",
  "properties": {
    "iso:country":"GB",
    "wof:name":"SL2 3RY",
    "wof:placetype":"postalcode"
},
  "geometry": {"coordinates":[-0.62290911267919,51.53824740061624],"type":"Point"}
}