{
  "type": "Feature",
  "properties": {
    "iso:country":"GB",
    "wof:name":"PA1 1YN",
    "wof:placetype":"postalcode"
},
  "geometry": {"coordinates":[-4.42383974028534,55.84203142384818],"type":"Point"}
}