{
  "type": "Feature",
  "properties": {
    "iso:country":"GB",
    "wof:name":"AB52 6WZ",
    "wof:placetype":"postalcode"
},
  "geometry": {"coordinates":[-2.61012659779892,57.33898646046008],"type":"Point"}
}