{
  "type": "Feature",
  "properties": {
    "iso:country": "GB",
    "wof:name": "SN7 7BH",
    "wof:placetype": "postalcode"
  },
  "geometry": {"coordinates":[-1.578901,51.656309],"type":"Point"}
}
