{
  "type": "Feature",
  "properties": {
    "iso:country":"GB",
    "wof:name":"SN7 7BH",
    "wof:placetype":"postalcode"
},
  "geometry": {"coordinates":[-1.57890138507337,51.65630870537215],"type":"Point"}
}