{
  "type": "Feature",
  "properties": {
    "iso:country":"GB",
    "wof:name":"DE22 2LU",
    "wof:placetype":"postalcode"
},
  "geometry": {"coordinates":[-1.4997812896247,52.9483566232616],"type":"Point"}
}