{
  "type": "Feature",
  "properties": {
    "iso:country":"GB",
    "wof:name":"PE9 4UB",
    "wof:placetype":"postalcode"
},
  "geometry": {"coordinates":[-0.42587160486932,52.6575512665158],"type":"Point"}
}