{
  "type": "Feature",
  "properties": {
    "date:inception_lower": "1990-02-01",
    "date:inception_upper": "1990-02-01",
    "iso:country": "GB",
    "wof:name": "PE9 4UB",
    "wof:placetype": "postalcode"
  },
  "geometry": {"coordinates":[-0.425872,52.657551],"type":"Point"}
}
