{
  "type": "Feature",
  "properties": {
    "iso:country":"GB",
    "wof:name":"TA19 9AQ",
    "wof:placetype":"postalcode"
},
  "geometry": {"coordinates":[-2.91739141248465,50.92979855754533],"type":"Point"}
}