{
  "type": "Feature",
  "properties": {
    "date:inception_lower": "1980-01-01",
    "date:inception_upper": "1980-01-01",
    "iso:country": "GB",
    "wof:name": "TA19 9AQ",
    "wof:placetype": "postalcode"
  },
  "geometry": {"coordinates":[-2.917391,50.929799],"type":"Point"}
}
