{
  "type": "Feature",
  "properties": {
    "date:inception_lower": "1980-01-01",
    "date:inception_upper": "1980-01-01",
    "iso:country": "GB",
    "wof:name": "HD4 5QB",
    "wof:placetype": "postalcode"
  },
  "geometry": {"coordinates":[-1.819678,53.635067],"type":"Point"}
}
