{
  "type": "Feature",
  "properties": {
    "iso:country":"GB",
    "wof:name":"E14 7GX",
    "wof:placetype":"postalcode"
},
  "geometry": {"coordinates":[-0.03420941939189,51.51625425570946],"type":"Point"}
}