{
  "type": "Feature",
  "properties": {
    "iso:country":"GB",
    "wof:name":"DY11 5HW",
    "wof:placetype":"postalcode"
},
  "geometry": {"coordinates":[-2.26048646691275,52.39807228857163],"type":"Point"}
}