{
  "type": "Feature",
  "properties": {
    "iso:country": "GB",
    "wof:name": "B28 9LA",
    "wof:placetype": "postalcode"
  },
  "geometry": {"coordinates":[-1.83546,52.43203],"type":"Point"}
}
