{
  "type": "Feature",
  "properties": {
    "date:inception_lower": "1980-01-01",
    "date:inception_upper": "1980-01-01",
    "iso:country": "GB",
    "wof:name": "B28 9LA",
    "wof:placetype": "postalcode"
  },
  "geometry": {"coordinates":[-1.83546,52.43203],"type":"Point"}
}
