{
  "type": "Feature",
  "properties": {
    "iso:country":"GB",
    "wof:name":"B28 9LA",
    "wof:placetype":"postalcode"
},
  "geometry": {"coordinates":[-1.83546044248522,52.43203037532277],"type":"Point"}
}