{
  "type": "Feature",
  "properties": {
    "iso:country":"GB",
    "wof:name":"M43 7GP",
    "wof:placetype":"postalcode"
},
  "geometry": {"coordinates":[-2.13649034714227,53.488614836328],"type":"Point"}
}