{
  "type": "Feature",
  "properties": {
    "iso:country": "GB",
    "wof:name": "LE17 4DD",
    "wof:placetype": "postalcode"
  },
  "geometry": {"coordinates":[-1.203607,52.452489],"type":"Point"}
}
