{
  "type": "Feature",
  "properties": {
    "iso:country":"GB",
    "wof:name":"LE17 4DD",
    "wof:placetype":"postalcode"
},
  "geometry": {"coordinates":[-1.20360736849519,52.45248865523986],"type":"Point"}
}