{
  "type": "Feature",
  "properties": {
    "iso:country": "GB",
    "wof:name": "CO4 5XT",
    "wof:placetype": "postalcode"
  },
  "geometry": {"coordinates":[0.899493,51.906631],"type":"Point"}
}
