{
  "type": "Feature",
  "properties": {
    "iso:country":"GB",
    "wof:name":"CO4 5XT",
    "wof:placetype":"postalcode"
},
  "geometry": {"coordinates":[0.8994926443127,51.90663097138889],"type":"Point"}
}