{
  "type": "Feature",
  "properties": {
    "date:inception_lower": "1995-07-01",
    "date:inception_upper": "1995-07-01",
    "iso:country": "GB",
    "wof:name": "RG20 6NX",
    "wof:placetype": "postalcode"
  },
  "geometry": {"coordinates":[-1.254513,51.515132],"type":"Point"}
}
