{
  "type": "Feature",
  "properties": {
    "date:inception_lower": "1980-01-01",
    "date:inception_upper": "1980-01-01",
    "iso:country": "GB",
    "wof:name": "SY20 9QP",
    "wof:placetype": "postalcode"
  },
  "geometry": {"coordinates":[-3.732245,52.676619],"type":"Point"}
}
