{
  "type": "Feature",
  "properties": {
    "iso:country":"GB",
    "wof:name":"SY20 9QP",
    "wof:placetype":"postalcode"
},
  "geometry": {"coordinates":[-3.73224551758717,52.67661882989484],"type":"Point"}
}