{
  "type": "Feature",
  "properties": {
    "iso:country": "GB",
    "wof:name": "TF7 5FF",
    "wof:placetype": "postalcode"
  },
  "geometry": {"coordinates":[-2.450937,52.637675],"type":"Point"}
}
