{
  "type": "Feature",
  "properties": {
    "iso:country":"GB",
    "wof:name":"TF7 5FF",
    "wof:placetype":"postalcode"
},
  "geometry": {"coordinates":[-2.4509369035853,52.63767493973327],"type":"Point"}
}