{
  "type": "Feature",
  "properties": {
    "iso:country": "GB",
    "wof:name": "DA13 9QE",
    "wof:placetype": "postalcode"
  },
  "geometry": {"coordinates":[0.325247,51.412543],"type":"Point"}
}
