{
  "type": "Feature",
  "properties": {
    "iso:country":"GB",
    "wof:name":"DA13 9QE",
    "wof:placetype":"postalcode"
},
  "geometry": {"coordinates":[0.32725485338139,51.41243981324519],"type":"Point"}
}