{
  "type": "Feature",
  "properties": {
    "date:inception_lower": "1980-01-01",
    "date:inception_upper": "1980-01-01",
    "iso:country": "GB",
    "wof:name": "DA13 9QE",
    "wof:placetype": "postalcode"
  },
  "geometry": {"coordinates":[0.325247,51.412543],"type":"Point"}
}
