{
  "type": "Feature",
  "properties": {
    "iso:country":"GB",
    "wof:name":"B48 7DE",
    "wof:placetype":"postalcode"
},
  "geometry": {"coordinates":[-1.98474865442279,52.34271000969562],"type":"Point"}
}