{
  "type": "Feature",
  "properties": {
    "date:inception_lower":"1980-01-01",
    "date:inception_upper":"1980-01-31",
    "iso:country":"GB",
    "wof:name":"B48 7DE",
    "wof:placetype":"postalcode"
},
  "geometry": {"coordinates":[-1.984323,52.343267],"type":"Point"}
}