{
  "type": "Feature",
  "properties": {
    "iso:country": "GB",
    "wof:name": "B48 7DE",
    "wof:placetype": "postalcode"
  },
  "geometry": {"coordinates":[-1.984323,52.343267],"type":"Point"}
}
