{
  "type": "Feature",
  "properties": {
    "iso:country":"GB",
    "wof:name":"NE65 8TD",
    "wof:placetype":"postalcode"
},
  "geometry": {"coordinates":[-1.75554262083956,55.23925384430265],"type":"Point"}
}