{
  "type": "Feature",
  "properties": {
    "iso:country": "GB",
    "wof:name": "BS34 8QZ",
    "wof:placetype": "postalcode"
  },
  "geometry": {"coordinates":[-2.551875,51.501704],"type":"Point"}
}
