{
  "type": "Feature",
  "properties": {
    "iso:country":"GB",
    "wof:name":"BS34 8QZ",
    "wof:placetype":"postalcode"
},
  "geometry": {"coordinates":[-2.5520762955102,51.5017765232333],"type":"Point"}
}