{
  "type": "Feature",
  "properties": {
    "date:inception_lower": "1980-01-01",
    "date:inception_upper": "1980-01-01",
    "iso:country": "GB",
    "wof:name": "SA15 1PR",
    "wof:placetype": "postalcode"
  },
  "geometry": {"coordinates":[-4.146117,51.676626],"type":"Point"}
}
