{
  "type": "Feature",
  "properties": {
    "iso:country":"GB",
    "wof:name":"SA15 1PR",
    "wof:placetype":"postalcode"
},
  "geometry": {"coordinates":[-4.1461170145739,51.6766255520139],"type":"Point"}
}