{
  "type": "Feature",
  "properties": {
    "iso:country":"GB",
    "wof:name":"KA7 3DA",
    "wof:placetype":"postalcode"
},
  "geometry": {"coordinates":[-4.61723696000335,55.45429867675458],"type":"Point"}
}