{
  "type": "Feature",
  "properties": {
    "date:inception_lower": "1997-12-01",
    "date:inception_upper": "1997-12-01",
    "iso:country": "GB",
    "wof:name": "CT18 7NW",
    "wof:placetype": "postalcode"
  },
  "geometry": {"coordinates":[1.159352,51.114405],"type":"Point"}
}
