{
  "type": "Feature",
  "properties": {
    "iso:country":"GB",
    "wof:name":"NW3 3SB",
    "wof:placetype":"postalcode"
},
  "geometry": {"coordinates":[-0.16372664852557,51.54309171095581],"type":"Point"}
}