{
  "type": "Feature",
  "properties": {
    "date:inception_lower":"1986-09-01",
    "date:inception_upper":"1986-09-30",
    "iso:country":"GB",
    "wof:name":"EH39 4RH",
    "wof:placetype":"postalcode"
},
  "geometry": {"coordinates":[-2.733637,56.055616],"type":"Point"}
}