{
  "type": "Feature",
  "properties": {
    "iso:country":"GB",
    "wof:name":"S5 8LP",
    "wof:placetype":"postalcode"
},
  "geometry": {"coordinates":[-1.49042626686707,53.41519594286101],"type":"Point"}
}