{
  "type": "Feature",
  "properties": {
    "date:inception_lower": "1980-01-01",
    "date:inception_upper": "1980-01-01",
    "iso:country": "GB",
    "wof:name": "PO37 6LT",
    "wof:placetype": "postalcode"
  },
  "geometry": {"coordinates":[-1.186956,50.627601],"type":"Point"}
}
