{
  "type": "Feature",
  "properties": {
    "iso:country":"GB",
    "wof:name":"CF33 6BX",
    "wof:placetype":"postalcode"
},
  "geometry": {"coordinates":[-3.68097664260222,51.52670799353513],"type":"Point"}
}