{
  "type": "Feature",
  "properties": {
    "date:inception_lower": "1995-07-01",
    "date:inception_upper": "1995-07-01",
    "iso:country": "GB",
    "wof:name": "CF33 6BX",
    "wof:placetype": "postalcode"
  },
  "geometry": {"coordinates":[-3.681123,51.526717],"type":"Point"}
}
