{
  "type": "Feature",
  "properties": {
    "iso:country":"GB",
    "wof:name":"TS17 0XS",
    "wof:placetype":"postalcode"
},
  "geometry": {"coordinates":[-1.30916186186927,54.51791895634072],"type":"Point"}
}