{
  "type": "Feature",
  "properties": {
    "iso:country":"GB",
    "wof:name":"SP11 6AB",
    "wof:placetype":"postalcode"
},
  "geometry": {"coordinates":[-1.46943211302511,51.22858278848559],"type":"Point"}
}