{
  "type": "Feature",
  "properties": {
    "date:inception_lower":"1980-01-01",
    "date:inception_upper":"1980-01-31",
    "iso:country":"GB",
    "wof:name":"SP11 6AB",
    "wof:placetype":"postalcode"
},
  "geometry": {"coordinates":[-1.469432,51.228583],"type":"Point"}
}