{
  "type": "Feature",
  "properties": {
    "iso:country": "GB",
    "wof:name": "SP11 6AB",
    "wof:placetype": "postalcode"
  },
  "geometry": {"coordinates":[-1.469432,51.228583],"type":"Point"}
}
