{
  "type": "Feature",
  "properties": {
    "iso:country":"GB",
    "wof:name":"SE5 0TW",
    "wof:placetype":"postalcode"
},
  "geometry": {"coordinates":[-0.10133031519264,51.47814340978631],"type":"Point"}
}