{
  "type": "Feature",
  "properties": {
    "iso:country": "GB",
    "wof:name": "E1 5AA",
    "wof:placetype": "postalcode"
  },
  "geometry": {"coordinates":[-0.061954,51.518991],"type":"Point"}
}
