{
  "type": "Feature",
  "properties": {
    "iso:country":"GB",
    "wof:name":"E1 5AA",
    "wof:placetype":"postalcode"
},
  "geometry": {"coordinates":[-0.06195388055318,51.51899111317555],"type":"Point"}
}