{
  "type": "Feature",
  "properties": {
    "iso:country":"GB",
    "wof:name":"TN4 0XD",
    "wof:placetype":"postalcode"
},
  "geometry": {"coordinates":[0.25699706880036,51.16753267382018],"type":"Point"}
}