{
  "type": "Feature",
  "properties": {
    "iso:country": "GB",
    "wof:name": "B76 1BG",
    "wof:placetype": "postalcode"
  },
  "geometry": {"coordinates":[-1.81044,52.55947],"type":"Point"}
}
