{
  "type": "Feature",
  "properties": {
    "iso:country":"GB",
    "wof:name":"B76 1BG",
    "wof:placetype":"postalcode"
},
  "geometry": {"coordinates":[-1.81043965164685,52.55947041279937],"type":"Point"}
}