{
  "type": "Feature",
  "properties": {
    "iso:country":"GB",
    "wof:name":"GU21 5JZ",
    "wof:placetype":"postalcode"
},
  "geometry": {"coordinates":[-0.53650064269496,51.32779967057544],"type":"Point"}
}