{
  "type": "Feature",
  "properties": {
    "iso:country":"GB",
    "wof:name":"PE38 9UG",
    "wof:placetype":"postalcode"
},
  "geometry": {"coordinates":[0.37796429534721,52.59284617525373],"type":"Point"}
}