{
  "type": "Feature",
  "properties": {
    "date:inception_lower": "2002-07-01",
    "date:inception_upper": "2002-07-01",
    "iso:country": "GB",
    "wof:name": "PE38 9UG",
    "wof:placetype": "postalcode"
  },
  "geometry": {"coordinates":[0.377964,52.592846],"type":"Point"}
}
