{
  "type": "Feature",
  "properties": {
    "iso:country": "GB",
    "wof:name": "AL3 7QP",
    "wof:placetype": "postalcode"
  },
  "geometry": {"coordinates":[-0.39707,51.798099],"type":"Point"}
}
