{
  "type": "Feature",
  "properties": {
    "iso:country": "GB",
    "wof:name": "LA3 2BU",
    "wof:placetype": "postalcode"
  },
  "geometry": {"coordinates":[-2.890478,54.047001],"type":"Point"}
}
