{
  "type": "Feature",
  "properties": {
    "date:inception_lower": "1980-01-01",
    "date:inception_upper": "1980-01-01",
    "iso:country": "GB",
    "wof:name": "LA3 2BU",
    "wof:placetype": "postalcode"
  },
  "geometry": {"coordinates":[-2.890478,54.047001],"type":"Point"}
}
