{
  "type": "Feature",
  "properties": {
    "iso:country":"GB",
    "wof:name":"LA3 2BU",
    "wof:placetype":"postalcode"
},
  "geometry": {"coordinates":[-2.89047817361005,54.04700070017672],"type":"Point"}
}