{
  "type": "Feature",
  "properties": {
    "iso:country": "GB",
    "wof:name": "SE20 7DF",
    "wof:placetype": "postalcode"
  },
  "geometry": {"coordinates":[-0.056246,51.408197],"type":"Point"}
}
