{
  "type": "Feature",
  "properties": {
    "iso:country":"GB",
    "wof:name":"SE20 7DF",
    "wof:placetype":"postalcode"
},
  "geometry": {"coordinates":[-0.05624624404543,51.40819685598429],"type":"Point"}
}