{
  "type": "Feature",
  "properties": {
    "date:inception_lower": "2004-03-01",
    "date:inception_upper": "2004-03-01",
    "iso:country": "GB",
    "wof:name": "SE20 7DF",
    "wof:placetype": "postalcode"
  },
  "geometry": {"coordinates":[-0.056246,51.408197],"type":"Point"}
}
