{
  "type": "Feature",
  "properties": {
    "iso:country":"GB",
    "wof:name":"ML5 4JE",
    "wof:placetype":"postalcode"
},
  "geometry": {"coordinates":[-4.01844239265037,55.84712416221796],"type":"Point"}
}