{
  "type": "Feature",
  "properties": {
    "date:inception_lower":"1996-06-01",
    "date:inception_upper":"1996-06-30",
    "iso:country":"GB",
    "wof:name":"AB53 5SH",
    "wof:placetype":"postalcode"
},
  "geometry": {"coordinates":[-2.340402,57.627098],"type":"Point"}
}