{
  "type": "Feature",
  "properties": {
    "date:inception_lower": "1992-01-01",
    "date:inception_upper": "1992-01-01",
    "iso:country": "GB",
    "wof:name": "PL21 0UR",
    "wof:placetype": "postalcode"
  },
  "geometry": {"coordinates":[-3.918459,50.387972],"type":"Point"}
}
