{
  "type": "Feature",
  "properties": {
    "iso:country": "GB",
    "wof:name": "CM99 2EY",
    "wof:placetype": "postalcode"
  },
  "geometry": {"coordinates":[0.500628,51.742499],"type":"Point"}
}
