{
  "type": "Feature",
  "properties": {
    "iso:country": "GB",
    "wof:name": "AB15 8QA",
    "wof:placetype": "postalcode"
  },
  "geometry": {"coordinates":[-2.214741,57.146926],"type":"Point"}
}
