{
  "type": "Feature",
  "properties": {
    "iso:country":"GB",
    "wof:name":"DY1 1LQ",
    "wof:placetype":"postalcode"
},
  "geometry": {"coordinates":[-2.08124801030608,52.51188440437367],"type":"Point"}
}