{
  "type": "Feature",
  "properties": {
    "iso:country":"GB",
    "wof:name":"LS25 2ED",
    "wof:placetype":"postalcode"
},
  "geometry": {"coordinates":[-1.37698115212112,53.79553286614298],"type":"Point"}
}