{
  "type": "Feature",
  "properties": {
    "date:inception_lower":"1980-01-01",
    "date:inception_upper":"1980-01-31",
    "iso:country":"GB",
    "wof:name":"LS25 2ED",
    "wof:placetype":"postalcode"
},
  "geometry": {"coordinates":[-1.376981,53.795533],"type":"Point"}
}