{
  "type": "Feature",
  "properties": {
    "iso:country":"GB",
    "wof:name":"EX39 4NY",
    "wof:placetype":"postalcode"
},
  "geometry": {"coordinates":[-4.16629334186648,51.02705191438584],"type":"Point"}
}