{
  "type": "Feature",
  "properties": {
    "iso:country":"GB",
    "wof:name":"KY10 2AY",
    "wof:placetype":"postalcode"
},
  "geometry": {"coordinates":[-2.76387911366791,56.20604435031102],"type":"Point"}
}