{
  "type": "Feature",
  "properties": {
    "date:inception_lower": "2021-01-01",
    "date:inception_upper": "2021-01-01",
    "iso:country": "GB",
    "wof:name": "LD3 8AQ",
    "wof:placetype": "postalcode"
  },
  "geometry": {"coordinates":[-3.39332,51.936776],"type":"Point"}
}
