{
  "type": "Feature",
  "properties": {
    "iso:country":"GB",
    "wof:name":"CV21 4PD",
    "wof:placetype":"postalcode"
},
  "geometry": {"coordinates":[-1.21207827008957,52.3603409886259],"type":"Point"}
}