{
  "type": "Feature",
  "properties": {
    "date:inception_lower": "2005-03-01",
    "date:inception_upper": "2005-03-01",
    "iso:country": "GB",
    "wof:name": "CV21 4PD",
    "wof:placetype": "postalcode"
  },
  "geometry": {"coordinates":[-1.212064,52.360358],"type":"Point"}
}
