{
  "type": "Feature",
  "properties": {
    "iso:country": "GB",
    "wof:name": "CV21 4PD",
    "wof:placetype": "postalcode"
  },
  "geometry": {"coordinates":[-1.212064,52.360358],"type":"Point"}
}
