{
  "type": "Feature",
  "properties": {
    "iso:country": "GB",
    "wof:name": "RH13 5PT",
    "wof:placetype": "postalcode"
  },
  "geometry": {"coordinates":[-0.312851,51.069865],"type":"Point"}
}
