{
  "type": "Feature",
  "properties": {
    "iso:country":"GB",
    "wof:name":"DL9 4AL",
    "wof:placetype":"postalcode"
},
  "geometry": {"coordinates":[-1.71968902298108,54.37962055741898],"type":"Point"}
}