{
  "type": "Feature",
  "properties": {
    "iso:country":"GB",
    "wof:name":"SS16 4JG",
    "wof:placetype":"postalcode"
},
  "geometry": {"coordinates":[0.48395508598459,51.56506852852283],"type":"Point"}
}