{
  "type": "Feature",
  "properties": {
    "iso:country": "GB",
    "wof:name": "EH54 7DE",
    "wof:placetype": "postalcode"
  },
  "geometry": {"coordinates":[-3.533006,55.881009],"type":"Point"}
}
