{
  "type": "Feature",
  "properties": {
    "date:inception_lower": "1991-03-01",
    "date:inception_upper": "1991-03-01",
    "iso:country": "GB",
    "wof:name": "EH54 7DE",
    "wof:placetype": "postalcode"
  },
  "geometry": {"coordinates":[-3.532111,55.881124],"type":"Point"}
}
