{
  "type": "Feature",
  "properties": {
    "date:inception_lower":"1994-12-01",
    "date:inception_upper":"1994-12-31",
    "iso:country":"GB",
    "wof:name":"BB9 9AW",
    "wof:placetype":"postalcode"
},
  "geometry": {"coordinates":[-2.214107,53.834573],"type":"Point"}
}