{
  "type": "Feature",
  "properties": {
    "iso:country":"GB",
    "wof:name":"BB9 9AW",
    "wof:placetype":"postalcode"
},
  "geometry": {"coordinates":[-2.21410658223501,53.83457272258423],"type":"Point"}
}