{
  "type": "Feature",
  "properties": {
    "iso:country": "GB",
    "wof:name": "DN14 9NL",
    "wof:placetype": "postalcode"
  },
  "geometry": {"coordinates":[-1.020279,53.71149],"type":"Point"}
}
