{
  "type": "Feature",
  "properties": {
    "iso:country":"GB",
    "wof:name":"DN14 9NL",
    "wof:placetype":"postalcode"
},
  "geometry": {"coordinates":[-1.0202790417647,53.71149022784767],"type":"Point"}
}