{
  "type": "Feature",
  "properties": {
    "iso:country":"GB",
    "wof:name":"SW15 6AP",
    "wof:placetype":"postalcode"
},
  "geometry": {"coordinates":[-0.21933683544453,51.46062504159786],"type":"Point"}
}