{
  "type": "Feature",
  "properties": {
    "date:inception_lower":"2001-06-01",
    "date:inception_upper":"2001-06-30",
    "iso:country":"GB",
    "wof:name":"M24 2QZ",
    "wof:placetype":"postalcode"
},
  "geometry": {"coordinates":[-2.190579,53.552044],"type":"Point"}
}