{
  "type": "Feature",
  "properties": {
    "iso:country": "GB",
    "wof:name": "CH48 1LP",
    "wof:placetype": "postalcode"
  },
  "geometry": {"coordinates":[-3.156421,53.35955],"type":"Point"}
}
