{
  "type": "Feature",
  "properties": {
    "iso:country": "GB",
    "wof:name": "NG24 3UX",
    "wof:placetype": "postalcode"
  },
  "geometry": {"coordinates":[-0.771137,53.048861],"type":"Point"}
}
