{
  "type": "Feature",
  "properties": {
    "iso:country":"GB",
    "wof:name":"NG24 3UX",
    "wof:placetype":"postalcode"
},
  "geometry": {"coordinates":[-0.77120230072297,53.04880462374617],"type":"Point"}
}