{
  "type": "Feature",
  "properties": {
    "date:inception_lower": "1981-09-01",
    "date:inception_upper": "1981-09-01",
    "iso:country": "GB",
    "wof:name": "SY21 7HZ",
    "wof:placetype": "postalcode"
  },
  "geometry": {"coordinates":[-3.142302,52.66396],"type":"Point"}
}
