{
  "type": "Feature",
  "properties": {
    "iso:country":"GB",
    "wof:name":"TR4 8NB",
    "wof:placetype":"postalcode"
},
  "geometry": {"coordinates":[-5.17711340967603,50.25545902567071],"type":"Point"}
}