{
  "type": "Feature",
  "properties": {
    "iso:country": "GB",
    "wof:name": "OX12 9XE",
    "wof:placetype": "postalcode"
  },
  "geometry": {"coordinates":[-1.503116,51.552504],"type":"Point"}
}
