{
  "type": "Feature",
  "properties": {
    "iso:country":"GB",
    "wof:name":"PE31 7RS",
    "wof:placetype":"postalcode"
},
  "geometry": {"coordinates":[0.49480907035819,52.91032539133941],"type":"Point"}
}