{
  "type": "Feature",
  "properties": {
    "date:inception_lower":"2001-12-01",
    "date:inception_upper":"2001-12-31",
    "iso:country":"GB",
    "wof:name":"PE31 7RS",
    "wof:placetype":"postalcode"
},
  "geometry": {"coordinates":[0.494809,52.910325],"type":"Point"}
}