{
  "type": "Feature",
  "properties": {
    "iso:country":"GB",
    "wof:name":"B98 7LJ",
    "wof:placetype":"postalcode"
},
  "geometry": {"coordinates":[-1.92845863416774,52.29590443297619],"type":"Point"}
}