{
  "type": "Feature",
  "properties": {
    "date:inception_lower": "1995-12-01",
    "date:inception_upper": "1995-12-01",
    "iso:country": "GB",
    "wof:name": "TN5 7NF",
    "wof:placetype": "postalcode"
  },
  "geometry": {"coordinates":[0.435133,51.054972],"type":"Point"}
}
