{
  "type": "Feature",
  "properties": {
    "iso:country":"GB",
    "wof:name":"TN5 7NF",
    "wof:placetype":"postalcode"
},
  "geometry": {"coordinates":[0.43513260878937,51.05497214658049],"type":"Point"}
}