{
  "type": "Feature",
  "properties": {
    "date:inception_lower":"1980-01-01",
    "date:inception_upper":"1980-01-31",
    "iso:country":"GB",
    "wof:name":"HP22 6AN",
    "wof:placetype":"postalcode"
},
  "geometry": {"coordinates":[-0.748779,51.774808],"type":"Point"}
}