{
  "type": "Feature",
  "properties": {
    "iso:country": "GB",
    "wof:name": "HP22 6AN",
    "wof:placetype": "postalcode"
  },
  "geometry": {"coordinates":[-0.748779,51.774808],"type":"Point"}
}
