{
  "type": "Feature",
  "properties": {
    "iso:country":"GB",
    "wof:name":"LE7 9PQ",
    "wof:placetype":"postalcode"
},
  "geometry": {"coordinates":[-1.04069513412474,52.62764949093835],"type":"Point"}
}