{
  "type": "Feature",
  "properties": {
    "iso:country":"GB",
    "wof:name":"LS6 4RT",
    "wof:placetype":"postalcode"
},
  "geometry": {"coordinates":[-1.56431770534137,53.84076905775507],"type":"Point"}
}