{
  "type": "Feature",
  "properties": {
    "date:inception_lower": "1980-01-01",
    "date:inception_upper": "1980-01-01",
    "iso:country": "GB",
    "wof:name": "N17 0XD",
    "wof:placetype": "postalcode"
  },
  "geometry": {"coordinates":[-0.050065,51.59793],"type":"Point"}
}
