{
  "type": "Feature",
  "properties": {
    "iso:country": "GB",
    "wof:name": "N17 0XD",
    "wof:placetype": "postalcode"
  },
  "geometry": {"coordinates":[-0.050065,51.59793],"type":"Point"}
}
