{
  "type": "Feature",
  "properties": {
    "iso:country":"GB",
    "wof:name":"N17 0XD",
    "wof:placetype":"postalcode"
},
  "geometry": {"coordinates":[-0.05171930198071,51.60103141862649],"type":"Point"}
}