{
  "type": "Feature",
  "properties": {
    "iso:country":"GB",
    "wof:name":"LL20 7YL",
    "wof:placetype":"postalcode"
},
  "geometry": {"coordinates":[-3.11865590834411,52.98045034781757],"type":"Point"}
}