{
  "type": "Feature",
  "properties": {
    "iso:country": "GB",
    "wof:name": "LL20 7YL",
    "wof:placetype": "postalcode"
  },
  "geometry": {"coordinates":[-3.118625,52.980474],"type":"Point"}
}
