{
  "type": "Feature",
  "properties": {
    "iso:country":"GB",
    "wof:name":"KA24 4JT",
    "wof:placetype":"postalcode"
},
  "geometry": {"coordinates":[-4.72713338636405,55.70197975395071],"type":"Point"}
}