{
  "type": "Feature",
  "properties": {
    "iso:country": "GB",
    "wof:name": "KA24 4JT",
    "wof:placetype": "postalcode"
  },
  "geometry": {"coordinates":[-4.727133,55.70198],"type":"Point"}
}
