{
  "type": "Feature",
  "properties": {
    "iso:country":"GB",
    "wof:name":"CH3 6PB",
    "wof:placetype":"postalcode"
},
  "geometry": {"coordinates":[-2.85576207005676,53.06730514867817],"type":"Point"}
}