{
  "type": "Feature",
  "properties": {
    "date:inception_lower": "1980-01-01",
    "date:inception_upper": "1980-01-01",
    "iso:country": "GB",
    "wof:name": "CH3 6PB",
    "wof:placetype": "postalcode"
  },
  "geometry": {"coordinates":[-2.855762,53.067305],"type":"Point"}
}
