{
  "type": "Feature",
  "properties": {
    "iso:country":"GB",
    "wof:name":"S80 4TF",
    "wof:placetype":"postalcode"
},
  "geometry": {"coordinates":[-1.20206550070277,53.2840612915212],"type":"Point"}
}