{
  "type": "Feature",
  "properties": {
    "iso:country": "GB",
    "wof:name": "OX9 2JS",
    "wof:placetype": "postalcode"
  },
  "geometry": {"coordinates":[-1.068619,51.733059],"type":"Point"}
}
