{
  "type": "Feature",
  "properties": {
    "date:inception_lower": "1980-01-01",
    "date:inception_upper": "1980-01-01",
    "iso:country": "GB",
    "wof:name": "OX9 2JS",
    "wof:placetype": "postalcode"
  },
  "geometry": {"coordinates":[-1.067638,51.733591],"type":"Point"}
}
