{
  "type": "Feature",
  "properties": {
    "iso:country":"GB",
    "wof:name":"OX9 2JS",
    "wof:placetype":"postalcode"
},
  "geometry": {"coordinates":[-1.06863917460609,51.7330539693855],"type":"Point"}
}