{
  "type": "Feature",
  "properties": {
    "iso:country":"GB",
    "wof:name":"LE11 3YF",
    "wof:placetype":"postalcode"
},
  "geometry": {"coordinates":[-1.25536998161488,52.74983638684008],"type":"Point"}
}