{
  "type": "Feature",
  "properties": {
    "date:inception_lower":"1980-01-01",
    "date:inception_upper":"1980-01-31",
    "iso:country":"GB",
    "wof:name":"LE11 3YF",
    "wof:placetype":"postalcode"
},
  "geometry": {"coordinates":[-1.257806,52.749052],"type":"Point"}
}