{
  "type": "Feature",
  "properties": {
    "date:inception_lower": "1986-01-01",
    "date:inception_upper": "1986-01-01",
    "iso:country": "GB",
    "wof:name": "SO43 7HL",
    "wof:placetype": "postalcode"
  },
  "geometry": {"coordinates":[-1.671098,50.924031],"type":"Point"}
}
