{
  "type": "Feature",
  "properties": {
    "iso:country": "GB",
    "wof:name": "SO43 7HL",
    "wof:placetype": "postalcode"
  },
  "geometry": {"coordinates":[-1.67115,50.924039],"type":"Point"}
}
