{
  "type": "Feature",
  "properties": {
    "iso:country": "GB",
    "wof:name": "DN10 5DY",
    "wof:placetype": "postalcode"
  },
  "geometry": {"coordinates":[-0.965428,53.395344],"type":"Point"}
}
