{
  "type": "Feature",
  "properties": {
    "date:inception_lower": "1984-10-01",
    "date:inception_upper": "1984-10-01",
    "iso:country": "GB",
    "wof:name": "LL11 4EQ",
    "wof:placetype": "postalcode"
  },
  "geometry": {"coordinates":[-3.020447,53.072218],"type":"Point"}
}
