{
  "type": "Feature",
  "properties": {
    "iso:country":"GB",
    "wof:name":"LL11 4EQ",
    "wof:placetype":"postalcode"
},
  "geometry": {"coordinates":[-3.02044694319786,53.07221813586849],"type":"Point"}
}