{
  "type": "Feature",
  "properties": {
    "iso:country":"GB",
    "wof:name":"NE34 7PQ",
    "wof:placetype":"postalcode"
},
  "geometry": {"coordinates":[-1.40619290143282,54.97132755352006],"type":"Point"}
}