{
  "type": "Feature",
  "properties": {
    "iso:country": "GB",
    "wof:name": "E6 2NG",
    "wof:placetype": "postalcode"
  },
  "geometry": {"coordinates":[0.059289,51.534767],"type":"Point"}
}
