{
  "type": "Feature",
  "properties": {
    "iso:country":"GB",
    "wof:name":"W7 3DT",
    "wof:placetype":"postalcode"
},
  "geometry": {"coordinates":[-0.34499464808921,51.52341601994387],"type":"Point"}
}