{
  "type": "Feature",
  "properties": {
    "iso:country":"GB",
    "wof:name":"OX10 6AP",
    "wof:placetype":"postalcode"
},
  "geometry": {"coordinates":[-1.08132751653478,51.55335064707544],"type":"Point"}
}