{
  "type": "Feature",
  "properties": {
    "iso:country": "GB",
    "wof:name": "HU8 0QJ",
    "wof:placetype": "postalcode"
  },
  "geometry": {"coordinates":[-0.296629,53.773611],"type":"Point"}
}
