{
  "type": "Feature",
  "properties": {
    "iso:country":"GB",
    "wof:name":"ME3 9EW",
    "wof:placetype":"postalcode"
},
  "geometry": {"coordinates":[0.55996925986681,51.42183174701852],"type":"Point"}
}