{
  "type": "Feature",
  "properties": {
    "iso:country":"GB",
    "wof:name":"TQ2 8PX",
    "wof:placetype":"postalcode"
},
  "geometry": {"coordinates":[-3.53282202945886,50.49906176175217],"type":"Point"}
}