{
  "type": "Feature",
  "properties": {
    "iso:country":"GB",
    "wof:name":"SN25 1RS",
    "wof:placetype":"postalcode"
},
  "geometry": {"coordinates":[-1.81150603580983,51.59398183262645],"type":"Point"}
}