{
  "type": "Feature",
  "properties": {
    "date:inception_lower": "2000-06-01",
    "date:inception_upper": "2000-06-01",
    "iso:country": "GB",
    "wof:name": "SN25 1RS",
    "wof:placetype": "postalcode"
  },
  "geometry": {"coordinates":[-1.811506,51.593982],"type":"Point"}
}
