{
  "type": "Feature",
  "properties": {
    "date:inception_lower":"1980-01-01",
    "date:inception_upper":"1980-01-31",
    "iso:country":"GB",
    "wof:name":"KY5 0DD",
    "wof:placetype":"postalcode"
},
  "geometry": {"coordinates":[-3.261772,56.139348],"type":"Point"}
}