{
  "type": "Feature",
  "properties": {
    "date:inception_lower": "1980-01-01",
    "date:inception_upper": "1980-01-01",
    "iso:country": "GB",
    "wof:name": "G82 2AT",
    "wof:placetype": "postalcode"
  },
  "geometry": {"coordinates":[-4.556034,55.951832],"type":"Point"}
}
