{
  "type": "Feature",
  "properties": {
    "date:inception_lower": "2010-11-01",
    "date:inception_upper": "2010-11-01",
    "iso:country": "GB",
    "wof:name": "SG1 3BY",
    "wof:placetype": "postalcode"
  },
  "geometry": {"coordinates":[-0.209534,51.91252],"type":"Point"}
}
