{
  "type": "Feature",
  "properties": {
    "iso:country":"GB",
    "wof:name":"G72 7SY",
    "wof:placetype":"postalcode"
},
  "geometry": {"coordinates":[-4.14296407525903,55.82074307487719],"type":"Point"}
}