{
  "type": "Feature",
  "properties": {
    "iso:country":"GB",
    "wof:name":"PL5 1EF",
    "wof:placetype":"postalcode"
},
  "geometry": {"coordinates":[-4.18775419772718,50.40138172664781],"type":"Point"}
}