{
  "type": "Feature",
  "properties": {
    "iso:country":"GB",
    "wof:name":"NE21 5TT",
    "wof:placetype":"postalcode"
},
  "geometry": {"coordinates":[-1.69531727734919,54.96637404373751],"type":"Point"}
}