{
  "type": "Feature",
  "properties": {
    "iso:country": "GB",
    "wof:name": "NE21 5TT",
    "wof:placetype": "postalcode"
  },
  "geometry": {"coordinates":[-1.695317,54.966374],"type":"Point"}
}
