{
  "type": "Feature",
  "properties": {
    "date:inception_lower":"1983-07-01",
    "date:inception_upper":"1983-07-31",
    "iso:country":"GB",
    "wof:name":"NE21 5TT",
    "wof:placetype":"postalcode"
},
  "geometry": {"coordinates":[-1.695317,54.966374],"type":"Point"}
}