{
  "type": "Feature",
  "properties": {
    "date:inception_lower":"1980-01-01",
    "date:inception_upper":"1980-01-31",
    "iso:country":"GB",
    "wof:name":"LS6 2JA",
    "wof:placetype":"postalcode"
},
  "geometry": {"coordinates":[-1.554567,53.817257],"type":"Point"}
}