{
  "type": "Feature",
  "properties": {
    "iso:country":"GB",
    "wof:name":"M24 2SH",
    "wof:placetype":"postalcode"
},
  "geometry": {"coordinates":[-2.16157482834158,53.58124453950326],"type":"Point"}
}