{
  "type": "Feature",
  "properties": {
    "iso:country":"GB",
    "wof:name":"DE14 1DG",
    "wof:placetype":"postalcode"
},
  "geometry": {"coordinates":[-1.63253712769478,52.80214282426124],"type":"Point"}
}