{
  "type": "Feature",
  "properties": {
    "iso:country": "GB",
    "wof:name": "GU1 2SP",
    "wof:placetype": "postalcode"
  },
  "geometry": {"coordinates":[-0.545134,51.241328],"type":"Point"}
}
