{
  "type": "Feature",
  "properties": {
    "iso:country":"GB",
    "wof:name":"RM15 6TP",
    "wof:placetype":"postalcode"
},
  "geometry": {"coordinates":[0.30341253726666,51.51852637166951],"type":"Point"}
}