{
  "type": "Feature",
  "properties": {
    "iso:country": "GB",
    "wof:name": "RM15 6TP",
    "wof:placetype": "postalcode"
  },
  "geometry": {"coordinates":[0.303413,51.518526],"type":"Point"}
}
