{
  "type": "Feature",
  "properties": {
    "iso:country":"GB",
    "wof:name":"CO3 0RF",
    "wof:placetype":"postalcode"
},
  "geometry": {"coordinates":[0.84804475739687,51.87921674652898],"type":"Point"}
}