{
  "type": "Feature",
  "properties": {
    "date:inception_lower": "2007-01-01",
    "date:inception_upper": "2007-01-01",
    "iso:country": "GB",
    "wof:name": "CO3 0RF",
    "wof:placetype": "postalcode"
  },
  "geometry": {"coordinates":[0.848045,51.879217],"type":"Point"}
}
