{
  "type": "Feature",
  "properties": {
    "iso:country":"GB",
    "wof:name":"DN11 8BN",
    "wof:placetype":"postalcode"
},
  "geometry": {"coordinates":[-1.0431185940333,53.42214963829415],"type":"Point"}
}