{
  "type": "Feature",
  "properties": {
    "iso:country":"GB",
    "wof:name":"B95 5BW",
    "wof:placetype":"postalcode"
},
  "geometry": {"coordinates":[-1.77813045069982,52.29655414470576],"type":"Point"}
}