{
  "type": "Feature",
  "properties": {
    "date:inception_lower": "2002-06-01",
    "date:inception_upper": "2002-06-01",
    "iso:country": "GB",
    "wof:name": "B95 5BW",
    "wof:placetype": "postalcode"
  },
  "geometry": {"coordinates":[-1.77813,52.296554],"type":"Point"}
}
