{
  "type": "Feature",
  "properties": {
    "iso:country": "GB",
    "wof:name": "L20 6NH",
    "wof:placetype": "postalcode"
  },
  "geometry": {"coordinates":[-2.988959,53.466774],"type":"Point"}
}
