{
  "type": "Feature",
  "properties": {
    "iso:country":"GB",
    "wof:name":"SW8 4RB",
    "wof:placetype":"postalcode"
},
  "geometry": {"coordinates":[-0.13090978260071,51.47673920747211],"type":"Point"}
}