{
  "type": "Feature",
  "properties": {
    "iso:country":"GB",
    "wof:name":"AB16 7XJ",
    "wof:placetype":"postalcode"
},
  "geometry": {"coordinates":[-2.14313152210429,57.16799467804607],"type":"Point"}
}