{
  "type": "Feature",
  "properties": {
    "iso:country": "GB",
    "wof:name": "AB16 7XJ",
    "wof:placetype": "postalcode"
  },
  "geometry": {"coordinates":[-2.143131,57.167995],"type":"Point"}
}
