{
  "type": "Feature",
  "properties": {
    "iso:country":"GB",
    "wof:name":"AB56 5AQ",
    "wof:placetype":"postalcode"
},
  "geometry": {"coordinates":[-2.96398284424852,57.65728774655152],"type":"Point"}
}