{
  "type": "Feature",
  "properties": {
    "iso:country": "GB",
    "wof:name": "N16 9PB",
    "wof:placetype": "postalcode"
  },
  "geometry": {"coordinates":[-0.083743,51.556183],"type":"Point"}
}
