{
  "type": "Feature",
  "properties": {
    "iso:country":"GB",
    "wof:name":"N16 9PB",
    "wof:placetype":"postalcode"
},
  "geometry": {"coordinates":[-0.08374301095682,51.5561825608972],"type":"Point"}
}