{
  "type": "Feature",
  "properties": {
    "date:inception_lower": "1980-01-01",
    "date:inception_upper": "1980-01-01",
    "iso:country": "GB",
    "wof:name": "FK8 3RT",
    "wof:placetype": "postalcode"
  },
  "geometry": {"coordinates":[-4.363616,56.154748],"type":"Point"}
}
