{
  "type": "Feature",
  "properties": {
    "iso:country": "GB",
    "wof:name": "FK8 3RT",
    "wof:placetype": "postalcode"
  },
  "geometry": {"coordinates":[-4.363616,56.154748],"type":"Point"}
}
