{
  "type": "Feature",
  "properties": {
    "iso:country":"GB",
    "wof:name":"FK8 3RT",
    "wof:placetype":"postalcode"
},
  "geometry": {"coordinates":[-4.36361576930969,56.15474787163895],"type":"Point"}
}