{
  "type": "Feature",
  "properties": {
    "iso:country":"GB",
    "wof:name":"ST9 9QG",
    "wof:placetype":"postalcode"
},
  "geometry": {"coordinates":[-2.06525852764924,53.08277992914859],"type":"Point"}
}