{
  "type": "Feature",
  "properties": {
    "date:inception_lower": "2022-04-01",
    "date:inception_upper": "2022-04-01",
    "iso:country": "GB",
    "wof:name": "GL6 8GD",
    "wof:placetype": "postalcode"
  },
  "geometry": {"coordinates":[-2.152543,51.729976],"type":"Point"}
}
