{
  "type": "Feature",
  "properties": {
    "iso:country": "GB",
    "wof:name": "BS36 2EQ",
    "wof:placetype": "postalcode"
  },
  "geometry": {"coordinates":[-2.477605,51.531811],"type":"Point"}
}
