{
  "type": "Feature",
  "properties": {
    "iso:country":"GB",
    "wof:name":"CW5 8JH",
    "wof:placetype":"postalcode"
},
  "geometry": {"coordinates":[-2.63307865546633,53.0691302056394],"type":"Point"}
}