{
  "type": "Feature",
  "properties": {
    "date:inception_lower": "1980-01-01",
    "date:inception_upper": "1980-01-01",
    "iso:country": "GB",
    "wof:name": "CW5 8JH",
    "wof:placetype": "postalcode"
  },
  "geometry": {"coordinates":[-2.633064,53.069183],"type":"Point"}
}
