{
  "type": "Feature",
  "properties": {
    "iso:country":"GB",
    "wof:name":"KT12 3DR",
    "wof:placetype":"postalcode"
},
  "geometry": {"coordinates":[-0.39604808947625,51.38102137973647],"type":"Point"}
}