{
  "type": "Feature",
  "properties": {
    "iso:country": "GB",
    "wof:name": "PR5 0RX",
    "wof:placetype": "postalcode"
  },
  "geometry": {"coordinates":[-2.587434,53.734741],"type":"Point"}
}
