{
  "type": "Feature",
  "properties": {
    "iso:country": "GB",
    "wof:name": "AL8 6UL",
    "wof:placetype": "postalcode"
  },
  "geometry": {"coordinates":[-0.210624,51.805121],"type":"Point"}
}
