{
  "type": "Feature",
  "properties": {
    "iso:country":"GB",
    "wof:name":"AL8 6UL",
    "wof:placetype":"postalcode"
},
  "geometry": {"coordinates":[-0.2106243127179,51.80512080666306],"type":"Point"}
}