{
  "type": "Feature",
  "properties": {
    "date:inception_lower": "2002-06-01",
    "date:inception_upper": "2002-06-01",
    "iso:country": "GB",
    "wof:name": "CM77 7WP",
    "wof:placetype": "postalcode"
  },
  "geometry": {"coordinates":[0.523172,51.855475],"type":"Point"}
}
