{
  "type": "Feature",
  "properties": {
    "date:inception_lower":"1980-01-01",
    "date:inception_upper":"1980-01-31",
    "iso:country":"GB",
    "wof:name":"HG4 3LL",
    "wof:placetype":"postalcode"
},
  "geometry": {"coordinates":[-1.511718,54.122675],"type":"Point"}
}