{
  "type": "Feature",
  "properties": {
    "iso:country": "GB",
    "wof:name": "HG4 3LL",
    "wof:placetype": "postalcode"
  },
  "geometry": {"coordinates":[-1.511718,54.122675],"type":"Point"}
}
