{
  "type": "Feature",
  "properties": {
    "iso:country":"GB",
    "wof:name":"HG4 3LL",
    "wof:placetype":"postalcode"
},
  "geometry": {"coordinates":[-1.51171816702523,54.12267504730598],"type":"Point"}
}