{
  "type": "Feature",
  "properties": {
    "iso:country": "GB",
    "wof:name": "CW2 8UF",
    "wof:placetype": "postalcode"
  },
  "geometry": {"coordinates":[-2.485983,53.094237],"type":"Point"}
}
