{
  "type": "Feature",
  "properties": {
    "iso:country":"GB",
    "wof:name":"NP26 4GW",
    "wof:placetype":"postalcode"
},
  "geometry": {"coordinates":[-2.74727126985269,51.59478266120857],"type":"Point"}
}