{
  "type": "Feature",
  "properties": {
    "iso:country":"GB",
    "wof:name":"EH34 5HQ",
    "wof:placetype":"postalcode"
},
  "geometry": {"coordinates":[-2.8815163578546,55.90952958313451],"type":"Point"}
}