{
  "type": "Feature",
  "properties": {
    "iso:country":"GB",
    "wof:name":"RM14 2SS",
    "wof:placetype":"postalcode"
},
  "geometry": {"coordinates":[0.24928513811757,51.55711369070116],"type":"Point"}
}