{
  "type": "Feature",
  "properties": {
    "iso:country":"GB",
    "wof:name":"RH17 5GL",
    "wof:placetype":"postalcode"
},
  "geometry": {"coordinates":[-0.13361750075675,51.00809095647329],"type":"Point"}
}