{
  "type": "Feature",
  "properties": {
    "iso:country":"GB",
    "wof:name":"EX8 3DS",
    "wof:placetype":"postalcode"
},
  "geometry": {"coordinates":[-3.40907652024206,50.62636313897693],"type":"Point"}
}