{
  "type": "Feature",
  "properties": {
    "iso:country":"GB",
    "wof:name":"BS37 4GB",
    "wof:placetype":"postalcode"
},
  "geometry": {"coordinates":[-2.42410995925245,51.5353710008765],"type":"Point"}
}