{
  "type": "Feature",
  "properties": {
    "date:inception_lower": "2013-08-01",
    "date:inception_upper": "2013-08-01",
    "iso:country": "GB",
    "wof:name": "BS37 4GB",
    "wof:placetype": "postalcode"
  },
  "geometry": {"coordinates":[-2.424079,51.535379],"type":"Point"}
}
