{
  "type": "Feature",
  "properties": {
    "iso:country": "GB",
    "wof:name": "BS37 4GB",
    "wof:placetype": "postalcode"
  },
  "geometry": {"coordinates":[-2.42411,51.535371],"type":"Point"}
}
