{
  "type": "Feature",
  "properties": {
    "iso:country":"GB",
    "wof:name":"SA14 8NB",
    "wof:placetype":"postalcode"
},
  "geometry": {"coordinates":[-4.12521658023736,51.68806665783051],"type":"Point"}
}