{
  "type": "Feature",
  "properties": {
    "iso:country":"GB",
    "wof:name":"NG2 7DB",
    "wof:placetype":"postalcode"
},
  "geometry": {"coordinates":[-1.13303802609378,52.91474866359282],"type":"Point"}
}