{
  "type": "Feature",
  "properties": {
    "iso:country": "GB",
    "wof:name": "L17 0AA",
    "wof:placetype": "postalcode"
  },
  "geometry": {"coordinates":[-2.929867,53.370412],"type":"Point"}
}
