{
  "type": "Feature",
  "properties": {
    "iso:country":"GB",
    "wof:name":"L17 0AA",
    "wof:placetype":"postalcode"
},
  "geometry": {"coordinates":[-2.92986707853725,53.37041198926757],"type":"Point"}
}