{
  "type": "Feature",
  "properties": {
    "iso:country": "GB",
    "wof:name": "NG12 2NW",
    "wof:placetype": "postalcode"
  },
  "geometry": {"coordinates":[-1.006474,52.945563],"type":"Point"}
}
