{
  "type": "Feature",
  "properties": {
    "iso:country":"GB",
    "wof:name":"DE5 3TL",
    "wof:placetype":"postalcode"
},
  "geometry": {"coordinates":[-1.40221623895918,53.04285122003638],"type":"Point"}
}