{
  "type": "Feature",
  "properties": {
    "iso:country": "GB",
    "wof:name": "DE5 3TL",
    "wof:placetype": "postalcode"
  },
  "geometry": {"coordinates":[-1.401902,53.042779],"type":"Point"}
}
