{
  "type": "Feature",
  "properties": {
    "iso:country":"GB",
    "wof:name":"M24 4JQ",
    "wof:placetype":"postalcode"
},
  "geometry": {"coordinates":[-2.22042625670926,53.55631573133407],"type":"Point"}
}