{
  "type": "Feature",
  "properties": {
    "iso:country":"GB",
    "wof:name":"TQ1 2BX",
    "wof:placetype":"postalcode"
},
  "geometry": {"coordinates":[-3.52258557034976,50.45960611420788],"type":"Point"}
}