{
  "type": "Feature",
  "properties": {
    "iso:country":"GB",
    "wof:name":"TW17 8RW",
    "wof:placetype":"postalcode"
},
  "geometry": {"coordinates":[-0.43178395608733,51.41219603583239],"type":"Point"}
}