{
  "type": "Feature",
  "properties": {
    "iso:country":"GB",
    "wof:name":"TF2 8AG",
    "wof:placetype":"postalcode"
},
  "geometry": {"coordinates":[-2.43913250851403,52.72046970446867],"type":"Point"}
}