{
  "type": "Feature",
  "properties": {
    "date:inception_lower":"2018-08-01",
    "date:inception_upper":"2018-08-31",
    "iso:country":"GB",
    "wof:name":"KA30 0AP",
    "wof:placetype":"postalcode"
},
  "geometry": {"coordinates":[-4.867607,55.794246],"type":"Point"}
}