{
  "type": "Feature",
  "properties": {
    "date:inception_lower": "1980-01-01",
    "date:inception_upper": "1980-01-01",
    "iso:country": "GB",
    "wof:name": "WS3 5DW",
    "wof:placetype": "postalcode"
  },
  "geometry": {"coordinates":[-1.977099,52.63339],"type":"Point"}
}
