{
  "type": "Feature",
  "properties": {
    "iso:country":"GB",
    "wof:name":"WS3 5DW",
    "wof:placetype":"postalcode"
},
  "geometry": {"coordinates":[-1.97709922733391,52.63338969744624],"type":"Point"}
}