{
  "type": "Feature",
  "properties": {
    "iso:country":"GB",
    "wof:name":"L12 0AJ",
    "wof:placetype":"postalcode"
},
  "geometry": {"coordinates":[-2.87734611883554,53.44098565423995],"type":"Point"}
}