{
  "type": "Feature",
  "properties": {
    "iso:country":"GB",
    "wof:name":"BD20 5HL",
    "wof:placetype":"postalcode"
},
  "geometry": {"coordinates":[-1.87561546546803,53.87804853614821],"type":"Point"}
}