{
  "type": "Feature",
  "properties": {
    "iso:country": "GB",
    "wof:name": "BN44 3SQ",
    "wof:placetype": "postalcode"
  },
  "geometry": {"coordinates":[-0.322155,50.890893],"type":"Point"}
}
