{
  "type": "Feature",
  "properties": {
    "iso:country":"GB",
    "wof:name":"BN44 3SQ",
    "wof:placetype":"postalcode"
},
  "geometry": {"coordinates":[-0.32215542379712,50.89089283392341],"type":"Point"}
}