{
  "type": "Feature",
  "properties": {
    "iso:country":"GB",
    "wof:name":"WF13 4LG",
    "wof:placetype":"postalcode"
},
  "geometry": {"coordinates":[-1.64345430448478,53.69695167396709],"type":"Point"}
}