{
  "type": "Feature",
  "properties": {
    "iso:country":"GB",
    "wof:name":"LE1 6NW",
    "wof:placetype":"postalcode"
},
  "geometry": {"coordinates":[-1.13010097123625,52.63172872378646],"type":"Point"}
}