{
  "type": "Feature",
  "properties": {
    "date:inception_lower":"1980-01-01",
    "date:inception_upper":"1980-01-31",
    "iso:country":"GB",
    "wof:name":"SS16 5JR",
    "wof:placetype":"postalcode"
},
  "geometry": {"coordinates":[0.460464,51.554655],"type":"Point"}
}