{
  "type": "Feature",
  "properties": {
    "iso:country": "GB",
    "wof:name": "SS16 5JR",
    "wof:placetype": "postalcode"
  },
  "geometry": {"coordinates":[0.460464,51.554655],"type":"Point"}
}
