{
  "type": "Feature",
  "properties": {
    "iso:country":"GB",
    "wof:name":"LA9 7RA",
    "wof:placetype":"postalcode"
},
  "geometry": {"coordinates":[-2.72209483933434,54.31337208296259],"type":"Point"}
}