{
  "type": "Feature",
  "properties": {
    "iso:country": "GB",
    "wof:name": "LA9 7RA",
    "wof:placetype": "postalcode"
  },
  "geometry": {"coordinates":[-2.72211,54.313363],"type":"Point"}
}
