{
  "type": "Feature",
  "properties": {
    "date:inception_lower": "1980-01-01",
    "date:inception_upper": "1980-01-01",
    "iso:country": "GB",
    "wof:name": "LA9 7RA",
    "wof:placetype": "postalcode"
  },
  "geometry": {"coordinates":[-2.72211,54.313363],"type":"Point"}
}
