{
  "type": "Feature",
  "properties": {
    "iso:country": "GB",
    "wof:name": "NW10 4NX",
    "wof:placetype": "postalcode"
  },
  "geometry": {"coordinates":[-0.245745,51.536236],"type":"Point"}
}
