{
  "type": "Feature",
  "properties": {
    "iso:country": "GB",
    "wof:name": "TA3 6LX",
    "wof:placetype": "postalcode"
  },
  "geometry": {"coordinates":[-2.972556,51.021642],"type":"Point"}
}
