{
  "type": "Feature",
  "properties": {
    "iso:country":"GB",
    "wof:name":"TA3 6LX",
    "wof:placetype":"postalcode"
},
  "geometry": {"coordinates":[-2.97255615763902,51.02164245906409],"type":"Point"}
}