{
  "type": "Feature",
  "properties": {
    "iso:country":"GB",
    "wof:name":"W1H 2JF",
    "wof:placetype":"postalcode"
},
  "geometry": {"coordinates":[-0.15948012102826,51.51966275638313],"type":"Point"}
}