{
  "type": "Feature",
  "properties": {
    "date:inception_lower": "1980-01-01",
    "date:inception_upper": "1980-01-01",
    "iso:country": "GB",
    "wof:name": "PL4 7DD",
    "wof:placetype": "postalcode"
  },
  "geometry": {"coordinates":[-4.129214,50.383499],"type":"Point"}
}
