{
  "type": "Feature",
  "properties": {
    "iso:country":"GB",
    "wof:name":"B63 2SL",
    "wof:placetype":"postalcode"
},
  "geometry": {"coordinates":[-2.0774315409457,52.46164214295608],"type":"Point"}
}