{
  "type": "Feature",
  "properties": {
    "iso:country": "GB",
    "wof:name": "M33 2JW",
    "wof:placetype": "postalcode"
  },
  "geometry": {"coordinates":[-2.294814,53.421517],"type":"Point"}
}
