{
  "type": "Feature",
  "properties": {
    "iso:country":"GB",
    "wof:name":"CV11 6LW",
    "wof:placetype":"postalcode"
},
  "geometry": {"coordinates":[-1.4408775297807,52.52897754927594],"type":"Point"}
}