{
  "type": "Feature",
  "properties": {
    "date:inception_lower":"1980-01-01",
    "date:inception_upper":"1980-01-31",
    "iso:country":"GB",
    "wof:name":"CV11 6LW",
    "wof:placetype":"postalcode"
},
  "geometry": {"coordinates":[-1.440877,52.528978],"type":"Point"}
}