{
  "type": "Feature",
  "properties": {
    "iso:country":"GB",
    "wof:name":"CV1 4FP",
    "wof:placetype":"postalcode"
},
  "geometry": {"coordinates":[-1.49902668539895,52.41895680363488],"type":"Point"}
}