{
  "type": "Feature",
  "properties": {
    "date:inception_lower":"1980-01-01",
    "date:inception_upper":"1980-01-31",
    "iso:country":"GB",
    "wof:name":"CV1 4FP",
    "wof:placetype":"postalcode"
},
  "geometry": {"coordinates":[-1.499027,52.418957],"type":"Point"}
}