{
  "type": "Feature",
  "properties": {
    "iso:country": "GB",
    "wof:name": "CV1 4FP",
    "wof:placetype": "postalcode"
  },
  "geometry": {"coordinates":[-1.499027,52.418957],"type":"Point"}
}
