{
  "type": "Feature",
  "properties": {
    "iso:country":"GB",
    "wof:name":"WD5 0HU",
    "wof:placetype":"postalcode"
},
  "geometry": {"coordinates":[-0.42900864893989,51.70025806205758],"type":"Point"}
}