{
  "type": "Feature",
  "properties": {
    "iso:country":"GB",
    "wof:name":"LS17 9DW",
    "wof:placetype":"postalcode"
},
  "geometry": {"coordinates":[-1.44750998025337,53.88121063158084],"type":"Point"}
}