{
  "type": "Feature",
  "properties": {
    "iso:country":"GB",
    "wof:name":"CO2 8BB",
    "wof:placetype":"postalcode"
},
  "geometry": {"coordinates":[0.92202192749925,51.8720144651868],"type":"Point"}
}