{
  "type": "Feature",
  "properties": {
    "iso:country": "GB",
    "wof:name": "SY10 7DA",
    "wof:placetype": "postalcode"
  },
  "geometry": {"coordinates":[-3.072278,52.872858],"type":"Point"}
}
