{
  "type": "Feature",
  "properties": {
    "iso:country":"GB",
    "wof:name":"SY10 7DA",
    "wof:placetype":"postalcode"
},
  "geometry": {"coordinates":[-3.07227807570966,52.87285751803617],"type":"Point"}
}