{
  "type": "Feature",
  "properties": {
    "date:inception_lower": "1980-01-01",
    "date:inception_upper": "1980-01-01",
    "iso:country": "GB",
    "wof:name": "EC3V 9AA",
    "wof:placetype": "postalcode"
  },
  "geometry": {"coordinates":[-0.088968,51.513142],"type":"Point"}
}
