{
  "type": "Feature",
  "properties": {
    "iso:country": "GB",
    "wof:name": "PO21 2SL",
    "wof:placetype": "postalcode"
  },
  "geometry": {"coordinates":[-0.687957,50.78339],"type":"Point"}
}
