{
  "type": "Feature",
  "properties": {
    "date:inception_lower":"1980-01-01",
    "date:inception_upper":"1980-01-31",
    "iso:country":"GB",
    "wof:name":"LU6 2PL",
    "wof:placetype":"postalcode"
},
  "geometry": {"coordinates":[-0.51043,51.854169],"type":"Point"}
}