{
  "type": "Feature",
  "properties": {
    "iso:country":"GB",
    "wof:name":"LU6 2PL",
    "wof:placetype":"postalcode"
},
  "geometry": {"coordinates":[-0.51045653697001,51.85416058754524],"type":"Point"}
}