{
  "type": "Feature",
  "properties": {
    "iso:country":"GB",
    "wof:name":"OX25 3QY",
    "wof:placetype":"postalcode"
},
  "geometry": {"coordinates":[-1.22636399137711,51.86509155945019],"type":"Point"}
}