{
  "type": "Feature",
  "properties": {
    "date:inception_lower": "1980-01-01",
    "date:inception_upper": "1980-01-01",
    "iso:country": "GB",
    "wof:name": "TR11 5QA",
    "wof:placetype": "postalcode"
  },
  "geometry": {"coordinates":[-5.188415,50.121314],"type":"Point"}
}
