{
  "type": "Feature",
  "properties": {
    "iso:country":"GB",
    "wof:name":"NE46 3ER",
    "wof:placetype":"postalcode"
},
  "geometry": {"coordinates":[-2.10812166995753,54.97404846033064],"type":"Point"}
}