{
  "type": "Feature",
  "properties": {
    "iso:country": "GB",
    "wof:name": "NE46 3ER",
    "wof:placetype": "postalcode"
  },
  "geometry": {"coordinates":[-2.108122,54.974048],"type":"Point"}
}
