{
  "type": "Feature",
  "properties": {
    "date:inception_lower": "2018-09-01",
    "date:inception_upper": "2018-09-01",
    "iso:country": "GB",
    "wof:name": "TQ5 9FR",
    "wof:placetype": "postalcode"
  },
  "geometry": {"coordinates":[-3.500766,50.395137],"type":"Point"}
}
