{
  "type": "Feature",
  "properties": {
    "iso:country": "GB",
    "wof:name": "RH17 6HE",
    "wof:placetype": "postalcode"
  },
  "geometry": {"coordinates":[-0.199108,51.059858],"type":"Point"}
}
