{
  "type": "Feature",
  "properties": {
    "date:inception_lower": "1980-01-01",
    "date:inception_upper": "1980-01-01",
    "iso:country": "GB",
    "wof:name": "SW12 8HP",
    "wof:placetype": "postalcode"
  },
  "geometry": {"coordinates":[-0.160528,51.442101],"type":"Point"}
}
