{
  "type": "Feature",
  "properties": {
    "iso:country":"GB",
    "wof:name":"SW12 8HP",
    "wof:placetype":"postalcode"
},
  "geometry": {"coordinates":[-0.16052796433519,51.44210064947927],"type":"Point"}
}