{
  "type": "Feature",
  "properties": {
    "iso:country":"GB",
    "wof:name":"S71 1DZ",
    "wof:placetype":"postalcode"
},
  "geometry": {"coordinates":[-1.47381000969239,53.55216321273604],"type":"Point"}
}