{
  "type": "Feature",
  "properties": {
    "iso:country":"GB",
    "wof:name":"W4 2BQ",
    "wof:placetype":"postalcode"
},
  "geometry": {"coordinates":[-0.25713058045867,51.49106580106742],"type":"Point"}
}