{
  "type": "Feature",
  "properties": {
    "iso:country": "GB",
    "wof:name": "CM8 2YH",
    "wof:placetype": "postalcode"
  },
  "geometry": {"coordinates":[0.629033,51.809197],"type":"Point"}
}
