{
  "type": "Feature",
  "properties": {
    "iso:country":"GB",
    "wof:name":"CM8 2YH",
    "wof:placetype":"postalcode"
},
  "geometry": {"coordinates":[0.62903257322715,51.8091969844902],"type":"Point"}
}