{
  "type": "Feature",
  "properties": {
    "date:inception_lower": "1990-02-01",
    "date:inception_upper": "1990-02-01",
    "iso:country": "GB",
    "wof:name": "CM8 2YH",
    "wof:placetype": "postalcode"
  },
  "geometry": {"coordinates":[0.62915,51.809257],"type":"Point"}
}
