{
  "type": "Feature",
  "properties": {
    "date:inception_lower":"1990-02-01",
    "date:inception_upper":"1990-02-28",
    "iso:country":"GB",
    "wof:name":"CM8 2YH",
    "wof:placetype":"postalcode"
},
  "geometry": {"coordinates":[0.629033,51.809197],"type":"Point"}
}