{
  "type": "Feature",
  "properties": {
    "iso:country":"GB",
    "wof:name":"CB25 9JE",
    "wof:placetype":"postalcode"
},
  "geometry": {"coordinates":[0.18773345482941,52.24294150434471],"type":"Point"}
}