{
  "type": "Feature",
  "properties": {
    "date:inception_lower": "2006-09-01",
    "date:inception_upper": "2006-09-01",
    "iso:country": "GB",
    "wof:name": "CB25 9JE",
    "wof:placetype": "postalcode"
  },
  "geometry": {"coordinates":[0.189208,52.243153],"type":"Point"}
}
