{
  "type": "Feature",
  "properties": {
    "date:inception_lower": "1980-01-01",
    "date:inception_upper": "1980-01-01",
    "iso:country": "GB",
    "wof:name": "B79 8DE",
    "wof:placetype": "postalcode"
  },
  "geometry": {"coordinates":[-1.704066,52.64159],"type":"Point"}
}
