{
  "type": "Feature",
  "properties": {
    "iso:country":"GB",
    "wof:name":"B79 8DE",
    "wof:placetype":"postalcode"
},
  "geometry": {"coordinates":[-1.70406555589853,52.64159019147674],"type":"Point"}
}