{
  "type": "Feature",
  "properties": {
    "iso:country": "GB",
    "wof:name": "B79 8DE",
    "wof:placetype": "postalcode"
  },
  "geometry": {"coordinates":[-1.704066,52.64159],"type":"Point"}
}
