{
  "type": "Feature",
  "properties": {
    "date:inception_lower": "2005-07-01",
    "date:inception_upper": "2005-07-01",
    "iso:country": "GB",
    "wof:name": "DE65 5QH",
    "wof:placetype": "postalcode"
  },
  "geometry": {"coordinates":[-1.683287,52.872613],"type":"Point"}
}
