{
  "type": "Feature",
  "properties": {
    "iso:country":"GB",
    "wof:name":"DE65 5QH",
    "wof:placetype":"postalcode"
},
  "geometry": {"coordinates":[-1.68328727978362,52.87261344939773],"type":"Point"}
}