{
  "type": "Feature",
  "properties": {
    "iso:country":"GB",
    "wof:name":"BA1 1HJ",
    "wof:placetype":"postalcode"
},
  "geometry": {"coordinates":[-2.36313359317455,51.38246729128316],"type":"Point"}
}