{
  "type": "Feature",
  "properties": {
    "iso:country":"GB",
    "wof:name":"SP11 7EP",
    "wof:placetype":"postalcode"
},
  "geometry": {"coordinates":[-1.62559452437629,51.16113488002051],"type":"Point"}
}