{
  "type": "Feature",
  "properties": {
    "iso:country": "GB",
    "wof:name": "SP11 7EP",
    "wof:placetype": "postalcode"
  },
  "geometry": {"coordinates":[-1.625594,51.161135],"type":"Point"}
}
