{
  "type": "Feature",
  "properties": {
    "iso:country":"GB",
    "wof:name":"NG19 7HT",
    "wof:placetype":"postalcode"
},
  "geometry": {"coordinates":[-1.21584540006782,53.16045415463445],"type":"Point"}
}