{
  "type": "Feature",
  "properties": {
    "iso:country":"GB",
    "wof:name":"SE18 1SB",
    "wof:placetype":"postalcode"
},
  "geometry": {"coordinates":[0.08989785406403,51.48841594510788],"type":"Point"}
}