{
  "type": "Feature",
  "properties": {
    "iso:country":"GB",
    "wof:name":"TS3 0NN",
    "wof:placetype":"postalcode"
},
  "geometry": {"coordinates":[-1.18490252680638,54.55183596122833],"type":"Point"}
}