{
  "type": "Feature",
  "properties": {
    "iso:country":"GB",
    "wof:name":"PL21 9FF",
    "wof:placetype":"postalcode"
},
  "geometry": {"coordinates":[-3.92625989488756,50.38807339630132],"type":"Point"}
}