{
  "type": "Feature",
  "properties": {
    "date:inception_lower":"2010-07-01",
    "date:inception_upper":"2010-07-31",
    "iso:country":"GB",
    "wof:name":"PL21 9FF",
    "wof:placetype":"postalcode"
},
  "geometry": {"coordinates":[-3.92626,50.388073],"type":"Point"}
}