{
  "type": "Feature",
  "properties": {
    "iso:country":"GB",
    "wof:name":"TQ7 3AN",
    "wof:placetype":"postalcode"
},
  "geometry": {"coordinates":[-3.87194464575079,50.27836838935779],"type":"Point"}
}