{
  "type": "Feature",
  "properties": {
    "iso:country": "GB",
    "wof:name": "TQ7 3AN",
    "wof:placetype": "postalcode"
  },
  "geometry": {"coordinates":[-3.871928,50.278351],"type":"Point"}
}
