{
  "type": "Feature",
  "properties": {
    "iso:country": "GB",
    "wof:name": "NG2 7PW",
    "wof:placetype": "postalcode"
  },
  "geometry": {"coordinates":[-1.132939,52.929969],"type":"Point"}
}
