{
  "type": "Feature",
  "properties": {
    "iso:country":"GB",
    "wof:name":"NG19 8AX",
    "wof:placetype":"postalcode"
},
  "geometry": {"coordinates":[-1.19125752401798,53.16680694012281],"type":"Point"}
}