{
  "type": "Feature",
  "properties": {
    "iso:country": "GB",
    "wof:name": "S21 3WD",
    "wof:placetype": "postalcode"
  },
  "geometry": {"coordinates":[-1.330449,53.294318],"type":"Point"}
}
