{
  "type": "Feature",
  "properties": {
    "iso:country":"GB",
    "wof:name":"OX28 1NG",
    "wof:placetype":"postalcode"
},
  "geometry": {"coordinates":[-1.48133444619554,51.79092152206856],"type":"Point"}
}