{
  "type": "Feature",
  "properties": {
    "iso:country":"GB",
    "wof:name":"NP12 3NP",
    "wof:placetype":"postalcode"
},
  "geometry": {"coordinates":[-3.21082488028998,51.66671535073863],"type":"Point"}
}