{
  "type": "Feature",
  "properties": {
    "iso:country": "GB",
    "wof:name": "NP12 3NP",
    "wof:placetype": "postalcode"
  },
  "geometry": {"coordinates":[-3.210825,51.666715],"type":"Point"}
}
