{
  "type": "Feature",
  "properties": {
    "date:inception_lower": "1980-01-01",
    "date:inception_upper": "1980-01-01",
    "iso:country": "GB",
    "wof:name": "SM1 2RQ",
    "wof:placetype": "postalcode"
  },
  "geometry": {"coordinates":[-0.195753,51.363207],"type":"Point"}
}
