{
  "type": "Feature",
  "properties": {
    "iso:country": "GB",
    "wof:name": "MK3 5QL",
    "wof:placetype": "postalcode"
  },
  "geometry": {"coordinates":[-0.736845,51.969184],"type":"Point"}
}
