{
  "type": "Feature",
  "properties": {
    "date:inception_lower": "1987-04-01",
    "date:inception_upper": "1987-04-01",
    "iso:country": "GB",
    "wof:name": "BN13 2TZ",
    "wof:placetype": "postalcode"
  },
  "geometry": {"coordinates":[-0.42029,50.828312],"type":"Point"}
}
