{
  "type": "Feature",
  "properties": {
    "iso:country":"GB",
    "wof:name":"ME13 7NQ",
    "wof:placetype":"postalcode"
},
  "geometry": {"coordinates":[0.87555099541878,51.31454915306297],"type":"Point"}
}