{
  "type": "Feature",
  "properties": {
    "date:inception_lower": "1980-01-01",
    "date:inception_upper": "1980-01-01",
    "iso:country": "GB",
    "wof:name": "E3 4NT",
    "wof:placetype": "postalcode"
  },
  "geometry": {"coordinates":[-0.022976,51.526704],"type":"Point"}
}
