{
  "type": "Feature",
  "properties": {
    "iso:country":"GB",
    "wof:name":"G81 2RL",
    "wof:placetype":"postalcode"
},
  "geometry": {"coordinates":[-4.38788108529302,55.90213500419742],"type":"Point"}
}