{
  "type": "Feature",
  "properties": {
    "date:inception_lower": "1991-09-01",
    "date:inception_upper": "1991-09-01",
    "iso:country": "GB",
    "wof:name": "GU3 3EA",
    "wof:placetype": "postalcode"
  },
  "geometry": {"coordinates":[-0.63925,51.248863],"type":"Point"}
}
