{
  "type": "Feature",
  "properties": {
    "iso:country":"GB",
    "wof:name":"N1 1TJ",
    "wof:placetype":"postalcode"
},
  "geometry": {"coordinates":[-0.104175885613,51.54007621184982],"type":"Point"}
}