{
  "type": "Feature",
  "properties": {
    "iso:country": "GB",
    "wof:name": "EX32 0JN",
    "wof:placetype": "postalcode"
  },
  "geometry": {"coordinates":[-4.014273,51.062415],"type":"Point"}
}
