{
  "type": "Feature",
  "properties": {
    "iso:country":"GB",
    "wof:name":"EX32 0JN",
    "wof:placetype":"postalcode"
},
  "geometry": {"coordinates":[-4.01413808681421,51.06246560164303],"type":"Point"}
}