{
  "type": "Feature",
  "properties": {
    "date:inception_lower": "2017-06-01",
    "date:inception_upper": "2017-06-01",
    "iso:country": "GB",
    "wof:name": "LE16 9FN",
    "wof:placetype": "postalcode"
  },
  "geometry": {"coordinates":[-0.94097,52.478811],"type":"Point"}
}
