{
  "type": "Feature",
  "properties": {
    "iso:country": "GB",
    "wof:name": "LE16 9FN",
    "wof:placetype": "postalcode"
  },
  "geometry": {"coordinates":[-0.941244,52.477833],"type":"Point"}
}
