{
  "type": "Feature",
  "properties": {
    "iso:country":"GB",
    "wof:name":"KA3 3BA",
    "wof:placetype":"postalcode"
},
  "geometry": {"coordinates":[-4.53015605266426,55.67587228456877],"type":"Point"}
}