{
  "type": "Feature",
  "properties": {
    "iso:country": "GB",
    "wof:name": "KA16 9JP",
    "wof:placetype": "postalcode"
  },
  "geometry": {"coordinates":[-4.311518,55.604975],"type":"Point"}
}
