{
  "type": "Feature",
  "properties": {
    "date:inception_lower":"1980-01-01",
    "date:inception_upper":"1980-01-31",
    "iso:country":"GB",
    "wof:name":"KA16 9JP",
    "wof:placetype":"postalcode"
},
  "geometry": {"coordinates":[-4.311518,55.604975],"type":"Point"}
}