{
  "type": "Feature",
  "properties": {
    "iso:country": "GB",
    "wof:name": "HX2 0DE",
    "wof:placetype": "postalcode"
  },
  "geometry": {"coordinates":[-1.89343,53.726969],"type":"Point"}
}
