{
  "type": "Feature",
  "properties": {
    "date:inception_lower": "1980-01-01",
    "date:inception_upper": "1980-01-01",
    "iso:country": "GB",
    "wof:name": "BA6 8TR",
    "wof:placetype": "postalcode"
  },
  "geometry": {"coordinates":[-2.690711,51.096513],"type":"Point"}
}
