{
  "type": "Feature",
  "properties": {
    "iso:country": "GB",
    "wof:name": "B23 7EZ",
    "wof:placetype": "postalcode"
  },
  "geometry": {"coordinates":[-1.866294,52.522868],"type":"Point"}
}
