{
  "type": "Feature",
  "properties": {
    "iso:country":"GB",
    "wof:name":"B23 7EZ",
    "wof:placetype":"postalcode"
},
  "geometry": {"coordinates":[-1.8662936001724,52.52286786169159],"type":"Point"}
}