{
  "type": "Feature",
  "properties": {
    "iso:country": "GB",
    "wof:name": "SR5 2NX",
    "wof:placetype": "postalcode"
  },
  "geometry": {"coordinates":[-1.405402,54.925448],"type":"Point"}
}
