{
  "type": "Feature",
  "properties": {
    "date:inception_lower":"2005-11-01",
    "date:inception_upper":"2005-11-30",
    "iso:country":"GB",
    "wof:name":"CO3 8WA",
    "wof:placetype":"postalcode"
},
  "geometry": {"coordinates":[0.827758,51.878969],"type":"Point"}
}