{
  "type": "Feature",
  "properties": {
    "iso:country":"GB",
    "wof:name":"CO3 8WA",
    "wof:placetype":"postalcode"
},
  "geometry": {"coordinates":[0.82775808132928,51.87896887737639],"type":"Point"}
}