{
  "type": "Feature",
  "properties": {
    "iso:country": "GB",
    "wof:name": "CO3 8WA",
    "wof:placetype": "postalcode"
  },
  "geometry": {"coordinates":[0.827758,51.878969],"type":"Point"}
}
