{
  "type": "Feature",
  "properties": {
    "iso:country": "GB",
    "wof:name": "G4 9HA",
    "wof:placetype": "postalcode"
  },
  "geometry": {"coordinates":[-4.278601,55.873254],"type":"Point"}
}
