{
  "type": "Feature",
  "properties": {
    "date:inception_lower": "1980-01-01",
    "date:inception_upper": "1980-01-01",
    "iso:country": "GB",
    "wof:name": "G4 9HA",
    "wof:placetype": "postalcode"
  },
  "geometry": {"coordinates":[-4.278601,55.873254],"type":"Point"}
}
