{
  "type": "Feature",
  "properties": {
    "iso:country": "GB",
    "wof:name": "OX13 6HN",
    "wof:placetype": "postalcode"
  },
  "geometry": {"coordinates":[-1.30193,51.686316],"type":"Point"}
}
