{
  "type": "Feature",
  "properties": {
    "iso:country":"GB",
    "wof:name":"G20 0RG",
    "wof:placetype":"postalcode"
},
  "geometry": {"coordinates":[-4.28465503022588,55.89630226819909],"type":"Point"}
}