{
  "type": "Feature",
  "properties": {
    "iso:country": "GB",
    "wof:name": "NG10 3HX",
    "wof:placetype": "postalcode"
  },
  "geometry": {"coordinates":[-1.294234,52.887022],"type":"Point"}
}
