{
  "type": "Feature",
  "properties": {
    "iso:country":"GB",
    "wof:name":"HA7 4TJ",
    "wof:placetype":"postalcode"
},
  "geometry": {"coordinates":[-0.30303549995135,51.61402494599091],"type":"Point"}
}