{
  "type": "Feature",
  "properties": {
    "date:inception_lower":"1980-01-01",
    "date:inception_upper":"1980-01-31",
    "iso:country":"GB",
    "wof:name":"NN1 1LD",
    "wof:placetype":"postalcode"
},
  "geometry": {"coordinates":[-0.891693,52.237224],"type":"Point"}
}