{
  "type": "Feature",
  "properties": {
    "iso:country":"GB",
    "wof:name":"NN1 1LD",
    "wof:placetype":"postalcode"
},
  "geometry": {"coordinates":[-0.8916933372631,52.23722443522318],"type":"Point"}
}