{
  "type": "Feature",
  "properties": {
    "date:inception_lower": "1981-06-01",
    "date:inception_upper": "1981-06-01",
    "iso:country": "GB",
    "wof:name": "PR2 7AS",
    "wof:placetype": "postalcode"
  },
  "geometry": {"coordinates":[-2.73768,53.785756],"type":"Point"}
}
