{
  "type": "Feature",
  "properties": {
    "iso:country":"GB",
    "wof:name":"PR2 7AS",
    "wof:placetype":"postalcode"
},
  "geometry": {"coordinates":[-2.73767990948866,53.78575638669833],"type":"Point"}
}