{
  "type": "Feature",
  "properties": {
    "date:inception_lower": "1980-01-01",
    "date:inception_upper": "1980-01-01",
    "iso:country": "GB",
    "wof:name": "IV27 4JB",
    "wof:placetype": "postalcode"
  },
  "geometry": {"coordinates":[-5.275705,58.170377],"type":"Point"}
}
