{
  "type": "Feature",
  "properties": {
    "iso:country":"GB",
    "wof:name":"SS0 9BJ",
    "wof:placetype":"postalcode"
},
  "geometry": {"coordinates":[0.69711895118026,51.5480572688081],"type":"Point"}
}