{
  "type": "Feature",
  "properties": {
    "iso:country": "GB",
    "wof:name": "SS0 9BJ",
    "wof:placetype": "postalcode"
  },
  "geometry": {"coordinates":[0.697119,51.548057],"type":"Point"}
}
