{
  "type": "Feature",
  "properties": {
    "date:inception_lower": "1980-01-01",
    "date:inception_upper": "1980-01-01",
    "iso:country": "GB",
    "wof:name": "TS5 8NS",
    "wof:placetype": "postalcode"
  },
  "geometry": {"coordinates":[-1.258306,54.542614],"type":"Point"}
}
