{
  "type": "Feature",
  "properties": {
    "iso:country":"GB",
    "wof:name":"TS5 8NS",
    "wof:placetype":"postalcode"
},
  "geometry": {"coordinates":[-1.25829255063633,54.54260192826708],"type":"Point"}
}