{
  "type": "Feature",
  "properties": {
    "date:inception_lower": "2006-04-01",
    "date:inception_upper": "2006-04-01",
    "iso:country": "GB",
    "wof:name": "M33 2GS",
    "wof:placetype": "postalcode"
  },
  "geometry": {"coordinates":[-2.294037,53.42444],"type":"Point"}
}
