{
  "type": "Feature",
  "properties": {
    "iso:country":"GB",
    "wof:name":"M33 2GS",
    "wof:placetype":"postalcode"
},
  "geometry": {"coordinates":[-2.29397019597291,53.42351479879988],"type":"Point"}
}