{
  "type": "Feature",
  "properties": {
    "iso:country":"GB",
    "wof:name":"KT11 1BZ",
    "wof:placetype":"postalcode"
},
  "geometry": {"coordinates":[-0.41386622280046,51.33488093025014],"type":"Point"}
}