{
  "type": "Feature",
  "properties": {
    "date:inception_lower": "1990-08-01",
    "date:inception_upper": "1990-08-01",
    "iso:country": "GB",
    "wof:name": "AB52 6QH",
    "wof:placetype": "postalcode"
  },
  "geometry": {"coordinates":[-2.586571,57.319264],"type":"Point"}
}
