{
  "type": "Feature",
  "properties": {
    "iso:country":"GB",
    "wof:name":"AB52 6QH",
    "wof:placetype":"postalcode"
},
  "geometry": {"coordinates":[-2.58657094437331,57.31926415791042],"type":"Point"}
}