{
  "type": "Feature",
  "properties": {
    "iso:country": "GB",
    "wof:name": "EX34 8NJ",
    "wof:placetype": "postalcode"
  },
  "geometry": {"coordinates":[-4.109401,51.155278],"type":"Point"}
}
