{
  "type": "Feature",
  "properties": {
    "iso:country":"GB",
    "wof:name":"EX34 8NJ",
    "wof:placetype":"postalcode"
},
  "geometry": {"coordinates":[-4.10940133069666,51.15527761110285],"type":"Point"}
}