{
  "type": "Feature",
  "properties": {
    "iso:country": "GB",
    "wof:name": "RG20 9XU",
    "wof:placetype": "postalcode"
  },
  "geometry": {"coordinates":[-1.397691,51.33755],"type":"Point"}
}
