{
  "type": "Feature",
  "properties": {
    "iso:country":"GB",
    "wof:name":"RG20 9XU",
    "wof:placetype":"postalcode"
},
  "geometry": {"coordinates":[-1.39769111355177,51.33755036017562],"type":"Point"}
}