{
  "type": "Feature",
  "properties": {
    "date:inception_lower": "2012-04-01",
    "date:inception_upper": "2012-04-01",
    "iso:country": "GB",
    "wof:name": "BN1 1UE",
    "wof:placetype": "postalcode"
  },
  "geometry": {"coordinates":[-0.138083,50.823703],"type":"Point"}
}
