{
  "type": "Feature",
  "properties": {
    "iso:country": "GB",
    "wof:name": "BN1 1UE",
    "wof:placetype": "postalcode"
  },
  "geometry": {"coordinates":[-0.138083,50.823703],"type":"Point"}
}
