{
  "type": "Feature",
  "properties": {
    "iso:country": "GB",
    "wof:name": "L19 3PE",
    "wof:placetype": "postalcode"
  },
  "geometry": {"coordinates":[-2.920223,53.367177],"type":"Point"}
}
