{
  "type": "Feature",
  "properties": {
    "date:inception_lower": "1980-01-01",
    "date:inception_upper": "1980-01-01",
    "iso:country": "GB",
    "wof:name": "L19 3PE",
    "wof:placetype": "postalcode"
  },
  "geometry": {"coordinates":[-2.920223,53.367177],"type":"Point"}
}
