{
  "type": "Feature",
  "properties": {
    "iso:country": "GB",
    "wof:name": "NN29 7AJ",
    "wof:placetype": "postalcode"
  },
  "geometry": {"coordinates":[-0.644612,52.284789],"type":"Point"}
}
