{
  "type": "Feature",
  "properties": {
    "iso:country": "GB",
    "wof:name": "HP11 2LW",
    "wof:placetype": "postalcode"
  },
  "geometry": {"coordinates":[-0.759864,51.633586],"type":"Point"}
}
