{
  "type": "Feature",
  "properties": {
    "iso:country":"GB",
    "wof:name":"DN2 4HN",
    "wof:placetype":"postalcode"
},
  "geometry": {"coordinates":[-1.11209548820778,53.538556157913],"type":"Point"}
}