{
  "type": "Feature",
  "properties": {
    "date:inception_lower": "1980-01-01",
    "date:inception_upper": "1980-01-01",
    "iso:country": "GB",
    "wof:name": "B42 2DJ",
    "wof:placetype": "postalcode"
  },
  "geometry": {"coordinates":[-1.909715,52.536304],"type":"Point"}
}
