{
  "type": "Feature",
  "properties": {
    "iso:country":"GB",
    "wof:name":"KT19 8EU",
    "wof:placetype":"postalcode"
},
  "geometry": {"coordinates":[-0.26873835719969,51.33429153125632],"type":"Point"}
}