{
  "type": "Feature",
  "properties": {
    "date:inception_lower":"1980-01-01",
    "date:inception_upper":"1980-01-31",
    "iso:country":"GB",
    "wof:name":"BS23 4HE",
    "wof:placetype":"postalcode"
},
  "geometry": {"coordinates":[-2.980208,51.332314],"type":"Point"}
}