{
  "type": "Feature",
  "properties": {
    "iso:country":"GB",
    "wof:name":"BS23 4HE",
    "wof:placetype":"postalcode"
},
  "geometry": {"coordinates":[-2.98020762302681,51.33231447129342],"type":"Point"}
}