{
  "type": "Feature",
  "properties": {
    "iso:country":"GB",
    "wof:name":"PO7 8QY",
    "wof:placetype":"postalcode"
},
  "geometry": {"coordinates":[-1.00783998167245,50.88576601631696],"type":"Point"}
}