{
  "type": "Feature",
  "properties": {
    "iso:country":"GB",
    "wof:name":"W1T 4RR",
    "wof:placetype":"postalcode"
},
  "geometry": {"coordinates":[-0.13675473452854,51.51987948205942],"type":"Point"}
}