{
  "type": "Feature",
  "properties": {
    "iso:country": "GB",
    "wof:name": "W1T 4RR",
    "wof:placetype": "postalcode"
  },
  "geometry": {"coordinates":[-0.136755,51.519879],"type":"Point"}
}
