{
  "type": "Feature",
  "properties": {
    "iso:country":"GB",
    "wof:name":"DT3 5HX",
    "wof:placetype":"postalcode"
},
  "geometry": {"coordinates":[-2.46724270841072,50.62845428630504],"type":"Point"}
}