{
  "type": "Feature",
  "properties": {
    "iso:country": "GB",
    "wof:name": "DT3 5HX",
    "wof:placetype": "postalcode"
  },
  "geometry": {"coordinates":[-2.467243,50.628454],"type":"Point"}
}
