{
  "type": "Feature",
  "properties": {
    "date:inception_lower":"2004-05-01",
    "date:inception_upper":"2004-05-31",
    "iso:country":"GB",
    "wof:name":"DT3 5HX",
    "wof:placetype":"postalcode"
},
  "geometry": {"coordinates":[-2.467243,50.628454],"type":"Point"}
}