{
  "type": "Feature",
  "properties": {
    "iso:country":"GB",
    "wof:name":"SA33 4QE",
    "wof:placetype":"postalcode"
},
  "geometry": {"coordinates":[-4.46254785093401,51.77194572421816],"type":"Point"}
}