{
  "type": "Feature",
  "properties": {
    "date:inception_lower": "1980-01-01",
    "date:inception_upper": "1980-01-01",
    "iso:country": "GB",
    "wof:name": "SA33 4QE",
    "wof:placetype": "postalcode"
  },
  "geometry": {"coordinates":[-4.462548,51.771946],"type":"Point"}
}
