{
  "type": "Feature",
  "properties": {
    "iso:country":"GB",
    "wof:name":"BA21 3AG",
    "wof:placetype":"postalcode"
},
  "geometry": {"coordinates":[-2.64046633915301,50.9461332403766],"type":"Point"}
}