{
  "type": "Feature",
  "properties": {
    "date:inception_lower": "1980-01-01",
    "date:inception_upper": "1980-01-01",
    "iso:country": "GB",
    "wof:name": "BA21 3AG",
    "wof:placetype": "postalcode"
  },
  "geometry": {"coordinates":[-2.640453,50.946126],"type":"Point"}
}
