{
  "type": "Feature",
  "properties": {
    "iso:country":"GB",
    "wof:name":"CM9 8JT",
    "wof:placetype":"postalcode"
},
  "geometry": {"coordinates":[0.73924057895437,51.77862954809387],"type":"Point"}
}