{
  "type": "Feature",
  "properties": {
    "iso:country":"GB",
    "wof:name":"WS2 8QS",
    "wof:placetype":"postalcode"
},
  "geometry": {"coordinates":[-1.99811165685305,52.58974657995005],"type":"Point"}
}