{
  "type": "Feature",
  "properties": {
    "iso:country":"GB",
    "wof:name":"EX9 6AN",
    "wof:placetype":"postalcode"
},
  "geometry": {"coordinates":[-3.34393283324784,50.63598238608023],"type":"Point"}
}