{
  "type": "Feature",
  "properties": {
    "date:inception_lower":"1980-01-01",
    "date:inception_upper":"1980-01-31",
    "iso:country":"GB",
    "wof:name":"EX9 6AN",
    "wof:placetype":"postalcode"
},
  "geometry": {"coordinates":[-3.343933,50.635982],"type":"Point"}
}