{
  "type": "Feature",
  "properties": {
    "iso:country": "GB",
    "wof:name": "PL15 7FE",
    "wof:placetype": "postalcode"
  },
  "geometry": {"coordinates":[-4.435727,50.599476],"type":"Point"}
}
