{
  "type": "Feature",
  "properties": {
    "date:inception_lower": "2010-07-01",
    "date:inception_upper": "2010-07-01",
    "iso:country": "GB",
    "wof:name": "PL15 7FE",
    "wof:placetype": "postalcode"
  },
  "geometry": {"coordinates":[-4.435727,50.599476],"type":"Point"}
}
