{
  "type": "Feature",
  "properties": {
    "iso:country":"GB",
    "wof:name":"DE4 5EG",
    "wof:placetype":"postalcode"
},
  "geometry": {"coordinates":[-1.49897229062831,53.08400975099805],"type":"Point"}
}