{
  "type": "Feature",
  "properties": {
    "date:inception_lower": "1980-01-01",
    "date:inception_upper": "1980-01-01",
    "iso:country": "GB",
    "wof:name": "DE4 5EG",
    "wof:placetype": "postalcode"
  },
  "geometry": {"coordinates":[-1.498972,53.08401],"type":"Point"}
}
