{
  "type": "Feature",
  "properties": {
    "iso:country":"GB",
    "wof:name":"HX1 1QR",
    "wof:placetype":"postalcode"
},
  "geometry": {"coordinates":[-1.85461435381217,53.72270404521055],"type":"Point"}
}