{
  "type": "Feature",
  "properties": {
    "iso:country":"GB",
    "wof:name":"HP27 0SZ",
    "wof:placetype":"postalcode"
},
  "geometry": {"coordinates":[-0.78097293007168,51.69291859070343],"type":"Point"}
}