{
  "type": "Feature",
  "properties": {
    "iso:country":"GB",
    "wof:name":"SK10 2EH",
    "wof:placetype":"postalcode"
},
  "geometry": {"coordinates":[-2.12837019759911,53.27017403531484],"type":"Point"}
}