{
  "type": "Feature",
  "properties": {
    "date:inception_lower": "1980-01-01",
    "date:inception_upper": "1980-01-01",
    "iso:country": "GB",
    "wof:name": "SK10 2EH",
    "wof:placetype": "postalcode"
  },
  "geometry": {"coordinates":[-2.12837,53.270174],"type":"Point"}
}
