{
  "type": "Feature",
  "properties": {
    "iso:country": "GB",
    "wof:name": "EX31 3LQ",
    "wof:placetype": "postalcode"
  },
  "geometry": {"coordinates":[-4.053323,51.009222],"type":"Point"}
}
