{
  "type": "Feature",
  "properties": {
    "date:inception_lower":"1980-01-01",
    "date:inception_upper":"1980-01-31",
    "iso:country":"GB",
    "wof:name":"EX31 3LQ",
    "wof:placetype":"postalcode"
},
  "geometry": {"coordinates":[-4.053323,51.009222],"type":"Point"}
}