{
  "type": "Feature",
  "properties": {
    "iso:country":"GB",
    "wof:name":"EX31 3LQ",
    "wof:placetype":"postalcode"
},
  "geometry": {"coordinates":[-4.05298005589406,51.00942103813554],"type":"Point"}
}