{
  "type": "Feature",
  "properties": {
    "iso:country":"GB",
    "wof:name":"KT22 8AN",
    "wof:placetype":"postalcode"
},
  "geometry": {"coordinates":[-0.32864533923392,51.29516268853014],"type":"Point"}
}