{
  "type": "Feature",
  "properties": {
    "iso:country": "GB",
    "wof:name": "PA13 4BB",
    "wof:placetype": "postalcode"
  },
  "geometry": {"coordinates":[-4.627007,55.889731],"type":"Point"}
}
