{
  "type": "Feature",
  "properties": {
    "iso:country": "GB",
    "wof:name": "FK4 1GF",
    "wof:placetype": "postalcode"
  },
  "geometry": {"coordinates":[-3.894774,56.0003],"type":"Point"}
}
