{
  "type": "Feature",
  "properties": {
    "date:inception_lower": "2002-12-01",
    "date:inception_upper": "2002-12-01",
    "iso:country": "GB",
    "wof:name": "FK4 1GF",
    "wof:placetype": "postalcode"
  },
  "geometry": {"coordinates":[-3.894774,56.0003],"type":"Point"}
}
