{
  "type": "Feature",
  "properties": {
    "iso:country":"GB",
    "wof:name":"FK4 1GF",
    "wof:placetype":"postalcode"
},
  "geometry": {"coordinates":[-3.89477448954214,56.0003001358501],"type":"Point"}
}