{
  "type": "Feature",
  "properties": {
    "iso:country":"GB",
    "wof:name":"ME1 3JJ",
    "wof:placetype":"postalcode"
},
  "geometry": {"coordinates":[0.48548140463874,51.37217270809492],"type":"Point"}
}