{
  "type": "Feature",
  "properties": {
    "date:inception_lower":"1980-01-01",
    "date:inception_upper":"1980-01-31",
    "iso:country":"GB",
    "wof:name":"ME1 3JJ",
    "wof:placetype":"postalcode"
},
  "geometry": {"coordinates":[0.485481,51.372173],"type":"Point"}
}