{
  "type": "Feature",
  "properties": {
    "iso:country":"GB",
    "wof:name":"RH20 4QX",
    "wof:placetype":"postalcode"
},
  "geometry": {"coordinates":[-0.46305317900349,50.92311250258263],"type":"Point"}
}