{
  "type": "Feature",
  "properties": {
    "date:inception_lower": "1981-06-01",
    "date:inception_upper": "1981-06-01",
    "iso:country": "GB",
    "wof:name": "RH20 4QX",
    "wof:placetype": "postalcode"
  },
  "geometry": {"coordinates":[-0.463053,50.923112],"type":"Point"}
}
