{
  "type": "Feature",
  "properties": {
    "iso:country": "GB",
    "wof:name": "CT2 9BB",
    "wof:placetype": "postalcode"
  },
  "geometry": {"coordinates":[1.030008,51.284703],"type":"Point"}
}
