{
  "type": "Feature",
  "properties": {
    "iso:country":"GB",
    "wof:name":"CT2 9BB",
    "wof:placetype":"postalcode"
},
  "geometry": {"coordinates":[1.03000797623098,51.28470287977056],"type":"Point"}
}