{
  "type": "Feature",
  "properties": {
    "date:inception_lower": "2018-12-01",
    "date:inception_upper": "2018-12-01",
    "iso:country": "GB",
    "wof:name": "SN11 0FP",
    "wof:placetype": "postalcode"
  },
  "geometry": {"coordinates":[-1.998577,51.423563],"type":"Point"}
}
