{
  "type": "Feature",
  "properties": {
    "iso:country": "GB",
    "wof:name": "SN11 0FP",
    "wof:placetype": "postalcode"
  },
  "geometry": {"coordinates":[-1.998577,51.423563],"type":"Point"}
}
