{
  "type": "Feature",
  "properties": {
    "iso:country":"GB",
    "wof:name":"DD1 3HZ",
    "wof:placetype":"postalcode"
},
  "geometry": {"coordinates":[-2.95695806782152,56.46293821712987],"type":"Point"}
}