{
  "type": "Feature",
  "properties": {
    "date:inception_lower": "2013-02-01",
    "date:inception_upper": "2013-02-01",
    "iso:country": "GB",
    "wof:name": "DD1 3HZ",
    "wof:placetype": "postalcode"
  },
  "geometry": {"coordinates":[-2.956958,56.462938],"type":"Point"}
}
