{
  "type": "Feature",
  "properties": {
    "iso:country":"GB",
    "wof:name":"OX3 7HG",
    "wof:placetype":"postalcode"
},
  "geometry": {"coordinates":[-1.2053235597996,51.75023275159727],"type":"Point"}
}