{
  "type": "Feature",
  "properties": {
    "iso:country": "GB",
    "wof:name": "OX3 7HG",
    "wof:placetype": "postalcode"
  },
  "geometry": {"coordinates":[-1.205324,51.750233],"type":"Point"}
}
