{
  "type": "Feature",
  "properties": {
    "iso:country":"GB",
    "wof:name":"BB4 8JE",
    "wof:placetype":"postalcode"
},
  "geometry": {"coordinates":[-2.28986257003056,53.71260771942024],"type":"Point"}
}