{
  "type": "Feature",
  "properties": {
    "iso:country":"GB",
    "wof:name":"M16 0GG",
    "wof:placetype":"postalcode"
},
  "geometry": {"coordinates":[-2.28437519938423,53.44914638248072],"type":"Point"}
}