{
  "type": "Feature",
  "properties": {
    "iso:country":"GB",
    "wof:name":"LS17 0DD",
    "wof:placetype":"postalcode"
},
  "geometry": {"coordinates":[-1.57575384550785,53.93622548848175],"type":"Point"}
}