{
  "type": "Feature",
  "properties": {
    "date:inception_lower":"2010-03-01",
    "date:inception_upper":"2010-03-31",
    "iso:country":"GB",
    "wof:name":"BB11 9TA",
    "wof:placetype":"postalcode"
},
  "geometry": {"coordinates":[-2.244648,53.787597],"type":"Point"}
}