{
  "type": "Feature",
  "properties": {
    "iso:country": "GB",
    "wof:name": "CV3 1PU",
    "wof:placetype": "postalcode"
  },
  "geometry": {"coordinates":[-1.485585,52.400146],"type":"Point"}
}
