{
  "type": "Feature",
  "properties": {
    "iso:country":"GB",
    "wof:name":"CV3 1PU",
    "wof:placetype":"postalcode"
},
  "geometry": {"coordinates":[-1.48558553300053,52.40014565408337],"type":"Point"}
}