{
  "type": "Feature",
  "properties": {
    "date:inception_lower": "2017-09-01",
    "date:inception_upper": "2017-09-01",
    "iso:country": "GB",
    "wof:name": "NG33 5FD",
    "wof:placetype": "postalcode"
  },
  "geometry": {"coordinates":[-0.665256,52.845888],"type":"Point"}
}
