{
  "type": "Feature",
  "properties": {
    "iso:country": "GB",
    "wof:name": "SA68 0TN",
    "wof:placetype": "postalcode"
  },
  "geometry": {"coordinates":[-4.847348,51.710204],"type":"Point"}
}
