{
  "type": "Feature",
  "properties": {
    "date:inception_lower": "1980-01-01",
    "date:inception_upper": "1980-01-01",
    "iso:country": "GB",
    "wof:name": "SA68 0TN",
    "wof:placetype": "postalcode"
  },
  "geometry": {"coordinates":[-4.847348,51.710204],"type":"Point"}
}
