{
  "type": "Feature",
  "properties": {
    "iso:country": "GB",
    "wof:name": "WS4 1HU",
    "wof:placetype": "postalcode"
  },
  "geometry": {"coordinates":[-1.94771,52.60865],"type":"Point"}
}
