{
  "type": "Feature",
  "properties": {
    "iso:country":"GB",
    "wof:name":"WS4 1HU",
    "wof:placetype":"postalcode"
},
  "geometry": {"coordinates":[-1.94771047135654,52.6086496546969],"type":"Point"}
}