{
  "type": "Feature",
  "properties": {
    "iso:country": "GB",
    "wof:name": "LN6 3RE",
    "wof:placetype": "postalcode"
  },
  "geometry": {"coordinates":[-0.604365,53.207242],"type":"Point"}
}
