{
  "type": "Feature",
  "properties": {
    "iso:country":"GB",
    "wof:name":"LN6 3RE",
    "wof:placetype":"postalcode"
},
  "geometry": {"coordinates":[-0.60436455042636,53.20724222971276],"type":"Point"}
}