{
  "type": "Feature",
  "properties": {
    "iso:country": "GB",
    "wof:name": "TA12 6DQ",
    "wof:placetype": "postalcode"
  },
  "geometry": {"coordinates":[-2.769951,50.978229],"type":"Point"}
}
