{
  "type": "Feature",
  "properties": {
    "iso:country": "GB",
    "wof:name": "SY7 0QN",
    "wof:placetype": "postalcode"
  },
  "geometry": {"coordinates":[-2.877853,52.367233],"type":"Point"}
}
