{
  "type": "Feature",
  "properties": {
    "iso:country":"GB",
    "wof:name":"HU8 9QN",
    "wof:placetype":"postalcode"
},
  "geometry": {"coordinates":[-0.26978586204995,53.78059824035795],"type":"Point"}
}