{
  "type": "Feature",
  "properties": {
    "iso:country": "GB",
    "wof:name": "CT17 0XF",
    "wof:placetype": "postalcode"
  },
  "geometry": {"coordinates":[1.273564,51.148538],"type":"Point"}
}
