{
  "type": "Feature",
  "properties": {
    "iso:country": "GB",
    "wof:name": "UB8 3TT",
    "wof:placetype": "postalcode"
  },
  "geometry": {"coordinates":[-0.46981,51.535101],"type":"Point"}
}
