{
  "type": "Feature",
  "properties": {
    "iso:country":"GB",
    "wof:name":"UB8 3TT",
    "wof:placetype":"postalcode"
},
  "geometry": {"coordinates":[-0.46980986838406,51.53510073376166],"type":"Point"}
}