{
  "type": "Feature",
  "properties": {
    "date:inception_lower": "2005-01-01",
    "date:inception_upper": "2005-01-01",
    "iso:country": "GB",
    "wof:name": "ME16 0ZL",
    "wof:placetype": "postalcode"
  },
  "geometry": {"coordinates":[0.482856,51.270736],"type":"Point"}
}
