{
  "type": "Feature",
  "properties": {
    "iso:country":"GB",
    "wof:name":"KT4 8LH",
    "wof:placetype":"postalcode"
},
  "geometry": {"coordinates":[-0.23334682853053,51.37772798409047],"type":"Point"}
}