{
  "type": "Feature",
  "properties": {
    "date:inception_lower": "1980-01-01",
    "date:inception_upper": "1980-01-01",
    "iso:country": "GB",
    "wof:name": "MK1 1DX",
    "wof:placetype": "postalcode"
  },
  "geometry": {"coordinates":[-0.73295,52.002553],"type":"Point"}
}
