{
  "type": "Feature",
  "properties": {
    "iso:country":"GB",
    "wof:name":"IV18 0HF",
    "wof:placetype":"postalcode"
},
  "geometry": {"coordinates":[-4.15976877913397,57.68892493168281],"type":"Point"}
}