{
  "type": "Feature",
  "properties": {
    "date:inception_lower":"1980-01-01",
    "date:inception_upper":"1980-01-31",
    "iso:country":"GB",
    "wof:name":"IV18 0HF",
    "wof:placetype":"postalcode"
},
  "geometry": {"coordinates":[-4.159769,57.688925],"type":"Point"}
}