{
  "type": "Feature",
  "properties": {
    "iso:country": "GB",
    "wof:name": "IV18 0HF",
    "wof:placetype": "postalcode"
  },
  "geometry": {"coordinates":[-4.159769,57.688925],"type":"Point"}
}
