{
  "type": "Feature",
  "properties": {
    "iso:country": "GB",
    "wof:name": "KT13 0DE",
    "wof:placetype": "postalcode"
  },
  "geometry": {"coordinates":[-0.452407,51.362266],"type":"Point"}
}
