{
  "type": "Feature",
  "properties": {
    "iso:country":"GB",
    "wof:name":"KT13 0DE",
    "wof:placetype":"postalcode"
},
  "geometry": {"coordinates":[-0.45240729714055,51.36226581296756],"type":"Point"}
}