{
  "type": "Feature",
  "properties": {
    "iso:country":"GB",
    "wof:name":"HU5 3JU",
    "wof:placetype":"postalcode"
},
  "geometry": {"coordinates":[-0.36678174477741,53.75488358251582],"type":"Point"}
}