{
  "type": "Feature",
  "properties": {
    "iso:country":"GB",
    "wof:name":"CM7 4JD",
    "wof:placetype":"postalcode"
},
  "geometry": {"coordinates":[0.45323317604183,51.98139701223975],"type":"Point"}
}