{
  "type": "Feature",
  "properties": {
    "iso:country": "GB",
    "wof:name": "DY3 1TG",
    "wof:placetype": "postalcode"
  },
  "geometry": {"coordinates":[-2.115989,52.535011],"type":"Point"}
}
