{
  "type": "Feature",
  "properties": {
    "iso:country": "GB",
    "wof:name": "BR6 8ND",
    "wof:placetype": "postalcode"
  },
  "geometry": {"coordinates":[0.059146,51.366243],"type":"Point"}
}
