{
  "type": "Feature",
  "properties": {
    "iso:country":"GB",
    "wof:name":"BR6 8ND",
    "wof:placetype":"postalcode"
},
  "geometry": {"coordinates":[0.05914639788455,51.36624341416204],"type":"Point"}
}