{
  "type": "Feature",
  "properties": {
    "date:inception_lower": "1980-01-01",
    "date:inception_upper": "1980-01-01",
    "iso:country": "GB",
    "wof:name": "TS3 0SJ",
    "wof:placetype": "postalcode"
  },
  "geometry": {"coordinates":[-1.180978,54.557017],"type":"Point"}
}
