{
  "type": "Feature",
  "properties": {
    "iso:country":"GB",
    "wof:name":"TS3 0SJ",
    "wof:placetype":"postalcode"
},
  "geometry": {"coordinates":[-1.18091977336737,54.5569317299456],"type":"Point"}
}