{
  "type": "Feature",
  "properties": {
    "iso:country":"GB",
    "wof:name":"LE12 8NP",
    "wof:placetype":"postalcode"
},
  "geometry": {"coordinates":[-1.14396495978722,52.74953444604215],"type":"Point"}
}