{
  "type": "Feature",
  "properties": {
    "iso:country": "GB",
    "wof:name": "S66 8NE",
    "wof:placetype": "postalcode"
  },
  "geometry": {"coordinates":[-1.211329,53.421167],"type":"Point"}
}
