{
  "type": "Feature",
  "properties": {
    "iso:country": "GB",
    "wof:name": "OX10 6BL",
    "wof:placetype": "postalcode"
  },
  "geometry": {"coordinates":[-1.121072,51.572393],"type":"Point"}
}
