{
  "type": "Feature",
  "properties": {
    "iso:country":"GB",
    "wof:name":"OX10 6BL",
    "wof:placetype":"postalcode"
},
  "geometry": {"coordinates":[-1.12107203607309,51.57239349229677],"type":"Point"}
}