{
  "type": "Feature",
  "properties": {
    "iso:country":"GB",
    "wof:name":"DA15 9LQ",
    "wof:placetype":"postalcode"
},
  "geometry": {"coordinates":[0.11845645998453,51.44477355022563],"type":"Point"}
}