{
  "type": "Feature",
  "properties": {
    "iso:country":"GB",
    "wof:name":"BH17 8PJ",
    "wof:placetype":"postalcode"
},
  "geometry": {"coordinates":[-1.97280915887302,50.73986467546075],"type":"Point"}
}