{
  "type": "Feature",
  "properties": {
    "date:inception_lower": "2020-02-01",
    "date:inception_upper": "2020-02-01",
    "iso:country": "GB",
    "wof:name": "NE22 7FF",
    "wof:placetype": "postalcode"
  },
  "geometry": {"coordinates":[-1.544035,55.143528],"type":"Point"}
}
