{
  "type": "Feature",
  "properties": {
    "iso:country":"GB",
    "wof:name":"NE3 1EH",
    "wof:placetype":"postalcode"
},
  "geometry": {"coordinates":[-1.62409607340479,55.00960541189279],"type":"Point"}
}