{
  "type": "Feature",
  "properties": {
    "date:inception_lower":"1980-01-01",
    "date:inception_upper":"1980-01-31",
    "iso:country":"GB",
    "wof:name":"NE3 1EH",
    "wof:placetype":"postalcode"
},
  "geometry": {"coordinates":[-1.624096,55.009605],"type":"Point"}
}