{
  "type": "Feature",
  "properties": {
    "iso:country": "GB",
    "wof:name": "NE3 1EH",
    "wof:placetype": "postalcode"
  },
  "geometry": {"coordinates":[-1.624096,55.009605],"type":"Point"}
}
