{
  "type": "Feature",
  "properties": {
    "iso:country":"GB",
    "wof:name":"WA7 5YA",
    "wof:placetype":"postalcode"
},
  "geometry": {"coordinates":[-2.71061672152179,53.32730746485981],"type":"Point"}
}