{
  "type": "Feature",
  "properties": {
    "iso:country": "GB",
    "wof:name": "WA7 5YA",
    "wof:placetype": "postalcode"
  },
  "geometry": {"coordinates":[-2.710617,53.327307],"type":"Point"}
}
