{
  "type": "Feature",
  "properties": {
    "iso:country": "GB",
    "wof:name": "TQ12 3HP",
    "wof:placetype": "postalcode"
  },
  "geometry": {"coordinates":[-3.586412,50.553151],"type":"Point"}
}
