{
  "type": "Feature",
  "properties": {
    "iso:country":"GB",
    "wof:name":"TQ12 3HP",
    "wof:placetype":"postalcode"
},
  "geometry": {"coordinates":[-3.5864122305018,50.55315072236602],"type":"Point"}
}