{
  "type": "Feature",
  "properties": {
    "iso:country":"GB",
    "wof:name":"PE31 7EA",
    "wof:placetype":"postalcode"
},
  "geometry": {"coordinates":[0.48911196794582,52.90798124310198],"type":"Point"}
}