{
  "type": "Feature",
  "properties": {
    "date:inception_lower": "2023-08-01",
    "date:inception_upper": "2023-08-01",
    "iso:country": "GB",
    "wof:name": "TQ12 3RY",
    "wof:placetype": "postalcode"
  },
  "geometry": {"coordinates":[-3.595945,50.569971],"type":"Point"}
}
