{
  "type": "Feature",
  "properties": {
    "date:inception_lower": "2008-08-01",
    "date:inception_upper": "2008-08-01",
    "iso:country": "GB",
    "wof:name": "KT18 5FB",
    "wof:placetype": "postalcode"
  },
  "geometry": {"coordinates":[-0.228146,51.310304],"type":"Point"}
}
