{
  "type": "Feature",
  "properties": {
    "iso:country":"GB",
    "wof:name":"NG3 5BS",
    "wof:placetype":"postalcode"
},
  "geometry": {"coordinates":[-1.15143872465797,52.96853093585169],"type":"Point"}
}