{
  "type": "Feature",
  "properties": {
    "iso:country":"GB",
    "wof:name":"DE24 3LZ",
    "wof:placetype":"postalcode"
},
  "geometry": {"coordinates":[-1.50514879890618,52.87701232659905],"type":"Point"}
}