{
  "type": "Feature",
  "properties": {
    "date:inception_lower":"1980-01-01",
    "date:inception_upper":"1980-01-31",
    "iso:country":"GB",
    "wof:name":"BN24 5LA",
    "wof:placetype":"postalcode"
},
  "geometry": {"coordinates":[0.339312,50.820238],"type":"Point"}
}