{
  "type": "Feature",
  "properties": {
    "iso:country":"GB",
    "wof:name":"LS6 2EY",
    "wof:placetype":"postalcode"
},
  "geometry": {"coordinates":[-1.56082069932051,53.81912223318516],"type":"Point"}
}