{
  "type": "Feature",
  "properties": {
    "iso:country": "GB",
    "wof:name": "PR5 6ZH",
    "wof:placetype": "postalcode"
  },
  "geometry": {"coordinates":[-2.652645,53.732329],"type":"Point"}
}
