{
  "type": "Feature",
  "properties": {
    "date:inception_lower": "2018-04-01",
    "date:inception_upper": "2018-04-01",
    "iso:country": "GB",
    "wof:name": "LE18 3TX",
    "wof:placetype": "postalcode"
  },
  "geometry": {"coordinates":[-1.099131,52.572289],"type":"Point"}
}
