{
  "type": "Feature",
  "properties": {
    "iso:country":"GB",
    "wof:name":"SS5 6ER",
    "wof:placetype":"postalcode"
},
  "geometry": {"coordinates":[0.61165552956664,51.62261378030878],"type":"Point"}
}