{
  "type": "Feature",
  "properties": {
    "iso:country": "GB",
    "wof:name": "SS5 6ER",
    "wof:placetype": "postalcode"
  },
  "geometry": {"coordinates":[0.611641,51.622605],"type":"Point"}
}
