{
  "type": "Feature",
  "properties": {
    "iso:country": "GB",
    "wof:name": "DL15 8AU",
    "wof:placetype": "postalcode"
  },
  "geometry": {"coordinates":[-1.720904,54.67682],"type":"Point"}
}
