{
  "type": "Feature",
  "properties": {
    "iso:country":"GB",
    "wof:name":"DL15 8AU",
    "wof:placetype":"postalcode"
},
  "geometry": {"coordinates":[-1.7209042098794,54.6768199076992],"type":"Point"}
}