{
  "type": "Feature",
  "properties": {
    "iso:country":"GB",
    "wof:name":"N18 2QX",
    "wof:placetype":"postalcode"
},
  "geometry": {"coordinates":[-0.06209376231672,51.61715580896495],"type":"Point"}
}