{
  "type": "Feature",
  "properties": {
    "date:inception_lower": "2009-11-01",
    "date:inception_upper": "2009-11-01",
    "iso:country": "GB",
    "wof:name": "OX7 5TP",
    "wof:placetype": "postalcode"
  },
  "geometry": {"coordinates":[-1.50039,51.947906],"type":"Point"}
}
