{
  "type": "Feature",
  "properties": {
    "iso:country":"GB",
    "wof:name":"OX7 5TP",
    "wof:placetype":"postalcode"
},
  "geometry": {"coordinates":[-1.5003905087509,51.94787852836318],"type":"Point"}
}