{
  "type": "Feature",
  "properties": {
    "iso:country":"GB",
    "wof:name":"AB56 5JR",
    "wof:placetype":"postalcode"
},
  "geometry": {"coordinates":[-2.92080373916499,57.63311342023899],"type":"Point"}
}