{
  "type": "Feature",
  "properties": {
    "iso:country": "GB",
    "wof:name": "AB56 5JR",
    "wof:placetype": "postalcode"
  },
  "geometry": {"coordinates":[-2.920804,57.633097],"type":"Point"}
}
