{
  "type": "Feature",
  "properties": {
    "iso:country":"GB",
    "wof:name":"SP11 8EE",
    "wof:placetype":"postalcode"
},
  "geometry": {"coordinates":[-1.57743289712164,51.20942883301382],"type":"Point"}
}