{
  "type": "Feature",
  "properties": {
    "date:inception_lower":"1992-08-01",
    "date:inception_upper":"1992-08-31",
    "iso:country":"GB",
    "wof:name":"DE22 1AA",
    "wof:placetype":"postalcode"
},
  "geometry": {"coordinates":[-1.484091,52.930832],"type":"Point"}
}