{
  "type": "Feature",
  "properties": {
    "iso:country":"GB",
    "wof:name":"SE27 9QL",
    "wof:placetype":"postalcode"
},
  "geometry": {"coordinates":[-0.09480061905951,51.42850602054682],"type":"Point"}
}