{
  "type": "Feature",
  "properties": {
    "iso:country": "GB",
    "wof:name": "SE27 9QL",
    "wof:placetype": "postalcode"
  },
  "geometry": {"coordinates":[-0.094801,51.428506],"type":"Point"}
}
