{
  "type": "Feature",
  "properties": {
    "date:inception_lower": "1980-01-01",
    "date:inception_upper": "1980-01-01",
    "iso:country": "GB",
    "wof:name": "SE27 9QL",
    "wof:placetype": "postalcode"
  },
  "geometry": {"coordinates":[-0.094801,51.428506],"type":"Point"}
}
