{
  "type": "Feature",
  "properties": {
    "iso:country":"GB",
    "wof:name":"EX22 7UR",
    "wof:placetype":"postalcode"
},
  "geometry": {"coordinates":[-4.38455101265095,50.90001475565245],"type":"Point"}
}