{
  "type": "Feature",
  "properties": {
    "date:inception_lower": "1990-02-01",
    "date:inception_upper": "1990-02-01",
    "iso:country": "GB",
    "wof:name": "EX22 7UR",
    "wof:placetype": "postalcode"
  },
  "geometry": {"coordinates":[-4.384551,50.900015],"type":"Point"}
}
