{
  "type": "Feature",
  "properties": {
    "date:inception_lower": "1980-01-01",
    "date:inception_upper": "1980-01-01",
    "iso:country": "GB",
    "wof:name": "DN10 6PL",
    "wof:placetype": "postalcode"
  },
  "geometry": {"coordinates":[-1.026442,53.438096],"type":"Point"}
}
