{
  "type": "Feature",
  "properties": {
    "iso:country": "GB",
    "wof:name": "DN22 0NW",
    "wof:placetype": "postalcode"
  },
  "geometry": {"coordinates":[-0.796822,53.276491],"type":"Point"}
}
