{
  "type": "Feature",
  "properties": {
    "iso:country":"GB",
    "wof:name":"DN22 0NW",
    "wof:placetype":"postalcode"
},
  "geometry": {"coordinates":[-0.79682198205028,53.27649109842982],"type":"Point"}
}