{
  "type": "Feature",
  "properties": {
    "iso:country":"GB",
    "wof:name":"NR24 2DA",
    "wof:placetype":"postalcode"
},
  "geometry": {"coordinates":[1.03575044600161,52.85640406396316],"type":"Point"}
}