{
  "type": "Feature",
  "properties": {
    "date:inception_lower": "1980-01-01",
    "date:inception_upper": "1980-01-01",
    "iso:country": "GB",
    "wof:name": "NR24 2DA",
    "wof:placetype": "postalcode"
  },
  "geometry": {"coordinates":[1.03577,52.856439],"type":"Point"}
}
