{
  "type": "Feature",
  "properties": {
    "iso:country":"GB",
    "wof:name":"ZE2 9PW",
    "wof:placetype":"postalcode"
},
  "geometry": {"coordinates":[-1.6825933860031,60.32698915562086],"type":"Point"}
}