{
  "type": "Feature",
  "properties": {
    "iso:country":"GB",
    "wof:name":"ML9 3PX",
    "wof:placetype":"postalcode"
},
  "geometry": {"coordinates":[-3.96284322644874,55.72518165884499],"type":"Point"}
}