{
  "type": "Feature",
  "properties": {
    "date:inception_lower": "1980-01-01",
    "date:inception_upper": "1980-01-01",
    "iso:country": "GB",
    "wof:name": "LA9 5NE",
    "wof:placetype": "postalcode"
  },
  "geometry": {"coordinates":[-2.749719,54.319405],"type":"Point"}
}
