{
  "type": "Feature",
  "properties": {
    "iso:country":"GB",
    "wof:name":"LA9 5NE",
    "wof:placetype":"postalcode"
},
  "geometry": {"coordinates":[-2.74971910471051,54.31940483815661],"type":"Point"}
}