{
  "type": "Feature",
  "properties": {
    "iso:country":"GB",
    "wof:name":"BR7 5PN",
    "wof:placetype":"postalcode"
},
  "geometry": {"coordinates":[0.07420304402147,51.4085323406535],"type":"Point"}
}