{
  "type": "Feature",
  "properties": {
    "iso:country":"GB",
    "wof:name":"LL12 8YG",
    "wof:placetype":"postalcode"
},
  "geometry": {"coordinates":[-2.95474344381908,53.08505207944854],"type":"Point"}
}