{
  "type": "Feature",
  "properties": {
    "date:inception_lower": "1980-01-01",
    "date:inception_upper": "1980-01-01",
    "iso:country": "GB",
    "wof:name": "KY8 1JE",
    "wof:placetype": "postalcode"
  },
  "geometry": {"coordinates":[-3.02842,56.177541],"type":"Point"}
}
