{
  "type": "Feature",
  "properties": {
    "iso:country":"GB",
    "wof:name":"KY8 1JE",
    "wof:placetype":"postalcode"
},
  "geometry": {"coordinates":[-3.02842001862687,56.17754061324574],"type":"Point"}
}