{
  "type": "Feature",
  "properties": {
    "iso:country":"GB",
    "wof:name":"SK11 0AE",
    "wof:placetype":"postalcode"
},
  "geometry": {"coordinates":[-2.0956072115759,53.25643408320289],"type":"Point"}
}