{
  "type": "Feature",
  "properties": {
    "iso:country": "GB",
    "wof:name": "NP23 7RB",
    "wof:placetype": "postalcode"
  },
  "geometry": {"coordinates":[-3.183687,51.742243],"type":"Point"}
}
