{
  "type": "Feature",
  "properties": {
    "date:inception_lower": "1980-01-01",
    "date:inception_upper": "1980-01-01",
    "iso:country": "GB",
    "wof:name": "WA9 2AN",
    "wof:placetype": "postalcode"
  },
  "geometry": {"coordinates":[-2.69553,53.452985],"type":"Point"}
}
