{
  "type": "Feature",
  "properties": {
    "iso:country":"GB",
    "wof:name":"WA9 2AN",
    "wof:placetype":"postalcode"
},
  "geometry": {"coordinates":[-2.69553140505896,53.45296940162581],"type":"Point"}
}