{
  "type": "Feature",
  "properties": {
    "iso:country": "GB",
    "wof:name": "WA9 2AN",
    "wof:placetype": "postalcode"
  },
  "geometry": {"coordinates":[-2.69553,53.452985],"type":"Point"}
}
