{
  "type": "Feature",
  "properties": {
    "iso:country":"GB",
    "wof:name":"B18 7HR",
    "wof:placetype":"postalcode"
},
  "geometry": {"coordinates":[-1.92396119922897,52.49086077715759],"type":"Point"}
}