{
  "type": "Feature",
  "properties": {
    "iso:country": "GB",
    "wof:name": "HU17 8NP",
    "wof:placetype": "postalcode"
  },
  "geometry": {"coordinates":[-0.432505,53.837929],"type":"Point"}
}
