{
  "type": "Feature",
  "properties": {
    "date:inception_lower":"1980-01-01",
    "date:inception_upper":"1980-01-31",
    "iso:country":"GB",
    "wof:name":"HU17 8NP",
    "wof:placetype":"postalcode"
},
  "geometry": {"coordinates":[-0.432505,53.837929],"type":"Point"}
}