{
  "type": "Feature",
  "properties": {
    "iso:country":"GB",
    "wof:name":"HU17 8NP",
    "wof:placetype":"postalcode"
},
  "geometry": {"coordinates":[-0.43250523180074,53.83792925237579],"type":"Point"}
}