{
  "type": "Feature",
  "properties": {
    "iso:country": "GB",
    "wof:name": "NN1 1RS",
    "wof:placetype": "postalcode"
  },
  "geometry": {"coordinates":[-0.899477,52.236953],"type":"Point"}
}
