{
  "type": "Feature",
  "properties": {
    "iso:country":"GB",
    "wof:name":"WF8 4AR",
    "wof:placetype":"postalcode"
},
  "geometry": {"coordinates":[-1.32312485068698,53.68846995238393],"type":"Point"}
}