{
  "type": "Feature",
  "properties": {
    "iso:country":"GB",
    "wof:name":"EX34 7EH",
    "wof:placetype":"postalcode"
},
  "geometry": {"coordinates":[-4.19842773253638,51.18784822929648],"type":"Point"}
}