{
  "type": "Feature",
  "properties": {
    "iso:country":"GB",
    "wof:name":"TR14 0PW",
    "wof:placetype":"postalcode"
},
  "geometry": {"coordinates":[-5.31613417351737,50.17943981151288],"type":"Point"}
}