{
  "type": "Feature",
  "properties": {
    "iso:country":"GB",
    "wof:name":"LS29 9NR",
    "wof:placetype":"postalcode"
},
  "geometry": {"coordinates":[-1.84349381178348,53.92197939844539],"type":"Point"}
}