{
  "type": "Feature",
  "properties": {
    "iso:country": "GB",
    "wof:name": "LS29 9NR",
    "wof:placetype": "postalcode"
  },
  "geometry": {"coordinates":[-1.843494,53.921979],"type":"Point"}
}
