{
  "type": "Feature",
  "properties": {
    "iso:country":"GB",
    "wof:name":"IG4 5PP",
    "wof:placetype":"postalcode"
},
  "geometry": {"coordinates":[0.04291907833495,51.58489916736067],"type":"Point"}
}