{
  "type": "Feature",
  "properties": {
    "iso:country":"GB",
    "wof:name":"NE24 5BA",
    "wof:placetype":"postalcode"
},
  "geometry": {"coordinates":[-1.52565680422902,55.1283462833095],"type":"Point"}
}