{
  "type": "Feature",
  "properties": {
    "iso:country":"GB",
    "wof:name":"B13 8NB",
    "wof:placetype":"postalcode"
},
  "geometry": {"coordinates":[-1.89494508288921,52.44231970437848],"type":"Point"}
}