{
  "type": "Feature",
  "properties": {
    "iso:country": "GB",
    "wof:name": "NP16 5NA",
    "wof:placetype": "postalcode"
  },
  "geometry": {"coordinates":[-2.68797,51.645587],"type":"Point"}
}
