{
  "type": "Feature",
  "properties": {
    "iso:country":"GB",
    "wof:name":"ME8 7HW",
    "wof:placetype":"postalcode"
},
  "geometry": {"coordinates":[0.60799471514855,51.36412128924599],"type":"Point"}
}