{
  "type": "Feature",
  "properties": {
    "date:inception_lower":"1981-06-01",
    "date:inception_upper":"1981-06-30",
    "iso:country":"GB",
    "wof:name":"ME8 7HW",
    "wof:placetype":"postalcode"
},
  "geometry": {"coordinates":[0.607995,51.364121],"type":"Point"}
}