{
  "type": "Feature",
  "properties": {
    "date:inception_lower":"1980-01-01",
    "date:inception_upper":"1980-01-31",
    "iso:country":"GB",
    "wof:name":"LL55 4BN",
    "wof:placetype":"postalcode"
},
  "geometry": {"coordinates":[-4.186211,53.149756],"type":"Point"}
}