{
  "type": "Feature",
  "properties": {
    "iso:country":"GB",
    "wof:name":"LL55 4BN",
    "wof:placetype":"postalcode"
},
  "geometry": {"coordinates":[-4.18620478580021,53.14973887212032],"type":"Point"}
}