{
  "type": "Feature",
  "properties": {
    "iso:country": "GB",
    "wof:name": "CV23 9HU",
    "wof:placetype": "postalcode"
  },
  "geometry": {"coordinates":[-1.396894,52.356635],"type":"Point"}
}
