{
  "type": "Feature",
  "properties": {
    "iso:country":"GB",
    "wof:name":"IV2 4DA",
    "wof:placetype":"postalcode"
},
  "geometry": {"coordinates":[-4.22978141106764,57.45356260308845],"type":"Point"}
}