{
  "type": "Feature",
  "properties": {
    "iso:country":"GB",
    "wof:name":"TS10 1EA",
    "wof:placetype":"postalcode"
},
  "geometry": {"coordinates":[-1.06879075623228,54.618339042672],"type":"Point"}
}