{
  "type": "Feature",
  "properties": {
    "iso:country": "GB",
    "wof:name": "TS10 1EA",
    "wof:placetype": "postalcode"
  },
  "geometry": {"coordinates":[-1.068791,54.618339],"type":"Point"}
}
