{
  "type": "Feature",
  "properties": {
    "date:inception_lower":"1980-01-01",
    "date:inception_upper":"1980-01-31",
    "iso:country":"GB",
    "wof:name":"TS10 1EA",
    "wof:placetype":"postalcode"
},
  "geometry": {"coordinates":[-1.068791,54.618339],"type":"Point"}
}