{
  "type": "Feature",
  "properties": {
    "date:inception_lower":"1980-01-01",
    "date:inception_upper":"1980-01-31",
    "iso:country":"GB",
    "wof:name":"NN2 7JY",
    "wof:placetype":"postalcode"
},
  "geometry": {"coordinates":[-0.88444,52.257268],"type":"Point"}
}