{
  "type": "Feature",
  "properties": {
    "iso:country":"GB",
    "wof:name":"DA6 7LZ",
    "wof:placetype":"postalcode"
},
  "geometry": {"coordinates":[0.1487677725133,51.45374530532111],"type":"Point"}
}