{
  "type": "Feature",
  "properties": {
    "date:inception_lower": "1984-06-01",
    "date:inception_upper": "1984-06-01",
    "iso:country": "GB",
    "wof:name": "G40 1JG",
    "wof:placetype": "postalcode"
  },
  "geometry": {"coordinates":[-4.22859,55.844673],"type":"Point"}
}
