{
  "type": "Feature",
  "properties": {
    "iso:country": "GB",
    "wof:name": "SO19 0JL",
    "wof:placetype": "postalcode"
  },
  "geometry": {"coordinates":[-1.338034,50.898194],"type":"Point"}
}
