{
  "type": "Feature",
  "properties": {
    "iso:country":"GB",
    "wof:name":"SO24 0PR",
    "wof:placetype":"postalcode"
},
  "geometry": {"coordinates":[-1.17154448377328,51.0560917828813],"type":"Point"}
}