{
  "type": "Feature",
  "properties": {
    "iso:country": "GB",
    "wof:name": "SO24 0PR",
    "wof:placetype": "postalcode"
  },
  "geometry": {"coordinates":[-1.171544,51.056092],"type":"Point"}
}
