{
  "type": "Feature",
  "properties": {
    "date:inception_lower": "1980-01-01",
    "date:inception_upper": "1980-01-01",
    "iso:country": "GB",
    "wof:name": "DN3 3PW",
    "wof:placetype": "postalcode"
  },
  "geometry": {"coordinates":[-0.99689,53.528234],"type":"Point"}
}
