{
  "type": "Feature",
  "properties": {
    "iso:country":"GB",
    "wof:name":"DN3 3PW",
    "wof:placetype":"postalcode"
},
  "geometry": {"coordinates":[-0.99689031782545,53.52823427465596],"type":"Point"}
}