{
  "type": "Feature",
  "properties": {
    "iso:country":"GB",
    "wof:name":"DA17 5DE",
    "wof:placetype":"postalcode"
},
  "geometry": {"coordinates":[0.14199715983167,51.49082109100149],"type":"Point"}
}