{
  "type": "Feature",
  "properties": {
    "iso:country":"GB",
    "wof:name":"MK3 7WD",
    "wof:placetype":"postalcode"
},
  "geometry": {"coordinates":[-0.75895054596177,52.00287422303136],"type":"Point"}
}