{
  "type": "Feature",
  "properties": {
    "date:inception_lower": "2001-12-01",
    "date:inception_upper": "2001-12-01",
    "iso:country": "GB",
    "wof:name": "MK3 7WD",
    "wof:placetype": "postalcode"
  },
  "geometry": {"coordinates":[-0.758951,52.002874],"type":"Point"}
}
