{
  "type": "Feature",
  "properties": {
    "iso:country":"GB",
    "wof:name":"AL6 0EH",
    "wof:placetype":"postalcode"
},
  "geometry": {"coordinates":[-0.18247887203249,51.82942619951032],"type":"Point"}
}