{
  "type": "Feature",
  "properties": {
    "iso:country":"GB",
    "wof:name":"LE19 2GB",
    "wof:placetype":"postalcode"
},
  "geometry": {"coordinates":[-1.21000858417123,52.57166876118506],"type":"Point"}
}