{
  "type": "Feature",
  "properties": {
    "iso:country":"GB",
    "wof:name":"TS7 0JA",
    "wof:placetype":"postalcode"
},
  "geometry": {"coordinates":[-1.17021053486726,54.52536782401505],"type":"Point"}
}