{
  "type": "Feature",
  "properties": {
    "iso:country": "GB",
    "wof:name": "TS7 0JA",
    "wof:placetype": "postalcode"
  },
  "geometry": {"coordinates":[-1.17021,54.525368],"type":"Point"}
}
