{
  "type": "Feature",
  "properties": {
    "iso:country":"GB",
    "wof:name":"YO26 4ZH",
    "wof:placetype":"postalcode"
},
  "geometry": {"coordinates":[-1.10402356999696,53.96197339945012],"type":"Point"}
}