{
  "type": "Feature",
  "properties": {
    "iso:country":"GB",
    "wof:name":"BN23 6AP",
    "wof:placetype":"postalcode"
},
  "geometry": {"coordinates":[0.31779651377076,50.78831640321177],"type":"Point"}
}