{
  "type": "Feature",
  "properties": {
    "iso:country":"GB",
    "wof:name":"SR8 1LH",
    "wof:placetype":"postalcode"
},
  "geometry": {"coordinates":[-1.34307600077601,54.74927773979029],"type":"Point"}
}