{
  "type": "Feature",
  "properties": {
    "iso:country":"GB",
    "wof:name":"GU5 0SP",
    "wof:placetype":"postalcode"
},
  "geometry": {"coordinates":[-0.51878809026959,51.18332850193755],"type":"Point"}
}