{
  "type": "Feature",
  "properties": {
    "iso:country":"GB",
    "wof:name":"RH6 9NW",
    "wof:placetype":"postalcode"
},
  "geometry": {"coordinates":[-0.11547301060754,51.17385759639698],"type":"Point"}
}