{
  "type": "Feature",
  "properties": {
    "date:inception_lower": "1980-01-01",
    "date:inception_upper": "1980-01-01",
    "iso:country": "GB",
    "wof:name": "RH6 9NW",
    "wof:placetype": "postalcode"
  },
  "geometry": {"coordinates":[-0.115473,51.173858],"type":"Point"}
}
