{
  "type": "Feature",
  "properties": {
    "iso:country": "GB",
    "wof:name": "SP7 8FU",
    "wof:placetype": "postalcode"
  },
  "geometry": {"coordinates":[-2.180224,51.008054],"type":"Point"}
}
