{
  "type": "Feature",
  "properties": {
    "date:inception_lower": "2015-07-01",
    "date:inception_upper": "2015-07-01",
    "iso:country": "GB",
    "wof:name": "SP7 8FU",
    "wof:placetype": "postalcode"
  },
  "geometry": {"coordinates":[-2.180224,51.008054],"type":"Point"}
}
