{
  "type": "Feature",
  "properties": {
    "date:inception_lower": "2024-09-01",
    "date:inception_upper": "2024-09-01",
    "iso:country": "GB",
    "wof:name": "NR9 5JQ",
    "wof:placetype": "postalcode"
  },
  "geometry": {"coordinates":[1.093915,52.705868],"type":"Point"}
}
