{
  "type": "Feature",
  "properties": {
    "date:inception_lower": "1980-01-01",
    "date:inception_upper": "1980-01-01",
    "iso:country": "GB",
    "wof:name": "TS9 7BT",
    "wof:placetype": "postalcode"
  },
  "geometry": {"coordinates":[-1.235562,54.418051],"type":"Point"}
}
