{
  "type": "Feature",
  "properties": {
    "iso:country":"GB",
    "wof:name":"TS9 7BT",
    "wof:placetype":"postalcode"
},
  "geometry": {"coordinates":[-1.23556182072101,54.41805082517547],"type":"Point"}
}