{
  "type": "Feature",
  "properties": {
    "iso:country": "GB",
    "wof:name": "S35 4HF",
    "wof:placetype": "postalcode"
  },
  "geometry": {"coordinates":[-1.491733,53.469681],"type":"Point"}
}
