{
  "type": "Feature",
  "properties": {
    "iso:country": "GB",
    "wof:name": "S35 4HF",
    "wof:placetype": "postalcode"
  },
  "geometry": {"coordinates":[-1.491717,53.469699],"type":"Point"}
}
