{
  "type": "Feature",
  "properties": {
    "iso:country":"GB",
    "wof:name":"S35 4HF",
    "wof:placetype":"postalcode"
},
  "geometry": {"coordinates":[-1.49173262418531,53.46968137988053],"type":"Point"}
}