{
  "type": "Feature",
  "properties": {
    "iso:country":"GB",
    "wof:name":"WD25 7HS",
    "wof:placetype":"postalcode"
},
  "geometry": {"coordinates":[-0.39313388898724,51.69743495827335],"type":"Point"}
}