{
  "type": "Feature",
  "properties": {
    "iso:country":"GB",
    "wof:name":"SP2 7QQ",
    "wof:placetype":"postalcode"
},
  "geometry": {"coordinates":[-1.80045054204001,51.0702849382356],"type":"Point"}
}