{
  "type": "Feature",
  "properties": {
    "date:inception_lower": "1980-01-01",
    "date:inception_upper": "1980-01-01",
    "iso:country": "GB",
    "wof:name": "M32 8JJ",
    "wof:placetype": "postalcode"
  },
  "geometry": {"coordinates":[-2.300084,53.443346],"type":"Point"}
}
