{
  "type": "Feature",
  "properties": {
    "iso:country":"GB",
    "wof:name":"WD6 4DT",
    "wof:placetype":"postalcode"
},
  "geometry": {"coordinates":[-0.28242531409291,51.66640135450832],"type":"Point"}
}