{
  "type": "Feature",
  "properties": {
    "iso:country": "GB",
    "wof:name": "GU10 5RZ",
    "wof:placetype": "postalcode"
  },
  "geometry": {"coordinates":[-0.875831,51.246796],"type":"Point"}
}
