{
  "type": "Feature",
  "properties": {
    "iso:country":"GB",
    "wof:name":"GU10 5RZ",
    "wof:placetype":"postalcode"
},
  "geometry": {"coordinates":[-0.87583127355312,51.2467963953272],"type":"Point"}
}