{
  "type": "Feature",
  "properties": {
    "date:inception_lower": "2005-03-01",
    "date:inception_upper": "2005-03-01",
    "iso:country": "GB",
    "wof:name": "GU10 5RZ",
    "wof:placetype": "postalcode"
  },
  "geometry": {"coordinates":[-0.875831,51.246796],"type":"Point"}
}
