{
  "type": "Feature",
  "properties": {
    "iso:country":"GB",
    "wof:name":"M19 1DR",
    "wof:placetype":"postalcode"
},
  "geometry": {"coordinates":[-2.20237020871229,53.42936809441672],"type":"Point"}
}