{
  "type": "Feature",
  "properties": {
    "iso:country":"GB",
    "wof:name":"GU1 1AF",
    "wof:placetype":"postalcode"
},
  "geometry": {"coordinates":[-0.567107423851,51.26402637745439],"type":"Point"}
}