{
  "type": "Feature",
  "properties": {
    "iso:country": "GB",
    "wof:name": "GU1 1AF",
    "wof:placetype": "postalcode"
  },
  "geometry": {"coordinates":[-0.567107,51.264026],"type":"Point"}
}
