{
  "type": "Feature",
  "properties": {
    "iso:country":"GB",
    "wof:name":"PL26 6JL",
    "wof:placetype":"postalcode"
},
  "geometry": {"coordinates":[-4.78943966491302,50.24203137215705],"type":"Point"}
}