{
  "type": "Feature",
  "properties": {
    "iso:country": "GB",
    "wof:name": "PL26 6JL",
    "wof:placetype": "postalcode"
  },
  "geometry": {"coordinates":[-4.789506,50.241967],"type":"Point"}
}
