{
  "type": "Feature",
  "properties": {
    "iso:country":"GB",
    "wof:name":"HA9 0AS",
    "wof:placetype":"postalcode"
},
  "geometry": {"coordinates":[-0.27330456281369,51.56049213654456],"type":"Point"}
}