{
  "type": "Feature",
  "properties": {
    "iso:country":"GB",
    "wof:name":"PO5 2PL",
    "wof:placetype":"postalcode"
},
  "geometry": {"coordinates":[-1.07740095665732,50.78559086445602],"type":"Point"}
}