{
  "type": "Feature",
  "properties": {
    "iso:country":"GB",
    "wof:name":"GU25 4RY",
    "wof:placetype":"postalcode"
},
  "geometry": {"coordinates":[-0.57214548812731,51.40197633307177],"type":"Point"}
}