{
  "type": "Feature",
  "properties": {
    "iso:country":"GB",
    "wof:name":"N6 4AP",
    "wof:placetype":"postalcode"
},
  "geometry": {"coordinates":[-0.15376729059465,51.57643219470888],"type":"Point"}
}