{
  "type": "Feature",
  "properties": {
    "date:inception_lower":"2001-12-01",
    "date:inception_upper":"2001-12-31",
    "iso:country":"GB",
    "wof:name":"WF4 5RB",
    "wof:placetype":"postalcode"
},
  "geometry": {"coordinates":[-1.541691,53.664904],"type":"Point"}
}