{
  "type": "Feature",
  "properties": {
    "iso:country":"GB",
    "wof:name":"LU3 1HE",
    "wof:placetype":"postalcode"
},
  "geometry": {"coordinates":[-0.42400814894537,51.89141978457121],"type":"Point"}
}