{
  "type": "Feature",
  "properties": {
    "date:inception_lower":"2011-01-01",
    "date:inception_upper":"2011-01-31",
    "iso:country":"GB",
    "wof:name":"PE1 4QT",
    "wof:placetype":"postalcode"
},
  "geometry": {"coordinates":[-0.22242,52.594237],"type":"Point"}
}