{
  "type": "Feature",
  "properties": {
    "iso:country":"GB",
    "wof:name":"PE1 4QT",
    "wof:placetype":"postalcode"
},
  "geometry": {"coordinates":[-0.22242002122261,52.59423738336743],"type":"Point"}
}