{
  "type": "Feature",
  "properties": {
    "iso:country":"GB",
    "wof:name":"DA1 4TE",
    "wof:placetype":"postalcode"
},
  "geometry": {"coordinates":[0.18074900493639,51.45521405714467],"type":"Point"}
}