{
  "type": "Feature",
  "properties": {
    "date:inception_lower": "1988-03-01",
    "date:inception_upper": "1988-03-01",
    "iso:country": "GB",
    "wof:name": "GU12 4NZ",
    "wof:placetype": "postalcode"
  },
  "geometry": {"coordinates":[-0.753396,51.24597],"type":"Point"}
}
