{
  "type": "Feature",
  "properties": {
    "iso:country": "GB",
    "wof:name": "GU12 4NZ",
    "wof:placetype": "postalcode"
  },
  "geometry": {"coordinates":[-0.753396,51.24597],"type":"Point"}
}
