{
  "type": "Feature",
  "properties": {
    "iso:country": "GB",
    "wof:name": "BS30 9YS",
    "wof:placetype": "postalcode"
  },
  "geometry": {"coordinates":[-2.48179,51.440654],"type":"Point"}
}
