{
  "type": "Feature",
  "properties": {
    "iso:country":"GB",
    "wof:name":"BS30 9YS",
    "wof:placetype":"postalcode"
},
  "geometry": {"coordinates":[-2.48174586857785,51.44065614588467],"type":"Point"}
}