{
  "type": "Feature",
  "properties": {
    "iso:country": "GB",
    "wof:name": "AB25 2DH",
    "wof:placetype": "postalcode"
  },
  "geometry": {"coordinates":[-2.12543,57.146059],"type":"Point"}
}
