{
  "type": "Feature",
  "properties": {
    "iso:country":"GB",
    "wof:name":"CH66 3PQ",
    "wof:placetype":"postalcode"
},
  "geometry": {"coordinates":[-2.9337439764962,53.27962865300641],"type":"Point"}
}