{
  "type": "Feature",
  "properties": {
    "iso:country": "GB",
    "wof:name": "CH66 3PQ",
    "wof:placetype": "postalcode"
  },
  "geometry": {"coordinates":[-2.933744,53.279629],"type":"Point"}
}
