{
  "type": "Feature",
  "properties": {
    "date:inception_lower": "2023-11-01",
    "date:inception_upper": "2023-11-01",
    "iso:country": "GB",
    "wof:name": "BD20 0FY",
    "wof:placetype": "postalcode"
  },
  "geometry": {"coordinates":[-1.941028,53.908105],"type":"Point"}
}
