{
  "type": "Feature",
  "properties": {
    "date:inception_lower":"1980-01-01",
    "date:inception_upper":"1980-01-31",
    "iso:country":"GB",
    "wof:name":"SS16 5LL",
    "wof:placetype":"postalcode"
},
  "geometry": {"coordinates":[0.42743,51.55037],"type":"Point"}
}