{
  "type": "Feature",
  "properties": {
    "iso:country": "GB",
    "wof:name": "SS16 5LL",
    "wof:placetype": "postalcode"
  },
  "geometry": {"coordinates":[0.42743,51.55037],"type":"Point"}
}
