{
  "type": "Feature",
  "properties": {
    "iso:country":"GB",
    "wof:name":"SY4 4JD",
    "wof:placetype":"postalcode"
},
  "geometry": {"coordinates":[-2.64345180976861,52.7873908114625],"type":"Point"}
}