{
  "type": "Feature",
  "properties": {
    "date:inception_lower": "2021-06-01",
    "date:inception_upper": "2021-06-01",
    "iso:country": "GB",
    "wof:name": "B49 5RQ",
    "wof:placetype": "postalcode"
  },
  "geometry": {"coordinates":[-1.88144,52.219345],"type":"Point"}
}
