{
  "type": "Feature",
  "properties": {
    "iso:country": "GB",
    "wof:name": "EH1 1JS",
    "wof:placetype": "postalcode"
  },
  "geometry": {"coordinates":[-3.189292,55.948414],"type":"Point"}
}
