{
  "type": "Feature",
  "properties": {
    "iso:country":"GB",
    "wof:name":"L39 6RL",
    "wof:placetype":"postalcode"
},
  "geometry": {"coordinates":[-2.90313673928723,53.54107183086445],"type":"Point"}
}