{
  "type": "Feature",
  "properties": {
    "iso:country":"GB",
    "wof:name":"BB2 4FN",
    "wof:placetype":"postalcode"
},
  "geometry": {"coordinates":[-2.49483028041036,53.72578687867352],"type":"Point"}
}