{
  "type": "Feature",
  "properties": {
    "date:inception_lower":"2005-01-01",
    "date:inception_upper":"2005-01-31",
    "iso:country":"GB",
    "wof:name":"BB2 4FN",
    "wof:placetype":"postalcode"
},
  "geometry": {"coordinates":[-2.49483,53.725787],"type":"Point"}
}