{
  "type": "Feature",
  "properties": {
    "iso:country": "GB",
    "wof:name": "RH12 5GQ",
    "wof:placetype": "postalcode"
  },
  "geometry": {"coordinates":[-0.319759,51.083274],"type":"Point"}
}
