{
  "type": "Feature",
  "properties": {
    "iso:country":"GB",
    "wof:name":"RH12 5GQ",
    "wof:placetype":"postalcode"
},
  "geometry": {"coordinates":[-0.3197595022157,51.08327378593015],"type":"Point"}
}