{
  "type": "Feature",
  "properties": {
    "iso:country": "GB",
    "wof:name": "E15 1DT",
    "wof:placetype": "postalcode"
  },
  "geometry": {"coordinates":[-0.003878,51.549377],"type":"Point"}
}
