{
  "type": "Feature",
  "properties": {
    "iso:country": "GB",
    "wof:name": "GU6 8NH",
    "wof:placetype": "postalcode"
  },
  "geometry": {"coordinates":[-0.508753,51.142231],"type":"Point"}
}
