{
  "type": "Feature",
  "properties": {
    "iso:country":"GB",
    "wof:name":"GU6 8NH",
    "wof:placetype":"postalcode"
},
  "geometry": {"coordinates":[-0.50875309278732,51.14223059692406],"type":"Point"}
}