{
  "type": "Feature",
  "properties": {
    "iso:country":"GB",
    "wof:name":"CR4 4EF",
    "wof:placetype":"postalcode"
},
  "geometry": {"coordinates":[-0.17058273850831,51.40076614495204],"type":"Point"}
}