{
  "type": "Feature",
  "properties": {
    "iso:country":"GB",
    "wof:name":"CO6 2SQ",
    "wof:placetype":"postalcode"
},
  "geometry": {"coordinates":[0.69593237546159,51.92652734914818],"type":"Point"}
}