{
  "type": "Feature",
  "properties": {
    "iso:country": "GB",
    "wof:name": "GU31 4DA",
    "wof:placetype": "postalcode"
  },
  "geometry": {"coordinates":[-0.918097,51.011891],"type":"Point"}
}
