{
  "type": "Feature",
  "properties": {
    "iso:country": "GB",
    "wof:name": "ST4 5QQ",
    "wof:placetype": "postalcode"
  },
  "geometry": {"coordinates":[-2.202529,52.990271],"type":"Point"}
}
