{
  "type": "Feature",
  "properties": {
    "iso:country":"GB",
    "wof:name":"ST4 5QQ",
    "wof:placetype":"postalcode"
},
  "geometry": {"coordinates":[-2.20252883058791,52.990270935553],"type":"Point"}
}