{
  "type": "Feature",
  "properties": {
    "iso:country":"GB",
    "wof:name":"NR33 8TZ",
    "wof:placetype":"postalcode"
},
  "geometry": {"coordinates":[1.71277051706165,52.45300746958375],"type":"Point"}
}