{
  "type": "Feature",
  "properties": {
    "date:inception_lower": "1990-02-01",
    "date:inception_upper": "1990-02-01",
    "iso:country": "GB",
    "wof:name": "NR33 8TZ",
    "wof:placetype": "postalcode"
  },
  "geometry": {"coordinates":[1.712771,52.453007],"type":"Point"}
}
