{
  "type": "Feature",
  "properties": {
    "iso:country": "GB",
    "wof:name": "OX15 4LA",
    "wof:placetype": "postalcode"
  },
  "geometry": {"coordinates":[-1.434867,51.997149],"type":"Point"}
}
