{
  "type": "Feature",
  "properties": {
    "iso:country":"GB",
    "wof:name":"OX15 4LA",
    "wof:placetype":"postalcode"
},
  "geometry": {"coordinates":[-1.43486662058141,51.9971489157019],"type":"Point"}
}