{
  "type": "Feature",
  "properties": {
    "iso:country":"GB",
    "wof:name":"GL5 3PN",
    "wof:placetype":"postalcode"
},
  "geometry": {"coordinates":[-2.22979655850131,51.73035821485332],"type":"Point"}
}