{
  "type": "Feature",
  "properties": {
    "iso:country":"GB",
    "wof:name":"KT20 6UF",
    "wof:placetype":"postalcode"
},
  "geometry": {"coordinates":[-0.21903351165387,51.27995873631702],"type":"Point"}
}