{
  "type": "Feature",
  "properties": {
    "date:inception_lower": "1996-12-01",
    "date:inception_upper": "1996-12-01",
    "iso:country": "GB",
    "wof:name": "KT20 6UF",
    "wof:placetype": "postalcode"
  },
  "geometry": {"coordinates":[-0.219033,51.279959],"type":"Point"}
}
