{
  "type": "Feature",
  "properties": {
    "iso:country":"GB",
    "wof:name":"BH16 6EU",
    "wof:placetype":"postalcode"
},
  "geometry": {"coordinates":[-2.0873315674194,50.73286558174262],"type":"Point"}
}