{
  "type": "Feature",
  "properties": {
    "iso:country": "GB",
    "wof:name": "BD3 7JW",
    "wof:placetype": "postalcode"
  },
  "geometry": {"coordinates":[-1.723173,53.80421],"type":"Point"}
}
