{
  "type": "Feature",
  "properties": {
    "iso:country":"GB",
    "wof:name":"PE13 4RT",
    "wof:placetype":"postalcode"
},
  "geometry": {"coordinates":[0.101760052108,52.654860526262],"type":"Point"}
}