{
  "type": "Feature",
  "properties": {
    "iso:country":"GB",
    "wof:name":"GL7 5JW",
    "wof:placetype":"postalcode"
},
  "geometry": {"coordinates":[-1.8276886210947,51.70090358415187],"type":"Point"}
}