{
  "type": "Feature",
  "properties": {
    "date:inception_lower": "1980-01-01",
    "date:inception_upper": "1980-01-01",
    "iso:country": "GB",
    "wof:name": "GL7 5JW",
    "wof:placetype": "postalcode"
  },
  "geometry": {"coordinates":[-1.827689,51.700904],"type":"Point"}
}
