{
  "type": "Feature",
  "properties": {
    "iso:country":"GB",
    "wof:name":"G66 1QY",
    "wof:placetype":"postalcode"
},
  "geometry": {"coordinates":[-4.15157598442189,55.94106608323977],"type":"Point"}
}