{
  "type": "Feature",
  "properties": {
    "date:inception_lower": "1995-12-01",
    "date:inception_upper": "1995-12-01",
    "iso:country": "GB",
    "wof:name": "G66 1QY",
    "wof:placetype": "postalcode"
  },
  "geometry": {"coordinates":[-4.151499,55.941053],"type":"Point"}
}
