{
  "type": "Feature",
  "properties": {
    "date:inception_lower":"1980-01-01",
    "date:inception_upper":"1980-01-31",
    "iso:country":"GB",
    "wof:name":"ST17 0AB",
    "wof:placetype":"postalcode"
},
  "geometry": {"coordinates":[-2.085437,52.79396],"type":"Point"}
}