{
  "type": "Feature",
  "properties": {
    "iso:country":"GB",
    "wof:name":"ST17 0AB",
    "wof:placetype":"postalcode"
},
  "geometry": {"coordinates":[-2.0854372624876,52.79396013272969],"type":"Point"}
}