{
  "type": "Feature",
  "properties": {
    "iso:country": "GB",
    "wof:name": "ST17 0AB",
    "wof:placetype": "postalcode"
  },
  "geometry": {"coordinates":[-2.085437,52.79396],"type":"Point"}
}
