{
  "type": "Feature",
  "properties": {
    "iso:country": "GB",
    "wof:name": "NE65 9BZ",
    "wof:placetype": "postalcode"
  },
  "geometry": {"coordinates":[-1.635091,55.310391],"type":"Point"}
}
