{
  "type": "Feature",
  "properties": {
    "date:inception_lower":"1980-01-01",
    "date:inception_upper":"1980-01-31",
    "iso:country":"GB",
    "wof:name":"ST3 5AH",
    "wof:placetype":"postalcode"
},
  "geometry": {"coordinates":[-2.128918,52.998608],"type":"Point"}
}