{
  "type": "Feature",
  "properties": {
    "date:inception_lower":"2011-05-01",
    "date:inception_upper":"2011-05-31",
    "iso:country":"GB",
    "wof:name":"BL9 0NP",
    "wof:placetype":"postalcode"
},
  "geometry": {"coordinates":[-2.290904,53.595723],"type":"Point"}
}