{
  "type": "Feature",
  "properties": {
    "iso:country": "GB",
    "wof:name": "BL9 0NP",
    "wof:placetype": "postalcode"
  },
  "geometry": {"coordinates":[-2.290904,53.595723],"type":"Point"}
}
