{
  "type": "Feature",
  "properties": {
    "date:inception_lower": "1986-04-01",
    "date:inception_upper": "1986-04-01",
    "iso:country": "GB",
    "wof:name": "CT3 4HD",
    "wof:placetype": "postalcode"
  },
  "geometry": {"coordinates":[1.165764,51.315081],"type":"Point"}
}
