{
  "type": "Feature",
  "properties": {
    "iso:country":"GB",
    "wof:name":"CT3 4HD",
    "wof:placetype":"postalcode"
},
  "geometry": {"coordinates":[1.16576357258518,51.31508135599013],"type":"Point"}
}