{
  "type": "Feature",
  "properties": {
    "date:inception_lower": "1990-02-01",
    "date:inception_upper": "1990-02-01",
    "iso:country": "GB",
    "wof:name": "CA14 1NQ",
    "wof:placetype": "postalcode"
  },
  "geometry": {"coordinates":[-3.552724,54.657005],"type":"Point"}
}
