{
  "type": "Feature",
  "properties": {
    "iso:country":"GB",
    "wof:name":"CA14 1NQ",
    "wof:placetype":"postalcode"
},
  "geometry": {"coordinates":[-3.55272438870666,54.65700478592797],"type":"Point"}
}