{
  "type": "Feature",
  "properties": {
    "iso:country": "GB",
    "wof:name": "DL14 6TY",
    "wof:placetype": "postalcode"
  },
  "geometry": {"coordinates":[-1.685828,54.656325],"type":"Point"}
}
