{
  "type": "Feature",
  "properties": {
    "iso:country":"GB",
    "wof:name":"DL14 6TY",
    "wof:placetype":"postalcode"
},
  "geometry": {"coordinates":[-1.68582835067607,54.65632533683133],"type":"Point"}
}