{
  "type": "Feature",
  "properties": {
    "iso:country":"GB",
    "wof:name":"HA9 8FH",
    "wof:placetype":"postalcode"
},
  "geometry": {"coordinates":[-0.28427844268466,51.56522118312654],"type":"Point"}
}