{
  "type": "Feature",
  "properties": {
    "iso:country": "GB",
    "wof:name": "SE16 2EE",
    "wof:placetype": "postalcode"
  },
  "geometry": {"coordinates":[-0.060015,51.498141],"type":"Point"}
}
