{
  "type": "Feature",
  "properties": {
    "iso:country":"GB",
    "wof:name":"DN4 8WA",
    "wof:placetype":"postalcode"
},
  "geometry": {"coordinates":[-1.13163679456842,53.50385052053016],"type":"Point"}
}