{
  "type": "Feature",
  "properties": {
    "iso:country": "GB",
    "wof:name": "DN4 8WA",
    "wof:placetype": "postalcode"
  },
  "geometry": {"coordinates":[-1.131639,53.503871],"type":"Point"}
}
