{
  "type": "Feature",
  "properties": {
    "iso:country":"GB",
    "wof:name":"CA13 9AY",
    "wof:placetype":"postalcode"
},
  "geometry": {"coordinates":[-3.35234653491223,54.66120559429498],"type":"Point"}
}