{
  "type": "Feature",
  "properties": {
    "iso:country":"GB",
    "wof:name":"SA16 0EU",
    "wof:placetype":"postalcode"
},
  "geometry": {"coordinates":[-4.25646646389409,51.68155283711521],"type":"Point"}
}