{
  "type": "Feature",
  "properties": {
    "date:inception_lower": "2017-04-01",
    "date:inception_upper": "2017-04-01",
    "iso:country": "GB",
    "wof:name": "EX11 1GG",
    "wof:placetype": "postalcode"
  },
  "geometry": {"coordinates":[-3.328094,50.735762],"type":"Point"}
}
