{
  "type": "Feature",
  "properties": {
    "date:inception_lower":"1980-01-01",
    "date:inception_upper":"1980-01-31",
    "iso:country":"GB",
    "wof:name":"BD6 1SS",
    "wof:placetype":"postalcode"
},
  "geometry": {"coordinates":[-1.773868,53.762774],"type":"Point"}
}