{
  "type": "Feature",
  "properties": {
    "iso:country":"GB",
    "wof:name":"B32 4JR",
    "wof:placetype":"postalcode"
},
  "geometry": {"coordinates":[-2.00892699564304,52.42758616533376],"type":"Point"}
}