{
  "type": "Feature",
  "properties": {
    "date:inception_lower": "1981-06-01",
    "date:inception_upper": "1981-06-01",
    "iso:country": "GB",
    "wof:name": "B32 4JR",
    "wof:placetype": "postalcode"
  },
  "geometry": {"coordinates":[-2.008927,52.427586],"type":"Point"}
}
