{
  "type": "Feature",
  "properties": {
    "date:inception_lower": "1980-01-01",
    "date:inception_upper": "1980-01-01",
    "iso:country": "GB",
    "wof:name": "HU11 5BW",
    "wof:placetype": "postalcode"
  },
  "geometry": {"coordinates":[-0.24566,53.865044],"type":"Point"}
}
