{
  "type": "Feature",
  "properties": {
    "iso:country": "GB",
    "wof:name": "HU11 5BW",
    "wof:placetype": "postalcode"
  },
  "geometry": {"coordinates":[-0.24566,53.865044],"type":"Point"}
}
