{
  "type": "Feature",
  "properties": {
    "iso:country":"GB",
    "wof:name":"CA3 9HW",
    "wof:placetype":"postalcode"
},
  "geometry": {"coordinates":[-2.93263916632389,54.91396605830829],"type":"Point"}
}