{
  "type": "Feature",
  "properties": {
    "iso:country":"GB",
    "wof:name":"HU11 5SN",
    "wof:placetype":"postalcode"
},
  "geometry": {"coordinates":[-0.24073249406777,53.91191168306942],"type":"Point"}
}