{
  "type": "Feature",
  "properties": {
    "iso:country": "GB",
    "wof:name": "HU11 5SN",
    "wof:placetype": "postalcode"
  },
  "geometry": {"coordinates":[-0.240732,53.911912],"type":"Point"}
}
