{
  "type": "Feature",
  "properties": {
    "iso:country":"GB",
    "wof:name":"HA5 1EA",
    "wof:placetype":"postalcode"
},
  "geometry": {"coordinates":[-0.38169822451281,51.58916640583637],"type":"Point"}
}