{
  "type": "Feature",
  "properties": {
    "iso:country": "GB",
    "wof:name": "HA5 1EA",
    "wof:placetype": "postalcode"
  },
  "geometry": {"coordinates":[-0.381698,51.589166],"type":"Point"}
}
