{
  "type": "Feature",
  "properties": {
    "date:inception_lower": "1980-01-01",
    "date:inception_upper": "1980-01-01",
    "iso:country": "GB",
    "wof:name": "BB2 1UL",
    "wof:placetype": "postalcode"
  },
  "geometry": {"coordinates":[-2.501351,53.742693],"type":"Point"}
}
