{
  "type": "Feature",
  "properties": {
    "iso:country": "GB",
    "wof:name": "BB2 1UL",
    "wof:placetype": "postalcode"
  },
  "geometry": {"coordinates":[-2.501351,53.742693],"type":"Point"}
}
