{
  "type": "Feature",
  "properties": {
    "iso:country":"GB",
    "wof:name":"CH61 5XY",
    "wof:placetype":"postalcode"
},
  "geometry": {"coordinates":[-3.10448295627675,53.34299901711386],"type":"Point"}
}