{
  "type": "Feature",
  "properties": {
    "date:inception_lower":"1999-06-01",
    "date:inception_upper":"1999-06-30",
    "iso:country":"GB",
    "wof:name":"CH61 5XY",
    "wof:placetype":"postalcode"
},
  "geometry": {"coordinates":[-3.104483,53.342999],"type":"Point"}
}