{
  "type": "Feature",
  "properties": {
    "iso:country": "GB",
    "wof:name": "LS29 0HP",
    "wof:placetype": "postalcode"
  },
  "geometry": {"coordinates":[-1.790019,53.943681],"type":"Point"}
}
