{
  "type": "Feature",
  "properties": {
    "date:inception_lower": "1980-01-01",
    "date:inception_upper": "1980-01-01",
    "iso:country": "GB",
    "wof:name": "LS29 0HP",
    "wof:placetype": "postalcode"
  },
  "geometry": {"coordinates":[-1.789796,53.945622],"type":"Point"}
}
