{
  "type": "Feature",
  "properties": {
    "iso:country":"GB",
    "wof:name":"SO51 0GG",
    "wof:placetype":"postalcode"
},
  "geometry": {"coordinates":[-1.55515201938447,51.01205014907912],"type":"Point"}
}