{
  "type": "Feature",
  "properties": {
    "iso:country":"GB",
    "wof:name":"WN3 5UJ",
    "wof:placetype":"postalcode"
},
  "geometry": {"coordinates":[-2.65246441435721,53.53156595895918],"type":"Point"}
}