{
  "type": "Feature",
  "properties": {
    "date:inception_lower": "1992-01-01",
    "date:inception_upper": "1992-01-01",
    "iso:country": "GB",
    "wof:name": "WN3 5UJ",
    "wof:placetype": "postalcode"
  },
  "geometry": {"coordinates":[-2.652464,53.531566],"type":"Point"}
}
