{
  "type": "Feature",
  "properties": {
    "iso:country":"GB",
    "wof:name":"NR1 1UN",
    "wof:placetype":"postalcode"
},
  "geometry": {"coordinates":[1.30469360639744,52.6244321960088],"type":"Point"}
}