{
  "type": "Feature",
  "properties": {
    "date:inception_lower":"2002-09-01",
    "date:inception_upper":"2002-09-30",
    "iso:country":"GB",
    "wof:name":"NR1 1UN",
    "wof:placetype":"postalcode"
},
  "geometry": {"coordinates":[1.304694,52.624432],"type":"Point"}
}