{
  "type": "Feature",
  "properties": {
    "date:inception_lower":"1980-01-01",
    "date:inception_upper":"1980-01-31",
    "iso:country":"GB",
    "wof:name":"CV3 1JL",
    "wof:placetype":"postalcode"
},
  "geometry": {"coordinates":[-1.488508,52.402144],"type":"Point"}
}