{
  "type": "Feature",
  "properties": {
    "iso:country":"GB",
    "wof:name":"CV3 1JL",
    "wof:placetype":"postalcode"
},
  "geometry": {"coordinates":[-1.48845900434836,52.40204605127626],"type":"Point"}
}