{
  "type": "Feature",
  "properties": {
    "iso:country":"GB",
    "wof:name":"M46 0QJ",
    "wof:placetype":"postalcode"
},
  "geometry": {"coordinates":[-2.50751554831137,53.51918210079615],"type":"Point"}
}