{
  "type": "Feature",
  "properties": {
    "date:inception_lower": "1994-05-01",
    "date:inception_upper": "1994-05-01",
    "iso:country": "GB",
    "wof:name": "M46 0QJ",
    "wof:placetype": "postalcode"
  },
  "geometry": {"coordinates":[-2.507516,53.519182],"type":"Point"}
}
