{
  "type": "Feature",
  "properties": {
    "iso:country":"GB",
    "wof:name":"RG42 2AU",
    "wof:placetype":"postalcode"
},
  "geometry": {"coordinates":[-0.76025828353168,51.42270356446604],"type":"Point"}
}