{
  "type": "Feature",
  "properties": {
    "iso:country": "GB",
    "wof:name": "PE12 8DN",
    "wof:placetype": "postalcode"
  },
  "geometry": {"coordinates":[0.018045,52.81814],"type":"Point"}
}
