{
  "type": "Feature",
  "properties": {
    "iso:country":"GB",
    "wof:name":"PE12 8DN",
    "wof:placetype":"postalcode"
},
  "geometry": {"coordinates":[0.01800279349766,52.81811065119295],"type":"Point"}
}