{
  "type": "Feature",
  "properties": {
    "date:inception_lower": "1995-01-01",
    "date:inception_upper": "1995-01-01",
    "iso:country": "GB",
    "wof:name": "CA13 0DN",
    "wof:placetype": "postalcode"
  },
  "geometry": {"coordinates":[-3.371444,54.657917],"type":"Point"}
}
