{
  "type": "Feature",
  "properties": {
    "iso:country":"GB",
    "wof:name":"NP20 2AG",
    "wof:placetype":"postalcode"
},
  "geometry": {"coordinates":[-2.98817141070856,51.58206748702807],"type":"Point"}
}