{
  "type": "Feature",
  "properties": {
    "iso:country":"GB",
    "wof:name":"RH1 3LH",
    "wof:placetype":"postalcode"
},
  "geometry": {"coordinates":[-0.15308711158945,51.2564188840077],"type":"Point"}
}