{
  "type": "Feature",
  "properties": {
    "date:inception_lower": "1980-01-01",
    "date:inception_upper": "1980-01-01",
    "iso:country": "GB",
    "wof:name": "RH1 3LH",
    "wof:placetype": "postalcode"
  },
  "geometry": {"coordinates":[-0.153087,51.256419],"type":"Point"}
}
