{
  "type": "Feature",
  "properties": {
    "date:inception_lower":"1980-01-01",
    "date:inception_upper":"1980-01-31",
    "iso:country":"GB",
    "wof:name":"SA68 0SW",
    "wof:placetype":"postalcode"
},
  "geometry": {"coordinates":[-4.800655,51.723001],"type":"Point"}
}