{
  "type": "Feature",
  "properties": {
    "iso:country":"GB",
    "wof:name":"SA68 0SW",
    "wof:placetype":"postalcode"
},
  "geometry": {"coordinates":[-4.80065477037116,51.72300069626407],"type":"Point"}
}