{
  "type": "Feature",
  "properties": {
    "iso:country": "GB",
    "wof:name": "B90 4JT",
    "wof:placetype": "postalcode"
  },
  "geometry": {"coordinates":[-1.814791,52.383912],"type":"Point"}
}
