{
  "type": "Feature",
  "properties": {
    "iso:country":"GB",
    "wof:name":"TS19 8XD",
    "wof:placetype":"postalcode"
},
  "geometry": {"coordinates":[-1.36069848665946,54.58007780823118],"type":"Point"}
}