{
  "type": "Feature",
  "properties": {
    "date:inception_lower": "2013-11-01",
    "date:inception_upper": "2013-11-01",
    "iso:country": "GB",
    "wof:name": "CB2 9BE",
    "wof:placetype": "postalcode"
  },
  "geometry": {"coordinates":[0.123397,52.169874],"type":"Point"}
}
