{
  "type": "Feature",
  "properties": {
    "date:inception_lower": "2006-05-01",
    "date:inception_upper": "2006-05-01",
    "iso:country": "GB",
    "wof:name": "B65 8EG",
    "wof:placetype": "postalcode"
  },
  "geometry": {"coordinates":[-2.047675,52.478604],"type":"Point"}
}
