{
  "type": "Feature",
  "properties": {
    "iso:country":"GB",
    "wof:name":"GL15 5LT",
    "wof:placetype":"postalcode"
},
  "geometry": {"coordinates":[-2.53080064597757,51.72976113117201],"type":"Point"}
}