{
  "type": "Feature",
  "properties": {
    "iso:country":"GB",
    "wof:name":"SK9 7RX",
    "wof:placetype":"postalcode"
},
  "geometry": {"coordinates":[-2.25457710669629,53.31066317814953],"type":"Point"}
}