{
  "type": "Feature",
  "properties": {
    "iso:country": "GB",
    "wof:name": "PO31 7GD",
    "wof:placetype": "postalcode"
  },
  "geometry": {"coordinates":[-1.29758,50.757088],"type":"Point"}
}
