{
  "type": "Feature",
  "properties": {
    "iso:country":"GB",
    "wof:name":"PO31 7GD",
    "wof:placetype":"postalcode"
},
  "geometry": {"coordinates":[-1.29757966974507,50.75708830929456],"type":"Point"}
}