{
  "type": "Feature",
  "properties": {
    "date:inception_lower": "2010-03-01",
    "date:inception_upper": "2010-03-01",
    "iso:country": "GB",
    "wof:name": "PO31 7GD",
    "wof:placetype": "postalcode"
  },
  "geometry": {"coordinates":[-1.29758,50.757088],"type":"Point"}
}
