{
  "type": "Feature",
  "properties": {
    "iso:country":"GB",
    "wof:name":"LA14 3JW",
    "wof:placetype":"postalcode"
},
  "geometry": {"coordinates":[-3.25496235620665,54.10082377727604],"type":"Point"}
}