{
  "type": "Feature",
  "properties": {
    "iso:country":"GB",
    "wof:name":"PL28 8QW",
    "wof:placetype":"postalcode"
},
  "geometry": {"coordinates":[-4.97688343273903,50.54069439986452],"type":"Point"}
}