{
  "type": "Feature",
  "properties": {
    "iso:country": "GB",
    "wof:name": "PL28 8QW",
    "wof:placetype": "postalcode"
  },
  "geometry": {"coordinates":[-4.976883,50.540694],"type":"Point"}
}
