{
  "type": "Feature",
  "properties": {
    "iso:country":"GB",
    "wof:name":"WD17 3TU",
    "wof:placetype":"postalcode"
},
  "geometry": {"coordinates":[-0.42920974109104,51.67564078518322],"type":"Point"}
}