{
  "type": "Feature",
  "properties": {
    "date:inception_lower":"2000-10-01",
    "date:inception_upper":"2000-10-31",
    "iso:country":"GB",
    "wof:name":"WD17 3TU",
    "wof:placetype":"postalcode"
},
  "geometry": {"coordinates":[-0.42921,51.675641],"type":"Point"}
}