{
  "type": "Feature",
  "properties": {
    "iso:country": "GB",
    "wof:name": "NR24 2QU",
    "wof:placetype": "postalcode"
  },
  "geometry": {"coordinates":[0.997987,52.84955],"type":"Point"}
}
