{
  "type": "Feature",
  "properties": {
    "iso:country":"GB",
    "wof:name":"NR24 2QU",
    "wof:placetype":"postalcode"
},
  "geometry": {"coordinates":[0.9979873568688,52.84954958396435],"type":"Point"}
}