{
  "type": "Feature",
  "properties": {
    "iso:country":"GB",
    "wof:name":"WA7 3AW",
    "wof:placetype":"postalcode"
},
  "geometry": {"coordinates":[-2.65452708000567,53.32073401732715],"type":"Point"}
}