{
  "type": "Feature",
  "properties": {
    "iso:country":"GB",
    "wof:name":"FY6 7HR",
    "wof:placetype":"postalcode"
},
  "geometry": {"coordinates":[-2.98448756138716,53.85508110997253],"type":"Point"}
}