{
  "type": "Feature",
  "properties": {
    "iso:country": "GB",
    "wof:name": "RM16 5UA",
    "wof:placetype": "postalcode"
  },
  "geometry": {"coordinates":[0.299889,51.496941],"type":"Point"}
}
