{
  "type": "Feature",
  "properties": {
    "date:inception_lower": "2006-01-01",
    "date:inception_upper": "2006-01-01",
    "iso:country": "GB",
    "wof:name": "RM16 5UA",
    "wof:placetype": "postalcode"
  },
  "geometry": {"coordinates":[0.299889,51.496941],"type":"Point"}
}
