{
  "type": "Feature",
  "properties": {
    "iso:country":"GB",
    "wof:name":"RM16 5UA",
    "wof:placetype":"postalcode"
},
  "geometry": {"coordinates":[0.29931089358317,51.49661879052893],"type":"Point"}
}