{
  "type": "Feature",
  "properties": {
    "iso:country":"GB",
    "wof:name":"NE6 2DR",
    "wof:placetype":"postalcode"
},
  "geometry": {"coordinates":[-1.58080446555083,54.97464236351654],"type":"Point"}
}