{
  "type": "Feature",
  "properties": {
    "iso:country": "GB",
    "wof:name": "WA15 6AU",
    "wof:placetype": "postalcode"
  },
  "geometry": {"coordinates":[-2.321353,53.406968],"type":"Point"}
}
