{
  "type": "Feature",
  "properties": {
    "iso:country":"GB",
    "wof:name":"OX4 4EA",
    "wof:placetype":"postalcode"
},
  "geometry": {"coordinates":[-1.23392887684806,51.73250299054496],"type":"Point"}
}