{
  "type": "Feature",
  "properties": {
    "date:inception_lower": "1980-01-01",
    "date:inception_upper": "1980-01-01",
    "iso:country": "GB",
    "wof:name": "OX4 4EA",
    "wof:placetype": "postalcode"
  },
  "geometry": {"coordinates":[-1.23391,51.732508],"type":"Point"}
}
