{
  "type": "Feature",
  "properties": {
    "date:inception_lower": "1988-03-01",
    "date:inception_upper": "1988-03-01",
    "iso:country": "GB",
    "wof:name": "DY10 2JJ",
    "wof:placetype": "postalcode"
  },
  "geometry": {"coordinates":[-2.246842,52.391782],"type":"Point"}
}
