{
  "type": "Feature",
  "properties": {
    "iso:country":"GB",
    "wof:name":"WV5 0EB",
    "wof:placetype":"postalcode"
},
  "geometry": {"coordinates":[-2.19269395283035,52.53028337824352],"type":"Point"}
}