{
  "type": "Feature",
  "properties": {
    "iso:country": "GB",
    "wof:name": "NG33 5BG",
    "wof:placetype": "postalcode"
  },
  "geometry": {"coordinates":[-0.606017,52.852333],"type":"Point"}
}
