{
  "type": "Feature",
  "properties": {
    "date:inception_lower": "1998-12-01",
    "date:inception_upper": "1998-12-01",
    "iso:country": "GB",
    "wof:name": "NG33 5BG",
    "wof:placetype": "postalcode"
  },
  "geometry": {"coordinates":[-0.606017,52.852333],"type":"Point"}
}
