{
  "type": "Feature",
  "properties": {
    "iso:country":"GB",
    "wof:name":"NG33 5BG",
    "wof:placetype":"postalcode"
},
  "geometry": {"coordinates":[-0.60601753726136,52.85233320340175],"type":"Point"}
}