{
  "type": "Feature",
  "properties": {
    "iso:country": "GB",
    "wof:name": "TF3 1TX",
    "wof:placetype": "postalcode"
  },
  "geometry": {"coordinates":[-2.444383,52.651544],"type":"Point"}
}
