{
  "type": "Feature",
  "properties": {
    "iso:country":"GB",
    "wof:name":"TF3 1TX",
    "wof:placetype":"postalcode"
},
  "geometry": {"coordinates":[-2.44438351193756,52.65154396993638],"type":"Point"}
}