{
  "type": "Feature",
  "properties": {
    "iso:country":"GB",
    "wof:name":"SW12 0HZ",
    "wof:placetype":"postalcode"
},
  "geometry": {"coordinates":[-0.14225940571815,51.44442939646535],"type":"Point"}
}