{
  "type": "Feature",
  "properties": {
    "iso:country":"GB",
    "wof:name":"SO45 3GS",
    "wof:placetype":"postalcode"
},
  "geometry": {"coordinates":[-1.39350759874706,50.85532241158973],"type":"Point"}
}