{
  "type": "Feature",
  "properties": {
    "date:inception_lower":"2000-06-01",
    "date:inception_upper":"2000-06-30",
    "iso:country":"GB",
    "wof:name":"M34 5SF",
    "wof:placetype":"postalcode"
},
  "geometry": {"coordinates":[-2.122074,53.46498],"type":"Point"}
}