{
  "type": "Feature",
  "properties": {
    "iso:country": "GB",
    "wof:name": "M34 5SF",
    "wof:placetype": "postalcode"
  },
  "geometry": {"coordinates":[-2.122074,53.46498],"type":"Point"}
}
