{
  "type": "Feature",
  "properties": {
    "date:inception_lower": "2000-06-01",
    "date:inception_upper": "2000-06-01",
    "iso:country": "GB",
    "wof:name": "M34 5SF",
    "wof:placetype": "postalcode"
  },
  "geometry": {"coordinates":[-2.131595,53.480241],"type":"Point"}
}
