{
  "type": "Feature",
  "properties": {
    "iso:country":"GB",
    "wof:name":"BR3 4QN",
    "wof:placetype":"postalcode"
},
  "geometry": {"coordinates":[-0.04524923457697,51.40644019612943],"type":"Point"}
}