{
  "type": "Feature",
  "properties": {
    "date:inception_lower":"1994-12-01",
    "date:inception_upper":"1994-12-31",
    "iso:country":"GB",
    "wof:name":"SO18 2LP",
    "wof:placetype":"postalcode"
},
  "geometry": {"coordinates":[-1.372581,50.940029],"type":"Point"}
}