{
  "type": "Feature",
  "properties": {
    "iso:country":"GB",
    "wof:name":"BS10 6BS",
    "wof:placetype":"postalcode"
},
  "geometry": {"coordinates":[-2.59591409604989,51.50711869269393],"type":"Point"}
}