{
  "type": "Feature",
  "properties": {
    "iso:country":"GB",
    "wof:name":"SY11 2XQ",
    "wof:placetype":"postalcode"
},
  "geometry": {"coordinates":[-3.03633487670649,52.86213727175222],"type":"Point"}
}