{
  "type": "Feature",
  "properties": {
    "iso:country": "GB",
    "wof:name": "SY11 2XQ",
    "wof:placetype": "postalcode"
  },
  "geometry": {"coordinates":[-3.036335,52.862137],"type":"Point"}
}
