{
  "type": "Feature",
  "properties": {
    "iso:country":"GB",
    "wof:name":"WF8 3RQ",
    "wof:placetype":"postalcode"
},
  "geometry": {"coordinates":[-1.31247899470033,53.67734472126168],"type":"Point"}
}