{
  "type": "Feature",
  "properties": {
    "date:inception_lower": "1990-02-01",
    "date:inception_upper": "1990-02-01",
    "iso:country": "GB",
    "wof:name": "WF8 3RQ",
    "wof:placetype": "postalcode"
  },
  "geometry": {"coordinates":[-1.312479,53.677345],"type":"Point"}
}
