{
  "type": "Feature",
  "properties": {
    "date:inception_lower": "2002-06-01",
    "date:inception_upper": "2002-06-01",
    "iso:country": "GB",
    "wof:name": "BS30 9UT",
    "wof:placetype": "postalcode"
  },
  "geometry": {"coordinates":[-2.486258,51.438794],"type":"Point"}
}
