{
  "type": "Feature",
  "properties": {
    "iso:country":"GB",
    "wof:name":"BS30 9UT",
    "wof:placetype":"postalcode"
},
  "geometry": {"coordinates":[-2.4862581773223,51.43879422375301],"type":"Point"}
}