{
  "type": "Feature",
  "properties": {
    "date:inception_lower": "2004-02-01",
    "date:inception_upper": "2004-02-01",
    "iso:country": "GB",
    "wof:name": "GU21 5BL",
    "wof:placetype": "postalcode"
  },
  "geometry": {"coordinates":[-0.554258,51.321788],"type":"Point"}
}
