{
  "type": "Feature",
  "properties": {
    "iso:country":"GB",
    "wof:name":"GU21 5BL",
    "wof:placetype":"postalcode"
},
  "geometry": {"coordinates":[-0.55425790361821,51.32178848402255],"type":"Point"}
}