{
  "type": "Feature",
  "properties": {
    "date:inception_lower": "1980-01-01",
    "date:inception_upper": "1980-01-01",
    "iso:country": "GB",
    "wof:name": "BS13 7LD",
    "wof:placetype": "postalcode"
  },
  "geometry": {"coordinates":[-2.613154,51.423884],"type":"Point"}
}
