{
  "type": "Feature",
  "properties": {
    "iso:country":"GB",
    "wof:name":"CM4 9LP",
    "wof:placetype":"postalcode"
},
  "geometry": {"coordinates":[0.44707500563108,51.66311369051164],"type":"Point"}
}