{
  "type": "Feature",
  "properties": {
    "iso:country": "GB",
    "wof:name": "CM4 9LP",
    "wof:placetype": "postalcode"
  },
  "geometry": {"coordinates":[0.447075,51.663114],"type":"Point"}
}
