{
  "type": "Feature",
  "properties": {
    "iso:country":"GB",
    "wof:name":"SW17 8PB",
    "wof:placetype":"postalcode"
},
  "geometry": {"coordinates":[-0.16243698896767,51.43110567816685],"type":"Point"}
}