{
  "type": "Feature",
  "properties": {
    "date:inception_lower": "1980-01-01",
    "date:inception_upper": "1980-01-01",
    "iso:country": "GB",
    "wof:name": "PL10 1DJ",
    "wof:placetype": "postalcode"
  },
  "geometry": {"coordinates":[-4.208699,50.3479],"type":"Point"}
}
