{
  "type": "Feature",
  "properties": {
    "iso:country":"GB",
    "wof:name":"PL10 1DJ",
    "wof:placetype":"postalcode"
},
  "geometry": {"coordinates":[-4.20869882727643,50.34790049798496],"type":"Point"}
}