{
  "type": "Feature",
  "properties": {
    "iso:country":"GB",
    "wof:name":"S12 4XA",
    "wof:placetype":"postalcode"
},
  "geometry": {"coordinates":[-1.4053412724296,53.34961657099708],"type":"Point"}
}