{
  "type": "Feature",
  "properties": {
    "iso:country": "GB",
    "wof:name": "S12 4XA",
    "wof:placetype": "postalcode"
  },
  "geometry": {"coordinates":[-1.405386,53.349645],"type":"Point"}
}
