{
  "type": "Feature",
  "properties": {
    "iso:country":"GB",
    "wof:name":"GU7 3DU",
    "wof:placetype":"postalcode"
},
  "geometry": {"coordinates":[-0.60741368062804,51.18900309125819],"type":"Point"}
}