{
  "type": "Feature",
  "properties": {
    "iso:country":"GB",
    "wof:name":"YO24 3ND",
    "wof:placetype":"postalcode"
},
  "geometry": {"coordinates":[-1.12652744507656,53.94267994953508],"type":"Point"}
}