{
  "type": "Feature",
  "properties": {
    "iso:country":"GB",
    "wof:name":"S12 4BX",
    "wof:placetype":"postalcode"
},
  "geometry": {"coordinates":[-1.37137256460559,53.3467818763207],"type":"Point"}
}