{
  "type": "Feature",
  "properties": {
    "date:inception_lower": "1991-03-01",
    "date:inception_upper": "1991-03-01",
    "iso:country": "GB",
    "wof:name": "TD5 7TU",
    "wof:placetype": "postalcode"
  },
  "geometry": {"coordinates":[-2.426033,55.608709],"type":"Point"}
}
