{
  "type": "Feature",
  "properties": {
    "iso:country":"GB",
    "wof:name":"TD5 7TU",
    "wof:placetype":"postalcode"
},
  "geometry": {"coordinates":[-2.42603348397181,55.60870938550577],"type":"Point"}
}