{
  "type": "Feature",
  "properties": {
    "date:inception_lower": "1983-03-01",
    "date:inception_upper": "1983-03-01",
    "iso:country": "GB",
    "wof:name": "MK16 0JF",
    "wof:placetype": "postalcode"
  },
  "geometry": {"coordinates":[-0.727066,52.078177],"type":"Point"}
}
