{
  "type": "Feature",
  "properties": {
    "iso:country":"GB",
    "wof:name":"YO32 5XB",
    "wof:placetype":"postalcode"
},
  "geometry": {"coordinates":[-1.02983833449294,54.0401866429381],"type":"Point"}
}