{
  "type": "Feature",
  "properties": {
    "iso:country": "GB",
    "wof:name": "YO32 5XB",
    "wof:placetype": "postalcode"
  },
  "geometry": {"coordinates":[-1.029838,54.040187],"type":"Point"}
}
