{
  "type": "Feature",
  "properties": {
    "iso:country": "GB",
    "wof:name": "EX34 7AR",
    "wof:placetype": "postalcode"
  },
  "geometry": {"coordinates":[-4.195976,51.176913],"type":"Point"}
}
