{
  "type": "Feature",
  "properties": {
    "iso:country":"GB",
    "wof:name":"EX34 7AR",
    "wof:placetype":"postalcode"
},
  "geometry": {"coordinates":[-4.19597583882676,51.17691340092333],"type":"Point"}
}