{
  "type": "Feature",
  "properties": {
    "iso:country":"GB",
    "wof:name":"SK6 8HU",
    "wof:placetype":"postalcode"
},
  "geometry": {"coordinates":[-2.06935753408533,53.36508965629609],"type":"Point"}
}