{
  "type": "Feature",
  "properties": {
    "iso:country": "GB",
    "wof:name": "SK6 8HU",
    "wof:placetype": "postalcode"
  },
  "geometry": {"coordinates":[-2.069357,53.36509],"type":"Point"}
}
