{
  "type": "Feature",
  "properties": {
    "iso:country": "GB",
    "wof:name": "DE21 2PL",
    "wof:placetype": "postalcode"
  },
  "geometry": {"coordinates":[-1.442419,52.946349],"type":"Point"}
}
