{
  "type": "Feature",
  "properties": {
    "iso:country":"GB",
    "wof:name":"DE21 2PL",
    "wof:placetype":"postalcode"
},
  "geometry": {"coordinates":[-1.44241899485319,52.94634856396153],"type":"Point"}
}