{
  "type": "Feature",
  "properties": {
    "date:inception_lower": "1980-01-01",
    "date:inception_upper": "1980-01-01",
    "iso:country": "GB",
    "wof:name": "W3 9DJ",
    "wof:placetype": "postalcode"
  },
  "geometry": {"coordinates":[-0.271716,51.507234],"type":"Point"}
}
