{
  "type": "Feature",
  "properties": {
    "iso:country":"GB",
    "wof:name":"W3 9DJ",
    "wof:placetype":"postalcode"
},
  "geometry": {"coordinates":[-0.27171616805264,51.50723414266658],"type":"Point"}
}