{
  "type": "Feature",
  "properties": {
    "date:inception_lower": "2011-05-01",
    "date:inception_upper": "2011-05-01",
    "iso:country": "GB",
    "wof:name": "M4 4EF",
    "wof:placetype": "postalcode"
  },
  "geometry": {"coordinates":[-2.240172,53.48988],"type":"Point"}
}
