{
  "type": "Feature",
  "properties": {
    "iso:country":"GB",
    "wof:name":"HG5 0NW",
    "wof:placetype":"postalcode"
},
  "geometry": {"coordinates":[-1.46330881790179,54.01826604502531],"type":"Point"}
}