{
  "type": "Feature",
  "properties": {
    "date:inception_lower":"1980-01-01",
    "date:inception_upper":"1980-01-31",
    "iso:country":"GB",
    "wof:name":"HG5 0NW",
    "wof:placetype":"postalcode"
},
  "geometry": {"coordinates":[-1.463309,54.018266],"type":"Point"}
}