{
  "type": "Feature",
  "properties": {
    "date:inception_lower":"2012-09-01",
    "date:inception_upper":"2012-09-30",
    "iso:country":"GB",
    "wof:name":"RH6 9FF",
    "wof:placetype":"postalcode"
},
  "geometry": {"coordinates":[-0.150389,51.182185],"type":"Point"}
}