{
  "type": "Feature",
  "properties": {
    "iso:country":"GB",
    "wof:name":"L36 1TH",
    "wof:placetype":"postalcode"
},
  "geometry": {"coordinates":[-2.82512189031038,53.42159158202936],"type":"Point"}
}