{
  "type": "Feature",
  "properties": {
    "date:inception_lower": "1980-01-01",
    "date:inception_upper": "1980-01-01",
    "iso:country": "GB",
    "wof:name": "L36 1TH",
    "wof:placetype": "postalcode"
  },
  "geometry": {"coordinates":[-2.825122,53.421592],"type":"Point"}
}
