{
  "type": "Feature",
  "properties": {
    "iso:country":"GB",
    "wof:name":"PE20 3NY",
    "wof:placetype":"postalcode"
},
  "geometry": {"coordinates":[-0.166608745289,52.95238674422593],"type":"Point"}
}