{
  "type": "Feature",
  "properties": {
    "date:inception_lower":"1980-01-01",
    "date:inception_upper":"1980-01-31",
    "iso:country":"GB",
    "wof:name":"PE20 3NY",
    "wof:placetype":"postalcode"
},
  "geometry": {"coordinates":[-0.166237,52.952566],"type":"Point"}
}