{
  "type": "Feature",
  "properties": {
    "iso:country":"GB",
    "wof:name":"SY10 8LL",
    "wof:placetype":"postalcode"
},
  "geometry": {"coordinates":[-3.07312936938437,52.80801515423208],"type":"Point"}
}