{
  "type": "Feature",
  "properties": {
    "date:inception_lower": "1980-01-01",
    "date:inception_upper": "1980-01-01",
    "iso:country": "GB",
    "wof:name": "SA2 7NJ",
    "wof:placetype": "postalcode"
  },
  "geometry": {"coordinates":[-4.003776,51.620645],"type":"Point"}
}
