{
  "type": "Feature",
  "properties": {
    "iso:country":"GB",
    "wof:name":"SA2 7NJ",
    "wof:placetype":"postalcode"
},
  "geometry": {"coordinates":[-4.00377625322187,51.62064498637951],"type":"Point"}
}