{
  "type": "Feature",
  "properties": {
    "iso:country":"GB",
    "wof:name":"HS2 9NT",
    "wof:placetype":"postalcode"
},
  "geometry": {"coordinates":[-6.45653742789183,58.14456913086713],"type":"Point"}
}