{
  "type": "Feature",
  "properties": {
    "iso:country":"GB",
    "wof:name":"DH2 2QS",
    "wof:placetype":"postalcode"
},
  "geometry": {"coordinates":[-1.60785944167326,54.86419150475037],"type":"Point"}
}