{
  "type": "Feature",
  "properties": {
    "iso:country":"GB",
    "wof:name":"E6 6WN",
    "wof:placetype":"postalcode"
},
  "geometry": {"coordinates":[0.06674248882538,51.51309787318551],"type":"Point"}
}