{
  "type": "Feature",
  "properties": {
    "iso:country": "GB",
    "wof:name": "KA23 9LT",
    "wof:placetype": "postalcode"
  },
  "geometry": {"coordinates":[-4.862165,55.685938],"type":"Point"}
}
