{
  "type": "Feature",
  "properties": {
    "date:inception_lower":"1980-01-01",
    "date:inception_upper":"1980-01-31",
    "iso:country":"GB",
    "wof:name":"KA23 9LT",
    "wof:placetype":"postalcode"
},
  "geometry": {"coordinates":[-4.86217,55.685915],"type":"Point"}
}