{
  "type": "Feature",
  "properties": {
    "iso:country":"GB",
    "wof:name":"W10 6HY",
    "wof:placetype":"postalcode"
},
  "geometry": {"coordinates":[-0.21663033811104,51.51711047783354],"type":"Point"}
}