{
  "type": "Feature",
  "properties": {
    "iso:country":"GB",
    "wof:name":"SA69 9AJ",
    "wof:placetype":"postalcode"
},
  "geometry": {"coordinates":[-4.69623914622228,51.71725178533171],"type":"Point"}
}