{
  "type": "Feature",
  "properties": {
    "iso:country": "GB",
    "wof:name": "RG1 4NN",
    "wof:placetype": "postalcode"
  },
  "geometry": {"coordinates":[-0.958359,51.453586],"type":"Point"}
}
