{
  "type": "Feature",
  "properties": {
    "date:inception_lower":"2016-08-01",
    "date:inception_upper":"2016-08-31",
    "iso:country":"GB",
    "wof:name":"RG1 4NN",
    "wof:placetype":"postalcode"
},
  "geometry": {"coordinates":[-0.958359,51.453586],"type":"Point"}
}