{
  "type": "Feature",
  "properties": {
    "date:inception_lower": "1986-07-01",
    "date:inception_upper": "1986-07-01",
    "iso:country": "GB",
    "wof:name": "DE1 3BZ",
    "wof:placetype": "postalcode"
  },
  "geometry": {"coordinates":[-1.477686,52.928081],"type":"Point"}
}
