{
  "type": "Feature",
  "properties": {
    "date:inception_lower":"2008-12-01",
    "date:inception_upper":"2008-12-31",
    "iso:country":"GB",
    "wof:name":"PE33 0BF",
    "wof:placetype":"postalcode"
},
  "geometry": {"coordinates":[0.42021,52.690064],"type":"Point"}
}