{
  "type": "Feature",
  "properties": {
    "iso:country": "GB",
    "wof:name": "PE33 0BF",
    "wof:placetype": "postalcode"
  },
  "geometry": {"coordinates":[0.42021,52.690064],"type":"Point"}
}
