{
  "type": "Feature",
  "properties": {
    "iso:country":"GB",
    "wof:name":"PE33 0BF",
    "wof:placetype":"postalcode"
},
  "geometry": {"coordinates":[0.42021044880358,52.69006386052332],"type":"Point"}
}