{
  "type": "Feature",
  "properties": {
    "iso:country":"GB",
    "wof:name":"RH17 5QN",
    "wof:placetype":"postalcode"
},
  "geometry": {"coordinates":[-0.20476723166797,50.99099483647367],"type":"Point"}
}