{
  "type": "Feature",
  "properties": {
    "iso:country":"GB",
    "wof:name":"S80 1XA",
    "wof:placetype":"postalcode"
},
  "geometry": {"coordinates":[-1.12644563086505,53.2984083588608],"type":"Point"}
}