{
  "type": "Feature",
  "properties": {
    "iso:country": "GB",
    "wof:name": "S80 1XA",
    "wof:placetype": "postalcode"
  },
  "geometry": {"coordinates":[-1.126446,53.298408],"type":"Point"}
}
