{
  "type": "Feature",
  "properties": {
    "iso:country":"GB",
    "wof:name":"KY5 0ND",
    "wof:placetype":"postalcode"
},
  "geometry": {"coordinates":[-3.27545596100301,56.14725805932273],"type":"Point"}
}