{
  "type": "Feature",
  "properties": {
    "date:inception_lower": "1980-01-01",
    "date:inception_upper": "1980-01-01",
    "iso:country": "GB",
    "wof:name": "KY5 0ND",
    "wof:placetype": "postalcode"
  },
  "geometry": {"coordinates":[-3.275456,56.147258],"type":"Point"}
}
