{
  "type": "Feature",
  "properties": {
    "iso:country":"GB",
    "wof:name":"LN8 3ER",
    "wof:placetype":"postalcode"
},
  "geometry": {"coordinates":[-0.33003689879116,53.38904726864165],"type":"Point"}
}