{
  "type": "Feature",
  "properties": {
    "date:inception_lower": "2002-07-01",
    "date:inception_upper": "2002-07-01",
    "iso:country": "GB",
    "wof:name": "LL13 9FX",
    "wof:placetype": "postalcode"
  },
  "geometry": {"coordinates":[-2.960967,53.05478],"type":"Point"}
}
