{
  "type": "Feature",
  "properties": {
    "iso:country": "GB",
    "wof:name": "LL13 9FX",
    "wof:placetype": "postalcode"
  },
  "geometry": {"coordinates":[-2.960967,53.05478],"type":"Point"}
}
