{
  "type": "Feature",
  "properties": {
    "iso:country": "GB",
    "wof:name": "EN2 6PN",
    "wof:placetype": "postalcode"
  },
  "geometry": {"coordinates":[-0.091789,51.649619],"type":"Point"}
}
