{
  "type": "Feature",
  "properties": {
    "iso:country":"GB",
    "wof:name":"BA14 9PG",
    "wof:placetype":"postalcode"
},
  "geometry": {"coordinates":[-2.2332029047609,51.29412173926768],"type":"Point"}
}