{
  "type": "Feature",
  "properties": {
    "iso:country": "GB",
    "wof:name": "BA14 9PG",
    "wof:placetype": "postalcode"
  },
  "geometry": {"coordinates":[-2.233203,51.294122],"type":"Point"}
}
