{
  "type": "Feature",
  "properties": {
    "iso:country":"GB",
    "wof:name":"CV1 5GD",
    "wof:placetype":"postalcode"
},
  "geometry": {"coordinates":[-1.49999983810456,52.41481646515744],"type":"Point"}
}