{
  "type": "Feature",
  "properties": {
    "date:inception_lower": "1991-01-01",
    "date:inception_upper": "1991-01-01",
    "iso:country": "GB",
    "wof:name": "HG3 2NX",
    "wof:placetype": "postalcode"
  },
  "geometry": {"coordinates":[-1.567043,54.00079],"type":"Point"}
}
