{
  "type": "Feature",
  "properties": {
    "iso:country":"GB",
    "wof:name":"NP16 7EP",
    "wof:placetype":"postalcode"
},
  "geometry": {"coordinates":[-2.66486028733335,51.64856166002004],"type":"Point"}
}