{
  "type": "Feature",
  "properties": {
    "iso:country":"GB",
    "wof:name":"SW14 8LD",
    "wof:placetype":"postalcode"
},
  "geometry": {"coordinates":[-0.26868644394156,51.46055484205341],"type":"Point"}
}