{
  "type": "Feature",
  "properties": {
    "date:inception_lower": "1994-05-01",
    "date:inception_upper": "1994-05-01",
    "iso:country": "GB",
    "wof:name": "SW14 8LD",
    "wof:placetype": "postalcode"
  },
  "geometry": {"coordinates":[-0.268686,51.460555],"type":"Point"}
}
