{
  "type": "Feature",
  "properties": {
    "iso:country":"GB",
    "wof:name":"SA13 3RS",
    "wof:placetype":"postalcode"
},
  "geometry": {"coordinates":[-3.64234909925603,51.64296656960829],"type":"Point"}
}