{
  "type": "Feature",
  "properties": {
    "iso:country": "GB",
    "wof:name": "SA13 3RS",
    "wof:placetype": "postalcode"
  },
  "geometry": {"coordinates":[-3.642552,51.642985],"type":"Point"}
}
