{
  "type": "Feature",
  "properties": {
    "date:inception_lower": "1994-05-01",
    "date:inception_upper": "1994-05-01",
    "iso:country": "GB",
    "wof:name": "BB2 3WJ",
    "wof:placetype": "postalcode"
  },
  "geometry": {"coordinates":[-2.46539,53.727864],"type":"Point"}
}
