{
  "type": "Feature",
  "properties": {
    "iso:country":"GB",
    "wof:name":"BB2 3WJ",
    "wof:placetype":"postalcode"
},
  "geometry": {"coordinates":[-2.46539013111019,53.72786430939173],"type":"Point"}
}