{
  "type": "Feature",
  "properties": {
    "iso:country": "GB",
    "wof:name": "M21 8EF",
    "wof:placetype": "postalcode"
  },
  "geometry": {"coordinates":[-2.282001,53.434006],"type":"Point"}
}
