{
  "type": "Feature",
  "properties": {
    "date:inception_lower":"2009-12-01",
    "date:inception_upper":"2009-12-31",
    "iso:country":"GB",
    "wof:name":"PO1 5FJ",
    "wof:placetype":"postalcode"
},
  "geometry": {"coordinates":[-1.076644,50.798085],"type":"Point"}
}