{
  "type": "Feature",
  "properties": {
    "iso:country":"GB",
    "wof:name":"IP22 2RY",
    "wof:placetype":"postalcode"
},
  "geometry": {"coordinates":[0.9485499974399,52.39444545658731],"type":"Point"}
}