{
  "type": "Feature",
  "properties": {
    "iso:country":"GB",
    "wof:name":"MK3 5HQ",
    "wof:placetype":"postalcode"
},
  "geometry": {"coordinates":[-0.73803470026975,51.99238405271333],"type":"Point"}
}