{
  "type": "Feature",
  "properties": {
    "date:inception_lower": "2009-10-01",
    "date:inception_upper": "2009-10-01",
    "iso:country": "GB",
    "wof:name": "WR11 4RP",
    "wof:placetype": "postalcode"
  },
  "geometry": {"coordinates":[-1.936893,52.096322],"type":"Point"}
}
