{
  "type": "Feature",
  "properties": {
    "iso:country": "GB",
    "wof:name": "W8 7DN",
    "wof:placetype": "postalcode"
  },
  "geometry": {"coordinates":[-0.196766,51.500036],"type":"Point"}
}
