{
  "type": "Feature",
  "properties": {
    "date:inception_lower": "1999-06-01",
    "date:inception_upper": "1999-06-01",
    "iso:country": "GB",
    "wof:name": "CF23 5BB",
    "wof:placetype": "postalcode"
  },
  "geometry": {"coordinates":[-3.163546,51.496287],"type":"Point"}
}
