{
  "type": "Feature",
  "properties": {
    "iso:country": "GB",
    "wof:name": "TS18 4QL",
    "wof:placetype": "postalcode"
  },
  "geometry": {"coordinates":[-1.339445,54.569278],"type":"Point"}
}
