{
  "type": "Feature",
  "properties": {
    "date:inception_lower": "2005-05-01",
    "date:inception_upper": "2005-05-01",
    "iso:country": "GB",
    "wof:name": "TS18 4QL",
    "wof:placetype": "postalcode"
  },
  "geometry": {"coordinates":[-1.339445,54.569278],"type":"Point"}
}
