{
  "type": "Feature",
  "properties": {
    "date:inception_lower": "2002-10-01",
    "date:inception_upper": "2002-10-01",
    "iso:country": "GB",
    "wof:name": "NN6 9RT",
    "wof:placetype": "postalcode"
  },
  "geometry": {"coordinates":[-0.905167,52.322842],"type":"Point"}
}
