{
  "type": "Feature",
  "properties": {
    "iso:country":"GB",
    "wof:name":"NN6 9RT",
    "wof:placetype":"postalcode"
},
  "geometry": {"coordinates":[-0.90516724496407,52.32284247691384],"type":"Point"}
}