{
  "type": "Feature",
  "properties": {
    "date:inception_lower":"1997-06-01",
    "date:inception_upper":"1997-06-30",
    "iso:country":"GB",
    "wof:name":"S25 5HB",
    "wof:placetype":"postalcode"
},
  "geometry": {"coordinates":[-1.22285,53.34882],"type":"Point"}
}