{
  "type": "Feature",
  "properties": {
    "iso:country":"GB",
    "wof:name":"S25 5HB",
    "wof:placetype":"postalcode"
},
  "geometry": {"coordinates":[-1.22284955873918,53.34881983362302],"type":"Point"}
}