{
  "type": "Feature",
  "properties": {
    "iso:country": "GB",
    "wof:name": "S25 5HB",
    "wof:placetype": "postalcode"
  },
  "geometry": {"coordinates":[-1.22285,53.34882],"type":"Point"}
}
