{
  "type": "Feature",
  "properties": {
    "iso:country":"GB",
    "wof:name":"UB5 6JP",
    "wof:placetype":"postalcode"
},
  "geometry": {"coordinates":[-0.39571727148544,51.53294200470497],"type":"Point"}
}