{
  "type": "Feature",
  "properties": {
    "date:inception_lower": "1980-01-01",
    "date:inception_upper": "1980-01-01",
    "iso:country": "GB",
    "wof:name": "TS23 2HB",
    "wof:placetype": "postalcode"
  },
  "geometry": {"coordinates":[-1.283047,54.606559],"type":"Point"}
}
