{
  "type": "Feature",
  "properties": {
    "date:inception_lower":"2003-10-01",
    "date:inception_upper":"2003-10-31",
    "iso:country":"GB",
    "wof:name":"CO15 2DX",
    "wof:placetype":"postalcode"
},
  "geometry": {"coordinates":[1.121576,51.776216],"type":"Point"}
}