{
  "type": "Feature",
  "properties": {
    "iso:country":"GB",
    "wof:name":"RM13 7YP",
    "wof:placetype":"postalcode"
},
  "geometry": {"coordinates":[0.18267719218964,51.53481059182856],"type":"Point"}
}