{
  "type": "Feature",
  "properties": {
    "iso:country":"GB",
    "wof:name":"NN3 8AF",
    "wof:placetype":"postalcode"
},
  "geometry": {"coordinates":[-0.84063948417258,52.27276910348308],"type":"Point"}
}