{
  "type": "Feature",
  "properties": {
    "date:inception_lower":"1991-01-01",
    "date:inception_upper":"1991-01-31",
    "iso:country":"GB",
    "wof:name":"SS2 6BG",
    "wof:placetype":"postalcode"
},
  "geometry": {"coordinates":[0.707585,51.543571],"type":"Point"}
}