{
  "type": "Feature",
  "properties": {
    "date:inception_lower":"1980-01-01",
    "date:inception_upper":"1980-01-31",
    "iso:country":"GB",
    "wof:name":"SA70 7SR",
    "wof:placetype":"postalcode"
},
  "geometry": {"coordinates":[-4.801038,51.655881],"type":"Point"}
}