{
  "type": "Feature",
  "properties": {
    "iso:country":"GB",
    "wof:name":"SA70 7SR",
    "wof:placetype":"postalcode"
},
  "geometry": {"coordinates":[-4.80103799916467,51.65588090356836],"type":"Point"}
}