{
  "type": "Feature",
  "properties": {
    "iso:country":"GB",
    "wof:name":"WF13 3DS",
    "wof:placetype":"postalcode"
},
  "geometry": {"coordinates":[-1.66582583373512,53.68334512205973],"type":"Point"}
}