{
  "type": "Feature",
  "properties": {
    "iso:country":"GB",
    "wof:name":"LL11 3HU",
    "wof:placetype":"postalcode"
},
  "geometry": {"coordinates":[-3.06184426983683,53.05553990128065],"type":"Point"}
}