{
  "type": "Feature",
  "properties": {
    "iso:country":"GB",
    "wof:name":"TF10 7GB",
    "wof:placetype":"postalcode"
},
  "geometry": {"coordinates":[-2.37480808615313,52.7760845055398],"type":"Point"}
}