{
  "type": "Feature",
  "properties": {
    "date:inception_lower": "2007-07-01",
    "date:inception_upper": "2007-07-01",
    "iso:country": "GB",
    "wof:name": "TF10 7GB",
    "wof:placetype": "postalcode"
  },
  "geometry": {"coordinates":[-2.374808,52.776085],"type":"Point"}
}
