{
  "type": "Feature",
  "properties": {
    "iso:country":"GB",
    "wof:name":"TW16 7NL",
    "wof:placetype":"postalcode"
},
  "geometry": {"coordinates":[-0.42636993707802,51.42078309789947],"type":"Point"}
}