{
  "type": "Feature",
  "properties": {
    "iso:country":"GB",
    "wof:name":"WF3 1FA",
    "wof:placetype":"postalcode"
},
  "geometry": {"coordinates":[-1.55699157696694,53.72697142242503],"type":"Point"}
}