{
  "type": "Feature",
  "properties": {
    "iso:country":"GB",
    "wof:name":"B92 8RX",
    "wof:placetype":"postalcode"
},
  "geometry": {"coordinates":[-1.7855597238863,52.4372816276349],"type":"Point"}
}