{
  "type": "Feature",
  "properties": {
    "iso:country":"GB",
    "wof:name":"WA15 7BQ",
    "wof:placetype":"postalcode"
},
  "geometry": {"coordinates":[-2.31384184268843,53.3960310452225],"type":"Point"}
}