{
  "type": "Feature",
  "properties": {
    "date:inception_lower": "1980-01-01",
    "date:inception_upper": "1980-01-01",
    "iso:country": "GB",
    "wof:name": "WA15 7BQ",
    "wof:placetype": "postalcode"
  },
  "geometry": {"coordinates":[-2.313842,53.396031],"type":"Point"}
}
