{
  "type": "Feature",
  "properties": {
    "iso:country": "GB",
    "wof:name": "CF83 8JA",
    "wof:placetype": "postalcode"
  },
  "geometry": {"coordinates":[-3.183935,51.593105],"type":"Point"}
}
