{
  "type": "Feature",
  "properties": {
    "date:inception_lower":"2016-02-01",
    "date:inception_upper":"2016-02-29",
    "iso:country":"GB",
    "wof:name":"CF83 8JA",
    "wof:placetype":"postalcode"
},
  "geometry": {"coordinates":[-3.183935,51.593105],"type":"Point"}
}