{
  "type": "Feature",
  "properties": {
    "iso:country":"GB",
    "wof:name":"UB5 6RP",
    "wof:placetype":"postalcode"
},
  "geometry": {"coordinates":[-0.377544242057,51.53190976810384],"type":"Point"}
}