{
  "type": "Feature",
  "properties": {
    "date:inception_lower": "1997-06-01",
    "date:inception_upper": "1997-06-01",
    "iso:country": "GB",
    "wof:name": "S20 1EH",
    "wof:placetype": "postalcode"
  },
  "geometry": {"coordinates":[-1.332606,53.341726],"type":"Point"}
}
