{
  "type": "Feature",
  "properties": {
    "iso:country":"GB",
    "wof:name":"S20 1EH",
    "wof:placetype":"postalcode"
},
  "geometry": {"coordinates":[-1.33260642146693,53.34172649557344],"type":"Point"}
}