{
  "type": "Feature",
  "properties": {
    "iso:country": "GB",
    "wof:name": "PO10 7EG",
    "wof:placetype": "postalcode"
  },
  "geometry": {"coordinates":[-0.937593,50.84531],"type":"Point"}
}
