{
  "type": "Feature",
  "properties": {
    "iso:country":"GB",
    "wof:name":"RG18 9RG",
    "wof:placetype":"postalcode"
},
  "geometry": {"coordinates":[-1.26634844343508,51.45472898050087],"type":"Point"}
}