{
  "type": "Feature",
  "properties": {
    "iso:country":"GB",
    "wof:name":"OL10 4SU",
    "wof:placetype":"postalcode"
},
  "geometry": {"coordinates":[-2.24235497775877,53.59772736055754],"type":"Point"}
}