{
  "type": "Feature",
  "properties": {
    "date:inception_lower": "2020-05-01",
    "date:inception_upper": "2020-05-01",
    "iso:country": "GB",
    "wof:name": "E9 6FU",
    "wof:placetype": "postalcode"
  },
  "geometry": {"coordinates":[-0.04736,51.547824],"type":"Point"}
}
