{
  "type": "Feature",
  "properties": {
    "iso:country":"GB",
    "wof:name":"PH7 3WB",
    "wof:placetype":"postalcode"
},
  "geometry": {"coordinates":[-3.83890370952807,56.37251745025251],"type":"Point"}
}