{
  "type": "Feature",
  "properties": {
    "date:inception_lower":"1980-01-01",
    "date:inception_upper":"1980-01-31",
    "iso:country":"GB",
    "wof:name":"NW2 5JN",
    "wof:placetype":"postalcode"
},
  "geometry": {"coordinates":[-0.227571,51.546513],"type":"Point"}
}