{
  "type": "Feature",
  "properties": {
    "iso:country":"GB",
    "wof:name":"NW2 5JN",
    "wof:placetype":"postalcode"
},
  "geometry": {"coordinates":[-0.2275402699991,51.54645612796758],"type":"Point"}
}