{
  "type": "Feature",
  "properties": {
    "iso:country": "GB",
    "wof:name": "NW2 5JN",
    "wof:placetype": "postalcode"
  },
  "geometry": {"coordinates":[-0.227571,51.546513],"type":"Point"}
}
