{
  "type": "Feature",
  "properties": {
    "date:inception_lower":"2012-11-01",
    "date:inception_upper":"2012-11-30",
    "iso:country":"GB",
    "wof:name":"CH2 3FF",
    "wof:placetype":"postalcode"
},
  "geometry": {"coordinates":[-2.875046,53.193194],"type":"Point"}
}