{
  "type": "Feature",
  "properties": {
    "iso:country":"GB",
    "wof:name":"CH2 3FF",
    "wof:placetype":"postalcode"
},
  "geometry": {"coordinates":[-2.8750465035305,53.19319426924422],"type":"Point"}
}