{
  "type": "Feature",
  "properties": {
    "iso:country":"GB",
    "wof:name":"BN10 8DU",
    "wof:placetype":"postalcode"
},
  "geometry": {"coordinates":[0.0025813786321,50.79711419361949],"type":"Point"}
}