{
  "type": "Feature",
  "properties": {
    "iso:country":"GB",
    "wof:name":"GL1 4QT",
    "wof:placetype":"postalcode"
},
  "geometry": {"coordinates":[-2.23748797839942,51.85224333088927],"type":"Point"}
}