{
  "type": "Feature",
  "properties": {
    "iso:country": "GB",
    "wof:name": "LA3 3FN",
    "wof:placetype": "postalcode"
  },
  "geometry": {"coordinates":[-2.897553,54.014582],"type":"Point"}
}
