{
  "type": "Feature",
  "properties": {
    "date:inception_lower": "2010-08-01",
    "date:inception_upper": "2010-08-01",
    "iso:country": "GB",
    "wof:name": "BL9 0JS",
    "wof:placetype": "postalcode"
  },
  "geometry": {"coordinates":[-2.291137,53.594455],"type":"Point"}
}
