{
  "type": "Feature",
  "properties": {
    "iso:country":"GB",
    "wof:name":"BL9 0JS",
    "wof:placetype":"postalcode"
},
  "geometry": {"coordinates":[-2.29113754608788,53.59445463553483],"type":"Point"}
}