{
  "type": "Feature",
  "properties": {
    "iso:country":"GB",
    "wof:name":"TR19 6QZ",
    "wof:placetype":"postalcode"
},
  "geometry": {"coordinates":[-5.53988163484401,50.08335713351524],"type":"Point"}
}