{
  "type": "Feature",
  "properties": {
    "iso:country":"GB",
    "wof:name":"NG5 1HW",
    "wof:placetype":"postalcode"
},
  "geometry": {"coordinates":[-1.17008250475174,52.98478061634371],"type":"Point"}
}