{
  "type": "Feature",
  "properties": {
    "date:inception_lower": "1980-01-01",
    "date:inception_upper": "1980-01-01",
    "iso:country": "GB",
    "wof:name": "NG5 1HW",
    "wof:placetype": "postalcode"
  },
  "geometry": {"coordinates":[-1.170063,52.984863],"type":"Point"}
}
