{
  "type": "Feature",
  "properties": {
    "iso:country": "GB",
    "wof:name": "NE61 3FP",
    "wof:placetype": "postalcode"
  },
  "geometry": {"coordinates":[-1.711568,55.180745],"type":"Point"}
}
