{
  "type": "Feature",
  "properties": {
    "date:inception_lower": "2018-03-01",
    "date:inception_upper": "2018-03-01",
    "iso:country": "GB",
    "wof:name": "NE61 3FP",
    "wof:placetype": "postalcode"
  },
  "geometry": {"coordinates":[-1.711787,55.180952],"type":"Point"}
}
