{
  "type": "Feature",
  "properties": {
    "iso:country":"GB",
    "wof:name":"GL16 8GA",
    "wof:placetype":"postalcode"
},
  "geometry": {"coordinates":[-2.62342554133722,51.7971445342055],"type":"Point"}
}