{
  "type": "Feature",
  "properties": {
    "date:inception_lower":"2015-10-01",
    "date:inception_upper":"2015-10-31",
    "iso:country":"GB",
    "wof:name":"GL16 8GA",
    "wof:placetype":"postalcode"
},
  "geometry": {"coordinates":[-2.623486,51.797176],"type":"Point"}
}