{
  "type": "Feature",
  "properties": {
    "iso:country":"GB",
    "wof:name":"PL9 9SR",
    "wof:placetype":"postalcode"
},
  "geometry": {"coordinates":[-4.11894100399001,50.35690190625486],"type":"Point"}
}