{
  "type": "Feature",
  "properties": {
    "iso:country": "GB",
    "wof:name": "KA3 6FL",
    "wof:placetype": "postalcode"
  },
  "geometry": {"coordinates":[-4.485124,55.634961],"type":"Point"}
}
