{
  "type": "Feature",
  "properties": {
    "date:inception_lower":"2002-06-01",
    "date:inception_upper":"2002-06-30",
    "iso:country":"GB",
    "wof:name":"KA3 6FL",
    "wof:placetype":"postalcode"
},
  "geometry": {"coordinates":[-4.485124,55.634961],"type":"Point"}
}