{
  "type": "Feature",
  "properties": {
    "date:inception_lower": "2015-06-01",
    "date:inception_upper": "2015-06-01",
    "iso:country": "GB",
    "wof:name": "DY12 1PQ",
    "wof:placetype": "postalcode"
  },
  "geometry": {"coordinates":[-2.318247,52.408593],"type":"Point"}
}
