{
  "type": "Feature",
  "properties": {
    "iso:country":"GB",
    "wof:name":"DY12 1PQ",
    "wof:placetype":"postalcode"
},
  "geometry": {"coordinates":[-2.31770253531395,52.40845966991144],"type":"Point"}
}