{
  "type": "Feature",
  "properties": {
    "date:inception_lower":"1980-01-01",
    "date:inception_upper":"1980-01-31",
    "iso:country":"GB",
    "wof:name":"BN11 3EN",
    "wof:placetype":"postalcode"
},
  "geometry": {"coordinates":[-0.365844,50.811365],"type":"Point"}
}