{
  "type": "Feature",
  "properties": {
    "iso:country":"GB",
    "wof:name":"WV15 5AF",
    "wof:placetype":"postalcode"
},
  "geometry": {"coordinates":[-2.41153568296027,52.53630498284495],"type":"Point"}
}