{
  "type": "Feature",
  "properties": {
    "iso:country":"GB",
    "wof:name":"EH10 5AA",
    "wof:placetype":"postalcode"
},
  "geometry": {"coordinates":[-3.21319438888258,55.93444658059011],"type":"Point"}
}