{
  "type": "Feature",
  "properties": {
    "iso:country":"GB",
    "wof:name":"BD13 1BS",
    "wof:placetype":"postalcode"
},
  "geometry": {"coordinates":[-1.83603287980278,53.76999316522873],"type":"Point"}
}