{
  "type": "Feature",
  "properties": {
    "iso:country": "GB",
    "wof:name": "RG40 5RT",
    "wof:placetype": "postalcode"
  },
  "geometry": {"coordinates":[-0.807638,51.439138],"type":"Point"}
}
