{
  "type": "Feature",
  "properties": {
    "iso:country": "GB",
    "wof:name": "PL27 7FE",
    "wof:placetype": "postalcode"
  },
  "geometry": {"coordinates":[-4.85353,50.515721],"type":"Point"}
}
