{
  "type": "Feature",
  "properties": {
    "iso:country":"GB",
    "wof:name":"PL27 7FE",
    "wof:placetype":"postalcode"
},
  "geometry": {"coordinates":[-4.85368019725541,50.51538405758811],"type":"Point"}
}