{
  "type": "Feature",
  "properties": {
    "date:inception_lower":"2008-04-01",
    "date:inception_upper":"2008-04-30",
    "iso:country":"GB",
    "wof:name":"PL27 7FE",
    "wof:placetype":"postalcode"
},
  "geometry": {"coordinates":[-4.85353,50.515721],"type":"Point"}
}