{
  "type": "Feature",
  "properties": {
    "iso:country": "GB",
    "wof:name": "PH1 4NQ",
    "wof:placetype": "postalcode"
  },
  "geometry": {"coordinates":[-3.449667,56.481325],"type":"Point"}
}
