{
  "type": "Feature",
  "properties": {
    "iso:country": "GB",
    "wof:name": "HP20 2XB",
    "wof:placetype": "postalcode"
  },
  "geometry": {"coordinates":[-0.797188,51.827212],"type":"Point"}
}
