{
  "type": "Feature",
  "properties": {
    "iso:country":"GB",
    "wof:name":"PL3 5NZ",
    "wof:placetype":"postalcode"
},
  "geometry": {"coordinates":[-4.13674456871398,50.39455921647968],"type":"Point"}
}