{
  "type": "Feature",
  "properties": {
    "date:inception_lower":"1980-01-01",
    "date:inception_upper":"1980-01-31",
    "iso:country":"GB",
    "wof:name":"SY17 5JQ",
    "wof:placetype":"postalcode"
},
  "geometry": {"coordinates":[-3.428839,52.5287],"type":"Point"}
}