{
  "type": "Feature",
  "properties": {
    "iso:country":"GB",
    "wof:name":"M2 1EN",
    "wof:placetype":"postalcode"
},
  "geometry": {"coordinates":[-2.24182556800811,53.4812481569381],"type":"Point"}
}