{
  "type": "Feature",
  "properties": {
    "iso:country":"GB",
    "wof:name":"M25 3DP",
    "wof:placetype":"postalcode"
},
  "geometry": {"coordinates":[-2.28442137952995,53.53707127244612],"type":"Point"}
}