{
  "type": "Feature",
  "properties": {
    "date:inception_lower":"1992-01-01",
    "date:inception_upper":"1992-01-31",
    "iso:country":"GB",
    "wof:name":"PE13 3AL",
    "wof:placetype":"postalcode"
},
  "geometry": {"coordinates":[0.161367,52.668489],"type":"Point"}
}