{
  "type": "Feature",
  "properties": {
    "date:inception_lower": "1994-05-01",
    "date:inception_upper": "1994-05-01",
    "iso:country": "GB",
    "wof:name": "WA16 8PU",
    "wof:placetype": "postalcode"
  },
  "geometry": {"coordinates":[-2.363991,53.298782],"type":"Point"}
}
