{
  "type": "Feature",
  "properties": {
    "date:inception_lower":"1994-05-01",
    "date:inception_upper":"1994-05-31",
    "iso:country":"GB",
    "wof:name":"WA16 8PU",
    "wof:placetype":"postalcode"
},
  "geometry": {"coordinates":[-2.363962,53.29873],"type":"Point"}
}