{
  "type": "Feature",
  "properties": {
    "iso:country": "GB",
    "wof:name": "LS28 8LX",
    "wof:placetype": "postalcode"
  },
  "geometry": {"coordinates":[-1.668064,53.787631],"type":"Point"}
}
