{
  "type": "Feature",
  "properties": {
    "iso:country":"GB",
    "wof:name":"SA4 6TU",
    "wof:placetype":"postalcode"
},
  "geometry": {"coordinates":[-4.07202375482573,51.66317281178537],"type":"Point"}
}