{
  "type": "Feature",
  "properties": {
    "date:inception_lower":"1993-01-01",
    "date:inception_upper":"1993-01-31",
    "iso:country":"GB",
    "wof:name":"SA4 6TU",
    "wof:placetype":"postalcode"
},
  "geometry": {"coordinates":[-4.072998,51.663485],"type":"Point"}
}