{
  "type": "Feature",
  "properties": {
    "iso:country":"GB",
    "wof:name":"AB34 4TB",
    "wof:placetype":"postalcode"
},
  "geometry": {"coordinates":[-2.84349574938237,57.13840705281409],"type":"Point"}
}