{
  "type": "Feature",
  "properties": {
    "date:inception_lower":"1990-08-01",
    "date:inception_upper":"1990-08-31",
    "iso:country":"GB",
    "wof:name":"AB34 4TB",
    "wof:placetype":"postalcode"
},
  "geometry": {"coordinates":[-2.843496,57.138407],"type":"Point"}
}