{
  "type": "Feature",
  "properties": {
    "date:inception_lower": "1990-08-01",
    "date:inception_upper": "1990-08-01",
    "iso:country": "GB",
    "wof:name": "AB34 4TB",
    "wof:placetype": "postalcode"
  },
  "geometry": {"coordinates":[-2.844157,57.139045],"type":"Point"}
}
