{
  "type": "Feature",
  "properties": {
    "date:inception_lower": "2019-08-01",
    "date:inception_upper": "2019-08-01",
    "iso:country": "GB",
    "wof:name": "CR5 3HZ",
    "wof:placetype": "postalcode"
  },
  "geometry": {"coordinates":[-0.149723,51.312776],"type":"Point"}
}
