{
  "type": "Feature",
  "properties": {
    "iso:country": "GB",
    "wof:name": "CR5 3HZ",
    "wof:placetype": "postalcode"
  },
  "geometry": {"coordinates":[-0.149723,51.312776],"type":"Point"}
}
