{
  "type": "Feature",
  "properties": {
    "iso:country":"GB",
    "wof:name":"L21 8PD",
    "wof:placetype":"postalcode"
},
  "geometry": {"coordinates":[-2.99178975407206,53.47058027427595],"type":"Point"}
}