{
  "type": "Feature",
  "properties": {
    "iso:country": "GB",
    "wof:name": "G84 7QN",
    "wof:placetype": "postalcode"
  },
  "geometry": {"coordinates":[-4.729563,56.004853],"type":"Point"}
}
