{
  "type": "Feature",
  "properties": {
    "iso:country": "GB",
    "wof:name": "S21 1BG",
    "wof:placetype": "postalcode"
  },
  "geometry": {"coordinates":[-1.326679,53.324201],"type":"Point"}
}
