{
  "type": "Feature",
  "properties": {
    "iso:country":"GB",
    "wof:name":"S21 1BG",
    "wof:placetype":"postalcode"
},
  "geometry": {"coordinates":[-1.32667929198494,53.32420093905981],"type":"Point"}
}