{
  "type": "Feature",
  "properties": {
    "date:inception_lower": "2021-02-01",
    "date:inception_upper": "2021-02-01",
    "iso:country": "GB",
    "wof:name": "KA30 9BF",
    "wof:placetype": "postalcode"
  },
  "geometry": {"coordinates":[-4.859232,55.795134],"type":"Point"}
}
