{
  "type": "Feature",
  "properties": {
    "iso:country":"GB",
    "wof:name":"PA3 4JB",
    "wof:placetype":"postalcode"
},
  "geometry": {"coordinates":[-4.39234005434504,55.85737027231155],"type":"Point"}
}