{
  "type": "Feature",
  "properties": {
    "date:inception_lower": "1980-01-01",
    "date:inception_upper": "1980-01-01",
    "iso:country": "GB",
    "wof:name": "PA3 4JB",
    "wof:placetype": "postalcode"
  },
  "geometry": {"coordinates":[-4.392228,55.85734],"type":"Point"}
}
