{
  "type": "Feature",
  "properties": {
    "date:inception_lower": "2000-12-01",
    "date:inception_upper": "2000-12-01",
    "iso:country": "GB",
    "wof:name": "IP8 3TD",
    "wof:placetype": "postalcode"
  },
  "geometry": {"coordinates":[1.120001,52.031478],"type":"Point"}
}
