{
  "type": "Feature",
  "properties": {
    "iso:country": "GB",
    "wof:name": "IP8 3TD",
    "wof:placetype": "postalcode"
  },
  "geometry": {"coordinates":[1.119799,52.031504],"type":"Point"}
}
