{
  "type": "Feature",
  "properties": {
    "date:inception_lower": "1996-12-01",
    "date:inception_upper": "1996-12-01",
    "iso:country": "GB",
    "wof:name": "HA8 5TX",
    "wof:placetype": "postalcode"
  },
  "geometry": {"coordinates":[-0.275706,51.607224],"type":"Point"}
}
