{
  "type": "Feature",
  "properties": {
    "iso:country":"GB",
    "wof:name":"CW8 2XJ",
    "wof:placetype":"postalcode"
},
  "geometry": {"coordinates":[-2.61916838507402,53.2415509657414],"type":"Point"}
}