{
  "type": "Feature",
  "properties": {
    "iso:country":"GB",
    "wof:name":"GL51 0FH",
    "wof:placetype":"postalcode"
},
  "geometry": {"coordinates":[-2.12490357195719,51.89608574555974],"type":"Point"}
}