{
  "type": "Feature",
  "properties": {
    "iso:country":"GB",
    "wof:name":"EN3 5PR",
    "wof:placetype":"postalcode"
},
  "geometry": {"coordinates":[-0.04398356224454,51.66441647744141],"type":"Point"}
}