{
  "type": "Feature",
  "properties": {
    "date:inception_lower":"1980-01-01",
    "date:inception_upper":"1980-01-31",
    "iso:country":"GB",
    "wof:name":"EN3 5PR",
    "wof:placetype":"postalcode"
},
  "geometry": {"coordinates":[-0.043984,51.664416],"type":"Point"}
}