{
  "type": "Feature",
  "properties": {
    "date:inception_lower": "1980-01-01",
    "date:inception_upper": "1980-01-01",
    "iso:country": "GB",
    "wof:name": "NR34 7PL",
    "wof:placetype": "postalcode"
  },
  "geometry": {"coordinates":[1.635222,52.44029],"type":"Point"}
}
