{
  "type": "Feature",
  "properties": {
    "iso:country": "GB",
    "wof:name": "GL4 3AY",
    "wof:placetype": "postalcode"
  },
  "geometry": {"coordinates":[-2.212217,51.85952],"type":"Point"}
}
