{
  "type": "Feature",
  "properties": {
    "date:inception_lower": "1980-01-01",
    "date:inception_upper": "1980-01-01",
    "iso:country": "GB",
    "wof:name": "WN7 4QZ",
    "wof:placetype": "postalcode"
  },
  "geometry": {"coordinates":[-2.544081,53.494941],"type":"Point"}
}
