{
  "type": "Feature",
  "properties": {
    "iso:country":"GB",
    "wof:name":"WN7 4QZ",
    "wof:placetype":"postalcode"
},
  "geometry": {"coordinates":[-2.54408063608014,53.49494099401924],"type":"Point"}
}