{
  "type": "Feature",
  "properties": {
    "date:inception_lower": "1983-07-01",
    "date:inception_upper": "1983-07-01",
    "iso:country": "GB",
    "wof:name": "CO11 1JJ",
    "wof:placetype": "postalcode"
  },
  "geometry": {"coordinates":[1.085086,51.941783],"type":"Point"}
}
