{
  "type": "Feature",
  "properties": {
    "iso:country": "GB",
    "wof:name": "AB24 3NW",
    "wof:placetype": "postalcode"
  },
  "geometry": {"coordinates":[-2.109606,57.159692],"type":"Point"}
}
