{
  "type": "Feature",
  "properties": {
    "iso:country":"GB",
    "wof:name":"EN3 4NY",
    "wof:placetype":"postalcode"
},
  "geometry": {"coordinates":[-0.0440043726424,51.64009229981199],"type":"Point"}
}