{
  "type": "Feature",
  "properties": {
    "iso:country":"GB",
    "wof:name":"WS3 1RU",
    "wof:placetype":"postalcode"
},
  "geometry": {"coordinates":[-1.97068861366815,52.60810015236885],"type":"Point"}
}