{
  "type": "Feature",
  "properties": {
    "iso:country":"GB",
    "wof:name":"CF3 0BE",
    "wof:placetype":"postalcode"
},
  "geometry": {"coordinates":[-3.10747991746159,51.52184523348656],"type":"Point"}
}