{
  "type": "Feature",
  "properties": {
    "iso:country": "GB",
    "wof:name": "BS40 8TQ",
    "wof:placetype": "postalcode"
  },
  "geometry": {"coordinates":[-2.592615,51.34934],"type":"Point"}
}
