{
  "type": "Feature",
  "properties": {
    "iso:country":"GB",
    "wof:name":"BS40 8TQ",
    "wof:placetype":"postalcode"
},
  "geometry": {"coordinates":[-2.59261507204882,51.34934039944872],"type":"Point"}
}