{
  "type": "Feature",
  "properties": {
    "date:inception_lower": "1997-12-01",
    "date:inception_upper": "1997-12-01",
    "iso:country": "GB",
    "wof:name": "BS40 8TQ",
    "wof:placetype": "postalcode"
  },
  "geometry": {"coordinates":[-2.592615,51.34934],"type":"Point"}
}
