{
  "type": "Feature",
  "properties": {
    "iso:country": "GB",
    "wof:name": "SL6 2AZ",
    "wof:placetype": "postalcode"
  },
  "geometry": {"coordinates":[-0.685151,51.496879],"type":"Point"}
}
