{
  "type": "Feature",
  "properties": {
    "iso:country":"GB",
    "wof:name":"SL6 2AZ",
    "wof:placetype":"postalcode"
},
  "geometry": {"coordinates":[-0.68515130758188,51.49687895900593],"type":"Point"}
}