{
  "type": "Feature",
  "properties": {
    "iso:country":"GB",
    "wof:name":"GL5 3NZ",
    "wof:placetype":"postalcode"
},
  "geometry": {"coordinates":[-2.23301879744613,51.73188035416347],"type":"Point"}
}