{
  "type": "Feature",
  "properties": {
    "iso:country":"GB",
    "wof:name":"SY18 6QT",
    "wof:placetype":"postalcode"
},
  "geometry": {"coordinates":[-3.5008758834442,52.4056770699773],"type":"Point"}
}