{
  "type": "Feature",
  "properties": {
    "iso:country":"GB",
    "wof:name":"EX4 6DB",
    "wof:placetype":"postalcode"
},
  "geometry": {"coordinates":[-3.52528309904743,50.73165053867784],"type":"Point"}
}