{
  "type": "Feature",
  "properties": {
    "iso:country":"GB",
    "wof:name":"CB23 7BF",
    "wof:placetype":"postalcode"
},
  "geometry": {"coordinates":[0.0254073501661,52.19216713839569],"type":"Point"}
}