{
  "type": "Feature",
  "properties": {
    "iso:country": "GB",
    "wof:name": "CB23 7BF",
    "wof:placetype": "postalcode"
  },
  "geometry": {"coordinates":[0.025407,52.192167],"type":"Point"}
}
