{
  "type": "Feature",
  "properties": {
    "date:inception_lower":"2012-06-01",
    "date:inception_upper":"2012-06-30",
    "iso:country":"GB",
    "wof:name":"CB23 7BF",
    "wof:placetype":"postalcode"
},
  "geometry": {"coordinates":[0.025407,52.192167],"type":"Point"}
}