{
  "type": "Feature",
  "properties": {
    "date:inception_lower":"1980-01-01",
    "date:inception_upper":"1980-01-31",
    "iso:country":"GB",
    "wof:name":"LS14 1DY",
    "wof:placetype":"postalcode"
},
  "geometry": {"coordinates":[-1.466338,53.839699],"type":"Point"}
}