{
  "type": "Feature",
  "properties": {
    "date:inception_lower": "1980-01-01",
    "date:inception_upper": "1980-01-01",
    "iso:country": "GB",
    "wof:name": "PO22 7JG",
    "wof:placetype": "postalcode"
  },
  "geometry": {"coordinates":[-0.647663,50.789009],"type":"Point"}
}
