{
  "type": "Feature",
  "properties": {
    "iso:country":"GB",
    "wof:name":"PO22 7JG",
    "wof:placetype":"postalcode"
},
  "geometry": {"coordinates":[-0.64766348623041,50.78900912723927],"type":"Point"}
}