{
  "type": "Feature",
  "properties": {
    "iso:country":"GB",
    "wof:name":"RG2 8QA",
    "wof:placetype":"postalcode"
},
  "geometry": {"coordinates":[-0.95773417320775,51.41301688692554],"type":"Point"}
}