{
  "type": "Feature",
  "properties": {
    "iso:country": "GB",
    "wof:name": "RG2 8QA",
    "wof:placetype": "postalcode"
  },
  "geometry": {"coordinates":[-0.957501,51.41289],"type":"Point"}
}
