{
  "type": "Feature",
  "properties": {
    "date:inception_lower":"1980-01-01",
    "date:inception_upper":"1980-01-31",
    "iso:country":"GB",
    "wof:name":"RG2 8QA",
    "wof:placetype":"postalcode"
},
  "geometry": {"coordinates":[-0.957501,51.41289],"type":"Point"}
}