{
  "type": "Feature",
  "properties": {
    "iso:country":"GB",
    "wof:name":"LA9 5PB",
    "wof:placetype":"postalcode"
},
  "geometry": {"coordinates":[-2.75959169879632,54.34040954758058],"type":"Point"}
}