{
  "type": "Feature",
  "properties": {
    "iso:country": "GB",
    "wof:name": "LA9 5PB",
    "wof:placetype": "postalcode"
  },
  "geometry": {"coordinates":[-2.759592,54.34041],"type":"Point"}
}
