{
  "type": "Feature",
  "properties": {
    "date:inception_lower":"1993-08-01",
    "date:inception_upper":"1993-08-31",
    "iso:country":"GB",
    "wof:name":"OL11 2PD",
    "wof:placetype":"postalcode"
},
  "geometry": {"coordinates":[-2.168425,53.602277],"type":"Point"}
}