{
  "type": "Feature",
  "properties": {
    "iso:country":"GB",
    "wof:name":"OL11 2PD",
    "wof:placetype":"postalcode"
},
  "geometry": {"coordinates":[-2.16842517586207,53.60227663640231],"type":"Point"}
}