{
  "type": "Feature",
  "properties": {
    "iso:country": "GB",
    "wof:name": "HU17 8GP",
    "wof:placetype": "postalcode"
  },
  "geometry": {"coordinates":[-0.495097,53.820547],"type":"Point"}
}
