{
  "type": "Feature",
  "properties": {
    "date:inception_lower": "2019-12-01",
    "date:inception_upper": "2019-12-01",
    "iso:country": "GB",
    "wof:name": "HU17 8GP",
    "wof:placetype": "postalcode"
  },
  "geometry": {"coordinates":[-0.495126,53.820593],"type":"Point"}
}
