{
  "type": "Feature",
  "properties": {
    "iso:country": "GB",
    "wof:name": "CA5 6HB",
    "wof:placetype": "postalcode"
  },
  "geometry": {"coordinates":[-3.058363,54.899339],"type":"Point"}
}
