{
  "type": "Feature",
  "properties": {
    "date:inception_lower": "1995-01-01",
    "date:inception_upper": "1995-01-01",
    "iso:country": "GB",
    "wof:name": "YO21 3AX",
    "wof:placetype": "postalcode"
  },
  "geometry": {"coordinates":[-0.616278,54.486569],"type":"Point"}
}
