{
  "type": "Feature",
  "properties": {
    "iso:country":"GB",
    "wof:name":"KW1 5QW",
    "wof:placetype":"postalcode"
},
  "geometry": {"coordinates":[-3.08804773035105,58.43582192215963],"type":"Point"}
}