{
  "type": "Feature",
  "properties": {
    "iso:country": "GB",
    "wof:name": "KW1 5QW",
    "wof:placetype": "postalcode"
  },
  "geometry": {"coordinates":[-3.088048,58.435822],"type":"Point"}
}
