{
  "type": "Feature",
  "properties": {
    "date:inception_lower": "1980-01-01",
    "date:inception_upper": "1980-01-01",
    "iso:country": "GB",
    "wof:name": "KA3 5JW",
    "wof:placetype": "postalcode"
  },
  "geometry": {"coordinates":[-4.498348,55.68891],"type":"Point"}
}
