{
  "type": "Feature",
  "properties": {
    "iso:country":"GB",
    "wof:name":"KA3 5JW",
    "wof:placetype":"postalcode"
},
  "geometry": {"coordinates":[-4.49834809415466,55.68890997317314],"type":"Point"}
}