{
  "type": "Feature",
  "properties": {
    "date:inception_lower": "2019-06-01",
    "date:inception_upper": "2019-06-01",
    "iso:country": "GB",
    "wof:name": "DE1 2RG",
    "wof:placetype": "postalcode"
  },
  "geometry": {"coordinates":[-1.472635,52.914961],"type":"Point"}
}
