{
  "type": "Feature",
  "properties": {
    "iso:country": "GB",
    "wof:name": "L2 9UW",
    "wof:placetype": "postalcode"
  },
  "geometry": {"coordinates":[-2.98892,53.405462],"type":"Point"}
}
