{
  "type": "Feature",
  "properties": {
    "iso:country":"GB",
    "wof:name":"L2 9UW",
    "wof:placetype":"postalcode"
},
  "geometry": {"coordinates":[-2.98892029432366,53.40546159766393],"type":"Point"}
}