{
  "type": "Feature",
  "properties": {
    "iso:country": "GB",
    "wof:name": "B77 5AN",
    "wof:placetype": "postalcode"
  },
  "geometry": {"coordinates":[-1.658708,52.607694],"type":"Point"}
}
