{
  "type": "Feature",
  "properties": {
    "date:inception_lower":"2008-05-01",
    "date:inception_upper":"2008-05-31",
    "iso:country":"GB",
    "wof:name":"B77 5AN",
    "wof:placetype":"postalcode"
},
  "geometry": {"coordinates":[-1.658708,52.607694],"type":"Point"}
}