{
  "type": "Feature",
  "properties": {
    "iso:country": "GB",
    "wof:name": "EH49 7LW",
    "wof:placetype": "postalcode"
  },
  "geometry": {"coordinates":[-3.574777,55.983515],"type":"Point"}
}
