{
  "type": "Feature",
  "properties": {
    "iso:country": "GB",
    "wof:name": "NE3 2SG",
    "wof:placetype": "postalcode"
  },
  "geometry": {"coordinates":[-1.6726,55.013358],"type":"Point"}
}
