{
  "type": "Feature",
  "properties": {
    "date:inception_lower":"1983-03-01",
    "date:inception_upper":"1983-03-31",
    "iso:country":"GB",
    "wof:name":"NE3 2SG",
    "wof:placetype":"postalcode"
},
  "geometry": {"coordinates":[-1.6726,55.013358],"type":"Point"}
}