{
  "type": "Feature",
  "properties": {
    "iso:country":"GB",
    "wof:name":"DA16 1QL",
    "wof:placetype":"postalcode"
},
  "geometry": {"coordinates":[0.10921230840846,51.46370842880832],"type":"Point"}
}