{
  "type": "Feature",
  "properties": {
    "date:inception_lower":"1980-01-01",
    "date:inception_upper":"1980-01-31",
    "iso:country":"GB",
    "wof:name":"DA16 1QL",
    "wof:placetype":"postalcode"
},
  "geometry": {"coordinates":[0.109212,51.463708],"type":"Point"}
}