{
  "type": "Feature",
  "properties": {
    "iso:country":"GB",
    "wof:name":"RG26 5XB",
    "wof:placetype":"postalcode"
},
  "geometry": {"coordinates":[-1.04730083826289,51.32309523200806],"type":"Point"}
}