{
  "type": "Feature",
  "properties": {
    "iso:country": "GB",
    "wof:name": "S35 2PS",
    "wof:placetype": "postalcode"
  },
  "geometry": {"coordinates":[-1.468278,53.478047],"type":"Point"}
}
