{
  "type": "Feature",
  "properties": {
    "iso:country":"GB",
    "wof:name":"B36 8DY",
    "wof:placetype":"postalcode"
},
  "geometry": {"coordinates":[-1.81284693462631,52.49627526121387],"type":"Point"}
}