{
  "type": "Feature",
  "properties": {
    "iso:country":"GB",
    "wof:name":"S44 6UL",
    "wof:placetype":"postalcode"
},
  "geometry": {"coordinates":[-1.2872546758326,53.20781672006267],"type":"Point"}
}