{
  "type": "Feature",
  "properties": {
    "date:inception_lower":"1980-01-01",
    "date:inception_upper":"1980-01-31",
    "iso:country":"GB",
    "wof:name":"S44 6UL",
    "wof:placetype":"postalcode"
},
  "geometry": {"coordinates":[-1.287268,53.207835],"type":"Point"}
}