{
  "type": "Feature",
  "properties": {
    "iso:country":"GB",
    "wof:name":"TQ1 3BS",
    "wof:placetype":"postalcode"
},
  "geometry": {"coordinates":[-3.52889277665227,50.47126013935191],"type":"Point"}
}