{
  "type": "Feature",
  "properties": {
    "date:inception_lower": "1987-10-01",
    "date:inception_upper": "1987-10-01",
    "iso:country": "GB",
    "wof:name": "LA9 6JQ",
    "wof:placetype": "postalcode"
  },
  "geometry": {"coordinates":[-2.731321,54.330051],"type":"Point"}
}
