{
  "type": "Feature",
  "properties": {
    "iso:country":"GB",
    "wof:name":"LA9 6JQ",
    "wof:placetype":"postalcode"
},
  "geometry": {"coordinates":[-2.73132142402232,54.33005102586242],"type":"Point"}
}