{
  "type": "Feature",
  "properties": {
    "iso:country":"GB",
    "wof:name":"WS11 9SD",
    "wof:placetype":"postalcode"
},
  "geometry": {"coordinates":[-1.97166432681317,52.67564907355033],"type":"Point"}
}