{
  "type": "Feature",
  "properties": {
    "date:inception_lower": "2024-04-01",
    "date:inception_upper": "2024-04-01",
    "iso:country": "GB",
    "wof:name": "OL15 8FJ",
    "wof:placetype": "postalcode"
  },
  "geometry": {"coordinates":[-2.115784,53.644043],"type":"Point"}
}
