{
  "type": "Feature",
  "properties": {
    "iso:country":"GB",
    "wof:name":"DE73 5SL",
    "wof:placetype":"postalcode"
},
  "geometry": {"coordinates":[-1.44419271686093,52.87291333349315],"type":"Point"}
}