{
  "type": "Feature",
  "properties": {
    "iso:country":"GB",
    "wof:name":"WA10 3UF",
    "wof:placetype":"postalcode"
},
  "geometry": {"coordinates":[-2.7475167954516,53.45053401009681],"type":"Point"}
}