{
  "type": "Feature",
  "properties": {
    "iso:country":"GB",
    "wof:name":"SE11 4BS",
    "wof:placetype":"postalcode"
},
  "geometry": {"coordinates":[-0.10445590204159,51.49271700780102],"type":"Point"}
}