{
  "type": "Feature",
  "properties": {
    "iso:country":"GB",
    "wof:name":"SA19 9BE",
    "wof:placetype":"postalcode"
},
  "geometry": {"coordinates":[-3.88450546854419,51.94924310711254],"type":"Point"}
}