{
  "type": "Feature",
  "properties": {
    "iso:country": "GB",
    "wof:name": "CH41 0BL",
    "wof:placetype": "postalcode"
  },
  "geometry": {"coordinates":[-3.052587,53.397241],"type":"Point"}
}
