{
  "type": "Feature",
  "properties": {
    "date:inception_lower": "1980-01-01",
    "date:inception_upper": "1980-01-01",
    "iso:country": "GB",
    "wof:name": "LL15 2SE",
    "wof:placetype": "postalcode"
  },
  "geometry": {"coordinates":[-3.295437,53.082862],"type":"Point"}
}
