{
  "type": "Feature",
  "properties": {
    "iso:country": "GB",
    "wof:name": "RG42 5LD",
    "wof:placetype": "postalcode"
  },
  "geometry": {"coordinates":[-0.787663,51.434437],"type":"Point"}
}
