{
  "type": "Feature",
  "properties": {
    "iso:country":"GB",
    "wof:name":"SA2 8DY",
    "wof:placetype":"postalcode"
},
  "geometry": {"coordinates":[-3.99804393227244,51.60591403120129],"type":"Point"}
}