{
  "type": "Feature",
  "properties": {
    "date:inception_lower": "2023-11-01",
    "date:inception_upper": "2023-11-01",
    "iso:country": "GB",
    "wof:name": "PE26 2AF",
    "wof:placetype": "postalcode"
  },
  "geometry": {"coordinates":[-0.111617,52.45449],"type":"Point"}
}
