{
  "type": "Feature",
  "properties": {
    "iso:country":"GB",
    "wof:name":"G32 8YG",
    "wof:placetype":"postalcode"
},
  "geometry": {"coordinates":[-4.1586520614446,55.83622333760454],"type":"Point"}
}