{
  "type": "Feature",
  "properties": {
    "date:inception_lower": "1980-01-01",
    "date:inception_upper": "1980-01-01",
    "iso:country": "GB",
    "wof:name": "G32 8YG",
    "wof:placetype": "postalcode"
  },
  "geometry": {"coordinates":[-4.159215,55.835948],"type":"Point"}
}
