{
  "type": "Feature",
  "properties": {
    "iso:country":"GB",
    "wof:name":"WF9 3DT",
    "wof:placetype":"postalcode"
},
  "geometry": {"coordinates":[-1.33016689936166,53.58909807210604],"type":"Point"}
}