{
  "type": "Feature",
  "properties": {
    "date:inception_lower": "2020-04-01",
    "date:inception_upper": "2020-04-01",
    "iso:country": "GB",
    "wof:name": "G12 0AW",
    "wof:placetype": "postalcode"
  },
  "geometry": {"coordinates":[-4.315059,55.889248],"type":"Point"}
}
