{
  "type": "Feature",
  "properties": {
    "iso:country": "GB",
    "wof:name": "G12 0AW",
    "wof:placetype": "postalcode"
  },
  "geometry": {"coordinates":[-4.315059,55.889248],"type":"Point"}
}
