{
  "type": "Feature",
  "properties": {
    "iso:country":"GB",
    "wof:name":"CF14 5AX",
    "wof:placetype":"postalcode"
},
  "geometry": {"coordinates":[-3.18416211595125,51.53467373732912],"type":"Point"}
}