{
  "type": "Feature",
  "properties": {
    "iso:country": "GB",
    "wof:name": "CF14 5AX",
    "wof:placetype": "postalcode"
  },
  "geometry": {"coordinates":[-3.184162,51.534674],"type":"Point"}
}
