{
  "type": "Feature",
  "properties": {
    "iso:country": "GB",
    "wof:name": "SO45 6AY",
    "wof:placetype": "postalcode"
  },
  "geometry": {"coordinates":[-1.40572,50.870304],"type":"Point"}
}
