{
  "type": "Feature",
  "properties": {
    "iso:country":"GB",
    "wof:name":"SO45 6AY",
    "wof:placetype":"postalcode"
},
  "geometry": {"coordinates":[-1.40571979530935,50.87030384186784],"type":"Point"}
}