{
  "type": "Feature",
  "properties": {
    "iso:country": "GB",
    "wof:name": "SR4 8DS",
    "wof:placetype": "postalcode"
  },
  "geometry": {"coordinates":[-1.437973,54.90143],"type":"Point"}
}
