{
  "type": "Feature",
  "properties": {
    "iso:country":"GB",
    "wof:name":"SR4 8DS",
    "wof:placetype":"postalcode"
},
  "geometry": {"coordinates":[-1.43816110340541,54.90138547556528],"type":"Point"}
}