{
  "type": "Feature",
  "properties": {
    "iso:country": "GB",
    "wof:name": "TR20 9AR",
    "wof:placetype": "postalcode"
  },
  "geometry": {"coordinates":[-5.403318,50.110315],"type":"Point"}
}
