{
  "type": "Feature",
  "properties": {
    "iso:country":"GB",
    "wof:name":"TR20 9AR",
    "wof:placetype":"postalcode"
},
  "geometry": {"coordinates":[-5.40331822804929,50.11031492255559],"type":"Point"}
}