{
  "type": "Feature",
  "properties": {
    "iso:country":"GB",
    "wof:name":"ME1 2UH",
    "wof:placetype":"postalcode"
},
  "geometry": {"coordinates":[0.50205946294865,51.36103644046494],"type":"Point"}
}