{
  "type": "Feature",
  "properties": {
    "iso:country":"GB",
    "wof:name":"DL1 4XW",
    "wof:placetype":"postalcode"
},
  "geometry": {"coordinates":[-1.50926721401668,54.52098997239622],"type":"Point"}
}