{
  "type": "Feature",
  "properties": {
    "date:inception_lower": "1980-01-01",
    "date:inception_upper": "1980-01-01",
    "iso:country": "GB",
    "wof:name": "EX31 2LD",
    "wof:placetype": "postalcode"
  },
  "geometry": {"coordinates":[-4.089183,51.073631],"type":"Point"}
}
