{
  "type": "Feature",
  "properties": {
    "date:inception_lower": "2015-06-01",
    "date:inception_upper": "2015-06-01",
    "iso:country": "GB",
    "wof:name": "NE25 9ZE",
    "wof:placetype": "postalcode"
  },
  "geometry": {"coordinates":[-1.467388,55.050922],"type":"Point"}
}
