{
  "type": "Feature",
  "properties": {
    "iso:country":"GB",
    "wof:name":"NE25 9ZE",
    "wof:placetype":"postalcode"
},
  "geometry": {"coordinates":[-1.46731456777148,55.05076153760911],"type":"Point"}
}