{
  "type": "Feature",
  "properties": {
    "iso:country":"GB",
    "wof:name":"HU6 7QH",
    "wof:placetype":"postalcode"
},
  "geometry": {"coordinates":[-0.33419202071777,53.77004924630263],"type":"Point"}
}