{
  "type": "Feature",
  "properties": {
    "date:inception_lower":"1993-01-01",
    "date:inception_upper":"1993-01-31",
    "iso:country":"GB",
    "wof:name":"SY8 2QD",
    "wof:placetype":"postalcode"
},
  "geometry": {"coordinates":[-2.721531,52.376495],"type":"Point"}
}