{
  "type": "Feature",
  "properties": {
    "iso:country": "GB",
    "wof:name": "SY8 2QD",
    "wof:placetype": "postalcode"
  },
  "geometry": {"coordinates":[-2.721531,52.376495],"type":"Point"}
}
