{
  "type": "Feature",
  "properties": {
    "iso:country":"GB",
    "wof:name":"B14 6EN",
    "wof:placetype":"postalcode"
},
  "geometry": {"coordinates":[-1.89198242497491,52.42050721449056],"type":"Point"}
}