{
  "type": "Feature",
  "properties": {
    "date:inception_lower": "1980-01-01",
    "date:inception_upper": "1980-01-01",
    "iso:country": "GB",
    "wof:name": "B14 6EN",
    "wof:placetype": "postalcode"
  },
  "geometry": {"coordinates":[-1.891982,52.420507],"type":"Point"}
}
