{
  "type": "Feature",
  "properties": {
    "iso:country":"GB",
    "wof:name":"B91 1DD",
    "wof:placetype":"postalcode"
},
  "geometry": {"coordinates":[-1.79922413477616,52.42779411648477],"type":"Point"}
}