{
  "type": "Feature",
  "properties": {
    "iso:country":"GB",
    "wof:name":"B24 0ED",
    "wof:placetype":"postalcode"
},
  "geometry": {"coordinates":[-1.82380263380037,52.53025596638921],"type":"Point"}
}