{
  "type": "Feature",
  "properties": {
    "iso:country":"GB",
    "wof:name":"LD2 3RF",
    "wof:placetype":"postalcode"
},
  "geometry": {"coordinates":[-3.42162260548229,52.16887337445506],"type":"Point"}
}