{
  "type": "Feature",
  "properties": {
    "iso:country":"GB",
    "wof:name":"NG23 6TG",
    "wof:placetype":"postalcode"
},
  "geometry": {"coordinates":[-0.86572299843192,53.21627282619156],"type":"Point"}
}