{
  "type": "Feature",
  "properties": {
    "iso:country":"GB",
    "wof:name":"TA21 0PR",
    "wof:placetype":"postalcode"
},
  "geometry": {"coordinates":[-3.34371025333161,50.95961768265345],"type":"Point"}
}