{
  "type": "Feature",
  "properties": {
    "date:inception_lower": "1980-01-01",
    "date:inception_upper": "1980-01-01",
    "iso:country": "GB",
    "wof:name": "TA21 0PR",
    "wof:placetype": "postalcode"
  },
  "geometry": {"coordinates":[-3.34371,50.959618],"type":"Point"}
}
