{
  "type": "Feature",
  "properties": {
    "iso:country": "GB",
    "wof:name": "TA21 0PR",
    "wof:placetype": "postalcode"
  },
  "geometry": {"coordinates":[-3.34371,50.959618],"type":"Point"}
}
