{
  "type": "Feature",
  "properties": {
    "iso:country":"GB",
    "wof:name":"NG1 6BF",
    "wof:placetype":"postalcode"
},
  "geometry": {"coordinates":[-1.15135023555793,52.95175590778333],"type":"Point"}
}