{
  "type": "Feature",
  "properties": {
    "date:inception_lower": "2014-10-01",
    "date:inception_upper": "2014-10-01",
    "iso:country": "GB",
    "wof:name": "NG1 6BF",
    "wof:placetype": "postalcode"
  },
  "geometry": {"coordinates":[-1.15135,52.951756],"type":"Point"}
}
