{
  "type": "Feature",
  "properties": {
    "iso:country":"GB",
    "wof:name":"SE3 8NW",
    "wof:placetype":"postalcode"
},
  "geometry": {"coordinates":[0.0461137602516,51.46763247787333],"type":"Point"}
}