{
  "type": "Feature",
  "properties": {
    "iso:country":"GB",
    "wof:name":"ME3 9BW",
    "wof:placetype":"postalcode"
},
  "geometry": {"coordinates":[0.56584798797278,51.42123548127972],"type":"Point"}
}