{
  "type": "Feature",
  "properties": {
    "date:inception_lower": "1990-02-01",
    "date:inception_upper": "1990-02-01",
    "iso:country": "GB",
    "wof:name": "ME3 9BW",
    "wof:placetype": "postalcode"
  },
  "geometry": {"coordinates":[0.565848,51.421235],"type":"Point"}
}
