{
  "type": "Feature",
  "properties": {
    "date:inception_lower":"1980-01-01",
    "date:inception_upper":"1980-01-31",
    "iso:country":"GB",
    "wof:name":"NE47 0LA",
    "wof:placetype":"postalcode"
},
  "geometry": {"coordinates":[-2.097672,54.923258],"type":"Point"}
}