{
  "type": "Feature",
  "properties": {
    "iso:country":"GB",
    "wof:name":"NE47 0LA",
    "wof:placetype":"postalcode"
},
  "geometry": {"coordinates":[-2.09767187918911,54.92325813579288],"type":"Point"}
}