{
  "type": "Feature",
  "properties": {
    "iso:country":"GB",
    "wof:name":"B14 6HR",
    "wof:placetype":"postalcode"
},
  "geometry": {"coordinates":[-1.90610683183065,52.42353090815311],"type":"Point"}
}