{
  "type": "Feature",
  "properties": {
    "date:inception_lower": "1980-01-01",
    "date:inception_upper": "1980-01-01",
    "iso:country": "GB",
    "wof:name": "RG7 2JJ",
    "wof:placetype": "postalcode"
  },
  "geometry": {"coordinates":[-1.067612,51.37356],"type":"Point"}
}
