{
  "type": "Feature",
  "properties": {
    "iso:country":"GB",
    "wof:name":"RG7 2JJ",
    "wof:placetype":"postalcode"
},
  "geometry": {"coordinates":[-1.06763191559402,51.37355981189766],"type":"Point"}
}