{
  "type": "Feature",
  "properties": {
    "iso:country": "GB",
    "wof:name": "ST12 9ES",
    "wof:placetype": "postalcode"
  },
  "geometry": {"coordinates":[-2.173557,52.946753],"type":"Point"}
}
