{
  "type": "Feature",
  "properties": {
    "iso:country":"GB",
    "wof:name":"ST12 9ES",
    "wof:placetype":"postalcode"
},
  "geometry": {"coordinates":[-2.17366237163194,52.94676387396285],"type":"Point"}
}