{
  "type": "Feature",
  "properties": {
    "iso:country":"GB",
    "wof:name":"HU17 8RN",
    "wof:placetype":"postalcode"
},
  "geometry": {"coordinates":[-0.43434769683293,53.82683401713367],"type":"Point"}
}