{
  "type": "Feature",
  "properties": {
    "date:inception_lower": "1993-08-01",
    "date:inception_upper": "1993-08-01",
    "iso:country": "GB",
    "wof:name": "HU17 8RN",
    "wof:placetype": "postalcode"
  },
  "geometry": {"coordinates":[-0.434348,53.826834],"type":"Point"}
}
