{
  "type": "Feature",
  "properties": {
    "iso:country": "GB",
    "wof:name": "SO20 8EJ",
    "wof:placetype": "postalcode"
  },
  "geometry": {"coordinates":[-1.583141,51.132064],"type":"Point"}
}
