{
  "type": "Feature",
  "properties": {
    "iso:country":"GB",
    "wof:name":"LL69 9BZ",
    "wof:placetype":"postalcode"
},
  "geometry": {"coordinates":[-4.31527441867132,53.38703006833796],"type":"Point"}
}