{
  "type": "Feature",
  "properties": {
    "date:inception_lower": "1985-04-01",
    "date:inception_upper": "1985-04-01",
    "iso:country": "GB",
    "wof:name": "LL69 9BZ",
    "wof:placetype": "postalcode"
  },
  "geometry": {"coordinates":[-4.315278,53.386968],"type":"Point"}
}
