{
  "type": "Feature",
  "properties": {
    "iso:country": "GB",
    "wof:name": "LL69 9BZ",
    "wof:placetype": "postalcode"
  },
  "geometry": {"coordinates":[-4.315274,53.38703],"type":"Point"}
}
