{
  "type": "Feature",
  "properties": {
    "date:inception_lower": "2007-02-01",
    "date:inception_upper": "2007-02-01",
    "iso:country": "GB",
    "wof:name": "KY16 8TJ",
    "wof:placetype": "postalcode"
  },
  "geometry": {"coordinates":[-2.810802,56.327299],"type":"Point"}
}
