{
  "type": "Feature",
  "properties": {
    "iso:country":"GB",
    "wof:name":"KY16 8TJ",
    "wof:placetype":"postalcode"
},
  "geometry": {"coordinates":[-2.81080226006338,56.32729864118773],"type":"Point"}
}