{
  "type": "Feature",
  "properties": {
    "iso:country":"GB",
    "wof:name":"PE31 7BP",
    "wof:placetype":"postalcode"
},
  "geometry": {"coordinates":[0.49060694924947,52.89982147198118],"type":"Point"}
}