{
  "type": "Feature",
  "properties": {
    "iso:country": "GB",
    "wof:name": "TR13 8GW",
    "wof:placetype": "postalcode"
  },
  "geometry": {"coordinates":[-5.2646,50.114204],"type":"Point"}
}
