{
  "type": "Feature",
  "properties": {
    "iso:country":"GB",
    "wof:name":"TR13 8GW",
    "wof:placetype":"postalcode"
},
  "geometry": {"coordinates":[-5.26459993824729,50.11420358607121],"type":"Point"}
}