{
  "type": "Feature",
  "properties": {
    "iso:country":"GB",
    "wof:name":"SE11 5EP",
    "wof:placetype":"postalcode"
},
  "geometry": {"coordinates":[-0.12093996839982,51.48876479177922],"type":"Point"}
}