{
  "type": "Feature",
  "properties": {
    "iso:country":"GB",
    "wof:name":"DD10 8TP",
    "wof:placetype":"postalcode"
},
  "geometry": {"coordinates":[-2.45682285818627,56.71060782783161],"type":"Point"}
}