{
  "type": "Feature",
  "properties": {
    "date:inception_lower": "1995-12-01",
    "date:inception_upper": "1995-12-01",
    "iso:country": "GB",
    "wof:name": "DD10 8TP",
    "wof:placetype": "postalcode"
  },
  "geometry": {"coordinates":[-2.456823,56.710608],"type":"Point"}
}
