{
  "type": "Feature",
  "properties": {
    "iso:country":"GB",
    "wof:name":"WA4 5DL",
    "wof:placetype":"postalcode"
},
  "geometry": {"coordinates":[-2.57192552925631,53.34729813798478],"type":"Point"}
}