{
  "type": "Feature",
  "properties": {
    "date:inception_lower":"2007-04-01",
    "date:inception_upper":"2007-04-30",
    "iso:country":"GB",
    "wof:name":"SO97 4AH",
    "wof:placetype":"postalcode"
},
  "geometry": {"coordinates":[-1.361961,50.948487],"type":"Point"}
}