{
  "type": "Feature",
  "properties": {
    "iso:country":"GB",
    "wof:name":"WV6 7RW",
    "wof:placetype":"postalcode"
},
  "geometry": {"coordinates":[-2.19471768110636,52.59112335309302],"type":"Point"}
}