{
  "type": "Feature",
  "properties": {
    "iso:country": "GB",
    "wof:name": "WV6 7RW",
    "wof:placetype": "postalcode"
  },
  "geometry": {"coordinates":[-2.194718,52.591123],"type":"Point"}
}
