{
  "type": "Feature",
  "properties": {
    "iso:country": "GB",
    "wof:name": "BS27 3FB",
    "wof:placetype": "postalcode"
  },
  "geometry": {"coordinates":[-2.789671,51.278351],"type":"Point"}
}
