{
  "type": "Feature",
  "properties": {
    "date:inception_lower": "2015-12-01",
    "date:inception_upper": "2015-12-01",
    "iso:country": "GB",
    "wof:name": "BS27 3FB",
    "wof:placetype": "postalcode"
  },
  "geometry": {"coordinates":[-2.789671,51.278351],"type":"Point"}
}
