{
  "type": "Feature",
  "properties": {
    "iso:country":"GB",
    "wof:name":"TN4 9BY",
    "wof:placetype":"postalcode"
},
  "geometry": {"coordinates":[0.27158536164745,51.15117883791743],"type":"Point"}
}