{
  "type": "Feature",
  "properties": {
    "iso:country":"GB",
    "wof:name":"HG4 3AG",
    "wof:placetype":"postalcode"
},
  "geometry": {"coordinates":[-1.5283198478319,54.11586571944623],"type":"Point"}
}