{
  "type": "Feature",
  "properties": {
    "iso:country": "GB",
    "wof:name": "CO15 1UR",
    "wof:placetype": "postalcode"
  },
  "geometry": {"coordinates":[1.143824,51.786523],"type":"Point"}
}
