{
  "type": "Feature",
  "properties": {
    "iso:country":"GB",
    "wof:name":"CO15 1UR",
    "wof:placetype":"postalcode"
},
  "geometry": {"coordinates":[1.14382407339808,51.78652330562943],"type":"Point"}
}