{
  "type": "Feature",
  "properties": {
    "iso:country":"GB",
    "wof:name":"CA7 2DG",
    "wof:placetype":"postalcode"
},
  "geometry": {"coordinates":[-3.32899053189465,54.73831542016711],"type":"Point"}
}