{
  "type": "Feature",
  "properties": {
    "iso:country": "GB",
    "wof:name": "CO16 9PE",
    "wof:placetype": "postalcode"
  },
  "geometry": {"coordinates":[1.139806,51.822401],"type":"Point"}
}
