{
  "type": "Feature",
  "properties": {
    "iso:country":"GB",
    "wof:name":"CO16 9PE",
    "wof:placetype":"postalcode"
},
  "geometry": {"coordinates":[1.13980621421151,51.82240056874524],"type":"Point"}
}