{
  "type": "Feature",
  "properties": {
    "iso:country":"GB",
    "wof:name":"BN2 3QB",
    "wof:placetype":"postalcode"
},
  "geometry": {"coordinates":[-0.12386258956594,50.83735798395369],"type":"Point"}
}