{
  "type": "Feature",
  "properties": {
    "iso:country": "GB",
    "wof:name": "CF38 2AH",
    "wof:placetype": "postalcode"
  },
  "geometry": {"coordinates":[-3.35719,51.559352],"type":"Point"}
}
