{
  "type": "Feature",
  "properties": {
    "date:inception_lower": "2013-09-01",
    "date:inception_upper": "2013-09-01",
    "iso:country": "GB",
    "wof:name": "BB4 8FT",
    "wof:placetype": "postalcode"
  },
  "geometry": {"coordinates":[-2.285572,53.714434],"type":"Point"}
}
