{
  "type": "Feature",
  "properties": {
    "iso:country": "GB",
    "wof:name": "LL57 4HE",
    "wof:placetype": "postalcode"
  },
  "geometry": {"coordinates":[-4.117563,53.172261],"type":"Point"}
}
