{
  "type": "Feature",
  "properties": {
    "iso:country": "GB",
    "wof:name": "PE36 5NQ",
    "wof:placetype": "postalcode"
  },
  "geometry": {"coordinates":[0.54339,52.901004],"type":"Point"}
}
