{
  "type": "Feature",
  "properties": {
    "iso:country":"GB",
    "wof:name":"PL6 6NU",
    "wof:placetype":"postalcode"
},
  "geometry": {"coordinates":[-4.14696744836621,50.42679546341643],"type":"Point"}
}