{
  "type": "Feature",
  "properties": {
    "iso:country":"GB",
    "wof:name":"NR9 3NF",
    "wof:placetype":"postalcode"
},
  "geometry": {"coordinates":[1.19743896147775,52.61949990497676],"type":"Point"}
}