{
  "type": "Feature",
  "properties": {
    "iso:country":"GB",
    "wof:name":"CR8 1EY",
    "wof:placetype":"postalcode"
},
  "geometry": {"coordinates":[-0.09386329714504,51.32824864015363],"type":"Point"}
}