{
  "type": "Feature",
  "properties": {
    "iso:country":"GB",
    "wof:name":"CA15 8HF",
    "wof:placetype":"postalcode"
},
  "geometry": {"coordinates":[-3.49188512672494,54.70538605513308],"type":"Point"}
}