{
  "type": "Feature",
  "properties": {
    "iso:country": "GB",
    "wof:name": "BA20 2FB",
    "wof:placetype": "postalcode"
  },
  "geometry": {"coordinates":[-2.641274,50.939654],"type":"Point"}
}
