{
  "type": "Feature",
  "properties": {
    "iso:country":"GB",
    "wof:name":"BA5 2QF",
    "wof:placetype":"postalcode"
},
  "geometry": {"coordinates":[-2.65254617034074,51.20950297172694],"type":"Point"}
}