{
  "type": "Feature",
  "properties": {
    "iso:country":"GB",
    "wof:name":"UB5 6HY",
    "wof:placetype":"postalcode"
},
  "geometry": {"coordinates":[-0.39303703797755,51.53412826394842],"type":"Point"}
}