{
  "type": "Feature",
  "properties": {
    "iso:country": "GB",
    "wof:name": "BN8 5NJ",
    "wof:placetype": "postalcode"
  },
  "geometry": {"coordinates":[0.085859,50.895354],"type":"Point"}
}
