{
  "type": "Feature",
  "properties": {
    "iso:country":"GB",
    "wof:name":"CV23 9RN",
    "wof:placetype":"postalcode"
},
  "geometry": {"coordinates":[-1.41188435212961,52.31879090542689],"type":"Point"}
}