{
  "type": "Feature",
  "properties": {
    "iso:country": "GB",
    "wof:name": "CV23 9RN",
    "wof:placetype": "postalcode"
  },
  "geometry": {"coordinates":[-1.411884,52.318791],"type":"Point"}
}
