{
  "type": "Feature",
  "properties": {
    "date:inception_lower": "2004-01-01",
    "date:inception_upper": "2004-01-01",
    "iso:country": "GB",
    "wof:name": "HU11 4AT",
    "wof:placetype": "postalcode"
  },
  "geometry": {"coordinates":[-0.259332,53.779036],"type":"Point"}
}
