{
  "type": "Feature",
  "properties": {
    "iso:country":"GB",
    "wof:name":"ME4 5HW",
    "wof:placetype":"postalcode"
},
  "geometry": {"coordinates":[0.53824397249471,51.37372116507229],"type":"Point"}
}