{
  "type": "Feature",
  "properties": {
    "iso:country":"GB",
    "wof:name":"NE10 8AL",
    "wof:placetype":"postalcode"
},
  "geometry": {"coordinates":[-1.52106858945798,54.94928722148997],"type":"Point"}
}