{
  "type": "Feature",
  "properties": {
    "date:inception_lower": "1980-01-01",
    "date:inception_upper": "1980-01-01",
    "iso:country": "GB",
    "wof:name": "FK1 5PT",
    "wof:placetype": "postalcode"
  },
  "geometry": {"coordinates":[-3.812214,55.992007],"type":"Point"}
}
