{
  "type": "Feature",
  "properties": {
    "iso:country":"GB",
    "wof:name":"FK1 5PT",
    "wof:placetype":"postalcode"
},
  "geometry": {"coordinates":[-3.81221419823904,55.99200696204206],"type":"Point"}
}