{
  "type": "Feature",
  "properties": {
    "iso:country":"GB",
    "wof:name":"SY3 7TX",
    "wof:placetype":"postalcode"
},
  "geometry": {"coordinates":[-2.74275164146019,52.69751531020766],"type":"Point"}
}