{
  "type": "Feature",
  "properties": {
    "iso:country":"GB",
    "wof:name":"GL53 8NB",
    "wof:placetype":"postalcode"
},
  "geometry": {"coordinates":[-2.05345927894868,51.88169172234523],"type":"Point"}
}