{
  "type": "Feature",
  "properties": {
    "iso:country": "GB",
    "wof:name": "GL53 8NB",
    "wof:placetype": "postalcode"
  },
  "geometry": {"coordinates":[-2.053459,51.881692],"type":"Point"}
}
