{
  "type": "Feature",
  "properties": {
    "iso:country":"GB",
    "wof:name":"BS22 8HT",
    "wof:placetype":"postalcode"
},
  "geometry": {"coordinates":[-2.94487271743145,51.35766554289162],"type":"Point"}
}