{
  "type": "Feature",
  "properties": {
    "iso:country": "GB",
    "wof:name": "BS22 8HT",
    "wof:placetype": "postalcode"
  },
  "geometry": {"coordinates":[-2.944873,51.357666],"type":"Point"}
}
