{
  "type": "Feature",
  "properties": {
    "iso:country":"GB",
    "wof:name":"RG20 8RG",
    "wof:placetype":"postalcode"
},
  "geometry": {"coordinates":[-1.37307196024829,51.4658591760975],"type":"Point"}
}