{
  "type": "Feature",
  "properties": {
    "date:inception_lower":"2007-11-01",
    "date:inception_upper":"2007-11-30",
    "iso:country":"GB",
    "wof:name":"WD17 2AB",
    "wof:placetype":"postalcode"
},
  "geometry": {"coordinates":[-0.392902,51.657962],"type":"Point"}
}