{
  "type": "Feature",
  "properties": {
    "iso:country": "GB",
    "wof:name": "WD17 2AB",
    "wof:placetype": "postalcode"
  },
  "geometry": {"coordinates":[-0.392934,51.6579],"type":"Point"}
}
