{
  "type": "Feature",
  "properties": {
    "date:inception_lower": "1980-01-01",
    "date:inception_upper": "1980-01-01",
    "iso:country": "GB",
    "wof:name": "CB4 1LN",
    "wof:placetype": "postalcode"
  },
  "geometry": {"coordinates":[0.142876,52.22338],"type":"Point"}
}
