{
  "type": "Feature",
  "properties": {
    "iso:country": "GB",
    "wof:name": "FY5 4NF",
    "wof:placetype": "postalcode"
  },
  "geometry": {"coordinates":[-3.002866,53.87215],"type":"Point"}
}
