{
  "type": "Feature",
  "properties": {
    "iso:country": "GB",
    "wof:name": "EC1Y 8JY",
    "wof:placetype": "postalcode"
  },
  "geometry": {"coordinates":[-0.09458,51.523303],"type":"Point"}
}
