{
  "type": "Feature",
  "properties": {
    "date:inception_lower":"1980-01-01",
    "date:inception_upper":"1980-01-31",
    "iso:country":"GB",
    "wof:name":"S71 4HS",
    "wof:placetype":"postalcode"
},
  "geometry": {"coordinates":[-1.464499,53.60225],"type":"Point"}
}