{
  "type": "Feature",
  "properties": {
    "iso:country":"GB",
    "wof:name":"S71 4HS",
    "wof:placetype":"postalcode"
},
  "geometry": {"coordinates":[-1.4644988014814,53.60225023621231],"type":"Point"}
}