{
  "type": "Feature",
  "properties": {
    "iso:country": "GB",
    "wof:name": "PO33 2FX",
    "wof:placetype": "postalcode"
  },
  "geometry": {"coordinates":[-1.16026,50.73092],"type":"Point"}
}
