{
  "type": "Feature",
  "properties": {
    "iso:country":"GB",
    "wof:name":"PO33 2FX",
    "wof:placetype":"postalcode"
},
  "geometry": {"coordinates":[-1.16026022183677,50.73091986349826],"type":"Point"}
}