{
  "type": "Feature",
  "properties": {
    "iso:country":"GB",
    "wof:name":"L28 1NN",
    "wof:placetype":"postalcode"
},
  "geometry": {"coordinates":[-2.86730331468004,53.43500955175767],"type":"Point"}
}