{
  "type": "Feature",
  "properties": {
    "iso:country": "GB",
    "wof:name": "L28 1NN",
    "wof:placetype": "postalcode"
  },
  "geometry": {"coordinates":[-2.867303,53.43501],"type":"Point"}
}
