{
  "type": "Feature",
  "properties": {
    "iso:country":"GB",
    "wof:name":"B61 9ED",
    "wof:placetype":"postalcode"
},
  "geometry": {"coordinates":[-2.12190022469551,52.35194364212119],"type":"Point"}
}