{
  "type": "Feature",
  "properties": {
    "iso:country": "GB",
    "wof:name": "B61 9ED",
    "wof:placetype": "postalcode"
  },
  "geometry": {"coordinates":[-2.1219,52.351944],"type":"Point"}
}
