{
  "type": "Feature",
  "properties": {
    "iso:country":"GB",
    "wof:name":"CA6 5TG",
    "wof:placetype":"postalcode"
},
  "geometry": {"coordinates":[-2.96630880852105,55.00723597065414],"type":"Point"}
}