{
  "type": "Feature",
  "properties": {
    "iso:country": "GB",
    "wof:name": "CA6 5TG",
    "wof:placetype": "postalcode"
  },
  "geometry": {"coordinates":[-2.966312,55.007242],"type":"Point"}
}
