{
  "type": "Feature",
  "properties": {
    "date:inception_lower": "1990-11-01",
    "date:inception_upper": "1990-11-01",
    "iso:country": "GB",
    "wof:name": "AB52 6YP",
    "wof:placetype": "postalcode"
  },
  "geometry": {"coordinates":[-2.734226,57.349876],"type":"Point"}
}
