{
  "type": "Feature",
  "properties": {
    "iso:country":"GB",
    "wof:name":"DD5 3QW",
    "wof:placetype":"postalcode"
},
  "geometry": {"coordinates":[-2.81537931533459,56.53334380736709],"type":"Point"}
}