{
  "type": "Feature",
  "properties": {
    "iso:country": "GB",
    "wof:name": "GU25 4EE",
    "wof:placetype": "postalcode"
  },
  "geometry": {"coordinates":[-0.549545,51.394289],"type":"Point"}
}
