{
  "type": "Feature",
  "properties": {
    "iso:country":"GB",
    "wof:name":"WS10 7SE",
    "wof:placetype":"postalcode"
},
  "geometry": {"coordinates":[-2.03777669173928,52.55867168393121],"type":"Point"}
}