{
  "type": "Feature",
  "properties": {
    "date:inception_lower": "1980-01-01",
    "date:inception_upper": "1980-01-01",
    "iso:country": "GB",
    "wof:name": "WS10 7SE",
    "wof:placetype": "postalcode"
  },
  "geometry": {"coordinates":[-2.037777,52.558672],"type":"Point"}
}
