{
  "type": "Feature",
  "properties": {
    "iso:country": "GB",
    "wof:name": "PO40 9BZ",
    "wof:placetype": "postalcode"
  },
  "geometry": {"coordinates":[-1.512645,50.686018],"type":"Point"}
}
