{
  "type": "Feature",
  "properties": {
    "iso:country":"GB",
    "wof:name":"PO40 9BZ",
    "wof:placetype":"postalcode"
},
  "geometry": {"coordinates":[-1.51264527809448,50.68601813782514],"type":"Point"}
}