{
  "type": "Feature",
  "properties": {
    "iso:country":"GB",
    "wof:name":"LA11 7AS",
    "wof:placetype":"postalcode"
},
  "geometry": {"coordinates":[-2.92254470619293,54.17893416509325],"type":"Point"}
}