{
  "type": "Feature",
  "properties": {
    "date:inception_lower": "1980-01-01",
    "date:inception_upper": "1980-01-01",
    "iso:country": "GB",
    "wof:name": "LA11 7AS",
    "wof:placetype": "postalcode"
  },
  "geometry": {"coordinates":[-2.922545,54.178934],"type":"Point"}
}
