{
  "type": "Feature",
  "properties": {
    "iso:country": "GB",
    "wof:name": "WF14 9LU",
    "wof:placetype": "postalcode"
  },
  "geometry": {"coordinates":[-1.691976,53.683002],"type":"Point"}
}
