{
  "type": "Feature",
  "properties": {
    "iso:country": "GB",
    "wof:name": "DN22 0QW",
    "wof:placetype": "postalcode"
  },
  "geometry": {"coordinates":[-0.927815,53.265398],"type":"Point"}
}
