{
  "type": "Feature",
  "properties": {
    "iso:country":"GB",
    "wof:name":"DN22 0QW",
    "wof:placetype":"postalcode"
},
  "geometry": {"coordinates":[-0.9268717529705,53.26475169766812],"type":"Point"}
}