{
  "type": "Feature",
  "properties": {
    "iso:country": "GB",
    "wof:name": "GL4 0YE",
    "wof:placetype": "postalcode"
  },
  "geometry": {"coordinates":[-2.249148,51.828987],"type":"Point"}
}
