{
  "type": "Feature",
  "properties": {
    "iso:country":"GB",
    "wof:name":"GL4 0YE",
    "wof:placetype":"postalcode"
},
  "geometry": {"coordinates":[-2.24914836030616,51.82898655063024],"type":"Point"}
}