{
  "type": "Feature",
  "properties": {
    "iso:country":"GB",
    "wof:name":"W11 4RD",
    "wof:placetype":"postalcode"
},
  "geometry": {"coordinates":[-0.214564946177,51.50800570119383],"type":"Point"}
}