{
  "type": "Feature",
  "properties": {
    "iso:country": "GB",
    "wof:name": "PE19 7GS",
    "wof:placetype": "postalcode"
  },
  "geometry": {"coordinates":[-0.287148,52.23063],"type":"Point"}
}
