{
  "type": "Feature",
  "properties": {
    "iso:country":"GB",
    "wof:name":"DY6 9LJ",
    "wof:placetype":"postalcode"
},
  "geometry": {"coordinates":[-2.16670278556449,52.49452503882953],"type":"Point"}
}