{
  "type": "Feature",
  "properties": {
    "date:inception_lower": "1980-01-01",
    "date:inception_upper": "1980-01-01",
    "iso:country": "GB",
    "wof:name": "AL3 5SY",
    "wof:placetype": "postalcode"
  },
  "geometry": {"coordinates":[-0.34167,51.760976],"type":"Point"}
}
