{
  "type": "Feature",
  "properties": {
    "iso:country":"GB",
    "wof:name":"AL3 5SY",
    "wof:placetype":"postalcode"
},
  "geometry": {"coordinates":[-0.34166962256489,51.76097648275581],"type":"Point"}
}