{
  "type": "Feature",
  "properties": {
    "iso:country":"GB",
    "wof:name":"BN18 9PE",
    "wof:placetype":"postalcode"
},
  "geometry": {"coordinates":[-0.55228678407042,50.87606856776557],"type":"Point"}
}