{
  "type": "Feature",
  "properties": {
    "iso:country": "GB",
    "wof:name": "BN18 9PE",
    "wof:placetype": "postalcode"
  },
  "geometry": {"coordinates":[-0.552287,50.876069],"type":"Point"}
}
