{
  "type": "Feature",
  "properties": {
    "iso:country":"GB",
    "wof:name":"EH20 9AX",
    "wof:placetype":"postalcode"
},
  "geometry": {"coordinates":[-3.14902579045764,55.87623391886234],"type":"Point"}
}