{
  "type": "Feature",
  "properties": {
    "date:inception_lower": "1980-01-01",
    "date:inception_upper": "1980-01-01",
    "iso:country": "GB",
    "wof:name": "WV6 8PP",
    "wof:placetype": "postalcode"
  },
  "geometry": {"coordinates":[-2.176198,52.588851],"type":"Point"}
}
