{
  "type": "Feature",
  "properties": {
    "iso:country":"GB",
    "wof:name":"WV6 8PP",
    "wof:placetype":"postalcode"
},
  "geometry": {"coordinates":[-2.17619783675346,52.58885100409337],"type":"Point"}
}