{
  "type": "Feature",
  "properties": {
    "iso:country":"GB",
    "wof:name":"PE21 8SA",
    "wof:placetype":"postalcode"
},
  "geometry": {"coordinates":[-0.02900452288295,52.97945772882188],"type":"Point"}
}