{
  "type": "Feature",
  "properties": {
    "date:inception_lower":"1980-01-01",
    "date:inception_upper":"1980-01-31",
    "iso:country":"GB",
    "wof:name":"CM2 7NQ",
    "wof:placetype":"postalcode"
},
  "geometry": {"coordinates":[0.486782,51.725348],"type":"Point"}
}