{
  "type": "Feature",
  "properties": {
    "iso:country":"GB",
    "wof:name":"CM2 7NQ",
    "wof:placetype":"postalcode"
},
  "geometry": {"coordinates":[0.48678196564206,51.72534807083855],"type":"Point"}
}