{
  "type": "Feature",
  "properties": {
    "date:inception_lower":"1980-01-01",
    "date:inception_upper":"1980-01-31",
    "iso:country":"GB",
    "wof:name":"BN1 7BJ",
    "wof:placetype":"postalcode"
},
  "geometry": {"coordinates":[-0.126747,50.840876],"type":"Point"}
}