{
  "type": "Feature",
  "properties": {
    "iso:country":"GB",
    "wof:name":"BN1 7BJ",
    "wof:placetype":"postalcode"
},
  "geometry": {"coordinates":[-0.12674690477344,50.84087580193648],"type":"Point"}
}