{
  "type": "Feature",
  "properties": {
    "iso:country": "GB",
    "wof:name": "BN1 7BJ",
    "wof:placetype": "postalcode"
  },
  "geometry": {"coordinates":[-0.126747,50.840876],"type":"Point"}
}
