{
  "type": "Feature",
  "properties": {
    "iso:country":"GB",
    "wof:name":"W1T 4RX",
    "wof:placetype":"postalcode"
},
  "geometry": {"coordinates":[-0.13693199308608,51.51977438768862],"type":"Point"}
}