{
  "type": "Feature",
  "properties": {
    "date:inception_lower":"2008-05-01",
    "date:inception_upper":"2008-05-31",
    "iso:country":"GB",
    "wof:name":"CV21 2XQ",
    "wof:placetype":"postalcode"
},
  "geometry": {"coordinates":[-1.257214,52.373777],"type":"Point"}
}