{
  "type": "Feature",
  "properties": {
    "iso:country": "GB",
    "wof:name": "LN6 7TT",
    "wof:placetype": "postalcode"
  },
  "geometry": {"coordinates":[-0.553363,53.217102],"type":"Point"}
}
