{
  "type": "Feature",
  "properties": {
    "iso:country":"GB",
    "wof:name":"NE24 3PL",
    "wof:placetype":"postalcode"
},
  "geometry": {"coordinates":[-1.50091492153594,55.10906221445656],"type":"Point"}
}