{
  "type": "Feature",
  "properties": {
    "iso:country":"GB",
    "wof:name":"WF9 2BP",
    "wof:placetype":"postalcode"
},
  "geometry": {"coordinates":[-1.3015177167015,53.59404875859022],"type":"Point"}
}