{
  "type": "Feature",
  "properties": {
    "iso:country":"GB",
    "wof:name":"BB9 9NN",
    "wof:placetype":"postalcode"
},
  "geometry": {"coordinates":[-2.19341276772931,53.83496742738843],"type":"Point"}
}