{
  "type": "Feature",
  "properties": {
    "iso:country":"GB",
    "wof:name":"BS20 6QN",
    "wof:placetype":"postalcode"
},
  "geometry": {"coordinates":[-2.76894793445094,51.47463182825042],"type":"Point"}
}