{
  "type": "Feature",
  "properties": {
    "iso:country":"GB",
    "wof:name":"DA1 4BZ",
    "wof:placetype":"postalcode"
},
  "geometry": {"coordinates":[0.17283116341905,51.45155706987008],"type":"Point"}
}