{
  "type": "Feature",
  "properties": {
    "date:inception_lower": "1986-04-01",
    "date:inception_upper": "1986-04-01",
    "iso:country": "GB",
    "wof:name": "DA1 4BZ",
    "wof:placetype": "postalcode"
  },
  "geometry": {"coordinates":[0.172831,51.451557],"type":"Point"}
}
