{
  "type": "Feature",
  "properties": {
    "iso:country": "GB",
    "wof:name": "DA1 4BZ",
    "wof:placetype": "postalcode"
  },
  "geometry": {"coordinates":[0.172831,51.451557],"type":"Point"}
}
