{
  "type": "Feature",
  "properties": {
    "iso:country":"GB",
    "wof:name":"WS10 9TU",
    "wof:placetype":"postalcode"
},
  "geometry": {"coordinates":[-2.02369392812741,52.56581329772192],"type":"Point"}
}