{
  "type": "Feature",
  "properties": {
    "date:inception_lower": "2004-08-01",
    "date:inception_upper": "2004-08-01",
    "iso:country": "GB",
    "wof:name": "WS10 9TU",
    "wof:placetype": "postalcode"
  },
  "geometry": {"coordinates":[-2.023694,52.565813],"type":"Point"}
}
