{
  "type": "Feature",
  "properties": {
    "iso:country":"GB",
    "wof:name":"CH41 6RT",
    "wof:placetype":"postalcode"
},
  "geometry": {"coordinates":[-3.02267039124889,53.3914600714716],"type":"Point"}
}