{
  "type": "Feature",
  "properties": {
    "iso:country": "GB",
    "wof:name": "DH9 8UG",
    "wof:placetype": "postalcode"
  },
  "geometry": {"coordinates":[-1.748342,54.856646],"type":"Point"}
}
