{
  "type": "Feature",
  "properties": {
    "date:inception_lower":"1995-12-01",
    "date:inception_upper":"1995-12-31",
    "iso:country":"GB",
    "wof:name":"DH9 8UG",
    "wof:placetype":"postalcode"
},
  "geometry": {"coordinates":[-1.748342,54.856646],"type":"Point"}
}