{
  "type": "Feature",
  "properties": {
    "date:inception_lower": "1980-01-01",
    "date:inception_upper": "1980-01-01",
    "iso:country": "GB",
    "wof:name": "SW2 3EP",
    "wof:placetype": "postalcode"
  },
  "geometry": {"coordinates":[-0.118051,51.44416],"type":"Point"}
}
