{
  "type": "Feature",
  "properties": {
    "iso:country":"GB",
    "wof:name":"SW2 3EP",
    "wof:placetype":"postalcode"
},
  "geometry": {"coordinates":[-0.11805149033691,51.44416015269572],"type":"Point"}
}