{
  "type": "Feature",
  "properties": {
    "iso:country":"GB",
    "wof:name":"S13 8UF",
    "wof:placetype":"postalcode"
},
  "geometry": {"coordinates":[-1.38616115134681,53.36821614006284],"type":"Point"}
}