{
  "type": "Feature",
  "properties": {
    "iso:country":"GB",
    "wof:name":"NW3 7XA",
    "wof:placetype":"postalcode"
},
  "geometry": {"coordinates":[-0.18696584402248,51.55962148443913],"type":"Point"}
}