{
  "type": "Feature",
  "properties": {
    "iso:country":"GB",
    "wof:name":"HA4 0NR",
    "wof:placetype":"postalcode"
},
  "geometry": {"coordinates":[-0.39337733969013,51.56377116945113],"type":"Point"}
}