{
  "type": "Feature",
  "properties": {
    "iso:country":"GB",
    "wof:name":"YO25 4LA",
    "wof:placetype":"postalcode"
},
  "geometry": {"coordinates":[-0.38634763524936,54.01958421039775],"type":"Point"}
}