{
  "type": "Feature",
  "properties": {
    "iso:country":"GB",
    "wof:name":"YO12 7PE",
    "wof:placetype":"postalcode"
},
  "geometry": {"coordinates":[-0.40206662728112,54.28722945066386],"type":"Point"}
}