{
  "type": "Feature",
  "properties": {
    "date:inception_lower": "2023-06-01",
    "date:inception_upper": "2023-06-01",
    "iso:country": "GB",
    "wof:name": "SW1A 2BH",
    "wof:placetype": "postalcode"
  },
  "geometry": {"coordinates":[-0.12569,51.505083],"type":"Point"}
}
