{
  "type": "Feature",
  "properties": {
    "iso:country": "GB",
    "wof:name": "CB7 5PQ",
    "wof:placetype": "postalcode"
  },
  "geometry": {"coordinates":[0.350361,52.324222],"type":"Point"}
}
