{
  "type": "Feature",
  "properties": {
    "date:inception_lower":"2018-01-01",
    "date:inception_upper":"2018-01-31",
    "iso:country":"GB",
    "wof:name":"CB7 5PQ",
    "wof:placetype":"postalcode"
},
  "geometry": {"coordinates":[0.350361,52.324222],"type":"Point"}
}