{
  "type": "Feature",
  "properties": {
    "iso:country": "GB",
    "wof:name": "BB12 7JZ",
    "wof:placetype": "postalcode"
  },
  "geometry": {"coordinates":[-2.316971,53.783455],"type":"Point"}
}
