{
  "type": "Feature",
  "properties": {
    "iso:country":"GB",
    "wof:name":"HP2 5DJ",
    "wof:placetype":"postalcode"
},
  "geometry": {"coordinates":[-0.47131901361209,51.76085478206389],"type":"Point"}
}