{
  "type": "Feature",
  "properties": {
    "date:inception_lower":"1983-03-01",
    "date:inception_upper":"1983-03-31",
    "iso:country":"GB",
    "wof:name":"HP2 5DJ",
    "wof:placetype":"postalcode"
},
  "geometry": {"coordinates":[-0.471319,51.760855],"type":"Point"}
}