{
  "type": "Feature",
  "properties": {
    "iso:country": "GB",
    "wof:name": "SY14 7LL",
    "wof:placetype": "postalcode"
  },
  "geometry": {"coordinates":[-2.829822,52.994223],"type":"Point"}
}
