{
  "type": "Feature",
  "properties": {
    "iso:country":"GB",
    "wof:name":"SY14 7LL",
    "wof:placetype":"postalcode"
},
  "geometry": {"coordinates":[-2.83128426738002,52.99431417090565],"type":"Point"}
}