{
  "type": "Feature",
  "properties": {
    "date:inception_lower": "1980-01-01",
    "date:inception_upper": "1980-01-01",
    "iso:country": "GB",
    "wof:name": "KT13 0HR",
    "wof:placetype": "postalcode"
  },
  "geometry": {"coordinates":[-0.43483,51.360863],"type":"Point"}
}
