{
  "type": "Feature",
  "properties": {
    "iso:country": "GB",
    "wof:name": "PR6 8NX",
    "wof:placetype": "postalcode"
  },
  "geometry": {"coordinates":[-2.600008,53.723311],"type":"Point"}
}
