{
  "type": "Feature",
  "properties": {
    "iso:country":"GB",
    "wof:name":"DD5 2EE",
    "wof:placetype":"postalcode"
},
  "geometry": {"coordinates":[-2.8673171322722,56.46536690699082],"type":"Point"}
}