{
  "type": "Feature",
  "properties": {
    "iso:country":"GB",
    "wof:name":"DG11 1EA",
    "wof:placetype":"postalcode"
},
  "geometry": {"coordinates":[-3.40770082555348,55.05848655894452],"type":"Point"}
}