{
  "type": "Feature",
  "properties": {
    "date:inception_lower": "1980-01-01",
    "date:inception_upper": "1980-01-01",
    "iso:country": "GB",
    "wof:name": "DG11 1EA",
    "wof:placetype": "postalcode"
  },
  "geometry": {"coordinates":[-3.407701,55.058487],"type":"Point"}
}
