{
  "type": "Feature",
  "properties": {
    "iso:country":"GB",
    "wof:name":"CH3 6AE",
    "wof:placetype":"postalcode"
},
  "geometry": {"coordinates":[-2.84267910934937,53.18367443037268],"type":"Point"}
}