{
  "type": "Feature",
  "properties": {
    "date:inception_lower": "1980-01-01",
    "date:inception_upper": "1980-01-01",
    "iso:country": "GB",
    "wof:name": "B34 7DZ",
    "wof:placetype": "postalcode"
  },
  "geometry": {"coordinates":[-1.775737,52.497487],"type":"Point"}
}
