{
  "type": "Feature",
  "properties": {
    "iso:country": "GB",
    "wof:name": "B34 7DZ",
    "wof:placetype": "postalcode"
  },
  "geometry": {"coordinates":[-1.775737,52.497487],"type":"Point"}
}
