{
  "type": "Feature",
  "properties": {
    "iso:country":"GB",
    "wof:name":"B34 7DZ",
    "wof:placetype":"postalcode"
},
  "geometry": {"coordinates":[-1.77573701626486,52.49748740638272],"type":"Point"}
}