{
  "type": "Feature",
  "properties": {
    "iso:country":"GB",
    "wof:name":"DL1 1DG",
    "wof:placetype":"postalcode"
},
  "geometry": {"coordinates":[-1.52284575551197,54.52373137762316],"type":"Point"}
}