{
  "type": "Feature",
  "properties": {
    "date:inception_lower":"2012-07-01",
    "date:inception_upper":"2012-07-31",
    "iso:country":"GB",
    "wof:name":"WR11 2AN",
    "wof:placetype":"postalcode"
},
  "geometry": {"coordinates":[-1.966307,52.084919],"type":"Point"}
}