{
  "type": "Feature",
  "properties": {
    "date:inception_lower": "1980-01-01",
    "date:inception_upper": "1980-01-01",
    "iso:country": "GB",
    "wof:name": "CO5 8RJ",
    "wof:placetype": "postalcode"
  },
  "geometry": {"coordinates":[0.92015,51.782331],"type":"Point"}
}
