{
  "type": "Feature",
  "properties": {
    "iso:country": "GB",
    "wof:name": "TS21 1DS",
    "wof:placetype": "postalcode"
  },
  "geometry": {"coordinates":[-1.389533,54.591748],"type":"Point"}
}
