{
  "type": "Feature",
  "properties": {
    "iso:country": "GB",
    "wof:name": "GL6 0PE",
    "wof:placetype": "postalcode"
  },
  "geometry": {"coordinates":[-2.235569,51.684923],"type":"Point"}
}
