{
  "type": "Feature",
  "properties": {
    "iso:country":"GB",
    "wof:name":"GL6 0PE",
    "wof:placetype":"postalcode"
},
  "geometry": {"coordinates":[-2.23556909410091,51.68492342650318],"type":"Point"}
}