{
  "type": "Feature",
  "properties": {
    "date:inception_lower":"1992-08-01",
    "date:inception_upper":"1992-08-31",
    "iso:country":"GB",
    "wof:name":"SY3 6DA",
    "wof:placetype":"postalcode"
},
  "geometry": {"coordinates":[-2.777402,52.698048],"type":"Point"}
}