{
  "type": "Feature",
  "properties": {
    "iso:country":"GB",
    "wof:name":"CA8 2NW",
    "wof:placetype":"postalcode"
},
  "geometry": {"coordinates":[-2.6582589237405,54.92908040643703],"type":"Point"}
}