{
  "type": "Feature",
  "properties": {
    "iso:country": "GB",
    "wof:name": "IP33 2DN",
    "wof:placetype": "postalcode"
  },
  "geometry": {"coordinates":[0.695755,52.237374],"type":"Point"}
}
