{
  "type": "Feature",
  "properties": {
    "iso:country":"GB",
    "wof:name":"NE65 0UW",
    "wof:placetype":"postalcode"
},
  "geometry": {"coordinates":[-1.61217433588239,55.34691897196095],"type":"Point"}
}