{
  "type": "Feature",
  "properties": {
    "iso:country":"GB",
    "wof:name":"CF47 8NF",
    "wof:placetype":"postalcode"
},
  "geometry": {"coordinates":[-3.38039671765498,51.74947458289952],"type":"Point"}
}