{
  "type": "Feature",
  "properties": {
    "date:inception_lower": "2022-04-01",
    "date:inception_upper": "2022-04-01",
    "iso:country": "GB",
    "wof:name": "RH11 9UH",
    "wof:placetype": "postalcode"
  },
  "geometry": {"coordinates":[-0.188026,51.083857],"type":"Point"}
}
