{
  "type": "Feature",
  "properties": {
    "iso:country": "GB",
    "wof:name": "SL7 1TY",
    "wof:placetype": "postalcode"
  },
  "geometry": {"coordinates":[-0.761799,51.582659],"type":"Point"}
}
