{
  "type": "Feature",
  "properties": {
    "iso:country":"GB",
    "wof:name":"BS10 6NZ",
    "wof:placetype":"postalcode"
},
  "geometry": {"coordinates":[-2.60038112434747,51.51262571347716],"type":"Point"}
}