{
  "type": "Feature",
  "properties": {
    "iso:country":"GB",
    "wof:name":"PR7 4HD",
    "wof:placetype":"postalcode"
},
  "geometry": {"coordinates":[-2.60075689595805,53.60996457792361],"type":"Point"}
}