{
  "type": "Feature",
  "properties": {
    "date:inception_lower": "1997-06-01",
    "date:inception_upper": "1997-06-01",
    "iso:country": "GB",
    "wof:name": "PR7 4HD",
    "wof:placetype": "postalcode"
  },
  "geometry": {"coordinates":[-2.602103,53.610021],"type":"Point"}
}
