{
  "type": "Feature",
  "properties": {
    "date:inception_lower": "2018-01-01",
    "date:inception_upper": "2018-01-01",
    "iso:country": "GB",
    "wof:name": "OX11 0FU",
    "wof:placetype": "postalcode"
  },
  "geometry": {"coordinates":[-1.295576,51.604207],"type":"Point"}
}
