{
  "type": "Feature",
  "properties": {
    "iso:country": "GB",
    "wof:name": "LL18 4UG",
    "wof:placetype": "postalcode"
  },
  "geometry": {"coordinates":[-3.462263,53.310078],"type":"Point"}
}
