{
  "type": "Feature",
  "properties": {
    "iso:country":"GB",
    "wof:name":"SW9 8QL",
    "wof:placetype":"postalcode"
},
  "geometry": {"coordinates":[-0.10829160122738,51.4606034449077],"type":"Point"}
}