{
  "type": "Feature",
  "properties": {
    "iso:country":"GB",
    "wof:name":"PO33 3JH",
    "wof:placetype":"postalcode"
},
  "geometry": {"coordinates":[-1.17711915680073,50.71649858522544],"type":"Point"}
}