{
  "type": "Feature",
  "properties": {
    "iso:country": "GB",
    "wof:name": "DL12 8NB",
    "wof:placetype": "postalcode"
  },
  "geometry": {"coordinates":[-1.923965,54.543107],"type":"Point"}
}
