{
  "type": "Feature",
  "properties": {
    "iso:country":"GB",
    "wof:name":"LE4 3JG",
    "wof:placetype":"postalcode"
},
  "geometry": {"coordinates":[-1.1321820994048,52.6803796638255],"type":"Point"}
}