{
  "type": "Feature",
  "properties": {
    "date:inception_lower": "1980-01-01",
    "date:inception_upper": "1980-01-01",
    "iso:country": "GB",
    "wof:name": "DN39 6YN",
    "wof:placetype": "postalcode"
  },
  "geometry": {"coordinates":[-0.328215,53.585483],"type":"Point"}
}
