{
  "type": "Feature",
  "properties": {
    "iso:country":"GB",
    "wof:name":"DN39 6YN",
    "wof:placetype":"postalcode"
},
  "geometry": {"coordinates":[-0.32821087532666,53.58545212606895],"type":"Point"}
}