{
  "type": "Feature",
  "properties": {
    "iso:country":"GB",
    "wof:name":"DN9 2AF",
    "wof:placetype":"postalcode"
},
  "geometry": {"coordinates":[-0.85944427401083,53.49053443142135],"type":"Point"}
}