{
  "type": "Feature",
  "properties": {
    "iso:country":"GB",
    "wof:name":"GU9 7XN",
    "wof:placetype":"postalcode"
},
  "geometry": {"coordinates":[-0.80429131524797,51.2115211781471],"type":"Point"}
}