{
  "type": "Feature",
  "properties": {
    "iso:country": "GB",
    "wof:name": "GU9 7XN",
    "wof:placetype": "postalcode"
  },
  "geometry": {"coordinates":[-0.804291,51.211521],"type":"Point"}
}
