{
  "type": "Feature",
  "properties": {
    "iso:country":"GB",
    "wof:name":"M33 4HY",
    "wof:placetype":"postalcode"
},
  "geometry": {"coordinates":[-2.34866889022771,53.40866221310973],"type":"Point"}
}