{
  "type": "Feature",
  "properties": {
    "date:inception_lower": "1980-01-01",
    "date:inception_upper": "1980-01-01",
    "iso:country": "GB",
    "wof:name": "SK9 3AB",
    "wof:placetype": "postalcode"
  },
  "geometry": {"coordinates":[-2.213688,53.345645],"type":"Point"}
}
