{
  "type": "Feature",
  "properties": {
    "iso:country":"GB",
    "wof:name":"ML2 7HP",
    "wof:placetype":"postalcode"
},
  "geometry": {"coordinates":[-3.91318043802288,55.79392414942531],"type":"Point"}
}