{
  "type": "Feature",
  "properties": {
    "iso:country":"GB",
    "wof:name":"NW1 6AN",
    "wof:placetype":"postalcode"
},
  "geometry": {"coordinates":[-0.15902613269605,51.52341448596981],"type":"Point"}
}