{
  "type": "Feature",
  "properties": {
    "iso:country":"GB",
    "wof:name":"ME7 4BE",
    "wof:placetype":"postalcode"
},
  "geometry": {"coordinates":[0.55800279295129,51.37373195173205],"type":"Point"}
}