{
  "type": "Feature",
  "properties": {
    "iso:country":"GB",
    "wof:name":"NR11 6NN",
    "wof:placetype":"postalcode"
},
  "geometry": {"coordinates":[1.22474384337636,52.80425677149954],"type":"Point"}
}