{
  "type": "Feature",
  "properties": {
    "iso:country":"GB",
    "wof:name":"NW5 2SR",
    "wof:placetype":"postalcode"
},
  "geometry": {"coordinates":[-0.13259295612194,51.54796877490242],"type":"Point"}
}