{
  "type": "Feature",
  "properties": {
    "iso:country": "GB",
    "wof:name": "NW5 2SR",
    "wof:placetype": "postalcode"
  },
  "geometry": {"coordinates":[-0.132593,51.547969],"type":"Point"}
}
