{
  "type": "Feature",
  "properties": {
    "date:inception_lower": "1980-01-01",
    "date:inception_upper": "1980-01-01",
    "iso:country": "GB",
    "wof:name": "TS18 4LS",
    "wof:placetype": "postalcode"
  },
  "geometry": {"coordinates":[-1.332869,54.569422],"type":"Point"}
}
