{
  "type": "Feature",
  "properties": {
    "iso:country": "GB",
    "wof:name": "TS18 4LS",
    "wof:placetype": "postalcode"
  },
  "geometry": {"coordinates":[-1.332869,54.569422],"type":"Point"}
}
