{
  "type": "Feature",
  "properties": {
    "iso:country":"GB",
    "wof:name":"TS18 4LS",
    "wof:placetype":"postalcode"
},
  "geometry": {"coordinates":[-1.33286925238648,54.56942188480819],"type":"Point"}
}