{
  "type": "Feature",
  "properties": {
    "iso:country": "GB",
    "wof:name": "ML8 4LE",
    "wof:placetype": "postalcode"
  },
  "geometry": {"coordinates":[-3.828805,55.725714],"type":"Point"}
}
