{
  "type": "Feature",
  "properties": {
    "date:inception_lower":"2015-07-01",
    "date:inception_upper":"2015-07-31",
    "iso:country":"GB",
    "wof:name":"ML8 4LE",
    "wof:placetype":"postalcode"
},
  "geometry": {"coordinates":[-3.828805,55.725714],"type":"Point"}
}