{
  "type": "Feature",
  "properties": {
    "iso:country":"GB",
    "wof:name":"ML8 4LE",
    "wof:placetype":"postalcode"
},
  "geometry": {"coordinates":[-3.82883721954428,55.72571382137805],"type":"Point"}
}