{
  "type": "Feature",
  "properties": {
    "iso:country":"GB",
    "wof:name":"S64 8LX",
    "wof:placetype":"postalcode"
},
  "geometry": {"coordinates":[-1.30932852803265,53.48835296533083],"type":"Point"}
}