{
  "type": "Feature",
  "properties": {
    "iso:country": "GB",
    "wof:name": "S64 8LX",
    "wof:placetype": "postalcode"
  },
  "geometry": {"coordinates":[-1.309328,53.488353],"type":"Point"}
}
