{
  "type": "Feature",
  "properties": {
    "iso:country":"GB",
    "wof:name":"CF14 1JX",
    "wof:placetype":"postalcode"
},
  "geometry": {"coordinates":[-3.20709399135757,51.50661909667974],"type":"Point"}
}