{
  "type": "Feature",
  "properties": {
    "iso:country": "GB",
    "wof:name": "ST4 5DJ",
    "wof:placetype": "postalcode"
  },
  "geometry": {"coordinates":[-2.195044,53.002023],"type":"Point"}
}
