{
  "type": "Feature",
  "properties": {
    "iso:country": "GB",
    "wof:name": "BN1 6NL",
    "wof:placetype": "postalcode"
  },
  "geometry": {"coordinates":[-0.139848,50.851464],"type":"Point"}
}
