{
  "type": "Feature",
  "properties": {
    "iso:country":"GB",
    "wof:name":"CM2 8QY",
    "wof:placetype":"postalcode"
},
  "geometry": {"coordinates":[0.47183222385574,51.69923298219319],"type":"Point"}
}