{
  "type": "Feature",
  "properties": {
    "iso:country":"GB",
    "wof:name":"NP20 5LY",
    "wof:placetype":"postalcode"
},
  "geometry": {"coordinates":[-2.99968567637118,51.59902708430476],"type":"Point"}
}