{
  "type": "Feature",
  "properties": {
    "iso:country":"GB",
    "wof:name":"HU10 7QH",
    "wof:placetype":"postalcode"
},
  "geometry": {"coordinates":[-0.45053045051548,53.75306500971212],"type":"Point"}
}