{
  "type": "Feature",
  "properties": {
    "date:inception_lower": "1980-01-01",
    "date:inception_upper": "1980-01-01",
    "iso:country": "GB",
    "wof:name": "HU10 7QH",
    "wof:placetype": "postalcode"
  },
  "geometry": {"coordinates":[-0.45053,53.753065],"type":"Point"}
}
