{
  "type": "Feature",
  "properties": {
    "iso:country":"GB",
    "wof:name":"BR3 3JF",
    "wof:placetype":"postalcode"
},
  "geometry": {"coordinates":[-0.03307302206622,51.39331381061785],"type":"Point"}
}