{
  "type": "Feature",
  "properties": {
    "iso:country": "GB",
    "wof:name": "PE23 4PX",
    "wof:placetype": "postalcode"
  },
  "geometry": {"coordinates":[0.111538,53.194179],"type":"Point"}
}
