{
  "type": "Feature",
  "properties": {
    "iso:country": "GB",
    "wof:name": "CM15 0QU",
    "wof:placetype": "postalcode"
  },
  "geometry": {"coordinates":[0.302241,51.662657],"type":"Point"}
}
