{
  "type": "Feature",
  "properties": {
    "iso:country":"GB",
    "wof:name":"SK6 3AH",
    "wof:placetype":"postalcode"
},
  "geometry": {"coordinates":[-2.09183976529572,53.41438575351063],"type":"Point"}
}