{
  "type": "Feature",
  "properties": {
    "date:inception_lower": "1980-01-01",
    "date:inception_upper": "1980-01-01",
    "iso:country": "GB",
    "wof:name": "SK6 3AH",
    "wof:placetype": "postalcode"
  },
  "geometry": {"coordinates":[-2.09184,53.414386],"type":"Point"}
}
