{
  "type": "Feature",
  "properties": {
    "iso:country":"GB",
    "wof:name":"AL5 5SY",
    "wof:placetype":"postalcode"
},
  "geometry": {"coordinates":[-0.33813700528721,51.81218045534553],"type":"Point"}
}