{
  "type": "Feature",
  "properties": {
    "iso:country": "GB",
    "wof:name": "HX1 4RR",
    "wof:placetype": "postalcode"
  },
  "geometry": {"coordinates":[-1.886518,53.727904],"type":"Point"}
}
