{
  "type": "Feature",
  "properties": {
    "date:inception_lower": "2008-09-01",
    "date:inception_upper": "2008-09-01",
    "iso:country": "GB",
    "wof:name": "HX1 4RR",
    "wof:placetype": "postalcode"
  },
  "geometry": {"coordinates":[-1.886518,53.727904],"type":"Point"}
}
