{
  "type": "Feature",
  "properties": {
    "iso:country": "GB",
    "wof:name": "HU17 9AF",
    "wof:placetype": "postalcode"
  },
  "geometry": {"coordinates":[-0.414938,53.847146],"type":"Point"}
}
