{
  "type": "Feature",
  "properties": {
    "iso:country":"GB",
    "wof:name":"HU17 9AF",
    "wof:placetype":"postalcode"
},
  "geometry": {"coordinates":[-0.41486086184277,53.8471717661636],"type":"Point"}
}