{
  "type": "Feature",
  "properties": {
    "iso:country": "GB",
    "wof:name": "BH24 1NQ",
    "wof:placetype": "postalcode"
  },
  "geometry": {"coordinates":[-1.786205,50.842475],"type":"Point"}
}
