{
  "type": "Feature",
  "properties": {
    "iso:country":"GB",
    "wof:name":"RG7 4BP",
    "wof:placetype":"postalcode"
},
  "geometry": {"coordinates":[-1.09485058690459,51.41687122233352],"type":"Point"}
}