{
  "type": "Feature",
  "properties": {
    "iso:country":"GB",
    "wof:name":"WA13 9DP",
    "wof:placetype":"postalcode"
},
  "geometry": {"coordinates":[-2.47737556341928,53.38309351530491],"type":"Point"}
}