{
  "type": "Feature",
  "properties": {
    "iso:country":"GB",
    "wof:name":"SL6 9RL",
    "wof:placetype":"postalcode"
},
  "geometry": {"coordinates":[-0.72228673036361,51.55931562044553],"type":"Point"}
}