{
  "type": "Feature",
  "properties": {
    "date:inception_lower": "1991-09-01",
    "date:inception_upper": "1991-09-01",
    "iso:country": "GB",
    "wof:name": "LS8 5JB",
    "wof:placetype": "postalcode"
  },
  "geometry": {"coordinates":[-1.516411,53.813433],"type":"Point"}
}
