{
  "type": "Feature",
  "properties": {
    "iso:country":"GB",
    "wof:name":"LS8 5JB",
    "wof:placetype":"postalcode"
},
  "geometry": {"coordinates":[-1.51641112437562,53.81343287828966],"type":"Point"}
}