{
  "type": "Feature",
  "properties": {
    "iso:country":"GB",
    "wof:name":"CR8 2JR",
    "wof:placetype":"postalcode"
},
  "geometry": {"coordinates":[-0.11668015920952,51.34485874556362],"type":"Point"}
}