{
  "type": "Feature",
  "properties": {
    "date:inception_lower": "1999-12-01",
    "date:inception_upper": "1999-12-01",
    "iso:country": "GB",
    "wof:name": "TW19 7DB",
    "wof:placetype": "postalcode"
  },
  "geometry": {"coordinates":[-0.471918,51.454694],"type":"Point"}
}
