{
  "type": "Feature",
  "properties": {
    "iso:country": "GB",
    "wof:name": "TW19 7DB",
    "wof:placetype": "postalcode"
  },
  "geometry": {"coordinates":[-0.472421,51.454727],"type":"Point"}
}
