{
  "type": "Feature",
  "properties": {
    "date:inception_lower": "1980-01-01",
    "date:inception_upper": "1980-01-01",
    "iso:country": "GB",
    "wof:name": "NR20 3QD",
    "wof:placetype": "postalcode"
  },
  "geometry": {"coordinates":[1.035799,52.658682],"type":"Point"}
}
