{
  "type": "Feature",
  "properties": {
    "date:inception_lower":"2008-01-01",
    "date:inception_upper":"2008-01-31",
    "iso:country":"GB",
    "wof:name":"BA15 1ZY",
    "wof:placetype":"postalcode"
},
  "geometry": {"coordinates":[-2.251174,51.336364],"type":"Point"}
}