{
  "type": "Feature",
  "properties": {
    "iso:country":"GB",
    "wof:name":"PA23 8ES",
    "wof:placetype":"postalcode"
},
  "geometry": {"coordinates":[-4.92684110884211,55.95564903634931],"type":"Point"}
}