{
  "type": "Feature",
  "properties": {
    "date:inception_lower":"1980-01-01",
    "date:inception_upper":"1980-01-31",
    "iso:country":"GB",
    "wof:name":"SK9 4DA",
    "wof:placetype":"postalcode"
},
  "geometry": {"coordinates":[-2.227944,53.33727],"type":"Point"}
}