{
  "type": "Feature",
  "properties": {
    "iso:country":"GB",
    "wof:name":"E17 7LH",
    "wof:placetype":"postalcode"
},
  "geometry": {"coordinates":[-0.03694933091059,51.5802194107852],"type":"Point"}
}