{
  "type": "Feature",
  "properties": {
    "date:inception_lower": "1997-06-01",
    "date:inception_upper": "1997-06-01",
    "iso:country": "GB",
    "wof:name": "HG3 3UB",
    "wof:placetype": "postalcode"
  },
  "geometry": {"coordinates":[-1.493691,54.095323],"type":"Point"}
}
