{
  "type": "Feature",
  "properties": {
    "iso:country": "GB",
    "wof:name": "HG3 3UB",
    "wof:placetype": "postalcode"
  },
  "geometry": {"coordinates":[-1.493691,54.095323],"type":"Point"}
}
