{
  "type": "Feature",
  "properties": {
    "iso:country":"GB",
    "wof:name":"HG3 3UB",
    "wof:placetype":"postalcode"
},
  "geometry": {"coordinates":[-1.4936908874771,54.09532325919679],"type":"Point"}
}