{
  "type": "Feature",
  "properties": {
    "iso:country":"GB",
    "wof:name":"WS3 2TP",
    "wof:placetype":"postalcode"
},
  "geometry": {"coordinates":[-2.02216054813011,52.62543382712571],"type":"Point"}
}