{
  "type": "Feature",
  "properties": {
    "iso:country": "GB",
    "wof:name": "SW4 9JP",
    "wof:placetype": "postalcode"
  },
  "geometry": {"coordinates":[-0.141605,51.455219],"type":"Point"}
}
