{
  "type": "Feature",
  "properties": {
    "iso:country":"GB",
    "wof:name":"SW4 9JP",
    "wof:placetype":"postalcode"
},
  "geometry": {"coordinates":[-0.14160548266026,51.45521913549743],"type":"Point"}
}