{
  "type": "Feature",
  "properties": {
    "date:inception_lower": "2016-11-01",
    "date:inception_upper": "2016-11-01",
    "iso:country": "GB",
    "wof:name": "CV6 5ER",
    "wof:placetype": "postalcode"
  },
  "geometry": {"coordinates":[-1.50091,52.423324],"type":"Point"}
}
