{
  "type": "Feature",
  "properties": {
    "iso:country": "GB",
    "wof:name": "CV6 5ER",
    "wof:placetype": "postalcode"
  },
  "geometry": {"coordinates":[-1.50091,52.423315],"type":"Point"}
}
