{
  "type": "Feature",
  "properties": {
    "iso:country":"GB",
    "wof:name":"BN17 7NY",
    "wof:placetype":"postalcode"
},
  "geometry": {"coordinates":[-0.55003641406624,50.82031068672965],"type":"Point"}
}