{
  "type": "Feature",
  "properties": {
    "iso:country":"GB",
    "wof:name":"HR2 7DQ",
    "wof:placetype":"postalcode"
},
  "geometry": {"coordinates":[-2.73211125671231,52.03583120745417],"type":"Point"}
}