{
  "type": "Feature",
  "properties": {
    "iso:country":"GB",
    "wof:name":"NN7 3BJ",
    "wof:placetype":"postalcode"
},
  "geometry": {"coordinates":[-0.93963238809235,52.17477436048376],"type":"Point"}
}