{
  "type": "Feature",
  "properties": {
    "iso:country": "GB",
    "wof:name": "NN7 3BJ",
    "wof:placetype": "postalcode"
  },
  "geometry": {"coordinates":[-0.939632,52.174774],"type":"Point"}
}
