{
  "type": "Feature",
  "properties": {
    "date:inception_lower": "1996-06-01",
    "date:inception_upper": "1996-06-01",
    "iso:country": "GB",
    "wof:name": "TS24 8PH",
    "wof:placetype": "postalcode"
  },
  "geometry": {"coordinates":[-1.213978,54.695227],"type":"Point"}
}
