{
  "type": "Feature",
  "properties": {
    "iso:country":"GB",
    "wof:name":"TS24 8PH",
    "wof:placetype":"postalcode"
},
  "geometry": {"coordinates":[-1.21397786623716,54.69522703389634],"type":"Point"}
}