{
  "type": "Feature",
  "properties": {
    "date:inception_lower": "1980-01-01",
    "date:inception_upper": "1980-01-01",
    "iso:country": "GB",
    "wof:name": "HP5 2UA",
    "wof:placetype": "postalcode"
  },
  "geometry": {"coordinates":[-0.678156,51.741315],"type":"Point"}
}
