{
  "type": "Feature",
  "properties": {
    "iso:country": "GB",
    "wof:name": "HP5 2UA",
    "wof:placetype": "postalcode"
  },
  "geometry": {"coordinates":[-0.678156,51.741315],"type":"Point"}
}
