{
  "type": "Feature",
  "properties": {
    "iso:country": "GB",
    "wof:name": "AL4 8DA",
    "wof:placetype": "postalcode"
  },
  "geometry": {"coordinates":[-0.293661,51.811741],"type":"Point"}
}
