{
  "type": "Feature",
  "properties": {
    "date:inception_lower":"1980-01-01",
    "date:inception_upper":"1980-01-31",
    "iso:country":"GB",
    "wof:name":"AL4 8DA",
    "wof:placetype":"postalcode"
},
  "geometry": {"coordinates":[-0.293661,51.811741],"type":"Point"}
}