{
  "type": "Feature",
  "properties": {
    "date:inception_lower":"1980-01-01",
    "date:inception_upper":"1980-01-31",
    "iso:country":"GB",
    "wof:name":"B78 1PG",
    "wof:placetype":"postalcode"
},
  "geometry": {"coordinates":[-1.618315,52.604973],"type":"Point"}
}