{
  "type": "Feature",
  "properties": {
    "iso:country": "GB",
    "wof:name": "B78 1PG",
    "wof:placetype": "postalcode"
  },
  "geometry": {"coordinates":[-1.618315,52.604973],"type":"Point"}
}
