{
  "type": "Feature",
  "properties": {
    "iso:country":"GB",
    "wof:name":"B78 1PG",
    "wof:placetype":"postalcode"
},
  "geometry": {"coordinates":[-1.61831478598805,52.60497250816422],"type":"Point"}
}