{
  "type": "Feature",
  "properties": {
    "iso:country":"GB",
    "wof:name":"SK2 7HD",
    "wof:placetype":"postalcode"
},
  "geometry": {"coordinates":[-2.13246881612081,53.38795709278543],"type":"Point"}
}