{
  "type": "Feature",
  "properties": {
    "iso:country":"GB",
    "wof:name":"B24 0QQ",
    "wof:placetype":"postalcode"
},
  "geometry": {"coordinates":[-1.79806546350861,52.52371521812841],"type":"Point"}
}