{
  "type": "Feature",
  "properties": {
    "iso:country":"GB",
    "wof:name":"IP17 3LN",
    "wof:placetype":"postalcode"
},
  "geometry": {"coordinates":[1.53871831699774,52.25496548491629],"type":"Point"}
}