{
  "type": "Feature",
  "properties": {
    "iso:country":"GB",
    "wof:name":"TN8 7JJ",
    "wof:placetype":"postalcode"
},
  "geometry": {"coordinates":[0.09389400590739,51.14220187190537],"type":"Point"}
}