{
  "type": "Feature",
  "properties": {
    "iso:country": "GB",
    "wof:name": "E16 1SD",
    "wof:placetype": "postalcode"
  },
  "geometry": {"coordinates":[0.018981,51.504964],"type":"Point"}
}
