{
  "type": "Feature",
  "properties": {
    "iso:country": "GB",
    "wof:name": "PE20 1PW",
    "wof:placetype": "postalcode"
  },
  "geometry": {"coordinates":[-0.085058,52.93124],"type":"Point"}
}
