{
  "type": "Feature",
  "properties": {
    "iso:country": "GB",
    "wof:name": "RG26 4HF",
    "wof:placetype": "postalcode"
  },
  "geometry": {"coordinates":[-1.15427,51.356062],"type":"Point"}
}
