{
  "type": "Feature",
  "properties": {
    "iso:country":"GB",
    "wof:name":"RG26 4HF",
    "wof:placetype":"postalcode"
},
  "geometry": {"coordinates":[-1.15427001347711,51.35606237202372],"type":"Point"}
}