{
  "type": "Feature",
  "properties": {
    "date:inception_lower":"2002-06-01",
    "date:inception_upper":"2002-06-30",
    "iso:country":"GB",
    "wof:name":"DE23 1JY",
    "wof:placetype":"postalcode"
},
  "geometry": {"coordinates":[-1.489287,52.88909],"type":"Point"}
}