{
  "type": "Feature",
  "properties": {
    "iso:country":"GB",
    "wof:name":"NW1 3LP",
    "wof:placetype":"postalcode"
},
  "geometry": {"coordinates":[-0.141833405651,51.52754970955565],"type":"Point"}
}