{
  "type": "Feature",
  "properties": {
    "iso:country":"GB",
    "wof:name":"TS10 4JP",
    "wof:placetype":"postalcode"
},
  "geometry": {"coordinates":[-1.06985173638849,54.60440816860853],"type":"Point"}
}