{
  "type": "Feature",
  "properties": {
    "iso:country":"GB",
    "wof:name":"CM0 7TR",
    "wof:placetype":"postalcode"
},
  "geometry": {"coordinates":[0.88114711230782,51.69861760129663],"type":"Point"}
}