{
  "type": "Feature",
  "properties": {
    "iso:country":"GB",
    "wof:name":"NG17 2TH",
    "wof:placetype":"postalcode"
},
  "geometry": {"coordinates":[-1.29481889044181,53.12182698762545],"type":"Point"}
}