{
  "type": "Feature",
  "properties": {
    "date:inception_lower":"2010-07-01",
    "date:inception_upper":"2010-07-31",
    "iso:country":"GB",
    "wof:name":"NG17 2TH",
    "wof:placetype":"postalcode"
},
  "geometry": {"coordinates":[-1.294819,53.121827],"type":"Point"}
}