{
  "type": "Feature",
  "properties": {
    "iso:country": "GB",
    "wof:name": "NG17 2TH",
    "wof:placetype": "postalcode"
  },
  "geometry": {"coordinates":[-1.294819,53.121827],"type":"Point"}
}
