{
  "type": "Feature",
  "properties": {
    "iso:country": "GB",
    "wof:name": "OL10 1LT",
    "wof:placetype": "postalcode"
  },
  "geometry": {"coordinates":[-2.217457,53.592893],"type":"Point"}
}
