{
  "type": "Feature",
  "properties": {
    "iso:country": "GB",
    "wof:name": "KA7 2QN",
    "wof:placetype": "postalcode"
  },
  "geometry": {"coordinates":[-4.626238,55.445036],"type":"Point"}
}
