{
  "type": "Feature",
  "properties": {
    "iso:country": "GB",
    "wof:name": "ME19 5QD",
    "wof:placetype": "postalcode"
  },
  "geometry": {"coordinates":[0.427851,51.303223],"type":"Point"}
}
