{
  "type": "Feature",
  "properties": {
    "iso:country":"GB",
    "wof:name":"ME19 5QD",
    "wof:placetype":"postalcode"
},
  "geometry": {"coordinates":[0.42785073647311,51.30322340888139],"type":"Point"}
}