{
  "type": "Feature",
  "properties": {
    "date:inception_lower": "2020-12-01",
    "date:inception_upper": "2020-12-01",
    "iso:country": "GB",
    "wof:name": "SA5 9FA",
    "wof:placetype": "postalcode"
  },
  "geometry": {"coordinates":[-3.949639,51.651399],"type":"Point"}
}
