{
  "type": "Feature",
  "properties": {
    "iso:country":"GB",
    "wof:name":"B14 4NZ",
    "wof:placetype":"postalcode"
},
  "geometry": {"coordinates":[-1.87662436511313,52.40710601650958],"type":"Point"}
}