{
  "type": "Feature",
  "properties": {
    "iso:country":"GB",
    "wof:name":"DH7 9BD",
    "wof:placetype":"postalcode"
},
  "geometry": {"coordinates":[-1.73946888643238,54.75894485466144],"type":"Point"}
}