{
  "type": "Feature",
  "properties": {
    "date:inception_lower": "1980-01-01",
    "date:inception_upper": "1980-01-01",
    "iso:country": "GB",
    "wof:name": "DH7 9BD",
    "wof:placetype": "postalcode"
  },
  "geometry": {"coordinates":[-1.739469,54.758945],"type":"Point"}
}
