{
  "type": "Feature",
  "properties": {
    "iso:country":"GB",
    "wof:name":"TN8 7BA",
    "wof:placetype":"postalcode"
},
  "geometry": {"coordinates":[0.15569960000955,51.19560531530989],"type":"Point"}
}