{
  "type": "Feature",
  "properties": {
    "iso:country":"GB",
    "wof:name":"HD9 3EF",
    "wof:placetype":"postalcode"
},
  "geometry": {"coordinates":[-1.79099811889066,53.58424590537584],"type":"Point"}
}