{
  "type": "Feature",
  "properties": {
    "iso:country": "GB",
    "wof:name": "HD9 3EF",
    "wof:placetype": "postalcode"
  },
  "geometry": {"coordinates":[-1.790998,53.584246],"type":"Point"}
}
