{
  "type": "Feature",
  "properties": {
    "iso:country":"GB",
    "wof:name":"NN14 6FD",
    "wof:placetype":"postalcode"
},
  "geometry": {"coordinates":[-0.80076107436686,52.42411519837876],"type":"Point"}
}