{
  "type": "Feature",
  "properties": {
    "iso:country":"GB",
    "wof:name":"PE2 7EE",
    "wof:placetype":"postalcode"
},
  "geometry": {"coordinates":[-0.29030931950152,52.55468817866455],"type":"Point"}
}