{
  "type": "Feature",
  "properties": {
    "date:inception_lower": "1980-01-01",
    "date:inception_upper": "1980-01-01",
    "iso:country": "GB",
    "wof:name": "CM24 8JE",
    "wof:placetype": "postalcode"
  },
  "geometry": {"coordinates":[0.192132,51.906462],"type":"Point"}
}
