{
  "type": "Feature",
  "properties": {
    "date:inception_lower": "1992-01-01",
    "date:inception_upper": "1992-01-01",
    "iso:country": "GB",
    "wof:name": "B60 3DX",
    "wof:placetype": "postalcode"
  },
  "geometry": {"coordinates":[-2.063878,52.314964],"type":"Point"}
}
