{
  "type": "Feature",
  "properties": {
    "iso:country":"GB",
    "wof:name":"IP17 2QA",
    "wof:placetype":"postalcode"
},
  "geometry": {"coordinates":[1.49243577941892,52.2227417328279],"type":"Point"}
}