{
  "type": "Feature",
  "properties": {
    "date:inception_lower": "1980-01-01",
    "date:inception_upper": "1980-01-01",
    "iso:country": "GB",
    "wof:name": "IP17 2QA",
    "wof:placetype": "postalcode"
  },
  "geometry": {"coordinates":[1.492436,52.222742],"type":"Point"}
}
