{
  "type": "Feature",
  "properties": {
    "iso:country":"GB",
    "wof:name":"CF31 1DX",
    "wof:placetype":"postalcode"
},
  "geometry": {"coordinates":[-3.57733107675332,51.50515473501918],"type":"Point"}
}