{
  "type": "Feature",
  "properties": {
    "iso:country": "GB",
    "wof:name": "NN11 3DN",
    "wof:placetype": "postalcode"
  },
  "geometry": {"coordinates":[-1.187924,52.166081],"type":"Point"}
}
