{
  "type": "Feature",
  "properties": {
    "iso:country": "GB",
    "wof:name": "DN9 1ER",
    "wof:placetype": "postalcode"
  },
  "geometry": {"coordinates":[-0.820158,53.525543],"type":"Point"}
}
