{
  "type": "Feature",
  "properties": {
    "iso:country":"GB",
    "wof:name":"DN9 1ER",
    "wof:placetype":"postalcode"
},
  "geometry": {"coordinates":[-0.82015785654846,53.52554263343659],"type":"Point"}
}