{
  "type": "Feature",
  "properties": {
    "date:inception_lower": "1980-01-01",
    "date:inception_upper": "1980-01-01",
    "iso:country": "GB",
    "wof:name": "KY7 6PN",
    "wof:placetype": "postalcode"
  },
  "geometry": {"coordinates":[-3.101979,56.194034],"type":"Point"}
}
