{
  "type": "Feature",
  "properties": {
    "iso:country": "GB",
    "wof:name": "KY7 6PN",
    "wof:placetype": "postalcode"
  },
  "geometry": {"coordinates":[-3.101961,56.19405],"type":"Point"}
}
