{
  "type": "Feature",
  "properties": {
    "iso:country":"GB",
    "wof:name":"NN9 5YA",
    "wof:placetype":"postalcode"
},
  "geometry": {"coordinates":[-0.61769922193607,52.31670906984811],"type":"Point"}
}