{
  "type": "Feature",
  "properties": {
    "date:inception_lower": "1992-08-01",
    "date:inception_upper": "1992-08-01",
    "iso:country": "GB",
    "wof:name": "NN9 5YA",
    "wof:placetype": "postalcode"
  },
  "geometry": {"coordinates":[-0.617699,52.316709],"type":"Point"}
}
