{
  "type": "Feature",
  "properties": {
    "iso:country":"GB",
    "wof:name":"BN18 0DN",
    "wof:placetype":"postalcode"
},
  "geometry": {"coordinates":[-0.60860772806815,50.8305114791015],"type":"Point"}
}