{
  "type": "Feature",
  "properties": {
    "iso:country":"GB",
    "wof:name":"LL30 3EA",
    "wof:placetype":"postalcode"
},
  "geometry": {"coordinates":[-3.78369924914199,53.31476499087303],"type":"Point"}
}