{
  "type": "Feature",
  "properties": {
    "iso:country":"GB",
    "wof:name":"SP5 4AS",
    "wof:placetype":"postalcode"
},
  "geometry": {"coordinates":[-1.88211161508699,51.03859935861325],"type":"Point"}
}