{
  "type": "Feature",
  "properties": {
    "iso:country": "GB",
    "wof:name": "SP5 4AS",
    "wof:placetype": "postalcode"
  },
  "geometry": {"coordinates":[-1.882112,51.038599],"type":"Point"}
}
