{
  "type": "Feature",
  "properties": {
    "iso:country":"GB",
    "wof:name":"DN15 9NL",
    "wof:placetype":"postalcode"
},
  "geometry": {"coordinates":[-0.59392402522025,53.68797349101593],"type":"Point"}
}