{
  "type": "Feature",
  "properties": {
    "date:inception_lower": "2022-07-01",
    "date:inception_upper": "2022-07-01",
    "iso:country": "GB",
    "wof:name": "HG5 0UE",
    "wof:placetype": "postalcode"
  },
  "geometry": {"coordinates":[-1.467997,54.012541],"type":"Point"}
}
