{
  "type": "Feature",
  "properties": {
    "date:inception_lower":"1980-01-01",
    "date:inception_upper":"1980-01-31",
    "iso:country":"GB",
    "wof:name":"S5 9QG",
    "wof:placetype":"postalcode"
},
  "geometry": {"coordinates":[-1.488635,53.429094],"type":"Point"}
}