{
  "type": "Feature",
  "properties": {
    "iso:country":"GB",
    "wof:name":"S5 9QG",
    "wof:placetype":"postalcode"
},
  "geometry": {"coordinates":[-1.48863473290111,53.42909369480274],"type":"Point"}
}