{
  "type": "Feature",
  "properties": {
    "date:inception_lower": "2000-06-01",
    "date:inception_upper": "2000-06-01",
    "iso:country": "GB",
    "wof:name": "SN25 1HU",
    "wof:placetype": "postalcode"
  },
  "geometry": {"coordinates":[-1.806037,51.589963],"type":"Point"}
}
