{
  "type": "Feature",
  "properties": {
    "iso:country":"GB",
    "wof:name":"KW10 6SB",
    "wof:placetype":"postalcode"
},
  "geometry": {"coordinates":[-3.97146914639085,57.97908435330496],"type":"Point"}
}