{
  "type": "Feature",
  "properties": {
    "date:inception_lower": "1980-01-01",
    "date:inception_upper": "1980-01-01",
    "iso:country": "GB",
    "wof:name": "NE61 6SE",
    "wof:placetype": "postalcode"
  },
  "geometry": {"coordinates":[-1.649177,55.177873],"type":"Point"}
}
