{
  "type": "Feature",
  "properties": {
    "iso:country":"GB",
    "wof:name":"RM14 2QW",
    "wof:placetype":"postalcode"
},
  "geometry": {"coordinates":[0.23981471541723,51.55874275587266],"type":"Point"}
}