{
  "type": "Feature",
  "properties": {
    "iso:country":"GB",
    "wof:name":"NN14 1JX",
    "wof:placetype":"postalcode"
},
  "geometry": {"coordinates":[-0.79688854938045,52.39889328576722],"type":"Point"}
}