{
  "type": "Feature",
  "properties": {
    "iso:country": "GB",
    "wof:name": "AB43 9PQ",
    "wof:placetype": "postalcode"
  },
  "geometry": {"coordinates":[-2.012448,57.688007],"type":"Point"}
}
