{
  "type": "Feature",
  "properties": {
    "iso:country":"GB",
    "wof:name":"AB43 9PQ",
    "wof:placetype":"postalcode"
},
  "geometry": {"coordinates":[-2.01244784997621,57.68800709990195],"type":"Point"}
}