{
  "type": "Feature",
  "properties": {
    "iso:country": "GB",
    "wof:name": "LL18 5LX",
    "wof:placetype": "postalcode"
  },
  "geometry": {"coordinates":[-3.518559,53.304439],"type":"Point"}
}
