{
  "type": "Feature",
  "properties": {
    "iso:country": "GB",
    "wof:name": "SY16 1EQ",
    "wof:placetype": "postalcode"
  },
  "geometry": {"coordinates":[-3.317405,52.512269],"type":"Point"}
}
