{
  "type": "Feature",
  "properties": {
    "iso:country":"GB",
    "wof:name":"SY16 1EQ",
    "wof:placetype":"postalcode"
},
  "geometry": {"coordinates":[-3.31740221250067,52.51225441958825],"type":"Point"}
}