{
  "type": "Feature",
  "properties": {
    "date:inception_lower": "1980-01-01",
    "date:inception_upper": "1980-01-01",
    "iso:country": "GB",
    "wof:name": "SY16 1EQ",
    "wof:placetype": "postalcode"
  },
  "geometry": {"coordinates":[-3.317404,52.512233],"type":"Point"}
}
