{
  "type": "Feature",
  "properties": {
    "iso:country":"GB",
    "wof:name":"AL9 6EA",
    "wof:placetype":"postalcode"
},
  "geometry": {"coordinates":[-0.17300471394585,51.74575187583354],"type":"Point"}
}