{
  "type": "Feature",
  "properties": {
    "date:inception_lower":"1980-01-01",
    "date:inception_upper":"1980-01-31",
    "iso:country":"GB",
    "wof:name":"BL8 3DH",
    "wof:placetype":"postalcode"
},
  "geometry": {"coordinates":[-2.343172,53.596267],"type":"Point"}
}