{
  "type": "Feature",
  "properties": {
    "iso:country":"GB",
    "wof:name":"BL8 3DH",
    "wof:placetype":"postalcode"
},
  "geometry": {"coordinates":[-2.34317179752004,53.59626707396534],"type":"Point"}
}