{
  "type": "Feature",
  "properties": {
    "date:inception_lower": "1980-01-01",
    "date:inception_upper": "1980-01-01",
    "iso:country": "GB",
    "wof:name": "LA11 6SD",
    "wof:placetype": "postalcode"
  },
  "geometry": {"coordinates":[-2.867555,54.266658],"type":"Point"}
}
