{
  "type": "Feature",
  "properties": {
    "date:inception_lower": "1980-01-01",
    "date:inception_upper": "1980-01-01",
    "iso:country": "GB",
    "wof:name": "W5 4XH",
    "wof:placetype": "postalcode"
  },
  "geometry": {"coordinates":[-0.307956,51.496747],"type":"Point"}
}
