{
  "type": "Feature",
  "properties": {
    "iso:country":"GB",
    "wof:name":"W5 4XH",
    "wof:placetype":"postalcode"
},
  "geometry": {"coordinates":[-0.30795639880103,51.49674692984844],"type":"Point"}
}