{
  "type": "Feature",
  "properties": {
    "iso:country":"GB",
    "wof:name":"NR34 9QA",
    "wof:placetype":"postalcode"
},
  "geometry": {"coordinates":[1.56476679629034,52.45706243688105],"type":"Point"}
}