{
  "type": "Feature",
  "properties": {
    "iso:country": "GB",
    "wof:name": "AL1 3DP",
    "wof:placetype": "postalcode"
  },
  "geometry": {"coordinates":[-0.338379,51.753125],"type":"Point"}
}
