{
  "type": "Feature",
  "properties": {
    "iso:country":"GB",
    "wof:name":"AL1 3DP",
    "wof:placetype":"postalcode"
},
  "geometry": {"coordinates":[-0.33837869739656,51.75312499629368],"type":"Point"}
}