{
  "type": "Feature",
  "properties": {
    "iso:country":"GB",
    "wof:name":"CF15 9YY",
    "wof:placetype":"postalcode"
},
  "geometry": {"coordinates":[-3.26143411946045,51.5349201960075],"type":"Point"}
}