{
  "type": "Feature",
  "properties": {
    "iso:country":"GB",
    "wof:name":"CR9 6AZ",
    "wof:placetype":"postalcode"
},
  "geometry": {"coordinates":[-0.09133416758678,51.37669654240222],"type":"Point"}
}