{
  "type": "Feature",
  "properties": {
    "iso:country":"GB",
    "wof:name":"PO9 1DP",
    "wof:placetype":"postalcode"
},
  "geometry": {"coordinates":[-0.98828567974071,50.85587727517861],"type":"Point"}
}