{
  "type": "Feature",
  "properties": {
    "iso:country": "GB",
    "wof:name": "PO9 1DP",
    "wof:placetype": "postalcode"
  },
  "geometry": {"coordinates":[-0.988286,50.855877],"type":"Point"}
}
