{
  "type": "Feature",
  "properties": {
    "iso:country":"GB",
    "wof:name":"SP2 9NB",
    "wof:placetype":"postalcode"
},
  "geometry": {"coordinates":[-1.81864080619301,51.07207699062151],"type":"Point"}
}