{
  "type": "Feature",
  "properties": {
    "date:inception_lower": "1980-01-01",
    "date:inception_upper": "1980-01-01",
    "iso:country": "GB",
    "wof:name": "SP2 9NB",
    "wof:placetype": "postalcode"
  },
  "geometry": {"coordinates":[-1.818641,51.072077],"type":"Point"}
}
