{
  "type": "Feature",
  "properties": {
    "iso:country":"GB",
    "wof:name":"ZE1 0GF",
    "wof:placetype":"postalcode"
},
  "geometry": {"coordinates":[-1.16271286262626,60.14655948304878],"type":"Point"}
}