{
  "type": "Feature",
  "properties": {
    "date:inception_lower": "1994-05-01",
    "date:inception_upper": "1994-05-01",
    "iso:country": "GB",
    "wof:name": "ZE1 0GF",
    "wof:placetype": "postalcode"
  },
  "geometry": {"coordinates":[-1.162847,60.146534],"type":"Point"}
}
