{
  "type": "Feature",
  "properties": {
    "date:inception_lower":"1999-06-01",
    "date:inception_upper":"1999-06-30",
    "iso:country":"GB",
    "wof:name":"PO21 2FB",
    "wof:placetype":"postalcode"
},
  "geometry": {"coordinates":[-0.68694,50.782469],"type":"Point"}
}