{
  "type": "Feature",
  "properties": {
    "iso:country": "GB",
    "wof:name": "PO21 2FB",
    "wof:placetype": "postalcode"
  },
  "geometry": {"coordinates":[-0.68694,50.782469],"type":"Point"}
}
