{
  "type": "Feature",
  "properties": {
    "iso:country":"GB",
    "wof:name":"PO21 2FB",
    "wof:placetype":"postalcode"
},
  "geometry": {"coordinates":[-0.68696074584115,50.78247944466627],"type":"Point"}
}