{
  "type": "Feature",
  "properties": {
    "iso:country":"GB",
    "wof:name":"BS36 2UR",
    "wof:placetype":"postalcode"
},
  "geometry": {"coordinates":[-2.46701665621613,51.51006774439848],"type":"Point"}
}