{
  "type": "Feature",
  "properties": {
    "iso:country": "GB",
    "wof:name": "IP11 9DW",
    "wof:placetype": "postalcode"
  },
  "geometry": {"coordinates":[1.33714,51.9745],"type":"Point"}
}
