{
  "type": "Feature",
  "properties": {
    "date:inception_lower": "1980-01-01",
    "date:inception_upper": "1980-01-01",
    "iso:country": "GB",
    "wof:name": "CR0 3JN",
    "wof:placetype": "postalcode"
  },
  "geometry": {"coordinates":[-0.118129,51.384144],"type":"Point"}
}
