{
  "type": "Feature",
  "properties": {
    "iso:country":"GB",
    "wof:name":"CR0 3JN",
    "wof:placetype":"postalcode"
},
  "geometry": {"coordinates":[-0.11812892312866,51.38414432317359],"type":"Point"}
}