{
  "type": "Feature",
  "properties": {
    "iso:country":"GB",
    "wof:name":"OX16 5HP",
    "wof:placetype":"postalcode"
},
  "geometry": {"coordinates":[-1.34017892730879,52.05746153936605],"type":"Point"}
}