{
  "type": "Feature",
  "properties": {
    "date:inception_lower": "1996-06-01",
    "date:inception_upper": "1996-06-01",
    "iso:country": "GB",
    "wof:name": "CA13 0JR",
    "wof:placetype": "postalcode"
  },
  "geometry": {"coordinates":[-3.382368,54.668713],"type":"Point"}
}
