{
  "type": "Feature",
  "properties": {
    "iso:country":"GB",
    "wof:name":"CA13 0JR",
    "wof:placetype":"postalcode"
},
  "geometry": {"coordinates":[-3.38236791798532,54.6687127562564],"type":"Point"}
}