{
  "type": "Feature",
  "properties": {
    "iso:country": "GB",
    "wof:name": "KY15 4BN",
    "wof:placetype": "postalcode"
  },
  "geometry": {"coordinates":[-3.008275,56.321437],"type":"Point"}
}
