{
  "type": "Feature",
  "properties": {
    "iso:country":"GB",
    "wof:name":"KY15 4BN",
    "wof:placetype":"postalcode"
},
  "geometry": {"coordinates":[-3.00827529534611,56.32143713037438],"type":"Point"}
}