{
  "type": "Feature",
  "properties": {
    "date:inception_lower": "1992-08-01",
    "date:inception_upper": "1992-08-01",
    "iso:country": "GB",
    "wof:name": "LE67 5PX",
    "wof:placetype": "postalcode"
  },
  "geometry": {"coordinates":[-1.348166,52.730416],"type":"Point"}
}
