{
  "type": "Feature",
  "properties": {
    "iso:country":"GB",
    "wof:name":"CO11 1SS",
    "wof:placetype":"postalcode"
},
  "geometry": {"coordinates":[1.06266220236758,51.96442670930212],"type":"Point"}
}