{
  "type": "Feature",
  "properties": {
    "iso:country":"GB",
    "wof:name":"M6 8LE",
    "wof:placetype":"postalcode"
},
  "geometry": {"coordinates":[-2.3254343887201,53.49418170841826],"type":"Point"}
}