{
  "type": "Feature",
  "properties": {
    "iso:country":"GB",
    "wof:name":"DN21 1EG",
    "wof:placetype":"postalcode"
},
  "geometry": {"coordinates":[-0.76538601706283,53.40448229938053],"type":"Point"}
}