{
  "type": "Feature",
  "properties": {
    "date:inception_lower": "2005-03-01",
    "date:inception_upper": "2005-03-01",
    "iso:country": "GB",
    "wof:name": "RH20 4BF",
    "wof:placetype": "postalcode"
  },
  "geometry": {"coordinates":[-0.46261,50.915418],"type":"Point"}
}
