{
  "type": "Feature",
  "properties": {
    "iso:country":"GB",
    "wof:name":"RH20 4BF",
    "wof:placetype":"postalcode"
},
  "geometry": {"coordinates":[-0.46260958783294,50.91541762833337],"type":"Point"}
}