{
  "type": "Feature",
  "properties": {
    "date:inception_lower": "2010-11-01",
    "date:inception_upper": "2010-11-01",
    "iso:country": "GB",
    "wof:name": "L7 1QL",
    "wof:placetype": "postalcode"
  },
  "geometry": {"coordinates":[-2.950711,53.405376],"type":"Point"}
}
