{
  "type": "Feature",
  "properties": {
    "iso:country": "GB",
    "wof:name": "NR12 9AD",
    "wof:placetype": "postalcode"
  },
  "geometry": {"coordinates":[1.454306,52.768643],"type":"Point"}
}
