{
  "type": "Feature",
  "properties": {
    "iso:country":"GB",
    "wof:name":"RG10 0PU",
    "wof:placetype":"postalcode"
},
  "geometry": {"coordinates":[-0.8026746044077,51.46169309199234],"type":"Point"}
}