{
  "type": "Feature",
  "properties": {
    "iso:country":"GB",
    "wof:name":"BS2 9UF",
    "wof:placetype":"postalcode"
},
  "geometry": {"coordinates":[-2.57477043522082,51.46998111206229],"type":"Point"}
}