{
  "type": "Feature",
  "properties": {
    "iso:country": "GB",
    "wof:name": "ST15 8RN",
    "wof:placetype": "postalcode"
  },
  "geometry": {"coordinates":[-2.08852,52.931558],"type":"Point"}
}
