{
  "type": "Feature",
  "properties": {
    "iso:country":"GB",
    "wof:name":"ST15 8RN",
    "wof:placetype":"postalcode"
},
  "geometry": {"coordinates":[-2.08852052242754,52.93155824927736],"type":"Point"}
}