{
  "type": "Feature",
  "properties": {
    "iso:country":"GB",
    "wof:name":"B27 7AE",
    "wof:placetype":"postalcode"
},
  "geometry": {"coordinates":[-1.81464674916772,52.43594625976185],"type":"Point"}
}