{
  "type": "Feature",
  "properties": {
    "iso:country": "GB",
    "wof:name": "OL4 2PD",
    "wof:placetype": "postalcode"
  },
  "geometry": {"coordinates":[-2.082544,53.554468],"type":"Point"}
}
