{
  "type": "Feature",
  "properties": {
    "date:inception_lower":"1980-01-01",
    "date:inception_upper":"1980-01-31",
    "iso:country":"GB",
    "wof:name":"OL4 2PD",
    "wof:placetype":"postalcode"
},
  "geometry": {"coordinates":[-2.082544,53.554468],"type":"Point"}
}