{
  "type": "Feature",
  "properties": {
    "date:inception_lower": "2023-07-01",
    "date:inception_upper": "2023-07-01",
    "iso:country": "GB",
    "wof:name": "TF2 5AA",
    "wof:placetype": "postalcode"
  },
  "geometry": {"coordinates":[-2.408991,52.685991],"type":"Point"}
}
