{
  "type": "Feature",
  "properties": {
    "date:inception_lower": "2018-04-01",
    "date:inception_upper": "2018-04-01",
    "iso:country": "GB",
    "wof:name": "HA3 3ND",
    "wof:placetype": "postalcode"
  },
  "geometry": {"coordinates":[-0.329664,51.585229],"type":"Point"}
}
