{
  "type": "Feature",
  "properties": {
    "date:inception_lower": "1980-01-01",
    "date:inception_upper": "1980-01-01",
    "iso:country": "GB",
    "wof:name": "SW17 8JA",
    "wof:placetype": "postalcode"
  },
  "geometry": {"coordinates":[-0.162054,51.432044],"type":"Point"}
}
