{
  "type": "Feature",
  "properties": {
    "iso:country": "GB",
    "wof:name": "GL10 3BX",
    "wof:placetype": "postalcode"
  },
  "geometry": {"coordinates":[-2.272899,51.756867],"type":"Point"}
}
