{
  "type": "Feature",
  "properties": {
    "iso:country":"GB",
    "wof:name":"GL10 3BX",
    "wof:placetype":"postalcode"
},
  "geometry": {"coordinates":[-2.27290194785128,51.75686163771477],"type":"Point"}
}