{
  "type": "Feature",
  "properties": {
    "iso:country":"GB",
    "wof:name":"SO24 9HS",
    "wof:placetype":"postalcode"
},
  "geometry": {"coordinates":[-1.17592106532725,51.08604915730442],"type":"Point"}
}