{
  "type": "Feature",
  "properties": {
    "iso:country": "GB",
    "wof:name": "SO24 9HS",
    "wof:placetype": "postalcode"
  },
  "geometry": {"coordinates":[-1.175921,51.086049],"type":"Point"}
}
