{
  "type": "Feature",
  "properties": {
    "date:inception_lower":"1980-01-01",
    "date:inception_upper":"1980-01-31",
    "iso:country":"GB",
    "wof:name":"SO24 9HS",
    "wof:placetype":"postalcode"
},
  "geometry": {"coordinates":[-1.175921,51.086049],"type":"Point"}
}