{
  "type": "Feature",
  "properties": {
    "iso:country":"GB",
    "wof:name":"NW1 2ES",
    "wof:placetype":"postalcode"
},
  "geometry": {"coordinates":[-0.13524444669492,51.52721134484472],"type":"Point"}
}