{
  "type": "Feature",
  "properties": {
    "date:inception_lower": "2007-07-01",
    "date:inception_upper": "2007-07-01",
    "iso:country": "GB",
    "wof:name": "S1 4DF",
    "wof:placetype": "postalcode"
  },
  "geometry": {"coordinates":[-1.474103,53.384591],"type":"Point"}
}
