{
  "type": "Feature",
  "properties": {
    "date:inception_lower": "1980-01-01",
    "date:inception_upper": "1980-01-01",
    "iso:country": "GB",
    "wof:name": "ME18 5QL",
    "wof:placetype": "postalcode"
  },
  "geometry": {"coordinates":[0.381934,51.267356],"type":"Point"}
}
