{
  "type": "Feature",
  "properties": {
    "iso:country":"GB",
    "wof:name":"PE19 2QE",
    "wof:placetype":"postalcode"
},
  "geometry": {"coordinates":[-0.263363425913,52.21423254358092],"type":"Point"}
}