{
  "type": "Feature",
  "properties": {
    "date:inception_lower": "1993-08-01",
    "date:inception_upper": "1993-08-01",
    "iso:country": "GB",
    "wof:name": "MK42 9EB",
    "wof:placetype": "postalcode"
  },
  "geometry": {"coordinates":[-0.472566,52.117215],"type":"Point"}
}
