{
  "type": "Feature",
  "properties": {
    "iso:country":"GB",
    "wof:name":"MK42 9EB",
    "wof:placetype":"postalcode"
},
  "geometry": {"coordinates":[-0.47256611063693,52.11721514389762],"type":"Point"}
}