{
  "type": "Feature",
  "properties": {
    "iso:country":"GB",
    "wof:name":"RH2 8DN",
    "wof:placetype":"postalcode"
},
  "geometry": {"coordinates":[-0.24886735545977,51.20614652823041],"type":"Point"}
}