{
  "type": "Feature",
  "properties": {
    "iso:country": "GB",
    "wof:name": "RH2 8DN",
    "wof:placetype": "postalcode"
  },
  "geometry": {"coordinates":[-0.248867,51.206147],"type":"Point"}
}
