{
  "type": "Feature",
  "properties": {
    "date:inception_lower":"1980-01-01",
    "date:inception_upper":"1980-01-31",
    "iso:country":"GB",
    "wof:name":"RH2 8DN",
    "wof:placetype":"postalcode"
},
  "geometry": {"coordinates":[-0.248867,51.206147],"type":"Point"}
}