{
  "type": "Feature",
  "properties": {
    "iso:country":"GB",
    "wof:name":"SO31 5DP",
    "wof:placetype":"postalcode"
},
  "geometry": {"coordinates":[-1.35448867470067,50.87539143904166],"type":"Point"}
}