{
  "type": "Feature",
  "properties": {
    "date:inception_lower": "1980-01-01",
    "date:inception_upper": "1980-01-01",
    "iso:country": "GB",
    "wof:name": "TF9 4BN",
    "wof:placetype": "postalcode"
  },
  "geometry": {"coordinates":[-2.388257,52.921158],"type":"Point"}
}
