{
  "type": "Feature",
  "properties": {
    "iso:country":"GB",
    "wof:name":"DE21 6AJ",
    "wof:placetype":"postalcode"
},
  "geometry": {"coordinates":[-1.45836610731536,52.92779629939299],"type":"Point"}
}