{
  "type": "Feature",
  "properties": {
    "date:inception_lower": "1980-01-01",
    "date:inception_upper": "1980-01-01",
    "iso:country": "GB",
    "wof:name": "CT15 5EA",
    "wof:placetype": "postalcode"
  },
  "geometry": {"coordinates":[1.324676,51.144776],"type":"Point"}
}
