{
  "type": "Feature",
  "properties": {
    "iso:country":"GB",
    "wof:name":"CT15 5EA",
    "wof:placetype":"postalcode"
},
  "geometry": {"coordinates":[1.32467578504493,51.14477641510239],"type":"Point"}
}