{
  "type": "Feature",
  "properties": {
    "iso:country":"GB",
    "wof:name":"AL4 0UR",
    "wof:placetype":"postalcode"
},
  "geometry": {"coordinates":[-0.30365609171899,51.7560818987819],"type":"Point"}
}