{
  "type": "Feature",
  "properties": {
    "date:inception_lower":"2008-07-01",
    "date:inception_upper":"2008-07-31",
    "iso:country":"GB",
    "wof:name":"DY12 3EE",
    "wof:placetype":"postalcode"
},
  "geometry": {"coordinates":[-2.344472,52.390041],"type":"Point"}
}