{
  "type": "Feature",
  "properties": {
    "iso:country":"GB",
    "wof:name":"DY12 3EE",
    "wof:placetype":"postalcode"
},
  "geometry": {"coordinates":[-2.34450433310461,52.38999975383022],"type":"Point"}
}