{
  "type": "Feature",
  "properties": {
    "iso:country": "GB",
    "wof:name": "DY12 3EE",
    "wof:placetype": "postalcode"
  },
  "geometry": {"coordinates":[-2.344472,52.390041],"type":"Point"}
}
