{
  "type": "Feature",
  "properties": {
    "iso:country":"GB",
    "wof:name":"SN13 9JB",
    "wof:placetype":"postalcode"
},
  "geometry": {"coordinates":[-2.18419578427,51.42600038870294],"type":"Point"}
}