{
  "type": "Feature",
  "properties": {
    "iso:country":"GB",
    "wof:name":"LS2 3AG",
    "wof:placetype":"postalcode"
},
  "geometry": {"coordinates":[-1.54750176102913,53.8005664253859],"type":"Point"}
}