{
  "type": "Feature",
  "properties": {
    "iso:country": "GB",
    "wof:name": "GU7 3SQ",
    "wof:placetype": "postalcode"
  },
  "geometry": {"coordinates":[-0.603999,51.20398],"type":"Point"}
}
