{
  "type": "Feature",
  "properties": {
    "iso:country":"GB",
    "wof:name":"OX4 4UT",
    "wof:placetype":"postalcode"
},
  "geometry": {"coordinates":[-1.22432990942352,51.70195048436695],"type":"Point"}
}