{
  "type": "Feature",
  "properties": {
    "iso:country": "GB",
    "wof:name": "OX4 4UT",
    "wof:placetype": "postalcode"
  },
  "geometry": {"coordinates":[-1.22433,51.70195],"type":"Point"}
}
