{
  "type": "Feature",
  "properties": {
    "iso:country":"GB",
    "wof:name":"TA1 2EF",
    "wof:placetype":"postalcode"
},
  "geometry": {"coordinates":[-3.08720387945647,51.01859938545527],"type":"Point"}
}