{
  "type": "Feature",
  "properties": {
    "date:inception_lower": "2023-07-01",
    "date:inception_upper": "2023-07-01",
    "iso:country": "GB",
    "wof:name": "SS17 9JX",
    "wof:placetype": "postalcode"
  },
  "geometry": {"coordinates":[0.472547,51.52951],"type":"Point"}
}
