{
  "type": "Feature",
  "properties": {
    "iso:country":"GB",
    "wof:name":"RG20 6PU",
    "wof:placetype":"postalcode"
},
  "geometry": {"coordinates":[-1.24713475419697,51.51947304117433],"type":"Point"}
}