{
  "type": "Feature",
  "properties": {
    "date:inception_lower":"1995-07-01",
    "date:inception_upper":"1995-07-31",
    "iso:country":"GB",
    "wof:name":"RG20 6PU",
    "wof:placetype":"postalcode"
},
  "geometry": {"coordinates":[-1.247135,51.519473],"type":"Point"}
}