{
  "type": "Feature",
  "properties": {
    "iso:country":"GB",
    "wof:name":"HR2 7AD",
    "wof:placetype":"postalcode"
},
  "geometry": {"coordinates":[-2.72796455676906,52.04529725617806],"type":"Point"}
}