{
  "type": "Feature",
  "properties": {
    "iso:country": "GB",
    "wof:name": "HR2 7AD",
    "wof:placetype": "postalcode"
  },
  "geometry": {"coordinates":[-2.727965,52.045297],"type":"Point"}
}
