{
  "type": "Feature",
  "properties": {
    "date:inception_lower":"2002-09-01",
    "date:inception_upper":"2002-09-30",
    "iso:country":"GB",
    "wof:name":"EX39 4RS",
    "wof:placetype":"postalcode"
},
  "geometry": {"coordinates":[-4.197003,51.016909],"type":"Point"}
}