{
  "type": "Feature",
  "properties": {
    "iso:country": "GB",
    "wof:name": "EX39 4RS",
    "wof:placetype": "postalcode"
  },
  "geometry": {"coordinates":[-4.197003,51.016909],"type":"Point"}
}
