{
  "type": "Feature",
  "properties": {
    "iso:country":"GB",
    "wof:name":"B21 0SU",
    "wof:placetype":"postalcode"
},
  "geometry": {"coordinates":[-1.93257521948678,52.50164491133568],"type":"Point"}
}