{
  "type": "Feature",
  "properties": {
    "iso:country":"GB",
    "wof:name":"RH12 5HS",
    "wof:placetype":"postalcode"
},
  "geometry": {"coordinates":[-0.32167850583681,51.08035167519606],"type":"Point"}
}