{
  "type": "Feature",
  "properties": {
    "iso:country":"GB",
    "wof:name":"SS16 5EY",
    "wof:placetype":"postalcode"
},
  "geometry": {"coordinates":[0.45832127787357,51.56227204608617],"type":"Point"}
}