{
  "type": "Feature",
  "properties": {
    "iso:country":"GB",
    "wof:name":"L8 2YD",
    "wof:placetype":"postalcode"
},
  "geometry": {"coordinates":[-2.95719957903214,53.39355814779628],"type":"Point"}
}