{
  "type": "Feature",
  "properties": {
    "date:inception_lower": "1980-01-01",
    "date:inception_upper": "1980-01-01",
    "iso:country": "GB",
    "wof:name": "HU12 0DS",
    "wof:placetype": "postalcode"
  },
  "geometry": {"coordinates":[-0.081205,53.699654],"type":"Point"}
}
