{
  "type": "Feature",
  "properties": {
    "iso:country":"GB",
    "wof:name":"RG1 1LX",
    "wof:placetype":"postalcode"
},
  "geometry": {"coordinates":[-0.97271384062687,51.45808154671727],"type":"Point"}
}