{
  "type": "Feature",
  "properties": {
    "iso:country":"GB",
    "wof:name":"TA9 4NF",
    "wof:placetype":"postalcode"
},
  "geometry": {"coordinates":[-2.88892950664616,51.22680203545705],"type":"Point"}
}