{
  "type": "Feature",
  "properties": {
    "date:inception_lower": "1980-01-01",
    "date:inception_upper": "1980-01-01",
    "iso:country": "GB",
    "wof:name": "DN7 6EL",
    "wof:placetype": "postalcode"
  },
  "geometry": {"coordinates":[-0.980702,53.586722],"type":"Point"}
}
