{
  "type": "Feature",
  "properties": {
    "date:inception_lower":"1980-01-01",
    "date:inception_upper":"1980-01-31",
    "iso:country":"GB",
    "wof:name":"DN12 3BZ",
    "wof:placetype":"postalcode"
},
  "geometry": {"coordinates":[-1.228532,53.484974],"type":"Point"}
}