{
  "type": "Feature",
  "properties": {
    "iso:country":"GB",
    "wof:name":"DN12 3BZ",
    "wof:placetype":"postalcode"
},
  "geometry": {"coordinates":[-1.22853206530336,53.48497357781093],"type":"Point"}
}