{
  "type": "Feature",
  "properties": {
    "iso:country":"GB",
    "wof:name":"LA19 5TN",
    "wof:placetype":"postalcode"
},
  "geometry": {"coordinates":[-3.35621576210505,54.31501767147051],"type":"Point"}
}