{
  "type": "Feature",
  "properties": {
    "iso:country": "GB",
    "wof:name": "LA19 5TN",
    "wof:placetype": "postalcode"
  },
  "geometry": {"coordinates":[-3.356216,54.315018],"type":"Point"}
}
