{
  "type": "Feature",
  "properties": {
    "iso:country":"GB",
    "wof:name":"SA70 8NS",
    "wof:placetype":"postalcode"
},
  "geometry": {"coordinates":[-4.79387622420484,51.68493928392591],"type":"Point"}
}