{
  "type": "Feature",
  "properties": {
    "date:inception_lower":"1980-01-01",
    "date:inception_upper":"1980-01-31",
    "iso:country":"GB",
    "wof:name":"SA70 8NS",
    "wof:placetype":"postalcode"
},
  "geometry": {"coordinates":[-4.793876,51.684939],"type":"Point"}
}