{
  "type": "Feature",
  "properties": {
    "date:inception_lower": "2016-12-01",
    "date:inception_upper": "2016-12-01",
    "iso:country": "GB",
    "wof:name": "TW7 4FS",
    "wof:placetype": "postalcode"
  },
  "geometry": {"coordinates":[-0.349393,51.472528],"type":"Point"}
}
