{
  "type": "Feature",
  "properties": {
    "date:inception_lower": "2013-07-01",
    "date:inception_upper": "2013-07-01",
    "iso:country": "GB",
    "wof:name": "AB15 9LZ",
    "wof:placetype": "postalcode"
  },
  "geometry": {"coordinates":[-2.175231,57.123344],"type":"Point"}
}
