{
  "type": "Feature",
  "properties": {
    "iso:country":"GB",
    "wof:name":"AB15 9LZ",
    "wof:placetype":"postalcode"
},
  "geometry": {"coordinates":[-2.17523060553126,57.12334418464505],"type":"Point"}
}