{
  "type": "Feature",
  "properties": {
    "iso:country":"GB",
    "wof:name":"CA6 6AG",
    "wof:placetype":"postalcode"
},
  "geometry": {"coordinates":[-2.95338259755685,54.97117591003293],"type":"Point"}
}