{
  "type": "Feature",
  "properties": {
    "iso:country": "GB",
    "wof:name": "CA6 6AG",
    "wof:placetype": "postalcode"
  },
  "geometry": {"coordinates":[-2.953383,54.971176],"type":"Point"}
}
