{
  "type": "Feature",
  "properties": {
    "date:inception_lower": "1980-01-01",
    "date:inception_upper": "1980-01-01",
    "iso:country": "GB",
    "wof:name": "CA6 6AG",
    "wof:placetype": "postalcode"
  },
  "geometry": {"coordinates":[-2.953383,54.971176],"type":"Point"}
}
