{
  "type": "Feature",
  "properties": {
    "date:inception_lower": "1980-01-01",
    "date:inception_upper": "1980-01-01",
    "iso:country": "GB",
    "wof:name": "CM14 4TU",
    "wof:placetype": "postalcode"
  },
  "geometry": {"coordinates":[0.295223,51.622178],"type":"Point"}
}
