{
  "type": "Feature",
  "properties": {
    "iso:country":"GB",
    "wof:name":"CM14 4TU",
    "wof:placetype":"postalcode"
},
  "geometry": {"coordinates":[0.29522281032148,51.62217828320609],"type":"Point"}
}