{
  "type": "Feature",
  "properties": {
    "iso:country": "GB",
    "wof:name": "DG7 1LB",
    "wof:placetype": "postalcode"
  },
  "geometry": {"coordinates":[-3.926412,54.943804],"type":"Point"}
}
