{
  "type": "Feature",
  "properties": {
    "iso:country":"GB",
    "wof:name":"SW6 7TJ",
    "wof:placetype":"postalcode"
},
  "geometry": {"coordinates":[-0.20610581262943,51.48379482471145],"type":"Point"}
}