{
  "type": "Feature",
  "properties": {
    "iso:country":"GB",
    "wof:name":"HU10 7PP",
    "wof:placetype":"postalcode"
},
  "geometry": {"coordinates":[-0.45525055792743,53.74595270394385],"type":"Point"}
}