{
  "type": "Feature",
  "properties": {
    "iso:country":"GB",
    "wof:name":"RM17 6NQ",
    "wof:placetype":"postalcode"
},
  "geometry": {"coordinates":[0.32165997073669,51.47625857625204],"type":"Point"}
}