{
  "type": "Feature",
  "properties": {
    "iso:country": "GB",
    "wof:name": "UB6 9TN",
    "wof:placetype": "postalcode"
  },
  "geometry": {"coordinates":[-0.364567,51.53556],"type":"Point"}
}
