{
  "type": "Feature",
  "properties": {
    "iso:country":"GB",
    "wof:name":"UB6 9TN",
    "wof:placetype":"postalcode"
},
  "geometry": {"coordinates":[-0.36456739657827,51.53556027964792],"type":"Point"}
}