{
  "type": "Feature",
  "properties": {
    "date:inception_lower": "1997-12-01",
    "date:inception_upper": "1997-12-01",
    "iso:country": "GB",
    "wof:name": "S40 3RA",
    "wof:placetype": "postalcode"
  },
  "geometry": {"coordinates":[-1.464201,53.231809],"type":"Point"}
}
