{
  "type": "Feature",
  "properties": {
    "iso:country":"GB",
    "wof:name":"S40 3RA",
    "wof:placetype":"postalcode"
},
  "geometry": {"coordinates":[-1.46420146335446,53.23180889013128],"type":"Point"}
}