{
  "type": "Feature",
  "properties": {
    "date:inception_lower": "2021-08-01",
    "date:inception_upper": "2021-08-01",
    "iso:country": "GB",
    "wof:name": "GL3 1GJ",
    "wof:placetype": "postalcode"
  },
  "geometry": {"coordinates":[-2.198766,51.882469],"type":"Point"}
}
