{
  "type": "Feature",
  "properties": {
    "iso:country": "GB",
    "wof:name": "PA17 5DW",
    "wof:placetype": "postalcode"
  },
  "geometry": {"coordinates":[-4.887734,55.869001],"type":"Point"}
}
