{
  "type": "Feature",
  "properties": {
    "iso:country":"GB",
    "wof:name":"PA17 5DW",
    "wof:placetype":"postalcode"
},
  "geometry": {"coordinates":[-4.88773381498716,55.86900104022068],"type":"Point"}
}