{
  "type": "Feature",
  "properties": {
    "date:inception_lower":"1994-09-01",
    "date:inception_upper":"1994-09-30",
    "iso:country":"GB",
    "wof:name":"PA17 5DW",
    "wof:placetype":"postalcode"
},
  "geometry": {"coordinates":[-4.887734,55.869001],"type":"Point"}
}