{
  "type": "Feature",
  "properties": {
    "iso:country":"GB",
    "wof:name":"WV15 5LP",
    "wof:placetype":"postalcode"
},
  "geometry": {"coordinates":[-2.35717981771047,52.57824859590732],"type":"Point"}
}