{
  "type": "Feature",
  "properties": {
    "iso:country":"GB",
    "wof:name":"GU23 6AA",
    "wof:placetype":"postalcode"
},
  "geometry": {"coordinates":[-0.49244075182139,51.30008374467022],"type":"Point"}
}