{
  "type": "Feature",
  "properties": {
    "date:inception_lower": "1980-01-01",
    "date:inception_upper": "1980-01-01",
    "iso:country": "GB",
    "wof:name": "GU23 6AA",
    "wof:placetype": "postalcode"
  },
  "geometry": {"coordinates":[-0.492419,51.300081],"type":"Point"}
}
