{
  "type": "Feature",
  "properties": {
    "iso:country":"GB",
    "wof:name":"IP21 4QN",
    "wof:placetype":"postalcode"
},
  "geometry": {"coordinates":[1.24547531860759,52.4233722881014],"type":"Point"}
}