{
  "type": "Feature",
  "properties": {
    "date:inception_lower": "1999-06-01",
    "date:inception_upper": "1999-06-01",
    "iso:country": "GB",
    "wof:name": "NP11 3DH",
    "wof:placetype": "postalcode"
  },
  "geometry": {"coordinates":[-3.146963,51.670423],"type":"Point"}
}
