{
  "type": "Feature",
  "properties": {
    "date:inception_lower":"1994-12-01",
    "date:inception_upper":"1994-12-31",
    "iso:country":"GB",
    "wof:name":"SO31 9RS",
    "wof:placetype":"postalcode"
},
  "geometry": {"coordinates":[-1.282752,50.851547],"type":"Point"}
}