{
  "type": "Feature",
  "properties": {
    "iso:country":"GB",
    "wof:name":"SO31 9RS",
    "wof:placetype":"postalcode"
},
  "geometry": {"coordinates":[-1.28275224886194,50.8515471482346],"type":"Point"}
}