{
  "type": "Feature",
  "properties": {
    "iso:country":"GB",
    "wof:name":"ML3 8DE",
    "wof:placetype":"postalcode"
},
  "geometry": {"coordinates":[-4.06212917245298,55.75715748089446],"type":"Point"}
}