{
  "type": "Feature",
  "properties": {
    "iso:country":"GB",
    "wof:name":"CT6 7TB",
    "wof:placetype":"postalcode"
},
  "geometry": {"coordinates":[1.13651092728147,51.34807002354869],"type":"Point"}
}