{
  "type": "Feature",
  "properties": {
    "iso:country": "GB",
    "wof:name": "CT15 7BQ",
    "wof:placetype": "postalcode"
  },
  "geometry": {"coordinates":[1.23498,51.115224],"type":"Point"}
}
