{
  "type": "Feature",
  "properties": {
    "iso:country":"GB",
    "wof:name":"LS2 9DF",
    "wof:placetype":"postalcode"
},
  "geometry": {"coordinates":[-1.56045683898596,53.80743648613873],"type":"Point"}
}