{
  "type": "Feature",
  "properties": {
    "date:inception_lower":"2000-12-01",
    "date:inception_upper":"2000-12-31",
    "iso:country":"GB",
    "wof:name":"LS2 9DF",
    "wof:placetype":"postalcode"
},
  "geometry": {"coordinates":[-1.560457,53.807436],"type":"Point"}
}