{
  "type": "Feature",
  "properties": {
    "iso:country":"GB",
    "wof:name":"LN3 5AH",
    "wof:placetype":"postalcode"
},
  "geometry": {"coordinates":[-0.37048247699447,53.32144650866373],"type":"Point"}
}