{
  "type": "Feature",
  "properties": {
    "date:inception_lower":"2011-09-01",
    "date:inception_upper":"2011-09-30",
    "iso:country":"GB",
    "wof:name":"SE13 7FS",
    "wof:placetype":"postalcode"
},
  "geometry": {"coordinates":[-0.018348,51.464927],"type":"Point"}
}