{
  "type": "Feature",
  "properties": {
    "iso:country":"GB",
    "wof:name":"DN14 8NF",
    "wof:placetype":"postalcode"
},
  "geometry": {"coordinates":[-0.96095531590346,53.6902180276907],"type":"Point"}
}