{
  "type": "Feature",
  "properties": {
    "date:inception_lower":"2016-12-01",
    "date:inception_upper":"2016-12-31",
    "iso:country":"GB",
    "wof:name":"HD3 3YZ",
    "wof:placetype":"postalcode"
},
  "geometry": {"coordinates":[-1.878581,53.651811],"type":"Point"}
}