{
  "type": "Feature",
  "properties": {
    "iso:country": "GB",
    "wof:name": "HD3 3YZ",
    "wof:placetype": "postalcode"
  },
  "geometry": {"coordinates":[-1.878581,53.651811],"type":"Point"}
}
