{
  "type": "Feature",
  "properties": {
    "iso:country": "GB",
    "wof:name": "HR9 5SQ",
    "wof:placetype": "postalcode"
  },
  "geometry": {"coordinates":[-2.557479,51.882001],"type":"Point"}
}
