{
  "type": "Feature",
  "properties": {
    "iso:country":"GB",
    "wof:name":"HR9 5SQ",
    "wof:placetype":"postalcode"
},
  "geometry": {"coordinates":[-2.55747925413717,51.88200059528157],"type":"Point"}
}