{
  "type": "Feature",
  "properties": {
    "iso:country":"GB",
    "wof:name":"LE4 8EE",
    "wof:placetype":"postalcode"
},
  "geometry": {"coordinates":[-1.09782479460287,52.68017716242942],"type":"Point"}
}