{
  "type": "Feature",
  "properties": {
    "iso:country": "GB",
    "wof:name": "OL16 5AQ",
    "wof:placetype": "postalcode"
  },
  "geometry": {"coordinates":[-2.136987,53.614979],"type":"Point"}
}
