{
  "type": "Feature",
  "properties": {
    "date:inception_lower": "2002-06-01",
    "date:inception_upper": "2002-06-01",
    "iso:country": "GB",
    "wof:name": "WA12 0GA",
    "wof:placetype": "postalcode"
  },
  "geometry": {"coordinates":[-2.63408,53.457231],"type":"Point"}
}
