{
  "type": "Feature",
  "properties": {
    "iso:country":"GB",
    "wof:name":"WA12 0GA",
    "wof:placetype":"postalcode"
},
  "geometry": {"coordinates":[-2.63407989913722,53.45723051456081],"type":"Point"}
}