{
  "type": "Feature",
  "properties": {
    "iso:country":"GB",
    "wof:name":"CF43 4RD",
    "wof:placetype":"postalcode"
},
  "geometry": {"coordinates":[-3.44994552990087,51.66574142481196],"type":"Point"}
}