{
  "type": "Feature",
  "properties": {
    "iso:country":"GB",
    "wof:name":"TD11 3EE",
    "wof:placetype":"postalcode"
},
  "geometry": {"coordinates":[-2.34307881188366,55.77940063786201],"type":"Point"}
}