{
  "type": "Feature",
  "properties": {
    "iso:country":"GB",
    "wof:name":"ST7 3RT",
    "wof:placetype":"postalcode"
},
  "geometry": {"coordinates":[-2.29288291852103,53.11387165269005],"type":"Point"}
}