{
  "type": "Feature",
  "properties": {
    "iso:country":"GB",
    "wof:name":"BR2 7LR",
    "wof:placetype":"postalcode"
},
  "geometry": {"coordinates":[0.01648057614205,51.37935985617801],"type":"Point"}
}