{
  "type": "Feature",
  "properties": {
    "iso:country":"GB",
    "wof:name":"B26 2QX",
    "wof:placetype":"postalcode"
},
  "geometry": {"coordinates":[-1.78913807279883,52.46732369622583],"type":"Point"}
}