{
  "type": "Feature",
  "properties": {
    "date:inception_lower": "2007-01-01",
    "date:inception_upper": "2007-01-01",
    "iso:country": "GB",
    "wof:name": "EX20 1BP",
    "wof:placetype": "postalcode"
  },
  "geometry": {"coordinates":[-4.000516,50.742198],"type":"Point"}
}
