{
  "type": "Feature",
  "properties": {
    "iso:country":"GB",
    "wof:name":"SN11 9LF",
    "wof:placetype":"postalcode"
},
  "geometry": {"coordinates":[-2.0393339382914,51.46220393417109],"type":"Point"}
}