{
  "type": "Feature",
  "properties": {
    "date:inception_lower":"1980-01-01",
    "date:inception_upper":"1980-01-31",
    "iso:country":"GB",
    "wof:name":"SN11 9LF",
    "wof:placetype":"postalcode"
},
  "geometry": {"coordinates":[-2.037414,51.463138],"type":"Point"}
}