{
  "type": "Feature",
  "properties": {
    "iso:country": "GB",
    "wof:name": "SN11 9LF",
    "wof:placetype": "postalcode"
  },
  "geometry": {"coordinates":[-2.039327,51.462203],"type":"Point"}
}
