{
  "type": "Feature",
  "properties": {
    "iso:country":"GB",
    "wof:name":"PO36 9BN",
    "wof:placetype":"postalcode"
},
  "geometry": {"coordinates":[-1.16081754037412,50.65684035584929],"type":"Point"}
}