{
  "type": "Feature",
  "properties": {
    "iso:country":"GB",
    "wof:name":"DD4 9QH",
    "wof:placetype":"postalcode"
},
  "geometry": {"coordinates":[-2.93481892115515,56.49450756557104],"type":"Point"}
}