{
  "type": "Feature",
  "properties": {
    "iso:country":"GB",
    "wof:name":"EH7 4NQ",
    "wof:placetype":"postalcode"
},
  "geometry": {"coordinates":[-3.18519235404452,55.9636434276706],"type":"Point"}
}