{
  "type": "Feature",
  "properties": {
    "iso:country": "GB",
    "wof:name": "DY2 9JX",
    "wof:placetype": "postalcode"
  },
  "geometry": {"coordinates":[-2.071523,52.48802],"type":"Point"}
}
