{
  "type": "Feature",
  "properties": {
    "date:inception_lower": "1980-01-01",
    "date:inception_upper": "1980-01-01",
    "iso:country": "GB",
    "wof:name": "SS14 1QP",
    "wof:placetype": "postalcode"
  },
  "geometry": {"coordinates":[0.474524,51.571554],"type":"Point"}
}
