{
  "type": "Feature",
  "properties": {
    "iso:country":"GB",
    "wof:name":"SS14 1QP",
    "wof:placetype":"postalcode"
},
  "geometry": {"coordinates":[0.47452394452748,51.57155414839168],"type":"Point"}
}