{
  "type": "Feature",
  "properties": {
    "iso:country":"GB",
    "wof:name":"OX14 4AH",
    "wof:placetype":"postalcode"
},
  "geometry": {"coordinates":[-1.27789510619416,51.64219352526376],"type":"Point"}
}