{
  "type": "Feature",
  "properties": {
    "iso:country":"GB",
    "wof:name":"L30 3SW",
    "wof:placetype":"postalcode"
},
  "geometry": {"coordinates":[-2.9759783630735,53.48467912111719],"type":"Point"}
}