{
  "type": "Feature",
  "properties": {
    "iso:country": "GB",
    "wof:name": "L30 3SW",
    "wof:placetype": "postalcode"
  },
  "geometry": {"coordinates":[-2.975978,53.484679],"type":"Point"}
}
