{
  "type": "Feature",
  "properties": {
    "iso:country":"GB",
    "wof:name":"HA3 8UB",
    "wof:placetype":"postalcode"
},
  "geometry": {"coordinates":[-0.30621060305501,51.58847899501773],"type":"Point"}
}