{
  "type": "Feature",
  "properties": {
    "iso:country": "GB",
    "wof:name": "NN14 3DT",
    "wof:placetype": "postalcode"
  },
  "geometry": {"coordinates":[-0.43681,52.40848],"type":"Point"}
}
