{
  "type": "Feature",
  "properties": {
    "date:inception_lower": "1980-01-01",
    "date:inception_upper": "1980-01-01",
    "iso:country": "GB",
    "wof:name": "NN14 3DT",
    "wof:placetype": "postalcode"
  },
  "geometry": {"coordinates":[-0.436642,52.409071],"type":"Point"}
}
