{
  "type": "Feature",
  "properties": {
    "iso:country":"GB",
    "wof:name":"SO22 5HP",
    "wof:placetype":"postalcode"
},
  "geometry": {"coordinates":[-1.33212811550343,51.06836862450717],"type":"Point"}
}