{
  "type": "Feature",
  "properties": {
    "iso:country": "GB",
    "wof:name": "BD4 0RX",
    "wof:placetype": "postalcode"
  },
  "geometry": {"coordinates":[-1.657399,53.77393],"type":"Point"}
}
