{
  "type": "Feature",
  "properties": {
    "iso:country":"GB",
    "wof:name":"BD4 0RX",
    "wof:placetype":"postalcode"
},
  "geometry": {"coordinates":[-1.65739934993119,53.7739304488687],"type":"Point"}
}