{
  "type": "Feature",
  "properties": {
    "date:inception_lower": "1980-01-01",
    "date:inception_upper": "1980-01-01",
    "iso:country": "GB",
    "wof:name": "EH4 2DZ",
    "wof:placetype": "postalcode"
  },
  "geometry": {"coordinates":[-3.237695,55.955795],"type":"Point"}
}
