{
  "type": "Feature",
  "properties": {
    "date:inception_lower": "2019-01-01",
    "date:inception_upper": "2019-01-01",
    "iso:country": "GB",
    "wof:name": "CF3 5UY",
    "wof:placetype": "postalcode"
  },
  "geometry": {"coordinates":[-3.11219,51.524895],"type":"Point"}
}
