{
  "type": "Feature",
  "properties": {
    "iso:country":"GB",
    "wof:name":"LD3 7AF",
    "wof:placetype":"postalcode"
},
  "geometry": {"coordinates":[-3.39038937217118,51.94673032758246],"type":"Point"}
}