{
  "type": "Feature",
  "properties": {
    "iso:country":"GB",
    "wof:name":"HD5 8EW",
    "wof:placetype":"postalcode"
},
  "geometry": {"coordinates":[-1.75466920746566,53.63925707342587],"type":"Point"}
}