{
  "type": "Feature",
  "properties": {
    "date:inception_lower": "1980-01-01",
    "date:inception_upper": "1980-01-01",
    "iso:country": "GB",
    "wof:name": "HD5 8EW",
    "wof:placetype": "postalcode"
  },
  "geometry": {"coordinates":[-1.754669,53.639257],"type":"Point"}
}
