{
  "type": "Feature",
  "properties": {
    "iso:country":"GB",
    "wof:name":"EC4V 4AP",
    "wof:placetype":"postalcode"
},
  "geometry": {"coordinates":[-0.09801121393986,51.51153302595897],"type":"Point"}
}