{
  "type": "Feature",
  "properties": {
    "iso:country":"GB",
    "wof:name":"HA9 8HU",
    "wof:placetype":"postalcode"
},
  "geometry": {"coordinates":[-0.28553842528402,51.56394471102991],"type":"Point"}
}