{
  "type": "Feature",
  "properties": {
    "date:inception_lower": "2018-09-01",
    "date:inception_upper": "2018-09-01",
    "iso:country": "GB",
    "wof:name": "SW11 7AY",
    "wof:placetype": "postalcode"
  },
  "geometry": {"coordinates":[-0.130311,51.481965],"type":"Point"}
}
