{
  "type": "Feature",
  "properties": {
    "iso:country": "GB",
    "wof:name": "SW11 7AY",
    "wof:placetype": "postalcode"
  },
  "geometry": {"coordinates":[-0.130311,51.481965],"type":"Point"}
}
