{
  "type": "Feature",
  "properties": {
    "iso:country":"GB",
    "wof:name":"OX14 1JJ",
    "wof:placetype":"postalcode"
},
  "geometry": {"coordinates":[-1.28833025867022,51.67996702869736],"type":"Point"}
}