{
  "type": "Feature",
  "properties": {
    "iso:country": "GB",
    "wof:name": "MK42 9GA",
    "wof:placetype": "postalcode"
  },
  "geometry": {"coordinates":[-0.458695,52.112431],"type":"Point"}
}
