{
  "type": "Feature",
  "properties": {
    "date:inception_lower": "2000-06-01",
    "date:inception_upper": "2000-06-01",
    "iso:country": "GB",
    "wof:name": "MK42 9GA",
    "wof:placetype": "postalcode"
  },
  "geometry": {"coordinates":[-0.458688,52.112434],"type":"Point"}
}
