{
  "type": "Feature",
  "properties": {
    "iso:country":"GB",
    "wof:name":"MK42 9GA",
    "wof:placetype":"postalcode"
},
  "geometry": {"coordinates":[-0.4586951762089,52.11243109438247],"type":"Point"}
}