{
  "type": "Feature",
  "properties": {
    "iso:country":"GB",
    "wof:name":"EX24 6EY",
    "wof:placetype":"postalcode"
},
  "geometry": {"coordinates":[-3.06382683442122,50.74296243382838],"type":"Point"}
}