{
  "type": "Feature",
  "properties": {
    "iso:country": "GB",
    "wof:name": "EX24 6EY",
    "wof:placetype": "postalcode"
  },
  "geometry": {"coordinates":[-3.063827,50.742962],"type":"Point"}
}
