{
  "type": "Feature",
  "properties": {
    "iso:country":"GB",
    "wof:name":"GL51 7SR",
    "wof:placetype":"postalcode"
},
  "geometry": {"coordinates":[-2.11747052828564,51.89898847161132],"type":"Point"}
}