{
  "type": "Feature",
  "properties": {
    "date:inception_lower": "1980-01-01",
    "date:inception_upper": "1980-01-01",
    "iso:country": "GB",
    "wof:name": "PE30 5ER",
    "wof:placetype": "postalcode"
  },
  "geometry": {"coordinates":[0.403125,52.751312],"type":"Point"}
}
