{
  "type": "Feature",
  "properties": {
    "date:inception_lower":"2005-01-01",
    "date:inception_upper":"2005-01-31",
    "iso:country":"GB",
    "wof:name":"MK4 4EX",
    "wof:placetype":"postalcode"
},
  "geometry": {"coordinates":[-0.80199,52.005909],"type":"Point"}
}