{
  "type": "Feature",
  "properties": {
    "iso:country": "GB",
    "wof:name": "MK4 4EX",
    "wof:placetype": "postalcode"
  },
  "geometry": {"coordinates":[-0.80199,52.005909],"type":"Point"}
}
