{
  "type": "Feature",
  "properties": {
    "iso:country":"GB",
    "wof:name":"MK4 4EX",
    "wof:placetype":"postalcode"
},
  "geometry": {"coordinates":[-0.80199029103711,52.00590920855953],"type":"Point"}
}