{
  "type": "Feature",
  "properties": {
    "iso:country": "GB",
    "wof:name": "SP7 9LW",
    "wof:placetype": "postalcode"
  },
  "geometry": {"coordinates":[-2.139691,51.004216],"type":"Point"}
}
