{
  "type": "Feature",
  "properties": {
    "date:inception_lower":"2004-08-01",
    "date:inception_upper":"2004-08-31",
    "iso:country":"GB",
    "wof:name":"SP7 9LW",
    "wof:placetype":"postalcode"
},
  "geometry": {"coordinates":[-2.139691,51.004216],"type":"Point"}
}