{
  "type": "Feature",
  "properties": {
    "iso:country": "GB",
    "wof:name": "MK4 4LU",
    "wof:placetype": "postalcode"
  },
  "geometry": {"coordinates":[-0.804324,51.997923],"type":"Point"}
}
