{
  "type": "Feature",
  "properties": {
    "date:inception_lower": "2019-10-01",
    "date:inception_upper": "2019-10-01",
    "iso:country": "GB",
    "wof:name": "MK4 4LU",
    "wof:placetype": "postalcode"
  },
  "geometry": {"coordinates":[-0.80389,51.997819],"type":"Point"}
}
