{
  "type": "Feature",
  "properties": {
    "date:inception_lower": "1980-01-01",
    "date:inception_upper": "1980-01-01",
    "iso:country": "GB",
    "wof:name": "TA24 5DP",
    "wof:placetype": "postalcode"
  },
  "geometry": {"coordinates":[-3.475016,51.203939],"type":"Point"}
}
