{
  "type": "Feature",
  "properties": {
    "iso:country": "GB",
    "wof:name": "GL6 6ED",
    "wof:placetype": "postalcode"
  },
  "geometry": {"coordinates":[-2.227612,51.762488],"type":"Point"}
}
