{
  "type": "Feature",
  "properties": {
    "iso:country":"GB",
    "wof:name":"TW15 1DS",
    "wof:placetype":"postalcode"
},
  "geometry": {"coordinates":[-0.44873933536175,51.43253747276979],"type":"Point"}
}