{
  "type": "Feature",
  "properties": {
    "iso:country":"GB",
    "wof:name":"SE17 2AF",
    "wof:placetype":"postalcode"
},
  "geometry": {"coordinates":[-0.08406631632334,51.48838393990204],"type":"Point"}
}