{
  "type": "Feature",
  "properties": {
    "date:inception_lower": "1982-03-01",
    "date:inception_upper": "1982-03-01",
    "iso:country": "GB",
    "wof:name": "MK46 5BT",
    "wof:placetype": "postalcode"
  },
  "geometry": {"coordinates":[-0.707657,52.13933],"type":"Point"}
}
