{
  "type": "Feature",
  "properties": {
    "iso:country":"GB",
    "wof:name":"NE23 7FH",
    "wof:placetype":"postalcode"
},
  "geometry": {"coordinates":[-1.54817795919046,55.06429796075232],"type":"Point"}
}