{
  "type": "Feature",
  "properties": {
    "iso:country": "GB",
    "wof:name": "NE23 7FH",
    "wof:placetype": "postalcode"
  },
  "geometry": {"coordinates":[-1.551877,55.068066],"type":"Point"}
}
