{
  "type": "Feature",
  "properties": {
    "date:inception_lower":"2015-08-01",
    "date:inception_upper":"2015-08-31",
    "iso:country":"GB",
    "wof:name":"NE23 7FH",
    "wof:placetype":"postalcode"
},
  "geometry": {"coordinates":[-1.551877,55.068066],"type":"Point"}
}