{
  "type": "Feature",
  "properties": {
    "iso:country":"GB",
    "wof:name":"DN5 7NP",
    "wof:placetype":"postalcode"
},
  "geometry": {"coordinates":[-1.17049961265083,53.51881390201624],"type":"Point"}
}