{
  "type": "Feature",
  "properties": {
    "iso:country":"GB",
    "wof:name":"HP21 8HB",
    "wof:placetype":"postalcode"
},
  "geometry": {"coordinates":[-0.81521235478494,51.80004325305883],"type":"Point"}
}