{
  "type": "Feature",
  "properties": {
    "iso:country": "GB",
    "wof:name": "EH14 5JS",
    "wof:placetype": "postalcode"
  },
  "geometry": {"coordinates":[-3.301119,55.899871],"type":"Point"}
}
