{
  "type": "Feature",
  "properties": {
    "iso:country":"GB",
    "wof:name":"PO8 9NY",
    "wof:placetype":"postalcode"
},
  "geometry": {"coordinates":[-1.00259657430059,50.9176093385415],"type":"Point"}
}