{
  "type": "Feature",
  "properties": {
    "iso:country": "GB",
    "wof:name": "ST8 6BS",
    "wof:placetype": "postalcode"
  },
  "geometry": {"coordinates":[-2.176022,53.120556],"type":"Point"}
}
