{
  "type": "Feature",
  "properties": {
    "iso:country":"GB",
    "wof:name":"HP22 5LR",
    "wof:placetype":"postalcode"
},
  "geometry": {"coordinates":[-0.70835399511746,51.80224501586601],"type":"Point"}
}