{
  "type": "Feature",
  "properties": {
    "iso:country":"GB",
    "wof:name":"NE46 4SZ",
    "wof:placetype":"postalcode"
},
  "geometry": {"coordinates":[-2.11409221782771,54.99155707013458],"type":"Point"}
}