{
  "type": "Feature",
  "properties": {
    "date:inception_lower":"2001-12-01",
    "date:inception_upper":"2001-12-31",
    "iso:country":"GB",
    "wof:name":"NE46 4SZ",
    "wof:placetype":"postalcode"
},
  "geometry": {"coordinates":[-2.114092,54.991557],"type":"Point"}
}