{
  "type": "Feature",
  "properties": {
    "date:inception_lower":"1984-02-01",
    "date:inception_upper":"1984-02-29",
    "iso:country":"GB",
    "wof:name":"WA7 6HN",
    "wof:placetype":"postalcode"
},
  "geometry": {"coordinates":[-2.6606,53.327083],"type":"Point"}
}