{
  "type": "Feature",
  "properties": {
    "iso:country":"GB",
    "wof:name":"BH20 4BH",
    "wof:placetype":"postalcode"
},
  "geometry": {"coordinates":[-2.12358540108703,50.69293216258646],"type":"Point"}
}