{
  "type": "Feature",
  "properties": {
    "date:inception_lower": "1997-06-01",
    "date:inception_upper": "1997-06-01",
    "iso:country": "GB",
    "wof:name": "BH20 4BH",
    "wof:placetype": "postalcode"
  },
  "geometry": {"coordinates":[-2.123585,50.692932],"type":"Point"}
}
