{
  "type": "Feature",
  "properties": {
    "iso:country":"GB",
    "wof:name":"W1U 3BY",
    "wof:placetype":"postalcode"
},
  "geometry": {"coordinates":[-0.15505104802396,51.51726412175866],"type":"Point"}
}