{
  "type": "Feature",
  "properties": {
    "date:inception_lower":"2000-12-01",
    "date:inception_upper":"2000-12-31",
    "iso:country":"GB",
    "wof:name":"W1U 3BY",
    "wof:placetype":"postalcode"
},
  "geometry": {"coordinates":[-0.155051,51.517264],"type":"Point"}
}