{
  "type": "Feature",
  "properties": {
    "iso:country": "GB",
    "wof:name": "BS35 2QA",
    "wof:placetype": "postalcode"
  },
  "geometry": {"coordinates":[-2.530532,51.586747],"type":"Point"}
}
