{
  "type": "Feature",
  "properties": {
    "iso:country":"GB",
    "wof:name":"NE20 9AS",
    "wof:placetype":"postalcode"
},
  "geometry": {"coordinates":[-1.77653861428675,55.0421508764424],"type":"Point"}
}