{
  "type": "Feature",
  "properties": {
    "date:inception_lower": "1980-01-01",
    "date:inception_upper": "1980-01-01",
    "iso:country": "GB",
    "wof:name": "HG1 4QE",
    "wof:placetype": "postalcode"
  },
  "geometry": {"coordinates":[-1.502991,54.001549],"type":"Point"}
}
