{
  "type": "Feature",
  "properties": {
    "date:inception_lower":"1980-01-01",
    "date:inception_upper":"1980-01-31",
    "iso:country":"GB",
    "wof:name":"EH1 1RF",
    "wof:placetype":"postalcode"
},
  "geometry": {"coordinates":[-3.189854,55.949505],"type":"Point"}
}