{
  "type": "Feature",
  "properties": {
    "date:inception_lower": "1990-07-01",
    "date:inception_upper": "1990-07-01",
    "iso:country": "GB",
    "wof:name": "OX10 6SL",
    "wof:placetype": "postalcode"
  },
  "geometry": {"coordinates":[-1.11243,51.614278],"type":"Point"}
}
