{
  "type": "Feature",
  "properties": {
    "iso:country":"GB",
    "wof:name":"OX10 6SL",
    "wof:placetype":"postalcode"
},
  "geometry": {"coordinates":[-1.11226725071548,51.61402112847455],"type":"Point"}
}