{
  "type": "Feature",
  "properties": {
    "date:inception_lower":"1980-01-01",
    "date:inception_upper":"1980-01-31",
    "iso:country":"GB",
    "wof:name":"KT16 0QZ",
    "wof:placetype":"postalcode"
},
  "geometry": {"coordinates":[-0.535084,51.354516],"type":"Point"}
}