{
  "type": "Feature",
  "properties": {
    "iso:country": "GB",
    "wof:name": "AL4 0SH",
    "wof:placetype": "postalcode"
  },
  "geometry": {"coordinates":[-0.300925,51.744308],"type":"Point"}
}
