{
  "type": "Feature",
  "properties": {
    "date:inception_lower": "1998-12-01",
    "date:inception_upper": "1998-12-01",
    "iso:country": "GB",
    "wof:name": "AL4 0SH",
    "wof:placetype": "postalcode"
  },
  "geometry": {"coordinates":[-0.300925,51.744308],"type":"Point"}
}
