{
  "type": "Feature",
  "properties": {
    "iso:country":"GB",
    "wof:name":"AL4 0SH",
    "wof:placetype":"postalcode"
},
  "geometry": {"coordinates":[-0.30092488110279,51.74430789167496],"type":"Point"}
}