{
  "type": "Feature",
  "properties": {
    "iso:country":"GB",
    "wof:name":"HD6 4DY",
    "wof:placetype":"postalcode"
},
  "geometry": {"coordinates":[-1.77626185718998,53.72323967293621],"type":"Point"}
}