{
  "type": "Feature",
  "properties": {
    "date:inception_lower":"2009-06-01",
    "date:inception_upper":"2009-06-30",
    "iso:country":"GB",
    "wof:name":"BN8 6QZ",
    "wof:placetype":"postalcode"
},
  "geometry": {"coordinates":[0.17994,50.936382],"type":"Point"}
}