{
  "type": "Feature",
  "properties": {
    "iso:country": "GB",
    "wof:name": "MK43 9RR",
    "wof:placetype": "postalcode"
  },
  "geometry": {"coordinates":[-0.524025,52.091259],"type":"Point"}
}
