{
  "type": "Feature",
  "properties": {
    "date:inception_lower": "2019-03-01",
    "date:inception_upper": "2019-03-01",
    "iso:country": "GB",
    "wof:name": "MK43 9RR",
    "wof:placetype": "postalcode"
  },
  "geometry": {"coordinates":[-0.524959,52.091253],"type":"Point"}
}
