{
  "type": "Feature",
  "properties": {
    "iso:country": "GB",
    "wof:name": "EX23 0DU",
    "wof:placetype": "postalcode"
  },
  "geometry": {"coordinates":[-4.543665,50.760364],"type":"Point"}
}
