{
  "type": "Feature",
  "properties": {
    "date:inception_lower": "2022-07-01",
    "date:inception_upper": "2022-07-01",
    "iso:country": "GB",
    "wof:name": "TS8 9GT",
    "wof:placetype": "postalcode"
  },
  "geometry": {"coordinates":[-1.232245,54.517881],"type":"Point"}
}
