{
  "type": "Feature",
  "properties": {
    "iso:country":"GB",
    "wof:name":"SE2 9LP",
    "wof:placetype":"postalcode"
},
  "geometry": {"coordinates":[0.11276746917233,51.4914233662082],"type":"Point"}
}