{
  "type": "Feature",
  "properties": {
    "iso:country": "GB",
    "wof:name": "LE7 9DW",
    "wof:placetype": "postalcode"
  },
  "geometry": {"coordinates":[-1.031674,52.635065],"type":"Point"}
}
