{
  "type": "Feature",
  "properties": {
    "date:inception_lower": "2019-12-01",
    "date:inception_upper": "2019-12-01",
    "iso:country": "GB",
    "wof:name": "LE7 9DW",
    "wof:placetype": "postalcode"
  },
  "geometry": {"coordinates":[-1.031592,52.634732],"type":"Point"}
}
