{
  "type": "Feature",
  "properties": {
    "iso:country":"GB",
    "wof:name":"EN2 6EY",
    "wof:placetype":"postalcode"
},
  "geometry": {"coordinates":[-0.08377833843682,51.64726767631123],"type":"Point"}
}