{
  "type": "Feature",
  "properties": {
    "iso:country": "GB",
    "wof:name": "IP7 6LF",
    "wof:placetype": "postalcode"
  },
  "geometry": {"coordinates":[0.952449,52.061565],"type":"Point"}
}
