{
  "type": "Feature",
  "properties": {
    "iso:country":"GB",
    "wof:name":"IP7 6LF",
    "wof:placetype":"postalcode"
},
  "geometry": {"coordinates":[0.95256331374539,52.06154739196496],"type":"Point"}
}