{
  "type": "Feature",
  "properties": {
    "iso:country":"GB",
    "wof:name":"KT9 1PU",
    "wof:placetype":"postalcode"
},
  "geometry": {"coordinates":[-0.3110135712171,51.3687117614559],"type":"Point"}
}