{
  "type": "Feature",
  "properties": {
    "iso:country": "GB",
    "wof:name": "ME14 3DW",
    "wof:placetype": "postalcode"
  },
  "geometry": {"coordinates":[0.513237,51.309084],"type":"Point"}
}
