{
  "type": "Feature",
  "properties": {
    "iso:country":"GB",
    "wof:name":"NN11 3SB",
    "wof:placetype":"postalcode"
},
  "geometry": {"coordinates":[-1.18716880990506,52.16097838621034],"type":"Point"}
}