{
  "type": "Feature",
  "properties": {
    "date:inception_lower": "1993-08-01",
    "date:inception_upper": "1993-08-01",
    "iso:country": "GB",
    "wof:name": "NN11 3SB",
    "wof:placetype": "postalcode"
  },
  "geometry": {"coordinates":[-1.187101,52.160676],"type":"Point"}
}
