{
  "type": "Feature",
  "properties": {
    "iso:country":"GB",
    "wof:name":"TN5 6JN",
    "wof:placetype":"postalcode"
},
  "geometry": {"coordinates":[0.30670544834644,51.06023140004746],"type":"Point"}
}