{
  "type": "Feature",
  "properties": {
    "iso:country": "GB",
    "wof:name": "SA14 9AN",
    "wof:placetype": "postalcode"
  },
  "geometry": {"coordinates":[-4.113591,51.682788],"type":"Point"}
}
