{
  "type": "Feature",
  "properties": {
    "iso:country":"GB",
    "wof:name":"SA14 9AN",
    "wof:placetype":"postalcode"
},
  "geometry": {"coordinates":[-4.11359761281886,51.68276392962461],"type":"Point"}
}