{
  "type": "Feature",
  "properties": {
    "date:inception_lower": "1980-01-01",
    "date:inception_upper": "1980-01-01",
    "iso:country": "GB",
    "wof:name": "BS9 2LX",
    "wof:placetype": "postalcode"
  },
  "geometry": {"coordinates":[-2.644738,51.492366],"type":"Point"}
}
