{
  "type": "Feature",
  "properties": {
    "iso:country":"GB",
    "wof:name":"BS9 2LX",
    "wof:placetype":"postalcode"
},
  "geometry": {"coordinates":[-2.64473823995433,51.49236594109539],"type":"Point"}
}