{
  "type": "Feature",
  "properties": {
    "iso:country": "GB",
    "wof:name": "BD21 1DP",
    "wof:placetype": "postalcode"
  },
  "geometry": {"coordinates":[-1.912614,53.860761],"type":"Point"}
}
