{
  "type": "Feature",
  "properties": {
    "iso:country": "GB",
    "wof:name": "YO61 1NH",
    "wof:placetype": "postalcode"
  },
  "geometry": {"coordinates":[-1.080375,54.106285],"type":"Point"}
}
