{
  "type": "Feature",
  "properties": {
    "iso:country":"GB",
    "wof:name":"WA9 3TE",
    "wof:placetype":"postalcode"
},
  "geometry": {"coordinates":[-2.71970919242315,53.43476786050189],"type":"Point"}
}