{
  "type": "Feature",
  "properties": {
    "date:inception_lower": "1980-01-01",
    "date:inception_upper": "1980-01-01",
    "iso:country": "GB",
    "wof:name": "WA9 3TE",
    "wof:placetype": "postalcode"
  },
  "geometry": {"coordinates":[-2.719709,53.434768],"type":"Point"}
}
