{
  "type": "Feature",
  "properties": {
    "iso:country": "GB",
    "wof:name": "WA9 3TE",
    "wof:placetype": "postalcode"
  },
  "geometry": {"coordinates":[-2.719709,53.434768],"type":"Point"}
}
