{
  "type": "Feature",
  "properties": {
    "date:inception_lower": "2000-12-01",
    "date:inception_upper": "2000-12-01",
    "iso:country": "GB",
    "wof:name": "BB9 6DU",
    "wof:placetype": "postalcode"
  },
  "geometry": {"coordinates":[-2.228963,53.8393],"type":"Point"}
}
