{
  "type": "Feature",
  "properties": {
    "iso:country": "GB",
    "wof:name": "PL19 8DG",
    "wof:placetype": "postalcode"
  },
  "geometry": {"coordinates":[-4.148163,50.542682],"type":"Point"}
}
