{
  "type": "Feature",
  "properties": {
    "iso:country":"GB",
    "wof:name":"PL19 8DG",
    "wof:placetype":"postalcode"
},
  "geometry": {"coordinates":[-4.14816265852961,50.54268210137929],"type":"Point"}
}