{
  "type": "Feature",
  "properties": {
    "date:inception_lower": "2003-06-01",
    "date:inception_upper": "2003-06-01",
    "iso:country": "GB",
    "wof:name": "EH54 7EX",
    "wof:placetype": "postalcode"
  },
  "geometry": {"coordinates":[-3.529509,55.88231],"type":"Point"}
}
