{
  "type": "Feature",
  "properties": {
    "iso:country":"GB",
    "wof:name":"EH54 7EX",
    "wof:placetype":"postalcode"
},
  "geometry": {"coordinates":[-3.52950868571102,55.88231041530112],"type":"Point"}
}