{
  "type": "Feature",
  "properties": {
    "date:inception_lower":"1994-05-01",
    "date:inception_upper":"1994-05-31",
    "iso:country":"GB",
    "wof:name":"SY10 9BT",
    "wof:placetype":"postalcode"
},
  "geometry": {"coordinates":[-3.100858,52.833328],"type":"Point"}
}