{
  "type": "Feature",
  "properties": {
    "date:inception_lower": "1980-01-01",
    "date:inception_upper": "1980-01-01",
    "iso:country": "GB",
    "wof:name": "SS4 2EG",
    "wof:placetype": "postalcode"
  },
  "geometry": {"coordinates":[0.80339,51.595891],"type":"Point"}
}
