{
  "type": "Feature",
  "properties": {
    "iso:country":"GB",
    "wof:name":"LA18 4JD",
    "wof:placetype":"postalcode"
},
  "geometry": {"coordinates":[-3.27636450263073,54.20702692751947],"type":"Point"}
}