{
  "type": "Feature",
  "properties": {
    "date:inception_lower":"1991-09-01",
    "date:inception_upper":"1991-09-30",
    "iso:country":"GB",
    "wof:name":"NR9 4BN",
    "wof:placetype":"postalcode"
},
  "geometry": {"coordinates":[1.122734,52.626647],"type":"Point"}
}