{
  "type": "Feature",
  "properties": {
    "iso:country":"GB",
    "wof:name":"NR9 4BN",
    "wof:placetype":"postalcode"
},
  "geometry": {"coordinates":[1.12273434665771,52.6266474921167],"type":"Point"}
}