{
  "type": "Feature",
  "properties": {
    "date:inception_lower": "1992-08-01",
    "date:inception_upper": "1992-08-01",
    "iso:country": "GB",
    "wof:name": "MK13 7BQ",
    "wof:placetype": "postalcode"
  },
  "geometry": {"coordinates":[-0.785467,52.06304],"type":"Point"}
}
