{
  "type": "Feature",
  "properties": {
    "iso:country":"GB",
    "wof:name":"CH46 6BG",
    "wof:placetype":"postalcode"
},
  "geometry": {"coordinates":[-3.12487356878852,53.4020376547229],"type":"Point"}
}