{
  "type": "Feature",
  "properties": {
    "iso:country": "GB",
    "wof:name": "CH46 6BG",
    "wof:placetype": "postalcode"
  },
  "geometry": {"coordinates":[-3.124874,53.402038],"type":"Point"}
}
