{
  "type": "Feature",
  "properties": {
    "iso:country":"GB",
    "wof:name":"CH61 1BX",
    "wof:placetype":"postalcode"
},
  "geometry": {"coordinates":[-3.07326445647657,53.34754478469329],"type":"Point"}
}