{
  "type": "Feature",
  "properties": {
    "iso:country":"GB",
    "wof:name":"SS1 3LJ",
    "wof:placetype":"postalcode"
},
  "geometry": {"coordinates":[0.76431264051437,51.53310087282575],"type":"Point"}
}