{
  "type": "Feature",
  "properties": {
    "iso:country": "GB",
    "wof:name": "SS1 3LJ",
    "wof:placetype": "postalcode"
  },
  "geometry": {"coordinates":[0.764313,51.533101],"type":"Point"}
}
