{
  "type": "Feature",
  "properties": {
    "date:inception_lower": "1980-01-01",
    "date:inception_upper": "1980-01-01",
    "iso:country": "GB",
    "wof:name": "L27 2YA",
    "wof:placetype": "postalcode"
  },
  "geometry": {"coordinates":[-2.843081,53.39761],"type":"Point"}
}
