{
  "type": "Feature",
  "properties": {
    "iso:country":"GB",
    "wof:name":"L27 2YA",
    "wof:placetype":"postalcode"
},
  "geometry": {"coordinates":[-2.84308098364784,53.39760978250501],"type":"Point"}
}