{
  "type": "Feature",
  "properties": {
    "iso:country":"GB",
    "wof:name":"NR10 3LT",
    "wof:placetype":"postalcode"
},
  "geometry": {"coordinates":[1.29453216074766,52.71216025077074],"type":"Point"}
}