{
  "type": "Feature",
  "properties": {
    "date:inception_lower":"1980-01-01",
    "date:inception_upper":"1980-01-31",
    "iso:country":"GB",
    "wof:name":"G74 3AE",
    "wof:placetype":"postalcode"
},
  "geometry": {"coordinates":[-4.158761,55.772425],"type":"Point"}
}