{
  "type": "Feature",
  "properties": {
    "iso:country": "GB",
    "wof:name": "DE65 5FD",
    "wof:placetype": "postalcode"
  },
  "geometry": {"coordinates":[-1.635626,52.874508],"type":"Point"}
}
