{
  "type": "Feature",
  "properties": {
    "iso:country":"GB",
    "wof:name":"TN23 5LF",
    "wof:placetype":"postalcode"
},
  "geometry": {"coordinates":[0.84190032796765,51.13309322478174],"type":"Point"}
}