{
  "type": "Feature",
  "properties": {
    "date:inception_lower": "1994-12-01",
    "date:inception_upper": "1994-12-01",
    "iso:country": "GB",
    "wof:name": "TN23 5LF",
    "wof:placetype": "postalcode"
  },
  "geometry": {"coordinates":[0.8419,51.133093],"type":"Point"}
}
