{
  "type": "Feature",
  "properties": {
    "iso:country":"GB",
    "wof:name":"S40 4UP",
    "wof:placetype":"postalcode"
},
  "geometry": {"coordinates":[-1.47078701723105,53.24809922979097],"type":"Point"}
}