{
  "type": "Feature",
  "properties": {
    "iso:country":"GB",
    "wof:name":"SE6 3HP",
    "wof:placetype":"postalcode"
},
  "geometry": {"coordinates":[-0.02437859961041,51.42995700514624],"type":"Point"}
}