{
  "type": "Feature",
  "properties": {
    "iso:country":"GB",
    "wof:name":"YO25 8SL",
    "wof:placetype":"postalcode"
},
  "geometry": {"coordinates":[-0.21828228904936,53.97752442552977],"type":"Point"}
}