{
  "type": "Feature",
  "properties": {
    "iso:country": "GB",
    "wof:name": "YO25 8SL",
    "wof:placetype": "postalcode"
  },
  "geometry": {"coordinates":[-0.218282,53.977524],"type":"Point"}
}
