{
  "type": "Feature",
  "properties": {
    "iso:country": "GB",
    "wof:name": "EC4Y 7EB",
    "wof:placetype": "postalcode"
  },
  "geometry": {"coordinates":[-0.108543,51.51202],"type":"Point"}
}
