{
  "type": "Feature",
  "properties": {
    "date:inception_lower": "1980-01-01",
    "date:inception_upper": "1980-01-01",
    "iso:country": "GB",
    "wof:name": "EC4Y 7EB",
    "wof:placetype": "postalcode"
  },
  "geometry": {"coordinates":[-0.108543,51.51202],"type":"Point"}
}
