{
  "type": "Feature",
  "properties": {
    "iso:country":"GB",
    "wof:name":"EC4Y 7EB",
    "wof:placetype":"postalcode"
},
  "geometry": {"coordinates":[-0.10856919356967,51.51201850674293],"type":"Point"}
}