{
  "type": "Feature",
  "properties": {
    "date:inception_lower": "2013-08-01",
    "date:inception_upper": "2013-08-01",
    "iso:country": "GB",
    "wof:name": "SO21 1RD",
    "wof:placetype": "postalcode"
  },
  "geometry": {"coordinates":[-1.296369,51.052974],"type":"Point"}
}
