{
  "type": "Feature",
  "properties": {
    "date:inception_lower":"1993-08-01",
    "date:inception_upper":"1993-08-31",
    "iso:country":"GB",
    "wof:name":"SG5 2JJ",
    "wof:placetype":"postalcode"
},
  "geometry": {"coordinates":[-0.2867,51.954592],"type":"Point"}
}