{
  "type": "Feature",
  "properties": {
    "iso:country":"GB",
    "wof:name":"YO25 5XS",
    "wof:placetype":"postalcode"
},
  "geometry": {"coordinates":[-0.46104095611062,54.00825809064132],"type":"Point"}
}