{
  "type": "Feature",
  "properties": {
    "iso:country":"GB",
    "wof:name":"CO13 0LQ",
    "wof:placetype":"postalcode"
},
  "geometry": {"coordinates":[1.22382438401114,51.84063254763625],"type":"Point"}
}