{
  "type": "Feature",
  "properties": {
    "iso:country":"GB",
    "wof:name":"IP19 9NB",
    "wof:placetype":"postalcode"
},
  "geometry": {"coordinates":[1.61433011402527,52.30625404039069],"type":"Point"}
}