{
  "type": "Feature",
  "properties": {
    "date:inception_lower":"1980-01-01",
    "date:inception_upper":"1980-01-31",
    "iso:country":"GB",
    "wof:name":"IP19 9NB",
    "wof:placetype":"postalcode"
},
  "geometry": {"coordinates":[1.61433,52.306254],"type":"Point"}
}