{
  "type": "Feature",
  "properties": {
    "iso:country": "GB",
    "wof:name": "IP19 9NB",
    "wof:placetype": "postalcode"
  },
  "geometry": {"coordinates":[1.61433,52.306254],"type":"Point"}
}
