{
  "type": "Feature",
  "properties": {
    "iso:country":"GB",
    "wof:name":"LN7 6RJ",
    "wof:placetype":"postalcode"
},
  "geometry": {"coordinates":[-0.30559318717144,53.49820552688195],"type":"Point"}
}