{
  "type": "Feature",
  "properties": {
    "iso:country": "GB",
    "wof:name": "IP14 5JR",
    "wof:placetype": "postalcode"
  },
  "geometry": {"coordinates":[1.087745,52.215452],"type":"Point"}
}
