{
  "type": "Feature",
  "properties": {
    "date:inception_lower": "2021-02-01",
    "date:inception_upper": "2021-02-01",
    "iso:country": "GB",
    "wof:name": "CM1 9GU",
    "wof:placetype": "postalcode"
  },
  "geometry": {"coordinates":[0.500628,51.742499],"type":"Point"}
}
