{
  "type": "Feature",
  "properties": {
    "iso:country": "GB",
    "wof:name": "HP22 4PD",
    "wof:placetype": "postalcode"
  },
  "geometry": {"coordinates":[-0.737719,51.863121],"type":"Point"}
}
