{
  "type": "Feature",
  "properties": {
    "iso:country":"GB",
    "wof:name":"HP22 4PD",
    "wof:placetype":"postalcode"
},
  "geometry": {"coordinates":[-0.73771899053832,51.86312138066544],"type":"Point"}
}