{
  "type": "Feature",
  "properties": {
    "date:inception_lower": "1992-01-01",
    "date:inception_upper": "1992-01-01",
    "iso:country": "GB",
    "wof:name": "RH7 6LA",
    "wof:placetype": "postalcode"
  },
  "geometry": {"coordinates":[-0.050356,51.194796],"type":"Point"}
}
