{
  "type": "Feature",
  "properties": {
    "date:inception_lower": "1993-08-01",
    "date:inception_upper": "1993-08-01",
    "iso:country": "GB",
    "wof:name": "DY10 1JB",
    "wof:placetype": "postalcode"
  },
  "geometry": {"coordinates":[-2.250987,52.376472],"type":"Point"}
}
