{
  "type": "Feature",
  "properties": {
    "iso:country":"GB",
    "wof:name":"DY10 1JB",
    "wof:placetype":"postalcode"
},
  "geometry": {"coordinates":[-2.2509872100695,52.37647161529754],"type":"Point"}
}