{
  "type": "Feature",
  "properties": {
    "iso:country":"GB",
    "wof:name":"FK13 6EL",
    "wof:placetype":"postalcode"
},
  "geometry": {"coordinates":[-3.74298813299433,56.15436934114386],"type":"Point"}
}