{
  "type": "Feature",
  "properties": {
    "iso:country":"GB",
    "wof:name":"WF13 2EB",
    "wof:placetype":"postalcode"
},
  "geometry": {"coordinates":[-1.63181063151573,53.69658391759447],"type":"Point"}
}