{
  "type": "Feature",
  "properties": {
    "iso:country":"GB",
    "wof:name":"NE46 1SX",
    "wof:placetype":"postalcode"
},
  "geometry": {"coordinates":[-2.08335983521282,54.92857072180552],"type":"Point"}
}