{
  "type": "Feature",
  "properties": {
    "iso:country":"GB",
    "wof:name":"M46 9QN",
    "wof:placetype":"postalcode"
},
  "geometry": {"coordinates":[-2.47428233502229,53.533367576236],"type":"Point"}
}