{
  "type": "Feature",
  "properties": {
    "date:inception_lower":"1980-01-01",
    "date:inception_upper":"1980-01-31",
    "iso:country":"GB",
    "wof:name":"CT16 1EL",
    "wof:placetype":"postalcode"
},
  "geometry": {"coordinates":[1.308898,51.129932],"type":"Point"}
}