{
  "type": "Feature",
  "properties": {
    "iso:country":"GB",
    "wof:name":"CT16 1EL",
    "wof:placetype":"postalcode"
},
  "geometry": {"coordinates":[1.30889839838004,51.12993240753546],"type":"Point"}
}