{
  "type": "Feature",
  "properties": {
    "iso:country":"GB",
    "wof:name":"CF72 9TA",
    "wof:placetype":"postalcode"
},
  "geometry": {"coordinates":[-3.45341993516334,51.540179646993],"type":"Point"}
}