{
  "type": "Feature",
  "properties": {
    "date:inception_lower": "2005-08-01",
    "date:inception_upper": "2005-08-01",
    "iso:country": "GB",
    "wof:name": "HU7 4WG",
    "wof:placetype": "postalcode"
  },
  "geometry": {"coordinates":[-0.342266,53.781559],"type":"Point"}
}
