{
  "type": "Feature",
  "properties": {
    "iso:country":"GB",
    "wof:name":"SK3 0SN",
    "wof:placetype":"postalcode"
},
  "geometry": {"coordinates":[-2.19031444069942,53.39894371892594],"type":"Point"}
}