{
  "type": "Feature",
  "properties": {
    "iso:country":"GB",
    "wof:name":"CO12 5HD",
    "wof:placetype":"postalcode"
},
  "geometry": {"coordinates":[1.21800246076915,51.93600513300639],"type":"Point"}
}