{
  "type": "Feature",
  "properties": {
    "iso:country": "GB",
    "wof:name": "CO12 5HD",
    "wof:placetype": "postalcode"
  },
  "geometry": {"coordinates":[1.218033,51.936018],"type":"Point"}
}
