{
  "type": "Feature",
  "properties": {
    "date:inception_lower":"1980-01-01",
    "date:inception_upper":"1980-01-31",
    "iso:country":"GB",
    "wof:name":"CO12 5HD",
    "wof:placetype":"postalcode"
},
  "geometry": {"coordinates":[1.218033,51.936018],"type":"Point"}
}