{
  "type": "Feature",
  "properties": {
    "date:inception_lower": "1980-01-01",
    "date:inception_upper": "1980-01-01",
    "iso:country": "GB",
    "wof:name": "SO20 8AB",
    "wof:placetype": "postalcode"
  },
  "geometry": {"coordinates":[-1.55963,51.096099],"type":"Point"}
}
