{
  "type": "Feature",
  "properties": {
    "date:inception_lower": "1980-01-01",
    "date:inception_upper": "1980-01-01",
    "iso:country": "GB",
    "wof:name": "HU9 3QP",
    "wof:placetype": "postalcode"
  },
  "geometry": {"coordinates":[-0.284389,53.76194],"type":"Point"}
}
