{
  "type": "Feature",
  "properties": {
    "iso:country": "GB",
    "wof:name": "HU9 3QP",
    "wof:placetype": "postalcode"
  },
  "geometry": {"coordinates":[-0.284389,53.76194],"type":"Point"}
}
