{
  "type": "Feature",
  "properties": {
    "iso:country":"GB",
    "wof:name":"HU9 3QP",
    "wof:placetype":"postalcode"
},
  "geometry": {"coordinates":[-0.28438884232395,53.76193974525622],"type":"Point"}
}