{
  "type": "Feature",
  "properties": {
    "iso:country":"GB",
    "wof:name":"AB16 5SZ",
    "wof:placetype":"postalcode"
},
  "geometry": {"coordinates":[-2.1540851969046,57.15779496503797],"type":"Point"}
}