{
  "type": "Feature",
  "properties": {
    "iso:country":"GB",
    "wof:name":"LU5 5BN",
    "wof:placetype":"postalcode"
},
  "geometry": {"coordinates":[-0.52087407260085,51.89469126725329],"type":"Point"}
}