{
  "type": "Feature",
  "properties": {
    "iso:country": "GB",
    "wof:name": "LU5 5BN",
    "wof:placetype": "postalcode"
  },
  "geometry": {"coordinates":[-0.520874,51.894691],"type":"Point"}
}
