{
  "type": "Feature",
  "properties": {
    "iso:country":"GB",
    "wof:name":"BA11 3JX",
    "wof:placetype":"postalcode"
},
  "geometry": {"coordinates":[-2.37273796068945,51.22389353445491],"type":"Point"}
}