{
  "type": "Feature",
  "properties": {
    "iso:country": "GB",
    "wof:name": "OX15 0QR",
    "wof:placetype": "postalcode"
  },
  "geometry": {"coordinates":[-1.349951,51.984016],"type":"Point"}
}
