{
  "type": "Feature",
  "properties": {
    "iso:country":"GB",
    "wof:name":"OX15 0QR",
    "wof:placetype":"postalcode"
},
  "geometry": {"coordinates":[-1.34995127945843,51.98401602141701],"type":"Point"}
}