{
  "type": "Feature",
  "properties": {
    "iso:country": "GB",
    "wof:name": "AB12 5WG",
    "wof:placetype": "postalcode"
  },
  "geometry": {"coordinates":[-2.202021,57.101145],"type":"Point"}
}
