{
  "type": "Feature",
  "properties": {
    "iso:country": "GB",
    "wof:name": "AB12 5WG",
    "wof:placetype": "postalcode"
  },
  "geometry": {"coordinates":[-2.201873,57.101146],"type":"Point"}
}
