{
  "type": "Feature",
  "properties": {
    "date:inception_lower": "2015-05-01",
    "date:inception_upper": "2015-05-01",
    "iso:country": "GB",
    "wof:name": "BR2 9UQ",
    "wof:placetype": "postalcode"
  },
  "geometry": {"coordinates":[0.038029,51.386973],"type":"Point"}
}
