{
  "type": "Feature",
  "properties": {
    "iso:country":"GB",
    "wof:name":"WF16 9QE",
    "wof:placetype":"postalcode"
},
  "geometry": {"coordinates":[-1.67005255470954,53.71597481861738],"type":"Point"}
}