{
  "type": "Feature",
  "properties": {
    "iso:country": "GB",
    "wof:name": "WF16 9QE",
    "wof:placetype": "postalcode"
  },
  "geometry": {"coordinates":[-1.670053,53.715975],"type":"Point"}
}
