{
  "type": "Feature",
  "properties": {
    "iso:country": "GB",
    "wof:name": "M18 8AD",
    "wof:placetype": "postalcode"
  },
  "geometry": {"coordinates":[-2.18587,53.466095],"type":"Point"}
}
