{
  "type": "Feature",
  "properties": {
    "iso:country":"GB",
    "wof:name":"M18 8AD",
    "wof:placetype":"postalcode"
},
  "geometry": {"coordinates":[-2.1858701839552,53.46609498329261],"type":"Point"}
}