{
  "type": "Feature",
  "properties": {
    "iso:country": "GB",
    "wof:name": "WS11 8JX",
    "wof:placetype": "postalcode"
  },
  "geometry": {"coordinates":[-2.01896,52.670149],"type":"Point"}
}
