{
  "type": "Feature",
  "properties": {
    "iso:country":"GB",
    "wof:name":"WS11 8JX",
    "wof:placetype":"postalcode"
},
  "geometry": {"coordinates":[-2.01895966300062,52.6701491648768],"type":"Point"}
}