{
  "type": "Feature",
  "properties": {
    "date:inception_lower":"2003-03-01",
    "date:inception_upper":"2003-03-31",
    "iso:country":"GB",
    "wof:name":"WS11 8JX",
    "wof:placetype":"postalcode"
},
  "geometry": {"coordinates":[-2.01896,52.670149],"type":"Point"}
}