{
  "type": "Feature",
  "properties": {
    "iso:country":"GB",
    "wof:name":"CO10 8DD",
    "wof:placetype":"postalcode"
},
  "geometry": {"coordinates":[0.62200087212689,52.10329991102762],"type":"Point"}
}