{
  "type": "Feature",
  "properties": {
    "date:inception_lower": "1980-01-01",
    "date:inception_upper": "1980-01-01",
    "iso:country": "GB",
    "wof:name": "CO10 8DD",
    "wof:placetype": "postalcode"
  },
  "geometry": {"coordinates":[0.622031,52.103314],"type":"Point"}
}
