{
  "type": "Feature",
  "properties": {
    "iso:country":"GB",
    "wof:name":"NW9 7EA",
    "wof:placetype":"postalcode"
},
  "geometry": {"coordinates":[-0.23927450033636,51.57685602924838],"type":"Point"}
}