{
  "type": "Feature",
  "properties": {
    "iso:country":"GB",
    "wof:name":"ME7 1DB",
    "wof:placetype":"postalcode"
},
  "geometry": {"coordinates":[0.54908861264296,51.38760559262575],"type":"Point"}
}