{
  "type": "Feature",
  "properties": {
    "date:inception_lower": "1980-01-01",
    "date:inception_upper": "1980-01-01",
    "iso:country": "GB",
    "wof:name": "ST18 9BU",
    "wof:placetype": "postalcode"
  },
  "geometry": {"coordinates":[-2.149064,52.769967],"type":"Point"}
}
