{
  "type": "Feature",
  "properties": {
    "iso:country":"GB",
    "wof:name":"HP16 9QN",
    "wof:placetype":"postalcode"
},
  "geometry": {"coordinates":[-0.68010673945473,51.70913780704799],"type":"Point"}
}