{
  "type": "Feature",
  "properties": {
    "iso:country": "GB",
    "wof:name": "SP10 1QL",
    "wof:placetype": "postalcode"
  },
  "geometry": {"coordinates":[-1.481476,51.205811],"type":"Point"}
}
