{
  "type": "Feature",
  "properties": {
    "date:inception_lower": "1985-10-01",
    "date:inception_upper": "1985-10-01",
    "iso:country": "GB",
    "wof:name": "CH1 5LS",
    "wof:placetype": "postalcode"
  },
  "geometry": {"coordinates":[-2.924079,53.200078],"type":"Point"}
}
