{
  "type": "Feature",
  "properties": {
    "iso:country":"GB",
    "wof:name":"CH1 5LS",
    "wof:placetype":"postalcode"
},
  "geometry": {"coordinates":[-2.92407941904715,53.20007823661401],"type":"Point"}
}