{
  "type": "Feature",
  "properties": {
    "iso:country":"GB",
    "wof:name":"SY11 4BE",
    "wof:placetype":"postalcode"
},
  "geometry": {"coordinates":[-3.01207461203896,52.87217237221333],"type":"Point"}
}