{
  "type": "Feature",
  "properties": {
    "iso:country":"GB",
    "wof:name":"S71 2AY",
    "wof:placetype":"postalcode"
},
  "geometry": {"coordinates":[-1.45991355399896,53.57430271522172],"type":"Point"}
}