{
  "type": "Feature",
  "properties": {
    "iso:country":"GB",
    "wof:name":"NE18 0PE",
    "wof:placetype":"postalcode"
},
  "geometry": {"coordinates":[-1.8789423609325,55.04250223378109],"type":"Point"}
}