{
  "type": "Feature",
  "properties": {
    "date:inception_lower": "1980-01-01",
    "date:inception_upper": "1980-01-01",
    "iso:country": "GB",
    "wof:name": "NE18 0PE",
    "wof:placetype": "postalcode"
  },
  "geometry": {"coordinates":[-1.878953,55.042508],"type":"Point"}
}
