{
  "type": "Feature",
  "properties": {
    "iso:country":"GB",
    "wof:name":"YO7 3RF",
    "wof:placetype":"postalcode"
},
  "geometry": {"coordinates":[-1.35237242407951,54.22024761873146],"type":"Point"}
}