{
  "type": "Feature",
  "properties": {
    "date:inception_lower":"2014-06-01",
    "date:inception_upper":"2014-06-30",
    "iso:country":"GB",
    "wof:name":"YO7 3RF",
    "wof:placetype":"postalcode"
},
  "geometry": {"coordinates":[-1.35264,54.220361],"type":"Point"}
}