{
  "type": "Feature",
  "properties": {
    "iso:country": "GB",
    "wof:name": "YO7 3RF",
    "wof:placetype": "postalcode"
  },
  "geometry": {"coordinates":[-1.353509,54.220708],"type":"Point"}
}
