{
  "type": "Feature",
  "properties": {
    "iso:country":"GB",
    "wof:name":"IP32 6SE",
    "wof:placetype":"postalcode"
},
  "geometry": {"coordinates":[0.69638988058005,52.26016564126621],"type":"Point"}
}