{
  "type": "Feature",
  "properties": {
    "iso:country": "GB",
    "wof:name": "IP32 6SE",
    "wof:placetype": "postalcode"
  },
  "geometry": {"coordinates":[0.69639,52.260166],"type":"Point"}
}
