{
  "type": "Feature",
  "properties": {
    "date:inception_lower": "1980-01-01",
    "date:inception_upper": "1980-01-01",
    "iso:country": "GB",
    "wof:name": "DN36 4AG",
    "wof:placetype": "postalcode"
  },
  "geometry": {"coordinates":[-0.037137,53.536387],"type":"Point"}
}
