{
  "type": "Feature",
  "properties": {
    "iso:country":"GB",
    "wof:name":"GU34 2NL",
    "wof:placetype":"postalcode"
},
  "geometry": {"coordinates":[-0.9771212411592,51.16105806987856],"type":"Point"}
}