{
  "type": "Feature",
  "properties": {
    "date:inception_lower": "1980-01-01",
    "date:inception_upper": "1980-01-01",
    "iso:country": "GB",
    "wof:name": "GU34 2NL",
    "wof:placetype": "postalcode"
  },
  "geometry": {"coordinates":[-0.977106,51.161055],"type":"Point"}
}
