{
  "type": "Feature",
  "properties": {
    "iso:country": "GB",
    "wof:name": "GU34 2NL",
    "wof:placetype": "postalcode"
  },
  "geometry": {"coordinates":[-0.977251,51.160949],"type":"Point"}
}
