{
  "type": "Feature",
  "properties": {
    "iso:country":"GB",
    "wof:name":"ME17 1HS",
    "wof:placetype":"postalcode"
},
  "geometry": {"coordinates":[0.68188449819204,51.24087259213766],"type":"Point"}
}