{
  "type": "Feature",
  "properties": {
    "iso:country":"GB",
    "wof:name":"NN18 0AD",
    "wof:placetype":"postalcode"
},
  "geometry": {"coordinates":[-0.7258135449391,52.48951996580402],"type":"Point"}
}