{
  "type": "Feature",
  "properties": {
    "date:inception_lower": "2019-06-01",
    "date:inception_upper": "2019-06-01",
    "iso:country": "GB",
    "wof:name": "GU16 6FP",
    "wof:placetype": "postalcode"
  },
  "geometry": {"coordinates":[-0.706047,51.303923],"type":"Point"}
}
