{
  "type": "Feature",
  "properties": {
    "iso:country":"GB",
    "wof:name":"ME3 8QR",
    "wof:placetype":"postalcode"
},
  "geometry": {"coordinates":[0.58302001336757,51.44667875629101],"type":"Point"}
}