{
  "type": "Feature",
  "properties": {
    "iso:country": "GB",
    "wof:name": "ME3 8QR",
    "wof:placetype": "postalcode"
  },
  "geometry": {"coordinates":[0.58302,51.446679],"type":"Point"}
}
