{
  "type": "Feature",
  "properties": {
    "date:inception_lower": "2021-11-01",
    "date:inception_upper": "2021-11-01",
    "iso:country": "GB",
    "wof:name": "DE56 2NF",
    "wof:placetype": "postalcode"
  },
  "geometry": {"coordinates":[-1.468541,53.066053],"type":"Point"}
}
