{
  "type": "Feature",
  "properties": {
    "iso:country":"GB",
    "wof:name":"PL5 4EF",
    "wof:placetype":"postalcode"
},
  "geometry": {"coordinates":[-4.15023087945262,50.4170932560456],"type":"Point"}
}