{
  "type": "Feature",
  "properties": {
    "iso:country":"GB",
    "wof:name":"NN7 3RB",
    "wof:placetype":"postalcode"
},
  "geometry": {"coordinates":[-1.00629319149511,52.21059821844023],"type":"Point"}
}