{
  "type": "Feature",
  "properties": {
    "iso:country":"GB",
    "wof:name":"CM20 1AP",
    "wof:placetype":"postalcode"
},
  "geometry": {"coordinates":[0.09215216271363,51.76805571537926],"type":"Point"}
}