{
  "type": "Feature",
  "properties": {
    "date:inception_lower":"2006-01-01",
    "date:inception_upper":"2006-01-31",
    "iso:country":"GB",
    "wof:name":"IP12 3QW",
    "wof:placetype":"postalcode"
},
  "geometry": {"coordinates":[1.432222,52.051502],"type":"Point"}
}