{
  "type": "Feature",
  "properties": {
    "iso:country":"GB",
    "wof:name":"IP12 3QW",
    "wof:placetype":"postalcode"
},
  "geometry": {"coordinates":[1.43222235277472,52.05150156372621],"type":"Point"}
}