{
  "type": "Feature",
  "properties": {
    "iso:country":"GB",
    "wof:name":"L25 4TF",
    "wof:placetype":"postalcode"
},
  "geometry": {"coordinates":[-2.87145005005567,53.3838598130496],"type":"Point"}
}