{
  "type": "Feature",
  "properties": {
    "iso:country": "GB",
    "wof:name": "GL1 5QN",
    "wof:placetype": "postalcode"
  },
  "geometry": {"coordinates":[-2.259107,51.84797],"type":"Point"}
}
