{
  "type": "Feature",
  "properties": {
    "iso:country":"GB",
    "wof:name":"CF5 3SU",
    "wof:placetype":"postalcode"
},
  "geometry": {"coordinates":[-3.25163031415156,51.49603625107733],"type":"Point"}
}