{
  "type": "Feature",
  "properties": {
    "date:inception_lower": "2019-06-01",
    "date:inception_upper": "2019-06-01",
    "iso:country": "GB",
    "wof:name": "BD23 6FB",
    "wof:placetype": "postalcode"
  },
  "geometry": {"coordinates":[-2.00698,53.967582],"type":"Point"}
}
