{
  "type": "Feature",
  "properties": {
    "iso:country":"GB",
    "wof:name":"DG2 9BF",
    "wof:placetype":"postalcode"
},
  "geometry": {"coordinates":[-3.6271193073363,55.07630506855537],"type":"Point"}
}