{
  "type": "Feature",
  "properties": {
    "date:inception_lower": "2001-06-01",
    "date:inception_upper": "2001-06-01",
    "iso:country": "GB",
    "wof:name": "DG2 9BF",
    "wof:placetype": "postalcode"
  },
  "geometry": {"coordinates":[-3.627119,55.076305],"type":"Point"}
}
