{
  "type": "Feature",
  "properties": {
    "iso:country":"GB",
    "wof:name":"DL13 2RW",
    "wof:placetype":"postalcode"
},
  "geometry": {"coordinates":[-1.95728505415838,54.72646969412705],"type":"Point"}
}