{
  "type": "Feature",
  "properties": {
    "iso:country":"GB",
    "wof:name":"DG5 4QH",
    "wof:placetype":"postalcode"
},
  "geometry": {"coordinates":[-3.79196420250527,54.8628781576973],"type":"Point"}
}