{
  "type": "Feature",
  "properties": {
    "date:inception_lower":"2011-01-01",
    "date:inception_upper":"2011-01-31",
    "iso:country":"GB",
    "wof:name":"HP6 6FE",
    "wof:placetype":"postalcode"
},
  "geometry": {"coordinates":[-0.594661,51.674841],"type":"Point"}
}