{
  "type": "Feature",
  "properties": {
    "iso:country": "GB",
    "wof:name": "HP6 6FE",
    "wof:placetype": "postalcode"
  },
  "geometry": {"coordinates":[-0.594661,51.674841],"type":"Point"}
}
