{
  "type": "Feature",
  "properties": {
    "iso:country":"GB",
    "wof:name":"HP6 6FE",
    "wof:placetype":"postalcode"
},
  "geometry": {"coordinates":[-0.59466152179283,51.6748413622009],"type":"Point"}
}