{
  "type": "Feature",
  "properties": {
    "date:inception_lower":"1980-01-01",
    "date:inception_upper":"1980-01-31",
    "iso:country":"GB",
    "wof:name":"SS3 0LF",
    "wof:placetype":"postalcode"
},
  "geometry": {"coordinates":[0.78338,51.565045],"type":"Point"}
}