{
  "type": "Feature",
  "properties": {
    "iso:country":"GB",
    "wof:name":"SK7 4EP",
    "wof:placetype":"postalcode"
},
  "geometry": {"coordinates":[-2.12232394301527,53.3789164314888],"type":"Point"}
}