{
  "type": "Feature",
  "properties": {
    "date:inception_lower": "1980-01-01",
    "date:inception_upper": "1980-01-01",
    "iso:country": "GB",
    "wof:name": "SK7 4EP",
    "wof:placetype": "postalcode"
  },
  "geometry": {"coordinates":[-2.122324,53.378916],"type":"Point"}
}
