{
  "type": "Feature",
  "properties": {
    "iso:country": "GB",
    "wof:name": "SA10 6FY",
    "wof:placetype": "postalcode"
  },
  "geometry": {"coordinates":[-3.861557,51.645041],"type":"Point"}
}
