{
  "type": "Feature",
  "properties": {
    "date:inception_lower":"2015-01-01",
    "date:inception_upper":"2015-01-31",
    "iso:country":"GB",
    "wof:name":"SA10 6FY",
    "wof:placetype":"postalcode"
},
  "geometry": {"coordinates":[-3.861557,51.645041],"type":"Point"}
}