{
  "type": "Feature",
  "properties": {
    "iso:country":"GB",
    "wof:name":"NN11 4QZ",
    "wof:placetype":"postalcode"
},
  "geometry": {"coordinates":[-1.1794965207422,52.25778102950237],"type":"Point"}
}