{
  "type": "Feature",
  "properties": {
    "iso:country":"GB",
    "wof:name":"SN2 2NP",
    "wof:placetype":"postalcode"
},
  "geometry": {"coordinates":[-1.8032397271413,51.57264081143749],"type":"Point"}
}