{
  "type": "Feature",
  "properties": {
    "iso:country":"GB",
    "wof:name":"HD2 2FA",
    "wof:placetype":"postalcode"
},
  "geometry": {"coordinates":[-1.7860577635851,53.67423631524795],"type":"Point"}
}