{
  "type": "Feature",
  "properties": {
    "date:inception_lower": "1993-08-01",
    "date:inception_upper": "1993-08-01",
    "iso:country": "GB",
    "wof:name": "LL53 7DH",
    "wof:placetype": "postalcode"
  },
  "geometry": {"coordinates":[-4.504492,52.80604],"type":"Point"}
}
