{
  "type": "Feature",
  "properties": {
    "iso:country":"GB",
    "wof:name":"LL53 7DH",
    "wof:placetype":"postalcode"
},
  "geometry": {"coordinates":[-4.50449161345919,52.80604047093114],"type":"Point"}
}