{
  "type": "Feature",
  "properties": {
    "iso:country": "GB",
    "wof:name": "SO53 2JD",
    "wof:placetype": "postalcode"
  },
  "geometry": {"coordinates":[-1.3764,50.979285],"type":"Point"}
}
