{
  "type": "Feature",
  "properties": {
    "iso:country": "GB",
    "wof:name": "RM3 8DX",
    "wof:placetype": "postalcode"
  },
  "geometry": {"coordinates":[0.218529,51.606342],"type":"Point"}
}
