{
  "type": "Feature",
  "properties": {
    "iso:country":"GB",
    "wof:name":"RM3 8DX",
    "wof:placetype":"postalcode"
},
  "geometry": {"coordinates":[0.21852939840893,51.60634178584763],"type":"Point"}
}