{
  "type": "Feature",
  "properties": {
    "iso:country":"GB",
    "wof:name":"DL17 0NL",
    "wof:placetype":"postalcode"
},
  "geometry": {"coordinates":[-1.55614011621093,54.64766105291002],"type":"Point"}
}