{
  "type": "Feature",
  "properties": {
    "iso:country":"GB",
    "wof:name":"GU10 5AF",
    "wof:placetype":"postalcode"
},
  "geometry": {"coordinates":[-0.82977660805744,51.23461020037299],"type":"Point"}
}