{
  "type": "Feature",
  "properties": {
    "date:inception_lower":"1983-01-01",
    "date:inception_upper":"1983-01-31",
    "iso:country":"GB",
    "wof:name":"PO14 4NQ",
    "wof:placetype":"postalcode"
},
  "geometry": {"coordinates":[-1.264004,50.854974],"type":"Point"}
}