{
  "type": "Feature",
  "properties": {
    "date:inception_lower": "2019-08-01",
    "date:inception_upper": "2019-08-01",
    "iso:country": "GB",
    "wof:name": "LE7 3AD",
    "wof:placetype": "postalcode"
  },
  "geometry": {"coordinates":[-1.046746,52.703126],"type":"Point"}
}
