{
  "type": "Feature",
  "properties": {
    "iso:country": "GB",
    "wof:name": "LE7 3AD",
    "wof:placetype": "postalcode"
  },
  "geometry": {"coordinates":[-1.046544,52.702873],"type":"Point"}
}
