{
  "type": "Feature",
  "properties": {
    "iso:country":"GB",
    "wof:name":"M46 0QS",
    "wof:placetype":"postalcode"
},
  "geometry": {"coordinates":[-2.50797319576423,53.51709482868153],"type":"Point"}
}