{
  "type": "Feature",
  "properties": {
    "date:inception_lower": "2013-10-01",
    "date:inception_upper": "2013-10-01",
    "iso:country": "GB",
    "wof:name": "DH1 3UD",
    "wof:placetype": "postalcode"
  },
  "geometry": {"coordinates":[-1.564123,54.773423],"type":"Point"}
}
