{
  "type": "Feature",
  "properties": {
    "iso:country":"GB",
    "wof:name":"DH1 3UD",
    "wof:placetype":"postalcode"
},
  "geometry": {"coordinates":[-1.56412337252553,54.77342254648885],"type":"Point"}
}