{
  "type": "Feature",
  "properties": {
    "iso:country": "GB",
    "wof:name": "TA6 4SP",
    "wof:placetype": "postalcode"
  },
  "geometry": {"coordinates":[-3.0034,51.181702],"type":"Point"}
}
