{
  "type": "Feature",
  "properties": {
    "iso:country":"GB",
    "wof:name":"TA6 4SP",
    "wof:placetype":"postalcode"
},
  "geometry": {"coordinates":[-3.00340612477615,51.18172449377262],"type":"Point"}
}