{
  "type": "Feature",
  "properties": {
    "iso:country":"GB",
    "wof:name":"CW2 5AL",
    "wof:placetype":"postalcode"
},
  "geometry": {"coordinates":[-2.44195556109478,53.06611960246924],"type":"Point"}
}