{
  "type": "Feature",
  "properties": {
    "iso:country":"GB",
    "wof:name":"KY12 7TZ",
    "wof:placetype":"postalcode"
},
  "geometry": {"coordinates":[-3.44392010654604,56.0738157426349],"type":"Point"}
}