{
  "type": "Feature",
  "properties": {
    "iso:country":"GB",
    "wof:name":"B77 5AS",
    "wof:placetype":"postalcode"
},
  "geometry": {"coordinates":[-1.66560864239139,52.60908884351087],"type":"Point"}
}