{
  "type": "Feature",
  "properties": {
    "date:inception_lower": "1998-12-01",
    "date:inception_upper": "1998-12-01",
    "iso:country": "GB",
    "wof:name": "B77 5AS",
    "wof:placetype": "postalcode"
  },
  "geometry": {"coordinates":[-1.665609,52.609089],"type":"Point"}
}
