{
  "type": "Feature",
  "properties": {
    "date:inception_lower": "1999-06-01",
    "date:inception_upper": "1999-06-01",
    "iso:country": "GB",
    "wof:name": "NP25 3PS",
    "wof:placetype": "postalcode"
  },
  "geometry": {"coordinates":[-2.718883,51.810487],"type":"Point"}
}
