{
  "type": "Feature",
  "properties": {
    "iso:country":"GB",
    "wof:name":"NP25 3PS",
    "wof:placetype":"postalcode"
},
  "geometry": {"coordinates":[-2.71880642000628,51.81044632941377],"type":"Point"}
}