{
  "type": "Feature",
  "properties": {
    "iso:country":"GB",
    "wof:name":"PO1 5QA",
    "wof:placetype":"postalcode"
},
  "geometry": {"coordinates":[-1.07124915978388,50.80109959140158],"type":"Point"}
}