{
  "type": "Feature",
  "properties": {
    "iso:country": "GB",
    "wof:name": "PO1 5QA",
    "wof:placetype": "postalcode"
  },
  "geometry": {"coordinates":[-1.071249,50.8011],"type":"Point"}
}
