{
  "type": "Feature",
  "properties": {
    "iso:country":"GB",
    "wof:name":"LL68 9HS",
    "wof:placetype":"postalcode"
},
  "geometry": {"coordinates":[-4.33385172279062,53.41101499279524],"type":"Point"}
}