{
  "type": "Feature",
  "properties": {
    "iso:country": "GB",
    "wof:name": "PE15 8PE",
    "wof:placetype": "postalcode"
  },
  "geometry": {"coordinates":[0.091172,52.563076],"type":"Point"}
}
