{
  "type": "Feature",
  "properties": {
    "iso:country":"GB",
    "wof:name":"DN17 3JZ",
    "wof:placetype":"postalcode"
},
  "geometry": {"coordinates":[-0.74417707491391,53.54226141389704],"type":"Point"}
}