{
  "type": "Feature",
  "properties": {
    "iso:country": "GB",
    "wof:name": "SA71 5RP",
    "wof:placetype": "postalcode"
  },
  "geometry": {"coordinates":[-4.952634,51.669675],"type":"Point"}
}
