{
  "type": "Feature",
  "properties": {
    "date:inception_lower": "1980-01-01",
    "date:inception_upper": "1980-01-01",
    "iso:country": "GB",
    "wof:name": "SA71 5RP",
    "wof:placetype": "postalcode"
  },
  "geometry": {"coordinates":[-4.952634,51.669675],"type":"Point"}
}
