{
  "type": "Feature",
  "properties": {
    "iso:country":"GB",
    "wof:name":"SA71 5RP",
    "wof:placetype":"postalcode"
},
  "geometry": {"coordinates":[-4.95263445136015,51.66967544424877],"type":"Point"}
}