{
  "type": "Feature",
  "properties": {
    "iso:country":"GB",
    "wof:name":"BS16 3AP",
    "wof:placetype":"postalcode"
},
  "geometry": {"coordinates":[-2.54396706405312,51.47531626506081],"type":"Point"}
}