{
  "type": "Feature",
  "properties": {
    "iso:country":"GB",
    "wof:name":"G72 0EX",
    "wof:placetype":"postalcode"
},
  "geometry": {"coordinates":[-4.10036540924373,55.78594283550286],"type":"Point"}
}