{
  "type": "Feature",
  "properties": {
    "iso:country":"GB",
    "wof:name":"EC1M 6AS",
    "wof:placetype":"postalcode"
},
  "geometry": {"coordinates":[-0.10047570240532,51.5219233892156],"type":"Point"}
}