{
  "type": "Feature",
  "properties": {
    "iso:country":"GB",
    "wof:name":"DA8 2PR",
    "wof:placetype":"postalcode"
},
  "geometry": {"coordinates":[0.18280329872332,51.47413300775591],"type":"Point"}
}