{
  "type": "Feature",
  "properties": {
    "iso:country":"GB",
    "wof:name":"B11 4NB",
    "wof:placetype":"postalcode"
},
  "geometry": {"coordinates":[-1.86898409191795,52.45060961785451],"type":"Point"}
}