{
  "type": "Feature",
  "properties": {
    "iso:country":"GB",
    "wof:name":"LU5 4EJ",
    "wof:placetype":"postalcode"
},
  "geometry": {"coordinates":[-0.50248224730825,51.87786018483607],"type":"Point"}
}