{
  "type": "Feature",
  "properties": {
    "iso:country":"GB",
    "wof:name":"S73 9BB",
    "wof:placetype":"postalcode"
},
  "geometry": {"coordinates":[-1.3792463533332,53.53981824587382],"type":"Point"}
}