{
  "type": "Feature",
  "properties": {
    "date:inception_lower": "1980-01-01",
    "date:inception_upper": "1980-01-01",
    "iso:country": "GB",
    "wof:name": "S73 9BB",
    "wof:placetype": "postalcode"
  },
  "geometry": {"coordinates":[-1.379246,53.539818],"type":"Point"}
}
