{
  "type": "Feature",
  "properties": {
    "iso:country":"GB",
    "wof:name":"HU6 8DS",
    "wof:placetype":"postalcode"
},
  "geometry": {"coordinates":[-0.36652169171597,53.77878205498174],"type":"Point"}
}