{
  "type": "Feature",
  "properties": {
    "iso:country": "GB",
    "wof:name": "HU6 8DS",
    "wof:placetype": "postalcode"
  },
  "geometry": {"coordinates":[-0.366522,53.778782],"type":"Point"}
}
