{
  "type": "Feature",
  "properties": {
    "iso:country":"GB",
    "wof:name":"PO7 5AS",
    "wof:placetype":"postalcode"
},
  "geometry": {"coordinates":[-1.05038698416362,50.85790075173055],"type":"Point"}
}