{
  "type": "Feature",
  "properties": {
    "iso:country": "GB",
    "wof:name": "PO7 5AS",
    "wof:placetype": "postalcode"
  },
  "geometry": {"coordinates":[-1.050357,50.857927],"type":"Point"}
}
