{
  "type": "Feature",
  "properties": {
    "date:inception_lower":"1980-01-01",
    "date:inception_upper":"1980-01-31",
    "iso:country":"GB",
    "wof:name":"PO7 5AS",
    "wof:placetype":"postalcode"
},
  "geometry": {"coordinates":[-1.050387,50.857901],"type":"Point"}
}