{
  "type": "Feature",
  "properties": {
    "iso:country":"GB",
    "wof:name":"LU4 0QA",
    "wof:placetype":"postalcode"
},
  "geometry": {"coordinates":[-0.48603159246463,51.89747617441976],"type":"Point"}
}