{
  "type": "Feature",
  "properties": {
    "iso:country":"GB",
    "wof:name":"PO21 1XX",
    "wof:placetype":"postalcode"
},
  "geometry": {"coordinates":[-0.6783008716168,50.78121255381154],"type":"Point"}
}