{
  "type": "Feature",
  "properties": {
    "iso:country": "GB",
    "wof:name": "PO21 1XX",
    "wof:placetype": "postalcode"
  },
  "geometry": {"coordinates":[-0.678301,50.781213],"type":"Point"}
}
