{
  "type": "Feature",
  "properties": {
    "date:inception_lower": "1990-02-01",
    "date:inception_upper": "1990-02-01",
    "iso:country": "GB",
    "wof:name": "PO21 1XX",
    "wof:placetype": "postalcode"
  },
  "geometry": {"coordinates":[-0.678301,50.781213],"type":"Point"}
}
