{
  "type": "Feature",
  "properties": {
    "iso:country":"GB",
    "wof:name":"ME9 7HL",
    "wof:placetype":"postalcode"
},
  "geometry": {"coordinates":[0.65027850660537,51.38505379069655],"type":"Point"}
}