{
  "type": "Feature",
  "properties": {
    "iso:country": "GB",
    "wof:name": "ME9 7HL",
    "wof:placetype": "postalcode"
  },
  "geometry": {"coordinates":[0.650279,51.385054],"type":"Point"}
}
