{
  "type": "Feature",
  "properties": {
    "iso:country":"GB",
    "wof:name":"LD8 2TW",
    "wof:placetype":"postalcode"
},
  "geometry": {"coordinates":[-3.21496952018847,52.22096597873273],"type":"Point"}
}