{
  "type": "Feature",
  "properties": {
    "date:inception_lower": "1980-01-01",
    "date:inception_upper": "1980-01-01",
    "iso:country": "GB",
    "wof:name": "LD8 2TW",
    "wof:placetype": "postalcode"
  },
  "geometry": {"coordinates":[-3.214969,52.220966],"type":"Point"}
}
