{
  "type": "Feature",
  "properties": {
    "iso:country": "GB",
    "wof:name": "LL41 3PU",
    "wof:placetype": "postalcode"
  },
  "geometry": {"coordinates":[-3.950025,52.992256],"type":"Point"}
}
