{
  "type": "Feature",
  "properties": {
    "iso:country": "GB",
    "wof:name": "WF5 8JR",
    "wof:placetype": "postalcode"
  },
  "geometry": {"coordinates":[-1.580203,53.676002],"type":"Point"}
}
