{
  "type": "Feature",
  "properties": {
    "date:inception_lower":"1980-01-01",
    "date:inception_upper":"1980-01-31",
    "iso:country":"GB",
    "wof:name":"NG34 8ES",
    "wof:placetype":"postalcode"
},
  "geometry": {"coordinates":[-0.439301,53.012343],"type":"Point"}
}