{
  "type": "Feature",
  "properties": {
    "date:inception_lower": "2024-08-01",
    "date:inception_upper": "2024-08-01",
    "iso:country": "GB",
    "wof:name": "EX15 2FW",
    "wof:placetype": "postalcode"
  },
  "geometry": {"coordinates":[-3.374954,50.885901],"type":"Point"}
}
