{
  "type": "Feature",
  "properties": {
    "date:inception_lower": "1980-01-01",
    "date:inception_upper": "1980-01-01",
    "iso:country": "GB",
    "wof:name": "SG19 2DE",
    "wof:placetype": "postalcode"
  },
  "geometry": {"coordinates":[-0.258304,52.138855],"type":"Point"}
}
