{
  "type": "Feature",
  "properties": {
    "iso:country": "GB",
    "wof:name": "WV14 8RY",
    "wof:placetype": "postalcode"
  },
  "geometry": {"coordinates":[-2.072963,52.553864],"type":"Point"}
}
