{
  "type": "Feature",
  "properties": {
    "iso:country": "GB",
    "wof:name": "HX2 8XA",
    "wof:placetype": "postalcode"
  },
  "geometry": {"coordinates":[-1.893436,53.760566],"type":"Point"}
}
