{
  "type": "Feature",
  "properties": {
    "date:inception_lower": "1980-01-01",
    "date:inception_upper": "1980-01-01",
    "iso:country": "GB",
    "wof:name": "EH4 1ER",
    "wof:placetype": "postalcode"
  },
  "geometry": {"coordinates":[-3.217076,55.958184],"type":"Point"}
}
