{
  "type": "Feature",
  "properties": {
    "iso:country":"GB",
    "wof:name":"IP19 0AX",
    "wof:placetype":"postalcode"
},
  "geometry": {"coordinates":[1.46240369161283,52.34798390070065],"type":"Point"}
}