{
  "type": "Feature",
  "properties": {
    "iso:country":"GB",
    "wof:name":"NW9 9TE",
    "wof:placetype":"postalcode"
},
  "geometry": {"coordinates":[-0.2802210221633,51.59359531439213],"type":"Point"}
}