{
  "type": "Feature",
  "properties": {
    "iso:country":"GB",
    "wof:name":"TN20 6HR",
    "wof:placetype":"postalcode"
},
  "geometry": {"coordinates":[0.21776595798575,51.00767702507773],"type":"Point"}
}