{
  "type": "Feature",
  "properties": {
    "date:inception_lower": "1980-01-01",
    "date:inception_upper": "1980-01-01",
    "iso:country": "GB",
    "wof:name": "TN20 6HR",
    "wof:placetype": "postalcode"
  },
  "geometry": {"coordinates":[0.217766,51.007677],"type":"Point"}
}
