{
  "type": "Feature",
  "properties": {
    "iso:country":"GB",
    "wof:name":"LL57 3EF",
    "wof:placetype":"postalcode"
},
  "geometry": {"coordinates":[-4.06434848518521,53.19143696936068],"type":"Point"}
}