{
  "type": "Feature",
  "properties": {
    "iso:country": "GB",
    "wof:name": "RH17 7HG",
    "wof:placetype": "postalcode"
  },
  "geometry": {"coordinates":[-0.010255,51.02679],"type":"Point"}
}
