{
  "type": "Feature",
  "properties": {
    "date:inception_lower": "1980-01-01",
    "date:inception_upper": "1980-01-01",
    "iso:country": "GB",
    "wof:name": "RH17 7HG",
    "wof:placetype": "postalcode"
  },
  "geometry": {"coordinates":[-0.01106,51.025968],"type":"Point"}
}
