{
  "type": "Feature",
  "properties": {
    "iso:country":"GB",
    "wof:name":"RH17 7HG",
    "wof:placetype":"postalcode"
},
  "geometry": {"coordinates":[-0.01026785431765,51.02678475194249],"type":"Point"}
}