{
  "type": "Feature",
  "properties": {
    "iso:country": "GB",
    "wof:name": "CM1 3GP",
    "wof:placetype": "postalcode"
  },
  "geometry": {"coordinates":[0.456638,51.727835],"type":"Point"}
}
