{
  "type": "Feature",
  "properties": {
    "iso:country":"GB",
    "wof:name":"CM1 3GP",
    "wof:placetype":"postalcode"
},
  "geometry": {"coordinates":[0.4566374910518,51.72783496452876],"type":"Point"}
}