{
  "type": "Feature",
  "properties": {
    "iso:country": "GB",
    "wof:name": "NG7 1QR",
    "wof:placetype": "postalcode"
  },
  "geometry": {"coordinates":[-1.174228,52.952369],"type":"Point"}
}
