{
  "type": "Feature",
  "properties": {
    "iso:country":"GB",
    "wof:name":"BR2 0TJ",
    "wof:placetype":"postalcode"
},
  "geometry": {"coordinates":[0.00707414199894,51.39427865832771],"type":"Point"}
}