{
  "type": "Feature",
  "properties": {
    "iso:country":"GB",
    "wof:name":"DD7 7JD",
    "wof:placetype":"postalcode"
},
  "geometry": {"coordinates":[-2.7152991966484,56.49840083996849],"type":"Point"}
}