{
  "type": "Feature",
  "properties": {
    "iso:country":"GB",
    "wof:name":"CV6 6GH",
    "wof:placetype":"postalcode"
},
  "geometry": {"coordinates":[-1.49462064550945,52.4403795101634],"type":"Point"}
}