{
  "type": "Feature",
  "properties": {
    "iso:country": "GB",
    "wof:name": "CV6 6GH",
    "wof:placetype": "postalcode"
  },
  "geometry": {"coordinates":[-1.494621,52.44038],"type":"Point"}
}
