{
  "type": "Feature",
  "properties": {
    "date:inception_lower": "1980-01-01",
    "date:inception_upper": "1980-01-01",
    "iso:country": "GB",
    "wof:name": "HA4 0QT",
    "wof:placetype": "postalcode"
  },
  "geometry": {"coordinates":[-0.385231,51.564424],"type":"Point"}
}
