{
  "type": "Feature",
  "properties": {
    "iso:country":"GB",
    "wof:name":"HA4 0QT",
    "wof:placetype":"postalcode"
},
  "geometry": {"coordinates":[-0.38523149417118,51.56442369779388],"type":"Point"}
}