{
  "type": "Feature",
  "properties": {
    "iso:country":"GB",
    "wof:name":"PR5 6AN",
    "wof:placetype":"postalcode"
},
  "geometry": {"coordinates":[-2.636863905988,53.72123297768069],"type":"Point"}
}