{
  "type": "Feature",
  "properties": {
    "iso:country":"GB",
    "wof:name":"EX15 1HN",
    "wof:placetype":"postalcode"
},
  "geometry": {"coordinates":[-3.39689940826489,50.85528702972726],"type":"Point"}
}