{
  "type": "Feature",
  "properties": {
    "iso:country": "GB",
    "wof:name": "EX15 1HN",
    "wof:placetype": "postalcode"
  },
  "geometry": {"coordinates":[-3.396899,50.855287],"type":"Point"}
}
