{
  "type": "Feature",
  "properties": {
    "date:inception_lower": "1980-01-01",
    "date:inception_upper": "1980-01-01",
    "iso:country": "GB",
    "wof:name": "KT23 3QE",
    "wof:placetype": "postalcode"
  },
  "geometry": {"coordinates":[-0.385872,51.278871],"type":"Point"}
}
