{
  "type": "Feature",
  "properties": {
    "iso:country":"GB",
    "wof:name":"KT23 3QE",
    "wof:placetype":"postalcode"
},
  "geometry": {"coordinates":[-0.38587239743907,51.27887067144984],"type":"Point"}
}