{
  "type": "Feature",
  "properties": {
    "iso:country":"GB",
    "wof:name":"WV14 8NE",
    "wof:placetype":"postalcode"
},
  "geometry": {"coordinates":[-2.04979509979528,52.55587137234025],"type":"Point"}
}