{
  "type": "Feature",
  "properties": {
    "iso:country": "GB",
    "wof:name": "WV14 8NE",
    "wof:placetype": "postalcode"
  },
  "geometry": {"coordinates":[-2.049795,52.555871],"type":"Point"}
}
