{
  "type": "Feature",
  "properties": {
    "iso:country":"GB",
    "wof:name":"SW18 5RJ",
    "wof:placetype":"postalcode"
},
  "geometry": {"coordinates":[-0.20599760083944,51.44507146035377],"type":"Point"}
}