{
  "type": "Feature",
  "properties": {
    "date:inception_lower": "1980-01-01",
    "date:inception_upper": "1980-01-01",
    "iso:country": "GB",
    "wof:name": "PL12 6ND",
    "wof:placetype": "postalcode"
  },
  "geometry": {"coordinates":[-4.225655,50.43983],"type":"Point"}
}
