{
  "type": "Feature",
  "properties": {
    "iso:country": "GB",
    "wof:name": "CM7 4FA",
    "wof:placetype": "postalcode"
  },
  "geometry": {"coordinates":[0.442346,51.944564],"type":"Point"}
}
