{
  "type": "Feature",
  "properties": {
    "date:inception_lower":"2014-07-01",
    "date:inception_upper":"2014-07-31",
    "iso:country":"GB",
    "wof:name":"CM7 4FA",
    "wof:placetype":"postalcode"
},
  "geometry": {"coordinates":[0.442346,51.944564],"type":"Point"}
}