{
  "type": "Feature",
  "properties": {
    "iso:country":"GB",
    "wof:name":"CM7 4FA",
    "wof:placetype":"postalcode"
},
  "geometry": {"coordinates":[0.44234598452808,51.94456442587908],"type":"Point"}
}