{
  "type": "Feature",
  "properties": {
    "iso:country":"GB",
    "wof:name":"ME5 0HP",
    "wof:placetype":"postalcode"
},
  "geometry": {"coordinates":[0.52545218596091,51.35983279730578],"type":"Point"}
}