{
  "type": "Feature",
  "properties": {
    "iso:country": "GB",
    "wof:name": "CW7 2QG",
    "wof:placetype": "postalcode"
  },
  "geometry": {"coordinates":[-2.581312,53.204617],"type":"Point"}
}
