{
  "type": "Feature",
  "properties": {
    "date:inception_lower":"2010-09-01",
    "date:inception_upper":"2010-09-30",
    "iso:country":"GB",
    "wof:name":"RG12 9PE",
    "wof:placetype":"postalcode"
},
  "geometry": {"coordinates":[-0.746179,51.40689],"type":"Point"}
}