{
  "type": "Feature",
  "properties": {
    "iso:country": "GB",
    "wof:name": "RG12 9PE",
    "wof:placetype": "postalcode"
  },
  "geometry": {"coordinates":[-0.746179,51.40689],"type":"Point"}
}
