{
  "type": "Feature",
  "properties": {
    "iso:country":"GB",
    "wof:name":"S36 6FR",
    "wof:placetype":"postalcode"
},
  "geometry": {"coordinates":[-1.63665639677524,53.52223480402819],"type":"Point"}
}