{
  "type": "Feature",
  "properties": {
    "iso:country": "GB",
    "wof:name": "PO36 9PQ",
    "wof:placetype": "postalcode"
  },
  "geometry": {"coordinates":[-1.17871,50.643263],"type":"Point"}
}
