{
  "type": "Feature",
  "properties": {
    "iso:country":"GB",
    "wof:name":"HR9 5JG",
    "wof:placetype":"postalcode"
},
  "geometry": {"coordinates":[-2.58127066153008,51.91308406129869],"type":"Point"}
}