{
  "type": "Feature",
  "properties": {
    "date:inception_lower": "1989-07-01",
    "date:inception_upper": "1989-07-01",
    "iso:country": "GB",
    "wof:name": "PA2 9PF",
    "wof:placetype": "postalcode"
  },
  "geometry": {"coordinates":[-4.449458,55.838162],"type":"Point"}
}
