{
  "type": "Feature",
  "properties": {
    "date:inception_lower": "1992-08-01",
    "date:inception_upper": "1992-08-01",
    "iso:country": "GB",
    "wof:name": "DE55 6EA",
    "wof:placetype": "postalcode"
  },
  "geometry": {"coordinates":[-1.445629,53.116521],"type":"Point"}
}
