{
  "type": "Feature",
  "properties": {
    "iso:country":"GB",
    "wof:name":"SS13 3PF",
    "wof:placetype":"postalcode"
},
  "geometry": {"coordinates":[0.50331294703399,51.57308373591642],"type":"Point"}
}