{
  "type": "Feature",
  "properties": {
    "date:inception_lower":"1980-01-01",
    "date:inception_upper":"1980-01-31",
    "iso:country":"GB",
    "wof:name":"ML12 6TZ",
    "wof:placetype":"postalcode"
},
  "geometry": {"coordinates":[-3.657978,55.472901],"type":"Point"}
}