{
  "type": "Feature",
  "properties": {
    "iso:country": "GB",
    "wof:name": "ML12 6TZ",
    "wof:placetype": "postalcode"
  },
  "geometry": {"coordinates":[-3.657978,55.472901],"type":"Point"}
}
