{
  "type": "Feature",
  "properties": {
    "iso:country":"GB",
    "wof:name":"HA5 5LQ",
    "wof:placetype":"postalcode"
},
  "geometry": {"coordinates":[-0.37916992369048,51.58435668979882],"type":"Point"}
}