{
  "type": "Feature",
  "properties": {
    "date:inception_lower":"1980-01-01",
    "date:inception_upper":"1980-01-31",
    "iso:country":"GB",
    "wof:name":"HA5 5LQ",
    "wof:placetype":"postalcode"
},
  "geometry": {"coordinates":[-0.37917,51.584357],"type":"Point"}
}