{
  "type": "Feature",
  "properties": {
    "date:inception_lower": "2016-11-01",
    "date:inception_upper": "2016-11-01",
    "iso:country": "GB",
    "wof:name": "L25 8AA",
    "wof:placetype": "postalcode"
  },
  "geometry": {"coordinates":[-2.86336,53.3734],"type":"Point"}
}
