{
  "type": "Feature",
  "properties": {
    "iso:country": "GB",
    "wof:name": "L25 8AA",
    "wof:placetype": "postalcode"
  },
  "geometry": {"coordinates":[-2.86336,53.3734],"type":"Point"}
}
