{
  "type": "Feature",
  "properties": {
    "iso:country":"GB",
    "wof:name":"M23 2QB",
    "wof:placetype":"postalcode"
},
  "geometry": {"coordinates":[-2.2821396108063,53.38675309567036],"type":"Point"}
}