{
  "type": "Feature",
  "properties": {
    "date:inception_lower": "1994-05-01",
    "date:inception_upper": "1994-05-01",
    "iso:country": "GB",
    "wof:name": "M23 2QB",
    "wof:placetype": "postalcode"
  },
  "geometry": {"coordinates":[-2.28214,53.386753],"type":"Point"}
}
