{
  "type": "Feature",
  "properties": {
    "iso:country":"GB",
    "wof:name":"NR13 3RN",
    "wof:placetype":"postalcode"
},
  "geometry": {"coordinates":[1.51108253780114,52.58136991792799],"type":"Point"}
}