{
  "type": "Feature",
  "properties": {
    "date:inception_lower": "1980-01-01",
    "date:inception_upper": "1980-01-01",
    "iso:country": "GB",
    "wof:name": "NR13 3RN",
    "wof:placetype": "postalcode"
  },
  "geometry": {"coordinates":[1.511083,52.58137],"type":"Point"}
}
