{
  "type": "Feature",
  "properties": {
    "iso:country":"GB",
    "wof:name":"WD24 7QU",
    "wof:placetype":"postalcode"
},
  "geometry": {"coordinates":[-0.394936675922,51.67756033419061],"type":"Point"}
}