{
  "type": "Feature",
  "properties": {
    "iso:country":"GB",
    "wof:name":"W12 8BX",
    "wof:placetype":"postalcode"
},
  "geometry": {"coordinates":[-0.23557759459254,51.50458284458594],"type":"Point"}
}