{
  "type": "Feature",
  "properties": {
    "iso:country":"GB",
    "wof:name":"GU17 0HL",
    "wof:placetype":"postalcode"
},
  "geometry": {"coordinates":[-0.78585247050299,51.33605385160703],"type":"Point"}
}