{
  "type": "Feature",
  "properties": {
    "date:inception_lower": "1980-01-01",
    "date:inception_upper": "1980-01-01",
    "iso:country": "GB",
    "wof:name": "GU17 0HL",
    "wof:placetype": "postalcode"
  },
  "geometry": {"coordinates":[-0.785852,51.336054],"type":"Point"}
}
