{
  "type": "Feature",
  "properties": {
    "iso:country": "GB",
    "wof:name": "DH2 1AX",
    "wof:placetype": "postalcode"
  },
  "geometry": {"coordinates":[-1.608483,54.899123],"type":"Point"}
}
