{
  "type": "Feature",
  "properties": {
    "date:inception_lower": "2018-11-01",
    "date:inception_upper": "2018-11-01",
    "iso:country": "GB",
    "wof:name": "DH2 1AX",
    "wof:placetype": "postalcode"
  },
  "geometry": {"coordinates":[-1.607827,54.899273],"type":"Point"}
}
