{
  "type": "Feature",
  "properties": {
    "iso:country": "GB",
    "wof:name": "PO21 2RB",
    "wof:placetype": "postalcode"
  },
  "geometry": {"coordinates":[-0.692363,50.781533],"type":"Point"}
}
