{
  "type": "Feature",
  "properties": {
    "iso:country":"GB",
    "wof:name":"OX13 5PH",
    "wof:placetype":"postalcode"
},
  "geometry": {"coordinates":[-1.38776130280738,51.66101594503122],"type":"Point"}
}