{
  "type": "Feature",
  "properties": {
    "iso:country": "GB",
    "wof:name": "OX13 5PH",
    "wof:placetype": "postalcode"
  },
  "geometry": {"coordinates":[-1.387761,51.661016],"type":"Point"}
}
