{
  "type": "Feature",
  "properties": {
    "iso:country": "GB",
    "wof:name": "WR1 2EJ",
    "wof:placetype": "postalcode"
  },
  "geometry": {"coordinates":[-2.221962,52.192934],"type":"Point"}
}
