{
  "type": "Feature",
  "properties": {
    "iso:country":"GB",
    "wof:name":"WR1 2EJ",
    "wof:placetype":"postalcode"
},
  "geometry": {"coordinates":[-2.22211217443145,52.19296605538769],"type":"Point"}
}