{
  "type": "Feature",
  "properties": {
    "date:inception_lower": "2001-12-01",
    "date:inception_upper": "2001-12-01",
    "iso:country": "GB",
    "wof:name": "RM8 2TE",
    "wof:placetype": "postalcode"
  },
  "geometry": {"coordinates":[0.126786,51.556746],"type":"Point"}
}
