{
  "type": "Feature",
  "properties": {
    "iso:country":"GB",
    "wof:name":"S62 7SB",
    "wof:placetype":"postalcode"
},
  "geometry": {"coordinates":[-1.39601142428511,53.47717304927028],"type":"Point"}
}