{
  "type": "Feature",
  "properties": {
    "iso:country": "GB",
    "wof:name": "S62 7SB",
    "wof:placetype": "postalcode"
  },
  "geometry": {"coordinates":[-1.396011,53.477173],"type":"Point"}
}
