{
  "type": "Feature",
  "properties": {
    "date:inception_lower": "1980-01-01",
    "date:inception_upper": "1980-01-01",
    "iso:country": "GB",
    "wof:name": "TF12 5JN",
    "wof:placetype": "postalcode"
  },
  "geometry": {"coordinates":[-2.484185,52.589679],"type":"Point"}
}
