{
  "type": "Feature",
  "properties": {
    "iso:country": "GB",
    "wof:name": "TF12 5JN",
    "wof:placetype": "postalcode"
  },
  "geometry": {"coordinates":[-2.484185,52.589679],"type":"Point"}
}
