{
  "type": "Feature",
  "properties": {
    "iso:country":"GB",
    "wof:name":"TF12 5JN",
    "wof:placetype":"postalcode"
},
  "geometry": {"coordinates":[-2.4839205980975,52.58958396788302],"type":"Point"}
}