{
  "type": "Feature",
  "properties": {
    "date:inception_lower":"1998-06-01",
    "date:inception_upper":"1998-06-30",
    "iso:country":"GB",
    "wof:name":"YO25 4LH",
    "wof:placetype":"postalcode"
},
  "geometry": {"coordinates":[-0.396794,54.013486],"type":"Point"}
}