{
  "type": "Feature",
  "properties": {
    "iso:country": "GB",
    "wof:name": "TF10 8AG",
    "wof:placetype": "postalcode"
  },
  "geometry": {"coordinates":[-2.396173,52.799289],"type":"Point"}
}
