{
  "type": "Feature",
  "properties": {
    "iso:country":"GB",
    "wof:name":"NG17 5BP",
    "wof:placetype":"postalcode"
},
  "geometry": {"coordinates":[-1.26297197663544,53.11767893127325],"type":"Point"}
}