{
  "type": "Feature",
  "properties": {
    "iso:country":"GB",
    "wof:name":"HU10 7DT",
    "wof:placetype":"postalcode"
},
  "geometry": {"coordinates":[-0.44531119345944,53.74325332779851],"type":"Point"}
}