{
  "type": "Feature",
  "properties": {
    "iso:country":"GB",
    "wof:name":"CB6 1BY",
    "wof:placetype":"postalcode"
},
  "geometry": {"coordinates":[0.27151844335341,52.40930166742411],"type":"Point"}
}