{
  "type": "Feature",
  "properties": {
    "iso:country": "GB",
    "wof:name": "WC1B 3PE",
    "wof:placetype": "postalcode"
  },
  "geometry": {"coordinates":[-0.12682,51.517851],"type":"Point"}
}
