{
  "type": "Feature",
  "properties": {
    "date:inception_lower": "1985-04-01",
    "date:inception_upper": "1985-04-01",
    "iso:country": "GB",
    "wof:name": "SG19 1TB",
    "wof:placetype": "postalcode"
  },
  "geometry": {"coordinates":[-0.29333,52.138117],"type":"Point"}
}
