{
  "type": "Feature",
  "properties": {
    "date:inception_lower":"1980-01-01",
    "date:inception_upper":"1980-01-31",
    "iso:country":"GB",
    "wof:name":"TA17 8SH",
    "wof:placetype":"postalcode"
},
  "geometry": {"coordinates":[-2.8249,50.911398],"type":"Point"}
}