{
  "type": "Feature",
  "properties": {
    "iso:country":"GB",
    "wof:name":"TA17 8SH",
    "wof:placetype":"postalcode"
},
  "geometry": {"coordinates":[-2.82490045983186,50.91139759662579],"type":"Point"}
}