{
  "type": "Feature",
  "properties": {
    "iso:country":"GB",
    "wof:name":"BH12 2HZ",
    "wof:placetype":"postalcode"
},
  "geometry": {"coordinates":[-1.93780310375401,50.73065185959218],"type":"Point"}
}