{
  "type": "Feature",
  "properties": {
    "date:inception_lower": "1997-12-01",
    "date:inception_upper": "1997-12-01",
    "iso:country": "GB",
    "wof:name": "PO30 5XL",
    "wof:placetype": "postalcode"
  },
  "geometry": {"coordinates":[-1.32241,50.696064],"type":"Point"}
}
