{
  "type": "Feature",
  "properties": {
    "iso:country":"GB",
    "wof:name":"NE15 6DN",
    "wof:placetype":"postalcode"
},
  "geometry": {"coordinates":[-1.68262305066822,54.97178727336714],"type":"Point"}
}