{
  "type": "Feature",
  "properties": {
    "iso:country": "GB",
    "wof:name": "PE28 0TD",
    "wof:placetype": "postalcode"
  },
  "geometry": {"coordinates":[-0.341607,52.341316],"type":"Point"}
}
