{
  "type": "Feature",
  "properties": {
    "iso:country":"GB",
    "wof:name":"PE28 0TD",
    "wof:placetype":"postalcode"
},
  "geometry": {"coordinates":[-0.34160709378257,52.34131589845464],"type":"Point"}
}