{
  "type": "Feature",
  "properties": {
    "iso:country":"GB",
    "wof:name":"B74 2XT",
    "wof:placetype":"postalcode"
},
  "geometry": {"coordinates":[-1.83563358839634,52.58325913499129],"type":"Point"}
}