{
  "type": "Feature",
  "properties": {
    "iso:country":"GB",
    "wof:name":"PE9 4HW",
    "wof:placetype":"postalcode"
},
  "geometry": {"coordinates":[-0.46707489379266,52.68552145401966],"type":"Point"}
}