{
  "type": "Feature",
  "properties": {
    "iso:country": "GB",
    "wof:name": "PE9 4HW",
    "wof:placetype": "postalcode"
  },
  "geometry": {"coordinates":[-0.467075,52.685521],"type":"Point"}
}
