{
  "type": "Feature",
  "properties": {
    "iso:country": "GB",
    "wof:name": "WF10 4TL",
    "wof:placetype": "postalcode"
  },
  "geometry": {"coordinates":[-1.346887,53.711953],"type":"Point"}
}
