{
  "type": "Feature",
  "properties": {
    "date:inception_lower": "2005-09-01",
    "date:inception_upper": "2005-09-01",
    "iso:country": "GB",
    "wof:name": "RH12 1PX",
    "wof:placetype": "postalcode"
  },
  "geometry": {"coordinates":[-0.345169,51.059382],"type":"Point"}
}
