{
  "type": "Feature",
  "properties": {
    "iso:country":"GB",
    "wof:name":"RH12 1PX",
    "wof:placetype":"postalcode"
},
  "geometry": {"coordinates":[-0.34516933226796,51.05938236480899],"type":"Point"}
}