{
  "type": "Feature",
  "properties": {
    "date:inception_lower":"1990-07-01",
    "date:inception_upper":"1990-07-31",
    "iso:country":"GB",
    "wof:name":"PO1 3RJ",
    "wof:placetype":"postalcode"
},
  "geometry": {"coordinates":[-1.100484,50.79801],"type":"Point"}
}