{
  "type": "Feature",
  "properties": {
    "iso:country":"GB",
    "wof:name":"WV7 3DS",
    "wof:placetype":"postalcode"
},
  "geometry": {"coordinates":[-2.27080910617596,52.63602143465633],"type":"Point"}
}