{
  "type": "Feature",
  "properties": {
    "date:inception_lower": "1980-01-01",
    "date:inception_upper": "1980-01-01",
    "iso:country": "GB",
    "wof:name": "WV7 3DS",
    "wof:placetype": "postalcode"
  },
  "geometry": {"coordinates":[-2.270703,52.636234],"type":"Point"}
}
