{
  "type": "Feature",
  "properties": {
    "iso:country":"GB",
    "wof:name":"IV15 9NU",
    "wof:placetype":"postalcode"
},
  "geometry": {"coordinates":[-4.43773639963069,57.59434838685425],"type":"Point"}
}