{
  "type": "Feature",
  "properties": {
    "date:inception_lower": "1980-01-01",
    "date:inception_upper": "1980-01-01",
    "iso:country": "GB",
    "wof:name": "IV15 9NU",
    "wof:placetype": "postalcode"
  },
  "geometry": {"coordinates":[-4.437736,57.594348],"type":"Point"}
}
