{
  "type": "Feature",
  "properties": {
    "iso:country":"GB",
    "wof:name":"NE10 8DY",
    "wof:placetype":"postalcode"
},
  "geometry": {"coordinates":[-1.53366916402162,54.94244365263424],"type":"Point"}
}