{
  "type": "Feature",
  "properties": {
    "date:inception_lower": "2000-06-01",
    "date:inception_upper": "2000-06-01",
    "iso:country": "GB",
    "wof:name": "CA7 5HL",
    "wof:placetype": "postalcode"
  },
  "geometry": {"coordinates":[-3.269502,54.86986],"type":"Point"}
}
