{
  "type": "Feature",
  "properties": {
    "iso:country":"GB",
    "wof:name":"CA7 5HL",
    "wof:placetype":"postalcode"
},
  "geometry": {"coordinates":[-3.26950240212546,54.8698603004617],"type":"Point"}
}