{
  "type": "Feature",
  "properties": {
    "iso:country": "GB",
    "wof:name": "LL30 2UB",
    "wof:placetype": "postalcode"
  },
  "geometry": {"coordinates":[-3.831722,53.321768],"type":"Point"}
}
