{
  "type": "Feature",
  "properties": {
    "iso:country": "GB",
    "wof:name": "OL6 9JJ",
    "wof:placetype": "postalcode"
  },
  "geometry": {"coordinates":[-2.084172,53.492843],"type":"Point"}
}
