{
  "type": "Feature",
  "properties": {
    "iso:country":"GB",
    "wof:name":"SL1 2SX",
    "wof:placetype":"postalcode"
},
  "geometry": {"coordinates":[-0.6156985608839,51.50499998458216],"type":"Point"}
}