{
  "type": "Feature",
  "properties": {
    "iso:country": "GB",
    "wof:name": "SL1 2SX",
    "wof:placetype": "postalcode"
  },
  "geometry": {"coordinates":[-0.615699,51.505],"type":"Point"}
}
