{
  "type": "Feature",
  "properties": {
    "iso:country":"GB",
    "wof:name":"BR5 2JS",
    "wof:placetype":"postalcode"
},
  "geometry": {"coordinates":[0.10731939132993,51.40228487912757],"type":"Point"}
}