{
  "type": "Feature",
  "properties": {
    "iso:country":"GB",
    "wof:name":"M20 4WY",
    "wof:placetype":"postalcode"
},
  "geometry": {"coordinates":[-2.21632735441283,53.43344237136995],"type":"Point"}
}