{
  "type": "Feature",
  "properties": {
    "iso:country":"GB",
    "wof:name":"IV30 6UF",
    "wof:placetype":"postalcode"
},
  "geometry": {"coordinates":[-3.32033170561313,57.63476441900459],"type":"Point"}
}