{
  "type": "Feature",
  "properties": {
    "iso:country": "GB",
    "wof:name": "IV30 6UF",
    "wof:placetype": "postalcode"
  },
  "geometry": {"coordinates":[-3.320332,57.634764],"type":"Point"}
}
