{
  "type": "Feature",
  "properties": {
    "iso:country": "GB",
    "wof:name": "FY5 4DY",
    "wof:placetype": "postalcode"
  },
  "geometry": {"coordinates":[-3.000276,53.87606],"type":"Point"}
}
