{
  "type": "Feature",
  "properties": {
    "iso:country":"GB",
    "wof:name":"BA21 3SQ",
    "wof:placetype":"postalcode"
},
  "geometry": {"coordinates":[-2.66499927780197,50.94861287037715],"type":"Point"}
}