{
  "type": "Feature",
  "properties": {
    "date:inception_lower": "1988-03-01",
    "date:inception_upper": "1988-03-01",
    "iso:country": "GB",
    "wof:name": "BA21 3SQ",
    "wof:placetype": "postalcode"
  },
  "geometry": {"coordinates":[-2.664999,50.948613],"type":"Point"}
}
