{
  "type": "Feature",
  "properties": {
    "iso:country": "GB",
    "wof:name": "NG12 3HQ",
    "wof:placetype": "postalcode"
  },
  "geometry": {"coordinates":[-1.044398,52.914153],"type":"Point"}
}
