{
  "type": "Feature",
  "properties": {
    "iso:country":"GB",
    "wof:name":"NG12 3HQ",
    "wof:placetype":"postalcode"
},
  "geometry": {"coordinates":[-1.04430113924101,52.91397829420459],"type":"Point"}
}