{
  "type": "Feature",
  "properties": {
    "date:inception_lower": "1980-01-01",
    "date:inception_upper": "1980-01-01",
    "iso:country": "GB",
    "wof:name": "WF6 2PH",
    "wof:placetype": "postalcode"
  },
  "geometry": {"coordinates":[-1.407266,53.721273],"type":"Point"}
}
