{
  "type": "Feature",
  "properties": {
    "iso:country": "GB",
    "wof:name": "LN4 4XX",
    "wof:placetype": "postalcode"
  },
  "geometry": {"coordinates":[-0.17391,53.105692],"type":"Point"}
}
