{
  "type": "Feature",
  "properties": {
    "iso:country":"GB",
    "wof:name":"IP4 1PD",
    "wof:placetype":"postalcode"
},
  "geometry": {"coordinates":[1.17403959286986,52.05553418481644],"type":"Point"}
}