{
  "type": "Feature",
  "properties": {
    "iso:country":"GB",
    "wof:name":"GL4 8BA",
    "wof:placetype":"postalcode"
},
  "geometry": {"coordinates":[-2.19711164292618,51.83547795605911],"type":"Point"}
}