{
  "type": "Feature",
  "properties": {
    "iso:country": "GB",
    "wof:name": "GL4 8BA",
    "wof:placetype": "postalcode"
  },
  "geometry": {"coordinates":[-2.197108,51.835484],"type":"Point"}
}
