{
  "type": "Feature",
  "properties": {
    "iso:country": "GB",
    "wof:name": "YO41 1JD",
    "wof:placetype": "postalcode"
  },
  "geometry": {"coordinates":[-0.883759,54.031989],"type":"Point"}
}
