{
  "type": "Feature",
  "properties": {
    "iso:country":"GB",
    "wof:name":"YO41 1JD",
    "wof:placetype":"postalcode"
},
  "geometry": {"coordinates":[-0.88348922515579,54.03144805202776],"type":"Point"}
}