{
  "type": "Feature",
  "properties": {
    "iso:country":"GB",
    "wof:name":"CT20 2NJ",
    "wof:placetype":"postalcode"
},
  "geometry": {"coordinates":[1.15798838363983,51.08165900346359],"type":"Point"}
}