{
  "type": "Feature",
  "properties": {
    "iso:country":"GB",
    "wof:name":"RM15 6DP",
    "wof:placetype":"postalcode"
},
  "geometry": {"coordinates":[0.30468847613516,51.51553358828043],"type":"Point"}
}