{
  "type": "Feature",
  "properties": {
    "iso:country":"GB",
    "wof:name":"TN34 1TH",
    "wof:placetype":"postalcode"
},
  "geometry": {"coordinates":[0.56855589057657,50.86330940632159],"type":"Point"}
}