{
  "type": "Feature",
  "properties": {
    "iso:country": "GB",
    "wof:name": "TN34 1TH",
    "wof:placetype": "postalcode"
  },
  "geometry": {"coordinates":[0.568556,50.863309],"type":"Point"}
}
