{
  "type": "Feature",
  "properties": {
    "date:inception_lower":"1984-10-01",
    "date:inception_upper":"1984-10-31",
    "iso:country":"GB",
    "wof:name":"TN34 1TH",
    "wof:placetype":"postalcode"
},
  "geometry": {"coordinates":[0.568556,50.863309],"type":"Point"}
}