{
  "type": "Feature",
  "properties": {
    "iso:country":"GB",
    "wof:name":"CF15 9HP",
    "wof:placetype":"postalcode"
},
  "geometry": {"coordinates":[-3.27563577092957,51.54574571506753],"type":"Point"}
}