{
  "type": "Feature",
  "properties": {
    "date:inception_lower": "2000-10-01",
    "date:inception_upper": "2000-10-01",
    "iso:country": "GB",
    "wof:name": "WD23 1BL",
    "wof:placetype": "postalcode"
  },
  "geometry": {"coordinates":[-0.359095,51.641537],"type":"Point"}
}
