{
  "type": "Feature",
  "properties": {
    "date:inception_lower": "1995-01-01",
    "date:inception_upper": "1995-01-01",
    "iso:country": "GB",
    "wof:name": "NE41 8JP",
    "wof:placetype": "postalcode"
  },
  "geometry": {"coordinates":[-1.814765,54.963782],"type":"Point"}
}
