{
  "type": "Feature",
  "properties": {
    "iso:country":"GB",
    "wof:name":"NE41 8JP",
    "wof:placetype":"postalcode"
},
  "geometry": {"coordinates":[-1.81528526339089,54.96365868714331],"type":"Point"}
}