{
  "type": "Feature",
  "properties": {
    "iso:country": "GB",
    "wof:name": "NE41 8JP",
    "wof:placetype": "postalcode"
  },
  "geometry": {"coordinates":[-1.814985,54.963567],"type":"Point"}
}
