{
  "type": "Feature",
  "properties": {
    "date:inception_lower":"1995-01-01",
    "date:inception_upper":"1995-01-31",
    "iso:country":"GB",
    "wof:name":"NE41 8JP",
    "wof:placetype":"postalcode"
},
  "geometry": {"coordinates":[-1.814985,54.963567],"type":"Point"}
}