{
  "type": "Feature",
  "properties": {
    "iso:country":"GB",
    "wof:name":"RG2 7EE",
    "wof:placetype":"postalcode"
},
  "geometry": {"coordinates":[-0.94710142325765,51.43082478760433],"type":"Point"}
}