{
  "type": "Feature",
  "properties": {
    "date:inception_lower": "1992-08-01",
    "date:inception_upper": "1992-08-01",
    "iso:country": "GB",
    "wof:name": "NW4 3HF",
    "wof:placetype": "postalcode"
  },
  "geometry": {"coordinates":[-0.226936,51.580924],"type":"Point"}
}
