{
  "type": "Feature",
  "properties": {
    "iso:country":"GB",
    "wof:name":"NW4 3HF",
    "wof:placetype":"postalcode"
},
  "geometry": {"coordinates":[-0.22693559615355,51.58092362098851],"type":"Point"}
}