{
  "type": "Feature",
  "properties": {
    "iso:country": "GB",
    "wof:name": "IP27 0LA",
    "wof:placetype": "postalcode"
  },
  "geometry": {"coordinates":[0.603763,52.442987],"type":"Point"}
}
