{
  "type": "Feature",
  "properties": {
    "iso:country":"GB",
    "wof:name":"SA46 0BN",
    "wof:placetype":"postalcode"
},
  "geometry": {"coordinates":[-4.2618789542351,52.24376356462641],"type":"Point"}
}