{
  "type": "Feature",
  "properties": {
    "iso:country": "GB",
    "wof:name": "SA46 0BN",
    "wof:placetype": "postalcode"
  },
  "geometry": {"coordinates":[-4.261773,52.243703],"type":"Point"}
}
