{
  "type": "Feature",
  "properties": {
    "iso:country":"GB",
    "wof:name":"PO19 3PX",
    "wof:placetype":"postalcode"
},
  "geometry": {"coordinates":[-0.81075685427222,50.84334920655094],"type":"Point"}
}