{
  "type": "Feature",
  "properties": {
    "iso:country":"GB",
    "wof:name":"L18 1HZ",
    "wof:placetype":"postalcode"
},
  "geometry": {"coordinates":[-2.92319956191968,53.38735394689592],"type":"Point"}
}