{
  "type": "Feature",
  "properties": {
    "iso:country": "GB",
    "wof:name": "FY6 9EG",
    "wof:placetype": "postalcode"
  },
  "geometry": {"coordinates":[-2.949677,53.874731],"type":"Point"}
}
