{
  "type": "Feature",
  "properties": {
    "iso:country":"GB",
    "wof:name":"FY6 9EG",
    "wof:placetype":"postalcode"
},
  "geometry": {"coordinates":[-2.9496766877446,53.87473136075862],"type":"Point"}
}