{
  "type": "Feature",
  "properties": {
    "iso:country":"GB",
    "wof:name":"AL8 7QA",
    "wof:placetype":"postalcode"
},
  "geometry": {"coordinates":[-0.20150813427228,51.80712182196805],"type":"Point"}
}