{
  "type": "Feature",
  "properties": {
    "date:inception_lower": "1992-08-01",
    "date:inception_upper": "1992-08-01",
    "iso:country": "GB",
    "wof:name": "AL8 7QA",
    "wof:placetype": "postalcode"
  },
  "geometry": {"coordinates":[-0.201545,51.807048],"type":"Point"}
}
