{
  "type": "Feature",
  "properties": {
    "iso:country":"GB",
    "wof:name":"HR4 9HF",
    "wof:placetype":"postalcode"
},
  "geometry": {"coordinates":[-2.71438683097488,52.06340689545592],"type":"Point"}
}