{
  "type": "Feature",
  "properties": {
    "iso:country": "GB",
    "wof:name": "WA16 7EB",
    "wof:placetype": "postalcode"
  },
  "geometry": {"coordinates":[-2.331876,53.31164],"type":"Point"}
}
