{
  "type": "Feature",
  "properties": {
    "date:inception_lower":"1990-02-01",
    "date:inception_upper":"1990-02-28",
    "iso:country":"GB",
    "wof:name":"WA16 7EB",
    "wof:placetype":"postalcode"
},
  "geometry": {"coordinates":[-2.331876,53.31164],"type":"Point"}
}