{
  "type": "Feature",
  "properties": {
    "iso:country": "GB",
    "wof:name": "LS12 4PS",
    "wof:placetype": "postalcode"
  },
  "geometry": {"coordinates":[-1.597491,53.783919],"type":"Point"}
}
