{
  "type": "Feature",
  "properties": {
    "iso:country":"GB",
    "wof:name":"W11 2PY",
    "wof:placetype":"postalcode"
},
  "geometry": {"coordinates":[-0.2046028088895,51.51288939216651],"type":"Point"}
}