{
  "type": "Feature",
  "properties": {
    "iso:country": "GB",
    "wof:name": "KA9 1SW",
    "wof:placetype": "postalcode"
  },
  "geometry": {"coordinates":[-4.625357,55.489604],"type":"Point"}
}
