{
  "type": "Feature",
  "properties": {
    "iso:country":"GB",
    "wof:name":"KA9 1SW",
    "wof:placetype":"postalcode"
},
  "geometry": {"coordinates":[-4.62535732508807,55.48960353772494],"type":"Point"}
}