{
  "type": "Feature",
  "properties": {
    "iso:country": "GB",
    "wof:name": "CF32 8EW",
    "wof:placetype": "postalcode"
  },
  "geometry": {"coordinates":[-3.586797,51.610784],"type":"Point"}
}
