{
  "type": "Feature",
  "properties": {
    "iso:country":"GB",
    "wof:name":"NG5 4PF",
    "wof:placetype":"postalcode"
},
  "geometry": {"coordinates":[-1.12082757039032,52.9904136929902],"type":"Point"}
}