{
  "type": "Feature",
  "properties": {
    "iso:country": "GB",
    "wof:name": "NG5 4PF",
    "wof:placetype": "postalcode"
  },
  "geometry": {"coordinates":[-1.120828,52.990414],"type":"Point"}
}
