{
  "type": "Feature",
  "properties": {
    "iso:country": "GB",
    "wof:name": "GL51 0ED",
    "wof:placetype": "postalcode"
  },
  "geometry": {"coordinates":[-2.11175,51.913128],"type":"Point"}
}
