{
  "type": "Feature",
  "properties": {
    "iso:country":"GB",
    "wof:name":"TR11 5NZ",
    "wof:placetype":"postalcode"
},
  "geometry": {"coordinates":[-5.07815096902993,50.16163587443118],"type":"Point"}
}