{
  "type": "Feature",
  "properties": {
    "iso:country":"GB",
    "wof:name":"NE25 8SR",
    "wof:placetype":"postalcode"
},
  "geometry": {"coordinates":[-1.46941918516258,55.03836973951593],"type":"Point"}
}