{
  "type": "Feature",
  "properties": {
    "date:inception_lower":"2012-06-01",
    "date:inception_upper":"2012-06-30",
    "iso:country":"GB",
    "wof:name":"HP19 9AA",
    "wof:placetype":"postalcode"
},
  "geometry": {"coordinates":[-0.823361,51.83351],"type":"Point"}
}