{
  "type": "Feature",
  "properties": {
    "iso:country":"GB",
    "wof:name":"HP19 9AA",
    "wof:placetype":"postalcode"
},
  "geometry": {"coordinates":[-0.82336152096489,51.83351021167862],"type":"Point"}
}