{
  "type": "Feature",
  "properties": {
    "iso:country": "GB",
    "wof:name": "HP19 9AA",
    "wof:placetype": "postalcode"
  },
  "geometry": {"coordinates":[-0.823361,51.83351],"type":"Point"}
}
