{
  "type": "Feature",
  "properties": {
    "date:inception_lower": "2015-07-01",
    "date:inception_upper": "2015-07-01",
    "iso:country": "GB",
    "wof:name": "DL8 5PY",
    "wof:placetype": "postalcode"
  },
  "geometry": {"coordinates":[-1.807111,54.304032],"type":"Point"}
}
