{
  "type": "Feature",
  "properties": {
    "iso:country": "GB",
    "wof:name": "DL8 5PY",
    "wof:placetype": "postalcode"
  },
  "geometry": {"coordinates":[-1.807111,54.304032],"type":"Point"}
}
