{
  "type": "Feature",
  "properties": {
    "iso:country":"GB",
    "wof:name":"DL8 5PY",
    "wof:placetype":"postalcode"
},
  "geometry": {"coordinates":[-1.80635210040633,54.30402875748688],"type":"Point"}
}