{
  "type": "Feature",
  "properties": {
    "iso:country":"GB",
    "wof:name":"PH3 1PG",
    "wof:placetype":"postalcode"
},
  "geometry": {"coordinates":[-3.70322357578494,56.28059135365003],"type":"Point"}
}