{
  "type": "Feature",
  "properties": {
    "iso:country":"GB",
    "wof:name":"SY3 0AS",
    "wof:placetype":"postalcode"
},
  "geometry": {"coordinates":[-2.76682704396772,52.66880119462465],"type":"Point"}
}