{
  "type": "Feature",
  "properties": {
    "iso:country":"GB",
    "wof:name":"SN16 9DJ",
    "wof:placetype":"postalcode"
},
  "geometry": {"coordinates":[-2.05680421939272,51.59708600176744],"type":"Point"}
}