{
  "type": "Feature",
  "properties": {
    "date:inception_lower": "1980-01-01",
    "date:inception_upper": "1980-01-01",
    "iso:country": "GB",
    "wof:name": "NR25 7PS",
    "wof:placetype": "postalcode"
  },
  "geometry": {"coordinates":[1.019544,52.953687],"type":"Point"}
}
