{
  "type": "Feature",
  "properties": {
    "iso:country": "GB",
    "wof:name": "LN4 3HD",
    "wof:placetype": "postalcode"
  },
  "geometry": {"coordinates":[-0.391357,53.138567],"type":"Point"}
}
