{
  "type": "Feature",
  "properties": {
    "date:inception_lower":"1992-08-01",
    "date:inception_upper":"1992-08-31",
    "iso:country":"GB",
    "wof:name":"DE55 6HP",
    "wof:placetype":"postalcode"
},
  "geometry": {"coordinates":[-1.378412,53.138149],"type":"Point"}
}