{
  "type": "Feature",
  "properties": {
    "iso:country": "GB",
    "wof:name": "DE55 6HP",
    "wof:placetype": "postalcode"
  },
  "geometry": {"coordinates":[-1.378412,53.138149],"type":"Point"}
}
