{
  "type": "Feature",
  "properties": {
    "date:inception_lower": "2020-12-01",
    "date:inception_upper": "2020-12-01",
    "iso:country": "GB",
    "wof:name": "WF6 2GA",
    "wof:placetype": "postalcode"
  },
  "geometry": {"coordinates":[-1.425131,53.700525],"type":"Point"}
}
