{
  "type": "Feature",
  "properties": {
    "iso:country": "GB",
    "wof:name": "B45 8EA",
    "wof:placetype": "postalcode"
  },
  "geometry": {"coordinates":[-2.001939,52.388624],"type":"Point"}
}
