{
  "type": "Feature",
  "properties": {
    "iso:country":"GB",
    "wof:name":"B45 8EA",
    "wof:placetype":"postalcode"
},
  "geometry": {"coordinates":[-2.00193940481406,52.38862354791985],"type":"Point"}
}