{
  "type": "Feature",
  "properties": {
    "iso:country":"GB",
    "wof:name":"E13 0NP",
    "wof:placetype":"postalcode"
},
  "geometry": {"coordinates":[0.02203065816289,51.53511800846477],"type":"Point"}
}