{
  "type": "Feature",
  "properties": {
    "iso:country": "GB",
    "wof:name": "BS16 3YH",
    "wof:placetype": "postalcode"
  },
  "geometry": {"coordinates":[-2.543664,51.474068],"type":"Point"}
}
