{
  "type": "Feature",
  "properties": {
    "iso:country":"GB",
    "wof:name":"BS16 3YH",
    "wof:placetype":"postalcode"
},
  "geometry": {"coordinates":[-2.54366424567729,51.47406783850442],"type":"Point"}
}