{
  "type": "Feature",
  "properties": {
    "iso:country": "GB",
    "wof:name": "SA72 6TJ",
    "wof:placetype": "postalcode"
  },
  "geometry": {"coordinates":[-4.955711,51.691727],"type":"Point"}
}
