{
  "type": "Feature",
  "properties": {
    "iso:country":"GB",
    "wof:name":"SA72 6TJ",
    "wof:placetype":"postalcode"
},
  "geometry": {"coordinates":[-4.95545688263896,51.69168453493197],"type":"Point"}
}