{
  "type": "Feature",
  "properties": {
    "date:inception_lower": "1980-01-01",
    "date:inception_upper": "1980-01-01",
    "iso:country": "GB",
    "wof:name": "SA72 6TJ",
    "wof:placetype": "postalcode"
  },
  "geometry": {"coordinates":[-4.955492,51.691696],"type":"Point"}
}
