{
  "type": "Feature",
  "properties": {
    "date:inception_lower": "1980-01-01",
    "date:inception_upper": "1980-01-01",
    "iso:country": "GB",
    "wof:name": "S66 8JS",
    "wof:placetype": "postalcode"
  },
  "geometry": {"coordinates":[-1.203623,53.428496],"type":"Point"}
}
