{
  "type": "Feature",
  "properties": {
    "iso:country":"GB",
    "wof:name":"BR6 7DP",
    "wof:placetype":"postalcode"
},
  "geometry": {"coordinates":[0.07734583285155,51.36142558846509],"type":"Point"}
}