{
  "type": "Feature",
  "properties": {
    "iso:country": "GB",
    "wof:name": "KY8 3HN",
    "wof:placetype": "postalcode"
  },
  "geometry": {"coordinates":[-3.01317,56.184459],"type":"Point"}
}
