{
  "type": "Feature",
  "properties": {
    "iso:country":"GB",
    "wof:name":"DE56 0AG",
    "wof:placetype":"postalcode"
},
  "geometry": {"coordinates":[-1.46187365552323,53.0132107449263],"type":"Point"}
}