{
  "type": "Feature",
  "properties": {
    "iso:country":"GB",
    "wof:name":"AB53 4DF",
    "wof:placetype":"postalcode"
},
  "geometry": {"coordinates":[-2.45062344301752,57.53899416335497],"type":"Point"}
}