{
  "type": "Feature",
  "properties": {
    "iso:country":"GB",
    "wof:name":"CF40 1PS",
    "wof:placetype":"postalcode"
},
  "geometry": {"coordinates":[-3.44243946178136,51.60832165577644],"type":"Point"}
}