{
  "type": "Feature",
  "properties": {
    "date:inception_lower": "1980-01-01",
    "date:inception_upper": "1980-01-01",
    "iso:country": "GB",
    "wof:name": "MK42 8DD",
    "wof:placetype": "postalcode"
  },
  "geometry": {"coordinates":[-0.491271,52.120633],"type":"Point"}
}
