{
  "type": "Feature",
  "properties": {
    "iso:country": "GB",
    "wof:name": "WA7 4BJ",
    "wof:placetype": "postalcode"
  },
  "geometry": {"coordinates":[-2.747069,53.328882],"type":"Point"}
}
