{
  "type": "Feature",
  "properties": {
    "iso:country": "GB",
    "wof:name": "LD7 1RD",
    "wof:placetype": "postalcode"
  },
  "geometry": {"coordinates":[-3.107788,52.374507],"type":"Point"}
}
