{
  "type": "Feature",
  "properties": {
    "iso:country": "GB",
    "wof:name": "LD7 1RD",
    "wof:placetype": "postalcode"
  },
  "geometry": {"coordinates":[-3.108487,52.3737],"type":"Point"}
}
