{
  "type": "Feature",
  "properties": {
    "iso:country":"GB",
    "wof:name":"EH1 1PE",
    "wof:placetype":"postalcode"
},
  "geometry": {"coordinates":[-3.18892895371273,55.95019213700205],"type":"Point"}
}