{
  "type": "Feature",
  "properties": {
    "iso:country":"GB",
    "wof:name":"CF11 8BD",
    "wof:placetype":"postalcode"
},
  "geometry": {"coordinates":[-3.2066624670373,51.46737376380792],"type":"Point"}
}