{
  "type": "Feature",
  "properties": {
    "iso:country":"GB",
    "wof:name":"HD3 3SW",
    "wof:placetype":"postalcode"
},
  "geometry": {"coordinates":[-1.83778104645377,53.6586510552172],"type":"Point"}
}