{
  "type": "Feature",
  "properties": {
    "iso:country":"GB",
    "wof:name":"AB25 3SB",
    "wof:placetype":"postalcode"
},
  "geometry": {"coordinates":[-2.11264595761376,57.15370690633076],"type":"Point"}
}