{
  "type": "Feature",
  "properties": {
    "iso:country":"GB",
    "wof:name":"NE10 0QE",
    "wof:placetype":"postalcode"
},
  "geometry": {"coordinates":[-1.53849540757986,54.95447678017781],"type":"Point"}
}