{
  "type": "Feature",
  "properties": {
    "iso:country":"GB",
    "wof:name":"SO41 9DG",
    "wof:placetype":"postalcode"
},
  "geometry": {"coordinates":[-1.54379659778403,50.76244737772822],"type":"Point"}
}