{
  "type": "Feature",
  "properties": {
    "iso:country": "GB",
    "wof:name": "SO41 9DG",
    "wof:placetype": "postalcode"
  },
  "geometry": {"coordinates":[-1.543797,50.762447],"type":"Point"}
}
