{
  "type": "Feature",
  "properties": {
    "iso:country":"GB",
    "wof:name":"BD15 7DQ",
    "wof:placetype":"postalcode"
},
  "geometry": {"coordinates":[-1.82752707645414,53.80570848048202],"type":"Point"}
}