{
  "type": "Feature",
  "properties": {
    "date:inception_lower":"1980-01-01",
    "date:inception_upper":"1980-01-31",
    "iso:country":"GB",
    "wof:name":"BD15 7DQ",
    "wof:placetype":"postalcode"
},
  "geometry": {"coordinates":[-1.827527,53.805708],"type":"Point"}
}