{
  "type": "Feature",
  "properties": {
    "iso:country":"GB",
    "wof:name":"BD3 9PJ",
    "wof:placetype":"postalcode"
},
  "geometry": {"coordinates":[-1.72820541832842,53.79383139114625],"type":"Point"}
}