{
  "type": "Feature",
  "properties": {
    "date:inception_lower": "1980-01-01",
    "date:inception_upper": "1980-01-01",
    "iso:country": "GB",
    "wof:name": "CT14 6NX",
    "wof:placetype": "postalcode"
  },
  "geometry": {"coordinates":[1.402707,51.233815],"type":"Point"}
}
