{
  "type": "Feature",
  "properties": {
    "iso:country": "GB",
    "wof:name": "NR27 0FA",
    "wof:placetype": "postalcode"
  },
  "geometry": {"coordinates":[1.300035,52.92233],"type":"Point"}
}
