{
  "type": "Feature",
  "properties": {
    "iso:country":"GB",
    "wof:name":"NR27 0FA",
    "wof:placetype":"postalcode"
},
  "geometry": {"coordinates":[1.30007872465481,52.92234492621869],"type":"Point"}
}