{
  "type": "Feature",
  "properties": {
    "date:inception_lower":"2016-04-01",
    "date:inception_upper":"2016-04-30",
    "iso:country":"GB",
    "wof:name":"CH5 9AN",
    "wof:placetype":"postalcode"
},
  "geometry": {"coordinates":[-3.017188,53.208659],"type":"Point"}
}