{
  "type": "Feature",
  "properties": {
    "date:inception_lower":"1980-01-01",
    "date:inception_upper":"1980-01-31",
    "iso:country":"GB",
    "wof:name":"OL4 5DF",
    "wof:placetype":"postalcode"
},
  "geometry": {"coordinates":[-2.071721,53.53666],"type":"Point"}
}