{
  "type": "Feature",
  "properties": {
    "iso:country": "GB",
    "wof:name": "TQ7 4PJ",
    "wof:placetype": "postalcode"
  },
  "geometry": {"coordinates":[-3.914449,50.315209],"type":"Point"}
}
