{
  "type": "Feature",
  "properties": {
    "iso:country":"GB",
    "wof:name":"EH12 7QA",
    "wof:placetype":"postalcode"
},
  "geometry": {"coordinates":[-3.2875968557199,55.93680927582258],"type":"Point"}
}