{
  "type": "Feature",
  "properties": {
    "iso:country": "GB",
    "wof:name": "GU14 0HJ",
    "wof:placetype": "postalcode"
  },
  "geometry": {"coordinates":[-0.773623,51.294427],"type":"Point"}
}
