{
  "type": "Feature",
  "properties": {
    "iso:country":"GB",
    "wof:name":"NP16 5SS",
    "wof:placetype":"postalcode"
},
  "geometry": {"coordinates":[-2.66400012604568,51.62332769041035],"type":"Point"}
}