{
  "type": "Feature",
  "properties": {
    "iso:country": "GB",
    "wof:name": "WA7 3FR",
    "wof:placetype": "postalcode"
  },
  "geometry": {"coordinates":[-2.662341,53.315423],"type":"Point"}
}
