{
  "type": "Feature",
  "properties": {
    "iso:country":"GB",
    "wof:name":"BD4 0TL",
    "wof:placetype":"postalcode"
},
  "geometry": {"coordinates":[-1.70682609659494,53.77935532795543],"type":"Point"}
}