{
  "type": "Feature",
  "properties": {
    "iso:country": "GB",
    "wof:name": "TQ7 2NG",
    "wof:placetype": "postalcode"
  },
  "geometry": {"coordinates":[-3.667296,50.234822],"type":"Point"}
}
