{
  "type": "Feature",
  "properties": {
    "date:inception_lower": "1980-01-01",
    "date:inception_upper": "1980-01-01",
    "iso:country": "GB",
    "wof:name": "TQ7 2NG",
    "wof:placetype": "postalcode"
  },
  "geometry": {"coordinates":[-3.666867,50.234594],"type":"Point"}
}
