{
  "type": "Feature",
  "properties": {
    "date:inception_lower": "1980-01-01",
    "date:inception_upper": "1980-01-01",
    "iso:country": "GB",
    "wof:name": "L35 3SX",
    "wof:placetype": "postalcode"
  },
  "geometry": {"coordinates":[-2.800887,53.415642],"type":"Point"}
}
