{
  "type": "Feature",
  "properties": {
    "iso:country":"GB",
    "wof:name":"B79 0BL",
    "wof:placetype":"postalcode"
},
  "geometry": {"coordinates":[-1.6286216495701,52.66607275164185],"type":"Point"}
}