{
  "type": "Feature",
  "properties": {
    "iso:country":"GB",
    "wof:name":"W1F 9PS",
    "wof:placetype":"postalcode"
},
  "geometry": {"coordinates":[-0.13874063946024,51.51288786585138],"type":"Point"}
}