{
  "type": "Feature",
  "properties": {
    "iso:country": "GB",
    "wof:name": "DL7 9JA",
    "wof:placetype": "postalcode"
  },
  "geometry": {"coordinates":[-1.425021,54.283873],"type":"Point"}
}
