{
  "type": "Feature",
  "properties": {
    "iso:country":"GB",
    "wof:name":"DL7 9JA",
    "wof:placetype":"postalcode"
},
  "geometry": {"coordinates":[-1.42409821243024,54.28329879121542],"type":"Point"}
}