{
  "type": "Feature",
  "properties": {
    "date:inception_lower": "1980-01-01",
    "date:inception_upper": "1980-01-01",
    "iso:country": "GB",
    "wof:name": "DL7 9JA",
    "wof:placetype": "postalcode"
  },
  "geometry": {"coordinates":[-1.425011,54.283451],"type":"Point"}
}
