{
  "type": "Feature",
  "properties": {
    "iso:country": "GB",
    "wof:name": "DL7 9JA",
    "wof:placetype": "postalcode"
  },
  "geometry": {"coordinates":[-1.424107,54.283311],"type":"Point"}
}
