{
  "type": "Feature",
  "properties": {
    "date:inception_lower":"1980-01-01",
    "date:inception_upper":"1980-01-31",
    "iso:country":"GB",
    "wof:name":"TA6 7NY",
    "wof:placetype":"postalcode"
},
  "geometry": {"coordinates":[-3.035529,51.12759],"type":"Point"}
}