{
  "type": "Feature",
  "properties": {
    "iso:country":"GB",
    "wof:name":"TA6 7NY",
    "wof:placetype":"postalcode"
},
  "geometry": {"coordinates":[-3.03552907922197,51.12758955672118],"type":"Point"}
}