{
  "type": "Feature",
  "properties": {
    "iso:country": "GB",
    "wof:name": "TA6 7NY",
    "wof:placetype": "postalcode"
  },
  "geometry": {"coordinates":[-3.035529,51.12759],"type":"Point"}
}
