{
  "type": "Feature",
  "properties": {
    "date:inception_lower": "2021-11-01",
    "date:inception_upper": "2021-11-01",
    "iso:country": "GB",
    "wof:name": "SO24 4BL",
    "wof:placetype": "postalcode"
  },
  "geometry": {"coordinates":[-1.162398,51.090049],"type":"Point"}
}
