{
  "type": "Feature",
  "properties": {
    "iso:country":"GB",
    "wof:name":"PA4 8TX",
    "wof:placetype":"postalcode"
},
  "geometry": {"coordinates":[-4.38791637155129,55.87642041128926],"type":"Point"}
}