{
  "type": "Feature",
  "properties": {
    "iso:country":"GB",
    "wof:name":"SE14 6TT",
    "wof:placetype":"postalcode"
},
  "geometry": {"coordinates":[-0.02903501576109,51.47317349096793],"type":"Point"}
}