{
  "type": "Feature",
  "properties": {
    "iso:country":"GB",
    "wof:name":"AB53 8LB",
    "wof:placetype":"postalcode"
},
  "geometry": {"coordinates":[-2.40852598879121,57.43853218671221],"type":"Point"}
}