{
  "type": "Feature",
  "properties": {
    "iso:country": "GB",
    "wof:name": "CW12 4GU",
    "wof:placetype": "postalcode"
  },
  "geometry": {"coordinates":[-2.22007,53.161391],"type":"Point"}
}
