{
  "type": "Feature",
  "properties": {
    "iso:country": "GB",
    "wof:name": "PO30 5UH",
    "wof:placetype": "postalcode"
  },
  "geometry": {"coordinates":[-1.338314,50.725645],"type":"Point"}
}
