{
  "type": "Feature",
  "properties": {
    "iso:country":"GB",
    "wof:name":"PO30 5UH",
    "wof:placetype":"postalcode"
},
  "geometry": {"coordinates":[-1.33831400840239,50.72564495798653],"type":"Point"}
}