{
  "type": "Feature",
  "properties": {
    "iso:country":"GB",
    "wof:name":"N18 1JZ",
    "wof:placetype":"postalcode"
},
  "geometry": {"coordinates":[-0.08507330220873,51.61961916917207],"type":"Point"}
}