{
  "type": "Feature",
  "properties": {
    "iso:country": "GB",
    "wof:name": "RG9 4RT",
    "wof:placetype": "postalcode"
  },
  "geometry": {"coordinates":[-0.956675,51.558327],"type":"Point"}
}
