{
  "type": "Feature",
  "properties": {
    "date:inception_lower":"1980-01-01",
    "date:inception_upper":"1980-01-31",
    "iso:country":"GB",
    "wof:name":"RG9 4RT",
    "wof:placetype":"postalcode"
},
  "geometry": {"coordinates":[-0.956675,51.558327],"type":"Point"}
}