{
  "type": "Feature",
  "properties": {
    "iso:country":"GB",
    "wof:name":"RG9 4RT",
    "wof:placetype":"postalcode"
},
  "geometry": {"coordinates":[-0.95450719863122,51.55815210063169],"type":"Point"}
}