{
  "type": "Feature",
  "properties": {
    "iso:country":"GB",
    "wof:name":"M21 9WL",
    "wof:placetype":"postalcode"
},
  "geometry": {"coordinates":[-2.28251103405547,53.44505204522261],"type":"Point"}
}