{
  "type": "Feature",
  "properties": {
    "iso:country":"GB",
    "wof:name":"NR21 0BQ",
    "wof:placetype":"postalcode"
},
  "geometry": {"coordinates":[0.96722976631586,52.86334415222996],"type":"Point"}
}