{
  "type": "Feature",
  "properties": {
    "iso:country": "GB",
    "wof:name": "NR21 0BQ",
    "wof:placetype": "postalcode"
  },
  "geometry": {"coordinates":[0.967169,52.863309],"type":"Point"}
}
