{
  "type": "Feature",
  "properties": {
    "iso:country": "GB",
    "wof:name": "RH16 2GJ",
    "wof:placetype": "postalcode"
  },
  "geometry": {"coordinates":[-0.075978,51.005884],"type":"Point"}
}
