{
  "type": "Feature",
  "properties": {
    "iso:country": "GB",
    "wof:name": "NG32 3LD",
    "wof:placetype": "postalcode"
  },
  "geometry": {"coordinates":[-0.588174,53.039995],"type":"Point"}
}
