{
  "type": "Feature",
  "properties": {
    "date:inception_lower": "1980-01-01",
    "date:inception_upper": "1980-01-01",
    "iso:country": "GB",
    "wof:name": "NG32 3LD",
    "wof:placetype": "postalcode"
  },
  "geometry": {"coordinates":[-0.588174,53.039995],"type":"Point"}
}
