{
  "type": "Feature",
  "properties": {
    "iso:country": "GB",
    "wof:name": "PE38 0BD",
    "wof:placetype": "postalcode"
  },
  "geometry": {"coordinates":[0.338767,52.589258],"type":"Point"}
}
