{
  "type": "Feature",
  "properties": {
    "date:inception_lower": "1980-01-01",
    "date:inception_upper": "1980-01-01",
    "iso:country": "GB",
    "wof:name": "PE38 0BD",
    "wof:placetype": "postalcode"
  },
  "geometry": {"coordinates":[0.338434,52.589121],"type":"Point"}
}
