{
  "type": "Feature",
  "properties": {
    "date:inception_lower":"1980-01-01",
    "date:inception_upper":"1980-01-31",
    "iso:country":"GB",
    "wof:name":"DN15 7NN",
    "wof:placetype":"postalcode"
},
  "geometry": {"coordinates":[-0.655096,53.595644],"type":"Point"}
}