{
  "type": "Feature",
  "properties": {
    "iso:country":"GB",
    "wof:name":"BN1 8EL",
    "wof:placetype":"postalcode"
},
  "geometry": {"coordinates":[-0.1359439175631,50.8556644048724],"type":"Point"}
}