{
  "type": "Feature",
  "properties": {
    "date:inception_lower": "2023-12-01",
    "date:inception_upper": "2023-12-01",
    "iso:country": "GB",
    "wof:name": "CH65 6AB",
    "wof:placetype": "postalcode"
  },
  "geometry": {"coordinates":[-2.909149,53.268419],"type":"Point"}
}
