{
  "type": "Feature",
  "properties": {
    "date:inception_lower": "1987-04-01",
    "date:inception_upper": "1987-04-01",
    "iso:country": "GB",
    "wof:name": "PO12 4LH",
    "wof:placetype": "postalcode"
  },
  "geometry": {"coordinates":[-1.135448,50.812609],"type":"Point"}
}
