{
  "type": "Feature",
  "properties": {
    "date:inception_lower": "2000-06-01",
    "date:inception_upper": "2000-06-01",
    "iso:country": "GB",
    "wof:name": "HP19 0WS",
    "wof:placetype": "postalcode"
  },
  "geometry": {"coordinates":[-0.806193,51.829651],"type":"Point"}
}
