{
  "type": "Feature",
  "properties": {
    "iso:country":"GB",
    "wof:name":"HP19 0WS",
    "wof:placetype":"postalcode"
},
  "geometry": {"coordinates":[-0.80619302585913,51.82965075766926],"type":"Point"}
}