{
  "type": "Feature",
  "properties": {
    "iso:country": "GB",
    "wof:name": "AB33 8ND",
    "wof:placetype": "postalcode"
  },
  "geometry": {"coordinates":[-2.72041,57.234109],"type":"Point"}
}
