{
  "type": "Feature",
  "properties": {
    "iso:country":"GB",
    "wof:name":"AB33 8ND",
    "wof:placetype":"postalcode"
},
  "geometry": {"coordinates":[-2.72040962925038,57.23410944700382],"type":"Point"}
}