{
  "type": "Feature",
  "properties": {
    "date:inception_lower": "1980-01-01",
    "date:inception_upper": "1980-01-01",
    "iso:country": "GB",
    "wof:name": "NR3 2DN",
    "wof:placetype": "postalcode"
  },
  "geometry": {"coordinates":[1.282685,52.643462],"type":"Point"}
}
