{
  "type": "Feature",
  "properties": {
    "iso:country":"GB",
    "wof:name":"WA5 3EU",
    "wof:placetype":"postalcode"
},
  "geometry": {"coordinates":[-2.6568408862417,53.39509454675164],"type":"Point"}
}