{
  "type": "Feature",
  "properties": {
    "iso:country":"GB",
    "wof:name":"HG2 9LD",
    "wof:placetype":"postalcode"
},
  "geometry": {"coordinates":[-1.54958676148832,53.96862120010096],"type":"Point"}
}