{
  "type": "Feature",
  "properties": {
    "iso:country":"GB",
    "wof:name":"SE14 6NH",
    "wof:placetype":"postalcode"
},
  "geometry": {"coordinates":[-0.03719225162363,51.47468621672194],"type":"Point"}
}