{
  "type": "Feature",
  "properties": {
    "date:inception_lower": "1980-01-01",
    "date:inception_upper": "1980-01-01",
    "iso:country": "GB",
    "wof:name": "CH5 3EL",
    "wof:placetype": "postalcode"
  },
  "geometry": {"coordinates":[-3.037508,53.186395],"type":"Point"}
}
