{
  "type": "Feature",
  "properties": {
    "iso:country":"GB",
    "wof:name":"ML7 4BT",
    "wof:placetype":"postalcode"
},
  "geometry": {"coordinates":[-3.8063202290306,55.82252774938084],"type":"Point"}
}