{
  "type": "Feature",
  "properties": {
    "date:inception_lower":"1980-01-01",
    "date:inception_upper":"1980-01-31",
    "iso:country":"GB",
    "wof:name":"ML7 4BT",
    "wof:placetype":"postalcode"
},
  "geometry": {"coordinates":[-3.80632,55.822528],"type":"Point"}
}