{
  "type": "Feature",
  "properties": {
    "iso:country": "GB",
    "wof:name": "ML7 4BT",
    "wof:placetype": "postalcode"
  },
  "geometry": {"coordinates":[-3.80632,55.822528],"type":"Point"}
}
