{
  "type": "Feature",
  "properties": {
    "iso:country":"GB",
    "wof:name":"AB25 2QN",
    "wof:placetype":"postalcode"
},
  "geometry": {"coordinates":[-2.12020556927209,57.15039412939475],"type":"Point"}
}