{
  "type": "Feature",
  "properties": {
    "date:inception_lower":"1995-07-01",
    "date:inception_upper":"1995-07-31",
    "iso:country":"GB",
    "wof:name":"IP24 2BU",
    "wof:placetype":"postalcode"
},
  "geometry": {"coordinates":[0.754013,52.415626],"type":"Point"}
}