{
  "type": "Feature",
  "properties": {
    "iso:country": "GB",
    "wof:name": "LS12 1JH",
    "wof:placetype": "postalcode"
  },
  "geometry": {"coordinates":[-1.575599,53.790611],"type":"Point"}
}
