{
  "type": "Feature",
  "properties": {
    "iso:country": "GB",
    "wof:name": "AB55 5PD",
    "wof:placetype": "postalcode"
  },
  "geometry": {"coordinates":[-2.9207,57.524412],"type":"Point"}
}
