{
  "type": "Feature",
  "properties": {
    "iso:country":"GB",
    "wof:name":"AB55 5PD",
    "wof:placetype":"postalcode"
},
  "geometry": {"coordinates":[-2.92069984390731,57.52441232504583],"type":"Point"}
}