{
  "type": "Feature",
  "properties": {
    "date:inception_lower": "1980-01-01",
    "date:inception_upper": "1980-01-01",
    "iso:country": "GB",
    "wof:name": "LE16 7TG",
    "wof:placetype": "postalcode"
  },
  "geometry": {"coordinates":[-0.941179,52.516025],"type":"Point"}
}
