{
  "type": "Feature",
  "properties": {
    "iso:country":"GB",
    "wof:name":"LE16 7TG",
    "wof:placetype":"postalcode"
},
  "geometry": {"coordinates":[-0.94117883078756,52.51602463201883],"type":"Point"}
}