{
  "type": "Feature",
  "properties": {
    "iso:country": "GB",
    "wof:name": "DD2 2TA",
    "wof:placetype": "postalcode"
  },
  "geometry": {"coordinates":[-3.025714,56.477771],"type":"Point"}
}
