{
  "type": "Feature",
  "properties": {
    "iso:country":"GB",
    "wof:name":"CF3 3JP",
    "wof:placetype":"postalcode"
},
  "geometry": {"coordinates":[-3.12948633826071,51.50773398378094],"type":"Point"}
}