{
  "type": "Feature",
  "properties": {
    "date:inception_lower": "1980-01-01",
    "date:inception_upper": "1980-01-01",
    "iso:country": "GB",
    "wof:name": "KT21 1HY",
    "wof:placetype": "postalcode"
  },
  "geometry": {"coordinates":[-0.288023,51.311023],"type":"Point"}
}
