{
  "type": "Feature",
  "properties": {
    "iso:country": "GB",
    "wof:name": "PH2 7BY",
    "wof:placetype": "postalcode"
  },
  "geometry": {"coordinates":[-3.404816,56.396842],"type":"Point"}
}
