{
  "type": "Feature",
  "properties": {
    "iso:country":"GB",
    "wof:name":"PE14 0NR",
    "wof:placetype":"postalcode"
},
  "geometry": {"coordinates":[0.13311794159632,52.62231783930231],"type":"Point"}
}