{
  "type": "Feature",
  "properties": {
    "date:inception_lower": "1984-02-01",
    "date:inception_upper": "1984-02-01",
    "iso:country": "GB",
    "wof:name": "LS7 4DF",
    "wof:placetype": "postalcode"
  },
  "geometry": {"coordinates":[-1.530248,53.812407],"type":"Point"}
}
