{
  "type": "Feature",
  "properties": {
    "iso:country":"GB",
    "wof:name":"SO41 5QR",
    "wof:placetype":"postalcode"
},
  "geometry": {"coordinates":[-1.53000978864089,50.78420883382202],"type":"Point"}
}