{
  "type": "Feature",
  "properties": {
    "date:inception_lower": "1980-01-01",
    "date:inception_upper": "1980-01-01",
    "iso:country": "GB",
    "wof:name": "N10 1NL",
    "wof:placetype": "postalcode"
  },
  "geometry": {"coordinates":[-0.151496,51.594705],"type":"Point"}
}
