{
  "type": "Feature",
  "properties": {
    "iso:country":"GB",
    "wof:name":"N10 1NL",
    "wof:placetype":"postalcode"
},
  "geometry": {"coordinates":[-0.15149602000029,51.59470495373399],"type":"Point"}
}