{
  "type": "Feature",
  "properties": {
    "iso:country": "GB",
    "wof:name": "SK9 2NZ",
    "wof:placetype": "postalcode"
  },
  "geometry": {"coordinates":[-2.207169,53.339321],"type":"Point"}
}
