{
  "type": "Feature",
  "properties": {
    "iso:country": "GB",
    "wof:name": "TN6 3LS",
    "wof:placetype": "postalcode"
  },
  "geometry": {"coordinates":[0.217806,51.042866],"type":"Point"}
}
