{
  "type": "Feature",
  "properties": {
    "iso:country":"GB",
    "wof:name":"TN6 3LS",
    "wof:placetype":"postalcode"
},
  "geometry": {"coordinates":[0.21780577863606,51.04286822219847],"type":"Point"}
}