{
  "type": "Feature",
  "properties": {
    "iso:country": "GB",
    "wof:name": "SL6 2DE",
    "wof:placetype": "postalcode"
  },
  "geometry": {"coordinates":[-0.687485,51.494369],"type":"Point"}
}
