{
  "type": "Feature",
  "properties": {
    "iso:country":"GB",
    "wof:name":"SL6 2DE",
    "wof:placetype":"postalcode"
},
  "geometry": {"coordinates":[-0.68748512627363,51.49436935258641],"type":"Point"}
}