{
  "type": "Feature",
  "properties": {
    "date:inception_lower":"2018-12-01",
    "date:inception_upper":"2018-12-31",
    "iso:country":"GB",
    "wof:name":"LE3 4AL",
    "wof:placetype":"postalcode"
},
  "geometry": {"coordinates":[-1.190553,52.606194],"type":"Point"}
}