{
  "type": "Feature",
  "properties": {
    "iso:country": "GB",
    "wof:name": "EX6 6AU",
    "wof:placetype": "postalcode"
  },
  "geometry": {"coordinates":[-3.681717,50.735749],"type":"Point"}
}
