{
  "type": "Feature",
  "properties": {
    "iso:country":"GB",
    "wof:name":"YO17 8NG",
    "wof:placetype":"postalcode"
},
  "geometry": {"coordinates":[-0.6830077740548,54.16808122803887],"type":"Point"}
}