{
  "type": "Feature",
  "properties": {
    "iso:country": "GB",
    "wof:name": "YO17 8NG",
    "wof:placetype": "postalcode"
  },
  "geometry": {"coordinates":[-0.683008,54.168081],"type":"Point"}
}
