{
  "type": "Feature",
  "properties": {
    "iso:country":"GB",
    "wof:name":"SK14 1SA",
    "wof:placetype":"postalcode"
},
  "geometry": {"coordinates":[-2.08312246065277,53.44959116752942],"type":"Point"}
}