{
  "type": "Feature",
  "properties": {
    "date:inception_lower": "1994-12-01",
    "date:inception_upper": "1994-12-01",
    "iso:country": "GB",
    "wof:name": "SK14 1SA",
    "wof:placetype": "postalcode"
  },
  "geometry": {"coordinates":[-2.083122,53.449591],"type":"Point"}
}
