{
  "type": "Feature",
  "properties": {
    "iso:country":"GB",
    "wof:name":"L23 7TQ",
    "wof:placetype":"postalcode"
},
  "geometry": {"coordinates":[-3.02781531411685,53.49194788096574],"type":"Point"}
}