{
  "type": "Feature",
  "properties": {
    "iso:country":"GB",
    "wof:name":"SO32 1GZ",
    "wof:placetype":"postalcode"
},
  "geometry": {"coordinates":[-1.21520708103784,50.95713488329064],"type":"Point"}
}