{
  "type": "Feature",
  "properties": {
    "iso:country": "GB",
    "wof:name": "SO32 1GZ",
    "wof:placetype": "postalcode"
  },
  "geometry": {"coordinates":[-1.215207,50.957135],"type":"Point"}
}
