{
  "type": "Feature",
  "properties": {
    "iso:country":"GB",
    "wof:name":"B27 6HP",
    "wof:placetype":"postalcode"
},
  "geometry": {"coordinates":[-1.82075925099169,52.4521017511487],"type":"Point"}
}