{
  "type": "Feature",
  "properties": {
    "iso:country":"GB",
    "wof:name":"SA4 3YU",
    "wof:placetype":"postalcode"
},
  "geometry": {"coordinates":[-4.11171342156578,51.64258285082877],"type":"Point"}
}