{
  "type": "Feature",
  "properties": {
    "iso:country":"GB",
    "wof:name":"OX29 7AB",
    "wof:placetype":"postalcode"
},
  "geometry": {"coordinates":[-1.47756643843379,51.76314924998605],"type":"Point"}
}