{
  "type": "Feature",
  "properties": {
    "date:inception_lower":"2008-04-01",
    "date:inception_upper":"2008-04-30",
    "iso:country":"GB",
    "wof:name":"OX29 7AB",
    "wof:placetype":"postalcode"
},
  "geometry": {"coordinates":[-1.477566,51.763149],"type":"Point"}
}