{
  "type": "Feature",
  "properties": {
    "iso:country": "GB",
    "wof:name": "OX29 7AB",
    "wof:placetype": "postalcode"
  },
  "geometry": {"coordinates":[-1.477566,51.763149],"type":"Point"}
}
