{
  "type": "Feature",
  "properties": {
    "iso:country":"GB",
    "wof:name":"CB9 7AU",
    "wof:placetype":"postalcode"
},
  "geometry": {"coordinates":[0.39766147892359,52.05718027268432],"type":"Point"}
}