{
  "type": "Feature",
  "properties": {
    "date:inception_lower": "1980-01-01",
    "date:inception_upper": "1980-01-01",
    "iso:country": "GB",
    "wof:name": "CB9 7AU",
    "wof:placetype": "postalcode"
  },
  "geometry": {"coordinates":[0.397662,52.05718],"type":"Point"}
}
