{
  "type": "Feature",
  "properties": {
    "iso:country": "GB",
    "wof:name": "CB9 7AU",
    "wof:placetype": "postalcode"
  },
  "geometry": {"coordinates":[0.397662,52.05718],"type":"Point"}
}
