{
  "type": "Feature",
  "properties": {
    "iso:country":"GB",
    "wof:name":"TW2 7AL",
    "wof:placetype":"postalcode"
},
  "geometry": {"coordinates":[-0.37130596057678,51.45417492782747],"type":"Point"}
}