{
  "type": "Feature",
  "properties": {
    "iso:country":"GB",
    "wof:name":"B90 3RH",
    "wof:placetype":"postalcode"
},
  "geometry": {"coordinates":[-1.81099570756797,52.40567994474895],"type":"Point"}
}