{
  "type": "Feature",
  "properties": {
    "date:inception_lower": "1992-08-01",
    "date:inception_upper": "1992-08-01",
    "iso:country": "GB",
    "wof:name": "NE11 9PT",
    "wof:placetype": "postalcode"
  },
  "geometry": {"coordinates":[-1.644698,54.941282],"type":"Point"}
}
