{
  "type": "Feature",
  "properties": {
    "date:inception_lower":"1980-01-01",
    "date:inception_upper":"1980-01-31",
    "iso:country":"GB",
    "wof:name":"BL7 9TY",
    "wof:placetype":"postalcode"
},
  "geometry": {"coordinates":[-2.444234,53.62885],"type":"Point"}
}