{
  "type": "Feature",
  "properties": {
    "iso:country": "GB",
    "wof:name": "TF1 2HP",
    "wof:placetype": "postalcode"
  },
  "geometry": {"coordinates":[-2.522602,52.695535],"type":"Point"}
}
