{
  "type": "Feature",
  "properties": {
    "date:inception_lower":"2003-09-01",
    "date:inception_upper":"2003-09-30",
    "iso:country":"GB",
    "wof:name":"TF1 2HP",
    "wof:placetype":"postalcode"
},
  "geometry": {"coordinates":[-2.522602,52.695535],"type":"Point"}
}