{
  "type": "Feature",
  "properties": {
    "iso:country":"GB",
    "wof:name":"TF1 2HP",
    "wof:placetype":"postalcode"
},
  "geometry": {"coordinates":[-2.52260154724635,52.69553521062533],"type":"Point"}
}