{
  "type": "Feature",
  "properties": {
    "iso:country":"GB",
    "wof:name":"W1S 3NL",
    "wof:placetype":"postalcode"
},
  "geometry": {"coordinates":[-0.14091852275025,51.51036853436745],"type":"Point"}
}