{
  "type": "Feature",
  "properties": {
    "iso:country": "GB",
    "wof:name": "PL27 6FD",
    "wof:placetype": "postalcode"
  },
  "geometry": {"coordinates":[-4.924415,50.545012],"type":"Point"}
}
