{
  "type": "Feature",
  "properties": {
    "date:inception_lower":"2010-09-01",
    "date:inception_upper":"2010-09-30",
    "iso:country":"GB",
    "wof:name":"PL27 6FD",
    "wof:placetype":"postalcode"
},
  "geometry": {"coordinates":[-4.924415,50.545012],"type":"Point"}
}