{
  "type": "Feature",
  "properties": {
    "date:inception_lower":"1983-01-01",
    "date:inception_upper":"1983-01-31",
    "iso:country":"GB",
    "wof:name":"CF41 7QN",
    "wof:placetype":"postalcode"
},
  "geometry": {"coordinates":[-3.479363,51.647292],"type":"Point"}
}