{
  "type": "Feature",
  "properties": {
    "date:inception_lower": "1980-01-01",
    "date:inception_upper": "1980-01-01",
    "iso:country": "GB",
    "wof:name": "HA1 2PN",
    "wof:placetype": "postalcode"
  },
  "geometry": {"coordinates":[-0.324156,51.584897],"type":"Point"}
}
