{
  "type": "Feature",
  "properties": {
    "iso:country":"GB",
    "wof:name":"HA1 2PN",
    "wof:placetype":"postalcode"
},
  "geometry": {"coordinates":[-0.32415586102746,51.58489692314029],"type":"Point"}
}