{
  "type": "Feature",
  "properties": {
    "iso:country":"GB",
    "wof:name":"GU21 3QW",
    "wof:placetype":"postalcode"
},
  "geometry": {"coordinates":[-0.60223984673629,51.32443014090882],"type":"Point"}
}