{
  "type": "Feature",
  "properties": {
    "date:inception_lower": "2002-12-01",
    "date:inception_upper": "2002-12-01",
    "iso:country": "GB",
    "wof:name": "SE18 6WD",
    "wof:placetype": "postalcode"
  },
  "geometry": {"coordinates":[0.084847,51.490736],"type":"Point"}
}
