{
  "type": "Feature",
  "properties": {
    "iso:country":"GB",
    "wof:name":"BB7 4HT",
    "wof:placetype":"postalcode"
},
  "geometry": {"coordinates":[-2.26430969312717,53.93555890596418],"type":"Point"}
}