{
  "type": "Feature",
  "properties": {
    "iso:country": "GB",
    "wof:name": "BB7 4HT",
    "wof:placetype": "postalcode"
  },
  "geometry": {"coordinates":[-2.26431,53.935559],"type":"Point"}
}
