{
  "type": "Feature",
  "properties": {
    "iso:country":"GB",
    "wof:name":"N5 1PP",
    "wof:placetype":"postalcode"
},
  "geometry": {"coordinates":[-0.1066400311671,51.55088902434053],"type":"Point"}
}