{
  "type": "Feature",
  "properties": {
    "iso:country": "GB",
    "wof:name": "HG3 2YQ",
    "wof:placetype": "postalcode"
  },
  "geometry": {"coordinates":[-1.565559,54.007657],"type":"Point"}
}
