{
  "type": "Feature",
  "properties": {
    "iso:country": "GB",
    "wof:name": "CO9 1PW",
    "wof:placetype": "postalcode"
  },
  "geometry": {"coordinates":[0.64117,51.937734],"type":"Point"}
}
