{
  "type": "Feature",
  "properties": {
    "iso:country":"GB",
    "wof:name":"CO9 1PW",
    "wof:placetype":"postalcode"
},
  "geometry": {"coordinates":[0.64117006148415,51.93773380305122],"type":"Point"}
}