{
  "type": "Feature",
  "properties": {
    "iso:country":"GB",
    "wof:name":"BA21 5EL",
    "wof:placetype":"postalcode"
},
  "geometry": {"coordinates":[-2.60509557180533,50.94737404995179],"type":"Point"}
}