{
  "type": "Feature",
  "properties": {
    "iso:country":"GB",
    "wof:name":"NG33 4AB",
    "wof:placetype":"postalcode"
},
  "geometry": {"coordinates":[-0.57602109896777,52.89127304217303],"type":"Point"}
}