{
  "type": "Feature",
  "properties": {
    "date:inception_lower": "1980-01-01",
    "date:inception_upper": "1980-01-01",
    "iso:country": "GB",
    "wof:name": "CV21 3RB",
    "wof:placetype": "postalcode"
  },
  "geometry": {"coordinates":[-1.239332,52.375047],"type":"Point"}
}
