{
  "type": "Feature",
  "properties": {
    "date:inception_lower": "1995-07-01",
    "date:inception_upper": "1995-07-01",
    "iso:country": "GB",
    "wof:name": "RG40 2HW",
    "wof:placetype": "postalcode"
  },
  "geometry": {"coordinates":[-0.824016,51.405754],"type":"Point"}
}
