{
  "type": "Feature",
  "properties": {
    "date:inception_lower": "1990-02-01",
    "date:inception_upper": "1990-02-01",
    "iso:country": "GB",
    "wof:name": "TW8 9QP",
    "wof:placetype": "postalcode"
  },
  "geometry": {"coordinates":[-0.300638,51.494807],"type":"Point"}
}
