{
  "type": "Feature",
  "properties": {
    "iso:country":"GB",
    "wof:name":"DL16 7LA",
    "wof:placetype":"postalcode"
},
  "geometry": {"coordinates":[-1.59925224315197,54.67762023773537],"type":"Point"}
}