{
  "type": "Feature",
  "properties": {
    "date:inception_lower": "1980-01-01",
    "date:inception_upper": "1980-01-01",
    "iso:country": "GB",
    "wof:name": "S74 0JF",
    "wof:placetype": "postalcode"
  },
  "geometry": {"coordinates":[-1.426117,53.507271],"type":"Point"}
}
