{
  "type": "Feature",
  "properties": {
    "iso:country": "GB",
    "wof:name": "S74 0JF",
    "wof:placetype": "postalcode"
  },
  "geometry": {"coordinates":[-1.426117,53.507271],"type":"Point"}
}
