{
  "type": "Feature",
  "properties": {
    "iso:country":"GB",
    "wof:name":"S74 0JF",
    "wof:placetype":"postalcode"
},
  "geometry": {"coordinates":[-1.42611661222512,53.50727118242227],"type":"Point"}
}