{
  "type": "Feature",
  "properties": {
    "iso:country":"GB",
    "wof:name":"SA3 1HN",
    "wof:placetype":"postalcode"
},
  "geometry": {"coordinates":[-4.21144958194595,51.59547617502687],"type":"Point"}
}