{
  "type": "Feature",
  "properties": {
    "iso:country":"GB",
    "wof:name":"SO31 8DA",
    "wof:placetype":"postalcode"
},
  "geometry": {"coordinates":[-1.30894402718741,50.88832286589101],"type":"Point"}
}