{
  "type": "Feature",
  "properties": {
    "iso:country": "GB",
    "wof:name": "CF5 2PE",
    "wof:placetype": "postalcode"
  },
  "geometry": {"coordinates":[-3.243197,51.507995],"type":"Point"}
}
