{
  "type": "Feature",
  "properties": {
    "iso:country":"GB",
    "wof:name":"SW6 6PH",
    "wof:placetype":"postalcode"
},
  "geometry": {"coordinates":[-0.22055328668343,51.47672206318555],"type":"Point"}
}