{
  "type": "Feature",
  "properties": {
    "iso:country": "GB",
    "wof:name": "S5 8LY",
    "wof:placetype": "postalcode"
  },
  "geometry": {"coordinates":[-1.489655,53.419363],"type":"Point"}
}
