{
  "type": "Feature",
  "properties": {
    "iso:country": "GB",
    "wof:name": "PR2 6BH",
    "wof:placetype": "postalcode"
  },
  "geometry": {"coordinates":[-2.661112,53.778249],"type":"Point"}
}
