{
  "type": "Feature",
  "properties": {
    "iso:country":"GB",
    "wof:name":"PE1 3EG",
    "wof:placetype":"postalcode"
},
  "geometry": {"coordinates":[-0.24582400987623,52.59564729097622],"type":"Point"}
}