{
  "type": "Feature",
  "properties": {
    "iso:country": "GB",
    "wof:name": "PE1 3EG",
    "wof:placetype": "postalcode"
  },
  "geometry": {"coordinates":[-0.245824,52.595647],"type":"Point"}
}
