{
  "type": "Feature",
  "properties": {
    "iso:country":"GB",
    "wof:name":"IP21 4BD",
    "wof:placetype":"postalcode"
},
  "geometry": {"coordinates":[1.09078675787538,52.33837740643904],"type":"Point"}
}