{
  "type": "Feature",
  "properties": {
    "date:inception_lower": "1998-12-01",
    "date:inception_upper": "1998-12-01",
    "iso:country": "GB",
    "wof:name": "IP21 4BD",
    "wof:placetype": "postalcode"
  },
  "geometry": {"coordinates":[1.090743,52.338398],"type":"Point"}
}
