{
  "type": "Feature",
  "properties": {
    "iso:country": "GB",
    "wof:name": "BD3 9QF",
    "wof:placetype": "postalcode"
  },
  "geometry": {"coordinates":[-1.73992,53.792105],"type":"Point"}
}
