{
  "type": "Feature",
  "properties": {
    "iso:country":"GB",
    "wof:name":"BD3 9QF",
    "wof:placetype":"postalcode"
},
  "geometry": {"coordinates":[-1.73992011947428,53.79210468434051],"type":"Point"}
}