{
  "type": "Feature",
  "properties": {
    "date:inception_lower":"2007-03-01",
    "date:inception_upper":"2007-03-31",
    "iso:country":"GB",
    "wof:name":"BD3 9QF",
    "wof:placetype":"postalcode"
},
  "geometry": {"coordinates":[-1.73992,53.792105],"type":"Point"}
}