{
  "type": "Feature",
  "properties": {
    "date:inception_lower": "1980-01-01",
    "date:inception_upper": "1980-01-01",
    "iso:country": "GB",
    "wof:name": "PA16 0TE",
    "wof:placetype": "postalcode"
  },
  "geometry": {"coordinates":[-4.809509,55.942016],"type":"Point"}
}
