{
  "type": "Feature",
  "properties": {
    "iso:country":"GB",
    "wof:name":"EC3V 1LT",
    "wof:placetype":"postalcode"
},
  "geometry": {"coordinates":[-0.08362219356948,51.51236891372753],"type":"Point"}
}