{
  "type": "Feature",
  "properties": {
    "iso:country":"GB",
    "wof:name":"WD6 5ED",
    "wof:placetype":"postalcode"
},
  "geometry": {"coordinates":[-0.27650134998999,51.66665627120657],"type":"Point"}
}