{
  "type": "Feature",
  "properties": {
    "date:inception_lower": "1980-01-01",
    "date:inception_upper": "1980-01-01",
    "iso:country": "GB",
    "wof:name": "PE1 5LF",
    "wof:placetype": "postalcode"
  },
  "geometry": {"coordinates":[-0.22376,52.584466],"type":"Point"}
}
