{
  "type": "Feature",
  "properties": {
    "date:inception_lower":"1984-02-01",
    "date:inception_upper":"1984-02-29",
    "iso:country":"GB",
    "wof:name":"BL2 6RT",
    "wof:placetype":"postalcode"
},
  "geometry": {"coordinates":[-2.363084,53.573171],"type":"Point"}
}