{
  "type": "Feature",
  "properties": {
    "iso:country":"GB",
    "wof:name":"BL2 6RT",
    "wof:placetype":"postalcode"
},
  "geometry": {"coordinates":[-2.3630843404215,53.57317117847062],"type":"Point"}
}