{
  "type": "Feature",
  "properties": {
    "iso:country": "GB",
    "wof:name": "HR9 5RN",
    "wof:placetype": "postalcode"
  },
  "geometry": {"coordinates":[-2.594508,51.90596],"type":"Point"}
}
