{
  "type": "Feature",
  "properties": {
    "iso:country":"GB",
    "wof:name":"DA2 7BD",
    "wof:placetype":"postalcode"
},
  "geometry": {"coordinates":[0.19197784476444,51.43120010084333],"type":"Point"}
}