{
  "type": "Feature",
  "properties": {
    "date:inception_lower": "1980-01-01",
    "date:inception_upper": "1980-01-01",
    "iso:country": "GB",
    "wof:name": "DA2 7BD",
    "wof:placetype": "postalcode"
  },
  "geometry": {"coordinates":[0.192005,51.4312],"type":"Point"}
}
