{
  "type": "Feature",
  "properties": {
    "iso:country":"GB",
    "wof:name":"HA6 3BG",
    "wof:placetype":"postalcode"
},
  "geometry": {"coordinates":[-0.42388193963772,51.61202280674028],"type":"Point"}
}