{
  "type": "Feature",
  "properties": {
    "iso:country":"GB",
    "wof:name":"M46 0LR",
    "wof:placetype":"postalcode"
},
  "geometry": {"coordinates":[-2.50068733323275,53.52335459088623],"type":"Point"}
}