{
  "type": "Feature",
  "properties": {
    "date:inception_lower": "1994-05-01",
    "date:inception_upper": "1994-05-01",
    "iso:country": "GB",
    "wof:name": "M46 0LR",
    "wof:placetype": "postalcode"
  },
  "geometry": {"coordinates":[-2.500687,53.523355],"type":"Point"}
}
