{
  "type": "Feature",
  "properties": {
    "iso:country":"GB",
    "wof:name":"PE10 0NF",
    "wof:placetype":"postalcode"
},
  "geometry": {"coordinates":[-0.47187037037305,52.80065158537684],"type":"Point"}
}