{
  "type": "Feature",
  "properties": {
    "date:inception_lower":"1980-01-01",
    "date:inception_upper":"1980-01-31",
    "iso:country":"GB",
    "wof:name":"PE10 0NF",
    "wof:placetype":"postalcode"
},
  "geometry": {"coordinates":[-0.47187,52.800652],"type":"Point"}
}