{
  "type": "Feature",
  "properties": {
    "iso:country": "GB",
    "wof:name": "PE10 0NF",
    "wof:placetype": "postalcode"
  },
  "geometry": {"coordinates":[-0.47187,52.800652],"type":"Point"}
}
