{
  "type": "Feature",
  "properties": {
    "iso:country": "GB",
    "wof:name": "TQ9 7LE",
    "wof:placetype": "postalcode"
  },
  "geometry": {"coordinates":[-3.723335,50.381385],"type":"Point"}
}
