{
  "type": "Feature",
  "properties": {
    "date:inception_lower": "1992-08-01",
    "date:inception_upper": "1992-08-01",
    "iso:country": "GB",
    "wof:name": "MK15 8HR",
    "wof:placetype": "postalcode"
  },
  "geometry": {"coordinates":[-0.736279,52.067648],"type":"Point"}
}
