{
  "type": "Feature",
  "properties": {
    "iso:country":"GB",
    "wof:name":"WV11 2NX",
    "wof:placetype":"postalcode"
},
  "geometry": {"coordinates":[-2.0520230183828,52.61851130038283],"type":"Point"}
}