{
  "type": "Feature",
  "properties": {
    "date:inception_lower": "1980-01-01",
    "date:inception_upper": "1980-01-01",
    "iso:country": "GB",
    "wof:name": "WV11 2NX",
    "wof:placetype": "postalcode"
  },
  "geometry": {"coordinates":[-2.052023,52.618511],"type":"Point"}
}
