{
  "type": "Feature",
  "properties": {
    "iso:country": "GB",
    "wof:name": "W2 1BS",
    "wof:placetype": "postalcode"
  },
  "geometry": {"coordinates":[-0.173945,51.522362],"type":"Point"}
}
