{
  "type": "Feature",
  "properties": {
    "iso:country":"GB",
    "wof:name":"NE30 2LG",
    "wof:placetype":"postalcode"
},
  "geometry": {"coordinates":[-1.43454098635304,55.02170503987858],"type":"Point"}
}