{
  "type": "Feature",
  "properties": {
    "iso:country": "GB",
    "wof:name": "M25 1QH",
    "wof:placetype": "postalcode"
  },
  "geometry": {"coordinates":[-2.269423,53.53261],"type":"Point"}
}
