{
  "type": "Feature",
  "properties": {
    "iso:country":"GB",
    "wof:name":"TR19 7BT",
    "wof:placetype":"postalcode"
},
  "geometry": {"coordinates":[-5.69278923414858,50.07771475012986],"type":"Point"}
}