{
  "type": "Feature",
  "properties": {
    "iso:country": "GB",
    "wof:name": "BB2 5AS",
    "wof:placetype": "postalcode"
  },
  "geometry": {"coordinates":[-2.515285,53.725545],"type":"Point"}
}
