{
  "type": "Feature",
  "properties": {
    "date:inception_lower": "2007-11-01",
    "date:inception_upper": "2007-11-01",
    "iso:country": "GB",
    "wof:name": "PO19 1QQ",
    "wof:placetype": "postalcode"
  },
  "geometry": {"coordinates":[-0.78364,50.837413],"type":"Point"}
}
