{
  "type": "Feature",
  "properties": {
    "date:inception_lower":"1980-01-01",
    "date:inception_upper":"1980-01-31",
    "iso:country":"GB",
    "wof:name":"SO23 7LF",
    "wof:placetype":"postalcode"
},
  "geometry": {"coordinates":[-1.304588,51.092878],"type":"Point"}
}