{
  "type": "Feature",
  "properties": {
    "iso:country":"GB",
    "wof:name":"BA1 5AL",
    "wof:placetype":"postalcode"
},
  "geometry": {"coordinates":[-2.35926208075095,51.38351327652498],"type":"Point"}
}