{
  "type": "Feature",
  "properties": {
    "date:inception_lower": "1990-07-01",
    "date:inception_upper": "1990-07-01",
    "iso:country": "GB",
    "wof:name": "BA1 5AL",
    "wof:placetype": "postalcode"
  },
  "geometry": {"coordinates":[-2.35926,51.38351],"type":"Point"}
}
