{
  "type": "Feature",
  "properties": {
    "iso:country":"GB",
    "wof:name":"KY8 2EB",
    "wof:placetype":"postalcode"
},
  "geometry": {"coordinates":[-3.0401592283373,56.18514250278],"type":"Point"}
}