{
  "type": "Feature",
  "properties": {
    "iso:country":"GB",
    "wof:name":"DN35 0HJ",
    "wof:placetype":"postalcode"
},
  "geometry": {"coordinates":[-0.01948928652389,53.5442853768197],"type":"Point"}
}