{
  "type": "Feature",
  "properties": {
    "iso:country": "GB",
    "wof:name": "S74 9HU",
    "wof:placetype": "postalcode"
  },
  "geometry": {"coordinates":[-1.448819,53.501832],"type":"Point"}
}
