{
  "type": "Feature",
  "properties": {
    "iso:country":"GB",
    "wof:name":"S74 9HU",
    "wof:placetype":"postalcode"
},
  "geometry": {"coordinates":[-1.44881908216385,53.50183204176025],"type":"Point"}
}