{
  "type": "Feature",
  "properties": {
    "iso:country": "GB",
    "wof:name": "ME15 8LS",
    "wof:placetype": "postalcode"
  },
  "geometry": {"coordinates":[0.561478,51.263717],"type":"Point"}
}
