{
  "type": "Feature",
  "properties": {
    "date:inception_lower": "1980-01-01",
    "date:inception_upper": "1980-01-01",
    "iso:country": "GB",
    "wof:name": "HR9 7PJ",
    "wof:placetype": "postalcode"
  },
  "geometry": {"coordinates":[-2.514225,51.914709],"type":"Point"}
}
