{
  "type": "Feature",
  "properties": {
    "iso:country":"GB",
    "wof:name":"HR9 7PJ",
    "wof:placetype":"postalcode"
},
  "geometry": {"coordinates":[-2.51422489112229,51.9147088833608],"type":"Point"}
}