{
  "type": "Feature",
  "properties": {
    "date:inception_lower": "1980-01-01",
    "date:inception_upper": "1980-01-01",
    "iso:country": "GB",
    "wof:name": "BD10 8TR",
    "wof:placetype": "postalcode"
  },
  "geometry": {"coordinates":[-1.738826,53.829025],"type":"Point"}
}
