{
  "type": "Feature",
  "properties": {
    "iso:country":"GB",
    "wof:name":"TW8 0GF",
    "wof:placetype":"postalcode"
},
  "geometry": {"coordinates":[-0.30159925241135,51.4902614749826],"type":"Point"}
}