{
  "type": "Feature",
  "properties": {
    "date:inception_lower": "2009-10-01",
    "date:inception_upper": "2009-10-01",
    "iso:country": "GB",
    "wof:name": "TW8 0GF",
    "wof:placetype": "postalcode"
  },
  "geometry": {"coordinates":[-0.301599,51.490261],"type":"Point"}
}
