{
  "type": "Feature",
  "properties": {
    "date:inception_lower":"1995-01-01",
    "date:inception_upper":"1995-01-31",
    "iso:country":"GB",
    "wof:name":"SN15 3WA",
    "wof:placetype":"postalcode"
},
  "geometry": {"coordinates":[-2.109116,51.449464],"type":"Point"}
}