{
  "type": "Feature",
  "properties": {
    "iso:country": "GB",
    "wof:name": "SN15 3WA",
    "wof:placetype": "postalcode"
  },
  "geometry": {"coordinates":[-2.109116,51.449464],"type":"Point"}
}
