{
  "type": "Feature",
  "properties": {
    "date:inception_lower":"2011-05-01",
    "date:inception_upper":"2011-05-31",
    "iso:country":"GB",
    "wof:name":"TS10 4RX",
    "wof:placetype":"postalcode"
},
  "geometry": {"coordinates":[-1.067846,54.596637],"type":"Point"}
}