{
  "type": "Feature",
  "properties": {
    "iso:country":"GB",
    "wof:name":"TS10 4RX",
    "wof:placetype":"postalcode"
},
  "geometry": {"coordinates":[-1.06784641327204,54.5966368474895],"type":"Point"}
}