{
  "type": "Feature",
  "properties": {
    "iso:country": "GB",
    "wof:name": "DE7 5EB",
    "wof:placetype": "postalcode"
  },
  "geometry": {"coordinates":[-1.294154,52.968816],"type":"Point"}
}
