{
  "type": "Feature",
  "properties": {
    "iso:country":"GB",
    "wof:name":"DE7 5EB",
    "wof:placetype":"postalcode"
},
  "geometry": {"coordinates":[-1.29415412952861,52.96881645266917],"type":"Point"}
}