{
  "type": "Feature",
  "properties": {
    "iso:country":"GB",
    "wof:name":"LS15 8TX",
    "wof:placetype":"postalcode"
},
  "geometry": {"coordinates":[-1.4459692833129,53.81473722354629],"type":"Point"}
}