{
  "type": "Feature",
  "properties": {
    "date:inception_lower": "2020-08-01",
    "date:inception_upper": "2020-08-01",
    "iso:country": "GB",
    "wof:name": "TN39 4GN",
    "wof:placetype": "postalcode"
  },
  "geometry": {"coordinates":[0.426219,50.844002],"type":"Point"}
}
