{
  "type": "Feature",
  "properties": {
    "iso:country":"GB",
    "wof:name":"S11 8UL",
    "wof:placetype":"postalcode"
},
  "geometry": {"coordinates":[-1.50135855852166,53.36547180095994],"type":"Point"}
}