{
  "type": "Feature",
  "properties": {
    "iso:country": "GB",
    "wof:name": "S11 8UL",
    "wof:placetype": "postalcode"
  },
  "geometry": {"coordinates":[-1.501359,53.365472],"type":"Point"}
}
