{
  "type": "Feature",
  "properties": {
    "date:inception_lower": "1980-01-01",
    "date:inception_upper": "1980-01-01",
    "iso:country": "GB",
    "wof:name": "S11 8UL",
    "wof:placetype": "postalcode"
  },
  "geometry": {"coordinates":[-1.501359,53.365472],"type":"Point"}
}
