{
  "type": "Feature",
  "properties": {
    "date:inception_lower":"2006-05-01",
    "date:inception_upper":"2006-05-31",
    "iso:country":"GB",
    "wof:name":"LN6 9JH",
    "wof:placetype":"postalcode"
},
  "geometry": {"coordinates":[-0.662991,53.147864],"type":"Point"}
}