{
  "type": "Feature",
  "properties": {
    "iso:country":"GB",
    "wof:name":"LN6 9JH",
    "wof:placetype":"postalcode"
},
  "geometry": {"coordinates":[-0.66299102885849,53.14786398060369],"type":"Point"}
}