{
  "type": "Feature",
  "properties": {
    "iso:country":"GB",
    "wof:name":"KA10 6QZ",
    "wof:placetype":"postalcode"
},
  "geometry": {"coordinates":[-4.65712799425236,55.54946667615041],"type":"Point"}
}