{
  "type": "Feature",
  "properties": {
    "date:inception_lower": "1980-01-01",
    "date:inception_upper": "1980-01-01",
    "iso:country": "GB",
    "wof:name": "KA10 6QZ",
    "wof:placetype": "postalcode"
  },
  "geometry": {"coordinates":[-4.657128,55.549467],"type":"Point"}
}
