{
  "type": "Feature",
  "properties": {
    "iso:country": "GB",
    "wof:name": "G42 0AF",
    "wof:placetype": "postalcode"
  },
  "geometry": {"coordinates":[-4.239445,55.831458],"type":"Point"}
}
