{
  "type": "Feature",
  "properties": {
    "date:inception_lower": "2018-04-01",
    "date:inception_upper": "2018-04-01",
    "iso:country": "GB",
    "wof:name": "G42 0AF",
    "wof:placetype": "postalcode"
  },
  "geometry": {"coordinates":[-4.239445,55.831458],"type":"Point"}
}
