{
  "type": "Feature",
  "properties": {
    "iso:country":"GB",
    "wof:name":"BD14 6AZ",
    "wof:placetype":"postalcode"
},
  "geometry": {"coordinates":[-1.81975615210034,53.78359564504953],"type":"Point"}
}