{
  "type": "Feature",
  "properties": {
    "date:inception_lower": "1980-01-01",
    "date:inception_upper": "1980-01-01",
    "iso:country": "GB",
    "wof:name": "SG13 8LQ",
    "wof:placetype": "postalcode"
  },
  "geometry": {"coordinates":[-0.140551,51.772336],"type":"Point"}
}
