{
  "type": "Feature",
  "properties": {
    "date:inception_lower":"2007-11-01",
    "date:inception_upper":"2007-11-30",
    "iso:country":"GB",
    "wof:name":"G33 1PB",
    "wof:placetype":"postalcode"
},
  "geometry": {"coordinates":[-4.194845,55.873986],"type":"Point"}
}