{
  "type": "Feature",
  "properties": {
    "iso:country":"GB",
    "wof:name":"CO3 0JW",
    "wof:placetype":"postalcode"
},
  "geometry": {"coordinates":[0.84760564116475,51.87824708793049],"type":"Point"}
}