{
  "type": "Feature",
  "properties": {
    "iso:country": "GB",
    "wof:name": "BA2 7PS",
    "wof:placetype": "postalcode"
  },
  "geometry": {"coordinates":[-2.332123,51.380542],"type":"Point"}
}
