{
  "type": "Feature",
  "properties": {
    "iso:country":"GB",
    "wof:name":"N11 1NX",
    "wof:placetype":"postalcode"
},
  "geometry": {"coordinates":[-0.14482258635751,51.61674787636315],"type":"Point"}
}