{
  "type": "Feature",
  "properties": {
    "iso:country":"GB",
    "wof:name":"BS8 1HA",
    "wof:placetype":"postalcode"
},
  "geometry": {"coordinates":[-2.60683136739345,51.45581054929274],"type":"Point"}
}