{
  "type": "Feature",
  "properties": {
    "iso:country":"GB",
    "wof:name":"CH7 6YR",
    "wof:placetype":"postalcode"
},
  "geometry": {"coordinates":[-3.11243642604481,53.16944147608462],"type":"Point"}
}