{
  "type": "Feature",
  "properties": {
    "iso:country": "GB",
    "wof:name": "CH7 6YR",
    "wof:placetype": "postalcode"
  },
  "geometry": {"coordinates":[-3.112436,53.169441],"type":"Point"}
}
