{
  "type": "Feature",
  "properties": {
    "date:inception_lower": "2017-11-01",
    "date:inception_upper": "2017-11-01",
    "iso:country": "GB",
    "wof:name": "LE7 7WE",
    "wof:placetype": "postalcode"
  },
  "geometry": {"coordinates":[-1.131061,52.716422],"type":"Point"}
}
