{
  "type": "Feature",
  "properties": {
    "date:inception_lower":"2017-11-01",
    "date:inception_upper":"2017-11-30",
    "iso:country":"GB",
    "wof:name":"LE7 7WE",
    "wof:placetype":"postalcode"
},
  "geometry": {"coordinates":[-1.131046,52.716431],"type":"Point"}
}