{
  "type": "Feature",
  "properties": {
    "iso:country": "GB",
    "wof:name": "LE7 7WE",
    "wof:placetype": "postalcode"
  },
  "geometry": {"coordinates":[-1.131046,52.716431],"type":"Point"}
}
