{
  "type": "Feature",
  "properties": {
    "iso:country": "GB",
    "wof:name": "SR2 0FR",
    "wof:placetype": "postalcode"
  },
  "geometry": {"coordinates":[-1.372563,54.863697],"type":"Point"}
}
