{
  "type": "Feature",
  "properties": {
    "date:inception_lower": "2019-04-01",
    "date:inception_upper": "2019-04-01",
    "iso:country": "GB",
    "wof:name": "SR2 0FR",
    "wof:placetype": "postalcode"
  },
  "geometry": {"coordinates":[-1.373596,54.861339],"type":"Point"}
}
