{
  "type": "Feature",
  "properties": {
    "iso:country":"GB",
    "wof:name":"SS7 4JG",
    "wof:placetype":"postalcode"
},
  "geometry": {"coordinates":[0.55968597180819,51.57487997205525],"type":"Point"}
}