{
  "type": "Feature",
  "properties": {
    "iso:country":"GB",
    "wof:name":"PR9 7LP",
    "wof:placetype":"postalcode"
},
  "geometry": {"coordinates":[-2.96812258457211,53.66030080923301],"type":"Point"}
}