{
  "type": "Feature",
  "properties": {
    "iso:country": "GB",
    "wof:name": "LA14 4PE",
    "wof:placetype": "postalcode"
  },
  "geometry": {"coordinates":[-3.207425,54.139555],"type":"Point"}
}
