{
  "type": "Feature",
  "properties": {
    "iso:country":"GB",
    "wof:name":"PO33 1EB",
    "wof:placetype":"postalcode"
},
  "geometry": {"coordinates":[-1.1531298816036,50.72087724740844],"type":"Point"}
}