{
  "type": "Feature",
  "properties": {
    "iso:country":"GB",
    "wof:name":"B34 7EA",
    "wof:placetype":"postalcode"
},
  "geometry": {"coordinates":[-1.77659893108604,52.49890045653744],"type":"Point"}
}