{
  "type": "Feature",
  "properties": {
    "date:inception_lower": "2000-12-01",
    "date:inception_upper": "2000-12-01",
    "iso:country": "GB",
    "wof:name": "G53 6DH",
    "wof:placetype": "postalcode"
  },
  "geometry": {"coordinates":[-4.348766,55.821405],"type":"Point"}
}
