{
  "type": "Feature",
  "properties": {
    "iso:country": "GB",
    "wof:name": "LL22 9EA",
    "wof:placetype": "postalcode"
  },
  "geometry": {"coordinates":[-3.53913,53.240034],"type":"Point"}
}
