{
  "type": "Feature",
  "properties": {
    "date:inception_lower":"2016-02-01",
    "date:inception_upper":"2016-02-29",
    "iso:country":"GB",
    "wof:name":"OL16 4FU",
    "wof:placetype":"postalcode"
},
  "geometry": {"coordinates":[-2.135226,53.59358],"type":"Point"}
}