{
  "type": "Feature",
  "properties": {
    "iso:country": "GB",
    "wof:name": "OL16 4FU",
    "wof:placetype": "postalcode"
  },
  "geometry": {"coordinates":[-2.135226,53.59358],"type":"Point"}
}
