{
  "type": "Feature",
  "properties": {
    "iso:country":"GB",
    "wof:name":"ME13 9UB",
    "wof:placetype":"postalcode"
},
  "geometry": {"coordinates":[0.95291680626592,51.3028368137221],"type":"Point"}
}