{
  "type": "Feature",
  "properties": {
    "date:inception_lower": "2017-04-01",
    "date:inception_upper": "2017-04-01",
    "iso:country": "GB",
    "wof:name": "G5 9LQ",
    "wof:placetype": "postalcode"
  },
  "geometry": {"coordinates":[-4.256853,55.852152],"type":"Point"}
}
