{
  "type": "Feature",
  "properties": {
    "date:inception_lower":"1980-01-01",
    "date:inception_upper":"1980-01-31",
    "iso:country":"GB",
    "wof:name":"OX16 9LX",
    "wof:placetype":"postalcode"
},
  "geometry": {"coordinates":[-1.348055,52.054431],"type":"Point"}
}