{
  "type": "Feature",
  "properties": {
    "iso:country": "GB",
    "wof:name": "OX16 9LX",
    "wof:placetype": "postalcode"
  },
  "geometry": {"coordinates":[-1.348055,52.054431],"type":"Point"}
}
