{
  "type": "Feature",
  "properties": {
    "iso:country":"GB",
    "wof:name":"OX16 9LX",
    "wof:placetype":"postalcode"
},
  "geometry": {"coordinates":[-1.34805518361605,52.05443051849407],"type":"Point"}
}