{
  "type": "Feature",
  "properties": {
    "iso:country": "GB",
    "wof:name": "CV23 8BJ",
    "wof:placetype": "postalcode"
  },
  "geometry": {"coordinates":[-1.236737,52.302208],"type":"Point"}
}
