{
  "type": "Feature",
  "properties": {
    "iso:country":"GB",
    "wof:name":"CV23 8BJ",
    "wof:placetype":"postalcode"
},
  "geometry": {"coordinates":[-1.2367659416599,52.30218231852911],"type":"Point"}
}