{
  "type": "Feature",
  "properties": {
    "date:inception_lower": "1980-01-01",
    "date:inception_upper": "1980-01-01",
    "iso:country": "GB",
    "wof:name": "CV23 8BJ",
    "wof:placetype": "postalcode"
  },
  "geometry": {"coordinates":[-1.236737,52.302208],"type":"Point"}
}
