{
  "type": "Feature",
  "properties": {
    "iso:country": "GB",
    "wof:name": "LU7 2NZ",
    "wof:placetype": "postalcode"
  },
  "geometry": {"coordinates":[-0.673799,51.91268],"type":"Point"}
}
