{
  "type": "Feature",
  "properties": {
    "iso:country":"GB",
    "wof:name":"LU7 2NZ",
    "wof:placetype":"postalcode"
},
  "geometry": {"coordinates":[-0.67379900020477,51.91268042277878],"type":"Point"}
}