{
  "type": "Feature",
  "properties": {
    "iso:country":"GB",
    "wof:name":"YO42 2ER",
    "wof:placetype":"postalcode"
},
  "geometry": {"coordinates":[-0.78864505590387,53.934777823513],"type":"Point"}
}