{
  "type": "Feature",
  "properties": {
    "iso:country": "GB",
    "wof:name": "YO42 2ER",
    "wof:placetype": "postalcode"
  },
  "geometry": {"coordinates":[-0.788645,53.934778],"type":"Point"}
}
