{
  "type": "Feature",
  "properties": {
    "iso:country":"GB",
    "wof:name":"W14 8SU",
    "wof:placetype":"postalcode"
},
  "geometry": {"coordinates":[-0.21096417889861,51.49508264529285],"type":"Point"}
}