{
  "type": "Feature",
  "properties": {
    "iso:country":"GB",
    "wof:name":"LL34 6SH",
    "wof:placetype":"postalcode"
},
  "geometry": {"coordinates":[-3.90012979368893,53.27314032403692],"type":"Point"}
}