{
  "type": "Feature",
  "properties": {
    "date:inception_lower": "1993-08-01",
    "date:inception_upper": "1993-08-01",
    "iso:country": "GB",
    "wof:name": "NN3 7UZ",
    "wof:placetype": "postalcode"
  },
  "geometry": {"coordinates":[-0.837116,52.291477],"type":"Point"}
}
