{
  "type": "Feature",
  "properties": {
    "iso:country":"GB",
    "wof:name":"NN3 7UZ",
    "wof:placetype":"postalcode"
},
  "geometry": {"coordinates":[-0.83711766874158,52.29141720365547],"type":"Point"}
}