{
  "type": "Feature",
  "properties": {
    "iso:country":"GB",
    "wof:name":"AB54 7XX",
    "wof:placetype":"postalcode"
},
  "geometry": {"coordinates":[-2.74032109205446,57.47755033863896],"type":"Point"}
}