{
  "type": "Feature",
  "properties": {
    "date:inception_lower": "1992-08-01",
    "date:inception_upper": "1992-08-01",
    "iso:country": "GB",
    "wof:name": "LE67 3RA",
    "wof:placetype": "postalcode"
  },
  "geometry": {"coordinates":[-1.366801,52.718759],"type":"Point"}
}
