{
  "type": "Feature",
  "properties": {
    "iso:country":"GB",
    "wof:name":"LE67 3RA",
    "wof:placetype":"postalcode"
},
  "geometry": {"coordinates":[-1.36680081425153,52.71875860554944],"type":"Point"}
}