{
  "type": "Feature",
  "properties": {
    "iso:country":"GB",
    "wof:name":"WS1 3QP",
    "wof:placetype":"postalcode"
},
  "geometry": {"coordinates":[-1.98933140348237,52.57938089700906],"type":"Point"}
}