{
  "type": "Feature",
  "properties": {
    "iso:country":"GB",
    "wof:name":"OX25 4QX",
    "wof:placetype":"postalcode"
},
  "geometry": {"coordinates":[-1.30266090660792,51.9124205548876],"type":"Point"}
}