{
  "type": "Feature",
  "properties": {
    "iso:country":"GB",
    "wof:name":"BS22 9QS",
    "wof:placetype":"postalcode"
},
  "geometry": {"coordinates":[-2.95335117350199,51.35859494381128],"type":"Point"}
}