{
  "type": "Feature",
  "properties": {
    "iso:country":"GB",
    "wof:name":"LL13 9UY",
    "wof:placetype":"postalcode"
},
  "geometry": {"coordinates":[-2.91384199959878,53.04100165707273],"type":"Point"}
}