{
  "type": "Feature",
  "properties": {
    "iso:country":"GB",
    "wof:name":"PO21 3SA",
    "wof:placetype":"postalcode"
},
  "geometry": {"coordinates":[-0.70216590689766,50.78099487841217],"type":"Point"}
}