{
  "type": "Feature",
  "properties": {
    "iso:country":"GB",
    "wof:name":"TQ12 3HD",
    "wof:placetype":"postalcode"
},
  "geometry": {"coordinates":[-3.59544510523164,50.54724439017863],"type":"Point"}
}