{
  "type": "Feature",
  "properties": {
    "date:inception_lower":"1980-01-01",
    "date:inception_upper":"1980-01-31",
    "iso:country":"GB",
    "wof:name":"SK3 0DS",
    "wof:placetype":"postalcode"
},
  "geometry": {"coordinates":[-2.165211,53.405947],"type":"Point"}
}