{
  "type": "Feature",
  "properties": {
    "date:inception_lower": "1980-01-01",
    "date:inception_upper": "1980-01-01",
    "iso:country": "GB",
    "wof:name": "RH13 5SU",
    "wof:placetype": "postalcode"
  },
  "geometry": {"coordinates":[-0.311224,51.069877],"type":"Point"}
}
