{
  "type": "Feature",
  "properties": {
    "iso:country":"GB",
    "wof:name":"DG8 7AA",
    "wof:placetype":"postalcode"
},
  "geometry": {"coordinates":[-4.45085346195926,55.00070696239359],"type":"Point"}
}