{
  "type": "Feature",
  "properties": {
    "iso:country":"GB",
    "wof:name":"BS21 6HL",
    "wof:placetype":"postalcode"
},
  "geometry": {"coordinates":[-2.848631927714,51.43521072283703],"type":"Point"}
}