{
  "type": "Feature",
  "properties": {
    "iso:country": "GB",
    "wof:name": "HP13 7GW",
    "wof:placetype": "postalcode"
  },
  "geometry": {"coordinates":[-0.723652,51.640886],"type":"Point"}
}
