{
  "type": "Feature",
  "properties": {
    "iso:country":"GB",
    "wof:name":"HP13 7GW",
    "wof:placetype":"postalcode"
},
  "geometry": {"coordinates":[-0.72365191111538,51.64088625001613],"type":"Point"}
}