{
  "type": "Feature",
  "properties": {
    "iso:country": "GB",
    "wof:name": "MK6 2JX",
    "wof:placetype": "postalcode"
  },
  "geometry": {"coordinates":[-0.757592,52.034059],"type":"Point"}
}
