{
  "type": "Feature",
  "properties": {
    "iso:country":"GB",
    "wof:name":"SO18 5HJ",
    "wof:placetype":"postalcode"
},
  "geometry": {"coordinates":[-1.33925031209155,50.9177598906603],"type":"Point"}
}