{
  "type": "Feature",
  "properties": {
    "iso:country": "GB",
    "wof:name": "SO18 5HJ",
    "wof:placetype": "postalcode"
  },
  "geometry": {"coordinates":[-1.33925,50.91776],"type":"Point"}
}
