{
  "type": "Feature",
  "properties": {
    "iso:country": "GB",
    "wof:name": "PE30 3DB",
    "wof:placetype": "postalcode"
  },
  "geometry": {"coordinates":[0.428669,52.773352],"type":"Point"}
}
