{
  "type": "Feature",
  "properties": {
    "date:inception_lower":"1980-01-01",
    "date:inception_upper":"1980-01-31",
    "iso:country":"GB",
    "wof:name":"PE30 3DB",
    "wof:placetype":"postalcode"
},
  "geometry": {"coordinates":[0.428669,52.773352],"type":"Point"}
}