{
  "type": "Feature",
  "properties": {
    "iso:country":"GB",
    "wof:name":"L34 5NE",
    "wof:placetype":"postalcode"
},
  "geometry": {"coordinates":[-2.80094077804944,53.42323040387019],"type":"Point"}
}