{
  "type": "Feature",
  "properties": {
    "date:inception_lower": "2013-08-01",
    "date:inception_upper": "2013-08-01",
    "iso:country": "GB",
    "wof:name": "L34 5NE",
    "wof:placetype": "postalcode"
  },
  "geometry": {"coordinates":[-2.800941,53.42323],"type":"Point"}
}
