{
  "type": "Feature",
  "properties": {
    "iso:country": "GB",
    "wof:name": "NW2 2HH",
    "wof:placetype": "postalcode"
  },
  "geometry": {"coordinates":[-0.195938,51.56074],"type":"Point"}
}
