{
  "type": "Feature",
  "properties": {
    "iso:country":"GB",
    "wof:name":"NW2 2HH",
    "wof:placetype":"postalcode"
},
  "geometry": {"coordinates":[-0.19593821304426,51.56073994858826],"type":"Point"}
}