{
  "type": "Feature",
  "properties": {
    "iso:country": "GB",
    "wof:name": "GL52 3PE",
    "wof:placetype": "postalcode"
  },
  "geometry": {"coordinates":[-2.06007,51.930958],"type":"Point"}
}
