{
  "type": "Feature",
  "properties": {
    "iso:country":"GB",
    "wof:name":"LL58 8TP",
    "wof:placetype":"postalcode"
},
  "geometry": {"coordinates":[-4.14093601560556,53.28875627143761],"type":"Point"}
}