{
  "type": "Feature",
  "properties": {
    "iso:country":"GB",
    "wof:name":"EC1R 5DL",
    "wof:placetype":"postalcode"
},
  "geometry": {"coordinates":[-0.1089843367434,51.52217777594833],"type":"Point"}
}