{
  "type": "Feature",
  "properties": {
    "iso:country":"GB",
    "wof:name":"TN21 9QR",
    "wof:placetype":"postalcode"
},
  "geometry": {"coordinates":[0.31723674136927,50.93893101607134],"type":"Point"}
}