{
  "type": "Feature",
  "properties": {
    "iso:country": "GB",
    "wof:name": "TN21 9QR",
    "wof:placetype": "postalcode"
  },
  "geometry": {"coordinates":[0.317237,50.938931],"type":"Point"}
}
