{
  "type": "Feature",
  "properties": {
    "date:inception_lower": "1980-01-01",
    "date:inception_upper": "1980-01-01",
    "iso:country": "GB",
    "wof:name": "DL6 2DP",
    "wof:placetype": "postalcode"
  },
  "geometry": {"coordinates":[-1.347692,54.374069],"type":"Point"}
}
