{
  "type": "Feature",
  "properties": {
    "iso:country":"GB",
    "wof:name":"LA9 7NP",
    "wof:placetype":"postalcode"
},
  "geometry": {"coordinates":[-2.73173348322428,54.31601919677224],"type":"Point"}
}