{
  "type": "Feature",
  "properties": {
    "iso:country":"GB",
    "wof:name":"TQ9 5JZ",
    "wof:placetype":"postalcode"
},
  "geometry": {"coordinates":[-3.69346386881645,50.43540717411199],"type":"Point"}
}