{
  "type": "Feature",
  "properties": {
    "date:inception_lower": "2003-08-01",
    "date:inception_upper": "2003-08-01",
    "iso:country": "GB",
    "wof:name": "TQ9 5JZ",
    "wof:placetype": "postalcode"
  },
  "geometry": {"coordinates":[-3.693464,50.435407],"type":"Point"}
}
