{
  "type": "Feature",
  "properties": {
    "iso:country": "GB",
    "wof:name": "RG25 3EA",
    "wof:placetype": "postalcode"
  },
  "geometry": {"coordinates":[-1.259044,51.250215],"type":"Point"}
}
