{
  "type": "Feature",
  "properties": {
    "iso:country":"GB",
    "wof:name":"RG25 3EA",
    "wof:placetype":"postalcode"
},
  "geometry": {"coordinates":[-1.25780454828902,51.250820857877],"type":"Point"}
}