{
  "type": "Feature",
  "properties": {
    "iso:country":"GB",
    "wof:name":"SW6 3UJ",
    "wof:placetype":"postalcode"
},
  "geometry": {"coordinates":[-0.20946726316591,51.46710219883124],"type":"Point"}
}