{
  "type": "Feature",
  "properties": {
    "iso:country": "GB",
    "wof:name": "S63 9AN",
    "wof:placetype": "postalcode"
  },
  "geometry": {"coordinates":[-1.311849,53.532961],"type":"Point"}
}
