{
  "type": "Feature",
  "properties": {
    "iso:country":"GB",
    "wof:name":"IP12 1SA",
    "wof:placetype":"postalcode"
},
  "geometry": {"coordinates":[1.31946206553368,52.09846508903981],"type":"Point"}
}