{
  "type": "Feature",
  "properties": {
    "iso:country": "GB",
    "wof:name": "IP12 1SA",
    "wof:placetype": "postalcode"
  },
  "geometry": {"coordinates":[1.319462,52.098465],"type":"Point"}
}
