{
  "type": "Feature",
  "properties": {
    "iso:country":"GB",
    "wof:name":"IG2 7QB",
    "wof:placetype":"postalcode"
},
  "geometry": {"coordinates":[0.09619131825925,51.58127981139319],"type":"Point"}
}