{
  "type": "Feature",
  "properties": {
    "iso:country":"GB",
    "wof:name":"L25 6JG",
    "wof:placetype":"postalcode"
},
  "geometry": {"coordinates":[-2.88389496668207,53.38440650644763],"type":"Point"}
}