{
  "type": "Feature",
  "properties": {
    "iso:country": "GB",
    "wof:name": "NE66 3TB",
    "wof:placetype": "postalcode"
  },
  "geometry": {"coordinates":[-1.606323,55.472636],"type":"Point"}
}
