{
  "type": "Feature",
  "properties": {
    "iso:country":"GB",
    "wof:name":"BS8 1RU",
    "wof:placetype":"postalcode"
},
  "geometry": {"coordinates":[-2.61108192432894,51.45832410802311],"type":"Point"}
}