{
  "type": "Feature",
  "properties": {
    "date:inception_lower":"1980-01-01",
    "date:inception_upper":"1980-01-31",
    "iso:country":"GB",
    "wof:name":"FK1 4DZ",
    "wof:placetype":"postalcode"
},
  "geometry": {"coordinates":[-3.811873,56.002526],"type":"Point"}
}