{
  "type": "Feature",
  "properties": {
    "iso:country": "GB",
    "wof:name": "FK1 4DZ",
    "wof:placetype": "postalcode"
  },
  "geometry": {"coordinates":[-3.811873,56.002526],"type":"Point"}
}
