{
  "type": "Feature",
  "properties": {
    "iso:country": "GB",
    "wof:name": "ME3 8UH",
    "wof:placetype": "postalcode"
  },
  "geometry": {"coordinates":[0.502191,51.436129],"type":"Point"}
}
