{
  "type": "Feature",
  "properties": {
    "iso:country": "GB",
    "wof:name": "NN14 4LD",
    "wof:placetype": "postalcode"
  },
  "geometry": {"coordinates":[-0.536174,52.395782],"type":"Point"}
}
