{
  "type": "Feature",
  "properties": {
    "iso:country":"GB",
    "wof:name":"PL7 1JE",
    "wof:placetype":"postalcode"
},
  "geometry": {"coordinates":[-4.03777189215997,50.38399584855711],"type":"Point"}
}