{
  "type": "Feature",
  "properties": {
    "iso:country":"GB",
    "wof:name":"ST6 5SP",
    "wof:placetype":"postalcode"
},
  "geometry": {"coordinates":[-2.22071378419704,53.07692971755786],"type":"Point"}
}