{
  "type": "Feature",
  "properties": {
    "iso:country":"GB",
    "wof:name":"WF10 3JW",
    "wof:placetype":"postalcode"
},
  "geometry": {"coordinates":[-1.31843420952081,53.72388416551407],"type":"Point"}
}