{
  "type": "Feature",
  "properties": {
    "iso:country":"GB",
    "wof:name":"CT17 0UY",
    "wof:placetype":"postalcode"
},
  "geometry": {"coordinates":[1.28336223082884,51.1419597368016],"type":"Point"}
}