{
  "type": "Feature",
  "properties": {
    "iso:country": "GB",
    "wof:name": "CT17 0UY",
    "wof:placetype": "postalcode"
  },
  "geometry": {"coordinates":[1.283339,51.141995],"type":"Point"}
}
