{
  "type": "Feature",
  "properties": {
    "iso:country": "GB",
    "wof:name": "LE19 4LQ",
    "wof:placetype": "postalcode"
  },
  "geometry": {"coordinates":[-1.22722,52.611123],"type":"Point"}
}
