{
  "type": "Feature",
  "properties": {
    "iso:country": "GB",
    "wof:name": "S11 9DZ",
    "wof:placetype": "postalcode"
  },
  "geometry": {"coordinates":[-1.497252,53.363153],"type":"Point"}
}
