{
  "type": "Feature",
  "properties": {
    "iso:country": "GB",
    "wof:name": "ST17 9DQ",
    "wof:placetype": "postalcode"
  },
  "geometry": {"coordinates":[-2.11423,52.79141],"type":"Point"}
}
