{
  "type": "Feature",
  "properties": {
    "iso:country":"GB",
    "wof:name":"ST17 9DQ",
    "wof:placetype":"postalcode"
},
  "geometry": {"coordinates":[-2.11423021544671,52.79140980182171],"type":"Point"}
}