{
  "type": "Feature",
  "properties": {
    "iso:country":"GB",
    "wof:name":"DD5 2BS",
    "wof:placetype":"postalcode"
},
  "geometry": {"coordinates":[-2.87536804563222,56.46540921756992],"type":"Point"}
}