{
  "type": "Feature",
  "properties": {
    "date:inception_lower":"1999-06-01",
    "date:inception_upper":"1999-06-30",
    "iso:country":"GB",
    "wof:name":"NP26 5AY",
    "wof:placetype":"postalcode"
},
  "geometry": {"coordinates":[-2.768254,51.611111],"type":"Point"}
}