{
  "type": "Feature",
  "properties": {
    "date:inception_lower":"2012-07-01",
    "date:inception_upper":"2012-07-31",
    "iso:country":"GB",
    "wof:name":"HP3 8LQ",
    "wof:placetype":"postalcode"
},
  "geometry": {"coordinates":[-0.424948,51.746764],"type":"Point"}
}