{
  "type": "Feature",
  "properties": {
    "iso:country":"GB",
    "wof:name":"HP3 8LQ",
    "wof:placetype":"postalcode"
},
  "geometry": {"coordinates":[-0.42494780191739,51.74676378038122],"type":"Point"}
}