{
  "type": "Feature",
  "properties": {
    "iso:country":"GB",
    "wof:name":"B61 0LD",
    "wof:placetype":"postalcode"
},
  "geometry": {"coordinates":[-2.05471851116305,52.36449928769779],"type":"Point"}
}