{
  "type": "Feature",
  "properties": {
    "date:inception_lower": "2008-05-01",
    "date:inception_upper": "2008-05-01",
    "iso:country": "GB",
    "wof:name": "G67 1BE",
    "wof:placetype": "postalcode"
  },
  "geometry": {"coordinates":[-3.996258,55.944949],"type":"Point"}
}
