{
  "type": "Feature",
  "properties": {
    "iso:country":"GB",
    "wof:name":"GL14 1NA",
    "wof:placetype":"postalcode"
},
  "geometry": {"coordinates":[-2.40807775760394,51.84406064218989],"type":"Point"}
}