{
  "type": "Feature",
  "properties": {
    "date:inception_lower":"1980-01-01",
    "date:inception_upper":"1980-01-31",
    "iso:country":"GB",
    "wof:name":"GL14 1NA",
    "wof:placetype":"postalcode"
},
  "geometry": {"coordinates":[-2.408078,51.844061],"type":"Point"}
}