{
  "type": "Feature",
  "properties": {
    "iso:country": "GB",
    "wof:name": "EX32 9DH",
    "wof:placetype": "postalcode"
  },
  "geometry": {"coordinates":[-4.038951,51.06753],"type":"Point"}
}
