{
  "type": "Feature",
  "properties": {
    "iso:country":"GB",
    "wof:name":"EX32 9DH",
    "wof:placetype":"postalcode"
},
  "geometry": {"coordinates":[-4.03895100742874,51.0675301243765],"type":"Point"}
}