{
  "type": "Feature",
  "properties": {
    "iso:country": "GB",
    "wof:name": "SL4 4HA",
    "wof:placetype": "postalcode"
  },
  "geometry": {"coordinates":[-0.636954,51.471088],"type":"Point"}
}
