{
  "type": "Feature",
  "properties": {
    "iso:country":"GB",
    "wof:name":"SL4 4HA",
    "wof:placetype":"postalcode"
},
  "geometry": {"coordinates":[-0.63695423890013,51.47108809297534],"type":"Point"}
}