{
  "type": "Feature",
  "properties": {
    "date:inception_lower":"1980-01-01",
    "date:inception_upper":"1980-01-31",
    "iso:country":"GB",
    "wof:name":"G31 2RF",
    "wof:placetype":"postalcode"
},
  "geometry": {"coordinates":[-4.217357,55.860586],"type":"Point"}
}