{
  "type": "Feature",
  "properties": {
    "iso:country": "GB",
    "wof:name": "SG12 0AZ",
    "wof:placetype": "postalcode"
  },
  "geometry": {"coordinates":[-0.047978,51.81389],"type":"Point"}
}
