{
  "type": "Feature",
  "properties": {
    "iso:country": "GB",
    "wof:name": "KA30 8DW",
    "wof:placetype": "postalcode"
  },
  "geometry": {"coordinates":[-4.868507,55.79601],"type":"Point"}
}
