{
  "type": "Feature",
  "properties": {
    "iso:country":"GB",
    "wof:name":"LE13 0DE",
    "wof:placetype":"postalcode"
},
  "geometry": {"coordinates":[-0.89425267868932,52.76354401076252],"type":"Point"}
}