{
  "type": "Feature",
  "properties": {
    "date:inception_lower":"1982-03-01",
    "date:inception_upper":"1982-03-31",
    "iso:country":"GB",
    "wof:name":"LE13 0DE",
    "wof:placetype":"postalcode"
},
  "geometry": {"coordinates":[-0.894253,52.763544],"type":"Point"}
}