{
  "type": "Feature",
  "properties": {
    "iso:country": "GB",
    "wof:name": "M24 6XJ",
    "wof:placetype": "postalcode"
  },
  "geometry": {"coordinates":[-2.203689,53.572614],"type":"Point"}
}
