{
  "type": "Feature",
  "properties": {
    "iso:country":"GB",
    "wof:name":"BL1 5XP",
    "wof:placetype":"postalcode"
},
  "geometry": {"coordinates":[-2.46913089712781,53.57912992015081],"type":"Point"}
}