{
  "type": "Feature",
  "properties": {
    "iso:country":"GB",
    "wof:name":"RG20 5PN",
    "wof:placetype":"postalcode"
},
  "geometry": {"coordinates":[-1.24704895320903,51.32331731761899],"type":"Point"}
}