{
  "type": "Feature",
  "properties": {
    "iso:country": "GB",
    "wof:name": "NG6 8TH",
    "wof:placetype": "postalcode"
  },
  "geometry": {"coordinates":[-1.177557,53.026525],"type":"Point"}
}
