{
  "type": "Feature",
  "properties": {
    "iso:country":"GB",
    "wof:name":"NG6 8TH",
    "wof:placetype":"postalcode"
},
  "geometry": {"coordinates":[-1.17755671567821,53.02652542161434],"type":"Point"}
}