{
  "type": "Feature",
  "properties": {
    "date:inception_lower":"1980-01-01",
    "date:inception_upper":"1980-01-31",
    "iso:country":"GB",
    "wof:name":"NG6 8TH",
    "wof:placetype":"postalcode"
},
  "geometry": {"coordinates":[-1.177557,53.026525],"type":"Point"}
}