{
  "type": "Feature",
  "properties": {
    "iso:country": "GB",
    "wof:name": "RG6 4JJ",
    "wof:placetype": "postalcode"
  },
  "geometry": {"coordinates":[-0.918229,51.422361],"type":"Point"}
}
