{
  "type": "Feature",
  "properties": {
    "iso:country":"GB",
    "wof:name":"CB6 1NB",
    "wof:placetype":"postalcode"
},
  "geometry": {"coordinates":[0.30920577000548,52.45717254028992],"type":"Point"}
}