{
  "type": "Feature",
  "properties": {
    "date:inception_lower":"2003-03-01",
    "date:inception_upper":"2003-03-31",
    "iso:country":"GB",
    "wof:name":"WS7 1YX",
    "wof:placetype":"postalcode"
},
  "geometry": {"coordinates":[-1.938162,52.688662],"type":"Point"}
}