{
  "type": "Feature",
  "properties": {
    "iso:country": "GB",
    "wof:name": "WS7 1YX",
    "wof:placetype": "postalcode"
  },
  "geometry": {"coordinates":[-1.938162,52.688662],"type":"Point"}
}
