{
  "type": "Feature",
  "properties": {
    "iso:country":"GB",
    "wof:name":"AB42 0QJ",
    "wof:placetype":"postalcode"
},
  "geometry": {"coordinates":[-1.88299401533436,57.38801175235101],"type":"Point"}
}