{
  "type": "Feature",
  "properties": {
    "iso:country":"GB",
    "wof:name":"CV6 6HY",
    "wof:placetype":"postalcode"
},
  "geometry": {"coordinates":[-1.50131151207321,52.44191823431331],"type":"Point"}
}