{
  "type": "Feature",
  "properties": {
    "date:inception_lower": "2016-09-01",
    "date:inception_upper": "2016-09-01",
    "iso:country": "GB",
    "wof:name": "SE10 0TZ",
    "wof:placetype": "postalcode"
  },
  "geometry": {"coordinates":[0.002445,51.48809],"type":"Point"}
}
