{
  "type": "Feature",
  "properties": {
    "iso:country":"GB",
    "wof:name":"W1W 8LF",
    "wof:placetype":"postalcode"
},
  "geometry": {"coordinates":[-0.141580211017,51.51677269181601],"type":"Point"}
}