{
  "type": "Feature",
  "properties": {
    "iso:country": "GB",
    "wof:name": "YO43 4RJ",
    "wof:placetype": "postalcode"
  },
  "geometry": {"coordinates":[-0.591562,53.853198],"type":"Point"}
}
