{
  "type": "Feature",
  "properties": {
    "date:inception_lower": "1998-06-01",
    "date:inception_upper": "1998-06-01",
    "iso:country": "GB",
    "wof:name": "YO43 4RJ",
    "wof:placetype": "postalcode"
  },
  "geometry": {"coordinates":[-0.591414,53.852612],"type":"Point"}
}
