{
  "type": "Feature",
  "properties": {
    "iso:country":"GB",
    "wof:name":"YO43 4RJ",
    "wof:placetype":"postalcode"
},
  "geometry": {"coordinates":[-0.59155491173725,53.85317801173203],"type":"Point"}
}