{
  "type": "Feature",
  "properties": {
    "date:inception_lower": "1998-06-01",
    "date:inception_upper": "1998-06-01",
    "iso:country": "GB",
    "wof:name": "SN15 3EW",
    "wof:placetype": "postalcode"
  },
  "geometry": {"coordinates":[-2.114184,51.456436],"type":"Point"}
}
