{
  "type": "Feature",
  "properties": {
    "iso:country":"GB",
    "wof:name":"ME1 3YA",
    "wof:placetype":"postalcode"
},
  "geometry": {"coordinates":[0.46201474361395,51.32418431223435],"type":"Point"}
}