{
  "type": "Feature",
  "properties": {
    "date:inception_lower": "1980-01-01",
    "date:inception_upper": "1980-01-01",
    "iso:country": "GB",
    "wof:name": "PO15 5BW",
    "wof:placetype": "postalcode"
  },
  "geometry": {"coordinates":[-1.214945,50.855221],"type":"Point"}
}
