{
  "type": "Feature",
  "properties": {
    "date:inception_lower": "2023-03-01",
    "date:inception_upper": "2023-03-01",
    "iso:country": "GB",
    "wof:name": "G66 3FL",
    "wof:placetype": "postalcode"
  },
  "geometry": {"coordinates":[-4.155191,55.93344],"type":"Point"}
}
