{
  "type": "Feature",
  "properties": {
    "iso:country":"GB",
    "wof:name":"TN33 0AQ",
    "wof:placetype":"postalcode"
},
  "geometry": {"coordinates":[0.48658030446028,50.91533572123899],"type":"Point"}
}