{
  "type": "Feature",
  "properties": {
    "iso:country":"GB",
    "wof:name":"SA10 6SG",
    "wof:placetype":"postalcode"
},
  "geometry": {"coordinates":[-3.86285656774635,51.6602037179061],"type":"Point"}
}