{
  "type": "Feature",
  "properties": {
    "iso:country": "GB",
    "wof:name": "SA10 6SG",
    "wof:placetype": "postalcode"
  },
  "geometry": {"coordinates":[-3.862857,51.660204],"type":"Point"}
}
