{
  "type": "Feature",
  "properties": {
    "iso:country":"GB",
    "wof:name":"AB39 3QQ",
    "wof:placetype":"postalcode"
},
  "geometry": {"coordinates":[-2.27613635672343,57.04499110845234],"type":"Point"}
}