{
  "type": "Feature",
  "properties": {
    "iso:country":"GB",
    "wof:name":"DG14 0RW",
    "wof:placetype":"postalcode"
},
  "geometry": {"coordinates":[-2.91835014832134,55.08707493320466],"type":"Point"}
}