{
  "type": "Feature",
  "properties": {
    "iso:country":"GB",
    "wof:name":"IG1 1HG",
    "wof:placetype":"postalcode"
},
  "geometry": {"coordinates":[0.07610544866838,51.55322897743327],"type":"Point"}
}