{
  "type": "Feature",
  "properties": {
    "iso:country":"GB",
    "wof:name":"DE72 3NW",
    "wof:placetype":"postalcode"
},
  "geometry": {"coordinates":[-1.34507290537342,52.8961765517065],"type":"Point"}
}