{
  "type": "Feature",
  "properties": {
    "iso:country":"GB",
    "wof:name":"LL18 5US",
    "wof:placetype":"postalcode"
},
  "geometry": {"coordinates":[-3.49796148868585,53.26822879863696],"type":"Point"}
}