{
  "type": "Feature",
  "properties": {
    "date:inception_lower":"1980-01-01",
    "date:inception_upper":"1980-01-31",
    "iso:country":"GB",
    "wof:name":"LL18 5US",
    "wof:placetype":"postalcode"
},
  "geometry": {"coordinates":[-3.497961,53.268229],"type":"Point"}
}