{
  "type": "Feature",
  "properties": {
    "iso:country":"GB",
    "wof:name":"L12 4YB",
    "wof:placetype":"postalcode"
},
  "geometry": {"coordinates":[-2.89099756978671,53.43507780822139],"type":"Point"}
}