{
  "type": "Feature",
  "properties": {
    "iso:country": "GB",
    "wof:name": "L12 4YB",
    "wof:placetype": "postalcode"
  },
  "geometry": {"coordinates":[-2.890998,53.435078],"type":"Point"}
}
