{
  "type": "Feature",
  "properties": {
    "date:inception_lower": "1980-01-01",
    "date:inception_upper": "1980-01-01",
    "iso:country": "GB",
    "wof:name": "L12 4YB",
    "wof:placetype": "postalcode"
  },
  "geometry": {"coordinates":[-2.890998,53.435078],"type":"Point"}
}
