{
  "type": "Feature",
  "properties": {
    "iso:country":"GB",
    "wof:name":"SA14 7UH",
    "wof:placetype":"postalcode"
},
  "geometry": {"coordinates":[-4.06092411486666,51.83860371223483],"type":"Point"}
}