{
  "type": "Feature",
  "properties": {
    "date:inception_lower":"1980-01-01",
    "date:inception_upper":"1980-01-31",
    "iso:country":"GB",
    "wof:name":"SA14 7UH",
    "wof:placetype":"postalcode"
},
  "geometry": {"coordinates":[-4.060944,51.838612],"type":"Point"}
}