{
  "type": "Feature",
  "properties": {
    "iso:country": "GB",
    "wof:name": "DG16 5JL",
    "wof:placetype": "postalcode"
  },
  "geometry": {"coordinates":[-3.109551,54.998231],"type":"Point"}
}
