{
  "type": "Feature",
  "properties": {
    "iso:country":"GB",
    "wof:name":"DG16 5JL",
    "wof:placetype":"postalcode"
},
  "geometry": {"coordinates":[-3.1095509626373,54.99823123368212],"type":"Point"}
}