{
  "type": "Feature",
  "properties": {
    "iso:country":"GB",
    "wof:name":"SE16 3AA",
    "wof:placetype":"postalcode"
},
  "geometry": {"coordinates":[-0.05817291561671,51.48689687494685],"type":"Point"}
}