{
  "type": "Feature",
  "properties": {
    "iso:country":"GB",
    "wof:name":"IV2 3TE",
    "wof:placetype":"postalcode"
},
  "geometry": {"coordinates":[-4.19829981640618,57.46339756827859],"type":"Point"}
}