{
  "type": "Feature",
  "properties": {
    "date:inception_lower":"1980-01-01",
    "date:inception_upper":"1980-01-31",
    "iso:country":"GB",
    "wof:name":"CO11 2XN",
    "wof:placetype":"postalcode"
},
  "geometry": {"coordinates":[1.119226,51.934655],"type":"Point"}
}