{
  "type": "Feature",
  "properties": {
    "iso:country":"GB",
    "wof:name":"CO11 2XN",
    "wof:placetype":"postalcode"
},
  "geometry": {"coordinates":[1.1192259179988,51.93465470525788],"type":"Point"}
}