{
  "type": "Feature",
  "properties": {
    "iso:country":"GB",
    "wof:name":"SM1 4NS",
    "wof:placetype":"postalcode"
},
  "geometry": {"coordinates":[-0.1824366336912,51.36502500599098],"type":"Point"}
}