{
  "type": "Feature",
  "properties": {
    "iso:country": "GB",
    "wof:name": "E14 2EH",
    "wof:placetype": "postalcode"
  },
  "geometry": {"coordinates":[-0.003729,51.507268],"type":"Point"}
}
