{
  "type": "Feature",
  "properties": {
    "iso:country":"GB",
    "wof:name":"E14 2EH",
    "wof:placetype":"postalcode"
},
  "geometry": {"coordinates":[-0.00372919162421,51.50726832338882],"type":"Point"}
}