{
  "type": "Feature",
  "properties": {
    "iso:country":"GB",
    "wof:name":"TW6 1NP",
    "wof:placetype":"postalcode"
},
  "geometry": {"coordinates":[-0.4551392480778,51.47352779190609],"type":"Point"}
}