{
  "type": "Feature",
  "properties": {
    "date:inception_lower": "1991-09-01",
    "date:inception_upper": "1991-09-01",
    "iso:country": "GB",
    "wof:name": "TW6 1NP",
    "wof:placetype": "postalcode"
  },
  "geometry": {"coordinates":[-0.458327,51.471907],"type":"Point"}
}
