{
  "type": "Feature",
  "properties": {
    "iso:country": "GB",
    "wof:name": "BN21 3BE",
    "wof:placetype": "postalcode"
  },
  "geometry": {"coordinates":[0.287577,50.766842],"type":"Point"}
}
