{
  "type": "Feature",
  "properties": {
    "iso:country":"GB",
    "wof:name":"SG5 1XJ",
    "wof:placetype":"postalcode"
},
  "geometry": {"coordinates":[-0.28062051055678,51.95907132205205],"type":"Point"}
}