{
  "type": "Feature",
  "properties": {
    "iso:country":"GB",
    "wof:name":"G15 7PA",
    "wof:placetype":"postalcode"
},
  "geometry": {"coordinates":[-4.35073969054942,55.9125476427028],"type":"Point"}
}