{
  "type": "Feature",
  "properties": {
    "date:inception_lower": "2018-10-01",
    "date:inception_upper": "2018-10-01",
    "iso:country": "GB",
    "wof:name": "B90 4NP",
    "wof:placetype": "postalcode"
  },
  "geometry": {"coordinates":[-1.808726,52.39867],"type":"Point"}
}
