{
  "type": "Feature",
  "properties": {
    "iso:country":"GB",
    "wof:name":"B90 4NP",
    "wof:placetype":"postalcode"
},
  "geometry": {"coordinates":[-1.80348921444793,52.39795422563071],"type":"Point"}
}