{
  "type": "Feature",
  "properties": {
    "iso:country": "GB",
    "wof:name": "B90 4NP",
    "wof:placetype": "postalcode"
  },
  "geometry": {"coordinates":[-1.808726,52.39867],"type":"Point"}
}
