{
  "type": "Feature",
  "properties": {
    "iso:country":"GB",
    "wof:name":"KY8 4GA",
    "wof:placetype":"postalcode"
},
  "geometry": {"coordinates":[-3.00136191085624,56.1962447791378],"type":"Point"}
}