{
  "type": "Feature",
  "properties": {
    "iso:country":"GB",
    "wof:name":"W8 6TG",
    "wof:placetype":"postalcode"
},
  "geometry": {"coordinates":[-0.19292952503079,51.49904159053958],"type":"Point"}
}