{
  "type": "Feature",
  "properties": {
    "date:inception_lower": "1980-01-01",
    "date:inception_upper": "1980-01-01",
    "iso:country": "GB",
    "wof:name": "CW3 9JW",
    "wof:placetype": "postalcode"
  },
  "geometry": {"coordinates":[-2.335464,53.00294],"type":"Point"}
}
