{
  "type": "Feature",
  "properties": {
    "iso:country":"GB",
    "wof:name":"CW3 9JW",
    "wof:placetype":"postalcode"
},
  "geometry": {"coordinates":[-2.3354339530129,53.00286052462537],"type":"Point"}
}