{
  "type": "Feature",
  "properties": {
    "date:inception_lower": "1996-06-01",
    "date:inception_upper": "1996-06-01",
    "iso:country": "GB",
    "wof:name": "AB16 7AL",
    "wof:placetype": "postalcode"
  },
  "geometry": {"coordinates":[-2.148044,57.164189],"type":"Point"}
}
