{
  "type": "Feature",
  "properties": {
    "iso:country":"GB",
    "wof:name":"SA17 5RA",
    "wof:placetype":"postalcode"
},
  "geometry": {"coordinates":[-4.3285371894078,51.78011882192927],"type":"Point"}
}