{
  "type": "Feature",
  "properties": {
    "iso:country":"GB",
    "wof:name":"ME12 3SD",
    "wof:placetype":"postalcode"
},
  "geometry": {"coordinates":[0.81124989891694,51.41975871391093],"type":"Point"}
}