{
  "type": "Feature",
  "properties": {
    "date:inception_lower": "1980-01-01",
    "date:inception_upper": "1980-01-01",
    "iso:country": "GB",
    "wof:name": "ME12 3SD",
    "wof:placetype": "postalcode"
  },
  "geometry": {"coordinates":[0.81125,51.419759],"type":"Point"}
}
