{
  "type": "Feature",
  "properties": {
    "iso:country":"GB",
    "wof:name":"N16 8BA",
    "wof:placetype":"postalcode"
},
  "geometry": {"coordinates":[-0.07701207914078,51.54886042717072],"type":"Point"}
}