{
  "type": "Feature",
  "properties": {
    "iso:country": "GB",
    "wof:name": "N16 8BA",
    "wof:placetype": "postalcode"
  },
  "geometry": {"coordinates":[-0.077012,51.54886],"type":"Point"}
}
