{
  "type": "Feature",
  "properties": {
    "iso:country":"GB",
    "wof:name":"BS6 7LJ",
    "wof:placetype":"postalcode"
},
  "geometry": {"coordinates":[-2.6082035632693,51.47674494006952],"type":"Point"}
}