{
  "type": "Feature",
  "properties": {
    "iso:country": "GB",
    "wof:name": "G66 1DU",
    "wof:placetype": "postalcode"
  },
  "geometry": {"coordinates":[-4.162645,55.936244],"type":"Point"}
}
