{
  "type": "Feature",
  "properties": {
    "iso:country":"GB",
    "wof:name":"SN12 7DR",
    "wof:placetype":"postalcode"
},
  "geometry": {"coordinates":[-2.12763667273262,51.38276312507598],"type":"Point"}
}