{
  "type": "Feature",
  "properties": {
    "iso:country": "GB",
    "wof:name": "SN12 7DR",
    "wof:placetype": "postalcode"
  },
  "geometry": {"coordinates":[-2.127637,51.382763],"type":"Point"}
}
