{
  "type": "Feature",
  "properties": {
    "iso:country": "GB",
    "wof:name": "DN20 0PZ",
    "wof:placetype": "postalcode"
  },
  "geometry": {"coordinates":[-0.501446,53.635812],"type":"Point"}
}
