{
  "type": "Feature",
  "properties": {
    "date:inception_lower":"1980-01-01",
    "date:inception_upper":"1980-01-31",
    "iso:country":"GB",
    "wof:name":"DN20 0PZ",
    "wof:placetype":"postalcode"
},
  "geometry": {"coordinates":[-0.501446,53.635812],"type":"Point"}
}