{
  "type": "Feature",
  "properties": {
    "iso:country":"GB",
    "wof:name":"DN20 0PZ",
    "wof:placetype":"postalcode"
},
  "geometry": {"coordinates":[-0.50144586240808,53.63581227553685],"type":"Point"}
}