{
  "type": "Feature",
  "properties": {
    "iso:country":"GB",
    "wof:name":"TA1 3JS",
    "wof:placetype":"postalcode"
},
  "geometry": {"coordinates":[-3.10800942695521,51.00922248491324],"type":"Point"}
}