{
  "type": "Feature",
  "properties": {
    "iso:country":"GB",
    "wof:name":"CR8 3BG",
    "wof:placetype":"postalcode"
},
  "geometry": {"coordinates":[-0.12761613957202,51.33513304700055],"type":"Point"}
}