{
  "type": "Feature",
  "properties": {
    "iso:country":"GB",
    "wof:name":"SO14 2NZ",
    "wof:placetype":"postalcode"
},
  "geometry": {"coordinates":[-1.40456909563292,50.9015109901326],"type":"Point"}
}