{
  "type": "Feature",
  "properties": {
    "iso:country": "GB",
    "wof:name": "TS11 6DF",
    "wof:placetype": "postalcode"
  },
  "geometry": {"coordinates":[-1.024354,54.590111],"type":"Point"}
}
