{
  "type": "Feature",
  "properties": {
    "iso:country":"GB",
    "wof:name":"BL2 2LQ",
    "wof:placetype":"postalcode"
},
  "geometry": {"coordinates":[-2.41173347333022,53.58953412289845],"type":"Point"}
}