{
  "type": "Feature",
  "properties": {
    "iso:country": "GB",
    "wof:name": "LS17 8DB",
    "wof:placetype": "postalcode"
  },
  "geometry": {"coordinates":[-1.531952,53.84853],"type":"Point"}
}
