{
  "type": "Feature",
  "properties": {
    "iso:country":"GB",
    "wof:name":"LS17 8DB",
    "wof:placetype":"postalcode"
},
  "geometry": {"coordinates":[-1.53195194396776,53.84852969790835],"type":"Point"}
}