{
  "type": "Feature",
  "properties": {
    "iso:country":"GB",
    "wof:name":"E3 2HG",
    "wof:placetype":"postalcode"
},
  "geometry": {"coordinates":[-0.02873721928377,51.53082938047874],"type":"Point"}
}