{
  "type": "Feature",
  "properties": {
    "iso:country":"GB",
    "wof:name":"FK12 5NL",
    "wof:placetype":"postalcode"
},
  "geometry": {"coordinates":[-3.81591494136758,56.1521327846505],"type":"Point"}
}