{
  "type": "Feature",
  "properties": {
    "iso:country": "GB",
    "wof:name": "GU35 9FJ",
    "wof:placetype": "postalcode"
  },
  "geometry": {"coordinates":[-0.869912,51.110978],"type":"Point"}
}
