{
  "type": "Feature",
  "properties": {
    "iso:country":"GB",
    "wof:name":"MK41 6AP",
    "wof:placetype":"postalcode"
},
  "geometry": {"coordinates":[-0.50361070658947,52.16494303343929],"type":"Point"}
}