{
  "type": "Feature",
  "properties": {
    "date:inception_lower":"2002-06-01",
    "date:inception_upper":"2002-06-30",
    "iso:country":"GB",
    "wof:name":"CM77 8DH",
    "wof:placetype":"postalcode"
},
  "geometry": {"coordinates":[0.582405,51.866024],"type":"Point"}
}