{
  "type": "Feature",
  "properties": {
    "iso:country":"GB",
    "wof:name":"CM77 8DH",
    "wof:placetype":"postalcode"
},
  "geometry": {"coordinates":[0.58240458846793,51.86602388490935],"type":"Point"}
}