{
  "type": "Feature",
  "properties": {
    "iso:country": "GB",
    "wof:name": "SA15 4SA",
    "wof:placetype": "postalcode"
  },
  "geometry": {"coordinates":[-4.180799,51.69896],"type":"Point"}
}
