{
  "type": "Feature",
  "properties": {
    "iso:country":"GB",
    "wof:name":"SA15 4SA",
    "wof:placetype":"postalcode"
},
  "geometry": {"coordinates":[-4.18085171211593,51.69900671255962],"type":"Point"}
}