{
  "type": "Feature",
  "properties": {
    "date:inception_lower": "1980-01-01",
    "date:inception_upper": "1980-01-01",
    "iso:country": "GB",
    "wof:name": "SA15 4SA",
    "wof:placetype": "postalcode"
  },
  "geometry": {"coordinates":[-4.180799,51.69896],"type":"Point"}
}
