{
  "type": "Feature",
  "properties": {
    "iso:country":"GB",
    "wof:name":"SK5 6AW",
    "wof:placetype":"postalcode"
},
  "geometry": {"coordinates":[-2.15969386521452,53.43894271444326],"type":"Point"}
}