{
  "type": "Feature",
  "properties": {
    "iso:country": "GB",
    "wof:name": "SK5 6AW",
    "wof:placetype": "postalcode"
  },
  "geometry": {"coordinates":[-2.159694,53.438943],"type":"Point"}
}
