{
  "type": "Feature",
  "properties": {
    "iso:country":"GB",
    "wof:name":"LL15 2HB",
    "wof:placetype":"postalcode"
},
  "geometry": {"coordinates":[-3.26641048918495,53.07716260628511],"type":"Point"}
}