{
  "type": "Feature",
  "properties": {
    "iso:country": "GB",
    "wof:name": "LL15 2HB",
    "wof:placetype": "postalcode"
  },
  "geometry": {"coordinates":[-3.26641,53.077179],"type":"Point"}
}
