{
  "type": "Feature",
  "properties": {
    "iso:country":"GB",
    "wof:name":"RH13 0PA",
    "wof:placetype":"postalcode"
},
  "geometry": {"coordinates":[-0.39802099765354,51.05208805653218],"type":"Point"}
}