{
  "type": "Feature",
  "properties": {
    "iso:country": "GB",
    "wof:name": "YO32 5SW",
    "wof:placetype": "postalcode"
  },
  "geometry": {"coordinates":[-1.041096,54.025895],"type":"Point"}
}
