{
  "type": "Feature",
  "properties": {
    "iso:country":"GB",
    "wof:name":"YO32 5SW",
    "wof:placetype":"postalcode"
},
  "geometry": {"coordinates":[-1.04122214512328,54.02593308824371],"type":"Point"}
}