{
  "type": "Feature",
  "properties": {
    "iso:country": "GB",
    "wof:name": "WF7 7FU",
    "wof:placetype": "postalcode"
  },
  "geometry": {"coordinates":[-1.348976,53.643231],"type":"Point"}
}
