{
  "type": "Feature",
  "properties": {
    "date:inception_lower": "2018-04-01",
    "date:inception_upper": "2018-04-01",
    "iso:country": "GB",
    "wof:name": "WF7 7FU",
    "wof:placetype": "postalcode"
  },
  "geometry": {"coordinates":[-1.348976,53.643231],"type":"Point"}
}
