{
  "type": "Feature",
  "properties": {
    "iso:country": "GB",
    "wof:name": "PL11 2QB",
    "wof:placetype": "postalcode"
  },
  "geometry": {"coordinates":[-4.226448,50.385357],"type":"Point"}
}
