{
  "type": "Feature",
  "properties": {
    "iso:country":"GB",
    "wof:name":"PL11 2QB",
    "wof:placetype":"postalcode"
},
  "geometry": {"coordinates":[-4.22644817048391,50.3853566552765],"type":"Point"}
}