{
  "type": "Feature",
  "properties": {
    "date:inception_lower": "2000-06-01",
    "date:inception_upper": "2000-06-01",
    "iso:country": "GB",
    "wof:name": "PE28 9LN",
    "wof:placetype": "postalcode"
  },
  "geometry": {"coordinates":[-0.064579,52.297045],"type":"Point"}
}
