{
  "type": "Feature",
  "properties": {
    "iso:country":"GB",
    "wof:name":"HS6 5HP",
    "wof:placetype":"postalcode"
},
  "geometry": {"coordinates":[-7.25870253046766,57.5109512164243],"type":"Point"}
}