{
  "type": "Feature",
  "properties": {
    "iso:country":"GB",
    "wof:name":"CV4 9TZ",
    "wof:placetype":"postalcode"
},
  "geometry": {"coordinates":[-1.60103526193177,52.40178705021399],"type":"Point"}
}