{
  "type": "Feature",
  "properties": {
    "iso:country": "GB",
    "wof:name": "DL6 1EF",
    "wof:placetype": "postalcode"
  },
  "geometry": {"coordinates":[-1.43536,54.342587],"type":"Point"}
}
