{
  "type": "Feature",
  "properties": {
    "iso:country":"GB",
    "wof:name":"SM2 6BP",
    "wof:placetype":"postalcode"
},
  "geometry": {"coordinates":[-0.20078143607179,51.34265567276214],"type":"Point"}
}