{
  "type": "Feature",
  "properties": {
    "date:inception_lower":"1980-01-01",
    "date:inception_upper":"1980-01-31",
    "iso:country":"GB",
    "wof:name":"SM2 6BP",
    "wof:placetype":"postalcode"
},
  "geometry": {"coordinates":[-0.200781,51.342656],"type":"Point"}
}