{
  "type": "Feature",
  "properties": {
    "iso:country": "GB",
    "wof:name": "RG30 3RN",
    "wof:placetype": "postalcode"
  },
  "geometry": {"coordinates":[-1.030593,51.407617],"type":"Point"}
}
