{
  "type": "Feature",
  "properties": {
    "iso:country":"GB",
    "wof:name":"RG30 3RN",
    "wof:placetype":"postalcode"
},
  "geometry": {"coordinates":[-1.03059316574227,51.40761741973292],"type":"Point"}
}