{
  "type": "Feature",
  "properties": {
    "date:inception_lower": "2007-08-01",
    "date:inception_upper": "2007-08-01",
    "iso:country": "GB",
    "wof:name": "NW2 2LA",
    "wof:placetype": "postalcode"
  },
  "geometry": {"coordinates":[-0.200634,51.56494],"type":"Point"}
}
