{
  "type": "Feature",
  "properties": {
    "iso:country":"GB",
    "wof:name":"NW2 2LA",
    "wof:placetype":"postalcode"
},
  "geometry": {"coordinates":[-0.20063432586406,51.56493955506313],"type":"Point"}
}