{
  "type": "Feature",
  "properties": {
    "date:inception_lower": "2021-10-01",
    "date:inception_upper": "2021-10-01",
    "iso:country": "GB",
    "wof:name": "RH3 7FF",
    "wof:placetype": "postalcode"
  },
  "geometry": {"coordinates":[-0.268247,51.239185],"type":"Point"}
}
