{
  "type": "Feature",
  "properties": {
    "iso:country":"GB",
    "wof:name":"BN6 9NH",
    "wof:placetype":"postalcode"
},
  "geometry": {"coordinates":[-0.15279306824699,50.92400306249705],"type":"Point"}
}