{
  "type": "Feature",
  "properties": {
    "date:inception_lower": "1980-01-01",
    "date:inception_upper": "1980-01-01",
    "iso:country": "GB",
    "wof:name": "RG9 4JL",
    "wof:placetype": "postalcode"
  },
  "geometry": {"coordinates":[-0.95974,51.510839],"type":"Point"}
}
