{
  "type": "Feature",
  "properties": {
    "iso:country":"GB",
    "wof:name":"RG9 4JL",
    "wof:placetype":"postalcode"
},
  "geometry": {"coordinates":[-0.95974046133714,51.51083908365824],"type":"Point"}
}