{
  "type": "Feature",
  "properties": {
    "iso:country":"GB",
    "wof:name":"LE18 3QX",
    "wof:placetype":"postalcode"
},
  "geometry": {"coordinates":[-1.10052448545355,52.58251215042217],"type":"Point"}
}