{
  "type": "Feature",
  "properties": {
    "iso:country":"GB",
    "wof:name":"NP11 6HX",
    "wof:placetype":"postalcode"
},
  "geometry": {"coordinates":[-3.0935840090976,51.61257631141674],"type":"Point"}
}