{
  "type": "Feature",
  "properties": {
    "iso:country":"GB",
    "wof:name":"CF3 2TW",
    "wof:placetype":"postalcode"
},
  "geometry": {"coordinates":[-3.06349585501489,51.53077653264845],"type":"Point"}
}