{
  "type": "Feature",
  "properties": {
    "iso:country": "GB",
    "wof:name": "CF3 2TW",
    "wof:placetype": "postalcode"
  },
  "geometry": {"coordinates":[-3.063496,51.530777],"type":"Point"}
}
