{
  "type": "Feature",
  "properties": {
    "date:inception_lower": "1999-06-01",
    "date:inception_upper": "1999-06-01",
    "iso:country": "GB",
    "wof:name": "CF3 2TW",
    "wof:placetype": "postalcode"
  },
  "geometry": {"coordinates":[-3.063496,51.530777],"type":"Point"}
}
