{
  "type": "Feature",
  "properties": {
    "date:inception_lower": "1983-07-01",
    "date:inception_upper": "1983-07-01",
    "iso:country": "GB",
    "wof:name": "BD8 9TG",
    "wof:placetype": "postalcode"
  },
  "geometry": {"coordinates":[-1.790959,53.797863],"type":"Point"}
}
