{
  "type": "Feature",
  "properties": {
    "iso:country":"GB",
    "wof:name":"BD8 9TG",
    "wof:placetype":"postalcode"
},
  "geometry": {"coordinates":[-1.79089525777848,53.79786671291581],"type":"Point"}
}