{
  "type": "Feature",
  "properties": {
    "iso:country": "GB",
    "wof:name": "CO1 2UT",
    "wof:placetype": "postalcode"
  },
  "geometry": {"coordinates":[0.913142,51.889053],"type":"Point"}
}
