{
  "type": "Feature",
  "properties": {
    "date:inception_lower": "1980-01-01",
    "date:inception_upper": "1980-01-01",
    "iso:country": "GB",
    "wof:name": "GU35 0AU",
    "wof:placetype": "postalcode"
  },
  "geometry": {"coordinates":[-0.863898,51.1127],"type":"Point"}
}
