{
  "type": "Feature",
  "properties": {
    "iso:country":"GB",
    "wof:name":"GU35 0AU",
    "wof:placetype":"postalcode"
},
  "geometry": {"coordinates":[-0.86377461667179,51.11263126367694],"type":"Point"}
}