{
  "type": "Feature",
  "properties": {
    "iso:country":"GB",
    "wof:name":"GU47 8JX",
    "wof:placetype":"postalcode"
},
  "geometry": {"coordinates":[-0.81485666092841,51.34805860138822],"type":"Point"}
}