{
  "type": "Feature",
  "properties": {
    "date:inception_lower": "2002-06-01",
    "date:inception_upper": "2002-06-01",
    "iso:country": "GB",
    "wof:name": "GU47 8JX",
    "wof:placetype": "postalcode"
  },
  "geometry": {"coordinates":[-0.814857,51.348059],"type":"Point"}
}
