{
  "type": "Feature",
  "properties": {
    "date:inception_lower": "2018-01-01",
    "date:inception_upper": "2018-01-01",
    "iso:country": "GB",
    "wof:name": "TA19 9FN",
    "wof:placetype": "postalcode"
  },
  "geometry": {"coordinates":[-2.964878,50.933679],"type":"Point"}
}
