{
  "type": "Feature",
  "properties": {
    "iso:country":"GB",
    "wof:name":"HU14 3RB",
    "wof:placetype":"postalcode"
},
  "geometry": {"coordinates":[-0.48906085149728,53.74191616971724],"type":"Point"}
}