{
  "type": "Feature",
  "properties": {
    "iso:country":"GB",
    "wof:name":"B46 2QW",
    "wof:placetype":"postalcode"
},
  "geometry": {"coordinates":[-1.65566880644868,52.47913832943979],"type":"Point"}
}