{
  "type": "Feature",
  "properties": {
    "iso:country": "GB",
    "wof:name": "B46 2QW",
    "wof:placetype": "postalcode"
  },
  "geometry": {"coordinates":[-1.655669,52.479138],"type":"Point"}
}
