{
  "type": "Feature",
  "properties": {
    "iso:country":"GB",
    "wof:name":"BA22 8QP",
    "wof:placetype":"postalcode"
},
  "geometry": {"coordinates":[-2.6820685954868,51.00215409750999],"type":"Point"}
}