{
  "type": "Feature",
  "properties": {
    "iso:country": "GB",
    "wof:name": "BA22 8QP",
    "wof:placetype": "postalcode"
  },
  "geometry": {"coordinates":[-2.682069,51.002154],"type":"Point"}
}
