{
  "type": "Feature",
  "properties": {
    "date:inception_lower": "1997-06-01",
    "date:inception_upper": "1997-06-01",
    "iso:country": "GB",
    "wof:name": "BA22 8QP",
    "wof:placetype": "postalcode"
  },
  "geometry": {"coordinates":[-2.682069,51.002154],"type":"Point"}
}
