{
  "type": "Feature",
  "properties": {
    "date:inception_lower": "2002-12-01",
    "date:inception_upper": "2002-12-01",
    "iso:country": "GB",
    "wof:name": "PE20 1XA",
    "wof:placetype": "postalcode"
  },
  "geometry": {"coordinates":[-0.054488,52.929107],"type":"Point"}
}
