{
  "type": "Feature",
  "properties": {
    "iso:country": "GB",
    "wof:name": "PE20 1XA",
    "wof:placetype": "postalcode"
  },
  "geometry": {"coordinates":[-0.054488,52.929107],"type":"Point"}
}
