{
  "type": "Feature",
  "properties": {
    "iso:country": "GB",
    "wof:name": "BA5 1GD",
    "wof:placetype": "postalcode"
  },
  "geometry": {"coordinates":[-2.646977,51.208261],"type":"Point"}
}
