{
  "type": "Feature",
  "properties": {
    "iso:country": "GB",
    "wof:name": "RH17 6QN",
    "wof:placetype": "postalcode"
  },
  "geometry": {"coordinates":[-0.115428,51.043601],"type":"Point"}
}
