{
  "type": "Feature",
  "properties": {
    "iso:country": "GB",
    "wof:name": "KA8 9RY",
    "wof:placetype": "postalcode"
  },
  "geometry": {"coordinates":[-4.592019,55.474224],"type":"Point"}
}
