{
  "type": "Feature",
  "properties": {
    "date:inception_lower": "1980-01-01",
    "date:inception_upper": "1980-01-01",
    "iso:country": "GB",
    "wof:name": "KA8 9RY",
    "wof:placetype": "postalcode"
  },
  "geometry": {"coordinates":[-4.592019,55.474224],"type":"Point"}
}
