{
  "type": "Feature",
  "properties": {
    "iso:country": "GB",
    "wof:name": "ZE2 9FH",
    "wof:placetype": "postalcode"
  },
  "geometry": {"coordinates":[-1.216618,60.126919],"type":"Point"}
}
