{
  "type": "Feature",
  "properties": {
    "date:inception_lower": "2019-12-01",
    "date:inception_upper": "2019-12-01",
    "iso:country": "GB",
    "wof:name": "ZE2 9FH",
    "wof:placetype": "postalcode"
  },
  "geometry": {"coordinates":[-1.215823,60.195912],"type":"Point"}
}
