{
  "type": "Feature",
  "properties": {
    "iso:country": "GB",
    "wof:name": "ZE2 9FH",
    "wof:placetype": "postalcode"
  },
  "geometry": {"coordinates":[-1.215823,60.195912],"type":"Point"}
}
