{
  "type": "Feature",
  "properties": {
    "iso:country": "GB",
    "wof:name": "TS25 1PJ",
    "wof:placetype": "postalcode"
  },
  "geometry": {"coordinates":[-1.207899,54.673477],"type":"Point"}
}
