{
  "type": "Feature",
  "properties": {
    "date:inception_lower": "1998-12-01",
    "date:inception_upper": "1998-12-01",
    "iso:country": "GB",
    "wof:name": "EC1A 9JU",
    "wof:placetype": "postalcode"
  },
  "geometry": {"coordinates":[-0.102454,51.518433],"type":"Point"}
}
