{
  "type": "Feature",
  "properties": {
    "iso:country": "GB",
    "wof:name": "EC1A 9JU",
    "wof:placetype": "postalcode"
  },
  "geometry": {"coordinates":[-0.102454,51.518433],"type":"Point"}
}
