{
  "type": "Feature",
  "properties": {
    "date:inception_lower":"1980-01-01",
    "date:inception_upper":"1980-01-31",
    "iso:country":"GB",
    "wof:name":"DN17 1TT",
    "wof:placetype":"postalcode"
},
  "geometry": {"coordinates":[-0.682563,53.579697],"type":"Point"}
}