{
  "type": "Feature",
  "properties": {
    "date:inception_lower": "1980-01-01",
    "date:inception_upper": "1980-01-01",
    "iso:country": "GB",
    "wof:name": "DN17 1TT",
    "wof:placetype": "postalcode"
  },
  "geometry": {"coordinates":[-0.682743,53.579726],"type":"Point"}
}
