{
  "type": "Feature",
  "properties": {
    "iso:country":"GB",
    "wof:name":"KY12 9HY",
    "wof:placetype":"postalcode"
},
  "geometry": {"coordinates":[-3.49904129951613,56.08412109105019],"type":"Point"}
}