{
  "type": "Feature",
  "properties": {
    "iso:country": "GB",
    "wof:name": "S10 2QJ",
    "wof:placetype": "postalcode"
  },
  "geometry": {"coordinates":[-1.499015,53.375682],"type":"Point"}
}
