{
  "type": "Feature",
  "properties": {
    "iso:country":"GB",
    "wof:name":"CT14 0HF",
    "wof:placetype":"postalcode"
},
  "geometry": {"coordinates":[1.35846909281798,51.21247983492303],"type":"Point"}
}