{
  "type": "Feature",
  "properties": {
    "iso:country": "GB",
    "wof:name": "CT14 0HF",
    "wof:placetype": "postalcode"
  },
  "geometry": {"coordinates":[1.358469,51.21248],"type":"Point"}
}
