{
  "type": "Feature",
  "properties": {
    "iso:country": "GB",
    "wof:name": "LA4 4EZ",
    "wof:placetype": "postalcode"
  },
  "geometry": {"coordinates":[-2.879594,54.066072],"type":"Point"}
}
