{
  "type": "Feature",
  "properties": {
    "iso:country":"GB",
    "wof:name":"LA4 4EZ",
    "wof:placetype":"postalcode"
},
  "geometry": {"coordinates":[-2.87959439928317,54.06607223878142],"type":"Point"}
}