{
  "type": "Feature",
  "properties": {
    "iso:country": "GB",
    "wof:name": "YO8 4DF",
    "wof:placetype": "postalcode"
  },
  "geometry": {"coordinates":[-1.082869,53.785996],"type":"Point"}
}
