{
  "type": "Feature",
  "properties": {
    "iso:country":"GB",
    "wof:name":"SY8 4BU",
    "wof:placetype":"postalcode"
},
  "geometry": {"coordinates":[-2.71021648155472,52.34700305244586],"type":"Point"}
}