{
  "type": "Feature",
  "properties": {
    "iso:country": "GB",
    "wof:name": "SY8 4BU",
    "wof:placetype": "postalcode"
  },
  "geometry": {"coordinates":[-2.711122,52.344107],"type":"Point"}
}
