{
  "type": "Feature",
  "properties": {
    "date:inception_lower":"1980-01-01",
    "date:inception_upper":"1980-01-31",
    "iso:country":"GB",
    "wof:name":"RH6 9HA",
    "wof:placetype":"postalcode"
},
  "geometry": {"coordinates":[-0.158395,51.169091],"type":"Point"}
}