{
  "type": "Feature",
  "properties": {
    "iso:country":"GB",
    "wof:name":"EX5 4EQ",
    "wof:placetype":"postalcode"
},
  "geometry": {"coordinates":[-3.50958807776819,50.76354706482609],"type":"Point"}
}