{
  "type": "Feature",
  "properties": {
    "date:inception_lower":"1980-01-01",
    "date:inception_upper":"1980-01-31",
    "iso:country":"GB",
    "wof:name":"EX5 4EQ",
    "wof:placetype":"postalcode"
},
  "geometry": {"coordinates":[-3.509588,50.763547],"type":"Point"}
}