{
  "type": "Feature",
  "properties": {
    "iso:country": "GB",
    "wof:name": "GL55 6HG",
    "wof:placetype": "postalcode"
  },
  "geometry": {"coordinates":[-1.778165,52.05419],"type":"Point"}
}
