{
  "type": "Feature",
  "properties": {
    "date:inception_lower":"1999-12-01",
    "date:inception_upper":"1999-12-31",
    "iso:country":"GB",
    "wof:name":"GL55 6HG",
    "wof:placetype":"postalcode"
},
  "geometry": {"coordinates":[-1.778165,52.05419],"type":"Point"}
}