{
  "type": "Feature",
  "properties": {
    "iso:country":"GB",
    "wof:name":"GL55 6HG",
    "wof:placetype":"postalcode"
},
  "geometry": {"coordinates":[-1.77816485412733,52.05418989747945],"type":"Point"}
}