{
  "type": "Feature",
  "properties": {
    "iso:country":"GB",
    "wof:name":"DN35 0AD",
    "wof:placetype":"postalcode"
},
  "geometry": {"coordinates":[-0.02022289853355,53.55379086604927],"type":"Point"}
}