{
  "type": "Feature",
  "properties": {
    "iso:country":"GB",
    "wof:name":"CB8 7FL",
    "wof:placetype":"postalcode"
},
  "geometry": {"coordinates":[0.40381315677753,52.25649744953618],"type":"Point"}
}