{
  "type": "Feature",
  "properties": {
    "iso:country": "GB",
    "wof:name": "CH60 8NG",
    "wof:placetype": "postalcode"
  },
  "geometry": {"coordinates":[-3.093122,53.316954],"type":"Point"}
}
