{
  "type": "Feature",
  "properties": {
    "iso:country":"GB",
    "wof:name":"PE6 9PJ",
    "wof:placetype":"postalcode"
},
  "geometry": {"coordinates":[-0.34752624661789,52.71316163733115],"type":"Point"}
}