{
  "type": "Feature",
  "properties": {
    "iso:country": "GB",
    "wof:name": "PE6 9PJ",
    "wof:placetype": "postalcode"
  },
  "geometry": {"coordinates":[-0.347455,52.713181],"type":"Point"}
}
