{
  "type": "Feature",
  "properties": {
    "date:inception_lower": "2019-06-01",
    "date:inception_upper": "2019-06-01",
    "iso:country": "GB",
    "wof:name": "EX2 7SP",
    "wof:placetype": "postalcode"
  },
  "geometry": {"coordinates":[-3.47837,50.701181],"type":"Point"}
}
