{
  "type": "Feature",
  "properties": {
    "iso:country": "GB",
    "wof:name": "EX2 7SP",
    "wof:placetype": "postalcode"
  },
  "geometry": {"coordinates":[-3.478011,50.701033],"type":"Point"}
}
