{
  "type": "Feature",
  "properties": {
    "iso:country": "GB",
    "wof:name": "EX2 7SP",
    "wof:placetype": "postalcode"
  },
  "geometry": {"coordinates":[-3.47837,50.701181],"type":"Point"}
}
