{
  "type": "Feature",
  "properties": {
    "iso:country":"GB",
    "wof:name":"HA6 2QP",
    "wof:placetype":"postalcode"
},
  "geometry": {"coordinates":[-0.42712258880216,51.60601460769865],"type":"Point"}
}