{
  "type": "Feature",
  "properties": {
    "iso:country":"GB",
    "wof:name":"EH8 7SS",
    "wof:placetype":"postalcode"
},
  "geometry": {"coordinates":[-3.13182213909509,55.95236534834499],"type":"Point"}
}