{
  "type": "Feature",
  "properties": {
    "date:inception_lower":"1980-01-01",
    "date:inception_upper":"1980-01-31",
    "iso:country":"GB",
    "wof:name":"LS12 1JD",
    "wof:placetype":"postalcode"
},
  "geometry": {"coordinates":[-1.575379,53.790231],"type":"Point"}
}