{
  "type": "Feature",
  "properties": {
    "iso:country":"GB",
    "wof:name":"HU9 4HR",
    "wof:placetype":"postalcode"
},
  "geometry": {"coordinates":[-0.25776554929983,53.76593350987348],"type":"Point"}
}