{
  "type": "Feature",
  "properties": {
    "date:inception_lower": "1980-01-01",
    "date:inception_upper": "1980-01-01",
    "iso:country": "GB",
    "wof:name": "HU9 4HR",
    "wof:placetype": "postalcode"
  },
  "geometry": {"coordinates":[-0.257766,53.765934],"type":"Point"}
}
