{
  "type": "Feature",
  "properties": {
    "iso:country": "GB",
    "wof:name": "SN15 4AF",
    "wof:placetype": "postalcode"
  },
  "geometry": {"coordinates":[-1.958584,51.508303],"type":"Point"}
}
