{
  "type": "Feature",
  "properties": {
    "iso:country":"GB",
    "wof:name":"SN15 4AF",
    "wof:placetype":"postalcode"
},
  "geometry": {"coordinates":[-1.95858389741536,51.50830275398627],"type":"Point"}
}