{
  "type": "Feature",
  "properties": {
    "iso:country":"GB",
    "wof:name":"M1 6DD",
    "wof:placetype":"postalcode"
},
  "geometry": {"coordinates":[-2.23916411701162,53.47690310358468],"type":"Point"}
}