{
  "type": "Feature",
  "properties": {
    "iso:country": "GB",
    "wof:name": "M1 6DD",
    "wof:placetype": "postalcode"
  },
  "geometry": {"coordinates":[-2.239422,53.477226],"type":"Point"}
}
