{
  "type": "Feature",
  "properties": {
    "iso:country":"GB",
    "wof:name":"S63 7EE",
    "wof:placetype":"postalcode"
},
  "geometry": {"coordinates":[-1.32732331877922,53.50266652040755],"type":"Point"}
}