{
  "type": "Feature",
  "properties": {
    "iso:country":"GB",
    "wof:name":"HP1 2TJ",
    "wof:placetype":"postalcode"
},
  "geometry": {"coordinates":[-0.50626135601805,51.75846259905362],"type":"Point"}
}