{
  "type": "Feature",
  "properties": {
    "date:inception_lower": "1990-02-01",
    "date:inception_upper": "1990-02-01",
    "iso:country": "GB",
    "wof:name": "HP1 2TJ",
    "wof:placetype": "postalcode"
  },
  "geometry": {"coordinates":[-0.506261,51.758463],"type":"Point"}
}
