{
  "type": "Feature",
  "properties": {
    "iso:country":"GB",
    "wof:name":"LS29 9BP",
    "wof:placetype":"postalcode"
},
  "geometry": {"coordinates":[-1.84408455709069,53.9269054659235],"type":"Point"}
}