{
  "type": "Feature",
  "properties": {
    "iso:country":"GB",
    "wof:name":"S26 2DX",
    "wof:placetype":"postalcode"
},
  "geometry": {"coordinates":[-1.30504311559306,53.36497610233866],"type":"Point"}
}