{
  "type": "Feature",
  "properties": {
    "iso:country": "GB",
    "wof:name": "M28 3DJ",
    "wof:placetype": "postalcode"
  },
  "geometry": {"coordinates":[-2.393246,53.521545],"type":"Point"}
}
