{
  "type": "Feature",
  "properties": {
    "iso:country":"GB",
    "wof:name":"M28 3DJ",
    "wof:placetype":"postalcode"
},
  "geometry": {"coordinates":[-2.39324557344078,53.52154529954521],"type":"Point"}
}