{
  "type": "Feature",
  "properties": {
    "iso:country":"GB",
    "wof:name":"SG14 1RE",
    "wof:placetype":"postalcode"
},
  "geometry": {"coordinates":[-0.0808592727498,51.79734627587657],"type":"Point"}
}