{
  "type": "Feature",
  "properties": {
    "iso:country":"GB",
    "wof:name":"RG30 1BS",
    "wof:placetype":"postalcode"
},
  "geometry": {"coordinates":[-0.99385913845584,51.45802208022024],"type":"Point"}
}