{
  "type": "Feature",
  "properties": {
    "iso:country":"GB",
    "wof:name":"E14 8AJ",
    "wof:placetype":"postalcode"
},
  "geometry": {"coordinates":[-0.02956721735911,51.50993546651922],"type":"Point"}
}