{
  "type": "Feature",
  "properties": {
    "iso:country":"GB",
    "wof:name":"YO43 3FA",
    "wof:placetype":"postalcode"
},
  "geometry": {"coordinates":[-0.67204682694951,53.86016298230031],"type":"Point"}
}