{
  "type": "Feature",
  "properties": {
    "iso:country": "GB",
    "wof:name": "YO43 3FA",
    "wof:placetype": "postalcode"
  },
  "geometry": {"coordinates":[-0.671931,53.859964],"type":"Point"}
}
