{
  "type": "Feature",
  "properties": {
    "date:inception_lower": "2014-08-01",
    "date:inception_upper": "2014-08-01",
    "iso:country": "GB",
    "wof:name": "YO43 3FA",
    "wof:placetype": "postalcode"
  },
  "geometry": {"coordinates":[-0.671931,53.859964],"type":"Point"}
}
