{
  "type": "Feature",
  "properties": {
    "iso:country":"GB",
    "wof:name":"DE14 2FD",
    "wof:placetype":"postalcode"
},
  "geometry": {"coordinates":[-1.63914073648877,52.81791267829878],"type":"Point"}
}