{
  "type": "Feature",
  "properties": {
    "date:inception_lower": "1980-01-01",
    "date:inception_upper": "1980-01-01",
    "iso:country": "GB",
    "wof:name": "NP7 0DR",
    "wof:placetype": "postalcode"
  },
  "geometry": {"coordinates":[-3.094032,51.827591],"type":"Point"}
}
