{
  "type": "Feature",
  "properties": {
    "iso:country":"GB",
    "wof:name":"WD3 3HQ",
    "wof:placetype":"postalcode"
},
  "geometry": {"coordinates":[-0.44291346914271,51.64885630825943],"type":"Point"}
}