{
  "type": "Feature",
  "properties": {
    "iso:country": "GB",
    "wof:name": "WA11 9AT",
    "wof:placetype": "postalcode"
  },
  "geometry": {"coordinates":[-2.725348,53.470686],"type":"Point"}
}
