{
  "type": "Feature",
  "properties": {
    "date:inception_lower":"1990-02-01",
    "date:inception_upper":"1990-02-28",
    "iso:country":"GB",
    "wof:name":"SY1 4PR",
    "wof:placetype":"postalcode"
},
  "geometry": {"coordinates":[-2.717581,52.736308],"type":"Point"}
}