{
  "type": "Feature",
  "properties": {
    "iso:country":"GB",
    "wof:name":"SY1 4PR",
    "wof:placetype":"postalcode"
},
  "geometry": {"coordinates":[-2.71758137514567,52.73630847097654],"type":"Point"}
}