{
  "type": "Feature",
  "properties": {
    "iso:country": "GB",
    "wof:name": "SY1 4PR",
    "wof:placetype": "postalcode"
  },
  "geometry": {"coordinates":[-2.717581,52.736308],"type":"Point"}
}
