{
  "type": "Feature",
  "properties": {
    "iso:country":"GB",
    "wof:name":"BL3 3SE",
    "wof:placetype":"postalcode"
},
  "geometry": {"coordinates":[-2.46327034590512,53.55699639082165],"type":"Point"}
}