{
  "type": "Feature",
  "properties": {
    "date:inception_lower":"1980-01-01",
    "date:inception_upper":"1980-01-31",
    "iso:country":"GB",
    "wof:name":"BL3 3SE",
    "wof:placetype":"postalcode"
},
  "geometry": {"coordinates":[-2.46327,53.556996],"type":"Point"}
}