{
  "type": "Feature",
  "properties": {
    "date:inception_lower": "1996-06-01",
    "date:inception_upper": "1996-06-01",
    "iso:country": "GB",
    "wof:name": "PE21 9PB",
    "wof:placetype": "postalcode"
  },
  "geometry": {"coordinates":[-0.033782,52.989382],"type":"Point"}
}
