{
  "type": "Feature",
  "properties": {
    "date:inception_lower": "2020-08-01",
    "date:inception_upper": "2020-08-01",
    "iso:country": "GB",
    "wof:name": "L14 9AF",
    "wof:placetype": "postalcode"
  },
  "geometry": {"coordinates":[-2.859829,53.424203],"type":"Point"}
}
