{
  "type": "Feature",
  "properties": {
    "iso:country":"GB",
    "wof:name":"HP18 0WN",
    "wof:placetype":"postalcode"
},
  "geometry": {"coordinates":[-0.85477713982372,51.82856028286052],"type":"Point"}
}