{
  "type": "Feature",
  "properties": {
    "iso:country": "GB",
    "wof:name": "HP18 0WN",
    "wof:placetype": "postalcode"
  },
  "geometry": {"coordinates":[-0.854777,51.82856],"type":"Point"}
}
