{
  "type": "Feature",
  "properties": {
    "iso:country":"GB",
    "wof:name":"CF31 5AP",
    "wof:placetype":"postalcode"
},
  "geometry": {"coordinates":[-3.59968601242063,51.5012280084191],"type":"Point"}
}