{
  "type": "Feature",
  "properties": {
    "date:inception_lower": "2000-12-01",
    "date:inception_upper": "2000-12-01",
    "iso:country": "GB",
    "wof:name": "CF31 5AP",
    "wof:placetype": "postalcode"
  },
  "geometry": {"coordinates":[-3.599686,51.501228],"type":"Point"}
}
