{
  "type": "Feature",
  "properties": {
    "iso:country":"GB",
    "wof:name":"CT2 0BA",
    "wof:placetype":"postalcode"
},
  "geometry": {"coordinates":[1.12257458925853,51.29943075849798],"type":"Point"}
}