{
  "type": "Feature",
  "properties": {
    "iso:country":"GB",
    "wof:name":"BD23 1DQ",
    "wof:placetype":"postalcode"
},
  "geometry": {"coordinates":[-2.02556850426897,53.96068059054014],"type":"Point"}
}