{
  "type": "Feature",
  "properties": {
    "iso:country": "GB",
    "wof:name": "WD18 0GS",
    "wof:placetype": "postalcode"
  },
  "geometry": {"coordinates":[-0.397581,51.64666],"type":"Point"}
}
