{
  "type": "Feature",
  "properties": {
    "iso:country": "GB",
    "wof:name": "E10 5DT",
    "wof:placetype": "postalcode"
  },
  "geometry": {"coordinates":[-0.014121,51.568846],"type":"Point"}
}
