{
  "type": "Feature",
  "properties": {
    "iso:country":"GB",
    "wof:name":"E10 5DT",
    "wof:placetype":"postalcode"
},
  "geometry": {"coordinates":[-0.01412067050013,51.56884637327717],"type":"Point"}
}