{
  "type": "Feature",
  "properties": {
    "iso:country": "GB",
    "wof:name": "AB23 8QT",
    "wof:placetype": "postalcode"
  },
  "geometry": {"coordinates":[-2.095649,57.18367],"type":"Point"}
}
