{
  "type": "Feature",
  "properties": {
    "iso:country": "GB",
    "wof:name": "IP4 1NG",
    "wof:placetype": "postalcode"
  },
  "geometry": {"coordinates":[1.16469,52.056182],"type":"Point"}
}
