{
  "type": "Feature",
  "properties": {
    "iso:country":"GB",
    "wof:name":"IP4 1NG",
    "wof:placetype":"postalcode"
},
  "geometry": {"coordinates":[1.1646896855476,52.05618158795132],"type":"Point"}
}