{
  "type": "Feature",
  "properties": {
    "iso:country": "GB",
    "wof:name": "GL10 3HN",
    "wof:placetype": "postalcode"
  },
  "geometry": {"coordinates":[-2.274919,51.733552],"type":"Point"}
}
