{
  "type": "Feature",
  "properties": {
    "iso:country":"GB",
    "wof:name":"WS8 6JE",
    "wof:placetype":"postalcode"
},
  "geometry": {"coordinates":[-1.92330902575048,52.65450201834133],"type":"Point"}
}