{
  "type": "Feature",
  "properties": {
    "date:inception_lower":"1980-01-01",
    "date:inception_upper":"1980-01-31",
    "iso:country":"GB",
    "wof:name":"WS8 6JE",
    "wof:placetype":"postalcode"
},
  "geometry": {"coordinates":[-1.923309,52.654502],"type":"Point"}
}