{
  "type": "Feature",
  "properties": {
    "date:inception_lower": "1980-01-01",
    "date:inception_upper": "1980-01-01",
    "iso:country": "GB",
    "wof:name": "PR5 5JF",
    "wof:placetype": "postalcode"
  },
  "geometry": {"coordinates":[-2.687605,53.720753],"type":"Point"}
}
