{
  "type": "Feature",
  "properties": {
    "iso:country": "GB",
    "wof:name": "PR5 5JF",
    "wof:placetype": "postalcode"
  },
  "geometry": {"coordinates":[-2.686761,53.72084],"type":"Point"}
}
