{
  "type": "Feature",
  "properties": {
    "date:inception_lower": "1995-07-01",
    "date:inception_upper": "1995-07-01",
    "iso:country": "GB",
    "wof:name": "WN4 8SW",
    "wof:placetype": "postalcode"
  },
  "geometry": {"coordinates":[-2.623249,53.491004],"type":"Point"}
}
