{
  "type": "Feature",
  "properties": {
    "iso:country":"GB",
    "wof:name":"BN20 7GB",
    "wof:placetype":"postalcode"
},
  "geometry": {"coordinates":[0.2713199886096,50.75475693810723],"type":"Point"}
}