{
  "type": "Feature",
  "properties": {
    "iso:country": "GB",
    "wof:name": "BN20 7GB",
    "wof:placetype": "postalcode"
  },
  "geometry": {"coordinates":[0.27132,50.754757],"type":"Point"}
}
