{
  "type": "Feature",
  "properties": {
    "date:inception_lower": "2001-06-01",
    "date:inception_upper": "2001-06-01",
    "iso:country": "GB",
    "wof:name": "GU51 3QS",
    "wof:placetype": "postalcode"
  },
  "geometry": {"coordinates":[-0.845948,51.275847],"type":"Point"}
}
