{
  "type": "Feature",
  "properties": {
    "date:inception_lower": "1980-01-01",
    "date:inception_upper": "1980-01-01",
    "iso:country": "GB",
    "wof:name": "DN22 7UB",
    "wof:placetype": "postalcode"
  },
  "geometry": {"coordinates":[-0.952383,53.30552],"type":"Point"}
}
