{
  "type": "Feature",
  "properties": {
    "iso:country": "GB",
    "wof:name": "DN22 7UB",
    "wof:placetype": "postalcode"
  },
  "geometry": {"coordinates":[-0.952383,53.30552],"type":"Point"}
}
