{
  "type": "Feature",
  "properties": {
    "iso:country":"GB",
    "wof:name":"NN1 3HD",
    "wof:placetype":"postalcode"
},
  "geometry": {"coordinates":[-0.89581450286093,52.24406004958897],"type":"Point"}
}