{
  "type": "Feature",
  "properties": {
    "date:inception_lower": "2010-04-01",
    "date:inception_upper": "2010-04-01",
    "iso:country": "GB",
    "wof:name": "S73 9BU",
    "wof:placetype": "postalcode"
  },
  "geometry": {"coordinates":[-1.38011,53.542681],"type":"Point"}
}
