{
  "type": "Feature",
  "properties": {
    "iso:country":"GB",
    "wof:name":"S73 9BU",
    "wof:placetype":"postalcode"
},
  "geometry": {"coordinates":[-1.38010992065358,53.54268106537274],"type":"Point"}
}