{
  "type": "Feature",
  "properties": {
    "iso:country": "GB",
    "wof:name": "S73 9BU",
    "wof:placetype": "postalcode"
  },
  "geometry": {"coordinates":[-1.38011,53.542681],"type":"Point"}
}
