{
  "type": "Feature",
  "properties": {
    "iso:country":"GB",
    "wof:name":"N9 8BU",
    "wof:placetype":"postalcode"
},
  "geometry": {"coordinates":[-0.04886721983187,51.6358928110142],"type":"Point"}
}