{
  "type": "Feature",
  "properties": {
    "iso:country":"GB",
    "wof:name":"L20 4JE",
    "wof:placetype":"postalcode"
},
  "geometry": {"coordinates":[-2.99975950526067,53.45520581492318],"type":"Point"}
}