{
  "type": "Feature",
  "properties": {
    "date:inception_lower":"1980-01-01",
    "date:inception_upper":"1980-01-31",
    "iso:country":"GB",
    "wof:name":"L20 4JE",
    "wof:placetype":"postalcode"
},
  "geometry": {"coordinates":[-2.999759,53.455206],"type":"Point"}
}