{
  "type": "Feature",
  "properties": {
    "iso:country": "GB",
    "wof:name": "L20 4JE",
    "wof:placetype": "postalcode"
  },
  "geometry": {"coordinates":[-2.999759,53.455206],"type":"Point"}
}
