{
  "type": "Feature",
  "properties": {
    "iso:country":"GB",
    "wof:name":"NN8 4AB",
    "wof:placetype":"postalcode"
},
  "geometry": {"coordinates":[-0.68389012234674,52.30942722414596],"type":"Point"}
}