{
  "type": "Feature",
  "properties": {
    "iso:country":"GB",
    "wof:name":"NN1 3JY",
    "wof:placetype":"postalcode"
},
  "geometry": {"coordinates":[-0.88864299229299,52.24150232914812],"type":"Point"}
}