{
  "type": "Feature",
  "properties": {
    "iso:country": "GB",
    "wof:name": "TS13 4DS",
    "wof:placetype": "postalcode"
  },
  "geometry": {"coordinates":[-0.910349,54.562729],"type":"Point"}
}
