{
  "type": "Feature",
  "properties": {
    "iso:country": "GB",
    "wof:name": "HP5 2LF",
    "wof:placetype": "postalcode"
  },
  "geometry": {"coordinates":[-0.617457,51.721779],"type":"Point"}
}
