{
  "type": "Feature",
  "properties": {
    "iso:country": "GB",
    "wof:name": "G73 2JH",
    "wof:placetype": "postalcode"
  },
  "geometry": {"coordinates":[-4.217531,55.828597],"type":"Point"}
}
