{
  "type": "Feature",
  "properties": {
    "iso:country":"GB",
    "wof:name":"M40 1PT",
    "wof:placetype":"postalcode"
},
  "geometry": {"coordinates":[-2.17225908008382,53.49356612849882],"type":"Point"}
}