{
  "type": "Feature",
  "properties": {
    "date:inception_lower":"2010-08-01",
    "date:inception_upper":"2010-08-31",
    "iso:country":"GB",
    "wof:name":"SW1P 3EU",
    "wof:placetype":"postalcode"
},
  "geometry": {"coordinates":[-0.12792,51.495594],"type":"Point"}
}