{
  "type": "Feature",
  "properties": {
    "iso:country":"GB",
    "wof:name":"SW1P 3EU",
    "wof:placetype":"postalcode"
},
  "geometry": {"coordinates":[-0.12792001105319,51.49559386822143],"type":"Point"}
}