{
  "type": "Feature",
  "properties": {
    "iso:country":"GB",
    "wof:name":"RH4 2LH",
    "wof:placetype":"postalcode"
},
  "geometry": {"coordinates":[-0.32912618096233,51.21786860559371],"type":"Point"}
}