{
  "type": "Feature",
  "properties": {
    "date:inception_lower":"2007-03-01",
    "date:inception_upper":"2007-03-31",
    "iso:country":"GB",
    "wof:name":"RH4 2LH",
    "wof:placetype":"postalcode"
},
  "geometry": {"coordinates":[-0.329126,51.217869],"type":"Point"}
}