{
  "type": "Feature",
  "properties": {
    "iso:country": "GB",
    "wof:name": "IP14 6FB",
    "wof:placetype": "postalcode"
  },
  "geometry": {"coordinates":[1.166526,52.189844],"type":"Point"}
}
