{
  "type": "Feature",
  "properties": {
    "iso:country":"GB",
    "wof:name":"IG8 0QF",
    "wof:placetype":"postalcode"
},
  "geometry": {"coordinates":[0.03183987615044,51.61740191449276],"type":"Point"}
}