{
  "type": "Feature",
  "properties": {
    "iso:country": "GB",
    "wof:name": "SO14 1NE",
    "wof:placetype": "postalcode"
  },
  "geometry": {"coordinates":[-1.396337,50.906882],"type":"Point"}
}
