{
  "type": "Feature",
  "properties": {
    "date:inception_lower": "2021-12-01",
    "date:inception_upper": "2021-12-01",
    "iso:country": "GB",
    "wof:name": "B90 8DG",
    "wof:placetype": "postalcode"
  },
  "geometry": {"coordinates":[-1.800747,52.37192],"type":"Point"}
}
