{
  "type": "Feature",
  "properties": {
    "date:inception_lower": "1984-05-01",
    "date:inception_upper": "1984-05-01",
    "iso:country": "GB",
    "wof:name": "FK6 6ED",
    "wof:placetype": "postalcode"
  },
  "geometry": {"coordinates":[-3.900768,56.020916],"type":"Point"}
}
