{
  "type": "Feature",
  "properties": {
    "iso:country": "GB",
    "wof:name": "FK6 6ED",
    "wof:placetype": "postalcode"
  },
  "geometry": {"coordinates":[-3.900768,56.020916],"type":"Point"}
}
