{
  "type": "Feature",
  "properties": {
    "iso:country": "GB",
    "wof:name": "DH8 7HE",
    "wof:placetype": "postalcode"
  },
  "geometry": {"coordinates":[-1.819555,54.846951],"type":"Point"}
}
