{
  "type": "Feature",
  "properties": {
    "iso:country": "GB",
    "wof:name": "PO16 0UW",
    "wof:placetype": "postalcode"
  },
  "geometry": {"coordinates":[-1.180474,50.842475],"type":"Point"}
}
