{
  "type": "Feature",
  "properties": {
    "iso:country":"GB",
    "wof:name":"EX1 1SG",
    "wof:placetype":"postalcode"
},
  "geometry": {"coordinates":[-3.52721253446816,50.72126500147491],"type":"Point"}
}