{
  "type": "Feature",
  "properties": {
    "date:inception_lower":"2013-02-01",
    "date:inception_upper":"2013-02-28",
    "iso:country":"GB",
    "wof:name":"EX1 1SG",
    "wof:placetype":"postalcode"
},
  "geometry": {"coordinates":[-3.527212,50.721265],"type":"Point"}
}