{
  "type": "Feature",
  "properties": {
    "iso:country": "GB",
    "wof:name": "YO18 8HH",
    "wof:placetype": "postalcode"
  },
  "geometry": {"coordinates":[-0.840922,54.290726],"type":"Point"}
}
