{
  "type": "Feature",
  "properties": {
    "iso:country":"GB",
    "wof:name":"CR4 4AU",
    "wof:placetype":"postalcode"
},
  "geometry": {"coordinates":[-0.16672274125335,51.38404245039967],"type":"Point"}
}