{
  "type": "Feature",
  "properties": {
    "iso:country":"GB",
    "wof:name":"DE24 8DH",
    "wof:placetype":"postalcode"
},
  "geometry": {"coordinates":[-1.45650007508918,52.89385276105364],"type":"Point"}
}