{
  "type": "Feature",
  "properties": {
    "iso:country":"GB",
    "wof:name":"PL2 3SE",
    "wof:placetype":"postalcode"
},
  "geometry": {"coordinates":[-4.14872997518936,50.40010371264405],"type":"Point"}
}