{
  "type": "Feature",
  "properties": {
    "date:inception_lower":"2005-07-01",
    "date:inception_upper":"2005-07-31",
    "iso:country":"GB",
    "wof:name":"BH9 2PR",
    "wof:placetype":"postalcode"
},
  "geometry": {"coordinates":[-1.880917,50.746471],"type":"Point"}
}