{
  "type": "Feature",
  "properties": {
    "date:inception_lower":"2009-10-01",
    "date:inception_upper":"2009-10-31",
    "iso:country":"GB",
    "wof:name":"RG2 6AD",
    "wof:placetype":"postalcode"
},
  "geometry": {"coordinates":[-0.989784,51.419637],"type":"Point"}
}