{
  "type": "Feature",
  "properties": {
    "iso:country": "GB",
    "wof:name": "RG2 6AD",
    "wof:placetype": "postalcode"
  },
  "geometry": {"coordinates":[-0.989784,51.419637],"type":"Point"}
}
