{
  "type": "Feature",
  "properties": {
    "iso:country":"GB",
    "wof:name":"RG2 6AD",
    "wof:placetype":"postalcode"
},
  "geometry": {"coordinates":[-0.98978356770351,51.41963672755568],"type":"Point"}
}