{
  "type": "Feature",
  "properties": {
    "iso:country":"GB",
    "wof:name":"PL14 4RU",
    "wof:placetype":"postalcode"
},
  "geometry": {"coordinates":[-4.47100695936594,50.45163560699393],"type":"Point"}
}