{
  "type": "Feature",
  "properties": {
    "date:inception_lower": "1998-06-01",
    "date:inception_upper": "1998-06-01",
    "iso:country": "GB",
    "wof:name": "BS2 0TD",
    "wof:placetype": "postalcode"
  },
  "geometry": {"coordinates":[-2.569006,51.448699],"type":"Point"}
}
