{
  "type": "Feature",
  "properties": {
    "iso:country":"GB",
    "wof:name":"BS2 0TD",
    "wof:placetype":"postalcode"
},
  "geometry": {"coordinates":[-2.56900601625911,51.44869908487327],"type":"Point"}
}