{
  "type": "Feature",
  "properties": {
    "date:inception_lower": "1980-01-01",
    "date:inception_upper": "1980-01-01",
    "iso:country": "GB",
    "wof:name": "SA2 0HD",
    "wof:placetype": "postalcode"
  },
  "geometry": {"coordinates":[-3.966442,51.617859],"type":"Point"}
}
