{
  "type": "Feature",
  "properties": {
    "iso:country":"GB",
    "wof:name":"SA2 0HD",
    "wof:placetype":"postalcode"
},
  "geometry": {"coordinates":[-3.96644211395935,51.617859365342],"type":"Point"}
}