{
  "type": "Feature",
  "properties": {
    "date:inception_lower": "2003-05-01",
    "date:inception_upper": "2003-05-01",
    "iso:country": "GB",
    "wof:name": "NE61 5PW",
    "wof:placetype": "postalcode"
  },
  "geometry": {"coordinates":[-1.620731,55.241722],"type":"Point"}
}
