{
  "type": "Feature",
  "properties": {
    "iso:country":"GB",
    "wof:name":"NE61 5PW",
    "wof:placetype":"postalcode"
},
  "geometry": {"coordinates":[-1.62073143931722,55.24172224722505],"type":"Point"}
}