{
  "type": "Feature",
  "properties": {
    "date:inception_lower": "2019-11-01",
    "date:inception_upper": "2019-11-01",
    "iso:country": "GB",
    "wof:name": "GL52 8PU",
    "wof:placetype": "postalcode"
  },
  "geometry": {"coordinates":[-2.056056,51.954282],"type":"Point"}
}
