{
  "type": "Feature",
  "properties": {
    "date:inception_lower": "2005-01-01",
    "date:inception_upper": "2005-01-01",
    "iso:country": "GB",
    "wof:name": "DE4 5PH",
    "wof:placetype": "postalcode"
  },
  "geometry": {"coordinates":[-1.47544,53.103954],"type":"Point"}
}
