{
  "type": "Feature",
  "properties": {
    "iso:country":"GB",
    "wof:name":"DE4 5PH",
    "wof:placetype":"postalcode"
},
  "geometry": {"coordinates":[-1.47543981694641,53.10395416372961],"type":"Point"}
}