{
  "type": "Feature",
  "properties": {
    "iso:country":"GB",
    "wof:name":"BB5 3LZ",
    "wof:placetype":"postalcode"
},
  "geometry": {"coordinates":[-2.39536735756824,53.74571465835989],"type":"Point"}
}