{
  "type": "Feature",
  "properties": {
    "iso:country":"GB",
    "wof:name":"IP25 6JW",
    "wof:placetype":"postalcode"
},
  "geometry": {"coordinates":[0.86551871779964,52.57018567569102],"type":"Point"}
}