{
  "type": "Feature",
  "properties": {
    "iso:country":"GB",
    "wof:name":"TD1 2NN",
    "wof:placetype":"postalcode"
},
  "geometry": {"coordinates":[-2.76329331247467,55.61229413442612],"type":"Point"}
}