{
  "type": "Feature",
  "properties": {
    "date:inception_lower":"2012-11-01",
    "date:inception_upper":"2012-11-30",
    "iso:country":"GB",
    "wof:name":"TD1 2NN",
    "wof:placetype":"postalcode"
},
  "geometry": {"coordinates":[-2.763293,55.612294],"type":"Point"}
}