{
  "type": "Feature",
  "properties": {
    "iso:country":"GB",
    "wof:name":"BN3 5LL",
    "wof:placetype":"postalcode"
},
  "geometry": {"coordinates":[-0.19771797471977,50.83362978489448],"type":"Point"}
}