{
  "type": "Feature",
  "properties": {
    "iso:country": "GB",
    "wof:name": "SS7 2DD",
    "wof:placetype": "postalcode"
  },
  "geometry": {"coordinates":[0.612969,51.551676],"type":"Point"}
}
