{
  "type": "Feature",
  "properties": {
    "date:inception_lower": "1998-12-01",
    "date:inception_upper": "1998-12-01",
    "iso:country": "GB",
    "wof:name": "CT21 5WD",
    "wof:placetype": "postalcode"
  },
  "geometry": {"coordinates":[1.111366,51.073825],"type":"Point"}
}
