{
  "type": "Feature",
  "properties": {
    "iso:country":"GB",
    "wof:name":"YO8 9FR",
    "wof:placetype":"postalcode"
},
  "geometry": {"coordinates":[-1.07949691808869,53.77155271722292],"type":"Point"}
}