{
  "type": "Feature",
  "properties": {
    "date:inception_lower": "2004-11-01",
    "date:inception_upper": "2004-11-01",
    "iso:country": "GB",
    "wof:name": "YO8 9FR",
    "wof:placetype": "postalcode"
  },
  "geometry": {"coordinates":[-1.079497,53.771553],"type":"Point"}
}
