{
  "type": "Feature",
  "properties": {
    "iso:country": "GB",
    "wof:name": "LS26 0LN",
    "wof:placetype": "postalcode"
  },
  "geometry": {"coordinates":[-1.481319,53.753785],"type":"Point"}
}
