{
  "type": "Feature",
  "properties": {
    "iso:country":"GB",
    "wof:name":"OL12 9JA",
    "wof:placetype":"postalcode"
},
  "geometry": {"coordinates":[-2.13715063136842,53.64146036863921],"type":"Point"}
}