{
  "type": "Feature",
  "properties": {
    "iso:country":"GB",
    "wof:name":"B24 9PT",
    "wof:placetype":"postalcode"
},
  "geometry": {"coordinates":[-1.80925021291162,52.51735091110987],"type":"Point"}
}