{
  "type": "Feature",
  "properties": {
    "iso:country":"GB",
    "wof:name":"ML2 9BH",
    "wof:placetype":"postalcode"
},
  "geometry": {"coordinates":[-3.88320537668603,55.78100576310273],"type":"Point"}
}