{
  "type": "Feature",
  "properties": {
    "iso:country":"GB",
    "wof:name":"NR30 2LF",
    "wof:placetype":"postalcode"
},
  "geometry": {"coordinates":[1.73434752695776,52.60487096129906],"type":"Point"}
}