{
  "type": "Feature",
  "properties": {
    "iso:country":"GB",
    "wof:name":"EH23 4PS",
    "wof:placetype":"postalcode"
},
  "geometry": {"coordinates":[-3.03985620866133,55.84684297067412],"type":"Point"}
}