{
  "type": "Feature",
  "properties": {
    "iso:country":"GB",
    "wof:name":"CA2 5SR",
    "wof:placetype":"postalcode"
},
  "geometry": {"coordinates":[-2.94484286645454,54.89552989347426],"type":"Point"}
}