{
  "type": "Feature",
  "properties": {
    "date:inception_lower": "2004-09-01",
    "date:inception_upper": "2004-09-01",
    "iso:country": "GB",
    "wof:name": "CA2 5SR",
    "wof:placetype": "postalcode"
  },
  "geometry": {"coordinates":[-2.945103,54.895831],"type":"Point"}
}
