{
  "type": "Feature",
  "properties": {
    "iso:country":"GB",
    "wof:name":"S75 5EF",
    "wof:placetype":"postalcode"
},
  "geometry": {"coordinates":[-1.54850433330635,53.58241762763919],"type":"Point"}
}