{
  "type": "Feature",
  "properties": {
    "iso:country": "GB",
    "wof:name": "NG12 5LH",
    "wof:placetype": "postalcode"
  },
  "geometry": {"coordinates":[-1.09531,52.875417],"type":"Point"}
}
