{
  "type": "Feature",
  "properties": {
    "iso:country": "GB",
    "wof:name": "PO21 4UD",
    "wof:placetype": "postalcode"
  },
  "geometry": {"coordinates":[-0.740253,50.773049],"type":"Point"}
}
