{
  "type": "Feature",
  "properties": {
    "iso:country":"GB",
    "wof:name":"PO21 4UD",
    "wof:placetype":"postalcode"
},
  "geometry": {"coordinates":[-0.74025280187364,50.77304888254813],"type":"Point"}
}