{
  "type": "Feature",
  "properties": {
    "date:inception_lower": "1980-01-01",
    "date:inception_upper": "1980-01-01",
    "iso:country": "GB",
    "wof:name": "B92 7JZ",
    "wof:placetype": "postalcode"
  },
  "geometry": {"coordinates":[-1.80372,52.445314],"type":"Point"}
}
