{
  "type": "Feature",
  "properties": {
    "iso:country":"GB",
    "wof:name":"E11 4LP",
    "wof:placetype":"postalcode"
},
  "geometry": {"coordinates":[0.00514285885791,51.55801538696713],"type":"Point"}
}