{
  "type": "Feature",
  "properties": {
    "date:inception_lower": "1980-01-01",
    "date:inception_upper": "1980-01-01",
    "iso:country": "GB",
    "wof:name": "BH19 3HW",
    "wof:placetype": "postalcode"
  },
  "geometry": {"coordinates":[-2.009303,50.608349],"type":"Point"}
}
