{
  "type": "Feature",
  "properties": {
    "date:inception_lower": "1985-10-01",
    "date:inception_upper": "1985-10-01",
    "iso:country": "GB",
    "wof:name": "BS3 4DG",
    "wof:placetype": "postalcode"
  },
  "geometry": {"coordinates":[-2.596959,51.441511],"type":"Point"}
}
