{
  "type": "Feature",
  "properties": {
    "iso:country":"GB",
    "wof:name":"DH4 7SL",
    "wof:placetype":"postalcode"
},
  "geometry": {"coordinates":[-1.51289288834527,54.87905306991922],"type":"Point"}
}