{
  "type": "Feature",
  "properties": {
    "iso:country":"GB",
    "wof:name":"EN8 0AJ",
    "wof:placetype":"postalcode"
},
  "geometry": {"coordinates":[-0.03443987355889,51.71017228843001],"type":"Point"}
}