{
  "type": "Feature",
  "properties": {
    "date:inception_lower":"1980-01-01",
    "date:inception_upper":"1980-01-31",
    "iso:country":"GB",
    "wof:name":"EN8 0AJ",
    "wof:placetype":"postalcode"
},
  "geometry": {"coordinates":[-0.03444,51.710172],"type":"Point"}
}