{
  "type": "Feature",
  "properties": {
    "iso:country":"GB",
    "wof:name":"NP25 4RL",
    "wof:placetype":"postalcode"
},
  "geometry": {"coordinates":[-2.73562976601849,51.77375711773828],"type":"Point"}
}