{
  "type": "Feature",
  "properties": {
    "date:inception_lower": "1999-06-01",
    "date:inception_upper": "1999-06-01",
    "iso:country": "GB",
    "wof:name": "NP25 4RL",
    "wof:placetype": "postalcode"
  },
  "geometry": {"coordinates":[-2.730057,51.77394],"type":"Point"}
}
