{
  "type": "Feature",
  "properties": {
    "iso:country":"GB",
    "wof:name":"M19 1JG",
    "wof:placetype":"postalcode"
},
  "geometry": {"coordinates":[-2.19804265217848,53.42761360538568],"type":"Point"}
}