{
  "type": "Feature",
  "properties": {
    "iso:country": "GB",
    "wof:name": "M19 1JG",
    "wof:placetype": "postalcode"
  },
  "geometry": {"coordinates":[-2.198043,53.427614],"type":"Point"}
}
