{
  "type": "Feature",
  "properties": {
    "date:inception_lower": "1992-01-01",
    "date:inception_upper": "1992-01-01",
    "iso:country": "GB",
    "wof:name": "M19 1JG",
    "wof:placetype": "postalcode"
  },
  "geometry": {"coordinates":[-2.198043,53.427614],"type":"Point"}
}
