{
  "type": "Feature",
  "properties": {
    "iso:country":"GB",
    "wof:name":"TN13 3BU",
    "wof:placetype":"postalcode"
},
  "geometry": {"coordinates":[0.19666337348773,51.27558502354308],"type":"Point"}
}