{
  "type": "Feature",
  "properties": {
    "date:inception_lower": "1999-06-01",
    "date:inception_upper": "1999-06-01",
    "iso:country": "GB",
    "wof:name": "TN13 3BU",
    "wof:placetype": "postalcode"
  },
  "geometry": {"coordinates":[0.196663,51.275585],"type":"Point"}
}
