{
  "type": "Feature",
  "properties": {
    "iso:country": "GB",
    "wof:name": "BS20 7BZ",
    "wof:placetype": "postalcode"
  },
  "geometry": {"coordinates":[-2.767942,51.486533],"type":"Point"}
}
