{
  "type": "Feature",
  "properties": {
    "iso:country":"GB",
    "wof:name":"RM14 2AE",
    "wof:placetype":"postalcode"
},
  "geometry": {"coordinates":[0.24459429104534,51.55296786516029],"type":"Point"}
}