{
  "type": "Feature",
  "properties": {
    "date:inception_lower": "1991-09-01",
    "date:inception_upper": "1991-09-01",
    "iso:country": "GB",
    "wof:name": "OX18 3LE",
    "wof:placetype": "postalcode"
  },
  "geometry": {"coordinates":[-1.603471,51.754614],"type":"Point"}
}
