{
  "type": "Feature",
  "properties": {
    "iso:country":"GB",
    "wof:name":"YO19 6HN",
    "wof:placetype":"postalcode"
},
  "geometry": {"coordinates":[-1.08949253400211,53.8789308341464],"type":"Point"}
}