{
  "type": "Feature",
  "properties": {
    "date:inception_lower": "2022-05-01",
    "date:inception_upper": "2022-05-01",
    "iso:country": "GB",
    "wof:name": "CW5 6YQ",
    "wof:placetype": "postalcode"
  },
  "geometry": {"coordinates":[-2.53389,53.076276],"type":"Point"}
}
