{
  "type": "Feature",
  "properties": {
    "iso:country": "GB",
    "wof:name": "LS25 6HY",
    "wof:placetype": "postalcode"
  },
  "geometry": {"coordinates":[-1.253645,53.796582],"type":"Point"}
}
