{
  "type": "Feature",
  "properties": {
    "date:inception_lower":"1984-10-01",
    "date:inception_upper":"1984-10-31",
    "iso:country":"GB",
    "wof:name":"LS25 6HY",
    "wof:placetype":"postalcode"
},
  "geometry": {"coordinates":[-1.253645,53.796582],"type":"Point"}
}