{
  "type": "Feature",
  "properties": {
    "iso:country":"GB",
    "wof:name":"OL8 4QF",
    "wof:placetype":"postalcode"
},
  "geometry": {"coordinates":[-2.1363565352368,53.52200691324657],"type":"Point"}
}