{
  "type": "Feature",
  "properties": {
    "iso:country":"GB",
    "wof:name":"TD3 6JW",
    "wof:placetype":"postalcode"
},
  "geometry": {"coordinates":[-2.56457094900054,55.67993369344666],"type":"Point"}
}