{
  "type": "Feature",
  "properties": {
    "iso:country":"GB",
    "wof:name":"B79 7UF",
    "wof:placetype":"postalcode"
},
  "geometry": {"coordinates":[-1.72569668725128,52.64228945104774],"type":"Point"}
}