{
  "type": "Feature",
  "properties": {
    "date:inception_lower": "1989-07-01",
    "date:inception_upper": "1989-07-01",
    "iso:country": "GB",
    "wof:name": "ML4 3HT",
    "wof:placetype": "postalcode"
  },
  "geometry": {"coordinates":[-4.038591,55.819759],"type":"Point"}
}
