{
  "type": "Feature",
  "properties": {
    "iso:country":"GB",
    "wof:name":"ML4 3HT",
    "wof:placetype":"postalcode"
},
  "geometry": {"coordinates":[-4.03859072488489,55.8197589117773],"type":"Point"}
}