{
  "type": "Feature",
  "properties": {
    "iso:country":"GB",
    "wof:name":"NW1 9PE",
    "wof:placetype":"postalcode"
},
  "geometry": {"coordinates":[-0.1396358303343,51.5418488873827],"type":"Point"}
}