{
  "type": "Feature",
  "properties": {
    "iso:country": "GB",
    "wof:name": "SP7 8FF",
    "wof:placetype": "postalcode"
  },
  "geometry": {"coordinates":[-2.182888,51.011359],"type":"Point"}
}
