{
  "type": "Feature",
  "properties": {
    "date:inception_lower":"2004-03-01",
    "date:inception_upper":"2004-03-31",
    "iso:country":"GB",
    "wof:name":"SP7 8FF",
    "wof:placetype":"postalcode"
},
  "geometry": {"coordinates":[-2.182888,51.011359],"type":"Point"}
}