{
  "type": "Feature",
  "properties": {
    "iso:country": "GB",
    "wof:name": "PO20 2AE",
    "wof:placetype": "postalcode"
  },
  "geometry": {"coordinates":[-0.724026,50.838575],"type":"Point"}
}
