{
  "type": "Feature",
  "properties": {
    "date:inception_lower":"1999-12-01",
    "date:inception_upper":"1999-12-31",
    "iso:country":"GB",
    "wof:name":"TW3 3LL",
    "wof:placetype":"postalcode"
},
  "geometry": {"coordinates":[-0.373285,51.466522],"type":"Point"}
}