{
  "type": "Feature",
  "properties": {
    "iso:country": "GB",
    "wof:name": "TW3 3LL",
    "wof:placetype": "postalcode"
  },
  "geometry": {"coordinates":[-0.373285,51.466522],"type":"Point"}
}
