{
  "type": "Feature",
  "properties": {
    "iso:country":"GB",
    "wof:name":"TW3 3LL",
    "wof:placetype":"postalcode"
},
  "geometry": {"coordinates":[-0.37328507628431,51.46652189857124],"type":"Point"}
}