{
  "type": "Feature",
  "properties": {
    "iso:country":"GB",
    "wof:name":"DD10 0TP",
    "wof:placetype":"postalcode"
},
  "geometry": {"coordinates":[-2.2850538687195,56.84499285297542],"type":"Point"}
}