{
  "type": "Feature",
  "properties": {
    "date:inception_lower": "2005-06-01",
    "date:inception_upper": "2005-06-01",
    "iso:country": "GB",
    "wof:name": "EX2 7QB",
    "wof:placetype": "postalcode"
  },
  "geometry": {"coordinates":[-3.478997,50.713901],"type":"Point"}
}
