{
  "type": "Feature",
  "properties": {
    "iso:country":"GB",
    "wof:name":"EX2 7QB",
    "wof:placetype":"postalcode"
},
  "geometry": {"coordinates":[-3.47899693978882,50.7139007783943],"type":"Point"}
}