{
  "type": "Feature",
  "properties": {
    "iso:country": "GB",
    "wof:name": "EX2 7QB",
    "wof:placetype": "postalcode"
  },
  "geometry": {"coordinates":[-3.478997,50.713901],"type":"Point"}
}
