{
  "type": "Feature",
  "properties": {
    "iso:country": "GB",
    "wof:name": "MK17 0SJ",
    "wof:placetype": "postalcode"
  },
  "geometry": {"coordinates":[-0.827996,51.938368],"type":"Point"}
}
