{
  "type": "Feature",
  "properties": {
    "iso:country": "GB",
    "wof:name": "HR4 7QP",
    "wof:placetype": "postalcode"
  },
  "geometry": {"coordinates":[-2.753963,52.086042],"type":"Point"}
}
