{
  "type": "Feature",
  "properties": {
    "iso:country":"GB",
    "wof:name":"HR4 7QP",
    "wof:placetype":"postalcode"
},
  "geometry": {"coordinates":[-2.75396346993496,52.08604178017713],"type":"Point"}
}