{
  "type": "Feature",
  "properties": {
    "date:inception_lower": "2001-12-01",
    "date:inception_upper": "2001-12-01",
    "iso:country": "GB",
    "wof:name": "HR4 7QP",
    "wof:placetype": "postalcode"
  },
  "geometry": {"coordinates":[-2.753963,52.086042],"type":"Point"}
}
