{
  "type": "Feature",
  "properties": {
    "iso:country":"GB",
    "wof:name":"LA8 8ET",
    "wof:placetype":"postalcode"
},
  "geometry": {"coordinates":[-2.81150831251871,54.2320416533637],"type":"Point"}
}