{
  "type": "Feature",
  "properties": {
    "date:inception_lower":"1980-01-01",
    "date:inception_upper":"1980-01-31",
    "iso:country":"GB",
    "wof:name":"LA8 8ET",
    "wof:placetype":"postalcode"
},
  "geometry": {"coordinates":[-2.811508,54.232042],"type":"Point"}
}