{
  "type": "Feature",
  "properties": {
    "iso:country": "GB",
    "wof:name": "YO13 9BA",
    "wof:placetype": "postalcode"
  },
  "geometry": {"coordinates":[-0.591853,54.210796],"type":"Point"}
}
