{
  "type": "Feature",
  "properties": {
    "iso:country":"GB",
    "wof:name":"YO13 9BA",
    "wof:placetype":"postalcode"
},
  "geometry": {"coordinates":[-0.59185283305994,54.21079565872999],"type":"Point"}
}