{
  "type": "Feature",
  "properties": {
    "date:inception_lower":"1990-07-01",
    "date:inception_upper":"1990-07-31",
    "iso:country":"GB",
    "wof:name":"BR1 3TN",
    "wof:placetype":"postalcode"
},
  "geometry": {"coordinates":[0.00881,51.408628],"type":"Point"}
}