{
  "type": "Feature",
  "properties": {
    "iso:country": "GB",
    "wof:name": "BR1 3TN",
    "wof:placetype": "postalcode"
  },
  "geometry": {"coordinates":[0.00881,51.408628],"type":"Point"}
}
