{
  "type": "Feature",
  "properties": {
    "iso:country": "GB",
    "wof:name": "HA8 9FA",
    "wof:placetype": "postalcode"
  },
  "geometry": {"coordinates":[-0.258967,51.611779],"type":"Point"}
}
