{
  "type": "Feature",
  "properties": {
    "iso:country": "GB",
    "wof:name": "LL14 4EB",
    "wof:placetype": "postalcode"
  },
  "geometry": {"coordinates":[-3.026423,53.029161],"type":"Point"}
}
