{
  "type": "Feature",
  "properties": {
    "iso:country":"GB",
    "wof:name":"WV16 6RJ",
    "wof:placetype":"postalcode"
},
  "geometry": {"coordinates":[-2.53692255980421,52.48652813379429],"type":"Point"}
}