{
  "type": "Feature",
  "properties": {
    "iso:country": "GB",
    "wof:name": "WV16 6RJ",
    "wof:placetype": "postalcode"
  },
  "geometry": {"coordinates":[-2.536923,52.486528],"type":"Point"}
}
