{
  "type": "Feature",
  "properties": {
    "date:inception_lower": "1980-01-01",
    "date:inception_upper": "1980-01-01",
    "iso:country": "GB",
    "wof:name": "BB7 3LX",
    "wof:placetype": "postalcode"
  },
  "geometry": {"coordinates":[-2.51287,53.876598],"type":"Point"}
}
