{
  "type": "Feature",
  "properties": {
    "iso:country":"GB",
    "wof:name":"BB7 3LX",
    "wof:placetype":"postalcode"
},
  "geometry": {"coordinates":[-2.51261028111016,53.87651375557567],"type":"Point"}
}