{
  "type": "Feature",
  "properties": {
    "iso:country":"GB",
    "wof:name":"NW6 4RG",
    "wof:placetype":"postalcode"
},
  "geometry": {"coordinates":[-0.1774044574869,51.5436557029422],"type":"Point"}
}