{
  "type": "Feature",
  "properties": {
    "date:inception_lower": "2008-01-01",
    "date:inception_upper": "2008-01-01",
    "iso:country": "GB",
    "wof:name": "HD7 4HG",
    "wof:placetype": "postalcode"
  },
  "geometry": {"coordinates":[-1.855608,53.63606],"type":"Point"}
}
