{
  "type": "Feature",
  "properties": {
    "iso:country":"GB",
    "wof:name":"HD7 4HG",
    "wof:placetype":"postalcode"
},
  "geometry": {"coordinates":[-1.85560756171123,53.63605954968733],"type":"Point"}
}