{
  "type": "Feature",
  "properties": {
    "iso:country":"GB",
    "wof:name":"N19 3RD",
    "wof:placetype":"postalcode"
},
  "geometry": {"coordinates":[-0.13314825274991,51.5689300268614],"type":"Point"}
}