{
  "type": "Feature",
  "properties": {
    "date:inception_lower": "1990-08-01",
    "date:inception_upper": "1990-08-01",
    "iso:country": "GB",
    "wof:name": "AB51 0HG",
    "wof:placetype": "postalcode"
  },
  "geometry": {"coordinates":[-2.348436,57.301205],"type":"Point"}
}
