{
  "type": "Feature",
  "properties": {
    "date:inception_lower": "2022-09-01",
    "date:inception_upper": "2022-09-01",
    "iso:country": "GB",
    "wof:name": "RG6 9UP",
    "wof:placetype": "postalcode"
  },
  "geometry": {"coordinates":[-0.945616,51.457626],"type":"Point"}
}
