{
  "type": "Feature",
  "properties": {
    "date:inception_lower": "2004-05-01",
    "date:inception_upper": "2004-05-01",
    "iso:country": "GB",
    "wof:name": "LE2 6FX",
    "wof:placetype": "postalcode"
  },
  "geometry": {"coordinates":[-1.121384,52.605117],"type":"Point"}
}
