{
  "type": "Feature",
  "properties": {
    "iso:country":"GB",
    "wof:name":"BH21 1DG",
    "wof:placetype":"postalcode"
},
  "geometry": {"coordinates":[-1.98098838074555,50.80540427047553],"type":"Point"}
}