{
  "type": "Feature",
  "properties": {
    "iso:country": "GB",
    "wof:name": "RM12 4HE",
    "wof:placetype": "postalcode"
  },
  "geometry": {"coordinates":[0.193305,51.55821],"type":"Point"}
}
