{
  "type": "Feature",
  "properties": {
    "iso:country":"GB",
    "wof:name":"RM17 5TA",
    "wof:placetype":"postalcode"
},
  "geometry": {"coordinates":[0.34534244028844,51.4859314563903],"type":"Point"}
}