{
  "type": "Feature",
  "properties": {
    "iso:country":"GB",
    "wof:name":"PR3 5BB",
    "wof:placetype":"postalcode"
},
  "geometry": {"coordinates":[-2.73505824798563,53.83198063310267],"type":"Point"}
}