{
  "type": "Feature",
  "properties": {
    "date:inception_lower":"1980-01-01",
    "date:inception_upper":"1980-01-31",
    "iso:country":"GB",
    "wof:name":"PR3 5BB",
    "wof:placetype":"postalcode"
},
  "geometry": {"coordinates":[-2.735058,53.831981],"type":"Point"}
}