{
  "type": "Feature",
  "properties": {
    "iso:country": "GB",
    "wof:name": "SY7 9QA",
    "wof:placetype": "postalcode"
  },
  "geometry": {"coordinates":[-2.840288,52.447021],"type":"Point"}
}
