{
  "type": "Feature",
  "properties": {
    "iso:country":"GB",
    "wof:name":"W1W 8HG",
    "wof:placetype":"postalcode"
},
  "geometry": {"coordinates":[-0.13882298240545,51.51617143749102],"type":"Point"}
}