{
  "type": "Feature",
  "properties": {
    "iso:country":"GB",
    "wof:name":"NW9 8HG",
    "wof:placetype":"postalcode"
},
  "geometry": {"coordinates":[-0.26716102791983,51.57257713533978],"type":"Point"}
}