{
  "type": "Feature",
  "properties": {
    "iso:country":"GB",
    "wof:name":"TR16 6PS",
    "wof:placetype":"postalcode"
},
  "geometry": {"coordinates":[-5.24004894433033,50.18129242495932],"type":"Point"}
}