{
  "type": "Feature",
  "properties": {
    "iso:country":"GB",
    "wof:name":"CM8 1XQ",
    "wof:placetype":"postalcode"
},
  "geometry": {"coordinates":[0.64669445998711,51.7927026666978],"type":"Point"}
}