{
  "type": "Feature",
  "properties": {
    "date:inception_lower":"2016-05-01",
    "date:inception_upper":"2016-05-31",
    "iso:country":"GB",
    "wof:name":"NG22 9WJ",
    "wof:placetype":"postalcode"
},
  "geometry": {"coordinates":[-1.003505,53.206414],"type":"Point"}
}