{
  "type": "Feature",
  "properties": {
    "iso:country": "GB",
    "wof:name": "NG22 9WJ",
    "wof:placetype": "postalcode"
  },
  "geometry": {"coordinates":[-1.003505,53.206414],"type":"Point"}
}
