{
  "type": "Feature",
  "properties": {
    "iso:country":"GB",
    "wof:name":"HU8 9EL",
    "wof:placetype":"postalcode"
},
  "geometry": {"coordinates":[-0.27352573486066,53.77416194080775],"type":"Point"}
}