{
  "type": "Feature",
  "properties": {
    "iso:country": "GB",
    "wof:name": "BA9 9BQ",
    "wof:placetype": "postalcode"
  },
  "geometry": {"coordinates":[-2.415791,51.056127],"type":"Point"}
}
