{
  "type": "Feature",
  "properties": {
    "iso:country":"GB",
    "wof:name":"LE6 0BH",
    "wof:placetype":"postalcode"
},
  "geometry": {"coordinates":[-1.2333889065153,52.66085894565126],"type":"Point"}
}