{
  "type": "Feature",
  "properties": {
    "iso:country": "GB",
    "wof:name": "PL28 8PH",
    "wof:placetype": "postalcode"
  },
  "geometry": {"coordinates":[-4.995812,50.52444],"type":"Point"}
}
