{
  "type": "Feature",
  "properties": {
    "date:inception_lower": "1980-01-01",
    "date:inception_upper": "1980-01-01",
    "iso:country": "GB",
    "wof:name": "PL28 8PH",
    "wof:placetype": "postalcode"
  },
  "geometry": {"coordinates":[-4.995812,50.52444],"type":"Point"}
}
