{
  "type": "Feature",
  "properties": {
    "date:inception_lower":"2011-09-01",
    "date:inception_upper":"2011-09-30",
    "iso:country":"GB",
    "wof:name":"W3 9AY",
    "wof:placetype":"postalcode"
},
  "geometry": {"coordinates":[-0.2835,51.506562],"type":"Point"}
}