{
  "type": "Feature",
  "properties": {
    "iso:country":"GB",
    "wof:name":"GU9 8JD",
    "wof:placetype":"postalcode"
},
  "geometry": {"coordinates":[-0.79393393720611,51.20299807322178],"type":"Point"}
}