{
  "type": "Feature",
  "properties": {
    "date:inception_lower": "1980-01-01",
    "date:inception_upper": "1980-01-01",
    "iso:country": "GB",
    "wof:name": "GU34 3RT",
    "wof:placetype": "postalcode"
  },
  "geometry": {"coordinates":[-1.021387,51.07966],"type":"Point"}
}
