{
  "type": "Feature",
  "properties": {
    "iso:country":"GB",
    "wof:name":"SM3 9PS",
    "wof:placetype":"postalcode"
},
  "geometry": {"coordinates":[-0.20123016905721,51.38106117627537],"type":"Point"}
}