{
  "type": "Feature",
  "properties": {
    "date:inception_lower": "2019-06-01",
    "date:inception_upper": "2019-06-01",
    "iso:country": "GB",
    "wof:name": "AB43 8ZH",
    "wof:placetype": "postalcode"
  },
  "geometry": {"coordinates":[-1.937557,57.674891],"type":"Point"}
}
