{
  "type": "Feature",
  "properties": {
    "iso:country":"GB",
    "wof:name":"M9 8BL",
    "wof:placetype":"postalcode"
},
  "geometry": {"coordinates":[-2.21518247727377,53.51654277053094],"type":"Point"}
}