{
  "type": "Feature",
  "properties": {
    "iso:country":"GB",
    "wof:name":"PL14 6RL",
    "wof:placetype":"postalcode"
},
  "geometry": {"coordinates":[-4.46644312207515,50.47736722071869],"type":"Point"}
}