{
  "type": "Feature",
  "properties": {
    "iso:country": "GB",
    "wof:name": "CO9 1DF",
    "wof:placetype": "postalcode"
  },
  "geometry": {"coordinates":[0.62964,51.938864],"type":"Point"}
}
