{
  "type": "Feature",
  "properties": {
    "iso:country":"GB",
    "wof:name":"CO9 1DF",
    "wof:placetype":"postalcode"
},
  "geometry": {"coordinates":[0.62964016032508,51.93886437322521],"type":"Point"}
}