{
  "type": "Feature",
  "properties": {
    "date:inception_lower": "1996-06-01",
    "date:inception_upper": "1996-06-01",
    "iso:country": "GB",
    "wof:name": "AB55 5HS",
    "wof:placetype": "postalcode"
  },
  "geometry": {"coordinates":[-2.965927,57.536812],"type":"Point"}
}
