{
  "type": "Feature",
  "properties": {
    "iso:country":"GB",
    "wof:name":"AB55 5HS",
    "wof:placetype":"postalcode"
},
  "geometry": {"coordinates":[-2.96592738107582,57.53681214212126],"type":"Point"}
}