{
  "type": "Feature",
  "properties": {
    "iso:country": "GB",
    "wof:name": "DN15 8FD",
    "wof:placetype": "postalcode"
  },
  "geometry": {"coordinates":[-0.663874,53.594241],"type":"Point"}
}
