{
  "type": "Feature",
  "properties": {
    "iso:country":"GB",
    "wof:name":"CM16 6BP",
    "wof:placetype":"postalcode"
},
  "geometry": {"coordinates":[0.15990623031537,51.71148968683546],"type":"Point"}
}