{
  "type": "Feature",
  "properties": {
    "iso:country":"GB",
    "wof:name":"CB4 0WN",
    "wof:placetype":"postalcode"
},
  "geometry": {"coordinates":[0.14231579494118,52.23394656590169],"type":"Point"}
}