{
  "type": "Feature",
  "properties": {
    "iso:country": "GB",
    "wof:name": "CB4 0WN",
    "wof:placetype": "postalcode"
  },
  "geometry": {"coordinates":[0.142316,52.233947],"type":"Point"}
}
