{
  "type": "Feature",
  "properties": {
    "iso:country":"GB",
    "wof:name":"ME12 4LH",
    "wof:placetype":"postalcode"
},
  "geometry": {"coordinates":[0.91504139479668,51.39881064813365],"type":"Point"}
}