{
  "type": "Feature",
  "properties": {
    "date:inception_lower": "1980-01-01",
    "date:inception_upper": "1980-01-01",
    "iso:country": "GB",
    "wof:name": "ST13 7AY",
    "wof:placetype": "postalcode"
  },
  "geometry": {"coordinates":[-2.029245,53.079729],"type":"Point"}
}
