{
  "type": "Feature",
  "properties": {
    "iso:country":"GB",
    "wof:name":"CM3 3EW",
    "wof:placetype":"postalcode"
},
  "geometry": {"coordinates":[0.55845784515967,51.75474521104125],"type":"Point"}
}