{
  "type": "Feature",
  "properties": {
    "date:inception_lower": "1980-01-01",
    "date:inception_upper": "1980-01-01",
    "iso:country": "GB",
    "wof:name": "TQ9 7SG",
    "wof:placetype": "postalcode"
  },
  "geometry": {"coordinates":[-3.722375,50.414108],"type":"Point"}
}
