{
  "type": "Feature",
  "properties": {
    "iso:country":"GB",
    "wof:name":"TQ9 7SG",
    "wof:placetype":"postalcode"
},
  "geometry": {"coordinates":[-3.72237514824289,50.41410783195541],"type":"Point"}
}