{
  "type": "Feature",
  "properties": {
    "iso:country":"GB",
    "wof:name":"BN45 7FF",
    "wof:placetype":"postalcode"
},
  "geometry": {"coordinates":[-0.15990897762922,50.90196489021171],"type":"Point"}
}