{
  "type": "Feature",
  "properties": {
    "iso:country":"GB",
    "wof:name":"SA73 1HL",
    "wof:placetype":"postalcode"
},
  "geometry": {"coordinates":[-4.98851618743209,51.72382834731473],"type":"Point"}
}