{
  "type": "Feature",
  "properties": {
    "date:inception_lower": "1980-01-01",
    "date:inception_upper": "1980-01-01",
    "iso:country": "GB",
    "wof:name": "TF9 3AT",
    "wof:placetype": "postalcode"
  },
  "geometry": {"coordinates":[-2.490637,52.90606],"type":"Point"}
}
