{
  "type": "Feature",
  "properties": {
    "iso:country":"GB",
    "wof:name":"SR4 8NR",
    "wof:placetype":"postalcode"
},
  "geometry": {"coordinates":[-1.43160399407465,54.89416583181064],"type":"Point"}
}