{
  "type": "Feature",
  "properties": {
    "iso:country":"GB",
    "wof:name":"AL7 1DW",
    "wof:placetype":"postalcode"
},
  "geometry": {"coordinates":[-0.19292635462805,51.81641389370347],"type":"Point"}
}