{
  "type": "Feature",
  "properties": {
    "date:inception_lower": "1980-01-01",
    "date:inception_upper": "1980-01-01",
    "iso:country": "GB",
    "wof:name": "AL7 1DW",
    "wof:placetype": "postalcode"
  },
  "geometry": {"coordinates":[-0.192902,51.81643],"type":"Point"}
}
