{
  "type": "Feature",
  "properties": {
    "iso:country": "GB",
    "wof:name": "AL7 1DW",
    "wof:placetype": "postalcode"
  },
  "geometry": {"coordinates":[-0.192926,51.816414],"type":"Point"}
}
