{
  "type": "Feature",
  "properties": {
    "date:inception_lower": "1980-01-01",
    "date:inception_upper": "1980-01-01",
    "iso:country": "GB",
    "wof:name": "IG6 2AJ",
    "wof:placetype": "postalcode"
  },
  "geometry": {"coordinates":[0.083941,51.592777],"type":"Point"}
}
