{
  "type": "Feature",
  "properties": {
    "iso:country":"GB",
    "wof:name":"NG10 3RX",
    "wof:placetype":"postalcode"
},
  "geometry": {"coordinates":[-1.29186280825665,52.89211377238831],"type":"Point"}
}