{
  "type": "Feature",
  "properties": {
    "date:inception_lower": "1998-06-01",
    "date:inception_upper": "1998-06-01",
    "iso:country": "GB",
    "wof:name": "NG10 3RX",
    "wof:placetype": "postalcode"
  },
  "geometry": {"coordinates":[-1.291863,52.892114],"type":"Point"}
}
