{
  "type": "Feature",
  "properties": {
    "iso:country":"GB",
    "wof:name":"WV16 5BW",
    "wof:placetype":"postalcode"
},
  "geometry": {"coordinates":[-2.4305459226815,52.53395388097498],"type":"Point"}
}