{
  "type": "Feature",
  "properties": {
    "date:inception_lower": "1998-06-01",
    "date:inception_upper": "1998-06-01",
    "iso:country": "GB",
    "wof:name": "YO26 6JH",
    "wof:placetype": "postalcode"
  },
  "geometry": {"coordinates":[-1.150199,53.985982],"type":"Point"}
}
