{
  "type": "Feature",
  "properties": {
    "iso:country":"GB",
    "wof:name":"EH48 1EF",
    "wof:placetype":"postalcode"
},
  "geometry": {"coordinates":[-3.63215930717625,55.89709516032072],"type":"Point"}
}