{
  "type": "Feature",
  "properties": {
    "iso:country":"GB",
    "wof:name":"BH1 3PE",
    "wof:placetype":"postalcode"
},
  "geometry": {"coordinates":[-1.85825350870459,50.72303763017244],"type":"Point"}
}