{
  "type": "Feature",
  "properties": {
    "date:inception_lower":"1980-01-01",
    "date:inception_upper":"1980-01-31",
    "iso:country":"GB",
    "wof:name":"BH1 3PE",
    "wof:placetype":"postalcode"
},
  "geometry": {"coordinates":[-1.858253,50.723038],"type":"Point"}
}