{
  "type": "Feature",
  "properties": {
    "iso:country": "GB",
    "wof:name": "YO7 3LT",
    "wof:placetype": "postalcode"
  },
  "geometry": {"coordinates":[-1.416546,54.153465],"type":"Point"}
}
