{
  "type": "Feature",
  "properties": {
    "iso:country":"GB",
    "wof:name":"MK43 8EN",
    "wof:placetype":"postalcode"
},
  "geometry": {"coordinates":[-0.62667379398143,52.16216007523205],"type":"Point"}
}