{
  "type": "Feature",
  "properties": {
    "iso:country":"GB",
    "wof:name":"AB53 4EA",
    "wof:placetype":"postalcode"
},
  "geometry": {"coordinates":[-2.46184342843702,57.53730080777684],"type":"Point"}
}