{
  "type": "Feature",
  "properties": {
    "date:inception_lower": "1999-12-01",
    "date:inception_upper": "1999-12-01",
    "iso:country": "GB",
    "wof:name": "L5 9RG",
    "wof:placetype": "postalcode"
  },
  "geometry": {"coordinates":[-2.991571,53.422402],"type":"Point"}
}
