{
  "type": "Feature",
  "properties": {
    "iso:country": "GB",
    "wof:name": "EX21 5SQ",
    "wof:placetype": "postalcode"
  },
  "geometry": {"coordinates":[-4.212708,50.862092],"type":"Point"}
}
