{
  "type": "Feature",
  "properties": {
    "iso:country":"GB",
    "wof:name":"NE24 5EX",
    "wof:placetype":"postalcode"
},
  "geometry": {"coordinates":[-1.52328463688626,55.13000844168236],"type":"Point"}
}