{
  "type": "Feature",
  "properties": {
    "iso:country": "GB",
    "wof:name": "NE24 5EX",
    "wof:placetype": "postalcode"
  },
  "geometry": {"coordinates":[-1.523285,55.130008],"type":"Point"}
}
