{
  "type": "Feature",
  "properties": {
    "iso:country":"GB",
    "wof:name":"TR3 6RN",
    "wof:placetype":"postalcode"
},
  "geometry": {"coordinates":[-5.05386298678113,50.20610516979227],"type":"Point"}
}