{
  "type": "Feature",
  "properties": {
    "iso:country": "GB",
    "wof:name": "NG12 5QL",
    "wof:placetype": "postalcode"
  },
  "geometry": {"coordinates":[-1.032556,52.853706],"type":"Point"}
}
