{
  "type": "Feature",
  "properties": {
    "iso:country":"GB",
    "wof:name":"NG12 5QL",
    "wof:placetype":"postalcode"
},
  "geometry": {"coordinates":[-1.03255653505725,52.85370629103996],"type":"Point"}
}