{
  "type": "Feature",
  "properties": {
    "date:inception_lower": "1980-01-01",
    "date:inception_upper": "1980-01-01",
    "iso:country": "GB",
    "wof:name": "L29 5XA",
    "wof:placetype": "postalcode"
  },
  "geometry": {"coordinates":[-3.011619,53.511241],"type":"Point"}
}
