{
  "type": "Feature",
  "properties": {
    "iso:country": "GB",
    "wof:name": "HP16 0SS",
    "wof:placetype": "postalcode"
  },
  "geometry": {"coordinates":[-0.737146,51.693031],"type":"Point"}
}
