{
  "type": "Feature",
  "properties": {
    "date:inception_lower":"1991-09-01",
    "date:inception_upper":"1991-09-30",
    "iso:country":"GB",
    "wof:name":"DN15 8EN",
    "wof:placetype":"postalcode"
},
  "geometry": {"coordinates":[-0.676916,53.60125],"type":"Point"}
}