{
  "type": "Feature",
  "properties": {
    "iso:country":"GB",
    "wof:name":"DN15 8EN",
    "wof:placetype":"postalcode"
},
  "geometry": {"coordinates":[-0.67691651821006,53.60125019708381],"type":"Point"}
}