{
  "type": "Feature",
  "properties": {
    "iso:country": "GB",
    "wof:name": "SY6 6DN",
    "wof:placetype": "postalcode"
  },
  "geometry": {"coordinates":[-2.808756,52.539273],"type":"Point"}
}
