{
  "type": "Feature",
  "properties": {
    "iso:country": "GB",
    "wof:name": "WS15 4ED",
    "wof:placetype": "postalcode"
  },
  "geometry": {"coordinates":[-1.854609,52.749674],"type":"Point"}
}
