{
  "type": "Feature",
  "properties": {
    "iso:country":"GB",
    "wof:name":"WS15 4ED",
    "wof:placetype":"postalcode"
},
  "geometry": {"coordinates":[-1.85460909462308,52.74967390236121],"type":"Point"}
}