{
  "type": "Feature",
  "properties": {
    "iso:country":"GB",
    "wof:name":"SN8 3LH",
    "wof:placetype":"postalcode"
},
  "geometry": {"coordinates":[-1.63740478445353,51.39465432158408],"type":"Point"}
}