{
  "type": "Feature",
  "properties": {
    "iso:country": "GB",
    "wof:name": "OX26 1BA",
    "wof:placetype": "postalcode"
  },
  "geometry": {"coordinates":[-1.188845,51.885427],"type":"Point"}
}
