{
  "type": "Feature",
  "properties": {
    "iso:country":"GB",
    "wof:name":"L17 7EU",
    "wof:placetype":"postalcode"
},
  "geometry": {"coordinates":[-2.96667661185299,53.37710391048645],"type":"Point"}
}