{
  "type": "Feature",
  "properties": {
    "iso:country": "GB",
    "wof:name": "BA11 3LQ",
    "wof:placetype": "postalcode"
  },
  "geometry": {"coordinates":[-2.408743,51.219794],"type":"Point"}
}
