{
  "type": "Feature",
  "properties": {
    "iso:country":"GB",
    "wof:name":"BA11 3LQ",
    "wof:placetype":"postalcode"
},
  "geometry": {"coordinates":[-2.40874477766983,51.21979880410401],"type":"Point"}
}