{
  "type": "Feature",
  "properties": {
    "date:inception_lower": "1980-01-01",
    "date:inception_upper": "1980-01-01",
    "iso:country": "GB",
    "wof:name": "BA11 3LQ",
    "wof:placetype": "postalcode"
  },
  "geometry": {"coordinates":[-2.408743,51.219794],"type":"Point"}
}
