{
  "type": "Feature",
  "properties": {
    "date:inception_lower": "2022-10-01",
    "date:inception_upper": "2022-10-01",
    "iso:country": "GB",
    "wof:name": "BA5 2NY",
    "wof:placetype": "postalcode"
  },
  "geometry": {"coordinates":[-2.669177,51.213963],"type":"Point"}
}
