{
  "type": "Feature",
  "properties": {
    "iso:country":"GB",
    "wof:name":"NP26 4QD",
    "wof:placetype":"postalcode"
},
  "geometry": {"coordinates":[-2.76448430859278,51.59163265465698],"type":"Point"}
}