{
  "type": "Feature",
  "properties": {
    "iso:country": "GB",
    "wof:name": "DN36 5JZ",
    "wof:placetype": "postalcode"
  },
  "geometry": {"coordinates":[-0.009448,53.491285],"type":"Point"}
}
