{
  "type": "Feature",
  "properties": {
    "iso:country":"GB",
    "wof:name":"G33 1JQ",
    "wof:placetype":"postalcode"
},
  "geometry": {"coordinates":[-4.19184473538425,55.88399693701545],"type":"Point"}
}