{
  "type": "Feature",
  "properties": {
    "iso:country":"GB",
    "wof:name":"DH3 1GJ",
    "wof:placetype":"postalcode"
},
  "geometry": {"coordinates":[-1.57115766341332,54.9049197731109],"type":"Point"}
}