{
  "type": "Feature",
  "properties": {
    "date:inception_lower": "2012-12-01",
    "date:inception_upper": "2012-12-01",
    "iso:country": "GB",
    "wof:name": "DH3 1GJ",
    "wof:placetype": "postalcode"
  },
  "geometry": {"coordinates":[-1.571158,54.90492],"type":"Point"}
}
