{
  "type": "Feature",
  "properties": {
    "iso:country": "GB",
    "wof:name": "EH1 2AN",
    "wof:placetype": "postalcode"
  },
  "geometry": {"coordinates":[-3.208239,55.94907],"type":"Point"}
}
