{
  "type": "Feature",
  "properties": {
    "iso:country": "GB",
    "wof:name": "LA22 0PS",
    "wof:placetype": "postalcode"
  },
  "geometry": {"coordinates":[-3.017808,54.384738],"type":"Point"}
}
