{
  "type": "Feature",
  "properties": {
    "iso:country":"GB",
    "wof:name":"LA22 0PS",
    "wof:placetype":"postalcode"
},
  "geometry": {"coordinates":[-3.01518336846912,54.38457278850256],"type":"Point"}
}