{
  "type": "Feature",
  "properties": {
    "iso:country":"GB",
    "wof:name":"TW7 4PL",
    "wof:placetype":"postalcode"
},
  "geometry": {"coordinates":[-0.34497606951035,51.48057643470413],"type":"Point"}
}