{
  "type": "Feature",
  "properties": {
    "iso:country":"GB",
    "wof:name":"BS7 0BW",
    "wof:placetype":"postalcode"
},
  "geometry": {"coordinates":[-2.58476719662748,51.49065730104362],"type":"Point"}
}