{
  "type": "Feature",
  "properties": {
    "date:inception_lower": "1980-01-01",
    "date:inception_upper": "1980-01-01",
    "iso:country": "GB",
    "wof:name": "NE35 9HL",
    "wof:placetype": "postalcode"
  },
  "geometry": {"coordinates":[-1.465618,54.955922],"type":"Point"}
}
