{
  "type": "Feature",
  "properties": {
    "iso:country":"GB",
    "wof:name":"BA1 5AQ",
    "wof:placetype":"postalcode"
},
  "geometry": {"coordinates":[-2.35946500209399,51.38190314238435],"type":"Point"}
}