{
  "type": "Feature",
  "properties": {
    "iso:country":"GB",
    "wof:name":"SN10 4AU",
    "wof:placetype":"postalcode"
},
  "geometry": {"coordinates":[-1.97987574843455,51.28587352604325],"type":"Point"}
}