{
  "type": "Feature",
  "properties": {
    "iso:country":"GB",
    "wof:name":"LS26 0PW",
    "wof:placetype":"postalcode"
},
  "geometry": {"coordinates":[-1.49374445703925,53.75597747512528],"type":"Point"}
}