{
  "type": "Feature",
  "properties": {
    "iso:country":"GB",
    "wof:name":"DY7 5LR",
    "wof:placetype":"postalcode"
},
  "geometry": {"coordinates":[-2.23953452189607,52.46417554986164],"type":"Point"}
}