{
  "type": "Feature",
  "properties": {
    "iso:country": "GB",
    "wof:name": "DY7 5LR",
    "wof:placetype": "postalcode"
  },
  "geometry": {"coordinates":[-2.239534,52.464176],"type":"Point"}
}
