{
  "type": "Feature",
  "properties": {
    "iso:country":"GB",
    "wof:name":"B65 0AN",
    "wof:placetype":"postalcode"
},
  "geometry": {"coordinates":[-2.04351741551392,52.47253742967233],"type":"Point"}
}