{
  "type": "Feature",
  "properties": {
    "date:inception_lower": "1994-05-01",
    "date:inception_upper": "1994-05-01",
    "iso:country": "GB",
    "wof:name": "M11 2BD",
    "wof:placetype": "postalcode"
  },
  "geometry": {"coordinates":[-2.19325,53.475836],"type":"Point"}
}
