{
  "type": "Feature",
  "properties": {
    "iso:country":"GB",
    "wof:name":"M11 2BD",
    "wof:placetype":"postalcode"
},
  "geometry": {"coordinates":[-2.19325022902163,53.47583574386777],"type":"Point"}
}