{
  "type": "Feature",
  "properties": {
    "iso:country":"GB",
    "wof:name":"HG5 0NJ",
    "wof:placetype":"postalcode"
},
  "geometry": {"coordinates":[-1.46559361016693,54.0162359991247],"type":"Point"}
}