{
  "type": "Feature",
  "properties": {
    "iso:country":"GB",
    "wof:name":"CO15 6EF",
    "wof:placetype":"postalcode"
},
  "geometry": {"coordinates":[1.16547594562843,51.79666298252462],"type":"Point"}
}