{
  "type": "Feature",
  "properties": {
    "date:inception_lower":"2004-07-01",
    "date:inception_upper":"2004-07-31",
    "iso:country":"GB",
    "wof:name":"WA13 9GB",
    "wof:placetype":"postalcode"
},
  "geometry": {"coordinates":[-2.497419,53.384702],"type":"Point"}
}