{
  "type": "Feature",
  "properties": {
    "iso:country":"GB",
    "wof:name":"M40 1EN",
    "wof:placetype":"postalcode"
},
  "geometry": {"coordinates":[-2.17828740769797,53.5041366460776],"type":"Point"}
}