{
  "type": "Feature",
  "properties": {
    "iso:country":"GB",
    "wof:name":"LS9 8NL",
    "wof:placetype":"postalcode"
},
  "geometry": {"coordinates":[-1.52115327944121,53.79311195408186],"type":"Point"}
}