{
  "type": "Feature",
  "properties": {
    "iso:country":"GB",
    "wof:name":"NR31 9LY",
    "wof:placetype":"postalcode"
},
  "geometry": {"coordinates":[1.65581880008327,52.55978733084592],"type":"Point"}
}