{
  "type": "Feature",
  "properties": {
    "iso:country": "GB",
    "wof:name": "NR31 9LY",
    "wof:placetype": "postalcode"
  },
  "geometry": {"coordinates":[1.655819,52.559787],"type":"Point"}
}
