{
  "type": "Feature",
  "properties": {
    "iso:country":"GB",
    "wof:name":"CA2 4NR",
    "wof:placetype":"postalcode"
},
  "geometry": {"coordinates":[-2.91780024012576,54.86992737828063],"type":"Point"}
}