{
  "type": "Feature",
  "properties": {
    "iso:country": "GB",
    "wof:name": "TN23 5TY",
    "wof:placetype": "postalcode"
  },
  "geometry": {"coordinates":[0.84974,51.132255],"type":"Point"}
}
