{
  "type": "Feature",
  "properties": {
    "iso:country":"GB",
    "wof:name":"SL4 5DS",
    "wof:placetype":"postalcode"
},
  "geometry": {"coordinates":[-0.61213397782486,51.4805174324477],"type":"Point"}
}