{
  "type": "Feature",
  "properties": {
    "iso:country":"GB",
    "wof:name":"KT24 6BG",
    "wof:placetype":"postalcode"
},
  "geometry": {"coordinates":[-0.45651646872776,51.26516546571371],"type":"Point"}
}