{
  "type": "Feature",
  "properties": {
    "iso:country":"GB",
    "wof:name":"G72 8PZ",
    "wof:placetype":"postalcode"
},
  "geometry": {"coordinates":[-4.15972350557728,55.81205567856389],"type":"Point"}
}