{
  "type": "Feature",
  "properties": {
    "iso:country":"GB",
    "wof:name":"NP7 9EH",
    "wof:placetype":"postalcode"
},
  "geometry": {"coordinates":[-2.98901684614575,51.75769152530534],"type":"Point"}
}