{
  "type": "Feature",
  "properties": {
    "date:inception_lower": "1992-10-01",
    "date:inception_upper": "1992-10-01",
    "iso:country": "GB",
    "wof:name": "PA16 8JE",
    "wof:placetype": "postalcode"
  },
  "geometry": {"coordinates":[-4.766173,55.953709],"type":"Point"}
}
