{
  "type": "Feature",
  "properties": {
    "iso:country":"GB",
    "wof:name":"PA16 8JE",
    "wof:placetype":"postalcode"
},
  "geometry": {"coordinates":[-4.76617343169409,55.95370905851072],"type":"Point"}
}