{
  "type": "Feature",
  "properties": {
    "iso:country": "GB",
    "wof:name": "NE66 2XH",
    "wof:placetype": "postalcode"
  },
  "geometry": {"coordinates":[-1.679936,55.369824],"type":"Point"}
}
