{
  "type": "Feature",
  "properties": {
    "iso:country":"GB",
    "wof:name":"NN14 3HF",
    "wof:placetype":"postalcode"
},
  "geometry": {"coordinates":[-0.60675463767104,52.45627019141236],"type":"Point"}
}