{
  "type": "Feature",
  "properties": {
    "date:inception_lower":"1980-01-01",
    "date:inception_upper":"1980-01-31",
    "iso:country":"GB",
    "wof:name":"NN14 3HF",
    "wof:placetype":"postalcode"
},
  "geometry": {"coordinates":[-0.606755,52.45627],"type":"Point"}
}