{
  "type": "Feature",
  "properties": {
    "iso:country": "GB",
    "wof:name": "DN32 8QH",
    "wof:placetype": "postalcode"
  },
  "geometry": {"coordinates":[-0.055694,53.553715],"type":"Point"}
}
