{
  "type": "Feature",
  "properties": {
    "iso:country":"GB",
    "wof:name":"LN9 5LX",
    "wof:placetype":"postalcode"
},
  "geometry": {"coordinates":[-0.12247460817388,53.22093238731519],"type":"Point"}
}