{
  "type": "Feature",
  "properties": {
    "iso:country": "GB",
    "wof:name": "LN9 5LX",
    "wof:placetype": "postalcode"
  },
  "geometry": {"coordinates":[-0.122475,53.220932],"type":"Point"}
}
