{
  "type": "Feature",
  "properties": {
    "iso:country": "GB",
    "wof:name": "BA5 2TY",
    "wof:placetype": "postalcode"
  },
  "geometry": {"coordinates":[-2.648814,51.208565],"type":"Point"}
}
