{
  "type": "Feature",
  "properties": {
    "date:inception_lower": "2013-05-01",
    "date:inception_upper": "2013-05-01",
    "iso:country": "GB",
    "wof:name": "BA5 2TY",
    "wof:placetype": "postalcode"
  },
  "geometry": {"coordinates":[-2.648814,51.208565],"type":"Point"}
}
