{
  "type": "Feature",
  "properties": {
    "iso:country":"GB",
    "wof:name":"BA5 2TY",
    "wof:placetype":"postalcode"
},
  "geometry": {"coordinates":[-2.64881153077903,51.20860655793885],"type":"Point"}
}