{
  "type": "Feature",
  "properties": {
    "date:inception_lower": "1980-01-01",
    "date:inception_upper": "1980-01-01",
    "iso:country": "GB",
    "wof:name": "W11 1NT",
    "wof:placetype": "postalcode"
  },
  "geometry": {"coordinates":[-0.209221,51.515289],"type":"Point"}
}
