{
  "type": "Feature",
  "properties": {
    "iso:country":"GB",
    "wof:name":"W11 1NT",
    "wof:placetype":"postalcode"
},
  "geometry": {"coordinates":[-0.20922136405533,51.51528903687136],"type":"Point"}
}