{
  "type": "Feature",
  "properties": {
    "date:inception_lower": "2023-04-01",
    "date:inception_upper": "2023-04-01",
    "iso:country": "GB",
    "wof:name": "IG11 7HH",
    "wof:placetype": "postalcode"
  },
  "geometry": {"coordinates":[0.072954,51.532801],"type":"Point"}
}
