{
  "type": "Feature",
  "properties": {
    "date:inception_lower":"1980-01-01",
    "date:inception_upper":"1980-01-31",
    "iso:country":"GB",
    "wof:name":"SN10 5TR",
    "wof:placetype":"postalcode"
},
  "geometry": {"coordinates":[-2.030076,51.284576],"type":"Point"}
}