{
  "type": "Feature",
  "properties": {
    "iso:country": "GB",
    "wof:name": "SN10 5TR",
    "wof:placetype": "postalcode"
  },
  "geometry": {"coordinates":[-2.030076,51.284576],"type":"Point"}
}
