{
  "type": "Feature",
  "properties": {
    "iso:country":"GB",
    "wof:name":"ML1 3QT",
    "wof:placetype":"postalcode"
},
  "geometry": {"coordinates":[-4.00950161329145,55.79799497411514],"type":"Point"}
}