{
  "type": "Feature",
  "properties": {
    "date:inception_lower": "1980-01-01",
    "date:inception_upper": "1980-01-01",
    "iso:country": "GB",
    "wof:name": "NR34 9XD",
    "wof:placetype": "postalcode"
  },
  "geometry": {"coordinates":[1.56284,52.447425],"type":"Point"}
}
