{
  "type": "Feature",
  "properties": {
    "iso:country":"GB",
    "wof:name":"KY7 4PL",
    "wof:placetype":"postalcode"
},
  "geometry": {"coordinates":[-3.16303447529565,56.18539525165972],"type":"Point"}
}