{
  "type": "Feature",
  "properties": {
    "iso:country":"GB",
    "wof:name":"CB1 3TB",
    "wof:placetype":"postalcode"
},
  "geometry": {"coordinates":[0.16121355472694,52.19003594217529],"type":"Point"}
}