{
  "type": "Feature",
  "properties": {
    "iso:country":"GB",
    "wof:name":"TW7 5NA",
    "wof:placetype":"postalcode"
},
  "geometry": {"coordinates":[-0.3334650185574,51.48306615227919],"type":"Point"}
}