{
  "type": "Feature",
  "properties": {
    "iso:country":"GB",
    "wof:name":"PE28 5RF",
    "wof:placetype":"postalcode"
},
  "geometry": {"coordinates":[-0.3207717647177,52.41270761151478],"type":"Point"}
}