{
  "type": "Feature",
  "properties": {
    "iso:country": "GB",
    "wof:name": "PE28 5RF",
    "wof:placetype": "postalcode"
  },
  "geometry": {"coordinates":[-0.320772,52.412708],"type":"Point"}
}
