{
  "type": "Feature",
  "properties": {
    "iso:country":"GB",
    "wof:name":"KY11 1DT",
    "wof:placetype":"postalcode"
},
  "geometry": {"coordinates":[-3.39136077446282,56.0299048405009],"type":"Point"}
}