{
  "type": "Feature",
  "properties": {
    "iso:country": "GB",
    "wof:name": "M11 4BA",
    "wof:placetype": "postalcode"
  },
  "geometry": {"coordinates":[-2.180053,53.486849],"type":"Point"}
}
