{
  "type": "Feature",
  "properties": {
    "iso:country":"GB",
    "wof:name":"M11 4BA",
    "wof:placetype":"postalcode"
},
  "geometry": {"coordinates":[-2.18005340117133,53.48684925377659],"type":"Point"}
}