{
  "type": "Feature",
  "properties": {
    "iso:country":"GB",
    "wof:name":"BS23 1AU",
    "wof:placetype":"postalcode"
},
  "geometry": {"coordinates":[-2.98035532137854,51.34663749002942],"type":"Point"}
}