{
  "type": "Feature",
  "properties": {
    "date:inception_lower": "1980-01-01",
    "date:inception_upper": "1980-01-01",
    "iso:country": "GB",
    "wof:name": "BS23 1AU",
    "wof:placetype": "postalcode"
  },
  "geometry": {"coordinates":[-2.98039,51.346625],"type":"Point"}
}
