{
  "type": "Feature",
  "properties": {
    "date:inception_lower":"1994-12-01",
    "date:inception_upper":"1994-12-31",
    "iso:country":"GB",
    "wof:name":"L7 3LP",
    "wof:placetype":"postalcode"
},
  "geometry": {"coordinates":[-2.952887,53.399759],"type":"Point"}
}