{
  "type": "Feature",
  "properties": {
    "iso:country": "GB",
    "wof:name": "L7 3LP",
    "wof:placetype": "postalcode"
  },
  "geometry": {"coordinates":[-2.952887,53.399759],"type":"Point"}
}
