{
  "type": "Feature",
  "properties": {
    "iso:country": "GB",
    "wof:name": "CA3 0BF",
    "wof:placetype": "postalcode"
  },
  "geometry": {"coordinates":[-2.933576,54.917218],"type":"Point"}
}
