{
  "type": "Feature",
  "properties": {
    "date:inception_lower": "2018-10-01",
    "date:inception_upper": "2018-10-01",
    "iso:country": "GB",
    "wof:name": "CA3 0BF",
    "wof:placetype": "postalcode"
  },
  "geometry": {"coordinates":[-2.933032,54.917294],"type":"Point"}
}
