{
  "type": "Feature",
  "properties": {
    "iso:country": "GB",
    "wof:name": "NE26 1QD",
    "wof:placetype": "postalcode"
  },
  "geometry": {"coordinates":[-1.452488,55.048737],"type":"Point"}
}
