{
  "type": "Feature",
  "properties": {
    "iso:country": "GB",
    "wof:name": "EX14 9RU",
    "wof:placetype": "postalcode"
  },
  "geometry": {"coordinates":[-3.139142,50.79548],"type":"Point"}
}
