{
  "type": "Feature",
  "properties": {
    "date:inception_lower":"1981-06-01",
    "date:inception_upper":"1981-06-30",
    "iso:country":"GB",
    "wof:name":"ST4 8TX",
    "wof:placetype":"postalcode"
},
  "geometry": {"coordinates":[-2.180449,52.971807],"type":"Point"}
}