{
  "type": "Feature",
  "properties": {
    "iso:country":"GB",
    "wof:name":"ST4 8TX",
    "wof:placetype":"postalcode"
},
  "geometry": {"coordinates":[-2.18044881495304,52.97180675727753],"type":"Point"}
}