{
  "type": "Feature",
  "properties": {
    "iso:country":"GB",
    "wof:name":"NE65 9LY",
    "wof:placetype":"postalcode"
},
  "geometry": {"coordinates":[-1.73388830382174,55.32401629775882],"type":"Point"}
}