{
  "type": "Feature",
  "properties": {
    "date:inception_lower":"1993-01-01",
    "date:inception_upper":"1993-01-31",
    "iso:country":"GB",
    "wof:name":"NE65 9LY",
    "wof:placetype":"postalcode"
},
  "geometry": {"coordinates":[-1.733888,55.324016],"type":"Point"}
}