{
  "type": "Feature",
  "properties": {
    "iso:country":"GB",
    "wof:name":"RG14 6QS",
    "wof:placetype":"postalcode"
},
  "geometry": {"coordinates":[-1.3460293713857,51.38272704607526],"type":"Point"}
}