{
  "type": "Feature",
  "properties": {
    "iso:country":"GB",
    "wof:name":"WR4 0PS",
    "wof:placetype":"postalcode"
},
  "geometry": {"coordinates":[-2.17544184542302,52.2032129193755],"type":"Point"}
}