{
  "type": "Feature",
  "properties": {
    "iso:country":"GB",
    "wof:name":"GU35 8NS",
    "wof:placetype":"postalcode"
},
  "geometry": {"coordinates":[-0.81226061207256,51.1175958525039],"type":"Point"}
}