{
  "type": "Feature",
  "properties": {
    "iso:country": "GB",
    "wof:name": "NE29 6RE",
    "wof:placetype": "postalcode"
  },
  "geometry": {"coordinates":[-1.448893,55.00599],"type":"Point"}
}
