{
  "type": "Feature",
  "properties": {
    "iso:country":"GB",
    "wof:name":"TF7 5UF",
    "wof:placetype":"postalcode"
},
  "geometry": {"coordinates":[-2.46855575213483,52.63118782209702],"type":"Point"}
}