{
  "type": "Feature",
  "properties": {
    "iso:country":"GB",
    "wof:name":"FK9 4QY",
    "wof:placetype":"postalcode"
},
  "geometry": {"coordinates":[-3.93958460601033,56.14968687225556],"type":"Point"}
}