{
  "type": "Feature",
  "properties": {
    "date:inception_lower":"1980-01-01",
    "date:inception_upper":"1980-01-31",
    "iso:country":"GB",
    "wof:name":"FK9 4QY",
    "wof:placetype":"postalcode"
},
  "geometry": {"coordinates":[-3.939577,56.149681],"type":"Point"}
}