{
  "type": "Feature",
  "properties": {
    "iso:country": "GB",
    "wof:name": "FK9 4QY",
    "wof:placetype": "postalcode"
  },
  "geometry": {"coordinates":[-3.939158,56.149669],"type":"Point"}
}
