{
  "type": "Feature",
  "properties": {
    "iso:country":"GB",
    "wof:name":"SS2 6QU",
    "wof:placetype":"postalcode"
},
  "geometry": {"coordinates":[0.69940271656479,51.56421125453791],"type":"Point"}
}