{
  "type": "Feature",
  "properties": {
    "iso:country":"GB",
    "wof:name":"NE3 4DN",
    "wof:placetype":"postalcode"
},
  "geometry": {"coordinates":[-1.6242079605122,55.00265042990173],"type":"Point"}
}