{
  "type": "Feature",
  "properties": {
    "iso:country": "GB",
    "wof:name": "NE3 4DN",
    "wof:placetype": "postalcode"
  },
  "geometry": {"coordinates":[-1.624208,55.00265],"type":"Point"}
}
