{
  "type": "Feature",
  "properties": {
    "iso:country":"GB",
    "wof:name":"LL60 6BA",
    "wof:placetype":"postalcode"
},
  "geometry": {"coordinates":[-4.22989632038398,53.22600645951488],"type":"Point"}
}