{
  "type": "Feature",
  "properties": {
    "date:inception_lower": "1980-01-01",
    "date:inception_upper": "1980-01-01",
    "iso:country": "GB",
    "wof:name": "DH5 0QG",
    "wof:placetype": "postalcode"
  },
  "geometry": {"coordinates":[-1.437565,54.807572],"type":"Point"}
}
