{
  "type": "Feature",
  "properties": {
    "iso:country":"GB",
    "wof:name":"OL2 5ST",
    "wof:placetype":"postalcode"
},
  "geometry": {"coordinates":[-2.12958787165236,53.57248398820855],"type":"Point"}
}