{
  "type": "Feature",
  "properties": {
    "date:inception_lower": "1980-01-01",
    "date:inception_upper": "1980-01-01",
    "iso:country": "GB",
    "wof:name": "OL2 5ST",
    "wof:placetype": "postalcode"
  },
  "geometry": {"coordinates":[-2.129588,53.572484],"type":"Point"}
}
