{
  "type": "Feature",
  "properties": {
    "iso:country": "GB",
    "wof:name": "YO18 8ND",
    "wof:placetype": "postalcode"
  },
  "geometry": {"coordinates":[-0.783833,54.253655],"type":"Point"}
}
