{
  "type": "Feature",
  "properties": {
    "date:inception_lower": "2011-03-01",
    "date:inception_upper": "2011-03-01",
    "iso:country": "GB",
    "wof:name": "YO18 8ND",
    "wof:placetype": "postalcode"
  },
  "geometry": {"coordinates":[-0.78391,54.253573],"type":"Point"}
}
