{
  "type": "Feature",
  "properties": {
    "iso:country":"GB",
    "wof:name":"YO18 8ND",
    "wof:placetype":"postalcode"
},
  "geometry": {"coordinates":[-0.78383288603073,54.25365534145968],"type":"Point"}
}