{
  "type": "Feature",
  "properties": {
    "date:inception_lower":"2011-03-01",
    "date:inception_upper":"2011-03-31",
    "iso:country":"GB",
    "wof:name":"YO18 8ND",
    "wof:placetype":"postalcode"
},
  "geometry": {"coordinates":[-0.783833,54.253655],"type":"Point"}
}