{
  "type": "Feature",
  "properties": {
    "date:inception_lower": "1992-08-01",
    "date:inception_upper": "1992-08-01",
    "iso:country": "GB",
    "wof:name": "LE7 3RE",
    "wof:placetype": "postalcode"
  },
  "geometry": {"coordinates":[-0.981407,52.683585],"type":"Point"}
}
