{
  "type": "Feature",
  "properties": {
    "iso:country": "GB",
    "wof:name": "RH10 4EX",
    "wof:placetype": "postalcode"
  },
  "geometry": {"coordinates":[-0.067651,51.122437],"type":"Point"}
}
