{
  "type": "Feature",
  "properties": {
    "date:inception_lower":"1980-01-01",
    "date:inception_upper":"1980-01-31",
    "iso:country":"GB",
    "wof:name":"RH10 4EX",
    "wof:placetype":"postalcode"
},
  "geometry": {"coordinates":[-0.067651,51.122437],"type":"Point"}
}