{
  "type": "Feature",
  "properties": {
    "iso:country":"GB",
    "wof:name":"RH10 4EX",
    "wof:placetype":"postalcode"
},
  "geometry": {"coordinates":[-0.06765112225713,51.12243723835758],"type":"Point"}
}