{
  "type": "Feature",
  "properties": {
    "iso:country":"GB",
    "wof:name":"L37 2LW",
    "wof:placetype":"postalcode"
},
  "geometry": {"coordinates":[-3.08371830860516,53.55210166121862],"type":"Point"}
}