{
  "type": "Feature",
  "properties": {
    "date:inception_lower":"1980-01-01",
    "date:inception_upper":"1980-01-31",
    "iso:country":"GB",
    "wof:name":"L37 2LW",
    "wof:placetype":"postalcode"
},
  "geometry": {"coordinates":[-3.083718,53.552102],"type":"Point"}
}