{
  "type": "Feature",
  "properties": {
    "date:inception_lower": "2024-01-01",
    "date:inception_upper": "2024-01-01",
    "iso:country": "GB",
    "wof:name": "LL75 8NH",
    "wof:placetype": "postalcode"
  },
  "geometry": {"coordinates":[-4.217403,53.287646],"type":"Point"}
}
