{
  "type": "Feature",
  "properties": {
    "iso:country":"GB",
    "wof:name":"PO9 5SY",
    "wof:placetype":"postalcode"
},
  "geometry": {"coordinates":[-0.96963298283204,50.86870863984973],"type":"Point"}
}