{
  "type": "Feature",
  "properties": {
    "date:inception_lower": "1996-06-01",
    "date:inception_upper": "1996-06-01",
    "iso:country": "GB",
    "wof:name": "AB10 6AY",
    "wof:placetype": "postalcode"
  },
  "geometry": {"coordinates":[-2.111638,57.131942],"type":"Point"}
}
