{
  "type": "Feature",
  "properties": {
    "iso:country":"GB",
    "wof:name":"NE15 9PY",
    "wof:placetype":"postalcode"
},
  "geometry": {"coordinates":[-1.75478174973553,54.99169670168769],"type":"Point"}
}