{
  "type": "Feature",
  "properties": {
    "iso:country": "GB",
    "wof:name": "NE15 9PY",
    "wof:placetype": "postalcode"
  },
  "geometry": {"coordinates":[-1.754795,54.991704],"type":"Point"}
}
