{
  "type": "Feature",
  "properties": {
    "date:inception_lower": "1980-01-01",
    "date:inception_upper": "1980-01-01",
    "iso:country": "GB",
    "wof:name": "PO30 1XY",
    "wof:placetype": "postalcode"
  },
  "geometry": {"coordinates":[-1.314793,50.687288],"type":"Point"}
}
