{
  "type": "Feature",
  "properties": {
    "iso:country":"GB",
    "wof:name":"DA1 1EF",
    "wof:placetype":"postalcode"
},
  "geometry": {"coordinates":[0.22232363387557,51.43454055672771],"type":"Point"}
}