{
  "type": "Feature",
  "properties": {
    "date:inception_lower": "1990-07-01",
    "date:inception_upper": "1990-07-01",
    "iso:country": "GB",
    "wof:name": "DA1 1EF",
    "wof:placetype": "postalcode"
  },
  "geometry": {"coordinates":[0.222324,51.434541],"type":"Point"}
}
