{
  "type": "Feature",
  "properties": {
    "iso:country": "GB",
    "wof:name": "DA1 1EF",
    "wof:placetype": "postalcode"
  },
  "geometry": {"coordinates":[0.222324,51.434541],"type":"Point"}
}
