{
  "type": "Feature",
  "properties": {
    "iso:country": "GB",
    "wof:name": "SE12 9QX",
    "wof:placetype": "postalcode"
  },
  "geometry": {"coordinates":[0.032889,51.427296],"type":"Point"}
}
