{
  "type": "Feature",
  "properties": {
    "iso:country":"GB",
    "wof:name":"SE12 9QX",
    "wof:placetype":"postalcode"
},
  "geometry": {"coordinates":[0.03288930765477,51.42729600427099],"type":"Point"}
}