{
  "type": "Feature",
  "properties": {
    "iso:country":"GB",
    "wof:name":"CA1 2SF",
    "wof:placetype":"postalcode"
},
  "geometry": {"coordinates":[-2.90119178217754,54.8923837389822],"type":"Point"}
}