{
  "type": "Feature",
  "properties": {
    "iso:country":"GB",
    "wof:name":"NN8 1RR",
    "wof:placetype":"postalcode"
},
  "geometry": {"coordinates":[-0.62462829869605,52.30757430515413],"type":"Point"}
}