{
  "type": "Feature",
  "properties": {
    "iso:country":"GB",
    "wof:name":"CV35 0LR",
    "wof:placetype":"postalcode"
},
  "geometry": {"coordinates":[-1.50604685357998,52.15856330847878],"type":"Point"}
}