{
  "type": "Feature",
  "properties": {
    "date:inception_lower": "1980-01-01",
    "date:inception_upper": "1980-01-01",
    "iso:country": "GB",
    "wof:name": "CV35 0LR",
    "wof:placetype": "postalcode"
  },
  "geometry": {"coordinates":[-1.506047,52.158563],"type":"Point"}
}
