{
  "type": "Feature",
  "properties": {
    "iso:country": "GB",
    "wof:name": "TN2 4EY",
    "wof:placetype": "postalcode"
  },
  "geometry": {"coordinates":[0.326244,51.147298],"type":"Point"}
}
