{
  "type": "Feature",
  "properties": {
    "iso:country":"GB",
    "wof:name":"TN2 4EY",
    "wof:placetype":"postalcode"
},
  "geometry": {"coordinates":[0.3262439246235,51.14729818033518],"type":"Point"}
}