{
  "type": "Feature",
  "properties": {
    "iso:country":"GB",
    "wof:name":"DG9 7HW",
    "wof:placetype":"postalcode"
},
  "geometry": {"coordinates":[-5.01579342677488,54.90268472106209],"type":"Point"}
}