{
  "type": "Feature",
  "properties": {
    "iso:country":"GB",
    "wof:name":"GL5 2SG",
    "wof:placetype":"postalcode"
},
  "geometry": {"coordinates":[-2.19867496162234,51.72248484231775],"type":"Point"}
}