{
  "type": "Feature",
  "properties": {
    "iso:country":"GB",
    "wof:name":"OL9 7HY",
    "wof:placetype":"postalcode"
},
  "geometry": {"coordinates":[-2.1403209036243,53.53037948218024],"type":"Point"}
}