{
  "type": "Feature",
  "properties": {
    "iso:country":"GB",
    "wof:name":"HX3 7NA",
    "wof:placetype":"postalcode"
},
  "geometry": {"coordinates":[-1.81781320978463,53.75208972366464],"type":"Point"}
}