{
  "type": "Feature",
  "properties": {
    "iso:country":"GB",
    "wof:name":"NW10 1AB",
    "wof:placetype":"postalcode"
},
  "geometry": {"coordinates":[-0.24454641264831,51.55689113568273],"type":"Point"}
}