{
  "type": "Feature",
  "properties": {
    "iso:country":"GB",
    "wof:name":"SN15 2JQ",
    "wof:placetype":"postalcode"
},
  "geometry": {"coordinates":[-2.05794808531568,51.38483259185698],"type":"Point"}
}