{
  "type": "Feature",
  "properties": {
    "date:inception_lower":"2011-09-01",
    "date:inception_upper":"2011-09-30",
    "iso:country":"GB",
    "wof:name":"SO51 8LD",
    "wof:placetype":"postalcode"
},
  "geometry": {"coordinates":[-1.498505,50.989511],"type":"Point"}
}