{
  "type": "Feature",
  "properties": {
    "iso:country":"GB",
    "wof:name":"SO51 8LD",
    "wof:placetype":"postalcode"
},
  "geometry": {"coordinates":[-1.49850497376473,50.98951097521811],"type":"Point"}
}