{
  "type": "Feature",
  "properties": {
    "iso:country":"GB",
    "wof:name":"BS15 1XW",
    "wof:placetype":"postalcode"
},
  "geometry": {"coordinates":[-2.5038002825709,51.47055041806133],"type":"Point"}
}