{
  "type": "Feature",
  "properties": {
    "date:inception_lower": "1980-01-01",
    "date:inception_upper": "1980-01-01",
    "iso:country": "GB",
    "wof:name": "BS15 1XW",
    "wof:placetype": "postalcode"
  },
  "geometry": {"coordinates":[-2.503358,51.470874],"type":"Point"}
}
