{
  "type": "Feature",
  "properties": {
    "iso:country":"GB",
    "wof:name":"N14 7BD",
    "wof:placetype":"postalcode"
},
  "geometry": {"coordinates":[-0.11926888546193,51.62235715492897],"type":"Point"}
}