{
  "type": "Feature",
  "properties": {
    "iso:country": "GB",
    "wof:name": "L15 4LG",
    "wof:placetype": "postalcode"
  },
  "geometry": {"coordinates":[-2.924157,53.399633],"type":"Point"}
}
