{
  "type": "Feature",
  "properties": {
    "date:inception_lower": "1980-01-01",
    "date:inception_upper": "1980-01-01",
    "iso:country": "GB",
    "wof:name": "L15 4LG",
    "wof:placetype": "postalcode"
  },
  "geometry": {"coordinates":[-2.924384,53.399703],"type":"Point"}
}
