{
  "type": "Feature",
  "properties": {
    "iso:country":"GB",
    "wof:name":"L15 4LG",
    "wof:placetype":"postalcode"
},
  "geometry": {"coordinates":[-2.92438401638921,53.39968654432313],"type":"Point"}
}