{
  "type": "Feature",
  "properties": {
    "iso:country":"GB",
    "wof:name":"DE12 7LD",
    "wof:placetype":"postalcode"
},
  "geometry": {"coordinates":[-1.4994701316925,52.70532363376062],"type":"Point"}
}