{
  "type": "Feature",
  "properties": {
    "date:inception_lower":"1996-06-01",
    "date:inception_upper":"1996-06-30",
    "iso:country":"GB",
    "wof:name":"DE12 7LD",
    "wof:placetype":"postalcode"
},
  "geometry": {"coordinates":[-1.49947,52.705324],"type":"Point"}
}