{
  "type": "Feature",
  "properties": {
    "iso:country": "GB",
    "wof:name": "DE12 7LD",
    "wof:placetype": "postalcode"
  },
  "geometry": {"coordinates":[-1.49947,52.705324],"type":"Point"}
}
