{
  "type": "Feature",
  "properties": {
    "iso:country":"GB",
    "wof:name":"S12 2FS",
    "wof:placetype":"postalcode"
},
  "geometry": {"coordinates":[-1.42320794392154,53.3581356710135],"type":"Point"}
}