{
  "type": "Feature",
  "properties": {
    "iso:country":"GB",
    "wof:name":"GU29 9EE",
    "wof:placetype":"postalcode"
},
  "geometry": {"coordinates":[-0.74007231372358,50.98745478017182],"type":"Point"}
}