{
  "type": "Feature",
  "properties": {
    "iso:country": "GB",
    "wof:name": "B80 7JH",
    "wof:placetype": "postalcode"
  },
  "geometry": {"coordinates":[-1.90795,52.272156],"type":"Point"}
}
