{
  "type": "Feature",
  "properties": {
    "iso:country":"GB",
    "wof:name":"M9 5PX",
    "wof:placetype":"postalcode"
},
  "geometry": {"coordinates":[-2.21027570784377,53.50936078869447],"type":"Point"}
}