{
  "type": "Feature",
  "properties": {
    "iso:country": "GB",
    "wof:name": "M9 5PX",
    "wof:placetype": "postalcode"
  },
  "geometry": {"coordinates":[-2.210276,53.509361],"type":"Point"}
}
