{
  "type": "Feature",
  "properties": {
    "iso:country":"GB",
    "wof:name":"SE24 9LT",
    "wof:placetype":"postalcode"
},
  "geometry": {"coordinates":[-0.09895201676226,51.45359998480256],"type":"Point"}
}