{
  "type": "Feature",
  "properties": {
    "date:inception_lower": "1981-06-01",
    "date:inception_upper": "1981-06-01",
    "iso:country": "GB",
    "wof:name": "NG19 0NZ",
    "wof:placetype": "postalcode"
  },
  "geometry": {"coordinates":[-1.157408,53.156046],"type":"Point"}
}
