{
  "type": "Feature",
  "properties": {
    "date:inception_lower": "1980-01-01",
    "date:inception_upper": "1980-01-01",
    "iso:country": "GB",
    "wof:name": "SA5 4RP",
    "wof:placetype": "postalcode"
  },
  "geometry": {"coordinates":[-4.005067,51.635421],"type":"Point"}
}
