{
  "type": "Feature",
  "properties": {
    "iso:country": "GB",
    "wof:name": "SA5 4RP",
    "wof:placetype": "postalcode"
  },
  "geometry": {"coordinates":[-4.003911,51.63313],"type":"Point"}
}
