{
  "type": "Feature",
  "properties": {
    "iso:country":"GB",
    "wof:name":"SA5 4RP",
    "wof:placetype":"postalcode"
},
  "geometry": {"coordinates":[-4.00389287159781,51.63312462042003],"type":"Point"}
}