{
  "type": "Feature",
  "properties": {
    "iso:country":"GB",
    "wof:name":"SE27 9DQ",
    "wof:placetype":"postalcode"
},
  "geometry": {"coordinates":[-0.10476331123254,51.43700373714403],"type":"Point"}
}