{
  "type": "Feature",
  "properties": {
    "iso:country": "GB",
    "wof:name": "SE27 9DQ",
    "wof:placetype": "postalcode"
  },
  "geometry": {"coordinates":[-0.104763,51.437004],"type":"Point"}
}
