{
  "type": "Feature",
  "properties": {
    "date:inception_lower":"1980-01-01",
    "date:inception_upper":"1980-01-31",
    "iso:country":"GB",
    "wof:name":"SE27 9DQ",
    "wof:placetype":"postalcode"
},
  "geometry": {"coordinates":[-0.104763,51.437004],"type":"Point"}
}