{
  "type": "Feature",
  "properties": {
    "iso:country":"GB",
    "wof:name":"SK2 5HT",
    "wof:placetype":"postalcode"
},
  "geometry": {"coordinates":[-2.11501162631426,53.3987345440143],"type":"Point"}
}