{
  "type": "Feature",
  "properties": {
    "iso:country":"GB",
    "wof:name":"CO4 9ES",
    "wof:placetype":"postalcode"
},
  "geometry": {"coordinates":[0.90985911325393,51.91898397102324],"type":"Point"}
}