{
  "type": "Feature",
  "properties": {
    "iso:country":"GB",
    "wof:name":"G84 9AL",
    "wof:placetype":"postalcode"
},
  "geometry": {"coordinates":[-4.72842740496837,56.01468430065369],"type":"Point"}
}