{
  "type": "Feature",
  "properties": {
    "iso:country": "GB",
    "wof:name": "B32 3TT",
    "wof:placetype": "postalcode"
  },
  "geometry": {"coordinates":[-1.997293,52.44367],"type":"Point"}
}
