{
  "type": "Feature",
  "properties": {
    "date:inception_lower":"2010-07-01",
    "date:inception_upper":"2010-07-31",
    "iso:country":"GB",
    "wof:name":"EX31 4EW",
    "wof:placetype":"postalcode"
},
  "geometry": {"coordinates":[-4.135432,51.092778],"type":"Point"}
}