{
  "type": "Feature",
  "properties": {
    "iso:country":"GB",
    "wof:name":"EX31 4EW",
    "wof:placetype":"postalcode"
},
  "geometry": {"coordinates":[-4.13543192190684,51.09277780078258],"type":"Point"}
}