{
  "type": "Feature",
  "properties": {
    "iso:country":"GB",
    "wof:name":"CW7 2DA",
    "wof:placetype":"postalcode"
},
  "geometry": {"coordinates":[-2.53348980695019,53.19713752095156],"type":"Point"}
}