{
  "type": "Feature",
  "properties": {
    "iso:country":"GB",
    "wof:name":"ST3 6EZ",
    "wof:placetype":"postalcode"
},
  "geometry": {"coordinates":[-2.1008810434111,52.98804567861725],"type":"Point"}
}