{
  "type": "Feature",
  "properties": {
    "iso:country":"GB",
    "wof:name":"WR14 3AL",
    "wof:placetype":"postalcode"
},
  "geometry": {"coordinates":[-2.32131347014377,52.10996191180782],"type":"Point"}
}