{
  "type": "Feature",
  "properties": {
    "iso:country":"GB",
    "wof:name":"LA5 0RY",
    "wof:placetype":"postalcode"
},
  "geometry": {"coordinates":[-2.8269511184773,54.1765008972077],"type":"Point"}
}