{
  "type": "Feature",
  "properties": {
    "iso:country":"GB",
    "wof:name":"SE18 7HW",
    "wof:placetype":"postalcode"
},
  "geometry": {"coordinates":[0.07566976959201,51.48500861069881],"type":"Point"}
}