{
  "type": "Feature",
  "properties": {
    "iso:country":"GB",
    "wof:name":"W1K 6RP",
    "wof:placetype":"postalcode"
},
  "geometry": {"coordinates":[-0.15472232947364,51.5129155791436],"type":"Point"}
}