{
  "type": "Feature",
  "properties": {
    "iso:country":"GB",
    "wof:name":"OL16 2RD",
    "wof:placetype":"postalcode"
},
  "geometry": {"coordinates":[-2.12909956258496,53.63511467884594],"type":"Point"}
}