{
  "type": "Feature",
  "properties": {
    "iso:country":"GB",
    "wof:name":"SW1V 3NW",
    "wof:placetype":"postalcode"
},
  "geometry": {"coordinates":[-0.1357846782544,51.48573743077534],"type":"Point"}
}