{
  "type": "Feature",
  "properties": {
    "iso:country": "GB",
    "wof:name": "HP14 4ND",
    "wof:placetype": "postalcode"
  },
  "geometry": {"coordinates":[-0.765408,51.670466],"type":"Point"}
}
