{
  "type": "Feature",
  "properties": {
    "iso:country": "GB",
    "wof:name": "BS9 2NQ",
    "wof:placetype": "postalcode"
  },
  "geometry": {"coordinates":[-2.650806,51.491613],"type":"Point"}
}
