{
  "type": "Feature",
  "properties": {
    "iso:country":"GB",
    "wof:name":"LL20 8RH",
    "wof:placetype":"postalcode"
},
  "geometry": {"coordinates":[-3.17380706355255,52.96879817874358],"type":"Point"}
}