{
  "type": "Feature",
  "properties": {
    "iso:country":"GB",
    "wof:name":"M13 9NU",
    "wof:placetype":"postalcode"
},
  "geometry": {"coordinates":[-2.22940288024697,53.46334966815132],"type":"Point"}
}