{
  "type": "Feature",
  "properties": {
    "iso:country": "GB",
    "wof:name": "M13 9NU",
    "wof:placetype": "postalcode"
  },
  "geometry": {"coordinates":[-2.229403,53.46335],"type":"Point"}
}
