{
  "type": "Feature",
  "properties": {
    "date:inception_lower": "2010-04-01",
    "date:inception_upper": "2010-04-01",
    "iso:country": "GB",
    "wof:name": "M13 9NU",
    "wof:placetype": "postalcode"
  },
  "geometry": {"coordinates":[-2.229403,53.46335],"type":"Point"}
}
