{
  "type": "Feature",
  "properties": {
    "date:inception_lower": "1995-01-01",
    "date:inception_upper": "1995-01-01",
    "iso:country": "GB",
    "wof:name": "TN38 9TG",
    "wof:placetype": "postalcode"
  },
  "geometry": {"coordinates":[0.528862,50.874592],"type":"Point"}
}
