{
  "type": "Feature",
  "properties": {
    "date:inception_lower": "2021-07-01",
    "date:inception_upper": "2021-07-01",
    "iso:country": "GB",
    "wof:name": "OX20 1GF",
    "wof:placetype": "postalcode"
  },
  "geometry": {"coordinates":[-1.341525,51.842332],"type":"Point"}
}
