{
  "type": "Feature",
  "properties": {
    "date:inception_lower": "2016-07-01",
    "date:inception_upper": "2016-07-01",
    "iso:country": "GB",
    "wof:name": "SL0 0AF",
    "wof:placetype": "postalcode"
  },
  "geometry": {"coordinates":[-0.523449,51.531285],"type":"Point"}
}
