{
  "type": "Feature",
  "properties": {
    "iso:country":"GB",
    "wof:name":"NR11 6JR",
    "wof:placetype":"postalcode"
},
  "geometry": {"coordinates":[1.25342147408102,52.78468620498194],"type":"Point"}
}