{
  "type": "Feature",
  "properties": {
    "iso:country":"GB",
    "wof:name":"B44 0LB",
    "wof:placetype":"postalcode"
},
  "geometry": {"coordinates":[-1.87011628296999,52.54605701134109],"type":"Point"}
}