{
  "type": "Feature",
  "properties": {
    "iso:country":"GB",
    "wof:name":"CW8 4NN",
    "wof:placetype":"postalcode"
},
  "geometry": {"coordinates":[-2.5421598674895,53.27442105764409],"type":"Point"}
}