{
  "type": "Feature",
  "properties": {
    "iso:country":"GB",
    "wof:name":"PL6 8SL",
    "wof:placetype":"postalcode"
},
  "geometry": {"coordinates":[-4.1012189315026,50.40796057818614],"type":"Point"}
}