{
  "type": "Feature",
  "properties": {
    "iso:country": "GB",
    "wof:name": "EN11 0JU",
    "wof:placetype": "postalcode"
  },
  "geometry": {"coordinates":[-0.003984,51.765088],"type":"Point"}
}
