{
  "type": "Feature",
  "properties": {
    "date:inception_lower": "2001-12-01",
    "date:inception_upper": "2001-12-01",
    "iso:country": "GB",
    "wof:name": "CT14 7DR",
    "wof:placetype": "postalcode"
  },
  "geometry": {"coordinates":[1.400846,51.211884],"type":"Point"}
}
