{
  "type": "Feature",
  "properties": {
    "date:inception_lower":"1997-06-01",
    "date:inception_upper":"1997-06-30",
    "iso:country":"GB",
    "wof:name":"GL2 4NT",
    "wof:placetype":"postalcode"
},
  "geometry": {"coordinates":[-2.285067,51.832007],"type":"Point"}
}