{
  "type": "Feature",
  "properties": {
    "date:inception_lower": "1983-07-01",
    "date:inception_upper": "1983-07-01",
    "iso:country": "GB",
    "wof:name": "LS12 4QP",
    "wof:placetype": "postalcode"
  },
  "geometry": {"coordinates":[-1.614757,53.79282],"type":"Point"}
}
