{
  "type": "Feature",
  "properties": {
    "iso:country":"GB",
    "wof:name":"CH65 6QL",
    "wof:placetype":"postalcode"
},
  "geometry": {"coordinates":[-2.9041672324988,53.27675540929049],"type":"Point"}
}