{
  "type": "Feature",
  "properties": {
    "iso:country":"GB",
    "wof:name":"PL19 0AQ",
    "wof:placetype":"postalcode"
},
  "geometry": {"coordinates":[-4.1447754142812,50.55046155111717],"type":"Point"}
}