{
  "type": "Feature",
  "properties": {
    "iso:country": "GB",
    "wof:name": "SS4 1JU",
    "wof:placetype": "postalcode"
  },
  "geometry": {"coordinates":[0.722768,51.577293],"type":"Point"}
}
