{
  "type": "Feature",
  "properties": {
    "iso:country":"GB",
    "wof:name":"SS4 1JU",
    "wof:placetype":"postalcode"
},
  "geometry": {"coordinates":[0.72403304868609,51.57697039021278],"type":"Point"}
}