{
  "type": "Feature",
  "properties": {
    "date:inception_lower": "1992-08-01",
    "date:inception_upper": "1992-08-01",
    "iso:country": "GB",
    "wof:name": "SS4 1JU",
    "wof:placetype": "postalcode"
  },
  "geometry": {"coordinates":[0.723392,51.577117],"type":"Point"}
}
