{
  "type": "Feature",
  "properties": {
    "iso:country":"GB",
    "wof:name":"M20 4WX",
    "wof:placetype":"postalcode"
},
  "geometry": {"coordinates":[-2.2194546708063,53.43278049782956],"type":"Point"}
}