{
  "type": "Feature",
  "properties": {
    "date:inception_lower": "1980-01-01",
    "date:inception_upper": "1980-01-01",
    "iso:country": "GB",
    "wof:name": "HP21 8PG",
    "wof:placetype": "postalcode"
  },
  "geometry": {"coordinates":[-0.824669,51.806684],"type":"Point"}
}
