{
  "type": "Feature",
  "properties": {
    "iso:country":"GB",
    "wof:name":"HP21 8PG",
    "wof:placetype":"postalcode"
},
  "geometry": {"coordinates":[-0.82466922415316,51.80668391194253],"type":"Point"}
}