{
  "type": "Feature",
  "properties": {
    "iso:country":"GB",
    "wof:name":"RM17 5AL",
    "wof:placetype":"postalcode"
},
  "geometry": {"coordinates":[0.32185646563974,51.49061673067607],"type":"Point"}
}