{
  "type": "Feature",
  "properties": {
    "iso:country":"GB",
    "wof:name":"LN11 9DR",
    "wof:placetype":"postalcode"
},
  "geometry": {"coordinates":[0.00222989051099,53.36404138189602],"type":"Point"}
}