{
  "type": "Feature",
  "properties": {
    "iso:country":"GB",
    "wof:name":"PR2 6NQ",
    "wof:placetype":"postalcode"
},
  "geometry": {"coordinates":[-2.66498442098871,53.76980527855562],"type":"Point"}
}