{
  "type": "Feature",
  "properties": {
    "iso:country":"GB",
    "wof:name":"LU6 1QD",
    "wof:placetype":"postalcode"
},
  "geometry": {"coordinates":[-0.53338430967601,51.88227762969913],"type":"Point"}
}