{
  "type": "Feature",
  "properties": {
    "date:inception_lower":"1992-08-01",
    "date:inception_upper":"1992-08-31",
    "iso:country":"GB",
    "wof:name":"LU6 1QD",
    "wof:placetype":"postalcode"
},
  "geometry": {"coordinates":[-0.533384,51.882278],"type":"Point"}
}