{
  "type": "Feature",
  "properties": {
    "iso:country": "GB",
    "wof:name": "LU6 1QD",
    "wof:placetype": "postalcode"
  },
  "geometry": {"coordinates":[-0.533384,51.882278],"type":"Point"}
}
