{
  "type": "Feature",
  "properties": {
    "iso:country": "GB",
    "wof:name": "EH7 6NF",
    "wof:placetype": "postalcode"
  },
  "geometry": {"coordinates":[-3.148916,55.960585],"type":"Point"}
}
