{
  "type": "Feature",
  "properties": {
    "date:inception_lower":"2010-02-01",
    "date:inception_upper":"2010-02-28",
    "iso:country":"GB",
    "wof:name":"EH7 6NF",
    "wof:placetype":"postalcode"
},
  "geometry": {"coordinates":[-3.148897,55.960582],"type":"Point"}
}