{
  "type": "Feature",
  "properties": {
    "date:inception_lower": "1990-07-01",
    "date:inception_upper": "1990-07-01",
    "iso:country": "GB",
    "wof:name": "OX10 7ER",
    "wof:placetype": "postalcode"
  },
  "geometry": {"coordinates":[-1.140699,51.626587],"type":"Point"}
}
