{
  "type": "Feature",
  "properties": {
    "iso:country":"GB",
    "wof:name":"OX10 7ER",
    "wof:placetype":"postalcode"
},
  "geometry": {"coordinates":[-1.14069857627226,51.62658693776724],"type":"Point"}
}