{
  "type": "Feature",
  "properties": {
    "iso:country":"GB",
    "wof:name":"KY16 8PQ",
    "wof:placetype":"postalcode"
},
  "geometry": {"coordinates":[-2.83752375561056,56.32614152969075],"type":"Point"}
}