{
  "type": "Feature",
  "properties": {
    "iso:country": "GB",
    "wof:name": "E15 4EX",
    "wof:placetype": "postalcode"
  },
  "geometry": {"coordinates":[0.00798,51.541843],"type":"Point"}
}
