{
  "type": "Feature",
  "properties": {
    "date:inception_lower": "1999-12-01",
    "date:inception_upper": "1999-12-01",
    "iso:country": "GB",
    "wof:name": "E15 4EX",
    "wof:placetype": "postalcode"
  },
  "geometry": {"coordinates":[0.00798,51.541843],"type":"Point"}
}
