{
  "type": "Feature",
  "properties": {
    "date:inception_lower": "1991-09-01",
    "date:inception_upper": "1991-09-01",
    "iso:country": "GB",
    "wof:name": "IP19 8PG",
    "wof:placetype": "postalcode"
  },
  "geometry": {"coordinates":[1.492632,52.338702],"type":"Point"}
}
