{
  "type": "Feature",
  "properties": {
    "iso:country":"GB",
    "wof:name":"E2 7PE",
    "wof:placetype":"postalcode"
},
  "geometry": {"coordinates":[-0.07469045736386,51.52902975192337],"type":"Point"}
}