{
  "type": "Feature",
  "properties": {
    "date:inception_lower": "1980-01-01",
    "date:inception_upper": "1980-01-01",
    "iso:country": "GB",
    "wof:name": "E2 7PE",
    "wof:placetype": "postalcode"
  },
  "geometry": {"coordinates":[-0.07469,51.52903],"type":"Point"}
}
