{
  "type": "Feature",
  "properties": {
    "iso:country": "GB",
    "wof:name": "BL4 9SY",
    "wof:placetype": "postalcode"
  },
  "geometry": {"coordinates":[-2.411604,53.540467],"type":"Point"}
}
