{
  "type": "Feature",
  "properties": {
    "iso:country":"GB",
    "wof:name":"SE17 3DU",
    "wof:placetype":"postalcode"
},
  "geometry": {"coordinates":[-0.09812286866937,51.48704805525207],"type":"Point"}
}