{
  "type": "Feature",
  "properties": {
    "date:inception_lower": "1980-01-01",
    "date:inception_upper": "1980-01-01",
    "iso:country": "GB",
    "wof:name": "SE17 3DU",
    "wof:placetype": "postalcode"
  },
  "geometry": {"coordinates":[-0.098123,51.487048],"type":"Point"}
}
