{
  "type": "Feature",
  "properties": {
    "date:inception_lower": "2019-10-01",
    "date:inception_upper": "2019-10-01",
    "iso:country": "GB",
    "wof:name": "TD1 2ER",
    "wof:placetype": "postalcode"
  },
  "geometry": {"coordinates":[-2.755761,55.613337],"type":"Point"}
}
