{
  "type": "Feature",
  "properties": {
    "iso:country": "GB",
    "wof:name": "TD1 2ER",
    "wof:placetype": "postalcode"
  },
  "geometry": {"coordinates":[-2.756846,55.613627],"type":"Point"}
}
