{
  "type": "Feature",
  "properties": {
    "iso:country": "GB",
    "wof:name": "TS20 2FA",
    "wof:placetype": "postalcode"
  },
  "geometry": {"coordinates":[-1.306266,54.577499],"type":"Point"}
}
