{
  "type": "Feature",
  "properties": {
    "date:inception_lower": "2016-09-01",
    "date:inception_upper": "2016-09-01",
    "iso:country": "GB",
    "wof:name": "TS20 2FA",
    "wof:placetype": "postalcode"
  },
  "geometry": {"coordinates":[-1.306266,54.577499],"type":"Point"}
}
