{
  "type": "Feature",
  "properties": {
    "iso:country":"GB",
    "wof:name":"N1 2PR",
    "wof:placetype":"postalcode"
},
  "geometry": {"coordinates":[-0.09145285481165,51.5456880731589],"type":"Point"}
}