{
  "type": "Feature",
  "properties": {
    "date:inception_lower": "1995-12-01",
    "date:inception_upper": "1995-12-01",
    "iso:country": "GB",
    "wof:name": "BA3 3RZ",
    "wof:placetype": "postalcode"
  },
  "geometry": {"coordinates":[-2.458538,51.289594],"type":"Point"}
}
