{
  "type": "Feature",
  "properties": {
    "date:inception_lower":"1995-12-01",
    "date:inception_upper":"1995-12-31",
    "iso:country":"GB",
    "wof:name":"BA3 3RZ",
    "wof:placetype":"postalcode"
},
  "geometry": {"coordinates":[-2.458827,51.289862],"type":"Point"}
}