{
  "type": "Feature",
  "properties": {
    "iso:country": "GB",
    "wof:name": "BA3 3RZ",
    "wof:placetype": "postalcode"
  },
  "geometry": {"coordinates":[-2.458827,51.289862],"type":"Point"}
}
