{
  "type": "Feature",
  "properties": {
    "iso:country":"GB",
    "wof:name":"MK11 1EZ",
    "wof:placetype":"postalcode"
},
  "geometry": {"coordinates":[-0.84724573912593,52.04937407573627],"type":"Point"}
}