{
  "type": "Feature",
  "properties": {
    "date:inception_lower": "1980-01-01",
    "date:inception_upper": "1980-01-01",
    "iso:country": "GB",
    "wof:name": "HA7 3SL",
    "wof:placetype": "postalcode"
  },
  "geometry": {"coordinates":[-0.321542,51.613527],"type":"Point"}
}
