{
  "type": "Feature",
  "properties": {
    "iso:country":"GB",
    "wof:name":"HA7 3SL",
    "wof:placetype":"postalcode"
},
  "geometry": {"coordinates":[-0.32154175238234,51.61352666370412],"type":"Point"}
}