{
  "type": "Feature",
  "properties": {
    "iso:country":"GB",
    "wof:name":"FY1 4SS",
    "wof:placetype":"postalcode"
},
  "geometry": {"coordinates":[-3.05411394644077,53.81559689771647],"type":"Point"}
}