{
  "type": "Feature",
  "properties": {
    "iso:country": "GB",
    "wof:name": "PE31 8PN",
    "wof:placetype": "postalcode"
  },
  "geometry": {"coordinates":[0.617694,52.900684],"type":"Point"}
}
