{
  "type": "Feature",
  "properties": {
    "date:inception_lower":"1980-01-01",
    "date:inception_upper":"1980-01-31",
    "iso:country":"GB",
    "wof:name":"PE31 8PN",
    "wof:placetype":"postalcode"
},
  "geometry": {"coordinates":[0.617694,52.900684],"type":"Point"}
}