{
  "type": "Feature",
  "properties": {
    "iso:country":"GB",
    "wof:name":"PE31 8PN",
    "wof:placetype":"postalcode"
},
  "geometry": {"coordinates":[0.61769352621526,52.900684342211],"type":"Point"}
}