{
  "type": "Feature",
  "properties": {
    "date:inception_lower":"2007-01-01",
    "date:inception_upper":"2007-01-31",
    "iso:country":"GB",
    "wof:name":"G22 6PU",
    "wof:placetype":"postalcode"
},
  "geometry": {"coordinates":[-4.269115,55.895062],"type":"Point"}
}