{
  "type": "Feature",
  "properties": {
    "iso:country":"GB",
    "wof:name":"G22 6PU",
    "wof:placetype":"postalcode"
},
  "geometry": {"coordinates":[-4.2691151087279,55.89506189866574],"type":"Point"}
}