{
  "type": "Feature",
  "properties": {
    "iso:country": "GB",
    "wof:name": "G22 6PU",
    "wof:placetype": "postalcode"
  },
  "geometry": {"coordinates":[-4.269115,55.895062],"type":"Point"}
}
