{
  "type": "Feature",
  "properties": {
    "iso:country":"GB",
    "wof:name":"AL6 0PU",
    "wof:placetype":"postalcode"
},
  "geometry": {"coordinates":[-0.19878505179459,51.84158247525862],"type":"Point"}
}