{
  "type": "Feature",
  "properties": {
    "date:inception_lower":"1980-01-01",
    "date:inception_upper":"1980-01-31",
    "iso:country":"GB",
    "wof:name":"AL6 0PU",
    "wof:placetype":"postalcode"
},
  "geometry": {"coordinates":[-0.198785,51.841582],"type":"Point"}
}