{
  "type": "Feature",
  "properties": {
    "iso:country": "GB",
    "wof:name": "CF24 4TS",
    "wof:placetype": "postalcode"
  },
  "geometry": {"coordinates":[-3.168846,51.49423],"type":"Point"}
}
