{
  "type": "Feature",
  "properties": {
    "date:inception_lower": "2017-10-01",
    "date:inception_upper": "2017-10-01",
    "iso:country": "GB",
    "wof:name": "BD16 4FH",
    "wof:placetype": "postalcode"
  },
  "geometry": {"coordinates":[-1.831946,53.855747],"type":"Point"}
}
