{
  "type": "Feature",
  "properties": {
    "iso:country": "GB",
    "wof:name": "BD16 4FH",
    "wof:placetype": "postalcode"
  },
  "geometry": {"coordinates":[-1.831885,53.855918],"type":"Point"}
}
