{
  "type": "Feature",
  "properties": {
    "iso:country":"GB",
    "wof:name":"WS10 0BE",
    "wof:placetype":"postalcode"
},
  "geometry": {"coordinates":[-2.01215306150174,52.55107173613227],"type":"Point"}
}