{
  "type": "Feature",
  "properties": {
    "date:inception_lower": "1980-01-01",
    "date:inception_upper": "1980-01-01",
    "iso:country": "GB",
    "wof:name": "WS10 0BE",
    "wof:placetype": "postalcode"
  },
  "geometry": {"coordinates":[-2.012153,52.551072],"type":"Point"}
}
