{
  "type": "Feature",
  "properties": {
    "iso:country":"GB",
    "wof:name":"SW13 9JT",
    "wof:placetype":"postalcode"
},
  "geometry": {"coordinates":[-0.23743946741293,51.48769609309719],"type":"Point"}
}