{
  "type": "Feature",
  "properties": {
    "iso:country":"GB",
    "wof:name":"MK45 1EN",
    "wof:placetype":"postalcode"
},
  "geometry": {"coordinates":[-0.50326009907083,52.01050388974473],"type":"Point"}
}