{
  "type": "Feature",
  "properties": {
    "date:inception_lower": "1991-09-01",
    "date:inception_upper": "1991-09-01",
    "iso:country": "GB",
    "wof:name": "MK45 1EN",
    "wof:placetype": "postalcode"
  },
  "geometry": {"coordinates":[-0.50326,52.010504],"type":"Point"}
}
