{
  "type": "Feature",
  "properties": {
    "iso:country":"GB",
    "wof:name":"HA4 6QX",
    "wof:placetype":"postalcode"
},
  "geometry": {"coordinates":[-0.39962125662393,51.54947800972722],"type":"Point"}
}