{
  "type": "Feature",
  "properties": {
    "date:inception_lower":"1980-01-01",
    "date:inception_upper":"1980-01-31",
    "iso:country":"GB",
    "wof:name":"NW1 8JP",
    "wof:placetype":"postalcode"
},
  "geometry": {"coordinates":[-0.154376,51.538961],"type":"Point"}
}