{
  "type": "Feature",
  "properties": {
    "iso:country":"GB",
    "wof:name":"NW1 8JP",
    "wof:placetype":"postalcode"
},
  "geometry": {"coordinates":[-0.15437561729957,51.53896131871758],"type":"Point"}
}