{
  "type": "Feature",
  "properties": {
    "date:inception_lower":"2007-01-01",
    "date:inception_upper":"2007-01-31",
    "iso:country":"GB",
    "wof:name":"SO14 2NW",
    "wof:placetype":"postalcode"
},
  "geometry": {"coordinates":[-1.403752,50.897568],"type":"Point"}
}