{
  "type": "Feature",
  "properties": {
    "iso:country":"GB",
    "wof:name":"OX11 9DS",
    "wof:placetype":"postalcode"
},
  "geometry": {"coordinates":[-1.21688967968911,51.55520552335299],"type":"Point"}
}