{
  "type": "Feature",
  "properties": {
    "iso:country":"GB",
    "wof:name":"E5 9JG",
    "wof:placetype":"postalcode"
},
  "geometry": {"coordinates":[-0.05444388737327,51.56667126726897],"type":"Point"}
}