{
  "type": "Feature",
  "properties": {
    "iso:country":"GB",
    "wof:name":"ME10 4BQ",
    "wof:placetype":"postalcode"
},
  "geometry": {"coordinates":[0.74279069708243,51.33897033000697],"type":"Point"}
}