{
  "type": "Feature",
  "properties": {
    "iso:country":"GB",
    "wof:name":"SE9 3AN",
    "wof:placetype":"postalcode"
},
  "geometry": {"coordinates":[0.05540531577651,51.43729901497979],"type":"Point"}
}