{
  "type": "Feature",
  "properties": {
    "iso:country":"GB",
    "wof:name":"BL1 3EJ",
    "wof:placetype":"postalcode"
},
  "geometry": {"coordinates":[-2.44821058980986,53.59034674334823],"type":"Point"}
}