{
  "type": "Feature",
  "properties": {
    "date:inception_lower": "1986-07-01",
    "date:inception_upper": "1986-07-01",
    "iso:country": "GB",
    "wof:name": "M12 4WW",
    "wof:placetype": "postalcode"
  },
  "geometry": {"coordinates":[-2.194707,53.461569],"type":"Point"}
}
