{
  "type": "Feature",
  "properties": {
    "iso:country": "GB",
    "wof:name": "HD7 5WE",
    "wof:placetype": "postalcode"
  },
  "geometry": {"coordinates":[-1.886034,53.619793],"type":"Point"}
}
