{
  "type": "Feature",
  "properties": {
    "date:inception_lower": "2015-10-01",
    "date:inception_upper": "2015-10-01",
    "iso:country": "GB",
    "wof:name": "HD7 5WE",
    "wof:placetype": "postalcode"
  },
  "geometry": {"coordinates":[-1.886034,53.619793],"type":"Point"}
}
