{
  "type": "Feature",
  "properties": {
    "iso:country":"GB",
    "wof:name":"NW5 2PE",
    "wof:placetype":"postalcode"
},
  "geometry": {"coordinates":[-0.13978984542238,51.55257034249872],"type":"Point"}
}