{
  "type": "Feature",
  "properties": {
    "iso:country":"GB",
    "wof:name":"PE34 3BW",
    "wof:placetype":"postalcode"
},
  "geometry": {"coordinates":[0.32387120521384,52.68664228515652],"type":"Point"}
}