{
  "type": "Feature",
  "properties": {
    "date:inception_lower": "1980-01-01",
    "date:inception_upper": "1980-01-01",
    "iso:country": "GB",
    "wof:name": "PE34 3BW",
    "wof:placetype": "postalcode"
  },
  "geometry": {"coordinates":[0.323871,52.686642],"type":"Point"}
}
