{
  "type": "Feature",
  "properties": {
    "iso:country": "GB",
    "wof:name": "PE34 3BW",
    "wof:placetype": "postalcode"
  },
  "geometry": {"coordinates":[0.323871,52.686642],"type":"Point"}
}
