{
  "type": "Feature",
  "properties": {
    "date:inception_lower": "2011-11-01",
    "date:inception_upper": "2011-11-01",
    "iso:country": "GB",
    "wof:name": "M40 7EN",
    "wof:placetype": "postalcode"
  },
  "geometry": {"coordinates":[-2.209043,53.489029],"type":"Point"}
}
