{
  "type": "Feature",
  "properties": {
    "iso:country":"GB",
    "wof:name":"ME2 2RT",
    "wof:placetype":"postalcode"
},
  "geometry": {"coordinates":[0.46384318744408,51.39039203239607],"type":"Point"}
}