{
  "type": "Feature",
  "properties": {
    "iso:country":"GB",
    "wof:name":"PA4 9RH",
    "wof:placetype":"postalcode"
},
  "geometry": {"coordinates":[-4.45111655047243,55.88074100780121],"type":"Point"}
}