{
  "type": "Feature",
  "properties": {
    "iso:country": "GB",
    "wof:name": "L18 1JH",
    "wof:placetype": "postalcode"
  },
  "geometry": {"coordinates":[-2.922303,53.386219],"type":"Point"}
}
