{
  "type": "Feature",
  "properties": {
    "iso:country": "GB",
    "wof:name": "DL14 0PT",
    "wof:placetype": "postalcode"
  },
  "geometry": {"coordinates":[-1.78941,54.650015],"type":"Point"}
}
