{
  "type": "Feature",
  "properties": {
    "iso:country": "GB",
    "wof:name": "BH23 4TN",
    "wof:placetype": "postalcode"
  },
  "geometry": {"coordinates":[-1.737389,50.737325],"type":"Point"}
}
