{
  "type": "Feature",
  "properties": {
    "iso:country":"GB",
    "wof:name":"BH23 4TN",
    "wof:placetype":"postalcode"
},
  "geometry": {"coordinates":[-1.73738917303383,50.73732452819001],"type":"Point"}
}