{
  "type": "Feature",
  "properties": {
    "date:inception_lower":"1990-02-01",
    "date:inception_upper":"1990-02-28",
    "iso:country":"GB",
    "wof:name":"BH23 4TN",
    "wof:placetype":"postalcode"
},
  "geometry": {"coordinates":[-1.737389,50.737325],"type":"Point"}
}