{
  "type": "Feature",
  "properties": {
    "iso:country":"GB",
    "wof:name":"DN33 2AD",
    "wof:placetype":"postalcode"
},
  "geometry": {"coordinates":[-0.0929495192405,53.55064869764671],"type":"Point"}
}