{
  "type": "Feature",
  "properties": {
    "date:inception_lower":"1994-05-01",
    "date:inception_upper":"1994-05-31",
    "iso:country":"GB",
    "wof:name":"M33 6NS",
    "wof:placetype":"postalcode"
},
  "geometry": {"coordinates":[-2.329508,53.426685],"type":"Point"}
}