{
  "type": "Feature",
  "properties": {
    "iso:country": "GB",
    "wof:name": "BS15 9QF",
    "wof:placetype": "postalcode"
  },
  "geometry": {"coordinates":[-2.50444,51.456782],"type":"Point"}
}
