{
  "type": "Feature",
  "properties": {
    "date:inception_lower": "2003-08-01",
    "date:inception_upper": "2003-08-01",
    "iso:country": "GB",
    "wof:name": "WR10 2BS",
    "wof:placetype": "postalcode"
  },
  "geometry": {"coordinates":[-2.107061,52.135093],"type":"Point"}
}
