{
  "type": "Feature",
  "properties": {
    "iso:country": "GB",
    "wof:name": "WR10 2BS",
    "wof:placetype": "postalcode"
  },
  "geometry": {"coordinates":[-2.107061,52.135093],"type":"Point"}
}
