{
  "type": "Feature",
  "properties": {
    "iso:country":"GB",
    "wof:name":"SN5 7ED",
    "wof:placetype":"postalcode"
},
  "geometry": {"coordinates":[-1.82709656362847,51.56357007114224],"type":"Point"}
}