{
  "type": "Feature",
  "properties": {
    "iso:country":"GB",
    "wof:name":"HU9 3BT",
    "wof:placetype":"postalcode"
},
  "geometry": {"coordinates":[-0.29883228611815,53.75854092458235],"type":"Point"}
}