{
  "type": "Feature",
  "properties": {
    "iso:country":"GB",
    "wof:name":"SP3 4FA",
    "wof:placetype":"postalcode"
},
  "geometry": {"coordinates":[-1.90196266754195,51.19548411048852],"type":"Point"}
}