{
  "type": "Feature",
  "properties": {
    "date:inception_lower":"2015-07-01",
    "date:inception_upper":"2015-07-31",
    "iso:country":"GB",
    "wof:name":"SP3 4FA",
    "wof:placetype":"postalcode"
},
  "geometry": {"coordinates":[-1.901963,51.195484],"type":"Point"}
}