{
  "type": "Feature",
  "properties": {
    "iso:country":"GB",
    "wof:name":"PE38 9RW",
    "wof:placetype":"postalcode"
},
  "geometry": {"coordinates":[0.37568878200755,52.59636269546707],"type":"Point"}
}