{
  "type": "Feature",
  "properties": {
    "date:inception_lower": "1980-01-01",
    "date:inception_upper": "1980-01-01",
    "iso:country": "GB",
    "wof:name": "KY10 3SH",
    "wof:placetype": "postalcode"
  },
  "geometry": {"coordinates":[-2.626783,56.259492],"type":"Point"}
}
