{
  "type": "Feature",
  "properties": {
    "iso:country": "GB",
    "wof:name": "BA21 5BX",
    "wof:placetype": "postalcode"
  },
  "geometry": {"coordinates":[-2.615576,50.950898],"type":"Point"}
}
