{
  "type": "Feature",
  "properties": {
    "iso:country": "GB",
    "wof:name": "PE35 6EN",
    "wof:placetype": "postalcode"
  },
  "geometry": {"coordinates":[0.516335,52.826203],"type":"Point"}
}
