{
  "type": "Feature",
  "properties": {
    "iso:country":"GB",
    "wof:name":"PE35 6EN",
    "wof:placetype":"postalcode"
},
  "geometry": {"coordinates":[0.51633472429549,52.82620331967909],"type":"Point"}
}