{
  "type": "Feature",
  "properties": {
    "date:inception_lower": "1980-01-01",
    "date:inception_upper": "1980-01-01",
    "iso:country": "GB",
    "wof:name": "PE35 6EN",
    "wof:placetype": "postalcode"
  },
  "geometry": {"coordinates":[0.516345,52.826389],"type":"Point"}
}
