{
  "type": "Feature",
  "properties": {
    "iso:country":"GB",
    "wof:name":"DL13 1NR",
    "wof:placetype":"postalcode"
},
  "geometry": {"coordinates":[-2.15639235218099,54.73644088665427],"type":"Point"}
}