{
  "type": "Feature",
  "properties": {
    "iso:country": "GB",
    "wof:name": "DL13 1NR",
    "wof:placetype": "postalcode"
  },
  "geometry": {"coordinates":[-2.156392,54.736441],"type":"Point"}
}
