{
  "type": "Feature",
  "properties": {
    "iso:country":"GB",
    "wof:name":"NE5 5DH",
    "wof:placetype":"postalcode"
},
  "geometry": {"coordinates":[-1.70086313336253,54.98727179778733],"type":"Point"}
}