{
  "type": "Feature",
  "properties": {
    "iso:country":"GB",
    "wof:name":"BR2 7BD",
    "wof:placetype":"postalcode"
},
  "geometry": {"coordinates":[0.01832051799174,51.37643246466182],"type":"Point"}
}