{
  "type": "Feature",
  "properties": {
    "iso:country":"GB",
    "wof:name":"EH22 4LE",
    "wof:placetype":"postalcode"
},
  "geometry": {"coordinates":[-3.06477504360683,55.86624507758429],"type":"Point"}
}