{
  "type": "Feature",
  "properties": {
    "iso:country": "GB",
    "wof:name": "DN14 7XT",
    "wof:placetype": "postalcode"
  },
  "geometry": {"coordinates":[-0.722038,53.718946],"type":"Point"}
}
