{
  "type": "Feature",
  "properties": {
    "iso:country":"GB",
    "wof:name":"DN14 7XT",
    "wof:placetype":"postalcode"
},
  "geometry": {"coordinates":[-0.72203822073705,53.71894583582202],"type":"Point"}
}