{
  "type": "Feature",
  "properties": {
    "date:inception_lower":"1980-01-01",
    "date:inception_upper":"1980-01-31",
    "iso:country":"GB",
    "wof:name":"DN21 3NE",
    "wof:placetype":"postalcode"
},
  "geometry": {"coordinates":[-0.721779,53.441077],"type":"Point"}
}