{
  "type": "Feature",
  "properties": {
    "iso:country": "GB",
    "wof:name": "DN21 3NE",
    "wof:placetype": "postalcode"
  },
  "geometry": {"coordinates":[-0.721779,53.441077],"type":"Point"}
}
