{
  "type": "Feature",
  "properties": {
    "iso:country":"GB",
    "wof:name":"DN21 3NE",
    "wof:placetype":"postalcode"
},
  "geometry": {"coordinates":[-0.72177922525138,53.44107688979592],"type":"Point"}
}