{
  "type": "Feature",
  "properties": {
    "date:inception_lower": "1998-06-01",
    "date:inception_upper": "1998-06-01",
    "iso:country": "GB",
    "wof:name": "YO17 6RH",
    "wof:placetype": "postalcode"
  },
  "geometry": {"coordinates":[-0.772271,54.180222],"type":"Point"}
}
