{
  "type": "Feature",
  "properties": {
    "iso:country": "GB",
    "wof:name": "YO17 6RH",
    "wof:placetype": "postalcode"
  },
  "geometry": {"coordinates":[-0.781725,54.184526],"type":"Point"}
}
