{
  "type": "Feature",
  "properties": {
    "date:inception_lower": "2010-12-01",
    "date:inception_upper": "2010-12-01",
    "iso:country": "GB",
    "wof:name": "BB8 9PN",
    "wof:placetype": "postalcode"
  },
  "geometry": {"coordinates":[-2.193769,53.856187],"type":"Point"}
}
