{
  "type": "Feature",
  "properties": {
    "iso:country":"GB",
    "wof:name":"BB8 9PN",
    "wof:placetype":"postalcode"
},
  "geometry": {"coordinates":[-2.19376918027837,53.85618728077576],"type":"Point"}
}