{
  "type": "Feature",
  "properties": {
    "iso:country":"GB",
    "wof:name":"CT21 6PH",
    "wof:placetype":"postalcode"
},
  "geometry": {"coordinates":[1.061272300301,51.06593826970349],"type":"Point"}
}