{
  "type": "Feature",
  "properties": {
    "iso:country":"GB",
    "wof:name":"PR6 8JD",
    "wof:placetype":"postalcode"
},
  "geometry": {"coordinates":[-2.58356869546065,53.69844969425314],"type":"Point"}
}