{
  "type": "Feature",
  "properties": {
    "date:inception_lower":"1980-01-01",
    "date:inception_upper":"1980-01-31",
    "iso:country":"GB",
    "wof:name":"PR6 8JD",
    "wof:placetype":"postalcode"
},
  "geometry": {"coordinates":[-2.583569,53.69845],"type":"Point"}
}