{
  "type": "Feature",
  "properties": {
    "iso:country":"GB",
    "wof:name":"NN10 0EQ",
    "wof:placetype":"postalcode"
},
  "geometry": {"coordinates":[-0.59150818055246,52.29046991902973],"type":"Point"}
}