{
  "type": "Feature",
  "properties": {
    "iso:country":"GB",
    "wof:name":"E11 3JJ",
    "wof:placetype":"postalcode"
},
  "geometry": {"coordinates":[0.00699481398525,51.5558434768388],"type":"Point"}
}