{
  "type": "Feature",
  "properties": {
    "date:inception_lower":"1999-06-01",
    "date:inception_upper":"1999-06-30",
    "iso:country":"GB",
    "wof:name":"LL52 0LJ",
    "wof:placetype":"postalcode"
},
  "geometry": {"coordinates":[-4.297461,52.916743],"type":"Point"}
}