{
  "type": "Feature",
  "properties": {
    "iso:country":"GB",
    "wof:name":"LL52 0LJ",
    "wof:placetype":"postalcode"
},
  "geometry": {"coordinates":[-4.29746127835485,52.91674261055545],"type":"Point"}
}