{
  "type": "Feature",
  "properties": {
    "iso:country": "GB",
    "wof:name": "HX6 1NT",
    "wof:placetype": "postalcode"
  },
  "geometry": {"coordinates":[-1.943146,53.701567],"type":"Point"}
}
