{
  "type": "Feature",
  "properties": {
    "iso:country":"GB",
    "wof:name":"HA7 1FD",
    "wof:placetype":"postalcode"
},
  "geometry": {"coordinates":[-0.29776788110253,51.60541508683035],"type":"Point"}
}