{
  "type": "Feature",
  "properties": {
    "iso:country": "GB",
    "wof:name": "HX1 1LN",
    "wof:placetype": "postalcode"
  },
  "geometry": {"coordinates":[-1.862196,53.721428],"type":"Point"}
}
