{
  "type": "Feature",
  "properties": {
    "iso:country":"GB",
    "wof:name":"HX1 1LN",
    "wof:placetype":"postalcode"
},
  "geometry": {"coordinates":[-1.8621958497323,53.72142769175849],"type":"Point"}
}