{
  "type": "Feature",
  "properties": {
    "iso:country":"GB",
    "wof:name":"IP23 8AF",
    "wof:placetype":"postalcode"
},
  "geometry": {"coordinates":[1.15873447377387,52.34615708569162],"type":"Point"}
}