{
  "type": "Feature",
  "properties": {
    "iso:country":"GB",
    "wof:name":"G63 9SF",
    "wof:placetype":"postalcode"
},
  "geometry": {"coordinates":[-4.37875306627661,56.0411164432007],"type":"Point"}
}