{
  "type": "Feature",
  "properties": {
    "date:inception_lower":"2002-10-01",
    "date:inception_upper":"2002-10-31",
    "iso:country":"GB",
    "wof:name":"WD18 0BT",
    "wof:placetype":"postalcode"
},
  "geometry": {"coordinates":[-0.391324,51.649717],"type":"Point"}
}