{
  "type": "Feature",
  "properties": {
    "iso:country":"GB",
    "wof:name":"WA15 8QW",
    "wof:placetype":"postalcode"
},
  "geometry": {"coordinates":[-2.32408200490537,53.38403083618573],"type":"Point"}
}