{
  "type": "Feature",
  "properties": {
    "iso:country":"GB",
    "wof:name":"BH9 2AA",
    "wof:placetype":"postalcode"
},
  "geometry": {"coordinates":[-1.87930540462716,50.73949085876022],"type":"Point"}
}