{
  "type": "Feature",
  "properties": {
    "iso:country": "GB",
    "wof:name": "WF4 3LR",
    "wof:placetype": "postalcode"
  },
  "geometry": {"coordinates":[-1.521882,53.629952],"type":"Point"}
}
