{
  "type": "Feature",
  "properties": {
    "iso:country":"GB",
    "wof:name":"WF4 3LR",
    "wof:placetype":"postalcode"
},
  "geometry": {"coordinates":[-1.52188245259756,53.62995245119877],"type":"Point"}
}