{
  "type": "Feature",
  "properties": {
    "iso:country": "GB",
    "wof:name": "WS1 4ED",
    "wof:placetype": "postalcode"
  },
  "geometry": {"coordinates":[-1.981486,52.566929],"type":"Point"}
}
