{
  "type": "Feature",
  "properties": {
    "date:inception_lower":"1980-01-01",
    "date:inception_upper":"1980-01-31",
    "iso:country":"GB",
    "wof:name":"WS1 4ED",
    "wof:placetype":"postalcode"
},
  "geometry": {"coordinates":[-1.981486,52.566929],"type":"Point"}
}