{
  "type": "Feature",
  "properties": {
    "iso:country":"GB",
    "wof:name":"NE46 1XG",
    "wof:placetype":"postalcode"
},
  "geometry": {"coordinates":[-2.10049141882682,54.97139510485432],"type":"Point"}
}