{
  "type": "Feature",
  "properties": {
    "iso:country":"GB",
    "wof:name":"BB9 0PS",
    "wof:placetype":"postalcode"
},
  "geometry": {"coordinates":[-2.21924353759884,53.82605186848544],"type":"Point"}
}