{
  "type": "Feature",
  "properties": {
    "iso:country":"GB",
    "wof:name":"NN17 1LS",
    "wof:placetype":"postalcode"
},
  "geometry": {"coordinates":[-0.7044146416468,52.49198476909498],"type":"Point"}
}