{
  "type": "Feature",
  "properties": {
    "iso:country": "GB",
    "wof:name": "NN17 1LS",
    "wof:placetype": "postalcode"
  },
  "geometry": {"coordinates":[-0.704415,52.491985],"type":"Point"}
}
