{
  "type": "Feature",
  "properties": {
    "iso:country":"GB",
    "wof:name":"E18 2JX",
    "wof:placetype":"postalcode"
},
  "geometry": {"coordinates":[0.01764001766622,51.59459889680349],"type":"Point"}
}