{
  "type": "Feature",
  "properties": {
    "iso:country":"GB",
    "wof:name":"DA16 3NQ",
    "wof:placetype":"postalcode"
},
  "geometry": {"coordinates":[0.09498964537058,51.47128364984243],"type":"Point"}
}