{
  "type": "Feature",
  "properties": {
    "date:inception_lower":"1980-01-01",
    "date:inception_upper":"1980-01-31",
    "iso:country":"GB",
    "wof:name":"DA16 3NQ",
    "wof:placetype":"postalcode"
},
  "geometry": {"coordinates":[0.09499,51.471284],"type":"Point"}
}