{
  "type": "Feature",
  "properties": {
    "iso:country": "GB",
    "wof:name": "DA16 3NQ",
    "wof:placetype": "postalcode"
  },
  "geometry": {"coordinates":[0.09499,51.471284],"type":"Point"}
}
