{
  "type": "Feature",
  "properties": {
    "iso:country":"GB",
    "wof:name":"IP25 7JN",
    "wof:placetype":"postalcode"
},
  "geometry": {"coordinates":[0.81242608710736,52.59431871182549],"type":"Point"}
}