{
  "type": "Feature",
  "properties": {
    "iso:country":"GB",
    "wof:name":"NE33 1HU",
    "wof:placetype":"postalcode"
},
  "geometry": {"coordinates":[-1.43380362791968,54.99854394689142],"type":"Point"}
}