{
  "type": "Feature",
  "properties": {
    "iso:country": "GB",
    "wof:name": "NE33 1HU",
    "wof:placetype": "postalcode"
  },
  "geometry": {"coordinates":[-1.433804,54.998544],"type":"Point"}
}
