{
  "type": "Feature",
  "properties": {
    "iso:country":"GB",
    "wof:name":"DY6 9PP",
    "wof:placetype":"postalcode"
},
  "geometry": {"coordinates":[-2.1659614436207,52.48932090186869],"type":"Point"}
}