{
  "type": "Feature",
  "properties": {
    "date:inception_lower": "1980-01-01",
    "date:inception_upper": "1980-01-01",
    "iso:country": "GB",
    "wof:name": "DY6 9PP",
    "wof:placetype": "postalcode"
  },
  "geometry": {"coordinates":[-2.16597,52.489353],"type":"Point"}
}
