{
  "type": "Feature",
  "properties": {
    "iso:country":"GB",
    "wof:name":"SS15 6AW",
    "wof:placetype":"postalcode"
},
  "geometry": {"coordinates":[0.41881226065282,51.57634932434971],"type":"Point"}
}