{
  "type": "Feature",
  "properties": {
    "iso:country":"GB",
    "wof:name":"FY1 6DA",
    "wof:placetype":"postalcode"
},
  "geometry": {"coordinates":[-3.0523478107034,53.80088042643884],"type":"Point"}
}