{
  "type": "Feature",
  "properties": {
    "date:inception_lower": "1980-01-01",
    "date:inception_upper": "1980-01-01",
    "iso:country": "GB",
    "wof:name": "OX11 9JN",
    "wof:placetype": "postalcode"
  },
  "geometry": {"coordinates":[-1.25917,51.580692],"type":"Point"}
}
