{
  "type": "Feature",
  "properties": {
    "iso:country":"GB",
    "wof:name":"OX11 9JN",
    "wof:placetype":"postalcode"
},
  "geometry": {"coordinates":[-1.25917037118131,51.58069221619002],"type":"Point"}
}