{
  "type": "Feature",
  "properties": {
    "iso:country": "GB",
    "wof:name": "KT10 0JF",
    "wof:placetype": "postalcode"
  },
  "geometry": {"coordinates":[-0.337444,51.355718],"type":"Point"}
}
