{
  "type": "Feature",
  "properties": {
    "date:inception_lower": "1980-01-01",
    "date:inception_upper": "1980-01-01",
    "iso:country": "GB",
    "wof:name": "EH15 1HF",
    "wof:placetype": "postalcode"
  },
  "geometry": {"coordinates":[-3.111148,55.954638],"type":"Point"}
}
