{
  "type": "Feature",
  "properties": {
    "date:inception_lower": "1980-01-01",
    "date:inception_upper": "1980-01-01",
    "iso:country": "GB",
    "wof:name": "TA8 2QE",
    "wof:placetype": "postalcode"
  },
  "geometry": {"coordinates":[-2.994727,51.250639],"type":"Point"}
}
