{
  "type": "Feature",
  "properties": {
    "iso:country":"GB",
    "wof:name":"TA8 2QE",
    "wof:placetype":"postalcode"
},
  "geometry": {"coordinates":[-2.99470428077992,51.25066103605652],"type":"Point"}
}