{
  "type": "Feature",
  "properties": {
    "date:inception_lower": "1980-01-01",
    "date:inception_upper": "1980-01-01",
    "iso:country": "GB",
    "wof:name": "IG4 5NW",
    "wof:placetype": "postalcode"
  },
  "geometry": {"coordinates":[0.057426,51.582973],"type":"Point"}
}
