{
  "type": "Feature",
  "properties": {
    "iso:country":"GB",
    "wof:name":"LL12 8TB",
    "wof:placetype":"postalcode"
},
  "geometry": {"coordinates":[-2.95841329816171,53.09835381673292],"type":"Point"}
}