{
  "type": "Feature",
  "properties": {
    "date:inception_lower": "2005-04-01",
    "date:inception_upper": "2005-04-01",
    "iso:country": "GB",
    "wof:name": "HR1 4NH",
    "wof:placetype": "postalcode"
  },
  "geometry": {"coordinates":[-2.618401,52.007191],"type":"Point"}
}
