{
  "type": "Feature",
  "properties": {
    "iso:country":"GB",
    "wof:name":"NN17 2SX",
    "wof:placetype":"postalcode"
},
  "geometry": {"coordinates":[-0.72096586322188,52.49619257261009],"type":"Point"}
}