{
  "type": "Feature",
  "properties": {
    "date:inception_lower": "1980-01-01",
    "date:inception_upper": "1980-01-01",
    "iso:country": "GB",
    "wof:name": "NN17 2SX",
    "wof:placetype": "postalcode"
  },
  "geometry": {"coordinates":[-0.720966,52.496193],"type":"Point"}
}
