{
  "type": "Feature",
  "properties": {
    "iso:country":"GB",
    "wof:name":"TS15 0DT",
    "wof:placetype":"postalcode"
},
  "geometry": {"coordinates":[-1.29442421819723,54.44887553605543],"type":"Point"}
}