{
  "type": "Feature",
  "properties": {
    "iso:country":"GB",
    "wof:name":"ML4 1EG",
    "wof:placetype":"postalcode"
},
  "geometry": {"coordinates":[-3.98588786899544,55.82051360264648],"type":"Point"}
}