{
  "type": "Feature",
  "properties": {
    "date:inception_lower":"1982-08-01",
    "date:inception_upper":"1982-08-31",
    "iso:country":"GB",
    "wof:name":"ML4 1EG",
    "wof:placetype":"postalcode"
},
  "geometry": {"coordinates":[-3.985888,55.820514],"type":"Point"}
}