{
  "type": "Feature",
  "properties": {
    "date:inception_lower": "2011-05-01",
    "date:inception_upper": "2011-05-01",
    "iso:country": "GB",
    "wof:name": "TF4 3EQ",
    "wof:placetype": "postalcode"
  },
  "geometry": {"coordinates":[-2.484648,52.651485],"type":"Point"}
}
