{
  "type": "Feature",
  "properties": {
    "iso:country":"GB",
    "wof:name":"TF4 3EQ",
    "wof:placetype":"postalcode"
},
  "geometry": {"coordinates":[-2.48464843803873,52.65148494133564],"type":"Point"}
}