{
  "type": "Feature",
  "properties": {
    "iso:country": "GB",
    "wof:name": "PE13 2SL",
    "wof:placetype": "postalcode"
  },
  "geometry": {"coordinates":[0.174716,52.653166],"type":"Point"}
}
