{
  "type": "Feature",
  "properties": {
    "date:inception_lower":"1980-01-01",
    "date:inception_upper":"1980-01-31",
    "iso:country":"GB",
    "wof:name":"PE13 2SL",
    "wof:placetype":"postalcode"
},
  "geometry": {"coordinates":[0.174716,52.653166],"type":"Point"}
}