{
  "type": "Feature",
  "properties": {
    "iso:country": "GB",
    "wof:name": "NP4 7RY",
    "wof:placetype": "postalcode"
  },
  "geometry": {"coordinates":[-3.064902,51.74328],"type":"Point"}
}
