{
  "type": "Feature",
  "properties": {
    "iso:country":"GB",
    "wof:name":"L25 5LX",
    "wof:placetype":"postalcode"
},
  "geometry": {"coordinates":[-2.852327952804,53.37567420796633],"type":"Point"}
}