{
  "type": "Feature",
  "properties": {
    "date:inception_lower": "1980-01-01",
    "date:inception_upper": "1980-01-01",
    "iso:country": "GB",
    "wof:name": "TW12 3BG",
    "wof:placetype": "postalcode"
  },
  "geometry": {"coordinates":[-0.374005,51.422748],"type":"Point"}
}
