{
  "type": "Feature",
  "properties": {
    "iso:country":"GB",
    "wof:name":"N21 1SN",
    "wof:placetype":"postalcode"
},
  "geometry": {"coordinates":[-0.1171682219116,51.64657589445028],"type":"Point"}
}