{
  "type": "Feature",
  "properties": {
    "date:inception_lower": "1996-06-01",
    "date:inception_upper": "1996-06-01",
    "iso:country": "GB",
    "wof:name": "N21 1SN",
    "wof:placetype": "postalcode"
  },
  "geometry": {"coordinates":[-0.117168,51.646576],"type":"Point"}
}
