{
  "type": "Feature",
  "properties": {
    "iso:country":"GB",
    "wof:name":"CM5 0DH",
    "wof:placetype":"postalcode"
},
  "geometry": {"coordinates":[0.21876093602825,51.73211905003912],"type":"Point"}
}