{
  "type": "Feature",
  "properties": {
    "iso:country":"GB",
    "wof:name":"S80 1PX",
    "wof:placetype":"postalcode"
},
  "geometry": {"coordinates":[-1.12256533812696,53.31056897259769],"type":"Point"}
}