{
  "type": "Feature",
  "properties": {
    "iso:country": "GB",
    "wof:name": "S80 1PX",
    "wof:placetype": "postalcode"
  },
  "geometry": {"coordinates":[-1.122565,53.310569],"type":"Point"}
}
