{
  "type": "Feature",
  "properties": {
    "date:inception_lower": "2014-09-01",
    "date:inception_upper": "2014-09-01",
    "iso:country": "GB",
    "wof:name": "YO10 5FP",
    "wof:placetype": "postalcode"
  },
  "geometry": {"coordinates":[-1.025828,53.948791],"type":"Point"}
}
