{
  "type": "Feature",
  "properties": {
    "iso:country": "GB",
    "wof:name": "GU28 8BH",
    "wof:placetype": "postalcode"
  },
  "geometry": {"coordinates":[-0.608809,50.986679],"type":"Point"}
}
