{
  "type": "Feature",
  "properties": {
    "date:inception_lower": "1992-01-01",
    "date:inception_upper": "1992-01-01",
    "iso:country": "GB",
    "wof:name": "HP14 3LL",
    "wof:placetype": "postalcode"
  },
  "geometry": {"coordinates":[-0.833117,51.617442],"type":"Point"}
}
