{
  "type": "Feature",
  "properties": {
    "iso:country":"GB",
    "wof:name":"HP14 3LL",
    "wof:placetype":"postalcode"
},
  "geometry": {"coordinates":[-0.83311668674468,51.61744157902469],"type":"Point"}
}