{
  "type": "Feature",
  "properties": {
    "iso:country": "GB",
    "wof:name": "SE1 9HN",
    "wof:placetype": "postalcode"
  },
  "geometry": {"coordinates":[-0.094276,51.506059],"type":"Point"}
}
