{
  "type": "Feature",
  "properties": {
    "iso:country":"GB",
    "wof:name":"M9 6SL",
    "wof:placetype":"postalcode"
},
  "geometry": {"coordinates":[-2.20915958488342,53.52458909394732],"type":"Point"}
}