{
  "type": "Feature",
  "properties": {
    "iso:country":"GB",
    "wof:name":"TS5 6DW",
    "wof:placetype":"postalcode"
},
  "geometry": {"coordinates":[-1.24777749373206,54.56047522884876],"type":"Point"}
}