{
  "type": "Feature",
  "properties": {
    "iso:country":"GB",
    "wof:name":"PA16 0FQ",
    "wof:placetype":"postalcode"
},
  "geometry": {"coordinates":[-4.86778127052577,55.90539701105838],"type":"Point"}
}