{
  "type": "Feature",
  "properties": {
    "iso:country":"GB",
    "wof:name":"DD9 7HW",
    "wof:placetype":"postalcode"
},
  "geometry": {"coordinates":[-2.65160883946953,56.7263433545654],"type":"Point"}
}