{
  "type": "Feature",
  "properties": {
    "iso:country":"GB",
    "wof:name":"PE12 9JL",
    "wof:placetype":"postalcode"
},
  "geometry": {"coordinates":[0.115215115819,52.78919259150523],"type":"Point"}
}