{
  "type": "Feature",
  "properties": {
    "date:inception_lower": "1980-01-01",
    "date:inception_upper": "1980-01-01",
    "iso:country": "GB",
    "wof:name": "WR8 0DG",
    "wof:placetype": "postalcode"
  },
  "geometry": {"coordinates":[-2.276661,52.081701],"type":"Point"}
}
