{
  "type": "Feature",
  "properties": {
    "date:inception_lower": "2006-09-01",
    "date:inception_upper": "2006-09-01",
    "iso:country": "GB",
    "wof:name": "DA11 8BD",
    "wof:placetype": "postalcode"
  },
  "geometry": {"coordinates":[0.338136,51.435435],"type":"Point"}
}
