{
  "type": "Feature",
  "properties": {
    "date:inception_lower":"1980-01-01",
    "date:inception_upper":"1980-01-31",
    "iso:country":"GB",
    "wof:name":"NR17 1AE",
    "wof:placetype":"postalcode"
},
  "geometry": {"coordinates":[0.991414,52.525279],"type":"Point"}
}