{
  "type": "Feature",
  "properties": {
    "iso:country": "GB",
    "wof:name": "NR17 1AE",
    "wof:placetype": "postalcode"
  },
  "geometry": {"coordinates":[0.993455,52.525484],"type":"Point"}
}
