{
  "type": "Feature",
  "properties": {
    "iso:country":"GB",
    "wof:name":"NR17 1AE",
    "wof:placetype":"postalcode"
},
  "geometry": {"coordinates":[0.99141366185837,52.52527914354041],"type":"Point"}
}