{
  "type": "Feature",
  "properties": {
    "iso:country":"GB",
    "wof:name":"WF3 1WD",
    "wof:placetype":"postalcode"
},
  "geometry": {"coordinates":[-1.57837785385243,53.71477072198658],"type":"Point"}
}