{
  "type": "Feature",
  "properties": {
    "date:inception_lower": "2002-11-01",
    "date:inception_upper": "2002-11-01",
    "iso:country": "GB",
    "wof:name": "WF3 1WD",
    "wof:placetype": "postalcode"
  },
  "geometry": {"coordinates":[-1.578378,53.714771],"type":"Point"}
}
