{
  "type": "Feature",
  "properties": {
    "iso:country":"GB",
    "wof:name":"SE20 7EU",
    "wof:placetype":"postalcode"
},
  "geometry": {"coordinates":[-0.05215536857159,51.41411809963663],"type":"Point"}
}