{
  "type": "Feature",
  "properties": {
    "iso:country":"GB",
    "wof:name":"G74 5AF",
    "wof:placetype":"postalcode"
},
  "geometry": {"coordinates":[-4.25036457532097,55.76950056349066],"type":"Point"}
}