{
  "type": "Feature",
  "properties": {
    "iso:country":"GB",
    "wof:name":"EX31 4DW",
    "wof:placetype":"postalcode"
},
  "geometry": {"coordinates":[-4.07520625203108,51.11251499426677],"type":"Point"}
}