{
  "type": "Feature",
  "properties": {
    "iso:country":"GB",
    "wof:name":"TN17 4JB",
    "wof:placetype":"postalcode"
},
  "geometry": {"coordinates":[0.61208893466538,51.06260805894209],"type":"Point"}
}