{
  "type": "Feature",
  "properties": {
    "date:inception_lower": "1980-01-01",
    "date:inception_upper": "1980-01-01",
    "iso:country": "GB",
    "wof:name": "TN17 4JB",
    "wof:placetype": "postalcode"
  },
  "geometry": {"coordinates":[0.61202,51.062897],"type":"Point"}
}
