{
  "type": "Feature",
  "properties": {
    "iso:country": "GB",
    "wof:name": "EH26 9JW",
    "wof:placetype": "postalcode"
  },
  "geometry": {"coordinates":[-3.239973,55.832615],"type":"Point"}
}
