{
  "type": "Feature",
  "properties": {
    "iso:country":"GB",
    "wof:name":"EH26 9JW",
    "wof:placetype":"postalcode"
},
  "geometry": {"coordinates":[-3.23997333293089,55.83261535439702],"type":"Point"}
}