{
  "type": "Feature",
  "properties": {
    "iso:country":"GB",
    "wof:name":"CM7 5RU",
    "wof:placetype":"postalcode"
},
  "geometry": {"coordinates":[0.54466037695947,51.88780034919692],"type":"Point"}
}