{
  "type": "Feature",
  "properties": {
    "date:inception_lower":"1985-10-01",
    "date:inception_upper":"1985-10-31",
    "iso:country":"GB",
    "wof:name":"CM7 5RU",
    "wof:placetype":"postalcode"
},
  "geometry": {"coordinates":[0.54466,51.8878],"type":"Point"}
}