{
  "type": "Feature",
  "properties": {
    "iso:country": "GB",
    "wof:name": "CM7 5RU",
    "wof:placetype": "postalcode"
  },
  "geometry": {"coordinates":[0.54466,51.8878],"type":"Point"}
}
