{
  "type": "Feature",
  "properties": {
    "iso:country":"GB",
    "wof:name":"EH48 4JF",
    "wof:placetype":"postalcode"
},
  "geometry": {"coordinates":[-3.6443823105215,55.90512789945388],"type":"Point"}
}