{
  "type": "Feature",
  "properties": {
    "date:inception_lower": "1980-01-01",
    "date:inception_upper": "1980-01-01",
    "iso:country": "GB",
    "wof:name": "EH48 4JF",
    "wof:placetype": "postalcode"
  },
  "geometry": {"coordinates":[-3.644382,55.905128],"type":"Point"}
}
