{
  "type": "Feature",
  "properties": {
    "iso:country": "GB",
    "wof:name": "FK9 4BQ",
    "wof:placetype": "postalcode"
  },
  "geometry": {"coordinates":[-3.942091,56.149899],"type":"Point"}
}
