{
  "type": "Feature",
  "properties": {
    "iso:country":"GB",
    "wof:name":"DL12 0DR",
    "wof:placetype":"postalcode"
},
  "geometry": {"coordinates":[-1.98972183243866,54.59497491784062],"type":"Point"}
}