{
  "type": "Feature",
  "properties": {
    "iso:country": "GB",
    "wof:name": "SA33 4EJ",
    "wof:placetype": "postalcode"
  },
  "geometry": {"coordinates":[-4.497525,51.810759],"type":"Point"}
}
