{
  "type": "Feature",
  "properties": {
    "iso:country":"GB",
    "wof:name":"TF2 7HY",
    "wof:placetype":"postalcode"
},
  "geometry": {"coordinates":[-2.44623727484096,52.71595732325568],"type":"Point"}
}