{
  "type": "Feature",
  "properties": {
    "iso:country": "GB",
    "wof:name": "SA4 4ZB",
    "wof:placetype": "postalcode"
  },
  "geometry": {"coordinates":[-4.0566,51.668723],"type":"Point"}
}
