{
  "type": "Feature",
  "properties": {
    "iso:country":"GB",
    "wof:name":"SA4 4ZB",
    "wof:placetype":"postalcode"
},
  "geometry": {"coordinates":[-4.0566005213707,51.66872264469247],"type":"Point"}
}