{
  "type": "Feature",
  "properties": {
    "iso:country":"GB",
    "wof:name":"GL3 4HN",
    "wof:placetype":"postalcode"
},
  "geometry": {"coordinates":[-2.15530163476732,51.8444417183797],"type":"Point"}
}