{
  "type": "Feature",
  "properties": {
    "iso:country":"GB",
    "wof:name":"OX26 3YA",
    "wof:placetype":"postalcode"
},
  "geometry": {"coordinates":[-1.15392462080994,51.91228187188192],"type":"Point"}
}