{
  "type": "Feature",
  "properties": {
    "iso:country":"GB",
    "wof:name":"DT10 1HA",
    "wof:placetype":"postalcode"
},
  "geometry": {"coordinates":[-2.27959530400144,50.93653088210045],"type":"Point"}
}