{
  "type": "Feature",
  "properties": {
    "iso:country":"GB",
    "wof:name":"G81 2DR",
    "wof:placetype":"postalcode"
},
  "geometry": {"coordinates":[-4.40558892284239,55.90649076354468],"type":"Point"}
}