{
  "type": "Feature",
  "properties": {
    "date:inception_lower": "1982-08-01",
    "date:inception_upper": "1982-08-01",
    "iso:country": "GB",
    "wof:name": "G81 2DR",
    "wof:placetype": "postalcode"
  },
  "geometry": {"coordinates":[-4.405387,55.906048],"type":"Point"}
}
