{
  "type": "Feature",
  "properties": {
    "iso:country": "GB",
    "wof:name": "IP14 5PY",
    "wof:placetype": "postalcode"
  },
  "geometry": {"coordinates":[1.133236,52.251199],"type":"Point"}
}
