{
  "type": "Feature",
  "properties": {
    "iso:country": "GB",
    "wof:name": "EH11 2TN",
    "wof:placetype": "postalcode"
  },
  "geometry": {"coordinates":[-3.243578,55.93847],"type":"Point"}
}
