{
  "type": "Feature",
  "properties": {
    "date:inception_lower": "1980-01-01",
    "date:inception_upper": "1980-01-01",
    "iso:country": "GB",
    "wof:name": "DA8 3QF",
    "wof:placetype": "postalcode"
  },
  "geometry": {"coordinates":[0.181614,51.466755],"type":"Point"}
}
