{
  "type": "Feature",
  "properties": {
    "iso:country":"GB",
    "wof:name":"DA8 3QF",
    "wof:placetype":"postalcode"
},
  "geometry": {"coordinates":[0.18214195472325,51.46480162776761],"type":"Point"}
}