{
  "type": "Feature",
  "properties": {
    "date:inception_lower": "1998-12-01",
    "date:inception_upper": "1998-12-01",
    "iso:country": "GB",
    "wof:name": "G66 8HR",
    "wof:placetype": "postalcode"
  },
  "geometry": {"coordinates":[-4.167306,55.961209],"type":"Point"}
}
