{
  "type": "Feature",
  "properties": {
    "iso:country": "GB",
    "wof:name": "G66 8HR",
    "wof:placetype": "postalcode"
  },
  "geometry": {"coordinates":[-4.167306,55.961209],"type":"Point"}
}
