{
  "type": "Feature",
  "properties": {
    "date:inception_lower": "2001-12-01",
    "date:inception_upper": "2001-12-01",
    "iso:country": "GB",
    "wof:name": "PE15 0SH",
    "wof:placetype": "postalcode"
  },
  "geometry": {"coordinates":[0.05893,52.51604],"type":"Point"}
}
