{
  "type": "Feature",
  "properties": {
    "iso:country":"GB",
    "wof:name":"DE72 3FZ",
    "wof:placetype":"postalcode"
},
  "geometry": {"coordinates":[-1.37439874626726,52.90566560805978],"type":"Point"}
}