{
  "type": "Feature",
  "properties": {
    "date:inception_lower": "2017-03-01",
    "date:inception_upper": "2017-03-01",
    "iso:country": "GB",
    "wof:name": "AB21 0BY",
    "wof:placetype": "postalcode"
  },
  "geometry": {"coordinates":[-2.205188,57.196568],"type":"Point"}
}
