{
  "type": "Feature",
  "properties": {
    "iso:country":"GB",
    "wof:name":"E3 5PG",
    "wof:placetype":"postalcode"
},
  "geometry": {"coordinates":[-0.03355285654962,51.53283462820948],"type":"Point"}
}