{
  "type": "Feature",
  "properties": {
    "iso:country":"GB",
    "wof:name":"LS25 7BB",
    "wof:placetype":"postalcode"
},
  "geometry": {"coordinates":[-1.36450969842067,53.76690312601779],"type":"Point"}
}