{
  "type": "Feature",
  "properties": {
    "iso:country": "GB",
    "wof:name": "CB10 2PJ",
    "wof:placetype": "postalcode"
  },
  "geometry": {"coordinates":[0.37759,52.025331],"type":"Point"}
}
