{
  "type": "Feature",
  "properties": {
    "iso:country":"GB",
    "wof:name":"NR34 0BD",
    "wof:placetype":"postalcode"
},
  "geometry": {"coordinates":[1.62359958917278,52.47313591740144],"type":"Point"}
}