{
  "type": "Feature",
  "properties": {
    "iso:country":"GB",
    "wof:name":"B60 2NB",
    "wof:placetype":"postalcode"
},
  "geometry": {"coordinates":[-2.05735187563349,52.33418321719495],"type":"Point"}
}