{
  "type": "Feature",
  "properties": {
    "iso:country":"GB",
    "wof:name":"KA10 7NE",
    "wof:placetype":"postalcode"
},
  "geometry": {"coordinates":[-4.6432923010456,55.5611279075337],"type":"Point"}
}