{
  "type": "Feature",
  "properties": {
    "date:inception_lower": "2007-04-01",
    "date:inception_upper": "2007-04-01",
    "iso:country": "GB",
    "wof:name": "KA10 7NE",
    "wof:placetype": "postalcode"
  },
  "geometry": {"coordinates":[-4.643292,55.561128],"type":"Point"}
}
