{
  "type": "Feature",
  "properties": {
    "iso:country":"GB",
    "wof:name":"SE2 0XX",
    "wof:placetype":"postalcode"
},
  "geometry": {"coordinates":[0.10363967001744,51.48027448816911],"type":"Point"}
}