{
  "type": "Feature",
  "properties": {
    "iso:country": "GB",
    "wof:name": "NW10 1HL",
    "wof:placetype": "postalcode"
  },
  "geometry": {"coordinates":[-0.234296,51.55413],"type":"Point"}
}
