{
  "type": "Feature",
  "properties": {
    "date:inception_lower":"1980-01-01",
    "date:inception_upper":"1980-01-31",
    "iso:country":"GB",
    "wof:name":"NW10 1HL",
    "wof:placetype":"postalcode"
},
  "geometry": {"coordinates":[-0.234296,51.55413],"type":"Point"}
}