{
  "type": "Feature",
  "properties": {
    "date:inception_lower": "2001-12-01",
    "date:inception_upper": "2001-12-01",
    "iso:country": "GB",
    "wof:name": "CH2 3HA",
    "wof:placetype": "postalcode"
  },
  "geometry": {"coordinates":[-2.868232,53.195941],"type":"Point"}
}
