{
  "type": "Feature",
  "properties": {
    "iso:country":"GB",
    "wof:name":"DA8 1EH",
    "wof:placetype":"postalcode"
},
  "geometry": {"coordinates":[0.1592495107958,51.47607101393308],"type":"Point"}
}