{
  "type": "Feature",
  "properties": {
    "iso:country":"GB",
    "wof:name":"CO3 0PB",
    "wof:placetype":"postalcode"
},
  "geometry": {"coordinates":[0.83914887453986,51.88747205554891],"type":"Point"}
}