{
  "type": "Feature",
  "properties": {
    "iso:country": "GB",
    "wof:name": "CO3 0PB",
    "wof:placetype": "postalcode"
  },
  "geometry": {"coordinates":[0.839149,51.887472],"type":"Point"}
}
