{
  "type": "Feature",
  "properties": {
    "date:inception_lower": "2020-11-01",
    "date:inception_upper": "2020-11-01",
    "iso:country": "GB",
    "wof:name": "DL1 5BF",
    "wof:placetype": "postalcode"
  },
  "geometry": {"coordinates":[-1.554413,54.522892],"type":"Point"}
}
