{
  "type": "Feature",
  "properties": {
    "iso:country":"GB",
    "wof:name":"CT18 7DU",
    "wof:placetype":"postalcode"
},
  "geometry": {"coordinates":[1.15811088928276,51.12681938622909],"type":"Point"}
}