{
  "type": "Feature",
  "properties": {
    "date:inception_lower": "1980-01-01",
    "date:inception_upper": "1980-01-01",
    "iso:country": "GB",
    "wof:name": "SW19 4TS",
    "wof:placetype": "postalcode"
  },
  "geometry": {"coordinates":[-0.229713,51.42286],"type":"Point"}
}
