{
  "type": "Feature",
  "properties": {
    "date:inception_lower":"1984-10-01",
    "date:inception_upper":"1984-10-31",
    "iso:country":"GB",
    "wof:name":"WV12 5YT",
    "wof:placetype":"postalcode"
},
  "geometry": {"coordinates":[-2.046682,52.610342],"type":"Point"}
}