{
  "type": "Feature",
  "properties": {
    "iso:country": "GB",
    "wof:name": "WV12 5YT",
    "wof:placetype": "postalcode"
  },
  "geometry": {"coordinates":[-2.046682,52.610342],"type":"Point"}
}
