{
  "type": "Feature",
  "properties": {
    "iso:country":"GB",
    "wof:name":"NG3 1JF",
    "wof:placetype":"postalcode"
},
  "geometry": {"coordinates":[-1.13576101449213,52.9550146757872],"type":"Point"}
}