{
  "type": "Feature",
  "properties": {
    "date:inception_lower": "2020-01-01",
    "date:inception_upper": "2020-01-01",
    "iso:country": "GB",
    "wof:name": "CM3 5BQ",
    "wof:placetype": "postalcode"
  },
  "geometry": {"coordinates":[0.596085,51.65106],"type":"Point"}
}
