{
  "type": "Feature",
  "properties": {
    "iso:country": "GB",
    "wof:name": "CM3 5BQ",
    "wof:placetype": "postalcode"
  },
  "geometry": {"coordinates":[0.596085,51.65106],"type":"Point"}
}
