{
  "type": "Feature",
  "properties": {
    "iso:country": "GB",
    "wof:name": "CM77 8NY",
    "wof:placetype": "postalcode"
  },
  "geometry": {"coordinates":[0.595983,51.85309],"type":"Point"}
}
