{
  "type": "Feature",
  "properties": {
    "iso:country":"GB",
    "wof:name":"CM77 8NY",
    "wof:placetype":"postalcode"
},
  "geometry": {"coordinates":[0.59598258622676,51.85308962505788],"type":"Point"}
}