{
  "type": "Feature",
  "properties": {
    "iso:country": "GB",
    "wof:name": "CM77 8NY",
    "wof:placetype": "postalcode"
  },
  "geometry": {"coordinates":[0.596136,51.852997],"type":"Point"}
}
