{
  "type": "Feature",
  "properties": {
    "iso:country":"GB",
    "wof:name":"OX4 6BZ",
    "wof:placetype":"postalcode"
},
  "geometry": {"coordinates":[-1.19437424081331,51.72649312952129],"type":"Point"}
}