{
  "type": "Feature",
  "properties": {
    "date:inception_lower": "1986-07-01",
    "date:inception_upper": "1986-07-01",
    "iso:country": "GB",
    "wof:name": "OL16 2YX",
    "wof:placetype": "postalcode"
  },
  "geometry": {"coordinates":[-2.136363,53.617705],"type":"Point"}
}
