{
  "type": "Feature",
  "properties": {
    "iso:country":"GB",
    "wof:name":"OL16 2YX",
    "wof:placetype":"postalcode"
},
  "geometry": {"coordinates":[-2.13636297714999,53.61770541271],"type":"Point"}
}