{
  "type": "Feature",
  "properties": {
    "iso:country": "GB",
    "wof:name": "TS15 9UY",
    "wof:placetype": "postalcode"
  },
  "geometry": {"coordinates":[-1.342277,54.498035],"type":"Point"}
}
