{
  "type": "Feature",
  "properties": {
    "date:inception_lower": "1986-07-01",
    "date:inception_upper": "1986-07-01",
    "iso:country": "GB",
    "wof:name": "TS15 9UY",
    "wof:placetype": "postalcode"
  },
  "geometry": {"coordinates":[-1.342277,54.498035],"type":"Point"}
}
