{
  "type": "Feature",
  "properties": {
    "iso:country":"GB",
    "wof:name":"DH7 7EP",
    "wof:placetype":"postalcode"
},
  "geometry": {"coordinates":[-1.65032436334071,54.76927105496569],"type":"Point"}
}