{
  "type": "Feature",
  "properties": {
    "iso:country":"GB",
    "wof:name":"DN18 5AH",
    "wof:placetype":"postalcode"
},
  "geometry": {"coordinates":[-0.45333667045536,53.68779579655182],"type":"Point"}
}