{
  "type": "Feature",
  "properties": {
    "iso:country": "GB",
    "wof:name": "SO31 9TS",
    "wof:placetype": "postalcode"
  },
  "geometry": {"coordinates":[-1.289666,50.855582],"type":"Point"}
}
