{
  "type": "Feature",
  "properties": {
    "iso:country":"GB",
    "wof:name":"SO31 9TS",
    "wof:placetype":"postalcode"
},
  "geometry": {"coordinates":[-1.28966598624541,50.85558213383559],"type":"Point"}
}