{
  "type": "Feature",
  "properties": {
    "iso:country":"GB",
    "wof:name":"GU4 7EH",
    "wof:placetype":"postalcode"
},
  "geometry": {"coordinates":[-0.52945026968112,51.25291233840141],"type":"Point"}
}