{
  "type": "Feature",
  "properties": {
    "iso:country":"GB",
    "wof:name":"RM14 3DD",
    "wof:placetype":"postalcode"
},
  "geometry": {"coordinates":[0.25748462702227,51.557216981817],"type":"Point"}
}