{
  "type": "Feature",
  "properties": {
    "iso:country": "GB",
    "wof:name": "WV3 7BN",
    "wof:placetype": "postalcode"
  },
  "geometry": {"coordinates":[-2.152519,52.575291],"type":"Point"}
}
