{
  "type": "Feature",
  "properties": {
    "iso:country": "GB",
    "wof:name": "SK5 8LY",
    "wof:placetype": "postalcode"
  },
  "geometry": {"coordinates":[-2.139266,53.429665],"type":"Point"}
}
