{
  "type": "Feature",
  "properties": {
    "iso:country": "GB",
    "wof:name": "EX34 0AL",
    "wof:placetype": "postalcode"
  },
  "geometry": {"coordinates":[-4.035345,51.205423],"type":"Point"}
}
