{
  "type": "Feature",
  "properties": {
    "iso:country":"GB",
    "wof:name":"M41 0XP",
    "wof:placetype":"postalcode"
},
  "geometry": {"coordinates":[-2.34984997147393,53.44989827448538],"type":"Point"}
}