{
  "type": "Feature",
  "properties": {
    "date:inception_lower": "1994-05-01",
    "date:inception_upper": "1994-05-01",
    "iso:country": "GB",
    "wof:name": "M41 0XP",
    "wof:placetype": "postalcode"
  },
  "geometry": {"coordinates":[-2.34985,53.449898],"type":"Point"}
}
