{
  "type": "Feature",
  "properties": {
    "iso:country":"GB",
    "wof:name":"NG7 3FF",
    "wof:placetype":"postalcode"
},
  "geometry": {"coordinates":[-1.18042046385113,52.95877388643696],"type":"Point"}
}