{
  "type": "Feature",
  "properties": {
    "date:inception_lower": "1980-01-01",
    "date:inception_upper": "1980-01-01",
    "iso:country": "GB",
    "wof:name": "NG7 3FF",
    "wof:placetype": "postalcode"
  },
  "geometry": {"coordinates":[-1.18042,52.958774],"type":"Point"}
}
