{
  "type": "Feature",
  "properties": {
    "date:inception_lower": "1980-01-01",
    "date:inception_upper": "1980-01-01",
    "iso:country": "GB",
    "wof:name": "CM22 7TS",
    "wof:placetype": "postalcode"
  },
  "geometry": {"coordinates":[0.20463,51.857661],"type":"Point"}
}
