{
  "type": "Feature",
  "properties": {
    "iso:country":"GB",
    "wof:name":"CM22 7TS",
    "wof:placetype":"postalcode"
},
  "geometry": {"coordinates":[0.20463007555012,51.85766054320163],"type":"Point"}
}