{
  "type": "Feature",
  "properties": {
    "iso:country": "GB",
    "wof:name": "TR7 1AA",
    "wof:placetype": "postalcode"
  },
  "geometry": {"coordinates":[-5.087275,50.41367],"type":"Point"}
}
