{
  "type": "Feature",
  "properties": {
    "date:inception_lower":"2011-06-01",
    "date:inception_upper":"2011-06-30",
    "iso:country":"GB",
    "wof:name":"TR7 1AA",
    "wof:placetype":"postalcode"
},
  "geometry": {"coordinates":[-5.087275,50.41367],"type":"Point"}
}