{
  "type": "Feature",
  "properties": {
    "iso:country":"GB",
    "wof:name":"NE21 4AG",
    "wof:placetype":"postalcode"
},
  "geometry": {"coordinates":[-1.71468139098526,54.9646956117595],"type":"Point"}
}