{
  "type": "Feature",
  "properties": {
    "iso:country": "GB",
    "wof:name": "PO21 5ES",
    "wof:placetype": "postalcode"
  },
  "geometry": {"coordinates":[-0.691415,50.794966],"type":"Point"}
}
