{
  "type": "Feature",
  "properties": {
    "iso:country":"GB",
    "wof:name":"PO21 5ES",
    "wof:placetype":"postalcode"
},
  "geometry": {"coordinates":[-0.69150510991006,50.79500384193781],"type":"Point"}
}