{
  "type": "Feature",
  "properties": {
    "iso:country":"GB",
    "wof:name":"EC4V 3QH",
    "wof:placetype":"postalcode"
},
  "geometry": {"coordinates":[-0.09732819008902,51.51063168405519],"type":"Point"}
}