{
  "type": "Feature",
  "properties": {
    "iso:country":"GB",
    "wof:name":"YO24 1EW",
    "wof:placetype":"postalcode"
},
  "geometry": {"coordinates":[-1.10956501745761,53.94224985050331],"type":"Point"}
}