{
  "type": "Feature",
  "properties": {
    "date:inception_lower": "2017-05-01",
    "date:inception_upper": "2017-05-01",
    "iso:country": "GB",
    "wof:name": "PL13 2RW",
    "wof:placetype": "postalcode"
  },
  "geometry": {"coordinates":[-4.571005,50.392473],"type":"Point"}
}
