{
  "type": "Feature",
  "properties": {
    "date:inception_lower":"1987-04-01",
    "date:inception_upper":"1987-04-30",
    "iso:country":"GB",
    "wof:name":"TN37 7HY",
    "wof:placetype":"postalcode"
},
  "geometry": {"coordinates":[0.567126,50.882031],"type":"Point"}
}