{
  "type": "Feature",
  "properties": {
    "iso:country": "GB",
    "wof:name": "TN37 7HY",
    "wof:placetype": "postalcode"
  },
  "geometry": {"coordinates":[0.567126,50.882031],"type":"Point"}
}
