{
  "type": "Feature",
  "properties": {
    "iso:country":"GB",
    "wof:name":"DY1 2BW",
    "wof:placetype":"postalcode"
},
  "geometry": {"coordinates":[-2.09660651260912,52.50740484190823],"type":"Point"}
}