{
  "type": "Feature",
  "properties": {
    "date:inception_lower":"1985-04-01",
    "date:inception_upper":"1985-04-30",
    "iso:country":"GB",
    "wof:name":"WN2 4HT",
    "wof:placetype":"postalcode"
},
  "geometry": {"coordinates":[-2.541557,53.527536],"type":"Point"}
}