{
  "type": "Feature",
  "properties": {
    "iso:country":"GB",
    "wof:name":"LL13 8DS",
    "wof:placetype":"postalcode"
},
  "geometry": {"coordinates":[-2.98802590681665,53.04344691766333],"type":"Point"}
}