{
  "type": "Feature",
  "properties": {
    "iso:country":"GB",
    "wof:name":"IP10 0LA",
    "wof:placetype":"postalcode"
},
  "geometry": {"coordinates":[1.18079251247557,52.02142657930031],"type":"Point"}
}