{
  "type": "Feature",
  "properties": {
    "iso:country": "GB",
    "wof:name": "IP10 0LA",
    "wof:placetype": "postalcode"
  },
  "geometry": {"coordinates":[1.180793,52.021427],"type":"Point"}
}
