{
  "type": "Feature",
  "properties": {
    "iso:country": "GB",
    "wof:name": "HX1 3SA",
    "wof:placetype": "postalcode"
  },
  "geometry": {"coordinates":[-1.885671,53.715475],"type":"Point"}
}
