{
  "type": "Feature",
  "properties": {
    "iso:country":"GB",
    "wof:name":"CF11 6AS",
    "wof:placetype":"postalcode"
},
  "geometry": {"coordinates":[-3.18590244057755,51.47735985263848],"type":"Point"}
}