{
  "type": "Feature",
  "properties": {
    "iso:country": "GB",
    "wof:name": "IP17 1UR",
    "wof:placetype": "postalcode"
  },
  "geometry": {"coordinates":[1.562472,52.192934],"type":"Point"}
}
