{
  "type": "Feature",
  "properties": {
    "iso:country":"GB",
    "wof:name":"S66 3YF",
    "wof:placetype":"postalcode"
},
  "geometry": {"coordinates":[-1.27015031519181,53.43434098813567],"type":"Point"}
}