{
  "type": "Feature",
  "properties": {
    "date:inception_lower": "2022-06-01",
    "date:inception_upper": "2022-06-01",
    "iso:country": "GB",
    "wof:name": "EX3 0FS",
    "wof:placetype": "postalcode"
  },
  "geometry": {"coordinates":[-3.466724,50.694205],"type":"Point"}
}
