{
  "type": "Feature",
  "properties": {
    "iso:country":"GB",
    "wof:name":"PR6 8LP",
    "wof:placetype":"postalcode"
},
  "geometry": {"coordinates":[-2.61348963475098,53.68541096090291],"type":"Point"}
}