{
  "type": "Feature",
  "properties": {
    "date:inception_lower": "1980-01-01",
    "date:inception_upper": "1980-01-01",
    "iso:country": "GB",
    "wof:name": "PR6 8LP",
    "wof:placetype": "postalcode"
  },
  "geometry": {"coordinates":[-2.61349,53.685411],"type":"Point"}
}
