{
  "type": "Feature",
  "properties": {
    "date:inception_lower": "2020-08-01",
    "date:inception_upper": "2020-08-01",
    "iso:country": "GB",
    "wof:name": "CV23 1DR",
    "wof:placetype": "postalcode"
  },
  "geometry": {"coordinates":[-1.206488,52.368358],"type":"Point"}
}
