{
  "type": "Feature",
  "properties": {
    "iso:country": "GB",
    "wof:name": "NN7 2AP",
    "wof:placetype": "postalcode"
  },
  "geometry": {"coordinates":[-0.803737,52.18118],"type":"Point"}
}
