{
  "type": "Feature",
  "properties": {
    "date:inception_lower": "1980-01-01",
    "date:inception_upper": "1980-01-01",
    "iso:country": "GB",
    "wof:name": "CH7 4JW",
    "wof:placetype": "postalcode"
  },
  "geometry": {"coordinates":[-3.101628,53.154539],"type":"Point"}
}
