{
  "type": "Feature",
  "properties": {
    "iso:country":"GB",
    "wof:name":"CH7 4JW",
    "wof:placetype":"postalcode"
},
  "geometry": {"coordinates":[-3.10162767552862,53.15453867572218],"type":"Point"}
}