{
  "type": "Feature",
  "properties": {
    "iso:country": "GB",
    "wof:name": "KW14 7SJ",
    "wof:placetype": "postalcode"
  },
  "geometry": {"coordinates":[-3.542914,58.588285],"type":"Point"}
}
