{
  "type": "Feature",
  "properties": {
    "iso:country":"GB",
    "wof:name":"KW14 7SJ",
    "wof:placetype":"postalcode"
},
  "geometry": {"coordinates":[-3.54291415782884,58.5882851210899],"type":"Point"}
}