{
  "type": "Feature",
  "properties": {
    "iso:country":"GB",
    "wof:name":"DD2 3LZ",
    "wof:placetype":"postalcode"
},
  "geometry": {"coordinates":[-3.01062506021028,56.4763041024033],"type":"Point"}
}