{
  "type": "Feature",
  "properties": {
    "iso:country":"GB",
    "wof:name":"GU19 5QT",
    "wof:placetype":"postalcode"
},
  "geometry": {"coordinates":[-0.69293220998468,51.35211221076923],"type":"Point"}
}