{
  "type": "Feature",
  "properties": {
    "date:inception_lower": "1980-01-01",
    "date:inception_upper": "1980-01-01",
    "iso:country": "GB",
    "wof:name": "RH11 0EG",
    "wof:placetype": "postalcode"
  },
  "geometry": {"coordinates":[-0.214436,51.118404],"type":"Point"}
}
