{
  "type": "Feature",
  "properties": {
    "date:inception_lower": "2012-05-01",
    "date:inception_upper": "2012-05-01",
    "iso:country": "GB",
    "wof:name": "L20 6FD",
    "wof:placetype": "postalcode"
  },
  "geometry": {"coordinates":[-2.989031,53.463367],"type":"Point"}
}
