{
  "type": "Feature",
  "properties": {
    "iso:country":"GB",
    "wof:name":"L20 6FD",
    "wof:placetype":"postalcode"
},
  "geometry": {"coordinates":[-2.98903077436508,53.46336712802013],"type":"Point"}
}