{
  "type": "Feature",
  "properties": {
    "iso:country": "GB",
    "wof:name": "BD21 4TH",
    "wof:placetype": "postalcode"
  },
  "geometry": {"coordinates":[-1.886182,53.864151],"type":"Point"}
}
