{
  "type": "Feature",
  "properties": {
    "iso:country":"GB",
    "wof:name":"BD21 4TH",
    "wof:placetype":"postalcode"
},
  "geometry": {"coordinates":[-1.88617900863042,53.86413681406847],"type":"Point"}
}