{
  "type": "Feature",
  "properties": {
    "iso:country":"GB",
    "wof:name":"CT4 8HS",
    "wof:placetype":"postalcode"
},
  "geometry": {"coordinates":[0.90621686150631,51.24476031283481],"type":"Point"}
}