{
  "type": "Feature",
  "properties": {
    "iso:country": "GB",
    "wof:name": "CT4 8HS",
    "wof:placetype": "postalcode"
  },
  "geometry": {"coordinates":[0.906217,51.24476],"type":"Point"}
}
