{
  "type": "Feature",
  "properties": {
    "date:inception_lower":"1980-01-01",
    "date:inception_upper":"1980-01-31",
    "iso:country":"GB",
    "wof:name":"CT4 8HS",
    "wof:placetype":"postalcode"
},
  "geometry": {"coordinates":[0.906217,51.24476],"type":"Point"}
}