{
  "type": "Feature",
  "properties": {
    "iso:country":"GB",
    "wof:name":"FK3 9AY",
    "wof:placetype":"postalcode"
},
  "geometry": {"coordinates":[-3.70117686632991,56.01551565694576],"type":"Point"}
}