{
  "type": "Feature",
  "properties": {
    "date:inception_lower": "1980-01-01",
    "date:inception_upper": "1980-01-01",
    "iso:country": "GB",
    "wof:name": "BN13 3LH",
    "wof:placetype": "postalcode"
  },
  "geometry": {"coordinates":[-0.416275,50.83869],"type":"Point"}
}
