{
  "type": "Feature",
  "properties": {
    "iso:country":"GB",
    "wof:name":"BN13 3LH",
    "wof:placetype":"postalcode"
},
  "geometry": {"coordinates":[-0.41627509428732,50.8386895198034],"type":"Point"}
}