{
  "type": "Feature",
  "properties": {
    "iso:country": "GB",
    "wof:name": "BN13 3LH",
    "wof:placetype": "postalcode"
  },
  "geometry": {"coordinates":[-0.416275,50.83869],"type":"Point"}
}
