{
  "type": "Feature",
  "properties": {
    "iso:country":"GB",
    "wof:name":"PE19 7RE",
    "wof:placetype":"postalcode"
},
  "geometry": {"coordinates":[-0.27784939493953,52.22799481891108],"type":"Point"}
}