{
  "type": "Feature",
  "properties": {
    "date:inception_lower":"2000-06-01",
    "date:inception_upper":"2000-06-30",
    "iso:country":"GB",
    "wof:name":"CA8 7AZ",
    "wof:placetype":"postalcode"
},
  "geometry": {"coordinates":[-2.618294,55.02624],"type":"Point"}
}