{
  "type": "Feature",
  "properties": {
    "iso:country": "GB",
    "wof:name": "CA8 7AZ",
    "wof:placetype": "postalcode"
  },
  "geometry": {"coordinates":[-2.598206,55.029162],"type":"Point"}
}
