{
  "type": "Feature",
  "properties": {
    "iso:country":"GB",
    "wof:name":"CA8 7AZ",
    "wof:placetype":"postalcode"
},
  "geometry": {"coordinates":[-2.61828795875413,55.02623527851571],"type":"Point"}
}