{
  "type": "Feature",
  "properties": {
    "iso:country": "GB",
    "wof:name": "RG22 5BH",
    "wof:placetype": "postalcode"
  },
  "geometry": {"coordinates":[-1.134749,51.257053],"type":"Point"}
}
