{
  "type": "Feature",
  "properties": {
    "iso:country":"GB",
    "wof:name":"DH8 6AY",
    "wof:placetype":"postalcode"
},
  "geometry": {"coordinates":[-1.82460825716656,54.85610642840514],"type":"Point"}
}