{
  "type": "Feature",
  "properties": {
    "iso:country": "GB",
    "wof:name": "DH8 6AY",
    "wof:placetype": "postalcode"
  },
  "geometry": {"coordinates":[-1.824608,54.856106],"type":"Point"}
}
