{
  "type": "Feature",
  "properties": {
    "iso:country":"GB",
    "wof:name":"EH42 1BT",
    "wof:placetype":"postalcode"
},
  "geometry": {"coordinates":[-2.51697527864249,56.00232020712932],"type":"Point"}
}