{
  "type": "Feature",
  "properties": {
    "iso:country":"GB",
    "wof:name":"DD7 7NA",
    "wof:placetype":"postalcode"
},
  "geometry": {"coordinates":[-2.72833487287874,56.499681685802],"type":"Point"}
}