{
  "type": "Feature",
  "properties": {
    "iso:country":"GB",
    "wof:name":"SL2 5AH",
    "wof:placetype":"postalcode"
},
  "geometry": {"coordinates":[-0.59356658854199,51.51389962392701],"type":"Point"}
}