{
  "type": "Feature",
  "properties": {
    "iso:country": "GB",
    "wof:name": "SL2 5AH",
    "wof:placetype": "postalcode"
  },
  "geometry": {"coordinates":[-0.593567,51.5139],"type":"Point"}
}
