{
  "type": "Feature",
  "properties": {
    "date:inception_lower":"1987-10-01",
    "date:inception_upper":"1987-10-31",
    "iso:country":"GB",
    "wof:name":"CT14 6TH",
    "wof:placetype":"postalcode"
},
  "geometry": {"coordinates":[1.395012,51.230296],"type":"Point"}
}