{
  "type": "Feature",
  "properties": {
    "iso:country":"GB",
    "wof:name":"CR9 4LT",
    "wof:placetype":"postalcode"
},
  "geometry": {"coordinates":[-0.11735334190705,51.35716266658482],"type":"Point"}
}