{
  "type": "Feature",
  "properties": {
    "date:inception_lower":"1980-01-01",
    "date:inception_upper":"1980-01-31",
    "iso:country":"GB",
    "wof:name":"CR9 4LT",
    "wof:placetype":"postalcode"
},
  "geometry": {"coordinates":[-0.117353,51.357163],"type":"Point"}
}