{
  "type": "Feature",
  "properties": {
    "date:inception_lower": "2019-11-01",
    "date:inception_upper": "2019-11-01",
    "iso:country": "GB",
    "wof:name": "MK42 9EW",
    "wof:placetype": "postalcode"
  },
  "geometry": {"coordinates":[-0.460433,52.114354],"type":"Point"}
}
