{
  "type": "Feature",
  "properties": {
    "iso:country": "GB",
    "wof:name": "MK42 9EW",
    "wof:placetype": "postalcode"
  },
  "geometry": {"coordinates":[-0.460433,52.114336],"type":"Point"}
}
