{
  "type": "Feature",
  "properties": {
    "date:inception_lower":"1978-05-01",
    "date:inception_upper":"1978-05-31",
    "iso:country":"GB",
    "wof:name":"FK15 0HH",
    "wof:placetype":"postalcode"
},
  "geometry": {"coordinates":[-3.951197,56.198363],"type":"Point"}
}