{
  "type": "Feature",
  "properties": {
    "iso:country":"GB",
    "wof:name":"FK15 0HH",
    "wof:placetype":"postalcode"
},
  "geometry": {"coordinates":[-3.95119728228961,56.19836306352136],"type":"Point"}
}