{
  "type": "Feature",
  "properties": {
    "iso:country": "GB",
    "wof:name": "SY3 9LL",
    "wof:placetype": "postalcode"
  },
  "geometry": {"coordinates":[-2.757168,52.687454],"type":"Point"}
}
