{
  "type": "Feature",
  "properties": {
    "iso:country":"GB",
    "wof:name":"SY3 9LL",
    "wof:placetype":"postalcode"
},
  "geometry": {"coordinates":[-2.75716785007061,52.68745435121578],"type":"Point"}
}