{
  "type": "Feature",
  "properties": {
    "iso:country":"GB",
    "wof:name":"HS2 0XR",
    "wof:placetype":"postalcode"
},
  "geometry": {"coordinates":[-6.39666610093932,58.21351611945855],"type":"Point"}
}