{
  "type": "Feature",
  "properties": {
    "iso:country":"GB",
    "wof:name":"LS8 2JU",
    "wof:placetype":"postalcode"
},
  "geometry": {"coordinates":[-1.50151060503352,53.82893018129772],"type":"Point"}
}