{
  "type": "Feature",
  "properties": {
    "iso:country":"GB",
    "wof:name":"WA4 6RJ",
    "wof:placetype":"postalcode"
},
  "geometry": {"coordinates":[-2.58814356545992,53.37310688879858],"type":"Point"}
}