{
  "type": "Feature",
  "properties": {
    "iso:country":"GB",
    "wof:name":"CB2 9HB",
    "wof:placetype":"postalcode"
},
  "geometry": {"coordinates":[0.11754895832927,52.17942610043943],"type":"Point"}
}