{
  "type": "Feature",
  "properties": {
    "iso:country": "GB",
    "wof:name": "CB2 9HB",
    "wof:placetype": "postalcode"
  },
  "geometry": {"coordinates":[0.117549,52.179426],"type":"Point"}
}
