{
  "type": "Feature",
  "properties": {
    "iso:country":"GB",
    "wof:name":"B77 1NR",
    "wof:placetype":"postalcode"
},
  "geometry": {"coordinates":[-1.68056944397301,52.60483297231317],"type":"Point"}
}