{
  "type": "Feature",
  "properties": {
    "date:inception_lower": "1980-01-01",
    "date:inception_upper": "1980-01-01",
    "iso:country": "GB",
    "wof:name": "RM7 7LJ",
    "wof:placetype": "postalcode"
  },
  "geometry": {"coordinates":[0.171672,51.57991],"type":"Point"}
}
