{
  "type": "Feature",
  "properties": {
    "iso:country":"GB",
    "wof:name":"RM7 7LJ",
    "wof:placetype":"postalcode"
},
  "geometry": {"coordinates":[0.17168714154279,51.57987984905219],"type":"Point"}
}