{
  "type": "Feature",
  "properties": {
    "iso:country": "GB",
    "wof:name": "HD9 6QJ",
    "wof:placetype": "postalcode"
  },
  "geometry": {"coordinates":[-1.783521,53.60789],"type":"Point"}
}
