{
  "type": "Feature",
  "properties": {
    "date:inception_lower": "2001-06-01",
    "date:inception_upper": "2001-06-01",
    "iso:country": "GB",
    "wof:name": "HD9 6QJ",
    "wof:placetype": "postalcode"
  },
  "geometry": {"coordinates":[-1.783521,53.60789],"type":"Point"}
}
