{
  "type": "Feature",
  "properties": {
    "iso:country":"GB",
    "wof:name":"CW9 8LJ",
    "wof:placetype":"postalcode"
},
  "geometry": {"coordinates":[-2.49888078730145,53.22925218015818],"type":"Point"}
}