{
  "type": "Feature",
  "properties": {
    "iso:country": "GB",
    "wof:name": "TQ3 3AT",
    "wof:placetype": "postalcode"
  },
  "geometry": {"coordinates":[-3.571329,50.436105],"type":"Point"}
}
