{
  "type": "Feature",
  "properties": {
    "date:inception_lower": "2002-06-01",
    "date:inception_upper": "2002-06-01",
    "iso:country": "GB",
    "wof:name": "TQ3 3AT",
    "wof:placetype": "postalcode"
  },
  "geometry": {"coordinates":[-3.571329,50.436105],"type":"Point"}
}
