{
  "type": "Feature",
  "properties": {
    "iso:country":"GB",
    "wof:name":"TQ3 3AT",
    "wof:placetype":"postalcode"
},
  "geometry": {"coordinates":[-3.57132865326752,50.43610490786128],"type":"Point"}
}