{
  "type": "Feature",
  "properties": {
    "iso:country": "GB",
    "wof:name": "AB22 8JP",
    "wof:placetype": "postalcode"
  },
  "geometry": {"coordinates":[-2.106694,57.179729],"type":"Point"}
}
