{
  "type": "Feature",
  "properties": {
    "iso:country": "GB",
    "wof:name": "PO19 3NU",
    "wof:placetype": "postalcode"
  },
  "geometry": {"coordinates":[-0.79079,50.844871],"type":"Point"}
}
