{
  "type": "Feature",
  "properties": {
    "date:inception_lower": "1980-01-01",
    "date:inception_upper": "1980-01-01",
    "iso:country": "GB",
    "wof:name": "PO19 3NU",
    "wof:placetype": "postalcode"
  },
  "geometry": {"coordinates":[-0.79079,50.844871],"type":"Point"}
}
