{
  "type": "Feature",
  "properties": {
    "date:inception_lower": "1980-01-01",
    "date:inception_upper": "1980-01-01",
    "iso:country": "GB",
    "wof:name": "CT1 3TA",
    "wof:placetype": "postalcode"
  },
  "geometry": {"coordinates":[1.072499,51.273206],"type":"Point"}
}
