{
  "type": "Feature",
  "properties": {
    "iso:country":"GB",
    "wof:name":"CT1 3TA",
    "wof:placetype":"postalcode"
},
  "geometry": {"coordinates":[1.07249910589758,51.27320593650294],"type":"Point"}
}