{
  "type": "Feature",
  "properties": {
    "iso:country":"GB",
    "wof:name":"TS1 5EE",
    "wof:placetype":"postalcode"
},
  "geometry": {"coordinates":[-1.24224663263264,54.57520646329302],"type":"Point"}
}