{
  "type": "Feature",
  "properties": {
    "date:inception_lower": "1997-06-01",
    "date:inception_upper": "1997-06-01",
    "iso:country": "GB",
    "wof:name": "S20 4SF",
    "wof:placetype": "postalcode"
  },
  "geometry": {"coordinates":[-1.35534,53.326193],"type":"Point"}
}
