{
  "type": "Feature",
  "properties": {
    "iso:country":"GB",
    "wof:name":"NN4 0JF",
    "wof:placetype":"postalcode"
},
  "geometry": {"coordinates":[-0.911202891566,52.21493808124096],"type":"Point"}
}