{
  "type": "Feature",
  "properties": {
    "iso:country":"GB",
    "wof:name":"LN2 3QG",
    "wof:placetype":"postalcode"
},
  "geometry": {"coordinates":[-0.47895603856789,53.30542097400173],"type":"Point"}
}