{
  "type": "Feature",
  "properties": {
    "date:inception_lower": "1980-01-01",
    "date:inception_upper": "1980-01-01",
    "iso:country": "GB",
    "wof:name": "DL14 0HL",
    "wof:placetype": "postalcode"
  },
  "geometry": {"coordinates":[-1.749348,54.651216],"type":"Point"}
}
