{
  "type": "Feature",
  "properties": {
    "iso:country":"GB",
    "wof:name":"NE38 8AE",
    "wof:placetype":"postalcode"
},
  "geometry": {"coordinates":[-1.5212537207358,54.88241126937851],"type":"Point"}
}