{
  "type": "Feature",
  "properties": {
    "iso:country":"GB",
    "wof:name":"BD23 6RR",
    "wof:placetype":"postalcode"
},
  "geometry": {"coordinates":[-1.98567703241794,53.97919719802321],"type":"Point"}
}