{
  "type": "Feature",
  "properties": {
    "iso:country":"GB",
    "wof:name":"GL56 9LR",
    "wof:placetype":"postalcode"
},
  "geometry": {"coordinates":[-1.74017481378613,52.01884199300375],"type":"Point"}
}