{
  "type": "Feature",
  "properties": {
    "date:inception_lower":"1980-01-01",
    "date:inception_upper":"1980-01-31",
    "iso:country":"GB",
    "wof:name":"NE65 0PL",
    "wof:placetype":"postalcode"
},
  "geometry": {"coordinates":[-1.580258,55.333524],"type":"Point"}
}