{
  "type": "Feature",
  "properties": {
    "iso:country": "GB",
    "wof:name": "SK14 5EF",
    "wof:placetype": "postalcode"
  },
  "geometry": {"coordinates":[-2.071835,53.43483],"type":"Point"}
}
