{
  "type": "Feature",
  "properties": {
    "iso:country":"GB",
    "wof:name":"ML5 4QE",
    "wof:placetype":"postalcode"
},
  "geometry": {"coordinates":[-4.00645489222424,55.85194856668946],"type":"Point"}
}