{
  "type": "Feature",
  "properties": {
    "iso:country": "GB",
    "wof:name": "ML5 4QE",
    "wof:placetype": "postalcode"
  },
  "geometry": {"coordinates":[-4.006579,55.852086],"type":"Point"}
}
