{
  "type": "Feature",
  "properties": {
    "date:inception_lower":"2005-03-01",
    "date:inception_upper":"2005-03-31",
    "iso:country":"GB",
    "wof:name":"DD1 9TS",
    "wof:placetype":"postalcode"
},
  "geometry": {"coordinates":[-2.96941,56.45994],"type":"Point"}
}