{
  "type": "Feature",
  "properties": {
    "iso:country":"GB",
    "wof:name":"CV5 9GU",
    "wof:placetype":"postalcode"
},
  "geometry": {"coordinates":[-1.55924184118255,52.42310715079375],"type":"Point"}
}