{
  "type": "Feature",
  "properties": {
    "iso:country":"GB",
    "wof:name":"LS16 7DY",
    "wof:placetype":"postalcode"
},
  "geometry": {"coordinates":[-1.62062608180418,53.85735417487199],"type":"Point"}
}