{
  "type": "Feature",
  "properties": {
    "date:inception_lower": "1996-12-01",
    "date:inception_upper": "1996-12-01",
    "iso:country": "GB",
    "wof:name": "LN8 6AP",
    "wof:placetype": "postalcode"
  },
  "geometry": {"coordinates":[-0.215827,53.365996],"type":"Point"}
}
