{
  "type": "Feature",
  "properties": {
    "iso:country":"GB",
    "wof:name":"LN8 6AP",
    "wof:placetype":"postalcode"
},
  "geometry": {"coordinates":[-0.21784844393153,53.36434828745409],"type":"Point"}
}