{
  "type": "Feature",
  "properties": {
    "iso:country": "GB",
    "wof:name": "LN8 6AP",
    "wof:placetype": "postalcode"
  },
  "geometry": {"coordinates":[-0.215827,53.365996],"type":"Point"}
}
