{
  "type": "Feature",
  "properties": {
    "iso:country": "GB",
    "wof:name": "DE45 1BT",
    "wof:placetype": "postalcode"
  },
  "geometry": {"coordinates":[-1.675271,53.213424],"type":"Point"}
}
