{
  "type": "Feature",
  "properties": {
    "date:inception_lower":"1990-02-01",
    "date:inception_upper":"1990-02-28",
    "iso:country":"GB",
    "wof:name":"GL5 2BU",
    "wof:placetype":"postalcode"
},
  "geometry": {"coordinates":[-2.199611,51.724542],"type":"Point"}
}