{
  "type": "Feature",
  "properties": {
    "iso:country": "GB",
    "wof:name": "SO23 7NX",
    "wof:placetype": "postalcode"
  },
  "geometry": {"coordinates":[-1.300604,51.104171],"type":"Point"}
}
