{
  "type": "Feature",
  "properties": {
    "iso:country":"GB",
    "wof:name":"SO23 7NX",
    "wof:placetype":"postalcode"
},
  "geometry": {"coordinates":[-1.30060414810036,51.10417129632011],"type":"Point"}
}