{
  "type": "Feature",
  "properties": {
    "iso:country":"GB",
    "wof:name":"SE3 0LJ",
    "wof:placetype":"postalcode"
},
  "geometry": {"coordinates":[0.02133364153161,51.47021161653839],"type":"Point"}
}