{
  "type": "Feature",
  "properties": {
    "date:inception_lower": "1980-01-01",
    "date:inception_upper": "1980-01-01",
    "iso:country": "GB",
    "wof:name": "EH2 4JF",
    "wof:placetype": "postalcode"
  },
  "geometry": {"coordinates":[-3.205838,55.952723],"type":"Point"}
}
