{
  "type": "Feature",
  "properties": {
    "iso:country":"GB",
    "wof:name":"BD12 7HX",
    "wof:placetype":"postalcode"
},
  "geometry": {"coordinates":[-1.73197279418999,53.75049961261046],"type":"Point"}
}