{
  "type": "Feature",
  "properties": {
    "date:inception_lower": "2018-02-01",
    "date:inception_upper": "2018-02-01",
    "iso:country": "GB",
    "wof:name": "IV30 8AE",
    "wof:placetype": "postalcode"
  },
  "geometry": {"coordinates":[-3.28491,57.636803],"type":"Point"}
}
