{
  "type": "Feature",
  "properties": {
    "iso:country":"GB",
    "wof:name":"PA4 0UU",
    "wof:placetype":"postalcode"
},
  "geometry": {"coordinates":[-4.37941147580036,55.8704196037861],"type":"Point"}
}