{
  "type": "Feature",
  "properties": {
    "iso:country":"GB",
    "wof:name":"WR3 7QS",
    "wof:placetype":"postalcode"
},
  "geometry": {"coordinates":[-2.23453127413485,52.22331154551124],"type":"Point"}
}