{
  "type": "Feature",
  "properties": {
    "date:inception_lower":"1995-01-01",
    "date:inception_upper":"1995-01-31",
    "iso:country":"GB",
    "wof:name":"BN27 3UX",
    "wof:placetype":"postalcode"
},
  "geometry": {"coordinates":[0.244756,50.868874],"type":"Point"}
}