{
  "type": "Feature",
  "properties": {
    "iso:country":"GB",
    "wof:name":"ST13 8JQ",
    "wof:placetype":"postalcode"
},
  "geometry": {"coordinates":[-2.04184986747267,53.09801792652073],"type":"Point"}
}