{
  "type": "Feature",
  "properties": {
    "iso:country": "GB",
    "wof:name": "ST13 8JQ",
    "wof:placetype": "postalcode"
  },
  "geometry": {"coordinates":[-2.04185,53.098018],"type":"Point"}
}
