{
  "type": "Feature",
  "properties": {
    "date:inception_lower": "1993-01-01",
    "date:inception_upper": "1993-01-01",
    "iso:country": "GB",
    "wof:name": "CF64 2QQ",
    "wof:placetype": "postalcode"
  },
  "geometry": {"coordinates":[-3.19659,51.442803],"type":"Point"}
}
