{
  "type": "Feature",
  "properties": {
    "iso:country":"GB",
    "wof:name":"CF64 2QQ",
    "wof:placetype":"postalcode"
},
  "geometry": {"coordinates":[-3.19658990612147,51.44280304816167],"type":"Point"}
}