{
  "type": "Feature",
  "properties": {
    "iso:country":"GB",
    "wof:name":"AB39 2AR",
    "wof:placetype":"postalcode"
},
  "geometry": {"coordinates":[-2.20963239774279,56.96545683047083],"type":"Point"}
}