{
  "type": "Feature",
  "properties": {
    "date:inception_lower": "1980-01-01",
    "date:inception_upper": "1980-01-01",
    "iso:country": "GB",
    "wof:name": "SA62 3BJ",
    "wof:placetype": "postalcode"
  },
  "geometry": {"coordinates":[-5.225336,51.735127],"type":"Point"}
}
