{
  "type": "Feature",
  "properties": {
    "iso:country":"GB",
    "wof:name":"SA62 3BJ",
    "wof:placetype":"postalcode"
},
  "geometry": {"coordinates":[-5.22533635030887,51.73512661541964],"type":"Point"}
}