{
  "type": "Feature",
  "properties": {
    "date:inception_lower": "2021-11-01",
    "date:inception_upper": "2021-11-01",
    "iso:country": "GB",
    "wof:name": "NG2 5PN",
    "wof:placetype": "postalcode"
  },
  "geometry": {"coordinates":[-1.101299,52.938464],"type":"Point"}
}
