{
  "type": "Feature",
  "properties": {
    "iso:country":"GB",
    "wof:name":"TN4 8PF",
    "wof:placetype":"postalcode"
},
  "geometry": {"coordinates":[0.23657939673697,51.1354945426509],"type":"Point"}
}