{
  "type": "Feature",
  "properties": {
    "date:inception_lower":"1980-01-01",
    "date:inception_upper":"1980-01-31",
    "iso:country":"GB",
    "wof:name":"WF15 7QG",
    "wof:placetype":"postalcode"
},
  "geometry": {"coordinates":[-1.701442,53.697595],"type":"Point"}
}