{
  "type": "Feature",
  "properties": {
    "iso:country":"GB",
    "wof:name":"WF15 7QG",
    "wof:placetype":"postalcode"
},
  "geometry": {"coordinates":[-1.7014417623325,53.69759545472905],"type":"Point"}
}