{
  "type": "Feature",
  "properties": {
    "iso:country": "GB",
    "wof:name": "LE12 9HE",
    "wof:placetype": "postalcode"
  },
  "geometry": {"coordinates":[-1.283341,52.763358],"type":"Point"}
}
