{
  "type": "Feature",
  "properties": {
    "iso:country":"GB",
    "wof:name":"LE12 9HE",
    "wof:placetype":"postalcode"
},
  "geometry": {"coordinates":[-1.2833415229178,52.76335835742937],"type":"Point"}
}