{
  "type": "Feature",
  "properties": {
    "date:inception_lower":"1983-07-01",
    "date:inception_upper":"1983-07-31",
    "iso:country":"GB",
    "wof:name":"LE12 9HE",
    "wof:placetype":"postalcode"
},
  "geometry": {"coordinates":[-1.283341,52.763358],"type":"Point"}
}