{
  "type": "Feature",
  "properties": {
    "iso:country":"GB",
    "wof:name":"TW14 9QQ",
    "wof:placetype":"postalcode"
},
  "geometry": {"coordinates":[-0.42415896361036,51.44617468441714],"type":"Point"}
}