{
  "type": "Feature",
  "properties": {
    "iso:country":"GB",
    "wof:name":"NE24 3DL",
    "wof:placetype":"postalcode"
},
  "geometry": {"coordinates":[-1.50273533998397,55.12278244004301],"type":"Point"}
}