{
  "type": "Feature",
  "properties": {
    "iso:country": "GB",
    "wof:name": "E17 3RP",
    "wof:placetype": "postalcode"
  },
  "geometry": {"coordinates":[0.002693,51.592229],"type":"Point"}
}
