{
  "type": "Feature",
  "properties": {
    "iso:country":"GB",
    "wof:name":"E17 3RP",
    "wof:placetype":"postalcode"
},
  "geometry": {"coordinates":[0.00269342570215,51.59222907743469],"type":"Point"}
}