{
  "type": "Feature",
  "properties": {
    "iso:country":"GB",
    "wof:name":"LL12 8HG",
    "wof:placetype":"postalcode"
},
  "geometry": {"coordinates":[-2.97030189856749,53.08974452669139],"type":"Point"}
}