{
  "type": "Feature",
  "properties": {
    "iso:country":"GB",
    "wof:name":"LE10 0RJ",
    "wof:placetype":"postalcode"
},
  "geometry": {"coordinates":[-1.37144963051245,52.54958509847754],"type":"Point"}
}