{
  "type": "Feature",
  "properties": {
    "iso:country":"GB",
    "wof:name":"LL59 5SN",
    "wof:placetype":"postalcode"
},
  "geometry": {"coordinates":[-4.15700574191672,53.26882221090223],"type":"Point"}
}