{
  "type": "Feature",
  "properties": {
    "iso:country": "GB",
    "wof:name": "NG16 4EZ",
    "wof:placetype": "postalcode"
  },
  "geometry": {"coordinates":[-1.332809,53.027776],"type":"Point"}
}
