{
  "type": "Feature",
  "properties": {
    "date:inception_lower": "2003-09-01",
    "date:inception_upper": "2003-09-01",
    "iso:country": "GB",
    "wof:name": "W4 3LQ",
    "wof:placetype": "postalcode"
  },
  "geometry": {"coordinates":[-0.270664,51.482867],"type":"Point"}
}
