{
  "type": "Feature",
  "properties": {
    "iso:country":"GB",
    "wof:name":"W4 3LQ",
    "wof:placetype":"postalcode"
},
  "geometry": {"coordinates":[-0.27066441176776,51.48286725262632],"type":"Point"}
}