{
  "type": "Feature",
  "properties": {
    "iso:country": "GB",
    "wof:name": "W4 3LQ",
    "wof:placetype": "postalcode"
  },
  "geometry": {"coordinates":[-0.270664,51.482867],"type":"Point"}
}
