{
  "type": "Feature",
  "properties": {
    "iso:country": "GB",
    "wof:name": "DE21 2UW",
    "wof:placetype": "postalcode"
  },
  "geometry": {"coordinates":[-1.441829,52.941339],"type":"Point"}
}
