{
  "type": "Feature",
  "properties": {
    "date:inception_lower": "1980-01-01",
    "date:inception_upper": "1980-01-01",
    "iso:country": "GB",
    "wof:name": "BD13 3SD",
    "wof:placetype": "postalcode"
  },
  "geometry": {"coordinates":[-1.882066,53.806988],"type":"Point"}
}
