{
  "type": "Feature",
  "properties": {
    "iso:country":"GB",
    "wof:name":"EX20 2RG",
    "wof:placetype":"postalcode"
},
  "geometry": {"coordinates":[-3.9028730126788,50.73000084700823],"type":"Point"}
}