{
  "type": "Feature",
  "properties": {
    "iso:country":"GB",
    "wof:name":"TS12 3HP",
    "wof:placetype":"postalcode"
},
  "geometry": {"coordinates":[-0.95608424194466,54.53467420050303],"type":"Point"}
}