{
  "type": "Feature",
  "properties": {
    "iso:country": "GB",
    "wof:name": "TS12 3HP",
    "wof:placetype": "postalcode"
  },
  "geometry": {"coordinates":[-0.956084,54.534674],"type":"Point"}
}
