{
  "type": "Feature",
  "properties": {
    "iso:country":"GB",
    "wof:name":"RM5 2RS",
    "wof:placetype":"postalcode"
},
  "geometry": {"coordinates":[0.16617308471715,51.60900147486046],"type":"Point"}
}