{
  "type": "Feature",
  "properties": {
    "iso:country": "GB",
    "wof:name": "EN6 2LA",
    "wof:placetype": "postalcode"
  },
  "geometry": {"coordinates":[-0.200309,51.696572],"type":"Point"}
}
