{
  "type": "Feature",
  "properties": {
    "date:inception_lower":"1980-01-01",
    "date:inception_upper":"1980-01-31",
    "iso:country":"GB",
    "wof:name":"EN6 2LA",
    "wof:placetype":"postalcode"
},
  "geometry": {"coordinates":[-0.200309,51.696572],"type":"Point"}
}