{
  "type": "Feature",
  "properties": {
    "iso:country":"GB",
    "wof:name":"EN6 2LA",
    "wof:placetype":"postalcode"
},
  "geometry": {"coordinates":[-0.20030882848962,51.69657248731905],"type":"Point"}
}