{
  "type": "Feature",
  "properties": {
    "iso:country":"GB",
    "wof:name":"PR8 5DL",
    "wof:placetype":"postalcode"
},
  "geometry": {"coordinates":[-3.00417893642161,53.63461100472956],"type":"Point"}
}