{
  "type": "Feature",
  "properties": {
    "iso:country":"GB",
    "wof:name":"NE48 2JW",
    "wof:placetype":"postalcode"
},
  "geometry": {"coordinates":[-2.25606944649944,55.14403232892776],"type":"Point"}
}