{
  "type": "Feature",
  "properties": {
    "iso:country": "GB",
    "wof:name": "NE48 2JW",
    "wof:placetype": "postalcode"
  },
  "geometry": {"coordinates":[-2.256069,55.144032],"type":"Point"}
}
