{
  "type": "Feature",
  "properties": {
    "iso:country": "GB",
    "wof:name": "BN11 2RX",
    "wof:placetype": "postalcode"
  },
  "geometry": {"coordinates":[-0.344476,50.819949],"type":"Point"}
}
