{
  "type": "Feature",
  "properties": {
    "date:inception_lower": "2018-05-01",
    "date:inception_upper": "2018-05-01",
    "iso:country": "GB",
    "wof:name": "SN7 7GX",
    "wof:placetype": "postalcode"
  },
  "geometry": {"coordinates":[-1.592931,51.645859],"type":"Point"}
}
