{
  "type": "Feature",
  "properties": {
    "iso:country": "GB",
    "wof:name": "SA31 3BA",
    "wof:placetype": "postalcode"
  },
  "geometry": {"coordinates":[-4.316007,51.856544],"type":"Point"}
}
