{
  "type": "Feature",
  "properties": {
    "date:inception_lower": "1980-01-01",
    "date:inception_upper": "1980-01-01",
    "iso:country": "GB",
    "wof:name": "SA31 3BA",
    "wof:placetype": "postalcode"
  },
  "geometry": {"coordinates":[-4.315976,51.856491],"type":"Point"}
}
