{
  "type": "Feature",
  "properties": {
    "iso:country":"GB",
    "wof:name":"SA31 3BA",
    "wof:placetype":"postalcode"
},
  "geometry": {"coordinates":[-4.31595177547137,51.85646380063039],"type":"Point"}
}