{
  "type": "Feature",
  "properties": {
    "iso:country":"GB",
    "wof:name":"DD5 2PX",
    "wof:placetype":"postalcode"
},
  "geometry": {"coordinates":[-2.85119164532341,56.482351186715],"type":"Point"}
}