{
  "type": "Feature",
  "properties": {
    "iso:country": "GB",
    "wof:name": "DD5 2PX",
    "wof:placetype": "postalcode"
  },
  "geometry": {"coordinates":[-2.851192,56.482351],"type":"Point"}
}
