{
  "type": "Feature",
  "properties": {
    "iso:country":"GB",
    "wof:name":"HP1 3AU",
    "wof:placetype":"postalcode"
},
  "geometry": {"coordinates":[-0.47790651400768,51.77093014807595],"type":"Point"}
}