{
  "type": "Feature",
  "properties": {
    "iso:country": "GB",
    "wof:name": "HP1 3AU",
    "wof:placetype": "postalcode"
  },
  "geometry": {"coordinates":[-0.477906,51.77093],"type":"Point"}
}
