{
  "type": "Feature",
  "properties": {
    "iso:country":"GB",
    "wof:name":"CR0 0JA",
    "wof:placetype":"postalcode"
},
  "geometry": {"coordinates":[-0.01854285185337,51.34433674744797],"type":"Point"}
}