{
  "type": "Feature",
  "properties": {
    "iso:country":"GB",
    "wof:name":"PO32 6JQ",
    "wof:placetype":"postalcode"
},
  "geometry": {"coordinates":[-1.27898716525016,50.75103966809059],"type":"Point"}
}