{
  "type": "Feature",
  "properties": {
    "iso:country":"GB",
    "wof:name":"PO4 9BL",
    "wof:placetype":"postalcode"
},
  "geometry": {"coordinates":[-1.06596097092636,50.78732538540149],"type":"Point"}
}