{
  "type": "Feature",
  "properties": {
    "iso:country":"GB",
    "wof:name":"CV5 6JT",
    "wof:placetype":"postalcode"
},
  "geometry": {"coordinates":[-1.52487911614125,52.40225188225389],"type":"Point"}
}