{
  "type": "Feature",
  "properties": {
    "date:inception_lower": "1980-01-01",
    "date:inception_upper": "1980-01-01",
    "iso:country": "GB",
    "wof:name": "CV5 6JT",
    "wof:placetype": "postalcode"
  },
  "geometry": {"coordinates":[-1.524879,52.402252],"type":"Point"}
}
