{
  "type": "Feature",
  "properties": {
    "iso:country":"GB",
    "wof:name":"B10 0BP",
    "wof:placetype":"postalcode"
},
  "geometry": {"coordinates":[-1.86905906881755,52.47001909760235],"type":"Point"}
}