{
  "type": "Feature",
  "properties": {
    "iso:country": "GB",
    "wof:name": "OX18 2BA",
    "wof:placetype": "postalcode"
  },
  "geometry": {"coordinates":[-1.519883,51.757014],"type":"Point"}
}
