{
  "type": "Feature",
  "properties": {
    "date:inception_lower": "1991-09-01",
    "date:inception_upper": "1991-09-01",
    "iso:country": "GB",
    "wof:name": "OX18 2BA",
    "wof:placetype": "postalcode"
  },
  "geometry": {"coordinates":[-1.519883,51.757014],"type":"Point"}
}
