{
  "type": "Feature",
  "properties": {
    "date:inception_lower": "1980-01-01",
    "date:inception_upper": "1980-01-01",
    "iso:country": "GB",
    "wof:name": "L14 0NE",
    "wof:placetype": "postalcode"
  },
  "geometry": {"coordinates":[-2.87171,53.417908],"type":"Point"}
}
