{
  "type": "Feature",
  "properties": {
    "iso:country":"GB",
    "wof:name":"B13 8PY",
    "wof:placetype":"postalcode"
},
  "geometry": {"coordinates":[-1.89263829718211,52.44111297534567],"type":"Point"}
}