{
  "type": "Feature",
  "properties": {
    "iso:country": "GB",
    "wof:name": "NN17 3AE",
    "wof:placetype": "postalcode"
  },
  "geometry": {"coordinates":[-0.647828,52.565344],"type":"Point"}
}
