{
  "type": "Feature",
  "properties": {
    "date:inception_lower": "2016-05-01",
    "date:inception_upper": "2016-05-01",
    "iso:country": "GB",
    "wof:name": "MK45 4GR",
    "wof:placetype": "postalcode"
  },
  "geometry": {"coordinates":[-0.429932,52.005037],"type":"Point"}
}
