{
  "type": "Feature",
  "properties": {
    "iso:country": "GB",
    "wof:name": "CF64 2SH",
    "wof:placetype": "postalcode"
  },
  "geometry": {"coordinates":[-3.184554,51.441442],"type":"Point"}
}
