{
  "type": "Feature",
  "properties": {
    "iso:country": "GB",
    "wof:name": "TQ6 0DB",
    "wof:placetype": "postalcode"
  },
  "geometry": {"coordinates":[-3.568283,50.349005],"type":"Point"}
}
