{
  "type": "Feature",
  "properties": {
    "iso:country":"GB",
    "wof:name":"TQ6 0DB",
    "wof:placetype":"postalcode"
},
  "geometry": {"coordinates":[-3.56828263824027,50.34900501203193],"type":"Point"}
}