{
  "type": "Feature",
  "properties": {
    "iso:country": "GB",
    "wof:name": "KA13 6QW",
    "wof:placetype": "postalcode"
  },
  "geometry": {"coordinates":[-4.725339,55.65152],"type":"Point"}
}
