{
  "type": "Feature",
  "properties": {
    "date:inception_lower": "1980-01-01",
    "date:inception_upper": "1980-01-01",
    "iso:country": "GB",
    "wof:name": "KA13 6QW",
    "wof:placetype": "postalcode"
  },
  "geometry": {"coordinates":[-4.725339,55.65152],"type":"Point"}
}
