{
  "type": "Feature",
  "properties": {
    "iso:country":"GB",
    "wof:name":"KA13 6QW",
    "wof:placetype":"postalcode"
},
  "geometry": {"coordinates":[-4.7253393258511,55.65152022768758],"type":"Point"}
}