{
  "type": "Feature",
  "properties": {
    "iso:country": "GB",
    "wof:name": "DY3 3SS",
    "wof:placetype": "postalcode"
  },
  "geometry": {"coordinates":[-2.125889,52.542911],"type":"Point"}
}
