{
  "type": "Feature",
  "properties": {
    "iso:country":"GB",
    "wof:name":"S75 4BH",
    "wof:placetype":"postalcode"
},
  "geometry": {"coordinates":[-1.58521158377782,53.58826702041033],"type":"Point"}
}