{
  "type": "Feature",
  "properties": {
    "iso:country":"GB",
    "wof:name":"GU16 6TU",
    "wof:placetype":"postalcode"
},
  "geometry": {"coordinates":[-0.69196925689922,51.31178028474034],"type":"Point"}
}