{
  "type": "Feature",
  "properties": {
    "date:inception_lower": "1981-06-01",
    "date:inception_upper": "1981-06-01",
    "iso:country": "GB",
    "wof:name": "GU16 6TU",
    "wof:placetype": "postalcode"
  },
  "geometry": {"coordinates":[-0.691969,51.31178],"type":"Point"}
}
