{
  "type": "Feature",
  "properties": {
    "iso:country":"GB",
    "wof:name":"S11 7AW",
    "wof:placetype":"postalcode"
},
  "geometry": {"coordinates":[-1.51138077118112,53.36558513396162],"type":"Point"}
}