{
  "type": "Feature",
  "properties": {
    "date:inception_lower": "1980-01-01",
    "date:inception_upper": "1980-01-01",
    "iso:country": "GB",
    "wof:name": "EH15 1LD",
    "wof:placetype": "postalcode"
  },
  "geometry": {"coordinates":[-3.120946,55.942877],"type":"Point"}
}
