{
  "type": "Feature",
  "properties": {
    "iso:country":"GB",
    "wof:name":"B64 7PB",
    "wof:placetype":"postalcode"
},
  "geometry": {"coordinates":[-2.05668708671523,52.46775814684469],"type":"Point"}
}