{
  "type": "Feature",
  "properties": {
    "iso:country": "GB",
    "wof:name": "B64 7PB",
    "wof:placetype": "postalcode"
  },
  "geometry": {"coordinates":[-2.056687,52.467758],"type":"Point"}
}
