{
  "type": "Feature",
  "properties": {
    "date:inception_lower": "2018-08-01",
    "date:inception_upper": "2018-08-01",
    "iso:country": "GB",
    "wof:name": "NG22 8FW",
    "wof:placetype": "postalcode"
  },
  "geometry": {"coordinates":[-1.026378,53.103468],"type":"Point"}
}
