{
  "type": "Feature",
  "properties": {
    "iso:country": "GB",
    "wof:name": "NG22 8FW",
    "wof:placetype": "postalcode"
  },
  "geometry": {"coordinates":[-1.026378,53.103468],"type":"Point"}
}
