{
  "type": "Feature",
  "properties": {
    "date:inception_lower": "2020-09-01",
    "date:inception_upper": "2020-09-01",
    "iso:country": "GB",
    "wof:name": "OX14 2AX",
    "wof:placetype": "postalcode"
  },
  "geometry": {"coordinates":[-1.240335,51.704299],"type":"Point"}
}
