{
  "type": "Feature",
  "properties": {
    "iso:country":"GB",
    "wof:name":"YO13 0JW",
    "wof:placetype":"postalcode"
},
  "geometry": {"coordinates":[-0.51728737977112,54.29666453198555],"type":"Point"}
}