{
  "type": "Feature",
  "properties": {
    "date:inception_lower": "2000-06-01",
    "date:inception_upper": "2000-06-01",
    "iso:country": "GB",
    "wof:name": "GL51 6QE",
    "wof:placetype": "postalcode"
  },
  "geometry": {"coordinates":[-2.123278,51.891457],"type":"Point"}
}
