{
  "type": "Feature",
  "properties": {
    "date:inception_lower":"1980-01-01",
    "date:inception_upper":"1980-01-31",
    "iso:country":"GB",
    "wof:name":"NR10 4HP",
    "wof:placetype":"postalcode"
},
  "geometry": {"coordinates":[1.191529,52.77099],"type":"Point"}
}