{
  "type": "Feature",
  "properties": {
    "iso:country":"GB",
    "wof:name":"NR10 4HP",
    "wof:placetype":"postalcode"
},
  "geometry": {"coordinates":[1.19152897432371,52.77099015359189],"type":"Point"}
}