{
  "type": "Feature",
  "properties": {
    "iso:country": "GB",
    "wof:name": "CO12 5JZ",
    "wof:placetype": "postalcode"
  },
  "geometry": {"coordinates":[1.217421,51.917718],"type":"Point"}
}
