{
  "type": "Feature",
  "properties": {
    "iso:country":"GB",
    "wof:name":"CO12 5JZ",
    "wof:placetype":"postalcode"
},
  "geometry": {"coordinates":[1.21742088661859,51.91771785014813],"type":"Point"}
}