{
  "type": "Feature",
  "properties": {
    "date:inception_lower": "1980-01-01",
    "date:inception_upper": "1980-01-01",
    "iso:country": "GB",
    "wof:name": "SL4 2JG",
    "wof:placetype": "postalcode"
  },
  "geometry": {"coordinates":[-0.59435,51.474301],"type":"Point"}
}
