{
  "type": "Feature",
  "properties": {
    "iso:country":"GB",
    "wof:name":"SL4 2JG",
    "wof:placetype":"postalcode"
},
  "geometry": {"coordinates":[-0.59883007296629,51.47479313439759],"type":"Point"}
}