{
  "type": "Feature",
  "properties": {
    "iso:country": "GB",
    "wof:name": "KT8 2PR",
    "wof:placetype": "postalcode"
  },
  "geometry": {"coordinates":[-0.365735,51.400566],"type":"Point"}
}
