{
  "type": "Feature",
  "properties": {
    "date:inception_lower": "1985-10-01",
    "date:inception_upper": "1985-10-01",
    "iso:country": "GB",
    "wof:name": "YO17 9DL",
    "wof:placetype": "postalcode"
  },
  "geometry": {"coordinates":[-0.774562,54.128242],"type":"Point"}
}
