{
  "type": "Feature",
  "properties": {
    "iso:country": "GB",
    "wof:name": "KY4 8ED",
    "wof:placetype": "postalcode"
  },
  "geometry": {"coordinates":[-3.361494,56.099085],"type":"Point"}
}
