{
  "type": "Feature",
  "properties": {
    "iso:country":"GB",
    "wof:name":"BD7 4AA",
    "wof:placetype":"postalcode"
},
  "geometry": {"coordinates":[-1.78577674605265,53.78041200756102],"type":"Point"}
}