{
  "type": "Feature",
  "properties": {
    "iso:country":"GB",
    "wof:name":"NE24 1HG",
    "wof:placetype":"postalcode"
},
  "geometry": {"coordinates":[-1.51810078733346,55.12810099115354],"type":"Point"}
}