{
  "type": "Feature",
  "properties": {
    "iso:country":"GB",
    "wof:name":"MK41 7JP",
    "wof:placetype":"postalcode"
},
  "geometry": {"coordinates":[-0.45639142370939,52.1537519019021],"type":"Point"}
}