{
  "type": "Feature",
  "properties": {
    "iso:country": "GB",
    "wof:name": "MK41 7JP",
    "wof:placetype": "postalcode"
  },
  "geometry": {"coordinates":[-0.456391,52.153752],"type":"Point"}
}
