{
  "type": "Feature",
  "properties": {
    "date:inception_lower": "1980-01-01",
    "date:inception_upper": "1980-01-01",
    "iso:country": "GB",
    "wof:name": "MK41 7JP",
    "wof:placetype": "postalcode"
  },
  "geometry": {"coordinates":[-0.456391,52.153752],"type":"Point"}
}
