{
  "type": "Feature",
  "properties": {
    "iso:country": "GB",
    "wof:name": "NG31 8WR",
    "wof:placetype": "postalcode"
  },
  "geometry": {"coordinates":[-0.662501,52.921554],"type":"Point"}
}
