{
  "type": "Feature",
  "properties": {
    "date:inception_lower": "2022-09-01",
    "date:inception_upper": "2022-09-01",
    "iso:country": "GB",
    "wof:name": "WR5 2SY",
    "wof:placetype": "postalcode"
  },
  "geometry": {"coordinates":[-2.208967,52.164079],"type":"Point"}
}
