{
  "type": "Feature",
  "properties": {
    "iso:country": "GB",
    "wof:name": "LL23 7RG",
    "wof:placetype": "postalcode"
  },
  "geometry": {"coordinates":[-3.48969,52.928255],"type":"Point"}
}
