{
  "type": "Feature",
  "properties": {
    "iso:country":"GB",
    "wof:name":"LL23 7RG",
    "wof:placetype":"postalcode"
},
  "geometry": {"coordinates":[-3.48969048286488,52.92825501421952],"type":"Point"}
}