{
  "type": "Feature",
  "properties": {
    "date:inception_lower": "2022-02-01",
    "date:inception_upper": "2022-02-01",
    "iso:country": "GB",
    "wof:name": "CH66 4AX",
    "wof:placetype": "postalcode"
  },
  "geometry": {"coordinates":[-2.948371,53.277138],"type":"Point"}
}
