{
  "type": "Feature",
  "properties": {
    "iso:country":"GB",
    "wof:name":"NG7 3BU",
    "wof:placetype":"postalcode"
},
  "geometry": {"coordinates":[-1.17805430015575,52.95637534033477],"type":"Point"}
}