{
  "type": "Feature",
  "properties": {
    "date:inception_lower": "1980-01-01",
    "date:inception_upper": "1980-01-01",
    "iso:country": "GB",
    "wof:name": "CM6 1QJ",
    "wof:placetype": "postalcode"
  },
  "geometry": {"coordinates":[0.312661,51.790722],"type":"Point"}
}
