{
  "type": "Feature",
  "properties": {
    "iso:country":"GB",
    "wof:name":"CA8 9ER",
    "wof:placetype":"postalcode"
},
  "geometry": {"coordinates":[-2.76834187630336,54.86544726606],"type":"Point"}
}