{
  "type": "Feature",
  "properties": {
    "date:inception_lower": "2000-06-01",
    "date:inception_upper": "2000-06-01",
    "iso:country": "GB",
    "wof:name": "CA8 9ER",
    "wof:placetype": "postalcode"
  },
  "geometry": {"coordinates":[-2.768376,54.865346],"type":"Point"}
}
