{
  "type": "Feature",
  "properties": {
    "iso:country": "GB",
    "wof:name": "UB7 9BU",
    "wof:placetype": "postalcode"
  },
  "geometry": {"coordinates":[-0.468974,51.508437],"type":"Point"}
}
