{
  "type": "Feature",
  "properties": {
    "iso:country":"GB",
    "wof:name":"UB7 9BU",
    "wof:placetype":"postalcode"
},
  "geometry": {"coordinates":[-0.46897406451462,51.50843709296723],"type":"Point"}
}