{
  "type": "Feature",
  "properties": {
    "date:inception_lower": "2015-10-01",
    "date:inception_upper": "2015-10-01",
    "iso:country": "GB",
    "wof:name": "YO30 4ZH",
    "wof:placetype": "postalcode"
  },
  "geometry": {"coordinates":[-1.103392,53.989004],"type":"Point"}
}
