{
  "type": "Feature",
  "properties": {
    "iso:country":"GB",
    "wof:name":"YO30 4ZH",
    "wof:placetype":"postalcode"
},
  "geometry": {"coordinates":[-1.1033829547004,53.98898662662461],"type":"Point"}
}