{
  "type": "Feature",
  "properties": {
    "iso:country":"GB",
    "wof:name":"B25 8EH",
    "wof:placetype":"postalcode"
},
  "geometry": {"coordinates":[-1.82432303299249,52.45880464438884],"type":"Point"}
}