{
  "type": "Feature",
  "properties": {
    "date:inception_lower": "2024-09-01",
    "date:inception_upper": "2024-09-01",
    "iso:country": "GB",
    "wof:name": "CO5 9FY",
    "wof:placetype": "postalcode"
  },
  "geometry": {"coordinates":[0.702647,51.84388],"type":"Point"}
}
