{
  "type": "Feature",
  "properties": {
    "iso:country":"GB",
    "wof:name":"CM4 0SA",
    "wof:placetype":"postalcode"
},
  "geometry": {"coordinates":[0.32314182302792,51.69494823821285],"type":"Point"}
}