{
  "type": "Feature",
  "properties": {
    "iso:country":"GB",
    "wof:name":"PA15 4HR",
    "wof:placetype":"postalcode"
},
  "geometry": {"coordinates":[-4.76980384903793,55.94173544335661],"type":"Point"}
}