{
  "type": "Feature",
  "properties": {
    "date:inception_lower":"2002-10-01",
    "date:inception_upper":"2002-10-31",
    "iso:country":"GB",
    "wof:name":"MK10 9HB",
    "wof:placetype":"postalcode"
},
  "geometry": {"coordinates":[-0.701301,52.045062],"type":"Point"}
}