{
  "type": "Feature",
  "properties": {
    "iso:country": "GB",
    "wof:name": "MK10 9HB",
    "wof:placetype": "postalcode"
  },
  "geometry": {"coordinates":[-0.701495,52.044929],"type":"Point"}
}
