{
  "type": "Feature",
  "properties": {
    "iso:country":"GB",
    "wof:name":"EN2 7AL",
    "wof:placetype":"postalcode"
},
  "geometry": {"coordinates":[-0.09142635508143,51.65342612640764],"type":"Point"}
}