{
  "type": "Feature",
  "properties": {
    "date:inception_lower":"1980-01-01",
    "date:inception_upper":"1980-01-31",
    "iso:country":"GB",
    "wof:name":"ML9 2AL",
    "wof:placetype":"postalcode"
},
  "geometry": {"coordinates":[-3.970958,55.74432],"type":"Point"}
}