{
  "type": "Feature",
  "properties": {
    "iso:country": "GB",
    "wof:name": "ML9 2AL",
    "wof:placetype": "postalcode"
  },
  "geometry": {"coordinates":[-3.970958,55.74432],"type":"Point"}
}
