{
  "type": "Feature",
  "properties": {
    "iso:country":"GB",
    "wof:name":"DN14 7GL",
    "wof:placetype":"postalcode"
},
  "geometry": {"coordinates":[-0.86806255613917,53.74048557960101],"type":"Point"}
}