{
  "type": "Feature",
  "properties": {
    "date:inception_lower":"2003-06-01",
    "date:inception_upper":"2003-06-30",
    "iso:country":"GB",
    "wof:name":"DN14 7GL",
    "wof:placetype":"postalcode"
},
  "geometry": {"coordinates":[-0.868063,53.740486],"type":"Point"}
}