{
  "type": "Feature",
  "properties": {
    "iso:country": "GB",
    "wof:name": "DN14 7GL",
    "wof:placetype": "postalcode"
  },
  "geometry": {"coordinates":[-0.868063,53.740486],"type":"Point"}
}
