{
  "type": "Feature",
  "properties": {
    "iso:country":"GB",
    "wof:name":"BS21 5DF",
    "wof:placetype":"postalcode"
},
  "geometry": {"coordinates":[-2.85213457057142,51.42552812239794],"type":"Point"}
}