{
  "type": "Feature",
  "properties": {
    "iso:country": "GB",
    "wof:name": "BS21 5DF",
    "wof:placetype": "postalcode"
  },
  "geometry": {"coordinates":[-2.852135,51.425528],"type":"Point"}
}
