{
  "type": "Feature",
  "properties": {
    "iso:country":"GB",
    "wof:name":"KY16 0HH",
    "wof:placetype":"postalcode"
},
  "geometry": {"coordinates":[-2.88416689229965,56.381683439988],"type":"Point"}
}