{
  "type": "Feature",
  "properties": {
    "iso:country":"GB",
    "wof:name":"B90 4GD",
    "wof:placetype":"postalcode"
},
  "geometry": {"coordinates":[-1.81074004276086,52.37950934357391],"type":"Point"}
}