{
  "type": "Feature",
  "properties": {
    "iso:country": "GB",
    "wof:name": "B90 4GD",
    "wof:placetype": "postalcode"
  },
  "geometry": {"coordinates":[-1.81074,52.379509],"type":"Point"}
}
