{
  "type": "Feature",
  "properties": {
    "iso:country":"GB",
    "wof:name":"GU51 3BL",
    "wof:placetype":"postalcode"
},
  "geometry": {"coordinates":[-0.84093221480666,51.28202033632565],"type":"Point"}
}