{
  "type": "Feature",
  "properties": {
    "iso:country": "GB",
    "wof:name": "WN7 1UY",
    "wof:placetype": "postalcode"
  },
  "geometry": {"coordinates":[-2.521311,53.499186],"type":"Point"}
}
