{
  "type": "Feature",
  "properties": {
    "iso:country":"GB",
    "wof:name":"WN7 1UY",
    "wof:placetype":"postalcode"
},
  "geometry": {"coordinates":[-2.5213114315682,53.49918622151621],"type":"Point"}
}