{
  "type": "Feature",
  "properties": {
    "iso:country":"GB",
    "wof:name":"WD18 6PW",
    "wof:placetype":"postalcode"
},
  "geometry": {"coordinates":[-0.42190041302664,51.64458335731049],"type":"Point"}
}