{
  "type": "Feature",
  "properties": {
    "iso:country": "GB",
    "wof:name": "NG5 8DN",
    "wof:placetype": "postalcode"
  },
  "geometry": {"coordinates":[-1.119487,53.010181],"type":"Point"}
}
