{
  "type": "Feature",
  "properties": {
    "iso:country":"GB",
    "wof:name":"NG5 8DN",
    "wof:placetype":"postalcode"
},
  "geometry": {"coordinates":[-1.11948706087683,53.01018057805846],"type":"Point"}
}