{
  "type": "Feature",
  "properties": {
    "date:inception_lower": "2007-07-01",
    "date:inception_upper": "2007-07-01",
    "iso:country": "GB",
    "wof:name": "NR34 0DR",
    "wof:placetype": "postalcode"
  },
  "geometry": {"coordinates":[1.557378,52.497299],"type":"Point"}
}
