{
  "type": "Feature",
  "properties": {
    "iso:country":"GB",
    "wof:name":"NR34 0DR",
    "wof:placetype":"postalcode"
},
  "geometry": {"coordinates":[1.55882498595652,52.49616949921842],"type":"Point"}
}