{
  "type": "Feature",
  "properties": {
    "iso:country": "GB",
    "wof:name": "NR34 0DR",
    "wof:placetype": "postalcode"
  },
  "geometry": {"coordinates":[1.558825,52.496169],"type":"Point"}
}
