{
  "type": "Feature",
  "properties": {
    "iso:country":"GB",
    "wof:name":"SW9 8HH",
    "wof:placetype":"postalcode"
},
  "geometry": {"coordinates":[-0.11502072508321,51.46184490022483],"type":"Point"}
}