{
  "type": "Feature",
  "properties": {
    "iso:country":"GB",
    "wof:name":"SO23 7AY",
    "wof:placetype":"postalcode"
},
  "geometry": {"coordinates":[-1.31488882551224,51.07408689053874],"type":"Point"}
}