{
  "type": "Feature",
  "properties": {
    "iso:country":"GB",
    "wof:name":"TS2 1SW",
    "wof:placetype":"postalcode"
},
  "geometry": {"coordinates":[-1.22956567394931,54.57990753877205],"type":"Point"}
}