{
  "type": "Feature",
  "properties": {
    "iso:country": "GB",
    "wof:name": "PA8 7EP",
    "wof:placetype": "postalcode"
  },
  "geometry": {"coordinates":[-4.446991,55.890647],"type":"Point"}
}
