{
  "type": "Feature",
  "properties": {
    "date:inception_lower":"2002-09-01",
    "date:inception_upper":"2002-09-30",
    "iso:country":"GB",
    "wof:name":"PA8 7EP",
    "wof:placetype":"postalcode"
},
  "geometry": {"coordinates":[-4.446991,55.890647],"type":"Point"}
}