{
  "type": "Feature",
  "properties": {
    "iso:country":"GB",
    "wof:name":"N22 5RH",
    "wof:placetype":"postalcode"
},
  "geometry": {"coordinates":[-0.10473007704834,51.60168357706183],"type":"Point"}
}