{
  "type": "Feature",
  "properties": {
    "date:inception_lower": "2006-07-01",
    "date:inception_upper": "2006-07-01",
    "iso:country": "GB",
    "wof:name": "N22 5RH",
    "wof:placetype": "postalcode"
  },
  "geometry": {"coordinates":[-0.10473,51.601684],"type":"Point"}
}
