{
  "type": "Feature",
  "properties": {
    "iso:country":"GB",
    "wof:name":"SG5 3TJ",
    "wof:placetype":"postalcode"
},
  "geometry": {"coordinates":[-0.27601756591003,51.97661879341839],"type":"Point"}
}