{
  "type": "Feature",
  "properties": {
    "iso:country":"GB",
    "wof:name":"WA9 1RQ",
    "wof:placetype":"postalcode"
},
  "geometry": {"coordinates":[-2.7096620563377,53.45329975247518],"type":"Point"}
}