{
  "type": "Feature",
  "properties": {
    "date:inception_lower":"1980-01-01",
    "date:inception_upper":"1980-01-31",
    "iso:country":"GB",
    "wof:name":"WA9 1RQ",
    "wof:placetype":"postalcode"
},
  "geometry": {"coordinates":[-2.709662,53.4533],"type":"Point"}
}