{
  "type": "Feature",
  "properties": {
    "iso:country": "GB",
    "wof:name": "WA9 1RQ",
    "wof:placetype": "postalcode"
  },
  "geometry": {"coordinates":[-2.709662,53.4533],"type":"Point"}
}
