{
  "type": "Feature",
  "properties": {
    "date:inception_lower": "2005-08-01",
    "date:inception_upper": "2005-08-01",
    "iso:country": "GB",
    "wof:name": "CF48 4NJ",
    "wof:placetype": "postalcode"
  },
  "geometry": {"coordinates":[-3.344166,51.710507],"type":"Point"}
}
