{
  "type": "Feature",
  "properties": {
    "iso:country":"GB",
    "wof:name":"CF48 4NJ",
    "wof:placetype":"postalcode"
},
  "geometry": {"coordinates":[-3.34416841506499,51.71050204873954],"type":"Point"}
}