{
  "type": "Feature",
  "properties": {
    "iso:country":"GB",
    "wof:name":"HS1 2NB",
    "wof:placetype":"postalcode"
},
  "geometry": {"coordinates":[-6.38593200983753,58.20884070986867],"type":"Point"}
}