{
  "type": "Feature",
  "properties": {
    "iso:country":"GB",
    "wof:name":"SL5 7AX",
    "wof:placetype":"postalcode"
},
  "geometry": {"coordinates":[-0.6575035378515,51.40225674527463],"type":"Point"}
}