{
  "type": "Feature",
  "properties": {
    "iso:country":"GB",
    "wof:name":"E15 3PT",
    "wof:placetype":"postalcode"
},
  "geometry": {"coordinates":[0.01478059801627,51.53387587603852],"type":"Point"}
}