{
  "type": "Feature",
  "properties": {
    "date:inception_lower":"1980-01-01",
    "date:inception_upper":"1980-01-31",
    "iso:country":"GB",
    "wof:name":"PE14 9SJ",
    "wof:placetype":"postalcode"
},
  "geometry": {"coordinates":[0.220141,52.52887],"type":"Point"}
}