{
  "type": "Feature",
  "properties": {
    "iso:country":"GB",
    "wof:name":"DE11 7ED",
    "wof:placetype":"postalcode"
},
  "geometry": {"coordinates":[-1.530191904775,52.76762166641476],"type":"Point"}
}