{
  "type": "Feature",
  "properties": {
    "date:inception_lower": "2006-04-01",
    "date:inception_upper": "2006-04-01",
    "iso:country": "GB",
    "wof:name": "DE11 7ED",
    "wof:placetype": "postalcode"
  },
  "geometry": {"coordinates":[-1.530192,52.767622],"type":"Point"}
}
