{
  "type": "Feature",
  "properties": {
    "iso:country":"GB",
    "wof:name":"L20 9DS",
    "wof:placetype":"postalcode"
},
  "geometry": {"coordinates":[-2.97326767464029,53.45645833829814],"type":"Point"}
}