{
  "type": "Feature",
  "properties": {
    "iso:country": "GB",
    "wof:name": "TQ2 8JD",
    "wof:placetype": "postalcode"
  },
  "geometry": {"coordinates":[-3.54172,50.487819],"type":"Point"}
}
