{
  "type": "Feature",
  "properties": {
    "iso:country":"GB",
    "wof:name":"IV20 1XD",
    "wof:placetype":"postalcode"
},
  "geometry": {"coordinates":[-3.89687146682118,57.76353146139601],"type":"Point"}
}