{
  "type": "Feature",
  "properties": {
    "iso:country": "GB",
    "wof:name": "WC1H 0AY",
    "wof:placetype": "postalcode"
  },
  "geometry": {"coordinates":[-0.133363,51.525635],"type":"Point"}
}
