{
  "type": "Feature",
  "properties": {
    "date:inception_lower": "2000-12-01",
    "date:inception_upper": "2000-12-01",
    "iso:country": "GB",
    "wof:name": "WC1H 0AY",
    "wof:placetype": "postalcode"
  },
  "geometry": {"coordinates":[-0.133363,51.525635],"type":"Point"}
}
