{
  "type": "Feature",
  "properties": {
    "iso:country":"GB",
    "wof:name":"WC1H 0AY",
    "wof:placetype":"postalcode"
},
  "geometry": {"coordinates":[-0.13336270695008,51.52563470611202],"type":"Point"}
}