{
  "type": "Feature",
  "properties": {
    "date:inception_lower":"1980-01-01",
    "date:inception_upper":"1980-01-31",
    "iso:country":"GB",
    "wof:name":"B75 7TQ",
    "wof:placetype":"postalcode"
},
  "geometry": {"coordinates":[-1.81741,52.568309],"type":"Point"}
}