{
  "type": "Feature",
  "properties": {
    "iso:country":"GB",
    "wof:name":"B75 7TQ",
    "wof:placetype":"postalcode"
},
  "geometry": {"coordinates":[-1.81740959322006,52.56830937479289],"type":"Point"}
}