{
  "type": "Feature",
  "properties": {
    "iso:country": "GB",
    "wof:name": "SE5 0JE",
    "wof:placetype": "postalcode"
  },
  "geometry": {"coordinates":[-0.077302,51.484478],"type":"Point"}
}
