{
  "type": "Feature",
  "properties": {
    "iso:country":"GB",
    "wof:name":"SE5 0JE",
    "wof:placetype":"postalcode"
},
  "geometry": {"coordinates":[-0.07730215028693,51.48447834069213],"type":"Point"}
}