{
  "type": "Feature",
  "properties": {
    "date:inception_lower": "1980-01-01",
    "date:inception_upper": "1980-01-01",
    "iso:country": "GB",
    "wof:name": "TS16 0BE",
    "wof:placetype": "postalcode"
  },
  "geometry": {"coordinates":[-1.34523,54.534539],"type":"Point"}
}
