{
  "type": "Feature",
  "properties": {
    "iso:country":"GB",
    "wof:name":"M19 2SD",
    "wof:placetype":"postalcode"
},
  "geometry": {"coordinates":[-2.18474901496341,53.43341455629599],"type":"Point"}
}