{
  "type": "Feature",
  "properties": {
    "iso:country": "GB",
    "wof:name": "M19 2SD",
    "wof:placetype": "postalcode"
  },
  "geometry": {"coordinates":[-2.184749,53.433415],"type":"Point"}
}
