{
  "type": "Feature",
  "properties": {
    "date:inception_lower": "1980-01-01",
    "date:inception_upper": "1980-01-01",
    "iso:country": "GB",
    "wof:name": "M19 2SD",
    "wof:placetype": "postalcode"
  },
  "geometry": {"coordinates":[-2.184749,53.433415],"type":"Point"}
}
