{
  "type": "Feature",
  "properties": {
    "iso:country":"GB",
    "wof:name":"LN6 9XW",
    "wof:placetype":"postalcode"
},
  "geometry": {"coordinates":[-0.58104616943355,53.18154414794638],"type":"Point"}
}