{
  "type": "Feature",
  "properties": {
    "iso:country":"GB",
    "wof:name":"WF2 7JH",
    "wof:placetype":"postalcode"
},
  "geometry": {"coordinates":[-1.49288348340824,53.66744915224452],"type":"Point"}
}