{
  "type": "Feature",
  "properties": {
    "iso:country":"GB",
    "wof:name":"G15 6DP",
    "wof:placetype":"postalcode"
},
  "geometry": {"coordinates":[-4.35109998381695,55.90819075364197],"type":"Point"}
}