{
  "type": "Feature",
  "properties": {
    "iso:country":"GB",
    "wof:name":"L16 4PR",
    "wof:placetype":"postalcode"
},
  "geometry": {"coordinates":[-2.8939772370695,53.39990015955592],"type":"Point"}
}