{
  "type": "Feature",
  "properties": {
    "date:inception_lower": "2021-10-01",
    "date:inception_upper": "2021-10-01",
    "iso:country": "GB",
    "wof:name": "SA33 6AN",
    "wof:placetype": "postalcode"
  },
  "geometry": {"coordinates":[-4.360344,51.916688],"type":"Point"}
}
