{
  "type": "Feature",
  "properties": {
    "iso:country":"GB",
    "wof:name":"IV15 9FE",
    "wof:placetype":"postalcode"
},
  "geometry": {"coordinates":[-4.4245711892292,57.59040544162816],"type":"Point"}
}