{
  "type": "Feature",
  "properties": {
    "iso:country":"GB",
    "wof:name":"GU21 2DD",
    "wof:placetype":"postalcode"
},
  "geometry": {"coordinates":[-0.61111408321454,51.31809720363254],"type":"Point"}
}