{
  "type": "Feature",
  "properties": {
    "iso:country": "GB",
    "wof:name": "GU21 2DD",
    "wof:placetype": "postalcode"
  },
  "geometry": {"coordinates":[-0.611114,51.318097],"type":"Point"}
}
