{
  "type": "Feature",
  "properties": {
    "iso:country":"GB",
    "wof:name":"TS17 9NA",
    "wof:placetype":"postalcode"
},
  "geometry": {"coordinates":[-1.29166349385956,54.53375187522824],"type":"Point"}
}