{
  "type": "Feature",
  "properties": {
    "date:inception_lower":"1980-01-01",
    "date:inception_upper":"1980-01-31",
    "iso:country":"GB",
    "wof:name":"TS17 9NA",
    "wof:placetype":"postalcode"
},
  "geometry": {"coordinates":[-1.291663,54.533752],"type":"Point"}
}