{
  "type": "Feature",
  "properties": {
    "date:inception_lower":"1980-01-01",
    "date:inception_upper":"1980-01-31",
    "iso:country":"GB",
    "wof:name":"S65 3LJ",
    "wof:placetype":"postalcode"
},
  "geometry": {"coordinates":[-1.318511,53.438204],"type":"Point"}
}