{
  "type": "Feature",
  "properties": {
    "iso:country": "GB",
    "wof:name": "S65 3LJ",
    "wof:placetype": "postalcode"
  },
  "geometry": {"coordinates":[-1.318511,53.438204],"type":"Point"}
}
