{
  "type": "Feature",
  "properties": {
    "iso:country": "GB",
    "wof:name": "NG9 2EZ",
    "wof:placetype": "postalcode"
  },
  "geometry": {"coordinates":[-1.20252,52.92676],"type":"Point"}
}
