{
  "type": "Feature",
  "properties": {
    "iso:country":"GB",
    "wof:name":"KT19 9RZ",
    "wof:placetype":"postalcode"
},
  "geometry": {"coordinates":[-0.27027951547544,51.35703859770418],"type":"Point"}
}