{
  "type": "Feature",
  "properties": {
    "iso:country": "GB",
    "wof:name": "CW7 3AG",
    "wof:placetype": "postalcode"
  },
  "geometry": {"coordinates":[-2.511583,53.193989],"type":"Point"}
}
