{
  "type": "Feature",
  "properties": {
    "date:inception_lower":"1980-01-01",
    "date:inception_upper":"1980-01-31",
    "iso:country":"GB",
    "wof:name":"CW7 3AG",
    "wof:placetype":"postalcode"
},
  "geometry": {"coordinates":[-2.511583,53.193989],"type":"Point"}
}