{
  "type": "Feature",
  "properties": {
    "iso:country":"GB",
    "wof:name":"BS24 8BD",
    "wof:placetype":"postalcode"
},
  "geometry": {"coordinates":[-2.9122671406599,51.33504852598458],"type":"Point"}
}