{
  "type": "Feature",
  "properties": {
    "iso:country":"GB",
    "wof:name":"SS16 5TY",
    "wof:placetype":"postalcode"
},
  "geometry": {"coordinates":[0.44635986233081,51.56307969540791],"type":"Point"}
}