{
  "type": "Feature",
  "properties": {
    "iso:country":"GB",
    "wof:name":"DG2 0LT",
    "wof:placetype":"postalcode"
},
  "geometry": {"coordinates":[-3.6313704652265,55.08107435224783],"type":"Point"}
}