{
  "type": "Feature",
  "properties": {
    "iso:country":"GB",
    "wof:name":"BS37 6LP",
    "wof:placetype":"postalcode"
},
  "geometry": {"coordinates":[-2.37954822730604,51.5339322248784],"type":"Point"}
}