{
  "type": "Feature",
  "properties": {
    "iso:country": "GB",
    "wof:name": "BS37 6LP",
    "wof:placetype": "postalcode"
  },
  "geometry": {"coordinates":[-2.379548,51.533932],"type":"Point"}
}
