{
  "type": "Feature",
  "properties": {
    "iso:country":"GB",
    "wof:name":"EX8 2HZ",
    "wof:placetype":"postalcode"
},
  "geometry": {"coordinates":[-3.39757661952316,50.61855157621321],"type":"Point"}
}