{
  "type": "Feature",
  "properties": {
    "iso:country":"GB",
    "wof:name":"TQ2 8HH",
    "wof:placetype":"postalcode"
},
  "geometry": {"coordinates":[-3.53495799906992,50.49144298121729],"type":"Point"}
}