{
  "type": "Feature",
  "properties": {
    "date:inception_lower":"1980-01-01",
    "date:inception_upper":"1980-01-31",
    "iso:country":"GB",
    "wof:name":"EH21 6AF",
    "wof:placetype":"postalcode"
},
  "geometry": {"coordinates":[-3.057154,55.943882],"type":"Point"}
}