{
  "type": "Feature",
  "properties": {
    "iso:country":"GB",
    "wof:name":"IP27 0AD",
    "wof:placetype":"postalcode"
},
  "geometry": {"coordinates":[0.62336836508027,52.44667122595662],"type":"Point"}
}