{
  "type": "Feature",
  "properties": {
    "iso:country":"GB",
    "wof:name":"CO7 9HU",
    "wof:placetype":"postalcode"
},
  "geometry": {"coordinates":[0.94922739439756,51.87278318405295],"type":"Point"}
}