{
  "type": "Feature",
  "properties": {
    "date:inception_lower":"1991-09-01",
    "date:inception_upper":"1991-09-30",
    "iso:country":"GB",
    "wof:name":"CB10 1RS",
    "wof:placetype":"postalcode"
},
  "geometry": {"coordinates":[0.183515,52.084355],"type":"Point"}
}