{
  "type": "Feature",
  "properties": {
    "iso:country": "GB",
    "wof:name": "CB10 1RS",
    "wof:placetype": "postalcode"
  },
  "geometry": {"coordinates":[0.183515,52.084355],"type":"Point"}
}
