{
  "type": "Feature",
  "properties": {
    "iso:country":"GB",
    "wof:name":"NN6 8SJ",
    "wof:placetype":"postalcode"
},
  "geometry": {"coordinates":[-1.01764664781255,52.37516683842723],"type":"Point"}
}