{
  "type": "Feature",
  "properties": {
    "iso:country": "GB",
    "wof:name": "NN6 8SJ",
    "wof:placetype": "postalcode"
  },
  "geometry": {"coordinates":[-1.017647,52.375167],"type":"Point"}
}
