{
  "type": "Feature",
  "properties": {
    "iso:country": "GB",
    "wof:name": "NP16 6PE",
    "wof:placetype": "postalcode"
  },
  "geometry": {"coordinates":[-2.745772,51.686514],"type":"Point"}
}
