{
  "type": "Feature",
  "properties": {
    "date:inception_lower":"1999-06-01",
    "date:inception_upper":"1999-06-30",
    "iso:country":"GB",
    "wof:name":"NP16 6PE",
    "wof:placetype":"postalcode"
},
  "geometry": {"coordinates":[-2.745772,51.686514],"type":"Point"}
}