{
  "type": "Feature",
  "properties": {
    "iso:country":"GB",
    "wof:name":"NP16 6PE",
    "wof:placetype":"postalcode"
},
  "geometry": {"coordinates":[-2.74577232059721,51.6865136852787],"type":"Point"}
}