{
  "type": "Feature",
  "properties": {
    "iso:country":"GB",
    "wof:name":"L26 6BP",
    "wof:placetype":"postalcode"
},
  "geometry": {"coordinates":[-2.8211666100757,53.37016679207077],"type":"Point"}
}