{
  "type": "Feature",
  "properties": {
    "iso:country":"GB",
    "wof:name":"WR2 6LQ",
    "wof:placetype":"postalcode"
},
  "geometry": {"coordinates":[-2.25701001422614,52.2271844917293],"type":"Point"}
}