{
  "type": "Feature",
  "properties": {
    "iso:country":"GB",
    "wof:name":"OL11 4DF",
    "wof:placetype":"postalcode"
},
  "geometry": {"coordinates":[-2.18395796540354,53.61226665228325],"type":"Point"}
}