{
  "type": "Feature",
  "properties": {
    "iso:country":"GB",
    "wof:name":"PO33 1YQ",
    "wof:placetype":"postalcode"
},
  "geometry": {"coordinates":[-1.12357429785691,50.69377911905195],"type":"Point"}
}