{
  "type": "Feature",
  "properties": {
    "iso:country": "GB",
    "wof:name": "TS3 7NJ",
    "wof:placetype": "postalcode"
  },
  "geometry": {"coordinates":[-1.208503,54.55548],"type":"Point"}
}
