{
  "type": "Feature",
  "properties": {
    "iso:country":"GB",
    "wof:name":"TS3 7NJ",
    "wof:placetype":"postalcode"
},
  "geometry": {"coordinates":[-1.2085026012869,54.5554795965484],"type":"Point"}
}