{
  "type": "Feature",
  "properties": {
    "iso:country":"GB",
    "wof:name":"TN9 2PY",
    "wof:placetype":"postalcode"
},
  "geometry": {"coordinates":[0.25764531199389,51.18548907795885],"type":"Point"}
}