{
  "type": "Feature",
  "properties": {
    "date:inception_lower": "1985-04-01",
    "date:inception_upper": "1985-04-01",
    "iso:country": "GB",
    "wof:name": "TN9 2PY",
    "wof:placetype": "postalcode"
  },
  "geometry": {"coordinates":[0.257645,51.185489],"type":"Point"}
}
