{
  "type": "Feature",
  "properties": {
    "iso:country":"GB",
    "wof:name":"LU7 9HH",
    "wof:placetype":"postalcode"
},
  "geometry": {"coordinates":[-0.65121168541843,51.90229043416142],"type":"Point"}
}