{
  "type": "Feature",
  "properties": {
    "date:inception_lower":"1980-01-01",
    "date:inception_upper":"1980-01-31",
    "iso:country":"GB",
    "wof:name":"B26 1JF",
    "wof:placetype":"postalcode"
},
  "geometry": {"coordinates":[-1.80663,52.459469],"type":"Point"}
}