{
  "type": "Feature",
  "properties": {
    "iso:country": "GB",
    "wof:name": "B26 1JF",
    "wof:placetype": "postalcode"
  },
  "geometry": {"coordinates":[-1.80663,52.459469],"type":"Point"}
}
