{
  "type": "Feature",
  "properties": {
    "date:inception_lower": "2017-04-01",
    "date:inception_upper": "2017-04-01",
    "iso:country": "GB",
    "wof:name": "S70 6FG",
    "wof:placetype": "postalcode"
  },
  "geometry": {"coordinates":[-1.503021,53.545421],"type":"Point"}
}
