{
  "type": "Feature",
  "properties": {
    "iso:country": "GB",
    "wof:name": "S70 6FG",
    "wof:placetype": "postalcode"
  },
  "geometry": {"coordinates":[-1.503021,53.545421],"type":"Point"}
}
