{
  "type": "Feature",
  "properties": {
    "iso:country":"GB",
    "wof:name":"BA11 3NE",
    "wof:placetype":"postalcode"
},
  "geometry": {"coordinates":[-2.33810810821273,51.23500487995199],"type":"Point"}
}