{
  "type": "Feature",
  "properties": {
    "iso:country": "GB",
    "wof:name": "BA11 3NE",
    "wof:placetype": "postalcode"
  },
  "geometry": {"coordinates":[-2.338108,51.235005],"type":"Point"}
}
