{
  "type": "Feature",
  "properties": {
    "date:inception_lower":"2004-06-01",
    "date:inception_upper":"2004-06-30",
    "iso:country":"GB",
    "wof:name":"BA11 3NE",
    "wof:placetype":"postalcode"
},
  "geometry": {"coordinates":[-2.338108,51.235005],"type":"Point"}
}