{
  "type": "Feature",
  "properties": {
    "iso:country": "GB",
    "wof:name": "TA2 8HT",
    "wof:placetype": "postalcode"
  },
  "geometry": {"coordinates":[-3.115955,51.061919],"type":"Point"}
}
