{
  "type": "Feature",
  "properties": {
    "iso:country":"GB",
    "wof:name":"CH4 8NS",
    "wof:placetype":"postalcode"
},
  "geometry": {"coordinates":[-2.91889137127657,53.17099333847842],"type":"Point"}
}