{
  "type": "Feature",
  "properties": {
    "iso:country":"GB",
    "wof:name":"RG14 6JQ",
    "wof:placetype":"postalcode"
},
  "geometry": {"coordinates":[-1.33032731276929,51.39034435103498],"type":"Point"}
}