{
  "type": "Feature",
  "properties": {
    "date:inception_lower": "1992-08-01",
    "date:inception_upper": "1992-08-01",
    "iso:country": "GB",
    "wof:name": "CT21 4PF",
    "wof:placetype": "postalcode"
  },
  "geometry": {"coordinates":[0.984742,51.079821],"type":"Point"}
}
