{
  "type": "Feature",
  "properties": {
    "iso:country": "GB",
    "wof:name": "CT21 4PF",
    "wof:placetype": "postalcode"
  },
  "geometry": {"coordinates":[0.984742,51.079821],"type":"Point"}
}
