{
  "type": "Feature",
  "properties": {
    "iso:country":"GB",
    "wof:name":"CT21 4PF",
    "wof:placetype":"postalcode"
},
  "geometry": {"coordinates":[0.98470874967575,51.07981981415092],"type":"Point"}
}