{
  "type": "Feature",
  "properties": {
    "iso:country":"GB",
    "wof:name":"CV2 1NN",
    "wof:placetype":"postalcode"
},
  "geometry": {"coordinates":[-1.4658520115142,52.45203917703947],"type":"Point"}
}