{
  "type": "Feature",
  "properties": {
    "date:inception_lower": "1980-01-01",
    "date:inception_upper": "1980-01-01",
    "iso:country": "GB",
    "wof:name": "CV2 1NN",
    "wof:placetype": "postalcode"
  },
  "geometry": {"coordinates":[-1.465852,52.452039],"type":"Point"}
}
