{
  "type": "Feature",
  "properties": {
    "date:inception_lower":"1980-01-01",
    "date:inception_upper":"1980-01-31",
    "iso:country":"GB",
    "wof:name":"L7 8RP",
    "wof:placetype":"postalcode"
},
  "geometry": {"coordinates":[-2.956545,53.408638],"type":"Point"}
}