{
  "type": "Feature",
  "properties": {
    "iso:country":"GB",
    "wof:name":"DY10 3NQ",
    "wof:placetype":"postalcode"
},
  "geometry": {"coordinates":[-2.17906732107379,52.40565862929639],"type":"Point"}
}