{
  "type": "Feature",
  "properties": {
    "date:inception_lower":"1998-06-01",
    "date:inception_upper":"1998-06-30",
    "iso:country":"GB",
    "wof:name":"DA11 8NE",
    "wof:placetype":"postalcode"
},
  "geometry": {"coordinates":[0.341226,51.423835],"type":"Point"}
}