{
  "type": "Feature",
  "properties": {
    "iso:country":"GB",
    "wof:name":"CA17 4RQ",
    "wof:placetype":"postalcode"
},
  "geometry": {"coordinates":[-2.34938480533708,54.47370438944493],"type":"Point"}
}