{
  "type": "Feature",
  "properties": {
    "date:inception_lower":"2009-07-01",
    "date:inception_upper":"2009-07-31",
    "iso:country":"GB",
    "wof:name":"CA17 4RQ",
    "wof:placetype":"postalcode"
},
  "geometry": {"coordinates":[-2.349385,54.473704],"type":"Point"}
}