{
  "type": "Feature",
  "properties": {
    "date:inception_lower": "2001-06-01",
    "date:inception_upper": "2001-06-01",
    "iso:country": "GB",
    "wof:name": "HR1 1DA",
    "wof:placetype": "postalcode"
  },
  "geometry": {"coordinates":[-2.708795,52.062164],"type":"Point"}
}
