{
  "type": "Feature",
  "properties": {
    "iso:country":"GB",
    "wof:name":"EN8 0XG",
    "wof:placetype":"postalcode"
},
  "geometry": {"coordinates":[-0.02300704358293,51.71609525440476],"type":"Point"}
}