{
  "type": "Feature",
  "properties": {
    "iso:country": "GB",
    "wof:name": "EN8 0XG",
    "wof:placetype": "postalcode"
  },
  "geometry": {"coordinates":[-0.023007,51.716095],"type":"Point"}
}
