{
  "type": "Feature",
  "properties": {
    "date:inception_lower":"1994-12-01",
    "date:inception_upper":"1994-12-31",
    "iso:country":"GB",
    "wof:name":"EN8 0XG",
    "wof:placetype":"postalcode"
},
  "geometry": {"coordinates":[-0.023007,51.716095],"type":"Point"}
}