{
  "type": "Feature",
  "properties": {
    "iso:country":"GB",
    "wof:name":"GU34 2HS",
    "wof:placetype":"postalcode"
},
  "geometry": {"coordinates":[-0.97764931851703,51.15722297569786],"type":"Point"}
}