{
  "type": "Feature",
  "properties": {
    "iso:country":"GB",
    "wof:name":"B69 4SH",
    "wof:placetype":"postalcode"
},
  "geometry": {"coordinates":[-2.01304954886638,52.49196308310533],"type":"Point"}
}