{
  "type": "Feature",
  "properties": {
    "iso:country":"GB",
    "wof:name":"DA12 5JG",
    "wof:placetype":"postalcode"
},
  "geometry": {"coordinates":[0.37989525948726,51.41114854970661],"type":"Point"}
}