{
  "type": "Feature",
  "properties": {
    "iso:country":"GB",
    "wof:name":"BA13 4QZ",
    "wof:placetype":"postalcode"
},
  "geometry": {"coordinates":[-2.19486581934151,51.26661400048689],"type":"Point"}
}