{
  "type": "Feature",
  "properties": {
    "iso:country":"GB",
    "wof:name":"SN7 7LU",
    "wof:placetype":"postalcode"
},
  "geometry": {"coordinates":[-1.60460212788006,51.64152639931624],"type":"Point"}
}