{
  "type": "Feature",
  "properties": {
    "iso:country": "GB",
    "wof:name": "SN7 7LU",
    "wof:placetype": "postalcode"
  },
  "geometry": {"coordinates":[-1.604094,51.641824],"type":"Point"}
}
