{
  "type": "Feature",
  "properties": {
    "iso:country":"GB",
    "wof:name":"PL2 3NQ",
    "wof:placetype":"postalcode"
},
  "geometry": {"coordinates":[-4.1474682426232,50.3970959271144],"type":"Point"}
}