{
  "type": "Feature",
  "properties": {
    "date:inception_lower": "1980-01-01",
    "date:inception_upper": "1980-01-01",
    "iso:country": "GB",
    "wof:name": "PL2 3NQ",
    "wof:placetype": "postalcode"
  },
  "geometry": {"coordinates":[-4.147468,50.397096],"type":"Point"}
}
