{
  "type": "Feature",
  "properties": {
    "date:inception_lower": "2023-10-01",
    "date:inception_upper": "2023-10-01",
    "iso:country": "GB",
    "wof:name": "WN3 4QW",
    "wof:placetype": "postalcode"
  },
  "geometry": {"coordinates":[-2.61511,53.535815],"type":"Point"}
}
