{
  "type": "Feature",
  "properties": {
    "iso:country": "GB",
    "wof:name": "TS17 5BN",
    "wof:placetype": "postalcode"
  },
  "geometry": {"coordinates":[-1.318367,54.522689],"type":"Point"}
}
