{
  "type": "Feature",
  "properties": {
    "iso:country":"GB",
    "wof:name":"NP16 6JP",
    "wof:placetype":"postalcode"
},
  "geometry": {"coordinates":[-2.69837716370969,51.62124896285892],"type":"Point"}
}