{
  "type": "Feature",
  "properties": {
    "iso:country": "GB",
    "wof:name": "NP16 6JP",
    "wof:placetype": "postalcode"
  },
  "geometry": {"coordinates":[-2.698377,51.621249],"type":"Point"}
}
