{
  "type": "Feature",
  "properties": {
    "iso:country":"GB",
    "wof:name":"G53 5YR",
    "wof:placetype":"postalcode"
},
  "geometry": {"coordinates":[-4.35447444747368,55.83740224477793],"type":"Point"}
}