{
  "type": "Feature",
  "properties": {
    "date:inception_lower": "2013-02-01",
    "date:inception_upper": "2013-02-01",
    "iso:country": "GB",
    "wof:name": "CV3 2SB",
    "wof:placetype": "postalcode"
  },
  "geometry": {"coordinates":[-1.433373,52.397677],"type":"Point"}
}
