{
  "type": "Feature",
  "properties": {
    "iso:country":"GB",
    "wof:name":"CV3 2SB",
    "wof:placetype":"postalcode"
},
  "geometry": {"coordinates":[-1.43273775862134,52.39745867781946],"type":"Point"}
}