{
  "type": "Feature",
  "properties": {
    "iso:country": "GB",
    "wof:name": "CV3 2SB",
    "wof:placetype": "postalcode"
  },
  "geometry": {"coordinates":[-1.433343,52.397704],"type":"Point"}
}
