{
  "type": "Feature",
  "properties": {
    "iso:country":"GB",
    "wof:name":"SO41 5PA",
    "wof:placetype":"postalcode"
},
  "geometry": {"coordinates":[-1.53379820007276,50.78125645824501],"type":"Point"}
}