{
  "type": "Feature",
  "properties": {
    "date:inception_lower":"1992-08-01",
    "date:inception_upper":"1992-08-31",
    "iso:country":"GB",
    "wof:name":"SO41 5PA",
    "wof:placetype":"postalcode"
},
  "geometry": {"coordinates":[-1.533798,50.781256],"type":"Point"}
}