{
  "type": "Feature",
  "properties": {
    "iso:country":"GB",
    "wof:name":"CV9 1BL",
    "wof:placetype":"postalcode"
},
  "geometry": {"coordinates":[-1.54648668900734,52.5769317846258],"type":"Point"}
}