{
  "type": "Feature",
  "properties": {
    "date:inception_lower": "2020-05-01",
    "date:inception_upper": "2020-05-01",
    "iso:country": "GB",
    "wof:name": "WF12 7AY",
    "wof:placetype": "postalcode"
  },
  "geometry": {"coordinates":[-1.609403,53.696151],"type":"Point"}
}
