{
  "type": "Feature",
  "properties": {
    "iso:country":"GB",
    "wof:name":"SO14 3HP",
    "wof:placetype":"postalcode"
},
  "geometry": {"coordinates":[-1.40042960195994,50.90160671701597],"type":"Point"}
}