{
  "type": "Feature",
  "properties": {
    "iso:country": "GB",
    "wof:name": "PO30 5JL",
    "wof:placetype": "postalcode"
  },
  "geometry": {"coordinates":[-1.296002,50.700622],"type":"Point"}
}
