{
  "type": "Feature",
  "properties": {
    "iso:country":"GB",
    "wof:name":"LS27 7TB",
    "wof:placetype":"postalcode"
},
  "geometry": {"coordinates":[-1.58833184736868,53.76142666346632],"type":"Point"}
}