{
  "type": "Feature",
  "properties": {
    "date:inception_lower": "1980-01-01",
    "date:inception_upper": "1980-01-01",
    "iso:country": "GB",
    "wof:name": "LS27 7TB",
    "wof:placetype": "postalcode"
  },
  "geometry": {"coordinates":[-1.588332,53.761427],"type":"Point"}
}
