{
  "type": "Feature",
  "properties": {
    "iso:country": "GB",
    "wof:name": "HU10 6FJ",
    "wof:placetype": "postalcode"
  },
  "geometry": {"coordinates":[-0.452045,53.76095],"type":"Point"}
}
