{
  "type": "Feature",
  "properties": {
    "iso:country":"GB",
    "wof:name":"HU10 6FJ",
    "wof:placetype":"postalcode"
},
  "geometry": {"coordinates":[-0.45204543467542,53.76094996013476],"type":"Point"}
}