{
  "type": "Feature",
  "properties": {
    "date:inception_lower": "1980-01-01",
    "date:inception_upper": "1980-01-01",
    "iso:country": "GB",
    "wof:name": "SW12 0LS",
    "wof:placetype": "postalcode"
  },
  "geometry": {"coordinates":[-0.14516,51.446355],"type":"Point"}
}
