{
  "type": "Feature",
  "properties": {
    "iso:country": "GB",
    "wof:name": "NG33 4HP",
    "wof:placetype": "postalcode"
  },
  "geometry": {"coordinates":[-0.522801,52.884015],"type":"Point"}
}
