{
  "type": "Feature",
  "properties": {
    "iso:country":"GB",
    "wof:name":"NG33 4HP",
    "wof:placetype":"postalcode"
},
  "geometry": {"coordinates":[-0.52280069825059,52.88401536776934],"type":"Point"}
}