{
  "type": "Feature",
  "properties": {
    "date:inception_lower": "1980-01-01",
    "date:inception_upper": "1980-01-01",
    "iso:country": "GB",
    "wof:name": "NG33 4HP",
    "wof:placetype": "postalcode"
  },
  "geometry": {"coordinates":[-0.522801,52.884015],"type":"Point"}
}
