{
  "type": "Feature",
  "properties": {
    "iso:country":"GB",
    "wof:name":"NE40 3QE",
    "wof:placetype":"postalcode"
},
  "geometry": {"coordinates":[-1.7675588534893,54.9767417562212],"type":"Point"}
}