{
  "type": "Feature",
  "properties": {
    "date:inception_lower": "1984-10-01",
    "date:inception_upper": "1984-10-01",
    "iso:country": "GB",
    "wof:name": "B12 9HF",
    "wof:placetype": "postalcode"
  },
  "geometry": {"coordinates":[-1.893385,52.460991],"type":"Point"}
}
