{
  "type": "Feature",
  "properties": {
    "iso:country":"GB",
    "wof:name":"B12 9HF",
    "wof:placetype":"postalcode"
},
  "geometry": {"coordinates":[-1.89338483029977,52.46099055241055],"type":"Point"}
}