{
  "type": "Feature",
  "properties": {
    "iso:country": "GB",
    "wof:name": "DN37 0SL",
    "wof:placetype": "postalcode"
  },
  "geometry": {"coordinates":[-0.172185,53.489336],"type":"Point"}
}
