{
  "type": "Feature",
  "properties": {
    "date:inception_lower": "1998-12-01",
    "date:inception_upper": "1998-12-01",
    "iso:country": "GB",
    "wof:name": "S41 0GE",
    "wof:placetype": "postalcode"
  },
  "geometry": {"coordinates":[-1.41021,53.227464],"type":"Point"}
}
