{
  "type": "Feature",
  "properties": {
    "iso:country": "GB",
    "wof:name": "S41 0GE",
    "wof:placetype": "postalcode"
  },
  "geometry": {"coordinates":[-1.41021,53.227464],"type":"Point"}
}
