{
  "type": "Feature",
  "properties": {
    "iso:country":"GB",
    "wof:name":"WA4 1UY",
    "wof:placetype":"postalcode"
},
  "geometry": {"coordinates":[-2.55740190235376,53.38543415864229],"type":"Point"}
}