{
  "type": "Feature",
  "properties": {
    "iso:country": "GB",
    "wof:name": "NG3 4GP",
    "wof:placetype": "postalcode"
  },
  "geometry": {"coordinates":[-1.149833,52.963845],"type":"Point"}
}
