{
  "type": "Feature",
  "properties": {
    "date:inception_lower":"1980-01-01",
    "date:inception_upper":"1980-01-31",
    "iso:country":"GB",
    "wof:name":"PO12 1NJ",
    "wof:placetype":"postalcode"
},
  "geometry": {"coordinates":[-1.122903,50.794233],"type":"Point"}
}