{
  "type": "Feature",
  "properties": {
    "iso:country":"GB",
    "wof:name":"PO12 1NJ",
    "wof:placetype":"postalcode"
},
  "geometry": {"coordinates":[-1.12290350851053,50.79423311915231],"type":"Point"}
}