{
  "type": "Feature",
  "properties": {
    "date:inception_lower": "2020-12-01",
    "date:inception_upper": "2020-12-01",
    "iso:country": "GB",
    "wof:name": "TN25 6FB",
    "wof:placetype": "postalcode"
  },
  "geometry": {"coordinates":[1.000489,51.104711],"type":"Point"}
}
