{
  "type": "Feature",
  "properties": {
    "date:inception_lower": "1980-01-01",
    "date:inception_upper": "1980-01-01",
    "iso:country": "GB",
    "wof:name": "WR10 2EX",
    "wof:placetype": "postalcode"
  },
  "geometry": {"coordinates":[-2.065152,52.139736],"type":"Point"}
}
