{
  "type": "Feature",
  "properties": {
    "iso:country":"GB",
    "wof:name":"WR10 2EX",
    "wof:placetype":"postalcode"
},
  "geometry": {"coordinates":[-2.06515165775187,52.13973626574801],"type":"Point"}
}