{
  "type": "Feature",
  "properties": {
    "iso:country": "GB",
    "wof:name": "SG6 4YE",
    "wof:placetype": "postalcode"
  },
  "geometry": {"coordinates":[-0.235864,51.992533],"type":"Point"}
}
