{
  "type": "Feature",
  "properties": {
    "iso:country":"GB",
    "wof:name":"SL2 1DT",
    "wof:placetype":"postalcode"
},
  "geometry": {"coordinates":[-0.61286470908689,51.52857058559937],"type":"Point"}
}