{
  "type": "Feature",
  "properties": {
    "iso:country":"GB",
    "wof:name":"KA12 9PS",
    "wof:placetype":"postalcode"
},
  "geometry": {"coordinates":[-4.6643342427566,55.63385865277223],"type":"Point"}
}