{
  "type": "Feature",
  "properties": {
    "iso:country":"GB",
    "wof:name":"SW17 9LG",
    "wof:placetype":"postalcode"
},
  "geometry": {"coordinates":[-0.16192629561711,51.4201716573389],"type":"Point"}
}