{
  "type": "Feature",
  "properties": {
    "iso:country": "GB",
    "wof:name": "MK5 7ER",
    "wof:placetype": "postalcode"
  },
  "geometry": {"coordinates":[-0.779817,52.015357],"type":"Point"}
}
