{
  "type": "Feature",
  "properties": {
    "iso:country":"GB",
    "wof:name":"KY11 1HB",
    "wof:placetype":"postalcode"
},
  "geometry": {"coordinates":[-3.39975535880257,56.0108860705687],"type":"Point"}
}