{
  "type": "Feature",
  "properties": {
    "iso:country":"GB",
    "wof:name":"B43 5PS",
    "wof:placetype":"postalcode"
},
  "geometry": {"coordinates":[-1.93670925157262,52.53636617738848],"type":"Point"}
}