{
  "type": "Feature",
  "properties": {
    "date:inception_lower": "1980-01-01",
    "date:inception_upper": "1980-01-01",
    "iso:country": "GB",
    "wof:name": "B43 5PS",
    "wof:placetype": "postalcode"
  },
  "geometry": {"coordinates":[-1.936709,52.536366],"type":"Point"}
}
