{
  "type": "Feature",
  "properties": {
    "iso:country": "GB",
    "wof:name": "CM12 9SG",
    "wof:placetype": "postalcode"
  },
  "geometry": {"coordinates":[0.39602,51.604012],"type":"Point"}
}
