{
  "type": "Feature",
  "properties": {
    "iso:country":"GB",
    "wof:name":"PL2 1EG",
    "wof:placetype":"postalcode"
},
  "geometry": {"coordinates":[-4.17153923387535,50.38160123303433],"type":"Point"}
}