{
  "type": "Feature",
  "properties": {
    "iso:country": "GB",
    "wof:name": "PR25 4QG",
    "wof:placetype": "postalcode"
  },
  "geometry": {"coordinates":[-2.684103,53.704596],"type":"Point"}
}
