{
  "type": "Feature",
  "properties": {
    "date:inception_lower": "2001-06-01",
    "date:inception_upper": "2001-06-01",
    "iso:country": "GB",
    "wof:name": "PR25 4QG",
    "wof:placetype": "postalcode"
  },
  "geometry": {"coordinates":[-2.684103,53.704596],"type":"Point"}
}
