{
  "type": "Feature",
  "properties": {
    "iso:country":"GB",
    "wof:name":"PR25 4QG",
    "wof:placetype":"postalcode"
},
  "geometry": {"coordinates":[-2.684102935776,53.70459585594804],"type":"Point"}
}