{
  "type": "Feature",
  "properties": {
    "iso:country": "GB",
    "wof:name": "NN11 3FF",
    "wof:placetype": "postalcode"
  },
  "geometry": {"coordinates":[-1.133851,52.213011],"type":"Point"}
}
