{
  "type": "Feature",
  "properties": {
    "iso:country":"GB",
    "wof:name":"TA4 4ER",
    "wof:placetype":"postalcode"
},
  "geometry": {"coordinates":[-3.26149603346189,51.14503626017252],"type":"Point"}
}