{
  "type": "Feature",
  "properties": {
    "iso:country":"GB",
    "wof:name":"S42 7EX",
    "wof:placetype":"postalcode"
},
  "geometry": {"coordinates":[-1.49751420689175,53.21813793102809],"type":"Point"}
}