{
  "type": "Feature",
  "properties": {
    "iso:country": "GB",
    "wof:name": "S42 7EX",
    "wof:placetype": "postalcode"
  },
  "geometry": {"coordinates":[-1.497513,53.218147],"type":"Point"}
}
