{
  "type": "Feature",
  "properties": {
    "iso:country":"GB",
    "wof:name":"B94 5ET",
    "wof:placetype":"postalcode"
},
  "geometry": {"coordinates":[-1.86881048777663,52.36023217243505],"type":"Point"}
}