{
  "type": "Feature",
  "properties": {
    "date:inception_lower": "1980-01-01",
    "date:inception_upper": "1980-01-01",
    "iso:country": "GB",
    "wof:name": "DA14 6PU",
    "wof:placetype": "postalcode"
  },
  "geometry": {"coordinates":[0.090249,51.426458],"type":"Point"}
}
