{
  "type": "Feature",
  "properties": {
    "iso:country":"GB",
    "wof:name":"DA14 6PU",
    "wof:placetype":"postalcode"
},
  "geometry": {"coordinates":[0.09024858312457,51.42645786580869],"type":"Point"}
}