{
  "type": "Feature",
  "properties": {
    "iso:country":"GB",
    "wof:name":"NR27 0BE",
    "wof:placetype":"postalcode"
},
  "geometry": {"coordinates":[1.30604629671716,52.92508373019911],"type":"Point"}
}