{
  "type": "Feature",
  "properties": {
    "iso:country":"GB",
    "wof:name":"DL3 6JR",
    "wof:placetype":"postalcode"
},
  "geometry": {"coordinates":[-1.55460685481929,54.52835489729099],"type":"Point"}
}