{
  "type": "Feature",
  "properties": {
    "iso:country":"GB",
    "wof:name":"CB1 2NE",
    "wof:placetype":"postalcode"
},
  "geometry": {"coordinates":[0.13550135797355,52.20517008291559],"type":"Point"}
}