{
  "type": "Feature",
  "properties": {
    "iso:country":"GB",
    "wof:name":"EX12 2UQ",
    "wof:placetype":"postalcode"
},
  "geometry": {"coordinates":[-3.07708857236952,50.71868554467633],"type":"Point"}
}