{
  "type": "Feature",
  "properties": {
    "date:inception_lower": "1988-03-01",
    "date:inception_upper": "1988-03-01",
    "iso:country": "GB",
    "wof:name": "EX12 2UQ",
    "wof:placetype": "postalcode"
  },
  "geometry": {"coordinates":[-3.077089,50.718686],"type":"Point"}
}
