{
  "type": "Feature",
  "properties": {
    "iso:country": "GB",
    "wof:name": "S33 9JN",
    "wof:placetype": "postalcode"
  },
  "geometry": {"coordinates":[-1.739346,53.326966],"type":"Point"}
}
