{
  "type": "Feature",
  "properties": {
    "iso:country":"GB",
    "wof:name":"S33 9JN",
    "wof:placetype":"postalcode"
},
  "geometry": {"coordinates":[-1.73934630882823,53.3269656954567],"type":"Point"}
}