{
  "type": "Feature",
  "properties": {
    "date:inception_lower":"1997-06-01",
    "date:inception_upper":"1997-06-30",
    "iso:country":"GB",
    "wof:name":"S33 9JN",
    "wof:placetype":"postalcode"
},
  "geometry": {"coordinates":[-1.739346,53.326966],"type":"Point"}
}