{
  "type": "Feature",
  "properties": {
    "date:inception_lower":"1980-01-01",
    "date:inception_upper":"1980-01-31",
    "iso:country":"GB",
    "wof:name":"OX17 2JZ",
    "wof:placetype":"postalcode"
},
  "geometry": {"coordinates":[-1.279674,52.091425],"type":"Point"}
}