{
  "type": "Feature",
  "properties": {
    "iso:country": "GB",
    "wof:name": "OX17 2JZ",
    "wof:placetype": "postalcode"
  },
  "geometry": {"coordinates":[-1.279674,52.091425],"type":"Point"}
}
