{
  "type": "Feature",
  "properties": {
    "iso:country": "GB",
    "wof:name": "NN5 5DQ",
    "wof:placetype": "postalcode"
  },
  "geometry": {"coordinates":[-0.909824,52.237789],"type":"Point"}
}
