{
  "type": "Feature",
  "properties": {
    "iso:country":"GB",
    "wof:name":"NN5 5DQ",
    "wof:placetype":"postalcode"
},
  "geometry": {"coordinates":[-0.90982379813103,52.23778883166779],"type":"Point"}
}