{
  "type": "Feature",
  "properties": {
    "date:inception_lower": "1980-06-01",
    "date:inception_upper": "1980-06-01",
    "iso:country": "GB",
    "wof:name": "KA3 3HT",
    "wof:placetype": "postalcode"
  },
  "geometry": {"coordinates":[-4.520082,55.683207],"type":"Point"}
}
