{
  "type": "Feature",
  "properties": {
    "iso:country":"GB",
    "wof:name":"KA3 3HT",
    "wof:placetype":"postalcode"
},
  "geometry": {"coordinates":[-4.52008210424049,55.68320736681716],"type":"Point"}
}