{
  "type": "Feature",
  "properties": {
    "iso:country":"GB",
    "wof:name":"SE14 5TL",
    "wof:placetype":"postalcode"
},
  "geometry": {"coordinates":[-0.04477570464804,51.46740295982474],"type":"Point"}
}