{
  "type": "Feature",
  "properties": {
    "iso:country": "GB",
    "wof:name": "SE14 5TL",
    "wof:placetype": "postalcode"
  },
  "geometry": {"coordinates":[-0.044776,51.467403],"type":"Point"}
}
