{
  "type": "Feature",
  "properties": {
    "iso:country":"GB",
    "wof:name":"DT3 4JD",
    "wof:placetype":"postalcode"
},
  "geometry": {"coordinates":[-2.54893977412818,50.64111955557726],"type":"Point"}
}