{
  "type": "Feature",
  "properties": {
    "iso:country":"GB",
    "wof:name":"SR2 8ED",
    "wof:placetype":"postalcode"
},
  "geometry": {"coordinates":[-1.37690105161454,54.90074544572521],"type":"Point"}
}