{
  "type": "Feature",
  "properties": {
    "iso:country":"GB",
    "wof:name":"GL55 6TY",
    "wof:placetype":"postalcode"
},
  "geometry": {"coordinates":[-1.7678033468263,52.09215524420489],"type":"Point"}
}