{
  "type": "Feature",
  "properties": {
    "iso:country": "GB",
    "wof:name": "GL55 6TY",
    "wof:placetype": "postalcode"
  },
  "geometry": {"coordinates":[-1.767803,52.092155],"type":"Point"}
}
