{
  "type": "Feature",
  "properties": {
    "date:inception_lower": "1992-08-01",
    "date:inception_upper": "1992-08-01",
    "iso:country": "GB",
    "wof:name": "GL55 6TY",
    "wof:placetype": "postalcode"
  },
  "geometry": {"coordinates":[-1.767803,52.092155],"type":"Point"}
}
