{
  "type": "Feature",
  "properties": {
    "date:inception_lower": "2019-02-01",
    "date:inception_upper": "2019-02-01",
    "iso:country": "GB",
    "wof:name": "BS29 6AH",
    "wof:placetype": "postalcode"
  },
  "geometry": {"coordinates":[-2.864573,51.327476],"type":"Point"}
}
