{
  "type": "Feature",
  "properties": {
    "iso:country":"GB",
    "wof:name":"WS14 0JZ",
    "wof:placetype":"postalcode"
},
  "geometry": {"coordinates":[-1.83727262493297,52.62693372654029],"type":"Point"}
}