{
  "type": "Feature",
  "properties": {
    "iso:country":"GB",
    "wof:name":"WA15 6LY",
    "wof:placetype":"postalcode"
},
  "geometry": {"coordinates":[-2.33048671154272,53.39374793733494],"type":"Point"}
}