{
  "type": "Feature",
  "properties": {
    "iso:country": "GB",
    "wof:name": "SN25 2FJ",
    "wof:placetype": "postalcode"
  },
  "geometry": {"coordinates":[-1.804088,51.60359],"type":"Point"}
}
