{
  "type": "Feature",
  "properties": {
    "iso:country":"GB",
    "wof:name":"AL7 4LB",
    "wof:placetype":"postalcode"
},
  "geometry": {"coordinates":[-0.19143100787521,51.78526942044832],"type":"Point"}
}