{
  "type": "Feature",
  "properties": {
    "iso:country": "GB",
    "wof:name": "AL7 4LB",
    "wof:placetype": "postalcode"
  },
  "geometry": {"coordinates":[-0.191431,51.785269],"type":"Point"}
}
