{
  "type": "Feature",
  "properties": {
    "iso:country": "GB",
    "wof:name": "CV31 2TF",
    "wof:placetype": "postalcode"
  },
  "geometry": {"coordinates":[-1.531302,52.270639],"type":"Point"}
}
