{
  "type": "Feature",
  "properties": {
    "iso:country":"GB",
    "wof:name":"LN4 2ND",
    "wof:placetype":"postalcode"
},
  "geometry": {"coordinates":[-0.53149868472717,53.19336750066993],"type":"Point"}
}