{
  "type": "Feature",
  "properties": {
    "date:inception_lower": "2016-11-01",
    "date:inception_upper": "2016-11-01",
    "iso:country": "GB",
    "wof:name": "KY12 0DY",
    "wof:placetype": "postalcode"
  },
  "geometry": {"coordinates":[-3.442668,56.082541],"type":"Point"}
}
