{
  "type": "Feature",
  "properties": {
    "iso:country":"GB",
    "wof:name":"SK8 1NE",
    "wof:placetype":"postalcode"
},
  "geometry": {"coordinates":[-2.21688249778794,53.39174345027648],"type":"Point"}
}