{
  "type": "Feature",
  "properties": {
    "iso:country": "GB",
    "wof:name": "YO41 5SJ",
    "wof:placetype": "postalcode"
  },
  "geometry": {"coordinates":[-0.832214,53.969294],"type":"Point"}
}
