{
  "type": "Feature",
  "properties": {
    "date:inception_lower":"2000-06-01",
    "date:inception_upper":"2000-06-30",
    "iso:country":"GB",
    "wof:name":"CA7 2DU",
    "wof:placetype":"postalcode"
},
  "geometry": {"coordinates":[-3.350341,54.719851],"type":"Point"}
}