{
  "type": "Feature",
  "properties": {
    "iso:country":"GB",
    "wof:name":"CA7 2DU",
    "wof:placetype":"postalcode"
},
  "geometry": {"coordinates":[-3.36015573076733,54.72784995307932],"type":"Point"}
}