{
  "type": "Feature",
  "properties": {
    "iso:country":"GB",
    "wof:name":"S73 9EB",
    "wof:placetype":"postalcode"
},
  "geometry": {"coordinates":[-1.38153461914037,53.53811329322465],"type":"Point"}
}