{
  "type": "Feature",
  "properties": {
    "date:inception_lower": "1980-01-01",
    "date:inception_upper": "1980-01-01",
    "iso:country": "GB",
    "wof:name": "CF47 8TD",
    "wof:placetype": "postalcode"
  },
  "geometry": {"coordinates":[-3.385282,51.752897],"type":"Point"}
}
