{
  "type": "Feature",
  "properties": {
    "iso:country":"GB",
    "wof:name":"CF47 8TD",
    "wof:placetype":"postalcode"
},
  "geometry": {"coordinates":[-3.38528194519753,51.7528968722367],"type":"Point"}
}