{
  "type": "Feature",
  "properties": {
    "date:inception_lower":"1980-01-01",
    "date:inception_upper":"1980-01-31",
    "iso:country":"GB",
    "wof:name":"BS5 8EA",
    "wof:placetype":"postalcode"
},
  "geometry": {"coordinates":[-2.548087,51.458708],"type":"Point"}
}