{
  "type": "Feature",
  "properties": {
    "iso:country": "GB",
    "wof:name": "NN16 0RS",
    "wof:placetype": "postalcode"
  },
  "geometry": {"coordinates":[-0.717163,52.399539],"type":"Point"}
}
