{
  "type": "Feature",
  "properties": {
    "date:inception_lower": "1980-01-01",
    "date:inception_upper": "1980-01-01",
    "iso:country": "GB",
    "wof:name": "NN16 0RS",
    "wof:placetype": "postalcode"
  },
  "geometry": {"coordinates":[-0.717163,52.399539],"type":"Point"}
}
