{
  "type": "Feature",
  "properties": {
    "iso:country":"GB",
    "wof:name":"DA1 5JJ",
    "wof:placetype":"postalcode"
},
  "geometry": {"coordinates":[0.22267964800205,51.45461529387613],"type":"Point"}
}