{
  "type": "Feature",
  "properties": {
    "date:inception_lower": "1980-01-01",
    "date:inception_upper": "1980-01-01",
    "iso:country": "GB",
    "wof:name": "DA1 5JJ",
    "wof:placetype": "postalcode"
  },
  "geometry": {"coordinates":[0.22268,51.454615],"type":"Point"}
}
