{
  "type": "Feature",
  "properties": {
    "date:inception_lower":"1996-06-01",
    "date:inception_upper":"1996-06-30",
    "iso:country":"GB",
    "wof:name":"NN16 9FP",
    "wof:placetype":"postalcode"
},
  "geometry": {"coordinates":[-0.732437,52.415329],"type":"Point"}
}