{
  "type": "Feature",
  "properties": {
    "date:inception_lower": "2023-09-01",
    "date:inception_upper": "2023-09-01",
    "iso:country": "GB",
    "wof:name": "LL77 7BB",
    "wof:placetype": "postalcode"
  },
  "geometry": {"coordinates":[-4.300828,53.249499],"type":"Point"}
}
