{
  "type": "Feature",
  "properties": {
    "iso:country":"GB",
    "wof:name":"LE3 2AS",
    "wof:placetype":"postalcode"
},
  "geometry": {"coordinates":[-1.15392274924355,52.62233583126101],"type":"Point"}
}