{
  "type": "Feature",
  "properties": {
    "iso:country":"GB",
    "wof:name":"SO16 3LN",
    "wof:placetype":"postalcode"
},
  "geometry": {"coordinates":[-1.38351074751981,50.94007833657427],"type":"Point"}
}