{
  "type": "Feature",
  "properties": {
    "iso:country":"GB",
    "wof:name":"W10 6BQ",
    "wof:placetype":"postalcode"
},
  "geometry": {"coordinates":[-0.2144252930254,51.5230029325276],"type":"Point"}
}