{
  "type": "Feature",
  "properties": {
    "iso:country":"GB",
    "wof:name":"G5 0LX",
    "wof:placetype":"postalcode"
},
  "geometry": {"coordinates":[-4.23780602683685,55.84075806390901],"type":"Point"}
}