{
  "type": "Feature",
  "properties": {
    "iso:country": "GB",
    "wof:name": "W1J 7EG",
    "wof:placetype": "postalcode"
  },
  "geometry": {"coordinates":[-0.145744,51.506884],"type":"Point"}
}
