{
  "type": "Feature",
  "properties": {
    "date:inception_lower": "1990-02-01",
    "date:inception_upper": "1990-02-01",
    "iso:country": "GB",
    "wof:name": "NR34 7BX",
    "wof:placetype": "postalcode"
  },
  "geometry": {"coordinates":[1.582543,52.446793],"type":"Point"}
}
