{
  "type": "Feature",
  "properties": {
    "iso:country":"GB",
    "wof:name":"NR34 7BX",
    "wof:placetype":"postalcode"
},
  "geometry": {"coordinates":[1.58254326658247,52.44679266265059],"type":"Point"}
}