{
  "type": "Feature",
  "properties": {
    "iso:country": "GB",
    "wof:name": "ML5 4TS",
    "wof:placetype": "postalcode"
  },
  "geometry": {"coordinates":[-4.002281,55.850004],"type":"Point"}
}
