{
  "type": "Feature",
  "properties": {
    "iso:country":"GB",
    "wof:name":"RG4 6TS",
    "wof:placetype":"postalcode"
},
  "geometry": {"coordinates":[-0.91775782618052,51.47701871521587],"type":"Point"}
}