{
  "type": "Feature",
  "properties": {
    "iso:country": "GB",
    "wof:name": "RG4 6TS",
    "wof:placetype": "postalcode"
  },
  "geometry": {"coordinates":[-0.917758,51.477019],"type":"Point"}
}
