{
  "type": "Feature",
  "properties": {
    "iso:country":"GB",
    "wof:name":"WA4 4NN",
    "wof:placetype":"postalcode"
},
  "geometry": {"coordinates":[-2.56891100014013,53.33299343504335],"type":"Point"}
}