{
  "type": "Feature",
  "properties": {
    "date:inception_lower": "2017-05-01",
    "date:inception_upper": "2017-05-01",
    "iso:country": "GB",
    "wof:name": "N10 3EW",
    "wof:placetype": "postalcode"
  },
  "geometry": {"coordinates":[-0.149246,51.587614],"type":"Point"}
}
