{
  "type": "Feature",
  "properties": {
    "iso:country": "GB",
    "wof:name": "BA12 8LG",
    "wof:placetype": "postalcode"
  },
  "geometry": {"coordinates":[-2.187061,51.201265],"type":"Point"}
}
