{
  "type": "Feature",
  "properties": {
    "iso:country":"GB",
    "wof:name":"SN5 6DD",
    "wof:placetype":"postalcode"
},
  "geometry": {"coordinates":[-1.83947065405732,51.55639451776698],"type":"Point"}
}