{
  "type": "Feature",
  "properties": {
    "iso:country":"GB",
    "wof:name":"HA8 0LL",
    "wof:placetype":"postalcode"
},
  "geometry": {"coordinates":[-0.26688281048839,51.60075478156426],"type":"Point"}
}