{
  "type": "Feature",
  "properties": {
    "date:inception_lower":"1984-03-01",
    "date:inception_upper":"1984-03-31",
    "iso:country":"GB",
    "wof:name":"EH6 5JP",
    "wof:placetype":"postalcode"
},
  "geometry": {"coordinates":[-3.179539,55.971057],"type":"Point"}
}