{
  "type": "Feature",
  "properties": {
    "iso:country":"GB",
    "wof:name":"NR3 2RE",
    "wof:placetype":"postalcode"
},
  "geometry": {"coordinates":[1.28232922568835,52.64786229800466],"type":"Point"}
}