{
  "type": "Feature",
  "properties": {
    "iso:country":"GB",
    "wof:name":"TW1 1QF",
    "wof:placetype":"postalcode"
},
  "geometry": {"coordinates":[-0.32285093518005,51.46303271451368],"type":"Point"}
}