{
  "type": "Feature",
  "properties": {
    "date:inception_lower": "1980-01-01",
    "date:inception_upper": "1980-01-01",
    "iso:country": "GB",
    "wof:name": "DL13 3AJ",
    "wof:placetype": "postalcode"
  },
  "geometry": {"coordinates":[-1.884949,54.730907],"type":"Point"}
}
