{
  "type": "Feature",
  "properties": {
    "iso:country":"GB",
    "wof:name":"BS39 6UA",
    "wof:placetype":"postalcode"
},
  "geometry": {"coordinates":[-2.53088763961205,51.29857197716145],"type":"Point"}
}