{
  "type": "Feature",
  "properties": {
    "iso:country": "GB",
    "wof:name": "BS39 6UA",
    "wof:placetype": "postalcode"
  },
  "geometry": {"coordinates":[-2.530888,51.298572],"type":"Point"}
}
