{
  "type": "Feature",
  "properties": {
    "date:inception_lower": "1980-01-01",
    "date:inception_upper": "1980-01-01",
    "iso:country": "GB",
    "wof:name": "NE42 5NN",
    "wof:placetype": "postalcode"
  },
  "geometry": {"coordinates":[-1.829452,54.95224],"type":"Point"}
}
