{
  "type": "Feature",
  "properties": {
    "iso:country":"GB",
    "wof:name":"NE42 5NN",
    "wof:placetype":"postalcode"
},
  "geometry": {"coordinates":[-1.82945234837214,54.95223987732367],"type":"Point"}
}