{
  "type": "Feature",
  "properties": {
    "iso:country": "GB",
    "wof:name": "OL11 1LQ",
    "wof:placetype": "postalcode"
  },
  "geometry": {"coordinates":[-2.158668,53.60396],"type":"Point"}
}
