{
  "type": "Feature",
  "properties": {
    "iso:country":"GB",
    "wof:name":"OL11 1LQ",
    "wof:placetype":"postalcode"
},
  "geometry": {"coordinates":[-2.15941045381029,53.60409564373379],"type":"Point"}
}