{
  "type": "Feature",
  "properties": {
    "date:inception_lower":"2008-04-01",
    "date:inception_upper":"2008-04-30",
    "iso:country":"GB",
    "wof:name":"OL11 1LQ",
    "wof:placetype":"postalcode"
},
  "geometry": {"coordinates":[-2.158668,53.60396],"type":"Point"}
}