{
  "type": "Feature",
  "properties": {
    "iso:country": "GB",
    "wof:name": "G69 7QH",
    "wof:placetype": "postalcode"
  },
  "geometry": {"coordinates":[-4.080357,55.854576],"type":"Point"}
}
