{
  "type": "Feature",
  "properties": {
    "iso:country": "GB",
    "wof:name": "LL20 7YD",
    "wof:placetype": "postalcode"
  },
  "geometry": {"coordinates":[-3.111362,52.980686],"type":"Point"}
}
