{
  "type": "Feature",
  "properties": {
    "iso:country":"GB",
    "wof:name":"PA5 8DY",
    "wof:placetype":"postalcode"
},
  "geometry": {"coordinates":[-4.51582817303663,55.83503359618269],"type":"Point"}
}