{
  "type": "Feature",
  "properties": {
    "iso:country": "GB",
    "wof:name": "PA5 8DY",
    "wof:placetype": "postalcode"
  },
  "geometry": {"coordinates":[-4.515828,55.835034],"type":"Point"}
}
