{
  "type": "Feature",
  "properties": {
    "iso:country":"GB",
    "wof:name":"NW5 3QL",
    "wof:placetype":"postalcode"
},
  "geometry": {"coordinates":[-0.15269062878015,51.54602984256719],"type":"Point"}
}