{
  "type": "Feature",
  "properties": {
    "iso:country": "GB",
    "wof:name": "NW5 3QL",
    "wof:placetype": "postalcode"
  },
  "geometry": {"coordinates":[-0.152691,51.54603],"type":"Point"}
}
