{
  "type": "Feature",
  "properties": {
    "iso:country":"GB",
    "wof:name":"M14 6QL",
    "wof:placetype":"postalcode"
},
  "geometry": {"coordinates":[-2.2102345911243,53.44016768637479],"type":"Point"}
}