{
  "type": "Feature",
  "properties": {
    "iso:country": "GB",
    "wof:name": "TS19 7PJ",
    "wof:placetype": "postalcode"
  },
  "geometry": {"coordinates":[-1.35944,54.567552],"type":"Point"}
}
