{
  "type": "Feature",
  "properties": {
    "iso:country":"GB",
    "wof:name":"CT5 2QH",
    "wof:placetype":"postalcode"
},
  "geometry": {"coordinates":[1.06161418340309,51.36496586091409],"type":"Point"}
}