{
  "type": "Feature",
  "properties": {
    "iso:country":"GB",
    "wof:name":"MK6 2LP",
    "wof:placetype":"postalcode"
},
  "geometry": {"coordinates":[-0.74123913700946,52.03910960554814],"type":"Point"}
}