{
  "type": "Feature",
  "properties": {
    "iso:country": "GB",
    "wof:name": "MK6 2LP",
    "wof:placetype": "postalcode"
  },
  "geometry": {"coordinates":[-0.741239,52.03911],"type":"Point"}
}
