{
  "type": "Feature",
  "properties": {
    "iso:country":"GB",
    "wof:name":"EH49 7SW",
    "wof:placetype":"postalcode"
},
  "geometry": {"coordinates":[-3.59383310927147,55.9776272313515],"type":"Point"}
}