{
  "type": "Feature",
  "properties": {
    "iso:country": "GB",
    "wof:name": "EH49 7SW",
    "wof:placetype": "postalcode"
  },
  "geometry": {"coordinates":[-3.593833,55.977627],"type":"Point"}
}
