{
  "type": "Feature",
  "properties": {
    "date:inception_lower":"1985-01-01",
    "date:inception_upper":"1985-01-31",
    "iso:country":"GB",
    "wof:name":"EH49 7SW",
    "wof:placetype":"postalcode"
},
  "geometry": {"coordinates":[-3.593833,55.977627],"type":"Point"}
}