{
  "type": "Feature",
  "properties": {
    "iso:country":"GB",
    "wof:name":"BL3 6YA",
    "wof:placetype":"postalcode"
},
  "geometry": {"coordinates":[-2.43126678282918,53.5672730070801],"type":"Point"}
}