{
  "type": "Feature",
  "properties": {
    "date:inception_lower": "1980-01-01",
    "date:inception_upper": "1980-01-01",
    "iso:country": "GB",
    "wof:name": "NR19 1NA",
    "wof:placetype": "postalcode"
  },
  "geometry": {"coordinates":[0.94245,52.661437],"type":"Point"}
}
