{
  "type": "Feature",
  "properties": {
    "iso:country": "GB",
    "wof:name": "DL13 4LH",
    "wof:placetype": "postalcode"
  },
  "geometry": {"coordinates":[-1.812087,54.740413],"type":"Point"}
}
