{
  "type": "Feature",
  "properties": {
    "date:inception_lower":"1980-01-01",
    "date:inception_upper":"1980-01-31",
    "iso:country":"GB",
    "wof:name":"CV22 6RA",
    "wof:placetype":"postalcode"
},
  "geometry": {"coordinates":[-1.292583,52.338006],"type":"Point"}
}