{
  "type": "Feature",
  "properties": {
    "iso:country":"GB",
    "wof:name":"TS16 0GG",
    "wof:placetype":"postalcode"
},
  "geometry": {"coordinates":[-1.35667950535149,54.5139929786269],"type":"Point"}
}