{
  "type": "Feature",
  "properties": {
    "date:inception_lower":"2002-06-01",
    "date:inception_upper":"2002-06-30",
    "iso:country":"GB",
    "wof:name":"TS16 0GG",
    "wof:placetype":"postalcode"
},
  "geometry": {"coordinates":[-1.356679,54.513993],"type":"Point"}
}