{
  "type": "Feature",
  "properties": {
    "iso:country":"GB",
    "wof:name":"SW3 2AP",
    "wof:placetype":"postalcode"
},
  "geometry": {"coordinates":[-0.16950820173023,51.4938763687795],"type":"Point"}
}