{
  "type": "Feature",
  "properties": {
    "iso:country":"GB",
    "wof:name":"E2 8ES",
    "wof:placetype":"postalcode"
},
  "geometry": {"coordinates":[-0.07394995553519,51.5322279393835],"type":"Point"}
}