{
  "type": "Feature",
  "properties": {
    "date:inception_lower": "1994-05-01",
    "date:inception_upper": "1994-05-01",
    "iso:country": "GB",
    "wof:name": "E2 8ES",
    "wof:placetype": "postalcode"
  },
  "geometry": {"coordinates":[-0.07395,51.532228],"type":"Point"}
}
