{
  "type": "Feature",
  "properties": {
    "iso:country":"GB",
    "wof:name":"WV14 8LR",
    "wof:placetype":"postalcode"
},
  "geometry": {"coordinates":[-2.05173056507326,52.55864839898432],"type":"Point"}
}