{
  "type": "Feature",
  "properties": {
    "date:inception_lower": "2020-10-01",
    "date:inception_upper": "2020-10-01",
    "iso:country": "GB",
    "wof:name": "LS23 7GD",
    "wof:placetype": "postalcode"
  },
  "geometry": {"coordinates":[-1.328551,53.919522],"type":"Point"}
}
