{
  "type": "Feature",
  "properties": {
    "iso:country":"GB",
    "wof:name":"N20 0PL",
    "wof:placetype":"postalcode"
},
  "geometry": {"coordinates":[-0.17843293132306,51.62655429358975],"type":"Point"}
}