{
  "type": "Feature",
  "properties": {
    "iso:country": "GB",
    "wof:name": "NN3 3JA",
    "wof:placetype": "postalcode"
  },
  "geometry": {"coordinates":[-0.850473,52.251251],"type":"Point"}
}
