{
  "type": "Feature",
  "properties": {
    "iso:country":"GB",
    "wof:name":"SP2 9LT",
    "wof:placetype":"postalcode"
},
  "geometry": {"coordinates":[-1.81840419285569,51.08149138128428],"type":"Point"}
}