{
  "type": "Feature",
  "properties": {
    "iso:country":"GB",
    "wof:name":"WR4 9FP",
    "wof:placetype":"postalcode"
},
  "geometry": {"coordinates":[-2.16136881161428,52.2122144265144],"type":"Point"}
}