{
  "type": "Feature",
  "properties": {
    "iso:country": "GB",
    "wof:name": "DN37 7AL",
    "wof:placetype": "postalcode"
  },
  "geometry": {"coordinates":[-0.16934,53.548732],"type":"Point"}
}
