{
  "type": "Feature",
  "properties": {
    "date:inception_lower": "1980-01-01",
    "date:inception_upper": "1980-01-01",
    "iso:country": "GB",
    "wof:name": "BS14 0JP",
    "wof:placetype": "postalcode"
  },
  "geometry": {"coordinates":[-2.56584,51.406786],"type":"Point"}
}
