{
  "type": "Feature",
  "properties": {
    "iso:country": "GB",
    "wof:name": "BS14 0JP",
    "wof:placetype": "postalcode"
  },
  "geometry": {"coordinates":[-2.56584,51.406786],"type":"Point"}
}
