{
  "type": "Feature",
  "properties": {
    "iso:country":"GB",
    "wof:name":"BS14 0JP",
    "wof:placetype":"postalcode"
},
  "geometry": {"coordinates":[-2.56584006423476,51.40678624469619],"type":"Point"}
}