{
  "type": "Feature",
  "properties": {
    "date:inception_lower": "1980-01-01",
    "date:inception_upper": "1980-01-01",
    "iso:country": "GB",
    "wof:name": "LS16 7PE",
    "wof:placetype": "postalcode"
  },
  "geometry": {"coordinates":[-1.593867,53.859001],"type":"Point"}
}
