{
  "type": "Feature",
  "properties": {
    "iso:country":"GB",
    "wof:name":"LS16 7PE",
    "wof:placetype":"postalcode"
},
  "geometry": {"coordinates":[-1.59386742530754,53.85900133412079],"type":"Point"}
}