{
  "type": "Feature",
  "properties": {
    "date:inception_lower": "2000-06-01",
    "date:inception_upper": "2000-06-01",
    "iso:country": "GB",
    "wof:name": "SO53 3QB",
    "wof:placetype": "postalcode"
  },
  "geometry": {"coordinates":[-1.392121,50.966598],"type":"Point"}
}
