{
  "type": "Feature",
  "properties": {
    "iso:country":"GB",
    "wof:name":"SO53 3QB",
    "wof:placetype":"postalcode"
},
  "geometry": {"coordinates":[-1.39215972889078,50.96662429455616],"type":"Point"}
}