{
  "type": "Feature",
  "properties": {
    "iso:country": "GB",
    "wof:name": "SO53 3QB",
    "wof:placetype": "postalcode"
  },
  "geometry": {"coordinates":[-1.39215,50.966616],"type":"Point"}
}
