{
  "type": "Feature",
  "properties": {
    "iso:country":"GB",
    "wof:name":"LS27 7UQ",
    "wof:placetype":"postalcode"
},
  "geometry": {"coordinates":[-1.59813566638871,53.75932973189089],"type":"Point"}
}