{
  "type": "Feature",
  "properties": {
    "iso:country":"GB",
    "wof:name":"BR6 7SY",
    "wof:placetype":"postalcode"
},
  "geometry": {"coordinates":[0.11242976788637,51.34093250344706],"type":"Point"}
}