{
  "type": "Feature",
  "properties": {
    "date:inception_lower":"1980-01-01",
    "date:inception_upper":"1980-01-31",
    "iso:country":"GB",
    "wof:name":"BR6 7SY",
    "wof:placetype":"postalcode"
},
  "geometry": {"coordinates":[0.11243,51.340932],"type":"Point"}
}