{
  "type": "Feature",
  "properties": {
    "iso:country": "GB",
    "wof:name": "CV37 8XQ",
    "wof:placetype": "postalcode"
  },
  "geometry": {"coordinates":[-1.812212,52.119488],"type":"Point"}
}
