{
  "type": "Feature",
  "properties": {
    "date:inception_lower": "1980-01-01",
    "date:inception_upper": "1980-01-01",
    "iso:country": "GB",
    "wof:name": "CV37 8XQ",
    "wof:placetype": "postalcode"
  },
  "geometry": {"coordinates":[-1.812212,52.119488],"type":"Point"}
}
