{
  "type": "Feature",
  "properties": {
    "iso:country":"GB",
    "wof:name":"SO32 1EL",
    "wof:placetype":"postalcode"
},
  "geometry": {"coordinates":[-1.20567906331642,50.95479539604676],"type":"Point"}
}