{
  "type": "Feature",
  "properties": {
    "iso:country":"GB",
    "wof:name":"AB42 3LJ",
    "wof:placetype":"postalcode"
},
  "geometry": {"coordinates":[-1.85922068702252,57.50167116198681],"type":"Point"}
}