{
  "type": "Feature",
  "properties": {
    "iso:country":"GB",
    "wof:name":"PL1 3JL",
    "wof:placetype":"postalcode"
},
  "geometry": {"coordinates":[-4.15613833458359,50.37203003520404],"type":"Point"}
}