{
  "type": "Feature",
  "properties": {
    "date:inception_lower": "1996-06-01",
    "date:inception_upper": "1996-06-01",
    "iso:country": "GB",
    "wof:name": "PL1 3JL",
    "wof:placetype": "postalcode"
  },
  "geometry": {"coordinates":[-4.156138,50.37203],"type":"Point"}
}
