{
  "type": "Feature",
  "properties": {
    "iso:country": "GB",
    "wof:name": "WR3 7WJ",
    "wof:placetype": "postalcode"
  },
  "geometry": {"coordinates":[-2.229065,52.228667],"type":"Point"}
}
