{
  "type": "Feature",
  "properties": {
    "date:inception_lower":"2018-09-01",
    "date:inception_upper":"2018-09-30",
    "iso:country":"GB",
    "wof:name":"WR3 7WJ",
    "wof:placetype":"postalcode"
},
  "geometry": {"coordinates":[-2.229065,52.228667],"type":"Point"}
}