{
  "type": "Feature",
  "properties": {
    "date:inception_lower": "2018-09-01",
    "date:inception_upper": "2018-09-01",
    "iso:country": "GB",
    "wof:name": "WR3 7WJ",
    "wof:placetype": "postalcode"
  },
  "geometry": {"coordinates":[-2.229094,52.228712],"type":"Point"}
}
