{
  "type": "Feature",
  "properties": {
    "date:inception_lower": "2002-06-01",
    "date:inception_upper": "2002-06-01",
    "iso:country": "GB",
    "wof:name": "L21 9QB",
    "wof:placetype": "postalcode"
  },
  "geometry": {"coordinates":[-3.007805,53.47761],"type":"Point"}
}
