{
  "type": "Feature",
  "properties": {
    "iso:country": "GB",
    "wof:name": "CM8 1SD",
    "wof:placetype": "postalcode"
  },
  "geometry": {"coordinates":[0.593053,51.834242],"type":"Point"}
}
