{
  "type": "Feature",
  "properties": {
    "iso:country":"GB",
    "wof:name":"CM8 1SD",
    "wof:placetype":"postalcode"
},
  "geometry": {"coordinates":[0.59302501956499,51.8342333867847],"type":"Point"}
}