{
  "type": "Feature",
  "properties": {
    "iso:country": "GB",
    "wof:name": "SM3 9BB",
    "wof:placetype": "postalcode"
  },
  "geometry": {"coordinates":[-0.218982,51.378832],"type":"Point"}
}
