{
  "type": "Feature",
  "properties": {
    "iso:country":"GB",
    "wof:name":"BR1 4JE",
    "wof:placetype":"postalcode"
},
  "geometry": {"coordinates":[0.00166675247325,51.41595393550437],"type":"Point"}
}