{
  "type": "Feature",
  "properties": {
    "iso:country":"GB",
    "wof:name":"TF11 9HN",
    "wof:placetype":"postalcode"
},
  "geometry": {"coordinates":[-2.34584285991967,52.6452293072032],"type":"Point"}
}