{
  "type": "Feature",
  "properties": {
    "iso:country":"GB",
    "wof:name":"ME15 9JD",
    "wof:placetype":"postalcode"
},
  "geometry": {"coordinates":[0.55715589221347,51.23982507242202],"type":"Point"}
}