{
  "type": "Feature",
  "properties": {
    "date:inception_lower":"1980-01-01",
    "date:inception_upper":"1980-01-31",
    "iso:country":"GB",
    "wof:name":"B23 6LH",
    "wof:placetype":"postalcode"
},
  "geometry": {"coordinates":[-1.848363,52.529777],"type":"Point"}
}