{
  "type": "Feature",
  "properties": {
    "iso:country":"GB",
    "wof:name":"AL2 1LX",
    "wof:placetype":"postalcode"
},
  "geometry": {"coordinates":[-0.30431177607824,51.72580628153009],"type":"Point"}
}