{
  "type": "Feature",
  "properties": {
    "iso:country": "GB",
    "wof:name": "AL2 1LX",
    "wof:placetype": "postalcode"
  },
  "geometry": {"coordinates":[-0.304312,51.725806],"type":"Point"}
}
