{
  "type": "Feature",
  "properties": {
    "iso:country":"GB",
    "wof:name":"UB5 6FX",
    "wof:placetype":"postalcode"
},
  "geometry": {"coordinates":[-0.37936496944091,51.53098175783046],"type":"Point"}
}