{
  "type": "Feature",
  "properties": {
    "iso:country": "GB",
    "wof:name": "G81 6PX",
    "wof:placetype": "postalcode"
  },
  "geometry": {"coordinates":[-4.405599,55.9286],"type":"Point"}
}
