{
  "type": "Feature",
  "properties": {
    "iso:country":"GB",
    "wof:name":"G81 6PX",
    "wof:placetype":"postalcode"
},
  "geometry": {"coordinates":[-4.40559856351693,55.92860042360689],"type":"Point"}
}