{
  "type": "Feature",
  "properties": {
    "date:inception_lower": "2018-01-01",
    "date:inception_upper": "2018-01-01",
    "iso:country": "GB",
    "wof:name": "CV33 9PN",
    "wof:placetype": "postalcode"
  },
  "geometry": {"coordinates":[-1.461113,52.232527],"type":"Point"}
}
