{
  "type": "Feature",
  "properties": {
    "iso:country":"GB",
    "wof:name":"PE26 1JF",
    "wof:placetype":"postalcode"
},
  "geometry": {"coordinates":[-0.10972240544487,52.45075543600792],"type":"Point"}
}