{
  "type": "Feature",
  "properties": {
    "iso:country":"GB",
    "wof:name":"TQ5 9LG",
    "wof:placetype":"postalcode"
},
  "geometry": {"coordinates":[-3.52179709172459,50.3871629699446],"type":"Point"}
}