{
  "type": "Feature",
  "properties": {
    "iso:country":"GB",
    "wof:name":"WS12 1JG",
    "wof:placetype":"postalcode"
},
  "geometry": {"coordinates":[-1.9724122854593,52.70947723823666],"type":"Point"}
}