{
  "type": "Feature",
  "properties": {
    "date:inception_lower": "1987-10-01",
    "date:inception_upper": "1987-10-01",
    "iso:country": "GB",
    "wof:name": "LN10 6TA",
    "wof:placetype": "postalcode"
  },
  "geometry": {"coordinates":[-0.219485,53.148107],"type":"Point"}
}
