{
  "type": "Feature",
  "properties": {
    "date:inception_lower":"1980-01-01",
    "date:inception_upper":"1980-01-31",
    "iso:country":"GB",
    "wof:name":"CT4 6PN",
    "wof:placetype":"postalcode"
},
  "geometry": {"coordinates":[1.156246,51.207563],"type":"Point"}
}