{
  "type": "Feature",
  "properties": {
    "iso:country":"GB",
    "wof:name":"LU2 7EX",
    "wof:placetype":"postalcode"
},
  "geometry": {"coordinates":[-0.41235411400069,51.90500240323776],"type":"Point"}
}