{
  "type": "Feature",
  "properties": {
    "iso:country": "GB",
    "wof:name": "LU2 7EX",
    "wof:placetype": "postalcode"
  },
  "geometry": {"coordinates":[-0.412354,51.905002],"type":"Point"}
}
