{
  "type": "Feature",
  "properties": {
    "iso:country":"GB",
    "wof:name":"TA10 0LJ",
    "wof:placetype":"postalcode"
},
  "geometry": {"coordinates":[-2.85015255896736,51.01771452424855],"type":"Point"}
}