{
  "type": "Feature",
  "properties": {
    "date:inception_lower": "1980-01-01",
    "date:inception_upper": "1980-01-01",
    "iso:country": "GB",
    "wof:name": "TA10 0LJ",
    "wof:placetype": "postalcode"
  },
  "geometry": {"coordinates":[-2.850153,51.017715],"type":"Point"}
}
