{
  "type": "Feature",
  "properties": {
    "iso:country":"GB",
    "wof:name":"BS21 6JR",
    "wof:placetype":"postalcode"
},
  "geometry": {"coordinates":[-2.84764539897768,51.4301015361846],"type":"Point"}
}