{
  "type": "Feature",
  "properties": {
    "date:inception_lower": "2000-12-01",
    "date:inception_upper": "2000-12-01",
    "iso:country": "GB",
    "wof:name": "MK19 6GH",
    "wof:placetype": "postalcode"
  },
  "geometry": {"coordinates":[-0.886843,52.053891],"type":"Point"}
}
