{
  "type": "Feature",
  "properties": {
    "iso:country":"GB",
    "wof:name":"CH65 8AF",
    "wof:placetype":"postalcode"
},
  "geometry": {"coordinates":[-2.92159604263317,53.28243787751106],"type":"Point"}
}