{
  "type": "Feature",
  "properties": {
    "iso:country": "GB",
    "wof:name": "LS26 0FH",
    "wof:placetype": "postalcode"
  },
  "geometry": {"coordinates":[-1.469458,53.746982],"type":"Point"}
}
