{
  "type": "Feature",
  "properties": {
    "iso:country":"GB",
    "wof:name":"SS1 3LU",
    "wof:placetype":"postalcode"
},
  "geometry": {"coordinates":[0.76273846934835,51.53734705824311],"type":"Point"}
}