{
  "type": "Feature",
  "properties": {
    "date:inception_lower": "1984-09-01",
    "date:inception_upper": "1984-09-01",
    "iso:country": "GB",
    "wof:name": "KY7 6YH",
    "wof:placetype": "postalcode"
  },
  "geometry": {"coordinates":[-3.160021,56.209935],"type":"Point"}
}
