{
  "type": "Feature",
  "properties": {
    "iso:country": "GB",
    "wof:name": "GL14 2HE",
    "wof:placetype": "postalcode"
  },
  "geometry": {"coordinates":[-2.50144,51.821564],"type":"Point"}
}
