{
  "type": "Feature",
  "properties": {
    "iso:country":"GB",
    "wof:name":"ST5 0QR",
    "wof:placetype":"postalcode"
},
  "geometry": {"coordinates":[-2.22234422401788,53.01678952093663],"type":"Point"}
}