{
  "type": "Feature",
  "properties": {
    "date:inception_lower":"1980-01-01",
    "date:inception_upper":"1980-01-31",
    "iso:country":"GB",
    "wof:name":"ST5 0QR",
    "wof:placetype":"postalcode"
},
  "geometry": {"coordinates":[-2.222344,53.01679],"type":"Point"}
}