{
  "type": "Feature",
  "properties": {
    "date:inception_lower": "2022-08-01",
    "date:inception_upper": "2022-08-01",
    "iso:country": "GB",
    "wof:name": "S66 1DA",
    "wof:placetype": "postalcode"
  },
  "geometry": {"coordinates":[-1.27533,53.413008],"type":"Point"}
}
