{
  "type": "Feature",
  "properties": {
    "iso:country":"GB",
    "wof:name":"SE16 6SH",
    "wof:placetype":"postalcode"
},
  "geometry": {"coordinates":[-0.04507420879477,51.500159201454],"type":"Point"}
}