{
  "type": "Feature",
  "properties": {
    "iso:country":"GB",
    "wof:name":"TF1 5BT",
    "wof:placetype":"postalcode"
},
  "geometry": {"coordinates":[-2.48783193191625,52.69841632571259],"type":"Point"}
}