{
  "type": "Feature",
  "properties": {
    "iso:country":"GB",
    "wof:name":"PE7 1HA",
    "wof:placetype":"postalcode"
},
  "geometry": {"coordinates":[-0.13065000668266,52.55734558114244],"type":"Point"}
}