{
  "type": "Feature",
  "properties": {
    "iso:country": "GB",
    "wof:name": "PE7 1HA",
    "wof:placetype": "postalcode"
  },
  "geometry": {"coordinates":[-0.13065,52.557346],"type":"Point"}
}
