{
  "type": "Feature",
  "properties": {
    "iso:country": "GB",
    "wof:name": "CO10 1NT",
    "wof:placetype": "postalcode"
  },
  "geometry": {"coordinates":[0.729161,52.0485],"type":"Point"}
}
