{
  "type": "Feature",
  "properties": {
    "iso:country":"GB",
    "wof:name":"EX12 2NF",
    "wof:placetype":"postalcode"
},
  "geometry": {"coordinates":[-3.06375097970542,50.70396060598925],"type":"Point"}
}