{
  "type": "Feature",
  "properties": {
    "iso:country": "GB",
    "wof:name": "BL8 2LX",
    "wof:placetype": "postalcode"
  },
  "geometry": {"coordinates":[-2.327884,53.590863],"type":"Point"}
}
