{
  "type": "Feature",
  "properties": {
    "iso:country": "GB",
    "wof:name": "EX4 4HA",
    "wof:placetype": "postalcode"
  },
  "geometry": {"coordinates":[-3.527549,50.72814],"type":"Point"}
}
