{
  "type": "Feature",
  "properties": {
    "date:inception_lower": "1994-12-01",
    "date:inception_upper": "1994-12-01",
    "iso:country": "GB",
    "wof:name": "WS10 7DD",
    "wof:placetype": "postalcode"
  },
  "geometry": {"coordinates":[-2.035647,52.55157],"type":"Point"}
}
