{
  "type": "Feature",
  "properties": {
    "iso:country":"GB",
    "wof:name":"WS10 7DD",
    "wof:placetype":"postalcode"
},
  "geometry": {"coordinates":[-2.03564683277432,52.55157037275673],"type":"Point"}
}