{
  "type": "Feature",
  "properties": {
    "iso:country": "GB",
    "wof:name": "CM7 4FG",
    "wof:placetype": "postalcode"
  },
  "geometry": {"coordinates":[0.526486,51.943607],"type":"Point"}
}
