{
  "type": "Feature",
  "properties": {
    "iso:country":"GB",
    "wof:name":"LE18 4PD",
    "wof:placetype":"postalcode"
},
  "geometry": {"coordinates":[-1.1323495900556,52.57927037170806],"type":"Point"}
}