{
  "type": "Feature",
  "properties": {
    "iso:country":"GB",
    "wof:name":"SA44 6EY",
    "wof:placetype":"postalcode"
},
  "geometry": {"coordinates":[-4.40623594825026,52.1621255974802],"type":"Point"}
}