{
  "type": "Feature",
  "properties": {
    "iso:country":"GB",
    "wof:name":"NR9 5RD",
    "wof:placetype":"postalcode"
},
  "geometry": {"coordinates":[1.05900855308178,52.7208408707976],"type":"Point"}
}