{
  "type": "Feature",
  "properties": {
    "iso:country":"GB",
    "wof:name":"N7 6PJ",
    "wof:placetype":"postalcode"
},
  "geometry": {"coordinates":[-0.11698618028516,51.55812362076637],"type":"Point"}
}