{
  "type": "Feature",
  "properties": {
    "iso:country":"GB",
    "wof:name":"TF9 3PP",
    "wof:placetype":"postalcode"
},
  "geometry": {"coordinates":[-2.5397737689226,52.89855084004792],"type":"Point"}
}