{
  "type": "Feature",
  "properties": {
    "iso:country":"GB",
    "wof:name":"TN11 8DN",
    "wof:placetype":"postalcode"
},
  "geometry": {"coordinates":[0.1781702237144,51.16978286094582],"type":"Point"}
}