{
  "type": "Feature",
  "properties": {
    "date:inception_lower": "1980-01-01",
    "date:inception_upper": "1980-01-01",
    "iso:country": "GB",
    "wof:name": "TS11 8JG",
    "wof:placetype": "postalcode"
  },
  "geometry": {"coordinates":[-1.037565,54.577877],"type":"Point"}
}
