{
  "type": "Feature",
  "properties": {
    "iso:country":"GB",
    "wof:name":"WC2R 2PH",
    "wof:placetype":"postalcode"
},
  "geometry": {"coordinates":[-0.11371171859661,51.51103121366675],"type":"Point"}
}