{
  "type": "Feature",
  "properties": {
    "iso:country":"GB",
    "wof:name":"GU6 7RB",
    "wof:placetype":"postalcode"
},
  "geometry": {"coordinates":[-0.4414991945316,51.15051734540208],"type":"Point"}
}