{
  "type": "Feature",
  "properties": {
    "iso:country":"GB",
    "wof:name":"ST3 5PW",
    "wof:placetype":"postalcode"
},
  "geometry": {"coordinates":[-2.10607967376191,52.98191051426679],"type":"Point"}
}