{
  "type": "Feature",
  "properties": {
    "iso:country": "GB",
    "wof:name": "SE16 4UB",
    "wof:placetype": "postalcode"
  },
  "geometry": {"coordinates":[-0.068002,51.501079],"type":"Point"}
}
