{
  "type": "Feature",
  "properties": {
    "iso:country":"GB",
    "wof:name":"SE16 4UB",
    "wof:placetype":"postalcode"
},
  "geometry": {"coordinates":[-0.06800177163854,51.50107872091595],"type":"Point"}
}