{
  "type": "Feature",
  "properties": {
    "iso:country":"GB",
    "wof:name":"DN17 1AF",
    "wof:placetype":"postalcode"
},
  "geometry": {"coordinates":[-0.66529063647166,53.58413192320781],"type":"Point"}
}