{
  "type": "Feature",
  "properties": {
    "date:inception_lower":"1980-01-01",
    "date:inception_upper":"1980-01-31",
    "iso:country":"GB",
    "wof:name":"ME7 3RU",
    "wof:placetype":"postalcode"
},
  "geometry": {"coordinates":[0.578607,51.339437],"type":"Point"}
}