{
  "type": "Feature",
  "properties": {
    "iso:country":"GB",
    "wof:name":"YO25 6XZ",
    "wof:placetype":"postalcode"
},
  "geometry": {"coordinates":[-0.44447450105043,54.00155504780339],"type":"Point"}
}