{
  "type": "Feature",
  "properties": {
    "iso:country":"GB",
    "wof:name":"LE3 3JF",
    "wof:placetype":"postalcode"
},
  "geometry": {"coordinates":[-1.21323985696024,52.62443458856364],"type":"Point"}
}