{
  "type": "Feature",
  "properties": {
    "date:inception_lower": "1980-01-01",
    "date:inception_upper": "1980-01-01",
    "iso:country": "GB",
    "wof:name": "SG6 4RY",
    "wof:placetype": "postalcode"
  },
  "geometry": {"coordinates":[-0.230547,51.988857],"type":"Point"}
}
