{
  "type": "Feature",
  "properties": {
    "date:inception_lower": "1992-01-01",
    "date:inception_upper": "1992-01-01",
    "iso:country": "GB",
    "wof:name": "RH10 7RE",
    "wof:placetype": "postalcode"
  },
  "geometry": {"coordinates":[-0.148342,51.112547],"type":"Point"}
}
