{
  "type": "Feature",
  "properties": {
    "iso:country":"GB",
    "wof:name":"BD6 1DT",
    "wof:placetype":"postalcode"
},
  "geometry": {"coordinates":[-1.76572275332999,53.75988186296407],"type":"Point"}
}