{
  "type": "Feature",
  "properties": {
    "iso:country":"GB",
    "wof:name":"CF45 3EN",
    "wof:placetype":"postalcode"
},
  "geometry": {"coordinates":[-3.40023751318365,51.68369893597006],"type":"Point"}
}