{
  "type": "Feature",
  "properties": {
    "iso:country":"GB",
    "wof:name":"LL11 6AD",
    "wof:placetype":"postalcode"
},
  "geometry": {"coordinates":[-3.03570576542849,53.06742972713937],"type":"Point"}
}