{
  "type": "Feature",
  "properties": {
    "iso:country":"GB",
    "wof:name":"PA2 9HT",
    "wof:placetype":"postalcode"
},
  "geometry": {"coordinates":[-4.4552670051546,55.82871693597324],"type":"Point"}
}