{
  "type": "Feature",
  "properties": {
    "iso:country":"GB",
    "wof:name":"CO5 9XJ",
    "wof:placetype":"postalcode"
},
  "geometry": {"coordinates":[0.77951348123634,51.8318334590647],"type":"Point"}
}