{
  "type": "Feature",
  "properties": {
    "iso:country":"GB",
    "wof:name":"SL6 5HD",
    "wof:placetype":"postalcode"
},
  "geometry": {"coordinates":[-0.75208679439299,51.5278050210304],"type":"Point"}
}