{
  "type": "Feature",
  "properties": {
    "iso:country":"GB",
    "wof:name":"ME7 4HL",
    "wof:placetype":"postalcode"
},
  "geometry": {"coordinates":[0.55223751419295,51.37910101368292],"type":"Point"}
}