{
  "type": "Feature",
  "properties": {
    "iso:country":"GB",
    "wof:name":"HG5 0RW",
    "wof:placetype":"postalcode"
},
  "geometry": {"coordinates":[-1.40072750942777,54.02510682932795],"type":"Point"}
}