{
  "type": "Feature",
  "properties": {
    "date:inception_lower": "2002-11-01",
    "date:inception_upper": "2002-11-01",
    "iso:country": "GB",
    "wof:name": "N1 7NS",
    "wof:placetype": "postalcode"
  },
  "geometry": {"coordinates":[-0.089066,51.528653],"type":"Point"}
}
