{
  "type": "Feature",
  "properties": {
    "iso:country":"GB",
    "wof:name":"LS28 5QL",
    "wof:placetype":"postalcode"
},
  "geometry": {"coordinates":[-1.6845885097687,53.83078212445376],"type":"Point"}
}