{
  "type": "Feature",
  "properties": {
    "iso:country":"GB",
    "wof:name":"HD6 4DL",
    "wof:placetype":"postalcode"
},
  "geometry": {"coordinates":[-1.77774734407327,53.72030332846684],"type":"Point"}
}