{
  "type": "Feature",
  "properties": {
    "iso:country":"GB",
    "wof:name":"AB12 3AZ",
    "wof:placetype":"postalcode"
},
  "geometry": {"coordinates":[-2.08955654338642,57.12719868897535],"type":"Point"}
}