{
  "type": "Feature",
  "properties": {
    "iso:country":"GB",
    "wof:name":"SG8 9BT",
    "wof:placetype":"postalcode"
},
  "geometry": {"coordinates":[-0.02667965491124,52.04764324601946],"type":"Point"}
}