{
  "type": "Feature",
  "properties": {
    "iso:country": "GB",
    "wof:name": "NR17 2SB",
    "wof:placetype": "postalcode"
  },
  "geometry": {"coordinates":[1.026138,52.520142],"type":"Point"}
}
