{
  "type": "Feature",
  "properties": {
    "iso:country":"GB",
    "wof:name":"NR17 2SB",
    "wof:placetype":"postalcode"
},
  "geometry": {"coordinates":[1.02613752257096,52.52014200112752],"type":"Point"}
}