{
  "type": "Feature",
  "properties": {
    "iso:country":"GB",
    "wof:name":"BL3 4XP",
    "wof:placetype":"postalcode"
},
  "geometry": {"coordinates":[-2.47591283031446,53.56438912909329],"type":"Point"}
}