{
  "type": "Feature",
  "properties": {
    "date:inception_lower":"1987-04-01",
    "date:inception_upper":"1987-04-30",
    "iso:country":"GB",
    "wof:name":"BL3 4XP",
    "wof:placetype":"postalcode"
},
  "geometry": {"coordinates":[-2.475913,53.564389],"type":"Point"}
}