{
  "type": "Feature",
  "properties": {
    "iso:country": "GB",
    "wof:name": "CW8 3GZ",
    "wof:placetype": "postalcode"
  },
  "geometry": {"coordinates":[-2.58755,53.263302],"type":"Point"}
}
