{
  "type": "Feature",
  "properties": {
    "date:inception_lower":"2000-12-01",
    "date:inception_upper":"2000-12-31",
    "iso:country":"GB",
    "wof:name":"CW8 3GZ",
    "wof:placetype":"postalcode"
},
  "geometry": {"coordinates":[-2.58755,53.263302],"type":"Point"}
}