{
  "type": "Feature",
  "properties": {
    "date:inception_lower": "1980-01-01",
    "date:inception_upper": "1980-01-01",
    "iso:country": "GB",
    "wof:name": "DT9 5EY",
    "wof:placetype": "postalcode"
  },
  "geometry": {"coordinates":[-2.455226,50.970242],"type":"Point"}
}
