{
  "type": "Feature",
  "properties": {
    "iso:country": "GB",
    "wof:name": "DT9 5EY",
    "wof:placetype": "postalcode"
  },
  "geometry": {"coordinates":[-2.455596,50.970168],"type":"Point"}
}
