{
  "type": "Feature",
  "properties": {
    "iso:country":"GB",
    "wof:name":"DT9 5EY",
    "wof:placetype":"postalcode"
},
  "geometry": {"coordinates":[-2.45479043856208,50.97070815372683],"type":"Point"}
}