{
  "type": "Feature",
  "properties": {
    "iso:country":"GB",
    "wof:name":"DN15 7UA",
    "wof:placetype":"postalcode"
},
  "geometry": {"coordinates":[-0.69119190776947,53.58872375429191],"type":"Point"}
}