{
  "type": "Feature",
  "properties": {
    "iso:country": "GB",
    "wof:name": "WS13 7NX",
    "wof:placetype": "postalcode"
  },
  "geometry": {"coordinates":[-1.830452,52.694545],"type":"Point"}
}
