{
  "type": "Feature",
  "properties": {
    "date:inception_lower": "1980-01-01",
    "date:inception_upper": "1980-01-01",
    "iso:country": "GB",
    "wof:name": "WS13 7NX",
    "wof:placetype": "postalcode"
  },
  "geometry": {"coordinates":[-1.830452,52.694545],"type":"Point"}
}
