{
  "type": "Feature",
  "properties": {
    "date:inception_lower": "2017-11-01",
    "date:inception_upper": "2017-11-01",
    "iso:country": "GB",
    "wof:name": "NN18 8TY",
    "wof:placetype": "postalcode"
  },
  "geometry": {"coordinates":[-0.695824,52.477207],"type":"Point"}
}
