{
  "type": "Feature",
  "properties": {
    "iso:country":"GB",
    "wof:name":"CR4 3JR",
    "wof:placetype":"postalcode"
},
  "geometry": {"coordinates":[-0.1680947502223,51.41625753262882],"type":"Point"}
}