{
  "type": "Feature",
  "properties": {
    "iso:country":"GB",
    "wof:name":"LE17 4SA",
    "wof:placetype":"postalcode"
},
  "geometry": {"coordinates":[-1.21183720188794,52.46628080041197],"type":"Point"}
}