{
  "type": "Feature",
  "properties": {
    "iso:country": "GB",
    "wof:name": "LE17 4SA",
    "wof:placetype": "postalcode"
  },
  "geometry": {"coordinates":[-1.211837,52.466281],"type":"Point"}
}
