{
  "type": "Feature",
  "properties": {
    "iso:country": "GB",
    "wof:name": "NR14 7NZ",
    "wof:placetype": "postalcode"
  },
  "geometry": {"coordinates":[1.381814,52.567751],"type":"Point"}
}
