{
  "type": "Feature",
  "properties": {
    "iso:country":"GB",
    "wof:name":"NR14 7NZ",
    "wof:placetype":"postalcode"
},
  "geometry": {"coordinates":[1.38181391633949,52.56775074458036],"type":"Point"}
}