{
  "type": "Feature",
  "properties": {
    "date:inception_lower":"1980-01-01",
    "date:inception_upper":"1980-01-31",
    "iso:country":"GB",
    "wof:name":"NR14 7NZ",
    "wof:placetype":"postalcode"
},
  "geometry": {"coordinates":[1.381814,52.567751],"type":"Point"}
}