{
  "type": "Feature",
  "properties": {
    "iso:country": "GB",
    "wof:name": "NG8 3BP",
    "wof:placetype": "postalcode"
  },
  "geometry": {"coordinates":[-1.213621,52.961021],"type":"Point"}
}
