{
  "type": "Feature",
  "properties": {
    "iso:country": "GB",
    "wof:name": "CF3 3JF",
    "wof:placetype": "postalcode"
  },
  "geometry": {"coordinates":[-3.122964,51.510296],"type":"Point"}
}
