{
  "type": "Feature",
  "properties": {
    "iso:country":"GB",
    "wof:name":"CF3 3JF",
    "wof:placetype":"postalcode"
},
  "geometry": {"coordinates":[-3.1229643387692,51.51029635255104],"type":"Point"}
}