{
  "type": "Feature",
  "properties": {
    "date:inception_lower":"1999-06-01",
    "date:inception_upper":"1999-06-30",
    "iso:country":"GB",
    "wof:name":"CF3 3JF",
    "wof:placetype":"postalcode"
},
  "geometry": {"coordinates":[-3.122964,51.510296],"type":"Point"}
}