{
  "type": "Feature",
  "properties": {
    "iso:country": "GB",
    "wof:name": "HD1 3ED",
    "wof:placetype": "postalcode"
  },
  "geometry": {"coordinates":[-1.785076,53.641041],"type":"Point"}
}
