{
  "type": "Feature",
  "properties": {
    "iso:country":"GB",
    "wof:name":"IG1 1SF",
    "wof:placetype":"postalcode"
},
  "geometry": {"coordinates":[0.08459256101231,51.55618096498537],"type":"Point"}
}