{
  "type": "Feature",
  "properties": {
    "iso:country":"GB",
    "wof:name":"DD5 4PF",
    "wof:placetype":"postalcode"
},
  "geometry": {"coordinates":[-2.82684363430784,56.47970363130429],"type":"Point"}
}