{
  "type": "Feature",
  "properties": {
    "iso:country": "GB",
    "wof:name": "DD5 4PF",
    "wof:placetype": "postalcode"
  },
  "geometry": {"coordinates":[-2.826844,56.479704],"type":"Point"}
}
