{
  "type": "Feature",
  "properties": {
    "iso:country":"GB",
    "wof:name":"BA6 9DD",
    "wof:placetype":"postalcode"
},
  "geometry": {"coordinates":[-2.71289279374982,51.14873279263758],"type":"Point"}
}