{
  "type": "Feature",
  "properties": {
    "iso:country":"GB",
    "wof:name":"BB5 6LY",
    "wof:placetype":"postalcode"
},
  "geometry": {"coordinates":[-2.34160398941507,53.77430929103175],"type":"Point"}
}