{
  "type": "Feature",
  "properties": {
    "iso:country": "GB",
    "wof:name": "EX11 1UN",
    "wof:placetype": "postalcode"
  },
  "geometry": {"coordinates":[-3.329962,50.733116],"type":"Point"}
}
