{
  "type": "Feature",
  "properties": {
    "iso:country":"GB",
    "wof:name":"M20 2ED",
    "wof:placetype":"postalcode"
},
  "geometry": {"coordinates":[-2.24881356391575,53.42912747578734],"type":"Point"}
}