{
  "type": "Feature",
  "properties": {
    "date:inception_lower": "2004-05-01",
    "date:inception_upper": "2004-05-01",
    "iso:country": "GB",
    "wof:name": "M20 2ED",
    "wof:placetype": "postalcode"
  },
  "geometry": {"coordinates":[-2.248814,53.429127],"type":"Point"}
}
