{
  "type": "Feature",
  "properties": {
    "iso:country":"GB",
    "wof:name":"S71 2HA",
    "wof:placetype":"postalcode"
},
  "geometry": {"coordinates":[-1.45505464212574,53.56577764789493],"type":"Point"}
}