{
  "type": "Feature",
  "properties": {
    "iso:country":"GB",
    "wof:name":"DL16 7BX",
    "wof:placetype":"postalcode"
},
  "geometry": {"coordinates":[-1.62058143536049,54.69036008340727],"type":"Point"}
}