{
  "type": "Feature",
  "properties": {
    "iso:country":"GB",
    "wof:name":"S12 2EP",
    "wof:placetype":"postalcode"
},
  "geometry": {"coordinates":[-1.41266235567388,53.3536078651742],"type":"Point"}
}