{
  "type": "Feature",
  "properties": {
    "date:inception_lower": "1980-01-01",
    "date:inception_upper": "1980-01-01",
    "iso:country": "GB",
    "wof:name": "S12 2EP",
    "wof:placetype": "postalcode"
  },
  "geometry": {"coordinates":[-1.412691,53.353645],"type":"Point"}
}
