{
  "type": "Feature",
  "properties": {
    "iso:country": "GB",
    "wof:name": "S12 2EP",
    "wof:placetype": "postalcode"
  },
  "geometry": {"coordinates":[-1.412691,53.353645],"type":"Point"}
}
