{
  "type": "Feature",
  "properties": {
    "date:inception_lower": "1990-02-01",
    "date:inception_upper": "1990-02-01",
    "iso:country": "GB",
    "wof:name": "CM8 2YJ",
    "wof:placetype": "postalcode"
  },
  "geometry": {"coordinates":[0.629534,51.810085],"type":"Point"}
}
