{
  "type": "Feature",
  "properties": {
    "iso:country":"GB",
    "wof:name":"CM8 2YJ",
    "wof:placetype":"postalcode"
},
  "geometry": {"coordinates":[0.62953403449269,51.81008508767419],"type":"Point"}
}