{
  "type": "Feature",
  "properties": {
    "iso:country": "GB",
    "wof:name": "BN7 3BA",
    "wof:placetype": "postalcode"
  },
  "geometry": {"coordinates":[-0.050653,50.920337],"type":"Point"}
}
