{
  "type": "Feature",
  "properties": {
    "iso:country":"GB",
    "wof:name":"BN7 3BA",
    "wof:placetype":"postalcode"
},
  "geometry": {"coordinates":[-0.05065304982611,50.92033675902218],"type":"Point"}
}