{
  "type": "Feature",
  "properties": {
    "date:inception_lower": "1980-01-01",
    "date:inception_upper": "1980-01-01",
    "iso:country": "GB",
    "wof:name": "BN7 3BA",
    "wof:placetype": "postalcode"
  },
  "geometry": {"coordinates":[-0.050653,50.920337],"type":"Point"}
}
