{
  "type": "Feature",
  "properties": {
    "iso:country": "GB",
    "wof:name": "SO14 0AY",
    "wof:placetype": "postalcode"
  },
  "geometry": {"coordinates":[-1.400375,50.906993],"type":"Point"}
}
