{
  "type": "Feature",
  "properties": {
    "iso:country":"GB",
    "wof:name":"SO14 0AY",
    "wof:placetype":"postalcode"
},
  "geometry": {"coordinates":[-1.40037466819824,50.90699293377029],"type":"Point"}
}