{
  "type": "Feature",
  "properties": {
    "iso:country":"GB",
    "wof:name":"KT22 7QG",
    "wof:placetype":"postalcode"
},
  "geometry": {"coordinates":[-0.33209226658009,51.31205496890246],"type":"Point"}
}