{
  "type": "Feature",
  "properties": {
    "iso:country": "GB",
    "wof:name": "SY4 3HE",
    "wof:placetype": "postalcode"
  },
  "geometry": {"coordinates":[-2.764651,52.832093],"type":"Point"}
}
