{
  "type": "Feature",
  "properties": {
    "iso:country":"GB",
    "wof:name":"TR12 7EQ",
    "wof:placetype":"postalcode"
},
  "geometry": {"coordinates":[-5.24880699148747,50.02309243489738],"type":"Point"}
}