{
  "type": "Feature",
  "properties": {
    "iso:country":"GB",
    "wof:name":"GL1 2QU",
    "wof:placetype":"postalcode"
},
  "geometry": {"coordinates":[-2.24915707076295,51.86733292265933],"type":"Point"}
}