{
  "type": "Feature",
  "properties": {
    "iso:country":"GB",
    "wof:name":"BS11 8DG",
    "wof:placetype":"postalcode"
},
  "geometry": {"coordinates":[-2.68282235591513,51.50200512695469],"type":"Point"}
}