{
  "type": "Feature",
  "properties": {
    "iso:country":"GB",
    "wof:name":"DA16 1LF",
    "wof:placetype":"postalcode"
},
  "geometry": {"coordinates":[0.11711386841428,51.46832322963299],"type":"Point"}
}