{
  "type": "Feature",
  "properties": {
    "iso:country": "GB",
    "wof:name": "HP19 9PX",
    "wof:placetype": "postalcode"
  },
  "geometry": {"coordinates":[-0.816619,51.822203],"type":"Point"}
}
