{
  "type": "Feature",
  "properties": {
    "date:inception_lower": "2000-06-01",
    "date:inception_upper": "2000-06-01",
    "iso:country": "GB",
    "wof:name": "HP19 9PX",
    "wof:placetype": "postalcode"
  },
  "geometry": {"coordinates":[-0.816698,51.822211],"type":"Point"}
}
