{
  "type": "Feature",
  "properties": {
    "iso:country":"GB",
    "wof:name":"CM2 7RR",
    "wof:placetype":"postalcode"
},
  "geometry": {"coordinates":[0.5223236449774,51.71712590333485],"type":"Point"}
}