{
  "type": "Feature",
  "properties": {
    "iso:country":"GB",
    "wof:name":"L26 9XY",
    "wof:placetype":"postalcode"
},
  "geometry": {"coordinates":[-2.82466939316677,53.35932002760813],"type":"Point"}
}