{
  "type": "Feature",
  "properties": {
    "date:inception_lower": "1980-01-01",
    "date:inception_upper": "1980-01-01",
    "iso:country": "GB",
    "wof:name": "W10 4UL",
    "wof:placetype": "postalcode"
  },
  "geometry": {"coordinates":[-0.207101,51.530382],"type":"Point"}
}
