{
  "type": "Feature",
  "properties": {
    "date:inception_lower": "1983-01-01",
    "date:inception_upper": "1983-01-01",
    "iso:country": "GB",
    "wof:name": "BN2 1SU",
    "wof:placetype": "postalcode"
  },
  "geometry": {"coordinates":[-0.131614,50.821798],"type":"Point"}
}
