{
  "type": "Feature",
  "properties": {
    "iso:country":"GB",
    "wof:name":"EX17 4ES",
    "wof:placetype":"postalcode"
},
  "geometry": {"coordinates":[-3.70266578241374,50.82181713569761],"type":"Point"}
}