{
  "type": "Feature",
  "properties": {
    "iso:country":"GB",
    "wof:name":"TF4 2FB",
    "wof:placetype":"postalcode"
},
  "geometry": {"coordinates":[-2.48580415604363,52.6783865596648],"type":"Point"}
}