{
  "type": "Feature",
  "properties": {
    "date:inception_lower": "2008-01-01",
    "date:inception_upper": "2008-01-01",
    "iso:country": "GB",
    "wof:name": "TF4 2FB",
    "wof:placetype": "postalcode"
  },
  "geometry": {"coordinates":[-2.485804,52.678387],"type":"Point"}
}
