{
  "type": "Feature",
  "properties": {
    "iso:country":"GB",
    "wof:name":"HP1 3JG",
    "wof:placetype":"postalcode"
},
  "geometry": {"coordinates":[-0.48171280084699,51.76331836532693],"type":"Point"}
}