{
  "type": "Feature",
  "properties": {
    "iso:country": "GB",
    "wof:name": "HP1 3JG",
    "wof:placetype": "postalcode"
  },
  "geometry": {"coordinates":[-0.481713,51.763318],"type":"Point"}
}
