{
  "type": "Feature",
  "properties": {
    "date:inception_lower":"2006-10-01",
    "date:inception_upper":"2006-10-31",
    "iso:country":"GB",
    "wof:name":"HP1 3JG",
    "wof:placetype":"postalcode"
},
  "geometry": {"coordinates":[-0.481713,51.763318],"type":"Point"}
}