{
  "type": "Feature",
  "properties": {
    "date:inception_lower":"1980-01-01",
    "date:inception_upper":"1980-01-31",
    "iso:country":"GB",
    "wof:name":"EX21 5RU",
    "wof:placetype":"postalcode"
},
  "geometry": {"coordinates":[-4.219074,50.861782],"type":"Point"}
}