{
  "type": "Feature",
  "properties": {
    "date:inception_lower": "2024-01-01",
    "date:inception_upper": "2024-01-01",
    "iso:country": "GB",
    "wof:name": "WS2 0BQ",
    "wof:placetype": "postalcode"
  },
  "geometry": {"coordinates":[-2.022667,52.58745],"type":"Point"}
}
