{
  "type": "Feature",
  "properties": {
    "date:inception_lower": "2019-12-01",
    "date:inception_upper": "2019-12-01",
    "iso:country": "GB",
    "wof:name": "TQ12 6WL",
    "wof:placetype": "postalcode"
  },
  "geometry": {"coordinates":[-3.618663,50.540176],"type":"Point"}
}
