{
  "type": "Feature",
  "properties": {
    "iso:country": "GB",
    "wof:name": "TQ12 6WL",
    "wof:placetype": "postalcode"
  },
  "geometry": {"coordinates":[-3.618694,50.540661],"type":"Point"}
}
