{
  "type": "Feature",
  "properties": {
    "date:inception_lower": "2022-02-01",
    "date:inception_upper": "2022-02-01",
    "iso:country": "GB",
    "wof:name": "S41 9FD",
    "wof:placetype": "postalcode"
  },
  "geometry": {"coordinates":[-1.437379,53.280181],"type":"Point"}
}
