{
  "type": "Feature",
  "properties": {
    "date:inception_lower": "1981-06-01",
    "date:inception_upper": "1981-06-01",
    "iso:country": "GB",
    "wof:name": "WN2 2JP",
    "wof:placetype": "postalcode"
  },
  "geometry": {"coordinates":[-2.603182,53.54893],"type":"Point"}
}
