{
  "type": "Feature",
  "properties": {
    "iso:country":"GB",
    "wof:name":"WN2 2JP",
    "wof:placetype":"postalcode"
},
  "geometry": {"coordinates":[-2.60318201688735,53.54892991075651],"type":"Point"}
}