{
  "type": "Feature",
  "properties": {
    "iso:country": "GB",
    "wof:name": "WN2 2JP",
    "wof:placetype": "postalcode"
  },
  "geometry": {"coordinates":[-2.603182,53.54893],"type":"Point"}
}
