{
  "type": "Feature",
  "properties": {
    "iso:country":"GB",
    "wof:name":"PO11 0JX",
    "wof:placetype":"postalcode"
},
  "geometry": {"coordinates":[-0.98549750965428,50.79838016875298],"type":"Point"}
}