{
  "type": "Feature",
  "properties": {
    "date:inception_lower": "1980-01-01",
    "date:inception_upper": "1980-01-01",
    "iso:country": "GB",
    "wof:name": "PO11 0JX",
    "wof:placetype": "postalcode"
  },
  "geometry": {"coordinates":[-0.985497,50.79838],"type":"Point"}
}
