{
  "type": "Feature",
  "properties": {
    "iso:country":"GB",
    "wof:name":"PL5 1QT",
    "wof:placetype":"postalcode"
},
  "geometry": {"coordinates":[-4.18324546239681,50.40860801415418],"type":"Point"}
}