{
  "type": "Feature",
  "properties": {
    "iso:country":"GB",
    "wof:name":"S5 7LT",
    "wof:placetype":"postalcode"
},
  "geometry": {"coordinates":[-1.47342427208717,53.41404359070681],"type":"Point"}
}