{
  "type": "Feature",
  "properties": {
    "iso:country":"GB",
    "wof:name":"PL18 9DT",
    "wof:placetype":"postalcode"
},
  "geometry": {"coordinates":[-4.21884316745621,50.51582134317964],"type":"Point"}
}