{
  "type": "Feature",
  "properties": {
    "iso:country":"GB",
    "wof:name":"SL9 9NZ",
    "wof:placetype":"postalcode"
},
  "geometry": {"coordinates":[-0.56493891767204,51.61081044669447],"type":"Point"}
}