{
  "type": "Feature",
  "properties": {
    "iso:country":"GB",
    "wof:name":"WF4 3PB",
    "wof:placetype":"postalcode"
},
  "geometry": {"coordinates":[-1.52380821240497,53.64157299592704],"type":"Point"}
}