{
  "type": "Feature",
  "properties": {
    "iso:country":"GB",
    "wof:name":"UB6 9BY",
    "wof:placetype":"postalcode"
},
  "geometry": {"coordinates":[-0.35754851410359,51.51985167838493],"type":"Point"}
}