{
  "type": "Feature",
  "properties": {
    "iso:country": "GB",
    "wof:name": "MK3 5NE",
    "wof:placetype": "postalcode"
  },
  "geometry": {"coordinates":[-0.737252,51.976462],"type":"Point"}
}
