{
  "type": "Feature",
  "properties": {
    "iso:country":"GB",
    "wof:name":"RG17 7TR",
    "wof:placetype":"postalcode"
},
  "geometry": {"coordinates":[-1.55987974490149,51.4871464938492],"type":"Point"}
}