{
  "type": "Feature",
  "properties": {
    "iso:country":"GB",
    "wof:name":"IG5 0NW",
    "wof:placetype":"postalcode"
},
  "geometry": {"coordinates":[0.05714988365318,51.59667371846844],"type":"Point"}
}