{
  "type": "Feature",
  "properties": {
    "date:inception_lower": "1990-02-01",
    "date:inception_upper": "1990-02-01",
    "iso:country": "GB",
    "wof:name": "CT11 0NU",
    "wof:placetype": "postalcode"
  },
  "geometry": {"coordinates":[1.385745,51.336547],"type":"Point"}
}
