{
  "type": "Feature",
  "properties": {
    "iso:country":"GB",
    "wof:name":"B61 0AS",
    "wof:placetype":"postalcode"
},
  "geometry": {"coordinates":[-2.06093608283262,52.3472441354849],"type":"Point"}
}