{
  "type": "Feature",
  "properties": {
    "date:inception_lower": "1980-01-01",
    "date:inception_upper": "1980-01-01",
    "iso:country": "GB",
    "wof:name": "B61 0AS",
    "wof:placetype": "postalcode"
  },
  "geometry": {"coordinates":[-2.060936,52.347244],"type":"Point"}
}
