{
  "type": "Feature",
  "properties": {
    "iso:country":"GB",
    "wof:name":"BS5 0EJ",
    "wof:placetype":"postalcode"
},
  "geometry": {"coordinates":[-2.56400274447876,51.46190499970488],"type":"Point"}
}