{
  "type": "Feature",
  "properties": {
    "date:inception_lower": "1980-01-01",
    "date:inception_upper": "1980-01-01",
    "iso:country": "GB",
    "wof:name": "BS5 0EJ",
    "wof:placetype": "postalcode"
  },
  "geometry": {"coordinates":[-2.564003,51.461905],"type":"Point"}
}
