{
  "type": "Feature",
  "properties": {
    "date:inception_lower": "1995-12-01",
    "date:inception_upper": "1995-12-01",
    "iso:country": "GB",
    "wof:name": "BL3 1HQ",
    "wof:placetype": "postalcode"
  },
  "geometry": {"coordinates":[-2.369742,53.560837],"type":"Point"}
}
