{
  "type": "Feature",
  "properties": {
    "date:inception_lower": "2022-11-01",
    "date:inception_upper": "2022-11-01",
    "iso:country": "GB",
    "wof:name": "SA12 6FA",
    "wof:placetype": "postalcode"
  },
  "geometry": {"coordinates":[-3.809861,51.589602],"type":"Point"}
}
