{
  "type": "Feature",
  "properties": {
    "iso:country":"GB",
    "wof:name":"NG3 1AN",
    "wof:placetype":"postalcode"
},
  "geometry": {"coordinates":[-1.14788863795446,52.96203311682674],"type":"Point"}
}