{
  "type": "Feature",
  "properties": {
    "date:inception_lower":"1980-01-01",
    "date:inception_upper":"1980-01-31",
    "iso:country":"GB",
    "wof:name":"NG3 1AN",
    "wof:placetype":"postalcode"
},
  "geometry": {"coordinates":[-1.147889,52.962033],"type":"Point"}
}