{
  "type": "Feature",
  "properties": {
    "iso:country":"GB",
    "wof:name":"PL31 1JY",
    "wof:placetype":"postalcode"
},
  "geometry": {"coordinates":[-4.73216297815969,50.47077212052758],"type":"Point"}
}