{
  "type": "Feature",
  "properties": {
    "date:inception_lower": "1980-01-01",
    "date:inception_upper": "1980-01-01",
    "iso:country": "GB",
    "wof:name": "PL31 1JY",
    "wof:placetype": "postalcode"
  },
  "geometry": {"coordinates":[-4.732163,50.470772],"type":"Point"}
}
