{
  "type": "Feature",
  "properties": {
    "date:inception_lower": "1980-01-01",
    "date:inception_upper": "1980-01-01",
    "iso:country": "GB",
    "wof:name": "LL23 7TL",
    "wof:placetype": "postalcode"
  },
  "geometry": {"coordinates":[-3.665976,52.85423],"type":"Point"}
}
