{
  "type": "Feature",
  "properties": {
    "iso:country":"GB",
    "wof:name":"RG19 3TZ",
    "wof:placetype":"postalcode"
},
  "geometry": {"coordinates":[-1.2819705815859,51.4047327349138],"type":"Point"}
}