{
  "type": "Feature",
  "properties": {
    "date:inception_lower": "2017-12-01",
    "date:inception_upper": "2017-12-01",
    "iso:country": "GB",
    "wof:name": "BS16 1XN",
    "wof:placetype": "postalcode"
  },
  "geometry": {"coordinates":[-2.526372,51.499043],"type":"Point"}
}
