{
  "type": "Feature",
  "properties": {
    "iso:country":"GB",
    "wof:name":"IP12 3HT",
    "wof:placetype":"postalcode"
},
  "geometry": {"coordinates":[1.40082585495094,52.07260531385633],"type":"Point"}
}