{
  "type": "Feature",
  "properties": {
    "date:inception_lower": "1999-12-01",
    "date:inception_upper": "1999-12-01",
    "iso:country": "GB",
    "wof:name": "BB8 9PF",
    "wof:placetype": "postalcode"
  },
  "geometry": {"coordinates":[-2.184434,53.852661],"type":"Point"}
}
