{
  "type": "Feature",
  "properties": {
    "iso:country":"GB",
    "wof:name":"SW15 4EY",
    "wof:placetype":"postalcode"
},
  "geometry": {"coordinates":[-0.24338335974638,51.45070939315222],"type":"Point"}
}