{
  "type": "Feature",
  "properties": {
    "date:inception_lower":"1991-09-01",
    "date:inception_upper":"1991-09-30",
    "iso:country":"GB",
    "wof:name":"B97 5TG",
    "wof:placetype":"postalcode"
},
  "geometry": {"coordinates":[-1.971643,52.293279],"type":"Point"}
}