{
  "type": "Feature",
  "properties": {
    "date:inception_lower": "2022-12-01",
    "date:inception_upper": "2022-12-01",
    "iso:country": "GB",
    "wof:name": "SN5 1EB",
    "wof:placetype": "postalcode"
  },
  "geometry": {"coordinates":[-1.818203,51.562677],"type":"Point"}
}
