{
  "type": "Feature",
  "properties": {
    "iso:country": "GB",
    "wof:name": "NN14 4PH",
    "wof:placetype": "postalcode"
  },
  "geometry": {"coordinates":[-0.541056,52.393909],"type":"Point"}
}
