{
  "type": "Feature",
  "properties": {
    "iso:country":"GB",
    "wof:name":"IG6 2RA",
    "wof:placetype":"postalcode"
},
  "geometry": {"coordinates":[0.08017409603007,51.6009710312981],"type":"Point"}
}