{
  "type": "Feature",
  "properties": {
    "date:inception_lower": "1980-01-01",
    "date:inception_upper": "1980-01-01",
    "iso:country": "GB",
    "wof:name": "IG6 2RA",
    "wof:placetype": "postalcode"
  },
  "geometry": {"coordinates":[0.080174,51.600971],"type":"Point"}
}
