{
  "type": "Feature",
  "properties": {
    "iso:country":"GB",
    "wof:name":"NG15 9BA",
    "wof:placetype":"postalcode"
},
  "geometry": {"coordinates":[-1.16410791337318,53.08590519376329],"type":"Point"}
}