{
  "type": "Feature",
  "properties": {
    "date:inception_lower": "2006-05-01",
    "date:inception_upper": "2006-05-01",
    "iso:country": "GB",
    "wof:name": "BS22 7WB",
    "wof:placetype": "postalcode"
  },
  "geometry": {"coordinates":[-2.900161,51.364843],"type":"Point"}
}
