{
  "type": "Feature",
  "properties": {
    "iso:country":"GB",
    "wof:name":"GL7 1LF",
    "wof:placetype":"postalcode"
},
  "geometry": {"coordinates":[-1.95783759099035,51.70903318878083],"type":"Point"}
}