{
  "type": "Feature",
  "properties": {
    "iso:country":"GB",
    "wof:name":"NW11 6UE",
    "wof:placetype":"postalcode"
},
  "geometry": {"coordinates":[-0.18252489515578,51.5798216060487],"type":"Point"}
}