{
  "type": "Feature",
  "properties": {
    "iso:country": "GB",
    "wof:name": "NW11 6UE",
    "wof:placetype": "postalcode"
  },
  "geometry": {"coordinates":[-0.182525,51.579822],"type":"Point"}
}
