{
  "type": "Feature",
  "properties": {
    "iso:country": "GB",
    "wof:name": "SK17 6TP",
    "wof:placetype": "postalcode"
  },
  "geometry": {"coordinates":[-1.929989,53.256019],"type":"Point"}
}
