{
  "type": "Feature",
  "properties": {
    "date:inception_lower": "2000-06-01",
    "date:inception_upper": "2000-06-01",
    "iso:country": "GB",
    "wof:name": "SK17 6TP",
    "wof:placetype": "postalcode"
  },
  "geometry": {"coordinates":[-1.929284,53.256172],"type":"Point"}
}
