{
  "type": "Feature",
  "properties": {
    "iso:country": "GB",
    "wof:name": "TA19 9BN",
    "wof:placetype": "postalcode"
  },
  "geometry": {"coordinates":[-2.917445,50.927451],"type":"Point"}
}
