{
  "type": "Feature",
  "properties": {
    "iso:country":"GB",
    "wof:name":"TA19 9BN",
    "wof:placetype":"postalcode"
},
  "geometry": {"coordinates":[-2.91744482536979,50.92745107349159],"type":"Point"}
}