{
  "type": "Feature",
  "properties": {
    "iso:country":"GB",
    "wof:name":"NP23 5QQ",
    "wof:placetype":"postalcode"
},
  "geometry": {"coordinates":[-3.20050572136147,51.7969472264896],"type":"Point"}
}