{
  "type": "Feature",
  "properties": {
    "date:inception_lower":"1980-01-01",
    "date:inception_upper":"1980-01-31",
    "iso:country":"GB",
    "wof:name":"DH1 2NA",
    "wof:placetype":"postalcode"
},
  "geometry": {"coordinates":[-1.552298,54.761284],"type":"Point"}
}