{
  "type": "Feature",
  "properties": {
    "iso:country":"GB",
    "wof:name":"DH1 2NA",
    "wof:placetype":"postalcode"
},
  "geometry": {"coordinates":[-1.5522416211243,54.76123841757641],"type":"Point"}
}