{
  "type": "Feature",
  "properties": {
    "iso:country": "GB",
    "wof:name": "DH1 2NA",
    "wof:placetype": "postalcode"
  },
  "geometry": {"coordinates":[-1.552252,54.761248],"type":"Point"}
}
