{
  "type": "Feature",
  "properties": {
    "iso:country": "GB",
    "wof:name": "SN5 7BH",
    "wof:placetype": "postalcode"
  },
  "geometry": {"coordinates":[-1.822672,51.558735],"type":"Point"}
}
