{
  "type": "Feature",
  "properties": {
    "iso:country":"GB",
    "wof:name":"SA6 7HH",
    "wof:placetype":"postalcode"
},
  "geometry": {"coordinates":[-3.94144565872007,51.66203272453228],"type":"Point"}
}