{
  "type": "Feature",
  "properties": {
    "date:inception_lower": "1980-01-01",
    "date:inception_upper": "1980-01-01",
    "iso:country": "GB",
    "wof:name": "TD8 6AH",
    "wof:placetype": "postalcode"
  },
  "geometry": {"coordinates":[-2.554268,55.478204],"type":"Point"}
}
