{
  "type": "Feature",
  "properties": {
    "iso:country":"GB",
    "wof:name":"HR6 8PT",
    "wof:placetype":"postalcode"
},
  "geometry": {"coordinates":[-2.74395611792461,52.22391395275737],"type":"Point"}
}