{
  "type": "Feature",
  "properties": {
    "iso:country":"GB",
    "wof:name":"HG4 2HR",
    "wof:placetype":"postalcode"
},
  "geometry": {"coordinates":[-1.54442733535637,54.14109285506508],"type":"Point"}
}