{
  "type": "Feature",
  "properties": {
    "iso:country": "GB",
    "wof:name": "GL2 4TQ",
    "wof:placetype": "postalcode"
  },
  "geometry": {"coordinates":[-2.278506,51.822321],"type":"Point"}
}
