{
  "type": "Feature",
  "properties": {
    "iso:country":"GB",
    "wof:name":"GL2 4TQ",
    "wof:placetype":"postalcode"
},
  "geometry": {"coordinates":[-2.27850630875122,51.8223212507042],"type":"Point"}
}