{
  "type": "Feature",
  "properties": {
    "iso:country": "GB",
    "wof:name": "SL2 2QB",
    "wof:placetype": "postalcode"
  },
  "geometry": {"coordinates":[-0.641332,51.53598],"type":"Point"}
}
