{
  "type": "Feature",
  "properties": {
    "iso:country": "GB",
    "wof:name": "LL26 0BQ",
    "wof:placetype": "postalcode"
  },
  "geometry": {"coordinates":[-3.786066,53.156685],"type":"Point"}
}
