{
  "type": "Feature",
  "properties": {
    "iso:country":"GB",
    "wof:name":"LL26 0BQ",
    "wof:placetype":"postalcode"
},
  "geometry": {"coordinates":[-3.78606628077465,53.15668462083985],"type":"Point"}
}