{
  "type": "Feature",
  "properties": {
    "date:inception_lower": "2021-01-01",
    "date:inception_upper": "2021-01-01",
    "iso:country": "GB",
    "wof:name": "EX20 3GJ",
    "wof:placetype": "postalcode"
  },
  "geometry": {"coordinates":[-4.092956,50.776858],"type":"Point"}
}
