{
  "type": "Feature",
  "properties": {
    "date:inception_lower":"2010-03-01",
    "date:inception_upper":"2010-03-31",
    "iso:country":"GB",
    "wof:name":"LN3 5SH",
    "wof:placetype":"postalcode"
},
  "geometry": {"coordinates":[-0.325215,53.207889],"type":"Point"}
}