{
  "type": "Feature",
  "properties": {
    "iso:country": "GB",
    "wof:name": "YO42 1RW",
    "wof:placetype": "postalcode"
  },
  "geometry": {"coordinates":[-0.757551,53.900062],"type":"Point"}
}
