{
  "type": "Feature",
  "properties": {
    "iso:country":"GB",
    "wof:name":"YO42 1RW",
    "wof:placetype":"postalcode"
},
  "geometry": {"coordinates":[-0.75755079704892,53.9000615606354],"type":"Point"}
}