{
  "type": "Feature",
  "properties": {
    "iso:country":"GB",
    "wof:name":"W1H 7HE",
    "wof:placetype":"postalcode"
},
  "geometry": {"coordinates":[-0.16202437937278,51.51589883420568],"type":"Point"}
}