{
  "type": "Feature",
  "properties": {
    "iso:country": "GB",
    "wof:name": "B68 8LX",
    "wof:placetype": "postalcode"
  },
  "geometry": {"coordinates":[-2.019673,52.482289],"type":"Point"}
}
