{
  "type": "Feature",
  "properties": {
    "iso:country": "GB",
    "wof:name": "SY4 5LQ",
    "wof:placetype": "postalcode"
  },
  "geometry": {"coordinates":[-2.601081,52.864213],"type":"Point"}
}
