{
  "type": "Feature",
  "properties": {
    "date:inception_lower":"1980-01-01",
    "date:inception_upper":"1980-01-31",
    "iso:country":"GB",
    "wof:name":"SY4 5LQ",
    "wof:placetype":"postalcode"
},
  "geometry": {"coordinates":[-2.601081,52.864213],"type":"Point"}
}