{
  "type": "Feature",
  "properties": {
    "iso:country":"GB",
    "wof:name":"LS27 8DE",
    "wof:placetype":"postalcode"
},
  "geometry": {"coordinates":[-1.58739433204132,53.745640353143],"type":"Point"}
}