{
  "type": "Feature",
  "properties": {
    "iso:country":"GB",
    "wof:name":"TW8 9LF",
    "wof:placetype":"postalcode"
},
  "geometry": {"coordinates":[-0.32031545911796,51.49444270024112],"type":"Point"}
}