{
  "type": "Feature",
  "properties": {
    "date:inception_lower": "2018-01-01",
    "date:inception_upper": "2018-01-01",
    "iso:country": "GB",
    "wof:name": "DL8 5BZ",
    "wof:placetype": "postalcode"
  },
  "geometry": {"coordinates":[-1.820691,54.30851],"type":"Point"}
}
