{
  "type": "Feature",
  "properties": {
    "iso:country": "GB",
    "wof:name": "TW3 4LS",
    "wof:placetype": "postalcode"
  },
  "geometry": {"coordinates":[-0.383042,51.475182],"type":"Point"}
}
