{
  "type": "Feature",
  "properties": {
    "iso:country":"GB",
    "wof:name":"GL6 0NN",
    "wof:placetype":"postalcode"
},
  "geometry": {"coordinates":[-2.23026360970503,51.70261961169336],"type":"Point"}
}