{
  "type": "Feature",
  "properties": {
    "iso:country":"GB",
    "wof:name":"LE2 7LE",
    "wof:placetype":"postalcode"
},
  "geometry": {"coordinates":[-1.13885493929699,52.62460065659526],"type":"Point"}
}