{
  "type": "Feature",
  "properties": {
    "date:inception_lower": "1980-01-01",
    "date:inception_upper": "1980-01-01",
    "iso:country": "GB",
    "wof:name": "WV4 6RQ",
    "wof:placetype": "postalcode"
  },
  "geometry": {"coordinates":[-2.114058,52.555791],"type":"Point"}
}
