{
  "type": "Feature",
  "properties": {
    "iso:country":"GB",
    "wof:name":"WV4 6RQ",
    "wof:placetype":"postalcode"
},
  "geometry": {"coordinates":[-2.11405840787504,52.555790803388],"type":"Point"}
}