{
  "type": "Feature",
  "properties": {
    "iso:country": "GB",
    "wof:name": "WV4 6RQ",
    "wof:placetype": "postalcode"
  },
  "geometry": {"coordinates":[-2.114058,52.555791],"type":"Point"}
}
