{
  "type": "Feature",
  "properties": {
    "iso:country":"GB",
    "wof:name":"LA3 3BN",
    "wof:placetype":"postalcode"
},
  "geometry": {"coordinates":[-2.83824688176399,54.05848521413689],"type":"Point"}
}