{
  "type": "Feature",
  "properties": {
    "iso:country": "GB",
    "wof:name": "LA3 3BN",
    "wof:placetype": "postalcode"
  },
  "geometry": {"coordinates":[-2.838247,54.058485],"type":"Point"}
}
