{
  "type": "Feature",
  "properties": {
    "iso:country":"GB",
    "wof:name":"WF3 1BB",
    "wof:placetype":"postalcode"
},
  "geometry": {"coordinates":[-1.5816487719026,53.72260186689385],"type":"Point"}
}