{
  "type": "Feature",
  "properties": {
    "iso:country":"GB",
    "wof:name":"NW2 6SD",
    "wof:placetype":"postalcode"
},
  "geometry": {"coordinates":[-0.22069182562431,51.55896875018501],"type":"Point"}
}