{
  "type": "Feature",
  "properties": {
    "iso:country":"GB",
    "wof:name":"B12 9PS",
    "wof:placetype":"postalcode"
},
  "geometry": {"coordinates":[-1.89436611576525,52.45683805332987],"type":"Point"}
}