{
  "type": "Feature",
  "properties": {
    "iso:country": "GB",
    "wof:name": "YO23 2SA",
    "wof:placetype": "postalcode"
  },
  "geometry": {"coordinates":[-1.092455,53.919858],"type":"Point"}
}
