{
  "type": "Feature",
  "properties": {
    "iso:country":"GB",
    "wof:name":"YO23 2SA",
    "wof:placetype":"postalcode"
},
  "geometry": {"coordinates":[-1.09245478844885,53.91985831161693],"type":"Point"}
}