{
  "type": "Feature",
  "properties": {
    "iso:country":"GB",
    "wof:name":"NG4 3GJ",
    "wof:placetype":"postalcode"
},
  "geometry": {"coordinates":[-1.07330718853026,52.9735661518548],"type":"Point"}
}