{
  "type": "Feature",
  "properties": {
    "iso:country":"GB",
    "wof:name":"ST6 6NA",
    "wof:placetype":"postalcode"
},
  "geometry": {"coordinates":[-2.19805183908175,53.06656928357532],"type":"Point"}
}