{
  "type": "Feature",
  "properties": {
    "date:inception_lower": "2005-02-01",
    "date:inception_upper": "2005-02-01",
    "iso:country": "GB",
    "wof:name": "B60 9SQ",
    "wof:placetype": "postalcode"
  },
  "geometry": {"coordinates":[-2.050652,52.340372],"type":"Point"}
}
