{
  "type": "Feature",
  "properties": {
    "date:inception_lower": "1980-01-01",
    "date:inception_upper": "1980-01-01",
    "iso:country": "GB",
    "wof:name": "TA24 6RT",
    "wof:placetype": "postalcode"
  },
  "geometry": {"coordinates":[-3.44902,51.184301],"type":"Point"}
}
