{
  "type": "Feature",
  "properties": {
    "iso:country":"GB",
    "wof:name":"EX38 8DG",
    "wof:placetype":"postalcode"
},
  "geometry": {"coordinates":[-4.15339280817947,50.95300361974258],"type":"Point"}
}