{
  "type": "Feature",
  "properties": {
    "iso:country":"GB",
    "wof:name":"BS8 4JS",
    "wof:placetype":"postalcode"
},
  "geometry": {"coordinates":[-2.61924533790834,51.45425300318532],"type":"Point"}
}