{
  "type": "Feature",
  "properties": {
    "date:inception_lower": "1980-01-01",
    "date:inception_upper": "1980-01-01",
    "iso:country": "GB",
    "wof:name": "W11 4LH",
    "wof:placetype": "postalcode"
  },
  "geometry": {"coordinates":[-0.208555,51.507303],"type":"Point"}
}
