{
  "type": "Feature",
  "properties": {
    "iso:country":"GB",
    "wof:name":"W11 4LH",
    "wof:placetype":"postalcode"
},
  "geometry": {"coordinates":[-0.20855462888725,51.50730256775542],"type":"Point"}
}