{
  "type": "Feature",
  "properties": {
    "iso:country":"GB",
    "wof:name":"SR3 2TW",
    "wof:placetype":"postalcode"
},
  "geometry": {"coordinates":[-1.41844685368837,54.86803380134602],"type":"Point"}
}