{
  "type": "Feature",
  "properties": {
    "iso:country":"GB",
    "wof:name":"IP19 9HS",
    "wof:placetype":"postalcode"
},
  "geometry": {"coordinates":[1.51885754765657,52.31615587219056],"type":"Point"}
}