{
  "type": "Feature",
  "properties": {
    "date:inception_lower": "1980-01-01",
    "date:inception_upper": "1980-01-01",
    "iso:country": "GB",
    "wof:name": "SW3 6EH",
    "wof:placetype": "postalcode"
  },
  "geometry": {"coordinates":[-0.175608,51.489044],"type":"Point"}
}
