{
  "type": "Feature",
  "properties": {
    "iso:country":"GB",
    "wof:name":"SW3 6EH",
    "wof:placetype":"postalcode"
},
  "geometry": {"coordinates":[-0.17560754989868,51.48904352650586],"type":"Point"}
}