{
  "type": "Feature",
  "properties": {
    "iso:country": "GB",
    "wof:name": "TR11 5HP",
    "wof:placetype": "postalcode"
  },
  "geometry": {"coordinates":[-5.092474,50.121466],"type":"Point"}
}
