{
  "type": "Feature",
  "properties": {
    "iso:country":"GB",
    "wof:name":"TR11 5HP",
    "wof:placetype":"postalcode"
},
  "geometry": {"coordinates":[-5.09247384948881,50.12146614241779],"type":"Point"}
}