{
  "type": "Feature",
  "properties": {
    "iso:country":"GB",
    "wof:name":"G72 0DY",
    "wof:placetype":"postalcode"
},
  "geometry": {"coordinates":[-4.10284621000251,55.78432764711554],"type":"Point"}
}