{
  "type": "Feature",
  "properties": {
    "date:inception_lower":"1985-04-01",
    "date:inception_upper":"1985-04-30",
    "iso:country":"GB",
    "wof:name":"CB5 8UE",
    "wof:placetype":"postalcode"
},
  "geometry": {"coordinates":[0.171666,52.214779],"type":"Point"}
}