{
  "type": "Feature",
  "properties": {
    "iso:country": "GB",
    "wof:name": "CB5 8UE",
    "wof:placetype": "postalcode"
  },
  "geometry": {"coordinates":[0.171666,52.214779],"type":"Point"}
}
