{
  "type": "Feature",
  "properties": {
    "iso:country":"GB",
    "wof:name":"CB5 8UE",
    "wof:placetype":"postalcode"
},
  "geometry": {"coordinates":[0.17166633374604,52.21477873920254],"type":"Point"}
}