{
  "type": "Feature",
  "properties": {
    "iso:country":"GB",
    "wof:name":"BH19 1DZ",
    "wof:placetype":"postalcode"
},
  "geometry": {"coordinates":[-1.96225468114084,50.61117564116789],"type":"Point"}
}