{
  "type": "Feature",
  "properties": {
    "iso:country":"GB",
    "wof:name":"SY16 3LW",
    "wof:placetype":"postalcode"
},
  "geometry": {"coordinates":[-3.35026680546397,52.53927805414942],"type":"Point"}
}