{
  "type": "Feature",
  "properties": {
    "iso:country":"GB",
    "wof:name":"AB31 6PJ",
    "wof:placetype":"postalcode"
},
  "geometry": {"coordinates":[-2.64950620884005,57.00193677976058],"type":"Point"}
}