{
  "type": "Feature",
  "properties": {
    "date:inception_lower": "2024-03-01",
    "date:inception_upper": "2024-03-01",
    "iso:country": "GB",
    "wof:name": "MK42 6FW",
    "wof:placetype": "postalcode"
  },
  "geometry": {"coordinates":[-0.466559,52.083908],"type":"Point"}
}
