{
  "type": "Feature",
  "properties": {
    "iso:country":"GB",
    "wof:name":"M23 1HR",
    "wof:placetype":"postalcode"
},
  "geometry": {"coordinates":[-2.29212298854113,53.39773111447499],"type":"Point"}
}