{
  "type": "Feature",
  "properties": {
    "date:inception_lower":"1993-08-01",
    "date:inception_upper":"1993-08-31",
    "iso:country":"GB",
    "wof:name":"SY23 3YD",
    "wof:placetype":"postalcode"
},
  "geometry": {"coordinates":[-4.062706,52.400551],"type":"Point"}
}