{
  "type": "Feature",
  "properties": {
    "iso:country": "GB",
    "wof:name": "SY23 3YD",
    "wof:placetype": "postalcode"
  },
  "geometry": {"coordinates":[-4.062706,52.400551],"type":"Point"}
}
