{
  "type": "Feature",
  "properties": {
    "iso:country":"GB",
    "wof:name":"CR4 2LZ",
    "wof:placetype":"postalcode"
},
  "geometry": {"coordinates":[-0.15721103461988,51.40616803446424],"type":"Point"}
}