{
  "type": "Feature",
  "properties": {
    "date:inception_lower":"1980-01-01",
    "date:inception_upper":"1980-01-31",
    "iso:country":"GB",
    "wof:name":"BN25 4AB",
    "wof:placetype":"postalcode"
},
  "geometry": {"coordinates":[0.145043,50.773868],"type":"Point"}
}