{
  "type": "Feature",
  "properties": {
    "iso:country":"GB",
    "wof:name":"BN25 4AB",
    "wof:placetype":"postalcode"
},
  "geometry": {"coordinates":[0.14504326444293,50.77386822912936],"type":"Point"}
}