{
  "type": "Feature",
  "properties": {
    "iso:country":"GB",
    "wof:name":"HP18 0EP",
    "wof:placetype":"postalcode"
},
  "geometry": {"coordinates":[-0.91750793408869,51.82379541710613],"type":"Point"}
}