{
  "type": "Feature",
  "properties": {
    "date:inception_lower": "1991-09-01",
    "date:inception_upper": "1991-09-01",
    "iso:country": "GB",
    "wof:name": "BB4 6TP",
    "wof:placetype": "postalcode"
  },
  "geometry": {"coordinates":[-2.317394,53.700835],"type":"Point"}
}
