{
  "type": "Feature",
  "properties": {
    "iso:country":"GB",
    "wof:name":"CH7 5NP",
    "wof:placetype":"postalcode"
},
  "geometry": {"coordinates":[-3.23485270072805,53.19494270015073],"type":"Point"}
}