{
  "type": "Feature",
  "properties": {
    "iso:country":"GB",
    "wof:name":"W3 6QG",
    "wof:placetype":"postalcode"
},
  "geometry": {"coordinates":[-0.26208516800749,51.51418681660969],"type":"Point"}
}