{
  "type": "Feature",
  "properties": {
    "iso:country":"GB",
    "wof:name":"CH2 4AU",
    "wof:placetype":"postalcode"
},
  "geometry": {"coordinates":[-2.89775187180095,53.22466713625552],"type":"Point"}
}