{
  "type": "Feature",
  "properties": {
    "iso:country": "GB",
    "wof:name": "CH2 4AU",
    "wof:placetype": "postalcode"
  },
  "geometry": {"coordinates":[-2.897752,53.224667],"type":"Point"}
}
