{
  "type": "Feature",
  "properties": {
    "iso:country":"GB",
    "wof:name":"TN12 0EY",
    "wof:placetype":"postalcode"
},
  "geometry": {"coordinates":[0.54096697153709,51.14387186521476],"type":"Point"}
}