{
  "type": "Feature",
  "properties": {
    "iso:country":"GB",
    "wof:name":"CV47 2RQ",
    "wof:placetype":"postalcode"
},
  "geometry": {"coordinates":[-1.42669489678107,52.21589667298611],"type":"Point"}
}