{
  "type": "Feature",
  "properties": {
    "iso:country": "GB",
    "wof:name": "NG20 0FE",
    "wof:placetype": "postalcode"
  },
  "geometry": {"coordinates":[-1.156143,53.20759],"type":"Point"}
}
