{
  "type": "Feature",
  "properties": {
    "iso:country":"GB",
    "wof:name":"SE7 8TU",
    "wof:placetype":"postalcode"
},
  "geometry": {"coordinates":[0.03933116633148,51.48407254202085],"type":"Point"}
}