{
  "type": "Feature",
  "properties": {
    "iso:country": "GB",
    "wof:name": "HP2 4NZ",
    "wof:placetype": "postalcode"
  },
  "geometry": {"coordinates":[-0.430134,51.753451],"type":"Point"}
}
