{
  "type": "Feature",
  "properties": {
    "iso:country": "GB",
    "wof:name": "ME13 8XR",
    "wof:placetype": "postalcode"
  },
  "geometry": {"coordinates":[0.88823,51.307572],"type":"Point"}
}
