{
  "type": "Feature",
  "properties": {
    "iso:country":"GB",
    "wof:name":"ME13 8XR",
    "wof:placetype":"postalcode"
},
  "geometry": {"coordinates":[0.88823030902026,51.30757220295514],"type":"Point"}
}