{
  "type": "Feature",
  "properties": {
    "date:inception_lower": "1992-08-01",
    "date:inception_upper": "1992-08-01",
    "iso:country": "GB",
    "wof:name": "ME13 8XR",
    "wof:placetype": "postalcode"
  },
  "geometry": {"coordinates":[0.88823,51.307572],"type":"Point"}
}
