{
  "type": "Feature",
  "properties": {
    "iso:country": "GB",
    "wof:name": "PO22 6LW",
    "wof:placetype": "postalcode"
  },
  "geometry": {"coordinates":[-0.605768,50.795225],"type":"Point"}
}
