{
  "type": "Feature",
  "properties": {
    "iso:country":"GB",
    "wof:name":"PO22 6LW",
    "wof:placetype":"postalcode"
},
  "geometry": {"coordinates":[-0.60576782032569,50.79522478460488],"type":"Point"}
}