{
  "type": "Feature",
  "properties": {
    "date:inception_lower": "1980-01-01",
    "date:inception_upper": "1980-01-01",
    "iso:country": "GB",
    "wof:name": "PO22 6LW",
    "wof:placetype": "postalcode"
  },
  "geometry": {"coordinates":[-0.605768,50.795225],"type":"Point"}
}
