{
  "type": "Feature",
  "properties": {
    "iso:country":"GB",
    "wof:name":"HX2 6AT",
    "wof:placetype":"postalcode"
},
  "geometry": {"coordinates":[-1.94030650907916,53.71722255243422],"type":"Point"}
}