{
  "type": "Feature",
  "properties": {
    "iso:country": "GB",
    "wof:name": "SY1 4PD",
    "wof:placetype": "postalcode"
  },
  "geometry": {"coordinates":[-2.721416,52.735359],"type":"Point"}
}
