{
  "type": "Feature",
  "properties": {
    "iso:country": "GB",
    "wof:name": "CV32 7TG",
    "wof:placetype": "postalcode"
  },
  "geometry": {"coordinates":[-1.516052,52.313273],"type":"Point"}
}
