{
  "type": "Feature",
  "properties": {
    "iso:country": "GB",
    "wof:name": "TS10 2UL",
    "wof:placetype": "postalcode"
  },
  "geometry": {"coordinates":[-1.043771,54.592984],"type":"Point"}
}
