{
  "type": "Feature",
  "properties": {
    "iso:country":"GB",
    "wof:name":"S41 0GF",
    "wof:placetype":"postalcode"
},
  "geometry": {"coordinates":[-1.41827024141775,53.23399372988233],"type":"Point"}
}