{
  "type": "Feature",
  "properties": {
    "iso:country": "GB",
    "wof:name": "S41 0GF",
    "wof:placetype": "postalcode"
  },
  "geometry": {"coordinates":[-1.418283,53.234012],"type":"Point"}
}
