{
  "type": "Feature",
  "properties": {
    "iso:country":"GB",
    "wof:name":"LL18 2PP",
    "wof:placetype":"postalcode"
},
  "geometry": {"coordinates":[-3.47385798934509,53.3142232401382],"type":"Point"}
}