{
  "type": "Feature",
  "properties": {
    "iso:country":"GB",
    "wof:name":"G32 6HZ",
    "wof:placetype":"postalcode"
},
  "geometry": {"coordinates":[-4.18758527483763,55.86172134448694],"type":"Point"}
}