{
  "type": "Feature",
  "properties": {
    "iso:country": "GB",
    "wof:name": "G32 6HZ",
    "wof:placetype": "postalcode"
  },
  "geometry": {"coordinates":[-4.187585,55.861721],"type":"Point"}
}
