{
  "type": "Feature",
  "properties": {
    "iso:country": "GB",
    "wof:name": "YO8 5RD",
    "wof:placetype": "postalcode"
  },
  "geometry": {"coordinates":[-0.959388,53.825544],"type":"Point"}
}
