{
  "type": "Feature",
  "properties": {
    "iso:country":"GB",
    "wof:name":"YO8 5RD",
    "wof:placetype":"postalcode"
},
  "geometry": {"coordinates":[-0.95938788465707,53.82554367019885],"type":"Point"}
}