{
  "type": "Feature",
  "properties": {
    "date:inception_lower":"1999-12-01",
    "date:inception_upper":"1999-12-31",
    "iso:country":"GB",
    "wof:name":"YO8 5RD",
    "wof:placetype":"postalcode"
},
  "geometry": {"coordinates":[-0.959388,53.825544],"type":"Point"}
}