{
  "type": "Feature",
  "properties": {
    "iso:country":"GB",
    "wof:name":"CO2 8XS",
    "wof:placetype":"postalcode"
},
  "geometry": {"coordinates":[0.91021426083942,51.86578692376805],"type":"Point"}
}