{
  "type": "Feature",
  "properties": {
    "iso:country": "GB",
    "wof:name": "CO2 8XS",
    "wof:placetype": "postalcode"
  },
  "geometry": {"coordinates":[0.910214,51.865787],"type":"Point"}
}
