{
  "type": "Feature",
  "properties": {
    "date:inception_lower":"1995-12-01",
    "date:inception_upper":"1995-12-31",
    "iso:country":"GB",
    "wof:name":"SN8 3TY",
    "wof:placetype":"postalcode"
},
  "geometry": {"coordinates":[-1.666429,51.346536],"type":"Point"}
}