{
  "type": "Feature",
  "properties": {
    "iso:country": "GB",
    "wof:name": "SN8 3TY",
    "wof:placetype": "postalcode"
  },
  "geometry": {"coordinates":[-1.666429,51.346536],"type":"Point"}
}
