{
  "type": "Feature",
  "properties": {
    "iso:country":"GB",
    "wof:name":"SN8 3TY",
    "wof:placetype":"postalcode"
},
  "geometry": {"coordinates":[-1.66642866678103,51.34653597051852],"type":"Point"}
}