{
  "type": "Feature",
  "properties": {
    "iso:country":"GB",
    "wof:name":"NG4 2NF",
    "wof:placetype":"postalcode"
},
  "geometry": {"coordinates":[-1.07280357296758,52.96787185296348],"type":"Point"}
}