{
  "type": "Feature",
  "properties": {
    "iso:country": "GB",
    "wof:name": "NE28 9QX",
    "wof:placetype": "postalcode"
  },
  "geometry": {"coordinates":[-1.517928,55.010822],"type":"Point"}
}
