{
  "type": "Feature",
  "properties": {
    "iso:country": "GB",
    "wof:name": "LN6 7ND",
    "wof:placetype": "postalcode"
  },
  "geometry": {"coordinates":[-0.570694,53.207985],"type":"Point"}
}
