{
  "type": "Feature",
  "properties": {
    "iso:country":"GB",
    "wof:name":"BR7 5LX",
    "wof:placetype":"postalcode"
},
  "geometry": {"coordinates":[0.06844385855749,51.41474032126656],"type":"Point"}
}