{
  "type": "Feature",
  "properties": {
    "iso:country": "GB",
    "wof:name": "BR7 5LX",
    "wof:placetype": "postalcode"
  },
  "geometry": {"coordinates":[0.068444,51.41474],"type":"Point"}
}
