{
  "type": "Feature",
  "properties": {
    "iso:country":"GB",
    "wof:name":"B37 5SD",
    "wof:placetype":"postalcode"
},
  "geometry": {"coordinates":[-1.73931464388172,52.47671794374894],"type":"Point"}
}