{
  "type": "Feature",
  "properties": {
    "iso:country": "GB",
    "wof:name": "B37 5SD",
    "wof:placetype": "postalcode"
  },
  "geometry": {"coordinates":[-1.739315,52.476718],"type":"Point"}
}
