{
  "type": "Feature",
  "properties": {
    "iso:country":"GB",
    "wof:name":"SK17 0BT",
    "wof:placetype":"postalcode"
},
  "geometry": {"coordinates":[-1.86732487006645,53.20125267169705],"type":"Point"}
}