{
  "type": "Feature",
  "properties": {
    "iso:country": "GB",
    "wof:name": "SK17 0BT",
    "wof:placetype": "postalcode"
  },
  "geometry": {"coordinates":[-1.867325,53.201253],"type":"Point"}
}
