{
  "type": "Feature",
  "properties": {
    "date:inception_lower": "2023-10-01",
    "date:inception_upper": "2023-10-01",
    "iso:country": "GB",
    "wof:name": "S35 9AJ",
    "wof:placetype": "postalcode"
  },
  "geometry": {"coordinates":[-1.465476,53.446789],"type":"Point"}
}
