{
  "type": "Feature",
  "properties": {
    "iso:country":"GB",
    "wof:name":"LU6 2HL",
    "wof:placetype":"postalcode"
},
  "geometry": {"coordinates":[-0.58397481807092,51.86469840389478],"type":"Point"}
}