{
  "type": "Feature",
  "properties": {
    "iso:country": "GB",
    "wof:name": "LU6 2HL",
    "wof:placetype": "postalcode"
  },
  "geometry": {"coordinates":[-0.583975,51.864698],"type":"Point"}
}
