{
  "type": "Feature",
  "properties": {
    "date:inception_lower": "1980-01-01",
    "date:inception_upper": "1980-01-01",
    "iso:country": "GB",
    "wof:name": "LU6 2HL",
    "wof:placetype": "postalcode"
  },
  "geometry": {"coordinates":[-0.583975,51.864698],"type":"Point"}
}
