{
  "type": "Feature",
  "properties": {
    "iso:country":"GB",
    "wof:name":"CF63 4JN",
    "wof:placetype":"postalcode"
},
  "geometry": {"coordinates":[-3.26753356744458,51.40353523833144],"type":"Point"}
}