{
  "type": "Feature",
  "properties": {
    "date:inception_lower": "1993-08-01",
    "date:inception_upper": "1993-08-01",
    "iso:country": "GB",
    "wof:name": "CF63 4JN",
    "wof:placetype": "postalcode"
  },
  "geometry": {"coordinates":[-3.2675,51.403499],"type":"Point"}
}
