{
  "type": "Feature",
  "properties": {
    "iso:country":"GB",
    "wof:name":"B94 6JU",
    "wof:placetype":"postalcode"
},
  "geometry": {"coordinates":[-1.73605869039219,52.33901847613637],"type":"Point"}
}