{
  "type": "Feature",
  "properties": {
    "iso:country": "GB",
    "wof:name": "B94 6JU",
    "wof:placetype": "postalcode"
  },
  "geometry": {"coordinates":[-1.735995,52.338215],"type":"Point"}
}
