{
  "type": "Feature",
  "properties": {
    "date:inception_lower": "1992-01-01",
    "date:inception_upper": "1992-01-01",
    "iso:country": "GB",
    "wof:name": "B50 4NU",
    "wof:placetype": "postalcode"
  },
  "geometry": {"coordinates":[-1.860755,52.149089],"type":"Point"}
}
