{
  "type": "Feature",
  "properties": {
    "iso:country":"GB",
    "wof:name":"NG24 4LD",
    "wof:placetype":"postalcode"
},
  "geometry": {"coordinates":[-0.8084902187582,53.05935111810523],"type":"Point"}
}