{
  "type": "Feature",
  "properties": {
    "iso:country": "GB",
    "wof:name": "E14 8FA",
    "wof:placetype": "postalcode"
  },
  "geometry": {"coordinates":[-0.023424,51.499753],"type":"Point"}
}
