{
  "type": "Feature",
  "properties": {
    "iso:country":"GB",
    "wof:name":"W12 7EE",
    "wof:placetype":"postalcode"
},
  "geometry": {"coordinates":[-0.22572569124193,51.51152923792652],"type":"Point"}
}