{
  "type": "Feature",
  "properties": {
    "date:inception_lower": "2017-06-01",
    "date:inception_upper": "2017-06-01",
    "iso:country": "GB",
    "wof:name": "IP28 6RY",
    "wof:placetype": "postalcode"
  },
  "geometry": {"coordinates":[0.636554,52.264403],"type":"Point"}
}
