{
  "type": "Feature",
  "properties": {
    "iso:country":"GB",
    "wof:name":"EX8 5AB",
    "wof:placetype":"postalcode"
},
  "geometry": {"coordinates":[-3.42061457804174,50.6428157018909],"type":"Point"}
}