{
  "type": "Feature",
  "properties": {
    "iso:country": "GB",
    "wof:name": "EX8 5AB",
    "wof:placetype": "postalcode"
  },
  "geometry": {"coordinates":[-3.420677,50.64302],"type":"Point"}
}
