{
  "type": "Feature",
  "properties": {
    "date:inception_lower": "2021-07-01",
    "date:inception_upper": "2021-07-01",
    "iso:country": "GB",
    "wof:name": "BA5 1GQ",
    "wof:placetype": "postalcode"
  },
  "geometry": {"coordinates":[-2.666791,51.211279],"type":"Point"}
}
