{
  "type": "Feature",
  "properties": {
    "iso:country":"GB",
    "wof:name":"FK9 5AF",
    "wof:placetype":"postalcode"
},
  "geometry": {"coordinates":[-3.93568553736037,56.13457896656349],"type":"Point"}
}