{
  "type": "Feature",
  "properties": {
    "date:inception_lower": "2005-06-01",
    "date:inception_upper": "2005-06-01",
    "iso:country": "GB",
    "wof:name": "FK9 5AF",
    "wof:placetype": "postalcode"
  },
  "geometry": {"coordinates":[-3.935646,56.134564],"type":"Point"}
}
