{
  "type": "Feature",
  "properties": {
    "iso:country":"GB",
    "wof:name":"G62 8NT",
    "wof:placetype":"postalcode"
},
  "geometry": {"coordinates":[-4.31968644072163,55.94560865529731],"type":"Point"}
}