{
  "type": "Feature",
  "properties": {
    "iso:country": "GB",
    "wof:name": "G62 8NT",
    "wof:placetype": "postalcode"
  },
  "geometry": {"coordinates":[-4.319686,55.945609],"type":"Point"}
}
