{
  "type": "Feature",
  "properties": {
    "iso:country":"GB",
    "wof:name":"M43 7LP",
    "wof:placetype":"postalcode"
},
  "geometry": {"coordinates":[-2.13366724200821,53.49187184362658],"type":"Point"}
}