{
  "type": "Feature",
  "properties": {
    "iso:country":"GB",
    "wof:name":"BD4 6RX",
    "wof:placetype":"postalcode"
},
  "geometry": {"coordinates":[-1.74076925050382,53.75774533040908],"type":"Point"}
}