{
  "type": "Feature",
  "properties": {
    "date:inception_lower": "1984-10-01",
    "date:inception_upper": "1984-10-01",
    "iso:country": "GB",
    "wof:name": "BD4 6RX",
    "wof:placetype": "postalcode"
  },
  "geometry": {"coordinates":[-1.740769,53.757745],"type":"Point"}
}
