{
  "type": "Feature",
  "properties": {
    "iso:country":"GB",
    "wof:name":"BH15 1QX",
    "wof:placetype":"postalcode"
},
  "geometry": {"coordinates":[-1.98030297794234,50.7128522097322],"type":"Point"}
}