{
  "type": "Feature",
  "properties": {
    "iso:country": "GB",
    "wof:name": "HX3 6EZ",
    "wof:placetype": "postalcode"
  },
  "geometry": {"coordinates":[-1.865583,53.733278],"type":"Point"}
}
