{
  "type": "Feature",
  "properties": {
    "date:inception_lower":"1992-08-01",
    "date:inception_upper":"1992-08-31",
    "iso:country":"GB",
    "wof:name":"HX3 6EZ",
    "wof:placetype":"postalcode"
},
  "geometry": {"coordinates":[-1.865583,53.733278],"type":"Point"}
}