{
  "type": "Feature",
  "properties": {
    "iso:country": "GB",
    "wof:name": "FY6 8DZ",
    "wof:placetype": "postalcode"
  },
  "geometry": {"coordinates":[-2.989183,53.842738],"type":"Point"}
}
