{
  "type": "Feature",
  "properties": {
    "iso:country":"GB",
    "wof:name":"FY6 8DZ",
    "wof:placetype":"postalcode"
},
  "geometry": {"coordinates":[-2.98918302385252,53.84273752409783],"type":"Point"}
}