{
  "type": "Feature",
  "properties": {
    "date:inception_lower": "1991-01-01",
    "date:inception_upper": "1991-01-01",
    "iso:country": "GB",
    "wof:name": "SW18 4BG",
    "wof:placetype": "postalcode"
  },
  "geometry": {"coordinates":[-0.195572,51.449992],"type":"Point"}
}
