{
  "type": "Feature",
  "properties": {
    "date:inception_lower":"1980-01-01",
    "date:inception_upper":"1980-01-31",
    "iso:country":"GB",
    "wof:name":"RH1 4AF",
    "wof:placetype":"postalcode"
},
  "geometry": {"coordinates":[-0.162709,51.240113],"type":"Point"}
}