{
  "type": "Feature",
  "properties": {
    "iso:country":"GB",
    "wof:name":"RH1 4AF",
    "wof:placetype":"postalcode"
},
  "geometry": {"coordinates":[-0.16270858737611,51.24011339358572],"type":"Point"}
}