{
  "type": "Feature",
  "properties": {
    "date:inception_lower": "2019-06-01",
    "date:inception_upper": "2019-06-01",
    "iso:country": "GB",
    "wof:name": "CM3 1FN",
    "wof:placetype": "postalcode"
  },
  "geometry": {"coordinates":[0.511813,51.831725],"type":"Point"}
}
