{
  "type": "Feature",
  "properties": {
    "date:inception_lower": "2023-08-01",
    "date:inception_upper": "2023-08-01",
    "iso:country": "GB",
    "wof:name": "IG3 8DA",
    "wof:placetype": "postalcode"
  },
  "geometry": {"coordinates":[0.097821,51.563114],"type":"Point"}
}
