{
  "type": "Feature",
  "properties": {
    "iso:country": "GB",
    "wof:name": "SW19 2BX",
    "wof:placetype": "postalcode"
  },
  "geometry": {"coordinates":[-0.176864,51.420675],"type":"Point"}
}
