{
  "type": "Feature",
  "properties": {
    "date:inception_lower": "1980-01-01",
    "date:inception_upper": "1980-01-01",
    "iso:country": "GB",
    "wof:name": "SS17 7JW",
    "wof:placetype": "postalcode"
  },
  "geometry": {"coordinates":[0.449615,51.526724],"type":"Point"}
}
