{
  "type": "Feature",
  "properties": {
    "date:inception_lower": "1980-01-01",
    "date:inception_upper": "1980-01-01",
    "iso:country": "GB",
    "wof:name": "SY7 8AJ",
    "wof:placetype": "postalcode"
  },
  "geometry": {"coordinates":[-2.925046,52.482679],"type":"Point"}
}
