{
  "type": "Feature",
  "properties": {
    "iso:country": "GB",
    "wof:name": "SY7 8AJ",
    "wof:placetype": "postalcode"
  },
  "geometry": {"coordinates":[-2.92487,52.482698],"type":"Point"}
}
