{
  "type": "Feature",
  "properties": {
    "iso:country":"GB",
    "wof:name":"SY7 8AJ",
    "wof:placetype":"postalcode"
},
  "geometry": {"coordinates":[-2.92491728288832,52.48269190941762],"type":"Point"}
}