{
  "type": "Feature",
  "properties": {
    "iso:country":"GB",
    "wof:name":"TS10 2BS",
    "wof:placetype":"postalcode"
},
  "geometry": {"coordinates":[-1.06111302139274,54.61280661112527],"type":"Point"}
}