{
  "type": "Feature",
  "properties": {
    "iso:country":"GB",
    "wof:name":"OX29 7US",
    "wof:placetype":"postalcode"
},
  "geometry": {"coordinates":[-1.4830119165246,51.76465685065046],"type":"Point"}
}