{
  "type": "Feature",
  "properties": {
    "iso:country":"GB",
    "wof:name":"GU31 4PU",
    "wof:placetype":"postalcode"
},
  "geometry": {"coordinates":[-0.92658830883203,51.00530594874814],"type":"Point"}
}