{
  "type": "Feature",
  "properties": {
    "iso:country": "GB",
    "wof:name": "GU31 4PU",
    "wof:placetype": "postalcode"
  },
  "geometry": {"coordinates":[-0.926588,51.005306],"type":"Point"}
}
