{
  "type": "Feature",
  "properties": {
    "iso:country":"GB",
    "wof:name":"HS2 9QE",
    "wof:placetype":"postalcode"
},
  "geometry": {"coordinates":[-6.47073436321827,58.09007287806494],"type":"Point"}
}