{
  "type": "Feature",
  "properties": {
    "iso:country":"GB",
    "wof:name":"CB25 9NP",
    "wof:placetype":"postalcode"
},
  "geometry": {"coordinates":[0.18556292969064,52.2646433011906],"type":"Point"}
}