{
  "type": "Feature",
  "properties": {
    "iso:country": "GB",
    "wof:name": "OL2 7XJ",
    "wof:placetype": "postalcode"
  },
  "geometry": {"coordinates":[-2.099461,53.584935],"type":"Point"}
}
