{
  "type": "Feature",
  "properties": {
    "iso:country": "GB",
    "wof:name": "LE5 0UD",
    "wof:placetype": "postalcode"
  },
  "geometry": {"coordinates":[-1.090847,52.650772],"type":"Point"}
}
