{
  "type": "Feature",
  "properties": {
    "date:inception_lower":"2015-02-01",
    "date:inception_upper":"2015-02-28",
    "iso:country":"GB",
    "wof:name":"LE5 0UD",
    "wof:placetype":"postalcode"
},
  "geometry": {"coordinates":[-1.090847,52.650772],"type":"Point"}
}