{
  "type": "Feature",
  "properties": {
    "iso:country":"GB",
    "wof:name":"LE5 0UD",
    "wof:placetype":"postalcode"
},
  "geometry": {"coordinates":[-1.090846894128,52.65077160312445],"type":"Point"}
}