{
  "type": "Feature",
  "properties": {
    "date:inception_lower": "2023-01-01",
    "date:inception_upper": "2023-01-01",
    "iso:country": "GB",
    "wof:name": "S43 3FT",
    "wof:placetype": "postalcode"
  },
  "geometry": {"coordinates":[-1.336226,53.258485],"type":"Point"}
}
