{
  "type": "Feature",
  "properties": {
    "iso:country":"GB",
    "wof:name":"PO22 8LL",
    "wof:placetype":"postalcode"
},
  "geometry": {"coordinates":[-0.63832497391519,50.79791155054792],"type":"Point"}
}