{
  "type": "Feature",
  "properties": {
    "iso:country":"GB",
    "wof:name":"CH8 9SJ",
    "wof:placetype":"postalcode"
},
  "geometry": {"coordinates":[-3.29339192336954,53.32842555974283],"type":"Point"}
}