{
  "type": "Feature",
  "properties": {
    "iso:country": "GB",
    "wof:name": "PE8 5AD",
    "wof:placetype": "postalcode"
  },
  "geometry": {"coordinates":[-0.534391,52.486368],"type":"Point"}
}
