{
  "type": "Feature",
  "properties": {
    "iso:country":"GB",
    "wof:name":"LL59 5HD",
    "wof:placetype":"postalcode"
},
  "geometry": {"coordinates":[-4.1664900532205,53.22179110108408],"type":"Point"}
}