{
  "type": "Feature",
  "properties": {
    "date:inception_lower": "1980-01-01",
    "date:inception_upper": "1980-01-01",
    "iso:country": "GB",
    "wof:name": "LL59 5HD",
    "wof:placetype": "postalcode"
  },
  "geometry": {"coordinates":[-4.16649,53.221791],"type":"Point"}
}
