{
  "type": "Feature",
  "properties": {
    "iso:country":"GB",
    "wof:name":"PA4 8FJ",
    "wof:placetype":"postalcode"
},
  "geometry": {"coordinates":[-4.38328792325678,55.88385313673081],"type":"Point"}
}