{
  "type": "Feature",
  "properties": {
    "iso:country": "GB",
    "wof:name": "PA4 8FJ",
    "wof:placetype": "postalcode"
  },
  "geometry": {"coordinates":[-4.383301,55.883523],"type":"Point"}
}
