{
  "type": "Feature",
  "properties": {
    "date:inception_lower": "2000-06-01",
    "date:inception_upper": "2000-06-01",
    "iso:country": "GB",
    "wof:name": "PE27 3LQ",
    "wof:placetype": "postalcode"
  },
  "geometry": {"coordinates":[-0.061323,52.338344],"type":"Point"}
}
