{
  "type": "Feature",
  "properties": {
    "iso:country":"GB",
    "wof:name":"PA8 7WF",
    "wof:placetype":"postalcode"
},
  "geometry": {"coordinates":[-4.45456041801314,55.90539804690258],"type":"Point"}
}