{
  "type": "Feature",
  "properties": {
    "date:inception_lower": "1999-06-01",
    "date:inception_upper": "1999-06-01",
    "iso:country": "GB",
    "wof:name": "DN19 7TZ",
    "wof:placetype": "postalcode"
  },
  "geometry": {"coordinates":[-0.334912,53.675493],"type":"Point"}
}
