{
  "type": "Feature",
  "properties": {
    "iso:country":"GB",
    "wof:name":"PL12 4UB",
    "wof:placetype":"postalcode"
},
  "geometry": {"coordinates":[-4.23988976827552,50.41057075004093],"type":"Point"}
}