{
  "type": "Feature",
  "properties": {
    "iso:country": "GB",
    "wof:name": "PL12 4UB",
    "wof:placetype": "postalcode"
  },
  "geometry": {"coordinates":[-4.23989,50.410571],"type":"Point"}
}
