{
  "type": "Feature",
  "properties": {
    "date:inception_lower": "2020-10-01",
    "date:inception_upper": "2020-10-01",
    "iso:country": "GB",
    "wof:name": "CT16 3GZ",
    "wof:placetype": "postalcode"
  },
  "geometry": {"coordinates":[1.305205,51.160637],"type":"Point"}
}
