{
  "type": "Feature",
  "properties": {
    "iso:country":"GB",
    "wof:name":"L32 8TH",
    "wof:placetype":"postalcode"
},
  "geometry": {"coordinates":[-2.87623572898595,53.47845900697796],"type":"Point"}
}