{
  "type": "Feature",
  "properties": {
    "iso:country":"GB",
    "wof:name":"CB10 1PL",
    "wof:placetype":"postalcode"
},
  "geometry": {"coordinates":[0.20273422817892,52.06382766237142],"type":"Point"}
}