{
  "type": "Feature",
  "properties": {
    "iso:country":"GB",
    "wof:name":"N17 7AN",
    "wof:placetype":"postalcode"
},
  "geometry": {"coordinates":[-0.0818457176509,51.60229199504857],"type":"Point"}
}