{
  "type": "Feature",
  "properties": {
    "iso:country":"GB",
    "wof:name":"SA11 1DB",
    "wof:placetype":"postalcode"
},
  "geometry": {"coordinates":[-3.80590571067759,51.66242443624679],"type":"Point"}
}