{
  "type": "Feature",
  "properties": {
    "date:inception_lower":"1998-06-01",
    "date:inception_upper":"1998-06-30",
    "iso:country":"GB",
    "wof:name":"SA11 1DB",
    "wof:placetype":"postalcode"
},
  "geometry": {"coordinates":[-3.805906,51.662424],"type":"Point"}
}