{
  "type": "Feature",
  "properties": {
    "iso:country":"GB",
    "wof:name":"WD3 4ES",
    "wof:placetype":"postalcode"
},
  "geometry": {"coordinates":[-0.48509189837668,51.65318459267161],"type":"Point"}
}