{
  "type": "Feature",
  "properties": {
    "iso:country":"GB",
    "wof:name":"TS6 9LE",
    "wof:placetype":"postalcode"
},
  "geometry": {"coordinates":[-1.13263823268222,54.56015426778654],"type":"Point"}
}