{
  "type": "Feature",
  "properties": {
    "iso:country":"GB",
    "wof:name":"S63 0RY",
    "wof:placetype":"postalcode"
},
  "geometry": {"coordinates":[-1.32464074166704,53.54908624302023],"type":"Point"}
}