{
  "type": "Feature",
  "properties": {
    "date:inception_lower": "1980-01-01",
    "date:inception_upper": "1980-01-01",
    "iso:country": "GB",
    "wof:name": "PH2 0PJ",
    "wof:placetype": "postalcode"
  },
  "geometry": {"coordinates":[-3.469934,56.388925],"type":"Point"}
}
