{
  "type": "Feature",
  "properties": {
    "iso:country":"GB",
    "wof:name":"PH2 0PJ",
    "wof:placetype":"postalcode"
},
  "geometry": {"coordinates":[-3.46993428274345,56.38892550130129],"type":"Point"}
}