{
  "type": "Feature",
  "properties": {
    "iso:country":"GB",
    "wof:name":"SA31 2EP",
    "wof:placetype":"postalcode"
},
  "geometry": {"coordinates":[-4.29286058675646,51.86416442023301],"type":"Point"}
}