{
  "type": "Feature",
  "properties": {
    "iso:country":"GB",
    "wof:name":"SE5 7LE",
    "wof:placetype":"postalcode"
},
  "geometry": {"coordinates":[-0.09208444752531,51.47746276274268],"type":"Point"}
}