{
  "type": "Feature",
  "properties": {
    "iso:country":"GB",
    "wof:name":"SN14 8ES",
    "wof:placetype":"postalcode"
},
  "geometry": {"coordinates":[-2.37594791609289,51.47842132592314],"type":"Point"}
}