{
  "type": "Feature",
  "properties": {
    "date:inception_lower": "1995-07-01",
    "date:inception_upper": "1995-07-01",
    "iso:country": "GB",
    "wof:name": "CM7 3QL",
    "wof:placetype": "postalcode"
  },
  "geometry": {"coordinates":[0.556079,51.875691],"type":"Point"}
}
