{
  "type": "Feature",
  "properties": {
    "iso:country": "GB",
    "wof:name": "CM7 3QL",
    "wof:placetype": "postalcode"
  },
  "geometry": {"coordinates":[0.556079,51.875691],"type":"Point"}
}
