{
  "type": "Feature",
  "properties": {
    "date:inception_lower": "2002-09-01",
    "date:inception_upper": "2002-09-01",
    "iso:country": "GB",
    "wof:name": "M15 6HE",
    "wof:placetype": "postalcode"
  },
  "geometry": {"coordinates":[-2.244013,53.468516],"type":"Point"}
}
