{
  "type": "Feature",
  "properties": {
    "iso:country": "GB",
    "wof:name": "GU31 4EB",
    "wof:placetype": "postalcode"
  },
  "geometry": {"coordinates":[-0.931718,51.004759],"type":"Point"}
}
