{
  "type": "Feature",
  "properties": {
    "iso:country":"GB",
    "wof:name":"GU31 4EB",
    "wof:placetype":"postalcode"
},
  "geometry": {"coordinates":[-0.93171765360568,51.00475944272717],"type":"Point"}
}