{
  "type": "Feature",
  "properties": {
    "date:inception_lower": "1986-01-01",
    "date:inception_upper": "1986-01-01",
    "iso:country": "GB",
    "wof:name": "SO41 5QX",
    "wof:placetype": "postalcode"
  },
  "geometry": {"coordinates":[-1.523225,50.781798],"type":"Point"}
}
