{
  "type": "Feature",
  "properties": {
    "date:inception_lower": "1980-01-01",
    "date:inception_upper": "1980-01-01",
    "iso:country": "GB",
    "wof:name": "HG5 9ET",
    "wof:placetype": "postalcode"
  },
  "geometry": {"coordinates":[-1.466304,54.018412],"type":"Point"}
}
