{
  "type": "Feature",
  "properties": {
    "iso:country": "GB",
    "wof:name": "WF3 1QY",
    "wof:placetype": "postalcode"
  },
  "geometry": {"coordinates":[-1.566781,53.733056],"type":"Point"}
}
