{
  "type": "Feature",
  "properties": {
    "iso:country":"GB",
    "wof:name":"DD3 9JF",
    "wof:placetype":"postalcode"
},
  "geometry": {"coordinates":[-3.01339380374572,56.4924716318136],"type":"Point"}
}