{
  "type": "Feature",
  "properties": {
    "iso:country":"GB",
    "wof:name":"NG16 2WJ",
    "wof:placetype":"postalcode"
},
  "geometry": {"coordinates":[-1.28813299714435,53.0054122617052],"type":"Point"}
}