{
  "type": "Feature",
  "properties": {
    "iso:country":"GB",
    "wof:name":"M45 8LA",
    "wof:placetype":"postalcode"
},
  "geometry": {"coordinates":[-2.27569777012687,53.55292023664839],"type":"Point"}
}