{
  "type": "Feature",
  "properties": {
    "date:inception_lower": "2002-11-01",
    "date:inception_upper": "2002-11-01",
    "iso:country": "GB",
    "wof:name": "OX12 9BN",
    "wof:placetype": "postalcode"
  },
  "geometry": {"coordinates":[-1.425831,51.598765],"type":"Point"}
}
