{
  "type": "Feature",
  "properties": {
    "iso:country": "GB",
    "wof:name": "OX12 9BN",
    "wof:placetype": "postalcode"
  },
  "geometry": {"coordinates":[-1.425847,51.598763],"type":"Point"}
}
