{
  "type": "Feature",
  "properties": {
    "iso:country":"GB",
    "wof:name":"OX12 9BN",
    "wof:placetype":"postalcode"
},
  "geometry": {"coordinates":[-1.42584729382091,51.59876317445093],"type":"Point"}
}