{
  "type": "Feature",
  "properties": {
    "date:inception_lower": "1992-01-01",
    "date:inception_upper": "1992-01-01",
    "iso:country": "GB",
    "wof:name": "DN35 7PJ",
    "wof:placetype": "postalcode"
  },
  "geometry": {"coordinates":[-0.054961,53.569904],"type":"Point"}
}
