{
  "type": "Feature",
  "properties": {
    "iso:country":"GB",
    "wof:name":"ST13 5PF",
    "wof:placetype":"postalcode"
},
  "geometry": {"coordinates":[-2.02736643711091,53.10234588424363],"type":"Point"}
}