{
  "type": "Feature",
  "properties": {
    "iso:country":"GB",
    "wof:name":"NG16 5FF",
    "wof:placetype":"postalcode"
},
  "geometry": {"coordinates":[-1.29057018567409,53.05309712952118],"type":"Point"}
}