{
  "type": "Feature",
  "properties": {
    "date:inception_lower":"2012-07-01",
    "date:inception_upper":"2012-07-31",
    "iso:country":"GB",
    "wof:name":"TR15 3FD",
    "wof:placetype":"postalcode"
},
  "geometry": {"coordinates":[-5.271171,50.225841],"type":"Point"}
}