{
  "type": "Feature",
  "properties": {
    "date:inception_lower": "1999-06-01",
    "date:inception_upper": "1999-06-01",
    "iso:country": "GB",
    "wof:name": "NP19 4LX",
    "wof:placetype": "postalcode"
  },
  "geometry": {"coordinates":[-2.955457,51.582293],"type":"Point"}
}
