{
  "type": "Feature",
  "properties": {
    "date:inception_lower": "1980-01-01",
    "date:inception_upper": "1980-01-01",
    "iso:country": "GB",
    "wof:name": "DY8 5AS",
    "wof:placetype": "postalcode"
  },
  "geometry": {"coordinates":[-2.164521,52.475816],"type":"Point"}
}
