{
  "type": "Feature",
  "properties": {
    "iso:country":"GB",
    "wof:name":"BA1 1LF",
    "wof:placetype":"postalcode"
},
  "geometry": {"coordinates":[-2.35748631667387,51.38060540526569],"type":"Point"}
}