{
  "type": "Feature",
  "properties": {
    "iso:country":"GB",
    "wof:name":"CV31 2DL",
    "wof:placetype":"postalcode"
},
  "geometry": {"coordinates":[-1.53207154240005,52.283528427969],"type":"Point"}
}