{
  "type": "Feature",
  "properties": {
    "iso:country": "GB",
    "wof:name": "CV31 2DL",
    "wof:placetype": "postalcode"
  },
  "geometry": {"coordinates":[-1.531943,52.283534],"type":"Point"}
}
