{
  "type": "Feature",
  "properties": {
    "date:inception_lower":"1980-01-01",
    "date:inception_upper":"1980-01-31",
    "iso:country":"GB",
    "wof:name":"CV31 2DL",
    "wof:placetype":"postalcode"
},
  "geometry": {"coordinates":[-1.532003,52.283426],"type":"Point"}
}