{
  "type": "Feature",
  "properties": {
    "iso:country": "GB",
    "wof:name": "E12 5DH",
    "wof:placetype": "postalcode"
  },
  "geometry": {"coordinates":[0.04065,51.559437],"type":"Point"}
}
