{
  "type": "Feature",
  "properties": {
    "iso:country": "GB",
    "wof:name": "TS21 2AL",
    "wof:placetype": "postalcode"
  },
  "geometry": {"coordinates":[-1.454344,54.656682],"type":"Point"}
}
