{
  "type": "Feature",
  "properties": {
    "iso:country":"GB",
    "wof:name":"TW3 4LE",
    "wof:placetype":"postalcode"
},
  "geometry": {"coordinates":[-0.37495443611072,51.4754564302696],"type":"Point"}
}