{
  "type": "Feature",
  "properties": {
    "date:inception_lower": "1980-01-01",
    "date:inception_upper": "1980-01-01",
    "iso:country": "GB",
    "wof:name": "PA2 7RU",
    "wof:placetype": "postalcode"
  },
  "geometry": {"coordinates":[-4.418704,55.828273],"type":"Point"}
}
