{
  "type": "Feature",
  "properties": {
    "iso:country":"GB",
    "wof:name":"NE33 4RG",
    "wof:placetype":"postalcode"
},
  "geometry": {"coordinates":[-1.4386040324139,54.97603747655618],"type":"Point"}
}