{
  "type": "Feature",
  "properties": {
    "iso:country":"GB",
    "wof:name":"SW16 5PQ",
    "wof:placetype":"postalcode"
},
  "geometry": {"coordinates":[-0.13631261887344,51.42153870351638],"type":"Point"}
}