{
  "type": "Feature",
  "properties": {
    "iso:country": "GB",
    "wof:name": "SG5 4LB",
    "wof:placetype": "postalcode"
  },
  "geometry": {"coordinates":[-0.229836,52.013465],"type":"Point"}
}
