{
  "type": "Feature",
  "properties": {
    "iso:country":"GB",
    "wof:name":"SG5 4LB",
    "wof:placetype":"postalcode"
},
  "geometry": {"coordinates":[-0.22983609719065,52.0134651324317],"type":"Point"}
}