{
  "type": "Feature",
  "properties": {
    "date:inception_lower": "2024-04-01",
    "date:inception_upper": "2024-04-01",
    "iso:country": "GB",
    "wof:name": "GL2 2LD",
    "wof:placetype": "postalcode"
  },
  "geometry": {"coordinates":[-2.273694,51.818707],"type":"Point"}
}
