{
  "type": "Feature",
  "properties": {
    "iso:country":"GB",
    "wof:name":"SL2 2HG",
    "wof:placetype":"postalcode"
},
  "geometry": {"coordinates":[-0.63449722260968,51.53503781101954],"type":"Point"}
}