{
  "type": "Feature",
  "properties": {
    "date:inception_lower":"1980-01-01",
    "date:inception_upper":"1980-01-31",
    "iso:country":"GB",
    "wof:name":"SL2 2HG",
    "wof:placetype":"postalcode"
},
  "geometry": {"coordinates":[-0.634497,51.535038],"type":"Point"}
}