{
  "type": "Feature",
  "properties": {
    "iso:country":"GB",
    "wof:name":"BA13 3ED",
    "wof:placetype":"postalcode"
},
  "geometry": {"coordinates":[-2.16572057410355,51.25696574415666],"type":"Point"}
}