{
  "type": "Feature",
  "properties": {
    "date:inception_lower":"2000-06-01",
    "date:inception_upper":"2000-06-30",
    "iso:country":"GB",
    "wof:name":"CO12 3DF",
    "wof:placetype":"postalcode"
},
  "geometry": {"coordinates":[1.285251,51.938904],"type":"Point"}
}