{
  "type": "Feature",
  "properties": {
    "date:inception_lower": "2006-04-01",
    "date:inception_upper": "2006-04-01",
    "iso:country": "GB",
    "wof:name": "OX18 3WN",
    "wof:placetype": "postalcode"
  },
  "geometry": {"coordinates":[-1.598807,51.785617],"type":"Point"}
}
