{
  "type": "Feature",
  "properties": {
    "iso:country": "GB",
    "wof:name": "OX18 3WN",
    "wof:placetype": "postalcode"
  },
  "geometry": {"coordinates":[-1.598807,51.785617],"type":"Point"}
}
