{
  "type": "Feature",
  "properties": {
    "iso:country":"GB",
    "wof:name":"OX18 3WN",
    "wof:placetype":"postalcode"
},
  "geometry": {"coordinates":[-1.59880693327901,51.78561747609236],"type":"Point"}
}