{
  "type": "Feature",
  "properties": {
    "date:inception_lower": "1995-01-01",
    "date:inception_upper": "1995-01-01",
    "iso:country": "GB",
    "wof:name": "NG17 4NZ",
    "wof:placetype": "postalcode"
  },
  "geometry": {"coordinates":[-1.230735,53.136577],"type":"Point"}
}
