{
  "type": "Feature",
  "properties": {
    "iso:country":"GB",
    "wof:name":"NG17 4NZ",
    "wof:placetype":"postalcode"
},
  "geometry": {"coordinates":[-1.23073480381861,53.13657711374407],"type":"Point"}
}