{
  "type": "Feature",
  "properties": {
    "iso:country":"GB",
    "wof:name":"LN2 1QE",
    "wof:placetype":"postalcode"
},
  "geometry": {"coordinates":[-0.53706788555182,53.23598408958846],"type":"Point"}
}