{
  "type": "Feature",
  "properties": {
    "iso:country": "GB",
    "wof:name": "LN2 1QE",
    "wof:placetype": "postalcode"
  },
  "geometry": {"coordinates":[-0.537068,53.235984],"type":"Point"}
}
