{
  "type": "Feature",
  "properties": {
    "date:inception_lower": "2002-07-01",
    "date:inception_upper": "2002-07-01",
    "iso:country": "GB",
    "wof:name": "NN29 7NL",
    "wof:placetype": "postalcode"
  },
  "geometry": {"coordinates":[-0.714742,52.2733],"type":"Point"}
}
