{
  "type": "Feature",
  "properties": {
    "iso:country": "GB",
    "wof:name": "NN29 7NL",
    "wof:placetype": "postalcode"
  },
  "geometry": {"coordinates":[-0.714742,52.2733],"type":"Point"}
}
