{
  "type": "Feature",
  "properties": {
    "iso:country": "GB",
    "wof:name": "NG4 1JF",
    "wof:placetype": "postalcode"
  },
  "geometry": {"coordinates":[-1.113007,52.96639],"type":"Point"}
}
