{
  "type": "Feature",
  "properties": {
    "iso:country":"GB",
    "wof:name":"NG4 1JF",
    "wof:placetype":"postalcode"
},
  "geometry": {"coordinates":[-1.11300671170054,52.96638963715328],"type":"Point"}
}