{
  "type": "Feature",
  "properties": {
    "date:inception_lower": "2005-06-01",
    "date:inception_upper": "2005-06-01",
    "iso:country": "GB",
    "wof:name": "NG4 1JF",
    "wof:placetype": "postalcode"
  },
  "geometry": {"coordinates":[-1.113007,52.96639],"type":"Point"}
}
