{
  "type": "Feature",
  "properties": {
    "date:inception_lower": "1996-12-01",
    "date:inception_upper": "1996-12-01",
    "iso:country": "GB",
    "wof:name": "M22 1GY",
    "wof:placetype": "postalcode"
  },
  "geometry": {"coordinates":[-2.269889,53.372993],"type":"Point"}
}
