{
  "type": "Feature",
  "properties": {
    "iso:country":"GB",
    "wof:name":"M22 1GY",
    "wof:placetype":"postalcode"
},
  "geometry": {"coordinates":[-2.26988908619925,53.372992905536],"type":"Point"}
}