{
  "type": "Feature",
  "properties": {
    "iso:country":"GB",
    "wof:name":"CV2 1HD",
    "wof:placetype":"postalcode"
},
  "geometry": {"coordinates":[-1.46306809419548,52.44137329864076],"type":"Point"}
}