{
  "type": "Feature",
  "properties": {
    "date:inception_lower": "2007-07-01",
    "date:inception_upper": "2007-07-01",
    "iso:country": "GB",
    "wof:name": "TS19 8BF",
    "wof:placetype": "postalcode"
  },
  "geometry": {"coordinates":[-1.352988,54.585312],"type":"Point"}
}
