{
  "type": "Feature",
  "properties": {
    "iso:country":"GB",
    "wof:name":"N21 3QJ",
    "wof:placetype":"postalcode"
},
  "geometry": {"coordinates":[-0.10766431055808,51.62800672765918],"type":"Point"}
}