{
  "type": "Feature",
  "properties": {
    "iso:country":"GB",
    "wof:name":"NG15 7PF",
    "wof:placetype":"postalcode"
},
  "geometry": {"coordinates":[-1.19165244044588,53.03099984247858],"type":"Point"}
}