{
  "type": "Feature",
  "properties": {
    "iso:country":"GB",
    "wof:name":"EN8 0SH",
    "wof:placetype":"postalcode"
},
  "geometry": {"coordinates":[-0.03637153686199,51.71269547613828],"type":"Point"}
}