{
  "type": "Feature",
  "properties": {
    "date:inception_lower": "2022-10-01",
    "date:inception_upper": "2022-10-01",
    "iso:country": "GB",
    "wof:name": "NN11 2AQ",
    "wof:placetype": "postalcode"
  },
  "geometry": {"coordinates":[-1.167468,52.285943],"type":"Point"}
}
