{
  "type": "Feature",
  "properties": {
    "iso:country":"GB",
    "wof:name":"WN6 7NP",
    "wof:placetype":"postalcode"
},
  "geometry": {"coordinates":[-2.65679327691404,53.55391466233814],"type":"Point"}
}