{
  "type": "Feature",
  "properties": {
    "date:inception_lower": "1980-01-01",
    "date:inception_upper": "1980-01-01",
    "iso:country": "GB",
    "wof:name": "WN6 7NP",
    "wof:placetype": "postalcode"
  },
  "geometry": {"coordinates":[-2.656793,53.553915],"type":"Point"}
}
