{
  "type": "Feature",
  "properties": {
    "iso:country": "GB",
    "wof:name": "WN6 7NP",
    "wof:placetype": "postalcode"
  },
  "geometry": {"coordinates":[-2.656793,53.553915],"type":"Point"}
}
