{
  "type": "Feature",
  "properties": {
    "iso:country":"GB",
    "wof:name":"S62 5DT",
    "wof:placetype":"postalcode"
},
  "geometry": {"coordinates":[-1.33110860117448,53.46426145148043],"type":"Point"}
}