{
  "type": "Feature",
  "properties": {
    "iso:country":"GB",
    "wof:name":"WF3 4NU",
    "wof:placetype":"postalcode"
},
  "geometry": {"coordinates":[-1.47606994735555,53.70638574946532],"type":"Point"}
}