{
  "type": "Feature",
  "properties": {
    "iso:country":"GB",
    "wof:name":"RG20 9JJ",
    "wof:placetype":"postalcode"
},
  "geometry": {"coordinates":[-1.28318361009029,51.36113892348901],"type":"Point"}
}