{
  "type": "Feature",
  "properties": {
    "iso:country":"GB",
    "wof:name":"WN5 9EJ",
    "wof:placetype":"postalcode"
},
  "geometry": {"coordinates":[-2.66179773829147,53.53606284421421],"type":"Point"}
}