{
  "type": "Feature",
  "properties": {
    "iso:country": "GB",
    "wof:name": "WF8 4DE",
    "wof:placetype": "postalcode"
  },
  "geometry": {"coordinates":[-1.330393,53.688475],"type":"Point"}
}
