{
  "type": "Feature",
  "properties": {
    "iso:country":"GB",
    "wof:name":"EN9 3AY",
    "wof:placetype":"postalcode"
},
  "geometry": {"coordinates":[0.0229242775721,51.68227505137138],"type":"Point"}
}