{
  "type": "Feature",
  "properties": {
    "iso:country": "GB",
    "wof:name": "E16 2DN",
    "wof:placetype": "postalcode"
  },
  "geometry": {"coordinates":[0.047623,51.502624],"type":"Point"}
}
