{
  "type": "Feature",
  "properties": {
    "iso:country":"GB",
    "wof:name":"E16 2DN",
    "wof:placetype":"postalcode"
},
  "geometry": {"coordinates":[0.0476232056201,51.5026239735995],"type":"Point"}
}