{
  "type": "Feature",
  "properties": {
    "iso:country":"GB",
    "wof:name":"HR1 4AD",
    "wof:placetype":"postalcode"
},
  "geometry": {"coordinates":[-2.66265348142638,52.06681103487612],"type":"Point"}
}