{
  "type": "Feature",
  "properties": {
    "iso:country": "GB",
    "wof:name": "HR1 4AD",
    "wof:placetype": "postalcode"
  },
  "geometry": {"coordinates":[-2.662653,52.066811],"type":"Point"}
}
