{
  "type": "Feature",
  "properties": {
    "iso:country":"GB",
    "wof:name":"BB2 7AQ",
    "wof:placetype":"postalcode"
},
  "geometry": {"coordinates":[-2.51153716503001,53.75615056157217],"type":"Point"}
}