{
  "type": "Feature",
  "properties": {
    "iso:country": "GB",
    "wof:name": "BB2 7AQ",
    "wof:placetype": "postalcode"
  },
  "geometry": {"coordinates":[-2.511537,53.756151],"type":"Point"}
}
