{
  "type": "Feature",
  "properties": {
    "iso:country":"GB",
    "wof:name":"BN26 5DU",
    "wof:placetype":"postalcode"
},
  "geometry": {"coordinates":[0.24567940859527,50.81443385433984],"type":"Point"}
}