{
  "type": "Feature",
  "properties": {
    "iso:country": "GB",
    "wof:name": "DL8 5BZ",
    "wof:placetype": "postalcode"
  },
  "geometry": {"coordinates":[-1.820645,54.30851],"type":"Point"}
}
