{
  "type": "Feature",
  "properties": {
    "iso:country":"GB",
    "wof:name":"DA2 7LQ",
    "wof:placetype":"postalcode"
},
  "geometry": {"coordinates":[0.2588199972683,51.42216971098042],"type":"Point"}
}