{
  "type": "Feature",
  "properties": {
    "date:inception_lower": "1980-01-01",
    "date:inception_upper": "1980-01-01",
    "iso:country": "GB",
    "wof:name": "NN14 3DL",
    "wof:placetype": "postalcode"
  },
  "geometry": {"coordinates":[-0.491282,52.400279],"type":"Point"}
}
