{
  "type": "Feature",
  "properties": {
    "iso:country":"GB",
    "wof:name":"NN14 3DL",
    "wof:placetype":"postalcode"
},
  "geometry": {"coordinates":[-0.4912816641553,52.40027934703172],"type":"Point"}
}