{
  "type": "Feature",
  "properties": {
    "date:inception_lower":"1994-05-01",
    "date:inception_upper":"1994-05-31",
    "iso:country":"GB",
    "wof:name":"M28 7EU",
    "wof:placetype":"postalcode"
},
  "geometry": {"coordinates":[-2.392243,53.514223],"type":"Point"}
}