{
  "type": "Feature",
  "properties": {
    "iso:country":"GB",
    "wof:name":"M28 7EU",
    "wof:placetype":"postalcode"
},
  "geometry": {"coordinates":[-2.39224275663239,53.51422301710954],"type":"Point"}
}