{
  "type": "Feature",
  "properties": {
    "iso:country":"GB",
    "wof:name":"EX23 9PF",
    "wof:placetype":"postalcode"
},
  "geometry": {"coordinates":[-4.51913359136158,50.91776505867721],"type":"Point"}
}