{
  "type": "Feature",
  "properties": {
    "iso:country":"GB",
    "wof:name":"FK7 0BE",
    "wof:placetype":"postalcode"
},
  "geometry": {"coordinates":[-3.93307305531409,56.10240350518765],"type":"Point"}
}