{
  "type": "Feature",
  "properties": {
    "iso:country":"GB",
    "wof:name":"PA5 8ET",
    "wof:placetype":"postalcode"
},
  "geometry": {"coordinates":[-4.50831193468639,55.83488156610721],"type":"Point"}
}