{
  "type": "Feature",
  "properties": {
    "iso:country":"GB",
    "wof:name":"B93 0JU",
    "wof:placetype":"postalcode"
},
  "geometry": {"coordinates":[-1.73543511894044,52.38943389597006],"type":"Point"}
}