{
  "type": "Feature",
  "properties": {
    "date:inception_lower": "1980-01-01",
    "date:inception_upper": "1980-01-01",
    "iso:country": "GB",
    "wof:name": "B93 0JU",
    "wof:placetype": "postalcode"
  },
  "geometry": {"coordinates":[-1.735412,52.389386],"type":"Point"}
}
