{
  "type": "Feature",
  "properties": {
    "date:inception_lower": "1980-01-01",
    "date:inception_upper": "1980-01-01",
    "iso:country": "GB",
    "wof:name": "M34 5JE",
    "wof:placetype": "postalcode"
  },
  "geometry": {"coordinates":[-2.112695,53.472514],"type":"Point"}
}
