{
  "type": "Feature",
  "properties": {
    "iso:country":"GB",
    "wof:name":"DE73 6NJ",
    "wof:placetype":"postalcode"
},
  "geometry": {"coordinates":[-1.42598775460458,52.87330322333545],"type":"Point"}
}