{
  "type": "Feature",
  "properties": {
    "iso:country":"GB",
    "wof:name":"WF9 2PP",
    "wof:placetype":"postalcode"
},
  "geometry": {"coordinates":[-1.29899637330201,53.59667662678153],"type":"Point"}
}