{
  "type": "Feature",
  "properties": {
    "iso:country":"GB",
    "wof:name":"B23 7YB",
    "wof:placetype":"postalcode"
},
  "geometry": {"coordinates":[-1.87113498499926,52.52040998818944],"type":"Point"}
}