{
  "type": "Feature",
  "properties": {
    "iso:country":"GB",
    "wof:name":"M13 0WH",
    "wof:placetype":"postalcode"
},
  "geometry": {"coordinates":[-2.20397874601829,53.45723871763882],"type":"Point"}
}