{
  "type": "Feature",
  "properties": {
    "iso:country":"GB",
    "wof:name":"TS27 3QX",
    "wof:placetype":"postalcode"
},
  "geometry": {"coordinates":[-1.25306500012669,54.71359161861732],"type":"Point"}
}