{
  "type": "Feature",
  "properties": {
    "iso:country":"GB",
    "wof:name":"OL8 3BP",
    "wof:placetype":"postalcode"
},
  "geometry": {"coordinates":[-2.11244994722199,53.5276405832138],"type":"Point"}
}