{
  "type": "Feature",
  "properties": {
    "iso:country": "GB",
    "wof:name": "OL8 3BP",
    "wof:placetype": "postalcode"
  },
  "geometry": {"coordinates":[-2.11245,53.527641],"type":"Point"}
}
