{
  "type": "Feature",
  "properties": {
    "iso:country": "GB",
    "wof:name": "TN15 0QW",
    "wof:placetype": "postalcode"
  },
  "geometry": {"coordinates":[0.299575,51.257906],"type":"Point"}
}
