{
  "type": "Feature",
  "properties": {
    "iso:country":"GB",
    "wof:name":"TN15 0QW",
    "wof:placetype":"postalcode"
},
  "geometry": {"coordinates":[0.29957514355141,51.25790584959032],"type":"Point"}
}