{
  "type": "Feature",
  "properties": {
    "date:inception_lower":"1992-08-01",
    "date:inception_upper":"1992-08-31",
    "iso:country":"GB",
    "wof:name":"DE23 8QJ",
    "wof:placetype":"postalcode"
},
  "geometry": {"coordinates":[-1.479474,52.904275],"type":"Point"}
}