{
  "type": "Feature",
  "properties": {
    "iso:country": "GB",
    "wof:name": "M22 4HL",
    "wof:placetype": "postalcode"
  },
  "geometry": {"coordinates":[-2.255977,53.409104],"type":"Point"}
}
