{
  "type": "Feature",
  "properties": {
    "iso:country":"GB",
    "wof:name":"M22 4HL",
    "wof:placetype":"postalcode"
},
  "geometry": {"coordinates":[-2.25597739466718,53.40910380217795],"type":"Point"}
}