{
  "type": "Feature",
  "properties": {
    "iso:country": "GB",
    "wof:name": "NE24 4ND",
    "wof:placetype": "postalcode"
  },
  "geometry": {"coordinates":[-1.549967,55.123963],"type":"Point"}
}
