{
  "type": "Feature",
  "properties": {
    "iso:country":"GB",
    "wof:name":"IV9 8RP",
    "wof:placetype":"postalcode"
},
  "geometry": {"coordinates":[-4.20506664811952,57.55657374435466],"type":"Point"}
}