{
  "type": "Feature",
  "properties": {
    "iso:country":"GB",
    "wof:name":"W11 1QR",
    "wof:placetype":"postalcode"
},
  "geometry": {"coordinates":[-0.20528324534139,51.51794455931896],"type":"Point"}
}