{
  "type": "Feature",
  "properties": {
    "date:inception_lower": "1999-12-01",
    "date:inception_upper": "1999-12-01",
    "iso:country": "GB",
    "wof:name": "CV47 0HQ",
    "wof:placetype": "postalcode"
  },
  "geometry": {"coordinates":[-1.39006,52.252178],"type":"Point"}
}
