{
  "type": "Feature",
  "properties": {
    "iso:country":"GB",
    "wof:name":"CV47 0HQ",
    "wof:placetype":"postalcode"
},
  "geometry": {"coordinates":[-1.39005973419555,52.25217842250019],"type":"Point"}
}