{
  "type": "Feature",
  "properties": {
    "iso:country":"GB",
    "wof:name":"W1W 7BP",
    "wof:placetype":"postalcode"
},
  "geometry": {"coordinates":[-0.13929621522686,51.51870583890452],"type":"Point"}
}