{
  "type": "Feature",
  "properties": {
    "iso:country":"GB",
    "wof:name":"TS14 6HE",
    "wof:placetype":"postalcode"
},
  "geometry": {"coordinates":[-1.05325545548069,54.53967960722042],"type":"Point"}
}