{
  "type": "Feature",
  "properties": {
    "date:inception_lower":"1980-01-01",
    "date:inception_upper":"1980-01-31",
    "iso:country":"GB",
    "wof:name":"TS14 6HE",
    "wof:placetype":"postalcode"
},
  "geometry": {"coordinates":[-1.053255,54.53968],"type":"Point"}
}