{
  "type": "Feature",
  "properties": {
    "date:inception_lower": "2017-09-01",
    "date:inception_upper": "2017-09-01",
    "iso:country": "GB",
    "wof:name": "NG10 5BE",
    "wof:placetype": "postalcode"
  },
  "geometry": {"coordinates":[-1.286863,52.922083],"type":"Point"}
}
