{
  "type": "Feature",
  "properties": {
    "iso:country":"GB",
    "wof:name":"AL10 0RQ",
    "wof:placetype":"postalcode"
},
  "geometry": {"coordinates":[-0.22830358146775,51.77039156520046],"type":"Point"}
}