{
  "type": "Feature",
  "properties": {
    "iso:country":"GB",
    "wof:name":"SO17 2LW",
    "wof:placetype":"postalcode"
},
  "geometry": {"coordinates":[-1.382597348992,50.92413889405294],"type":"Point"}
}