{
  "type": "Feature",
  "properties": {
    "iso:country": "GB",
    "wof:name": "SO17 2LW",
    "wof:placetype": "postalcode"
  },
  "geometry": {"coordinates":[-1.382597,50.924139],"type":"Point"}
}
