{
  "type": "Feature",
  "properties": {
    "iso:country": "GB",
    "wof:name": "HA0 1UG",
    "wof:placetype": "postalcode"
  },
  "geometry": {"coordinates":[-0.292834,51.541723],"type":"Point"}
}
