{
  "type": "Feature",
  "properties": {
    "iso:country":"GB",
    "wof:name":"HD3 4UQ",
    "wof:placetype":"postalcode"
},
  "geometry": {"coordinates":[-1.84114167807844,53.65021565028506],"type":"Point"}
}