{
  "type": "Feature",
  "properties": {
    "iso:country": "GB",
    "wof:name": "EX20 2QE",
    "wof:placetype": "postalcode"
  },
  "geometry": {"coordinates":[-3.90025,50.705636],"type":"Point"}
}
