{
  "type": "Feature",
  "properties": {
    "date:inception_lower": "1999-12-01",
    "date:inception_upper": "1999-12-01",
    "iso:country": "GB",
    "wof:name": "PR4 3XF",
    "wof:placetype": "postalcode"
  },
  "geometry": {"coordinates":[-2.842372,53.816588],"type":"Point"}
}
