{
  "type": "Feature",
  "properties": {
    "iso:country":"GB",
    "wof:name":"PR4 3XF",
    "wof:placetype":"postalcode"
},
  "geometry": {"coordinates":[-2.84237198484755,53.81658816727674],"type":"Point"}
}