{
  "type": "Feature",
  "properties": {
    "iso:country":"GB",
    "wof:name":"WN5 7QY",
    "wof:placetype":"postalcode"
},
  "geometry": {"coordinates":[-2.71586223248369,53.48795895461082],"type":"Point"}
}