{
  "type": "Feature",
  "properties": {
    "iso:country":"GB",
    "wof:name":"BA11 2QN",
    "wof:placetype":"postalcode"
},
  "geometry": {"coordinates":[-2.35473856597324,51.25561899603115],"type":"Point"}
}