{
  "type": "Feature",
  "properties": {
    "iso:country":"GB",
    "wof:name":"B13 9AA",
    "wof:placetype":"postalcode"
},
  "geometry": {"coordinates":[-1.88414964473664,52.44685859543431],"type":"Point"}
}