{
  "type": "Feature",
  "properties": {
    "iso:country":"GB",
    "wof:name":"LL77 9AZ",
    "wof:placetype":"postalcode"
},
  "geometry": {"coordinates":[-4.30842809792601,53.25376674792228],"type":"Point"}
}