{
  "type": "Feature",
  "properties": {
    "date:inception_lower":"1991-01-01",
    "date:inception_upper":"1991-01-31",
    "iso:country":"GB",
    "wof:name":"WS12 4TQ",
    "wof:placetype":"postalcode"
},
  "geometry": {"coordinates":[-2.03849,52.714769],"type":"Point"}
}