{
  "type": "Feature",
  "properties": {
    "date:inception_lower": "2020-09-01",
    "date:inception_upper": "2020-09-01",
    "iso:country": "GB",
    "wof:name": "WA16 1FU",
    "wof:placetype": "postalcode"
  },
  "geometry": {"coordinates":[-2.35944,53.312504],"type":"Point"}
}
