{
  "type": "Feature",
  "properties": {
    "iso:country": "GB",
    "wof:name": "DG12 5BG",
    "wof:placetype": "postalcode"
  },
  "geometry": {"coordinates":[-3.260653,54.989659],"type":"Point"}
}
