{
  "type": "Feature",
  "properties": {
    "iso:country":"GB",
    "wof:name":"KY12 9NU",
    "wof:placetype":"postalcode"
},
  "geometry": {"coordinates":[-3.50028722088902,56.08185952397026],"type":"Point"}
}