{
  "type": "Feature",
  "properties": {
    "iso:country":"GB",
    "wof:name":"HD1 6HA",
    "wof:placetype":"postalcode"
},
  "geometry": {"coordinates":[-1.78464994729267,53.65938533533738],"type":"Point"}
}