{
  "type": "Feature",
  "properties": {
    "date:inception_lower": "1980-01-01",
    "date:inception_upper": "1980-01-01",
    "iso:country": "GB",
    "wof:name": "HD1 6HA",
    "wof:placetype": "postalcode"
  },
  "geometry": {"coordinates":[-1.78465,53.659385],"type":"Point"}
}
