{
  "type": "Feature",
  "properties": {
    "date:inception_lower":"2000-06-01",
    "date:inception_upper":"2000-06-30",
    "iso:country":"GB",
    "wof:name":"DH4 4UW",
    "wof:placetype":"postalcode"
},
  "geometry": {"coordinates":[-1.486517,54.864701],"type":"Point"}
}