{
  "type": "Feature",
  "properties": {
    "iso:country":"GB",
    "wof:name":"DH4 4UW",
    "wof:placetype":"postalcode"
},
  "geometry": {"coordinates":[-1.4865174251552,54.86470095968461],"type":"Point"}
}