{
  "type": "Feature",
  "properties": {
    "iso:country":"GB",
    "wof:name":"SE8 5HY",
    "wof:placetype":"postalcode"
},
  "geometry": {"coordinates":[-0.03944911413091,51.48451699608756],"type":"Point"}
}