{
  "type": "Feature",
  "properties": {
    "iso:country": "GB",
    "wof:name": "SY17 5LG",
    "wof:placetype": "postalcode"
  },
  "geometry": {"coordinates":[-3.539138,52.563995],"type":"Point"}
}
