{
  "type": "Feature",
  "properties": {
    "date:inception_lower": "1980-01-01",
    "date:inception_upper": "1980-01-01",
    "iso:country": "GB",
    "wof:name": "SY17 5LG",
    "wof:placetype": "postalcode"
  },
  "geometry": {"coordinates":[-3.539138,52.563995],"type":"Point"}
}
