{
  "type": "Feature",
  "properties": {
    "date:inception_lower": "1980-01-01",
    "date:inception_upper": "1980-01-01",
    "iso:country": "GB",
    "wof:name": "DE7 5QU",
    "wof:placetype": "postalcode"
  },
  "geometry": {"coordinates":[-1.307592,52.969291],"type":"Point"}
}
