{
  "type": "Feature",
  "properties": {
    "date:inception_lower":"2001-06-01",
    "date:inception_upper":"2001-06-30",
    "iso:country":"GB",
    "wof:name":"NR33 7UP",
    "wof:placetype":"postalcode"
},
  "geometry": {"coordinates":[1.707506,52.421618],"type":"Point"}
}