{
  "type": "Feature",
  "properties": {
    "date:inception_lower": "2001-06-01",
    "date:inception_upper": "2001-06-01",
    "iso:country": "GB",
    "wof:name": "NR33 7UP",
    "wof:placetype": "postalcode"
  },
  "geometry": {"coordinates":[1.7078,52.421797],"type":"Point"}
}
