{
  "type": "Feature",
  "properties": {
    "iso:country":"GB",
    "wof:name":"NR33 7UP",
    "wof:placetype":"postalcode"
},
  "geometry": {"coordinates":[1.70748531446427,52.42096287534942],"type":"Point"}
}