{
  "type": "Feature",
  "properties": {
    "iso:country":"GB",
    "wof:name":"SS8 8JW",
    "wof:placetype":"postalcode"
},
  "geometry": {"coordinates":[0.60808437344499,51.52225418150929],"type":"Point"}
}