{
  "type": "Feature",
  "properties": {
    "iso:country": "GB",
    "wof:name": "SS8 8JW",
    "wof:placetype": "postalcode"
  },
  "geometry": {"coordinates":[0.608084,51.522254],"type":"Point"}
}
