{
  "type": "Feature",
  "properties": {
    "iso:country":"GB",
    "wof:name":"AL2 3HW",
    "wof:placetype":"postalcode"
},
  "geometry": {"coordinates":[-0.35638892681313,51.72793100939535],"type":"Point"}
}