{
  "type": "Feature",
  "properties": {
    "iso:country":"GB",
    "wof:name":"RG20 0NB",
    "wof:placetype":"postalcode"
},
  "geometry": {"coordinates":[-1.36488672812987,51.36681636653721],"type":"Point"}
}