{
  "type": "Feature",
  "properties": {
    "date:inception_lower": "1995-07-01",
    "date:inception_upper": "1995-07-01",
    "iso:country": "GB",
    "wof:name": "RG20 0NB",
    "wof:placetype": "postalcode"
  },
  "geometry": {"coordinates":[-1.365018,51.366429],"type":"Point"}
}
