{
  "type": "Feature",
  "properties": {
    "iso:country":"GB",
    "wof:name":"NE9 5LZ",
    "wof:placetype":"postalcode"
},
  "geometry": {"coordinates":[-1.59248215267467,54.94917893783107],"type":"Point"}
}