{
  "type": "Feature",
  "properties": {
    "date:inception_lower": "1994-05-01",
    "date:inception_upper": "1994-05-01",
    "iso:country": "GB",
    "wof:name": "NE9 5LZ",
    "wof:placetype": "postalcode"
  },
  "geometry": {"coordinates":[-1.592482,54.949179],"type":"Point"}
}
