{
  "type": "Feature",
  "properties": {
    "iso:country":"GB",
    "wof:name":"SA2 7HX",
    "wof:placetype":"postalcode"
},
  "geometry": {"coordinates":[-4.0422761693279,51.61164516050811],"type":"Point"}
}