{
  "type": "Feature",
  "properties": {
    "iso:country": "GB",
    "wof:name": "SA2 7HX",
    "wof:placetype": "postalcode"
  },
  "geometry": {"coordinates":[-4.042276,51.611645],"type":"Point"}
}
