{
  "type": "Feature",
  "properties": {
    "date:inception_lower": "1980-01-01",
    "date:inception_upper": "1980-01-01",
    "iso:country": "GB",
    "wof:name": "SA2 7HX",
    "wof:placetype": "postalcode"
  },
  "geometry": {"coordinates":[-4.042276,51.611645],"type":"Point"}
}
