{
  "type": "Feature",
  "properties": {
    "iso:country":"GB",
    "wof:name":"SO51 8JL",
    "wof:placetype":"postalcode"
},
  "geometry": {"coordinates":[-1.48888015879822,50.99020665617014],"type":"Point"}
}