{
  "type": "Feature",
  "properties": {
    "iso:country": "GB",
    "wof:name": "SO51 8JL",
    "wof:placetype": "postalcode"
  },
  "geometry": {"coordinates":[-1.488799,50.990217],"type":"Point"}
}
