{
  "type": "Feature",
  "properties": {
    "iso:country": "GB",
    "wof:name": "PE28 5BS",
    "wof:placetype": "postalcode"
  },
  "geometry": {"coordinates":[-0.29029,52.438524],"type":"Point"}
}
