{
  "type": "Feature",
  "properties": {
    "date:inception_lower": "2018-07-01",
    "date:inception_upper": "2018-07-01",
    "iso:country": "GB",
    "wof:name": "PE28 5BS",
    "wof:placetype": "postalcode"
  },
  "geometry": {"coordinates":[-0.29057,52.438492],"type":"Point"}
}
