{
  "type": "Feature",
  "properties": {
    "iso:country": "GB",
    "wof:name": "SY4 3AH",
    "wof:placetype": "postalcode"
  },
  "geometry": {"coordinates":[-2.742336,52.76193],"type":"Point"}
}
