{
  "type": "Feature",
  "properties": {
    "iso:country":"GB",
    "wof:name":"SY4 3AH",
    "wof:placetype":"postalcode"
},
  "geometry": {"coordinates":[-2.74233593402192,52.76192966627207],"type":"Point"}
}