{
  "type": "Feature",
  "properties": {
    "iso:country":"GB",
    "wof:name":"WS11 7AD",
    "wof:placetype":"postalcode"
},
  "geometry": {"coordinates":[-1.99809303522253,52.69290351605277],"type":"Point"}
}