{
  "type": "Feature",
  "properties": {
    "iso:country": "GB",
    "wof:name": "TQ3 1EX",
    "wof:placetype": "postalcode"
  },
  "geometry": {"coordinates":[-3.569609,50.455636],"type":"Point"}
}
