{
  "type": "Feature",
  "properties": {
    "iso:country":"GB",
    "wof:name":"B80 7BU",
    "wof:placetype":"postalcode"
},
  "geometry": {"coordinates":[-1.8788780921987,52.29235791033538],"type":"Point"}
}