{
  "type": "Feature",
  "properties": {
    "iso:country": "GB",
    "wof:name": "IV2 3HD",
    "wof:placetype": "postalcode"
  },
  "geometry": {"coordinates":[-4.223839,57.475107],"type":"Point"}
}
