{
  "type": "Feature",
  "properties": {
    "iso:country":"GB",
    "wof:name":"G81 4AX",
    "wof:placetype":"postalcode"
},
  "geometry": {"coordinates":[-4.43039678667111,55.91070402757133],"type":"Point"}
}