{
  "type": "Feature",
  "properties": {
    "date:inception_lower": "2009-08-01",
    "date:inception_upper": "2009-08-01",
    "iso:country": "GB",
    "wof:name": "G81 4AX",
    "wof:placetype": "postalcode"
  },
  "geometry": {"coordinates":[-4.430382,55.910722],"type":"Point"}
}
