{
  "type": "Feature",
  "properties": {
    "iso:country": "GB",
    "wof:name": "KT12 2DZ",
    "wof:placetype": "postalcode"
  },
  "geometry": {"coordinates":[-0.403222,51.396613],"type":"Point"}
}
