{
  "type": "Feature",
  "properties": {
    "date:inception_lower": "1980-01-01",
    "date:inception_upper": "1980-01-01",
    "iso:country": "GB",
    "wof:name": "KT12 2DZ",
    "wof:placetype": "postalcode"
  },
  "geometry": {"coordinates":[-0.403222,51.396613],"type":"Point"}
}
