{
  "type": "Feature",
  "properties": {
    "iso:country": "GB",
    "wof:name": "SY3 8FD",
    "wof:placetype": "postalcode"
  },
  "geometry": {"coordinates":[-2.772152,52.710926],"type":"Point"}
}
