{
  "type": "Feature",
  "properties": {
    "date:inception_lower": "2020-04-01",
    "date:inception_upper": "2020-04-01",
    "iso:country": "GB",
    "wof:name": "SY3 8FD",
    "wof:placetype": "postalcode"
  },
  "geometry": {"coordinates":[-2.77218,52.711645],"type":"Point"}
}
