{
  "type": "Feature",
  "properties": {
    "iso:country":"GB",
    "wof:name":"AB34 5DD",
    "wof:placetype":"postalcode"
},
  "geometry": {"coordinates":[-2.7248369200213,57.05857713113736],"type":"Point"}
}