{
  "type": "Feature",
  "properties": {
    "date:inception_lower":"1980-01-01",
    "date:inception_upper":"1980-01-31",
    "iso:country":"GB",
    "wof:name":"NE23 8DY",
    "wof:placetype":"postalcode"
},
  "geometry": {"coordinates":[-1.60202,55.086807],"type":"Point"}
}