{
  "type": "Feature",
  "properties": {
    "iso:country":"GB",
    "wof:name":"NE23 8DY",
    "wof:placetype":"postalcode"
},
  "geometry": {"coordinates":[-1.60201980222144,55.08680722484562],"type":"Point"}
}