{
  "type": "Feature",
  "properties": {
    "iso:country":"GB",
    "wof:name":"MK42 7EH",
    "wof:placetype":"postalcode"
},
  "geometry": {"coordinates":[-0.50259123100246,52.11471405810134],"type":"Point"}
}