{
  "type": "Feature",
  "properties": {
    "date:inception_lower": "2024-07-01",
    "date:inception_upper": "2024-07-01",
    "iso:country": "GB",
    "wof:name": "B60 4GE",
    "wof:placetype": "postalcode"
  },
  "geometry": {"coordinates":[-2.083073,52.288359],"type":"Point"}
}
