{
  "type": "Feature",
  "properties": {
    "date:inception_lower":"1991-09-01",
    "date:inception_upper":"1991-09-30",
    "iso:country":"GB",
    "wof:name":"CV21 3LR",
    "wof:placetype":"postalcode"
},
  "geometry": {"coordinates":[-1.247348,52.376995],"type":"Point"}
}