{
  "type": "Feature",
  "properties": {
    "date:inception_lower": "1980-01-01",
    "date:inception_upper": "1980-01-01",
    "iso:country": "GB",
    "wof:name": "TF11 8JS",
    "wof:placetype": "postalcode"
  },
  "geometry": {"coordinates":[-2.299083,52.7002],"type":"Point"}
}
