{
  "type": "Feature",
  "properties": {
    "iso:country":"GB",
    "wof:name":"TF11 8JS",
    "wof:placetype":"postalcode"
},
  "geometry": {"coordinates":[-2.29908611806525,52.70018479759277],"type":"Point"}
}