{
  "type": "Feature",
  "properties": {
    "date:inception_lower": "1993-08-01",
    "date:inception_upper": "1993-08-01",
    "iso:country": "GB",
    "wof:name": "EX6 8TB",
    "wof:placetype": "postalcode"
  },
  "geometry": {"coordinates":[-3.500649,50.682237],"type":"Point"}
}
