{
  "type": "Feature",
  "properties": {
    "iso:country":"GB",
    "wof:name":"EX6 8TB",
    "wof:placetype":"postalcode"
},
  "geometry": {"coordinates":[-3.50064944552259,50.6822373359701],"type":"Point"}
}