{
  "type": "Feature",
  "properties": {
    "iso:country": "GB",
    "wof:name": "HR9 6JL",
    "wof:placetype": "postalcode"
  },
  "geometry": {"coordinates":[-2.638261,51.84033],"type":"Point"}
}
