{
  "type": "Feature",
  "properties": {
    "date:inception_lower":"1980-01-01",
    "date:inception_upper":"1980-01-31",
    "iso:country":"GB",
    "wof:name":"HR9 6JL",
    "wof:placetype":"postalcode"
},
  "geometry": {"coordinates":[-2.638261,51.84033],"type":"Point"}
}