{
  "type": "Feature",
  "properties": {
    "iso:country":"GB",
    "wof:name":"SE18 1SY",
    "wof:placetype":"postalcode"
},
  "geometry": {"coordinates":[0.08538324333219,51.48355027677588],"type":"Point"}
}