{
  "type": "Feature",
  "properties": {
    "iso:country": "GB",
    "wof:name": "CO11 1AP",
    "wof:placetype": "postalcode"
  },
  "geometry": {"coordinates":[1.066683,51.945273],"type":"Point"}
}
