{
  "type": "Feature",
  "properties": {
    "iso:country":"GB",
    "wof:name":"SA61 2TW",
    "wof:placetype":"postalcode"
},
  "geometry": {"coordinates":[-4.98583330676409,51.80147809367245],"type":"Point"}
}