{
  "type": "Feature",
  "properties": {
    "iso:country":"GB",
    "wof:name":"ML5 2SL",
    "wof:placetype":"postalcode"
},
  "geometry": {"coordinates":[-4.06095601620086,55.89430198543531],"type":"Point"}
}