{
  "type": "Feature",
  "properties": {
    "date:inception_lower": "1980-01-01",
    "date:inception_upper": "1980-01-01",
    "iso:country": "GB",
    "wof:name": "ML5 2SL",
    "wof:placetype": "postalcode"
  },
  "geometry": {"coordinates":[-4.060956,55.894302],"type":"Point"}
}
