{
  "type": "Feature",
  "properties": {
    "date:inception_lower": "1996-12-01",
    "date:inception_upper": "1996-12-01",
    "iso:country": "GB",
    "wof:name": "G74 4XG",
    "wof:placetype": "postalcode"
  },
  "geometry": {"coordinates":[-4.187766,55.767396],"type":"Point"}
}
