{
  "type": "Feature",
  "properties": {
    "iso:country": "GB",
    "wof:name": "LA6 1NN",
    "wof:placetype": "postalcode"
  },
  "geometry": {"coordinates":[-2.700486,54.18408],"type":"Point"}
}
