{
  "type": "Feature",
  "properties": {
    "iso:country":"GB",
    "wof:name":"LA6 1NN",
    "wof:placetype":"postalcode"
},
  "geometry": {"coordinates":[-2.70048602080151,54.18407968439755],"type":"Point"}
}