{
  "type": "Feature",
  "properties": {
    "iso:country": "GB",
    "wof:name": "EH41 3TF",
    "wof:placetype": "postalcode"
  },
  "geometry": {"coordinates":[-2.804621,55.954915],"type":"Point"}
}
