{
  "type": "Feature",
  "properties": {
    "date:inception_lower":"2016-04-01",
    "date:inception_upper":"2016-04-30",
    "iso:country":"GB",
    "wof:name":"EH41 3TF",
    "wof:placetype":"postalcode"
},
  "geometry": {"coordinates":[-2.804603,55.954834],"type":"Point"}
}