{
  "type": "Feature",
  "properties": {
    "iso:country":"GB",
    "wof:name":"IV2 4BZ",
    "wof:placetype":"postalcode"
},
  "geometry": {"coordinates":[-4.22836246251415,57.45325524130461],"type":"Point"}
}