{
  "type": "Feature",
  "properties": {
    "iso:country": "GB",
    "wof:name": "E1W 1BQ",
    "wof:placetype": "postalcode"
  },
  "geometry": {"coordinates":[-0.067662,51.50576],"type":"Point"}
}
