{
  "type": "Feature",
  "properties": {
    "iso:country":"GB",
    "wof:name":"SE25 4TB",
    "wof:placetype":"postalcode"
},
  "geometry": {"coordinates":[-0.07129069851275,51.39956061044437],"type":"Point"}
}