{
  "type": "Feature",
  "properties": {
    "iso:country":"GB",
    "wof:name":"S18 8RJ",
    "wof:placetype":"postalcode"
},
  "geometry": {"coordinates":[-1.49924689658888,53.30199336425186],"type":"Point"}
}