{
  "type": "Feature",
  "properties": {
    "iso:country": "GB",
    "wof:name": "UB7 7LY",
    "wof:placetype": "postalcode"
  },
  "geometry": {"coordinates":[-0.47902,51.512686],"type":"Point"}
}
