{
  "type": "Feature",
  "properties": {
    "iso:country":"GB",
    "wof:name":"UB7 7LY",
    "wof:placetype":"postalcode"
},
  "geometry": {"coordinates":[-0.47902041610654,51.51268619719731],"type":"Point"}
}