{
  "type": "Feature",
  "properties": {
    "iso:country": "GB",
    "wof:name": "LE15 9TE",
    "wof:placetype": "postalcode"
  },
  "geometry": {"coordinates":[-0.717238,52.586794],"type":"Point"}
}
