{
  "type": "Feature",
  "properties": {
    "iso:country":"GB",
    "wof:name":"LN7 6AA",
    "wof:placetype":"postalcode"
},
  "geometry": {"coordinates":[-0.33505870106286,53.48611517634475],"type":"Point"}
}