{
  "type": "Feature",
  "properties": {
    "iso:country":"GB",
    "wof:name":"CO6 5BQ",
    "wof:placetype":"postalcode"
},
  "geometry": {"coordinates":[0.90602077780288,52.02045384390223],"type":"Point"}
}