{
  "type": "Feature",
  "properties": {
    "iso:country":"GB",
    "wof:name":"NN12 8BD",
    "wof:placetype":"postalcode"
},
  "geometry": {"coordinates":[-1.02113939813329,52.13969535102628],"type":"Point"}
}