{
  "type": "Feature",
  "properties": {
    "date:inception_lower":"1980-01-01",
    "date:inception_upper":"1980-01-31",
    "iso:country":"GB",
    "wof:name":"G82 5EZ",
    "wof:placetype":"postalcode"
},
  "geometry": {"coordinates":[-4.658677,55.97222],"type":"Point"}
}