{
  "type": "Feature",
  "properties": {
    "iso:country":"GB",
    "wof:name":"G82 5EZ",
    "wof:placetype":"postalcode"
},
  "geometry": {"coordinates":[-4.65867663443707,55.97221981621539],"type":"Point"}
}