{
  "type": "Feature",
  "properties": {
    "iso:country": "GB",
    "wof:name": "LN1 2QU",
    "wof:placetype": "postalcode"
  },
  "geometry": {"coordinates":[-0.751467,53.26374],"type":"Point"}
}
