{
  "type": "Feature",
  "properties": {
    "date:inception_lower":"2018-09-01",
    "date:inception_upper":"2018-09-30",
    "iso:country":"GB",
    "wof:name":"LN1 2QU",
    "wof:placetype":"postalcode"
},
  "geometry": {"coordinates":[-0.751467,53.26374],"type":"Point"}
}