{
  "type": "Feature",
  "properties": {
    "date:inception_lower": "1980-01-01",
    "date:inception_upper": "1980-01-01",
    "iso:country": "GB",
    "wof:name": "GL16 8NG",
    "wof:placetype": "postalcode"
  },
  "geometry": {"coordinates":[-2.635481,51.776756],"type":"Point"}
}
