{
  "type": "Feature",
  "properties": {
    "iso:country": "GB",
    "wof:name": "NE65 9TY",
    "wof:placetype": "postalcode"
  },
  "geometry": {"coordinates":[-1.613872,55.306761],"type":"Point"}
}
