{
  "type": "Feature",
  "properties": {
    "iso:country":"GB",
    "wof:name":"NE65 9TY",
    "wof:placetype":"postalcode"
},
  "geometry": {"coordinates":[-1.61384198183714,55.30675798624335],"type":"Point"}
}