{
  "type": "Feature",
  "properties": {
    "date:inception_lower":"1989-10-01",
    "date:inception_upper":"1989-10-31",
    "iso:country":"GB",
    "wof:name":"EH21 6UN",
    "wof:placetype":"postalcode"
},
  "geometry": {"coordinates":[-3.07125,55.937731],"type":"Point"}
}