{
  "type": "Feature",
  "properties": {
    "date:inception_lower": "2019-05-01",
    "date:inception_upper": "2019-05-01",
    "iso:country": "GB",
    "wof:name": "ME10 3NH",
    "wof:placetype": "postalcode"
  },
  "geometry": {"coordinates":[0.769652,51.344817],"type":"Point"}
}
