{
  "type": "Feature",
  "properties": {
    "date:inception_lower": "1980-01-01",
    "date:inception_upper": "1980-01-01",
    "iso:country": "GB",
    "wof:name": "TF4 2EW",
    "wof:placetype": "postalcode"
  },
  "geometry": {"coordinates":[-2.457626,52.666956],"type":"Point"}
}
