{
  "type": "Feature",
  "properties": {
    "iso:country":"GB",
    "wof:name":"TF4 2EW",
    "wof:placetype":"postalcode"
},
  "geometry": {"coordinates":[-2.45762640127586,52.66695592849204],"type":"Point"}
}