{
  "type": "Feature",
  "properties": {
    "date:inception_lower": "1980-01-01",
    "date:inception_upper": "1980-01-01",
    "iso:country": "GB",
    "wof:name": "ST5 5JN",
    "wof:placetype": "postalcode"
  },
  "geometry": {"coordinates":[-2.280754,52.937756],"type":"Point"}
}
