{
  "type": "Feature",
  "properties": {
    "iso:country":"GB",
    "wof:name":"ST5 5JN",
    "wof:placetype":"postalcode"
},
  "geometry": {"coordinates":[-2.28203614571173,52.93795313471946],"type":"Point"}
}