{
  "type": "Feature",
  "properties": {
    "iso:country": "GB",
    "wof:name": "CA7 8BD",
    "wof:placetype": "postalcode"
  },
  "geometry": {"coordinates":[-3.064936,54.831071],"type":"Point"}
}
