{
  "type": "Feature",
  "properties": {
    "iso:country":"GB",
    "wof:name":"CA7 8BD",
    "wof:placetype":"postalcode"
},
  "geometry": {"coordinates":[-3.06493573433472,54.83107103421661],"type":"Point"}
}