{
  "type": "Feature",
  "properties": {
    "iso:country":"GB",
    "wof:name":"ST5 6RB",
    "wof:placetype":"postalcode"
},
  "geometry": {"coordinates":[-2.28543917832185,53.01858736768937],"type":"Point"}
}