{
  "type": "Feature",
  "properties": {
    "iso:country": "GB",
    "wof:name": "ST5 6RB",
    "wof:placetype": "postalcode"
  },
  "geometry": {"coordinates":[-2.285439,53.018587],"type":"Point"}
}
