{
  "type": "Feature",
  "properties": {
    "iso:country":"GB",
    "wof:name":"TF7 5TZ",
    "wof:placetype":"postalcode"
},
  "geometry": {"coordinates":[-2.46660063997783,52.64183946151163],"type":"Point"}
}