{
  "type": "Feature",
  "properties": {
    "date:inception_lower": "1994-12-01",
    "date:inception_upper": "1994-12-01",
    "iso:country": "GB",
    "wof:name": "TF7 5TZ",
    "wof:placetype": "postalcode"
  },
  "geometry": {"coordinates":[-2.466601,52.641839],"type":"Point"}
}
