{
  "type": "Feature",
  "properties": {
    "iso:country":"GB",
    "wof:name":"PL27 7EU",
    "wof:placetype":"postalcode"
},
  "geometry": {"coordinates":[-4.84204477413778,50.51872724827263],"type":"Point"}
}