{
  "type": "Feature",
  "properties": {
    "date:inception_lower":"1980-01-01",
    "date:inception_upper":"1980-01-31",
    "iso:country":"GB",
    "wof:name":"BN11 1UP",
    "wof:placetype":"postalcode"
},
  "geometry": {"coordinates":[-0.377508,50.818435],"type":"Point"}
}