{
  "type": "Feature",
  "properties": {
    "iso:country":"GB",
    "wof:name":"NN3 7SB",
    "wof:placetype":"postalcode"
},
  "geometry": {"coordinates":[-0.85709461918895,52.28943643705116],"type":"Point"}
}