{
  "type": "Feature",
  "properties": {
    "iso:country":"GB",
    "wof:name":"BB5 4JB",
    "wof:placetype":"postalcode"
},
  "geometry": {"coordinates":[-2.38899724054639,53.75537973416932],"type":"Point"}
}