{
  "type": "Feature",
  "properties": {
    "iso:country":"GB",
    "wof:name":"TR18 3LN",
    "wof:placetype":"postalcode"
},
  "geometry": {"coordinates":[-5.53195222840589,50.12322923416735],"type":"Point"}
}