{
  "type": "Feature",
  "properties": {
    "iso:country":"GB",
    "wof:name":"GL5 5AF",
    "wof:placetype":"postalcode"
},
  "geometry": {"coordinates":[-2.2185518053178,51.71053624527504],"type":"Point"}
}