{
  "type": "Feature",
  "properties": {
    "iso:country":"GB",
    "wof:name":"CV11 5HF",
    "wof:placetype":"postalcode"
},
  "geometry": {"coordinates":[-1.4855174697581,52.52473884288478],"type":"Point"}
}