{
  "type": "Feature",
  "properties": {
    "date:inception_lower":"2006-10-01",
    "date:inception_upper":"2006-10-31",
    "iso:country":"GB",
    "wof:name":"CO2 7TF",
    "wof:placetype":"postalcode"
},
  "geometry": {"coordinates":[0.899696,51.87165],"type":"Point"}
}