{
  "type": "Feature",
  "properties": {
    "iso:country": "GB",
    "wof:name": "CO2 7TF",
    "wof:placetype": "postalcode"
  },
  "geometry": {"coordinates":[0.899696,51.87165],"type":"Point"}
}
