{
  "type": "Feature",
  "properties": {
    "iso:country":"GB",
    "wof:name":"CO2 7TF",
    "wof:placetype":"postalcode"
},
  "geometry": {"coordinates":[0.89969619773327,51.8716498331934],"type":"Point"}
}