{
  "type": "Feature",
  "properties": {
    "iso:country":"GB",
    "wof:name":"EX6 8LN",
    "wof:placetype":"postalcode"
},
  "geometry": {"coordinates":[-3.47416760636457,50.63849899222465],"type":"Point"}
}