{
  "type": "Feature",
  "properties": {
    "iso:country":"GB",
    "wof:name":"LA14 4TG",
    "wof:placetype":"postalcode"
},
  "geometry": {"coordinates":[-3.23025797949773,54.13884701491682],"type":"Point"}
}