{
  "type": "Feature",
  "properties": {
    "iso:country": "GB",
    "wof:name": "GL3 4AY",
    "wof:placetype": "postalcode"
  },
  "geometry": {"coordinates":[-2.165398,51.850524],"type":"Point"}
}
