{
  "type": "Feature",
  "properties": {
    "date:inception_lower": "2015-07-01",
    "date:inception_upper": "2015-07-01",
    "iso:country": "GB",
    "wof:name": "WR10 2FD",
    "wof:placetype": "postalcode"
  },
  "geometry": {"coordinates":[-2.067761,52.131107],"type":"Point"}
}
