{
  "type": "Feature",
  "properties": {
    "iso:country":"GB",
    "wof:name":"WR10 2FD",
    "wof:placetype":"postalcode"
},
  "geometry": {"coordinates":[-2.06624754559905,52.1299360207023],"type":"Point"}
}