{
  "type": "Feature",
  "properties": {
    "iso:country": "GB",
    "wof:name": "HG4 3PX",
    "wof:placetype": "postalcode"
  },
  "geometry": {"coordinates":[-1.651004,54.140011],"type":"Point"}
}
