{
  "type": "Feature",
  "properties": {
    "date:inception_lower": "1987-04-01",
    "date:inception_upper": "1987-04-01",
    "iso:country": "GB",
    "wof:name": "B97 4SD",
    "wof:placetype": "postalcode"
  },
  "geometry": {"coordinates":[-1.946996,52.305129],"type":"Point"}
}
