{
  "type": "Feature",
  "properties": {
    "iso:country": "GB",
    "wof:name": "CA3 9AP",
    "wof:placetype": "postalcode"
  },
  "geometry": {"coordinates":[-2.928254,54.907107],"type":"Point"}
}
