{
  "type": "Feature",
  "properties": {
    "iso:country":"GB",
    "wof:name":"CM5 9BT",
    "wof:placetype":"postalcode"
},
  "geometry": {"coordinates":[0.24400471215195,51.69558772329273],"type":"Point"}
}