{
  "type": "Feature",
  "properties": {
    "iso:country": "GB",
    "wof:name": "CM5 9BT",
    "wof:placetype": "postalcode"
  },
  "geometry": {"coordinates":[0.244005,51.695588],"type":"Point"}
}
