{
  "type": "Feature",
  "properties": {
    "date:inception_lower": "1980-01-01",
    "date:inception_upper": "1980-01-01",
    "iso:country": "GB",
    "wof:name": "RM15 5JS",
    "wof:placetype": "postalcode"
  },
  "geometry": {"coordinates":[0.271483,51.506325],"type":"Point"}
}
