{
  "type": "Feature",
  "properties": {
    "iso:country": "GB",
    "wof:name": "RM15 5JS",
    "wof:placetype": "postalcode"
  },
  "geometry": {"coordinates":[0.271483,51.506325],"type":"Point"}
}
