{
  "type": "Feature",
  "properties": {
    "iso:country":"GB",
    "wof:name":"RM15 5JS",
    "wof:placetype":"postalcode"
},
  "geometry": {"coordinates":[0.27148252418901,51.50632513213961],"type":"Point"}
}