{
  "type": "Feature",
  "properties": {
    "iso:country": "GB",
    "wof:name": "GU3 3HL",
    "wof:placetype": "postalcode"
  },
  "geometry": {"coordinates":[-0.599707,51.261471],"type":"Point"}
}
