{
  "type": "Feature",
  "properties": {
    "iso:country":"GB",
    "wof:name":"GU3 3HL",
    "wof:placetype":"postalcode"
},
  "geometry": {"coordinates":[-0.59970711280732,51.26147131336032],"type":"Point"}
}