{
  "type": "Feature",
  "properties": {
    "iso:country":"GB",
    "wof:name":"SS8 8HR",
    "wof:placetype":"postalcode"
},
  "geometry": {"coordinates":[0.6071664573178,51.52713109756785],"type":"Point"}
}