{
  "type": "Feature",
  "properties": {
    "iso:country": "GB",
    "wof:name": "PE11 2RN",
    "wof:placetype": "postalcode"
  },
  "geometry": {"coordinates":[-0.150051,52.780337],"type":"Point"}
}
