{
  "type": "Feature",
  "properties": {
    "iso:country": "GB",
    "wof:name": "SN15 2NS",
    "wof:placetype": "postalcode"
  },
  "geometry": {"coordinates":[-2.138142,51.441816],"type":"Point"}
}
