{
  "type": "Feature",
  "properties": {
    "iso:country":"GB",
    "wof:name":"SN15 2NS",
    "wof:placetype":"postalcode"
},
  "geometry": {"coordinates":[-2.1381464194282,51.44181703650173],"type":"Point"}
}