{
  "type": "Feature",
  "properties": {
    "date:inception_lower":"1980-01-01",
    "date:inception_upper":"1980-01-31",
    "iso:country":"GB",
    "wof:name":"SN15 2NS",
    "wof:placetype":"postalcode"
},
  "geometry": {"coordinates":[-2.138142,51.441816],"type":"Point"}
}