{
  "type": "Feature",
  "properties": {
    "date:inception_lower": "1981-06-01",
    "date:inception_upper": "1981-06-01",
    "iso:country": "GB",
    "wof:name": "WF11 8TA",
    "wof:placetype": "postalcode"
  },
  "geometry": {"coordinates":[-1.276898,53.712999],"type":"Point"}
}
