{
  "type": "Feature",
  "properties": {
    "iso:country": "GB",
    "wof:name": "WF11 8TA",
    "wof:placetype": "postalcode"
  },
  "geometry": {"coordinates":[-1.276898,53.712999],"type":"Point"}
}
