{
  "type": "Feature",
  "properties": {
    "iso:country":"GB",
    "wof:name":"EH19 2NT",
    "wof:placetype":"postalcode"
},
  "geometry": {"coordinates":[-3.11676080870758,55.86975585976226],"type":"Point"}
}