{
  "type": "Feature",
  "properties": {
    "iso:country":"GB",
    "wof:name":"AL4 0XD",
    "wof:placetype":"postalcode"
},
  "geometry": {"coordinates":[-0.29989787948317,51.75430113518441],"type":"Point"}
}