{
  "type": "Feature",
  "properties": {
    "iso:country": "GB",
    "wof:name": "AL4 0XD",
    "wof:placetype": "postalcode"
  },
  "geometry": {"coordinates":[-0.299898,51.754301],"type":"Point"}
}
