{
  "type": "Feature",
  "properties": {
    "date:inception_lower":"1980-01-01",
    "date:inception_upper":"1980-01-31",
    "iso:country":"GB",
    "wof:name":"SW16 5EA",
    "wof:placetype":"postalcode"
},
  "geometry": {"coordinates":[-0.132475,51.414409],"type":"Point"}
}