{
  "type": "Feature",
  "properties": {
    "date:inception_lower": "1980-01-01",
    "date:inception_upper": "1980-01-01",
    "iso:country": "GB",
    "wof:name": "BD21 2RN",
    "wof:placetype": "postalcode"
  },
  "geometry": {"coordinates":[-1.924472,53.86973],"type":"Point"}
}
