{
  "type": "Feature",
  "properties": {
    "iso:country":"GB",
    "wof:name":"WN8 8QY",
    "wof:placetype":"postalcode"
},
  "geometry": {"coordinates":[-2.79225700199149,53.55577237272037],"type":"Point"}
}