{
  "type": "Feature",
  "properties": {
    "date:inception_lower":"1988-03-01",
    "date:inception_upper":"1988-03-31",
    "iso:country":"GB",
    "wof:name":"CT14 6TL",
    "wof:placetype":"postalcode"
},
  "geometry": {"coordinates":[1.396311,51.230816],"type":"Point"}
}