{
  "type": "Feature",
  "properties": {
    "iso:country": "GB",
    "wof:name": "CT14 6TL",
    "wof:placetype": "postalcode"
  },
  "geometry": {"coordinates":[1.396311,51.230816],"type":"Point"}
}
