{
  "type": "Feature",
  "properties": {
    "iso:country":"GB",
    "wof:name":"DE55 6FH",
    "wof:placetype":"postalcode"
},
  "geometry": {"coordinates":[-1.44976351538106,53.1484781196289],"type":"Point"}
}