{
  "type": "Feature",
  "properties": {
    "iso:country": "GB",
    "wof:name": "DE55 6FH",
    "wof:placetype": "postalcode"
  },
  "geometry": {"coordinates":[-1.449763,53.148478],"type":"Point"}
}
