{
  "type": "Feature",
  "properties": {
    "date:inception_lower": "1980-01-01",
    "date:inception_upper": "1980-01-01",
    "iso:country": "GB",
    "wof:name": "RH15 0BJ",
    "wof:placetype": "postalcode"
  },
  "geometry": {"coordinates":[-0.12431,50.941248],"type":"Point"}
}
