{
  "type": "Feature",
  "properties": {
    "iso:country": "GB",
    "wof:name": "AB30 1BY",
    "wof:placetype": "postalcode"
  },
  "geometry": {"coordinates":[-2.567591,56.84189],"type":"Point"}
}
