{
  "type": "Feature",
  "properties": {
    "date:inception_lower": "1990-08-01",
    "date:inception_upper": "1990-08-01",
    "iso:country": "GB",
    "wof:name": "AB30 1BY",
    "wof:placetype": "postalcode"
  },
  "geometry": {"coordinates":[-2.567591,56.84189],"type":"Point"}
}
