{
  "type": "Feature",
  "properties": {
    "iso:country":"GB",
    "wof:name":"AB30 1BY",
    "wof:placetype":"postalcode"
},
  "geometry": {"coordinates":[-2.56759089471774,56.84188963052061],"type":"Point"}
}