{
  "type": "Feature",
  "properties": {
    "iso:country": "GB",
    "wof:name": "NE17 7PT",
    "wof:placetype": "postalcode"
  },
  "geometry": {"coordinates":[-1.828622,54.901529],"type":"Point"}
}
