{
  "type": "Feature",
  "properties": {
    "iso:country":"GB",
    "wof:name":"BN17 7LW",
    "wof:placetype":"postalcode"
},
  "geometry": {"coordinates":[-0.54239761242565,50.82444226702453],"type":"Point"}
}