{
  "type": "Feature",
  "properties": {
    "iso:country": "GB",
    "wof:name": "BN17 7LW",
    "wof:placetype": "postalcode"
  },
  "geometry": {"coordinates":[-0.542398,50.824442],"type":"Point"}
}
