{
  "type": "Feature",
  "properties": {
    "iso:country":"GB",
    "wof:name":"CA6 4JX",
    "wof:placetype":"postalcode"
},
  "geometry": {"coordinates":[-2.86082813556269,54.96187337658696],"type":"Point"}
}