{
  "type": "Feature",
  "properties": {
    "date:inception_lower": "1980-01-01",
    "date:inception_upper": "1980-01-01",
    "iso:country": "GB",
    "wof:name": "CA6 4JX",
    "wof:placetype": "postalcode"
  },
  "geometry": {"coordinates":[-2.860828,54.961873],"type":"Point"}
}
