{
  "type": "Feature",
  "properties": {
    "iso:country":"GB",
    "wof:name":"DY1 4HW",
    "wof:placetype":"postalcode"
},
  "geometry": {"coordinates":[-2.09057786261035,52.52036408173147],"type":"Point"}
}