{
  "type": "Feature",
  "properties": {
    "iso:country":"GB",
    "wof:name":"B42 2PR",
    "wof:placetype":"postalcode"
},
  "geometry": {"coordinates":[-1.90900506177476,52.53742697044414],"type":"Point"}
}