{
  "type": "Feature",
  "properties": {
    "iso:country":"GB",
    "wof:name":"CM8 1BZ",
    "wof:placetype":"postalcode"
},
  "geometry": {"coordinates":[0.63682834784786,51.79287949079477],"type":"Point"}
}