{
  "type": "Feature",
  "properties": {
    "date:inception_lower": "1980-01-01",
    "date:inception_upper": "1980-01-01",
    "iso:country": "GB",
    "wof:name": "CM8 1BZ",
    "wof:placetype": "postalcode"
  },
  "geometry": {"coordinates":[0.637482,51.792199],"type":"Point"}
}
