{
  "type": "Feature",
  "properties": {
    "date:inception_lower": "1980-01-01",
    "date:inception_upper": "1980-01-01",
    "iso:country": "GB",
    "wof:name": "CM23 4AX",
    "wof:placetype": "postalcode"
  },
  "geometry": {"coordinates":[0.156015,51.837753],"type":"Point"}
}
