{
  "type": "Feature",
  "properties": {
    "iso:country":"GB",
    "wof:name":"CM23 4AX",
    "wof:placetype":"postalcode"
},
  "geometry": {"coordinates":[0.15601531487672,51.83775330067225],"type":"Point"}
}