{
  "type": "Feature",
  "properties": {
    "iso:country": "GB",
    "wof:name": "GL16 7PD",
    "wof:placetype": "postalcode"
  },
  "geometry": {"coordinates":[-2.611409,51.837128],"type":"Point"}
}
