{
  "type": "Feature",
  "properties": {
    "date:inception_lower": "1983-03-01",
    "date:inception_upper": "1983-03-01",
    "iso:country": "GB",
    "wof:name": "LS25 6LB",
    "wof:placetype": "postalcode"
  },
  "geometry": {"coordinates":[-1.244752,53.798081],"type":"Point"}
}
