{
  "type": "Feature",
  "properties": {
    "iso:country":"GB",
    "wof:name":"CW12 3QP",
    "wof:placetype":"postalcode"
},
  "geometry": {"coordinates":[-2.17116734204384,53.15858654230807],"type":"Point"}
}