{
  "type": "Feature",
  "properties": {
    "iso:country": "GB",
    "wof:name": "CW12 3QP",
    "wof:placetype": "postalcode"
  },
  "geometry": {"coordinates":[-2.171615,53.158334],"type":"Point"}
}
