{
  "type": "Feature",
  "properties": {
    "iso:country":"GB",
    "wof:name":"NE4 6PY",
    "wof:placetype":"postalcode"
},
  "geometry": {"coordinates":[-1.63975413467541,54.97222509893179],"type":"Point"}
}