{
  "type": "Feature",
  "properties": {
    "iso:country": "GB",
    "wof:name": "NE4 6PY",
    "wof:placetype": "postalcode"
  },
  "geometry": {"coordinates":[-1.639754,54.972225],"type":"Point"}
}
