{
  "type": "Feature",
  "properties": {
    "iso:country":"GB",
    "wof:name":"LA6 2NJ",
    "wof:placetype":"postalcode"
},
  "geometry": {"coordinates":[-2.61206576413259,54.17852196893287],"type":"Point"}
}