{
  "type": "Feature",
  "properties": {
    "date:inception_lower": "1993-01-01",
    "date:inception_upper": "1993-01-01",
    "iso:country": "GB",
    "wof:name": "LA6 2NJ",
    "wof:placetype": "postalcode"
  },
  "geometry": {"coordinates":[-2.612066,54.178522],"type":"Point"}
}
