{
  "type": "Feature",
  "properties": {
    "date:inception_lower": "1984-10-01",
    "date:inception_upper": "1984-10-01",
    "iso:country": "GB",
    "wof:name": "MK8 8LH",
    "wof:placetype": "postalcode"
  },
  "geometry": {"coordinates":[-0.800878,52.038248],"type":"Point"}
}
