{
  "type": "Feature",
  "properties": {
    "iso:country":"GB",
    "wof:name":"E18 2JL",
    "wof:placetype":"postalcode"
},
  "geometry": {"coordinates":[0.02031819966998,51.59475965214139],"type":"Point"}
}