{
  "type": "Feature",
  "properties": {
    "iso:country":"GB",
    "wof:name":"NE71 6XJ",
    "wof:placetype":"postalcode"
},
  "geometry": {"coordinates":[-2.15252959099267,55.56701629252881],"type":"Point"}
}