{
  "type": "Feature",
  "properties": {
    "iso:country":"GB",
    "wof:name":"S6 1LB",
    "wof:placetype":"postalcode"
},
  "geometry": {"coordinates":[-1.49422855802987,53.42189064899641],"type":"Point"}
}