{
  "type": "Feature",
  "properties": {
    "date:inception_lower": "1980-01-01",
    "date:inception_upper": "1980-01-01",
    "iso:country": "GB",
    "wof:name": "ME8 7UT",
    "wof:placetype": "postalcode"
  },
  "geometry": {"coordinates":[0.629278,51.37175],"type":"Point"}
}
