{
  "type": "Feature",
  "properties": {
    "iso:country":"GB",
    "wof:name":"ME8 7UT",
    "wof:placetype":"postalcode"
},
  "geometry": {"coordinates":[0.62926205291388,51.3717220951599],"type":"Point"}
}