{
  "type": "Feature",
  "properties": {
    "iso:country": "GB",
    "wof:name": "CT15 7ER",
    "wof:placetype": "postalcode"
  },
  "geometry": {"coordinates":[1.249268,51.161425],"type":"Point"}
}
