{
  "type": "Feature",
  "properties": {
    "date:inception_lower":"1980-01-01",
    "date:inception_upper":"1980-01-31",
    "iso:country":"GB",
    "wof:name":"CT15 7ER",
    "wof:placetype":"postalcode"
},
  "geometry": {"coordinates":[1.249268,51.161425],"type":"Point"}
}