{
  "type": "Feature",
  "properties": {
    "iso:country":"GB",
    "wof:name":"PR8 5AL",
    "wof:placetype":"postalcode"
},
  "geometry": {"coordinates":[-3.0079944483408,53.63732944346074],"type":"Point"}
}