{
  "type": "Feature",
  "properties": {
    "iso:country":"GB",
    "wof:name":"HR8 2SQ",
    "wof:placetype":"postalcode"
},
  "geometry": {"coordinates":[-2.49582199047773,52.06258751588032],"type":"Point"}
}