{
  "type": "Feature",
  "properties": {
    "iso:country": "GB",
    "wof:name": "HR8 2SQ",
    "wof:placetype": "postalcode"
  },
  "geometry": {"coordinates":[-2.49582,52.062598],"type":"Point"}
}
