{
  "type": "Feature",
  "properties": {
    "iso:country":"GB",
    "wof:name":"OL4 3EE",
    "wof:placetype":"postalcode"
},
  "geometry": {"coordinates":[-2.08594691091676,53.5430866444574],"type":"Point"}
}