{
  "type": "Feature",
  "properties": {
    "iso:country":"GB",
    "wof:name":"SP10 2HY",
    "wof:placetype":"postalcode"
},
  "geometry": {"coordinates":[-1.48490453553207,51.20114539607064],"type":"Point"}
}