{
  "type": "Feature",
  "properties": {
    "iso:country": "GB",
    "wof:name": "TR10 8HT",
    "wof:placetype": "postalcode"
  },
  "geometry": {"coordinates":[-5.103,50.168],"type":"Point"}
}
