{
  "type": "Feature",
  "properties": {
    "iso:country":"GB",
    "wof:name":"NE9 6EH",
    "wof:placetype":"postalcode"
},
  "geometry": {"coordinates":[-1.60097182748901,54.93376858639216],"type":"Point"}
}