{
  "type": "Feature",
  "properties": {
    "date:inception_lower":"2013-04-01",
    "date:inception_upper":"2013-04-30",
    "iso:country":"GB",
    "wof:name":"EH17 8PZ",
    "wof:placetype":"postalcode"
},
  "geometry": {"coordinates":[-3.138465,55.90474],"type":"Point"}
}