{
  "type": "Feature",
  "properties": {
    "iso:country":"GB",
    "wof:name":"EH17 8PZ",
    "wof:placetype":"postalcode"
},
  "geometry": {"coordinates":[-3.13832127705342,55.90478147121738],"type":"Point"}
}