{
  "type": "Feature",
  "properties": {
    "iso:country":"GB",
    "wof:name":"G44 4UA",
    "wof:placetype":"postalcode"
},
  "geometry": {"coordinates":[-4.2567588366332,55.82521386523769],"type":"Point"}
}