{
  "type": "Feature",
  "properties": {
    "date:inception_lower": "2017-01-01",
    "date:inception_upper": "2017-01-01",
    "iso:country": "GB",
    "wof:name": "LE9 6TA",
    "wof:placetype": "postalcode"
  },
  "geometry": {"coordinates":[-1.216301,52.532658],"type":"Point"}
}
