{
  "type": "Feature",
  "properties": {
    "iso:country": "GB",
    "wof:name": "LE9 6TA",
    "wof:placetype": "postalcode"
  },
  "geometry": {"coordinates":[-1.219417,52.533209],"type":"Point"}
}
