{
  "type": "Feature",
  "properties": {
    "iso:country":"GB",
    "wof:name":"SS17 0LF",
    "wof:placetype":"postalcode"
},
  "geometry": {"coordinates":[0.42044933517521,51.51342606649049],"type":"Point"}
}