{
  "type": "Feature",
  "properties": {
    "iso:country":"GB",
    "wof:name":"CW3 9PD",
    "wof:placetype":"postalcode"
},
  "geometry": {"coordinates":[-2.33475730894088,52.99630031147576],"type":"Point"}
}