{
  "type": "Feature",
  "properties": {
    "iso:country": "GB",
    "wof:name": "CW3 9PD",
    "wof:placetype": "postalcode"
  },
  "geometry": {"coordinates":[-2.334757,52.9963],"type":"Point"}
}
