{
  "type": "Feature",
  "properties": {
    "iso:country": "GB",
    "wof:name": "EX19 8UB",
    "wof:placetype": "postalcode"
  },
  "geometry": {"coordinates":[-3.946049,50.856162],"type":"Point"}
}
