{
  "type": "Feature",
  "properties": {
    "date:inception_lower": "2000-12-01",
    "date:inception_upper": "2000-12-01",
    "iso:country": "GB",
    "wof:name": "EX19 8UB",
    "wof:placetype": "postalcode"
  },
  "geometry": {"coordinates":[-3.946161,50.856134],"type":"Point"}
}
