{
  "type": "Feature",
  "properties": {
    "iso:country":"GB",
    "wof:name":"EX19 8UB",
    "wof:placetype":"postalcode"
},
  "geometry": {"coordinates":[-3.94602717689533,50.8561699408959],"type":"Point"}
}