{
  "type": "Feature",
  "properties": {
    "date:inception_lower": "1987-05-01",
    "date:inception_upper": "1987-05-01",
    "iso:country": "GB",
    "wof:name": "KA17 0HW",
    "wof:placetype": "postalcode"
  },
  "geometry": {"coordinates":[-4.27168,55.6107],"type":"Point"}
}
