{
  "type": "Feature",
  "properties": {
    "iso:country": "GB",
    "wof:name": "KA17 0HW",
    "wof:placetype": "postalcode"
  },
  "geometry": {"coordinates":[-4.27168,55.6107],"type":"Point"}
}
