{
  "type": "Feature",
  "properties": {
    "iso:country": "GB",
    "wof:name": "EX32 7HQ",
    "wof:placetype": "postalcode"
  },
  "geometry": {"coordinates":[-4.04816,51.085356],"type":"Point"}
}
