{
  "type": "Feature",
  "properties": {
    "iso:country":"GB",
    "wof:name":"WF13 2AL",
    "wof:placetype":"postalcode"
},
  "geometry": {"coordinates":[-1.63484856179908,53.69555957047599],"type":"Point"}
}