{
  "type": "Feature",
  "properties": {
    "date:inception_lower":"1991-09-01",
    "date:inception_upper":"1991-09-30",
    "iso:country":"GB",
    "wof:name":"IP27 0SP",
    "wof:placetype":"postalcode"
},
  "geometry": {"coordinates":[0.634445,52.442387],"type":"Point"}
}