{
  "type": "Feature",
  "properties": {
    "iso:country": "GB",
    "wof:name": "TF9 4PE",
    "wof:placetype": "postalcode"
  },
  "geometry": {"coordinates":[-2.387519,52.920181],"type":"Point"}
}
