{
  "type": "Feature",
  "properties": {
    "date:inception_lower": "2015-09-01",
    "date:inception_upper": "2015-09-01",
    "iso:country": "GB",
    "wof:name": "CM22 6TW",
    "wof:placetype": "postalcode"
  },
  "geometry": {"coordinates":[0.279224,51.868719],"type":"Point"}
}
