{
  "type": "Feature",
  "properties": {
    "date:inception_lower": "1981-06-01",
    "date:inception_upper": "1981-06-01",
    "iso:country": "GB",
    "wof:name": "NW10 7LT",
    "wof:placetype": "postalcode"
  },
  "geometry": {"coordinates":[-0.270027,51.526877],"type":"Point"}
}
