{
  "type": "Feature",
  "properties": {
    "iso:country":"GB",
    "wof:name":"NN3 7UY",
    "wof:placetype":"postalcode"
},
  "geometry": {"coordinates":[-0.84106385361261,52.28796759215503],"type":"Point"}
}