{
  "type": "Feature",
  "properties": {
    "iso:country":"GB",
    "wof:name":"WA4 3HU",
    "wof:placetype":"postalcode"
},
  "geometry": {"coordinates":[-2.53906971576991,53.36602187025367],"type":"Point"}
}