{
  "type": "Feature",
  "properties": {
    "date:inception_lower": "2021-10-01",
    "date:inception_upper": "2021-10-01",
    "iso:country": "GB",
    "wof:name": "OL3 7FY",
    "wof:placetype": "postalcode"
  },
  "geometry": {"coordinates":[-2.010115,53.540878],"type":"Point"}
}
