{
  "type": "Feature",
  "properties": {
    "iso:country":"GB",
    "wof:name":"SR5 1DY",
    "wof:placetype":"postalcode"
},
  "geometry": {"coordinates":[-1.38787194025738,54.91871120004066],"type":"Point"}
}