{
  "type": "Feature",
  "properties": {
    "iso:country": "GB",
    "wof:name": "CV47 2TJ",
    "wof:placetype": "postalcode"
  },
  "geometry": {"coordinates":[-1.428911,52.170017],"type":"Point"}
}
