{
  "type": "Feature",
  "properties": {
    "iso:country":"GB",
    "wof:name":"CV47 2TJ",
    "wof:placetype":"postalcode"
},
  "geometry": {"coordinates":[-1.42892235490606,52.17000193359263],"type":"Point"}
}