{
  "type": "Feature",
  "properties": {
    "date:inception_lower":"1999-12-01",
    "date:inception_upper":"1999-12-31",
    "iso:country":"GB",
    "wof:name":"CV47 2TJ",
    "wof:placetype":"postalcode"
},
  "geometry": {"coordinates":[-1.428911,52.170017],"type":"Point"}
}