{
  "type": "Feature",
  "properties": {
    "iso:country":"GB",
    "wof:name":"NE64 6RH",
    "wof:placetype":"postalcode"
},
  "geometry": {"coordinates":[-1.51925619457246,55.18336066449073],"type":"Point"}
}