{
  "type": "Feature",
  "properties": {
    "iso:country":"GB",
    "wof:name":"NE40 4SQ",
    "wof:placetype":"postalcode"
},
  "geometry": {"coordinates":[-1.77961960891994,54.95395713188091],"type":"Point"}
}