{
  "type": "Feature",
  "properties": {
    "date:inception_lower": "1980-01-01",
    "date:inception_upper": "1980-01-01",
    "iso:country": "GB",
    "wof:name": "NE40 4SQ",
    "wof:placetype": "postalcode"
  },
  "geometry": {"coordinates":[-1.77962,54.953957],"type":"Point"}
}
