{
  "type": "Feature",
  "properties": {
    "date:inception_lower": "1980-01-01",
    "date:inception_upper": "1980-01-01",
    "iso:country": "GB",
    "wof:name": "LL55 3PA",
    "wof:placetype": "postalcode"
  },
  "geometry": {"coordinates":[-4.151332,53.143109],"type":"Point"}
}
