{
  "type": "Feature",
  "properties": {
    "iso:country":"GB",
    "wof:name":"LL55 3PA",
    "wof:placetype":"postalcode"
},
  "geometry": {"coordinates":[-4.15018108400226,53.14411953935259],"type":"Point"}
}