{
  "type": "Feature",
  "properties": {
    "iso:country": "GB",
    "wof:name": "LL55 3PA",
    "wof:placetype": "postalcode"
  },
  "geometry": {"coordinates":[-4.151361,53.143081],"type":"Point"}
}
