{
  "type": "Feature",
  "properties": {
    "date:inception_lower": "2022-05-01",
    "date:inception_upper": "2022-05-01",
    "iso:country": "GB",
    "wof:name": "FK6 6FN",
    "wof:placetype": "postalcode"
  },
  "geometry": {"coordinates":[-3.915466,56.035516],"type":"Point"}
}
