{
  "type": "Feature",
  "properties": {
    "date:inception_lower": "1980-01-01",
    "date:inception_upper": "1980-01-01",
    "iso:country": "GB",
    "wof:name": "OX12 8JS",
    "wof:placetype": "postalcode"
  },
  "geometry": {"coordinates":[-1.343395,51.597693],"type":"Point"}
}
