{
  "type": "Feature",
  "properties": {
    "iso:country":"GB",
    "wof:name":"PL7 1PL",
    "wof:placetype":"postalcode"
},
  "geometry": {"coordinates":[-4.02803832689757,50.3879706059797],"type":"Point"}
}