{
  "type": "Feature",
  "properties": {
    "iso:country":"GB",
    "wof:name":"HX2 8AF",
    "wof:placetype":"postalcode"
},
  "geometry": {"coordinates":[-1.88908928647284,53.7407529086887],"type":"Point"}
}