{
  "type": "Feature",
  "properties": {
    "iso:country":"GB",
    "wof:name":"NW11 8PS",
    "wof:placetype":"postalcode"
},
  "geometry": {"coordinates":[-0.20763468768016,51.57147622605581],"type":"Point"}
}