{
  "type": "Feature",
  "properties": {
    "date:inception_lower": "1994-05-01",
    "date:inception_upper": "1994-05-01",
    "iso:country": "GB",
    "wof:name": "M27 8FL",
    "wof:placetype": "postalcode"
  },
  "geometry": {"coordinates":[-2.333639,53.519776],"type":"Point"}
}
