{
  "type": "Feature",
  "properties": {
    "iso:country":"GB",
    "wof:name":"B32 3DX",
    "wof:placetype":"postalcode"
},
  "geometry": {"coordinates":[-1.9720469113241,52.4444485686079],"type":"Point"}
}