{
  "type": "Feature",
  "properties": {
    "iso:country":"GB",
    "wof:name":"HA3 5JW",
    "wof:placetype":"postalcode"
},
  "geometry": {"coordinates":[-0.34425422891825,51.60340031714688],"type":"Point"}
}