{
  "type": "Feature",
  "properties": {
    "iso:country":"GB",
    "wof:name":"ME10 2EE",
    "wof:placetype":"postalcode"
},
  "geometry": {"coordinates":[0.73376434380028,51.3511254178388],"type":"Point"}
}