{
  "type": "Feature",
  "properties": {
    "iso:country":"GB",
    "wof:name":"GL52 2BH",
    "wof:placetype":"postalcode"
},
  "geometry": {"coordinates":[-2.06811093789777,51.9058515491996],"type":"Point"}
}