{
  "type": "Feature",
  "properties": {
    "iso:country": "GB",
    "wof:name": "GL52 2BH",
    "wof:placetype": "postalcode"
  },
  "geometry": {"coordinates":[-2.068111,51.905852],"type":"Point"}
}
