{
  "type": "Feature",
  "properties": {
    "iso:country":"GB",
    "wof:name":"IP4 4SY",
    "wof:placetype":"postalcode"
},
  "geometry": {"coordinates":[1.17376219252185,52.06005663336676],"type":"Point"}
}