{
  "type": "Feature",
  "properties": {
    "date:inception_lower": "2004-10-01",
    "date:inception_upper": "2004-10-01",
    "iso:country": "GB",
    "wof:name": "IP4 4SY",
    "wof:placetype": "postalcode"
  },
  "geometry": {"coordinates":[1.173762,52.060057],"type":"Point"}
}
