{
  "type": "Feature",
  "properties": {
    "iso:country":"GB",
    "wof:name":"HU11 4JQ",
    "wof:placetype":"postalcode"
},
  "geometry": {"coordinates":[-0.28719399226081,53.80818426622425],"type":"Point"}
}