{
  "type": "Feature",
  "properties": {
    "date:inception_lower": "2015-01-01",
    "date:inception_upper": "2015-01-01",
    "iso:country": "GB",
    "wof:name": "ST7 2LY",
    "wof:placetype": "postalcode"
  },
  "geometry": {"coordinates":[-2.321634,53.092771],"type":"Point"}
}
