{
  "type": "Feature",
  "properties": {
    "iso:country":"GB",
    "wof:name":"HA9 7RQ",
    "wof:placetype":"postalcode"
},
  "geometry": {"coordinates":[-0.29986354631493,51.56747127529198],"type":"Point"}
}