{
  "type": "Feature",
  "properties": {
    "iso:country": "GB",
    "wof:name": "DL14 8UR",
    "wof:placetype": "postalcode"
  },
  "geometry": {"coordinates":[-1.641328,54.64398],"type":"Point"}
}
