{
  "type": "Feature",
  "properties": {
    "iso:country": "GB",
    "wof:name": "LN6 0RY",
    "wof:placetype": "postalcode"
  },
  "geometry": {"coordinates":[-0.578158,53.213657],"type":"Point"}
}
