{
  "type": "Feature",
  "properties": {
    "date:inception_lower": "1995-12-01",
    "date:inception_upper": "1995-12-01",
    "iso:country": "GB",
    "wof:name": "LN6 0RY",
    "wof:placetype": "postalcode"
  },
  "geometry": {"coordinates":[-0.578158,53.213657],"type":"Point"}
}
