{
  "type": "Feature",
  "properties": {
    "iso:country":"GB",
    "wof:name":"L32 1TN",
    "wof:placetype":"postalcode"
},
  "geometry": {"coordinates":[-2.89012253875449,53.48825295905646],"type":"Point"}
}