{
  "type": "Feature",
  "properties": {
    "iso:country": "GB",
    "wof:name": "KY5 0HR",
    "wof:placetype": "postalcode"
  },
  "geometry": {"coordinates":[-3.305869,56.168838],"type":"Point"}
}
