{
  "type": "Feature",
  "properties": {
    "iso:country": "GB",
    "wof:name": "SA16 0HZ",
    "wof:placetype": "postalcode"
  },
  "geometry": {"coordinates":[-4.304281,51.710103],"type":"Point"}
}
