{
  "type": "Feature",
  "properties": {
    "date:inception_lower": "1986-07-01",
    "date:inception_upper": "1986-07-01",
    "iso:country": "GB",
    "wof:name": "CH8 8RA",
    "wof:placetype": "postalcode"
  },
  "geometry": {"coordinates":[-3.279253,53.279442],"type":"Point"}
}
