{
  "type": "Feature",
  "properties": {
    "iso:country":"GB",
    "wof:name":"CH8 8RA",
    "wof:placetype":"postalcode"
},
  "geometry": {"coordinates":[-3.2792533929741,53.27944229033956],"type":"Point"}
}