{
  "type": "Feature",
  "properties": {
    "iso:country":"GB",
    "wof:name":"WV14 8HS",
    "wof:placetype":"postalcode"
},
  "geometry": {"coordinates":[-2.08159590130658,52.54050797258997],"type":"Point"}
}