{
  "type": "Feature",
  "properties": {
    "date:inception_lower":"1980-01-01",
    "date:inception_upper":"1980-01-31",
    "iso:country":"GB",
    "wof:name":"WV14 8HS",
    "wof:placetype":"postalcode"
},
  "geometry": {"coordinates":[-2.081596,52.540508],"type":"Point"}
}