{
  "type": "Feature",
  "properties": {
    "iso:country":"GB",
    "wof:name":"E12 6QT",
    "wof:placetype":"postalcode"
},
  "geometry": {"coordinates":[0.05324621977097,51.54692273656237],"type":"Point"}
}