{
  "type": "Feature",
  "properties": {
    "iso:country": "GB",
    "wof:name": "GL2 9LH",
    "wof:placetype": "postalcode"
  },
  "geometry": {"coordinates":[-2.212589,51.910714],"type":"Point"}
}
