{
  "type": "Feature",
  "properties": {
    "iso:country":"GB",
    "wof:name":"GL2 9LH",
    "wof:placetype":"postalcode"
},
  "geometry": {"coordinates":[-2.2124711191372,51.9103633920302],"type":"Point"}
}