{
  "type": "Feature",
  "properties": {
    "iso:country": "GB",
    "wof:name": "SR8 3SD",
    "wof:placetype": "postalcode"
  },
  "geometry": {"coordinates":[-1.321104,54.786676],"type":"Point"}
}
