{
  "type": "Feature",
  "properties": {
    "iso:country":"GB",
    "wof:name":"SR8 3SD",
    "wof:placetype":"postalcode"
},
  "geometry": {"coordinates":[-1.32110421077571,54.78667630513269],"type":"Point"}
}