{
  "type": "Feature",
  "properties": {
    "iso:country":"GB",
    "wof:name":"KA21 6GU",
    "wof:placetype":"postalcode"
},
  "geometry": {"coordinates":[-4.78686227018534,55.64905875758981],"type":"Point"}
}