{
  "type": "Feature",
  "properties": {
    "date:inception_lower": "2010-05-01",
    "date:inception_upper": "2010-05-01",
    "iso:country": "GB",
    "wof:name": "KA21 6GU",
    "wof:placetype": "postalcode"
  },
  "geometry": {"coordinates":[-4.786862,55.649059],"type":"Point"}
}
