{
  "type": "Feature",
  "properties": {
    "date:inception_lower": "2018-09-01",
    "date:inception_upper": "2018-09-01",
    "iso:country": "GB",
    "wof:name": "NE70 7PT",
    "wof:placetype": "postalcode"
  },
  "geometry": {"coordinates":[-1.832674,55.595057],"type":"Point"}
}
