{
  "type": "Feature",
  "properties": {
    "iso:country": "GB",
    "wof:name": "PR5 6NB",
    "wof:placetype": "postalcode"
  },
  "geometry": {"coordinates":[-2.656361,53.723752],"type":"Point"}
}
