{
  "type": "Feature",
  "properties": {
    "date:inception_lower": "2019-03-01",
    "date:inception_upper": "2019-03-01",
    "iso:country": "GB",
    "wof:name": "LE67 2HN",
    "wof:placetype": "postalcode"
  },
  "geometry": {"coordinates":[-1.354169,52.709323],"type":"Point"}
}
