{
  "type": "Feature",
  "properties": {
    "iso:country": "GB",
    "wof:name": "LE67 2HN",
    "wof:placetype": "postalcode"
  },
  "geometry": {"coordinates":[-1.356382,52.708823],"type":"Point"}
}
