{
  "type": "Feature",
  "properties": {
    "date:inception_lower": "1992-08-01",
    "date:inception_upper": "1992-08-01",
    "iso:country": "GB",
    "wof:name": "LA5 0JH",
    "wof:placetype": "postalcode"
  },
  "geometry": {"coordinates":[-2.83048,54.203511],"type":"Point"}
}
