{
  "type": "Feature",
  "properties": {
    "iso:country":"GB",
    "wof:name":"LA5 0JH",
    "wof:placetype":"postalcode"
},
  "geometry": {"coordinates":[-2.8304800506182,54.20351149675041],"type":"Point"}
}