{
  "type": "Feature",
  "properties": {
    "iso:country":"GB",
    "wof:name":"OX49 5BY",
    "wof:placetype":"postalcode"
},
  "geometry": {"coordinates":[-1.00246234695893,51.64684014129106],"type":"Point"}
}