{
  "type": "Feature",
  "properties": {
    "iso:country": "GB",
    "wof:name": "NE25 9HJ",
    "wof:placetype": "postalcode"
  },
  "geometry": {"coordinates":[-1.491623,55.04329],"type":"Point"}
}
