{
  "type": "Feature",
  "properties": {
    "iso:country":"GB",
    "wof:name":"NE25 9HJ",
    "wof:placetype":"postalcode"
},
  "geometry": {"coordinates":[-1.49162313175096,55.04329004138307],"type":"Point"}
}