{
  "type": "Feature",
  "properties": {
    "iso:country": "GB",
    "wof:name": "CA25 5AB",
    "wof:placetype": "postalcode"
  },
  "geometry": {"coordinates":[-3.516826,54.521762],"type":"Point"}
}
