{
  "type": "Feature",
  "properties": {
    "iso:country":"GB",
    "wof:name":"CA25 5AB",
    "wof:placetype":"postalcode"
},
  "geometry": {"coordinates":[-3.51663891554288,54.52175530215371],"type":"Point"}
}