{
  "type": "Feature",
  "properties": {
    "iso:country":"GB",
    "wof:name":"SM3 8AY",
    "wof:placetype":"postalcode"
},
  "geometry": {"coordinates":[-0.21624492329215,51.35819767134478],"type":"Point"}
}