{
  "type": "Feature",
  "properties": {
    "iso:country":"GB",
    "wof:name":"NR6 7PG",
    "wof:placetype":"postalcode"
},
  "geometry": {"coordinates":[1.31375284306158,52.66468639441202],"type":"Point"}
}