{
  "type": "Feature",
  "properties": {
    "date:inception_lower": "2011-12-01",
    "date:inception_upper": "2011-12-01",
    "iso:country": "GB",
    "wof:name": "L32 4UW",
    "wof:placetype": "postalcode"
  },
  "geometry": {"coordinates":[-2.904362,53.480335],"type":"Point"}
}
