{
  "type": "Feature",
  "properties": {
    "iso:country":"GB",
    "wof:name":"L32 4UW",
    "wof:placetype":"postalcode"
},
  "geometry": {"coordinates":[-2.90436240224531,53.4803347980661],"type":"Point"}
}