{
  "type": "Feature",
  "properties": {
    "iso:country":"GB",
    "wof:name":"NG1 5AG",
    "wof:placetype":"postalcode"
},
  "geometry": {"coordinates":[-1.16083955787449,52.95518533695375],"type":"Point"}
}