{
  "type": "Feature",
  "properties": {
    "iso:country": "GB",
    "wof:name": "NG1 5AG",
    "wof:placetype": "postalcode"
  },
  "geometry": {"coordinates":[-1.16084,52.955185],"type":"Point"}
}
