{
  "type": "Feature",
  "properties": {
    "iso:country": "GB",
    "wof:name": "SR2 0LL",
    "wof:placetype": "postalcode"
  },
  "geometry": {"coordinates":[-1.364534,54.868087],"type":"Point"}
}
