{
  "type": "Feature",
  "properties": {
    "date:inception_lower": "1980-01-01",
    "date:inception_upper": "1980-01-01",
    "iso:country": "GB",
    "wof:name": "SR2 0LL",
    "wof:placetype": "postalcode"
  },
  "geometry": {"coordinates":[-1.364534,54.868087],"type":"Point"}
}
