{
  "type": "Feature",
  "properties": {
    "iso:country":"GB",
    "wof:name":"SR2 0LL",
    "wof:placetype":"postalcode"
},
  "geometry": {"coordinates":[-1.36453429510547,54.86808734940111],"type":"Point"}
}