{
  "type": "Feature",
  "properties": {
    "iso:country":"GB",
    "wof:name":"NE29 0QZ",
    "wof:placetype":"postalcode"
},
  "geometry": {"coordinates":[-1.46074799852671,55.00941388759319],"type":"Point"}
}