{
  "type": "Feature",
  "properties": {
    "iso:country": "GB",
    "wof:name": "CT20 2NP",
    "wof:placetype": "postalcode"
  },
  "geometry": {"coordinates":[1.153861,51.082283],"type":"Point"}
}
