{
  "type": "Feature",
  "properties": {
    "iso:country":"GB",
    "wof:name":"CT20 2NP",
    "wof:placetype":"postalcode"
},
  "geometry": {"coordinates":[1.15386098984017,51.08228323470015],"type":"Point"}
}