{
  "type": "Feature",
  "properties": {
    "iso:country":"GB",
    "wof:name":"OX11 0BU",
    "wof:placetype":"postalcode"
},
  "geometry": {"coordinates":[-1.25638798705241,51.60615651434681],"type":"Point"}
}