{
  "type": "Feature",
  "properties": {
    "iso:country":"GB",
    "wof:name":"GL51 7AW",
    "wof:placetype":"postalcode"
},
  "geometry": {"coordinates":[-2.10605312129974,51.89531308832441],"type":"Point"}
}