{
  "type": "Feature",
  "properties": {
    "iso:country": "GB",
    "wof:name": "G14 9BH",
    "wof:placetype": "postalcode"
  },
  "geometry": {"coordinates":[-4.347258,55.881948],"type":"Point"}
}
