{
  "type": "Feature",
  "properties": {
    "iso:country":"GB",
    "wof:name":"G14 9BH",
    "wof:placetype":"postalcode"
},
  "geometry": {"coordinates":[-4.34725806582175,55.88194829881444],"type":"Point"}
}