{
  "type": "Feature",
  "properties": {
    "iso:country": "GB",
    "wof:name": "BD23 3LX",
    "wof:placetype": "postalcode"
  },
  "geometry": {"coordinates":[-2.107078,53.983272],"type":"Point"}
}
