{
  "type": "Feature",
  "properties": {
    "iso:country":"GB",
    "wof:name":"BN17 7BS",
    "wof:placetype":"postalcode"
},
  "geometry": {"coordinates":[-0.5503144607823,50.81178868330006],"type":"Point"}
}