{
  "type": "Feature",
  "properties": {
    "iso:country":"GB",
    "wof:name":"PO18 8QJ",
    "wof:placetype":"postalcode"
},
  "geometry": {"coordinates":[-0.85053678630994,50.82733579390159],"type":"Point"}
}