{
  "type": "Feature",
  "properties": {
    "date:inception_lower": "1980-01-01",
    "date:inception_upper": "1980-01-01",
    "iso:country": "GB",
    "wof:name": "PO18 8QJ",
    "wof:placetype": "postalcode"
  },
  "geometry": {"coordinates":[-0.850537,50.827336],"type":"Point"}
}
