{
  "type": "Feature",
  "properties": {
    "iso:country":"GB",
    "wof:name":"CO12 3LT",
    "wof:placetype":"postalcode"
},
  "geometry": {"coordinates":[1.28767861001883,51.94245185045288],"type":"Point"}
}