{
  "type": "Feature",
  "properties": {
    "iso:country":"GB",
    "wof:name":"WR6 6QZ",
    "wof:placetype":"postalcode"
},
  "geometry": {"coordinates":[-2.36114837889912,52.23456239258261],"type":"Point"}
}