{
  "type": "Feature",
  "properties": {
    "date:inception_lower":"1996-06-01",
    "date:inception_upper":"1996-06-30",
    "iso:country":"GB",
    "wof:name":"SR7 7SL",
    "wof:placetype":"postalcode"
},
  "geometry": {"coordinates":[-1.340184,54.836334],"type":"Point"}
}