{
  "type": "Feature",
  "properties": {
    "iso:country":"GB",
    "wof:name":"SR7 7SL",
    "wof:placetype":"postalcode"
},
  "geometry": {"coordinates":[-1.34018449135863,54.83633381696641],"type":"Point"}
}