{
  "type": "Feature",
  "properties": {
    "iso:country": "GB",
    "wof:name": "SR7 7SL",
    "wof:placetype": "postalcode"
  },
  "geometry": {"coordinates":[-1.340184,54.836334],"type":"Point"}
}
