{
  "type": "Feature",
  "properties": {
    "iso:country":"GB",
    "wof:name":"NR5 8DH",
    "wof:placetype":"postalcode"
},
  "geometry": {"coordinates":[1.2494615795776,52.63295838788535],"type":"Point"}
}