{
  "type": "Feature",
  "properties": {
    "iso:country":"GB",
    "wof:name":"S70 4BE",
    "wof:placetype":"postalcode"
},
  "geometry": {"coordinates":[-1.4562460496565,53.53525829921482],"type":"Point"}
}