{
  "type": "Feature",
  "properties": {
    "date:inception_lower":"1980-01-01",
    "date:inception_upper":"1980-01-31",
    "iso:country":"GB",
    "wof:name":"SE4 1ET",
    "wof:placetype":"postalcode"
},
  "geometry": {"coordinates":[-0.035139,51.455434],"type":"Point"}
}