{
  "type": "Feature",
  "properties": {
    "iso:country":"GB",
    "wof:name":"SE4 1ET",
    "wof:placetype":"postalcode"
},
  "geometry": {"coordinates":[-0.03526809327984,51.45545458219993],"type":"Point"}
}