{
  "type": "Feature",
  "properties": {
    "iso:country": "GB",
    "wof:name": "SE4 1ET",
    "wof:placetype": "postalcode"
  },
  "geometry": {"coordinates":[-0.035139,51.455434],"type":"Point"}
}
