{
  "type": "Feature",
  "properties": {
    "iso:country":"GB",
    "wof:name":"AB56 1LJ",
    "wof:placetype":"postalcode"
},
  "geometry": {"coordinates":[-2.95964469754073,57.67323826609334],"type":"Point"}
}