{
  "type": "Feature",
  "properties": {
    "date:inception_lower": "1980-01-01",
    "date:inception_upper": "1980-01-01",
    "iso:country": "GB",
    "wof:name": "WS14 9BD",
    "wof:placetype": "postalcode"
  },
  "geometry": {"coordinates":[-1.825764,52.675354],"type":"Point"}
}
