{
  "type": "Feature",
  "properties": {
    "iso:country":"GB",
    "wof:name":"WS14 9BD",
    "wof:placetype":"postalcode"
},
  "geometry": {"coordinates":[-1.82576414633347,52.67535392910235],"type":"Point"}
}