{
  "type": "Feature",
  "properties": {
    "iso:country": "GB",
    "wof:name": "WS14 9BD",
    "wof:placetype": "postalcode"
  },
  "geometry": {"coordinates":[-1.825764,52.675354],"type":"Point"}
}
