{
  "type": "Feature",
  "properties": {
    "iso:country":"GB",
    "wof:name":"PE1 4YR",
    "wof:placetype":"postalcode"
},
  "geometry": {"coordinates":[-0.23287989024255,52.57975672442565],"type":"Point"}
}