{
  "type": "Feature",
  "properties": {
    "iso:country":"GB",
    "wof:name":"WF4 4EJ",
    "wof:placetype":"postalcode"
},
  "geometry": {"coordinates":[-1.66915258199931,53.64133449496663],"type":"Point"}
}