{
  "type": "Feature",
  "properties": {
    "iso:country":"GB",
    "wof:name":"L14 1PY",
    "wof:placetype":"postalcode"
},
  "geometry": {"coordinates":[-2.90118629033315,53.41293374427704],"type":"Point"}
}