{
  "type": "Feature",
  "properties": {
    "iso:country":"GB",
    "wof:name":"DH3 1DB",
    "wof:placetype":"postalcode"
},
  "geometry": {"coordinates":[-1.57858219891105,54.89585150890917],"type":"Point"}
}