{
  "type": "Feature",
  "properties": {
    "iso:country":"GB",
    "wof:name":"GL4 4DD",
    "wof:placetype":"postalcode"
},
  "geometry": {"coordinates":[-2.21242407994827,51.83882287564265],"type":"Point"}
}