{
  "type": "Feature",
  "properties": {
    "iso:country": "GB",
    "wof:name": "GL4 4DD",
    "wof:placetype": "postalcode"
  },
  "geometry": {"coordinates":[-2.212424,51.838823],"type":"Point"}
}
