{
  "type": "Feature",
  "properties": {
    "iso:country":"GB",
    "wof:name":"RG41 5PX",
    "wof:placetype":"postalcode"
},
  "geometry": {"coordinates":[-0.88588456317963,51.43237218444119],"type":"Point"}
}