{
  "type": "Feature",
  "properties": {
    "iso:country": "GB",
    "wof:name": "RG41 5PX",
    "wof:placetype": "postalcode"
  },
  "geometry": {"coordinates":[-0.885852,51.432355],"type":"Point"}
}
