{
  "type": "Feature",
  "properties": {
    "iso:country": "GB",
    "wof:name": "RG41 5PX",
    "wof:placetype": "postalcode"
  },
  "geometry": {"coordinates":[-0.885885,51.432372],"type":"Point"}
}
