{
  "type": "Feature",
  "properties": {
    "date:inception_lower": "2007-11-01",
    "date:inception_upper": "2007-11-01",
    "iso:country": "GB",
    "wof:name": "RG41 5PX",
    "wof:placetype": "postalcode"
  },
  "geometry": {"coordinates":[-0.885852,51.432355],"type":"Point"}
}
