{
  "type": "Feature",
  "properties": {
    "iso:country":"GB",
    "wof:name":"DN3 2AW",
    "wof:placetype":"postalcode"
},
  "geometry": {"coordinates":[-1.07169676052832,53.53876181612579],"type":"Point"}
}