{
  "type": "Feature",
  "properties": {
    "iso:country": "GB",
    "wof:name": "DN3 2AW",
    "wof:placetype": "postalcode"
  },
  "geometry": {"coordinates":[-1.071697,53.538762],"type":"Point"}
}
