{
  "type": "Feature",
  "properties": {
    "date:inception_lower": "1980-01-01",
    "date:inception_upper": "1980-01-01",
    "iso:country": "GB",
    "wof:name": "WA11 9BJ",
    "wof:placetype": "postalcode"
  },
  "geometry": {"coordinates":[-2.710454,53.460171],"type":"Point"}
}
