{
  "type": "Feature",
  "properties": {
    "iso:country":"GB",
    "wof:name":"WA11 9BJ",
    "wof:placetype":"postalcode"
},
  "geometry": {"coordinates":[-2.71045444025135,53.46017137528319],"type":"Point"}
}