{
  "type": "Feature",
  "properties": {
    "iso:country":"GB",
    "wof:name":"NE43 7UH",
    "wof:placetype":"postalcode"
},
  "geometry": {"coordinates":[-1.94385980501221,54.98172217264701],"type":"Point"}
}