{
  "type": "Feature",
  "properties": {
    "iso:country": "GB",
    "wof:name": "NE43 7UH",
    "wof:placetype": "postalcode"
  },
  "geometry": {"coordinates":[-1.94386,54.981722],"type":"Point"}
}
