{
  "type": "Feature",
  "properties": {
    "date:inception_lower": "1997-06-01",
    "date:inception_upper": "1997-06-01",
    "iso:country": "GB",
    "wof:name": "DT3 4NS",
    "wof:placetype": "postalcode"
  },
  "geometry": {"coordinates":[-2.568038,50.668698],"type":"Point"}
}
