{
  "type": "Feature",
  "properties": {
    "iso:country":"GB",
    "wof:name":"PO15 6LD",
    "wof:placetype":"postalcode"
},
  "geometry": {"coordinates":[-1.21064001682568,50.86188199468355],"type":"Point"}
}