{
  "type": "Feature",
  "properties": {
    "iso:country": "GB",
    "wof:name": "EH16 5QW",
    "wof:placetype": "postalcode"
  },
  "geometry": {"coordinates":[-3.168078,55.92304],"type":"Point"}
}
