{
  "type": "Feature",
  "properties": {
    "iso:country": "GB",
    "wof:name": "G74 4FX",
    "wof:placetype": "postalcode"
  },
  "geometry": {"coordinates":[-4.169387,55.778296],"type":"Point"}
}
