{
  "type": "Feature",
  "properties": {
    "iso:country":"GB",
    "wof:name":"GL20 7HX",
    "wof:placetype":"postalcode"
},
  "geometry": {"coordinates":[-2.08080797007425,52.03097667036911],"type":"Point"}
}