{
  "type": "Feature",
  "properties": {
    "date:inception_lower": "1980-01-01",
    "date:inception_upper": "1980-01-01",
    "iso:country": "GB",
    "wof:name": "GL20 7HX",
    "wof:placetype": "postalcode"
  },
  "geometry": {"coordinates":[-2.080808,52.030977],"type":"Point"}
}
