{
  "type": "Feature",
  "properties": {
    "iso:country":"GB",
    "wof:name":"AB15 5NQ",
    "wof:placetype":"postalcode"
},
  "geometry": {"coordinates":[-2.13042388630787,57.15157864435393],"type":"Point"}
}