{
  "type": "Feature",
  "properties": {
    "date:inception_lower": "1980-01-01",
    "date:inception_upper": "1980-01-01",
    "iso:country": "GB",
    "wof:name": "CW10 9EF",
    "wof:placetype": "postalcode"
  },
  "geometry": {"coordinates":[-2.442658,53.195595],"type":"Point"}
}
