{
  "type": "Feature",
  "properties": {
    "iso:country":"GB",
    "wof:name":"CW10 9EF",
    "wof:placetype":"postalcode"
},
  "geometry": {"coordinates":[-2.44265814814228,53.19559512672193],"type":"Point"}
}