{
  "type": "Feature",
  "properties": {
    "iso:country":"GB",
    "wof:name":"IV30 5QH",
    "wof:placetype":"postalcode"
},
  "geometry": {"coordinates":[-3.39609046917972,57.70024803433393],"type":"Point"}
}