{
  "type": "Feature",
  "properties": {
    "iso:country": "GB",
    "wof:name": "IV30 5QH",
    "wof:placetype": "postalcode"
  },
  "geometry": {"coordinates":[-3.39609,57.700248],"type":"Point"}
}
