{
  "type": "Feature",
  "properties": {
    "iso:country":"GB",
    "wof:name":"TW1 4HF",
    "wof:placetype":"postalcode"
},
  "geometry": {"coordinates":[-0.33096073267627,51.44592802395264],"type":"Point"}
}