{
  "type": "Feature",
  "properties": {
    "iso:country": "GB",
    "wof:name": "BA21 5LD",
    "wof:placetype": "postalcode"
  },
  "geometry": {"coordinates":[-2.620775,50.950016],"type":"Point"}
}
