{
  "type": "Feature",
  "properties": {
    "date:inception_lower": "1980-01-01",
    "date:inception_upper": "1980-01-01",
    "iso:country": "GB",
    "wof:name": "LN4 3EU",
    "wof:placetype": "postalcode"
  },
  "geometry": {"coordinates":[-0.401839,53.1398],"type":"Point"}
}
