{
  "type": "Feature",
  "properties": {
    "iso:country":"GB",
    "wof:name":"LN4 3EU",
    "wof:placetype":"postalcode"
},
  "geometry": {"coordinates":[-0.40183909002819,53.13980022419214],"type":"Point"}
}