{
  "type": "Feature",
  "properties": {
    "iso:country":"GB",
    "wof:name":"DN10 4LQ",
    "wof:placetype":"postalcode"
},
  "geometry": {"coordinates":[-0.84640707546499,53.42437615097284],"type":"Point"}
}