{
  "type": "Feature",
  "properties": {
    "iso:country":"GB",
    "wof:name":"CO15 5PN",
    "wof:placetype":"postalcode"
},
  "geometry": {"coordinates":[1.19197489060816,51.80565081213338],"type":"Point"}
}