{
  "type": "Feature",
  "properties": {
    "date:inception_lower":"2005-03-01",
    "date:inception_upper":"2005-03-31",
    "iso:country":"GB",
    "wof:name":"YO24 4HU",
    "wof:placetype":"postalcode"
},
  "geometry": {"coordinates":[-1.117222,53.956975],"type":"Point"}
}