{
  "type": "Feature",
  "properties": {
    "iso:country":"GB",
    "wof:name":"BB2 6PX",
    "wof:placetype":"postalcode"
},
  "geometry": {"coordinates":[-2.51148853024188,53.75090170145378],"type":"Point"}
}