{
  "type": "Feature",
  "properties": {
    "iso:country": "GB",
    "wof:name": "BB2 6PX",
    "wof:placetype": "postalcode"
  },
  "geometry": {"coordinates":[-2.511488,53.750902],"type":"Point"}
}
