{
  "type": "Feature",
  "properties": {
    "iso:country":"GB",
    "wof:name":"WF5 9TP",
    "wof:placetype":"postalcode"
},
  "geometry": {"coordinates":[-1.54294247189293,53.68493490871108],"type":"Point"}
}