{
  "type": "Feature",
  "properties": {
    "iso:country":"GB",
    "wof:name":"SK6 5AH",
    "wof:placetype":"postalcode"
},
  "geometry": {"coordinates":[-2.04804019643985,53.39751302734953],"type":"Point"}
}