{
  "type": "Feature",
  "properties": {
    "iso:country": "GB",
    "wof:name": "SK6 5AH",
    "wof:placetype": "postalcode"
  },
  "geometry": {"coordinates":[-2.04804,53.397513],"type":"Point"}
}
