{
  "type": "Feature",
  "properties": {
    "date:inception_lower":"1996-06-01",
    "date:inception_upper":"1996-06-30",
    "iso:country":"GB",
    "wof:name":"AB21 7PE",
    "wof:placetype":"postalcode"
},
  "geometry": {"coordinates":[-2.165596,57.243972],"type":"Point"}
}