{
  "type": "Feature",
  "properties": {
    "iso:country":"GB",
    "wof:name":"AB21 7PE",
    "wof:placetype":"postalcode"
},
  "geometry": {"coordinates":[-2.16559647615965,57.24397165679003],"type":"Point"}
}