{
  "type": "Feature",
  "properties": {
    "iso:country":"GB",
    "wof:name":"WF15 7BJ",
    "wof:placetype":"postalcode"
},
  "geometry": {"coordinates":[-1.67818859179673,53.70216419362922],"type":"Point"}
}