{
  "type": "Feature",
  "properties": {
    "date:inception_lower":"1998-06-01",
    "date:inception_upper":"1998-06-30",
    "iso:country":"GB",
    "wof:name":"SA14 8WD",
    "wof:placetype":"postalcode"
},
  "geometry": {"coordinates":[-4.089344,51.692011],"type":"Point"}
}