{
  "type": "Feature",
  "properties": {
    "iso:country": "GB",
    "wof:name": "SA14 8WD",
    "wof:placetype": "postalcode"
  },
  "geometry": {"coordinates":[-4.089344,51.692011],"type":"Point"}
}
