{
  "type": "Feature",
  "properties": {
    "iso:country": "GB",
    "wof:name": "TS15 0JQ",
    "wof:placetype": "postalcode"
  },
  "geometry": {"coordinates":[-1.278908,54.457771],"type":"Point"}
}
