{
  "type": "Feature",
  "properties": {
    "date:inception_lower":"1980-01-01",
    "date:inception_upper":"1980-01-31",
    "iso:country":"GB",
    "wof:name":"NE4 5RJ",
    "wof:placetype":"postalcode"
},
  "geometry": {"coordinates":[-1.630577,54.97297],"type":"Point"}
}