{
  "type": "Feature",
  "properties": {
    "iso:country":"GB",
    "wof:name":"NE4 5RJ",
    "wof:placetype":"postalcode"
},
  "geometry": {"coordinates":[-1.63057745449624,54.9729704113557],"type":"Point"}
}