{
  "type": "Feature",
  "properties": {
    "iso:country":"GB",
    "wof:name":"FK1 3DX",
    "wof:placetype":"postalcode"
},
  "geometry": {"coordinates":[-3.91632750848149,55.94034088372748],"type":"Point"}
}