{
  "type": "Feature",
  "properties": {
    "date:inception_lower": "1980-01-01",
    "date:inception_upper": "1980-01-01",
    "iso:country": "GB",
    "wof:name": "SM2 5EL",
    "wof:placetype": "postalcode"
  },
  "geometry": {"coordinates":[-0.181419,51.359515],"type":"Point"}
}
