{
  "type": "Feature",
  "properties": {
    "iso:country":"GB",
    "wof:name":"SM2 5EL",
    "wof:placetype":"postalcode"
},
  "geometry": {"coordinates":[-0.18141948867386,51.35951469933713],"type":"Point"}
}