{
  "type": "Feature",
  "properties": {
    "iso:country":"GB",
    "wof:name":"ST1 3DY",
    "wof:placetype":"postalcode"
},
  "geometry": {"coordinates":[-2.16754799810647,53.02035825495229],"type":"Point"}
}