{
  "type": "Feature",
  "properties": {
    "iso:country": "GB",
    "wof:name": "RM15 5JX",
    "wof:placetype": "postalcode"
  },
  "geometry": {"coordinates":[0.274499,51.504684],"type":"Point"}
}
