{
  "type": "Feature",
  "properties": {
    "iso:country":"GB",
    "wof:name":"ST4 3AW",
    "wof:placetype":"postalcode"
},
  "geometry": {"coordinates":[-2.1631808051163,52.99686666852004],"type":"Point"}
}