{
  "type": "Feature",
  "properties": {
    "iso:country":"GB",
    "wof:name":"EX2 4RD",
    "wof:placetype":"postalcode"
},
  "geometry": {"coordinates":[-3.51487007840188,50.71238780923487],"type":"Point"}
}