{
  "type": "Feature",
  "properties": {
    "iso:country":"GB",
    "wof:name":"DA12 4QX",
    "wof:placetype":"postalcode"
},
  "geometry": {"coordinates":[0.39138888186815,51.41644541353825],"type":"Point"}
}