{
  "type": "Feature",
  "properties": {
    "date:inception_lower":"1994-05-01",
    "date:inception_upper":"1994-05-31",
    "iso:country":"GB",
    "wof:name":"M20 6AL",
    "wof:placetype":"postalcode"
},
  "geometry": {"coordinates":[-2.229841,53.42184],"type":"Point"}
}