{
  "type": "Feature",
  "properties": {
    "iso:country": "GB",
    "wof:name": "M20 6AL",
    "wof:placetype": "postalcode"
  },
  "geometry": {"coordinates":[-2.229841,53.42184],"type":"Point"}
}
