{
  "type": "Feature",
  "properties": {
    "iso:country":"GB",
    "wof:name":"PO7 5UX",
    "wof:placetype":"postalcode"
},
  "geometry": {"coordinates":[-1.02815281044258,50.86810435077116],"type":"Point"}
}