{
  "type": "Feature",
  "properties": {
    "date:inception_lower":"1980-01-01",
    "date:inception_upper":"1980-01-31",
    "iso:country":"GB",
    "wof:name":"EX8 1LD",
    "wof:placetype":"postalcode"
},
  "geometry": {"coordinates":[-3.409274,50.621163],"type":"Point"}
}