{
  "type": "Feature",
  "properties": {
    "iso:country":"GB",
    "wof:name":"EX8 1LD",
    "wof:placetype":"postalcode"
},
  "geometry": {"coordinates":[-3.40927447456238,50.62116258835096],"type":"Point"}
}