{
  "type": "Feature",
  "properties": {
    "date:inception_lower": "2020-07-01",
    "date:inception_upper": "2020-07-01",
    "iso:country": "GB",
    "wof:name": "PE3 6BJ",
    "wof:placetype": "postalcode"
  },
  "geometry": {"coordinates":[-0.255618,52.572875],"type":"Point"}
}
