{
  "type": "Feature",
  "properties": {
    "iso:country":"GB",
    "wof:name":"DT4 9JX",
    "wof:placetype":"postalcode"
},
  "geometry": {"coordinates":[-2.46344391418797,50.59583424693976],"type":"Point"}
}