{
  "type": "Feature",
  "properties": {
    "date:inception_lower": "1980-01-01",
    "date:inception_upper": "1980-01-01",
    "iso:country": "GB",
    "wof:name": "SR8 2JL",
    "wof:placetype": "postalcode"
  },
  "geometry": {"coordinates":[-1.354861,54.758507],"type":"Point"}
}
