{
  "type": "Feature",
  "properties": {
    "iso:country": "GB",
    "wof:name": "SR8 2JL",
    "wof:placetype": "postalcode"
  },
  "geometry": {"coordinates":[-1.354861,54.758507],"type":"Point"}
}
