{
  "type": "Feature",
  "properties": {
    "date:inception_lower": "1980-01-01",
    "date:inception_upper": "1980-01-01",
    "iso:country": "GB",
    "wof:name": "CT15 4BJ",
    "wof:placetype": "postalcode"
  },
  "geometry": {"coordinates":[1.272728,51.196957],"type":"Point"}
}
