{
  "type": "Feature",
  "properties": {
    "iso:country":"GB",
    "wof:name":"CT15 4BJ",
    "wof:placetype":"postalcode"
},
  "geometry": {"coordinates":[1.27272822672993,51.19695729937656],"type":"Point"}
}