{
  "type": "Feature",
  "properties": {
    "date:inception_lower": "2000-06-01",
    "date:inception_upper": "2000-06-01",
    "iso:country": "GB",
    "wof:name": "SO24 9XE",
    "wof:placetype": "postalcode"
  },
  "geometry": {"coordinates":[-1.162453,51.079938],"type":"Point"}
}
