{
  "type": "Feature",
  "properties": {
    "iso:country":"GB",
    "wof:name":"PL15 8JN",
    "wof:placetype":"postalcode"
},
  "geometry": {"coordinates":[-4.36298314570363,50.64697243644444],"type":"Point"}
}