{
  "type": "Feature",
  "properties": {
    "iso:country":"GB",
    "wof:name":"LL21 9AE",
    "wof:placetype":"postalcode"
},
  "geometry": {"coordinates":[-3.37090115523703,52.98859634059054],"type":"Point"}
}