{
  "type": "Feature",
  "properties": {
    "iso:country":"GB",
    "wof:name":"W13 9YA",
    "wof:placetype":"postalcode"
},
  "geometry": {"coordinates":[-0.3215479410741,51.49814720203945],"type":"Point"}
}