{
  "type": "Feature",
  "properties": {
    "iso:country":"GB",
    "wof:name":"SO15 2TD",
    "wof:placetype":"postalcode"
},
  "geometry": {"coordinates":[-1.41368491303955,50.91734788709935],"type":"Point"}
}