{
  "type": "Feature",
  "properties": {
    "iso:country":"GB",
    "wof:name":"WS15 3DJ",
    "wof:placetype":"postalcode"
},
  "geometry": {"coordinates":[-1.87725235909273,52.81612286350743],"type":"Point"}
}