{
  "type": "Feature",
  "properties": {
    "date:inception_lower": "1994-05-01",
    "date:inception_upper": "1994-05-01",
    "iso:country": "GB",
    "wof:name": "WS15 3DJ",
    "wof:placetype": "postalcode"
  },
  "geometry": {"coordinates":[-1.877249,52.816149],"type":"Point"}
}
