{
  "type": "Feature",
  "properties": {
    "iso:country": "GB",
    "wof:name": "BN25 4PZ",
    "wof:placetype": "postalcode"
  },
  "geometry": {"coordinates":[0.115986,50.77242],"type":"Point"}
}
