{
  "type": "Feature",
  "properties": {
    "iso:country":"GB",
    "wof:name":"BN25 4PZ",
    "wof:placetype":"postalcode"
},
  "geometry": {"coordinates":[0.11598603419067,50.77242049452568],"type":"Point"}
}