{
  "type": "Feature",
  "properties": {
    "iso:country": "GB",
    "wof:name": "CB23 4LP",
    "wof:placetype": "postalcode"
  },
  "geometry": {"coordinates":[-0.063173,52.278307],"type":"Point"}
}
