{
  "type": "Feature",
  "properties": {
    "date:inception_lower": "2006-09-01",
    "date:inception_upper": "2006-09-01",
    "iso:country": "GB",
    "wof:name": "CB23 4LP",
    "wof:placetype": "postalcode"
  },
  "geometry": {"coordinates":[-0.063173,52.278307],"type":"Point"}
}
