{
  "type": "Feature",
  "properties": {
    "iso:country":"GB",
    "wof:name":"CB23 4LP",
    "wof:placetype":"postalcode"
},
  "geometry": {"coordinates":[-0.06342431923862,52.27813499765995],"type":"Point"}
}