{
  "type": "Feature",
  "properties": {
    "iso:country":"GB",
    "wof:name":"GL11 6HP",
    "wof:placetype":"postalcode"
},
  "geometry": {"coordinates":[-2.37887616411653,51.692343723146],"type":"Point"}
}