{
  "type": "Feature",
  "properties": {
    "date:inception_lower": "1980-01-01",
    "date:inception_upper": "1980-01-01",
    "iso:country": "GB",
    "wof:name": "SA44 4LB",
    "wof:placetype": "postalcode"
  },
  "geometry": {"coordinates":[-4.308939,52.048214],"type":"Point"}
}
