{
  "type": "Feature",
  "properties": {
    "iso:country": "GB",
    "wof:name": "PO33 1DP",
    "wof:placetype": "postalcode"
  },
  "geometry": {"coordinates":[-1.147039,50.72021],"type":"Point"}
}
