{
  "type": "Feature",
  "properties": {
    "iso:country": "GB",
    "wof:name": "PO33 1DP",
    "wof:placetype": "postalcode"
  },
  "geometry": {"coordinates":[-1.147022,50.720221],"type":"Point"}
}
