{
  "type": "Feature",
  "properties": {
    "iso:country":"GB",
    "wof:name":"PO33 1DP",
    "wof:placetype":"postalcode"
},
  "geometry": {"coordinates":[-1.14702196654748,50.7202212215608],"type":"Point"}
}