{
  "type": "Feature",
  "properties": {
    "iso:country":"GB",
    "wof:name":"EH4 3LR",
    "wof:placetype":"postalcode"
},
  "geometry": {"coordinates":[-3.24716447444186,55.95342624042775],"type":"Point"}
}