{
  "type": "Feature",
  "properties": {
    "iso:country":"GB",
    "wof:name":"SO40 7EB",
    "wof:placetype":"postalcode"
},
  "geometry": {"coordinates":[-1.50666645564199,50.90362343832943],"type":"Point"}
}