{
  "type": "Feature",
  "properties": {
    "iso:country": "GB",
    "wof:name": "SO40 7EB",
    "wof:placetype": "postalcode"
  },
  "geometry": {"coordinates":[-1.50643,50.903695],"type":"Point"}
}
