{
  "type": "Feature",
  "properties": {
    "iso:country": "GB",
    "wof:name": "CR0 6NG",
    "wof:placetype": "postalcode"
  },
  "geometry": {"coordinates":[-0.068204,51.383772],"type":"Point"}
}
