{
  "type": "Feature",
  "properties": {
    "date:inception_lower":"1980-01-01",
    "date:inception_upper":"1980-01-31",
    "iso:country":"GB",
    "wof:name":"CR0 6NG",
    "wof:placetype":"postalcode"
},
  "geometry": {"coordinates":[-0.068204,51.383772],"type":"Point"}
}