{
  "type": "Feature",
  "properties": {
    "iso:country":"GB",
    "wof:name":"CR0 6NG",
    "wof:placetype":"postalcode"
},
  "geometry": {"coordinates":[-0.068203612848,51.3837724309986],"type":"Point"}
}