{
  "type": "Feature",
  "properties": {
    "iso:country":"GB",
    "wof:name":"WS7 0HP",
    "wof:placetype":"postalcode"
},
  "geometry": {"coordinates":[-1.89913640728891,52.67511527810896],"type":"Point"}
}