{
  "type": "Feature",
  "properties": {
    "iso:country": "GB",
    "wof:name": "WS7 0HP",
    "wof:placetype": "postalcode"
  },
  "geometry": {"coordinates":[-1.899136,52.675115],"type":"Point"}
}
