{
  "type": "Feature",
  "properties": {
    "iso:country":"GB",
    "wof:name":"PE3 9TY",
    "wof:placetype":"postalcode"
},
  "geometry": {"coordinates":[-0.26875726153546,52.58206690578689],"type":"Point"}
}