{
  "type": "Feature",
  "properties": {
    "iso:country":"GB",
    "wof:name":"SM6 0EF",
    "wof:placetype":"postalcode"
},
  "geometry": {"coordinates":[-0.15335532606771,51.36088319398729],"type":"Point"}
}