{
  "type": "Feature",
  "properties": {
    "date:inception_lower": "1980-01-01",
    "date:inception_upper": "1980-01-01",
    "iso:country": "GB",
    "wof:name": "PR4 3UE",
    "wof:placetype": "postalcode"
  },
  "geometry": {"coordinates":[-2.858681,53.824783],"type":"Point"}
}
