{
  "type": "Feature",
  "properties": {
    "iso:country": "GB",
    "wof:name": "PR4 3UE",
    "wof:placetype": "postalcode"
  },
  "geometry": {"coordinates":[-2.858439,53.82483],"type":"Point"}
}
