{
  "type": "Feature",
  "properties": {
    "date:inception_lower":"1980-01-01",
    "date:inception_upper":"1980-01-31",
    "iso:country":"GB",
    "wof:name":"SY3 8TG",
    "wof:placetype":"postalcode"
},
  "geometry": {"coordinates":[-2.785532,52.711542],"type":"Point"}
}