{
  "type": "Feature",
  "properties": {
    "date:inception_lower": "2019-07-01",
    "date:inception_upper": "2019-07-01",
    "iso:country": "GB",
    "wof:name": "KY16 8AU",
    "wof:placetype": "postalcode"
  },
  "geometry": {"coordinates":[-2.66217,56.299495],"type":"Point"}
}
