{
  "type": "Feature",
  "properties": {
    "iso:country":"GB",
    "wof:name":"BL8 1WG",
    "wof:placetype":"postalcode"
},
  "geometry": {"coordinates":[-2.32837532118254,53.61128311854389],"type":"Point"}
}