{
  "type": "Feature",
  "properties": {
    "date:inception_lower": "2004-09-01",
    "date:inception_upper": "2004-09-01",
    "iso:country": "GB",
    "wof:name": "BL8 1WG",
    "wof:placetype": "postalcode"
  },
  "geometry": {"coordinates":[-2.328375,53.611283],"type":"Point"}
}
