{
  "type": "Feature",
  "properties": {
    "iso:country": "GB",
    "wof:name": "BL8 1WG",
    "wof:placetype": "postalcode"
  },
  "geometry": {"coordinates":[-2.328375,53.611283],"type":"Point"}
}
