{
  "type": "Feature",
  "properties": {
    "iso:country":"GB",
    "wof:name":"HU8 7SA",
    "wof:placetype":"postalcode"
},
  "geometry": {"coordinates":[-0.3196505471616,53.75763901450978],"type":"Point"}
}