{
  "type": "Feature",
  "properties": {
    "date:inception_lower":"1980-01-01",
    "date:inception_upper":"1980-01-31",
    "iso:country":"GB",
    "wof:name":"HU8 7SA",
    "wof:placetype":"postalcode"
},
  "geometry": {"coordinates":[-0.31965,53.757639],"type":"Point"}
}