{
  "type": "Feature",
  "properties": {
    "iso:country": "GB",
    "wof:name": "HU8 7SA",
    "wof:placetype": "postalcode"
  },
  "geometry": {"coordinates":[-0.31965,53.757639],"type":"Point"}
}
