{
  "type": "Feature",
  "properties": {
    "iso:country":"GB",
    "wof:name":"S10 5DE",
    "wof:placetype":"postalcode"
},
  "geometry": {"coordinates":[-1.51005840537526,53.37737288358311],"type":"Point"}
}