{
  "type": "Feature",
  "properties": {
    "iso:country":"GB",
    "wof:name":"SS3 9XF",
    "wof:placetype":"postalcode"
},
  "geometry": {"coordinates":[0.88599902579138,51.58308019464594],"type":"Point"}
}