{
  "type": "Feature",
  "properties": {
    "iso:country": "GB",
    "wof:name": "SS3 9XF",
    "wof:placetype": "postalcode"
  },
  "geometry": {"coordinates":[0.885999,51.58308],"type":"Point"}
}
