{
  "type": "Feature",
  "properties": {
    "iso:country": "GB",
    "wof:name": "EX13 7BX",
    "wof:placetype": "postalcode"
  },
  "geometry": {"coordinates":[-2.982019,50.835677],"type":"Point"}
}
