{
  "type": "Feature",
  "properties": {
    "iso:country":"GB",
    "wof:name":"NN11 4QW",
    "wof:placetype":"postalcode"
},
  "geometry": {"coordinates":[-1.18153261037113,52.25541266732293],"type":"Point"}
}