{
  "type": "Feature",
  "properties": {
    "date:inception_lower": "1980-01-01",
    "date:inception_upper": "1980-01-01",
    "iso:country": "GB",
    "wof:name": "BN3 7JJ",
    "wof:placetype": "postalcode"
  },
  "geometry": {"coordinates":[-0.192853,50.839724],"type":"Point"}
}
