{
  "type": "Feature",
  "properties": {
    "iso:country":"GB",
    "wof:name":"BN3 7JJ",
    "wof:placetype":"postalcode"
},
  "geometry": {"coordinates":[-0.19285291571843,50.83972399895704],"type":"Point"}
}