{
  "type": "Feature",
  "properties": {
    "iso:country":"GB",
    "wof:name":"SE9 5BG",
    "wof:placetype":"postalcode"
},
  "geometry": {"coordinates":[0.05988567079047,51.44861429043561],"type":"Point"}
}