{
  "type": "Feature",
  "properties": {
    "iso:country":"GB",
    "wof:name":"EX34 9HG",
    "wof:placetype":"postalcode"
},
  "geometry": {"coordinates":[-4.12118921808569,51.20834046925691],"type":"Point"}
}