{
  "type": "Feature",
  "properties": {
    "iso:country": "GB",
    "wof:name": "BL4 7QX",
    "wof:placetype": "postalcode"
  },
  "geometry": {"coordinates":[-2.392479,53.549742],"type":"Point"}
}
