{
  "type": "Feature",
  "properties": {
    "date:inception_lower": "1980-01-01",
    "date:inception_upper": "1980-01-01",
    "iso:country": "GB",
    "wof:name": "BL4 7QX",
    "wof:placetype": "postalcode"
  },
  "geometry": {"coordinates":[-2.392328,53.549779],"type":"Point"}
}
