{
  "type": "Feature",
  "properties": {
    "iso:country":"GB",
    "wof:name":"CH66 3NN",
    "wof:placetype":"postalcode"
},
  "geometry": {"coordinates":[-2.9270461724843,53.28338442065346],"type":"Point"}
}