{
  "type": "Feature",
  "properties": {
    "iso:country":"GB",
    "wof:name":"LS14 3BD",
    "wof:placetype":"postalcode"
},
  "geometry": {"coordinates":[-1.44455221866462,53.87711645447695],"type":"Point"}
}