{
  "type": "Feature",
  "properties": {
    "iso:country": "GB",
    "wof:name": "LS14 3BD",
    "wof:placetype": "postalcode"
  },
  "geometry": {"coordinates":[-1.444552,53.877116],"type":"Point"}
}
