{
  "type": "Feature",
  "properties": {
    "iso:country": "GB",
    "wof:name": "TA1 5JL",
    "wof:placetype": "postalcode"
  },
  "geometry": {"coordinates":[-3.140746,51.007262],"type":"Point"}
}
