{
  "type": "Feature",
  "properties": {
    "iso:country":"GB",
    "wof:name":"PE20 2QA",
    "wof:placetype":"postalcode"
},
  "geometry": {"coordinates":[-0.14420000513359,52.89894065765817],"type":"Point"}
}