{
  "type": "Feature",
  "properties": {
    "iso:country": "GB",
    "wof:name": "LL11 5LT",
    "wof:placetype": "postalcode"
  },
  "geometry": {"coordinates":[-3.076033,53.08248],"type":"Point"}
}
