{
  "type": "Feature",
  "properties": {
    "iso:country":"GB",
    "wof:name":"LL11 5LT",
    "wof:placetype":"postalcode"
},
  "geometry": {"coordinates":[-3.07603350914671,53.08247976528579],"type":"Point"}
}