{
  "type": "Feature",
  "properties": {
    "iso:country": "GB",
    "wof:name": "KA14 3DD",
    "wof:placetype": "postalcode"
  },
  "geometry": {"coordinates":[-4.67424,55.746235],"type":"Point"}
}
