{
  "type": "Feature",
  "properties": {
    "iso:country":"GB",
    "wof:name":"KA14 3DD",
    "wof:placetype":"postalcode"
},
  "geometry": {"coordinates":[-4.6742397745512,55.74623546263214],"type":"Point"}
}