{
  "type": "Feature",
  "properties": {
    "date:inception_lower":"2003-11-01",
    "date:inception_upper":"2003-11-30",
    "iso:country":"GB",
    "wof:name":"KA14 3DD",
    "wof:placetype":"postalcode"
},
  "geometry": {"coordinates":[-4.67424,55.746235],"type":"Point"}
}