{
  "type": "Feature",
  "properties": {
    "iso:country": "GB",
    "wof:name": "HU17 0BQ",
    "wof:placetype": "postalcode"
  },
  "geometry": {"coordinates":[-0.421298,53.84456],"type":"Point"}
}
