{
  "type": "Feature",
  "properties": {
    "date:inception_lower": "1983-03-01",
    "date:inception_upper": "1983-03-01",
    "iso:country": "GB",
    "wof:name": "HU17 0BQ",
    "wof:placetype": "postalcode"
  },
  "geometry": {"coordinates":[-0.421426,53.844626],"type":"Point"}
}
