{
  "type": "Feature",
  "properties": {
    "iso:country":"GB",
    "wof:name":"SE14 9BU",
    "wof:placetype":"postalcode"
},
  "geometry": {"coordinates":[-0.04551722818386,51.47464543535277],"type":"Point"}
}