{
  "type": "Feature",
  "properties": {
    "iso:country": "GB",
    "wof:name": "SY2 5JA",
    "wof:placetype": "postalcode"
  },
  "geometry": {"coordinates":[-2.731288,52.710181],"type":"Point"}
}
