{
  "type": "Feature",
  "properties": {
    "iso:country":"GB",
    "wof:name":"SY2 5JA",
    "wof:placetype":"postalcode"
},
  "geometry": {"coordinates":[-2.73128818347306,52.7101813228096],"type":"Point"}
}