{
  "type": "Feature",
  "properties": {
    "iso:country": "GB",
    "wof:name": "SE9 3DL",
    "wof:placetype": "postalcode"
  },
  "geometry": {"coordinates":[0.056078,51.427917],"type":"Point"}
}
