{
  "type": "Feature",
  "properties": {
    "iso:country":"GB",
    "wof:name":"SE9 3DL",
    "wof:placetype":"postalcode"
},
  "geometry": {"coordinates":[0.05607752147967,51.42791667261793],"type":"Point"}
}