{
  "type": "Feature",
  "properties": {
    "iso:country":"GB",
    "wof:name":"DD2 1RX",
    "wof:placetype":"postalcode"
},
  "geometry": {"coordinates":[-3.00039423946434,56.46076287751595],"type":"Point"}
}