{
  "type": "Feature",
  "properties": {
    "iso:country":"GB",
    "wof:name":"EN7 5LX",
    "wof:placetype":"postalcode"
},
  "geometry": {"coordinates":[-0.06185568423875,51.701014993404],"type":"Point"}
}