{
  "type": "Feature",
  "properties": {
    "date:inception_lower": "1995-07-01",
    "date:inception_upper": "1995-07-01",
    "iso:country": "GB",
    "wof:name": "WR5 2PN",
    "wof:placetype": "postalcode"
  },
  "geometry": {"coordinates":[-2.197236,52.165131],"type":"Point"}
}
