{
  "type": "Feature",
  "properties": {
    "iso:country":"GB",
    "wof:name":"WR5 2PN",
    "wof:placetype":"postalcode"
},
  "geometry": {"coordinates":[-2.19723639721437,52.16513098224286],"type":"Point"}
}