{
  "type": "Feature",
  "properties": {
    "date:inception_lower": "1980-01-01",
    "date:inception_upper": "1980-01-01",
    "iso:country": "GB",
    "wof:name": "G66 3SR",
    "wof:placetype": "postalcode"
  },
  "geometry": {"coordinates":[-4.123015,55.942937],"type":"Point"}
}
