{
  "type": "Feature",
  "properties": {
    "iso:country":"GB",
    "wof:name":"G66 3SR",
    "wof:placetype":"postalcode"
},
  "geometry": {"coordinates":[-4.12301468260503,55.94293676578711],"type":"Point"}
}