{
  "type": "Feature",
  "properties": {
    "iso:country":"GB",
    "wof:name":"RG22 5JX",
    "wof:placetype":"postalcode"
},
  "geometry": {"coordinates":[-1.14251165773639,51.24113118809227],"type":"Point"}
}