{
  "type": "Feature",
  "properties": {
    "date:inception_lower":"1983-07-01",
    "date:inception_upper":"1983-07-31",
    "iso:country":"GB",
    "wof:name":"RG22 5JX",
    "wof:placetype":"postalcode"
},
  "geometry": {"coordinates":[-1.142512,51.241131],"type":"Point"}
}