{
  "type": "Feature",
  "properties": {
    "iso:country":"GB",
    "wof:name":"DT1 2RZ",
    "wof:placetype":"postalcode"
},
  "geometry": {"coordinates":[-2.44315967471478,50.70297290365554],"type":"Point"}
}