{
  "type": "Feature",
  "properties": {
    "iso:country":"GB",
    "wof:name":"PO21 1DL",
    "wof:placetype":"postalcode"
},
  "geometry": {"coordinates":[-0.67322160396809,50.78626294915292],"type":"Point"}
}