{
  "type": "Feature",
  "properties": {
    "iso:country": "GB",
    "wof:name": "PO21 1DL",
    "wof:placetype": "postalcode"
  },
  "geometry": {"coordinates":[-0.673222,50.786263],"type":"Point"}
}
