{
  "type": "Feature",
  "properties": {
    "iso:country": "GB",
    "wof:name": "MK19 7LP",
    "wof:placetype": "postalcode"
  },
  "geometry": {"coordinates":[-0.827248,52.113606],"type":"Point"}
}
