{
  "type": "Feature",
  "properties": {
    "iso:country":"GB",
    "wof:name":"MK19 7LP",
    "wof:placetype":"postalcode"
},
  "geometry": {"coordinates":[-0.82724757223012,52.11360648893205],"type":"Point"}
}