{
  "type": "Feature",
  "properties": {
    "date:inception_lower": "2011-12-01",
    "date:inception_upper": "2011-12-01",
    "iso:country": "GB",
    "wof:name": "PL33 9BE",
    "wof:placetype": "postalcode"
  },
  "geometry": {"coordinates":[-4.730097,50.625822],"type":"Point"}
}
