{
  "type": "Feature",
  "properties": {
    "iso:country":"GB",
    "wof:name":"PL33 9BE",
    "wof:placetype":"postalcode"
},
  "geometry": {"coordinates":[-4.72972148991282,50.62584751936256],"type":"Point"}
}