{
  "type": "Feature",
  "properties": {
    "date:inception_lower": "1980-01-01",
    "date:inception_upper": "1980-01-01",
    "iso:country": "GB",
    "wof:name": "MK12 5HD",
    "wof:placetype": "postalcode"
  },
  "geometry": {"coordinates":[-0.807621,52.060452],"type":"Point"}
}
