{
  "type": "Feature",
  "properties": {
    "iso:country":"GB",
    "wof:name":"OX9 3SE",
    "wof:placetype":"postalcode"
},
  "geometry": {"coordinates":[-0.96646598887332,51.73931224877719],"type":"Point"}
}