{
  "type": "Feature",
  "properties": {
    "iso:country": "GB",
    "wof:name": "CH62 7HQ",
    "wof:placetype": "postalcode"
  },
  "geometry": {"coordinates":[-2.977795,53.332283],"type":"Point"}
}
