{
  "type": "Feature",
  "properties": {
    "date:inception_lower":"2017-01-01",
    "date:inception_upper":"2017-01-31",
    "iso:country":"GB",
    "wof:name":"M6 5LU",
    "wof:placetype":"postalcode"
},
  "geometry": {"coordinates":[-2.294154,53.485103],"type":"Point"}
}