{
  "type": "Feature",
  "properties": {
    "iso:country": "GB",
    "wof:name": "HR1 1TT",
    "wof:placetype": "postalcode"
  },
  "geometry": {"coordinates":[-2.692839,52.050031],"type":"Point"}
}
