{
  "type": "Feature",
  "properties": {
    "date:inception_lower": "1999-06-01",
    "date:inception_upper": "1999-06-01",
    "iso:country": "GB",
    "wof:name": "CF3 3AP",
    "wof:placetype": "postalcode"
  },
  "geometry": {"coordinates":[-3.133189,51.502492],"type":"Point"}
}
