{
  "type": "Feature",
  "properties": {
    "iso:country":"GB",
    "wof:name":"SY14 7AJ",
    "wof:placetype":"postalcode"
},
  "geometry": {"coordinates":[-2.806217116263,53.01311287663377],"type":"Point"}
}