{
  "type": "Feature",
  "properties": {
    "iso:country":"GB",
    "wof:name":"EX36 3JN",
    "wof:placetype":"postalcode"
},
  "geometry": {"coordinates":[-3.79352987336532,51.05513376051359],"type":"Point"}
}