{
  "type": "Feature",
  "properties": {
    "iso:country":"GB",
    "wof:name":"RG6 1EU",
    "wof:placetype":"postalcode"
},
  "geometry": {"coordinates":[-0.92548116443102,51.44798302821922],"type":"Point"}
}