{
  "type": "Feature",
  "properties": {
    "iso:country":"GB",
    "wof:name":"LL13 8SY",
    "wof:placetype":"postalcode"
},
  "geometry": {"coordinates":[-2.98342282195739,53.04829443116325],"type":"Point"}
}