{
  "type": "Feature",
  "properties": {
    "date:inception_lower":"2004-03-01",
    "date:inception_upper":"2004-03-31",
    "iso:country":"GB",
    "wof:name":"WR15 8RF",
    "wof:placetype":"postalcode"
},
  "geometry": {"coordinates":[-2.533934,52.260123],"type":"Point"}
}