{
  "type": "Feature",
  "properties": {
    "iso:country":"GB",
    "wof:name":"WR15 8RF",
    "wof:placetype":"postalcode"
},
  "geometry": {"coordinates":[-2.5339335935125,52.26012296934944],"type":"Point"}
}