{
  "type": "Feature",
  "properties": {
    "iso:country":"GB",
    "wof:name":"M41 8NZ",
    "wof:placetype":"postalcode"
},
  "geometry": {"coordinates":[-2.37640645353472,53.46125989993319],"type":"Point"}
}