{
  "type": "Feature",
  "properties": {
    "date:inception_lower": "1980-01-01",
    "date:inception_upper": "1980-01-01",
    "iso:country": "GB",
    "wof:name": "TA1 4NP",
    "wof:placetype": "postalcode"
  },
  "geometry": {"coordinates":[-3.127945,51.00253],"type":"Point"}
}
