{
  "type": "Feature",
  "properties": {
    "iso:country":"GB",
    "wof:name":"BL6 7LY",
    "wof:placetype":"postalcode"
},
  "geometry": {"coordinates":[-2.54535937045035,53.60738963079326],"type":"Point"}
}