{
  "type": "Feature",
  "properties": {
    "date:inception_lower": "1980-01-01",
    "date:inception_upper": "1980-01-01",
    "iso:country": "GB",
    "wof:name": "BL6 7LY",
    "wof:placetype": "postalcode"
  },
  "geometry": {"coordinates":[-2.545359,53.60739],"type":"Point"}
}
