{
  "type": "Feature",
  "properties": {
    "iso:country": "GB",
    "wof:name": "NR17 2LR",
    "wof:placetype": "postalcode"
  },
  "geometry": {"coordinates":[1.082603,52.522668],"type":"Point"}
}
