{
  "type": "Feature",
  "properties": {
    "iso:country":"GB",
    "wof:name":"NR17 2LR",
    "wof:placetype":"postalcode"
},
  "geometry": {"coordinates":[1.08254817524414,52.52251617883813],"type":"Point"}
}