{
  "type": "Feature",
  "properties": {
    "iso:country":"GB",
    "wof:name":"LA15 8LR",
    "wof:placetype":"postalcode"
},
  "geometry": {"coordinates":[-3.18336875294214,54.15054321885863],"type":"Point"}
}