{
  "type": "Feature",
  "properties": {
    "iso:country":"GB",
    "wof:name":"GU28 0JL",
    "wof:placetype":"postalcode"
},
  "geometry": {"coordinates":[-0.58982666813768,50.96969467970244],"type":"Point"}
}