{
  "type": "Feature",
  "properties": {
    "date:inception_lower": "2016-07-01",
    "date:inception_upper": "2016-07-01",
    "iso:country": "GB",
    "wof:name": "DT11 7FY",
    "wof:placetype": "postalcode"
  },
  "geometry": {"coordinates":[-2.166837,50.865322],"type":"Point"}
}
