{
  "type": "Feature",
  "properties": {
    "iso:country": "GB",
    "wof:name": "HP19 0WJ",
    "wof:placetype": "postalcode"
  },
  "geometry": {"coordinates":[-0.807365,51.830894],"type":"Point"}
}
