{
  "type": "Feature",
  "properties": {
    "iso:country":"GB",
    "wof:name":"HP19 0WJ",
    "wof:placetype":"postalcode"
},
  "geometry": {"coordinates":[-0.8073646609387,51.83089446569556],"type":"Point"}
}