{
  "type": "Feature",
  "properties": {
    "date:inception_lower":"2012-05-01",
    "date:inception_upper":"2012-05-31",
    "iso:country":"GB",
    "wof:name":"PE11 3WA",
    "wof:placetype":"postalcode"
},
  "geometry": {"coordinates":[-0.173524,52.789152],"type":"Point"}
}