{
  "type": "Feature",
  "properties": {
    "iso:country":"GB",
    "wof:name":"PE11 3WA",
    "wof:placetype":"postalcode"
},
  "geometry": {"coordinates":[-0.17352388420214,52.7891520631226],"type":"Point"}
}