{
  "type": "Feature",
  "properties": {
    "iso:country": "GB",
    "wof:name": "NE48 3AE",
    "wof:placetype": "postalcode"
  },
  "geometry": {"coordinates":[-2.193329,55.070486],"type":"Point"}
}
