{
  "type": "Feature",
  "properties": {
    "iso:country": "GB",
    "wof:name": "TS9 5QE",
    "wof:placetype": "postalcode"
  },
  "geometry": {"coordinates":[-1.193963,54.475703],"type":"Point"}
}
