{
  "type": "Feature",
  "properties": {
    "iso:country": "GB",
    "wof:name": "M9 5UB",
    "wof:placetype": "postalcode"
  },
  "geometry": {"coordinates":[-2.212312,53.509546],"type":"Point"}
}
