{
  "type": "Feature",
  "properties": {
    "iso:country":"GB",
    "wof:name":"M9 5UB",
    "wof:placetype":"postalcode"
},
  "geometry": {"coordinates":[-2.21231222762192,53.50954594157263],"type":"Point"}
}