{
  "type": "Feature",
  "properties": {
    "date:inception_lower": "1980-01-01",
    "date:inception_upper": "1980-01-01",
    "iso:country": "GB",
    "wof:name": "KA8 9RJ",
    "wof:placetype": "postalcode"
  },
  "geometry": {"coordinates":[-4.601584,55.472403],"type":"Point"}
}
