{
  "type": "Feature",
  "properties": {
    "iso:country": "GB",
    "wof:name": "KA8 9RJ",
    "wof:placetype": "postalcode"
  },
  "geometry": {"coordinates":[-4.601584,55.472403],"type":"Point"}
}
