{
  "type": "Feature",
  "properties": {
    "iso:country":"GB",
    "wof:name":"KA8 9RJ",
    "wof:placetype":"postalcode"
},
  "geometry": {"coordinates":[-4.60158418437953,55.47240343605292],"type":"Point"}
}