{
  "type": "Feature",
  "properties": {
    "iso:country":"GB",
    "wof:name":"SK1 2NR",
    "wof:placetype":"postalcode"
},
  "geometry": {"coordinates":[-2.14509459393048,53.4132451981414],"type":"Point"}
}