{
  "type": "Feature",
  "properties": {
    "date:inception_lower": "1980-01-01",
    "date:inception_upper": "1980-01-01",
    "iso:country": "GB",
    "wof:name": "SK1 2NR",
    "wof:placetype": "postalcode"
  },
  "geometry": {"coordinates":[-2.145095,53.413245],"type":"Point"}
}
