{
  "type": "Feature",
  "properties": {
    "iso:country": "GB",
    "wof:name": "SL0 9JU",
    "wof:placetype": "postalcode"
  },
  "geometry": {"coordinates":[-0.502925,51.518524],"type":"Point"}
}
