{
  "type": "Feature",
  "properties": {
    "date:inception_lower": "2021-07-01",
    "date:inception_upper": "2021-07-01",
    "iso:country": "GB",
    "wof:name": "TR8 4UT",
    "wof:placetype": "postalcode"
  },
  "geometry": {"coordinates":[-5.009529,50.424381],"type":"Point"}
}
