{
  "type": "Feature",
  "properties": {
    "iso:country":"GB",
    "wof:name":"DY9 9QR",
    "wof:placetype":"postalcode"
},
  "geometry": {"coordinates":[-2.11162241365125,52.40976924258889],"type":"Point"}
}