{
  "type": "Feature",
  "properties": {
    "date:inception_lower": "2018-12-01",
    "date:inception_upper": "2018-12-01",
    "iso:country": "GB",
    "wof:name": "CF3 0FJ",
    "wof:placetype": "postalcode"
  },
  "geometry": {"coordinates":[-3.103527,51.518395],"type":"Point"}
}
