{
  "type": "Feature",
  "properties": {
    "date:inception_lower":"1980-01-01",
    "date:inception_upper":"1980-01-31",
    "iso:country":"GB",
    "wof:name":"SA31 2AN",
    "wof:placetype":"postalcode"
},
  "geometry": {"coordinates":[-4.286609,51.870338],"type":"Point"}
}