{
  "type": "Feature",
  "properties": {
    "date:inception_lower":"2013-12-01",
    "date:inception_upper":"2013-12-31",
    "iso:country":"GB",
    "wof:name":"EH1 3AN",
    "wof:placetype":"postalcode"
},
  "geometry": {"coordinates":[-3.186549,55.955044],"type":"Point"}
}