{
  "type": "Feature",
  "properties": {
    "iso:country":"GB",
    "wof:name":"EH1 3AN",
    "wof:placetype":"postalcode"
},
  "geometry": {"coordinates":[-3.18623780131384,55.95540269126637],"type":"Point"}
}