{
  "type": "Feature",
  "properties": {
    "iso:country":"GB",
    "wof:name":"B95 5JA",
    "wof:placetype":"postalcode"
},
  "geometry": {"coordinates":[-1.78358143525459,52.28828421561226],"type":"Point"}
}