{
  "type": "Feature",
  "properties": {
    "date:inception_lower":"1993-08-01",
    "date:inception_upper":"1993-08-31",
    "iso:country":"GB",
    "wof:name":"E8 3EX",
    "wof:placetype":"postalcode"
},
  "geometry": {"coordinates":[-0.067374,51.545528],"type":"Point"}
}