{
  "type": "Feature",
  "properties": {
    "iso:country": "GB",
    "wof:name": "E8 3EX",
    "wof:placetype": "postalcode"
  },
  "geometry": {"coordinates":[-0.067374,51.545528],"type":"Point"}
}
