{
  "type": "Feature",
  "properties": {
    "iso:country":"GB",
    "wof:name":"E8 3EX",
    "wof:placetype":"postalcode"
},
  "geometry": {"coordinates":[-0.06737423329775,51.54552768775468],"type":"Point"}
}