{
  "type": "Feature",
  "properties": {
    "iso:country":"GB",
    "wof:name":"SY7 8LN",
    "wof:placetype":"postalcode"
},
  "geometry": {"coordinates":[-3.02915332384323,52.42184708292603],"type":"Point"}
}