{
  "type": "Feature",
  "properties": {
    "iso:country": "GB",
    "wof:name": "SY7 8LN",
    "wof:placetype": "postalcode"
  },
  "geometry": {"coordinates":[-3.029153,52.421847],"type":"Point"}
}
