{
  "type": "Feature",
  "properties": {
    "date:inception_lower": "1996-12-01",
    "date:inception_upper": "1996-12-01",
    "iso:country": "GB",
    "wof:name": "SY7 8LN",
    "wof:placetype": "postalcode"
  },
  "geometry": {"coordinates":[-3.029182,52.42187],"type":"Point"}
}
