{
  "type": "Feature",
  "properties": {
    "date:inception_lower":"1996-12-01",
    "date:inception_upper":"1996-12-31",
    "iso:country":"GB",
    "wof:name":"SY7 8LN",
    "wof:placetype":"postalcode"
},
  "geometry": {"coordinates":[-3.029153,52.421847],"type":"Point"}
}