{
  "type": "Feature",
  "properties": {
    "date:inception_lower": "2008-02-01",
    "date:inception_upper": "2008-02-01",
    "iso:country": "GB",
    "wof:name": "PA4 8BS",
    "wof:placetype": "postalcode"
  },
  "geometry": {"coordinates":[-4.372693,55.876341],"type":"Point"}
}
