{
  "type": "Feature",
  "properties": {
    "iso:country":"GB",
    "wof:name":"PA4 8BS",
    "wof:placetype":"postalcode"
},
  "geometry": {"coordinates":[-4.37142595153748,55.87577768243749],"type":"Point"}
}