{
  "type": "Feature",
  "properties": {
    "iso:country": "GB",
    "wof:name": "PA4 8BS",
    "wof:placetype": "postalcode"
  },
  "geometry": {"coordinates":[-4.372693,55.876341],"type":"Point"}
}
