{
  "type": "Feature",
  "properties": {
    "iso:country":"GB",
    "wof:name":"B20 2HX",
    "wof:placetype":"postalcode"
},
  "geometry": {"coordinates":[-1.93488382282079,52.51451975920707],"type":"Point"}
}