{
  "type": "Feature",
  "properties": {
    "date:inception_lower":"1980-01-01",
    "date:inception_upper":"1980-01-31",
    "iso:country":"GB",
    "wof:name":"B20 2HX",
    "wof:placetype":"postalcode"
},
  "geometry": {"coordinates":[-1.934884,52.51452],"type":"Point"}
}