{
  "type": "Feature",
  "properties": {
    "iso:country":"GB",
    "wof:name":"TW20 9EL",
    "wof:placetype":"postalcode"
},
  "geometry": {"coordinates":[-0.54514179762809,51.42206562292102],"type":"Point"}
}