{
  "type": "Feature",
  "properties": {
    "iso:country":"GB",
    "wof:name":"SO40 9BX",
    "wof:placetype":"postalcode"
},
  "geometry": {"coordinates":[-1.49519668124172,50.91482398972274],"type":"Point"}
}