{
  "type": "Feature",
  "properties": {
    "iso:country": "GB",
    "wof:name": "KY11 2QR",
    "wof:placetype": "postalcode"
  },
  "geometry": {"coordinates":[-3.416591,56.035243],"type":"Point"}
}
