{
  "type": "Feature",
  "properties": {
    "iso:country": "GB",
    "wof:name": "PE31 8SF",
    "wof:placetype": "postalcode"
  },
  "geometry": {"coordinates":[0.71828,52.862222],"type":"Point"}
}
