{
  "type": "Feature",
  "properties": {
    "date:inception_lower": "1980-01-01",
    "date:inception_upper": "1980-01-01",
    "iso:country": "GB",
    "wof:name": "BN9 0RU",
    "wof:placetype": "postalcode"
  },
  "geometry": {"coordinates":[0.067483,50.806289],"type":"Point"}
}
