{
  "type": "Feature",
  "properties": {
    "iso:country": "GB",
    "wof:name": "BN9 0RU",
    "wof:placetype": "postalcode"
  },
  "geometry": {"coordinates":[0.067483,50.806289],"type":"Point"}
}
