{
  "type": "Feature",
  "properties": {
    "iso:country":"GB",
    "wof:name":"BN9 0RU",
    "wof:placetype":"postalcode"
},
  "geometry": {"coordinates":[0.06748335213856,50.80628855340591],"type":"Point"}
}