{
  "type": "Feature",
  "properties": {
    "iso:country":"GB",
    "wof:name":"RM15 4AB",
    "wof:placetype":"postalcode"
},
  "geometry": {"coordinates":[0.25972458724083,51.49848556493924],"type":"Point"}
}