{
  "type": "Feature",
  "properties": {
    "date:inception_lower": "2021-06-01",
    "date:inception_upper": "2021-06-01",
    "iso:country": "GB",
    "wof:name": "NG16 3SD",
    "wof:placetype": "postalcode"
  },
  "geometry": {"coordinates":[-1.289053,53.016448],"type":"Point"}
}
