{
  "type": "Feature",
  "properties": {
    "date:inception_lower": "1980-01-01",
    "date:inception_upper": "1980-01-01",
    "iso:country": "GB",
    "wof:name": "BD21 1AN",
    "wof:placetype": "postalcode"
  },
  "geometry": {"coordinates":[-1.915387,53.85786],"type":"Point"}
}
