{
  "type": "Feature",
  "properties": {
    "iso:country": "GB",
    "wof:name": "CT10 2QH",
    "wof:placetype": "postalcode"
  },
  "geometry": {"coordinates":[1.420275,51.360153],"type":"Point"}
}
