{
  "type": "Feature",
  "properties": {
    "iso:country":"GB",
    "wof:name":"LL55 1HY",
    "wof:placetype":"postalcode"
},
  "geometry": {"coordinates":[-4.26747461602747,53.14496370624627],"type":"Point"}
}