{
  "type": "Feature",
  "properties": {
    "iso:country": "GB",
    "wof:name": "LE3 6PY",
    "wof:placetype": "postalcode"
  },
  "geometry": {"coordinates":[-1.193184,52.633739],"type":"Point"}
}
