{
  "type": "Feature",
  "properties": {
    "date:inception_lower": "2007-07-01",
    "date:inception_upper": "2007-07-01",
    "iso:country": "GB",
    "wof:name": "TD9 9QJ",
    "wof:placetype": "postalcode"
  },
  "geometry": {"coordinates":[-2.786085,55.426164],"type":"Point"}
}
