{
  "type": "Feature",
  "properties": {
    "iso:country":"GB",
    "wof:name":"NE34 7JE",
    "wof:placetype":"postalcode"
},
  "geometry": {"coordinates":[-1.39126321847978,54.98033899240229],"type":"Point"}
}