{
  "type": "Feature",
  "properties": {
    "iso:country": "GB",
    "wof:name": "NR17 2RR",
    "wof:placetype": "postalcode"
  },
  "geometry": {"coordinates":[1.0039,52.511212],"type":"Point"}
}
