{
  "type": "Feature",
  "properties": {
    "date:inception_lower":"1997-06-01",
    "date:inception_upper":"1997-06-30",
    "iso:country":"GB",
    "wof:name":"NR17 2RR",
    "wof:placetype":"postalcode"
},
  "geometry": {"coordinates":[1.0039,52.511212],"type":"Point"}
}