{
  "type": "Feature",
  "properties": {
    "iso:country":"GB",
    "wof:name":"NR17 2RR",
    "wof:placetype":"postalcode"
},
  "geometry": {"coordinates":[1.0039003022976,52.51121220393816],"type":"Point"}
}