{
  "type": "Feature",
  "properties": {
    "iso:country":"GB",
    "wof:name":"NG9 5BT",
    "wof:placetype":"postalcode"
},
  "geometry": {"coordinates":[-1.235464919539,52.92112407576604],"type":"Point"}
}