{
  "type": "Feature",
  "properties": {
    "iso:country":"GB",
    "wof:name":"PR8 6PU",
    "wof:placetype":"postalcode"
},
  "geometry": {"coordinates":[-2.99803526112335,53.64151171188667],"type":"Point"}
}