{
  "type": "Feature",
  "properties": {
    "iso:country": "GB",
    "wof:name": "TN22 4NG",
    "wof:placetype": "postalcode"
  },
  "geometry": {"coordinates":[0.136271,50.99191],"type":"Point"}
}
