{
  "type": "Feature",
  "properties": {
    "iso:country":"GB",
    "wof:name":"OX20 1LQ",
    "wof:placetype":"postalcode"
},
  "geometry": {"coordinates":[-1.34370665020345,51.85019589666732],"type":"Point"}
}