{
  "type": "Feature",
  "properties": {
    "iso:country":"GB",
    "wof:name":"DD3 6NF",
    "wof:placetype":"postalcode"
},
  "geometry": {"coordinates":[-2.9748685315324,56.46839618010506],"type":"Point"}
}