{
  "type": "Feature",
  "properties": {
    "date:inception_lower": "1980-01-01",
    "date:inception_upper": "1980-01-01",
    "iso:country": "GB",
    "wof:name": "HP13 6QW",
    "wof:placetype": "postalcode"
  },
  "geometry": {"coordinates":[-0.740418,51.634539],"type":"Point"}
}
