{
  "type": "Feature",
  "properties": {
    "iso:country":"GB",
    "wof:name":"HP13 6QW",
    "wof:placetype":"postalcode"
},
  "geometry": {"coordinates":[-0.74041813389204,51.63453925739718],"type":"Point"}
}