{
  "type": "Feature",
  "properties": {
    "iso:country":"GB",
    "wof:name":"LL13 9SL",
    "wof:placetype":"postalcode"
},
  "geometry": {"coordinates":[-2.89409278125907,53.07982406769514],"type":"Point"}
}