{
  "type": "Feature",
  "properties": {
    "iso:country":"GB",
    "wof:name":"SW11 6RP",
    "wof:placetype":"postalcode"
},
  "geometry": {"coordinates":[-0.16100194607007,51.45609153601259],"type":"Point"}
}