{
  "type": "Feature",
  "properties": {
    "date:inception_lower": "1994-05-01",
    "date:inception_upper": "1994-05-01",
    "iso:country": "GB",
    "wof:name": "PE11 1HX",
    "wof:placetype": "postalcode"
  },
  "geometry": {"coordinates":[-0.165567,52.792629],"type":"Point"}
}
