{
  "type": "Feature",
  "properties": {
    "iso:country": "GB",
    "wof:name": "BS4 1HX",
    "wof:placetype": "postalcode"
  },
  "geometry": {"coordinates":[-2.578313,51.423342],"type":"Point"}
}
