{
  "type": "Feature",
  "properties": {
    "iso:country":"GB",
    "wof:name":"KY11 2RB",
    "wof:placetype":"postalcode"
},
  "geometry": {"coordinates":[-3.42505706814098,56.03981768355722],"type":"Point"}
}