{
  "type": "Feature",
  "properties": {
    "iso:country": "GB",
    "wof:name": "GU35 9NZ",
    "wof:placetype": "postalcode"
  },
  "geometry": {"coordinates":[-0.885034,51.134414],"type":"Point"}
}
