{
  "type": "Feature",
  "properties": {
    "iso:country":"GB",
    "wof:name":"PE31 7RQ",
    "wof:placetype":"postalcode"
},
  "geometry": {"coordinates":[0.49727445232578,52.87432496555301],"type":"Point"}
}