{
  "type": "Feature",
  "properties": {
    "date:inception_lower": "1981-06-01",
    "date:inception_upper": "1981-06-01",
    "iso:country": "GB",
    "wof:name": "PE31 7RQ",
    "wof:placetype": "postalcode"
  },
  "geometry": {"coordinates":[0.497274,52.874325],"type":"Point"}
}
