{
  "type": "Feature",
  "properties": {
    "iso:country": "GB",
    "wof:name": "OL7 9DY",
    "wof:placetype": "postalcode"
  },
  "geometry": {"coordinates":[-2.103549,53.496441],"type":"Point"}
}
