{
  "type": "Feature",
  "properties": {
    "iso:country":"GB",
    "wof:name":"BB12 0AT",
    "wof:placetype":"postalcode"
},
  "geometry": {"coordinates":[-2.2460533151062,53.79686984262938],"type":"Point"}
}