{
  "type": "Feature",
  "properties": {
    "date:inception_lower": "2024-01-01",
    "date:inception_upper": "2024-01-01",
    "iso:country": "GB",
    "wof:name": "PE11 1ZL",
    "wof:placetype": "postalcode"
  },
  "geometry": {"coordinates":[-0.15307,52.786878],"type":"Point"}
}
