{
  "type": "Feature",
  "properties": {
    "iso:country":"GB",
    "wof:name":"BB18 6AG",
    "wof:placetype":"postalcode"
},
  "geometry": {"coordinates":[-2.18235487263408,53.91622596018285],"type":"Point"}
}