{
  "type": "Feature",
  "properties": {
    "iso:country": "GB",
    "wof:name": "BB18 6AG",
    "wof:placetype": "postalcode"
  },
  "geometry": {"coordinates":[-2.182355,53.916226],"type":"Point"}
}
