{
  "type": "Feature",
  "properties": {
    "iso:country":"GB",
    "wof:name":"IP13 6DT",
    "wof:placetype":"postalcode"
},
  "geometry": {"coordinates":[1.35502930648167,52.12129220942096],"type":"Point"}
}