{
  "type": "Feature",
  "properties": {
    "iso:country":"GB",
    "wof:name":"HU12 0DH",
    "wof:placetype":"postalcode"
},
  "geometry": {"coordinates":[-0.07154772401343,53.72498444068067],"type":"Point"}
}