{
  "type": "Feature",
  "properties": {
    "iso:country":"GB",
    "wof:name":"SG4 9AT",
    "wof:placetype":"postalcode"
},
  "geometry": {"coordinates":[-0.27528765916647,51.93646899370369],"type":"Point"}
}