{
  "type": "Feature",
  "properties": {
    "iso:country": "GB",
    "wof:name": "SG4 9AT",
    "wof:placetype": "postalcode"
  },
  "geometry": {"coordinates":[-0.275236,51.936475],"type":"Point"}
}
