{
  "type": "Feature",
  "properties": {
    "iso:country":"GB",
    "wof:name":"WV16 6UP",
    "wof:placetype":"postalcode"
},
  "geometry": {"coordinates":[-2.55091531835248,52.50087481857661],"type":"Point"}
}