{
  "type": "Feature",
  "properties": {
    "date:inception_lower": "1980-01-01",
    "date:inception_upper": "1980-01-01",
    "iso:country": "GB",
    "wof:name": "WV16 6UP",
    "wof:placetype": "postalcode"
  },
  "geometry": {"coordinates":[-2.550915,52.500875],"type":"Point"}
}
