{
  "type": "Feature",
  "properties": {
    "iso:country":"GB",
    "wof:name":"BH17 0GG",
    "wof:placetype":"postalcode"
},
  "geometry": {"coordinates":[-1.97425308822254,50.74277861472148],"type":"Point"}
}