{
  "type": "Feature",
  "properties": {
    "date:inception_lower": "1990-02-01",
    "date:inception_upper": "1990-02-01",
    "iso:country": "GB",
    "wof:name": "CF43 3LJ",
    "wof:placetype": "postalcode"
  },
  "geometry": {"coordinates":[-3.430295,51.636363],"type":"Point"}
}
