{
  "type": "Feature",
  "properties": {
    "date:inception_lower": "1980-01-01",
    "date:inception_upper": "1980-01-01",
    "iso:country": "GB",
    "wof:name": "SW13 9EN",
    "wof:placetype": "postalcode"
  },
  "geometry": {"coordinates":[-0.236098,51.483629],"type":"Point"}
}
