{
  "type": "Feature",
  "properties": {
    "iso:country": "GB",
    "wof:name": "SW13 9EN",
    "wof:placetype": "postalcode"
  },
  "geometry": {"coordinates":[-0.236098,51.483629],"type":"Point"}
}
