{
  "type": "Feature",
  "properties": {
    "date:inception_lower": "1985-10-01",
    "date:inception_upper": "1985-10-01",
    "iso:country": "GB",
    "wof:name": "SS15 6SY",
    "wof:placetype": "postalcode"
  },
  "geometry": {"coordinates":[0.401322,51.572851],"type":"Point"}
}
