{
  "type": "Feature",
  "properties": {
    "iso:country":"GB",
    "wof:name":"SS15 6SY",
    "wof:placetype":"postalcode"
},
  "geometry": {"coordinates":[0.40132242870141,51.57285056265084],"type":"Point"}
}