{
  "type": "Feature",
  "properties": {
    "iso:country":"GB",
    "wof:name":"HU17 9SD",
    "wof:placetype":"postalcode"
},
  "geometry": {"coordinates":[-0.38193759572401,53.86128543247393],"type":"Point"}
}