{
  "type": "Feature",
  "properties": {
    "date:inception_lower": "1988-03-01",
    "date:inception_upper": "1988-03-01",
    "iso:country": "GB",
    "wof:name": "TA6 3TP",
    "wof:placetype": "postalcode"
  },
  "geometry": {"coordinates":[-3.007929,51.13752],"type":"Point"}
}
