{
  "type": "Feature",
  "properties": {
    "iso:country":"GB",
    "wof:name":"N19 5RP",
    "wof:placetype":"postalcode"
},
  "geometry": {"coordinates":[-0.13403331633999,51.56282025190056],"type":"Point"}
}