{
  "type": "Feature",
  "properties": {
    "iso:country":"GB",
    "wof:name":"BA6 8EB",
    "wof:placetype":"postalcode"
},
  "geometry": {"coordinates":[-2.70634614124229,51.15068785280336],"type":"Point"}
}