{
  "type": "Feature",
  "properties": {
    "iso:country": "GB",
    "wof:name": "BA6 8EB",
    "wof:placetype": "postalcode"
  },
  "geometry": {"coordinates":[-2.706346,51.150688],"type":"Point"}
}
