{
  "type": "Feature",
  "properties": {
    "date:inception_lower":"1980-01-01",
    "date:inception_upper":"1980-01-31",
    "iso:country":"GB",
    "wof:name":"BN17 5DE",
    "wof:placetype":"postalcode"
},
  "geometry": {"coordinates":[-0.550657,50.808519],"type":"Point"}
}