{
  "type": "Feature",
  "properties": {
    "date:inception_lower": "1980-01-01",
    "date:inception_upper": "1980-01-01",
    "iso:country": "GB",
    "wof:name": "BN7 3BB",
    "wof:placetype": "postalcode"
  },
  "geometry": {"coordinates":[-0.050638,50.917297],"type":"Point"}
}
