{
  "type": "Feature",
  "properties": {
    "iso:country":"GB",
    "wof:name":"BN7 3BB",
    "wof:placetype":"postalcode"
},
  "geometry": {"coordinates":[-0.05063781993769,50.91729672677471],"type":"Point"}
}