{
  "type": "Feature",
  "properties": {
    "iso:country": "GB",
    "wof:name": "PO19 6BA",
    "wof:placetype": "postalcode"
  },
  "geometry": {"coordinates":[-0.779547,50.845707],"type":"Point"}
}
