{
  "type": "Feature",
  "properties": {
    "date:inception_lower":"2002-06-01",
    "date:inception_upper":"2002-06-30",
    "iso:country":"GB",
    "wof:name":"PO19 6BA",
    "wof:placetype":"postalcode"
},
  "geometry": {"coordinates":[-0.779547,50.845707],"type":"Point"}
}