{
  "type": "Feature",
  "properties": {
    "iso:country":"GB",
    "wof:name":"BB1 6BE",
    "wof:placetype":"postalcode"
},
  "geometry": {"coordinates":[-2.48187224250705,53.75097954180705],"type":"Point"}
}