{
  "type": "Feature",
  "properties": {
    "date:inception_lower": "1980-01-01",
    "date:inception_upper": "1980-01-01",
    "iso:country": "GB",
    "wof:name": "BB1 6BE",
    "wof:placetype": "postalcode"
  },
  "geometry": {"coordinates":[-2.482022,53.750994],"type":"Point"}
}
