{
  "type": "Feature",
  "properties": {
    "iso:country":"GB",
    "wof:name":"FY5 2HN",
    "wof:placetype":"postalcode"
},
  "geometry": {"coordinates":[-3.02122658149001,53.88412972106735],"type":"Point"}
}