{
  "type": "Feature",
  "properties": {
    "date:inception_lower": "1980-01-01",
    "date:inception_upper": "1980-01-01",
    "iso:country": "GB",
    "wof:name": "HA6 3QH",
    "wof:placetype": "postalcode"
  },
  "geometry": {"coordinates":[-0.411469,51.611388],"type":"Point"}
}
