{
  "type": "Feature",
  "properties": {
    "iso:country":"GB",
    "wof:name":"HA6 3QH",
    "wof:placetype":"postalcode"
},
  "geometry": {"coordinates":[-0.41146881597049,51.6113879114358],"type":"Point"}
}