{
  "type": "Feature",
  "properties": {
    "iso:country": "GB",
    "wof:name": "HA6 3QH",
    "wof:placetype": "postalcode"
  },
  "geometry": {"coordinates":[-0.411469,51.611388],"type":"Point"}
}
