{
  "type": "Feature",
  "properties": {
    "iso:country":"GB",
    "wof:name":"SL6 5LW",
    "wof:placetype":"postalcode"
},
  "geometry": {"coordinates":[-0.81298892017952,51.54071080535829],"type":"Point"}
}