{
  "type": "Feature",
  "properties": {
    "iso:country": "GB",
    "wof:name": "SL6 5LW",
    "wof:placetype": "postalcode"
  },
  "geometry": {"coordinates":[-0.812989,51.540711],"type":"Point"}
}
