{
  "type": "Feature",
  "properties": {
    "iso:country": "GB",
    "wof:name": "LS14 5QN",
    "wof:placetype": "postalcode"
  },
  "geometry": {"coordinates":[-1.438247,53.820921],"type":"Point"}
}
