{
  "type": "Feature",
  "properties": {
    "date:inception_lower": "2007-03-01",
    "date:inception_upper": "2007-03-01",
    "iso:country": "GB",
    "wof:name": "LS14 5QN",
    "wof:placetype": "postalcode"
  },
  "geometry": {"coordinates":[-1.438247,53.820921],"type":"Point"}
}
