{
  "type": "Feature",
  "properties": {
    "iso:country":"GB",
    "wof:name":"LS14 5QN",
    "wof:placetype":"postalcode"
},
  "geometry": {"coordinates":[-1.43824703965075,53.82092105941021],"type":"Point"}
}