{
  "type": "Feature",
  "properties": {
    "iso:country": "GB",
    "wof:name": "WR13 6LW",
    "wof:placetype": "postalcode"
  },
  "geometry": {"coordinates":[-2.285882,52.054042],"type":"Point"}
}
