{
  "type": "Feature",
  "properties": {
    "iso:country":"GB",
    "wof:name":"LU4 9BA",
    "wof:placetype":"postalcode"
},
  "geometry": {"coordinates":[-0.4586445577376,51.90525808336391],"type":"Point"}
}