{
  "type": "Feature",
  "properties": {
    "iso:country": "GB",
    "wof:name": "NE30 1NH",
    "wof:placetype": "postalcode"
  },
  "geometry": {"coordinates":[-1.443864,55.008053],"type":"Point"}
}
