{
  "type": "Feature",
  "properties": {
    "date:inception_lower": "1980-01-01",
    "date:inception_upper": "1980-01-01",
    "iso:country": "GB",
    "wof:name": "NE30 1NH",
    "wof:placetype": "postalcode"
  },
  "geometry": {"coordinates":[-1.443864,55.008053],"type":"Point"}
}
