{
  "type": "Feature",
  "properties": {
    "iso:country": "GB",
    "wof:name": "PH16 5HQ",
    "wof:placetype": "postalcode"
  },
  "geometry": {"coordinates":[-3.729067,56.702815],"type":"Point"}
}
