{
  "type": "Feature",
  "properties": {
    "iso:country":"GB",
    "wof:name":"PH16 5HQ",
    "wof:placetype":"postalcode"
},
  "geometry": {"coordinates":[-3.72906744539594,56.70281471012942],"type":"Point"}
}