{
  "type": "Feature",
  "properties": {
    "iso:country": "GB",
    "wof:name": "WR11 7WA",
    "wof:placetype": "postalcode"
  },
  "geometry": {"coordinates":[-1.971427,52.042699],"type":"Point"}
}
