{
  "type": "Feature",
  "properties": {
    "iso:country":"GB",
    "wof:name":"WR11 7WA",
    "wof:placetype":"postalcode"
},
  "geometry": {"coordinates":[-1.97147945126694,52.04256313281805],"type":"Point"}
}