{
  "type": "Feature",
  "properties": {
    "iso:country":"GB",
    "wof:name":"SE16 5SW",
    "wof:placetype":"postalcode"
},
  "geometry": {"coordinates":[-0.04352647157297,51.50635629303246],"type":"Point"}
}