{
  "type": "Feature",
  "properties": {
    "iso:country":"GB",
    "wof:name":"S72 8JG",
    "wof:placetype":"postalcode"
},
  "geometry": {"coordinates":[-1.41153728894236,53.56816025709698],"type":"Point"}
}