{
  "type": "Feature",
  "properties": {
    "iso:country":"GB",
    "wof:name":"SW5 9HB",
    "wof:placetype":"postalcode"
},
  "geometry": {"coordinates":[-0.1976296975865,51.49092178087682],"type":"Point"}
}