{
  "type": "Feature",
  "properties": {
    "iso:country":"GB",
    "wof:name":"B90 4QG",
    "wof:placetype":"postalcode"
},
  "geometry": {"coordinates":[-1.81270192663325,52.3949934368467],"type":"Point"}
}