{
  "type": "Feature",
  "properties": {
    "iso:country": "GB",
    "wof:name": "GU2 8FP",
    "wof:placetype": "postalcode"
  },
  "geometry": {"coordinates":[-0.607258,51.251094],"type":"Point"}
}
