{
  "type": "Feature",
  "properties": {
    "iso:country":"GB",
    "wof:name":"CV6 1NY",
    "wof:placetype":"postalcode"
},
  "geometry": {"coordinates":[-1.52353917747943,52.42158428638445],"type":"Point"}
}