{
  "type": "Feature",
  "properties": {
    "iso:country":"GB",
    "wof:name":"DA6 7LR",
    "wof:placetype":"postalcode"
},
  "geometry": {"coordinates":[0.14724957229778,51.45451954082269],"type":"Point"}
}