{
  "type": "Feature",
  "properties": {
    "iso:country": "GB",
    "wof:name": "ML6 6NS",
    "wof:placetype": "postalcode"
  },
  "geometry": {"coordinates":[-3.985592,55.87391],"type":"Point"}
}
