{
  "type": "Feature",
  "properties": {
    "iso:country":"GB",
    "wof:name":"ML6 6NS",
    "wof:placetype":"postalcode"
},
  "geometry": {"coordinates":[-3.98559232212671,55.87390951819961],"type":"Point"}
}