{
  "type": "Feature",
  "properties": {
    "date:inception_lower": "1980-01-01",
    "date:inception_upper": "1980-01-01",
    "iso:country": "GB",
    "wof:name": "LN6 8QG",
    "wof:placetype": "postalcode"
  },
  "geometry": {"coordinates":[-0.5944,53.190998],"type":"Point"}
}
