{
  "type": "Feature",
  "properties": {
    "iso:country": "GB",
    "wof:name": "PO16 8NA",
    "wof:placetype": "postalcode"
  },
  "geometry": {"coordinates":[-1.154454,50.848719],"type":"Point"}
}
