{
  "type": "Feature",
  "properties": {
    "iso:country":"GB",
    "wof:name":"PO16 8NA",
    "wof:placetype":"postalcode"
},
  "geometry": {"coordinates":[-1.15445438301537,50.8487190235343],"type":"Point"}
}