{
  "type": "Feature",
  "properties": {
    "date:inception_lower": "1980-01-01",
    "date:inception_upper": "1980-01-01",
    "iso:country": "GB",
    "wof:name": "SA68 0QR",
    "wof:placetype": "postalcode"
  },
  "geometry": {"coordinates":[-4.721237,51.72485],"type":"Point"}
}
