{
  "type": "Feature",
  "properties": {
    "iso:country": "GB",
    "wof:name": "WS15 3HQ",
    "wof:placetype": "postalcode"
  },
  "geometry": {"coordinates":[-1.926786,52.768187],"type":"Point"}
}
