{
  "type": "Feature",
  "properties": {
    "iso:country":"GB",
    "wof:name":"WS15 3HQ",
    "wof:placetype":"postalcode"
},
  "geometry": {"coordinates":[-1.92678575596918,52.76818676995237],"type":"Point"}
}