{
  "type": "Feature",
  "properties": {
    "date:inception_lower": "1980-01-01",
    "date:inception_upper": "1980-01-01",
    "iso:country": "GB",
    "wof:name": "WS15 3HQ",
    "wof:placetype": "postalcode"
  },
  "geometry": {"coordinates":[-1.926786,52.768187],"type":"Point"}
}
