{
  "type": "Feature",
  "properties": {
    "iso:country": "GB",
    "wof:name": "OL13 9SW",
    "wof:placetype": "postalcode"
  },
  "geometry": {"coordinates":[-2.177577,53.690848],"type":"Point"}
}
