{
  "type": "Feature",
  "properties": {
    "iso:country":"GB",
    "wof:name":"KA12 8JD",
    "wof:placetype":"postalcode"
},
  "geometry": {"coordinates":[-4.67229885111254,55.60334818178886],"type":"Point"}
}