{
  "type": "Feature",
  "properties": {
    "date:inception_lower": "2018-08-01",
    "date:inception_upper": "2018-08-01",
    "iso:country": "GB",
    "wof:name": "KY12 0YU",
    "wof:placetype": "postalcode"
  },
  "geometry": {"coordinates":[-3.409641,56.095575],"type":"Point"}
}
