{
  "type": "Feature",
  "properties": {
    "date:inception_lower":"2002-10-01",
    "date:inception_upper":"2002-10-31",
    "iso:country":"GB",
    "wof:name":"WV13 1DE",
    "wof:placetype":"postalcode"
},
  "geometry": {"coordinates":[-2.055914,52.588906],"type":"Point"}
}