{
  "type": "Feature",
  "properties": {
    "iso:country":"GB",
    "wof:name":"GU24 9LN",
    "wof:placetype":"postalcode"
},
  "geometry": {"coordinates":[-0.63681353421255,51.33508880554157],"type":"Point"}
}