{
  "type": "Feature",
  "properties": {
    "date:inception_lower": "1980-01-01",
    "date:inception_upper": "1980-01-01",
    "iso:country": "GB",
    "wof:name": "BS13 0DF",
    "wof:placetype": "postalcode"
  },
  "geometry": {"coordinates":[-2.604544,51.40252],"type":"Point"}
}
