{
  "type": "Feature",
  "properties": {
    "iso:country":"GB",
    "wof:name":"LE18 3QL",
    "wof:placetype":"postalcode"
},
  "geometry": {"coordinates":[-1.09683176200924,52.59127635662993],"type":"Point"}
}