{
  "type": "Feature",
  "properties": {
    "iso:country":"GB",
    "wof:name":"PL8 1LN",
    "wof:placetype":"postalcode"
},
  "geometry": {"coordinates":[-3.95084667897471,50.33517334552696],"type":"Point"}
}