{
  "type": "Feature",
  "properties": {
    "iso:country":"GB",
    "wof:name":"NE2 3RG",
    "wof:placetype":"postalcode"
},
  "geometry": {"coordinates":[-1.602740268631,55.00137812724684],"type":"Point"}
}