{
  "type": "Feature",
  "properties": {
    "iso:country": "GB",
    "wof:name": "NE2 3RG",
    "wof:placetype": "postalcode"
  },
  "geometry": {"coordinates":[-1.60274,55.001378],"type":"Point"}
}
