{
  "type": "Feature",
  "properties": {
    "iso:country":"GB",
    "wof:name":"NG2 4ED",
    "wof:placetype":"postalcode"
},
  "geometry": {"coordinates":[-1.09260286567767,52.95384810312866],"type":"Point"}
}