{
  "type": "Feature",
  "properties": {
    "iso:country": "GB",
    "wof:name": "LL14 3PL",
    "wof:placetype": "postalcode"
  },
  "geometry": {"coordinates":[-3.071326,52.970413],"type":"Point"}
}
