{
  "type": "Feature",
  "properties": {
    "iso:country":"GB",
    "wof:name":"KY8 1LB",
    "wof:placetype":"postalcode"
},
  "geometry": {"coordinates":[-3.0304062650191,56.17291477982522],"type":"Point"}
}