{
  "type": "Feature",
  "properties": {
    "date:inception_lower": "1980-01-01",
    "date:inception_upper": "1980-01-01",
    "iso:country": "GB",
    "wof:name": "NG8 3AY",
    "wof:placetype": "postalcode"
  },
  "geometry": {"coordinates":[-1.218114,52.9736],"type":"Point"}
}
