{
  "type": "Feature",
  "properties": {
    "iso:country":"GB",
    "wof:name":"NG8 3AY",
    "wof:placetype":"postalcode"
},
  "geometry": {"coordinates":[-1.21811393018883,52.97359961867989],"type":"Point"}
}