{
  "type": "Feature",
  "properties": {
    "iso:country":"GB",
    "wof:name":"ME4 5PL",
    "wof:placetype":"postalcode"
},
  "geometry": {"coordinates":[0.52989788559969,51.37611417340402],"type":"Point"}
}