{
  "type": "Feature",
  "properties": {
    "date:inception_lower":"1980-01-01",
    "date:inception_upper":"1980-01-31",
    "iso:country":"GB",
    "wof:name":"CM1 3JF",
    "wof:placetype":"postalcode"
},
  "geometry": {"coordinates":[0.426202,51.72744],"type":"Point"}
}