{
  "type": "Feature",
  "properties": {
    "iso:country":"GB",
    "wof:name":"AL9 5DS",
    "wof:placetype":"postalcode"
},
  "geometry": {"coordinates":[-0.21281673523489,51.77131709576264],"type":"Point"}
}