{
  "type": "Feature",
  "properties": {
    "iso:country": "GB",
    "wof:name": "AL9 5DS",
    "wof:placetype": "postalcode"
  },
  "geometry": {"coordinates":[-0.212817,51.771317],"type":"Point"}
}
