{
  "type": "Feature",
  "properties": {
    "iso:country":"GB",
    "wof:name":"WS11 4AL",
    "wof:placetype":"postalcode"
},
  "geometry": {"coordinates":[-2.03412276893974,52.69595501507594],"type":"Point"}
}