{
  "type": "Feature",
  "properties": {
    "date:inception_lower":"2003-03-01",
    "date:inception_upper":"2003-03-31",
    "iso:country":"GB",
    "wof:name":"WS11 4AL",
    "wof:placetype":"postalcode"
},
  "geometry": {"coordinates":[-2.034123,52.695955],"type":"Point"}
}