{
  "type": "Feature",
  "properties": {
    "iso:country": "GB",
    "wof:name": "WS11 4AL",
    "wof:placetype": "postalcode"
  },
  "geometry": {"coordinates":[-2.034123,52.695955],"type":"Point"}
}
