{
  "type": "Feature",
  "properties": {
    "iso:country":"GB",
    "wof:name":"PE20 1TA",
    "wof:placetype":"postalcode"
},
  "geometry": {"coordinates":[-0.1116904466601,52.95553658215008],"type":"Point"}
}