{
  "type": "Feature",
  "properties": {
    "iso:country":"GB",
    "wof:name":"SA4 4GF",
    "wof:placetype":"postalcode"
},
  "geometry": {"coordinates":[-4.04607352939795,51.67805197425689],"type":"Point"}
}