{
  "type": "Feature",
  "properties": {
    "iso:country": "GB",
    "wof:name": "SA4 4GF",
    "wof:placetype": "postalcode"
  },
  "geometry": {"coordinates":[-4.046073,51.678052],"type":"Point"}
}
