{
  "type": "Feature",
  "properties": {
    "iso:country":"GB",
    "wof:name":"BN6 8UG",
    "wof:placetype":"postalcode"
},
  "geometry": {"coordinates":[-0.11038899059894,50.92193047330321],"type":"Point"}
}