{
  "type": "Feature",
  "properties": {
    "iso:country": "GB",
    "wof:name": "BN6 8UG",
    "wof:placetype": "postalcode"
  },
  "geometry": {"coordinates":[-0.110389,50.92193],"type":"Point"}
}
