{
  "type": "Feature",
  "properties": {
    "date:inception_lower": "2003-02-01",
    "date:inception_upper": "2003-02-01",
    "iso:country": "GB",
    "wof:name": "FK5 4FY",
    "wof:placetype": "postalcode"
  },
  "geometry": {"coordinates":[-3.828429,56.036583],"type":"Point"}
}
