{
  "type": "Feature",
  "properties": {
    "iso:country":"GB",
    "wof:name":"SA15 4DF",
    "wof:placetype":"postalcode"
},
  "geometry": {"coordinates":[-4.18007659654389,51.68950686345979],"type":"Point"}
}