{
  "type": "Feature",
  "properties": {
    "iso:country":"GB",
    "wof:name":"BS16 3JG",
    "wof:placetype":"postalcode"
},
  "geometry": {"coordinates":[-2.53300950409502,51.47652651892379],"type":"Point"}
}