{
  "type": "Feature",
  "properties": {
    "iso:country": "GB",
    "wof:name": "GU7 1UJ",
    "wof:placetype": "postalcode"
  },
  "geometry": {"coordinates":[-0.626322,51.167452],"type":"Point"}
}
