{
  "type": "Feature",
  "properties": {
    "iso:country":"GB",
    "wof:name":"GU7 1UJ",
    "wof:placetype":"postalcode"
},
  "geometry": {"coordinates":[-0.62634214996748,51.16745596740722],"type":"Point"}
}