{
  "type": "Feature",
  "properties": {
    "iso:country":"GB",
    "wof:name":"NG3 6GG",
    "wof:placetype":"postalcode"
},
  "geometry": {"coordinates":[-1.10779213737101,52.9788460347507],"type":"Point"}
}