{
  "type": "Feature",
  "properties": {
    "iso:country": "GB",
    "wof:name": "RH10 3SB",
    "wof:placetype": "postalcode"
  },
  "geometry": {"coordinates":[-0.143965,51.131587],"type":"Point"}
}
