{
  "type": "Feature",
  "properties": {
    "date:inception_lower": "1990-02-01",
    "date:inception_upper": "1990-02-01",
    "iso:country": "GB",
    "wof:name": "RH10 3SB",
    "wof:placetype": "postalcode"
  },
  "geometry": {"coordinates":[-0.143965,51.131587],"type":"Point"}
}
