{
  "type": "Feature",
  "properties": {
    "iso:country":"GB",
    "wof:name":"RH10 3SB",
    "wof:placetype":"postalcode"
},
  "geometry": {"coordinates":[-0.14396479894021,51.1315874085769],"type":"Point"}
}