{
  "type": "Feature",
  "properties": {
    "iso:country":"GB",
    "wof:name":"CW7 2PF",
    "wof:placetype":"postalcode"
},
  "geometry": {"coordinates":[-2.52083388608803,53.21628607990464],"type":"Point"}
}