{
  "type": "Feature",
  "properties": {
    "iso:country":"GB",
    "wof:name":"PO22 6BB",
    "wof:placetype":"postalcode"
},
  "geometry": {"coordinates":[-0.63448939995133,50.80049269384102],"type":"Point"}
}