{
  "type": "Feature",
  "properties": {
    "iso:country":"GB",
    "wof:name":"KA12 8PN",
    "wof:placetype":"postalcode"
},
  "geometry": {"coordinates":[-4.67678273924736,55.61019867090402],"type":"Point"}
}