{
  "type": "Feature",
  "properties": {
    "date:inception_lower":"1989-07-01",
    "date:inception_upper":"1989-07-31",
    "iso:country":"GB",
    "wof:name":"KA12 8PN",
    "wof:placetype":"postalcode"
},
  "geometry": {"coordinates":[-4.676783,55.610199],"type":"Point"}
}