{
  "type": "Feature",
  "properties": {
    "iso:country":"GB",
    "wof:name":"SY11 1AP",
    "wof:placetype":"postalcode"
},
  "geometry": {"coordinates":[-3.05845652919814,52.86048574685391],"type":"Point"}
}