{
  "type": "Feature",
  "properties": {
    "date:inception_lower": "2020-04-01",
    "date:inception_upper": "2020-04-01",
    "iso:country": "GB",
    "wof:name": "PE38 8DL",
    "wof:placetype": "postalcode"
  },
  "geometry": {"coordinates":[0.378004,52.601425],"type":"Point"}
}
