{
  "type": "Feature",
  "properties": {
    "iso:country":"GB",
    "wof:name":"PL19 9JT",
    "wof:placetype":"postalcode"
},
  "geometry": {"coordinates":[-4.09741626931441,50.55878069925726],"type":"Point"}
}