{
  "type": "Feature",
  "properties": {
    "iso:country":"GB",
    "wof:name":"SG9 9EG",
    "wof:placetype":"postalcode"
},
  "geometry": {"coordinates":[-0.02716754132388,51.94875760455711],"type":"Point"}
}