{
  "type": "Feature",
  "properties": {
    "date:inception_lower":"1980-01-01",
    "date:inception_upper":"1980-01-31",
    "iso:country":"GB",
    "wof:name":"OL8 4HN",
    "wof:placetype":"postalcode"
},
  "geometry": {"coordinates":[-2.120053,53.527849],"type":"Point"}
}