{
  "type": "Feature",
  "properties": {
    "date:inception_lower": "1980-01-01",
    "date:inception_upper": "1980-01-01",
    "iso:country": "GB",
    "wof:name": "BH19 3AA",
    "wof:placetype": "postalcode"
  },
  "geometry": {"coordinates":[-1.982958,50.634245],"type":"Point"}
}
