{
  "type": "Feature",
  "properties": {
    "iso:country": "GB",
    "wof:name": "CH66 3LE",
    "wof:placetype": "postalcode"
  },
  "geometry": {"coordinates":[-2.92783,53.274578],"type":"Point"}
}
