{
  "type": "Feature",
  "properties": {
    "date:inception_lower":"1998-12-01",
    "date:inception_upper":"1998-12-31",
    "iso:country":"GB",
    "wof:name":"S41 0GD",
    "wof:placetype":"postalcode"
},
  "geometry": {"coordinates":[-1.411433,53.227875],"type":"Point"}
}