{
  "type": "Feature",
  "properties": {
    "date:inception_lower": "1980-01-01",
    "date:inception_upper": "1980-01-01",
    "iso:country": "GB",
    "wof:name": "BB8 9AS",
    "wof:placetype": "postalcode"
  },
  "geometry": {"coordinates":[-2.177598,53.856883],"type":"Point"}
}
