{
  "type": "Feature",
  "properties": {
    "iso:country":"GB",
    "wof:name":"CM8 3US",
    "wof:placetype":"postalcode"
},
  "geometry": {"coordinates":[0.64759612412062,51.79843804179111],"type":"Point"}
}