{
  "type": "Feature",
  "properties": {
    "date:inception_lower": "1980-01-01",
    "date:inception_upper": "1980-01-01",
    "iso:country": "GB",
    "wof:name": "CM13 1TP",
    "wof:placetype": "postalcode"
  },
  "geometry": {"coordinates":[0.357479,51.638094],"type":"Point"}
}
