{
  "type": "Feature",
  "properties": {
    "iso:country":"GB",
    "wof:name":"CM13 1TP",
    "wof:placetype":"postalcode"
},
  "geometry": {"coordinates":[0.35747891020709,51.63809395115599],"type":"Point"}
}