{
  "type": "Feature",
  "properties": {
    "iso:country": "GB",
    "wof:name": "TN2 5LZ",
    "wof:placetype": "postalcode"
  },
  "geometry": {"coordinates":[0.265494,51.117904],"type":"Point"}
}
