{
  "type": "Feature",
  "properties": {
    "iso:country":"GB",
    "wof:name":"DA11 8PN",
    "wof:placetype":"postalcode"
},
  "geometry": {"coordinates":[0.34516342280763,51.42403476627268],"type":"Point"}
}