{
  "type": "Feature",
  "properties": {
    "date:inception_lower": "1980-01-01",
    "date:inception_upper": "1980-01-01",
    "iso:country": "GB",
    "wof:name": "LD2 3SS",
    "wof:placetype": "postalcode"
  },
  "geometry": {"coordinates":[-3.401797,52.152657],"type":"Point"}
}
