{
  "type": "Feature",
  "properties": {
    "iso:country":"GB",
    "wof:name":"LD2 3SS",
    "wof:placetype":"postalcode"
},
  "geometry": {"coordinates":[-3.40179681895024,52.15265696916703],"type":"Point"}
}