{
  "type": "Feature",
  "properties": {
    "iso:country":"GB",
    "wof:name":"OX29 4EF",
    "wof:placetype":"postalcode"
},
  "geometry": {"coordinates":[-1.37832707302311,51.78726636697312],"type":"Point"}
}