{
  "type": "Feature",
  "properties": {
    "iso:country":"GB",
    "wof:name":"SW20 9NZ",
    "wof:placetype":"postalcode"
},
  "geometry": {"coordinates":[-0.21272908850815,51.407180772811],"type":"Point"}
}