{
  "type": "Feature",
  "properties": {
    "date:inception_lower": "1980-01-01",
    "date:inception_upper": "1980-01-01",
    "iso:country": "GB",
    "wof:name": "SW20 9NZ",
    "wof:placetype": "postalcode"
  },
  "geometry": {"coordinates":[-0.212718,51.407207],"type":"Point"}
}
