{
  "type": "Feature",
  "properties": {
    "iso:country":"GB",
    "wof:name":"SY13 4AP",
    "wof:placetype":"postalcode"
},
  "geometry": {"coordinates":[-2.58638363608483,52.98698307700231],"type":"Point"}
}