{
  "type": "Feature",
  "properties": {
    "iso:country":"GB",
    "wof:name":"E1 8NB",
    "wof:placetype":"postalcode"
},
  "geometry": {"coordinates":[-0.07101200644078,51.50929355359378],"type":"Point"}
}