{
  "type": "Feature",
  "properties": {
    "date:inception_lower": "1990-07-01",
    "date:inception_upper": "1990-07-01",
    "iso:country": "GB",
    "wof:name": "E1 8NB",
    "wof:placetype": "postalcode"
  },
  "geometry": {"coordinates":[-0.071012,51.509294],"type":"Point"}
}
