{
  "type": "Feature",
  "properties": {
    "iso:country": "GB",
    "wof:name": "E1 8NB",
    "wof:placetype": "postalcode"
  },
  "geometry": {"coordinates":[-0.071012,51.509294],"type":"Point"}
}
