{
  "type": "Feature",
  "properties": {
    "iso:country":"GB",
    "wof:name":"IP14 3LR",
    "wof:placetype":"postalcode"
},
  "geometry": {"coordinates":[0.94441209838467,52.23016181210581],"type":"Point"}
}