{
  "type": "Feature",
  "properties": {
    "date:inception_lower": "1980-01-01",
    "date:inception_upper": "1980-01-01",
    "iso:country": "GB",
    "wof:name": "BB2 2SW",
    "wof:placetype": "postalcode"
  },
  "geometry": {"coordinates":[-2.505686,53.74254],"type":"Point"}
}
