{
  "type": "Feature",
  "properties": {
    "date:inception_lower":"2018-08-01",
    "date:inception_upper":"2018-08-31",
    "iso:country":"GB",
    "wof:name":"RG24 9NS",
    "wof:placetype":"postalcode"
},
  "geometry": {"coordinates":[-1.09984,51.284009],"type":"Point"}
}