{
  "type": "Feature",
  "properties": {
    "iso:country": "GB",
    "wof:name": "LS25 3DG",
    "wof:placetype": "postalcode"
  },
  "geometry": {"coordinates":[-1.344213,53.814772],"type":"Point"}
}
