{
  "type": "Feature",
  "properties": {
    "iso:country":"GB",
    "wof:name":"LS25 3DG",
    "wof:placetype":"postalcode"
},
  "geometry": {"coordinates":[-1.34415907641833,53.81502394553679],"type":"Point"}
}