{
  "type": "Feature",
  "properties": {
    "iso:country":"GB",
    "wof:name":"GL6 7NS",
    "wof:placetype":"postalcode"
},
  "geometry": {"coordinates":[-2.12699158873484,51.72962437646399],"type":"Point"}
}