{
  "type": "Feature",
  "properties": {
    "iso:country":"GB",
    "wof:name":"B79 0NN",
    "wof:placetype":"postalcode"
},
  "geometry": {"coordinates":[-1.58902734857447,52.66560954451295],"type":"Point"}
}