{
  "type": "Feature",
  "properties": {
    "date:inception_lower":"1980-01-01",
    "date:inception_upper":"1980-01-31",
    "iso:country":"GB",
    "wof:name":"B79 0NN",
    "wof:placetype":"postalcode"
},
  "geometry": {"coordinates":[-1.589138,52.665735],"type":"Point"}
}