{
  "type": "Feature",
  "properties": {
    "iso:country": "GB",
    "wof:name": "DD3 9HR",
    "wof:placetype": "postalcode"
  },
  "geometry": {"coordinates":[-3.007508,56.494065],"type":"Point"}
}
