{
  "type": "Feature",
  "properties": {
    "iso:country": "GB",
    "wof:name": "LA1 5NU",
    "wof:placetype": "postalcode"
  },
  "geometry": {"coordinates":[-2.80991,54.049197],"type":"Point"}
}
