{
  "type": "Feature",
  "properties": {
    "iso:country":"GB",
    "wof:name":"WS2 8DH",
    "wof:placetype":"postalcode"
},
  "geometry": {"coordinates":[-1.98961029802723,52.58587155746217],"type":"Point"}
}