{
  "type": "Feature",
  "properties": {
    "date:inception_lower":"1993-01-01",
    "date:inception_upper":"1993-01-31",
    "iso:country":"GB",
    "wof:name":"CF63 1LJ",
    "wof:placetype":"postalcode"
},
  "geometry": {"coordinates":[-3.256187,51.415986],"type":"Point"}
}