{
  "type": "Feature",
  "properties": {
    "iso:country":"GB",
    "wof:name":"CF63 1LJ",
    "wof:placetype":"postalcode"
},
  "geometry": {"coordinates":[-3.25618663964781,51.41598558679148],"type":"Point"}
}