{
  "type": "Feature",
  "properties": {
    "iso:country":"GB",
    "wof:name":"TW12 3ED",
    "wof:placetype":"postalcode"
},
  "geometry": {"coordinates":[-0.37401060486464,51.42827850693793],"type":"Point"}
}