{
  "type": "Feature",
  "properties": {
    "iso:country": "GB",
    "wof:name": "TW12 3ED",
    "wof:placetype": "postalcode"
  },
  "geometry": {"coordinates":[-0.374011,51.428279],"type":"Point"}
}
