{
  "type": "Feature",
  "properties": {
    "iso:country":"GB",
    "wof:name":"SO21 1PX",
    "wof:placetype":"postalcode"
},
  "geometry": {"coordinates":[-1.31357851309578,51.01885749682781],"type":"Point"}
}