{
  "type": "Feature",
  "properties": {
    "iso:country":"GB",
    "wof:name":"TN8 6RG",
    "wof:placetype":"postalcode"
},
  "geometry": {"coordinates":[0.06010602743461,51.23482031037383],"type":"Point"}
}