{
  "type": "Feature",
  "properties": {
    "iso:country": "GB",
    "wof:name": "TN8 6RG",
    "wof:placetype": "postalcode"
  },
  "geometry": {"coordinates":[0.060871,51.235309],"type":"Point"}
}
