{
  "type": "Feature",
  "properties": {
    "iso:country":"GB",
    "wof:name":"NG7 7LY",
    "wof:placetype":"postalcode"
},
  "geometry": {"coordinates":[-1.16158127098168,52.97225260765329],"type":"Point"}
}