{
  "type": "Feature",
  "properties": {
    "iso:country":"GB",
    "wof:name":"BB1 9HH",
    "wof:placetype":"postalcode"
},
  "geometry": {"coordinates":[-2.4892746321042,53.7902634669184],"type":"Point"}
}