{
  "type": "Feature",
  "properties": {
    "date:inception_lower": "1980-01-01",
    "date:inception_upper": "1980-01-01",
    "iso:country": "GB",
    "wof:name": "BN12 6DN",
    "wof:placetype": "postalcode"
  },
  "geometry": {"coordinates":[-0.414799,50.819452],"type":"Point"}
}
