{
  "type": "Feature",
  "properties": {
    "iso:country":"GB",
    "wof:name":"BN12 6DN",
    "wof:placetype":"postalcode"
},
  "geometry": {"coordinates":[-0.41496671782382,50.81945330002932],"type":"Point"}
}