{
  "type": "Feature",
  "properties": {
    "iso:country": "GB",
    "wof:name": "NG10 1LL",
    "wof:placetype": "postalcode"
  },
  "geometry": {"coordinates":[-1.26827,52.896771],"type":"Point"}
}
