{
  "type": "Feature",
  "properties": {
    "iso:country":"GB",
    "wof:name":"LL60 6NF",
    "wof:placetype":"postalcode"
},
  "geometry": {"coordinates":[-4.32900681710604,53.18771452183702],"type":"Point"}
}