{
  "type": "Feature",
  "properties": {
    "date:inception_lower": "1980-01-01",
    "date:inception_upper": "1980-01-01",
    "iso:country": "GB",
    "wof:name": "LL60 6NF",
    "wof:placetype": "postalcode"
  },
  "geometry": {"coordinates":[-4.328996,53.187696],"type":"Point"}
}
