{
  "type": "Feature",
  "properties": {
    "date:inception_lower":"1980-01-01",
    "date:inception_upper":"1980-01-31",
    "iso:country":"GB",
    "wof:name":"LL60 6NF",
    "wof:placetype":"postalcode"
},
  "geometry": {"coordinates":[-4.329007,53.187715],"type":"Point"}
}