{
  "type": "Feature",
  "properties": {
    "date:inception_lower": "2003-11-01",
    "date:inception_upper": "2003-11-01",
    "iso:country": "GB",
    "wof:name": "BS6 5ED",
    "wof:placetype": "postalcode"
  },
  "geometry": {"coordinates":[-2.587323,51.46749],"type":"Point"}
}
