{
  "type": "Feature",
  "properties": {
    "iso:country": "GB",
    "wof:name": "SG1 5PJ",
    "wof:placetype": "postalcode"
  },
  "geometry": {"coordinates":[-0.182734,51.916068],"type":"Point"}
}
