{
  "type": "Feature",
  "properties": {
    "date:inception_lower":"1982-03-01",
    "date:inception_upper":"1982-03-31",
    "iso:country":"GB",
    "wof:name":"SG1 5PJ",
    "wof:placetype":"postalcode"
},
  "geometry": {"coordinates":[-0.182734,51.916068],"type":"Point"}
}