{
  "type": "Feature",
  "properties": {
    "iso:country":"GB",
    "wof:name":"TR20 8AQ",
    "wof:placetype":"postalcode"
},
  "geometry": {"coordinates":[-5.49282965130923,50.13825081673115],"type":"Point"}
}