{
  "type": "Feature",
  "properties": {
    "date:inception_lower": "1980-01-01",
    "date:inception_upper": "1980-01-01",
    "iso:country": "GB",
    "wof:name": "EX16 5EE",
    "wof:placetype": "postalcode"
  },
  "geometry": {"coordinates":[-3.493849,50.895609],"type":"Point"}
}
