{
  "type": "Feature",
  "properties": {
    "iso:country": "GB",
    "wof:name": "WA9 1BF",
    "wof:placetype": "postalcode"
  },
  "geometry": {"coordinates":[-2.70977,53.447142],"type":"Point"}
}
