{
  "type": "Feature",
  "properties": {
    "date:inception_lower":"2008-01-01",
    "date:inception_upper":"2008-01-31",
    "iso:country":"GB",
    "wof:name":"WA9 1BF",
    "wof:placetype":"postalcode"
},
  "geometry": {"coordinates":[-2.70977,53.447142],"type":"Point"}
}