{
  "type": "Feature",
  "properties": {
    "iso:country":"GB",
    "wof:name":"SE1 3DD",
    "wof:placetype":"postalcode"
},
  "geometry": {"coordinates":[-0.07809445801458,51.49920323734288],"type":"Point"}
}