{
  "type": "Feature",
  "properties": {
    "date:inception_lower": "2008-05-01",
    "date:inception_upper": "2008-05-01",
    "iso:country": "GB",
    "wof:name": "HX6 4BL",
    "wof:placetype": "postalcode"
  },
  "geometry": {"coordinates":[-1.942775,53.673524],"type":"Point"}
}
