{
  "type": "Feature",
  "properties": {
    "iso:country":"GB",
    "wof:name":"DN36 4BE",
    "wof:placetype":"postalcode"
},
  "geometry": {"coordinates":[-0.06352491433894,53.52294554717886],"type":"Point"}
}