{
  "type": "Feature",
  "properties": {
    "iso:country": "GB",
    "wof:name": "DN36 4BE",
    "wof:placetype": "postalcode"
  },
  "geometry": {"coordinates":[-0.063525,53.522946],"type":"Point"}
}
