{
  "type": "Feature",
  "properties": {
    "iso:country": "GB",
    "wof:name": "CF63 2XQ",
    "wof:placetype": "postalcode"
  },
  "geometry": {"coordinates":[-3.240137,51.412218],"type":"Point"}
}
