{
  "type": "Feature",
  "properties": {
    "iso:country": "GB",
    "wof:name": "TN23 6LX",
    "wof:placetype": "postalcode"
  },
  "geometry": {"coordinates":[0.860117,51.126919],"type":"Point"}
}
