{
  "type": "Feature",
  "properties": {
    "iso:country":"GB",
    "wof:name":"BS26 2DH",
    "wof:placetype":"postalcode"
},
  "geometry": {"coordinates":[-2.81321794507859,51.28547729187046],"type":"Point"}
}