{
  "type": "Feature",
  "properties": {
    "date:inception_lower": "2004-01-01",
    "date:inception_upper": "2004-01-01",
    "iso:country": "GB",
    "wof:name": "PL15 7PJ",
    "wof:placetype": "postalcode"
  },
  "geometry": {"coordinates":[-4.387307,50.628614],"type":"Point"}
}
