{
  "type": "Feature",
  "properties": {
    "iso:country":"GB",
    "wof:name":"PL15 7PJ",
    "wof:placetype":"postalcode"
},
  "geometry": {"coordinates":[-4.38727530860675,50.62862328341936],"type":"Point"}
}