{
  "type": "Feature",
  "properties": {
    "iso:country": "GB",
    "wof:name": "PL15 7PJ",
    "wof:placetype": "postalcode"
  },
  "geometry": {"coordinates":[-4.387307,50.628614],"type":"Point"}
}
