{
  "type": "Feature",
  "properties": {
    "iso:country":"GB",
    "wof:name":"DN22 6NY",
    "wof:placetype":"postalcode"
},
  "geometry": {"coordinates":[-0.94243255773211,53.32376066307816],"type":"Point"}
}