{
  "type": "Feature",
  "properties": {
    "iso:country": "GB",
    "wof:name": "DN22 6NY",
    "wof:placetype": "postalcode"
  },
  "geometry": {"coordinates":[-0.942433,53.323761],"type":"Point"}
}
