{
  "type": "Feature",
  "properties": {
    "iso:country":"GB",
    "wof:name":"S10 1LN",
    "wof:placetype":"postalcode"
},
  "geometry": {"coordinates":[-1.50293170491022,53.38654784870571],"type":"Point"}
}