{
  "type": "Feature",
  "properties": {
    "date:inception_lower": "2016-11-01",
    "date:inception_upper": "2016-11-01",
    "iso:country": "GB",
    "wof:name": "RG7 1FJ",
    "wof:placetype": "postalcode"
  },
  "geometry": {"coordinates":[-0.963046,51.395882],"type":"Point"}
}
