{
  "type": "Feature",
  "properties": {
    "iso:country":"GB",
    "wof:name":"B49 6DB",
    "wof:placetype":"postalcode"
},
  "geometry": {"coordinates":[-1.8639390582587,52.2199607179299],"type":"Point"}
}