{
  "type": "Feature",
  "properties": {
    "iso:country":"GB",
    "wof:name":"ME7 4EA",
    "wof:placetype":"postalcode"
},
  "geometry": {"coordinates":[0.55645953696359,51.38213871241896],"type":"Point"}
}