{
  "type": "Feature",
  "properties": {
    "iso:country": "GB",
    "wof:name": "M41 8QZ",
    "wof:placetype": "postalcode"
  },
  "geometry": {"coordinates":[-2.392345,53.45187],"type":"Point"}
}
