{
  "type": "Feature",
  "properties": {
    "iso:country":"GB",
    "wof:name":"G83 8AY",
    "wof:placetype":"postalcode"
},
  "geometry": {"coordinates":[-4.57035008698995,55.99934198413],"type":"Point"}
}