{
  "type": "Feature",
  "properties": {
    "date:inception_lower":"1991-01-01",
    "date:inception_upper":"1991-01-31",
    "iso:country":"GB",
    "wof:name":"DN16 1DN",
    "wof:placetype":"postalcode"
},
  "geometry": {"coordinates":[-0.618596,53.593894],"type":"Point"}
}