{
  "type": "Feature",
  "properties": {
    "iso:country": "GB",
    "wof:name": "DN16 1DN",
    "wof:placetype": "postalcode"
  },
  "geometry": {"coordinates":[-0.618596,53.593894],"type":"Point"}
}
