{
  "type": "Feature",
  "properties": {
    "iso:country":"GB",
    "wof:name":"DN16 1DN",
    "wof:placetype":"postalcode"
},
  "geometry": {"coordinates":[-0.61859600765793,53.59389438922079],"type":"Point"}
}