{
  "type": "Feature",
  "properties": {
    "iso:country":"GB",
    "wof:name":"G52 3ER",
    "wof:placetype":"postalcode"
},
  "geometry": {"coordinates":[-4.3472228326592,55.84375137819752],"type":"Point"}
}