{
  "type": "Feature",
  "properties": {
    "iso:country":"GB",
    "wof:name":"BN5 9SH",
    "wof:placetype":"postalcode"
},
  "geometry": {"coordinates":[-0.27922590824551,50.92106962134032],"type":"Point"}
}