{
  "type": "Feature",
  "properties": {
    "iso:country":"GB",
    "wof:name":"IP14 5LW",
    "wof:placetype":"postalcode"
},
  "geometry": {"coordinates":[1.01473386938744,52.18679951882498],"type":"Point"}
}