{
  "type": "Feature",
  "properties": {
    "date:inception_lower": "1980-01-01",
    "date:inception_upper": "1980-01-01",
    "iso:country": "GB",
    "wof:name": "CH8 8LE",
    "wof:placetype": "postalcode"
  },
  "geometry": {"coordinates":[-3.245105,53.26303],"type":"Point"}
}
