{
  "type": "Feature",
  "properties": {
    "iso:country":"GB",
    "wof:name":"CH8 8LE",
    "wof:placetype":"postalcode"
},
  "geometry": {"coordinates":[-3.24510479672087,53.26302968803207],"type":"Point"}
}