{
  "type": "Feature",
  "properties": {
    "iso:country":"GB",
    "wof:name":"SO97 4AJ",
    "wof:placetype":"postalcode"
},
  "geometry": {"coordinates":[-1.36196137556479,50.94848747112531],"type":"Point"}
}