{
  "type": "Feature",
  "properties": {
    "date:inception_lower":"2012-02-01",
    "date:inception_upper":"2012-02-29",
    "iso:country":"GB",
    "wof:name":"TA6 6WS",
    "wof:placetype":"postalcode"
},
  "geometry": {"coordinates":[-2.996918,51.107764],"type":"Point"}
}