{
  "type": "Feature",
  "properties": {
    "date:inception_lower": "1980-01-01",
    "date:inception_upper": "1980-01-01",
    "iso:country": "GB",
    "wof:name": "EX39 4NN",
    "wof:placetype": "postalcode"
  },
  "geometry": {"coordinates":[-4.181559,51.036292],"type":"Point"}
}
