{
  "type": "Feature",
  "properties": {
    "date:inception_lower": "1981-06-01",
    "date:inception_upper": "1981-06-01",
    "iso:country": "GB",
    "wof:name": "NE23 7XQ",
    "wof:placetype": "postalcode"
  },
  "geometry": {"coordinates":[-1.594614,55.069296],"type":"Point"}
}
