{
  "type": "Feature",
  "properties": {
    "iso:country": "GB",
    "wof:name": "NE23 7XQ",
    "wof:placetype": "postalcode"
  },
  "geometry": {"coordinates":[-1.594614,55.069296],"type":"Point"}
}
