{
  "type": "Feature",
  "properties": {
    "iso:country":"GB",
    "wof:name":"NE23 7XQ",
    "wof:placetype":"postalcode"
},
  "geometry": {"coordinates":[-1.59461435955751,55.06929583976431],"type":"Point"}
}