{
  "type": "Feature",
  "properties": {
    "iso:country": "GB",
    "wof:name": "IP28 8QN",
    "wof:placetype": "postalcode"
  },
  "geometry": {"coordinates":[0.415527,52.383048],"type":"Point"}
}
