{
  "type": "Feature",
  "properties": {
    "iso:country":"GB",
    "wof:name":"WA14 2HX",
    "wof:placetype":"postalcode"
},
  "geometry": {"coordinates":[-2.3556885205327,53.37557236844749],"type":"Point"}
}