{
  "type": "Feature",
  "properties": {
    "iso:country":"GB",
    "wof:name":"CM12 0AA",
    "wof:placetype":"postalcode"
},
  "geometry": {"coordinates":[0.41914676411951,51.62909613471039],"type":"Point"}
}