{
  "type": "Feature",
  "properties": {
    "iso:country": "GB",
    "wof:name": "WS15 1FA",
    "wof:placetype": "postalcode"
  },
  "geometry": {"coordinates":[-1.913127,52.747294],"type":"Point"}
}
