{
  "type": "Feature",
  "properties": {
    "date:inception_lower": "1980-01-01",
    "date:inception_upper": "1980-01-01",
    "iso:country": "GB",
    "wof:name": "CM18 6QT",
    "wof:placetype": "postalcode"
  },
  "geometry": {"coordinates":[0.110585,51.755865],"type":"Point"}
}
