{
  "type": "Feature",
  "properties": {
    "iso:country":"GB",
    "wof:name":"NW9 5QS",
    "wof:placetype":"postalcode"
},
  "geometry": {"coordinates":[-0.2433951228744,51.60173648841994],"type":"Point"}
}