{
  "type": "Feature",
  "properties": {
    "iso:country":"GB",
    "wof:name":"BN8 4AE",
    "wof:placetype":"postalcode"
},
  "geometry": {"coordinates":[-0.02324412264336,50.93825846087845],"type":"Point"}
}