{
  "type": "Feature",
  "properties": {
    "iso:country":"GB",
    "wof:name":"LS27 8ET",
    "wof:placetype":"postalcode"
},
  "geometry": {"coordinates":[-1.58131347333843,53.74416320663246],"type":"Point"}
}