{
  "type": "Feature",
  "properties": {
    "iso:country": "GB",
    "wof:name": "IP14 6RS",
    "wof:placetype": "postalcode"
  },
  "geometry": {"coordinates":[1.179847,52.223698],"type":"Point"}
}
