{
  "type": "Feature",
  "properties": {
    "iso:country":"GB",
    "wof:name":"TN4 8SH",
    "wof:placetype":"postalcode"
},
  "geometry": {"coordinates":[0.22643294727739,51.13585008407794],"type":"Point"}
}