{
  "type": "Feature",
  "properties": {
    "date:inception_lower":"2013-02-01",
    "date:inception_upper":"2013-02-28",
    "iso:country":"GB",
    "wof:name":"HP19 9DX",
    "wof:placetype":"postalcode"
},
  "geometry": {"coordinates":[-0.821133,51.836032],"type":"Point"}
}