{
  "type": "Feature",
  "properties": {
    "iso:country":"GB",
    "wof:name":"HP19 9DX",
    "wof:placetype":"postalcode"
},
  "geometry": {"coordinates":[-0.82113322458397,51.83603246778881],"type":"Point"}
}