{
  "type": "Feature",
  "properties": {
    "iso:country": "GB",
    "wof:name": "S71 5EZ",
    "wof:placetype": "postalcode"
  },
  "geometry": {"coordinates":[-1.404084,53.541967],"type":"Point"}
}
