{
  "type": "Feature",
  "properties": {
    "iso:country":"GB",
    "wof:name":"S71 5EZ",
    "wof:placetype":"postalcode"
},
  "geometry": {"coordinates":[-1.4040837005004,53.54196694416063],"type":"Point"}
}