{
  "type": "Feature",
  "properties": {
    "iso:country":"GB",
    "wof:name":"GL7 5DB",
    "wof:placetype":"postalcode"
},
  "geometry": {"coordinates":[-1.78670552151108,51.73880600673181],"type":"Point"}
}