{
  "type": "Feature",
  "properties": {
    "iso:country":"GB",
    "wof:name":"IG9 5RD",
    "wof:placetype":"postalcode"
},
  "geometry": {"coordinates":[0.04240036214888,51.63254198685588],"type":"Point"}
}