{
  "type": "Feature",
  "properties": {
    "date:inception_lower": "1980-01-01",
    "date:inception_upper": "1980-01-01",
    "iso:country": "GB",
    "wof:name": "BH16 6BG",
    "wof:placetype": "postalcode"
  },
  "geometry": {"coordinates":[-2.07822,50.757881],"type":"Point"}
}
