{
  "type": "Feature",
  "properties": {
    "iso:country":"GB",
    "wof:name":"BH16 6BG",
    "wof:placetype":"postalcode"
},
  "geometry": {"coordinates":[-2.07831909290585,50.75788951012582],"type":"Point"}
}