{
  "type": "Feature",
  "properties": {
    "date:inception_lower": "2021-04-01",
    "date:inception_upper": "2021-04-01",
    "iso:country": "GB",
    "wof:name": "BN8 5GE",
    "wof:placetype": "postalcode"
  },
  "geometry": {"coordinates":[0.07902,50.897311],"type":"Point"}
}
