{
  "type": "Feature",
  "properties": {
    "iso:country": "GB",
    "wof:name": "NE5 1EF",
    "wof:placetype": "postalcode"
  },
  "geometry": {"coordinates":[-1.716126,54.996834],"type":"Point"}
}
