{
  "type": "Feature",
  "properties": {
    "iso:country": "GB",
    "wof:name": "LN11 9DN",
    "wof:placetype": "postalcode"
  },
  "geometry": {"coordinates":[0.006516,53.365091],"type":"Point"}
}
