{
  "type": "Feature",
  "properties": {
    "iso:country":"GB",
    "wof:name":"PR2 2PP",
    "wof:placetype":"postalcode"
},
  "geometry": {"coordinates":[-2.71650612485712,53.76344128174049],"type":"Point"}
}