{
  "type": "Feature",
  "properties": {
    "iso:country": "GB",
    "wof:name": "BL6 4PL",
    "wof:placetype": "postalcode"
  },
  "geometry": {"coordinates":[-2.497122,53.575673],"type":"Point"}
}
