{
  "type": "Feature",
  "properties": {
    "iso:country":"GB",
    "wof:name":"BL6 4PL",
    "wof:placetype":"postalcode"
},
  "geometry": {"coordinates":[-2.49712225533115,53.57567314683133],"type":"Point"}
}