{
  "type": "Feature",
  "properties": {
    "iso:country":"GB",
    "wof:name":"L21 5HU",
    "wof:placetype":"postalcode"
},
  "geometry": {"coordinates":[-2.98293831368226,53.47283771896924],"type":"Point"}
}