{
  "type": "Feature",
  "properties": {
    "date:inception_lower":"1980-01-01",
    "date:inception_upper":"1980-01-31",
    "iso:country":"GB",
    "wof:name":"SG12 8DB",
    "wof:placetype":"postalcode"
},
  "geometry": {"coordinates":[0.004058,51.79548],"type":"Point"}
}