{
  "type": "Feature",
  "properties": {
    "iso:country":"GB",
    "wof:name":"SG12 8DB",
    "wof:placetype":"postalcode"
},
  "geometry": {"coordinates":[0.00405830106878,51.79547974846164],"type":"Point"}
}