{
  "type": "Feature",
  "properties": {
    "iso:country": "GB",
    "wof:name": "SG12 8DB",
    "wof:placetype": "postalcode"
  },
  "geometry": {"coordinates":[0.004058,51.79548],"type":"Point"}
}
