{
  "type": "Feature",
  "properties": {
    "iso:country":"GB",
    "wof:name":"OX26 6WG",
    "wof:placetype":"postalcode"
},
  "geometry": {"coordinates":[-1.14446506303171,51.89366491400751],"type":"Point"}
}