{
  "type": "Feature",
  "properties": {
    "iso:country":"GB",
    "wof:name":"TR4 8ER",
    "wof:placetype":"postalcode"
},
  "geometry": {"coordinates":[-5.17940231507699,50.27149004401969],"type":"Point"}
}