{
  "type": "Feature",
  "properties": {
    "iso:country": "GB",
    "wof:name": "TR4 8ER",
    "wof:placetype": "postalcode"
  },
  "geometry": {"coordinates":[-5.179402,50.27149],"type":"Point"}
}
