{
  "type": "Feature",
  "properties": {
    "iso:country":"GB",
    "wof:name":"IP17 2BH",
    "wof:placetype":"postalcode"
},
  "geometry": {"coordinates":[1.44691623412005,52.21271238854932],"type":"Point"}
}