{
  "type": "Feature",
  "properties": {
    "iso:country":"GB",
    "wof:name":"PO1 4LZ",
    "wof:placetype":"postalcode"
},
  "geometry": {"coordinates":[-1.08161125948684,50.80529130029817],"type":"Point"}
}