{
  "type": "Feature",
  "properties": {
    "iso:country": "GB",
    "wof:name": "NR18 0GD",
    "wof:placetype": "postalcode"
  },
  "geometry": {"coordinates":[1.139672,52.585088],"type":"Point"}
}
