{
  "type": "Feature",
  "properties": {
    "date:inception_lower":"2014-09-01",
    "date:inception_upper":"2014-09-30",
    "iso:country":"GB",
    "wof:name":"NR18 0GD",
    "wof:placetype":"postalcode"
},
  "geometry": {"coordinates":[1.139672,52.585088],"type":"Point"}
}