{
  "type": "Feature",
  "properties": {
    "iso:country":"GB",
    "wof:name":"NR18 0GD",
    "wof:placetype":"postalcode"
},
  "geometry": {"coordinates":[1.13935641743519,52.58468574211487],"type":"Point"}
}