{
  "type": "Feature",
  "properties": {
    "iso:country": "GB",
    "wof:name": "NE12 6SJ",
    "wof:placetype": "postalcode"
  },
  "geometry": {"coordinates":[-1.578918,55.038519],"type":"Point"}
}
