{
  "type": "Feature",
  "properties": {
    "iso:country":"GB",
    "wof:name":"RG7 4AT",
    "wof:placetype":"postalcode"
},
  "geometry": {"coordinates":[-1.06894280725024,51.42508471779204],"type":"Point"}
}