{
  "type": "Feature",
  "properties": {
    "iso:country":"GB",
    "wof:name":"M19 2EY",
    "wof:placetype":"postalcode"
},
  "geometry": {"coordinates":[-2.19746498109368,53.44258044745652],"type":"Point"}
}