{
  "type": "Feature",
  "properties": {
    "iso:country": "GB",
    "wof:name": "CM1 3HJ",
    "wof:placetype": "postalcode"
  },
  "geometry": {"coordinates":[0.426688,51.724285],"type":"Point"}
}
