{
  "type": "Feature",
  "properties": {
    "iso:country":"GB",
    "wof:name":"SW19 1ER",
    "wof:placetype":"postalcode"
},
  "geometry": {"coordinates":[-0.19109965463957,51.41967233801297],"type":"Point"}
}