{
  "type": "Feature",
  "properties": {
    "iso:country":"GB",
    "wof:name":"PO19 8PL",
    "wof:placetype":"postalcode"
},
  "geometry": {"coordinates":[-0.758648358572,50.83032444828979],"type":"Point"}
}