{
  "type": "Feature",
  "properties": {
    "iso:country":"GB",
    "wof:name":"CM20 3JN",
    "wof:placetype":"postalcode"
},
  "geometry": {"coordinates":[0.11175523489242,51.77505195919714],"type":"Point"}
}