{
  "type": "Feature",
  "properties": {
    "iso:country": "GB",
    "wof:name": "CM20 3JN",
    "wof:placetype": "postalcode"
  },
  "geometry": {"coordinates":[0.111794,51.774995],"type":"Point"}
}
