{
  "type": "Feature",
  "properties": {
    "iso:country": "GB",
    "wof:name": "E11 4HZ",
    "wof:placetype": "postalcode"
  },
  "geometry": {"coordinates":[0.001685,51.556797],"type":"Point"}
}
