{
  "type": "Feature",
  "properties": {
    "iso:country":"GB",
    "wof:name":"PE15 8JR",
    "wof:placetype":"postalcode"
},
  "geometry": {"coordinates":[0.07977916240535,52.55678453180707],"type":"Point"}
}