{
  "type": "Feature",
  "properties": {
    "iso:country":"GB",
    "wof:name":"CT2 9NE",
    "wof:placetype":"postalcode"
},
  "geometry": {"coordinates":[1.06960302210889,51.30825294424118],"type":"Point"}
}