{
  "type": "Feature",
  "properties": {
    "date:inception_lower": "2009-03-01",
    "date:inception_upper": "2009-03-01",
    "iso:country": "GB",
    "wof:name": "TR19 7AL",
    "wof:placetype": "postalcode"
  },
  "geometry": {"coordinates":[-5.67274,50.146926],"type":"Point"}
}
