{
  "type": "Feature",
  "properties": {
    "iso:country":"GB",
    "wof:name":"TR19 7AL",
    "wof:placetype":"postalcode"
},
  "geometry": {"coordinates":[-5.67273983231427,50.14692603004659],"type":"Point"}
}