{
  "type": "Feature",
  "properties": {
    "iso:country":"GB",
    "wof:name":"NR35 1AQ",
    "wof:placetype":"postalcode"
},
  "geometry": {"coordinates":[1.43461279844677,52.45651940614369],"type":"Point"}
}