{
  "type": "Feature",
  "properties": {
    "date:inception_lower": "1980-01-01",
    "date:inception_upper": "1980-01-01",
    "iso:country": "GB",
    "wof:name": "NR35 1AQ",
    "wof:placetype": "postalcode"
  },
  "geometry": {"coordinates":[1.434613,52.456519],"type":"Point"}
}
