{
  "type": "Feature",
  "properties": {
    "date:inception_lower": "2007-01-01",
    "date:inception_upper": "2007-01-01",
    "iso:country": "GB",
    "wof:name": "SK11 7WJ",
    "wof:placetype": "postalcode"
  },
  "geometry": {"coordinates":[-2.133622,53.242761],"type":"Point"}
}
