{
  "type": "Feature",
  "properties": {
    "date:inception_lower": "1995-07-01",
    "date:inception_upper": "1995-07-01",
    "iso:country": "GB",
    "wof:name": "RG45 6DR",
    "wof:placetype": "postalcode"
  },
  "geometry": {"coordinates":[-0.81793,51.367027],"type":"Point"}
}
