{
  "type": "Feature",
  "properties": {
    "iso:country": "GB",
    "wof:name": "WF10 5QG",
    "wof:placetype": "postalcode"
  },
  "geometry": {"coordinates":[-1.381441,53.709027],"type":"Point"}
}
