{
  "type": "Feature",
  "properties": {
    "iso:country":"GB",
    "wof:name":"HD8 9QQ",
    "wof:placetype":"postalcode"
},
  "geometry": {"coordinates":[-1.6052500915601,53.60047798992881],"type":"Point"}
}