{
  "type": "Feature",
  "properties": {
    "iso:country":"GB",
    "wof:name":"PE33 9AT",
    "wof:placetype":"postalcode"
},
  "geometry": {"coordinates":[0.48505999345444,52.58323710532969],"type":"Point"}
}