{
  "type": "Feature",
  "properties": {
    "iso:country": "GB",
    "wof:name": "PE33 9AT",
    "wof:placetype": "postalcode"
  },
  "geometry": {"coordinates":[0.48506,52.583237],"type":"Point"}
}
