{
  "type": "Feature",
  "properties": {
    "iso:country": "GB",
    "wof:name": "NG32 2BU",
    "wof:placetype": "postalcode"
  },
  "geometry": {"coordinates":[-0.601838,52.960146],"type":"Point"}
}
