{
  "type": "Feature",
  "properties": {
    "iso:country":"GB",
    "wof:name":"M24 6EH",
    "wof:placetype":"postalcode"
},
  "geometry": {"coordinates":[-2.19550469181092,53.55970277511832],"type":"Point"}
}