{
  "type": "Feature",
  "properties": {
    "iso:country":"GB",
    "wof:name":"W14 8AH",
    "wof:placetype":"postalcode"
},
  "geometry": {"coordinates":[-0.21440586618394,51.5032282968578],"type":"Point"}
}