{
  "type": "Feature",
  "properties": {
    "date:inception_lower": "2022-12-01",
    "date:inception_upper": "2022-12-01",
    "iso:country": "GB",
    "wof:name": "IP14 1XT",
    "wof:placetype": "postalcode"
  },
  "geometry": {"coordinates":[0.970866,52.197949],"type":"Point"}
}
