{
  "type": "Feature",
  "properties": {
    "date:inception_lower": "2016-09-01",
    "date:inception_upper": "2016-09-01",
    "iso:country": "GB",
    "wof:name": "L34 1WD",
    "wof:placetype": "postalcode"
  },
  "geometry": {"coordinates":[-2.801854,53.428643],"type":"Point"}
}
