{
  "type": "Feature",
  "properties": {
    "date:inception_lower": "2018-05-01",
    "date:inception_upper": "2018-05-01",
    "iso:country": "GB",
    "wof:name": "YO43 3GS",
    "wof:placetype": "postalcode"
  },
  "geometry": {"coordinates":[-0.681921,53.863123],"type":"Point"}
}
