{
  "type": "Feature",
  "properties": {
    "iso:country":"GB",
    "wof:name":"LS27 9DT",
    "wof:placetype":"postalcode"
},
  "geometry": {"coordinates":[-1.58931877740049,53.73798908929232],"type":"Point"}
}