{
  "type": "Feature",
  "properties": {
    "iso:country": "GB",
    "wof:name": "SK14 5EE",
    "wof:placetype": "postalcode"
  },
  "geometry": {"coordinates":[-2.073731,53.434802],"type":"Point"}
}
