{
  "type": "Feature",
  "properties": {
    "iso:country":"GB",
    "wof:name":"EX17 5JG",
    "wof:placetype":"postalcode"
},
  "geometry": {"coordinates":[-3.73709308686952,50.78311461778127],"type":"Point"}
}