{
  "type": "Feature",
  "properties": {
    "iso:country": "GB",
    "wof:name": "WN1 2XW",
    "wof:placetype": "postalcode"
  },
  "geometry": {"coordinates":[-2.636667,53.590873],"type":"Point"}
}
