{
  "type": "Feature",
  "properties": {
    "iso:country":"GB",
    "wof:name":"WN1 2XW",
    "wof:placetype":"postalcode"
},
  "geometry": {"coordinates":[-2.63666988966703,53.59093911711133],"type":"Point"}
}