{
  "type": "Feature",
  "properties": {
    "date:inception_lower": "1980-01-01",
    "date:inception_upper": "1980-01-01",
    "iso:country": "GB",
    "wof:name": "WN1 2XW",
    "wof:placetype": "postalcode"
  },
  "geometry": {"coordinates":[-2.636667,53.590873],"type":"Point"}
}
