{
  "type": "Feature",
  "properties": {
    "iso:country": "GB",
    "wof:name": "TF1 6PB",
    "wof:placetype": "postalcode"
  },
  "geometry": {"coordinates":[-2.4908,52.716339],"type":"Point"}
}
