{
  "type": "Feature",
  "properties": {
    "iso:country":"GB",
    "wof:name":"GU27 3TA",
    "wof:placetype":"postalcode"
},
  "geometry": {"coordinates":[-0.72676662950482,51.05194982831956],"type":"Point"}
}