{
  "type": "Feature",
  "properties": {
    "date:inception_lower": "2006-04-01",
    "date:inception_upper": "2006-04-01",
    "iso:country": "GB",
    "wof:name": "GU27 3TA",
    "wof:placetype": "postalcode"
  },
  "geometry": {"coordinates":[-0.726767,51.05195],"type":"Point"}
}
