{
  "type": "Feature",
  "properties": {
    "iso:country": "GB",
    "wof:name": "GU27 3TA",
    "wof:placetype": "postalcode"
  },
  "geometry": {"coordinates":[-0.726767,51.05195],"type":"Point"}
}
