{
  "type": "Feature",
  "properties": {
    "iso:country": "GB",
    "wof:name": "SW6 2QU",
    "wof:placetype": "postalcode"
  },
  "geometry": {"coordinates":[-0.185517,51.472004],"type":"Point"}
}
