{
  "type": "Feature",
  "properties": {
    "iso:country":"GB",
    "wof:name":"SW6 2QU",
    "wof:placetype":"postalcode"
},
  "geometry": {"coordinates":[-0.18551714147768,51.47200361464587],"type":"Point"}
}