{
  "type": "Feature",
  "properties": {
    "iso:country":"GB",
    "wof:name":"WF3 1HW",
    "wof:placetype":"postalcode"
},
  "geometry": {"coordinates":[-1.57774684205071,53.71574820997896],"type":"Point"}
}