{
  "type": "Feature",
  "properties": {
    "iso:country":"GB",
    "wof:name":"L4 1TH",
    "wof:placetype":"postalcode"
},
  "geometry": {"coordinates":[-2.98116713700507,53.43524289909583],"type":"Point"}
}