{
  "type": "Feature",
  "properties": {
    "iso:country": "GB",
    "wof:name": "YO61 3GS",
    "wof:placetype": "postalcode"
  },
  "geometry": {"coordinates":[-1.186082,54.117451],"type":"Point"}
}
