{
  "type": "Feature",
  "properties": {
    "iso:country":"GB",
    "wof:name":"M5 3SS",
    "wof:placetype":"postalcode"
},
  "geometry": {"coordinates":[-2.28217967529354,53.4745351024341],"type":"Point"}
}