{
  "type": "Feature",
  "properties": {
    "date:inception_lower": "1995-01-01",
    "date:inception_upper": "1995-01-01",
    "iso:country": "GB",
    "wof:name": "M5 3SS",
    "wof:placetype": "postalcode"
  },
  "geometry": {"coordinates":[-2.28218,53.474535],"type":"Point"}
}
