{
  "type": "Feature",
  "properties": {
    "iso:country":"GB",
    "wof:name":"PE1 3XN",
    "wof:placetype":"postalcode"
},
  "geometry": {"coordinates":[-0.23880356663314,52.60024532845186],"type":"Point"}
}