{
  "type": "Feature",
  "properties": {
    "iso:country":"GB",
    "wof:name":"SG6 3JU",
    "wof:placetype":"postalcode"
},
  "geometry": {"coordinates":[-0.22586993461649,51.97078459767245],"type":"Point"}
}