{
  "type": "Feature",
  "properties": {
    "iso:country":"GB",
    "wof:name":"KA6 5AN",
    "wof:placetype":"postalcode"
},
  "geometry": {"coordinates":[-4.50965357117272,55.48671897027306],"type":"Point"}
}