{
  "type": "Feature",
  "properties": {
    "iso:country":"GB",
    "wof:name":"G74 3QD",
    "wof:placetype":"postalcode"
},
  "geometry": {"coordinates":[-4.1453403073279,55.77719416379973],"type":"Point"}
}