{
  "type": "Feature",
  "properties": {
    "iso:country": "GB",
    "wof:name": "G74 3QD",
    "wof:placetype": "postalcode"
  },
  "geometry": {"coordinates":[-4.14534,55.777194],"type":"Point"}
}
