{
  "type": "Feature",
  "properties": {
    "iso:country":"GB",
    "wof:name":"SL7 3QQ",
    "wof:placetype":"postalcode"
},
  "geometry": {"coordinates":[-0.78469921885953,51.59909282109066],"type":"Point"}
}