{
  "type": "Feature",
  "properties": {
    "iso:country":"GB",
    "wof:name":"UB2 4LG",
    "wof:placetype":"postalcode"
},
  "geometry": {"coordinates":[-0.36600118551329,51.49510609048671],"type":"Point"}
}