{
  "type": "Feature",
  "properties": {
    "iso:country":"GB",
    "wof:name":"IP29 5EG",
    "wof:placetype":"postalcode"
},
  "geometry": {"coordinates":[0.57777532038758,52.23622527920086],"type":"Point"}
}