{
  "type": "Feature",
  "properties": {
    "date:inception_lower":"1980-01-01",
    "date:inception_upper":"1980-01-31",
    "iso:country":"GB",
    "wof:name":"BA4 5QT",
    "wof:placetype":"postalcode"
},
  "geometry": {"coordinates":[-2.549083,51.1826],"type":"Point"}
}