{
  "type": "Feature",
  "properties": {
    "iso:country": "GB",
    "wof:name": "BA4 5QT",
    "wof:placetype": "postalcode"
  },
  "geometry": {"coordinates":[-2.549083,51.1826],"type":"Point"}
}
