{
  "type": "Feature",
  "properties": {
    "date:inception_lower":"2012-09-01",
    "date:inception_upper":"2012-09-30",
    "iso:country":"GB",
    "wof:name":"BA2 4FA",
    "wof:placetype":"postalcode"
},
  "geometry": {"coordinates":[-2.352871,51.376687],"type":"Point"}
}