{
  "type": "Feature",
  "properties": {
    "iso:country": "GB",
    "wof:name": "BA2 4FA",
    "wof:placetype": "postalcode"
  },
  "geometry": {"coordinates":[-2.352871,51.376687],"type":"Point"}
}
