{
  "type": "Feature",
  "properties": {
    "date:inception_lower":"1990-02-01",
    "date:inception_upper":"1990-02-28",
    "iso:country":"GB",
    "wof:name":"PE2 8NP",
    "wof:placetype":"postalcode"
},
  "geometry": {"coordinates":[-0.211988,52.556363],"type":"Point"}
}