{
  "type": "Feature",
  "properties": {
    "iso:country":"GB",
    "wof:name":"PE2 8NP",
    "wof:placetype":"postalcode"
},
  "geometry": {"coordinates":[-0.21198783895155,52.55636328731001],"type":"Point"}
}