{
  "type": "Feature",
  "properties": {
    "iso:country": "GB",
    "wof:name": "PA43 7JB",
    "wof:placetype": "postalcode"
  },
  "geometry": {"coordinates":[-6.277464,55.755346],"type":"Point"}
}
