{
  "type": "Feature",
  "properties": {
    "iso:country": "GB",
    "wof:name": "NE5 2JT",
    "wof:placetype": "postalcode"
  },
  "geometry": {"coordinates":[-1.702883,54.990934],"type":"Point"}
}
