{
  "type": "Feature",
  "properties": {
    "date:inception_lower": "1984-10-01",
    "date:inception_upper": "1984-10-01",
    "iso:country": "GB",
    "wof:name": "SK8 2PY",
    "wof:placetype": "postalcode"
  },
  "geometry": {"coordinates":[-2.21754,53.396857],"type":"Point"}
}
