{
  "type": "Feature",
  "properties": {
    "iso:country":"GB",
    "wof:name":"SK8 2PY",
    "wof:placetype":"postalcode"
},
  "geometry": {"coordinates":[-2.21754014967181,53.39685675689245],"type":"Point"}
}