{
  "type": "Feature",
  "properties": {
    "date:inception_lower":"1984-10-01",
    "date:inception_upper":"1984-10-31",
    "iso:country":"GB",
    "wof:name":"TQ9 5NH",
    "wof:placetype":"postalcode"
},
  "geometry": {"coordinates":[-3.692984,50.433804],"type":"Point"}
}