{
  "type": "Feature",
  "properties": {
    "iso:country":"GB",
    "wof:name":"TQ9 5NH",
    "wof:placetype":"postalcode"
},
  "geometry": {"coordinates":[-3.69298422427888,50.4338042568472],"type":"Point"}
}