{
  "type": "Feature",
  "properties": {
    "iso:country": "GB",
    "wof:name": "TQ9 5NH",
    "wof:placetype": "postalcode"
  },
  "geometry": {"coordinates":[-3.692984,50.433804],"type":"Point"}
}
