{
  "type": "Feature",
  "properties": {
    "date:inception_lower":"1980-01-01",
    "date:inception_upper":"1980-01-31",
    "iso:country":"GB",
    "wof:name":"BN1 2PG",
    "wof:placetype":"postalcode"
},
  "geometry": {"coordinates":[-0.155949,50.823597],"type":"Point"}
}