{
  "type": "Feature",
  "properties": {
    "iso:country":"GB",
    "wof:name":"BN1 2PG",
    "wof:placetype":"postalcode"
},
  "geometry": {"coordinates":[-0.15594911735837,50.82359693864496],"type":"Point"}
}