{
  "type": "Feature",
  "properties": {
    "iso:country": "GB",
    "wof:name": "TR26 2GP",
    "wof:placetype": "postalcode"
  },
  "geometry": {"coordinates":[-5.482532,50.206315],"type":"Point"}
}
