{
  "type": "Feature",
  "properties": {
    "date:inception_lower": "1996-06-01",
    "date:inception_upper": "1996-06-01",
    "iso:country": "GB",
    "wof:name": "G82 5HP",
    "wof:placetype": "postalcode"
  },
  "geometry": {"coordinates":[-4.606393,55.951028],"type":"Point"}
}
