{
  "type": "Feature",
  "properties": {
    "iso:country": "GB",
    "wof:name": "CO2 9ET",
    "wof:placetype": "postalcode"
  },
  "geometry": {"coordinates":[0.872213,51.868097],"type":"Point"}
}
