{
  "type": "Feature",
  "properties": {
    "iso:country":"GB",
    "wof:name":"TN18 4BP",
    "wof:placetype":"postalcode"
},
  "geometry": {"coordinates":[0.50829056233589,51.04904430378695],"type":"Point"}
}