{
  "type": "Feature",
  "properties": {
    "iso:country": "GB",
    "wof:name": "TN18 4BP",
    "wof:placetype": "postalcode"
  },
  "geometry": {"coordinates":[0.508377,51.049041],"type":"Point"}
}
