{
  "type": "Feature",
  "properties": {
    "date:inception_lower": "1980-01-01",
    "date:inception_upper": "1980-01-01",
    "iso:country": "GB",
    "wof:name": "ZE2 9AH",
    "wof:placetype": "postalcode"
  },
  "geometry": {"coordinates":[-0.985926,60.341632],"type":"Point"}
}
