{
  "type": "Feature",
  "properties": {
    "iso:country": "GB",
    "wof:name": "ZE2 9AH",
    "wof:placetype": "postalcode"
  },
  "geometry": {"coordinates":[-0.985926,60.341632],"type":"Point"}
}
