{
  "type": "Feature",
  "properties": {
    "iso:country":"GB",
    "wof:name":"ZE2 9AH",
    "wof:placetype":"postalcode"
},
  "geometry": {"coordinates":[-0.98664187815549,60.34191550442959],"type":"Point"}
}