{
  "type": "Feature",
  "properties": {
    "date:inception_lower":"1980-01-01",
    "date:inception_upper":"1980-01-31",
    "iso:country":"GB",
    "wof:name":"CF5 1NB",
    "wof:placetype":"postalcode"
},
  "geometry": {"coordinates":[-3.208978,51.481998],"type":"Point"}
}