{
  "type": "Feature",
  "properties": {
    "iso:country":"GB",
    "wof:name":"CF5 1NB",
    "wof:placetype":"postalcode"
},
  "geometry": {"coordinates":[-3.20897825926438,51.48199778964644],"type":"Point"}
}