{
  "type": "Feature",
  "properties": {
    "iso:country":"GB",
    "wof:name":"LL21 0PS",
    "wof:placetype":"postalcode"
},
  "geometry": {"coordinates":[-3.50708681463065,52.99431040395343],"type":"Point"}
}