{
  "type": "Feature",
  "properties": {
    "iso:country":"GB",
    "wof:name":"OX1 3DZ",
    "wof:placetype":"postalcode"
},
  "geometry": {"coordinates":[-1.25649008977307,51.75274331940221],"type":"Point"}
}