{
  "type": "Feature",
  "properties": {
    "iso:country":"GB",
    "wof:name":"HA7 3HF",
    "wof:placetype":"postalcode"
},
  "geometry": {"coordinates":[-0.3238418262172,51.62676001165293],"type":"Point"}
}