{
  "type": "Feature",
  "properties": {
    "iso:country":"GB",
    "wof:name":"S44 6PR",
    "wof:placetype":"postalcode"
},
  "geometry": {"coordinates":[-1.29688517875318,53.23141615655196],"type":"Point"}
}