{
  "type": "Feature",
  "properties": {
    "iso:country":"GB",
    "wof:name":"SY11 2TE",
    "wof:placetype":"postalcode"
},
  "geometry": {"coordinates":[-3.05863543465696,52.85685227466283],"type":"Point"}
}