{
  "type": "Feature",
  "properties": {
    "iso:country": "GB",
    "wof:name": "ME19 4NJ",
    "wof:placetype": "postalcode"
  },
  "geometry": {"coordinates":[0.410994,51.273408],"type":"Point"}
}
