{
  "type": "Feature",
  "properties": {
    "iso:country": "GB",
    "wof:name": "CA14 3UT",
    "wof:placetype": "postalcode"
  },
  "geometry": {"coordinates":[-3.553011,54.637299],"type":"Point"}
}
