{
  "type": "Feature",
  "properties": {
    "iso:country": "GB",
    "wof:name": "BD17 6ND",
    "wof:placetype": "postalcode"
  },
  "geometry": {"coordinates":[-1.764062,53.853228],"type":"Point"}
}
