{
  "type": "Feature",
  "properties": {
    "iso:country":"GB",
    "wof:name":"BD17 6ND",
    "wof:placetype":"postalcode"
},
  "geometry": {"coordinates":[-1.76406221779232,53.85322761483853],"type":"Point"}
}