{
  "type": "Feature",
  "properties": {
    "date:inception_lower":"1980-01-01",
    "date:inception_upper":"1980-01-31",
    "iso:country":"GB",
    "wof:name":"PE12 9JA",
    "wof:placetype":"postalcode"
},
  "geometry": {"coordinates":[0.121681,52.784923],"type":"Point"}
}