{
  "type": "Feature",
  "properties": {
    "iso:country":"GB",
    "wof:name":"CV7 7AJ",
    "wof:placetype":"postalcode"
},
  "geometry": {"coordinates":[-1.66349141963269,52.38968268159299],"type":"Point"}
}