{
  "type": "Feature",
  "properties": {
    "iso:country":"GB",
    "wof:name":"LS7 3LF",
    "wof:placetype":"postalcode"
},
  "geometry": {"coordinates":[-1.53886678064439,53.82234748556488],"type":"Point"}
}