{
  "type": "Feature",
  "properties": {
    "date:inception_lower":"1980-01-01",
    "date:inception_upper":"1980-01-31",
    "iso:country":"GB",
    "wof:name":"G67 1NX",
    "wof:placetype":"postalcode"
},
  "geometry": {"coordinates":[-4.005318,55.939607],"type":"Point"}
}