{
  "type": "Feature",
  "properties": {
    "iso:country":"GB",
    "wof:name":"G67 1NX",
    "wof:placetype":"postalcode"
},
  "geometry": {"coordinates":[-4.00531782468814,55.93960708465121],"type":"Point"}
}