{
  "type": "Feature",
  "properties": {
    "iso:country":"GB",
    "wof:name":"PE13 5BL",
    "wof:placetype":"postalcode"
},
  "geometry": {"coordinates":[0.12799809826284,52.67360658784757],"type":"Point"}
}