{
  "type": "Feature",
  "properties": {
    "date:inception_lower": "1980-01-01",
    "date:inception_upper": "1980-01-01",
    "iso:country": "GB",
    "wof:name": "PE13 5BL",
    "wof:placetype": "postalcode"
  },
  "geometry": {"coordinates":[0.128014,52.673626],"type":"Point"}
}
