{
  "type": "Feature",
  "properties": {
    "iso:country": "GB",
    "wof:name": "PE13 5BL",
    "wof:placetype": "postalcode"
  },
  "geometry": {"coordinates":[0.128014,52.673626],"type":"Point"}
}
