{
  "type": "Feature",
  "properties": {
    "iso:country":"GB",
    "wof:name":"BH21 1SE",
    "wof:placetype":"postalcode"
},
  "geometry": {"coordinates":[-1.97628574899373,50.78753521788298],"type":"Point"}
}