{
  "type": "Feature",
  "properties": {
    "iso:country": "GB",
    "wof:name": "LS28 7QH",
    "wof:placetype": "postalcode"
  },
  "geometry": {"coordinates":[-1.662571,53.800684],"type":"Point"}
}
