{
  "type": "Feature",
  "properties": {
    "date:inception_lower": "2008-02-01",
    "date:inception_upper": "2008-02-01",
    "iso:country": "GB",
    "wof:name": "SN10 2JR",
    "wof:placetype": "postalcode"
  },
  "geometry": {"coordinates":[-1.980446,51.361566],"type":"Point"}
}
