{
  "type": "Feature",
  "properties": {
    "iso:country":"GB",
    "wof:name":"CH3 6HW",
    "wof:placetype":"postalcode"
},
  "geometry": {"coordinates":[-2.86800720372931,53.12553004769438],"type":"Point"}
}