{
  "type": "Feature",
  "properties": {
    "date:inception_lower":"1980-01-01",
    "date:inception_upper":"1980-01-31",
    "iso:country":"GB",
    "wof:name":"NG15 7SP",
    "wof:placetype":"postalcode"
},
  "geometry": {"coordinates":[-1.199776,53.035181],"type":"Point"}
}