{
  "type": "Feature",
  "properties": {
    "iso:country":"GB",
    "wof:name":"DH4 5DG",
    "wof:placetype":"postalcode"
},
  "geometry": {"coordinates":[-1.48030569892487,54.84251385438112],"type":"Point"}
}