{
  "type": "Feature",
  "properties": {
    "iso:country": "GB",
    "wof:name": "DH4 5DG",
    "wof:placetype": "postalcode"
  },
  "geometry": {"coordinates":[-1.480306,54.842514],"type":"Point"}
}
