{
  "type": "Feature",
  "properties": {
    "iso:country": "GB",
    "wof:name": "CW5 8LJ",
    "wof:placetype": "postalcode"
  },
  "geometry": {"coordinates":[-2.552031,53.079053],"type":"Point"}
}
