{
  "type": "Feature",
  "properties": {
    "iso:country":"GB",
    "wof:name":"CW5 8LJ",
    "wof:placetype":"postalcode"
},
  "geometry": {"coordinates":[-2.55203149740844,53.07905348566975],"type":"Point"}
}