{
  "type": "Feature",
  "properties": {
    "date:inception_lower":"1980-01-01",
    "date:inception_upper":"1980-01-31",
    "iso:country":"GB",
    "wof:name":"CW5 8LJ",
    "wof:placetype":"postalcode"
},
  "geometry": {"coordinates":[-2.552031,53.079053],"type":"Point"}
}