{
  "type": "Feature",
  "properties": {
    "iso:country":"GB",
    "wof:name":"MK45 2YU",
    "wof:placetype":"postalcode"
},
  "geometry": {"coordinates":[-0.52984507043759,52.03915248512372],"type":"Point"}
}