{
  "type": "Feature",
  "properties": {
    "date:inception_lower": "2005-02-01",
    "date:inception_upper": "2005-02-01",
    "iso:country": "GB",
    "wof:name": "DN21 3HB",
    "wof:placetype": "postalcode"
  },
  "geometry": {"coordinates":[-0.662907,53.504058],"type":"Point"}
}
