{
  "type": "Feature",
  "properties": {
    "date:inception_lower": "1980-01-01",
    "date:inception_upper": "1980-01-01",
    "iso:country": "GB",
    "wof:name": "UB8 2BX",
    "wof:placetype": "postalcode"
  },
  "geometry": {"coordinates":[-0.474894,51.542603],"type":"Point"}
}
