{
  "type": "Feature",
  "properties": {
    "iso:country":"GB",
    "wof:name":"DT1 3WQ",
    "wof:placetype":"postalcode"
},
  "geometry": {"coordinates":[-2.46193374871575,50.71131719785243],"type":"Point"}
}