{
  "type": "Feature",
  "properties": {
    "date:inception_lower": "1980-01-01",
    "date:inception_upper": "1980-01-01",
    "iso:country": "GB",
    "wof:name": "BD16 4PN",
    "wof:placetype": "postalcode"
  },
  "geometry": {"coordinates":[-1.825301,53.848029],"type":"Point"}
}
