{
  "type": "Feature",
  "properties": {
    "iso:country":"GB",
    "wof:name":"BD16 4PN",
    "wof:placetype":"postalcode"
},
  "geometry": {"coordinates":[-1.82530144065162,53.84802939867676],"type":"Point"}
}