{
  "type": "Feature",
  "properties": {
    "iso:country":"GB",
    "wof:name":"NR10 5AA",
    "wof:placetype":"postalcode"
},
  "geometry": {"coordinates":[1.29202674340455,52.77066978993023],"type":"Point"}
}