{
  "type": "Feature",
  "properties": {
    "iso:country": "GB",
    "wof:name": "BH20 6EE",
    "wof:placetype": "postalcode"
  },
  "geometry": {"coordinates":[-2.230904,50.676636],"type":"Point"}
}
