{
  "type": "Feature",
  "properties": {
    "date:inception_lower":"1998-06-01",
    "date:inception_upper":"1998-06-30",
    "iso:country":"GB",
    "wof:name":"L9 8HP",
    "wof:placetype":"postalcode"
},
  "geometry": {"coordinates":[-2.962576,53.468482],"type":"Point"}
}