{
  "type": "Feature",
  "properties": {
    "iso:country":"GB",
    "wof:name":"DE56 0JN",
    "wof:placetype":"postalcode"
},
  "geometry": {"coordinates":[-1.43489572475316,53.00633473756729],"type":"Point"}
}