{
  "type": "Feature",
  "properties": {
    "date:inception_lower": "1992-08-01",
    "date:inception_upper": "1992-08-01",
    "iso:country": "GB",
    "wof:name": "DE56 0JN",
    "wof:placetype": "postalcode"
  },
  "geometry": {"coordinates":[-1.434896,53.006335],"type":"Point"}
}
