{
  "type": "Feature",
  "properties": {
    "iso:country":"GB",
    "wof:name":"DD11 3RH",
    "wof:placetype":"postalcode"
},
  "geometry": {"coordinates":[-2.6336661647187,56.58057263563079],"type":"Point"}
}