{
  "type": "Feature",
  "properties": {
    "date:inception_lower": "1991-01-01",
    "date:inception_upper": "1991-01-01",
    "iso:country": "GB",
    "wof:name": "SL1 3XY",
    "wof:placetype": "postalcode"
  },
  "geometry": {"coordinates":[-0.602536,51.525508],"type":"Point"}
}
