{
  "type": "Feature",
  "properties": {
    "iso:country":"GB",
    "wof:name":"NN15 5QG",
    "wof:placetype":"postalcode"
},
  "geometry": {"coordinates":[-0.68890234517949,52.3616923763551],"type":"Point"}
}