{
  "type": "Feature",
  "properties": {
    "iso:country":"GB",
    "wof:name":"GU21 6HJ",
    "wof:placetype":"postalcode"
},
  "geometry": {"coordinates":[-0.55736426000669,51.3206667706533],"type":"Point"}
}