{
  "type": "Feature",
  "properties": {
    "iso:country":"GB",
    "wof:name":"DA2 6HP",
    "wof:placetype":"postalcode"
},
  "geometry": {"coordinates":[0.2468253341796,51.44008974868889],"type":"Point"}
}