{
  "type": "Feature",
  "properties": {
    "iso:country": "GB",
    "wof:name": "DA2 6HP",
    "wof:placetype": "postalcode"
  },
  "geometry": {"coordinates":[0.246825,51.44009],"type":"Point"}
}
