{
  "type": "Feature",
  "properties": {
    "iso:country":"GB",
    "wof:name":"B47 6JG",
    "wof:placetype":"postalcode"
},
  "geometry": {"coordinates":[-1.88421646918831,52.38191444646117],"type":"Point"}
}