{
  "type": "Feature",
  "properties": {
    "iso:country":"GB",
    "wof:name":"S20 4HD",
    "wof:placetype":"postalcode"
},
  "geometry": {"coordinates":[-1.34983411676796,53.3229360404964],"type":"Point"}
}