{
  "type": "Feature",
  "properties": {
    "iso:country":"GB",
    "wof:name":"WR2 4RQ",
    "wof:placetype":"postalcode"
},
  "geometry": {"coordinates":[-2.27326833702699,52.16167070189328],"type":"Point"}
}