{
  "type": "Feature",
  "properties": {
    "iso:country":"GB",
    "wof:name":"KT5 8TD",
    "wof:placetype":"postalcode"
},
  "geometry": {"coordinates":[-0.295291501241,51.38974238612905],"type":"Point"}
}