{
  "type": "Feature",
  "properties": {
    "iso:country": "GB",
    "wof:name": "KT5 8TD",
    "wof:placetype": "postalcode"
  },
  "geometry": {"coordinates":[-0.295291,51.389742],"type":"Point"}
}
