{
  "type": "Feature",
  "properties": {
    "iso:country": "GB",
    "wof:name": "GL51 3QY",
    "wof:placetype": "postalcode"
  },
  "geometry": {"coordinates":[-2.108855,51.888163],"type":"Point"}
}
