{
  "type": "Feature",
  "properties": {
    "iso:country":"GB",
    "wof:name":"FY4 3QA",
    "wof:placetype":"postalcode"
},
  "geometry": {"coordinates":[-3.03297115885741,53.78410579305663],"type":"Point"}
}