{
  "type": "Feature",
  "properties": {
    "iso:country": "GB",
    "wof:name": "MK45 4DU",
    "wof:placetype": "postalcode"
  },
  "geometry": {"coordinates":[-0.428238,52.007218],"type":"Point"}
}
