{
  "type": "Feature",
  "properties": {
    "iso:country":"GB",
    "wof:name":"HP3 0HE",
    "wof:placetype":"postalcode"
},
  "geometry": {"coordinates":[-0.53129920546507,51.72674040366343],"type":"Point"}
}