{
  "type": "Feature",
  "properties": {
    "date:inception_lower": "1980-01-01",
    "date:inception_upper": "1980-01-01",
    "iso:country": "GB",
    "wof:name": "WF15 7DA",
    "wof:placetype": "postalcode"
  },
  "geometry": {"coordinates":[-1.694684,53.704194],"type":"Point"}
}
