{
  "type": "Feature",
  "properties": {
    "iso:country":"GB",
    "wof:name":"FK5 3HJ",
    "wof:placetype":"postalcode"
},
  "geometry": {"coordinates":[-3.82320142433817,56.02376451684658],"type":"Point"}
}