{
  "type": "Feature",
  "properties": {
    "date:inception_lower": "2013-03-01",
    "date:inception_upper": "2013-03-01",
    "iso:country": "GB",
    "wof:name": "OX4 2SY",
    "wof:placetype": "postalcode"
  },
  "geometry": {"coordinates":[-1.223609,51.741525],"type":"Point"}
}
