{
  "type": "Feature",
  "properties": {
    "iso:country":"GB",
    "wof:name":"EX16 6LZ",
    "wof:placetype":"postalcode"
},
  "geometry": {"coordinates":[-3.4868036151291,50.90258547731912],"type":"Point"}
}