{
  "type": "Feature",
  "properties": {
    "iso:country":"GB",
    "wof:name":"SK16 5RP",
    "wof:placetype":"postalcode"
},
  "geometry": {"coordinates":[-2.08486233869125,53.46879830110709],"type":"Point"}
}