{
  "type": "Feature",
  "properties": {
    "iso:country": "GB",
    "wof:name": "PL30 4LR",
    "wof:placetype": "postalcode"
  },
  "geometry": {"coordinates":[-4.686115,50.561641],"type":"Point"}
}
