{
  "type": "Feature",
  "properties": {
    "iso:country":"GB",
    "wof:name":"PL30 4LR",
    "wof:placetype":"postalcode"
},
  "geometry": {"coordinates":[-4.6861153638191,50.56164061070024],"type":"Point"}
}