{
  "type": "Feature",
  "properties": {
    "iso:country": "GB",
    "wof:name": "RM20 3JQ",
    "wof:placetype": "postalcode"
  },
  "geometry": {"coordinates":[0.267517,51.47695],"type":"Point"}
}
