{
  "type": "Feature",
  "properties": {
    "date:inception_lower":"2004-04-01",
    "date:inception_upper":"2004-04-30",
    "iso:country":"GB",
    "wof:name":"SA33 4AW",
    "wof:placetype":"postalcode"
},
  "geometry": {"coordinates":[-4.511473,51.820507],"type":"Point"}
}