{
  "type": "Feature",
  "properties": {
    "iso:country":"GB",
    "wof:name":"SA33 4AW",
    "wof:placetype":"postalcode"
},
  "geometry": {"coordinates":[-4.51147300759477,51.82050657740203],"type":"Point"}
}