{
  "type": "Feature",
  "properties": {
    "date:inception_lower":"2012-05-01",
    "date:inception_upper":"2012-05-31",
    "iso:country":"GB",
    "wof:name":"TS6 9TN",
    "wof:placetype":"postalcode"
},
  "geometry": {"coordinates":[-1.164569,54.571631],"type":"Point"}
}