{
  "type": "Feature",
  "properties": {
    "iso:country":"GB",
    "wof:name":"TS6 9TN",
    "wof:placetype":"postalcode"
},
  "geometry": {"coordinates":[-1.16456897367305,54.57163074072226],"type":"Point"}
}