{
  "type": "Feature",
  "properties": {
    "iso:country":"GB",
    "wof:name":"SK9 7WF",
    "wof:placetype":"postalcode"
},
  "geometry": {"coordinates":[-2.28939745459103,53.29305567643224],"type":"Point"}
}