{
  "type": "Feature",
  "properties": {
    "date:inception_lower": "1997-06-01",
    "date:inception_upper": "1997-06-01",
    "iso:country": "GB",
    "wof:name": "SK9 7WF",
    "wof:placetype": "postalcode"
  },
  "geometry": {"coordinates":[-2.289397,53.293056],"type":"Point"}
}
