{
  "type": "Feature",
  "properties": {
    "date:inception_lower":"1984-10-01",
    "date:inception_upper":"1984-10-31",
    "iso:country":"GB",
    "wof:name":"GU32 1HP",
    "wof:placetype":"postalcode"
},
  "geometry": {"coordinates":[-1.028747,50.980951],"type":"Point"}
}