{
  "type": "Feature",
  "properties": {
    "iso:country":"GB",
    "wof:name":"GU32 1HP",
    "wof:placetype":"postalcode"
},
  "geometry": {"coordinates":[-1.02861717657248,50.98108247069281],"type":"Point"}
}