{
  "type": "Feature",
  "properties": {
    "iso:country":"GB",
    "wof:name":"BN27 1PD",
    "wof:placetype":"postalcode"
},
  "geometry": {"coordinates":[0.26603426083835,50.87798675928536],"type":"Point"}
}