{
  "type": "Feature",
  "properties": {
    "date:inception_lower": "1980-01-01",
    "date:inception_upper": "1980-01-01",
    "iso:country": "GB",
    "wof:name": "PR6 9HR",
    "wof:placetype": "postalcode"
  },
  "geometry": {"coordinates":[-2.589562,53.614658],"type":"Point"}
}
