{
  "type": "Feature",
  "properties": {
    "iso:country":"GB",
    "wof:name":"BS10 7QQ",
    "wof:placetype":"postalcode"
},
  "geometry": {"coordinates":[-2.63070831196836,51.50797971670015],"type":"Point"}
}