{
  "type": "Feature",
  "properties": {
    "date:inception_lower":"1980-01-01",
    "date:inception_upper":"1980-01-31",
    "iso:country":"GB",
    "wof:name":"BS10 7QQ",
    "wof:placetype":"postalcode"
},
  "geometry": {"coordinates":[-2.630708,51.50798],"type":"Point"}
}