{
  "type": "Feature",
  "properties": {
    "iso:country": "GB",
    "wof:name": "DE24 0TG",
    "wof:placetype": "postalcode"
  },
  "geometry": {"coordinates":[-1.411229,52.888019],"type":"Point"}
}
