{
  "type": "Feature",
  "properties": {
    "date:inception_lower":"1980-01-01",
    "date:inception_upper":"1980-01-31",
    "iso:country":"GB",
    "wof:name":"DE15 9PU",
    "wof:placetype":"postalcode"
},
  "geometry": {"coordinates":[-1.623332,52.783703],"type":"Point"}
}