{
  "type": "Feature",
  "properties": {
    "iso:country": "GB",
    "wof:name": "DE15 9PU",
    "wof:placetype": "postalcode"
  },
  "geometry": {"coordinates":[-1.623332,52.783703],"type":"Point"}
}
