{
  "type": "Feature",
  "properties": {
    "iso:country":"GB",
    "wof:name":"LL31 9UR",
    "wof:placetype":"postalcode"
},
  "geometry": {"coordinates":[-3.82696580417747,53.29337901898982],"type":"Point"}
}