{
  "type": "Feature",
  "properties": {
    "date:inception_lower": "1980-01-01",
    "date:inception_upper": "1980-01-01",
    "iso:country": "GB",
    "wof:name": "LL31 9UR",
    "wof:placetype": "postalcode"
  },
  "geometry": {"coordinates":[-3.826966,53.293379],"type":"Point"}
}
