{
  "type": "Feature",
  "properties": {
    "iso:country":"GB",
    "wof:name":"SA73 2AJ",
    "wof:placetype":"postalcode"
},
  "geometry": {"coordinates":[-5.03934228086847,51.71339453832352],"type":"Point"}
}