{
  "type": "Feature",
  "properties": {
    "iso:country":"GB",
    "wof:name":"L37 1YX",
    "wof:placetype":"postalcode"
},
  "geometry": {"coordinates":[-3.08057930028806,53.56574808145452],"type":"Point"}
}