{
  "type": "Feature",
  "properties": {
    "iso:country": "GB",
    "wof:name": "PE7 1RE",
    "wof:placetype": "postalcode"
  },
  "geometry": {"coordinates":[-0.130252,52.56116],"type":"Point"}
}
