{
  "type": "Feature",
  "properties": {
    "iso:country": "GB",
    "wof:name": "NG7 3PN",
    "wof:placetype": "postalcode"
  },
  "geometry": {"coordinates":[-1.171485,52.956449],"type":"Point"}
}
