{
  "type": "Feature",
  "properties": {
    "iso:country":"GB",
    "wof:name":"SA32 7JJ",
    "wof:placetype":"postalcode"
},
  "geometry": {"coordinates":[-4.20634466855746,51.92158173595957],"type":"Point"}
}