{
  "type": "Feature",
  "properties": {
    "iso:country":"GB",
    "wof:name":"DT7 3XG",
    "wof:placetype":"postalcode"
},
  "geometry": {"coordinates":[-2.9618497424756,50.73940593751809],"type":"Point"}
}