{
  "type": "Feature",
  "properties": {
    "iso:country":"GB",
    "wof:name":"KT1 2SA",
    "wof:placetype":"postalcode"
},
  "geometry": {"coordinates":[-0.30142699112721,51.40376085751084],"type":"Point"}
}