{
  "type": "Feature",
  "properties": {
    "iso:country":"GB",
    "wof:name":"S80 3QH",
    "wof:placetype":"postalcode"
},
  "geometry": {"coordinates":[-1.14427931835884,53.30174666580316],"type":"Point"}
}