{
  "type": "Feature",
  "properties": {
    "iso:country":"GB",
    "wof:name":"S1 4JL",
    "wof:placetype":"postalcode"
},
  "geometry": {"coordinates":[-1.47993458663985,53.37982527844458],"type":"Point"}
}