{
  "type": "Feature",
  "properties": {
    "iso:country": "GB",
    "wof:name": "DH3 3PS",
    "wof:placetype": "postalcode"
  },
  "geometry": {"coordinates":[-1.570283,54.853766],"type":"Point"}
}
