{
  "type": "Feature",
  "properties": {
    "iso:country":"GB",
    "wof:name":"DH3 3PS",
    "wof:placetype":"postalcode"
},
  "geometry": {"coordinates":[-1.57028274439154,54.85376598796856],"type":"Point"}
}