{
  "type": "Feature",
  "properties": {
    "iso:country":"GB",
    "wof:name":"ME20 6TZ",
    "wof:placetype":"postalcode"
},
  "geometry": {"coordinates":[0.43901949697077,51.31119333169494],"type":"Point"}
}