{
  "type": "Feature",
  "properties": {
    "iso:country":"GB",
    "wof:name":"AL6 9QF",
    "wof:placetype":"postalcode"
},
  "geometry": {"coordinates":[-0.22069332566821,51.82825714596932],"type":"Point"}
}