{
  "type": "Feature",
  "properties": {
    "iso:country":"GB",
    "wof:name":"DN14 0RN",
    "wof:placetype":"postalcode"
},
  "geometry": {"coordinates":[-1.18888261423088,53.72087540520406],"type":"Point"}
}