{
  "type": "Feature",
  "properties": {
    "iso:country": "GB",
    "wof:name": "DN14 0RN",
    "wof:placetype": "postalcode"
  },
  "geometry": {"coordinates":[-1.188883,53.720875],"type":"Point"}
}
