{
  "type": "Feature",
  "properties": {
    "date:inception_lower":"2000-10-01",
    "date:inception_upper":"2000-10-31",
    "iso:country":"GB",
    "wof:name":"GL52 8LE",
    "wof:placetype":"postalcode"
},
  "geometry": {"coordinates":[-2.054685,51.946003],"type":"Point"}
}