{
  "type": "Feature",
  "properties": {
    "date:inception_lower":"2012-12-01",
    "date:inception_upper":"2012-12-31",
    "iso:country":"GB",
    "wof:name":"PA16 0FT",
    "wof:placetype":"postalcode"
},
  "geometry": {"coordinates":[-4.863358,55.904928],"type":"Point"}
}