{
  "type": "Feature",
  "properties": {
    "iso:country":"GB",
    "wof:name":"LL49 9GB",
    "wof:placetype":"postalcode"
},
  "geometry": {"coordinates":[-4.14424998976514,52.93057701929828],"type":"Point"}
}