{
  "type": "Feature",
  "properties": {
    "iso:country": "GB",
    "wof:name": "LL49 9GB",
    "wof:placetype": "postalcode"
  },
  "geometry": {"coordinates":[-4.143937,52.930574],"type":"Point"}
}
