{
  "type": "Feature",
  "properties": {
    "date:inception_lower": "1993-01-01",
    "date:inception_upper": "1993-01-01",
    "iso:country": "GB",
    "wof:name": "LL49 9GB",
    "wof:placetype": "postalcode"
  },
  "geometry": {"coordinates":[-4.143937,52.930574],"type":"Point"}
}
