{
  "type": "Feature",
  "properties": {
    "iso:country":"GB",
    "wof:name":"NP26 4BN",
    "wof:placetype":"postalcode"
},
  "geometry": {"coordinates":[-2.74997764909894,51.5881836188141],"type":"Point"}
}