{
  "type": "Feature",
  "properties": {
    "iso:country": "GB",
    "wof:name": "ST5 5AX",
    "wof:placetype": "postalcode"
  },
  "geometry": {"coordinates":[-2.281086,53.002552],"type":"Point"}
}
