{
  "type": "Feature",
  "properties": {
    "iso:country":"GB",
    "wof:name":"ST5 5AX",
    "wof:placetype":"postalcode"
},
  "geometry": {"coordinates":[-2.28108643090179,53.00255206064559],"type":"Point"}
}