{
  "type": "Feature",
  "properties": {
    "date:inception_lower": "1980-01-01",
    "date:inception_upper": "1980-01-01",
    "iso:country": "GB",
    "wof:name": "ST5 5AX",
    "wof:placetype": "postalcode"
  },
  "geometry": {"coordinates":[-2.281086,53.002552],"type":"Point"}
}
