{
  "type": "Feature",
  "properties": {
    "iso:country":"GB",
    "wof:name":"TN30 7AY",
    "wof:placetype":"postalcode"
},
  "geometry": {"coordinates":[0.69908179515452,51.07017343771486],"type":"Point"}
}