{
  "type": "Feature",
  "properties": {
    "iso:country":"GB",
    "wof:name":"KT22 0DT",
    "wof:placetype":"postalcode"
},
  "geometry": {"coordinates":[-0.32688417425666,51.32624290631577],"type":"Point"}
}