{
  "type": "Feature",
  "properties": {
    "iso:country": "GB",
    "wof:name": "LL49 9AN",
    "wof:placetype": "postalcode"
  },
  "geometry": {"coordinates":[-4.132799,52.926468],"type":"Point"}
}
