{
  "type": "Feature",
  "properties": {
    "iso:country":"GB",
    "wof:name":"LL49 9AN",
    "wof:placetype":"postalcode"
},
  "geometry": {"coordinates":[-4.13279908317587,52.92646753857689],"type":"Point"}
}