{
  "type": "Feature",
  "properties": {
    "date:inception_lower":"1997-06-01",
    "date:inception_upper":"1997-06-30",
    "iso:country":"GB",
    "wof:name":"HR9 5GL",
    "wof:placetype":"postalcode"
},
  "geometry": {"coordinates":[-2.575559,51.907529],"type":"Point"}
}