{
  "type": "Feature",
  "properties": {
    "iso:country":"GB",
    "wof:name":"SW11 5DA",
    "wof:placetype":"postalcode"
},
  "geometry": {"coordinates":[-0.15549908599737,51.47262333223189],"type":"Point"}
}