{
  "type": "Feature",
  "properties": {
    "iso:country": "GB",
    "wof:name": "DE12 8ET",
    "wof:placetype": "postalcode"
  },
  "geometry": {"coordinates":[-1.638202,52.734244],"type":"Point"}
}
