{
  "type": "Feature",
  "properties": {
    "iso:country":"GB",
    "wof:name":"M35 0AY",
    "wof:placetype":"postalcode"
},
  "geometry": {"coordinates":[-2.16676482343026,53.50693970682906],"type":"Point"}
}