{
  "type": "Feature",
  "properties": {
    "iso:country":"GB",
    "wof:name":"LS1 5RL",
    "wof:placetype":"postalcode"
},
  "geometry": {"coordinates":[-1.5482887975598,53.79938296967688],"type":"Point"}
}