{
  "type": "Feature",
  "properties": {
    "date:inception_lower":"1980-01-01",
    "date:inception_upper":"1980-01-31",
    "iso:country":"GB",
    "wof:name":"CF44 6HY",
    "wof:placetype":"postalcode"
},
  "geometry": {"coordinates":[-3.446586,51.685547],"type":"Point"}
}