{
  "type": "Feature",
  "properties": {
    "iso:country":"GB",
    "wof:name":"DD3 9RD",
    "wof:placetype":"postalcode"
},
  "geometry": {"coordinates":[-3.0043920161427,56.49846554998035],"type":"Point"}
}