{
  "type": "Feature",
  "properties": {
    "iso:country": "GB",
    "wof:name": "DD3 9RD",
    "wof:placetype": "postalcode"
  },
  "geometry": {"coordinates":[-3.004392,56.498466],"type":"Point"}
}
