{
  "type": "Feature",
  "properties": {
    "iso:country":"GB",
    "wof:name":"AB12 3UP",
    "wof:placetype":"postalcode"
},
  "geometry": {"coordinates":[-2.08869469251278,57.09840858657902],"type":"Point"}
}