{
  "type": "Feature",
  "properties": {
    "iso:country": "GB",
    "wof:name": "AB12 3UP",
    "wof:placetype": "postalcode"
  },
  "geometry": {"coordinates":[-2.088695,57.098409],"type":"Point"}
}
