{
  "type": "Feature",
  "properties": {
    "iso:country":"GB",
    "wof:name":"OL11 5YJ",
    "wof:placetype":"postalcode"
},
  "geometry": {"coordinates":[-2.20466498793568,53.6183719627015],"type":"Point"}
}