{
  "type": "Feature",
  "properties": {
    "iso:country": "GB",
    "wof:name": "AL7 4LP",
    "wof:placetype": "postalcode"
  },
  "geometry": {"coordinates":[-0.187604,51.783817],"type":"Point"}
}
