{
  "type": "Feature",
  "properties": {
    "date:inception_lower": "2023-12-01",
    "date:inception_upper": "2023-12-01",
    "iso:country": "GB",
    "wof:name": "OL2 7FB",
    "wof:placetype": "postalcode"
  },
  "geometry": {"coordinates":[-2.110415,53.575557],"type":"Point"}
}
