{
  "type": "Feature",
  "properties": {
    "iso:country":"GB",
    "wof:name":"KA23 9QF",
    "wof:placetype":"postalcode"
},
  "geometry": {"coordinates":[-4.87909884415585,55.71791599095393],"type":"Point"}
}