{
  "type": "Feature",
  "properties": {
    "date:inception_lower": "1980-01-01",
    "date:inception_upper": "1980-01-01",
    "iso:country": "GB",
    "wof:name": "KA23 9QF",
    "wof:placetype": "postalcode"
  },
  "geometry": {"coordinates":[-4.87809,55.717711],"type":"Point"}
}
