{
  "type": "Feature",
  "properties": {
    "iso:country": "GB",
    "wof:name": "BA1 2JE",
    "wof:placetype": "postalcode"
  },
  "geometry": {"coordinates":[-2.362564,51.383098],"type":"Point"}
}
