{
  "type": "Feature",
  "properties": {
    "iso:country":"GB",
    "wof:name":"BA1 2JE",
    "wof:placetype":"postalcode"
},
  "geometry": {"coordinates":[-2.36256381239909,51.38309847470494],"type":"Point"}
}