{
  "type": "Feature",
  "properties": {
    "iso:country":"GB",
    "wof:name":"HP21 7NF",
    "wof:placetype":"postalcode"
},
  "geometry": {"coordinates":[-0.797111730417,51.80392364852454],"type":"Point"}
}