{
  "type": "Feature",
  "properties": {
    "iso:country":"GB",
    "wof:name":"SG8 6FB",
    "wof:placetype":"postalcode"
},
  "geometry": {"coordinates":[0.01135573169554,52.07721298842871],"type":"Point"}
}