{
  "type": "Feature",
  "properties": {
    "date:inception_lower":"2008-10-01",
    "date:inception_upper":"2008-10-31",
    "iso:country":"GB",
    "wof:name":"SG8 6FB",
    "wof:placetype":"postalcode"
},
  "geometry": {"coordinates":[0.011356,52.077213],"type":"Point"}
}