{
  "type": "Feature",
  "properties": {
    "date:inception_lower": "1999-12-01",
    "date:inception_upper": "1999-12-01",
    "iso:country": "GB",
    "wof:name": "HP17 8UZ",
    "wof:placetype": "postalcode"
  },
  "geometry": {"coordinates":[-0.885077,51.79267],"type":"Point"}
}
