{
  "type": "Feature",
  "properties": {
    "iso:country":"GB",
    "wof:name":"E7 8PN",
    "wof:placetype":"postalcode"
},
  "geometry": {"coordinates":[0.04147886335434,51.53890879191301],"type":"Point"}
}