{
  "type": "Feature",
  "properties": {
    "date:inception_lower": "1980-01-01",
    "date:inception_upper": "1980-01-01",
    "iso:country": "GB",
    "wof:name": "L31 1BW",
    "wof:placetype": "postalcode"
  },
  "geometry": {"coordinates":[-2.911667,53.487884],"type":"Point"}
}
