{
  "type": "Feature",
  "properties": {
    "iso:country":"GB",
    "wof:name":"L31 1BW",
    "wof:placetype":"postalcode"
},
  "geometry": {"coordinates":[-2.91166685723706,53.48788377466382],"type":"Point"}
}