{
  "type": "Feature",
  "properties": {
    "iso:country": "GB",
    "wof:name": "L31 1BW",
    "wof:placetype": "postalcode"
  },
  "geometry": {"coordinates":[-2.911667,53.487884],"type":"Point"}
}
