{
  "type": "Feature",
  "properties": {
    "date:inception_lower": "1980-01-01",
    "date:inception_upper": "1980-01-01",
    "iso:country": "GB",
    "wof:name": "SW16 1NY",
    "wof:placetype": "postalcode"
  },
  "geometry": {"coordinates":[-0.143738,51.427834],"type":"Point"}
}
