{
  "type": "Feature",
  "properties": {
    "iso:country":"GB",
    "wof:name":"S25 1YU",
    "wof:placetype":"postalcode"
},
  "geometry": {"coordinates":[-1.21558172284069,53.38712771119392],"type":"Point"}
}