{
  "type": "Feature",
  "properties": {
    "iso:country": "GB",
    "wof:name": "S25 1YU",
    "wof:placetype": "postalcode"
  },
  "geometry": {"coordinates":[-1.215582,53.387128],"type":"Point"}
}
