{
  "type": "Feature",
  "properties": {
    "iso:country": "GB",
    "wof:name": "HD9 6NG",
    "wof:placetype": "postalcode"
  },
  "geometry": {"coordinates":[-1.791733,53.603833],"type":"Point"}
}
