{
  "type": "Feature",
  "properties": {
    "iso:country": "GB",
    "wof:name": "G40 3DP",
    "wof:placetype": "postalcode"
  },
  "geometry": {"coordinates":[-4.221652,55.85073],"type":"Point"}
}
