{
  "type": "Feature",
  "properties": {
    "iso:country":"GB",
    "wof:name":"B98 0AX",
    "wof:placetype":"postalcode"
},
  "geometry": {"coordinates":[-1.8853221379148,52.29513332473071],"type":"Point"}
}