{
  "type": "Feature",
  "properties": {
    "iso:country":"GB",
    "wof:name":"TR27 6NE",
    "wof:placetype":"postalcode"
},
  "geometry": {"coordinates":[-5.45482127030112,50.16710730479075],"type":"Point"}
}