{
  "type": "Feature",
  "properties": {
    "iso:country":"GB",
    "wof:name":"CV32 5UP",
    "wof:placetype":"postalcode"
},
  "geometry": {"coordinates":[-1.53010590229185,52.29751856164201],"type":"Point"}
}