{
  "type": "Feature",
  "properties": {
    "iso:country": "GB",
    "wof:name": "CV32 5UP",
    "wof:placetype": "postalcode"
  },
  "geometry": {"coordinates":[-1.53011,52.297534],"type":"Point"}
}
