{
  "type": "Feature",
  "properties": {
    "iso:country":"GB",
    "wof:name":"MK9 3BA",
    "wof:placetype":"postalcode"
},
  "geometry": {"coordinates":[-0.75310234902048,52.04399203989191],"type":"Point"}
}