{
  "type": "Feature",
  "properties": {
    "date:inception_lower": "1999-06-01",
    "date:inception_upper": "1999-06-01",
    "iso:country": "GB",
    "wof:name": "CH66 3SQ",
    "wof:placetype": "postalcode"
  },
  "geometry": {"coordinates":[-2.942899,53.283341],"type":"Point"}
}
