{
  "type": "Feature",
  "properties": {
    "iso:country":"GB",
    "wof:name":"CH41 8JT",
    "wof:placetype":"postalcode"
},
  "geometry": {"coordinates":[-3.05281966825821,53.40056448593191],"type":"Point"}
}