{
  "type": "Feature",
  "properties": {
    "date:inception_lower": "1999-06-01",
    "date:inception_upper": "1999-06-01",
    "iso:country": "GB",
    "wof:name": "CH41 8JT",
    "wof:placetype": "postalcode"
  },
  "geometry": {"coordinates":[-3.05282,53.400564],"type":"Point"}
}
