{
  "type": "Feature",
  "properties": {
    "iso:country": "GB",
    "wof:name": "CH41 8JT",
    "wof:placetype": "postalcode"
  },
  "geometry": {"coordinates":[-3.05282,53.400564],"type":"Point"}
}
