{
  "type": "Feature",
  "properties": {
    "iso:country": "GB",
    "wof:name": "WD6 2AA",
    "wof:placetype": "postalcode"
  },
  "geometry": {"coordinates":[-0.261386,51.650508],"type":"Point"}
}
