{
  "type": "Feature",
  "properties": {
    "date:inception_lower":"1980-01-01",
    "date:inception_upper":"1980-01-31",
    "iso:country":"GB",
    "wof:name":"WD6 2AA",
    "wof:placetype":"postalcode"
},
  "geometry": {"coordinates":[-0.261386,51.650508],"type":"Point"}
}