{
  "type": "Feature",
  "properties": {
    "iso:country":"GB",
    "wof:name":"SK6 5DL",
    "wof:placetype":"postalcode"
},
  "geometry": {"coordinates":[-2.04165539865409,53.40435573059908],"type":"Point"}
}