{
  "type": "Feature",
  "properties": {
    "date:inception_lower": "1982-03-01",
    "date:inception_upper": "1982-03-01",
    "iso:country": "GB",
    "wof:name": "SK6 5DL",
    "wof:placetype": "postalcode"
  },
  "geometry": {"coordinates":[-2.041655,53.404356],"type":"Point"}
}
