{
  "type": "Feature",
  "properties": {
    "iso:country":"GB",
    "wof:name":"RM11 3JT",
    "wof:placetype":"postalcode"
},
  "geometry": {"coordinates":[0.22966982184146,51.56960159964157],"type":"Point"}
}