{
  "type": "Feature",
  "properties": {
    "date:inception_lower": "1980-01-01",
    "date:inception_upper": "1980-01-01",
    "iso:country": "GB",
    "wof:name": "L35 5HB",
    "wof:placetype": "postalcode"
  },
  "geometry": {"coordinates":[-2.805479,53.418894],"type":"Point"}
}
