{
  "type": "Feature",
  "properties": {
    "iso:country":"GB",
    "wof:name":"L35 5HB",
    "wof:placetype":"postalcode"
},
  "geometry": {"coordinates":[-2.80547864546063,53.41889425028049],"type":"Point"}
}