{
  "type": "Feature",
  "properties": {
    "iso:country":"GB",
    "wof:name":"M41 9PZ",
    "wof:placetype":"postalcode"
},
  "geometry": {"coordinates":[-2.3343290570266,53.45032026654256],"type":"Point"}
}