{
  "type": "Feature",
  "properties": {
    "iso:country":"GB",
    "wof:name":"E11 2AP",
    "wof:placetype":"postalcode"
},
  "geometry": {"coordinates":[0.02404669530927,51.5815212447227],"type":"Point"}
}