{
  "type": "Feature",
  "properties": {
    "iso:country":"GB",
    "wof:name":"KA2 9JE",
    "wof:placetype":"postalcode"
},
  "geometry": {"coordinates":[-4.5981117315399,55.58161792929502],"type":"Point"}
}