{
  "type": "Feature",
  "properties": {
    "iso:country": "GB",
    "wof:name": "KA2 9JE",
    "wof:placetype": "postalcode"
  },
  "geometry": {"coordinates":[-4.598112,55.581618],"type":"Point"}
}
