{
  "type": "Feature",
  "properties": {
    "iso:country":"GB",
    "wof:name":"HA4 9HP",
    "wof:placetype":"postalcode"
},
  "geometry": {"coordinates":[-0.3928685102346,51.5655176740573],"type":"Point"}
}