{
  "type": "Feature",
  "properties": {
    "date:inception_lower": "1980-01-01",
    "date:inception_upper": "1980-01-01",
    "iso:country": "GB",
    "wof:name": "HA4 9HP",
    "wof:placetype": "postalcode"
  },
  "geometry": {"coordinates":[-0.392868,51.565518],"type":"Point"}
}
