{
  "type": "Feature",
  "properties": {
    "iso:country": "GB",
    "wof:name": "TN12 7JG",
    "wof:placetype": "postalcode"
  },
  "geometry": {"coordinates":[0.376588,51.155612],"type":"Point"}
}
