{
  "type": "Feature",
  "properties": {
    "date:inception_lower": "1980-01-01",
    "date:inception_upper": "1980-01-01",
    "iso:country": "GB",
    "wof:name": "TN12 7JG",
    "wof:placetype": "postalcode"
  },
  "geometry": {"coordinates":[0.376588,51.155612],"type":"Point"}
}
