{
  "type": "Feature",
  "properties": {
    "iso:country":"GB",
    "wof:name":"TN12 7JG",
    "wof:placetype":"postalcode"
},
  "geometry": {"coordinates":[0.37658765826278,51.1556121031253],"type":"Point"}
}