{
  "type": "Feature",
  "properties": {
    "iso:country":"GB",
    "wof:name":"S10 5ST",
    "wof:placetype":"postalcode"
},
  "geometry": {"coordinates":[-1.53948575818613,53.3750630171882],"type":"Point"}
}