{
  "type": "Feature",
  "properties": {
    "iso:country": "GB",
    "wof:name": "S10 5ST",
    "wof:placetype": "postalcode"
  },
  "geometry": {"coordinates":[-1.539486,53.375063],"type":"Point"}
}
