{
  "type": "Feature",
  "properties": {
    "date:inception_lower": "2006-09-01",
    "date:inception_upper": "2006-09-01",
    "iso:country": "GB",
    "wof:name": "S10 5ST",
    "wof:placetype": "postalcode"
  },
  "geometry": {"coordinates":[-1.539486,53.375063],"type":"Point"}
}
