{
  "type": "Feature",
  "properties": {
    "iso:country":"GB",
    "wof:name":"M34 5TD",
    "wof:placetype":"postalcode"
},
  "geometry": {"coordinates":[-2.1350377467097,53.48206392040233],"type":"Point"}
}