{
  "type": "Feature",
  "properties": {
    "date:inception_lower":"1980-01-01",
    "date:inception_upper":"1980-01-31",
    "iso:country":"GB",
    "wof:name":"GU10 1HJ",
    "wof:placetype":"postalcode"
},
  "geometry": {"coordinates":[-0.694319,51.222351],"type":"Point"}
}