{
  "type": "Feature",
  "properties": {
    "iso:country": "GB",
    "wof:name": "GU10 1HJ",
    "wof:placetype": "postalcode"
  },
  "geometry": {"coordinates":[-0.694319,51.222351],"type":"Point"}
}
