{
  "type": "Feature",
  "properties": {
    "date:inception_lower":"1980-01-01",
    "date:inception_upper":"1980-01-31",
    "iso:country":"GB",
    "wof:name":"WF12 7SP",
    "wof:placetype":"postalcode"
},
  "geometry": {"coordinates":[-1.598171,53.703082],"type":"Point"}
}