{
  "type": "Feature",
  "properties": {
    "iso:country":"GB",
    "wof:name":"WF12 7SP",
    "wof:placetype":"postalcode"
},
  "geometry": {"coordinates":[-1.59817150217876,53.70308218541221],"type":"Point"}
}