{
  "type": "Feature",
  "properties": {
    "iso:country":"GB",
    "wof:name":"CA11 9NA",
    "wof:placetype":"postalcode"
},
  "geometry": {"coordinates":[-2.69726051581976,54.72435399527063],"type":"Point"}
}