{
  "type": "Feature",
  "properties": {
    "iso:country": "GB",
    "wof:name": "LS9 9DZ",
    "wof:placetype": "postalcode"
  },
  "geometry": {"coordinates":[-1.506458,53.798391],"type":"Point"}
}
