{
  "type": "Feature",
  "properties": {
    "iso:country":"GB",
    "wof:name":"LS9 9DZ",
    "wof:placetype":"postalcode"
},
  "geometry": {"coordinates":[-1.50645764147961,53.7983913149264],"type":"Point"}
}