{
  "type": "Feature",
  "properties": {
    "date:inception_lower": "1980-01-01",
    "date:inception_upper": "1980-01-01",
    "iso:country": "GB",
    "wof:name": "BS5 9RN",
    "wof:placetype": "postalcode"
  },
  "geometry": {"coordinates":[-2.55493,51.456841],"type":"Point"}
}
