{
  "type": "Feature",
  "properties": {
    "iso:country": "GB",
    "wof:name": "BS5 9RN",
    "wof:placetype": "postalcode"
  },
  "geometry": {"coordinates":[-2.55493,51.456841],"type":"Point"}
}
