{
  "type": "Feature",
  "properties": {
    "iso:country": "GB",
    "wof:name": "GU16 7EA",
    "wof:placetype": "postalcode"
  },
  "geometry": {"coordinates":[-0.741001,51.31319],"type":"Point"}
}
