{
  "type": "Feature",
  "properties": {
    "iso:country":"GB",
    "wof:name":"WV14 9RP",
    "wof:placetype":"postalcode"
},
  "geometry": {"coordinates":[-2.10890740032001,52.54845994584328],"type":"Point"}
}