{
  "type": "Feature",
  "properties": {
    "iso:country":"GB",
    "wof:name":"LN1 2DD",
    "wof:placetype":"postalcode"
},
  "geometry": {"coordinates":[-0.6785687148727,53.32652394818272],"type":"Point"}
}