{
  "type": "Feature",
  "properties": {
    "date:inception_lower": "1980-01-01",
    "date:inception_upper": "1980-01-01",
    "iso:country": "GB",
    "wof:name": "LN1 2DD",
    "wof:placetype": "postalcode"
  },
  "geometry": {"coordinates":[-0.678449,53.326553],"type":"Point"}
}
