{
  "type": "Feature",
  "properties": {
    "date:inception_lower": "2011-01-01",
    "date:inception_upper": "2011-01-01",
    "iso:country": "GB",
    "wof:name": "BA11 1FY",
    "wof:placetype": "postalcode"
  },
  "geometry": {"coordinates":[-2.31444,51.229883],"type":"Point"}
}
