{
  "type": "Feature",
  "properties": {
    "iso:country":"GB",
    "wof:name":"BA11 1FY",
    "wof:placetype":"postalcode"
},
  "geometry": {"coordinates":[-2.31443972849838,51.22988257838707],"type":"Point"}
}