{
  "type": "Feature",
  "properties": {
    "iso:country":"GB",
    "wof:name":"S71 5RA",
    "wof:placetype":"postalcode"
},
  "geometry": {"coordinates":[-1.44753502933942,53.55653901489033],"type":"Point"}
}