{
  "type": "Feature",
  "properties": {
    "iso:country":"GB",
    "wof:name":"HX7 8QN",
    "wof:placetype":"postalcode"
},
  "geometry": {"coordinates":[-2.00593929257109,53.76160211230621],"type":"Point"}
}