{
  "type": "Feature",
  "properties": {
    "iso:country": "GB",
    "wof:name": "HX7 8QN",
    "wof:placetype": "postalcode"
  },
  "geometry": {"coordinates":[-2.005939,53.761602],"type":"Point"}
}
