{
  "type": "Feature",
  "properties": {
    "date:inception_lower":"1998-12-01",
    "date:inception_upper":"1998-12-31",
    "iso:country":"GB",
    "wof:name":"NG32 3FB",
    "wof:placetype":"postalcode"
},
  "geometry": {"coordinates":[-0.601828,53.019965],"type":"Point"}
}