{
  "type": "Feature",
  "properties": {
    "iso:country":"GB",
    "wof:name":"NG32 3FB",
    "wof:placetype":"postalcode"
},
  "geometry": {"coordinates":[-0.60182814143677,53.01996526379099],"type":"Point"}
}