{
  "type": "Feature",
  "properties": {
    "iso:country":"GB",
    "wof:name":"S61 4NS",
    "wof:placetype":"postalcode"
},
  "geometry": {"coordinates":[-1.36751547177174,53.45005085138128],"type":"Point"}
}