{
  "type": "Feature",
  "properties": {
    "iso:country":"GB",
    "wof:name":"DD2 4RT",
    "wof:placetype":"postalcode"
},
  "geometry": {"coordinates":[-3.04598010015606,56.47261508448925],"type":"Point"}
}