{
  "type": "Feature",
  "properties": {
    "iso:country":"GB",
    "wof:name":"BN22 8TZ",
    "wof:placetype":"postalcode"
},
  "geometry": {"coordinates":[0.29438916468391,50.7866567303524],"type":"Point"}
}