{
  "type": "Feature",
  "properties": {
    "iso:country": "GB",
    "wof:name": "CF31 2PA",
    "wof:placetype": "postalcode"
  },
  "geometry": {"coordinates":[-3.564922,51.510924],"type":"Point"}
}
