{
  "type": "Feature",
  "properties": {
    "date:inception_lower": "1988-03-01",
    "date:inception_upper": "1988-03-01",
    "iso:country": "GB",
    "wof:name": "CF31 2PA",
    "wof:placetype": "postalcode"
  },
  "geometry": {"coordinates":[-3.564922,51.510924],"type":"Point"}
}
