{
  "type": "Feature",
  "properties": {
    "iso:country": "GB",
    "wof:name": "GU24 9LA",
    "wof:placetype": "postalcode"
  },
  "geometry": {"coordinates":[-0.655207,51.328054],"type":"Point"}
}
