{
  "type": "Feature",
  "properties": {
    "iso:country":"GB",
    "wof:name":"GU24 9LA",
    "wof:placetype":"postalcode"
},
  "geometry": {"coordinates":[-0.65520748938872,51.3280536412822],"type":"Point"}
}