{
  "type": "Feature",
  "properties": {
    "date:inception_lower":"2013-01-01",
    "date:inception_upper":"2013-01-31",
    "iso:country":"GB",
    "wof:name":"GU24 9LA",
    "wof:placetype":"postalcode"
},
  "geometry": {"coordinates":[-0.655207,51.328054],"type":"Point"}
}