{
  "type": "Feature",
  "properties": {
    "iso:country":"GB",
    "wof:name":"PE21 7QG",
    "wof:placetype":"postalcode"
},
  "geometry": {"coordinates":[-0.04989993360274,52.97754572941123],"type":"Point"}
}