{
  "type": "Feature",
  "properties": {
    "iso:country": "GB",
    "wof:name": "PE21 7QG",
    "wof:placetype": "postalcode"
  },
  "geometry": {"coordinates":[-0.0499,52.977546],"type":"Point"}
}
