{
  "type": "Feature",
  "properties": {
    "date:inception_lower": "2011-10-01",
    "date:inception_upper": "2011-10-01",
    "iso:country": "GB",
    "wof:name": "SG8 5FF",
    "wof:placetype": "postalcode"
  },
  "geometry": {"coordinates":[-0.029267,52.04783],"type":"Point"}
}
