{
  "type": "Feature",
  "properties": {
    "iso:country":"GB",
    "wof:name":"SG8 5FF",
    "wof:placetype":"postalcode"
},
  "geometry": {"coordinates":[-0.02926731399356,52.04783042847807],"type":"Point"}
}