{
  "type": "Feature",
  "properties": {
    "iso:country": "GB",
    "wof:name": "CT9 3HD",
    "wof:placetype": "postalcode"
  },
  "geometry": {"coordinates":[1.420865,51.384054],"type":"Point"}
}
