{
  "type": "Feature",
  "properties": {
    "iso:country":"GB",
    "wof:name":"NG2 5AT",
    "wof:placetype":"postalcode"
},
  "geometry": {"coordinates":[-1.1059007963456,52.93408195172875],"type":"Point"}
}