{
  "type": "Feature",
  "properties": {
    "date:inception_lower": "2007-10-01",
    "date:inception_upper": "2007-10-01",
    "iso:country": "GB",
    "wof:name": "NG2 5AT",
    "wof:placetype": "postalcode"
  },
  "geometry": {"coordinates":[-1.105897,52.934102],"type":"Point"}
}
