{
  "type": "Feature",
  "properties": {
    "date:inception_lower":"2004-11-01",
    "date:inception_upper":"2004-11-30",
    "iso:country":"GB",
    "wof:name":"TR2 5TB",
    "wof:placetype":"postalcode"
},
  "geometry": {"coordinates":[-4.907845,50.269765],"type":"Point"}
}