{
  "type": "Feature",
  "properties": {
    "iso:country":"GB",
    "wof:name":"TR2 5TB",
    "wof:placetype":"postalcode"
},
  "geometry": {"coordinates":[-4.90784480619766,50.26976509849081],"type":"Point"}
}