{
  "type": "Feature",
  "properties": {
    "iso:country": "GB",
    "wof:name": "TR2 5TB",
    "wof:placetype": "postalcode"
  },
  "geometry": {"coordinates":[-4.907845,50.269765],"type":"Point"}
}
