{
  "type": "Feature",
  "properties": {
    "iso:country": "GB",
    "wof:name": "ME9 8JW",
    "wof:placetype": "postalcode"
  },
  "geometry": {"coordinates":[0.7041,51.333233],"type":"Point"}
}
