{
  "type": "Feature",
  "properties": {
    "iso:country":"GB",
    "wof:name":"ME9 8JW",
    "wof:placetype":"postalcode"
},
  "geometry": {"coordinates":[0.70409956997571,51.33323290220379],"type":"Point"}
}