{
  "type": "Feature",
  "properties": {
    "date:inception_lower": "1985-10-01",
    "date:inception_upper": "1985-10-01",
    "iso:country": "GB",
    "wof:name": "ME9 8JW",
    "wof:placetype": "postalcode"
  },
  "geometry": {"coordinates":[0.7041,51.333233],"type":"Point"}
}
