{
  "type": "Feature",
  "properties": {
    "iso:country":"GB",
    "wof:name":"TN33 0DP",
    "wof:placetype":"postalcode"
},
  "geometry": {"coordinates":[0.49647730255872,50.91177862053861],"type":"Point"}
}