{
  "type": "Feature",
  "properties": {
    "iso:country": "GB",
    "wof:name": "OL16 5SG",
    "wof:placetype": "postalcode"
  },
  "geometry": {"coordinates":[-2.150161,53.612305],"type":"Point"}
}
