{
  "type": "Feature",
  "properties": {
    "iso:country":"GB",
    "wof:name":"OL16 5SG",
    "wof:placetype":"postalcode"
},
  "geometry": {"coordinates":[-2.15016074800143,53.61230491195218],"type":"Point"}
}