{
  "type": "Feature",
  "properties": {
    "iso:country":"GB",
    "wof:name":"BD23 6RP",
    "wof:placetype":"postalcode"
},
  "geometry": {"coordinates":[-1.98990087113034,53.97810112066848],"type":"Point"}
}