{
  "type": "Feature",
  "properties": {
    "iso:country": "GB",
    "wof:name": "CV21 3JT",
    "wof:placetype": "postalcode"
  },
  "geometry": {"coordinates":[-1.2529,52.375358],"type":"Point"}
}
