{
  "type": "Feature",
  "properties": {
    "iso:country":"GB",
    "wof:name":"CV21 3JT",
    "wof:placetype":"postalcode"
},
  "geometry": {"coordinates":[-1.25320820201016,52.37525319997611],"type":"Point"}
}