{
  "type": "Feature",
  "properties": {
    "date:inception_lower": "2015-12-01",
    "date:inception_upper": "2015-12-01",
    "iso:country": "GB",
    "wof:name": "TQ13 7FA",
    "wof:placetype": "postalcode"
  },
  "geometry": {"coordinates":[-3.835176,50.555816],"type":"Point"}
}
