{
  "type": "Feature",
  "properties": {
    "date:inception_lower": "1980-01-01",
    "date:inception_upper": "1980-01-01",
    "iso:country": "GB",
    "wof:name": "DA1 2ES",
    "wof:placetype": "postalcode"
  },
  "geometry": {"coordinates":[0.211942,51.44569],"type":"Point"}
}
