{
  "type": "Feature",
  "properties": {
    "iso:country":"GB",
    "wof:name":"DA1 2ES",
    "wof:placetype":"postalcode"
},
  "geometry": {"coordinates":[0.21194189766266,51.44569049313159],"type":"Point"}
}