{
  "type": "Feature",
  "properties": {
    "iso:country": "GB",
    "wof:name": "SP10 2LU",
    "wof:placetype": "postalcode"
  },
  "geometry": {"coordinates":[-1.493967,51.200897],"type":"Point"}
}
