{
  "type": "Feature",
  "properties": {
    "date:inception_lower":"1980-01-01",
    "date:inception_upper":"1980-01-31",
    "iso:country":"GB",
    "wof:name":"G51 3RT",
    "wof:placetype":"postalcode"
},
  "geometry": {"coordinates":[-4.321074,55.854476],"type":"Point"}
}