{
  "type": "Feature",
  "properties": {
    "iso:country":"GB",
    "wof:name":"PO21 2JT",
    "wof:placetype":"postalcode"
},
  "geometry": {"coordinates":[-0.68045185333573,50.78643488621906],"type":"Point"}
}