{
  "type": "Feature",
  "properties": {
    "iso:country": "GB",
    "wof:name": "GU7 3DH",
    "wof:placetype": "postalcode"
  },
  "geometry": {"coordinates":[-0.590426,51.200319],"type":"Point"}
}
