{
  "type": "Feature",
  "properties": {
    "date:inception_lower": "1995-12-01",
    "date:inception_upper": "1995-12-01",
    "iso:country": "GB",
    "wof:name": "GU7 3DH",
    "wof:placetype": "postalcode"
  },
  "geometry": {"coordinates":[-0.590426,51.200319],"type":"Point"}
}
