{
  "type": "Feature",
  "properties": {
    "date:inception_lower": "1980-01-01",
    "date:inception_upper": "1980-01-01",
    "iso:country": "GB",
    "wof:name": "HU8 8NH",
    "wof:placetype": "postalcode"
  },
  "geometry": {"coordinates":[-0.305225,53.761014],"type":"Point"}
}
