{
  "type": "Feature",
  "properties": {
    "iso:country":"GB",
    "wof:name":"HU8 8NH",
    "wof:placetype":"postalcode"
},
  "geometry": {"coordinates":[-0.30522528882652,53.76101362187581],"type":"Point"}
}