{
  "type": "Feature",
  "properties": {
    "iso:country":"GB",
    "wof:name":"LU7 9QQ",
    "wof:placetype":"postalcode"
},
  "geometry": {"coordinates":[-0.55710316426966,51.92787011881622],"type":"Point"}
}