{
  "type": "Feature",
  "properties": {
    "iso:country":"GB",
    "wof:name":"DL8 4EY",
    "wof:placetype":"postalcode"
},
  "geometry": {"coordinates":[-1.94883645644467,54.31816606831887],"type":"Point"}
}