{
  "type": "Feature",
  "properties": {
    "date:inception_lower": "2015-04-01",
    "date:inception_upper": "2015-04-01",
    "iso:country": "GB",
    "wof:name": "TS7 0PL",
    "wof:placetype": "postalcode"
  },
  "geometry": {"coordinates":[-1.180132,54.519854],"type":"Point"}
}
