{
  "type": "Feature",
  "properties": {
    "iso:country": "GB",
    "wof:name": "TS7 0PL",
    "wof:placetype": "postalcode"
  },
  "geometry": {"coordinates":[-1.180132,54.519854],"type":"Point"}
}
