{
  "type": "Feature",
  "properties": {
    "iso:country":"GB",
    "wof:name":"TS7 0PL",
    "wof:placetype":"postalcode"
},
  "geometry": {"coordinates":[-1.18013228055759,54.51985443556112],"type":"Point"}
}