{
  "type": "Feature",
  "properties": {
    "iso:country":"GB",
    "wof:name":"TN1 1JY",
    "wof:placetype":"postalcode"
},
  "geometry": {"coordinates":[0.26134045609157,51.13349833802413],"type":"Point"}
}