{
  "type": "Feature",
  "properties": {
    "iso:country":"GB",
    "wof:name":"HX7 7DH",
    "wof:placetype":"postalcode"
},
  "geometry": {"coordinates":[-2.01271427885249,53.74408391311515],"type":"Point"}
}