{
  "type": "Feature",
  "properties": {
    "date:inception_lower": "1980-01-01",
    "date:inception_upper": "1980-01-01",
    "iso:country": "GB",
    "wof:name": "HX7 7DH",
    "wof:placetype": "postalcode"
  },
  "geometry": {"coordinates":[-2.012714,53.744084],"type":"Point"}
}
