{
  "type": "Feature",
  "properties": {
    "iso:country": "GB",
    "wof:name": "NR16 1FE",
    "wof:placetype": "postalcode"
  },
  "geometry": {"coordinates":[1.152138,52.541525],"type":"Point"}
}
