{
  "type": "Feature",
  "properties": {
    "date:inception_lower":"2010-09-01",
    "date:inception_upper":"2010-09-30",
    "iso:country":"GB",
    "wof:name":"NR16 1FE",
    "wof:placetype":"postalcode"
},
  "geometry": {"coordinates":[1.152138,52.541525],"type":"Point"}
}