{
  "type": "Feature",
  "properties": {
    "date:inception_lower": "2010-09-01",
    "date:inception_upper": "2010-09-01",
    "iso:country": "GB",
    "wof:name": "NR16 1FE",
    "wof:placetype": "postalcode"
  },
  "geometry": {"coordinates":[1.146866,52.538761],"type":"Point"}
}
