{
  "type": "Feature",
  "properties": {
    "iso:country":"GB",
    "wof:name":"SY11 3QA",
    "wof:placetype":"postalcode"
},
  "geometry": {"coordinates":[-3.00009201318812,52.9260592285653],"type":"Point"}
}