{
  "type": "Feature",
  "properties": {
    "date:inception_lower":"1980-01-01",
    "date:inception_upper":"1980-01-31",
    "iso:country":"GB",
    "wof:name":"TN30 6NH",
    "wof:placetype":"postalcode"
},
  "geometry": {"coordinates":[0.697891,51.081354],"type":"Point"}
}