{
  "type": "Feature",
  "properties": {
    "iso:country":"GB",
    "wof:name":"TN30 6NH",
    "wof:placetype":"postalcode"
},
  "geometry": {"coordinates":[0.69789071509054,51.08135377290489],"type":"Point"}
}