{
  "type": "Feature",
  "properties": {
    "iso:country":"GB",
    "wof:name":"PO38 2QP",
    "wof:placetype":"postalcode"
},
  "geometry": {"coordinates":[-1.27950174814782,50.59817286749147],"type":"Point"}
}