{
  "type": "Feature",
  "properties": {
    "date:inception_lower": "1990-02-01",
    "date:inception_upper": "1990-02-01",
    "iso:country": "GB",
    "wof:name": "BD16 3LZ",
    "wof:placetype": "postalcode"
  },
  "geometry": {"coordinates":[-1.821391,53.8596],"type":"Point"}
}
