{
  "type": "Feature",
  "properties": {
    "iso:country": "GB",
    "wof:name": "HX7 8NE",
    "wof:placetype": "postalcode"
  },
  "geometry": {"coordinates":[-1.996902,53.734285],"type":"Point"}
}
