{
  "type": "Feature",
  "properties": {
    "date:inception_lower": "2009-11-01",
    "date:inception_upper": "2009-11-01",
    "iso:country": "GB",
    "wof:name": "HX7 8NE",
    "wof:placetype": "postalcode"
  },
  "geometry": {"coordinates":[-1.996902,53.734285],"type":"Point"}
}
