{
  "type": "Feature",
  "properties": {
    "iso:country":"GB",
    "wof:name":"HX7 8NE",
    "wof:placetype":"postalcode"
},
  "geometry": {"coordinates":[-1.99699157173775,53.73426964033154],"type":"Point"}
}