{
  "type": "Feature",
  "properties": {
    "date:inception_lower": "2013-03-01",
    "date:inception_upper": "2013-03-01",
    "iso:country": "GB",
    "wof:name": "WN6 8GB",
    "wof:placetype": "postalcode"
  },
  "geometry": {"coordinates":[-2.689243,53.567646],"type":"Point"}
}
