{
  "type": "Feature",
  "properties": {
    "iso:country":"GB",
    "wof:name":"WN6 8GB",
    "wof:placetype":"postalcode"
},
  "geometry": {"coordinates":[-2.68924346186346,53.56764620179214],"type":"Point"}
}