{
  "type": "Feature",
  "properties": {
    "iso:country":"GB",
    "wof:name":"RG7 2NS",
    "wof:placetype":"postalcode"
},
  "geometry": {"coordinates":[-1.10657023619674,51.35857685282703],"type":"Point"}
}