{
  "type": "Feature",
  "properties": {
    "date:inception_lower": "1980-01-01",
    "date:inception_upper": "1980-01-01",
    "iso:country": "GB",
    "wof:name": "RG7 2NS",
    "wof:placetype": "postalcode"
  },
  "geometry": {"coordinates":[-1.10657,51.358577],"type":"Point"}
}
