{
  "type": "Feature",
  "properties": {
    "iso:country": "GB",
    "wof:name": "NG6 0DW",
    "wof:placetype": "postalcode"
  },
  "geometry": {"coordinates":[-1.179519,52.993035],"type":"Point"}
}
