{
  "type": "Feature",
  "properties": {
    "iso:country":"GB",
    "wof:name":"NG6 0DW",
    "wof:placetype":"postalcode"
},
  "geometry": {"coordinates":[-1.17951888324053,52.99303546444266],"type":"Point"}
}