{
  "type": "Feature",
  "properties": {
    "date:inception_lower":"1980-01-01",
    "date:inception_upper":"1980-01-31",
    "iso:country":"GB",
    "wof:name":"EH55 8TB",
    "wof:placetype":"postalcode"
},
  "geometry": {"coordinates":[-3.559093,55.860984],"type":"Point"}
}