{
  "type": "Feature",
  "properties": {
    "iso:country":"GB",
    "wof:name":"CF36 3AF",
    "wof:placetype":"postalcode"
},
  "geometry": {"coordinates":[-3.70821517856631,51.47873583953733],"type":"Point"}
}