{
  "type": "Feature",
  "properties": {
    "date:inception_lower": "2016-06-01",
    "date:inception_upper": "2016-06-01",
    "iso:country": "GB",
    "wof:name": "SS17 0FS",
    "wof:placetype": "postalcode"
  },
  "geometry": {"coordinates":[0.415118,51.510426],"type":"Point"}
}
