{
  "type": "Feature",
  "properties": {
    "iso:country": "GB",
    "wof:name": "CV22 6PJ",
    "wof:placetype": "postalcode"
  },
  "geometry": {"coordinates":[-1.287805,52.338731],"type":"Point"}
}
