{
  "type": "Feature",
  "properties": {
    "iso:country":"GB",
    "wof:name":"SN7 8DA",
    "wof:placetype":"postalcode"
},
  "geometry": {"coordinates":[-1.66804056765741,51.67738202003798],"type":"Point"}
}