{
  "type": "Feature",
  "properties": {
    "date:inception_lower": "1980-01-01",
    "date:inception_upper": "1980-01-01",
    "iso:country": "GB",
    "wof:name": "OX7 6DW",
    "wof:placetype": "postalcode"
  },
  "geometry": {"coordinates":[-1.600746,51.850036],"type":"Point"}
}
