{
  "type": "Feature",
  "properties": {
    "iso:country":"GB",
    "wof:name":"OX7 6DW",
    "wof:placetype":"postalcode"
},
  "geometry": {"coordinates":[-1.60074636693717,51.85003577690209],"type":"Point"}
}