{
  "type": "Feature",
  "properties": {
    "iso:country": "GB",
    "wof:name": "OX7 6DW",
    "wof:placetype": "postalcode"
  },
  "geometry": {"coordinates":[-1.600746,51.850036],"type":"Point"}
}
