{
  "type": "Feature",
  "properties": {
    "date:inception_lower": "1982-03-01",
    "date:inception_upper": "1982-03-01",
    "iso:country": "GB",
    "wof:name": "PO13 0DR",
    "wof:placetype": "postalcode"
  },
  "geometry": {"coordinates":[-1.165773,50.814601],"type":"Point"}
}
