{
  "type": "Feature",
  "properties": {
    "iso:country": "GB",
    "wof:name": "RG5 3BQ",
    "wof:placetype": "postalcode"
  },
  "geometry": {"coordinates":[-0.909874,51.458],"type":"Point"}
}
