{
  "type": "Feature",
  "properties": {
    "iso:country":"GB",
    "wof:name":"RG5 3BQ",
    "wof:placetype":"postalcode"
},
  "geometry": {"coordinates":[-0.90987376081588,51.45799982163287],"type":"Point"}
}