{
  "type": "Feature",
  "properties": {
    "iso:country":"GB",
    "wof:name":"B42 2QJ",
    "wof:placetype":"postalcode"
},
  "geometry": {"coordinates":[-1.90430864831953,52.54113609427748],"type":"Point"}
}