{
  "type": "Feature",
  "properties": {
    "iso:country": "GB",
    "wof:name": "LS10 1JT",
    "wof:placetype": "postalcode"
  },
  "geometry": {"coordinates":[-1.531866,53.790826],"type":"Point"}
}
