{
  "type": "Feature",
  "properties": {
    "iso:country": "GB",
    "wof:name": "GU30 7GW",
    "wof:placetype": "postalcode"
  },
  "geometry": {"coordinates":[-0.807205,51.074591],"type":"Point"}
}
