{
  "type": "Feature",
  "properties": {
    "iso:country": "GB",
    "wof:name": "IV30 4LZ",
    "wof:placetype": "postalcode"
  },
  "geometry": {"coordinates":[-3.32202,57.657708],"type":"Point"}
}
