{
  "type": "Feature",
  "properties": {
    "iso:country":"GB",
    "wof:name":"IV30 4LZ",
    "wof:placetype":"postalcode"
},
  "geometry": {"coordinates":[-3.32202002896875,57.65770812495806],"type":"Point"}
}