{
  "type": "Feature",
  "properties": {
    "date:inception_lower":"1998-12-01",
    "date:inception_upper":"1998-12-31",
    "iso:country":"GB",
    "wof:name":"IV30 4LZ",
    "wof:placetype":"postalcode"
},
  "geometry": {"coordinates":[-3.32202,57.657708],"type":"Point"}
}