{
  "type": "Feature",
  "properties": {
    "date:inception_lower": "1983-07-01",
    "date:inception_upper": "1983-07-01",
    "iso:country": "GB",
    "wof:name": "CV22 6SP",
    "wof:placetype": "postalcode"
  },
  "geometry": {"coordinates":[-1.278196,52.36346],"type":"Point"}
}
