{
  "type": "Feature",
  "properties": {
    "iso:country": "GB",
    "wof:name": "CV22 6SP",
    "wof:placetype": "postalcode"
  },
  "geometry": {"coordinates":[-1.278196,52.36346],"type":"Point"}
}
