{
  "type": "Feature",
  "properties": {
    "iso:country":"GB",
    "wof:name":"BS3 4NX",
    "wof:placetype":"postalcode"
},
  "geometry": {"coordinates":[-2.59667996204123,51.43778944493275],"type":"Point"}
}