{
  "type": "Feature",
  "properties": {
    "iso:country":"GB",
    "wof:name":"YO16 7GZ",
    "wof:placetype":"postalcode"
},
  "geometry": {"coordinates":[-0.19731494077777,54.10138530189632],"type":"Point"}
}