{
  "type": "Feature",
  "properties": {
    "iso:country":"GB",
    "wof:name":"HG2 8HZ",
    "wof:placetype":"postalcode"
},
  "geometry": {"coordinates":[-1.52968878290617,53.98394107764212],"type":"Point"}
}