{
  "type": "Feature",
  "properties": {
    "iso:country": "GB",
    "wof:name": "HG2 8HZ",
    "wof:placetype": "postalcode"
  },
  "geometry": {"coordinates":[-1.529689,53.983941],"type":"Point"}
}
