{
  "type": "Feature",
  "properties": {
    "iso:country": "GB",
    "wof:name": "PA19 1TA",
    "wof:placetype": "postalcode"
  },
  "geometry": {"coordinates":[-4.822924,55.951765],"type":"Point"}
}
