{
  "type": "Feature",
  "properties": {
    "date:inception_lower": "1980-01-01",
    "date:inception_upper": "1980-01-01",
    "iso:country": "GB",
    "wof:name": "NE10 8DQ",
    "wof:placetype": "postalcode"
  },
  "geometry": {"coordinates":[-1.537287,54.944147],"type":"Point"}
}
