{
  "type": "Feature",
  "properties": {
    "iso:country": "GB",
    "wof:name": "NE10 8DQ",
    "wof:placetype": "postalcode"
  },
  "geometry": {"coordinates":[-1.537287,54.944147],"type":"Point"}
}
