{
  "type": "Feature",
  "properties": {
    "iso:country":"GB",
    "wof:name":"CR5 1AN",
    "wof:placetype":"postalcode"
},
  "geometry": {"coordinates":[-0.13869781233028,51.31353818926789],"type":"Point"}
}