{
  "type": "Feature",
  "properties": {
    "iso:country":"GB",
    "wof:name":"L20 7DL",
    "wof:placetype":"postalcode"
},
  "geometry": {"coordinates":[-2.99174412616682,53.44213090357957],"type":"Point"}
}