{
  "type": "Feature",
  "properties": {
    "date:inception_lower": "2006-08-01",
    "date:inception_upper": "2006-08-01",
    "iso:country": "GB",
    "wof:name": "L20 7DL",
    "wof:placetype": "postalcode"
  },
  "geometry": {"coordinates":[-2.991863,53.442128],"type":"Point"}
}
