{
  "type": "Feature",
  "properties": {
    "date:inception_lower":"2004-09-01",
    "date:inception_upper":"2004-09-30",
    "iso:country":"GB",
    "wof:name":"NW7 1HH",
    "wof:placetype":"postalcode"
},
  "geometry": {"coordinates":[-0.211706,51.607085],"type":"Point"}
}