{
  "type": "Feature",
  "properties": {
    "iso:country":"GB",
    "wof:name":"BA11 2NF",
    "wof:placetype":"postalcode"
},
  "geometry": {"coordinates":[-2.30800237771803,51.25242439828384],"type":"Point"}
}