{
  "type": "Feature",
  "properties": {
    "date:inception_lower": "1980-01-01",
    "date:inception_upper": "1980-01-01",
    "iso:country": "GB",
    "wof:name": "SW15 6EN",
    "wof:placetype": "postalcode"
  },
  "geometry": {"coordinates":[-0.21874,51.458323],"type":"Point"}
}
