{
  "type": "Feature",
  "properties": {
    "iso:country":"GB",
    "wof:name":"DT8 3FJ",
    "wof:placetype":"postalcode"
},
  "geometry": {"coordinates":[-2.77582086004787,50.84252714003691],"type":"Point"}
}