{
  "type": "Feature",
  "properties": {
    "iso:country": "GB",
    "wof:name": "DT8 3FJ",
    "wof:placetype": "postalcode"
  },
  "geometry": {"coordinates":[-2.775821,50.842527],"type":"Point"}
}
