{
  "type": "Feature",
  "properties": {
    "date:inception_lower":"2009-02-01",
    "date:inception_upper":"2009-02-28",
    "iso:country":"GB",
    "wof:name":"DT8 3FJ",
    "wof:placetype":"postalcode"
},
  "geometry": {"coordinates":[-2.775821,50.842527],"type":"Point"}
}