{
  "type": "Feature",
  "properties": {
    "date:inception_lower": "2024-09-01",
    "date:inception_upper": "2024-09-01",
    "iso:country": "GB",
    "wof:name": "IP7 6SG",
    "wof:placetype": "postalcode"
  },
  "geometry": {"coordinates":[0.946997,52.049893],"type":"Point"}
}
