{
  "type": "Feature",
  "properties": {
    "date:inception_lower": "1980-01-01",
    "date:inception_upper": "1980-01-01",
    "iso:country": "GB",
    "wof:name": "SR6 7TN",
    "wof:placetype": "postalcode"
  },
  "geometry": {"coordinates":[-1.404667,54.945619],"type":"Point"}
}
