{
  "type": "Feature",
  "properties": {
    "iso:country": "GB",
    "wof:name": "SR6 7TN",
    "wof:placetype": "postalcode"
  },
  "geometry": {"coordinates":[-1.404667,54.945619],"type":"Point"}
}
