{
  "type": "Feature",
  "properties": {
    "iso:country":"GB",
    "wof:name":"SR6 7TN",
    "wof:placetype":"postalcode"
},
  "geometry": {"coordinates":[-1.40466712293656,54.94561904924111],"type":"Point"}
}