{
  "type": "Feature",
  "properties": {
    "iso:country":"GB",
    "wof:name":"BD6 2LP",
    "wof:placetype":"postalcode"
},
  "geometry": {"coordinates":[-1.78794611133465,53.75945580598437],"type":"Point"}
}