{
  "type": "Feature",
  "properties": {
    "iso:country":"GB",
    "wof:name":"NR6 5PL",
    "wof:placetype":"postalcode"
},
  "geometry": {"coordinates":[1.26177534204978,52.66294594365054],"type":"Point"}
}