{
  "type": "Feature",
  "properties": {
    "iso:country":"GB",
    "wof:name":"KT6 7SR",
    "wof:placetype":"postalcode"
},
  "geometry": {"coordinates":[-0.30056436428437,51.37776900814118],"type":"Point"}
}