{
  "type": "Feature",
  "properties": {
    "date:inception_lower": "1992-01-01",
    "date:inception_upper": "1992-01-01",
    "iso:country": "GB",
    "wof:name": "RG26 5NW",
    "wof:placetype": "postalcode"
  },
  "geometry": {"coordinates":[-1.05631,51.331648],"type":"Point"}
}
