{
  "type": "Feature",
  "properties": {
    "date:inception_lower": "1989-10-01",
    "date:inception_upper": "1989-10-01",
    "iso:country": "GB",
    "wof:name": "KY5 8LQ",
    "wof:placetype": "postalcode"
  },
  "geometry": {"coordinates":[-3.317377,56.138498],"type":"Point"}
}
