{
  "type": "Feature",
  "properties": {
    "iso:country":"GB",
    "wof:name":"KY5 8LQ",
    "wof:placetype":"postalcode"
},
  "geometry": {"coordinates":[-3.31737666674146,56.13849771476243],"type":"Point"}
}