{
  "type": "Feature",
  "properties": {
    "iso:country":"GB",
    "wof:name":"DH5 0AL",
    "wof:placetype":"postalcode"
},
  "geometry": {"coordinates":[-1.45089368355277,54.81592808386173],"type":"Point"}
}