{
  "type": "Feature",
  "properties": {
    "iso:country":"GB",
    "wof:name":"DL1 4QZ",
    "wof:placetype":"postalcode"
},
  "geometry": {"coordinates":[-1.50829000527744,54.52260366115522],"type":"Point"}
}