{
  "type": "Feature",
  "properties": {
    "iso:country":"GB",
    "wof:name":"ME3 9GZ",
    "wof:placetype":"postalcode"
},
  "geometry": {"coordinates":[0.56174323309338,51.42731502611637],"type":"Point"}
}