{
  "type": "Feature",
  "properties": {
    "date:inception_lower": "1999-06-01",
    "date:inception_upper": "1999-06-01",
    "iso:country": "GB",
    "wof:name": "CF10 3AS",
    "wof:placetype": "postalcode"
  },
  "geometry": {"coordinates":[-3.181234,51.489501],"type":"Point"}
}
