{
  "type": "Feature",
  "properties": {
    "iso:country":"GB",
    "wof:name":"EC2A 1AF",
    "wof:placetype":"postalcode"
},
  "geometry": {"coordinates":[-0.08748789108367,51.52123573315789],"type":"Point"}
}