{
  "type": "Feature",
  "properties": {
    "iso:country": "GB",
    "wof:name": "DA8 1NW",
    "wof:placetype": "postalcode"
  },
  "geometry": {"coordinates":[0.149181,51.476328],"type":"Point"}
}
