{
  "type": "Feature",
  "properties": {
    "iso:country":"GB",
    "wof:name":"DA8 1NW",
    "wof:placetype":"postalcode"
},
  "geometry": {"coordinates":[0.14918096783162,51.47632796618331],"type":"Point"}
}