{
  "type": "Feature",
  "properties": {
    "iso:country": "GB",
    "wof:name": "PO21 5GB",
    "wof:placetype": "postalcode"
  },
  "geometry": {"coordinates":[-0.690841,50.79389],"type":"Point"}
}
