{
  "type": "Feature",
  "properties": {
    "iso:country":"GB",
    "wof:name":"PO21 5GB",
    "wof:placetype":"postalcode"
},
  "geometry": {"coordinates":[-0.69084095246848,50.79389024906153],"type":"Point"}
}