{
  "type": "Feature",
  "properties": {
    "date:inception_lower": "2014-06-01",
    "date:inception_upper": "2014-06-01",
    "iso:country": "GB",
    "wof:name": "PO21 5GB",
    "wof:placetype": "postalcode"
  },
  "geometry": {"coordinates":[-0.690841,50.79389],"type":"Point"}
}
