{
  "type": "Feature",
  "properties": {
    "date:inception_lower":"1986-01-01",
    "date:inception_upper":"1986-01-31",
    "iso:country":"GB",
    "wof:name":"SO51 0PN",
    "wof:placetype":"postalcode"
},
  "geometry": {"coordinates":[-1.46646,51.02327],"type":"Point"}
}