{
  "type": "Feature",
  "properties": {
    "iso:country": "GB",
    "wof:name": "SO51 0PN",
    "wof:placetype": "postalcode"
  },
  "geometry": {"coordinates":[-1.46646,51.02327],"type":"Point"}
}
