{
  "type": "Feature",
  "properties": {
    "iso:country":"GB",
    "wof:name":"SO51 0PN",
    "wof:placetype":"postalcode"
},
  "geometry": {"coordinates":[-1.46645969673629,51.02327009649068],"type":"Point"}
}