{
  "type": "Feature",
  "properties": {
    "iso:country":"GB",
    "wof:name":"SM6 9QL",
    "wof:placetype":"postalcode"
},
  "geometry": {"coordinates":[-0.14676027066575,51.35666038236071],"type":"Point"}
}