{
  "type": "Feature",
  "properties": {
    "iso:country": "GB",
    "wof:name": "NG11 6BB",
    "wof:placetype": "postalcode"
  },
  "geometry": {"coordinates":[-1.143243,52.894974],"type":"Point"}
}
