{
  "type": "Feature",
  "properties": {
    "iso:country":"GB",
    "wof:name":"OL16 5NW",
    "wof:placetype":"postalcode"
},
  "geometry": {"coordinates":[-2.14250774612105,53.61089414284272],"type":"Point"}
}