{
  "type": "Feature",
  "properties": {
    "iso:country":"GB",
    "wof:name":"S41 8XG",
    "wof:placetype":"postalcode"
},
  "geometry": {"coordinates":[-1.46420754180135,53.25412837123038],"type":"Point"}
}