{
  "type": "Feature",
  "properties": {
    "iso:country": "GB",
    "wof:name": "B32 2PL",
    "wof:placetype": "postalcode"
  },
  "geometry": {"coordinates":[-1.978525,52.452924],"type":"Point"}
}
