{
  "type": "Feature",
  "properties": {
    "iso:country":"GB",
    "wof:name":"W2 4SS",
    "wof:placetype":"postalcode"
},
  "geometry": {"coordinates":[-0.18793221836618,51.51315458955761],"type":"Point"}
}