{
  "type": "Feature",
  "properties": {
    "date:inception_lower": "1980-01-01",
    "date:inception_upper": "1980-01-01",
    "iso:country": "GB",
    "wof:name": "W2 4SS",
    "wof:placetype": "postalcode"
  },
  "geometry": {"coordinates":[-0.187932,51.513155],"type":"Point"}
}
