{
  "type": "Feature",
  "properties": {
    "iso:country": "GB",
    "wof:name": "LL63 5UE",
    "wof:placetype": "postalcode"
  },
  "geometry": {"coordinates":[-4.469232,53.243242],"type":"Point"}
}
