{
  "type": "Feature",
  "properties": {
    "date:inception_lower":"1980-01-01",
    "date:inception_upper":"1980-01-31",
    "iso:country":"GB",
    "wof:name":"LL63 5UE",
    "wof:placetype":"postalcode"
},
  "geometry": {"coordinates":[-4.469232,53.243242],"type":"Point"}
}