{
  "type": "Feature",
  "properties": {
    "iso:country":"GB",
    "wof:name":"LL63 5UE",
    "wof:placetype":"postalcode"
},
  "geometry": {"coordinates":[-4.46933156969537,53.24323981627169],"type":"Point"}
}