{
  "type": "Feature",
  "properties": {
    "iso:country":"GB",
    "wof:name":"S35 9TA",
    "wof:placetype":"postalcode"
},
  "geometry": {"coordinates":[-1.46538993172515,53.43927495129719],"type":"Point"}
}