{
  "type": "Feature",
  "properties": {
    "iso:country":"GB",
    "wof:name":"EX2 6JL",
    "wof:placetype":"postalcode"
},
  "geometry": {"coordinates":[-3.50484785552244,50.70284984778549],"type":"Point"}
}