{
  "type": "Feature",
  "properties": {
    "iso:country": "GB",
    "wof:name": "EX2 6JL",
    "wof:placetype": "postalcode"
  },
  "geometry": {"coordinates":[-3.50472,50.702814],"type":"Point"}
}
