{
  "type": "Feature",
  "properties": {
    "date:inception_lower": "2002-05-01",
    "date:inception_upper": "2002-05-01",
    "iso:country": "GB",
    "wof:name": "EX2 6JL",
    "wof:placetype": "postalcode"
  },
  "geometry": {"coordinates":[-3.504862,50.702839],"type":"Point"}
}
