{
  "type": "Feature",
  "properties": {
    "iso:country":"GB",
    "wof:name":"BN11 4RY",
    "wof:placetype":"postalcode"
},
  "geometry": {"coordinates":[-0.38887748979476,50.81230606192642],"type":"Point"}
}