{
  "type": "Feature",
  "properties": {
    "iso:country":"GB",
    "wof:name":"SN3 1NR",
    "wof:placetype":"postalcode"
},
  "geometry": {"coordinates":[-1.75964433380192,51.54345459338047],"type":"Point"}
}