{
  "type": "Feature",
  "properties": {
    "iso:country":"GB",
    "wof:name":"N2 0AS",
    "wof:placetype":"postalcode"
},
  "geometry": {"coordinates":[-0.16324316751453,51.58373883350397],"type":"Point"}
}