{
  "type": "Feature",
  "properties": {
    "iso:country": "GB",
    "wof:name": "OL10 3QD",
    "wof:placetype": "postalcode"
  },
  "geometry": {"coordinates":[-2.242584,53.587525],"type":"Point"}
}
