{
  "type": "Feature",
  "properties": {
    "iso:country":"GB",
    "wof:name":"CR4 4LD",
    "wof:placetype":"postalcode"
},
  "geometry": {"coordinates":[-0.16410455784243,51.39847062728923],"type":"Point"}
}