{
  "type": "Feature",
  "properties": {
    "date:inception_lower": "1980-01-01",
    "date:inception_upper": "1980-01-01",
    "iso:country": "GB",
    "wof:name": "CR4 4LD",
    "wof:placetype": "postalcode"
  },
  "geometry": {"coordinates":[-0.164105,51.398471],"type":"Point"}
}
