{
  "type": "Feature",
  "properties": {
    "iso:country": "GB",
    "wof:name": "CR4 4LD",
    "wof:placetype": "postalcode"
  },
  "geometry": {"coordinates":[-0.164105,51.398471],"type":"Point"}
}
