{
  "type": "Feature",
  "properties": {
    "date:inception_lower": "1980-01-01",
    "date:inception_upper": "1980-01-01",
    "iso:country": "GB",
    "wof:name": "ME9 7TU",
    "wof:placetype": "postalcode"
  },
  "geometry": {"coordinates":[0.638972,51.342175],"type":"Point"}
}
