{
  "type": "Feature",
  "properties": {
    "iso:country":"GB",
    "wof:name":"ME9 7TU",
    "wof:placetype":"postalcode"
},
  "geometry": {"coordinates":[0.63919027402114,51.3424758446082],"type":"Point"}
}