{
  "type": "Feature",
  "properties": {
    "iso:country":"GB",
    "wof:name":"SN2 1JG",
    "wof:placetype":"postalcode"
},
  "geometry": {"coordinates":[-1.80009519958271,51.57570155922846],"type":"Point"}
}