{
  "type": "Feature",
  "properties": {
    "date:inception_lower":"2004-07-01",
    "date:inception_upper":"2004-07-31",
    "iso:country":"GB",
    "wof:name":"FY1 6JX",
    "wof:placetype":"postalcode"
},
  "geometry": {"coordinates":[-3.04853,53.805489],"type":"Point"}
}