{
  "type": "Feature",
  "properties": {
    "iso:country": "GB",
    "wof:name": "WV7 3JF",
    "wof:placetype": "postalcode"
  },
  "geometry": {"coordinates":[-2.275183,52.633611],"type":"Point"}
}
