{
  "type": "Feature",
  "properties": {
    "iso:country":"GB",
    "wof:name":"OX12 8LG",
    "wof:placetype":"postalcode"
},
  "geometry": {"coordinates":[-1.33764472424914,51.59204978386847],"type":"Point"}
}