{
  "type": "Feature",
  "properties": {
    "iso:country": "GB",
    "wof:name": "SL5 8JR",
    "wof:placetype": "postalcode"
  },
  "geometry": {"coordinates":[-0.693882,51.419699],"type":"Point"}
}
