{
  "type": "Feature",
  "properties": {
    "iso:country":"GB",
    "wof:name":"SL5 8JR",
    "wof:placetype":"postalcode"
},
  "geometry": {"coordinates":[-0.69388181779502,51.41969883728047],"type":"Point"}
}