{
  "type": "Feature",
  "properties": {
    "iso:country": "GB",
    "wof:name": "CF48 2EB",
    "wof:placetype": "postalcode"
  },
  "geometry": {"coordinates":[-3.354148,51.769355],"type":"Point"}
}
