{
  "type": "Feature",
  "properties": {
    "iso:country":"GB",
    "wof:name":"RH6 7HR",
    "wof:placetype":"postalcode"
},
  "geometry": {"coordinates":[-0.16455624247158,51.17350496326729],"type":"Point"}
}