{
  "type": "Feature",
  "properties": {
    "iso:country": "GB",
    "wof:name": "S26 6QY",
    "wof:placetype": "postalcode"
  },
  "geometry": {"coordinates":[-1.253001,53.340976],"type":"Point"}
}
