{
  "type": "Feature",
  "properties": {
    "iso:country":"GB",
    "wof:name":"M44 6DP",
    "wof:placetype":"postalcode"
},
  "geometry": {"coordinates":[-2.41707382006472,53.44910710324914],"type":"Point"}
}