{
  "type": "Feature",
  "properties": {
    "iso:country":"GB",
    "wof:name":"EX35 6HG",
    "wof:placetype":"postalcode"
},
  "geometry": {"coordinates":[-3.83601874834855,51.22936057358909],"type":"Point"}
}