{
  "type": "Feature",
  "properties": {
    "date:inception_lower": "2018-10-01",
    "date:inception_upper": "2018-10-01",
    "iso:country": "GB",
    "wof:name": "RG45 6JF",
    "wof:placetype": "postalcode"
  },
  "geometry": {"coordinates":[-0.789561,51.377753],"type":"Point"}
}
