{
  "type": "Feature",
  "properties": {
    "iso:country": "GB",
    "wof:name": "RG45 6JF",
    "wof:placetype": "postalcode"
  },
  "geometry": {"coordinates":[-0.789858,51.377918],"type":"Point"}
}
