{
  "type": "Feature",
  "properties": {
    "iso:country": "GB",
    "wof:name": "NE3 1AT",
    "wof:placetype": "postalcode"
  },
  "geometry": {"coordinates":[-1.61238,55.008508],"type":"Point"}
}
