{
  "type": "Feature",
  "properties": {
    "iso:country":"GB",
    "wof:name":"NE3 1AT",
    "wof:placetype":"postalcode"
},
  "geometry": {"coordinates":[-1.61237958979365,55.00850830738968],"type":"Point"}
}