{
  "type": "Feature",
  "properties": {
    "iso:country": "GB",
    "wof:name": "SA67 8JW",
    "wof:placetype": "postalcode"
  },
  "geometry": {"coordinates":[-4.692562,51.735773],"type":"Point"}
}
