{
  "type": "Feature",
  "properties": {
    "iso:country":"GB",
    "wof:name":"HP1 3RE",
    "wof:placetype":"postalcode"
},
  "geometry": {"coordinates":[-0.49666646046324,51.76160429714239],"type":"Point"}
}