{
  "type": "Feature",
  "properties": {
    "date:inception_lower": "1980-01-01",
    "date:inception_upper": "1980-01-01",
    "iso:country": "GB",
    "wof:name": "HP1 3RE",
    "wof:placetype": "postalcode"
  },
  "geometry": {"coordinates":[-0.496666,51.761604],"type":"Point"}
}
