{
  "type": "Feature",
  "properties": {
    "iso:country":"GB",
    "wof:name":"EX33 2EW",
    "wof:placetype":"postalcode"
},
  "geometry": {"coordinates":[-4.16074319198359,51.11829450718744],"type":"Point"}
}