{
  "type": "Feature",
  "properties": {
    "iso:country":"GB",
    "wof:name":"YO25 4DG",
    "wof:placetype":"postalcode"
},
  "geometry": {"coordinates":[-0.37806560643269,54.04138725874915],"type":"Point"}
}