{
  "type": "Feature",
  "properties": {
    "iso:country": "GB",
    "wof:name": "YO25 4DG",
    "wof:placetype": "postalcode"
  },
  "geometry": {"coordinates":[-0.374919,54.040555],"type":"Point"}
}
