{
  "type": "Feature",
  "properties": {
    "iso:country":"GB",
    "wof:name":"WA5 3RF",
    "wof:placetype":"postalcode"
},
  "geometry": {"coordinates":[-2.64735458121412,53.40419801910115],"type":"Point"}
}