{
  "type": "Feature",
  "properties": {
    "date:inception_lower":"1997-12-01",
    "date:inception_upper":"1997-12-31",
    "iso:country":"GB",
    "wof:name":"WA5 3RF",
    "wof:placetype":"postalcode"
},
  "geometry": {"coordinates":[-2.647355,53.404198],"type":"Point"}
}