{
  "type": "Feature",
  "properties": {
    "iso:country": "GB",
    "wof:name": "WA5 3RF",
    "wof:placetype": "postalcode"
  },
  "geometry": {"coordinates":[-2.647355,53.404198],"type":"Point"}
}
