{
  "type": "Feature",
  "properties": {
    "iso:country":"GB",
    "wof:name":"LE2 5UW",
    "wof:placetype":"postalcode"
},
  "geometry": {"coordinates":[-1.07641335354749,52.59070538572023],"type":"Point"}
}