{
  "type": "Feature",
  "properties": {
    "iso:country":"GB",
    "wof:name":"DY2 8RF",
    "wof:placetype":"postalcode"
},
  "geometry": {"coordinates":[-2.08580467915792,52.50619955143662],"type":"Point"}
}