{
  "type": "Feature",
  "properties": {
    "date:inception_lower": "1990-09-01",
    "date:inception_upper": "1990-09-01",
    "iso:country": "GB",
    "wof:name": "KW1 4AR",
    "wof:placetype": "postalcode"
  },
  "geometry": {"coordinates":[-3.08941,58.442577],"type":"Point"}
}
