{
  "type": "Feature",
  "properties": {
    "iso:country": "GB",
    "wof:name": "KW1 4AR",
    "wof:placetype": "postalcode"
  },
  "geometry": {"coordinates":[-3.08941,58.442577],"type":"Point"}
}
