{
  "type": "Feature",
  "properties": {
    "iso:country":"GB",
    "wof:name":"SY23 3HY",
    "wof:placetype":"postalcode"
},
  "geometry": {"coordinates":[-3.98845277920279,52.42594763341181],"type":"Point"}
}