{
  "type": "Feature",
  "properties": {
    "iso:country":"GB",
    "wof:name":"RG22 5UY",
    "wof:placetype":"postalcode"
},
  "geometry": {"coordinates":[-1.14172807841996,51.23627871344811],"type":"Point"}
}