{
  "type": "Feature",
  "properties": {
    "date:inception_lower": "1980-01-01",
    "date:inception_upper": "1980-01-01",
    "iso:country": "GB",
    "wof:name": "EX9 7AQ",
    "wof:placetype": "postalcode"
  },
  "geometry": {"coordinates":[-3.342998,50.641398],"type":"Point"}
}
