{
  "type": "Feature",
  "properties": {
    "iso:country":"GB",
    "wof:name":"EX9 7AQ",
    "wof:placetype":"postalcode"
},
  "geometry": {"coordinates":[-3.34299834998761,50.64139812411011],"type":"Point"}
}