{
  "type": "Feature",
  "properties": {
    "iso:country":"GB",
    "wof:name":"TN38 0RA",
    "wof:placetype":"postalcode"
},
  "geometry": {"coordinates":[0.55652609679044,50.85981405783637],"type":"Point"}
}