{
  "type": "Feature",
  "properties": {
    "iso:country": "GB",
    "wof:name": "DE14 1BX",
    "wof:placetype": "postalcode"
  },
  "geometry": {"coordinates":[-1.639027,52.806019],"type":"Point"}
}
