{
  "type": "Feature",
  "properties": {
    "date:inception_lower": "1997-12-01",
    "date:inception_upper": "1997-12-01",
    "iso:country": "GB",
    "wof:name": "AL7 1GB",
    "wof:placetype": "postalcode"
  },
  "geometry": {"coordinates":[-0.192745,51.809343],"type":"Point"}
}
