{
  "type": "Feature",
  "properties": {
    "iso:country":"GB",
    "wof:name":"N19 5SJ",
    "wof:placetype":"postalcode"
},
  "geometry": {"coordinates":[-0.13432859646048,51.56406590462452],"type":"Point"}
}