{
  "type": "Feature",
  "properties": {
    "iso:country":"GB",
    "wof:name":"HG4 2EW",
    "wof:placetype":"postalcode"
},
  "geometry": {"coordinates":[-1.54629962932992,54.14205259842449],"type":"Point"}
}