{
  "type": "Feature",
  "properties": {
    "date:inception_lower": "1980-01-01",
    "date:inception_upper": "1980-01-01",
    "iso:country": "GB",
    "wof:name": "NR10 5ED",
    "wof:placetype": "postalcode"
  },
  "geometry": {"coordinates":[1.330867,52.773578],"type":"Point"}
}
