{
  "type": "Feature",
  "properties": {
    "iso:country":"GB",
    "wof:name":"NR10 5ED",
    "wof:placetype":"postalcode"
},
  "geometry": {"coordinates":[1.33086192043815,52.77356893580556],"type":"Point"}
}