{
  "type": "Feature",
  "properties": {
    "iso:country":"GB",
    "wof:name":"S18 4AF",
    "wof:placetype":"postalcode"
},
  "geometry": {"coordinates":[-1.44860991840921,53.29332964926243],"type":"Point"}
}