{
  "type": "Feature",
  "properties": {
    "iso:country": "GB",
    "wof:name": "S80 4WD",
    "wof:placetype": "postalcode"
  },
  "geometry": {"coordinates":[-1.21791,53.265643],"type":"Point"}
}
