{
  "type": "Feature",
  "properties": {
    "date:inception_lower": "2020-01-01",
    "date:inception_upper": "2020-01-01",
    "iso:country": "GB",
    "wof:name": "S80 4WD",
    "wof:placetype": "postalcode"
  },
  "geometry": {"coordinates":[-1.218265,53.26587],"type":"Point"}
}
