{
  "type": "Feature",
  "properties": {
    "iso:country": "GB",
    "wof:name": "S80 4WD",
    "wof:placetype": "postalcode"
  },
  "geometry": {"coordinates":[-1.218491,53.265827],"type":"Point"}
}
