{
  "type": "Feature",
  "properties": {
    "iso:country":"GB",
    "wof:name":"PH1 3JF",
    "wof:placetype":"postalcode"
},
  "geometry": {"coordinates":[-3.469418564844,56.45120809792962],"type":"Point"}
}