{
  "type": "Feature",
  "properties": {
    "iso:country": "GB",
    "wof:name": "PH1 3JF",
    "wof:placetype": "postalcode"
  },
  "geometry": {"coordinates":[-3.469419,56.451208],"type":"Point"}
}
