{
  "type": "Feature",
  "properties": {
    "iso:country": "GB",
    "wof:name": "CF11 8TW",
    "wof:placetype": "postalcode"
  },
  "geometry": {"coordinates":[-3.196697,51.45352],"type":"Point"}
}
