{
  "type": "Feature",
  "properties": {
    "iso:country": "GB",
    "wof:name": "GU8 5TX",
    "wof:placetype": "postalcode"
  },
  "geometry": {"coordinates":[-0.644986,51.133043],"type":"Point"}
}
