{
  "type": "Feature",
  "properties": {
    "iso:country":"GB",
    "wof:name":"GU8 5TX",
    "wof:placetype":"postalcode"
},
  "geometry": {"coordinates":[-0.64498607078314,51.13304313014623],"type":"Point"}
}