{
  "type": "Feature",
  "properties": {
    "date:inception_lower":"2004-06-01",
    "date:inception_upper":"2004-06-30",
    "iso:country":"GB",
    "wof:name":"GU8 5TX",
    "wof:placetype":"postalcode"
},
  "geometry": {"coordinates":[-0.644986,51.133043],"type":"Point"}
}