{
  "type": "Feature",
  "properties": {
    "date:inception_lower":"2009-03-01",
    "date:inception_upper":"2009-03-31",
    "iso:country":"GB",
    "wof:name":"NE61 9SQ",
    "wof:placetype":"postalcode"
},
  "geometry": {"coordinates":[-1.684509,55.153608],"type":"Point"}
}