{
  "type": "Feature",
  "properties": {
    "iso:country": "GB",
    "wof:name": "NE61 9SQ",
    "wof:placetype": "postalcode"
  },
  "geometry": {"coordinates":[-1.684509,55.153608],"type":"Point"}
}
