{
  "type": "Feature",
  "properties": {
    "date:inception_lower": "1980-01-01",
    "date:inception_upper": "1980-01-01",
    "iso:country": "GB",
    "wof:name": "SG12 7RE",
    "wof:placetype": "postalcode"
  },
  "geometry": {"coordinates":[0.02957,51.824967],"type":"Point"}
}
