{
  "type": "Feature",
  "properties": {
    "iso:country": "GB",
    "wof:name": "KY15 4QW",
    "wof:placetype": "postalcode"
  },
  "geometry": {"coordinates":[-2.994431,56.385304],"type":"Point"}
}
