{
  "type": "Feature",
  "properties": {
    "date:inception_lower": "1980-07-01",
    "date:inception_upper": "1980-07-01",
    "iso:country": "GB",
    "wof:name": "KY15 4QW",
    "wof:placetype": "postalcode"
  },
  "geometry": {"coordinates":[-2.994431,56.385304],"type":"Point"}
}
