{
  "type": "Feature",
  "properties": {
    "date:inception_lower": "1990-02-01",
    "date:inception_upper": "1990-02-01",
    "iso:country": "GB",
    "wof:name": "SK7 1JG",
    "wof:placetype": "postalcode"
  },
  "geometry": {"coordinates":[-2.171467,53.353418],"type":"Point"}
}
