{
  "type": "Feature",
  "properties": {
    "date:inception_lower": "2021-05-01",
    "date:inception_upper": "2021-05-01",
    "iso:country": "GB",
    "wof:name": "PH7 4FE",
    "wof:placetype": "postalcode"
  },
  "geometry": {"coordinates":[-3.855245,56.366352],"type":"Point"}
}
