{
  "type": "Feature",
  "properties": {
    "date:inception_lower": "1994-12-01",
    "date:inception_upper": "1994-12-01",
    "iso:country": "GB",
    "wof:name": "B50 4JF",
    "wof:placetype": "postalcode"
  },
  "geometry": {"coordinates":[-1.849004,52.173516],"type":"Point"}
}
