{
  "type": "Feature",
  "properties": {
    "iso:country":"GB",
    "wof:name":"B50 4JF",
    "wof:placetype":"postalcode"
},
  "geometry": {"coordinates":[-1.84900450363857,52.17351616802042],"type":"Point"}
}