{
  "type": "Feature",
  "properties": {
    "date:inception_lower": "1980-01-01",
    "date:inception_upper": "1980-01-01",
    "iso:country": "GB",
    "wof:name": "LA12 9NY",
    "wof:placetype": "postalcode"
  },
  "geometry": {"coordinates":[-3.094578,54.178392],"type":"Point"}
}
