{
  "type": "Feature",
  "properties": {
    "iso:country":"GB",
    "wof:name":"LA12 9NY",
    "wof:placetype":"postalcode"
},
  "geometry": {"coordinates":[-3.0945778712094,54.17839203653492],"type":"Point"}
}