{
  "type": "Feature",
  "properties": {
    "iso:country":"GB",
    "wof:name":"CB6 3JA",
    "wof:placetype":"postalcode"
},
  "geometry": {"coordinates":[0.2197817197972,52.35081273794333],"type":"Point"}
}