{
  "type": "Feature",
  "properties": {
    "date:inception_lower": "1995-07-01",
    "date:inception_upper": "1995-07-01",
    "iso:country": "GB",
    "wof:name": "CB6 3JA",
    "wof:placetype": "postalcode"
  },
  "geometry": {"coordinates":[0.219782,52.350813],"type":"Point"}
}
