{
  "type": "Feature",
  "properties": {
    "iso:country":"GB",
    "wof:name":"CM7 3EQ",
    "wof:placetype":"postalcode"
},
  "geometry": {"coordinates":[0.57005600467435,51.87899257854427],"type":"Point"}
}