{
  "type": "Feature",
  "properties": {
    "date:inception_lower": "2000-06-01",
    "date:inception_upper": "2000-06-01",
    "iso:country": "GB",
    "wof:name": "CM7 3EQ",
    "wof:placetype": "postalcode"
  },
  "geometry": {"coordinates":[0.570056,51.878993],"type":"Point"}
}
