{
  "type": "Feature",
  "properties": {
    "date:inception_lower": "2017-01-01",
    "date:inception_upper": "2017-01-01",
    "iso:country": "GB",
    "wof:name": "TR11 5FU",
    "wof:placetype": "postalcode"
  },
  "geometry": {"coordinates":[-5.085001,50.144629],"type":"Point"}
}
