{
  "type": "Feature",
  "properties": {
    "iso:country":"GB",
    "wof:name":"FY2 0EJ",
    "wof:placetype":"postalcode"
},
  "geometry": {"coordinates":[-3.02711675235379,53.85692584415626],"type":"Point"}
}