{
  "type": "Feature",
  "properties": {
    "iso:country":"GB",
    "wof:name":"GU35 9DF",
    "wof:placetype":"postalcode"
},
  "geometry": {"coordinates":[-0.86588904063406,51.10036811006915],"type":"Point"}
}