{
  "type": "Feature",
  "properties": {
    "iso:country": "GB",
    "wof:name": "GU35 9DF",
    "wof:placetype": "postalcode"
  },
  "geometry": {"coordinates":[-0.865889,51.100368],"type":"Point"}
}
