{
  "type": "Feature",
  "properties": {
    "iso:country": "GB",
    "wof:name": "BH20 7LN",
    "wof:placetype": "postalcode"
  },
  "geometry": {"coordinates":[-2.21772,50.75113],"type":"Point"}
}
