{
  "type": "Feature",
  "properties": {
    "iso:country":"GB",
    "wof:name":"BD16 4AN",
    "wof:placetype":"postalcode"
},
  "geometry": {"coordinates":[-1.83205649484083,53.85786278474838],"type":"Point"}
}