{
  "type": "Feature",
  "properties": {
    "iso:country":"GB",
    "wof:name":"LE4 2WF",
    "wof:placetype":"postalcode"
},
  "geometry": {"coordinates":[-1.14971501706538,52.68166638869668],"type":"Point"}
}