{
  "type": "Feature",
  "properties": {
    "iso:country":"GB",
    "wof:name":"NR31 9TR",
    "wof:placetype":"postalcode"
},
  "geometry": {"coordinates":[1.72463449268541,52.5384988427997],"type":"Point"}
}