{
  "type": "Feature",
  "properties": {
    "iso:country": "GB",
    "wof:name": "NR31 9TR",
    "wof:placetype": "postalcode"
  },
  "geometry": {"coordinates":[1.724635,52.538499],"type":"Point"}
}
