{
  "type": "Feature",
  "properties": {
    "iso:country":"GB",
    "wof:name":"SK2 5HY",
    "wof:placetype":"postalcode"
},
  "geometry": {"coordinates":[-2.10751130140424,53.39448096829955],"type":"Point"}
}