{
  "type": "Feature",
  "properties": {
    "iso:country":"GB",
    "wof:name":"G67 4BX",
    "wof:placetype":"postalcode"
},
  "geometry": {"coordinates":[-4.02626096429506,55.93560664634911],"type":"Point"}
}