{
  "type": "Feature",
  "properties": {
    "date:inception_lower": "1980-01-01",
    "date:inception_upper": "1980-01-01",
    "iso:country": "GB",
    "wof:name": "G67 4BX",
    "wof:placetype": "postalcode"
  },
  "geometry": {"coordinates":[-4.026024,55.935525],"type":"Point"}
}
