{
  "type": "Feature",
  "properties": {
    "iso:country":"GB",
    "wof:name":"CF23 8PW",
    "wof:placetype":"postalcode"
},
  "geometry": {"coordinates":[-3.13475344438207,51.53703245286523],"type":"Point"}
}