{
  "type": "Feature",
  "properties": {
    "iso:country": "GB",
    "wof:name": "PL7 2GR",
    "wof:placetype": "postalcode"
  },
  "geometry": {"coordinates":[-4.023011,50.390837],"type":"Point"}
}
