{
  "type": "Feature",
  "properties": {
    "date:inception_lower": "1980-01-01",
    "date:inception_upper": "1980-01-01",
    "iso:country": "GB",
    "wof:name": "PE20 3QZ",
    "wof:placetype": "postalcode"
  },
  "geometry": {"coordinates":[-0.136965,52.976286],"type":"Point"}
}
