{
  "type": "Feature",
  "properties": {
    "date:inception_lower": "1980-01-01",
    "date:inception_upper": "1980-01-01",
    "iso:country": "GB",
    "wof:name": "GU12 6DE",
    "wof:placetype": "postalcode"
  },
  "geometry": {"coordinates":[-0.704773,51.25243],"type":"Point"}
}
