{
  "type": "Feature",
  "properties": {
    "iso:country":"GB",
    "wof:name":"DA9 9FW",
    "wof:placetype":"postalcode"
},
  "geometry": {"coordinates":[0.29332994969751,51.45294846762426],"type":"Point"}
}