{
  "type": "Feature",
  "properties": {
    "iso:country":"GB",
    "wof:name":"NW3 3PT",
    "wof:placetype":"postalcode"
},
  "geometry": {"coordinates":[-0.16142696524133,51.54397292261163],"type":"Point"}
}