{
  "type": "Feature",
  "properties": {
    "iso:country":"GB",
    "wof:name":"B93 8LS",
    "wof:placetype":"postalcode"
},
  "geometry": {"coordinates":[-1.74984518184537,52.37465849193421],"type":"Point"}
}