{
  "type": "Feature",
  "properties": {
    "date:inception_lower":"1985-04-01",
    "date:inception_upper":"1985-04-30",
    "iso:country":"GB",
    "wof:name":"B93 8LS",
    "wof:placetype":"postalcode"
},
  "geometry": {"coordinates":[-1.749845,52.374658],"type":"Point"}
}