{
  "type": "Feature",
  "properties": {
    "iso:country":"GB",
    "wof:name":"GL6 6AY",
    "wof:placetype":"postalcode"
},
  "geometry": {"coordinates":[-2.23290420820424,51.76307070594498],"type":"Point"}
}