{
  "type": "Feature",
  "properties": {
    "iso:country": "GB",
    "wof:name": "GL6 6AY",
    "wof:placetype": "postalcode"
  },
  "geometry": {"coordinates":[-2.232904,51.763071],"type":"Point"}
}
