{
  "type": "Feature",
  "properties": {
    "iso:country": "GB",
    "wof:name": "GL53 9NN",
    "wof:placetype": "postalcode"
  },
  "geometry": {"coordinates":[-2.057809,51.830073],"type":"Point"}
}
