{
  "type": "Feature",
  "properties": {
    "date:inception_lower":"1980-01-01",
    "date:inception_upper":"1980-01-31",
    "iso:country":"GB",
    "wof:name":"GL53 9NN",
    "wof:placetype":"postalcode"
},
  "geometry": {"coordinates":[-2.057809,51.830073],"type":"Point"}
}