{
  "type": "Feature",
  "properties": {
    "iso:country":"GB",
    "wof:name":"GL53 9NN",
    "wof:placetype":"postalcode"
},
  "geometry": {"coordinates":[-2.05780925299619,51.83007280456076],"type":"Point"}
}