{
  "type": "Feature",
  "properties": {
    "iso:country":"GB",
    "wof:name":"TN35 4SJ",
    "wof:placetype":"postalcode"
},
  "geometry": {"coordinates":[0.57264127345904,50.90987259139652],"type":"Point"}
}