{
  "type": "Feature",
  "properties": {
    "iso:country":"GB",
    "wof:name":"HG3 1DN",
    "wof:placetype":"postalcode"
},
  "geometry": {"coordinates":[-1.50291391093427,53.96444670660488],"type":"Point"}
}