{
  "type": "Feature",
  "properties": {
    "date:inception_lower": "2018-10-01",
    "date:inception_upper": "2018-10-01",
    "iso:country": "GB",
    "wof:name": "DT9 3QH",
    "wof:placetype": "postalcode"
  },
  "geometry": {"coordinates":[-2.524471,50.948774],"type":"Point"}
}
