{
  "type": "Feature",
  "properties": {
    "iso:country":"GB",
    "wof:name":"B14 6QU",
    "wof:placetype":"postalcode"
},
  "geometry": {"coordinates":[-1.91529018113915,52.41973503162305],"type":"Point"}
}