{
  "type": "Feature",
  "properties": {
    "iso:country": "GB",
    "wof:name": "RG12 2RL",
    "wof:placetype": "postalcode"
  },
  "geometry": {"coordinates":[-0.732317,51.417369],"type":"Point"}
}
