{
  "type": "Feature",
  "properties": {
    "date:inception_lower": "1980-01-01",
    "date:inception_upper": "1980-01-01",
    "iso:country": "GB",
    "wof:name": "B60 4ED",
    "wof:placetype": "postalcode"
  },
  "geometry": {"coordinates":[-2.086119,52.298142],"type":"Point"}
}
