{
  "type": "Feature",
  "properties": {
    "iso:country":"GB",
    "wof:name":"B60 4ED",
    "wof:placetype":"postalcode"
},
  "geometry": {"coordinates":[-2.08660303759426,52.29806064393415],"type":"Point"}
}