{
  "type": "Feature",
  "properties": {
    "iso:country": "GB",
    "wof:name": "BS3 5BS",
    "wof:placetype": "postalcode"
  },
  "geometry": {"coordinates":[-2.578919,51.438301],"type":"Point"}
}
