{
  "type": "Feature",
  "properties": {
    "iso:country":"GB",
    "wof:name":"BS3 5BS",
    "wof:placetype":"postalcode"
},
  "geometry": {"coordinates":[-2.57891880416135,51.43830114361967],"type":"Point"}
}