{
  "type": "Feature",
  "properties": {
    "date:inception_lower":"1980-01-01",
    "date:inception_upper":"1980-01-31",
    "iso:country":"GB",
    "wof:name":"WA3 5EW",
    "wof:placetype":"postalcode"
},
  "geometry": {"coordinates":[-2.510638,53.448977],"type":"Point"}
}