{
  "type": "Feature",
  "properties": {
    "iso:country":"GB",
    "wof:name":"WA3 5EW",
    "wof:placetype":"postalcode"
},
  "geometry": {"coordinates":[-2.51063792630041,53.44897734129245],"type":"Point"}
}