{
  "type": "Feature",
  "properties": {
    "iso:country":"GB",
    "wof:name":"L25 7RT",
    "wof:placetype":"postalcode"
},
  "geometry": {"coordinates":[-2.8737549200215,53.3723371811511],"type":"Point"}
}