{
  "type": "Feature",
  "properties": {
    "date:inception_lower": "1980-01-01",
    "date:inception_upper": "1980-01-01",
    "iso:country": "GB",
    "wof:name": "IV25 3SH",
    "wof:placetype": "postalcode"
  },
  "geometry": {"coordinates":[-4.029532,57.880736],"type":"Point"}
}
