{
  "type": "Feature",
  "properties": {
    "iso:country":"GB",
    "wof:name":"IV25 3SH",
    "wof:placetype":"postalcode"
},
  "geometry": {"coordinates":[-4.02953201944757,57.88073551442115],"type":"Point"}
}