{
  "type": "Feature",
  "properties": {
    "iso:country": "GB",
    "wof:name": "IV25 3SH",
    "wof:placetype": "postalcode"
  },
  "geometry": {"coordinates":[-4.029532,57.880736],"type":"Point"}
}
