{
  "type": "Feature",
  "properties": {
    "date:inception_lower": "1996-06-01",
    "date:inception_upper": "1996-06-01",
    "iso:country": "GB",
    "wof:name": "EX15 2TA",
    "wof:placetype": "postalcode"
  },
  "geometry": {"coordinates":[-3.366404,50.889093],"type":"Point"}
}
