{
  "type": "Feature",
  "properties": {
    "iso:country": "GB",
    "wof:name": "EX15 2TA",
    "wof:placetype": "postalcode"
  },
  "geometry": {"coordinates":[-3.366404,50.889093],"type":"Point"}
}
