{
  "type": "Feature",
  "properties": {
    "iso:country":"GB",
    "wof:name":"BD6 3WN",
    "wof:placetype":"postalcode"
},
  "geometry": {"coordinates":[-1.81236358760477,53.77031803185611],"type":"Point"}
}