{
  "type": "Feature",
  "properties": {
    "date:inception_lower": "2022-12-01",
    "date:inception_upper": "2022-12-01",
    "iso:country": "GB",
    "wof:name": "NR9 3RR",
    "wof:placetype": "postalcode"
  },
  "geometry": {"coordinates":[1.186706,52.606135],"type":"Point"}
}
