{
  "type": "Feature",
  "properties": {
    "iso:country":"GB",
    "wof:name":"NE23 6DQ",
    "wof:placetype":"postalcode"
},
  "geometry": {"coordinates":[-1.58458461479136,55.08365782853051],"type":"Point"}
}