{
  "type": "Feature",
  "properties": {
    "iso:country":"GB",
    "wof:name":"BN1 7GP",
    "wof:placetype":"postalcode"
},
  "geometry": {"coordinates":[-0.13040340389476,50.8424993093828],"type":"Point"}
}