{
  "type": "Feature",
  "properties": {
    "date:inception_lower": "1984-02-01",
    "date:inception_upper": "1984-02-01",
    "iso:country": "GB",
    "wof:name": "WS14 9XA",
    "wof:placetype": "postalcode"
  },
  "geometry": {"coordinates":[-1.79979,52.682514],"type":"Point"}
}
