{
  "type": "Feature",
  "properties": {
    "iso:country":"GB",
    "wof:name":"WS14 9XA",
    "wof:placetype":"postalcode"
},
  "geometry": {"coordinates":[-1.79979030282047,52.68251368710278],"type":"Point"}
}