{
  "type": "Feature",
  "properties": {
    "iso:country":"GB",
    "wof:name":"BN17 6DW",
    "wof:placetype":"postalcode"
},
  "geometry": {"coordinates":[-0.52859827296258,50.81536589142645],"type":"Point"}
}