{
  "type": "Feature",
  "properties": {
    "date:inception_lower":"1985-04-01",
    "date:inception_upper":"1985-04-30",
    "iso:country":"GB",
    "wof:name":"PL2 2BW",
    "wof:placetype":"postalcode"
},
  "geometry": {"coordinates":[-4.171932,50.392666],"type":"Point"}
}