{
  "type": "Feature",
  "properties": {
    "iso:country": "GB",
    "wof:name": "SE2 9XL",
    "wof:placetype": "postalcode"
  },
  "geometry": {"coordinates":[0.120663,51.499518],"type":"Point"}
}
