{
  "type": "Feature",
  "properties": {
    "date:inception_lower": "1980-01-01",
    "date:inception_upper": "1980-01-01",
    "iso:country": "GB",
    "wof:name": "SE2 9XL",
    "wof:placetype": "postalcode"
  },
  "geometry": {"coordinates":[0.120663,51.499518],"type":"Point"}
}
