{
  "type": "Feature",
  "properties": {
    "iso:country":"GB",
    "wof:name":"CW2 5PZ",
    "wof:placetype":"postalcode"
},
  "geometry": {"coordinates":[-2.38027855236396,53.04929841865557],"type":"Point"}
}