{
  "type": "Feature",
  "properties": {
    "date:inception_lower":"1994-12-01",
    "date:inception_upper":"1994-12-31",
    "iso:country":"GB",
    "wof:name":"SO14 6RT",
    "wof:placetype":"postalcode"
},
  "geometry": {"coordinates":[-1.397336,50.918721],"type":"Point"}
}