{
  "type": "Feature",
  "properties": {
    "iso:country":"GB",
    "wof:name":"LE2 8HD",
    "wof:placetype":"postalcode"
},
  "geometry": {"coordinates":[-1.14526702761283,52.60408691505849],"type":"Point"}
}