{
  "type": "Feature",
  "properties": {
    "date:inception_lower": "1991-01-01",
    "date:inception_upper": "1991-01-01",
    "iso:country": "GB",
    "wof:name": "ST1 3SL",
    "wof:placetype": "postalcode"
  },
  "geometry": {"coordinates":[-2.170326,53.021766],"type":"Point"}
}
