{
  "type": "Feature",
  "properties": {
    "iso:country": "GB",
    "wof:name": "NN15 5RD",
    "wof:placetype": "postalcode"
  },
  "geometry": {"coordinates":[-0.68621,52.358875],"type":"Point"}
}
