{
  "type": "Feature",
  "properties": {
    "iso:country":"GB",
    "wof:name":"RM6 6EX",
    "wof:placetype":"postalcode"
},
  "geometry": {"coordinates":[0.1419358402831,51.57029186591905],"type":"Point"}
}