{
  "type": "Feature",
  "properties": {
    "iso:country":"GB",
    "wof:name":"TQ2 8QN",
    "wof:placetype":"postalcode"
},
  "geometry": {"coordinates":[-3.53751939669642,50.49998909312738],"type":"Point"}
}