{
  "type": "Feature",
  "properties": {
    "iso:country":"GB",
    "wof:name":"G11 7JU",
    "wof:placetype":"postalcode"
},
  "geometry": {"coordinates":[-4.31578209727691,55.87590290794826],"type":"Point"}
}