{
  "type": "Feature",
  "properties": {
    "date:inception_lower": "1980-01-01",
    "date:inception_upper": "1980-01-01",
    "iso:country": "GB",
    "wof:name": "G11 7JU",
    "wof:placetype": "postalcode"
  },
  "geometry": {"coordinates":[-4.315782,55.875903],"type":"Point"}
}
