{
  "type": "Feature",
  "properties": {
    "iso:country": "GB",
    "wof:name": "G11 7JU",
    "wof:placetype": "postalcode"
  },
  "geometry": {"coordinates":[-4.315782,55.875903],"type":"Point"}
}
