{
  "type": "Feature",
  "properties": {
    "iso:country":"GB",
    "wof:name":"SA6 6TL",
    "wof:placetype":"postalcode"
},
  "geometry": {"coordinates":[-3.9293067334619,51.68295126647779],"type":"Point"}
}