{
  "type": "Feature",
  "properties": {
    "date:inception_lower": "1980-01-01",
    "date:inception_upper": "1980-01-01",
    "iso:country": "GB",
    "wof:name": "B34 6NB",
    "wof:placetype": "postalcode"
  },
  "geometry": {"coordinates":[-1.79716,52.499513],"type":"Point"}
}
