{
  "type": "Feature",
  "properties": {
    "iso:country":"GB",
    "wof:name":"ST7 4SQ",
    "wof:placetype":"postalcode"
},
  "geometry": {"coordinates":[-2.22731786975012,53.09512010487116],"type":"Point"}
}