{
  "type": "Feature",
  "properties": {
    "date:inception_lower": "1980-01-01",
    "date:inception_upper": "1980-01-01",
    "iso:country": "GB",
    "wof:name": "RG8 9ET",
    "wof:placetype": "postalcode"
  },
  "geometry": {"coordinates":[-1.134624,51.51869],"type":"Point"}
}
