{
  "type": "Feature",
  "properties": {
    "iso:country":"GB",
    "wof:name":"RG8 9ET",
    "wof:placetype":"postalcode"
},
  "geometry": {"coordinates":[-1.13453266115504,51.51851677502704],"type":"Point"}
}