{
  "type": "Feature",
  "properties": {
    "iso:country": "GB",
    "wof:name": "SS17 7HT",
    "wof:placetype": "postalcode"
  },
  "geometry": {"coordinates":[0.448871,51.52173],"type":"Point"}
}
