{
  "type": "Feature",
  "properties": {
    "date:inception_lower":"1980-01-01",
    "date:inception_upper":"1980-01-31",
    "iso:country":"GB",
    "wof:name":"CM21 0AA",
    "wof:placetype":"postalcode"
},
  "geometry": {"coordinates":[0.137487,51.803615],"type":"Point"}
}