{
  "type": "Feature",
  "properties": {
    "iso:country":"GB",
    "wof:name":"CM21 0AA",
    "wof:placetype":"postalcode"
},
  "geometry": {"coordinates":[0.13748743358277,51.80361452624361],"type":"Point"}
}