{
  "type": "Feature",
  "properties": {
    "iso:country": "GB",
    "wof:name": "CM21 0AA",
    "wof:placetype": "postalcode"
  },
  "geometry": {"coordinates":[0.137487,51.803615],"type":"Point"}
}
