{
  "type": "Feature",
  "properties": {
    "date:inception_lower": "1993-08-01",
    "date:inception_upper": "1993-08-01",
    "iso:country": "GB",
    "wof:name": "CT3 2BD",
    "wof:placetype": "postalcode"
  },
  "geometry": {"coordinates":[1.287173,51.2763],"type":"Point"}
}
