{
  "type": "Feature",
  "properties": {
    "iso:country": "GB",
    "wof:name": "CT3 2BD",
    "wof:placetype": "postalcode"
  },
  "geometry": {"coordinates":[1.287173,51.2763],"type":"Point"}
}
