{
  "type": "Feature",
  "properties": {
    "iso:country": "GB",
    "wof:name": "PH1 5HR",
    "wof:placetype": "postalcode"
  },
  "geometry": {"coordinates":[-3.436692,56.403458],"type":"Point"}
}
