{
  "type": "Feature",
  "properties": {
    "iso:country":"GB",
    "wof:name":"PH1 5HR",
    "wof:placetype":"postalcode"
},
  "geometry": {"coordinates":[-3.43669162191814,56.4034578690102],"type":"Point"}
}