{
  "type": "Feature",
  "properties": {
    "date:inception_lower": "1980-01-01",
    "date:inception_upper": "1980-01-01",
    "iso:country": "GB",
    "wof:name": "E9 7HT",
    "wof:placetype": "postalcode"
  },
  "geometry": {"coordinates":[-0.053325,51.53544],"type":"Point"}
}
