{
  "type": "Feature",
  "properties": {
    "iso:country":"GB",
    "wof:name":"EH47 9HP",
    "wof:placetype":"postalcode"
},
  "geometry": {"coordinates":[-3.71006814784425,55.82702225031171],"type":"Point"}
}