{
  "type": "Feature",
  "properties": {
    "date:inception_lower":"1980-01-01",
    "date:inception_upper":"1980-01-31",
    "iso:country":"GB",
    "wof:name":"BA12 6ED",
    "wof:placetype":"postalcode"
},
  "geometry": {"coordinates":[-2.266946,51.093268],"type":"Point"}
}