{
  "type": "Feature",
  "properties": {
    "iso:country":"GB",
    "wof:name":"NW4 1QP",
    "wof:placetype":"postalcode"
},
  "geometry": {"coordinates":[-0.22200845789482,51.59141504613766],"type":"Point"}
}