{
  "type": "Feature",
  "properties": {
    "iso:country": "GB",
    "wof:name": "G4 9NT",
    "wof:placetype": "postalcode"
  },
  "geometry": {"coordinates":[-4.26319,55.868856],"type":"Point"}
}
