{
  "type": "Feature",
  "properties": {
    "date:inception_lower":"1980-01-01",
    "date:inception_upper":"1980-01-31",
    "iso:country":"GB",
    "wof:name":"SA33 4PQ",
    "wof:placetype":"postalcode"
},
  "geometry": {"coordinates":[-4.56597,51.748859],"type":"Point"}
}