{
  "type": "Feature",
  "properties": {
    "iso:country":"GB",
    "wof:name":"SA33 4PQ",
    "wof:placetype":"postalcode"
},
  "geometry": {"coordinates":[-4.56597027511501,51.74885913164103],"type":"Point"}
}