{
  "type": "Feature",
  "properties": {
    "iso:country":"GB",
    "wof:name":"SY25 6AA",
    "wof:placetype":"postalcode"
},
  "geometry": {"coordinates":[-3.89896429782437,52.29094787020922],"type":"Point"}
}