{
  "type": "Feature",
  "properties": {
    "iso:country": "GB",
    "wof:name": "SY25 6AA",
    "wof:placetype": "postalcode"
  },
  "geometry": {"coordinates":[-3.898964,52.290948],"type":"Point"}
}
