{
  "type": "Feature",
  "properties": {
    "iso:country":"GB",
    "wof:name":"SP11 9EN",
    "wof:placetype":"postalcode"
},
  "geometry": {"coordinates":[-1.57328171184938,51.28530547995111],"type":"Point"}
}