{
  "type": "Feature",
  "properties": {
    "iso:country":"GB",
    "wof:name":"RG10 0SJ",
    "wof:placetype":"postalcode"
},
  "geometry": {"coordinates":[-0.85569447546937,51.45059585458552],"type":"Point"}
}