{
  "type": "Feature",
  "properties": {
    "iso:country": "GB",
    "wof:name": "BB5 2TJ",
    "wof:placetype": "postalcode"
  },
  "geometry": {"coordinates":[-2.344686,53.739409],"type":"Point"}
}
