{
  "type": "Feature",
  "properties": {
    "iso:country":"GB",
    "wof:name":"NW9 5GP",
    "wof:placetype":"postalcode"
},
  "geometry": {"coordinates":[-0.24849711857425,51.60424064012425],"type":"Point"}
}