{
  "type": "Feature",
  "properties": {
    "iso:country":"GB",
    "wof:name":"L9 1EJ",
    "wof:placetype":"postalcode"
},
  "geometry": {"coordinates":[-2.97141377338757,53.44781716501604],"type":"Point"}
}