{
  "type": "Feature",
  "properties": {
    "iso:country":"GB",
    "wof:name":"YO26 6NP",
    "wof:placetype":"postalcode"
},
  "geometry": {"coordinates":[-1.14693764689549,53.98247270772571],"type":"Point"}
}