{
  "type": "Feature",
  "properties": {
    "iso:country":"GB",
    "wof:name":"B6 6LP",
    "wof:placetype":"postalcode"
},
  "geometry": {"coordinates":[-1.89600902756645,52.50918802496783],"type":"Point"}
}