{
  "type": "Feature",
  "properties": {
    "iso:country":"GB",
    "wof:name":"RM3 8NH",
    "wof:placetype":"postalcode"
},
  "geometry": {"coordinates":[0.22404012345603,51.60089573109245],"type":"Point"}
}