{
  "type": "Feature",
  "properties": {
    "iso:country":"GB",
    "wof:name":"NP23 5FE",
    "wof:placetype":"postalcode"
},
  "geometry": {"coordinates":[-3.20313033578689,51.78441324415153],"type":"Point"}
}