{
  "type": "Feature",
  "properties": {
    "iso:country":"GB",
    "wof:name":"WF6 2EU",
    "wof:placetype":"postalcode"
},
  "geometry": {"coordinates":[-1.40767678679328,53.70282253650676],"type":"Point"}
}