{
  "type": "Feature",
  "properties": {
    "date:inception_lower":"2002-05-01",
    "date:inception_upper":"2002-05-31",
    "iso:country":"GB",
    "wof:name":"IV15 9SY",
    "wof:placetype":"postalcode"
},
  "geometry": {"coordinates":[-4.436561,57.605549],"type":"Point"}
}