{
  "type": "Feature",
  "properties": {
    "date:inception_lower": "2012-07-01",
    "date:inception_upper": "2012-07-01",
    "iso:country": "GB",
    "wof:name": "DA1 5FQ",
    "wof:placetype": "postalcode"
  },
  "geometry": {"coordinates":[0.225494,51.460992],"type":"Point"}
}
