{
  "type": "Feature",
  "properties": {
    "iso:country":"GB",
    "wof:name":"EH47 7QE",
    "wof:placetype":"postalcode"
},
  "geometry": {"coordinates":[-3.61604208770813,55.87603754169085],"type":"Point"}
}