{
  "type": "Feature",
  "properties": {
    "iso:country": "GB",
    "wof:name": "PH14 9RZ",
    "wof:placetype": "postalcode"
  },
  "geometry": {"coordinates":[-3.167629,56.442905],"type":"Point"}
}
