{
  "type": "Feature",
  "properties": {
    "iso:country":"GB",
    "wof:name":"PH14 9RZ",
    "wof:placetype":"postalcode"
},
  "geometry": {"coordinates":[-3.16762912026003,56.44290509163702],"type":"Point"}
}