{
  "type": "Feature",
  "properties": {
    "iso:country":"GB",
    "wof:name":"SE20 8LH",
    "wof:placetype":"postalcode"
},
  "geometry": {"coordinates":[-0.06042162203733,51.41282535896169],"type":"Point"}
}