{
  "type": "Feature",
  "properties": {
    "iso:country":"GB",
    "wof:name":"S35 2BB",
    "wof:placetype":"postalcode"
},
  "geometry": {"coordinates":[-1.46568178881384,53.46521732962991],"type":"Point"}
}