{
  "type": "Feature",
  "properties": {
    "iso:country": "GB",
    "wof:name": "S35 2BB",
    "wof:placetype": "postalcode"
  },
  "geometry": {"coordinates":[-1.465682,53.465217],"type":"Point"}
}
