{
  "type": "Feature",
  "properties": {
    "date:inception_lower":"1997-06-01",
    "date:inception_upper":"1997-06-30",
    "iso:country":"GB",
    "wof:name":"S35 2BB",
    "wof:placetype":"postalcode"
},
  "geometry": {"coordinates":[-1.465682,53.465217],"type":"Point"}
}