{
  "type": "Feature",
  "properties": {
    "iso:country": "GB",
    "wof:name": "DL1 2LE",
    "wof:placetype": "postalcode"
  },
  "geometry": {"coordinates":[-1.533463,54.53642],"type":"Point"}
}
