{
  "type": "Feature",
  "properties": {
    "iso:country":"GB",
    "wof:name":"DT2 9BE",
    "wof:placetype":"postalcode"
},
  "geometry": {"coordinates":[-2.6573091427658,50.69671887547474],"type":"Point"}
}