{
  "type": "Feature",
  "properties": {
    "iso:country": "GB",
    "wof:name": "L40 8JB",
    "wof:placetype": "postalcode"
  },
  "geometry": {"coordinates":[-2.865099,53.602761],"type":"Point"}
}
