{
  "type": "Feature",
  "properties": {
    "iso:country":"GB",
    "wof:name":"L40 8JB",
    "wof:placetype":"postalcode"
},
  "geometry": {"coordinates":[-2.86510009458573,53.60274524693477],"type":"Point"}
}