{
  "type": "Feature",
  "properties": {
    "iso:country":"GB",
    "wof:name":"HP2 4SA",
    "wof:placetype":"postalcode"
},
  "geometry": {"coordinates":[-0.43081538872548,51.74966571132357],"type":"Point"}
}