{
  "type": "Feature",
  "properties": {
    "iso:country":"GB",
    "wof:name":"WS1 3DG",
    "wof:placetype":"postalcode"
},
  "geometry": {"coordinates":[-1.97780489596922,52.58138404981506],"type":"Point"}
}