{
  "type": "Feature",
  "properties": {
    "iso:country": "GB",
    "wof:name": "WS1 3DG",
    "wof:placetype": "postalcode"
  },
  "geometry": {"coordinates":[-1.977805,52.581384],"type":"Point"}
}
