{
  "type": "Feature",
  "properties": {
    "iso:country":"GB",
    "wof:name":"CH7 5LB",
    "wof:placetype":"postalcode"
},
  "geometry": {"coordinates":[-3.19870409823595,53.15044560187198],"type":"Point"}
}