{
  "type": "Feature",
  "properties": {
    "date:inception_lower": "2012-12-01",
    "date:inception_upper": "2012-12-01",
    "iso:country": "GB",
    "wof:name": "CH7 5LB",
    "wof:placetype": "postalcode"
  },
  "geometry": {"coordinates":[-3.198703,53.150452],"type":"Point"}
}
