{
  "type": "Feature",
  "properties": {
    "iso:country":"GB",
    "wof:name":"PO16 8RL",
    "wof:placetype":"postalcode"
},
  "geometry": {"coordinates":[-1.15877504812541,50.85332750426922],"type":"Point"}
}