{
  "type": "Feature",
  "properties": {
    "iso:country":"GB",
    "wof:name":"S36 6AR",
    "wof:placetype":"postalcode"
},
  "geometry": {"coordinates":[-1.62812936327625,53.52626238637346],"type":"Point"}
}