{
  "type": "Feature",
  "properties": {
    "date:inception_lower": "1997-06-01",
    "date:inception_upper": "1997-06-01",
    "iso:country": "GB",
    "wof:name": "S36 6AR",
    "wof:placetype": "postalcode"
  },
  "geometry": {"coordinates":[-1.628129,53.526262],"type":"Point"}
}
