{
  "type": "Feature",
  "properties": {
    "date:inception_lower": "1981-06-01",
    "date:inception_upper": "1981-06-01",
    "iso:country": "GB",
    "wof:name": "CW12 4JX",
    "wof:placetype": "postalcode"
  },
  "geometry": {"coordinates":[-2.224722,53.164295],"type":"Point"}
}
