{
  "type": "Feature",
  "properties": {
    "iso:country": "GB",
    "wof:name": "CW12 4JX",
    "wof:placetype": "postalcode"
  },
  "geometry": {"coordinates":[-2.224722,53.164295],"type":"Point"}
}
