{
  "type": "Feature",
  "properties": {
    "iso:country":"GB",
    "wof:name":"HD4 7SW",
    "wof:placetype":"postalcode"
},
  "geometry": {"coordinates":[-1.80073937616037,53.61351033925308],"type":"Point"}
}