{
  "type": "Feature",
  "properties": {
    "date:inception_lower": "1980-01-01",
    "date:inception_upper": "1980-01-01",
    "iso:country": "GB",
    "wof:name": "DH6 5LB",
    "wof:placetype": "postalcode"
  },
  "geometry": {"coordinates":[-1.538544,54.708471],"type":"Point"}
}
