{
  "type": "Feature",
  "properties": {
    "iso:country":"GB",
    "wof:name":"DH6 5LB",
    "wof:placetype":"postalcode"
},
  "geometry": {"coordinates":[-1.53854430961843,54.70847144987599],"type":"Point"}
}