{
  "type": "Feature",
  "properties": {
    "iso:country":"GB",
    "wof:name":"DL6 1HB",
    "wof:placetype":"postalcode"
},
  "geometry": {"coordinates":[-1.42224971305354,54.33966746203668],"type":"Point"}
}