{
  "type": "Feature",
  "properties": {
    "iso:country": "GB",
    "wof:name": "DL6 1HB",
    "wof:placetype": "postalcode"
  },
  "geometry": {"coordinates":[-1.42225,54.339667],"type":"Point"}
}
