{
  "type": "Feature",
  "properties": {
    "iso:country":"GB",
    "wof:name":"LL24 0SR",
    "wof:placetype":"postalcode"
},
  "geometry": {"coordinates":[-3.89239467213725,53.09718909558055],"type":"Point"}
}