{
  "type": "Feature",
  "properties": {
    "date:inception_lower": "1980-01-01",
    "date:inception_upper": "1980-01-01",
    "iso:country": "GB",
    "wof:name": "PL22 0LN",
    "wof:placetype": "postalcode"
  },
  "geometry": {"coordinates":[-4.630625,50.436675],"type":"Point"}
}
