{
  "type": "Feature",
  "properties": {
    "iso:country":"GB",
    "wof:name":"PL22 0LN",
    "wof:placetype":"postalcode"
},
  "geometry": {"coordinates":[-4.63062537065147,50.43667491373879],"type":"Point"}
}