{
  "type": "Feature",
  "properties": {
    "date:inception_lower": "1980-01-01",
    "date:inception_upper": "1980-01-01",
    "iso:country": "GB",
    "wof:name": "MK41 9ND",
    "wof:placetype": "postalcode"
  },
  "geometry": {"coordinates":[-0.437814,52.144744],"type":"Point"}
}
