{
  "type": "Feature",
  "properties": {
    "iso:country":"GB",
    "wof:name":"TD15 1HQ",
    "wof:placetype":"postalcode"
},
  "geometry": {"coordinates":[-2.00254022167406,55.76738185123346],"type":"Point"}
}