{
  "type": "Feature",
  "properties": {
    "iso:country":"GB",
    "wof:name":"SE11 6HX",
    "wof:placetype":"postalcode"
},
  "geometry": {"coordinates":[-0.11528250964837,51.49042754977398],"type":"Point"}
}