{
  "type": "Feature",
  "properties": {
    "date:inception_lower": "1980-01-01",
    "date:inception_upper": "1980-01-01",
    "iso:country": "GB",
    "wof:name": "SE11 6HX",
    "wof:placetype": "postalcode"
  },
  "geometry": {"coordinates":[-0.115282,51.490428],"type":"Point"}
}
