{
  "type": "Feature",
  "properties": {
    "iso:country":"GB",
    "wof:name":"BB1 4EL",
    "wof:placetype":"postalcode"
},
  "geometry": {"coordinates":[-2.42155671239488,53.76869778066936],"type":"Point"}
}