{
  "type": "Feature",
  "properties": {
    "date:inception_lower":"1980-01-01",
    "date:inception_upper":"1980-01-31",
    "iso:country":"GB",
    "wof:name":"CW4 8PL",
    "wof:placetype":"postalcode"
},
  "geometry": {"coordinates":[-2.32219,53.223208],"type":"Point"}
}