{
  "type": "Feature",
  "properties": {
    "iso:country":"GB",
    "wof:name":"CW4 8PL",
    "wof:placetype":"postalcode"
},
  "geometry": {"coordinates":[-2.32258337926799,53.22351391710097],"type":"Point"}
}