{
  "type": "Feature",
  "properties": {
    "iso:country": "GB",
    "wof:name": "TR2 4QP",
    "wof:placetype": "postalcode"
  },
  "geometry": {"coordinates":[-4.899169,50.298354],"type":"Point"}
}
