{
  "type": "Feature",
  "properties": {
    "iso:country":"GB",
    "wof:name":"TR2 4QP",
    "wof:placetype":"postalcode"
},
  "geometry": {"coordinates":[-4.89916862927508,50.29835369264246],"type":"Point"}
}