{
  "type": "Feature",
  "properties": {
    "date:inception_lower": "1980-01-01",
    "date:inception_upper": "1980-01-01",
    "iso:country": "GB",
    "wof:name": "LU4 8RT",
    "wof:placetype": "postalcode"
  },
  "geometry": {"coordinates":[-0.457184,51.892318],"type":"Point"}
}
