{
  "type": "Feature",
  "properties": {
    "date:inception_lower":"2011-09-01",
    "date:inception_upper":"2011-09-30",
    "iso:country":"GB",
    "wof:name":"CV4 9ZG",
    "wof:placetype":"postalcode"
},
  "geometry": {"coordinates":[-1.599731,52.412688],"type":"Point"}
}