{
  "type": "Feature",
  "properties": {
    "iso:country":"GB",
    "wof:name":"SW15 4BQ",
    "wof:placetype":"postalcode"
},
  "geometry": {"coordinates":[-0.23898399491104,51.44497812354298],"type":"Point"}
}