{
  "type": "Feature",
  "properties": {
    "iso:country": "GB",
    "wof:name": "PR2 9SH",
    "wof:placetype": "postalcode"
  },
  "geometry": {"coordinates":[-2.712571,53.797099],"type":"Point"}
}
