{
  "type": "Feature",
  "properties": {
    "iso:country":"GB",
    "wof:name":"M40 8NP",
    "wof:placetype":"postalcode"
},
  "geometry": {"coordinates":[-2.20574514174148,53.50169257576204],"type":"Point"}
}