{
  "type": "Feature",
  "properties": {
    "date:inception_lower":"1980-01-01",
    "date:inception_upper":"1980-01-31",
    "iso:country":"GB",
    "wof:name":"NE62 5NU",
    "wof:placetype":"postalcode"
},
  "geometry": {"coordinates":[-1.606168,55.160461],"type":"Point"}
}