{
  "type": "Feature",
  "properties": {
    "iso:country": "GB",
    "wof:name": "NE62 5NU",
    "wof:placetype": "postalcode"
  },
  "geometry": {"coordinates":[-1.606168,55.160461],"type":"Point"}
}
