{
  "type": "Feature",
  "properties": {
    "iso:country":"GB",
    "wof:name":"NE62 5NU",
    "wof:placetype":"postalcode"
},
  "geometry": {"coordinates":[-1.60616835704079,55.16046132783528],"type":"Point"}
}