{
  "type": "Feature",
  "properties": {
    "iso:country": "GB",
    "wof:name": "SS17 8HN",
    "wof:placetype": "postalcode"
  },
  "geometry": {"coordinates":[0.440793,51.530793],"type":"Point"}
}
