{
  "type": "Feature",
  "properties": {
    "iso:country":"GB",
    "wof:name":"ST4 8BT",
    "wof:placetype":"postalcode"
},
  "geometry": {"coordinates":[-2.18279033106996,52.96562757772583],"type":"Point"}
}