{
  "type": "Feature",
  "properties": {
    "iso:country": "GB",
    "wof:name": "NP19 7GG",
    "wof:placetype": "postalcode"
  },
  "geometry": {"coordinates":[-2.980184,51.597204],"type":"Point"}
}
