{
  "type": "Feature",
  "properties": {
    "date:inception_lower":"1999-06-01",
    "date:inception_upper":"1999-06-30",
    "iso:country":"GB",
    "wof:name":"NP19 4YH",
    "wof:placetype":"postalcode"
},
  "geometry": {"coordinates":[-2.966564,51.570414],"type":"Point"}
}