{
  "type": "Feature",
  "properties": {
    "iso:country":"GB",
    "wof:name":"S3 7JF",
    "wof:placetype":"postalcode"
},
  "geometry": {"coordinates":[-1.48189888302099,53.38767194985397],"type":"Point"}
}