{
  "type": "Feature",
  "properties": {
    "iso:country":"GB",
    "wof:name":"BR3 1JF",
    "wof:placetype":"postalcode"
},
  "geometry": {"coordinates":[-0.04578489611608,51.41141313415787],"type":"Point"}
}