{
  "type": "Feature",
  "properties": {
    "date:inception_lower": "1980-01-01",
    "date:inception_upper": "1980-01-01",
    "iso:country": "GB",
    "wof:name": "BR3 1JF",
    "wof:placetype": "postalcode"
  },
  "geometry": {"coordinates":[-0.045759,51.411412],"type":"Point"}
}
