{
  "type": "Feature",
  "properties": {
    "iso:country":"GB",
    "wof:name":"UB2 4QA",
    "wof:placetype":"postalcode"
},
  "geometry": {"coordinates":[-0.36964465998694,51.49998565096082],"type":"Point"}
}