{
  "type": "Feature",
  "properties": {
    "iso:country": "GB",
    "wof:name": "TA4 1EH",
    "wof:placetype": "postalcode"
  },
  "geometry": {"coordinates":[-3.146202,51.00657],"type":"Point"}
}
