{
  "type": "Feature",
  "properties": {
    "iso:country":"GB",
    "wof:name":"TA4 1EH",
    "wof:placetype":"postalcode"
},
  "geometry": {"coordinates":[-3.14620220997616,51.00656982834682],"type":"Point"}
}