{
  "type": "Feature",
  "properties": {
    "date:inception_lower": "1980-01-01",
    "date:inception_upper": "1980-01-01",
    "iso:country": "GB",
    "wof:name": "NN16 8JB",
    "wof:placetype": "postalcode"
  },
  "geometry": {"coordinates":[-0.726613,52.400567],"type":"Point"}
}
