{
  "type": "Feature",
  "properties": {
    "iso:country":"GB",
    "wof:name":"S36 9QY",
    "wof:placetype":"postalcode"
},
  "geometry": {"coordinates":[-1.64941783225395,53.52940967558216],"type":"Point"}
}