{
  "type": "Feature",
  "properties": {
    "iso:country":"GB",
    "wof:name":"LL31 9DL",
    "wof:placetype":"postalcode"
},
  "geometry": {"coordinates":[-3.83615758469165,53.29778676521943],"type":"Point"}
}