{
  "type": "Feature",
  "properties": {
    "date:inception_lower": "1987-04-01",
    "date:inception_upper": "1987-04-01",
    "iso:country": "GB",
    "wof:name": "LL31 9DL",
    "wof:placetype": "postalcode"
  },
  "geometry": {"coordinates":[-3.836192,53.297821],"type":"Point"}
}
