{
  "type": "Feature",
  "properties": {
    "iso:country":"GB",
    "wof:name":"B46 1JT",
    "wof:placetype":"postalcode"
},
  "geometry": {"coordinates":[-1.71034314951925,52.51208906976761],"type":"Point"}
}