{
  "type": "Feature",
  "properties": {
    "iso:country":"GB",
    "wof:name":"EX32 9FA",
    "wof:placetype":"postalcode"
},
  "geometry": {"coordinates":[-4.03997168244305,51.06639713507182],"type":"Point"}
}