{
  "type": "Feature",
  "properties": {
    "date:inception_lower":"2013-01-01",
    "date:inception_upper":"2013-01-31",
    "iso:country":"GB",
    "wof:name":"EX32 9FA",
    "wof:placetype":"postalcode"
},
  "geometry": {"coordinates":[-4.039972,51.066397],"type":"Point"}
}