{
  "type": "Feature",
  "properties": {
    "iso:country": "GB",
    "wof:name": "CH8 7TJ",
    "wof:placetype": "postalcode"
  },
  "geometry": {"coordinates":[-3.221251,53.274055],"type":"Point"}
}
