{
  "type": "Feature",
  "properties": {
    "iso:country":"GB",
    "wof:name":"CH8 7TJ",
    "wof:placetype":"postalcode"
},
  "geometry": {"coordinates":[-3.22125089004205,53.27405468441583],"type":"Point"}
}