{
  "type": "Feature",
  "properties": {
    "date:inception_lower":"1985-10-01",
    "date:inception_upper":"1985-10-31",
    "iso:country":"GB",
    "wof:name":"CH8 7TJ",
    "wof:placetype":"postalcode"
},
  "geometry": {"coordinates":[-3.221251,53.274055],"type":"Point"}
}