{
  "type": "Feature",
  "properties": {
    "iso:country": "GB",
    "wof:name": "IP19 8QP",
    "wof:placetype": "postalcode"
  },
  "geometry": {"coordinates":[1.518768,52.363631],"type":"Point"}
}
