{
  "type": "Feature",
  "properties": {
    "iso:country":"GB",
    "wof:name":"IP19 8QP",
    "wof:placetype":"postalcode"
},
  "geometry": {"coordinates":[1.51876839415988,52.36363134249141],"type":"Point"}
}