{
  "type": "Feature",
  "properties": {
    "date:inception_lower": "1980-01-01",
    "date:inception_upper": "1980-01-01",
    "iso:country": "GB",
    "wof:name": "N8 9LB",
    "wof:placetype": "postalcode"
  },
  "geometry": {"coordinates":[-0.11391,51.578424],"type":"Point"}
}
