{
  "type": "Feature",
  "properties": {
    "iso:country":"GB",
    "wof:name":"LN6 5AT",
    "wof:placetype":"postalcode"
},
  "geometry": {"coordinates":[-0.61757195856082,53.23977657659517],"type":"Point"}
}