{
  "type": "Feature",
  "properties": {
    "date:inception_lower": "1993-01-01",
    "date:inception_upper": "1993-01-01",
    "iso:country": "GB",
    "wof:name": "LN6 5AT",
    "wof:placetype": "postalcode"
  },
  "geometry": {"coordinates":[-0.617572,53.239777],"type":"Point"}
}
