{
  "type": "Feature",
  "properties": {
    "iso:country":"GB",
    "wof:name":"CM13 3AA",
    "wof:placetype":"postalcode"
},
  "geometry": {"coordinates":[0.29447527320095,51.60306492747151],"type":"Point"}
}