{
  "type": "Feature",
  "properties": {
    "date:inception_lower":"1980-01-01",
    "date:inception_upper":"1980-01-31",
    "iso:country":"GB",
    "wof:name":"NP44 2EF",
    "wof:placetype":"postalcode"
},
  "geometry": {"coordinates":[-3.006631,51.658438],"type":"Point"}
}