{
  "type": "Feature",
  "properties": {
    "iso:country":"GB",
    "wof:name":"NP44 2EF",
    "wof:placetype":"postalcode"
},
  "geometry": {"coordinates":[-3.00663097846478,51.65843804030481],"type":"Point"}
}