{
  "type": "Feature",
  "properties": {
    "iso:country":"GB",
    "wof:name":"RG24 9PG",
    "wof:placetype":"postalcode"
},
  "geometry": {"coordinates":[-1.08118181079638,51.28726290654366],"type":"Point"}
}