{
  "type": "Feature",
  "properties": {
    "date:inception_lower": "1980-01-01",
    "date:inception_upper": "1980-01-01",
    "iso:country": "GB",
    "wof:name": "EH37 5UQ",
    "wof:placetype": "postalcode"
  },
  "geometry": {"coordinates":[-2.958585,55.882133],"type":"Point"}
}
