{
  "type": "Feature",
  "properties": {
    "iso:country":"GB",
    "wof:name":"EH37 5UQ",
    "wof:placetype":"postalcode"
},
  "geometry": {"coordinates":[-2.95858511782856,55.88213258716191],"type":"Point"}
}