{
  "type": "Feature",
  "properties": {
    "iso:country":"GB",
    "wof:name":"SA1 8SB",
    "wof:placetype":"postalcode"
},
  "geometry": {"coordinates":[-3.91513285556581,51.61066867896904],"type":"Point"}
}