{
  "type": "Feature",
  "properties": {
    "iso:country": "GB",
    "wof:name": "SA1 8SB",
    "wof:placetype": "postalcode"
  },
  "geometry": {"coordinates":[-3.915151,51.610673],"type":"Point"}
}
