{
  "type": "Feature",
  "properties": {
    "iso:country":"GB",
    "wof:name":"PO2 9DE",
    "wof:placetype":"postalcode"
},
  "geometry": {"coordinates":[-1.07901293209158,50.81762687762986],"type":"Point"}
}