{
  "type": "Feature",
  "properties": {
    "iso:country":"GB",
    "wof:name":"G69 6PN",
    "wof:placetype":"postalcode"
},
  "geometry": {"coordinates":[-4.12136334365407,55.85530493818732],"type":"Point"}
}