{
  "type": "Feature",
  "properties": {
    "date:inception_lower": "1990-07-01",
    "date:inception_upper": "1990-07-01",
    "iso:country": "GB",
    "wof:name": "CM16 7HS",
    "wof:placetype": "postalcode"
  },
  "geometry": {"coordinates":[0.102646,51.671068],"type":"Point"}
}
