{
  "type": "Feature",
  "properties": {
    "iso:country": "GB",
    "wof:name": "CM16 7HS",
    "wof:placetype": "postalcode"
  },
  "geometry": {"coordinates":[0.10266,51.67101],"type":"Point"}
}
