{
  "type": "Feature",
  "properties": {
    "iso:country": "GB",
    "wof:name": "OX5 2AH",
    "wof:placetype": "postalcode"
  },
  "geometry": {"coordinates":[-1.284791,51.826512],"type":"Point"}
}
