{
  "type": "Feature",
  "properties": {
    "iso:country":"GB",
    "wof:name":"OX5 2AH",
    "wof:placetype":"postalcode"
},
  "geometry": {"coordinates":[-1.28479063292783,51.82651167901796],"type":"Point"}
}