{
  "type": "Feature",
  "properties": {
    "iso:country":"GB",
    "wof:name":"CV2 4GU",
    "wof:placetype":"postalcode"
},
  "geometry": {"coordinates":[-1.49051831572003,52.41340051934754],"type":"Point"}
}