{
  "type": "Feature",
  "properties": {
    "iso:country": "GB",
    "wof:name": "LE10 3DE",
    "wof:placetype": "postalcode"
  },
  "geometry": {"coordinates":[-1.410099,52.534815],"type":"Point"}
}
