{
  "type": "Feature",
  "properties": {
    "iso:country":"GB",
    "wof:name":"SA17 4AA",
    "wof:placetype":"postalcode"
},
  "geometry": {"coordinates":[-4.24199400484237,51.72005826630256],"type":"Point"}
}