{
  "type": "Feature",
  "properties": {
    "iso:country": "GB",
    "wof:name": "SA17 4AA",
    "wof:placetype": "postalcode"
  },
  "geometry": {"coordinates":[-4.241966,51.720077],"type":"Point"}
}
