{
  "type": "Feature",
  "properties": {
    "iso:country": "GB",
    "wof:name": "NN18 8TT",
    "wof:placetype": "postalcode"
  },
  "geometry": {"coordinates":[-0.669045,52.475075],"type":"Point"}
}
