{
  "type": "Feature",
  "properties": {
    "iso:country":"GB",
    "wof:name":"KY1 3LA",
    "wof:placetype":"postalcode"
},
  "geometry": {"coordinates":[-3.14042554192523,56.12984423794886],"type":"Point"}
}