{
  "type": "Feature",
  "properties": {
    "date:inception_lower":"1980-01-01",
    "date:inception_upper":"1980-01-31",
    "iso:country":"GB",
    "wof:name":"PL20 7SD",
    "wof:placetype":"postalcode"
},
  "geometry": {"coordinates":[-4.101268,50.508245],"type":"Point"}
}