{
  "type": "Feature",
  "properties": {
    "iso:country":"GB",
    "wof:name":"SP5 3PH",
    "wof:placetype":"postalcode"
},
  "geometry": {"coordinates":[-1.74460492900108,50.99197117177297],"type":"Point"}
}