{
  "type": "Feature",
  "properties": {
    "date:inception_lower":"2005-04-01",
    "date:inception_upper":"2005-04-30",
    "iso:country":"GB",
    "wof:name":"LL36 9DJ",
    "wof:placetype":"postalcode"
},
  "geometry": {"coordinates":[-4.086039,52.586678],"type":"Point"}
}