{
  "type": "Feature",
  "properties": {
    "iso:country":"GB",
    "wof:name":"LL36 9DJ",
    "wof:placetype":"postalcode"
},
  "geometry": {"coordinates":[-4.08603862402512,52.58667827319623],"type":"Point"}
}