{
  "type": "Feature",
  "properties": {
    "iso:country":"GB",
    "wof:name":"S62 5AA",
    "wof:placetype":"postalcode"
},
  "geometry": {"coordinates":[-1.34294583692124,53.46146871641799],"type":"Point"}
}