{
  "type": "Feature",
  "properties": {
    "iso:country": "GB",
    "wof:name": "SL9 0RQ",
    "wof:placetype": "postalcode"
  },
  "geometry": {"coordinates":[-0.542846,51.62016],"type":"Point"}
}
