{
  "type": "Feature",
  "properties": {
    "iso:country":"GB",
    "wof:name":"SL9 0RQ",
    "wof:placetype":"postalcode"
},
  "geometry": {"coordinates":[-0.54284620466826,51.62015970739218],"type":"Point"}
}