{
  "type": "Feature",
  "properties": {
    "iso:country":"GB",
    "wof:name":"NW10 1PH",
    "wof:placetype":"postalcode"
},
  "geometry": {"coordinates":[-0.2501311825868,51.55458259738259],"type":"Point"}
}