{
  "type": "Feature",
  "properties": {
    "iso:country":"GB",
    "wof:name":"BN2 7AX",
    "wof:placetype":"postalcode"
},
  "geometry": {"coordinates":[-0.06925670705613,50.8155841381792],"type":"Point"}
}