{
  "type": "Feature",
  "properties": {
    "iso:country":"GB",
    "wof:name":"GU8 5YZ",
    "wof:placetype":"postalcode"
},
  "geometry": {"coordinates":[-0.60594612835686,51.18594614610993],"type":"Point"}
}