{
  "type": "Feature",
  "properties": {
    "date:inception_lower": "1980-01-01",
    "date:inception_upper": "1980-01-01",
    "iso:country": "GB",
    "wof:name": "RH17 7DR",
    "wof:placetype": "postalcode"
  },
  "geometry": {"coordinates":[-0.031388,51.033861],"type":"Point"}
}
