{
  "type": "Feature",
  "properties": {
    "date:inception_lower":"1980-01-01",
    "date:inception_upper":"1980-01-31",
    "iso:country":"GB",
    "wof:name":"BA20 2EZ",
    "wof:placetype":"postalcode"
},
  "geometry": {"coordinates":[-2.662849,50.943526],"type":"Point"}
}