{
  "type": "Feature",
  "properties": {
    "iso:country":"GB",
    "wof:name":"GU24 9RJ",
    "wof:placetype":"postalcode"
},
  "geometry": {"coordinates":[-0.65179249796328,51.34123301229045],"type":"Point"}
}