{
  "type": "Feature",
  "properties": {
    "iso:country": "GB",
    "wof:name": "NR29 4SW",
    "wof:placetype": "postalcode"
  },
  "geometry": {"coordinates":[1.63212,52.700337],"type":"Point"}
}
