{
  "type": "Feature",
  "properties": {
    "date:inception_lower":"1980-01-01",
    "date:inception_upper":"1980-01-31",
    "iso:country":"GB",
    "wof:name":"NR29 4SW",
    "wof:placetype":"postalcode"
},
  "geometry": {"coordinates":[1.63212,52.700337],"type":"Point"}
}