{
  "type": "Feature",
  "properties": {
    "iso:country":"GB",
    "wof:name":"CT10 2PB",
    "wof:placetype":"postalcode"
},
  "geometry": {"coordinates":[1.40529217293678,51.36039246627994],"type":"Point"}
}