{
  "type": "Feature",
  "properties": {
    "date:inception_lower":"2007-11-01",
    "date:inception_upper":"2007-11-30",
    "iso:country":"GB",
    "wof:name":"G45 0AH",
    "wof:placetype":"postalcode"
},
  "geometry": {"coordinates":[-4.22171,55.807239],"type":"Point"}
}