{
  "type": "Feature",
  "properties": {
    "iso:country":"GB",
    "wof:name":"G45 0AH",
    "wof:placetype":"postalcode"
},
  "geometry": {"coordinates":[-4.2217104482774,55.80723919966327],"type":"Point"}
}