{
  "type": "Feature",
  "properties": {
    "iso:country":"GB",
    "wof:name":"ME1 1NH",
    "wof:placetype":"postalcode"
},
  "geometry": {"coordinates":[0.50661809002858,51.38873801904822],"type":"Point"}
}