{
  "type": "Feature",
  "properties": {
    "date:inception_lower": "2016-05-01",
    "date:inception_upper": "2016-05-01",
    "iso:country": "GB",
    "wof:name": "PA76 6SG",
    "wof:placetype": "postalcode"
  },
  "geometry": {"coordinates":[-6.394708,56.332807],"type":"Point"}
}
