{
  "type": "Feature",
  "properties": {
    "iso:country":"GB",
    "wof:name":"DE56 1BD",
    "wof:placetype":"postalcode"
},
  "geometry": {"coordinates":[-1.48479498767553,53.02596004891402],"type":"Point"}
}