{
  "type": "Feature",
  "properties": {
    "iso:country": "GB",
    "wof:name": "DE56 1BD",
    "wof:placetype": "postalcode"
  },
  "geometry": {"coordinates":[-1.484795,53.02596],"type":"Point"}
}
