{
  "type": "Feature",
  "properties": {
    "iso:country":"GB",
    "wof:name":"BD8 0AB",
    "wof:placetype":"postalcode"
},
  "geometry": {"coordinates":[-1.80461015321583,53.80316574715207],"type":"Point"}
}