{
  "type": "Feature",
  "properties": {
    "iso:country": "GB",
    "wof:name": "BD8 0AB",
    "wof:placetype": "postalcode"
  },
  "geometry": {"coordinates":[-1.80461,53.803166],"type":"Point"}
}
