{
  "type": "Feature",
  "properties": {
    "iso:country": "GB",
    "wof:name": "DH8 8TZ",
    "wof:placetype": "postalcode"
  },
  "geometry": {"coordinates":[-1.854124,54.856667],"type":"Point"}
}
