{
  "type": "Feature",
  "properties": {
    "iso:country":"GB",
    "wof:name":"DH8 8TZ",
    "wof:placetype":"postalcode"
},
  "geometry": {"coordinates":[-1.85412379770711,54.85666661188613],"type":"Point"}
}