{
  "type": "Feature",
  "properties": {
    "date:inception_lower":"1980-01-01",
    "date:inception_upper":"1980-01-31",
    "iso:country":"GB",
    "wof:name":"CT6 6RD",
    "wof:placetype":"postalcode"
},
  "geometry": {"coordinates":[1.169822,51.372862],"type":"Point"}
}