{
  "type": "Feature",
  "properties": {
    "iso:country": "GB",
    "wof:name": "LA23 2EW",
    "wof:placetype": "postalcode"
  },
  "geometry": {"coordinates":[-2.90975,54.370539],"type":"Point"}
}
