{
  "type": "Feature",
  "properties": {
    "date:inception_lower": "1980-01-01",
    "date:inception_upper": "1980-01-01",
    "iso:country": "GB",
    "wof:name": "PL2 1EL",
    "wof:placetype": "postalcode"
  },
  "geometry": {"coordinates":[-4.1663,50.381159],"type":"Point"}
}
