{
  "type": "Feature",
  "properties": {
    "iso:country":"GB",
    "wof:name":"PL2 1EL",
    "wof:placetype":"postalcode"
},
  "geometry": {"coordinates":[-4.16630041524821,50.38115930700113],"type":"Point"}
}