{
  "type": "Feature",
  "properties": {
    "iso:country":"GB",
    "wof:name":"SA3 4BB",
    "wof:placetype":"postalcode"
},
  "geometry": {"coordinates":[-4.00032607133822,51.57503962526406],"type":"Point"}
}