{
  "type": "Feature",
  "properties": {
    "iso:country":"GB",
    "wof:name":"CV31 3LZ",
    "wof:placetype":"postalcode"
},
  "geometry": {"coordinates":[-1.54395309440139,52.27848635199804],"type":"Point"}
}