{
  "type": "Feature",
  "properties": {
    "iso:country": "GB",
    "wof:name": "PE13 4PY",
    "wof:placetype": "postalcode"
  },
  "geometry": {"coordinates":[0.049846,52.684821],"type":"Point"}
}
