{
  "type": "Feature",
  "properties": {
    "date:inception_lower": "1988-03-01",
    "date:inception_upper": "1988-03-01",
    "iso:country": "GB",
    "wof:name": "SL1 9JY",
    "wof:placetype": "postalcode"
  },
  "geometry": {"coordinates":[-0.621731,51.506114],"type":"Point"}
}
