{
  "type": "Feature",
  "properties": {
    "iso:country":"GB",
    "wof:name":"TF9 3NP",
    "wof:placetype":"postalcode"
},
  "geometry": {"coordinates":[-2.5744911156402,52.85291018322067],"type":"Point"}
}