{
  "type": "Feature",
  "properties": {
    "iso:country":"GB",
    "wof:name":"KY15 4HD",
    "wof:placetype":"postalcode"
},
  "geometry": {"coordinates":[-3.00642318466216,56.32294366017808],"type":"Point"}
}