{
  "type": "Feature",
  "properties": {
    "iso:country": "GB",
    "wof:name": "PA11 3DS",
    "wof:placetype": "postalcode"
  },
  "geometry": {"coordinates":[-4.577262,55.853248],"type":"Point"}
}
