{
  "type": "Feature",
  "properties": {
    "iso:country":"GB",
    "wof:name":"HU3 1RG",
    "wof:placetype":"postalcode"
},
  "geometry": {"coordinates":[-0.35249720116502,53.75168572288901],"type":"Point"}
}