{
  "type": "Feature",
  "properties": {
    "iso:country":"GB",
    "wof:name":"GU27 2LP",
    "wof:placetype":"postalcode"
},
  "geometry": {"coordinates":[-0.70196798367632,51.09640629802047],"type":"Point"}
}