{
  "type": "Feature",
  "properties": {
    "date:inception_lower": "1996-06-01",
    "date:inception_upper": "1996-06-01",
    "iso:country": "GB",
    "wof:name": "GU27 2LP",
    "wof:placetype": "postalcode"
  },
  "geometry": {"coordinates":[-0.701968,51.096406],"type":"Point"}
}
