{
  "type": "Feature",
  "properties": {
    "iso:country":"GB",
    "wof:name":"SE25 4DW",
    "wof:placetype":"postalcode"
},
  "geometry": {"coordinates":[-0.07223790585217,51.40677937988208],"type":"Point"}
}