{
  "type": "Feature",
  "properties": {
    "date:inception_lower": "2016-06-01",
    "date:inception_upper": "2016-06-01",
    "iso:country": "GB",
    "wof:name": "SE27 0DD",
    "wof:placetype": "postalcode"
  },
  "geometry": {"coordinates":[-0.105694,51.428413],"type":"Point"}
}
