{
  "type": "Feature",
  "properties": {
    "date:inception_lower": "1980-01-01",
    "date:inception_upper": "1980-01-01",
    "iso:country": "GB",
    "wof:name": "S65 3PG",
    "wof:placetype": "postalcode"
  },
  "geometry": {"coordinates":[-1.319711,53.435676],"type":"Point"}
}
