{
  "type": "Feature",
  "properties": {
    "iso:country":"GB",
    "wof:name":"S65 3PG",
    "wof:placetype":"postalcode"
},
  "geometry": {"coordinates":[-1.31971095508637,53.4356760980729],"type":"Point"}
}