{
  "type": "Feature",
  "properties": {
    "iso:country":"GB",
    "wof:name":"PL12 4EY",
    "wof:placetype":"postalcode"
},
  "geometry": {"coordinates":[-4.22634584583277,50.40839337684768],"type":"Point"}
}