{
  "type": "Feature",
  "properties": {
    "iso:country": "GB",
    "wof:name": "TN23 7XA",
    "wof:placetype": "postalcode"
  },
  "geometry": {"coordinates":[0.865731,51.142549],"type":"Point"}
}
