{
  "type": "Feature",
  "properties": {
    "iso:country":"GB",
    "wof:name":"TN23 7XA",
    "wof:placetype":"postalcode"
},
  "geometry": {"coordinates":[0.86573047621525,51.14254909913682],"type":"Point"}
}