{
  "type": "Feature",
  "properties": {
    "iso:country":"GB",
    "wof:name":"CF33 6LL",
    "wof:placetype":"postalcode"
},
  "geometry": {"coordinates":[-3.68873591633302,51.5306970053074],"type":"Point"}
}