{
  "type": "Feature",
  "properties": {
    "date:inception_lower":"1980-01-01",
    "date:inception_upper":"1980-01-31",
    "iso:country":"GB",
    "wof:name":"CF33 6LL",
    "wof:placetype":"postalcode"
},
  "geometry": {"coordinates":[-3.688736,51.530697],"type":"Point"}
}