{
  "type": "Feature",
  "properties": {
    "iso:country": "GB",
    "wof:name": "AB15 5LZ",
    "wof:placetype": "postalcode"
  },
  "geometry": {"coordinates":[-2.131594,57.148804],"type":"Point"}
}
