{
  "type": "Feature",
  "properties": {
    "date:inception_lower": "1996-06-01",
    "date:inception_upper": "1996-06-01",
    "iso:country": "GB",
    "wof:name": "AB15 5LZ",
    "wof:placetype": "postalcode"
  },
  "geometry": {"coordinates":[-2.131594,57.148804],"type":"Point"}
}
