{
  "type": "Feature",
  "properties": {
    "iso:country":"GB",
    "wof:name":"E3 2JA",
    "wof:placetype":"postalcode"
},
  "geometry": {"coordinates":[-0.02955346122817,51.53663433547661],"type":"Point"}
}