{
  "type": "Feature",
  "properties": {
    "iso:country":"GB",
    "wof:name":"SA18 2AP",
    "wof:placetype":"postalcode"
},
  "geometry": {"coordinates":[-3.93291913236355,51.8077046460631],"type":"Point"}
}