{
  "type": "Feature",
  "properties": {
    "iso:country": "GB",
    "wof:name": "SA18 2AP",
    "wof:placetype": "postalcode"
  },
  "geometry": {"coordinates":[-3.932919,51.807705],"type":"Point"}
}
