{
  "type": "Feature",
  "properties": {
    "iso:country":"GB",
    "wof:name":"NE12 5US",
    "wof:placetype":"postalcode"
},
  "geometry": {"coordinates":[-1.5844052576877,55.04199746328981],"type":"Point"}
}