{
  "type": "Feature",
  "properties": {
    "date:inception_lower": "1990-02-01",
    "date:inception_upper": "1990-02-01",
    "iso:country": "GB",
    "wof:name": "BA9 9RN",
    "wof:placetype": "postalcode"
  },
  "geometry": {"coordinates":[-2.406103,51.051252],"type":"Point"}
}
