{
  "type": "Feature",
  "properties": {
    "iso:country": "GB",
    "wof:name": "LE17 6DG",
    "wof:placetype": "postalcode"
  },
  "geometry": {"coordinates":[-1.187901,52.399124],"type":"Point"}
}
