{
  "type": "Feature",
  "properties": {
    "date:inception_lower": "1980-01-01",
    "date:inception_upper": "1980-01-01",
    "iso:country": "GB",
    "wof:name": "LE17 6DG",
    "wof:placetype": "postalcode"
  },
  "geometry": {"coordinates":[-1.187613,52.398878],"type":"Point"}
}
