{
  "type": "Feature",
  "properties": {
    "iso:country":"GB",
    "wof:name":"LE17 6DG",
    "wof:placetype":"postalcode"
},
  "geometry": {"coordinates":[-1.18790120508032,52.39912352766432],"type":"Point"}
}