{
  "type": "Feature",
  "properties": {
    "iso:country":"GB",
    "wof:name":"CH43 7NS",
    "wof:placetype":"postalcode"
},
  "geometry": {"coordinates":[-3.08193382341537,53.3962321322611],"type":"Point"}
}