{
  "type": "Feature",
  "properties": {
    "date:inception_lower":"1980-01-01",
    "date:inception_upper":"1980-01-31",
    "iso:country":"GB",
    "wof:name":"LL23 7NS",
    "wof:placetype":"postalcode"
},
  "geometry": {"coordinates":[-3.629034,52.942986],"type":"Point"}
}