{
  "type": "Feature",
  "properties": {
    "iso:country":"GB",
    "wof:name":"LL23 7NS",
    "wof:placetype":"postalcode"
},
  "geometry": {"coordinates":[-3.62903355949698,52.94298579762454],"type":"Point"}
}