{
  "type": "Feature",
  "properties": {
    "date:inception_lower": "1980-01-01",
    "date:inception_upper": "1980-01-01",
    "iso:country": "GB",
    "wof:name": "WR6 6TH",
    "wof:placetype": "postalcode"
  },
  "geometry": {"coordinates":[-2.29962,52.29764],"type":"Point"}
}
