{
  "type": "Feature",
  "properties": {
    "iso:country":"GB",
    "wof:name":"WR6 6TH",
    "wof:placetype":"postalcode"
},
  "geometry": {"coordinates":[-2.29961989641634,52.29763997569192],"type":"Point"}
}