{
  "type": "Feature",
  "properties": {
    "iso:country": "GB",
    "wof:name": "SL8 5QS",
    "wof:placetype": "postalcode"
  },
  "geometry": {"coordinates":[-0.716353,51.578457],"type":"Point"}
}
