{
  "type": "Feature",
  "properties": {
    "iso:country":"GB",
    "wof:name":"SL8 5QS",
    "wof:placetype":"postalcode"
},
  "geometry": {"coordinates":[-0.71635258654449,51.57845749594393],"type":"Point"}
}