{
  "type": "Feature",
  "properties": {
    "iso:country":"GB",
    "wof:name":"NR33 8HQ",
    "wof:placetype":"postalcode"
},
  "geometry": {"coordinates":[1.69969288394841,52.44998174724579],"type":"Point"}
}