{
  "type": "Feature",
  "properties": {
    "date:inception_lower": "1983-07-01",
    "date:inception_upper": "1983-07-01",
    "iso:country": "GB",
    "wof:name": "NR33 8HQ",
    "wof:placetype": "postalcode"
  },
  "geometry": {"coordinates":[1.699693,52.449982],"type":"Point"}
}
