{
  "type": "Feature",
  "properties": {
    "iso:country":"GB",
    "wof:name":"N16 5AH",
    "wof:placetype":"postalcode"
},
  "geometry": {"coordinates":[-0.07809343824288,51.57487550079158],"type":"Point"}
}