{
  "type": "Feature",
  "properties": {
    "iso:country": "GB",
    "wof:name": "N16 5AH",
    "wof:placetype": "postalcode"
  },
  "geometry": {"coordinates":[-0.078093,51.574875],"type":"Point"}
}
