{
  "type": "Feature",
  "properties": {
    "date:inception_lower": "1980-01-01",
    "date:inception_upper": "1980-01-01",
    "iso:country": "GB",
    "wof:name": "N16 5AH",
    "wof:placetype": "postalcode"
  },
  "geometry": {"coordinates":[-0.078093,51.574875],"type":"Point"}
}
