{
  "type": "Feature",
  "properties": {
    "date:inception_lower":"1999-12-01",
    "date:inception_upper":"1999-12-31",
    "iso:country":"GB",
    "wof:name":"IP11 2QX",
    "wof:placetype":"postalcode"
},
  "geometry": {"coordinates":[1.330198,51.956519],"type":"Point"}
}