{
  "type": "Feature",
  "properties": {
    "iso:country":"GB",
    "wof:name":"IP11 2QX",
    "wof:placetype":"postalcode"
},
  "geometry": {"coordinates":[1.33019830620297,51.95651917012616],"type":"Point"}
}