{
  "type": "Feature",
  "properties": {
    "iso:country": "GB",
    "wof:name": "LN11 0ZP",
    "wof:placetype": "postalcode"
  },
  "geometry": {"coordinates":[0.004992,53.370403],"type":"Point"}
}
