{
  "type": "Feature",
  "properties": {
    "iso:country":"GB",
    "wof:name":"CA2 4PP",
    "wof:placetype":"postalcode"
},
  "geometry": {"coordinates":[-2.92243184506658,54.8734959650137],"type":"Point"}
}