{
  "type": "Feature",
  "properties": {
    "iso:country":"GB",
    "wof:name":"SW8 3DE",
    "wof:placetype":"postalcode"
},
  "geometry": {"coordinates":[-0.14845394810044,51.46809694573394],"type":"Point"}
}