{
  "type": "Feature",
  "properties": {
    "iso:country":"GB",
    "wof:name":"OX26 3FS",
    "wof:placetype":"postalcode"
},
  "geometry": {"coordinates":[-1.15446439137108,51.91527977219538],"type":"Point"}
}