{
  "type": "Feature",
  "properties": {
    "date:inception_lower": "2000-10-01",
    "date:inception_upper": "2000-10-01",
    "iso:country": "GB",
    "wof:name": "OX26 1TE",
    "wof:placetype": "postalcode"
  },
  "geometry": {"coordinates":[-1.194443,51.890861],"type":"Point"}
}
