{
  "type": "Feature",
  "properties": {
    "date:inception_lower": "2013-07-01",
    "date:inception_upper": "2013-07-01",
    "iso:country": "GB",
    "wof:name": "CH46 7TF",
    "wof:placetype": "postalcode"
  },
  "geometry": {"coordinates":[-3.124347,53.403733],"type":"Point"}
}
