{
  "type": "Feature",
  "properties": {
    "date:inception_lower":"1998-06-01",
    "date:inception_upper":"1998-06-30",
    "iso:country":"GB",
    "wof:name":"NR16 2TB",
    "wof:placetype":"postalcode"
},
  "geometry": {"coordinates":[0.971045,52.472752],"type":"Point"}
}