{
  "type": "Feature",
  "properties": {
    "iso:country":"GB",
    "wof:name":"NR16 2TB",
    "wof:placetype":"postalcode"
},
  "geometry": {"coordinates":[0.97104456858831,52.47275155439042],"type":"Point"}
}