{
  "type": "Feature",
  "properties": {
    "iso:country": "GB",
    "wof:name": "NR16 2TB",
    "wof:placetype": "postalcode"
  },
  "geometry": {"coordinates":[0.971045,52.472752],"type":"Point"}
}
