{
  "type": "Feature",
  "properties": {
    "iso:country":"GB",
    "wof:name":"HA7 4YP",
    "wof:placetype":"postalcode"
},
  "geometry": {"coordinates":[-0.29394612121501,51.6222289655485],"type":"Point"}
}