{
  "type": "Feature",
  "properties": {
    "iso:country": "GB",
    "wof:name": "HA7 4YP",
    "wof:placetype": "postalcode"
  },
  "geometry": {"coordinates":[-0.293946,51.622229],"type":"Point"}
}
