{
  "type": "Feature",
  "properties": {
    "date:inception_lower":"1997-06-01",
    "date:inception_upper":"1997-06-30",
    "iso:country":"GB",
    "wof:name":"HA7 4YP",
    "wof:placetype":"postalcode"
},
  "geometry": {"coordinates":[-0.293946,51.622229],"type":"Point"}
}