{
  "type": "Feature",
  "properties": {
    "iso:country": "GB",
    "wof:name": "ST7 3JW",
    "wof:placetype": "postalcode"
  },
  "geometry": {"coordinates":[-2.245986,53.113743],"type":"Point"}
}
