{
  "type": "Feature",
  "properties": {
    "date:inception_lower": "1980-01-01",
    "date:inception_upper": "1980-01-01",
    "iso:country": "GB",
    "wof:name": "CO5 8QN",
    "wof:placetype": "postalcode"
  },
  "geometry": {"coordinates":[0.910262,51.77807],"type":"Point"}
}
