{
  "type": "Feature",
  "properties": {
    "iso:country":"GB",
    "wof:name":"BD9 5QN",
    "wof:placetype":"postalcode"
},
  "geometry": {"coordinates":[-1.79298337866633,53.81471376808737],"type":"Point"}
}