{
  "type": "Feature",
  "properties": {
    "iso:country": "GB",
    "wof:name": "BS1 6GS",
    "wof:placetype": "postalcode"
  },
  "geometry": {"coordinates":[-2.608408,51.448843],"type":"Point"}
}
