{
  "type": "Feature",
  "properties": {
    "date:inception_lower": "1981-09-01",
    "date:inception_upper": "1981-09-01",
    "iso:country": "GB",
    "wof:name": "AL9 5EP",
    "wof:placetype": "postalcode"
  },
  "geometry": {"coordinates":[-0.214626,51.766009],"type":"Point"}
}
