{
  "type": "Feature",
  "properties": {
    "iso:country":"GB",
    "wof:name":"ME8 0JW",
    "wof:placetype":"postalcode"
},
  "geometry": {"coordinates":[0.58974856559586,51.35571240333574],"type":"Point"}
}