{
  "type": "Feature",
  "properties": {
    "iso:country":"GB",
    "wof:name":"CF35 5DE",
    "wof:placetype":"postalcode"
},
  "geometry": {"coordinates":[-3.5212451317629,51.4941520061321],"type":"Point"}
}