{
  "type": "Feature",
  "properties": {
    "iso:country": "GB",
    "wof:name": "CF35 5DE",
    "wof:placetype": "postalcode"
  },
  "geometry": {"coordinates":[-3.521245,51.494152],"type":"Point"}
}
