{
  "type": "Feature",
  "properties": {
    "date:inception_lower":"1980-01-01",
    "date:inception_upper":"1980-01-31",
    "iso:country":"GB",
    "wof:name":"CF35 5DE",
    "wof:placetype":"postalcode"
},
  "geometry": {"coordinates":[-3.521245,51.494152],"type":"Point"}
}