{
  "type": "Feature",
  "properties": {
    "iso:country":"GB",
    "wof:name":"SG2 9JQ",
    "wof:placetype":"postalcode"
},
  "geometry": {"coordinates":[-0.16503261993591,51.89692793852802],"type":"Point"}
}