{
  "type": "Feature",
  "properties": {
    "iso:country":"GB",
    "wof:name":"SE15 3HS",
    "wof:placetype":"postalcode"
},
  "geometry": {"coordinates":[-0.05310063452634,51.46530232476545],"type":"Point"}
}