{
  "type": "Feature",
  "properties": {
    "date:inception_lower": "1981-06-01",
    "date:inception_upper": "1981-06-01",
    "iso:country": "GB",
    "wof:name": "SE15 3HS",
    "wof:placetype": "postalcode"
  },
  "geometry": {"coordinates":[-0.053101,51.465302],"type":"Point"}
}
