{
  "type": "Feature",
  "properties": {
    "iso:country":"GB",
    "wof:name":"M33 6RX",
    "wof:placetype":"postalcode"
},
  "geometry": {"coordinates":[-2.33490756106671,53.42242718596209],"type":"Point"}
}