{
  "type": "Feature",
  "properties": {
    "iso:country": "GB",
    "wof:name": "M33 6RX",
    "wof:placetype": "postalcode"
  },
  "geometry": {"coordinates":[-2.334908,53.422427],"type":"Point"}
}
