{
  "type": "Feature",
  "properties": {
    "iso:country":"GB",
    "wof:name":"E11 1EG",
    "wof:placetype":"postalcode"
},
  "geometry": {"coordinates":[-0.00342451089476,51.56925836561903],"type":"Point"}
}