{
  "type": "Feature",
  "properties": {
    "date:inception_lower":"1980-01-01",
    "date:inception_upper":"1980-01-31",
    "iso:country":"GB",
    "wof:name":"CA11 8SS",
    "wof:placetype":"postalcode"
},
  "geometry": {"coordinates":[-2.68088,54.68264],"type":"Point"}
}