{
  "type": "Feature",
  "properties": {
    "iso:country":"GB",
    "wof:name":"CA11 8SS",
    "wof:placetype":"postalcode"
},
  "geometry": {"coordinates":[-2.68087962458767,54.68264050201645],"type":"Point"}
}