{
  "type": "Feature",
  "properties": {
    "iso:country": "GB",
    "wof:name": "LU7 0FN",
    "wof:placetype": "postalcode"
  },
  "geometry": {"coordinates":[-0.772648,51.934774],"type":"Point"}
}
