{
  "type": "Feature",
  "properties": {
    "iso:country":"GB",
    "wof:name":"ML5 3BU",
    "wof:placetype":"postalcode"
},
  "geometry": {"coordinates":[-4.02574496795574,55.86190449917184],"type":"Point"}
}