{
  "type": "Feature",
  "properties": {
    "iso:country": "GB",
    "wof:name": "PL12 4SA",
    "wof:placetype": "postalcode"
  },
  "geometry": {"coordinates":[-4.262377,50.421684],"type":"Point"}
}
