{
  "type": "Feature",
  "properties": {
    "iso:country":"GB",
    "wof:name":"PL12 4SA",
    "wof:placetype":"postalcode"
},
  "geometry": {"coordinates":[-4.26237673268139,50.42168427461447],"type":"Point"}
}