{
  "type": "Feature",
  "properties": {
    "iso:country":"GB",
    "wof:name":"N16 5PU",
    "wof:placetype":"postalcode"
},
  "geometry": {"coordinates":[-0.07423352035128,51.57025301944692],"type":"Point"}
}