{
  "type": "Feature",
  "properties": {
    "date:inception_lower": "2022-06-01",
    "date:inception_upper": "2022-06-01",
    "iso:country": "GB",
    "wof:name": "NG22 9XW",
    "wof:placetype": "postalcode"
  },
  "geometry": {"coordinates":[-1.009604,53.21139],"type":"Point"}
}
