{
  "type": "Feature",
  "properties": {
    "iso:country":"GB",
    "wof:name":"DA8 2EX",
    "wof:placetype":"postalcode"
},
  "geometry": {"coordinates":[0.1820750941231,51.47154759827083],"type":"Point"}
}