{
  "type": "Feature",
  "properties": {
    "iso:country": "GB",
    "wof:name": "DA8 2EX",
    "wof:placetype": "postalcode"
  },
  "geometry": {"coordinates":[0.182075,51.471548],"type":"Point"}
}
