{
  "type": "Feature",
  "properties": {
    "date:inception_lower": "2003-10-01",
    "date:inception_upper": "2003-10-01",
    "iso:country": "GB",
    "wof:name": "DA8 2EX",
    "wof:placetype": "postalcode"
  },
  "geometry": {"coordinates":[0.182075,51.471548],"type":"Point"}
}
