{
  "type": "Feature",
  "properties": {
    "iso:country":"GB",
    "wof:name":"SW19 1EP",
    "wof:placetype":"postalcode"
},
  "geometry": {"coordinates":[-0.19191576487216,51.41976586425605],"type":"Point"}
}