{
  "type": "Feature",
  "properties": {
    "date:inception_lower":"1980-01-01",
    "date:inception_upper":"1980-01-31",
    "iso:country":"GB",
    "wof:name":"CO8 5HF",
    "wof:placetype":"postalcode"
},
  "geometry": {"coordinates":[0.731955,51.984992],"type":"Point"}
}