{
  "type": "Feature",
  "properties": {
    "iso:country":"GB",
    "wof:name":"CO8 5HF",
    "wof:placetype":"postalcode"
},
  "geometry": {"coordinates":[0.73192297351752,51.98498037275273],"type":"Point"}
}