{
  "type": "Feature",
  "properties": {
    "iso:country":"GB",
    "wof:name":"CA8 1DA",
    "wof:placetype":"postalcode"
},
  "geometry": {"coordinates":[-2.7332434179912,54.94548277927282],"type":"Point"}
}