{
  "type": "Feature",
  "properties": {
    "iso:country":"GB",
    "wof:name":"SG2 8TT",
    "wof:placetype":"postalcode"
},
  "geometry": {"coordinates":[-0.17541812026553,51.87986985459245],"type":"Point"}
}