{
  "type": "Feature",
  "properties": {
    "iso:country":"GB",
    "wof:name":"ML6 9EL",
    "wof:placetype":"postalcode"
},
  "geometry": {"coordinates":[-3.98735729429905,55.85839664046097],"type":"Point"}
}