{
  "type": "Feature",
  "properties": {
    "iso:country":"GB",
    "wof:name":"TN6 3QA",
    "wof:placetype":"postalcode"
},
  "geometry": {"coordinates":[0.22583920113734,51.03754413687372],"type":"Point"}
}