{
  "type": "Feature",
  "properties": {
    "iso:country": "GB",
    "wof:name": "TN6 3QA",
    "wof:placetype": "postalcode"
  },
  "geometry": {"coordinates":[0.225868,51.037541],"type":"Point"}
}
