{
  "type": "Feature",
  "properties": {
    "iso:country":"GB",
    "wof:name":"TR13 8RT",
    "wof:placetype":"postalcode"
},
  "geometry": {"coordinates":[-5.27159176609476,50.0993877185584],"type":"Point"}
}