{
  "type": "Feature",
  "properties": {
    "iso:country":"GB",
    "wof:name":"TF3 2AA",
    "wof:placetype":"postalcode"
},
  "geometry": {"coordinates":[-2.43442455315192,52.66088531587967],"type":"Point"}
}