{
  "type": "Feature",
  "properties": {
    "iso:country": "GB",
    "wof:name": "TF3 2AA",
    "wof:placetype": "postalcode"
  },
  "geometry": {"coordinates":[-2.434425,52.660885],"type":"Point"}
}
