{
  "type": "Feature",
  "properties": {
    "date:inception_lower": "1992-08-01",
    "date:inception_upper": "1992-08-01",
    "iso:country": "GB",
    "wof:name": "LE67 3RB",
    "wof:placetype": "postalcode"
  },
  "geometry": {"coordinates":[-1.367832,52.719106],"type":"Point"}
}
