{
  "type": "Feature",
  "properties": {
    "iso:country":"GB",
    "wof:name":"S41 0EN",
    "wof:placetype":"postalcode"
},
  "geometry": {"coordinates":[-1.41707202688591,53.23396990109831],"type":"Point"}
}