{
  "type": "Feature",
  "properties": {
    "iso:country": "GB",
    "wof:name": "HP13 7QJ",
    "wof:placetype": "postalcode"
  },
  "geometry": {"coordinates":[-0.725339,51.635851],"type":"Point"}
}
