{
  "type": "Feature",
  "properties": {
    "iso:country":"GB",
    "wof:name":"HP13 7QJ",
    "wof:placetype":"postalcode"
},
  "geometry": {"coordinates":[-0.72533938564586,51.63585120867309],"type":"Point"}
}