{
  "type": "Feature",
  "properties": {
    "iso:country":"GB",
    "wof:name":"SN14 0BQ",
    "wof:placetype":"postalcode"
},
  "geometry": {"coordinates":[-2.1372380586717,51.45554820027066],"type":"Point"}
}