{
  "type": "Feature",
  "properties": {
    "date:inception_lower": "1990-02-01",
    "date:inception_upper": "1990-02-01",
    "iso:country": "GB",
    "wof:name": "TA1 2SD",
    "wof:placetype": "postalcode"
  },
  "geometry": {"coordinates":[-3.075413,51.007495],"type":"Point"}
}
