{
  "type": "Feature",
  "properties": {
    "date:inception_lower": "1980-01-01",
    "date:inception_upper": "1980-01-01",
    "iso:country": "GB",
    "wof:name": "CM16 7AB",
    "wof:placetype": "postalcode"
  },
  "geometry": {"coordinates":[0.115584,51.693911],"type":"Point"}
}
