{
  "type": "Feature",
  "properties": {
    "iso:country":"GB",
    "wof:name":"CM16 7AB",
    "wof:placetype":"postalcode"
},
  "geometry": {"coordinates":[0.11549992167598,51.69390800884021],"type":"Point"}
}