{
  "type": "Feature",
  "properties": {
    "iso:country":"GB",
    "wof:name":"E16 2GJ",
    "wof:placetype":"postalcode"
},
  "geometry": {"coordinates":[0.0685892744629,51.50677937107527],"type":"Point"}
}