{
  "type": "Feature",
  "properties": {
    "date:inception_lower":"2007-05-01",
    "date:inception_upper":"2007-05-31",
    "iso:country":"GB",
    "wof:name":"E16 2GJ",
    "wof:placetype":"postalcode"
},
  "geometry": {"coordinates":[0.068589,51.506779],"type":"Point"}
}