{
  "type": "Feature",
  "properties": {
    "iso:country": "GB",
    "wof:name": "LA10 5EP",
    "wof:placetype": "postalcode"
  },
  "geometry": {"coordinates":[-2.584837,54.305164],"type":"Point"}
}
