{
  "type": "Feature",
  "properties": {
    "date:inception_lower":"1980-01-01",
    "date:inception_upper":"1980-01-31",
    "iso:country":"GB",
    "wof:name":"BS15 3NS",
    "wof:placetype":"postalcode"
},
  "geometry": {"coordinates":[-2.509635,51.432149],"type":"Point"}
}