{
  "type": "Feature",
  "properties": {
    "iso:country":"GB",
    "wof:name":"BS15 3NS",
    "wof:placetype":"postalcode"
},
  "geometry": {"coordinates":[-2.50963501881692,51.4321489671885],"type":"Point"}
}