{
  "type": "Feature",
  "properties": {
    "date:inception_lower": "1994-05-01",
    "date:inception_upper": "1994-05-01",
    "iso:country": "GB",
    "wof:name": "M27 5NA",
    "wof:placetype": "postalcode"
  },
  "geometry": {"coordinates":[-2.32439,53.501555],"type":"Point"}
}
