{
  "type": "Feature",
  "properties": {
    "iso:country":"GB",
    "wof:name":"M27 5NA",
    "wof:placetype":"postalcode"
},
  "geometry": {"coordinates":[-2.32439036915089,53.50155507809255],"type":"Point"}
}