{
  "type": "Feature",
  "properties": {
    "iso:country":"GB",
    "wof:name":"CF3 6XE",
    "wof:placetype":"postalcode"
},
  "geometry": {"coordinates":[-3.09770511764176,51.54331959613577],"type":"Point"}
}