{
  "type": "Feature",
  "properties": {
    "iso:country": "GB",
    "wof:name": "CF3 6XE",
    "wof:placetype": "postalcode"
  },
  "geometry": {"coordinates":[-3.097705,51.54332],"type":"Point"}
}
