{
  "type": "Feature",
  "properties": {
    "date:inception_lower": "2019-09-01",
    "date:inception_upper": "2019-09-01",
    "iso:country": "GB",
    "wof:name": "TF1 2FU",
    "wof:placetype": "postalcode"
  },
  "geometry": {"coordinates":[-2.535104,52.696897],"type":"Point"}
}
