{
  "type": "Feature",
  "properties": {
    "iso:country": "GB",
    "wof:name": "TF1 2FU",
    "wof:placetype": "postalcode"
  },
  "geometry": {"coordinates":[-2.535252,52.696932],"type":"Point"}
}
