{
  "type": "Feature",
  "properties": {
    "iso:country":"GB",
    "wof:name":"M22 5AD",
    "wof:placetype":"postalcode"
},
  "geometry": {"coordinates":[-2.24530313572609,53.38668173405048],"type":"Point"}
}