{
  "type": "Feature",
  "properties": {
    "iso:country":"GB",
    "wof:name":"CV8 1LN",
    "wof:placetype":"postalcode"
},
  "geometry": {"coordinates":[-1.5764144554536,52.34509027415258],"type":"Point"}
}