{
  "type": "Feature",
  "properties": {
    "iso:country": "GB",
    "wof:name": "TS21 2BH",
    "wof:placetype": "postalcode"
  },
  "geometry": {"coordinates":[-1.452456,54.652747],"type":"Point"}
}
