{
  "type": "Feature",
  "properties": {
    "date:inception_lower": "1990-02-01",
    "date:inception_upper": "1990-02-01",
    "iso:country": "GB",
    "wof:name": "TS21 2BH",
    "wof:placetype": "postalcode"
  },
  "geometry": {"coordinates":[-1.452455,54.652837],"type":"Point"}
}
