{
  "type": "Feature",
  "properties": {
    "iso:country":"GB",
    "wof:name":"TS21 2BH",
    "wof:placetype":"postalcode"
},
  "geometry": {"coordinates":[-1.45244284810859,54.65282672385744],"type":"Point"}
}