{
  "type": "Feature",
  "properties": {
    "iso:country": "GB",
    "wof:name": "G5 0TP",
    "wof:placetype": "postalcode"
  },
  "geometry": {"coordinates":[-4.253613,55.845907],"type":"Point"}
}
