{
  "type": "Feature",
  "properties": {
    "iso:country": "GB",
    "wof:name": "NE4 5DW",
    "wof:placetype": "postalcode"
  },
  "geometry": {"coordinates":[-1.630064,54.976105],"type":"Point"}
}
