{
  "type": "Feature",
  "properties": {
    "iso:country":"GB",
    "wof:name":"LA23 1DX",
    "wof:placetype":"postalcode"
},
  "geometry": {"coordinates":[-2.90650023552807,54.3781490982406],"type":"Point"}
}