{
  "type": "Feature",
  "properties": {
    "iso:country": "GB",
    "wof:name": "SA6 5AE",
    "wof:placetype": "postalcode"
  },
  "geometry": {"coordinates":[-3.911043,51.685174],"type":"Point"}
}
