{
  "type": "Feature",
  "properties": {
    "iso:country":"GB",
    "wof:name":"SA6 5AE",
    "wof:placetype":"postalcode"
},
  "geometry": {"coordinates":[-3.91104299850532,51.68517429811975],"type":"Point"}
}