{
  "type": "Feature",
  "properties": {
    "iso:country":"GB",
    "wof:name":"B19 3ND",
    "wof:placetype":"postalcode"
},
  "geometry": {"coordinates":[-1.89840501584701,52.4924148920003],"type":"Point"}
}