{
  "type": "Feature",
  "properties": {
    "date:inception_lower": "2011-06-01",
    "date:inception_upper": "2011-06-01",
    "iso:country": "GB",
    "wof:name": "E4 8AS",
    "wof:placetype": "postalcode"
  },
  "geometry": {"coordinates":[-0.024763,51.615996],"type":"Point"}
}
