{
  "type": "Feature",
  "properties": {
    "iso:country":"GB",
    "wof:name":"E4 8AS",
    "wof:placetype":"postalcode"
},
  "geometry": {"coordinates":[-0.02476682507763,51.6165066594334],"type":"Point"}
}