{
  "type": "Feature",
  "properties": {
    "iso:country": "GB",
    "wof:name": "WS5 3BT",
    "wof:placetype": "postalcode"
  },
  "geometry": {"coordinates":[-1.93644,52.580362],"type":"Point"}
}
