{
  "type": "Feature",
  "properties": {
    "iso:country":"GB",
    "wof:name":"WS5 3BT",
    "wof:placetype":"postalcode"
},
  "geometry": {"coordinates":[-1.93643956439984,52.58036230756669],"type":"Point"}
}