{
  "type": "Feature",
  "properties": {
    "date:inception_lower": "2018-09-01",
    "date:inception_upper": "2018-09-01",
    "iso:country": "GB",
    "wof:name": "WV10 0BX",
    "wof:placetype": "postalcode"
  },
  "geometry": {"coordinates":[-2.112366,52.594419],"type":"Point"}
}
