{
  "type": "Feature",
  "properties": {
    "iso:country":"GB",
    "wof:name":"PE1 5EW",
    "wof:placetype":"postalcode"
},
  "geometry": {"coordinates":[-0.23069501292584,52.57976905202747],"type":"Point"}
}