{
  "type": "Feature",
  "properties": {
    "iso:country":"GB",
    "wof:name":"CV4 9SE",
    "wof:placetype":"postalcode"
},
  "geometry": {"coordinates":[-1.58037064194846,52.40323489006905],"type":"Point"}
}