{
  "type": "Feature",
  "properties": {
    "iso:country": "GB",
    "wof:name": "CV4 9SE",
    "wof:placetype": "postalcode"
  },
  "geometry": {"coordinates":[-1.580371,52.403235],"type":"Point"}
}
