{
  "type": "Feature",
  "properties": {
    "iso:country":"GB",
    "wof:name":"SW4 7QQ",
    "wof:placetype":"postalcode"
},
  "geometry": {"coordinates":[-0.12327261879511,51.46212116693436],"type":"Point"}
}