{
  "type": "Feature",
  "properties": {
    "iso:country": "GB",
    "wof:name": "SG2 8AR",
    "wof:placetype": "postalcode"
  },
  "geometry": {"coordinates":[-0.178681,51.882528],"type":"Point"}
}
