{
  "type": "Feature",
  "properties": {
    "iso:country":"GB",
    "wof:name":"SG2 8AR",
    "wof:placetype":"postalcode"
},
  "geometry": {"coordinates":[-0.17868141059331,51.88252808331407],"type":"Point"}
}