{
  "type": "Feature",
  "properties": {
    "date:inception_lower": "2017-05-01",
    "date:inception_upper": "2017-05-01",
    "iso:country": "GB",
    "wof:name": "SG6 3BA",
    "wof:placetype": "postalcode"
  },
  "geometry": {"coordinates":[-0.226799,51.98051],"type":"Point"}
}
