{
  "type": "Feature",
  "properties": {
    "iso:country":"GB",
    "wof:name":"S60 5SJ",
    "wof:placetype":"postalcode"
},
  "geometry": {"coordinates":[-1.36106240883022,53.39538330941728],"type":"Point"}
}