{
  "type": "Feature",
  "properties": {
    "iso:country":"GB",
    "wof:name":"SK17 9BW",
    "wof:placetype":"postalcode"
},
  "geometry": {"coordinates":[-1.92558937495159,53.25276417129528],"type":"Point"}
}