{
  "type": "Feature",
  "properties": {
    "iso:country":"GB",
    "wof:name":"EH48 2RW",
    "wof:placetype":"postalcode"
},
  "geometry": {"coordinates":[-3.65316359231179,55.89044364225638],"type":"Point"}
}