{
  "type": "Feature",
  "properties": {
    "iso:country":"GB",
    "wof:name":"LL77 7AQ",
    "wof:placetype":"postalcode"
},
  "geometry": {"coordinates":[-4.34521855716821,53.24418324160303],"type":"Point"}
}