{
  "type": "Feature",
  "properties": {
    "iso:country": "GB",
    "wof:name": "LL77 7AQ",
    "wof:placetype": "postalcode"
  },
  "geometry": {"coordinates":[-4.345219,53.244183],"type":"Point"}
}
