{
  "type": "Feature",
  "properties": {
    "iso:country":"GB",
    "wof:name":"CA13 0QG",
    "wof:placetype":"postalcode"
},
  "geometry": {"coordinates":[-3.30732156687779,54.69101690516644],"type":"Point"}
}