{
  "type": "Feature",
  "properties": {
    "date:inception_lower": "1980-01-01",
    "date:inception_upper": "1980-01-01",
    "iso:country": "GB",
    "wof:name": "CV3 5FD",
    "wof:placetype": "postalcode"
  },
  "geometry": {"coordinates":[-1.508113,52.395682],"type":"Point"}
}
