{
  "type": "Feature",
  "properties": {
    "iso:country":"GB",
    "wof:name":"CV3 5FD",
    "wof:placetype":"postalcode"
},
  "geometry": {"coordinates":[-1.50812272468303,52.39566552294533],"type":"Point"}
}