{
  "type": "Feature",
  "properties": {
    "iso:country":"GB",
    "wof:name":"LU6 1PH",
    "wof:placetype":"postalcode"
},
  "geometry": {"coordinates":[-0.5331138030716,51.88389274088706],"type":"Point"}
}