{
  "type": "Feature",
  "properties": {
    "iso:country":"GB",
    "wof:name":"AL3 5EH",
    "wof:placetype":"postalcode"
},
  "geometry": {"coordinates":[-0.34054452149621,51.75293079666587],"type":"Point"}
}