{
  "type": "Feature",
  "properties": {
    "iso:country":"GB",
    "wof:name":"SP11 9AZ",
    "wof:placetype":"postalcode"
},
  "geometry": {"coordinates":[-1.56984800363157,51.24300410003907],"type":"Point"}
}