{
  "type": "Feature",
  "properties": {
    "date:inception_lower": "2005-07-01",
    "date:inception_upper": "2005-07-01",
    "iso:country": "GB",
    "wof:name": "TA9 3EA",
    "wof:placetype": "postalcode"
  },
  "geometry": {"coordinates":[-2.98098,51.225203],"type":"Point"}
}
