{
  "type": "Feature",
  "properties": {
    "iso:country":"GB",
    "wof:name":"TA9 3EA",
    "wof:placetype":"postalcode"
},
  "geometry": {"coordinates":[-2.98098023311989,51.225203205737],"type":"Point"}
}