{
  "type": "Feature",
  "properties": {
    "iso:country":"GB",
    "wof:name":"BN2 3QH",
    "wof:placetype":"postalcode"
},
  "geometry": {"coordinates":[-0.12119239895503,50.83735998370364],"type":"Point"}
}