{
  "type": "Feature",
  "properties": {
    "iso:country":"GB",
    "wof:name":"CV3 2NL",
    "wof:placetype":"postalcode"
},
  "geometry": {"coordinates":[-1.42357694718788,52.39104932201746],"type":"Point"}
}