{
  "type": "Feature",
  "properties": {
    "date:inception_lower":"1980-01-01",
    "date:inception_upper":"1980-01-31",
    "iso:country":"GB",
    "wof:name":"CV3 2NL",
    "wof:placetype":"postalcode"
},
  "geometry": {"coordinates":[-1.423577,52.391049],"type":"Point"}
}