{
  "type": "Feature",
  "properties": {
    "iso:country": "GB",
    "wof:name": "CV3 2NL",
    "wof:placetype": "postalcode"
  },
  "geometry": {"coordinates":[-1.423577,52.391049],"type":"Point"}
}
