{
  "type": "Feature",
  "properties": {
    "date:inception_lower": "1980-01-01",
    "date:inception_upper": "1980-01-01",
    "iso:country": "GB",
    "wof:name": "WR11 4PA",
    "wof:placetype": "postalcode"
  },
  "geometry": {"coordinates":[-1.946244,52.09454],"type":"Point"}
}
