{
  "type": "Feature",
  "properties": {
    "iso:country": "GB",
    "wof:name": "WR11 4PA",
    "wof:placetype": "postalcode"
  },
  "geometry": {"coordinates":[-1.945494,52.094133],"type":"Point"}
}
