{
  "type": "Feature",
  "properties": {
    "iso:country":"GB",
    "wof:name":"SP10 2HT",
    "wof:placetype":"postalcode"
},
  "geometry": {"coordinates":[-1.48493911098624,51.19804330630544],"type":"Point"}
}