{
  "type": "Feature",
  "properties": {
    "iso:country": "GB",
    "wof:name": "FK2 8BZ",
    "wof:placetype": "postalcode"
  },
  "geometry": {"coordinates":[-3.788249,56.029246],"type":"Point"}
}
