{
  "type": "Feature",
  "properties": {
    "iso:country":"GB",
    "wof:name":"FK2 8BZ",
    "wof:placetype":"postalcode"
},
  "geometry": {"coordinates":[-3.78824935894134,56.02924574147037],"type":"Point"}
}