{
  "type": "Feature",
  "properties": {
    "date:inception_lower": "1980-01-01",
    "date:inception_upper": "1980-01-01",
    "iso:country": "GB",
    "wof:name": "HG4 3PH",
    "wof:placetype": "postalcode"
  },
  "geometry": {"coordinates":[-1.637697,54.12836],"type":"Point"}
}
