{
  "type": "Feature",
  "properties": {
    "iso:country": "GB",
    "wof:name": "DY10 3SH",
    "wof:placetype": "postalcode"
  },
  "geometry": {"coordinates":[-2.229691,52.422526],"type":"Point"}
}
