{
  "type": "Feature",
  "properties": {
    "iso:country":"GB",
    "wof:name":"DY10 3SH",
    "wof:placetype":"postalcode"
},
  "geometry": {"coordinates":[-2.22969143482867,52.42252629261515],"type":"Point"}
}