{
  "type": "Feature",
  "properties": {
    "iso:country":"GB",
    "wof:name":"DY4 7DG",
    "wof:placetype":"postalcode"
},
  "geometry": {"coordinates":[-2.04105663398081,52.5329595914767],"type":"Point"}
}