{
  "type": "Feature",
  "properties": {
    "iso:country":"GB",
    "wof:name":"G53 7FS",
    "wof:placetype":"postalcode"
},
  "geometry": {"coordinates":[-4.36145287846197,55.82711228101769],"type":"Point"}
}