{
  "type": "Feature",
  "properties": {
    "date:inception_lower":"1993-08-01",
    "date:inception_upper":"1993-08-31",
    "iso:country":"GB",
    "wof:name":"NN3 7UT",
    "wof:placetype":"postalcode"
},
  "geometry": {"coordinates":[-0.8448,52.289757],"type":"Point"}
}