{
  "type": "Feature",
  "properties": {
    "iso:country": "GB",
    "wof:name": "DE45 1EN",
    "wof:placetype": "postalcode"
  },
  "geometry": {"coordinates":[-1.674858,53.210564],"type":"Point"}
}
