{
  "type": "Feature",
  "properties": {
    "date:inception_lower":"1998-12-01",
    "date:inception_upper":"1998-12-31",
    "iso:country":"GB",
    "wof:name":"EC1R 5LB",
    "wof:placetype":"postalcode"
},
  "geometry": {"coordinates":[-0.11079,51.522782],"type":"Point"}
}