{
  "type": "Feature",
  "properties": {
    "iso:country":"GB",
    "wof:name":"EC1R 5LB",
    "wof:placetype":"postalcode"
},
  "geometry": {"coordinates":[-0.11079000765661,51.52278239455349],"type":"Point"}
}