{
  "type": "Feature",
  "properties": {
    "iso:country":"GB",
    "wof:name":"SY16 4AJ",
    "wof:placetype":"postalcode"
},
  "geometry": {"coordinates":[-3.3378664011579,52.46360152276263],"type":"Point"}
}