{
  "type": "Feature",
  "properties": {
    "iso:country": "GB",
    "wof:name": "SY16 4AJ",
    "wof:placetype": "postalcode"
  },
  "geometry": {"coordinates":[-3.337866,52.463602],"type":"Point"}
}
