{
  "type": "Feature",
  "properties": {
    "iso:country":"GB",
    "wof:name":"EN1 2NE",
    "wof:placetype":"postalcode"
},
  "geometry": {"coordinates":[-0.0724768654307,51.63426850539032],"type":"Point"}
}