{
  "type": "Feature",
  "properties": {
    "date:inception_lower":"1980-01-01",
    "date:inception_upper":"1980-01-31",
    "iso:country":"GB",
    "wof:name":"EN1 2NE",
    "wof:placetype":"postalcode"
},
  "geometry": {"coordinates":[-0.072477,51.634268],"type":"Point"}
}