{
  "type": "Feature",
  "properties": {
    "date:inception_lower": "2023-12-01",
    "date:inception_upper": "2023-12-01",
    "iso:country": "GB",
    "wof:name": "N22 9NW",
    "wof:placetype": "postalcode"
  },
  "geometry": {"coordinates":[-0.119662,51.598609],"type":"Point"}
}
