{
  "type": "Feature",
  "properties": {
    "iso:country": "GB",
    "wof:name": "BD21 1EH",
    "wof:placetype": "postalcode"
  },
  "geometry": {"coordinates":[-1.911251,53.859615],"type":"Point"}
}
