{
  "type": "Feature",
  "properties": {
    "iso:country":"GB",
    "wof:name":"BD21 1EH",
    "wof:placetype":"postalcode"
},
  "geometry": {"coordinates":[-1.91124760975133,53.85960106835415],"type":"Point"}
}