{
  "type": "Feature",
  "properties": {
    "date:inception_lower": "1981-06-01",
    "date:inception_upper": "1981-06-01",
    "iso:country": "GB",
    "wof:name": "SK7 5BW",
    "wof:placetype": "postalcode"
  },
  "geometry": {"coordinates":[-2.139396,53.377935],"type":"Point"}
}
