{
  "type": "Feature",
  "properties": {
    "iso:country": "GB",
    "wof:name": "SK7 5BW",
    "wof:placetype": "postalcode"
  },
  "geometry": {"coordinates":[-2.139563,53.378258],"type":"Point"}
}
