{
  "type": "Feature",
  "properties": {
    "iso:country":"GB",
    "wof:name":"HP4 3YP",
    "wof:placetype":"postalcode"
},
  "geometry": {"coordinates":[-0.56785299829524,51.75762860217793],"type":"Point"}
}