{
  "type": "Feature",
  "properties": {
    "iso:country":"GB",
    "wof:name":"NE61 5QA",
    "wof:placetype":"postalcode"
},
  "geometry": {"coordinates":[-1.63239483534202,55.24408524402622],"type":"Point"}
}