{
  "type": "Feature",
  "properties": {
    "iso:country": "GB",
    "wof:name": "NE61 5QA",
    "wof:placetype": "postalcode"
  },
  "geometry": {"coordinates":[-1.63248,55.244844],"type":"Point"}
}
