{
  "type": "Feature",
  "properties": {
    "iso:country": "GB",
    "wof:name": "ME12 2FH",
    "wof:placetype": "postalcode"
  },
  "geometry": {"coordinates":[0.798686,51.434252],"type":"Point"}
}
