{
  "type": "Feature",
  "properties": {
    "iso:country":"GB",
    "wof:name":"ME12 2FH",
    "wof:placetype":"postalcode"
},
  "geometry": {"coordinates":[0.79868601116767,51.43425202390574],"type":"Point"}
}