{
  "type": "Feature",
  "properties": {
    "date:inception_lower":"2015-05-01",
    "date:inception_upper":"2015-05-31",
    "iso:country":"GB",
    "wof:name":"E16 1FQ",
    "wof:placetype":"postalcode"
},
  "geometry": {"coordinates":[0.011128,51.515146],"type":"Point"}
}