{
  "type": "Feature",
  "properties": {
    "iso:country":"GB",
    "wof:name":"E16 1FQ",
    "wof:placetype":"postalcode"
},
  "geometry": {"coordinates":[0.01119643702492,51.51536751622181],"type":"Point"}
}