{
  "type": "Feature",
  "properties": {
    "iso:country": "GB",
    "wof:name": "E16 1FQ",
    "wof:placetype": "postalcode"
  },
  "geometry": {"coordinates":[0.011128,51.515146],"type":"Point"}
}
