{
  "type": "Feature",
  "properties": {
    "iso:country":"GB",
    "wof:name":"S12 2RD",
    "wof:placetype":"postalcode"
},
  "geometry": {"coordinates":[-1.43798053814069,53.35335218845923],"type":"Point"}
}