{
  "type": "Feature",
  "properties": {
    "iso:country":"GB",
    "wof:name":"BH11 8QE",
    "wof:placetype":"postalcode"
},
  "geometry": {"coordinates":[-1.93075527149477,50.7539568210378],"type":"Point"}
}