{
  "type": "Feature",
  "properties": {
    "iso:country":"GB",
    "wof:name":"DL11 7QX",
    "wof:placetype":"postalcode"
},
  "geometry": {"coordinates":[-1.84154311543327,54.48427078295573],"type":"Point"}
}