{
  "type": "Feature",
  "properties": {
    "iso:country": "GB",
    "wof:name": "SN6 6PR",
    "wof:placetype": "postalcode"
  },
  "geometry": {"coordinates":[-1.930481,51.645309],"type":"Point"}
}
