{
  "type": "Feature",
  "properties": {
    "date:inception_lower": "1981-06-01",
    "date:inception_upper": "1981-06-01",
    "iso:country": "GB",
    "wof:name": "SN6 6PR",
    "wof:placetype": "postalcode"
  },
  "geometry": {"coordinates":[-1.930481,51.645309],"type":"Point"}
}
