{
  "type": "Feature",
  "properties": {
    "iso:country":"GB",
    "wof:name":"B65 8DL",
    "wof:placetype":"postalcode"
},
  "geometry": {"coordinates":[-2.0477663200796,52.48087846730552],"type":"Point"}
}