{
  "type": "Feature",
  "properties": {
    "iso:country":"GB",
    "wof:name":"BA20 1QE",
    "wof:placetype":"postalcode"
},
  "geometry": {"coordinates":[-2.63216378043078,50.94060318422211],"type":"Point"}
}