{
  "type": "Feature",
  "properties": {
    "iso:country": "GB",
    "wof:name": "BA20 1QE",
    "wof:placetype": "postalcode"
  },
  "geometry": {"coordinates":[-2.632164,50.940603],"type":"Point"}
}
