{
  "type": "Feature",
  "properties": {
    "date:inception_lower": "1993-01-01",
    "date:inception_upper": "1993-01-01",
    "iso:country": "GB",
    "wof:name": "SY6 6BJ",
    "wof:placetype": "postalcode"
  },
  "geometry": {"coordinates":[-2.805399,52.537945],"type":"Point"}
}
