{
  "type": "Feature",
  "properties": {
    "iso:country":"GB",
    "wof:name":"SE9 4PB",
    "wof:placetype":"postalcode"
},
  "geometry": {"coordinates":[0.03544634694207,51.43077681208781],"type":"Point"}
}