{
  "type": "Feature",
  "properties": {
    "iso:country": "GB",
    "wof:name": "DN11 8FD",
    "wof:placetype": "postalcode"
  },
  "geometry": {"coordinates":[-1.060705,53.425833],"type":"Point"}
}
