{
  "type": "Feature",
  "properties": {
    "date:inception_lower": "2019-07-01",
    "date:inception_upper": "2019-07-01",
    "iso:country": "GB",
    "wof:name": "DN11 8FD",
    "wof:placetype": "postalcode"
  },
  "geometry": {"coordinates":[-1.060337,53.42547],"type":"Point"}
}
