{
  "type": "Feature",
  "properties": {
    "iso:country":"GB",
    "wof:name":"EH32 0HD",
    "wof:placetype":"postalcode"
},
  "geometry": {"coordinates":[-2.95520590064791,55.97098703357852],"type":"Point"}
}