{
  "type": "Feature",
  "properties": {
    "iso:country":"GB",
    "wof:name":"HG5 8AJ",
    "wof:placetype":"postalcode"
},
  "geometry": {"coordinates":[-1.46603757504092,54.00778049537524],"type":"Point"}
}