{
  "type": "Feature",
  "properties": {
    "iso:country":"GB",
    "wof:name":"ML2 8HF",
    "wof:placetype":"postalcode"
},
  "geometry": {"coordinates":[-3.88577173791985,55.77372305516908],"type":"Point"}
}