{
  "type": "Feature",
  "properties": {
    "iso:country":"GB",
    "wof:name":"ME9 8EF",
    "wof:placetype":"postalcode"
},
  "geometry": {"coordinates":[0.72518560540157,51.31402751103499],"type":"Point"}
}