{
  "type": "Feature",
  "properties": {
    "iso:country": "GB",
    "wof:name": "ME9 8EF",
    "wof:placetype": "postalcode"
  },
  "geometry": {"coordinates":[0.725186,51.314028],"type":"Point"}
}
