{
  "type": "Feature",
  "properties": {
    "iso:country":"GB",
    "wof:name":"SA12 8DR",
    "wof:placetype":"postalcode"
},
  "geometry": {"coordinates":[-3.78925654099473,51.59985040705157],"type":"Point"}
}