{
  "type": "Feature",
  "properties": {
    "iso:country": "GB",
    "wof:name": "SA12 8DR",
    "wof:placetype": "postalcode"
  },
  "geometry": {"coordinates":[-3.789256,51.59985],"type":"Point"}
}
