{
  "type": "Feature",
  "properties": {
    "iso:country": "GB",
    "wof:name": "DL16 6RS",
    "wof:placetype": "postalcode"
  },
  "geometry": {"coordinates":[-1.605167,54.702524],"type":"Point"}
}
