{
  "type": "Feature",
  "properties": {
    "iso:country":"GB",
    "wof:name":"DL16 6RS",
    "wof:placetype":"postalcode"
},
  "geometry": {"coordinates":[-1.60516750542016,54.70252377738171],"type":"Point"}
}