{
  "type": "Feature",
  "properties": {
    "iso:country": "GB",
    "wof:name": "TS22 5GU",
    "wof:placetype": "postalcode"
  },
  "geometry": {"coordinates":[-1.346888,54.645422],"type":"Point"}
}
