{
  "type": "Feature",
  "properties": {
    "date:inception_lower": "2019-12-01",
    "date:inception_upper": "2019-12-01",
    "iso:country": "GB",
    "wof:name": "TS22 5GU",
    "wof:placetype": "postalcode"
  },
  "geometry": {"coordinates":[-1.344912,54.645968],"type":"Point"}
}
