{
  "type": "Feature",
  "properties": {
    "iso:country": "GB",
    "wof:name": "OX4 7GR",
    "wof:placetype": "postalcode"
  },
  "geometry": {"coordinates":[-1.19799,51.713606],"type":"Point"}
}
