{
  "type": "Feature",
  "properties": {
    "iso:country":"GB",
    "wof:name":"NR5 0PT",
    "wof:placetype":"postalcode"
},
  "geometry": {"coordinates":[1.21445721987261,52.65026418389449],"type":"Point"}
}