{
  "type": "Feature",
  "properties": {
    "date:inception_lower": "1982-03-01",
    "date:inception_upper": "1982-03-01",
    "iso:country": "GB",
    "wof:name": "NR5 0PT",
    "wof:placetype": "postalcode"
  },
  "geometry": {"coordinates":[1.214457,52.650264],"type":"Point"}
}
