{
  "type": "Feature",
  "properties": {
    "iso:country": "GB",
    "wof:name": "NR5 0PT",
    "wof:placetype": "postalcode"
  },
  "geometry": {"coordinates":[1.214457,52.650264],"type":"Point"}
}
