{
  "type": "Feature",
  "properties": {
    "iso:country":"GB",
    "wof:name":"TR9 6QY",
    "wof:placetype":"postalcode"
},
  "geometry": {"coordinates":[-4.94264157002286,50.39826131582394],"type":"Point"}
}