{
  "type": "Feature",
  "properties": {
    "date:inception_lower": "1992-08-01",
    "date:inception_upper": "1992-08-01",
    "iso:country": "GB",
    "wof:name": "YO7 3ED",
    "wof:placetype": "postalcode"
  },
  "geometry": {"coordinates":[-1.398057,54.203588],"type":"Point"}
}
