{
  "type": "Feature",
  "properties": {
    "iso:country":"GB",
    "wof:name":"YO7 3ED",
    "wof:placetype":"postalcode"
},
  "geometry": {"coordinates":[-1.39805676833245,54.20358788884786],"type":"Point"}
}