{
  "type": "Feature",
  "properties": {
    "iso:country": "GB",
    "wof:name": "DE11 0JJ",
    "wof:placetype": "postalcode"
  },
  "geometry": {"coordinates":[-1.568683,52.785558],"type":"Point"}
}
