{
  "type": "Feature",
  "properties": {
    "iso:country":"GB",
    "wof:name":"M34 5HE",
    "wof:placetype":"postalcode"
},
  "geometry": {"coordinates":[-2.1146107036451,53.47320471583867],"type":"Point"}
}