{
  "type": "Feature",
  "properties": {
    "date:inception_lower":"2016-02-01",
    "date:inception_upper":"2016-02-29",
    "iso:country":"GB",
    "wof:name":"CV47 2QF",
    "wof:placetype":"postalcode"
},
  "geometry": {"coordinates":[-1.43259,52.218764],"type":"Point"}
}