{
  "type": "Feature",
  "properties": {
    "iso:country": "GB",
    "wof:name": "CV47 2QF",
    "wof:placetype": "postalcode"
  },
  "geometry": {"coordinates":[-1.43259,52.218764],"type":"Point"}
}
