{
  "type": "Feature",
  "properties": {
    "iso:country": "GB",
    "wof:name": "SR5 4EA",
    "wof:placetype": "postalcode"
  },
  "geometry": {"coordinates":[-1.448281,54.926549],"type":"Point"}
}
