{
  "type": "Feature",
  "properties": {
    "iso:country":"GB",
    "wof:name":"SR5 4EA",
    "wof:placetype":"postalcode"
},
  "geometry": {"coordinates":[-1.44828092476679,54.92654887322519],"type":"Point"}
}