{
  "type": "Feature",
  "properties": {
    "iso:country": "GB",
    "wof:name": "TD11 3PE",
    "wof:placetype": "postalcode"
  },
  "geometry": {"coordinates":[-2.492858,55.808111],"type":"Point"}
}
