{
  "type": "Feature",
  "properties": {
    "date:inception_lower":"1980-01-01",
    "date:inception_upper":"1980-01-31",
    "iso:country":"GB",
    "wof:name":"SN16 9QX",
    "wof:placetype":"postalcode"
},
  "geometry": {"coordinates":[-1.964629,51.610923],"type":"Point"}
}