{
  "type": "Feature",
  "properties": {
    "iso:country":"GB",
    "wof:name":"SN16 9QX",
    "wof:placetype":"postalcode"
},
  "geometry": {"coordinates":[-1.96462870440137,51.61092324935716],"type":"Point"}
}