{
  "type": "Feature",
  "properties": {
    "date:inception_lower": "2021-12-01",
    "date:inception_upper": "2021-12-01",
    "iso:country": "GB",
    "wof:name": "CH66 7PD",
    "wof:placetype": "postalcode"
  },
  "geometry": {"coordinates":[-2.980368,53.29386],"type":"Point"}
}
