{
  "type": "Feature",
  "properties": {
    "date:inception_lower": "1980-01-01",
    "date:inception_upper": "1980-01-01",
    "iso:country": "GB",
    "wof:name": "B5 7PA",
    "wof:placetype": "postalcode"
  },
  "geometry": {"coordinates":[-1.902317,52.461843],"type":"Point"}
}
