{
  "type": "Feature",
  "properties": {
    "iso:country":"GB",
    "wof:name":"B5 7PA",
    "wof:placetype":"postalcode"
},
  "geometry": {"coordinates":[-1.90231662975214,52.4618433041895],"type":"Point"}
}