{
  "type": "Feature",
  "properties": {
    "iso:country":"GB",
    "wof:name":"TR13 8DB",
    "wof:placetype":"postalcode"
},
  "geometry": {"coordinates":[-5.26499875490036,50.09807114828802],"type":"Point"}
}