{
  "type": "Feature",
  "properties": {
    "iso:country":"GB",
    "wof:name":"LE7 7GR",
    "wof:placetype":"postalcode"
},
  "geometry": {"coordinates":[-1.18182146000404,52.66781408793744],"type":"Point"}
}