{
  "type": "Feature",
  "properties": {
    "date:inception_lower": "2013-04-01",
    "date:inception_upper": "2013-04-01",
    "iso:country": "GB",
    "wof:name": "N12 2DX",
    "wof:placetype": "postalcode"
  },
  "geometry": {"coordinates":[-0.180728,51.616851],"type":"Point"}
}
