{
  "type": "Feature",
  "properties": {
    "iso:country": "GB",
    "wof:name": "WF4 2EU",
    "wof:placetype": "postalcode"
  },
  "geometry": {"coordinates":[-1.407464,53.622996],"type":"Point"}
}
