{
  "type": "Feature",
  "properties": {
    "iso:country":"GB",
    "wof:name":"WF4 2EU",
    "wof:placetype":"postalcode"
},
  "geometry": {"coordinates":[-1.40746404439579,53.62299637886463],"type":"Point"}
}