{
  "type": "Feature",
  "properties": {
    "iso:country": "GB",
    "wof:name": "LA19 5UH",
    "wof:placetype": "postalcode"
  },
  "geometry": {"coordinates":[-3.361399,54.28342],"type":"Point"}
}
