{
  "type": "Feature",
  "properties": {
    "iso:country":"GB",
    "wof:name":"TN8 5JR",
    "wof:placetype":"postalcode"
},
  "geometry": {"coordinates":[0.05690449878491,51.20253729315644],"type":"Point"}
}