{
  "type": "Feature",
  "properties": {
    "date:inception_lower": "1980-01-01",
    "date:inception_upper": "1980-01-01",
    "iso:country": "GB",
    "wof:name": "TN8 5JR",
    "wof:placetype": "postalcode"
  },
  "geometry": {"coordinates":[0.056905,51.202537],"type":"Point"}
}
