{
  "type": "Feature",
  "properties": {
    "iso:country":"GB",
    "wof:name":"RH1 2DJ",
    "wof:placetype":"postalcode"
},
  "geometry": {"coordinates":[-0.17797840333034,51.24306795360294],"type":"Point"}
}