{
  "type": "Feature",
  "properties": {
    "iso:country":"GB",
    "wof:name":"E17 5DL",
    "wof:placetype":"postalcode"
},
  "geometry": {"coordinates":[-0.02226668804641,51.59991833039315],"type":"Point"}
}