{
  "type": "Feature",
  "properties": {
    "date:inception_lower": "1980-01-01",
    "date:inception_upper": "1980-01-01",
    "iso:country": "GB",
    "wof:name": "GL3 1BT",
    "wof:placetype": "postalcode"
  },
  "geometry": {"coordinates":[-2.206276,51.885495],"type":"Point"}
}
