{
  "type": "Feature",
  "properties": {
    "iso:country": "GB",
    "wof:name": "CR6 9PB",
    "wof:placetype": "postalcode"
  },
  "geometry": {"coordinates":[-0.032135,51.313954],"type":"Point"}
}
