{
  "type": "Feature",
  "properties": {
    "date:inception_lower": "1999-06-01",
    "date:inception_upper": "1999-06-01",
    "iso:country": "GB",
    "wof:name": "DY6 7FQ",
    "wof:placetype": "postalcode"
  },
  "geometry": {"coordinates":[-2.148907,52.506775],"type":"Point"}
}
