{
  "type": "Feature",
  "properties": {
    "iso:country":"GB",
    "wof:name":"DY6 7FQ",
    "wof:placetype":"postalcode"
},
  "geometry": {"coordinates":[-2.14890746604371,52.50677512025099],"type":"Point"}
}