{
  "type": "Feature",
  "properties": {
    "iso:country":"GB",
    "wof:name":"LE12 8UE",
    "wof:placetype":"postalcode"
},
  "geometry": {"coordinates":[-1.18943953169389,52.75556232365272],"type":"Point"}
}