{
  "type": "Feature",
  "properties": {
    "iso:country":"GB",
    "wof:name":"SP4 8AQ",
    "wof:placetype":"postalcode"
},
  "geometry": {"coordinates":[-1.7778092701988,51.20258000128977],"type":"Point"}
}