{
  "type": "Feature",
  "properties": {
    "iso:country": "GB",
    "wof:name": "SP4 8AQ",
    "wof:placetype": "postalcode"
  },
  "geometry": {"coordinates":[-1.777809,51.20258],"type":"Point"}
}
