{
  "type": "Feature",
  "properties": {
    "date:inception_lower": "1980-01-01",
    "date:inception_upper": "1980-01-01",
    "iso:country": "GB",
    "wof:name": "DN37 9AL",
    "wof:placetype": "postalcode"
  },
  "geometry": {"coordinates":[-0.123632,53.569554],"type":"Point"}
}
