{
  "type": "Feature",
  "properties": {
    "date:inception_lower": "2006-04-01",
    "date:inception_upper": "2006-04-01",
    "iso:country": "GB",
    "wof:name": "NN4 6LU",
    "wof:placetype": "postalcode"
  },
  "geometry": {"coordinates":[-0.891112,52.207639],"type":"Point"}
}
