{
  "type": "Feature",
  "properties": {
    "iso:country":"GB",
    "wof:name":"CW12 2EL",
    "wof:placetype":"postalcode"
},
  "geometry": {"coordinates":[-2.19464331079312,53.17095516265562],"type":"Point"}
}