{
  "type": "Feature",
  "properties": {
    "iso:country": "GB",
    "wof:name": "NG18 4SY",
    "wof:placetype": "postalcode"
  },
  "geometry": {"coordinates":[-1.187979,53.12254],"type":"Point"}
}
