{
  "type": "Feature",
  "properties": {
    "date:inception_lower": "1980-01-01",
    "date:inception_upper": "1980-01-01",
    "iso:country": "GB",
    "wof:name": "EX31 2EQ",
    "wof:placetype": "postalcode"
  },
  "geometry": {"coordinates":[-4.077409,51.072743],"type":"Point"}
}
