{
  "type": "Feature",
  "properties": {
    "date:inception_lower":"1996-06-01",
    "date:inception_upper":"1996-06-30",
    "iso:country":"GB",
    "wof:name":"GL52 6PZ",
    "wof:placetype":"postalcode"
},
  "geometry": {"coordinates":[-2.052464,51.900016],"type":"Point"}
}