{
  "type": "Feature",
  "properties": {
    "iso:country": "GB",
    "wof:name": "GL52 6PZ",
    "wof:placetype": "postalcode"
  },
  "geometry": {"coordinates":[-2.052464,51.900016],"type":"Point"}
}
