{
  "type": "Feature",
  "properties": {
    "iso:country": "GB",
    "wof:name": "WD25 0EL",
    "wof:placetype": "postalcode"
  },
  "geometry": {"coordinates":[-0.400886,51.691135],"type":"Point"}
}
