{
  "type": "Feature",
  "properties": {
    "iso:country":"GB",
    "wof:name":"WD25 0EL",
    "wof:placetype":"postalcode"
},
  "geometry": {"coordinates":[-0.40076456961513,51.69113679610148],"type":"Point"}
}