{
  "type": "Feature",
  "properties": {
    "date:inception_lower":"2000-10-01",
    "date:inception_upper":"2000-10-31",
    "iso:country":"GB",
    "wof:name":"WD25 0EL",
    "wof:placetype":"postalcode"
},
  "geometry": {"coordinates":[-0.400886,51.691135],"type":"Point"}
}