{
  "type": "Feature",
  "properties": {
    "iso:country":"GB",
    "wof:name":"IP4 4HL",
    "wof:placetype":"postalcode"
},
  "geometry": {"coordinates":[1.18072204301773,52.06087616276175],"type":"Point"}
}