{
  "type": "Feature",
  "properties": {
    "iso:country":"GB",
    "wof:name":"DD3 7QF",
    "wof:placetype":"postalcode"
},
  "geometry": {"coordinates":[-2.96539618289784,56.47249526119214],"type":"Point"}
}