{
  "type": "Feature",
  "properties": {
    "date:inception_lower": "1988-11-01",
    "date:inception_upper": "1988-11-01",
    "iso:country": "GB",
    "wof:name": "DD3 7QF",
    "wof:placetype": "postalcode"
  },
  "geometry": {"coordinates":[-2.965396,56.472495],"type":"Point"}
}
