{
  "type": "Feature",
  "properties": {
    "iso:country": "GB",
    "wof:name": "DD3 7QF",
    "wof:placetype": "postalcode"
  },
  "geometry": {"coordinates":[-2.965396,56.472495],"type":"Point"}
}
