{
  "type": "Feature",
  "properties": {
    "iso:country":"GB",
    "wof:name":"LE3 6HT",
    "wof:placetype":"postalcode"
},
  "geometry": {"coordinates":[-1.16890345106574,52.63394901259386],"type":"Point"}
}