{
  "type": "Feature",
  "properties": {
    "iso:country": "GB",
    "wof:name": "LE3 6HT",
    "wof:placetype": "postalcode"
  },
  "geometry": {"coordinates":[-1.168903,52.633949],"type":"Point"}
}
