{
  "type": "Feature",
  "properties": {
    "iso:country": "GB",
    "wof:name": "KA13 6WF",
    "wof:placetype": "postalcode"
  },
  "geometry": {"coordinates":[-4.721328,55.658549],"type":"Point"}
}
