{
  "type": "Feature",
  "properties": {
    "iso:country":"GB",
    "wof:name":"KA13 6WF",
    "wof:placetype":"postalcode"
},
  "geometry": {"coordinates":[-4.7213282702708,55.65854871182293],"type":"Point"}
}