{
  "type": "Feature",
  "properties": {
    "iso:country": "GB",
    "wof:name": "WV14 8PZ",
    "wof:placetype": "postalcode"
  },
  "geometry": {"coordinates":[-2.071361,52.557002],"type":"Point"}
}
