{
  "type": "Feature",
  "properties": {
    "date:inception_lower": "1984-02-01",
    "date:inception_upper": "1984-02-01",
    "iso:country": "GB",
    "wof:name": "SY3 5EX",
    "wof:placetype": "postalcode"
  },
  "geometry": {"coordinates":[-2.810792,52.709565],"type":"Point"}
}
