{
  "type": "Feature",
  "properties": {
    "date:inception_lower": "1992-08-01",
    "date:inception_upper": "1992-08-01",
    "iso:country": "GB",
    "wof:name": "CW5 5YB",
    "wof:placetype": "postalcode"
  },
  "geometry": {"coordinates":[-2.518884,53.07718],"type":"Point"}
}
