{
  "type": "Feature",
  "properties": {
    "iso:country":"GB",
    "wof:name":"CW5 5YB",
    "wof:placetype":"postalcode"
},
  "geometry": {"coordinates":[-2.5188840692047,53.07718013725322],"type":"Point"}
}