{
  "type": "Feature",
  "properties": {
    "iso:country": "GB",
    "wof:name": "MK16 9PQ",
    "wof:placetype": "postalcode"
  },
  "geometry": {"coordinates":[-0.7043,52.109991],"type":"Point"}
}
