{
  "type": "Feature",
  "properties": {
    "date:inception_lower":"1983-07-01",
    "date:inception_upper":"1983-07-31",
    "iso:country":"GB",
    "wof:name":"MK16 9PQ",
    "wof:placetype":"postalcode"
},
  "geometry": {"coordinates":[-0.7043,52.109991],"type":"Point"}
}