{
  "type": "Feature",
  "properties": {
    "iso:country":"GB",
    "wof:name":"HP17 8EQ",
    "wof:placetype":"postalcode"
},
  "geometry": {"coordinates":[-0.9402868449593,51.77064806562684],"type":"Point"}
}