{
  "type": "Feature",
  "properties": {
    "date:inception_lower": "1980-01-01",
    "date:inception_upper": "1980-01-01",
    "iso:country": "GB",
    "wof:name": "HP17 8EQ",
    "wof:placetype": "postalcode"
  },
  "geometry": {"coordinates":[-0.940287,51.770648],"type":"Point"}
}
