{
  "type": "Feature",
  "properties": {
    "iso:country":"GB",
    "wof:name":"SL1 2LS",
    "wof:placetype":"postalcode"
},
  "geometry": {"coordinates":[-0.59871042210889,51.50594926165779],"type":"Point"}
}