{
  "type": "Feature",
  "properties": {
    "iso:country": "GB",
    "wof:name": "SL1 2LS",
    "wof:placetype": "postalcode"
  },
  "geometry": {"coordinates":[-0.59871,51.505949],"type":"Point"}
}
