{
  "type": "Feature",
  "properties": {
    "iso:country":"GB",
    "wof:name":"S5 9DH",
    "wof:placetype":"postalcode"
},
  "geometry": {"coordinates":[-1.47339000222957,53.43753072298016],"type":"Point"}
}