{
  "type": "Feature",
  "properties": {
    "date:inception_lower": "2019-12-01",
    "date:inception_upper": "2019-12-01",
    "iso:country": "GB",
    "wof:name": "HU8 7LA",
    "wof:placetype": "postalcode"
  },
  "geometry": {"coordinates":[-0.32306,53.750669],"type":"Point"}
}
