{
  "type": "Feature",
  "properties": {
    "iso:country": "GB",
    "wof:name": "HU8 7LA",
    "wof:placetype": "postalcode"
  },
  "geometry": {"coordinates":[-0.32306,53.750669],"type":"Point"}
}
