{
  "type": "Feature",
  "properties": {
    "iso:country": "GB",
    "wof:name": "SP10 1EF",
    "wof:placetype": "postalcode"
  },
  "geometry": {"coordinates":[-1.468365,51.219235],"type":"Point"}
}
