{
  "type": "Feature",
  "properties": {
    "date:inception_lower": "1981-06-01",
    "date:inception_upper": "1981-06-01",
    "iso:country": "GB",
    "wof:name": "OL16 5SX",
    "wof:placetype": "postalcode"
  },
  "geometry": {"coordinates":[-2.142669,53.609528],"type":"Point"}
}
