{
  "type": "Feature",
  "properties": {
    "iso:country":"GB",
    "wof:name":"B62 0HT",
    "wof:placetype":"postalcode"
},
  "geometry": {"coordinates":[-2.01403880706848,52.45418712006239],"type":"Point"}
}