{
  "type": "Feature",
  "properties": {
    "iso:country": "GB",
    "wof:name": "NE34 8TD",
    "wof:placetype": "postalcode"
  },
  "geometry": {"coordinates":[-1.421872,54.962965],"type":"Point"}
}
