{
  "type": "Feature",
  "properties": {
    "iso:country":"GB",
    "wof:name":"NE34 8TD",
    "wof:placetype":"postalcode"
},
  "geometry": {"coordinates":[-1.42187183586573,54.96296486601349],"type":"Point"}
}