{
  "type": "Feature",
  "properties": {
    "iso:country":"GB",
    "wof:name":"PL31 2DL",
    "wof:placetype":"postalcode"
},
  "geometry": {"coordinates":[-4.71824933700558,50.47121509502865],"type":"Point"}
}