{
  "type": "Feature",
  "properties": {
    "date:inception_lower":"1980-01-01",
    "date:inception_upper":"1980-01-31",
    "iso:country":"GB",
    "wof:name":"EH14 1JQ",
    "wof:placetype":"postalcode"
},
  "geometry": {"coordinates":[-3.247728,55.920165],"type":"Point"}
}