{
  "type": "Feature",
  "properties": {
    "date:inception_lower": "1980-01-01",
    "date:inception_upper": "1980-01-01",
    "iso:country": "GB",
    "wof:name": "HG5 0ND",
    "wof:placetype": "postalcode"
  },
  "geometry": {"coordinates":[-1.464631,54.017508],"type":"Point"}
}
