{
  "type": "Feature",
  "properties": {
    "iso:country":"GB",
    "wof:name":"HG5 0ND",
    "wof:placetype":"postalcode"
},
  "geometry": {"coordinates":[-1.46463108478786,54.01750797896048],"type":"Point"}
}