{
  "type": "Feature",
  "properties": {
    "iso:country": "GB",
    "wof:name": "CO2 0HZ",
    "wof:placetype": "postalcode"
  },
  "geometry": {"coordinates":[0.86659,51.848676],"type":"Point"}
}
