{
  "type": "Feature",
  "properties": {
    "iso:country":"GB",
    "wof:name":"CO2 0HZ",
    "wof:placetype":"postalcode"
},
  "geometry": {"coordinates":[0.86728311784673,51.84906143312397],"type":"Point"}
}