{
  "type": "Feature",
  "properties": {
    "iso:country":"GB",
    "wof:name":"HU9 4BL",
    "wof:placetype":"postalcode"
},
  "geometry": {"coordinates":[-0.26099412221249,53.77555393203626],"type":"Point"}
}