{
  "type": "Feature",
  "properties": {
    "iso:country":"GB",
    "wof:name":"DE65 6BD",
    "wof:placetype":"postalcode"
},
  "geometry": {"coordinates":[-1.5468678684581,52.87303459983127],"type":"Point"}
}