{
  "type": "Feature",
  "properties": {
    "iso:country": "GB",
    "wof:name": "AB51 4FR",
    "wof:placetype": "postalcode"
  },
  "geometry": {"coordinates":[-2.388004,57.293732],"type":"Point"}
}
