{
  "type": "Feature",
  "properties": {
    "date:inception_lower": "1999-06-01",
    "date:inception_upper": "1999-06-01",
    "iso:country": "GB",
    "wof:name": "CH42 7JS",
    "wof:placetype": "postalcode"
  },
  "geometry": {"coordinates":[-3.031824,53.37823],"type":"Point"}
}
