{
  "type": "Feature",
  "properties": {
    "date:inception_lower":"1980-01-01",
    "date:inception_upper":"1980-01-31",
    "iso:country":"GB",
    "wof:name":"DE14 1RB",
    "wof:placetype":"postalcode"
},
  "geometry": {"coordinates":[-1.624768,52.817293],"type":"Point"}
}