{
  "type": "Feature",
  "properties": {
    "iso:country":"GB",
    "wof:name":"BN18 8DF",
    "wof:placetype":"postalcode"
},
  "geometry": {"coordinates":[-0.5529225053537,50.85416044586174],"type":"Point"}
}