{
  "type": "Feature",
  "properties": {
    "date:inception_lower":"1980-01-01",
    "date:inception_upper":"1980-01-31",
    "iso:country":"GB",
    "wof:name":"TR4 8NH",
    "wof:placetype":"postalcode"
},
  "geometry": {"coordinates":[-5.15668,50.258157],"type":"Point"}
}