{
  "type": "Feature",
  "properties": {
    "iso:country":"GB",
    "wof:name":"TR4 8NH",
    "wof:placetype":"postalcode"
},
  "geometry": {"coordinates":[-5.15668847459062,50.25807622095259],"type":"Point"}
}