{
  "type": "Feature",
  "properties": {
    "iso:country": "GB",
    "wof:name": "TR4 8NH",
    "wof:placetype": "postalcode"
  },
  "geometry": {"coordinates":[-5.15668,50.258157],"type":"Point"}
}
