{
  "type": "Feature",
  "properties": {
    "date:inception_lower": "1980-01-01",
    "date:inception_upper": "1980-01-01",
    "iso:country": "GB",
    "wof:name": "TR4 8NH",
    "wof:placetype": "postalcode"
  },
  "geometry": {"coordinates":[-5.156736,50.258066],"type":"Point"}
}
