{
  "type": "Feature",
  "properties": {
    "iso:country": "GB",
    "wof:name": "CO11 1QQ",
    "wof:placetype": "postalcode"
  },
  "geometry": {"coordinates":[1.062878,51.95862],"type":"Point"}
}
