{
  "type": "Feature",
  "properties": {
    "iso:country":"GB",
    "wof:name":"S5 0GA",
    "wof:placetype":"postalcode"
},
  "geometry": {"coordinates":[-1.44182948318831,53.43477180550644],"type":"Point"}
}