{
  "type": "Feature",
  "properties": {
    "iso:country":"GB",
    "wof:name":"YO14 9RE",
    "wof:placetype":"postalcode"
},
  "geometry": {"coordinates":[-0.27950280195055,54.18829576170794],"type":"Point"}
}