{
  "type": "Feature",
  "properties": {
    "date:inception_lower":"1980-01-01",
    "date:inception_upper":"1980-01-31",
    "iso:country":"GB",
    "wof:name":"YO14 9RE",
    "wof:placetype":"postalcode"
},
  "geometry": {"coordinates":[-0.279503,54.188296],"type":"Point"}
}