{
  "type": "Feature",
  "properties": {
    "date:inception_lower": "2024-02-01",
    "date:inception_upper": "2024-02-01",
    "iso:country": "GB",
    "wof:name": "LA6 1FZ",
    "wof:placetype": "postalcode"
  },
  "geometry": {"coordinates":[-2.734824,54.126167],"type":"Point"}
}
