{
  "type": "Feature",
  "properties": {
    "iso:country": "GB",
    "wof:name": "LE12 8GZ",
    "wof:placetype": "postalcode"
  },
  "geometry": {"coordinates":[-1.151976,52.75433],"type":"Point"}
}
