{
  "type": "Feature",
  "properties": {
    "date:inception_lower": "2022-02-01",
    "date:inception_upper": "2022-02-01",
    "iso:country": "GB",
    "wof:name": "S41 8FA",
    "wof:placetype": "postalcode"
  },
  "geometry": {"coordinates":[-1.454222,53.262533],"type":"Point"}
}
