{
  "type": "Feature",
  "properties": {
    "date:inception_lower": "1980-01-01",
    "date:inception_upper": "1980-01-01",
    "iso:country": "GB",
    "wof:name": "CH3 7SW",
    "wof:placetype": "postalcode"
  },
  "geometry": {"coordinates":[-2.829902,53.207073],"type":"Point"}
}
