{
  "type": "Feature",
  "properties": {
    "iso:country":"GB",
    "wof:name":"CH3 7SW",
    "wof:placetype":"postalcode"
},
  "geometry": {"coordinates":[-2.8299024866528,53.20707296755283],"type":"Point"}
}