{
  "type": "Feature",
  "properties": {
    "iso:country": "GB",
    "wof:name": "TN37 6BQ",
    "wof:placetype": "postalcode"
  },
  "geometry": {"coordinates":[0.561118,50.861917],"type":"Point"}
}
