{
  "type": "Feature",
  "properties": {
    "iso:country": "GB",
    "wof:name": "TS17 0BB",
    "wof:placetype": "postalcode"
  },
  "geometry": {"coordinates":[-1.303136,54.539786],"type":"Point"}
}
