{
  "type": "Feature",
  "properties": {
    "iso:country":"GB",
    "wof:name":"TS17 0BB",
    "wof:placetype":"postalcode"
},
  "geometry": {"coordinates":[-1.30313572809321,54.53978589420753],"type":"Point"}
}