{
  "type": "Feature",
  "properties": {
    "date:inception_lower":"1995-07-01",
    "date:inception_upper":"1995-07-31",
    "iso:country":"GB",
    "wof:name":"HS2 9QH",
    "wof:placetype":"postalcode"
},
  "geometry": {"coordinates":[-6.41609,58.102422],"type":"Point"}
}