{
  "type": "Feature",
  "properties": {
    "iso:country":"GB",
    "wof:name":"HS2 9QH",
    "wof:placetype":"postalcode"
},
  "geometry": {"coordinates":[-6.41593722512697,58.10259948992994],"type":"Point"}
}