{
  "type": "Feature",
  "properties": {
    "date:inception_lower": "2001-12-01",
    "date:inception_upper": "2001-12-01",
    "iso:country": "GB",
    "wof:name": "BB7 4SB",
    "wof:placetype": "postalcode"
  },
  "geometry": {"coordinates":[-2.392194,53.8948],"type":"Point"}
}
