{
  "type": "Feature",
  "properties": {
    "iso:country": "GB",
    "wof:name": "BB7 4SB",
    "wof:placetype": "postalcode"
  },
  "geometry": {"coordinates":[-2.392194,53.8948],"type":"Point"}
}
