{
  "type": "Feature",
  "properties": {
    "iso:country":"GB",
    "wof:name":"BB7 4SB",
    "wof:placetype":"postalcode"
},
  "geometry": {"coordinates":[-2.39219386655122,53.89479981323606],"type":"Point"}
}