{
  "type": "Feature",
  "properties": {
    "date:inception_lower": "1984-10-01",
    "date:inception_upper": "1984-10-01",
    "iso:country": "GB",
    "wof:name": "OL11 2QS",
    "wof:placetype": "postalcode"
  },
  "geometry": {"coordinates":[-2.158276,53.595747],"type":"Point"}
}
