{
  "type": "Feature",
  "properties": {
    "iso:country":"GB",
    "wof:name":"ST5 8AR",
    "wof:placetype":"postalcode"
},
  "geometry": {"coordinates":[-2.22542599404057,53.03319789295426],"type":"Point"}
}