{
  "type": "Feature",
  "properties": {
    "iso:country":"GB",
    "wof:name":"CF46 6HJ",
    "wof:placetype":"postalcode"
},
  "geometry": {"coordinates":[-3.28532994028417,51.65066443142769],"type":"Point"}
}