{
  "type": "Feature",
  "properties": {
    "iso:country": "GB",
    "wof:name": "FK10 3ES",
    "wof:placetype": "postalcode"
  },
  "geometry": {"coordinates":[-3.78412,56.129601],"type":"Point"}
}
