{
  "type": "Feature",
  "properties": {
    "iso:country":"GB",
    "wof:name":"FK10 3ES",
    "wof:placetype":"postalcode"
},
  "geometry": {"coordinates":[-3.78412008836735,56.12960055537665],"type":"Point"}
}