{
  "type": "Feature",
  "properties": {
    "iso:country":"GB",
    "wof:name":"DT8 3SQ",
    "wof:placetype":"postalcode"
},
  "geometry": {"coordinates":[-2.69833006985424,50.83306192317368],"type":"Point"}
}