{
  "type": "Feature",
  "properties": {
    "iso:country": "GB",
    "wof:name": "DT8 3SQ",
    "wof:placetype": "postalcode"
  },
  "geometry": {"coordinates":[-2.69833,50.833062],"type":"Point"}
}
