{
  "type": "Feature",
  "properties": {
    "iso:country": "GB",
    "wof:name": "CH3 8LZ",
    "wof:placetype": "postalcode"
  },
  "geometry": {"coordinates":[-2.765546,53.193409],"type":"Point"}
}
