{
  "type": "Feature",
  "properties": {
    "iso:country":"GB",
    "wof:name":"CH3 8LZ",
    "wof:placetype":"postalcode"
},
  "geometry": {"coordinates":[-2.76554653560203,53.19340903968376],"type":"Point"}
}