{
  "type": "Feature",
  "properties": {
    "iso:country":"GB",
    "wof:name":"WC2E 8JF",
    "wof:placetype":"postalcode"
},
  "geometry": {"coordinates":[-0.12478160762822,51.51133462262951],"type":"Point"}
}