{
  "type": "Feature",
  "properties": {
    "iso:country":"GB",
    "wof:name":"SG1 4DL",
    "wof:placetype":"postalcode"
},
  "geometry": {"coordinates":[-0.18768559841494,51.92308577057726],"type":"Point"}
}