{
  "type": "Feature",
  "properties": {
    "iso:country":"GB",
    "wof:name":"ML4 3HA",
    "wof:placetype":"postalcode"
},
  "geometry": {"coordinates":[-4.02565787678447,55.82676684181303],"type":"Point"}
}