{
  "type": "Feature",
  "properties": {
    "date:inception_lower":"1980-01-01",
    "date:inception_upper":"1980-01-31",
    "iso:country":"GB",
    "wof:name":"ML4 3HA",
    "wof:placetype":"postalcode"
},
  "geometry": {"coordinates":[-4.025658,55.826767],"type":"Point"}
}