{
  "type": "Feature",
  "properties": {
    "iso:country":"GB",
    "wof:name":"SW11 5DN",
    "wof:placetype":"postalcode"
},
  "geometry": {"coordinates":[-0.15880129039791,51.47250437534828],"type":"Point"}
}