{
  "type": "Feature",
  "properties": {
    "iso:country":"GB",
    "wof:name":"SR2 8BZ",
    "wof:placetype":"postalcode"
},
  "geometry": {"coordinates":[-1.37001786206689,54.90014382242149],"type":"Point"}
}