{
  "type": "Feature",
  "properties": {
    "date:inception_lower": "1980-01-01",
    "date:inception_upper": "1980-01-01",
    "iso:country": "GB",
    "wof:name": "SA10 8SB",
    "wof:placetype": "postalcode"
  },
  "geometry": {"coordinates":[-3.751061,51.726119],"type":"Point"}
}
