{
  "type": "Feature",
  "properties": {
    "iso:country": "GB",
    "wof:name": "CF40 2QN",
    "wof:placetype": "postalcode"
  },
  "geometry": {"coordinates":[-3.449002,51.62086],"type":"Point"}
}
