{
  "type": "Feature",
  "properties": {
    "iso:country":"GB",
    "wof:name":"NE5 2DJ",
    "wof:placetype":"postalcode"
},
  "geometry": {"coordinates":[-1.6729518684804,54.9854477113867],"type":"Point"}
}