{
  "type": "Feature",
  "properties": {
    "date:inception_lower": "1995-12-01",
    "date:inception_upper": "1995-12-01",
    "iso:country": "GB",
    "wof:name": "G72 0AR",
    "wof:placetype": "postalcode"
  },
  "geometry": {"coordinates":[-4.095027,55.794042],"type":"Point"}
}
