{
  "type": "Feature",
  "properties": {
    "iso:country": "GB",
    "wof:name": "G72 0AR",
    "wof:placetype": "postalcode"
  },
  "geometry": {"coordinates":[-4.095027,55.794042],"type":"Point"}
}
