{
  "type": "Feature",
  "properties": {
    "iso:country":"GB",
    "wof:name":"TN28 8HF",
    "wof:placetype":"postalcode"
},
  "geometry": {"coordinates":[0.93230836435209,50.9857047445912],"type":"Point"}
}