{
  "type": "Feature",
  "properties": {
    "iso:country": "GB",
    "wof:name": "TN28 8HF",
    "wof:placetype": "postalcode"
  },
  "geometry": {"coordinates":[0.932308,50.985705],"type":"Point"}
}
