{
  "type": "Feature",
  "properties": {
    "iso:country":"GB",
    "wof:name":"TS7 0DB",
    "wof:placetype":"postalcode"
},
  "geometry": {"coordinates":[-1.17561380532506,54.52559349212719],"type":"Point"}
}