{
  "type": "Feature",
  "properties": {
    "iso:country":"GB",
    "wof:name":"B64 6AH",
    "wof:placetype":"postalcode"
},
  "geometry": {"coordinates":[-2.08389470404671,52.47039396364865],"type":"Point"}
}