{
  "type": "Feature",
  "properties": {
    "date:inception_lower":"1980-01-01",
    "date:inception_upper":"1980-01-31",
    "iso:country":"GB",
    "wof:name":"B20 1NL",
    "wof:placetype":"postalcode"
},
  "geometry": {"coordinates":[-1.938917,52.517749],"type":"Point"}
}