{
  "type": "Feature",
  "properties": {
    "iso:country":"GB",
    "wof:name":"B20 1NL",
    "wof:placetype":"postalcode"
},
  "geometry": {"coordinates":[-1.93891692829378,52.51774927589268],"type":"Point"}
}