{
  "type": "Feature",
  "properties": {
    "date:inception_lower": "2022-04-01",
    "date:inception_upper": "2022-04-01",
    "iso:country": "GB",
    "wof:name": "CV7 8QT",
    "wof:placetype": "postalcode"
  },
  "geometry": {"coordinates":[-1.544031,52.448454],"type":"Point"}
}
