{
  "type": "Feature",
  "properties": {
    "iso:country":"GB",
    "wof:name":"S42 7AT",
    "wof:placetype":"postalcode"
},
  "geometry": {"coordinates":[-1.49390357445426,53.25511200021948],"type":"Point"}
}