{
  "type": "Feature",
  "properties": {
    "iso:country":"GB",
    "wof:name":"PE19 2EL",
    "wof:placetype":"postalcode"
},
  "geometry": {"coordinates":[-0.25948280421632,52.22475823452176],"type":"Point"}
}