{
  "type": "Feature",
  "properties": {
    "iso:country":"GB",
    "wof:name":"CF42 5DY",
    "wof:placetype":"postalcode"
},
  "geometry": {"coordinates":[-3.56514488672788,51.67659029362643],"type":"Point"}
}