{
  "type": "Feature",
  "properties": {
    "date:inception_lower": "1985-10-01",
    "date:inception_upper": "1985-10-01",
    "iso:country": "GB",
    "wof:name": "FY6 7ES",
    "wof:placetype": "postalcode"
  },
  "geometry": {"coordinates":[-2.995512,53.851952],"type":"Point"}
}
