{
  "type": "Feature",
  "properties": {
    "iso:country":"GB",
    "wof:name":"LE4 3LS",
    "wof:placetype":"postalcode"
},
  "geometry": {"coordinates":[-1.12843084306473,52.68528761638835],"type":"Point"}
}