{
  "type": "Feature",
  "properties": {
    "iso:country":"GB",
    "wof:name":"HD8 0TS",
    "wof:placetype":"postalcode"
},
  "geometry": {"coordinates":[-1.69085114420225,53.61531752969498],"type":"Point"}
}