{
  "type": "Feature",
  "properties": {
    "date:inception_lower": "1980-01-01",
    "date:inception_upper": "1980-01-01",
    "iso:country": "GB",
    "wof:name": "HD8 0TS",
    "wof:placetype": "postalcode"
  },
  "geometry": {"coordinates":[-1.690899,53.615315],"type":"Point"}
}
