{
  "type": "Feature",
  "properties": {
    "iso:country": "GB",
    "wof:name": "ST8 9BP",
    "wof:placetype": "postalcode"
  },
  "geometry": {"coordinates":[-2.173984,53.11557],"type":"Point"}
}
