{
  "type": "Feature",
  "properties": {
    "iso:country":"GB",
    "wof:name":"BS8 4NU",
    "wof:placetype":"postalcode"
},
  "geometry": {"coordinates":[-2.62608604668575,51.45248127072016],"type":"Point"}
}