{
  "type": "Feature",
  "properties": {
    "iso:country":"GB",
    "wof:name":"LN6 8TJ",
    "wof:placetype":"postalcode"
},
  "geometry": {"coordinates":[-0.58096525774316,53.1957827936695],"type":"Point"}
}