{
  "type": "Feature",
  "properties": {
    "iso:country":"GB",
    "wof:name":"IG11 7DL",
    "wof:placetype":"postalcode"
},
  "geometry": {"coordinates":[0.08693771969158,51.53398115820814],"type":"Point"}
}