{
  "type": "Feature",
  "properties": {
    "iso:country": "GB",
    "wof:name": "IG11 7DL",
    "wof:placetype": "postalcode"
  },
  "geometry": {"coordinates":[0.086938,51.533981],"type":"Point"}
}
