{
  "type": "Feature",
  "properties": {
    "iso:country":"GB",
    "wof:name":"B20 3NJ",
    "wof:placetype":"postalcode"
},
  "geometry": {"coordinates":[-1.91098312097142,52.51427051208166],"type":"Point"}
}