{
  "type": "Feature",
  "properties": {
    "iso:country":"GB",
    "wof:name":"BR1 2QE",
    "wof:placetype":"postalcode"
},
  "geometry": {"coordinates":[0.0356111453439,51.40373245733137],"type":"Point"}
}