{
  "type": "Feature",
  "properties": {
    "iso:country":"GB",
    "wof:name":"SY13 4NL",
    "wof:placetype":"postalcode"
},
  "geometry": {"coordinates":[-2.66963132889782,52.96149879958937],"type":"Point"}
}