{
  "type": "Feature",
  "properties": {
    "iso:country": "GB",
    "wof:name": "LE7 9RP",
    "wof:placetype": "postalcode"
  },
  "geometry": {"coordinates":[-1.030112,52.63053],"type":"Point"}
}
