{
  "type": "Feature",
  "properties": {
    "iso:country":"GB",
    "wof:name":"LE7 9RP",
    "wof:placetype":"postalcode"
},
  "geometry": {"coordinates":[-1.03011226478007,52.63053007139313],"type":"Point"}
}