{
  "type": "Feature",
  "properties": {
    "date:inception_lower":"1980-01-01",
    "date:inception_upper":"1980-01-31",
    "iso:country":"GB",
    "wof:name":"TA4 3PL",
    "wof:placetype":"postalcode"
},
  "geometry": {"coordinates":[-3.252461,51.07635],"type":"Point"}
}