{
  "type": "Feature",
  "properties": {
    "iso:country":"GB",
    "wof:name":"TA4 3PL",
    "wof:placetype":"postalcode"
},
  "geometry": {"coordinates":[-3.25246077228358,51.07634961688876],"type":"Point"}
}