{
  "type": "Feature",
  "properties": {
    "iso:country": "GB",
    "wof:name": "ML1 5BJ",
    "wof:placetype": "postalcode"
  },
  "geometry": {"coordinates":[-3.945373,55.814745],"type":"Point"}
}
