{
  "type": "Feature",
  "properties": {
    "date:inception_lower":"1980-01-01",
    "date:inception_upper":"1980-01-31",
    "iso:country":"GB",
    "wof:name":"ML1 5BJ",
    "wof:placetype":"postalcode"
},
  "geometry": {"coordinates":[-3.945373,55.814745],"type":"Point"}
}