{
  "type": "Feature",
  "properties": {
    "iso:country":"GB",
    "wof:name":"ML1 5BJ",
    "wof:placetype":"postalcode"
},
  "geometry": {"coordinates":[-3.94537311411999,55.81474467897904],"type":"Point"}
}