{
  "type": "Feature",
  "properties": {
    "date:inception_lower": "2023-04-01",
    "date:inception_upper": "2023-04-01",
    "iso:country": "GB",
    "wof:name": "OX14 9NT",
    "wof:placetype": "postalcode"
  },
  "geometry": {"coordinates":[-1.287686,51.669213],"type":"Point"}
}
