{
  "type": "Feature",
  "properties": {
    "iso:country":"GB",
    "wof:name":"SK23 9US",
    "wof:placetype":"postalcode"
},
  "geometry": {"coordinates":[-1.9376985530707,53.30536421491281],"type":"Point"}
}