{
  "type": "Feature",
  "properties": {
    "date:inception_lower": "1996-12-01",
    "date:inception_upper": "1996-12-01",
    "iso:country": "GB",
    "wof:name": "SK23 9US",
    "wof:placetype": "postalcode"
  },
  "geometry": {"coordinates":[-1.937699,53.305364],"type":"Point"}
}
