{
  "type": "Feature",
  "properties": {
    "iso:country": "GB",
    "wof:name": "SK23 9US",
    "wof:placetype": "postalcode"
  },
  "geometry": {"coordinates":[-1.937699,53.305364],"type":"Point"}
}
