{
  "type": "Feature",
  "properties": {
    "iso:country":"GB",
    "wof:name":"SY13 2LL",
    "wof:placetype":"postalcode"
},
  "geometry": {"coordinates":[-2.80505824930421,52.91236681705055],"type":"Point"}
}