{
  "type": "Feature",
  "properties": {
    "iso:country": "GB",
    "wof:name": "SE22 8GB",
    "wof:placetype": "postalcode"
  },
  "geometry": {"coordinates":[-0.068977,51.443911],"type":"Point"}
}
