{
  "type": "Feature",
  "properties": {
    "date:inception_lower":"2002-08-01",
    "date:inception_upper":"2002-08-31",
    "iso:country":"GB",
    "wof:name":"SE22 8GB",
    "wof:placetype":"postalcode"
},
  "geometry": {"coordinates":[-0.068977,51.443911],"type":"Point"}
}