{
  "type": "Feature",
  "properties": {
    "iso:country":"GB",
    "wof:name":"SE22 8GB",
    "wof:placetype":"postalcode"
},
  "geometry": {"coordinates":[-0.06897654300303,51.44391054041523],"type":"Point"}
}