{
  "type": "Feature",
  "properties": {
    "iso:country":"GB",
    "wof:name":"WD4 9AD",
    "wof:placetype":"postalcode"
},
  "geometry": {"coordinates":[-0.46535664402893,51.68622553018204],"type":"Point"}
}