{
  "type": "Feature",
  "properties": {
    "iso:country": "GB",
    "wof:name": "WD4 9AD",
    "wof:placetype": "postalcode"
  },
  "geometry": {"coordinates":[-0.465357,51.686226],"type":"Point"}
}
