{
  "type": "Feature",
  "properties": {
    "date:inception_lower": "2016-06-01",
    "date:inception_upper": "2016-06-01",
    "iso:country": "GB",
    "wof:name": "BL9 9FY",
    "wof:placetype": "postalcode"
  },
  "geometry": {"coordinates":[-2.292193,53.574748],"type":"Point"}
}
