{
  "type": "Feature",
  "properties": {
    "iso:country":"GB",
    "wof:name":"HU6 8DB",
    "wof:placetype":"postalcode"
},
  "geometry": {"coordinates":[-0.38006930005244,53.78009848568052],"type":"Point"}
}