{
  "type": "Feature",
  "properties": {
    "iso:country":"GB",
    "wof:name":"DN19 7JF",
    "wof:placetype":"postalcode"
},
  "geometry": {"coordinates":[-0.33021921237734,53.67701858814124],"type":"Point"}
}