{
  "type": "Feature",
  "properties": {
    "date:inception_lower": "1980-01-01",
    "date:inception_upper": "1980-01-01",
    "iso:country": "GB",
    "wof:name": "DN19 7JF",
    "wof:placetype": "postalcode"
  },
  "geometry": {"coordinates":[-0.330219,53.677019],"type":"Point"}
}
