{
  "type": "Feature",
  "properties": {
    "iso:country":"GB",
    "wof:name":"FK8 3EX",
    "wof:placetype":"postalcode"
},
  "geometry": {"coordinates":[-4.25815056907608,56.13293200692108],"type":"Point"}
}