{
  "type": "Feature",
  "properties": {
    "iso:country":"GB",
    "wof:name":"DT11 8DA",
    "wof:placetype":"postalcode"
},
  "geometry": {"coordinates":[-2.06795079941266,50.9201744706055],"type":"Point"}
}