{
  "type": "Feature",
  "properties": {
    "iso:country": "GB",
    "wof:name": "DT11 8DA",
    "wof:placetype": "postalcode"
  },
  "geometry": {"coordinates":[-2.067951,50.920174],"type":"Point"}
}
