{
  "type": "Feature",
  "properties": {
    "iso:country":"GB",
    "wof:name":"ML5 4EQ",
    "wof:placetype":"postalcode"
},
  "geometry": {"coordinates":[-4.03359704985089,55.85223078094566],"type":"Point"}
}