{
  "type": "Feature",
  "properties": {
    "iso:country":"GB",
    "wof:name":"NG20 9HB",
    "wof:placetype":"postalcode"
},
  "geometry": {"coordinates":[-1.20313638747273,53.2345299795468],"type":"Point"}
}