{
  "type": "Feature",
  "properties": {
    "iso:country": "GB",
    "wof:name": "NG20 9HB",
    "wof:placetype": "postalcode"
  },
  "geometry": {"coordinates":[-1.203135,53.234541],"type":"Point"}
}
