{
  "type": "Feature",
  "properties": {
    "iso:country":"GB",
    "wof:name":"PE21 7RX",
    "wof:placetype":"postalcode"
},
  "geometry": {"coordinates":[-0.02579599519361,52.96586453543151],"type":"Point"}
}