{
  "type": "Feature",
  "properties": {
    "date:inception_lower": "1993-01-01",
    "date:inception_upper": "1993-01-01",
    "iso:country": "GB",
    "wof:name": "PE21 7RX",
    "wof:placetype": "postalcode"
  },
  "geometry": {"coordinates":[-0.025796,52.965865],"type":"Point"}
}
