{
  "type": "Feature",
  "properties": {
    "iso:country":"GB",
    "wof:name":"IG1 2EW",
    "wof:placetype":"postalcode"
},
  "geometry": {"coordinates":[0.07147245997348,51.55349072926808],"type":"Point"}
}