{
  "type": "Feature",
  "properties": {
    "iso:country": "GB",
    "wof:name": "SO20 8BN",
    "wof:placetype": "postalcode"
  },
  "geometry": {"coordinates":[-1.557571,51.091928],"type":"Point"}
}
