{
  "type": "Feature",
  "properties": {
    "iso:country":"GB",
    "wof:name":"SO20 8BN",
    "wof:placetype":"postalcode"
},
  "geometry": {"coordinates":[-1.5575708064634,51.09192815604924],"type":"Point"}
}