{
  "type": "Feature",
  "properties": {
    "date:inception_lower": "1988-03-01",
    "date:inception_upper": "1988-03-01",
    "iso:country": "GB",
    "wof:name": "SO20 8BN",
    "wof:placetype": "postalcode"
  },
  "geometry": {"coordinates":[-1.557571,51.091928],"type":"Point"}
}
