{
  "type": "Feature",
  "properties": {
    "iso:country": "GB",
    "wof:name": "NE47 6DA",
    "wof:placetype": "postalcode"
  },
  "geometry": {"coordinates":[-2.276392,54.965542],"type":"Point"}
}
