{
  "type": "Feature",
  "properties": {
    "iso:country":"GB",
    "wof:name":"NE47 6DA",
    "wof:placetype":"postalcode"
},
  "geometry": {"coordinates":[-2.27639210647833,54.9655417521524],"type":"Point"}
}