{
  "type": "Feature",
  "properties": {
    "iso:country":"GB",
    "wof:name":"LL12 7UP",
    "wof:placetype":"postalcode"
},
  "geometry": {"coordinates":[-2.9793844406527,53.05835098744037],"type":"Point"}
}