{
  "type": "Feature",
  "properties": {
    "iso:country":"GB",
    "wof:name":"PO35 5ST",
    "wof:placetype":"postalcode"
},
  "geometry": {"coordinates":[-1.07822554899398,50.68873512866882],"type":"Point"}
}