{
  "type": "Feature",
  "properties": {
    "iso:country": "GB",
    "wof:name": "BS30 6PJ",
    "wof:placetype": "postalcode"
  },
  "geometry": {"coordinates":[-2.476568,51.438097],"type":"Point"}
}
