{
  "type": "Feature",
  "properties": {
    "date:inception_lower":"1997-12-01",
    "date:inception_upper":"1997-12-31",
    "iso:country":"GB",
    "wof:name":"BS30 6PJ",
    "wof:placetype":"postalcode"
},
  "geometry": {"coordinates":[-2.476568,51.438097],"type":"Point"}
}