{
  "type": "Feature",
  "properties": {
    "iso:country":"GB",
    "wof:name":"BS30 6PJ",
    "wof:placetype":"postalcode"
},
  "geometry": {"coordinates":[-2.47656846028267,51.43809672057448],"type":"Point"}
}