{
  "type": "Feature",
  "properties": {
    "date:inception_lower": "2018-07-01",
    "date:inception_upper": "2018-07-01",
    "iso:country": "GB",
    "wof:name": "B16 8WG",
    "wof:placetype": "postalcode"
  },
  "geometry": {"coordinates":[-1.914117,52.476188],"type":"Point"}
}
