{
  "type": "Feature",
  "properties": {
    "iso:country": "GB",
    "wof:name": "NN3 6NG",
    "wof:placetype": "postalcode"
  },
  "geometry": {"coordinates":[-0.870424,52.269192],"type":"Point"}
}
