{
  "type": "Feature",
  "properties": {
    "iso:country":"GB",
    "wof:name":"NN3 6NG",
    "wof:placetype":"postalcode"
},
  "geometry": {"coordinates":[-0.87042360282729,52.26919172324281],"type":"Point"}
}