{
  "type": "Feature",
  "properties": {
    "iso:country": "GB",
    "wof:name": "OX17 1QD",
    "wof:placetype": "postalcode"
  },
  "geometry": {"coordinates":[-1.318203,52.11755],"type":"Point"}
}
