{
  "type": "Feature",
  "properties": {
    "iso:country":"GB",
    "wof:name":"M11 3DT",
    "wof:placetype":"postalcode"
},
  "geometry": {"coordinates":[-2.20419517435904,53.47721073151599],"type":"Point"}
}