{
  "type": "Feature",
  "properties": {
    "iso:country":"GB",
    "wof:name":"SP2 7HE",
    "wof:placetype":"postalcode"
},
  "geometry": {"coordinates":[-1.81236767039469,51.07742641495991],"type":"Point"}
}