{
  "type": "Feature",
  "properties": {
    "date:inception_lower": "2002-09-01",
    "date:inception_upper": "2002-09-01",
    "iso:country": "GB",
    "wof:name": "DD3 0RN",
    "wof:placetype": "postalcode"
  },
  "geometry": {"coordinates":[-3.011595,56.499952],"type":"Point"}
}
