{
  "type": "Feature",
  "properties": {
    "iso:country":"GB",
    "wof:name":"DD3 0RN",
    "wof:placetype":"postalcode"
},
  "geometry": {"coordinates":[-3.01159525688134,56.49995241515978],"type":"Point"}
}