{
  "type": "Feature",
  "properties": {
    "iso:country": "GB",
    "wof:name": "LN11 9SA",
    "wof:placetype": "postalcode"
  },
  "geometry": {"coordinates":[-0.048754,53.326172],"type":"Point"}
}
