{
  "type": "Feature",
  "properties": {
    "iso:country":"GB",
    "wof:name":"L8 6QW",
    "wof:placetype":"postalcode"
},
  "geometry": {"coordinates":[-2.97170390389743,53.38597113954985],"type":"Point"}
}