{
  "type": "Feature",
  "properties": {
    "iso:country": "GB",
    "wof:name": "L8 6QW",
    "wof:placetype": "postalcode"
  },
  "geometry": {"coordinates":[-2.971704,53.385971],"type":"Point"}
}
