{
  "type": "Feature",
  "properties": {
    "date:inception_lower": "2023-05-01",
    "date:inception_upper": "2023-05-01",
    "iso:country": "GB",
    "wof:name": "WA16 0XQ",
    "wof:placetype": "postalcode"
  },
  "geometry": {"coordinates":[-2.388221,53.305231],"type":"Point"}
}
