{
  "type": "Feature",
  "properties": {
    "iso:country":"GB",
    "wof:name":"BN2 8LP",
    "wof:placetype":"postalcode"
},
  "geometry": {"coordinates":[-0.03830159649878,50.80423940132115],"type":"Point"}
}