{
  "type": "Feature",
  "properties": {
    "iso:country":"GB",
    "wof:name":"KT6 6BE",
    "wof:placetype":"postalcode"
},
  "geometry": {"coordinates":[-0.29620511323149,51.38681512234124],"type":"Point"}
}