{
  "type": "Feature",
  "properties": {
    "iso:country":"GB",
    "wof:name":"BB9 9EY",
    "wof:placetype":"postalcode"
},
  "geometry": {"coordinates":[-2.19958927732608,53.83649423183368],"type":"Point"}
}