{
  "type": "Feature",
  "properties": {
    "date:inception_lower": "2022-08-01",
    "date:inception_upper": "2022-08-01",
    "iso:country": "GB",
    "wof:name": "PE28 5WR",
    "wof:placetype": "postalcode"
  },
  "geometry": {"coordinates":[-0.290104,52.434206],"type":"Point"}
}
