{
  "type": "Feature",
  "properties": {
    "iso:country":"GB",
    "wof:name":"PA20 0LL",
    "wof:placetype":"postalcode"
},
  "geometry": {"coordinates":[-5.08029602733521,55.86023823515318],"type":"Point"}
}