{
  "type": "Feature",
  "properties": {
    "iso:country":"GB",
    "wof:name":"PE7 3AE",
    "wof:placetype":"postalcode"
},
  "geometry": {"coordinates":[-0.26648211537105,52.51437693407485],"type":"Point"}
}