{
  "type": "Feature",
  "properties": {
    "date:inception_lower": "2000-06-01",
    "date:inception_upper": "2000-06-01",
    "iso:country": "GB",
    "wof:name": "CA7 4TP",
    "wof:placetype": "postalcode"
  },
  "geometry": {"coordinates":[-3.28866,54.840253],"type":"Point"}
}
