{
  "type": "Feature",
  "properties": {
    "iso:country":"GB",
    "wof:name":"CA7 4TP",
    "wof:placetype":"postalcode"
},
  "geometry": {"coordinates":[-3.2886601383331,54.84025259425384],"type":"Point"}
}