{
  "type": "Feature",
  "properties": {
    "iso:country":"GB",
    "wof:name":"PO14 3JB",
    "wof:placetype":"postalcode"
},
  "geometry": {"coordinates":[-1.22115637601391,50.83190820598335],"type":"Point"}
}