{
  "type": "Feature",
  "properties": {
    "iso:country":"GB",
    "wof:name":"KA10 6SE",
    "wof:placetype":"postalcode"
},
  "geometry": {"coordinates":[-4.65141549724256,55.55857928889553],"type":"Point"}
}