{
  "type": "Feature",
  "properties": {
    "iso:country":"GB",
    "wof:name":"LA4 4DR",
    "wof:placetype":"postalcode"
},
  "geometry": {"coordinates":[-2.87558115855641,54.06705424116652],"type":"Point"}
}