{
  "type": "Feature",
  "properties": {
    "iso:country":"GB",
    "wof:name":"TA9 4DX",
    "wof:placetype":"postalcode"
},
  "geometry": {"coordinates":[-2.95354711583701,51.24900738666418],"type":"Point"}
}