{
  "type": "Feature",
  "properties": {
    "iso:country": "GB",
    "wof:name": "TA9 4DX",
    "wof:placetype": "postalcode"
  },
  "geometry": {"coordinates":[-2.953547,51.249007],"type":"Point"}
}
