{
  "type": "Feature",
  "properties": {
    "date:inception_lower":"1980-01-01",
    "date:inception_upper":"1980-01-31",
    "iso:country":"GB",
    "wof:name":"TA9 4DX",
    "wof:placetype":"postalcode"
},
  "geometry": {"coordinates":[-2.953547,51.249007],"type":"Point"}
}