{
  "type": "Feature",
  "properties": {
    "iso:country":"GB",
    "wof:name":"BR3 5HW",
    "wof:placetype":"postalcode"
},
  "geometry": {"coordinates":[-0.01393364487401,51.4094028261453],"type":"Point"}
}