{
  "type": "Feature",
  "properties": {
    "iso:country":"GB",
    "wof:name":"CR4 3NY",
    "wof:placetype":"postalcode"
},
  "geometry": {"coordinates":[-0.16563941487032,51.4043039051752],"type":"Point"}
}