{
  "type": "Feature",
  "properties": {
    "iso:country": "GB",
    "wof:name": "WA14 1SB",
    "wof:placetype": "postalcode"
  },
  "geometry": {"coordinates":[-2.351537,53.386235],"type":"Point"}
}
