{
  "type": "Feature",
  "properties": {
    "date:inception_lower":"1999-12-01",
    "date:inception_upper":"1999-12-31",
    "iso:country":"GB",
    "wof:name":"UB2 5QS",
    "wof:placetype":"postalcode"
},
  "geometry": {"coordinates":[-0.382085,51.497757],"type":"Point"}
}