{
  "type": "Feature",
  "properties": {
    "iso:country":"GB",
    "wof:name":"UB2 5QS",
    "wof:placetype":"postalcode"
},
  "geometry": {"coordinates":[-0.38208516666106,51.49775698407085],"type":"Point"}
}