{
  "type": "Feature",
  "properties": {
    "date:inception_lower": "2024-10-01",
    "date:inception_upper": "2024-10-01",
    "iso:country": "GB",
    "wof:name": "CB22 3GL",
    "wof:placetype": "postalcode"
  },
  "geometry": {"coordinates":[0.183128,52.126682],"type":"Point"}
}
