{
  "type": "Feature",
  "properties": {
    "date:inception_lower":"1980-01-01",
    "date:inception_upper":"1980-01-31",
    "iso:country":"GB",
    "wof:name":"SK6 7HL",
    "wof:placetype":"postalcode"
},
  "geometry": {"coordinates":[-2.059318,53.385706],"type":"Point"}
}