{
  "type": "Feature",
  "properties": {
    "iso:country":"GB",
    "wof:name":"SK6 7HL",
    "wof:placetype":"postalcode"
},
  "geometry": {"coordinates":[-2.05931790263354,53.38570593913376],"type":"Point"}
}