{
  "type": "Feature",
  "properties": {
    "iso:country":"GB",
    "wof:name":"TN13 3JD",
    "wof:placetype":"postalcode"
},
  "geometry": {"coordinates":[0.18010580911391,51.28079589861458],"type":"Point"}
}