{
  "type": "Feature",
  "properties": {
    "iso:country":"GB",
    "wof:name":"OX15 4ET",
    "wof:placetype":"postalcode"
},
  "geometry": {"coordinates":[-1.37548702744531,52.01679980749048],"type":"Point"}
}