{
  "type": "Feature",
  "properties": {
    "iso:country": "GB",
    "wof:name": "OX15 4ET",
    "wof:placetype": "postalcode"
  },
  "geometry": {"coordinates":[-1.375587,52.016874],"type":"Point"}
}
