{
  "type": "Feature",
  "properties": {
    "iso:country":"GB",
    "wof:name":"CO4 9UW",
    "wof:placetype":"postalcode"
},
  "geometry": {"coordinates":[0.91323189960991,51.90975399460607],"type":"Point"}
}