{
  "type": "Feature",
  "properties": {
    "iso:country":"GB",
    "wof:name":"TS25 4EY",
    "wof:placetype":"postalcode"
},
  "geometry": {"coordinates":[-1.24342129759668,54.66293571574023],"type":"Point"}
}