{
  "type": "Feature",
  "properties": {
    "date:inception_lower": "2021-05-01",
    "date:inception_upper": "2021-05-01",
    "iso:country": "GB",
    "wof:name": "DN4 8FN",
    "wof:placetype": "postalcode"
  },
  "geometry": {"coordinates":[-1.130995,53.49628],"type":"Point"}
}
