{
  "type": "Feature",
  "properties": {
    "iso:country": "GB",
    "wof:name": "NE8 3DJ",
    "wof:placetype": "postalcode"
  },
  "geometry": {"coordinates":[-1.597364,54.955917],"type":"Point"}
}
