{
  "type": "Feature",
  "properties": {
    "iso:country":"GB",
    "wof:name":"GL50 1LN",
    "wof:placetype":"postalcode"
},
  "geometry": {"coordinates":[-2.07539946161342,51.90087515263743],"type":"Point"}
}