{
  "type": "Feature",
  "properties": {
    "iso:country": "GB",
    "wof:name": "ST4 2HN",
    "wof:placetype": "postalcode"
  },
  "geometry": {"coordinates":[-2.177074,53.005809],"type":"Point"}
}
