{
  "type": "Feature",
  "properties": {
    "date:inception_lower":"1983-07-01",
    "date:inception_upper":"1983-07-31",
    "iso:country":"GB",
    "wof:name":"ST4 2HN",
    "wof:placetype":"postalcode"
},
  "geometry": {"coordinates":[-2.177074,53.005809],"type":"Point"}
}