{
  "type": "Feature",
  "properties": {
    "iso:country":"GB",
    "wof:name":"ST4 2HN",
    "wof:placetype":"postalcode"
},
  "geometry": {"coordinates":[-2.17707381559012,53.00580896829151],"type":"Point"}
}