{
  "type": "Feature",
  "properties": {
    "iso:country":"GB",
    "wof:name":"M26 2DL",
    "wof:placetype":"postalcode"
},
  "geometry": {"coordinates":[-2.31016933826679,53.56899679448334],"type":"Point"}
}