{
  "type": "Feature",
  "properties": {
    "date:inception_lower": "1995-12-01",
    "date:inception_upper": "1995-12-01",
    "iso:country": "GB",
    "wof:name": "M26 2DL",
    "wof:placetype": "postalcode"
  },
  "geometry": {"coordinates":[-2.311417,53.568488],"type":"Point"}
}
