{
  "type": "Feature",
  "properties": {
    "iso:country":"GB",
    "wof:name":"N13 4PA",
    "wof:placetype":"postalcode"
},
  "geometry": {"coordinates":[-0.11778665071488,51.61453699866745],"type":"Point"}
}