{
  "type": "Feature",
  "properties": {
    "iso:country": "GB",
    "wof:name": "RG20 5LZ",
    "wof:placetype": "postalcode"
  },
  "geometry": {"coordinates":[-1.233372,51.324182],"type":"Point"}
}
