{
  "type": "Feature",
  "properties": {
    "iso:country":"GB",
    "wof:name":"RG20 5LZ",
    "wof:placetype":"postalcode"
},
  "geometry": {"coordinates":[-1.23337238495126,51.32418177252335],"type":"Point"}
}