{
  "type": "Feature",
  "properties": {
    "iso:country":"GB",
    "wof:name":"SN8 3AL",
    "wof:placetype":"postalcode"
},
  "geometry": {"coordinates":[-1.66693707892949,51.34770634115148],"type":"Point"}
}