{
  "type": "Feature",
  "properties": {
    "iso:country":"GB",
    "wof:name":"SN7 8HJ",
    "wof:placetype":"postalcode"
},
  "geometry": {"coordinates":[-1.51301924667984,51.63943822382232],"type":"Point"}
}