{
  "type": "Feature",
  "properties": {
    "iso:country":"GB",
    "wof:name":"NP26 5PY",
    "wof:placetype":"postalcode"
},
  "geometry": {"coordinates":[-2.73604459498977,51.58793916145461],"type":"Point"}
}