{
  "type": "Feature",
  "properties": {
    "date:inception_lower":"1990-02-01",
    "date:inception_upper":"1990-02-28",
    "iso:country":"GB",
    "wof:name":"YO21 2DH",
    "wof:placetype":"postalcode"
},
  "geometry": {"coordinates":[-0.938942,54.462644],"type":"Point"}
}