{
  "type": "Feature",
  "properties": {
    "iso:country":"GB",
    "wof:name":"YO21 2DH",
    "wof:placetype":"postalcode"
},
  "geometry": {"coordinates":[-0.93894206285487,54.46264383318545],"type":"Point"}
}