{
  "type": "Feature",
  "properties": {
    "iso:country":"GB",
    "wof:name":"RM16 3BB",
    "wof:placetype":"postalcode"
},
  "geometry": {"coordinates":[0.37508295003494,51.50440728557499],"type":"Point"}
}