{
  "type": "Feature",
  "properties": {
    "date:inception_lower": "1980-01-01",
    "date:inception_upper": "1980-01-01",
    "iso:country": "GB",
    "wof:name": "RM16 3BB",
    "wof:placetype": "postalcode"
  },
  "geometry": {"coordinates":[0.375083,51.504407],"type":"Point"}
}
