{
  "type": "Feature",
  "properties": {
    "iso:country":"GB",
    "wof:name":"UB8 3TJ",
    "wof:placetype":"postalcode"
},
  "geometry": {"coordinates":[-0.47962972023562,51.52295413575754],"type":"Point"}
}