{
  "type": "Feature",
  "properties": {
    "iso:country": "GB",
    "wof:name": "KT5 8EQ",
    "wof:placetype": "postalcode"
  },
  "geometry": {"coordinates":[-0.292819,51.395929],"type":"Point"}
}
