{
  "type": "Feature",
  "properties": {
    "iso:country":"GB",
    "wof:name":"KT5 8EQ",
    "wof:placetype":"postalcode"
},
  "geometry": {"coordinates":[-0.29281905464638,51.39592920728735],"type":"Point"}
}