{
  "type": "Feature",
  "properties": {
    "iso:country": "GB",
    "wof:name": "CO9 1NY",
    "wof:placetype": "postalcode"
  },
  "geometry": {"coordinates":[0.639917,51.938194],"type":"Point"}
}
