{
  "type": "Feature",
  "properties": {
    "iso:country":"GB",
    "wof:name":"G40 3BP",
    "wof:placetype":"postalcode"
},
  "geometry": {"coordinates":[-4.21965326603341,55.84649745888226],"type":"Point"}
}