{
  "type": "Feature",
  "properties": {
    "date:inception_lower": "1980-01-01",
    "date:inception_upper": "1980-01-01",
    "iso:country": "GB",
    "wof:name": "KW17 2QL",
    "wof:placetype": "postalcode"
  },
  "geometry": {"coordinates":[-2.7692,58.944033],"type":"Point"}
}
