{
  "type": "Feature",
  "properties": {
    "iso:country":"GB",
    "wof:name":"BS9 4RR",
    "wof:placetype":"postalcode"
},
  "geometry": {"coordinates":[-2.60028366105366,51.48767459411024],"type":"Point"}
}