{
  "type": "Feature",
  "properties": {
    "iso:country":"GB",
    "wof:name":"DN2 5AE",
    "wof:placetype":"postalcode"
},
  "geometry": {"coordinates":[-1.10671310084583,53.53403972669123],"type":"Point"}
}