{
  "type": "Feature",
  "properties": {
    "date:inception_lower": "1980-01-01",
    "date:inception_upper": "1980-01-01",
    "iso:country": "GB",
    "wof:name": "DN2 5AE",
    "wof:placetype": "postalcode"
  },
  "geometry": {"coordinates":[-1.106713,53.53404],"type":"Point"}
}
