{
  "type": "Feature",
  "properties": {
    "date:inception_lower": "1980-01-01",
    "date:inception_upper": "1980-01-01",
    "iso:country": "GB",
    "wof:name": "PO4 0NJ",
    "wof:placetype": "postalcode"
  },
  "geometry": {"coordinates":[-1.072459,50.78226],"type":"Point"}
}
