{
  "type": "Feature",
  "properties": {
    "iso:country":"GB",
    "wof:name":"G64 2SX",
    "wof:placetype":"postalcode"
},
  "geometry": {"coordinates":[-4.23673651337054,55.9010829885114],"type":"Point"}
}