{
  "type": "Feature",
  "properties": {
    "iso:country": "GB",
    "wof:name": "G64 2SX",
    "wof:placetype": "postalcode"
  },
  "geometry": {"coordinates":[-4.236736,55.901083],"type":"Point"}
}
