{
  "type": "Feature",
  "properties": {
    "iso:country": "GB",
    "wof:name": "W10 4HP",
    "wof:placetype": "postalcode"
  },
  "geometry": {"coordinates":[-0.209972,51.531073],"type":"Point"}
}
