{
  "type": "Feature",
  "properties": {
    "date:inception_lower": "1980-01-01",
    "date:inception_upper": "1980-01-01",
    "iso:country": "GB",
    "wof:name": "LS12 2PY",
    "wof:placetype": "postalcode"
  },
  "geometry": {"coordinates":[-1.578657,53.800912],"type":"Point"}
}
