{
  "type": "Feature",
  "properties": {
    "iso:country":"GB",
    "wof:name":"LS12 2PY",
    "wof:placetype":"postalcode"
},
  "geometry": {"coordinates":[-1.57863847065613,53.8008955016649],"type":"Point"}
}