{
  "type": "Feature",
  "properties": {
    "iso:country":"GB",
    "wof:name":"HR2 8AR",
    "wof:placetype":"postalcode"
},
  "geometry": {"coordinates":[-2.72331848298925,51.98059177801075],"type":"Point"}
}