{
  "type": "Feature",
  "properties": {
    "iso:country":"GB",
    "wof:name":"HU12 9JY",
    "wof:placetype":"postalcode"
},
  "geometry": {"coordinates":[-0.13318454539877,53.66326767446899],"type":"Point"}
}