{
  "type": "Feature",
  "properties": {
    "iso:country":"GB",
    "wof:name":"DN3 3BA",
    "wof:placetype":"postalcode"
},
  "geometry": {"coordinates":[-1.06054837561629,53.53386582077094],"type":"Point"}
}