{
  "type": "Feature",
  "properties": {
    "iso:country": "GB",
    "wof:name": "HR1 3QG",
    "wof:placetype": "postalcode"
  },
  "geometry": {"coordinates":[-2.636213,52.099143],"type":"Point"}
}
