{
  "type": "Feature",
  "properties": {
    "iso:country":"GB",
    "wof:name":"HR1 3QG",
    "wof:placetype":"postalcode"
},
  "geometry": {"coordinates":[-2.63621288154837,52.09914349349525],"type":"Point"}
}