{
  "type": "Feature",
  "properties": {
    "iso:country":"GB",
    "wof:name":"BS8 3BF",
    "wof:placetype":"postalcode"
},
  "geometry": {"coordinates":[-2.61963531385473,51.46285594622758],"type":"Point"}
}