{
  "type": "Feature",
  "properties": {
    "date:inception_lower": "2014-02-01",
    "date:inception_upper": "2014-02-01",
    "iso:country": "GB",
    "wof:name": "BS8 3BF",
    "wof:placetype": "postalcode"
  },
  "geometry": {"coordinates":[-2.619635,51.462856],"type":"Point"}
}
