{
  "type": "Feature",
  "properties": {
    "iso:country":"GB",
    "wof:name":"DL5 7JD",
    "wof:placetype":"postalcode"
},
  "geometry": {"coordinates":[-1.61305834054755,54.62988259397154],"type":"Point"}
}