{
  "type": "Feature",
  "properties": {
    "iso:country": "GB",
    "wof:name": "DL5 7JD",
    "wof:placetype": "postalcode"
  },
  "geometry": {"coordinates":[-1.613058,54.629883],"type":"Point"}
}
