{
  "type": "Feature",
  "properties": {
    "iso:country": "GB",
    "wof:name": "SP10 2JJ",
    "wof:placetype": "postalcode"
  },
  "geometry": {"coordinates":[-1.488781,51.205254],"type":"Point"}
}
