{
  "type": "Feature",
  "properties": {
    "iso:country": "GB",
    "wof:name": "LN13 0AS",
    "wof:placetype": "postalcode"
  },
  "geometry": {"coordinates":[0.099203,53.271965],"type":"Point"}
}
