{
  "type": "Feature",
  "properties": {
    "iso:country":"GB",
    "wof:name":"LN13 0AS",
    "wof:placetype":"postalcode"
},
  "geometry": {"coordinates":[0.09898241485951,53.27176448994279],"type":"Point"}
}