{
  "type": "Feature",
  "properties": {
    "iso:country":"GB",
    "wof:name":"BS23 3PN",
    "wof:placetype":"postalcode"
},
  "geometry": {"coordinates":[-2.96563343054231,51.34369353703622],"type":"Point"}
}