{
  "type": "Feature",
  "properties": {
    "iso:country":"GB",
    "wof:name":"M23 2WU",
    "wof:placetype":"postalcode"
},
  "geometry": {"coordinates":[-2.28770843768712,53.37870397173071],"type":"Point"}
}