{
  "type": "Feature",
  "properties": {
    "date:inception_lower": "1994-05-01",
    "date:inception_upper": "1994-05-01",
    "iso:country": "GB",
    "wof:name": "M23 2WU",
    "wof:placetype": "postalcode"
  },
  "geometry": {"coordinates":[-2.287708,53.378704],"type":"Point"}
}
