{
  "type": "Feature",
  "properties": {
    "iso:country": "GB",
    "wof:name": "TR26 2LB",
    "wof:placetype": "postalcode"
  },
  "geometry": {"coordinates":[-5.461775,50.193387],"type":"Point"}
}
