{
  "type": "Feature",
  "properties": {
    "date:inception_lower": "1999-06-01",
    "date:inception_upper": "1999-06-01",
    "iso:country": "GB",
    "wof:name": "RM16 6RS",
    "wof:placetype": "postalcode"
  },
  "geometry": {"coordinates":[0.303997,51.490115],"type":"Point"}
}
