{
  "type": "Feature",
  "properties": {
    "date:inception_lower": "1999-12-01",
    "date:inception_upper": "1999-12-01",
    "iso:country": "GB",
    "wof:name": "SM1 2XS",
    "wof:placetype": "postalcode"
  },
  "geometry": {"coordinates":[-0.208195,51.362778],"type":"Point"}
}
