{
  "type": "Feature",
  "properties": {
    "iso:country":"GB",
    "wof:name":"SM1 2XS",
    "wof:placetype":"postalcode"
},
  "geometry": {"coordinates":[-0.20819517851837,51.36277797490074],"type":"Point"}
}