{
  "type": "Feature",
  "properties": {
    "iso:country":"GB",
    "wof:name":"TW8 9JL",
    "wof:placetype":"postalcode"
},
  "geometry": {"coordinates":[-0.3155246365146,51.49036340213051],"type":"Point"}
}