{
  "type": "Feature",
  "properties": {
    "iso:country":"GB",
    "wof:name":"DD8 1UW",
    "wof:placetype":"postalcode"
},
  "geometry": {"coordinates":[-2.95060083244191,56.61430190504391],"type":"Point"}
}