{
  "type": "Feature",
  "properties": {
    "iso:country":"GB",
    "wof:name":"RH8 0AL",
    "wof:placetype":"postalcode"
},
  "geometry": {"coordinates":[0.00215896362595,51.26116849509553],"type":"Point"}
}