{
  "type": "Feature",
  "properties": {
    "iso:country": "GB",
    "wof:name": "N11 3JA",
    "wof:placetype": "postalcode"
  },
  "geometry": {"coordinates":[-0.154129,51.615231],"type":"Point"}
}
