{
  "type": "Feature",
  "properties": {
    "date:inception_lower":"1980-01-01",
    "date:inception_upper":"1980-01-31",
    "iso:country":"GB",
    "wof:name":"N11 3JA",
    "wof:placetype":"postalcode"
},
  "geometry": {"coordinates":[-0.154129,51.615231],"type":"Point"}
}