{
  "type": "Feature",
  "properties": {
    "iso:country": "GB",
    "wof:name": "S44 6DZ",
    "wof:placetype": "postalcode"
  },
  "geometry": {"coordinates":[-1.277982,53.229407],"type":"Point"}
}
