{
  "type": "Feature",
  "properties": {
    "iso:country":"GB",
    "wof:name":"S44 6DZ",
    "wof:placetype":"postalcode"
},
  "geometry": {"coordinates":[-1.27796824756193,53.22939743914302],"type":"Point"}
}