{
  "type": "Feature",
  "properties": {
    "iso:country":"GB",
    "wof:name":"LN7 6AG",
    "wof:placetype":"postalcode"
},
  "geometry": {"coordinates":[-0.37022908032835,53.46704781001807],"type":"Point"}
}