{
  "type": "Feature",
  "properties": {
    "iso:country":"GB",
    "wof:name":"TS18 5AA",
    "wof:placetype":"postalcode"
},
  "geometry": {"coordinates":[-1.34677714998511,54.56150828905203],"type":"Point"}
}