{
  "type": "Feature",
  "properties": {
    "iso:country":"GB",
    "wof:name":"CF47 0PT",
    "wof:placetype":"postalcode"
},
  "geometry": {"coordinates":[-3.37238884910436,51.7433641258684],"type":"Point"}
}