{
  "type": "Feature",
  "properties": {
    "date:inception_lower": "1980-01-01",
    "date:inception_upper": "1980-01-01",
    "iso:country": "GB",
    "wof:name": "CF47 0PT",
    "wof:placetype": "postalcode"
  },
  "geometry": {"coordinates":[-3.372389,51.743364],"type":"Point"}
}
