{
  "type": "Feature",
  "properties": {
    "iso:country": "GB",
    "wof:name": "EX36 3NG",
    "wof:placetype": "postalcode"
  },
  "geometry": {"coordinates":[-3.702596,51.042384],"type":"Point"}
}
