{
  "type": "Feature",
  "properties": {
    "iso:country":"GB",
    "wof:name":"LU2 7QH",
    "wof:placetype":"postalcode"
},
  "geometry": {"coordinates":[-0.41037950985595,51.88722618243425],"type":"Point"}
}