{
  "type": "Feature",
  "properties": {
    "date:inception_lower": "2022-06-01",
    "date:inception_upper": "2022-06-01",
    "iso:country": "GB",
    "wof:name": "FY6 7XU",
    "wof:placetype": "postalcode"
  },
  "geometry": {"coordinates":[-2.967389,53.846948],"type":"Point"}
}
