{
  "type": "Feature",
  "properties": {
    "iso:country": "GB",
    "wof:name": "PA16 7DE",
    "wof:placetype": "postalcode"
  },
  "geometry": {"coordinates":[-4.795285,55.949501],"type":"Point"}
}
