{
  "type": "Feature",
  "properties": {
    "date:inception_lower":"1980-01-01",
    "date:inception_upper":"1980-01-31",
    "iso:country":"GB",
    "wof:name":"PA16 7DE",
    "wof:placetype":"postalcode"
},
  "geometry": {"coordinates":[-4.795285,55.949501],"type":"Point"}
}