{
  "type": "Feature",
  "properties": {
    "date:inception_lower": "1980-01-01",
    "date:inception_upper": "1980-01-01",
    "iso:country": "GB",
    "wof:name": "PA16 7DE",
    "wof:placetype": "postalcode"
  },
  "geometry": {"coordinates":[-4.795314,55.949512],"type":"Point"}
}
