{
  "type": "Feature",
  "properties": {
    "iso:country":"GB",
    "wof:name":"SN8 4EJ",
    "wof:placetype":"postalcode"
},
  "geometry": {"coordinates":[-1.78912036594772,51.40862949642752],"type":"Point"}
}