{
  "type": "Feature",
  "properties": {
    "iso:country": "GB",
    "wof:name": "SN8 4EJ",
    "wof:placetype": "postalcode"
  },
  "geometry": {"coordinates":[-1.78912,51.408629],"type":"Point"}
}
