{
  "type": "Feature",
  "properties": {
    "date:inception_lower": "1980-01-01",
    "date:inception_upper": "1980-01-01",
    "iso:country": "GB",
    "wof:name": "KY1 1JW",
    "wof:placetype": "postalcode"
  },
  "geometry": {"coordinates":[-3.157896,56.111046],"type":"Point"}
}
