{
  "type": "Feature",
  "properties": {
    "date:inception_lower": "2005-10-01",
    "date:inception_upper": "2005-10-01",
    "iso:country": "GB",
    "wof:name": "FK11 7DU",
    "wof:placetype": "postalcode"
  },
  "geometry": {"coordinates":[-3.856864,56.146941],"type":"Point"}
}
