{
  "type": "Feature",
  "properties": {
    "iso:country":"GB",
    "wof:name":"SN10 2QB",
    "wof:placetype":"postalcode"
},
  "geometry": {"coordinates":[-2.03468190778485,51.36438581818042],"type":"Point"}
}