{
  "type": "Feature",
  "properties": {
    "date:inception_lower": "2023-07-01",
    "date:inception_upper": "2023-07-01",
    "iso:country": "GB",
    "wof:name": "CV34 0AN",
    "wof:placetype": "postalcode"
  },
  "geometry": {"coordinates":[-1.563912,52.25985],"type":"Point"}
}
