{
  "type": "Feature",
  "properties": {
    "iso:country":"GB",
    "wof:name":"AB24 4SG",
    "wof:placetype":"postalcode"
},
  "geometry": {"coordinates":[-2.12410010018527,57.16337975335923],"type":"Point"}
}