{
  "type": "Feature",
  "properties": {
    "iso:country": "GB",
    "wof:name": "NG1 1DB",
    "wof:placetype": "postalcode"
  },
  "geometry": {"coordinates":[-1.138528,52.955116],"type":"Point"}
}
