{
  "type": "Feature",
  "properties": {
    "date:inception_lower": "1980-01-01",
    "date:inception_upper": "1980-01-01",
    "iso:country": "GB",
    "wof:name": "NG1 1DB",
    "wof:placetype": "postalcode"
  },
  "geometry": {"coordinates":[-1.138455,52.954911],"type":"Point"}
}
