{
  "type": "Feature",
  "properties": {
    "iso:country":"GB",
    "wof:name":"NG1 1DB",
    "wof:placetype":"postalcode"
},
  "geometry": {"coordinates":[-1.13852768898845,52.95511566024327],"type":"Point"}
}