{
  "type": "Feature",
  "properties": {
    "iso:country":"GB",
    "wof:name":"N11 1JW",
    "wof:placetype":"postalcode"
},
  "geometry": {"coordinates":[-0.14302084642949,51.6170071439348],"type":"Point"}
}