{
  "type": "Feature",
  "properties": {
    "date:inception_lower": "1980-01-01",
    "date:inception_upper": "1980-01-01",
    "iso:country": "GB",
    "wof:name": "PE21 0AA",
    "wof:placetype": "postalcode"
  },
  "geometry": {"coordinates":[-0.01282,52.970207],"type":"Point"}
}
