{
  "type": "Feature",
  "properties": {
    "iso:country": "GB",
    "wof:name": "S36 6FF",
    "wof:placetype": "postalcode"
  },
  "geometry": {"coordinates":[-1.623004,53.522507],"type":"Point"}
}
