{
  "type": "Feature",
  "properties": {
    "iso:country":"GB",
    "wof:name":"SP11 9NH",
    "wof:placetype":"postalcode"
},
  "geometry": {"coordinates":[-1.6112669248257,51.2545506054681],"type":"Point"}
}