{
  "type": "Feature",
  "properties": {
    "date:inception_lower":"2000-12-01",
    "date:inception_upper":"2000-12-31",
    "iso:country":"GB",
    "wof:name":"LE7 4XW",
    "wof:placetype":"postalcode"
},
  "geometry": {"coordinates":[-1.04495,52.714491],"type":"Point"}
}