{
  "type": "Feature",
  "properties": {
    "iso:country":"GB",
    "wof:name":"LE7 4XW",
    "wof:placetype":"postalcode"
},
  "geometry": {"coordinates":[-1.04494991717633,52.71449124747662],"type":"Point"}
}