{
  "type": "Feature",
  "properties": {
    "iso:country":"GB",
    "wof:name":"BD4 8JB",
    "wof:placetype":"postalcode"
},
  "geometry": {"coordinates":[-1.7106726060956,53.78713929253981],"type":"Point"}
}