{
  "type": "Feature",
  "properties": {
    "date:inception_lower": "2022-09-01",
    "date:inception_upper": "2022-09-01",
    "iso:country": "GB",
    "wof:name": "DL2 2ZT",
    "wof:placetype": "postalcode"
  },
  "geometry": {"coordinates":[-1.653049,54.594983],"type":"Point"}
}
