{
  "type": "Feature",
  "properties": {
    "iso:country":"GB",
    "wof:name":"DA4 9HQ",
    "wof:placetype":"postalcode"
},
  "geometry": {"coordinates":[0.23734295791477,51.40888523660556],"type":"Point"}
}