{
  "type": "Feature",
  "properties": {
    "date:inception_lower": "1980-01-01",
    "date:inception_upper": "1980-01-01",
    "iso:country": "GB",
    "wof:name": "DA4 9HQ",
    "wof:placetype": "postalcode"
  },
  "geometry": {"coordinates":[0.237343,51.408885],"type":"Point"}
}
