{
  "type": "Feature",
  "properties": {
    "iso:country":"GB",
    "wof:name":"BR5 2JP",
    "wof:placetype":"postalcode"
},
  "geometry": {"coordinates":[0.10871957873167,51.40271832892417],"type":"Point"}
}