{
  "type": "Feature",
  "properties": {
    "iso:country": "GB",
    "wof:name": "B30 2JS",
    "wof:placetype": "postalcode"
  },
  "geometry": {"coordinates":[-1.922738,52.428538],"type":"Point"}
}
