{
  "type": "Feature",
  "properties": {
    "iso:country": "GB",
    "wof:name": "NE9 7AE",
    "wof:placetype": "postalcode"
  },
  "geometry": {"coordinates":[-1.573026,54.922944],"type":"Point"}
}
