{
  "type": "Feature",
  "properties": {
    "iso:country":"GB",
    "wof:name":"NE9 7AE",
    "wof:placetype":"postalcode"
},
  "geometry": {"coordinates":[-1.57302563727066,54.92294401147225],"type":"Point"}
}