{
  "type": "Feature",
  "properties": {
    "iso:country":"GB",
    "wof:name":"DA3 8QH",
    "wof:placetype":"postalcode"
},
  "geometry": {"coordinates":[0.31653855440567,51.36373785684113],"type":"Point"}
}