{
  "type": "Feature",
  "properties": {
    "iso:country": "GB",
    "wof:name": "DA3 8QH",
    "wof:placetype": "postalcode"
  },
  "geometry": {"coordinates":[0.316539,51.363738],"type":"Point"}
}
