{
  "type": "Feature",
  "properties": {
    "date:inception_lower": "1980-01-01",
    "date:inception_upper": "1980-01-01",
    "iso:country": "GB",
    "wof:name": "SR6 8AQ",
    "wof:placetype": "postalcode"
  },
  "geometry": {"coordinates":[-1.367181,54.942806],"type":"Point"}
}
