{
  "type": "Feature",
  "properties": {
    "date:inception_lower": "1998-06-01",
    "date:inception_upper": "1998-06-01",
    "iso:country": "GB",
    "wof:name": "YO32 9TB",
    "wof:placetype": "postalcode"
  },
  "geometry": {"coordinates":[-1.058809,53.980979],"type":"Point"}
}
