{
  "type": "Feature",
  "properties": {
    "iso:country": "GB",
    "wof:name": "CR2 0AS",
    "wof:placetype": "postalcode"
  },
  "geometry": {"coordinates":[-0.073789,51.344521],"type":"Point"}
}
