{
  "type": "Feature",
  "properties": {
    "iso:country":"GB",
    "wof:name":"CR2 0AS",
    "wof:placetype":"postalcode"
},
  "geometry": {"coordinates":[-0.07378904143121,51.34452094140812],"type":"Point"}
}