{
  "type": "Feature",
  "properties": {
    "date:inception_lower": "2015-04-01",
    "date:inception_upper": "2015-04-01",
    "iso:country": "GB",
    "wof:name": "EX21 5XZ",
    "wof:placetype": "postalcode"
  },
  "geometry": {"coordinates":[-4.209242,50.794814],"type":"Point"}
}
