{
  "type": "Feature",
  "properties": {
    "iso:country":"GB",
    "wof:name":"EX21 5XZ",
    "wof:placetype":"postalcode"
},
  "geometry": {"coordinates":[-4.2092578892111,50.79480217027129],"type":"Point"}
}