{
  "type": "Feature",
  "properties": {
    "iso:country": "GB",
    "wof:name": "EX21 5XZ",
    "wof:placetype": "postalcode"
  },
  "geometry": {"coordinates":[-4.209242,50.794814],"type":"Point"}
}
