{
  "type": "Feature",
  "properties": {
    "iso:country":"GB",
    "wof:name":"ME6 5LS",
    "wof:placetype":"postalcode"
},
  "geometry": {"coordinates":[0.43178610323683,51.32419554318594],"type":"Point"}
}