{
  "type": "Feature",
  "properties": {
    "iso:country":"GB",
    "wof:name":"BN13 1BP",
    "wof:placetype":"postalcode"
},
  "geometry": {"coordinates":[-0.39600251362314,50.82061505558048],"type":"Point"}
}