{
  "type": "Feature",
  "properties": {
    "iso:country":"GB",
    "wof:name":"TA6 7JH",
    "wof:placetype":"postalcode"
},
  "geometry": {"coordinates":[-3.0365018253204,51.12444260556652],"type":"Point"}
}