{
  "type": "Feature",
  "properties": {
    "iso:country":"GB",
    "wof:name":"TN14 6AD",
    "wof:placetype":"postalcode"
},
  "geometry": {"coordinates":[0.12499175314109,51.27940824494011],"type":"Point"}
}