{
  "type": "Feature",
  "properties": {
    "iso:country":"GB",
    "wof:name":"SO50 7BA",
    "wof:placetype":"postalcode"
},
  "geometry": {"coordinates":[-1.30139048930186,50.96653952864726],"type":"Point"}
}