{
  "type": "Feature",
  "properties": {
    "iso:country":"GB",
    "wof:name":"NR34 9TD",
    "wof:placetype":"postalcode"
},
  "geometry": {"coordinates":[1.56764484088905,52.45387246808954],"type":"Point"}
}