{
  "type": "Feature",
  "properties": {
    "date:inception_lower":"2007-07-01",
    "date:inception_upper":"2007-07-31",
    "iso:country":"GB",
    "wof:name":"NR34 9TD",
    "wof:placetype":"postalcode"
},
  "geometry": {"coordinates":[1.567645,52.453872],"type":"Point"}
}