{
  "type": "Feature",
  "properties": {
    "date:inception_lower": "1980-01-01",
    "date:inception_upper": "1980-01-01",
    "iso:country": "GB",
    "wof:name": "DN40 2DY",
    "wof:placetype": "postalcode"
  },
  "geometry": {"coordinates":[-0.226326,53.614666],"type":"Point"}
}
