{
  "type": "Feature",
  "properties": {
    "iso:country":"GB",
    "wof:name":"DN40 2DY",
    "wof:placetype":"postalcode"
},
  "geometry": {"coordinates":[-0.22632595260644,53.614666241684],"type":"Point"}
}