{
  "type": "Feature",
  "properties": {
    "iso:country":"GB",
    "wof:name":"BR1 3SR",
    "wof:placetype":"postalcode"
},
  "geometry": {"coordinates":[0.00238348553641,51.41458377669415],"type":"Point"}
}