{
  "type": "Feature",
  "properties": {
    "iso:country":"GB",
    "wof:name":"CT2 7UJ",
    "wof:placetype":"postalcode"
},
  "geometry": {"coordinates":[1.0857354649016,51.28690716453056],"type":"Point"}
}