{
  "type": "Feature",
  "properties": {
    "iso:country": "GB",
    "wof:name": "CT2 7UJ",
    "wof:placetype": "postalcode"
  },
  "geometry": {"coordinates":[1.085736,51.286907],"type":"Point"}
}
