{
  "type": "Feature",
  "properties": {
    "iso:country": "GB",
    "wof:name": "PL31 2PD",
    "wof:placetype": "postalcode"
  },
  "geometry": {"coordinates":[-4.732769,50.480059],"type":"Point"}
}
