{
  "type": "Feature",
  "properties": {
    "iso:country":"GB",
    "wof:name":"PL31 2PD",
    "wof:placetype":"postalcode"
},
  "geometry": {"coordinates":[-4.73276923811969,50.4800586955572],"type":"Point"}
}