{
  "type": "Feature",
  "properties": {
    "iso:country":"GB",
    "wof:name":"NN8 4SH",
    "wof:placetype":"postalcode"
},
  "geometry": {"coordinates":[-0.69419409714214,52.31169037386778],"type":"Point"}
}