{
  "type": "Feature",
  "properties": {
    "iso:country":"GB",
    "wof:name":"W1F 8EN",
    "wof:placetype":"postalcode"
},
  "geometry": {"coordinates":[-0.13608030989582,51.51450923306848],"type":"Point"}
}