{
  "type": "Feature",
  "properties": {
    "date:inception_lower": "1980-01-01",
    "date:inception_upper": "1980-01-01",
    "iso:country": "GB",
    "wof:name": "NE65 7LN",
    "wof:placetype": "postalcode"
  },
  "geometry": {"coordinates":[-2.021069,55.286806],"type":"Point"}
}
