{
  "type": "Feature",
  "properties": {
    "iso:country":"GB",
    "wof:name":"NE65 7LN",
    "wof:placetype":"postalcode"
},
  "geometry": {"coordinates":[-2.02106931831959,55.28680631050273],"type":"Point"}
}