{
  "type": "Feature",
  "properties": {
    "iso:country": "GB",
    "wof:name": "NR20 3GD",
    "wof:placetype": "postalcode"
  },
  "geometry": {"coordinates":[0.965999,52.68233],"type":"Point"}
}
