{
  "type": "Feature",
  "properties": {
    "date:inception_lower": "2015-11-01",
    "date:inception_upper": "2015-11-01",
    "iso:country": "GB",
    "wof:name": "NR20 3GD",
    "wof:placetype": "postalcode"
  },
  "geometry": {"coordinates":[0.964452,52.682],"type":"Point"}
}
