{
  "type": "Feature",
  "properties": {
    "date:inception_lower": "2014-06-01",
    "date:inception_upper": "2014-06-01",
    "iso:country": "GB",
    "wof:name": "LS18 4FR",
    "wof:placetype": "postalcode"
  },
  "geometry": {"coordinates":[-1.664572,53.832262],"type":"Point"}
}
