{
  "type": "Feature",
  "properties": {
    "iso:country": "GB",
    "wof:name": "LS18 4FR",
    "wof:placetype": "postalcode"
  },
  "geometry": {"coordinates":[-1.664582,53.832229],"type":"Point"}
}
