{
  "type": "Feature",
  "properties": {
    "iso:country":"GB",
    "wof:name":"LS18 4FR",
    "wof:placetype":"postalcode"
},
  "geometry": {"coordinates":[-1.66458204296646,53.83222889254949],"type":"Point"}
}