{
  "type": "Feature",
  "properties": {
    "iso:country":"GB",
    "wof:name":"NG11 8QX",
    "wof:placetype":"postalcode"
},
  "geometry": {"coordinates":[-1.19547745842658,52.901433739336],"type":"Point"}
}