{
  "type": "Feature",
  "properties": {
    "iso:country": "GB",
    "wof:name": "NG11 8QX",
    "wof:placetype": "postalcode"
  },
  "geometry": {"coordinates":[-1.195477,52.901434],"type":"Point"}
}
