{
  "type": "Feature",
  "properties": {
    "date:inception_lower": "1980-01-01",
    "date:inception_upper": "1980-01-01",
    "iso:country": "GB",
    "wof:name": "IP27 0QS",
    "wof:placetype": "postalcode"
  },
  "geometry": {"coordinates":[0.605921,52.471823],"type":"Point"}
}
