{
  "type": "Feature",
  "properties": {
    "iso:country":"GB",
    "wof:name":"TN5 7ER",
    "wof:placetype":"postalcode"
},
  "geometry": {"coordinates":[0.3683208616942,51.01920126408091],"type":"Point"}
}