{
  "type": "Feature",
  "properties": {
    "date:inception_lower": "1999-06-01",
    "date:inception_upper": "1999-06-01",
    "iso:country": "GB",
    "wof:name": "CH47 9SA",
    "wof:placetype": "postalcode"
  },
  "geometry": {"coordinates":[-3.152463,53.395014],"type":"Point"}
}
