{
  "type": "Feature",
  "properties": {
    "iso:country": "GB",
    "wof:name": "CH47 9SA",
    "wof:placetype": "postalcode"
  },
  "geometry": {"coordinates":[-3.152463,53.395014],"type":"Point"}
}
