{
  "type": "Feature",
  "properties": {
    "iso:country":"GB",
    "wof:name":"CH47 9SA",
    "wof:placetype":"postalcode"
},
  "geometry": {"coordinates":[-3.15262608315584,53.39485131910875],"type":"Point"}
}