{
  "type": "Feature",
  "properties": {
    "date:inception_lower":"1999-06-01",
    "date:inception_upper":"1999-06-30",
    "iso:country":"GB",
    "wof:name":"CH47 9SA",
    "wof:placetype":"postalcode"
},
  "geometry": {"coordinates":[-3.152565,53.394905],"type":"Point"}
}