{
  "type": "Feature",
  "properties": {
    "iso:country": "GB",
    "wof:name": "ST14 8QP",
    "wof:placetype": "postalcode"
  },
  "geometry": {"coordinates":[-1.925967,52.857757],"type":"Point"}
}
