{
  "type": "Feature",
  "properties": {
    "date:inception_lower": "1980-01-01",
    "date:inception_upper": "1980-01-01",
    "iso:country": "GB",
    "wof:name": "BH22 0BT",
    "wof:placetype": "postalcode"
  },
  "geometry": {"coordinates":[-1.867809,50.821365],"type":"Point"}
}
