{
  "type": "Feature",
  "properties": {
    "iso:country":"GB",
    "wof:name":"BH22 0BT",
    "wof:placetype":"postalcode"
},
  "geometry": {"coordinates":[-1.86780884867945,50.82136487337643],"type":"Point"}
}