{
  "type": "Feature",
  "properties": {
    "date:inception_lower":"1980-01-01",
    "date:inception_upper":"1980-01-31",
    "iso:country":"GB",
    "wof:name":"BS11 0ED",
    "wof:placetype":"postalcode"
},
  "geometry": {"coordinates":[-2.672572,51.489791],"type":"Point"}
}