{
  "type": "Feature",
  "properties": {
    "iso:country":"GB",
    "wof:name":"BS11 0ED",
    "wof:placetype":"postalcode"
},
  "geometry": {"coordinates":[-2.67257199655204,51.48979082680395],"type":"Point"}
}