{
  "type": "Feature",
  "properties": {
    "iso:country":"GB",
    "wof:name":"TQ3 2PE",
    "wof:placetype":"postalcode"
},
  "geometry": {"coordinates":[-3.55734300809222,50.44718439896248],"type":"Point"}
}