{
  "type": "Feature",
  "properties": {
    "iso:country": "GB",
    "wof:name": "TQ3 2PE",
    "wof:placetype": "postalcode"
  },
  "geometry": {"coordinates":[-3.557343,50.447184],"type":"Point"}
}
