{
  "type": "Feature",
  "properties": {
    "iso:country":"GB",
    "wof:name":"WV13 3DB",
    "wof:placetype":"postalcode"
},
  "geometry": {"coordinates":[-2.06983098935252,52.58745143160343],"type":"Point"}
}