{
  "type": "Feature",
  "properties": {
    "date:inception_lower": "1980-01-01",
    "date:inception_upper": "1980-01-01",
    "iso:country": "GB",
    "wof:name": "WV13 3DB",
    "wof:placetype": "postalcode"
  },
  "geometry": {"coordinates":[-2.069831,52.587451],"type":"Point"}
}
