{
  "type": "Feature",
  "properties": {
    "date:inception_lower": "1980-01-01",
    "date:inception_upper": "1980-01-01",
    "iso:country": "GB",
    "wof:name": "L40 6JB",
    "wof:placetype": "postalcode"
  },
  "geometry": {"coordinates":[-2.824693,53.568845],"type":"Point"}
}
