{
  "type": "Feature",
  "properties": {
    "date:inception_lower":"1980-01-01",
    "date:inception_upper":"1980-01-31",
    "iso:country":"GB",
    "wof:name":"GL10 2BQ",
    "wof:placetype":"postalcode"
},
  "geometry": {"coordinates":[-2.286407,51.743523],"type":"Point"}
}