{
  "type": "Feature",
  "properties": {
    "date:inception_lower": "2008-05-01",
    "date:inception_upper": "2008-05-01",
    "iso:country": "GB",
    "wof:name": "NE6 3UF",
    "wof:placetype": "postalcode"
  },
  "geometry": {"coordinates":[-1.541465,54.969279],"type":"Point"}
}
