{
  "type": "Feature",
  "properties": {
    "iso:country":"GB",
    "wof:name":"NE6 3UF",
    "wof:placetype":"postalcode"
},
  "geometry": {"coordinates":[-1.54146551811989,54.96927947363876],"type":"Point"}
}