{
  "type": "Feature",
  "properties": {
    "iso:country": "GB",
    "wof:name": "SK15 1JX",
    "wof:placetype": "postalcode"
  },
  "geometry": {"coordinates":[-2.054588,53.483674],"type":"Point"}
}
