{
  "type": "Feature",
  "properties": {
    "date:inception_lower": "1990-02-01",
    "date:inception_upper": "1990-02-01",
    "iso:country": "GB",
    "wof:name": "SK15 1JX",
    "wof:placetype": "postalcode"
  },
  "geometry": {"coordinates":[-2.054588,53.483674],"type":"Point"}
}
