{
  "type": "Feature",
  "properties": {
    "iso:country":"GB",
    "wof:name":"SK15 1JX",
    "wof:placetype":"postalcode"
},
  "geometry": {"coordinates":[-2.05458768706268,53.48367392733869],"type":"Point"}
}