{
  "type": "Feature",
  "properties": {
    "iso:country":"GB",
    "wof:name":"TS23 3AR",
    "wof:placetype":"postalcode"
},
  "geometry": {"coordinates":[-1.28029889910458,54.60962517562673],"type":"Point"}
}