{
  "type": "Feature",
  "properties": {
    "date:inception_lower": "1991-09-01",
    "date:inception_upper": "1991-09-01",
    "iso:country": "GB",
    "wof:name": "WA14 4UR",
    "wof:placetype": "postalcode"
  },
  "geometry": {"coordinates":[-2.36596,53.393698],"type":"Point"}
}
