{
  "type": "Feature",
  "properties": {
    "iso:country": "GB",
    "wof:name": "WA14 4UR",
    "wof:placetype": "postalcode"
  },
  "geometry": {"coordinates":[-2.36596,53.393698],"type":"Point"}
}
