{
  "type": "Feature",
  "properties": {
    "iso:country":"GB",
    "wof:name":"TN13 1LU",
    "wof:placetype":"postalcode"
},
  "geometry": {"coordinates":[0.19284436011891,51.27096216362],"type":"Point"}
}