{
  "type": "Feature",
  "properties": {
    "iso:country": "GB",
    "wof:name": "TN27 8NG",
    "wof:placetype": "postalcode"
  },
  "geometry": {"coordinates":[0.693846,51.15153],"type":"Point"}
}
