{
  "type": "Feature",
  "properties": {
    "date:inception_lower": "1980-01-01",
    "date:inception_upper": "1980-01-01",
    "iso:country": "GB",
    "wof:name": "TN27 8NG",
    "wof:placetype": "postalcode"
  },
  "geometry": {"coordinates":[0.693846,51.15153],"type":"Point"}
}
