{
  "type": "Feature",
  "properties": {
    "date:inception_lower": "1987-04-01",
    "date:inception_upper": "1987-04-01",
    "iso:country": "GB",
    "wof:name": "NG10 1GZ",
    "wof:placetype": "postalcode"
  },
  "geometry": {"coordinates":[-1.275835,52.884394],"type":"Point"}
}
