{
  "type": "Feature",
  "properties": {
    "iso:country":"GB",
    "wof:name":"NG10 1GZ",
    "wof:placetype":"postalcode"
},
  "geometry": {"coordinates":[-1.27583460188878,52.88439405360017],"type":"Point"}
}