{
  "type": "Feature",
  "properties": {
    "iso:country":"GB",
    "wof:name":"DE13 8FJ",
    "wof:placetype":"postalcode"
},
  "geometry": {"coordinates":[-1.78189140996051,52.75391359612335],"type":"Point"}
}