{
  "type": "Feature",
  "properties": {
    "date:inception_lower":"2008-03-01",
    "date:inception_upper":"2008-03-31",
    "iso:country":"GB",
    "wof:name":"NP7 9FF",
    "wof:placetype":"postalcode"
},
  "geometry": {"coordinates":[-3.030392,51.811289],"type":"Point"}
}