{
  "type": "Feature",
  "properties": {
    "iso:country":"GB",
    "wof:name":"NP7 9FF",
    "wof:placetype":"postalcode"
},
  "geometry": {"coordinates":[-3.03032760387238,51.81130274762847],"type":"Point"}
}