{
  "type": "Feature",
  "properties": {
    "iso:country":"GB",
    "wof:name":"OX15 4FP",
    "wof:placetype":"postalcode"
},
  "geometry": {"coordinates":[-1.37327327483856,52.01358733189459],"type":"Point"}
}