{
  "type": "Feature",
  "properties": {
    "date:inception_lower":"2011-10-01",
    "date:inception_upper":"2011-10-31",
    "iso:country":"GB",
    "wof:name":"OX15 4FP",
    "wof:placetype":"postalcode"
},
  "geometry": {"coordinates":[-1.373273,52.013587],"type":"Point"}
}