{
  "type": "Feature",
  "properties": {
    "iso:country":"GB",
    "wof:name":"EN2 7RG",
    "wof:placetype":"postalcode"
},
  "geometry": {"coordinates":[-0.109119646736,51.64998954430193],"type":"Point"}
}