{
  "type": "Feature",
  "properties": {
    "iso:country": "GB",
    "wof:name": "EN2 7RG",
    "wof:placetype": "postalcode"
  },
  "geometry": {"coordinates":[-0.10912,51.64999],"type":"Point"}
}
