{
  "type": "Feature",
  "properties": {
    "iso:country": "GB",
    "wof:name": "CO7 6JX",
    "wof:placetype": "postalcode"
  },
  "geometry": {"coordinates":[0.972483,51.976097],"type":"Point"}
}
