{
  "type": "Feature",
  "properties": {
    "date:inception_lower":"1998-06-01",
    "date:inception_upper":"1998-06-30",
    "iso:country":"GB",
    "wof:name":"SG18 8UJ",
    "wof:placetype":"postalcode"
},
  "geometry": {"coordinates":[-0.246604,52.080032],"type":"Point"}
}