{
  "type": "Feature",
  "properties": {
    "iso:country": "GB",
    "wof:name": "SG18 8UJ",
    "wof:placetype": "postalcode"
  },
  "geometry": {"coordinates":[-0.246604,52.080032],"type":"Point"}
}
