{
  "type": "Feature",
  "properties": {
    "date:inception_lower": "2023-01-01",
    "date:inception_upper": "2023-01-01",
    "iso:country": "GB",
    "wof:name": "G78 2FN",
    "wof:placetype": "postalcode"
  },
  "geometry": {"coordinates":[-4.395021,55.786651],"type":"Point"}
}
