{
  "type": "Feature",
  "properties": {
    "iso:country":"GB",
    "wof:name":"S6 5FL",
    "wof:placetype":"postalcode"
},
  "geometry": {"coordinates":[-1.51343515226079,53.39895948934181],"type":"Point"}
}