{
  "type": "Feature",
  "properties": {
    "iso:country": "GB",
    "wof:name": "LA1 3TE",
    "wof:placetype": "postalcode"
  },
  "geometry": {"coordinates":[-2.77169,54.049691],"type":"Point"}
}
