{
  "type": "Feature",
  "properties": {
    "iso:country":"GB",
    "wof:name":"OL1 3NU",
    "wof:placetype":"postalcode"
},
  "geometry": {"coordinates":[-2.09368364497588,53.54779969595352],"type":"Point"}
}