{
  "type": "Feature",
  "properties": {
    "date:inception_lower": "1995-12-01",
    "date:inception_upper": "1995-12-01",
    "iso:country": "GB",
    "wof:name": "OL1 3NU",
    "wof:placetype": "postalcode"
  },
  "geometry": {"coordinates":[-2.093684,53.5478],"type":"Point"}
}
