{
  "type": "Feature",
  "properties": {
    "iso:country":"GB",
    "wof:name":"S70 6BT",
    "wof:placetype":"postalcode"
},
  "geometry": {"coordinates":[-1.49148333828773,53.5535519294025],"type":"Point"}
}