{
  "type": "Feature",
  "properties": {
    "date:inception_lower":"1980-01-01",
    "date:inception_upper":"1980-01-31",
    "iso:country":"GB",
    "wof:name":"S70 6BT",
    "wof:placetype":"postalcode"
},
  "geometry": {"coordinates":[-1.491483,53.553552],"type":"Point"}
}