{
  "type": "Feature",
  "properties": {
    "iso:country":"GB",
    "wof:name":"EN8 8EZ",
    "wof:placetype":"postalcode"
},
  "geometry": {"coordinates":[-0.04989935857654,51.68188817309176],"type":"Point"}
}