{
  "type": "Feature",
  "properties": {
    "date:inception_lower": "1980-01-01",
    "date:inception_upper": "1980-01-01",
    "iso:country": "GB",
    "wof:name": "LE10 0TJ",
    "wof:placetype": "postalcode"
  },
  "geometry": {"coordinates":[-1.385249,52.545702],"type":"Point"}
}
