{
  "type": "Feature",
  "properties": {
    "iso:country":"GB",
    "wof:name":"W10 5UF",
    "wof:placetype":"postalcode"
},
  "geometry": {"coordinates":[-0.2096674486838,51.51898274018766],"type":"Point"}
}