{
  "type": "Feature",
  "properties": {
    "iso:country":"GB",
    "wof:name":"TS11 8AA",
    "wof:placetype":"postalcode"
},
  "geometry": {"coordinates":[-1.01876645382472,54.58500608070966],"type":"Point"}
}