{
  "type": "Feature",
  "properties": {
    "iso:country": "GB",
    "wof:name": "TS11 8AA",
    "wof:placetype": "postalcode"
  },
  "geometry": {"coordinates":[-1.02017,54.587138],"type":"Point"}
}
