{
  "type": "Feature",
  "properties": {
    "iso:country": "GB",
    "wof:name": "AB31 5BJ",
    "wof:placetype": "postalcode"
  },
  "geometry": {"coordinates":[-2.478801,57.06095],"type":"Point"}
}
