{
  "type": "Feature",
  "properties": {
    "iso:country":"GB",
    "wof:name":"WS10 7BJ",
    "wof:placetype":"postalcode"
},
  "geometry": {"coordinates":[-2.03905853144313,52.55705309409255],"type":"Point"}
}