{
  "type": "Feature",
  "properties": {
    "iso:country": "GB",
    "wof:name": "WS10 7BJ",
    "wof:placetype": "postalcode"
  },
  "geometry": {"coordinates":[-2.039053,52.557069],"type":"Point"}
}
