{
  "type": "Feature",
  "properties": {
    "date:inception_lower":"2003-05-01",
    "date:inception_upper":"2003-05-31",
    "iso:country":"GB",
    "wof:name":"WS10 7BJ",
    "wof:placetype":"postalcode"
},
  "geometry": {"coordinates":[-2.039053,52.557069],"type":"Point"}
}