{
  "type": "Feature",
  "properties": {
    "date:inception_lower":"1980-01-01",
    "date:inception_upper":"1980-01-31",
    "iso:country":"GB",
    "wof:name":"B44 0AL",
    "wof:placetype":"postalcode"
},
  "geometry": {"coordinates":[-1.863147,52.544242],"type":"Point"}
}