{
  "type": "Feature",
  "properties": {
    "date:inception_lower":"1980-01-01",
    "date:inception_upper":"1980-01-31",
    "iso:country":"GB",
    "wof:name":"RH19 1UB",
    "wof:placetype":"postalcode"
},
  "geometry": {"coordinates":[-0.038073,51.134859],"type":"Point"}
}