{
  "type": "Feature",
  "properties": {
    "iso:country": "GB",
    "wof:name": "HP27 9SB",
    "wof:placetype": "postalcode"
  },
  "geometry": {"coordinates":[-0.854837,51.732865],"type":"Point"}
}
