{
  "type": "Feature",
  "properties": {
    "iso:country":"GB",
    "wof:name":"HP27 9SB",
    "wof:placetype":"postalcode"
},
  "geometry": {"coordinates":[-0.8548367065162,51.73286485810391],"type":"Point"}
}