{
  "type": "Feature",
  "properties": {
    "date:inception_lower": "2022-09-01",
    "date:inception_upper": "2022-09-01",
    "iso:country": "GB",
    "wof:name": "M7 3AG",
    "wof:placetype": "postalcode"
  },
  "geometry": {"coordinates":[-2.290534,53.51338],"type":"Point"}
}
