{
  "type": "Feature",
  "properties": {
    "iso:country":"GB",
    "wof:name":"CA10 1QD",
    "wof:placetype":"postalcode"
},
  "geometry": {"coordinates":[-2.60916703864822,54.64791983213188],"type":"Point"}
}