{
  "type": "Feature",
  "properties": {
    "date:inception_lower":"1980-01-01",
    "date:inception_upper":"1980-01-31",
    "iso:country":"GB",
    "wof:name":"CA10 1QD",
    "wof:placetype":"postalcode"
},
  "geometry": {"coordinates":[-2.604612,54.648634],"type":"Point"}
}