{
  "type": "Feature",
  "properties": {
    "iso:country":"GB",
    "wof:name":"SW13 0EB",
    "wof:placetype":"postalcode"
},
  "geometry": {"coordinates":[-0.2416658776737,51.47218463319601],"type":"Point"}
}