{
  "type": "Feature",
  "properties": {
    "date:inception_lower": "1980-01-01",
    "date:inception_upper": "1980-01-01",
    "iso:country": "GB",
    "wof:name": "SW13 0EB",
    "wof:placetype": "postalcode"
  },
  "geometry": {"coordinates":[-0.241666,51.472185],"type":"Point"}
}
