{
  "type": "Feature",
  "properties": {
    "iso:country":"GB",
    "wof:name":"EX8 4NP",
    "wof:placetype":"postalcode"
},
  "geometry": {"coordinates":[-3.39896333925817,50.63193500350438],"type":"Point"}
}