{
  "type": "Feature",
  "properties": {
    "iso:country": "GB",
    "wof:name": "DL13 2LN",
    "wof:placetype": "postalcode"
  },
  "geometry": {"coordinates":[-2.030786,54.743044],"type":"Point"}
}
