{
  "type": "Feature",
  "properties": {
    "iso:country":"GB",
    "wof:name":"GU27 2NZ",
    "wof:placetype":"postalcode"
},
  "geometry": {"coordinates":[-0.71265619664682,51.08796353089739],"type":"Point"}
}