{
  "type": "Feature",
  "properties": {
    "iso:country": "GB",
    "wof:name": "GU27 2NZ",
    "wof:placetype": "postalcode"
  },
  "geometry": {"coordinates":[-0.712656,51.087964],"type":"Point"}
}
