{
  "type": "Feature",
  "properties": {
    "iso:country":"GB",
    "wof:name":"CO2 8AT",
    "wof:placetype":"postalcode"
},
  "geometry": {"coordinates":[0.92350277761268,51.8744599053226],"type":"Point"}
}