{
  "type": "Feature",
  "properties": {
    "iso:country":"GB",
    "wof:name":"IV36 1JF",
    "wof:placetype":"postalcode"
},
  "geometry": {"coordinates":[-3.63269664553627,57.60422734899346],"type":"Point"}
}