{
  "type": "Feature",
  "properties": {
    "date:inception_lower":"1996-06-01",
    "date:inception_upper":"1996-06-30",
    "iso:country":"GB",
    "wof:name":"CV4 7EJ",
    "wof:placetype":"postalcode"
},
  "geometry": {"coordinates":[-1.552445,52.385602],"type":"Point"}
}