{
  "type": "Feature",
  "properties": {
    "iso:country":"GB",
    "wof:name":"CV4 7EJ",
    "wof:placetype":"postalcode"
},
  "geometry": {"coordinates":[-1.55244515353066,52.38560172977568],"type":"Point"}
}