{
  "type": "Feature",
  "properties": {
    "iso:country":"GB",
    "wof:name":"IV30 4NX",
    "wof:placetype":"postalcode"
},
  "geometry": {"coordinates":[-3.32639408518295,57.65999798640857],"type":"Point"}
}