{
  "type": "Feature",
  "properties": {
    "iso:country":"GB",
    "wof:name":"HP21 9NJ",
    "wof:placetype":"postalcode"
},
  "geometry": {"coordinates":[-0.79808965104577,51.80696376742097],"type":"Point"}
}