{
  "type": "Feature",
  "properties": {
    "date:inception_lower": "1986-01-01",
    "date:inception_upper": "1986-01-01",
    "iso:country": "GB",
    "wof:name": "HP21 9NJ",
    "wof:placetype": "postalcode"
  },
  "geometry": {"coordinates":[-0.79809,51.806964],"type":"Point"}
}
