{
  "type": "Feature",
  "properties": {
    "iso:country": "GB",
    "wof:name": "HP21 9NJ",
    "wof:placetype": "postalcode"
  },
  "geometry": {"coordinates":[-0.79809,51.806964],"type":"Point"}
}
