{
  "type": "Feature",
  "properties": {
    "date:inception_lower": "1980-01-01",
    "date:inception_upper": "1980-01-01",
    "iso:country": "GB",
    "wof:name": "HU9 5TR",
    "wof:placetype": "postalcode"
  },
  "geometry": {"coordinates":[-0.282255,53.756788],"type":"Point"}
}
