{
  "type": "Feature",
  "properties": {
    "iso:country":"GB",
    "wof:name":"SE16 3ET",
    "wof:placetype":"postalcode"
},
  "geometry": {"coordinates":[-0.06219089591592,51.48759282888962],"type":"Point"}
}