{
  "type": "Feature",
  "properties": {
    "date:inception_lower": "1980-01-01",
    "date:inception_upper": "1980-01-01",
    "iso:country": "GB",
    "wof:name": "LL41 4SF",
    "wof:placetype": "postalcode"
  },
  "geometry": {"coordinates":[-3.921819,52.900948],"type":"Point"}
}
