{
  "type": "Feature",
  "properties": {
    "iso:country":"GB",
    "wof:name":"SW7 1DU",
    "wof:placetype":"postalcode"
},
  "geometry": {"coordinates":[-0.16466569351321,51.50110259269667],"type":"Point"}
}