{
  "type": "Feature",
  "properties": {
    "date:inception_lower": "1980-01-01",
    "date:inception_upper": "1980-01-01",
    "iso:country": "GB",
    "wof:name": "SA20 0DA",
    "wof:placetype": "postalcode"
  },
  "geometry": {"coordinates":[-3.791899,51.99555],"type":"Point"}
}
