{
  "type": "Feature",
  "properties": {
    "iso:country":"GB",
    "wof:name":"SA20 0DA",
    "wof:placetype":"postalcode"
},
  "geometry": {"coordinates":[-3.79198802184679,51.99522451825958],"type":"Point"}
}