{
  "type": "Feature",
  "properties": {
    "date:inception_lower":"2010-07-01",
    "date:inception_upper":"2010-07-31",
    "iso:country":"GB",
    "wof:name":"NE23 7PU",
    "wof:placetype":"postalcode"
},
  "geometry": {"coordinates":[-1.578018,55.045184],"type":"Point"}
}