{
  "type": "Feature",
  "properties": {
    "iso:country": "GB",
    "wof:name": "NE23 7PU",
    "wof:placetype": "postalcode"
  },
  "geometry": {"coordinates":[-1.578018,55.045184],"type":"Point"}
}
