{
  "type": "Feature",
  "properties": {
    "iso:country":"GB",
    "wof:name":"NE23 7PU",
    "wof:placetype":"postalcode"
},
  "geometry": {"coordinates":[-1.57801840871756,55.04518356975665],"type":"Point"}
}