{
  "type": "Feature",
  "properties": {
    "iso:country": "GB",
    "wof:name": "NW10 8SH",
    "wof:placetype": "postalcode"
  },
  "geometry": {"coordinates":[-0.251867,51.539162],"type":"Point"}
}
