{
  "type": "Feature",
  "properties": {
    "iso:country":"GB",
    "wof:name":"YO24 1DT",
    "wof:placetype":"postalcode"
},
  "geometry": {"coordinates":[-1.10410958360146,53.94871666017125],"type":"Point"}
}