{
  "type": "Feature",
  "properties": {
    "date:inception_lower":"1998-06-01",
    "date:inception_upper":"1998-06-30",
    "iso:country":"GB",
    "wof:name":"YO24 1DT",
    "wof:placetype":"postalcode"
},
  "geometry": {"coordinates":[-1.10411,53.948717],"type":"Point"}
}