{
  "type": "Feature",
  "properties": {
    "iso:country": "GB",
    "wof:name": "YO24 1DT",
    "wof:placetype": "postalcode"
  },
  "geometry": {"coordinates":[-1.10411,53.948717],"type":"Point"}
}
