{
  "type": "Feature",
  "properties": {
    "iso:country":"GB",
    "wof:name":"CW7 1DA",
    "wof:placetype":"postalcode"
},
  "geometry": {"coordinates":[-2.53598369389568,53.18706765168385],"type":"Point"}
}