{
  "type": "Feature",
  "properties": {
    "iso:country":"GB",
    "wof:name":"SP4 8ED",
    "wof:placetype":"postalcode"
},
  "geometry": {"coordinates":[-1.77369532275231,51.19796825288],"type":"Point"}
}