{
  "type": "Feature",
  "properties": {
    "date:inception_lower": "1980-01-01",
    "date:inception_upper": "1980-01-01",
    "iso:country": "GB",
    "wof:name": "SP4 8ED",
    "wof:placetype": "postalcode"
  },
  "geometry": {"coordinates":[-1.773695,51.197968],"type":"Point"}
}
