{
  "type": "Feature",
  "properties": {
    "date:inception_lower":"1980-01-01",
    "date:inception_upper":"1980-01-31",
    "iso:country":"GB",
    "wof:name":"SN10 2JD",
    "wof:placetype":"postalcode"
},
  "geometry": {"coordinates":[-1.99646,51.367988],"type":"Point"}
}