{
  "type": "Feature",
  "properties": {
    "iso:country": "GB",
    "wof:name": "SN10 2JD",
    "wof:placetype": "postalcode"
  },
  "geometry": {"coordinates":[-1.99646,51.367988],"type":"Point"}
}
