{
  "type": "Feature",
  "properties": {
    "iso:country":"GB",
    "wof:name":"SN10 2JD",
    "wof:placetype":"postalcode"
},
  "geometry": {"coordinates":[-1.99646020085668,51.36798765220621],"type":"Point"}
}