{
  "type": "Feature",
  "properties": {
    "iso:country":"GB",
    "wof:name":"LL21 9BE",
    "wof:placetype":"postalcode"
},
  "geometry": {"coordinates":[-3.31830770409464,52.98403113077505],"type":"Point"}
}