{
  "type": "Feature",
  "properties": {
    "iso:country":"GB",
    "wof:name":"PL30 4HF",
    "wof:placetype":"postalcode"
},
  "geometry": {"coordinates":[-4.6056542979937,50.49636914645006],"type":"Point"}
}