{
  "type": "Feature",
  "properties": {
    "date:inception_lower":"1980-01-01",
    "date:inception_upper":"1980-01-31",
    "iso:country":"GB",
    "wof:name":"PL30 4HF",
    "wof:placetype":"postalcode"
},
  "geometry": {"coordinates":[-4.605654,50.496369],"type":"Point"}
}