{
  "type": "Feature",
  "properties": {
    "iso:country":"GB",
    "wof:name":"CH7 6PP",
    "wof:placetype":"postalcode"
},
  "geometry": {"coordinates":[-3.18358282123679,53.21063727945559],"type":"Point"}
}