{
  "type": "Feature",
  "properties": {
    "date:inception_lower": "1993-08-01",
    "date:inception_upper": "1993-08-01",
    "iso:country": "GB",
    "wof:name": "CH7 6PP",
    "wof:placetype": "postalcode"
  },
  "geometry": {"coordinates":[-3.183583,53.210637],"type":"Point"}
}
