{
  "type": "Feature",
  "properties": {
    "iso:country":"GB",
    "wof:name":"BD19 4HA",
    "wof:placetype":"postalcode"
},
  "geometry": {"coordinates":[-1.68246244781491,53.72602107782487],"type":"Point"}
}