{
  "type": "Feature",
  "properties": {
    "date:inception_lower":"1991-01-01",
    "date:inception_upper":"1991-01-31",
    "iso:country":"GB",
    "wof:name":"PO7 4TA",
    "wof:placetype":"postalcode"
},
  "geometry": {"coordinates":[-1.091559,50.945007],"type":"Point"}
}