{
  "type": "Feature",
  "properties": {
    "iso:country":"GB",
    "wof:name":"PO7 4TA",
    "wof:placetype":"postalcode"
},
  "geometry": {"coordinates":[-1.09155885900112,50.94500717541976],"type":"Point"}
}