{
  "type": "Feature",
  "properties": {
    "iso:country":"GB",
    "wof:name":"G71 6BF",
    "wof:placetype":"postalcode"
},
  "geometry": {"coordinates":[-4.08585073831975,55.8351430493779],"type":"Point"}
}