{
  "type": "Feature",
  "properties": {
    "iso:country": "GB",
    "wof:name": "G71 6BF",
    "wof:placetype": "postalcode"
  },
  "geometry": {"coordinates":[-4.085851,55.835143],"type":"Point"}
}
