{
  "type": "Feature",
  "properties": {
    "date:inception_lower":"2015-05-01",
    "date:inception_upper":"2015-05-31",
    "iso:country":"GB",
    "wof:name":"G71 6BF",
    "wof:placetype":"postalcode"
},
  "geometry": {"coordinates":[-4.085851,55.835143],"type":"Point"}
}