{
  "type": "Feature",
  "properties": {
    "date:inception_lower": "1980-01-01",
    "date:inception_upper": "1980-01-01",
    "iso:country": "GB",
    "wof:name": "PO22 6HW",
    "wof:placetype": "postalcode"
  },
  "geometry": {"coordinates":[-0.613309,50.795477],"type":"Point"}
}
