{
  "type": "Feature",
  "properties": {
    "iso:country":"GB",
    "wof:name":"GL4 6BT",
    "wof:placetype":"postalcode"
},
  "geometry": {"coordinates":[-2.22705790886957,51.85107714274723],"type":"Point"}
}