{
  "type": "Feature",
  "properties": {
    "iso:country": "GB",
    "wof:name": "YO16 4DG",
    "wof:placetype": "postalcode"
  },
  "geometry": {"coordinates":[-0.214998,54.094206],"type":"Point"}
}
