{
  "type": "Feature",
  "properties": {
    "iso:country":"GB",
    "wof:name":"YO16 4DG",
    "wof:placetype":"postalcode"
},
  "geometry": {"coordinates":[-0.21499803949242,54.09420614253815],"type":"Point"}
}