{
  "type": "Feature",
  "properties": {
    "iso:country":"GB",
    "wof:name":"SP10 3LL",
    "wof:placetype":"postalcode"
},
  "geometry": {"coordinates":[-1.51143474208552,51.20981948346564],"type":"Point"}
}