{
  "type": "Feature",
  "properties": {
    "date:inception_lower": "1997-12-01",
    "date:inception_upper": "1997-12-01",
    "iso:country": "GB",
    "wof:name": "TN21 0QZ",
    "wof:placetype": "postalcode"
  },
  "geometry": {"coordinates":[0.224308,50.972788],"type":"Point"}
}
