{
  "type": "Feature",
  "properties": {
    "iso:country": "GB",
    "wof:name": "TN21 0QZ",
    "wof:placetype": "postalcode"
  },
  "geometry": {"coordinates":[0.224332,50.972684],"type":"Point"}
}
