{
  "type": "Feature",
  "properties": {
    "iso:country":"GB",
    "wof:name":"TN21 0QZ",
    "wof:placetype":"postalcode"
},
  "geometry": {"coordinates":[0.22433172790448,50.97268377911531],"type":"Point"}
}