{
  "type": "Feature",
  "properties": {
    "iso:country": "GB",
    "wof:name": "TR8 4HL",
    "wof:placetype": "postalcode"
  },
  "geometry": {"coordinates":[-5.044533,50.413386],"type":"Point"}
}
