{
  "type": "Feature",
  "properties": {
    "iso:country":"GB",
    "wof:name":"YO10 3AG",
    "wof:placetype":"postalcode"
},
  "geometry": {"coordinates":[-1.05202752836464,53.95484242774496],"type":"Point"}
}