{
  "type": "Feature",
  "properties": {
    "date:inception_lower": "1998-06-01",
    "date:inception_upper": "1998-06-01",
    "iso:country": "GB",
    "wof:name": "YO10 3AG",
    "wof:placetype": "postalcode"
  },
  "geometry": {"coordinates":[-1.052027,53.954842],"type":"Point"}
}
