{
  "type": "Feature",
  "properties": {
    "iso:country":"GB",
    "wof:name":"LS8 2PA",
    "wof:placetype":"postalcode"
},
  "geometry": {"coordinates":[-1.50276101394482,53.82469302501029],"type":"Point"}
}