{
  "type": "Feature",
  "properties": {
    "iso:country":"GB",
    "wof:name":"SG1 4DT",
    "wof:placetype":"postalcode"
},
  "geometry": {"coordinates":[-0.18360341390754,51.92333755829952],"type":"Point"}
}