{
  "type": "Feature",
  "properties": {
    "iso:country":"GB",
    "wof:name":"CF32 0PS",
    "wof:placetype":"postalcode"
},
  "geometry": {"coordinates":[-3.62889672539138,51.45937130586385],"type":"Point"}
}