{
  "type": "Feature",
  "properties": {
    "iso:country": "GB",
    "wof:name": "NG19 6NW",
    "wof:placetype": "postalcode"
  },
  "geometry": {"coordinates":[-1.222954,53.153606],"type":"Point"}
}
