{
  "type": "Feature",
  "properties": {
    "iso:country":"GB",
    "wof:name":"NG19 6NW",
    "wof:placetype":"postalcode"
},
  "geometry": {"coordinates":[-1.22295361134585,53.15360604095835],"type":"Point"}
}