{
  "type": "Feature",
  "properties": {
    "iso:country":"GB",
    "wof:name":"NE22 5AL",
    "wof:placetype":"postalcode"
},
  "geometry": {"coordinates":[-1.58684273435277,55.1290362049364],"type":"Point"}
}