{
  "type": "Feature",
  "properties": {
    "date:inception_lower": "2005-06-01",
    "date:inception_upper": "2005-06-01",
    "iso:country": "GB",
    "wof:name": "LL11 1PA",
    "wof:placetype": "postalcode"
  },
  "geometry": {"coordinates":[-2.999658,53.048483],"type":"Point"}
}
