{
  "type": "Feature",
  "properties": {
    "iso:country":"GB",
    "wof:name":"G51 4UB",
    "wof:placetype":"postalcode"
},
  "geometry": {"coordinates":[-4.32390062657904,55.85471882139434],"type":"Point"}
}