{
  "type": "Feature",
  "properties": {
    "iso:country":"GB",
    "wof:name":"DN5 7HW",
    "wof:placetype":"postalcode"
},
  "geometry": {"coordinates":[-1.27436769930755,53.52428908841973],"type":"Point"}
}