{
  "type": "Feature",
  "properties": {
    "iso:country": "GB",
    "wof:name": "CO2 7JX",
    "wof:placetype": "postalcode"
  },
  "geometry": {"coordinates":[0.880753,51.873276],"type":"Point"}
}
