{
  "type": "Feature",
  "properties": {
    "iso:country":"GB",
    "wof:name":"CO2 7JX",
    "wof:placetype":"postalcode"
},
  "geometry": {"coordinates":[0.88075266406173,51.87327566134999],"type":"Point"}
}