{
  "type": "Feature",
  "properties": {
    "date:inception_lower":"1991-01-01",
    "date:inception_upper":"1991-01-31",
    "iso:country":"GB",
    "wof:name":"TS6 9BU",
    "wof:placetype":"postalcode"
},
  "geometry": {"coordinates":[-1.155087,54.559666],"type":"Point"}
}