{
  "type": "Feature",
  "properties": {
    "iso:country":"GB",
    "wof:name":"TS6 9BU",
    "wof:placetype":"postalcode"
},
  "geometry": {"coordinates":[-1.15508671700184,54.55966598110299],"type":"Point"}
}