{
  "type": "Feature",
  "properties": {
    "iso:country":"GB",
    "wof:name":"SG14 1DP",
    "wof:placetype":"postalcode"
},
  "geometry": {"coordinates":[-0.07779226166244,51.79648687224928],"type":"Point"}
}