{
  "type": "Feature",
  "properties": {
    "iso:country": "GB",
    "wof:name": "TA19 9HZ",
    "wof:placetype": "postalcode"
  },
  "geometry": {"coordinates":[-2.895636,50.954762],"type":"Point"}
}
