{
  "type": "Feature",
  "properties": {
    "iso:country":"GB",
    "wof:name":"GL51 6UJ",
    "wof:placetype":"postalcode"
},
  "geometry": {"coordinates":[-2.13369744746097,51.89177843217578],"type":"Point"}
}