{
  "type": "Feature",
  "properties": {
    "iso:country": "GB",
    "wof:name": "GL51 6UJ",
    "wof:placetype": "postalcode"
  },
  "geometry": {"coordinates":[-2.133697,51.891778],"type":"Point"}
}
