{
  "type": "Feature",
  "properties": {
    "iso:country": "GB",
    "wof:name": "CH64 2XP",
    "wof:placetype": "postalcode"
  },
  "geometry": {"coordinates":[-3.009509,53.292774],"type":"Point"}
}
