{
  "type": "Feature",
  "properties": {
    "iso:country": "GB",
    "wof:name": "YO18 8AR",
    "wof:placetype": "postalcode"
  },
  "geometry": {"coordinates":[-0.786946,54.249552],"type":"Point"}
}
