{
  "type": "Feature",
  "properties": {
    "iso:country": "GB",
    "wof:name": "EX2 6AU",
    "wof:placetype": "postalcode"
  },
  "geometry": {"coordinates":[-3.50342,50.711781],"type":"Point"}
}
