{
  "type": "Feature",
  "properties": {
    "iso:country":"GB",
    "wof:name":"IP9 1JJ",
    "wof:placetype":"postalcode"
},
  "geometry": {"coordinates":[1.21243327499657,51.99323423134891],"type":"Point"}
}