{
  "type": "Feature",
  "properties": {
    "iso:country": "GB",
    "wof:name": "CV31 1PX",
    "wof:placetype": "postalcode"
  },
  "geometry": {"coordinates":[-1.520754,52.28259],"type":"Point"}
}
