{
  "type": "Feature",
  "properties": {
    "iso:country": "GB",
    "wof:name": "AB39 3QB",
    "wof:placetype": "postalcode"
  },
  "geometry": {"coordinates":[-2.205639,56.992862],"type":"Point"}
}
