{
  "type": "Feature",
  "properties": {
    "iso:country":"GB",
    "wof:name":"AB39 3QB",
    "wof:placetype":"postalcode"
},
  "geometry": {"coordinates":[-2.20563923164152,56.99286245401395],"type":"Point"}
}