{
  "type": "Feature",
  "properties": {
    "iso:country":"GB",
    "wof:name":"OX5 1NJ",
    "wof:placetype":"postalcode"
},
  "geometry": {"coordinates":[-1.30729795159078,51.80841233081753],"type":"Point"}
}