{
  "type": "Feature",
  "properties": {
    "date:inception_lower":"1980-01-01",
    "date:inception_upper":"1980-01-31",
    "iso:country":"GB",
    "wof:name":"OX5 1NJ",
    "wof:placetype":"postalcode"
},
  "geometry": {"coordinates":[-1.307298,51.808412],"type":"Point"}
}