{
  "type": "Feature",
  "properties": {
    "date:inception_lower":"1980-01-01",
    "date:inception_upper":"1980-01-31",
    "iso:country":"GB",
    "wof:name":"L34 2TN",
    "wof:placetype":"postalcode"
},
  "geometry": {"coordinates":[-2.785019,53.432981],"type":"Point"}
}