{
  "type": "Feature",
  "properties": {
    "iso:country": "GB",
    "wof:name": "OX33 1TF",
    "wof:placetype": "postalcode"
  },
  "geometry": {"coordinates":[-1.163879,51.743948],"type":"Point"}
}
