{
  "type": "Feature",
  "properties": {
    "iso:country":"GB",
    "wof:name":"OX33 1TF",
    "wof:placetype":"postalcode"
},
  "geometry": {"coordinates":[-1.16362243774512,51.74295725879808],"type":"Point"}
}