{
  "type": "Feature",
  "properties": {
    "date:inception_lower": "1992-08-01",
    "date:inception_upper": "1992-08-01",
    "iso:country": "GB",
    "wof:name": "LE67 3SN",
    "wof:placetype": "postalcode"
  },
  "geometry": {"coordinates":[-1.368806,52.716234],"type":"Point"}
}
