{
  "type": "Feature",
  "properties": {
    "iso:country":"GB",
    "wof:name":"DE1 2HL",
    "wof:placetype":"postalcode"
},
  "geometry": {"coordinates":[-1.48002837337729,52.91511010997559],"type":"Point"}
}