{
  "type": "Feature",
  "properties": {
    "date:inception_lower": "1981-06-01",
    "date:inception_upper": "1981-06-01",
    "iso:country": "GB",
    "wof:name": "CV21 2JR",
    "wof:placetype": "postalcode"
  },
  "geometry": {"coordinates":[-1.26319,52.373157],"type":"Point"}
}
