{
  "type": "Feature",
  "properties": {
    "iso:country":"GB",
    "wof:name":"TQ12 6FA",
    "wof:placetype":"postalcode"
},
  "geometry": {"coordinates":[-3.6232823676236,50.52307133339608],"type":"Point"}
}