{
  "type": "Feature",
  "properties": {
    "iso:country":"GB",
    "wof:name":"CV4 7BY",
    "wof:placetype":"postalcode"
},
  "geometry": {"coordinates":[-1.54587454054857,52.38732077824201],"type":"Point"}
}