{
  "type": "Feature",
  "properties": {
    "date:inception_lower":"1980-01-01",
    "date:inception_upper":"1980-01-31",
    "iso:country":"GB",
    "wof:name":"CV4 7BY",
    "wof:placetype":"postalcode"
},
  "geometry": {"coordinates":[-1.545874,52.387321],"type":"Point"}
}