{
  "type": "Feature",
  "properties": {
    "iso:country": "GB",
    "wof:name": "UB1 3ND",
    "wof:placetype": "postalcode"
  },
  "geometry": {"coordinates":[-0.359446,51.515571],"type":"Point"}
}
