{
  "type": "Feature",
  "properties": {
    "iso:country":"GB",
    "wof:name":"UB1 3ND",
    "wof:placetype":"postalcode"
},
  "geometry": {"coordinates":[-0.35944638951208,51.51557094136275],"type":"Point"}
}