{
  "type": "Feature",
  "properties": {
    "iso:country":"GB",
    "wof:name":"TR12 7QE",
    "wof:placetype":"postalcode"
},
  "geometry": {"coordinates":[-5.270810322924,50.04152783095968],"type":"Point"}
}