{
  "type": "Feature",
  "properties": {
    "date:inception_lower": "1980-01-01",
    "date:inception_upper": "1980-01-01",
    "iso:country": "GB",
    "wof:name": "TR12 7QE",
    "wof:placetype": "postalcode"
  },
  "geometry": {"coordinates":[-5.27081,50.041528],"type":"Point"}
}
