{
  "type": "Feature",
  "properties": {
    "iso:country":"GB",
    "wof:name":"N8 7LN",
    "wof:placetype":"postalcode"
},
  "geometry": {"coordinates":[-0.12424974791777,51.59125121633273],"type":"Point"}
}