{
  "type": "Feature",
  "properties": {
    "iso:country": "GB",
    "wof:name": "RG42 1XB",
    "wof:placetype": "postalcode"
  },
  "geometry": {"coordinates":[-0.76949,51.421704],"type":"Point"}
}
