{
  "type": "Feature",
  "properties": {
    "iso:country":"GB",
    "wof:name":"RG42 1XB",
    "wof:placetype":"postalcode"
},
  "geometry": {"coordinates":[-0.76948998017232,51.42170379659301],"type":"Point"}
}