{
  "type": "Feature",
  "properties": {
    "iso:country": "GB",
    "wof:name": "CH7 5HX",
    "wof:placetype": "postalcode"
  },
  "geometry": {"coordinates":[-3.191597,53.192947],"type":"Point"}
}
