{
  "type": "Feature",
  "properties": {
    "iso:country":"GB",
    "wof:name":"CB8 9TX",
    "wof:placetype":"postalcode"
},
  "geometry": {"coordinates":[0.41646340084041,52.18971375671688],"type":"Point"}
}