{
  "type": "Feature",
  "properties": {
    "date:inception_lower": "1980-01-01",
    "date:inception_upper": "1980-01-01",
    "iso:country": "GB",
    "wof:name": "CB8 9TX",
    "wof:placetype": "postalcode"
  },
  "geometry": {"coordinates":[0.416463,52.189714],"type":"Point"}
}
