{
  "type": "Feature",
  "properties": {
    "iso:country":"GB",
    "wof:name":"BD18 2PH",
    "wof:placetype":"postalcode"
},
  "geometry": {"coordinates":[-1.75997468620401,53.83429996791067],"type":"Point"}
}