{
  "type": "Feature",
  "properties": {
    "iso:country": "GB",
    "wof:name": "BD18 2PH",
    "wof:placetype": "postalcode"
  },
  "geometry": {"coordinates":[-1.759975,53.8343],"type":"Point"}
}
