{
  "type": "Feature",
  "properties": {
    "iso:country":"GB",
    "wof:name":"PR4 1RU",
    "wof:placetype":"postalcode"
},
  "geometry": {"coordinates":[-2.87368213373505,53.75112711326893],"type":"Point"}
}