{
  "type": "Feature",
  "properties": {
    "iso:country":"GB",
    "wof:name":"HP22 5SE",
    "wof:placetype":"postalcode"
},
  "geometry": {"coordinates":[-0.76199504723919,51.7865742861847],"type":"Point"}
}