{
  "type": "Feature",
  "properties": {
    "date:inception_lower": "1980-01-01",
    "date:inception_upper": "1980-01-01",
    "iso:country": "GB",
    "wof:name": "HP22 5SE",
    "wof:placetype": "postalcode"
  },
  "geometry": {"coordinates":[-0.761995,51.786574],"type":"Point"}
}
