{
  "type": "Feature",
  "properties": {
    "date:inception_lower": "2007-11-01",
    "date:inception_upper": "2007-11-01",
    "iso:country": "GB",
    "wof:name": "DL17 9EY",
    "wof:placetype": "postalcode"
  },
  "geometry": {"coordinates":[-1.526824,54.688727],"type":"Point"}
}
