{
  "type": "Feature",
  "properties": {
    "date:inception_lower":"2008-12-01",
    "date:inception_upper":"2008-12-31",
    "iso:country":"GB",
    "wof:name":"ME3 8FD",
    "wof:placetype":"postalcode"
},
  "geometry": {"coordinates":[0.514709,51.414394],"type":"Point"}
}