{
  "type": "Feature",
  "properties": {
    "iso:country":"GB",
    "wof:name":"ME3 8FD",
    "wof:placetype":"postalcode"
},
  "geometry": {"coordinates":[0.51470941475151,51.4143940030476],"type":"Point"}
}