{
  "type": "Feature",
  "properties": {
    "iso:country": "GB",
    "wof:name": "NP11 4PS",
    "wof:placetype": "postalcode"
  },
  "geometry": {"coordinates":[-3.140223,51.676108],"type":"Point"}
}
