{
  "type": "Feature",
  "properties": {
    "iso:country":"GB",
    "wof:name":"EH20 9SE",
    "wof:placetype":"postalcode"
},
  "geometry": {"coordinates":[-3.13789499272884,55.87820632228939],"type":"Point"}
}