{
  "type": "Feature",
  "properties": {
    "date:inception_lower":"1980-01-01",
    "date:inception_upper":"1980-01-31",
    "iso:country":"GB",
    "wof:name":"RH8 9JJ",
    "wof:placetype":"postalcode"
},
  "geometry": {"coordinates":[-0.015824,51.251365],"type":"Point"}
}