{
  "type": "Feature",
  "properties": {
    "iso:country": "GB",
    "wof:name": "RH8 9JJ",
    "wof:placetype": "postalcode"
  },
  "geometry": {"coordinates":[-0.015824,51.251365],"type":"Point"}
}
