{
  "type": "Feature",
  "properties": {
    "iso:country":"GB",
    "wof:name":"S44 6EZ",
    "wof:placetype":"postalcode"
},
  "geometry": {"coordinates":[-1.28278362582043,53.22899502822391],"type":"Point"}
}