{
  "type": "Feature",
  "properties": {
    "iso:country": "GB",
    "wof:name": "PO7 6HR",
    "wof:placetype": "postalcode"
  },
  "geometry": {"coordinates":[-1.050286,50.900642],"type":"Point"}
}
