{
  "type": "Feature",
  "properties": {
    "iso:country": "GB",
    "wof:name": "WA5 3XW",
    "wof:placetype": "postalcode"
  },
  "geometry": {"coordinates":[-2.661837,53.404027],"type":"Point"}
}
