{
  "type": "Feature",
  "properties": {
    "iso:country":"GB",
    "wof:name":"NR9 5RX",
    "wof:placetype":"postalcode"
},
  "geometry": {"coordinates":[1.05544258720824,52.72004257377474],"type":"Point"}
}