{
  "type": "Feature",
  "properties": {
    "iso:country":"GB",
    "wof:name":"SA62 6RT",
    "wof:placetype":"postalcode"
},
  "geometry": {"coordinates":[-5.26855160516475,51.8798390472755],"type":"Point"}
}