{
  "type": "Feature",
  "properties": {
    "date:inception_lower": "1995-12-01",
    "date:inception_upper": "1995-12-01",
    "iso:country": "GB",
    "wof:name": "SA62 6RT",
    "wof:placetype": "postalcode"
  },
  "geometry": {"coordinates":[-5.268586,51.879845],"type":"Point"}
}
