{
  "type": "Feature",
  "properties": {
    "iso:country": "GB",
    "wof:name": "OL3 6BP",
    "wof:placetype": "postalcode"
  },
  "geometry": {"coordinates":[-2.003916,53.549751],"type":"Point"}
}
