{
  "type": "Feature",
  "properties": {
    "date:inception_lower":"1980-01-01",
    "date:inception_upper":"1980-01-31",
    "iso:country":"GB",
    "wof:name":"DY7 5NG",
    "wof:placetype":"postalcode"
},
  "geometry": {"coordinates":[-2.287623,52.44479],"type":"Point"}
}