{
  "type": "Feature",
  "properties": {
    "iso:country": "GB",
    "wof:name": "DY7 5NG",
    "wof:placetype": "postalcode"
  },
  "geometry": {"coordinates":[-2.287623,52.44479],"type":"Point"}
}
