{
  "type": "Feature",
  "properties": {
    "date:inception_lower": "1980-01-01",
    "date:inception_upper": "1980-01-01",
    "iso:country": "GB",
    "wof:name": "CA9 3AR",
    "wof:placetype": "postalcode"
  },
  "geometry": {"coordinates":[-2.450867,54.810256],"type":"Point"}
}
