{
  "type": "Feature",
  "properties": {
    "iso:country":"GB",
    "wof:name":"WA3 5LS",
    "wof:placetype":"postalcode"
},
  "geometry": {"coordinates":[-2.49591326228002,53.46975804177573],"type":"Point"}
}