{
  "type": "Feature",
  "properties": {
    "date:inception_lower": "1980-01-01",
    "date:inception_upper": "1980-01-01",
    "iso:country": "GB",
    "wof:name": "DL9 3AB",
    "wof:placetype": "postalcode"
  },
  "geometry": {"coordinates":[-1.745651,54.378887],"type":"Point"}
}
