{
  "type": "Feature",
  "properties": {
    "iso:country":"GB",
    "wof:name":"DL9 3AB",
    "wof:placetype":"postalcode"
},
  "geometry": {"coordinates":[-1.74565061850236,54.37888711514754],"type":"Point"}
}