{
  "type": "Feature",
  "properties": {
    "date:inception_lower": "1998-12-01",
    "date:inception_upper": "1998-12-01",
    "iso:country": "GB",
    "wof:name": "EC4R 3XJ",
    "wof:placetype": "postalcode"
  },
  "geometry": {"coordinates":[-0.09139,51.509951],"type":"Point"}
}
