{
  "type": "Feature",
  "properties": {
    "iso:country":"GB",
    "wof:name":"EC4R 3XJ",
    "wof:placetype":"postalcode"
},
  "geometry": {"coordinates":[-0.09139037522854,51.50995068854725],"type":"Point"}
}