{
  "type": "Feature",
  "properties": {
    "date:inception_lower":"2005-02-01",
    "date:inception_upper":"2005-02-28",
    "iso:country":"GB",
    "wof:name":"EH6 5FB",
    "wof:placetype":"postalcode"
},
  "geometry": {"coordinates":[-3.185644,55.965849],"type":"Point"}
}