{
  "type": "Feature",
  "properties": {
    "iso:country":"GB",
    "wof:name":"EH6 5FB",
    "wof:placetype":"postalcode"
},
  "geometry": {"coordinates":[-3.18564429730262,55.96584949980824],"type":"Point"}
}