{
  "type": "Feature",
  "properties": {
    "iso:country": "GB",
    "wof:name": "LS7 3JQ",
    "wof:placetype": "postalcode"
  },
  "geometry": {"coordinates":[-1.538789,53.81833],"type":"Point"}
}
