{
  "type": "Feature",
  "properties": {
    "date:inception_lower": "1983-03-01",
    "date:inception_upper": "1983-03-01",
    "iso:country": "GB",
    "wof:name": "W12 9PP",
    "wof:placetype": "postalcode"
  },
  "geometry": {"coordinates":[-0.23757,51.504983],"type":"Point"}
}
