{
  "type": "Feature",
  "properties": {
    "iso:country":"GB",
    "wof:name":"W12 9PP",
    "wof:placetype":"postalcode"
},
  "geometry": {"coordinates":[-0.23768098625703,51.50496517283939],"type":"Point"}
}