{
  "type": "Feature",
  "properties": {
    "iso:country":"GB",
    "wof:name":"NG18 3DF",
    "wof:placetype":"postalcode"
},
  "geometry": {"coordinates":[-1.17838642252434,53.14208850824241],"type":"Point"}
}