{
  "type": "Feature",
  "properties": {
    "iso:country": "GB",
    "wof:name": "NG18 3DF",
    "wof:placetype": "postalcode"
  },
  "geometry": {"coordinates":[-1.178323,53.142179],"type":"Point"}
}
