{
  "type": "Feature",
  "properties": {
    "date:inception_lower": "1980-01-01",
    "date:inception_upper": "1980-01-01",
    "iso:country": "GB",
    "wof:name": "N9 8LJ",
    "wof:placetype": "postalcode"
  },
  "geometry": {"coordinates":[-0.048801,51.62843],"type":"Point"}
}
