{
  "type": "Feature",
  "properties": {
    "iso:country":"GB",
    "wof:name":"N9 8LJ",
    "wof:placetype":"postalcode"
},
  "geometry": {"coordinates":[-0.04940306741146,51.6284559655738],"type":"Point"}
}