{
  "type": "Feature",
  "properties": {
    "iso:country": "GB",
    "wof:name": "KY4 8HA",
    "wof:placetype": "postalcode"
  },
  "geometry": {"coordinates":[-3.36169,56.083242],"type":"Point"}
}
