{
  "type": "Feature",
  "properties": {
    "iso:country":"GB",
    "wof:name":"KY5 9ET",
    "wof:placetype":"postalcode"
},
  "geometry": {"coordinates":[-3.31434429231851,56.1316921463329],"type":"Point"}
}