{
  "type": "Feature",
  "properties": {
    "date:inception_lower":"1980-07-01",
    "date:inception_upper":"1980-07-31",
    "iso:country":"GB",
    "wof:name":"KY5 9ET",
    "wof:placetype":"postalcode"
},
  "geometry": {"coordinates":[-3.314344,56.131692],"type":"Point"}
}