{
  "type": "Feature",
  "properties": {
    "iso:country":"GB",
    "wof:name":"DY8 1NA",
    "wof:placetype":"postalcode"
},
  "geometry": {"coordinates":[-2.13980578361331,52.45219018196214],"type":"Point"}
}