{
  "type": "Feature",
  "properties": {
    "iso:country": "GB",
    "wof:name": "DY8 1NA",
    "wof:placetype": "postalcode"
  },
  "geometry": {"coordinates":[-2.13977,52.452204],"type":"Point"}
}
