{
  "type": "Feature",
  "properties": {
    "iso:country":"GB",
    "wof:name":"DN9 2BX",
    "wof:placetype":"postalcode"
},
  "geometry": {"coordinates":[-0.92496423562544,53.52214415886858],"type":"Point"}
}