{
  "type": "Feature",
  "properties": {
    "iso:country": "GB",
    "wof:name": "SK6 6LZ",
    "wof:placetype": "postalcode"
  },
  "geometry": {"coordinates":[-2.066823,53.396812],"type":"Point"}
}
