{
  "type": "Feature",
  "properties": {
    "iso:country":"GB",
    "wof:name":"SK6 6LZ",
    "wof:placetype":"postalcode"
},
  "geometry": {"coordinates":[-2.06682265072285,53.3968118331336],"type":"Point"}
}