{
  "type": "Feature",
  "properties": {
    "date:inception_lower":"1982-03-01",
    "date:inception_upper":"1982-03-31",
    "iso:country":"GB",
    "wof:name":"SG19 3NQ",
    "wof:placetype":"postalcode"
},
  "geometry": {"coordinates":[-0.197029,52.155179],"type":"Point"}
}