{
  "type": "Feature",
  "properties": {
    "iso:country": "GB",
    "wof:name": "SG19 3NQ",
    "wof:placetype": "postalcode"
  },
  "geometry": {"coordinates":[-0.197029,52.155179],"type":"Point"}
}
