{
  "type": "Feature",
  "properties": {
    "iso:country":"GB",
    "wof:name":"PE11 3HE",
    "wof:placetype":"postalcode"
},
  "geometry": {"coordinates":[-0.1686000029799,52.77891664503889],"type":"Point"}
}