{
  "type": "Feature",
  "properties": {
    "iso:country":"GB",
    "wof:name":"G51 4EH",
    "wof:placetype":"postalcode"
},
  "geometry": {"coordinates":[-4.33110517716488,55.85549023936555],"type":"Point"}
}