{
  "type": "Feature",
  "properties": {
    "iso:country":"GB",
    "wof:name":"SE6 4UR",
    "wof:placetype":"postalcode"
},
  "geometry": {"coordinates":[-0.03478679880615,51.44420561773163],"type":"Point"}
}