{
  "type": "Feature",
  "properties": {
    "iso:country": "GB",
    "wof:name": "TA5 2DS",
    "wof:placetype": "postalcode"
  },
  "geometry": {"coordinates":[-3.084358,51.108249],"type":"Point"}
}
