{
  "type": "Feature",
  "properties": {
    "date:inception_lower": "1980-01-01",
    "date:inception_upper": "1980-01-01",
    "iso:country": "GB",
    "wof:name": "TA5 2DS",
    "wof:placetype": "postalcode"
  },
  "geometry": {"coordinates":[-3.084358,51.108249],"type":"Point"}
}
