{
  "type": "Feature",
  "properties": {
    "iso:country": "GB",
    "wof:name": "W10 4SR",
    "wof:placetype": "postalcode"
  },
  "geometry": {"coordinates":[-0.21742,51.526908],"type":"Point"}
}
