{
  "type": "Feature",
  "properties": {
    "iso:country":"GB",
    "wof:name":"W10 4SR",
    "wof:placetype":"postalcode"
},
  "geometry": {"coordinates":[-0.21576091352221,51.52681805108584],"type":"Point"}
}