{
  "type": "Feature",
  "properties": {
    "iso:country": "GB",
    "wof:name": "CW7 4DL",
    "wof:placetype": "postalcode"
  },
  "geometry": {"coordinates":[-2.558552,53.139924],"type":"Point"}
}
