{
  "type": "Feature",
  "properties": {
    "date:inception_lower":"1980-01-01",
    "date:inception_upper":"1980-01-31",
    "iso:country":"GB",
    "wof:name":"CW7 4DL",
    "wof:placetype":"postalcode"
},
  "geometry": {"coordinates":[-2.558552,53.139924],"type":"Point"}
}