{
  "type": "Feature",
  "properties": {
    "iso:country":"GB",
    "wof:name":"CW7 4DL",
    "wof:placetype":"postalcode"
},
  "geometry": {"coordinates":[-2.55835613913992,53.13978140843531],"type":"Point"}
}