{
  "type": "Feature",
  "properties": {
    "iso:country":"GB",
    "wof:name":"DH1 3RF",
    "wof:placetype":"postalcode"
},
  "geometry": {"coordinates":[-1.586713309377,54.76547653993548],"type":"Point"}
}