{
  "type": "Feature",
  "properties": {
    "date:inception_lower":"2014-06-01",
    "date:inception_upper":"2014-06-30",
    "iso:country":"GB",
    "wof:name":"DH1 3RF",
    "wof:placetype":"postalcode"
},
  "geometry": {"coordinates":[-1.586713,54.765477],"type":"Point"}
}