{
  "type": "Feature",
  "properties": {
    "iso:country":"GB",
    "wof:name":"OL15 0AQ",
    "wof:placetype":"postalcode"
},
  "geometry": {"coordinates":[-2.09042162449816,53.63148303608637],"type":"Point"}
}