{
  "type": "Feature",
  "properties": {
    "iso:country":"GB",
    "wof:name":"KA8 9QN",
    "wof:placetype":"postalcode"
},
  "geometry": {"coordinates":[-4.60680822238776,55.47291245731797],"type":"Point"}
}