{
  "type": "Feature",
  "properties": {
    "iso:country": "GB",
    "wof:name": "OL16 4BE",
    "wof:placetype": "postalcode"
  },
  "geometry": {"coordinates":[-2.123333,53.612938],"type":"Point"}
}
