{
  "type": "Feature",
  "properties": {
    "iso:country":"GB",
    "wof:name":"LN7 6JZ",
    "wof:placetype":"postalcode"
},
  "geometry": {"coordinates":[-0.42139556106316,53.5237297496792],"type":"Point"}
}