{
  "type": "Feature",
  "properties": {
    "iso:country":"GB",
    "wof:name":"DL2 3DD",
    "wof:placetype":"postalcode"
},
  "geometry": {"coordinates":[-1.73381734079363,54.5469452505957],"type":"Point"}
}