{
  "type": "Feature",
  "properties": {
    "iso:country":"GB",
    "wof:name":"G52 1HH",
    "wof:placetype":"postalcode"
},
  "geometry": {"coordinates":[-4.3240265181057,55.84612426920715],"type":"Point"}
}