{
  "type": "Feature",
  "properties": {
    "date:inception_lower": "1980-01-01",
    "date:inception_upper": "1980-01-01",
    "iso:country": "GB",
    "wof:name": "G52 1HH",
    "wof:placetype": "postalcode"
  },
  "geometry": {"coordinates":[-4.324026,55.846124],"type":"Point"}
}
