{
  "type": "Feature",
  "properties": {
    "iso:country":"GB",
    "wof:name":"NE19 1HS",
    "wof:placetype":"postalcode"
},
  "geometry": {"coordinates":[-2.21173813639137,55.28384757737747],"type":"Point"}
}