{
  "type": "Feature",
  "properties": {
    "iso:country": "GB",
    "wof:name": "NE19 1HS",
    "wof:placetype": "postalcode"
  },
  "geometry": {"coordinates":[-2.21162,55.283779],"type":"Point"}
}
