{
  "type": "Feature",
  "properties": {
    "iso:country":"GB",
    "wof:name":"NP20 3PF",
    "wof:placetype":"postalcode"
},
  "geometry": {"coordinates":[-3.03419602885274,51.57694123468895],"type":"Point"}
}