{
  "type": "Feature",
  "properties": {
    "date:inception_lower":"2005-03-01",
    "date:inception_upper":"2005-03-31",
    "iso:country":"GB",
    "wof:name":"NP20 3PF",
    "wof:placetype":"postalcode"
},
  "geometry": {"coordinates":[-3.034196,51.576941],"type":"Point"}
}