{
  "type": "Feature",
  "properties": {
    "iso:country": "GB",
    "wof:name": "ML12 6DB",
    "wof:placetype": "postalcode"
  },
  "geometry": {"coordinates":[-3.527154,55.623303],"type":"Point"}
}
