{
  "type": "Feature",
  "properties": {
    "iso:country":"GB",
    "wof:name":"ML12 6DB",
    "wof:placetype":"postalcode"
},
  "geometry": {"coordinates":[-3.52715385331968,55.623303184161],"type":"Point"}
}