{
  "type": "Feature",
  "properties": {
    "iso:country":"GB",
    "wof:name":"BR2 7QP",
    "wof:placetype":"postalcode"
},
  "geometry": {"coordinates":[0.00562896266068,51.38292745056758],"type":"Point"}
}