{
  "type": "Feature",
  "properties": {
    "iso:country":"GB",
    "wof:name":"DN3 2LS",
    "wof:placetype":"postalcode"
},
  "geometry": {"coordinates":[-1.06262879132979,53.55307299989435],"type":"Point"}
}