{
  "type": "Feature",
  "properties": {
    "date:inception_lower":"1980-01-01",
    "date:inception_upper":"1980-01-31",
    "iso:country":"GB",
    "wof:name":"LL20 8RA",
    "wof:placetype":"postalcode"
},
  "geometry": {"coordinates":[-3.174595,52.969857],"type":"Point"}
}