{
  "type": "Feature",
  "properties": {
    "iso:country":"GB",
    "wof:name":"BH4 9DD",
    "wof:placetype":"postalcode"
},
  "geometry": {"coordinates":[-1.89800671728684,50.72224277007422],"type":"Point"}
}