{
  "type": "Feature",
  "properties": {
    "iso:country": "GB",
    "wof:name": "RH15 9XA",
    "wof:placetype": "postalcode"
  },
  "geometry": {"coordinates":[-0.155905,50.960079],"type":"Point"}
}
