{
  "type": "Feature",
  "properties": {
    "iso:country":"GB",
    "wof:name":"E6 5RS",
    "wof:placetype":"postalcode"
},
  "geometry": {"coordinates":[0.05214564665442,51.51284161407568],"type":"Point"}
}