{
  "type": "Feature",
  "properties": {
    "iso:country": "GB",
    "wof:name": "E6 5RS",
    "wof:placetype": "postalcode"
  },
  "geometry": {"coordinates":[0.052146,51.512842],"type":"Point"}
}
