{
  "type": "Feature",
  "properties": {
    "iso:country": "GB",
    "wof:name": "CH61 8RH",
    "wof:placetype": "postalcode"
  },
  "geometry": {"coordinates":[-3.09693,53.349532],"type":"Point"}
}
