{
  "type": "Feature",
  "properties": {
    "iso:country":"GB",
    "wof:name":"FY1 4EE",
    "wof:placetype":"postalcode"
},
  "geometry": {"coordinates":[-3.04052793692659,53.81285725172592],"type":"Point"}
}