{
  "type": "Feature",
  "properties": {
    "iso:country":"GB",
    "wof:name":"TN1 2RU",
    "wof:placetype":"postalcode"
},
  "geometry": {"coordinates":[0.26907552161988,51.13703581243669],"type":"Point"}
}