{
  "type": "Feature",
  "properties": {
    "iso:country": "GB",
    "wof:name": "LL51 9TX",
    "wof:placetype": "postalcode"
  },
  "geometry": {"coordinates":[-4.240353,52.97455],"type":"Point"}
}
