{
  "type": "Feature",
  "properties": {
    "iso:country":"GB",
    "wof:name":"LL29 8UA",
    "wof:placetype":"postalcode"
},
  "geometry": {"coordinates":[-3.66646244439436,53.28020505205079],"type":"Point"}
}