{
  "type": "Feature",
  "properties": {
    "iso:country":"GB",
    "wof:name":"N16 7QJ",
    "wof:placetype":"postalcode"
},
  "geometry": {"coordinates":[-0.07042953579522,51.55751107533207],"type":"Point"}
}