{
  "type": "Feature",
  "properties": {
    "date:inception_lower": "1980-01-01",
    "date:inception_upper": "1980-01-01",
    "iso:country": "GB",
    "wof:name": "GL15 6UP",
    "wof:placetype": "postalcode"
  },
  "geometry": {"coordinates":[-2.636532,51.710268],"type":"Point"}
}
