{
  "type": "Feature",
  "properties": {
    "iso:country": "GB",
    "wof:name": "GL15 6UP",
    "wof:placetype": "postalcode"
  },
  "geometry": {"coordinates":[-2.636517,51.71025],"type":"Point"}
}
