{
  "type": "Feature",
  "properties": {
    "iso:country": "GB",
    "wof:name": "GL15 6UP",
    "wof:placetype": "postalcode"
  },
  "geometry": {"coordinates":[-2.636544,51.710264],"type":"Point"}
}
