{
  "type": "Feature",
  "properties": {
    "iso:country":"GB",
    "wof:name":"GL15 6UP",
    "wof:placetype":"postalcode"
},
  "geometry": {"coordinates":[-2.63654377352471,51.71026416810135],"type":"Point"}
}