{
  "type": "Feature",
  "properties": {
    "iso:country":"GB",
    "wof:name":"SY3 9NG",
    "wof:placetype":"postalcode"
},
  "geometry": {"coordinates":[-2.75747877345111,52.69003245017627],"type":"Point"}
}