{
  "type": "Feature",
  "properties": {
    "date:inception_lower": "1994-05-01",
    "date:inception_upper": "1994-05-01",
    "iso:country": "GB",
    "wof:name": "NN29 7HJ",
    "wof:placetype": "postalcode"
  },
  "geometry": {"coordinates":[-0.642691,52.263185],"type":"Point"}
}
