{
  "type": "Feature",
  "properties": {
    "iso:country":"GB",
    "wof:name":"NN29 7HJ",
    "wof:placetype":"postalcode"
},
  "geometry": {"coordinates":[-0.64276522921967,52.26318928051109],"type":"Point"}
}