{
  "type": "Feature",
  "properties": {
    "iso:country":"GB",
    "wof:name":"N7 6JN",
    "wof:placetype":"postalcode"
},
  "geometry": {"coordinates":[-0.12175467710693,51.56003451528793],"type":"Point"}
}