{
  "type": "Feature",
  "properties": {
    "iso:country":"GB",
    "wof:name":"CW2 5BX",
    "wof:placetype":"postalcode"
},
  "geometry": {"coordinates":[-2.44688558612329,53.06519327617464],"type":"Point"}
}