{
  "type": "Feature",
  "properties": {
    "iso:country":"GB",
    "wof:name":"G61 3HZ",
    "wof:placetype":"postalcode"
},
  "geometry": {"coordinates":[-4.33789761015964,55.9294192292835],"type":"Point"}
}