{
  "type": "Feature",
  "properties": {
    "iso:country":"GB",
    "wof:name":"KA1 3TE",
    "wof:placetype":"postalcode"
},
  "geometry": {"coordinates":[-4.48253334835214,55.58923646718355],"type":"Point"}
}