{
  "type": "Feature",
  "properties": {
    "iso:country":"GB",
    "wof:name":"BD1 5JA",
    "wof:placetype":"postalcode"
},
  "geometry": {"coordinates":[-1.74033514895205,53.79618612957861],"type":"Point"}
}