{
  "type": "Feature",
  "properties": {
    "iso:country":"GB",
    "wof:name":"RG20 4AJ",
    "wof:placetype":"postalcode"
},
  "geometry": {"coordinates":[-1.28349740575923,51.36496236961553],"type":"Point"}
}