{
  "type": "Feature",
  "properties": {
    "iso:country": "GB",
    "wof:name": "RG20 4AJ",
    "wof:placetype": "postalcode"
  },
  "geometry": {"coordinates":[-1.283497,51.364962],"type":"Point"}
}
