{
  "type": "Feature",
  "properties": {
    "iso:country":"GB",
    "wof:name":"M29 8FS",
    "wof:placetype":"postalcode"
},
  "geometry": {"coordinates":[-2.47366861648776,53.51758628002108],"type":"Point"}
}