{
  "type": "Feature",
  "properties": {
    "iso:country": "GB",
    "wof:name": "M29 8FS",
    "wof:placetype": "postalcode"
  },
  "geometry": {"coordinates":[-2.473669,53.517586],"type":"Point"}
}
