{
  "type": "Feature",
  "properties": {
    "iso:country": "GB",
    "wof:name": "OL10 3PT",
    "wof:placetype": "postalcode"
  },
  "geometry": {"coordinates":[-2.248501,53.58683],"type":"Point"}
}
