{
  "type": "Feature",
  "properties": {
    "iso:country":"GB",
    "wof:name":"LS5 3JB",
    "wof:placetype":"postalcode"
},
  "geometry": {"coordinates":[-1.60050343959271,53.81671726061036],"type":"Point"}
}