{
  "type": "Feature",
  "properties": {
    "iso:country":"GB",
    "wof:name":"CV32 7TN",
    "wof:placetype":"postalcode"
},
  "geometry": {"coordinates":[-1.51059317648959,52.31307351006743],"type":"Point"}
}