{
  "type": "Feature",
  "properties": {
    "iso:country": "GB",
    "wof:name": "WF3 1ND",
    "wof:placetype": "postalcode"
  },
  "geometry": {"coordinates":[-1.586699,53.724082],"type":"Point"}
}
