{
  "type": "Feature",
  "properties": {
    "date:inception_lower": "1980-01-01",
    "date:inception_upper": "1980-01-01",
    "iso:country": "GB",
    "wof:name": "DY14 9JW",
    "wof:placetype": "postalcode"
  },
  "geometry": {"coordinates":[-2.457939,52.339818],"type":"Point"}
}
