{
  "type": "Feature",
  "properties": {
    "iso:country":"GB",
    "wof:name":"NG14 6AW",
    "wof:placetype":"postalcode"
},
  "geometry": {"coordinates":[-1.02385125660908,53.02907627589863],"type":"Point"}
}