{
  "type": "Feature",
  "properties": {
    "iso:country":"GB",
    "wof:name":"TF9 4HN",
    "wof:placetype":"postalcode"
},
  "geometry": {"coordinates":[-2.40298789068011,52.9586752081813],"type":"Point"}
}