{
  "type": "Feature",
  "properties": {
    "date:inception_lower":"1981-06-01",
    "date:inception_upper":"1981-06-30",
    "iso:country":"GB",
    "wof:name":"NR28 0LY",
    "wof:placetype":"postalcode"
},
  "geometry": {"coordinates":[1.3851,52.827426],"type":"Point"}
}