{
  "type": "Feature",
  "properties": {
    "iso:country": "GB",
    "wof:name": "NR28 0LY",
    "wof:placetype": "postalcode"
  },
  "geometry": {"coordinates":[1.3851,52.827426],"type":"Point"}
}
