{
  "type": "Feature",
  "properties": {
    "iso:country": "GB",
    "wof:name": "CV37 8GG",
    "wof:placetype": "postalcode"
  },
  "geometry": {"coordinates":[-1.788985,52.176332],"type":"Point"}
}
