{
  "type": "Feature",
  "properties": {
    "date:inception_lower": "2018-10-01",
    "date:inception_upper": "2018-10-01",
    "iso:country": "GB",
    "wof:name": "CV37 8GG",
    "wof:placetype": "postalcode"
  },
  "geometry": {"coordinates":[-1.788736,52.176341],"type":"Point"}
}
