{
  "type": "Feature",
  "properties": {
    "iso:country":"GB",
    "wof:name":"WF8 1HA",
    "wof:placetype":"postalcode"
},
  "geometry": {"coordinates":[-1.30957225758392,53.69309351865565],"type":"Point"}
}