{
  "type": "Feature",
  "properties": {
    "iso:country":"GB",
    "wof:name":"CV8 3BT",
    "wof:placetype":"postalcode"
},
  "geometry": {"coordinates":[-1.4773598570809,52.34867657977475],"type":"Point"}
}