{
  "type": "Feature",
  "properties": {
    "iso:country":"GB",
    "wof:name":"CV47 1FQ",
    "wof:placetype":"postalcode"
},
  "geometry": {"coordinates":[-1.38158921051779,52.25137917979117],"type":"Point"}
}