{
  "type": "Feature",
  "properties": {
    "iso:country": "GB",
    "wof:name": "LA6 2JG",
    "wof:placetype": "postalcode"
  },
  "geometry": {"coordinates":[-2.545709,54.180737],"type":"Point"}
}
