{
  "type": "Feature",
  "properties": {
    "iso:country": "GB",
    "wof:name": "ME9 9EX",
    "wof:placetype": "postalcode"
  },
  "geometry": {"coordinates":[0.824898,51.338754],"type":"Point"}
}
