{
  "type": "Feature",
  "properties": {
    "date:inception_lower": "1980-01-01",
    "date:inception_upper": "1980-01-01",
    "iso:country": "GB",
    "wof:name": "ME9 9EX",
    "wof:placetype": "postalcode"
  },
  "geometry": {"coordinates":[0.824898,51.338754],"type":"Point"}
}
