{
  "type": "Feature",
  "properties": {
    "date:inception_lower": "1980-01-01",
    "date:inception_upper": "1980-01-01",
    "iso:country": "GB",
    "wof:name": "NR17 1DA",
    "wof:placetype": "postalcode"
  },
  "geometry": {"coordinates":[0.879736,52.529256],"type":"Point"}
}
