{
  "type": "Feature",
  "properties": {
    "iso:country":"GB",
    "wof:name":"OX2 8PW",
    "wof:placetype":"postalcode"
},
  "geometry": {"coordinates":[-1.29060875877886,51.78310163934235],"type":"Point"}
}