{
  "type": "Feature",
  "properties": {
    "date:inception_lower": "1990-08-01",
    "date:inception_upper": "1990-08-01",
    "iso:country": "GB",
    "wof:name": "AB51 0FA",
    "wof:placetype": "postalcode"
  },
  "geometry": {"coordinates":[-2.315033,57.338401],"type":"Point"}
}
