{
  "type": "Feature",
  "properties": {
    "date:inception_lower": "1980-01-01",
    "date:inception_upper": "1980-01-01",
    "iso:country": "GB",
    "wof:name": "KW5 6DW",
    "wof:placetype": "postalcode"
  },
  "geometry": {"coordinates":[-3.384805,58.27573],"type":"Point"}
}
