{
  "type": "Feature",
  "properties": {
    "iso:country": "GB",
    "wof:name": "OX7 6QD",
    "wof:placetype": "postalcode"
  },
  "geometry": {"coordinates":[-1.61867,51.881823],"type":"Point"}
}
