{
  "type": "Feature",
  "properties": {
    "date:inception_lower": "1993-01-01",
    "date:inception_upper": "1993-01-01",
    "iso:country": "GB",
    "wof:name": "OX7 6QD",
    "wof:placetype": "postalcode"
  },
  "geometry": {"coordinates":[-1.61867,51.881823],"type":"Point"}
}
