{
  "type": "Feature",
  "properties": {
    "iso:country": "GB",
    "wof:name": "CT9 3XS",
    "wof:placetype": "postalcode"
  },
  "geometry": {"coordinates":[1.40934,51.37697],"type":"Point"}
}
