{
  "type": "Feature",
  "properties": {
    "iso:country": "GB",
    "wof:name": "RG20 6QR",
    "wof:placetype": "postalcode"
  },
  "geometry": {"coordinates":[-1.249258,51.51804],"type":"Point"}
}
