{
  "type": "Feature",
  "properties": {
    "iso:country": "GB",
    "wof:name": "B98 7US",
    "wof:placetype": "postalcode"
  },
  "geometry": {"coordinates":[-1.914532,52.282514],"type":"Point"}
}
