{
  "type": "Feature",
  "properties": {
    "iso:country":"GB",
    "wof:name":"B98 7US",
    "wof:placetype":"postalcode"
},
  "geometry": {"coordinates":[-1.91453986082275,52.28249973726442],"type":"Point"}
}