{
  "type": "Feature",
  "properties": {
    "iso:country":"GB",
    "wof:name":"DT7 3LT",
    "wof:placetype":"postalcode"
},
  "geometry": {"coordinates":[-2.94793565654877,50.73182199820627],"type":"Point"}
}