{
  "type": "Feature",
  "properties": {
    "date:inception_lower": "1980-01-01",
    "date:inception_upper": "1980-01-01",
    "iso:country": "GB",
    "wof:name": "GU25 4NG",
    "wof:placetype": "postalcode"
  },
  "geometry": {"coordinates":[-0.606607,51.398147],"type":"Point"}
}
