{
  "type": "Feature",
  "properties": {
    "date:inception_lower":"1980-01-01",
    "date:inception_upper":"1980-01-31",
    "iso:country":"GB",
    "wof:name":"B6 5BX",
    "wof:placetype":"postalcode"
},
  "geometry": {"coordinates":[-1.888901,52.499796],"type":"Point"}
}