{
  "type": "Feature",
  "properties": {
    "iso:country":"GB",
    "wof:name":"TN28 8BJ",
    "wof:placetype":"postalcode"
},
  "geometry": {"coordinates":[0.94500489924735,50.98884809340083],"type":"Point"}
}