{
  "type": "Feature",
  "properties": {
    "date:inception_lower": "2021-07-01",
    "date:inception_upper": "2021-07-01",
    "iso:country": "GB",
    "wof:name": "WF10 5YG",
    "wof:placetype": "postalcode"
  },
  "geometry": {"coordinates":[-1.370294,53.719197],"type":"Point"}
}
