{
  "type": "Feature",
  "properties": {
    "iso:country":"GB",
    "wof:name":"WN2 5NB",
    "wof:placetype":"postalcode"
},
  "geometry": {"coordinates":[-2.59198251087782,53.52184963442522],"type":"Point"}
}