{
  "type": "Feature",
  "properties": {
    "date:inception_lower": "1980-01-01",
    "date:inception_upper": "1980-01-01",
    "iso:country": "GB",
    "wof:name": "WN2 5NB",
    "wof:placetype": "postalcode"
  },
  "geometry": {"coordinates":[-2.591982,53.521865],"type":"Point"}
}
