{
  "type": "Feature",
  "properties": {
    "iso:country":"GB",
    "wof:name":"GU23 7DJ",
    "wof:placetype":"postalcode"
},
  "geometry": {"coordinates":[-0.5169889100033,51.28925556516991],"type":"Point"}
}