{
  "type": "Feature",
  "properties": {
    "date:inception_lower":"1980-01-01",
    "date:inception_upper":"1980-01-31",
    "iso:country":"GB",
    "wof:name":"SY4 5TX",
    "wof:placetype":"postalcode"
},
  "geometry": {"coordinates":[-2.747214,52.859119],"type":"Point"}
}