{
  "type": "Feature",
  "properties": {
    "iso:country":"GB",
    "wof:name":"SY4 5TX",
    "wof:placetype":"postalcode"
},
  "geometry": {"coordinates":[-2.74972956242573,52.85926813708005],"type":"Point"}
}