{
  "type": "Feature",
  "properties": {
    "iso:country": "GB",
    "wof:name": "SY4 5TX",
    "wof:placetype": "postalcode"
  },
  "geometry": {"coordinates":[-2.747214,52.859119],"type":"Point"}
}
