{
  "type": "Feature",
  "properties": {
    "date:inception_lower": "1980-01-01",
    "date:inception_upper": "1980-01-01",
    "iso:country": "GB",
    "wof:name": "TA3 7HP",
    "wof:placetype": "postalcode"
  },
  "geometry": {"coordinates":[-3.125151,50.98539],"type":"Point"}
}
