{
  "type": "Feature",
  "properties": {
    "iso:country":"GB",
    "wof:name":"TA3 7HP",
    "wof:placetype":"postalcode"
},
  "geometry": {"coordinates":[-3.12515063950763,50.98539010416405],"type":"Point"}
}