{
  "type": "Feature",
  "properties": {
    "iso:country": "GB",
    "wof:name": "RM11 1EB",
    "wof:placetype": "postalcode"
  },
  "geometry": {"coordinates":[0.195637,51.568924],"type":"Point"}
}
