{
  "type": "Feature",
  "properties": {
    "iso:country":"GB",
    "wof:name":"RM11 1EB",
    "wof:placetype":"postalcode"
},
  "geometry": {"coordinates":[0.19562504919173,51.56893970025661],"type":"Point"}
}