{
  "type": "Feature",
  "properties": {
    "iso:country":"GB",
    "wof:name":"NG34 8GD",
    "wof:placetype":"postalcode"
},
  "geometry": {"coordinates":[-0.45170836673646,52.98136339085033],"type":"Point"}
}