{
  "type": "Feature",
  "properties": {
    "date:inception_lower":"2006-01-01",
    "date:inception_upper":"2006-01-31",
    "iso:country":"GB",
    "wof:name":"NG34 8GD",
    "wof:placetype":"postalcode"
},
  "geometry": {"coordinates":[-0.451708,52.981363],"type":"Point"}
}