{
  "type": "Feature",
  "properties": {
    "date:inception_lower": "1983-07-01",
    "date:inception_upper": "1983-07-01",
    "iso:country": "GB",
    "wof:name": "TN28 8UL",
    "wof:placetype": "postalcode"
  },
  "geometry": {"coordinates":[0.965168,50.951136],"type":"Point"}
}
