{
  "type": "Feature",
  "properties": {
    "iso:country":"GB",
    "wof:name":"TN28 8UL",
    "wof:placetype":"postalcode"
},
  "geometry": {"coordinates":[0.96507476779519,50.95112868970488],"type":"Point"}
}