{
  "type": "Feature",
  "properties": {
    "iso:country":"GB",
    "wof:name":"BL1 7PL",
    "wof:placetype":"postalcode"
},
  "geometry": {"coordinates":[-2.47267266100115,53.60551477376775],"type":"Point"}
}