{
  "type": "Feature",
  "properties": {
    "iso:country": "GB",
    "wof:name": "BL1 7PL",
    "wof:placetype": "postalcode"
  },
  "geometry": {"coordinates":[-2.472671,53.605531],"type":"Point"}
}
