{
  "type": "Feature",
  "properties": {
    "iso:country":"GB",
    "wof:name":"SN6 8EL",
    "wof:placetype":"postalcode"
},
  "geometry": {"coordinates":[-1.65784176409547,51.59704258895027],"type":"Point"}
}