{
  "type": "Feature",
  "properties": {
    "date:inception_lower": "1980-01-01",
    "date:inception_upper": "1980-01-01",
    "iso:country": "GB",
    "wof:name": "DL5 5RE",
    "wof:placetype": "postalcode"
  },
  "geometry": {"coordinates":[-1.560503,54.62104],"type":"Point"}
}
