{
  "type": "Feature",
  "properties": {
    "iso:country":"GB",
    "wof:name":"DL5 5RE",
    "wof:placetype":"postalcode"
},
  "geometry": {"coordinates":[-1.56050277694403,54.62104011626463],"type":"Point"}
}