{
  "type": "Feature",
  "properties": {
    "date:inception_lower": "1980-01-01",
    "date:inception_upper": "1980-01-01",
    "iso:country": "GB",
    "wof:name": "CO5 9XB",
    "wof:placetype": "postalcode"
  },
  "geometry": {"coordinates":[0.797984,51.834273],"type":"Point"}
}
