{
  "type": "Feature",
  "properties": {
    "iso:country":"GB",
    "wof:name":"WD25 0DL",
    "wof:placetype":"postalcode"
},
  "geometry": {"coordinates":[-0.39077266568918,51.68894118197734],"type":"Point"}
}