{
  "type": "Feature",
  "properties": {
    "iso:country":"GB",
    "wof:name":"S10 3RE",
    "wof:placetype":"postalcode"
},
  "geometry": {"coordinates":[-1.53860411084673,53.36623272630604],"type":"Point"}
}