{
  "type": "Feature",
  "properties": {
    "iso:country": "GB",
    "wof:name": "S10 3RE",
    "wof:placetype": "postalcode"
  },
  "geometry": {"coordinates":[-1.538604,53.366233],"type":"Point"}
}
