{
  "type": "Feature",
  "properties": {
    "iso:country": "GB",
    "wof:name": "NP13 2QA",
    "wof:placetype": "postalcode"
  },
  "geometry": {"coordinates":[-3.124775,51.72331],"type":"Point"}
}
