{
  "type": "Feature",
  "properties": {
    "iso:country":"GB",
    "wof:name":"GL12 8HG",
    "wof:placetype":"postalcode"
},
  "geometry": {"coordinates":[-2.43179717176354,51.63305240107032],"type":"Point"}
}