{
  "type": "Feature",
  "properties": {
    "iso:country":"GB",
    "wof:name":"TA10 0EG",
    "wof:placetype":"postalcode"
},
  "geometry": {"coordinates":[-2.86452941316103,51.02418246186603],"type":"Point"}
}