{
  "type": "Feature",
  "properties": {
    "date:inception_lower": "1980-01-01",
    "date:inception_upper": "1980-01-01",
    "iso:country": "GB",
    "wof:name": "TA10 0EG",
    "wof:placetype": "postalcode"
  },
  "geometry": {"coordinates":[-2.864529,51.024182],"type":"Point"}
}
