{
  "type": "Feature",
  "properties": {
    "iso:country":"GB",
    "wof:name":"S60 3DS",
    "wof:placetype":"postalcode"
},
  "geometry": {"coordinates":[-1.34147108866074,53.40683641278186],"type":"Point"}
}