{
  "type": "Feature",
  "properties": {
    "iso:country":"GB",
    "wof:name":"M17 1HX",
    "wof:placetype":"postalcode"
},
  "geometry": {"coordinates":[-2.31888390269947,53.46088807046093],"type":"Point"}
}