{
  "type": "Feature",
  "properties": {
    "iso:country": "GB",
    "wof:name": "SE13 6UX",
    "wof:placetype": "postalcode"
  },
  "geometry": {"coordinates":[-0.005142,51.449163],"type":"Point"}
}
