{
  "type": "Feature",
  "properties": {
    "iso:country":"GB",
    "wof:name":"SE13 6UX",
    "wof:placetype":"postalcode"
},
  "geometry": {"coordinates":[-0.00514214884721,51.44916345759754],"type":"Point"}
}