{
  "type": "Feature",
  "properties": {
    "date:inception_lower": "2017-01-01",
    "date:inception_upper": "2017-01-01",
    "iso:country": "GB",
    "wof:name": "FY6 9FF",
    "wof:placetype": "postalcode"
  },
  "geometry": {"coordinates":[-2.953658,53.878165],"type":"Point"}
}
