{
  "type": "Feature",
  "properties": {
    "iso:country":"GB",
    "wof:name":"NE4 6TZ",
    "wof:placetype":"postalcode"
},
  "geometry": {"coordinates":[-1.63732152314192,54.97000725540852],"type":"Point"}
}