{
  "type": "Feature",
  "properties": {
    "iso:country": "GB",
    "wof:name": "ME19 6AL",
    "wof:placetype": "postalcode"
  },
  "geometry": {"coordinates":[0.43863,51.286523],"type":"Point"}
}
