{
  "type": "Feature",
  "properties": {
    "iso:country":"GB",
    "wof:name":"SW4 0RL",
    "wof:placetype":"postalcode"
},
  "geometry": {"coordinates":[-0.1453936347824,51.46225736376149],"type":"Point"}
}