{
  "type": "Feature",
  "properties": {
    "iso:country": "GB",
    "wof:name": "S12 3BR",
    "wof:placetype": "postalcode"
  },
  "geometry": {"coordinates":[-1.392439,53.342109],"type":"Point"}
}
