{
  "type": "Feature",
  "properties": {
    "iso:country":"GB",
    "wof:name":"S12 3BR",
    "wof:placetype":"postalcode"
},
  "geometry": {"coordinates":[-1.39243869956018,53.34210890061897],"type":"Point"}
}