{
  "type": "Feature",
  "properties": {
    "date:inception_lower": "2009-08-01",
    "date:inception_upper": "2009-08-01",
    "iso:country": "GB",
    "wof:name": "S12 3BR",
    "wof:placetype": "postalcode"
  },
  "geometry": {"coordinates":[-1.392423,53.342164],"type":"Point"}
}
