{
  "type": "Feature",
  "properties": {
    "iso:country":"GB",
    "wof:name":"AL4 0QN",
    "wof:placetype":"postalcode"
},
  "geometry": {"coordinates":[-0.24581786711692,51.74144806423301],"type":"Point"}
}