{
  "type": "Feature",
  "properties": {
    "iso:country": "GB",
    "wof:name": "AL4 0QN",
    "wof:placetype": "postalcode"
  },
  "geometry": {"coordinates":[-0.245818,51.741448],"type":"Point"}
}
