{
  "type": "Feature",
  "properties": {
    "date:inception_lower":"1980-01-01",
    "date:inception_upper":"1980-01-31",
    "iso:country":"GB",
    "wof:name":"AL4 0QN",
    "wof:placetype":"postalcode"
},
  "geometry": {"coordinates":[-0.245818,51.741448],"type":"Point"}
}