{
  "type": "Feature",
  "properties": {
    "date:inception_lower":"1990-06-01",
    "date:inception_upper":"1990-06-30",
    "iso:country":"GB",
    "wof:name":"DG11 2BX",
    "wof:placetype":"postalcode"
},
  "geometry": {"coordinates":[-3.355561,55.120432],"type":"Point"}
}