{
  "type": "Feature",
  "properties": {
    "iso:country": "GB",
    "wof:name": "BL8 3DX",
    "wof:placetype": "postalcode"
  },
  "geometry": {"coordinates":[-2.332097,53.608134],"type":"Point"}
}
