{
  "type": "Feature",
  "properties": {
    "iso:country":"GB",
    "wof:name":"BL8 3DX",
    "wof:placetype":"postalcode"
},
  "geometry": {"coordinates":[-2.33190211072157,53.60807355347046],"type":"Point"}
}