{
  "type": "Feature",
  "properties": {
    "iso:country":"GB",
    "wof:name":"BR3 4QX",
    "wof:placetype":"postalcode"
},
  "geometry": {"coordinates":[-0.04575289185424,51.40575615389736],"type":"Point"}
}