{
  "type": "Feature",
  "properties": {
    "date:inception_lower":"2015-06-01",
    "date:inception_upper":"2015-06-30",
    "iso:country":"GB",
    "wof:name":"E14 6TJ",
    "wof:placetype":"postalcode"
},
  "geometry": {"coordinates":[-0.023262,51.515461],"type":"Point"}
}