{
  "type": "Feature",
  "properties": {
    "iso:country": "GB",
    "wof:name": "E14 6TJ",
    "wof:placetype": "postalcode"
  },
  "geometry": {"coordinates":[-0.023262,51.515461],"type":"Point"}
}
