{
  "type": "Feature",
  "properties": {
    "iso:country":"GB",
    "wof:name":"PR3 2TQ",
    "wof:placetype":"postalcode"
},
  "geometry": {"coordinates":[-2.55972426829146,53.87934114128694],"type":"Point"}
}