{
  "type": "Feature",
  "properties": {
    "date:inception_lower": "1980-01-01",
    "date:inception_upper": "1980-01-01",
    "iso:country": "GB",
    "wof:name": "PR3 2TQ",
    "wof:placetype": "postalcode"
  },
  "geometry": {"coordinates":[-2.559724,53.879341],"type":"Point"}
}
