{
  "type": "Feature",
  "properties": {
    "iso:country":"GB",
    "wof:name":"SO31 9GD",
    "wof:placetype":"postalcode"
},
  "geometry": {"coordinates":[-1.29464553623764,50.85134083784934],"type":"Point"}
}