{
  "type": "Feature",
  "properties": {
    "date:inception_lower": "1990-08-01",
    "date:inception_upper": "1990-08-01",
    "iso:country": "GB",
    "wof:name": "AB56 1TB",
    "wof:placetype": "postalcode"
  },
  "geometry": {"coordinates":[-2.936044,57.684527],"type":"Point"}
}
