{
  "type": "Feature",
  "properties": {
    "iso:country":"GB",
    "wof:name":"AB56 1TB",
    "wof:placetype":"postalcode"
},
  "geometry": {"coordinates":[-2.93604431761058,57.68452676199189],"type":"Point"}
}