{
  "type": "Feature",
  "properties": {
    "iso:country":"GB",
    "wof:name":"GU6 7HR",
    "wof:placetype":"postalcode"
},
  "geometry": {"coordinates":[-0.47174686813055,51.14121335216502],"type":"Point"}
}