{
  "type": "Feature",
  "properties": {
    "iso:country": "GB",
    "wof:name": "IP8 4ED",
    "wof:placetype": "postalcode"
  },
  "geometry": {"coordinates":[1.09633,52.077165],"type":"Point"}
}
