{
  "type": "Feature",
  "properties": {
    "date:inception_lower": "1980-01-01",
    "date:inception_upper": "1980-01-01",
    "iso:country": "GB",
    "wof:name": "IP8 4ED",
    "wof:placetype": "postalcode"
  },
  "geometry": {"coordinates":[1.096344,52.077162],"type":"Point"}
}
