{
  "type": "Feature",
  "properties": {
    "iso:country": "GB",
    "wof:name": "SE2 9PG",
    "wof:placetype": "postalcode"
  },
  "geometry": {"coordinates":[0.109953,51.494118],"type":"Point"}
}
