{
  "type": "Feature",
  "properties": {
    "iso:country":"GB",
    "wof:name":"KT11 3EE",
    "wof:placetype":"postalcode"
},
  "geometry": {"coordinates":[-0.41085179425567,51.32823060054455],"type":"Point"}
}