{
  "type": "Feature",
  "properties": {
    "iso:country": "GB",
    "wof:name": "DL3 0ZS",
    "wof:placetype": "postalcode"
  },
  "geometry": {"coordinates":[-1.555754,54.553621],"type":"Point"}
}
