{
  "type": "Feature",
  "properties": {
    "iso:country":"GB",
    "wof:name":"SE2 9PE",
    "wof:placetype":"postalcode"
},
  "geometry": {"coordinates":[0.11068436062726,51.49404182821987],"type":"Point"}
}