{
  "type": "Feature",
  "properties": {
    "iso:country": "GB",
    "wof:name": "LS3 1LT",
    "wof:placetype": "postalcode"
  },
  "geometry": {"coordinates":[-1.565692,53.800811],"type":"Point"}
}
