{
  "type": "Feature",
  "properties": {
    "iso:country":"GB",
    "wof:name":"HA1 4SA",
    "wof:placetype":"postalcode"
},
  "geometry": {"coordinates":[-0.34769607390504,51.59013141886246],"type":"Point"}
}