{
  "type": "Feature",
  "properties": {
    "date:inception_lower":"1980-01-01",
    "date:inception_upper":"1980-01-31",
    "iso:country":"GB",
    "wof:name":"HA1 4SA",
    "wof:placetype":"postalcode"
},
  "geometry": {"coordinates":[-0.347696,51.590131],"type":"Point"}
}