{
  "type": "Feature",
  "properties": {
    "date:inception_lower":"1980-01-01",
    "date:inception_upper":"1980-01-31",
    "iso:country":"GB",
    "wof:name":"TD5 7SA",
    "wof:placetype":"postalcode"
},
  "geometry": {"coordinates":[-2.53167,55.633177],"type":"Point"}
}