{
  "type": "Feature",
  "properties": {
    "iso:country": "GB",
    "wof:name": "TD5 7SA",
    "wof:placetype": "postalcode"
  },
  "geometry": {"coordinates":[-2.53167,55.633177],"type":"Point"}
}
