{
  "type": "Feature",
  "properties": {
    "date:inception_lower": "2022-02-01",
    "date:inception_upper": "2022-02-01",
    "iso:country": "GB",
    "wof:name": "DN21 1FL",
    "wof:placetype": "postalcode"
  },
  "geometry": {"coordinates":[-0.763122,53.386151],"type":"Point"}
}
