{
  "type": "Feature",
  "properties": {
    "iso:country":"GB",
    "wof:name":"TQ12 3EX",
    "wof:placetype":"postalcode"
},
  "geometry": {"coordinates":[-3.58396983491661,50.54977540884634],"type":"Point"}
}