{
  "type": "Feature",
  "properties": {
    "iso:country":"GB",
    "wof:name":"NE24 5RY",
    "wof:placetype":"postalcode"
},
  "geometry": {"coordinates":[-1.52921092751335,55.11816984682203],"type":"Point"}
}