{
  "type": "Feature",
  "properties": {
    "iso:country":"GB",
    "wof:name":"WN6 0SH",
    "wof:placetype":"postalcode"
},
  "geometry": {"coordinates":[-2.6913499106132,53.59124677323546],"type":"Point"}
}