{
  "type": "Feature",
  "properties": {
    "iso:country": "GB",
    "wof:name": "WN6 0SH",
    "wof:placetype": "postalcode"
  },
  "geometry": {"coordinates":[-2.69135,53.591247],"type":"Point"}
}
