{
  "type": "Feature",
  "properties": {
    "iso:country": "GB",
    "wof:name": "SA11 1PD",
    "wof:placetype": "postalcode"
  },
  "geometry": {"coordinates":[-3.806509,51.657245],"type":"Point"}
}
