{
  "type": "Feature",
  "properties": {
    "iso:country": "GB",
    "wof:name": "DN15 7NH",
    "wof:placetype": "postalcode"
  },
  "geometry": {"coordinates":[-0.655268,53.594357],"type":"Point"}
}
