{
  "type": "Feature",
  "properties": {
    "iso:country": "GB",
    "wof:name": "TA10 9FL",
    "wof:placetype": "postalcode"
  },
  "geometry": {"coordinates":[-2.819669,51.043941],"type":"Point"}
}
