{
  "type": "Feature",
  "properties": {
    "iso:country":"GB",
    "wof:name":"LS11 9RU",
    "wof:placetype":"postalcode"
},
  "geometry": {"coordinates":[-1.56664321100826,53.789177326363],"type":"Point"}
}