{
  "type": "Feature",
  "properties": {
    "iso:country":"GB",
    "wof:name":"M46 0PY",
    "wof:placetype":"postalcode"
},
  "geometry": {"coordinates":[-2.51470293533053,53.52111084950273],"type":"Point"}
}