{
  "type": "Feature",
  "properties": {
    "iso:country":"GB",
    "wof:name":"ST4 8HA",
    "wof:placetype":"postalcode"
},
  "geometry": {"coordinates":[-2.19544268998591,52.97486632250268],"type":"Point"}
}