{
  "type": "Feature",
  "properties": {
    "iso:country":"GB",
    "wof:name":"CV37 0HZ",
    "wof:placetype":"postalcode"
},
  "geometry": {"coordinates":[-1.71087753556393,52.20070664082213],"type":"Point"}
}