{
  "type": "Feature",
  "properties": {
    "iso:country":"GB",
    "wof:name":"M7 2XF",
    "wof:placetype":"postalcode"
},
  "geometry": {"coordinates":[-2.25695068168489,53.49807889077372],"type":"Point"}
}