{
  "type": "Feature",
  "properties": {
    "iso:country":"GB",
    "wof:name":"PL27 7SZ",
    "wof:placetype":"postalcode"
},
  "geometry": {"coordinates":[-4.96806189227962,50.4865342362002],"type":"Point"}
}