{
  "type": "Feature",
  "properties": {
    "date:inception_lower": "1980-01-01",
    "date:inception_upper": "1980-01-01",
    "iso:country": "GB",
    "wof:name": "PL27 7SZ",
    "wof:placetype": "postalcode"
  },
  "geometry": {"coordinates":[-4.96887,50.486137],"type":"Point"}
}
