{
  "type": "Feature",
  "properties": {
    "date:inception_lower":"1980-01-01",
    "date:inception_upper":"1980-01-31",
    "iso:country":"GB",
    "wof:name":"LU2 0LY",
    "wof:placetype":"postalcode"
},
  "geometry": {"coordinates":[-0.400214,51.886234],"type":"Point"}
}