{
  "type": "Feature",
  "properties": {
    "iso:country":"GB",
    "wof:name":"SA48 7HE",
    "wof:placetype":"postalcode"
},
  "geometry": {"coordinates":[-4.07815532647442,52.11289379419732],"type":"Point"}
}