{
  "type": "Feature",
  "properties": {
    "iso:country":"GB",
    "wof:name":"ST9 0HL",
    "wof:placetype":"postalcode"
},
  "geometry": {"coordinates":[-2.07945799033669,53.02729064459684],"type":"Point"}
}