{
  "type": "Feature",
  "properties": {
    "iso:country":"GB",
    "wof:name":"UB10 8EJ",
    "wof:placetype":"postalcode"
},
  "geometry": {"coordinates":[-0.46443172529201,51.5603792502636],"type":"Point"}
}