{
  "type": "Feature",
  "properties": {
    "iso:country":"GB",
    "wof:name":"DA15 8ER",
    "wof:placetype":"postalcode"
},
  "geometry": {"coordinates":[0.09218051629893,51.44072209756893],"type":"Point"}
}