{
  "type": "Feature",
  "properties": {
    "date:inception_lower": "1980-01-01",
    "date:inception_upper": "1980-01-01",
    "iso:country": "GB",
    "wof:name": "DA15 8ER",
    "wof:placetype": "postalcode"
  },
  "geometry": {"coordinates":[0.092181,51.440722],"type":"Point"}
}
