{
  "type": "Feature",
  "properties": {
    "iso:country":"GB",
    "wof:name":"SA18 2TT",
    "wof:placetype":"postalcode"
},
  "geometry": {"coordinates":[-3.98357545064685,51.84372884847937],"type":"Point"}
}