{
  "type": "Feature",
  "properties": {
    "iso:country": "GB",
    "wof:name": "IP6 8DL",
    "wof:placetype": "postalcode"
  },
  "geometry": {"coordinates":[1.048991,52.15606],"type":"Point"}
}
