{
  "type": "Feature",
  "properties": {
    "iso:country":"GB",
    "wof:name":"G71 8HS",
    "wof:placetype":"postalcode"
},
  "geometry": {"coordinates":[-4.06942936847599,55.8095016916613],"type":"Point"}
}