{
  "type": "Feature",
  "properties": {
    "iso:country":"GB",
    "wof:name":"TS7 9HS",
    "wof:placetype":"postalcode"
},
  "geometry": {"coordinates":[-1.17320195831817,54.53943522900226],"type":"Point"}
}