{
  "type": "Feature",
  "properties": {
    "date:inception_lower": "1980-01-01",
    "date:inception_upper": "1980-01-01",
    "iso:country": "GB",
    "wof:name": "IV9 8RD",
    "wof:placetype": "postalcode"
  },
  "geometry": {"coordinates":[-4.167631,57.571634],"type":"Point"}
}
