{
  "type": "Feature",
  "properties": {
    "date:inception_lower": "2008-11-01",
    "date:inception_upper": "2008-11-01",
    "iso:country": "GB",
    "wof:name": "EH19 3FS",
    "wof:placetype": "postalcode"
  },
  "geometry": {"coordinates":[-3.100581,55.866119],"type":"Point"}
}
