{
  "type": "Feature",
  "properties": {
    "iso:country":"GB",
    "wof:name":"EH19 3FS",
    "wof:placetype":"postalcode"
},
  "geometry": {"coordinates":[-3.10058119213685,55.86611873575691],"type":"Point"}
}