{
  "type": "Feature",
  "properties": {
    "iso:country": "GB",
    "wof:name": "DA1 1JE",
    "wof:placetype": "postalcode"
  },
  "geometry": {"coordinates":[0.215732,51.438667],"type":"Point"}
}
