{
  "type": "Feature",
  "properties": {
    "iso:country":"GB",
    "wof:name":"BS3 2BA",
    "wof:placetype":"postalcode"
},
  "geometry": {"coordinates":[-2.61347826471899,51.43845800847218],"type":"Point"}
}