{
  "type": "Feature",
  "properties": {
    "date:inception_lower": "1980-01-01",
    "date:inception_upper": "1980-01-01",
    "iso:country": "GB",
    "wof:name": "BS3 2BA",
    "wof:placetype": "postalcode"
  },
  "geometry": {"coordinates":[-2.613478,51.438458],"type":"Point"}
}
