{
  "type": "Feature",
  "properties": {
    "iso:country":"GB",
    "wof:name":"S41 0ND",
    "wof:placetype":"postalcode"
},
  "geometry": {"coordinates":[-1.40252188505201,53.21587502583728],"type":"Point"}
}