{
  "type": "Feature",
  "properties": {
    "iso:country": "GB",
    "wof:name": "S41 0ND",
    "wof:placetype": "postalcode"
  },
  "geometry": {"coordinates":[-1.402536,53.215886],"type":"Point"}
}
