{
  "type": "Feature",
  "properties": {
    "date:inception_lower": "1980-01-01",
    "date:inception_upper": "1980-01-01",
    "iso:country": "GB",
    "wof:name": "NE38 8AG",
    "wof:placetype": "postalcode"
  },
  "geometry": {"coordinates":[-1.52125,54.884029],"type":"Point"}
}
