{
  "type": "Feature",
  "properties": {
    "iso:country":"GB",
    "wof:name":"SK5 6BU",
    "wof:placetype":"postalcode"
},
  "geometry": {"coordinates":[-2.16487837940706,53.43663460145356],"type":"Point"}
}