{
  "type": "Feature",
  "properties": {
    "iso:country":"GB",
    "wof:name":"SY15 6HB",
    "wof:placetype":"postalcode"
},
  "geometry": {"coordinates":[-3.1596299749892,52.57448293860053],"type":"Point"}
}