{
  "type": "Feature",
  "properties": {
    "date:inception_lower": "1980-01-01",
    "date:inception_upper": "1980-01-01",
    "iso:country": "GB",
    "wof:name": "SY15 6HB",
    "wof:placetype": "postalcode"
  },
  "geometry": {"coordinates":[-3.15963,52.574483],"type":"Point"}
}
