{
  "type": "Feature",
  "properties": {
    "date:inception_lower": "2001-06-01",
    "date:inception_upper": "2001-06-01",
    "iso:country": "GB",
    "wof:name": "PR26 9BA",
    "wof:placetype": "postalcode"
  },
  "geometry": {"coordinates":[-2.78905,53.690746],"type":"Point"}
}
