{
  "type": "Feature",
  "properties": {
    "iso:country":"GB",
    "wof:name":"PR26 9BA",
    "wof:placetype":"postalcode"
},
  "geometry": {"coordinates":[-2.78905023043582,53.69074648361565],"type":"Point"}
}