{
  "type": "Feature",
  "properties": {
    "iso:country":"GB",
    "wof:name":"LL63 5LZ",
    "wof:placetype":"postalcode"
},
  "geometry": {"coordinates":[-4.46374849943509,53.191458303678],"type":"Point"}
}