{
  "type": "Feature",
  "properties": {
    "iso:country": "GB",
    "wof:name": "LL63 5LZ",
    "wof:placetype": "postalcode"
  },
  "geometry": {"coordinates":[-4.463748,53.191458],"type":"Point"}
}
