{
  "type": "Feature",
  "properties": {
    "iso:country": "GB",
    "wof:name": "WA16 9LW",
    "wof:placetype": "postalcode"
  },
  "geometry": {"coordinates":[-2.384816,53.236973],"type":"Point"}
}
