{
  "type": "Feature",
  "properties": {
    "date:inception_lower": "1993-02-01",
    "date:inception_upper": "1993-02-01",
    "iso:country": "GB",
    "wof:name": "DD2 3FF",
    "wof:placetype": "postalcode"
  },
  "geometry": {"coordinates":[-3.005396,56.471944],"type":"Point"}
}
