{
  "type": "Feature",
  "properties": {
    "iso:country":"GB",
    "wof:name":"DD2 3FF",
    "wof:placetype":"postalcode"
},
  "geometry": {"coordinates":[-3.00539586486745,56.47194414558636],"type":"Point"}
}