{
  "type": "Feature",
  "properties": {
    "iso:country": "GB",
    "wof:name": "DD2 3FF",
    "wof:placetype": "postalcode"
  },
  "geometry": {"coordinates":[-3.005396,56.471944],"type":"Point"}
}
