{
  "type": "Feature",
  "properties": {
    "date:inception_lower": "2024-10-01",
    "date:inception_upper": "2024-10-01",
    "iso:country": "GB",
    "wof:name": "NE28 8BL",
    "wof:placetype": "postalcode"
  },
  "geometry": {"coordinates":[-1.55111,55.002185],"type":"Point"}
}
