{
  "type": "Feature",
  "properties": {
    "iso:country":"GB",
    "wof:name":"W3 6ND",
    "wof:placetype":"postalcode"
},
  "geometry": {"coordinates":[-0.26583734637541,51.50646394902163],"type":"Point"}
}