{
  "type": "Feature",
  "properties": {
    "iso:country":"GB",
    "wof:name":"NW1 0AY",
    "wof:placetype":"postalcode"
},
  "geometry": {"coordinates":[-0.14029717420214,51.53942241383568],"type":"Point"}
}