{
  "type": "Feature",
  "properties": {
    "iso:country":"GB",
    "wof:name":"N17 8BH",
    "wof:placetype":"postalcode"
},
  "geometry": {"coordinates":[-0.07025192953709,51.60327096976572],"type":"Point"}
}