{
  "type": "Feature",
  "properties": {
    "iso:country":"GB",
    "wof:name":"TD8 6TX",
    "wof:placetype":"postalcode"
},
  "geometry": {"coordinates":[-2.57256536322992,55.51950676199017],"type":"Point"}
}