{
  "type": "Feature",
  "properties": {
    "date:inception_lower": "1980-01-01",
    "date:inception_upper": "1980-01-01",
    "iso:country": "GB",
    "wof:name": "TD8 6TX",
    "wof:placetype": "postalcode"
  },
  "geometry": {"coordinates":[-2.572823,55.519452],"type":"Point"}
}
