{
  "type": "Feature",
  "properties": {
    "iso:country":"GB",
    "wof:name":"SN1 2DN",
    "wof:placetype":"postalcode"
},
  "geometry": {"coordinates":[-1.78108294569131,51.56530063201649],"type":"Point"}
}