{
  "type": "Feature",
  "properties": {
    "iso:country":"GB",
    "wof:name":"BH10 5NP",
    "wof:placetype":"postalcode"
},
  "geometry": {"coordinates":[-1.89599945110879,50.76517185242801],"type":"Point"}
}