{
  "type": "Feature",
  "properties": {
    "iso:country":"GB",
    "wof:name":"WA14 3BU",
    "wof:placetype":"postalcode"
},
  "geometry": {"coordinates":[-2.36385320385893,53.36884221155538],"type":"Point"}
}