{
  "type": "Feature",
  "properties": {
    "iso:country":"GB",
    "wof:name":"M16 8PX",
    "wof:placetype":"postalcode"
},
  "geometry": {"coordinates":[-2.24889569705298,53.44831780069484],"type":"Point"}
}