{
  "type": "Feature",
  "properties": {
    "iso:country":"GB",
    "wof:name":"PO38 2DP",
    "wof:placetype":"postalcode"
},
  "geometry": {"coordinates":[-1.28158738076079,50.58832041766902],"type":"Point"}
}