{
  "type": "Feature",
  "properties": {
    "date:inception_lower": "2022-10-01",
    "date:inception_upper": "2022-10-01",
    "iso:country": "GB",
    "wof:name": "G21 1AQ",
    "wof:placetype": "postalcode"
  },
  "geometry": {"coordinates":[-4.228644,55.88378],"type":"Point"}
}
