{
  "type": "Feature",
  "properties": {
    "iso:country": "GB",
    "wof:name": "CV2 1AW",
    "wof:placetype": "postalcode"
  },
  "geometry": {"coordinates":[-1.462475,52.430852],"type":"Point"}
}
