{
  "type": "Feature",
  "properties": {
    "date:inception_lower": "1980-01-01",
    "date:inception_upper": "1980-01-01",
    "iso:country": "GB",
    "wof:name": "CV2 1AW",
    "wof:placetype": "postalcode"
  },
  "geometry": {"coordinates":[-1.462475,52.430852],"type":"Point"}
}
