{
  "type": "Feature",
  "properties": {
    "date:inception_lower": "2012-12-01",
    "date:inception_upper": "2012-12-01",
    "iso:country": "GB",
    "wof:name": "BS34 5AS",
    "wof:placetype": "postalcode"
  },
  "geometry": {"coordinates":[-2.576646,51.526178],"type":"Point"}
}
