{
  "type": "Feature",
  "properties": {
    "iso:country":"GB",
    "wof:name":"BA1 4BP",
    "wof:placetype":"postalcode"
},
  "geometry": {"coordinates":[-2.38897439787994,51.39489173830621],"type":"Point"}
}