{
  "type": "Feature",
  "properties": {
    "iso:country":"GB",
    "wof:name":"WF9 5HU",
    "wof:placetype":"postalcode"
},
  "geometry": {"coordinates":[-1.35238971933745,53.61872933947486],"type":"Point"}
}