{
  "type": "Feature",
  "properties": {
    "iso:country":"GB",
    "wof:name":"YO18 7HX",
    "wof:placetype":"postalcode"
},
  "geometry": {"coordinates":[-0.76284765392002,54.24192829088386],"type":"Point"}
}