{
  "type": "Feature",
  "properties": {
    "iso:country":"GB",
    "wof:name":"FK14 7NT",
    "wof:placetype":"postalcode"
},
  "geometry": {"coordinates":[-3.63945326288141,56.15640660378391],"type":"Point"}
}