{
  "type": "Feature",
  "properties": {
    "date:inception_lower": "1980-01-01",
    "date:inception_upper": "1980-01-01",
    "iso:country": "GB",
    "wof:name": "FK14 7NT",
    "wof:placetype": "postalcode"
  },
  "geometry": {"coordinates":[-3.639453,56.156407],"type":"Point"}
}
