{
  "type": "Feature",
  "properties": {
    "iso:country": "GB",
    "wof:name": "LS28 8FB",
    "wof:placetype": "postalcode"
  },
  "geometry": {"coordinates":[-1.667508,53.790749],"type":"Point"}
}
