{
  "type": "Feature",
  "properties": {
    "iso:country":"GB",
    "wof:name":"ME9 0TF",
    "wof:placetype":"postalcode"
},
  "geometry": {"coordinates":[0.71100679816763,51.28336356940316],"type":"Point"}
}