{
  "type": "Feature",
  "properties": {
    "iso:country":"GB",
    "wof:name":"PL2 2RF",
    "wof:placetype":"postalcode"
},
  "geometry": {"coordinates":[-4.15875700013311,50.39470124629291],"type":"Point"}
}