{
  "type": "Feature",
  "properties": {
    "iso:country":"GB",
    "wof:name":"BR3 3HZ",
    "wof:placetype":"postalcode"
},
  "geometry": {"coordinates":[-0.03136965758578,51.39381577869331],"type":"Point"}
}