{
  "type": "Feature",
  "properties": {
    "iso:country":"GB",
    "wof:name":"SW19 6PH",
    "wof:placetype":"postalcode"
},
  "geometry": {"coordinates":[-0.21129236714342,51.44178017345939],"type":"Point"}
}