{
  "type": "Feature",
  "properties": {
    "date:inception_lower": "2001-06-01",
    "date:inception_upper": "2001-06-01",
    "iso:country": "GB",
    "wof:name": "GU51 5SS",
    "wof:placetype": "postalcode"
  },
  "geometry": {"coordinates":[-0.866581,51.264638],"type":"Point"}
}
