{
  "type": "Feature",
  "properties": {
    "iso:country": "GB",
    "wof:name": "W3 8HP",
    "wof:placetype": "postalcode"
  },
  "geometry": {"coordinates":[-0.281529,51.502262],"type":"Point"}
}
