{
  "type": "Feature",
  "properties": {
    "iso:country":"GB",
    "wof:name":"CV7 7HR",
    "wof:placetype":"postalcode"
},
  "geometry": {"coordinates":[-1.6520564366424,52.46109379827748],"type":"Point"}
}