{
  "type": "Feature",
  "properties": {
    "iso:country":"GB",
    "wof:name":"DT6 5ER",
    "wof:placetype":"postalcode"
},
  "geometry": {"coordinates":[-2.76484683195478,50.73940813008205],"type":"Point"}
}