{
  "type": "Feature",
  "properties": {
    "date:inception_lower": "1980-01-01",
    "date:inception_upper": "1980-01-01",
    "iso:country": "GB",
    "wof:name": "PA23 7HU",
    "wof:placetype": "postalcode"
  },
  "geometry": {"coordinates":[-4.928484,55.945437],"type":"Point"}
}
