{
  "type": "Feature",
  "properties": {
    "iso:country":"GB",
    "wof:name":"PA23 7HU",
    "wof:placetype":"postalcode"
},
  "geometry": {"coordinates":[-4.92850541495731,55.94544275978011],"type":"Point"}
}