{
  "type": "Feature",
  "properties": {
    "date:inception_lower": "1993-01-01",
    "date:inception_upper": "1993-01-01",
    "iso:country": "GB",
    "wof:name": "MK40 4QE",
    "wof:placetype": "postalcode"
  },
  "geometry": {"coordinates":[-0.50848,52.140273],"type":"Point"}
}
