{
  "type": "Feature",
  "properties": {
    "iso:country": "GB",
    "wof:name": "OX44 7HZ",
    "wof:placetype": "postalcode"
  },
  "geometry": {"coordinates":[-1.078843,51.720466],"type":"Point"}
}
