{
  "type": "Feature",
  "properties": {
    "date:inception_lower": "1990-02-01",
    "date:inception_upper": "1990-02-01",
    "iso:country": "GB",
    "wof:name": "TQ12 6UL",
    "wof:placetype": "postalcode"
  },
  "geometry": {"coordinates":[-3.674111,50.560871],"type":"Point"}
}
