{
  "type": "Feature",
  "properties": {
    "iso:country":"GB",
    "wof:name":"TQ12 6UL",
    "wof:placetype":"postalcode"
},
  "geometry": {"coordinates":[-3.67411061695107,50.56087126533787],"type":"Point"}
}