{
  "type": "Feature",
  "properties": {
    "iso:country": "GB",
    "wof:name": "TQ12 6UL",
    "wof:placetype": "postalcode"
  },
  "geometry": {"coordinates":[-3.674111,50.560871],"type":"Point"}
}
