{
  "type": "Feature",
  "properties": {
    "date:inception_lower": "1997-12-01",
    "date:inception_upper": "1997-12-01",
    "iso:country": "GB",
    "wof:name": "BS39 6ET",
    "wof:placetype": "postalcode"
  },
  "geometry": {"coordinates":[-2.533816,51.31099],"type":"Point"}
}
