{
  "type": "Feature",
  "properties": {
    "iso:country":"GB",
    "wof:name":"BS39 6ET",
    "wof:placetype":"postalcode"
},
  "geometry": {"coordinates":[-2.53372725415151,51.31090487371089],"type":"Point"}
}