{
  "type": "Feature",
  "properties": {
    "iso:country": "GB",
    "wof:name": "BS39 6ET",
    "wof:placetype": "postalcode"
  },
  "geometry": {"coordinates":[-2.533729,51.310901],"type":"Point"}
}
