{
  "type": "Feature",
  "properties": {
    "date:inception_lower": "1980-01-01",
    "date:inception_upper": "1980-01-01",
    "iso:country": "GB",
    "wof:name": "HA4 7BD",
    "wof:placetype": "postalcode"
  },
  "geometry": {"coordinates":[-0.425294,51.575203],"type":"Point"}
}
