{
  "type": "Feature",
  "properties": {
    "iso:country": "GB",
    "wof:name": "HA4 7BD",
    "wof:placetype": "postalcode"
  },
  "geometry": {"coordinates":[-0.425294,51.575203],"type":"Point"}
}
