{
  "type": "Feature",
  "properties": {
    "iso:country":"GB",
    "wof:name":"ST4 4FB",
    "wof:placetype":"postalcode"
},
  "geometry": {"coordinates":[-2.1900663631851,52.98833189237011],"type":"Point"}
}