{
  "type": "Feature",
  "properties": {
    "iso:country": "GB",
    "wof:name": "ST4 4FB",
    "wof:placetype": "postalcode"
  },
  "geometry": {"coordinates":[-2.190066,52.988332],"type":"Point"}
}
