{
  "type": "Feature",
  "properties": {
    "date:inception_lower":"2007-07-01",
    "date:inception_upper":"2007-07-31",
    "iso:country":"GB",
    "wof:name":"ST4 4FB",
    "wof:placetype":"postalcode"
},
  "geometry": {"coordinates":[-2.190066,52.988332],"type":"Point"}
}