{
  "type": "Feature",
  "properties": {
    "iso:country":"GB",
    "wof:name":"NG9 4JJ",
    "wof:placetype":"postalcode"
},
  "geometry": {"coordinates":[-1.24971708155018,52.92179921162438],"type":"Point"}
}