{
  "type": "Feature",
  "properties": {
    "iso:country": "GB",
    "wof:name": "PE12 6FR",
    "wof:placetype": "postalcode"
  },
  "geometry": {"coordinates":[-0.145977,52.75031],"type":"Point"}
}
