{
  "type": "Feature",
  "properties": {
    "iso:country": "GB",
    "wof:name": "S41 9TE",
    "wof:placetype": "postalcode"
  },
  "geometry": {"coordinates":[-1.413337,53.27708],"type":"Point"}
}
