{
  "type": "Feature",
  "properties": {
    "date:inception_lower":"1981-06-01",
    "date:inception_upper":"1981-06-30",
    "iso:country":"GB",
    "wof:name":"SG6 4JE",
    "wof:placetype":"postalcode"
},
  "geometry": {"coordinates":[-0.23478,51.988624],"type":"Point"}
}