{
  "type": "Feature",
  "properties": {
    "iso:country":"GB",
    "wof:name":"SG6 4JE",
    "wof:placetype":"postalcode"
},
  "geometry": {"coordinates":[-0.23479397244144,51.98856952440268],"type":"Point"}
}