{
  "type": "Feature",
  "properties": {
    "iso:country": "GB",
    "wof:name": "CO16 8YN",
    "wof:placetype": "postalcode"
  },
  "geometry": {"coordinates":[1.144265,51.809105],"type":"Point"}
}
