{
  "type": "Feature",
  "properties": {
    "date:inception_lower": "1980-01-01",
    "date:inception_upper": "1980-01-01",
    "iso:country": "GB",
    "wof:name": "L17 8TQ",
    "wof:placetype": "postalcode"
  },
  "geometry": {"coordinates":[-2.950188,53.380553],"type":"Point"}
}
