{
  "type": "Feature",
  "properties": {
    "iso:country":"GB",
    "wof:name":"L17 8TQ",
    "wof:placetype":"postalcode"
},
  "geometry": {"coordinates":[-2.95018783574169,53.38055325197382],"type":"Point"}
}