{
  "type": "Feature",
  "properties": {
    "date:inception_lower": "1995-07-01",
    "date:inception_upper": "1995-07-01",
    "iso:country": "GB",
    "wof:name": "CA11 9HS",
    "wof:placetype": "postalcode"
  },
  "geometry": {"coordinates":[-2.756566,54.669879],"type":"Point"}
}
