{
  "type": "Feature",
  "properties": {
    "iso:country": "GB",
    "wof:name": "EX20 2DE",
    "wof:placetype": "postalcode"
  },
  "geometry": {"coordinates":[-3.896973,50.801038],"type":"Point"}
}
