{
  "type": "Feature",
  "properties": {
    "iso:country":"GB",
    "wof:name":"WF2 7ES",
    "wof:placetype":"postalcode"
},
  "geometry": {"coordinates":[-1.50617143142609,53.64288578346897],"type":"Point"}
}