{
  "type": "Feature",
  "properties": {
    "iso:country":"GB",
    "wof:name":"EX11 1SY",
    "wof:placetype":"postalcode"
},
  "geometry": {"coordinates":[-3.26938220041489,50.75245248818769],"type":"Point"}
}