{
  "type": "Feature",
  "properties": {
    "iso:country": "GB",
    "wof:name": "M20 4UZ",
    "wof:placetype": "postalcode"
  },
  "geometry": {"coordinates":[-2.221425,53.429703],"type":"Point"}
}
