{
  "type": "Feature",
  "properties": {
    "iso:country":"GB",
    "wof:name":"SG1 2RD",
    "wof:placetype":"postalcode"
},
  "geometry": {"coordinates":[-0.22139739033496,51.90906919554342],"type":"Point"}
}