{
  "type": "Feature",
  "properties": {
    "iso:country": "GB",
    "wof:name": "SG1 2RD",
    "wof:placetype": "postalcode"
  },
  "geometry": {"coordinates":[-0.221397,51.909069],"type":"Point"}
}
