{
  "type": "Feature",
  "properties": {
    "iso:country":"GB",
    "wof:name":"NP12 2HF",
    "wof:placetype":"postalcode"
},
  "geometry": {"coordinates":[-3.20427023916515,51.64855663096148],"type":"Point"}
}