{
  "type": "Feature",
  "properties": {
    "iso:country": "GB",
    "wof:name": "NP12 2HF",
    "wof:placetype": "postalcode"
  },
  "geometry": {"coordinates":[-3.204279,51.64856],"type":"Point"}
}
