{
  "type": "Feature",
  "properties": {
    "iso:country":"GB",
    "wof:name":"BN11 4TJ",
    "wof:placetype":"postalcode"
},
  "geometry": {"coordinates":[-0.39115441217896,50.81089856475917],"type":"Point"}
}