{
  "type": "Feature",
  "properties": {
    "date:inception_lower": "2005-06-01",
    "date:inception_upper": "2005-06-01",
    "iso:country": "GB",
    "wof:name": "BN11 4TJ",
    "wof:placetype": "postalcode"
  },
  "geometry": {"coordinates":[-0.391154,50.810899],"type":"Point"}
}
