{
  "type": "Feature",
  "properties": {
    "iso:country": "GB",
    "wof:name": "EX37 9ES",
    "wof:placetype": "postalcode"
  },
  "geometry": {"coordinates":[-3.909999,50.924396],"type":"Point"}
}
