{
  "type": "Feature",
  "properties": {
    "iso:country": "GB",
    "wof:name": "G75 8ZT",
    "wof:placetype": "postalcode"
  },
  "geometry": {"coordinates":[-4.205027,55.759708],"type":"Point"}
}
