{
  "type": "Feature",
  "properties": {
    "iso:country": "GB",
    "wof:name": "CO9 3QQ",
    "wof:placetype": "postalcode"
  },
  "geometry": {"coordinates":[0.591271,51.984015],"type":"Point"}
}
