{
  "type": "Feature",
  "properties": {
    "iso:country": "GB",
    "wof:name": "WS14 9PP",
    "wof:placetype": "postalcode"
  },
  "geometry": {"coordinates":[-1.761062,52.677579],"type":"Point"}
}
