{
  "type": "Feature",
  "properties": {
    "iso:country":"GB",
    "wof:name":"HA0 2LW",
    "wof:placetype":"postalcode"
},
  "geometry": {"coordinates":[-0.31595056740736,51.55500618475771],"type":"Point"}
}