{
  "type": "Feature",
  "properties": {
    "iso:country": "GB",
    "wof:name": "DL5 5AJ",
    "wof:placetype": "postalcode"
  },
  "geometry": {"coordinates":[-1.560719,54.619693],"type":"Point"}
}
