{
  "type": "Feature",
  "properties": {
    "iso:country":"GB",
    "wof:name":"DL5 5AJ",
    "wof:placetype":"postalcode"
},
  "geometry": {"coordinates":[-1.56071860927075,54.61969287790669],"type":"Point"}
}