{
  "type": "Feature",
  "properties": {
    "date:inception_lower": "1980-01-01",
    "date:inception_upper": "1980-01-01",
    "iso:country": "GB",
    "wof:name": "CV31 2LA",
    "wof:placetype": "postalcode"
  },
  "geometry": {"coordinates":[-1.532953,52.266639],"type":"Point"}
}
