{
  "type": "Feature",
  "properties": {
    "date:inception_lower":"1997-06-01",
    "date:inception_upper":"1997-06-30",
    "iso:country":"GB",
    "wof:name":"WF16 9JJ",
    "wof:placetype":"postalcode"
},
  "geometry": {"coordinates":[-1.66492,53.709759],"type":"Point"}
}