{
  "type": "Feature",
  "properties": {
    "iso:country": "GB",
    "wof:name": "WF16 9JJ",
    "wof:placetype": "postalcode"
  },
  "geometry": {"coordinates":[-1.66492,53.709759],"type":"Point"}
}
