{
  "type": "Feature",
  "properties": {
    "iso:country":"GB",
    "wof:name":"IP9 2HR",
    "wof:placetype":"postalcode"
},
  "geometry": {"coordinates":[1.04915997445963,52.0022814902511],"type":"Point"}
}