{
  "type": "Feature",
  "properties": {
    "iso:country": "GB",
    "wof:name": "IP9 2HR",
    "wof:placetype": "postalcode"
  },
  "geometry": {"coordinates":[1.04916,52.002281],"type":"Point"}
}
