{
  "type": "Feature",
  "properties": {
    "iso:country":"GB",
    "wof:name":"ST6 5JF",
    "wof:placetype":"postalcode"
},
  "geometry": {"coordinates":[-2.21875867064121,53.05934170425453],"type":"Point"}
}