{
  "type": "Feature",
  "properties": {
    "iso:country": "GB",
    "wof:name": "SK4 3AW",
    "wof:placetype": "postalcode"
  },
  "geometry": {"coordinates":[-2.209872,53.412689],"type":"Point"}
}
