{
  "type": "Feature",
  "properties": {
    "iso:country":"GB",
    "wof:name":"N1 0AX",
    "wof:placetype":"postalcode"
},
  "geometry": {"coordinates":[-0.12196554916692,51.53670240639178],"type":"Point"}
}