{
  "type": "Feature",
  "properties": {
    "iso:country":"GB",
    "wof:name":"RM5 2BB",
    "wof:placetype":"postalcode"
},
  "geometry": {"coordinates":[0.15638718658716,51.59816555966373],"type":"Point"}
}