{
  "type": "Feature",
  "properties": {
    "iso:country":"GB",
    "wof:name":"SS2 6XY",
    "wof:placetype":"postalcode"
},
  "geometry": {"coordinates":[0.66973293502307,51.57107793461134],"type":"Point"}
}