{
  "type": "Feature",
  "properties": {
    "date:inception_lower": "1986-04-01",
    "date:inception_upper": "1986-04-01",
    "iso:country": "GB",
    "wof:name": "SS2 6XY",
    "wof:placetype": "postalcode"
  },
  "geometry": {"coordinates":[0.669733,51.571078],"type":"Point"}
}
