{
  "type": "Feature",
  "properties": {
    "iso:country": "GB",
    "wof:name": "NE38 7ET",
    "wof:placetype": "postalcode"
  },
  "geometry": {"coordinates":[-1.510311,54.894032],"type":"Point"}
}
