{
  "type": "Feature",
  "properties": {
    "date:inception_lower": "1980-01-01",
    "date:inception_upper": "1980-01-01",
    "iso:country": "GB",
    "wof:name": "NE38 7ET",
    "wof:placetype": "postalcode"
  },
  "geometry": {"coordinates":[-1.510311,54.894032],"type":"Point"}
}
