{
  "type": "Feature",
  "properties": {
    "date:inception_lower": "1980-01-01",
    "date:inception_upper": "1980-01-01",
    "iso:country": "GB",
    "wof:name": "CO13 9AL",
    "wof:placetype": "postalcode"
  },
  "geometry": {"coordinates":[1.248253,51.836677],"type":"Point"}
}
