{
  "type": "Feature",
  "properties": {
    "iso:country":"GB",
    "wof:name":"CO13 9AL",
    "wof:placetype":"postalcode"
},
  "geometry": {"coordinates":[1.24825263612574,51.83667694878671],"type":"Point"}
}