{
  "type": "Feature",
  "properties": {
    "iso:country":"GB",
    "wof:name":"S40 2FP",
    "wof:placetype":"postalcode"
},
  "geometry": {"coordinates":[-1.42546783598854,53.22903976071936],"type":"Point"}
}