{
  "type": "Feature",
  "properties": {
    "iso:country": "GB",
    "wof:name": "S40 2FP",
    "wof:placetype": "postalcode"
  },
  "geometry": {"coordinates":[-1.425468,53.22904],"type":"Point"}
}
