{
  "type": "Feature",
  "properties": {
    "iso:country":"GB",
    "wof:name":"NR31 0DB",
    "wof:placetype":"postalcode"
},
  "geometry": {"coordinates":[1.71501560921085,52.6058304284015],"type":"Point"}
}