{
  "type": "Feature",
  "properties": {
    "iso:country": "GB",
    "wof:name": "NR31 0DB",
    "wof:placetype": "postalcode"
  },
  "geometry": {"coordinates":[1.715016,52.60583],"type":"Point"}
}
