{
  "type": "Feature",
  "properties": {
    "iso:country":"GB",
    "wof:name":"SL4 2PX",
    "wof:placetype":"postalcode"
},
  "geometry": {"coordinates":[-0.58562637942212,51.46034615074999],"type":"Point"}
}