{
  "type": "Feature",
  "properties": {
    "iso:country": "GB",
    "wof:name": "SL4 2PX",
    "wof:placetype": "postalcode"
  },
  "geometry": {"coordinates":[-0.585068,51.460143],"type":"Point"}
}
