{
  "type": "Feature",
  "properties": {
    "iso:country":"GB",
    "wof:name":"TQ2 5RS",
    "wof:placetype":"postalcode"
},
  "geometry": {"coordinates":[-3.5359665714146,50.46907144534415],"type":"Point"}
}