{
  "type": "Feature",
  "properties": {
    "date:inception_lower": "1980-01-01",
    "date:inception_upper": "1980-01-01",
    "iso:country": "GB",
    "wof:name": "ME7 1PD",
    "wof:placetype": "postalcode"
  },
  "geometry": {"coordinates":[0.547862,51.394243],"type":"Point"}
}
