{
  "type": "Feature",
  "properties": {
    "date:inception_lower":"1980-01-01",
    "date:inception_upper":"1980-01-31",
    "iso:country":"GB",
    "wof:name":"PL19 9HZ",
    "wof:placetype":"postalcode"
},
  "geometry": {"coordinates":[-4.137288,50.548153],"type":"Point"}
}