{
  "type": "Feature",
  "properties": {
    "iso:country":"GB",
    "wof:name":"PL19 9HZ",
    "wof:placetype":"postalcode"
},
  "geometry": {"coordinates":[-4.13728794195054,50.54815287821167],"type":"Point"}
}