{
  "type": "Feature",
  "properties": {
    "iso:country": "GB",
    "wof:name": "MK2 2TP",
    "wof:placetype": "postalcode"
  },
  "geometry": {"coordinates":[-0.728788,51.99643],"type":"Point"}
}
