{
  "type": "Feature",
  "properties": {
    "date:inception_lower":"2005-10-01",
    "date:inception_upper":"2005-10-31",
    "iso:country":"GB",
    "wof:name":"L2 4UQ",
    "wof:placetype":"postalcode"
},
  "geometry": {"coordinates":[-2.989639,53.406606],"type":"Point"}
}