{
  "type": "Feature",
  "properties": {
    "iso:country": "GB",
    "wof:name": "L2 4UQ",
    "wof:placetype": "postalcode"
  },
  "geometry": {"coordinates":[-2.989639,53.406606],"type":"Point"}
}
