{
  "type": "Feature",
  "properties": {
    "date:inception_lower":"1991-03-01",
    "date:inception_upper":"1991-03-31",
    "iso:country":"GB",
    "wof:name":"AB22 8XZ",
    "wof:placetype":"postalcode"
},
  "geometry": {"coordinates":[-2.134125,57.17864],"type":"Point"}
}