{
  "type": "Feature",
  "properties": {
    "iso:country": "GB",
    "wof:name": "AB22 8XZ",
    "wof:placetype": "postalcode"
  },
  "geometry": {"coordinates":[-2.134125,57.17864],"type":"Point"}
}
