{
  "type": "Feature",
  "properties": {
    "iso:country":"GB",
    "wof:name":"AB22 8XZ",
    "wof:placetype":"postalcode"
},
  "geometry": {"coordinates":[-2.13412517638063,57.17864049370302],"type":"Point"}
}