{
  "type": "Feature",
  "properties": {
    "iso:country":"GB",
    "wof:name":"S81 9AE",
    "wof:placetype":"postalcode"
},
  "geometry": {"coordinates":[-1.10843310554518,53.35709898647151],"type":"Point"}
}