{
  "type": "Feature",
  "properties": {
    "iso:country": "GB",
    "wof:name": "S81 9AE",
    "wof:placetype": "postalcode"
  },
  "geometry": {"coordinates":[-1.108433,53.357099],"type":"Point"}
}
