{
  "type": "Feature",
  "properties": {
    "date:inception_lower":"1980-01-01",
    "date:inception_upper":"1980-01-31",
    "iso:country":"GB",
    "wof:name":"B62 0JN",
    "wof:placetype":"postalcode"
},
  "geometry": {"coordinates":[-2.047921,52.433654],"type":"Point"}
}