{
  "type": "Feature",
  "properties": {
    "iso:country": "GB",
    "wof:name": "YO19 6LP",
    "wof:placetype": "postalcode"
  },
  "geometry": {"coordinates":[-1.081388,53.887453],"type":"Point"}
}
