{
  "type": "Feature",
  "properties": {
    "iso:country":"GB",
    "wof:name":"NW6 4QU",
    "wof:placetype":"postalcode"
},
  "geometry": {"coordinates":[-0.19235540365699,51.53903111581131],"type":"Point"}
}