{
  "type": "Feature",
  "properties": {
    "iso:country": "GB",
    "wof:name": "KY13 8QU",
    "wof:placetype": "postalcode"
  },
  "geometry": {"coordinates":[-3.430986,56.208911],"type":"Point"}
}
