{
  "type": "Feature",
  "properties": {
    "iso:country":"GB",
    "wof:name":"KY13 8QU",
    "wof:placetype":"postalcode"
},
  "geometry": {"coordinates":[-3.43098606857412,56.20891110576788],"type":"Point"}
}