{
  "type": "Feature",
  "properties": {
    "iso:country": "GB",
    "wof:name": "AL7 1JG",
    "wof:placetype": "postalcode"
  },
  "geometry": {"coordinates":[-0.191071,51.801987],"type":"Point"}
}
