{
  "type": "Feature",
  "properties": {
    "iso:country":"GB",
    "wof:name":"AB51 5AX",
    "wof:placetype":"postalcode"
},
  "geometry": {"coordinates":[-2.45221283591556,57.37458743922717],"type":"Point"}
}