{
  "type": "Feature",
  "properties": {
    "iso:country": "GB",
    "wof:name": "E15 3DS",
    "wof:placetype": "postalcode"
  },
  "geometry": {"coordinates":[0.010778,51.532047],"type":"Point"}
}
