{
  "type": "Feature",
  "properties": {
    "iso:country":"GB",
    "wof:name":"N19 3TT",
    "wof:placetype":"postalcode"
},
  "geometry": {"coordinates":[-0.13703163030991,51.56994494309961],"type":"Point"}
}