{
  "type": "Feature",
  "properties": {
    "date:inception_lower": "2021-07-01",
    "date:inception_upper": "2021-07-01",
    "iso:country": "GB",
    "wof:name": "NP44 1FN",
    "wof:placetype": "postalcode"
  },
  "geometry": {"coordinates":[-3.025422,51.668879],"type":"Point"}
}
