{
  "type": "Feature",
  "properties": {
    "date:inception_lower":"1980-01-01",
    "date:inception_upper":"1980-01-31",
    "iso:country":"GB",
    "wof:name":"WF4 4JL",
    "wof:placetype":"postalcode"
},
  "geometry": {"coordinates":[-1.586003,53.618623],"type":"Point"}
}