{
  "type": "Feature",
  "properties": {
    "iso:country":"GB",
    "wof:name":"WF4 4JL",
    "wof:placetype":"postalcode"
},
  "geometry": {"coordinates":[-1.58600270925095,53.61862330828178],"type":"Point"}
}