{
  "type": "Feature",
  "properties": {
    "iso:country": "GB",
    "wof:name": "SY3 9DU",
    "wof:placetype": "postalcode"
  },
  "geometry": {"coordinates":[-2.772831,52.692271],"type":"Point"}
}
