{
  "type": "Feature",
  "properties": {
    "iso:country":"GB",
    "wof:name":"SY3 9DU",
    "wof:placetype":"postalcode"
},
  "geometry": {"coordinates":[-2.77283113196669,52.69227068711003],"type":"Point"}
}