{
  "type": "Feature",
  "properties": {
    "iso:country":"GB",
    "wof:name":"SW19 6EN",
    "wof:placetype":"postalcode"
},
  "geometry": {"coordinates":[-0.21627526508857,51.44351971712739],"type":"Point"}
}