{
  "type": "Feature",
  "properties": {
    "date:inception_lower": "1980-01-01",
    "date:inception_upper": "1980-01-01",
    "iso:country": "GB",
    "wof:name": "UB4 8AF",
    "wof:placetype": "postalcode"
  },
  "geometry": {"coordinates":[-0.425678,51.529175],"type":"Point"}
}
