{
  "type": "Feature",
  "properties": {
    "iso:country":"GB",
    "wof:name":"EX12 2BH",
    "wof:placetype":"postalcode"
},
  "geometry": {"coordinates":[-3.07382265730636,50.70966872912707],"type":"Point"}
}