{
  "type": "Feature",
  "properties": {
    "iso:country":"GB",
    "wof:name":"IV7 8HP",
    "wof:placetype":"postalcode"
},
  "geometry": {"coordinates":[-4.437849372678,57.5622847048414],"type":"Point"}
}