{
  "type": "Feature",
  "properties": {
    "date:inception_lower": "1991-03-01",
    "date:inception_upper": "1991-03-01",
    "iso:country": "GB",
    "wof:name": "IV7 8HP",
    "wof:placetype": "postalcode"
  },
  "geometry": {"coordinates":[-4.437849,57.562285],"type":"Point"}
}
