{
  "type": "Feature",
  "properties": {
    "date:inception_lower": "1980-01-01",
    "date:inception_upper": "1980-01-01",
    "iso:country": "GB",
    "wof:name": "WR3 7BU",
    "wof:placetype": "postalcode"
  },
  "geometry": {"coordinates":[-2.226733,52.21363],"type":"Point"}
}
