{
  "type": "Feature",
  "properties": {
    "iso:country":"GB",
    "wof:name":"WR3 7BU",
    "wof:placetype":"postalcode"
},
  "geometry": {"coordinates":[-2.22678163225534,52.21360811034058],"type":"Point"}
}