{
  "type": "Feature",
  "properties": {
    "iso:country":"GB",
    "wof:name":"WS1 4DN",
    "wof:placetype":"postalcode"
},
  "geometry": {"coordinates":[-1.99042558000948,52.56932138668565],"type":"Point"}
}