{
  "type": "Feature",
  "properties": {
    "iso:country":"GB",
    "wof:name":"SR2 9RT",
    "wof:placetype":"postalcode"
},
  "geometry": {"coordinates":[-1.36362483153949,54.88428529498171],"type":"Point"}
}