{
  "type": "Feature",
  "properties": {
    "iso:country":"GB",
    "wof:name":"ME7 4AY",
    "wof:placetype":"postalcode"
},
  "geometry": {"coordinates":[0.55601784937018,51.37395516231934],"type":"Point"}
}