{
  "type": "Feature",
  "properties": {
    "iso:country":"GB",
    "wof:name":"RG10 9HT",
    "wof:placetype":"postalcode"
},
  "geometry": {"coordinates":[-0.86601374954891,51.480189561172],"type":"Point"}
}