{
  "type": "Feature",
  "properties": {
    "iso:country": "GB",
    "wof:name": "RG10 9HT",
    "wof:placetype": "postalcode"
  },
  "geometry": {"coordinates":[-0.866014,51.48019],"type":"Point"}
}
