{
  "type": "Feature",
  "properties": {
    "date:inception_lower":"1980-01-01",
    "date:inception_upper":"1980-01-31",
    "iso:country":"GB",
    "wof:name":"RG10 9HT",
    "wof:placetype":"postalcode"
},
  "geometry": {"coordinates":[-0.866014,51.48019],"type":"Point"}
}