{
  "type": "Feature",
  "properties": {
    "iso:country": "GB",
    "wof:name": "BS49 4PW",
    "wof:placetype": "postalcode"
  },
  "geometry": {"coordinates":[-2.773772,51.3938],"type":"Point"}
}
