{
  "type": "Feature",
  "properties": {
    "date:inception_lower":"1997-12-01",
    "date:inception_upper":"1997-12-31",
    "iso:country":"GB",
    "wof:name":"BS49 4PW",
    "wof:placetype":"postalcode"
},
  "geometry": {"coordinates":[-2.773772,51.3938],"type":"Point"}
}