{
  "type": "Feature",
  "properties": {
    "iso:country": "GB",
    "wof:name": "CA13 9QL",
    "wof:placetype": "postalcode"
  },
  "geometry": {"coordinates":[-3.363169,54.662621],"type":"Point"}
}
