{
  "type": "Feature",
  "properties": {
    "iso:country": "GB",
    "wof:name": "LS25 7AJ",
    "wof:placetype": "postalcode"
  },
  "geometry": {"coordinates":[-1.36654,53.766096],"type":"Point"}
}
