{
  "type": "Feature",
  "properties": {
    "date:inception_lower": "1980-01-01",
    "date:inception_upper": "1980-01-01",
    "iso:country": "GB",
    "wof:name": "ML11 0HN",
    "wof:placetype": "postalcode"
  },
  "geometry": {"coordinates":[-3.921581,55.599494],"type":"Point"}
}
