{
  "type": "Feature",
  "properties": {
    "iso:country":"GB",
    "wof:name":"ML11 0HN",
    "wof:placetype":"postalcode"
},
  "geometry": {"coordinates":[-3.92171286797356,55.59936702916748],"type":"Point"}
}