{
  "type": "Feature",
  "properties": {
    "date:inception_lower": "1980-01-01",
    "date:inception_upper": "1980-01-01",
    "iso:country": "GB",
    "wof:name": "RG14 7AN",
    "wof:placetype": "postalcode"
  },
  "geometry": {"coordinates":[-1.329878,51.388606],"type":"Point"}
}
