{
  "type": "Feature",
  "properties": {
    "iso:country":"GB",
    "wof:name":"FY5 1SB",
    "wof:placetype":"postalcode"
},
  "geometry": {"coordinates":[-3.03842789908026,53.85997438081197],"type":"Point"}
}