{
  "type": "Feature",
  "properties": {
    "iso:country":"GB",
    "wof:name":"CH4 0RZ",
    "wof:placetype":"postalcode"
},
  "geometry": {"coordinates":[-2.99415490105781,53.16254114448753],"type":"Point"}
}