{
  "type": "Feature",
  "properties": {
    "iso:country": "GB",
    "wof:name": "CH4 0RZ",
    "wof:placetype": "postalcode"
  },
  "geometry": {"coordinates":[-2.994155,53.162541],"type":"Point"}
}
