{
  "type": "Feature",
  "properties": {
    "date:inception_lower": "1980-01-01",
    "date:inception_upper": "1980-01-01",
    "iso:country": "GB",
    "wof:name": "CH4 0RZ",
    "wof:placetype": "postalcode"
  },
  "geometry": {"coordinates":[-2.994155,53.162541],"type":"Point"}
}
