{
  "type": "Feature",
  "properties": {
    "iso:country": "GB",
    "wof:name": "RG12 7RS",
    "wof:placetype": "postalcode"
  },
  "geometry": {"coordinates":[-0.759884,51.40994],"type":"Point"}
}
