{
  "type": "Feature",
  "properties": {
    "iso:country":"GB",
    "wof:name":"RG12 7RS",
    "wof:placetype":"postalcode"
},
  "geometry": {"coordinates":[-0.75988453983202,51.40993988060896],"type":"Point"}
}