{
  "type": "Feature",
  "properties": {
    "iso:country":"GB",
    "wof:name":"BA14 0DL",
    "wof:placetype":"postalcode"
},
  "geometry": {"coordinates":[-2.21920840977346,51.31278876663548],"type":"Point"}
}