{
  "type": "Feature",
  "properties": {
    "iso:country": "GB",
    "wof:name": "BN14 8QE",
    "wof:placetype": "postalcode"
  },
  "geometry": {"coordinates":[-0.360957,50.831399],"type":"Point"}
}
