{
  "type": "Feature",
  "properties": {
    "iso:country":"GB",
    "wof:name":"HD8 8TX",
    "wof:placetype":"postalcode"
},
  "geometry": {"coordinates":[-1.64181958084624,53.56818103513528],"type":"Point"}
}