{
  "type": "Feature",
  "properties": {
    "iso:country":"GB",
    "wof:name":"CO10 5HL",
    "wof:placetype":"postalcode"
},
  "geometry": {"coordinates":[0.86393706952043,52.02958812054587],"type":"Point"}
}