{
  "type": "Feature",
  "properties": {
    "date:inception_lower": "2020-04-01",
    "date:inception_upper": "2020-04-01",
    "iso:country": "GB",
    "wof:name": "IP17 1FZ",
    "wof:placetype": "postalcode"
  },
  "geometry": {"coordinates":[1.496844,52.217325],"type":"Point"}
}
