{
  "type": "Feature",
  "properties": {
    "date:inception_lower": "2015-07-01",
    "date:inception_upper": "2015-07-01",
    "iso:country": "GB",
    "wof:name": "NP12 3SN",
    "wof:placetype": "postalcode"
  },
  "geometry": {"coordinates":[-3.217243,51.663064],"type":"Point"}
}
