{
  "type": "Feature",
  "properties": {
    "iso:country": "GB",
    "wof:name": "NP12 3SN",
    "wof:placetype": "postalcode"
  },
  "geometry": {"coordinates":[-3.217214,51.663091],"type":"Point"}
}
