{
  "type": "Feature",
  "properties": {
    "iso:country":"GB",
    "wof:name":"NP12 3SN",
    "wof:placetype":"postalcode"
},
  "geometry": {"coordinates":[-3.21722006594815,51.66308852584841],"type":"Point"}
}