{
  "type": "Feature",
  "properties": {
    "iso:country": "GB",
    "wof:name": "MK42 0YB",
    "wof:placetype": "postalcode"
  },
  "geometry": {"coordinates":[-0.427484,52.111024],"type":"Point"}
}
