{
  "type": "Feature",
  "properties": {
    "iso:country":"GB",
    "wof:name":"CW8 3EB",
    "wof:placetype":"postalcode"
},
  "geometry": {"coordinates":[-2.5723577518978,53.25618524569079],"type":"Point"}
}