{
  "type": "Feature",
  "properties": {
    "iso:country": "GB",
    "wof:name": "SW15 5NB",
    "wof:placetype": "postalcode"
  },
  "geometry": {"coordinates":[-0.242969,51.461125],"type":"Point"}
}
