{
  "type": "Feature",
  "properties": {
    "iso:country":"GB",
    "wof:name":"SW15 5NB",
    "wof:placetype":"postalcode"
},
  "geometry": {"coordinates":[-0.24296906630007,51.46112546057564],"type":"Point"}
}