{
  "type": "Feature",
  "properties": {
    "iso:country":"GB",
    "wof:name":"LL29 7EN",
    "wof:placetype":"postalcode"
},
  "geometry": {"coordinates":[-3.7291301094312,53.29170959915992],"type":"Point"}
}