{
  "type": "Feature",
  "properties": {
    "iso:country":"GB",
    "wof:name":"HA4 9QH",
    "wof:placetype":"postalcode"
},
  "geometry": {"coordinates":[-0.38679806988986,51.57234036450087],"type":"Point"}
}