{
  "type": "Feature",
  "properties": {
    "iso:country": "GB",
    "wof:name": "CT9 4BW",
    "wof:placetype": "postalcode"
  },
  "geometry": {"coordinates":[1.390456,51.37446],"type":"Point"}
}
