{
  "type": "Feature",
  "properties": {
    "date:inception_lower":"1995-12-01",
    "date:inception_upper":"1995-12-31",
    "iso:country":"GB",
    "wof:name":"NR17 2RG",
    "wof:placetype":"postalcode"
},
  "geometry": {"coordinates":[1.022065,52.521379],"type":"Point"}
}