{
  "type": "Feature",
  "properties": {
    "iso:country":"GB",
    "wof:name":"NR17 2RG",
    "wof:placetype":"postalcode"
},
  "geometry": {"coordinates":[1.02206501288178,52.52137927564958],"type":"Point"}
}