{
  "type": "Feature",
  "properties": {
    "date:inception_lower": "1980-01-01",
    "date:inception_upper": "1980-01-01",
    "iso:country": "GB",
    "wof:name": "S75 1BW",
    "wof:placetype": "postalcode"
  },
  "geometry": {"coordinates":[-1.48497,53.562908],"type":"Point"}
}
