{
  "type": "Feature",
  "properties": {
    "iso:country": "GB",
    "wof:name": "S75 1BW",
    "wof:placetype": "postalcode"
  },
  "geometry": {"coordinates":[-1.48497,53.562908],"type":"Point"}
}
