{
  "type": "Feature",
  "properties": {
    "iso:country":"GB",
    "wof:name":"S75 1BW",
    "wof:placetype":"postalcode"
},
  "geometry": {"coordinates":[-1.48496978604727,53.56290798839132],"type":"Point"}
}