{
  "type": "Feature",
  "properties": {
    "iso:country":"GB",
    "wof:name":"CR8 5JN",
    "wof:placetype":"postalcode"
},
  "geometry": {"coordinates":[-0.1087522449489,51.31733895127151],"type":"Point"}
}