{
  "type": "Feature",
  "properties": {
    "iso:country":"GB",
    "wof:name":"PR5 4BF",
    "wof:placetype":"postalcode"
},
  "geometry": {"coordinates":[-2.69091956544392,53.73693246130562],"type":"Point"}
}