{
  "type": "Feature",
  "properties": {
    "iso:country": "GB",
    "wof:name": "PR5 4BF",
    "wof:placetype": "postalcode"
  },
  "geometry": {"coordinates":[-2.69092,53.736932],"type":"Point"}
}
