{
  "type": "Feature",
  "properties": {
    "date:inception_lower":"1994-12-01",
    "date:inception_upper":"1994-12-31",
    "iso:country":"GB",
    "wof:name":"PR5 4BF",
    "wof:placetype":"postalcode"
},
  "geometry": {"coordinates":[-2.69092,53.736932],"type":"Point"}
}