{
  "type": "Feature",
  "properties": {
    "iso:country": "GB",
    "wof:name": "DN34 4AE",
    "wof:placetype": "postalcode"
  },
  "geometry": {"coordinates":[-0.104409,53.563102],"type":"Point"}
}
