{
  "type": "Feature",
  "properties": {
    "iso:country":"GB",
    "wof:name":"RH5 5BS",
    "wof:placetype":"postalcode"
},
  "geometry": {"coordinates":[-0.25825785483074,51.14807598711121],"type":"Point"}
}