{
  "type": "Feature",
  "properties": {
    "iso:country":"GB",
    "wof:name":"CT3 2JX",
    "wof:placetype":"postalcode"
},
  "geometry": {"coordinates":[1.24446901215869,51.28611166489228],"type":"Point"}
}