{
  "type": "Feature",
  "properties": {
    "iso:country":"GB",
    "wof:name":"HX7 5PB",
    "wof:placetype":"postalcode"
},
  "geometry": {"coordinates":[-1.9760895031708,53.73083390215778],"type":"Point"}
}