{
  "type": "Feature",
  "properties": {
    "iso:country":"GB",
    "wof:name":"S6 4BJ",
    "wof:placetype":"postalcode"
},
  "geometry": {"coordinates":[-1.52112907959535,53.41024435267104],"type":"Point"}
}