{
  "type": "Feature",
  "properties": {
    "iso:country": "GB",
    "wof:name": "G69 7JD",
    "wof:placetype": "postalcode"
  },
  "geometry": {"coordinates":[-4.114477,55.849429],"type":"Point"}
}
