{
  "type": "Feature",
  "properties": {
    "date:inception_lower":"1980-01-01",
    "date:inception_upper":"1980-01-31",
    "iso:country":"GB",
    "wof:name":"EC4R 2RA",
    "wof:placetype":"postalcode"
},
  "geometry": {"coordinates":[-0.092255,51.511664],"type":"Point"}
}