{
  "type": "Feature",
  "properties": {
    "iso:country":"GB",
    "wof:name":"EC4R 2RA",
    "wof:placetype":"postalcode"
},
  "geometry": {"coordinates":[-0.09225550706058,51.5116643591073],"type":"Point"}
}