{
  "type": "Feature",
  "properties": {
    "iso:country":"GB",
    "wof:name":"TA22 9QW",
    "wof:placetype":"postalcode"
},
  "geometry": {"coordinates":[-3.62721030889669,51.0640883457674],"type":"Point"}
}