{
  "type": "Feature",
  "properties": {
    "iso:country": "GB",
    "wof:name": "TA22 9QW",
    "wof:placetype": "postalcode"
  },
  "geometry": {"coordinates":[-3.62721,51.064088],"type":"Point"}
}
