{
  "type": "Feature",
  "properties": {
    "iso:country": "GB",
    "wof:name": "TN31 6FP",
    "wof:placetype": "postalcode"
  },
  "geometry": {"coordinates":[0.66706,50.938187],"type":"Point"}
}
