{
  "type": "Feature",
  "properties": {
    "iso:country": "GB",
    "wof:name": "GU31 5SS",
    "wof:placetype": "postalcode"
  },
  "geometry": {"coordinates":[-0.931626,50.977106],"type":"Point"}
}
