{
  "type": "Feature",
  "properties": {
    "date:inception_lower": "1996-06-01",
    "date:inception_upper": "1996-06-01",
    "iso:country": "GB",
    "wof:name": "GU31 5SS",
    "wof:placetype": "postalcode"
  },
  "geometry": {"coordinates":[-0.931626,50.977106],"type":"Point"}
}
