{
  "type": "Feature",
  "properties": {
    "iso:country":"GB",
    "wof:name":"N19 5HZ",
    "wof:placetype":"postalcode"
},
  "geometry": {"coordinates":[-0.14090698255342,51.56444009003043],"type":"Point"}
}