{
  "type": "Feature",
  "properties": {
    "iso:country":"GB",
    "wof:name":"TF9 2QD",
    "wof:placetype":"postalcode"
},
  "geometry": {"coordinates":[-2.42505294560017,52.90895921100181],"type":"Point"}
}