{
  "type": "Feature",
  "properties": {
    "iso:country": "GB",
    "wof:name": "TF9 2QD",
    "wof:placetype": "postalcode"
  },
  "geometry": {"coordinates":[-2.425053,52.908959],"type":"Point"}
}
