{
  "type": "Feature",
  "properties": {
    "iso:country":"GB",
    "wof:name":"NG4 1JT",
    "wof:placetype":"postalcode"
},
  "geometry": {"coordinates":[-1.1140506641293,52.96922012536894],"type":"Point"}
}