{
  "type": "Feature",
  "properties": {
    "iso:country":"GB",
    "wof:name":"RG23 7TW",
    "wof:placetype":"postalcode"
},
  "geometry": {"coordinates":[-1.17935102197037,51.24628686735501],"type":"Point"}
}