{
  "type": "Feature",
  "properties": {
    "date:inception_lower":"2012-08-01",
    "date:inception_upper":"2012-08-31",
    "iso:country":"GB",
    "wof:name":"RG23 7TW",
    "wof:placetype":"postalcode"
},
  "geometry": {"coordinates":[-1.179351,51.246287],"type":"Point"}
}