{
  "type": "Feature",
  "properties": {
    "iso:country": "GB",
    "wof:name": "RG23 7TW",
    "wof:placetype": "postalcode"
  },
  "geometry": {"coordinates":[-1.179351,51.246287],"type":"Point"}
}
