{
  "type": "Feature",
  "properties": {
    "iso:country":"GB",
    "wof:name":"GL6 9AE",
    "wof:placetype":"postalcode"
},
  "geometry": {"coordinates":[-2.20784138437419,51.70098011637241],"type":"Point"}
}