{
  "type": "Feature",
  "properties": {
    "iso:country": "GB",
    "wof:name": "WV11 3XD",
    "wof:placetype": "postalcode"
  },
  "geometry": {"coordinates":[-2.076688,52.60086],"type":"Point"}
}
