{
  "type": "Feature",
  "properties": {
    "iso:country":"GB",
    "wof:name":"WV11 3XD",
    "wof:placetype":"postalcode"
},
  "geometry": {"coordinates":[-2.07668839638459,52.60085993449567],"type":"Point"}
}