{
  "type": "Feature",
  "properties": {
    "iso:country":"GB",
    "wof:name":"EN6 5HG",
    "wof:placetype":"postalcode"
},
  "geometry": {"coordinates":[-0.16819742162685,51.69913348930857],"type":"Point"}
}