{
  "type": "Feature",
  "properties": {
    "date:inception_lower": "2022-12-01",
    "date:inception_upper": "2022-12-01",
    "iso:country": "GB",
    "wof:name": "CT1 1DQ",
    "wof:placetype": "postalcode"
  },
  "geometry": {"coordinates":[1.100731,51.279968],"type":"Point"}
}
