{
  "type": "Feature",
  "properties": {
    "iso:country": "GB",
    "wof:name": "CT4 5RY",
    "wof:placetype": "postalcode"
  },
  "geometry": {"coordinates":[1.025331,51.209795],"type":"Point"}
}
