{
  "type": "Feature",
  "properties": {
    "iso:country":"GB",
    "wof:name":"CT4 5RY",
    "wof:placetype":"postalcode"
},
  "geometry": {"coordinates":[1.02529954649543,51.20978309554493],"type":"Point"}
}