{
  "type": "Feature",
  "properties": {
    "iso:country":"GB",
    "wof:name":"NR35 2AT",
    "wof:placetype":"postalcode"
},
  "geometry": {"coordinates":[1.3610077541019,52.47306228115033],"type":"Point"}
}