{
  "type": "Feature",
  "properties": {
    "date:inception_lower": "2012-02-01",
    "date:inception_upper": "2012-02-01",
    "iso:country": "GB",
    "wof:name": "CH62 2FD",
    "wof:placetype": "postalcode"
  },
  "geometry": {"coordinates":[-2.987504,53.344285],"type":"Point"}
}
