{
  "type": "Feature",
  "properties": {
    "iso:country": "GB",
    "wof:name": "BA3 4XW",
    "wof:placetype": "postalcode"
  },
  "geometry": {"coordinates":[-2.477933,51.273753],"type":"Point"}
}
