{
  "type": "Feature",
  "properties": {
    "iso:country":"GB",
    "wof:name":"B73 5NG",
    "wof:placetype":"postalcode"
},
  "geometry": {"coordinates":[-1.82979471966794,52.5360092582187],"type":"Point"}
}