{
  "type": "Feature",
  "properties": {
    "iso:country":"GB",
    "wof:name":"NE61 3PU",
    "wof:placetype":"postalcode"
},
  "geometry": {"coordinates":[-1.74453405740947,55.16560996984889],"type":"Point"}
}