{
  "type": "Feature",
  "properties": {
    "iso:country": "GB",
    "wof:name": "SO18 4QE",
    "wof:placetype": "postalcode"
  },
  "geometry": {"coordinates":[-1.363497,50.925691],"type":"Point"}
}
