{
  "type": "Feature",
  "properties": {
    "date:inception_lower": "1995-01-01",
    "date:inception_upper": "1995-01-01",
    "iso:country": "GB",
    "wof:name": "SW6 1EF",
    "wof:placetype": "postalcode"
  },
  "geometry": {"coordinates":[-0.197805,51.478434],"type":"Point"}
}
