{
  "type": "Feature",
  "properties": {
    "iso:country":"GB",
    "wof:name":"SW6 1EF",
    "wof:placetype":"postalcode"
},
  "geometry": {"coordinates":[-0.19780519884561,51.47843392098002],"type":"Point"}
}