{
  "type": "Feature",
  "properties": {
    "iso:country":"GB",
    "wof:name":"DL15 0QE",
    "wof:placetype":"postalcode"
},
  "geometry": {"coordinates":[-1.69224569051604,54.70964173080053],"type":"Point"}
}