{
  "type": "Feature",
  "properties": {
    "date:inception_lower":"1980-01-01",
    "date:inception_upper":"1980-01-31",
    "iso:country":"GB",
    "wof:name":"DL15 0QE",
    "wof:placetype":"postalcode"
},
  "geometry": {"coordinates":[-1.692246,54.709642],"type":"Point"}
}