{
  "type": "Feature",
  "properties": {
    "date:inception_lower": "1980-01-01",
    "date:inception_upper": "1980-01-01",
    "iso:country": "GB",
    "wof:name": "EX32 8DA",
    "wof:placetype": "postalcode"
  },
  "geometry": {"coordinates":[-4.042073,51.077818],"type":"Point"}
}
