{
  "type": "Feature",
  "properties": {
    "iso:country":"GB",
    "wof:name":"EX32 8DA",
    "wof:placetype":"postalcode"
},
  "geometry": {"coordinates":[-4.04207309545311,51.07781791833467],"type":"Point"}
}