{
  "type": "Feature",
  "properties": {
    "date:inception_lower": "2010-12-01",
    "date:inception_upper": "2010-12-01",
    "iso:country": "GB",
    "wof:name": "BA21 5ET",
    "wof:placetype": "postalcode"
  },
  "geometry": {"coordinates":[-2.603902,50.957373],"type":"Point"}
}
