{
  "type": "Feature",
  "properties": {
    "iso:country":"GB",
    "wof:name":"CO10 8HJ",
    "wof:placetype":"postalcode"
},
  "geometry": {"coordinates":[0.54395229293048,52.06620706014159],"type":"Point"}
}