{
  "type": "Feature",
  "properties": {
    "iso:country": "GB",
    "wof:name": "FK10 2QQ",
    "wof:placetype": "postalcode"
  },
  "geometry": {"coordinates":[-3.842932,56.128971],"type":"Point"}
}
