{
  "type": "Feature",
  "properties": {
    "iso:country":"GB",
    "wof:name":"FK10 2QQ",
    "wof:placetype":"postalcode"
},
  "geometry": {"coordinates":[-3.84293240204499,56.12897057333847],"type":"Point"}
}