{
  "type": "Feature",
  "properties": {
    "date:inception_lower": "2006-04-01",
    "date:inception_upper": "2006-04-01",
    "iso:country": "GB",
    "wof:name": "RG31 7QD",
    "wof:placetype": "postalcode"
  },
  "geometry": {"coordinates":[-1.049548,51.441339],"type":"Point"}
}
