{
  "type": "Feature",
  "properties": {
    "iso:country":"GB",
    "wof:name":"CV22 7NA",
    "wof:placetype":"postalcode"
},
  "geometry": {"coordinates":[-1.28695845269448,52.36013308003289],"type":"Point"}
}