{
  "type": "Feature",
  "properties": {
    "date:inception_lower": "1980-01-01",
    "date:inception_upper": "1980-01-01",
    "iso:country": "GB",
    "wof:name": "HP22 4EE",
    "wof:placetype": "postalcode"
  },
  "geometry": {"coordinates":[-0.851718,51.862671],"type":"Point"}
}
