{
  "type": "Feature",
  "properties": {
    "iso:country":"GB",
    "wof:name":"HP22 4EE",
    "wof:placetype":"postalcode"
},
  "geometry": {"coordinates":[-0.85171842093265,51.86267064636281],"type":"Point"}
}