{
  "type": "Feature",
  "properties": {
    "date:inception_lower": "1997-06-01",
    "date:inception_upper": "1997-06-01",
    "iso:country": "GB",
    "wof:name": "S25 3QX",
    "wof:placetype": "postalcode"
  },
  "geometry": {"coordinates":[-1.217227,53.375291],"type":"Point"}
}
