{
  "type": "Feature",
  "properties": {
    "iso:country": "GB",
    "wof:name": "CB21 4NE",
    "wof:placetype": "postalcode"
  },
  "geometry": {"coordinates":[0.289917,52.095383],"type":"Point"}
}
