{
  "type": "Feature",
  "properties": {
    "iso:country":"GB",
    "wof:name":"CB21 4NE",
    "wof:placetype":"postalcode"
},
  "geometry": {"coordinates":[0.2899169470266,52.0953830851639],"type":"Point"}
}