{
  "type": "Feature",
  "properties": {
    "iso:country": "GB",
    "wof:name": "EN3 6WP",
    "wof:placetype": "postalcode"
  },
  "geometry": {"coordinates":[-0.01399,51.671422],"type":"Point"}
}
