{
  "type": "Feature",
  "properties": {
    "date:inception_lower":"2000-06-01",
    "date:inception_upper":"2000-06-30",
    "iso:country":"GB",
    "wof:name":"EN3 6WP",
    "wof:placetype":"postalcode"
},
  "geometry": {"coordinates":[-0.01399,51.671422],"type":"Point"}
}