{
  "type": "Feature",
  "properties": {
    "iso:country":"GB",
    "wof:name":"EN3 6WP",
    "wof:placetype":"postalcode"
},
  "geometry": {"coordinates":[-0.01399039506941,51.67142174410785],"type":"Point"}
}