{
  "type": "Feature",
  "properties": {
    "iso:country":"GB",
    "wof:name":"WD25 9PR",
    "wof:placetype":"postalcode"
},
  "geometry": {"coordinates":[-0.37274851868914,51.70017567417234],"type":"Point"}
}