{
  "type": "Feature",
  "properties": {
    "date:inception_lower":"2011-11-01",
    "date:inception_upper":"2011-11-30",
    "iso:country":"GB",
    "wof:name":"WD25 9PR",
    "wof:placetype":"postalcode"
},
  "geometry": {"coordinates":[-0.372748,51.700176],"type":"Point"}
}