{
  "type": "Feature",
  "properties": {
    "iso:country": "GB",
    "wof:name": "WD25 9PR",
    "wof:placetype": "postalcode"
  },
  "geometry": {"coordinates":[-0.372748,51.700176],"type":"Point"}
}
