{
  "type": "Feature",
  "properties": {
    "iso:country":"GB",
    "wof:name":"HU17 9EQ",
    "wof:placetype":"postalcode"
},
  "geometry": {"coordinates":[-0.42852767849741,53.84309079118889],"type":"Point"}
}