{
  "type": "Feature",
  "properties": {
    "iso:country": "GB",
    "wof:name": "YO16 4RA",
    "wof:placetype": "postalcode"
  },
  "geometry": {"coordinates":[-0.216187,54.083967],"type":"Point"}
}
