{
  "type": "Feature",
  "properties": {
    "iso:country":"GB",
    "wof:name":"EN6 5LX",
    "wof:placetype":"postalcode"
},
  "geometry": {"coordinates":[-0.17060381833451,51.696158596472],"type":"Point"}
}