{
  "type": "Feature",
  "properties": {
    "iso:country":"GB",
    "wof:name":"NP11 4RD",
    "wof:placetype":"postalcode"
},
  "geometry": {"coordinates":[-3.14388204212114,51.67152272168989],"type":"Point"}
}