{
  "type": "Feature",
  "properties": {
    "iso:country": "GB",
    "wof:name": "SE26 5JZ",
    "wof:placetype": "postalcode"
  },
  "geometry": {"coordinates":[-0.045014,51.425447],"type":"Point"}
}
