{
  "type": "Feature",
  "properties": {
    "iso:country":"GB",
    "wof:name":"SE26 5JZ",
    "wof:placetype":"postalcode"
},
  "geometry": {"coordinates":[-0.04501361113906,51.42544694232793],"type":"Point"}
}