{
  "type": "Feature",
  "properties": {
    "date:inception_lower": "1995-07-01",
    "date:inception_upper": "1995-07-01",
    "iso:country": "GB",
    "wof:name": "HX6 3DE",
    "wof:placetype": "postalcode"
  },
  "geometry": {"coordinates":[-1.91715,53.70361],"type":"Point"}
}
