{
  "type": "Feature",
  "properties": {
    "iso:country":"GB",
    "wof:name":"GU11 1RY",
    "wof:placetype":"postalcode"
},
  "geometry": {"coordinates":[-0.76579537328928,51.25162299671656],"type":"Point"}
}