{
  "type": "Feature",
  "properties": {
    "iso:country":"GB",
    "wof:name":"RH1 5AU",
    "wof:placetype":"postalcode"
},
  "geometry": {"coordinates":[-0.1658588749187,51.2120510760427],"type":"Point"}
}