{
  "type": "Feature",
  "properties": {
    "date:inception_lower": "1980-01-01",
    "date:inception_upper": "1980-01-01",
    "iso:country": "GB",
    "wof:name": "LL57 1NG",
    "wof:placetype": "postalcode"
  },
  "geometry": {"coordinates":[-4.113337,53.222944],"type":"Point"}
}
