{
  "type": "Feature",
  "properties": {
    "date:inception_lower": "2018-10-01",
    "date:inception_upper": "2018-10-01",
    "iso:country": "GB",
    "wof:name": "PL13 2FL",
    "wof:placetype": "postalcode"
  },
  "geometry": {"coordinates":[-4.562722,50.386297],"type":"Point"}
}
