{
  "type": "Feature",
  "properties": {
    "date:inception_lower": "1980-01-01",
    "date:inception_upper": "1980-01-01",
    "iso:country": "GB",
    "wof:name": "SS15 5BZ",
    "wof:placetype": "postalcode"
  },
  "geometry": {"coordinates":[0.443597,51.571825],"type":"Point"}
}
