{
  "type": "Feature",
  "properties": {
    "iso:country":"GB",
    "wof:name":"SS15 5BZ",
    "wof:placetype":"postalcode"
},
  "geometry": {"coordinates":[0.44359673616175,51.57182473195504],"type":"Point"}
}