{
  "type": "Feature",
  "properties": {
    "date:inception_lower": "1980-01-01",
    "date:inception_upper": "1980-01-01",
    "iso:country": "GB",
    "wof:name": "CT1 1DB",
    "wof:placetype": "postalcode"
  },
  "geometry": {"coordinates":[1.09211,51.287617],"type":"Point"}
}
