{
  "type": "Feature",
  "properties": {
    "iso:country":"GB",
    "wof:name":"CT1 1DB",
    "wof:placetype":"postalcode"
},
  "geometry": {"coordinates":[1.09206430085185,51.28759456263096],"type":"Point"}
}