{
  "type": "Feature",
  "properties": {
    "iso:country":"GB",
    "wof:name":"ME9 0TS",
    "wof:placetype":"postalcode"
},
  "geometry": {"coordinates":[0.69373943597616,51.28655045125608],"type":"Point"}
}