{
  "type": "Feature",
  "properties": {
    "iso:country": "GB",
    "wof:name": "TN16 3RN",
    "wof:placetype": "postalcode"
  },
  "geometry": {"coordinates":[0.026074,51.305317],"type":"Point"}
}
