{
  "type": "Feature",
  "properties": {
    "iso:country":"GB",
    "wof:name":"TN16 3RN",
    "wof:placetype":"postalcode"
},
  "geometry": {"coordinates":[0.02607387889269,51.30531735954444],"type":"Point"}
}