{
  "type": "Feature",
  "properties": {
    "iso:country": "GB",
    "wof:name": "HP23 5DF",
    "wof:placetype": "postalcode"
  },
  "geometry": {"coordinates":[-0.66573,51.800259],"type":"Point"}
}
