{
  "type": "Feature",
  "properties": {
    "iso:country": "GB",
    "wof:name": "N19 5NW",
    "wof:placetype": "postalcode"
  },
  "geometry": {"coordinates":[-0.137838,51.568222],"type":"Point"}
}
