{
  "type": "Feature",
  "properties": {
    "iso:country":"GB",
    "wof:name":"N19 5NW",
    "wof:placetype":"postalcode"
},
  "geometry": {"coordinates":[-0.13783795577879,51.56822220228811],"type":"Point"}
}