{
  "type": "Feature",
  "properties": {
    "iso:country": "GB",
    "wof:name": "TN3 9LT",
    "wof:placetype": "postalcode"
  },
  "geometry": {"coordinates":[0.215301,51.070515],"type":"Point"}
}
