{
  "type": "Feature",
  "properties": {
    "iso:country": "GB",
    "wof:name": "KT22 9TX",
    "wof:placetype": "postalcode"
  },
  "geometry": {"coordinates":[-0.359526,51.293576],"type":"Point"}
}
