{
  "type": "Feature",
  "properties": {
    "iso:country":"GB",
    "wof:name":"KT22 9TX",
    "wof:placetype":"postalcode"
},
  "geometry": {"coordinates":[-0.35952554499423,51.29357605968529],"type":"Point"}
}