{
  "type": "Feature",
  "properties": {
    "date:inception_lower":"1980-01-01",
    "date:inception_upper":"1980-01-31",
    "iso:country":"GB",
    "wof:name":"KT22 9TX",
    "wof:placetype":"postalcode"
},
  "geometry": {"coordinates":[-0.359526,51.293576],"type":"Point"}
}