{
  "type": "Feature",
  "properties": {
    "date:inception_lower": "2022-06-01",
    "date:inception_upper": "2022-06-01",
    "iso:country": "GB",
    "wof:name": "SY10 7FE",
    "wof:placetype": "postalcode"
  },
  "geometry": {"coordinates":[-3.086267,52.89761],"type":"Point"}
}
