{
  "type": "Feature",
  "properties": {
    "date:inception_lower": "2021-09-01",
    "date:inception_upper": "2021-09-01",
    "iso:country": "GB",
    "wof:name": "B61 0HW",
    "wof:placetype": "postalcode"
  },
  "geometry": {"coordinates":[-2.045298,52.364472],"type":"Point"}
}
