{
  "type": "Feature",
  "properties": {
    "iso:country":"GB",
    "wof:name":"WR13 5DG",
    "wof:placetype":"postalcode"
},
  "geometry": {"coordinates":[-2.33049297049321,52.16844680350028],"type":"Point"}
}