{
  "type": "Feature",
  "properties": {
    "iso:country": "GB",
    "wof:name": "EH15 2JL",
    "wof:placetype": "postalcode"
  },
  "geometry": {"coordinates":[-3.093522,55.945801],"type":"Point"}
}
