{
  "type": "Feature",
  "properties": {
    "date:inception_lower": "1980-01-01",
    "date:inception_upper": "1980-01-01",
    "iso:country": "GB",
    "wof:name": "EH15 2JL",
    "wof:placetype": "postalcode"
  },
  "geometry": {"coordinates":[-3.093522,55.945801],"type":"Point"}
}
