{
  "type": "Feature",
  "properties": {
    "date:inception_lower":"1998-12-01",
    "date:inception_upper":"1998-12-31",
    "iso:country":"GB",
    "wof:name":"G78 4BB",
    "wof:placetype":"postalcode"
},
  "geometry": {"coordinates":[-4.498791,55.763638],"type":"Point"}
}