{
  "type": "Feature",
  "properties": {
    "iso:country":"GB",
    "wof:name":"AB24 4LG",
    "wof:placetype":"postalcode"
},
  "geometry": {"coordinates":[-2.13308475697922,57.16531085610308],"type":"Point"}
}