{
  "type": "Feature",
  "properties": {
    "iso:country": "GB",
    "wof:name": "AB24 4LG",
    "wof:placetype": "postalcode"
  },
  "geometry": {"coordinates":[-2.133085,57.165311],"type":"Point"}
}
