{
  "type": "Feature",
  "properties": {
    "iso:country":"GB",
    "wof:name":"PR1 4ST",
    "wof:placetype":"postalcode"
},
  "geometry": {"coordinates":[-2.67414109113365,53.7636781048841],"type":"Point"}
}