{
  "type": "Feature",
  "properties": {
    "iso:country": "GB",
    "wof:name": "ML11 7RB",
    "wof:placetype": "postalcode"
  },
  "geometry": {"coordinates":[-3.790063,55.68953],"type":"Point"}
}
