{
  "type": "Feature",
  "properties": {
    "iso:country":"GB",
    "wof:name":"ML11 7RB",
    "wof:placetype":"postalcode"
},
  "geometry": {"coordinates":[-3.79006320811218,55.68952952581595],"type":"Point"}
}