{
  "type": "Feature",
  "properties": {
    "date:inception_lower": "2020-07-01",
    "date:inception_upper": "2020-07-01",
    "iso:country": "GB",
    "wof:name": "NR21 9FE",
    "wof:placetype": "postalcode"
  },
  "geometry": {"coordinates":[0.719716,52.911303],"type":"Point"}
}
