{
  "type": "Feature",
  "properties": {
    "iso:country":"GB",
    "wof:name":"TR11 2LN",
    "wof:placetype":"postalcode"
},
  "geometry": {"coordinates":[-5.07558392138528,50.15895121132708],"type":"Point"}
}