{
  "type": "Feature",
  "properties": {
    "date:inception_lower": "1980-01-01",
    "date:inception_upper": "1980-01-01",
    "iso:country": "GB",
    "wof:name": "LS15 8PU",
    "wof:placetype": "postalcode"
  },
  "geometry": {"coordinates":[-1.436762,53.796844],"type":"Point"}
}
