{
  "type": "Feature",
  "properties": {
    "iso:country":"GB",
    "wof:name":"LS15 8PU",
    "wof:placetype":"postalcode"
},
  "geometry": {"coordinates":[-1.43676208349585,53.79684404963886],"type":"Point"}
}