{
  "type": "Feature",
  "properties": {
    "iso:country":"GB",
    "wof:name":"SL4 3NH",
    "wof:placetype":"postalcode"
},
  "geometry": {"coordinates":[-0.62391126187443,51.47294999818834],"type":"Point"}
}