{
  "type": "Feature",
  "properties": {
    "iso:country": "GB",
    "wof:name": "ML3 8AG",
    "wof:placetype": "postalcode"
  },
  "geometry": {"coordinates":[-4.054891,55.757108],"type":"Point"}
}
