{
  "type": "Feature",
  "properties": {
    "iso:country":"GB",
    "wof:name":"S42 5PQ",
    "wof:placetype":"postalcode"
},
  "geometry": {"coordinates":[-1.38181184288471,53.18145839782599],"type":"Point"}
}