{
  "type": "Feature",
  "properties": {
    "iso:country": "GB",
    "wof:name": "S42 5PQ",
    "wof:placetype": "postalcode"
  },
  "geometry": {"coordinates":[-1.381874,53.181226],"type":"Point"}
}
