{
  "type": "Feature",
  "properties": {
    "iso:country":"GB",
    "wof:name":"W4 5AR",
    "wof:placetype":"postalcode"
},
  "geometry": {"coordinates":[-0.26650317930421,51.50106937109981],"type":"Point"}
}