{
  "type": "Feature",
  "properties": {
    "date:inception_lower": "1998-12-01",
    "date:inception_upper": "1998-12-01",
    "iso:country": "GB",
    "wof:name": "CM2 0NP",
    "wof:placetype": "postalcode"
  },
  "geometry": {"coordinates":[0.463207,51.731465],"type":"Point"}
}
