{
  "type": "Feature",
  "properties": {
    "iso:country":"GB",
    "wof:name":"PL9 7QT",
    "wof:placetype":"postalcode"
},
  "geometry": {"coordinates":[-4.0977041588901,50.36310643788154],"type":"Point"}
}