{
  "type": "Feature",
  "properties": {
    "iso:country":"GB",
    "wof:name":"LE3 1ES",
    "wof:placetype":"postalcode"
},
  "geometry": {"coordinates":[-1.16976879042346,52.61867210914513],"type":"Point"}
}