{
  "type": "Feature",
  "properties": {
    "iso:country": "GB",
    "wof:name": "LE3 1ES",
    "wof:placetype": "postalcode"
  },
  "geometry": {"coordinates":[-1.169769,52.618672],"type":"Point"}
}
