{
  "type": "Feature",
  "properties": {
    "iso:country": "GB",
    "wof:name": "BA22 9EE",
    "wof:placetype": "postalcode"
  },
  "geometry": {"coordinates":[-2.719012,50.914662],"type":"Point"}
}
