{
  "type": "Feature",
  "properties": {
    "iso:country":"GB",
    "wof:name":"BA22 9EE",
    "wof:placetype":"postalcode"
},
  "geometry": {"coordinates":[-2.71903720777941,50.91453475413784],"type":"Point"}
}