{
  "type": "Feature",
  "properties": {
    "iso:country":"GB",
    "wof:name":"BH23 8JJ",
    "wof:placetype":"postalcode"
},
  "geometry": {"coordinates":[-1.73179792766507,50.77595316344332],"type":"Point"}
}