{
  "type": "Feature",
  "properties": {
    "iso:country":"GB",
    "wof:name":"SL5 0BS",
    "wof:placetype":"postalcode"
},
  "geometry": {"coordinates":[-0.64093077040373,51.39827105247146],"type":"Point"}
}