{
  "type": "Feature",
  "properties": {
    "iso:country":"GB",
    "wof:name":"AB56 4LD",
    "wof:placetype":"postalcode"
},
  "geometry": {"coordinates":[-2.86067449216609,57.70216486412509],"type":"Point"}
}