{
  "type": "Feature",
  "properties": {
    "date:inception_lower": "1998-06-01",
    "date:inception_upper": "1998-06-01",
    "iso:country": "GB",
    "wof:name": "CV23 0TG",
    "wof:placetype": "postalcode"
  },
  "geometry": {"coordinates":[-1.174393,52.386605],"type":"Point"}
}
