{
  "type": "Feature",
  "properties": {
    "iso:country":"GB",
    "wof:name":"CV23 0TG",
    "wof:placetype":"postalcode"
},
  "geometry": {"coordinates":[-1.17439255659144,52.38660535518644],"type":"Point"}
}