{
  "type": "Feature",
  "properties": {
    "iso:country": "GB",
    "wof:name": "OX4 1BN",
    "wof:placetype": "postalcode"
  },
  "geometry": {"coordinates":[-1.239855,51.749526],"type":"Point"}
}
