{
  "type": "Feature",
  "properties": {
    "iso:country":"GB",
    "wof:name":"OX4 1BN",
    "wof:placetype":"postalcode"
},
  "geometry": {"coordinates":[-1.23985539029655,51.74952598013878],"type":"Point"}
}