{
  "type": "Feature",
  "properties": {
    "date:inception_lower": "1980-01-01",
    "date:inception_upper": "1980-01-01",
    "iso:country": "GB",
    "wof:name": "OX4 1BN",
    "wof:placetype": "postalcode"
  },
  "geometry": {"coordinates":[-1.239879,51.749585],"type":"Point"}
}
