{
  "type": "Feature",
  "properties": {
    "date:inception_lower": "1996-12-01",
    "date:inception_upper": "1996-12-01",
    "iso:country": "GB",
    "wof:name": "DE24 3HS",
    "wof:placetype": "postalcode"
  },
  "geometry": {"coordinates":[-1.500306,52.879509],"type":"Point"}
}
