{
  "type": "Feature",
  "properties": {
    "iso:country":"GB",
    "wof:name":"SG6 3NN",
    "wof:placetype":"postalcode"
},
  "geometry": {"coordinates":[-0.23033297818665,51.96540274407948],"type":"Point"}
}