{
  "type": "Feature",
  "properties": {
    "iso:country":"GB",
    "wof:name":"CB24 8UW",
    "wof:placetype":"postalcode"
},
  "geometry": {"coordinates":[0.12086620344618,52.28350137512165],"type":"Point"}
}