{
  "type": "Feature",
  "properties": {
    "date:inception_lower": "1980-01-01",
    "date:inception_upper": "1980-01-01",
    "iso:country": "GB",
    "wof:name": "SG14 1BW",
    "wof:placetype": "postalcode"
  },
  "geometry": {"coordinates":[-0.077138,51.79653],"type":"Point"}
}
