{
  "type": "Feature",
  "properties": {
    "iso:country":"GB",
    "wof:name":"PE7 1JF",
    "wof:placetype":"postalcode"
},
  "geometry": {"coordinates":[-0.13425140470075,52.55590987799078],"type":"Point"}
}