{
  "type": "Feature",
  "properties": {
    "iso:country": "GB",
    "wof:name": "PE7 1JF",
    "wof:placetype": "postalcode"
  },
  "geometry": {"coordinates":[-0.134251,52.55591],"type":"Point"}
}
