{
  "type": "Feature",
  "properties": {
    "iso:country":"GB",
    "wof:name":"KY2 6SJ",
    "wof:placetype":"postalcode"
},
  "geometry": {"coordinates":[-3.19195812611115,56.1345421554178],"type":"Point"}
}