{
  "type": "Feature",
  "properties": {
    "date:inception_lower": "2005-03-01",
    "date:inception_upper": "2005-03-01",
    "iso:country": "GB",
    "wof:name": "KY2 6SJ",
    "wof:placetype": "postalcode"
  },
  "geometry": {"coordinates":[-3.191958,56.134542],"type":"Point"}
}
