{
  "type": "Feature",
  "properties": {
    "date:inception_lower": "2005-03-01",
    "date:inception_upper": "2005-03-01",
    "iso:country": "GB",
    "wof:name": "KA8 9FD",
    "wof:placetype": "postalcode"
  },
  "geometry": {"coordinates":[-4.620671,55.477686],"type":"Point"}
}
