{
  "type": "Feature",
  "properties": {
    "iso:country":"GB",
    "wof:name":"KA8 9FD",
    "wof:placetype":"postalcode"
},
  "geometry": {"coordinates":[-4.62067110619931,55.4776859653104],"type":"Point"}
}