{
  "type": "Feature",
  "properties": {
    "iso:country": "GB",
    "wof:name": "KA8 9FD",
    "wof:placetype": "postalcode"
  },
  "geometry": {"coordinates":[-4.620671,55.477686],"type":"Point"}
}
