{
  "type": "Feature",
  "properties": {
    "iso:country":"GB",
    "wof:name":"BD19 4AZ",
    "wof:placetype":"postalcode"
},
  "geometry": {"coordinates":[-1.69059719676338,53.74102548724733],"type":"Point"}
}