{
  "type": "Feature",
  "properties": {
    "date:inception_lower": "2012-12-01",
    "date:inception_upper": "2012-12-01",
    "iso:country": "GB",
    "wof:name": "YO10 5FE",
    "wof:placetype": "postalcode"
  },
  "geometry": {"coordinates":[-1.044049,53.944902],"type":"Point"}
}
