{
  "type": "Feature",
  "properties": {
    "iso:country": "GB",
    "wof:name": "YO10 5FE",
    "wof:placetype": "postalcode"
  },
  "geometry": {"coordinates":[-1.04371,53.945079],"type":"Point"}
}
