{
  "type": "Feature",
  "properties": {
    "iso:country":"GB",
    "wof:name":"YO10 5FE",
    "wof:placetype":"postalcode"
},
  "geometry": {"coordinates":[-1.04394924912376,53.94490948540429],"type":"Point"}
}