{
  "type": "Feature",
  "properties": {
    "date:inception_lower":"2002-10-01",
    "date:inception_upper":"2002-10-31",
    "iso:country":"GB",
    "wof:name":"LL29 9LQ",
    "wof:placetype":"postalcode"
},
  "geometry": {"coordinates":[-3.681392,53.291026],"type":"Point"}
}