{
  "type": "Feature",
  "properties": {
    "iso:country": "GB",
    "wof:name": "LL29 9LQ",
    "wof:placetype": "postalcode"
  },
  "geometry": {"coordinates":[-3.681392,53.291026],"type":"Point"}
}
