{
  "type": "Feature",
  "properties": {
    "iso:country": "GB",
    "wof:name": "SL0 9BX",
    "wof:placetype": "postalcode"
  },
  "geometry": {"coordinates":[-0.503939,51.517307],"type":"Point"}
}
