{
  "type": "Feature",
  "properties": {
    "date:inception_lower": "2018-01-01",
    "date:inception_upper": "2018-01-01",
    "iso:country": "GB",
    "wof:name": "SL0 9BX",
    "wof:placetype": "postalcode"
  },
  "geometry": {"coordinates":[-0.503939,51.517307],"type":"Point"}
}
