{
  "type": "Feature",
  "properties": {
    "iso:country":"GB",
    "wof:name":"NW8 9JP",
    "wof:placetype":"postalcode"
},
  "geometry": {"coordinates":[-0.17393740358282,51.53083253174223],"type":"Point"}
}