{
  "type": "Feature",
  "properties": {
    "iso:country": "GB",
    "wof:name": "KT8 1PH",
    "wof:placetype": "postalcode"
  },
  "geometry": {"coordinates":[-0.360461,51.40533],"type":"Point"}
}
