{
  "type": "Feature",
  "properties": {
    "date:inception_lower": "1991-09-01",
    "date:inception_upper": "1991-09-01",
    "iso:country": "GB",
    "wof:name": "KT8 1PH",
    "wof:placetype": "postalcode"
  },
  "geometry": {"coordinates":[-0.360461,51.40533],"type":"Point"}
}
