{
  "type": "Feature",
  "properties": {
    "iso:country":"GB",
    "wof:name":"WF9 2DJ",
    "wof:placetype":"postalcode"
},
  "geometry": {"coordinates":[-1.27768118588629,53.59993855878515],"type":"Point"}
}