{
  "type": "Feature",
  "properties": {
    "iso:country": "GB",
    "wof:name": "WF9 2DJ",
    "wof:placetype": "postalcode"
  },
  "geometry": {"coordinates":[-1.277681,53.599939],"type":"Point"}
}
