{
  "type": "Feature",
  "properties": {
    "iso:country":"GB",
    "wof:name":"PR3 1JA",
    "wof:placetype":"postalcode"
},
  "geometry": {"coordinates":[-2.77318698752131,53.90648589348042],"type":"Point"}
}