{
  "type": "Feature",
  "properties": {
    "date:inception_lower": "2015-01-01",
    "date:inception_upper": "2015-01-01",
    "iso:country": "GB",
    "wof:name": "NN10 0TA",
    "wof:placetype": "postalcode"
  },
  "geometry": {"coordinates":[-0.581851,52.285697],"type":"Point"}
}
