{
  "type": "Feature",
  "properties": {
    "iso:country": "GB",
    "wof:name": "E2 0LF",
    "wof:placetype": "postalcode"
  },
  "geometry": {"coordinates":[-0.052943,51.524795],"type":"Point"}
}
