{
  "type": "Feature",
  "properties": {
    "iso:country":"GB",
    "wof:name":"BR3 3QQ",
    "wof:placetype":"postalcode"
},
  "geometry": {"coordinates":[-0.03734991243249,51.39884415146495],"type":"Point"}
}