{
  "type": "Feature",
  "properties": {
    "iso:country":"GB",
    "wof:name":"PL19 9RD",
    "wof:placetype":"postalcode"
},
  "geometry": {"coordinates":[-4.13546830405383,50.54537111305697],"type":"Point"}
}