{
  "type": "Feature",
  "properties": {
    "iso:country": "GB",
    "wof:name": "PL19 9RD",
    "wof:placetype": "postalcode"
  },
  "geometry": {"coordinates":[-4.135468,50.545371],"type":"Point"}
}
