{
  "type": "Feature",
  "properties": {
    "iso:country":"GB",
    "wof:name":"NR6 6RG",
    "wof:placetype":"postalcode"
},
  "geometry": {"coordinates":[1.28390905343743,52.6567041536759],"type":"Point"}
}