{
  "type": "Feature",
  "properties": {
    "iso:country": "GB",
    "wof:name": "NR6 6RG",
    "wof:placetype": "postalcode"
  },
  "geometry": {"coordinates":[1.283909,52.656704],"type":"Point"}
}
