{
  "type": "Feature",
  "properties": {
    "iso:country":"GB",
    "wof:name":"SA5 7HJ",
    "wof:placetype":"postalcode"
},
  "geometry": {"coordinates":[-3.96209757142238,51.65710323657809],"type":"Point"}
}