{
  "type": "Feature",
  "properties": {
    "iso:country": "GB",
    "wof:name": "SA5 7HJ",
    "wof:placetype": "postalcode"
  },
  "geometry": {"coordinates":[-3.962098,51.657103],"type":"Point"}
}
