{
  "type": "Feature",
  "properties": {
    "iso:country":"GB",
    "wof:name":"BH19 2JA",
    "wof:placetype":"postalcode"
},
  "geometry": {"coordinates":[-1.95723167191709,50.60192926937204],"type":"Point"}
}