{
  "type": "Feature",
  "properties": {
    "iso:country":"GB",
    "wof:name":"RG4 7HZ",
    "wof:placetype":"postalcode"
},
  "geometry": {"coordinates":[-0.99373069591263,51.4854640018206],"type":"Point"}
}