{
  "type": "Feature",
  "properties": {
    "iso:country":"GB",
    "wof:name":"DH7 8NT",
    "wof:placetype":"postalcode"
},
  "geometry": {"coordinates":[-1.62090230441495,54.75082317153728],"type":"Point"}
}