{
  "type": "Feature",
  "properties": {
    "date:inception_lower":"2012-09-01",
    "date:inception_upper":"2012-09-30",
    "iso:country":"GB",
    "wof:name":"DH7 8NT",
    "wof:placetype":"postalcode"
},
  "geometry": {"coordinates":[-1.620902,54.750823],"type":"Point"}
}