{
  "type": "Feature",
  "properties": {
    "iso:country": "GB",
    "wof:name": "SN7 7UQ",
    "wof:placetype": "postalcode"
  },
  "geometry": {"coordinates":[-1.58453,51.65097],"type":"Point"}
}
