{
  "type": "Feature",
  "properties": {
    "date:inception_lower": "1980-01-01",
    "date:inception_upper": "1980-01-01",
    "iso:country": "GB",
    "wof:name": "SN7 7UQ",
    "wof:placetype": "postalcode"
  },
  "geometry": {"coordinates":[-1.58453,51.65097],"type":"Point"}
}
