{
  "type": "Feature",
  "properties": {
    "date:inception_lower": "2016-05-01",
    "date:inception_upper": "2016-05-01",
    "iso:country": "GB",
    "wof:name": "LN11 9DP",
    "wof:placetype": "postalcode"
  },
  "geometry": {"coordinates":[0.007155,53.363974],"type":"Point"}
}
