{
  "type": "Feature",
  "properties": {
    "iso:country":"GB",
    "wof:name":"NE61 4AW",
    "wof:placetype":"postalcode"
},
  "geometry": {"coordinates":[-1.95597023963502,55.15301931366918],"type":"Point"}
}