{
  "type": "Feature",
  "properties": {
    "iso:country": "GB",
    "wof:name": "S41 0UG",
    "wof:placetype": "postalcode"
  },
  "geometry": {"coordinates":[-1.415637,53.252346],"type":"Point"}
}
