{
  "type": "Feature",
  "properties": {
    "iso:country":"GB",
    "wof:name":"SP4 7PJ",
    "wof:placetype":"postalcode"
},
  "geometry": {"coordinates":[-1.7696965125781,51.17326852427421],"type":"Point"}
}