{
  "type": "Feature",
  "properties": {
    "iso:country": "GB",
    "wof:name": "SP4 7PJ",
    "wof:placetype": "postalcode"
  },
  "geometry": {"coordinates":[-1.769696,51.173269],"type":"Point"}
}
