{
  "type": "Feature",
  "properties": {
    "date:inception_lower": "2021-05-01",
    "date:inception_upper": "2021-05-01",
    "iso:country": "GB",
    "wof:name": "WN6 0FH",
    "wof:placetype": "postalcode"
  },
  "geometry": {"coordinates":[-2.661339,53.584142],"type":"Point"}
}
