{
  "type": "Feature",
  "properties": {
    "iso:country":"GB",
    "wof:name":"B64 6EG",
    "wof:placetype":"postalcode"
},
  "geometry": {"coordinates":[-2.06826482827833,52.47278639242159],"type":"Point"}
}