{
  "type": "Feature",
  "properties": {
    "iso:country": "GB",
    "wof:name": "B64 6EG",
    "wof:placetype": "postalcode"
  },
  "geometry": {"coordinates":[-2.068265,52.472786],"type":"Point"}
}
