{
  "type": "Feature",
  "properties": {
    "date:inception_lower": "2012-12-01",
    "date:inception_upper": "2012-12-01",
    "iso:country": "GB",
    "wof:name": "BB7 9GX",
    "wof:placetype": "postalcode"
  },
  "geometry": {"coordinates":[-2.398786,53.839224],"type":"Point"}
}
