{
  "type": "Feature",
  "properties": {
    "iso:country":"GB",
    "wof:name":"BD21 2HB",
    "wof:placetype":"postalcode"
},
  "geometry": {"coordinates":[-1.91656432222591,53.86964430733601],"type":"Point"}
}