{
  "type": "Feature",
  "properties": {
    "iso:country": "GB",
    "wof:name": "EH41 3TG",
    "wof:placetype": "postalcode"
  },
  "geometry": {"coordinates":[-2.805693,55.954863],"type":"Point"}
}
