{
  "type": "Feature",
  "properties": {
    "date:inception_lower": "2016-06-01",
    "date:inception_upper": "2016-06-01",
    "iso:country": "GB",
    "wof:name": "EH41 3TG",
    "wof:placetype": "postalcode"
  },
  "geometry": {"coordinates":[-2.805693,55.954863],"type":"Point"}
}
