{
  "type": "Feature",
  "properties": {
    "iso:country":"GB",
    "wof:name":"M15 4AY",
    "wof:placetype":"postalcode"
},
  "geometry": {"coordinates":[-2.25550655615734,53.46601116892558],"type":"Point"}
}