{
  "type": "Feature",
  "properties": {
    "iso:country":"GB",
    "wof:name":"SA18 1YG",
    "wof:placetype":"postalcode"
},
  "geometry": {"coordinates":[-3.85767492051852,51.79319069863471],"type":"Point"}
}