{
  "type": "Feature",
  "properties": {
    "iso:country": "GB",
    "wof:name": "AB54 4JR",
    "wof:placetype": "postalcode"
  },
  "geometry": {"coordinates":[-2.870961,57.279114],"type":"Point"}
}
