{
  "type": "Feature",
  "properties": {
    "iso:country":"GB",
    "wof:name":"AB54 4JR",
    "wof:placetype":"postalcode"
},
  "geometry": {"coordinates":[-2.87096102589709,57.27911416575878],"type":"Point"}
}