{
  "type": "Feature",
  "properties": {
    "iso:country":"GB",
    "wof:name":"BD5 0QZ",
    "wof:placetype":"postalcode"
},
  "geometry": {"coordinates":[-1.75413096227648,53.78645421828081],"type":"Point"}
}