{
  "type": "Feature",
  "properties": {
    "iso:country":"GB",
    "wof:name":"HR2 6BB",
    "wof:placetype":"postalcode"
},
  "geometry": {"coordinates":[-2.71282954626309,52.04439183725392],"type":"Point"}
}