{
  "type": "Feature",
  "properties": {
    "iso:country":"GB",
    "wof:name":"RH13 8DB",
    "wof:placetype":"postalcode"
},
  "geometry": {"coordinates":[-0.27671354687842,50.9913499317183],"type":"Point"}
}