{
  "type": "Feature",
  "properties": {
    "date:inception_lower": "1980-01-01",
    "date:inception_upper": "1980-01-01",
    "iso:country": "GB",
    "wof:name": "RH13 8DB",
    "wof:placetype": "postalcode"
  },
  "geometry": {"coordinates":[-0.276714,50.99135],"type":"Point"}
}
