{
  "type": "Feature",
  "properties": {
    "iso:country":"GB",
    "wof:name":"DG1 4AQ",
    "wof:placetype":"postalcode"
},
  "geometry": {"coordinates":[-3.60025375389057,55.06135586607741],"type":"Point"}
}