{
  "type": "Feature",
  "properties": {
    "date:inception_lower": "1980-01-01",
    "date:inception_upper": "1980-01-01",
    "iso:country": "GB",
    "wof:name": "DG1 4AQ",
    "wof:placetype": "postalcode"
  },
  "geometry": {"coordinates":[-3.600266,55.061361],"type":"Point"}
}
