{
  "type": "Feature",
  "properties": {
    "iso:country":"GB",
    "wof:name":"NG24 2EZ",
    "wof:placetype":"postalcode"
},
  "geometry": {"coordinates":[-0.79667163794313,53.08346817108335],"type":"Point"}
}