{
  "type": "Feature",
  "properties": {
    "iso:country": "GB",
    "wof:name": "NG24 2EZ",
    "wof:placetype": "postalcode"
  },
  "geometry": {"coordinates":[-0.796672,53.083468],"type":"Point"}
}
