{
  "type": "Feature",
  "properties": {
    "iso:country": "GB",
    "wof:name": "TN34 3EP",
    "wof:placetype": "postalcode"
  },
  "geometry": {"coordinates":[0.592046,50.85814],"type":"Point"}
}
