{
  "type": "Feature",
  "properties": {
    "date:inception_lower":"1980-01-01",
    "date:inception_upper":"1980-01-31",
    "iso:country":"GB",
    "wof:name":"TN34 3EP",
    "wof:placetype":"postalcode"
},
  "geometry": {"coordinates":[0.592046,50.85814],"type":"Point"}
}