{
  "type": "Feature",
  "properties": {
    "iso:country": "GB",
    "wof:name": "L36 5AB",
    "wof:placetype": "postalcode"
  },
  "geometry": {"coordinates":[-2.830296,53.407612],"type":"Point"}
}
