{
  "type": "Feature",
  "properties": {
    "iso:country":"GB",
    "wof:name":"ST5 2JT",
    "wof:placetype":"postalcode"
},
  "geometry": {"coordinates":[-2.24328050657756,53.00761549893155],"type":"Point"}
}