{
  "type": "Feature",
  "properties": {
    "iso:country": "GB",
    "wof:name": "NG4 3FS",
    "wof:placetype": "postalcode"
  },
  "geometry": {"coordinates":[-1.078411,52.970785],"type":"Point"}
}
