{
  "type": "Feature",
  "properties": {
    "iso:country": "GB",
    "wof:name": "FY8 3SP",
    "wof:placetype": "postalcode"
  },
  "geometry": {"coordinates":[-3.010669,53.755416],"type":"Point"}
}
