{
  "type": "Feature",
  "properties": {
    "iso:country":"GB",
    "wof:name":"FY8 3SP",
    "wof:placetype":"postalcode"
},
  "geometry": {"coordinates":[-3.01066885417653,53.75541611528165],"type":"Point"}
}