{
  "type": "Feature",
  "properties": {
    "iso:country":"GB",
    "wof:name":"SK6 8BN",
    "wof:placetype":"postalcode"
},
  "geometry": {"coordinates":[-2.07326137317506,53.3631727409714],"type":"Point"}
}