{
  "type": "Feature",
  "properties": {
    "date:inception_lower": "1980-01-01",
    "date:inception_upper": "1980-01-01",
    "iso:country": "GB",
    "wof:name": "SK6 8BN",
    "wof:placetype": "postalcode"
  },
  "geometry": {"coordinates":[-2.073261,53.363173],"type":"Point"}
}
