{
  "type": "Feature",
  "properties": {
    "iso:country": "GB",
    "wof:name": "SK6 8BN",
    "wof:placetype": "postalcode"
  },
  "geometry": {"coordinates":[-2.073261,53.363173],"type":"Point"}
}
