{
  "type": "Feature",
  "properties": {
    "date:inception_lower": "1987-10-01",
    "date:inception_upper": "1987-10-01",
    "iso:country": "GB",
    "wof:name": "HA3 0PP",
    "wof:placetype": "postalcode"
  },
  "geometry": {"coordinates":[-0.296493,51.57559],"type":"Point"}
}
