{
  "type": "Feature",
  "properties": {
    "iso:country":"GB",
    "wof:name":"KT1 2TA",
    "wof:placetype":"postalcode"
},
  "geometry": {"coordinates":[-0.30282121716335,51.40610111712609],"type":"Point"}
}