{
  "type": "Feature",
  "properties": {
    "iso:country": "GB",
    "wof:name": "WN8 7TA",
    "wof:placetype": "postalcode"
  },
  "geometry": {"coordinates":[-2.759131,53.592499],"type":"Point"}
}
