{
  "type": "Feature",
  "properties": {
    "iso:country":"GB",
    "wof:name":"WN8 7TA",
    "wof:placetype":"postalcode"
},
  "geometry": {"coordinates":[-2.75913142901181,53.59249866466291],"type":"Point"}
}