{
  "type": "Feature",
  "properties": {
    "iso:country": "GB",
    "wof:name": "AB30 1NF",
    "wof:placetype": "postalcode"
  },
  "geometry": {"coordinates":[-2.413278,56.873022],"type":"Point"}
}
