{
  "type": "Feature",
  "properties": {
    "iso:country":"GB",
    "wof:name":"B24 8QH",
    "wof:placetype":"postalcode"
},
  "geometry": {"coordinates":[-1.84632240189134,52.51458193715243],"type":"Point"}
}