{
  "type": "Feature",
  "properties": {
    "date:inception_lower":"1980-01-01",
    "date:inception_upper":"1980-01-31",
    "iso:country":"GB",
    "wof:name":"RH8 0QS",
    "wof:placetype":"postalcode"
},
  "geometry": {"coordinates":[0.008653,51.251983],"type":"Point"}
}