{
  "type": "Feature",
  "properties": {
    "date:inception_lower": "1980-01-01",
    "date:inception_upper": "1980-01-01",
    "iso:country": "GB",
    "wof:name": "DH3 2DT",
    "wof:placetype": "postalcode"
  },
  "geometry": {"coordinates":[-1.567467,54.885487],"type":"Point"}
}
