{
  "type": "Feature",
  "properties": {
    "iso:country":"GB",
    "wof:name":"DH3 2DT",
    "wof:placetype":"postalcode"
},
  "geometry": {"coordinates":[-1.56746694401916,54.88548709825729],"type":"Point"}
}