{
  "type": "Feature",
  "properties": {
    "iso:country":"GB",
    "wof:name":"IP18 6XA",
    "wof:placetype":"postalcode"
},
  "geometry": {"coordinates":[1.67445008151428,52.34060120517046],"type":"Point"}
}