{
  "type": "Feature",
  "properties": {
    "iso:country": "GB",
    "wof:name": "TF1 3QR",
    "wof:placetype": "postalcode"
  },
  "geometry": {"coordinates":[-2.526244,52.714173],"type":"Point"}
}
