{
  "type": "Feature",
  "properties": {
    "iso:country":"GB",
    "wof:name":"TF1 3QR",
    "wof:placetype":"postalcode"
},
  "geometry": {"coordinates":[-2.52624383933145,52.71417274955206],"type":"Point"}
}