{
  "type": "Feature",
  "properties": {
    "date:inception_lower":"1980-01-01",
    "date:inception_upper":"1980-01-31",
    "iso:country":"GB",
    "wof:name":"SY21 0JH",
    "wof:placetype":"postalcode"
},
  "geometry": {"coordinates":[-3.490762,52.653639],"type":"Point"}
}