{
  "type": "Feature",
  "properties": {
    "iso:country": "GB",
    "wof:name": "SY21 0JH",
    "wof:placetype": "postalcode"
  },
  "geometry": {"coordinates":[-3.490762,52.653639],"type":"Point"}
}
