{
  "type": "Feature",
  "properties": {
    "date:inception_lower": "1987-10-01",
    "date:inception_upper": "1987-10-01",
    "iso:country": "GB",
    "wof:name": "RG6 4ED",
    "wof:placetype": "postalcode"
  },
  "geometry": {"coordinates":[-0.920778,51.422232],"type":"Point"}
}
