{
  "type": "Feature",
  "properties": {
    "iso:country":"GB",
    "wof:name":"RH2 9EG",
    "wof:placetype":"postalcode"
},
  "geometry": {"coordinates":[-0.21323520163813,51.24276619014563],"type":"Point"}
}