{
  "type": "Feature",
  "properties": {
    "date:inception_lower":"1980-01-01",
    "date:inception_upper":"1980-01-31",
    "iso:country":"GB",
    "wof:name":"RH2 9EG",
    "wof:placetype":"postalcode"
},
  "geometry": {"coordinates":[-0.213235,51.242766],"type":"Point"}
}