{
  "type": "Feature",
  "properties": {
    "iso:country":"GB",
    "wof:name":"WS10 7HZ",
    "wof:placetype":"postalcode"
},
  "geometry": {"coordinates":[-2.02686065968117,52.55750600877762],"type":"Point"}
}