{
  "type": "Feature",
  "properties": {
    "iso:country": "GB",
    "wof:name": "YO10 4UZ",
    "wof:placetype": "postalcode"
  },
  "geometry": {"coordinates":[-1.07375,53.955246],"type":"Point"}
}
