{
  "type": "Feature",
  "properties": {
    "iso:country":"GB",
    "wof:name":"YO7 3HA",
    "wof:placetype":"postalcode"
},
  "geometry": {"coordinates":[-1.34425335549292,54.17994856245841],"type":"Point"}
}