{
  "type": "Feature",
  "properties": {
    "date:inception_lower": "2005-06-01",
    "date:inception_upper": "2005-06-01",
    "iso:country": "GB",
    "wof:name": "YO7 3HA",
    "wof:placetype": "postalcode"
  },
  "geometry": {"coordinates":[-1.344193,54.179867],"type":"Point"}
}
