{
  "type": "Feature",
  "properties": {
    "iso:country":"GB",
    "wof:name":"PR9 0UE",
    "wof:placetype":"postalcode"
},
  "geometry": {"coordinates":[-3.00367951200937,53.64797225476426],"type":"Point"}
}