{
  "type": "Feature",
  "properties": {
    "iso:country": "GB",
    "wof:name": "SS4 1JA",
    "wof:placetype": "postalcode"
  },
  "geometry": {"coordinates":[0.707774,51.571285],"type":"Point"}
}
