{
  "type": "Feature",
  "properties": {
    "iso:country":"GB",
    "wof:name":"SS4 1JA",
    "wof:placetype":"postalcode"
},
  "geometry": {"coordinates":[0.70777413637798,51.57128514146127],"type":"Point"}
}