{
  "type": "Feature",
  "properties": {
    "iso:country":"GB",
    "wof:name":"B49 6DH",
    "wof:placetype":"postalcode"
},
  "geometry": {"coordinates":[-1.86307399537621,52.1965757401197],"type":"Point"}
}