{
  "type": "Feature",
  "properties": {
    "iso:country": "GB",
    "wof:name": "B49 6DH",
    "wof:placetype": "postalcode"
  },
  "geometry": {"coordinates":[-1.863652,52.196194],"type":"Point"}
}
