{
  "type": "Feature",
  "properties": {
    "date:inception_lower": "1980-01-01",
    "date:inception_upper": "1980-01-01",
    "iso:country": "GB",
    "wof:name": "B49 6DH",
    "wof:placetype": "postalcode"
  },
  "geometry": {"coordinates":[-1.863066,52.196589],"type":"Point"}
}
