{
  "type": "Feature",
  "properties": {
    "iso:country": "GB",
    "wof:name": "SO14 1TA",
    "wof:placetype": "postalcode"
  },
  "geometry": {"coordinates":[-1.394631,50.906819],"type":"Point"}
}
