{
  "type": "Feature",
  "properties": {
    "date:inception_lower": "1980-01-01",
    "date:inception_upper": "1980-01-01",
    "iso:country": "GB",
    "wof:name": "IG10 3ES",
    "wof:placetype": "postalcode"
  },
  "geometry": {"coordinates":[0.068647,51.640913],"type":"Point"}
}
