{
  "type": "Feature",
  "properties": {
    "iso:country":"GB",
    "wof:name":"LE5 4PX",
    "wof:placetype":"postalcode"
},
  "geometry": {"coordinates":[-1.09359175833193,52.63096965859415],"type":"Point"}
}