{
  "type": "Feature",
  "properties": {
    "iso:country":"GB",
    "wof:name":"GU34 5LB",
    "wof:placetype":"postalcode"
},
  "geometry": {"coordinates":[-1.05642863582276,51.15217474011171],"type":"Point"}
}