{
  "type": "Feature",
  "properties": {
    "date:inception_lower": "2011-03-01",
    "date:inception_upper": "2011-03-01",
    "iso:country": "GB",
    "wof:name": "LN5 9LW",
    "wof:placetype": "postalcode"
  },
  "geometry": {"coordinates":[-0.64438,53.124424],"type":"Point"}
}
