{
  "type": "Feature",
  "properties": {
    "iso:country":"GB",
    "wof:name":"LN5 9LW",
    "wof:placetype":"postalcode"
},
  "geometry": {"coordinates":[-0.64438028128964,53.12442432314934],"type":"Point"}
}