{
  "type": "Feature",
  "properties": {
    "date:inception_lower": "1980-01-01",
    "date:inception_upper": "1980-01-01",
    "iso:country": "GB",
    "wof:name": "E11 4RD",
    "wof:placetype": "postalcode"
  },
  "geometry": {"coordinates":[0.009615,51.563892],"type":"Point"}
}
