{
  "type": "Feature",
  "properties": {
    "iso:country":"GB",
    "wof:name":"SR4 9AB",
    "wof:placetype":"postalcode"
},
  "geometry": {"coordinates":[-1.44297600457853,54.89939466738547],"type":"Point"}
}