{
  "type": "Feature",
  "properties": {
    "iso:country": "GB",
    "wof:name": "WV16 5LZ",
    "wof:placetype": "postalcode"
  },
  "geometry": {"coordinates":[-2.4494,52.535304],"type":"Point"}
}
