{
  "type": "Feature",
  "properties": {
    "iso:country":"GB",
    "wof:name":"WV16 5LZ",
    "wof:placetype":"postalcode"
},
  "geometry": {"coordinates":[-2.44940031357053,52.53530417276745],"type":"Point"}
}