{
  "type": "Feature",
  "properties": {
    "iso:country":"GB",
    "wof:name":"SE3 0XQ",
    "wof:placetype":"postalcode"
},
  "geometry": {"coordinates":[-0.00225682448602,51.46580485697752],"type":"Point"}
}