{
  "type": "Feature",
  "properties": {
    "iso:country":"GB",
    "wof:name":"NW3 2PT",
    "wof:placetype":"postalcode"
},
  "geometry": {"coordinates":[-0.16593725224556,51.55446574275862],"type":"Point"}
}