{
  "type": "Feature",
  "properties": {
    "iso:country": "GB",
    "wof:name": "N1 3QG",
    "wof:placetype": "postalcode"
  },
  "geometry": {"coordinates":[-0.087576,51.545283],"type":"Point"}
}
