{
  "type": "Feature",
  "properties": {
    "iso:country":"GB",
    "wof:name":"N1 3QG",
    "wof:placetype":"postalcode"
},
  "geometry": {"coordinates":[-0.08757578628183,51.54528321986867],"type":"Point"}
}