{
  "type": "Feature",
  "properties": {
    "date:inception_lower":"1990-02-01",
    "date:inception_upper":"1990-02-28",
    "iso:country":"GB",
    "wof:name":"N1 3QG",
    "wof:placetype":"postalcode"
},
  "geometry": {"coordinates":[-0.087576,51.545283],"type":"Point"}
}