{
  "type": "Feature",
  "properties": {
    "date:inception_lower": "2021-01-01",
    "date:inception_upper": "2021-01-01",
    "iso:country": "GB",
    "wof:name": "SL2 2DW",
    "wof:placetype": "postalcode"
  },
  "geometry": {"coordinates":[-0.629696,51.53636],"type":"Point"}
}
