{
  "type": "Feature",
  "properties": {
    "iso:country": "GB",
    "wof:name": "AL3 8BS",
    "wof:placetype": "postalcode"
  },
  "geometry": {"coordinates":[-0.435989,51.819628],"type":"Point"}
}
