{
  "type": "Feature",
  "properties": {
    "iso:country":"GB",
    "wof:name":"AL3 8BS",
    "wof:placetype":"postalcode"
},
  "geometry": {"coordinates":[-0.4359888045201,51.81962798794299],"type":"Point"}
}