{
  "type": "Feature",
  "properties": {
    "date:inception_lower": "1980-01-01",
    "date:inception_upper": "1980-01-01",
    "iso:country": "GB",
    "wof:name": "W14 9TL",
    "wof:placetype": "postalcode"
  },
  "geometry": {"coordinates":[-0.208622,51.485147],"type":"Point"}
}
