{
  "type": "Feature",
  "properties": {
    "iso:country":"GB",
    "wof:name":"W14 9TL",
    "wof:placetype":"postalcode"
},
  "geometry": {"coordinates":[-0.20864531429409,51.48514654697127],"type":"Point"}
}