{
  "type": "Feature",
  "properties": {
    "iso:country":"GB",
    "wof:name":"TN1 2SW",
    "wof:placetype":"postalcode"
},
  "geometry": {"coordinates":[0.26756942149061,51.13547318030493],"type":"Point"}
}