{
  "type": "Feature",
  "properties": {
    "date:inception_lower": "2017-05-01",
    "date:inception_upper": "2017-05-01",
    "iso:country": "GB",
    "wof:name": "CA11 7UD",
    "wof:placetype": "postalcode"
  },
  "geometry": {"coordinates":[-2.753351,54.666052],"type":"Point"}
}
