{
  "type": "Feature",
  "properties": {
    "iso:country": "GB",
    "wof:name": "CA11 7UD",
    "wof:placetype": "postalcode"
  },
  "geometry": {"coordinates":[-2.753445,54.66606],"type":"Point"}
}
