{
  "type": "Feature",
  "properties": {
    "iso:country": "GB",
    "wof:name": "WA6 6RG",
    "wof:placetype": "postalcode"
  },
  "geometry": {"coordinates":[-2.719686,53.291684],"type":"Point"}
}
