{
  "type": "Feature",
  "properties": {
    "date:inception_lower":"2010-05-01",
    "date:inception_upper":"2010-05-31",
    "iso:country":"GB",
    "wof:name":"G73 5AD",
    "wof:placetype":"postalcode"
},
  "geometry": {"coordinates":[-4.199201,55.817],"type":"Point"}
}