{
  "type": "Feature",
  "properties": {
    "iso:country": "GB",
    "wof:name": "G73 5AD",
    "wof:placetype": "postalcode"
  },
  "geometry": {"coordinates":[-4.199201,55.817],"type":"Point"}
}
