{
  "type": "Feature",
  "properties": {
    "date:inception_lower": "2009-10-01",
    "date:inception_upper": "2009-10-01",
    "iso:country": "GB",
    "wof:name": "BB11 3NP",
    "wof:placetype": "postalcode"
  },
  "geometry": {"coordinates":[-2.233743,53.780923],"type":"Point"}
}
