{
  "type": "Feature",
  "properties": {
    "date:inception_lower":"1980-01-01",
    "date:inception_upper":"1980-01-31",
    "iso:country":"GB",
    "wof:name":"NR16 1PQ",
    "wof:placetype":"postalcode"
},
  "geometry": {"coordinates":[1.095507,52.454632],"type":"Point"}
}