{
  "type": "Feature",
  "properties": {
    "iso:country":"GB",
    "wof:name":"NR16 1PQ",
    "wof:placetype":"postalcode"
},
  "geometry": {"coordinates":[1.0947640307397,52.45426150070382],"type":"Point"}
}