{
  "type": "Feature",
  "properties": {
    "iso:country":"GB",
    "wof:name":"DN3 2NH",
    "wof:placetype":"postalcode"
},
  "geometry": {"coordinates":[-1.06748923337251,53.55513343541907],"type":"Point"}
}