{
  "type": "Feature",
  "properties": {
    "iso:country": "GB",
    "wof:name": "DN3 2NH",
    "wof:placetype": "postalcode"
  },
  "geometry": {"coordinates":[-1.067489,53.555133],"type":"Point"}
}
