{
  "type": "Feature",
  "properties": {
    "iso:country": "GB",
    "wof:name": "MK6 4AE",
    "wof:placetype": "postalcode"
  },
  "geometry": {"coordinates":[-0.746754,52.011853],"type":"Point"}
}
