{
  "type": "Feature",
  "properties": {
    "iso:country":"GB",
    "wof:name":"L14 3LF",
    "wof:placetype":"postalcode"
},
  "geometry": {"coordinates":[-2.89570810173953,53.4099816812688],"type":"Point"}
}