{
  "type": "Feature",
  "properties": {
    "iso:country":"GB",
    "wof:name":"N3 2SJ",
    "wof:placetype":"postalcode"
},
  "geometry": {"coordinates":[-0.19208013404759,51.59980630447034],"type":"Point"}
}