{
  "type": "Feature",
  "properties": {
    "iso:country": "GB",
    "wof:name": "CH42 0JZ",
    "wof:placetype": "postalcode"
  },
  "geometry": {"coordinates":[-3.031292,53.382334],"type":"Point"}
}
