{
  "type": "Feature",
  "properties": {
    "iso:country":"GB",
    "wof:name":"CH42 0JZ",
    "wof:placetype":"postalcode"
},
  "geometry": {"coordinates":[-3.03129175329515,53.38233397397966],"type":"Point"}
}