{
  "type": "Feature",
  "properties": {
    "iso:country": "GB",
    "wof:name": "KT13 8PB",
    "wof:placetype": "postalcode"
  },
  "geometry": {"coordinates":[-0.456705,51.37457],"type":"Point"}
}
