{
  "type": "Feature",
  "properties": {
    "iso:country":"GB",
    "wof:name":"KT13 8PB",
    "wof:placetype":"postalcode"
},
  "geometry": {"coordinates":[-0.45670512252959,51.37457012977387],"type":"Point"}
}