{
  "type": "Feature",
  "properties": {
    "iso:country":"GB",
    "wof:name":"HD2 1RX",
    "wof:placetype":"postalcode"
},
  "geometry": {"coordinates":[-1.75328867022126,53.68148074442716],"type":"Point"}
}