{
  "type": "Feature",
  "properties": {
    "iso:country": "GB",
    "wof:name": "HD2 1RX",
    "wof:placetype": "postalcode"
  },
  "geometry": {"coordinates":[-1.75329,53.68155],"type":"Point"}
}
