{
  "type": "Feature",
  "properties": {
    "iso:country": "GB",
    "wof:name": "TD9 9EW",
    "wof:placetype": "postalcode"
  },
  "geometry": {"coordinates":[-2.786822,55.42111],"type":"Point"}
}
