{
  "type": "Feature",
  "properties": {
    "date:inception_lower":"1980-01-01",
    "date:inception_upper":"1980-01-31",
    "iso:country":"GB",
    "wof:name":"TD9 9EW",
    "wof:placetype":"postalcode"
},
  "geometry": {"coordinates":[-2.786822,55.42111],"type":"Point"}
}