{
  "type": "Feature",
  "properties": {
    "iso:country": "GB",
    "wof:name": "TF10 9DX",
    "wof:placetype": "postalcode"
  },
  "geometry": {"coordinates":[-2.322538,52.749845],"type":"Point"}
}
