{
  "type": "Feature",
  "properties": {
    "iso:country":"GB",
    "wof:name":"TF10 9DX",
    "wof:placetype":"postalcode"
},
  "geometry": {"coordinates":[-2.32253770348235,52.74984486442477],"type":"Point"}
}