{
  "type": "Feature",
  "properties": {
    "date:inception_lower":"1980-01-01",
    "date:inception_upper":"1980-01-31",
    "iso:country":"GB",
    "wof:name":"TF10 9DX",
    "wof:placetype":"postalcode"
},
  "geometry": {"coordinates":[-2.322538,52.749845],"type":"Point"}
}