{
  "type": "Feature",
  "properties": {
    "iso:country":"GB",
    "wof:name":"RG9 5RL",
    "wof:placetype":"postalcode"
},
  "geometry": {"coordinates":[-1.00721222945369,51.57688978136531],"type":"Point"}
}