{
  "type": "Feature",
  "properties": {
    "iso:country": "GB",
    "wof:name": "RG9 5RL",
    "wof:placetype": "postalcode"
  },
  "geometry": {"coordinates":[-1.007212,51.57689],"type":"Point"}
}
