{
  "type": "Feature",
  "properties": {
    "iso:country":"GB",
    "wof:name":"EN8 8TA",
    "wof:placetype":"postalcode"
},
  "geometry": {"coordinates":[-0.03185582959842,51.69800730302474],"type":"Point"}
}