{
  "type": "Feature",
  "properties": {
    "iso:country": "GB",
    "wof:name": "IP24 2EH",
    "wof:placetype": "postalcode"
  },
  "geometry": {"coordinates":[0.75077,52.410943],"type":"Point"}
}
