{
  "type": "Feature",
  "properties": {
    "iso:country": "GB",
    "wof:name": "TF9 3JY",
    "wof:placetype": "postalcode"
  },
  "geometry": {"coordinates":[-2.555249,52.818329],"type":"Point"}
}
