{
  "type": "Feature",
  "properties": {
    "iso:country":"GB",
    "wof:name":"TF9 3JY",
    "wof:placetype":"postalcode"
},
  "geometry": {"coordinates":[-2.5552494193868,52.81832915069192],"type":"Point"}
}