{
  "type": "Feature",
  "properties": {
    "iso:country":"GB",
    "wof:name":"TS18 2HN",
    "wof:placetype":"postalcode"
},
  "geometry": {"coordinates":[-1.30473658476582,54.56836488644685],"type":"Point"}
}