{
  "type": "Feature",
  "properties": {
    "iso:country":"GB",
    "wof:name":"LL22 7AJ",
    "wof:placetype":"postalcode"
},
  "geometry": {"coordinates":[-3.57370423623245,53.28382091808125],"type":"Point"}
}