{
  "type": "Feature",
  "properties": {
    "iso:country":"GB",
    "wof:name":"KA9 1AQ",
    "wof:placetype":"postalcode"
},
  "geometry": {"coordinates":[-4.61288209298022,55.50131326009618],"type":"Point"}
}