{
  "type": "Feature",
  "properties": {
    "date:inception_lower": "1980-01-01",
    "date:inception_upper": "1980-01-01",
    "iso:country": "GB",
    "wof:name": "CF42 6TW",
    "wof:placetype": "postalcode"
  },
  "geometry": {"coordinates":[-3.511208,51.663027],"type":"Point"}
}
