{
  "type": "Feature",
  "properties": {
    "iso:country":"GB",
    "wof:name":"CH5 2LL",
    "wof:placetype":"postalcode"
},
  "geometry": {"coordinates":[-3.03100908056991,53.2379803234268],"type":"Point"}
}