{
  "type": "Feature",
  "properties": {
    "iso:country": "GB",
    "wof:name": "CH5 2LL",
    "wof:placetype": "postalcode"
  },
  "geometry": {"coordinates":[-3.031062,53.237762],"type":"Point"}
}
