{
  "type": "Feature",
  "properties": {
    "date:inception_lower":"1983-03-01",
    "date:inception_upper":"1983-03-31",
    "iso:country":"GB",
    "wof:name":"RH11 9NY",
    "wof:placetype":"postalcode"
},
  "geometry": {"coordinates":[-0.203891,51.098904],"type":"Point"}
}