{
  "type": "Feature",
  "properties": {
    "iso:country": "GB",
    "wof:name": "RH11 9NY",
    "wof:placetype": "postalcode"
  },
  "geometry": {"coordinates":[-0.203891,51.098904],"type":"Point"}
}
