{
  "type": "Feature",
  "properties": {
    "iso:country": "GB",
    "wof:name": "TN40 1LP",
    "wof:placetype": "postalcode"
  },
  "geometry": {"coordinates":[0.480015,50.839457],"type":"Point"}
}
