{
  "type": "Feature",
  "properties": {
    "iso:country": "GB",
    "wof:name": "BR8 8EL",
    "wof:placetype": "postalcode"
  },
  "geometry": {"coordinates":[0.160846,51.379421],"type":"Point"}
}
