{
  "type": "Feature",
  "properties": {
    "iso:country":"GB",
    "wof:name":"BR8 8EL",
    "wof:placetype":"postalcode"
},
  "geometry": {"coordinates":[0.16082601790345,51.37895360885528],"type":"Point"}
}