{
  "type": "Feature",
  "properties": {
    "date:inception_lower": "1980-01-01",
    "date:inception_upper": "1980-01-01",
    "iso:country": "GB",
    "wof:name": "SG7 6LN",
    "wof:placetype": "postalcode"
  },
  "geometry": {"coordinates":[-0.180761,51.981804],"type":"Point"}
}
