{
  "type": "Feature",
  "properties": {
    "iso:country":"GB",
    "wof:name":"EH4 8AJ",
    "wof:placetype":"postalcode"
},
  "geometry": {"coordinates":[-3.31759305836243,55.96119357756835],"type":"Point"}
}