{
  "type": "Feature",
  "properties": {
    "iso:country":"GB",
    "wof:name":"NG7 7EW",
    "wof:placetype":"postalcode"
},
  "geometry": {"coordinates":[-1.17220633254243,52.97887137086447],"type":"Point"}
}