{
  "type": "Feature",
  "properties": {
    "iso:country":"GB",
    "wof:name":"LD2 3HZ",
    "wof:placetype":"postalcode"
},
  "geometry": {"coordinates":[-3.37193137375112,52.09121213925],"type":"Point"}
}