{
  "type": "Feature",
  "properties": {
    "iso:country":"GB",
    "wof:name":"OL1 3FS",
    "wof:placetype":"postalcode"
},
  "geometry": {"coordinates":[-2.10952110928487,53.54422682455352],"type":"Point"}
}