{
  "type": "Feature",
  "properties": {
    "iso:country":"GB",
    "wof:name":"E10 6EL",
    "wof:placetype":"postalcode"
},
  "geometry": {"coordinates":[-0.00030267526599,51.57726256515879],"type":"Point"}
}