{
  "type": "Feature",
  "properties": {
    "iso:country":"GB",
    "wof:name":"NE10 9PY",
    "wof:placetype":"postalcode"
},
  "geometry": {"coordinates":[-1.56531183711649,54.94813235131792],"type":"Point"}
}