{
  "type": "Feature",
  "properties": {
    "iso:country":"GB",
    "wof:name":"DY4 0SS",
    "wof:placetype":"postalcode"
},
  "geometry": {"coordinates":[-2.05142886061839,52.54039913059921],"type":"Point"}
}