{
  "type": "Feature",
  "properties": {
    "iso:country": "GB",
    "wof:name": "GU95 1AX",
    "wof:placetype": "postalcode"
  },
  "geometry": {"coordinates":[-0.763075,51.326293],"type":"Point"}
}
