{
  "type": "Feature",
  "properties": {
    "iso:country":"GB",
    "wof:name":"TQ14 8AY",
    "wof:placetype":"postalcode"
},
  "geometry": {"coordinates":[-3.49402314225611,50.54613500122025],"type":"Point"}
}