{
  "type": "Feature",
  "properties": {
    "iso:country":"GB",
    "wof:name":"BS40 6PU",
    "wof:placetype":"postalcode"
},
  "geometry": {"coordinates":[-2.67577120010786,51.33196739854453],"type":"Point"}
}