{
  "type": "Feature",
  "properties": {
    "iso:country": "GB",
    "wof:name": "BS40 6PU",
    "wof:placetype": "postalcode"
  },
  "geometry": {"coordinates":[-2.675771,51.331967],"type":"Point"}
}
