{
  "type": "Feature",
  "properties": {
    "date:inception_lower": "2001-06-01",
    "date:inception_upper": "2001-06-01",
    "iso:country": "GB",
    "wof:name": "GU52 7SL",
    "wof:placetype": "postalcode"
  },
  "geometry": {"coordinates":[-0.84641,51.272255],"type":"Point"}
}
