{
  "type": "Feature",
  "properties": {
    "iso:country":"GB",
    "wof:name":"GU52 7SL",
    "wof:placetype":"postalcode"
},
  "geometry": {"coordinates":[-0.84641033713349,51.27225494371146],"type":"Point"}
}