{
  "type": "Feature",
  "properties": {
    "iso:country":"GB",
    "wof:name":"EH52 5AD",
    "wof:placetype":"postalcode"
},
  "geometry": {"coordinates":[-3.45087598611316,55.93817518052283],"type":"Point"}
}