{
  "type": "Feature",
  "properties": {
    "date:inception_lower":"1996-06-01",
    "date:inception_upper":"1996-06-30",
    "iso:country":"GB",
    "wof:name":"EH52 5AD",
    "wof:placetype":"postalcode"
},
  "geometry": {"coordinates":[-3.450876,55.938175],"type":"Point"}
}