{
  "type": "Feature",
  "properties": {
    "iso:country":"GB",
    "wof:name":"WD6 2PS",
    "wof:placetype":"postalcode"
},
  "geometry": {"coordinates":[-0.25392159122557,51.64953434479008],"type":"Point"}
}