{
  "type": "Feature",
  "properties": {
    "iso:country":"GB",
    "wof:name":"EN2 8QA",
    "wof:placetype":"postalcode"
},
  "geometry": {"coordinates":[-0.09632508288182,51.65761515747712],"type":"Point"}
}