{
  "type": "Feature",
  "properties": {
    "date:inception_lower": "1980-01-01",
    "date:inception_upper": "1980-01-01",
    "iso:country": "GB",
    "wof:name": "PR4 4GE",
    "wof:placetype": "postalcode"
  },
  "geometry": {"coordinates":[-2.800235,53.700784],"type":"Point"}
}
