{
  "type": "Feature",
  "properties": {
    "date:inception_lower": "2016-07-01",
    "date:inception_upper": "2016-07-01",
    "iso:country": "GB",
    "wof:name": "E14 7SZ",
    "wof:placetype": "postalcode"
  },
  "geometry": {"coordinates":[-0.027195,51.513798],"type":"Point"}
}
