{
  "type": "Feature",
  "properties": {
    "iso:country":"GB",
    "wof:name":"BL0 9DU",
    "wof:placetype":"postalcode"
},
  "geometry": {"coordinates":[-2.32102934651654,53.64908067983804],"type":"Point"}
}