{
  "type": "Feature",
  "properties": {
    "iso:country": "GB",
    "wof:name": "BL0 9DU",
    "wof:placetype": "postalcode"
  },
  "geometry": {"coordinates":[-2.321029,53.649081],"type":"Point"}
}
