{
  "type": "Feature",
  "properties": {
    "date:inception_lower":"1986-04-01",
    "date:inception_upper":"1986-04-30",
    "iso:country":"GB",
    "wof:name":"NG12 4DR",
    "wof:placetype":"postalcode"
},
  "geometry": {"coordinates":[-1.125284,52.905264],"type":"Point"}
}