{
  "type": "Feature",
  "properties": {
    "iso:country":"GB",
    "wof:name":"SG9 9PT",
    "wof:placetype":"postalcode"
},
  "geometry": {"coordinates":[-0.08455318702792,51.94649520862051],"type":"Point"}
}