{
  "type": "Feature",
  "properties": {
    "date:inception_lower": "2005-07-01",
    "date:inception_upper": "2005-07-01",
    "iso:country": "GB",
    "wof:name": "YO11 2QD",
    "wof:placetype": "postalcode"
  },
  "geometry": {"coordinates":[-0.400586,54.271516],"type":"Point"}
}
