{
  "type": "Feature",
  "properties": {
    "iso:country":"GB",
    "wof:name":"YO11 2QD",
    "wof:placetype":"postalcode"
},
  "geometry": {"coordinates":[-0.40058599485389,54.27151617719955],"type":"Point"}
}