{
  "type": "Feature",
  "properties": {
    "iso:country":"GB",
    "wof:name":"B44 0NS",
    "wof:placetype":"postalcode"
},
  "geometry": {"coordinates":[-1.8677852852485,52.54642302067648],"type":"Point"}
}