{
  "type": "Feature",
  "properties": {
    "date:inception_lower": "1980-01-01",
    "date:inception_upper": "1980-01-01",
    "iso:country": "GB",
    "wof:name": "B44 0NS",
    "wof:placetype": "postalcode"
  },
  "geometry": {"coordinates":[-1.867785,52.546423],"type":"Point"}
}
