{
  "type": "Feature",
  "properties": {
    "date:inception_lower":"1980-01-01",
    "date:inception_upper":"1980-01-31",
    "iso:country":"GB",
    "wof:name":"WR8 0LB",
    "wof:placetype":"postalcode"
},
  "geometry": {"coordinates":[-2.215496,52.062229],"type":"Point"}
}