{
  "type": "Feature",
  "properties": {
    "iso:country": "GB",
    "wof:name": "WR8 0LB",
    "wof:placetype": "postalcode"
  },
  "geometry": {"coordinates":[-2.215496,52.062229],"type":"Point"}
}
