{
  "type": "Feature",
  "properties": {
    "iso:country":"GB",
    "wof:name":"WR8 0LB",
    "wof:placetype":"postalcode"
},
  "geometry": {"coordinates":[-2.21549650575207,52.0622292997805],"type":"Point"}
}