{
  "type": "Feature",
  "properties": {
    "date:inception_lower": "2019-09-01",
    "date:inception_upper": "2019-09-01",
    "iso:country": "GB",
    "wof:name": "M13 9NJ",
    "wof:placetype": "postalcode"
  },
  "geometry": {"coordinates":[-2.226874,53.469681],"type":"Point"}
}
