{
  "type": "Feature",
  "properties": {
    "date:inception_lower":"1998-06-01",
    "date:inception_upper":"1998-06-30",
    "iso:country":"GB",
    "wof:name":"BH12 5HT",
    "wof:placetype":"postalcode"
},
  "geometry": {"coordinates":[-1.900933,50.738801],"type":"Point"}
}