{
  "type": "Feature",
  "properties": {
    "iso:country": "GB",
    "wof:name": "BH12 5HT",
    "wof:placetype": "postalcode"
  },
  "geometry": {"coordinates":[-1.900933,50.738801],"type":"Point"}
}
