{
  "type": "Feature",
  "properties": {
    "iso:country":"GB",
    "wof:name":"SN6 8TH",
    "wof:placetype":"postalcode"
},
  "geometry": {"coordinates":[-1.665781293924,51.61682839452569],"type":"Point"}
}