{
  "type": "Feature",
  "properties": {
    "iso:country": "GB",
    "wof:name": "DE15 0FA",
    "wof:placetype": "postalcode"
  },
  "geometry": {"coordinates":[-1.598093,52.803973],"type":"Point"}
}
