{
  "type": "Feature",
  "properties": {
    "date:inception_lower": "1980-01-01",
    "date:inception_upper": "1980-01-01",
    "iso:country": "GB",
    "wof:name": "HP14 4SS",
    "wof:placetype": "postalcode"
  },
  "geometry": {"coordinates":[-0.785709,51.673276],"type":"Point"}
}
