{
  "type": "Feature",
  "properties": {
    "iso:country":"GB",
    "wof:name":"IG8 7GG",
    "wof:placetype":"postalcode"
},
  "geometry": {"coordinates":[0.04266458647373,51.60689953473401],"type":"Point"}
}