{
  "type": "Feature",
  "properties": {
    "date:inception_lower": "2009-11-01",
    "date:inception_upper": "2009-11-01",
    "iso:country": "GB",
    "wof:name": "BS7 0FD",
    "wof:placetype": "postalcode"
  },
  "geometry": {"coordinates":[-2.583854,51.499122],"type":"Point"}
}
