{
  "type": "Feature",
  "properties": {
    "iso:country":"GB",
    "wof:name":"BS7 0FD",
    "wof:placetype":"postalcode"
},
  "geometry": {"coordinates":[-2.58396431028202,51.498834646158],"type":"Point"}
}