{
  "type": "Feature",
  "properties": {
    "date:inception_lower":"1988-03-01",
    "date:inception_upper":"1988-03-31",
    "iso:country":"GB",
    "wof:name":"DN19 7DU",
    "wof:placetype":"postalcode"
},
  "geometry": {"coordinates":[-0.374445,53.676575],"type":"Point"}
}