{
  "type": "Feature",
  "properties": {
    "iso:country":"GB",
    "wof:name":"NR20 4NZ",
    "wof:placetype":"postalcode"
},
  "geometry": {"coordinates":[0.98799637569645,52.71354311074246],"type":"Point"}
}