{
  "type": "Feature",
  "properties": {
    "date:inception_lower": "1980-01-01",
    "date:inception_upper": "1980-01-01",
    "iso:country": "GB",
    "wof:name": "NR20 4NZ",
    "wof:placetype": "postalcode"
  },
  "geometry": {"coordinates":[0.988019,52.713567],"type":"Point"}
}
