{
  "type": "Feature",
  "properties": {
    "date:inception_lower": "1980-01-01",
    "date:inception_upper": "1980-01-01",
    "iso:country": "GB",
    "wof:name": "NG13 8AD",
    "wof:placetype": "postalcode"
  },
  "geometry": {"coordinates":[-0.953476,52.951664],"type":"Point"}
}
