{
  "type": "Feature",
  "properties": {
    "iso:country":"GB",
    "wof:name":"TF3 2DX",
    "wof:placetype":"postalcode"
},
  "geometry": {"coordinates":[-2.43630472352939,52.67448887114345],"type":"Point"}
}