{
  "type": "Feature",
  "properties": {
    "date:inception_lower":"1980-01-01",
    "date:inception_upper":"1980-01-31",
    "iso:country":"GB",
    "wof:name":"EH32 9QG",
    "wof:placetype":"postalcode"
},
  "geometry": {"coordinates":[-2.967683,55.957978],"type":"Point"}
}