{
  "type": "Feature",
  "properties": {
    "iso:country":"GB",
    "wof:name":"B70 8JY",
    "wof:placetype":"postalcode"
},
  "geometry": {"coordinates":[-2.0080902363689,52.51335955434926],"type":"Point"}
}