{
  "type": "Feature",
  "properties": {
    "iso:country":"GB",
    "wof:name":"BB5 4PS",
    "wof:placetype":"postalcode"
},
  "geometry": {"coordinates":[-2.41596489168005,53.74480002054884],"type":"Point"}
}