{
  "type": "Feature",
  "properties": {
    "iso:country":"GB",
    "wof:name":"LE6 0NX",
    "wof:placetype":"postalcode"
},
  "geometry": {"coordinates":[-1.23827084838463,52.64708192565234],"type":"Point"}
}