{
  "type": "Feature",
  "properties": {
    "iso:country":"GB",
    "wof:name":"PA76 6SQ",
    "wof:placetype":"postalcode"
},
  "geometry": {"coordinates":[-6.39148195830032,56.3348848368466],"type":"Point"}
}