{
  "type": "Feature",
  "properties": {
    "iso:country": "GB",
    "wof:name": "NN3 3QZ",
    "wof:placetype": "postalcode"
  },
  "geometry": {"coordinates":[-0.846177,52.262133],"type":"Point"}
}
