{
  "type": "Feature",
  "properties": {
    "iso:country":"GB",
    "wof:name":"B74 3AS",
    "wof:placetype":"postalcode"
},
  "geometry": {"coordinates":[-1.86552989059722,52.59932558925269],"type":"Point"}
}