{
  "type": "Feature",
  "properties": {
    "iso:country": "GB",
    "wof:name": "TN3 8HE",
    "wof:placetype": "postalcode"
  },
  "geometry": {"coordinates":[0.38773,51.092744],"type":"Point"}
}
