{
  "type": "Feature",
  "properties": {
    "iso:country":"GB",
    "wof:name":"TN3 8HE",
    "wof:placetype":"postalcode"
},
  "geometry": {"coordinates":[0.38772990578915,51.09274400493253],"type":"Point"}
}