{
  "type": "Feature",
  "properties": {
    "iso:country":"GB",
    "wof:name":"NE12 6BQ",
    "wof:placetype":"postalcode"
},
  "geometry": {"coordinates":[-1.54749504778126,55.03459611250628],"type":"Point"}
}