{
  "type": "Feature",
  "properties": {
    "iso:country":"GB",
    "wof:name":"LL15 2HP",
    "wof:placetype":"postalcode"
},
  "geometry": {"coordinates":[-3.25774423324853,53.06510951533885],"type":"Point"}
}