{
  "type": "Feature",
  "properties": {
    "date:inception_lower":"1980-01-01",
    "date:inception_upper":"1980-01-31",
    "iso:country":"GB",
    "wof:name":"LN9 6JA",
    "wof:placetype":"postalcode"
},
  "geometry": {"coordinates":[-0.099319,53.179255],"type":"Point"}
}