{
  "type": "Feature",
  "properties": {
    "iso:country": "GB",
    "wof:name": "LN9 6JA",
    "wof:placetype": "postalcode"
  },
  "geometry": {"coordinates":[-0.099319,53.179255],"type":"Point"}
}
