{
  "type": "Feature",
  "properties": {
    "iso:country":"GB",
    "wof:name":"LN9 6JA",
    "wof:placetype":"postalcode"
},
  "geometry": {"coordinates":[-0.09931921244307,53.17925508802885],"type":"Point"}
}