{
  "type": "Feature",
  "properties": {
    "iso:country":"GB",
    "wof:name":"NN7 4RT",
    "wof:placetype":"postalcode"
},
  "geometry": {"coordinates":[-1.08126992484072,52.2297712468888],"type":"Point"}
}