{
  "type": "Feature",
  "properties": {
    "date:inception_lower": "2018-10-01",
    "date:inception_upper": "2018-10-01",
    "iso:country": "GB",
    "wof:name": "M4 6FX",
    "wof:placetype": "postalcode"
  },
  "geometry": {"coordinates":[-2.228206,53.48494],"type":"Point"}
}
