{
  "type": "Feature",
  "properties": {
    "date:inception_lower": "2005-09-01",
    "date:inception_upper": "2005-09-01",
    "iso:country": "GB",
    "wof:name": "RG1 5JQ",
    "wof:placetype": "postalcode"
  },
  "geometry": {"coordinates":[-0.952688,51.444417],"type":"Point"}
}
