{
  "type": "Feature",
  "properties": {
    "iso:country": "GB",
    "wof:name": "RG1 5JQ",
    "wof:placetype": "postalcode"
  },
  "geometry": {"coordinates":[-0.952688,51.444417],"type":"Point"}
}
