{
  "type": "Feature",
  "properties": {
    "iso:country":"GB",
    "wof:name":"PE13 5RH",
    "wof:placetype":"postalcode"
},
  "geometry": {"coordinates":[0.13130825907423,52.74552210623717],"type":"Point"}
}