{
  "type": "Feature",
  "properties": {
    "iso:country": "GB",
    "wof:name": "PE13 5RH",
    "wof:placetype": "postalcode"
  },
  "geometry": {"coordinates":[0.131308,52.745542],"type":"Point"}
}
