{
  "type": "Feature",
  "properties": {
    "date:inception_lower":"1980-01-01",
    "date:inception_upper":"1980-01-31",
    "iso:country":"GB",
    "wof:name":"BB12 7DR",
    "wof:placetype":"postalcode"
},
  "geometry": {"coordinates":[-2.307632,53.791083],"type":"Point"}
}