{
  "type": "Feature",
  "properties": {
    "iso:country":"GB",
    "wof:name":"BB12 7DR",
    "wof:placetype":"postalcode"
},
  "geometry": {"coordinates":[-2.30763234304652,53.7910830989407],"type":"Point"}
}