{
  "type": "Feature",
  "properties": {
    "iso:country": "GB",
    "wof:name": "CM5 0PP",
    "wof:placetype": "postalcode"
  },
  "geometry": {"coordinates":[0.294129,51.75021],"type":"Point"}
}
