{
  "type": "Feature",
  "properties": {
    "iso:country":"GB",
    "wof:name":"CM5 0PP",
    "wof:placetype":"postalcode"
},
  "geometry": {"coordinates":[0.29409952252523,51.75015035389136],"type":"Point"}
}