{
  "type": "Feature",
  "properties": {
    "iso:country":"GB",
    "wof:name":"ST1 4LD",
    "wof:placetype":"postalcode"
},
  "geometry": {"coordinates":[-2.18576308447193,53.01994462825165],"type":"Point"}
}