{
  "type": "Feature",
  "properties": {
    "date:inception_lower":"2018-08-01",
    "date:inception_upper":"2018-08-31",
    "iso:country":"GB",
    "wof:name":"IP7 5AU",
    "wof:placetype":"postalcode"
},
  "geometry": {"coordinates":[0.957345,52.041593],"type":"Point"}
}