{
  "type": "Feature",
  "properties": {
    "iso:country": "GB",
    "wof:name": "IP7 5AU",
    "wof:placetype": "postalcode"
  },
  "geometry": {"coordinates":[0.957345,52.041593],"type":"Point"}
}
