{
  "type": "Feature",
  "properties": {
    "iso:country": "GB",
    "wof:name": "RH7 6DH",
    "wof:placetype": "postalcode"
  },
  "geometry": {"coordinates":[-0.019716,51.176691],"type":"Point"}
}
