{
  "type": "Feature",
  "properties": {
    "iso:country": "GB",
    "wof:name": "EN8 7FN",
    "wof:placetype": "postalcode"
  },
  "geometry": {"coordinates":[-0.024995,51.687464],"type":"Point"}
}
