{
  "type": "Feature",
  "properties": {
    "iso:country":"GB",
    "wof:name":"DD2 1JZ",
    "wof:placetype":"postalcode"
},
  "geometry": {"coordinates":[-3.00254398709632,56.45735835941571],"type":"Point"}
}