{
  "type": "Feature",
  "properties": {
    "iso:country":"GB",
    "wof:name":"S7 2DA",
    "wof:placetype":"postalcode"
},
  "geometry": {"coordinates":[-1.49242522998786,53.35213086264624],"type":"Point"}
}