{
  "type": "Feature",
  "properties": {
    "iso:country": "GB",
    "wof:name": "S7 2DA",
    "wof:placetype": "postalcode"
  },
  "geometry": {"coordinates":[-1.492425,53.352131],"type":"Point"}
}
