{
  "type": "Feature",
  "properties": {
    "iso:country": "GB",
    "wof:name": "MK43 1AA",
    "wof:placetype": "postalcode"
  },
  "geometry": {"coordinates":[-0.602223,52.076738],"type":"Point"}
}
