{
  "type": "Feature",
  "properties": {
    "date:inception_lower": "2017-12-01",
    "date:inception_upper": "2017-12-01",
    "iso:country": "GB",
    "wof:name": "MK43 1AA",
    "wof:placetype": "postalcode"
  },
  "geometry": {"coordinates":[-0.602644,52.077273],"type":"Point"}
}
