{
  "type": "Feature",
  "properties": {
    "iso:country":"GB",
    "wof:name":"OX29 7QT",
    "wof:placetype":"postalcode"
},
  "geometry": {"coordinates":[-1.44408893053551,51.72938673861366],"type":"Point"}
}