{
  "type": "Feature",
  "properties": {
    "iso:country":"GB",
    "wof:name":"NE28 6HB",
    "wof:placetype":"postalcode"
},
  "geometry": {"coordinates":[-1.53269251725735,54.98897998763997],"type":"Point"}
}