{
  "type": "Feature",
  "properties": {
    "iso:country": "GB",
    "wof:name": "DA11 0DU",
    "wof:placetype": "postalcode"
  },
  "geometry": {"coordinates":[0.366474,51.436413],"type":"Point"}
}
