{
  "type": "Feature",
  "properties": {
    "iso:country":"GB",
    "wof:name":"DA11 0DU",
    "wof:placetype":"postalcode"
},
  "geometry": {"coordinates":[0.3664742427775,51.43641273016949],"type":"Point"}
}