{
  "type": "Feature",
  "properties": {
    "iso:country":"GB",
    "wof:name":"W1U 1PG",
    "wof:placetype":"postalcode"
},
  "geometry": {"coordinates":[-0.14682049647536,51.51656784397341],"type":"Point"}
}