{
  "type": "Feature",
  "properties": {
    "iso:country":"GB",
    "wof:name":"EH4 7PX",
    "wof:placetype":"postalcode"
},
  "geometry": {"coordinates":[-3.29015532945856,55.95646097746194],"type":"Point"}
}