{
  "type": "Feature",
  "properties": {
    "date:inception_lower": "2013-10-01",
    "date:inception_upper": "2013-10-01",
    "iso:country": "GB",
    "wof:name": "LE10 3AZ",
    "wof:placetype": "postalcode"
  },
  "geometry": {"coordinates":[-1.369851,52.485387],"type":"Point"}
}
