{
  "type": "Feature",
  "properties": {
    "iso:country": "GB",
    "wof:name": "LE10 3AZ",
    "wof:placetype": "postalcode"
  },
  "geometry": {"coordinates":[-1.369851,52.485387],"type":"Point"}
}
