{
  "type": "Feature",
  "properties": {
    "date:inception_lower":"2013-10-01",
    "date:inception_upper":"2013-10-31",
    "iso:country":"GB",
    "wof:name":"LE10 3AZ",
    "wof:placetype":"postalcode"
},
  "geometry": {"coordinates":[-1.369906,52.485361],"type":"Point"}
}