{
  "type": "Feature",
  "properties": {
    "iso:country": "GB",
    "wof:name": "LE10 3AZ",
    "wof:placetype": "postalcode"
  },
  "geometry": {"coordinates":[-1.369906,52.485361],"type":"Point"}
}
