{
  "type": "Feature",
  "properties": {
    "iso:country":"GB",
    "wof:name":"LE10 3AZ",
    "wof:placetype":"postalcode"
},
  "geometry": {"coordinates":[-1.36990583563768,52.48536103380818],"type":"Point"}
}