{
  "type": "Feature",
  "properties": {
    "iso:country":"GB",
    "wof:name":"YO12 4QU",
    "wof:placetype":"postalcode"
},
  "geometry": {"coordinates":[-0.43957427262984,54.23826689062927],"type":"Point"}
}