{
  "type": "Feature",
  "properties": {
    "iso:country":"GB",
    "wof:name":"G83 0PS",
    "wof:placetype":"postalcode"
},
  "geometry": {"coordinates":[-4.58049769312239,55.98795770629019],"type":"Point"}
}