{
  "type": "Feature",
  "properties": {
    "iso:country":"GB",
    "wof:name":"BR1 5SJ",
    "wof:placetype":"postalcode"
},
  "geometry": {"coordinates":[-0.01060495433228,51.42976898400089],"type":"Point"}
}