{
  "type": "Feature",
  "properties": {
    "date:inception_lower":"1992-08-01",
    "date:inception_upper":"1992-08-31",
    "iso:country":"GB",
    "wof:name":"LE7 3DX",
    "wof:placetype":"postalcode"
},
  "geometry": {"coordinates":[-1.051491,52.705005],"type":"Point"}
}