{
  "type": "Feature",
  "properties": {
    "date:inception_lower": "1990-02-01",
    "date:inception_upper": "1990-02-01",
    "iso:country": "GB",
    "wof:name": "NG6 0QT",
    "wof:placetype": "postalcode"
  },
  "geometry": {"coordinates":[-1.184457,52.983163],"type":"Point"}
}
