{
  "type": "Feature",
  "properties": {
    "iso:country":"GB",
    "wof:name":"G83 0PL",
    "wof:placetype":"postalcode"
},
  "geometry": {"coordinates":[-4.57679670546739,55.98968897055112],"type":"Point"}
}