{
  "type": "Feature",
  "properties": {
    "iso:country":"GB",
    "wof:name":"CO6 2AH",
    "wof:placetype":"postalcode"
},
  "geometry": {"coordinates":[0.77647838777676,51.91904214494622],"type":"Point"}
}