{
  "type": "Feature",
  "properties": {
    "iso:country": "GB",
    "wof:name": "B9 5LE",
    "wof:placetype": "postalcode"
  },
  "geometry": {"coordinates":[-1.849189,52.482024],"type":"Point"}
}
