{
  "type": "Feature",
  "properties": {
    "iso:country":"GB",
    "wof:name":"HA8 8XB",
    "wof:placetype":"postalcode"
},
  "geometry": {"coordinates":[-0.26743188607749,51.62767661554606],"type":"Point"}
}