{
  "type": "Feature",
  "properties": {
    "iso:country":"GB",
    "wof:name":"M5 4NQ",
    "wof:placetype":"postalcode"
},
  "geometry": {"coordinates":[-2.27165502793056,53.48970507080707],"type":"Point"}
}