{
  "type": "Feature",
  "properties": {
    "date:inception_lower":"2015-08-01",
    "date:inception_upper":"2015-08-31",
    "iso:country":"GB",
    "wof:name":"M5 4NQ",
    "wof:placetype":"postalcode"
},
  "geometry": {"coordinates":[-2.271501,53.489542],"type":"Point"}
}