{
  "type": "Feature",
  "properties": {
    "iso:country":"GB",
    "wof:name":"N14 6DA",
    "wof:placetype":"postalcode"
},
  "geometry": {"coordinates":[-0.12554888656966,51.6298223469488],"type":"Point"}
}