{
  "type": "Feature",
  "properties": {
    "iso:country": "GB",
    "wof:name": "N14 6DA",
    "wof:placetype": "postalcode"
  },
  "geometry": {"coordinates":[-0.125549,51.629822],"type":"Point"}
}
