{
  "type": "Feature",
  "properties": {
    "iso:country":"GB",
    "wof:name":"LN4 4NU",
    "wof:placetype":"postalcode"
},
  "geometry": {"coordinates":[-0.18334035387256,53.10993909320045],"type":"Point"}
}