{
  "type": "Feature",
  "properties": {
    "iso:country": "GB",
    "wof:name": "LN4 4NU",
    "wof:placetype": "postalcode"
  },
  "geometry": {"coordinates":[-0.18334,53.109939],"type":"Point"}
}
