{
  "type": "Feature",
  "properties": {
    "iso:country":"GB",
    "wof:name":"HP12 3JJ",
    "wof:placetype":"postalcode"
},
  "geometry": {"coordinates":[-0.77784778578509,51.63057375874462],"type":"Point"}
}