{
  "type": "Feature",
  "properties": {
    "date:inception_lower": "1980-01-01",
    "date:inception_upper": "1980-01-01",
    "iso:country": "GB",
    "wof:name": "HP12 3JJ",
    "wof:placetype": "postalcode"
  },
  "geometry": {"coordinates":[-0.777848,51.630574],"type":"Point"}
}
