{
  "type": "Feature",
  "properties": {
    "iso:country":"GB",
    "wof:name":"SN14 6NR",
    "wof:placetype":"postalcode"
},
  "geometry": {"coordinates":[-2.24340748694829,51.54978615359972],"type":"Point"}
}