{
  "type": "Feature",
  "properties": {
    "date:inception_lower":"2015-06-01",
    "date:inception_upper":"2015-06-30",
    "iso:country":"GB",
    "wof:name":"OX11 6DQ",
    "wof:placetype":"postalcode"
},
  "geometry": {"coordinates":[-1.265977,51.605878],"type":"Point"}
}