{
  "type": "Feature",
  "properties": {
    "iso:country":"GB",
    "wof:name":"OX11 6DQ",
    "wof:placetype":"postalcode"
},
  "geometry": {"coordinates":[-1.26599569908426,51.60583931495698],"type":"Point"}
}