{
  "type": "Feature",
  "properties": {
    "iso:country":"GB",
    "wof:name":"N1 6EP",
    "wof:placetype":"postalcode"
},
  "geometry": {"coordinates":[-0.08240279416034,51.52870645719317],"type":"Point"}
}