{
  "type": "Feature",
  "properties": {
    "iso:country": "GB",
    "wof:name": "SR3 3BW",
    "wof:placetype": "postalcode"
  },
  "geometry": {"coordinates":[-1.42499,54.881212],"type":"Point"}
}
