{
  "type": "Feature",
  "properties": {
    "iso:country":"GB",
    "wof:name":"SR3 3BW",
    "wof:placetype":"postalcode"
},
  "geometry": {"coordinates":[-1.42499053981238,54.8812121797969],"type":"Point"}
}