{
  "type": "Feature",
  "properties": {
    "iso:country":"GB",
    "wof:name":"NG11 9EG",
    "wof:placetype":"postalcode"
},
  "geometry": {"coordinates":[-1.17965492275842,52.89613858297491],"type":"Point"}
}