{
  "type": "Feature",
  "properties": {
    "iso:country":"GB",
    "wof:name":"G71 7RX",
    "wof:placetype":"postalcode"
},
  "geometry": {"coordinates":[-4.12147677505301,55.83188238589035],"type":"Point"}
}