{
  "type": "Feature",
  "properties": {
    "iso:country": "GB",
    "wof:name": "G71 7RX",
    "wof:placetype": "postalcode"
  },
  "geometry": {"coordinates":[-4.121464,55.831878],"type":"Point"}
}
