{
  "type": "Feature",
  "properties": {
    "iso:country":"GB",
    "wof:name":"SO40 9BN",
    "wof:placetype":"postalcode"
},
  "geometry": {"coordinates":[-1.49241094042984,50.91591798934646],"type":"Point"}
}