{
  "type": "Feature",
  "properties": {
    "date:inception_lower": "1998-06-01",
    "date:inception_upper": "1998-06-01",
    "iso:country": "GB",
    "wof:name": "DE14 3JT",
    "wof:placetype": "postalcode"
  },
  "geometry": {"coordinates":[-1.65025,52.790681],"type":"Point"}
}
