{
  "type": "Feature",
  "properties": {
    "date:inception_lower":"1980-01-01",
    "date:inception_upper":"1980-01-31",
    "iso:country":"GB",
    "wof:name":"NE4 8BE",
    "wof:placetype":"postalcode"
},
  "geometry": {"coordinates":[-1.655845,54.970322],"type":"Point"}
}