{
  "type": "Feature",
  "properties": {
    "iso:country":"GB",
    "wof:name":"NE4 8BE",
    "wof:placetype":"postalcode"
},
  "geometry": {"coordinates":[-1.65584495539764,54.97032164081018],"type":"Point"}
}