{
  "type": "Feature",
  "properties": {
    "iso:country": "GB",
    "wof:name": "NE4 8BE",
    "wof:placetype": "postalcode"
  },
  "geometry": {"coordinates":[-1.655845,54.970322],"type":"Point"}
}
