{
  "type": "Feature",
  "properties": {
    "iso:country":"GB",
    "wof:name":"DL8 5LB",
    "wof:placetype":"postalcode"
},
  "geometry": {"coordinates":[-1.8234037417545,54.31266462545436],"type":"Point"}
}