{
  "type": "Feature",
  "properties": {
    "iso:country":"GB",
    "wof:name":"RG8 9TU",
    "wof:placetype":"postalcode"
},
  "geometry": {"coordinates":[-1.20208794872051,51.51494933212142],"type":"Point"}
}