{
  "type": "Feature",
  "properties": {
    "iso:country": "GB",
    "wof:name": "W13 0FJ",
    "wof:placetype": "postalcode"
  },
  "geometry": {"coordinates":[-0.329402,51.528196],"type":"Point"}
}
