{
  "type": "Feature",
  "properties": {
    "iso:country": "GB",
    "wof:name": "M18 8GZ",
    "wof:placetype": "postalcode"
  },
  "geometry": {"coordinates":[-2.166063,53.466223],"type":"Point"}
}
