{
  "type": "Feature",
  "properties": {
    "iso:country":"GB",
    "wof:name":"M18 8GZ",
    "wof:placetype":"postalcode"
},
  "geometry": {"coordinates":[-2.16606267716502,53.46622306729657],"type":"Point"}
}