{
  "type": "Feature",
  "properties": {
    "iso:country":"GB",
    "wof:name":"L32 3XX",
    "wof:placetype":"postalcode"
},
  "geometry": {"coordinates":[-2.88226513778907,53.46767306934271],"type":"Point"}
}