{
  "type": "Feature",
  "properties": {
    "date:inception_lower": "1980-01-01",
    "date:inception_upper": "1980-01-01",
    "iso:country": "GB",
    "wof:name": "SA4 3LT",
    "wof:placetype": "postalcode"
  },
  "geometry": {"coordinates":[-4.097486,51.639331],"type":"Point"}
}
