{
  "type": "Feature",
  "properties": {
    "iso:country":"GB",
    "wof:name":"SA4 3LT",
    "wof:placetype":"postalcode"
},
  "geometry": {"coordinates":[-4.09748556100655,51.63933084864561],"type":"Point"}
}