{
  "type": "Feature",
  "properties": {
    "iso:country":"GB",
    "wof:name":"SY1 2SQ",
    "wof:placetype":"postalcode"
},
  "geometry": {"coordinates":[-2.74219962965995,52.71817735105979],"type":"Point"}
}