{
  "type": "Feature",
  "properties": {
    "iso:country": "GB",
    "wof:name": "SY1 2SQ",
    "wof:placetype": "postalcode"
  },
  "geometry": {"coordinates":[-2.742227,52.718192],"type":"Point"}
}
