{
  "type": "Feature",
  "properties": {
    "iso:country": "GB",
    "wof:name": "DE24 3LT",
    "wof:placetype": "postalcode"
  },
  "geometry": {"coordinates":[-1.49815,52.875724],"type":"Point"}
}
