{
  "type": "Feature",
  "properties": {
    "date:inception_lower": "1992-08-01",
    "date:inception_upper": "1992-08-01",
    "iso:country": "GB",
    "wof:name": "DE24 3LT",
    "wof:placetype": "postalcode"
  },
  "geometry": {"coordinates":[-1.49815,52.875724],"type":"Point"}
}
