{
  "type": "Feature",
  "properties": {
    "iso:country":"GB",
    "wof:name":"BB5 6SJ",
    "wof:placetype":"postalcode"
},
  "geometry": {"coordinates":[-2.35659017629302,53.75403350580842],"type":"Point"}
}