{
  "type": "Feature",
  "properties": {
    "iso:country": "GB",
    "wof:name": "BB5 6SJ",
    "wof:placetype": "postalcode"
  },
  "geometry": {"coordinates":[-2.35659,53.754034],"type":"Point"}
}
