{
  "type": "Feature",
  "properties": {
    "date:inception_lower":"1991-01-01",
    "date:inception_upper":"1991-01-31",
    "iso:country":"GB",
    "wof:name":"RH12 5QW",
    "wof:placetype":"postalcode"
},
  "geometry": {"coordinates":[-0.307034,51.082209],"type":"Point"}
}