{
  "type": "Feature",
  "properties": {
    "iso:country":"GB",
    "wof:name":"B29 4DG",
    "wof:placetype":"postalcode"
},
  "geometry": {"coordinates":[-1.96141977310328,52.43313615644064],"type":"Point"}
}