{
  "type": "Feature",
  "properties": {
    "date:inception_lower": "1990-02-01",
    "date:inception_upper": "1990-02-01",
    "iso:country": "GB",
    "wof:name": "MK15 9LL",
    "wof:placetype": "postalcode"
  },
  "geometry": {"coordinates":[-0.717862,52.063278],"type":"Point"}
}
