{
  "type": "Feature",
  "properties": {
    "iso:country":"GB",
    "wof:name":"DH1 3PP",
    "wof:placetype":"postalcode"
},
  "geometry": {"coordinates":[-1.59120834032474,54.76667798885968],"type":"Point"}
}