{
  "type": "Feature",
  "properties": {
    "date:inception_lower": "2018-04-01",
    "date:inception_upper": "2018-04-01",
    "iso:country": "GB",
    "wof:name": "SK23 7GJ",
    "wof:placetype": "postalcode"
  },
  "geometry": {"coordinates":[-1.953171,53.317845],"type":"Point"}
}
