{
  "type": "Feature",
  "properties": {
    "iso:country": "GB",
    "wof:name": "EX15 3QA",
    "wof:placetype": "postalcode"
  },
  "geometry": {"coordinates":[-3.177088,50.885949],"type":"Point"}
}
