{
  "type": "Feature",
  "properties": {
    "iso:country": "GB",
    "wof:name": "S17 3PX",
    "wof:placetype": "postalcode"
  },
  "geometry": {"coordinates":[-1.5397,53.32026],"type":"Point"}
}
