{
  "type": "Feature",
  "properties": {
    "iso:country":"GB",
    "wof:name":"S17 3PX",
    "wof:placetype":"postalcode"
},
  "geometry": {"coordinates":[-1.53970031696655,53.32025962354049],"type":"Point"}
}