{
  "type": "Feature",
  "properties": {
    "iso:country":"GB",
    "wof:name":"N19 3RF",
    "wof:placetype":"postalcode"
},
  "geometry": {"coordinates":[-0.13227561477281,51.56874528401359],"type":"Point"}
}