{
  "type": "Feature",
  "properties": {
    "iso:country":"GB",
    "wof:name":"L18 3NN",
    "wof:placetype":"postalcode"
},
  "geometry": {"coordinates":[-2.88433786025522,53.37603456439415],"type":"Point"}
}