{
  "type": "Feature",
  "properties": {
    "iso:country": "GB",
    "wof:name": "WV16 6XG",
    "wof:placetype": "postalcode"
  },
  "geometry": {"coordinates":[-2.537877,52.556427],"type":"Point"}
}
