{
  "type": "Feature",
  "properties": {
    "iso:country":"GB",
    "wof:name":"WV16 6XG",
    "wof:placetype":"postalcode"
},
  "geometry": {"coordinates":[-2.53786428721797,52.55642108097643],"type":"Point"}
}