{
  "type": "Feature",
  "properties": {
    "iso:country":"GB",
    "wof:name":"TQ14 0HP",
    "wof:placetype":"postalcode"
},
  "geometry": {"coordinates":[-3.49921217074109,50.53707475108522],"type":"Point"}
}