{
  "type": "Feature",
  "properties": {
    "iso:country": "GB",
    "wof:name": "M5 3PX",
    "wof:placetype": "postalcode"
  },
  "geometry": {"coordinates":[-2.273485,53.469826],"type":"Point"}
}
