{
  "type": "Feature",
  "properties": {
    "iso:country": "GB",
    "wof:name": "WD24 6PE",
    "wof:placetype": "postalcode"
  },
  "geometry": {"coordinates":[-0.395955,51.672889],"type":"Point"}
}
