{
  "type": "Feature",
  "properties": {
    "iso:country":"GB",
    "wof:name":"WD24 6PE",
    "wof:placetype":"postalcode"
},
  "geometry": {"coordinates":[-0.39595506347699,51.67288941161812],"type":"Point"}
}