{
  "type": "Feature",
  "properties": {
    "iso:country":"GB",
    "wof:name":"EX5 3AA",
    "wof:placetype":"postalcode"
},
  "geometry": {"coordinates":[-3.44259965982109,50.7615982958333],"type":"Point"}
}