{
  "type": "Feature",
  "properties": {
    "iso:country": "GB",
    "wof:name": "S11 9QT",
    "wof:placetype": "postalcode"
  },
  "geometry": {"coordinates":[-1.521793,53.341582],"type":"Point"}
}
