{
  "type": "Feature",
  "properties": {
    "iso:country":"GB",
    "wof:name":"TA4 1AF",
    "wof:placetype":"postalcode"
},
  "geometry": {"coordinates":[-3.15479055988069,51.02008203885261],"type":"Point"}
}