{
  "type": "Feature",
  "properties": {
    "iso:country":"GB",
    "wof:name":"B37 6QJ",
    "wof:placetype":"postalcode"
},
  "geometry": {"coordinates":[-1.7415994845015,52.48882346001727],"type":"Point"}
}