{
  "type": "Feature",
  "properties": {
    "iso:country": "GB",
    "wof:name": "B37 6QJ",
    "wof:placetype": "postalcode"
  },
  "geometry": {"coordinates":[-1.741599,52.488823],"type":"Point"}
}
