{
  "type": "Feature",
  "properties": {
    "date:inception_lower": "1987-04-01",
    "date:inception_upper": "1987-04-01",
    "iso:country": "GB",
    "wof:name": "NN8 3XQ",
    "wof:placetype": "postalcode"
  },
  "geometry": {"coordinates":[-0.72205,52.307643],"type":"Point"}
}
