{
  "type": "Feature",
  "properties": {
    "date:inception_lower": "2014-05-01",
    "date:inception_upper": "2014-05-01",
    "iso:country": "GB",
    "wof:name": "SN7 7GH",
    "wof:placetype": "postalcode"
  },
  "geometry": {"coordinates":[-1.593637,51.64763],"type":"Point"}
}
