{
  "type": "Feature",
  "properties": {
    "iso:country":"GB",
    "wof:name":"SN7 7GH",
    "wof:placetype":"postalcode"
},
  "geometry": {"coordinates":[-1.59363706998947,51.64763004628995],"type":"Point"}
}