{
  "type": "Feature",
  "properties": {
    "iso:country": "GB",
    "wof:name": "PR9 8EU",
    "wof:placetype": "postalcode"
  },
  "geometry": {"coordinates":[-2.923397,53.682074],"type":"Point"}
}
