{
  "type": "Feature",
  "properties": {
    "iso:country":"GB",
    "wof:name":"BA1 2BT",
    "wof:placetype":"postalcode"
},
  "geometry": {"coordinates":[-2.3675294768879,51.38232769353764],"type":"Point"}
}