{
  "type": "Feature",
  "properties": {
    "iso:country":"GB",
    "wof:name":"SM4 4DF",
    "wof:placetype":"postalcode"
},
  "geometry": {"coordinates":[-0.20351818568881,51.40043038374892],"type":"Point"}
}