{
  "type": "Feature",
  "properties": {
    "iso:country": "GB",
    "wof:name": "LS8 5EN",
    "wof:placetype": "postalcode"
  },
  "geometry": {"coordinates":[-1.524962,53.809413],"type":"Point"}
}
