{
  "type": "Feature",
  "properties": {
    "iso:country": "GB",
    "wof:name": "L18 6JT",
    "wof:placetype": "postalcode"
  },
  "geometry": {"coordinates":[-2.900959,53.376539],"type":"Point"}
}
