{
  "type": "Feature",
  "properties": {
    "iso:country":"GB",
    "wof:name":"FK8 3BL",
    "wof:placetype":"postalcode"
},
  "geometry": {"coordinates":[-4.0836036438608,56.12487474454768],"type":"Point"}
}