{
  "type": "Feature",
  "properties": {
    "iso:country": "GB",
    "wof:name": "FK8 3BL",
    "wof:placetype": "postalcode"
  },
  "geometry": {"coordinates":[-4.083604,56.124875],"type":"Point"}
}
