{
  "type": "Feature",
  "properties": {
    "iso:country":"GB",
    "wof:name":"PA15 2HJ",
    "wof:placetype":"postalcode"
},
  "geometry": {"coordinates":[-4.7229670795897,55.93846567527744],"type":"Point"}
}