{
  "type": "Feature",
  "properties": {
    "iso:country":"GB",
    "wof:name":"NE33 5JN",
    "wof:placetype":"postalcode"
},
  "geometry": {"coordinates":[-1.44286833020168,54.98061314393502],"type":"Point"}
}