{
  "type": "Feature",
  "properties": {
    "iso:country": "GB",
    "wof:name": "NE33 5JN",
    "wof:placetype": "postalcode"
  },
  "geometry": {"coordinates":[-1.442868,54.980613],"type":"Point"}
}
