{
  "type": "Feature",
  "properties": {
    "iso:country":"GB",
    "wof:name":"PE11 4XL",
    "wof:placetype":"postalcode"
},
  "geometry": {"coordinates":[-0.20532307526086,52.90285579534106],"type":"Point"}
}