{
  "type": "Feature",
  "properties": {
    "date:inception_lower":"1980-01-01",
    "date:inception_upper":"1980-01-31",
    "iso:country":"GB",
    "wof:name":"PE11 4XL",
    "wof:placetype":"postalcode"
},
  "geometry": {"coordinates":[-0.205328,52.902888],"type":"Point"}
}