{
  "type": "Feature",
  "properties": {
    "iso:country":"GB",
    "wof:name":"SG1 1EN",
    "wof:placetype":"postalcode"
},
  "geometry": {"coordinates":[-0.20004322052192,51.90100250442623],"type":"Point"}
}