{
  "type": "Feature",
  "properties": {
    "iso:country":"GB",
    "wof:name":"NE29 9PB",
    "wof:placetype":"postalcode"
},
  "geometry": {"coordinates":[-1.45390453088777,55.01709360629049],"type":"Point"}
}