{
  "type": "Feature",
  "properties": {
    "iso:country":"GB",
    "wof:name":"SY11 4JW",
    "wof:placetype":"postalcode"
},
  "geometry": {"coordinates":[-2.96790224911451,52.82602779073294],"type":"Point"}
}