{
  "type": "Feature",
  "properties": {
    "iso:country": "GB",
    "wof:name": "SY11 4JW",
    "wof:placetype": "postalcode"
  },
  "geometry": {"coordinates":[-2.967902,52.826028],"type":"Point"}
}
