{
  "type": "Feature",
  "properties": {
    "iso:country":"GB",
    "wof:name":"BN8 5JP",
    "wof:placetype":"postalcode"
},
  "geometry": {"coordinates":[0.0598928441,50.8956847471817],"type":"Point"}
}