{
  "type": "Feature",
  "properties": {
    "iso:country": "GB",
    "wof:name": "TS20 1LX",
    "wof:placetype": "postalcode"
  },
  "geometry": {"coordinates":[-1.314686,54.595796],"type":"Point"}
}
