{
  "type": "Feature",
  "properties": {
    "iso:country":"GB",
    "wof:name":"TS20 1LX",
    "wof:placetype":"postalcode"
},
  "geometry": {"coordinates":[-1.314685846198,54.5957959815215],"type":"Point"}
}