{
  "type": "Feature",
  "properties": {
    "date:inception_lower": "1980-01-01",
    "date:inception_upper": "1980-01-01",
    "iso:country": "GB",
    "wof:name": "RG9 2LU",
    "wof:placetype": "postalcode"
  },
  "geometry": {"coordinates":[-0.8962,51.536517],"type":"Point"}
}
