{
  "type": "Feature",
  "properties": {
    "iso:country":"GB",
    "wof:name":"RG9 2LU",
    "wof:placetype":"postalcode"
},
  "geometry": {"coordinates":[-0.89621971556209,51.53651474985725],"type":"Point"}
}