{
  "type": "Feature",
  "properties": {
    "iso:country": "GB",
    "wof:name": "PE8 5HS",
    "wof:placetype": "postalcode"
  },
  "geometry": {"coordinates":[-0.445747,52.504721],"type":"Point"}
}
