{
  "type": "Feature",
  "properties": {
    "iso:country":"GB",
    "wof:name":"PE8 5HS",
    "wof:placetype":"postalcode"
},
  "geometry": {"coordinates":[-0.44574662710871,52.50472054985438],"type":"Point"}
}