{
  "type": "Feature",
  "properties": {
    "date:inception_lower":"1980-01-01",
    "date:inception_upper":"1980-01-31",
    "iso:country":"GB",
    "wof:name":"PE8 5HS",
    "wof:placetype":"postalcode"
},
  "geometry": {"coordinates":[-0.445747,52.504721],"type":"Point"}
}