{
  "type": "Feature",
  "properties": {
    "iso:country": "GB",
    "wof:name": "NE5 3AS",
    "wof:placetype": "postalcode"
  },
  "geometry": {"coordinates":[-1.65414,54.990626],"type":"Point"}
}
