{
  "type": "Feature",
  "properties": {
    "iso:country": "GB",
    "wof:name": "M22 5BG",
    "wof:placetype": "postalcode"
  },
  "geometry": {"coordinates":[-2.245434,53.383392],"type":"Point"}
}
