{
  "type": "Feature",
  "properties": {
    "iso:country":"GB",
    "wof:name":"WV11 2BD",
    "wof:placetype":"postalcode"
},
  "geometry": {"coordinates":[-2.0728367935483,52.64636843894093],"type":"Point"}
}