{
  "type": "Feature",
  "properties": {
    "iso:country": "GB",
    "wof:name": "WV11 2BD",
    "wof:placetype": "postalcode"
  },
  "geometry": {"coordinates":[-2.07283,52.646384],"type":"Point"}
}
