{
  "type": "Feature",
  "properties": {
    "iso:country": "GB",
    "wof:name": "L17 5BY",
    "wof:placetype": "postalcode"
  },
  "geometry": {"coordinates":[-2.948306,53.373009],"type":"Point"}
}
