{
  "type": "Feature",
  "properties": {
    "iso:country":"GB",
    "wof:name":"L17 5BY",
    "wof:placetype":"postalcode"
},
  "geometry": {"coordinates":[-2.94830634362034,53.37300851310783],"type":"Point"}
}