{
  "type": "Feature",
  "properties": {
    "date:inception_lower": "1994-12-01",
    "date:inception_upper": "1994-12-01",
    "iso:country": "GB",
    "wof:name": "L17 5BY",
    "wof:placetype": "postalcode"
  },
  "geometry": {"coordinates":[-2.948306,53.373009],"type":"Point"}
}
