{
  "type": "Feature",
  "properties": {
    "iso:country":"GB",
    "wof:name":"EX32 0NR",
    "wof:placetype":"postalcode"
},
  "geometry": {"coordinates":[-4.00320861247695,51.05591753121572],"type":"Point"}
}