{
  "type": "Feature",
  "properties": {
    "iso:country": "GB",
    "wof:name": "EX32 0NR",
    "wof:placetype": "postalcode"
  },
  "geometry": {"coordinates":[-4.003209,51.055918],"type":"Point"}
}
