{
  "type": "Feature",
  "properties": {
    "iso:country": "GB",
    "wof:name": "PO32 6DZ",
    "wof:placetype": "postalcode"
  },
  "geometry": {"coordinates":[-1.284765,50.753564],"type":"Point"}
}
