{
  "type": "Feature",
  "properties": {
    "iso:country":"GB",
    "wof:name":"W1G 6LP",
    "wof:placetype":"postalcode"
},
  "geometry": {"coordinates":[-0.14942433787046,51.52131202645572],"type":"Point"}
}