{
  "type": "Feature",
  "properties": {
    "iso:country":"GB",
    "wof:name":"HX3 8XA",
    "wof:placetype":"postalcode"
},
  "geometry": {"coordinates":[-1.78371231910999,53.71844470702005],"type":"Point"}
}