{
  "type": "Feature",
  "properties": {
    "iso:country":"GB",
    "wof:name":"WS11 9QT",
    "wof:placetype":"postalcode"
},
  "geometry": {"coordinates":[-1.96399538149063,52.66712480619389],"type":"Point"}
}