{
  "type": "Feature",
  "properties": {
    "iso:country": "GB",
    "wof:name": "NE47 0HF",
    "wof:placetype": "postalcode"
  },
  "geometry": {"coordinates":[-2.125263,54.910113],"type":"Point"}
}
