{
  "type": "Feature",
  "properties": {
    "date:inception_lower": "1980-01-01",
    "date:inception_upper": "1980-01-01",
    "iso:country": "GB",
    "wof:name": "NE47 0HF",
    "wof:placetype": "postalcode"
  },
  "geometry": {"coordinates":[-2.125263,54.910113],"type":"Point"}
}
