{
  "type": "Feature",
  "properties": {
    "iso:country":"GB",
    "wof:name":"NE47 0HF",
    "wof:placetype":"postalcode"
},
  "geometry": {"coordinates":[-2.12526293043447,54.9101127986406],"type":"Point"}
}