{
  "type": "Feature",
  "properties": {
    "iso:country": "GB",
    "wof:name": "CB7 4TU",
    "wof:placetype": "postalcode"
  },
  "geometry": {"coordinates":[0.27879,52.4049],"type":"Point"}
}
