{
  "type": "Feature",
  "properties": {
    "iso:country":"GB",
    "wof:name":"B15 2BS",
    "wof:placetype":"postalcode"
},
  "geometry": {"coordinates":[-1.90542221082755,52.46869618833804],"type":"Point"}
}