{
  "type": "Feature",
  "properties": {
    "iso:country":"GB",
    "wof:name":"UB8 2AG",
    "wof:placetype":"postalcode"
},
  "geometry": {"coordinates":[-0.48282905778545,51.53468532141843],"type":"Point"}
}