{
  "type": "Feature",
  "properties": {
    "iso:country":"GB",
    "wof:name":"DY5 4EE",
    "wof:placetype":"postalcode"
},
  "geometry": {"coordinates":[-2.1273897450024,52.49911389757042],"type":"Point"}
}