{
  "type": "Feature",
  "properties": {
    "date:inception_lower": "1980-01-01",
    "date:inception_upper": "1980-01-01",
    "iso:country": "GB",
    "wof:name": "DY5 4EE",
    "wof:placetype": "postalcode"
  },
  "geometry": {"coordinates":[-2.12739,52.499114],"type":"Point"}
}
