{
  "type": "Feature",
  "properties": {
    "iso:country": "GB",
    "wof:name": "PO3 6LB",
    "wof:placetype": "postalcode"
  },
  "geometry": {"coordinates":[-1.057695,50.814597],"type":"Point"}
}
