{
  "type": "Feature",
  "properties": {
    "iso:country": "GB",
    "wof:name": "CW6 9AT",
    "wof:placetype": "postalcode"
  },
  "geometry": {"coordinates":[-2.622751,53.155966],"type":"Point"}
}
