{
  "type": "Feature",
  "properties": {
    "iso:country":"GB",
    "wof:name":"CW6 9AT",
    "wof:placetype":"postalcode"
},
  "geometry": {"coordinates":[-2.62275114849675,53.15596589225422],"type":"Point"}
}