{
  "type": "Feature",
  "properties": {
    "iso:country":"GB",
    "wof:name":"WS10 9AJ",
    "wof:placetype":"postalcode"
},
  "geometry": {"coordinates":[-2.01294997594228,52.55283366005124],"type":"Point"}
}