{
  "type": "Feature",
  "properties": {
    "iso:country": "GB",
    "wof:name": "WS10 9AJ",
    "wof:placetype": "postalcode"
  },
  "geometry": {"coordinates":[-2.01295,52.552834],"type":"Point"}
}
