{
  "type": "Feature",
  "properties": {
    "iso:country":"GB",
    "wof:name":"NR25 6AP",
    "wof:placetype":"postalcode"
},
  "geometry": {"coordinates":[1.08657269847797,52.90572275407126],"type":"Point"}
}