{
  "type": "Feature",
  "properties": {
    "iso:country": "GB",
    "wof:name": "NR25 6AP",
    "wof:placetype": "postalcode"
  },
  "geometry": {"coordinates":[1.086748,52.905881],"type":"Point"}
}
