{
  "type": "Feature",
  "properties": {
    "iso:country": "GB",
    "wof:name": "CM3 2BF",
    "wof:placetype": "postalcode"
  },
  "geometry": {"coordinates":[0.600062,51.777718],"type":"Point"}
}
