{
  "type": "Feature",
  "properties": {
    "iso:country":"GB",
    "wof:name":"CM3 2BF",
    "wof:placetype":"postalcode"
},
  "geometry": {"coordinates":[0.60006157138136,51.77771779879921],"type":"Point"}
}