{
  "type": "Feature",
  "properties": {
    "iso:country": "GB",
    "wof:name": "SK11 7QF",
    "wof:placetype": "postalcode"
  },
  "geometry": {"coordinates":[-2.123155,53.250224],"type":"Point"}
}
