{
  "type": "Feature",
  "properties": {
    "iso:country":"GB",
    "wof:name":"SK11 7QF",
    "wof:placetype":"postalcode"
},
  "geometry": {"coordinates":[-2.12315476258841,53.25022446696622],"type":"Point"}
}