{
  "type": "Feature",
  "properties": {
    "iso:country":"GB",
    "wof:name":"B65 0PE",
    "wof:placetype":"postalcode"
},
  "geometry": {"coordinates":[-2.02987737878716,52.48262842823432],"type":"Point"}
}