{
  "type": "Feature",
  "properties": {
    "iso:country": "GB",
    "wof:name": "B65 0PE",
    "wof:placetype": "postalcode"
  },
  "geometry": {"coordinates":[-2.029877,52.482628],"type":"Point"}
}
