{
  "type": "Feature",
  "properties": {
    "iso:country":"GB",
    "wof:name":"NG12 5LY",
    "wof:placetype":"postalcode"
},
  "geometry": {"coordinates":[-1.09690517126133,52.87230024172801],"type":"Point"}
}