{
  "type": "Feature",
  "properties": {
    "date:inception_lower": "2013-12-01",
    "date:inception_upper": "2013-12-01",
    "iso:country": "GB",
    "wof:name": "NG12 5LY",
    "wof:placetype": "postalcode"
  },
  "geometry": {"coordinates":[-1.096905,52.8723],"type":"Point"}
}
