{
  "type": "Feature",
  "properties": {
    "iso:country": "GB",
    "wof:name": "TS6 9DJ",
    "wof:placetype": "postalcode"
  },
  "geometry": {"coordinates":[-1.154388,54.560569],"type":"Point"}
}
