{
  "type": "Feature",
  "properties": {
    "iso:country":"GB",
    "wof:name":"TS6 9DJ",
    "wof:placetype":"postalcode"
},
  "geometry": {"coordinates":[-1.15438763117768,54.56056879911764],"type":"Point"}
}