{
  "type": "Feature",
  "properties": {
    "iso:country":"GB",
    "wof:name":"DH9 6PQ",
    "wof:placetype":"postalcode"
},
  "geometry": {"coordinates":[-1.68764440085799,54.86203232624742],"type":"Point"}
}