{
  "type": "Feature",
  "properties": {
    "iso:country": "GB",
    "wof:name": "NR30 3BT",
    "wof:placetype": "postalcode"
  },
  "geometry": {"coordinates":[1.734441,52.602152],"type":"Point"}
}
