{
  "type": "Feature",
  "properties": {
    "iso:country":"GB",
    "wof:name":"NR30 3BT",
    "wof:placetype":"postalcode"
},
  "geometry": {"coordinates":[1.73444096010074,52.60215158756803],"type":"Point"}
}