{
  "type": "Feature",
  "properties": {
    "date:inception_lower":"1980-01-01",
    "date:inception_upper":"1980-01-31",
    "iso:country":"GB",
    "wof:name":"DY2 9SF",
    "wof:placetype":"postalcode"
},
  "geometry": {"coordinates":[-2.077852,52.478091],"type":"Point"}
}