{
  "type": "Feature",
  "properties": {
    "date:inception_lower": "1998-06-01",
    "date:inception_upper": "1998-06-01",
    "iso:country": "GB",
    "wof:name": "YO30 1BF",
    "wof:placetype": "postalcode"
  },
  "geometry": {"coordinates":[-1.155721,54.022844],"type":"Point"}
}
