{
  "type": "Feature",
  "properties": {
    "iso:country": "GB",
    "wof:name": "YO30 1BF",
    "wof:placetype": "postalcode"
  },
  "geometry": {"coordinates":[-1.155721,54.022844],"type":"Point"}
}
