{
  "type": "Feature",
  "properties": {
    "iso:country":"GB",
    "wof:name":"YO30 1BF",
    "wof:placetype":"postalcode"
},
  "geometry": {"coordinates":[-1.15577444340771,54.02282805763034],"type":"Point"}
}