{
  "type": "Feature",
  "properties": {
    "date:inception_lower": "1998-12-01",
    "date:inception_upper": "1998-12-01",
    "iso:country": "GB",
    "wof:name": "SW6 1HY",
    "wof:placetype": "postalcode"
  },
  "geometry": {"coordinates":[-0.189187,51.481143],"type":"Point"}
}
