{
  "type": "Feature",
  "properties": {
    "iso:country": "GB",
    "wof:name": "SW6 1HY",
    "wof:placetype": "postalcode"
  },
  "geometry": {"coordinates":[-0.189187,51.481143],"type":"Point"}
}
