{
  "type": "Feature",
  "properties": {
    "iso:country":"GB",
    "wof:name":"SW6 1HY",
    "wof:placetype":"postalcode"
},
  "geometry": {"coordinates":[-0.18918694548213,51.48114277545341],"type":"Point"}
}