{
  "type": "Feature",
  "properties": {
    "iso:country":"GB",
    "wof:name":"TW18 3BP",
    "wof:placetype":"postalcode"
},
  "geometry": {"coordinates":[-0.53045677599578,51.433734204409],"type":"Point"}
}