{
  "type": "Feature",
  "properties": {
    "iso:country": "GB",
    "wof:name": "L22 9QT",
    "wof:placetype": "postalcode"
  },
  "geometry": {"coordinates":[-3.028238,53.478883],"type":"Point"}
}
