{
  "type": "Feature",
  "properties": {
    "iso:country": "GB",
    "wof:name": "GU27 3RU",
    "wof:placetype": "postalcode"
  },
  "geometry": {"coordinates":[-0.734197,51.085325],"type":"Point"}
}
