{
  "type": "Feature",
  "properties": {
    "date:inception_lower":"1980-01-01",
    "date:inception_upper":"1980-01-31",
    "iso:country":"GB",
    "wof:name":"GU27 3RU",
    "wof:placetype":"postalcode"
},
  "geometry": {"coordinates":[-0.734197,51.085325],"type":"Point"}
}