{
  "type": "Feature",
  "properties": {
    "iso:country":"GB",
    "wof:name":"GU27 3RU",
    "wof:placetype":"postalcode"
},
  "geometry": {"coordinates":[-0.7341758979411,51.08527590185668],"type":"Point"}
}