{
  "type": "Feature",
  "properties": {
    "iso:country":"GB",
    "wof:name":"NP19 8JT",
    "wof:placetype":"postalcode"
},
  "geometry": {"coordinates":[-2.96771773750451,51.58601444152857],"type":"Point"}
}