{
  "type": "Feature",
  "properties": {
    "iso:country": "GB",
    "wof:name": "SY9 5BX",
    "wof:placetype": "postalcode"
  },
  "geometry": {"coordinates":[-2.99249,52.487799],"type":"Point"}
}
