{
  "type": "Feature",
  "properties": {
    "date:inception_lower": "1993-08-01",
    "date:inception_upper": "1993-08-01",
    "iso:country": "GB",
    "wof:name": "SY9 5BX",
    "wof:placetype": "postalcode"
  },
  "geometry": {"coordinates":[-2.99249,52.487799],"type":"Point"}
}
