{
  "type": "Feature",
  "properties": {
    "iso:country":"GB",
    "wof:name":"HA0 2SF",
    "wof:placetype":"postalcode"
},
  "geometry": {"coordinates":[-0.32899120244719,51.55971571675762],"type":"Point"}
}