{
  "type": "Feature",
  "properties": {
    "iso:country":"GB",
    "wof:name":"BS8 2AQ",
    "wof:placetype":"postalcode"
},
  "geometry": {"coordinates":[-2.61403883079358,51.46844222720502],"type":"Point"}
}