{
  "type": "Feature",
  "properties": {
    "iso:country":"GB",
    "wof:name":"YO25 9HW",
    "wof:placetype":"postalcode"
},
  "geometry": {"coordinates":[-0.41332922794644,53.98402444274258],"type":"Point"}
}