{
  "type": "Feature",
  "properties": {
    "iso:country": "GB",
    "wof:name": "TD6 0SN",
    "wof:placetype": "postalcode"
  },
  "geometry": {"coordinates":[-2.712789,55.565406],"type":"Point"}
}
