{
  "type": "Feature",
  "properties": {
    "date:inception_lower": "1980-01-01",
    "date:inception_upper": "1980-01-01",
    "iso:country": "GB",
    "wof:name": "TD6 0SN",
    "wof:placetype": "postalcode"
  },
  "geometry": {"coordinates":[-2.712789,55.565406],"type":"Point"}
}
