{
  "type": "Feature",
  "properties": {
    "iso:country":"GB",
    "wof:name":"TD6 0SN",
    "wof:placetype":"postalcode"
},
  "geometry": {"coordinates":[-2.71278462067988,55.56540613209213],"type":"Point"}
}