{
  "type": "Feature",
  "properties": {
    "iso:country": "GB",
    "wof:name": "TD6 0SN",
    "wof:placetype": "postalcode"
  },
  "geometry": {"coordinates":[-2.7126,55.565497],"type":"Point"}
}
