{
  "type": "Feature",
  "properties": {
    "iso:country":"GB",
    "wof:name":"ST6 8FG",
    "wof:placetype":"postalcode"
},
  "geometry": {"coordinates":[-2.16300473519093,53.05286923133058],"type":"Point"}
}