{
  "type": "Feature",
  "properties": {
    "date:inception_lower":"2011-03-01",
    "date:inception_upper":"2011-03-31",
    "iso:country":"GB",
    "wof:name":"ST6 8FG",
    "wof:placetype":"postalcode"
},
  "geometry": {"coordinates":[-2.163005,53.052869],"type":"Point"}
}