{
  "type": "Feature",
  "properties": {
    "iso:country": "GB",
    "wof:name": "GL15 4HA",
    "wof:placetype": "postalcode"
  },
  "geometry": {"coordinates":[-2.555569,51.768187],"type":"Point"}
}
