{
  "type": "Feature",
  "properties": {
    "date:inception_lower": "2004-10-01",
    "date:inception_upper": "2004-10-01",
    "iso:country": "GB",
    "wof:name": "GL15 4HA",
    "wof:placetype": "postalcode"
  },
  "geometry": {"coordinates":[-2.555569,51.768187],"type":"Point"}
}
