{
  "type": "Feature",
  "properties": {
    "iso:country": "GB",
    "wof:name": "CV35 9UE",
    "wof:placetype": "postalcode"
  },
  "geometry": {"coordinates":[-1.592187,52.202101],"type":"Point"}
}
