{
  "type": "Feature",
  "properties": {
    "date:inception_lower":"1992-01-01",
    "date:inception_upper":"1992-01-31",
    "iso:country":"GB",
    "wof:name":"GU30 7YB",
    "wof:placetype":"postalcode"
},
  "geometry": {"coordinates":[-0.804377,51.084243],"type":"Point"}
}