{
  "type": "Feature",
  "properties": {
    "iso:country":"GB",
    "wof:name":"GU30 7YB",
    "wof:placetype":"postalcode"
},
  "geometry": {"coordinates":[-0.80437714585316,51.08424330417167],"type":"Point"}
}