{
  "type": "Feature",
  "properties": {
    "iso:country": "GB",
    "wof:name": "SY1 3EX",
    "wof:placetype": "postalcode"
  },
  "geometry": {"coordinates":[-2.74178,52.732698],"type":"Point"}
}
