{
  "type": "Feature",
  "properties": {
    "iso:country":"GB",
    "wof:name":"KT1 4AB",
    "wof:placetype":"postalcode"
},
  "geometry": {"coordinates":[-0.30993558940933,51.40422558473495],"type":"Point"}
}