{
  "type": "Feature",
  "properties": {
    "iso:country": "GB",
    "wof:name": "KT1 4AB",
    "wof:placetype": "postalcode"
  },
  "geometry": {"coordinates":[-0.309936,51.404226],"type":"Point"}
}
