{
  "type": "Feature",
  "properties": {
    "iso:country":"GB",
    "wof:name":"OL12 0AY",
    "wof:placetype":"postalcode"
},
  "geometry": {"coordinates":[-2.15977437041101,53.62040882400385],"type":"Point"}
}