{
  "type": "Feature",
  "properties": {
    "date:inception_lower": "2023-04-01",
    "date:inception_upper": "2023-04-01",
    "iso:country": "GB",
    "wof:name": "DD5 3FY",
    "wof:placetype": "postalcode"
  },
  "geometry": {"coordinates":[-2.870072,56.487026],"type":"Point"}
}
