{
  "type": "Feature",
  "properties": {
    "date:inception_lower": "2024-06-01",
    "date:inception_upper": "2024-06-01",
    "iso:country": "GB",
    "wof:name": "OL11 3FU",
    "wof:placetype": "postalcode"
  },
  "geometry": {"coordinates":[-2.185015,53.59523],"type":"Point"}
}
