{
  "type": "Feature",
  "properties": {
    "iso:country":"GB",
    "wof:name":"W5 3SA",
    "wof:placetype":"postalcode"
},
  "geometry": {"coordinates":[-0.28481421660873,51.51453936235929],"type":"Point"}
}