{
  "type": "Feature",
  "properties": {
    "iso:country": "GB",
    "wof:name": "BS8 3UX",
    "wof:placetype": "postalcode"
  },
  "geometry": {"coordinates":[-2.690441,51.439673],"type":"Point"}
}
