{
  "type": "Feature",
  "properties": {
    "iso:country": "GB",
    "wof:name": "AB21 7JU",
    "wof:placetype": "postalcode"
  },
  "geometry": {"coordinates":[-2.180349,57.207759],"type":"Point"}
}
