{
  "type": "Feature",
  "properties": {
    "iso:country": "GB",
    "wof:name": "WN3 5BF",
    "wof:placetype": "postalcode"
  },
  "geometry": {"coordinates":[-2.651659,53.530201],"type":"Point"}
}
