{
  "type": "Feature",
  "properties": {
    "date:inception_lower": "2014-12-01",
    "date:inception_upper": "2014-12-01",
    "iso:country": "GB",
    "wof:name": "WN3 5BF",
    "wof:placetype": "postalcode"
  },
  "geometry": {"coordinates":[-2.651659,53.530201],"type":"Point"}
}
