{
  "type": "Feature",
  "properties": {
    "iso:country":"GB",
    "wof:name":"WN3 5BF",
    "wof:placetype":"postalcode"
},
  "geometry": {"coordinates":[-2.65277029670976,53.52987444529668],"type":"Point"}
}