{
  "type": "Feature",
  "properties": {
    "iso:country":"GB",
    "wof:name":"WN3 6RR",
    "wof:placetype":"postalcode"
},
  "geometry": {"coordinates":[-2.65845656190808,53.5229939892582],"type":"Point"}
}