{
  "type": "Feature",
  "properties": {
    "iso:country": "GB",
    "wof:name": "EH14 5HY",
    "wof:placetype": "postalcode"
  },
  "geometry": {"coordinates":[-3.299882,55.900684],"type":"Point"}
}
