{
  "type": "Feature",
  "properties": {
    "iso:country": "GB",
    "wof:name": "HX3 8UD",
    "wof:placetype": "postalcode"
  },
  "geometry": {"coordinates":[-1.788836,53.727172],"type":"Point"}
}
