{
  "type": "Feature",
  "properties": {
    "date:inception_lower": "1980-01-01",
    "date:inception_upper": "1980-01-01",
    "iso:country": "GB",
    "wof:name": "CA28 6AY",
    "wof:placetype": "postalcode"
  },
  "geometry": {"coordinates":[-3.588663,54.557366],"type":"Point"}
}
