{
  "type": "Feature",
  "properties": {
    "iso:country":"GB",
    "wof:name":"WD23 2BE",
    "wof:placetype":"postalcode"
},
  "geometry": {"coordinates":[-0.3688163629883,51.66383833558106],"type":"Point"}
}