{
  "type": "Feature",
  "properties": {
    "iso:country": "GB",
    "wof:name": "WD23 2BE",
    "wof:placetype": "postalcode"
  },
  "geometry": {"coordinates":[-0.368816,51.663838],"type":"Point"}
}
