{
  "type": "Feature",
  "properties": {
    "date:inception_lower":"2000-10-01",
    "date:inception_upper":"2000-10-31",
    "iso:country":"GB",
    "wof:name":"WD23 2BE",
    "wof:placetype":"postalcode"
},
  "geometry": {"coordinates":[-0.368816,51.663838],"type":"Point"}
}