{
  "type": "Feature",
  "properties": {
    "iso:country":"GB",
    "wof:name":"LL41 3HG",
    "wof:placetype":"postalcode"
},
  "geometry": {"coordinates":[-3.93846729935511,52.99502532403885],"type":"Point"}
}