{
  "type": "Feature",
  "properties": {
    "date:inception_lower": "1980-01-01",
    "date:inception_upper": "1980-01-01",
    "iso:country": "GB",
    "wof:name": "LL41 3HG",
    "wof:placetype": "postalcode"
  },
  "geometry": {"coordinates":[-3.938467,52.995025],"type":"Point"}
}
