{
  "type": "Feature",
  "properties": {
    "iso:country":"GB",
    "wof:name":"NP19 4NX",
    "wof:placetype":"postalcode"
},
  "geometry": {"coordinates":[-2.95122807208591,51.57949547847018],"type":"Point"}
}