{
  "type": "Feature",
  "properties": {
    "iso:country":"GB",
    "wof:name":"CM9 6UR",
    "wof:placetype":"postalcode"
},
  "geometry": {"coordinates":[0.66899082741348,51.72032358677949],"type":"Point"}
}