{
  "type": "Feature",
  "properties": {
    "date:inception_lower": "1981-06-01",
    "date:inception_upper": "1981-06-01",
    "iso:country": "GB",
    "wof:name": "CM9 6UR",
    "wof:placetype": "postalcode"
  },
  "geometry": {"coordinates":[0.668991,51.720324],"type":"Point"}
}
