{
  "type": "Feature",
  "properties": {
    "date:inception_lower":"1980-01-01",
    "date:inception_upper":"1980-01-31",
    "iso:country":"GB",
    "wof:name":"SL0 9AT",
    "wof:placetype":"postalcode"
},
  "geometry": {"coordinates":[-0.506815,51.507972],"type":"Point"}
}