{
  "type": "Feature",
  "properties": {
    "date:inception_lower": "2020-04-01",
    "date:inception_upper": "2020-04-01",
    "iso:country": "GB",
    "wof:name": "SN1 1AL",
    "wof:placetype": "postalcode"
  },
  "geometry": {"coordinates":[-1.782674,51.559074],"type":"Point"}
}
