{
  "type": "Feature",
  "properties": {
    "iso:country":"GB",
    "wof:name":"CA16 6BA",
    "wof:placetype":"postalcode"
},
  "geometry": {"coordinates":[-2.50960712468926,54.58792532650085],"type":"Point"}
}