{
  "type": "Feature",
  "properties": {
    "iso:country": "GB",
    "wof:name": "LL68 0SG",
    "wof:placetype": "postalcode"
  },
  "geometry": {"coordinates":[-4.474466,53.380877],"type":"Point"}
}
