{
  "type": "Feature",
  "properties": {
    "iso:country":"GB",
    "wof:name":"YO25 6PA",
    "wof:placetype":"postalcode"
},
  "geometry": {"coordinates":[-0.43197165765874,54.00011620504355],"type":"Point"}
}