{
  "type": "Feature",
  "properties": {
    "iso:country": "GB",
    "wof:name": "YO25 6PA",
    "wof:placetype": "postalcode"
  },
  "geometry": {"coordinates":[-0.431972,54.000116],"type":"Point"}
}
