{
  "type": "Feature",
  "properties": {
    "iso:country": "GB",
    "wof:name": "DT6 5RJ",
    "wof:placetype": "postalcode"
  },
  "geometry": {"coordinates":[-2.760444,50.741433],"type":"Point"}
}
