{
  "type": "Feature",
  "properties": {
    "date:inception_lower":"1993-01-01",
    "date:inception_upper":"1993-01-31",
    "iso:country":"GB",
    "wof:name":"DT6 5RJ",
    "wof:placetype":"postalcode"
},
  "geometry": {"coordinates":[-2.760444,50.741433],"type":"Point"}
}