{
  "type": "Feature",
  "properties": {
    "iso:country":"GB",
    "wof:name":"LU3 3DN",
    "wof:placetype":"postalcode"
},
  "geometry": {"coordinates":[-0.4638220375988,51.91669115727422],"type":"Point"}
}