{
  "type": "Feature",
  "properties": {
    "date:inception_lower":"1980-01-01",
    "date:inception_upper":"1980-01-31",
    "iso:country":"GB",
    "wof:name":"LU3 3DN",
    "wof:placetype":"postalcode"
},
  "geometry": {"coordinates":[-0.463822,51.916691],"type":"Point"}
}