{
  "type": "Feature",
  "properties": {
    "iso:country":"GB",
    "wof:name":"RM8 1LA",
    "wof:placetype":"postalcode"
},
  "geometry": {"coordinates":[0.12323568902345,51.56197173611788],"type":"Point"}
}