{
  "type": "Feature",
  "properties": {
    "iso:country":"GB",
    "wof:name":"G73 3BU",
    "wof:placetype":"postalcode"
},
  "geometry": {"coordinates":[-4.20932750883509,55.82527543216246],"type":"Point"}
}