{
  "type": "Feature",
  "properties": {
    "iso:country":"GB",
    "wof:name":"NE12 6HE",
    "wof:placetype":"postalcode"
},
  "geometry": {"coordinates":[-1.56153969821824,55.03365001352802],"type":"Point"}
}