{
  "type": "Feature",
  "properties": {
    "date:inception_lower": "1980-01-01",
    "date:inception_upper": "1980-01-01",
    "iso:country": "GB",
    "wof:name": "ST2 8PB",
    "wof:placetype": "postalcode"
  },
  "geometry": {"coordinates":[-2.144556,53.027769],"type":"Point"}
}
