{
  "type": "Feature",
  "properties": {
    "iso:country":"GB",
    "wof:name":"ST2 8PB",
    "wof:placetype":"postalcode"
},
  "geometry": {"coordinates":[-2.14455576511564,53.02776855152171],"type":"Point"}
}