{
  "type": "Feature",
  "properties": {
    "iso:country": "GB",
    "wof:name": "ST2 8PB",
    "wof:placetype": "postalcode"
  },
  "geometry": {"coordinates":[-2.144556,53.027769],"type":"Point"}
}
