{
  "type": "Feature",
  "properties": {
    "date:inception_lower":"1990-07-01",
    "date:inception_upper":"1990-07-31",
    "iso:country":"GB",
    "wof:name":"PL35 0AL",
    "wof:placetype":"postalcode"
},
  "geometry": {"coordinates":[-4.695958,50.684209],"type":"Point"}
}