{
  "type": "Feature",
  "properties": {
    "iso:country": "GB",
    "wof:name": "PL35 0AL",
    "wof:placetype": "postalcode"
  },
  "geometry": {"coordinates":[-4.695958,50.684209],"type":"Point"}
}
