{
  "type": "Feature",
  "properties": {
    "iso:country":"GB",
    "wof:name":"DH9 6HX",
    "wof:placetype":"postalcode"
},
  "geometry": {"coordinates":[-1.69664142324466,54.86511947299578],"type":"Point"}
}