{
  "type": "Feature",
  "properties": {
    "date:inception_lower":"1980-01-01",
    "date:inception_upper":"1980-01-31",
    "iso:country":"GB",
    "wof:name":"DH9 6HX",
    "wof:placetype":"postalcode"
},
  "geometry": {"coordinates":[-1.696641,54.865119],"type":"Point"}
}