{
  "type": "Feature",
  "properties": {
    "iso:country": "GB",
    "wof:name": "DH9 6HX",
    "wof:placetype": "postalcode"
  },
  "geometry": {"coordinates":[-1.696641,54.865119],"type":"Point"}
}
