{
  "type": "Feature",
  "properties": {
    "iso:country":"GB",
    "wof:name":"HP17 8DB",
    "wof:placetype":"postalcode"
},
  "geometry": {"coordinates":[-0.92882284078786,51.7663721691545],"type":"Point"}
}