{
  "type": "Feature",
  "properties": {
    "iso:country": "GB",
    "wof:name": "BD17 7AN",
    "wof:placetype": "postalcode"
  },
  "geometry": {"coordinates":[-1.768585,53.837966],"type":"Point"}
}
