{
  "type": "Feature",
  "properties": {
    "iso:country":"GB",
    "wof:name":"SG18 0GY",
    "wof:placetype":"postalcode"
},
  "geometry": {"coordinates":[-0.25499886561327,52.08654689175929],"type":"Point"}
}