{
  "type": "Feature",
  "properties": {
    "iso:country":"GB",
    "wof:name":"AB21 0WW",
    "wof:placetype":"postalcode"
},
  "geometry": {"coordinates":[-2.18664016334029,57.26694725908393],"type":"Point"}
}