{
  "type": "Feature",
  "properties": {
    "date:inception_lower": "2005-02-01",
    "date:inception_upper": "2005-02-01",
    "iso:country": "GB",
    "wof:name": "PL19 1SP",
    "wof:placetype": "postalcode"
  },
  "geometry": {"coordinates":[-4.143304,50.552566],"type":"Point"}
}
