{
  "type": "Feature",
  "properties": {
    "iso:country": "GB",
    "wof:name": "LE67 8LY",
    "wof:placetype": "postalcode"
  },
  "geometry": {"coordinates":[-1.365891,52.751926],"type":"Point"}
}
