{
  "type": "Feature",
  "properties": {
    "iso:country":"GB",
    "wof:name":"BS4 3DP",
    "wof:placetype":"postalcode"
},
  "geometry": {"coordinates":[-2.58070051096342,51.44719406622951],"type":"Point"}
}