{
  "type": "Feature",
  "properties": {
    "date:inception_lower": "1999-06-01",
    "date:inception_upper": "1999-06-01",
    "iso:country": "GB",
    "wof:name": "BS4 3DP",
    "wof:placetype": "postalcode"
  },
  "geometry": {"coordinates":[-2.5807,51.447194],"type":"Point"}
}
