{
  "type": "Feature",
  "properties": {
    "iso:country": "GB",
    "wof:name": "PL24 2JR",
    "wof:placetype": "postalcode"
  },
  "geometry": {"coordinates":[-4.711733,50.347667],"type":"Point"}
}
