{
  "type": "Feature",
  "properties": {
    "date:inception_lower": "2006-09-01",
    "date:inception_upper": "2006-09-01",
    "iso:country": "GB",
    "wof:name": "CB23 3QN",
    "wof:placetype": "postalcode"
  },
  "geometry": {"coordinates":[-0.121165,52.24816],"type":"Point"}
}
