{
  "type": "Feature",
  "properties": {
    "iso:country":"GB",
    "wof:name":"RG12 9GJ",
    "wof:placetype":"postalcode"
},
  "geometry": {"coordinates":[-0.74254015081659,51.41007882074086],"type":"Point"}
}