{
  "type": "Feature",
  "properties": {
    "iso:country":"GB",
    "wof:name":"SS9 1AJ",
    "wof:placetype":"postalcode"
},
  "geometry": {"coordinates":[0.65694304331654,51.54132983624982],"type":"Point"}
}