{
  "type": "Feature",
  "properties": {
    "iso:country": "GB",
    "wof:name": "TF10 9DN",
    "wof:placetype": "postalcode"
  },
  "geometry": {"coordinates":[-2.295262,52.74961],"type":"Point"}
}
