{
  "type": "Feature",
  "properties": {
    "iso:country":"GB",
    "wof:name":"TF10 9DN",
    "wof:placetype":"postalcode"
},
  "geometry": {"coordinates":[-2.29526177590222,52.7496103072535],"type":"Point"}
}