{
  "type": "Feature",
  "properties": {
    "iso:country":"GB",
    "wof:name":"LA10 5SF",
    "wof:placetype":"postalcode"
},
  "geometry": {"coordinates":[-2.52619111544681,54.32072203498878],"type":"Point"}
}