{
  "type": "Feature",
  "properties": {
    "date:inception_lower": "1980-01-01",
    "date:inception_upper": "1980-01-01",
    "iso:country": "GB",
    "wof:name": "LA10 5SF",
    "wof:placetype": "postalcode"
  },
  "geometry": {"coordinates":[-2.526191,54.320722],"type":"Point"}
}
