{
  "type": "Feature",
  "properties": {
    "iso:country":"GB",
    "wof:name":"DL14 7GH",
    "wof:placetype":"postalcode"
},
  "geometry": {"coordinates":[-1.65846991971049,54.65826438450574],"type":"Point"}
}