{
  "type": "Feature",
  "properties": {
    "iso:country": "GB",
    "wof:name": "DL14 7GH",
    "wof:placetype": "postalcode"
  },
  "geometry": {"coordinates":[-1.65847,54.658264],"type":"Point"}
}
