{
  "type": "Feature",
  "properties": {
    "date:inception_lower": "2019-06-01",
    "date:inception_upper": "2019-06-01",
    "iso:country": "GB",
    "wof:name": "PA7 5LN",
    "wof:placetype": "postalcode"
  },
  "geometry": {"coordinates":[-4.501478,55.900277],"type":"Point"}
}
