{
  "type": "Feature",
  "properties": {
    "iso:country":"GB",
    "wof:name":"WS10 8YG",
    "wof:placetype":"postalcode"
},
  "geometry": {"coordinates":[-2.03929809716583,52.57741496789348],"type":"Point"}
}