{
  "type": "Feature",
  "properties": {
    "iso:country":"GB",
    "wof:name":"SO15 8PN",
    "wof:placetype":"postalcode"
},
  "geometry": {"coordinates":[-1.44288786845231,50.91396576464916],"type":"Point"}
}