{
  "type": "Feature",
  "properties": {
    "iso:country":"GB",
    "wof:name":"CR0 4DD",
    "wof:placetype":"postalcode"
},
  "geometry": {"coordinates":[-0.11065585600344,51.36424903478998],"type":"Point"}
}