{
  "type": "Feature",
  "properties": {
    "iso:country": "GB",
    "wof:name": "CR0 4DD",
    "wof:placetype": "postalcode"
  },
  "geometry": {"coordinates":[-0.110656,51.364249],"type":"Point"}
}
