{
  "type": "Feature",
  "properties": {
    "date:inception_lower": "1980-01-01",
    "date:inception_upper": "1980-01-01",
    "iso:country": "GB",
    "wof:name": "CR0 4DD",
    "wof:placetype": "postalcode"
  },
  "geometry": {"coordinates":[-0.110656,51.364249],"type":"Point"}
}
