{
  "type": "Feature",
  "properties": {
    "iso:country": "GB",
    "wof:name": "WA8 4YB",
    "wof:placetype": "postalcode"
  },
  "geometry": {"coordinates":[-2.772025,53.375439],"type":"Point"}
}
