{
  "type": "Feature",
  "properties": {
    "iso:country":"GB",
    "wof:name":"WA8 4YB",
    "wof:placetype":"postalcode"
},
  "geometry": {"coordinates":[-2.77202480478464,53.3754386993036],"type":"Point"}
}