{
  "type": "Feature",
  "properties": {
    "iso:country":"GB",
    "wof:name":"BD21 3DZ",
    "wof:placetype":"postalcode"
},
  "geometry": {"coordinates":[-1.9071655511195,53.86982617153809],"type":"Point"}
}