{
  "type": "Feature",
  "properties": {
    "date:inception_lower": "2007-07-01",
    "date:inception_upper": "2007-07-01",
    "iso:country": "GB",
    "wof:name": "DE65 5NY",
    "wof:placetype": "postalcode"
  },
  "geometry": {"coordinates":[-1.639888,52.869398],"type":"Point"}
}
