{
  "type": "Feature",
  "properties": {
    "iso:country":"GB",
    "wof:name":"CO10 7AJ",
    "wof:placetype":"postalcode"
},
  "geometry": {"coordinates":[0.67783929816442,52.05006480221729],"type":"Point"}
}