{
  "type": "Feature",
  "properties": {
    "iso:country": "GB",
    "wof:name": "CO10 7AJ",
    "wof:placetype": "postalcode"
  },
  "geometry": {"coordinates":[0.677839,52.050065],"type":"Point"}
}
