{
  "type": "Feature",
  "properties": {
    "date:inception_lower": "1994-05-01",
    "date:inception_upper": "1994-05-01",
    "iso:country": "GB",
    "wof:name": "M44 5ZB",
    "wof:placetype": "postalcode"
  },
  "geometry": {"coordinates":[-2.431752,53.435518],"type":"Point"}
}
