{
  "type": "Feature",
  "properties": {
    "iso:country":"GB",
    "wof:name":"M44 5ZB",
    "wof:placetype":"postalcode"
},
  "geometry": {"coordinates":[-2.43175224410902,53.43551814702577],"type":"Point"}
}