{
  "type": "Feature",
  "properties": {
    "date:inception_lower": "1980-01-01",
    "date:inception_upper": "1980-01-01",
    "iso:country": "GB",
    "wof:name": "M6 8AF",
    "wof:placetype": "postalcode"
  },
  "geometry": {"coordinates":[-2.318567,53.490928],"type":"Point"}
}
