{
  "type": "Feature",
  "properties": {
    "iso:country": "GB",
    "wof:name": "NG21 0HZ",
    "wof:placetype": "postalcode"
  },
  "geometry": {"coordinates":[-1.098756,53.117421],"type":"Point"}
}
