{
  "type": "Feature",
  "properties": {
    "iso:country":"GB",
    "wof:name":"NG21 0HZ",
    "wof:placetype":"postalcode"
},
  "geometry": {"coordinates":[-1.09875568329321,53.11742138431119],"type":"Point"}
}