{
  "type": "Feature",
  "properties": {
    "iso:country":"GB",
    "wof:name":"GL54 2LT",
    "wof:placetype":"postalcode"
},
  "geometry": {"coordinates":[-1.71285195849234,51.85461528546205],"type":"Point"}
}