{
  "type": "Feature",
  "properties": {
    "date:inception_lower":"1987-10-01",
    "date:inception_upper":"1987-10-31",
    "iso:country":"GB",
    "wof:name":"GL54 2LT",
    "wof:placetype":"postalcode"
},
  "geometry": {"coordinates":[-1.712852,51.854615],"type":"Point"}
}