{
  "type": "Feature",
  "properties": {
    "iso:country": "GB",
    "wof:name": "GL54 2LT",
    "wof:placetype": "postalcode"
  },
  "geometry": {"coordinates":[-1.712852,51.854615],"type":"Point"}
}
