{
  "type": "Feature",
  "properties": {
    "iso:country":"GB",
    "wof:name":"SO23 7JZ",
    "wof:placetype":"postalcode"
},
  "geometry": {"coordinates":[-1.31302672496075,51.08609860272833],"type":"Point"}
}