{
  "type": "Feature",
  "properties": {
    "iso:country":"GB",
    "wof:name":"S26 1JP",
    "wof:placetype":"postalcode"
},
  "geometry": {"coordinates":[-1.26051234976245,53.35128829790095],"type":"Point"}
}