{
  "type": "Feature",
  "properties": {
    "iso:country": "GB",
    "wof:name": "M24 1QJ",
    "wof:placetype": "postalcode"
  },
  "geometry": {"coordinates":[-2.198793,53.546368],"type":"Point"}
}
