{
  "type": "Feature",
  "properties": {
    "iso:country":"GB",
    "wof:name":"M24 1QJ",
    "wof:placetype":"postalcode"
},
  "geometry": {"coordinates":[-2.19879349162729,53.54636763772485],"type":"Point"}
}