{
  "type": "Feature",
  "properties": {
    "iso:country": "GB",
    "wof:name": "YO43 3PU",
    "wof:placetype": "postalcode"
  },
  "geometry": {"coordinates":[-0.682118,53.870656],"type":"Point"}
}
