{
  "type": "Feature",
  "properties": {
    "iso:country":"GB",
    "wof:name":"YO43 3PU",
    "wof:placetype":"postalcode"
},
  "geometry": {"coordinates":[-0.6821176613508,53.87065579140082],"type":"Point"}
}