{
  "type": "Feature",
  "properties": {
    "date:inception_lower": "2007-01-01",
    "date:inception_upper": "2007-01-01",
    "iso:country": "GB",
    "wof:name": "CM20 2DU",
    "wof:placetype": "postalcode"
  },
  "geometry": {"coordinates":[0.117763,51.783541],"type":"Point"}
}
