{
  "type": "Feature",
  "properties": {
    "iso:country":"GB",
    "wof:name":"DY9 9ST",
    "wof:placetype":"postalcode"
},
  "geometry": {"coordinates":[-2.11813354404146,52.39281659518232],"type":"Point"}
}