{
  "type": "Feature",
  "properties": {
    "iso:country":"GB",
    "wof:name":"SE4 1EU",
    "wof:placetype":"postalcode"
},
  "geometry": {"coordinates":[-0.03597487144244,51.45441427868442],"type":"Point"}
}