{
  "type": "Feature",
  "properties": {
    "iso:country":"GB",
    "wof:name":"PR3 2EX",
    "wof:placetype":"postalcode"
},
  "geometry": {"coordinates":[-2.67460363632652,53.86719164644761],"type":"Point"}
}