{
  "type": "Feature",
  "properties": {
    "iso:country": "GB",
    "wof:name": "PR3 2EX",
    "wof:placetype": "postalcode"
  },
  "geometry": {"coordinates":[-2.674604,53.867192],"type":"Point"}
}
