{
  "type": "Feature",
  "properties": {
    "iso:country":"GB",
    "wof:name":"CO12 4EX",
    "wof:placetype":"postalcode"
},
  "geometry": {"coordinates":[1.2606540311117,51.93343633389733],"type":"Point"}
}