{
  "type": "Feature",
  "properties": {
    "iso:country":"GB",
    "wof:name":"TF2 7DA",
    "wof:placetype":"postalcode"
},
  "geometry": {"coordinates":[-2.43995060074704,52.70467181530275],"type":"Point"}
}