{
  "type": "Feature",
  "properties": {
    "iso:country":"GB",
    "wof:name":"CM7 9RH",
    "wof:placetype":"postalcode"
},
  "geometry": {"coordinates":[0.56205130426305,51.89051640329011],"type":"Point"}
}