{
  "type": "Feature",
  "properties": {
    "date:inception_lower": "2007-11-01",
    "date:inception_upper": "2007-11-01",
    "iso:country": "GB",
    "wof:name": "CM7 9RH",
    "wof:placetype": "postalcode"
  },
  "geometry": {"coordinates":[0.562051,51.890516],"type":"Point"}
}
