{
  "type": "Feature",
  "properties": {
    "iso:country":"GB",
    "wof:name":"MK16 8HE",
    "wof:placetype":"postalcode"
},
  "geometry": {"coordinates":[-0.7216926498934,52.08646233685731],"type":"Point"}
}