{
  "type": "Feature",
  "properties": {
    "iso:country": "GB",
    "wof:name": "TA11 7PH",
    "wof:placetype": "postalcode"
  },
  "geometry": {"coordinates":[-2.727436,51.054039],"type":"Point"}
}
