{
  "type": "Feature",
  "properties": {
    "iso:country":"GB",
    "wof:name":"W1T 2RD",
    "wof:placetype":"postalcode"
},
  "geometry": {"coordinates":[-0.13370003276507,51.51914748734438],"type":"Point"}
}