{
  "type": "Feature",
  "properties": {
    "iso:country": "GB",
    "wof:name": "PL9 7DG",
    "wof:placetype": "postalcode"
  },
  "geometry": {"coordinates":[-4.093587,50.363157],"type":"Point"}
}
