{
  "type": "Feature",
  "properties": {
    "iso:country":"GB",
    "wof:name":"PL9 7DG",
    "wof:placetype":"postalcode"
},
  "geometry": {"coordinates":[-4.09380466381758,50.36268205249602],"type":"Point"}
}