{
  "type": "Feature",
  "properties": {
    "iso:country":"GB",
    "wof:name":"BB6 8AG",
    "wof:placetype":"postalcode"
},
  "geometry": {"coordinates":[-2.45453181013196,53.81993492471108],"type":"Point"}
}