{
  "type": "Feature",
  "properties": {
    "iso:country": "GB",
    "wof:name": "BB6 8AG",
    "wof:placetype": "postalcode"
  },
  "geometry": {"coordinates":[-2.454532,53.819935],"type":"Point"}
}
