{
  "type": "Feature",
  "properties": {
    "date:inception_lower": "1998-12-01",
    "date:inception_upper": "1998-12-01",
    "iso:country": "GB",
    "wof:name": "BB6 8AG",
    "wof:placetype": "postalcode"
  },
  "geometry": {"coordinates":[-2.454532,53.819935],"type":"Point"}
}
