{
  "type": "Feature",
  "properties": {
    "iso:country": "GB",
    "wof:name": "L9 1LE",
    "wof:placetype": "postalcode"
  },
  "geometry": {"coordinates":[-2.95243,53.454029],"type":"Point"}
}
