{
  "type": "Feature",
  "properties": {
    "iso:country":"GB",
    "wof:name":"PE15 9JE",
    "wof:placetype":"postalcode"
},
  "geometry": {"coordinates":[0.0883660006276,52.54935030979338],"type":"Point"}
}