{
  "type": "Feature",
  "properties": {
    "iso:country":"GB",
    "wof:name":"TF11 8QA",
    "wof:placetype":"postalcode"
},
  "geometry": {"coordinates":[-2.27802587311801,52.67419302767495],"type":"Point"}
}