{
  "type": "Feature",
  "properties": {
    "date:inception_lower":"1980-01-01",
    "date:inception_upper":"1980-01-31",
    "iso:country":"GB",
    "wof:name":"TF11 8QA",
    "wof:placetype":"postalcode"
},
  "geometry": {"coordinates":[-2.278026,52.674193],"type":"Point"}
}