{
  "type": "Feature",
  "properties": {
    "iso:country":"GB",
    "wof:name":"GU9 7DP",
    "wof:placetype":"postalcode"
},
  "geometry": {"coordinates":[-0.80121692569684,51.21358494156949],"type":"Point"}
}