{
  "type": "Feature",
  "properties": {
    "date:inception_lower":"1980-01-01",
    "date:inception_upper":"1980-01-31",
    "iso:country":"GB",
    "wof:name":"BH16 5AF",
    "wof:placetype":"postalcode"
},
  "geometry": {"coordinates":[-2.019981,50.727204],"type":"Point"}
}