{
  "type": "Feature",
  "properties": {
    "iso:country": "GB",
    "wof:name": "BH16 5AF",
    "wof:placetype": "postalcode"
  },
  "geometry": {"coordinates":[-2.019981,50.727204],"type":"Point"}
}
