{
  "type": "Feature",
  "properties": {
    "iso:country":"GB",
    "wof:name":"BH16 5AF",
    "wof:placetype":"postalcode"
},
  "geometry": {"coordinates":[-2.01998119863914,50.72720437428524],"type":"Point"}
}