{
  "type": "Feature",
  "properties": {
    "iso:country": "GB",
    "wof:name": "B6 4HT",
    "wof:placetype": "postalcode"
  },
  "geometry": {"coordinates":[-1.890934,52.497907],"type":"Point"}
}
