{
  "type": "Feature",
  "properties": {
    "iso:country":"GB",
    "wof:name":"BD14 6JW",
    "wof:placetype":"postalcode"
},
  "geometry": {"coordinates":[-1.81566338109879,53.77900555532578],"type":"Point"}
}