{
  "type": "Feature",
  "properties": {
    "iso:country": "GB",
    "wof:name": "BD14 6JW",
    "wof:placetype": "postalcode"
  },
  "geometry": {"coordinates":[-1.815636,53.778939],"type":"Point"}
}
