{
  "type": "Feature",
  "properties": {
    "iso:country":"GB",
    "wof:name":"M28 3PL",
    "wof:placetype":"postalcode"
},
  "geometry": {"coordinates":[-2.39285151643647,53.52785647353774],"type":"Point"}
}