{
  "type": "Feature",
  "properties": {
    "iso:country":"GB",
    "wof:name":"SG12 8HX",
    "wof:placetype":"postalcode"
},
  "geometry": {"coordinates":[0.01104753573511,51.78992004495512],"type":"Point"}
}