{
  "type": "Feature",
  "properties": {
    "date:inception_lower": "1980-01-01",
    "date:inception_upper": "1980-01-01",
    "iso:country": "GB",
    "wof:name": "SG12 8HX",
    "wof:placetype": "postalcode"
  },
  "geometry": {"coordinates":[0.011048,51.78992],"type":"Point"}
}
