{
  "type": "Feature",
  "properties": {
    "date:inception_lower": "2010-09-01",
    "date:inception_upper": "2010-09-01",
    "iso:country": "GB",
    "wof:name": "TW7 6GP",
    "wof:placetype": "postalcode"
  },
  "geometry": {"coordinates":[-0.323997,51.476142],"type":"Point"}
}
