{
  "type": "Feature",
  "properties": {
    "iso:country":"GB",
    "wof:name":"TW7 6GP",
    "wof:placetype":"postalcode"
},
  "geometry": {"coordinates":[-0.32399737492716,51.47614199613873],"type":"Point"}
}