{
  "type": "Feature",
  "properties": {
    "iso:country":"GB",
    "wof:name":"DL2 2EN",
    "wof:placetype":"postalcode"
},
  "geometry": {"coordinates":[-1.52866732356367,54.48909137368604],"type":"Point"}
}