{
  "type": "Feature",
  "properties": {
    "iso:country": "GB",
    "wof:name": "WS3 1DB",
    "wof:placetype": "postalcode"
  },
  "geometry": {"coordinates":[-1.984717,52.610089],"type":"Point"}
}
