{
  "type": "Feature",
  "properties": {
    "date:inception_lower":"1980-01-01",
    "date:inception_upper":"1980-01-31",
    "iso:country":"GB",
    "wof:name":"G43 1BB",
    "wof:placetype":"postalcode"
},
  "geometry": {"coordinates":[-4.327412,55.814037],"type":"Point"}
}