{
  "type": "Feature",
  "properties": {
    "iso:country":"GB",
    "wof:name":"G43 1BB",
    "wof:placetype":"postalcode"
},
  "geometry": {"coordinates":[-4.32741212317446,55.8140372033642],"type":"Point"}
}