{
  "type": "Feature",
  "properties": {
    "iso:country": "GB",
    "wof:name": "YO61 3UY",
    "wof:placetype": "postalcode"
  },
  "geometry": {"coordinates":[-1.248165,54.132085],"type":"Point"}
}
