{
  "type": "Feature",
  "properties": {
    "iso:country":"GB",
    "wof:name":"PE10 0AX",
    "wof:placetype":"postalcode"
},
  "geometry": {"coordinates":[-0.33744735234346,52.77030862071452],"type":"Point"}
}