{
  "type": "Feature",
  "properties": {
    "iso:country": "GB",
    "wof:name": "PE10 0AX",
    "wof:placetype": "postalcode"
  },
  "geometry": {"coordinates":[-0.337447,52.770309],"type":"Point"}
}
