{
  "type": "Feature",
  "properties": {
    "date:inception_lower":"1999-12-01",
    "date:inception_upper":"1999-12-31",
    "iso:country":"GB",
    "wof:name":"RH12 1WR",
    "wof:placetype":"postalcode"
},
  "geometry": {"coordinates":[-0.352082,51.067259],"type":"Point"}
}