{
  "type": "Feature",
  "properties": {
    "iso:country": "GB",
    "wof:name": "RH12 1WR",
    "wof:placetype": "postalcode"
  },
  "geometry": {"coordinates":[-0.352082,51.067259],"type":"Point"}
}
