{
  "type": "Feature",
  "properties": {
    "iso:country":"GB",
    "wof:name":"NE10 8EE",
    "wof:placetype":"postalcode"
},
  "geometry": {"coordinates":[-1.54371885546056,54.94824199971563],"type":"Point"}
}