{
  "type": "Feature",
  "properties": {
    "iso:country":"GB",
    "wof:name":"BA14 7JG",
    "wof:placetype":"postalcode"
},
  "geometry": {"coordinates":[-2.1964426697028,51.32371823067479],"type":"Point"}
}