{
  "type": "Feature",
  "properties": {
    "iso:country": "GB",
    "wof:name": "SL3 6QA",
    "wof:placetype": "postalcode"
  },
  "geometry": {"coordinates":[-0.547026,51.511822],"type":"Point"}
}
