{
  "type": "Feature",
  "properties": {
    "date:inception_lower":"1983-01-01",
    "date:inception_upper":"1983-01-31",
    "iso:country":"GB",
    "wof:name":"SL3 6QA",
    "wof:placetype":"postalcode"
},
  "geometry": {"coordinates":[-0.547026,51.511822],"type":"Point"}
}