{
  "type": "Feature",
  "properties": {
    "iso:country":"GB",
    "wof:name":"CR0 2LG",
    "wof:placetype":"postalcode"
},
  "geometry": {"coordinates":[-0.09682236509767,51.38780192856601],"type":"Point"}
}