{
  "type": "Feature",
  "properties": {
    "date:inception_lower": "1998-12-01",
    "date:inception_upper": "1998-12-01",
    "iso:country": "GB",
    "wof:name": "G66 7JY",
    "wof:placetype": "postalcode"
  },
  "geometry": {"coordinates":[-4.214909,55.982213],"type":"Point"}
}
