{
  "type": "Feature",
  "properties": {
    "iso:country":"GB",
    "wof:name":"SK14 3LJ",
    "wof:placetype":"postalcode"
},
  "geometry": {"coordinates":[-2.03454416980361,53.44524679142673],"type":"Point"}
}