{
  "type": "Feature",
  "properties": {
    "iso:country": "GB",
    "wof:name": "IV4 7GL",
    "wof:placetype": "postalcode"
  },
  "geometry": {"coordinates":[-4.489093,57.441914],"type":"Point"}
}
