{
  "type": "Feature",
  "properties": {
    "iso:country":"GB",
    "wof:name":"PO4 8AF",
    "wof:placetype":"postalcode"
},
  "geometry": {"coordinates":[-1.06800423983588,50.7937266115358],"type":"Point"}
}