{
  "type": "Feature",
  "properties": {
    "date:inception_lower":"1980-01-01",
    "date:inception_upper":"1980-01-31",
    "iso:country":"GB",
    "wof:name":"PO4 8AF",
    "wof:placetype":"postalcode"
},
  "geometry": {"coordinates":[-1.068004,50.793727],"type":"Point"}
}