{
  "type": "Feature",
  "properties": {
    "date:inception_lower": "1994-05-01",
    "date:inception_upper": "1994-05-01",
    "iso:country": "GB",
    "wof:name": "M20 2WZ",
    "wof:placetype": "postalcode"
  },
  "geometry": {"coordinates":[-2.240954,53.423292],"type":"Point"}
}
