{
  "type": "Feature",
  "properties": {
    "iso:country":"GB",
    "wof:name":"M20 2WZ",
    "wof:placetype":"postalcode"
},
  "geometry": {"coordinates":[-2.24095449238915,53.42329206512767],"type":"Point"}
}