{
  "type": "Feature",
  "properties": {
    "iso:country":"GB",
    "wof:name":"LL24 0YY",
    "wof:placetype":"postalcode"
},
  "geometry": {"coordinates":[-3.79633582863231,53.04042110363405],"type":"Point"}
}