{
  "type": "Feature",
  "properties": {
    "iso:country": "GB",
    "wof:name": "NR21 7NA",
    "wof:placetype": "postalcode"
  },
  "geometry": {"coordinates":[0.842426,52.820304],"type":"Point"}
}
