{
  "type": "Feature",
  "properties": {
    "iso:country":"GB",
    "wof:name":"NR21 7NA",
    "wof:placetype":"postalcode"
},
  "geometry": {"coordinates":[0.84242598491442,52.82030419487563],"type":"Point"}
}