{
  "type": "Feature",
  "properties": {
    "iso:country": "GB",
    "wof:name": "KW14 8AS",
    "wof:placetype": "postalcode"
  },
  "geometry": {"coordinates":[-3.516598,58.595937],"type":"Point"}
}
