{
  "type": "Feature",
  "properties": {
    "date:inception_lower": "1985-10-01",
    "date:inception_upper": "1985-10-01",
    "iso:country": "GB",
    "wof:name": "FY5 3EA",
    "wof:placetype": "postalcode"
  },
  "geometry": {"coordinates":[-3.042249,53.871186],"type":"Point"}
}
