{
  "type": "Feature",
  "properties": {
    "iso:country": "GB",
    "wof:name": "DL9 4PN",
    "wof:placetype": "postalcode"
  },
  "geometry": {"coordinates":[-1.687863,54.380019],"type":"Point"}
}
