{
  "type": "Feature",
  "properties": {
    "date:inception_lower": "1980-01-01",
    "date:inception_upper": "1980-01-01",
    "iso:country": "GB",
    "wof:name": "SW9 7QF",
    "wof:placetype": "postalcode"
  },
  "geometry": {"coordinates":[-0.113427,51.464257],"type":"Point"}
}
