{
  "type": "Feature",
  "properties": {
    "iso:country":"GB",
    "wof:name":"SW9 7QF",
    "wof:placetype":"postalcode"
},
  "geometry": {"coordinates":[-0.1137741539614,51.46449565502961],"type":"Point"}
}