{
  "type": "Feature",
  "properties": {
    "iso:country": "GB",
    "wof:name": "SW9 7QF",
    "wof:placetype": "postalcode"
  },
  "geometry": {"coordinates":[-0.113427,51.464257],"type":"Point"}
}
