{
  "type": "Feature",
  "properties": {
    "iso:country": "GB",
    "wof:name": "PE28 2BS",
    "wof:placetype": "postalcode"
  },
  "geometry": {"coordinates":[-0.108522,52.33375],"type":"Point"}
}
