{
  "type": "Feature",
  "properties": {
    "iso:country":"GB",
    "wof:name":"PE28 2BS",
    "wof:placetype":"postalcode"
},
  "geometry": {"coordinates":[-0.10852160221416,52.33374993110072],"type":"Point"}
}