{
  "type": "Feature",
  "properties": {
    "iso:country": "GB",
    "wof:name": "TN21 0QW",
    "wof:placetype": "postalcode"
  },
  "geometry": {"coordinates":[0.205312,50.963889],"type":"Point"}
}
