{
  "type": "Feature",
  "properties": {
    "iso:country":"GB",
    "wof:name":"SK11 6GD",
    "wof:placetype":"postalcode"
},
  "geometry": {"coordinates":[-2.12952062735528,53.25890986145077],"type":"Point"}
}