{
  "type": "Feature",
  "properties": {
    "iso:country": "GB",
    "wof:name": "SK11 6GD",
    "wof:placetype": "postalcode"
  },
  "geometry": {"coordinates":[-2.129521,53.25891],"type":"Point"}
}
