{
  "type": "Feature",
  "properties": {
    "date:inception_lower": "2016-01-01",
    "date:inception_upper": "2016-01-01",
    "iso:country": "GB",
    "wof:name": "CT21 6FN",
    "wof:placetype": "postalcode"
  },
  "geometry": {"coordinates":[1.076815,51.064526],"type":"Point"}
}
