{
  "type": "Feature",
  "properties": {
    "iso:country": "GB",
    "wof:name": "SY5 8ND",
    "wof:placetype": "postalcode"
  },
  "geometry": {"coordinates":[-2.816737,52.687086],"type":"Point"}
}
