{
  "type": "Feature",
  "properties": {
    "iso:country":"GB",
    "wof:name":"SY5 8ND",
    "wof:placetype":"postalcode"
},
  "geometry": {"coordinates":[-2.81673700341538,52.68708574004297],"type":"Point"}
}