{
  "type": "Feature",
  "properties": {
    "iso:country":"GB",
    "wof:name":"SW4 0DJ",
    "wof:placetype":"postalcode"
},
  "geometry": {"coordinates":[-0.13895480258124,51.46553654037649],"type":"Point"}
}