{
  "type": "Feature",
  "properties": {
    "date:inception_lower":"2009-08-01",
    "date:inception_upper":"2009-08-31",
    "iso:country":"GB",
    "wof:name":"SN5 4FA",
    "wof:placetype":"postalcode"
},
  "geometry": {"coordinates":[-1.865643,51.588113],"type":"Point"}
}