{
  "type": "Feature",
  "properties": {
    "iso:country":"GB",
    "wof:name":"SN5 4FA",
    "wof:placetype":"postalcode"
},
  "geometry": {"coordinates":[-1.86564342208571,51.58811288686049],"type":"Point"}
}