{
  "type": "Feature",
  "properties": {
    "iso:country": "GB",
    "wof:name": "SN5 4FA",
    "wof:placetype": "postalcode"
  },
  "geometry": {"coordinates":[-1.865643,51.588113],"type":"Point"}
}
