{
  "type": "Feature",
  "properties": {
    "iso:country":"GB",
    "wof:name":"BL1 6RT",
    "wof:placetype":"postalcode"
},
  "geometry": {"coordinates":[-2.435751784349,53.60401910592252],"type":"Point"}
}