{
  "type": "Feature",
  "properties": {
    "iso:country":"GB",
    "wof:name":"DY6 0DT",
    "wof:placetype":"postalcode"
},
  "geometry": {"coordinates":[-2.18457228691411,52.50232871501519],"type":"Point"}
}