{
  "type": "Feature",
  "properties": {
    "date:inception_lower": "2016-07-01",
    "date:inception_upper": "2016-07-01",
    "iso:country": "GB",
    "wof:name": "RG29 1FQ",
    "wof:placetype": "postalcode"
  },
  "geometry": {"coordinates":[-0.930791,51.257229],"type":"Point"}
}
