{
  "type": "Feature",
  "properties": {
    "date:inception_lower": "1980-01-01",
    "date:inception_upper": "1980-01-01",
    "iso:country": "GB",
    "wof:name": "KT7 0SS",
    "wof:placetype": "postalcode"
  },
  "geometry": {"coordinates":[-0.325962,51.389375],"type":"Point"}
}
