{
  "type": "Feature",
  "properties": {
    "iso:country": "GB",
    "wof:name": "KT7 0SS",
    "wof:placetype": "postalcode"
  },
  "geometry": {"coordinates":[-0.325962,51.389375],"type":"Point"}
}
