{
  "type": "Feature",
  "properties": {
    "iso:country":"GB",
    "wof:name":"L39 4XB",
    "wof:placetype":"postalcode"
},
  "geometry": {"coordinates":[-2.88405313031409,53.56450403776847],"type":"Point"}
}