{
  "type": "Feature",
  "properties": {
    "date:inception_lower": "1994-05-01",
    "date:inception_upper": "1994-05-01",
    "iso:country": "GB",
    "wof:name": "M25 9XW",
    "wof:placetype": "postalcode"
  },
  "geometry": {"coordinates":[-2.28947,53.516609],"type":"Point"}
}
