{
  "type": "Feature",
  "properties": {
    "iso:country":"GB",
    "wof:name":"M25 9XW",
    "wof:placetype":"postalcode"
},
  "geometry": {"coordinates":[-2.28939663661929,53.51660173058522],"type":"Point"}
}