{
  "type": "Feature",
  "properties": {
    "date:inception_lower": "1997-12-01",
    "date:inception_upper": "1997-12-01",
    "iso:country": "GB",
    "wof:name": "BS40 6LA",
    "wof:placetype": "postalcode"
  },
  "geometry": {"coordinates":[-2.652002,51.309721],"type":"Point"}
}
