{
  "type": "Feature",
  "properties": {
    "iso:country":"GB",
    "wof:name":"BS40 6LA",
    "wof:placetype":"postalcode"
},
  "geometry": {"coordinates":[-2.65200173938221,51.30972141139695],"type":"Point"}
}