{
  "type": "Feature",
  "properties": {
    "iso:country":"GB",
    "wof:name":"SW14 7RN",
    "wof:placetype":"postalcode"
},
  "geometry": {"coordinates":[-0.27268445345672,51.46370720776011],"type":"Point"}
}