{
  "type": "Feature",
  "properties": {
    "date:inception_lower":"1980-01-01",
    "date:inception_upper":"1980-01-31",
    "iso:country":"GB",
    "wof:name":"LL26 0LQ",
    "wof:placetype":"postalcode"
},
  "geometry": {"coordinates":[-3.751201,53.169879],"type":"Point"}
}