{
  "type": "Feature",
  "properties": {
    "iso:country": "GB",
    "wof:name": "LL26 0LQ",
    "wof:placetype": "postalcode"
  },
  "geometry": {"coordinates":[-3.751201,53.169879],"type":"Point"}
}
