{
  "type": "Feature",
  "properties": {
    "date:inception_lower": "1999-06-01",
    "date:inception_upper": "1999-06-01",
    "iso:country": "GB",
    "wof:name": "L33 1QZ",
    "wof:placetype": "postalcode"
  },
  "geometry": {"coordinates":[-2.872994,53.495238],"type":"Point"}
}
