{
  "type": "Feature",
  "properties": {
    "iso:country":"GB",
    "wof:name":"HR1 1XQ",
    "wof:placetype":"postalcode"
},
  "geometry": {"coordinates":[-2.68462617712199,52.05079873024423],"type":"Point"}
}