{
  "type": "Feature",
  "properties": {
    "iso:country":"GB",
    "wof:name":"TN4 8AH",
    "wof:placetype":"postalcode"
},
  "geometry": {"coordinates":[0.25193190873359,51.12903029927273],"type":"Point"}
}