{
  "type": "Feature",
  "properties": {
    "date:inception_lower":"2009-05-01",
    "date:inception_upper":"2009-05-31",
    "iso:country":"GB",
    "wof:name":"TN4 8AH",
    "wof:placetype":"postalcode"
},
  "geometry": {"coordinates":[0.251932,51.12903],"type":"Point"}
}