{
  "type": "Feature",
  "properties": {
    "date:inception_lower": "1980-01-01",
    "date:inception_upper": "1980-01-01",
    "iso:country": "GB",
    "wof:name": "G15 7NZ",
    "wof:placetype": "postalcode"
  },
  "geometry": {"coordinates":[-4.35088,55.9117],"type":"Point"}
}
