{
  "type": "Feature",
  "properties": {
    "date:inception_lower": "1980-01-01",
    "date:inception_upper": "1980-01-01",
    "iso:country": "GB",
    "wof:name": "G53 7BL",
    "wof:placetype": "postalcode"
  },
  "geometry": {"coordinates":[-4.360521,55.814368],"type":"Point"}
}
