{
  "type": "Feature",
  "properties": {
    "iso:country":"GB",
    "wof:name":"CV12 0QB",
    "wof:placetype":"postalcode"
},
  "geometry": {"coordinates":[-1.50350121380208,52.47877775668661],"type":"Point"}
}