{
  "type": "Feature",
  "properties": {
    "date:inception_lower":"1980-01-01",
    "date:inception_upper":"1980-01-31",
    "iso:country":"GB",
    "wof:name":"MK16 9LA",
    "wof:placetype":"postalcode"
},
  "geometry": {"coordinates":[-0.63169,52.117757],"type":"Point"}
}