{
  "type": "Feature",
  "properties": {
    "iso:country": "GB",
    "wof:name": "NN9 6LR",
    "wof:placetype": "postalcode"
  },
  "geometry": {"coordinates":[-0.532549,52.349036],"type":"Point"}
}
