{
  "type": "Feature",
  "properties": {
    "iso:country": "GB",
    "wof:name": "LN11 8AA",
    "wof:placetype": "postalcode"
  },
  "geometry": {"coordinates":[0.011385,53.368902],"type":"Point"}
}
