{
  "type": "Feature",
  "properties": {
    "iso:country":"GB",
    "wof:name":"RH15 9QE",
    "wof:placetype":"postalcode"
},
  "geometry": {"coordinates":[-0.14485482984947,50.95114487880453],"type":"Point"}
}