{
  "type": "Feature",
  "properties": {
    "iso:country":"GB",
    "wof:name":"SE12 0RP",
    "wof:placetype":"postalcode"
},
  "geometry": {"coordinates":[0.00453356584017,51.44860271391783],"type":"Point"}
}