{
  "type": "Feature",
  "properties": {
    "date:inception_lower": "1980-01-01",
    "date:inception_upper": "1980-01-01",
    "iso:country": "GB",
    "wof:name": "DN18 5EE",
    "wof:placetype": "postalcode"
  },
  "geometry": {"coordinates":[-0.444246,53.678473],"type":"Point"}
}
