{
  "type": "Feature",
  "properties": {
    "iso:country": "GB",
    "wof:name": "DN18 5EE",
    "wof:placetype": "postalcode"
  },
  "geometry": {"coordinates":[-0.444246,53.678473],"type":"Point"}
}
