{
  "type": "Feature",
  "properties": {
    "iso:country":"GB",
    "wof:name":"DN18 5EE",
    "wof:placetype":"postalcode"
},
  "geometry": {"coordinates":[-0.44424574703625,53.67847320999744],"type":"Point"}
}