{
  "type": "Feature",
  "properties": {
    "iso:country": "GB",
    "wof:name": "SO42 7WF",
    "wof:placetype": "postalcode"
  },
  "geometry": {"coordinates":[-1.473713,50.80788],"type":"Point"}
}
