{
  "type": "Feature",
  "properties": {
    "iso:country":"GB",
    "wof:name":"TN21 0JY",
    "wof:placetype":"postalcode"
},
  "geometry": {"coordinates":[0.22243591603383,50.89922317442088],"type":"Point"}
}