{
  "type": "Feature",
  "properties": {
    "date:inception_lower": "1980-01-01",
    "date:inception_upper": "1980-01-01",
    "iso:country": "GB",
    "wof:name": "TN21 0JY",
    "wof:placetype": "postalcode"
  },
  "geometry": {"coordinates":[0.222494,50.899245],"type":"Point"}
}
