{
  "type": "Feature",
  "properties": {
    "iso:country": "GB",
    "wof:name": "TN21 0JY",
    "wof:placetype": "postalcode"
  },
  "geometry": {"coordinates":[0.222436,50.899223],"type":"Point"}
}
