{
  "type": "Feature",
  "properties": {
    "iso:country": "GB",
    "wof:name": "NG2 7ND",
    "wof:placetype": "postalcode"
  },
  "geometry": {"coordinates":[-1.134326,52.929968],"type":"Point"}
}
