{
  "type": "Feature",
  "properties": {
    "iso:country":"GB",
    "wof:name":"DE24 9GP",
    "wof:placetype":"postalcode"
},
  "geometry": {"coordinates":[-1.48421055575699,52.88602060560224],"type":"Point"}
}