{
  "type": "Feature",
  "properties": {
    "iso:country": "GB",
    "wof:name": "DE24 9GP",
    "wof:placetype": "postalcode"
  },
  "geometry": {"coordinates":[-1.484211,52.886021],"type":"Point"}
}
