{
  "type": "Feature",
  "properties": {
    "iso:country": "GB",
    "wof:name": "PE1 4FT",
    "wof:placetype": "postalcode"
  },
  "geometry": {"coordinates":[-0.229899,52.598091],"type":"Point"}
}
