{
  "type": "Feature",
  "properties": {
    "date:inception_lower":"2003-02-01",
    "date:inception_upper":"2003-02-28",
    "iso:country":"GB",
    "wof:name":"L40 5BF",
    "wof:placetype":"postalcode"
},
  "geometry": {"coordinates":[-2.834253,53.596439],"type":"Point"}
}