{
  "type": "Feature",
  "properties": {
    "iso:country":"GB",
    "wof:name":"L40 5BF",
    "wof:placetype":"postalcode"
},
  "geometry": {"coordinates":[-2.83425274711435,53.59643866335345],"type":"Point"}
}