{
  "type": "Feature",
  "properties": {
    "date:inception_lower": "2000-06-01",
    "date:inception_upper": "2000-06-01",
    "iso:country": "GB",
    "wof:name": "SW10 9LB",
    "wof:placetype": "postalcode"
  },
  "geometry": {"coordinates":[-0.187339,51.486097],"type":"Point"}
}
