{
  "type": "Feature",
  "properties": {
    "iso:country":"GB",
    "wof:name":"SW10 9LB",
    "wof:placetype":"postalcode"
},
  "geometry": {"coordinates":[-0.18737680594674,51.48611463515292],"type":"Point"}
}