{
  "type": "Feature",
  "properties": {
    "iso:country":"GB",
    "wof:name":"CW10 9DJ",
    "wof:placetype":"postalcode"
},
  "geometry": {"coordinates":[-2.44805941965589,53.18820398793262],"type":"Point"}
}