{
  "type": "Feature",
  "properties": {
    "iso:country":"GB",
    "wof:name":"G76 7UX",
    "wof:placetype":"postalcode"
},
  "geometry": {"coordinates":[-4.29523119616473,55.78472247270316],"type":"Point"}
}