{
  "type": "Feature",
  "properties": {
    "iso:country": "GB",
    "wof:name": "YO18 7RZ",
    "wof:placetype": "postalcode"
  },
  "geometry": {"coordinates":[-0.72009,54.237121],"type":"Point"}
}
