{
  "type": "Feature",
  "properties": {
    "iso:country":"GB",
    "wof:name":"YO18 7RZ",
    "wof:placetype":"postalcode"
},
  "geometry": {"coordinates":[-0.72011697107899,54.23725784185486],"type":"Point"}
}