{
  "type": "Feature",
  "properties": {
    "iso:country":"GB",
    "wof:name":"LA13 0PA",
    "wof:placetype":"postalcode"
},
  "geometry": {"coordinates":[-3.20073875098757,54.13649365187522],"type":"Point"}
}