{
  "type": "Feature",
  "properties": {
    "date:inception_lower":"2015-08-01",
    "date:inception_upper":"2015-08-31",
    "iso:country":"GB",
    "wof:name":"EH16 4WE",
    "wof:placetype":"postalcode"
},
  "geometry": {"coordinates":[-3.120259,55.924059],"type":"Point"}
}