{
  "type": "Feature",
  "properties": {
    "iso:country":"GB",
    "wof:name":"EH16 4WE",
    "wof:placetype":"postalcode"
},
  "geometry": {"coordinates":[-3.12025866338014,55.92405917752015],"type":"Point"}
}