{
  "type": "Feature",
  "properties": {
    "date:inception_lower": "1997-06-01",
    "date:inception_upper": "1997-06-01",
    "iso:country": "GB",
    "wof:name": "S20 4GG",
    "wof:placetype": "postalcode"
  },
  "geometry": {"coordinates":[-1.349654,53.325938],"type":"Point"}
}
