{
  "type": "Feature",
  "properties": {
    "iso:country":"GB",
    "wof:name":"S20 4GG",
    "wof:placetype":"postalcode"
},
  "geometry": {"coordinates":[-1.3496386444092,53.32591926935393],"type":"Point"}
}