{
  "type": "Feature",
  "properties": {
    "iso:country":"GB",
    "wof:name":"LD6 5EF",
    "wof:placetype":"postalcode"
},
  "geometry": {"coordinates":[-3.50400086432195,52.30344638480948],"type":"Point"}
}