{
  "type": "Feature",
  "properties": {
    "date:inception_lower":"1980-01-01",
    "date:inception_upper":"1980-01-31",
    "iso:country":"GB",
    "wof:name":"LD6 5EF",
    "wof:placetype":"postalcode"
},
  "geometry": {"coordinates":[-3.504001,52.303446],"type":"Point"}
}