{
  "type": "Feature",
  "properties": {
    "iso:country":"GB",
    "wof:name":"SW6 4BL",
    "wof:placetype":"postalcode"
},
  "geometry": {"coordinates":[-0.19750000160308,51.47594730193907],"type":"Point"}
}