{
  "type": "Feature",
  "properties": {
    "iso:country": "GB",
    "wof:name": "LA12 9AU",
    "wof:placetype": "postalcode"
  },
  "geometry": {"coordinates":[-3.083279,54.196308],"type":"Point"}
}
