{
  "type": "Feature",
  "properties": {
    "date:inception_lower": "1980-01-01",
    "date:inception_upper": "1980-01-01",
    "iso:country": "GB",
    "wof:name": "LA12 9AU",
    "wof:placetype": "postalcode"
  },
  "geometry": {"coordinates":[-3.083279,54.196308],"type":"Point"}
}
