{
  "type": "Feature",
  "properties": {
    "iso:country":"GB",
    "wof:name":"TA3 6SU",
    "wof:placetype":"postalcode"
},
  "geometry": {"coordinates":[-2.95774711926154,50.991433153782],"type":"Point"}
}