{
  "type": "Feature",
  "properties": {
    "iso:country": "GB",
    "wof:name": "ME17 3NW",
    "wof:placetype": "postalcode"
  },
  "geometry": {"coordinates":[0.604715,51.217083],"type":"Point"}
}
