{
  "type": "Feature",
  "properties": {
    "iso:country":"GB",
    "wof:name":"BD10 8EP",
    "wof:placetype":"postalcode"
},
  "geometry": {"coordinates":[-1.72193596216772,53.82598497321621],"type":"Point"}
}