{
  "type": "Feature",
  "properties": {
    "iso:country":"GB",
    "wof:name":"NN6 9QL",
    "wof:placetype":"postalcode"
},
  "geometry": {"coordinates":[-0.82617832006709,52.33971484341466],"type":"Point"}
}