{
  "type": "Feature",
  "properties": {
    "date:inception_lower": "1980-01-01",
    "date:inception_upper": "1980-01-01",
    "iso:country": "GB",
    "wof:name": "NN6 9QL",
    "wof:placetype": "postalcode"
  },
  "geometry": {"coordinates":[-0.826178,52.339715],"type":"Point"}
}
