{
  "type": "Feature",
  "properties": {
    "iso:country":"GB",
    "wof:name":"LL54 7PD",
    "wof:placetype":"postalcode"
},
  "geometry": {"coordinates":[-4.247132916281,53.09589948450261],"type":"Point"}
}