{
  "type": "Feature",
  "properties": {
    "iso:country": "GB",
    "wof:name": "LL54 7PD",
    "wof:placetype": "postalcode"
  },
  "geometry": {"coordinates":[-4.247133,53.095899],"type":"Point"}
}
