{
  "type": "Feature",
  "properties": {
    "iso:country": "GB",
    "wof:name": "EX10 9SB",
    "wof:placetype": "postalcode"
  },
  "geometry": {"coordinates":[-3.238298,50.702111],"type":"Point"}
}
