{
  "type": "Feature",
  "properties": {
    "iso:country":"GB",
    "wof:name":"SS7 3UB",
    "wof:placetype":"postalcode"
},
  "geometry": {"coordinates":[0.60013073896398,51.57493477284125],"type":"Point"}
}