{
  "type": "Feature",
  "properties": {
    "date:inception_lower": "1982-03-01",
    "date:inception_upper": "1982-03-01",
    "iso:country": "GB",
    "wof:name": "SS7 3UB",
    "wof:placetype": "postalcode"
  },
  "geometry": {"coordinates":[0.600047,51.575023],"type":"Point"}
}
