{
  "type": "Feature",
  "properties": {
    "iso:country": "GB",
    "wof:name": "SS7 3UB",
    "wof:placetype": "postalcode"
  },
  "geometry": {"coordinates":[0.600172,51.574939],"type":"Point"}
}
