{
  "type": "Feature",
  "properties": {
    "date:inception_lower": "1994-05-01",
    "date:inception_upper": "1994-05-01",
    "iso:country": "GB",
    "wof:name": "M8 0SY",
    "wof:placetype": "postalcode"
  },
  "geometry": {"coordinates":[-2.237846,53.503096],"type":"Point"}
}
