{
  "type": "Feature",
  "properties": {
    "iso:country": "GB",
    "wof:name": "M8 0SY",
    "wof:placetype": "postalcode"
  },
  "geometry": {"coordinates":[-2.237846,53.503096],"type":"Point"}
}
