{
  "type": "Feature",
  "properties": {
    "iso:country": "GB",
    "wof:name": "BA10 0QH",
    "wof:placetype": "postalcode"
  },
  "geometry": {"coordinates":[-2.470624,51.1209],"type":"Point"}
}
