{
  "type": "Feature",
  "properties": {
    "date:inception_lower": "1980-01-01",
    "date:inception_upper": "1980-01-01",
    "iso:country": "GB",
    "wof:name": "BA10 0QH",
    "wof:placetype": "postalcode"
  },
  "geometry": {"coordinates":[-2.470597,51.121035],"type":"Point"}
}
