{
  "type": "Feature",
  "properties": {
    "iso:country":"GB",
    "wof:name":"SK14 1NR",
    "wof:placetype":"postalcode"
},
  "geometry": {"coordinates":[-2.07300480818395,53.45007419002278],"type":"Point"}
}