{
  "type": "Feature",
  "properties": {
    "iso:country":"GB",
    "wof:name":"ST5 3LD",
    "wof:placetype":"postalcode"
},
  "geometry": {"coordinates":[-2.2417442619842,52.98874133770551],"type":"Point"}
}