{
  "type": "Feature",
  "properties": {
    "date:inception_lower": "1980-01-01",
    "date:inception_upper": "1980-01-01",
    "iso:country": "GB",
    "wof:name": "ST5 3LD",
    "wof:placetype": "postalcode"
  },
  "geometry": {"coordinates":[-2.241744,52.988741],"type":"Point"}
}
