{
  "type": "Feature",
  "properties": {
    "date:inception_lower":"1980-01-01",
    "date:inception_upper":"1980-01-31",
    "iso:country":"GB",
    "wof:name":"CF5 3JY",
    "wof:placetype":"postalcode"
},
  "geometry": {"coordinates":[-3.242868,51.494331],"type":"Point"}
}