{
  "type": "Feature",
  "properties": {
    "iso:country": "GB",
    "wof:name": "CT11 8BT",
    "wof:placetype": "postalcode"
  },
  "geometry": {"coordinates":[1.425606,51.336691],"type":"Point"}
}
