{
  "type": "Feature",
  "properties": {
    "date:inception_lower":"1980-01-01",
    "date:inception_upper":"1980-01-31",
    "iso:country":"GB",
    "wof:name":"CT11 8BT",
    "wof:placetype":"postalcode"
},
  "geometry": {"coordinates":[1.425606,51.336691],"type":"Point"}
}