{
  "type": "Feature",
  "properties": {
    "iso:country": "GB",
    "wof:name": "B61 7NQ",
    "wof:placetype": "postalcode"
  },
  "geometry": {"coordinates":[-2.075712,52.326297],"type":"Point"}
}
