{
  "type": "Feature",
  "properties": {
    "iso:country":"GB",
    "wof:name":"B61 7NQ",
    "wof:placetype":"postalcode"
},
  "geometry": {"coordinates":[-2.0757122547733,52.32629743195687],"type":"Point"}
}