{
  "type": "Feature",
  "properties": {
    "date:inception_lower":"1980-01-01",
    "date:inception_upper":"1980-01-31",
    "iso:country":"GB",
    "wof:name":"B66 2RU",
    "wof:placetype":"postalcode"
},
  "geometry": {"coordinates":[-1.952795,52.493654],"type":"Point"}
}