{
  "type": "Feature",
  "properties": {
    "iso:country":"GB",
    "wof:name":"OX12 9JG",
    "wof:placetype":"postalcode"
},
  "geometry": {"coordinates":[-1.44852345956629,51.57772401560497],"type":"Point"}
}