{
  "type": "Feature",
  "properties": {
    "iso:country":"GB",
    "wof:name":"LL11 4YQ",
    "wof:placetype":"postalcode"
},
  "geometry": {"coordinates":[-3.02047898879782,53.06536789621449],"type":"Point"}
}