{
  "type": "Feature",
  "properties": {
    "date:inception_lower": "1993-08-01",
    "date:inception_upper": "1993-08-01",
    "iso:country": "GB",
    "wof:name": "LL11 4YQ",
    "wof:placetype": "postalcode"
  },
  "geometry": {"coordinates":[-3.020479,53.065368],"type":"Point"}
}
