{
  "type": "Feature",
  "properties": {
    "date:inception_lower":"1980-01-01",
    "date:inception_upper":"1980-01-31",
    "iso:country":"GB",
    "wof:name":"NG34 0DY",
    "wof:placetype":"postalcode"
},
  "geometry": {"coordinates":[-0.445581,52.912581],"type":"Point"}
}