{
  "type": "Feature",
  "properties": {
    "iso:country": "GB",
    "wof:name": "NG34 0DY",
    "wof:placetype": "postalcode"
  },
  "geometry": {"coordinates":[-0.445581,52.912581],"type":"Point"}
}
