{
  "type": "Feature",
  "properties": {
    "iso:country":"GB",
    "wof:name":"DN22 7YG",
    "wof:placetype":"postalcode"
},
  "geometry": {"coordinates":[-0.9637516333977,53.330590627047],"type":"Point"}
}