{
  "type": "Feature",
  "properties": {
    "iso:country":"GB",
    "wof:name":"B79 8DS",
    "wof:placetype":"postalcode"
},
  "geometry": {"coordinates":[-1.69973944780257,52.64101296438387],"type":"Point"}
}