{
  "type": "Feature",
  "properties": {
    "date:inception_lower":"1980-01-01",
    "date:inception_upper":"1980-01-31",
    "iso:country":"GB",
    "wof:name":"B79 8DS",
    "wof:placetype":"postalcode"
},
  "geometry": {"coordinates":[-1.699739,52.641013],"type":"Point"}
}