{
  "type": "Feature",
  "properties": {
    "iso:country":"GB",
    "wof:name":"HP21 7PG",
    "wof:placetype":"postalcode"
},
  "geometry": {"coordinates":[-0.79110000188194,51.80419469107625],"type":"Point"}
}