{
  "type": "Feature",
  "properties": {
    "date:inception_lower": "2009-03-01",
    "date:inception_upper": "2009-03-01",
    "iso:country": "GB",
    "wof:name": "TA7 0PJ",
    "wof:placetype": "postalcode"
  },
  "geometry": {"coordinates":[-2.877124,51.097619],"type":"Point"}
}
