{
  "type": "Feature",
  "properties": {
    "date:inception_lower":"1997-06-01",
    "date:inception_upper":"1997-06-30",
    "iso:country":"GB",
    "wof:name":"SK6 8HG",
    "wof:placetype":"postalcode"
},
  "geometry": {"coordinates":[-2.06916,53.373099],"type":"Point"}
}