{
  "type": "Feature",
  "properties": {
    "iso:country":"GB",
    "wof:name":"SK6 8HG",
    "wof:placetype":"postalcode"
},
  "geometry": {"coordinates":[-2.06916016914035,53.3730986188397],"type":"Point"}
}