{
  "type": "Feature",
  "properties": {
    "date:inception_lower": "1986-04-01",
    "date:inception_upper": "1986-04-01",
    "iso:country": "GB",
    "wof:name": "DA11 8SR",
    "wof:placetype": "postalcode"
  },
  "geometry": {"coordinates":[0.346216,51.427989],"type":"Point"}
}
