{
  "type": "Feature",
  "properties": {
    "iso:country": "GB",
    "wof:name": "DA11 8SR",
    "wof:placetype": "postalcode"
  },
  "geometry": {"coordinates":[0.346216,51.427989],"type":"Point"}
}
