{
  "type": "Feature",
  "properties": {
    "iso:country": "GB",
    "wof:name": "CT11 0RU",
    "wof:placetype": "postalcode"
  },
  "geometry": {"coordinates":[1.397589,51.335331],"type":"Point"}
}
