{
  "type": "Feature",
  "properties": {
    "iso:country":"GB",
    "wof:name":"SM6 8RE",
    "wof:placetype":"postalcode"
},
  "geometry": {"coordinates":[-0.1466572592883,51.3592126835114],"type":"Point"}
}