{
  "type": "Feature",
  "properties": {
    "iso:country":"GB",
    "wof:name":"L27 5RE",
    "wof:placetype":"postalcode"
},
  "geometry": {"coordinates":[-2.82653977202057,53.38297477900744],"type":"Point"}
}