{
  "type": "Feature",
  "properties": {
    "iso:country": "GB",
    "wof:name": "CF47 8NS",
    "wof:placetype": "postalcode"
  },
  "geometry": {"coordinates":[-3.387652,51.752716],"type":"Point"}
}
