{
  "type": "Feature",
  "properties": {
    "date:inception_lower": "1980-01-01",
    "date:inception_upper": "1980-01-01",
    "iso:country": "GB",
    "wof:name": "LL14 2DB",
    "wof:placetype": "postalcode"
  },
  "geometry": {"coordinates":[-3.057752,53.005415],"type":"Point"}
}
