{
  "type": "Feature",
  "properties": {
    "iso:country":"GB",
    "wof:name":"LL14 2DB",
    "wof:placetype":"postalcode"
},
  "geometry": {"coordinates":[-3.05775204825782,53.00541472576322],"type":"Point"}
}