{
  "type": "Feature",
  "properties": {
    "date:inception_lower": "1980-01-01",
    "date:inception_upper": "1980-01-01",
    "iso:country": "GB",
    "wof:name": "B42 1PL",
    "wof:placetype": "postalcode"
  },
  "geometry": {"coordinates":[-1.917642,52.531032],"type":"Point"}
}
