{
  "type": "Feature",
  "properties": {
    "iso:country":"GB",
    "wof:name":"PO5 1NJ",
    "wof:placetype":"postalcode"
},
  "geometry": {"coordinates":[-1.0795335222637,50.78824259749939],"type":"Point"}
}