{
  "type": "Feature",
  "properties": {
    "iso:country": "GB",
    "wof:name": "PO5 1NJ",
    "wof:placetype": "postalcode"
  },
  "geometry": {"coordinates":[-1.079548,50.788207],"type":"Point"}
}
