{
  "type": "Feature",
  "properties": {
    "iso:country": "GB",
    "wof:name": "CA2 6AH",
    "wof:placetype": "postalcode"
  },
  "geometry": {"coordinates":[-2.949899,54.881795],"type":"Point"}
}
