{
  "type": "Feature",
  "properties": {
    "iso:country":"GB",
    "wof:name":"CA2 6AH",
    "wof:placetype":"postalcode"
},
  "geometry": {"coordinates":[-2.94989894332641,54.88179467233557],"type":"Point"}
}