{
  "type": "Feature",
  "properties": {
    "iso:country":"GB",
    "wof:name":"NG10 4PA",
    "wof:placetype":"postalcode"
},
  "geometry": {"coordinates":[-1.29802479309021,52.90171516597017],"type":"Point"}
}