{
  "type": "Feature",
  "properties": {
    "date:inception_lower": "1982-03-01",
    "date:inception_upper": "1982-03-01",
    "iso:country": "GB",
    "wof:name": "NG10 4PA",
    "wof:placetype": "postalcode"
  },
  "geometry": {"coordinates":[-1.298025,52.901715],"type":"Point"}
}
