{
  "type": "Feature",
  "properties": {
    "date:inception_lower": "1980-01-01",
    "date:inception_upper": "1980-01-01",
    "iso:country": "GB",
    "wof:name": "YO7 4AG",
    "wof:placetype": "postalcode"
  },
  "geometry": {"coordinates":[-1.34914,54.274258],"type":"Point"}
}
