{
  "type": "Feature",
  "properties": {
    "iso:country":"GB",
    "wof:name":"YO7 4AG",
    "wof:placetype":"postalcode"
},
  "geometry": {"coordinates":[-1.34879096244991,54.27436879955924],"type":"Point"}
}