{
  "type": "Feature",
  "properties": {
    "iso:country": "GB",
    "wof:name": "HU7 3JY",
    "wof:placetype": "postalcode"
  },
  "geometry": {"coordinates":[-0.352755,53.796053],"type":"Point"}
}
