{
  "type": "Feature",
  "properties": {
    "iso:country": "GB",
    "wof:name": "CF62 6LX",
    "wof:placetype": "postalcode"
  },
  "geometry": {"coordinates":[-3.293562,51.403278],"type":"Point"}
}
