{
  "type": "Feature",
  "properties": {
    "date:inception_lower":"1980-01-01",
    "date:inception_upper":"1980-01-31",
    "iso:country":"GB",
    "wof:name":"E5 8NW",
    "wof:placetype":"postalcode"
},
  "geometry": {"coordinates":[-0.057972,51.553978],"type":"Point"}
}