{
  "type": "Feature",
  "properties": {
    "iso:country":"GB",
    "wof:name":"E5 8NW",
    "wof:placetype":"postalcode"
},
  "geometry": {"coordinates":[-0.05797154542347,51.55397828677818],"type":"Point"}
}