{
  "type": "Feature",
  "properties": {
    "date:inception_lower": "1980-01-01",
    "date:inception_upper": "1980-01-01",
    "iso:country": "GB",
    "wof:name": "EN2 8PF",
    "wof:placetype": "postalcode"
  },
  "geometry": {"coordinates":[-0.099004,51.658216],"type":"Point"}
}
