{
  "type": "Feature",
  "properties": {
    "iso:country":"GB",
    "wof:name":"EN2 8PF",
    "wof:placetype":"postalcode"
},
  "geometry": {"coordinates":[-0.09900356294424,51.65821607552938],"type":"Point"}
}