{
  "type": "Feature",
  "properties": {
    "iso:country":"GB",
    "wof:name":"AB43 9TU",
    "wof:placetype":"postalcode"
},
  "geometry": {"coordinates":[-2.01937107910958,57.68155696903716],"type":"Point"}
}