{
  "type": "Feature",
  "properties": {
    "date:inception_lower": "1980-01-01",
    "date:inception_upper": "1980-01-01",
    "iso:country": "GB",
    "wof:name": "TN11 8AL",
    "wof:placetype": "postalcode"
  },
  "geometry": {"coordinates":[0.198841,51.153837],"type":"Point"}
}
