{
  "type": "Feature",
  "properties": {
    "iso:country":"GB",
    "wof:name":"TN11 8AL",
    "wof:placetype":"postalcode"
},
  "geometry": {"coordinates":[0.19884104036203,51.15383746905478],"type":"Point"}
}