{
  "type": "Feature",
  "properties": {
    "date:inception_lower": "1980-01-01",
    "date:inception_upper": "1980-01-01",
    "iso:country": "GB",
    "wof:name": "N15 6SJ",
    "wof:placetype": "postalcode"
  },
  "geometry": {"coordinates":[-0.084528,51.57766],"type":"Point"}
}
