{
  "type": "Feature",
  "properties": {
    "iso:country":"GB",
    "wof:name":"N15 6SJ",
    "wof:placetype":"postalcode"
},
  "geometry": {"coordinates":[-0.08452831707005,51.57766047719915],"type":"Point"}
}