{
  "type": "Feature",
  "properties": {
    "date:inception_lower": "1980-01-01",
    "date:inception_upper": "1980-01-01",
    "iso:country": "GB",
    "wof:name": "NN2 7HU",
    "wof:placetype": "postalcode"
  },
  "geometry": {"coordinates":[-0.877881,52.254743],"type":"Point"}
}
