{
  "type": "Feature",
  "properties": {
    "iso:country":"GB",
    "wof:name":"DL11 7BH",
    "wof:placetype":"postalcode"
},
  "geometry": {"coordinates":[-1.72621603060118,54.51162780231443],"type":"Point"}
}