{
  "type": "Feature",
  "properties": {
    "date:inception_lower": "2008-10-01",
    "date:inception_upper": "2008-10-01",
    "iso:country": "GB",
    "wof:name": "IV30 6GT",
    "wof:placetype": "postalcode"
  },
  "geometry": {"coordinates":[-3.299954,57.633511],"type":"Point"}
}
