{
  "type": "Feature",
  "properties": {
    "iso:country":"GB",
    "wof:name":"E11 1DD",
    "wof:placetype":"postalcode"
},
  "geometry": {"coordinates":[-0.00062165717136,51.56933653503835],"type":"Point"}
}