{
  "type": "Feature",
  "properties": {
    "iso:country":"GB",
    "wof:name":"G68 9GT",
    "wof:placetype":"postalcode"
},
  "geometry": {"coordinates":[-4.03667172097439,55.94239075911061],"type":"Point"}
}