{
  "type": "Feature",
  "properties": {
    "date:inception_lower": "2015-08-01",
    "date:inception_upper": "2015-08-01",
    "iso:country": "GB",
    "wof:name": "G68 9GT",
    "wof:placetype": "postalcode"
  },
  "geometry": {"coordinates":[-4.036832,55.942388],"type":"Point"}
}
