{
  "type": "Feature",
  "properties": {
    "iso:country":"GB",
    "wof:name":"BD9 6AA",
    "wof:placetype":"postalcode"
},
  "geometry": {"coordinates":[-1.8027937275185,53.80844769836065],"type":"Point"}
}