{
  "type": "Feature",
  "properties": {
    "date:inception_lower": "2001-12-01",
    "date:inception_upper": "2001-12-01",
    "iso:country": "GB",
    "wof:name": "RM16 6BB",
    "wof:placetype": "postalcode"
  },
  "geometry": {"coordinates":[0.300202,51.483984],"type":"Point"}
}
