{
  "type": "Feature",
  "properties": {
    "date:inception_lower": "2016-10-01",
    "date:inception_upper": "2016-10-01",
    "iso:country": "GB",
    "wof:name": "BS16 2FP",
    "wof:placetype": "postalcode"
  },
  "geometry": {"coordinates":[-2.530127,51.484891],"type":"Point"}
}
