{
  "type": "Feature",
  "properties": {
    "iso:country":"GB",
    "wof:name":"CV5 9QA",
    "wof:placetype":"postalcode"
},
  "geometry": {"coordinates":[-1.57334103113871,52.42495685213373],"type":"Point"}
}