{
  "type": "Feature",
  "properties": {
    "iso:country":"GB",
    "wof:name":"DN7 6QY",
    "wof:placetype":"postalcode"
},
  "geometry": {"coordinates":[-1.00789132333505,53.57907634554071],"type":"Point"}
}