{
  "type": "Feature",
  "properties": {
    "iso:country":"GB",
    "wof:name":"S9 4LN",
    "wof:placetype":"postalcode"
},
  "geometry": {"coordinates":[-1.41359525087638,53.38634943184857],"type":"Point"}
}