{
  "type": "Feature",
  "properties": {
    "date:inception_lower":"1993-08-01",
    "date:inception_upper":"1993-08-31",
    "iso:country":"GB",
    "wof:name":"WS12 4RL",
    "wof:placetype":"postalcode"
},
  "geometry": {"coordinates":[-1.995176,52.716906],"type":"Point"}
}