{
  "type": "Feature",
  "properties": {
    "iso:country":"GB",
    "wof:name":"CM3 4DX",
    "wof:placetype":"postalcode"
},
  "geometry": {"coordinates":[0.57069030148928,51.71447640758556],"type":"Point"}
}