{
  "type": "Feature",
  "properties": {
    "iso:country":"GB",
    "wof:name":"CW5 7JX",
    "wof:placetype":"postalcode"
},
  "geometry": {"coordinates":[-2.47378489399091,53.0414566330867],"type":"Point"}
}