{
  "type": "Feature",
  "properties": {
    "iso:country": "GB",
    "wof:name": "SP6 3FF",
    "wof:placetype": "postalcode"
  },
  "geometry": {"coordinates":[-1.870499,50.923811],"type":"Point"}
}
