{
  "type": "Feature",
  "properties": {
    "date:inception_lower": "1980-01-01",
    "date:inception_upper": "1980-01-01",
    "iso:country": "GB",
    "wof:name": "TN22 1DB",
    "wof:placetype": "postalcode"
  },
  "geometry": {"coordinates":[0.097101,50.977805],"type":"Point"}
}
