{
  "type": "Feature",
  "properties": {
    "iso:country": "GB",
    "wof:name": "NR14 6FU",
    "wof:placetype": "postalcode"
  },
  "geometry": {"coordinates":[1.473195,52.534961],"type":"Point"}
}
