{
  "type": "Feature",
  "properties": {
    "iso:country":"GB",
    "wof:name":"HD2 2TP",
    "wof:placetype":"postalcode"
},
  "geometry": {"coordinates":[-1.79249631168327,53.66083728031479],"type":"Point"}
}