{
  "type": "Feature",
  "properties": {
    "date:inception_lower": "2017-10-01",
    "date:inception_upper": "2017-10-01",
    "iso:country": "GB",
    "wof:name": "NN15 5ZB",
    "wof:placetype": "postalcode"
  },
  "geometry": {"coordinates":[-0.670276,52.358892],"type":"Point"}
}
