{
  "type": "Feature",
  "properties": {
    "iso:country": "GB",
    "wof:name": "NN15 5ZB",
    "wof:placetype": "postalcode"
  },
  "geometry": {"coordinates":[-0.670705,52.358303],"type":"Point"}
}
