{
  "type": "Feature",
  "properties": {
    "date:inception_lower":"2017-10-01",
    "date:inception_upper":"2017-10-31",
    "iso:country":"GB",
    "wof:name":"NN15 5ZB",
    "wof:placetype":"postalcode"
},
  "geometry": {"coordinates":[-0.670761,52.35789],"type":"Point"}
}