{
  "type": "Feature",
  "properties": {
    "date:inception_lower": "2020-08-01",
    "date:inception_upper": "2020-08-01",
    "iso:country": "GB",
    "wof:name": "FY8 3FW",
    "wof:placetype": "postalcode"
  },
  "geometry": {"coordinates":[-3.007052,53.765375],"type":"Point"}
}
