{
  "type": "Feature",
  "properties": {
    "iso:country": "GB",
    "wof:name": "N17 8EA",
    "wof:placetype": "postalcode"
  },
  "geometry": {"coordinates":[-0.071877,51.606924],"type":"Point"}
}
