{
  "type": "Feature",
  "properties": {
    "date:inception_lower":"1994-12-01",
    "date:inception_upper":"1994-12-31",
    "iso:country":"GB",
    "wof:name":"SE28 8JY",
    "wof:placetype":"postalcode"
},
  "geometry": {"coordinates":[0.118397,51.505018],"type":"Point"}
}