{
  "type": "Feature",
  "properties": {
    "iso:country": "GB",
    "wof:name": "SN14 8AB",
    "wof:placetype": "postalcode"
  },
  "geometry": {"coordinates":[-2.324071,51.452681],"type":"Point"}
}
