{
  "type": "Feature",
  "properties": {
    "iso:country":"GB",
    "wof:name":"E5 0DR",
    "wof:placetype":"postalcode"
},
  "geometry": {"coordinates":[-0.04006917480516,51.55265543190949],"type":"Point"}
}