{
  "type": "Feature",
  "properties": {
    "iso:country": "GB",
    "wof:name": "RH17 7AL",
    "wof:placetype": "postalcode"
  },
  "geometry": {"coordinates":[-0.023372,51.035542],"type":"Point"}
}
