{
  "type": "Feature",
  "properties": {
    "iso:country":"GB",
    "wof:name":"RH17 7AL",
    "wof:placetype":"postalcode"
},
  "geometry": {"coordinates":[-0.0233717151734,51.0355418263987],"type":"Point"}
}