{
  "type": "Feature",
  "properties": {
    "date:inception_lower": "1981-06-01",
    "date:inception_upper": "1981-06-01",
    "iso:country": "GB",
    "wof:name": "RH17 7AL",
    "wof:placetype": "postalcode"
  },
  "geometry": {"coordinates":[-0.023372,51.035542],"type":"Point"}
}
