{
  "type": "Feature",
  "properties": {
    "iso:country":"GB",
    "wof:name":"SN8 2EG",
    "wof:placetype":"postalcode"
},
  "geometry": {"coordinates":[-1.61966636567506,51.48503565738974],"type":"Point"}
}