{
  "type": "Feature",
  "properties": {
    "iso:country":"GB",
    "wof:name":"SO15 2DP",
    "wof:placetype":"postalcode"
},
  "geometry": {"coordinates":[-1.40149731700664,50.91150392264479],"type":"Point"}
}