{
  "type": "Feature",
  "properties": {
    "iso:country":"GB",
    "wof:name":"WR9 7EX",
    "wof:placetype":"postalcode"
},
  "geometry": {"coordinates":[-2.12430280186842,52.26125669746665],"type":"Point"}
}