{
  "type": "Feature",
  "properties": {
    "date:inception_lower": "2004-08-01",
    "date:inception_upper": "2004-08-01",
    "iso:country": "GB",
    "wof:name": "WR9 7EX",
    "wof:placetype": "postalcode"
  },
  "geometry": {"coordinates":[-2.124303,52.261257],"type":"Point"}
}
