{
  "type": "Feature",
  "properties": {
    "iso:country": "GB",
    "wof:name": "WR9 7EX",
    "wof:placetype": "postalcode"
  },
  "geometry": {"coordinates":[-2.124303,52.261257],"type":"Point"}
}
