{
  "type": "Feature",
  "properties": {
    "date:inception_lower": "2009-01-01",
    "date:inception_upper": "2009-01-01",
    "iso:country": "GB",
    "wof:name": "ML6 7UY",
    "wof:placetype": "postalcode"
  },
  "geometry": {"coordinates":[-3.904809,55.918551],"type":"Point"}
}
