{
  "type": "Feature",
  "properties": {
    "iso:country":"GB",
    "wof:name":"ML6 7UY",
    "wof:placetype":"postalcode"
},
  "geometry": {"coordinates":[-3.9048181521401,55.91855610183104],"type":"Point"}
}