{
  "type": "Feature",
  "properties": {
    "iso:country": "GB",
    "wof:name": "M3 7EB",
    "wof:placetype": "postalcode"
  },
  "geometry": {"coordinates":[-2.250322,53.48603],"type":"Point"}
}
