{
  "type": "Feature",
  "properties": {
    "iso:country":"GB",
    "wof:name":"OL1 2AL",
    "wof:placetype":"postalcode"
},
  "geometry": {"coordinates":[-2.11690763250469,53.5467994703253],"type":"Point"}
}