{
  "type": "Feature",
  "properties": {
    "iso:country":"GB",
    "wof:name":"LN11 8NA",
    "wof:placetype":"postalcode"
},
  "geometry": {"coordinates":[0.03261415300678,53.33044356862543],"type":"Point"}
}