{
  "type": "Feature",
  "properties": {
    "iso:country": "GB",
    "wof:name": "TN17 4NG",
    "wof:placetype": "postalcode"
  },
  "geometry": {"coordinates":[0.638951,51.041282],"type":"Point"}
}
