{
  "type": "Feature",
  "properties": {
    "iso:country":"GB",
    "wof:name":"SE1 2EW",
    "wof:placetype":"postalcode"
},
  "geometry": {"coordinates":[-0.07067186439144,51.50165324226678],"type":"Point"}
}