{
  "type": "Feature",
  "properties": {
    "iso:country": "GB",
    "wof:name": "WF8 3PD",
    "wof:placetype": "postalcode"
  },
  "geometry": {"coordinates":[-1.313939,53.684409],"type":"Point"}
}
