{
  "type": "Feature",
  "properties": {
    "iso:country":"GB",
    "wof:name":"WF8 3PD",
    "wof:placetype":"postalcode"
},
  "geometry": {"coordinates":[-1.31393866737182,53.68440892214111],"type":"Point"}
}