{
  "type": "Feature",
  "properties": {
    "date:inception_lower":"1986-04-01",
    "date:inception_upper":"1986-04-30",
    "iso:country":"GB",
    "wof:name":"W4 5NZ",
    "wof:placetype":"postalcode"
},
  "geometry": {"coordinates":[-0.270813,51.497581],"type":"Point"}
}