{
  "type": "Feature",
  "properties": {
    "iso:country":"GB",
    "wof:name":"LS13 3DP",
    "wof:placetype":"postalcode"
},
  "geometry": {"coordinates":[-1.64351362608279,53.81003081271046],"type":"Point"}
}