{
  "type": "Feature",
  "properties": {
    "iso:country":"GB",
    "wof:name":"TD9 8JJ",
    "wof:placetype":"postalcode"
},
  "geometry": {"coordinates":[-2.65557665559888,55.40356159653517],"type":"Point"}
}