{
  "type": "Feature",
  "properties": {
    "iso:country":"GB",
    "wof:name":"NG23 7BB",
    "wof:placetype":"postalcode"
},
  "geometry": {"coordinates":[-0.75085975569124,53.24237133344148],"type":"Point"}
}