{
  "type": "Feature",
  "properties": {
    "iso:country": "GB",
    "wof:name": "NG23 7BB",
    "wof:placetype": "postalcode"
  },
  "geometry": {"coordinates":[-0.75086,53.242371],"type":"Point"}
}
