{
  "type": "Feature",
  "properties": {
    "date:inception_lower":"1999-12-01",
    "date:inception_upper":"1999-12-31",
    "iso:country":"GB",
    "wof:name":"PO6 4UQ",
    "wof:placetype":"postalcode"
},
  "geometry": {"coordinates":[-1.103946,50.842551],"type":"Point"}
}