{
  "type": "Feature",
  "properties": {
    "iso:country":"GB",
    "wof:name":"B46 2LN",
    "wof:placetype":"postalcode"
},
  "geometry": {"coordinates":[-1.63337837125629,52.51971508659082],"type":"Point"}
}