{
  "type": "Feature",
  "properties": {
    "iso:country": "GB",
    "wof:name": "SW1W 9SH",
    "wof:placetype": "postalcode"
  },
  "geometry": {"coordinates":[-0.146519,51.493102],"type":"Point"}
}
