{
  "type": "Feature",
  "properties": {
    "iso:country": "GB",
    "wof:name": "L37 8DA",
    "wof:placetype": "postalcode"
  },
  "geometry": {"coordinates":[-3.049626,53.559651],"type":"Point"}
}
