{
  "type": "Feature",
  "properties": {
    "iso:country":"GB",
    "wof:name":"L37 8DA",
    "wof:placetype":"postalcode"
},
  "geometry": {"coordinates":[-3.04962581776687,53.55965074758806],"type":"Point"}
}