{
  "type": "Feature",
  "properties": {
    "date:inception_lower": "2007-01-01",
    "date:inception_upper": "2007-01-01",
    "iso:country": "GB",
    "wof:name": "DA9 9SZ",
    "wof:placetype": "postalcode"
  },
  "geometry": {"coordinates":[0.293146,51.454454],"type":"Point"}
}
