{
  "type": "Feature",
  "properties": {
    "iso:country":"GB",
    "wof:name":"DA9 9SZ",
    "wof:placetype":"postalcode"
},
  "geometry": {"coordinates":[0.293146314032,51.45445391480769],"type":"Point"}
}