{
  "type": "Feature",
  "properties": {
    "iso:country":"GB",
    "wof:name":"SG18 0BP",
    "wof:placetype":"postalcode"
},
  "geometry": {"coordinates":[-0.26663680201809,52.09169094128978],"type":"Point"}
}