{
  "type": "Feature",
  "properties": {
    "date:inception_lower":"1980-01-01",
    "date:inception_upper":"1980-01-31",
    "iso:country":"GB",
    "wof:name":"SG18 0BP",
    "wof:placetype":"postalcode"
},
  "geometry": {"coordinates":[-0.266637,52.091691],"type":"Point"}
}