{
  "type": "Feature",
  "properties": {
    "iso:country": "GB",
    "wof:name": "SG18 0BP",
    "wof:placetype": "postalcode"
  },
  "geometry": {"coordinates":[-0.266637,52.091691],"type":"Point"}
}
