{
  "type": "Feature",
  "properties": {
    "iso:country":"GB",
    "wof:name":"AB23 8YA",
    "wof:placetype":"postalcode"
},
  "geometry": {"coordinates":[-2.06990107334974,57.2669588168913],"type":"Point"}
}