{
  "type": "Feature",
  "properties": {
    "iso:country": "GB",
    "wof:name": "G53 7SP",
    "wof:placetype": "postalcode"
  },
  "geometry": {"coordinates":[-4.34754,55.81059],"type":"Point"}
}
