{
  "type": "Feature",
  "properties": {
    "iso:country":"GB",
    "wof:name":"G53 7SP",
    "wof:placetype":"postalcode"
},
  "geometry": {"coordinates":[-4.34741766358526,55.81068186321673],"type":"Point"}
}