{
  "type": "Feature",
  "properties": {
    "date:inception_lower": "2004-03-01",
    "date:inception_upper": "2004-03-01",
    "iso:country": "GB",
    "wof:name": "WR15 8BF",
    "wof:placetype": "postalcode"
  },
  "geometry": {"coordinates":[-2.596982,52.309457],"type":"Point"}
}
