{
  "type": "Feature",
  "properties": {
    "iso:country":"GB",
    "wof:name":"CO3 0SD",
    "wof:placetype":"postalcode"
},
  "geometry": {"coordinates":[0.8377333860564,51.89199397021017],"type":"Point"}
}