{
  "type": "Feature",
  "properties": {
    "date:inception_lower": "2019-11-01",
    "date:inception_upper": "2019-11-01",
    "iso:country": "GB",
    "wof:name": "LN4 3BU",
    "wof:placetype": "postalcode"
  },
  "geometry": {"coordinates":[-0.315551,53.093298],"type":"Point"}
}
