{
  "type": "Feature",
  "properties": {
    "iso:country":"GB",
    "wof:name":"LA20 6ES",
    "wof:placetype":"postalcode"
},
  "geometry": {"coordinates":[-3.21847960150547,54.27871190940763],"type":"Point"}
}