{
  "type": "Feature",
  "properties": {
    "iso:country":"GB",
    "wof:name":"PE11 2JA",
    "wof:placetype":"postalcode"
},
  "geometry": {"coordinates":[-0.13204172595124,52.79507846335926],"type":"Point"}
}