{
  "type": "Feature",
  "properties": {
    "iso:country": "GB",
    "wof:name": "B77 5HA",
    "wof:placetype": "postalcode"
  },
  "geometry": {"coordinates":[-1.66966,52.598546],"type":"Point"}
}
