{
  "type": "Feature",
  "properties": {
    "iso:country": "GB",
    "wof:name": "SY24 5EG",
    "wof:placetype": "postalcode"
  },
  "geometry": {"coordinates":[-3.982994,52.487792],"type":"Point"}
}
