{
  "type": "Feature",
  "properties": {
    "iso:country":"GB",
    "wof:name":"SY24 5EG",
    "wof:placetype":"postalcode"
},
  "geometry": {"coordinates":[-3.98299378687806,52.48779211837454],"type":"Point"}
}