{
  "type": "Feature",
  "properties": {
    "iso:country":"GB",
    "wof:name":"BA11 4EW",
    "wof:placetype":"postalcode"
},
  "geometry": {"coordinates":[-2.33278682588918,51.22406799037132],"type":"Point"}
}