{
  "type": "Feature",
  "properties": {
    "date:inception_lower": "2008-12-01",
    "date:inception_upper": "2008-12-01",
    "iso:country": "GB",
    "wof:name": "YO17 9FX",
    "wof:placetype": "postalcode"
  },
  "geometry": {"coordinates":[-0.802437,54.063583],"type":"Point"}
}
