{
  "type": "Feature",
  "properties": {
    "iso:country": "GB",
    "wof:name": "YO17 9FX",
    "wof:placetype": "postalcode"
  },
  "geometry": {"coordinates":[-0.802538,54.063772],"type":"Point"}
}
