{
  "type": "Feature",
  "properties": {
    "iso:country":"GB",
    "wof:name":"YO17 9FX",
    "wof:placetype":"postalcode"
},
  "geometry": {"coordinates":[-0.80242630738429,54.06356491734695],"type":"Point"}
}