{
  "type": "Feature",
  "properties": {
    "iso:country":"GB",
    "wof:name":"SW15 2NZ",
    "wof:placetype":"postalcode"
},
  "geometry": {"coordinates":[-0.20642085234298,51.46181300870814],"type":"Point"}
}