{
  "type": "Feature",
  "properties": {
    "iso:country": "GB",
    "wof:name": "DE74 2BU",
    "wof:placetype": "postalcode"
  },
  "geometry": {"coordinates":[-1.314111,52.825938],"type":"Point"}
}
