{
  "type": "Feature",
  "properties": {
    "iso:country":"GB",
    "wof:name":"TN22 3PX",
    "wof:placetype":"postalcode"
},
  "geometry": {"coordinates":[0.02714990019858,50.98814442246099],"type":"Point"}
}