{
  "type": "Feature",
  "properties": {
    "date:inception_lower": "1999-06-01",
    "date:inception_upper": "1999-06-01",
    "iso:country": "GB",
    "wof:name": "B98 7AU",
    "wof:placetype": "postalcode"
  },
  "geometry": {"coordinates":[-1.916055,52.295195],"type":"Point"}
}
