{
  "type": "Feature",
  "properties": {
    "iso:country":"GB",
    "wof:name":"SE10 8PH",
    "wof:placetype":"postalcode"
},
  "geometry": {"coordinates":[-0.01140401830866,51.47893685954215],"type":"Point"}
}