{
  "type": "Feature",
  "properties": {
    "date:inception_lower":"1980-01-01",
    "date:inception_upper":"1980-01-31",
    "iso:country":"GB",
    "wof:name":"SE10 8PH",
    "wof:placetype":"postalcode"
},
  "geometry": {"coordinates":[-0.011404,51.478937],"type":"Point"}
}