{
  "type": "Feature",
  "properties": {
    "iso:country": "GB",
    "wof:name": "SY3 8ZP",
    "wof:placetype": "postalcode"
  },
  "geometry": {"coordinates":[-2.749114,52.713159],"type":"Point"}
}
