{
  "type": "Feature",
  "properties": {
    "iso:country":"GB",
    "wof:name":"LU6 3HY",
    "wof:placetype":"postalcode"
},
  "geometry": {"coordinates":[-0.51281422019589,51.88085954164593],"type":"Point"}
}