{
  "type": "Feature",
  "properties": {
    "iso:country":"GB",
    "wof:name":"G33 1RX",
    "wof:placetype":"postalcode"
},
  "geometry": {"coordinates":[-4.19506013745516,55.89846307125918],"type":"Point"}
}