{
  "type": "Feature",
  "properties": {
    "date:inception_lower":"1999-12-01",
    "date:inception_upper":"1999-12-31",
    "iso:country":"GB",
    "wof:name":"G33 1RX",
    "wof:placetype":"postalcode"
},
  "geometry": {"coordinates":[-4.19506,55.898463],"type":"Point"}
}