{
  "type": "Feature",
  "properties": {
    "date:inception_lower": "1999-12-01",
    "date:inception_upper": "1999-12-01",
    "iso:country": "GB",
    "wof:name": "G33 1RX",
    "wof:placetype": "postalcode"
  },
  "geometry": {"coordinates":[-4.1949,55.898416],"type":"Point"}
}
