{
  "type": "Feature",
  "properties": {
    "iso:country":"GB",
    "wof:name":"W1U 1EZ",
    "wof:placetype":"postalcode"
},
  "geometry": {"coordinates":[-0.15070745851447,51.51561304089469],"type":"Point"}
}