{
  "type": "Feature",
  "properties": {
    "iso:country":"GB",
    "wof:name":"M24 1PS",
    "wof:placetype":"postalcode"
},
  "geometry": {"coordinates":[-2.19170899963004,53.5349190614638],"type":"Point"}
}