{
  "type": "Feature",
  "properties": {
    "date:inception_lower": "1980-01-01",
    "date:inception_upper": "1980-01-01",
    "iso:country": "GB",
    "wof:name": "IP29 5RF",
    "wof:placetype": "postalcode"
  },
  "geometry": {"coordinates":[0.626101,52.203316],"type":"Point"}
}
