{
  "type": "Feature",
  "properties": {
    "iso:country": "GB",
    "wof:name": "DD7 7AH",
    "wof:placetype": "postalcode"
  },
  "geometry": {"coordinates":[-2.71506,56.50125],"type":"Point"}
}
