{
  "type": "Feature",
  "properties": {
    "iso:country":"GB",
    "wof:name":"NG2 3DE",
    "wof:placetype":"postalcode"
},
  "geometry": {"coordinates":[-1.14471445357915,52.94558649541896],"type":"Point"}
}