{
  "type": "Feature",
  "properties": {
    "iso:country": "GB",
    "wof:name": "WA15 9NP",
    "wof:placetype": "postalcode"
  },
  "geometry": {"coordinates":[-2.341561,53.372009],"type":"Point"}
}
