{
  "type": "Feature",
  "properties": {
    "iso:country": "GB",
    "wof:name": "RG4 7SY",
    "wof:placetype": "postalcode"
  },
  "geometry": {"coordinates":[-0.974006,51.468496],"type":"Point"}
}
