{
  "type": "Feature",
  "properties": {
    "iso:country":"GB",
    "wof:name":"RG4 7SY",
    "wof:placetype":"postalcode"
},
  "geometry": {"coordinates":[-0.97400606987328,51.46849641908354],"type":"Point"}
}