{
  "type": "Feature",
  "properties": {
    "iso:country":"GB",
    "wof:name":"NE31 1LH",
    "wof:placetype":"postalcode"
},
  "geometry": {"coordinates":[-1.51898484577991,54.97213121302761],"type":"Point"}
}