{
  "type": "Feature",
  "properties": {
    "iso:country": "GB",
    "wof:name": "GL2 7JJ",
    "wof:placetype": "postalcode"
  },
  "geometry": {"coordinates":[-2.394532,51.790628],"type":"Point"}
}
