{
  "type": "Feature",
  "properties": {
    "iso:country":"GB",
    "wof:name":"GL2 7JJ",
    "wof:placetype":"postalcode"
},
  "geometry": {"coordinates":[-2.39453178485349,51.79062826757993],"type":"Point"}
}