{
  "type": "Feature",
  "properties": {
    "iso:country": "GB",
    "wof:name": "LE4 7QZ",
    "wof:placetype": "postalcode"
  },
  "geometry": {"coordinates":[-1.122053,52.662119],"type":"Point"}
}
