{
  "type": "Feature",
  "properties": {
    "iso:country": "GB",
    "wof:name": "LE4 7QZ",
    "wof:placetype": "postalcode"
  },
  "geometry": {"coordinates":[-1.121965,52.662092],"type":"Point"}
}
