{
  "type": "Feature",
  "properties": {
    "date:inception_lower":"2005-08-01",
    "date:inception_upper":"2005-08-31",
    "iso:country":"GB",
    "wof:name":"LE4 7QZ",
    "wof:placetype":"postalcode"
},
  "geometry": {"coordinates":[-1.122053,52.662119],"type":"Point"}
}