{
  "type": "Feature",
  "properties": {
    "iso:country": "GB",
    "wof:name": "CM23 2UY",
    "wof:placetype": "postalcode"
  },
  "geometry": {"coordinates":[0.1357,51.877231],"type":"Point"}
}
