{
  "type": "Feature",
  "properties": {
    "iso:country": "GB",
    "wof:name": "NR12 9JE",
    "wof:placetype": "postalcode"
  },
  "geometry": {"coordinates":[1.48309,52.797426],"type":"Point"}
}
