{
  "type": "Feature",
  "properties": {
    "iso:country":"GB",
    "wof:name":"NR12 9JE",
    "wof:placetype":"postalcode"
},
  "geometry": {"coordinates":[1.48285450663325,52.79732392463218],"type":"Point"}
}