{
  "type": "Feature",
  "properties": {
    "iso:country":"GB",
    "wof:name":"LS12 6GZ",
    "wof:placetype":"postalcode"
},
  "geometry": {"coordinates":[-1.60440529173139,53.77976246041786],"type":"Point"}
}