{
  "type": "Feature",
  "properties": {
    "date:inception_lower": "2014-12-01",
    "date:inception_upper": "2014-12-01",
    "iso:country": "GB",
    "wof:name": "LS12 6GZ",
    "wof:placetype": "postalcode"
  },
  "geometry": {"coordinates":[-1.604229,53.77949],"type":"Point"}
}
