{
  "type": "Feature",
  "properties": {
    "iso:country": "GB",
    "wof:name": "L35 4NY",
    "wof:placetype": "postalcode"
  },
  "geometry": {"coordinates":[-2.764089,53.418303],"type":"Point"}
}
