{
  "type": "Feature",
  "properties": {
    "iso:country":"GB",
    "wof:name":"L35 4NY",
    "wof:placetype":"postalcode"
},
  "geometry": {"coordinates":[-2.7640892795731,53.41830338970875],"type":"Point"}
}