{
  "type": "Feature",
  "properties": {
    "iso:country": "GB",
    "wof:name": "CF83 8TG",
    "wof:placetype": "postalcode"
  },
  "geometry": {"coordinates":[-3.165173,51.593311],"type":"Point"}
}
