{
  "type": "Feature",
  "properties": {
    "iso:country":"GB",
    "wof:name":"GL9 1HS",
    "wof:placetype":"postalcode"
},
  "geometry": {"coordinates":[-2.33383434117113,51.51059458812392],"type":"Point"}
}