{
  "type": "Feature",
  "properties": {
    "iso:country":"GB",
    "wof:name":"AB21 7PW",
    "wof:placetype":"postalcode"
},
  "geometry": {"coordinates":[-2.17287619420551,57.25578330575649],"type":"Point"}
}