{
  "type": "Feature",
  "properties": {
    "iso:country": "GB",
    "wof:name": "AB21 7PW",
    "wof:placetype": "postalcode"
  },
  "geometry": {"coordinates":[-2.172997,57.255804],"type":"Point"}
}
