{
  "type": "Feature",
  "properties": {
    "iso:country":"GB",
    "wof:name":"G77 6QL",
    "wof:placetype":"postalcode"
},
  "geometry": {"coordinates":[-4.34176251663544,55.78163350881007],"type":"Point"}
}