{
  "type": "Feature",
  "properties": {
    "iso:country": "GB",
    "wof:name": "ME3 9QU",
    "wof:placetype": "postalcode"
  },
  "geometry": {"coordinates":[0.631949,51.454323],"type":"Point"}
}
