{
  "type": "Feature",
  "properties": {
    "iso:country":"GB",
    "wof:name":"ME3 9QU",
    "wof:placetype":"postalcode"
},
  "geometry": {"coordinates":[0.63194870846512,51.45432283175381],"type":"Point"}
}