{
  "type": "Feature",
  "properties": {
    "iso:country":"GB",
    "wof:name":"CA28 9LH",
    "wof:placetype":"postalcode"
},
  "geometry": {"coordinates":[-3.59269508771007,54.53265043259999],"type":"Point"}
}