{
  "type": "Feature",
  "properties": {
    "iso:country":"GB",
    "wof:name":"CB10 2LF",
    "wof:placetype":"postalcode"
},
  "geometry": {"coordinates":[0.28338634063833,52.0195065241131],"type":"Point"}
}