{
  "type": "Feature",
  "properties": {
    "date:inception_lower": "1980-01-01",
    "date:inception_upper": "1980-01-01",
    "iso:country": "GB",
    "wof:name": "CB10 2LF",
    "wof:placetype": "postalcode"
  },
  "geometry": {"coordinates":[0.283386,52.019507],"type":"Point"}
}
