{
  "type": "Feature",
  "properties": {
    "iso:country": "GB",
    "wof:name": "NE47 7JA",
    "wof:placetype": "postalcode"
  },
  "geometry": {"coordinates":[-2.343228,54.975041],"type":"Point"}
}
