{
  "type": "Feature",
  "properties": {
    "date:inception_lower": "2019-07-01",
    "date:inception_upper": "2019-07-01",
    "iso:country": "GB",
    "wof:name": "SS3 0FR",
    "wof:placetype": "postalcode"
  },
  "geometry": {"coordinates":[0.791621,51.552092],"type":"Point"}
}
