{
  "type": "Feature",
  "properties": {
    "date:inception_lower": "1996-06-01",
    "date:inception_upper": "1996-06-01",
    "iso:country": "GB",
    "wof:name": "B44 0HQ",
    "wof:placetype": "postalcode"
  },
  "geometry": {"coordinates":[-1.873661,52.538788],"type":"Point"}
}
