{
  "type": "Feature",
  "properties": {
    "date:inception_lower": "1980-01-01",
    "date:inception_upper": "1980-01-01",
    "iso:country": "GB",
    "wof:name": "B69 2HT",
    "wof:placetype": "postalcode"
  },
  "geometry": {"coordinates":[-2.046992,52.513719],"type":"Point"}
}
