{
  "type": "Feature",
  "properties": {
    "iso:country": "GB",
    "wof:name": "B69 2HT",
    "wof:placetype": "postalcode"
  },
  "geometry": {"coordinates":[-2.046992,52.513719],"type":"Point"}
}
