{
  "type": "Feature",
  "properties": {
    "iso:country":"GB",
    "wof:name":"B69 2HT",
    "wof:placetype":"postalcode"
},
  "geometry": {"coordinates":[-2.04699167270525,52.51371900139632],"type":"Point"}
}