{
  "type": "Feature",
  "properties": {
    "iso:country":"GB",
    "wof:name":"DD11 2PN",
    "wof:placetype":"postalcode"
},
  "geometry": {"coordinates":[-2.6826568342457,56.54036994263779],"type":"Point"}
}