{
  "type": "Feature",
  "properties": {
    "date:inception_lower": "1986-07-01",
    "date:inception_upper": "1986-07-01",
    "iso:country": "GB",
    "wof:name": "BS3 4NJ",
    "wof:placetype": "postalcode"
  },
  "geometry": {"coordinates":[-2.597765,51.440463],"type":"Point"}
}
