{
  "type": "Feature",
  "properties": {
    "date:inception_lower":"1980-01-01",
    "date:inception_upper":"1980-01-31",
    "iso:country":"GB",
    "wof:name":"CF36 5DB",
    "wof:placetype":"postalcode"
},
  "geometry": {"coordinates":[-3.687828,51.477682],"type":"Point"}
}