{
  "type": "Feature",
  "properties": {
    "iso:country":"GB",
    "wof:name":"CF36 5DB",
    "wof:placetype":"postalcode"
},
  "geometry": {"coordinates":[-3.68782784964476,51.4776822916867],"type":"Point"}
}