{
  "type": "Feature",
  "properties": {
    "date:inception_lower": "1980-01-01",
    "date:inception_upper": "1980-01-01",
    "iso:country": "GB",
    "wof:name": "B27 7TB",
    "wof:placetype": "postalcode"
  },
  "geometry": {"coordinates":[-1.836118,52.441048],"type":"Point"}
}
