{
  "type": "Feature",
  "properties": {
    "iso:country":"GB",
    "wof:name":"B27 7TB",
    "wof:placetype":"postalcode"
},
  "geometry": {"coordinates":[-1.83611832744817,52.44104829112342],"type":"Point"}
}