{
  "type": "Feature",
  "properties": {
    "iso:country":"GB",
    "wof:name":"CR8 3LH",
    "wof:placetype":"postalcode"
},
  "geometry": {"coordinates":[-0.13263590107529,51.33843259801778],"type":"Point"}
}