{
  "type": "Feature",
  "properties": {
    "iso:country": "GB",
    "wof:name": "CR8 3LH",
    "wof:placetype": "postalcode"
  },
  "geometry": {"coordinates":[-0.132636,51.338433],"type":"Point"}
}
