{
  "type": "Feature",
  "properties": {
    "iso:country":"GB",
    "wof:name":"WN3 6DD",
    "wof:placetype":"postalcode"
},
  "geometry": {"coordinates":[-2.67640104425763,53.52457464225343],"type":"Point"}
}