{
  "type": "Feature",
  "properties": {
    "iso:country":"GB",
    "wof:name":"IG1 1SS",
    "wof:placetype":"postalcode"
},
  "geometry": {"coordinates":[0.08902103588602,51.55743311617774],"type":"Point"}
}