{
  "type": "Feature",
  "properties": {
    "date:inception_lower":"1980-01-01",
    "date:inception_upper":"1980-01-31",
    "iso:country":"GB",
    "wof:name":"IG1 1SS",
    "wof:placetype":"postalcode"
},
  "geometry": {"coordinates":[0.089021,51.557433],"type":"Point"}
}