{
  "type": "Feature",
  "properties": {
    "date:inception_lower": "2019-10-01",
    "date:inception_upper": "2019-10-01",
    "iso:country": "GB",
    "wof:name": "S62 6GB",
    "wof:placetype": "postalcode"
  },
  "geometry": {"coordinates":[-1.342541,53.460505],"type":"Point"}
}
