{
  "type": "Feature",
  "properties": {
    "iso:country": "GB",
    "wof:name": "S62 6GB",
    "wof:placetype": "postalcode"
  },
  "geometry": {"coordinates":[-1.342541,53.460505],"type":"Point"}
}
