{
  "type": "Feature",
  "properties": {
    "iso:country":"GB",
    "wof:name":"SR2 0PB",
    "wof:placetype":"postalcode"
},
  "geometry": {"coordinates":[-1.36363094584969,54.86905316797316],"type":"Point"}
}