{
  "type": "Feature",
  "properties": {
    "iso:country":"GB",
    "wof:name":"W5 2AZ",
    "wof:placetype":"postalcode"
},
  "geometry": {"coordinates":[-0.30740884106964,51.5138604351213],"type":"Point"}
}