{
  "type": "Feature",
  "properties": {
    "date:inception_lower":"2012-09-01",
    "date:inception_upper":"2012-09-30",
    "iso:country":"GB",
    "wof:name":"W5 2AZ",
    "wof:placetype":"postalcode"
},
  "geometry": {"coordinates":[-0.30803,51.51361],"type":"Point"}
}