{
  "type": "Feature",
  "properties": {
    "iso:country":"GB",
    "wof:name":"EX14 4RQ",
    "wof:placetype":"postalcode"
},
  "geometry": {"coordinates":[-3.21738522131207,50.86004105762285],"type":"Point"}
}