{
  "type": "Feature",
  "properties": {
    "date:inception_lower": "1999-12-01",
    "date:inception_upper": "1999-12-01",
    "iso:country": "GB",
    "wof:name": "EX14 4RQ",
    "wof:placetype": "postalcode"
  },
  "geometry": {"coordinates":[-3.217385,50.860041],"type":"Point"}
}
