{
  "type": "Feature",
  "properties": {
    "date:inception_lower":"1996-12-01",
    "date:inception_upper":"1996-12-31",
    "iso:country":"GB",
    "wof:name":"WV14 0UD",
    "wof:placetype":"postalcode"
},
  "geometry": {"coordinates":[-2.088553,52.561458],"type":"Point"}
}