{
  "type": "Feature",
  "properties": {
    "iso:country":"GB",
    "wof:name":"WV14 0UD",
    "wof:placetype":"postalcode"
},
  "geometry": {"coordinates":[-2.08855328222466,52.56145830250575],"type":"Point"}
}