{
  "type": "Feature",
  "properties": {
    "iso:country":"GB",
    "wof:name":"CV6 2HS",
    "wof:placetype":"postalcode"
},
  "geometry": {"coordinates":[-1.5212722318823,52.44353797544635],"type":"Point"}
}