{
  "type": "Feature",
  "properties": {
    "iso:country": "GB",
    "wof:name": "DE23 3EX",
    "wof:placetype": "postalcode"
  },
  "geometry": {"coordinates":[-1.512239,52.89929],"type":"Point"}
}
