{
  "type": "Feature",
  "properties": {
    "iso:country":"GB",
    "wof:name":"DA7 6PX",
    "wof:placetype":"postalcode"
},
  "geometry": {"coordinates":[0.16133746487009,51.46845149536382],"type":"Point"}
}