{
  "type": "Feature",
  "properties": {
    "iso:country":"GB",
    "wof:name":"CV1 2HZ",
    "wof:placetype":"postalcode"
},
  "geometry": {"coordinates":[-1.49249038509433,52.40681921268098],"type":"Point"}
}