{
  "type": "Feature",
  "properties": {
    "date:inception_lower": "2010-03-01",
    "date:inception_upper": "2010-03-01",
    "iso:country": "GB",
    "wof:name": "WA88 1AQ",
    "wof:placetype": "postalcode"
  },
  "geometry": {"coordinates":[-2.768674,53.367973],"type":"Point"}
}
