{
  "type": "Feature",
  "properties": {
    "date:inception_lower": "1980-01-01",
    "date:inception_upper": "1980-01-01",
    "iso:country": "GB",
    "wof:name": "SG14 3JE",
    "wof:placetype": "postalcode"
  },
  "geometry": {"coordinates":[-0.076042,51.805226],"type":"Point"}
}
