{
  "type": "Feature",
  "properties": {
    "iso:country":"GB",
    "wof:name":"SG14 3JE",
    "wof:placetype":"postalcode"
},
  "geometry": {"coordinates":[-0.07604253670807,51.80522563388564],"type":"Point"}
}