{
  "type": "Feature",
  "properties": {
    "iso:country": "GB",
    "wof:name": "CM3 7AQ",
    "wof:placetype": "postalcode"
  },
  "geometry": {"coordinates":[0.602564,51.641234],"type":"Point"}
}
