{
  "type": "Feature",
  "properties": {
    "iso:country":"GB",
    "wof:name":"CM3 7AQ",
    "wof:placetype":"postalcode"
},
  "geometry": {"coordinates":[0.60256432038336,51.64123420505724],"type":"Point"}
}