{
  "type": "Feature",
  "properties": {
    "date:inception_lower": "1980-01-01",
    "date:inception_upper": "1980-01-01",
    "iso:country": "GB",
    "wof:name": "KT13 8NE",
    "wof:placetype": "postalcode"
  },
  "geometry": {"coordinates":[-0.45397,51.38028],"type":"Point"}
}
