{
  "type": "Feature",
  "properties": {
    "iso:country":"GB",
    "wof:name":"KT13 8NE",
    "wof:placetype":"postalcode"
},
  "geometry": {"coordinates":[-0.45396965659684,51.38028019484602],"type":"Point"}
}