{
  "type": "Feature",
  "properties": {
    "iso:country":"GB",
    "wof:name":"G71 5AW",
    "wof:placetype":"postalcode"
},
  "geometry": {"coordinates":[-4.0555974769684,55.82865154890161],"type":"Point"}
}