{
  "type": "Feature",
  "properties": {
    "iso:country": "GB",
    "wof:name": "NP11 4SY",
    "wof:placetype": "postalcode"
  },
  "geometry": {"coordinates":[-3.135996,51.651928],"type":"Point"}
}
