{
  "type": "Feature",
  "properties": {
    "iso:country":"GB",
    "wof:name":"SY11 2NF",
    "wof:placetype":"postalcode"
},
  "geometry": {"coordinates":[-3.05439618150241,52.85964987111429],"type":"Point"}
}