{
  "type": "Feature",
  "properties": {
    "iso:country":"GB",
    "wof:name":"NN3 9EG",
    "wof:placetype":"postalcode"
},
  "geometry": {"coordinates":[-0.81593697286372,52.26037749567843],"type":"Point"}
}