{
  "type": "Feature",
  "properties": {
    "iso:country":"GB",
    "wof:name":"TW2 6PS",
    "wof:placetype":"postalcode"
},
  "geometry": {"coordinates":[-0.35756367781221,51.44486496482745],"type":"Point"}
}