{
  "type": "Feature",
  "properties": {
    "date:inception_lower": "2018-11-01",
    "date:inception_upper": "2018-11-01",
    "iso:country": "GB",
    "wof:name": "WD18 9AF",
    "wof:placetype": "postalcode"
  },
  "geometry": {"coordinates":[-0.436389,51.639135],"type":"Point"}
}
