{
  "type": "Feature",
  "properties": {
    "iso:country":"GB",
    "wof:name":"BS7 0PX",
    "wof:placetype":"postalcode"
},
  "geometry": {"coordinates":[-2.57522655640629,51.49936338671745],"type":"Point"}
}