{
  "type": "Feature",
  "properties": {
    "iso:country":"GB",
    "wof:name":"HX7 8JA",
    "wof:placetype":"postalcode"
},
  "geometry": {"coordinates":[-2.00705865257344,53.74366195427188],"type":"Point"}
}