{
  "type": "Feature",
  "properties": {
    "iso:country":"GB",
    "wof:name":"ML6 8JX",
    "wof:placetype":"postalcode"
},
  "geometry": {"coordinates":[-3.9590015797569,55.86328195503017],"type":"Point"}
}