{
  "type": "Feature",
  "properties": {
    "iso:country": "GB",
    "wof:name": "CR5 3SY",
    "wof:placetype": "postalcode"
  },
  "geometry": {"coordinates":[-0.190235,51.278294],"type":"Point"}
}
