{
  "type": "Feature",
  "properties": {
    "iso:country":"GB",
    "wof:name":"CR5 3SY",
    "wof:placetype":"postalcode"
},
  "geometry": {"coordinates":[-0.19023504076246,51.278294077461],"type":"Point"}
}