{
  "type": "Feature",
  "properties": {
    "date:inception_lower":"1990-07-01",
    "date:inception_upper":"1990-07-31",
    "iso:country":"GB",
    "wof:name":"CR5 3SY",
    "wof:placetype":"postalcode"
},
  "geometry": {"coordinates":[-0.190235,51.278294],"type":"Point"}
}