{
  "type": "Feature",
  "properties": {
    "iso:country":"GB",
    "wof:name":"YO62 6NE",
    "wof:placetype":"postalcode"
},
  "geometry": {"coordinates":[-0.90526128426273,54.26534365326162],"type":"Point"}
}