{
  "type": "Feature",
  "properties": {
    "iso:country": "GB",
    "wof:name": "YO62 6NE",
    "wof:placetype": "postalcode"
  },
  "geometry": {"coordinates":[-0.905576,54.266117],"type":"Point"}
}
