{
  "type": "Feature",
  "properties": {
    "iso:country":"GB",
    "wof:name":"SM5 2GN",
    "wof:placetype":"postalcode"
},
  "geometry": {"coordinates":[-0.16805655591433,51.36647365655836],"type":"Point"}
}