{
  "type": "Feature",
  "properties": {
    "date:inception_lower": "1980-01-01",
    "date:inception_upper": "1980-01-01",
    "iso:country": "GB",
    "wof:name": "CV22 7ER",
    "wof:placetype": "postalcode"
  },
  "geometry": {"coordinates":[-1.288963,52.366969],"type":"Point"}
}
