{
  "type": "Feature",
  "properties": {
    "iso:country":"GB",
    "wof:name":"CV22 7ER",
    "wof:placetype":"postalcode"
},
  "geometry": {"coordinates":[-1.28896333208631,52.36696880143916],"type":"Point"}
}