{
  "type": "Feature",
  "properties": {
    "iso:country":"GB",
    "wof:name":"DT3 5SF",
    "wof:placetype":"postalcode"
},
  "geometry": {"coordinates":[-2.46404274129035,50.65380893604023],"type":"Point"}
}