{
  "type": "Feature",
  "properties": {
    "date:inception_lower":"1985-10-01",
    "date:inception_upper":"1985-10-31",
    "iso:country":"GB",
    "wof:name":"DT3 5SF",
    "wof:placetype":"postalcode"
},
  "geometry": {"coordinates":[-2.464043,50.653809],"type":"Point"}
}