{
  "type": "Feature",
  "properties": {
    "iso:country":"GB",
    "wof:name":"BL9 5HH",
    "wof:placetype":"postalcode"
},
  "geometry": {"coordinates":[-2.29830329864883,53.61004962532766],"type":"Point"}
}