{
  "type": "Feature",
  "properties": {
    "iso:country": "GB",
    "wof:name": "BL9 5HH",
    "wof:placetype": "postalcode"
  },
  "geometry": {"coordinates":[-2.298303,53.61005],"type":"Point"}
}
