{
  "type": "Feature",
  "properties": {
    "iso:country":"GB",
    "wof:name":"ME5 9PZ",
    "wof:placetype":"postalcode"
},
  "geometry": {"coordinates":[0.53582866880433,51.33027132858944],"type":"Point"}
}