{
  "type": "Feature",
  "properties": {
    "iso:country":"GB",
    "wof:name":"HP23 5DD",
    "wof:placetype":"postalcode"
},
  "geometry": {"coordinates":[-0.66308665027022,51.79842122423113],"type":"Point"}
}