{
  "type": "Feature",
  "properties": {
    "iso:country":"GB",
    "wof:name":"NN4 6BJ",
    "wof:placetype":"postalcode"
},
  "geometry": {"coordinates":[-0.87284743072968,52.20478707441659],"type":"Point"}
}