{
  "type": "Feature",
  "properties": {
    "iso:country": "GB",
    "wof:name": "NN4 6BJ",
    "wof:placetype": "postalcode"
  },
  "geometry": {"coordinates":[-0.872847,52.204787],"type":"Point"}
}
