{
  "type": "Feature",
  "properties": {
    "iso:country": "GB",
    "wof:name": "DN9 2BY",
    "wof:placetype": "postalcode"
  },
  "geometry": {"coordinates":[-0.926681,53.522843],"type":"Point"}
}
