{
  "type": "Feature",
  "properties": {
    "iso:country":"GB",
    "wof:name":"DN9 2BY",
    "wof:placetype":"postalcode"
},
  "geometry": {"coordinates":[-0.92668121195489,53.5228427326953],"type":"Point"}
}