{
  "type": "Feature",
  "properties": {
    "date:inception_lower": "1996-12-01",
    "date:inception_upper": "1996-12-01",
    "iso:country": "GB",
    "wof:name": "M90 1QD",
    "wof:placetype": "postalcode"
  },
  "geometry": {"coordinates":[-2.270841,53.361881],"type":"Point"}
}
