{
  "type": "Feature",
  "properties": {
    "iso:country": "GB",
    "wof:name": "M90 1QD",
    "wof:placetype": "postalcode"
  },
  "geometry": {"coordinates":[-2.270841,53.361881],"type":"Point"}
}
