{
  "type": "Feature",
  "properties": {
    "iso:country":"GB",
    "wof:name":"M90 1QD",
    "wof:placetype":"postalcode"
},
  "geometry": {"coordinates":[-2.27084059220109,53.36188079550021],"type":"Point"}
}