{
  "type": "Feature",
  "properties": {
    "date:inception_lower":"1980-01-01",
    "date:inception_upper":"1980-01-31",
    "iso:country":"GB",
    "wof:name":"DE14 3QA",
    "wof:placetype":"postalcode"
},
  "geometry": {"coordinates":[-1.647394,52.797316],"type":"Point"}
}