{
  "type": "Feature",
  "properties": {
    "iso:country":"GB",
    "wof:name":"CA14 1LE",
    "wof:placetype":"postalcode"
},
  "geometry": {"coordinates":[-3.54990746093512,54.66526465801672],"type":"Point"}
}