{
  "type": "Feature",
  "properties": {
    "iso:country":"GB",
    "wof:name":"TS19 9HH",
    "wof:placetype":"postalcode"
},
  "geometry": {"coordinates":[-1.33613153071294,54.58949875393533],"type":"Point"}
}