{
  "type": "Feature",
  "properties": {
    "date:inception_lower":"1980-01-01",
    "date:inception_upper":"1980-01-31",
    "iso:country":"GB",
    "wof:name":"CO3 4NL",
    "wof:placetype":"postalcode"
},
  "geometry": {"coordinates":[0.866875,51.880315],"type":"Point"}
}