{
  "type": "Feature",
  "properties": {
    "iso:country": "GB",
    "wof:name": "CO3 4NL",
    "wof:placetype": "postalcode"
  },
  "geometry": {"coordinates":[0.866875,51.880315],"type":"Point"}
}
