{
  "type": "Feature",
  "properties": {
    "date:inception_lower": "1980-01-01",
    "date:inception_upper": "1980-01-01",
    "iso:country": "GB",
    "wof:name": "PO6 2SG",
    "wof:placetype": "postalcode"
  },
  "geometry": {"coordinates":[-1.06776,50.841665],"type":"Point"}
}
