{
  "type": "Feature",
  "properties": {
    "iso:country":"GB",
    "wof:name":"WR1 1HP",
    "wof:placetype":"postalcode"
},
  "geometry": {"coordinates":[-2.22482832800432,52.20069265707202],"type":"Point"}
}