{
  "type": "Feature",
  "properties": {
    "iso:country": "GB",
    "wof:name": "NG25 0DE",
    "wof:placetype": "postalcode"
  },
  "geometry": {"coordinates":[-0.959943,53.082346],"type":"Point"}
}
