{
  "type": "Feature",
  "properties": {
    "iso:country":"GB",
    "wof:name":"HS2 0SW",
    "wof:placetype":"postalcode"
},
  "geometry": {"coordinates":[-6.2925236120246,58.46932747717881],"type":"Point"}
}