{
  "type": "Feature",
  "properties": {
    "date:inception_lower": "1995-07-01",
    "date:inception_upper": "1995-07-01",
    "iso:country": "GB",
    "wof:name": "HS2 0SW",
    "wof:placetype": "postalcode"
  },
  "geometry": {"coordinates":[-6.292524,58.469327],"type":"Point"}
}
