{
  "type": "Feature",
  "properties": {
    "iso:country": "GB",
    "wof:name": "PE9 2RS",
    "wof:placetype": "postalcode"
  },
  "geometry": {"coordinates":[-0.504608,52.651738],"type":"Point"}
}
