{
  "type": "Feature",
  "properties": {
    "iso:country":"GB",
    "wof:name":"PE9 2RS",
    "wof:placetype":"postalcode"
},
  "geometry": {"coordinates":[-0.50460830590129,52.65173816611353],"type":"Point"}
}