{
  "type": "Feature",
  "properties": {
    "date:inception_lower": "2020-08-01",
    "date:inception_upper": "2020-08-01",
    "iso:country": "GB",
    "wof:name": "CT9 2RY",
    "wof:placetype": "postalcode"
  },
  "geometry": {"coordinates":[1.404926,51.383951],"type":"Point"}
}
