{
  "type": "Feature",
  "properties": {
    "date:inception_lower": "2023-12-01",
    "date:inception_upper": "2023-12-01",
    "iso:country": "GB",
    "wof:name": "LS25 4FT",
    "wof:placetype": "postalcode"
  },
  "geometry": {"coordinates":[-1.330209,53.788089],"type":"Point"}
}
