{
  "type": "Feature",
  "properties": {
    "iso:country":"GB",
    "wof:name":"FK3 9DA",
    "wof:placetype":"postalcode"
},
  "geometry": {"coordinates":[-3.71049580522933,56.01366139179507],"type":"Point"}
}