{
  "type": "Feature",
  "properties": {
    "iso:country":"GB",
    "wof:name":"AB11 8SE",
    "wof:placetype":"postalcode"
},
  "geometry": {"coordinates":[-2.07820361217237,57.13241646589265],"type":"Point"}
}