{
  "type": "Feature",
  "properties": {
    "date:inception_lower": "2021-08-01",
    "date:inception_upper": "2021-08-01",
    "iso:country": "GB",
    "wof:name": "AB16 9BU",
    "wof:placetype": "postalcode"
  },
  "geometry": {"coordinates":[-2.159427,57.15303],"type":"Point"}
}
