{
  "type": "Feature",
  "properties": {
    "date:inception_lower": "2018-02-01",
    "date:inception_upper": "2018-02-01",
    "iso:country": "GB",
    "wof:name": "BH24 2FB",
    "wof:placetype": "postalcode"
  },
  "geometry": {"coordinates":[-1.855035,50.817914],"type":"Point"}
}
