{
  "type": "Feature",
  "properties": {
    "iso:country":"GB",
    "wof:name":"CV6 5FP",
    "wof:placetype":"postalcode"
},
  "geometry": {"coordinates":[-1.49164413570347,52.42801433791753],"type":"Point"}
}