{
  "type": "Feature",
  "properties": {
    "date:inception_lower": "1980-01-01",
    "date:inception_upper": "1980-01-01",
    "iso:country": "GB",
    "wof:name": "BN1 8YL",
    "wof:placetype": "postalcode"
  },
  "geometry": {"coordinates":[-0.210583,50.879724],"type":"Point"}
}
