{
  "type": "Feature",
  "properties": {
    "iso:country":"GB",
    "wof:name":"BN1 8YL",
    "wof:placetype":"postalcode"
},
  "geometry": {"coordinates":[-0.21061030125599,50.87973025360539],"type":"Point"}
}