{
  "type": "Feature",
  "properties": {
    "iso:country":"GB",
    "wof:name":"TR2 4JZ",
    "wof:placetype":"postalcode"
},
  "geometry": {"coordinates":[-4.94854159151615,50.29012129203753],"type":"Point"}
}