{
  "type": "Feature",
  "properties": {
    "date:inception_lower": "1983-01-01",
    "date:inception_upper": "1983-01-01",
    "iso:country": "GB",
    "wof:name": "TR2 4JZ",
    "wof:placetype": "postalcode"
  },
  "geometry": {"coordinates":[-4.948542,50.290121],"type":"Point"}
}
