{
  "type": "Feature",
  "properties": {
    "iso:country":"GB",
    "wof:name":"MK1 1NL",
    "wof:placetype":"postalcode"
},
  "geometry": {"coordinates":[-0.73736636606007,52.0078597708906],"type":"Point"}
}