{
  "type": "Feature",
  "properties": {
    "iso:country": "GB",
    "wof:name": "CF62 4HW",
    "wof:placetype": "postalcode"
  },
  "geometry": {"coordinates":[-3.414445,51.396881],"type":"Point"}
}
