{
  "type": "Feature",
  "properties": {
    "iso:country":"GB",
    "wof:name":"CF62 4HW",
    "wof:placetype":"postalcode"
},
  "geometry": {"coordinates":[-3.4144449750978,51.39688106519052],"type":"Point"}
}