{
  "type": "Feature",
  "properties": {
    "date:inception_lower":"1980-01-01",
    "date:inception_upper":"1980-01-31",
    "iso:country":"GB",
    "wof:name":"TR11 2NR",
    "wof:placetype":"postalcode"
},
  "geometry": {"coordinates":[-5.082376,50.158087],"type":"Point"}
}