{
  "type": "Feature",
  "properties": {
    "iso:country":"GB",
    "wof:name":"ST3 7ET",
    "wof:placetype":"postalcode"
},
  "geometry": {"coordinates":[-2.11840806639168,52.97502210863654],"type":"Point"}
}