{
  "type": "Feature",
  "properties": {
    "iso:country":"GB",
    "wof:name":"W1S 2YB",
    "wof:placetype":"postalcode"
},
  "geometry": {"coordinates":[-0.14315016664088,51.51148298743167],"type":"Point"}
}