{
  "type": "Feature",
  "properties": {
    "date:inception_lower": "2019-06-01",
    "date:inception_upper": "2019-06-01",
    "iso:country": "GB",
    "wof:name": "RH15 0ZE",
    "wof:placetype": "postalcode"
  },
  "geometry": {"coordinates":[-0.114959,50.954628],"type":"Point"}
}
