{
  "type": "Feature",
  "properties": {
    "date:inception_lower": "2008-03-01",
    "date:inception_upper": "2008-03-01",
    "iso:country": "GB",
    "wof:name": "ML10 6UQ",
    "wof:placetype": "postalcode"
  },
  "geometry": {"coordinates":[-4.018654,55.654058],"type":"Point"}
}
