{
  "type": "Feature",
  "properties": {
    "iso:country":"GB",
    "wof:name":"ML10 6UQ",
    "wof:placetype":"postalcode"
},
  "geometry": {"coordinates":[-4.01733218184819,55.65531308916814],"type":"Point"}
}