{
  "type": "Feature",
  "properties": {
    "iso:country":"GB",
    "wof:name":"TR5 0XN",
    "wof:placetype":"postalcode"
},
  "geometry": {"coordinates":[-5.17869171365325,50.31136123020123],"type":"Point"}
}