{
  "type": "Feature",
  "properties": {
    "iso:country":"GB",
    "wof:name":"E16 4HX",
    "wof:placetype":"postalcode"
},
  "geometry": {"coordinates":[0.01082864263651,51.52239710530225],"type":"Point"}
}