{
  "type": "Feature",
  "properties": {
    "iso:country": "GB",
    "wof:name": "NR10 3DY",
    "wof:placetype": "postalcode"
  },
  "geometry": {"coordinates":[1.239072,52.702663],"type":"Point"}
}
