{
  "type": "Feature",
  "properties": {
    "iso:country":"GB",
    "wof:name":"LE10 1PX",
    "wof:placetype":"postalcode"
},
  "geometry": {"coordinates":[-1.36726974371652,52.54694675366109],"type":"Point"}
}