{
  "type": "Feature",
  "properties": {
    "iso:country": "GB",
    "wof:name": "LE10 1PX",
    "wof:placetype": "postalcode"
  },
  "geometry": {"coordinates":[-1.36727,52.546947],"type":"Point"}
}
