{
  "type": "Feature",
  "properties": {
    "iso:country":"GB",
    "wof:name":"OL12 9LW",
    "wof:placetype":"postalcode"
},
  "geometry": {"coordinates":[-2.13093383198013,53.64626703841994],"type":"Point"}
}