{
  "type": "Feature",
  "properties": {
    "date:inception_lower": "1990-02-01",
    "date:inception_upper": "1990-02-01",
    "iso:country": "GB",
    "wof:name": "WV8 2JA",
    "wof:placetype": "postalcode"
  },
  "geometry": {"coordinates":[-2.18191,52.620792],"type":"Point"}
}
