{
  "type": "Feature",
  "properties": {
    "date:inception_lower":"2018-04-01",
    "date:inception_upper":"2018-04-30",
    "iso:country":"GB",
    "wof:name":"EN8 7DF",
    "wof:placetype":"postalcode"
},
  "geometry": {"coordinates":[-0.032949,51.687535],"type":"Point"}
}