{
  "type": "Feature",
  "properties": {
    "iso:country":"GB",
    "wof:name":"WV8 1PU",
    "wof:placetype":"postalcode"
},
  "geometry": {"coordinates":[-2.20078725494196,52.63039851111643],"type":"Point"}
}