{
  "type": "Feature",
  "properties": {
    "iso:country":"GB",
    "wof:name":"PR2 8DH",
    "wof:placetype":"postalcode"
},
  "geometry": {"coordinates":[-2.68826889466064,53.77880581474324],"type":"Point"}
}