{
  "type": "Feature",
  "properties": {
    "date:inception_lower": "2007-02-01",
    "date:inception_upper": "2007-02-01",
    "iso:country": "GB",
    "wof:name": "KY12 9UY",
    "wof:placetype": "postalcode"
  },
  "geometry": {"coordinates":[-3.580869,56.116986],"type":"Point"}
}
