{
  "type": "Feature",
  "properties": {
    "iso:country":"GB",
    "wof:name":"LL53 7YN",
    "wof:placetype":"postalcode"
},
  "geometry": {"coordinates":[-4.48858606792098,52.88521441583703],"type":"Point"}
}