{
  "type": "Feature",
  "properties": {
    "date:inception_lower":"1980-01-01",
    "date:inception_upper":"1980-01-31",
    "iso:country":"GB",
    "wof:name":"LL13 0SB",
    "wof:placetype":"postalcode"
},
  "geometry": {"coordinates":[-2.953389,53.021741],"type":"Point"}
}