{
  "type": "Feature",
  "properties": {
    "iso:country":"GB",
    "wof:name":"LL13 0SB",
    "wof:placetype":"postalcode"
},
  "geometry": {"coordinates":[-2.95338937897218,53.02174140959831],"type":"Point"}
}