{
  "type": "Feature",
  "properties": {
    "iso:country": "GB",
    "wof:name": "CO10 9BQ",
    "wof:placetype": "postalcode"
  },
  "geometry": {"coordinates":[0.741302,52.108607],"type":"Point"}
}
