{
  "type": "Feature",
  "properties": {
    "iso:country":"GB",
    "wof:name":"BH23 1JF",
    "wof:placetype":"postalcode"
},
  "geometry": {"coordinates":[-1.78176417210023,50.73301850378903],"type":"Point"}
}