{
  "type": "Feature",
  "properties": {
    "iso:country":"GB",
    "wof:name":"NE34 9JN",
    "wof:placetype":"postalcode"
},
  "geometry": {"coordinates":[-1.44901031726105,54.96452860554647],"type":"Point"}
}