{
  "type": "Feature",
  "properties": {
    "iso:country": "GB",
    "wof:name": "NE34 9JN",
    "wof:placetype": "postalcode"
  },
  "geometry": {"coordinates":[-1.44901,54.964529],"type":"Point"}
}
