{
  "type": "Feature",
  "properties": {
    "iso:country": "GB",
    "wof:name": "ST13 6LU",
    "wof:placetype": "postalcode"
  },
  "geometry": {"coordinates":[-2.019587,53.106725],"type":"Point"}
}
