{
  "type": "Feature",
  "properties": {
    "iso:country":"GB",
    "wof:name":"ST13 6LU",
    "wof:placetype":"postalcode"
},
  "geometry": {"coordinates":[-2.01958693853672,53.10672508133504],"type":"Point"}
}