{
  "type": "Feature",
  "properties": {
    "date:inception_lower": "1983-07-01",
    "date:inception_upper": "1983-07-01",
    "iso:country": "GB",
    "wof:name": "DE7 8TT",
    "wof:placetype": "postalcode"
  },
  "geometry": {"coordinates":[-1.320862,52.993792],"type":"Point"}
}
