{
  "type": "Feature",
  "properties": {
    "date:inception_lower": "2002-06-01",
    "date:inception_upper": "2002-06-01",
    "iso:country": "GB",
    "wof:name": "CO4 9RW",
    "wof:placetype": "postalcode"
  },
  "geometry": {"coordinates":[0.921313,51.911487],"type":"Point"}
}
