{
  "type": "Feature",
  "properties": {
    "iso:country":"GB",
    "wof:name":"CO4 9RW",
    "wof:placetype":"postalcode"
},
  "geometry": {"coordinates":[0.92131311578521,51.91148717965484],"type":"Point"}
}