{
  "type": "Feature",
  "properties": {
    "iso:country": "GB",
    "wof:name": "L39 3AG",
    "wof:placetype": "postalcode"
  },
  "geometry": {"coordinates":[-2.887116,53.568111],"type":"Point"}
}
