{
  "type": "Feature",
  "properties": {
    "iso:country":"GB",
    "wof:name":"SN3 6LF",
    "wof:placetype":"postalcode"
},
  "geometry": {"coordinates":[-1.72699140534557,51.54932656487765],"type":"Point"}
}