{
  "type": "Feature",
  "properties": {
    "iso:country": "GB",
    "wof:name": "CF40 1EX",
    "wof:placetype": "postalcode"
  },
  "geometry": {"coordinates":[-3.45321,51.6133],"type":"Point"}
}
