{
  "type": "Feature",
  "properties": {
    "iso:country":"GB",
    "wof:name":"CF40 1EX",
    "wof:placetype":"postalcode"
},
  "geometry": {"coordinates":[-3.45319838932152,51.61329635472787],"type":"Point"}
}