{
  "type": "Feature",
  "properties": {
    "date:inception_lower": "1980-01-01",
    "date:inception_upper": "1980-01-01",
    "iso:country": "GB",
    "wof:name": "BS7 0XJ",
    "wof:placetype": "postalcode"
  },
  "geometry": {"coordinates":[-2.5853,51.491761],"type":"Point"}
}
