{
  "type": "Feature",
  "properties": {
    "iso:country": "GB",
    "wof:name": "CO4 3PF",
    "wof:placetype": "postalcode"
  },
  "geometry": {"coordinates":[0.933374,51.891725],"type":"Point"}
}
