{
  "type": "Feature",
  "properties": {
    "iso:country":"GB",
    "wof:name":"CB1 9HD",
    "wof:placetype":"postalcode"
},
  "geometry": {"coordinates":[0.17418428820824,52.18450128649647],"type":"Point"}
}