{
  "type": "Feature",
  "properties": {
    "date:inception_lower":"2004-08-01",
    "date:inception_upper":"2004-08-31",
    "iso:country":"GB",
    "wof:name":"CB1 9HD",
    "wof:placetype":"postalcode"
},
  "geometry": {"coordinates":[0.174184,52.184501],"type":"Point"}
}