{
  "type": "Feature",
  "properties": {
    "date:inception_lower": "2018-01-01",
    "date:inception_upper": "2018-01-01",
    "iso:country": "GB",
    "wof:name": "OX15 4ST",
    "wof:placetype": "postalcode"
  },
  "geometry": {"coordinates":[-1.386693,52.019944],"type":"Point"}
}
