{
  "type": "Feature",
  "properties": {
    "iso:country": "GB",
    "wof:name": "SN9 5LN",
    "wof:placetype": "postalcode"
  },
  "geometry": {"coordinates":[-1.732486,51.342281],"type":"Point"}
}
