{
  "type": "Feature",
  "properties": {
    "iso:country":"GB",
    "wof:name":"SN9 5LN",
    "wof:placetype":"postalcode"
},
  "geometry": {"coordinates":[-1.73248598675616,51.34228135300643],"type":"Point"}
}