{
  "type": "Feature",
  "properties": {
    "iso:country":"GB",
    "wof:name":"SS17 9BZ",
    "wof:placetype":"postalcode"
},
  "geometry": {"coordinates":[0.46527356060531,51.528347400537],"type":"Point"}
}