{
  "type": "Feature",
  "properties": {
    "iso:country":"GB",
    "wof:name":"SW15 5EY",
    "wof:placetype":"postalcode"
},
  "geometry": {"coordinates":[-0.24331574792734,51.4524709058115],"type":"Point"}
}