{
  "type": "Feature",
  "properties": {
    "date:inception_lower": "1980-01-01",
    "date:inception_upper": "1980-01-01",
    "iso:country": "GB",
    "wof:name": "BN15 8UA",
    "wof:placetype": "postalcode"
  },
  "geometry": {"coordinates":[-0.332425,50.824652],"type":"Point"}
}
