{
  "type": "Feature",
  "properties": {
    "iso:country":"GB",
    "wof:name":"BN15 8UA",
    "wof:placetype":"postalcode"
},
  "geometry": {"coordinates":[-0.33242534848811,50.82465199667197],"type":"Point"}
}