{
  "type": "Feature",
  "properties": {
    "iso:country":"GB",
    "wof:name":"EX23 0BY",
    "wof:placetype":"postalcode"
},
  "geometry": {"coordinates":[-4.55038488744331,50.71416542472576],"type":"Point"}
}