{
  "type": "Feature",
  "properties": {
    "date:inception_lower": "1980-01-01",
    "date:inception_upper": "1980-01-01",
    "iso:country": "GB",
    "wof:name": "SA42 0NY",
    "wof:placetype": "postalcode"
  },
  "geometry": {"coordinates":[-4.787419,52.051413],"type":"Point"}
}
