{
  "type": "Feature",
  "properties": {
    "iso:country":"GB",
    "wof:name":"SA42 0NY",
    "wof:placetype":"postalcode"
},
  "geometry": {"coordinates":[-4.78741929236246,52.05141277969451],"type":"Point"}
}