{
  "type": "Feature",
  "properties": {
    "iso:country": "GB",
    "wof:name": "PL15 7TA",
    "wof:placetype": "postalcode"
  },
  "geometry": {"coordinates":[-4.455923,50.622996],"type":"Point"}
}
