{
  "type": "Feature",
  "properties": {
    "iso:country":"GB",
    "wof:name":"PL15 7TA",
    "wof:placetype":"postalcode"
},
  "geometry": {"coordinates":[-4.45581973126519,50.62301540845228],"type":"Point"}
}