{
  "type": "Feature",
  "properties": {
    "iso:country":"GB",
    "wof:name":"WR1 1UN",
    "wof:placetype":"postalcode"
},
  "geometry": {"coordinates":[-2.22009946618112,52.19420151778006],"type":"Point"}
}