{
  "type": "Feature",
  "properties": {
    "iso:country": "GB",
    "wof:name": "LL53 6NL",
    "wof:placetype": "postalcode"
  },
  "geometry": {"coordinates":[-4.449617,52.960933],"type":"Point"}
}
