{
  "type": "Feature",
  "properties": {
    "iso:country":"GB",
    "wof:name":"SN11 8RU",
    "wof:placetype":"postalcode"
},
  "geometry": {"coordinates":[-1.98702758111385,51.4537309202758],"type":"Point"}
}