{
  "type": "Feature",
  "properties": {
    "iso:country":"GB",
    "wof:name":"DE4 3PP",
    "wof:placetype":"postalcode"
},
  "geometry": {"coordinates":[-1.55753327642535,53.13280071199397],"type":"Point"}
}