{
  "type": "Feature",
  "properties": {
    "iso:country":"GB",
    "wof:name":"NE6 2BS",
    "wof:placetype":"postalcode"
},
  "geometry": {"coordinates":[-1.58031051408776,54.96957240065253],"type":"Point"}
}