{
  "type": "Feature",
  "properties": {
    "date:inception_lower": "2000-06-01",
    "date:inception_upper": "2000-06-01",
    "iso:country": "GB",
    "wof:name": "NE6 2BS",
    "wof:placetype": "postalcode"
  },
  "geometry": {"coordinates":[-1.58031,54.969572],"type":"Point"}
}
