{
  "type": "Feature",
  "properties": {
    "iso:country": "GB",
    "wof:name": "NE6 2BS",
    "wof:placetype": "postalcode"
  },
  "geometry": {"coordinates":[-1.58031,54.969572],"type":"Point"}
}
