{
  "type": "Feature",
  "properties": {
    "date:inception_lower": "2022-06-01",
    "date:inception_upper": "2022-06-01",
    "iso:country": "GB",
    "wof:name": "HU16 5FU",
    "wof:placetype": "postalcode"
  },
  "geometry": {"coordinates":[-0.422391,53.788962],"type":"Point"}
}
