{
  "type": "Feature",
  "properties": {
    "iso:country":"GB",
    "wof:name":"SL6 6EH",
    "wof:placetype":"postalcode"
},
  "geometry": {"coordinates":[-0.74044926317872,51.5222045958391],"type":"Point"}
}