{
  "type": "Feature",
  "properties": {
    "date:inception_lower": "1980-01-01",
    "date:inception_upper": "1980-01-01",
    "iso:country": "GB",
    "wof:name": "GL51 9JS",
    "wof:placetype": "postalcode"
  },
  "geometry": {"coordinates":[-2.09079,51.911167],"type":"Point"}
}
