{
  "type": "Feature",
  "properties": {
    "iso:country":"GB",
    "wof:name":"ME1 1SL",
    "wof:placetype":"postalcode"
},
  "geometry": {"coordinates":[0.50344923792855,51.38940835570666],"type":"Point"}
}