{
  "type": "Feature",
  "properties": {
    "date:inception_lower": "2018-03-01",
    "date:inception_upper": "2018-03-01",
    "iso:country": "GB",
    "wof:name": "SG10 6FD",
    "wof:placetype": "postalcode"
  },
  "geometry": {"coordinates":[0.06953,51.847974],"type":"Point"}
}
