{
  "type": "Feature",
  "properties": {
    "iso:country": "GB",
    "wof:name": "WF5 0HA",
    "wof:placetype": "postalcode"
  },
  "geometry": {"coordinates":[-1.559916,53.674743],"type":"Point"}
}
