{
  "type": "Feature",
  "properties": {
    "iso:country":"GB",
    "wof:name":"WF5 0HA",
    "wof:placetype":"postalcode"
},
  "geometry": {"coordinates":[-1.55991598691742,53.67474288553775],"type":"Point"}
}