{
  "type": "Feature",
  "properties": {
    "iso:country": "GB",
    "wof:name": "CB4 3HQ",
    "wof:placetype": "postalcode"
  },
  "geometry": {"coordinates":[0.115154,52.22049],"type":"Point"}
}
