{
  "type": "Feature",
  "properties": {
    "iso:country":"GB",
    "wof:name":"KT20 7AQ",
    "wof:placetype":"postalcode"
},
  "geometry": {"coordinates":[-0.21339280002405,51.27049334566696],"type":"Point"}
}