{
  "type": "Feature",
  "properties": {
    "iso:country":"GB",
    "wof:name":"RG2 7AS",
    "wof:placetype":"postalcode"
},
  "geometry": {"coordinates":[-0.96104969800069,51.44500353119457],"type":"Point"}
}