{
  "type": "Feature",
  "properties": {
    "date:inception_lower":"2010-08-01",
    "date:inception_upper":"2010-08-31",
    "iso:country":"GB",
    "wof:name":"KY12 8LN",
    "wof:placetype":"postalcode"
},
  "geometry": {"coordinates":[-3.561968,56.053409],"type":"Point"}
}