{
  "type": "Feature",
  "properties": {
    "iso:country":"GB",
    "wof:name":"KY12 8LN",
    "wof:placetype":"postalcode"
},
  "geometry": {"coordinates":[-3.56196796933776,56.05340898916037],"type":"Point"}
}