{
  "type": "Feature",
  "properties": {
    "iso:country": "GB",
    "wof:name": "FY1 2SG",
    "wof:placetype": "postalcode"
  },
  "geometry": {"coordinates":[-3.044153,53.828564],"type":"Point"}
}
