{
  "type": "Feature",
  "properties": {
    "date:inception_lower":"1996-06-01",
    "date:inception_upper":"1996-06-30",
    "iso:country":"GB",
    "wof:name":"FY1 2SG",
    "wof:placetype":"postalcode"
},
  "geometry": {"coordinates":[-3.044153,53.828564],"type":"Point"}
}