{
  "type": "Feature",
  "properties": {
    "date:inception_lower":"1980-01-01",
    "date:inception_upper":"1980-01-31",
    "iso:country":"GB",
    "wof:name":"G69 0NH",
    "wof:placetype":"postalcode"
},
  "geometry": {"coordinates":[-4.08008,55.91962],"type":"Point"}
}