{
  "type": "Feature",
  "properties": {
    "date:inception_lower":"1998-06-01",
    "date:inception_upper":"1998-06-30",
    "iso:country":"GB",
    "wof:name":"YO23 1JE",
    "wof:placetype":"postalcode"
},
  "geometry": {"coordinates":[-1.080205,53.952059],"type":"Point"}
}