{
  "type": "Feature",
  "properties": {
    "iso:country":"GB",
    "wof:name":"NE9 6HU",
    "wof:placetype":"postalcode"
},
  "geometry": {"coordinates":[-1.59993291599033,54.93623641361923],"type":"Point"}
}