{
  "type": "Feature",
  "properties": {
    "iso:country": "GB",
    "wof:name": "NE11 9LE",
    "wof:placetype": "postalcode"
  },
  "geometry": {"coordinates":[-1.63672,54.94488],"type":"Point"}
}
