{
  "type": "Feature",
  "properties": {
    "iso:country":"GB",
    "wof:name":"CV37 0UA",
    "wof:placetype":"postalcode"
},
  "geometry": {"coordinates":[-1.71444922869016,52.20274716237745],"type":"Point"}
}