{
  "type": "Feature",
  "properties": {
    "date:inception_lower": "1987-04-01",
    "date:inception_upper": "1987-04-01",
    "iso:country": "GB",
    "wof:name": "CV37 0UA",
    "wof:placetype": "postalcode"
  },
  "geometry": {"coordinates":[-1.714449,52.202747],"type":"Point"}
}
