{
  "type": "Feature",
  "properties": {
    "date:inception_lower":"1980-01-01",
    "date:inception_upper":"1980-01-31",
    "iso:country":"GB",
    "wof:name":"YO7 2PZ",
    "wof:placetype":"postalcode"
},
  "geometry": {"coordinates":[-1.255571,54.232029],"type":"Point"}
}