{
  "type": "Feature",
  "properties": {
    "iso:country":"GB",
    "wof:name":"YO7 2PZ",
    "wof:placetype":"postalcode"
},
  "geometry": {"coordinates":[-1.25557060491173,54.23202864020595],"type":"Point"}
}