{
  "type": "Feature",
  "properties": {
    "date:inception_lower":"1980-01-01",
    "date:inception_upper":"1980-01-31",
    "iso:country":"GB",
    "wof:name":"B30 3EG",
    "wof:placetype":"postalcode"
},
  "geometry": {"coordinates":[-1.931237,52.415062],"type":"Point"}
}