{
  "type": "Feature",
  "properties": {
    "iso:country":"GB",
    "wof:name":"B30 3EG",
    "wof:placetype":"postalcode"
},
  "geometry": {"coordinates":[-1.93123658022367,52.41506152543386],"type":"Point"}
}