{
  "type": "Feature",
  "properties": {
    "date:inception_lower": "1980-01-01",
    "date:inception_upper": "1980-01-01",
    "iso:country": "GB",
    "wof:name": "WF9 3HY",
    "wof:placetype": "postalcode"
  },
  "geometry": {"coordinates":[-1.331682,53.591695],"type":"Point"}
}
