{
  "type": "Feature",
  "properties": {
    "date:inception_lower": "1980-01-01",
    "date:inception_upper": "1980-01-01",
    "iso:country": "GB",
    "wof:name": "N7 9BZ",
    "wof:placetype": "postalcode"
  },
  "geometry": {"coordinates":[-0.118247,51.544709],"type":"Point"}
}
