{
  "type": "Feature",
  "properties": {
    "date:inception_lower": "2002-11-01",
    "date:inception_upper": "2002-11-01",
    "iso:country": "GB",
    "wof:name": "OX2 7JJ",
    "wof:placetype": "postalcode"
  },
  "geometry": {"coordinates":[-1.266563,51.780185],"type":"Point"}
}
