{
  "type": "Feature",
  "properties": {
    "iso:country": "GB",
    "wof:name": "AB53 8RG",
    "wof:placetype": "postalcode"
  },
  "geometry": {"coordinates":[-2.389896,57.433184],"type":"Point"}
}
