{
  "type": "Feature",
  "properties": {
    "date:inception_lower": "1996-06-01",
    "date:inception_upper": "1996-06-01",
    "iso:country": "GB",
    "wof:name": "AB53 8RG",
    "wof:placetype": "postalcode"
  },
  "geometry": {"coordinates":[-2.389896,57.433184],"type":"Point"}
}
