{
  "type": "Feature",
  "properties": {
    "date:inception_lower": "1980-01-01",
    "date:inception_upper": "1980-01-01",
    "iso:country": "GB",
    "wof:name": "PR7 5LJ",
    "wof:placetype": "postalcode"
  },
  "geometry": {"coordinates":[-2.681319,53.636488],"type":"Point"}
}
