{
  "type": "Feature",
  "properties": {
    "date:inception_lower":"1999-06-01",
    "date:inception_upper":"1999-06-30",
    "iso:country":"GB",
    "wof:name":"IV18 0RS",
    "wof:placetype":"postalcode"
},
  "geometry": {"coordinates":[-4.175779,57.690115],"type":"Point"}
}