{
  "type": "Feature",
  "properties": {
    "iso:country": "GB",
    "wof:name": "IV18 0RS",
    "wof:placetype": "postalcode"
  },
  "geometry": {"coordinates":[-4.175779,57.690115],"type":"Point"}
}
