{
  "type": "Feature",
  "properties": {
    "iso:country":"GB",
    "wof:name":"IV18 0RS",
    "wof:placetype":"postalcode"
},
  "geometry": {"coordinates":[-4.17577856611351,57.69011515837735],"type":"Point"}
}