{
  "type": "Feature",
  "properties": {
    "date:inception_lower":"2014-01-01",
    "date:inception_upper":"2014-01-31",
    "iso:country":"GB",
    "wof:name":"BS1 6UP",
    "wof:placetype":"postalcode"
},
  "geometry": {"coordinates":[-2.606951,51.448536],"type":"Point"}
}