{
  "type": "Feature",
  "properties": {
    "iso:country":"GB",
    "wof:name":"BS1 6UP",
    "wof:placetype":"postalcode"
},
  "geometry": {"coordinates":[-2.60695073565571,51.44853568642941],"type":"Point"}
}