{
  "type": "Feature",
  "properties": {
    "date:inception_lower":"1980-01-01",
    "date:inception_upper":"1980-01-31",
    "iso:country":"GB",
    "wof:name":"UB3 2EU",
    "wof:placetype":"postalcode"
},
  "geometry": {"coordinates":[-0.41535,51.511897],"type":"Point"}
}