{
  "type": "Feature",
  "properties": {
    "iso:country": "GB",
    "wof:name": "UB3 2EU",
    "wof:placetype": "postalcode"
  },
  "geometry": {"coordinates":[-0.41535,51.511897],"type":"Point"}
}
