{
  "type": "Feature",
  "properties": {
    "iso:country": "GB",
    "wof:name": "HS1 2JE",
    "wof:placetype": "postalcode"
  },
  "geometry": {"coordinates":[-6.385401,58.210478],"type":"Point"}
}
