{
  "type": "Feature",
  "properties": {
    "iso:country":"GB",
    "wof:name":"HS1 2JE",
    "wof:placetype":"postalcode"
},
  "geometry": {"coordinates":[-6.385414073074,58.21044134083022],"type":"Point"}
}