{
  "type": "Feature",
  "properties": {
    "iso:country":"GB",
    "wof:name":"NE33 5NQ",
    "wof:placetype":"postalcode"
},
  "geometry": {"coordinates":[-1.44413103707345,54.97856104875376],"type":"Point"}
}