{
  "type": "Feature",
  "properties": {
    "iso:country": "GB",
    "wof:name": "NE33 5NQ",
    "wof:placetype": "postalcode"
  },
  "geometry": {"coordinates":[-1.444131,54.978561],"type":"Point"}
}
