{
  "type": "Feature",
  "properties": {
    "iso:country":"GB",
    "wof:name":"GL3 2ST",
    "wof:placetype":"postalcode"
},
  "geometry": {"coordinates":[-2.19018265487189,51.88213428490193],"type":"Point"}
}