{
  "type": "Feature",
  "properties": {
    "iso:country":"GB",
    "wof:name":"SL0 9AR",
    "wof:placetype":"postalcode"
},
  "geometry": {"coordinates":[-0.49211291865455,51.50330556042897],"type":"Point"}
}