{
  "type": "Feature",
  "properties": {
    "iso:country": "GB",
    "wof:name": "SK4 4RE",
    "wof:placetype": "postalcode"
  },
  "geometry": {"coordinates":[-2.187457,53.426327],"type":"Point"}
}
