{
  "type": "Feature",
  "properties": {
    "iso:country": "GB",
    "wof:name": "MK44 2NU",
    "wof:placetype": "postalcode"
  },
  "geometry": {"coordinates":[-0.373154,52.203825],"type":"Point"}
}
