{
  "type": "Feature",
  "properties": {
    "iso:country":"GB",
    "wof:name":"MK44 2NU",
    "wof:placetype":"postalcode"
},
  "geometry": {"coordinates":[-0.37317505730706,52.20381206335055],"type":"Point"}
}