{
  "type": "Feature",
  "properties": {
    "iso:country": "GB",
    "wof:name": "S71 1AF",
    "wof:placetype": "postalcode"
  },
  "geometry": {"coordinates":[-1.473157,53.551261],"type":"Point"}
}
