{
  "type": "Feature",
  "properties": {
    "iso:country":"GB",
    "wof:name":"S71 1AF",
    "wof:placetype":"postalcode"
},
  "geometry": {"coordinates":[-1.47315707540808,53.55126149607906],"type":"Point"}
}