{
  "type": "Feature",
  "properties": {
    "iso:country":"GB",
    "wof:name":"RH14 0HR",
    "wof:placetype":"postalcode"
},
  "geometry": {"coordinates":[-0.53759573621419,51.00246993724609],"type":"Point"}
}