{
  "type": "Feature",
  "properties": {
    "iso:country": "GB",
    "wof:name": "SA31 1DA",
    "wof:placetype": "postalcode"
  },
  "geometry": {"coordinates":[-4.30509,51.858467],"type":"Point"}
}
