{
  "type": "Feature",
  "properties": {
    "date:inception_lower": "1980-01-01",
    "date:inception_upper": "1980-01-01",
    "iso:country": "GB",
    "wof:name": "SA31 1DA",
    "wof:placetype": "postalcode"
  },
  "geometry": {"coordinates":[-4.30509,51.858467],"type":"Point"}
}
