{
  "type": "Feature",
  "properties": {
    "iso:country": "GB",
    "wof:name": "TS18 5AB",
    "wof:placetype": "postalcode"
  },
  "geometry": {"coordinates":[-1.34828,54.561301],"type":"Point"}
}
