{
  "type": "Feature",
  "properties": {
    "iso:country":"GB",
    "wof:name":"TS18 5AB",
    "wof:placetype":"postalcode"
},
  "geometry": {"coordinates":[-1.34828050245272,54.5613007040586],"type":"Point"}
}