{
  "type": "Feature",
  "properties": {
    "date:inception_lower": "1983-07-01",
    "date:inception_upper": "1983-07-01",
    "iso:country": "GB",
    "wof:name": "WF17 8AP",
    "wof:placetype": "postalcode"
  },
  "geometry": {"coordinates":[-1.654855,53.712283],"type":"Point"}
}
