{
  "type": "Feature",
  "properties": {
    "iso:country":"GB",
    "wof:name":"EH3 6HE",
    "wof:placetype":"postalcode"
},
  "geometry": {"coordinates":[-3.20545900550078,55.95597091251014],"type":"Point"}
}