{
  "type": "Feature",
  "properties": {
    "iso:country":"GB",
    "wof:name":"DN7 4DF",
    "wof:placetype":"postalcode"
},
  "geometry": {"coordinates":[-1.02391530822654,53.56601274200295],"type":"Point"}
}