{
  "type": "Feature",
  "properties": {
    "iso:country":"GB",
    "wof:name":"SW19 6TL",
    "wof:placetype":"postalcode"
},
  "geometry": {"coordinates":[-0.2150189657118,51.44732241433932],"type":"Point"}
}