{
  "type": "Feature",
  "properties": {
    "iso:country": "GB",
    "wof:name": "LS12 4JE",
    "wof:placetype": "postalcode"
  },
  "geometry": {"coordinates":[-1.599547,53.792716],"type":"Point"}
}
