{
  "type": "Feature",
  "properties": {
    "iso:country": "GB",
    "wof:name": "IP7 7BA",
    "wof:placetype": "postalcode"
  },
  "geometry": {"coordinates":[0.867619,52.088675],"type":"Point"}
}
