{
  "type": "Feature",
  "properties": {
    "iso:country":"GB",
    "wof:name":"IP7 7BA",
    "wof:placetype":"postalcode"
},
  "geometry": {"coordinates":[0.86761883163633,52.08867472375098],"type":"Point"}
}