{
  "type": "Feature",
  "properties": {
    "iso:country":"GB",
    "wof:name":"CT1 2PT",
    "wof:placetype":"postalcode"
},
  "geometry": {"coordinates":[1.0750878514676,51.27525165278423],"type":"Point"}
}