{
  "type": "Feature",
  "properties": {
    "iso:country": "GB",
    "wof:name": "CT1 2PT",
    "wof:placetype": "postalcode"
  },
  "geometry": {"coordinates":[1.074978,51.275305],"type":"Point"}
}
