{
  "type": "Feature",
  "properties": {
    "date:inception_lower": "1980-01-01",
    "date:inception_upper": "1980-01-01",
    "iso:country": "GB",
    "wof:name": "SW14 8RA",
    "wof:placetype": "postalcode"
  },
  "geometry": {"coordinates":[-0.260278,51.461743],"type":"Point"}
}
