{
  "type": "Feature",
  "properties": {
    "iso:country":"GB",
    "wof:name":"SW14 8RA",
    "wof:placetype":"postalcode"
},
  "geometry": {"coordinates":[-0.26027764083069,51.4617432676025],"type":"Point"}
}