{
  "type": "Feature",
  "properties": {
    "iso:country":"GB",
    "wof:name":"NE37 2UA",
    "wof:placetype":"postalcode"
},
  "geometry": {"coordinates":[-1.52039028063628,54.90656335581593],"type":"Point"}
}