{
  "type": "Feature",
  "properties": {
    "date:inception_lower":"1994-12-01",
    "date:inception_upper":"1994-12-31",
    "iso:country":"GB",
    "wof:name":"RM16 6NX",
    "wof:placetype":"postalcode"
},
  "geometry": {"coordinates":[0.314304,51.489399],"type":"Point"}
}