{
  "type": "Feature",
  "properties": {
    "iso:country":"GB",
    "wof:name":"DN4 7BB",
    "wof:placetype":"postalcode"
},
  "geometry": {"coordinates":[-1.0939411734445,53.50894608348967],"type":"Point"}
}