{
  "type": "Feature",
  "properties": {
    "date:inception_lower": "1993-01-01",
    "date:inception_upper": "1993-01-01",
    "iso:country": "GB",
    "wof:name": "DN4 7BB",
    "wof:placetype": "postalcode"
  },
  "geometry": {"coordinates":[-1.093941,53.508946],"type":"Point"}
}
