{
  "type": "Feature",
  "properties": {
    "iso:country": "GB",
    "wof:name": "ST20 0FH",
    "wof:placetype": "postalcode"
  },
  "geometry": {"coordinates":[-2.24889,52.783086],"type":"Point"}
}
