{
  "type": "Feature",
  "properties": {
    "date:inception_lower": "2016-05-01",
    "date:inception_upper": "2016-05-01",
    "iso:country": "GB",
    "wof:name": "ST20 0FH",
    "wof:placetype": "postalcode"
  },
  "geometry": {"coordinates":[-2.24889,52.783086],"type":"Point"}
}
