{
  "type": "Feature",
  "properties": {
    "date:inception_lower": "2016-05-01",
    "date:inception_upper": "2016-05-01",
    "iso:country": "GB",
    "wof:name": "TA6 3FJ",
    "wof:placetype": "postalcode"
  },
  "geometry": {"coordinates":[-3.005676,51.133826],"type":"Point"}
}
