{
  "type": "Feature",
  "properties": {
    "iso:country":"GB",
    "wof:name":"LS6 1EW",
    "wof:placetype":"postalcode"
},
  "geometry": {"coordinates":[-1.57120935975772,53.8132636634814],"type":"Point"}
}