{
  "type": "Feature",
  "properties": {
    "iso:country":"GB",
    "wof:name":"TN11 8DB",
    "wof:placetype":"postalcode"
},
  "geometry": {"coordinates":[0.18104949294159,51.17320063633305],"type":"Point"}
}