{
  "type": "Feature",
  "properties": {
    "iso:country":"GB",
    "wof:name":"CB7 4BG",
    "wof:placetype":"postalcode"
},
  "geometry": {"coordinates":[0.26645441029493,52.39599200873765],"type":"Point"}
}