{
  "type": "Feature",
  "properties": {
    "iso:country": "GB",
    "wof:name": "CB7 4BG",
    "wof:placetype": "postalcode"
  },
  "geometry": {"coordinates":[0.266454,52.395992],"type":"Point"}
}
