{
  "type": "Feature",
  "properties": {
    "date:inception_lower":"1995-01-01",
    "date:inception_upper":"1995-01-31",
    "iso:country":"GB",
    "wof:name":"CB7 4BG",
    "wof:placetype":"postalcode"
},
  "geometry": {"coordinates":[0.266454,52.395992],"type":"Point"}
}