{
  "type": "Feature",
  "properties": {
    "iso:country":"GB",
    "wof:name":"CO5 0FN",
    "wof:placetype":"postalcode"
},
  "geometry": {"coordinates":[0.74281440278862,51.81577894444388],"type":"Point"}
}