{
  "type": "Feature",
  "properties": {
    "date:inception_lower": "2012-06-01",
    "date:inception_upper": "2012-06-01",
    "iso:country": "GB",
    "wof:name": "CO5 0FN",
    "wof:placetype": "postalcode"
  },
  "geometry": {"coordinates":[0.742814,51.815779],"type":"Point"}
}
