{
  "type": "Feature",
  "properties": {
    "iso:country":"GB",
    "wof:name":"BB18 6RT",
    "wof:placetype":"postalcode"
},
  "geometry": {"coordinates":[-2.13836962109263,53.91585337633745],"type":"Point"}
}