{
  "type": "Feature",
  "properties": {
    "date:inception_lower":"1981-09-01",
    "date:inception_upper":"1981-09-30",
    "iso:country":"GB",
    "wof:name":"SS13 1BX",
    "wof:placetype":"postalcode"
},
  "geometry": {"coordinates":[0.502336,51.589715],"type":"Point"}
}