{
  "type": "Feature",
  "properties": {
    "iso:country": "GB",
    "wof:name": "SS13 1BX",
    "wof:placetype": "postalcode"
  },
  "geometry": {"coordinates":[0.502336,51.589715],"type":"Point"}
}
