{
  "type": "Feature",
  "properties": {
    "iso:country":"GB",
    "wof:name":"SY16 2EL",
    "wof:placetype":"postalcode"
},
  "geometry": {"coordinates":[-3.32163286822941,52.51819492216266],"type":"Point"}
}