{
  "type": "Feature",
  "properties": {
    "iso:country": "GB",
    "wof:name": "CH4 0DR",
    "wof:placetype": "postalcode"
  },
  "geometry": {"coordinates":[-2.979653,53.172019],"type":"Point"}
}
