{
  "type": "Feature",
  "properties": {
    "iso:country":"GB",
    "wof:name":"CH4 0DR",
    "wof:placetype":"postalcode"
},
  "geometry": {"coordinates":[-2.97965287866628,53.17201917836731],"type":"Point"}
}