{
  "type": "Feature",
  "properties": {
    "iso:country":"GB",
    "wof:name":"WF15 7BW",
    "wof:placetype":"postalcode"
},
  "geometry": {"coordinates":[-1.68742822041698,53.70219762385783],"type":"Point"}
}