{
  "type": "Feature",
  "properties": {
    "date:inception_lower": "1983-01-01",
    "date:inception_upper": "1983-01-01",
    "iso:country": "GB",
    "wof:name": "LS24 8LX",
    "wof:placetype": "postalcode"
  },
  "geometry": {"coordinates":[-1.254208,53.889253],"type":"Point"}
}
