{
  "type": "Feature",
  "properties": {
    "iso:country":"GB",
    "wof:name":"LS24 8LX",
    "wof:placetype":"postalcode"
},
  "geometry": {"coordinates":[-1.2541529603885,53.88945905017611],"type":"Point"}
}