{
  "type": "Feature",
  "properties": {
    "iso:country": "GB",
    "wof:name": "TN11 0QP",
    "wof:placetype": "postalcode"
  },
  "geometry": {"coordinates":[0.310282,51.190981],"type":"Point"}
}
