{
  "type": "Feature",
  "properties": {
    "iso:country":"GB",
    "wof:name":"TN11 0QP",
    "wof:placetype":"postalcode"
},
  "geometry": {"coordinates":[0.31028147500312,51.19098148547628],"type":"Point"}
}