{
  "type": "Feature",
  "properties": {
    "iso:country": "GB",
    "wof:name": "OX14 4GS",
    "wof:placetype": "postalcode"
  },
  "geometry": {"coordinates":[-1.311757,51.645664],"type":"Point"}
}
