{
  "type": "Feature",
  "properties": {
    "iso:country":"GB",
    "wof:name":"BB7 9UJ",
    "wof:placetype":"postalcode"
},
  "geometry": {"coordinates":[-2.4220949649151,53.83287936848023],"type":"Point"}
}