{
  "type": "Feature",
  "properties": {
    "iso:country": "GB",
    "wof:name": "BB7 9UJ",
    "wof:placetype": "postalcode"
  },
  "geometry": {"coordinates":[-2.422095,53.832879],"type":"Point"}
}
