{
  "type": "Feature",
  "properties": {
    "iso:country": "GB",
    "wof:name": "DN12 1EZ",
    "wof:placetype": "postalcode"
  },
  "geometry": {"coordinates":[-1.187778,53.486108],"type":"Point"}
}
