{
  "type": "Feature",
  "properties": {
    "date:inception_lower": "2019-07-01",
    "date:inception_upper": "2019-07-01",
    "iso:country": "GB",
    "wof:name": "DN12 1EZ",
    "wof:placetype": "postalcode"
  },
  "geometry": {"coordinates":[-1.187793,53.486126],"type":"Point"}
}
