{
  "type": "Feature",
  "properties": {
    "date:inception_lower":"1996-06-01",
    "date:inception_upper":"1996-06-30",
    "iso:country":"GB",
    "wof:name":"SG2 7JS",
    "wof:placetype":"postalcode"
},
  "geometry": {"coordinates":[-0.130237,51.915128],"type":"Point"}
}