{
  "type": "Feature",
  "properties": {
    "iso:country": "GB",
    "wof:name": "SG2 7JS",
    "wof:placetype": "postalcode"
  },
  "geometry": {"coordinates":[-0.130237,51.915128],"type":"Point"}
}
