{
  "type": "Feature",
  "properties": {
    "iso:country":"GB",
    "wof:name":"SG2 7JS",
    "wof:placetype":"postalcode"
},
  "geometry": {"coordinates":[-0.13023698841247,51.91512845192248],"type":"Point"}
}