{
  "type": "Feature",
  "properties": {
    "date:inception_lower": "2021-08-01",
    "date:inception_upper": "2021-08-01",
    "iso:country": "GB",
    "wof:name": "BB4 7FF",
    "wof:placetype": "postalcode"
  },
  "geometry": {"coordinates":[-2.246825,53.685441],"type":"Point"}
}
