{
  "type": "Feature",
  "properties": {
    "iso:country":"GB",
    "wof:name":"NE37 1QD",
    "wof:placetype":"postalcode"
},
  "geometry": {"coordinates":[-1.53108612896912,54.91220359443175],"type":"Point"}
}