{
  "type": "Feature",
  "properties": {
    "date:inception_lower":"1984-02-01",
    "date:inception_upper":"1984-02-29",
    "iso:country":"GB",
    "wof:name":"NE37 1QD",
    "wof:placetype":"postalcode"
},
  "geometry": {"coordinates":[-1.531086,54.912204],"type":"Point"}
}