{
  "type": "Feature",
  "properties": {
    "iso:country": "GB",
    "wof:name": "NE37 1QD",
    "wof:placetype": "postalcode"
  },
  "geometry": {"coordinates":[-1.531086,54.912204],"type":"Point"}
}
