{
  "type": "Feature",
  "properties": {
    "iso:country": "GB",
    "wof:name": "DE55 6EQ",
    "wof:placetype": "postalcode"
  },
  "geometry": {"coordinates":[-1.403848,53.123349],"type":"Point"}
}
