{
  "type": "Feature",
  "properties": {
    "date:inception_lower": "1997-12-01",
    "date:inception_upper": "1997-12-01",
    "iso:country": "GB",
    "wof:name": "DE55 6EQ",
    "wof:placetype": "postalcode"
  },
  "geometry": {"coordinates":[-1.403848,53.123349],"type":"Point"}
}
