{
  "type": "Feature",
  "properties": {
    "iso:country":"GB",
    "wof:name":"DE55 6EQ",
    "wof:placetype":"postalcode"
},
  "geometry": {"coordinates":[-1.40368964548069,53.1230600135826],"type":"Point"}
}