{
  "type": "Feature",
  "properties": {
    "date:inception_lower": "1980-01-01",
    "date:inception_upper": "1980-01-01",
    "iso:country": "GB",
    "wof:name": "LD1 6PR",
    "wof:placetype": "postalcode"
  },
  "geometry": {"coordinates":[-3.401617,52.358637],"type":"Point"}
}
