{
  "type": "Feature",
  "properties": {
    "date:inception_lower": "2023-07-01",
    "date:inception_upper": "2023-07-01",
    "iso:country": "GB",
    "wof:name": "BN7 3FG",
    "wof:placetype": "postalcode"
  },
  "geometry": {"coordinates":[-0.060082,50.934834],"type":"Point"}
}
