{
  "type": "Feature",
  "properties": {
    "date:inception_lower": "1980-01-01",
    "date:inception_upper": "1980-01-01",
    "iso:country": "GB",
    "wof:name": "M6 5JA",
    "wof:placetype": "postalcode"
  },
  "geometry": {"coordinates":[-2.286704,53.488797],"type":"Point"}
}
