{
  "type": "Feature",
  "properties": {
    "iso:country":"GB",
    "wof:name":"WN3 6ND",
    "wof:placetype":"postalcode"
},
  "geometry": {"coordinates":[-2.66297136208375,53.51654221677725],"type":"Point"}
}