{
  "type": "Feature",
  "properties": {
    "date:inception_lower": "2007-03-01",
    "date:inception_upper": "2007-03-01",
    "iso:country": "GB",
    "wof:name": "WN3 6ND",
    "wof:placetype": "postalcode"
  },
  "geometry": {"coordinates":[-2.662971,53.516542],"type":"Point"}
}
