{
  "type": "Feature",
  "properties": {
    "iso:country":"GB",
    "wof:name":"ME16 0LD",
    "wof:placetype":"postalcode"
},
  "geometry": {"coordinates":[0.49673004383871,51.27410105721046],"type":"Point"}
}