{
  "type": "Feature",
  "properties": {
    "iso:country": "GB",
    "wof:name": "BA16 0GX",
    "wof:placetype": "postalcode"
  },
  "geometry": {"coordinates":[-2.757212,51.127451],"type":"Point"}
}
