{
  "type": "Feature",
  "properties": {
    "iso:country":"GB",
    "wof:name":"G63 9DN",
    "wof:placetype":"postalcode"
},
  "geometry": {"coordinates":[-4.30998191175274,55.98406863406567],"type":"Point"}
}