{
  "type": "Feature",
  "properties": {
    "iso:country":"GB",
    "wof:name":"BA14 6AQ",
    "wof:placetype":"postalcode"
},
  "geometry": {"coordinates":[-2.19061812273767,51.29305693791619],"type":"Point"}
}