{
  "type": "Feature",
  "properties": {
    "date:inception_lower": "1980-01-01",
    "date:inception_upper": "1980-01-01",
    "iso:country": "GB",
    "wof:name": "BA14 6AQ",
    "wof:placetype": "postalcode"
  },
  "geometry": {"coordinates":[-2.190618,51.293057],"type":"Point"}
}
