{
  "type": "Feature",
  "properties": {
    "iso:country":"GB",
    "wof:name":"AB37 9JQ",
    "wof:placetype":"postalcode"
},
  "geometry": {"coordinates":[-3.28648906056784,57.27533236059467],"type":"Point"}
}