{
  "type": "Feature",
  "properties": {
    "date:inception_lower":"1990-08-01",
    "date:inception_upper":"1990-08-31",
    "iso:country":"GB",
    "wof:name":"AB37 9JQ",
    "wof:placetype":"postalcode"
},
  "geometry": {"coordinates":[-3.286473,57.275337],"type":"Point"}
}