{
  "type": "Feature",
  "properties": {
    "iso:country":"GB",
    "wof:name":"ME2 3SP",
    "wof:placetype":"postalcode"
},
  "geometry": {"coordinates":[0.47656176112028,51.40177936741461],"type":"Point"}
}