{
  "type": "Feature",
  "properties": {
    "iso:country":"GB",
    "wof:name":"SW20 0JD",
    "wof:placetype":"postalcode"
},
  "geometry": {"coordinates":[-0.23141833034724,51.40762617442171],"type":"Point"}
}