{
  "type": "Feature",
  "properties": {
    "iso:country":"GB",
    "wof:name":"LL15 2UD",
    "wof:placetype":"postalcode"
},
  "geometry": {"coordinates":[-3.33140288155286,53.13214409078178],"type":"Point"}
}