{
  "type": "Feature",
  "properties": {
    "iso:country":"GB",
    "wof:name":"BA1 3BE",
    "wof:placetype":"postalcode"
},
  "geometry": {"coordinates":[-2.38092509065519,51.38620526059729],"type":"Point"}
}