{
  "type": "Feature",
  "properties": {
    "iso:country": "GB",
    "wof:name": "DN36 5XJ",
    "wof:placetype": "postalcode"
  },
  "geometry": {"coordinates":[0.05807,53.498708],"type":"Point"}
}
