{
  "type": "Feature",
  "properties": {
    "iso:country":"GB",
    "wof:name":"DN36 5XJ",
    "wof:placetype":"postalcode"
},
  "geometry": {"coordinates":[0.05806960823824,53.49870841160472],"type":"Point"}
}