{
  "type": "Feature",
  "properties": {
    "iso:country": "GB",
    "wof:name": "MK42 0ER",
    "wof:placetype": "postalcode"
  },
  "geometry": {"coordinates":[-0.45927,52.127958],"type":"Point"}
}
