{
  "type": "Feature",
  "properties": {
    "iso:country":"GB",
    "wof:name":"EC2A 4XY",
    "wof:placetype":"postalcode"
},
  "geometry": {"coordinates":[-0.08117829799228,51.52422612448415],"type":"Point"}
}