{
  "type": "Feature",
  "properties": {
    "date:inception_lower":"1998-12-01",
    "date:inception_upper":"1998-12-31",
    "iso:country":"GB",
    "wof:name":"EC2A 4XY",
    "wof:placetype":"postalcode"
},
  "geometry": {"coordinates":[-0.081178,51.524226],"type":"Point"}
}