{
  "type": "Feature",
  "properties": {
    "date:inception_lower": "2021-02-01",
    "date:inception_upper": "2021-02-01",
    "iso:country": "GB",
    "wof:name": "HP4 3FD",
    "wof:placetype": "postalcode"
  },
  "geometry": {"coordinates":[-0.592027,51.760383],"type":"Point"}
}
