{
  "type": "Feature",
  "properties": {
    "date:inception_lower": "1998-12-01",
    "date:inception_upper": "1998-12-01",
    "iso:country": "GB",
    "wof:name": "YO15 3TA",
    "wof:placetype": "postalcode"
  },
  "geometry": {"coordinates":[-0.21208,54.077417],"type":"Point"}
}
