{
  "type": "Feature",
  "properties": {
    "iso:country":"GB",
    "wof:name":"YO15 3TA",
    "wof:placetype":"postalcode"
},
  "geometry": {"coordinates":[-0.21208052391852,54.07741653443919],"type":"Point"}
}