{
  "type": "Feature",
  "properties": {
    "iso:country": "GB",
    "wof:name": "WS15 1EA",
    "wof:placetype": "postalcode"
  },
  "geometry": {"coordinates":[-1.930792,52.756161],"type":"Point"}
}
