{
  "type": "Feature",
  "properties": {
    "iso:country":"GB",
    "wof:name":"WS15 1EA",
    "wof:placetype":"postalcode"
},
  "geometry": {"coordinates":[-1.93079163365481,52.75616117628611],"type":"Point"}
}