{
  "type": "Feature",
  "properties": {
    "date:inception_lower": "1993-01-01",
    "date:inception_upper": "1993-01-01",
    "iso:country": "GB",
    "wof:name": "WS15 1EA",
    "wof:placetype": "postalcode"
  },
  "geometry": {"coordinates":[-1.930792,52.756161],"type":"Point"}
}
