{
  "type": "Feature",
  "properties": {
    "date:inception_lower": "2002-06-01",
    "date:inception_upper": "2002-06-01",
    "iso:country": "GB",
    "wof:name": "SA4 0UT",
    "wof:placetype": "postalcode"
  },
  "geometry": {"coordinates":[-4.051453,51.713532],"type":"Point"}
}
