{
  "type": "Feature",
  "properties": {
    "iso:country":"GB",
    "wof:name":"SA4 0UT",
    "wof:placetype":"postalcode"
},
  "geometry": {"coordinates":[-4.05145323586283,51.71353240222906],"type":"Point"}
}