{
  "type": "Feature",
  "properties": {
    "iso:country": "GB",
    "wof:name": "CV23 9DR",
    "wof:placetype": "postalcode"
  },
  "geometry": {"coordinates":[-1.293954,52.379109],"type":"Point"}
}
