{
  "type": "Feature",
  "properties": {
    "iso:country":"GB",
    "wof:name":"GL3 2JD",
    "wof:placetype":"postalcode"
},
  "geometry": {"coordinates":[-2.17193663860659,51.88623526865126],"type":"Point"}
}