{
  "type": "Feature",
  "properties": {
    "date:inception_lower":"1980-01-01",
    "date:inception_upper":"1980-01-31",
    "iso:country":"GB",
    "wof:name":"SE11 4NH",
    "wof:placetype":"postalcode"
},
  "geometry": {"coordinates":[-0.10696,51.492074],"type":"Point"}
}