{
  "type": "Feature",
  "properties": {
    "iso:country":"GB",
    "wof:name":"SE11 4NH",
    "wof:placetype":"postalcode"
},
  "geometry": {"coordinates":[-0.10696030523978,51.49207402748967],"type":"Point"}
}