{
  "type": "Feature",
  "properties": {
    "iso:country": "GB",
    "wof:name": "SE11 4NH",
    "wof:placetype": "postalcode"
  },
  "geometry": {"coordinates":[-0.10696,51.492074],"type":"Point"}
}
