{
  "type": "Feature",
  "properties": {
    "iso:country":"GB",
    "wof:name":"M24 4WG",
    "wof:placetype":"postalcode"
},
  "geometry": {"coordinates":[-2.22778944718966,53.55290432576014],"type":"Point"}
}