{
  "type": "Feature",
  "properties": {
    "iso:country":"GB",
    "wof:name":"HU17 9HT",
    "wof:placetype":"postalcode"
},
  "geometry": {"coordinates":[-0.42507997365146,53.84949962473175],"type":"Point"}
}