{
  "type": "Feature",
  "properties": {
    "iso:country":"GB",
    "wof:name":"B32 4HD",
    "wof:placetype":"postalcode"
},
  "geometry": {"coordinates":[-2.00523636718252,52.43349284660489],"type":"Point"}
}