{
  "type": "Feature",
  "properties": {
    "iso:country": "GB",
    "wof:name": "PO16 9HA",
    "wof:placetype": "postalcode"
  },
  "geometry": {"coordinates":[-1.130407,50.839451],"type":"Point"}
}
