{
  "type": "Feature",
  "properties": {
    "date:inception_lower": "2018-12-01",
    "date:inception_upper": "2018-12-01",
    "iso:country": "GB",
    "wof:name": "PR4 3FZ",
    "wof:placetype": "postalcode"
  },
  "geometry": {"coordinates":[-2.898136,53.794276],"type":"Point"}
}
