{
  "type": "Feature",
  "properties": {
    "iso:country":"GB",
    "wof:name":"CV23 9BD",
    "wof:placetype":"postalcode"
},
  "geometry": {"coordinates":[-1.30149713879768,52.38614787208034],"type":"Point"}
}