{
  "type": "Feature",
  "properties": {
    "iso:country": "GB",
    "wof:name": "CV23 9BD",
    "wof:placetype": "postalcode"
  },
  "geometry": {"coordinates":[-1.301497,52.386148],"type":"Point"}
}
