{
  "type": "Feature",
  "properties": {
    "date:inception_lower": "1980-01-01",
    "date:inception_upper": "1980-01-01",
    "iso:country": "GB",
    "wof:name": "TN12 7DU",
    "wof:placetype": "postalcode"
  },
  "geometry": {"coordinates":[0.379011,51.158522],"type":"Point"}
}
