{
  "type": "Feature",
  "properties": {
    "iso:country":"GB",
    "wof:name":"TN12 7DU",
    "wof:placetype":"postalcode"
},
  "geometry": {"coordinates":[0.37901125629966,51.15852172477842],"type":"Point"}
}