{
  "type": "Feature",
  "properties": {
    "iso:country": "GB",
    "wof:name": "EX1 3DQ",
    "wof:placetype": "postalcode"
  },
  "geometry": {"coordinates":[-3.472792,50.735571],"type":"Point"}
}
