{
  "type": "Feature",
  "properties": {
    "iso:country": "GB",
    "wof:name": "BD19 4BW",
    "wof:placetype": "postalcode"
  },
  "geometry": {"coordinates":[-1.710724,53.737687],"type":"Point"}
}
