{
  "type": "Feature",
  "properties": {
    "iso:country":"GB",
    "wof:name":"BD19 4BW",
    "wof:placetype":"postalcode"
},
  "geometry": {"coordinates":[-1.71072398583311,53.73768720367532],"type":"Point"}
}