{
  "type": "Feature",
  "properties": {
    "iso:country":"GB",
    "wof:name":"N9 9BE",
    "wof:placetype":"postalcode"
},
  "geometry": {"coordinates":[-0.06804717466839,51.62050920836061],"type":"Point"}
}