{
  "type": "Feature",
  "properties": {
    "iso:country":"GB",
    "wof:name":"BH8 9SU",
    "wof:placetype":"postalcode"
},
  "geometry": {"coordinates":[-1.85819272264065,50.75261437899621],"type":"Point"}
}