{
  "type": "Feature",
  "properties": {
    "date:inception_lower": "2003-03-01",
    "date:inception_upper": "2003-03-01",
    "iso:country": "GB",
    "wof:name": "BH8 9SU",
    "wof:placetype": "postalcode"
  },
  "geometry": {"coordinates":[-1.858185,50.752604],"type":"Point"}
}
