{
  "type": "Feature",
  "properties": {
    "iso:country":"GB",
    "wof:name":"PO33 1YL",
    "wof:placetype":"postalcode"
},
  "geometry": {"coordinates":[-1.12502357454886,50.6935022297312],"type":"Point"}
}