{
  "type": "Feature",
  "properties": {
    "iso:country":"GB",
    "wof:name":"NG5 6SD",
    "wof:placetype":"postalcode"
},
  "geometry": {"coordinates":[-1.10444512767197,52.99954163214215],"type":"Point"}
}