{
  "type": "Feature",
  "properties": {
    "date:inception_lower":"1991-08-01",
    "date:inception_upper":"1991-08-31",
    "iso:country":"GB",
    "wof:name":"AB51 0HF",
    "wof:placetype":"postalcode"
},
  "geometry": {"coordinates":[-2.41943,57.344779],"type":"Point"}
}