{
  "type": "Feature",
  "properties": {
    "date:inception_lower": "2004-09-01",
    "date:inception_upper": "2004-09-01",
    "iso:country": "GB",
    "wof:name": "SG13 8EB",
    "wof:placetype": "postalcode"
  },
  "geometry": {"coordinates":[-0.08045,51.793662],"type":"Point"}
}
