{
  "type": "Feature",
  "properties": {
    "iso:country": "GB",
    "wof:name": "SG13 8EB",
    "wof:placetype": "postalcode"
  },
  "geometry": {"coordinates":[-0.08045,51.793662],"type":"Point"}
}
