{
  "type": "Feature",
  "properties": {
    "iso:country":"GB",
    "wof:name":"SG13 8EB",
    "wof:placetype":"postalcode"
},
  "geometry": {"coordinates":[-0.08045014789113,51.7936617908737],"type":"Point"}
}