{
  "type": "Feature",
  "properties": {
    "iso:country": "GB",
    "wof:name": "NP4 9NE",
    "wof:placetype": "postalcode"
  },
  "geometry": {"coordinates":[-3.084394,51.773385],"type":"Point"}
}
