{
  "type": "Feature",
  "properties": {
    "iso:country":"GB",
    "wof:name":"NP4 9NE",
    "wof:placetype":"postalcode"
},
  "geometry": {"coordinates":[-3.08439440971049,51.77338531366368],"type":"Point"}
}