{
  "type": "Feature",
  "properties": {
    "iso:country":"GB",
    "wof:name":"KT1 2JN",
    "wof:placetype":"postalcode"
},
  "geometry": {"coordinates":[-0.3050754611909,51.40190727483211],"type":"Point"}
}