{
  "type": "Feature",
  "properties": {
    "iso:country": "GB",
    "wof:name": "KT1 2JN",
    "wof:placetype": "postalcode"
  },
  "geometry": {"coordinates":[-0.305053,51.401907],"type":"Point"}
}
