{
  "type": "Feature",
  "properties": {
    "iso:country": "GB",
    "wof:name": "ML8 4BF",
    "wof:placetype": "postalcode"
  },
  "geometry": {"coordinates":[-3.838932,55.733712],"type":"Point"}
}
