{
  "type": "Feature",
  "properties": {
    "date:inception_lower": "1980-01-01",
    "date:inception_upper": "1980-01-01",
    "iso:country": "GB",
    "wof:name": "YO7 4PS",
    "wof:placetype": "postalcode"
  },
  "geometry": {"coordinates":[-1.460895,54.197203],"type":"Point"}
}
