{
  "type": "Feature",
  "properties": {
    "iso:country":"GB",
    "wof:name":"YO7 4PS",
    "wof:placetype":"postalcode"
},
  "geometry": {"coordinates":[-1.46090036296237,54.19734243764156],"type":"Point"}
}