{
  "type": "Feature",
  "properties": {
    "iso:country":"GB",
    "wof:name":"NG7 1JG",
    "wof:placetype":"postalcode"
},
  "geometry": {"coordinates":[-1.16794221882824,52.9473065187517],"type":"Point"}
}