{
  "type": "Feature",
  "properties": {
    "iso:country": "GB",
    "wof:name": "HA8 8YP",
    "wof:placetype": "postalcode"
  },
  "geometry": {"coordinates":[-0.26479,51.623834],"type":"Point"}
}
