{
  "type": "Feature",
  "properties": {
    "iso:country":"GB",
    "wof:name":"CW9 5NQ",
    "wof:placetype":"postalcode"
},
  "geometry": {"coordinates":[-2.49681122673556,53.26396691467685],"type":"Point"}
}