{
  "type": "Feature",
  "properties": {
    "iso:country":"GB",
    "wof:name":"RH1 2BH",
    "wof:placetype":"postalcode"
},
  "geometry": {"coordinates":[-0.17826603671301,51.2470292791751],"type":"Point"}
}