{
  "type": "Feature",
  "properties": {
    "iso:country":"GB",
    "wof:name":"B92 7PB",
    "wof:placetype":"postalcode"
},
  "geometry": {"coordinates":[-1.79931798172938,52.44925348991806],"type":"Point"}
}