{
  "type": "Feature",
  "properties": {
    "iso:country":"GB",
    "wof:name":"GU22 9EA",
    "wof:placetype":"postalcode"
},
  "geometry": {"coordinates":[-0.55358652092802,51.30526120189153],"type":"Point"}
}