{
  "type": "Feature",
  "properties": {
    "iso:country": "GB",
    "wof:name": "GU22 9EA",
    "wof:placetype": "postalcode"
  },
  "geometry": {"coordinates":[-0.553586,51.305261],"type":"Point"}
}
