{
  "type": "Feature",
  "properties": {
    "date:inception_lower": "2020-11-01",
    "date:inception_upper": "2020-11-01",
    "iso:country": "GB",
    "wof:name": "ME17 3TU",
    "wof:placetype": "postalcode"
  },
  "geometry": {"coordinates":[0.591134,51.223851],"type":"Point"}
}
