{
  "type": "Feature",
  "properties": {
    "iso:country":"GB",
    "wof:name":"SW11 4NF",
    "wof:placetype":"postalcode"
},
  "geometry": {"coordinates":[-0.154448749508,51.47438732841291],"type":"Point"}
}