{
  "type": "Feature",
  "properties": {
    "iso:country":"GB",
    "wof:name":"ST4 2ER",
    "wof:placetype":"postalcode"
},
  "geometry": {"coordinates":[-2.17852594311082,53.01101151981464],"type":"Point"}
}