{
  "type": "Feature",
  "properties": {
    "iso:country": "GB",
    "wof:name": "S65 3HA",
    "wof:placetype": "postalcode"
  },
  "geometry": {"coordinates":[-1.318975,53.44218],"type":"Point"}
}
