{
  "type": "Feature",
  "properties": {
    "iso:country": "GB",
    "wof:name": "WF14 0PX",
    "wof:placetype": "postalcode"
  },
  "geometry": {"coordinates":[-1.682409,53.682734],"type":"Point"}
}
