{
  "type": "Feature",
  "properties": {
    "date:inception_lower": "2000-12-01",
    "date:inception_upper": "2000-12-01",
    "iso:country": "GB",
    "wof:name": "AL6 0BZ",
    "wof:placetype": "postalcode"
  },
  "geometry": {"coordinates":[-0.180205,51.815984],"type":"Point"}
}
