{
  "type": "Feature",
  "properties": {
    "iso:country": "GB",
    "wof:name": "TN3 0JP",
    "wof:placetype": "postalcode"
  },
  "geometry": {"coordinates":[0.204635,51.143692],"type":"Point"}
}
