{
  "type": "Feature",
  "properties": {
    "date:inception_lower":"2002-12-01",
    "date:inception_upper":"2002-12-31",
    "iso:country":"GB",
    "wof:name":"DD5 4HE",
    "wof:placetype":"postalcode"
},
  "geometry": {"coordinates":[-2.818537,56.487548],"type":"Point"}
}