{
  "type": "Feature",
  "properties": {
    "iso:country": "GB",
    "wof:name": "DD5 4HE",
    "wof:placetype": "postalcode"
  },
  "geometry": {"coordinates":[-2.818537,56.487548],"type":"Point"}
}
