{
  "type": "Feature",
  "properties": {
    "iso:country":"GB",
    "wof:name":"DD5 4HE",
    "wof:placetype":"postalcode"
},
  "geometry": {"coordinates":[-2.81853748048173,56.48754808612042],"type":"Point"}
}