{
  "type": "Feature",
  "properties": {
    "iso:country":"GB",
    "wof:name":"NG11 9NA",
    "wof:placetype":"postalcode"
},
  "geometry": {"coordinates":[-1.18134452814283,52.90113944552657],"type":"Point"}
}