{
  "type": "Feature",
  "properties": {
    "iso:country":"GB",
    "wof:name":"LE4 0HU",
    "wof:placetype":"postalcode"
},
  "geometry": {"coordinates":[-1.14423040027375,52.65575390313296],"type":"Point"}
}