{
  "type": "Feature",
  "properties": {
    "date:inception_lower": "1980-01-01",
    "date:inception_upper": "1980-01-01",
    "iso:country": "GB",
    "wof:name": "WN2 3JA",
    "wof:placetype": "postalcode"
  },
  "geometry": {"coordinates":[-2.582904,53.532968],"type":"Point"}
}
