{
  "type": "Feature",
  "properties": {
    "iso:country":"GB",
    "wof:name":"WN2 3JA",
    "wof:placetype":"postalcode"
},
  "geometry": {"coordinates":[-2.58290435928648,53.53296808827963],"type":"Point"}
}