{
  "type": "Feature",
  "properties": {
    "iso:country":"GB",
    "wof:name":"WA9 1NG",
    "wof:placetype":"postalcode"
},
  "geometry": {"coordinates":[-2.72153599360818,53.45463084239031],"type":"Point"}
}