{
  "type": "Feature",
  "properties": {
    "date:inception_lower": "1980-01-01",
    "date:inception_upper": "1980-01-01",
    "iso:country": "GB",
    "wof:name": "WA9 1NG",
    "wof:placetype": "postalcode"
  },
  "geometry": {"coordinates":[-2.721536,53.454631],"type":"Point"}
}
