{
  "type": "Feature",
  "properties": {
    "iso:country": "GB",
    "wof:name": "HU13 0FP",
    "wof:placetype": "postalcode"
  },
  "geometry": {"coordinates":[-0.462762,53.732252],"type":"Point"}
}
