{
  "type": "Feature",
  "properties": {
    "iso:country":"GB",
    "wof:name":"DY1 2AS",
    "wof:placetype":"postalcode"
},
  "geometry": {"coordinates":[-2.09524247945068,52.51024676430813],"type":"Point"}
}