{
  "type": "Feature",
  "properties": {
    "iso:country":"GB",
    "wof:name":"PA34 4JJ",
    "wof:placetype":"postalcode"
},
  "geometry": {"coordinates":[-5.47249497493352,56.40277956561164],"type":"Point"}
}