{
  "type": "Feature",
  "properties": {
    "iso:country":"GB",
    "wof:name":"HA0 1YU",
    "wof:placetype":"postalcode"
},
  "geometry": {"coordinates":[-0.30277306549969,51.5377669515135],"type":"Point"}
}