{
  "type": "Feature",
  "properties": {
    "iso:country": "GB",
    "wof:name": "DL12 9HA",
    "wof:placetype": "postalcode"
  },
  "geometry": {"coordinates":[-2.028942,54.59747],"type":"Point"}
}
