{
  "type": "Feature",
  "properties": {
    "date:inception_lower":"1980-01-01",
    "date:inception_upper":"1980-01-31",
    "iso:country":"GB",
    "wof:name":"DL12 9HA",
    "wof:placetype":"postalcode"
},
  "geometry": {"coordinates":[-2.028942,54.59747],"type":"Point"}
}