{
  "type": "Feature",
  "properties": {
    "date:inception_lower": "1980-01-01",
    "date:inception_upper": "1980-01-01",
    "iso:country": "GB",
    "wof:name": "TR26 2EW",
    "wof:placetype": "postalcode"
  },
  "geometry": {"coordinates":[-5.494694,50.207776],"type":"Point"}
}
