{
  "type": "Feature",
  "properties": {
    "iso:country":"GB",
    "wof:name":"TR26 2EW",
    "wof:placetype":"postalcode"
},
  "geometry": {"coordinates":[-5.49468381529388,50.20777408934109],"type":"Point"}
}