{
  "type": "Feature",
  "properties": {
    "iso:country":"GB",
    "wof:name":"HP12 3GW",
    "wof:placetype":"postalcode"
},
  "geometry": {"coordinates":[-0.76962536430959,51.63436333604529],"type":"Point"}
}