{
  "type": "Feature",
  "properties": {
    "iso:country":"GB",
    "wof:name":"EN5 3ES",
    "wof:placetype":"postalcode"
},
  "geometry": {"coordinates":[-0.22147119788468,51.65134934478772],"type":"Point"}
}