{
  "type": "Feature",
  "properties": {
    "iso:country": "GB",
    "wof:name": "PH2 8FB",
    "wof:placetype": "postalcode"
  },
  "geometry": {"coordinates":[-3.438636,56.394468],"type":"Point"}
}
