{
  "type": "Feature",
  "properties": {
    "iso:country":"GB",
    "wof:name":"NP12 0AH",
    "wof:placetype":"postalcode"
},
  "geometry": {"coordinates":[-3.19937479788903,51.68923104764619],"type":"Point"}
}