{
  "type": "Feature",
  "properties": {
    "iso:country": "GB",
    "wof:name": "NP12 0AH",
    "wof:placetype": "postalcode"
  },
  "geometry": {"coordinates":[-3.199375,51.689231],"type":"Point"}
}
