{
  "type": "Feature",
  "properties": {
    "iso:country":"GB",
    "wof:name":"B18 6EL",
    "wof:placetype":"postalcode"
},
  "geometry": {"coordinates":[-1.91008682045,52.49128259625188],"type":"Point"}
}