{
  "type": "Feature",
  "properties": {
    "iso:country":"GB",
    "wof:name":"B28 9NF",
    "wof:placetype":"postalcode"
},
  "geometry": {"coordinates":[-1.82982705709303,52.42442582616395],"type":"Point"}
}