{
  "type": "Feature",
  "properties": {
    "iso:country": "GB",
    "wof:name": "PO38 3DE",
    "wof:placetype": "postalcode"
  },
  "geometry": {"coordinates":[-1.218822,50.613196],"type":"Point"}
}
