{
  "type": "Feature",
  "properties": {
    "iso:country":"GB",
    "wof:name":"PO38 3DE",
    "wof:placetype":"postalcode"
},
  "geometry": {"coordinates":[-1.21882204252463,50.61319592342733],"type":"Point"}
}