{
  "type": "Feature",
  "properties": {
    "iso:country": "GB",
    "wof:name": "SO41 5QE",
    "wof:placetype": "postalcode"
  },
  "geometry": {"coordinates":[-1.540178,50.781543],"type":"Point"}
}
