{
  "type": "Feature",
  "properties": {
    "iso:country":"GB",
    "wof:name":"S8 0NG",
    "wof:placetype":"postalcode"
},
  "geometry": {"coordinates":[-1.48309778575877,53.34576277886449],"type":"Point"}
}