{
  "type": "Feature",
  "properties": {
    "iso:country":"GB",
    "wof:name":"RG20 0JE",
    "wof:placetype":"postalcode"
},
  "geometry": {"coordinates":[-1.39143505934769,51.40129671190023],"type":"Point"}
}