{
  "type": "Feature",
  "properties": {
    "iso:country": "GB",
    "wof:name": "RG20 0JE",
    "wof:placetype": "postalcode"
  },
  "geometry": {"coordinates":[-1.391418,51.401295],"type":"Point"}
}
