{
  "type": "Feature",
  "properties": {
    "iso:country":"GB",
    "wof:name":"RH8 0NZ",
    "wof:placetype":"postalcode"
},
  "geometry": {"coordinates":[-0.00756680494824,51.26430215194764],"type":"Point"}
}