{
  "type": "Feature",
  "properties": {
    "iso:country": "GB",
    "wof:name": "RH8 0NZ",
    "wof:placetype": "postalcode"
  },
  "geometry": {"coordinates":[-0.00754,51.2643],"type":"Point"}
}
