{
  "type": "Feature",
  "properties": {
    "iso:country": "GB",
    "wof:name": "S61 4NH",
    "wof:placetype": "postalcode"
  },
  "geometry": {"coordinates":[-1.371169,53.451563],"type":"Point"}
}
