{
  "type": "Feature",
  "properties": {
    "iso:country":"GB",
    "wof:name":"S61 4NH",
    "wof:placetype":"postalcode"
},
  "geometry": {"coordinates":[-1.3711674989974,53.45154425744671],"type":"Point"}
}