{
  "type": "Feature",
  "properties": {
    "date:inception_lower": "2016-03-01",
    "date:inception_upper": "2016-03-01",
    "iso:country": "GB",
    "wof:name": "CB7 5YH",
    "wof:placetype": "postalcode"
  },
  "geometry": {"coordinates":[0.271272,52.39821],"type":"Point"}
}
