{
  "type": "Feature",
  "properties": {
    "iso:country": "GB",
    "wof:name": "PO31 7PG",
    "wof:placetype": "postalcode"
  },
  "geometry": {"coordinates":[-1.294279,50.752462],"type":"Point"}
}
