{
  "type": "Feature",
  "properties": {
    "iso:country":"GB",
    "wof:name":"PO31 7PG",
    "wof:placetype":"postalcode"
},
  "geometry": {"coordinates":[-1.29443582357951,50.75214131066878],"type":"Point"}
}