{
  "type": "Feature",
  "properties": {
    "date:inception_lower": "1980-01-01",
    "date:inception_upper": "1980-01-01",
    "iso:country": "GB",
    "wof:name": "PO31 7PG",
    "wof:placetype": "postalcode"
  },
  "geometry": {"coordinates":[-1.294279,50.752462],"type":"Point"}
}
