{
  "type": "Feature",
  "properties": {
    "iso:country":"GB",
    "wof:name":"PL26 7PD",
    "wof:placetype":"postalcode"
},
  "geometry": {"coordinates":[-4.90019512574382,50.37402433280987],"type":"Point"}
}