{
  "type": "Feature",
  "properties": {
    "date:inception_lower":"1995-01-01",
    "date:inception_upper":"1995-01-31",
    "iso:country":"GB",
    "wof:name":"PL26 7PD",
    "wof:placetype":"postalcode"
},
  "geometry": {"coordinates":[-4.900195,50.374024],"type":"Point"}
}