{
  "type": "Feature",
  "properties": {
    "iso:country": "GB",
    "wof:name": "DY7 5DZ",
    "wof:placetype": "postalcode"
  },
  "geometry": {"coordinates":[-2.261766,52.512297],"type":"Point"}
}
