{
  "type": "Feature",
  "properties": {
    "iso:country":"GB",
    "wof:name":"SO45 1ZT",
    "wof:placetype":"postalcode"
},
  "geometry": {"coordinates":[-1.37267525166595,50.80695801381383],"type":"Point"}
}