{
  "type": "Feature",
  "properties": {
    "iso:country": "GB",
    "wof:name": "SO45 1ZT",
    "wof:placetype": "postalcode"
  },
  "geometry": {"coordinates":[-1.372675,50.806958],"type":"Point"}
}
