{
  "type": "Feature",
  "properties": {
    "iso:country":"GB",
    "wof:name":"PE4 5EH",
    "wof:placetype":"postalcode"
},
  "geometry": {"coordinates":[-0.28823948959937,52.6229976317174],"type":"Point"}
}