{
  "type": "Feature",
  "properties": {
    "date:inception_lower":"1991-09-01",
    "date:inception_upper":"1991-09-30",
    "iso:country":"GB",
    "wof:name":"PE4 5EH",
    "wof:placetype":"postalcode"
},
  "geometry": {"coordinates":[-0.288239,52.622998],"type":"Point"}
}