{
  "type": "Feature",
  "properties": {
    "iso:country": "GB",
    "wof:name": "PE4 5EH",
    "wof:placetype": "postalcode"
  },
  "geometry": {"coordinates":[-0.288239,52.622998],"type":"Point"}
}
