{
  "type": "Feature",
  "properties": {
    "iso:country":"GB",
    "wof:name":"RG30 3AX",
    "wof:placetype":"postalcode"
},
  "geometry": {"coordinates":[-1.00991083420472,51.44124503900108],"type":"Point"}
}