{
  "type": "Feature",
  "properties": {
    "date:inception_lower":"1988-03-01",
    "date:inception_upper":"1988-03-31",
    "iso:country":"GB",
    "wof:name":"NW1 4DQ",
    "wof:placetype":"postalcode"
},
  "geometry": {"coordinates":[-0.144389,51.531349],"type":"Point"}
}