{
  "type": "Feature",
  "properties": {
    "iso:country": "GB",
    "wof:name": "HP11 1JS",
    "wof:placetype": "postalcode"
  },
  "geometry": {"coordinates":[-0.70678,51.610642],"type":"Point"}
}
