{
  "type": "Feature",
  "properties": {
    "date:inception_lower": "1987-04-01",
    "date:inception_upper": "1987-04-01",
    "iso:country": "GB",
    "wof:name": "HP11 1JS",
    "wof:placetype": "postalcode"
  },
  "geometry": {"coordinates":[-0.70678,51.610642],"type":"Point"}
}
