{
  "type": "Feature",
  "properties": {
    "iso:country":"GB",
    "wof:name":"HP11 1JS",
    "wof:placetype":"postalcode"
},
  "geometry": {"coordinates":[-0.70677990534378,51.61064211142589],"type":"Point"}
}