{
  "type": "Feature",
  "properties": {
    "iso:country":"GB",
    "wof:name":"NP20 4FT",
    "wof:placetype":"postalcode"
},
  "geometry": {"coordinates":[-3.00575819233734,51.58111780142814],"type":"Point"}
}