{
  "type": "Feature",
  "properties": {
    "date:inception_lower": "1980-01-01",
    "date:inception_upper": "1980-01-01",
    "iso:country": "GB",
    "wof:name": "WS3 4AN",
    "wof:placetype": "postalcode"
  },
  "geometry": {"coordinates":[-1.979629,52.62627],"type":"Point"}
}
