{
  "type": "Feature",
  "properties": {
    "iso:country":"GB",
    "wof:name":"IV4 7ED",
    "wof:placetype":"postalcode"
},
  "geometry": {"coordinates":[-4.4662719827247,57.48213465226988],"type":"Point"}
}