{
  "type": "Feature",
  "properties": {
    "iso:country": "GB",
    "wof:name": "IV4 7ED",
    "wof:placetype": "postalcode"
  },
  "geometry": {"coordinates":[-4.465976,57.482194],"type":"Point"}
}
