{
  "type": "Feature",
  "properties": {
    "date:inception_lower": "2005-07-01",
    "date:inception_upper": "2005-07-01",
    "iso:country": "GB",
    "wof:name": "TW13 4GA",
    "wof:placetype": "postalcode"
  },
  "geometry": {"coordinates":[-0.41086,51.446643],"type":"Point"}
}
