{
  "type": "Feature",
  "properties": {
    "date:inception_lower":"1994-12-01",
    "date:inception_upper":"1994-12-31",
    "iso:country":"GB",
    "wof:name":"BB12 9NB",
    "wof:placetype":"postalcode"
},
  "geometry": {"coordinates":[-2.272097,53.849555],"type":"Point"}
}