{
  "type": "Feature",
  "properties": {
    "date:inception_lower":"1980-01-01",
    "date:inception_upper":"1980-01-31",
    "iso:country":"GB",
    "wof:name":"EX34 8AL",
    "wof:placetype":"postalcode"
},
  "geometry": {"coordinates":[-4.125601,51.208395],"type":"Point"}
}