{
  "type": "Feature",
  "properties": {
    "iso:country": "GB",
    "wof:name": "BR6 7NZ",
    "wof:placetype": "postalcode"
  },
  "geometry": {"coordinates":[0.103902,51.326221],"type":"Point"}
}
