{
  "type": "Feature",
  "properties": {
    "iso:country":"GB",
    "wof:name":"BR6 7NZ",
    "wof:placetype":"postalcode"
},
  "geometry": {"coordinates":[0.10439216814268,51.32626566127241],"type":"Point"}
}