{
  "type": "Feature",
  "properties": {
    "date:inception_lower": "1980-01-01",
    "date:inception_upper": "1980-01-01",
    "iso:country": "GB",
    "wof:name": "SK7 2QB",
    "wof:placetype": "postalcode"
  },
  "geometry": {"coordinates":[-2.165872,53.363215],"type":"Point"}
}
