{
  "type": "Feature",
  "properties": {
    "date:inception_lower": "1980-01-01",
    "date:inception_upper": "1980-01-01",
    "iso:country": "GB",
    "wof:name": "NP4 9HP",
    "wof:placetype": "postalcode"
  },
  "geometry": {"coordinates":[-3.072386,51.77123],"type":"Point"}
}
