{
  "type": "Feature",
  "properties": {
    "iso:country":"GB",
    "wof:name":"NP4 9HP",
    "wof:placetype":"postalcode"
},
  "geometry": {"coordinates":[-3.07238605674338,51.77122966411157],"type":"Point"}
}