{
  "type": "Feature",
  "properties": {
    "iso:country":"GB",
    "wof:name":"CF5 4TR",
    "wof:placetype":"postalcode"
},
  "geometry": {"coordinates":[-3.27025646123498,51.46907579741094],"type":"Point"}
}