{
  "type": "Feature",
  "properties": {
    "iso:country":"GB",
    "wof:name":"G66 2HX",
    "wof:placetype":"postalcode"
},
  "geometry": {"coordinates":[-4.14634737251884,55.94207400366396],"type":"Point"}
}