{
  "type": "Feature",
  "properties": {
    "iso:country": "GB",
    "wof:name": "RH15 0US",
    "wof:placetype": "postalcode"
  },
  "geometry": {"coordinates":[-0.098368,50.954017],"type":"Point"}
}
