{
  "type": "Feature",
  "properties": {
    "date:inception_lower":"2014-09-01",
    "date:inception_upper":"2014-09-30",
    "iso:country":"GB",
    "wof:name":"RH15 0US",
    "wof:placetype":"postalcode"
},
  "geometry": {"coordinates":[-0.094196,50.952636],"type":"Point"}
}