{
  "type": "Feature",
  "properties": {
    "date:inception_lower": "1980-01-01",
    "date:inception_upper": "1980-01-01",
    "iso:country": "GB",
    "wof:name": "LS23 6DP",
    "wof:placetype": "postalcode"
  },
  "geometry": {"coordinates":[-1.349203,53.904141],"type":"Point"}
}
