{
  "type": "Feature",
  "properties": {
    "iso:country": "GB",
    "wof:name": "YO62 6JD",
    "wof:placetype": "postalcode"
  },
  "geometry": {"coordinates":[-0.934005,54.265871],"type":"Point"}
}
