{
  "type": "Feature",
  "properties": {
    "iso:country":"GB",
    "wof:name":"YO62 6JD",
    "wof:placetype":"postalcode"
},
  "geometry": {"coordinates":[-0.93400544751463,54.26587079217833],"type":"Point"}
}