{
  "type": "Feature",
  "properties": {
    "date:inception_lower": "2022-04-01",
    "date:inception_upper": "2022-04-01",
    "iso:country": "GB",
    "wof:name": "ME17 4UZ",
    "wof:placetype": "postalcode"
  },
  "geometry": {"coordinates":[0.503638,51.233931],"type":"Point"}
}
