{
  "type": "Feature",
  "properties": {
    "iso:country":"GB",
    "wof:name":"SN6 6PF",
    "wof:placetype":"postalcode"
},
  "geometry": {"coordinates":[-1.92888713962838,51.64769938196681],"type":"Point"}
}