{
  "type": "Feature",
  "properties": {
    "date:inception_lower": "1980-01-01",
    "date:inception_upper": "1980-01-01",
    "iso:country": "GB",
    "wof:name": "SN6 6PF",
    "wof:placetype": "postalcode"
  },
  "geometry": {"coordinates":[-1.928887,51.647699],"type":"Point"}
}
