{
  "type": "Feature",
  "properties": {
    "iso:country":"GB",
    "wof:name":"S43 3AD",
    "wof:placetype":"postalcode"
},
  "geometry": {"coordinates":[-1.32335645980646,53.27417696411246],"type":"Point"}
}