{
  "type": "Feature",
  "properties": {
    "iso:country": "GB",
    "wof:name": "NR17 1YN",
    "wof:placetype": "postalcode"
  },
  "geometry": {"coordinates":[1.001599,52.50632],"type":"Point"}
}
