{
  "type": "Feature",
  "properties": {
    "iso:country": "GB",
    "wof:name": "NG14 7WQ",
    "wof:placetype": "postalcode"
  },
  "geometry": {"coordinates":[-0.996521,53.007786],"type":"Point"}
}
