{
  "type": "Feature",
  "properties": {
    "iso:country":"GB",
    "wof:name":"CA3 8XB",
    "wof:placetype":"postalcode"
},
  "geometry": {"coordinates":[-2.93635291056738,54.8978872472596],"type":"Point"}
}