{
  "type": "Feature",
  "properties": {
    "iso:country": "GB",
    "wof:name": "HP18 0EF",
    "wof:placetype": "postalcode"
  },
  "geometry": {"coordinates":[-0.91988,51.807714],"type":"Point"}
}
