{
  "type": "Feature",
  "properties": {
    "iso:country":"GB",
    "wof:name":"HP18 0EF",
    "wof:placetype":"postalcode"
},
  "geometry": {"coordinates":[-0.91988027875739,51.80771371283583],"type":"Point"}
}