{
  "type": "Feature",
  "properties": {
    "date:inception_lower": "1980-01-01",
    "date:inception_upper": "1980-01-01",
    "iso:country": "GB",
    "wof:name": "HP18 0EF",
    "wof:placetype": "postalcode"
  },
  "geometry": {"coordinates":[-0.91988,51.807714],"type":"Point"}
}
