{
  "type": "Feature",
  "properties": {
    "iso:country": "GB",
    "wof:name": "NW6 7SE",
    "wof:placetype": "postalcode"
  },
  "geometry": {"coordinates":[-0.205259,51.540929],"type":"Point"}
}
