{
  "type": "Feature",
  "properties": {
    "iso:country":"GB",
    "wof:name":"NW6 7SE",
    "wof:placetype":"postalcode"
},
  "geometry": {"coordinates":[-0.20525882121072,51.54092878853503],"type":"Point"}
}