{
  "type": "Feature",
  "properties": {
    "date:inception_lower":"1980-01-01",
    "date:inception_upper":"1980-01-31",
    "iso:country":"GB",
    "wof:name":"BB11 4BG",
    "wof:placetype":"postalcode"
},
  "geometry": {"coordinates":[-2.264734,53.78839],"type":"Point"}
}