{
  "type": "Feature",
  "properties": {
    "iso:country":"GB",
    "wof:name":"BB11 4BG",
    "wof:placetype":"postalcode"
},
  "geometry": {"coordinates":[-2.26473373479309,53.78839029754945],"type":"Point"}
}