{
  "type": "Feature",
  "properties": {
    "iso:country":"GB",
    "wof:name":"DE11 7DH",
    "wof:placetype":"postalcode"
},
  "geometry": {"coordinates":[-1.52677400477311,52.76435385416082],"type":"Point"}
}