{
  "type": "Feature",
  "properties": {
    "date:inception_lower": "1980-01-01",
    "date:inception_upper": "1980-01-01",
    "iso:country": "GB",
    "wof:name": "NN5 7HW",
    "wof:placetype": "postalcode"
  },
  "geometry": {"coordinates":[-0.920124,52.250228],"type":"Point"}
}
