{
  "type": "Feature",
  "properties": {
    "date:inception_lower": "1980-01-01",
    "date:inception_upper": "1980-01-01",
    "iso:country": "GB",
    "wof:name": "SN12 7HU",
    "wof:placetype": "postalcode"
  },
  "geometry": {"coordinates":[-2.125717,51.374502],"type":"Point"}
}
