{
  "type": "Feature",
  "properties": {
    "date:inception_lower": "1989-07-01",
    "date:inception_upper": "1989-07-01",
    "iso:country": "GB",
    "wof:name": "G72 7JT",
    "wof:placetype": "postalcode"
  },
  "geometry": {"coordinates":[-4.165293,55.823821],"type":"Point"}
}
