{
  "type": "Feature",
  "properties": {
    "iso:country": "GB",
    "wof:name": "G72 7JT",
    "wof:placetype": "postalcode"
  },
  "geometry": {"coordinates":[-4.165293,55.823821],"type":"Point"}
}
