{
  "type": "Feature",
  "properties": {
    "iso:country":"GB",
    "wof:name":"NE66 3QQ",
    "wof:placetype":"postalcode"
},
  "geometry": {"coordinates":[-1.63287850179069,55.39298051578335],"type":"Point"}
}