{
  "type": "Feature",
  "properties": {
    "iso:country": "GB",
    "wof:name": "PO15 6RT",
    "wof:placetype": "postalcode"
  },
  "geometry": {"coordinates":[-1.224662,50.875753],"type":"Point"}
}
