{
  "type": "Feature",
  "properties": {
    "date:inception_lower": "2006-01-01",
    "date:inception_upper": "2006-01-01",
    "iso:country": "GB",
    "wof:name": "GL1 1RB",
    "wof:placetype": "postalcode"
  },
  "geometry": {"coordinates":[-2.241477,51.862521],"type":"Point"}
}
