{
  "type": "Feature",
  "properties": {
    "iso:country":"GB",
    "wof:name":"GL1 1RB",
    "wof:placetype":"postalcode"
},
  "geometry": {"coordinates":[-2.24147752883467,51.86252082696262],"type":"Point"}
}