{
  "type": "Feature",
  "properties": {
    "iso:country":"GB",
    "wof:name":"SG13 7PT",
    "wof:placetype":"postalcode"
},
  "geometry": {"coordinates":[-0.0414232267599,51.78102240627239],"type":"Point"}
}