{
  "type": "Feature",
  "properties": {
    "iso:country": "GB",
    "wof:name": "M15 6PU",
    "wof:placetype": "postalcode"
  },
  "geometry": {"coordinates":[-2.238555,53.467763],"type":"Point"}
}
