{
  "type": "Feature",
  "properties": {
    "date:inception_lower": "1980-01-01",
    "date:inception_upper": "1980-01-01",
    "iso:country": "GB",
    "wof:name": "TS19 8ED",
    "wof:placetype": "postalcode"
  },
  "geometry": {"coordinates":[-1.347674,54.587515],"type":"Point"}
}
