{
  "type": "Feature",
  "properties": {
    "iso:country":"GB",
    "wof:name":"PA31 8JW",
    "wof:placetype":"postalcode"
},
  "geometry": {"coordinates":[-5.4286565682852,56.03472451773857],"type":"Point"}
}