{
  "type": "Feature",
  "properties": {
    "date:inception_lower": "1980-01-01",
    "date:inception_upper": "1980-01-01",
    "iso:country": "GB",
    "wof:name": "PA31 8JW",
    "wof:placetype": "postalcode"
  },
  "geometry": {"coordinates":[-5.428657,56.034725],"type":"Point"}
}
