{
  "type": "Feature",
  "properties": {
    "iso:country": "GB",
    "wof:name": "PA31 8JW",
    "wof:placetype": "postalcode"
  },
  "geometry": {"coordinates":[-5.428657,56.034725],"type":"Point"}
}
