{
  "type": "Feature",
  "properties": {
    "iso:country":"GB",
    "wof:name":"PE14 0AJ",
    "wof:placetype":"postalcode"
},
  "geometry": {"coordinates":[0.17351667348125,52.63524131610554],"type":"Point"}
}