{
  "type": "Feature",
  "properties": {
    "iso:country": "GB",
    "wof:name": "GL17 0HD",
    "wof:placetype": "postalcode"
  },
  "geometry": {"coordinates":[-2.490407,51.839563],"type":"Point"}
}
