{
  "type": "Feature",
  "properties": {
    "iso:country":"GB",
    "wof:name":"GL17 0HD",
    "wof:placetype":"postalcode"
},
  "geometry": {"coordinates":[-2.49021137743876,51.84033927198985],"type":"Point"}
}