{
  "type": "Feature",
  "properties": {
    "iso:country": "GB",
    "wof:name": "CF43 4BG",
    "wof:placetype": "postalcode"
  },
  "geometry": {"coordinates":[-3.482965,51.673503],"type":"Point"}
}
