{
  "type": "Feature",
  "properties": {
    "iso:country":"GB",
    "wof:name":"CF43 4BG",
    "wof:placetype":"postalcode"
},
  "geometry": {"coordinates":[-3.48296482214579,51.67350266010555],"type":"Point"}
}