{
  "type": "Feature",
  "properties": {
    "date:inception_lower": "1980-01-01",
    "date:inception_upper": "1980-01-01",
    "iso:country": "GB",
    "wof:name": "CF43 4BG",
    "wof:placetype": "postalcode"
  },
  "geometry": {"coordinates":[-3.482965,51.673503],"type":"Point"}
}
