{
  "type": "Feature",
  "properties": {
    "iso:country": "GB",
    "wof:name": "SG7 6BF",
    "wof:placetype": "postalcode"
  },
  "geometry": {"coordinates":[-0.188931,51.988592],"type":"Point"}
}
