{
  "type": "Feature",
  "properties": {
    "iso:country":"GB",
    "wof:name":"DD6 8BS",
    "wof:placetype":"postalcode"
},
  "geometry": {"coordinates":[-2.94243872721664,56.43957283987709],"type":"Point"}
}