{
  "type": "Feature",
  "properties": {
    "date:inception_lower":"1984-09-01",
    "date:inception_upper":"1984-09-30",
    "iso:country":"GB",
    "wof:name":"DD6 8BS",
    "wof:placetype":"postalcode"
},
  "geometry": {"coordinates":[-2.942439,56.439573],"type":"Point"}
}