{
  "type": "Feature",
  "properties": {
    "iso:country": "GB",
    "wof:name": "DD6 8BS",
    "wof:placetype": "postalcode"
  },
  "geometry": {"coordinates":[-2.942439,56.439573],"type":"Point"}
}
