{
  "type": "Feature",
  "properties": {
    "date:inception_lower": "2012-02-01",
    "date:inception_upper": "2012-02-01",
    "iso:country": "GB",
    "wof:name": "IP30 0AT",
    "wof:placetype": "postalcode"
  },
  "geometry": {"coordinates":[0.837291,52.148115],"type":"Point"}
}
