{
  "type": "Feature",
  "properties": {
    "iso:country":"GB",
    "wof:name":"IP30 0AT",
    "wof:placetype":"postalcode"
},
  "geometry": {"coordinates":[0.83740349635878,52.14807810699267],"type":"Point"}
}