{
  "type": "Feature",
  "properties": {
    "iso:country":"GB",
    "wof:name":"S6 3FG",
    "wof:placetype":"postalcode"
},
  "geometry": {"coordinates":[-1.49215961350294,53.38586434350923],"type":"Point"}
}