{
  "type": "Feature",
  "properties": {
    "iso:country":"GB",
    "wof:name":"SE2 0SY",
    "wof:placetype":"postalcode"
},
  "geometry": {"coordinates":[0.1130943236509,51.48603075924447],"type":"Point"}
}