{
  "type": "Feature",
  "properties": {
    "iso:country": "GB",
    "wof:name": "CO4 0JH",
    "wof:placetype": "postalcode"
  },
  "geometry": {"coordinates":[0.934155,51.904818],"type":"Point"}
}
