{
  "type": "Feature",
  "properties": {
    "iso:country":"GB",
    "wof:name":"CO4 0JH",
    "wof:placetype":"postalcode"
},
  "geometry": {"coordinates":[0.93415497948486,51.90481800125832],"type":"Point"}
}