{
  "type": "Feature",
  "properties": {
    "iso:country":"GB",
    "wof:name":"FY5 3DB",
    "wof:placetype":"postalcode"
},
  "geometry": {"coordinates":[-3.02220294833424,53.86366409284067],"type":"Point"}
}