{
  "type": "Feature",
  "properties": {
    "iso:country":"GB",
    "wof:name":"SE11 5AW",
    "wof:placetype":"postalcode"
},
  "geometry": {"coordinates":[-0.12220637309285,51.48704052090543],"type":"Point"}
}