{
  "type": "Feature",
  "properties": {
    "iso:country":"GB",
    "wof:name":"GU5 9HN",
    "wof:placetype":"postalcode"
},
  "geometry": {"coordinates":[-0.46472461363439,51.21754989090891],"type":"Point"}
}