{
  "type": "Feature",
  "properties": {
    "date:inception_lower":"1980-01-01",
    "date:inception_upper":"1980-01-31",
    "iso:country":"GB",
    "wof:name":"GU5 9HN",
    "wof:placetype":"postalcode"
},
  "geometry": {"coordinates":[-0.464725,51.21755],"type":"Point"}
}