{
  "type": "Feature",
  "properties": {
    "iso:country": "GB",
    "wof:name": "GU5 9HN",
    "wof:placetype": "postalcode"
  },
  "geometry": {"coordinates":[-0.464725,51.21755],"type":"Point"}
}
