{
  "type": "Feature",
  "properties": {
    "date:inception_lower":"1980-01-01",
    "date:inception_upper":"1980-01-31",
    "iso:country":"GB",
    "wof:name":"IP20 0DB",
    "wof:placetype":"postalcode"
},
  "geometry": {"coordinates":[1.335718,52.435869],"type":"Point"}
}