{
  "type": "Feature",
  "properties": {
    "iso:country": "GB",
    "wof:name": "IP20 0DB",
    "wof:placetype": "postalcode"
  },
  "geometry": {"coordinates":[1.335718,52.435869],"type":"Point"}
}
