{
  "type": "Feature",
  "properties": {
    "iso:country":"GB",
    "wof:name":"BS32 0BT",
    "wof:placetype":"postalcode"
},
  "geometry": {"coordinates":[-2.55195804830147,51.54323699214426],"type":"Point"}
}