{
  "type": "Feature",
  "properties": {
    "date:inception_lower": "1995-01-01",
    "date:inception_upper": "1995-01-01",
    "iso:country": "GB",
    "wof:name": "PR2 9ZD",
    "wof:placetype": "postalcode"
  },
  "geometry": {"coordinates":[-2.689318,53.797414],"type":"Point"}
}
