{
  "type": "Feature",
  "properties": {
    "iso:country":"GB",
    "wof:name":"PR2 9ZD",
    "wof:placetype":"postalcode"
},
  "geometry": {"coordinates":[-2.6893175779459,53.79741428003747],"type":"Point"}
}