{
  "type": "Feature",
  "properties": {
    "date:inception_lower":"2005-10-01",
    "date:inception_upper":"2005-10-31",
    "iso:country":"GB",
    "wof:name":"DL1 4JQ",
    "wof:placetype":"postalcode"
},
  "geometry": {"coordinates":[-1.543141,54.514526],"type":"Point"}
}