{
  "type": "Feature",
  "properties": {
    "iso:country":"GB",
    "wof:name":"DL1 4JQ",
    "wof:placetype":"postalcode"
},
  "geometry": {"coordinates":[-1.54314150546447,54.51452616319985],"type":"Point"}
}