{
  "type": "Feature",
  "properties": {
    "date:inception_lower": "2021-01-01",
    "date:inception_upper": "2021-01-01",
    "iso:country": "GB",
    "wof:name": "CB7 7AA",
    "wof:placetype": "postalcode"
  },
  "geometry": {"coordinates":[0.408554,52.336979],"type":"Point"}
}
