{
  "type": "Feature",
  "properties": {
    "iso:country":"GB",
    "wof:name":"HU5 5YW",
    "wof:placetype":"postalcode"
},
  "geometry": {"coordinates":[-0.41132106883038,53.74869543457199],"type":"Point"}
}