{
  "type": "Feature",
  "properties": {
    "iso:country": "GB",
    "wof:name": "HU5 5YW",
    "wof:placetype": "postalcode"
  },
  "geometry": {"coordinates":[-0.411321,53.748695],"type":"Point"}
}
