{
  "type": "Feature",
  "properties": {
    "iso:country":"GB",
    "wof:name":"HR9 5LS",
    "wof:placetype":"postalcode"
},
  "geometry": {"coordinates":[-2.57449490338943,51.91528415740578],"type":"Point"}
}