{
  "type": "Feature",
  "properties": {
    "iso:country": "GB",
    "wof:name": "HR9 5LS",
    "wof:placetype": "postalcode"
  },
  "geometry": {"coordinates":[-2.57451,51.915292],"type":"Point"}
}
