{
  "type": "Feature",
  "properties": {
    "date:inception_lower": "1981-06-01",
    "date:inception_upper": "1981-06-01",
    "iso:country": "GB",
    "wof:name": "RH10 6EA",
    "wof:placetype": "postalcode"
  },
  "geometry": {"coordinates":[-0.166777,51.107747],"type":"Point"}
}
