{
  "type": "Feature",
  "properties": {
    "iso:country": "GB",
    "wof:name": "RH10 6EA",
    "wof:placetype": "postalcode"
  },
  "geometry": {"coordinates":[-0.166777,51.107747],"type":"Point"}
}
