{
  "type": "Feature",
  "properties": {
    "iso:country":"GB",
    "wof:name":"CR0 6RN",
    "wof:placetype":"postalcode"
},
  "geometry": {"coordinates":[-0.07173197459406,51.38257156743682],"type":"Point"}
}