{
  "type": "Feature",
  "properties": {
    "iso:country":"GB",
    "wof:name":"IP4 5AR",
    "wof:placetype":"postalcode"
},
  "geometry": {"coordinates":[1.18074794758038,52.05508333923623],"type":"Point"}
}