{
  "type": "Feature",
  "properties": {
    "date:inception_lower":"2009-10-01",
    "date:inception_upper":"2009-10-31",
    "iso:country":"GB",
    "wof:name":"PO21 3FE",
    "wof:placetype":"postalcode"
},
  "geometry": {"coordinates":[-0.722818,50.786754],"type":"Point"}
}