{
  "type": "Feature",
  "properties": {
    "iso:country": "GB",
    "wof:name": "WS13 7TH",
    "wof:placetype": "postalcode"
  },
  "geometry": {"coordinates":[-1.822593,52.700843],"type":"Point"}
}
