{
  "type": "Feature",
  "properties": {
    "iso:country":"GB",
    "wof:name":"PO6 4NY",
    "wof:placetype":"postalcode"
},
  "geometry": {"coordinates":[-1.11718780046973,50.85134778259849],"type":"Point"}
}