{
  "type": "Feature",
  "properties": {
    "date:inception_lower":"1990-07-01",
    "date:inception_upper":"1990-07-31",
    "iso:country":"GB",
    "wof:name":"CV35 8QB",
    "wof:placetype":"postalcode"
},
  "geometry": {"coordinates":[-1.720494,52.280237],"type":"Point"}
}