{
  "type": "Feature",
  "properties": {
    "iso:country": "GB",
    "wof:name": "CV35 8QB",
    "wof:placetype": "postalcode"
  },
  "geometry": {"coordinates":[-1.720494,52.280237],"type":"Point"}
}
