{
  "type": "Feature",
  "properties": {
    "date:inception_lower": "1990-07-01",
    "date:inception_upper": "1990-07-01",
    "iso:country": "GB",
    "wof:name": "CV35 8QB",
    "wof:placetype": "postalcode"
  },
  "geometry": {"coordinates":[-1.720346,52.280417],"type":"Point"}
}
