{
  "type": "Feature",
  "properties": {
    "date:inception_lower": "1983-07-01",
    "date:inception_upper": "1983-07-01",
    "iso:country": "GB",
    "wof:name": "CV22 6SE",
    "wof:placetype": "postalcode"
  },
  "geometry": {"coordinates":[-1.279206,52.363664],"type":"Point"}
}
