{
  "type": "Feature",
  "properties": {
    "date:inception_lower": "1980-01-01",
    "date:inception_upper": "1980-01-01",
    "iso:country": "GB",
    "wof:name": "WF6 1QH",
    "wof:placetype": "postalcode"
  },
  "geometry": {"coordinates":[-1.404736,53.701864],"type":"Point"}
}
