{
  "type": "Feature",
  "properties": {
    "iso:country":"GB",
    "wof:name":"WN5 9HZ",
    "wof:placetype":"postalcode"
},
  "geometry": {"coordinates":[-2.66809766125386,53.53274698529817],"type":"Point"}
}