{
  "type": "Feature",
  "properties": {
    "iso:country":"GB",
    "wof:name":"FK1 4HT",
    "wof:placetype":"postalcode"
},
  "geometry": {"coordinates":[-3.82385352006588,56.00390399773959],"type":"Point"}
}