{
  "type": "Feature",
  "properties": {
    "date:inception_lower":"1990-02-01",
    "date:inception_upper":"1990-02-28",
    "iso:country":"GB",
    "wof:name":"LD7 1HW",
    "wof:placetype":"postalcode"
},
  "geometry": {"coordinates":[-3.038625,52.341165],"type":"Point"}
}