{
  "type": "Feature",
  "properties": {
    "iso:country": "GB",
    "wof:name": "LD7 1HW",
    "wof:placetype": "postalcode"
  },
  "geometry": {"coordinates":[-3.038625,52.341165],"type":"Point"}
}
