{
  "type": "Feature",
  "properties": {
    "iso:country":"GB",
    "wof:name":"LD7 1HW",
    "wof:placetype":"postalcode"
},
  "geometry": {"coordinates":[-3.0386249783302,52.34116455214645],"type":"Point"}
}