{
  "type": "Feature",
  "properties": {
    "iso:country":"GB",
    "wof:name":"HA5 4PE",
    "wof:placetype":"postalcode"
},
  "geometry": {"coordinates":[-0.37434841604207,51.6110595958059],"type":"Point"}
}