{
  "type": "Feature",
  "properties": {
    "date:inception_lower": "2020-01-01",
    "date:inception_upper": "2020-01-01",
    "iso:country": "GB",
    "wof:name": "LE16 7EA",
    "wof:placetype": "postalcode"
  },
  "geometry": {"coordinates":[-0.942712,52.488491],"type":"Point"}
}
