{
  "type": "Feature",
  "properties": {
    "iso:country": "GB",
    "wof:name": "LE16 7EA",
    "wof:placetype": "postalcode"
  },
  "geometry": {"coordinates":[-0.94133,52.48962],"type":"Point"}
}
