{
  "type": "Feature",
  "properties": {
    "date:inception_lower": "1980-01-01",
    "date:inception_upper": "1980-01-01",
    "iso:country": "GB",
    "wof:name": "GL19 4PW",
    "wof:placetype": "postalcode"
  },
  "geometry": {"coordinates":[-2.297107,51.990342],"type":"Point"}
}
