{
  "type": "Feature",
  "properties": {
    "iso:country": "GB",
    "wof:name": "MK11 2AB",
    "wof:placetype": "postalcode"
  },
  "geometry": {"coordinates":[-0.837597,52.049747],"type":"Point"}
}
