{
  "type": "Feature",
  "properties": {
    "date:inception_lower": "2012-08-01",
    "date:inception_upper": "2012-08-01",
    "iso:country": "GB",
    "wof:name": "PA2 7AJ",
    "wof:placetype": "postalcode"
  },
  "geometry": {"coordinates":[-4.397551,55.829887],"type":"Point"}
}
