{
  "type": "Feature",
  "properties": {
    "iso:country":"GB",
    "wof:name":"PA2 7AJ",
    "wof:placetype":"postalcode"
},
  "geometry": {"coordinates":[-4.39751800068299,55.82988358374859],"type":"Point"}
}