{
  "type": "Feature",
  "properties": {
    "iso:country": "GB",
    "wof:name": "PA2 7AJ",
    "wof:placetype": "postalcode"
  },
  "geometry": {"coordinates":[-4.397551,55.829887],"type":"Point"}
}
