{
  "type": "Feature",
  "properties": {
    "iso:country":"GB",
    "wof:name":"GU1 4RH",
    "wof:placetype":"postalcode"
},
  "geometry": {"coordinates":[-0.57594763724698,51.24186894801642],"type":"Point"}
}