{
  "type": "Feature",
  "properties": {
    "iso:country": "GB",
    "wof:name": "GU1 4RH",
    "wof:placetype": "postalcode"
  },
  "geometry": {"coordinates":[-0.575948,51.241869],"type":"Point"}
}
