{
  "type": "Feature",
  "properties": {
    "iso:country":"GB",
    "wof:name":"M12 5SW",
    "wof:placetype":"postalcode"
},
  "geometry": {"coordinates":[-2.19075607689735,53.45052820894214],"type":"Point"}
}