{
  "type": "Feature",
  "properties": {
    "iso:country":"GB",
    "wof:name":"ME18 6AJ",
    "wof:placetype":"postalcode"
},
  "geometry": {"coordinates":[0.42515959731071,51.24099879124648],"type":"Point"}
}