{
  "type": "Feature",
  "properties": {
    "iso:country": "GB",
    "wof:name": "ME18 6AJ",
    "wof:placetype": "postalcode"
  },
  "geometry": {"coordinates":[0.42516,51.240999],"type":"Point"}
}
