{
  "type": "Feature",
  "properties": {
    "iso:country":"GB",
    "wof:name":"SY4 3JJ",
    "wof:placetype":"postalcode"
},
  "geometry": {"coordinates":[-2.72136663853199,52.81391153875397],"type":"Point"}
}