{
  "type": "Feature",
  "properties": {
    "iso:country":"GB",
    "wof:name":"IP8 4PB",
    "wof:placetype":"postalcode"
},
  "geometry": {"coordinates":[1.04439989575562,52.09650585671741],"type":"Point"}
}