{
  "type": "Feature",
  "properties": {
    "iso:country": "GB",
    "wof:name": "DN15 7RU",
    "wof:placetype": "postalcode"
  },
  "geometry": {"coordinates":[-0.661981,53.595664],"type":"Point"}
}
