{
  "type": "Feature",
  "properties": {
    "iso:country":"GB",
    "wof:name":"DN15 7RU",
    "wof:placetype":"postalcode"
},
  "geometry": {"coordinates":[-0.66198070244375,53.59566378750679],"type":"Point"}
}