{
  "type": "Feature",
  "properties": {
    "iso:country":"GB",
    "wof:name":"NN18 0JB",
    "wof:placetype":"postalcode"
},
  "geometry": {"coordinates":[-0.72389716083509,52.48296320530186],"type":"Point"}
}