{
  "type": "Feature",
  "properties": {
    "date:inception_lower": "1980-01-01",
    "date:inception_upper": "1980-01-01",
    "iso:country": "GB",
    "wof:name": "NN18 0JB",
    "wof:placetype": "postalcode"
  },
  "geometry": {"coordinates":[-0.723897,52.482963],"type":"Point"}
}
