{
  "type": "Feature",
  "properties": {
    "iso:country":"GB",
    "wof:name":"WA10 1TP",
    "wof:placetype":"postalcode"
},
  "geometry": {"coordinates":[-2.73684219928473,53.4584474719444],"type":"Point"}
}