{
  "type": "Feature",
  "properties": {
    "iso:country":"GB",
    "wof:name":"W1G 9RJ",
    "wof:placetype":"postalcode"
},
  "geometry": {"coordinates":[-0.1478894837805,51.5168634960795],"type":"Point"}
}