{
  "type": "Feature",
  "properties": {
    "date:inception_lower": "1980-01-01",
    "date:inception_upper": "1980-01-01",
    "iso:country": "GB",
    "wof:name": "BL6 5JZ",
    "wof:placetype": "postalcode"
  },
  "geometry": {"coordinates":[-2.591412,53.601032],"type":"Point"}
}
