{
  "type": "Feature",
  "properties": {
    "iso:country":"GB",
    "wof:name":"BL6 5JZ",
    "wof:placetype":"postalcode"
},
  "geometry": {"coordinates":[-2.59141218719172,53.60103174186512],"type":"Point"}
}