{
  "type": "Feature",
  "properties": {
    "iso:country": "GB",
    "wof:name": "NR4 6EF",
    "wof:placetype": "postalcode"
  },
  "geometry": {"coordinates":[1.288094,52.606968],"type":"Point"}
}
