{
  "type": "Feature",
  "properties": {
    "iso:country": "GB",
    "wof:name": "SW3 2AD",
    "wof:placetype": "postalcode"
  },
  "geometry": {"coordinates":[-0.169324,51.498109],"type":"Point"}
}
