{
  "type": "Feature",
  "properties": {
    "iso:country":"GB",
    "wof:name":"TW9 2HR",
    "wof:placetype":"postalcode"
},
  "geometry": {"coordinates":[-0.29074069635557,51.46939424479179],"type":"Point"}
}