{
  "type": "Feature",
  "properties": {
    "date:inception_lower":"1998-12-01",
    "date:inception_upper":"1998-12-31",
    "iso:country":"GB",
    "wof:name":"DY1 2GX",
    "wof:placetype":"postalcode"
},
  "geometry": {"coordinates":[-2.10383,52.517779],"type":"Point"}
}