{
  "type": "Feature",
  "properties": {
    "date:inception_lower": "1980-01-01",
    "date:inception_upper": "1980-01-01",
    "iso:country": "GB",
    "wof:name": "PE3 6LY",
    "wof:placetype": "postalcode"
  },
  "geometry": {"coordinates":[-0.287577,52.572604],"type":"Point"}
}
