{
  "type": "Feature",
  "properties": {
    "iso:country":"GB",
    "wof:name":"PE3 6LY",
    "wof:placetype":"postalcode"
},
  "geometry": {"coordinates":[-0.28750829379721,52.57244962495419],"type":"Point"}
}