{
  "type": "Feature",
  "properties": {
    "iso:country":"GB",
    "wof:name":"YO19 5SH",
    "wof:placetype":"postalcode"
},
  "geometry": {"coordinates":[-0.97279644977541,53.96668480174204],"type":"Point"}
}