{
  "type": "Feature",
  "properties": {
    "date:inception_lower":"1998-06-01",
    "date:inception_upper":"1998-06-30",
    "iso:country":"GB",
    "wof:name":"YO19 5SH",
    "wof:placetype":"postalcode"
},
  "geometry": {"coordinates":[-0.972796,53.966685],"type":"Point"}
}