{
  "type": "Feature",
  "properties": {
    "date:inception_lower": "1980-01-01",
    "date:inception_upper": "1980-01-01",
    "iso:country": "GB",
    "wof:name": "SA9 1DS",
    "wof:placetype": "postalcode"
  },
  "geometry": {"coordinates":[-3.765392,51.775793],"type":"Point"}
}
