{
  "type": "Feature",
  "properties": {
    "iso:country":"GB",
    "wof:name":"SA9 1DS",
    "wof:placetype":"postalcode"
},
  "geometry": {"coordinates":[-3.76539208822462,51.77579275576901],"type":"Point"}
}