{
  "type": "Feature",
  "properties": {
    "iso:country":"GB",
    "wof:name":"LS7 2PX",
    "wof:placetype":"postalcode"
},
  "geometry": {"coordinates":[-1.55846979129948,53.83035759059014],"type":"Point"}
}