{
  "type": "Feature",
  "properties": {
    "date:inception_lower": "1999-06-01",
    "date:inception_upper": "1999-06-01",
    "iso:country": "GB",
    "wof:name": "NP12 0NH",
    "wof:placetype": "postalcode"
  },
  "geometry": {"coordinates":[-3.177289,51.676588],"type":"Point"}
}
