{
  "type": "Feature",
  "properties": {
    "iso:country": "GB",
    "wof:name": "NP12 0NH",
    "wof:placetype": "postalcode"
  },
  "geometry": {"coordinates":[-3.177289,51.676588],"type":"Point"}
}
