{
  "type": "Feature",
  "properties": {
    "date:inception_lower": "1999-12-01",
    "date:inception_upper": "1999-12-01",
    "iso:country": "GB",
    "wof:name": "BR3 5HQ",
    "wof:placetype": "postalcode"
  },
  "geometry": {"coordinates":[-0.016296,51.409641],"type":"Point"}
}
