{
  "type": "Feature",
  "properties": {
    "iso:country":"GB",
    "wof:name":"BR3 5HQ",
    "wof:placetype":"postalcode"
},
  "geometry": {"coordinates":[-0.01629597940529,51.40964068171525],"type":"Point"}
}