{
  "type": "Feature",
  "properties": {
    "iso:country":"GB",
    "wof:name":"IG8 0PS",
    "wof:placetype":"postalcode"
},
  "geometry": {"coordinates":[0.02661992928373,51.6169615938725],"type":"Point"}
}