{
  "type": "Feature",
  "properties": {
    "iso:country": "GB",
    "wof:name": "LD1 5UF",
    "wof:placetype": "postalcode"
  },
  "geometry": {"coordinates":[-3.260392,52.257037],"type":"Point"}
}
