{
  "type": "Feature",
  "properties": {
    "date:inception_lower": "2002-05-01",
    "date:inception_upper": "2002-05-01",
    "iso:country": "GB",
    "wof:name": "CF62 3LS",
    "wof:placetype": "postalcode"
  },
  "geometry": {"coordinates":[-3.342251,51.385942],"type":"Point"}
}
