{
  "type": "Feature",
  "properties": {
    "iso:country":"GB",
    "wof:name":"CF62 3LS",
    "wof:placetype":"postalcode"
},
  "geometry": {"coordinates":[-3.34225143326842,51.3859416751601],"type":"Point"}
}