{
  "type": "Feature",
  "properties": {
    "iso:country":"GB",
    "wof:name":"LE12 8HG",
    "wof:placetype":"postalcode"
},
  "geometry": {"coordinates":[-1.17965293091335,52.74332289133051],"type":"Point"}
}