{
  "type": "Feature",
  "properties": {
    "iso:country": "GB",
    "wof:name": "SA68 0US",
    "wof:placetype": "postalcode"
  },
  "geometry": {"coordinates":[-4.715772,51.738269],"type":"Point"}
}
