{
  "type": "Feature",
  "properties": {
    "date:inception_lower": "1980-01-01",
    "date:inception_upper": "1980-01-01",
    "iso:country": "GB",
    "wof:name": "PE22 7AB",
    "wof:placetype": "postalcode"
  },
  "geometry": {"coordinates":[-0.100561,53.019902],"type":"Point"}
}
