{
  "type": "Feature",
  "properties": {
    "iso:country": "GB",
    "wof:name": "WA4 3DF",
    "wof:placetype": "postalcode"
  },
  "geometry": {"coordinates":[-2.568215,53.36532],"type":"Point"}
}
