{
  "type": "Feature",
  "properties": {
    "iso:country":"GB",
    "wof:name":"WA4 3DF",
    "wof:placetype":"postalcode"
},
  "geometry": {"coordinates":[-2.56821466720887,53.3653203379957],"type":"Point"}
}