{
  "type": "Feature",
  "properties": {
    "date:inception_lower": "2002-08-01",
    "date:inception_upper": "2002-08-01",
    "iso:country": "GB",
    "wof:name": "SE15 3EP",
    "wof:placetype": "postalcode"
  },
  "geometry": {"coordinates":[-0.046502,51.457989],"type":"Point"}
}
