{
  "type": "Feature",
  "properties": {
    "iso:country":"GB",
    "wof:name":"SA2 0LT",
    "wof:placetype":"postalcode"
},
  "geometry": {"coordinates":[-3.97487677060488,51.61915652473604],"type":"Point"}
}