{
  "type": "Feature",
  "properties": {
    "iso:country":"GB",
    "wof:name":"IG11 8LQ",
    "wof:placetype":"postalcode"
},
  "geometry": {"coordinates":[0.07066742298955,51.53957522174691],"type":"Point"}
}