{
  "type": "Feature",
  "properties": {
    "date:inception_lower": "2017-02-01",
    "date:inception_upper": "2017-02-01",
    "iso:country": "GB",
    "wof:name": "GU7 1FJ",
    "wof:placetype": "postalcode"
  },
  "geometry": {"coordinates":[-0.607737,51.186135],"type":"Point"}
}
