{
  "type": "Feature",
  "properties": {
    "iso:country": "GB",
    "wof:name": "GU7 1FJ",
    "wof:placetype": "postalcode"
  },
  "geometry": {"coordinates":[-0.607737,51.186135],"type":"Point"}
}
