{
  "type": "Feature",
  "properties": {
    "date:inception_lower": "2004-09-01",
    "date:inception_upper": "2004-09-01",
    "iso:country": "GB",
    "wof:name": "N13 6AR",
    "wof:placetype": "postalcode"
  },
  "geometry": {"coordinates":[-0.105399,51.610348],"type":"Point"}
}
