{
  "type": "Feature",
  "properties": {
    "date:inception_lower": "1980-01-01",
    "date:inception_upper": "1980-01-01",
    "iso:country": "GB",
    "wof:name": "SA14 7TY",
    "wof:placetype": "postalcode"
  },
  "geometry": {"coordinates":[-4.046437,51.815872],"type":"Point"}
}
