{
  "type": "Feature",
  "properties": {
    "iso:country":"GB",
    "wof:name":"NR10 4PP",
    "wof:placetype":"postalcode"
},
  "geometry": {"coordinates":[1.17795386279121,52.73833172418364],"type":"Point"}
}