{
  "type": "Feature",
  "properties": {
    "iso:country": "GB",
    "wof:name": "RG19 4PS",
    "wof:placetype": "postalcode"
  },
  "geometry": {"coordinates":[-1.25327,51.396209],"type":"Point"}
}
