{
  "type": "Feature",
  "properties": {
    "iso:country":"GB",
    "wof:name":"RG19 4PS",
    "wof:placetype":"postalcode"
},
  "geometry": {"coordinates":[-1.25327016723196,51.39620907953435],"type":"Point"}
}