{
  "type": "Feature",
  "properties": {
    "iso:country":"GB",
    "wof:name":"BR3 4EA",
    "wof:placetype":"postalcode"
},
  "geometry": {"coordinates":[-0.05043183207234,51.40122080482276],"type":"Point"}
}