{
  "type": "Feature",
  "properties": {
    "iso:country": "GB",
    "wof:name": "GL18 1LN",
    "wof:placetype": "postalcode"
  },
  "geometry": {"coordinates":[-2.399204,51.959885],"type":"Point"}
}
