{
  "type": "Feature",
  "properties": {
    "iso:country":"GB",
    "wof:name":"GL18 1LN",
    "wof:placetype":"postalcode"
},
  "geometry": {"coordinates":[-2.39920399298871,51.95988486488676],"type":"Point"}
}