{
  "type": "Feature",
  "properties": {
    "date:inception_lower": "1980-01-01",
    "date:inception_upper": "1980-01-01",
    "iso:country": "GB",
    "wof:name": "GL18 1LN",
    "wof:placetype": "postalcode"
  },
  "geometry": {"coordinates":[-2.399204,51.959885],"type":"Point"}
}
