{
  "type": "Feature",
  "properties": {
    "iso:country":"GB",
    "wof:name":"NE15 8BP",
    "wof:placetype":"postalcode"
},
  "geometry": {"coordinates":[-1.71208132950721,54.9788428096103],"type":"Point"}
}