{
  "type": "Feature",
  "properties": {
    "iso:country": "GB",
    "wof:name": "E2 8BB",
    "wof:placetype": "postalcode"
  },
  "geometry": {"coordinates":[-0.07585,51.535038],"type":"Point"}
}
