{
  "type": "Feature",
  "properties": {
    "iso:country":"GB",
    "wof:name":"E2 8BB",
    "wof:placetype":"postalcode"
},
  "geometry": {"coordinates":[-0.07585000834435,51.53503782093025],"type":"Point"}
}