{
  "type": "Feature",
  "properties": {
    "iso:country": "GB",
    "wof:name": "YO21 2QP",
    "wof:placetype": "postalcode"
  },
  "geometry": {"coordinates":[-0.791115,54.447945],"type":"Point"}
}
