{
  "type": "Feature",
  "properties": {
    "iso:country": "GB",
    "wof:name": "PL7 4QX",
    "wof:placetype": "postalcode"
  },
  "geometry": {"coordinates":[-4.079075,50.394346],"type":"Point"}
}
