{
  "type": "Feature",
  "properties": {
    "iso:country": "GB",
    "wof:name": "NR20 4LA",
    "wof:placetype": "postalcode"
  },
  "geometry": {"coordinates":[0.976744,52.726605],"type":"Point"}
}
