{
  "type": "Feature",
  "properties": {
    "iso:country":"GB",
    "wof:name":"CF14 6QT",
    "wof:placetype":"postalcode"
},
  "geometry": {"coordinates":[-3.20688596730544,51.53418135256159],"type":"Point"}
}