{
  "type": "Feature",
  "properties": {
    "iso:country": "GB",
    "wof:name": "PL1 4RZ",
    "wof:placetype": "postalcode"
  },
  "geometry": {"coordinates":[-4.175286,50.370293],"type":"Point"}
}
