{
  "type": "Feature",
  "properties": {
    "iso:country":"GB",
    "wof:name":"TR4 9QW",
    "wof:placetype":"postalcode"
},
  "geometry": {"coordinates":[-5.11188945490758,50.34116499979768],"type":"Point"}
}