{
  "type": "Feature",
  "properties": {
    "iso:country": "GB",
    "wof:name": "SL7 2HR",
    "wof:placetype": "postalcode"
  },
  "geometry": {"coordinates":[-0.825706,51.595476],"type":"Point"}
}
