{
  "type": "Feature",
  "properties": {
    "iso:country":"GB",
    "wof:name":"SL7 2HR",
    "wof:placetype":"postalcode"
},
  "geometry": {"coordinates":[-0.82566573228729,51.59552638985587],"type":"Point"}
}