{
  "type": "Feature",
  "properties": {
    "date:inception_lower": "1980-01-01",
    "date:inception_upper": "1980-01-01",
    "iso:country": "GB",
    "wof:name": "SL7 2HR",
    "wof:placetype": "postalcode"
  },
  "geometry": {"coordinates":[-0.825647,51.59553],"type":"Point"}
}
