{
  "type": "Feature",
  "properties": {
    "iso:country":"GB",
    "wof:name":"DD4 9UA",
    "wof:placetype":"postalcode"
},
  "geometry": {"coordinates":[-2.95485800269826,56.49112069214525],"type":"Point"}
}