{
  "type": "Feature",
  "properties": {
    "iso:country":"GB",
    "wof:name":"CR4 3SH",
    "wof:placetype":"postalcode"
},
  "geometry": {"coordinates":[-0.17455106089285,51.41267130462442],"type":"Point"}
}