{
  "type": "Feature",
  "properties": {
    "date:inception_lower": "1995-07-01",
    "date:inception_upper": "1995-07-01",
    "iso:country": "GB",
    "wof:name": "SA6 5HL",
    "wof:placetype": "postalcode"
  },
  "geometry": {"coordinates":[-3.89203,51.699312],"type":"Point"}
}
