{
  "type": "Feature",
  "properties": {
    "iso:country":"GB",
    "wof:name":"SA6 5HL",
    "wof:placetype":"postalcode"
},
  "geometry": {"coordinates":[-3.8920303092738,51.69931234839044],"type":"Point"}
}