{
  "type": "Feature",
  "properties": {
    "iso:country": "GB",
    "wof:name": "LN1 3UF",
    "wof:placetype": "postalcode"
  },
  "geometry": {"coordinates":[-0.546201,53.244591],"type":"Point"}
}
