{
  "type": "Feature",
  "properties": {
    "iso:country":"GB",
    "wof:name":"OX4 6HD",
    "wof:placetype":"postalcode"
},
  "geometry": {"coordinates":[-1.19382077284875,51.72667815284559],"type":"Point"}
}