{
  "type": "Feature",
  "properties": {
    "date:inception_lower": "2007-11-01",
    "date:inception_upper": "2007-11-01",
    "iso:country": "GB",
    "wof:name": "OX4 6HD",
    "wof:placetype": "postalcode"
  },
  "geometry": {"coordinates":[-1.193821,51.726678],"type":"Point"}
}
