{
  "type": "Feature",
  "properties": {
    "iso:country": "GB",
    "wof:name": "BR3 6SA",
    "wof:placetype": "postalcode"
  },
  "geometry": {"coordinates":[-0.012572,51.396367],"type":"Point"}
}
