{
  "type": "Feature",
  "properties": {
    "iso:country": "GB",
    "wof:name": "N20 0FA",
    "wof:placetype": "postalcode"
  },
  "geometry": {"coordinates":[-0.171722,51.627541],"type":"Point"}
}
