{
  "type": "Feature",
  "properties": {
    "date:inception_lower": "1980-01-01",
    "date:inception_upper": "1980-01-01",
    "iso:country": "GB",
    "wof:name": "DE7 5BE",
    "wof:placetype": "postalcode"
  },
  "geometry": {"coordinates":[-1.294516,52.961196],"type":"Point"}
}
