{
  "type": "Feature",
  "properties": {
    "iso:country":"GB",
    "wof:name":"DE7 5BE",
    "wof:placetype":"postalcode"
},
  "geometry": {"coordinates":[-1.29451640212961,52.96119558789957],"type":"Point"}
}