{
  "type": "Feature",
  "properties": {
    "date:inception_lower": "2002-10-01",
    "date:inception_upper": "2002-10-01",
    "iso:country": "GB",
    "wof:name": "EH20 9FB",
    "wof:placetype": "postalcode"
  },
  "geometry": {"coordinates":[-3.173349,55.875052],"type":"Point"}
}
