{
  "type": "Feature",
  "properties": {
    "iso:country":"GB",
    "wof:name":"BR3 4BZ",
    "wof:placetype":"postalcode"
},
  "geometry": {"coordinates":[-0.0493019154144,51.39533871353649],"type":"Point"}
}