{
  "type": "Feature",
  "properties": {
    "iso:country": "GB",
    "wof:name": "SG4 9DQ",
    "wof:placetype": "postalcode"
  },
  "geometry": {"coordinates":[-0.267421,51.939948],"type":"Point"}
}
