{
  "type": "Feature",
  "properties": {
    "date:inception_lower": "1980-01-01",
    "date:inception_upper": "1980-01-01",
    "iso:country": "GB",
    "wof:name": "SG4 9DQ",
    "wof:placetype": "postalcode"
  },
  "geometry": {"coordinates":[-0.267421,51.939948],"type":"Point"}
}
