{
  "type": "Feature",
  "properties": {
    "iso:country":"GB",
    "wof:name":"TN23 3NP",
    "wof:placetype":"postalcode"
},
  "geometry": {"coordinates":[0.86810910465684,51.12003168424262],"type":"Point"}
}