{
  "type": "Feature",
  "properties": {
    "date:inception_lower": "2006-07-01",
    "date:inception_upper": "2006-07-01",
    "iso:country": "GB",
    "wof:name": "S81 8AH",
    "wof:placetype": "postalcode"
  },
  "geometry": {"coordinates":[-1.17436,53.347946],"type":"Point"}
}
