{
  "type": "Feature",
  "properties": {
    "iso:country": "GB",
    "wof:name": "S81 8AH",
    "wof:placetype": "postalcode"
  },
  "geometry": {"coordinates":[-1.17436,53.347946],"type":"Point"}
}
