{
  "type": "Feature",
  "properties": {
    "date:inception_lower": "2003-06-01",
    "date:inception_upper": "2003-06-01",
    "iso:country": "GB",
    "wof:name": "GU12 4SP",
    "wof:placetype": "postalcode"
  },
  "geometry": {"coordinates":[-0.746048,51.24678],"type":"Point"}
}
