{
  "type": "Feature",
  "properties": {
    "iso:country": "GB",
    "wof:name": "GU12 4SP",
    "wof:placetype": "postalcode"
  },
  "geometry": {"coordinates":[-0.74605,51.246726],"type":"Point"}
}
