{
  "type": "Feature",
  "properties": {
    "iso:country": "GB",
    "wof:name": "DE55 4TJ",
    "wof:placetype": "postalcode"
  },
  "geometry": {"coordinates":[-1.361668,53.077735],"type":"Point"}
}
