{
  "type": "Feature",
  "properties": {
    "iso:country":"GB",
    "wof:name":"WA7 5XU",
    "wof:placetype":"postalcode"
},
  "geometry": {"coordinates":[-2.71815144775441,53.33966696217895],"type":"Point"}
}