{
  "type": "Feature",
  "properties": {
    "iso:country": "GB",
    "wof:name": "WA7 5XU",
    "wof:placetype": "postalcode"
  },
  "geometry": {"coordinates":[-2.718151,53.339667],"type":"Point"}
}
