{
  "type": "Feature",
  "properties": {
    "iso:country":"GB",
    "wof:name":"M23 9JY",
    "wof:placetype":"postalcode"
},
  "geometry": {"coordinates":[-2.30658225373156,53.40285428723041],"type":"Point"}
}