{
  "type": "Feature",
  "properties": {
    "iso:country": "GB",
    "wof:name": "ME13 7LW",
    "wof:placetype": "postalcode"
  },
  "geometry": {"coordinates":[0.888722,51.315394],"type":"Point"}
}
