{
  "type": "Feature",
  "properties": {
    "date:inception_lower": "1990-02-01",
    "date:inception_upper": "1990-02-01",
    "iso:country": "GB",
    "wof:name": "ME13 7LW",
    "wof:placetype": "postalcode"
  },
  "geometry": {"coordinates":[0.888722,51.315394],"type":"Point"}
}
