{
  "type": "Feature",
  "properties": {
    "iso:country":"GB",
    "wof:name":"ME13 7LW",
    "wof:placetype":"postalcode"
},
  "geometry": {"coordinates":[0.88872178671679,51.31539406225088],"type":"Point"}
}