{
  "type": "Feature",
  "properties": {
    "iso:country": "GB",
    "wof:name": "NN3 7QX",
    "wof:placetype": "postalcode"
  },
  "geometry": {"coordinates":[-0.8553,52.285679],"type":"Point"}
}
