{
  "type": "Feature",
  "properties": {
    "date:inception_lower":"1993-08-01",
    "date:inception_upper":"1993-08-31",
    "iso:country":"GB",
    "wof:name":"NN3 7QX",
    "wof:placetype":"postalcode"
},
  "geometry": {"coordinates":[-0.8553,52.285679],"type":"Point"}
}