{
  "type": "Feature",
  "properties": {
    "date:inception_lower": "1980-01-01",
    "date:inception_upper": "1980-01-01",
    "iso:country": "GB",
    "wof:name": "LL13 0LF",
    "wof:placetype": "postalcode"
  },
  "geometry": {"coordinates":[-2.940496,52.951258],"type":"Point"}
}
