{
  "type": "Feature",
  "properties": {
    "iso:country": "GB",
    "wof:name": "WF14 9NN",
    "wof:placetype": "postalcode"
  },
  "geometry": {"coordinates":[-1.68272,53.675589],"type":"Point"}
}
