{
  "type": "Feature",
  "properties": {
    "iso:country":"GB",
    "wof:name":"WF14 9NN",
    "wof:placetype":"postalcode"
},
  "geometry": {"coordinates":[-1.68272041049458,53.67558929160345],"type":"Point"}
}