{
  "type": "Feature",
  "properties": {
    "iso:country": "GB",
    "wof:name": "MK45 3GG",
    "wof:placetype": "postalcode"
  },
  "geometry": {"coordinates":[-0.472045,52.064719],"type":"Point"}
}
