{
  "type": "Feature",
  "properties": {
    "iso:country": "GB",
    "wof:name": "BS24 7BN",
    "wof:placetype": "postalcode"
  },
  "geometry": {"coordinates":[-2.921755,51.351483],"type":"Point"}
}
