{
  "type": "Feature",
  "properties": {
    "iso:country":"GB",
    "wof:name":"BS24 7BN",
    "wof:placetype":"postalcode"
},
  "geometry": {"coordinates":[-2.92175523309064,51.35148346430884],"type":"Point"}
}