{
  "type": "Feature",
  "properties": {
    "date:inception_lower": "2023-12-01",
    "date:inception_upper": "2023-12-01",
    "iso:country": "GB",
    "wof:name": "KY7 6FQ",
    "wof:placetype": "postalcode"
  },
  "geometry": {"coordinates":[-3.170628,56.204571],"type":"Point"}
}
