{
  "type": "Feature",
  "properties": {
    "iso:country": "GB",
    "wof:name": "CF64 2PE",
    "wof:placetype": "postalcode"
  },
  "geometry": {"coordinates":[-3.196519,51.4489],"type":"Point"}
}
