{
  "type": "Feature",
  "properties": {
    "date:inception_lower":"1993-01-01",
    "date:inception_upper":"1993-01-31",
    "iso:country":"GB",
    "wof:name":"CF64 2PE",
    "wof:placetype":"postalcode"
},
  "geometry": {"coordinates":[-3.196519,51.4489],"type":"Point"}
}