{
  "type": "Feature",
  "properties": {
    "iso:country":"GB",
    "wof:name":"HD6 2EQ",
    "wof:placetype":"postalcode"
},
  "geometry": {"coordinates":[-1.79262531332218,53.70859150995358],"type":"Point"}
}