{
  "type": "Feature",
  "properties": {
    "iso:country": "GB",
    "wof:name": "SP9 7RB",
    "wof:placetype": "postalcode"
  },
  "geometry": {"coordinates":[-1.654974,51.238826],"type":"Point"}
}
