{
  "type": "Feature",
  "properties": {
    "iso:country":"GB",
    "wof:name":"SP9 7RB",
    "wof:placetype":"postalcode"
},
  "geometry": {"coordinates":[-1.65497448888528,51.23882578714642],"type":"Point"}
}