{
  "type": "Feature",
  "properties": {
    "iso:country": "GB",
    "wof:name": "HP5 3HB",
    "wof:placetype": "postalcode"
  },
  "geometry": {"coordinates":[-0.609813,51.713255],"type":"Point"}
}
