{
  "type": "Feature",
  "properties": {
    "iso:country":"GB",
    "wof:name":"HP5 3HB",
    "wof:placetype":"postalcode"
},
  "geometry": {"coordinates":[-0.60948140051052,51.71322377560386],"type":"Point"}
}