{
  "type": "Feature",
  "properties": {
    "iso:country":"GB",
    "wof:name":"YO10 4BP",
    "wof:placetype":"postalcode"
},
  "geometry": {"coordinates":[-1.077230000652,53.94809081011604],"type":"Point"}
}