{
  "type": "Feature",
  "properties": {
    "date:inception_lower": "1998-06-01",
    "date:inception_upper": "1998-06-01",
    "iso:country": "GB",
    "wof:name": "YO10 4BP",
    "wof:placetype": "postalcode"
  },
  "geometry": {"coordinates":[-1.077223,53.948118],"type":"Point"}
}
