{
  "type": "Feature",
  "properties": {
    "iso:country": "GB",
    "wof:name": "SA35 0DF",
    "wof:placetype": "postalcode"
  },
  "geometry": {"coordinates":[-4.56787,51.935793],"type":"Point"}
}
