{
  "type": "Feature",
  "properties": {
    "iso:country":"GB",
    "wof:name":"SA35 0DF",
    "wof:placetype":"postalcode"
},
  "geometry": {"coordinates":[-4.56786960861804,51.93579252109686],"type":"Point"}
}