{
  "type": "Feature",
  "properties": {
    "date:inception_lower": "2021-01-01",
    "date:inception_upper": "2021-01-01",
    "iso:country": "GB",
    "wof:name": "TQ2 5FA",
    "wof:placetype": "postalcode"
  },
  "geometry": {"coordinates":[-3.537695,50.470186],"type":"Point"}
}
