{
  "type": "Feature",
  "properties": {
    "iso:country": "GB",
    "wof:name": "NE6 5BB",
    "wof:placetype": "postalcode"
  },
  "geometry": {"coordinates":[-1.592935,54.980093],"type":"Point"}
}
