{
  "type": "Feature",
  "properties": {
    "iso:country":"GB",
    "wof:name":"NE6 5BB",
    "wof:placetype":"postalcode"
},
  "geometry": {"coordinates":[-1.59293492239633,54.98009326986649],"type":"Point"}
}