{
  "type": "Feature",
  "properties": {
    "iso:country": "GB",
    "wof:name": "HR3 6HA",
    "wof:placetype": "postalcode"
  },
  "geometry": {"coordinates":[-3.131959,52.11872],"type":"Point"}
}
