{
  "type": "Feature",
  "properties": {
    "date:inception_lower": "1993-08-01",
    "date:inception_upper": "1993-08-01",
    "iso:country": "GB",
    "wof:name": "HR3 6HA",
    "wof:placetype": "postalcode"
  },
  "geometry": {"coordinates":[-3.131959,52.11872],"type":"Point"}
}
