{
  "type": "Feature",
  "properties": {
    "iso:country": "GB",
    "wof:name": "PL19 9HE",
    "wof:placetype": "postalcode"
  },
  "geometry": {"coordinates":[-4.142549,50.548065],"type":"Point"}
}
