{
  "type": "Feature",
  "properties": {
    "iso:country":"GB",
    "wof:name":"AB32 7AS",
    "wof:placetype":"postalcode"
},
  "geometry": {"coordinates":[-2.42868562172943,57.15368933170216],"type":"Point"}
}