{
  "type": "Feature",
  "properties": {
    "date:inception_lower": "1990-08-01",
    "date:inception_upper": "1990-08-01",
    "iso:country": "GB",
    "wof:name": "AB32 7AS",
    "wof:placetype": "postalcode"
  },
  "geometry": {"coordinates":[-2.428686,57.153689],"type":"Point"}
}
