{
  "type": "Feature",
  "properties": {
    "iso:country":"GB",
    "wof:name":"OL2 5QJ",
    "wof:placetype":"postalcode"
},
  "geometry": {"coordinates":[-2.1254311549298,53.56605279983931],"type":"Point"}
}