{
  "type": "Feature",
  "properties": {
    "iso:country": "GB",
    "wof:name": "EH4 6LT",
    "wof:placetype": "postalcode"
  },
  "geometry": {"coordinates":[-3.301369,55.97178],"type":"Point"}
}
