{
  "type": "Feature",
  "properties": {
    "iso:country":"GB",
    "wof:name":"RM6 5JA",
    "wof:placetype":"postalcode"
},
  "geometry": {"coordinates":[0.12988646025938,51.58542120393727],"type":"Point"}
}