{
  "type": "Feature",
  "properties": {
    "iso:country":"GB",
    "wof:name":"B60 1JZ",
    "wof:placetype":"postalcode"
},
  "geometry": {"coordinates":[-2.04366327252013,52.3527897557161],"type":"Point"}
}