{
  "type": "Feature",
  "properties": {
    "iso:country": "GB",
    "wof:name": "SK10 5DX",
    "wof:placetype": "postalcode"
  },
  "geometry": {"coordinates":[-2.111925,53.289255],"type":"Point"}
}
