{
  "type": "Feature",
  "properties": {
    "iso:country":"GB",
    "wof:name":"SK10 5DX",
    "wof:placetype":"postalcode"
},
  "geometry": {"coordinates":[-2.11198653420309,53.28923773147887],"type":"Point"}
}