{
  "type": "Feature",
  "properties": {
    "date:inception_lower": "1980-01-01",
    "date:inception_upper": "1980-01-01",
    "iso:country": "GB",
    "wof:name": "MK45 1ET",
    "wof:placetype": "postalcode"
  },
  "geometry": {"coordinates":[-0.486957,52.005001],"type":"Point"}
}
