{
  "type": "Feature",
  "properties": {
    "iso:country":"GB",
    "wof:name":"MK45 1ET",
    "wof:placetype":"postalcode"
},
  "geometry": {"coordinates":[-0.48692286575547,52.00499023794283],"type":"Point"}
}