{
  "type": "Feature",
  "properties": {
    "iso:country": "GB",
    "wof:name": "SK1 3DU",
    "wof:placetype": "postalcode"
  },
  "geometry": {"coordinates":[-2.151573,53.407959],"type":"Point"}
}
