{
  "type": "Feature",
  "properties": {
    "date:inception_lower": "2004-01-01",
    "date:inception_upper": "2004-01-01",
    "iso:country": "GB",
    "wof:name": "SK1 3DU",
    "wof:placetype": "postalcode"
  },
  "geometry": {"coordinates":[-2.15192,53.408094],"type":"Point"}
}
