{
  "type": "Feature",
  "properties": {
    "iso:country":"GB",
    "wof:name":"SK1 3DU",
    "wof:placetype":"postalcode"
},
  "geometry": {"coordinates":[-2.15157490754795,53.40794287935763],"type":"Point"}
}