{
  "type": "Feature",
  "properties": {
    "iso:country": "GB",
    "wof:name": "CB7 5TF",
    "wof:placetype": "postalcode"
  },
  "geometry": {"coordinates":[0.339054,52.332056],"type":"Point"}
}
