{
  "type": "Feature",
  "properties": {
    "date:inception_lower": "1980-01-01",
    "date:inception_upper": "1980-01-01",
    "iso:country": "GB",
    "wof:name": "N3 2AB",
    "wof:placetype": "postalcode"
  },
  "geometry": {"coordinates":[-0.180503,51.600899],"type":"Point"}
}
