{
  "type": "Feature",
  "properties": {
    "iso:country":"GB",
    "wof:name":"LU7 2TX",
    "wof:placetype":"postalcode"
},
  "geometry": {"coordinates":[-0.68698831131607,51.92006634509277],"type":"Point"}
}