{
  "type": "Feature",
  "properties": {
    "iso:country": "GB",
    "wof:name": "RG7 1EH",
    "wof:placetype": "postalcode"
  },
  "geometry": {"coordinates":[-0.969843,51.39568],"type":"Point"}
}
