{
  "type": "Feature",
  "properties": {
    "iso:country":"GB",
    "wof:name":"RG7 1EH",
    "wof:placetype":"postalcode"
},
  "geometry": {"coordinates":[-0.96984285334955,51.39567956491554],"type":"Point"}
}