{
  "type": "Feature",
  "properties": {
    "date:inception_lower": "2004-07-01",
    "date:inception_upper": "2004-07-01",
    "iso:country": "GB",
    "wof:name": "AB41 8AX",
    "wof:placetype": "postalcode"
  },
  "geometry": {"coordinates":[-2.062036,57.371199],"type":"Point"}
}
