{
  "type": "Feature",
  "properties": {
    "iso:country":"GB",
    "wof:name":"AB41 8AX",
    "wof:placetype":"postalcode"
},
  "geometry": {"coordinates":[-2.06203589578602,57.37119894984958],"type":"Point"}
}