{
  "type": "Feature",
  "properties": {
    "iso:country": "GB",
    "wof:name": "TA20 2DL",
    "wof:placetype": "postalcode"
  },
  "geometry": {"coordinates":[-2.960204,50.872612],"type":"Point"}
}
