{
  "type": "Feature",
  "properties": {
    "iso:country": "GB",
    "wof:name": "B37 7UN",
    "wof:placetype": "postalcode"
  },
  "geometry": {"coordinates":[-1.733516,52.481191],"type":"Point"}
}
