{
  "type": "Feature",
  "properties": {
    "iso:country": "GB",
    "wof:name": "TS2 1AD",
    "wof:placetype": "postalcode"
  },
  "geometry": {"coordinates":[-1.226811,54.579944],"type":"Point"}
}
