{
  "type": "Feature",
  "properties": {
    "iso:country":"GB",
    "wof:name":"SG12 8BD",
    "wof:placetype":"postalcode"
},
  "geometry": {"coordinates":[-0.00411975878654,51.78893760671314],"type":"Point"}
}