{
  "type": "Feature",
  "properties": {
    "iso:country": "GB",
    "wof:name": "SG12 8BD",
    "wof:placetype": "postalcode"
  },
  "geometry": {"coordinates":[-0.00412,51.788938],"type":"Point"}
}
