{
  "type": "Feature",
  "properties": {
    "iso:country": "GB",
    "wof:name": "KY3 9ER",
    "wof:placetype": "postalcode"
  },
  "geometry": {"coordinates":[-3.227209,56.063689],"type":"Point"}
}
