{
  "type": "Feature",
  "properties": {
    "date:inception_lower": "1999-06-01",
    "date:inception_upper": "1999-06-01",
    "iso:country": "GB",
    "wof:name": "NP23 4DH",
    "wof:placetype": "postalcode"
  },
  "geometry": {"coordinates":[-3.173901,51.800516],"type":"Point"}
}
