{
  "type": "Feature",
  "properties": {
    "iso:country":"GB",
    "wof:name":"NP23 4DH",
    "wof:placetype":"postalcode"
},
  "geometry": {"coordinates":[-3.17390150329992,51.80051578022302],"type":"Point"}
}