{
  "type": "Feature",
  "properties": {
    "iso:country":"GB",
    "wof:name":"TS17 0DA",
    "wof:placetype":"postalcode"
},
  "geometry": {"coordinates":[-1.29210421786952,54.53954212648988],"type":"Point"}
}