{
  "type": "Feature",
  "properties": {
    "iso:country":"GB",
    "wof:name":"LL14 4BX",
    "wof:placetype":"postalcode"
},
  "geometry": {"coordinates":[-3.02212717997465,53.03097794823638],"type":"Point"}
}