{
  "type": "Feature",
  "properties": {
    "iso:country": "GB",
    "wof:name": "LL14 4BX",
    "wof:placetype": "postalcode"
  },
  "geometry": {"coordinates":[-3.022127,53.030978],"type":"Point"}
}
