{
  "type": "Feature",
  "properties": {
    "iso:country":"GB",
    "wof:name":"SM1 4PH",
    "wof:placetype":"postalcode"
},
  "geometry": {"coordinates":[-0.18438508871153,51.36297791424349],"type":"Point"}
}