{
  "type": "Feature",
  "properties": {
    "iso:country": "GB",
    "wof:name": "SG6 2HH",
    "wof:placetype": "postalcode"
  },
  "geometry": {"coordinates":[-0.222516,51.968432],"type":"Point"}
}
