{
  "type": "Feature",
  "properties": {
    "iso:country": "GB",
    "wof:name": "DE23 8SQ",
    "wof:placetype": "postalcode"
  },
  "geometry": {"coordinates":[-1.482372,52.904369],"type":"Point"}
}
