{
  "type": "Feature",
  "properties": {
    "iso:country":"GB",
    "wof:name":"RG1 3BD",
    "wof:placetype":"postalcode"
},
  "geometry": {"coordinates":[-0.96619131552137,51.45627081996319],"type":"Point"}
}