{
  "type": "Feature",
  "properties": {
    "iso:country":"GB",
    "wof:name":"HG3 3AN",
    "wof:placetype":"postalcode"
},
  "geometry": {"coordinates":[-1.62698505993478,54.03462230348115],"type":"Point"}
}