{
  "type": "Feature",
  "properties": {
    "iso:country": "GB",
    "wof:name": "AB51 0XW",
    "wof:placetype": "postalcode"
  },
  "geometry": {"coordinates":[-2.353501,57.239271],"type":"Point"}
}
