{
  "type": "Feature",
  "properties": {
    "date:inception_lower": "1980-01-01",
    "date:inception_upper": "1980-01-01",
    "iso:country": "GB",
    "wof:name": "EC1R 1XP",
    "wof:placetype": "postalcode"
  },
  "geometry": {"coordinates":[-0.109308,51.529683],"type":"Point"}
}
