{
  "type": "Feature",
  "properties": {
    "iso:country":"GB",
    "wof:name":"PR3 3FD",
    "wof:placetype":"postalcode"
},
  "geometry": {"coordinates":[-2.60619900493286,53.83017555839394],"type":"Point"}
}