{
  "type": "Feature",
  "properties": {
    "iso:country":"GB",
    "wof:name":"TR15 3NJ",
    "wof:placetype":"postalcode"
},
  "geometry": {"coordinates":[-5.26513805453614,50.2284574511084],"type":"Point"}
}