{
  "type": "Feature",
  "properties": {
    "date:inception_lower":"1980-01-01",
    "date:inception_upper":"1980-01-31",
    "iso:country":"GB",
    "wof:name":"DG8 8DN",
    "wof:placetype":"postalcode"
},
  "geometry": {"coordinates":[-4.429977,54.762215],"type":"Point"}
}