{
  "type": "Feature",
  "properties": {
    "iso:country":"GB",
    "wof:name":"DG8 8DN",
    "wof:placetype":"postalcode"
},
  "geometry": {"coordinates":[-4.42997692406515,54.76221467743606],"type":"Point"}
}