{
  "type": "Feature",
  "properties": {
    "iso:country": "GB",
    "wof:name": "CM13 1UP",
    "wof:placetype": "postalcode"
  },
  "geometry": {"coordinates":[0.389142,51.641369],"type":"Point"}
}
