{
  "type": "Feature",
  "properties": {
    "iso:country":"GB",
    "wof:name":"TR12 6DE",
    "wof:placetype":"postalcode"
},
  "geometry": {"coordinates":[-5.18502771954807,50.08053947649721],"type":"Point"}
}