{
  "type": "Feature",
  "properties": {
    "iso:country":"GB",
    "wof:name":"SY23 4DG",
    "wof:placetype":"postalcode"
},
  "geometry": {"coordinates":[-4.09010681137545,52.36197169959441],"type":"Point"}
}