{
  "type": "Feature",
  "properties": {
    "date:inception_lower": "1980-01-01",
    "date:inception_upper": "1980-01-01",
    "iso:country": "GB",
    "wof:name": "SY23 4DG",
    "wof:placetype": "postalcode"
  },
  "geometry": {"coordinates":[-4.090107,52.361972],"type":"Point"}
}
