{
  "type": "Feature",
  "properties": {
    "iso:country":"GB",
    "wof:name":"BH9 1LG",
    "wof:placetype":"postalcode"
},
  "geometry": {"coordinates":[-1.87321484380222,50.74355807697342],"type":"Point"}
}