{
  "type": "Feature",
  "properties": {
    "date:inception_lower":"1980-01-01",
    "date:inception_upper":"1980-01-31",
    "iso:country":"GB",
    "wof:name":"BH9 1LG",
    "wof:placetype":"postalcode"
},
  "geometry": {"coordinates":[-1.873215,50.743558],"type":"Point"}
}