{
  "type": "Feature",
  "properties": {
    "iso:country":"GB",
    "wof:name":"SP9 7QG",
    "wof:placetype":"postalcode"
},
  "geometry": {"coordinates":[-1.66086311364073,51.23865415291356],"type":"Point"}
}