{
  "type": "Feature",
  "properties": {
    "date:inception_lower": "1980-01-01",
    "date:inception_upper": "1980-01-01",
    "iso:country": "GB",
    "wof:name": "TN21 9EJ",
    "wof:placetype": "postalcode"
  },
  "geometry": {"coordinates":[0.266425,50.936993],"type":"Point"}
}
