{
  "type": "Feature",
  "properties": {
    "iso:country":"GB",
    "wof:name":"RG7 1JZ",
    "wof:placetype":"postalcode"
},
  "geometry": {"coordinates":[-0.99712180427334,51.39514281968369],"type":"Point"}
}