{
  "type": "Feature",
  "properties": {
    "iso:country": "GB",
    "wof:name": "PH20 1AB",
    "wof:placetype": "postalcode"
  },
  "geometry": {"coordinates":[-4.12828,57.063575],"type":"Point"}
}
