{
  "type": "Feature",
  "properties": {
    "iso:country":"GB",
    "wof:name":"KA2 9EW",
    "wof:placetype":"postalcode"
},
  "geometry": {"coordinates":[-4.59271608257194,55.58016821060959],"type":"Point"}
}