{
  "type": "Feature",
  "properties": {
    "iso:country": "GB",
    "wof:name": "KA2 9EW",
    "wof:placetype": "postalcode"
  },
  "geometry": {"coordinates":[-4.592716,55.580168],"type":"Point"}
}
