{
  "type": "Feature",
  "properties": {
    "date:inception_lower": "1980-01-01",
    "date:inception_upper": "1980-01-01",
    "iso:country": "GB",
    "wof:name": "LL26 0SU",
    "wof:placetype": "postalcode"
  },
  "geometry": {"coordinates":[-3.755375,53.099018],"type":"Point"}
}
