{
  "type": "Feature",
  "properties": {
    "iso:country":"GB",
    "wof:name":"LL26 0SU",
    "wof:placetype":"postalcode"
},
  "geometry": {"coordinates":[-3.75895367585342,53.09713293794525],"type":"Point"}
}