{
  "type": "Feature",
  "properties": {
    "iso:country":"GB",
    "wof:name":"BA1 7HW",
    "wof:placetype":"postalcode"
},
  "geometry": {"coordinates":[-2.31795331225912,51.41307139517058],"type":"Point"}
}