{
  "type": "Feature",
  "properties": {
    "iso:country":"GB",
    "wof:name":"B32 2RB",
    "wof:placetype":"postalcode"
},
  "geometry": {"coordinates":[-1.98590304451023,52.45338706615184],"type":"Point"}
}