{
  "type": "Feature",
  "properties": {
    "iso:country":"GB",
    "wof:name":"SE11 4TY",
    "wof:placetype":"postalcode"
},
  "geometry": {"coordinates":[-0.1067631060721,51.49335678198094],"type":"Point"}
}