{
  "type": "Feature",
  "properties": {
    "iso:country": "GB",
    "wof:name": "SE11 4TY",
    "wof:placetype": "postalcode"
  },
  "geometry": {"coordinates":[-0.106763,51.493357],"type":"Point"}
}
