{
  "type": "Feature",
  "properties": {
    "date:inception_lower":"2001-12-01",
    "date:inception_upper":"2001-12-31",
    "iso:country":"GB",
    "wof:name":"SE11 4TY",
    "wof:placetype":"postalcode"
},
  "geometry": {"coordinates":[-0.106763,51.493357],"type":"Point"}
}