{
  "type": "Feature",
  "properties": {
    "date:inception_lower": "1992-08-01",
    "date:inception_upper": "1992-08-01",
    "iso:country": "GB",
    "wof:name": "NG1 1EL",
    "wof:placetype": "postalcode"
  },
  "geometry": {"coordinates":[-1.14456,52.95569],"type":"Point"}
}
