{
  "type": "Feature",
  "properties": {
    "iso:country":"GB",
    "wof:name":"E1 4EG",
    "wof:placetype":"postalcode"
},
  "geometry": {"coordinates":[-0.04529989485585,51.52316608694569],"type":"Point"}
}