{
  "type": "Feature",
  "properties": {
    "iso:country": "GB",
    "wof:name": "E1 4EG",
    "wof:placetype": "postalcode"
  },
  "geometry": {"coordinates":[-0.0453,51.523166],"type":"Point"}
}
