{
  "type": "Feature",
  "properties": {
    "date:inception_lower": "1980-01-01",
    "date:inception_upper": "1980-01-01",
    "iso:country": "GB",
    "wof:name": "NW3 6HS",
    "wof:placetype": "postalcode"
  },
  "geometry": {"coordinates":[-0.189551,51.553118],"type":"Point"}
}
