{
  "type": "Feature",
  "properties": {
    "date:inception_lower": "2002-05-01",
    "date:inception_upper": "2002-05-01",
    "iso:country": "GB",
    "wof:name": "NE10 8WH",
    "wof:placetype": "postalcode"
  },
  "geometry": {"coordinates":[-1.534447,54.95075],"type":"Point"}
}
