{
  "type": "Feature",
  "properties": {
    "date:inception_lower": "2003-08-01",
    "date:inception_upper": "2003-08-01",
    "iso:country": "GB",
    "wof:name": "PH2 9GB",
    "wof:placetype": "postalcode"
  },
  "geometry": {"coordinates":[-3.318681,56.333805],"type":"Point"}
}
