{
  "type": "Feature",
  "properties": {
    "iso:country": "GB",
    "wof:name": "PH2 9GB",
    "wof:placetype": "postalcode"
  },
  "geometry": {"coordinates":[-3.318681,56.333805],"type":"Point"}
}
