{
  "type": "Feature",
  "properties": {
    "iso:country": "GB",
    "wof:name": "DT2 8UJ",
    "wof:placetype": "postalcode"
  },
  "geometry": {"coordinates":[-2.387181,50.678703],"type":"Point"}
}
