{
  "type": "Feature",
  "properties": {
    "iso:country":"GB",
    "wof:name":"DT2 8UJ",
    "wof:placetype":"postalcode"
},
  "geometry": {"coordinates":[-2.3871810188029,50.67870308696163],"type":"Point"}
}