{
  "type": "Feature",
  "properties": {
    "iso:country":"GB",
    "wof:name":"AB33 8EX",
    "wof:placetype":"postalcode"
},
  "geometry": {"coordinates":[-2.65067088309239,57.21356837079208],"type":"Point"}
}