{
  "type": "Feature",
  "properties": {
    "iso:country": "GB",
    "wof:name": "CR0 2DQ",
    "wof:placetype": "postalcode"
  },
  "geometry": {"coordinates":[-0.088326,51.38716],"type":"Point"}
}
