{
  "type": "Feature",
  "properties": {
    "iso:country": "GB",
    "wof:name": "RG41 4DQ",
    "wof:placetype": "postalcode"
  },
  "geometry": {"coordinates":[-0.879805,51.39721],"type":"Point"}
}
