{
  "type": "Feature",
  "properties": {
    "iso:country":"GB",
    "wof:name":"E5 8RD",
    "wof:placetype":"postalcode"
},
  "geometry": {"coordinates":[-0.06263301042486,51.56173498061092],"type":"Point"}
}