{
  "type": "Feature",
  "properties": {
    "iso:country": "GB",
    "wof:name": "E5 8RD",
    "wof:placetype": "postalcode"
  },
  "geometry": {"coordinates":[-0.062633,51.561735],"type":"Point"}
}
