{
  "type": "Feature",
  "properties": {
    "iso:country":"GB",
    "wof:name":"WA8 7PP",
    "wof:placetype":"postalcode"
},
  "geometry": {"coordinates":[-2.75821394038877,53.37307329913579],"type":"Point"}
}