{
  "type": "Feature",
  "properties": {
    "iso:country":"GB",
    "wof:name":"BS21 6HY",
    "wof:placetype":"postalcode"
},
  "geometry": {"coordinates":[-2.85389920406159,51.43145885400443],"type":"Point"}
}