{
  "type": "Feature",
  "properties": {
    "date:inception_lower": "1991-01-01",
    "date:inception_upper": "1991-01-01",
    "iso:country": "GB",
    "wof:name": "BS21 6HY",
    "wof:placetype": "postalcode"
  },
  "geometry": {"coordinates":[-2.853889,51.43143],"type":"Point"}
}
