{
  "type": "Feature",
  "properties": {
    "iso:country": "GB",
    "wof:name": "BS21 6HY",
    "wof:placetype": "postalcode"
  },
  "geometry": {"coordinates":[-2.853889,51.43143],"type":"Point"}
}
