{
  "type": "Feature",
  "properties": {
    "date:inception_lower": "2009-09-01",
    "date:inception_upper": "2009-09-01",
    "iso:country": "GB",
    "wof:name": "BA13 3FG",
    "wof:placetype": "postalcode"
  },
  "geometry": {"coordinates":[-2.197951,51.254191],"type":"Point"}
}
