{
  "type": "Feature",
  "properties": {
    "iso:country":"GB",
    "wof:name":"E4 8AA",
    "wof:placetype":"postalcode"
},
  "geometry": {"coordinates":[-0.01775511618456,51.62194583102737],"type":"Point"}
}