{
  "type": "Feature",
  "properties": {
    "iso:country": "GB",
    "wof:name": "KA2 9BG",
    "wof:placetype": "postalcode"
  },
  "geometry": {"coordinates":[-4.570689,55.586673],"type":"Point"}
}
