{
  "type": "Feature",
  "properties": {
    "iso:country": "GB",
    "wof:name": "AL8 7TA",
    "wof:placetype": "postalcode"
  },
  "geometry": {"coordinates":[-0.224662,51.784157],"type":"Point"}
}
