{
  "type": "Feature",
  "properties": {
    "iso:country": "GB",
    "wof:name": "MK43 0QL",
    "wof:placetype": "postalcode"
  },
  "geometry": {"coordinates":[-0.545593,52.062024],"type":"Point"}
}
