{
  "type": "Feature",
  "properties": {
    "date:inception_lower": "1980-01-01",
    "date:inception_upper": "1980-01-01",
    "iso:country": "GB",
    "wof:name": "NE13 7JU",
    "wof:placetype": "postalcode"
  },
  "geometry": {"coordinates":[-1.669724,55.055082],"type":"Point"}
}
