{
  "type": "Feature",
  "properties": {
    "iso:country":"GB",
    "wof:name":"NE13 7JU",
    "wof:placetype":"postalcode"
},
  "geometry": {"coordinates":[-1.66972385846258,55.05508185414266],"type":"Point"}
}