{
  "type": "Feature",
  "properties": {
    "date:inception_lower":"1987-04-01",
    "date:inception_upper":"1987-04-30",
    "iso:country":"GB",
    "wof:name":"LE15 9BW",
    "wof:placetype":"postalcode"
},
  "geometry": {"coordinates":[-0.675416,52.594767],"type":"Point"}
}