{
  "type": "Feature",
  "properties": {
    "iso:country":"GB",
    "wof:name":"LE15 9BW",
    "wof:placetype":"postalcode"
},
  "geometry": {"coordinates":[-0.67541606252521,52.59476659281581],"type":"Point"}
}