{
  "type": "Feature",
  "properties": {
    "date:inception_lower": "1980-01-01",
    "date:inception_upper": "1980-01-01",
    "iso:country": "GB",
    "wof:name": "EN3 6AL",
    "wof:placetype": "postalcode"
  },
  "geometry": {"coordinates":[-0.0371,51.670776],"type":"Point"}
}
