{
  "type": "Feature",
  "properties": {
    "iso:country":"GB",
    "wof:name":"EN3 6AL",
    "wof:placetype":"postalcode"
},
  "geometry": {"coordinates":[-0.03710036378051,51.67077616417031],"type":"Point"}
}