{
  "type": "Feature",
  "properties": {
    "iso:country":"GB",
    "wof:name":"DL13 5DW",
    "wof:placetype":"postalcode"
},
  "geometry": {"coordinates":[-1.80737343472046,54.61502473379772],"type":"Point"}
}