{
  "type": "Feature",
  "properties": {
    "iso:country": "GB",
    "wof:name": "DL13 5DW",
    "wof:placetype": "postalcode"
  },
  "geometry": {"coordinates":[-1.807373,54.615025],"type":"Point"}
}
