{
  "type": "Feature",
  "properties": {
    "iso:country": "GB",
    "wof:name": "YO10 5BG",
    "wof:placetype": "postalcode"
  },
  "geometry": {"coordinates":[-1.070724,53.952894],"type":"Point"}
}
