{
  "type": "Feature",
  "properties": {
    "iso:country":"GB",
    "wof:name":"YO10 5BG",
    "wof:placetype":"postalcode"
},
  "geometry": {"coordinates":[-1.07072376804015,53.95289423707324],"type":"Point"}
}