{
  "type": "Feature",
  "properties": {
    "iso:country":"GB",
    "wof:name":"SK8 7BY",
    "wof:placetype":"postalcode"
},
  "geometry": {"coordinates":[-2.18084170180568,53.37463533721932],"type":"Point"}
}