{
  "type": "Feature",
  "properties": {
    "iso:country": "GB",
    "wof:name": "DT11 0EW",
    "wof:placetype": "postalcode"
  },
  "geometry": {"coordinates":[-2.310491,50.862078],"type":"Point"}
}
