{
  "type": "Feature",
  "properties": {
    "iso:country":"GB",
    "wof:name":"DT11 0EW",
    "wof:placetype":"postalcode"
},
  "geometry": {"coordinates":[-2.3097695385613,50.86213232430501],"type":"Point"}
}