{
  "type": "Feature",
  "properties": {
    "iso:country": "GB",
    "wof:name": "CR0 4UA",
    "wof:placetype": "postalcode"
  },
  "geometry": {"coordinates":[-0.132377,51.372691],"type":"Point"}
}
