{
  "type": "Feature",
  "properties": {
    "iso:country":"GB",
    "wof:name":"CR0 4UA",
    "wof:placetype":"postalcode"
},
  "geometry": {"coordinates":[-0.1323773835573,51.37269079148957],"type":"Point"}
}