{
  "type": "Feature",
  "properties": {
    "date:inception_lower": "1980-01-01",
    "date:inception_upper": "1980-01-01",
    "iso:country": "GB",
    "wof:name": "N6 6QL",
    "wof:placetype": "postalcode"
  },
  "geometry": {"coordinates":[-0.147842,51.562419],"type":"Point"}
}
