{
  "type": "Feature",
  "properties": {
    "iso:country":"GB",
    "wof:name":"N6 6QL",
    "wof:placetype":"postalcode"
},
  "geometry": {"coordinates":[-0.1478425325335,51.56241856560951],"type":"Point"}
}