{
  "type": "Feature",
  "properties": {
    "iso:country":"GB",
    "wof:name":"W2 1DU",
    "wof:placetype":"postalcode"
},
  "geometry": {"coordinates":[-0.16912858460732,51.51952599707991],"type":"Point"}
}