{
  "type": "Feature",
  "properties": {
    "iso:country":"GB",
    "wof:name":"B60 2JW",
    "wof:placetype":"postalcode"
},
  "geometry": {"coordinates":[-2.05771535709651,52.33157588597032],"type":"Point"}
}