{
  "type": "Feature",
  "properties": {
    "date:inception_lower": "1998-12-01",
    "date:inception_upper": "1998-12-01",
    "iso:country": "GB",
    "wof:name": "CM7 3LE",
    "wof:placetype": "postalcode"
  },
  "geometry": {"coordinates":[0.582643,51.879562],"type":"Point"}
}
