{
  "type": "Feature",
  "properties": {
    "iso:country":"GB",
    "wof:name":"RG14 5SY",
    "wof:placetype":"postalcode"
},
  "geometry": {"coordinates":[-1.3102815067184,51.39970545730555],"type":"Point"}
}