{
  "type": "Feature",
  "properties": {
    "date:inception_lower": "2007-12-01",
    "date:inception_upper": "2007-12-01",
    "iso:country": "GB",
    "wof:name": "M7 4TD",
    "wof:placetype": "postalcode"
  },
  "geometry": {"coordinates":[-2.24298,53.506566],"type":"Point"}
}
