{
  "type": "Feature",
  "properties": {
    "iso:country": "GB",
    "wof:name": "NG14 6SD",
    "wof:placetype": "postalcode"
  },
  "geometry": {"coordinates":[-1.056987,53.033579],"type":"Point"}
}
