{
  "type": "Feature",
  "properties": {
    "date:inception_lower": "2009-09-01",
    "date:inception_upper": "2009-09-01",
    "iso:country": "GB",
    "wof:name": "S25 2AE",
    "wof:placetype": "postalcode"
  },
  "geometry": {"coordinates":[-1.210851,53.365732],"type":"Point"}
}
