{
  "type": "Feature",
  "properties": {
    "iso:country":"GB",
    "wof:name":"EX12 2QP",
    "wof:placetype":"postalcode"
},
  "geometry": {"coordinates":[-3.07439069376858,50.70415977627886],"type":"Point"}
}