{
  "type": "Feature",
  "properties": {
    "iso:country":"GB",
    "wof:name":"WV6 7AR",
    "wof:placetype":"postalcode"
},
  "geometry": {"coordinates":[-2.25734768878739,52.58568171954789],"type":"Point"}
}