{
  "type": "Feature",
  "properties": {
    "date:inception_lower":"1980-01-01",
    "date:inception_upper":"1980-01-31",
    "iso:country":"GB",
    "wof:name":"WV6 7AR",
    "wof:placetype":"postalcode"
},
  "geometry": {"coordinates":[-2.257348,52.585682],"type":"Point"}
}