{
  "type": "Feature",
  "properties": {
    "iso:country":"GB",
    "wof:name":"DN4 7PU",
    "wof:placetype":"postalcode"
},
  "geometry": {"coordinates":[-1.07714115564027,53.49654797630341],"type":"Point"}
}