{
  "type": "Feature",
  "properties": {
    "date:inception_lower": "2021-01-01",
    "date:inception_upper": "2021-01-01",
    "iso:country": "GB",
    "wof:name": "PL27 6GB",
    "wof:placetype": "postalcode"
  },
  "geometry": {"coordinates":[-4.904233,50.550385],"type":"Point"}
}
