{
  "type": "Feature",
  "properties": {
    "iso:country":"GB",
    "wof:name":"CM3 1BN",
    "wof:placetype":"postalcode"
},
  "geometry": {"coordinates":[0.45424061203194,51.81371400156382],"type":"Point"}
}