{
  "type": "Feature",
  "properties": {
    "date:inception_lower": "2020-11-01",
    "date:inception_upper": "2020-11-01",
    "iso:country": "GB",
    "wof:name": "DN14 7FQ",
    "wof:placetype": "postalcode"
  },
  "geometry": {"coordinates":[-0.865817,53.750318],"type":"Point"}
}
