{
  "type": "Feature",
  "properties": {
    "iso:country":"GB",
    "wof:name":"HU5 3BB",
    "wof:placetype":"postalcode"
},
  "geometry": {"coordinates":[-0.36174817276952,53.76106232854987],"type":"Point"}
}