{
  "type": "Feature",
  "properties": {
    "date:inception_lower": "1995-01-01",
    "date:inception_upper": "1995-01-01",
    "iso:country": "GB",
    "wof:name": "NG32 2BW",
    "wof:placetype": "postalcode"
  },
  "geometry": {"coordinates":[-0.677146,52.944201],"type":"Point"}
}
