{
  "type": "Feature",
  "properties": {
    "iso:country": "GB",
    "wof:name": "NG32 2BW",
    "wof:placetype": "postalcode"
  },
  "geometry": {"coordinates":[-0.68085,52.942804],"type":"Point"}
}
