{
  "type": "Feature",
  "properties": {
    "iso:country":"GB",
    "wof:name":"SP4 0JF",
    "wof:placetype":"postalcode"
},
  "geometry": {"coordinates":[-1.75681026119537,51.16476302850811],"type":"Point"}
}