{
  "type": "Feature",
  "properties": {
    "iso:country":"GB",
    "wof:name":"EX14 9HJ",
    "wof:placetype":"postalcode"
},
  "geometry": {"coordinates":[-3.13127689113494,50.81408199507049],"type":"Point"}
}