{
  "type": "Feature",
  "properties": {
    "iso:country": "GB",
    "wof:name": "EX14 9HJ",
    "wof:placetype": "postalcode"
  },
  "geometry": {"coordinates":[-3.131277,50.814082],"type":"Point"}
}
