{
  "type": "Feature",
  "properties": {
    "iso:country":"GB",
    "wof:name":"PR2 3NT",
    "wof:placetype":"postalcode"
},
  "geometry": {"coordinates":[-2.71899105040303,53.7898966485381],"type":"Point"}
}