{
  "type": "Feature",
  "properties": {
    "iso:country":"GB",
    "wof:name":"WF12 0AY",
    "wof:placetype":"postalcode"
},
  "geometry": {"coordinates":[-1.62830675822459,53.67309597364638],"type":"Point"}
}