{
  "type": "Feature",
  "properties": {
    "date:inception_lower": "2007-11-01",
    "date:inception_upper": "2007-11-01",
    "iso:country": "GB",
    "wof:name": "WF12 0AY",
    "wof:placetype": "postalcode"
  },
  "geometry": {"coordinates":[-1.628307,53.673096],"type":"Point"}
}
