{
  "type": "Feature",
  "properties": {
    "iso:country":"GB",
    "wof:name":"SR4 7DJ",
    "wof:placetype":"postalcode"
},
  "geometry": {"coordinates":[-1.40313960793778,54.90327648417942],"type":"Point"}
}