{
  "type": "Feature",
  "properties": {
    "date:inception_lower": "1987-10-01",
    "date:inception_upper": "1987-10-01",
    "iso:country": "GB",
    "wof:name": "LA9 7RR",
    "wof:placetype": "postalcode"
  },
  "geometry": {"coordinates":[-2.731016,54.311045],"type":"Point"}
}
