{
  "type": "Feature",
  "properties": {
    "iso:country":"GB",
    "wof:name":"LA9 7RR",
    "wof:placetype":"postalcode"
},
  "geometry": {"coordinates":[-2.73075453796366,54.31109104284013],"type":"Point"}
}