{
  "type": "Feature",
  "properties": {
    "date:inception_lower":"1987-10-01",
    "date:inception_upper":"1987-10-31",
    "iso:country":"GB",
    "wof:name":"LA9 7RR",
    "wof:placetype":"postalcode"
},
  "geometry": {"coordinates":[-2.730756,54.311101],"type":"Point"}
}