{
  "type": "Feature",
  "properties": {
    "iso:country":"GB",
    "wof:name":"NG9 8DB",
    "wof:placetype":"postalcode"
},
  "geometry": {"coordinates":[-1.27300864727119,52.93073565573772],"type":"Point"}
}