{
  "type": "Feature",
  "properties": {
    "iso:country": "GB",
    "wof:name": "YO25 4AF",
    "wof:placetype": "postalcode"
  },
  "geometry": {"coordinates":[-0.333788,54.040262],"type":"Point"}
}
