{
  "type": "Feature",
  "properties": {
    "date:inception_lower": "2018-08-01",
    "date:inception_upper": "2018-08-01",
    "iso:country": "GB",
    "wof:name": "YO25 4AF",
    "wof:placetype": "postalcode"
  },
  "geometry": {"coordinates":[-0.333852,54.0402],"type":"Point"}
}
