{
  "type": "Feature",
  "properties": {
    "iso:country":"GB",
    "wof:name":"NG12 3EP",
    "wof:placetype":"postalcode"
},
  "geometry": {"coordinates":[-1.01241875487243,52.86548790822674],"type":"Point"}
}