{
  "type": "Feature",
  "properties": {
    "iso:country":"GB",
    "wof:name":"DD2 4NJ",
    "wof:placetype":"postalcode"
},
  "geometry": {"coordinates":[-3.035366462695,56.47331501108626],"type":"Point"}
}