{
  "type": "Feature",
  "properties": {
    "date:inception_lower":"1980-01-01",
    "date:inception_upper":"1980-01-31",
    "iso:country":"GB",
    "wof:name":"SW1W 8BJ",
    "wof:placetype":"postalcode"
},
  "geometry": {"coordinates":[-0.157642,51.491622],"type":"Point"}
}