{
  "type": "Feature",
  "properties": {
    "iso:country":"GB",
    "wof:name":"SW1W 8BJ",
    "wof:placetype":"postalcode"
},
  "geometry": {"coordinates":[-0.15764220076432,51.49162227263292],"type":"Point"}
}