{
  "type": "Feature",
  "properties": {
    "iso:country":"GB",
    "wof:name":"RM3 0NP",
    "wof:placetype":"postalcode"
},
  "geometry": {"coordinates":[0.24492142395001,51.59153222594865],"type":"Point"}
}