{
  "type": "Feature",
  "properties": {
    "date:inception_lower": "1980-01-01",
    "date:inception_upper": "1980-01-01",
    "iso:country": "GB",
    "wof:name": "RM3 0NP",
    "wof:placetype": "postalcode"
  },
  "geometry": {"coordinates":[0.244877,51.591571],"type":"Point"}
}
