{
  "type": "Feature",
  "properties": {
    "iso:country":"GB",
    "wof:name":"CW5 5RB",
    "wof:placetype":"postalcode"
},
  "geometry": {"coordinates":[-2.52110260811618,53.07300846082272],"type":"Point"}
}