{
  "type": "Feature",
  "properties": {
    "date:inception_lower":"2008-06-01",
    "date:inception_upper":"2008-06-30",
    "iso:country":"GB",
    "wof:name":"CW5 5RB",
    "wof:placetype":"postalcode"
},
  "geometry": {"coordinates":[-2.521103,53.073008],"type":"Point"}
}