{
  "type": "Feature",
  "properties": {
    "iso:country":"GB",
    "wof:name":"EH10 5EF",
    "wof:placetype":"postalcode"
},
  "geometry": {"coordinates":[-3.21946855430873,55.93085330805117],"type":"Point"}
}