{
  "type": "Feature",
  "properties": {
    "date:inception_lower": "2022-04-01",
    "date:inception_upper": "2022-04-01",
    "iso:country": "GB",
    "wof:name": "NE61 5FB",
    "wof:placetype": "postalcode"
  },
  "geometry": {"coordinates":[-1.561049,55.218604],"type":"Point"}
}
