{
  "type": "Feature",
  "properties": {
    "date:inception_lower": "2022-04-01",
    "date:inception_upper": "2022-04-01",
    "iso:country": "GB",
    "wof:name": "NE61 5FB",
    "wof:placetype": "postalcode"
  },
  "geometry": {"coordinates":[-1.5607,55.218935],"type":"Point"}
}
