{
  "type": "Feature",
  "properties": {
    "iso:country":"GB",
    "wof:name":"S9 3AR",
    "wof:placetype":"postalcode"
},
  "geometry": {"coordinates":[-1.42380902019126,53.38821485647414],"type":"Point"}
}