{
  "type": "Feature",
  "properties": {
    "iso:country":"GB",
    "wof:name":"NE24 1HH",
    "wof:placetype":"postalcode"
},
  "geometry": {"coordinates":[-1.51746312399861,55.12896113252505],"type":"Point"}
}