{
  "type": "Feature",
  "properties": {
    "date:inception_lower": "1980-01-01",
    "date:inception_upper": "1980-01-01",
    "iso:country": "GB",
    "wof:name": "NE24 1HH",
    "wof:placetype": "postalcode"
  },
  "geometry": {"coordinates":[-1.517463,55.128961],"type":"Point"}
}
