{
  "type": "Feature",
  "properties": {
    "iso:country": "GB",
    "wof:name": "WV10 6XG",
    "wof:placetype": "postalcode"
  },
  "geometry": {"coordinates":[-2.143385,52.616053],"type":"Point"}
}
