{
  "type": "Feature",
  "properties": {
    "date:inception_lower": "1998-12-01",
    "date:inception_upper": "1998-12-01",
    "iso:country": "GB",
    "wof:name": "CV4 8GT",
    "wof:placetype": "postalcode"
  },
  "geometry": {"coordinates":[-1.581859,52.385745],"type":"Point"}
}
