{
  "type": "Feature",
  "properties": {
    "iso:country": "GB",
    "wof:name": "CV4 8GT",
    "wof:placetype": "postalcode"
  },
  "geometry": {"coordinates":[-1.581859,52.385745],"type":"Point"}
}
