{
  "type": "Feature",
  "properties": {
    "date:inception_lower": "2019-04-01",
    "date:inception_upper": "2019-04-01",
    "iso:country": "GB",
    "wof:name": "NE32 4AH",
    "wof:placetype": "postalcode"
  },
  "geometry": {"coordinates":[-1.475073,54.963546],"type":"Point"}
}
