{
  "type": "Feature",
  "properties": {
    "iso:country":"GB",
    "wof:name":"LA4 4NU",
    "wof:placetype":"postalcode"
},
  "geometry": {"coordinates":[-2.86549348282567,54.06839455522375],"type":"Point"}
}