{
  "type": "Feature",
  "properties": {
    "iso:country":"GB",
    "wof:name":"NG34 9LJ",
    "wof:placetype":"postalcode"
},
  "geometry": {"coordinates":[-0.2888092035323,52.97044561281694],"type":"Point"}
}