{
  "type": "Feature",
  "properties": {
    "date:inception_lower": "1980-01-01",
    "date:inception_upper": "1980-01-01",
    "iso:country": "GB",
    "wof:name": "NG34 9LJ",
    "wof:placetype": "postalcode"
  },
  "geometry": {"coordinates":[-0.288809,52.970446],"type":"Point"}
}
