{
  "type": "Feature",
  "properties": {
    "iso:country":"GB",
    "wof:name":"TN2 3HX",
    "wof:placetype":"postalcode"
},
  "geometry": {"coordinates":[0.28637549785154,51.14837238234836],"type":"Point"}
}