{
  "type": "Feature",
  "properties": {
    "iso:country": "GB",
    "wof:name": "EX20 2AS",
    "wof:placetype": "postalcode"
  },
  "geometry": {"coordinates":[-3.91295,50.836564],"type":"Point"}
}
