{
  "type": "Feature",
  "properties": {
    "iso:country": "GB",
    "wof:name": "EX20 2AS",
    "wof:placetype": "postalcode"
  },
  "geometry": {"coordinates":[-3.913561,50.836212],"type":"Point"}
}
