{
  "type": "Feature",
  "properties": {
    "iso:country":"GB",
    "wof:name":"EX20 2AS",
    "wof:placetype":"postalcode"
},
  "geometry": {"coordinates":[-3.91292919288083,50.83657196921063],"type":"Point"}
}