{
  "type": "Feature",
  "properties": {
    "date:inception_lower": "2022-02-01",
    "date:inception_upper": "2022-02-01",
    "iso:country": "GB",
    "wof:name": "LN5 0FQ",
    "wof:placetype": "postalcode"
  },
  "geometry": {"coordinates":[-0.519092,53.105389],"type":"Point"}
}
