{
  "type": "Feature",
  "properties": {
    "date:inception_lower": "1980-01-01",
    "date:inception_upper": "1980-01-01",
    "iso:country": "GB",
    "wof:name": "HA0 1LH",
    "wof:placetype": "postalcode"
  },
  "geometry": {"coordinates":[-0.295327,51.538288],"type":"Point"}
}
