{
  "type": "Feature",
  "properties": {
    "iso:country":"GB",
    "wof:name":"HA0 1LH",
    "wof:placetype":"postalcode"
},
  "geometry": {"coordinates":[-0.29532753532467,51.53828846482456],"type":"Point"}
}