{
  "type": "Feature",
  "properties": {
    "iso:country":"GB",
    "wof:name":"BB7 2NZ",
    "wof:placetype":"postalcode"
},
  "geometry": {"coordinates":[-2.40595424933787,53.86699042622684],"type":"Point"}
}