{
  "type": "Feature",
  "properties": {
    "iso:country":"GB",
    "wof:name":"PE9 3EW",
    "wof:placetype":"postalcode"
},
  "geometry": {"coordinates":[-0.41020590945503,52.63413736856059],"type":"Point"}
}