{
  "type": "Feature",
  "properties": {
    "iso:country": "GB",
    "wof:name": "PE9 3EW",
    "wof:placetype": "postalcode"
  },
  "geometry": {"coordinates":[-0.410206,52.634137],"type":"Point"}
}
