{
  "type": "Feature",
  "properties": {
    "date:inception_lower":"1994-05-01",
    "date:inception_upper":"1994-05-31",
    "iso:country":"GB",
    "wof:name":"PE9 3EW",
    "wof:placetype":"postalcode"
},
  "geometry": {"coordinates":[-0.410206,52.634137],"type":"Point"}
}