{
  "type": "Feature",
  "properties": {
    "date:inception_lower": "1980-01-01",
    "date:inception_upper": "1980-01-01",
    "iso:country": "GB",
    "wof:name": "S75 2JX",
    "wof:placetype": "postalcode"
  },
  "geometry": {"coordinates":[-1.511117,53.552618],"type":"Point"}
}
