{
  "type": "Feature",
  "properties": {
    "iso:country":"GB",
    "wof:name":"S75 2JX",
    "wof:placetype":"postalcode"
},
  "geometry": {"coordinates":[-1.51111670230019,53.55261805426791],"type":"Point"}
}