{
  "type": "Feature",
  "properties": {
    "iso:country":"GB",
    "wof:name":"NG17 3HL",
    "wof:placetype":"postalcode"
},
  "geometry": {"coordinates":[-1.28725669411851,53.14538749620199],"type":"Point"}
}