{
  "type": "Feature",
  "properties": {
    "iso:country": "GB",
    "wof:name": "NG17 3HL",
    "wof:placetype": "postalcode"
  },
  "geometry": {"coordinates":[-1.287257,53.145387],"type":"Point"}
}
