{
  "type": "Feature",
  "properties": {
    "iso:country":"GB",
    "wof:name":"TS5 7QD",
    "wof:placetype":"postalcode"
},
  "geometry": {"coordinates":[-1.23669177160238,54.5520837966689],"type":"Point"}
}