{
  "type": "Feature",
  "properties": {
    "date:inception_lower": "1980-01-01",
    "date:inception_upper": "1980-01-01",
    "iso:country": "GB",
    "wof:name": "TS5 7QD",
    "wof:placetype": "postalcode"
  },
  "geometry": {"coordinates":[-1.236722,54.552043],"type":"Point"}
}
