{
  "type": "Feature",
  "properties": {
    "iso:country":"GB",
    "wof:name":"M40 5LD",
    "wof:placetype":"postalcode"
},
  "geometry": {"coordinates":[-2.19307708768414,53.50403274640539],"type":"Point"}
}