{
  "type": "Feature",
  "properties": {
    "iso:country":"GB",
    "wof:name":"PE6 7DA",
    "wof:placetype":"postalcode"
},
  "geometry": {"coordinates":[-0.31492349338949,52.64331268634931],"type":"Point"}
}