{
  "type": "Feature",
  "properties": {
    "iso:country": "GB",
    "wof:name": "PE6 7DA",
    "wof:placetype": "postalcode"
  },
  "geometry": {"coordinates":[-0.314923,52.643313],"type":"Point"}
}
