{
  "type": "Feature",
  "properties": {
    "iso:country":"GB",
    "wof:name":"BR1 5HW",
    "wof:placetype":"postalcode"
},
  "geometry": {"coordinates":[0.01752044715239,51.43043928120396],"type":"Point"}
}