{
  "type": "Feature",
  "properties": {
    "iso:country":"GB",
    "wof:name":"BD10 8SY",
    "wof:placetype":"postalcode"
},
  "geometry": {"coordinates":[-1.73535888910331,53.82705790507454],"type":"Point"}
}