{
  "type": "Feature",
  "properties": {
    "date:inception_lower":"2002-10-01",
    "date:inception_upper":"2002-10-31",
    "iso:country":"GB",
    "wof:name":"BD10 8SY",
    "wof:placetype":"postalcode"
},
  "geometry": {"coordinates":[-1.735359,53.827058],"type":"Point"}
}