{
  "type": "Feature",
  "properties": {
    "iso:country":"GB",
    "wof:name":"HA1 3BG",
    "wof:placetype":"postalcode"
},
  "geometry": {"coordinates":[-0.3387042930349,51.57622845448537],"type":"Point"}
}