{
  "type": "Feature",
  "properties": {
    "iso:country":"GB",
    "wof:name":"CF83 8QN",
    "wof:placetype":"postalcode"
},
  "geometry": {"coordinates":[-3.15104735751806,51.59590466962222],"type":"Point"}
}