{
  "type": "Feature",
  "properties": {
    "date:inception_lower": "2000-06-01",
    "date:inception_upper": "2000-06-01",
    "iso:country": "GB",
    "wof:name": "DN40 2YD",
    "wof:placetype": "postalcode"
  },
  "geometry": {"coordinates":[-0.203057,53.641422],"type":"Point"}
}
