{
  "type": "Feature",
  "properties": {
    "iso:country":"GB",
    "wof:name":"DN40 2YD",
    "wof:placetype":"postalcode"
},
  "geometry": {"coordinates":[-0.20305654858514,53.6414224990459],"type":"Point"}
}