{
  "type": "Feature",
  "properties": {
    "iso:country": "GB",
    "wof:name": "SW16 2TQ",
    "wof:placetype": "postalcode"
  },
  "geometry": {"coordinates":[-0.12552,51.434325],"type":"Point"}
}
