{
  "type": "Feature",
  "properties": {
    "iso:country": "GB",
    "wof:name": "OX1 2EP",
    "wof:placetype": "postalcode"
  },
  "geometry": {"coordinates":[-1.266065,51.753465],"type":"Point"}
}
