{
  "type": "Feature",
  "properties": {
    "iso:country": "GB",
    "wof:name": "RG25 3FE",
    "wof:placetype": "postalcode"
  },
  "geometry": {"coordinates":[-1.258963,51.24723],"type":"Point"}
}
