{
  "type": "Feature",
  "properties": {
    "iso:country": "GB",
    "wof:name": "HR4 0EN",
    "wof:placetype": "postalcode"
  },
  "geometry": {"coordinates":[-2.730097,52.061548],"type":"Point"}
}
