{
  "type": "Feature",
  "properties": {
    "iso:country":"GB",
    "wof:name":"HR4 0EN",
    "wof:placetype":"postalcode"
},
  "geometry": {"coordinates":[-2.73012314959162,52.06143135415341],"type":"Point"}
}