{
  "type": "Feature",
  "properties": {
    "date:inception_lower":"2011-10-01",
    "date:inception_upper":"2011-10-31",
    "iso:country":"GB",
    "wof:name":"HR4 0EN",
    "wof:placetype":"postalcode"
},
  "geometry": {"coordinates":[-2.730097,52.061548],"type":"Point"}
}