{
  "type": "Feature",
  "properties": {
    "date:inception_lower":"1980-01-01",
    "date:inception_upper":"1980-01-31",
    "iso:country":"GB",
    "wof:name":"TN17 3ES",
    "wof:placetype":"postalcode"
},
  "geometry": {"coordinates":[0.531608,51.096686],"type":"Point"}
}