{
  "type": "Feature",
  "properties": {
    "iso:country":"GB",
    "wof:name":"DH4 6LU",
    "wof:placetype":"postalcode"
},
  "geometry": {"coordinates":[-1.49441082118336,54.83898775481676],"type":"Point"}
}