{
  "type": "Feature",
  "properties": {
    "iso:country":"GB",
    "wof:name":"CF47 8YR",
    "wof:placetype":"postalcode"
},
  "geometry": {"coordinates":[-3.37772741687075,51.75363309348177],"type":"Point"}
}