{
  "type": "Feature",
  "properties": {
    "date:inception_lower": "1980-01-01",
    "date:inception_upper": "1980-01-01",
    "iso:country": "GB",
    "wof:name": "CF47 8YR",
    "wof:placetype": "postalcode"
  },
  "geometry": {"coordinates":[-3.377727,51.753633],"type":"Point"}
}
