{
  "type": "Feature",
  "properties": {
    "date:inception_lower": "1980-01-01",
    "date:inception_upper": "1980-01-01",
    "iso:country": "GB",
    "wof:name": "EN6 1DD",
    "wof:placetype": "postalcode"
  },
  "geometry": {"coordinates":[-0.189421,51.700712],"type":"Point"}
}
