{
  "type": "Feature",
  "properties": {
    "iso:country": "GB",
    "wof:name": "TW11 0EL",
    "wof:placetype": "postalcode"
  },
  "geometry": {"coordinates":[-0.335598,51.421274],"type":"Point"}
}
