{
  "type": "Feature",
  "properties": {
    "iso:country":"GB",
    "wof:name":"CR5 3DB",
    "wof:placetype":"postalcode"
},
  "geometry": {"coordinates":[-0.15088509560314,51.31627622514288],"type":"Point"}
}