{
  "type": "Feature",
  "properties": {
    "iso:country":"GB",
    "wof:name":"BN16 1LQ",
    "wof:placetype":"postalcode"
},
  "geometry": {"coordinates":[-0.47548127951471,50.80874844383557],"type":"Point"}
}