{
  "type": "Feature",
  "properties": {
    "date:inception_lower": "1980-01-01",
    "date:inception_upper": "1980-01-01",
    "iso:country": "GB",
    "wof:name": "BN16 1LQ",
    "wof:placetype": "postalcode"
  },
  "geometry": {"coordinates":[-0.475481,50.808748],"type":"Point"}
}
