{
  "type": "Feature",
  "properties": {
    "date:inception_lower":"1980-01-01",
    "date:inception_upper":"1980-01-31",
    "iso:country":"GB",
    "wof:name":"GL15 5LL",
    "wof:placetype":"postalcode"
},
  "geometry": {"coordinates":[-2.529938,51.731415],"type":"Point"}
}