{
  "type": "Feature",
  "properties": {
    "iso:country":"GB",
    "wof:name":"GL15 5LL",
    "wof:placetype":"postalcode"
},
  "geometry": {"coordinates":[-2.52990785744254,51.73141954252999],"type":"Point"}
}