{
  "type": "Feature",
  "properties": {
    "date:inception_lower":"1994-05-01",
    "date:inception_upper":"1994-05-31",
    "iso:country":"GB",
    "wof:name":"GU11 3PW",
    "wof:placetype":"postalcode"
},
  "geometry": {"coordinates":[-0.769168,51.23906],"type":"Point"}
}