{
  "type": "Feature",
  "properties": {
    "date:inception_lower": "1995-12-01",
    "date:inception_upper": "1995-12-01",
    "iso:country": "GB",
    "wof:name": "M45 8SD",
    "wof:placetype": "postalcode"
  },
  "geometry": {"coordinates":[-2.282156,53.54815],"type":"Point"}
}
