{
  "type": "Feature",
  "properties": {
    "iso:country":"GB",
    "wof:name":"M45 8SD",
    "wof:placetype":"postalcode"
},
  "geometry": {"coordinates":[-2.28215641899437,53.5481503181681],"type":"Point"}
}