{
  "type": "Feature",
  "properties": {
    "iso:country":"GB",
    "wof:name":"WA7 1BH",
    "wof:placetype":"postalcode"
},
  "geometry": {"coordinates":[-2.72937368745744,53.34073146913041],"type":"Point"}
}