{
  "type": "Feature",
  "properties": {
    "iso:country":"GB",
    "wof:name":"ST6 4QP",
    "wof:placetype":"postalcode"
},
  "geometry": {"coordinates":[-2.23917290569025,53.07593218139025],"type":"Point"}
}