{
  "type": "Feature",
  "properties": {
    "iso:country":"GB",
    "wof:name":"TS5 6AS",
    "wof:placetype":"postalcode"
},
  "geometry": {"coordinates":[-1.24525441851949,54.5631196934546],"type":"Point"}
}