{
  "type": "Feature",
  "properties": {
    "iso:country":"GB",
    "wof:name":"DG7 3UG",
    "wof:placetype":"postalcode"
},
  "geometry": {"coordinates":[-4.10667261699352,55.18599300120882],"type":"Point"}
}