{
  "type": "Feature",
  "properties": {
    "iso:country":"GB",
    "wof:name":"LN10 6AG",
    "wof:placetype":"postalcode"
},
  "geometry": {"coordinates":[-0.18668415002139,53.16041620495981],"type":"Point"}
}