{
  "type": "Feature",
  "properties": {
    "iso:country": "GB",
    "wof:name": "LN10 6AG",
    "wof:placetype": "postalcode"
  },
  "geometry": {"coordinates":[-0.186133,53.160657],"type":"Point"}
}
