{
  "type": "Feature",
  "properties": {
    "iso:country":"GB",
    "wof:name":"SA19 8ER",
    "wof:placetype":"postalcode"
},
  "geometry": {"coordinates":[-3.8584198468819,51.98384504678263],"type":"Point"}
}