{
  "type": "Feature",
  "properties": {
    "iso:country": "GB",
    "wof:name": "SA19 8ER",
    "wof:placetype": "postalcode"
  },
  "geometry": {"coordinates":[-3.85842,51.983845],"type":"Point"}
}
