{
  "type": "Feature",
  "properties": {
    "date:inception_lower": "1980-01-01",
    "date:inception_upper": "1980-01-01",
    "iso:country": "GB",
    "wof:name": "NG9 7HD",
    "wof:placetype": "postalcode"
  },
  "geometry": {"coordinates":[-1.272588,52.929187],"type":"Point"}
}
