{
  "type": "Feature",
  "properties": {
    "iso:country":"GB",
    "wof:name":"DY8 1UX",
    "wof:placetype":"postalcode"
},
  "geometry": {"coordinates":[-2.15236952969933,52.45991502942601],"type":"Point"}
}