{
  "type": "Feature",
  "properties": {
    "date:inception_lower": "2002-10-01",
    "date:inception_upper": "2002-10-01",
    "iso:country": "GB",
    "wof:name": "NE46 3HJ",
    "wof:placetype": "postalcode"
  },
  "geometry": {"coordinates":[-2.104395,54.97681],"type":"Point"}
}
