{
  "type": "Feature",
  "properties": {
    "iso:country":"GB",
    "wof:name":"SO45 1WX",
    "wof:placetype":"postalcode"
},
  "geometry": {"coordinates":[-1.36904434645638,50.81522066287572],"type":"Point"}
}