{
  "type": "Feature",
  "properties": {
    "date:inception_lower": "1994-12-01",
    "date:inception_upper": "1994-12-01",
    "iso:country": "GB",
    "wof:name": "SO45 1WX",
    "wof:placetype": "postalcode"
  },
  "geometry": {"coordinates":[-1.369134,50.815203],"type":"Point"}
}
