{
  "type": "Feature",
  "properties": {
    "iso:country":"GB",
    "wof:name":"SN14 6FD",
    "wof:placetype":"postalcode"
},
  "geometry": {"coordinates":[-2.15062039278633,51.53772282551538],"type":"Point"}
}