{
  "type": "Feature",
  "properties": {
    "date:inception_lower": "2016-02-01",
    "date:inception_upper": "2016-02-01",
    "iso:country": "GB",
    "wof:name": "SN14 6FD",
    "wof:placetype": "postalcode"
  },
  "geometry": {"coordinates":[-2.150471,51.537606],"type":"Point"}
}
