{
  "type": "Feature",
  "properties": {
    "iso:country": "GB",
    "wof:name": "PL28 8JQ",
    "wof:placetype": "postalcode"
  },
  "geometry": {"coordinates":[-5.010923,50.530175],"type":"Point"}
}
