{
  "type": "Feature",
  "properties": {
    "iso:country":"GB",
    "wof:name":"PL28 8JQ",
    "wof:placetype":"postalcode"
},
  "geometry": {"coordinates":[-5.01092334575907,50.53017537838357],"type":"Point"}
}