{
  "type": "Feature",
  "properties": {
    "date:inception_lower":"1980-01-01",
    "date:inception_upper":"1980-01-31",
    "iso:country":"GB",
    "wof:name":"PL28 8JQ",
    "wof:placetype":"postalcode"
},
  "geometry": {"coordinates":[-5.010923,50.530175],"type":"Point"}
}