{
  "type": "Feature",
  "properties": {
    "iso:country":"GB",
    "wof:name":"NR1 3QS",
    "wof:placetype":"postalcode"
},
  "geometry": {"coordinates":[1.30251377006899,52.61648867517351],"type":"Point"}
}