{
  "type": "Feature",
  "properties": {
    "date:inception_lower":"2015-12-01",
    "date:inception_upper":"2015-12-31",
    "iso:country":"GB",
    "wof:name":"NR1 3QS",
    "wof:placetype":"postalcode"
},
  "geometry": {"coordinates":[1.302534,52.616073],"type":"Point"}
}