{
  "type": "Feature",
  "properties": {
    "iso:country": "GB",
    "wof:name": "NR1 3QS",
    "wof:placetype": "postalcode"
  },
  "geometry": {"coordinates":[1.302534,52.616073],"type":"Point"}
}
