{
  "type": "Feature",
  "properties": {
    "iso:country": "GB",
    "wof:name": "CA14 4HY",
    "wof:placetype": "postalcode"
  },
  "geometry": {"coordinates":[-3.540022,54.628146],"type":"Point"}
}
