{
  "type": "Feature",
  "properties": {
    "iso:country":"GB",
    "wof:name":"WA12 9JG",
    "wof:placetype":"postalcode"
},
  "geometry": {"coordinates":[-2.62558208109582,53.45492030739867],"type":"Point"}
}