{
  "type": "Feature",
  "properties": {
    "date:inception_lower": "1992-08-01",
    "date:inception_upper": "1992-08-01",
    "iso:country": "GB",
    "wof:name": "WA12 9JG",
    "wof:placetype": "postalcode"
  },
  "geometry": {"coordinates":[-2.625582,53.45492],"type":"Point"}
}
