{
  "type": "Feature",
  "properties": {
    "iso:country": "GB",
    "wof:name": "WA12 9JG",
    "wof:placetype": "postalcode"
  },
  "geometry": {"coordinates":[-2.625582,53.45492],"type":"Point"}
}
