{
  "type": "Feature",
  "properties": {
    "date:inception_lower": "1986-07-01",
    "date:inception_upper": "1986-07-01",
    "iso:country": "GB",
    "wof:name": "TA20 1DT",
    "wof:placetype": "postalcode"
  },
  "geometry": {"coordinates":[-2.967827,50.878637],"type":"Point"}
}
