{
  "type": "Feature",
  "properties": {
    "iso:country":"GB",
    "wof:name":"TA20 1DT",
    "wof:placetype":"postalcode"
},
  "geometry": {"coordinates":[-2.96782700914874,50.87863680306477],"type":"Point"}
}