{
  "type": "Feature",
  "properties": {
    "iso:country":"GB",
    "wof:name":"TQ2 5AL",
    "wof:placetype":"postalcode"
},
  "geometry": {"coordinates":[-3.54101121795757,50.46906769430002],"type":"Point"}
}