{
  "type": "Feature",
  "properties": {
    "iso:country":"GB",
    "wof:name":"W5 3SN",
    "wof:placetype":"postalcode"
},
  "geometry": {"coordinates":[-0.29894046953356,51.51138194022704],"type":"Point"}
}