{
  "type": "Feature",
  "properties": {
    "date:inception_lower": "2002-06-01",
    "date:inception_upper": "2002-06-01",
    "iso:country": "GB",
    "wof:name": "EN3 6TA",
    "wof:placetype": "postalcode"
  },
  "geometry": {"coordinates":[-0.015243,51.668233],"type":"Point"}
}
