{
  "type": "Feature",
  "properties": {
    "date:inception_lower":"2018-06-01",
    "date:inception_upper":"2018-06-30",
    "iso:country":"GB",
    "wof:name":"E14 9FZ",
    "wof:placetype":"postalcode"
},
  "geometry": {"coordinates":[-0.019174,51.49808],"type":"Point"}
}