{
  "type": "Feature",
  "properties": {
    "iso:country": "GB",
    "wof:name": "RH6 9HP",
    "wof:placetype": "postalcode"
  },
  "geometry": {"coordinates":[-0.16066,51.171124],"type":"Point"}
}
