{
  "type": "Feature",
  "properties": {
    "iso:country":"GB",
    "wof:name":"KT14 7SZ",
    "wof:placetype":"postalcode"
},
  "geometry": {"coordinates":[-0.47050031846011,51.3309490708543],"type":"Point"}
}