{
  "type": "Feature",
  "properties": {
    "iso:country": "GB",
    "wof:name": "KT14 7SZ",
    "wof:placetype": "postalcode"
  },
  "geometry": {"coordinates":[-0.4705,51.330949],"type":"Point"}
}
