{
  "type": "Feature",
  "properties": {
    "date:inception_lower":"2002-05-01",
    "date:inception_upper":"2002-05-31",
    "iso:country":"GB",
    "wof:name":"HR9 7FB",
    "wof:placetype":"postalcode"
},
  "geometry": {"coordinates":[-2.460502,51.931555],"type":"Point"}
}