{
  "type": "Feature",
  "properties": {
    "iso:country": "GB",
    "wof:name": "HR9 7FB",
    "wof:placetype": "postalcode"
  },
  "geometry": {"coordinates":[-2.460502,51.931555],"type":"Point"}
}
