{
  "type": "Feature",
  "properties": {
    "iso:country":"GB",
    "wof:name":"HR9 7FB",
    "wof:placetype":"postalcode"
},
  "geometry": {"coordinates":[-2.46014290521156,51.9319256089988],"type":"Point"}
}