{
  "type": "Feature",
  "properties": {
    "iso:country": "GB",
    "wof:name": "CF37 1EU",
    "wof:placetype": "postalcode"
  },
  "geometry": {"coordinates":[-3.357401,51.60324],"type":"Point"}
}
