{
  "type": "Feature",
  "properties": {
    "iso:country":"GB",
    "wof:name":"CF37 1EU",
    "wof:placetype":"postalcode"
},
  "geometry": {"coordinates":[-3.35740133115386,51.60323953692508],"type":"Point"}
}