{
  "type": "Feature",
  "properties": {
    "iso:country":"GB",
    "wof:name":"DD2 4JY",
    "wof:placetype":"postalcode"
},
  "geometry": {"coordinates":[-3.03150962543257,56.47655460321609],"type":"Point"}
}