{
  "type": "Feature",
  "properties": {
    "iso:country":"GB",
    "wof:name":"SA4 6UH",
    "wof:placetype":"postalcode"
},
  "geometry": {"coordinates":[-4.06859057849379,51.66494194451165],"type":"Point"}
}