{
  "type": "Feature",
  "properties": {
    "iso:country":"GB",
    "wof:name":"PA3 3FG",
    "wof:placetype":"postalcode"
},
  "geometry": {"coordinates":[-4.47250099748811,55.84110756457963],"type":"Point"}
}