{
  "type": "Feature",
  "properties": {
    "date:inception_lower": "2013-11-01",
    "date:inception_upper": "2013-11-01",
    "iso:country": "GB",
    "wof:name": "PA3 3FG",
    "wof:placetype": "postalcode"
  },
  "geometry": {"coordinates":[-4.472501,55.841108],"type":"Point"}
}
