{
  "type": "Feature",
  "properties": {
    "iso:country":"GB",
    "wof:name":"NP7 5DQ",
    "wof:placetype":"postalcode"
},
  "geometry": {"coordinates":[-3.02413719164989,51.82297361313655],"type":"Point"}
}