{
  "type": "Feature",
  "properties": {
    "iso:country": "GB",
    "wof:name": "NP7 5DQ",
    "wof:placetype": "postalcode"
  },
  "geometry": {"coordinates":[-3.024137,51.822974],"type":"Point"}
}
