{
  "type": "Feature",
  "properties": {
    "iso:country":"GB",
    "wof:name":"M46 0EQ",
    "wof:placetype":"postalcode"
},
  "geometry": {"coordinates":[-2.49137300150043,53.52398649016455],"type":"Point"}
}