{
  "type": "Feature",
  "properties": {
    "iso:country":"GB",
    "wof:name":"SR5 4HJ",
    "wof:placetype":"postalcode"
},
  "geometry": {"coordinates":[-1.4517638785035,54.92860453703815],"type":"Point"}
}