{
  "type": "Feature",
  "properties": {
    "iso:country":"GB",
    "wof:name":"GL14 2WW",
    "wof:placetype":"postalcode"
},
  "geometry": {"coordinates":[-2.49811979580934,51.82306123095445],"type":"Point"}
}