{
  "type": "Feature",
  "properties": {
    "date:inception_lower":"1992-05-01",
    "date:inception_upper":"1992-05-31",
    "iso:country":"GB",
    "wof:name":"EH17 8UE",
    "wof:placetype":"postalcode"
},
  "geometry": {"coordinates":[-3.146493,55.898748],"type":"Point"}
}