{
  "type": "Feature",
  "properties": {
    "iso:country":"GB",
    "wof:name":"EH17 8UE",
    "wof:placetype":"postalcode"
},
  "geometry": {"coordinates":[-3.14649280770061,55.89874827037002],"type":"Point"}
}