{
  "type": "Feature",
  "properties": {
    "iso:country":"GB",
    "wof:name":"NE65 8DT",
    "wof:placetype":"postalcode"
},
  "geometry": {"coordinates":[-1.79662283674507,55.30632701507928],"type":"Point"}
}