{
  "type": "Feature",
  "properties": {
    "iso:country":"GB",
    "wof:name":"SO18 1FZ",
    "wof:placetype":"postalcode"
},
  "geometry": {"coordinates":[-1.37643548778545,50.92423206008968],"type":"Point"}
}