{
  "type": "Feature",
  "properties": {
    "date:inception_lower":"1994-12-01",
    "date:inception_upper":"1994-12-31",
    "iso:country":"GB",
    "wof:name":"SO18 1FZ",
    "wof:placetype":"postalcode"
},
  "geometry": {"coordinates":[-1.376313,50.924168],"type":"Point"}
}