{
  "type": "Feature",
  "properties": {
    "iso:country": "GB",
    "wof:name": "RG40 4HN",
    "wof:placetype": "postalcode"
  },
  "geometry": {"coordinates":[-0.859347,51.384262],"type":"Point"}
}
