{
  "type": "Feature",
  "properties": {
    "date:inception_lower":"1995-07-01",
    "date:inception_upper":"1995-07-31",
    "iso:country":"GB",
    "wof:name":"RG40 4HN",
    "wof:placetype":"postalcode"
},
  "geometry": {"coordinates":[-0.859347,51.384262],"type":"Point"}
}