{
  "type": "Feature",
  "properties": {
    "iso:country":"GB",
    "wof:name":"RG40 4HN",
    "wof:placetype":"postalcode"
},
  "geometry": {"coordinates":[-0.85934685813156,51.38426159718566],"type":"Point"}
}