{
  "type": "Feature",
  "properties": {
    "iso:country":"GB",
    "wof:name":"ME6 5NQ",
    "wof:placetype":"postalcode"
},
  "geometry": {"coordinates":[0.44611509802763,51.32939207998056],"type":"Point"}
}