{
  "type": "Feature",
  "properties": {
    "date:inception_lower": "1984-10-01",
    "date:inception_upper": "1984-10-01",
    "iso:country": "GB",
    "wof:name": "ME6 5NQ",
    "wof:placetype": "postalcode"
  },
  "geometry": {"coordinates":[0.446115,51.329392],"type":"Point"}
}
