{
  "type": "Feature",
  "properties": {
    "iso:country":"GB",
    "wof:name":"SO21 2EY",
    "wof:placetype":"postalcode"
},
  "geometry": {"coordinates":[-1.3405598337536,51.01028125642897],"type":"Point"}
}