{
  "type": "Feature",
  "properties": {
    "iso:country": "GB",
    "wof:name": "SO21 2EY",
    "wof:placetype": "postalcode"
  },
  "geometry": {"coordinates":[-1.34056,51.010281],"type":"Point"}
}
