{
  "type": "Feature",
  "properties": {
    "iso:country":"GB",
    "wof:name":"LU7 0RR",
    "wof:placetype":"postalcode"
},
  "geometry": {"coordinates":[-0.66991056355035,51.84545240938195],"type":"Point"}
}