{
  "type": "Feature",
  "properties": {
    "iso:country": "GB",
    "wof:name": "LU7 0RR",
    "wof:placetype": "postalcode"
  },
  "geometry": {"coordinates":[-0.669911,51.845452],"type":"Point"}
}
