{
  "type": "Feature",
  "properties": {
    "iso:country": "GB",
    "wof:name": "HR6 0BY",
    "wof:placetype": "postalcode"
  },
  "geometry": {"coordinates":[-2.755626,52.251569],"type":"Point"}
}
