{
  "type": "Feature",
  "properties": {
    "iso:country":"GB",
    "wof:name":"AB41 8UG",
    "wof:placetype":"postalcode"
},
  "geometry": {"coordinates":[-2.08552418739617,57.46852082046569],"type":"Point"}
}