{
  "type": "Feature",
  "properties": {
    "iso:country":"GB",
    "wof:name":"BA5 2XP",
    "wof:placetype":"postalcode"
},
  "geometry": {"coordinates":[-2.63608604902301,51.21177869942245],"type":"Point"}
}