{
  "type": "Feature",
  "properties": {
    "iso:country": "GB",
    "wof:name": "PL7 1SU",
    "wof:placetype": "postalcode"
  },
  "geometry": {"coordinates":[-4.060866,50.386192],"type":"Point"}
}
