{
  "type": "Feature",
  "properties": {
    "iso:country":"GB",
    "wof:name":"BH23 6AG",
    "wof:placetype":"postalcode"
},
  "geometry": {"coordinates":[-1.78728693704166,50.75256072787993],"type":"Point"}
}