{
  "type": "Feature",
  "properties": {
    "date:inception_lower": "1980-01-01",
    "date:inception_upper": "1980-01-01",
    "iso:country": "GB",
    "wof:name": "BH23 6AG",
    "wof:placetype": "postalcode"
  },
  "geometry": {"coordinates":[-1.787576,50.752901],"type":"Point"}
}
