{
  "type": "Feature",
  "properties": {
    "date:inception_lower": "2002-05-01",
    "date:inception_upper": "2002-05-01",
    "iso:country": "GB",
    "wof:name": "IG8 7GL",
    "wof:placetype": "postalcode"
  },
  "geometry": {"coordinates":[0.043131,51.608276],"type":"Point"}
}
