{
  "type": "Feature",
  "properties": {
    "iso:country": "GB",
    "wof:name": "SS11 8PU",
    "wof:placetype": "postalcode"
  },
  "geometry": {"coordinates":[0.542977,51.609328],"type":"Point"}
}
