{
  "type": "Feature",
  "properties": {
    "iso:country":"GB",
    "wof:name":"SS11 8PU",
    "wof:placetype":"postalcode"
},
  "geometry": {"coordinates":[0.54297669075285,51.60932812970461],"type":"Point"}
}