{
  "type": "Feature",
  "properties": {
    "iso:country":"GB",
    "wof:name":"CF39 8RS",
    "wof:placetype":"postalcode"
},
  "geometry": {"coordinates":[-3.47818161905224,51.59541401309811],"type":"Point"}
}