{
  "type": "Feature",
  "properties": {
    "iso:country": "GB",
    "wof:name": "NG17 9GR",
    "wof:placetype": "postalcode"
  },
  "geometry": {"coordinates":[-1.264783,53.08247],"type":"Point"}
}
