{
  "type": "Feature",
  "properties": {
    "date:inception_lower": "1980-01-01",
    "date:inception_upper": "1980-01-01",
    "iso:country": "GB",
    "wof:name": "SN13 0AN",
    "wof:placetype": "postalcode"
  },
  "geometry": {"coordinates":[-2.193796,51.435344],"type":"Point"}
}
