{
  "type": "Feature",
  "properties": {
    "iso:country":"GB",
    "wof:name":"SN13 0AN",
    "wof:placetype":"postalcode"
},
  "geometry": {"coordinates":[-2.19379999179179,51.43534512013038],"type":"Point"}
}