{
  "type": "Feature",
  "properties": {
    "iso:country":"GB",
    "wof:name":"BB1 2DR",
    "wof:placetype":"postalcode"
},
  "geometry": {"coordinates":[-2.4337645371112,53.7446649834077],"type":"Point"}
}