{
  "type": "Feature",
  "properties": {
    "iso:country": "GB",
    "wof:name": "BB1 2DR",
    "wof:placetype": "postalcode"
  },
  "geometry": {"coordinates":[-2.433764,53.744665],"type":"Point"}
}
