{
  "type": "Feature",
  "properties": {
    "date:inception_lower":"1980-01-01",
    "date:inception_upper":"1980-01-31",
    "iso:country":"GB",
    "wof:name":"BB1 2DR",
    "wof:placetype":"postalcode"
},
  "geometry": {"coordinates":[-2.433764,53.744665],"type":"Point"}
}