{
  "type": "Feature",
  "properties": {
    "iso:country": "GB",
    "wof:name": "WS15 3LG",
    "wof:placetype": "postalcode"
  },
  "geometry": {"coordinates":[-1.923438,52.78424],"type":"Point"}
}
