{
  "type": "Feature",
  "properties": {
    "iso:country":"GB",
    "wof:name":"WS15 3LG",
    "wof:placetype":"postalcode"
},
  "geometry": {"coordinates":[-1.9234377579914,52.78423992447478],"type":"Point"}
}