{
  "type": "Feature",
  "properties": {
    "iso:country":"GB",
    "wof:name":"DE7 5QT",
    "wof:placetype":"postalcode"
},
  "geometry": {"coordinates":[-1.3089194335501,52.96916386629002],"type":"Point"}
}