{
  "type": "Feature",
  "properties": {
    "iso:country": "GB",
    "wof:name": "MK43 7QT",
    "wof:placetype": "postalcode"
  },
  "geometry": {"coordinates":[-0.557912,52.169953],"type":"Point"}
}
