{
  "type": "Feature",
  "properties": {
    "iso:country":"GB",
    "wof:name":"KA12 9BN",
    "wof:placetype":"postalcode"
},
  "geometry": {"coordinates":[-4.6736545615211,55.63025799872749],"type":"Point"}
}