{
  "type": "Feature",
  "properties": {
    "iso:country":"GB",
    "wof:name":"YO61 1TW",
    "wof:placetype":"postalcode"
},
  "geometry": {"coordinates":[-1.23159020136677,54.08992706155613],"type":"Point"}
}