{
  "type": "Feature",
  "properties": {
    "iso:country": "GB",
    "wof:name": "YO61 1TW",
    "wof:placetype": "postalcode"
  },
  "geometry": {"coordinates":[-1.23159,54.089927],"type":"Point"}
}
