{
  "type": "Feature",
  "properties": {
    "iso:country":"GB",
    "wof:name":"IG2 6LA",
    "wof:placetype":"postalcode"
},
  "geometry": {"coordinates":[0.07004443273701,51.5776343334454],"type":"Point"}
}