{
  "type": "Feature",
  "properties": {
    "iso:country":"GB",
    "wof:name":"G67 2RN",
    "wof:placetype":"postalcode"
},
  "geometry": {"coordinates":[-3.98943201551867,55.93020391867234],"type":"Point"}
}