{
  "type": "Feature",
  "properties": {
    "date:inception_lower": "1980-01-01",
    "date:inception_upper": "1980-01-01",
    "iso:country": "GB",
    "wof:name": "IG8 9QS",
    "wof:placetype": "postalcode"
  },
  "geometry": {"coordinates":[0.018924,51.610262],"type":"Point"}
}
