{
  "type": "Feature",
  "properties": {
    "iso:country": "GB",
    "wof:name": "IG8 9QS",
    "wof:placetype": "postalcode"
  },
  "geometry": {"coordinates":[0.018935,51.610189],"type":"Point"}
}
