{
  "type": "Feature",
  "properties": {
    "iso:country":"GB",
    "wof:name":"SW20 9ET",
    "wof:placetype":"postalcode"
},
  "geometry": {"coordinates":[-0.21259063711533,51.40556899035644],"type":"Point"}
}