{
  "type": "Feature",
  "properties": {
    "iso:country":"GB",
    "wof:name":"MK7 7LN",
    "wof:placetype":"postalcode"
},
  "geometry": {"coordinates":[-0.69673948202505,52.02214499181189],"type":"Point"}
}