{
  "type": "Feature",
  "properties": {
    "iso:country": "GB",
    "wof:name": "ST17 9XW",
    "wof:placetype": "postalcode"
  },
  "geometry": {"coordinates":[-2.137007,52.796087],"type":"Point"}
}
