{
  "type": "Feature",
  "properties": {
    "iso:country": "GB",
    "wof:name": "CV2 5JS",
    "wof:placetype": "postalcode"
  },
  "geometry": {"coordinates":[-1.463658,52.407285],"type":"Point"}
}
