{
  "type": "Feature",
  "properties": {
    "date:inception_lower": "1980-01-01",
    "date:inception_upper": "1980-01-01",
    "iso:country": "GB",
    "wof:name": "CV2 5JS",
    "wof:placetype": "postalcode"
  },
  "geometry": {"coordinates":[-1.463658,52.407285],"type":"Point"}
}
