{
  "type": "Feature",
  "properties": {
    "iso:country":"GB",
    "wof:name":"RH13 8GL",
    "wof:placetype":"postalcode"
},
  "geometry": {"coordinates":[-0.38247791788871,51.00963416428835],"type":"Point"}
}