{
  "type": "Feature",
  "properties": {
    "date:inception_lower": "2002-06-01",
    "date:inception_upper": "2002-06-01",
    "iso:country": "GB",
    "wof:name": "RH13 8GL",
    "wof:placetype": "postalcode"
  },
  "geometry": {"coordinates":[-0.382478,51.009634],"type":"Point"}
}
