{
  "type": "Feature",
  "properties": {
    "date:inception_lower": "1980-01-01",
    "date:inception_upper": "1980-01-01",
    "iso:country": "GB",
    "wof:name": "KY11 1DZ",
    "wof:placetype": "postalcode"
  },
  "geometry": {"coordinates":[-3.389901,56.029912],"type":"Point"}
}
