{
  "type": "Feature",
  "properties": {
    "iso:country":"GB",
    "wof:name":"ML11 9RD",
    "wof:placetype":"postalcode"
},
  "geometry": {"coordinates":[-3.91407095049647,55.66599963522538],"type":"Point"}
}