{
  "type": "Feature",
  "properties": {
    "date:inception_lower":"1997-06-01",
    "date:inception_upper":"1997-06-30",
    "iso:country":"GB",
    "wof:name":"LE14 4NL",
    "wof:placetype":"postalcode"
},
  "geometry": {"coordinates":[-0.919447,52.840739],"type":"Point"}
}