{
  "type": "Feature",
  "properties": {
    "iso:country":"GB",
    "wof:name":"LE14 4NL",
    "wof:placetype":"postalcode"
},
  "geometry": {"coordinates":[-0.91944747397165,52.84073861021541],"type":"Point"}
}