{
  "type": "Feature",
  "properties": {
    "iso:country":"GB",
    "wof:name":"L20 0BN",
    "wof:placetype":"postalcode"
},
  "geometry": {"coordinates":[-2.9778782217893,53.45851508286191],"type":"Point"}
}