{
  "type": "Feature",
  "properties": {
    "iso:country": "GB",
    "wof:name": "L20 0BN",
    "wof:placetype": "postalcode"
  },
  "geometry": {"coordinates":[-2.977878,53.458515],"type":"Point"}
}
