{
  "type": "Feature",
  "properties": {
    "date:inception_lower": "1980-01-01",
    "date:inception_upper": "1980-01-01",
    "iso:country": "GB",
    "wof:name": "RG27 0PE",
    "wof:placetype": "postalcode"
  },
  "geometry": {"coordinates":[-0.853853,51.339553],"type":"Point"}
}
