{
  "type": "Feature",
  "properties": {
    "iso:country": "GB",
    "wof:name": "RG27 0PE",
    "wof:placetype": "postalcode"
  },
  "geometry": {"coordinates":[-0.853853,51.339553],"type":"Point"}
}
