{
  "type": "Feature",
  "properties": {
    "iso:country": "GB",
    "wof:name": "TS6 8HG",
    "wof:placetype": "postalcode"
  },
  "geometry": {"coordinates":[-1.136745,54.563392],"type":"Point"}
}
