{
  "type": "Feature",
  "properties": {
    "iso:country": "GB",
    "wof:name": "GU17 9FH",
    "wof:placetype": "postalcode"
  },
  "geometry": {"coordinates":[-0.792595,51.306027],"type":"Point"}
}
