{
  "type": "Feature",
  "properties": {
    "iso:country":"GB",
    "wof:name":"GU1 3PT",
    "wof:placetype":"postalcode"
},
  "geometry": {"coordinates":[-0.56588311703295,51.23381471181904],"type":"Point"}
}