{
  "type": "Feature",
  "properties": {
    "date:inception_lower": "1980-01-01",
    "date:inception_upper": "1980-01-01",
    "iso:country": "GB",
    "wof:name": "GU1 3PT",
    "wof:placetype": "postalcode"
  },
  "geometry": {"coordinates":[-0.565883,51.233815],"type":"Point"}
}
