{
  "type": "Feature",
  "properties": {
    "iso:country":"GB",
    "wof:name":"NE21 5QJ",
    "wof:placetype":"postalcode"
},
  "geometry": {"coordinates":[-1.72179583579553,54.95675026246884],"type":"Point"}
}