{
  "type": "Feature",
  "properties": {
    "iso:country":"GB",
    "wof:name":"BH7 6QA",
    "wof:placetype":"postalcode"
},
  "geometry": {"coordinates":[-1.82311043031507,50.73697328603622],"type":"Point"}
}