{
  "type": "Feature",
  "properties": {
    "iso:country":"GB",
    "wof:name":"CH65 2HE",
    "wof:placetype":"postalcode"
},
  "geometry": {"coordinates":[-2.90381648177178,53.28927083001392],"type":"Point"}
}