{
  "type": "Feature",
  "properties": {
    "iso:country":"GB",
    "wof:name":"SS0 8LS",
    "wof:placetype":"postalcode"
},
  "geometry": {"coordinates":[0.68264231530221,51.54301113632487],"type":"Point"}
}