{
  "type": "Feature",
  "properties": {
    "date:inception_lower": "1990-02-01",
    "date:inception_upper": "1990-02-01",
    "iso:country": "GB",
    "wof:name": "ME8 6LJ",
    "wof:placetype": "postalcode"
  },
  "geometry": {"coordinates":[0.580948,51.375972],"type":"Point"}
}
