{
  "type": "Feature",
  "properties": {
    "iso:country":"GB",
    "wof:name":"ME8 6LJ",
    "wof:placetype":"postalcode"
},
  "geometry": {"coordinates":[0.58094783227897,51.37597160508452],"type":"Point"}
}