{
  "type": "Feature",
  "properties": {
    "iso:country":"GB",
    "wof:name":"N14 5PA",
    "wof:placetype":"postalcode"
},
  "geometry": {"coordinates":[-0.12931298545243,51.63315560285699],"type":"Point"}
}