{
  "type": "Feature",
  "properties": {
    "iso:country":"GB",
    "wof:name":"NR16 2HG",
    "wof:placetype":"postalcode"
},
  "geometry": {"coordinates":[1.02579350871598,52.44863698606869],"type":"Point"}
}