{
  "type": "Feature",
  "properties": {
    "iso:country":"GB",
    "wof:name":"TA6 6NZ",
    "wof:placetype":"postalcode"
},
  "geometry": {"coordinates":[-3.02290817374768,51.09125458995592],"type":"Point"}
}