{
  "type": "Feature",
  "properties": {
    "iso:country":"GB",
    "wof:name":"UB2 4BT",
    "wof:placetype":"postalcode"
},
  "geometry": {"coordinates":[-0.37759764180661,51.50160663275993],"type":"Point"}
}