{
  "type": "Feature",
  "properties": {
    "date:inception_lower":"2004-08-01",
    "date:inception_upper":"2004-08-31",
    "iso:country":"GB",
    "wof:name":"SA18 3UH",
    "wof:placetype":"postalcode"
},
  "geometry": {"coordinates":[-4.02049,51.781915],"type":"Point"}
}