{
  "type": "Feature",
  "properties": {
    "iso:country":"GB",
    "wof:name":"SA18 3UH",
    "wof:placetype":"postalcode"
},
  "geometry": {"coordinates":[-4.02045665369666,51.78193525750392],"type":"Point"}
}