{
  "type": "Feature",
  "properties": {
    "iso:country": "GB",
    "wof:name": "SA18 3UH",
    "wof:placetype": "postalcode"
  },
  "geometry": {"coordinates":[-4.02049,51.781915],"type":"Point"}
}
