{
  "type": "Feature",
  "properties": {
    "iso:country":"GB",
    "wof:name":"PA4 0XW",
    "wof:placetype":"postalcode"
},
  "geometry": {"coordinates":[-4.37365296176648,55.86747502050213],"type":"Point"}
}