{
  "type": "Feature",
  "properties": {
    "iso:country":"GB",
    "wof:name":"MK3 5PL",
    "wof:placetype":"postalcode"
},
  "geometry": {"coordinates":[-0.74396607845684,51.97299040413463],"type":"Point"}
}