{
  "type": "Feature",
  "properties": {
    "iso:country": "GB",
    "wof:name": "MK3 5PL",
    "wof:placetype": "postalcode"
  },
  "geometry": {"coordinates":[-0.744678,51.974356],"type":"Point"}
}
