{
  "type": "Feature",
  "properties": {
    "date:inception_lower": "1980-01-01",
    "date:inception_upper": "1980-01-01",
    "iso:country": "GB",
    "wof:name": "PR8 3EQ",
    "wof:placetype": "postalcode"
  },
  "geometry": {"coordinates":[-3.014842,53.614485],"type":"Point"}
}
