{
  "type": "Feature",
  "properties": {
    "iso:country":"GB",
    "wof:name":"PR8 3EQ",
    "wof:placetype":"postalcode"
},
  "geometry": {"coordinates":[-3.01484206101907,53.61448539028271],"type":"Point"}
}