{
  "type": "Feature",
  "properties": {
    "iso:country":"GB",
    "wof:name":"OL1 3JL",
    "wof:placetype":"postalcode"
},
  "geometry": {"coordinates":[-2.10677836017571,53.55170760746618],"type":"Point"}
}