{
  "type": "Feature",
  "properties": {
    "iso:country":"GB",
    "wof:name":"SW9 9TN",
    "wof:placetype":"postalcode"
},
  "geometry": {"coordinates":[-0.1174020149647,51.46729670830761],"type":"Point"}
}