{
  "type": "Feature",
  "properties": {
    "iso:country":"GB",
    "wof:name":"HA8 7PY",
    "wof:placetype":"postalcode"
},
  "geometry": {"coordinates":[-0.28121989112808,51.61570383797725],"type":"Point"}
}