{
  "type": "Feature",
  "properties": {
    "iso:country":"GB",
    "wof:name":"W14 0HP",
    "wof:placetype":"postalcode"
},
  "geometry": {"coordinates":[-0.21792087271141,51.49770644774502],"type":"Point"}
}