{
  "type": "Feature",
  "properties": {
    "iso:country":"GB",
    "wof:name":"CA7 2JP",
    "wof:placetype":"postalcode"
},
  "geometry": {"coordinates":[-3.30185118490302,54.7304494123555],"type":"Point"}
}