{
  "type": "Feature",
  "properties": {
    "iso:country": "GB",
    "wof:name": "IP9 1RL",
    "wof:placetype": "postalcode"
  },
  "geometry": {"coordinates":[1.266002,51.960172],"type":"Point"}
}
