{
  "type": "Feature",
  "properties": {
    "iso:country":"GB",
    "wof:name":"IP9 1RL",
    "wof:placetype":"postalcode"
},
  "geometry": {"coordinates":[1.26600205411181,51.96017185120171],"type":"Point"}
}