{
  "type": "Feature",
  "properties": {
    "date:inception_lower": "1990-02-01",
    "date:inception_upper": "1990-02-01",
    "iso:country": "GB",
    "wof:name": "IP9 1RL",
    "wof:placetype": "postalcode"
  },
  "geometry": {"coordinates":[1.266148,51.960173],"type":"Point"}
}
