{
  "type": "Feature",
  "properties": {
    "date:inception_lower": "1980-01-01",
    "date:inception_upper": "1980-01-01",
    "iso:country": "GB",
    "wof:name": "EN3 5PZ",
    "wof:placetype": "postalcode"
  },
  "geometry": {"coordinates":[-0.039244,51.66467],"type":"Point"}
}
