{
  "type": "Feature",
  "properties": {
    "iso:country":"GB",
    "wof:name":"M3 5HX",
    "wof:placetype":"postalcode"
},
  "geometry": {"coordinates":[-2.26047224080627,53.48237743254657],"type":"Point"}
}