{
  "type": "Feature",
  "properties": {
    "iso:country":"GB",
    "wof:name":"ME15 9WU",
    "wof:placetype":"postalcode"
},
  "geometry": {"coordinates":[0.5487452712474,51.24422669015426],"type":"Point"}
}