{
  "type": "Feature",
  "properties": {
    "date:inception_lower":"2011-06-01",
    "date:inception_upper":"2011-06-30",
    "iso:country":"GB",
    "wof:name":"ME15 9WU",
    "wof:placetype":"postalcode"
},
  "geometry": {"coordinates":[0.548745,51.244227],"type":"Point"}
}