{
  "type": "Feature",
  "properties": {
    "iso:country":"GB",
    "wof:name":"DY3 1UR",
    "wof:placetype":"postalcode"
},
  "geometry": {"coordinates":[-2.11685029850706,52.52968150169339],"type":"Point"}
}