{
  "type": "Feature",
  "properties": {
    "iso:country": "GB",
    "wof:name": "TS25 3HD",
    "wof:placetype": "postalcode"
  },
  "geometry": {"coordinates":[-1.235059,54.658309],"type":"Point"}
}
