{
  "type": "Feature",
  "properties": {
    "iso:country":"GB",
    "wof:name":"HP16 9AG",
    "wof:placetype":"postalcode"
},
  "geometry": {"coordinates":[-0.70821725091166,51.70648294134097],"type":"Point"}
}