{
  "type": "Feature",
  "properties": {
    "iso:country":"GB",
    "wof:name":"BN2 3ES",
    "wof:placetype":"postalcode"
},
  "geometry": {"coordinates":[-0.12145283278645,50.8315813780681],"type":"Point"}
}