{
  "type": "Feature",
  "properties": {
    "date:inception_lower": "2007-07-01",
    "date:inception_upper": "2007-07-01",
    "iso:country": "GB",
    "wof:name": "IV2 5DX",
    "wof:placetype": "postalcode"
  },
  "geometry": {"coordinates":[-4.145386,57.477482],"type":"Point"}
}
