{
  "type": "Feature",
  "properties": {
    "iso:country": "GB",
    "wof:name": "PO33 3TS",
    "wof:placetype": "postalcode"
  },
  "geometry": {"coordinates":[-1.18625,50.722765],"type":"Point"}
}
