{
  "type": "Feature",
  "properties": {
    "iso:country":"GB",
    "wof:name":"PO33 3TS",
    "wof:placetype":"postalcode"
},
  "geometry": {"coordinates":[-1.18626031329354,50.72276779049119],"type":"Point"}
}