{
  "type": "Feature",
  "properties": {
    "date:inception_lower": "1980-01-01",
    "date:inception_upper": "1980-01-01",
    "iso:country": "GB",
    "wof:name": "BD5 0QT",
    "wof:placetype": "postalcode"
  },
  "geometry": {"coordinates":[-1.75564,53.787976],"type":"Point"}
}
