{
  "type": "Feature",
  "properties": {
    "iso:country":"GB",
    "wof:name":"BD5 0QT",
    "wof:placetype":"postalcode"
},
  "geometry": {"coordinates":[-1.7556398929452,53.78797627053586],"type":"Point"}
}