{
  "type": "Feature",
  "properties": {
    "iso:country":"GB",
    "wof:name":"CF23 5JT",
    "wof:placetype":"postalcode"
},
  "geometry": {"coordinates":[-3.16411062395408,51.50260270529316],"type":"Point"}
}