{
  "type": "Feature",
  "properties": {
    "iso:country":"GB",
    "wof:name":"OL13 8NB",
    "wof:placetype":"postalcode"
},
  "geometry": {"coordinates":[-2.23260180243503,53.69525978162558],"type":"Point"}
}