{
  "type": "Feature",
  "properties": {
    "iso:country":"GB",
    "wof:name":"CV35 0SZ",
    "wof:placetype":"postalcode"
},
  "geometry": {"coordinates":[-1.50776463240131,52.09421590696464],"type":"Point"}
}