{
  "type": "Feature",
  "properties": {
    "iso:country": "GB",
    "wof:name": "CT20 1QQ",
    "wof:placetype": "postalcode"
  },
  "geometry": {"coordinates":[1.188291,51.077499],"type":"Point"}
}
