{
  "type": "Feature",
  "properties": {
    "iso:country":"GB",
    "wof:name":"CT20 1QQ",
    "wof:placetype":"postalcode"
},
  "geometry": {"coordinates":[1.18829087972954,51.07749862440738],"type":"Point"}
}