{
  "type": "Feature",
  "properties": {
    "date:inception_lower": "1980-01-01",
    "date:inception_upper": "1980-01-01",
    "iso:country": "GB",
    "wof:name": "UB5 6HX",
    "wof:placetype": "postalcode"
  },
  "geometry": {"coordinates":[-0.394507,51.532925],"type":"Point"}
}
