{
  "type": "Feature",
  "properties": {
    "iso:country":"GB",
    "wof:name":"UB5 6HX",
    "wof:placetype":"postalcode"
},
  "geometry": {"coordinates":[-0.39450675691041,51.5329254454622],"type":"Point"}
}