{
  "type": "Feature",
  "properties": {
    "iso:country":"GB",
    "wof:name":"SK3 9ES",
    "wof:placetype":"postalcode"
},
  "geometry": {"coordinates":[-2.17223183186116,53.40508343334545],"type":"Point"}
}