{
  "type": "Feature",
  "properties": {
    "iso:country": "GB",
    "wof:name": "SK3 9ES",
    "wof:placetype": "postalcode"
  },
  "geometry": {"coordinates":[-2.172232,53.405083],"type":"Point"}
}
