{
  "type": "Feature",
  "properties": {
    "date:inception_lower":"1980-01-01",
    "date:inception_upper":"1980-01-31",
    "iso:country":"GB",
    "wof:name":"BB4 7SG",
    "wof:placetype":"postalcode"
},
  "geometry": {"coordinates":[-2.281425,53.703739],"type":"Point"}
}