{
  "type": "Feature",
  "properties": {
    "date:inception_lower": "2001-06-01",
    "date:inception_upper": "2001-06-01",
    "iso:country": "GB",
    "wof:name": "OX29 0SN",
    "wof:placetype": "postalcode"
  },
  "geometry": {"coordinates":[-1.547358,51.795636],"type":"Point"}
}
