{
  "type": "Feature",
  "properties": {
    "iso:country": "GB",
    "wof:name": "WN5 9QN",
    "wof:placetype": "postalcode"
  },
  "geometry": {"coordinates":[-2.668269,53.536944],"type":"Point"}
}
