{
  "type": "Feature",
  "properties": {
    "date:inception_lower": "2008-04-01",
    "date:inception_upper": "2008-04-01",
    "iso:country": "GB",
    "wof:name": "CO15 3AW",
    "wof:placetype": "postalcode"
  },
  "geometry": {"coordinates":[1.14801,51.794155],"type":"Point"}
}
