{
  "type": "Feature",
  "properties": {
    "iso:country":"GB",
    "wof:name":"CO15 3AW",
    "wof:placetype":"postalcode"
},
  "geometry": {"coordinates":[1.14801041858667,51.79415520157618],"type":"Point"}
}