{
  "type": "Feature",
  "properties": {
    "iso:country":"GB",
    "wof:name":"WA8 9AF",
    "wof:placetype":"postalcode"
},
  "geometry": {"coordinates":[-2.74278043263158,53.3844692923236],"type":"Point"}
}