{
  "type": "Feature",
  "properties": {
    "iso:country":"GB",
    "wof:name":"NP10 8UA",
    "wof:placetype":"postalcode"
},
  "geometry": {"coordinates":[-3.0672255918668,51.58112331772061],"type":"Point"}
}