{
  "type": "Feature",
  "properties": {
    "date:inception_lower":"2012-08-01",
    "date:inception_upper":"2012-08-31",
    "iso:country":"GB",
    "wof:name":"NP10 8UA",
    "wof:placetype":"postalcode"
},
  "geometry": {"coordinates":[-3.067226,51.581123],"type":"Point"}
}