{
  "type": "Feature",
  "properties": {
    "iso:country":"GB",
    "wof:name":"BS23 2EE",
    "wof:placetype":"postalcode"
},
  "geometry": {"coordinates":[-2.99186052327574,51.3541388453517],"type":"Point"}
}