{
  "type": "Feature",
  "properties": {
    "iso:country":"GB",
    "wof:name":"HR1 3HW",
    "wof:placetype":"postalcode"
},
  "geometry": {"coordinates":[-2.65895959573492,52.14878174482337],"type":"Point"}
}