{
  "type": "Feature",
  "properties": {
    "date:inception_lower": "1980-01-01",
    "date:inception_upper": "1980-01-01",
    "iso:country": "GB",
    "wof:name": "HR1 3HW",
    "wof:placetype": "postalcode"
  },
  "geometry": {"coordinates":[-2.65896,52.148782],"type":"Point"}
}
