{
  "type": "Feature",
  "properties": {
    "iso:country":"GB",
    "wof:name":"WF10 2HL",
    "wof:placetype":"postalcode"
},
  "geometry": {"coordinates":[-1.38596275968826,53.75535722495156],"type":"Point"}
}