{
  "type": "Feature",
  "properties": {
    "date:inception_lower": "1980-01-01",
    "date:inception_upper": "1980-01-01",
    "iso:country": "GB",
    "wof:name": "WF10 2HL",
    "wof:placetype": "postalcode"
  },
  "geometry": {"coordinates":[-1.385963,53.755357],"type":"Point"}
}
