{
  "type": "Feature",
  "properties": {
    "date:inception_lower": "1996-06-01",
    "date:inception_upper": "1996-06-01",
    "iso:country": "GB",
    "wof:name": "AL3 7NX",
    "wof:placetype": "postalcode"
  },
  "geometry": {"coordinates":[-0.405761,51.802676],"type":"Point"}
}
