{
  "type": "Feature",
  "properties": {
    "iso:country":"GB",
    "wof:name":"AL3 7NX",
    "wof:placetype":"postalcode"
},
  "geometry": {"coordinates":[-0.40575539182668,51.80266812475774],"type":"Point"}
}