{
  "type": "Feature",
  "properties": {
    "iso:country": "GB",
    "wof:name": "AL3 7NX",
    "wof:placetype": "postalcode"
  },
  "geometry": {"coordinates":[-0.405761,51.802676],"type":"Point"}
}
