{
  "type": "Feature",
  "properties": {
    "iso:country":"GB",
    "wof:name":"IP18 6BW",
    "wof:placetype":"postalcode"
},
  "geometry": {"coordinates":[1.68362854283695,52.33071751043304],"type":"Point"}
}