{
  "type": "Feature",
  "properties": {
    "iso:country": "GB",
    "wof:name": "NN7 3AX",
    "wof:placetype": "postalcode"
  },
  "geometry": {"coordinates":[-0.928636,52.192396],"type":"Point"}
}
