{
  "type": "Feature",
  "properties": {
    "date:inception_lower": "1980-01-01",
    "date:inception_upper": "1980-01-01",
    "iso:country": "GB",
    "wof:name": "NN7 3AX",
    "wof:placetype": "postalcode"
  },
  "geometry": {"coordinates":[-0.928636,52.192396],"type":"Point"}
}
