{
  "type": "Feature",
  "properties": {
    "iso:country":"GB",
    "wof:name":"NN7 3AX",
    "wof:placetype":"postalcode"
},
  "geometry": {"coordinates":[-0.92863609926355,52.19239590018847],"type":"Point"}
}