{
  "type": "Feature",
  "properties": {
    "date:inception_lower": "1980-01-01",
    "date:inception_upper": "1980-01-01",
    "iso:country": "GB",
    "wof:name": "ST3 3DN",
    "wof:placetype": "postalcode"
  },
  "geometry": {"coordinates":[-2.155587,52.969226],"type":"Point"}
}
