{
  "type": "Feature",
  "properties": {
    "date:inception_lower": "1997-12-01",
    "date:inception_upper": "1997-12-01",
    "iso:country": "GB",
    "wof:name": "SS15 5GR",
    "wof:placetype": "postalcode"
  },
  "geometry": {"coordinates":[0.448623,51.586927],"type":"Point"}
}
