{
  "type": "Feature",
  "properties": {
    "iso:country":"GB",
    "wof:name":"SW1Y 4UH",
    "wof:placetype":"postalcode"
},
  "geometry": {"coordinates":[-0.13374407138017,51.50960713199462],"type":"Point"}
}