{
  "type": "Feature",
  "properties": {
    "iso:country": "GB",
    "wof:name": "PO5 3AZ",
    "wof:placetype": "postalcode"
  },
  "geometry": {"coordinates":[-1.093996,50.788653],"type":"Point"}
}
