{
  "type": "Feature",
  "properties": {
    "date:inception_lower": "1980-01-01",
    "date:inception_upper": "1980-01-01",
    "iso:country": "GB",
    "wof:name": "PO5 3AZ",
    "wof:placetype": "postalcode"
  },
  "geometry": {"coordinates":[-1.093996,50.788653],"type":"Point"}
}
