{
  "type": "Feature",
  "properties": {
    "iso:country":"GB",
    "wof:name":"KT17 1LS",
    "wof:placetype":"postalcode"
},
  "geometry": {"coordinates":[-0.2604265161196,51.33959992015834],"type":"Point"}
}