{
  "type": "Feature",
  "properties": {
    "iso:country": "GB",
    "wof:name": "KT17 1LS",
    "wof:placetype": "postalcode"
  },
  "geometry": {"coordinates":[-0.260426,51.3396],"type":"Point"}
}
