{
  "type": "Feature",
  "properties": {
    "date:inception_lower":"2000-06-01",
    "date:inception_upper":"2000-06-30",
    "iso:country":"GB",
    "wof:name":"EX11 1XZ",
    "wof:placetype":"postalcode"
},
  "geometry": {"coordinates":[-3.323959,50.733796],"type":"Point"}
}