{
  "type": "Feature",
  "properties": {
    "iso:country":"GB",
    "wof:name":"EX11 1XZ",
    "wof:placetype":"postalcode"
},
  "geometry": {"coordinates":[-3.32395868109474,50.73379629948667],"type":"Point"}
}