{
  "type": "Feature",
  "properties": {
    "iso:country":"GB",
    "wof:name":"AB24 2PB",
    "wof:placetype":"postalcode"
},
  "geometry": {"coordinates":[-2.11232978472424,57.17477230531095],"type":"Point"}
}