{
  "type": "Feature",
  "properties": {
    "iso:country": "GB",
    "wof:name": "AB24 2PB",
    "wof:placetype": "postalcode"
  },
  "geometry": {"coordinates":[-2.11233,57.174772],"type":"Point"}
}
