{
  "type": "Feature",
  "properties": {
    "iso:country":"GB",
    "wof:name":"ST5 7LE",
    "wof:placetype":"postalcode"
},
  "geometry": {"coordinates":[-2.25281269179776,53.03465295741588],"type":"Point"}
}