{
  "type": "Feature",
  "properties": {
    "iso:country":"GB",
    "wof:name":"PE28 4NW",
    "wof:placetype":"postalcode"
},
  "geometry": {"coordinates":[-0.22119416626308,52.31889335274187],"type":"Point"}
}