{
  "type": "Feature",
  "properties": {
    "date:inception_lower": "1990-08-01",
    "date:inception_upper": "1990-08-01",
    "iso:country": "GB",
    "wof:name": "AB35 5ZB",
    "wof:placetype": "postalcode"
  },
  "geometry": {"coordinates":[-3.043358,57.053113],"type":"Point"}
}
