{
  "type": "Feature",
  "properties": {
    "iso:country":"GB",
    "wof:name":"AB35 5ZB",
    "wof:placetype":"postalcode"
},
  "geometry": {"coordinates":[-3.04335813838722,57.05311264215259],"type":"Point"}
}