{
  "type": "Feature",
  "properties": {
    "iso:country":"GB",
    "wof:name":"GU9 9DQ",
    "wof:placetype":"postalcode"
},
  "geometry": {"coordinates":[-0.7785005085205,51.23341195145496],"type":"Point"}
}