{
  "type": "Feature",
  "properties": {
    "iso:country":"GB",
    "wof:name":"NW9 8PU",
    "wof:placetype":"postalcode"
},
  "geometry": {"coordinates":[-0.26967767283636,51.5693860398906],"type":"Point"}
}