{
  "type": "Feature",
  "properties": {
    "iso:country":"GB",
    "wof:name":"TN22 3PB",
    "wof:placetype":"postalcode"
},
  "geometry": {"coordinates":[0.05706075354738,51.03168922612188],"type":"Point"}
}