{
  "type": "Feature",
  "properties": {
    "date:inception_lower":"2008-09-01",
    "date:inception_upper":"2008-09-30",
    "iso:country":"GB",
    "wof:name":"DE14 1DZ",
    "wof:placetype":"postalcode"
},
  "geometry": {"coordinates":[-1.629994,52.802881],"type":"Point"}
}