{
  "type": "Feature",
  "properties": {
    "iso:country":"GB",
    "wof:name":"E3 4DL",
    "wof:placetype":"postalcode"
},
  "geometry": {"coordinates":[-0.02211768498743,51.52754355290568],"type":"Point"}
}