{
  "type": "Feature",
  "properties": {
    "iso:country":"GB",
    "wof:name":"E11 3BT",
    "wof:placetype":"postalcode"
},
  "geometry": {"coordinates":[0.01635966464362,51.56666290003214],"type":"Point"}
}