{
  "type": "Feature",
  "properties": {
    "iso:country": "GB",
    "wof:name": "EX16 4ES",
    "wof:placetype": "postalcode"
  },
  "geometry": {"coordinates":[-3.467448,50.900798],"type":"Point"}
}
