{
  "type": "Feature",
  "properties": {
    "date:inception_lower":"1980-01-01",
    "date:inception_upper":"1980-01-31",
    "iso:country":"GB",
    "wof:name":"EX16 4ES",
    "wof:placetype":"postalcode"
},
  "geometry": {"coordinates":[-3.467448,50.900798],"type":"Point"}
}