{
  "type": "Feature",
  "properties": {
    "date:inception_lower": "1984-02-01",
    "date:inception_upper": "1984-02-01",
    "iso:country": "GB",
    "wof:name": "RH11 0NS",
    "wof:placetype": "postalcode"
  },
  "geometry": {"coordinates":[-0.212614,51.129329],"type":"Point"}
}
