{
  "type": "Feature",
  "properties": {
    "iso:country":"GB",
    "wof:name":"RH11 0NS",
    "wof:placetype":"postalcode"
},
  "geometry": {"coordinates":[-0.21261433473953,51.12932948485175],"type":"Point"}
}