{
  "type": "Feature",
  "properties": {
    "iso:country": "GB",
    "wof:name": "LN1 1SN",
    "wof:placetype": "postalcode"
  },
  "geometry": {"coordinates":[-0.55581,53.231623],"type":"Point"}
}
