{
  "type": "Feature",
  "properties": {
    "iso:country":"GB",
    "wof:name":"HU9 5JT",
    "wof:placetype":"postalcode"
},
  "geometry": {"coordinates":[-0.2521462791705,53.75181945705742],"type":"Point"}
}