{
  "type": "Feature",
  "properties": {
    "iso:country": "GB",
    "wof:name": "HU9 5JT",
    "wof:placetype": "postalcode"
  },
  "geometry": {"coordinates":[-0.252146,53.751819],"type":"Point"}
}
