{
  "type": "Feature",
  "properties": {
    "iso:country":"GB",
    "wof:name":"HX6 3PU",
    "wof:placetype":"postalcode"
},
  "geometry": {"coordinates":[-1.91260365963663,53.704370618126],"type":"Point"}
}