{
  "type": "Feature",
  "properties": {
    "iso:country": "GB",
    "wof:name": "SK4 1QA",
    "wof:placetype": "postalcode"
  },
  "geometry": {"coordinates":[-2.166185,53.420417],"type":"Point"}
}
