{
  "type": "Feature",
  "properties": {
    "iso:country":"GB",
    "wof:name":"TN24 0QW",
    "wof:placetype":"postalcode"
},
  "geometry": {"coordinates":[0.89764702415649,51.14213096111964],"type":"Point"}
}