{
  "type": "Feature",
  "properties": {
    "date:inception_lower": "1980-01-01",
    "date:inception_upper": "1980-01-01",
    "iso:country": "GB",
    "wof:name": "TN24 0QW",
    "wof:placetype": "postalcode"
  },
  "geometry": {"coordinates":[0.897432,51.14184],"type":"Point"}
}
