{
  "type": "Feature",
  "properties": {
    "iso:country":"GB",
    "wof:name":"EN11 8EL",
    "wof:placetype":"postalcode"
},
  "geometry": {"coordinates":[-0.01034397491215,51.75985409416576],"type":"Point"}
}