{
  "type": "Feature",
  "properties": {
    "iso:country":"GB",
    "wof:name":"NP10 8JG",
    "wof:placetype":"postalcode"
},
  "geometry": {"coordinates":[-3.0594596966415,51.57734525183995],"type":"Point"}
}