{
  "type": "Feature",
  "properties": {
    "date:inception_lower": "2002-08-01",
    "date:inception_upper": "2002-08-01",
    "iso:country": "GB",
    "wof:name": "NE12 9FA",
    "wof:placetype": "postalcode"
  },
  "geometry": {"coordinates":[-1.563623,55.010374],"type":"Point"}
}
