{
  "type": "Feature",
  "properties": {
    "iso:country":"GB",
    "wof:name":"NE12 9FA",
    "wof:placetype":"postalcode"
},
  "geometry": {"coordinates":[-1.56362296482706,55.01037422376287],"type":"Point"}
}