{
  "type": "Feature",
  "properties": {
    "iso:country":"GB",
    "wof:name":"DT11 7HX",
    "wof:placetype":"postalcode"
},
  "geometry": {"coordinates":[-2.16175588934161,50.86174820670748],"type":"Point"}
}