{
  "type": "Feature",
  "properties": {
    "iso:country": "GB",
    "wof:name": "DT11 7HX",
    "wof:placetype": "postalcode"
  },
  "geometry": {"coordinates":[-2.161756,50.861748],"type":"Point"}
}
