{
  "type": "Feature",
  "properties": {
    "date:inception_lower": "2018-10-01",
    "date:inception_upper": "2018-10-01",
    "iso:country": "GB",
    "wof:name": "ST7 2ZX",
    "wof:placetype": "postalcode"
  },
  "geometry": {"coordinates":[-2.326445,53.099077],"type":"Point"}
}
