{
  "type": "Feature",
  "properties": {
    "iso:country": "GB",
    "wof:name": "ST7 2ZX",
    "wof:placetype": "postalcode"
  },
  "geometry": {"coordinates":[-2.326443,53.098861],"type":"Point"}
}
