{
  "type": "Feature",
  "properties": {
    "iso:country":"GB",
    "wof:name":"IG1 1LB",
    "wof:placetype":"postalcode"
},
  "geometry": {"coordinates":[0.0787815891239,51.55592436640723],"type":"Point"}
}