{
  "type": "Feature",
  "properties": {
    "iso:country":"GB",
    "wof:name":"YO11 1HE",
    "wof:placetype":"postalcode"
},
  "geometry": {"coordinates":[-0.39864260811044,54.28401115152186],"type":"Point"}
}