{
  "type": "Feature",
  "properties": {
    "date:inception_lower":"1980-01-01",
    "date:inception_upper":"1980-01-31",
    "iso:country":"GB",
    "wof:name":"LL53 6EP",
    "wof:placetype":"postalcode"
},
  "geometry": {"coordinates":[-4.537302,52.938439],"type":"Point"}
}