{
  "type": "Feature",
  "properties": {
    "iso:country":"GB",
    "wof:name":"LL53 6EP",
    "wof:placetype":"postalcode"
},
  "geometry": {"coordinates":[-4.53730219473643,52.93843893043145],"type":"Point"}
}