{
  "type": "Feature",
  "properties": {
    "iso:country":"GB",
    "wof:name":"CT16 2NY",
    "wof:placetype":"postalcode"
},
  "geometry": {"coordinates":[1.30426425230933,51.13570355266183],"type":"Point"}
}