{
  "type": "Feature",
  "properties": {
    "iso:country": "GB",
    "wof:name": "CT16 2NY",
    "wof:placetype": "postalcode"
  },
  "geometry": {"coordinates":[1.304264,51.135704],"type":"Point"}
}
