{
  "type": "Feature",
  "properties": {
    "date:inception_lower": "1992-08-01",
    "date:inception_upper": "1992-08-01",
    "iso:country": "GB",
    "wof:name": "LE12 7UJ",
    "wof:placetype": "postalcode"
  },
  "geometry": {"coordinates":[-1.15133,52.720093],"type":"Point"}
}
