{
  "type": "Feature",
  "properties": {
    "iso:country":"GB",
    "wof:name":"LE12 7UJ",
    "wof:placetype":"postalcode"
},
  "geometry": {"coordinates":[-1.1513514373878,52.72010985356453],"type":"Point"}
}