{
  "type": "Feature",
  "properties": {
    "iso:country":"GB",
    "wof:name":"BL9 9NZ",
    "wof:placetype":"postalcode"
},
  "geometry": {"coordinates":[-2.2955037363111,53.57278208648604],"type":"Point"}
}