{
  "type": "Feature",
  "properties": {
    "iso:country":"GB",
    "wof:name":"NG8 4EU",
    "wof:placetype":"postalcode"
},
  "geometry": {"coordinates":[-1.22229384722182,52.96390045520602],"type":"Point"}
}