{
  "type": "Feature",
  "properties": {
    "iso:country":"GB",
    "wof:name":"BH16 5QU",
    "wof:placetype":"postalcode"
},
  "geometry": {"coordinates":[-2.02766769835896,50.7398554455031],"type":"Point"}
}