{
  "type": "Feature",
  "properties": {
    "date:inception_lower": "1980-01-01",
    "date:inception_upper": "1980-01-01",
    "iso:country": "GB",
    "wof:name": "BH16 5QU",
    "wof:placetype": "postalcode"
  },
  "geometry": {"coordinates":[-2.027668,50.739855],"type":"Point"}
}
