{
  "type": "Feature",
  "properties": {
    "date:inception_lower": "1980-01-01",
    "date:inception_upper": "1980-01-01",
    "iso:country": "GB",
    "wof:name": "TS7 8QR",
    "wof:placetype": "postalcode"
  },
  "geometry": {"coordinates":[-1.1974,54.534233],"type":"Point"}
}
