{
  "type": "Feature",
  "properties": {
    "iso:country":"GB",
    "wof:name":"TS7 8QR",
    "wof:placetype":"postalcode"
},
  "geometry": {"coordinates":[-1.19740022832447,54.53423282751593],"type":"Point"}
}