{
  "type": "Feature",
  "properties": {
    "date:inception_lower": "1984-10-01",
    "date:inception_upper": "1984-10-01",
    "iso:country": "GB",
    "wof:name": "WR5 3SD",
    "wof:placetype": "postalcode"
  },
  "geometry": {"coordinates":[-2.214535,52.135504],"type":"Point"}
}
