{
  "type": "Feature",
  "properties": {
    "iso:country":"GB",
    "wof:name":"E9 7SN",
    "wof:placetype":"postalcode"
},
  "geometry": {"coordinates":[-0.05534319293371,51.5388272480732],"type":"Point"}
}