{
  "type": "Feature",
  "properties": {
    "iso:country":"GB",
    "wof:name":"LU7 9DY",
    "wof:placetype":"postalcode"
},
  "geometry": {"coordinates":[-0.64437569735769,51.84881149365471],"type":"Point"}
}