{
  "type": "Feature",
  "properties": {
    "iso:country":"GB",
    "wof:name":"PL2 3NT",
    "wof:placetype":"postalcode"
},
  "geometry": {"coordinates":[-4.14400085144574,50.39634143172156],"type":"Point"}
}