{
  "type": "Feature",
  "properties": {
    "date:inception_lower": "2007-11-01",
    "date:inception_upper": "2007-11-01",
    "iso:country": "GB",
    "wof:name": "S71 5DN",
    "wof:placetype": "postalcode"
  },
  "geometry": {"coordinates":[-1.424086,53.545831],"type":"Point"}
}
