{
  "type": "Feature",
  "properties": {
    "date:inception_lower": "2001-12-01",
    "date:inception_upper": "2001-12-01",
    "iso:country": "GB",
    "wof:name": "CV7 8NP",
    "wof:placetype": "postalcode"
  },
  "geometry": {"coordinates":[-1.530876,52.459048],"type":"Point"}
}
