{
  "type": "Feature",
  "properties": {
    "iso:country":"GB",
    "wof:name":"CV7 8NP",
    "wof:placetype":"postalcode"
},
  "geometry": {"coordinates":[-1.53087636424581,52.45904836371088],"type":"Point"}
}