{
  "type": "Feature",
  "properties": {
    "iso:country":"GB",
    "wof:name":"KY15 5NP",
    "wof:placetype":"postalcode"
},
  "geometry": {"coordinates":[-2.97209523452061,56.29048647524596],"type":"Point"}
}