{
  "type": "Feature",
  "properties": {
    "iso:country":"GB",
    "wof:name":"NG2 7JU",
    "wof:placetype":"postalcode"
},
  "geometry": {"coordinates":[-1.13933300195876,52.92953729417967],"type":"Point"}
}