{
  "type": "Feature",
  "properties": {
    "iso:country":"GB",
    "wof:name":"EX33 2JG",
    "wof:placetype":"postalcode"
},
  "geometry": {"coordinates":[-4.16130386370599,51.10826547895933],"type":"Point"}
}