{
  "type": "Feature",
  "properties": {
    "iso:country":"GB",
    "wof:name":"E5 9QH",
    "wof:placetype":"postalcode"
},
  "geometry": {"coordinates":[-0.05041382121672,51.55901466715938],"type":"Point"}
}