{
  "type": "Feature",
  "properties": {
    "iso:country": "GB",
    "wof:name": "DL12 9PH",
    "wof:placetype": "postalcode"
  },
  "geometry": {"coordinates":[-1.982629,54.569524],"type":"Point"}
}
