{
  "type": "Feature",
  "properties": {
    "iso:country": "GB",
    "wof:name": "HP5 1SF",
    "wof:placetype": "postalcode"
  },
  "geometry": {"coordinates":[-0.606609,51.697409],"type":"Point"}
}
