{
  "type": "Feature",
  "properties": {
    "iso:country":"GB",
    "wof:name":"HP5 1SF",
    "wof:placetype":"postalcode"
},
  "geometry": {"coordinates":[-0.60660915759255,51.69740921111774],"type":"Point"}
}