{
  "type": "Feature",
  "properties": {
    "iso:country":"GB",
    "wof:name":"NW1 1QA",
    "wof:placetype":"postalcode"
},
  "geometry": {"coordinates":[-0.13412714403076,51.53126717644307],"type":"Point"}
}