{
  "type": "Feature",
  "properties": {
    "date:inception_lower": "2019-07-01",
    "date:inception_upper": "2019-07-01",
    "iso:country": "GB",
    "wof:name": "SO32 2GQ",
    "wof:placetype": "postalcode"
  },
  "geometry": {"coordinates":[-1.278586,50.932959],"type":"Point"}
}
