{
  "type": "Feature",
  "properties": {
    "date:inception_lower":"2006-04-01",
    "date:inception_upper":"2006-04-30",
    "iso:country":"GB",
    "wof:name":"EH54 6GH",
    "wof:placetype":"postalcode"
},
  "geometry": {"coordinates":[-3.524612,55.877407],"type":"Point"}
}