{
  "type": "Feature",
  "properties": {
    "iso:country": "GB",
    "wof:name": "BD23 4NB",
    "wof:placetype": "postalcode"
  },
  "geometry": {"coordinates":[-2.254214,54.01869],"type":"Point"}
}
