{
  "type": "Feature",
  "properties": {
    "iso:country":"GB",
    "wof:name":"BD23 4NB",
    "wof:placetype":"postalcode"
},
  "geometry": {"coordinates":[-2.25421450182477,54.0186900923998],"type":"Point"}
}