{
  "type": "Feature",
  "properties": {
    "date:inception_lower":"1980-01-01",
    "date:inception_upper":"1980-01-31",
    "iso:country":"GB",
    "wof:name":"BD23 4NB",
    "wof:placetype":"postalcode"
},
  "geometry": {"coordinates":[-2.254214,54.01869],"type":"Point"}
}