{
  "type": "Feature",
  "properties": {
    "date:inception_lower":"1990-09-01",
    "date:inception_upper":"1990-09-30",
    "iso:country":"GB",
    "wof:name":"G69 6PX",
    "wof:placetype":"postalcode"
},
  "geometry": {"coordinates":[-4.110155,55.855462],"type":"Point"}
}