{
  "type": "Feature",
  "properties": {
    "iso:country":"GB",
    "wof:name":"G69 6PX",
    "wof:placetype":"postalcode"
},
  "geometry": {"coordinates":[-4.11015540925862,55.85546176723957],"type":"Point"}
}