{
  "type": "Feature",
  "properties": {
    "iso:country":"GB",
    "wof:name":"LA23 3LW",
    "wof:placetype":"postalcode"
},
  "geometry": {"coordinates":[-2.93778504020042,54.32549493444192],"type":"Point"}
}