{
  "type": "Feature",
  "properties": {
    "iso:country":"GB",
    "wof:name":"CT10 1HR",
    "wof:placetype":"postalcode"
},
  "geometry": {"coordinates":[1.44052807572329,51.36372463604224],"type":"Point"}
}