{
  "type": "Feature",
  "properties": {
    "date:inception_lower": "1980-01-01",
    "date:inception_upper": "1980-01-01",
    "iso:country": "GB",
    "wof:name": "TQ9 6PT",
    "wof:placetype": "postalcode"
  },
  "geometry": {"coordinates":[-3.629285,50.418327],"type":"Point"}
}
