{
  "type": "Feature",
  "properties": {
    "iso:country":"GB",
    "wof:name":"TQ9 6PT",
    "wof:placetype":"postalcode"
},
  "geometry": {"coordinates":[-3.62928454721547,50.41832724476613],"type":"Point"}
}