{
  "type": "Feature",
  "properties": {
    "iso:country":"GB",
    "wof:name":"AB31 4AW",
    "wof:placetype":"postalcode"
},
  "geometry": {"coordinates":[-2.53835242706998,57.06109860834801],"type":"Point"}
}