{
  "type": "Feature",
  "properties": {
    "iso:country": "GB",
    "wof:name": "LS28 8NQ",
    "wof:placetype": "postalcode"
  },
  "geometry": {"coordinates":[-1.66643,53.787597],"type":"Point"}
}
