{
  "type": "Feature",
  "properties": {
    "iso:country": "GB",
    "wof:name": "KW16 3DJ",
    "wof:placetype": "postalcode"
  },
  "geometry": {"coordinates":[-3.301339,58.957279],"type":"Point"}
}
