{
  "type": "Feature",
  "properties": {
    "iso:country":"GB",
    "wof:name":"KW16 3DJ",
    "wof:placetype":"postalcode"
},
  "geometry": {"coordinates":[-3.30133918670957,58.95727941220404],"type":"Point"}
}