{
  "type": "Feature",
  "properties": {
    "iso:country": "GB",
    "wof:name": "DN10 4BB",
    "wof:placetype": "postalcode"
  },
  "geometry": {"coordinates":[-0.8355,53.45397],"type":"Point"}
}
