{
  "type": "Feature",
  "properties": {
    "iso:country":"GB",
    "wof:name":"DN10 4BB",
    "wof:placetype":"postalcode"
},
  "geometry": {"coordinates":[-0.83550027638577,53.45397009712934],"type":"Point"}
}