{
  "type": "Feature",
  "properties": {
    "iso:country":"GB",
    "wof:name":"PR4 0LN",
    "wof:placetype":"postalcode"
},
  "geometry": {"coordinates":[-2.75860710163557,53.80577730902566],"type":"Point"}
}