{
  "type": "Feature",
  "properties": {
    "iso:country":"GB",
    "wof:name":"RM13 7SH",
    "wof:placetype":"postalcode"
},
  "geometry": {"coordinates":[0.18223385374015,51.53337998014139],"type":"Point"}
}