{
  "type": "Feature",
  "properties": {
    "iso:country":"GB",
    "wof:name":"SN7 8BL",
    "wof:placetype":"postalcode"
},
  "geometry": {"coordinates":[-1.63767569549138,51.67116033355705],"type":"Point"}
}