{
  "type": "Feature",
  "properties": {
    "iso:country": "GB",
    "wof:name": "SN7 8BL",
    "wof:placetype": "postalcode"
  },
  "geometry": {"coordinates":[-1.638121,51.662479],"type":"Point"}
}
