{
  "type": "Feature",
  "properties": {
    "date:inception_lower": "1980-01-01",
    "date:inception_upper": "1980-01-01",
    "iso:country": "GB",
    "wof:name": "SN7 8BL",
    "wof:placetype": "postalcode"
  },
  "geometry": {"coordinates":[-1.645687,51.663788],"type":"Point"}
}
