{
  "type": "Feature",
  "properties": {
    "date:inception_lower":"1984-10-01",
    "date:inception_upper":"1984-10-31",
    "iso:country":"GB",
    "wof:name":"DT4 9DP",
    "wof:placetype":"postalcode"
},
  "geometry": {"coordinates":[-2.470874,50.587546],"type":"Point"}
}