{
  "type": "Feature",
  "properties": {
    "iso:country": "GB",
    "wof:name": "DT4 9DP",
    "wof:placetype": "postalcode"
  },
  "geometry": {"coordinates":[-2.470874,50.587546],"type":"Point"}
}
