{
  "type": "Feature",
  "properties": {
    "iso:country": "GB",
    "wof:name": "GL18 1QR",
    "wof:placetype": "postalcode"
  },
  "geometry": {"coordinates":[-2.418343,51.928773],"type":"Point"}
}
