{
  "type": "Feature",
  "properties": {
    "iso:country":"GB",
    "wof:name":"GL18 1QR",
    "wof:placetype":"postalcode"
},
  "geometry": {"coordinates":[-2.41834277388064,51.92877302481867],"type":"Point"}
}