{
  "type": "Feature",
  "properties": {
    "date:inception_lower": "2008-02-01",
    "date:inception_upper": "2008-02-01",
    "iso:country": "GB",
    "wof:name": "W1J 0AH",
    "wof:placetype": "postalcode"
  },
  "geometry": {"coordinates":[-0.137449,51.509567],"type":"Point"}
}
