{
  "type": "Feature",
  "properties": {
    "date:inception_lower":"1980-01-01",
    "date:inception_upper":"1980-01-31",
    "iso:country":"GB",
    "wof:name":"B33 0SE",
    "wof:placetype":"postalcode"
},
  "geometry": {"coordinates":[-1.780688,52.476469],"type":"Point"}
}