{
  "type": "Feature",
  "properties": {
    "date:inception_lower": "1983-07-01",
    "date:inception_upper": "1983-07-01",
    "iso:country": "GB",
    "wof:name": "YO11 3UZ",
    "wof:placetype": "postalcode"
  },
  "geometry": {"coordinates":[-0.411966,54.237942],"type":"Point"}
}
