{
  "type": "Feature",
  "properties": {
    "iso:country":"GB",
    "wof:name":"YO22 4FG",
    "wof:placetype":"postalcode"
},
  "geometry": {"coordinates":[-0.61274904390906,54.48001213058159],"type":"Point"}
}