{
  "type": "Feature",
  "properties": {
    "date:inception_lower": "2004-09-01",
    "date:inception_upper": "2004-09-01",
    "iso:country": "GB",
    "wof:name": "YO22 4FG",
    "wof:placetype": "postalcode"
  },
  "geometry": {"coordinates":[-0.612749,54.480012],"type":"Point"}
}
