{
  "type": "Feature",
  "properties": {
    "iso:country":"GB",
    "wof:name":"KT23 3DQ",
    "wof:placetype":"postalcode"
},
  "geometry": {"coordinates":[-0.38566290185747,51.28239287259898],"type":"Point"}
}