{
  "type": "Feature",
  "properties": {
    "iso:country":"GB",
    "wof:name":"LN11 8JF",
    "wof:placetype":"postalcode"
},
  "geometry": {"coordinates":[0.0973540411857,53.33130076107877],"type":"Point"}
}