{
  "type": "Feature",
  "properties": {
    "iso:country":"GB",
    "wof:name":"CO6 4BB",
    "wof:placetype":"postalcode"
},
  "geometry": {"coordinates":[0.8669136408844,51.92315026764891],"type":"Point"}
}