{
  "type": "Feature",
  "properties": {
    "date:inception_lower":"1980-01-01",
    "date:inception_upper":"1980-01-31",
    "iso:country":"GB",
    "wof:name":"CO6 4BB",
    "wof:placetype":"postalcode"
},
  "geometry": {"coordinates":[0.866914,51.92315],"type":"Point"}
}