{
  "type": "Feature",
  "properties": {
    "iso:country":"GB",
    "wof:name":"GL7 1GJ",
    "wof:placetype":"postalcode"
},
  "geometry": {"coordinates":[-1.94938840283122,51.71961243720222],"type":"Point"}
}