{
  "type": "Feature",
  "properties": {
    "iso:country":"GB",
    "wof:name":"SE10 0HH",
    "wof:placetype":"postalcode"
},
  "geometry": {"coordinates":[0.00978627612778,51.48856646262379],"type":"Point"}
}