{
  "type": "Feature",
  "properties": {
    "iso:country": "GB",
    "wof:name": "SE10 0HH",
    "wof:placetype": "postalcode"
  },
  "geometry": {"coordinates":[0.009786,51.488566],"type":"Point"}
}
