{
  "type": "Feature",
  "properties": {
    "date:inception_lower": "1980-01-01",
    "date:inception_upper": "1980-01-01",
    "iso:country": "GB",
    "wof:name": "CV22 5DB",
    "wof:placetype": "postalcode"
  },
  "geometry": {"coordinates":[-1.260159,52.370721],"type":"Point"}
}
