{
  "type": "Feature",
  "properties": {
    "date:inception_lower":"1996-12-01",
    "date:inception_upper":"1996-12-31",
    "iso:country":"GB",
    "wof:name":"EX9 6ET",
    "wof:placetype":"postalcode"
},
  "geometry": {"coordinates":[-3.317478,50.636608],"type":"Point"}
}