{
  "type": "Feature",
  "properties": {
    "iso:country": "GB",
    "wof:name": "EX9 6ET",
    "wof:placetype": "postalcode"
  },
  "geometry": {"coordinates":[-3.317478,50.636608],"type":"Point"}
}
