{
  "type": "Feature",
  "properties": {
    "iso:country":"GB",
    "wof:name":"WN1 3TD",
    "wof:placetype":"postalcode"
},
  "geometry": {"coordinates":[-2.62311909832488,53.54889956514675],"type":"Point"}
}