{
  "type": "Feature",
  "properties": {
    "iso:country":"GB",
    "wof:name":"NR10 4AH",
    "wof:placetype":"postalcode"
},
  "geometry": {"coordinates":[1.16008764733004,52.76907161441265],"type":"Point"}
}