{
  "type": "Feature",
  "properties": {
    "iso:country":"GB",
    "wof:name":"FK4 1LR",
    "wof:placetype":"postalcode"
},
  "geometry": {"coordinates":[-3.88794026092476,56.00386479767247],"type":"Point"}
}