{
  "type": "Feature",
  "properties": {
    "iso:country": "GB",
    "wof:name": "YO25 3XH",
    "wof:placetype": "postalcode"
  },
  "geometry": {"coordinates":[-0.576344,54.070809],"type":"Point"}
}
