{
  "type": "Feature",
  "properties": {
    "iso:country":"GB",
    "wof:name":"OX14 3DJ",
    "wof:placetype":"postalcode"
},
  "geometry": {"coordinates":[-1.19385492704876,51.66040299667291],"type":"Point"}
}