{
  "type": "Feature",
  "properties": {
    "iso:country":"GB",
    "wof:name":"TN33 0QG",
    "wof:placetype":"postalcode"
},
  "geometry": {"coordinates":[0.53285484371534,50.93430760558997],"type":"Point"}
}