{
  "type": "Feature",
  "properties": {
    "iso:country":"GB",
    "wof:name":"PL3 5SY",
    "wof:placetype":"postalcode"
},
  "geometry": {"coordinates":[-4.13647311975958,50.39634508450778],"type":"Point"}
}