{
  "type": "Feature",
  "properties": {
    "iso:country": "GB",
    "wof:name": "BB5 6LJ",
    "wof:placetype": "postalcode"
  },
  "geometry": {"coordinates":[-2.337249,53.770561],"type":"Point"}
}
