{
  "type": "Feature",
  "properties": {
    "iso:country":"GB",
    "wof:name":"BB5 6LJ",
    "wof:placetype":"postalcode"
},
  "geometry": {"coordinates":[-2.33708302839326,53.77061003540283],"type":"Point"}
}