{
  "type": "Feature",
  "properties": {
    "date:inception_lower":"1980-01-01",
    "date:inception_upper":"1980-01-31",
    "iso:country":"GB",
    "wof:name":"GU24 0NY",
    "wof:placetype":"postalcode"
},
  "geometry": {"coordinates":[-0.65683,51.310816],"type":"Point"}
}