{
  "type": "Feature",
  "properties": {
    "iso:country":"GB",
    "wof:name":"NN10 9XD",
    "wof:placetype":"postalcode"
},
  "geometry": {"coordinates":[-0.60963485087785,52.2926806809869],"type":"Point"}
}