{
  "type": "Feature",
  "properties": {
    "iso:country": "GB",
    "wof:name": "NN10 9XD",
    "wof:placetype": "postalcode"
  },
  "geometry": {"coordinates":[-0.609635,52.292681],"type":"Point"}
}
