{
  "type": "Feature",
  "properties": {
    "date:inception_lower": "1980-01-01",
    "date:inception_upper": "1980-01-01",
    "iso:country": "GB",
    "wof:name": "PO17 6DH",
    "wof:placetype": "postalcode"
  },
  "geometry": {"coordinates":[-1.144856,50.890456],"type":"Point"}
}
