{
  "type": "Feature",
  "properties": {
    "iso:country":"GB",
    "wof:name":"PO17 6DH",
    "wof:placetype":"postalcode"
},
  "geometry": {"coordinates":[-1.1448558067624,50.89045589622155],"type":"Point"}
}