{
  "type": "Feature",
  "properties": {
    "iso:country": "GB",
    "wof:name": "PO17 6DH",
    "wof:placetype": "postalcode"
  },
  "geometry": {"coordinates":[-1.144856,50.890456],"type":"Point"}
}
