{
  "type": "Feature",
  "properties": {
    "iso:country":"GB",
    "wof:name":"NE61 4JX",
    "wof:placetype":"postalcode"
},
  "geometry": {"coordinates":[-1.91891060758536,55.19716606179016],"type":"Point"}
}