{
  "type": "Feature",
  "properties": {
    "date:inception_lower": "1980-01-01",
    "date:inception_upper": "1980-01-01",
    "iso:country": "GB",
    "wof:name": "NE61 4JX",
    "wof:placetype": "postalcode"
  },
  "geometry": {"coordinates":[-1.918911,55.197166],"type":"Point"}
}
