{
  "type": "Feature",
  "properties": {
    "iso:country":"GB",
    "wof:name":"KY4 8BG",
    "wof:placetype":"postalcode"
},
  "geometry": {"coordinates":[-3.37553569072226,56.08576590211449],"type":"Point"}
}