{
  "type": "Feature",
  "properties": {
    "iso:country":"GB",
    "wof:name":"LL19 8PE",
    "wof:placetype":"postalcode"
},
  "geometry": {"coordinates":[-3.41463544303562,53.31545283027554],"type":"Point"}
}