{
  "type": "Feature",
  "properties": {
    "iso:country": "GB",
    "wof:name": "LL19 8PE",
    "wof:placetype": "postalcode"
  },
  "geometry": {"coordinates":[-3.414635,53.315453],"type":"Point"}
}
