{
  "type": "Feature",
  "properties": {
    "iso:country":"GB",
    "wof:name":"DH8 6DR",
    "wof:placetype":"postalcode"
},
  "geometry": {"coordinates":[-1.80684220387749,54.86121073516042],"type":"Point"}
}