{
  "type": "Feature",
  "properties": {
    "iso:country": "GB",
    "wof:name": "HG3 1DJ",
    "wof:placetype": "postalcode"
  },
  "geometry": {"coordinates":[-1.494906,53.969995],"type":"Point"}
}
