{
  "type": "Feature",
  "properties": {
    "iso:country":"GB",
    "wof:name":"HG3 1DJ",
    "wof:placetype":"postalcode"
},
  "geometry": {"coordinates":[-1.49490558953013,53.96999475528111],"type":"Point"}
}