{
  "type": "Feature",
  "properties": {
    "date:inception_lower":"2011-05-01",
    "date:inception_upper":"2011-05-31",
    "iso:country":"GB",
    "wof:name":"TA9 3FW",
    "wof:placetype":"postalcode"
},
  "geometry": {"coordinates":[-2.973664,51.223232],"type":"Point"}
}