{
  "type": "Feature",
  "properties": {
    "iso:country":"GB",
    "wof:name":"BR8 7LE",
    "wof:placetype":"postalcode"
},
  "geometry": {"coordinates":[0.18519128457561,51.40324157976941],"type":"Point"}
}