{
  "type": "Feature",
  "properties": {
    "iso:country":"GB",
    "wof:name":"M22 1SB",
    "wof:placetype":"postalcode"
},
  "geometry": {"coordinates":[-2.27846068016027,53.37365633629392],"type":"Point"}
}