{
  "type": "Feature",
  "properties": {
    "date:inception_lower": "2018-09-01",
    "date:inception_upper": "2018-09-01",
    "iso:country": "GB",
    "wof:name": "KA24 9AB",
    "wof:placetype": "postalcode"
  },
  "geometry": {"coordinates":[-4.719564,55.70742],"type":"Point"}
}
