{
  "type": "Feature",
  "properties": {
    "iso:country":"GB",
    "wof:name":"EX20 3AH",
    "wof:placetype":"postalcode"
},
  "geometry": {"coordinates":[-4.02238012180251,50.7650605668674],"type":"Point"}
}