{
  "type": "Feature",
  "properties": {
    "iso:country":"GB",
    "wof:name":"TW8 0BW",
    "wof:placetype":"postalcode"
},
  "geometry": {"coordinates":[-0.29691897322564,51.49061624191477],"type":"Point"}
}