{
  "type": "Feature",
  "properties": {
    "date:inception_lower": "1994-12-01",
    "date:inception_upper": "1994-12-01",
    "iso:country": "GB",
    "wof:name": "TW8 0BW",
    "wof:placetype": "postalcode"
  },
  "geometry": {"coordinates":[-0.296919,51.490616],"type":"Point"}
}
