{
  "type": "Feature",
  "properties": {
    "iso:country": "GB",
    "wof:name": "TW8 0BW",
    "wof:placetype": "postalcode"
  },
  "geometry": {"coordinates":[-0.296919,51.490616],"type":"Point"}
}
