{
  "type": "Feature",
  "properties": {
    "iso:country":"GB",
    "wof:name":"LL36 9AF",
    "wof:placetype":"postalcode"
},
  "geometry": {"coordinates":[-4.08982445675808,52.58619789187748],"type":"Point"}
}