{
  "type": "Feature",
  "properties": {
    "iso:country":"GB",
    "wof:name":"BN27 4DY",
    "wof:placetype":"postalcode"
},
  "geometry": {"coordinates":[0.24563871418095,50.89758284523355],"type":"Point"}
}