{
  "type": "Feature",
  "properties": {
    "iso:country":"GB",
    "wof:name":"NR11 8NR",
    "wof:placetype":"postalcode"
},
  "geometry": {"coordinates":[1.35441973795601,52.88094449936483],"type":"Point"}
}