{
  "type": "Feature",
  "properties": {
    "iso:country": "GB",
    "wof:name": "NR11 8NR",
    "wof:placetype": "postalcode"
  },
  "geometry": {"coordinates":[1.354485,52.880981],"type":"Point"}
}
