{
  "type": "Feature",
  "properties": {
    "iso:country": "GB",
    "wof:name": "NR11 8NR",
    "wof:placetype": "postalcode"
  },
  "geometry": {"coordinates":[1.35442,52.880944],"type":"Point"}
}
