{
  "type": "Feature",
  "properties": {
    "iso:country":"GB",
    "wof:name":"CT13 9QB",
    "wof:placetype":"postalcode"
},
  "geometry": {"coordinates":[1.37691396006135,51.28420717439905],"type":"Point"}
}