{
  "type": "Feature",
  "properties": {
    "date:inception_lower": "1980-01-01",
    "date:inception_upper": "1980-01-01",
    "iso:country": "GB",
    "wof:name": "CT13 9QB",
    "wof:placetype": "postalcode"
  },
  "geometry": {"coordinates":[1.376914,51.284207],"type":"Point"}
}
