{
  "type": "Feature",
  "properties": {
    "date:inception_lower":"1986-07-01",
    "date:inception_upper":"1986-07-31",
    "iso:country":"GB",
    "wof:name":"EX39 3RG",
    "wof:placetype":"postalcode"
},
  "geometry": {"coordinates":[-4.229853,51.018085],"type":"Point"}
}