{
  "type": "Feature",
  "properties": {
    "date:inception_lower": "1980-01-01",
    "date:inception_upper": "1980-01-01",
    "iso:country": "GB",
    "wof:name": "MK42 0LD",
    "wof:placetype": "postalcode"
  },
  "geometry": {"coordinates":[-0.44216,52.124472],"type":"Point"}
}
