{
  "type": "Feature",
  "properties": {
    "iso:country": "GB",
    "wof:name": "SY13 3HE",
    "wof:placetype": "postalcode"
  },
  "geometry": {"coordinates":[-2.761746,52.951649],"type":"Point"}
}
