{
  "type": "Feature",
  "properties": {
    "date:inception_lower":"1980-01-01",
    "date:inception_upper":"1980-01-31",
    "iso:country":"GB",
    "wof:name":"SY13 3HE",
    "wof:placetype":"postalcode"
},
  "geometry": {"coordinates":[-2.761746,52.951649],"type":"Point"}
}