{
  "type": "Feature",
  "properties": {
    "iso:country":"GB",
    "wof:name":"SY13 3HE",
    "wof:placetype":"postalcode"
},
  "geometry": {"coordinates":[-2.76174554908921,52.95164889411675],"type":"Point"}
}