{
  "type": "Feature",
  "properties": {
    "iso:country": "GB",
    "wof:name": "S44 6QU",
    "wof:placetype": "postalcode"
  },
  "geometry": {"coordinates":[-1.302351,53.250918],"type":"Point"}
}
