{
  "type": "Feature",
  "properties": {
    "iso:country":"GB",
    "wof:name":"S44 6QU",
    "wof:placetype":"postalcode"
},
  "geometry": {"coordinates":[-1.3023508566149,53.25091840366014],"type":"Point"}
}