{
  "type": "Feature",
  "properties": {
    "iso:country":"GB",
    "wof:name":"CO4 0DY",
    "wof:placetype":"postalcode"
},
  "geometry": {"coordinates":[0.9265388929605,51.89636487505582],"type":"Point"}
}