{
  "type": "Feature",
  "properties": {
    "date:inception_lower": "1980-01-01",
    "date:inception_upper": "1980-01-01",
    "iso:country": "GB",
    "wof:name": "LE15 7JX",
    "wof:placetype": "postalcode"
  },
  "geometry": {"coordinates":[-0.748451,52.691586],"type":"Point"}
}
