{
  "type": "Feature",
  "properties": {
    "iso:country":"GB",
    "wof:name":"LE15 7JX",
    "wof:placetype":"postalcode"
},
  "geometry": {"coordinates":[-0.74845152140442,52.69158588743883],"type":"Point"}
}