{
  "type": "Feature",
  "properties": {
    "iso:country":"GB",
    "wof:name":"TS10 3DW",
    "wof:placetype":"postalcode"
},
  "geometry": {"coordinates":[-1.06385233990253,54.61826502475436],"type":"Point"}
}