{
  "type": "Feature",
  "properties": {
    "date:inception_lower":"2008-01-01",
    "date:inception_upper":"2008-01-31",
    "iso:country":"GB",
    "wof:name":"TS10 3DW",
    "wof:placetype":"postalcode"
},
  "geometry": {"coordinates":[-1.063932,54.618179],"type":"Point"}
}