{
  "type": "Feature",
  "properties": {
    "iso:country":"GB",
    "wof:name":"GU14 8AZ",
    "wof:placetype":"postalcode"
},
  "geometry": {"coordinates":[-0.75151526663145,51.30324007803405],"type":"Point"}
}