{
  "type": "Feature",
  "properties": {
    "iso:country":"GB",
    "wof:name":"LU7 1NR",
    "wof:placetype":"postalcode"
},
  "geometry": {"coordinates":[-0.65767903837095,51.91646291556367],"type":"Point"}
}