{
  "type": "Feature",
  "properties": {
    "iso:country":"GB",
    "wof:name":"HS1 2TY",
    "wof:placetype":"postalcode"
},
  "geometry": {"coordinates":[-6.39522280484262,58.22209152609724],"type":"Point"}
}