{
  "type": "Feature",
  "properties": {
    "date:inception_lower": "1980-01-01",
    "date:inception_upper": "1980-01-01",
    "iso:country": "GB",
    "wof:name": "WV8 1HE",
    "wof:placetype": "postalcode"
  },
  "geometry": {"coordinates":[-2.18593,52.624957],"type":"Point"}
}
