{
  "type": "Feature",
  "properties": {
    "iso:country":"GB",
    "wof:name":"HU16 4HD",
    "wof:placetype":"postalcode"
},
  "geometry": {"coordinates":[-0.41218294149245,53.79379584474878],"type":"Point"}
}