{
  "type": "Feature",
  "properties": {
    "iso:country":"GB",
    "wof:name":"AB21 9SL",
    "wof:placetype":"postalcode"
},
  "geometry": {"coordinates":[-2.19953922021424,57.18420372354677],"type":"Point"}
}