{
  "type": "Feature",
  "properties": {
    "iso:country":"GB",
    "wof:name":"FK9 4DB",
    "wof:placetype":"postalcode"
},
  "geometry": {"coordinates":[-3.9475449659535,56.14505942798232],"type":"Point"}
}