{
  "type": "Feature",
  "properties": {
    "iso:country": "GB",
    "wof:name": "SP3 6PR",
    "wof:placetype": "postalcode"
  },
  "geometry": {"coordinates":[-2.084992,51.059022],"type":"Point"}
}
