{
  "type": "Feature",
  "properties": {
    "iso:country":"GB",
    "wof:name":"SP3 6PR",
    "wof:placetype":"postalcode"
},
  "geometry": {"coordinates":[-2.08499190698441,51.05902167612786],"type":"Point"}
}