{
  "type": "Feature",
  "properties": {
    "date:inception_lower": "1980-01-01",
    "date:inception_upper": "1980-01-01",
    "iso:country": "GB",
    "wof:name": "EX15 2NL",
    "wof:placetype": "postalcode"
  },
  "geometry": {"coordinates":[-3.378125,50.791947],"type":"Point"}
}
