{
  "type": "Feature",
  "properties": {
    "date:inception_lower": "1980-01-01",
    "date:inception_upper": "1980-01-01",
    "iso:country": "GB",
    "wof:name": "EX15 2NL",
    "wof:placetype": "postalcode"
  },
  "geometry": {"coordinates":[-3.37812,50.792253],"type":"Point"}
}
