{
  "type": "Feature",
  "properties": {
    "iso:country":"GB",
    "wof:name":"EX15 2NL",
    "wof:placetype":"postalcode"
},
  "geometry": {"coordinates":[-3.3781120903346,50.7919566936571],"type":"Point"}
}