{
  "type": "Feature",
  "properties": {
    "iso:country": "GB",
    "wof:name": "RH3 7BA",
    "wof:placetype": "postalcode"
  },
  "geometry": {"coordinates":[-0.251751,51.243024],"type":"Point"}
}
