{
  "type": "Feature",
  "properties": {
    "iso:country": "GB",
    "wof:name": "BN14 7AJ",
    "wof:placetype": "postalcode"
  },
  "geometry": {"coordinates":[-0.376812,50.820916],"type":"Point"}
}
