{
  "type": "Feature",
  "properties": {
    "date:inception_lower": "2018-09-01",
    "date:inception_upper": "2018-09-01",
    "iso:country": "GB",
    "wof:name": "L9 1BF",
    "wof:placetype": "postalcode"
  },
  "geometry": {"coordinates":[-2.970393,53.450655],"type":"Point"}
}
