{
  "type": "Feature",
  "properties": {
    "date:inception_lower":"1980-01-01",
    "date:inception_upper":"1980-01-31",
    "iso:country":"GB",
    "wof:name":"LL40 1SH",
    "wof:placetype":"postalcode"
},
  "geometry": {"coordinates":[-3.892816,52.740965],"type":"Point"}
}