{
  "type": "Feature",
  "properties": {
    "iso:country":"GB",
    "wof:name":"G69 6AY",
    "wof:placetype":"postalcode"
},
  "geometry": {"coordinates":[-4.10221848311956,55.85642448030421],"type":"Point"}
}