{
  "type": "Feature",
  "properties": {
    "date:inception_lower": "1980-01-01",
    "date:inception_upper": "1980-01-01",
    "iso:country": "GB",
    "wof:name": "G69 6AY",
    "wof:placetype": "postalcode"
  },
  "geometry": {"coordinates":[-4.102218,55.856424],"type":"Point"}
}
