{
  "type": "Feature",
  "properties": {
    "date:inception_lower": "1980-01-01",
    "date:inception_upper": "1980-01-01",
    "iso:country": "GB",
    "wof:name": "CW7 4AL",
    "wof:placetype": "postalcode"
  },
  "geometry": {"coordinates":[-2.522773,53.18991],"type":"Point"}
}
