{
  "type": "Feature",
  "properties": {
    "iso:country":"GB",
    "wof:name":"SA33 5LE",
    "wof:placetype":"postalcode"
},
  "geometry": {"coordinates":[-4.39058492971605,51.77373783267743],"type":"Point"}
}