{
  "type": "Feature",
  "properties": {
    "date:inception_lower":"2011-05-01",
    "date:inception_upper":"2011-05-31",
    "iso:country":"GB",
    "wof:name":"SE1 8SW",
    "wof:placetype":"postalcode"
},
  "geometry": {"coordinates":[-0.113277,51.502706],"type":"Point"}
}