{
  "type": "Feature",
  "properties": {
    "iso:country":"GB",
    "wof:name":"SE1 8SW",
    "wof:placetype":"postalcode"
},
  "geometry": {"coordinates":[-0.1132774386912,51.50270612258222],"type":"Point"}
}