{
  "type": "Feature",
  "properties": {
    "date:inception_lower":"1980-01-01",
    "date:inception_upper":"1980-01-31",
    "iso:country":"GB",
    "wof:name":"IP1 5BQ",
    "wof:placetype":"postalcode"
},
  "geometry": {"coordinates":[1.115846,52.069203],"type":"Point"}
}