{
  "type": "Feature",
  "properties": {
    "iso:country":"GB",
    "wof:name":"WN8 8NH",
    "wof:placetype":"postalcode"
},
  "geometry": {"coordinates":[-2.79009340769668,53.54983625160244],"type":"Point"}
}