{
  "type": "Feature",
  "properties": {
    "date:inception_lower":"1998-06-01",
    "date:inception_upper":"1998-06-30",
    "iso:country":"GB",
    "wof:name":"YO31 0SB",
    "wof:placetype":"postalcode"
},
  "geometry": {"coordinates":[-1.058289,53.963736],"type":"Point"}
}