{
  "type": "Feature",
  "properties": {
    "date:inception_lower": "1980-01-01",
    "date:inception_upper": "1980-01-01",
    "iso:country": "GB",
    "wof:name": "EH14 3DG",
    "wof:placetype": "postalcode"
  },
  "geometry": {"coordinates":[-3.286278,55.91152],"type":"Point"}
}
