{
  "type": "Feature",
  "properties": {
    "date:inception_lower":"1980-01-01",
    "date:inception_upper":"1980-01-31",
    "iso:country":"GB",
    "wof:name":"PA15 4JA",
    "wof:placetype":"postalcode"
},
  "geometry": {"coordinates":[-4.76959,55.943055],"type":"Point"}
}