{
  "type": "Feature",
  "properties": {
    "iso:country": "GB",
    "wof:name": "PA15 4JA",
    "wof:placetype": "postalcode"
  },
  "geometry": {"coordinates":[-4.7695,55.943129],"type":"Point"}
}
