{
  "type": "Feature",
  "properties": {
    "date:inception_lower":"1980-01-01",
    "date:inception_upper":"1980-01-31",
    "iso:country":"GB",
    "wof:name":"RH12 4LB",
    "wof:placetype":"postalcode"
},
  "geometry": {"coordinates":[-0.297962,51.078885],"type":"Point"}
}