{
  "type": "Feature",
  "properties": {
    "iso:country":"GB",
    "wof:name":"RH12 4LB",
    "wof:placetype":"postalcode"
},
  "geometry": {"coordinates":[-0.29796156494784,51.07888463816325],"type":"Point"}
}