{
  "type": "Feature",
  "properties": {
    "iso:country":"GB",
    "wof:name":"LN1 2TS",
    "wof:placetype":"postalcode"
},
  "geometry": {"coordinates":[-0.59609453849208,53.24952196823951],"type":"Point"}
}