{
  "type": "Feature",
  "properties": {
    "date:inception_lower": "2007-02-01",
    "date:inception_upper": "2007-02-01",
    "iso:country": "GB",
    "wof:name": "OX49 5AA",
    "wof:placetype": "postalcode"
  },
  "geometry": {"coordinates":[-0.999368,51.613126],"type":"Point"}
}
