{
  "type": "Feature",
  "properties": {
    "iso:country": "GB",
    "wof:name": "OX49 5AA",
    "wof:placetype": "postalcode"
  },
  "geometry": {"coordinates":[-0.999368,51.613126],"type":"Point"}
}
