{
  "type": "Feature",
  "properties": {
    "iso:country":"GB",
    "wof:name":"OX49 5AA",
    "wof:placetype":"postalcode"
},
  "geometry": {"coordinates":[-0.9993886715049,51.61312256203428],"type":"Point"}
}