{
  "type": "Feature",
  "properties": {
    "iso:country":"GB",
    "wof:name":"KA10 6DN",
    "wof:placetype":"postalcode"
},
  "geometry": {"coordinates":[-4.6812816262914,55.54582106855963],"type":"Point"}
}