{
  "type": "Feature",
  "properties": {
    "iso:country": "GB",
    "wof:name": "KA10 6DN",
    "wof:placetype": "postalcode"
  },
  "geometry": {"coordinates":[-4.681261,55.54583],"type":"Point"}
}
