{
  "type": "Feature",
  "properties": {
    "date:inception_lower": "2004-09-01",
    "date:inception_upper": "2004-09-01",
    "iso:country": "GB",
    "wof:name": "KA10 6DN",
    "wof:placetype": "postalcode"
  },
  "geometry": {"coordinates":[-4.681261,55.54583],"type":"Point"}
}
