{
  "type": "Feature",
  "properties": {
    "iso:country":"GB",
    "wof:name":"EH47 8ND",
    "wof:placetype":"postalcode"
},
  "geometry": {"coordinates":[-3.68007813708619,55.86533097577573],"type":"Point"}
}