{
  "type": "Feature",
  "properties": {
    "iso:country": "GB",
    "wof:name": "WA8 6TX",
    "wof:placetype": "postalcode"
  },
  "geometry": {"coordinates":[-2.721709,53.378646],"type":"Point"}
}
