{
  "type": "Feature",
  "properties": {
    "iso:country": "GB",
    "wof:name": "BS15 3NR",
    "wof:placetype": "postalcode"
  },
  "geometry": {"coordinates":[-2.513412,51.435486],"type":"Point"}
}
