{
  "type": "Feature",
  "properties": {
    "iso:country":"GB",
    "wof:name":"BS15 3NR",
    "wof:placetype":"postalcode"
},
  "geometry": {"coordinates":[-2.51341252919042,51.43548636012076],"type":"Point"}
}