{
  "type": "Feature",
  "properties": {
    "date:inception_lower": "1980-01-01",
    "date:inception_upper": "1980-01-01",
    "iso:country": "GB",
    "wof:name": "BS15 3NR",
    "wof:placetype": "postalcode"
  },
  "geometry": {"coordinates":[-2.513412,51.435486],"type":"Point"}
}
