{
  "type": "Feature",
  "properties": {
    "iso:country":"GB",
    "wof:name":"SG13 8HQ",
    "wof:placetype":"postalcode"
},
  "geometry": {"coordinates":[-0.08270607523468,51.78765585013873],"type":"Point"}
}