{
  "type": "Feature",
  "properties": {
    "iso:country":"GB",
    "wof:name":"BS23 4DU",
    "wof:placetype":"postalcode"
},
  "geometry": {"coordinates":[-2.97958197588229,51.33461266883157],"type":"Point"}
}