{
  "type": "Feature",
  "properties": {
    "iso:country":"GB",
    "wof:name":"CO2 8JB",
    "wof:placetype":"postalcode"
},
  "geometry": {"coordinates":[0.92610143226242,51.88203088468433],"type":"Point"}
}