{
  "type": "Feature",
  "properties": {
    "iso:country":"GB",
    "wof:name":"WR11 4JG",
    "wof:placetype":"postalcode"
},
  "geometry": {"coordinates":[-1.94814597129657,52.09805411947465],"type":"Point"}
}