{
  "type": "Feature",
  "properties": {
    "iso:country": "GB",
    "wof:name": "LL13 9JG",
    "wof:placetype": "postalcode"
  },
  "geometry": {"coordinates":[-2.880131,53.081861],"type":"Point"}
}
