{
  "type": "Feature",
  "properties": {
    "iso:country":"GB",
    "wof:name":"LL13 9JG",
    "wof:placetype":"postalcode"
},
  "geometry": {"coordinates":[-2.88013147053657,53.08186087741341],"type":"Point"}
}