{
  "type": "Feature",
  "properties": {
    "iso:country":"GB",
    "wof:name":"AB54 4JP",
    "wof:placetype":"postalcode"
},
  "geometry": {"coordinates":[-2.87472512272726,57.28466662525605],"type":"Point"}
}