{
  "type": "Feature",
  "properties": {
    "iso:country":"GB",
    "wof:name":"NR17 1AQ",
    "wof:placetype":"postalcode"
},
  "geometry": {"coordinates":[0.98870303827161,52.54115745901812],"type":"Point"}
}