{
  "type": "Feature",
  "properties": {
    "iso:country":"GB",
    "wof:name":"SY3 7LU",
    "wof:placetype":"postalcode"
},
  "geometry": {"coordinates":[-2.7478528379799,52.700746537165],"type":"Point"}
}