{
  "type": "Feature",
  "properties": {
    "date:inception_lower": "1980-01-01",
    "date:inception_upper": "1980-01-01",
    "iso:country": "GB",
    "wof:name": "NG11 9HJ",
    "wof:placetype": "postalcode"
  },
  "geometry": {"coordinates":[-1.189459,52.898894],"type":"Point"}
}
