{
  "type": "Feature",
  "properties": {
    "iso:country":"GB",
    "wof:name":"NG11 9HJ",
    "wof:placetype":"postalcode"
},
  "geometry": {"coordinates":[-1.18945912588828,52.89889374386605],"type":"Point"}
}