{
  "type": "Feature",
  "properties": {
    "iso:country":"GB",
    "wof:name":"BL2 4EY",
    "wof:placetype":"postalcode"
},
  "geometry": {"coordinates":[-2.37553515530266,53.59954942295929],"type":"Point"}
}