{
  "type": "Feature",
  "properties": {
    "iso:country":"GB",
    "wof:name":"PO34 5AQ",
    "wof:placetype":"postalcode"
},
  "geometry": {"coordinates":[-1.1165501162391,50.72025517209146],"type":"Point"}
}