{
  "type": "Feature",
  "properties": {
    "iso:country": "GB",
    "wof:name": "PO34 5AQ",
    "wof:placetype": "postalcode"
  },
  "geometry": {"coordinates":[-1.116595,50.72028],"type":"Point"}
}
