{
  "type": "Feature",
  "properties": {
    "iso:country":"GB",
    "wof:name":"ML4 2RP",
    "wof:placetype":"postalcode"
},
  "geometry": {"coordinates":[-4.00071410848829,55.81671440545782],"type":"Point"}
}