{
  "type": "Feature",
  "properties": {
    "iso:country":"GB",
    "wof:name":"G72 7AQ",
    "wof:placetype":"postalcode"
},
  "geometry": {"coordinates":[-4.1900170122582,55.81803557272974],"type":"Point"}
}