{
  "type": "Feature",
  "properties": {
    "iso:country":"GB",
    "wof:name":"M11 4LZ",
    "wof:placetype":"postalcode"
},
  "geometry": {"coordinates":[-2.17707471411412,53.48811209147625],"type":"Point"}
}