{
  "type": "Feature",
  "properties": {
    "iso:country":"GB",
    "wof:name":"CB22 4SE",
    "wof:placetype":"postalcode"
},
  "geometry": {"coordinates":[0.15496510566292,52.09526626034207],"type":"Point"}
}