{
  "type": "Feature",
  "properties": {
    "date:inception_lower":"2006-09-01",
    "date:inception_upper":"2006-09-30",
    "iso:country":"GB",
    "wof:name":"CB22 4SE",
    "wof:placetype":"postalcode"
},
  "geometry": {"coordinates":[0.154965,52.095266],"type":"Point"}
}