{
  "type": "Feature",
  "properties": {
    "iso:country":"GB",
    "wof:name":"BB2 3UP",
    "wof:placetype":"postalcode"
},
  "geometry": {"coordinates":[-2.46841659621929,53.72606386903453],"type":"Point"}
}