{
  "type": "Feature",
  "properties": {
    "iso:country": "GB",
    "wof:name": "PR9 9TT",
    "wof:placetype": "postalcode"
  },
  "geometry": {"coordinates":[-2.960016,53.676492],"type":"Point"}
}
