{
  "type": "Feature",
  "properties": {
    "iso:country":"GB",
    "wof:name":"LS5 3RB",
    "wof:placetype":"postalcode"
},
  "geometry": {"coordinates":[-1.61906556886677,53.82492071162186],"type":"Point"}
}