{
  "type": "Feature",
  "properties": {
    "iso:country": "GB",
    "wof:name": "LS5 3RB",
    "wof:placetype": "postalcode"
  },
  "geometry": {"coordinates":[-1.619066,53.824921],"type":"Point"}
}
