{
  "type": "Feature",
  "properties": {
    "iso:country":"GB",
    "wof:name":"PL11 3EN",
    "wof:placetype":"postalcode"
},
  "geometry": {"coordinates":[-4.29514456930239,50.3731912837245],"type":"Point"}
}