{
  "type": "Feature",
  "properties": {
    "iso:country":"GB",
    "wof:name":"RG7 5UP",
    "wof:placetype":"postalcode"
},
  "geometry": {"coordinates":[-1.21782047540312,51.39980843253839],"type":"Point"}
}