{
  "type": "Feature",
  "properties": {
    "iso:country": "GB",
    "wof:name": "LE12 7EX",
    "wof:placetype": "postalcode"
  },
  "geometry": {"coordinates":[-1.148263,52.722092],"type":"Point"}
}
