{
  "type": "Feature",
  "properties": {
    "iso:country":"GB",
    "wof:name":"LE12 7EX",
    "wof:placetype":"postalcode"
},
  "geometry": {"coordinates":[-1.14826294227372,52.72209245393054],"type":"Point"}
}