{
  "type": "Feature",
  "properties": {
    "date:inception_lower":"1995-07-01",
    "date:inception_upper":"1995-07-31",
    "iso:country":"GB",
    "wof:name":"RG41 5LE",
    "wof:placetype":"postalcode"
},
  "geometry": {"coordinates":[-0.866089,51.431662],"type":"Point"}
}