{
  "type": "Feature",
  "properties": {
    "iso:country":"GB",
    "wof:name":"RG41 5LE",
    "wof:placetype":"postalcode"
},
  "geometry": {"coordinates":[-0.86613649684894,51.43166133802957],"type":"Point"}
}