{
  "type": "Feature",
  "properties": {
    "date:inception_lower":"2006-03-01",
    "date:inception_upper":"2006-03-31",
    "iso:country":"GB",
    "wof:name":"CF11 0SA",
    "wof:placetype":"postalcode"
},
  "geometry": {"coordinates":[-3.188194,51.449749],"type":"Point"}
}