{
  "type": "Feature",
  "properties": {
    "iso:country":"GB",
    "wof:name":"GL4 0PX",
    "wof:placetype":"postalcode"
},
  "geometry": {"coordinates":[-2.2549799423883,51.83380219364408],"type":"Point"}
}