{
  "type": "Feature",
  "properties": {
    "iso:country":"GB",
    "wof:name":"LS8 2JX",
    "wof:placetype":"postalcode"
},
  "geometry": {"coordinates":[-1.49373755467433,53.8297065706707],"type":"Point"}
}