{
  "type": "Feature",
  "properties": {
    "iso:country":"GB",
    "wof:name":"MK5 7FQ",
    "wof:placetype":"postalcode"
},
  "geometry": {"coordinates":[-0.78301429000111,52.01262892859303],"type":"Point"}
}