{
  "type": "Feature",
  "properties": {
    "date:inception_lower": "2021-09-01",
    "date:inception_upper": "2021-09-01",
    "iso:country": "GB",
    "wof:name": "CO11 1FL",
    "wof:placetype": "postalcode"
  },
  "geometry": {"coordinates":[1.065215,51.959589],"type":"Point"}
}
