{
  "type": "Feature",
  "properties": {
    "iso:country":"GB",
    "wof:name":"PH1 3LT",
    "wof:placetype":"postalcode"
},
  "geometry": {"coordinates":[-3.51949711704917,56.42661434194503],"type":"Point"}
}