{
  "type": "Feature",
  "properties": {
    "date:inception_lower": "1980-01-01",
    "date:inception_upper": "1980-01-01",
    "iso:country": "GB",
    "wof:name": "KA30 8HP",
    "wof:placetype": "postalcode"
  },
  "geometry": {"coordinates":[-4.860786,55.78908],"type":"Point"}
}
