{
  "type": "Feature",
  "properties": {
    "iso:country":"GB",
    "wof:name":"KA30 8HP",
    "wof:placetype":"postalcode"
},
  "geometry": {"coordinates":[-4.86078588481536,55.78907981914126],"type":"Point"}
}