{
  "type": "Feature",
  "properties": {
    "iso:country":"GB",
    "wof:name":"SA1 5BY",
    "wof:placetype":"postalcode"
},
  "geometry": {"coordinates":[-3.94427471476236,51.62205951135589],"type":"Point"}
}