{
  "type": "Feature",
  "properties": {
    "date:inception_lower": "1980-01-01",
    "date:inception_upper": "1980-01-01",
    "iso:country": "GB",
    "wof:name": "SA1 5BY",
    "wof:placetype": "postalcode"
  },
  "geometry": {"coordinates":[-3.944275,51.62206],"type":"Point"}
}
