{
  "type": "Feature",
  "properties": {
    "iso:country":"GB",
    "wof:name":"BA5 2EJ",
    "wof:placetype":"postalcode"
},
  "geometry": {"coordinates":[-2.66381676663072,51.20681387940932],"type":"Point"}
}