{
  "type": "Feature",
  "properties": {
    "iso:country":"GB",
    "wof:name":"NE24 3RW",
    "wof:placetype":"postalcode"
},
  "geometry": {"coordinates":[-1.51750733705865,55.10707119537972],"type":"Point"}
}