{
  "type": "Feature",
  "properties": {
    "iso:country": "GB",
    "wof:name": "NE24 3RW",
    "wof:placetype": "postalcode"
  },
  "geometry": {"coordinates":[-1.517507,55.107071],"type":"Point"}
}
