{
  "type": "Feature",
  "properties": {
    "iso:country":"GB",
    "wof:name":"L14 6TX",
    "wof:placetype":"postalcode"
},
  "geometry": {"coordinates":[-2.87230424867454,53.41019093781616],"type":"Point"}
}