{
  "type": "Feature",
  "properties": {
    "iso:country":"GB",
    "wof:name":"PL25 3HB",
    "wof:placetype":"postalcode"
},
  "geometry": {"coordinates":[-4.76479855819959,50.34377233769481],"type":"Point"}
}