{
  "type": "Feature",
  "properties": {
    "date:inception_lower":"1980-01-01",
    "date:inception_upper":"1980-01-31",
    "iso:country":"GB",
    "wof:name":"PL25 3HB",
    "wof:placetype":"postalcode"
},
  "geometry": {"coordinates":[-4.764799,50.343772],"type":"Point"}
}