{
  "type": "Feature",
  "properties": {
    "iso:country":"GB",
    "wof:name":"TR4 9DE",
    "wof:placetype":"postalcode"
},
  "geometry": {"coordinates":[-5.07723073860811,50.28949044407431],"type":"Point"}
}