{
  "type": "Feature",
  "properties": {
    "date:inception_lower":"1980-01-01",
    "date:inception_upper":"1980-01-31",
    "iso:country":"GB",
    "wof:name":"TR4 9DE",
    "wof:placetype":"postalcode"
},
  "geometry": {"coordinates":[-5.077231,50.28949],"type":"Point"}
}