{
  "type": "Feature",
  "properties": {
    "iso:country":"GB",
    "wof:name":"NG24 2JS",
    "wof:placetype":"postalcode"
},
  "geometry": {"coordinates":[-0.78386399520713,53.07543613973315],"type":"Point"}
}