{
  "type": "Feature",
  "properties": {
    "iso:country":"GB",
    "wof:name":"EX2 4HX",
    "wof:placetype":"postalcode"
},
  "geometry": {"coordinates":[-3.52636840815695,50.72057458168199],"type":"Point"}
}