{
  "type": "Feature",
  "properties": {
    "date:inception_lower": "1998-12-01",
    "date:inception_upper": "1998-12-01",
    "iso:country": "GB",
    "wof:name": "EC3N 4AT",
    "wof:placetype": "postalcode"
  },
  "geometry": {"coordinates":[-0.079461,51.510215],"type":"Point"}
}
