{
  "type": "Feature",
  "properties": {
    "iso:country":"GB",
    "wof:name":"PO8 9TR",
    "wof:placetype":"postalcode"
},
  "geometry": {"coordinates":[-1.02480039991559,50.91094446578683],"type":"Point"}
}