{
  "type": "Feature",
  "properties": {
    "date:inception_lower":"1980-01-01",
    "date:inception_upper":"1980-01-31",
    "iso:country":"GB",
    "wof:name":"DH9 7EU",
    "wof:placetype":"postalcode"
},
  "geometry": {"coordinates":[-1.702729,54.855151],"type":"Point"}
}