{
  "type": "Feature",
  "properties": {
    "iso:country":"GB",
    "wof:name":"ME8 7QD",
    "wof:placetype":"postalcode"
},
  "geometry": {"coordinates":[0.61823342457475,51.36982867778581],"type":"Point"}
}