{
  "type": "Feature",
  "properties": {
    "date:inception_lower":"1985-10-01",
    "date:inception_upper":"1985-10-31",
    "iso:country":"GB",
    "wof:name":"BH24 1JW",
    "wof:placetype":"postalcode"
},
  "geometry": {"coordinates":[-1.788045,50.848378],"type":"Point"}
}