{
  "type": "Feature",
  "properties": {
    "iso:country":"GB",
    "wof:name":"CM22 6PQ",
    "wof:placetype":"postalcode"
},
  "geometry": {"coordinates":[0.27125818235332,51.8988375409124],"type":"Point"}
}