{
  "type": "Feature",
  "properties": {
    "iso:country": "GB",
    "wof:name": "TQ9 5JX",
    "wof:placetype": "postalcode"
  },
  "geometry": {"coordinates":[-3.695509,50.437851],"type":"Point"}
}
