{
  "type": "Feature",
  "properties": {
    "date:inception_lower": "1980-01-01",
    "date:inception_upper": "1980-01-01",
    "iso:country": "GB",
    "wof:name": "EX22 6PX",
    "wof:placetype": "postalcode"
  },
  "geometry": {"coordinates":[-4.365966,50.764781],"type":"Point"}
}
