{
  "type": "Feature",
  "properties": {
    "iso:country": "GB",
    "wof:name": "EX22 6PX",
    "wof:placetype": "postalcode"
  },
  "geometry": {"coordinates":[-4.365966,50.764781],"type":"Point"}
}
