{
  "type": "Feature",
  "properties": {
    "iso:country":"GB",
    "wof:name":"EX22 6PX",
    "wof:placetype":"postalcode"
},
  "geometry": {"coordinates":[-4.36596613665859,50.76478093937108],"type":"Point"}
}