{
  "type": "Feature",
  "properties": {
    "date:inception_lower": "1980-01-01",
    "date:inception_upper": "1980-01-01",
    "iso:country": "GB",
    "wof:name": "LL11 4RR",
    "wof:placetype": "postalcode"
  },
  "geometry": {"coordinates":[-3.017837,53.076726],"type":"Point"}
}
