{
  "type": "Feature",
  "properties": {
    "date:inception_lower": "1998-06-01",
    "date:inception_upper": "1998-06-01",
    "iso:country": "GB",
    "wof:name": "GL5 1XR",
    "wof:placetype": "postalcode"
  },
  "geometry": {"coordinates":[-2.200798,51.753878],"type":"Point"}
}
