{
  "type": "Feature",
  "properties": {
    "iso:country": "GB",
    "wof:name": "GL5 1XR",
    "wof:placetype": "postalcode"
  },
  "geometry": {"coordinates":[-2.200798,51.753878],"type":"Point"}
}
