{
  "type": "Feature",
  "properties": {
    "iso:country":"GB",
    "wof:name":"EH19 2BQ",
    "wof:placetype":"postalcode"
},
  "geometry": {"coordinates":[-3.11708308106491,55.87541379742336],"type":"Point"}
}