{
  "type": "Feature",
  "properties": {
    "iso:country": "GB",
    "wof:name": "SN5 5QU",
    "wof:placetype": "postalcode"
  },
  "geometry": {"coordinates":[-1.830135,51.568816],"type":"Point"}
}
