{
  "type": "Feature",
  "properties": {
    "iso:country":"GB",
    "wof:name":"SN5 5QU",
    "wof:placetype":"postalcode"
},
  "geometry": {"coordinates":[-1.83013541027075,51.5688164709622],"type":"Point"}
}