{
  "type": "Feature",
  "properties": {
    "date:inception_lower":"2008-10-01",
    "date:inception_upper":"2008-10-31",
    "iso:country":"GB",
    "wof:name":"SG17 5FJ",
    "wof:placetype":"postalcode"
},
  "geometry": {"coordinates":[-0.326793,52.037424],"type":"Point"}
}