{
  "type": "Feature",
  "properties": {
    "iso:country": "GB",
    "wof:name": "SG17 5FJ",
    "wof:placetype": "postalcode"
  },
  "geometry": {"coordinates":[-0.326793,52.037424],"type":"Point"}
}
