{
  "type": "Feature",
  "properties": {
    "date:inception_lower": "2018-11-01",
    "date:inception_upper": "2018-11-01",
    "iso:country": "GB",
    "wof:name": "TR11 4FZ",
    "wof:placetype": "postalcode"
  },
  "geometry": {"coordinates":[-5.097575,50.151383],"type":"Point"}
}
