{
  "type": "Feature",
  "properties": {
    "iso:country":"GB",
    "wof:name":"UB8 3DY",
    "wof:placetype":"postalcode"
},
  "geometry": {"coordinates":[-0.44318087405756,51.52617188563285],"type":"Point"}
}