{
  "type": "Feature",
  "properties": {
    "iso:country": "GB",
    "wof:name": "LS15 9BG",
    "wof:placetype": "postalcode"
  },
  "geometry": {"coordinates":[-1.448552,53.796135],"type":"Point"}
}
