{
  "type": "Feature",
  "properties": {
    "iso:country":"GB",
    "wof:name":"S73 9HB",
    "wof:placetype":"postalcode"
},
  "geometry": {"coordinates":[-1.37282496640369,53.53629721604951],"type":"Point"}
}