{
  "type": "Feature",
  "properties": {
    "iso:country":"GB",
    "wof:name":"CM3 2LH",
    "wof:placetype":"postalcode"
},
  "geometry": {"coordinates":[0.59639080440367,51.77236707470154],"type":"Point"}
}