{
  "type": "Feature",
  "properties": {
    "iso:country": "GB",
    "wof:name": "CM3 2LH",
    "wof:placetype": "postalcode"
  },
  "geometry": {"coordinates":[0.596391,51.772367],"type":"Point"}
}
