{
  "type": "Feature",
  "properties": {
    "date:inception_lower": "1983-03-01",
    "date:inception_upper": "1983-03-01",
    "iso:country": "GB",
    "wof:name": "BL4 7SX",
    "wof:placetype": "postalcode"
  },
  "geometry": {"coordinates":[-2.405392,53.55042],"type":"Point"}
}
