{
  "type": "Feature",
  "properties": {
    "iso:country":"GB",
    "wof:name":"BH14 8NA",
    "wof:placetype":"postalcode"
},
  "geometry": {"coordinates":[-1.93999081778166,50.70388180309924],"type":"Point"}
}