{
  "type": "Feature",
  "properties": {
    "iso:country": "GB",
    "wof:name": "BD16 1HQ",
    "wof:placetype": "postalcode"
  },
  "geometry": {"coordinates":[-1.836027,53.845546],"type":"Point"}
}
