{
  "type": "Feature",
  "properties": {
    "iso:country":"GB",
    "wof:name":"BD16 1HQ",
    "wof:placetype":"postalcode"
},
  "geometry": {"coordinates":[-1.83602705787992,53.8455458761258],"type":"Point"}
}