{
  "type": "Feature",
  "properties": {
    "iso:country":"GB",
    "wof:name":"GL7 7BY",
    "wof:placetype":"postalcode"
},
  "geometry": {"coordinates":[-1.97935603415055,51.77809045002681],"type":"Point"}
}