{
  "type": "Feature",
  "properties": {
    "date:inception_lower":"1980-01-01",
    "date:inception_upper":"1980-01-31",
    "iso:country":"GB",
    "wof:name":"GL7 7BY",
    "wof:placetype":"postalcode"
},
  "geometry": {"coordinates":[-1.979356,51.77809],"type":"Point"}
}