{
  "type": "Feature",
  "properties": {
    "iso:country": "GB",
    "wof:name": "GL7 7BY",
    "wof:placetype": "postalcode"
  },
  "geometry": {"coordinates":[-1.979356,51.77809],"type":"Point"}
}
