{
  "type": "Feature",
  "properties": {
    "date:inception_lower":"1997-12-01",
    "date:inception_upper":"1997-12-31",
    "iso:country":"GB",
    "wof:name":"SK13 6TF",
    "wof:placetype":"postalcode"
},
  "geometry": {"coordinates":[-1.98471,53.445422],"type":"Point"}
}