{
  "type": "Feature",
  "properties": {
    "iso:country":"GB",
    "wof:name":"N1 7QD",
    "wof:placetype":"postalcode"
},
  "geometry": {"coordinates":[-0.09329491240917,51.5323281546653],"type":"Point"}
}