{
  "type": "Feature",
  "properties": {
    "date:inception_lower": "1980-01-01",
    "date:inception_upper": "1980-01-01",
    "iso:country": "GB",
    "wof:name": "SK9 1QP",
    "wof:placetype": "postalcode"
  },
  "geometry": {"coordinates":[-2.240932,53.315501],"type":"Point"}
}
