{
  "type": "Feature",
  "properties": {
    "iso:country":"GB",
    "wof:name":"W1H 5BF",
    "wof:placetype":"postalcode"
},
  "geometry": {"coordinates":[-0.16142788735486,51.51496326020734],"type":"Point"}
}