{
  "type": "Feature",
  "properties": {
    "iso:country":"GB",
    "wof:name":"CF3 0AB",
    "wof:placetype":"postalcode"
},
  "geometry": {"coordinates":[-3.10839212813157,51.52498374792923],"type":"Point"}
}