{
  "type": "Feature",
  "properties": {
    "date:inception_lower":"1981-09-01",
    "date:inception_upper":"1981-09-30",
    "iso:country":"GB",
    "wof:name":"CF3 0AB",
    "wof:placetype":"postalcode"
},
  "geometry": {"coordinates":[-3.108392,51.524984],"type":"Point"}
}