{
  "type": "Feature",
  "properties": {
    "date:inception_lower":"1980-01-01",
    "date:inception_upper":"1980-01-31",
    "iso:country":"GB",
    "wof:name":"KT16 9HE",
    "wof:placetype":"postalcode"
},
  "geometry": {"coordinates":[-0.512206,51.391933],"type":"Point"}
}