{
  "type": "Feature",
  "properties": {
    "iso:country":"GB",
    "wof:name":"CB9 7JJ",
    "wof:placetype":"postalcode"
},
  "geometry": {"coordinates":[0.46424046431255,52.13530974363196],"type":"Point"}
}