{
  "type": "Feature",
  "properties": {
    "iso:country":"GB",
    "wof:name":"LE2 4TQ",
    "wof:placetype":"postalcode"
},
  "geometry": {"coordinates":[-1.06108942611908,52.5914569642858],"type":"Point"}
}