{
  "type": "Feature",
  "properties": {
    "date:inception_lower": "1983-07-01",
    "date:inception_upper": "1983-07-01",
    "iso:country": "GB",
    "wof:name": "LE2 4TQ",
    "wof:placetype": "postalcode"
  },
  "geometry": {"coordinates":[-1.061066,52.591467],"type":"Point"}
}
