{
  "type": "Feature",
  "properties": {
    "iso:country": "GB",
    "wof:name": "EN11 0DE",
    "wof:placetype": "postalcode"
  },
  "geometry": {"coordinates":[0.003247,51.764083],"type":"Point"}
}
