{
  "type": "Feature",
  "properties": {
    "iso:country": "GB",
    "wof:name": "CF14 5DY",
    "wof:placetype": "postalcode"
  },
  "geometry": {"coordinates":[-3.188035,51.527279],"type":"Point"}
}
