{
  "type": "Feature",
  "properties": {
    "iso:country":"GB",
    "wof:name":"TN5 7QB",
    "wof:placetype":"postalcode"
},
  "geometry": {"coordinates":[0.42490666754982,51.07256090784716],"type":"Point"}
}