{
  "type": "Feature",
  "properties": {
    "date:inception_lower": "1980-01-01",
    "date:inception_upper": "1980-01-01",
    "iso:country": "GB",
    "wof:name": "TN5 7QB",
    "wof:placetype": "postalcode"
  },
  "geometry": {"coordinates":[0.424907,51.072561],"type":"Point"}
}
