{
  "type": "Feature",
  "properties": {
    "iso:country":"GB",
    "wof:name":"TR13 8YQ",
    "wof:placetype":"postalcode"
},
  "geometry": {"coordinates":[-5.27096505187076,50.11029982202807],"type":"Point"}
}