{
  "type": "Feature",
  "properties": {
    "date:inception_lower": "1990-07-01",
    "date:inception_upper": "1990-07-01",
    "iso:country": "GB",
    "wof:name": "TR13 8YQ",
    "wof:placetype": "postalcode"
  },
  "geometry": {"coordinates":[-5.271016,50.110289],"type":"Point"}
}
