{
  "type": "Feature",
  "properties": {
    "iso:country": "GB",
    "wof:name": "TR13 8YQ",
    "wof:placetype": "postalcode"
  },
  "geometry": {"coordinates":[-5.270921,50.108897],"type":"Point"}
}
