{
  "type": "Feature",
  "properties": {
    "date:inception_lower": "1992-01-01",
    "date:inception_upper": "1992-01-01",
    "iso:country": "GB",
    "wof:name": "PE31 6YZ",
    "wof:placetype": "postalcode"
  },
  "geometry": {"coordinates":[0.47971,52.792266],"type":"Point"}
}
