{
  "type": "Feature",
  "properties": {
    "iso:country":"GB",
    "wof:name":"WS10 7HX",
    "wof:placetype":"postalcode"
},
  "geometry": {"coordinates":[-2.02529653478662,52.55643656576437],"type":"Point"}
}