{
  "type": "Feature",
  "properties": {
    "iso:country":"GB",
    "wof:name":"SO30 2BE",
    "wof:placetype":"postalcode"
},
  "geometry": {"coordinates":[-1.30273476443709,50.92904003125115],"type":"Point"}
}