{
  "type": "Feature",
  "properties": {
    "date:inception_lower":"2010-08-01",
    "date:inception_upper":"2010-08-31",
    "iso:country":"GB",
    "wof:name":"SO30 2BE",
    "wof:placetype":"postalcode"
},
  "geometry": {"coordinates":[-1.30271,50.929022],"type":"Point"}
}