{
  "type": "Feature",
  "properties": {
    "iso:country":"GB",
    "wof:name":"CV37 0DQ",
    "wof:placetype":"postalcode"
},
  "geometry": {"coordinates":[-1.71469770889076,52.20507627854325],"type":"Point"}
}