{
  "type": "Feature",
  "properties": {
    "date:inception_lower": "2006-07-01",
    "date:inception_upper": "2006-07-01",
    "iso:country": "GB",
    "wof:name": "SS7 1NZ",
    "wof:placetype": "postalcode"
  },
  "geometry": {"coordinates":[0.562805,51.545394],"type":"Point"}
}
