{
  "type": "Feature",
  "properties": {
    "iso:country":"GB",
    "wof:name":"SS7 1NZ",
    "wof:placetype":"postalcode"
},
  "geometry": {"coordinates":[0.56280455512923,51.54539444463402],"type":"Point"}
}