{
  "type": "Feature",
  "properties": {
    "iso:country":"GB",
    "wof:name":"SE26 4LE",
    "wof:placetype":"postalcode"
},
  "geometry": {"coordinates":[-0.05513141385148,51.42735087439276],"type":"Point"}
}