{
  "type": "Feature",
  "properties": {
    "date:inception_lower": "2005-01-01",
    "date:inception_upper": "2005-01-01",
    "iso:country": "GB",
    "wof:name": "LE2 7GG",
    "wof:placetype": "postalcode"
  },
  "geometry": {"coordinates":[-1.137544,52.624402],"type":"Point"}
}
