{
  "type": "Feature",
  "properties": {
    "iso:country":"GB",
    "wof:name":"NN7 3JS",
    "wof:placetype":"postalcode"
},
  "geometry": {"coordinates":[-1.0383955574229,52.21909056830855],"type":"Point"}
}