{
  "type": "Feature",
  "properties": {
    "iso:country": "GB",
    "wof:name": "NN7 3JS",
    "wof:placetype": "postalcode"
  },
  "geometry": {"coordinates":[-1.038396,52.219091],"type":"Point"}
}
