{
  "type": "Feature",
  "properties": {
    "iso:country": "GB",
    "wof:name": "ST13 8XP",
    "wof:placetype": "postalcode"
  },
  "geometry": {"coordinates":[-2.02649,53.110167],"type":"Point"}
}
