{
  "type": "Feature",
  "properties": {
    "iso:country":"GB",
    "wof:name":"ST13 8XP",
    "wof:placetype":"postalcode"
},
  "geometry": {"coordinates":[-2.02649008163374,53.11016651703616],"type":"Point"}
}