{
  "type": "Feature",
  "properties": {
    "date:inception_lower": "1996-06-01",
    "date:inception_upper": "1996-06-01",
    "iso:country": "GB",
    "wof:name": "ST13 8XP",
    "wof:placetype": "postalcode"
  },
  "geometry": {"coordinates":[-2.026413,53.110202],"type":"Point"}
}
