{
  "type": "Feature",
  "properties": {
    "iso:country":"GB",
    "wof:name":"WR6 5RT",
    "wof:placetype":"postalcode"
},
  "geometry": {"coordinates":[-2.40633046785221,52.21149886527905],"type":"Point"}
}