{
  "type": "Feature",
  "properties": {
    "date:inception_lower":"1999-06-01",
    "date:inception_upper":"1999-06-30",
    "iso:country":"GB",
    "wof:name":"CH62 1DE",
    "wof:placetype":"postalcode"
},
  "geometry": {"coordinates":[-2.992624,53.362293],"type":"Point"}
}