{
  "type": "Feature",
  "properties": {
    "iso:country":"GB",
    "wof:name":"DA13 9NQ",
    "wof:placetype":"postalcode"
},
  "geometry": {"coordinates":[0.31664383617659,51.41305479304579],"type":"Point"}
}