{
  "type": "Feature",
  "properties": {
    "iso:country": "GB",
    "wof:name": "DA13 9NQ",
    "wof:placetype": "postalcode"
  },
  "geometry": {"coordinates":[0.316644,51.413055],"type":"Point"}
}
