{
  "type": "Feature",
  "properties": {
    "iso:country": "GB",
    "wof:name": "OX18 2EG",
    "wof:placetype": "postalcode"
  },
  "geometry": {"coordinates":[-1.491464,51.722993],"type":"Point"}
}
