{
  "type": "Feature",
  "properties": {
    "iso:country":"GB",
    "wof:name":"OX18 2EG",
    "wof:placetype":"postalcode"
},
  "geometry": {"coordinates":[-1.4914638627019,51.72299265140177],"type":"Point"}
}