{
  "type": "Feature",
  "properties": {
    "iso:country":"GB",
    "wof:name":"KT5 8BL",
    "wof:placetype":"postalcode"
},
  "geometry": {"coordinates":[-0.2928128291444,51.39995775732455],"type":"Point"}
}