{
  "type": "Feature",
  "properties": {
    "iso:country": "GB",
    "wof:name": "MK41 0DQ",
    "wof:placetype": "postalcode"
  },
  "geometry": {"coordinates":[-0.428536,52.155254],"type":"Point"}
}
