{
  "type": "Feature",
  "properties": {
    "iso:country":"GB",
    "wof:name":"KY4 9DR",
    "wof:placetype":"postalcode"
},
  "geometry": {"coordinates":[-3.36160704375808,56.10957913319859],"type":"Point"}
}