{
  "type": "Feature",
  "properties": {
    "iso:country": "GB",
    "wof:name": "KY4 9DR",
    "wof:placetype": "postalcode"
  },
  "geometry": {"coordinates":[-3.361607,56.109579],"type":"Point"}
}
