{
  "type": "Feature",
  "properties": {
    "iso:country":"GB",
    "wof:name":"CR4 3BQ",
    "wof:placetype":"postalcode"
},
  "geometry": {"coordinates":[-0.17681616686155,51.4027247652788],"type":"Point"}
}