{
  "type": "Feature",
  "properties": {
    "iso:country":"GB",
    "wof:name":"AB15 4YD",
    "wof:placetype":"postalcode"
},
  "geometry": {"coordinates":[-2.12817991090965,57.14315489044542],"type":"Point"}
}