{
  "type": "Feature",
  "properties": {
    "iso:country":"GB",
    "wof:name":"OL2 7YW",
    "wof:placetype":"postalcode"
},
  "geometry": {"coordinates":[-2.09180418741267,53.58581271076203],"type":"Point"}
}