{
  "type": "Feature",
  "properties": {
    "iso:country": "GB",
    "wof:name": "OL2 7YW",
    "wof:placetype": "postalcode"
  },
  "geometry": {"coordinates":[-2.091804,53.585813],"type":"Point"}
}
