{
  "type": "Feature",
  "properties": {
    "date:inception_lower": "1980-01-01",
    "date:inception_upper": "1980-01-01",
    "iso:country": "GB",
    "wof:name": "OL2 7YW",
    "wof:placetype": "postalcode"
  },
  "geometry": {"coordinates":[-2.091804,53.585813],"type":"Point"}
}
