{
  "type": "Feature",
  "properties": {
    "iso:country":"GB",
    "wof:name":"SL3 0BL",
    "wof:placetype":"postalcode"
},
  "geometry": {"coordinates":[-0.51775507483106,51.47501936209986],"type":"Point"}
}