{
  "type": "Feature",
  "properties": {
    "iso:country":"GB",
    "wof:name":"IV40 8DN",
    "wof:placetype":"postalcode"
},
  "geometry": {"coordinates":[-5.65558865182975,57.28521042839906],"type":"Point"}
}