{
  "type": "Feature",
  "properties": {
    "date:inception_lower": "1980-01-01",
    "date:inception_upper": "1980-01-01",
    "iso:country": "GB",
    "wof:name": "IV40 8DN",
    "wof:placetype": "postalcode"
  },
  "geometry": {"coordinates":[-5.65544,57.284813],"type":"Point"}
}
