{
  "type": "Feature",
  "properties": {
    "iso:country": "GB",
    "wof:name": "IP11 2EA",
    "wof:placetype": "postalcode"
  },
  "geometry": {"coordinates":[1.335721,51.951892],"type":"Point"}
}
