{
  "type": "Feature",
  "properties": {
    "iso:country":"GB",
    "wof:name":"IP11 2EA",
    "wof:placetype":"postalcode"
},
  "geometry": {"coordinates":[1.33572144632867,51.95189244730668],"type":"Point"}
}