{
  "type": "Feature",
  "properties": {
    "date:inception_lower": "1980-01-01",
    "date:inception_upper": "1980-01-01",
    "iso:country": "GB",
    "wof:name": "SA7 9PE",
    "wof:placetype": "postalcode"
  },
  "geometry": {"coordinates":[-3.876995,51.664358],"type":"Point"}
}
