{
  "type": "Feature",
  "properties": {
    "date:inception_lower":"1998-06-01",
    "date:inception_upper":"1998-06-30",
    "iso:country":"GB",
    "wof:name":"YO25 6SL",
    "wof:placetype":"postalcode"
},
  "geometry": {"coordinates":[-0.436667,53.997355],"type":"Point"}
}