{
  "type": "Feature",
  "properties": {
    "iso:country":"GB",
    "wof:name":"YO25 6SL",
    "wof:placetype":"postalcode"
},
  "geometry": {"coordinates":[-0.43666747493247,53.99735492459273],"type":"Point"}
}