{
  "type": "Feature",
  "properties": {
    "iso:country":"GB",
    "wof:name":"HR4 7PE",
    "wof:placetype":"postalcode"
},
  "geometry": {"coordinates":[-2.75188197520443,52.05163838683043],"type":"Point"}
}