{
  "type": "Feature",
  "properties": {
    "iso:country": "GB",
    "wof:name": "HR4 7PE",
    "wof:placetype": "postalcode"
  },
  "geometry": {"coordinates":[-2.751956,52.051629],"type":"Point"}
}
