{
  "type": "Feature",
  "properties": {
    "date:inception_lower": "1980-01-01",
    "date:inception_upper": "1980-01-01",
    "iso:country": "GB",
    "wof:name": "HR4 7PE",
    "wof:placetype": "postalcode"
  },
  "geometry": {"coordinates":[-2.751956,52.051629],"type":"Point"}
}
