{
  "type": "Feature",
  "properties": {
    "iso:country": "GB",
    "wof:name": "WA5 1BF",
    "wof:placetype": "postalcode"
  },
  "geometry": {"coordinates":[-2.615646,53.383269],"type":"Point"}
}
