{
  "type": "Feature",
  "properties": {
    "iso:country":"GB",
    "wof:name":"WA5 1BF",
    "wof:placetype":"postalcode"
},
  "geometry": {"coordinates":[-2.61564571586507,53.38326925769307],"type":"Point"}
}