{
  "type": "Feature",
  "properties": {
    "date:inception_lower": "1980-01-01",
    "date:inception_upper": "1980-01-01",
    "iso:country": "GB",
    "wof:name": "EX19 8EJ",
    "wof:placetype": "postalcode"
  },
  "geometry": {"coordinates":[-3.995323,50.831028],"type":"Point"}
}
