{
  "type": "Feature",
  "properties": {
    "iso:country": "GB",
    "wof:name": "LS22 4HW",
    "wof:placetype": "postalcode"
  },
  "geometry": {"coordinates":[-1.40794,53.918043],"type":"Point"}
}
