{
  "type": "Feature",
  "properties": {
    "iso:country":"GB",
    "wof:name":"LS22 4HW",
    "wof:placetype":"postalcode"
},
  "geometry": {"coordinates":[-1.40794014244261,53.91804343634197],"type":"Point"}
}