{
  "type": "Feature",
  "properties": {
    "iso:country":"GB",
    "wof:name":"CO16 9DZ",
    "wof:placetype":"postalcode"
},
  "geometry": {"coordinates":[1.12115831962068,51.84572436969099],"type":"Point"}
}