{
  "type": "Feature",
  "properties": {
    "iso:country":"GB",
    "wof:name":"HR1 3RE",
    "wof:placetype":"postalcode"
},
  "geometry": {"coordinates":[-2.60072212738588,52.11531512442023],"type":"Point"}
}