{
  "type": "Feature",
  "properties": {
    "date:inception_lower": "1980-01-01",
    "date:inception_upper": "1980-01-01",
    "iso:country": "GB",
    "wof:name": "GU34 5BT",
    "wof:placetype": "postalcode"
  },
  "geometry": {"coordinates":[-1.040845,51.111385],"type":"Point"}
}
