{
  "type": "Feature",
  "properties": {
    "iso:country":"GB",
    "wof:name":"SM6 0DW",
    "wof:placetype":"postalcode"
},
  "geometry": {"coordinates":[-0.15098108025923,51.36170004975072],"type":"Point"}
}