{
  "type": "Feature",
  "properties": {
    "date:inception_lower": "2018-11-01",
    "date:inception_upper": "2018-11-01",
    "iso:country": "GB",
    "wof:name": "SP2 9FR",
    "wof:placetype": "postalcode"
  },
  "geometry": {"coordinates":[-1.833358,51.092756],"type":"Point"}
}
