{
  "type": "Feature",
  "properties": {
    "date:inception_lower": "1980-01-01",
    "date:inception_upper": "1980-01-01",
    "iso:country": "GB",
    "wof:name": "TS12 2TT",
    "wof:placetype": "postalcode"
  },
  "geometry": {"coordinates":[-0.941291,54.564644],"type":"Point"}
}
