{
  "type": "Feature",
  "properties": {
    "iso:country":"GB",
    "wof:name":"TS12 2TT",
    "wof:placetype":"postalcode"
},
  "geometry": {"coordinates":[-0.94129114064674,54.56464421317187],"type":"Point"}
}