{
  "type": "Feature",
  "properties": {
    "iso:country":"GB",
    "wof:name":"NR31 8LN",
    "wof:placetype":"postalcode"
},
  "geometry": {"coordinates":[1.7154092517424,52.5808306779856],"type":"Point"}
}