{
  "type": "Feature",
  "properties": {
    "iso:country":"GB",
    "wof:name":"L30 9SP",
    "wof:placetype":"postalcode"
},
  "geometry": {"coordinates":[-2.9767821503801,53.47047021780372],"type":"Point"}
}