{
  "type": "Feature",
  "properties": {
    "date:inception_lower": "1980-01-01",
    "date:inception_upper": "1980-01-01",
    "iso:country": "GB",
    "wof:name": "L30 9SP",
    "wof:placetype": "postalcode"
  },
  "geometry": {"coordinates":[-2.976782,53.47047],"type":"Point"}
}
