{
  "type": "Feature",
  "properties": {
    "iso:country":"GB",
    "wof:name":"WF1 5DX",
    "wof:placetype":"postalcode"
},
  "geometry": {"coordinates":[-1.48374102967971,53.67247948624789],"type":"Point"}
}