{
  "type": "Feature",
  "properties": {
    "iso:country":"GB",
    "wof:name":"CV37 6QY",
    "wof:placetype":"postalcode"
},
  "geometry": {"coordinates":[-1.70675386453277,52.19365697613371],"type":"Point"}
}