{
  "type": "Feature",
  "properties": {
    "date:inception_lower": "2021-08-01",
    "date:inception_upper": "2021-08-01",
    "iso:country": "GB",
    "wof:name": "L7 9NP",
    "wof:placetype": "postalcode"
  },
  "geometry": {"coordinates":[-2.934382,53.408452],"type":"Point"}
}
