{
  "type": "Feature",
  "properties": {
    "iso:country": "GB",
    "wof:name": "YO11 2RY",
    "wof:placetype": "postalcode"
  },
  "geometry": {"coordinates":[-0.405061,54.270595],"type":"Point"}
}
