{
  "type": "Feature",
  "properties": {
    "iso:country":"GB",
    "wof:name":"YO11 2RY",
    "wof:placetype":"postalcode"
},
  "geometry": {"coordinates":[-0.40504510471503,54.27057753621605],"type":"Point"}
}