{
  "type": "Feature",
  "properties": {
    "date:inception_lower": "2012-06-01",
    "date:inception_upper": "2012-06-01",
    "iso:country": "GB",
    "wof:name": "SN16 1BE",
    "wof:placetype": "postalcode"
  },
  "geometry": {"coordinates":[-1.900248,51.53232],"type":"Point"}
}
