{
  "type": "Feature",
  "properties": {
    "iso:country": "GB",
    "wof:name": "LL30 2DW",
    "wof:placetype": "postalcode"
  },
  "geometry": {"coordinates":[-3.834636,53.3246],"type":"Point"}
}
