{
  "type": "Feature",
  "properties": {
    "iso:country":"GB",
    "wof:name":"LL30 2DW",
    "wof:placetype":"postalcode"
},
  "geometry": {"coordinates":[-3.83463629143462,53.32460040628359],"type":"Point"}
}