{
  "type": "Feature",
  "properties": {
    "iso:country": "GB",
    "wof:name": "GU34 5GR",
    "wof:placetype": "postalcode"
  },
  "geometry": {"coordinates":[-1.056207,51.115359],"type":"Point"}
}
