{
  "type": "Feature",
  "properties": {
    "date:inception_lower": "2016-04-01",
    "date:inception_upper": "2016-04-01",
    "iso:country": "GB",
    "wof:name": "GU34 5GR",
    "wof:placetype": "postalcode"
  },
  "geometry": {"coordinates":[-1.056207,51.115359],"type":"Point"}
}
