{
  "type": "Feature",
  "properties": {
    "date:inception_lower": "1980-01-01",
    "date:inception_upper": "1980-01-01",
    "iso:country": "GB",
    "wof:name": "SP10 2AN",
    "wof:placetype": "postalcode"
  },
  "geometry": {"coordinates":[-1.467994,51.202976],"type":"Point"}
}
