{
  "type": "Feature",
  "properties": {
    "iso:country":"GB",
    "wof:name":"SP10 2AN",
    "wof:placetype":"postalcode"
},
  "geometry": {"coordinates":[-1.4679942724404,51.20297608140686],"type":"Point"}
}