{
  "type": "Feature",
  "properties": {
    "iso:country":"GB",
    "wof:name":"M32 0QF",
    "wof:placetype":"postalcode"
},
  "geometry": {"coordinates":[-2.29769692665672,53.45935181524052],"type":"Point"}
}