{
  "type": "Feature",
  "properties": {
    "date:inception_lower":"1980-01-01",
    "date:inception_upper":"1980-01-31",
    "iso:country":"GB",
    "wof:name":"M32 0QF",
    "wof:placetype":"postalcode"
},
  "geometry": {"coordinates":[-2.297697,53.459352],"type":"Point"}
}