{
  "type": "Feature",
  "properties": {
    "iso:country": "GB",
    "wof:name": "GL50 4JR",
    "wof:placetype": "postalcode"
  },
  "geometry": {"coordinates":[-2.071802,51.905409],"type":"Point"}
}
