{
  "type": "Feature",
  "properties": {
    "iso:country":"GB",
    "wof:name":"GL50 4JR",
    "wof:placetype":"postalcode"
},
  "geometry": {"coordinates":[-2.07180227867389,51.90540879575562],"type":"Point"}
}