{
  "type": "Feature",
  "properties": {
    "iso:country":"GB",
    "wof:name":"G33 1BU",
    "wof:placetype":"postalcode"
},
  "geometry": {"coordinates":[-4.19023772380745,55.87505623843523],"type":"Point"}
}