{
  "type": "Feature",
  "properties": {
    "date:inception_lower": "1980-01-01",
    "date:inception_upper": "1980-01-01",
    "iso:country": "GB",
    "wof:name": "G33 1BU",
    "wof:placetype": "postalcode"
  },
  "geometry": {"coordinates":[-4.190238,55.875056],"type":"Point"}
}
