{
  "type": "Feature",
  "properties": {
    "iso:country":"GB",
    "wof:name":"MK4 4EA",
    "wof:placetype":"postalcode"
},
  "geometry": {"coordinates":[-0.80617534182495,52.00193264269509],"type":"Point"}
}