{
  "type": "Feature",
  "properties": {
    "date:inception_lower": "1993-01-01",
    "date:inception_upper": "1993-01-01",
    "iso:country": "GB",
    "wof:name": "SA4 6SD",
    "wof:placetype": "postalcode"
  },
  "geometry": {"coordinates":[-4.06569,51.665574],"type":"Point"}
}
