{
  "type": "Feature",
  "properties": {
    "iso:country":"GB",
    "wof:name":"SA4 6SD",
    "wof:placetype":"postalcode"
},
  "geometry": {"coordinates":[-4.06562784653098,51.66561459913715],"type":"Point"}
}