{
  "type": "Feature",
  "properties": {
    "iso:country": "GB",
    "wof:name": "CF72 9AA",
    "wof:placetype": "postalcode"
  },
  "geometry": {"coordinates":[-3.391237,51.524442],"type":"Point"}
}
