{
  "type": "Feature",
  "properties": {
    "iso:country":"GB",
    "wof:name":"CF72 9AA",
    "wof:placetype":"postalcode"
},
  "geometry": {"coordinates":[-3.39123747187647,51.5244423403857],"type":"Point"}
}