{
  "type": "Feature",
  "properties": {
    "date:inception_lower":"1980-01-01",
    "date:inception_upper":"1980-01-31",
    "iso:country":"GB",
    "wof:name":"OL12 0PL",
    "wof:placetype":"postalcode"
},
  "geometry": {"coordinates":[-2.157944,53.620616],"type":"Point"}
}