{
  "type": "Feature",
  "properties": {
    "iso:country":"GB",
    "wof:name":"DY12 2UZ",
    "wof:placetype":"postalcode"
},
  "geometry": {"coordinates":[-2.3510169129427,52.35335464254046],"type":"Point"}
}