{
  "type": "Feature",
  "properties": {
    "iso:country":"GB",
    "wof:name":"IV36 2UA",
    "wof:placetype":"postalcode"
},
  "geometry": {"coordinates":[-3.52097655594779,57.64848261117994],"type":"Point"}
}