{
  "type": "Feature",
  "properties": {
    "date:inception_lower": "2021-06-01",
    "date:inception_upper": "2021-06-01",
    "iso:country": "GB",
    "wof:name": "NR26 8QH",
    "wof:placetype": "postalcode"
  },
  "geometry": {"coordinates":[1.204243,52.932302],"type":"Point"}
}
