{
  "type": "Feature",
  "properties": {
    "date:inception_lower": "2021-05-01",
    "date:inception_upper": "2021-05-01",
    "iso:country": "GB",
    "wof:name": "NR32 3FD",
    "wof:placetype": "postalcode"
  },
  "geometry": {"coordinates":[1.705489,52.485392],"type":"Point"}
}
