{
  "type": "Feature",
  "properties": {
    "iso:country":"GB",
    "wof:name":"B36 8JX",
    "wof:placetype":"postalcode"
},
  "geometry": {"coordinates":[-1.81258236839295,52.50308022771734],"type":"Point"}
}