{
  "type": "Feature",
  "properties": {
    "iso:country": "GB",
    "wof:name": "BS35 1HN",
    "wof:placetype": "postalcode"
  },
  "geometry": {"coordinates":[-2.527784,51.613652],"type":"Point"}
}
