{
  "type": "Feature",
  "properties": {
    "iso:country": "GB",
    "wof:name": "DN18 5FR",
    "wof:placetype": "postalcode"
  },
  "geometry": {"coordinates":[-0.442799,53.681719],"type":"Point"}
}
