{
  "type": "Feature",
  "properties": {
    "iso:country":"GB",
    "wof:name":"CH7 2BL",
    "wof:placetype":"postalcode"
},
  "geometry": {"coordinates":[-3.08460607153999,53.16152687395246],"type":"Point"}
}