{
  "type": "Feature",
  "properties": {
    "iso:country":"GB",
    "wof:name":"W1J 7SD",
    "wof:placetype":"postalcode"
},
  "geometry": {"coordinates":[-0.15008326503504,51.5054057034282],"type":"Point"}
}