{
  "type": "Feature",
  "properties": {
    "iso:country":"GB",
    "wof:name":"CM9 6TF",
    "wof:placetype":"postalcode"
},
  "geometry": {"coordinates":[0.61672909140887,51.71221855053447],"type":"Point"}
}