{
  "type": "Feature",
  "properties": {
    "iso:country":"GB",
    "wof:name":"TA7 0RX",
    "wof:placetype":"postalcode"
},
  "geometry": {"coordinates":[-2.92049376909844,51.0644545329175],"type":"Point"}
}