{
  "type": "Feature",
  "properties": {
    "iso:country":"GB",
    "wof:name":"BS35 1JR",
    "wof:placetype":"postalcode"
},
  "geometry": {"coordinates":[-2.5174256161868,51.61592824671166],"type":"Point"}
}