{
  "type": "Feature",
  "properties": {
    "iso:country": "GB",
    "wof:name": "SA15 4NL",
    "wof:placetype": "postalcode"
  },
  "geometry": {"coordinates":[-4.172594,51.699124],"type":"Point"}
}
