{
  "type": "Feature",
  "properties": {
    "iso:country": "GB",
    "wof:name": "LA19 5XD",
    "wof:placetype": "postalcode"
  },
  "geometry": {"coordinates":[-3.396576,54.294783],"type":"Point"}
}
