{
  "type": "Feature",
  "properties": {
    "date:inception_lower": "1980-01-01",
    "date:inception_upper": "1980-01-01",
    "iso:country": "GB",
    "wof:name": "LA19 5XD",
    "wof:placetype": "postalcode"
  },
  "geometry": {"coordinates":[-3.396576,54.294783],"type":"Point"}
}
