{
  "type": "Feature",
  "properties": {
    "iso:country":"GB",
    "wof:name":"BA20 1LD",
    "wof:placetype":"postalcode"
},
  "geometry": {"coordinates":[-2.63024006002492,50.94148585272147],"type":"Point"}
}