{
  "type": "Feature",
  "properties": {
    "date:inception_lower": "2004-01-01",
    "date:inception_upper": "2004-01-01",
    "iso:country": "GB",
    "wof:name": "CV23 9QL",
    "wof:placetype": "postalcode"
  },
  "geometry": {"coordinates":[-1.364945,52.331602],"type":"Point"}
}
