{
  "type": "Feature",
  "properties": {
    "iso:country": "GB",
    "wof:name": "CV23 9QL",
    "wof:placetype": "postalcode"
  },
  "geometry": {"coordinates":[-1.364945,52.331602],"type":"Point"}
}
