{
  "type": "Feature",
  "properties": {
    "date:inception_lower": "2021-07-01",
    "date:inception_upper": "2021-07-01",
    "iso:country": "GB",
    "wof:name": "TR16 5FA",
    "wof:placetype": "postalcode"
  },
  "geometry": {"coordinates":[-5.206681,50.246631],"type":"Point"}
}
