{
  "type": "Feature",
  "properties": {
    "iso:country":"GB",
    "wof:name":"SM4 5AE",
    "wof:placetype":"postalcode"
},
  "geometry": {"coordinates":[-0.20087971570776,51.40062371276687],"type":"Point"}
}