{
  "type": "Feature",
  "properties": {
    "iso:country":"GB",
    "wof:name":"NG33 5DQ",
    "wof:placetype":"postalcode"
},
  "geometry": {"coordinates":[-0.65667904656524,52.85794256747958],"type":"Point"}
}