{
  "type": "Feature",
  "properties": {
    "date:inception_lower":"1980-01-01",
    "date:inception_upper":"1980-01-31",
    "iso:country":"GB",
    "wof:name":"NG33 5DQ",
    "wof:placetype":"postalcode"
},
  "geometry": {"coordinates":[-0.656679,52.857943],"type":"Point"}
}