{
  "type": "Feature",
  "properties": {
    "iso:country": "GB",
    "wof:name": "NG33 5DQ",
    "wof:placetype": "postalcode"
  },
  "geometry": {"coordinates":[-0.656679,52.857943],"type":"Point"}
}
