{
  "type": "Feature",
  "properties": {
    "iso:country":"GB",
    "wof:name":"LL30 1TB",
    "wof:placetype":"postalcode"
},
  "geometry": {"coordinates":[-3.8121510320562,53.3201795039467],"type":"Point"}
}