{
  "type": "Feature",
  "properties": {
    "iso:country": "GB",
    "wof:name": "LL30 1TB",
    "wof:placetype": "postalcode"
  },
  "geometry": {"coordinates":[-3.81214,53.320205],"type":"Point"}
}
