{
  "type": "Feature",
  "properties": {
    "iso:country": "GB",
    "wof:name": "BB8 8FJ",
    "wof:placetype": "postalcode"
  },
  "geometry": {"coordinates":[-2.183697,53.846933],"type":"Point"}
}
