{
  "type": "Feature",
  "properties": {
    "date:inception_lower":"1980-01-01",
    "date:inception_upper":"1980-01-31",
    "iso:country":"GB",
    "wof:name":"LL15 1YD",
    "wof:placetype":"postalcode"
},
  "geometry": {"coordinates":[-3.27531,53.129277],"type":"Point"}
}