{
  "type": "Feature",
  "properties": {
    "iso:country": "GB",
    "wof:name": "N22 7TP",
    "wof:placetype": "postalcode"
  },
  "geometry": {"coordinates":[-0.113176,51.596838],"type":"Point"}
}
