{
  "type": "Feature",
  "properties": {
    "date:inception_lower": "2017-08-01",
    "date:inception_upper": "2017-08-01",
    "iso:country": "GB",
    "wof:name": "PL22 0FD",
    "wof:placetype": "postalcode"
  },
  "geometry": {"coordinates":[-4.66449,50.408746],"type":"Point"}
}
