{
  "type": "Feature",
  "properties": {
    "iso:country":"GB",
    "wof:name":"SN2 2NQ",
    "wof:placetype":"postalcode"
},
  "geometry": {"coordinates":[-1.80746825607637,51.57929242803958],"type":"Point"}
}