{
  "type": "Feature",
  "properties": {
    "iso:country":"GB",
    "wof:name":"E16 3AW",
    "wof:placetype":"postalcode"
},
  "geometry": {"coordinates":[0.02362224211481,51.51085526297331],"type":"Point"}
}