{
  "type": "Feature",
  "properties": {
    "date:inception_lower": "1980-01-01",
    "date:inception_upper": "1980-01-01",
    "iso:country": "GB",
    "wof:name": "E16 3AW",
    "wof:placetype": "postalcode"
  },
  "geometry": {"coordinates":[0.023622,51.510855],"type":"Point"}
}
