{
  "type": "Feature",
  "properties": {
    "iso:country":"GB",
    "wof:name":"WV8 1EU",
    "wof:placetype":"postalcode"
},
  "geometry": {"coordinates":[-2.1798294035354,52.62856235347552],"type":"Point"}
}