{
  "type": "Feature",
  "properties": {
    "iso:country":"GB",
    "wof:name":"PA16 8DD",
    "wof:placetype":"postalcode"
},
  "geometry": {"coordinates":[-4.7692547106705,55.95288475692601],"type":"Point"}
}