{
  "type": "Feature",
  "properties": {
    "iso:country": "GB",
    "wof:name": "PA16 8DD",
    "wof:placetype": "postalcode"
  },
  "geometry": {"coordinates":[-4.769255,55.952885],"type":"Point"}
}
