{
  "type": "Feature",
  "properties": {
    "iso:country": "GB",
    "wof:name": "HG1 9WR",
    "wof:placetype": "postalcode"
  },
  "geometry": {"coordinates":[-1.545526,53.994928],"type":"Point"}
}
