{
  "type": "Feature",
  "properties": {
    "iso:country": "GB",
    "wof:name": "FY1 4JQ",
    "wof:placetype": "postalcode"
  },
  "geometry": {"coordinates":[-3.04531,53.81642],"type":"Point"}
}
