{
  "type": "Feature",
  "properties": {
    "iso:country":"GB",
    "wof:name":"B21 9PA",
    "wof:placetype":"postalcode"
},
  "geometry": {"coordinates":[-1.93412181501147,52.5116695381514],"type":"Point"}
}