{
  "type": "Feature",
  "properties": {
    "date:inception_lower": "1992-08-01",
    "date:inception_upper": "1992-08-01",
    "iso:country": "GB",
    "wof:name": "MK4 2HR",
    "wof:placetype": "postalcode"
  },
  "geometry": {"coordinates":[-0.777823,52.003674],"type":"Point"}
}
