{
  "type": "Feature",
  "properties": {
    "iso:country":"GB",
    "wof:name":"MK4 2HR",
    "wof:placetype":"postalcode"
},
  "geometry": {"coordinates":[-0.77782325788163,52.00367393239598],"type":"Point"}
}