{
  "type": "Feature",
  "properties": {
    "iso:country":"GB",
    "wof:name":"BN8 5ND",
    "wof:placetype":"postalcode"
},
  "geometry": {"coordinates":[0.07510237078333,50.89265428636816],"type":"Point"}
}