{
  "type": "Feature",
  "properties": {
    "iso:country":"GB",
    "wof:name":"BL4 0AZ",
    "wof:placetype":"postalcode"
},
  "geometry": {"coordinates":[-2.41469555165203,53.5479976150629],"type":"Point"}
}