{
  "type": "Feature",
  "properties": {
    "date:inception_lower": "1990-08-01",
    "date:inception_upper": "1990-08-01",
    "iso:country": "GB",
    "wof:name": "AB34 5AG",
    "wof:placetype": "postalcode"
  },
  "geometry": {"coordinates":[-2.656356,57.070898],"type":"Point"}
}
