{
  "type": "Feature",
  "properties": {
    "iso:country":"GB",
    "wof:name":"AB34 5AG",
    "wof:placetype":"postalcode"
},
  "geometry": {"coordinates":[-2.65676302738338,57.0708555532233],"type":"Point"}
}