{
  "type": "Feature",
  "properties": {
    "date:inception_lower":"1986-07-01",
    "date:inception_upper":"1986-07-31",
    "iso:country":"GB",
    "wof:name":"PA19 1JF",
    "wof:placetype":"postalcode"
},
  "geometry": {"coordinates":[-4.811237,55.947682],"type":"Point"}
}