{
  "type": "Feature",
  "properties": {
    "iso:country": "GB",
    "wof:name": "PA19 1JF",
    "wof:placetype": "postalcode"
  },
  "geometry": {"coordinates":[-4.811237,55.947682],"type":"Point"}
}
