{
  "type": "Feature",
  "properties": {
    "date:inception_lower":"1980-01-01",
    "date:inception_upper":"1980-01-31",
    "iso:country":"GB",
    "wof:name":"BL3 6TL",
    "wof:placetype":"postalcode"
},
  "geometry": {"coordinates":[-2.442391,53.566945],"type":"Point"}
}