{
  "type": "Feature",
  "properties": {
    "iso:country":"GB",
    "wof:name":"BL3 6TL",
    "wof:placetype":"postalcode"
},
  "geometry": {"coordinates":[-2.44239143488523,53.56694473190024],"type":"Point"}
}