{
  "type": "Feature",
  "properties": {
    "iso:country": "GB",
    "wof:name": "SL4 2QU",
    "wof:placetype": "postalcode"
  },
  "geometry": {"coordinates":[-0.587303,51.459665],"type":"Point"}
}
