{
  "type": "Feature",
  "properties": {
    "iso:country":"GB",
    "wof:name":"SL4 2QU",
    "wof:placetype":"postalcode"
},
  "geometry": {"coordinates":[-0.58730279286309,51.45966497289013],"type":"Point"}
}