{
  "type": "Feature",
  "properties": {
    "iso:country": "GB",
    "wof:name": "TW17 0QL",
    "wof:placetype": "postalcode"
  },
  "geometry": {"coordinates":[-0.463456,51.40553],"type":"Point"}
}
