{
  "type": "Feature",
  "properties": {
    "iso:country":"GB",
    "wof:name":"TW17 0QL",
    "wof:placetype":"postalcode"
},
  "geometry": {"coordinates":[-0.46345584749641,51.4055295715623],"type":"Point"}
}