{
  "type": "Feature",
  "properties": {
    "iso:country":"GB",
    "wof:name":"M28 3QA",
    "wof:placetype":"postalcode"
},
  "geometry": {"coordinates":[-2.39798770742828,53.5270215308828],"type":"Point"}
}