{
  "type": "Feature",
  "properties": {
    "iso:country": "GB",
    "wof:name": "M28 3QA",
    "wof:placetype": "postalcode"
  },
  "geometry": {"coordinates":[-2.397988,53.527022],"type":"Point"}
}
