{
  "type": "Feature",
  "properties": {
    "iso:country": "GB",
    "wof:name": "EH8 7AN",
    "wof:placetype": "postalcode"
  },
  "geometry": {"coordinates":[-3.154083,55.955052],"type":"Point"}
}
