{
  "type": "Feature",
  "properties": {
    "iso:country": "GB",
    "wof:name": "CM23 5HY",
    "wof:placetype": "postalcode"
  },
  "geometry": {"coordinates":[0.168831,51.870384],"type":"Point"}
}
