{
  "type": "Feature",
  "properties": {
    "iso:country":"GB",
    "wof:name":"CB3 0HS",
    "wof:placetype":"postalcode"
},
  "geometry": {"coordinates":[0.10315914529675,52.22133398802753],"type":"Point"}
}