{
  "type": "Feature",
  "properties": {
    "iso:country":"GB",
    "wof:name":"TN27 0GY",
    "wof:placetype":"postalcode"
},
  "geometry": {"coordinates":[0.79093880047968,51.21033163731853],"type":"Point"}
}