{
  "type": "Feature",
  "properties": {
    "date:inception_lower": "2004-06-01",
    "date:inception_upper": "2004-06-01",
    "iso:country": "GB",
    "wof:name": "TN27 0GY",
    "wof:placetype": "postalcode"
  },
  "geometry": {"coordinates":[0.790939,51.210332],"type":"Point"}
}
