{
  "type": "Feature",
  "properties": {
    "iso:country": "GB",
    "wof:name": "DL3 8NE",
    "wof:placetype": "postalcode"
  },
  "geometry": {"coordinates":[-1.575148,54.526263],"type":"Point"}
}
