{
  "type": "Feature",
  "properties": {
    "iso:country": "GB",
    "wof:name": "DN35 7AU",
    "wof:placetype": "postalcode"
  },
  "geometry": {"coordinates":[-0.053077,53.572121],"type":"Point"}
}
