{
  "type": "Feature",
  "properties": {
    "date:inception_lower": "2015-04-01",
    "date:inception_upper": "2015-04-01",
    "iso:country": "GB",
    "wof:name": "TF7 5GL",
    "wof:placetype": "postalcode"
  },
  "geometry": {"coordinates":[-2.471121,52.637737],"type":"Point"}
}
