{
  "type": "Feature",
  "properties": {
    "iso:country":"GB",
    "wof:name":"TF7 5GL",
    "wof:placetype":"postalcode"
},
  "geometry": {"coordinates":[-2.47103225143445,52.63753378702663],"type":"Point"}
}