{
  "type": "Feature",
  "properties": {
    "date:inception_lower":"1980-01-01",
    "date:inception_upper":"1980-01-31",
    "iso:country":"GB",
    "wof:name":"SG1 1DH",
    "wof:placetype":"postalcode"
},
  "geometry": {"coordinates":[-0.200088,51.901336],"type":"Point"}
}