{
  "type": "Feature",
  "properties": {
    "iso:country":"GB",
    "wof:name":"SG1 1DH",
    "wof:placetype":"postalcode"
},
  "geometry": {"coordinates":[-0.2000880380537,51.90133589025346],"type":"Point"}
}