{
  "type": "Feature",
  "properties": {
    "iso:country": "GB",
    "wof:name": "SG1 1DH",
    "wof:placetype": "postalcode"
  },
  "geometry": {"coordinates":[-0.200088,51.901336],"type":"Point"}
}
