{
  "type": "Feature",
  "properties": {
    "iso:country":"GB",
    "wof:name":"AB33 8HX",
    "wof:placetype":"postalcode"
},
  "geometry": {"coordinates":[-2.71380712084375,57.19847486705488],"type":"Point"}
}