{
  "type": "Feature",
  "properties": {
    "iso:country": "GB",
    "wof:name": "SW11 4HL",
    "wof:placetype": "postalcode"
  },
  "geometry": {"coordinates":[-0.16166,51.474556],"type":"Point"}
}
