{
  "type": "Feature",
  "properties": {
    "iso:country":"GB",
    "wof:name":"SW11 4HL",
    "wof:placetype":"postalcode"
},
  "geometry": {"coordinates":[-0.16168508269257,51.47455496025857],"type":"Point"}
}