{
  "type": "Feature",
  "properties": {
    "iso:country":"GB",
    "wof:name":"WS2 8SD",
    "wof:placetype":"postalcode"
},
  "geometry": {"coordinates":[-2.0023628376509,52.59066352047042],"type":"Point"}
}