{
  "type": "Feature",
  "properties": {
    "iso:country": "GB",
    "wof:name": "NN11 4NH",
    "wof:placetype": "postalcode"
  },
  "geometry": {"coordinates":[-1.175337,52.246658],"type":"Point"}
}
