{
  "type": "Feature",
  "properties": {
    "date:inception_lower": "1980-01-01",
    "date:inception_upper": "1980-01-01",
    "iso:country": "GB",
    "wof:name": "WA16 7BY",
    "wof:placetype": "postalcode"
  },
  "geometry": {"coordinates":[-2.288218,53.314171],"type":"Point"}
}
