{
  "type": "Feature",
  "properties": {
    "date:inception_lower": "1983-01-01",
    "date:inception_upper": "1983-01-01",
    "iso:country": "GB",
    "wof:name": "PR4 3TU",
    "wof:placetype": "postalcode"
  },
  "geometry": {"coordinates":[-2.837379,53.771835],"type":"Point"}
}
