{
  "type": "Feature",
  "properties": {
    "iso:country":"GB",
    "wof:name":"HP10 9BW",
    "wof:placetype":"postalcode"
},
  "geometry": {"coordinates":[-0.71034112848564,51.60269654835964],"type":"Point"}
}