{
  "type": "Feature",
  "properties": {
    "date:inception_lower": "1990-02-01",
    "date:inception_upper": "1990-02-01",
    "iso:country": "GB",
    "wof:name": "DN34 5TT",
    "wof:placetype": "postalcode"
  },
  "geometry": {"coordinates":[-0.114932,53.557713],"type":"Point"}
}
