{
  "type": "Feature",
  "properties": {
    "date:inception_lower":"2006-10-01",
    "date:inception_upper":"2006-10-31",
    "iso:country":"GB",
    "wof:name":"GL54 5RG",
    "wof:placetype":"postalcode"
},
  "geometry": {"coordinates":[-1.966019,51.955792],"type":"Point"}
}