{
  "type": "Feature",
  "properties": {
    "iso:country": "GB",
    "wof:name": "GL54 5RG",
    "wof:placetype": "postalcode"
  },
  "geometry": {"coordinates":[-1.966019,51.955792],"type":"Point"}
}
