{
  "type": "Feature",
  "properties": {
    "iso:country":"GB",
    "wof:name":"DL3 7LX",
    "wof:placetype":"postalcode"
},
  "geometry": {"coordinates":[-1.55735275901328,54.52448260964884],"type":"Point"}
}