{
  "type": "Feature",
  "properties": {
    "date:inception_lower":"1980-01-01",
    "date:inception_upper":"1980-01-31",
    "iso:country":"GB",
    "wof:name":"DL3 7LX",
    "wof:placetype":"postalcode"
},
  "geometry": {"coordinates":[-1.557353,54.524483],"type":"Point"}
}