{
  "type": "Feature",
  "properties": {
    "iso:country": "GB",
    "wof:name": "GU8 4EZ",
    "wof:placetype": "postalcode"
  },
  "geometry": {"coordinates":[-0.633546,51.134214],"type":"Point"}
}
