{
  "type": "Feature",
  "properties": {
    "iso:country": "GB",
    "wof:name": "BD2 4EW",
    "wof:placetype": "postalcode"
  },
  "geometry": {"coordinates":[-1.735971,53.819087],"type":"Point"}
}
