{
  "type": "Feature",
  "properties": {
    "iso:country":"GB",
    "wof:name":"BD2 4EW",
    "wof:placetype":"postalcode"
},
  "geometry": {"coordinates":[-1.7359710726028,53.81908694449776],"type":"Point"}
}