{
  "type": "Feature",
  "properties": {
    "date:inception_lower": "1994-12-01",
    "date:inception_upper": "1994-12-01",
    "iso:country": "GB",
    "wof:name": "SO50 7FN",
    "wof:placetype": "postalcode"
  },
  "geometry": {"coordinates":[-1.302708,50.967215],"type":"Point"}
}
