{
  "type": "Feature",
  "properties": {
    "iso:country":"GB",
    "wof:name":"SO50 7FN",
    "wof:placetype":"postalcode"
},
  "geometry": {"coordinates":[-1.30270412947943,50.96725777667999],"type":"Point"}
}