{
  "type": "Feature",
  "properties": {
    "iso:country": "GB",
    "wof:name": "SO50 7FN",
    "wof:placetype": "postalcode"
  },
  "geometry": {"coordinates":[-1.302708,50.967215],"type":"Point"}
}
