{
  "type": "Feature",
  "properties": {
    "iso:country": "GB",
    "wof:name": "WN1 2SE",
    "wof:placetype": "postalcode"
  },
  "geometry": {"coordinates":[-2.626529,53.564162],"type":"Point"}
}
