{
  "type": "Feature",
  "properties": {
    "iso:country":"GB",
    "wof:name":"WN1 2SE",
    "wof:placetype":"postalcode"
},
  "geometry": {"coordinates":[-2.62652920854067,53.56416215457625],"type":"Point"}
}