{
  "type": "Feature",
  "properties": {
    "iso:country": "GB",
    "wof:name": "ST10 4AG",
    "wof:placetype": "postalcode"
  },
  "geometry": {"coordinates":[-1.894892,52.977273],"type":"Point"}
}
