{
  "type": "Feature",
  "properties": {
    "iso:country":"GB",
    "wof:name":"WD24 7EE",
    "wof:placetype":"postalcode"
},
  "geometry": {"coordinates":[-0.38904504095041,51.67239919324513],"type":"Point"}
}