{
  "type": "Feature",
  "properties": {
    "date:inception_lower": "1980-01-01",
    "date:inception_upper": "1980-01-01",
    "iso:country": "GB",
    "wof:name": "E1 4AR",
    "wof:placetype": "postalcode"
  },
  "geometry": {"coordinates":[-0.048958,51.522229],"type":"Point"}
}
