{
  "type": "Feature",
  "properties": {
    "iso:country":"GB",
    "wof:name":"LL13 9BP",
    "wof:placetype":"postalcode"
},
  "geometry": {"coordinates":[-2.97120106728111,53.04810719769094],"type":"Point"}
}