{
  "type": "Feature",
  "properties": {
    "iso:country":"GB",
    "wof:name":"DE56 1TX",
    "wof:placetype":"postalcode"
},
  "geometry": {"coordinates":[-1.46439219922836,53.03251301211928],"type":"Point"}
}