{
  "type": "Feature",
  "properties": {
    "date:inception_lower":"1995-12-01",
    "date:inception_upper":"1995-12-31",
    "iso:country":"GB",
    "wof:name":"DE56 1TX",
    "wof:placetype":"postalcode"
},
  "geometry": {"coordinates":[-1.464392,53.032513],"type":"Point"}
}