{
  "type": "Feature",
  "properties": {
    "iso:country":"GB",
    "wof:name":"BB1 3JL",
    "wof:placetype":"postalcode"
},
  "geometry": {"coordinates":[-2.45559175754622,53.74961730328297],"type":"Point"}
}