{
  "type": "Feature",
  "properties": {
    "iso:country":"GB",
    "wof:name":"LS4 2JA",
    "wof:placetype":"postalcode"
},
  "geometry": {"coordinates":[-1.58226075327643,53.80765816597131],"type":"Point"}
}