{
  "type": "Feature",
  "properties": {
    "iso:country":"GB",
    "wof:name":"SA19 9DS",
    "wof:placetype":"postalcode"
},
  "geometry": {"coordinates":[-3.89761125682514,51.89913597742279],"type":"Point"}
}