{
  "type": "Feature",
  "properties": {
    "iso:country":"GB",
    "wof:name":"PL20 6RH",
    "wof:placetype":"postalcode"
},
  "geometry": {"coordinates":[-3.99416415578872,50.54775196085534],"type":"Point"}
}