{
  "type": "Feature",
  "properties": {
    "iso:country": "GB",
    "wof:name": "PL20 6RH",
    "wof:placetype": "postalcode"
  },
  "geometry": {"coordinates":[-3.994164,50.547752],"type":"Point"}
}
