{
  "type": "Feature",
  "properties": {
    "iso:country": "GB",
    "wof:name": "HP6 5AY",
    "wof:placetype": "postalcode"
  },
  "geometry": {"coordinates":[-0.604186,51.675036],"type":"Point"}
}
