{
  "type": "Feature",
  "properties": {
    "iso:country":"GB",
    "wof:name":"NG6 9JX",
    "wof:placetype":"postalcode"
},
  "geometry": {"coordinates":[-1.18781060121739,53.0037178612355],"type":"Point"}
}