{
  "type": "Feature",
  "properties": {
    "iso:country": "GB",
    "wof:name": "NG6 9JX",
    "wof:placetype": "postalcode"
  },
  "geometry": {"coordinates":[-1.187811,53.003718],"type":"Point"}
}
