{
  "type": "Feature",
  "properties": {
    "iso:country": "GB",
    "wof:name": "WA7 3DP",
    "wof:placetype": "postalcode"
  },
  "geometry": {"coordinates":[-2.649138,53.311847],"type":"Point"}
}
