{
  "type": "Feature",
  "properties": {
    "date:inception_lower":"1995-01-01",
    "date:inception_upper":"1995-01-31",
    "iso:country":"GB",
    "wof:name":"WA7 3DP",
    "wof:placetype":"postalcode"
},
  "geometry": {"coordinates":[-2.649138,53.311847],"type":"Point"}
}