{
  "type": "Feature",
  "properties": {
    "iso:country": "GB",
    "wof:name": "SY20 9JH",
    "wof:placetype": "postalcode"
  },
  "geometry": {"coordinates":[-3.653372,52.748942],"type":"Point"}
}
