{
  "type": "Feature",
  "properties": {
    "iso:country":"GB",
    "wof:name":"SY20 9JH",
    "wof:placetype":"postalcode"
},
  "geometry": {"coordinates":[-3.65337207441566,52.74894220393941],"type":"Point"}
}