{
  "type": "Feature",
  "properties": {
    "iso:country": "GB",
    "wof:name": "DE14 3JZ",
    "wof:placetype": "postalcode"
  },
  "geometry": {"coordinates":[-1.670206,52.79116],"type":"Point"}
}
