{
  "type": "Feature",
  "properties": {
    "iso:country":"GB",
    "wof:name":"KY12 8JB",
    "wof:placetype":"postalcode"
},
  "geometry": {"coordinates":[-3.62158381668844,56.05821110125437],"type":"Point"}
}