{
  "type": "Feature",
  "properties": {
    "date:inception_lower": "1997-12-01",
    "date:inception_upper": "1997-12-01",
    "iso:country": "GB",
    "wof:name": "IP24 1EZ",
    "wof:placetype": "postalcode"
  },
  "geometry": {"coordinates":[0.729519,52.420428],"type":"Point"}
}
