{
  "type": "Feature",
  "properties": {
    "iso:country": "GB",
    "wof:name": "TS12 3JA",
    "wof:placetype": "postalcode"
  },
  "geometry": {"coordinates":[-0.937964,54.518887],"type":"Point"}
}
