{
  "type": "Feature",
  "properties": {
    "iso:country":"GB",
    "wof:name":"S81 7DD",
    "wof:placetype":"postalcode"
},
  "geometry": {"coordinates":[-1.12971694025709,53.31906199847698],"type":"Point"}
}