{
  "type": "Feature",
  "properties": {
    "iso:country": "GB",
    "wof:name": "L10 4YW",
    "wof:placetype": "postalcode"
  },
  "geometry": {"coordinates":[-2.905321,53.468013],"type":"Point"}
}
