{
  "type": "Feature",
  "properties": {
    "iso:country":"GB",
    "wof:name":"ME13 0LU",
    "wof:placetype":"postalcode"
},
  "geometry": {"coordinates":[0.88246650671581,51.27399482446501],"type":"Point"}
}