{
  "type": "Feature",
  "properties": {
    "date:inception_lower": "1980-01-01",
    "date:inception_upper": "1980-01-01",
    "iso:country": "GB",
    "wof:name": "DY1 2NF",
    "wof:placetype": "postalcode"
  },
  "geometry": {"coordinates":[-2.116188,52.509874],"type":"Point"}
}
