{
  "type": "Feature",
  "properties": {
    "date:inception_lower": "1996-06-01",
    "date:inception_upper": "1996-06-01",
    "iso:country": "GB",
    "wof:name": "G75 9NP",
    "wof:placetype": "postalcode"
  },
  "geometry": {"coordinates":[-4.201816,55.738376],"type":"Point"}
}
