{
  "type": "Feature",
  "properties": {
    "iso:country":"GB",
    "wof:name":"TS26 8NH",
    "wof:placetype":"postalcode"
},
  "geometry": {"coordinates":[-1.23395161059008,54.68998971265233],"type":"Point"}
}