{
  "type": "Feature",
  "properties": {
    "iso:country": "GB",
    "wof:name": "TS26 8NH",
    "wof:placetype": "postalcode"
  },
  "geometry": {"coordinates":[-1.233952,54.68999],"type":"Point"}
}
