{
  "type": "Feature",
  "properties": {
    "iso:country":"GB",
    "wof:name":"LE67 8HT",
    "wof:placetype":"postalcode"
},
  "geometry": {"coordinates":[-1.39253772412246,52.7587894558102],"type":"Point"}
}