{
  "type": "Feature",
  "properties": {
    "date:inception_lower": "1999-06-01",
    "date:inception_upper": "1999-06-01",
    "iso:country": "GB",
    "wof:name": "CV34 5NG",
    "wof:placetype": "postalcode"
  },
  "geometry": {"coordinates":[-1.565114,52.289444],"type":"Point"}
}
