{
  "type": "Feature",
  "properties": {
    "iso:country": "GB",
    "wof:name": "CV34 5NG",
    "wof:placetype": "postalcode"
  },
  "geometry": {"coordinates":[-1.565114,52.289444],"type":"Point"}
}
