{
  "type": "Feature",
  "properties": {
    "iso:country":"GB",
    "wof:name":"LS9 7EX",
    "wof:placetype":"postalcode"
},
  "geometry": {"coordinates":[-1.51809391572894,53.80177317584802],"type":"Point"}
}