{
  "type": "Feature",
  "properties": {
    "iso:country":"GB",
    "wof:name":"LN6 0HE",
    "wof:placetype":"postalcode"
},
  "geometry": {"coordinates":[-0.57717254952817,53.21448095090459],"type":"Point"}
}