{
  "type": "Feature",
  "properties": {
    "date:inception_lower": "1980-01-01",
    "date:inception_upper": "1980-01-01",
    "iso:country": "GB",
    "wof:name": "LN6 0HE",
    "wof:placetype": "postalcode"
  },
  "geometry": {"coordinates":[-0.577173,53.214481],"type":"Point"}
}
