{
  "type": "Feature",
  "properties": {
    "iso:country": "GB",
    "wof:name": "BN45 7AT",
    "wof:placetype": "postalcode"
  },
  "geometry": {"coordinates":[-0.208242,50.893304],"type":"Point"}
}
