{
  "type": "Feature",
  "properties": {
    "iso:country":"GB",
    "wof:name":"BN45 7AT",
    "wof:placetype":"postalcode"
},
  "geometry": {"coordinates":[-0.20826980530573,50.89331021249876],"type":"Point"}
}