{
  "type": "Feature",
  "properties": {
    "iso:country": "GB",
    "wof:name": "SN8 3AD",
    "wof:placetype": "postalcode"
  },
  "geometry": {"coordinates":[-1.673034,51.352471],"type":"Point"}
}
