{
  "type": "Feature",
  "properties": {
    "date:inception_lower":"1980-01-01",
    "date:inception_upper":"1980-01-31",
    "iso:country":"GB",
    "wof:name":"DN8 5BZ",
    "wof:placetype":"postalcode"
},
  "geometry": {"coordinates":[-0.955218,53.615446],"type":"Point"}
}