{
  "type": "Feature",
  "properties": {
    "iso:country":"GB",
    "wof:name":"DN8 5BZ",
    "wof:placetype":"postalcode"
},
  "geometry": {"coordinates":[-0.95521867791818,53.61542778595116],"type":"Point"}
}