{
  "type": "Feature",
  "properties": {
    "iso:country":"GB",
    "wof:name":"SN12 7AD",
    "wof:placetype":"postalcode"
},
  "geometry": {"coordinates":[-2.12903789475709,51.3802888831513],"type":"Point"}
}