{
  "type": "Feature",
  "properties": {
    "iso:country": "GB",
    "wof:name": "CA8 9DW",
    "wof:placetype": "postalcode"
  },
  "geometry": {"coordinates":[-2.720462,54.874735],"type":"Point"}
}
