{
  "type": "Feature",
  "properties": {
    "iso:country":"GB",
    "wof:name":"CA8 9DW",
    "wof:placetype":"postalcode"
},
  "geometry": {"coordinates":[-2.72077025349267,54.87220033899087],"type":"Point"}
}