{
  "type": "Feature",
  "properties": {
    "date:inception_lower": "1980-01-01",
    "date:inception_upper": "1980-01-01",
    "iso:country": "GB",
    "wof:name": "CV34 5RU",
    "wof:placetype": "postalcode"
  },
  "geometry": {"coordinates":[-1.59771,52.287294],"type":"Point"}
}
