{
  "type": "Feature",
  "properties": {
    "iso:country":"GB",
    "wof:name":"CF72 8DB",
    "wof:placetype":"postalcode"
},
  "geometry": {"coordinates":[-3.37521069256847,51.54413500158359],"type":"Point"}
}