{
  "type": "Feature",
  "properties": {
    "iso:country":"GB",
    "wof:name":"CR0 0TE",
    "wof:placetype":"postalcode"
},
  "geometry": {"coordinates":[-0.01656455946523,51.34924934603739],"type":"Point"}
}