{
  "type": "Feature",
  "properties": {
    "iso:country":"GB",
    "wof:name":"B78 2JB",
    "wof:placetype":"postalcode"
},
  "geometry": {"coordinates":[-1.68074674267245,52.57025856487645],"type":"Point"}
}