{
  "type": "Feature",
  "properties": {
    "iso:country":"GB",
    "wof:name":"NW9 9ER",
    "wof:placetype":"postalcode"
},
  "geometry": {"coordinates":[-0.28088453762975,51.58443294411909],"type":"Point"}
}