{
  "type": "Feature",
  "properties": {
    "iso:country":"GB",
    "wof:name":"ME13 9JJ",
    "wof:placetype":"postalcode"
},
  "geometry": {"coordinates":[0.96311607781416,51.31303946544818],"type":"Point"}
}