{
  "type": "Feature",
  "properties": {
    "date:inception_lower": "1980-01-01",
    "date:inception_upper": "1980-01-01",
    "iso:country": "GB",
    "wof:name": "ME13 9JJ",
    "wof:placetype": "postalcode"
  },
  "geometry": {"coordinates":[0.964314,51.313346],"type":"Point"}
}
