{
  "type": "Feature",
  "properties": {
    "iso:country":"GB",
    "wof:name":"TS6 9TZ",
    "wof:placetype":"postalcode"
},
  "geometry": {"coordinates":[-1.15365773164556,54.56669291696839],"type":"Point"}
}