{
  "type": "Feature",
  "properties": {
    "date:inception_lower":"2009-03-01",
    "date:inception_upper":"2009-03-31",
    "iso:country":"GB",
    "wof:name":"TS6 9TZ",
    "wof:placetype":"postalcode"
},
  "geometry": {"coordinates":[-1.153658,54.566693],"type":"Point"}
}