{
  "type": "Feature",
  "properties": {
    "iso:country":"GB",
    "wof:name":"WA7 2SR",
    "wof:placetype":"postalcode"
},
  "geometry": {"coordinates":[-2.70007242506145,53.33714070268167],"type":"Point"}
}