{
  "type": "Feature",
  "properties": {
    "iso:country": "GB",
    "wof:name": "WA7 2SR",
    "wof:placetype": "postalcode"
  },
  "geometry": {"coordinates":[-2.700072,53.337141],"type":"Point"}
}
