{
  "type": "Feature",
  "properties": {
    "iso:country":"GB",
    "wof:name":"WS3 2RW",
    "wof:placetype":"postalcode"
},
  "geometry": {"coordinates":[-2.02524706624323,52.62369818349472],"type":"Point"}
}