{
  "type": "Feature",
  "properties": {
    "iso:country":"GB",
    "wof:name":"NE25 8PT",
    "wof:placetype":"postalcode"
},
  "geometry": {"coordinates":[-1.44058169509429,55.03719829075961],"type":"Point"}
}