{
  "type": "Feature",
  "properties": {
    "date:inception_lower": "1994-05-01",
    "date:inception_upper": "1994-05-01",
    "iso:country": "GB",
    "wof:name": "G51 4JP",
    "wof:placetype": "postalcode"
  },
  "geometry": {"coordinates":[-4.331957,55.864641],"type":"Point"}
}
