{
  "type": "Feature",
  "properties": {
    "iso:country": "GB",
    "wof:name": "WF14 9ET",
    "wof:placetype": "postalcode"
  },
  "geometry": {"coordinates":[-1.701111,53.684436],"type":"Point"}
}
