{
  "type": "Feature",
  "properties": {
    "date:inception_lower":"1990-02-01",
    "date:inception_upper":"1990-02-28",
    "iso:country":"GB",
    "wof:name":"NG13 8PY",
    "wof:placetype":"postalcode"
},
  "geometry": {"coordinates":[-0.971354,52.980603],"type":"Point"}
}