{
  "type": "Feature",
  "properties": {
    "iso:country": "GB",
    "wof:name": "NG13 8PY",
    "wof:placetype": "postalcode"
  },
  "geometry": {"coordinates":[-0.971354,52.980603],"type":"Point"}
}
