{
  "type": "Feature",
  "properties": {
    "iso:country":"GB",
    "wof:name":"NG13 8PY",
    "wof:placetype":"postalcode"
},
  "geometry": {"coordinates":[-0.97135408532268,52.98060277375564],"type":"Point"}
}