{
  "type": "Feature",
  "properties": {
    "iso:country":"GB",
    "wof:name":"BS36 1JL",
    "wof:placetype":"postalcode"
},
  "geometry": {"coordinates":[-2.50703393062748,51.52453970233167],"type":"Point"}
}