{
  "type": "Feature",
  "properties": {
    "iso:country":"GB",
    "wof:name":"EX36 4QR",
    "wof:placetype":"postalcode"
},
  "geometry": {"coordinates":[-3.71714071347798,50.98241254758936],"type":"Point"}
}