{
  "type": "Feature",
  "properties": {
    "iso:country": "GB",
    "wof:name": "EX36 4QR",
    "wof:placetype": "postalcode"
  },
  "geometry": {"coordinates":[-3.717141,50.982413],"type":"Point"}
}
