{
  "type": "Feature",
  "properties": {
    "iso:country": "GB",
    "wof:name": "WA3 3NR",
    "wof:placetype": "postalcode"
  },
  "geometry": {"coordinates":[-2.602878,53.476547],"type":"Point"}
}
