{
  "type": "Feature",
  "properties": {
    "iso:country":"GB",
    "wof:name":"WA3 3NR",
    "wof:placetype":"postalcode"
},
  "geometry": {"coordinates":[-2.60287779594585,53.47654680072234],"type":"Point"}
}