{
  "type": "Feature",
  "properties": {
    "iso:country":"GB",
    "wof:name":"BH11 9RQ",
    "wof:placetype":"postalcode"
},
  "geometry": {"coordinates":[-1.92980845949335,50.76147408255343],"type":"Point"}
}