{
  "type": "Feature",
  "properties": {
    "iso:country":"GB",
    "wof:name":"WN2 1US",
    "wof:placetype":"postalcode"
},
  "geometry": {"coordinates":[-2.59216218479137,53.57470995528334],"type":"Point"}
}