{
  "type": "Feature",
  "properties": {
    "iso:country":"GB",
    "wof:name":"LL13 0FG",
    "wof:placetype":"postalcode"
},
  "geometry": {"coordinates":[-2.93556385251345,52.9709754692843],"type":"Point"}
}