{
  "type": "Feature",
  "properties": {
    "date:inception_lower":"2014-11-01",
    "date:inception_upper":"2014-11-30",
    "iso:country":"GB",
    "wof:name":"LL13 0FG",
    "wof:placetype":"postalcode"
},
  "geometry": {"coordinates":[-2.935505,52.971037],"type":"Point"}
}