{
  "type": "Feature",
  "properties": {
    "iso:country": "GB",
    "wof:name": "LL13 0FG",
    "wof:placetype": "postalcode"
  },
  "geometry": {"coordinates":[-2.935505,52.971037],"type":"Point"}
}
