{
  "type": "Feature",
  "properties": {
    "date:inception_lower": "1998-06-01",
    "date:inception_upper": "1998-06-01",
    "iso:country": "GB",
    "wof:name": "YO26 6NN",
    "wof:placetype": "postalcode"
  },
  "geometry": {"coordinates":[-1.145939,53.984002],"type":"Point"}
}
