{
  "type": "Feature",
  "properties": {
    "iso:country":"GB",
    "wof:name":"YO26 6NN",
    "wof:placetype":"postalcode"
},
  "geometry": {"coordinates":[-1.14583873580904,53.98401083760412],"type":"Point"}
}