{
  "type": "Feature",
  "properties": {
    "iso:country":"GB",
    "wof:name":"NR17 2EQ",
    "wof:placetype":"postalcode"
},
  "geometry": {"coordinates":[1.01544588411368,52.51902116524563],"type":"Point"}
}