{
  "type": "Feature",
  "properties": {
    "iso:country":"GB",
    "wof:name":"L25 9QE",
    "wof:placetype":"postalcode"
},
  "geometry": {"coordinates":[-2.84667597466735,53.36506261385368],"type":"Point"}
}