{
  "type": "Feature",
  "properties": {
    "iso:country": "GB",
    "wof:name": "CB23 6GG",
    "wof:placetype": "postalcode"
  },
  "geometry": {"coordinates":[-0.063889,52.219697],"type":"Point"}
}
