{
  "type": "Feature",
  "properties": {
    "iso:country":"GB",
    "wof:name":"CB21 4SU",
    "wof:placetype":"postalcode"
},
  "geometry": {"coordinates":[0.3827341794764,52.06231211155418],"type":"Point"}
}