{
  "type": "Feature",
  "properties": {
    "iso:country": "GB",
    "wof:name": "DY11 6FE",
    "wof:placetype": "postalcode"
  },
  "geometry": {"coordinates":[-2.258686,52.387518],"type":"Point"}
}
