{
  "type": "Feature",
  "properties": {
    "iso:country":"GB",
    "wof:name":"SA15 2JW",
    "wof:placetype":"postalcode"
},
  "geometry": {"coordinates":[-4.17552180930454,51.67568866764143],"type":"Point"}
}