{
  "type": "Feature",
  "properties": {
    "iso:country": "GB",
    "wof:name": "SA15 2JW",
    "wof:placetype": "postalcode"
  },
  "geometry": {"coordinates":[-4.175522,51.675689],"type":"Point"}
}
