{
  "type": "Feature",
  "properties": {
    "date:inception_lower": "2006-02-01",
    "date:inception_upper": "2006-02-01",
    "iso:country": "GB",
    "wof:name": "SA15 2JW",
    "wof:placetype": "postalcode"
  },
  "geometry": {"coordinates":[-4.175522,51.675689],"type":"Point"}
}
