{
  "type": "Feature",
  "properties": {
    "iso:country":"GB",
    "wof:name":"PO4 0SE",
    "wof:placetype":"postalcode"
},
  "geometry": {"coordinates":[-1.07862588025036,50.78028579578216],"type":"Point"}
}