{
  "type": "Feature",
  "properties": {
    "iso:country":"GB",
    "wof:name":"BS30 7HB",
    "wof:placetype":"postalcode"
},
  "geometry": {"coordinates":[-2.49447106428148,51.44925307989243],"type":"Point"}
}