{
  "type": "Feature",
  "properties": {
    "iso:country": "GB",
    "wof:name": "BS30 7HB",
    "wof:placetype": "postalcode"
  },
  "geometry": {"coordinates":[-2.494471,51.449253],"type":"Point"}
}
