{
  "type": "Feature",
  "properties": {
    "iso:country": "GB",
    "wof:name": "L8 5RH",
    "wof:placetype": "postalcode"
  },
  "geometry": {"coordinates":[-2.974799,53.392463],"type":"Point"}
}
