{
  "type": "Feature",
  "properties": {
    "iso:country": "GB",
    "wof:name": "NE5 3HT",
    "wof:placetype": "postalcode"
  },
  "geometry": {"coordinates":[-1.659415,54.995143],"type":"Point"}
}
