{
  "type": "Feature",
  "properties": {
    "date:inception_lower": "1980-01-01",
    "date:inception_upper": "1980-01-01",
    "iso:country": "GB",
    "wof:name": "NE5 3HT",
    "wof:placetype": "postalcode"
  },
  "geometry": {"coordinates":[-1.659415,54.995143],"type":"Point"}
}
