{
  "type": "Feature",
  "properties": {
    "iso:country":"GB",
    "wof:name":"NE5 3HT",
    "wof:placetype":"postalcode"
},
  "geometry": {"coordinates":[-1.65941529650212,54.99514267501011],"type":"Point"}
}