{
  "type": "Feature",
  "properties": {
    "iso:country":"GB",
    "wof:name":"WN3 6HY",
    "wof:placetype":"postalcode"
},
  "geometry": {"coordinates":[-2.66703493220587,53.52560703145938],"type":"Point"}
}