{
  "type": "Feature",
  "properties": {
    "iso:country":"GB",
    "wof:name":"CV4 9LX",
    "wof:placetype":"postalcode"
},
  "geometry": {"coordinates":[-1.58279984358152,52.40749581433514],"type":"Point"}
}