{
  "type": "Feature",
  "properties": {
    "iso:country": "GB",
    "wof:name": "CV4 9LX",
    "wof:placetype": "postalcode"
  },
  "geometry": {"coordinates":[-1.5828,52.407496],"type":"Point"}
}
