{
  "type": "Feature",
  "properties": {
    "date:inception_lower": "1980-01-01",
    "date:inception_upper": "1980-01-01",
    "iso:country": "GB",
    "wof:name": "RM8 2BA",
    "wof:placetype": "postalcode"
  },
  "geometry": {"coordinates":[0.12161,51.555877],"type":"Point"}
}
