{
  "type": "Feature",
  "properties": {
    "iso:country":"GB",
    "wof:name":"NN29 7LD",
    "wof:placetype":"postalcode"
},
  "geometry": {"coordinates":[-0.63600012020605,52.23055509659204],"type":"Point"}
}