{
  "type": "Feature",
  "properties": {
    "iso:country": "GB",
    "wof:name": "GU21 6AR",
    "wof:placetype": "postalcode"
  },
  "geometry": {"coordinates":[-0.55887,51.32099],"type":"Point"}
}
