{
  "type": "Feature",
  "properties": {
    "iso:country": "GB",
    "wof:name": "BS20 7QY",
    "wof:placetype": "postalcode"
  },
  "geometry": {"coordinates":[-2.757721,51.487678],"type":"Point"}
}
