{
  "type": "Feature",
  "properties": {
    "iso:country": "GB",
    "wof:name": "NP4 7BA",
    "wof:placetype": "postalcode"
  },
  "geometry": {"coordinates":[-3.057786,51.722646],"type":"Point"}
}
