{
  "type": "Feature",
  "properties": {
    "date:inception_lower": "1986-07-01",
    "date:inception_upper": "1986-07-01",
    "iso:country": "GB",
    "wof:name": "NP4 7BA",
    "wof:placetype": "postalcode"
  },
  "geometry": {"coordinates":[-3.057793,51.72265],"type":"Point"}
}
