{
  "type": "Feature",
  "properties": {
    "iso:country":"GB",
    "wof:name":"DT9 3RF",
    "wof:placetype":"postalcode"
},
  "geometry": {"coordinates":[-2.51921895715445,50.94244611610052],"type":"Point"}
}