{
  "type": "Feature",
  "properties": {
    "date:inception_lower":"1980-01-01",
    "date:inception_upper":"1980-01-31",
    "iso:country":"GB",
    "wof:name":"G77 5JX",
    "wof:placetype":"postalcode"
},
  "geometry": {"coordinates":[-4.316729,55.769364],"type":"Point"}
}