{
  "type": "Feature",
  "properties": {
    "iso:country":"GB",
    "wof:name":"G77 5JX",
    "wof:placetype":"postalcode"
},
  "geometry": {"coordinates":[-4.31672860096137,55.76936350485506],"type":"Point"}
}