{
  "type": "Feature",
  "properties": {
    "iso:country": "GB",
    "wof:name": "G77 5JX",
    "wof:placetype": "postalcode"
  },
  "geometry": {"coordinates":[-4.316729,55.769364],"type":"Point"}
}
