{
  "type": "Feature",
  "properties": {
    "date:inception_lower": "1980-01-01",
    "date:inception_upper": "1980-01-01",
    "iso:country": "GB",
    "wof:name": "TN24 0UA",
    "wof:placetype": "postalcode"
  },
  "geometry": {"coordinates":[0.906055,51.136445],"type":"Point"}
}
