{
  "type": "Feature",
  "properties": {
    "iso:country":"GB",
    "wof:name":"TN24 0UA",
    "wof:placetype":"postalcode"
},
  "geometry": {"coordinates":[0.90605464574951,51.13644457985174],"type":"Point"}
}