{
  "type": "Feature",
  "properties": {
    "date:inception_lower": "2021-12-01",
    "date:inception_upper": "2021-12-01",
    "iso:country": "GB",
    "wof:name": "SY2 5WF",
    "wof:placetype": "postalcode"
  },
  "geometry": {"coordinates":[-2.718121,52.701745],"type":"Point"}
}
