{
  "type": "Feature",
  "properties": {
    "date:inception_lower":"1980-01-01",
    "date:inception_upper":"1980-01-31",
    "iso:country":"GB",
    "wof:name":"PA42 7DA",
    "wof:placetype":"postalcode"
},
  "geometry": {"coordinates":[-6.196948,55.63527],"type":"Point"}
}