{
  "type": "Feature",
  "properties": {
    "iso:country": "GB",
    "wof:name": "SG16 6AG",
    "wof:placetype": "postalcode"
  },
  "geometry": {"coordinates":[-0.284793,52.042647],"type":"Point"}
}
