{
  "type": "Feature",
  "properties": {
    "date:inception_lower":"1980-01-01",
    "date:inception_upper":"1980-01-31",
    "iso:country":"GB",
    "wof:name":"SG16 6AG",
    "wof:placetype":"postalcode"
},
  "geometry": {"coordinates":[-0.284793,52.042647],"type":"Point"}
}