{
  "type": "Feature",
  "properties": {
    "iso:country":"GB",
    "wof:name":"HU12 9PR",
    "wof:placetype":"postalcode"
},
  "geometry": {"coordinates":[-0.16674081749142,53.71937715993879],"type":"Point"}
}