{
  "type": "Feature",
  "properties": {
    "iso:country": "GB",
    "wof:name": "HU12 9PR",
    "wof:placetype": "postalcode"
  },
  "geometry": {"coordinates":[-0.166741,53.719377],"type":"Point"}
}
