{
  "type": "Feature",
  "properties": {
    "date:inception_lower": "1980-01-01",
    "date:inception_upper": "1980-01-01",
    "iso:country": "GB",
    "wof:name": "SA33 6SU",
    "wof:placetype": "postalcode"
  },
  "geometry": {"coordinates":[-4.414391,51.971704],"type":"Point"}
}
