{
  "type": "Feature",
  "properties": {
    "iso:country": "GB",
    "wof:name": "SA33 6SU",
    "wof:placetype": "postalcode"
  },
  "geometry": {"coordinates":[-4.414391,51.971704],"type":"Point"}
}
