{
  "type": "Feature",
  "properties": {
    "date:inception_lower": "1980-01-01",
    "date:inception_upper": "1980-01-01",
    "iso:country": "GB",
    "wof:name": "RH14 0BX",
    "wof:placetype": "postalcode"
  },
  "geometry": {"coordinates":[-0.509593,51.023352],"type":"Point"}
}
