{
  "type": "Feature",
  "properties": {
    "iso:country": "GB",
    "wof:name": "RH14 0BX",
    "wof:placetype": "postalcode"
  },
  "geometry": {"coordinates":[-0.509593,51.023352],"type":"Point"}
}
