{
  "type": "Feature",
  "properties": {
    "iso:country":"GB",
    "wof:name":"DD8 3JF",
    "wof:placetype":"postalcode"
},
  "geometry": {"coordinates":[-2.89549835069743,56.64881474196252],"type":"Point"}
}