{
  "type": "Feature",
  "properties": {
    "iso:country":"GB",
    "wof:name":"CR2 8BH",
    "wof:placetype":"postalcode"
},
  "geometry": {"coordinates":[-0.07435677338825,51.34262379975107],"type":"Point"}
}