{
  "type": "Feature",
  "properties": {
    "iso:country":"GB",
    "wof:name":"NW7 4RS",
    "wof:placetype":"postalcode"
},
  "geometry": {"coordinates":[-0.24302176976135,51.61627138251386],"type":"Point"}
}