{
  "type": "Feature",
  "properties": {
    "date:inception_lower": "1980-01-01",
    "date:inception_upper": "1980-01-01",
    "iso:country": "GB",
    "wof:name": "FY4 5LA",
    "wof:placetype": "postalcode"
  },
  "geometry": {"coordinates":[-2.989126,53.784382],"type":"Point"}
}
