{
  "type": "Feature",
  "properties": {
    "iso:country": "GB",
    "wof:name": "FY4 5LA",
    "wof:placetype": "postalcode"
  },
  "geometry": {"coordinates":[-2.987766,53.784487],"type":"Point"}
}
