{
  "type": "Feature",
  "properties": {
    "iso:country":"GB",
    "wof:name":"FY4 5LA",
    "wof:placetype":"postalcode"
},
  "geometry": {"coordinates":[-2.98867942412836,53.78458714310597],"type":"Point"}
}