{
  "type": "Feature",
  "properties": {
    "iso:country":"GB",
    "wof:name":"NG33 5JB",
    "wof:placetype":"postalcode"
},
  "geometry": {"coordinates":[-0.62522373629059,52.80377671785136],"type":"Point"}
}