{
  "type": "Feature",
  "properties": {
    "iso:country": "GB",
    "wof:name": "NG33 5JB",
    "wof:placetype": "postalcode"
  },
  "geometry": {"coordinates":[-0.625224,52.803777],"type":"Point"}
}
