{
  "type": "Feature",
  "properties": {
    "iso:country":"GB",
    "wof:name":"ME8 7NN",
    "wof:placetype":"postalcode"
},
  "geometry": {"coordinates":[0.61061827208602,51.37159956799229],"type":"Point"}
}