{
  "type": "Feature",
  "properties": {
    "iso:country":"GB",
    "wof:name":"BB2 7PQ",
    "wof:placetype":"postalcode"
},
  "geometry": {"coordinates":[-2.54778388473836,53.77579117228659],"type":"Point"}
}