{
  "type": "Feature",
  "properties": {
    "iso:country":"GB",
    "wof:name":"ST2 9LH",
    "wof:placetype":"postalcode"
},
  "geometry": {"coordinates":[-2.1408682463617,53.01717479040239],"type":"Point"}
}