{
  "type": "Feature",
  "properties": {
    "date:inception_lower": "1994-05-01",
    "date:inception_upper": "1994-05-01",
    "iso:country": "GB",
    "wof:name": "BD23 4HG",
    "wof:placetype": "postalcode"
  },
  "geometry": {"coordinates":[-2.224329,54.006931],"type":"Point"}
}
