{
  "type": "Feature",
  "properties": {
    "iso:country":"GB",
    "wof:name":"BD23 4HG",
    "wof:placetype":"postalcode"
},
  "geometry": {"coordinates":[-2.22432909653751,54.00693086785136],"type":"Point"}
}