{
  "type": "Feature",
  "properties": {
    "iso:country":"GB",
    "wof:name":"EX9 6BY",
    "wof:placetype":"postalcode"
},
  "geometry": {"coordinates":[-3.33245943114884,50.62830802524068],"type":"Point"}
}