{
  "type": "Feature",
  "properties": {
    "date:inception_lower": "1980-01-01",
    "date:inception_upper": "1980-01-01",
    "iso:country": "GB",
    "wof:name": "EX9 6BY",
    "wof:placetype": "postalcode"
  },
  "geometry": {"coordinates":[-3.332054,50.628013],"type":"Point"}
}
