{
  "type": "Feature",
  "properties": {
    "iso:country":"GB",
    "wof:name":"OL5 0AW",
    "wof:placetype":"postalcode"
},
  "geometry": {"coordinates":[-2.04401067021844,53.51420294614933],"type":"Point"}
}