{
  "type": "Feature",
  "properties": {
    "iso:country": "GB",
    "wof:name": "OL5 0AW",
    "wof:placetype": "postalcode"
  },
  "geometry": {"coordinates":[-2.044011,53.514203],"type":"Point"}
}
