{
  "type": "Feature",
  "properties": {
    "iso:country":"GB",
    "wof:name":"NP11 6NL",
    "wof:placetype":"postalcode"
},
  "geometry": {"coordinates":[-3.082107554643,51.6018657129484],"type":"Point"}
}