{
  "type": "Feature",
  "properties": {
    "iso:country":"GB",
    "wof:name":"PL17 7AT",
    "wof:placetype":"postalcode"
},
  "geometry": {"coordinates":[-4.31435030284637,50.50411203600668],"type":"Point"}
}