{
  "type": "Feature",
  "properties": {
    "iso:country": "GB",
    "wof:name": "KW15 1BU",
    "wof:placetype": "postalcode"
  },
  "geometry": {"coordinates":[-2.962355,58.978091],"type":"Point"}
}
