{
  "type": "Feature",
  "properties": {
    "iso:country":"GB",
    "wof:name":"KW15 1BU",
    "wof:placetype":"postalcode"
},
  "geometry": {"coordinates":[-2.9621264765677,58.97819911004641],"type":"Point"}
}