{
  "type": "Feature",
  "properties": {
    "date:inception_lower": "2009-07-01",
    "date:inception_upper": "2009-07-01",
    "iso:country": "GB",
    "wof:name": "BL8 1DE",
    "wof:placetype": "postalcode"
  },
  "geometry": {"coordinates":[-2.308708,53.600514],"type":"Point"}
}
