{
  "type": "Feature",
  "properties": {
    "iso:country": "GB",
    "wof:name": "BL8 1DE",
    "wof:placetype": "postalcode"
  },
  "geometry": {"coordinates":[-2.308708,53.600514],"type":"Point"}
}
