{
  "type": "Feature",
  "properties": {
    "date:inception_lower": "1992-08-01",
    "date:inception_upper": "1992-08-01",
    "iso:country": "GB",
    "wof:name": "SY21 7BA",
    "wof:placetype": "postalcode"
  },
  "geometry": {"coordinates":[-3.133913,52.663187],"type":"Point"}
}
