{
  "type": "Feature",
  "properties": {
    "iso:country":"GB",
    "wof:name":"SY21 7BA",
    "wof:placetype":"postalcode"
},
  "geometry": {"coordinates":[-3.13391261074703,52.66318671377952],"type":"Point"}
}