{
  "type": "Feature",
  "properties": {
    "iso:country":"GB",
    "wof:name":"W1F 7BH",
    "wof:placetype":"postalcode"
},
  "geometry": {"coordinates":[-0.1396571629069,51.51373870989198],"type":"Point"}
}