{
  "type": "Feature",
  "properties": {
    "iso:country":"GB",
    "wof:name":"SE27 0UT",
    "wof:placetype":"postalcode"
},
  "geometry": {"coordinates":[-0.10151022982938,51.42731995031655],"type":"Point"}
}