{
  "type": "Feature",
  "properties": {
    "iso:country":"GB",
    "wof:name":"GL9 1BP",
    "wof:placetype":"postalcode"
},
  "geometry": {"coordinates":[-2.34592501534283,51.58864105906149],"type":"Point"}
}