{
  "type": "Feature",
  "properties": {
    "iso:country":"GB",
    "wof:name":"PE20 2DG",
    "wof:placetype":"postalcode"
},
  "geometry": {"coordinates":[-0.03758324601383,52.87785180629486],"type":"Point"}
}