{
  "type": "Feature",
  "properties": {
    "iso:country": "GB",
    "wof:name": "EH6 7AG",
    "wof:placetype": "postalcode"
  },
  "geometry": {"coordinates":[-3.168819,55.972111],"type":"Point"}
}
