{
  "type": "Feature",
  "properties": {
    "iso:country":"GB",
    "wof:name":"B70 9BD",
    "wof:placetype":"postalcode"
},
  "geometry": {"coordinates":[-2.0253928539514,52.51926343419131],"type":"Point"}
}