{
  "type": "Feature",
  "properties": {
    "iso:country":"GB",
    "wof:name":"YO26 6PS",
    "wof:placetype":"postalcode"
},
  "geometry": {"coordinates":[-1.15795682335541,53.97369723523286],"type":"Point"}
}