{
  "type": "Feature",
  "properties": {
    "iso:country":"GB",
    "wof:name":"SE8 4RG",
    "wof:placetype":"postalcode"
},
  "geometry": {"coordinates":[-0.02569871468456,51.47740687257416],"type":"Point"}
}