{
  "type": "Feature",
  "properties": {
    "iso:country":"GB",
    "wof:name":"RM15 4UA",
    "wof:placetype":"postalcode"
},
  "geometry": {"coordinates":[0.25915816826693,51.50159907557433],"type":"Point"}
}