{
  "type": "Feature",
  "properties": {
    "iso:country": "GB",
    "wof:name": "RM15 4UA",
    "wof:placetype": "postalcode"
  },
  "geometry": {"coordinates":[0.259158,51.501599],"type":"Point"}
}
