{
  "type": "Feature",
  "properties": {
    "iso:country": "GB",
    "wof:name": "EH31 2DG",
    "wof:placetype": "postalcode"
  },
  "geometry": {"coordinates":[-2.829664,56.037172],"type":"Point"}
}
