{
  "type": "Feature",
  "properties": {
    "iso:country":"GB",
    "wof:name":"KT24 5NA",
    "wof:placetype":"postalcode"
},
  "geometry": {"coordinates":[-0.3991815831005,51.27134676854718],"type":"Point"}
}