{
  "type": "Feature",
  "properties": {
    "iso:country": "GB",
    "wof:name": "KT24 5NA",
    "wof:placetype": "postalcode"
  },
  "geometry": {"coordinates":[-0.399182,51.271347],"type":"Point"}
}
