{
  "type": "Feature",
  "properties": {
    "date:inception_lower": "1980-01-01",
    "date:inception_upper": "1980-01-01",
    "iso:country": "GB",
    "wof:name": "G73 3HS",
    "wof:placetype": "postalcode"
  },
  "geometry": {"coordinates":[-4.201198,55.825799],"type":"Point"}
}
