{
  "type": "Feature",
  "properties": {
    "date:inception_lower": "1980-01-01",
    "date:inception_upper": "1980-01-01",
    "iso:country": "GB",
    "wof:name": "CA28 8BX",
    "wof:placetype": "postalcode"
  },
  "geometry": {"coordinates":[-3.573908,54.529211],"type":"Point"}
}
