{
  "type": "Feature",
  "properties": {
    "iso:country":"GB",
    "wof:name":"CA28 8BX",
    "wof:placetype":"postalcode"
},
  "geometry": {"coordinates":[-3.57390848457179,54.52921136285448],"type":"Point"}
}