{
  "type": "Feature",
  "properties": {
    "iso:country":"GB",
    "wof:name":"KW15 1GN",
    "wof:placetype":"postalcode"
},
  "geometry": {"coordinates":[-2.97074730382816,58.98721454937376],"type":"Point"}
}