{
  "type": "Feature",
  "properties": {
    "date:inception_lower":"1997-06-01",
    "date:inception_upper":"1997-06-30",
    "iso:country":"GB",
    "wof:name":"KW15 1GN",
    "wof:placetype":"postalcode"
},
  "geometry": {"coordinates":[-2.971002,58.987394],"type":"Point"}
}