{
  "type": "Feature",
  "properties": {
    "date:inception_lower":"1980-01-01",
    "date:inception_upper":"1980-01-31",
    "iso:country":"GB",
    "wof:name":"MK41 9HJ",
    "wof:placetype":"postalcode"
},
  "geometry": {"coordinates":[-0.431528,52.146653],"type":"Point"}
}