{
  "type": "Feature",
  "properties": {
    "iso:country":"GB",
    "wof:name":"MK41 9HJ",
    "wof:placetype":"postalcode"
},
  "geometry": {"coordinates":[-0.43152794090837,52.1466534556094],"type":"Point"}
}