{
  "type": "Feature",
  "properties": {
    "date:inception_lower": "1980-01-01",
    "date:inception_upper": "1980-01-01",
    "iso:country": "GB",
    "wof:name": "TN33 9LY",
    "wof:placetype": "postalcode"
  },
  "geometry": {"coordinates":[0.430679,50.898369],"type":"Point"}
}
