{
  "type": "Feature",
  "properties": {
    "iso:country":"GB",
    "wof:name":"NP10 8HP",
    "wof:placetype":"postalcode"
},
  "geometry": {"coordinates":[-3.01126780987859,51.56210701219375],"type":"Point"}
}