{
  "type": "Feature",
  "properties": {
    "date:inception_lower": "2002-07-01",
    "date:inception_upper": "2002-07-01",
    "iso:country": "GB",
    "wof:name": "NP10 8HP",
    "wof:placetype": "postalcode"
  },
  "geometry": {"coordinates":[-3.011268,51.562107],"type":"Point"}
}
