{
  "type": "Feature",
  "properties": {
    "date:inception_lower": "1980-01-01",
    "date:inception_upper": "1980-01-01",
    "iso:country": "GB",
    "wof:name": "SY2 5LH",
    "wof:placetype": "postalcode"
  },
  "geometry": {"coordinates":[-2.717155,52.711212],"type":"Point"}
}
