{
  "type": "Feature",
  "properties": {
    "iso:country":"GB",
    "wof:name":"G42 8EL",
    "wof:placetype":"postalcode"
},
  "geometry": {"coordinates":[-4.25701165421481,55.83371139929304],"type":"Point"}
}