{
  "type": "Feature",
  "properties": {
    "iso:country":"GB",
    "wof:name":"CF44 7PR",
    "wof:placetype":"postalcode"
},
  "geometry": {"coordinates":[-3.45239389162655,51.71062540430029],"type":"Point"}
}