{
  "type": "Feature",
  "properties": {
    "iso:country": "GB",
    "wof:name": "DN22 0LJ",
    "wof:placetype": "postalcode"
  },
  "geometry": {"coordinates":[-0.842484,53.269455],"type":"Point"}
}
