{
  "type": "Feature",
  "properties": {
    "date:inception_lower":"1983-07-01",
    "date:inception_upper":"1983-07-31",
    "iso:country":"GB",
    "wof:name":"GU21 3LA",
    "wof:placetype":"postalcode"
},
  "geometry": {"coordinates":[-0.594861,51.320268],"type":"Point"}
}