{
  "type": "Feature",
  "properties": {
    "iso:country": "GB",
    "wof:name": "GU21 3LA",
    "wof:placetype": "postalcode"
  },
  "geometry": {"coordinates":[-0.594861,51.320268],"type":"Point"}
}
