{
  "type": "Feature",
  "properties": {
    "iso:country":"GB",
    "wof:name":"GU21 3LA",
    "wof:placetype":"postalcode"
},
  "geometry": {"coordinates":[-0.59486091354428,51.32026833080386],"type":"Point"}
}