{
  "type": "Feature",
  "properties": {
    "iso:country": "GB",
    "wof:name": "OX33 1BD",
    "wof:placetype": "postalcode"
  },
  "geometry": {"coordinates":[-1.132304,51.805957],"type":"Point"}
}
