{
  "type": "Feature",
  "properties": {
    "iso:country":"GB",
    "wof:name":"OX33 1BD",
    "wof:placetype":"postalcode"
},
  "geometry": {"coordinates":[-1.13230383810025,51.80595697191697],"type":"Point"}
}