{
  "type": "Feature",
  "properties": {
    "iso:country":"GB",
    "wof:name":"BL7 0QF",
    "wof:placetype":"postalcode"
},
  "geometry": {"coordinates":[-2.40764461487448,53.65906352559184],"type":"Point"}
}