{
  "type": "Feature",
  "properties": {
    "iso:country": "GB",
    "wof:name": "WF13 1LD",
    "wof:placetype": "postalcode"
  },
  "geometry": {"coordinates":[-1.63053,53.69063],"type":"Point"}
}
