{
  "type": "Feature",
  "properties": {
    "iso:country":"GB",
    "wof:name":"WF13 1LD",
    "wof:placetype":"postalcode"
},
  "geometry": {"coordinates":[-1.63052993995497,53.69062981011707],"type":"Point"}
}