{
  "type": "Feature",
  "properties": {
    "iso:country":"GB",
    "wof:name":"SA5 4AZ",
    "wof:placetype":"postalcode"
},
  "geometry": {"coordinates":[-3.98805960523499,51.64676571642386],"type":"Point"}
}