{
  "type": "Feature",
  "properties": {
    "date:inception_lower":"1981-09-01",
    "date:inception_upper":"1981-09-30",
    "iso:country":"GB",
    "wof:name":"KA30 8NX",
    "wof:placetype":"postalcode"
},
  "geometry": {"coordinates":[-4.877826,55.806606],"type":"Point"}
}