{
  "type": "Feature",
  "properties": {
    "iso:country": "GB",
    "wof:name": "KA30 8NX",
    "wof:placetype": "postalcode"
  },
  "geometry": {"coordinates":[-4.877826,55.806606],"type":"Point"}
}
