{
  "type": "Feature",
  "properties": {
    "iso:country":"GB",
    "wof:name":"EX33 1AH",
    "wof:placetype":"postalcode"
},
  "geometry": {"coordinates":[-4.16421573241655,51.10882314408978],"type":"Point"}
}