{
  "type": "Feature",
  "properties": {
    "date:inception_lower": "1980-01-01",
    "date:inception_upper": "1980-01-01",
    "iso:country": "GB",
    "wof:name": "L15 4LH",
    "wof:placetype": "postalcode"
  },
  "geometry": {"coordinates":[-2.934656,53.401728],"type":"Point"}
}
