{
  "type": "Feature",
  "properties": {
    "date:inception_lower": "1980-01-01",
    "date:inception_upper": "1980-01-01",
    "iso:country": "GB",
    "wof:name": "PR3 6HN",
    "wof:placetype": "postalcode"
  },
  "geometry": {"coordinates":[-2.924504,53.933998],"type":"Point"}
}
