{
  "type": "Feature",
  "properties": {
    "iso:country":"GB",
    "wof:name":"WS13 8NJ",
    "wof:placetype":"postalcode"
},
  "geometry": {"coordinates":[-1.76160185930126,52.71968720596238],"type":"Point"}
}