{
  "type": "Feature",
  "properties": {
    "iso:country": "GB",
    "wof:name": "WS13 8NJ",
    "wof:placetype": "postalcode"
  },
  "geometry": {"coordinates":[-1.761602,52.719687],"type":"Point"}
}
