{
  "type": "Feature",
  "properties": {
    "iso:country": "GB",
    "wof:name": "E4 6SS",
    "wof:placetype": "postalcode"
  },
  "geometry": {"coordinates":[-0.014214,51.619008],"type":"Point"}
}
