{
  "type": "Feature",
  "properties": {
    "date:inception_lower":"1980-01-01",
    "date:inception_upper":"1980-01-31",
    "iso:country":"GB",
    "wof:name":"NE47 7BX",
    "wof:placetype":"postalcode"
},
  "geometry": {"coordinates":[-2.335795,54.962355],"type":"Point"}
}