{
  "type": "Feature",
  "properties": {
    "iso:country": "GB",
    "wof:name": "NE47 7BX",
    "wof:placetype": "postalcode"
  },
  "geometry": {"coordinates":[-2.335795,54.962355],"type":"Point"}
}
