{
  "type": "Feature",
  "properties": {
    "iso:country":"GB",
    "wof:name":"NE47 7BX",
    "wof:placetype":"postalcode"
},
  "geometry": {"coordinates":[-2.33579547814592,54.96235476330231],"type":"Point"}
}