{
  "type": "Feature",
  "properties": {
    "date:inception_lower": "2022-02-01",
    "date:inception_upper": "2022-02-01",
    "iso:country": "GB",
    "wof:name": "DH3 3EE",
    "wof:placetype": "postalcode"
  },
  "geometry": {"coordinates":[-1.578059,54.854557],"type":"Point"}
}
