{
  "type": "Feature",
  "properties": {
    "iso:country":"GB",
    "wof:name":"DH3 3EE",
    "wof:placetype":"postalcode"
},
  "geometry": {"coordinates":[-1.57815470614256,54.85466525505355],"type":"Point"}
}