{
  "type": "Feature",
  "properties": {
    "iso:country":"GB",
    "wof:name":"WV7 3JJ",
    "wof:placetype":"postalcode"
},
  "geometry": {"coordinates":[-2.26222386075515,52.63353262488089],"type":"Point"}
}