{
  "type": "Feature",
  "properties": {
    "iso:country": "GB",
    "wof:name": "WV7 3JJ",
    "wof:placetype": "postalcode"
  },
  "geometry": {"coordinates":[-2.261969,52.633584],"type":"Point"}
}
