{
  "type": "Feature",
  "properties": {
    "iso:country":"GB",
    "wof:name":"HD6 4HY",
    "wof:placetype":"postalcode"
},
  "geometry": {"coordinates":[-1.76175677916831,53.70477714173254],"type":"Point"}
}