{
  "type": "Feature",
  "properties": {
    "iso:country": "GB",
    "wof:name": "HD6 4HY",
    "wof:placetype": "postalcode"
  },
  "geometry": {"coordinates":[-1.761757,53.704777],"type":"Point"}
}
