{
  "type": "Feature",
  "properties": {
    "iso:country":"GB",
    "wof:name":"TN1 2BF",
    "wof:placetype":"postalcode"
},
  "geometry": {"coordinates":[0.2624896637468,51.13683068433495],"type":"Point"}
}