{
  "type": "Feature",
  "properties": {
    "date:inception_lower": "1980-01-01",
    "date:inception_upper": "1980-01-01",
    "iso:country": "GB",
    "wof:name": "BD8 9HU",
    "wof:placetype": "postalcode"
  },
  "geometry": {"coordinates":[-1.785985,53.802807],"type":"Point"}
}
