{
  "type": "Feature",
  "properties": {
    "iso:country":"GB",
    "wof:name":"BD8 9HU",
    "wof:placetype":"postalcode"
},
  "geometry": {"coordinates":[-1.785996727611,53.80281944264237],"type":"Point"}
}