{
  "type": "Feature",
  "properties": {
    "iso:country": "GB",
    "wof:name": "BD8 9HU",
    "wof:placetype": "postalcode"
  },
  "geometry": {"coordinates":[-1.785997,53.802819],"type":"Point"}
}
