{
  "type": "Feature",
  "properties": {
    "date:inception_lower":"2001-12-01",
    "date:inception_upper":"2001-12-31",
    "iso:country":"GB",
    "wof:name":"GL17 0LY",
    "wof:placetype":"postalcode"
},
  "geometry": {"coordinates":[-2.458197,51.872296],"type":"Point"}
}