{
  "type": "Feature",
  "properties": {
    "date:inception_lower":"1980-01-01",
    "date:inception_upper":"1980-01-31",
    "iso:country":"GB",
    "wof:name":"TQ13 9ET",
    "wof:placetype":"postalcode"
},
  "geometry": {"coordinates":[-3.663433,50.593644],"type":"Point"}
}