{
  "type": "Feature",
  "properties": {
    "iso:country": "GB",
    "wof:name": "TQ13 9ET",
    "wof:placetype": "postalcode"
  },
  "geometry": {"coordinates":[-3.663433,50.593644],"type":"Point"}
}
