{
  "type": "Feature",
  "properties": {
    "iso:country":"GB",
    "wof:name":"HP12 4RR",
    "wof:placetype":"postalcode"
},
  "geometry": {"coordinates":[-0.78634301580425,51.6219219012043],"type":"Point"}
}