{
  "type": "Feature",
  "properties": {
    "iso:country":"GB",
    "wof:name":"NG9 3QR",
    "wof:placetype":"postalcode"
},
  "geometry": {"coordinates":[-1.27915604661757,52.95293207838846],"type":"Point"}
}