{
  "type": "Feature",
  "properties": {
    "date:inception_lower": "1980-01-01",
    "date:inception_upper": "1980-01-01",
    "iso:country": "GB",
    "wof:name": "DN20 9NH",
    "wof:placetype": "postalcode"
  },
  "geometry": {"coordinates":[-0.559858,53.518146],"type":"Point"}
}
