{
  "type": "Feature",
  "properties": {
    "date:inception_lower": "2007-07-01",
    "date:inception_upper": "2007-07-01",
    "iso:country": "GB",
    "wof:name": "HX6 4PW",
    "wof:placetype": "postalcode"
  },
  "geometry": {"coordinates":[-1.968143,53.65389],"type":"Point"}
}
