{
  "type": "Feature",
  "properties": {
    "iso:country":"GB",
    "wof:name":"HX6 4PW",
    "wof:placetype":"postalcode"
},
  "geometry": {"coordinates":[-1.96811375367839,53.65382189407459],"type":"Point"}
}