{
  "type": "Feature",
  "properties": {
    "iso:country":"GB",
    "wof:name":"MK43 8BE",
    "wof:placetype":"postalcode"
},
  "geometry": {"coordinates":[-0.59928934977062,52.15940151318684],"type":"Point"}
}