{
  "type": "Feature",
  "properties": {
    "iso:country":"GB",
    "wof:name":"HG3 3LN",
    "wof:placetype":"postalcode"
},
  "geometry": {"coordinates":[-1.62452901088384,54.03438997398459],"type":"Point"}
}