{
  "type": "Feature",
  "properties": {
    "iso:country": "GB",
    "wof:name": "HG3 3LN",
    "wof:placetype": "postalcode"
  },
  "geometry": {"coordinates":[-1.624529,54.03439],"type":"Point"}
}
