{
  "type": "Feature",
  "properties": {
    "iso:country":"GB",
    "wof:name":"RG2 8QG",
    "wof:placetype":"postalcode"
},
  "geometry": {"coordinates":[-0.95644750979905,51.41332015830786],"type":"Point"}
}