{
  "type": "Feature",
  "properties": {
    "iso:country": "GB",
    "wof:name": "RG2 8QG",
    "wof:placetype": "postalcode"
  },
  "geometry": {"coordinates":[-0.956447,51.41332],"type":"Point"}
}
