{
  "type": "Feature",
  "properties": {
    "iso:country": "GB",
    "wof:name": "WV5 7DE",
    "wof:placetype": "postalcode"
  },
  "geometry": {"coordinates":[-2.294572,52.548377],"type":"Point"}
}
