{
  "type": "Feature",
  "properties": {
    "iso:country":"GB",
    "wof:name":"WV5 7DE",
    "wof:placetype":"postalcode"
},
  "geometry": {"coordinates":[-2.29457187886516,52.5483768990059],"type":"Point"}
}