{
  "type": "Feature",
  "properties": {
    "date:inception_lower":"1980-01-01",
    "date:inception_upper":"1980-01-31",
    "iso:country":"GB",
    "wof:name":"WV5 7DE",
    "wof:placetype":"postalcode"
},
  "geometry": {"coordinates":[-2.294572,52.548377],"type":"Point"}
}