{
  "type": "Feature",
  "properties": {
    "date:inception_lower": "1980-01-01",
    "date:inception_upper": "1980-01-01",
    "iso:country": "GB",
    "wof:name": "N8 9PP",
    "wof:placetype": "postalcode"
  },
  "geometry": {"coordinates":[-0.115938,51.580696],"type":"Point"}
}
