{
  "type": "Feature",
  "properties": {
    "date:inception_lower": "1980-01-01",
    "date:inception_upper": "1980-01-01",
    "iso:country": "GB",
    "wof:name": "LL36 9AT",
    "wof:placetype": "postalcode"
  },
  "geometry": {"coordinates":[-4.10104,52.590747],"type":"Point"}
}
