{
  "type": "Feature",
  "properties": {
    "iso:country":"GB",
    "wof:name":"AB32 6QF",
    "wof:placetype":"postalcode"
},
  "geometry": {"coordinates":[-2.29447488261117,57.15254022180935],"type":"Point"}
}