{
  "type": "Feature",
  "properties": {
    "date:inception_lower": "1980-01-01",
    "date:inception_upper": "1980-01-01",
    "iso:country": "GB",
    "wof:name": "KA3 6JB",
    "wof:placetype": "postalcode"
  },
  "geometry": {"coordinates":[-4.408526,55.661944],"type":"Point"}
}
