{
  "type": "Feature",
  "properties": {
    "iso:country":"GB",
    "wof:name":"KA3 6JB",
    "wof:placetype":"postalcode"
},
  "geometry": {"coordinates":[-4.40852562536857,55.66194414511614],"type":"Point"}
}