{
  "type": "Feature",
  "properties": {
    "iso:country":"GB",
    "wof:name":"B37 7HW",
    "wof:placetype":"postalcode"
},
  "geometry": {"coordinates":[-1.73581882202122,52.46795394313211],"type":"Point"}
}