{
  "type": "Feature",
  "properties": {
    "iso:country":"GB",
    "wof:name":"ME1 3AU",
    "wof:placetype":"postalcode"
},
  "geometry": {"coordinates":[0.49560755157213,51.35888974959171],"type":"Point"}
}