{
  "type": "Feature",
  "properties": {
    "iso:country":"GB",
    "wof:name":"NR9 3LE",
    "wof:placetype":"postalcode"
},
  "geometry": {"coordinates":[1.19787864235763,52.62107086882266],"type":"Point"}
}