{
  "type": "Feature",
  "properties": {
    "date:inception_lower":"2013-07-01",
    "date:inception_upper":"2013-07-31",
    "iso:country":"GB",
    "wof:name":"CV2 2JU",
    "wof:placetype":"postalcode"
},
  "geometry": {"coordinates":[-1.432099,52.42715],"type":"Point"}
}