{
  "type": "Feature",
  "properties": {
    "iso:country":"GB",
    "wof:name":"PR8 3JW",
    "wof:placetype":"postalcode"
},
  "geometry": {"coordinates":[-3.03962673618941,53.6000704872881],"type":"Point"}
}