{
  "type": "Feature",
  "properties": {
    "iso:country": "GB",
    "wof:name": "PR8 3JW",
    "wof:placetype": "postalcode"
  },
  "geometry": {"coordinates":[-3.039627,53.60007],"type":"Point"}
}
