{
  "type": "Feature",
  "properties": {
    "date:inception_lower": "1980-01-01",
    "date:inception_upper": "1980-01-01",
    "iso:country": "GB",
    "wof:name": "PR8 3JW",
    "wof:placetype": "postalcode"
  },
  "geometry": {"coordinates":[-3.039627,53.60007],"type":"Point"}
}
