{
  "type": "Feature",
  "properties": {
    "iso:country":"GB",
    "wof:name":"RG40 3BD",
    "wof:placetype":"postalcode"
},
  "geometry": {"coordinates":[-0.81102486469603,51.39180226320886],"type":"Point"}
}