{
  "type": "Feature",
  "properties": {
    "iso:country": "GB",
    "wof:name": "BH16 5RX",
    "wof:placetype": "postalcode"
  },
  "geometry": {"coordinates":[-2.041753,50.737864],"type":"Point"}
}
