{
  "type": "Feature",
  "properties": {
    "date:inception_lower": "1985-10-01",
    "date:inception_upper": "1985-10-01",
    "iso:country": "GB",
    "wof:name": "BH16 5RX",
    "wof:placetype": "postalcode"
  },
  "geometry": {"coordinates":[-2.041753,50.737864],"type":"Point"}
}
