{
  "type": "Feature",
  "properties": {
    "iso:country":"GB",
    "wof:name":"S62 5DA",
    "wof:placetype":"postalcode"
},
  "geometry": {"coordinates":[-1.33859767149443,53.4621368617411],"type":"Point"}
}