{
  "type": "Feature",
  "properties": {
    "iso:country":"GB",
    "wof:name":"OX26 2EB",
    "wof:placetype":"postalcode"
},
  "geometry": {"coordinates":[-1.16284483007816,51.90322869712023],"type":"Point"}
}