{
  "type": "Feature",
  "properties": {
    "date:inception_lower":"1980-01-01",
    "date:inception_upper":"1980-01-31",
    "iso:country":"GB",
    "wof:name":"HU9 5TJ",
    "wof:placetype":"postalcode"
},
  "geometry": {"coordinates":[-0.275468,53.7551],"type":"Point"}
}