{
  "type": "Feature",
  "properties": {
    "date:inception_lower": "1983-07-01",
    "date:inception_upper": "1983-07-01",
    "iso:country": "GB",
    "wof:name": "IP19 8TJ",
    "wof:placetype": "postalcode"
  },
  "geometry": {"coordinates":[1.496674,52.339679],"type":"Point"}
}
