{
  "type": "Feature",
  "properties": {
    "date:inception_lower": "1980-01-01",
    "date:inception_upper": "1980-01-01",
    "iso:country": "GB",
    "wof:name": "WA14 4HN",
    "wof:placetype": "postalcode"
  },
  "geometry": {"coordinates":[-2.354156,53.393725],"type":"Point"}
}
