{
  "type": "Feature",
  "properties": {
    "iso:country":"GB",
    "wof:name":"NG16 1AZ",
    "wof:placetype":"postalcode"
},
  "geometry": {"coordinates":[-1.21512332706226,52.98414249556092],"type":"Point"}
}