{
  "type": "Feature",
  "properties": {
    "iso:country":"GB",
    "wof:name":"LU7 9QY",
    "wof:placetype":"postalcode"
},
  "geometry": {"coordinates":[-0.6454910091475,51.82761331127933],"type":"Point"}
}