{
  "type": "Feature",
  "properties": {
    "date:inception_lower": "2011-05-01",
    "date:inception_upper": "2011-05-01",
    "iso:country": "GB",
    "wof:name": "LU7 9QY",
    "wof:placetype": "postalcode"
  },
  "geometry": {"coordinates":[-0.645491,51.827613],"type":"Point"}
}
