{
  "type": "Feature",
  "properties": {
    "iso:country":"GB",
    "wof:name":"NN8 5FL",
    "wof:placetype":"postalcode"
},
  "geometry": {"coordinates":[-0.70837031314112,52.31703390382354],"type":"Point"}
}