{
  "type": "Feature",
  "properties": {
    "iso:country":"GB",
    "wof:name":"WS10 0SQ",
    "wof:placetype":"postalcode"
},
  "geometry": {"coordinates":[-1.99131277278254,52.55912698696807],"type":"Point"}
}