{
  "type": "Feature",
  "properties": {
    "iso:country":"GB",
    "wof:name":"CT9 1HR",
    "wof:placetype":"postalcode"
},
  "geometry": {"coordinates":[1.38464756497659,51.3907921237473],"type":"Point"}
}