{
  "type": "Feature",
  "properties": {
    "iso:country": "GB",
    "wof:name": "CT9 1HR",
    "wof:placetype": "postalcode"
  },
  "geometry": {"coordinates":[1.384648,51.390792],"type":"Point"}
}
