{
  "type": "Feature",
  "properties": {
    "iso:country":"GB",
    "wof:name":"GU35 9BE",
    "wof:placetype":"postalcode"
},
  "geometry": {"coordinates":[-0.86620116916773,51.1016210873334],"type":"Point"}
}