{
  "type": "Feature",
  "properties": {
    "date:inception_lower": "1980-01-01",
    "date:inception_upper": "1980-01-01",
    "iso:country": "GB",
    "wof:name": "GU35 9BE",
    "wof:placetype": "postalcode"
  },
  "geometry": {"coordinates":[-0.866201,51.101621],"type":"Point"}
}
