{
  "type": "Feature",
  "properties": {
    "date:inception_lower": "1980-01-01",
    "date:inception_upper": "1980-01-01",
    "iso:country": "GB",
    "wof:name": "WA5 2JR",
    "wof:placetype": "postalcode"
  },
  "geometry": {"coordinates":[-2.645741,53.383126],"type":"Point"}
}
