{
  "type": "Feature",
  "properties": {
    "iso:country":"GB",
    "wof:name":"NG17 9GD",
    "wof:placetype":"postalcode"
},
  "geometry": {"coordinates":[-1.25289477820748,53.08098504878824],"type":"Point"}
}