{
  "type": "Feature",
  "properties": {
    "date:inception_lower": "1980-01-01",
    "date:inception_upper": "1980-01-01",
    "iso:country": "GB",
    "wof:name": "TQ12 4QN",
    "wof:placetype": "postalcode"
  },
  "geometry": {"coordinates":[-3.524518,50.512221],"type":"Point"}
}
