{
  "type": "Feature",
  "properties": {
    "iso:country":"GB",
    "wof:name":"TR16 5TE",
    "wof:placetype":"postalcode"
},
  "geometry": {"coordinates":[-5.20725170380695,50.21826859659965],"type":"Point"}
}