{
  "type": "Feature",
  "properties": {
    "iso:country": "GB",
    "wof:name": "AB11 5HU",
    "wof:placetype": "postalcode"
  },
  "geometry": {"coordinates":[-2.09221,57.148641],"type":"Point"}
}
