{
  "type": "Feature",
  "properties": {
    "iso:country": "GB",
    "wof:name": "PR7 3BN",
    "wof:placetype": "postalcode"
  },
  "geometry": {"coordinates":[-2.660634,53.634736],"type":"Point"}
}
