{
  "type": "Feature",
  "properties": {
    "iso:country":"GB",
    "wof:name":"PR7 3BN",
    "wof:placetype":"postalcode"
},
  "geometry": {"coordinates":[-2.66063452064543,53.63473551887674],"type":"Point"}
}