{
  "type": "Feature",
  "properties": {
    "iso:country":"GB",
    "wof:name":"SS13 3HQ",
    "wof:placetype":"postalcode"
},
  "geometry": {"coordinates":[0.50504271026216,51.56753391531917],"type":"Point"}
}