{
  "type": "Feature",
  "properties": {
    "iso:country":"GB",
    "wof:name":"TA4 3SY",
    "wof:placetype":"postalcode"
},
  "geometry": {"coordinates":[-3.29237473302559,51.12452883177758],"type":"Point"}
}