{
  "type": "Feature",
  "properties": {
    "iso:country": "GB",
    "wof:name": "TA4 3SY",
    "wof:placetype": "postalcode"
  },
  "geometry": {"coordinates":[-3.292375,51.124529],"type":"Point"}
}
