{
  "type": "Feature",
  "properties": {
    "date:inception_lower":"1980-01-01",
    "date:inception_upper":"1980-01-31",
    "iso:country":"GB",
    "wof:name":"TA4 3SY",
    "wof:placetype":"postalcode"
},
  "geometry": {"coordinates":[-3.292375,51.124529],"type":"Point"}
}