{
  "type": "Feature",
  "properties": {
    "iso:country": "GB",
    "wof:name": "UB4 0XP",
    "wof:placetype": "postalcode"
  },
  "geometry": {"coordinates":[-0.400447,51.523457],"type":"Point"}
}
