{
  "type": "Feature",
  "properties": {
    "iso:country":"GB",
    "wof:name":"UB4 0XP",
    "wof:placetype":"postalcode"
},
  "geometry": {"coordinates":[-0.40044713988844,51.52345686178107],"type":"Point"}
}