{
  "type": "Feature",
  "properties": {
    "iso:country":"GB",
    "wof:name":"GU5 9LT",
    "wof:placetype":"postalcode"
},
  "geometry": {"coordinates":[-0.45062203735338,51.21707626730426],"type":"Point"}
}