{
  "type": "Feature",
  "properties": {
    "iso:country":"GB",
    "wof:name":"SK11 7PW",
    "wof:placetype":"postalcode"
},
  "geometry": {"coordinates":[-2.12071117368785,53.24998427410156],"type":"Point"}
}