{
  "type": "Feature",
  "properties": {
    "iso:country": "GB",
    "wof:name": "B4 6SH",
    "wof:placetype": "postalcode"
  },
  "geometry": {"coordinates":[-1.895055,52.482766],"type":"Point"}
}
