{
  "type": "Feature",
  "properties": {
    "iso:country":"GB",
    "wof:name":"OX4 2ED",
    "wof:placetype":"postalcode"
},
  "geometry": {"coordinates":[-1.22062951041899,51.73709104755152],"type":"Point"}
}