{
  "type": "Feature",
  "properties": {
    "iso:country": "GB",
    "wof:name": "SN11 9BA",
    "wof:placetype": "postalcode"
  },
  "geometry": {"coordinates":[-2.000728,51.44608],"type":"Point"}
}
