{
  "type": "Feature",
  "properties": {
    "iso:country":"GB",
    "wof:name":"SN11 9BA",
    "wof:placetype":"postalcode"
},
  "geometry": {"coordinates":[-2.00072820545166,51.44607980314113],"type":"Point"}
}