{
  "type": "Feature",
  "properties": {
    "iso:country":"GB",
    "wof:name":"SE14 5EE",
    "wof:placetype":"postalcode"
},
  "geometry": {"coordinates":[-0.04852420182024,51.47841848580148],"type":"Point"}
}