{
  "type": "Feature",
  "properties": {
    "iso:country":"GB",
    "wof:name":"BL3 4NQ",
    "wof:placetype":"postalcode"
},
  "geometry": {"coordinates":[-2.47428570279849,53.56874597830171],"type":"Point"}
}