{
  "type": "Feature",
  "properties": {
    "iso:country": "GB",
    "wof:name": "CH63 5PG",
    "wof:placetype": "postalcode"
  },
  "geometry": {"coordinates":[-3.031005,53.36239],"type":"Point"}
}
