{
  "type": "Feature",
  "properties": {
    "date:inception_lower": "1980-01-01",
    "date:inception_upper": "1980-01-01",
    "iso:country": "GB",
    "wof:name": "NE21 4EN",
    "wof:placetype": "postalcode"
  },
  "geometry": {"coordinates":[-1.72823,54.958921],"type":"Point"}
}
