{
  "type": "Feature",
  "properties": {
    "date:inception_lower": "2014-09-01",
    "date:inception_upper": "2014-09-01",
    "iso:country": "GB",
    "wof:name": "PR9 9DH",
    "wof:placetype": "postalcode"
  },
  "geometry": {"coordinates":[-2.981056,53.658757],"type":"Point"}
}
