{
  "type": "Feature",
  "properties": {
    "iso:country":"GB",
    "wof:name":"PR9 9DH",
    "wof:placetype":"postalcode"
},
  "geometry": {"coordinates":[-2.98105563204965,53.65875734721807],"type":"Point"}
}