{
  "type": "Feature",
  "properties": {
    "iso:country":"GB",
    "wof:name":"B43 6QL",
    "wof:placetype":"postalcode"
},
  "geometry": {"coordinates":[-1.95166161225259,52.54710709175934],"type":"Point"}
}