{
  "type": "Feature",
  "properties": {
    "date:inception_lower":"1980-01-01",
    "date:inception_upper":"1980-01-31",
    "iso:country":"GB",
    "wof:name":"CH5 2HT",
    "wof:placetype":"postalcode"
},
  "geometry": {"coordinates":[-3.010118,53.213637],"type":"Point"}
}