{
  "type": "Feature",
  "properties": {
    "iso:country":"GB",
    "wof:name":"CH5 2HT",
    "wof:placetype":"postalcode"
},
  "geometry": {"coordinates":[-3.01011814023306,53.21363665482521],"type":"Point"}
}