{
  "type": "Feature",
  "properties": {
    "iso:country":"GB",
    "wof:name":"NN18 0PB",
    "wof:placetype":"postalcode"
},
  "geometry": {"coordinates":[-0.7197997998633,52.48257730516637],"type":"Point"}
}