{
  "type": "Feature",
  "properties": {
    "iso:country":"GB",
    "wof:name":"CV7 7RT",
    "wof:placetype":"postalcode"
},
  "geometry": {"coordinates":[-1.64793407366482,52.39476178453079],"type":"Point"}
}