{
  "type": "Feature",
  "properties": {
    "iso:country":"GB",
    "wof:name":"M22 4YJ",
    "wof:placetype":"postalcode"
},
  "geometry": {"coordinates":[-2.25160768636774,53.4027851425827],"type":"Point"}
}