{
  "type": "Feature",
  "properties": {
    "iso:country": "GB",
    "wof:name": "NE8 4QR",
    "wof:placetype": "postalcode"
  },
  "geometry": {"coordinates":[-1.615084,54.951328],"type":"Point"}
}
