{
  "type": "Feature",
  "properties": {
    "iso:country":"GB",
    "wof:name":"NE8 4QR",
    "wof:placetype":"postalcode"
},
  "geometry": {"coordinates":[-1.61508431629863,54.95132837265942],"type":"Point"}
}