{
  "type": "Feature",
  "properties": {
    "iso:country": "GB",
    "wof:name": "BA21 5EZ",
    "wof:placetype": "postalcode"
  },
  "geometry": {"coordinates":[-2.615319,50.946511],"type":"Point"}
}
