{
  "type": "Feature",
  "properties": {
    "iso:country":"GB",
    "wof:name":"BA21 5EZ",
    "wof:placetype":"postalcode"
},
  "geometry": {"coordinates":[-2.61531902539656,50.94651129270526],"type":"Point"}
}