{
  "type": "Feature",
  "properties": {
    "date:inception_lower": "2010-08-01",
    "date:inception_upper": "2010-08-01",
    "iso:country": "GB",
    "wof:name": "BA21 5EZ",
    "wof:placetype": "postalcode"
  },
  "geometry": {"coordinates":[-2.615319,50.946511],"type":"Point"}
}
