{
  "type": "Feature",
  "properties": {
    "date:inception_lower": "1983-01-01",
    "date:inception_upper": "1983-01-01",
    "iso:country": "GB",
    "wof:name": "RG6 3AN",
    "wof:placetype": "postalcode"
  },
  "geometry": {"coordinates":[-0.9089,51.430592],"type":"Point"}
}
