{
  "type": "Feature",
  "properties": {
    "iso:country":"GB",
    "wof:name":"KY3 9SZ",
    "wof:placetype":"postalcode"
},
  "geometry": {"coordinates":[-3.17269136514546,56.06983518169686],"type":"Point"}
}