{
  "type": "Feature",
  "properties": {
    "iso:country": "GB",
    "wof:name": "LN2 5DP",
    "wof:placetype": "postalcode"
  },
  "geometry": {"coordinates":[-0.529247,53.228107],"type":"Point"}
}
