{
  "type": "Feature",
  "properties": {
    "date:inception_lower":"1980-01-01",
    "date:inception_upper":"1980-01-31",
    "iso:country":"GB",
    "wof:name":"SA11 2TY",
    "wof:placetype":"postalcode"
},
  "geometry": {"coordinates":[-3.796921,51.636701],"type":"Point"}
}