{
  "type": "Feature",
  "properties": {
    "iso:country":"GB",
    "wof:name":"SA11 2TY",
    "wof:placetype":"postalcode"
},
  "geometry": {"coordinates":[-3.79692085576128,51.63670059653761],"type":"Point"}
}