{
  "type": "Feature",
  "properties": {
    "iso:country":"GB",
    "wof:name":"DT6 6QG",
    "wof:placetype":"postalcode"
},
  "geometry": {"coordinates":[-2.89916304026902,50.73917789119672],"type":"Point"}
}