{
  "type": "Feature",
  "properties": {
    "iso:country": "GB",
    "wof:name": "CF15 7TX",
    "wof:placetype": "postalcode"
  },
  "geometry": {"coordinates":[-3.266201,51.561864],"type":"Point"}
}
