{
  "type": "Feature",
  "properties": {
    "date:inception_lower": "2017-06-01",
    "date:inception_upper": "2017-06-01",
    "iso:country": "GB",
    "wof:name": "CF15 7TX",
    "wof:placetype": "postalcode"
  },
  "geometry": {"coordinates":[-3.266201,51.561864],"type":"Point"}
}
