{
  "type": "Feature",
  "properties": {
    "iso:country": "GB",
    "wof:name": "CF15 7TX",
    "wof:placetype": "postalcode"
  },
  "geometry": {"coordinates":[-3.266095,51.561712],"type":"Point"}
}
