{
  "type": "Feature",
  "properties": {
    "iso:country": "GB",
    "wof:name": "WF15 8DT",
    "wof:placetype": "postalcode"
  },
  "geometry": {"coordinates":[-1.727119,53.710851],"type":"Point"}
}
