{
  "type": "Feature",
  "properties": {
    "iso:country":"GB",
    "wof:name":"PH2 6JB",
    "wof:placetype":"postalcode"
},
  "geometry": {"coordinates":[-3.29311393295272,56.47680970958596],"type":"Point"}
}