{
  "type": "Feature",
  "properties": {
    "iso:country": "GB",
    "wof:name": "PH2 6JB",
    "wof:placetype": "postalcode"
  },
  "geometry": {"coordinates":[-3.293114,56.47681],"type":"Point"}
}
