{
  "type": "Feature",
  "properties": {
    "iso:country":"GB",
    "wof:name":"S62 6DE",
    "wof:placetype":"postalcode"
},
  "geometry": {"coordinates":[-1.33922189184524,53.45491344625172],"type":"Point"}
}