{
  "type": "Feature",
  "properties": {
    "iso:country":"GB",
    "wof:name":"N20 8BU",
    "wof:placetype":"postalcode"
},
  "geometry": {"coordinates":[-0.18595617941562,51.6273811734342],"type":"Point"}
}