{
  "type": "Feature",
  "properties": {
    "iso:country":"GB",
    "wof:name":"DN7 6RH",
    "wof:placetype":"postalcode"
},
  "geometry": {"coordinates":[-1.00190448921467,53.57675242241313],"type":"Point"}
}