{
  "type": "Feature",
  "properties": {
    "date:inception_lower": "2021-06-01",
    "date:inception_upper": "2021-06-01",
    "iso:country": "GB",
    "wof:name": "RH15 0FB",
    "wof:placetype": "postalcode"
  },
  "geometry": {"coordinates":[-0.110344,50.963106],"type":"Point"}
}
