{
  "type": "Feature",
  "properties": {
    "iso:country":"GB",
    "wof:name":"BA12 8EJ",
    "wof:placetype":"postalcode"
},
  "geometry": {"coordinates":[-2.20215907104367,51.20080797903493],"type":"Point"}
}