{
  "type": "Feature",
  "properties": {
    "iso:country":"GB",
    "wof:name":"BR5 4DN",
    "wof:placetype":"postalcode"
},
  "geometry": {"coordinates":[0.114315461113,51.38532398869031],"type":"Point"}
}