{
  "type": "Feature",
  "properties": {
    "iso:country":"GB",
    "wof:name":"SG17 5BX",
    "wof:placetype":"postalcode"
},
  "geometry": {"coordinates":[-0.33881800436283,52.03831359843298],"type":"Point"}
}