{
  "type": "Feature",
  "properties": {
    "iso:country":"GB",
    "wof:name":"HD1 5NF",
    "wof:placetype":"postalcode"
},
  "geometry": {"coordinates":[-1.79315400562302,53.65321643565469],"type":"Point"}
}