{
  "type": "Feature",
  "properties": {
    "iso:country":"GB",
    "wof:name":"SN25 4YD",
    "wof:placetype":"postalcode"
},
  "geometry": {"coordinates":[-1.79330287105107,51.60342808991189],"type":"Point"}
}