{
  "type": "Feature",
  "properties": {
    "date:inception_lower": "2005-08-01",
    "date:inception_upper": "2005-08-01",
    "iso:country": "GB",
    "wof:name": "NR12 9WX",
    "wof:placetype": "postalcode"
  },
  "geometry": {"coordinates":[1.511906,52.772633],"type":"Point"}
}
