{
  "type": "Feature",
  "properties": {
    "iso:country": "GB",
    "wof:name": "SY9 5BF",
    "wof:placetype": "postalcode"
  },
  "geometry": {"coordinates":[-3.000877,52.496557],"type":"Point"}
}
