{
  "type": "Feature",
  "properties": {
    "date:inception_lower":"2004-11-01",
    "date:inception_upper":"2004-11-30",
    "iso:country":"GB",
    "wof:name":"SY9 5BF",
    "wof:placetype":"postalcode"
},
  "geometry": {"coordinates":[-3.000877,52.496557],"type":"Point"}
}