{
  "type": "Feature",
  "properties": {
    "iso:country":"GB",
    "wof:name":"SY9 5BF",
    "wof:placetype":"postalcode"
},
  "geometry": {"coordinates":[-3.0008771480878,52.49655687939472],"type":"Point"}
}