{
  "type": "Feature",
  "properties": {
    "date:inception_lower": "1980-01-01",
    "date:inception_upper": "1980-01-01",
    "iso:country": "GB",
    "wof:name": "NE32 4SR",
    "wof:placetype": "postalcode"
  },
  "geometry": {"coordinates":[-1.485905,54.95813],"type":"Point"}
}
