{
  "type": "Feature",
  "properties": {
    "iso:country":"GB",
    "wof:name":"SE18 1TF",
    "wof:placetype":"postalcode"
},
  "geometry": {"coordinates":[0.08583414034842,51.48490916491501],"type":"Point"}
}