{
  "type": "Feature",
  "properties": {
    "iso:country": "GB",
    "wof:name": "S18 2FY",
    "wof:placetype": "postalcode"
  },
  "geometry": {"coordinates":[-1.463383,53.304435],"type":"Point"}
}
