{
  "type": "Feature",
  "properties": {
    "date:inception_lower":"2009-05-01",
    "date:inception_upper":"2009-05-31",
    "iso:country":"GB",
    "wof:name":"S18 2FY",
    "wof:placetype":"postalcode"
},
  "geometry": {"coordinates":[-1.463383,53.304435],"type":"Point"}
}