{
  "type": "Feature",
  "properties": {
    "iso:country":"GB",
    "wof:name":"DY5 1PY",
    "wof:placetype":"postalcode"
},
  "geometry": {"coordinates":[-2.12831905876961,52.48945769393902],"type":"Point"}
}