{
  "type": "Feature",
  "properties": {
    "date:inception_lower": "1980-01-01",
    "date:inception_upper": "1980-01-01",
    "iso:country": "GB",
    "wof:name": "BD20 0HT",
    "wof:placetype": "postalcode"
  },
  "geometry": {"coordinates":[-1.930882,53.911429],"type":"Point"}
}
