{
  "type": "Feature",
  "properties": {
    "iso:country":"GB",
    "wof:name":"BD1 1QS",
    "wof:placetype":"postalcode"
},
  "geometry": {"coordinates":[-1.75410056863747,53.79425573256042],"type":"Point"}
}