{
  "type": "Feature",
  "properties": {
    "date:inception_lower":"1981-06-01",
    "date:inception_upper":"1981-06-30",
    "iso:country":"GB",
    "wof:name":"NR25 7PT",
    "wof:placetype":"postalcode"
},
  "geometry": {"coordinates":[1.009746,52.952191],"type":"Point"}
}