{
  "type": "Feature",
  "properties": {
    "iso:country": "GB",
    "wof:name": "NR25 7PT",
    "wof:placetype": "postalcode"
  },
  "geometry": {"coordinates":[1.009746,52.952191],"type":"Point"}
}
