{
  "type": "Feature",
  "properties": {
    "iso:country":"GB",
    "wof:name":"TW15 1AL",
    "wof:placetype":"postalcode"
},
  "geometry": {"coordinates":[-0.44242879614291,51.43154557306569],"type":"Point"}
}