{
  "type": "Feature",
  "properties": {
    "iso:country":"GB",
    "wof:name":"SO40 7GW",
    "wof:placetype":"postalcode"
},
  "geometry": {"coordinates":[-1.54692984288293,50.90922695894881],"type":"Point"}
}