{
  "type": "Feature",
  "properties": {
    "date:inception_lower":"1994-12-01",
    "date:inception_upper":"1994-12-31",
    "iso:country":"GB",
    "wof:name":"SO40 7GW",
    "wof:placetype":"postalcode"
},
  "geometry": {"coordinates":[-1.54693,50.909227],"type":"Point"}
}