{
  "type": "Feature",
  "properties": {
    "iso:country": "GB",
    "wof:name": "SO40 7GW",
    "wof:placetype": "postalcode"
  },
  "geometry": {"coordinates":[-1.54693,50.909227],"type":"Point"}
}
