{
  "type": "Feature",
  "properties": {
    "iso:country":"GB",
    "wof:name":"NP12 3PH",
    "wof:placetype":"postalcode"
},
  "geometry": {"coordinates":[-3.20908104248505,51.66530364504658],"type":"Point"}
}