{
  "type": "Feature",
  "properties": {
    "iso:country":"GB",
    "wof:name":"BS20 0QJ",
    "wof:placetype":"postalcode"
},
  "geometry": {"coordinates":[-2.68239620915891,51.46961976266166],"type":"Point"}
}