{
  "type": "Feature",
  "properties": {
    "iso:country": "GB",
    "wof:name": "TQ12 4NW",
    "wof:placetype": "postalcode"
  },
  "geometry": {"coordinates":[-3.586911,50.514202],"type":"Point"}
}
