{
  "type": "Feature",
  "properties": {
    "iso:country":"GB",
    "wof:name":"TQ12 4NW",
    "wof:placetype":"postalcode"
},
  "geometry": {"coordinates":[-3.58691142019201,50.51420154396305],"type":"Point"}
}