{
  "type": "Feature",
  "properties": {
    "iso:country":"GB",
    "wof:name":"KT2 5AP",
    "wof:placetype":"postalcode"
},
  "geometry": {"coordinates":[-0.30293811099126,51.41808977406567],"type":"Point"}
}