{
  "type": "Feature",
  "properties": {
    "iso:country":"GB",
    "wof:name":"WS7 3GJ",
    "wof:placetype":"postalcode"
},
  "geometry": {"coordinates":[-1.95172101248874,52.68173765906815],"type":"Point"}
}