{
  "type": "Feature",
  "properties": {
    "iso:country":"GB",
    "wof:name":"NR3 3EW",
    "wof:placetype":"postalcode"
},
  "geometry": {"coordinates":[1.29091922692606,52.64095955245686],"type":"Point"}
}