{
  "type": "Feature",
  "properties": {
    "date:inception_lower": "2000-12-01",
    "date:inception_upper": "2000-12-01",
    "iso:country": "GB",
    "wof:name": "DL9 3EN",
    "wof:placetype": "postalcode"
  },
  "geometry": {"coordinates":[-1.723238,54.374777],"type":"Point"}
}
