{
  "type": "Feature",
  "properties": {
    "iso:country": "GB",
    "wof:name": "DL9 3EN",
    "wof:placetype": "postalcode"
  },
  "geometry": {"coordinates":[-1.723238,54.374777],"type":"Point"}
}
