{
  "type": "Feature",
  "properties": {
    "date:inception_lower":"1980-01-01",
    "date:inception_upper":"1980-01-31",
    "iso:country":"GB",
    "wof:name":"TS18 1HQ",
    "wof:placetype":"postalcode"
},
  "geometry": {"coordinates":[-1.319729,54.564343],"type":"Point"}
}