{
  "type": "Feature",
  "properties": {
    "iso:country":"GB",
    "wof:name":"TR18 2EE",
    "wof:placetype":"postalcode"
},
  "geometry": {"coordinates":[-5.53446425266239,50.12066962885339],"type":"Point"}
}