{
  "type": "Feature",
  "properties": {
    "iso:country": "GB",
    "wof:name": "EH47 8DY",
    "wof:placetype": "postalcode"
  },
  "geometry": {"coordinates":[-3.641625,55.84325],"type":"Point"}
}
