{
  "type": "Feature",
  "properties": {
    "iso:country": "GB",
    "wof:name": "GL2 4TU",
    "wof:placetype": "postalcode"
  },
  "geometry": {"coordinates":[-2.287083,51.822642],"type":"Point"}
}
