{
  "type": "Feature",
  "properties": {
    "iso:country":"GB",
    "wof:name":"GL2 4TU",
    "wof:placetype":"postalcode"
},
  "geometry": {"coordinates":[-2.28708303372598,51.82264226745249],"type":"Point"}
}