{
  "type": "Feature",
  "properties": {
    "iso:country": "GB",
    "wof:name": "NE61 3XB",
    "wof:placetype": "postalcode"
  },
  "geometry": {"coordinates":[-1.798209,55.126918],"type":"Point"}
}
