{
  "type": "Feature",
  "properties": {
    "iso:country": "GB",
    "wof:name": "PA16 0LX",
    "wof:placetype": "postalcode"
  },
  "geometry": {"coordinates":[-4.857207,55.912618],"type":"Point"}
}
