{
  "type": "Feature",
  "properties": {
    "iso:country":"GB",
    "wof:name":"PA16 0LX",
    "wof:placetype":"postalcode"
},
  "geometry": {"coordinates":[-4.85720740209498,55.91261842092023],"type":"Point"}
}