{
  "type": "Feature",
  "properties": {
    "iso:country":"GB",
    "wof:name":"EX32 8HA",
    "wof:placetype":"postalcode"
},
  "geometry": {"coordinates":[-4.04385591616413,51.07648271557845],"type":"Point"}
}