{
  "type": "Feature",
  "properties": {
    "date:inception_lower": "1980-01-01",
    "date:inception_upper": "1980-01-01",
    "iso:country": "GB",
    "wof:name": "EX32 8HA",
    "wof:placetype": "postalcode"
  },
  "geometry": {"coordinates":[-4.043856,51.076483],"type":"Point"}
}
