{
  "type": "Feature",
  "properties": {
    "date:inception_lower": "1998-06-01",
    "date:inception_upper": "1998-06-01",
    "iso:country": "GB",
    "wof:name": "YO24 3HN",
    "wof:placetype": "postalcode"
  },
  "geometry": {"coordinates":[-1.1397,53.948132],"type":"Point"}
}
