{
  "type": "Feature",
  "properties": {
    "iso:country":"GB",
    "wof:name":"SO14 0FB",
    "wof:placetype":"postalcode"
},
  "geometry": {"coordinates":[-1.39344976282816,50.90907041289108],"type":"Point"}
}