{
  "type": "Feature",
  "properties": {
    "iso:country": "GB",
    "wof:name": "SO14 0FB",
    "wof:placetype": "postalcode"
  },
  "geometry": {"coordinates":[-1.39345,50.90907],"type":"Point"}
}
