{
  "type": "Feature",
  "properties": {
    "date:inception_lower":"2005-09-01",
    "date:inception_upper":"2005-09-30",
    "iso:country":"GB",
    "wof:name":"GU33 7JN",
    "wof:placetype":"postalcode"
},
  "geometry": {"coordinates":[-0.848245,51.047122],"type":"Point"}
}