{
  "type": "Feature",
  "properties": {
    "iso:country": "GB",
    "wof:name": "GU33 7JN",
    "wof:placetype": "postalcode"
  },
  "geometry": {"coordinates":[-0.848245,51.047122],"type":"Point"}
}
