{
  "type": "Feature",
  "properties": {
    "iso:country":"GB",
    "wof:name":"LS6 2JW",
    "wof:placetype":"postalcode"
},
  "geometry": {"coordinates":[-1.5548864126876,53.81436369331551],"type":"Point"}
}