{
  "type": "Feature",
  "properties": {
    "date:inception_lower":"1980-01-01",
    "date:inception_upper":"1980-01-31",
    "iso:country":"GB",
    "wof:name":"LS6 2JW",
    "wof:placetype":"postalcode"
},
  "geometry": {"coordinates":[-1.554886,53.814364],"type":"Point"}
}