{
  "type": "Feature",
  "properties": {
    "iso:country":"GB",
    "wof:name":"EX4 9AL",
    "wof:placetype":"postalcode"
},
  "geometry": {"coordinates":[-3.50390823100284,50.73986033585825],"type":"Point"}
}