{
  "type": "Feature",
  "properties": {
    "iso:country": "GB",
    "wof:name": "EX4 9AL",
    "wof:placetype": "postalcode"
  },
  "geometry": {"coordinates":[-3.503909,50.739859],"type":"Point"}
}
