{
  "type": "Feature",
  "properties": {
    "date:inception_lower": "2011-05-01",
    "date:inception_upper": "2011-05-01",
    "iso:country": "GB",
    "wof:name": "EX4 9AL",
    "wof:placetype": "postalcode"
  },
  "geometry": {"coordinates":[-3.504229,50.739675],"type":"Point"}
}
