{
  "type": "Feature",
  "properties": {
    "iso:country":"GB",
    "wof:name":"IV2 7JN",
    "wof:placetype":"postalcode"
},
  "geometry": {"coordinates":[-4.11353426153432,57.49319547130685],"type":"Point"}
}