{
  "type": "Feature",
  "properties": {
    "iso:country":"GB",
    "wof:name":"HD4 7DU",
    "wof:placetype":"postalcode"
},
  "geometry": {"coordinates":[-1.81133517751414,53.61355445168807],"type":"Point"}
}