{
  "type": "Feature",
  "properties": {
    "date:inception_lower":"1980-01-01",
    "date:inception_upper":"1980-01-31",
    "iso:country":"GB",
    "wof:name":"HD4 7DU",
    "wof:placetype":"postalcode"
},
  "geometry": {"coordinates":[-1.811335,53.613554],"type":"Point"}
}