{
  "type": "Feature",
  "properties": {
    "iso:country":"GB",
    "wof:name":"PR3 6BA",
    "wof:placetype":"postalcode"
},
  "geometry": {"coordinates":[-2.86567892875508,53.90013804388579],"type":"Point"}
}