{
  "type": "Feature",
  "properties": {
    "iso:country":"GB",
    "wof:name":"W1K 3DP",
    "wof:placetype":"postalcode"
},
  "geometry": {"coordinates":[-0.14737202423188,51.5111450879355],"type":"Point"}
}