{
  "type": "Feature",
  "properties": {
    "iso:country":"GB",
    "wof:name":"WF11 8LX",
    "wof:placetype":"postalcode"
},
  "geometry": {"coordinates":[-1.26666777279007,53.7122983495349],"type":"Point"}
}