{
  "type": "Feature",
  "properties": {
    "date:inception_lower": "1980-01-01",
    "date:inception_upper": "1980-01-01",
    "iso:country": "GB",
    "wof:name": "WF11 8LX",
    "wof:placetype": "postalcode"
  },
  "geometry": {"coordinates":[-1.266671,53.712316],"type":"Point"}
}
