{
  "type": "Feature",
  "properties": {
    "iso:country": "GB",
    "wof:name": "WF11 8LX",
    "wof:placetype": "postalcode"
  },
  "geometry": {"coordinates":[-1.26676,53.712416],"type":"Point"}
}
