{
  "type": "Feature",
  "properties": {
    "date:inception_lower": "2017-01-01",
    "date:inception_upper": "2017-01-01",
    "iso:country": "GB",
    "wof:name": "BD23 1FP",
    "wof:placetype": "postalcode"
  },
  "geometry": {"coordinates":[-2.011491,53.96369],"type":"Point"}
}
