{
  "type": "Feature",
  "properties": {
    "date:inception_lower":"1980-01-01",
    "date:inception_upper":"1980-01-31",
    "iso:country":"GB",
    "wof:name":"L4 6TG",
    "wof:placetype":"postalcode"
},
  "geometry": {"coordinates":[-2.962039,53.445394],"type":"Point"}
}