{
  "type": "Feature",
  "properties": {
    "date:inception_lower": "2018-10-01",
    "date:inception_upper": "2018-10-01",
    "iso:country": "GB",
    "wof:name": "NE63 9WS",
    "wof:placetype": "postalcode"
  },
  "geometry": {"coordinates":[-1.547205,55.179447],"type":"Point"}
}
