{
  "type": "Feature",
  "properties": {
    "iso:country":"GB",
    "wof:name":"CO16 9BL",
    "wof:placetype":"postalcode"
},
  "geometry": {"coordinates":[1.11674574974098,51.83167578119973],"type":"Point"}
}