{
  "type": "Feature",
  "properties": {
    "iso:country":"GB",
    "wof:name":"CA4 8RS",
    "wof:placetype":"postalcode"
},
  "geometry": {"coordinates":[-2.81600004044665,54.90539644890491],"type":"Point"}
}