{
  "type": "Feature",
  "properties": {
    "date:inception_lower":"1980-01-01",
    "date:inception_upper":"1980-01-31",
    "iso:country":"GB",
    "wof:name":"CA4 8RS",
    "wof:placetype":"postalcode"
},
  "geometry": {"coordinates":[-2.816004,54.905403],"type":"Point"}
}