{
  "type": "Feature",
  "properties": {
    "iso:country": "GB",
    "wof:name": "CA4 8RS",
    "wof:placetype": "postalcode"
  },
  "geometry": {"coordinates":[-2.816004,54.905403],"type":"Point"}
}
