{
  "type": "Feature",
  "properties": {
    "iso:country": "GB",
    "wof:name": "CF71 7LX",
    "wof:placetype": "postalcode"
  },
  "geometry": {"coordinates":[-3.446551,51.446297],"type":"Point"}
}
