{
  "type": "Feature",
  "properties": {
    "iso:country":"GB",
    "wof:name":"CF71 7LX",
    "wof:placetype":"postalcode"
},
  "geometry": {"coordinates":[-3.44655100758727,51.44629695009811],"type":"Point"}
}