{
  "type": "Feature",
  "properties": {
    "date:inception_lower":"1995-07-01",
    "date:inception_upper":"1995-07-31",
    "iso:country":"GB",
    "wof:name":"CF71 7LX",
    "wof:placetype":"postalcode"
},
  "geometry": {"coordinates":[-3.446551,51.446297],"type":"Point"}
}