{
  "type": "Feature",
  "properties": {
    "date:inception_lower": "1982-03-01",
    "date:inception_upper": "1982-03-01",
    "iso:country": "GB",
    "wof:name": "CW7 1QL",
    "wof:placetype": "postalcode"
  },
  "geometry": {"coordinates":[-2.545399,53.182548],"type":"Point"}
}
