{
  "type": "Feature",
  "properties": {
    "iso:country":"GB",
    "wof:name":"MK1 1BJ",
    "wof:placetype":"postalcode"
},
  "geometry": {"coordinates":[-0.71964963957121,52.00071834378493],"type":"Point"}
}