{
  "type": "Feature",
  "properties": {
    "iso:country":"GB",
    "wof:name":"HD4 6ND",
    "wof:placetype":"postalcode"
},
  "geometry": {"coordinates":[-1.77815775749465,53.63352342444809],"type":"Point"}
}