{
  "type": "Feature",
  "properties": {
    "iso:country": "GB",
    "wof:name": "SA66 7HS",
    "wof:placetype": "postalcode"
  },
  "geometry": {"coordinates":[-4.78304,51.845336],"type":"Point"}
}
