{
  "type": "Feature",
  "properties": {
    "date:inception_lower": "1983-03-01",
    "date:inception_upper": "1983-03-01",
    "iso:country": "GB",
    "wof:name": "LN6 9SR",
    "wof:placetype": "postalcode"
  },
  "geometry": {"coordinates":[-0.603858,53.184115],"type":"Point"}
}
