{
  "type": "Feature",
  "properties": {
    "iso:country":"GB",
    "wof:name":"LN6 9SR",
    "wof:placetype":"postalcode"
},
  "geometry": {"coordinates":[-0.60385836207174,53.1841150042325],"type":"Point"}
}