{
  "type": "Feature",
  "properties": {
    "iso:country": "GB",
    "wof:name": "BA14 9NZ",
    "wof:placetype": "postalcode"
  },
  "geometry": {"coordinates":[-2.25559,51.309523],"type":"Point"}
}
