{
  "type": "Feature",
  "properties": {
    "date:inception_lower": "2000-12-01",
    "date:inception_upper": "2000-12-01",
    "iso:country": "GB",
    "wof:name": "BA14 9NZ",
    "wof:placetype": "postalcode"
  },
  "geometry": {"coordinates":[-2.25559,51.309523],"type":"Point"}
}
