{
  "type": "Feature",
  "properties": {
    "iso:country":"GB",
    "wof:name":"DE13 0JN",
    "wof:placetype":"postalcode"
},
  "geometry": {"coordinates":[-1.63251644743849,52.82748414950802],"type":"Point"}
}