{
  "type": "Feature",
  "properties": {
    "date:inception_lower": "1985-04-01",
    "date:inception_upper": "1985-04-01",
    "iso:country": "GB",
    "wof:name": "DE13 0JN",
    "wof:placetype": "postalcode"
  },
  "geometry": {"coordinates":[-1.632516,52.827484],"type":"Point"}
}
