{
  "type": "Feature",
  "properties": {
    "iso:country": "GB",
    "wof:name": "DE13 0JN",
    "wof:placetype": "postalcode"
  },
  "geometry": {"coordinates":[-1.632516,52.827484],"type":"Point"}
}
