{
  "type": "Feature",
  "properties": {
    "iso:country":"GB",
    "wof:name":"ML11 7RP",
    "wof:placetype":"postalcode"
},
  "geometry": {"coordinates":[-3.7564856124606,55.67086401362308],"type":"Point"}
}