{
  "type": "Feature",
  "properties": {
    "iso:country":"GB",
    "wof:name":"B31 4LB",
    "wof:placetype":"postalcode"
},
  "geometry": {"coordinates":[-1.97836758832951,52.39516642480964],"type":"Point"}
}