{
  "type": "Feature",
  "properties": {
    "date:inception_lower": "1998-06-01",
    "date:inception_upper": "1998-06-01",
    "iso:country": "GB",
    "wof:name": "B31 4LB",
    "wof:placetype": "postalcode"
  },
  "geometry": {"coordinates":[-1.978374,52.395181],"type":"Point"}
}
