{
  "type": "Feature",
  "properties": {
    "iso:country":"GB",
    "wof:name":"DA6 8NF",
    "wof:placetype":"postalcode"
},
  "geometry": {"coordinates":[0.13349190595245,51.45612868578178],"type":"Point"}
}