{
  "type": "Feature",
  "properties": {
    "iso:country": "GB",
    "wof:name": "NE65 9ED",
    "wof:placetype": "postalcode"
  },
  "geometry": {"coordinates":[-1.709886,55.295935],"type":"Point"}
}
