{
  "type": "Feature",
  "properties": {
    "iso:country":"GB",
    "wof:name":"SM6 0EB",
    "wof:placetype":"postalcode"
},
  "geometry": {"coordinates":[-0.15348008175148,51.36135278107157],"type":"Point"}
}