{
  "type": "Feature",
  "properties": {
    "date:inception_lower": "1990-02-01",
    "date:inception_upper": "1990-02-01",
    "iso:country": "GB",
    "wof:name": "SM6 0EB",
    "wof:placetype": "postalcode"
  },
  "geometry": {"coordinates":[-0.15348,51.361353],"type":"Point"}
}
