{
  "type": "Feature",
  "properties": {
    "date:inception_lower":"1997-06-01",
    "date:inception_upper":"1997-06-30",
    "iso:country":"GB",
    "wof:name":"SN16 9YH",
    "wof:placetype":"postalcode"
},
  "geometry": {"coordinates":[-2.070431,51.633412],"type":"Point"}
}