{
  "type": "Feature",
  "properties": {
    "iso:country": "GB",
    "wof:name": "SS7 4LA",
    "wof:placetype": "postalcode"
  },
  "geometry": {"coordinates":[0.554428,51.574545],"type":"Point"}
}
