{
  "type": "Feature",
  "properties": {
    "date:inception_lower":"1980-01-01",
    "date:inception_upper":"1980-01-31",
    "iso:country":"GB",
    "wof:name":"SS7 4LA",
    "wof:placetype":"postalcode"
},
  "geometry": {"coordinates":[0.554428,51.574545],"type":"Point"}
}