{
  "type": "Feature",
  "properties": {
    "date:inception_lower": "1997-06-01",
    "date:inception_upper": "1997-06-01",
    "iso:country": "GB",
    "wof:name": "S33 6RT",
    "wof:placetype": "postalcode"
  },
  "geometry": {"coordinates":[-1.742318,53.349534],"type":"Point"}
}
