{
  "type": "Feature",
  "properties": {
    "iso:country":"GB",
    "wof:name":"S33 6RT",
    "wof:placetype":"postalcode"
},
  "geometry": {"coordinates":[-1.74231836979054,53.34953372201786],"type":"Point"}
}