{
  "type": "Feature",
  "properties": {
    "iso:country":"GB",
    "wof:name":"BS36 2QJ",
    "wof:placetype":"postalcode"
},
  "geometry": {"coordinates":[-2.46585612236931,51.52907140192316],"type":"Point"}
}