{
  "type": "Feature",
  "properties": {
    "iso:country": "GB",
    "wof:name": "BS36 2QJ",
    "wof:placetype": "postalcode"
  },
  "geometry": {"coordinates":[-2.465856,51.529071],"type":"Point"}
}
