{
  "type": "Feature",
  "properties": {
    "iso:country":"GB",
    "wof:name":"WD6 1HJ",
    "wof:placetype":"postalcode"
},
  "geometry": {"coordinates":[-0.27077280262622,51.65266119777267],"type":"Point"}
}