{
  "type": "Feature",
  "properties": {
    "iso:country":"GB",
    "wof:name":"EX2 8UL",
    "wof:placetype":"postalcode"
},
  "geometry": {"coordinates":[-3.53748770851767,50.69888042514499],"type":"Point"}
}