{
  "type": "Feature",
  "properties": {
    "date:inception_lower":"1980-01-01",
    "date:inception_upper":"1980-01-31",
    "iso:country":"GB",
    "wof:name":"EX2 8UL",
    "wof:placetype":"postalcode"
},
  "geometry": {"coordinates":[-3.537488,50.69888],"type":"Point"}
}