{
  "type": "Feature",
  "properties": {
    "iso:country": "GB",
    "wof:name": "TQ9 6RE",
    "wof:placetype": "postalcode"
  },
  "geometry": {"coordinates":[-3.628739,50.40106],"type":"Point"}
}
