{
  "type": "Feature",
  "properties": {
    "iso:country":"GB",
    "wof:name":"TQ9 6RE",
    "wof:placetype":"postalcode"
},
  "geometry": {"coordinates":[-3.62874725194042,50.40102164251206],"type":"Point"}
}