{
  "type": "Feature",
  "properties": {
    "iso:country":"GB",
    "wof:name":"CM4 0DX",
    "wof:placetype":"postalcode"
},
  "geometry": {"coordinates":[0.39106223137366,51.67398027647823],"type":"Point"}
}