{
  "type": "Feature",
  "properties": {
    "date:inception_lower": "1980-01-01",
    "date:inception_upper": "1980-01-01",
    "iso:country": "GB",
    "wof:name": "W5 3RS",
    "wof:placetype": "postalcode"
  },
  "geometry": {"coordinates":[-0.285413,51.513559],"type":"Point"}
}
