{
  "type": "Feature",
  "properties": {
    "iso:country": "GB",
    "wof:name": "W5 3RS",
    "wof:placetype": "postalcode"
  },
  "geometry": {"coordinates":[-0.285413,51.513559],"type":"Point"}
}
