{
  "type": "Feature",
  "properties": {
    "date:inception_lower": "1980-01-01",
    "date:inception_upper": "1980-01-01",
    "iso:country": "GB",
    "wof:name": "SA73 2LA",
    "wof:placetype": "postalcode"
  },
  "geometry": {"coordinates":[-5.028798,51.711814],"type":"Point"}
}
