{
  "type": "Feature",
  "properties": {
    "iso:country":"GB",
    "wof:name":"GL15 6EE",
    "wof:placetype":"postalcode"
},
  "geometry": {"coordinates":[-2.57329517289761,51.74790346845747],"type":"Point"}
}