{
  "type": "Feature",
  "properties": {
    "iso:country":"GB",
    "wof:name":"BN22 8JW",
    "wof:placetype":"postalcode"
},
  "geometry": {"coordinates":[0.29375513719645,50.77573248139996],"type":"Point"}
}