{
  "type": "Feature",
  "properties": {
    "iso:country":"GB",
    "wof:name":"CM13 1XA",
    "wof:placetype":"postalcode"
},
  "geometry": {"coordinates":[0.35539008712617,51.63961972774854],"type":"Point"}
}