{
  "type": "Feature",
  "properties": {
    "iso:country": "GB",
    "wof:name": "CM13 1XA",
    "wof:placetype": "postalcode"
  },
  "geometry": {"coordinates":[0.35539,51.63962],"type":"Point"}
}
