{
  "type": "Feature",
  "properties": {
    "iso:country": "GB",
    "wof:name": "LS26 8TN",
    "wof:placetype": "postalcode"
  },
  "geometry": {"coordinates":[-1.456291,53.752973],"type":"Point"}
}
