{
  "type": "Feature",
  "properties": {
    "date:inception_lower": "2020-08-01",
    "date:inception_upper": "2020-08-01",
    "iso:country": "GB",
    "wof:name": "EH52 5FN",
    "wof:placetype": "postalcode"
  },
  "geometry": {"coordinates":[-3.471289,55.913784],"type":"Point"}
}
