{
  "type": "Feature",
  "properties": {
    "iso:country":"GB",
    "wof:name":"WF16 0QA",
    "wof:placetype":"postalcode"
},
  "geometry": {"coordinates":[-1.66603037780687,53.70534870016487],"type":"Point"}
}