{
  "type": "Feature",
  "properties": {
    "date:inception_lower":"1980-01-01",
    "date:inception_upper":"1980-01-31",
    "iso:country":"GB",
    "wof:name":"WF16 0QA",
    "wof:placetype":"postalcode"
},
  "geometry": {"coordinates":[-1.66603,53.705349],"type":"Point"}
}