{
  "type": "Feature",
  "properties": {
    "date:inception_lower":"1980-01-01",
    "date:inception_upper":"1980-01-31",
    "iso:country":"GB",
    "wof:name":"NG31 9RE",
    "wof:placetype":"postalcode"
},
  "geometry": {"coordinates":[-0.617439,52.92285],"type":"Point"}
}