{
  "type": "Feature",
  "properties": {
    "iso:country": "GB",
    "wof:name": "NG31 9RE",
    "wof:placetype": "postalcode"
  },
  "geometry": {"coordinates":[-0.617439,52.92285],"type":"Point"}
}
