{
  "type": "Feature",
  "properties": {
    "iso:country": "GB",
    "wof:name": "L13 2BE",
    "wof:placetype": "postalcode"
  },
  "geometry": {"coordinates":[-2.926409,53.411186],"type":"Point"}
}
