{
  "type": "Feature",
  "properties": {
    "iso:country":"GB",
    "wof:name":"E14 1SB",
    "wof:placetype":"postalcode"
},
  "geometry": {"coordinates":[-0.0061750396168,51.50999874031407],"type":"Point"}
}