{
  "type": "Feature",
  "properties": {
    "iso:country": "GB",
    "wof:name": "SK23 0RP",
    "wof:placetype": "postalcode"
  },
  "geometry": {"coordinates":[-1.914246,53.32586],"type":"Point"}
}
