{
  "type": "Feature",
  "properties": {
    "iso:country":"GB",
    "wof:name":"BR3 4BF",
    "wof:placetype":"postalcode"
},
  "geometry": {"coordinates":[-0.046289182311,51.39857088132],"type":"Point"}
}