{
  "type": "Feature",
  "properties": {
    "iso:country": "GB",
    "wof:name": "SG4 0JW",
    "wof:placetype": "postalcode"
  },
  "geometry": {"coordinates":[-0.251868,51.95862],"type":"Point"}
}
