{
  "type": "Feature",
  "properties": {
    "iso:country":"GB",
    "wof:name":"WA5 2ES",
    "wof:placetype":"postalcode"
},
  "geometry": {"coordinates":[-2.65461263075154,53.38414951251725],"type":"Point"}
}