{
  "type": "Feature",
  "properties": {
    "iso:country": "GB",
    "wof:name": "WA5 2ES",
    "wof:placetype": "postalcode"
  },
  "geometry": {"coordinates":[-2.654613,53.38415],"type":"Point"}
}
