{
  "type": "Feature",
  "properties": {
    "iso:country": "GB",
    "wof:name": "SK9 4HB",
    "wof:placetype": "postalcode"
  },
  "geometry": {"coordinates":[-2.229314,53.346479],"type":"Point"}
}
