{
  "type": "Feature",
  "properties": {
    "iso:country":"GB",
    "wof:name":"SK9 4HB",
    "wof:placetype":"postalcode"
},
  "geometry": {"coordinates":[-2.22914949001073,53.3464088557054],"type":"Point"}
}