{
  "type": "Feature",
  "properties": {
    "iso:country": "GB",
    "wof:name": "HP5 1JP",
    "wof:placetype": "postalcode"
  },
  "geometry": {"coordinates":[-0.619539,51.701419],"type":"Point"}
}
