{
  "type": "Feature",
  "properties": {
    "iso:country":"GB",
    "wof:name":"HP5 1JP",
    "wof:placetype":"postalcode"
},
  "geometry": {"coordinates":[-0.61953883629895,51.70141930268278],"type":"Point"}
}