{
  "type": "Feature",
  "properties": {
    "date:inception_lower":"1980-01-01",
    "date:inception_upper":"1980-01-31",
    "iso:country":"GB",
    "wof:name":"CA7 0AW",
    "wof:placetype":"postalcode"
},
  "geometry": {"coordinates":[-3.206897,54.810636],"type":"Point"}
}