{
  "type": "Feature",
  "properties": {
    "iso:country":"GB",
    "wof:name":"CA7 0AW",
    "wof:placetype":"postalcode"
},
  "geometry": {"coordinates":[-3.20689703582675,54.81063585143418],"type":"Point"}
}