{
  "type": "Feature",
  "properties": {
    "date:inception_lower":"1993-08-01",
    "date:inception_upper":"1993-08-31",
    "iso:country":"GB",
    "wof:name":"ST16 1AW",
    "wof:placetype":"postalcode"
},
  "geometry": {"coordinates":[-2.13699,52.804528],"type":"Point"}
}