{
  "type": "Feature",
  "properties": {
    "date:inception_lower": "1980-01-01",
    "date:inception_upper": "1980-01-01",
    "iso:country": "GB",
    "wof:name": "SM3 8QW",
    "wof:placetype": "postalcode"
  },
  "geometry": {"coordinates":[-0.218561,51.361057],"type":"Point"}
}
