{
  "type": "Feature",
  "properties": {
    "iso:country":"GB",
    "wof:name":"SM3 8QW",
    "wof:placetype":"postalcode"
},
  "geometry": {"coordinates":[-0.21856138306909,51.36105660768825],"type":"Point"}
}