{
  "type": "Feature",
  "properties": {
    "iso:country":"GB",
    "wof:name":"WF7 7DA",
    "wof:placetype":"postalcode"
},
  "geometry": {"coordinates":[-1.33006979704284,53.64013373919632],"type":"Point"}
}