{
  "type": "Feature",
  "properties": {
    "date:inception_lower": "1980-01-01",
    "date:inception_upper": "1980-01-01",
    "iso:country": "GB",
    "wof:name": "WF7 7DA",
    "wof:placetype": "postalcode"
  },
  "geometry": {"coordinates":[-1.33007,53.640134],"type":"Point"}
}
