{
  "type": "Feature",
  "properties": {
    "iso:country":"GB",
    "wof:name":"SY25 6UU",
    "wof:placetype":"postalcode"
},
  "geometry": {"coordinates":[-3.95929403461492,52.18333907597551],"type":"Point"}
}