{
  "type": "Feature",
  "properties": {
    "iso:country": "GB",
    "wof:name": "SY25 6UU",
    "wof:placetype": "postalcode"
  },
  "geometry": {"coordinates":[-3.959294,52.183339],"type":"Point"}
}
