{
  "type": "Feature",
  "properties": {
    "date:inception_lower":"1983-01-01",
    "date:inception_upper":"1983-01-31",
    "iso:country":"GB",
    "wof:name":"SY25 6UU",
    "wof:placetype":"postalcode"
},
  "geometry": {"coordinates":[-3.959294,52.183339],"type":"Point"}
}