{
  "type": "Feature",
  "properties": {
    "iso:country":"GB",
    "wof:name":"LS27 7JU",
    "wof:placetype":"postalcode"
},
  "geometry": {"coordinates":[-1.6277885314331,53.7525135716495],"type":"Point"}
}