{
  "type": "Feature",
  "properties": {
    "iso:country": "GB",
    "wof:name": "CV5 8ND",
    "wof:placetype": "postalcode"
  },
  "geometry": {"coordinates":[-1.546624,52.419426],"type":"Point"}
}
