{
  "type": "Feature",
  "properties": {
    "iso:country":"GB",
    "wof:name":"CV5 8ND",
    "wof:placetype":"postalcode"
},
  "geometry": {"coordinates":[-1.54663323144666,52.4194095220543],"type":"Point"}
}