{
  "type": "Feature",
  "properties": {
    "iso:country":"GB",
    "wof:name":"PO18 8UH",
    "wof:placetype":"postalcode"
},
  "geometry": {"coordinates":[-0.88433918885023,50.85910274286299],"type":"Point"}
}