{
  "type": "Feature",
  "properties": {
    "iso:country":"GB",
    "wof:name":"PE7 1FX",
    "wof:placetype":"postalcode"
},
  "geometry": {"coordinates":[-0.13768336812395,52.56473920410194],"type":"Point"}
}