{
  "type": "Feature",
  "properties": {
    "date:inception_lower":"2005-11-01",
    "date:inception_upper":"2005-11-30",
    "iso:country":"GB",
    "wof:name":"TF2 9FT",
    "wof:placetype":"postalcode"
},
  "geometry": {"coordinates":[-2.424406,52.684394],"type":"Point"}
}