{
  "type": "Feature",
  "properties": {
    "iso:country":"GB",
    "wof:name":"TF2 9FT",
    "wof:placetype":"postalcode"
},
  "geometry": {"coordinates":[-2.42470320208718,52.684482650349],"type":"Point"}
}