{
  "type": "Feature",
  "properties": {
    "iso:country":"GB",
    "wof:name":"SW4 9AT",
    "wof:placetype":"postalcode"
},
  "geometry": {"coordinates":[-0.1549282692987,51.45607703730293],"type":"Point"}
}