{
  "type": "Feature",
  "properties": {
    "date:inception_lower":"1980-01-01",
    "date:inception_upper":"1980-01-31",
    "iso:country":"GB",
    "wof:name":"SW4 9AT",
    "wof:placetype":"postalcode"
},
  "geometry": {"coordinates":[-0.154928,51.456077],"type":"Point"}
}