{
  "type": "Feature",
  "properties": {
    "iso:country":"GB",
    "wof:name":"ST3 2DL",
    "wof:placetype":"postalcode"
},
  "geometry": {"coordinates":[-2.15871266892217,52.98920495148089],"type":"Point"}
}