{
  "type": "Feature",
  "properties": {
    "iso:country": "GB",
    "wof:name": "WA16 7QG",
    "wof:placetype": "postalcode"
  },
  "geometry": {"coordinates":[-2.329999,53.324842],"type":"Point"}
}
