{
  "type": "Feature",
  "properties": {
    "iso:country": "GB",
    "wof:name": "RG45 6EX",
    "wof:placetype": "postalcode"
  },
  "geometry": {"coordinates":[-0.810251,51.372857],"type":"Point"}
}
