{
  "type": "Feature",
  "properties": {
    "iso:country":"GB",
    "wof:name":"RG45 6EX",
    "wof:placetype":"postalcode"
},
  "geometry": {"coordinates":[-0.81025131283199,51.37285711071235],"type":"Point"}
}