{
  "type": "Feature",
  "properties": {
    "iso:country":"GB",
    "wof:name":"LS17 0HE",
    "wof:placetype":"postalcode"
},
  "geometry": {"coordinates":[-1.58225759854113,53.92252385239726],"type":"Point"}
}