{
  "type": "Feature",
  "properties": {
    "iso:country": "GB",
    "wof:name": "TA2 6UZ",
    "wof:placetype": "postalcode"
  },
  "geometry": {"coordinates":[-3.124292,51.027893],"type":"Point"}
}
