{
  "type": "Feature",
  "properties": {
    "iso:country":"GB",
    "wof:name":"TA2 6UZ",
    "wof:placetype":"postalcode"
},
  "geometry": {"coordinates":[-3.12434047443836,51.02790585865939],"type":"Point"}
}