{
  "type": "Feature",
  "properties": {
    "date:inception_lower":"2012-12-01",
    "date:inception_upper":"2012-12-31",
    "iso:country":"GB",
    "wof:name":"TA2 6UZ",
    "wof:placetype":"postalcode"
},
  "geometry": {"coordinates":[-3.124292,51.027893],"type":"Point"}
}