{
  "type": "Feature",
  "properties": {
    "date:inception_lower": "1980-01-01",
    "date:inception_upper": "1980-01-01",
    "iso:country": "GB",
    "wof:name": "HR3 6DH",
    "wof:placetype": "postalcode"
  },
  "geometry": {"coordinates":[-2.971247,52.113618],"type":"Point"}
}
