{
  "type": "Feature",
  "properties": {
    "iso:country":"GB",
    "wof:name":"HR3 6DH",
    "wof:placetype":"postalcode"
},
  "geometry": {"coordinates":[-2.97124698384665,52.11361762219764],"type":"Point"}
}