{
  "type": "Feature",
  "properties": {
    "iso:country":"GB",
    "wof:name":"BD18 3JY",
    "wof:placetype":"postalcode"
},
  "geometry": {"coordinates":[-1.789133863355,53.83731171809592],"type":"Point"}
}