{
  "type": "Feature",
  "properties": {
    "iso:country": "GB",
    "wof:name": "BS40 8EG",
    "wof:placetype": "postalcode"
  },
  "geometry": {"coordinates":[-2.661819,51.382725],"type":"Point"}
}
