{
  "type": "Feature",
  "properties": {
    "iso:country":"GB",
    "wof:name":"SM5 1PD",
    "wof:placetype":"postalcode"
},
  "geometry": {"coordinates":[-0.16517668491278,51.38281323327842],"type":"Point"}
}