{
  "type": "Feature",
  "properties": {
    "iso:country":"GB",
    "wof:name":"E9 6AP",
    "wof:placetype":"postalcode"
},
  "geometry": {"coordinates":[-0.04185051665229,51.54745149983836],"type":"Point"}
}