{
  "type": "Feature",
  "properties": {
    "date:inception_lower":"2004-09-01",
    "date:inception_upper":"2004-09-30",
    "iso:country":"GB",
    "wof:name":"CF10 5GF",
    "wof:placetype":"postalcode"
},
  "geometry": {"coordinates":[-3.175359,51.462674],"type":"Point"}
}