{
  "type": "Feature",
  "properties": {
    "iso:country":"GB",
    "wof:name":"CF10 5GF",
    "wof:placetype":"postalcode"
},
  "geometry": {"coordinates":[-3.17535871403285,51.46267430563913],"type":"Point"}
}