{
  "type": "Feature",
  "properties": {
    "iso:country": "GB",
    "wof:name": "KT6 7UQ",
    "wof:placetype": "postalcode"
  },
  "geometry": {"coordinates":[-0.299696,51.380652],"type":"Point"}
}
