{
  "type": "Feature",
  "properties": {
    "date:inception_lower":"1980-01-01",
    "date:inception_upper":"1980-01-31",
    "iso:country":"GB",
    "wof:name":"KT6 7UQ",
    "wof:placetype":"postalcode"
},
  "geometry": {"coordinates":[-0.299696,51.380652],"type":"Point"}
}