{
  "type": "Feature",
  "properties": {
    "iso:country":"GB",
    "wof:name":"KT6 7UQ",
    "wof:placetype":"postalcode"
},
  "geometry": {"coordinates":[-0.29969597578414,51.38065200135231],"type":"Point"}
}