{
  "type": "Feature",
  "properties": {
    "iso:country":"GB",
    "wof:name":"GU30 7PH",
    "wof:placetype":"postalcode"
},
  "geometry": {"coordinates":[-0.83134022712307,51.07827511028087],"type":"Point"}
}