{
  "type": "Feature",
  "properties": {
    "iso:country":"GB",
    "wof:name":"BS40 9YL",
    "wof:placetype":"postalcode"
},
  "geometry": {"coordinates":[-2.69035094865918,51.38521286206493],"type":"Point"}
}