{
  "type": "Feature",
  "properties": {
    "iso:country": "GB",
    "wof:name": "BS40 9YL",
    "wof:placetype": "postalcode"
  },
  "geometry": {"coordinates":[-2.690354,51.385192],"type":"Point"}
}
