{
  "type": "Feature",
  "properties": {
    "iso:country": "GB",
    "wof:name": "EX34 9GB",
    "wof:placetype": "postalcode"
  },
  "geometry": {"coordinates":[-4.121804,51.209561],"type":"Point"}
}
