{
  "type": "Feature",
  "properties": {
    "date:inception_lower": "1980-01-01",
    "date:inception_upper": "1980-01-01",
    "iso:country": "GB",
    "wof:name": "M29 7EW",
    "wof:placetype": "postalcode"
  },
  "geometry": {"coordinates":[-2.469282,53.489155],"type":"Point"}
}
