{
  "type": "Feature",
  "properties": {
    "iso:country":"GB",
    "wof:name":"SE1 0JP",
    "wof:placetype":"postalcode"
},
  "geometry": {"coordinates":[-0.0993271263407,51.50069134117046],"type":"Point"}
}