{
  "type": "Feature",
  "properties": {
    "iso:country":"GB",
    "wof:name":"DA11 9DE",
    "wof:placetype":"postalcode"
},
  "geometry": {"coordinates":[0.32855356488198,51.44619254570183],"type":"Point"}
}