{
  "type": "Feature",
  "properties": {
    "date:inception_lower": "1980-01-01",
    "date:inception_upper": "1980-01-01",
    "iso:country": "GB",
    "wof:name": "DA11 9DE",
    "wof:placetype": "postalcode"
  },
  "geometry": {"coordinates":[0.32863,51.446264],"type":"Point"}
}
