{
  "type": "Feature",
  "properties": {
    "iso:country":"GB",
    "wof:name":"SA20 0PF",
    "wof:placetype":"postalcode"
},
  "geometry": {"coordinates":[-3.79726347608891,52.09521271926173],"type":"Point"}
}