{
  "type": "Feature",
  "properties": {
    "iso:country":"GB",
    "wof:name":"DY8 4JH",
    "wof:placetype":"postalcode"
},
  "geometry": {"coordinates":[-2.14295717858626,52.46654343278434],"type":"Point"}
}