{
  "type": "Feature",
  "properties": {
    "date:inception_lower": "1992-08-01",
    "date:inception_upper": "1992-08-01",
    "iso:country": "GB",
    "wof:name": "YO7 3EX",
    "wof:placetype": "postalcode"
  },
  "geometry": {"coordinates":[-1.40586,54.201425],"type":"Point"}
}
