{
  "type": "Feature",
  "properties": {
    "iso:country":"GB",
    "wof:name":"YO7 3EX",
    "wof:placetype":"postalcode"
},
  "geometry": {"coordinates":[-1.40587547459054,54.2014337296618],"type":"Point"}
}