{
  "type": "Feature",
  "properties": {
    "iso:country": "GB",
    "wof:name": "DE21 4UB",
    "wof:placetype": "postalcode"
  },
  "geometry": {"coordinates":[-1.453665,52.946455],"type":"Point"}
}
