{
  "type": "Feature",
  "properties": {
    "iso:country":"GB",
    "wof:name":"SE2 9LA",
    "wof:placetype":"postalcode"
},
  "geometry": {"coordinates":[0.11694124131382,51.49507112484246],"type":"Point"}
}