{
  "type": "Feature",
  "properties": {
    "date:inception_lower":"1980-01-01",
    "date:inception_upper":"1980-01-31",
    "iso:country":"GB",
    "wof:name":"SE2 9LA",
    "wof:placetype":"postalcode"
},
  "geometry": {"coordinates":[0.116941,51.495071],"type":"Point"}
}