{
  "type": "Feature",
  "properties": {
    "iso:country": "GB",
    "wof:name": "PE20 1DZ",
    "wof:placetype": "postalcode"
  },
  "geometry": {"coordinates":[-0.055707,52.929136],"type":"Point"}
}
