{
  "type": "Feature",
  "properties": {
    "iso:country":"GB",
    "wof:name":"PE20 1DZ",
    "wof:placetype":"postalcode"
},
  "geometry": {"coordinates":[-0.05570705397715,52.9291363028456],"type":"Point"}
}