{
  "type": "Feature",
  "properties": {
    "iso:country": "GB",
    "wof:name": "DN20 0TT",
    "wof:placetype": "postalcode"
  },
  "geometry": {"coordinates":[-0.544859,53.566637],"type":"Point"}
}
