{
  "type": "Feature",
  "properties": {
    "iso:country":"GB",
    "wof:name":"BH25 7EJ",
    "wof:placetype":"postalcode"
},
  "geometry": {"coordinates":[-1.6653961978327,50.73796766949494],"type":"Point"}
}