{
  "type": "Feature",
  "properties": {
    "iso:country": "GB",
    "wof:name": "ME17 3QE",
    "wof:placetype": "postalcode"
  },
  "geometry": {"coordinates":[0.637003,51.226261],"type":"Point"}
}
