{
  "type": "Feature",
  "properties": {
    "iso:country": "GB",
    "wof:name": "DL11 7UN",
    "wof:placetype": "postalcode"
  },
  "geometry": {"coordinates":[-1.724962,54.538776],"type":"Point"}
}
