{
  "type": "Feature",
  "properties": {
    "date:inception_lower": "1980-01-01",
    "date:inception_upper": "1980-01-01",
    "iso:country": "GB",
    "wof:name": "DL11 7UN",
    "wof:placetype": "postalcode"
  },
  "geometry": {"coordinates":[-1.720746,54.538371],"type":"Point"}
}
