{
  "type": "Feature",
  "properties": {
    "iso:country": "GB",
    "wof:name": "DL11 7UN",
    "wof:placetype": "postalcode"
  },
  "geometry": {"coordinates":[-1.720746,54.538371],"type":"Point"}
}
