{
  "type": "Feature",
  "properties": {
    "iso:country":"GB",
    "wof:name":"DL11 7UN",
    "wof:placetype":"postalcode"
},
  "geometry": {"coordinates":[-1.7249527037919,54.53876536448671],"type":"Point"}
}