{
  "type": "Feature",
  "properties": {
    "iso:country": "GB",
    "wof:name": "GU16 8LZ",
    "wof:placetype": "postalcode"
  },
  "geometry": {"coordinates":[-0.722118,51.318372],"type":"Point"}
}
