{
  "type": "Feature",
  "properties": {
    "iso:country":"GB",
    "wof:name":"GU16 8LZ",
    "wof:placetype":"postalcode"
},
  "geometry": {"coordinates":[-0.72211768772377,51.31837168719485],"type":"Point"}
}