{
  "type": "Feature",
  "properties": {
    "iso:country":"GB",
    "wof:name":"ME14 3LS",
    "wof:placetype":"postalcode"
},
  "geometry": {"coordinates":[0.61846347527145,51.29123589837793],"type":"Point"}
}