{
  "type": "Feature",
  "properties": {
    "date:inception_lower": "1980-01-01",
    "date:inception_upper": "1980-01-01",
    "iso:country": "GB",
    "wof:name": "ME14 3LS",
    "wof:placetype": "postalcode"
  },
  "geometry": {"coordinates":[0.618666,51.29098],"type":"Point"}
}
