{
  "type": "Feature",
  "properties": {
    "iso:country":"GB",
    "wof:name":"DE55 3HA",
    "wof:placetype":"postalcode"
},
  "geometry": {"coordinates":[-1.34843739466272,53.09487723085518],"type":"Point"}
}