{
  "type": "Feature",
  "properties": {
    "date:inception_lower": "2007-07-01",
    "date:inception_upper": "2007-07-01",
    "iso:country": "GB",
    "wof:name": "DN20 8PQ",
    "wof:placetype": "postalcode"
  },
  "geometry": {"coordinates":[-0.481386,53.560913],"type":"Point"}
}
