{
  "type": "Feature",
  "properties": {
    "iso:country":"GB",
    "wof:name":"DN20 8PQ",
    "wof:placetype":"postalcode"
},
  "geometry": {"coordinates":[-0.48138642865511,53.56091327830598],"type":"Point"}
}