{
  "type": "Feature",
  "properties": {
    "date:inception_lower": "1994-12-01",
    "date:inception_upper": "1994-12-01",
    "iso:country": "GB",
    "wof:name": "LL22 8UJ",
    "wof:placetype": "postalcode"
  },
  "geometry": {"coordinates":[-3.720965,53.153362],"type":"Point"}
}
