{
  "type": "Feature",
  "properties": {
    "iso:country": "GB",
    "wof:name": "LL22 8UJ",
    "wof:placetype": "postalcode"
  },
  "geometry": {"coordinates":[-3.721699,53.156363],"type":"Point"}
}
