{
  "type": "Feature",
  "properties": {
    "iso:country":"GB",
    "wof:name":"LL22 8UJ",
    "wof:placetype":"postalcode"
},
  "geometry": {"coordinates":[-3.72096149251356,53.1533462653411],"type":"Point"}
}