{
  "type": "Feature",
  "properties": {
    "iso:country":"GB",
    "wof:name":"NR17 2LZ",
    "wof:placetype":"postalcode"
},
  "geometry": {"coordinates":[1.0302441368793,52.52111602620463],"type":"Point"}
}