{
  "type": "Feature",
  "properties": {
    "date:inception_lower": "2015-05-01",
    "date:inception_upper": "2015-05-01",
    "iso:country": "GB",
    "wof:name": "NR17 2LZ",
    "wof:placetype": "postalcode"
  },
  "geometry": {"coordinates":[1.030361,52.520992],"type":"Point"}
}
