{
  "type": "Feature",
  "properties": {
    "iso:country": "GB",
    "wof:name": "NR17 2LZ",
    "wof:placetype": "postalcode"
  },
  "geometry": {"coordinates":[1.030361,52.520992],"type":"Point"}
}
