{
  "type": "Feature",
  "properties": {
    "iso:country": "GB",
    "wof:name": "DN32 9PW",
    "wof:placetype": "postalcode"
  },
  "geometry": {"coordinates":[-0.078308,53.561283],"type":"Point"}
}
