{
  "type": "Feature",
  "properties": {
    "iso:country": "GB",
    "wof:name": "TR2 5TD",
    "wof:placetype": "postalcode"
  },
  "geometry": {"coordinates":[-4.918682,50.265211],"type":"Point"}
}
