{
  "type": "Feature",
  "properties": {
    "iso:country": "GB",
    "wof:name": "NG3 5DH",
    "wof:placetype": "postalcode"
  },
  "geometry": {"coordinates":[-1.143075,52.970469],"type":"Point"}
}
