{
  "type": "Feature",
  "properties": {
    "iso:country":"GB",
    "wof:name":"DE55 1AQ",
    "wof:placetype":"postalcode"
},
  "geometry": {"coordinates":[-1.39094693541913,53.07306976686248],"type":"Point"}
}