{
  "type": "Feature",
  "properties": {
    "iso:country":"GB",
    "wof:name":"GL2 4UG",
    "wof:placetype":"postalcode"
},
  "geometry": {"coordinates":[-2.28537021700684,51.82252056563495],"type":"Point"}
}