{
  "type": "Feature",
  "properties": {
    "iso:country": "GB",
    "wof:name": "GL2 4UG",
    "wof:placetype": "postalcode"
  },
  "geometry": {"coordinates":[-2.28537,51.822521],"type":"Point"}
}
