{
  "type": "Feature",
  "properties": {
    "date:inception_lower":"1997-06-01",
    "date:inception_upper":"1997-06-30",
    "iso:country":"GB",
    "wof:name":"S26 2EU",
    "wof:placetype":"postalcode"
},
  "geometry": {"coordinates":[-1.299792,53.36446],"type":"Point"}
}