{
  "type": "Feature",
  "properties": {
    "iso:country":"GB",
    "wof:name":"RH1 4NF",
    "wof:placetype":"postalcode"
},
  "geometry": {"coordinates":[-0.07969922087504,51.22329488286768],"type":"Point"}
}