{
  "type": "Feature",
  "properties": {
    "iso:country": "GB",
    "wof:name": "M24 5LQ",
    "wof:placetype": "postalcode"
  },
  "geometry": {"coordinates":[-2.210227,53.563408],"type":"Point"}
}
