{
  "type": "Feature",
  "properties": {
    "iso:country":"GB",
    "wof:name":"B49 5EX",
    "wof:placetype":"postalcode"
},
  "geometry": {"coordinates":[-1.87586745167488,52.21525389732979],"type":"Point"}
}