{
  "type": "Feature",
  "properties": {
    "iso:country": "GB",
    "wof:name": "B49 5EX",
    "wof:placetype": "postalcode"
  },
  "geometry": {"coordinates":[-1.875867,52.215254],"type":"Point"}
}
