{
  "type": "Feature",
  "properties": {
    "iso:country":"GB",
    "wof:name":"TW18 1JW",
    "wof:placetype":"postalcode"
},
  "geometry": {"coordinates":[-0.48074185121248,51.42319097716196],"type":"Point"}
}