{
  "type": "Feature",
  "properties": {
    "iso:country":"GB",
    "wof:name":"L4 3RA",
    "wof:placetype":"postalcode"
},
  "geometry": {"coordinates":[-2.97291596451638,53.44041608971163],"type":"Point"}
}