{
  "type": "Feature",
  "properties": {
    "iso:country":"GB",
    "wof:name":"NN8 3NR",
    "wof:placetype":"postalcode"
},
  "geometry": {"coordinates":[-0.71622500556584,52.30009995682991],"type":"Point"}
}