{
  "type": "Feature",
  "properties": {
    "iso:country":"GB",
    "wof:name":"TW3 2BE",
    "wof:placetype":"postalcode"
},
  "geometry": {"coordinates":[-0.36543395037264,51.46061265900464],"type":"Point"}
}