{
  "type": "Feature",
  "properties": {
    "iso:country":"GB",
    "wof:name":"SG1 5HZ",
    "wof:placetype":"postalcode"
},
  "geometry": {"coordinates":[-0.18691330813982,51.91662669118749],"type":"Point"}
}