{
  "type": "Feature",
  "properties": {
    "date:inception_lower":"2015-06-01",
    "date:inception_upper":"2015-06-30",
    "iso:country":"GB",
    "wof:name":"FK1 2RD",
    "wof:placetype":"postalcode"
},
  "geometry": {"coordinates":[-3.76948,55.985205],"type":"Point"}
}