{
  "type": "Feature",
  "properties": {
    "iso:country": "GB",
    "wof:name": "FK1 2RD",
    "wof:placetype": "postalcode"
  },
  "geometry": {"coordinates":[-3.76948,55.985205],"type":"Point"}
}
