{
  "type": "Feature",
  "properties": {
    "date:inception_lower": "2013-02-01",
    "date:inception_upper": "2013-02-01",
    "iso:country": "GB",
    "wof:name": "W3 6EQ",
    "wof:placetype": "postalcode"
  },
  "geometry": {"coordinates":[-0.261586,51.519737],"type":"Point"}
}
