{
  "type": "Feature",
  "properties": {
    "iso:country":"GB",
    "wof:name":"W3 6EQ",
    "wof:placetype":"postalcode"
},
  "geometry": {"coordinates":[-0.26158563573166,51.51973669716329],"type":"Point"}
}