{
  "type": "Feature",
  "properties": {
    "iso:country":"GB",
    "wof:name":"SW7 1JB",
    "wof:placetype":"postalcode"
},
  "geometry": {"coordinates":[-0.1690855536218,51.49903146439693],"type":"Point"}
}