{
  "type": "Feature",
  "properties": {
    "iso:country": "GB",
    "wof:name": "KA13 7EH",
    "wof:placetype": "postalcode"
  },
  "geometry": {"coordinates":[-4.698585,55.660768],"type":"Point"}
}
