{
  "type": "Feature",
  "properties": {
    "iso:country": "GB",
    "wof:name": "HP19 8DN",
    "wof:placetype": "postalcode"
  },
  "geometry": {"coordinates":[-0.823747,51.817024],"type":"Point"}
}
