{
  "type": "Feature",
  "properties": {
    "iso:country":"GB",
    "wof:name":"HP19 8DN",
    "wof:placetype":"postalcode"
},
  "geometry": {"coordinates":[-0.82374740804372,51.81702382923583],"type":"Point"}
}