{
  "type": "Feature",
  "properties": {
    "iso:country":"GB",
    "wof:name":"LL41 4HR",
    "wof:placetype":"postalcode"
},
  "geometry": {"coordinates":[-3.98740648679682,52.94416585365081],"type":"Point"}
}