{
  "type": "Feature",
  "properties": {
    "iso:country": "GB",
    "wof:name": "CH64 6UH",
    "wof:placetype": "postalcode"
  },
  "geometry": {"coordinates":[-3.078768,53.294217],"type":"Point"}
}
