{
  "type": "Feature",
  "properties": {
    "iso:country":"GB",
    "wof:name":"CH64 6UH",
    "wof:placetype":"postalcode"
},
  "geometry": {"coordinates":[-3.07876833753658,53.29421655866265],"type":"Point"}
}