{
  "type": "Feature",
  "properties": {
    "date:inception_lower": "2015-03-01",
    "date:inception_upper": "2015-03-01",
    "iso:country": "GB",
    "wof:name": "CH64 6UH",
    "wof:placetype": "postalcode"
  },
  "geometry": {"coordinates":[-3.078768,53.294217],"type":"Point"}
}
