{
  "type": "Feature",
  "properties": {
    "iso:country": "GB",
    "wof:name": "TN14 7SE",
    "wof:placetype": "postalcode"
  },
  "geometry": {"coordinates":[0.181417,51.333867],"type":"Point"}
}
