{
  "type": "Feature",
  "properties": {
    "iso:country":"GB",
    "wof:name":"TN14 7SE",
    "wof:placetype":"postalcode"
},
  "geometry": {"coordinates":[0.18141684192123,51.33386720611821],"type":"Point"}
}