{
  "type": "Feature",
  "properties": {
    "iso:country": "GB",
    "wof:name": "AB51 5DF",
    "wof:placetype": "postalcode"
  },
  "geometry": {"coordinates":[-2.40711,57.296052],"type":"Point"}
}
