{
  "type": "Feature",
  "properties": {
    "date:inception_lower": "2014-12-01",
    "date:inception_upper": "2014-12-01",
    "iso:country": "GB",
    "wof:name": "AB51 5DF",
    "wof:placetype": "postalcode"
  },
  "geometry": {"coordinates":[-2.40711,57.296052],"type":"Point"}
}
