{
  "type": "Feature",
  "properties": {
    "iso:country":"GB",
    "wof:name":"AB51 5DF",
    "wof:placetype":"postalcode"
},
  "geometry": {"coordinates":[-2.40709492724915,57.29614167947951],"type":"Point"}
}