{
  "type": "Feature",
  "properties": {
    "iso:country":"GB",
    "wof:name":"NR3 3NS",
    "wof:placetype":"postalcode"
},
  "geometry": {"coordinates":[1.2916305112113,52.65140834520124],"type":"Point"}
}