{
  "type": "Feature",
  "properties": {
    "iso:country": "GB",
    "wof:name": "DY14 0BZ",
    "wof:placetype": "postalcode"
  },
  "geometry": {"coordinates":[-2.507556,52.375293],"type":"Point"}
}
