{
  "type": "Feature",
  "properties": {
    "iso:country":"GB",
    "wof:name":"HU12 8SX",
    "wof:placetype":"postalcode"
},
  "geometry": {"coordinates":[-0.18158161589691,53.75266636131975],"type":"Point"}
}