{
  "type": "Feature",
  "properties": {
    "date:inception_lower": "1980-01-01",
    "date:inception_upper": "1980-01-01",
    "iso:country": "GB",
    "wof:name": "HU12 8SX",
    "wof:placetype": "postalcode"
  },
  "geometry": {"coordinates":[-0.181589,53.752688],"type":"Point"}
}
