{
  "type": "Feature",
  "properties": {
    "date:inception_lower": "1980-01-01",
    "date:inception_upper": "1980-01-01",
    "iso:country": "GB",
    "wof:name": "WV3 0BA",
    "wof:placetype": "postalcode"
  },
  "geometry": {"coordinates":[-2.146883,52.57564],"type":"Point"}
}
