{
  "type": "Feature",
  "properties": {
    "iso:country":"GB",
    "wof:name":"WV3 0BA",
    "wof:placetype":"postalcode"
},
  "geometry": {"coordinates":[-2.14688338482536,52.57564007309767],"type":"Point"}
}