{
  "type": "Feature",
  "properties": {
    "iso:country": "GB",
    "wof:name": "WV3 0BA",
    "wof:placetype": "postalcode"
  },
  "geometry": {"coordinates":[-2.146883,52.57564],"type":"Point"}
}
