{
  "type": "Feature",
  "properties": {
    "iso:country":"GB",
    "wof:name":"BD19 4RF",
    "wof:placetype":"postalcode"
},
  "geometry": {"coordinates":[-1.68149318880545,53.7279329738279],"type":"Point"}
}