{
  "type": "Feature",
  "properties": {
    "iso:country": "GB",
    "wof:name": "NG24 4WB",
    "wof:placetype": "postalcode"
  },
  "geometry": {"coordinates":[-0.817818,53.072911],"type":"Point"}
}
