{
  "type": "Feature",
  "properties": {
    "date:inception_lower": "1987-04-01",
    "date:inception_upper": "1987-04-01",
    "iso:country": "GB",
    "wof:name": "NG24 4WB",
    "wof:placetype": "postalcode"
  },
  "geometry": {"coordinates":[-0.817818,53.072911],"type":"Point"}
}
