{
  "type": "Feature",
  "properties": {
    "iso:country":"GB",
    "wof:name":"NG24 4WB",
    "wof:placetype":"postalcode"
},
  "geometry": {"coordinates":[-0.81781818114139,53.07291056070765],"type":"Point"}
}