{
  "type": "Feature",
  "properties": {
    "iso:country": "GB",
    "wof:name": "WF10 2FJ",
    "wof:placetype": "postalcode"
  },
  "geometry": {"coordinates":[-1.362903,53.746005],"type":"Point"}
}
