{
  "type": "Feature",
  "properties": {
    "date:inception_lower": "1980-01-01",
    "date:inception_upper": "1980-01-01",
    "iso:country": "GB",
    "wof:name": "PA16 8NT",
    "wof:placetype": "postalcode"
  },
  "geometry": {"coordinates":[-4.773475,55.953203],"type":"Point"}
}
