{
  "type": "Feature",
  "properties": {
    "iso:country":"GB",
    "wof:name":"PA16 8NT",
    "wof:placetype":"postalcode"
},
  "geometry": {"coordinates":[-4.77347498788394,55.95320325580415],"type":"Point"}
}