{
  "type": "Feature",
  "properties": {
    "iso:country":"GB",
    "wof:name":"NE1 7AD",
    "wof:placetype":"postalcode"
},
  "geometry": {"coordinates":[-1.61272436932105,54.97431677305721],"type":"Point"}
}