{
  "type": "Feature",
  "properties": {
    "iso:country":"GB",
    "wof:name":"B46 2HY",
    "wof:placetype":"postalcode"
},
  "geometry": {"coordinates":[-1.67401377235169,52.53308503781336],"type":"Point"}
}