{
  "type": "Feature",
  "properties": {
    "iso:country": "GB",
    "wof:name": "BB9 5FA",
    "wof:placetype": "postalcode"
  },
  "geometry": {"coordinates":[-2.21958,53.817746],"type":"Point"}
}
