{
  "type": "Feature",
  "properties": {
    "iso:country":"GB",
    "wof:name":"OX15 0PN",
    "wof:placetype":"postalcode"
},
  "geometry": {"coordinates":[-1.38532632899163,51.99102092806027],"type":"Point"}
}