{
  "type": "Feature",
  "properties": {
    "iso:country":"GB",
    "wof:name":"IV53 8UP",
    "wof:placetype":"postalcode"
},
  "geometry": {"coordinates":[-5.54889536313653,57.33263635882732],"type":"Point"}
}