{
  "type": "Feature",
  "properties": {
    "date:inception_lower": "1987-04-01",
    "date:inception_upper": "1987-04-01",
    "iso:country": "GB",
    "wof:name": "ME14 5UH",
    "wof:placetype": "postalcode"
  },
  "geometry": {"coordinates":[0.555365,51.274193],"type":"Point"}
}
