{
  "type": "Feature",
  "properties": {
    "iso:country":"GB",
    "wof:name":"OL12 7BH",
    "wof:placetype":"postalcode"
},
  "geometry": {"coordinates":[-2.17601947521057,53.6224173429329],"type":"Point"}
}