{
  "type": "Feature",
  "properties": {
    "date:inception_lower": "1980-01-01",
    "date:inception_upper": "1980-01-01",
    "iso:country": "GB",
    "wof:name": "OL12 7BH",
    "wof:placetype": "postalcode"
  },
  "geometry": {"coordinates":[-2.176019,53.622417],"type":"Point"}
}
