{
  "type": "Feature",
  "properties": {
    "iso:country":"GB",
    "wof:name":"W1W 7RP",
    "wof:placetype":"postalcode"
},
  "geometry": {"coordinates":[-0.14081427527567,51.51788461609529],"type":"Point"}
}