{
  "type": "Feature",
  "properties": {
    "date:inception_lower": "2012-10-01",
    "date:inception_upper": "2012-10-01",
    "iso:country": "GB",
    "wof:name": "N19 3TF",
    "wof:placetype": "postalcode"
  },
  "geometry": {"coordinates":[-0.135454,51.5676],"type":"Point"}
}
