{
  "type": "Feature",
  "properties": {
    "iso:country":"GB",
    "wof:name":"N19 3TF",
    "wof:placetype":"postalcode"
},
  "geometry": {"coordinates":[-0.13545370370068,51.56759983247861],"type":"Point"}
}