{
  "type": "Feature",
  "properties": {
    "iso:country": "GB",
    "wof:name": "DN6 0PA",
    "wof:placetype": "postalcode"
  },
  "geometry": {"coordinates":[-1.145891,53.616005],"type":"Point"}
}
