{
  "type": "Feature",
  "properties": {
    "iso:country":"GB",
    "wof:name":"DN6 0PA",
    "wof:placetype":"postalcode"
},
  "geometry": {"coordinates":[-1.14589059584184,53.6160051645686],"type":"Point"}
}