{
  "type": "Feature",
  "properties": {
    "iso:country":"GB",
    "wof:name":"BS4 4LU",
    "wof:placetype":"postalcode"
},
  "geometry": {"coordinates":[-2.54518154610246,51.43467747434524],"type":"Point"}
}