{
  "type": "Feature",
  "properties": {
    "iso:country":"GB",
    "wof:name":"BB3 2GX",
    "wof:placetype":"postalcode"
},
  "geometry": {"coordinates":[-2.45366043994379,53.68578172826199],"type":"Point"}
}