{
  "type": "Feature",
  "properties": {
    "iso:country": "GB",
    "wof:name": "BB3 2GX",
    "wof:placetype": "postalcode"
  },
  "geometry": {"coordinates":[-2.45366,53.685782],"type":"Point"}
}
