{
  "type": "Feature",
  "properties": {
    "date:inception_lower":"2007-08-01",
    "date:inception_upper":"2007-08-31",
    "iso:country":"GB",
    "wof:name":"BB3 2GX",
    "wof:placetype":"postalcode"
},
  "geometry": {"coordinates":[-2.45366,53.685782],"type":"Point"}
}