{
  "type": "Feature",
  "properties": {
    "iso:country": "GB",
    "wof:name": "SK17 9LW",
    "wof:placetype": "postalcode"
  },
  "geometry": {"coordinates":[-1.908856,53.241876],"type":"Point"}
}
