{
  "type": "Feature",
  "properties": {
    "iso:country":"GB",
    "wof:name":"BN42 4FX",
    "wof:placetype":"postalcode"
},
  "geometry": {"coordinates":[-0.23889734658923,50.83526586419896],"type":"Point"}
}