{
  "type": "Feature",
  "properties": {
    "date:inception_lower": "1990-07-01",
    "date:inception_upper": "1990-07-01",
    "iso:country": "GB",
    "wof:name": "BN42 4FX",
    "wof:placetype": "postalcode"
  },
  "geometry": {"coordinates":[-0.238897,50.835266],"type":"Point"}
}
