{
  "type": "Feature",
  "properties": {
    "iso:country":"GB",
    "wof:name":"CR4 1DY",
    "wof:placetype":"postalcode"
},
  "geometry": {"coordinates":[-0.14518128094068,51.40213838425384],"type":"Point"}
}