{
  "type": "Feature",
  "properties": {
    "iso:country":"GB",
    "wof:name":"HD4 6JH",
    "wof:placetype":"postalcode"
},
  "geometry": {"coordinates":[-1.78393061242746,53.62838371652667],"type":"Point"}
}