{
  "type": "Feature",
  "properties": {
    "iso:country":"GB",
    "wof:name":"BS3 5RQ",
    "wof:placetype":"postalcode"
},
  "geometry": {"coordinates":[-2.60437698597745,51.43017001709573],"type":"Point"}
}