{
  "type": "Feature",
  "properties": {
    "iso:country": "GB",
    "wof:name": "CV37 0BZ",
    "wof:placetype": "postalcode"
  },
  "geometry": {"coordinates":[-1.719706,52.207907],"type":"Point"}
}
