{
  "type": "Feature",
  "properties": {
    "date:inception_lower": "2019-07-01",
    "date:inception_upper": "2019-07-01",
    "iso:country": "GB",
    "wof:name": "CV37 0BZ",
    "wof:placetype": "postalcode"
  },
  "geometry": {"coordinates":[-1.720392,52.208125],"type":"Point"}
}
