{
  "type": "Feature",
  "properties": {
    "iso:country":"GB",
    "wof:name":"CM0 7DX",
    "wof:placetype":"postalcode"
},
  "geometry": {"coordinates":[0.84909910335517,51.67413625815866],"type":"Point"}
}