{
  "type": "Feature",
  "properties": {
    "date:inception_lower": "1980-01-01",
    "date:inception_upper": "1980-01-01",
    "iso:country": "GB",
    "wof:name": "SW8 1XZ",
    "wof:placetype": "postalcode"
  },
  "geometry": {"coordinates":[-0.12247,51.479212],"type":"Point"}
}
