{
  "type": "Feature",
  "properties": {
    "iso:country": "GB",
    "wof:name": "SY1 4YF",
    "wof:placetype": "postalcode"
  },
  "geometry": {"coordinates":[-2.713168,52.73994],"type":"Point"}
}
