{
  "type": "Feature",
  "properties": {
    "iso:country":"GB",
    "wof:name":"SY1 4YF",
    "wof:placetype":"postalcode"
},
  "geometry": {"coordinates":[-2.71316786187346,52.73993999112174],"type":"Point"}
}