{
  "type": "Feature",
  "properties": {
    "iso:country":"GB",
    "wof:name":"OX2 6AJ",
    "wof:placetype":"postalcode"
},
  "geometry": {"coordinates":[-1.26661956612018,51.7605933475557],"type":"Point"}
}