{
  "type": "Feature",
  "properties": {
    "iso:country":"GB",
    "wof:name":"B97 5TF",
    "wof:placetype":"postalcode"
},
  "geometry": {"coordinates":[-1.96750670580655,52.29512141094792],"type":"Point"}
}