{
  "type": "Feature",
  "properties": {
    "iso:country": "GB",
    "wof:name": "RH1 1QA",
    "wof:placetype": "postalcode"
  },
  "geometry": {"coordinates":[-0.166554,51.241055],"type":"Point"}
}
