{
  "type": "Feature",
  "properties": {
    "iso:country":"GB",
    "wof:name":"GU28 0DG",
    "wof:placetype":"postalcode"
},
  "geometry": {"coordinates":[-0.60940864468935,50.9888143441617],"type":"Point"}
}