{
  "type": "Feature",
  "properties": {
    "date:inception_lower": "2002-06-01",
    "date:inception_upper": "2002-06-01",
    "iso:country": "GB",
    "wof:name": "EX20 4JU",
    "wof:placetype": "postalcode"
  },
  "geometry": {"coordinates":[-4.193572,50.659433],"type":"Point"}
}
