{
  "type": "Feature",
  "properties": {
    "iso:country":"GB",
    "wof:name":"ST6 8JP",
    "wof:placetype":"postalcode"
},
  "geometry": {"coordinates":[-2.16543908485299,53.06521686874334],"type":"Point"}
}