{
  "type": "Feature",
  "properties": {
    "date:inception_lower": "1980-01-01",
    "date:inception_upper": "1980-01-01",
    "iso:country": "GB",
    "wof:name": "ST6 8JP",
    "wof:placetype": "postalcode"
  },
  "geometry": {"coordinates":[-2.165439,53.065217],"type":"Point"}
}
