{
  "type": "Feature",
  "properties": {
    "date:inception_lower":"1991-09-01",
    "date:inception_upper":"1991-09-30",
    "iso:country":"GB",
    "wof:name":"RG12 7ER",
    "wof:placetype":"postalcode"
},
  "geometry": {"coordinates":[-0.759115,51.4012],"type":"Point"}
}