{
  "type": "Feature",
  "properties": {
    "iso:country":"GB",
    "wof:name":"RG12 7ER",
    "wof:placetype":"postalcode"
},
  "geometry": {"coordinates":[-0.75911457421766,51.40120042772782],"type":"Point"}
}