{
  "type": "Feature",
  "properties": {
    "date:inception_lower":"2002-06-01",
    "date:inception_upper":"2002-06-30",
    "iso:country":"GB",
    "wof:name":"TA19 9RP",
    "wof:placetype":"postalcode"
},
  "geometry": {"coordinates":[-2.922788,50.928551],"type":"Point"}
}