{
  "type": "Feature",
  "properties": {
    "iso:country": "GB",
    "wof:name": "TA19 9RP",
    "wof:placetype": "postalcode"
  },
  "geometry": {"coordinates":[-2.922788,50.928551],"type":"Point"}
}
