{
  "type": "Feature",
  "properties": {
    "iso:country":"GB",
    "wof:name":"G64 2LZ",
    "wof:placetype":"postalcode"
},
  "geometry": {"coordinates":[-4.22345464530523,55.90687780959598],"type":"Point"}
}