{
  "type": "Feature",
  "properties": {
    "date:inception_lower":"2005-08-01",
    "date:inception_upper":"2005-08-31",
    "iso:country":"GB",
    "wof:name":"RG42 3RW",
    "wof:placetype":"postalcode"
},
  "geometry": {"coordinates":[-0.724526,51.426439],"type":"Point"}
}