{
  "type": "Feature",
  "properties": {
    "iso:country": "GB",
    "wof:name": "RG42 3RW",
    "wof:placetype": "postalcode"
  },
  "geometry": {"coordinates":[-0.724526,51.426439],"type":"Point"}
}
