{
  "type": "Feature",
  "properties": {
    "iso:country": "GB",
    "wof:name": "WR11 8YD",
    "wof:placetype": "postalcode"
  },
  "geometry": {"coordinates":[-1.863633,52.10918],"type":"Point"}
}
