{
  "type": "Feature",
  "properties": {
    "iso:country":"GB",
    "wof:name":"WR11 8YD",
    "wof:placetype":"postalcode"
},
  "geometry": {"coordinates":[-1.8636333701399,52.10918007379755],"type":"Point"}
}