{
  "type": "Feature",
  "properties": {
    "date:inception_lower":"2012-03-01",
    "date:inception_upper":"2012-03-31",
    "iso:country":"GB",
    "wof:name":"WS3 2DB",
    "wof:placetype":"postalcode"
},
  "geometry": {"coordinates":[-2.015055,52.625003],"type":"Point"}
}