{
  "type": "Feature",
  "properties": {
    "iso:country":"GB",
    "wof:name":"WS3 2DB",
    "wof:placetype":"postalcode"
},
  "geometry": {"coordinates":[-2.0150546532887,52.62500345162422],"type":"Point"}
}