{
  "type": "Feature",
  "properties": {
    "iso:country":"GB",
    "wof:name":"AB43 7EX",
    "wof:placetype":"postalcode"
},
  "geometry": {"coordinates":[-2.08805211141771,57.69382436670406],"type":"Point"}
}