{
  "type": "Feature",
  "properties": {
    "iso:country": "GB",
    "wof:name": "AB43 7EX",
    "wof:placetype": "postalcode"
  },
  "geometry": {"coordinates":[-2.088052,57.693824],"type":"Point"}
}
