{
  "type": "Feature",
  "properties": {
    "iso:country":"GB",
    "wof:name":"CH61 8TE",
    "wof:placetype":"postalcode"
},
  "geometry": {"coordinates":[-3.10412310191148,53.3470923970407],"type":"Point"}
}