{
  "type": "Feature",
  "properties": {
    "iso:country": "GB",
    "wof:name": "CH61 8TE",
    "wof:placetype": "postalcode"
  },
  "geometry": {"coordinates":[-3.104123,53.347092],"type":"Point"}
}
