{
  "type": "Feature",
  "properties": {
    "iso:country":"GB",
    "wof:name":"MK9 3NT",
    "wof:placetype":"postalcode"
},
  "geometry": {"coordinates":[-0.75250256601136,52.04301464903376],"type":"Point"}
}