{
  "type": "Feature",
  "properties": {
    "date:inception_lower":"1992-08-01",
    "date:inception_upper":"1992-08-31",
    "iso:country":"GB",
    "wof:name":"MK9 3NT",
    "wof:placetype":"postalcode"
},
  "geometry": {"coordinates":[-0.752503,52.043015],"type":"Point"}
}