{
  "type": "Feature",
  "properties": {
    "date:inception_lower": "1992-08-01",
    "date:inception_upper": "1992-08-01",
    "iso:country": "GB",
    "wof:name": "DE21 7GP",
    "wof:placetype": "postalcode"
  },
  "geometry": {"coordinates":[-1.410174,52.917508],"type":"Point"}
}
