{
  "type": "Feature",
  "properties": {
    "iso:country": "GB",
    "wof:name": "DE21 7GP",
    "wof:placetype": "postalcode"
  },
  "geometry": {"coordinates":[-1.410174,52.917508],"type":"Point"}
}
