{
  "type": "Feature",
  "properties": {
    "iso:country":"GB",
    "wof:name":"SO45 2NP",
    "wof:placetype":"postalcode"
},
  "geometry": {"coordinates":[-1.38906436021569,50.83220629690804],"type":"Point"}
}