{
  "type": "Feature",
  "properties": {
    "date:inception_lower": "1994-12-01",
    "date:inception_upper": "1994-12-01",
    "iso:country": "GB",
    "wof:name": "SO45 2NP",
    "wof:placetype": "postalcode"
  },
  "geometry": {"coordinates":[-1.38897,50.832107],"type":"Point"}
}
