{
  "type": "Feature",
  "properties": {
    "date:inception_lower": "1980-01-01",
    "date:inception_upper": "1980-01-01",
    "iso:country": "GB",
    "wof:name": "N12 0QB",
    "wof:placetype": "postalcode"
  },
  "geometry": {"coordinates":[-0.16513,51.60749],"type":"Point"}
}
