{
  "type": "Feature",
  "properties": {
    "iso:country":"GB",
    "wof:name":"N12 0QB",
    "wof:placetype":"postalcode"
},
  "geometry": {"coordinates":[-0.16512975976455,51.60749020254896],"type":"Point"}
}