{
  "type": "Feature",
  "properties": {
    "iso:country":"GB",
    "wof:name":"NP7 8AW",
    "wof:placetype":"postalcode"
},
  "geometry": {"coordinates":[-2.95884146852916,51.84809730598472],"type":"Point"}
}