{
  "type": "Feature",
  "properties": {
    "iso:country":"GB",
    "wof:name":"S60 3BA",
    "wof:placetype":"postalcode"
},
  "geometry": {"coordinates":[-1.3373410400433,53.4102832202237],"type":"Point"}
}