{
  "type": "Feature",
  "properties": {
    "iso:country":"GB",
    "wof:name":"N18 1NW",
    "wof:placetype":"postalcode"
},
  "geometry": {"coordinates":[-0.07689766226067,51.6192607063023],"type":"Point"}
}