{
  "type": "Feature",
  "properties": {
    "iso:country": "GB",
    "wof:name": "BL9 5ES",
    "wof:placetype": "postalcode"
  },
  "geometry": {"coordinates":[-2.294327,53.614275],"type":"Point"}
}
