{
  "type": "Feature",
  "properties": {
    "iso:country":"GB",
    "wof:name":"BL9 5ES",
    "wof:placetype":"postalcode"
},
  "geometry": {"coordinates":[-2.29432740639359,53.61427497657242],"type":"Point"}
}