{
  "type": "Feature",
  "properties": {
    "date:inception_lower":"1980-01-01",
    "date:inception_upper":"1980-01-31",
    "iso:country":"GB",
    "wof:name":"B37 5EQ",
    "wof:placetype":"postalcode"
},
  "geometry": {"coordinates":[-1.752849,52.478671],"type":"Point"}
}