{
  "type": "Feature",
  "properties": {
    "iso:country":"GB",
    "wof:name":"B37 5EQ",
    "wof:placetype":"postalcode"
},
  "geometry": {"coordinates":[-1.75284891067598,52.47867081668711],"type":"Point"}
}