{
  "type": "Feature",
  "properties": {
    "date:inception_lower": "1980-01-01",
    "date:inception_upper": "1980-01-01",
    "iso:country": "GB",
    "wof:name": "G61 2JT",
    "wof:placetype": "postalcode"
  },
  "geometry": {"coordinates":[-4.312224,55.909359],"type":"Point"}
}
