{
  "type": "Feature",
  "properties": {
    "date:inception_lower": "1980-01-01",
    "date:inception_upper": "1980-01-01",
    "iso:country": "GB",
    "wof:name": "WV4 4LW",
    "wof:placetype": "postalcode"
  },
  "geometry": {"coordinates":[-2.165628,52.564971],"type":"Point"}
}
