{
  "type": "Feature",
  "properties": {
    "iso:country":"GB",
    "wof:name":"WV4 4LW",
    "wof:placetype":"postalcode"
},
  "geometry": {"coordinates":[-2.16562767583612,52.56497134077105],"type":"Point"}
}