{
  "type": "Feature",
  "properties": {
    "date:inception_lower":"1999-06-01",
    "date:inception_upper":"1999-06-30",
    "iso:country":"GB",
    "wof:name":"ST10 1YU",
    "wof:placetype":"postalcode"
},
  "geometry": {"coordinates":[-1.976722,52.985192],"type":"Point"}
}