{
  "type": "Feature",
  "properties": {
    "iso:country":"GB",
    "wof:name":"SO21 1TH",
    "wof:placetype":"postalcode"
},
  "geometry": {"coordinates":[-1.31217681723345,50.98831118488955],"type":"Point"}
}