{
  "type": "Feature",
  "properties": {
    "iso:country":"GB",
    "wof:name":"CW12 1JD",
    "wof:placetype":"postalcode"
},
  "geometry": {"coordinates":[-2.21334172446726,53.16773203422312],"type":"Point"}
}