{
  "type": "Feature",
  "properties": {
    "date:inception_lower": "1980-01-01",
    "date:inception_upper": "1980-01-01",
    "iso:country": "GB",
    "wof:name": "CW6 9RG",
    "wof:placetype": "postalcode"
  },
  "geometry": {"coordinates":[-2.635026,53.102073],"type":"Point"}
}
