{
  "type": "Feature",
  "properties": {
    "iso:country": "GB",
    "wof:name": "YO25 5ET",
    "wof:placetype": "postalcode"
  },
  "geometry": {"coordinates":[-0.437116,54.013486],"type":"Point"}
}
