{
  "type": "Feature",
  "properties": {
    "iso:country":"GB",
    "wof:name":"SW17 0QT",
    "wof:placetype":"postalcode"
},
  "geometry": {"coordinates":[-0.1757462527968,51.42671836561096],"type":"Point"}
}