{
  "type": "Feature",
  "properties": {
    "iso:country": "GB",
    "wof:name": "SW17 0QT",
    "wof:placetype": "postalcode"
  },
  "geometry": {"coordinates":[-0.175694,51.426682],"type":"Point"}
}
