{
  "type": "Feature",
  "properties": {
    "iso:country": "GB",
    "wof:name": "LL35 0TB",
    "wof:placetype": "postalcode"
  },
  "geometry": {"coordinates":[-4.043986,52.547587],"type":"Point"}
}
