{
  "type": "Feature",
  "properties": {
    "date:inception_lower": "2016-08-01",
    "date:inception_upper": "2016-08-01",
    "iso:country": "GB",
    "wof:name": "LL35 0TB",
    "wof:placetype": "postalcode"
  },
  "geometry": {"coordinates":[-4.043986,52.547587],"type":"Point"}
}
