{
  "type": "Feature",
  "properties": {
    "date:inception_lower": "1980-01-01",
    "date:inception_upper": "1980-01-01",
    "iso:country": "GB",
    "wof:name": "PA1 1PX",
    "wof:placetype": "postalcode"
  },
  "geometry": {"coordinates":[-4.407508,55.845031],"type":"Point"}
}
