{
  "type": "Feature",
  "properties": {
    "iso:country":"GB",
    "wof:name":"PA1 1PX",
    "wof:placetype":"postalcode"
},
  "geometry": {"coordinates":[-4.40750850166927,55.84503061540484],"type":"Point"}
}