{
  "type": "Feature",
  "properties": {
    "iso:country": "GB",
    "wof:name": "NE32 3RP",
    "wof:placetype": "postalcode"
  },
  "geometry": {"coordinates":[-1.466663,54.97017],"type":"Point"}
}
