{
  "type": "Feature",
  "properties": {
    "iso:country":"GB",
    "wof:name":"SS3 9PJ",
    "wof:placetype":"postalcode"
},
  "geometry": {"coordinates":[0.77918048187323,51.53476401758508],"type":"Point"}
}