{
  "type": "Feature",
  "properties": {
    "date:inception_lower": "1980-01-01",
    "date:inception_upper": "1980-01-01",
    "iso:country": "GB",
    "wof:name": "SS3 9PJ",
    "wof:placetype": "postalcode"
  },
  "geometry": {"coordinates":[0.779198,51.534795],"type":"Point"}
}
