{
  "type": "Feature",
  "properties": {
    "iso:country": "GB",
    "wof:name": "SS3 9PJ",
    "wof:placetype": "postalcode"
  },
  "geometry": {"coordinates":[0.779181,51.534764],"type":"Point"}
}
