{
  "type": "Feature",
  "properties": {
    "iso:country":"GB",
    "wof:name":"N1 2YA",
    "wof:placetype":"postalcode"
},
  "geometry": {"coordinates":[-0.10037782136023,51.54470886353765],"type":"Point"}
}