{
  "type": "Feature",
  "properties": {
    "iso:country":"GB",
    "wof:name":"CT8 8AW",
    "wof:placetype":"postalcode"
},
  "geometry": {"coordinates":[1.34395601451831,51.38088861281808],"type":"Point"}
}