{
  "type": "Feature",
  "properties": {
    "date:inception_lower": "1980-01-01",
    "date:inception_upper": "1980-01-01",
    "iso:country": "GB",
    "wof:name": "CT8 8AW",
    "wof:placetype": "postalcode"
  },
  "geometry": {"coordinates":[1.343956,51.380889],"type":"Point"}
}
