{
  "type": "Feature",
  "properties": {
    "date:inception_lower": "2000-06-01",
    "date:inception_upper": "2000-06-01",
    "iso:country": "GB",
    "wof:name": "OX16 3HY",
    "wof:placetype": "postalcode"
  },
  "geometry": {"coordinates":[-1.32454,52.068326],"type":"Point"}
}
