{
  "type": "Feature",
  "properties": {
    "iso:country":"GB",
    "wof:name":"NR15 1AG",
    "wof:placetype":"postalcode"
},
  "geometry": {"coordinates":[1.32891442645982,52.55256778915861],"type":"Point"}
}