{
  "type": "Feature",
  "properties": {
    "date:inception_lower": "2009-02-01",
    "date:inception_upper": "2009-02-01",
    "iso:country": "GB",
    "wof:name": "NR15 1AG",
    "wof:placetype": "postalcode"
  },
  "geometry": {"coordinates":[1.328914,52.552568],"type":"Point"}
}
