{
  "type": "Feature",
  "properties": {
    "iso:country":"GB",
    "wof:name":"LU7 1FR",
    "wof:placetype":"postalcode"
},
  "geometry": {"coordinates":[-0.65860933163853,51.92232692451196],"type":"Point"}
}