{
  "type": "Feature",
  "properties": {
    "iso:country":"GB",
    "wof:name":"N16 7BA",
    "wof:placetype":"postalcode"
},
  "geometry": {"coordinates":[-0.06442265778079,51.55866209427744],"type":"Point"}
}