{
  "type": "Feature",
  "properties": {
    "iso:country":"GB",
    "wof:name":"CB6 1NH",
    "wof:placetype":"postalcode"
},
  "geometry": {"coordinates":[0.31111171007828,52.45702739995488],"type":"Point"}
}