{
  "type": "Feature",
  "properties": {
    "iso:country":"GB",
    "wof:name":"L40 7RE",
    "wof:placetype":"postalcode"
},
  "geometry": {"coordinates":[-2.84755783579739,53.59534740357447],"type":"Point"}
}