{
  "type": "Feature",
  "properties": {
    "iso:country": "GB",
    "wof:name": "TW15 3FJ",
    "wof:placetype": "postalcode"
  },
  "geometry": {"coordinates":[-0.471931,51.442832],"type":"Point"}
}
