{
  "type": "Feature",
  "properties": {
    "iso:country":"GB",
    "wof:name":"EN2 6HD",
    "wof:placetype":"postalcode"
},
  "geometry": {"coordinates":[-0.08279245913288,51.64528224890866],"type":"Point"}
}