{
  "type": "Feature",
  "properties": {
    "date:inception_lower": "1980-01-01",
    "date:inception_upper": "1980-01-01",
    "iso:country": "GB",
    "wof:name": "G13 4RW",
    "wof:placetype": "postalcode"
  },
  "geometry": {"coordinates":[-4.366587,55.892678],"type":"Point"}
}
