{
  "type": "Feature",
  "properties": {
    "iso:country": "GB",
    "wof:name": "G13 4RW",
    "wof:placetype": "postalcode"
  },
  "geometry": {"coordinates":[-4.366587,55.892678],"type":"Point"}
}
