{
  "type": "Feature",
  "properties": {
    "date:inception_lower": "1980-01-01",
    "date:inception_upper": "1980-01-01",
    "iso:country": "GB",
    "wof:name": "LA2 0JU",
    "wof:placetype": "postalcode"
  },
  "geometry": {"coordinates":[-2.787779,53.993503],"type":"Point"}
}
