{
  "type": "Feature",
  "properties": {
    "iso:country":"GB",
    "wof:name":"G33 2NS",
    "wof:placetype":"postalcode"
},
  "geometry": {"coordinates":[-4.18299705911224,55.86396878798408],"type":"Point"}
}