{
  "type": "Feature",
  "properties": {
    "iso:country": "GB",
    "wof:name": "PO21 5ST",
    "wof:placetype": "postalcode"
  },
  "geometry": {"coordinates":[-0.700392,50.794312],"type":"Point"}
}
