{
  "type": "Feature",
  "properties": {
    "iso:country":"GB",
    "wof:name":"PO21 5ST",
    "wof:placetype":"postalcode"
},
  "geometry": {"coordinates":[-0.70039247212451,50.79431179514353],"type":"Point"}
}