{
  "type": "Feature",
  "properties": {
    "date:inception_lower": "1980-01-01",
    "date:inception_upper": "1980-01-01",
    "iso:country": "GB",
    "wof:name": "RH20 1LB",
    "wof:placetype": "postalcode"
  },
  "geometry": {"coordinates":[-0.521916,50.948399],"type":"Point"}
}
