{
  "type": "Feature",
  "properties": {
    "iso:country":"GB",
    "wof:name":"M38 9GP",
    "wof:placetype":"postalcode"
},
  "geometry": {"coordinates":[-2.41422996151375,53.53278184600801],"type":"Point"}
}