{
  "type": "Feature",
  "properties": {
    "date:inception_lower": "1994-05-01",
    "date:inception_upper": "1994-05-01",
    "iso:country": "GB",
    "wof:name": "M38 9GP",
    "wof:placetype": "postalcode"
  },
  "geometry": {"coordinates":[-2.41423,53.532782],"type":"Point"}
}
