{
  "type": "Feature",
  "properties": {
    "iso:country":"GB",
    "wof:name":"WF1 5LF",
    "wof:placetype":"postalcode"
},
  "geometry": {"coordinates":[-1.48554426028105,53.67107608600744],"type":"Point"}
}