{
  "type": "Feature",
  "properties": {
    "iso:country":"GB",
    "wof:name":"SK10 1QL",
    "wof:placetype":"postalcode"
},
  "geometry": {"coordinates":[-2.10446756997467,53.25710977694481],"type":"Point"}
}