{
  "type": "Feature",
  "properties": {
    "iso:country":"GB",
    "wof:name":"M9 5TL",
    "wof:placetype":"postalcode"
},
  "geometry": {"coordinates":[-2.2251205248715,53.50510916997667],"type":"Point"}
}