{
  "type": "Feature",
  "properties": {
    "date:inception_lower": "1994-05-01",
    "date:inception_upper": "1994-05-01",
    "iso:country": "GB",
    "wof:name": "M9 5TL",
    "wof:placetype": "postalcode"
  },
  "geometry": {"coordinates":[-2.22512,53.505109],"type":"Point"}
}
