{
  "type": "Feature",
  "properties": {
    "date:inception_lower": "1980-01-01",
    "date:inception_upper": "1980-01-01",
    "iso:country": "GB",
    "wof:name": "CT20 2DX",
    "wof:placetype": "postalcode"
  },
  "geometry": {"coordinates":[1.174616,51.076945],"type":"Point"}
}
