{
  "type": "Feature",
  "properties": {
    "iso:country": "GB",
    "wof:name": "S2 2SE",
    "wof:placetype": "postalcode"
  },
  "geometry": {"coordinates":[-1.453082,53.376577],"type":"Point"}
}
