{
  "type": "Feature",
  "properties": {
    "iso:country":"GB",
    "wof:name":"S2 2SE",
    "wof:placetype":"postalcode"
},
  "geometry": {"coordinates":[-1.45308245171824,53.37657727493495],"type":"Point"}
}