{
  "type": "Feature",
  "properties": {
    "date:inception_lower": "1980-01-01",
    "date:inception_upper": "1980-01-01",
    "iso:country": "GB",
    "wof:name": "G71 8AE",
    "wof:placetype": "postalcode"
  },
  "geometry": {"coordinates":[-4.067544,55.803967],"type":"Point"}
}
