{
  "type": "Feature",
  "properties": {
    "iso:country":"GB",
    "wof:name":"G71 8AE",
    "wof:placetype":"postalcode"
},
  "geometry": {"coordinates":[-4.06755609039949,55.80397018802272],"type":"Point"}
}