{
  "type": "Feature",
  "properties": {
    "iso:country":"GB",
    "wof:name":"HA5 4PD",
    "wof:placetype":"postalcode"
},
  "geometry": {"coordinates":[-0.37214680089805,51.61164055197292],"type":"Point"}
}