{
  "type": "Feature",
  "properties": {
    "iso:country":"GB",
    "wof:name":"NP44 3NW",
    "wof:placetype":"postalcode"
},
  "geometry": {"coordinates":[-3.03103281767207,51.64691490855937],"type":"Point"}
}