{
  "type": "Feature",
  "properties": {
    "iso:country": "GB",
    "wof:name": "NP44 3NW",
    "wof:placetype": "postalcode"
  },
  "geometry": {"coordinates":[-3.031033,51.646915],"type":"Point"}
}
