{
  "type": "Feature",
  "properties": {
    "date:inception_lower":"1980-01-01",
    "date:inception_upper":"1980-01-31",
    "iso:country":"GB",
    "wof:name":"WV12 5XA",
    "wof:placetype":"postalcode"
},
  "geometry": {"coordinates":[-2.040381,52.615675],"type":"Point"}
}