{
  "type": "Feature",
  "properties": {
    "iso:country":"GB",
    "wof:name":"G81 2AX",
    "wof:placetype":"postalcode"
},
  "geometry": {"coordinates":[-4.4057587287752,55.91646384829136],"type":"Point"}
}