{
  "type": "Feature",
  "properties": {
    "iso:country":"GB",
    "wof:name":"DE7 8NG",
    "wof:placetype":"postalcode"
},
  "geometry": {"coordinates":[-1.30891366727405,52.98633354323221],"type":"Point"}
}