{
  "type": "Feature",
  "properties": {
    "iso:country":"GB",
    "wof:name":"LS1 4GQ",
    "wof:placetype":"postalcode"
},
  "geometry": {"coordinates":[-1.54855098951075,53.79334399247694],"type":"Point"}
}