{
  "type": "Feature",
  "properties": {
    "iso:country":"GB",
    "wof:name":"CF23 6ET",
    "wof:placetype":"postalcode"
},
  "geometry": {"coordinates":[-3.16564777074953,51.51315288136065],"type":"Point"}
}