{
  "type": "Feature",
  "properties": {
    "iso:country": "GB",
    "wof:name": "CV47 2TL",
    "wof:placetype": "postalcode"
  },
  "geometry": {"coordinates":[-1.428551,52.170441],"type":"Point"}
}
