{
  "type": "Feature",
  "properties": {
    "iso:country":"GB",
    "wof:name":"CV47 2TL",
    "wof:placetype":"postalcode"
},
  "geometry": {"coordinates":[-1.42855119316247,52.17044067374868],"type":"Point"}
}