{
  "type": "Feature",
  "properties": {
    "iso:country":"GB",
    "wof:name":"W1H 7LT",
    "wof:placetype":"postalcode"
},
  "geometry": {"coordinates":[-0.16077805561693,51.51606813967832],"type":"Point"}
}