{
  "type": "Feature",
  "properties": {
    "iso:country":"GB",
    "wof:name":"BN2 9PN",
    "wof:placetype":"postalcode"
},
  "geometry": {"coordinates":[-0.13341534350371,50.82788820305957],"type":"Point"}
}