{
  "type": "Feature",
  "properties": {
    "iso:country":"GB",
    "wof:name":"OL16 3NS",
    "wof:placetype":"postalcode"
},
  "geometry": {"coordinates":[-2.10657381927608,53.60830704574938],"type":"Point"}
}