{
  "type": "Feature",
  "properties": {
    "iso:country": "GB",
    "wof:name": "OL16 3NS",
    "wof:placetype": "postalcode"
  },
  "geometry": {"coordinates":[-2.106574,53.608307],"type":"Point"}
}
