{
  "type": "Feature",
  "properties": {
    "iso:country": "GB",
    "wof:name": "NG23 7DE",
    "wof:placetype": "postalcode"
  },
  "geometry": {"coordinates":[-0.716117,53.237588],"type":"Point"}
}
