{
  "type": "Feature",
  "properties": {
    "iso:country":"GB",
    "wof:name":"NG23 7DE",
    "wof:placetype":"postalcode"
},
  "geometry": {"coordinates":[-0.71611671361879,53.23758843810281],"type":"Point"}
}