{
  "type": "Feature",
  "properties": {
    "iso:country":"GB",
    "wof:name":"DL12 8PU",
    "wof:placetype":"postalcode"
},
  "geometry": {"coordinates":[-1.9243834965014,54.54229821849253],"type":"Point"}
}