{
  "type": "Feature",
  "properties": {
    "iso:country": "GB",
    "wof:name": "DL12 8PU",
    "wof:placetype": "postalcode"
  },
  "geometry": {"coordinates":[-1.924383,54.542298],"type":"Point"}
}
