{
  "type": "Feature",
  "properties": {
    "iso:country":"GB",
    "wof:name":"GU8 5DD",
    "wof:placetype":"postalcode"
},
  "geometry": {"coordinates":[-0.65423743950002,51.16190806723371],"type":"Point"}
}