{
  "type": "Feature",
  "properties": {
    "iso:country": "GB",
    "wof:name": "CT18 7TQ",
    "wof:placetype": "postalcode"
  },
  "geometry": {"coordinates":[1.159373,51.111355],"type":"Point"}
}
