{
  "type": "Feature",
  "properties": {
    "iso:country":"GB",
    "wof:name":"SE9 2PB",
    "wof:placetype":"postalcode"
},
  "geometry": {"coordinates":[0.06669434701262,51.45055380145651],"type":"Point"}
}