{
  "type": "Feature",
  "properties": {
    "date:inception_lower": "1980-01-01",
    "date:inception_upper": "1980-01-01",
    "iso:country": "GB",
    "wof:name": "SE9 2PB",
    "wof:placetype": "postalcode"
  },
  "geometry": {"coordinates":[0.066694,51.450554],"type":"Point"}
}
