{
  "type": "Feature",
  "properties": {
    "iso:country":"GB",
    "wof:name":"G72 8UP",
    "wof:placetype":"postalcode"
},
  "geometry": {"coordinates":[-4.14510519791525,55.81091860174308],"type":"Point"}
}