{
  "type": "Feature",
  "properties": {
    "iso:country":"GB",
    "wof:name":"E14 0LN",
    "wof:placetype":"postalcode"
},
  "geometry": {"coordinates":[-0.00638909242847,51.51565876631903],"type":"Point"}
}