{
  "type": "Feature",
  "properties": {
    "date:inception_lower":"2013-12-01",
    "date:inception_upper":"2013-12-31",
    "iso:country":"GB",
    "wof:name":"PE21 8FL",
    "wof:placetype":"postalcode"
},
  "geometry": {"coordinates":[-0.030447,52.981154],"type":"Point"}
}