{
  "type": "Feature",
  "properties": {
    "iso:country":"GB",
    "wof:name":"PE21 8FL",
    "wof:placetype":"postalcode"
},
  "geometry": {"coordinates":[-0.03044673841047,52.98115389588074],"type":"Point"}
}