{
  "type": "Feature",
  "properties": {
    "iso:country": "GB",
    "wof:name": "NR26 8SW",
    "wof:placetype": "postalcode"
  },
  "geometry": {"coordinates":[1.228736,52.935045],"type":"Point"}
}
