{
  "type": "Feature",
  "properties": {
    "iso:country":"GB",
    "wof:name":"B33 9UH",
    "wof:placetype":"postalcode"
},
  "geometry": {"coordinates":[-1.76884871881483,52.48522085250512],"type":"Point"}
}