{
  "type": "Feature",
  "properties": {
    "iso:country": "GB",
    "wof:name": "CF72 9FB",
    "wof:placetype": "postalcode"
  },
  "geometry": {"coordinates":[-3.440361,51.545844],"type":"Point"}
}
