{
  "type": "Feature",
  "properties": {
    "date:inception_lower": "2000-12-01",
    "date:inception_upper": "2000-12-01",
    "iso:country": "GB",
    "wof:name": "CF72 9FB",
    "wof:placetype": "postalcode"
  },
  "geometry": {"coordinates":[-3.440361,51.545844],"type":"Point"}
}
