{
  "type": "Feature",
  "properties": {
    "iso:country":"GB",
    "wof:name":"CF72 9FB",
    "wof:placetype":"postalcode"
},
  "geometry": {"coordinates":[-3.44036137202448,51.54584386159399],"type":"Point"}
}