{
  "type": "Feature",
  "properties": {
    "iso:country":"GB",
    "wof:name":"HD5 9DU",
    "wof:placetype":"postalcode"
},
  "geometry": {"coordinates":[-1.76639908798445,53.64599470343516],"type":"Point"}
}