{
  "type": "Feature",
  "properties": {
    "iso:country":"GB",
    "wof:name":"M26 1GQ",
    "wof:placetype":"postalcode"
},
  "geometry": {"coordinates":[-2.31772219756113,53.55329228012206],"type":"Point"}
}