{
  "type": "Feature",
  "properties": {
    "iso:country":"GB",
    "wof:name":"PL3 6JQ",
    "wof:placetype":"postalcode"
},
  "geometry": {"coordinates":[-4.10922844544465,50.3873894902374],"type":"Point"}
}