{
  "type": "Feature",
  "properties": {
    "date:inception_lower": "1980-01-01",
    "date:inception_upper": "1980-01-01",
    "iso:country": "GB",
    "wof:name": "OX15 5DX",
    "wof:placetype": "postalcode"
  },
  "geometry": {"coordinates":[-1.384727,52.043227],"type":"Point"}
}
