{
  "type": "Feature",
  "properties": {
    "iso:country":"GB",
    "wof:name":"CB8 7LP",
    "wof:placetype":"postalcode"
},
  "geometry": {"coordinates":[0.41191534939536,52.26430829786455],"type":"Point"}
}