{
  "type": "Feature",
  "properties": {
    "iso:country":"GB",
    "wof:name":"G82 1HS",
    "wof:placetype":"postalcode"
},
  "geometry": {"coordinates":[-4.55640715284356,55.94170394654037],"type":"Point"}
}