{
  "type": "Feature",
  "properties": {
    "iso:country":"GB",
    "wof:name":"PH2 6DA",
    "wof:placetype":"postalcode"
},
  "geometry": {"coordinates":[-3.36536369111421,56.48453588537785],"type":"Point"}
}