{
  "type": "Feature",
  "properties": {
    "iso:country":"GB",
    "wof:name":"CM1 3EN",
    "wof:placetype":"postalcode"
},
  "geometry": {"coordinates":[0.42713861284041,51.72918562082742],"type":"Point"}
}