{
  "type": "Feature",
  "properties": {
    "iso:country":"GB",
    "wof:name":"OX11 0TN",
    "wof:placetype":"postalcode"
},
  "geometry": {"coordinates":[-1.32613529350368,51.56794108132772],"type":"Point"}
}