{
  "type": "Feature",
  "properties": {
    "date:inception_lower": "2024-10-01",
    "date:inception_upper": "2024-10-01",
    "iso:country": "GB",
    "wof:name": "CW1 4UW",
    "wof:placetype": "postalcode"
  },
  "geometry": {"coordinates":[-2.466842,53.120721],"type":"Point"}
}
