{
  "type": "Feature",
  "properties": {
    "iso:country":"GB",
    "wof:name":"RH2 0BP",
    "wof:placetype":"postalcode"
},
  "geometry": {"coordinates":[-0.19773160100178,51.24280725403543],"type":"Point"}
}