{
  "type": "Feature",
  "properties": {
    "iso:country": "GB",
    "wof:name": "RH2 0BP",
    "wof:placetype": "postalcode"
  },
  "geometry": {"coordinates":[-0.197732,51.242807],"type":"Point"}
}
