{
  "type": "Feature",
  "properties": {
    "date:inception_lower": "1980-01-01",
    "date:inception_upper": "1980-01-01",
    "iso:country": "GB",
    "wof:name": "RH2 0BP",
    "wof:placetype": "postalcode"
  },
  "geometry": {"coordinates":[-0.197732,51.242807],"type":"Point"}
}
