{
  "type": "Feature",
  "properties": {
    "date:inception_lower": "1990-02-01",
    "date:inception_upper": "1990-02-01",
    "iso:country": "GB",
    "wof:name": "PE10 9XQ",
    "wof:placetype": "postalcode"
  },
  "geometry": {"coordinates":[-0.379971,52.772185],"type":"Point"}
}
