{
  "type": "Feature",
  "properties": {
    "date:inception_lower": "2019-05-01",
    "date:inception_upper": "2019-05-01",
    "iso:country": "GB",
    "wof:name": "EH7 4FH",
    "wof:placetype": "postalcode"
  },
  "geometry": {"coordinates":[-3.18073,55.962764],"type":"Point"}
}
