{
  "type": "Feature",
  "properties": {
    "date:inception_lower": "2020-02-01",
    "date:inception_upper": "2020-02-01",
    "iso:country": "GB",
    "wof:name": "PE10 9WH",
    "wof:placetype": "postalcode"
  },
  "geometry": {"coordinates":[-0.364827,52.767671],"type":"Point"}
}
