{
  "type": "Feature",
  "properties": {
    "iso:country":"GB",
    "wof:name":"KA3 6AJ",
    "wof:placetype":"postalcode"
},
  "geometry": {"coordinates":[-4.44496560736682,55.65373608734576],"type":"Point"}
}