{
  "type": "Feature",
  "properties": {
    "date:inception_lower":"1980-01-01",
    "date:inception_upper":"1980-01-31",
    "iso:country":"GB",
    "wof:name":"EN6 2DR",
    "wof:placetype":"postalcode"
},
  "geometry": {"coordinates":[-0.20282,51.695271],"type":"Point"}
}