{
  "type": "Feature",
  "properties": {
    "iso:country": "GB",
    "wof:name": "EN6 2DR",
    "wof:placetype": "postalcode"
  },
  "geometry": {"coordinates":[-0.20282,51.695271],"type":"Point"}
}
