{
  "type": "Feature",
  "properties": {
    "iso:country":"GB",
    "wof:name":"EN6 2DR",
    "wof:placetype":"postalcode"
},
  "geometry": {"coordinates":[-0.20282030601821,51.69527110209754],"type":"Point"}
}