{
  "type": "Feature",
  "properties": {
    "iso:country":"GB",
    "wof:name":"B14 6TL",
    "wof:placetype":"postalcode"
},
  "geometry": {"coordinates":[-1.90456154067252,52.42410503755659],"type":"Point"}
}