{
  "type": "Feature",
  "properties": {
    "iso:country": "GB",
    "wof:name": "EN1 2BE",
    "wof:placetype": "postalcode"
  },
  "geometry": {"coordinates":[-0.081027,51.644651],"type":"Point"}
}
