{
  "type": "Feature",
  "properties": {
    "iso:country":"GB",
    "wof:name":"W3 9RF",
    "wof:placetype":"postalcode"
},
  "geometry": {"coordinates":[-0.2809676205771,51.5072262215533],"type":"Point"}
}