{
  "type": "Feature",
  "properties": {
    "iso:country": "GB",
    "wof:name": "W3 9RF",
    "wof:placetype": "postalcode"
  },
  "geometry": {"coordinates":[-0.280968,51.507226],"type":"Point"}
}
