{
  "type": "Feature",
  "properties": {
    "iso:country": "GB",
    "wof:name": "DN31 2RZ",
    "wof:placetype": "postalcode"
  },
  "geometry": {"coordinates":[-0.105847,53.574173],"type":"Point"}
}
