{
  "type": "Feature",
  "properties": {
    "iso:country":"GB",
    "wof:name":"LL58 8EB",
    "wof:placetype":"postalcode"
},
  "geometry": {"coordinates":[-4.09489077709115,53.26301655173978],"type":"Point"}
}