{
  "type": "Feature",
  "properties": {
    "date:inception_lower":"1987-10-01",
    "date:inception_upper":"1987-10-31",
    "iso:country":"GB",
    "wof:name":"TQ12 5YN",
    "wof:placetype":"postalcode"
},
  "geometry": {"coordinates":[-3.635256,50.489906],"type":"Point"}
}