{
  "type": "Feature",
  "properties": {
    "date:inception_lower":"2011-02-01",
    "date:inception_upper":"2011-02-28",
    "iso:country":"GB",
    "wof:name":"BS26 2EZ",
    "wof:placetype":"postalcode"
},
  "geometry": {"coordinates":[-2.859495,51.291828],"type":"Point"}
}