{
  "type": "Feature",
  "properties": {
    "iso:country": "GB",
    "wof:name": "BS26 2EZ",
    "wof:placetype": "postalcode"
  },
  "geometry": {"coordinates":[-2.859495,51.291828],"type":"Point"}
}
