{
  "type": "Feature",
  "properties": {
    "date:inception_lower": "1980-01-01",
    "date:inception_upper": "1980-01-01",
    "iso:country": "GB",
    "wof:name": "W13 0EZ",
    "wof:placetype": "postalcode"
  },
  "geometry": {"coordinates":[-0.323777,51.51789],"type":"Point"}
}
