{
  "type": "Feature",
  "properties": {
    "date:inception_lower": "2022-07-01",
    "date:inception_upper": "2022-07-01",
    "iso:country": "GB",
    "wof:name": "LS16 6FW",
    "wof:placetype": "postalcode"
  },
  "geometry": {"coordinates":[-1.613615,53.838176],"type":"Point"}
}
