{
  "type": "Feature",
  "properties": {
    "iso:country": "GB",
    "wof:name": "BH8 9DS",
    "wof:placetype": "postalcode"
  },
  "geometry": {"coordinates":[-1.852855,50.741511],"type":"Point"}
}
