{
  "type": "Feature",
  "properties": {
    "iso:country":"GB",
    "wof:name":"NN7 3LU",
    "wof:placetype":"postalcode"
},
  "geometry": {"coordinates":[-1.03082263116078,52.2206649423325],"type":"Point"}
}