{
  "type": "Feature",
  "properties": {
    "iso:country":"GB",
    "wof:name":"E1 3BN",
    "wof:placetype":"postalcode"
},
  "geometry": {"coordinates":[-0.05324853220622,51.51829839754501],"type":"Point"}
}