{
  "type": "Feature",
  "properties": {
    "iso:country": "GB",
    "wof:name": "GL19 4NT",
    "wof:placetype": "postalcode"
  },
  "geometry": {"coordinates":[-2.278321,51.959899],"type":"Point"}
}
