{
  "type": "Feature",
  "properties": {
    "iso:country":"GB",
    "wof:name":"OX4 2DD",
    "wof:placetype":"postalcode"
},
  "geometry": {"coordinates":[-1.22219151436217,51.74227138178536],"type":"Point"}
}