{
  "type": "Feature",
  "properties": {
    "iso:country": "GB",
    "wof:name": "OX4 2DD",
    "wof:placetype": "postalcode"
  },
  "geometry": {"coordinates":[-1.222085,51.74233],"type":"Point"}
}
