{
  "type": "Feature",
  "properties": {
    "iso:country":"GB",
    "wof:name":"KT3 4EA",
    "wof:placetype":"postalcode"
},
  "geometry": {"coordinates":[-0.25409833962693,51.4014556531803],"type":"Point"}
}