{
  "type": "Feature",
  "properties": {
    "iso:country": "GB",
    "wof:name": "HR6 9EW",
    "wof:placetype": "postalcode"
  },
  "geometry": {"coordinates":[-2.895422,52.216119],"type":"Point"}
}
