{
  "type": "Feature",
  "properties": {
    "iso:country":"GB",
    "wof:name":"HR6 9EW",
    "wof:placetype":"postalcode"
},
  "geometry": {"coordinates":[-2.89542186012551,52.21611872571275],"type":"Point"}
}