{
  "type": "Feature",
  "properties": {
    "iso:country": "GB",
    "wof:name": "KA9 1DF",
    "wof:placetype": "postalcode"
  },
  "geometry": {"coordinates":[-4.596245,55.493721],"type":"Point"}
}
