{
  "type": "Feature",
  "properties": {
    "iso:country":"GB",
    "wof:name":"TN21 0HF",
    "wof:placetype":"postalcode"
},
  "geometry": {"coordinates":[0.25334663138634,50.93438974944121],"type":"Point"}
}