{
  "type": "Feature",
  "properties": {
    "iso:country":"GB",
    "wof:name":"B26 3BP",
    "wof:placetype":"postalcode"
},
  "geometry": {"coordinates":[-1.78813560176853,52.45843079767043],"type":"Point"}
}