{
  "type": "Feature",
  "properties": {
    "date:inception_lower": "1980-01-01",
    "date:inception_upper": "1980-01-01",
    "iso:country": "GB",
    "wof:name": "M22 4LJ",
    "wof:placetype": "postalcode"
  },
  "geometry": {"coordinates":[-2.251771,53.402479],"type":"Point"}
}
