{
  "type": "Feature",
  "properties": {
    "iso:country":"GB",
    "wof:name":"DT6 5QN",
    "wof:placetype":"postalcode"
},
  "geometry": {"coordinates":[-2.88777986939673,50.77796126768936],"type":"Point"}
}