{
  "type": "Feature",
  "properties": {
    "iso:country":"GB",
    "wof:name":"TW8 9AZ",
    "wof:placetype":"postalcode"
},
  "geometry": {"coordinates":[-0.29127085268065,51.49219767186496],"type":"Point"}
}