{
  "type": "Feature",
  "properties": {
    "iso:country": "GB",
    "wof:name": "PO33 2PQ",
    "wof:placetype": "postalcode"
  },
  "geometry": {"coordinates":[-1.166637,50.724518],"type":"Point"}
}
