{
  "type": "Feature",
  "properties": {
    "date:inception_lower":"1992-08-01",
    "date:inception_upper":"1992-08-31",
    "iso:country":"GB",
    "wof:name":"LE67 3BP",
    "wof:placetype":"postalcode"
},
  "geometry": {"coordinates":[-1.379774,52.715294],"type":"Point"}
}