{
  "type": "Feature",
  "properties": {
    "iso:country": "GB",
    "wof:name": "DA16 2JN",
    "wof:placetype": "postalcode"
  },
  "geometry": {"coordinates":[0.103844,51.455909],"type":"Point"}
}
