{
  "type": "Feature",
  "properties": {
    "iso:country":"GB",
    "wof:name":"DA16 2JN",
    "wof:placetype":"postalcode"
},
  "geometry": {"coordinates":[0.10384347034959,51.45590915912649],"type":"Point"}
}