{
  "type": "Feature",
  "properties": {
    "iso:country": "GB",
    "wof:name": "N1C 4DA",
    "wof:placetype": "postalcode"
  },
  "geometry": {"coordinates":[-0.122684,51.536824],"type":"Point"}
}
