{
  "type": "Feature",
  "properties": {
    "iso:country":"GB",
    "wof:name":"L34 2QH",
    "wof:placetype":"postalcode"
},
  "geometry": {"coordinates":[-2.77952334017347,53.43454517641944],"type":"Point"}
}