{
  "type": "Feature",
  "properties": {
    "date:inception_lower": "1980-01-01",
    "date:inception_upper": "1980-01-01",
    "iso:country": "GB",
    "wof:name": "L34 2QH",
    "wof:placetype": "postalcode"
  },
  "geometry": {"coordinates":[-2.779523,53.434545],"type":"Point"}
}
