{
  "type": "Feature",
  "properties": {
    "iso:country": "GB",
    "wof:name": "DE56 4EZ",
    "wof:placetype": "postalcode"
  },
  "geometry": {"coordinates":[-1.491861,52.987966],"type":"Point"}
}
