{
  "type": "Feature",
  "properties": {
    "iso:country": "GB",
    "wof:name": "NG19 0ER",
    "wof:placetype": "postalcode"
  },
  "geometry": {"coordinates":[-1.163716,53.15299],"type":"Point"}
}
