{
  "type": "Feature",
  "properties": {
    "date:inception_lower": "1980-01-01",
    "date:inception_upper": "1980-01-01",
    "iso:country": "GB",
    "wof:name": "PA1 3RA",
    "wof:placetype": "postalcode"
  },
  "geometry": {"coordinates":[-4.412761,55.848073],"type":"Point"}
}
