{
  "type": "Feature",
  "properties": {
    "iso:country": "GB",
    "wof:name": "SK9 3NH",
    "wof:placetype": "postalcode"
  },
  "geometry": {"coordinates":[-2.223443,53.352415],"type":"Point"}
}
