{
  "type": "Feature",
  "properties": {
    "iso:country":"GB",
    "wof:name":"PA8 6EE",
    "wof:placetype":"postalcode"
},
  "geometry": {"coordinates":[-4.46099651949248,55.90925115851213],"type":"Point"}
}