{
  "type": "Feature",
  "properties": {
    "iso:country": "GB",
    "wof:name": "WF15 7EJ",
    "wof:placetype": "postalcode"
  },
  "geometry": {"coordinates":[-1.694466,53.703337],"type":"Point"}
}
