{
  "type": "Feature",
  "properties": {
    "iso:country":"GB",
    "wof:name":"WF15 7EJ",
    "wof:placetype":"postalcode"
},
  "geometry": {"coordinates":[-1.69450943729695,53.7032674858487],"type":"Point"}
}