{
  "type": "Feature",
  "properties": {
    "iso:country":"GB",
    "wof:name":"OX17 2BT",
    "wof:placetype":"postalcode"
},
  "geometry": {"coordinates":[-1.24530632714739,52.06160358012271],"type":"Point"}
}