{
  "type": "Feature",
  "properties": {
    "iso:country":"GB",
    "wof:name":"DN17 2TL",
    "wof:placetype":"postalcode"
},
  "geometry": {"coordinates":[-0.6703135060421,53.55548593483442],"type":"Point"}
}