{
  "type": "Feature",
  "properties": {
    "iso:country": "GB",
    "wof:name": "DH8 0JT",
    "wof:placetype": "postalcode"
  },
  "geometry": {"coordinates":[-1.852247,54.862937],"type":"Point"}
}
