{
  "type": "Feature",
  "properties": {
    "iso:country": "GB",
    "wof:name": "B77 1QT",
    "wof:placetype": "postalcode"
  },
  "geometry": {"coordinates":[-1.684656,52.592995],"type":"Point"}
}
