{
  "type": "Feature",
  "properties": {
    "iso:country":"GB",
    "wof:name":"B77 1QT",
    "wof:placetype":"postalcode"
},
  "geometry": {"coordinates":[-1.68465596682395,52.59299534095747],"type":"Point"}
}