{
  "type": "Feature",
  "properties": {
    "iso:country": "GB",
    "wof:name": "TW11 0LA",
    "wof:placetype": "postalcode"
  },
  "geometry": {"coordinates":[-0.347821,51.427328],"type":"Point"}
}
