{
  "type": "Feature",
  "properties": {
    "iso:country":"GB",
    "wof:name":"TW11 0LA",
    "wof:placetype":"postalcode"
},
  "geometry": {"coordinates":[-0.34782123442974,51.42732779145178],"type":"Point"}
}