{
  "type": "Feature",
  "properties": {
    "date:inception_lower":"1980-01-01",
    "date:inception_upper":"1980-01-31",
    "iso:country":"GB",
    "wof:name":"TW11 0LA",
    "wof:placetype":"postalcode"
},
  "geometry": {"coordinates":[-0.347821,51.427328],"type":"Point"}
}