{
  "type": "Feature",
  "properties": {
    "date:inception_lower": "2006-09-01",
    "date:inception_upper": "2006-09-01",
    "iso:country": "GB",
    "wof:name": "CB24 8SN",
    "wof:placetype": "postalcode"
  },
  "geometry": {"coordinates":[0.137888,52.294146],"type":"Point"}
}
