{
  "type": "Feature",
  "properties": {
    "iso:country":"GB",
    "wof:name":"CB24 8SN",
    "wof:placetype":"postalcode"
},
  "geometry": {"coordinates":[0.13788748827549,52.29414641229687],"type":"Point"}
}