{
  "type": "Feature",
  "properties": {
    "iso:country":"GB",
    "wof:name":"RM16 6AZ",
    "wof:placetype":"postalcode"
},
  "geometry": {"coordinates":[0.29054311012166,51.47979346429639],"type":"Point"}
}