{
  "type": "Feature",
  "properties": {
    "date:inception_lower":"2002-05-01",
    "date:inception_upper":"2002-05-31",
    "iso:country":"GB",
    "wof:name":"RM16 6AZ",
    "wof:placetype":"postalcode"
},
  "geometry": {"coordinates":[0.290543,51.479793],"type":"Point"}
}