{
  "type": "Feature",
  "properties": {
    "iso:country":"GB",
    "wof:name":"CM8 3GF",
    "wof:placetype":"postalcode"
},
  "geometry": {"coordinates":[0.64897829685191,51.79925226137112],"type":"Point"}
}