{
  "type": "Feature",
  "properties": {
    "iso:country":"GB",
    "wof:name":"EH51 9BD",
    "wof:placetype":"postalcode"
},
  "geometry": {"coordinates":[-3.6052596935662,56.01242549339239],"type":"Point"}
}