{
  "type": "Feature",
  "properties": {
    "iso:country":"GB",
    "wof:name":"IP6 9JP",
    "wof:placetype":"postalcode"
},
  "geometry": {"coordinates":[1.20674468703899,52.14925579373067],"type":"Point"}
}