{
  "type": "Feature",
  "properties": {
    "iso:country": "GB",
    "wof:name": "IP6 9JP",
    "wof:placetype": "postalcode"
  },
  "geometry": {"coordinates":[1.206745,52.149256],"type":"Point"}
}
