{
  "type": "Feature",
  "properties": {
    "iso:country":"GB",
    "wof:name":"CA28 9RF",
    "wof:placetype":"postalcode"
},
  "geometry": {"coordinates":[-3.58549976695761,54.52963515433502],"type":"Point"}
}