{
  "type": "Feature",
  "properties": {
    "iso:country":"GB",
    "wof:name":"FK3 9EN",
    "wof:placetype":"postalcode"
},
  "geometry": {"coordinates":[-3.71174713136682,56.0114873474596],"type":"Point"}
}