{
  "type": "Feature",
  "properties": {
    "iso:country":"GB",
    "wof:name":"GL51 0WQ",
    "wof:placetype":"postalcode"
},
  "geometry": {"coordinates":[-2.11767666079086,51.91665526586556],"type":"Point"}
}