{
  "type": "Feature",
  "properties": {
    "iso:country": "GB",
    "wof:name": "GL51 0WQ",
    "wof:placetype": "postalcode"
  },
  "geometry": {"coordinates":[-2.117677,51.916655],"type":"Point"}
}
