{
  "type": "Feature",
  "properties": {
    "iso:country":"GB",
    "wof:name":"G84 8TR",
    "wof:placetype":"postalcode"
},
  "geometry": {"coordinates":[-4.73285344525366,56.00556179209731],"type":"Point"}
}