{
  "type": "Feature",
  "properties": {
    "iso:country": "GB",
    "wof:name": "G84 8TR",
    "wof:placetype": "postalcode"
  },
  "geometry": {"coordinates":[-4.732853,56.005562],"type":"Point"}
}
