{
  "type": "Feature",
  "properties": {
    "iso:country": "GB",
    "wof:name": "LL23 7TP",
    "wof:placetype": "postalcode"
  },
  "geometry": {"coordinates":[-3.667812,52.85486],"type":"Point"}
}
