{
  "type": "Feature",
  "properties": {
    "iso:country":"GB",
    "wof:name":"PH7 4BH",
    "wof:placetype":"postalcode"
},
  "geometry": {"coordinates":[-3.84560034963145,56.37538326640761],"type":"Point"}
}