{
  "type": "Feature",
  "properties": {
    "iso:country":"GB",
    "wof:name":"W12 9NB",
    "wof:placetype":"postalcode"
},
  "geometry": {"coordinates":[-0.24813942554869,51.49864732323505],"type":"Point"}
}