{
  "type": "Feature",
  "properties": {
    "date:inception_lower": "1980-01-01",
    "date:inception_upper": "1980-01-01",
    "iso:country": "GB",
    "wof:name": "WA4 6HE",
    "wof:placetype": "postalcode"
  },
  "geometry": {"coordinates":[-2.597312,53.372019],"type":"Point"}
}
