{
  "type": "Feature",
  "properties": {
    "iso:country":"GB",
    "wof:name":"WA4 6HE",
    "wof:placetype":"postalcode"
},
  "geometry": {"coordinates":[-2.59731197414725,53.37201865188773],"type":"Point"}
}