{
  "type": "Feature",
  "properties": {
    "iso:country":"GB",
    "wof:name":"OL9 0AA",
    "wof:placetype":"postalcode"
},
  "geometry": {"coordinates":[-2.14160627571909,53.55386452198046],"type":"Point"}
}