{
  "type": "Feature",
  "properties": {
    "date:inception_lower": "1983-03-01",
    "date:inception_upper": "1983-03-01",
    "iso:country": "GB",
    "wof:name": "B6 7DB",
    "wof:placetype": "postalcode"
  },
  "geometry": {"coordinates":[-1.874988,52.516114],"type":"Point"}
}
