{
  "type": "Feature",
  "properties": {
    "iso:country":"GB",
    "wof:name":"SG6 1FP",
    "wof:placetype":"postalcode"
},
  "geometry": {"coordinates":[-0.21711337903486,51.98196399058411],"type":"Point"}
}