{
  "type": "Feature",
  "properties": {
    "iso:country": "GB",
    "wof:name": "SG6 1FP",
    "wof:placetype": "postalcode"
  },
  "geometry": {"coordinates":[-0.216575,51.980913],"type":"Point"}
}
