{
  "type": "Feature",
  "properties": {
    "date:inception_lower":"2002-06-01",
    "date:inception_upper":"2002-06-30",
    "iso:country":"GB",
    "wof:name":"SG6 1FP",
    "wof:placetype":"postalcode"
},
  "geometry": {"coordinates":[-0.216575,51.980913],"type":"Point"}
}