{
  "type": "Feature",
  "properties": {
    "iso:country":"GB",
    "wof:name":"CV21 2LW",
    "wof:placetype":"postalcode"
},
  "geometry": {"coordinates":[-1.26563792805875,52.37599633656008],"type":"Point"}
}