{
  "type": "Feature",
  "properties": {
    "date:inception_lower": "1980-01-01",
    "date:inception_upper": "1980-01-01",
    "iso:country": "GB",
    "wof:name": "CV21 2LW",
    "wof:placetype": "postalcode"
  },
  "geometry": {"coordinates":[-1.265625,52.376067],"type":"Point"}
}
