{
  "type": "Feature",
  "properties": {
    "iso:country": "GB",
    "wof:name": "CV22 7AN",
    "wof:placetype": "postalcode"
  },
  "geometry": {"coordinates":[-1.269655,52.369341],"type":"Point"}
}
