{
  "type": "Feature",
  "properties": {
    "iso:country":"GB",
    "wof:name":"CV22 7AN",
    "wof:placetype":"postalcode"
},
  "geometry": {"coordinates":[-1.26965515507969,52.36934142073464],"type":"Point"}
}