{
  "type": "Feature",
  "properties": {
    "iso:country":"GB",
    "wof:name":"AL3 5QJ",
    "wof:placetype":"postalcode"
},
  "geometry": {"coordinates":[-0.33825749637303,51.75800591151535],"type":"Point"}
}