{
  "type": "Feature",
  "properties": {
    "date:inception_lower":"1980-01-01",
    "date:inception_upper":"1980-01-31",
    "iso:country":"GB",
    "wof:name":"AL3 5QJ",
    "wof:placetype":"postalcode"
},
  "geometry": {"coordinates":[-0.338257,51.758006],"type":"Point"}
}