{
  "type": "Feature",
  "properties": {
    "iso:country":"GB",
    "wof:name":"PE10 9HT",
    "wof:placetype":"postalcode"
},
  "geometry": {"coordinates":[-0.36423494616151,52.76947627458533],"type":"Point"}
}