{
  "type": "Feature",
  "properties": {
    "iso:country":"GB",
    "wof:name":"ST13 8QQ",
    "wof:placetype":"postalcode"
},
  "geometry": {"coordinates":[-2.12424087229895,53.10278736781787],"type":"Point"}
}