{
  "type": "Feature",
  "properties": {
    "date:inception_lower": "1993-08-01",
    "date:inception_upper": "1993-08-01",
    "iso:country": "GB",
    "wof:name": "BA12 8QP",
    "wof:placetype": "postalcode"
  },
  "geometry": {"coordinates":[-2.185604,51.209126],"type":"Point"}
}
