{
  "type": "Feature",
  "properties": {
    "iso:country":"GB",
    "wof:name":"NG22 8RA",
    "wof:placetype":"postalcode"
},
  "geometry": {"coordinates":[-1.04038272712649,53.1407510485456],"type":"Point"}
}