{
  "type": "Feature",
  "properties": {
    "iso:country": "GB",
    "wof:name": "SO40 2QS",
    "wof:placetype": "postalcode"
  },
  "geometry": {"coordinates":[-1.503008,50.911962],"type":"Point"}
}
