{
  "type": "Feature",
  "properties": {
    "iso:country":"GB",
    "wof:name":"SO40 2QS",
    "wof:placetype":"postalcode"
},
  "geometry": {"coordinates":[-1.50300814149338,50.91196191625475],"type":"Point"}
}