{
  "type": "Feature",
  "properties": {
    "iso:country":"GB",
    "wof:name":"CA11 8GW",
    "wof:placetype":"postalcode"
},
  "geometry": {"coordinates":[-2.7462015997922,54.65768556148014],"type":"Point"}
}