{
  "type": "Feature",
  "properties": {
    "date:inception_lower": "1995-07-01",
    "date:inception_upper": "1995-07-01",
    "iso:country": "GB",
    "wof:name": "CA11 8GW",
    "wof:placetype": "postalcode"
  },
  "geometry": {"coordinates":[-2.746202,54.657686],"type":"Point"}
}
