{
  "type": "Feature",
  "properties": {
    "iso:country": "GB",
    "wof:name": "CA11 8GW",
    "wof:placetype": "postalcode"
  },
  "geometry": {"coordinates":[-2.746202,54.657686],"type":"Point"}
}
