{
  "type": "Feature",
  "properties": {
    "iso:country":"GB",
    "wof:name":"BD21 2QN",
    "wof:placetype":"postalcode"
},
  "geometry": {"coordinates":[-1.91704017511214,53.86740666110875],"type":"Point"}
}