{
  "type": "Feature",
  "properties": {
    "iso:country": "GB",
    "wof:name": "SY8 4EE",
    "wof:placetype": "postalcode"
  },
  "geometry": {"coordinates":[-2.7416,52.334686],"type":"Point"}
}
