{
  "type": "Feature",
  "properties": {
    "iso:country":"GB",
    "wof:name":"SY8 4EE",
    "wof:placetype":"postalcode"
},
  "geometry": {"coordinates":[-2.74145463078158,52.33464713857026],"type":"Point"}
}