{
  "type": "Feature",
  "properties": {
    "iso:country": "GB",
    "wof:name": "BB4 5DF",
    "wof:placetype": "postalcode"
  },
  "geometry": {"coordinates":[-2.327572,53.704664],"type":"Point"}
}
