{
  "type": "Feature",
  "properties": {
    "iso:country":"GB",
    "wof:name":"BL0 9PN",
    "wof:placetype":"postalcode"
},
  "geometry": {"coordinates":[-2.3303756910625,53.63903335704698],"type":"Point"}
}