{
  "type": "Feature",
  "properties": {
    "date:inception_lower": "2001-06-01",
    "date:inception_upper": "2001-06-01",
    "iso:country": "GB",
    "wof:name": "G32 8JE",
    "wof:placetype": "postalcode"
  },
  "geometry": {"coordinates":[-4.147554,55.83915],"type":"Point"}
}
