{
  "type": "Feature",
  "properties": {
    "date:inception_lower": "1996-06-01",
    "date:inception_upper": "1996-06-01",
    "iso:country": "GB",
    "wof:name": "AB53 5SU",
    "wof:placetype": "postalcode"
  },
  "geometry": {"coordinates":[-2.377298,57.618014],"type":"Point"}
}
