{
  "type": "Feature",
  "properties": {
    "iso:country":"GB",
    "wof:name":"S7 2DF",
    "wof:placetype":"postalcode"
},
  "geometry": {"coordinates":[-1.48821565040874,53.35239154592144],"type":"Point"}
}