{
  "type": "Feature",
  "properties": {
    "iso:country":"GB",
    "wof:name":"B36 0NT",
    "wof:placetype":"postalcode"
},
  "geometry": {"coordinates":[-1.74082782067145,52.49734425749855],"type":"Point"}
}