{
  "type": "Feature",
  "properties": {
    "iso:country": "GB",
    "wof:name": "WF17 5RD",
    "wof:placetype": "postalcode"
  },
  "geometry": {"coordinates":[-1.636895,53.71294],"type":"Point"}
}
