{
  "type": "Feature",
  "properties": {
    "iso:country":"GB",
    "wof:name":"TS17 9AR",
    "wof:placetype":"postalcode"
},
  "geometry": {"coordinates":[-1.28563817704742,54.54781716284371],"type":"Point"}
}