{
  "type": "Feature",
  "properties": {
    "iso:country":"GB",
    "wof:name":"NW5 1PU",
    "wof:placetype":"postalcode"
},
  "geometry": {"coordinates":[-0.14788403211313,51.55678096452836],"type":"Point"}
}