{
  "type": "Feature",
  "properties": {
    "iso:country": "GB",
    "wof:name": "S74 8HS",
    "wof:placetype": "postalcode"
  },
  "geometry": {"coordinates":[-1.419997,53.497265],"type":"Point"}
}
