{
  "type": "Feature",
  "properties": {
    "iso:country":"GB",
    "wof:name":"S74 8HS",
    "wof:placetype":"postalcode"
},
  "geometry": {"coordinates":[-1.4204325769552,53.4972934647439],"type":"Point"}
}