{
  "type": "Feature",
  "properties": {
    "date:inception_lower": "2000-06-01",
    "date:inception_upper": "2000-06-01",
    "iso:country": "GB",
    "wof:name": "WN3 6LN",
    "wof:placetype": "postalcode"
  },
  "geometry": {"coordinates":[-2.666864,53.514741],"type":"Point"}
}
