{
  "type": "Feature",
  "properties": {
    "iso:country":"GB",
    "wof:name":"SA43 3BX",
    "wof:placetype":"postalcode"
},
  "geometry": {"coordinates":[-4.74910570275272,52.07431068709698],"type":"Point"}
}