{
  "type": "Feature",
  "properties": {
    "iso:country": "GB",
    "wof:name": "SE17 2DA",
    "wof:placetype": "postalcode"
  },
  "geometry": {"coordinates":[-0.089036,51.483287],"type":"Point"}
}
