{
  "type": "Feature",
  "properties": {
    "date:inception_lower": "2015-10-01",
    "date:inception_upper": "2015-10-01",
    "iso:country": "GB",
    "wof:name": "SE17 2DA",
    "wof:placetype": "postalcode"
  },
  "geometry": {"coordinates":[-0.089036,51.483287],"type":"Point"}
}
