{
  "type": "Feature",
  "properties": {
    "iso:country":"GB",
    "wof:name":"UB10 0SU",
    "wof:placetype":"postalcode"
},
  "geometry": {"coordinates":[-0.44050322011885,51.52648701663046],"type":"Point"}
}