{
  "type": "Feature",
  "properties": {
    "iso:country": "GB",
    "wof:name": "N1 6LB",
    "wof:placetype": "postalcode"
  },
  "geometry": {"coordinates":[-0.080287,51.529319],"type":"Point"}
}
