{
  "type": "Feature",
  "properties": {
    "iso:country":"GB",
    "wof:name":"W9 2EX",
    "wof:placetype":"postalcode"
},
  "geometry": {"coordinates":[-0.1968373799132,51.52778763190143],"type":"Point"}
}