{
  "type": "Feature",
  "properties": {
    "iso:country":"GB",
    "wof:name":"OL11 3JA",
    "wof:placetype":"postalcode"
},
  "geometry": {"coordinates":[-2.18456961182091,53.5965722052051],"type":"Point"}
}