{
  "type": "Feature",
  "properties": {
    "iso:country":"GB",
    "wof:name":"BR1 3AE",
    "wof:placetype":"postalcode"
},
  "geometry": {"coordinates":[0.02946730290799,51.40687861505292],"type":"Point"}
}