{
  "type": "Feature",
  "properties": {
    "iso:country": "GB",
    "wof:name": "BR1 3AE",
    "wof:placetype": "postalcode"
  },
  "geometry": {"coordinates":[0.029467,51.406879],"type":"Point"}
}
