{
  "type": "Feature",
  "properties": {
    "date:inception_lower":"1991-09-01",
    "date:inception_upper":"1991-09-30",
    "iso:country":"GB",
    "wof:name":"NR17 2RE",
    "wof:placetype":"postalcode"
},
  "geometry": {"coordinates":[1.011732,52.517317],"type":"Point"}
}