{
  "type": "Feature",
  "properties": {
    "iso:country":"GB",
    "wof:name":"CH7 2AU",
    "wof:placetype":"postalcode"
},
  "geometry": {"coordinates":[-3.07427489743994,53.16468590114572],"type":"Point"}
}