{
  "type": "Feature",
  "properties": {
    "date:inception_lower": "2023-03-01",
    "date:inception_upper": "2023-03-01",
    "iso:country": "GB",
    "wof:name": "WN7 5GJ",
    "wof:placetype": "postalcode"
  },
  "geometry": {"coordinates":[-2.524693,53.514261],"type":"Point"}
}
