{
  "type": "Feature",
  "properties": {
    "date:inception_lower": "2017-06-01",
    "date:inception_upper": "2017-06-01",
    "iso:country": "GB",
    "wof:name": "GL2 9NQ",
    "wof:placetype": "postalcode"
  },
  "geometry": {"coordinates":[-2.206954,51.916055],"type":"Point"}
}
