{
  "type": "Feature",
  "properties": {
    "iso:country": "GB",
    "wof:name": "L33 1RY",
    "wof:placetype": "postalcode"
  },
  "geometry": {"coordinates":[-2.87628,53.497416],"type":"Point"}
}
