{
  "type": "Feature",
  "properties": {
    "date:inception_lower": "1980-01-01",
    "date:inception_upper": "1980-01-01",
    "iso:country": "GB",
    "wof:name": "TS18 4EJ",
    "wof:placetype": "postalcode"
  },
  "geometry": {"coordinates":[-1.331993,54.554867],"type":"Point"}
}
