{
  "type": "Feature",
  "properties": {
    "iso:country": "GB",
    "wof:name": "LL29 8ER",
    "wof:placetype": "postalcode"
  },
  "geometry": {"coordinates":[-3.721198,53.293326],"type":"Point"}
}
