{
  "type": "Feature",
  "properties": {
    "iso:country":"GB",
    "wof:name":"LL29 8ER",
    "wof:placetype":"postalcode"
},
  "geometry": {"coordinates":[-3.72119816128509,53.29332568327762],"type":"Point"}
}