{
  "type": "Feature",
  "properties": {
    "date:inception_lower": "2003-10-01",
    "date:inception_upper": "2003-10-01",
    "iso:country": "GB",
    "wof:name": "ST7 4GP",
    "wof:placetype": "postalcode"
  },
  "geometry": {"coordinates":[-2.22077,53.084939],"type":"Point"}
}
