{
  "type": "Feature",
  "properties": {
    "iso:country":"GB",
    "wof:name":"ST7 4GP",
    "wof:placetype":"postalcode"
},
  "geometry": {"coordinates":[-2.22076973049452,53.08493886595623],"type":"Point"}
}