{
  "type": "Feature",
  "properties": {
    "iso:country":"GB",
    "wof:name":"DY3 3NT",
    "wof:placetype":"postalcode"
},
  "geometry": {"coordinates":[-2.13064505771803,52.53873783966],"type":"Point"}
}