{
  "type": "Feature",
  "properties": {
    "date:inception_lower": "1990-02-01",
    "date:inception_upper": "1990-02-01",
    "iso:country": "GB",
    "wof:name": "KT6 7JH",
    "wof:placetype": "postalcode"
  },
  "geometry": {"coordinates":[-0.280638,51.380103],"type":"Point"}
}
