{
  "type": "Feature",
  "properties": {
    "iso:country":"GB",
    "wof:name":"GU22 8LQ",
    "wof:placetype":"postalcode"
},
  "geometry": {"coordinates":[-0.53034517647273,51.32414363421584],"type":"Point"}
}