{
  "type": "Feature",
  "properties": {
    "iso:country": "GB",
    "wof:name": "G33 6FY",
    "wof:placetype": "postalcode"
  },
  "geometry": {"coordinates":[-4.143555,55.884501],"type":"Point"}
}
