{
  "type": "Feature",
  "properties": {
    "date:inception_lower": "2014-06-01",
    "date:inception_upper": "2014-06-01",
    "iso:country": "GB",
    "wof:name": "G33 6FY",
    "wof:placetype": "postalcode"
  },
  "geometry": {"coordinates":[-4.143555,55.88451],"type":"Point"}
}
