{
  "type": "Feature",
  "properties": {
    "iso:country":"GB",
    "wof:name":"G33 6FY",
    "wof:placetype":"postalcode"
},
  "geometry": {"coordinates":[-4.14356753085728,55.88450585525176],"type":"Point"}
}