{
  "type": "Feature",
  "properties": {
    "date:inception_lower":"2014-06-01",
    "date:inception_upper":"2014-06-30",
    "iso:country":"GB",
    "wof:name":"G33 6FY",
    "wof:placetype":"postalcode"
},
  "geometry": {"coordinates":[-4.143555,55.884501],"type":"Point"}
}