{
  "type": "Feature",
  "properties": {
    "date:inception_lower":"1990-02-01",
    "date:inception_upper":"1990-02-28",
    "iso:country":"GB",
    "wof:name":"BA2 4JN",
    "wof:placetype":"postalcode"
},
  "geometry": {"coordinates":[-2.353666,51.378963],"type":"Point"}
}