{
  "type": "Feature",
  "properties": {
    "iso:country":"GB",
    "wof:name":"BA2 4JN",
    "wof:placetype":"postalcode"
},
  "geometry": {"coordinates":[-2.35366593976793,51.37896253565974],"type":"Point"}
}