{
  "type": "Feature",
  "properties": {
    "date:inception_lower": "1994-12-01",
    "date:inception_upper": "1994-12-01",
    "iso:country": "GB",
    "wof:name": "L3 6LG",
    "wof:placetype": "postalcode"
  },
  "geometry": {"coordinates":[-2.99098,53.418396],"type":"Point"}
}
