{
  "type": "Feature",
  "properties": {
    "iso:country": "GB",
    "wof:name": "KT21 1DT",
    "wof:placetype": "postalcode"
  },
  "geometry": {"coordinates":[-0.295664,51.309273],"type":"Point"}
}
