{
  "type": "Feature",
  "properties": {
    "date:inception_lower":"2010-02-01",
    "date:inception_upper":"2010-02-28",
    "iso:country":"GB",
    "wof:name":"KT21 1DT",
    "wof:placetype":"postalcode"
},
  "geometry": {"coordinates":[-0.295664,51.309273],"type":"Point"}
}