{
  "type": "Feature",
  "properties": {
    "iso:country":"GB",
    "wof:name":"NG21 9BA",
    "wof:placetype":"postalcode"
},
  "geometry": {"coordinates":[-1.10974021613018,53.16503018598224],"type":"Point"}
}