{
  "type": "Feature",
  "properties": {
    "iso:country":"GB",
    "wof:name":"BB4 4RS",
    "wof:placetype":"postalcode"
},
  "geometry": {"coordinates":[-2.323433830496,53.69240626673268],"type":"Point"}
}