{
  "type": "Feature",
  "properties": {
    "date:inception_lower":"1998-06-01",
    "date:inception_upper":"1998-06-30",
    "iso:country":"GB",
    "wof:name":"BB4 4RS",
    "wof:placetype":"postalcode"
},
  "geometry": {"coordinates":[-2.324643,53.692257],"type":"Point"}
}