{
  "type": "Feature",
  "properties": {
    "iso:country": "GB",
    "wof:name": "S44 6PP",
    "wof:placetype": "postalcode"
  },
  "geometry": {"coordinates":[-1.293753,53.229627],"type":"Point"}
}
