{
  "type": "Feature",
  "properties": {
    "iso:country": "GB",
    "wof:name": "LS14 3JQ",
    "wof:placetype": "postalcode"
  },
  "geometry": {"coordinates":[-1.466981,53.866846],"type":"Point"}
}
