{
  "type": "Feature",
  "properties": {
    "iso:country": "GB",
    "wof:name": "PE6 8PN",
    "wof:placetype": "postalcode"
  },
  "geometry": {"coordinates":[-0.295686,52.67241],"type":"Point"}
}
