{
  "type": "Feature",
  "properties": {
    "iso:country":"GB",
    "wof:name":"PE6 8PN",
    "wof:placetype":"postalcode"
},
  "geometry": {"coordinates":[-0.29568587054018,52.67241025572925],"type":"Point"}
}