{
  "type": "Feature",
  "properties": {
    "date:inception_lower": "2018-01-01",
    "date:inception_upper": "2018-01-01",
    "iso:country": "GB",
    "wof:name": "NG24 2UB",
    "wof:placetype": "postalcode"
  },
  "geometry": {"coordinates":[-0.784669,53.074314],"type":"Point"}
}
