{
  "type": "Feature",
  "properties": {
    "iso:country": "GB",
    "wof:name": "CO2 7JW",
    "wof:placetype": "postalcode"
  },
  "geometry": {"coordinates":[0.882734,51.876087],"type":"Point"}
}
