{
  "type": "Feature",
  "properties": {
    "date:inception_lower":"1980-01-01",
    "date:inception_upper":"1980-01-31",
    "iso:country":"GB",
    "wof:name":"CO2 7JW",
    "wof:placetype":"postalcode"
},
  "geometry": {"coordinates":[0.882734,51.876087],"type":"Point"}
}