{
  "type": "Feature",
  "properties": {
    "iso:country": "GB",
    "wof:name": "TD5 8BY",
    "wof:placetype": "postalcode"
  },
  "geometry": {"coordinates":[-2.300978,55.55648],"type":"Point"}
}
