{
  "type": "Feature",
  "properties": {
    "iso:country":"GB",
    "wof:name":"TD5 8BY",
    "wof:placetype":"postalcode"
},
  "geometry": {"coordinates":[-2.30097831445993,55.55648010259673],"type":"Point"}
}