{
  "type": "Feature",
  "properties": {
    "date:inception_lower": "2019-06-01",
    "date:inception_upper": "2019-06-01",
    "iso:country": "GB",
    "wof:name": "DN14 7UR",
    "wof:placetype": "postalcode"
  },
  "geometry": {"coordinates":[-0.758425,53.704167],"type":"Point"}
}
