{
  "type": "Feature",
  "properties": {
    "iso:country":"GB",
    "wof:name":"EX15 3NW",
    "wof:placetype":"postalcode"
},
  "geometry": {"coordinates":[-3.29958175900371,50.89218538577823],"type":"Point"}
}