{
  "type": "Feature",
  "properties": {
    "iso:country":"GB",
    "wof:name":"PL8 2FD",
    "wof:placetype":"postalcode"
},
  "geometry": {"coordinates":[-4.0501085230001,50.35267672454044],"type":"Point"}
}