{
  "type": "Feature",
  "properties": {
    "iso:country": "GB",
    "wof:name": "PL8 2FD",
    "wof:placetype": "postalcode"
  },
  "geometry": {"coordinates":[-4.050166,50.352688],"type":"Point"}
}
