{
  "type": "Feature",
  "properties": {
    "iso:country": "GB",
    "wof:name": "G81 5BD",
    "wof:placetype": "postalcode"
  },
  "geometry": {"coordinates":[-4.3917,55.930381],"type":"Point"}
}
