{
  "type": "Feature",
  "properties": {
    "date:inception_lower": "2004-09-01",
    "date:inception_upper": "2004-09-01",
    "iso:country": "GB",
    "wof:name": "G81 5BD",
    "wof:placetype": "postalcode"
  },
  "geometry": {"coordinates":[-4.3917,55.930381],"type":"Point"}
}
