{
  "type": "Feature",
  "properties": {
    "iso:country":"GB",
    "wof:name":"PR4 6WE",
    "wof:placetype":"postalcode"
},
  "geometry": {"coordinates":[-2.83007744437285,53.67551239562158],"type":"Point"}
}