{
  "type": "Feature",
  "properties": {
    "iso:country":"GB",
    "wof:name":"FK10 2FD",
    "wof:placetype":"postalcode"
},
  "geometry": {"coordinates":[-3.81295398887589,56.12310598164116],"type":"Point"}
}