{
  "type": "Feature",
  "properties": {
    "date:inception_lower": "2012-11-01",
    "date:inception_upper": "2012-11-01",
    "iso:country": "GB",
    "wof:name": "FK10 2FD",
    "wof:placetype": "postalcode"
  },
  "geometry": {"coordinates":[-3.813383,56.123147],"type":"Point"}
}
