{
  "type": "Feature",
  "properties": {
    "date:inception_lower": "1999-06-01",
    "date:inception_upper": "1999-06-01",
    "iso:country": "GB",
    "wof:name": "CF3 5HW",
    "wof:placetype": "postalcode"
  },
  "geometry": {"coordinates":[-3.12516,51.521039],"type":"Point"}
}
