{
  "type": "Feature",
  "properties": {
    "date:inception_lower": "2009-02-01",
    "date:inception_upper": "2009-02-01",
    "iso:country": "GB",
    "wof:name": "SK8 3GZ",
    "wof:placetype": "postalcode"
  },
  "geometry": {"coordinates":[-2.216847,53.373011],"type":"Point"}
}
