{
  "type": "Feature",
  "properties": {
    "iso:country":"GB",
    "wof:name":"SK8 3GZ",
    "wof:placetype":"postalcode"
},
  "geometry": {"coordinates":[-2.21684733721381,53.37301126734133],"type":"Point"}
}