{
  "type": "Feature",
  "properties": {
    "date:inception_lower": "1997-12-01",
    "date:inception_upper": "1997-12-01",
    "iso:country": "GB",
    "wof:name": "BS40 7XE",
    "wof:placetype": "postalcode"
  },
  "geometry": {"coordinates":[-2.691581,51.343588],"type":"Point"}
}
