{
  "type": "Feature",
  "properties": {
    "iso:country": "GB",
    "wof:name": "BS40 7XE",
    "wof:placetype": "postalcode"
  },
  "geometry": {"coordinates":[-2.69211,51.343678],"type":"Point"}
}
