{
  "type": "Feature",
  "properties": {
    "iso:country": "GB",
    "wof:name": "G74 4HY",
    "wof:placetype": "postalcode"
  },
  "geometry": {"coordinates":[-4.172446,55.765403],"type":"Point"}
}
