{
  "type": "Feature",
  "properties": {
    "iso:country":"GB",
    "wof:name":"S70 2BP",
    "wof:placetype":"postalcode"
},
  "geometry": {"coordinates":[-1.48563686788675,53.55769757342484],"type":"Point"}
}