{
  "type": "Feature",
  "properties": {
    "iso:country": "GB",
    "wof:name": "TN25 7ES",
    "wof:placetype": "postalcode"
  },
  "geometry": {"coordinates":[0.939008,51.085107],"type":"Point"}
}
