{
  "type": "Feature",
  "properties": {
    "iso:country":"GB",
    "wof:name":"DA5 3NA",
    "wof:placetype":"postalcode"
},
  "geometry": {"coordinates":[0.14991391555018,51.43708732129193],"type":"Point"}
}