{
  "type": "Feature",
  "properties": {
    "iso:country": "GB",
    "wof:name": "DA5 3NA",
    "wof:placetype": "postalcode"
  },
  "geometry": {"coordinates":[0.149914,51.437087],"type":"Point"}
}
