{
  "type": "Feature",
  "properties": {
    "iso:country":"GB",
    "wof:name":"EX10 0BW",
    "wof:placetype":"postalcode"
},
  "geometry": {"coordinates":[-3.31216285556424,50.69909923840748],"type":"Point"}
}