{
  "type": "Feature",
  "properties": {
    "iso:country":"GB",
    "wof:name":"LE12 8RB",
    "wof:placetype":"postalcode"
},
  "geometry": {"coordinates":[-1.17413788439872,52.7514024182918],"type":"Point"}
}