{
  "type": "Feature",
  "properties": {
    "date:inception_lower":"1991-01-01",
    "date:inception_upper":"1991-01-31",
    "iso:country":"GB",
    "wof:name":"LE12 8RB",
    "wof:placetype":"postalcode"
},
  "geometry": {"coordinates":[-1.174138,52.751402],"type":"Point"}
}