{
  "type": "Feature",
  "properties": {
    "iso:country": "GB",
    "wof:name": "LE12 8RB",
    "wof:placetype": "postalcode"
  },
  "geometry": {"coordinates":[-1.174138,52.751402],"type":"Point"}
}
