{
  "type": "Feature",
  "properties": {
    "iso:country":"GB",
    "wof:name":"SL4 2QB",
    "wof:placetype":"postalcode"
},
  "geometry": {"coordinates":[-0.58693039510856,51.4619354954521],"type":"Point"}
}