{
  "type": "Feature",
  "properties": {
    "iso:country": "GB",
    "wof:name": "RH11 7RP",
    "wof:placetype": "postalcode"
  },
  "geometry": {"coordinates":[-0.196131,51.113694],"type":"Point"}
}
