{
  "type": "Feature",
  "properties": {
    "iso:country":"GB",
    "wof:name":"RG4 8TY",
    "wof:placetype":"postalcode"
},
  "geometry": {"coordinates":[-0.96181447256811,51.48107661202287],"type":"Point"}
}