{
  "type": "Feature",
  "properties": {
    "iso:country":"GB",
    "wof:name":"E6 3DD",
    "wof:placetype":"postalcode"
},
  "geometry": {"coordinates":[0.03968939865299,51.52984830693818],"type":"Point"}
}