{
  "type": "Feature",
  "properties": {
    "date:inception_lower": "1980-01-01",
    "date:inception_upper": "1980-01-01",
    "iso:country": "GB",
    "wof:name": "E6 3DD",
    "wof:placetype": "postalcode"
  },
  "geometry": {"coordinates":[0.039689,51.529848],"type":"Point"}
}
