{
  "type": "Feature",
  "properties": {
    "iso:country": "GB",
    "wof:name": "BD22 9RF",
    "wof:placetype": "postalcode"
  },
  "geometry": {"coordinates":[-1.97197,53.821608],"type":"Point"}
}
