{
  "type": "Feature",
  "properties": {
    "iso:country":"GB",
    "wof:name":"RG27 9UT",
    "wof:placetype":"postalcode"
},
  "geometry": {"coordinates":[-0.95932322403951,51.27827649801642],"type":"Point"}
}