{
  "type": "Feature",
  "properties": {
    "iso:country":"GB",
    "wof:name":"S81 0PN",
    "wof:placetype":"postalcode"
},
  "geometry": {"coordinates":[-1.11286600842578,53.32450210312742],"type":"Point"}
}