{
  "type": "Feature",
  "properties": {
    "iso:country":"GB",
    "wof:name":"NN18 9HH",
    "wof:placetype":"postalcode"
},
  "geometry": {"coordinates":[-0.7160565197116,52.47964179295508],"type":"Point"}
}