{
  "type": "Feature",
  "properties": {
    "iso:country":"GB",
    "wof:name":"IG2 7NG",
    "wof:placetype":"postalcode"
},
  "geometry": {"coordinates":[0.08689608729435,51.57876567089185],"type":"Point"}
}