{
  "type": "Feature",
  "properties": {
    "iso:country":"GB",
    "wof:name":"NG2 3HZ",
    "wof:placetype":"postalcode"
},
  "geometry": {"coordinates":[-1.13753409880987,52.94070724338983],"type":"Point"}
}