{
  "type": "Feature",
  "properties": {
    "iso:country": "GB",
    "wof:name": "NG2 3HZ",
    "wof:placetype": "postalcode"
  },
  "geometry": {"coordinates":[-1.137534,52.940707],"type":"Point"}
}
