{
  "type": "Feature",
  "properties": {
    "iso:country": "GB",
    "wof:name": "TQ2 8BY",
    "wof:placetype": "postalcode"
  },
  "geometry": {"coordinates":[-3.530928,50.494122],"type":"Point"}
}
