{
  "type": "Feature",
  "properties": {
    "iso:country":"GB",
    "wof:name":"SW7 4SF",
    "wof:placetype":"postalcode"
},
  "geometry": {"coordinates":[-0.18333770937112,51.49460398909999],"type":"Point"}
}