{
  "type": "Feature",
  "properties": {
    "date:inception_lower": "2014-11-01",
    "date:inception_upper": "2014-11-01",
    "iso:country": "GB",
    "wof:name": "PL23 1DW",
    "wof:placetype": "postalcode"
  },
  "geometry": {"coordinates":[-4.651387,50.338415],"type":"Point"}
}
