{
  "type": "Feature",
  "properties": {
    "iso:country":"GB",
    "wof:name":"PL23 1DW",
    "wof:placetype":"postalcode"
},
  "geometry": {"coordinates":[-4.6517145376779,50.33821351200152],"type":"Point"}
}