{
  "type": "Feature",
  "properties": {
    "date:inception_lower":"1980-01-01",
    "date:inception_upper":"1980-01-31",
    "iso:country":"GB",
    "wof:name":"EH23 4NW",
    "wof:placetype":"postalcode"
},
  "geometry": {"coordinates":[-3.013864,55.84414],"type":"Point"}
}