{
  "type": "Feature",
  "properties": {
    "date:inception_lower":"1980-01-01",
    "date:inception_upper":"1980-01-31",
    "iso:country":"GB",
    "wof:name":"SM5 1DP",
    "wof:placetype":"postalcode"
},
  "geometry": {"coordinates":[-0.168082,51.384181],"type":"Point"}
}