{
  "type": "Feature",
  "properties": {
    "iso:country": "GB",
    "wof:name": "WA8 6PB",
    "wof:placetype": "postalcode"
  },
  "geometry": {"coordinates":[-2.731874,53.36922],"type":"Point"}
}
