{
  "type": "Feature",
  "properties": {
    "iso:country":"GB",
    "wof:name":"WA8 6PB",
    "wof:placetype":"postalcode"
},
  "geometry": {"coordinates":[-2.73187431722734,53.36921975093368],"type":"Point"}
}