{
  "type": "Feature",
  "properties": {
    "iso:country":"GB",
    "wof:name":"HU5 5DW",
    "wof:placetype":"postalcode"
},
  "geometry": {"coordinates":[-0.39345978318183,53.75614302348608],"type":"Point"}
}