{
  "type": "Feature",
  "properties": {
    "iso:country": "GB",
    "wof:name": "HU5 5DW",
    "wof:placetype": "postalcode"
  },
  "geometry": {"coordinates":[-0.39346,53.756143],"type":"Point"}
}
