{
  "type": "Feature",
  "properties": {
    "iso:country": "GB",
    "wof:name": "TN11 8RS",
    "wof:placetype": "postalcode"
  },
  "geometry": {"coordinates":[0.211995,51.195328],"type":"Point"}
}
