{
  "type": "Feature",
  "properties": {
    "date:inception_lower": "1980-01-01",
    "date:inception_upper": "1980-01-01",
    "iso:country": "GB",
    "wof:name": "TN11 8RS",
    "wof:placetype": "postalcode"
  },
  "geometry": {"coordinates":[0.211995,51.195328],"type":"Point"}
}
