{
  "type": "Feature",
  "properties": {
    "iso:country":"GB",
    "wof:name":"TN11 8RS",
    "wof:placetype":"postalcode"
},
  "geometry": {"coordinates":[0.21199462330364,51.19532773354666],"type":"Point"}
}