{
  "type": "Feature",
  "properties": {
    "iso:country":"GB",
    "wof:name":"S71 4ET",
    "wof:placetype":"postalcode"
},
  "geometry": {"coordinates":[-1.45650770482651,53.59966153130738],"type":"Point"}
}