{
  "type": "Feature",
  "properties": {
    "iso:country": "GB",
    "wof:name": "S71 4ET",
    "wof:placetype": "postalcode"
  },
  "geometry": {"coordinates":[-1.456508,53.599662],"type":"Point"}
}
