{
  "type": "Feature",
  "properties": {
    "iso:country":"GB",
    "wof:name":"ST16 3WA",
    "wof:placetype":"postalcode"
},
  "geometry": {"coordinates":[-2.10390754126209,52.81553805402887],"type":"Point"}
}