{
  "type": "Feature",
  "properties": {
    "iso:country": "GB",
    "wof:name": "DN33 1JQ",
    "wof:placetype": "postalcode"
  },
  "geometry": {"coordinates":[-0.111982,53.546986],"type":"Point"}
}
