{
  "type": "Feature",
  "properties": {
    "iso:country":"GB",
    "wof:name":"S7 2DS",
    "wof:placetype":"postalcode"
},
  "geometry": {"coordinates":[-1.49857752568131,53.35530290884087],"type":"Point"}
}