{
  "type": "Feature",
  "properties": {
    "iso:country":"GB",
    "wof:name":"DE4 3GJ",
    "wof:placetype":"postalcode"
},
  "geometry": {"coordinates":[-1.54870652253155,53.14359040087754],"type":"Point"}
}