{
  "type": "Feature",
  "properties": {
    "date:inception_lower": "1986-04-01",
    "date:inception_upper": "1986-04-01",
    "iso:country": "GB",
    "wof:name": "DE4 3GJ",
    "wof:placetype": "postalcode"
  },
  "geometry": {"coordinates":[-1.548706,53.14359],"type":"Point"}
}
