{
  "type": "Feature",
  "properties": {
    "iso:country":"GB",
    "wof:name":"NR5 9LY",
    "wof:placetype":"postalcode"
},
  "geometry": {"coordinates":[1.213019647269,52.63711883301026],"type":"Point"}
}