{
  "type": "Feature",
  "properties": {
    "date:inception_lower":"2003-05-01",
    "date:inception_upper":"2003-05-31",
    "iso:country":"GB",
    "wof:name":"NR5 9LY",
    "wof:placetype":"postalcode"
},
  "geometry": {"coordinates":[1.21302,52.637119],"type":"Point"}
}