{
  "type": "Feature",
  "properties": {
    "iso:country": "GB",
    "wof:name": "NR5 9LY",
    "wof:placetype": "postalcode"
  },
  "geometry": {"coordinates":[1.21302,52.637119],"type":"Point"}
}
