{
  "type": "Feature",
  "properties": {
    "iso:country":"GB",
    "wof:name":"LD2 3AE",
    "wof:placetype":"postalcode"
},
  "geometry": {"coordinates":[-3.40121838490271,52.14959787105738],"type":"Point"}
}