{
  "type": "Feature",
  "properties": {
    "iso:country": "GB",
    "wof:name": "LD2 3AE",
    "wof:placetype": "postalcode"
  },
  "geometry": {"coordinates":[-3.401218,52.149598],"type":"Point"}
}
