{
  "type": "Feature",
  "properties": {
    "iso:country":"GB",
    "wof:name":"OL15 9HH",
    "wof:placetype":"postalcode"
},
  "geometry": {"coordinates":[-2.10025455478314,53.64574844501861],"type":"Point"}
}