{
  "type": "Feature",
  "properties": {
    "date:inception_lower": "2022-08-01",
    "date:inception_upper": "2022-08-01",
    "iso:country": "GB",
    "wof:name": "BH9 2FE",
    "wof:placetype": "postalcode"
  },
  "geometry": {"coordinates":[-1.879771,50.742241],"type":"Point"}
}
