{
  "type": "Feature",
  "properties": {
    "iso:country":"GB",
    "wof:name":"PE9 2DH",
    "wof:placetype":"postalcode"
},
  "geometry": {"coordinates":[-0.47746526957557,52.65092503424231],"type":"Point"}
}