{
  "type": "Feature",
  "properties": {
    "date:inception_lower": "1980-01-01",
    "date:inception_upper": "1980-01-01",
    "iso:country": "GB",
    "wof:name": "PE9 2DH",
    "wof:placetype": "postalcode"
  },
  "geometry": {"coordinates":[-0.477465,52.650925],"type":"Point"}
}
