{
  "type": "Feature",
  "properties": {
    "iso:country":"GB",
    "wof:name":"CR4 1PN",
    "wof:placetype":"postalcode"
},
  "geometry": {"coordinates":[-0.12793099348275,51.39856375633531],"type":"Point"}
}