{
  "type": "Feature",
  "properties": {
    "date:inception_lower": "2002-05-01",
    "date:inception_upper": "2002-05-01",
    "iso:country": "GB",
    "wof:name": "CR4 1PN",
    "wof:placetype": "postalcode"
  },
  "geometry": {"coordinates":[-0.127931,51.398564],"type":"Point"}
}
