{
  "type": "Feature",
  "properties": {
    "date:inception_lower": "1980-01-01",
    "date:inception_upper": "1980-01-01",
    "iso:country": "GB",
    "wof:name": "NG7 1FL",
    "wof:placetype": "postalcode"
  },
  "geometry": {"coordinates":[-1.155255,52.948449],"type":"Point"}
}
