{
  "type": "Feature",
  "properties": {
    "iso:country": "GB",
    "wof:name": "NG7 1FL",
    "wof:placetype": "postalcode"
  },
  "geometry": {"coordinates":[-1.155255,52.948449],"type":"Point"}
}
