{
  "type": "Feature",
  "properties": {
    "iso:country": "GB",
    "wof:name": "OX2 8AG",
    "wof:placetype": "postalcode"
  },
  "geometry": {"coordinates":[-1.279274,51.785748],"type":"Point"}
}
