{
  "type": "Feature",
  "properties": {
    "iso:country":"GB",
    "wof:name":"OX2 8AG",
    "wof:placetype":"postalcode"
},
  "geometry": {"coordinates":[-1.2792739012361,51.78574806739125],"type":"Point"}
}