{
  "type": "Feature",
  "properties": {
    "date:inception_lower":"1980-01-01",
    "date:inception_upper":"1980-01-31",
    "iso:country":"GB",
    "wof:name":"OX2 8AG",
    "wof:placetype":"postalcode"
},
  "geometry": {"coordinates":[-1.279274,51.785748],"type":"Point"}
}