{
  "type": "Feature",
  "properties": {
    "date:inception_lower":"1980-01-01",
    "date:inception_upper":"1980-01-31",
    "iso:country":"GB",
    "wof:name":"LS17 6DU",
    "wof:placetype":"postalcode"
},
  "geometry": {"coordinates":[-1.527827,53.846365],"type":"Point"}
}