{
  "type": "Feature",
  "properties": {
    "iso:country":"GB",
    "wof:name":"LS17 6DU",
    "wof:placetype":"postalcode"
},
  "geometry": {"coordinates":[-1.52782662809178,53.8463654201464],"type":"Point"}
}