{
  "type": "Feature",
  "properties": {
    "date:inception_lower": "2023-05-01",
    "date:inception_upper": "2023-05-01",
    "iso:country": "GB",
    "wof:name": "MK10 9XG",
    "wof:placetype": "postalcode"
  },
  "geometry": {"coordinates":[-0.703448,52.047469],"type":"Point"}
}
