{
  "type": "Feature",
  "properties": {
    "iso:country":"GB",
    "wof:name":"GL51 8NW",
    "wof:placetype":"postalcode"
},
  "geometry": {"coordinates":[-2.10010032719726,51.89774584645117],"type":"Point"}
}