{
  "type": "Feature",
  "properties": {
    "date:inception_lower":"1990-02-01",
    "date:inception_upper":"1990-02-28",
    "iso:country":"GB",
    "wof:name":"S6 6FE",
    "wof:placetype":"postalcode"
},
  "geometry": {"coordinates":[-1.544849,53.396468],"type":"Point"}
}