{
  "type": "Feature",
  "properties": {
    "date:inception_lower": "2009-11-01",
    "date:inception_upper": "2009-11-01",
    "iso:country": "GB",
    "wof:name": "PL6 8BN",
    "wof:placetype": "postalcode"
  },
  "geometry": {"coordinates":[-4.09464,50.407171],"type":"Point"}
}
