{
  "type": "Feature",
  "properties": {
    "iso:country":"GB",
    "wof:name":"PL6 8BN",
    "wof:placetype":"postalcode"
},
  "geometry": {"coordinates":[-4.09463959290521,50.40717086079807],"type":"Point"}
}