{
  "type": "Feature",
  "properties": {
    "iso:country": "GB",
    "wof:name": "PL6 8BN",
    "wof:placetype": "postalcode"
  },
  "geometry": {"coordinates":[-4.09464,50.407171],"type":"Point"}
}
