{
  "type": "Feature",
  "properties": {
    "iso:country":"GB",
    "wof:name":"TA7 0HY",
    "wof:placetype":"postalcode"
},
  "geometry": {"coordinates":[-2.96696689905107,51.12775409469639],"type":"Point"}
}