{
  "type": "Feature",
  "properties": {
    "iso:country":"GB",
    "wof:name":"NE40 4PG",
    "wof:placetype":"postalcode"
},
  "geometry": {"coordinates":[-1.79186865273277,54.96765573333518],"type":"Point"}
}