{
  "type": "Feature",
  "properties": {
    "date:inception_lower": "1980-01-01",
    "date:inception_upper": "1980-01-01",
    "iso:country": "GB",
    "wof:name": "NE40 4PG",
    "wof:placetype": "postalcode"
  },
  "geometry": {"coordinates":[-1.791869,54.967656],"type":"Point"}
}
