{
  "type": "Feature",
  "properties": {
    "date:inception_lower": "1980-01-01",
    "date:inception_upper": "1980-01-01",
    "iso:country": "GB",
    "wof:name": "LE16 9LD",
    "wof:placetype": "postalcode"
  },
  "geometry": {"coordinates":[-0.928267,52.468233],"type":"Point"}
}
