{
  "type": "Feature",
  "properties": {
    "iso:country":"GB",
    "wof:name":"LE16 9LD",
    "wof:placetype":"postalcode"
},
  "geometry": {"coordinates":[-0.92826746297407,52.46823264212588],"type":"Point"}
}