{
  "type": "Feature",
  "properties": {
    "date:inception_lower": "2021-09-01",
    "date:inception_upper": "2021-09-01",
    "iso:country": "GB",
    "wof:name": "ST14 5FY",
    "wof:placetype": "postalcode"
  },
  "geometry": {"coordinates":[-1.896409,52.908174],"type":"Point"}
}
