{
  "type": "Feature",
  "properties": {
    "iso:country":"GB",
    "wof:name":"DH5 9ND",
    "wof:placetype":"postalcode"
},
  "geometry": {"coordinates":[-1.45859564978274,54.81715787573892],"type":"Point"}
}