{
  "type": "Feature",
  "properties": {
    "iso:country": "GB",
    "wof:name": "DH5 9ND",
    "wof:placetype": "postalcode"
  },
  "geometry": {"coordinates":[-1.458596,54.817158],"type":"Point"}
}
