{
  "type": "Feature",
  "properties": {
    "iso:country": "GB",
    "wof:name": "CO4 5BE",
    "wof:placetype": "postalcode"
  },
  "geometry": {"coordinates":[0.917773,51.923051],"type":"Point"}
}
