{
  "type": "Feature",
  "properties": {
    "date:inception_lower": "2004-04-01",
    "date:inception_upper": "2004-04-01",
    "iso:country": "GB",
    "wof:name": "CO4 5BE",
    "wof:placetype": "postalcode"
  },
  "geometry": {"coordinates":[0.917773,51.923051],"type":"Point"}
}
