{
  "type": "Feature",
  "properties": {
    "date:inception_lower": "1999-06-01",
    "date:inception_upper": "1999-06-01",
    "iso:country": "GB",
    "wof:name": "NP20 2NL",
    "wof:placetype": "postalcode"
  },
  "geometry": {"coordinates":[-2.995335,51.576378],"type":"Point"}
}
