{
  "type": "Feature",
  "properties": {
    "iso:country": "GB",
    "wof:name": "NP20 2NL",
    "wof:placetype": "postalcode"
  },
  "geometry": {"coordinates":[-2.995335,51.576378],"type":"Point"}
}
