{
  "type": "Feature",
  "properties": {
    "iso:country":"GB",
    "wof:name":"CM13 3JJ",
    "wof:placetype":"postalcode"
},
  "geometry": {"coordinates":[0.29849211119069,51.57079147423197],"type":"Point"}
}