{
  "type": "Feature",
  "properties": {
    "iso:country": "GB",
    "wof:name": "CM13 3JJ",
    "wof:placetype": "postalcode"
  },
  "geometry": {"coordinates":[0.298492,51.570791],"type":"Point"}
}
