{
  "type": "Feature",
  "properties": {
    "iso:country": "GB",
    "wof:name": "NR29 4PB",
    "wof:placetype": "postalcode"
  },
  "geometry": {"coordinates":[1.637837,52.703481],"type":"Point"}
}
