{
  "type": "Feature",
  "properties": {
    "iso:country":"GB",
    "wof:name":"ML11 9AG",
    "wof:placetype":"postalcode"
},
  "geometry": {"coordinates":[-3.7737399675606,55.67054392121856],"type":"Point"}
}