{
  "type": "Feature",
  "properties": {
    "date:inception_lower": "1980-01-01",
    "date:inception_upper": "1980-01-01",
    "iso:country": "GB",
    "wof:name": "ML11 9AG",
    "wof:placetype": "postalcode"
  },
  "geometry": {"coordinates":[-3.77374,55.670544],"type":"Point"}
}
