{
  "type": "Feature",
  "properties": {
    "date:inception_lower":"2005-02-01",
    "date:inception_upper":"2005-02-28",
    "iso:country":"GB",
    "wof:name":"S80 9SP",
    "wof:placetype":"postalcode"
},
  "geometry": {"coordinates":[-1.123344,53.301864],"type":"Point"}
}