{
  "type": "Feature",
  "properties": {
    "iso:country":"GB",
    "wof:name":"SN10 2JZ",
    "wof:placetype":"postalcode"
},
  "geometry": {"coordinates":[-1.94822839444658,51.37648248985676],"type":"Point"}
}