{
  "type": "Feature",
  "properties": {
    "iso:country": "GB",
    "wof:name": "DY3 1BQ",
    "wof:placetype": "postalcode"
  },
  "geometry": {"coordinates":[-2.106475,52.533078],"type":"Point"}
}
