{
  "type": "Feature",
  "properties": {
    "iso:country":"GB",
    "wof:name":"DY3 1BQ",
    "wof:placetype":"postalcode"
},
  "geometry": {"coordinates":[-2.10652508339855,52.53299055406278],"type":"Point"}
}