{
  "type": "Feature",
  "properties": {
    "date:inception_lower": "1980-01-01",
    "date:inception_upper": "1980-01-01",
    "iso:country": "GB",
    "wof:name": "IP1 3QP",
    "wof:placetype": "postalcode"
  },
  "geometry": {"coordinates":[1.146177,52.064305],"type":"Point"}
}
