{
  "type": "Feature",
  "properties": {
    "date:inception_lower": "2024-01-01",
    "date:inception_upper": "2024-01-01",
    "iso:country": "GB",
    "wof:name": "LS11 1HU",
    "wof:placetype": "postalcode"
  },
  "geometry": {"coordinates":[-1.550416,53.785395],"type":"Point"}
}
