{
  "type": "Feature",
  "properties": {
    "date:inception_lower":"2011-01-01",
    "date:inception_upper":"2011-01-31",
    "iso:country":"GB",
    "wof:name":"RG20 5WF",
    "wof:placetype":"postalcode"
},
  "geometry": {"coordinates":[-1.322063,51.400071],"type":"Point"}
}