{
  "type": "Feature",
  "properties": {
    "date:inception_lower":"1980-01-01",
    "date:inception_upper":"1980-01-31",
    "iso:country":"GB",
    "wof:name":"PE25 3RB",
    "wof:placetype":"postalcode"
},
  "geometry": {"coordinates":[0.329133,53.141896],"type":"Point"}
}