{
  "type": "Feature",
  "properties": {
    "iso:country": "GB",
    "wof:name": "PE25 3RB",
    "wof:placetype": "postalcode"
  },
  "geometry": {"coordinates":[0.329133,53.141896],"type":"Point"}
}
