{
  "type": "Feature",
  "properties": {
    "iso:country":"GB",
    "wof:name":"TR15 3RP",
    "wof:placetype":"postalcode"
},
  "geometry": {"coordinates":[-5.26601836951367,50.22697531840105],"type":"Point"}
}