{
  "type": "Feature",
  "properties": {
    "date:inception_lower": "2007-09-01",
    "date:inception_upper": "2007-09-01",
    "iso:country": "GB",
    "wof:name": "BL3 1LY",
    "wof:placetype": "postalcode"
  },
  "geometry": {"coordinates":[-2.36678,53.564037],"type":"Point"}
}
