{
  "type": "Feature",
  "properties": {
    "iso:country":"GB",
    "wof:name":"BL3 1LY",
    "wof:placetype":"postalcode"
},
  "geometry": {"coordinates":[-2.36678054550964,53.56403671447477],"type":"Point"}
}