{
  "type": "Feature",
  "properties": {
    "iso:country": "GB",
    "wof:name": "DT3 6PT",
    "wof:placetype": "postalcode"
  },
  "geometry": {"coordinates":[-2.431198,50.636984],"type":"Point"}
}
