{
  "type": "Feature",
  "properties": {
    "date:inception_lower":"1980-01-01",
    "date:inception_upper":"1980-01-31",
    "iso:country":"GB",
    "wof:name":"DT3 6PT",
    "wof:placetype":"postalcode"
},
  "geometry": {"coordinates":[-2.431198,50.636984],"type":"Point"}
}