{
  "type": "Feature",
  "properties": {
    "iso:country":"GB",
    "wof:name":"PL8 2DY",
    "wof:placetype":"postalcode"
},
  "geometry": {"coordinates":[-3.99533987442697,50.34463551354838],"type":"Point"}
}