{
  "type": "Feature",
  "properties": {
    "date:inception_lower": "1980-12-01",
    "date:inception_upper": "1980-12-01",
    "iso:country": "GB",
    "wof:name": "EH54 6PN",
    "wof:placetype": "postalcode"
  },
  "geometry": {"coordinates":[-3.522582,55.873617],"type":"Point"}
}
