{
  "type": "Feature",
  "properties": {
    "iso:country":"GB",
    "wof:name":"S65 1RU",
    "wof:placetype":"postalcode"
},
  "geometry": {"coordinates":[-1.34838509505115,53.4367347578663],"type":"Point"}
}