{
  "type": "Feature",
  "properties": {
    "date:inception_lower": "1994-12-01",
    "date:inception_upper": "1994-12-01",
    "iso:country": "GB",
    "wof:name": "SO50 8LP",
    "wof:placetype": "postalcode"
  },
  "geometry": {"coordinates":[-1.324227,50.965182],"type":"Point"}
}
