{
  "type": "Feature",
  "properties": {
    "iso:country": "GB",
    "wof:name": "SO50 8LP",
    "wof:placetype": "postalcode"
  },
  "geometry": {"coordinates":[-1.324227,50.965182],"type":"Point"}
}
