{
  "type": "Feature",
  "properties": {
    "iso:country": "GB",
    "wof:name": "LS29 6LG",
    "wof:placetype": "postalcode"
  },
  "geometry": {"coordinates":[-1.739225,53.889523],"type":"Point"}
}
