{
  "type": "Feature",
  "properties": {
    "iso:country":"GB",
    "wof:name":"LS29 6LG",
    "wof:placetype":"postalcode"
},
  "geometry": {"coordinates":[-1.73922504938439,53.88952322557413],"type":"Point"}
}