{
  "type": "Feature",
  "properties": {
    "iso:country":"GB",
    "wof:name":"SA43 2PG",
    "wof:placetype":"postalcode"
},
  "geometry": {"coordinates":[-4.60886174984741,52.04964069923611],"type":"Point"}
}