{
  "type": "Feature",
  "properties": {
    "iso:country": "GB",
    "wof:name": "SA43 2PG",
    "wof:placetype": "postalcode"
  },
  "geometry": {"coordinates":[-4.608862,52.049641],"type":"Point"}
}
