{
  "type": "Feature",
  "properties": {
    "date:inception_lower": "2012-07-01",
    "date:inception_upper": "2012-07-01",
    "iso:country": "GB",
    "wof:name": "TN38 8DZ",
    "wof:placetype": "postalcode"
  },
  "geometry": {"coordinates":[0.515867,50.847617],"type":"Point"}
}
