{
  "type": "Feature",
  "properties": {
    "date:inception_lower": "1997-12-01",
    "date:inception_upper": "1997-12-01",
    "iso:country": "GB",
    "wof:name": "SS13 1LQ",
    "wof:placetype": "postalcode"
  },
  "geometry": {"coordinates":[0.516077,51.584695],"type":"Point"}
}
