{
  "type": "Feature",
  "properties": {
    "iso:country": "GB",
    "wof:name": "ST7 2DR",
    "wof:placetype": "postalcode"
  },
  "geometry": {"coordinates":[-2.300629,53.099874],"type":"Point"}
}
