{
  "type": "Feature",
  "properties": {
    "date:inception_lower": "1980-01-01",
    "date:inception_upper": "1980-01-01",
    "iso:country": "GB",
    "wof:name": "ST7 2DR",
    "wof:placetype": "postalcode"
  },
  "geometry": {"coordinates":[-2.300629,53.099874],"type":"Point"}
}
