{
  "type": "Feature",
  "properties": {
    "date:inception_lower":"1980-01-01",
    "date:inception_upper":"1980-01-31",
    "iso:country":"GB",
    "wof:name":"BL6 7EQ",
    "wof:placetype":"postalcode"
},
  "geometry": {"coordinates":[-2.54307,53.603407],"type":"Point"}
}