{
  "type": "Feature",
  "properties": {
    "iso:country":"GB",
    "wof:name":"BL6 7EQ",
    "wof:placetype":"postalcode"
},
  "geometry": {"coordinates":[-2.54307124595997,53.60339122973121],"type":"Point"}
}