{
  "type": "Feature",
  "properties": {
    "iso:country": "GB",
    "wof:name": "ME16 9HE",
    "wof:placetype": "postalcode"
  },
  "geometry": {"coordinates":[0.47109,51.26549],"type":"Point"}
}
