{
  "type": "Feature",
  "properties": {
    "iso:country":"GB",
    "wof:name":"ME16 9HE",
    "wof:placetype":"postalcode"
},
  "geometry": {"coordinates":[0.47108982677889,51.26548975855423],"type":"Point"}
}