{
  "type": "Feature",
  "properties": {
    "date:inception_lower":"1980-01-01",
    "date:inception_upper":"1980-01-31",
    "iso:country":"GB",
    "wof:name":"BS7 8EJ",
    "wof:placetype":"postalcode"
},
  "geometry": {"coordinates":[-2.592428,51.472581],"type":"Point"}
}