{
  "type": "Feature",
  "properties": {
    "iso:country":"GB",
    "wof:name":"BS7 8EJ",
    "wof:placetype":"postalcode"
},
  "geometry": {"coordinates":[-2.59206597648486,51.47258351880027],"type":"Point"}
}