{
  "type": "Feature",
  "properties": {
    "date:inception_lower": "1980-01-01",
    "date:inception_upper": "1980-01-01",
    "iso:country": "GB",
    "wof:name": "BS7 8EJ",
    "wof:placetype": "postalcode"
  },
  "geometry": {"coordinates":[-2.592068,51.472582],"type":"Point"}
}
