{
  "type": "Feature",
  "properties": {
    "iso:country":"GB",
    "wof:name":"SA31 3HE",
    "wof:placetype":"postalcode"
},
  "geometry": {"coordinates":[-4.33044739551191,51.85481948062803],"type":"Point"}
}