{
  "type": "Feature",
  "properties": {
    "iso:country":"GB",
    "wof:name":"RM3 9AA",
    "wof:placetype":"postalcode"
},
  "geometry": {"coordinates":[0.22169297295439,51.61256793156607],"type":"Point"}
}