{
  "type": "Feature",
  "properties": {
    "date:inception_lower": "1980-01-01",
    "date:inception_upper": "1980-01-01",
    "iso:country": "GB",
    "wof:name": "NG2 7PL",
    "wof:placetype": "postalcode"
  },
  "geometry": {"coordinates":[-1.133396,52.935393],"type":"Point"}
}
