{
  "type": "Feature",
  "properties": {
    "iso:country": "GB",
    "wof:name": "NG2 7PL",
    "wof:placetype": "postalcode"
  },
  "geometry": {"coordinates":[-1.133397,52.93534],"type":"Point"}
}
