{
  "type": "Feature",
  "properties": {
    "iso:country": "GB",
    "wof:name": "PO18 8PL",
    "wof:placetype": "postalcode"
  },
  "geometry": {"coordinates":[-0.87357,50.841373],"type":"Point"}
}
