{
  "type": "Feature",
  "properties": {
    "iso:country":"GB",
    "wof:name":"DD1 2JF",
    "wof:placetype":"postalcode"
},
  "geometry": {"coordinates":[-2.9671274133144,56.4639734724108],"type":"Point"}
}