{
  "type": "Feature",
  "properties": {
    "iso:country":"GB",
    "wof:name":"SA62 4JR",
    "wof:placetype":"postalcode"
},
  "geometry": {"coordinates":[-4.91407391922274,51.74172662555234],"type":"Point"}
}