{
  "type": "Feature",
  "properties": {
    "iso:country":"GB",
    "wof:name":"E20 1BE",
    "wof:placetype":"postalcode"
},
  "geometry": {"coordinates":[-0.00465014847335,51.54752609926374],"type":"Point"}
}