{
  "type": "Feature",
  "properties": {
    "iso:country": "GB",
    "wof:name": "E20 1BE",
    "wof:placetype": "postalcode"
  },
  "geometry": {"coordinates":[-0.00465,51.547526],"type":"Point"}
}
