{
  "type": "Feature",
  "properties": {
    "date:inception_lower": "2014-02-01",
    "date:inception_upper": "2014-02-01",
    "iso:country": "GB",
    "wof:name": "E20 1BE",
    "wof:placetype": "postalcode"
  },
  "geometry": {"coordinates":[-0.00465,51.547526],"type":"Point"}
}
