{
  "type": "Feature",
  "properties": {
    "iso:country":"GB",
    "wof:name":"PE19 7NA",
    "wof:placetype":"postalcode"
},
  "geometry": {"coordinates":[-0.2827829931558,52.22725748368493],"type":"Point"}
}