{
  "type": "Feature",
  "properties": {
    "iso:country": "GB",
    "wof:name": "PE19 7NA",
    "wof:placetype": "postalcode"
  },
  "geometry": {"coordinates":[-0.282783,52.227257],"type":"Point"}
}
