{
  "type": "Feature",
  "properties": {
    "date:inception_lower": "2000-06-01",
    "date:inception_upper": "2000-06-01",
    "iso:country": "GB",
    "wof:name": "PE19 7NA",
    "wof:placetype": "postalcode"
  },
  "geometry": {"coordinates":[-0.282783,52.227257],"type":"Point"}
}
