{
  "type": "Feature",
  "properties": {
    "date:inception_lower": "2021-10-01",
    "date:inception_upper": "2021-10-01",
    "iso:country": "GB",
    "wof:name": "IP6 8FF",
    "wof:placetype": "postalcode"
  },
  "geometry": {"coordinates":[1.059774,52.144645],"type":"Point"}
}
