{
  "type": "Feature",
  "properties": {
    "iso:country": "GB",
    "wof:name": "RG10 9SA",
    "wof:placetype": "postalcode"
  },
  "geometry": {"coordinates":[-0.837999,51.496678],"type":"Point"}
}
