{
  "type": "Feature",
  "properties": {
    "iso:country":"GB",
    "wof:name":"BH21 1AW",
    "wof:placetype":"postalcode"
},
  "geometry": {"coordinates":[-1.98018122987583,50.80117764321815],"type":"Point"}
}