{
  "type": "Feature",
  "properties": {
    "iso:country":"GB",
    "wof:name":"WN7 5DX",
    "wof:placetype":"postalcode"
},
  "geometry": {"coordinates":[-2.53310361555966,53.5090754829513],"type":"Point"}
}