{
  "type": "Feature",
  "properties": {
    "date:inception_lower": "1985-10-01",
    "date:inception_upper": "1985-10-01",
    "iso:country": "GB",
    "wof:name": "WN7 5DX",
    "wof:placetype": "postalcode"
  },
  "geometry": {"coordinates":[-2.533104,53.509075],"type":"Point"}
}
