{
  "type": "Feature",
  "properties": {
    "iso:country": "GB",
    "wof:name": "WN7 5DX",
    "wof:placetype": "postalcode"
  },
  "geometry": {"coordinates":[-2.533104,53.509075],"type":"Point"}
}
