{
  "type": "Feature",
  "properties": {
    "date:inception_lower": "1980-01-01",
    "date:inception_upper": "1980-01-01",
    "iso:country": "GB",
    "wof:name": "DL13 2RT",
    "wof:placetype": "postalcode"
  },
  "geometry": {"coordinates":[-1.95612,54.726532],"type":"Point"}
}
