{
  "type": "Feature",
  "properties": {
    "iso:country":"GB",
    "wof:name":"DL13 2RT",
    "wof:placetype":"postalcode"
},
  "geometry": {"coordinates":[-1.95612047886779,54.7265321867424],"type":"Point"}
}