{
  "type": "Feature",
  "properties": {
    "date:inception_lower": "1980-01-01",
    "date:inception_upper": "1980-01-01",
    "iso:country": "GB",
    "wof:name": "SS5 4LD",
    "wof:placetype": "postalcode"
  },
  "geometry": {"coordinates":[0.676826,51.593049],"type":"Point"}
}
