{
  "type": "Feature",
  "properties": {
    "iso:country":"GB",
    "wof:name":"PH50 4RE",
    "wof:placetype":"postalcode"
},
  "geometry": {"coordinates":[-4.95798582032849,56.71756884037345],"type":"Point"}
}