{
  "type": "Feature",
  "properties": {
    "date:inception_lower": "2009-08-01",
    "date:inception_upper": "2009-08-01",
    "iso:country": "GB",
    "wof:name": "BN1 2RU",
    "wof:placetype": "postalcode"
  },
  "geometry": {"coordinates":[-0.144372,50.82267],"type":"Point"}
}
