{
  "type": "Feature",
  "properties": {
    "iso:country": "GB",
    "wof:name": "BN1 2RU",
    "wof:placetype": "postalcode"
  },
  "geometry": {"coordinates":[-0.144568,50.822386],"type":"Point"}
}
