{
  "type": "Feature",
  "properties": {
    "iso:country": "GB",
    "wof:name": "BN1 2RU",
    "wof:placetype": "postalcode"
  },
  "geometry": {"coordinates":[-0.1444,50.822676],"type":"Point"}
}
