{
  "type": "Feature",
  "properties": {
    "iso:country":"GB",
    "wof:name":"BN1 2RU",
    "wof:placetype":"postalcode"
},
  "geometry": {"coordinates":[-0.14439964480868,50.82267634635573],"type":"Point"}
}