{
  "type": "Feature",
  "properties": {
    "iso:country":"GB",
    "wof:name":"CT6 8QX",
    "wof:placetype":"postalcode"
},
  "geometry": {"coordinates":[1.1110521517869,51.36597410908106],"type":"Point"}
}