{
  "type": "Feature",
  "properties": {
    "iso:country":"GB",
    "wof:name":"M20 5WL",
    "wof:placetype":"postalcode"
},
  "geometry": {"coordinates":[-2.22322716332884,53.40592470863707],"type":"Point"}
}