{
  "type": "Feature",
  "properties": {
    "iso:country": "GB",
    "wof:name": "M20 5WL",
    "wof:placetype": "postalcode"
  },
  "geometry": {"coordinates":[-2.223227,53.405925],"type":"Point"}
}
