{
  "type": "Feature",
  "properties": {
    "iso:country":"GB",
    "wof:name":"SO19 6BL",
    "wof:placetype":"postalcode"
},
  "geometry": {"coordinates":[-1.32889058727769,50.910075193719],"type":"Point"}
}