{
  "type": "Feature",
  "properties": {
    "iso:country": "GB",
    "wof:name": "SO19 6BL",
    "wof:placetype": "postalcode"
  },
  "geometry": {"coordinates":[-1.328891,50.910075],"type":"Point"}
}
