{
  "type": "Feature",
  "properties": {
    "date:inception_lower":"1980-01-01",
    "date:inception_upper":"1980-01-31",
    "iso:country":"GB",
    "wof:name":"RM3 0YP",
    "wof:placetype":"postalcode"
},
  "geometry": {"coordinates":[0.246449,51.600615],"type":"Point"}
}