{
  "type": "Feature",
  "properties": {
    "iso:country": "GB",
    "wof:name": "RM3 0YP",
    "wof:placetype": "postalcode"
  },
  "geometry": {"coordinates":[0.246449,51.600615],"type":"Point"}
}
