{
  "type": "Feature",
  "properties": {
    "iso:country":"GB",
    "wof:name":"RM3 0YP",
    "wof:placetype":"postalcode"
},
  "geometry": {"coordinates":[0.24640906068656,51.60061355141375],"type":"Point"}
}