{
  "type": "Feature",
  "properties": {
    "iso:country":"GB",
    "wof:name":"SA4 8RD",
    "wof:placetype":"postalcode"
},
  "geometry": {"coordinates":[-4.03968102943362,51.71249648552737],"type":"Point"}
}