{
  "type": "Feature",
  "properties": {
    "iso:country":"GB",
    "wof:name":"SP7 8PE",
    "wof:placetype":"postalcode"
},
  "geometry": {"coordinates":[-2.19395813827809,51.00658380114091],"type":"Point"}
}