{
  "type": "Feature",
  "properties": {
    "date:inception_lower": "2004-01-01",
    "date:inception_upper": "2004-01-01",
    "iso:country": "GB",
    "wof:name": "BL8 1WA",
    "wof:placetype": "postalcode"
  },
  "geometry": {"coordinates":[-2.327956,53.612073],"type":"Point"}
}
