{
  "type": "Feature",
  "properties": {
    "date:inception_lower": "2004-01-01",
    "date:inception_upper": "2004-01-01",
    "iso:country": "GB",
    "wof:name": "BL8 1WA",
    "wof:placetype": "postalcode"
  },
  "geometry": {"coordinates":[-2.328275,53.612056],"type":"Point"}
}
