{
  "type": "Feature",
  "properties": {
    "iso:country":"GB",
    "wof:name":"B9 4JU",
    "wof:placetype":"postalcode"
},
  "geometry": {"coordinates":[-1.87221585516176,52.47794270836891],"type":"Point"}
}