{
  "type": "Feature",
  "properties": {
    "date:inception_lower": "1980-01-01",
    "date:inception_upper": "1980-01-01",
    "iso:country": "GB",
    "wof:name": "B9 4JU",
    "wof:placetype": "postalcode"
  },
  "geometry": {"coordinates":[-1.872216,52.477943],"type":"Point"}
}
