{
  "type": "Feature",
  "properties": {
    "iso:country": "GB",
    "wof:name": "PL25 4GG",
    "wof:placetype": "postalcode"
  },
  "geometry": {"coordinates":[-4.790436,50.341096],"type":"Point"}
}
