{
  "type": "Feature",
  "properties": {
    "iso:country":"GB",
    "wof:name":"WN7 3XQ",
    "wof:placetype":"postalcode"
},
  "geometry": {"coordinates":[-2.50134523666372,53.4807193640079],"type":"Point"}
}