{
  "type": "Feature",
  "properties": {
    "iso:country":"GB",
    "wof:name":"DT6 5HT",
    "wof:placetype":"postalcode"
},
  "geometry": {"coordinates":[-2.77364810969878,50.76179604516142],"type":"Point"}
}