{
  "type": "Feature",
  "properties": {
    "iso:country": "GB",
    "wof:name": "BD20 9JH",
    "wof:placetype": "postalcode"
  },
  "geometry": {"coordinates":[-1.945729,53.931731],"type":"Point"}
}
