{
  "type": "Feature",
  "properties": {
    "iso:country": "GB",
    "wof:name": "SN38 1YY",
    "wof:placetype": "postalcode"
  },
  "geometry": {"coordinates":[-1.776689,51.540413],"type":"Point"}
}
