{
  "type": "Feature",
  "properties": {
    "iso:country":"GB",
    "wof:name":"GU24 0EH",
    "wof:placetype":"postalcode"
},
  "geometry": {"coordinates":[-0.63690748425731,51.30528943109152],"type":"Point"}
}