{
  "type": "Feature",
  "properties": {
    "iso:country":"GB",
    "wof:name":"LN2 2XD",
    "wof:placetype":"postalcode"
},
  "geometry": {"coordinates":[-0.44907701922244,53.28507021989538],"type":"Point"}
}