{
  "type": "Feature",
  "properties": {
    "iso:country":"GB",
    "wof:name":"W10 5YX",
    "wof:placetype":"postalcode"
},
  "geometry": {"coordinates":[-0.2051920151473,51.52063189858308],"type":"Point"}
}