{
  "type": "Feature",
  "properties": {
    "iso:country": "GB",
    "wof:name": "SA38 9RG",
    "wof:placetype": "postalcode"
  },
  "geometry": {"coordinates":[-4.483836,52.029579],"type":"Point"}
}
