{
  "type": "Feature",
  "properties": {
    "date:inception_lower": "2017-10-01",
    "date:inception_upper": "2017-10-01",
    "iso:country": "GB",
    "wof:name": "LL29 8PR",
    "wof:placetype": "postalcode"
  },
  "geometry": {"coordinates":[-3.727859,53.295826],"type":"Point"}
}
