{
  "type": "Feature",
  "properties": {
    "iso:country": "GB",
    "wof:name": "LL29 8PR",
    "wof:placetype": "postalcode"
  },
  "geometry": {"coordinates":[-3.727859,53.295826],"type":"Point"}
}
