{
  "type": "Feature",
  "properties": {
    "date:inception_lower": "1993-01-01",
    "date:inception_upper": "1993-01-01",
    "iso:country": "GB",
    "wof:name": "BN27 1UQ",
    "wof:placetype": "postalcode"
  },
  "geometry": {"coordinates":[0.25342,50.86787],"type":"Point"}
}
