{
  "type": "Feature",
  "properties": {
    "iso:country":"GB",
    "wof:name":"PA10 2ES",
    "wof:placetype":"postalcode"
},
  "geometry": {"coordinates":[-4.544150671756,55.83365085063012],"type":"Point"}
}