{
  "type": "Feature",
  "properties": {
    "date:inception_lower":"1980-01-01",
    "date:inception_upper":"1980-01-31",
    "iso:country":"GB",
    "wof:name":"PA10 2ES",
    "wof:placetype":"postalcode"
},
  "geometry": {"coordinates":[-4.544151,55.833651],"type":"Point"}
}