{
  "type": "Feature",
  "properties": {
    "iso:country":"GB",
    "wof:name":"M9 5TY",
    "wof:placetype":"postalcode"
},
  "geometry": {"coordinates":[-2.21363763335631,53.50924696006378],"type":"Point"}
}