{
  "type": "Feature",
  "properties": {
    "iso:country":"GB",
    "wof:name":"PL9 9RS",
    "wof:placetype":"postalcode"
},
  "geometry": {"coordinates":[-4.11401697063655,50.35208063563027],"type":"Point"}
}