{
  "type": "Feature",
  "properties": {
    "iso:country":"GB",
    "wof:name":"M5 5EB",
    "wof:placetype":"postalcode"
},
  "geometry": {"coordinates":[-2.30813755303384,53.48269539083987],"type":"Point"}
}