{
  "type": "Feature",
  "properties": {
    "date:inception_lower": "2004-11-01",
    "date:inception_upper": "2004-11-01",
    "iso:country": "GB",
    "wof:name": "M5 5EB",
    "wof:placetype": "postalcode"
  },
  "geometry": {"coordinates":[-2.308138,53.482695],"type":"Point"}
}
