{
  "type": "Feature",
  "properties": {
    "iso:country":"GB",
    "wof:name":"LS28 6PE",
    "wof:placetype":"postalcode"
},
  "geometry": {"coordinates":[-1.65068164285503,53.81001593404624],"type":"Point"}
}