{
  "type": "Feature",
  "properties": {
    "iso:country":"GB",
    "wof:name":"NG4 4FS",
    "wof:placetype":"postalcode"
},
  "geometry": {"coordinates":[-1.09498083120334,52.97969312410851],"type":"Point"}
}