{
  "type": "Feature",
  "properties": {
    "iso:country": "GB",
    "wof:name": "G65 0AU",
    "wof:placetype": "postalcode"
  },
  "geometry": {"coordinates":[-4.040107,55.981211],"type":"Point"}
}
