{
  "type": "Feature",
  "properties": {
    "date:inception_lower": "2012-09-01",
    "date:inception_upper": "2012-09-01",
    "iso:country": "GB",
    "wof:name": "G65 0AU",
    "wof:placetype": "postalcode"
  },
  "geometry": {"coordinates":[-4.040107,55.981211],"type":"Point"}
}
