{
  "type": "Feature",
  "properties": {
    "iso:country":"GB",
    "wof:name":"G65 0AU",
    "wof:placetype":"postalcode"
},
  "geometry": {"coordinates":[-4.04010701481861,55.98121105489622],"type":"Point"}
}