{
  "type": "Feature",
  "properties": {
    "iso:country":"GB",
    "wof:name":"MK46 5BN",
    "wof:placetype":"postalcode"
},
  "geometry": {"coordinates":[-0.70273344710847,52.15388609866569],"type":"Point"}
}