{
  "type": "Feature",
  "properties": {
    "date:inception_lower": "1988-03-01",
    "date:inception_upper": "1988-03-01",
    "iso:country": "GB",
    "wof:name": "MK46 5BN",
    "wof:placetype": "postalcode"
  },
  "geometry": {"coordinates":[-0.702963,52.153891],"type":"Point"}
}
