{
  "type": "Feature",
  "properties": {
    "iso:country": "GB",
    "wof:name": "MK46 5BN",
    "wof:placetype": "postalcode"
  },
  "geometry": {"coordinates":[-0.702733,52.153886],"type":"Point"}
}
