{
  "type": "Feature",
  "properties": {
    "iso:country": "GB",
    "wof:name": "EN5 3AN",
    "wof:placetype": "postalcode"
  },
  "geometry": {"coordinates":[-0.221548,51.647529],"type":"Point"}
}
