{
  "type": "Feature",
  "properties": {
    "iso:country":"GB",
    "wof:name":"EN5 3AN",
    "wof:placetype":"postalcode"
},
  "geometry": {"coordinates":[-0.22154844963152,51.64752881882814],"type":"Point"}
}