{
  "type": "Feature",
  "properties": {
    "iso:country":"GB",
    "wof:name":"CR5 1LJ",
    "wof:placetype":"postalcode"
},
  "geometry": {"coordinates":[-0.11939738414771,51.30267225265493],"type":"Point"}
}