{
  "type": "Feature",
  "properties": {
    "date:inception_lower": "1996-12-01",
    "date:inception_upper": "1996-12-01",
    "iso:country": "GB",
    "wof:name": "CF36 3EQ",
    "wof:placetype": "postalcode"
  },
  "geometry": {"coordinates":[-3.704545,51.480336],"type":"Point"}
}
