{
  "type": "Feature",
  "properties": {
    "iso:country":"GB",
    "wof:name":"PL20 7AL",
    "wof:placetype":"postalcode"
},
  "geometry": {"coordinates":[-4.19247414596574,50.48133347850067],"type":"Point"}
}