{
  "type": "Feature",
  "properties": {
    "iso:country":"GB",
    "wof:name":"ME7 2UU",
    "wof:placetype":"postalcode"
},
  "geometry": {"coordinates":[0.59091329581648,51.38423259952041],"type":"Point"}
}