{
  "type": "Feature",
  "properties": {
    "iso:country": "GB",
    "wof:name": "ME2 4SQ",
    "wof:placetype": "postalcode"
  },
  "geometry": {"coordinates":[0.51624,51.390933],"type":"Point"}
}
