{
  "type": "Feature",
  "properties": {
    "iso:country":"GB",
    "wof:name":"ME2 4SQ",
    "wof:placetype":"postalcode"
},
  "geometry": {"coordinates":[0.5162399132077,51.39093299381083],"type":"Point"}
}