{
  "type": "Feature",
  "properties": {
    "iso:country": "GB",
    "wof:name": "HX2 9QE",
    "wof:placetype": "postalcode"
  },
  "geometry": {"coordinates":[-1.881605,53.760331],"type":"Point"}
}
