{
  "type": "Feature",
  "properties": {
    "iso:country": "GB",
    "wof:name": "YO25 4QE",
    "wof:placetype": "postalcode"
  },
  "geometry": {"coordinates":[-0.390452,54.012511],"type":"Point"}
}
