{
  "type": "Feature",
  "properties": {
    "iso:country":"GB",
    "wof:name":"GU24 8HG",
    "wof:placetype":"postalcode"
},
  "geometry": {"coordinates":[-0.58651875603014,51.35262121764076],"type":"Point"}
}