{
  "type": "Feature",
  "properties": {
    "iso:country":"GB",
    "wof:name":"TN21 9AB",
    "wof:placetype":"postalcode"
},
  "geometry": {"coordinates":[0.27814307555764,50.96384875239142],"type":"Point"}
}