{
  "type": "Feature",
  "properties": {
    "iso:country":"GB",
    "wof:name":"LE67 9WG",
    "wof:placetype":"postalcode"
},
  "geometry": {"coordinates":[-1.27737785779525,52.68397843944731],"type":"Point"}
}