{
  "type": "Feature",
  "properties": {
    "date:inception_lower":"1992-08-01",
    "date:inception_upper":"1992-08-31",
    "iso:country":"GB",
    "wof:name":"LE67 9WG",
    "wof:placetype":"postalcode"
},
  "geometry": {"coordinates":[-1.277378,52.683978],"type":"Point"}
}