{
  "type": "Feature",
  "properties": {
    "iso:country":"GB",
    "wof:name":"W1W 7EB",
    "wof:placetype":"postalcode"
},
  "geometry": {"coordinates":[-0.14003682609028,51.51892441283186],"type":"Point"}
}