{
  "type": "Feature",
  "properties": {
    "iso:country":"GB",
    "wof:name":"NG2 6LJ",
    "wof:placetype":"postalcode"
},
  "geometry": {"coordinates":[-1.11113583211584,52.92692057252429],"type":"Point"}
}