{
  "type": "Feature",
  "properties": {
    "date:inception_lower": "2019-01-01",
    "date:inception_upper": "2019-01-01",
    "iso:country": "GB",
    "wof:name": "HR2 7PD",
    "wof:placetype": "postalcode"
  },
  "geometry": {"coordinates":[-2.7275,52.045327],"type":"Point"}
}
