{
  "type": "Feature",
  "properties": {
    "iso:country": "GB",
    "wof:name": "HR2 7PD",
    "wof:placetype": "postalcode"
  },
  "geometry": {"coordinates":[-2.7275,52.045327],"type":"Point"}
}
