{
  "type": "Feature",
  "properties": {
    "iso:country":"GB",
    "wof:name":"TN17 2BU",
    "wof:placetype":"postalcode"
},
  "geometry": {"coordinates":[0.55534347164615,51.1380452294846],"type":"Point"}
}