{
  "type": "Feature",
  "properties": {
    "iso:country":"GB",
    "wof:name":"NP22 3TA",
    "wof:placetype":"postalcode"
},
  "geometry": {"coordinates":[-3.24970992183868,51.76499102846245],"type":"Point"}
}