{
  "type": "Feature",
  "properties": {
    "iso:country":"GB",
    "wof:name":"CR0 8ND",
    "wof:placetype":"postalcode"
},
  "geometry": {"coordinates":[-0.02959711589133,51.37150178711624],"type":"Point"}
}