{
  "type": "Feature",
  "properties": {
    "date:inception_lower": "1980-01-01",
    "date:inception_upper": "1980-01-01",
    "iso:country": "GB",
    "wof:name": "CR0 8ND",
    "wof:placetype": "postalcode"
  },
  "geometry": {"coordinates":[-0.029597,51.371502],"type":"Point"}
}
