{
  "type": "Feature",
  "properties": {
    "iso:country":"GB",
    "wof:name":"OX2 7HS",
    "wof:placetype":"postalcode"
},
  "geometry": {"coordinates":[-1.26503469990511,51.77700142330798],"type":"Point"}
}