{
  "type": "Feature",
  "properties": {
    "iso:country": "GB",
    "wof:name": "HD1 6LF",
    "wof:placetype": "postalcode"
  },
  "geometry": {"coordinates":[-1.7799,53.659401],"type":"Point"}
}
