{
  "type": "Feature",
  "properties": {
    "iso:country": "GB",
    "wof:name": "YO25 5AW",
    "wof:placetype": "postalcode"
  },
  "geometry": {"coordinates":[-0.424406,54.006446],"type":"Point"}
}
