{
  "type": "Feature",
  "properties": {
    "iso:country":"GB",
    "wof:name":"HA9 8RJ",
    "wof:placetype":"postalcode"
},
  "geometry": {"coordinates":[-0.30061994798034,51.57195138053399],"type":"Point"}
}