{
  "type": "Feature",
  "properties": {
    "iso:country":"GB",
    "wof:name":"OX3 8TP",
    "wof:placetype":"postalcode"
},
  "geometry": {"coordinates":[-1.19985961447519,51.76104816200846],"type":"Point"}
}