{
  "type": "Feature",
  "properties": {
    "iso:country":"GB",
    "wof:name":"SN8 4HF",
    "wof:placetype":"postalcode"
},
  "geometry": {"coordinates":[-1.78820737558536,51.41019239374405],"type":"Point"}
}