{
  "type": "Feature",
  "properties": {
    "date:inception_lower": "1980-01-01",
    "date:inception_upper": "1980-01-01",
    "iso:country": "GB",
    "wof:name": "CM5 9NW",
    "wof:placetype": "postalcode"
  },
  "geometry": {"coordinates":[0.282517,51.71007],"type":"Point"}
}
