{
  "type": "Feature",
  "properties": {
    "iso:country":"GB",
    "wof:name":"CM5 9NW",
    "wof:placetype":"postalcode"
},
  "geometry": {"coordinates":[0.28251681732819,51.71007036237648],"type":"Point"}
}