{
  "type": "Feature",
  "properties": {
    "iso:country": "GB",
    "wof:name": "SK11 9JZ",
    "wof:placetype": "postalcode"
  },
  "geometry": {"coordinates":[-2.235243,53.258182],"type":"Point"}
}
