{
  "type": "Feature",
  "properties": {
    "iso:country": "GB",
    "wof:name": "MK12 5QZ",
    "wof:placetype": "postalcode"
  },
  "geometry": {"coordinates":[-0.805762,52.0618],"type":"Point"}
}
