{
  "type": "Feature",
  "properties": {
    "date:inception_lower": "2014-10-01",
    "date:inception_upper": "2014-10-01",
    "iso:country": "GB",
    "wof:name": "MK12 5QZ",
    "wof:placetype": "postalcode"
  },
  "geometry": {"coordinates":[-0.805762,52.0618],"type":"Point"}
}
