{
  "type": "Feature",
  "properties": {
    "iso:country":"GB",
    "wof:name":"MK12 5QZ",
    "wof:placetype":"postalcode"
},
  "geometry": {"coordinates":[-0.80576157256971,52.06180029944815],"type":"Point"}
}