{
  "type": "Feature",
  "properties": {
    "iso:country":"GB",
    "wof:name":"PE2 9DE",
    "wof:placetype":"postalcode"
},
  "geometry": {"coordinates":[-0.24995781237016,52.56156101107563],"type":"Point"}
}