{
  "type": "Feature",
  "properties": {
    "date:inception_lower":"1980-01-01",
    "date:inception_upper":"1980-01-31",
    "iso:country":"GB",
    "wof:name":"PE2 9DE",
    "wof:placetype":"postalcode"
},
  "geometry": {"coordinates":[-0.249958,52.561561],"type":"Point"}
}