{
  "type": "Feature",
  "properties": {
    "iso:country": "GB",
    "wof:name": "PO21 3EW",
    "wof:placetype": "postalcode"
  },
  "geometry": {"coordinates":[-0.718724,50.789155],"type":"Point"}
}
