{
  "type": "Feature",
  "properties": {
    "date:inception_lower": "1980-01-01",
    "date:inception_upper": "1980-01-01",
    "iso:country": "GB",
    "wof:name": "CA28 7PH",
    "wof:placetype": "postalcode"
  },
  "geometry": {"coordinates":[-3.584723,54.549068],"type":"Point"}
}
