{
  "type": "Feature",
  "properties": {
    "iso:country":"GB",
    "wof:name":"CA28 7PH",
    "wof:placetype":"postalcode"
},
  "geometry": {"coordinates":[-3.58472289356238,54.549068327597],"type":"Point"}
}