{
  "type": "Feature",
  "properties": {
    "iso:country":"GB",
    "wof:name":"CM15 9JN",
    "wof:placetype":"postalcode"
},
  "geometry": {"coordinates":[0.27858695026998,51.63789825230881],"type":"Point"}
}