{
  "type": "Feature",
  "properties": {
    "date:inception_lower": "1980-01-01",
    "date:inception_upper": "1980-01-01",
    "iso:country": "GB",
    "wof:name": "LS16 7RH",
    "wof:placetype": "postalcode"
  },
  "geometry": {"coordinates":[-1.613141,53.856216],"type":"Point"}
}
