{
  "type": "Feature",
  "properties": {
    "iso:country":"GB",
    "wof:name":"LS16 7RH",
    "wof:placetype":"postalcode"
},
  "geometry": {"coordinates":[-1.61314131826785,53.85621579455851],"type":"Point"}
}