{
  "type": "Feature",
  "properties": {
    "iso:country":"GB",
    "wof:name":"PL26 6EL",
    "wof:placetype":"postalcode"
},
  "geometry": {"coordinates":[-4.81609794481084,50.28924319908871],"type":"Point"}
}