{
  "type": "Feature",
  "properties": {
    "iso:country":"GB",
    "wof:name":"E8 3GZ",
    "wof:placetype":"postalcode"
},
  "geometry": {"coordinates":[-0.07065027744655,51.54274895871688],"type":"Point"}
}