{
  "type": "Feature",
  "properties": {
    "iso:country":"GB",
    "wof:name":"G81 2SS",
    "wof:placetype":"postalcode"
},
  "geometry": {"coordinates":[-4.37930745450864,55.90189660198409],"type":"Point"}
}