{
  "type": "Feature",
  "properties": {
    "iso:country": "GB",
    "wof:name": "G78 3RJ",
    "wof:placetype": "postalcode"
  },
  "geometry": {"coordinates":[-4.437294,55.778293],"type":"Point"}
}
