{
  "type": "Feature",
  "properties": {
    "iso:country":"GB",
    "wof:name":"G78 3RJ",
    "wof:placetype":"postalcode"
},
  "geometry": {"coordinates":[-4.43729418568346,55.77829257707922],"type":"Point"}
}