{
  "type": "Feature",
  "properties": {
    "date:inception_lower":"1993-08-01",
    "date:inception_upper":"1993-08-31",
    "iso:country":"GB",
    "wof:name":"WR8 0LY",
    "wof:placetype":"postalcode"
},
  "geometry": {"coordinates":[-2.214928,52.06232],"type":"Point"}
}