{
  "type": "Feature",
  "properties": {
    "date:inception_lower": "1993-08-01",
    "date:inception_upper": "1993-08-01",
    "iso:country": "GB",
    "wof:name": "WR8 0LY",
    "wof:placetype": "postalcode"
  },
  "geometry": {"coordinates":[-2.215038,52.062321],"type":"Point"}
}
