{
  "type": "Feature",
  "properties": {
    "iso:country": "GB",
    "wof:name": "M16 8LZ",
    "wof:placetype": "postalcode"
  },
  "geometry": {"coordinates":[-2.255659,53.446236],"type":"Point"}
}
