{
  "type": "Feature",
  "properties": {
    "date:inception_lower":"1985-10-01",
    "date:inception_upper":"1985-10-31",
    "iso:country":"GB",
    "wof:name":"M16 8LZ",
    "wof:placetype":"postalcode"
},
  "geometry": {"coordinates":[-2.255659,53.446236],"type":"Point"}
}