{
  "type": "Feature",
  "properties": {
    "date:inception_lower": "1985-10-01",
    "date:inception_upper": "1985-10-01",
    "iso:country": "GB",
    "wof:name": "M16 8LZ",
    "wof:placetype": "postalcode"
  },
  "geometry": {"coordinates":[-2.255914,53.446243],"type":"Point"}
}
