{
  "type": "Feature",
  "properties": {
    "iso:country":"GB",
    "wof:name":"SK13 7QY",
    "wof:placetype":"postalcode"
},
  "geometry": {"coordinates":[-1.947492170366,53.44506965731922],"type":"Point"}
}