{
  "type": "Feature",
  "properties": {
    "iso:country":"GB",
    "wof:name":"TS6 8DY",
    "wof:placetype":"postalcode"
},
  "geometry": {"coordinates":[-1.11507273050311,54.57007475231707],"type":"Point"}
}