{
  "type": "Feature",
  "properties": {
    "date:inception_lower": "2024-01-01",
    "date:inception_upper": "2024-01-01",
    "iso:country": "GB",
    "wof:name": "TF6 6FH",
    "wof:placetype": "postalcode"
  },
  "geometry": {"coordinates":[-2.549635,52.760468],"type":"Point"}
}
