{
  "type": "Feature",
  "properties": {
    "iso:country": "GB",
    "wof:name": "EN9 2PD",
    "wof:placetype": "postalcode"
  },
  "geometry": {"coordinates":[0.011652,51.746509],"type":"Point"}
}
