{
  "type": "Feature",
  "properties": {
    "iso:country": "GB",
    "wof:name": "NR25 6FF",
    "wof:placetype": "postalcode"
  },
  "geometry": {"coordinates":[1.100549,52.906681],"type":"Point"}
}
