{
  "type": "Feature",
  "properties": {
    "iso:country":"GB",
    "wof:name":"NR25 6FF",
    "wof:placetype":"postalcode"
},
  "geometry": {"coordinates":[1.10052763173547,52.90660008468991],"type":"Point"}
}