{
  "type": "Feature",
  "properties": {
    "date:inception_lower": "2014-02-01",
    "date:inception_upper": "2014-02-01",
    "iso:country": "GB",
    "wof:name": "NR25 6FF",
    "wof:placetype": "postalcode"
  },
  "geometry": {"coordinates":[1.100549,52.906681],"type":"Point"}
}
