{
  "type": "Feature",
  "properties": {
    "iso:country":"GB",
    "wof:name":"B91 3PS",
    "wof:placetype":"postalcode"
},
  "geometry": {"coordinates":[-1.79783711930679,52.40304209150533],"type":"Point"}
}