{
  "type": "Feature",
  "properties": {
    "iso:country": "GB",
    "wof:name": "CF36 5SG",
    "wof:placetype": "postalcode"
  },
  "geometry": {"coordinates":[-3.684977,51.485115],"type":"Point"}
}
