{
  "type": "Feature",
  "properties": {
    "date:inception_lower": "1980-01-01",
    "date:inception_upper": "1980-01-01",
    "iso:country": "GB",
    "wof:name": "CF36 5SG",
    "wof:placetype": "postalcode"
  },
  "geometry": {"coordinates":[-3.684977,51.485115],"type":"Point"}
}
