{
  "type": "Feature",
  "properties": {
    "iso:country":"GB",
    "wof:name":"CF36 5SG",
    "wof:placetype":"postalcode"
},
  "geometry": {"coordinates":[-3.68497693532798,51.48511502591754],"type":"Point"}
}