{
  "type": "Feature",
  "properties": {
    "iso:country":"GB",
    "wof:name":"WN7 5AG",
    "wof:placetype":"postalcode"
},
  "geometry": {"coordinates":[-2.5323783593238,53.49933516903815],"type":"Point"}
}