{
  "type": "Feature",
  "properties": {
    "iso:country":"GB",
    "wof:name":"NG16 5LA",
    "wof:placetype":"postalcode"
},
  "geometry": {"coordinates":[-1.33269540005081,53.06121533714368],"type":"Point"}
}