{
  "type": "Feature",
  "properties": {
    "iso:country": "GB",
    "wof:name": "HU9 1HR",
    "wof:placetype": "postalcode"
  },
  "geometry": {"coordinates":[-0.316872,53.74897],"type":"Point"}
}
