{
  "type": "Feature",
  "properties": {
    "iso:country": "GB",
    "wof:name": "GL50 1EG",
    "wof:placetype": "postalcode"
  },
  "geometry": {"coordinates":[-2.072431,51.898854],"type":"Point"}
}
