{
  "type": "Feature",
  "properties": {
    "iso:country":"GB",
    "wof:name":"TN40 2RY",
    "wof:placetype":"postalcode"
},
  "geometry": {"coordinates":[0.50298513587693,50.85195395178266],"type":"Point"}
}