{
  "type": "Feature",
  "properties": {
    "date:inception_lower": "2017-07-01",
    "date:inception_upper": "2017-07-01",
    "iso:country": "GB",
    "wof:name": "BH22 9FW",
    "wof:placetype": "postalcode"
  },
  "geometry": {"coordinates":[-1.901699,50.78853],"type":"Point"}
}
