{
  "type": "Feature",
  "properties": {
    "iso:country":"GB",
    "wof:name":"CB8 9TY",
    "wof:placetype":"postalcode"
},
  "geometry": {"coordinates":[0.43180859201519,52.17974050181384],"type":"Point"}
}