{
  "type": "Feature",
  "properties": {
    "iso:country": "GB",
    "wof:name": "CB8 9TY",
    "wof:placetype": "postalcode"
  },
  "geometry": {"coordinates":[0.431809,52.17974],"type":"Point"}
}
