{
  "type": "Feature",
  "properties": {
    "iso:country":"GB",
    "wof:name":"CF14 3PR",
    "wof:placetype":"postalcode"
},
  "geometry": {"coordinates":[-3.18506995043272,51.50023470155416],"type":"Point"}
}