{
  "type": "Feature",
  "properties": {
    "iso:country": "GB",
    "wof:name": "S72 9FQ",
    "wof:placetype": "postalcode"
  },
  "geometry": {"coordinates":[-1.400357,53.60813],"type":"Point"}
}
