{
  "type": "Feature",
  "properties": {
    "iso:country":"GB",
    "wof:name":"S72 9FQ",
    "wof:placetype":"postalcode"
},
  "geometry": {"coordinates":[-1.40035697873397,53.60813018171014],"type":"Point"}
}