{
  "type": "Feature",
  "properties": {
    "iso:country": "GB",
    "wof:name": "LL13 0EB",
    "wof:placetype": "postalcode"
  },
  "geometry": {"coordinates":[-2.93595,52.970244],"type":"Point"}
}
