{
  "type": "Feature",
  "properties": {
    "iso:country":"GB",
    "wof:name":"LL13 0EB",
    "wof:placetype":"postalcode"
},
  "geometry": {"coordinates":[-2.93595010697688,52.97024427534838],"type":"Point"}
}