{
  "type": "Feature",
  "properties": {
    "date:inception_lower": "1980-01-01",
    "date:inception_upper": "1980-01-01",
    "iso:country": "GB",
    "wof:name": "OX2 7SD",
    "wof:placetype": "postalcode"
  },
  "geometry": {"coordinates":[-1.267642,51.786045],"type":"Point"}
}
