{
  "type": "Feature",
  "properties": {
    "iso:country":"GB",
    "wof:name":"OX2 7SD",
    "wof:placetype":"postalcode"
},
  "geometry": {"coordinates":[-1.26764229092941,51.78604485591084],"type":"Point"}
}