{
  "type": "Feature",
  "properties": {
    "iso:country":"GB",
    "wof:name":"BS21 7JL",
    "wof:placetype":"postalcode"
},
  "geometry": {"coordinates":[-2.84912030755298,51.44137554521667],"type":"Point"}
}