{
  "type": "Feature",
  "properties": {
    "iso:country": "GB",
    "wof:name": "BS21 7JL",
    "wof:placetype": "postalcode"
  },
  "geometry": {"coordinates":[-2.84912,51.441376],"type":"Point"}
}
