{
  "type": "Feature",
  "properties": {
    "iso:country":"GB",
    "wof:name":"CO7 9RB",
    "wof:placetype":"postalcode"
},
  "geometry": {"coordinates":[0.96927556568059,51.86039782725279],"type":"Point"}
}