{
  "type": "Feature",
  "properties": {
    "iso:country": "GB",
    "wof:name": "OL16 3BL",
    "wof:placetype": "postalcode"
  },
  "geometry": {"coordinates":[-2.124461,53.616002],"type":"Point"}
}
