{
  "type": "Feature",
  "properties": {
    "date:inception_lower":"1995-07-01",
    "date:inception_upper":"1995-07-31",
    "iso:country":"GB",
    "wof:name":"OL16 3BL",
    "wof:placetype":"postalcode"
},
  "geometry": {"coordinates":[-2.124461,53.616002],"type":"Point"}
}