{
  "type": "Feature",
  "properties": {
    "iso:country":"GB",
    "wof:name":"OL16 3BL",
    "wof:placetype":"postalcode"
},
  "geometry": {"coordinates":[-2.12446085225602,53.61600165370226],"type":"Point"}
}