{
  "type": "Feature",
  "properties": {
    "date:inception_lower":"1993-01-01",
    "date:inception_upper":"1993-01-31",
    "iso:country":"GB",
    "wof:name":"BA20 2NZ",
    "wof:placetype":"postalcode"
},
  "geometry": {"coordinates":[-2.661204,50.933888],"type":"Point"}
}