{
  "type": "Feature",
  "properties": {
    "iso:country": "GB",
    "wof:name": "CH60 0BY",
    "wof:placetype": "postalcode"
  },
  "geometry": {"coordinates":[-3.096509,53.326728],"type":"Point"}
}
