{
  "type": "Feature",
  "properties": {
    "date:inception_lower": "1999-06-01",
    "date:inception_upper": "1999-06-01",
    "iso:country": "GB",
    "wof:name": "CH60 0BY",
    "wof:placetype": "postalcode"
  },
  "geometry": {"coordinates":[-3.096481,53.326809],"type":"Point"}
}
