{
  "type": "Feature",
  "properties": {
    "date:inception_lower": "1980-01-01",
    "date:inception_upper": "1980-01-01",
    "iso:country": "GB",
    "wof:name": "CV35 9AD",
    "wof:placetype": "postalcode"
  },
  "geometry": {"coordinates":[-1.521164,52.219626],"type":"Point"}
}
