{
  "type": "Feature",
  "properties": {
    "iso:country":"GB",
    "wof:name":"CV35 9AD",
    "wof:placetype":"postalcode"
},
  "geometry": {"coordinates":[-1.52116442406296,52.21962602154656],"type":"Point"}
}