{
  "type": "Feature",
  "properties": {
    "date:inception_lower":"1995-07-01",
    "date:inception_upper":"1995-07-31",
    "iso:country":"GB",
    "wof:name":"WF16 9HD",
    "wof:placetype":"postalcode"
},
  "geometry": {"coordinates":[-1.677951,53.71543],"type":"Point"}
}