{
  "type": "Feature",
  "properties": {
    "iso:country":"GB",
    "wof:name":"WF16 9HD",
    "wof:placetype":"postalcode"
},
  "geometry": {"coordinates":[-1.67795106238702,53.71543003864101],"type":"Point"}
}