{
  "type": "Feature",
  "properties": {
    "iso:country":"GB",
    "wof:name":"SA4 3YP",
    "wof:placetype":"postalcode"
},
  "geometry": {"coordinates":[-4.10869264832067,51.64258320538706],"type":"Point"}
}