{
  "type": "Feature",
  "properties": {
    "iso:country":"GB",
    "wof:name":"PA2 7ST",
    "wof:placetype":"postalcode"
},
  "geometry": {"coordinates":[-4.42158034030881,55.82393838616895],"type":"Point"}
}