{
  "type": "Feature",
  "properties": {
    "iso:country": "GB",
    "wof:name": "GU26 6TJ",
    "wof:placetype": "postalcode"
  },
  "geometry": {"coordinates":[-0.737403,51.112019],"type":"Point"}
}
