{
  "type": "Feature",
  "properties": {
    "iso:country":"GB",
    "wof:name":"GU26 6TJ",
    "wof:placetype":"postalcode"
},
  "geometry": {"coordinates":[-0.73740269150637,51.11201864411107],"type":"Point"}
}