{
  "type": "Feature",
  "properties": {
    "iso:country":"GB",
    "wof:name":"DH5 0JY",
    "wof:placetype":"postalcode"
},
  "geometry": {"coordinates":[-1.44065990740955,54.80876401265384],"type":"Point"}
}