{
  "type": "Feature",
  "properties": {
    "iso:country":"GB",
    "wof:name":"SY3 7EB",
    "wof:placetype":"postalcode"
},
  "geometry": {"coordinates":[-2.75010599640148,52.70269207976484],"type":"Point"}
}