{
  "type": "Feature",
  "properties": {
    "iso:country":"GB",
    "wof:name":"WS3 1ET",
    "wof:placetype":"postalcode"
},
  "geometry": {"coordinates":[-1.98595757500246,52.60855240046006],"type":"Point"}
}