{
  "type": "Feature",
  "properties": {
    "iso:country": "GB",
    "wof:name": "WS3 1ET",
    "wof:placetype": "postalcode"
  },
  "geometry": {"coordinates":[-1.985958,52.608552],"type":"Point"}
}
