{
  "type": "Feature",
  "properties": {
    "date:inception_lower": "1980-01-01",
    "date:inception_upper": "1980-01-01",
    "iso:country": "GB",
    "wof:name": "CA20 1BY",
    "wof:placetype": "postalcode"
  },
  "geometry": {"coordinates":[-3.467848,54.434295],"type":"Point"}
}
