{
  "type": "Feature",
  "properties": {
    "iso:country": "GB",
    "wof:name": "CA20 1BY",
    "wof:placetype": "postalcode"
  },
  "geometry": {"coordinates":[-3.467848,54.434295],"type":"Point"}
}
