{
  "type": "Feature",
  "properties": {
    "iso:country":"GB",
    "wof:name":"CA20 1BY",
    "wof:placetype":"postalcode"
},
  "geometry": {"coordinates":[-3.46784552189842,54.43428520347553],"type":"Point"}
}