{
  "type": "Feature",
  "properties": {
    "iso:country":"GB",
    "wof:name":"CO7 7EJ",
    "wof:placetype":"postalcode"
},
  "geometry": {"coordinates":[0.98879087957743,51.88087682836258],"type":"Point"}
}