{
  "type": "Feature",
  "properties": {
    "iso:country":"GB",
    "wof:name":"PL31 1DJ",
    "wof:placetype":"postalcode"
},
  "geometry": {"coordinates":[-4.70932866130683,50.46581039856371],"type":"Point"}
}