{
  "type": "Feature",
  "properties": {
    "date:inception_lower": "1981-09-01",
    "date:inception_upper": "1981-09-01",
    "iso:country": "GB",
    "wof:name": "PL31 1DJ",
    "wof:placetype": "postalcode"
  },
  "geometry": {"coordinates":[-4.709329,50.46581],"type":"Point"}
}
