{
  "type": "Feature",
  "properties": {
    "iso:country": "GB",
    "wof:name": "PL19 0HU",
    "wof:placetype": "postalcode"
  },
  "geometry": {"coordinates":[-4.135535,50.553725],"type":"Point"}
}
