{
  "type": "Feature",
  "properties": {
    "iso:country":"GB",
    "wof:name":"SG18 9HA",
    "wof:placetype":"postalcode"
},
  "geometry": {"coordinates":[-0.34042927605013,52.08612620737949],"type":"Point"}
}