{
  "type": "Feature",
  "properties": {
    "date:inception_lower": "2014-02-01",
    "date:inception_upper": "2014-02-01",
    "iso:country": "GB",
    "wof:name": "YO11 2NL",
    "wof:placetype": "postalcode"
  },
  "geometry": {"coordinates":[-0.401295,54.280981],"type":"Point"}
}
