{
  "type": "Feature",
  "properties": {
    "iso:country":"GB",
    "wof:name":"SO51 0QD",
    "wof:placetype":"postalcode"
},
  "geometry": {"coordinates":[-1.46748957936464,51.01675538411186],"type":"Point"}
}