{
  "type": "Feature",
  "properties": {
    "iso:country":"GB",
    "wof:name":"DL1 5TU",
    "wof:placetype":"postalcode"
},
  "geometry": {"coordinates":[-1.55588473298483,54.51025985785986],"type":"Point"}
}