{
  "type": "Feature",
  "properties": {
    "date:inception_lower": "1980-01-01",
    "date:inception_upper": "1980-01-01",
    "iso:country": "GB",
    "wof:name": "BS14 9SG",
    "wof:placetype": "postalcode"
  },
  "geometry": {"coordinates":[-2.570771,51.417184],"type":"Point"}
}
