{
  "type": "Feature",
  "properties": {
    "iso:country":"GB",
    "wof:name":"SE9 1HN",
    "wof:placetype":"postalcode"
},
  "geometry": {"coordinates":[0.05415601558206,51.4521051354461],"type":"Point"}
}