{
  "type": "Feature",
  "properties": {
    "date:inception_lower": "2020-06-01",
    "date:inception_upper": "2020-06-01",
    "iso:country": "GB",
    "wof:name": "GL3 1FE",
    "wof:placetype": "postalcode"
  },
  "geometry": {"coordinates":[-2.208965,51.888745],"type":"Point"}
}
