{
  "type": "Feature",
  "properties": {
    "iso:country":"GB",
    "wof:name":"SW10 0LD",
    "wof:placetype":"postalcode"
},
  "geometry": {"coordinates":[-0.18138042373727,51.48188524215159],"type":"Point"}
}