{
  "type": "Feature",
  "properties": {
    "iso:country":"GB",
    "wof:name":"NR6 5DR",
    "wof:placetype":"postalcode"
},
  "geometry": {"coordinates":[1.2566143788342,52.65322211143733],"type":"Point"}
}