{
  "type": "Feature",
  "properties": {
    "iso:country": "GB",
    "wof:name": "WR4 0QG",
    "wof:placetype": "postalcode"
  },
  "geometry": {"coordinates":[-2.176946,52.195191],"type":"Point"}
}
