{
  "type": "Feature",
  "properties": {
    "date:inception_lower": "2000-06-01",
    "date:inception_upper": "2000-06-01",
    "iso:country": "GB",
    "wof:name": "DN19 7TH",
    "wof:placetype": "postalcode"
  },
  "geometry": {"coordinates":[-0.382941,53.677311],"type":"Point"}
}
