{
  "type": "Feature",
  "properties": {
    "iso:country":"GB",
    "wof:name":"DD3 9SP",
    "wof:placetype":"postalcode"
},
  "geometry": {"coordinates":[-3.02260576516561,56.49680750620825],"type":"Point"}
}