{
  "type": "Feature",
  "properties": {
    "date:inception_lower": "1998-12-01",
    "date:inception_upper": "1998-12-01",
    "iso:country": "GB",
    "wof:name": "DD3 9SP",
    "wof:placetype": "postalcode"
  },
  "geometry": {"coordinates":[-3.022606,56.496808],"type":"Point"}
}
