{
  "type": "Feature",
  "properties": {
    "iso:country": "GB",
    "wof:name": "DD3 9SP",
    "wof:placetype": "postalcode"
  },
  "geometry": {"coordinates":[-3.022606,56.496808],"type":"Point"}
}
