{
  "type": "Feature",
  "properties": {
    "iso:country":"GB",
    "wof:name":"YO21 1LE",
    "wof:placetype":"postalcode"
},
  "geometry": {"coordinates":[-0.62873522430783,54.48059896895756],"type":"Point"}
}