{
  "type": "Feature",
  "properties": {
    "iso:country":"GB",
    "wof:name":"RG2 7HS",
    "wof:placetype":"postalcode"
},
  "geometry": {"coordinates":[-0.95416901084604,51.43377444053976],"type":"Point"}
}