{
  "type": "Feature",
  "properties": {
    "iso:country": "GB",
    "wof:name": "RG2 7HS",
    "wof:placetype": "postalcode"
  },
  "geometry": {"coordinates":[-0.954169,51.433774],"type":"Point"}
}
