{
  "type": "Feature",
  "properties": {
    "iso:country":"GB",
    "wof:name":"CF35 6PU",
    "wof:placetype":"postalcode"
},
  "geometry": {"coordinates":[-3.52385759460158,51.52841418151011],"type":"Point"}
}