{
  "type": "Feature",
  "properties": {
    "iso:country": "GB",
    "wof:name": "PR4 6EP",
    "wof:placetype": "postalcode"
  },
  "geometry": {"coordinates":[-2.844946,53.694632],"type":"Point"}
}
