{
  "type": "Feature",
  "properties": {
    "date:inception_lower": "2014-08-01",
    "date:inception_upper": "2014-08-01",
    "iso:country": "GB",
    "wof:name": "PR4 6EP",
    "wof:placetype": "postalcode"
  },
  "geometry": {"coordinates":[-2.845007,53.694695],"type":"Point"}
}
