{
  "type": "Feature",
  "properties": {
    "iso:country":"GB",
    "wof:name":"PR4 6EP",
    "wof:placetype":"postalcode"
},
  "geometry": {"coordinates":[-2.84500881914739,53.69467012012657],"type":"Point"}
}