{
  "type": "Feature",
  "properties": {
    "date:inception_lower":"2012-05-01",
    "date:inception_upper":"2012-05-31",
    "iso:country":"GB",
    "wof:name":"S70 6HG",
    "wof:placetype":"postalcode"
},
  "geometry": {"coordinates":[-1.503322,53.553116],"type":"Point"}
}