{
  "type": "Feature",
  "properties": {
    "iso:country": "GB",
    "wof:name": "S70 6HG",
    "wof:placetype": "postalcode"
  },
  "geometry": {"coordinates":[-1.503322,53.553116],"type":"Point"}
}
