{
  "type": "Feature",
  "properties": {
    "iso:country": "GB",
    "wof:name": "LE8 4BT",
    "wof:placetype": "postalcode"
  },
  "geometry": {"coordinates":[-1.163747,52.564456],"type":"Point"}
}
