{
  "type": "Feature",
  "properties": {
    "date:inception_lower": "1985-04-01",
    "date:inception_upper": "1985-04-01",
    "iso:country": "GB",
    "wof:name": "DT1 1EU",
    "wof:placetype": "postalcode"
  },
  "geometry": {"coordinates":[-2.434274,50.714679],"type":"Point"}
}
