{
  "type": "Feature",
  "properties": {
    "iso:country":"GB",
    "wof:name":"DT1 1EU",
    "wof:placetype":"postalcode"
},
  "geometry": {"coordinates":[-2.43426220670364,50.71473293787618],"type":"Point"}
}