{
  "type": "Feature",
  "properties": {
    "iso:country": "GB",
    "wof:name": "LL35 0HL",
    "wof:placetype": "postalcode"
  },
  "geometry": {"coordinates":[-4.047268,52.545393],"type":"Point"}
}
