{
  "type": "Feature",
  "properties": {
    "date:inception_lower":"1980-01-01",
    "date:inception_upper":"1980-01-31",
    "iso:country":"GB",
    "wof:name":"TN24 0AW",
    "wof:placetype":"postalcode"
},
  "geometry": {"coordinates":[0.899998,51.144276],"type":"Point"}
}