{
  "type": "Feature",
  "properties": {
    "iso:country":"GB",
    "wof:name":"NR20 4BD",
    "wof:placetype":"postalcode"
},
  "geometry": {"coordinates":[0.95319416132473,52.71173579622292],"type":"Point"}
}