{
  "type": "Feature",
  "properties": {
    "date:inception_lower": "2007-04-01",
    "date:inception_upper": "2007-04-01",
    "iso:country": "GB",
    "wof:name": "SE18 4GA",
    "wof:placetype": "postalcode"
  },
  "geometry": {"coordinates":[0.046812,51.474221],"type":"Point"}
}
