{
  "type": "Feature",
  "properties": {
    "iso:country": "GB",
    "wof:name": "SE18 4GA",
    "wof:placetype": "postalcode"
  },
  "geometry": {"coordinates":[0.046812,51.474221],"type":"Point"}
}
