{
  "type": "Feature",
  "properties": {
    "iso:country":"GB",
    "wof:name":"SE18 4GA",
    "wof:placetype":"postalcode"
},
  "geometry": {"coordinates":[0.04681178491083,51.47422100022548],"type":"Point"}
}