{
  "type": "Feature",
  "properties": {
    "date:inception_lower": "1993-08-01",
    "date:inception_upper": "1993-08-01",
    "iso:country": "GB",
    "wof:name": "CH3 6PE",
    "wof:placetype": "postalcode"
  },
  "geometry": {"coordinates":[-2.853274,53.061469],"type":"Point"}
}
