{
  "type": "Feature",
  "properties": {
    "iso:country":"GB",
    "wof:name":"NG34 8UP",
    "wof:placetype":"postalcode"
},
  "geometry": {"coordinates":[-0.42117508538981,52.98946648692364],"type":"Point"}
}