{
  "type": "Feature",
  "properties": {
    "iso:country": "GB",
    "wof:name": "NG34 8UP",
    "wof:placetype": "postalcode"
  },
  "geometry": {"coordinates":[-0.421175,52.989466],"type":"Point"}
}
