{
  "type": "Feature",
  "properties": {
    "iso:country":"GB",
    "wof:name":"SS9 5AS",
    "wof:placetype":"postalcode"
},
  "geometry": {"coordinates":[0.643558887053,51.57490841821199],"type":"Point"}
}