{
  "type": "Feature",
  "properties": {
    "iso:country": "GB",
    "wof:name": "S41 8NZ",
    "wof:placetype": "postalcode"
  },
  "geometry": {"coordinates":[-1.425003,53.253614],"type":"Point"}
}
