{
  "type": "Feature",
  "properties": {
    "iso:country":"GB",
    "wof:name":"S41 8NZ",
    "wof:placetype":"postalcode"
},
  "geometry": {"coordinates":[-1.42503351498943,53.25364035616941],"type":"Point"}
}