{
  "type": "Feature",
  "properties": {
    "iso:country":"GB",
    "wof:name":"SY13 2DN",
    "wof:placetype":"postalcode"
},
  "geometry": {"coordinates":[-2.67120937847104,52.89805142142655],"type":"Point"}
}