{
  "type": "Feature",
  "properties": {
    "iso:country":"GB",
    "wof:name":"BR4 9PF",
    "wof:placetype":"postalcode"
},
  "geometry": {"coordinates":[-0.02168305941757,51.37510942720526],"type":"Point"}
}