{
  "type": "Feature",
  "properties": {
    "date:inception_lower": "1980-01-01",
    "date:inception_upper": "1980-01-01",
    "iso:country": "GB",
    "wof:name": "BB12 9BN",
    "wof:placetype": "postalcode"
  },
  "geometry": {"coordinates":[-2.293336,53.826208],"type":"Point"}
}
