{
  "type": "Feature",
  "properties": {
    "iso:country":"GB",
    "wof:name":"S18 8YD",
    "wof:placetype":"postalcode"
},
  "geometry": {"coordinates":[-1.49848404142428,53.30563062542176],"type":"Point"}
}