{
  "type": "Feature",
  "properties": {
    "date:inception_lower":"1998-12-01",
    "date:inception_upper":"1998-12-31",
    "iso:country":"GB",
    "wof:name":"HX1 5AN",
    "wof:placetype":"postalcode"
},
  "geometry": {"coordinates":[-1.865524,53.723274],"type":"Point"}
}