{
  "type": "Feature",
  "properties": {
    "iso:country": "GB",
    "wof:name": "HX1 5AN",
    "wof:placetype": "postalcode"
  },
  "geometry": {"coordinates":[-1.865524,53.723274],"type":"Point"}
}
