{
  "type": "Feature",
  "properties": {
    "iso:country":"GB",
    "wof:name":"EX9 6SH",
    "wof:placetype":"postalcode"
},
  "geometry": {"coordinates":[-3.32771598531358,50.63709466212976],"type":"Point"}
}