{
  "type": "Feature",
  "properties": {
    "iso:country": "GB",
    "wof:name": "NW2 5LX",
    "wof:placetype": "postalcode"
  },
  "geometry": {"coordinates":[-0.233555,51.55053],"type":"Point"}
}
