{
  "type": "Feature",
  "properties": {
    "iso:country":"GB",
    "wof:name":"S70 4PD",
    "wof:placetype":"postalcode"
},
  "geometry": {"coordinates":[-1.47307377406708,53.54581413272644],"type":"Point"}
}