{
  "type": "Feature",
  "properties": {
    "iso:country": "GB",
    "wof:name": "TA10 9DL",
    "wof:placetype": "postalcode"
  },
  "geometry": {"coordinates":[-2.816189,51.072327],"type":"Point"}
}
