{
  "type": "Feature",
  "properties": {
    "iso:country": "GB",
    "wof:name": "TA10 9DL",
    "wof:placetype": "postalcode"
  },
  "geometry": {"coordinates":[-2.815669,51.072301],"type":"Point"}
}
