{
  "type": "Feature",
  "properties": {
    "iso:country":"GB",
    "wof:name":"TA10 9DL",
    "wof:placetype":"postalcode"
},
  "geometry": {"coordinates":[-2.81566930995119,51.07230121845246],"type":"Point"}
}