{
  "type": "Feature",
  "properties": {
    "iso:country":"GB",
    "wof:name":"DH9 9DY",
    "wof:placetype":"postalcode"
},
  "geometry": {"coordinates":[-1.76396915002023,54.87472248157054],"type":"Point"}
}