{
  "type": "Feature",
  "properties": {
    "iso:country":"GB",
    "wof:name":"EC1M 4NB",
    "wof:placetype":"postalcode"
},
  "geometry": {"coordinates":[-0.10221083786672,51.5214478937604],"type":"Point"}
}