{
  "type": "Feature",
  "properties": {
    "date:inception_lower":"1980-01-01",
    "date:inception_upper":"1980-01-31",
    "iso:country":"GB",
    "wof:name":"ME9 7UN",
    "wof:placetype":"postalcode"
},
  "geometry": {"coordinates":[0.637755,51.325726],"type":"Point"}
}