{
  "type": "Feature",
  "properties": {
    "iso:country": "GB",
    "wof:name": "M26 2GX",
    "wof:placetype": "postalcode"
  },
  "geometry": {"coordinates":[-2.319163,53.564281],"type":"Point"}
}
