{
  "type": "Feature",
  "properties": {
    "date:inception_lower": "1994-05-01",
    "date:inception_upper": "1994-05-01",
    "iso:country": "GB",
    "wof:name": "M26 2GX",
    "wof:placetype": "postalcode"
  },
  "geometry": {"coordinates":[-2.319163,53.564281],"type":"Point"}
}
