{
  "type": "Feature",
  "properties": {
    "iso:country":"GB",
    "wof:name":"M26 2GX",
    "wof:placetype":"postalcode"
},
  "geometry": {"coordinates":[-2.31916343242112,53.56428120106759],"type":"Point"}
}