{
  "type": "Feature",
  "properties": {
    "iso:country":"GB",
    "wof:name":"CT21 5SE",
    "wof:placetype":"postalcode"
},
  "geometry": {"coordinates":[1.11844462931261,51.07611915260059],"type":"Point"}
}