{
  "type": "Feature",
  "properties": {
    "iso:country": "GB",
    "wof:name": "OL9 7BX",
    "wof:placetype": "postalcode"
  },
  "geometry": {"coordinates":[-2.13621,53.532694],"type":"Point"}
}
