{
  "type": "Feature",
  "properties": {
    "date:inception_lower": "1985-04-01",
    "date:inception_upper": "1985-04-01",
    "iso:country": "GB",
    "wof:name": "HP12 3ES",
    "wof:placetype": "postalcode"
  },
  "geometry": {"coordinates":[-0.774824,51.633402],"type":"Point"}
}
