{
  "type": "Feature",
  "properties": {
    "iso:country":"GB",
    "wof:name":"HP12 3ES",
    "wof:placetype":"postalcode"
},
  "geometry": {"coordinates":[-0.77482417201819,51.63340162276586],"type":"Point"}
}