{
  "type": "Feature",
  "properties": {
    "iso:country":"GB",
    "wof:name":"SR7 9NP",
    "wof:placetype":"postalcode"
},
  "geometry": {"coordinates":[-1.38526551359797,54.81427460732807],"type":"Point"}
}