{
  "type": "Feature",
  "properties": {
    "iso:country":"GB",
    "wof:name":"BA15 2RR",
    "wof:placetype":"postalcode"
},
  "geometry": {"coordinates":[-2.23882106010194,51.37618696513357],"type":"Point"}
}