{
  "type": "Feature",
  "properties": {
    "iso:country":"GB",
    "wof:name":"ST5 0PL",
    "wof:placetype":"postalcode"
},
  "geometry": {"coordinates":[-2.21217260891192,53.01868685650797],"type":"Point"}
}