{
  "type": "Feature",
  "properties": {
    "iso:country":"GB",
    "wof:name":"E16 4JH",
    "wof:placetype":"postalcode"
},
  "geometry": {"coordinates":[0.01268002613181,51.51861540279225],"type":"Point"}
}