{
  "type": "Feature",
  "properties": {
    "date:inception_lower": "1980-01-01",
    "date:inception_upper": "1980-01-01",
    "iso:country": "GB",
    "wof:name": "KA1 3PW",
    "wof:placetype": "postalcode"
  },
  "geometry": {"coordinates":[-4.483783,55.593436],"type":"Point"}
}
