{
  "type": "Feature",
  "properties": {
    "iso:country":"GB",
    "wof:name":"KA1 3PW",
    "wof:placetype":"postalcode"
},
  "geometry": {"coordinates":[-4.48378272741825,55.59343566379767],"type":"Point"}
}