{
  "type": "Feature",
  "properties": {
    "iso:country":"GB",
    "wof:name":"M12 4WG",
    "wof:placetype":"postalcode"
},
  "geometry": {"coordinates":[-2.20602870189893,53.46382375339615],"type":"Point"}
}