{
  "type": "Feature",
  "properties": {
    "date:inception_lower": "1993-08-01",
    "date:inception_upper": "1993-08-01",
    "iso:country": "GB",
    "wof:name": "WF6 1SZ",
    "wof:placetype": "postalcode"
  },
  "geometry": {"coordinates":[-1.407876,53.69513],"type":"Point"}
}
