{
  "type": "Feature",
  "properties": {
    "iso:country": "GB",
    "wof:name": "WF6 1SZ",
    "wof:placetype": "postalcode"
  },
  "geometry": {"coordinates":[-1.407876,53.69513],"type":"Point"}
}
