{
  "type": "Feature",
  "properties": {
    "iso:country":"GB",
    "wof:name":"WF6 1SZ",
    "wof:placetype":"postalcode"
},
  "geometry": {"coordinates":[-1.40787560978785,53.69512957910514],"type":"Point"}
}