{
  "type": "Feature",
  "properties": {
    "date:inception_lower":"2004-08-01",
    "date:inception_upper":"2004-08-31",
    "iso:country":"GB",
    "wof:name":"CV6 5BH",
    "wof:placetype":"postalcode"
},
  "geometry": {"coordinates":[-1.494723,52.427524],"type":"Point"}
}