{
  "type": "Feature",
  "properties": {
    "iso:country":"GB",
    "wof:name":"CV6 5BH",
    "wof:placetype":"postalcode"
},
  "geometry": {"coordinates":[-1.49472348437535,52.42752408129218],"type":"Point"}
}