{
  "type": "Feature",
  "properties": {
    "iso:country":"GB",
    "wof:name":"W3 8BW",
    "wof:placetype":"postalcode"
},
  "geometry": {"coordinates":[-0.2749182222727,51.50028521674571],"type":"Point"}
}