{
  "type": "Feature",
  "properties": {
    "iso:country": "GB",
    "wof:name": "W3 8BW",
    "wof:placetype": "postalcode"
  },
  "geometry": {"coordinates":[-0.274918,51.500285],"type":"Point"}
}
