{
  "type": "Feature",
  "properties": {
    "date:inception_lower": "2017-05-01",
    "date:inception_upper": "2017-05-01",
    "iso:country": "GB",
    "wof:name": "WN6 7BF",
    "wof:placetype": "postalcode"
  },
  "geometry": {"coordinates":[-2.645169,53.555835],"type":"Point"}
}
