{
  "type": "Feature",
  "properties": {
    "iso:country": "GB",
    "wof:name": "WN6 7BF",
    "wof:placetype": "postalcode"
  },
  "geometry": {"coordinates":[-2.645169,53.555835],"type":"Point"}
}
