{
  "type": "Feature",
  "properties": {
    "iso:country":"GB",
    "wof:name":"EN1 3SL",
    "wof:placetype":"postalcode"
},
  "geometry": {"coordinates":[-0.06648860472581,51.65139051286845],"type":"Point"}
}