{
  "type": "Feature",
  "properties": {
    "date:inception_lower": "1980-01-01",
    "date:inception_upper": "1980-01-01",
    "iso:country": "GB",
    "wof:name": "EN1 3SL",
    "wof:placetype": "postalcode"
  },
  "geometry": {"coordinates":[-0.066489,51.651391],"type":"Point"}
}
