{
  "type": "Feature",
  "properties": {
    "iso:country": "GB",
    "wof:name": "SA1 3SH",
    "wof:placetype": "postalcode"
  },
  "geometry": {"coordinates":[-3.94745,51.615245],"type":"Point"}
}
