{
  "type": "Feature",
  "properties": {
    "iso:country":"GB",
    "wof:name":"CF37 2HP",
    "wof:placetype":"postalcode"
},
  "geometry": {"coordinates":[-3.34613895914116,51.60521259672963],"type":"Point"}
}