{
  "type": "Feature",
  "properties": {
    "date:inception_lower": "1980-01-01",
    "date:inception_upper": "1980-01-01",
    "iso:country": "GB",
    "wof:name": "BS21 6SW",
    "wof:placetype": "postalcode"
  },
  "geometry": {"coordinates":[-2.759344,51.445802],"type":"Point"}
}
