{
  "type": "Feature",
  "properties": {
    "iso:country":"GB",
    "wof:name":"BS21 6SW",
    "wof:placetype":"postalcode"
},
  "geometry": {"coordinates":[-2.75991477371462,51.44571947039423],"type":"Point"}
}