{
  "type": "Feature",
  "properties": {
    "date:inception_lower":"1980-01-01",
    "date:inception_upper":"1980-01-31",
    "iso:country":"GB",
    "wof:name":"SE23 1HA",
    "wof:placetype":"postalcode"
},
  "geometry": {"coordinates":[-0.044924,51.447415],"type":"Point"}
}