{
  "type": "Feature",
  "properties": {
    "iso:country":"GB",
    "wof:name":"SE23 1HA",
    "wof:placetype":"postalcode"
},
  "geometry": {"coordinates":[-0.0449245244674,51.44741468039761],"type":"Point"}
}