{
  "type": "Feature",
  "properties": {
    "iso:country":"GB",
    "wof:name":"NE6 2SE",
    "wof:placetype":"postalcode"
},
  "geometry": {"coordinates":[-1.56476218966138,54.975898049476],"type":"Point"}
}