{
  "type": "Feature",
  "properties": {
    "iso:country":"GB",
    "wof:name":"LA5 9RP",
    "wof:placetype":"postalcode"
},
  "geometry": {"coordinates":[-2.74370732693447,54.19059715432172],"type":"Point"}
}