{
  "type": "Feature",
  "properties": {
    "date:inception_lower": "1980-01-01",
    "date:inception_upper": "1980-01-01",
    "iso:country": "GB",
    "wof:name": "LA5 9RP",
    "wof:placetype": "postalcode"
  },
  "geometry": {"coordinates":[-2.743951,54.190534],"type":"Point"}
}
