{
  "type": "Feature",
  "properties": {
    "date:inception_lower": "1980-01-01",
    "date:inception_upper": "1980-01-01",
    "iso:country": "GB",
    "wof:name": "E11 1PT",
    "wof:placetype": "postalcode"
  },
  "geometry": {"coordinates":[0.018977,51.57883],"type":"Point"}
}
