{
  "type": "Feature",
  "properties": {
    "iso:country": "GB",
    "wof:name": "SO40 7LE",
    "wof:placetype": "postalcode"
  },
  "geometry": {"coordinates":[-1.537568,50.905189],"type":"Point"}
}
