{
  "type": "Feature",
  "properties": {
    "iso:country":"GB",
    "wof:name":"SO16 6RG",
    "wof:placetype":"postalcode"
},
  "geometry": {"coordinates":[-1.4230555646718,50.93378777078485],"type":"Point"}
}