{
  "type": "Feature",
  "properties": {
    "date:inception_lower": "2019-05-01",
    "date:inception_upper": "2019-05-01",
    "iso:country": "GB",
    "wof:name": "TW11 9FJ",
    "wof:placetype": "postalcode"
  },
  "geometry": {"coordinates":[-0.32146,51.428932],"type":"Point"}
}
