{
  "type": "Feature",
  "properties": {
    "iso:country":"GB",
    "wof:name":"PR3 3EX",
    "wof:placetype":"postalcode"
},
  "geometry": {"coordinates":[-2.61151536608326,53.82173573507881],"type":"Point"}
}