{
  "type": "Feature",
  "properties": {
    "iso:country":"GB",
    "wof:name":"E14 1GS",
    "wof:placetype":"postalcode"
},
  "geometry": {"coordinates":[-0.02831829412787,51.51316081995923],"type":"Point"}
}