{
  "type": "Feature",
  "properties": {
    "iso:country": "GB",
    "wof:name": "PL26 7JP",
    "wof:placetype": "postalcode"
  },
  "geometry": {"coordinates":[-4.855692,50.314504],"type":"Point"}
}
