{
  "type": "Feature",
  "properties": {
    "iso:country":"GB",
    "wof:name":"S10 9GF",
    "wof:placetype":"postalcode"
},
  "geometry": {"coordinates":[-1.51612558994056,53.37920434042385],"type":"Point"}
}