{
  "type": "Feature",
  "properties": {
    "iso:country":"GB",
    "wof:name":"GU30 7XX",
    "wof:placetype":"postalcode"
},
  "geometry": {"coordinates":[-0.80324628524841,51.07107566725152],"type":"Point"}
}