{
  "type": "Feature",
  "properties": {
    "iso:country":"GB",
    "wof:name":"BN16 1BZ",
    "wof:placetype":"postalcode"
},
  "geometry": {"coordinates":[-0.47238414373275,50.81493120516127],"type":"Point"}
}