{
  "type": "Feature",
  "properties": {
    "iso:country": "GB",
    "wof:name": "SG8 0DN",
    "wof:placetype": "postalcode"
  },
  "geometry": {"coordinates":[-0.082499,52.127126],"type":"Point"}
}
