{
  "type": "Feature",
  "properties": {
    "iso:country": "GB",
    "wof:name": "PE27 4AE",
    "wof:placetype": "postalcode"
  },
  "geometry": {"coordinates":[-0.059996,52.330236],"type":"Point"}
}
