{
  "type": "Feature",
  "properties": {
    "iso:country":"GB",
    "wof:name":"BN3 3PN",
    "wof:placetype":"postalcode"
},
  "geometry": {"coordinates":[-0.16671239998596,50.83336255939336],"type":"Point"}
}