{
  "type": "Feature",
  "properties": {
    "iso:country":"GB",
    "wof:name":"EH12 8EB",
    "wof:placetype":"postalcode"
},
  "geometry": {"coordinates":[-3.29793425380978,55.94625249670845],"type":"Point"}
}