{
  "type": "Feature",
  "properties": {
    "iso:country": "GB",
    "wof:name": "EH12 8EB",
    "wof:placetype": "postalcode"
  },
  "geometry": {"coordinates":[-3.297934,55.946252],"type":"Point"}
}
