{
  "type": "Feature",
  "properties": {
    "iso:country": "GB",
    "wof:name": "SA66 7RA",
    "wof:placetype": "postalcode"
  },
  "geometry": {"coordinates":[-4.821526,51.935248],"type":"Point"}
}
