{
  "type": "Feature",
  "properties": {
    "iso:country":"GB",
    "wof:name":"LS25 4BU",
    "wof:placetype":"postalcode"
},
  "geometry": {"coordinates":[-1.33323133238508,53.78868242434893],"type":"Point"}
}