{
  "type": "Feature",
  "properties": {
    "iso:country":"GB",
    "wof:name":"ML3 7FF",
    "wof:placetype":"postalcode"
},
  "geometry": {"coordinates":[-4.0299598307111,55.74044701578278],"type":"Point"}
}