{
  "type": "Feature",
  "properties": {
    "date:inception_lower": "2000-06-01",
    "date:inception_upper": "2000-06-01",
    "iso:country": "GB",
    "wof:name": "ML3 7FF",
    "wof:placetype": "postalcode"
  },
  "geometry": {"coordinates":[-4.02996,55.740447],"type":"Point"}
}
