{
  "type": "Feature",
  "properties": {
    "iso:country":"GB",
    "wof:name":"DN14 5EH",
    "wof:placetype":"postalcode"
},
  "geometry": {"coordinates":[-0.86742855375659,53.7054061007596],"type":"Point"}
}