{
  "type": "Feature",
  "properties": {
    "date:inception_lower": "1997-12-01",
    "date:inception_upper": "1997-12-01",
    "iso:country": "GB",
    "wof:name": "PE13 4XF",
    "wof:placetype": "postalcode"
  },
  "geometry": {"coordinates":[0.055376,52.650676],"type":"Point"}
}
