{
  "type": "Feature",
  "properties": {
    "iso:country":"GB",
    "wof:name":"SS2 4JN",
    "wof:placetype":"postalcode"
},
  "geometry": {"coordinates":[0.72633100126458,51.54253417345166],"type":"Point"}
}