{
  "type": "Feature",
  "properties": {
    "iso:country":"GB",
    "wof:name":"M27 0JR",
    "wof:placetype":"postalcode"
},
  "geometry": {"coordinates":[-2.35085207180943,53.50930922216061],"type":"Point"}
}