{
  "type": "Feature",
  "properties": {
    "iso:country":"GB",
    "wof:name":"BS3 1PZ",
    "wof:placetype":"postalcode"
},
  "geometry": {"coordinates":[-2.60693586610436,51.44524481662923],"type":"Point"}
}