{
  "type": "Feature",
  "properties": {
    "iso:country": "GB",
    "wof:name": "TA13 5LY",
    "wof:placetype": "postalcode"
  },
  "geometry": {"coordinates":[-2.807403,50.952346],"type":"Point"}
}
