{
  "type": "Feature",
  "properties": {
    "iso:country": "GB",
    "wof:name": "B78 1EL",
    "wof:placetype": "postalcode"
  },
  "geometry": {"coordinates":[-1.614143,52.620934],"type":"Point"}
}
