{
  "type": "Feature",
  "properties": {
    "iso:country":"GB",
    "wof:name":"B78 1EL",
    "wof:placetype":"postalcode"
},
  "geometry": {"coordinates":[-1.61414346193705,52.62093389175842],"type":"Point"}
}