{
  "type": "Feature",
  "properties": {
    "iso:country":"GB",
    "wof:name":"TQ1 2JB",
    "wof:placetype":"postalcode"
},
  "geometry": {"coordinates":[-3.49932201852134,50.46841623947458],"type":"Point"}
}