{
  "type": "Feature",
  "properties": {
    "iso:country":"GB",
    "wof:name":"GL13 9RW",
    "wof:placetype":"postalcode"
},
  "geometry": {"coordinates":[-2.46210996060472,51.70975833896033],"type":"Point"}
}