{
  "type": "Feature",
  "properties": {
    "iso:country":"GB",
    "wof:name":"ZE1 0YB",
    "wof:placetype":"postalcode"
},
  "geometry": {"coordinates":[-1.13558341423996,60.14826197391567],"type":"Point"}
}