{
  "type": "Feature",
  "properties": {
    "iso:country":"GB",
    "wof:name":"BD3 9LD",
    "wof:placetype":"postalcode"
},
  "geometry": {"coordinates":[-1.73728178002916,53.79406730939887],"type":"Point"}
}