{
  "type": "Feature",
  "properties": {
    "iso:country":"GB",
    "wof:name":"HD1 3BW",
    "wof:placetype":"postalcode"
},
  "geometry": {"coordinates":[-1.77471960836081,53.64304452121269],"type":"Point"}
}