{
  "type": "Feature",
  "properties": {
    "iso:country":"GB",
    "wof:name":"DD3 0DF",
    "wof:placetype":"postalcode"
},
  "geometry": {"coordinates":[-2.9791303500733,56.48892813101352],"type":"Point"}
}