{
  "type": "Feature",
  "properties": {
    "iso:country": "GB",
    "wof:name": "DD3 0DF",
    "wof:placetype": "postalcode"
  },
  "geometry": {"coordinates":[-2.97913,56.488928],"type":"Point"}
}
