{
  "type": "Feature",
  "properties": {
    "date:inception_lower": "2021-10-01",
    "date:inception_upper": "2021-10-01",
    "iso:country": "GB",
    "wof:name": "CO11 1FP",
    "wof:placetype": "postalcode"
  },
  "geometry": {"coordinates":[1.066443,51.95988],"type":"Point"}
}
