{
  "type": "Feature",
  "properties": {
    "date:inception_lower": "2021-10-01",
    "date:inception_upper": "2021-10-01",
    "iso:country": "GB",
    "wof:name": "CO11 1FP",
    "wof:placetype": "postalcode"
  },
  "geometry": {"coordinates":[1.067207,51.959977],"type":"Point"}
}
