{
  "type": "Feature",
  "properties": {
    "iso:country":"GB",
    "wof:name":"GL51 9BS",
    "wof:placetype":"postalcode"
},
  "geometry": {"coordinates":[-2.08939964419976,51.91014386825567],"type":"Point"}
}