{
  "type": "Feature",
  "properties": {
    "date:inception_lower": "1983-01-01",
    "date:inception_upper": "1983-01-01",
    "iso:country": "GB",
    "wof:name": "NG16 2FJ",
    "wof:placetype": "postalcode"
  },
  "geometry": {"coordinates":[-1.284883,53.016279],"type":"Point"}
}
