{
  "type": "Feature",
  "properties": {
    "iso:country":"GB",
    "wof:name":"NG16 2FJ",
    "wof:placetype":"postalcode"
},
  "geometry": {"coordinates":[-1.28488353213286,53.01627886401294],"type":"Point"}
}