{
  "type": "Feature",
  "properties": {
    "iso:country": "GB",
    "wof:name": "TA21 8JJ",
    "wof:placetype": "postalcode"
  },
  "geometry": {"coordinates":[-3.233776,50.981892],"type":"Point"}
}
