{
  "type": "Feature",
  "properties": {
    "iso:country":"GB",
    "wof:name":"NG23 5BE",
    "wof:placetype":"postalcode"
},
  "geometry": {"coordinates":[-0.73446511561119,53.03025135141292],"type":"Point"}
}