{
  "type": "Feature",
  "properties": {
    "date:inception_lower": "2000-06-01",
    "date:inception_upper": "2000-06-01",
    "iso:country": "GB",
    "wof:name": "LL18 5GZ",
    "wof:placetype": "postalcode"
  },
  "geometry": {"coordinates":[-3.5099,53.295946],"type":"Point"}
}
