{
  "type": "Feature",
  "properties": {
    "date:inception_lower":"2017-10-01",
    "date:inception_upper":"2017-10-31",
    "iso:country":"GB",
    "wof:name":"CO10 0WG",
    "wof:placetype":"postalcode"
},
  "geometry": {"coordinates":[0.746907,52.028415],"type":"Point"}
}