{
  "type": "Feature",
  "properties": {
    "iso:country": "GB",
    "wof:name": "CO10 0WG",
    "wof:placetype": "postalcode"
  },
  "geometry": {"coordinates":[0.746907,52.028415],"type":"Point"}
}
