{
  "type": "Feature",
  "properties": {
    "iso:country": "GB",
    "wof:name": "L3 2BX",
    "wof:placetype": "postalcode"
  },
  "geometry": {"coordinates":[-2.987166,53.411588],"type":"Point"}
}
