{
  "type": "Feature",
  "properties": {
    "iso:country":"GB",
    "wof:name":"PE25 1BX",
    "wof:placetype":"postalcode"
},
  "geometry": {"coordinates":[0.34584459511095,53.15082786614062],"type":"Point"}
}