{
  "type": "Feature",
  "properties": {
    "date:inception_lower":"2008-01-01",
    "date:inception_upper":"2008-01-31",
    "iso:country":"GB",
    "wof:name":"BH1 4AQ",
    "wof:placetype":"postalcode"
},
  "geometry": {"coordinates":[-1.84159,50.728178],"type":"Point"}
}