{
  "type": "Feature",
  "properties": {
    "iso:country": "GB",
    "wof:name": "DL11 7RQ",
    "wof:placetype": "postalcode"
  },
  "geometry": {"coordinates":[-1.830391,54.490079],"type":"Point"}
}
