{
  "type": "Feature",
  "properties": {
    "iso:country":"GB",
    "wof:name":"BN24 5AN",
    "wof:placetype":"postalcode"
},
  "geometry": {"coordinates":[0.29670845367071,50.82441280067542],"type":"Point"}
}