{
  "type": "Feature",
  "properties": {
    "date:inception_lower":"1980-01-01",
    "date:inception_upper":"1980-01-31",
    "iso:country":"GB",
    "wof:name":"BN24 5AN",
    "wof:placetype":"postalcode"
},
  "geometry": {"coordinates":[0.296708,50.824413],"type":"Point"}
}