{
  "type": "Feature",
  "properties": {
    "date:inception_lower":"1986-04-01",
    "date:inception_upper":"1986-04-30",
    "iso:country":"GB",
    "wof:name":"UB3 3PU",
    "wof:placetype":"postalcode"
},
  "geometry": {"coordinates":[-0.410108,51.510963],"type":"Point"}
}