{
  "type": "Feature",
  "properties": {
    "iso:country":"GB",
    "wof:name":"UB3 3PU",
    "wof:placetype":"postalcode"
},
  "geometry": {"coordinates":[-0.4101076930203,51.51096311670371],"type":"Point"}
}