{
  "type": "Feature",
  "properties": {
    "iso:country":"GB",
    "wof:name":"LN8 3UD",
    "wof:placetype":"postalcode"
},
  "geometry": {"coordinates":[-0.36317450976399,53.38997365311355],"type":"Point"}
}