{
  "type": "Feature",
  "properties": {
    "iso:country": "GB",
    "wof:name": "HG1 2NH",
    "wof:placetype": "postalcode"
  },
  "geometry": {"coordinates":[-1.565593,53.99354],"type":"Point"}
}
