{
  "type": "Feature",
  "properties": {
    "date:inception_lower":"1999-06-01",
    "date:inception_upper":"1999-06-30",
    "iso:country":"GB",
    "wof:name":"NP20 5DQ",
    "wof:placetype":"postalcode"
},
  "geometry": {"coordinates":[-3.006853,51.591494],"type":"Point"}
}