{
  "type": "Feature",
  "properties": {
    "iso:country":"GB",
    "wof:name":"NP7 8BP",
    "wof:placetype":"postalcode"
},
  "geometry": {"coordinates":[-2.94679476346353,51.82609445878968],"type":"Point"}
}