{
  "type": "Feature",
  "properties": {
    "iso:country": "GB",
    "wof:name": "NP7 8BP",
    "wof:placetype": "postalcode"
  },
  "geometry": {"coordinates":[-2.946795,51.826094],"type":"Point"}
}
