{
  "type": "Feature",
  "properties": {
    "iso:country":"GB",
    "wof:name":"DN38 6JD",
    "wof:placetype":"postalcode"
},
  "geometry": {"coordinates":[-0.40230257328928,53.57289063277807],"type":"Point"}
}