{
  "type": "Feature",
  "properties": {
    "iso:country":"GB",
    "wof:name":"DL12 0DQ",
    "wof:placetype":"postalcode"
},
  "geometry": {"coordinates":[-1.98665416772495,54.60519256049087],"type":"Point"}
}