{
  "type": "Feature",
  "properties": {
    "date:inception_lower":"1980-01-01",
    "date:inception_upper":"1980-01-31",
    "iso:country":"GB",
    "wof:name":"DL12 0DQ",
    "wof:placetype":"postalcode"
},
  "geometry": {"coordinates":[-1.986654,54.605193],"type":"Point"}
}