{
  "type": "Feature",
  "properties": {
    "iso:country":"GB",
    "wof:name":"MK15 0BX",
    "wof:placetype":"postalcode"
},
  "geometry": {"coordinates":[-0.7289144894619,52.04030800908047],"type":"Point"}
}