{
  "type": "Feature",
  "properties": {
    "iso:country":"GB",
    "wof:name":"NG1 3NG",
    "wof:placetype":"postalcode"
},
  "geometry": {"coordinates":[-1.14685734783685,52.95921200920377],"type":"Point"}
}