{
  "type": "Feature",
  "properties": {
    "iso:country": "GB",
    "wof:name": "NG1 3NG",
    "wof:placetype": "postalcode"
  },
  "geometry": {"coordinates":[-1.146914,52.95926],"type":"Point"}
}
