{
  "type": "Feature",
  "properties": {
    "date:inception_lower": "1980-01-01",
    "date:inception_upper": "1980-01-01",
    "iso:country": "GB",
    "wof:name": "BL3 4LA",
    "wof:placetype": "postalcode"
  },
  "geometry": {"coordinates":[-2.465154,53.55947],"type":"Point"}
}
