{
  "type": "Feature",
  "properties": {
    "iso:country":"GB",
    "wof:name":"SS7 1NG",
    "wof:placetype":"postalcode"
},
  "geometry": {"coordinates":[0.563486501503,51.54418341454946],"type":"Point"}
}