{
  "type": "Feature",
  "properties": {
    "iso:country":"GB",
    "wof:name":"LE18 1BB",
    "wof:placetype":"postalcode"
},
  "geometry": {"coordinates":[-1.11627016542005,52.58922038911481],"type":"Point"}
}