{
  "type": "Feature",
  "properties": {
    "iso:country": "GB",
    "wof:name": "PR1 9ZD",
    "wof:placetype": "postalcode"
  },
  "geometry": {"coordinates":[-2.717454,53.741862],"type":"Point"}
}
