{
  "type": "Feature",
  "properties": {
    "iso:country":"GB",
    "wof:name":"EH54 8JT",
    "wof:placetype":"postalcode"
},
  "geometry": {"coordinates":[-3.53709414243624,55.90150893091228],"type":"Point"}
}