{
  "type": "Feature",
  "properties": {
    "iso:country": "GB",
    "wof:name": "CA11 9SA",
    "wof:placetype": "postalcode"
  },
  "geometry": {"coordinates":[-2.878792,54.711275],"type":"Point"}
}
