{
  "type": "Feature",
  "properties": {
    "date:inception_lower":"1990-07-01",
    "date:inception_upper":"1990-07-31",
    "iso:country":"GB",
    "wof:name":"CA11 9SA",
    "wof:placetype":"postalcode"
},
  "geometry": {"coordinates":[-2.878792,54.711275],"type":"Point"}
}