{
  "type": "Feature",
  "properties": {
    "iso:country":"GB",
    "wof:name":"CA11 9SA",
    "wof:placetype":"postalcode"
},
  "geometry": {"coordinates":[-2.87879229586996,54.71127505374315],"type":"Point"}
}