{
  "type": "Feature",
  "properties": {
    "iso:country": "GB",
    "wof:name": "SA10 7NQ",
    "wof:placetype": "postalcode"
  },
  "geometry": {"coordinates":[-3.83052,51.661099],"type":"Point"}
}
