{
  "type": "Feature",
  "properties": {
    "iso:country":"GB",
    "wof:name":"CH65 9HQ",
    "wof:placetype":"postalcode"
},
  "geometry": {"coordinates":[-2.89309509576718,53.26000234848301],"type":"Point"}
}