{
  "type": "Feature",
  "properties": {
    "iso:country":"GB",
    "wof:name":"WV14 8BT",
    "wof:placetype":"postalcode"
},
  "geometry": {"coordinates":[-2.05868498579314,52.55284669200903],"type":"Point"}
}