{
  "type": "Feature",
  "properties": {
    "iso:country": "GB",
    "wof:name": "WV14 8BT",
    "wof:placetype": "postalcode"
  },
  "geometry": {"coordinates":[-2.058685,52.552847],"type":"Point"}
}
