{
  "type": "Feature",
  "properties": {
    "iso:country":"GB",
    "wof:name":"DL13 3QG",
    "wof:placetype":"postalcode"
},
  "geometry": {"coordinates":[-1.83686054589316,54.67193580912677],"type":"Point"}
}