{
  "type": "Feature",
  "properties": {
    "iso:country": "GB",
    "wof:name": "GU16 8PS",
    "wof:placetype": "postalcode"
  },
  "geometry": {"coordinates":[-0.726532,51.321693],"type":"Point"}
}
