{
  "type": "Feature",
  "properties": {
    "iso:country":"GB",
    "wof:name":"NN8 3DR",
    "wof:placetype":"postalcode"
},
  "geometry": {"coordinates":[-0.72729189577411,52.29824174031232],"type":"Point"}
}