{
  "type": "Feature",
  "properties": {
    "iso:country":"GB",
    "wof:name":"B5 7PF",
    "wof:placetype":"postalcode"
},
  "geometry": {"coordinates":[-1.90430941300214,52.45913894125017],"type":"Point"}
}