{
  "type": "Feature",
  "properties": {
    "iso:country": "GB",
    "wof:name": "M12 6DA",
    "wof:placetype": "postalcode"
  },
  "geometry": {"coordinates":[-2.218871,53.471531],"type":"Point"}
}
