{
  "type": "Feature",
  "properties": {
    "iso:country":"GB",
    "wof:name":"N3 1BL",
    "wof:placetype":"postalcode"
},
  "geometry": {"coordinates":[-0.20021514880054,51.60075861874019],"type":"Point"}
}