{
  "type": "Feature",
  "properties": {
    "iso:country": "GB",
    "wof:name": "N3 1BL",
    "wof:placetype": "postalcode"
  },
  "geometry": {"coordinates":[-0.200215,51.600759],"type":"Point"}
}
