{
  "type": "Feature",
  "properties": {
    "iso:country": "GB",
    "wof:name": "CW9 7DL",
    "wof:placetype": "postalcode"
  },
  "geometry": {"coordinates":[-2.490465,53.257036],"type":"Point"}
}
