{
  "type": "Feature",
  "properties": {
    "iso:country":"GB",
    "wof:name":"HD9 4HY",
    "wof:placetype":"postalcode"
},
  "geometry": {"coordinates":[-1.85879243637144,53.58799421308747],"type":"Point"}
}