{
  "type": "Feature",
  "properties": {
    "iso:country":"GB",
    "wof:name":"CR3 6BH",
    "wof:placetype":"postalcode"
},
  "geometry": {"coordinates":[-0.08404252067773,51.27594776634133],"type":"Point"}
}