{
  "type": "Feature",
  "properties": {
    "iso:country": "GB",
    "wof:name": "BA22 9LL",
    "wof:placetype": "postalcode"
  },
  "geometry": {"coordinates":[-2.666152,50.922565],"type":"Point"}
}
