{
  "type": "Feature",
  "properties": {
    "iso:country":"GB",
    "wof:name":"SO45 5DZ",
    "wof:placetype":"postalcode"
},
  "geometry": {"coordinates":[-1.40908706172859,50.86362148738267],"type":"Point"}
}