{
  "type": "Feature",
  "properties": {
    "iso:country": "GB",
    "wof:name": "DT4 8HB",
    "wof:placetype": "postalcode"
  },
  "geometry": {"coordinates":[-2.454982,50.609114],"type":"Point"}
}
