{
  "type": "Feature",
  "properties": {
    "iso:country":"GB",
    "wof:name":"DT4 8HB",
    "wof:placetype":"postalcode"
},
  "geometry": {"coordinates":[-2.45498191011835,50.60911417718302],"type":"Point"}
}