{
  "type": "Feature",
  "properties": {
    "iso:country": "GB",
    "wof:name": "HU3 2AH",
    "wof:placetype": "postalcode"
  },
  "geometry": {"coordinates":[-0.358043,53.735869],"type":"Point"}
}
