{
  "type": "Feature",
  "properties": {
    "iso:country":"GB",
    "wof:name":"HU3 2AH",
    "wof:placetype":"postalcode"
},
  "geometry": {"coordinates":[-0.35804323022739,53.7358690217002],"type":"Point"}
}