{
  "type": "Feature",
  "properties": {
    "iso:country":"GB",
    "wof:name":"TQ2 6TR",
    "wof:placetype":"postalcode"
},
  "geometry": {"coordinates":[-3.55630345119601,50.45928585849154],"type":"Point"}
}