{
  "type": "Feature",
  "properties": {
    "iso:country":"GB",
    "wof:name":"KA19 7EN",
    "wof:placetype":"postalcode"
},
  "geometry": {"coordinates":[-4.68031821526436,55.35566201382569],"type":"Point"}
}