{
  "type": "Feature",
  "properties": {
    "date:inception_lower": "1980-01-01",
    "date:inception_upper": "1980-01-01",
    "iso:country": "GB",
    "wof:name": "DN17 1AS",
    "wof:placetype": "postalcode"
  },
  "geometry": {"coordinates":[-0.665452,53.576601],"type":"Point"}
}
