{
  "type": "Feature",
  "properties": {
    "date:inception_lower": "1980-01-01",
    "date:inception_upper": "1980-01-01",
    "iso:country": "GB",
    "wof:name": "BB5 4PE",
    "wof:placetype": "postalcode"
  },
  "geometry": {"coordinates":[-2.395391,53.751512],"type":"Point"}
}
