{
  "type": "Feature",
  "properties": {
    "iso:country":"GB",
    "wof:name":"LA14 5UY",
    "wof:placetype":"postalcode"
},
  "geometry": {"coordinates":[-3.23795229094511,54.12635554365673],"type":"Point"}
}