{
  "type": "Feature",
  "properties": {
    "iso:country":"GB",
    "wof:name":"M40 1JG",
    "wof:placetype":"postalcode"
},
  "geometry": {"coordinates":[-2.17906161748584,53.49824807448484],"type":"Point"}
}