{
  "type": "Feature",
  "properties": {
    "iso:country":"GB",
    "wof:name":"M7 1SW",
    "wof:placetype":"postalcode"
},
  "geometry": {"coordinates":[-2.25363796164027,53.4936456847914],"type":"Point"}
}