{
  "type": "Feature",
  "properties": {
    "iso:country":"GB",
    "wof:name":"NR18 9ER",
    "wof:placetype":"postalcode"
},
  "geometry": {"coordinates":[1.08787229016072,52.5811301671668],"type":"Point"}
}