{
  "type": "Feature",
  "properties": {
    "date:inception_lower": "1980-01-01",
    "date:inception_upper": "1980-01-01",
    "iso:country": "GB",
    "wof:name": "NE63 9PS",
    "wof:placetype": "postalcode"
  },
  "geometry": {"coordinates":[-1.554044,55.176043],"type":"Point"}
}
