{
  "type": "Feature",
  "properties": {
    "iso:country": "GB",
    "wof:name": "NE63 9PS",
    "wof:placetype": "postalcode"
  },
  "geometry": {"coordinates":[-1.554044,55.176043],"type":"Point"}
}
