{
  "type": "Feature",
  "properties": {
    "iso:country":"GB",
    "wof:name":"AB16 7EW",
    "wof:placetype":"postalcode"
},
  "geometry": {"coordinates":[-2.16761440883215,57.17024600135709],"type":"Point"}
}