{
  "type": "Feature",
  "properties": {
    "iso:country":"GB",
    "wof:name":"NE65 0LX",
    "wof:placetype":"postalcode"
},
  "geometry": {"coordinates":[-1.5871192670155,55.33161512574475],"type":"Point"}
}