{
  "type": "Feature",
  "properties": {
    "iso:country": "GB",
    "wof:name": "FK2 0YE",
    "wof:placetype": "postalcode"
  },
  "geometry": {"coordinates":[-3.678895,55.999637],"type":"Point"}
}
