{
  "type": "Feature",
  "properties": {
    "date:inception_lower": "1990-07-01",
    "date:inception_upper": "1990-07-01",
    "iso:country": "GB",
    "wof:name": "CR6 9AB",
    "wof:placetype": "postalcode"
  },
  "geometry": {"coordinates":[-0.059293,51.320594],"type":"Point"}
}
