{
  "type": "Feature",
  "properties": {
    "iso:country": "GB",
    "wof:name": "CR6 9AB",
    "wof:placetype": "postalcode"
  },
  "geometry": {"coordinates":[-0.059164,51.320934],"type":"Point"}
}
