{
  "type": "Feature",
  "properties": {
    "iso:country":"GB",
    "wof:name":"CR6 9AB",
    "wof:placetype":"postalcode"
},
  "geometry": {"coordinates":[-0.05918500746738,51.32040384051899],"type":"Point"}
}