{
  "type": "Feature",
  "properties": {
    "iso:country": "GB",
    "wof:name": "ML3 8NP",
    "wof:placetype": "postalcode"
  },
  "geometry": {"coordinates":[-4.059203,55.773599],"type":"Point"}
}
