{
  "type": "Feature",
  "properties": {
    "iso:country":"GB",
    "wof:name":"ML3 8NP",
    "wof:placetype":"postalcode"
},
  "geometry": {"coordinates":[-4.05920288294918,55.77359913132224],"type":"Point"}
}