{
  "type": "Feature",
  "properties": {
    "iso:country": "GB",
    "wof:name": "NG13 8LJ",
    "wof:placetype": "postalcode"
  },
  "geometry": {"coordinates":[-0.961793,52.983657],"type":"Point"}
}
