{
  "type": "Feature",
  "properties": {
    "iso:country":"GB",
    "wof:name":"NG13 8LJ",
    "wof:placetype":"postalcode"
},
  "geometry": {"coordinates":[-0.96179316422196,52.98365705315241],"type":"Point"}
}