{
  "type": "Feature",
  "properties": {
    "date:inception_lower":"1994-12-01",
    "date:inception_upper":"1994-12-31",
    "iso:country":"GB",
    "wof:name":"LN10 6XX",
    "wof:placetype":"postalcode"
},
  "geometry": {"coordinates":[-0.242482,53.140456],"type":"Point"}
}