{
  "type": "Feature",
  "properties": {
    "iso:country":"GB",
    "wof:name":"LN10 6XX",
    "wof:placetype":"postalcode"
},
  "geometry": {"coordinates":[-0.24269712651379,53.14038082297196],"type":"Point"}
}