{
  "type": "Feature",
  "properties": {
    "date:inception_lower": "1994-12-01",
    "date:inception_upper": "1994-12-01",
    "iso:country": "GB",
    "wof:name": "LN10 6XX",
    "wof:placetype": "postalcode"
  },
  "geometry": {"coordinates":[-0.243144,53.14034],"type":"Point"}
}
