{
  "type": "Feature",
  "properties": {
    "iso:country": "GB",
    "wof:name": "NN15 6BL",
    "wof:placetype": "postalcode"
  },
  "geometry": {"coordinates":[-0.727646,52.390221],"type":"Point"}
}
