{
  "type": "Feature",
  "properties": {
    "iso:country":"GB",
    "wof:name":"NN15 6BL",
    "wof:placetype":"postalcode"
},
  "geometry": {"coordinates":[-0.72764601493764,52.39022067726273],"type":"Point"}
}