{
  "type": "Feature",
  "properties": {
    "iso:country":"GB",
    "wof:name":"W3 9PZ",
    "wof:placetype":"postalcode"
},
  "geometry": {"coordinates":[-0.2820671210424,51.51132486066624],"type":"Point"}
}