{
  "type": "Feature",
  "properties": {
    "iso:country":"GB",
    "wof:name":"UB4 9PR",
    "wof:placetype":"postalcode"
},
  "geometry": {"coordinates":[-0.38883459394607,51.52778506839579],"type":"Point"}
}