{
  "type": "Feature",
  "properties": {
    "date:inception_lower": "1980-01-01",
    "date:inception_upper": "1980-01-01",
    "iso:country": "GB",
    "wof:name": "SR4 7QD",
    "wof:placetype": "postalcode"
  },
  "geometry": {"coordinates":[-1.4124,54.896016],"type":"Point"}
}
