{
  "type": "Feature",
  "properties": {
    "iso:country":"GB",
    "wof:name":"SR4 7QD",
    "wof:placetype":"postalcode"
},
  "geometry": {"coordinates":[-1.41239956087174,54.89601559762325],"type":"Point"}
}