{
  "type": "Feature",
  "properties": {
    "iso:country": "GB",
    "wof:name": "PO14 4RG",
    "wof:placetype": "postalcode"
  },
  "geometry": {"coordinates":[-1.262229,50.852175],"type":"Point"}
}
