{
  "type": "Feature",
  "properties": {
    "iso:country": "GB",
    "wof:name": "GU33 6BL",
    "wof:placetype": "postalcode"
  },
  "geometry": {"coordinates":[-0.886739,51.0927],"type":"Point"}
}
