{
  "type": "Feature",
  "properties": {
    "iso:country":"GB",
    "wof:name":"GU33 6BL",
    "wof:placetype":"postalcode"
},
  "geometry": {"coordinates":[-0.88673948236133,51.09270007086405],"type":"Point"}
}