{
  "type": "Feature",
  "properties": {
    "date:inception_lower": "1980-01-01",
    "date:inception_upper": "1980-01-01",
    "iso:country": "GB",
    "wof:name": "GU33 6BL",
    "wof:placetype": "postalcode"
  },
  "geometry": {"coordinates":[-0.886739,51.0927],"type":"Point"}
}
