{
  "type": "Feature",
  "properties": {
    "iso:country":"GB",
    "wof:name":"L23 2TX",
    "wof:placetype":"postalcode"
},
  "geometry": {"coordinates":[-3.02471801410917,53.49726890549667],"type":"Point"}
}