{
  "type": "Feature",
  "properties": {
    "iso:country":"GB",
    "wof:name":"BB3 0LH",
    "wof:placetype":"postalcode"
},
  "geometry": {"coordinates":[-2.50533402869126,53.72079053962811],"type":"Point"}
}