{
  "type": "Feature",
  "properties": {
    "date:inception_lower": "2019-05-01",
    "date:inception_upper": "2019-05-01",
    "iso:country": "GB",
    "wof:name": "HU16 5FL",
    "wof:placetype": "postalcode"
  },
  "geometry": {"coordinates":[-0.437473,53.775254],"type":"Point"}
}
