{
  "type": "Feature",
  "properties": {
    "iso:country":"GB",
    "wof:name":"NE28 6LX",
    "wof:placetype":"postalcode"
},
  "geometry": {"coordinates":[-1.49948535403439,54.99128325436677],"type":"Point"}
}