{
  "type": "Feature",
  "properties": {
    "iso:country":"GB",
    "wof:name":"MK45 3HT",
    "wof:placetype":"postalcode"
},
  "geometry": {"coordinates":[-0.46698928500593,52.08648235634765],"type":"Point"}
}