{
  "type": "Feature",
  "properties": {
    "date:inception_lower": "1994-12-01",
    "date:inception_upper": "1994-12-01",
    "iso:country": "GB",
    "wof:name": "SO32 2BU",
    "wof:placetype": "postalcode"
  },
  "geometry": {"coordinates":[-1.279526,50.943827],"type":"Point"}
}
