{
  "type": "Feature",
  "properties": {
    "iso:country":"GB",
    "wof:name":"SO32 2BU",
    "wof:placetype":"postalcode"
},
  "geometry": {"coordinates":[-1.27952607620566,50.94382671384339],"type":"Point"}
}