{
  "type": "Feature",
  "properties": {
    "iso:country":"GB",
    "wof:name":"DL4 1EF",
    "wof:placetype":"postalcode"
},
  "geometry": {"coordinates":[-1.64740577424774,54.63457063427326],"type":"Point"}
}