{
  "type": "Feature",
  "properties": {
    "iso:country":"GB",
    "wof:name":"LA4 4LG",
    "wof:placetype":"postalcode"
},
  "geometry": {"coordinates":[-2.86938114850108,54.06284795880743],"type":"Point"}
}