{
  "type": "Feature",
  "properties": {
    "iso:country":"GB",
    "wof:name":"SA16 0YW",
    "wof:placetype":"postalcode"
},
  "geometry": {"coordinates":[-4.25931779020879,51.68797281003655],"type":"Point"}
}