{
  "type": "Feature",
  "properties": {
    "iso:country": "GB",
    "wof:name": "LS4 2JX",
    "wof:placetype": "postalcode"
  },
  "geometry": {"coordinates":[-1.586042,53.807608],"type":"Point"}
}
