{
  "type": "Feature",
  "properties": {
    "iso:country":"GB",
    "wof:name":"LS4 2JX",
    "wof:placetype":"postalcode"
},
  "geometry": {"coordinates":[-1.5860424059498,53.8076083525089],"type":"Point"}
}