{
  "type": "Feature",
  "properties": {
    "iso:country":"GB",
    "wof:name":"NW3 4RE",
    "wof:placetype":"postalcode"
},
  "geometry": {"coordinates":[-0.15926414877723,51.54610618629791],"type":"Point"}
}