{
  "type": "Feature",
  "properties": {
    "iso:country":"GB",
    "wof:name":"EC1M 5LA",
    "wof:placetype":"postalcode"
},
  "geometry": {"coordinates":[-0.10543765617862,51.52219248356999],"type":"Point"}
}