{
  "type": "Feature",
  "properties": {
    "iso:country":"GB",
    "wof:name":"TW10 6BW",
    "wof:placetype":"postalcode"
},
  "geometry": {"coordinates":[-0.29955163031687,51.45546722656881],"type":"Point"}
}