{
  "type": "Feature",
  "properties": {
    "date:inception_lower": "1980-01-01",
    "date:inception_upper": "1980-01-01",
    "iso:country": "GB",
    "wof:name": "IP6 9UG",
    "wof:placetype": "postalcode"
  },
  "geometry": {"coordinates":[1.094905,52.15774],"type":"Point"}
}
