{
  "type": "Feature",
  "properties": {
    "iso:country":"GB",
    "wof:name":"CF14 9HP",
    "wof:placetype":"postalcode"
},
  "geometry": {"coordinates":[-3.19881730865656,51.53657500567331],"type":"Point"}
}