{
  "type": "Feature",
  "properties": {
    "date:inception_lower": "2023-11-01",
    "date:inception_upper": "2023-11-01",
    "iso:country": "GB",
    "wof:name": "ME12 3XP",
    "wof:placetype": "postalcode"
  },
  "geometry": {"coordinates":[0.808766,51.416314],"type":"Point"}
}
