{
  "type": "Feature",
  "properties": {
    "date:inception_lower": "1980-01-01",
    "date:inception_upper": "1980-01-01",
    "iso:country": "GB",
    "wof:name": "BL9 9TT",
    "wof:placetype": "postalcode"
  },
  "geometry": {"coordinates":[-2.292503,53.57127],"type":"Point"}
}
