{
  "type": "Feature",
  "properties": {
    "iso:country":"GB",
    "wof:name":"BL9 9TT",
    "wof:placetype":"postalcode"
},
  "geometry": {"coordinates":[-2.29250328686146,53.57127043870617],"type":"Point"}
}