{
  "type": "Feature",
  "properties": {
    "iso:country": "GB",
    "wof:name": "KY1 2EU",
    "wof:placetype": "postalcode"
  },
  "geometry": {"coordinates":[-3.147117,56.124313],"type":"Point"}
}
