{
  "type": "Feature",
  "properties": {
    "iso:country":"GB",
    "wof:name":"HA4 9QJ",
    "wof:placetype":"postalcode"
},
  "geometry": {"coordinates":[-0.38811766584549,51.57134238226111],"type":"Point"}
}