{
  "type": "Feature",
  "properties": {
    "iso:country": "GB",
    "wof:name": "IV32 7NS",
    "wof:placetype": "postalcode"
  },
  "geometry": {"coordinates":[-3.108752,57.674005],"type":"Point"}
}
