{
  "type": "Feature",
  "properties": {
    "iso:country":"GB",
    "wof:name":"ME12 3QR",
    "wof:placetype":"postalcode"
},
  "geometry": {"coordinates":[0.82937816275912,51.42330659871361],"type":"Point"}
}