{
  "type": "Feature",
  "properties": {
    "iso:country": "GB",
    "wof:name": "ME12 3QR",
    "wof:placetype": "postalcode"
  },
  "geometry": {"coordinates":[0.829378,51.423307],"type":"Point"}
}
