{
  "type": "Feature",
  "properties": {
    "date:inception_lower":"1988-03-01",
    "date:inception_upper":"1988-03-31",
    "iso:country":"GB",
    "wof:name":"CW9 7RB",
    "wof:placetype":"postalcode"
},
  "geometry": {"coordinates":[-2.486416,53.24765],"type":"Point"}
}