{
  "type": "Feature",
  "properties": {
    "iso:country": "GB",
    "wof:name": "CW9 7RB",
    "wof:placetype": "postalcode"
  },
  "geometry": {"coordinates":[-2.486416,53.24765],"type":"Point"}
}
