{
  "type": "Feature",
  "properties": {
    "iso:country":"GB",
    "wof:name":"CO3 3QW",
    "wof:placetype":"postalcode"
},
  "geometry": {"coordinates":[0.8777844229175,51.88935690112294],"type":"Point"}
}