{
  "type": "Feature",
  "properties": {
    "iso:country": "GB",
    "wof:name": "NG20 9QE",
    "wof:placetype": "postalcode"
  },
  "geometry": {"coordinates":[-1.138192,53.218716],"type":"Point"}
}
