{
  "type": "Feature",
  "properties": {
    "date:inception_lower": "1980-01-01",
    "date:inception_upper": "1980-01-01",
    "iso:country": "GB",
    "wof:name": "NG4 2DX",
    "wof:placetype": "postalcode"
  },
  "geometry": {"coordinates":[-1.090404,52.955764],"type":"Point"}
}
