{
  "type": "Feature",
  "properties": {
    "iso:country":"GB",
    "wof:name":"DE21 7LT",
    "wof:placetype":"postalcode"
},
  "geometry": {"coordinates":[-1.38801257978413,52.92610653890834],"type":"Point"}
}