{
  "type": "Feature",
  "properties": {
    "iso:country":"GB",
    "wof:name":"SE5 7JB",
    "wof:placetype":"postalcode"
},
  "geometry": {"coordinates":[-0.09351568578387,51.47767488788791],"type":"Point"}
}