{
  "type": "Feature",
  "properties": {
    "iso:country":"GB",
    "wof:name":"CH1 6HX",
    "wof:placetype":"postalcode"
},
  "geometry": {"coordinates":[-2.99404340422939,53.23922029350048],"type":"Point"}
}