{
  "type": "Feature",
  "properties": {
    "iso:country":"GB",
    "wof:name":"HP12 3LX",
    "wof:placetype":"postalcode"
},
  "geometry": {"coordinates":[-0.78319814054452,51.62176347097207],"type":"Point"}
}