{
  "type": "Feature",
  "properties": {
    "iso:country":"GB",
    "wof:name":"AL9 5BY",
    "wof:placetype":"postalcode"
},
  "geometry": {"coordinates":[-0.21396082566978,51.77501223855644],"type":"Point"}
}