{
  "type": "Feature",
  "properties": {
    "date:inception_lower": "1985-10-01",
    "date:inception_upper": "1985-10-01",
    "iso:country": "GB",
    "wof:name": "AL9 5BY",
    "wof:placetype": "postalcode"
  },
  "geometry": {"coordinates":[-0.213961,51.775012],"type":"Point"}
}
