{
  "type": "Feature",
  "properties": {
    "iso:country":"GB",
    "wof:name":"AB41 8EG",
    "wof:placetype":"postalcode"
},
  "geometry": {"coordinates":[-2.02860513349006,57.42105578183791],"type":"Point"}
}