{
  "type": "Feature",
  "properties": {
    "date:inception_lower": "1980-01-01",
    "date:inception_upper": "1980-01-01",
    "iso:country": "GB",
    "wof:name": "IV2 3PS",
    "wof:placetype": "postalcode"
  },
  "geometry": {"coordinates":[-4.208796,57.481789],"type":"Point"}
}
