{
  "type": "Feature",
  "properties": {
    "date:inception_lower": "2019-07-01",
    "date:inception_upper": "2019-07-01",
    "iso:country": "GB",
    "wof:name": "B66 2AZ",
    "wof:placetype": "postalcode"
  },
  "geometry": {"coordinates":[-1.951169,52.493713],"type":"Point"}
}
