{
  "type": "Feature",
  "properties": {
    "iso:country": "GB",
    "wof:name": "CT7 9JA",
    "wof:placetype": "postalcode"
  },
  "geometry": {"coordinates":[1.298233,51.377904],"type":"Point"}
}
