{
  "type": "Feature",
  "properties": {
    "date:inception_lower": "2023-08-01",
    "date:inception_upper": "2023-08-01",
    "iso:country": "GB",
    "wof:name": "CV7 8QR",
    "wof:placetype": "postalcode"
  },
  "geometry": {"coordinates":[-1.541338,52.449864],"type":"Point"}
}
