{
  "type": "Feature",
  "properties": {
    "date:inception_lower": "2021-06-01",
    "date:inception_upper": "2021-06-01",
    "iso:country": "GB",
    "wof:name": "CV7 8QR",
    "wof:placetype": "postalcode"
  },
  "geometry": {"coordinates":[-1.551259,52.46977],"type":"Point"}
}
