{
  "type": "Feature",
  "properties": {
    "iso:country":"GB",
    "wof:name":"MK13 8NQ",
    "wof:placetype":"postalcode"
},
  "geometry": {"coordinates":[-0.77675441412215,52.04394320213759],"type":"Point"}
}