{
  "type": "Feature",
  "properties": {
    "iso:country": "GB",
    "wof:name": "CF83 3RN",
    "wof:placetype": "postalcode"
  },
  "geometry": {"coordinates":[-3.204327,51.574502],"type":"Point"}
}
