{
  "type": "Feature",
  "properties": {
    "iso:country":"GB",
    "wof:name":"CF83 3RN",
    "wof:placetype":"postalcode"
},
  "geometry": {"coordinates":[-3.20438782066257,51.57443647388372],"type":"Point"}
}