{
  "type": "Feature",
  "properties": {
    "iso:country": "GB",
    "wof:name": "GU11 3UE",
    "wof:placetype": "postalcode"
  },
  "geometry": {"coordinates":[-0.759913,51.236993],"type":"Point"}
}
