{
  "type": "Feature",
  "properties": {
    "iso:country":"GB",
    "wof:name":"GU11 3UE",
    "wof:placetype":"postalcode"
},
  "geometry": {"coordinates":[-0.75991265798654,51.23699328745645],"type":"Point"}
}