{
  "type": "Feature",
  "properties": {
    "iso:country": "GB",
    "wof:name": "WA6 0NH",
    "wof:placetype": "postalcode"
  },
  "geometry": {"coordinates":[-2.794542,53.247747],"type":"Point"}
}
