{
  "type": "Feature",
  "properties": {
    "iso:country":"GB",
    "wof:name":"WA6 0NH",
    "wof:placetype":"postalcode"
},
  "geometry": {"coordinates":[-2.7945415577971,53.24774686857766],"type":"Point"}
}