{
  "type": "Feature",
  "properties": {
    "iso:country": "GB",
    "wof:name": "ST6 6RL",
    "wof:placetype": "postalcode"
  },
  "geometry": {"coordinates":[-2.189519,53.074098],"type":"Point"}
}
