{
  "type": "Feature",
  "properties": {
    "iso:country": "GB",
    "wof:name": "EX14 9DJ",
    "wof:placetype": "postalcode"
  },
  "geometry": {"coordinates":[-3.089768,50.823974],"type":"Point"}
}
