{
  "type": "Feature",
  "properties": {
    "iso:country":"GB",
    "wof:name":"OL6 8XW",
    "wof:placetype":"postalcode"
},
  "geometry": {"coordinates":[-2.09568334665347,53.50441124858802],"type":"Point"}
}