{
  "type": "Feature",
  "properties": {
    "iso:country": "GB",
    "wof:name": "WS7 4YE",
    "wof:placetype": "postalcode"
  },
  "geometry": {"coordinates":[-1.929493,52.669824],"type":"Point"}
}
