{
  "type": "Feature",
  "properties": {
    "iso:country": "GB",
    "wof:name": "NG14 6FB",
    "wof:placetype": "postalcode"
  },
  "geometry": {"coordinates":[-1.089611,53.037472],"type":"Point"}
}
