{
  "type": "Feature",
  "properties": {
    "iso:country":"GB",
    "wof:name":"ST13 6BE",
    "wof:placetype":"postalcode"
},
  "geometry": {"coordinates":[-2.01736292086817,53.11071654699897],"type":"Point"}
}