{
  "type": "Feature",
  "properties": {
    "iso:country":"GB",
    "wof:name":"WN3 5TU",
    "wof:placetype":"postalcode"
},
  "geometry": {"coordinates":[-2.64322806210513,53.5343305529371],"type":"Point"}
}