{
  "type": "Feature",
  "properties": {
    "date:inception_lower":"1980-01-01",
    "date:inception_upper":"1980-01-31",
    "iso:country":"GB",
    "wof:name":"WN3 5TU",
    "wof:placetype":"postalcode"
},
  "geometry": {"coordinates":[-2.643228,53.534331],"type":"Point"}
}