{
  "type": "Feature",
  "properties": {
    "iso:country":"GB",
    "wof:name":"TN27 8PA",
    "wof:placetype":"postalcode"
},
  "geometry": {"coordinates":[0.69023447250772,51.16343998261364],"type":"Point"}
}