{
  "type": "Feature",
  "properties": {
    "iso:country":"GB",
    "wof:name":"BD16 1DU",
    "wof:placetype":"postalcode"
},
  "geometry": {"coordinates":[-1.83187312623728,53.84289769543277],"type":"Point"}
}