{
  "type": "Feature",
  "properties": {
    "iso:country":"GB",
    "wof:name":"SS0 7PS",
    "wof:placetype":"postalcode"
},
  "geometry": {"coordinates":[0.70027104244538,51.53576235467265],"type":"Point"}
}