{
  "type": "Feature",
  "properties": {
    "iso:country":"GB",
    "wof:name":"BD12 9JP",
    "wof:placetype":"postalcode"
},
  "geometry": {"coordinates":[-1.76862947248952,53.7360242224937],"type":"Point"}
}