{
  "type": "Feature",
  "properties": {
    "iso:country": "GB",
    "wof:name": "WS13 7HF",
    "wof:placetype": "postalcode"
  },
  "geometry": {"coordinates":[-1.838353,52.690537],"type":"Point"}
}
