{
  "type": "Feature",
  "properties": {
    "iso:country":"GB",
    "wof:name":"WS13 7HF",
    "wof:placetype":"postalcode"
},
  "geometry": {"coordinates":[-1.83835339047344,52.69053728865265],"type":"Point"}
}