{
  "type": "Feature",
  "properties": {
    "iso:country": "GB",
    "wof:name": "RG1 4FH",
    "wof:placetype": "postalcode"
  },
  "geometry": {"coordinates":[-0.960673,51.451835],"type":"Point"}
}
