{
  "type": "Feature",
  "properties": {
    "date:inception_lower": "2018-10-01",
    "date:inception_upper": "2018-10-01",
    "iso:country": "GB",
    "wof:name": "RG1 4FH",
    "wof:placetype": "postalcode"
  },
  "geometry": {"coordinates":[-0.960673,51.451835],"type":"Point"}
}
