{
  "type": "Feature",
  "properties": {
    "iso:country":"GB",
    "wof:name":"WN1 3JS",
    "wof:placetype":"postalcode"
},
  "geometry": {"coordinates":[-2.61454702344911,53.54685860854693],"type":"Point"}
}