{
  "type": "Feature",
  "properties": {
    "iso:country":"GB",
    "wof:name":"SW13 0BS",
    "wof:placetype":"postalcode"
},
  "geometry": {"coordinates":[-0.23911375499039,51.4726499114869],"type":"Point"}
}