{
  "type": "Feature",
  "properties": {
    "iso:country":"GB",
    "wof:name":"CR4 2AA",
    "wof:placetype":"postalcode"
},
  "geometry": {"coordinates":[-0.15652135489715,51.41330632932162],"type":"Point"}
}