{
  "type": "Feature",
  "properties": {
    "iso:country": "GB",
    "wof:name": "SE8 4DT",
    "wof:placetype": "postalcode"
  },
  "geometry": {"coordinates":[-0.027027,51.470316],"type":"Point"}
}
