{
  "type": "Feature",
  "properties": {
    "iso:country":"GB",
    "wof:name":"WV7 3EP",
    "wof:placetype":"postalcode"
},
  "geometry": {"coordinates":[-2.28471186286958,52.64027692234566],"type":"Point"}
}