{
  "type": "Feature",
  "properties": {
    "iso:country": "GB",
    "wof:name": "WV7 3EP",
    "wof:placetype": "postalcode"
  },
  "geometry": {"coordinates":[-2.284712,52.640277],"type":"Point"}
}
