{
  "type": "Feature",
  "properties": {
    "date:inception_lower": "1980-01-01",
    "date:inception_upper": "1980-01-01",
    "iso:country": "GB",
    "wof:name": "N4 4LD",
    "wof:placetype": "postalcode"
  },
  "geometry": {"coordinates":[-0.1092,51.576469],"type":"Point"}
}
