{
  "type": "Feature",
  "properties": {
    "iso:country": "GB",
    "wof:name": "DE56 4FG",
    "wof:placetype": "postalcode"
  },
  "geometry": {"coordinates":[-1.494244,52.994062],"type":"Point"}
}
