{
  "type": "Feature",
  "properties": {
    "iso:country":"GB",
    "wof:name":"DE56 4FG",
    "wof:placetype":"postalcode"
},
  "geometry": {"coordinates":[-1.49463787197449,52.99382075457969],"type":"Point"}
}