{
  "type": "Feature",
  "properties": {
    "iso:country": "GB",
    "wof:name": "LE4 7NJ",
    "wof:placetype": "postalcode"
  },
  "geometry": {"coordinates":[-1.107654,52.664582],"type":"Point"}
}
