{
  "type": "Feature",
  "properties": {
    "date:inception_lower": "1980-01-01",
    "date:inception_upper": "1980-01-01",
    "iso:country": "GB",
    "wof:name": "DT11 0RN",
    "wof:placetype": "postalcode"
  },
  "geometry": {"coordinates":[-2.278045,50.898533],"type":"Point"}
}
