{
  "type": "Feature",
  "properties": {
    "iso:country":"GB",
    "wof:name":"G82 2LG",
    "wof:placetype":"postalcode"
},
  "geometry": {"coordinates":[-4.55445496102217,55.94489029182415],"type":"Point"}
}