{
  "type": "Feature",
  "properties": {
    "date:inception_lower": "1989-07-01",
    "date:inception_upper": "1989-07-01",
    "iso:country": "GB",
    "wof:name": "G82 2LG",
    "wof:placetype": "postalcode"
  },
  "geometry": {"coordinates":[-4.554455,55.94489],"type":"Point"}
}
