{
  "type": "Feature",
  "properties": {
    "iso:country":"GB",
    "wof:name":"RH10 7AD",
    "wof:placetype":"postalcode"
},
  "geometry": {"coordinates":[-0.1595251841526,51.11659917156471],"type":"Point"}
}