{
  "type": "Feature",
  "properties": {
    "iso:country": "GB",
    "wof:name": "RG4 7NS",
    "wof:placetype": "postalcode"
  },
  "geometry": {"coordinates":[-0.992837,51.483541],"type":"Point"}
}
