{
  "type": "Feature",
  "properties": {
    "date:inception_lower": "2021-01-01",
    "date:inception_upper": "2021-01-01",
    "iso:country": "GB",
    "wof:name": "DN14 5FA",
    "wof:placetype": "postalcode"
  },
  "geometry": {"coordinates":[-0.870208,53.701911],"type":"Point"}
}
