{
  "type": "Feature",
  "properties": {
    "iso:country": "GB",
    "wof:name": "SS14 2EP",
    "wof:placetype": "postalcode"
  },
  "geometry": {"coordinates":[0.466302,51.575091],"type":"Point"}
}
