{
  "type": "Feature",
  "properties": {
    "iso:country":"GB",
    "wof:name":"HP6 6PQ",
    "wof:placetype":"postalcode"
},
  "geometry": {"coordinates":[-0.56637017195998,51.67492210588506],"type":"Point"}
}