{
  "type": "Feature",
  "properties": {
    "iso:country":"GB",
    "wof:name":"TS11 6AE",
    "wof:placetype":"postalcode"
},
  "geometry": {"coordinates":[-1.02605082027918,54.59229959116821],"type":"Point"}
}