{
  "type": "Feature",
  "properties": {
    "iso:country":"GB",
    "wof:name":"CF37 5RL",
    "wof:placetype":"postalcode"
},
  "geometry": {"coordinates":[-3.3160390719035,51.58552013962736],"type":"Point"}
}