{
  "type": "Feature",
  "properties": {
    "date:inception_lower": "2002-06-01",
    "date:inception_upper": "2002-06-01",
    "iso:country": "GB",
    "wof:name": "NW9 5RF",
    "wof:placetype": "postalcode"
  },
  "geometry": {"coordinates":[-0.248322,51.595282],"type":"Point"}
}
