{
  "type": "Feature",
  "properties": {
    "iso:country": "GB",
    "wof:name": "NW9 5RF",
    "wof:placetype": "postalcode"
  },
  "geometry": {"coordinates":[-0.248322,51.595282],"type":"Point"}
}
