{
  "type": "Feature",
  "properties": {
    "iso:country":"GB",
    "wof:name":"NW9 5RF",
    "wof:placetype":"postalcode"
},
  "geometry": {"coordinates":[-0.24832201438523,51.59528173065013],"type":"Point"}
}