{
  "type": "Feature",
  "properties": {
    "date:inception_lower": "1993-01-01",
    "date:inception_upper": "1993-01-01",
    "iso:country": "GB",
    "wof:name": "DN4 7BF",
    "wof:placetype": "postalcode"
  },
  "geometry": {"coordinates":[-1.09398,53.509243],"type":"Point"}
}
