{
  "type": "Feature",
  "properties": {
    "iso:country":"GB",
    "wof:name":"EH20 9DT",
    "wof:placetype":"postalcode"
},
  "geometry": {"coordinates":[-3.15216772881635,55.88031991689513],"type":"Point"}
}