{
  "type": "Feature",
  "properties": {
    "date:inception_lower": "1980-01-01",
    "date:inception_upper": "1980-01-01",
    "iso:country": "GB",
    "wof:name": "EH20 9DT",
    "wof:placetype": "postalcode"
  },
  "geometry": {"coordinates":[-3.152168,55.88032],"type":"Point"}
}
