{
  "type": "Feature",
  "properties": {
    "iso:country": "GB",
    "wof:name": "CW1 4JJ",
    "wof:placetype": "postalcode"
  },
  "geometry": {"coordinates":[-2.441945,53.110211],"type":"Point"}
}
