{
  "type": "Feature",
  "properties": {
    "iso:country":"GB",
    "wof:name":"B79 7QQ",
    "wof:placetype":"postalcode"
},
  "geometry": {"coordinates":[-1.70250702359099,52.63387308829659],"type":"Point"}
}