{
  "type": "Feature",
  "properties": {
    "iso:country": "GB",
    "wof:name": "LL11 3DU",
    "wof:placetype": "postalcode"
  },
  "geometry": {"coordinates":[-3.081213,53.051464],"type":"Point"}
}
