{
  "type": "Feature",
  "properties": {
    "iso:country":"GB",
    "wof:name":"RG7 1TR",
    "wof:placetype":"postalcode"
},
  "geometry": {"coordinates":[-0.9237294823588,51.37370243557332],"type":"Point"}
}