{
  "type": "Feature",
  "properties": {
    "date:inception_lower": "1980-01-01",
    "date:inception_upper": "1980-01-01",
    "iso:country": "GB",
    "wof:name": "RG7 1TR",
    "wof:placetype": "postalcode"
  },
  "geometry": {"coordinates":[-0.923729,51.373702],"type":"Point"}
}
