{
  "type": "Feature",
  "properties": {
    "iso:country":"GB",
    "wof:name":"WF9 3SQ",
    "wof:placetype":"postalcode"
},
  "geometry": {"coordinates":[-1.30801695790389,53.59760099091715],"type":"Point"}
}