{
  "type": "Feature",
  "properties": {
    "date:inception_lower":"1980-01-01",
    "date:inception_upper":"1980-01-31",
    "iso:country":"GB",
    "wof:name":"CF47 9DG",
    "wof:placetype":"postalcode"
},
  "geometry": {"coordinates":[-3.392491,51.76224],"type":"Point"}
}