{
  "type": "Feature",
  "properties": {
    "iso:country":"GB",
    "wof:name":"CF47 9DG",
    "wof:placetype":"postalcode"
},
  "geometry": {"coordinates":[-3.39279456600148,51.76210546576517],"type":"Point"}
}