{
  "type": "Feature",
  "properties": {
    "iso:country": "GB",
    "wof:name": "CF47 9DG",
    "wof:placetype": "postalcode"
  },
  "geometry": {"coordinates":[-3.392491,51.76224],"type":"Point"}
}
