{
  "type": "Feature",
  "properties": {
    "iso:country":"GB",
    "wof:name":"KA8 0NQ",
    "wof:placetype":"postalcode"
},
  "geometry": {"coordinates":[-4.59018680491733,55.47186325692363],"type":"Point"}
}