{
  "type": "Feature",
  "properties": {
    "date:inception_lower": "1980-01-01",
    "date:inception_upper": "1980-01-01",
    "iso:country": "GB",
    "wof:name": "KA8 0NQ",
    "wof:placetype": "postalcode"
  },
  "geometry": {"coordinates":[-4.590187,55.471863],"type":"Point"}
}
