{
  "type": "Feature",
  "properties": {
    "iso:country":"GB",
    "wof:name":"B14 4TL",
    "wof:placetype":"postalcode"
},
  "geometry": {"coordinates":[-1.87971121038047,52.40173312341648],"type":"Point"}
}