{
  "type": "Feature",
  "properties": {
    "date:inception_lower":"1980-01-01",
    "date:inception_upper":"1980-01-31",
    "iso:country":"GB",
    "wof:name":"LA22 9AG",
    "wof:placetype":"postalcode"
},
  "geometry": {"coordinates":[-2.964733,54.432754],"type":"Point"}
}