{
  "type": "Feature",
  "properties": {
    "date:inception_lower": "2019-04-01",
    "date:inception_upper": "2019-04-01",
    "iso:country": "GB",
    "wof:name": "PE8 5AX",
    "wof:placetype": "postalcode"
  },
  "geometry": {"coordinates":[-0.563789,52.493067],"type":"Point"}
}
