{
  "type": "Feature",
  "properties": {
    "iso:country": "GB",
    "wof:name": "DE56 0LN",
    "wof:placetype": "postalcode"
  },
  "geometry": {"coordinates":[-1.440464,53.013678],"type":"Point"}
}
