{
  "type": "Feature",
  "properties": {
    "iso:country":"GB",
    "wof:name":"DE56 0LN",
    "wof:placetype":"postalcode"
},
  "geometry": {"coordinates":[-1.44046385278894,53.01367831685996],"type":"Point"}
}