{
  "type": "Feature",
  "properties": {
    "iso:country": "GB",
    "wof:name": "PL11 3EF",
    "wof:placetype": "postalcode"
  },
  "geometry": {"coordinates":[-4.370674,50.363409],"type":"Point"}
}
