{
  "type": "Feature",
  "properties": {
    "iso:country":"GB",
    "wof:name":"PL11 3EF",
    "wof:placetype":"postalcode"
},
  "geometry": {"coordinates":[-4.37067449283044,50.3634093469366],"type":"Point"}
}