{
  "type": "Feature",
  "properties": {
    "date:inception_lower":"2009-03-01",
    "date:inception_upper":"2009-03-31",
    "iso:country":"GB",
    "wof:name":"PL11 3EF",
    "wof:placetype":"postalcode"
},
  "geometry": {"coordinates":[-4.370674,50.363409],"type":"Point"}
}