{
  "type": "Feature",
  "properties": {
    "iso:country": "GB",
    "wof:name": "PO40 9GE",
    "wof:placetype": "postalcode"
  },
  "geometry": {"coordinates":[-1.521324,50.689201],"type":"Point"}
}
