{
  "type": "Feature",
  "properties": {
    "date:inception_lower": "1980-01-01",
    "date:inception_upper": "1980-01-01",
    "iso:country": "GB",
    "wof:name": "LN4 3LN",
    "wof:placetype": "postalcode"
  },
  "geometry": {"coordinates":[-0.433882,53.093209],"type":"Point"}
}
