{
  "type": "Feature",
  "properties": {
    "iso:country":"GB",
    "wof:name":"LN4 3LN",
    "wof:placetype":"postalcode"
},
  "geometry": {"coordinates":[-0.43388235669937,53.09320866813018],"type":"Point"}
}