{
  "type": "Feature",
  "properties": {
    "iso:country": "GB",
    "wof:name": "OX26 1AJ",
    "wof:placetype": "postalcode"
  },
  "geometry": {"coordinates":[-1.169786,51.89309],"type":"Point"}
}
