{
  "type": "Feature",
  "properties": {
    "iso:country":"GB",
    "wof:name":"OX26 1AJ",
    "wof:placetype":"postalcode"
},
  "geometry": {"coordinates":[-1.17028015236461,51.89096356041658],"type":"Point"}
}