{
  "type": "Feature",
  "properties": {
    "iso:country":"GB",
    "wof:name":"M22 9RX",
    "wof:placetype":"postalcode"
},
  "geometry": {"coordinates":[-2.27441785122118,53.38539585281078],"type":"Point"}
}