{
  "type": "Feature",
  "properties": {
    "iso:country": "GB",
    "wof:name": "DE55 6DR",
    "wof:placetype": "postalcode"
  },
  "geometry": {"coordinates":[-1.44384,53.116118],"type":"Point"}
}
