{
  "type": "Feature",
  "properties": {
    "iso:country":"GB",
    "wof:name":"W12 7QD",
    "wof:placetype":"postalcode"
},
  "geometry": {"coordinates":[-0.23146503199972,51.51441255483014],"type":"Point"}
}