{
  "type": "Feature",
  "properties": {
    "date:inception_lower": "1988-03-01",
    "date:inception_upper": "1988-03-01",
    "iso:country": "GB",
    "wof:name": "SW18 5SN",
    "wof:placetype": "postalcode"
  },
  "geometry": {"coordinates":[-0.198344,51.456465],"type":"Point"}
}
