{
  "type": "Feature",
  "properties": {
    "iso:country":"GB",
    "wof:name":"SP1 1LR",
    "wof:placetype":"postalcode"
},
  "geometry": {"coordinates":[-1.78416000622435,51.07459923537471],"type":"Point"}
}