{
  "type": "Feature",
  "properties": {
    "iso:country":"GB",
    "wof:name":"S81 9RD",
    "wof:placetype":"postalcode"
},
  "geometry": {"coordinates":[-1.12031628828006,53.37104804457972],"type":"Point"}
}