{
  "type": "Feature",
  "properties": {
    "date:inception_lower": "1980-01-01",
    "date:inception_upper": "1980-01-01",
    "iso:country": "GB",
    "wof:name": "GU10 2BU",
    "wof:placetype": "postalcode"
  },
  "geometry": {"coordinates":[-0.752408,51.183784],"type":"Point"}
}
