{
  "type": "Feature",
  "properties": {
    "date:inception_lower": "1980-01-01",
    "date:inception_upper": "1980-01-01",
    "iso:country": "GB",
    "wof:name": "SA71 4NG",
    "wof:placetype": "postalcode"
  },
  "geometry": {"coordinates":[-4.92987,51.675085],"type":"Point"}
}
