{
  "type": "Feature",
  "properties": {
    "iso:country":"GB",
    "wof:name":"CW7 1LL",
    "wof:placetype":"postalcode"
},
  "geometry": {"coordinates":[-2.53770461680034,53.18466882152777],"type":"Point"}
}