{
  "type": "Feature",
  "properties": {
    "iso:country": "GB",
    "wof:name": "CW7 1LL",
    "wof:placetype": "postalcode"
  },
  "geometry": {"coordinates":[-2.537705,53.184669],"type":"Point"}
}
