{
  "type": "Feature",
  "properties": {
    "iso:country":"GB",
    "wof:name":"WA14 1HY",
    "wof:placetype":"postalcode"
},
  "geometry": {"coordinates":[-2.34908671410801,53.39356013794756],"type":"Point"}
}