{
  "type": "Feature",
  "properties": {
    "iso:country":"GB",
    "wof:name":"LS10 3SG",
    "wof:placetype":"postalcode"
},
  "geometry": {"coordinates":[-1.5494446851598,53.74957540937346],"type":"Point"}
}