{
  "type": "Feature",
  "properties": {
    "date:inception_lower": "1980-01-01",
    "date:inception_upper": "1980-01-01",
    "iso:country": "GB",
    "wof:name": "NG32 3JA",
    "wof:placetype": "postalcode"
  },
  "geometry": {"coordinates":[-0.608952,53.042757],"type":"Point"}
}
