{
  "type": "Feature",
  "properties": {
    "iso:country": "GB",
    "wof:name": "NG32 3JA",
    "wof:placetype": "postalcode"
  },
  "geometry": {"coordinates":[-0.608952,53.042757],"type":"Point"}
}
