{
  "type": "Feature",
  "properties": {
    "iso:country": "GB",
    "wof:name": "WF2 6DN",
    "wof:placetype": "postalcode"
  },
  "geometry": {"coordinates":[-1.492648,53.642928],"type":"Point"}
}
