{
  "type": "Feature",
  "properties": {
    "iso:country": "GB",
    "wof:name": "PE8 6DN",
    "wof:placetype": "postalcode"
  },
  "geometry": {"coordinates":[-0.437354,52.609604],"type":"Point"}
}
