{
  "type": "Feature",
  "properties": {
    "iso:country":"GB",
    "wof:name":"PE8 6DN",
    "wof:placetype":"postalcode"
},
  "geometry": {"coordinates":[-0.43735387676836,52.60960351586115],"type":"Point"}
}