{
  "type": "Feature",
  "properties": {
    "iso:country":"GB",
    "wof:name":"LL26 0NY",
    "wof:placetype":"postalcode"
},
  "geometry": {"coordinates":[-3.73200981154405,53.14322502428139],"type":"Point"}
}