{
  "type": "Feature",
  "properties": {
    "iso:country":"GB",
    "wof:name":"SO23 7LL",
    "wof:placetype":"postalcode"
},
  "geometry": {"coordinates":[-1.30406065429594,51.10702445933567],"type":"Point"}
}