{
  "type": "Feature",
  "properties": {
    "date:inception_lower": "2018-04-01",
    "date:inception_upper": "2018-04-01",
    "iso:country": "GB",
    "wof:name": "CW7 2RY",
    "wof:placetype": "postalcode"
  },
  "geometry": {"coordinates":[-2.555735,53.196179],"type":"Point"}
}
