{
  "type": "Feature",
  "properties": {
    "iso:country": "GB",
    "wof:name": "CW7 2RY",
    "wof:placetype": "postalcode"
  },
  "geometry": {"coordinates":[-2.555735,53.196179],"type":"Point"}
}
