{
  "type": "Feature",
  "properties": {
    "iso:country": "GB",
    "wof:name": "SO16 0AR",
    "wof:placetype": "postalcode"
  },
  "geometry": {"coordinates":[-1.460865,50.942547],"type":"Point"}
}
