{
  "type": "Feature",
  "properties": {
    "date:inception_lower": "2010-03-01",
    "date:inception_upper": "2010-03-01",
    "iso:country": "GB",
    "wof:name": "SO16 0AR",
    "wof:placetype": "postalcode"
  },
  "geometry": {"coordinates":[-1.460865,50.942547],"type":"Point"}
}
