{
  "type": "Feature",
  "properties": {
    "date:inception_lower": "1980-01-01",
    "date:inception_upper": "1980-01-01",
    "iso:country": "GB",
    "wof:name": "IP31 3EE",
    "wof:placetype": "postalcode"
  },
  "geometry": {"coordinates":[0.898126,52.287147],"type":"Point"}
}
