{
  "type": "Feature",
  "properties": {
    "iso:country":"GB",
    "wof:name":"L8 8AD",
    "wof:placetype":"postalcode"
},
  "geometry": {"coordinates":[-2.96043371646565,53.39226472927022],"type":"Point"}
}