{
  "type": "Feature",
  "properties": {
    "date:inception_lower": "2006-04-01",
    "date:inception_upper": "2006-04-01",
    "iso:country": "GB",
    "wof:name": "NR3 2FA",
    "wof:placetype": "postalcode"
  },
  "geometry": {"coordinates":[1.260845,52.643436],"type":"Point"}
}
