{
  "type": "Feature",
  "properties": {
    "iso:country": "GB",
    "wof:name": "SO22 6BU",
    "wof:placetype": "postalcode"
  },
  "geometry": {"coordinates":[-1.332177,51.074082],"type":"Point"}
}
