{
  "type": "Feature",
  "properties": {
    "iso:country":"GB",
    "wof:name":"SW8 2DN",
    "wof:placetype":"postalcode"
},
  "geometry": {"coordinates":[-0.12404521016185,51.47627887001777],"type":"Point"}
}