{
  "type": "Feature",
  "properties": {
    "iso:country": "GB",
    "wof:name": "OX25 5PB",
    "wof:placetype": "postalcode"
  },
  "geometry": {"coordinates":[-1.30326,51.91879],"type":"Point"}
}
