{
  "type": "Feature",
  "properties": {
    "iso:country":"GB",
    "wof:name":"N21 3HY",
    "wof:placetype":"postalcode"
},
  "geometry": {"coordinates":[-0.08938041810838,51.630570169891],"type":"Point"}
}