{
  "type": "Feature",
  "properties": {
    "iso:country":"GB",
    "wof:name":"ME16 0HT",
    "wof:placetype":"postalcode"
},
  "geometry": {"coordinates":[0.49021087342348,51.28346744220204],"type":"Point"}
}