{
  "type": "Feature",
  "properties": {
    "date:inception_lower": "2021-05-01",
    "date:inception_upper": "2021-05-01",
    "iso:country": "GB",
    "wof:name": "PA34 9AT",
    "wof:placetype": "postalcode"
  },
  "geometry": {"coordinates":[-5.474637,56.41121],"type":"Point"}
}
