{
  "type": "Feature",
  "properties": {
    "iso:country": "GB",
    "wof:name": "WA5 8EU",
    "wof:placetype": "postalcode"
  },
  "geometry": {"coordinates":[-2.640384,53.404811],"type":"Point"}
}
