{
  "type": "Feature",
  "properties": {
    "iso:country":"GB",
    "wof:name":"SN6 8NB",
    "wof:placetype":"postalcode"
},
  "geometry": {"coordinates":[-1.61864433380864,51.56440904068742],"type":"Point"}
}