{
  "type": "Feature",
  "properties": {
    "iso:country":"GB",
    "wof:name":"LS21 1LR",
    "wof:placetype":"postalcode"
},
  "geometry": {"coordinates":[-1.62792784730416,53.9031792980063],"type":"Point"}
}