{
  "type": "Feature",
  "properties": {
    "iso:country": "GB",
    "wof:name": "NG32 3SQ",
    "wof:placetype": "postalcode"
  },
  "geometry": {"coordinates":[-0.559248,52.988667],"type":"Point"}
}
