{
  "type": "Feature",
  "properties": {
    "iso:country":"GB",
    "wof:name":"M34 7RB",
    "wof:placetype":"postalcode"
},
  "geometry": {"coordinates":[-2.09599215649002,53.44770289868737],"type":"Point"}
}