{
  "type": "Feature",
  "properties": {
    "iso:country":"GB",
    "wof:name":"W1H 1JU",
    "wof:placetype":"postalcode"
},
  "geometry": {"coordinates":[-0.16273606005751,51.5193451096515],"type":"Point"}
}