{
  "type": "Feature",
  "properties": {
    "iso:country":"GB",
    "wof:name":"N2 9DY",
    "wof:placetype":"postalcode"
},
  "geometry": {"coordinates":[-0.16226639572813,51.59113326239503],"type":"Point"}
}