{
  "type": "Feature",
  "properties": {
    "iso:country": "GB",
    "wof:name": "SE18 5LG",
    "wof:placetype": "postalcode"
  },
  "geometry": {"coordinates":[0.052443,51.489626],"type":"Point"}
}
