{
  "type": "Feature",
  "properties": {
    "iso:country":"GB",
    "wof:name":"CV23 0UY",
    "wof:placetype":"postalcode"
},
  "geometry": {"coordinates":[-1.24462685427084,52.40382378578654],"type":"Point"}
}