{
  "type": "Feature",
  "properties": {
    "iso:country":"GB",
    "wof:name":"E11 3RN",
    "wof:placetype":"postalcode"
},
  "geometry": {"coordinates":[0.03149791995802,51.56379390243378],"type":"Point"}
}