{
  "type": "Feature",
  "properties": {
    "iso:country": "GB",
    "wof:name": "AB52 6RL",
    "wof:placetype": "postalcode"
  },
  "geometry": {"coordinates":[-2.59745,57.330765],"type":"Point"}
}
