{
  "type": "Feature",
  "properties": {
    "iso:country":"GB",
    "wof:name":"AB52 6RL",
    "wof:placetype":"postalcode"
},
  "geometry": {"coordinates":[-2.59745046693785,57.33076502607937],"type":"Point"}
}