{
  "type": "Feature",
  "properties": {
    "iso:country":"GB",
    "wof:name":"AL8 6RA",
    "wof:placetype":"postalcode"
},
  "geometry": {"coordinates":[-0.21117072275266,51.80157727170347],"type":"Point"}
}