{
  "type": "Feature",
  "properties": {
    "date:inception_lower": "1990-02-01",
    "date:inception_upper": "1990-02-01",
    "iso:country": "GB",
    "wof:name": "PO15 7AD",
    "wof:placetype": "postalcode"
  },
  "geometry": {"coordinates":[-1.244396,50.878121],"type":"Point"}
}
