{
  "type": "Feature",
  "properties": {
    "iso:country":"GB",
    "wof:name":"PO15 7AD",
    "wof:placetype":"postalcode"
},
  "geometry": {"coordinates":[-1.24779749019936,50.87682120100853],"type":"Point"}
}