{
  "type": "Feature",
  "properties": {
    "date:inception_lower": "1994-05-01",
    "date:inception_upper": "1994-05-01",
    "iso:country": "GB",
    "wof:name": "NW2 4NQ",
    "wof:placetype": "postalcode"
  },
  "geometry": {"coordinates":[-0.221706,51.552204],"type":"Point"}
}
