{
  "type": "Feature",
  "properties": {
    "iso:country":"GB",
    "wof:name":"NG9 3GP",
    "wof:placetype":"postalcode"
},
  "geometry": {"coordinates":[-1.24511914657804,52.94842389448745],"type":"Point"}
}