{
  "type": "Feature",
  "properties": {
    "iso:country":"GB",
    "wof:name":"B11 4JY",
    "wof:placetype":"postalcode"
},
  "geometry": {"coordinates":[-1.87062516710062,52.45801019296982],"type":"Point"}
}