{
  "type": "Feature",
  "properties": {
    "iso:country": "GB",
    "wof:name": "B11 4JY",
    "wof:placetype": "postalcode"
  },
  "geometry": {"coordinates":[-1.870561,52.457944],"type":"Point"}
}
