{
  "type": "Feature",
  "properties": {
    "iso:country": "GB",
    "wof:name": "LS11 6DD",
    "wof:placetype": "postalcode"
  },
  "geometry": {"coordinates":[-1.54996,53.776524],"type":"Point"}
}
