{
  "type": "Feature",
  "properties": {
    "iso:country":"GB",
    "wof:name":"LS11 6DD",
    "wof:placetype":"postalcode"
},
  "geometry": {"coordinates":[-1.54996051677475,53.77652364246761],"type":"Point"}
}