{
  "type": "Feature",
  "properties": {
    "date:inception_lower": "1981-09-01",
    "date:inception_upper": "1981-09-01",
    "iso:country": "GB",
    "wof:name": "LS11 6DD",
    "wof:placetype": "postalcode"
  },
  "geometry": {"coordinates":[-1.54996,53.776524],"type":"Point"}
}
