{
  "type": "Feature",
  "properties": {
    "iso:country": "GB",
    "wof:name": "IP9 2FE",
    "wof:placetype": "postalcode"
  },
  "geometry": {"coordinates":[1.125241,51.962983],"type":"Point"}
}
