{
  "type": "Feature",
  "properties": {
    "iso:country": "GB",
    "wof:name": "TW16 7TT",
    "wof:placetype": "postalcode"
  },
  "geometry": {"coordinates":[-0.419532,51.42222],"type":"Point"}
}
