{
  "type": "Feature",
  "properties": {
    "date:inception_lower": "1980-01-01",
    "date:inception_upper": "1980-01-01",
    "iso:country": "GB",
    "wof:name": "CO7 8PH",
    "wof:placetype": "postalcode"
  },
  "geometry": {"coordinates":[1.064287,51.857792],"type":"Point"}
}
