{
  "type": "Feature",
  "properties": {
    "date:inception_lower":"1995-01-01",
    "date:inception_upper":"1995-01-31",
    "iso:country":"GB",
    "wof:name":"NE30 1ND",
    "wof:placetype":"postalcode"
},
  "geometry": {"coordinates":[-1.443429,55.00788],"type":"Point"}
}