{
  "type": "Feature",
  "properties": {
    "iso:country": "GB",
    "wof:name": "NE30 1ND",
    "wof:placetype": "postalcode"
  },
  "geometry": {"coordinates":[-1.443429,55.00788],"type":"Point"}
}
