{
  "type": "Feature",
  "properties": {
    "iso:country": "GB",
    "wof:name": "TW11 9PA",
    "wof:placetype": "postalcode"
  },
  "geometry": {"coordinates":[-0.318919,51.424678],"type":"Point"}
}
