{
  "type": "Feature",
  "properties": {
    "iso:country":"GB",
    "wof:name":"TW11 9PA",
    "wof:placetype":"postalcode"
},
  "geometry": {"coordinates":[-0.31891905313396,51.42467773218067],"type":"Point"}
}