{
  "type": "Feature",
  "properties": {
    "iso:country":"GB",
    "wof:name":"BD19 3PP",
    "wof:placetype":"postalcode"
},
  "geometry": {"coordinates":[-1.71418753098351,53.7277007529116],"type":"Point"}
}