{
  "type": "Feature",
  "properties": {
    "iso:country": "GB",
    "wof:name": "BD19 3PP",
    "wof:placetype": "postalcode"
  },
  "geometry": {"coordinates":[-1.714187,53.727701],"type":"Point"}
}
