{
  "type": "Feature",
  "properties": {
    "date:inception_lower": "2006-08-01",
    "date:inception_upper": "2006-08-01",
    "iso:country": "GB",
    "wof:name": "BD19 3PP",
    "wof:placetype": "postalcode"
  },
  "geometry": {"coordinates":[-1.714187,53.727701],"type":"Point"}
}
