{
  "type": "Feature",
  "properties": {
    "iso:country": "GB",
    "wof:name": "PR7 4JF",
    "wof:placetype": "postalcode"
  },
  "geometry": {"coordinates":[-2.609764,53.613047],"type":"Point"}
}
