{
  "type": "Feature",
  "properties": {
    "iso:country":"GB",
    "wof:name":"PR7 4JF",
    "wof:placetype":"postalcode"
},
  "geometry": {"coordinates":[-2.60976422314094,53.61304696435556],"type":"Point"}
}