{
  "type": "Feature",
  "properties": {
    "iso:country": "GB",
    "wof:name": "G1 1HJ",
    "wof:placetype": "postalcode"
  },
  "geometry": {"coordinates":[-4.248979,55.860264],"type":"Point"}
}
