{
  "type": "Feature",
  "properties": {
    "iso:country":"GB",
    "wof:name":"ME1 1NG",
    "wof:placetype":"postalcode"
},
  "geometry": {"coordinates":[0.50898661944013,51.38605220183279],"type":"Point"}
}