{
  "type": "Feature",
  "properties": {
    "iso:country":"GB",
    "wof:name":"WF4 3NX",
    "wof:placetype":"postalcode"
},
  "geometry": {"coordinates":[-1.53243947178896,53.63796674142514],"type":"Point"}
}