{
  "type": "Feature",
  "properties": {
    "iso:country": "GB",
    "wof:name": "WF4 3NX",
    "wof:placetype": "postalcode"
  },
  "geometry": {"coordinates":[-1.532439,53.637967],"type":"Point"}
}
