{
  "type": "Feature",
  "properties": {
    "iso:country": "GB",
    "wof:name": "NR33 0EF",
    "wof:placetype": "postalcode"
  },
  "geometry": {"coordinates":[1.740235,52.464356],"type":"Point"}
}
