{
  "type": "Feature",
  "properties": {
    "iso:country": "GB",
    "wof:name": "TA8 2FE",
    "wof:placetype": "postalcode"
  },
  "geometry": {"coordinates":[-2.986077,51.242799],"type":"Point"}
}
