{
  "type": "Feature",
  "properties": {
    "iso:country":"GB",
    "wof:name":"SW1P 3ER",
    "wof:placetype":"postalcode"
},
  "geometry": {"coordinates":[-0.12744782047118,51.49516367967512],"type":"Point"}
}