{
  "type": "Feature",
  "properties": {
    "iso:country":"GB",
    "wof:name":"M43 6WS",
    "wof:placetype":"postalcode"
},
  "geometry": {"coordinates":[-2.16558228154851,53.48209734733804],"type":"Point"}
}