{
  "type": "Feature",
  "properties": {
    "iso:country": "GB",
    "wof:name": "M43 6WS",
    "wof:placetype": "postalcode"
  },
  "geometry": {"coordinates":[-2.165582,53.482097],"type":"Point"}
}
