{
  "type": "Feature",
  "properties": {
    "date:inception_lower": "1980-01-01",
    "date:inception_upper": "1980-01-01",
    "iso:country": "GB",
    "wof:name": "G20 0ET",
    "wof:placetype": "postalcode"
  },
  "geometry": {"coordinates":[-4.293302,55.895656],"type":"Point"}
}
