{
  "type": "Feature",
  "properties": {
    "iso:country":"GB",
    "wof:name":"G20 0ET",
    "wof:placetype":"postalcode"
},
  "geometry": {"coordinates":[-4.29330238414761,55.89565611181805],"type":"Point"}
}