{
  "type": "Feature",
  "properties": {
    "iso:country":"GB",
    "wof:name":"PL2 1PS",
    "wof:placetype":"postalcode"
},
  "geometry": {"coordinates":[-4.16842851951815,50.38525705358524],"type":"Point"}
}