{
  "type": "Feature",
  "properties": {
    "iso:country":"GB",
    "wof:name":"PE21 6DG",
    "wof:placetype":"postalcode"
},
  "geometry": {"coordinates":[-0.01517533509972,52.97081233136715],"type":"Point"}
}