{
  "type": "Feature",
  "properties": {
    "date:inception_lower": "2008-07-01",
    "date:inception_upper": "2008-07-01",
    "iso:country": "GB",
    "wof:name": "CT16 2GN",
    "wof:placetype": "postalcode"
  },
  "geometry": {"coordinates":[1.293282,51.151143],"type":"Point"}
}
