{
  "type": "Feature",
  "properties": {
    "iso:country":"GB",
    "wof:name":"CT16 2GN",
    "wof:placetype":"postalcode"
},
  "geometry": {"coordinates":[1.29328241496676,51.1511434820239],"type":"Point"}
}