{
  "type": "Feature",
  "properties": {
    "iso:country":"GB",
    "wof:name":"LL42 1PG",
    "wof:placetype":"postalcode"
},
  "geometry": {"coordinates":[-4.05753083485883,52.72387970155832],"type":"Point"}
}