{
  "type": "Feature",
  "properties": {
    "iso:country": "GB",
    "wof:name": "NN6 0FT",
    "wof:placetype": "postalcode"
  },
  "geometry": {"coordinates":[-0.753119,52.271442],"type":"Point"}
}
