{
  "type": "Feature",
  "properties": {
    "date:inception_lower": "2019-11-01",
    "date:inception_upper": "2019-11-01",
    "iso:country": "GB",
    "wof:name": "NN6 0FT",
    "wof:placetype": "postalcode"
  },
  "geometry": {"coordinates":[-0.752345,52.271335],"type":"Point"}
}
