{
  "type": "Feature",
  "properties": {
    "date:inception_lower": "2019-03-01",
    "date:inception_upper": "2019-03-01",
    "iso:country": "GB",
    "wof:name": "SE17 3FG",
    "wof:placetype": "postalcode"
  },
  "geometry": {"coordinates":[-0.096903,51.488055],"type":"Point"}
}
