{
  "type": "Feature",
  "properties": {
    "date:inception_lower": "1980-01-01",
    "date:inception_upper": "1980-01-01",
    "iso:country": "GB",
    "wof:name": "L15 5BP",
    "wof:placetype": "postalcode"
  },
  "geometry": {"coordinates":[-2.918835,53.391334],"type":"Point"}
}
