{
  "type": "Feature",
  "properties": {
    "iso:country":"GB",
    "wof:name":"GU32 1AP",
    "wof:placetype":"postalcode"
},
  "geometry": {"coordinates":[-1.08606691218425,51.01382893711396],"type":"Point"}
}