{
  "type": "Feature",
  "properties": {
    "date:inception_lower": "2012-11-01",
    "date:inception_upper": "2012-11-01",
    "iso:country": "GB",
    "wof:name": "GU32 1AP",
    "wof:placetype": "postalcode"
  },
  "geometry": {"coordinates":[-1.086067,51.013829],"type":"Point"}
}
