{
  "type": "Feature",
  "properties": {
    "date:inception_lower":"2008-05-01",
    "date:inception_upper":"2008-05-31",
    "iso:country":"GB",
    "wof:name":"PO30 3DW",
    "wof:placetype":"postalcode"
},
  "geometry": {"coordinates":[-1.301194,50.672326],"type":"Point"}
}