{
  "type": "Feature",
  "properties": {
    "iso:country":"GB",
    "wof:name":"PO30 3DW",
    "wof:placetype":"postalcode"
},
  "geometry": {"coordinates":[-1.30119409117017,50.67232579100237],"type":"Point"}
}