{
  "type": "Feature",
  "properties": {
    "date:inception_lower": "1980-01-01",
    "date:inception_upper": "1980-01-01",
    "iso:country": "GB",
    "wof:name": "SK11 6PB",
    "wof:placetype": "postalcode"
  },
  "geometry": {"coordinates":[-2.125252,53.259984],"type":"Point"}
}
