{
  "type": "Feature",
  "properties": {
    "iso:country":"GB",
    "wof:name":"EH54 6TA",
    "wof:placetype":"postalcode"
},
  "geometry": {"coordinates":[-3.54269600995015,55.89676612298118],"type":"Point"}
}