{
  "type": "Feature",
  "properties": {
    "iso:country": "GB",
    "wof:name": "CO9 3EZ",
    "wof:placetype": "postalcode"
  },
  "geometry": {"coordinates":[0.597477,51.988563],"type":"Point"}
}
