{
  "type": "Feature",
  "properties": {
    "iso:country":"GB",
    "wof:name":"HX5 9BW",
    "wof:placetype":"postalcode"
},
  "geometry": {"coordinates":[-1.83251353415812,53.68201302903464],"type":"Point"}
}