{
  "type": "Feature",
  "properties": {
    "iso:country":"GB",
    "wof:name":"RM14 3QR",
    "wof:placetype":"postalcode"
},
  "geometry": {"coordinates":[0.2803814491729,51.54225042744927],"type":"Point"}
}