{
  "type": "Feature",
  "properties": {
    "date:inception_lower": "2001-06-01",
    "date:inception_upper": "2001-06-01",
    "iso:country": "GB",
    "wof:name": "SE5 9BQ",
    "wof:placetype": "postalcode"
  },
  "geometry": {"coordinates":[-0.100633,51.47101],"type":"Point"}
}
