{
  "type": "Feature",
  "properties": {
    "iso:country":"GB",
    "wof:name":"SE5 9BQ",
    "wof:placetype":"postalcode"
},
  "geometry": {"coordinates":[-0.10063297671656,51.47100997184357],"type":"Point"}
}