{
  "type": "Feature",
  "properties": {
    "iso:country":"GB",
    "wof:name":"PO8 0UQ",
    "wof:placetype":"postalcode"
},
  "geometry": {"coordinates":[-0.99746915294758,50.91457987726799],"type":"Point"}
}