{
  "type": "Feature",
  "properties": {
    "date:inception_lower": "2014-06-01",
    "date:inception_upper": "2014-06-01",
    "iso:country": "GB",
    "wof:name": "PO8 0UQ",
    "wof:placetype": "postalcode"
  },
  "geometry": {"coordinates":[-0.997469,50.91458],"type":"Point"}
}
