{
  "type": "Feature",
  "properties": {
    "iso:country":"GB",
    "wof:name":"WN6 7EN",
    "wof:placetype":"postalcode"
},
  "geometry": {"coordinates":[-2.65039315842345,53.551945215313],"type":"Point"}
}