{
  "type": "Feature",
  "properties": {
    "iso:country": "GB",
    "wof:name": "IP1 4AL",
    "wof:placetype": "postalcode"
  },
  "geometry": {"coordinates":[1.133487,52.06458],"type":"Point"}
}
