{
  "type": "Feature",
  "properties": {
    "iso:country":"GB",
    "wof:name":"CV2 1JD",
    "wof:placetype":"postalcode"
},
  "geometry": {"coordinates":[-1.45543159142836,52.42715197287068],"type":"Point"}
}