{
  "type": "Feature",
  "properties": {
    "iso:country":"GB",
    "wof:name":"WD7 8DU",
    "wof:placetype":"postalcode"
},
  "geometry": {"coordinates":[-0.33067262766402,51.6807469956378],"type":"Point"}
}