{
  "type": "Feature",
  "properties": {
    "iso:country": "GB",
    "wof:name": "RG42 4EW",
    "wof:placetype": "postalcode"
  },
  "geometry": {"coordinates":[-0.791979,51.428341],"type":"Point"}
}
