{
  "type": "Feature",
  "properties": {
    "iso:country":"GB",
    "wof:name":"RG42 4EW",
    "wof:placetype":"postalcode"
},
  "geometry": {"coordinates":[-0.79201021620249,51.42834033025643],"type":"Point"}
}