{
  "type": "Feature",
  "properties": {
    "date:inception_lower": "1995-07-01",
    "date:inception_upper": "1995-07-01",
    "iso:country": "GB",
    "wof:name": "RG42 4EW",
    "wof:placetype": "postalcode"
  },
  "geometry": {"coordinates":[-0.791979,51.428341],"type":"Point"}
}
