{
  "type": "Feature",
  "properties": {
    "iso:country": "GB",
    "wof:name": "L5 9PR",
    "wof:placetype": "postalcode"
  },
  "geometry": {"coordinates":[-2.993911,53.429843],"type":"Point"}
}
