{
  "type": "Feature",
  "properties": {
    "iso:country": "GB",
    "wof:name": "SN1 1BF",
    "wof:placetype": "postalcode"
  },
  "geometry": {"coordinates":[-1.783998,51.562619],"type":"Point"}
}
