{
  "type": "Feature",
  "properties": {
    "iso:country": "GB",
    "wof:name": "SN1 1BF",
    "wof:placetype": "postalcode"
  },
  "geometry": {"coordinates":[-1.783724,51.562564],"type":"Point"}
}
