{
  "type": "Feature",
  "properties": {
    "date:inception_lower":"1995-12-01",
    "date:inception_upper":"1995-12-31",
    "iso:country":"GB",
    "wof:name":"SN1 1BF",
    "wof:placetype":"postalcode"
},
  "geometry": {"coordinates":[-1.783724,51.562564],"type":"Point"}
}