{
  "type": "Feature",
  "properties": {
    "iso:country": "GB",
    "wof:name": "B67 7LG",
    "wof:placetype": "postalcode"
  },
  "geometry": {"coordinates":[-1.985286,52.495271],"type":"Point"}
}
