{
  "type": "Feature",
  "properties": {
    "iso:country":"GB",
    "wof:name":"B67 7LG",
    "wof:placetype":"postalcode"
},
  "geometry": {"coordinates":[-1.9852860079696,52.49527124664694],"type":"Point"}
}