{
  "type": "Feature",
  "properties": {
    "iso:country":"GB",
    "wof:name":"DY4 9JW",
    "wof:placetype":"postalcode"
},
  "geometry": {"coordinates":[-2.06418766036886,52.54380003047884],"type":"Point"}
}