{
  "type": "Feature",
  "properties": {
    "iso:country": "GB",
    "wof:name": "YO22 4NZ",
    "wof:placetype": "postalcode"
  },
  "geometry": {"coordinates":[-0.619308,54.473149],"type":"Point"}
}
