{
  "type": "Feature",
  "properties": {
    "iso:country":"GB",
    "wof:name":"YO22 4NZ",
    "wof:placetype":"postalcode"
},
  "geometry": {"coordinates":[-0.61930845231633,54.47314865735221],"type":"Point"}
}