{
  "type": "Feature",
  "properties": {
    "date:inception_lower": "1980-01-01",
    "date:inception_upper": "1980-01-01",
    "iso:country": "GB",
    "wof:name": "BR6 8DD",
    "wof:placetype": "postalcode"
  },
  "geometry": {"coordinates":[0.081931,51.378018],"type":"Point"}
}
