{
  "type": "Feature",
  "properties": {
    "iso:country":"GB",
    "wof:name":"BR6 8DD",
    "wof:placetype":"postalcode"
},
  "geometry": {"coordinates":[0.08190500861989,51.37801760764457],"type":"Point"}
}