{
  "type": "Feature",
  "properties": {
    "iso:country":"GB",
    "wof:name":"DL3 6LQ",
    "wof:placetype":"postalcode"
},
  "geometry": {"coordinates":[-1.55873218711372,54.52837899516321],"type":"Point"}
}