{
  "type": "Feature",
  "properties": {
    "iso:country": "GB",
    "wof:name": "DN35 7HJ",
    "wof:placetype": "postalcode"
  },
  "geometry": {"coordinates":[-0.046109,53.564708],"type":"Point"}
}
