{
  "type": "Feature",
  "properties": {
    "iso:country":"GB",
    "wof:name":"DN35 7HJ",
    "wof:placetype":"postalcode"
},
  "geometry": {"coordinates":[-0.04610910209646,53.56470778809177],"type":"Point"}
}