{
  "type": "Feature",
  "properties": {
    "date:inception_lower": "2023-11-01",
    "date:inception_upper": "2023-11-01",
    "iso:country": "GB",
    "wof:name": "CV11 7AL",
    "wof:placetype": "postalcode"
  },
  "geometry": {"coordinates":[-1.435288,52.536466],"type":"Point"}
}
