{
  "type": "Feature",
  "properties": {
    "date:inception_lower": "2007-01-01",
    "date:inception_upper": "2007-01-01",
    "iso:country": "GB",
    "wof:name": "CA11 7EJ",
    "wof:placetype": "postalcode"
  },
  "geometry": {"coordinates":[-2.751201,54.663191],"type":"Point"}
}
