{
  "type": "Feature",
  "properties": {
    "iso:country": "GB",
    "wof:name": "CA11 7EJ",
    "wof:placetype": "postalcode"
  },
  "geometry": {"coordinates":[-2.751201,54.663191],"type":"Point"}
}
