{
  "type": "Feature",
  "properties": {
    "iso:country": "GB",
    "wof:name": "IP12 1JB",
    "wof:placetype": "postalcode"
  },
  "geometry": {"coordinates":[1.31398,52.102127],"type":"Point"}
}
