{
  "type": "Feature",
  "properties": {
    "date:inception_lower": "1980-01-01",
    "date:inception_upper": "1980-01-01",
    "iso:country": "GB",
    "wof:name": "IP12 1JB",
    "wof:placetype": "postalcode"
  },
  "geometry": {"coordinates":[1.31401,52.102143],"type":"Point"}
}
