{
  "type": "Feature",
  "properties": {
    "iso:country":"GB",
    "wof:name":"IP12 1JB",
    "wof:placetype":"postalcode"
},
  "geometry": {"coordinates":[1.31397970592461,52.10212722281602],"type":"Point"}
}