{
  "type": "Feature",
  "properties": {
    "iso:country":"GB",
    "wof:name":"IG1 1TW",
    "wof:placetype":"postalcode"
},
  "geometry": {"coordinates":[0.08602619693676,51.56134428219855],"type":"Point"}
}