{
  "type": "Feature",
  "properties": {
    "iso:country": "GB",
    "wof:name": "NG16 4HR",
    "wof:placetype": "postalcode"
  },
  "geometry": {"coordinates":[-1.33962,53.027797],"type":"Point"}
}
