{
  "type": "Feature",
  "properties": {
    "date:inception_lower": "2019-06-01",
    "date:inception_upper": "2019-06-01",
    "iso:country": "GB",
    "wof:name": "NG16 4HR",
    "wof:placetype": "postalcode"
  },
  "geometry": {"coordinates":[-1.33962,53.027797],"type":"Point"}
}
