{
  "type": "Feature",
  "properties": {
    "iso:country": "GB",
    "wof:name": "B5 7FJ",
    "wof:placetype": "postalcode"
  },
  "geometry": {"coordinates":[-1.895955,52.46721],"type":"Point"}
}
