{
  "type": "Feature",
  "properties": {
    "iso:country":"GB",
    "wof:name":"TS14 8HY",
    "wof:placetype":"postalcode"
},
  "geometry": {"coordinates":[-1.07194018566655,54.53364114484425],"type":"Point"}
}