{
  "type": "Feature",
  "properties": {
    "date:inception_lower": "1980-01-01",
    "date:inception_upper": "1980-01-01",
    "iso:country": "GB",
    "wof:name": "KT10 8EP",
    "wof:placetype": "postalcode"
  },
  "geometry": {"coordinates":[-0.354649,51.386203],"type":"Point"}
}
