{
  "type": "Feature",
  "properties": {
    "iso:country": "GB",
    "wof:name": "KT10 8EP",
    "wof:placetype": "postalcode"
  },
  "geometry": {"coordinates":[-0.354649,51.386203],"type":"Point"}
}
