{
  "type": "Feature",
  "properties": {
    "iso:country":"GB",
    "wof:name":"KT10 8EP",
    "wof:placetype":"postalcode"
},
  "geometry": {"coordinates":[-0.35464901256494,51.38620254754958],"type":"Point"}
}