{
  "type": "Feature",
  "properties": {
    "iso:country":"GB",
    "wof:name":"CV7 7LT",
    "wof:placetype":"postalcode"
},
  "geometry": {"coordinates":[-1.63982036621017,52.4401103898669],"type":"Point"}
}