{
  "type": "Feature",
  "properties": {
    "iso:country":"GB",
    "wof:name":"TF9 3EZ",
    "wof:placetype":"postalcode"
},
  "geometry": {"coordinates":[-2.50522576140132,52.90237953879262],"type":"Point"}
}