{
  "type": "Feature",
  "properties": {
    "iso:country": "GB",
    "wof:name": "TF9 3EZ",
    "wof:placetype": "postalcode"
  },
  "geometry": {"coordinates":[-2.505226,52.90238],"type":"Point"}
}
