{
  "type": "Feature",
  "properties": {
    "iso:country": "GB",
    "wof:name": "NR32 4RH",
    "wof:placetype": "postalcode"
  },
  "geometry": {"coordinates":[1.721329,52.491074],"type":"Point"}
}
