{
  "type": "Feature",
  "properties": {
    "iso:country":"GB",
    "wof:name":"NR32 4RH",
    "wof:placetype":"postalcode"
},
  "geometry": {"coordinates":[1.72132871852932,52.49107428568558],"type":"Point"}
}