{
  "type": "Feature",
  "properties": {
    "iso:country": "GB",
    "wof:name": "KY16 0LF",
    "wof:placetype": "postalcode"
  },
  "geometry": {"coordinates":[-2.880726,56.38134],"type":"Point"}
}
