{
  "type": "Feature",
  "properties": {
    "iso:country":"GB",
    "wof:name":"KY16 0LF",
    "wof:placetype":"postalcode"
},
  "geometry": {"coordinates":[-2.88072579916217,56.38133956907731],"type":"Point"}
}