{
  "type": "Feature",
  "properties": {
    "iso:country":"GB",
    "wof:name":"CR8 3YH",
    "wof:placetype":"postalcode"
},
  "geometry": {"coordinates":[-0.1186946826506,51.33914474149963],"type":"Point"}
}