{
  "type": "Feature",
  "properties": {
    "iso:country":"GB",
    "wof:name":"MK40 2PD",
    "wof:placetype":"postalcode"
},
  "geometry": {"coordinates":[-0.45801536551167,52.14482683341552],"type":"Point"}
}