{
  "type": "Feature",
  "properties": {
    "iso:country": "GB",
    "wof:name": "CA13 9YN",
    "wof:placetype": "postalcode"
  },
  "geometry": {"coordinates":[-3.249873,54.661803],"type":"Point"}
}
