{
  "type": "Feature",
  "properties": {
    "iso:country":"GB",
    "wof:name":"CA13 9YN",
    "wof:placetype":"postalcode"
},
  "geometry": {"coordinates":[-3.24987323923877,54.66180315524885],"type":"Point"}
}