{
  "type": "Feature",
  "properties": {
    "iso:country":"GB",
    "wof:name":"BN12 5JJ",
    "wof:placetype":"postalcode"
},
  "geometry": {"coordinates":[-0.45281483471168,50.81087821535726],"type":"Point"}
}