{
  "type": "Feature",
  "properties": {
    "iso:country":"GB",
    "wof:name":"TR2 5JT",
    "wof:placetype":"postalcode"
},
  "geometry": {"coordinates":[-4.91943586744634,50.24129131871484],"type":"Point"}
}