{
  "type": "Feature",
  "properties": {
    "iso:country": "GB",
    "wof:name": "IP12 1AE",
    "wof:placetype": "postalcode"
  },
  "geometry": {"coordinates":[1.324365,52.096249],"type":"Point"}
}
