{
  "type": "Feature",
  "properties": {
    "iso:country":"GB",
    "wof:name":"IP12 1AE",
    "wof:placetype":"postalcode"
},
  "geometry": {"coordinates":[1.32436481158718,52.09624913661776],"type":"Point"}
}