{
  "type": "Feature",
  "properties": {
    "iso:country":"GB",
    "wof:name":"CF24 3EQ",
    "wof:placetype":"postalcode"
},
  "geometry": {"coordinates":[-3.16218309444267,51.48856750908801],"type":"Point"}
}