{
  "type": "Feature",
  "properties": {
    "date:inception_lower": "2013-12-01",
    "date:inception_upper": "2013-12-01",
    "iso:country": "GB",
    "wof:name": "CF24 3EQ",
    "wof:placetype": "postalcode"
  },
  "geometry": {"coordinates":[-3.162183,51.488568],"type":"Point"}
}
