{
  "type": "Feature",
  "properties": {
    "iso:country":"GB",
    "wof:name":"G61 3PD",
    "wof:placetype":"postalcode"
},
  "geometry": {"coordinates":[-4.32737588043368,55.92668862599776],"type":"Point"}
}