{
  "type": "Feature",
  "properties": {
    "iso:country":"GB",
    "wof:name":"HA0 2FW",
    "wof:placetype":"postalcode"
},
  "geometry": {"coordinates":[-0.31735171752226,51.55417202162411],"type":"Point"}
}