{
  "type": "Feature",
  "properties": {
    "iso:country":"GB",
    "wof:name":"SP7 0LA",
    "wof:placetype":"postalcode"
},
  "geometry": {"coordinates":[-2.23091786064928,50.96400104463534],"type":"Point"}
}