{
  "type": "Feature",
  "properties": {
    "iso:country":"GB",
    "wof:name":"SG3 6FD",
    "wof:placetype":"postalcode"
},
  "geometry": {"coordinates":[-0.18343671652887,51.852145807966],"type":"Point"}
}