{
  "type": "Feature",
  "properties": {
    "date:inception_lower": "2009-07-01",
    "date:inception_upper": "2009-07-01",
    "iso:country": "GB",
    "wof:name": "SG3 6FD",
    "wof:placetype": "postalcode"
  },
  "geometry": {"coordinates":[-0.183437,51.852146],"type":"Point"}
}
