{
  "type": "Feature",
  "properties": {
    "iso:country":"GB",
    "wof:name":"BH15 3NP",
    "wof:placetype":"postalcode"
},
  "geometry": {"coordinates":[-1.95892145425497,50.73924914249545],"type":"Point"}
}