{
  "type": "Feature",
  "properties": {
    "date:inception_lower":"2002-12-01",
    "date:inception_upper":"2002-12-31",
    "iso:country":"GB",
    "wof:name":"PR1 1TW",
    "wof:placetype":"postalcode"
},
  "geometry": {"coordinates":[-2.69676,53.764645],"type":"Point"}
}