{
  "type": "Feature",
  "properties": {
    "date:inception_lower": "2021-02-01",
    "date:inception_upper": "2021-02-01",
    "iso:country": "GB",
    "wof:name": "PE8 6FF",
    "wof:placetype": "postalcode"
  },
  "geometry": {"coordinates":[-0.43563,52.6046],"type":"Point"}
}
