{
  "type": "Feature",
  "properties": {
    "iso:country": "GB",
    "wof:name": "NE23 6UD",
    "wof:placetype": "postalcode"
  },
  "geometry": {"coordinates":[-1.594444,55.081516],"type":"Point"}
}
