{
  "type": "Feature",
  "properties": {
    "iso:country":"GB",
    "wof:name":"EH42 1GF",
    "wof:placetype":"postalcode"
},
  "geometry": {"coordinates":[-2.51273567665911,55.9921491332658],"type":"Point"}
}