{
  "type": "Feature",
  "properties": {
    "date:inception_lower": "2008-05-01",
    "date:inception_upper": "2008-05-01",
    "iso:country": "GB",
    "wof:name": "PE19 9DP",
    "wof:placetype": "postalcode"
  },
  "geometry": {"coordinates":[-0.262344,52.233225],"type":"Point"}
}
