{
  "type": "Feature",
  "properties": {
    "iso:country": "GB",
    "wof:name": "NN5 5RA",
    "wof:placetype": "postalcode"
  },
  "geometry": {"coordinates":[-0.914084,52.231849],"type":"Point"}
}
