{
  "type": "Feature",
  "properties": {
    "iso:country":"GB",
    "wof:name":"NN5 5RA",
    "wof:placetype":"postalcode"
},
  "geometry": {"coordinates":[-0.91408382810776,52.23184925167154],"type":"Point"}
}