{
  "type": "Feature",
  "properties": {
    "date:inception_lower": "1998-12-01",
    "date:inception_upper": "1998-12-01",
    "iso:country": "GB",
    "wof:name": "NN5 5RA",
    "wof:placetype": "postalcode"
  },
  "geometry": {"coordinates":[-0.914084,52.231849],"type":"Point"}
}
