{
  "type": "Feature",
  "properties": {
    "date:inception_lower": "1980-01-01",
    "date:inception_upper": "1980-01-01",
    "iso:country": "GB",
    "wof:name": "SP6 3QB",
    "wof:placetype": "postalcode"
  },
  "geometry": {"coordinates":[-1.820404,50.971783],"type":"Point"}
}
