{
  "type": "Feature",
  "properties": {
    "iso:country": "GB",
    "wof:name": "SP6 3QB",
    "wof:placetype": "postalcode"
  },
  "geometry": {"coordinates":[-1.820404,50.971783],"type":"Point"}
}
