{
  "type": "Feature",
  "properties": {
    "date:inception_lower": "1980-01-01",
    "date:inception_upper": "1980-01-01",
    "iso:country": "GB",
    "wof:name": "LS25 5HP",
    "wof:placetype": "postalcode"
  },
  "geometry": {"coordinates":[-1.227463,53.753524],"type":"Point"}
}
