{
  "type": "Feature",
  "properties": {
    "iso:country": "GB",
    "wof:name": "LS25 5HP",
    "wof:placetype": "postalcode"
  },
  "geometry": {"coordinates":[-1.227459,53.753506],"type":"Point"}
}
