{
  "type": "Feature",
  "properties": {
    "date:inception_lower":"1981-06-01",
    "date:inception_upper":"1981-06-30",
    "iso:country":"GB",
    "wof:name":"SG18 0LF",
    "wof:placetype":"postalcode"
},
  "geometry": {"coordinates":[-0.264507,52.087137],"type":"Point"}
}