{
  "type": "Feature",
  "properties": {
    "iso:country": "GB",
    "wof:name": "SG18 0LF",
    "wof:placetype": "postalcode"
  },
  "geometry": {"coordinates":[-0.264507,52.087137],"type":"Point"}
}
