{
  "type": "Feature",
  "properties": {
    "date:inception_lower": "1980-01-01",
    "date:inception_upper": "1980-01-01",
    "iso:country": "GB",
    "wof:name": "NG24 1PY",
    "wof:placetype": "postalcode"
  },
  "geometry": {"coordinates":[-0.806122,53.075913],"type":"Point"}
}
