{
  "type": "Feature",
  "properties": {
    "date:inception_lower": "2004-05-01",
    "date:inception_upper": "2004-05-01",
    "iso:country": "GB",
    "wof:name": "LA13 0AZ",
    "wof:placetype": "postalcode"
  },
  "geometry": {"coordinates":[-3.195336,54.116306],"type":"Point"}
}
