{
  "type": "Feature",
  "properties": {
    "iso:country":"GB",
    "wof:name":"LA13 0AZ",
    "wof:placetype":"postalcode"
},
  "geometry": {"coordinates":[-3.1953358717815,54.11630629519906],"type":"Point"}
}