{
  "type": "Feature",
  "properties": {
    "iso:country": "GB",
    "wof:name": "B91 3LU",
    "wof:placetype": "postalcode"
  },
  "geometry": {"coordinates":[-1.784561,52.40683],"type":"Point"}
}
