{
  "type": "Feature",
  "properties": {
    "date:inception_lower": "1991-09-01",
    "date:inception_upper": "1991-09-01",
    "iso:country": "GB",
    "wof:name": "B91 3LU",
    "wof:placetype": "postalcode"
  },
  "geometry": {"coordinates":[-1.784561,52.40683],"type":"Point"}
}
