{
  "type": "Feature",
  "properties": {
    "date:inception_lower": "1980-01-01",
    "date:inception_upper": "1980-01-01",
    "iso:country": "GB",
    "wof:name": "DH1 4BD",
    "wof:placetype": "postalcode"
  },
  "geometry": {"coordinates":[-1.587557,54.777261],"type":"Point"}
}
