{
  "type": "Feature",
  "properties": {
    "iso:country":"GB",
    "wof:name":"DH1 4BD",
    "wof:placetype":"postalcode"
},
  "geometry": {"coordinates":[-1.58755713857044,54.77726080617575],"type":"Point"}
}