{
  "type": "Feature",
  "properties": {
    "iso:country":"GB",
    "wof:name":"WN2 4BQ",
    "wof:placetype":"postalcode"
},
  "geometry": {"coordinates":[-2.57002838117248,53.53808171467223],"type":"Point"}
}