{
  "type": "Feature",
  "properties": {
    "iso:country":"GB",
    "wof:name":"M20 3FQ",
    "wof:placetype":"postalcode"
},
  "geometry": {"coordinates":[-2.2306971513807,53.43817038189183],"type":"Point"}
}