{
  "type": "Feature",
  "properties": {
    "iso:country":"GB",
    "wof:name":"NG22 9RW",
    "wof:placetype":"postalcode"
},
  "geometry": {"coordinates":[-1.01931589606095,53.2025604964218],"type":"Point"}
}