{
  "type": "Feature",
  "properties": {
    "iso:country":"GB",
    "wof:name":"HA1 2QY",
    "wof:placetype":"postalcode"
},
  "geometry": {"coordinates":[-0.32191043685364,51.58511662187274],"type":"Point"}
}