{
  "type": "Feature",
  "properties": {
    "date:inception_lower":"1985-10-01",
    "date:inception_upper":"1985-10-31",
    "iso:country":"GB",
    "wof:name":"PO19 1EX",
    "wof:placetype":"postalcode"
},
  "geometry": {"coordinates":[-0.774011,50.836341],"type":"Point"}
}