{
  "type": "Feature",
  "properties": {
    "iso:country": "GB",
    "wof:name": "PO14 2AF",
    "wof:placetype": "postalcode"
  },
  "geometry": {"coordinates":[-1.206868,50.821219],"type":"Point"}
}
