{
  "type": "Feature",
  "properties": {
    "date:inception_lower": "1980-01-01",
    "date:inception_upper": "1980-01-01",
    "iso:country": "GB",
    "wof:name": "PO14 2AF",
    "wof:placetype": "postalcode"
  },
  "geometry": {"coordinates":[-1.206868,50.821219],"type":"Point"}
}
