{
  "type": "Feature",
  "properties": {
    "iso:country": "GB",
    "wof:name": "G2 1AR",
    "wof:placetype": "postalcode"
  },
  "geometry": {"coordinates":[-4.249866,55.860391],"type":"Point"}
}
