{
  "type": "Feature",
  "properties": {
    "date:inception_lower": "2011-08-01",
    "date:inception_upper": "2011-08-01",
    "iso:country": "GB",
    "wof:name": "G2 1AR",
    "wof:placetype": "postalcode"
  },
  "geometry": {"coordinates":[-4.249812,55.860531],"type":"Point"}
}
