{
  "type": "Feature",
  "properties": {
    "iso:country": "GB",
    "wof:name": "B76 1DQ",
    "wof:placetype": "postalcode"
  },
  "geometry": {"coordinates":[-1.808425,52.557948],"type":"Point"}
}
