{
  "type": "Feature",
  "properties": {
    "iso:country":"GB",
    "wof:name":"B76 1DQ",
    "wof:placetype":"postalcode"
},
  "geometry": {"coordinates":[-1.80842542705116,52.55794789077257],"type":"Point"}
}