{
  "type": "Feature",
  "properties": {
    "iso:country":"GB",
    "wof:name":"NN17 1AS",
    "wof:placetype":"postalcode"
},
  "geometry": {"coordinates":[-0.68217482820678,52.49244044711984],"type":"Point"}
}