{
  "type": "Feature",
  "properties": {
    "iso:country": "GB",
    "wof:name": "NN17 1AS",
    "wof:placetype": "postalcode"
  },
  "geometry": {"coordinates":[-0.682175,52.49244],"type":"Point"}
}
