{
  "type": "Feature",
  "properties": {
    "iso:country":"GB",
    "wof:name":"BB2 7QX",
    "wof:placetype":"postalcode"
},
  "geometry": {"coordinates":[-2.51274641059545,53.76079225219535],"type":"Point"}
}