{
  "type": "Feature",
  "properties": {
    "iso:country": "GB",
    "wof:name": "WF11 9HX",
    "wof:placetype": "postalcode"
  },
  "geometry": {"coordinates":[-1.259358,53.724774],"type":"Point"}
}
