{
  "type": "Feature",
  "properties": {
    "iso:country":"GB",
    "wof:name":"TS7 0JB",
    "wof:placetype":"postalcode"
},
  "geometry": {"coordinates":[-1.16910497356099,54.52502771117418],"type":"Point"}
}