{
  "type": "Feature",
  "properties": {
    "iso:country":"GB",
    "wof:name":"LA6 1HW",
    "wof:placetype":"postalcode"
},
  "geometry": {"coordinates":[-2.77002690851475,54.12986386726156],"type":"Point"}
}