{
  "type": "Feature",
  "properties": {
    "date:inception_lower": "1990-02-01",
    "date:inception_upper": "1990-02-01",
    "iso:country": "GB",
    "wof:name": "LA6 1HW",
    "wof:placetype": "postalcode"
  },
  "geometry": {"coordinates":[-2.770027,54.129864],"type":"Point"}
}
