{
  "type": "Feature",
  "properties": {
    "iso:country": "GB",
    "wof:name": "PE21 8PT",
    "wof:placetype": "postalcode"
  },
  "geometry": {"coordinates":[-0.034803,52.984292],"type":"Point"}
}
