{
  "type": "Feature",
  "properties": {
    "iso:country":"GB",
    "wof:name":"PE21 8PT",
    "wof:placetype":"postalcode"
},
  "geometry": {"coordinates":[-0.03480300362465,52.98429180580664],"type":"Point"}
}