{
  "type": "Feature",
  "properties": {
    "iso:country": "GB",
    "wof:name": "CB2 9DJ",
    "wof:placetype": "postalcode"
  },
  "geometry": {"coordinates":[0.123467,52.179027],"type":"Point"}
}
