{
  "type": "Feature",
  "properties": {
    "date:inception_lower": "2015-01-01",
    "date:inception_upper": "2015-01-01",
    "iso:country": "GB",
    "wof:name": "CB2 9DJ",
    "wof:placetype": "postalcode"
  },
  "geometry": {"coordinates":[0.123467,52.179027],"type":"Point"}
}
