{
  "type": "Feature",
  "properties": {
    "iso:country":"GB",
    "wof:name":"GU51 5SA",
    "wof:placetype":"postalcode"
},
  "geometry": {"coordinates":[-0.85272686701586,51.26729035622601],"type":"Point"}
}