{
  "type": "Feature",
  "properties": {
    "date:inception_lower":"1980-01-01",
    "date:inception_upper":"1980-01-31",
    "iso:country":"GB",
    "wof:name":"CO5 0ER",
    "wof:placetype":"postalcode"
},
  "geometry": {"coordinates":[0.750518,51.820995],"type":"Point"}
}