{
  "type": "Feature",
  "properties": {
    "iso:country":"GB",
    "wof:name":"GL5 3EW",
    "wof:placetype":"postalcode"
},
  "geometry": {"coordinates":[-2.2333858774829,51.74409854917947],"type":"Point"}
}