{
  "type": "Feature",
  "properties": {
    "iso:country":"GB",
    "wof:name":"UB5 4BE",
    "wof:placetype":"postalcode"
},
  "geometry": {"coordinates":[-0.37412540086045,51.55502637821019],"type":"Point"}
}