{
  "type": "Feature",
  "properties": {
    "iso:country": "GB",
    "wof:name": "UB5 4BE",
    "wof:placetype": "postalcode"
  },
  "geometry": {"coordinates":[-0.374125,51.555026],"type":"Point"}
}
