{
  "type": "Feature",
  "properties": {
    "iso:country":"GB",
    "wof:name":"PE30 3HL",
    "wof:placetype":"postalcode"
},
  "geometry": {"coordinates":[0.43644658427199,52.77801197547821],"type":"Point"}
}