{
  "type": "Feature",
  "properties": {
    "date:inception_lower": "2008-02-01",
    "date:inception_upper": "2008-02-01",
    "iso:country": "GB",
    "wof:name": "PE2 8GH",
    "wof:placetype": "postalcode"
  },
  "geometry": {"coordinates":[-0.230753,52.560008],"type":"Point"}
}
