{
  "type": "Feature",
  "properties": {
    "iso:country": "GB",
    "wof:name": "SS14 1TN",
    "wof:placetype": "postalcode"
  },
  "geometry": {"coordinates":[0.49418,51.566273],"type":"Point"}
}
