{
  "type": "Feature",
  "properties": {
    "date:inception_lower":"1980-01-01",
    "date:inception_upper":"1980-01-31",
    "iso:country":"GB",
    "wof:name":"PO21 5QS",
    "wof:placetype":"postalcode"
},
  "geometry": {"coordinates":[-0.704653,50.789557],"type":"Point"}
}