{
  "type": "Feature",
  "properties": {
    "iso:country": "GB",
    "wof:name": "PO21 5QS",
    "wof:placetype": "postalcode"
  },
  "geometry": {"coordinates":[-0.704653,50.789557],"type":"Point"}
}
