{
  "type": "Feature",
  "properties": {
    "iso:country":"GB",
    "wof:name":"PO21 5QS",
    "wof:placetype":"postalcode"
},
  "geometry": {"coordinates":[-0.70465284548207,50.78955690378206],"type":"Point"}
}