{
  "type": "Feature",
  "properties": {
    "iso:country": "GB",
    "wof:name": "DE7 4FY",
    "wof:placetype": "postalcode"
  },
  "geometry": {"coordinates":[-1.296702,52.954925],"type":"Point"}
}
