{
  "type": "Feature",
  "properties": {
    "iso:country":"GB",
    "wof:name":"DE7 4FY",
    "wof:placetype":"postalcode"
},
  "geometry": {"coordinates":[-1.2967023451103,52.95492493688162],"type":"Point"}
}