{
  "type": "Feature",
  "properties": {
    "iso:country":"GB",
    "wof:name":"HA7 3QA",
    "wof:placetype":"postalcode"
},
  "geometry": {"coordinates":[-0.31430847791701,51.61149869687254],"type":"Point"}
}