{
  "type": "Feature",
  "properties": {
    "iso:country": "GB",
    "wof:name": "CM3 5XX",
    "wof:placetype": "postalcode"
  },
  "geometry": {"coordinates":[0.618922,51.641914],"type":"Point"}
}
