{
  "type": "Feature",
  "properties": {
    "iso:country":"GB",
    "wof:name":"BS21 6RL",
    "wof:placetype":"postalcode"
},
  "geometry": {"coordinates":[-2.80032468327776,51.44598100520896],"type":"Point"}
}