{
  "type": "Feature",
  "properties": {
    "date:inception_lower":"1980-01-01",
    "date:inception_upper":"1980-01-31",
    "iso:country":"GB",
    "wof:name":"SE12 9RT",
    "wof:placetype":"postalcode"
},
  "geometry": {"coordinates":[0.031375,51.429544],"type":"Point"}
}