{
  "type": "Feature",
  "properties": {
    "iso:country":"GB",
    "wof:name":"SE12 9RT",
    "wof:placetype":"postalcode"
},
  "geometry": {"coordinates":[0.03145130566639,51.4295781385381],"type":"Point"}
}