{
  "type": "Feature",
  "properties": {
    "iso:country": "GB",
    "wof:name": "DE12 6LB",
    "wof:placetype": "postalcode"
  },
  "geometry": {"coordinates":[-1.563384,52.737184],"type":"Point"}
}
