{
  "type": "Feature",
  "properties": {
    "date:inception_lower":"2002-11-01",
    "date:inception_upper":"2002-11-30",
    "iso:country":"GB",
    "wof:name":"DE12 6LB",
    "wof:placetype":"postalcode"
},
  "geometry": {"coordinates":[-1.563384,52.737184],"type":"Point"}
}