{
  "type": "Feature",
  "properties": {
    "date:inception_lower":"1999-06-01",
    "date:inception_upper":"1999-06-30",
    "iso:country":"GB",
    "wof:name":"CF24 0EZ",
    "wof:placetype":"postalcode"
},
  "geometry": {"coordinates":[-3.162141,51.480664],"type":"Point"}
}