{
  "type": "Feature",
  "properties": {
    "iso:country":"GB",
    "wof:name":"CF24 0EZ",
    "wof:placetype":"postalcode"
},
  "geometry": {"coordinates":[-3.16214054267088,51.48066404976885],"type":"Point"}
}