{
  "type": "Feature",
  "properties": {
    "iso:country":"GB",
    "wof:name":"DY8 4EH",
    "wof:placetype":"postalcode"
},
  "geometry": {"coordinates":[-2.14565132935392,52.4711340214463],"type":"Point"}
}