{
  "type": "Feature",
  "properties": {
    "iso:country":"GB",
    "wof:name":"RG2 9FH",
    "wof:placetype":"postalcode"
},
  "geometry": {"coordinates":[-0.90506623518041,51.38637014414493],"type":"Point"}
}