{
  "type": "Feature",
  "properties": {
    "iso:country": "GB",
    "wof:name": "RG2 9FH",
    "wof:placetype": "postalcode"
  },
  "geometry": {"coordinates":[-0.905066,51.38637],"type":"Point"}
}
