{
  "type": "Feature",
  "properties": {
    "iso:country":"GB",
    "wof:name":"CB1 2AP",
    "wof:placetype":"postalcode"
},
  "geometry": {"coordinates":[0.13525503140496,52.20094833389709],"type":"Point"}
}