{
  "type": "Feature",
  "properties": {
    "iso:country":"GB",
    "wof:name":"BD23 3HN",
    "wof:placetype":"postalcode"
},
  "geometry": {"coordinates":[-2.04313896665577,53.94387747385524],"type":"Point"}
}