{
  "type": "Feature",
  "properties": {
    "iso:country":"GB",
    "wof:name":"BN11 2GA",
    "wof:placetype":"postalcode"
},
  "geometry": {"coordinates":[-0.35950844566826,50.81231047716825],"type":"Point"}
}