{
  "type": "Feature",
  "properties": {
    "date:inception_lower": "2005-12-01",
    "date:inception_upper": "2005-12-01",
    "iso:country": "GB",
    "wof:name": "BN11 2GA",
    "wof:placetype": "postalcode"
  },
  "geometry": {"coordinates":[-0.359508,50.81231],"type":"Point"}
}
