{
  "type": "Feature",
  "properties": {
    "iso:country": "GB",
    "wof:name": "TR20 9PG",
    "wof:placetype": "postalcode"
  },
  "geometry": {"coordinates":[-5.424153,50.117628],"type":"Point"}
}
