{
  "type": "Feature",
  "properties": {
    "date:inception_lower": "1980-01-01",
    "date:inception_upper": "1980-01-01",
    "iso:country": "GB",
    "wof:name": "TR20 9PG",
    "wof:placetype": "postalcode"
  },
  "geometry": {"coordinates":[-5.424333,50.117641],"type":"Point"}
}
