{
  "type": "Feature",
  "properties": {
    "iso:country":"GB",
    "wof:name":"SY14 8HD",
    "wof:placetype":"postalcode"
},
  "geometry": {"coordinates":[-2.66182770742624,53.06260934715057],"type":"Point"}
}