{
  "type": "Feature",
  "properties": {
    "date:inception_lower": "1980-01-01",
    "date:inception_upper": "1980-01-01",
    "iso:country": "GB",
    "wof:name": "SY14 8HD",
    "wof:placetype": "postalcode"
  },
  "geometry": {"coordinates":[-2.661828,53.062609],"type":"Point"}
}
