{
  "type": "Feature",
  "properties": {
    "iso:country": "GB",
    "wof:name": "EX14 3LE",
    "wof:placetype": "postalcode"
  },
  "geometry": {"coordinates":[-3.270496,50.824942],"type":"Point"}
}
