{
  "type": "Feature",
  "properties": {
    "date:inception_lower": "1999-12-01",
    "date:inception_upper": "1999-12-01",
    "iso:country": "GB",
    "wof:name": "EX14 3LE",
    "wof:placetype": "postalcode"
  },
  "geometry": {"coordinates":[-3.270496,50.824942],"type":"Point"}
}
