{
  "type": "Feature",
  "properties": {
    "iso:country":"GB",
    "wof:name":"NG2 2NR",
    "wof:placetype":"postalcode"
},
  "geometry": {"coordinates":[-1.15209877541946,52.93859160730413],"type":"Point"}
}