{
  "type": "Feature",
  "properties": {
    "iso:country":"GB",
    "wof:name":"HP15 6ED",
    "wof:placetype":"postalcode"
},
  "geometry": {"coordinates":[-0.73492217513553,51.67834181503905],"type":"Point"}
}