{
  "type": "Feature",
  "properties": {
    "date:inception_lower":"1997-12-01",
    "date:inception_upper":"1997-12-31",
    "iso:country":"GB",
    "wof:name":"SY10 8NT",
    "wof:placetype":"postalcode"
},
  "geometry": {"coordinates":[-3.081039,52.793173],"type":"Point"}
}