{
  "type": "Feature",
  "properties": {
    "iso:country":"GB",
    "wof:name":"SY10 8NT",
    "wof:placetype":"postalcode"
},
  "geometry": {"coordinates":[-3.08103927410901,52.79317294720105],"type":"Point"}
}