{
  "type": "Feature",
  "properties": {
    "iso:country":"GB",
    "wof:name":"BH21 2QT",
    "wof:placetype":"postalcode"
},
  "geometry": {"coordinates":[-1.97858985677303,50.80576356199487],"type":"Point"}
}