{
  "type": "Feature",
  "properties": {
    "iso:country":"GB",
    "wof:name":"RM13 7BB",
    "wof:placetype":"postalcode"
},
  "geometry": {"coordinates":[0.18851207230689,51.53650943525368],"type":"Point"}
}