{
  "type": "Feature",
  "properties": {
    "date:inception_lower": "1980-01-01",
    "date:inception_upper": "1980-01-01",
    "iso:country": "GB",
    "wof:name": "TN27 8EH",
    "wof:placetype": "postalcode"
  },
  "geometry": {"coordinates":[0.631946,51.115479],"type":"Point"}
}
