{
  "type": "Feature",
  "properties": {
    "iso:country":"GB",
    "wof:name":"BA12 9PD",
    "wof:placetype":"postalcode"
},
  "geometry": {"coordinates":[-2.18694488357116,51.19731745975857],"type":"Point"}
}