{
  "type": "Feature",
  "properties": {
    "date:inception_lower":"2017-10-01",
    "date:inception_upper":"2017-10-31",
    "iso:country":"GB",
    "wof:name":"SO31 7HN",
    "wof:placetype":"postalcode"
},
  "geometry": {"coordinates":[-1.274358,50.873572],"type":"Point"}
}