{
  "type": "Feature",
  "properties": {
    "iso:country":"GB",
    "wof:name":"WN4 9ED",
    "wof:placetype":"postalcode"
},
  "geometry": {"coordinates":[-2.6372494714823,53.48483564658542],"type":"Point"}
}