{
  "type": "Feature",
  "properties": {
    "iso:country":"GB",
    "wof:name":"TR20 8NP",
    "wof:placetype":"postalcode"
},
  "geometry": {"coordinates":[-5.62046801515955,50.14553762221698],"type":"Point"}
}