{
  "type": "Feature",
  "properties": {
    "date:inception_lower":"2015-07-01",
    "date:inception_upper":"2015-07-31",
    "iso:country":"GB",
    "wof:name":"CF5 3ET",
    "wof:placetype":"postalcode"
},
  "geometry": {"coordinates":[-3.248845,51.486885],"type":"Point"}
}