{
  "type": "Feature",
  "properties": {
    "iso:country":"GB",
    "wof:name":"CF5 3ET",
    "wof:placetype":"postalcode"
},
  "geometry": {"coordinates":[-3.24874496492312,51.48692219734551],"type":"Point"}
}