{
  "type": "Feature",
  "properties": {
    "iso:country": "GB",
    "wof:name": "CF5 3ET",
    "wof:placetype": "postalcode"
  },
  "geometry": {"coordinates":[-3.248845,51.486885],"type":"Point"}
}
