{
  "type": "Feature",
  "properties": {
    "iso:country":"GB",
    "wof:name":"S44 5EQ",
    "wof:placetype":"postalcode"
},
  "geometry": {"coordinates":[-1.33646255526886,53.24512641383618],"type":"Point"}
}