{
  "type": "Feature",
  "properties": {
    "iso:country":"GB",
    "wof:name":"CA7 3RQ",
    "wof:placetype":"postalcode"
},
  "geometry": {"coordinates":[-3.27776119531683,54.76141526541148],"type":"Point"}
}