{
  "type": "Feature",
  "properties": {
    "iso:country": "GB",
    "wof:name": "LE15 9RF",
    "wof:placetype": "postalcode"
  },
  "geometry": {"coordinates":[-0.725282,52.594442],"type":"Point"}
}
