{
  "type": "Feature",
  "properties": {
    "iso:country": "GB",
    "wof:name": "EX34 9LB",
    "wof:placetype": "postalcode"
  },
  "geometry": {"coordinates":[-4.118222,51.206398],"type":"Point"}
}
