{
  "type": "Feature",
  "properties": {
    "iso:country":"GB",
    "wof:name":"TQ2 5NY",
    "wof:placetype":"postalcode"
},
  "geometry": {"coordinates":[-3.53258580522026,50.46605817952604],"type":"Point"}
}