{
  "type": "Feature",
  "properties": {
    "iso:country": "GB",
    "wof:name": "TQ2 5NY",
    "wof:placetype": "postalcode"
  },
  "geometry": {"coordinates":[-3.53261,50.46635],"type":"Point"}
}
