{
  "type": "Feature",
  "properties": {
    "date:inception_lower": "1980-01-01",
    "date:inception_upper": "1980-01-01",
    "iso:country": "GB",
    "wof:name": "LE16 7AZ",
    "wof:placetype": "postalcode"
  },
  "geometry": {"coordinates":[-0.929862,52.484546],"type":"Point"}
}
