{
  "type": "Feature",
  "properties": {
    "iso:country":"GB",
    "wof:name":"LE16 7AZ",
    "wof:placetype":"postalcode"
},
  "geometry": {"coordinates":[-0.92987429254978,52.48452873918656],"type":"Point"}
}