{
  "type": "Feature",
  "properties": {
    "iso:country": "GB",
    "wof:name": "LE9 6PD",
    "wof:placetype": "postalcode"
  },
  "geometry": {"coordinates":[-1.207011,52.528703],"type":"Point"}
}
