{
  "type": "Feature",
  "properties": {
    "iso:country":"GB",
    "wof:name":"L22 0LP",
    "wof:placetype":"postalcode"
},
  "geometry": {"coordinates":[-3.02345005273937,53.47529305977742],"type":"Point"}
}