{
  "type": "Feature",
  "properties": {
    "iso:country": "GB",
    "wof:name": "PR4 6FR",
    "wof:placetype": "postalcode"
  },
  "geometry": {"coordinates":[-2.826607,53.662162],"type":"Point"}
}
