{
  "type": "Feature",
  "properties": {
    "iso:country":"GB",
    "wof:name":"PR4 6FR",
    "wof:placetype":"postalcode"
},
  "geometry": {"coordinates":[-2.82660671691599,53.66216162724675],"type":"Point"}
}