{
  "type": "Feature",
  "properties": {
    "iso:country": "GB",
    "wof:name": "EN5 3EL",
    "wof:placetype": "postalcode"
  },
  "geometry": {"coordinates":[-0.238863,51.643483],"type":"Point"}
}
