{
  "type": "Feature",
  "properties": {
    "iso:country":"GB",
    "wof:name":"BL4 9ED",
    "wof:placetype":"postalcode"
},
  "geometry": {"coordinates":[-2.40069823789667,53.54728134540196],"type":"Point"}
}