{
  "type": "Feature",
  "properties": {
    "date:inception_lower": "1993-08-01",
    "date:inception_upper": "1993-08-01",
    "iso:country": "GB",
    "wof:name": "SS99 1NN",
    "wof:placetype": "postalcode"
  },
  "geometry": {"coordinates":[0.729429,51.531166],"type":"Point"}
}
