{
  "type": "Feature",
  "properties": {
    "iso:country":"GB",
    "wof:name":"OL16 2ET",
    "wof:placetype":"postalcode"
},
  "geometry": {"coordinates":[-2.14634989437309,53.62049792554619],"type":"Point"}
}