{
  "type": "Feature",
  "properties": {
    "date:inception_lower": "1980-01-01",
    "date:inception_upper": "1980-01-01",
    "iso:country": "GB",
    "wof:name": "OL16 2ET",
    "wof:placetype": "postalcode"
  },
  "geometry": {"coordinates":[-2.14635,53.620498],"type":"Point"}
}
