{
  "type": "Feature",
  "properties": {
    "iso:country":"GB",
    "wof:name":"SN3 2EQ",
    "wof:placetype":"postalcode"
},
  "geometry": {"coordinates":[-1.753172928424,51.55354751614055],"type":"Point"}
}