{
  "type": "Feature",
  "properties": {
    "iso:country":"GB",
    "wof:name":"TF4 3HW",
    "wof:placetype":"postalcode"
},
  "geometry": {"coordinates":[-2.46647179436623,52.65056005781292],"type":"Point"}
}