{
  "type": "Feature",
  "properties": {
    "iso:country": "GB",
    "wof:name": "NP25 3DR",
    "wof:placetype": "postalcode"
  },
  "geometry": {"coordinates":[-2.710115,51.813044],"type":"Point"}
}
