{
  "type": "Feature",
  "properties": {
    "iso:country":"GB",
    "wof:name":"TN8 6NX",
    "wof:placetype":"postalcode"
},
  "geometry": {"coordinates":[0.11312307159715,51.23293061796721],"type":"Point"}
}