{
  "type": "Feature",
  "properties": {
    "iso:country": "GB",
    "wof:name": "TN8 6NX",
    "wof:placetype": "postalcode"
  },
  "geometry": {"coordinates":[0.113123,51.232931],"type":"Point"}
}
