{
  "type": "Feature",
  "properties": {
    "date:inception_lower":"1980-01-01",
    "date:inception_upper":"1980-01-31",
    "iso:country":"GB",
    "wof:name":"TN8 6NX",
    "wof:placetype":"postalcode"
},
  "geometry": {"coordinates":[0.113123,51.232931],"type":"Point"}
}