{
  "type": "Feature",
  "properties": {
    "iso:country":"GB",
    "wof:name":"DT5 1JZ",
    "wof:placetype":"postalcode"
},
  "geometry": {"coordinates":[-2.44300579204272,50.55732507770956],"type":"Point"}
}