{
  "type": "Feature",
  "properties": {
    "date:inception_lower": "1980-01-01",
    "date:inception_upper": "1980-01-01",
    "iso:country": "GB",
    "wof:name": "BS16 5JN",
    "wof:placetype": "postalcode"
  },
  "geometry": {"coordinates":[-2.50737,51.483418],"type":"Point"}
}
