{
  "type": "Feature",
  "properties": {
    "iso:country":"GB",
    "wof:name":"BS16 5JN",
    "wof:placetype":"postalcode"
},
  "geometry": {"coordinates":[-2.50729730518427,51.48339329109812],"type":"Point"}
}