{
  "type": "Feature",
  "properties": {
    "iso:country": "GB",
    "wof:name": "BS16 5JN",
    "wof:placetype": "postalcode"
  },
  "geometry": {"coordinates":[-2.50737,51.483418],"type":"Point"}
}
