{
  "type": "Feature",
  "properties": {
    "iso:country": "GB",
    "wof:name": "EN2 6JR",
    "wof:placetype": "postalcode"
  },
  "geometry": {"coordinates":[-0.086541,51.656827],"type":"Point"}
}
