{
  "type": "Feature",
  "properties": {
    "iso:country":"GB",
    "wof:name":"NW2 5BD",
    "wof:placetype":"postalcode"
},
  "geometry": {"coordinates":[-0.22880583434914,51.54877728446106],"type":"Point"}
}