{
  "type": "Feature",
  "properties": {
    "iso:country":"GB",
    "wof:name":"G51 4EG",
    "wof:placetype":"postalcode"
},
  "geometry": {"coordinates":[-4.33754442953503,55.85761494487341],"type":"Point"}
}