{
  "type": "Feature",
  "properties": {
    "date:inception_lower": "2001-12-01",
    "date:inception_upper": "2001-12-01",
    "iso:country": "GB",
    "wof:name": "G51 4EG",
    "wof:placetype": "postalcode"
  },
  "geometry": {"coordinates":[-4.337544,55.857615],"type":"Point"}
}
