{
  "type": "Feature",
  "properties": {
    "date:inception_lower": "2017-08-01",
    "date:inception_upper": "2017-08-01",
    "iso:country": "GB",
    "wof:name": "SO31 7PS",
    "wof:placetype": "postalcode"
  },
  "geometry": {"coordinates":[-1.298421,50.884006],"type":"Point"}
}
