{
  "type": "Feature",
  "properties": {
    "iso:country":"GB",
    "wof:name":"CR5 3DY",
    "wof:placetype":"postalcode"
},
  "geometry": {"coordinates":[-0.14552422629932,51.30829579149175],"type":"Point"}
}