{
  "type": "Feature",
  "properties": {
    "date:inception_lower": "2009-05-01",
    "date:inception_upper": "2009-05-01",
    "iso:country": "GB",
    "wof:name": "CR5 3DY",
    "wof:placetype": "postalcode"
  },
  "geometry": {"coordinates":[-0.145524,51.308296],"type":"Point"}
}
