{
  "type": "Feature",
  "properties": {
    "iso:country":"GB",
    "wof:name":"DG7 3TB",
    "wof:placetype":"postalcode"
},
  "geometry": {"coordinates":[-4.19098756736832,55.19153540791846],"type":"Point"}
}