{
  "type": "Feature",
  "properties": {
    "iso:country":"GB",
    "wof:name":"AL10 9PJ",
    "wof:placetype":"postalcode"
},
  "geometry": {"coordinates":[-0.24073394467449,51.75896953529496],"type":"Point"}
}