{
  "type": "Feature",
  "properties": {
    "date:inception_lower":"2013-03-01",
    "date:inception_upper":"2013-03-31",
    "iso:country":"GB",
    "wof:name":"NE30 1DP",
    "wof:placetype":"postalcode"
},
  "geometry": {"coordinates":[-1.439269,55.011303],"type":"Point"}
}