{
  "type": "Feature",
  "properties": {
    "iso:country":"GB",
    "wof:name":"NE30 1DP",
    "wof:placetype":"postalcode"
},
  "geometry": {"coordinates":[-1.43926888911472,55.01130282332822],"type":"Point"}
}