{
  "type": "Feature",
  "properties": {
    "date:inception_lower":"2014-06-01",
    "date:inception_upper":"2014-06-30",
    "iso:country":"GB",
    "wof:name":"PO12 2LW",
    "wof:placetype":"postalcode"
},
  "geometry": {"coordinates":[-1.152293,50.783758],"type":"Point"}
}