{
  "type": "Feature",
  "properties": {
    "iso:country":"GB",
    "wof:name":"PO12 2LW",
    "wof:placetype":"postalcode"
},
  "geometry": {"coordinates":[-1.15229271015644,50.7837579288442],"type":"Point"}
}