{
  "type": "Feature",
  "properties": {
    "iso:country":"GB",
    "wof:name":"BB8 7AW",
    "wof:placetype":"postalcode"
},
  "geometry": {"coordinates":[-2.1668972882857,53.86551218934308],"type":"Point"}
}