{
  "type": "Feature",
  "properties": {
    "iso:country":"GB",
    "wof:name":"B66 4JD",
    "wof:placetype":"postalcode"
},
  "geometry": {"coordinates":[-1.96941582882207,52.48378808657307],"type":"Point"}
}