{
  "type": "Feature",
  "properties": {
    "iso:country":"GB",
    "wof:name":"BN1 7GG",
    "wof:placetype":"postalcode"
},
  "geometry": {"coordinates":[-0.13010191404413,50.8457770852984],"type":"Point"}
}