{
  "type": "Feature",
  "properties": {
    "date:inception_lower": "1980-01-01",
    "date:inception_upper": "1980-01-01",
    "iso:country": "GB",
    "wof:name": "BN1 7GG",
    "wof:placetype": "postalcode"
  },
  "geometry": {"coordinates":[-0.130102,50.845777],"type":"Point"}
}
