{
  "type": "Feature",
  "properties": {
    "iso:country":"GB",
    "wof:name":"SS1 1BH",
    "wof:placetype":"postalcode"
},
  "geometry": {"coordinates":[0.71294367346411,51.53570367577201],"type":"Point"}
}