{
  "type": "Feature",
  "properties": {
    "iso:country":"GB",
    "wof:name":"TA6 4AW",
    "wof:placetype":"postalcode"
},
  "geometry": {"coordinates":[-2.98671721771304,51.15259666580345],"type":"Point"}
}