{
  "type": "Feature",
  "properties": {
    "iso:country": "GB",
    "wof:name": "TA6 4AW",
    "wof:placetype": "postalcode"
  },
  "geometry": {"coordinates":[-2.986495,51.152539],"type":"Point"}
}
