{
  "type": "Feature",
  "properties": {
    "date:inception_lower": "1985-04-01",
    "date:inception_upper": "1985-04-01",
    "iso:country": "GB",
    "wof:name": "M13 9LL",
    "wof:placetype": "postalcode"
  },
  "geometry": {"coordinates":[-2.224962,53.463852],"type":"Point"}
}
