{
  "type": "Feature",
  "properties": {
    "iso:country":"GB",
    "wof:name":"M13 9LL",
    "wof:placetype":"postalcode"
},
  "geometry": {"coordinates":[-2.22496220264657,53.46385248691974],"type":"Point"}
}