{
  "type": "Feature",
  "properties": {
    "iso:country": "GB",
    "wof:name": "GU31 4FX",
    "wof:placetype": "postalcode"
  },
  "geometry": {"coordinates":[-0.939032,50.997653],"type":"Point"}
}
