{
  "type": "Feature",
  "properties": {
    "iso:country":"GB",
    "wof:name":"ML6 9QT",
    "wof:placetype":"postalcode"
},
  "geometry": {"coordinates":[-3.96311268057371,55.85132683959647],"type":"Point"}
}