{
  "type": "Feature",
  "properties": {
    "iso:country":"GB",
    "wof:name":"CH64 3RD",
    "wof:placetype":"postalcode"
},
  "geometry": {"coordinates":[-3.06373051660572,53.29463931327565],"type":"Point"}
}