{
  "type": "Feature",
  "properties": {
    "iso:country":"GB",
    "wof:name":"YO15 2DP",
    "wof:placetype":"postalcode"
},
  "geometry": {"coordinates":[-0.19056001235435,54.08264091820058],"type":"Point"}
}