{
  "type": "Feature",
  "properties": {
    "iso:country": "GB",
    "wof:name": "YO15 2DP",
    "wof:placetype": "postalcode"
  },
  "geometry": {"coordinates":[-0.19056,54.082641],"type":"Point"}
}
