{
  "type": "Feature",
  "properties": {
    "iso:country":"GB",
    "wof:name":"NR30 5QT",
    "wof:placetype":"postalcode"
},
  "geometry": {"coordinates":[1.71926762566611,52.65594131470748],"type":"Point"}
}