{
  "type": "Feature",
  "properties": {
    "date:inception_lower":"1980-01-01",
    "date:inception_upper":"1980-01-31",
    "iso:country":"GB",
    "wof:name":"NR30 5QT",
    "wof:placetype":"postalcode"
},
  "geometry": {"coordinates":[1.719268,52.655941],"type":"Point"}
}