{
  "type": "Feature",
  "properties": {
    "iso:country":"GB",
    "wof:name":"LA2 0AT",
    "wof:placetype":"postalcode"
},
  "geometry": {"coordinates":[-2.82515093436105,53.99741315797652],"type":"Point"}
}