{
  "type": "Feature",
  "properties": {
    "iso:country":"GB",
    "wof:name":"BN14 9PT",
    "wof:placetype":"postalcode"
},
  "geometry": {"coordinates":[-0.38876748582602,50.83612759265345],"type":"Point"}
}