{
  "type": "Feature",
  "properties": {
    "iso:country":"GB",
    "wof:name":"CW8 1EH",
    "wof:placetype":"postalcode"
},
  "geometry": {"coordinates":[-2.5191915165131,53.25753436272988],"type":"Point"}
}