{
  "type": "Feature",
  "properties": {
    "date:inception_lower": "2021-11-01",
    "date:inception_upper": "2021-11-01",
    "iso:country": "GB",
    "wof:name": "LE9 9QS",
    "wof:placetype": "postalcode"
  },
  "geometry": {"coordinates":[-1.284626,52.627234],"type":"Point"}
}
