{
  "type": "Feature",
  "properties": {
    "iso:country": "GB",
    "wof:name": "OL10 3QN",
    "wof:placetype": "postalcode"
  },
  "geometry": {"coordinates":[-2.241274,53.58564],"type":"Point"}
}
