{
  "type": "Feature",
  "properties": {
    "date:inception_lower":"1980-01-01",
    "date:inception_upper":"1980-01-31",
    "iso:country":"GB",
    "wof:name":"WR14 3LU",
    "wof:placetype":"postalcode"
},
  "geometry": {"coordinates":[-2.311214,52.108667],"type":"Point"}
}