{
  "type": "Feature",
  "properties": {
    "iso:country":"GB",
    "wof:name":"TN23 4QU",
    "wof:placetype":"postalcode"
},
  "geometry": {"coordinates":[0.85635864013496,51.14244571266033],"type":"Point"}
}