{
  "type": "Feature",
  "properties": {
    "iso:country": "GB",
    "wof:name": "TN23 4QU",
    "wof:placetype": "postalcode"
  },
  "geometry": {"coordinates":[0.856359,51.142446],"type":"Point"}
}
