{
  "type": "Feature",
  "properties": {
    "iso:country":"GB",
    "wof:name":"ML4 2DF",
    "wof:placetype":"postalcode"
},
  "geometry": {"coordinates":[-4.01601431091535,55.80855591153798],"type":"Point"}
}