{
  "type": "Feature",
  "properties": {
    "iso:country":"GB",
    "wof:name":"LL40 1LT",
    "wof:placetype":"postalcode"
},
  "geometry": {"coordinates":[-3.88452110136136,52.74098014753765],"type":"Point"}
}