{
  "type": "Feature",
  "properties": {
    "iso:country":"GB",
    "wof:name":"N19 3XW",
    "wof:placetype":"postalcode"
},
  "geometry": {"coordinates":[-0.12317636576877,51.5721071528231],"type":"Point"}
}