{
  "type": "Feature",
  "properties": {
    "date:inception_lower": "1994-05-01",
    "date:inception_upper": "1994-05-01",
    "iso:country": "GB",
    "wof:name": "N19 3XW",
    "wof:placetype": "postalcode"
  },
  "geometry": {"coordinates":[-0.123176,51.572107],"type":"Point"}
}
