{
  "type": "Feature",
  "properties": {
    "iso:country":"GB",
    "wof:name":"WC2H 7HN",
    "wof:placetype":"postalcode"
},
  "geometry": {"coordinates":[-0.12980767530436,51.50966133196159],"type":"Point"}
}