{
  "type": "Feature",
  "properties": {
    "iso:country":"GB",
    "wof:name":"PL6 6SD",
    "wof:placetype":"postalcode"
},
  "geometry": {"coordinates":[-4.14628441736302,50.42414575488196],"type":"Point"}
}