{
  "type": "Feature",
  "properties": {
    "date:inception_lower":"2005-03-01",
    "date:inception_upper":"2005-03-31",
    "iso:country":"GB",
    "wof:name":"LU7 0TT",
    "wof:placetype":"postalcode"
},
  "geometry": {"coordinates":[-0.661245,51.846379],"type":"Point"}
}