{
  "type": "Feature",
  "properties": {
    "iso:country": "GB",
    "wof:name": "LU7 0TT",
    "wof:placetype": "postalcode"
  },
  "geometry": {"coordinates":[-0.661245,51.846379],"type":"Point"}
}
