{
  "type": "Feature",
  "properties": {
    "iso:country":"GB",
    "wof:name":"NE42 5PB",
    "wof:placetype":"postalcode"
},
  "geometry": {"coordinates":[-1.84132824132351,54.94982964348923],"type":"Point"}
}