{
  "type": "Feature",
  "properties": {
    "date:inception_lower": "1980-01-01",
    "date:inception_upper": "1980-01-01",
    "iso:country": "GB",
    "wof:name": "RH16 3PP",
    "wof:placetype": "postalcode"
  },
  "geometry": {"coordinates":[-0.09137,51.001743],"type":"Point"}
}
