{
  "type": "Feature",
  "properties": {
    "iso:country":"GB",
    "wof:name":"LU2 8EL",
    "wof:placetype":"postalcode"
},
  "geometry": {"coordinates":[-0.3858658509952,51.90709682496064],"type":"Point"}
}