{
  "type": "Feature",
  "properties": {
    "date:inception_lower": "1980-01-01",
    "date:inception_upper": "1980-01-01",
    "iso:country": "GB",
    "wof:name": "LU2 8EL",
    "wof:placetype": "postalcode"
  },
  "geometry": {"coordinates":[-0.385866,51.907097],"type":"Point"}
}
