{
  "type": "Feature",
  "properties": {
    "date:inception_lower": "2022-09-01",
    "date:inception_upper": "2022-09-01",
    "iso:country": "GB",
    "wof:name": "OX11 9GF",
    "wof:placetype": "postalcode"
  },
  "geometry": {"coordinates":[-1.224884,51.61581],"type":"Point"}
}
