{
  "type": "Feature",
  "properties": {
    "iso:country":"GB",
    "wof:name":"NG10 1QQ",
    "wof:placetype":"postalcode"
},
  "geometry": {"coordinates":[-1.27254999898838,52.89862238787994],"type":"Point"}
}