{
  "type": "Feature",
  "properties": {
    "date:inception_lower": "2008-01-01",
    "date:inception_upper": "2008-01-01",
    "iso:country": "GB",
    "wof:name": "NG10 1QQ",
    "wof:placetype": "postalcode"
  },
  "geometry": {"coordinates":[-1.27255,52.898622],"type":"Point"}
}
