{
  "type": "Feature",
  "properties": {
    "iso:country": "GB",
    "wof:name": "M26 2RS",
    "wof:placetype": "postalcode"
  },
  "geometry": {"coordinates":[-2.315634,53.566825],"type":"Point"}
}
