{
  "type": "Feature",
  "properties": {
    "iso:country":"GB",
    "wof:name":"M26 2RS",
    "wof:placetype":"postalcode"
},
  "geometry": {"coordinates":[-2.3156343507618,53.56682528614819],"type":"Point"}
}