{
  "type": "Feature",
  "properties": {
    "iso:country": "GB",
    "wof:name": "S66 8FP",
    "wof:placetype": "postalcode"
  },
  "geometry": {"coordinates":[-1.208127,53.428347],"type":"Point"}
}
