{
  "type": "Feature",
  "properties": {
    "iso:country":"GB",
    "wof:name":"LN6 7PL",
    "wof:placetype":"postalcode"
},
  "geometry": {"coordinates":[-0.56322395595406,53.20883891787612],"type":"Point"}
}