{
  "type": "Feature",
  "properties": {
    "iso:country":"GB",
    "wof:name":"TW11 0AQ",
    "wof:placetype":"postalcode"
},
  "geometry": {"coordinates":[-0.3353182018184,51.42305035027547],"type":"Point"}
}