{
  "type": "Feature",
  "properties": {
    "iso:country": "GB",
    "wof:name": "HR4 8PL",
    "wof:placetype": "postalcode"
  },
  "geometry": {"coordinates":[-2.803515,52.134885],"type":"Point"}
}
