{
  "type": "Feature",
  "properties": {
    "iso:country": "GB",
    "wof:name": "CM7 1UX",
    "wof:placetype": "postalcode"
  },
  "geometry": {"coordinates":[0.552445,51.879502],"type":"Point"}
}
