{
  "type": "Feature",
  "properties": {
    "iso:country":"GB",
    "wof:name":"CM7 1UX",
    "wof:placetype":"postalcode"
},
  "geometry": {"coordinates":[0.55244495517844,51.87950200897044],"type":"Point"}
}