{
  "type": "Feature",
  "properties": {
    "iso:country":"GB",
    "wof:name":"TS5 7EF",
    "wof:placetype":"postalcode"
},
  "geometry": {"coordinates":[-1.25455199879584,54.54514026353973],"type":"Point"}
}