{
  "type": "Feature",
  "properties": {
    "iso:country": "GB",
    "wof:name": "FY5 4BJ",
    "wof:placetype": "postalcode"
  },
  "geometry": {"coordinates":[-3.009828,53.87957],"type":"Point"}
}
