{
  "type": "Feature",
  "properties": {
    "date:inception_lower": "2017-02-01",
    "date:inception_upper": "2017-02-01",
    "iso:country": "GB",
    "wof:name": "BD23 2DD",
    "wof:placetype": "postalcode"
  },
  "geometry": {"coordinates":[-2.015202,53.942379],"type":"Point"}
}
