{
  "type": "Feature",
  "properties": {
    "iso:country":"GB",
    "wof:name":"RG14 7AS",
    "wof:placetype":"postalcode"
},
  "geometry": {"coordinates":[-1.32939109645759,51.38753356707531],"type":"Point"}
}