{
  "type": "Feature",
  "properties": {
    "iso:country":"GB",
    "wof:name":"TF4 3BZ",
    "wof:placetype":"postalcode"
},
  "geometry": {"coordinates":[-2.4784876434611,52.65719152716388],"type":"Point"}
}