{
  "type": "Feature",
  "properties": {
    "iso:country": "GB",
    "wof:name": "TF4 3BZ",
    "wof:placetype": "postalcode"
  },
  "geometry": {"coordinates":[-2.478486,52.657207],"type":"Point"}
}
