{
  "type": "Feature",
  "properties": {
    "iso:country": "GB",
    "wof:name": "S12 4QE",
    "wof:placetype": "postalcode"
  },
  "geometry": {"coordinates":[-1.390225,53.346746],"type":"Point"}
}
