{
  "type": "Feature",
  "properties": {
    "iso:country":"GB",
    "wof:name":"S12 4QE",
    "wof:placetype":"postalcode"
},
  "geometry": {"coordinates":[-1.39027010061049,53.34672707019794],"type":"Point"}
}