{
  "type": "Feature",
  "properties": {
    "date:inception_lower":"1980-01-01",
    "date:inception_upper":"1980-01-31",
    "iso:country":"GB",
    "wof:name":"TS10 5NW",
    "wof:placetype":"postalcode"
},
  "geometry": {"coordinates":[-1.084173,54.587774],"type":"Point"}
}