{
  "type": "Feature",
  "properties": {
    "iso:country": "GB",
    "wof:name": "TS10 5NW",
    "wof:placetype": "postalcode"
  },
  "geometry": {"coordinates":[-1.084173,54.587774],"type":"Point"}
}
