{
  "type": "Feature",
  "properties": {
    "iso:country":"GB",
    "wof:name":"SS14 3LR",
    "wof:placetype":"postalcode"
},
  "geometry": {"coordinates":[0.49110231184484,51.58283157190573],"type":"Point"}
}