{
  "type": "Feature",
  "properties": {
    "date:inception_lower": "1980-01-01",
    "date:inception_upper": "1980-01-01",
    "iso:country": "GB",
    "wof:name": "PE13 1RP",
    "wof:placetype": "postalcode"
  },
  "geometry": {"coordinates":[0.147969,52.670333],"type":"Point"}
}
