{
  "type": "Feature",
  "properties": {
    "iso:country":"GB",
    "wof:name":"DY5 1PX",
    "wof:placetype":"postalcode"
},
  "geometry": {"coordinates":[-2.12845414949725,52.49032957207064],"type":"Point"}
}