{
  "type": "Feature",
  "properties": {
    "iso:country":"GB",
    "wof:name":"GU15 2RA",
    "wof:placetype":"postalcode"
},
  "geometry": {"coordinates":[-0.75357045762659,51.3269294704893],"type":"Point"}
}