{
  "type": "Feature",
  "properties": {
    "iso:country": "GB",
    "wof:name": "GU15 2RA",
    "wof:placetype": "postalcode"
  },
  "geometry": {"coordinates":[-0.753523,51.326974],"type":"Point"}
}
