{
  "type": "Feature",
  "properties": {
    "iso:country":"GB",
    "wof:name":"B31 3AX",
    "wof:placetype":"postalcode"
},
  "geometry": {"coordinates":[-1.95032731963519,52.40884992016955],"type":"Point"}
}