{
  "type": "Feature",
  "properties": {
    "iso:country":"GB",
    "wof:name":"N15 3PY",
    "wof:placetype":"postalcode"
},
  "geometry": {"coordinates":[-0.09706757043579,51.58739649467921],"type":"Point"}
}