{
  "type": "Feature",
  "properties": {
    "iso:country": "GB",
    "wof:name": "KT24 5EG",
    "wof:placetype": "postalcode"
  },
  "geometry": {"coordinates":[-0.428396,51.284413],"type":"Point"}
}
