{
  "type": "Feature",
  "properties": {
    "iso:country":"GB",
    "wof:name":"KT24 5EG",
    "wof:placetype":"postalcode"
},
  "geometry": {"coordinates":[-0.4283964013597,51.28441307723369],"type":"Point"}
}