{
  "type": "Feature",
  "properties": {
    "iso:country":"GB",
    "wof:name":"PO40 9LN",
    "wof:placetype":"postalcode"
},
  "geometry": {"coordinates":[-1.52821888856839,50.68576742488901],"type":"Point"}
}