{
  "type": "Feature",
  "properties": {
    "iso:country":"GB",
    "wof:name":"G61 1JG",
    "wof:placetype":"postalcode"
},
  "geometry": {"coordinates":[-4.3295738110792,55.90329736996706],"type":"Point"}
}