{
  "type": "Feature",
  "properties": {
    "iso:country":"GB",
    "wof:name":"S36 7BX",
    "wof:placetype":"postalcode"
},
  "geometry": {"coordinates":[-1.63746181639535,53.53390421022645],"type":"Point"}
}