{
  "type": "Feature",
  "properties": {
    "iso:country":"GB",
    "wof:name":"NR9 4PX",
    "wof:placetype":"postalcode"
},
  "geometry": {"coordinates":[0.97433150390496,52.58446122082896],"type":"Point"}
}