{
  "type": "Feature",
  "properties": {
    "iso:country": "GB",
    "wof:name": "NR9 4PX",
    "wof:placetype": "postalcode"
  },
  "geometry": {"coordinates":[0.974332,52.584461],"type":"Point"}
}
