{
  "type": "Feature",
  "properties": {
    "iso:country":"GB",
    "wof:name":"SW1W 9AW",
    "wof:placetype":"postalcode"
},
  "geometry": {"coordinates":[-0.15465243055384,51.49502839040419],"type":"Point"}
}