{
  "type": "Feature",
  "properties": {
    "iso:country":"GB",
    "wof:name":"E14 9EG",
    "wof:placetype":"postalcode"
},
  "geometry": {"coordinates":[-0.02476507074798,51.50201309261208],"type":"Point"}
}