{
  "type": "Feature",
  "properties": {
    "iso:country": "GB",
    "wof:name": "SY25 6HU",
    "wof:placetype": "postalcode"
  },
  "geometry": {"coordinates":[-3.934822,52.22006],"type":"Point"}
}
