{
  "type": "Feature",
  "properties": {
    "iso:country":"GB",
    "wof:name":"BA3 4TS",
    "wof:placetype":"postalcode"
},
  "geometry": {"coordinates":[-2.54348081791282,51.24147851863513],"type":"Point"}
}