{
  "type": "Feature",
  "properties": {
    "iso:country":"GB",
    "wof:name":"TN7 4JT",
    "wof:placetype":"postalcode"
},
  "geometry": {"coordinates":[0.10592506363611,51.11220891195114],"type":"Point"}
}