{
  "type": "Feature",
  "properties": {
    "date:inception_lower": "1980-01-01",
    "date:inception_upper": "1980-01-01",
    "iso:country": "GB",
    "wof:name": "TN7 4JT",
    "wof:placetype": "postalcode"
  },
  "geometry": {"coordinates":[0.105994,51.112196],"type":"Point"}
}
