{
  "type": "Feature",
  "properties": {
    "iso:country":"GB",
    "wof:name":"EX2 7RD",
    "wof:placetype":"postalcode"
},
  "geometry": {"coordinates":[-3.47679189298065,50.71675262569128],"type":"Point"}
}