{
  "type": "Feature",
  "properties": {
    "date:inception_lower": "2005-11-01",
    "date:inception_upper": "2005-11-01",
    "iso:country": "GB",
    "wof:name": "EX2 7RD",
    "wof:placetype": "postalcode"
  },
  "geometry": {"coordinates":[-3.476792,50.716753],"type":"Point"}
}
