{
  "type": "Feature",
  "properties": {
    "iso:country": "GB",
    "wof:name": "CH7 1FR",
    "wof:placetype": "postalcode"
  },
  "geometry": {"coordinates":[-3.138239,53.157482],"type":"Point"}
}
