{
  "type": "Feature",
  "properties": {
    "iso:country": "GB",
    "wof:name": "PL19 9QF",
    "wof:placetype": "postalcode"
  },
  "geometry": {"coordinates":[-4.117909,50.598901],"type":"Point"}
}
