{
  "type": "Feature",
  "properties": {
    "iso:country": "GB",
    "wof:name": "DT2 9LY",
    "wof:placetype": "postalcode"
  },
  "geometry": {"coordinates":[-2.49302,50.698951],"type":"Point"}
}
