{
  "type": "Feature",
  "properties": {
    "date:inception_lower": "1980-01-01",
    "date:inception_upper": "1980-01-01",
    "iso:country": "GB",
    "wof:name": "DT2 9LY",
    "wof:placetype": "postalcode"
  },
  "geometry": {"coordinates":[-2.49302,50.698951],"type":"Point"}
}
