{
  "type": "Feature",
  "properties": {
    "iso:country":"GB",
    "wof:name":"TR3 7HP",
    "wof:placetype":"postalcode"
},
  "geometry": {"coordinates":[-5.14591190030039,50.18631157109703],"type":"Point"}
}