{
  "type": "Feature",
  "properties": {
    "iso:country": "GB",
    "wof:name": "TR3 7HP",
    "wof:placetype": "postalcode"
  },
  "geometry": {"coordinates":[-5.145912,50.186312],"type":"Point"}
}
