{
  "type": "Feature",
  "properties": {
    "iso:country":"GB",
    "wof:name":"PA23 8GA",
    "wof:placetype":"postalcode"
},
  "geometry": {"coordinates":[-4.9299990395742,55.96138989812188],"type":"Point"}
}