{
  "type": "Feature",
  "properties": {
    "iso:country": "GB",
    "wof:name": "PA23 8GA",
    "wof:placetype": "postalcode"
  },
  "geometry": {"coordinates":[-4.929999,55.96139],"type":"Point"}
}
