{
  "type": "Feature",
  "properties": {
    "iso:country":"GB",
    "wof:name":"KT3 3ES",
    "wof:placetype":"postalcode"
},
  "geometry": {"coordinates":[-0.27268777260081,51.40754928404571],"type":"Point"}
}