{
  "type": "Feature",
  "properties": {
    "iso:country": "GB",
    "wof:name": "SL6 6NS",
    "wof:placetype": "postalcode"
  },
  "geometry": {"coordinates":[-0.758198,51.536835],"type":"Point"}
}
