{
  "type": "Feature",
  "properties": {
    "iso:country": "GB",
    "wof:name": "LL65 3LQ",
    "wof:placetype": "postalcode"
  },
  "geometry": {"coordinates":[-4.377325,53.279061],"type":"Point"}
}
