{
  "type": "Feature",
  "properties": {
    "iso:country":"GB",
    "wof:name":"LL65 3LQ",
    "wof:placetype":"postalcode"
},
  "geometry": {"coordinates":[-4.37732542379655,53.27906120500726],"type":"Point"}
}