{
  "type": "Feature",
  "properties": {
    "date:inception_lower": "1980-01-01",
    "date:inception_upper": "1980-01-01",
    "iso:country": "GB",
    "wof:name": "LL65 3LQ",
    "wof:placetype": "postalcode"
  },
  "geometry": {"coordinates":[-4.377325,53.279061],"type":"Point"}
}
