{
  "type": "Feature",
  "properties": {
    "iso:country":"GB",
    "wof:name":"DH2 3HE",
    "wof:placetype":"postalcode"
},
  "geometry": {"coordinates":[-1.58787443888387,54.84699721457015],"type":"Point"}
}