{
  "type": "Feature",
  "properties": {
    "iso:country": "GB",
    "wof:name": "B16 8NH",
    "wof:placetype": "postalcode"
  },
  "geometry": {"coordinates":[-1.923913,52.473129],"type":"Point"}
}
