{
  "type": "Feature",
  "properties": {
    "iso:country":"GB",
    "wof:name":"B44 9BB",
    "wof:placetype":"postalcode"
},
  "geometry": {"coordinates":[-1.89972345538636,52.55395184709106],"type":"Point"}
}