{
  "type": "Feature",
  "properties": {
    "iso:country":"GB",
    "wof:name":"PE14 9BG",
    "wof:placetype":"postalcode"
},
  "geometry": {"coordinates":[0.22776699185449,52.60113557666926],"type":"Point"}
}