{
  "type": "Feature",
  "properties": {
    "iso:country": "GB",
    "wof:name": "DT7 3ST",
    "wof:placetype": "postalcode"
  },
  "geometry": {"coordinates":[-2.960652,50.730054],"type":"Point"}
}
