{
  "type": "Feature",
  "properties": {
    "iso:country":"GB",
    "wof:name":"DT7 3ST",
    "wof:placetype":"postalcode"
},
  "geometry": {"coordinates":[-2.96065215898405,50.7300542051985],"type":"Point"}
}