{
  "type": "Feature",
  "properties": {
    "iso:country":"GB",
    "wof:name":"N20 0LB",
    "wof:placetype":"postalcode"
},
  "geometry": {"coordinates":[-0.17453047885308,51.6269522865871],"type":"Point"}
}