{
  "type": "Feature",
  "properties": {
    "iso:country": "GB",
    "wof:name": "GL50 4BH",
    "wof:placetype": "postalcode"
  },
  "geometry": {"coordinates":[-2.082845,51.906857],"type":"Point"}
}
