{
  "type": "Feature",
  "properties": {
    "iso:country":"GB",
    "wof:name":"OX10 7DY",
    "wof:placetype":"postalcode"
},
  "geometry": {"coordinates":[-1.13901122584703,51.63635732451059],"type":"Point"}
}