{
  "type": "Feature",
  "properties": {
    "iso:country": "GB",
    "wof:name": "OX39 4DS",
    "wof:placetype": "postalcode"
  },
  "geometry": {"coordinates":[-0.908807,51.704552],"type":"Point"}
}
