{
  "type": "Feature",
  "properties": {
    "iso:country":"GB",
    "wof:name":"W1D 4TE",
    "wof:placetype":"postalcode"
},
  "geometry": {"coordinates":[-0.12992532100755,51.51382674498725],"type":"Point"}
}