{
  "type": "Feature",
  "properties": {
    "iso:country": "GB",
    "wof:name": "WV8 1FH",
    "wof:placetype": "postalcode"
  },
  "geometry": {"coordinates":[-2.189445,52.632482],"type":"Point"}
}
