{
  "type": "Feature",
  "properties": {
    "date:inception_lower":"2014-10-01",
    "date:inception_upper":"2014-10-31",
    "iso:country":"GB",
    "wof:name":"NG19 8TP",
    "wof:placetype":"postalcode"
},
  "geometry": {"coordinates":[-1.256103,53.180623],"type":"Point"}
}