{
  "type": "Feature",
  "properties": {
    "iso:country": "GB",
    "wof:name": "NG19 8TP",
    "wof:placetype": "postalcode"
  },
  "geometry": {"coordinates":[-1.256103,53.180623],"type":"Point"}
}
