{
  "type": "Feature",
  "properties": {
    "iso:country":"GB",
    "wof:name":"NG19 8TP",
    "wof:placetype":"postalcode"
},
  "geometry": {"coordinates":[-1.25610301943919,53.18062319464596],"type":"Point"}
}