{
  "type": "Feature",
  "properties": {
    "iso:country": "GB",
    "wof:name": "SP3 4FB",
    "wof:placetype": "postalcode"
  },
  "geometry": {"coordinates":[-1.901717,51.199238],"type":"Point"}
}
