{
  "type": "Feature",
  "properties": {
    "iso:country":"GB",
    "wof:name":"SP3 4FB",
    "wof:placetype":"postalcode"
},
  "geometry": {"coordinates":[-1.9017113674438,51.19926051260383],"type":"Point"}
}