{
  "type": "Feature",
  "properties": {
    "iso:country": "GB",
    "wof:name": "M14 5QU",
    "wof:placetype": "postalcode"
  },
  "geometry": {"coordinates":[-2.223073,53.454121],"type":"Point"}
}
