{
  "type": "Feature",
  "properties": {
    "date:inception_lower": "1980-01-01",
    "date:inception_upper": "1980-01-01",
    "iso:country": "GB",
    "wof:name": "LS25 6JG",
    "wof:placetype": "postalcode"
  },
  "geometry": {"coordinates":[-1.207709,53.796404],"type":"Point"}
}
