{
  "type": "Feature",
  "properties": {
    "iso:country":"GB",
    "wof:name":"LS25 6JG",
    "wof:placetype":"postalcode"
},
  "geometry": {"coordinates":[-1.207709092644,53.79640393989166],"type":"Point"}
}