{
  "type": "Feature",
  "properties": {
    "iso:country":"GB",
    "wof:name":"RH10 3BT",
    "wof:placetype":"postalcode"
},
  "geometry": {"coordinates":[-0.15665744162862,51.12259731360538],"type":"Point"}
}