{
  "type": "Feature",
  "properties": {
    "iso:country":"GB",
    "wof:name":"UB3 3JD",
    "wof:placetype":"postalcode"
},
  "geometry": {"coordinates":[-0.40974188058784,51.50739723622934],"type":"Point"}
}