{
  "type": "Feature",
  "properties": {
    "iso:country": "GB",
    "wof:name": "IG1 2RR",
    "wof:placetype": "postalcode"
  },
  "geometry": {"coordinates":[0.073463,51.553483],"type":"Point"}
}
