{
  "type": "Feature",
  "properties": {
    "iso:country":"GB",
    "wof:name":"DT9 4NR",
    "wof:placetype":"postalcode"
},
  "geometry": {"coordinates":[-2.48192310956209,51.00526470324839],"type":"Point"}
}