{
  "type": "Feature",
  "properties": {
    "iso:country":"GB",
    "wof:name":"BD15 0AZ",
    "wof:placetype":"postalcode"
},
  "geometry": {"coordinates":[-1.85697357688426,53.82252762585519],"type":"Point"}
}