{
  "type": "Feature",
  "properties": {
    "date:inception_lower": "1980-01-01",
    "date:inception_upper": "1980-01-01",
    "iso:country": "GB",
    "wof:name": "BD15 0AZ",
    "wof:placetype": "postalcode"
  },
  "geometry": {"coordinates":[-1.856974,53.822528],"type":"Point"}
}
