{
  "type": "Feature",
  "properties": {
    "iso:country":"GB",
    "wof:name":"FK6 6DZ",
    "wof:placetype":"postalcode"
},
  "geometry": {"coordinates":[-3.90295383088768,56.02216414901249],"type":"Point"}
}