{
  "type": "Feature",
  "properties": {
    "iso:country":"GB",
    "wof:name":"B33 9UJ",
    "wof:placetype":"postalcode"
},
  "geometry": {"coordinates":[-1.76381657187447,52.48720669890341],"type":"Point"}
}