{
  "type": "Feature",
  "properties": {
    "iso:country":"GB",
    "wof:name":"GU7 2LB",
    "wof:placetype":"postalcode"
},
  "geometry": {"coordinates":[-0.63039848872335,51.182619938784],"type":"Point"}
}