{
  "type": "Feature",
  "properties": {
    "iso:country":"GB",
    "wof:name":"TN37 7EB",
    "wof:placetype":"postalcode"
},
  "geometry": {"coordinates":[0.55555225179268,50.87214853517461],"type":"Point"}
}