{
  "type": "Feature",
  "properties": {
    "iso:country":"GB",
    "wof:name":"TF4 2GG",
    "wof:placetype":"postalcode"
},
  "geometry": {"coordinates":[-2.48700590670626,52.67340130748405],"type":"Point"}
}