{
  "type": "Feature",
  "properties": {
    "iso:country":"GB",
    "wof:name":"ST18 0ZX",
    "wof:placetype":"postalcode"
},
  "geometry": {"coordinates":[-1.96398138624767,52.79287099545215],"type":"Point"}
}