{
  "type": "Feature",
  "properties": {
    "iso:country": "GB",
    "wof:name": "ST18 0ZX",
    "wof:placetype": "postalcode"
  },
  "geometry": {"coordinates":[-1.963981,52.792871],"type":"Point"}
}
