{
  "type": "Feature",
  "properties": {
    "iso:country": "GB",
    "wof:name": "EX32 0RT",
    "wof:placetype": "postalcode"
  },
  "geometry": {"coordinates":[-3.905699,51.035632],"type":"Point"}
}
