{
  "type": "Feature",
  "properties": {
    "date:inception_lower":"1980-01-01",
    "date:inception_upper":"1980-01-31",
    "iso:country":"GB",
    "wof:name":"LE16 7RL",
    "wof:placetype":"postalcode"
},
  "geometry": {"coordinates":[-0.960236,52.497197],"type":"Point"}
}