{
  "type": "Feature",
  "properties": {
    "iso:country":"GB",
    "wof:name":"LE16 7RL",
    "wof:placetype":"postalcode"
},
  "geometry": {"coordinates":[-0.96023567733795,52.49719705504037],"type":"Point"}
}