{
  "type": "Feature",
  "properties": {
    "iso:country": "GB",
    "wof:name": "LE16 7RL",
    "wof:placetype": "postalcode"
  },
  "geometry": {"coordinates":[-0.960236,52.497197],"type":"Point"}
}
