{
  "type": "Feature",
  "properties": {
    "iso:country": "GB",
    "wof:name": "SW2 3EZ",
    "wof:placetype": "postalcode"
  },
  "geometry": {"coordinates":[-0.120285,51.442694],"type":"Point"}
}
