{
  "type": "Feature",
  "properties": {
    "iso:country":"GB",
    "wof:name":"LN12 2EQ",
    "wof:placetype":"postalcode"
},
  "geometry": {"coordinates":[0.265747320854,53.33618675983873],"type":"Point"}
}