{
  "type": "Feature",
  "properties": {
    "iso:country": "GB",
    "wof:name": "DN5 9HA",
    "wof:placetype": "postalcode"
  },
  "geometry": {"coordinates":[-1.166811,53.543858],"type":"Point"}
}
