{
  "type": "Feature",
  "properties": {
    "iso:country":"GB",
    "wof:name":"IP24 3HZ",
    "wof:placetype":"postalcode"
},
  "geometry": {"coordinates":[0.73794099571353,52.4098917810954],"type":"Point"}
}