{
  "type": "Feature",
  "properties": {
    "iso:country": "GB",
    "wof:name": "IP24 3HZ",
    "wof:placetype": "postalcode"
  },
  "geometry": {"coordinates":[0.737941,52.409892],"type":"Point"}
}
