{
  "type": "Feature",
  "properties": {
    "date:inception_lower": "2015-09-01",
    "date:inception_upper": "2015-09-01",
    "iso:country": "GB",
    "wof:name": "PH3 1FX",
    "wof:placetype": "postalcode"
  },
  "geometry": {"coordinates":[-3.702626,56.301034],"type":"Point"}
}
