{
  "type": "Feature",
  "properties": {
    "iso:country": "GB",
    "wof:name": "PR1 4QT",
    "wof:placetype": "postalcode"
  },
  "geometry": {"coordinates":[-2.670942,53.76188],"type":"Point"}
}
