{
  "type": "Feature",
  "properties": {
    "iso:country": "GB",
    "wof:name": "EH52 5LH",
    "wof:placetype": "postalcode"
  },
  "geometry": {"coordinates":[-3.483957,55.932866],"type":"Point"}
}
