{
  "type": "Feature",
  "properties": {
    "iso:country":"GB",
    "wof:name":"PO20 2AR",
    "wof:placetype":"postalcode"
},
  "geometry": {"coordinates":[-0.71012031971393,50.85223554610772],"type":"Point"}
}