{
  "type": "Feature",
  "properties": {
    "date:inception_lower": "2009-08-01",
    "date:inception_upper": "2009-08-01",
    "iso:country": "GB",
    "wof:name": "PO20 2AR",
    "wof:placetype": "postalcode"
  },
  "geometry": {"coordinates":[-0.71012,50.852236],"type":"Point"}
}
