{
  "type": "Feature",
  "properties": {
    "iso:country": "GB",
    "wof:name": "PO20 2AR",
    "wof:placetype": "postalcode"
  },
  "geometry": {"coordinates":[-0.71012,50.852236],"type":"Point"}
}
