{
  "type": "Feature",
  "properties": {
    "date:inception_lower": "2003-09-01",
    "date:inception_upper": "2003-09-01",
    "iso:country": "GB",
    "wof:name": "E14 8JR",
    "wof:placetype": "postalcode"
  },
  "geometry": {"coordinates":[-0.027173,51.499302],"type":"Point"}
}
