{
  "type": "Feature",
  "properties": {
    "iso:country": "GB",
    "wof:name": "WV2 2PJ",
    "wof:placetype": "postalcode"
  },
  "geometry": {"coordinates":[-2.092881,52.566855],"type":"Point"}
}
