{
  "type": "Feature",
  "properties": {
    "date:inception_lower":"2018-11-01",
    "date:inception_upper":"2018-11-30",
    "iso:country":"GB",
    "wof:name":"WV2 2PJ",
    "wof:placetype":"postalcode"
},
  "geometry": {"coordinates":[-2.092881,52.566855],"type":"Point"}
}