{
  "type": "Feature",
  "properties": {
    "iso:country":"GB",
    "wof:name":"SM4 6DL",
    "wof:placetype":"postalcode"
},
  "geometry": {"coordinates":[-0.1840955545264,51.39498723875847],"type":"Point"}
}