{
  "type": "Feature",
  "properties": {
    "date:inception_lower":"1980-01-01",
    "date:inception_upper":"1980-01-31",
    "iso:country":"GB",
    "wof:name":"SM4 6DL",
    "wof:placetype":"postalcode"
},
  "geometry": {"coordinates":[-0.184096,51.394987],"type":"Point"}
}