{
  "type": "Feature",
  "properties": {
    "iso:country": "GB",
    "wof:name": "SM4 6DL",
    "wof:placetype": "postalcode"
  },
  "geometry": {"coordinates":[-0.184096,51.394987],"type":"Point"}
}
