{
  "type": "Feature",
  "properties": {
    "iso:country": "GB",
    "wof:name": "CA6 4PD",
    "wof:placetype": "postalcode"
  },
  "geometry": {"coordinates":[-2.788341,54.955083],"type":"Point"}
}
