{
  "type": "Feature",
  "properties": {
    "iso:country":"GB",
    "wof:name":"LE18 1HA",
    "wof:placetype":"postalcode"
},
  "geometry": {"coordinates":[-1.11992422806907,52.59545073452583],"type":"Point"}
}