{
  "type": "Feature",
  "properties": {
    "iso:country":"GB",
    "wof:name":"KT10 9PH",
    "wof:placetype":"postalcode"
},
  "geometry": {"coordinates":[-0.35989450324973,51.37294026607059],"type":"Point"}
}