{
  "type": "Feature",
  "properties": {
    "iso:country":"GB",
    "wof:name":"BS7 0FB",
    "wof:placetype":"postalcode"
},
  "geometry": {"coordinates":[-2.56984997186337,51.49795998386236],"type":"Point"}
}