{
  "type": "Feature",
  "properties": {
    "date:inception_lower": "2008-09-01",
    "date:inception_upper": "2008-09-01",
    "iso:country": "GB",
    "wof:name": "BS7 0FB",
    "wof:placetype": "postalcode"
  },
  "geometry": {"coordinates":[-2.56985,51.49796],"type":"Point"}
}
