{
  "type": "Feature",
  "properties": {
    "iso:country":"GB",
    "wof:name":"HD4 6JE",
    "wof:placetype":"postalcode"
},
  "geometry": {"coordinates":[-1.78407907012746,53.62892327784248],"type":"Point"}
}