{
  "type": "Feature",
  "properties": {
    "iso:country":"GB",
    "wof:name":"CO7 9GD",
    "wof:placetype":"postalcode"
},
  "geometry": {"coordinates":[0.95334683051898,51.85560967472381],"type":"Point"}
}