{
  "type": "Feature",
  "properties": {
    "iso:country": "GB",
    "wof:name": "CO7 9GD",
    "wof:placetype": "postalcode"
  },
  "geometry": {"coordinates":[0.953347,51.85561],"type":"Point"}
}
