{
  "type": "Feature",
  "properties": {
    "iso:country":"GB",
    "wof:name":"SW1V 4NX",
    "wof:placetype":"postalcode"
},
  "geometry": {"coordinates":[-0.14577774971892,51.49006840965743],"type":"Point"}
}