{
  "type": "Feature",
  "properties": {
    "iso:country": "GB",
    "wof:name": "MK19 7DX",
    "wof:placetype": "postalcode"
  },
  "geometry": {"coordinates":[-0.789517,52.079949],"type":"Point"}
}
