{
  "type": "Feature",
  "properties": {
    "iso:country":"GB",
    "wof:name":"MK19 7DX",
    "wof:placetype":"postalcode"
},
  "geometry": {"coordinates":[-0.78951700138056,52.07994941237669],"type":"Point"}
}