{
  "type": "Feature",
  "properties": {
    "iso:country": "GB",
    "wof:name": "WR11 7TY",
    "wof:placetype": "postalcode"
  },
  "geometry": {"coordinates":[-1.975935,52.025356],"type":"Point"}
}
