{
  "type": "Feature",
  "properties": {
    "iso:country":"GB",
    "wof:name":"WR11 7TY",
    "wof:placetype":"postalcode"
},
  "geometry": {"coordinates":[-1.97593546805226,52.02535602862573],"type":"Point"}
}