{
  "type": "Feature",
  "properties": {
    "iso:country":"GB",
    "wof:name":"WN6 0AD",
    "wof:placetype":"postalcode"
},
  "geometry": {"coordinates":[-2.64459136142359,53.57340516749719],"type":"Point"}
}