{
  "type": "Feature",
  "properties": {
    "date:inception_lower": "1998-12-01",
    "date:inception_upper": "1998-12-01",
    "iso:country": "GB",
    "wof:name": "DN34 5HX",
    "wof:placetype": "postalcode"
  },
  "geometry": {"coordinates":[-0.11679,53.551557],"type":"Point"}
}
