{
  "type": "Feature",
  "properties": {
    "iso:country":"GB",
    "wof:name":"DN34 5HX",
    "wof:placetype":"postalcode"
},
  "geometry": {"coordinates":[-0.11679032338139,53.55155692255374],"type":"Point"}
}