{
  "type": "Feature",
  "properties": {
    "iso:country":"GB",
    "wof:name":"BB2 3AB",
    "wof:placetype":"postalcode"
},
  "geometry": {"coordinates":[-2.47795201401263,53.73828603060268],"type":"Point"}
}