{
  "type": "Feature",
  "properties": {
    "date:inception_lower":"1980-01-01",
    "date:inception_upper":"1980-01-31",
    "iso:country":"GB",
    "wof:name":"BB2 3AB",
    "wof:placetype":"postalcode"
},
  "geometry": {"coordinates":[-2.477952,53.738286],"type":"Point"}
}