{
  "type": "Feature",
  "properties": {
    "date:inception_lower": "2022-07-01",
    "date:inception_upper": "2022-07-01",
    "iso:country": "GB",
    "wof:name": "GU23 7BJ",
    "wof:placetype": "postalcode"
  },
  "geometry": {"coordinates":[-0.524748,51.28543],"type":"Point"}
}
