{
  "type": "Feature",
  "properties": {
    "iso:country":"GB",
    "wof:name":"HA3 5SD",
    "wof:placetype":"postalcode"
},
  "geometry": {"coordinates":[-0.33883697404868,51.59594120998995],"type":"Point"}
}