{
  "type": "Feature",
  "properties": {
    "date:inception_lower":"2018-07-01",
    "date:inception_upper":"2018-07-31",
    "iso:country":"GB",
    "wof:name":"NN18 9QA",
    "wof:placetype":"postalcode"
},
  "geometry": {"coordinates":[-0.729448,52.465642],"type":"Point"}
}