{
  "type": "Feature",
  "properties": {
    "date:inception_lower": "2018-07-01",
    "date:inception_upper": "2018-07-01",
    "iso:country": "GB",
    "wof:name": "NN18 9QA",
    "wof:placetype": "postalcode"
  },
  "geometry": {"coordinates":[-0.729297,52.465793],"type":"Point"}
}
