{
  "type": "Feature",
  "properties": {
    "date:inception_lower":"1980-01-01",
    "date:inception_upper":"1980-01-31",
    "iso:country":"GB",
    "wof:name":"SN12 8HQ",
    "wof:placetype":"postalcode"
},
  "geometry": {"coordinates":[-2.184994,51.392308],"type":"Point"}
}