{
  "type": "Feature",
  "properties": {
    "iso:country": "GB",
    "wof:name": "TA6 5JU",
    "wof:placetype": "postalcode"
  },
  "geometry": {"coordinates":[-2.993956,51.127474],"type":"Point"}
}
