{
  "type": "Feature",
  "properties": {
    "iso:country": "GB",
    "wof:name": "OL4 5PB",
    "wof:placetype": "postalcode"
  },
  "geometry": {"coordinates":[-2.07622,53.529961],"type":"Point"}
}
