{
  "type": "Feature",
  "properties": {
    "date:inception_lower": "1993-01-01",
    "date:inception_upper": "1993-01-01",
    "iso:country": "GB",
    "wof:name": "OL4 5PB",
    "wof:placetype": "postalcode"
  },
  "geometry": {"coordinates":[-2.07622,53.529961],"type":"Point"}
}
