{
  "type": "Feature",
  "properties": {
    "iso:country":"GB",
    "wof:name":"OL4 5PB",
    "wof:placetype":"postalcode"
},
  "geometry": {"coordinates":[-2.07622011024598,53.52996127732645],"type":"Point"}
}