{
  "type": "Feature",
  "properties": {
    "date:inception_lower": "2006-04-01",
    "date:inception_upper": "2006-04-01",
    "iso:country": "GB",
    "wof:name": "WF12 9BS",
    "wof:placetype": "postalcode"
  },
  "geometry": {"coordinates":[-1.622104,53.676453],"type":"Point"}
}
