{
  "type": "Feature",
  "properties": {
    "iso:country": "GB",
    "wof:name": "WF12 9BS",
    "wof:placetype": "postalcode"
  },
  "geometry": {"coordinates":[-1.621699,53.677408],"type":"Point"}
}
