{
  "type": "Feature",
  "properties": {
    "iso:country":"GB",
    "wof:name":"WF12 9BS",
    "wof:placetype":"postalcode"
},
  "geometry": {"coordinates":[-1.62210099949966,53.67643815355163],"type":"Point"}
}