{
  "type": "Feature",
  "properties": {
    "iso:country":"GB",
    "wof:name":"WD23 3BQ",
    "wof:placetype":"postalcode"
},
  "geometry": {"coordinates":[-0.35702043860963,51.65136377041586],"type":"Point"}
}