{
  "type": "Feature",
  "properties": {
    "date:inception_lower":"2000-10-01",
    "date:inception_upper":"2000-10-31",
    "iso:country":"GB",
    "wof:name":"WD23 3BQ",
    "wof:placetype":"postalcode"
},
  "geometry": {"coordinates":[-0.35702,51.651364],"type":"Point"}
}