{
  "type": "Feature",
  "properties": {
    "iso:country": "GB",
    "wof:name": "WD23 3BQ",
    "wof:placetype": "postalcode"
  },
  "geometry": {"coordinates":[-0.35702,51.651364],"type":"Point"}
}
