{
  "type": "Feature",
  "properties": {
    "iso:country": "GB",
    "wof:name": "LE12 9BT",
    "wof:placetype": "postalcode"
  },
  "geometry": {"coordinates":[-1.296138,52.773477],"type":"Point"}
}
