{
  "type": "Feature",
  "properties": {
    "date:inception_lower":"2004-06-01",
    "date:inception_upper":"2004-06-30",
    "iso:country":"GB",
    "wof:name":"LE12 9BT",
    "wof:placetype":"postalcode"
},
  "geometry": {"coordinates":[-1.296138,52.773477],"type":"Point"}
}