{
  "type": "Feature",
  "properties": {
    "iso:country":"GB",
    "wof:name":"SR6 7EE",
    "wof:placetype":"postalcode"
},
  "geometry": {"coordinates":[-1.36466682859063,54.9527945483997],"type":"Point"}
}