{
  "type": "Feature",
  "properties": {
    "date:inception_lower":"1986-04-01",
    "date:inception_upper":"1986-04-30",
    "iso:country":"GB",
    "wof:name":"SR6 7EE",
    "wof:placetype":"postalcode"
},
  "geometry": {"coordinates":[-1.364667,54.952795],"type":"Point"}
}