{
  "type": "Feature",
  "properties": {
    "iso:country": "GB",
    "wof:name": "SR6 7EE",
    "wof:placetype": "postalcode"
  },
  "geometry": {"coordinates":[-1.364667,54.952795],"type":"Point"}
}
