{
  "type": "Feature",
  "properties": {
    "iso:country":"GB",
    "wof:name":"G72 7NL",
    "wof:placetype":"postalcode"
},
  "geometry": {"coordinates":[-4.1591194956017,55.81786309683495],"type":"Point"}
}