{
  "type": "Feature",
  "properties": {
    "iso:country":"GB",
    "wof:name":"LL11 2PR",
    "wof:placetype":"postalcode"
},
  "geometry": {"coordinates":[-2.99336824139384,53.05846875122516],"type":"Point"}
}