{
  "type": "Feature",
  "properties": {
    "date:inception_lower": "1980-01-01",
    "date:inception_upper": "1980-01-01",
    "iso:country": "GB",
    "wof:name": "LL11 2PR",
    "wof:placetype": "postalcode"
  },
  "geometry": {"coordinates":[-2.993368,53.058469],"type":"Point"}
}
