{
  "type": "Feature",
  "properties": {
    "iso:country":"GB",
    "wof:name":"NR9 5NP",
    "wof:placetype":"postalcode"
},
  "geometry": {"coordinates":[1.16378322135631,52.72925903214473],"type":"Point"}
}