{
  "type": "Feature",
  "properties": {
    "date:inception_lower": "1980-01-01",
    "date:inception_upper": "1980-01-01",
    "iso:country": "GB",
    "wof:name": "NR9 5NP",
    "wof:placetype": "postalcode"
  },
  "geometry": {"coordinates":[1.163783,52.729259],"type":"Point"}
}
