{
  "type": "Feature",
  "properties": {
    "iso:country": "GB",
    "wof:name": "GL52 9QQ",
    "wof:placetype": "postalcode"
  },
  "geometry": {"coordinates":[-2.044094,51.946484],"type":"Point"}
}
