{
  "type": "Feature",
  "properties": {
    "iso:country":"GB",
    "wof:name":"GL52 9QQ",
    "wof:placetype":"postalcode"
},
  "geometry": {"coordinates":[-2.04409451262269,51.94648352074281],"type":"Point"}
}