{
  "type": "Feature",
  "properties": {
    "iso:country":"GB",
    "wof:name":"EX5 4PZ",
    "wof:placetype":"postalcode"
},
  "geometry": {"coordinates":[-3.4502374130283,50.80270116062447],"type":"Point"}
}