{
  "type": "Feature",
  "properties": {
    "iso:country": "GB",
    "wof:name": "EX5 4PZ",
    "wof:placetype": "postalcode"
  },
  "geometry": {"coordinates":[-3.450237,50.802701],"type":"Point"}
}
