{
  "type": "Feature",
  "properties": {
    "date:inception_lower":"1980-01-01",
    "date:inception_upper":"1980-01-31",
    "iso:country":"GB",
    "wof:name":"GL51 0LR",
    "wof:placetype":"postalcode"
},
  "geometry": {"coordinates":[-2.12611,51.911675],"type":"Point"}
}