{
  "type": "Feature",
  "properties": {
    "iso:country":"GB",
    "wof:name":"GL51 0LR",
    "wof:placetype":"postalcode"
},
  "geometry": {"coordinates":[-2.12610990758114,51.91167458467804],"type":"Point"}
}