{
  "type": "Feature",
  "properties": {
    "iso:country": "GB",
    "wof:name": "GL51 0LR",
    "wof:placetype": "postalcode"
  },
  "geometry": {"coordinates":[-2.12611,51.911675],"type":"Point"}
}
