{
  "type": "Feature",
  "properties": {
    "iso:country":"GB",
    "wof:name":"HP23 4DA",
    "wof:placetype":"postalcode"
},
  "geometry": {"coordinates":[-0.67225601910915,51.79136781801622],"type":"Point"}
}