{
  "type": "Feature",
  "properties": {
    "iso:country":"GB",
    "wof:name":"W3 8NZ",
    "wof:placetype":"postalcode"
},
  "geometry": {"coordinates":[-0.26634022890908,51.50574300071479],"type":"Point"}
}