{
  "type": "Feature",
  "properties": {
    "date:inception_lower": "1981-06-01",
    "date:inception_upper": "1981-06-01",
    "iso:country": "GB",
    "wof:name": "W3 8NZ",
    "wof:placetype": "postalcode"
  },
  "geometry": {"coordinates":[-0.26634,51.505743],"type":"Point"}
}
