{
  "type": "Feature",
  "properties": {
    "iso:country":"GB",
    "wof:name":"SE1 5UX",
    "wof:placetype":"postalcode"
},
  "geometry": {"coordinates":[-0.08250573271415,51.49262092607548],"type":"Point"}
}