{
  "type": "Feature",
  "properties": {
    "date:inception_lower": "2020-01-01",
    "date:inception_upper": "2020-01-01",
    "iso:country": "GB",
    "wof:name": "LU4 8FX",
    "wof:placetype": "postalcode"
  },
  "geometry": {"coordinates":[-0.446651,51.894427],"type":"Point"}
}
