{
  "type": "Feature",
  "properties": {
    "iso:country":"GB",
    "wof:name":"LS13 4LQ",
    "wof:placetype":"postalcode"
},
  "geometry": {"coordinates":[-1.64967769858046,53.80474604535475],"type":"Point"}
}