{
  "type": "Feature",
  "properties": {
    "date:inception_lower":"1992-08-01",
    "date:inception_upper":"1992-08-31",
    "iso:country":"GB",
    "wof:name":"LS13 4LQ",
    "wof:placetype":"postalcode"
},
  "geometry": {"coordinates":[-1.649678,53.804746],"type":"Point"}
}