{
  "type": "Feature",
  "properties": {
    "iso:country": "GB",
    "wof:name": "LS13 4LQ",
    "wof:placetype": "postalcode"
  },
  "geometry": {"coordinates":[-1.649678,53.804746],"type":"Point"}
}
