{
  "type": "Feature",
  "properties": {
    "iso:country":"GB",
    "wof:name":"ST6 1PF",
    "wof:placetype":"postalcode"
},
  "geometry": {"coordinates":[-2.17243444440064,53.05315255841625],"type":"Point"}
}