{
  "type": "Feature",
  "properties": {
    "iso:country": "GB",
    "wof:name": "ST6 1PF",
    "wof:placetype": "postalcode"
  },
  "geometry": {"coordinates":[-2.17239,53.053134],"type":"Point"}
}
