{
  "type": "Feature",
  "properties": {
    "date:inception_lower": "1980-01-01",
    "date:inception_upper": "1980-01-01",
    "iso:country": "GB",
    "wof:name": "BA21 5SR",
    "wof:placetype": "postalcode"
  },
  "geometry": {"coordinates":[-2.618254,50.959589],"type":"Point"}
}
