{
  "type": "Feature",
  "properties": {
    "iso:country": "GB",
    "wof:name": "BA21 5SR",
    "wof:placetype": "postalcode"
  },
  "geometry": {"coordinates":[-2.618254,50.959589],"type":"Point"}
}
