{
  "type": "Feature",
  "properties": {
    "iso:country":"GB",
    "wof:name":"BA21 5SR",
    "wof:placetype":"postalcode"
},
  "geometry": {"coordinates":[-2.61825409359602,50.95958874499689],"type":"Point"}
}