{
  "type": "Feature",
  "properties": {
    "iso:country": "GB",
    "wof:name": "SY10 0PE",
    "wof:placetype": "postalcode"
  },
  "geometry": {"coordinates":[-3.331728,52.809952],"type":"Point"}
}
