{
  "type": "Feature",
  "properties": {
    "iso:country": "GB",
    "wof:name": "NN13 5RQ",
    "wof:placetype": "postalcode"
  },
  "geometry": {"coordinates":[-1.147259,52.00763],"type":"Point"}
}
