{
  "type": "Feature",
  "properties": {
    "iso:country":"GB",
    "wof:name":"NN13 5RQ",
    "wof:placetype":"postalcode"
},
  "geometry": {"coordinates":[-1.14782946174697,52.00767730806582],"type":"Point"}
}