{
  "type": "Feature",
  "properties": {
    "iso:country": "GB",
    "wof:name": "SE27 0UZ",
    "wof:placetype": "postalcode"
  },
  "geometry": {"coordinates":[-0.100445,51.42733],"type":"Point"}
}
