{
  "type": "Feature",
  "properties": {
    "iso:country":"GB",
    "wof:name":"SE27 0UZ",
    "wof:placetype":"postalcode"
},
  "geometry": {"coordinates":[-0.10044533365101,51.42732967418709],"type":"Point"}
}