{
  "type": "Feature",
  "properties": {
    "iso:country":"GB",
    "wof:name":"SW2 2AX",
    "wof:placetype":"postalcode"
},
  "geometry": {"coordinates":[-0.11645321135085,51.44872971403385],"type":"Point"}
}