{
  "type": "Feature",
  "properties": {
    "iso:country":"GB",
    "wof:name":"CF36 3DR",
    "wof:placetype":"postalcode"
},
  "geometry": {"coordinates":[-3.70359137090066,51.48063757205292],"type":"Point"}
}