{
  "type": "Feature",
  "properties": {
    "date:inception_lower": "2013-09-01",
    "date:inception_upper": "2013-09-01",
    "iso:country": "GB",
    "wof:name": "CM3 8FF",
    "wof:placetype": "postalcode"
  },
  "geometry": {"coordinates":[0.536394,51.669986],"type":"Point"}
}
