{
  "type": "Feature",
  "properties": {
    "iso:country": "GB",
    "wof:name": "CM3 8FF",
    "wof:placetype": "postalcode"
  },
  "geometry": {"coordinates":[0.536394,51.669986],"type":"Point"}
}
