{
  "type": "Feature",
  "properties": {
    "iso:country":"GB",
    "wof:name":"SA48 8AN",
    "wof:placetype":"postalcode"
},
  "geometry": {"coordinates":[-4.08132083775275,52.12190183644339],"type":"Point"}
}