{
  "type": "Feature",
  "properties": {
    "iso:country": "GB",
    "wof:name": "OX14 1UQ",
    "wof:placetype": "postalcode"
  },
  "geometry": {"coordinates":[-1.301799,51.675826],"type":"Point"}
}
