{
  "type": "Feature",
  "properties": {
    "iso:country":"GB",
    "wof:name":"OX14 1UQ",
    "wof:placetype":"postalcode"
},
  "geometry": {"coordinates":[-1.30181605380745,51.67582199457594],"type":"Point"}
}