{
  "type": "Feature",
  "properties": {
    "iso:country":"GB",
    "wof:name":"HG3 3LB",
    "wof:placetype":"postalcode"
},
  "geometry": {"coordinates":[-1.60423415521538,54.08625544354921],"type":"Point"}
}