{
  "type": "Feature",
  "properties": {
    "iso:country":"GB",
    "wof:name":"B50 4QQ",
    "wof:placetype":"postalcode"
},
  "geometry": {"coordinates":[-1.85822112401219,52.16754894125308],"type":"Point"}
}