{
  "type": "Feature",
  "properties": {
    "date:inception_lower": "2000-12-01",
    "date:inception_upper": "2000-12-01",
    "iso:country": "GB",
    "wof:name": "B50 4QQ",
    "wof:placetype": "postalcode"
  },
  "geometry": {"coordinates":[-1.858221,52.167549],"type":"Point"}
}
