{
  "type": "Feature",
  "properties": {
    "date:inception_lower": "2021-11-01",
    "date:inception_upper": "2021-11-01",
    "iso:country": "GB",
    "wof:name": "OX12 0HF",
    "wof:placetype": "postalcode"
  },
  "geometry": {"coordinates":[-1.38842,51.636538],"type":"Point"}
}
