{
  "type": "Feature",
  "properties": {
    "iso:country":"GB",
    "wof:name":"PR4 6AH",
    "wof:placetype":"postalcode"
},
  "geometry": {"coordinates":[-2.84392448875373,53.69800347442867],"type":"Point"}
}