{
  "type": "Feature",
  "properties": {
    "iso:country":"GB",
    "wof:name":"ME15 6DP",
    "wof:placetype":"postalcode"
},
  "geometry": {"coordinates":[0.51643779403372,51.25481014208761],"type":"Point"}
}