{
  "type": "Feature",
  "properties": {
    "date:inception_lower": "1980-01-01",
    "date:inception_upper": "1980-01-01",
    "iso:country": "GB",
    "wof:name": "ME15 6DP",
    "wof:placetype": "postalcode"
  },
  "geometry": {"coordinates":[0.516323,51.254776],"type":"Point"}
}
