{
  "type": "Feature",
  "properties": {
    "iso:country": "GB",
    "wof:name": "BS28 4AS",
    "wof:placetype": "postalcode"
  },
  "geometry": {"coordinates":[-2.819524,51.22609],"type":"Point"}
}
