{
  "type": "Feature",
  "properties": {
    "date:inception_lower":"1980-01-01",
    "date:inception_upper":"1980-01-31",
    "iso:country":"GB",
    "wof:name":"DY13 8DU",
    "wof:placetype":"postalcode"
},
  "geometry": {"coordinates":[-2.277346,52.342196],"type":"Point"}
}