{
  "type": "Feature",
  "properties": {
    "iso:country":"GB",
    "wof:name":"CO10 0JL",
    "wof:placetype":"postalcode"
},
  "geometry": {"coordinates":[0.74784928613958,52.0255106515862],"type":"Point"}
}