{
  "type": "Feature",
  "properties": {
    "date:inception_lower":"1980-01-01",
    "date:inception_upper":"1980-01-31",
    "iso:country":"GB",
    "wof:name":"NG5 3JB",
    "wof:placetype":"postalcode"
},
  "geometry": {"coordinates":[-1.152575,52.99264],"type":"Point"}
}