{
  "type": "Feature",
  "properties": {
    "iso:country":"GB",
    "wof:name":"NG5 3JB",
    "wof:placetype":"postalcode"
},
  "geometry": {"coordinates":[-1.15257538169867,52.99263979254813],"type":"Point"}
}