{
  "type": "Feature",
  "properties": {
    "iso:country": "GB",
    "wof:name": "GU34 5TE",
    "wof:placetype": "postalcode"
  },
  "geometry": {"coordinates":[-1.037724,51.115816],"type":"Point"}
}
