{
  "type": "Feature",
  "properties": {
    "iso:country":"GB",
    "wof:name":"HP9 1JL",
    "wof:placetype":"postalcode"
},
  "geometry": {"coordinates":[-0.65462503306999,51.6137337324704],"type":"Point"}
}