{
  "type": "Feature",
  "properties": {
    "iso:country":"GB",
    "wof:name":"N16 0NS",
    "wof:placetype":"postalcode"
},
  "geometry": {"coordinates":[-0.07609173233138,51.56144386455272],"type":"Point"}
}