{
  "type": "Feature",
  "properties": {
    "iso:country":"GB",
    "wof:name":"SA44 6DU",
    "wof:placetype":"postalcode"
},
  "geometry": {"coordinates":[-4.4392955203915,52.13483743252348],"type":"Point"}
}