{
  "type": "Feature",
  "properties": {
    "date:inception_lower": "1980-01-01",
    "date:inception_upper": "1980-01-01",
    "iso:country": "GB",
    "wof:name": "CM3 5JW",
    "wof:placetype": "postalcode"
  },
  "geometry": {"coordinates":[0.612876,51.648865],"type":"Point"}
}
