{
  "type": "Feature",
  "properties": {
    "iso:country":"GB",
    "wof:name":"CM3 5JW",
    "wof:placetype":"postalcode"
},
  "geometry": {"coordinates":[0.61287546735837,51.64886532633343],"type":"Point"}
}