{
  "type": "Feature",
  "properties": {
    "iso:country":"GB",
    "wof:name":"RH9 8YZ",
    "wof:placetype":"postalcode"
},
  "geometry": {"coordinates":[-0.04704159904272,51.21799707193747],"type":"Point"}
}