{
  "type": "Feature",
  "properties": {
    "iso:country": "GB",
    "wof:name": "RH9 8YZ",
    "wof:placetype": "postalcode"
  },
  "geometry": {"coordinates":[-0.047042,51.217997],"type":"Point"}
}
