{
  "type": "Feature",
  "properties": {
    "date:inception_lower":"1986-04-01",
    "date:inception_upper":"1986-04-30",
    "iso:country":"GB",
    "wof:name":"RH9 8YZ",
    "wof:placetype":"postalcode"
},
  "geometry": {"coordinates":[-0.047042,51.217997],"type":"Point"}
}