{
  "type": "Feature",
  "properties": {
    "iso:country":"GB",
    "wof:name":"M17 1NB",
    "wof:placetype":"postalcode"
},
  "geometry": {"coordinates":[-2.31633523546726,53.4705664733928],"type":"Point"}
}