{
  "type": "Feature",
  "properties": {
    "date:inception_lower": "1980-01-01",
    "date:inception_upper": "1980-01-01",
    "iso:country": "GB",
    "wof:name": "SM2 6PS",
    "wof:placetype": "postalcode"
  },
  "geometry": {"coordinates":[-0.196085,51.356296],"type":"Point"}
}
