{
  "type": "Feature",
  "properties": {
    "iso:country":"GB",
    "wof:name":"SM2 6PS",
    "wof:placetype":"postalcode"
},
  "geometry": {"coordinates":[-0.19603986608,51.35626958892681],"type":"Point"}
}