{
  "type": "Feature",
  "properties": {
    "iso:country":"GB",
    "wof:name":"SM6 7PD",
    "wof:placetype":"postalcode"
},
  "geometry": {"coordinates":[-0.15017088330471,51.36826092309553],"type":"Point"}
}