{
  "type": "Feature",
  "properties": {
    "iso:country": "GB",
    "wof:name": "NG13 8AB",
    "wof:placetype": "postalcode"
  },
  "geometry": {"coordinates":[-0.952975,52.951595],"type":"Point"}
}
