{
  "type": "Feature",
  "properties": {
    "iso:country":"GB",
    "wof:name":"BB4 7PG",
    "wof:placetype":"postalcode"
},
  "geometry": {"coordinates":[-2.27571097396521,53.70095658865299],"type":"Point"}
}