{
  "type": "Feature",
  "properties": {
    "date:inception_lower": "1980-01-01",
    "date:inception_upper": "1980-01-01",
    "iso:country": "GB",
    "wof:name": "BB4 7PG",
    "wof:placetype": "postalcode"
  },
  "geometry": {"coordinates":[-2.275711,53.700957],"type":"Point"}
}
