{
  "type": "Feature",
  "properties": {
    "date:inception_lower":"2001-06-01",
    "date:inception_upper":"2001-06-30",
    "iso:country":"GB",
    "wof:name":"OX29 7YE",
    "wof:placetype":"postalcode"
},
  "geometry": {"coordinates":[-1.48712,51.766563],"type":"Point"}
}