{
  "type": "Feature",
  "properties": {
    "iso:country":"GB",
    "wof:name":"DH1 2SX",
    "wof:placetype":"postalcode"
},
  "geometry": {"coordinates":[-1.5378564729277,54.76078908754135],"type":"Point"}
}