{
  "type": "Feature",
  "properties": {
    "iso:country":"GB",
    "wof:name":"WA10 3DB",
    "wof:placetype":"postalcode"
},
  "geometry": {"coordinates":[-2.74272150399949,53.44496396531171],"type":"Point"}
}