{
  "type": "Feature",
  "properties": {
    "iso:country": "GB",
    "wof:name": "WA10 3DB",
    "wof:placetype": "postalcode"
  },
  "geometry": {"coordinates":[-2.743211,53.444635],"type":"Point"}
}
