{
  "type": "Feature",
  "properties": {
    "iso:country": "GB",
    "wof:name": "WA10 3DB",
    "wof:placetype": "postalcode"
  },
  "geometry": {"coordinates":[-2.74272,53.44498],"type":"Point"}
}
