{
  "type": "Feature",
  "properties": {
    "iso:country":"GB",
    "wof:name":"RG10 0NN",
    "wof:placetype":"postalcode"
},
  "geometry": {"coordinates":[-0.81618875369911,51.47403235275101],"type":"Point"}
}