{
  "type": "Feature",
  "properties": {
    "date:inception_lower": "1980-01-01",
    "date:inception_upper": "1980-01-01",
    "iso:country": "GB",
    "wof:name": "RG10 0NN",
    "wof:placetype": "postalcode"
  },
  "geometry": {"coordinates":[-0.816189,51.474032],"type":"Point"}
}
