{
  "type": "Feature",
  "properties": {
    "iso:country":"GB",
    "wof:name":"RM15 4SR",
    "wof:placetype":"postalcode"
},
  "geometry": {"coordinates":[0.24975409023563,51.50258026563232],"type":"Point"}
}