{
  "type": "Feature",
  "properties": {
    "date:inception_lower":"1980-01-01",
    "date:inception_upper":"1980-01-31",
    "iso:country":"GB",
    "wof:name":"RM15 4SR",
    "wof:placetype":"postalcode"
},
  "geometry": {"coordinates":[0.249754,51.50258],"type":"Point"}
}