{
  "type": "Feature",
  "properties": {
    "iso:country": "GB",
    "wof:name": "DY4 0RU",
    "wof:placetype": "postalcode"
  },
  "geometry": {"coordinates":[-2.055101,52.541054],"type":"Point"}
}
