{
  "type": "Feature",
  "properties": {
    "date:inception_lower": "1980-01-01",
    "date:inception_upper": "1980-01-01",
    "iso:country": "GB",
    "wof:name": "DY4 0RU",
    "wof:placetype": "postalcode"
  },
  "geometry": {"coordinates":[-2.055101,52.541054],"type":"Point"}
}
