{
  "type": "Feature",
  "properties": {
    "iso:country":"GB",
    "wof:name":"DY4 0RU",
    "wof:placetype":"postalcode"
},
  "geometry": {"coordinates":[-2.05510101462423,52.5410537304104],"type":"Point"}
}