{
  "type": "Feature",
  "properties": {
    "iso:country": "GB",
    "wof:name": "S74 9NA",
    "wof:placetype": "postalcode"
  },
  "geometry": {"coordinates":[-1.437149,53.498497],"type":"Point"}
}
