{
  "type": "Feature",
  "properties": {
    "date:inception_lower": "2005-04-01",
    "date:inception_upper": "2005-04-01",
    "iso:country": "GB",
    "wof:name": "HR2 6FD",
    "wof:placetype": "postalcode"
  },
  "geometry": {"coordinates":[-2.700677,52.041048],"type":"Point"}
}
