{
  "type": "Feature",
  "properties": {
    "iso:country":"GB",
    "wof:name":"HR2 6FD",
    "wof:placetype":"postalcode"
},
  "geometry": {"coordinates":[-2.70061785154301,52.04111153708957],"type":"Point"}
}