{
  "type": "Feature",
  "properties": {
    "date:inception_lower":"2006-07-01",
    "date:inception_upper":"2006-07-31",
    "iso:country":"GB",
    "wof:name":"NG2 7PJ",
    "wof:placetype":"postalcode"
},
  "geometry": {"coordinates":[-1.135013,52.929065],"type":"Point"}
}