{
  "type": "Feature",
  "properties": {
    "iso:country":"GB",
    "wof:name":"BS21 6RJ",
    "wof:placetype":"postalcode"
},
  "geometry": {"coordinates":[-2.80750944083896,51.44704669973407],"type":"Point"}
}