{
  "type": "Feature",
  "properties": {
    "date:inception_lower": "1980-01-01",
    "date:inception_upper": "1980-01-01",
    "iso:country": "GB",
    "wof:name": "BS21 6RJ",
    "wof:placetype": "postalcode"
  },
  "geometry": {"coordinates":[-2.807509,51.447047],"type":"Point"}
}
