{
  "type": "Feature",
  "properties": {
    "iso:country": "GB",
    "wof:name": "BS21 6RJ",
    "wof:placetype": "postalcode"
  },
  "geometry": {"coordinates":[-2.807509,51.447047],"type":"Point"}
}
