{
  "type": "Feature",
  "properties": {
    "iso:country":"GB",
    "wof:name":"DN11 9DX",
    "wof:placetype":"postalcode"
},
  "geometry": {"coordinates":[-1.12846367076118,53.47403880130831],"type":"Point"}
}