{
  "type": "Feature",
  "properties": {
    "iso:country":"GB",
    "wof:name":"G13 3LP",
    "wof:placetype":"postalcode"
},
  "geometry": {"coordinates":[-4.3480021024347,55.89479541487503],"type":"Point"}
}