{
  "type": "Feature",
  "properties": {
    "date:inception_lower":"1980-01-01",
    "date:inception_upper":"1980-01-31",
    "iso:country":"GB",
    "wof:name":"KT19 0HQ",
    "wof:placetype":"postalcode"
},
  "geometry": {"coordinates":[-0.265143,51.362592],"type":"Point"}
}