{
  "type": "Feature",
  "properties": {
    "iso:country":"GB",
    "wof:name":"HX7 5NT",
    "wof:placetype":"postalcode"
},
  "geometry": {"coordinates":[-1.98134881179102,53.73167970177328],"type":"Point"}
}