{
  "type": "Feature",
  "properties": {
    "date:inception_lower": "2013-07-01",
    "date:inception_upper": "2013-07-01",
    "iso:country": "GB",
    "wof:name": "OL11 2WD",
    "wof:placetype": "postalcode"
  },
  "geometry": {"coordinates":[-2.176823,53.586886],"type":"Point"}
}
