{
  "type": "Feature",
  "properties": {
    "iso:country": "GB",
    "wof:name": "OL11 2WD",
    "wof:placetype": "postalcode"
  },
  "geometry": {"coordinates":[-2.176823,53.586886],"type":"Point"}
}
