{
  "type": "Feature",
  "properties": {
    "date:inception_lower": "1980-01-01",
    "date:inception_upper": "1980-01-01",
    "iso:country": "GB",
    "wof:name": "SL7 3BN",
    "wof:placetype": "postalcode"
  },
  "geometry": {"coordinates":[-0.780628,51.582362],"type":"Point"}
}
