{
  "type": "Feature",
  "properties": {
    "iso:country": "GB",
    "wof:name": "SL7 3BN",
    "wof:placetype": "postalcode"
  },
  "geometry": {"coordinates":[-0.780628,51.582362],"type":"Point"}
}
