{
  "type": "Feature",
  "properties": {
    "date:inception_lower": "1991-09-01",
    "date:inception_upper": "1991-09-01",
    "iso:country": "GB",
    "wof:name": "NN14 4UL",
    "wof:placetype": "postalcode"
  },
  "geometry": {"coordinates":[-0.533362,52.395028],"type":"Point"}
}
