{
  "type": "Feature",
  "properties": {
    "iso:country": "GB",
    "wof:name": "YO22 4AF",
    "wof:placetype": "postalcode"
  },
  "geometry": {"coordinates":[-0.609317,54.483411],"type":"Point"}
}
