{
  "type": "Feature",
  "properties": {
    "iso:country":"GB",
    "wof:name":"TN4 0BP",
    "wof:placetype":"postalcode"
},
  "geometry": {"coordinates":[0.26444483336097,51.15399740105519],"type":"Point"}
}