{
  "type": "Feature",
  "properties": {
    "iso:country":"GB",
    "wof:name":"SK15 3LS",
    "wof:placetype":"postalcode"
},
  "geometry": {"coordinates":[-2.02227502862141,53.50452852161279],"type":"Point"}
}