{
  "type": "Feature",
  "properties": {
    "iso:country":"GB",
    "wof:name":"RG9 1DR",
    "wof:placetype":"postalcode"
},
  "geometry": {"coordinates":[-0.89886272810858,51.53035323157094],"type":"Point"}
}