{
  "type": "Feature",
  "properties": {
    "date:inception_lower": "1980-01-01",
    "date:inception_upper": "1980-01-01",
    "iso:country": "GB",
    "wof:name": "RG9 1DR",
    "wof:placetype": "postalcode"
  },
  "geometry": {"coordinates":[-0.898191,51.529918],"type":"Point"}
}
