{
  "type": "Feature",
  "properties": {
    "iso:country": "GB",
    "wof:name": "RG9 1DR",
    "wof:placetype": "postalcode"
  },
  "geometry": {"coordinates":[-0.898843,51.530356],"type":"Point"}
}
