{
  "type": "Feature",
  "properties": {
    "date:inception_lower": "1980-01-01",
    "date:inception_upper": "1980-01-01",
    "iso:country": "GB",
    "wof:name": "BS23 2AF",
    "wof:placetype": "postalcode"
  },
  "geometry": {"coordinates":[-2.980364,51.351454],"type":"Point"}
}
