{
  "type": "Feature",
  "properties": {
    "iso:country":"GB",
    "wof:name":"BS23 2AF",
    "wof:placetype":"postalcode"
},
  "geometry": {"coordinates":[-2.98039941853662,51.35139388104955],"type":"Point"}
}