{
  "type": "Feature",
  "properties": {
    "date:inception_lower": "1981-09-01",
    "date:inception_upper": "1981-09-01",
    "iso:country": "GB",
    "wof:name": "S66 8QL",
    "wof:placetype": "postalcode"
  },
  "geometry": {"coordinates":[-1.247307,53.424637],"type":"Point"}
}
