{
  "type": "Feature",
  "properties": {
    "iso:country": "GB",
    "wof:name": "S66 8QL",
    "wof:placetype": "postalcode"
  },
  "geometry": {"coordinates":[-1.246574,53.424407],"type":"Point"}
}
