{
  "type": "Feature",
  "properties": {
    "iso:country":"GB",
    "wof:name":"S66 8QL",
    "wof:placetype":"postalcode"
},
  "geometry": {"coordinates":[-1.24601059275904,53.42475293474889],"type":"Point"}
}