{
  "type": "Feature",
  "properties": {
    "iso:country":"GB",
    "wof:name":"CR5 3BP",
    "wof:placetype":"postalcode"
},
  "geometry": {"coordinates":[-0.1423336906125,51.31944122990082],"type":"Point"}
}