{
  "type": "Feature",
  "properties": {
    "date:inception_lower": "1990-07-01",
    "date:inception_upper": "1990-07-01",
    "iso:country": "GB",
    "wof:name": "CR5 3BP",
    "wof:placetype": "postalcode"
  },
  "geometry": {"coordinates":[-0.142308,51.319439],"type":"Point"}
}
