{
  "type": "Feature",
  "properties": {
    "iso:country":"GB",
    "wof:name":"NP23 5AE",
    "wof:placetype":"postalcode"
},
  "geometry": {"coordinates":[-3.19981668590016,51.77863861387949],"type":"Point"}
}