{
  "type": "Feature",
  "properties": {
    "iso:country":"GB",
    "wof:name":"DL11 6SN",
    "wof:placetype":"postalcode"
},
  "geometry": {"coordinates":[-1.94178734855804,54.38977226309833],"type":"Point"}
}