{
  "type": "Feature",
  "properties": {
    "iso:country": "GB",
    "wof:name": "TN12 6PL",
    "wof:placetype": "postalcode"
  },
  "geometry": {"coordinates":[0.41855,51.190645],"type":"Point"}
}
