{
  "type": "Feature",
  "properties": {
    "iso:country":"GB",
    "wof:name":"NW4 1QA",
    "wof:placetype":"postalcode"
},
  "geometry": {"coordinates":[-0.22192983813556,51.59010097825976],"type":"Point"}
}