{
  "type": "Feature",
  "properties": {
    "iso:country":"GB",
    "wof:name":"SL6 8JU",
    "wof:placetype":"postalcode"
},
  "geometry": {"coordinates":[-0.70122767919035,51.53947310866224],"type":"Point"}
}