{
  "type": "Feature",
  "properties": {
    "date:inception_lower": "1997-12-01",
    "date:inception_upper": "1997-12-01",
    "iso:country": "GB",
    "wof:name": "WF13 3JL",
    "wof:placetype": "postalcode"
  },
  "geometry": {"coordinates":[-1.65778,53.678532],"type":"Point"}
}
