{
  "type": "Feature",
  "properties": {
    "iso:country":"GB",
    "wof:name":"WF13 3JL",
    "wof:placetype":"postalcode"
},
  "geometry": {"coordinates":[-1.65777974795008,53.67853172223394],"type":"Point"}
}