{
  "type": "Feature",
  "properties": {
    "iso:country": "GB",
    "wof:name": "WF13 3JL",
    "wof:placetype": "postalcode"
  },
  "geometry": {"coordinates":[-1.65778,53.678532],"type":"Point"}
}
