{
  "type": "Feature",
  "properties": {
    "date:inception_lower": "1999-12-01",
    "date:inception_upper": "1999-12-01",
    "iso:country": "GB",
    "wof:name": "NP20 1JS",
    "wof:placetype": "postalcode"
  },
  "geometry": {"coordinates":[-2.997723,51.584281],"type":"Point"}
}
