{
  "type": "Feature",
  "properties": {
    "date:inception_lower":"1995-07-01",
    "date:inception_upper":"1995-07-31",
    "iso:country":"GB",
    "wof:name":"CF82 8HJ",
    "wof:placetype":"postalcode"
},
  "geometry": {"coordinates":[-3.239763,51.666341],"type":"Point"}
}