{
  "type": "Feature",
  "properties": {
    "iso:country":"GB",
    "wof:name":"PR5 6YS",
    "wof:placetype":"postalcode"
},
  "geometry": {"coordinates":[-2.64176201153591,53.72642001088249],"type":"Point"}
}