{
  "type": "Feature",
  "properties": {
    "iso:country": "GB",
    "wof:name": "PR5 6YS",
    "wof:placetype": "postalcode"
  },
  "geometry": {"coordinates":[-2.641762,53.72642],"type":"Point"}
}
