{
  "type": "Feature",
  "properties": {
    "date:inception_lower":"2006-10-01",
    "date:inception_upper":"2006-10-31",
    "iso:country":"GB",
    "wof:name":"KA22 8AB",
    "wof:placetype":"postalcode"
},
  "geometry": {"coordinates":[-4.816074,55.642548],"type":"Point"}
}