{
  "type": "Feature",
  "properties": {
    "iso:country":"GB",
    "wof:name":"SE27 0BS",
    "wof:placetype":"postalcode"
},
  "geometry": {"coordinates":[-0.10888346379224,51.43513686403781],"type":"Point"}
}