{
  "type": "Feature",
  "properties": {
    "iso:country":"GB",
    "wof:name":"OL4 5QJ",
    "wof:placetype":"postalcode"
},
  "geometry": {"coordinates":[-2.07118386222487,53.53138455344553],"type":"Point"}
}