{
  "type": "Feature",
  "properties": {
    "iso:country":"GB",
    "wof:name":"N11 2NN",
    "wof:placetype":"postalcode"
},
  "geometry": {"coordinates":[-0.13054620962922,51.60772683876836],"type":"Point"}
}