{
  "type": "Feature",
  "properties": {
    "iso:country": "GB",
    "wof:name": "PL10 1JP",
    "wof:placetype": "postalcode"
  },
  "geometry": {"coordinates":[-4.251753,50.346899],"type":"Point"}
}
