{
  "type": "Feature",
  "properties": {
    "iso:country":"GB",
    "wof:name":"CV6 4BP",
    "wof:placetype":"postalcode"
},
  "geometry": {"coordinates":[-1.51388138606599,52.43734063622183],"type":"Point"}
}