{
  "type": "Feature",
  "properties": {
    "date:inception_lower": "1990-02-01",
    "date:inception_upper": "1990-02-01",
    "iso:country": "GB",
    "wof:name": "GL20 5UR",
    "wof:placetype": "postalcode"
  },
  "geometry": {"coordinates":[-2.158723,51.993407],"type":"Point"}
}
