{
  "type": "Feature",
  "properties": {
    "date:inception_lower": "1980-01-01",
    "date:inception_upper": "1980-01-01",
    "iso:country": "GB",
    "wof:name": "BB7 2HZ",
    "wof:placetype": "postalcode"
  },
  "geometry": {"coordinates":[-2.393486,53.878434],"type":"Point"}
}
