{
  "type": "Feature",
  "properties": {
    "iso:country": "GB",
    "wof:name": "HP14 3EW",
    "wof:placetype": "postalcode"
  },
  "geometry": {"coordinates":[-0.874763,51.658458],"type":"Point"}
}
