{
  "type": "Feature",
  "properties": {
    "iso:country":"GB",
    "wof:name":"PE28 3ED",
    "wof:placetype":"postalcode"
},
  "geometry": {"coordinates":[0.00505421163103,52.38338921573606],"type":"Point"}
}