{
  "type": "Feature",
  "properties": {
    "iso:country": "GB",
    "wof:name": "PE28 3ED",
    "wof:placetype": "postalcode"
  },
  "geometry": {"coordinates":[0.005054,52.383389],"type":"Point"}
}
