{
  "type": "Feature",
  "properties": {
    "iso:country": "GB",
    "wof:name": "WR1 2BQ",
    "wof:placetype": "postalcode"
  },
  "geometry": {"coordinates":[-2.218636,52.186071],"type":"Point"}
}
