{
  "type": "Feature",
  "properties": {
    "iso:country":"GB",
    "wof:name":"E12 5NN",
    "wof:placetype":"postalcode"
},
  "geometry": {"coordinates":[0.06425487904936,51.55146869411164],"type":"Point"}
}