{
  "type": "Feature",
  "properties": {
    "iso:country": "GB",
    "wof:name": "RG6 5RY",
    "wof:placetype": "postalcode"
  },
  "geometry": {"coordinates":[-0.928387,51.432049],"type":"Point"}
}
