{
  "type": "Feature",
  "properties": {
    "iso:country":"GB",
    "wof:name":"RG6 5RY",
    "wof:placetype":"postalcode"
},
  "geometry": {"coordinates":[-0.92838675616688,51.43204898486596],"type":"Point"}
}