{
  "type": "Feature",
  "properties": {
    "iso:country":"GB",
    "wof:name":"TW8 0PB",
    "wof:placetype":"postalcode"
},
  "geometry": {"coordinates":[-0.30577481979591,51.48758819464147],"type":"Point"}
}