{
  "type": "Feature",
  "properties": {
    "iso:country": "GB",
    "wof:name": "TW8 0PB",
    "wof:placetype": "postalcode"
  },
  "geometry": {"coordinates":[-0.305775,51.487588],"type":"Point"}
}
