{
  "type": "Feature",
  "properties": {
    "date:inception_lower": "1997-06-01",
    "date:inception_upper": "1997-06-01",
    "iso:country": "GB",
    "wof:name": "SA6 5BP",
    "wof:placetype": "postalcode"
  },
  "geometry": {"coordinates":[-3.909315,51.683562],"type":"Point"}
}
