{
  "type": "Feature",
  "properties": {
    "date:inception_lower":"1997-06-01",
    "date:inception_upper":"1997-06-30",
    "iso:country":"GB",
    "wof:name":"SA6 5BP",
    "wof:placetype":"postalcode"
},
  "geometry": {"coordinates":[-3.909267,51.68354],"type":"Point"}
}