{
  "type": "Feature",
  "properties": {
    "iso:country":"GB",
    "wof:name":"LN13 0JQ",
    "wof:placetype":"postalcode"
},
  "geometry": {"coordinates":[0.1965911125409,53.29873989681188],"type":"Point"}
}