{
  "type": "Feature",
  "properties": {
    "iso:country": "GB",
    "wof:name": "LN13 0JQ",
    "wof:placetype": "postalcode"
  },
  "geometry": {"coordinates":[0.195826,53.299059],"type":"Point"}
}
