{
  "type": "Feature",
  "properties": {
    "date:inception_lower":"1980-01-01",
    "date:inception_upper":"1980-01-31",
    "iso:country":"GB",
    "wof:name":"LN13 0JQ",
    "wof:placetype":"postalcode"
},
  "geometry": {"coordinates":[0.195826,53.299059],"type":"Point"}
}