{
  "type": "Feature",
  "properties": {
    "date:inception_lower": "1980-01-01",
    "date:inception_upper": "1980-01-01",
    "iso:country": "GB",
    "wof:name": "CW4 8NR",
    "wof:placetype": "postalcode"
  },
  "geometry": {"coordinates":[-2.36331,53.227244],"type":"Point"}
}
