{
  "type": "Feature",
  "properties": {
    "iso:country":"GB",
    "wof:name":"B65 9LH",
    "wof:placetype":"postalcode"
},
  "geometry": {"coordinates":[-2.03944144613964,52.49102221665942],"type":"Point"}
}