{
  "type": "Feature",
  "properties": {
    "iso:country": "GB",
    "wof:name": "LL75 8UT",
    "wof:placetype": "postalcode"
  },
  "geometry": {"coordinates":[-4.218979,53.280235],"type":"Point"}
}
