{
  "type": "Feature",
  "properties": {
    "iso:country":"GB",
    "wof:name":"CO12 4NU",
    "wof:placetype":"postalcode"
},
  "geometry": {"coordinates":[1.25828824514928,51.93753133390192],"type":"Point"}
}