{
  "type": "Feature",
  "properties": {
    "iso:country":"GB",
    "wof:name":"SR4 8QG",
    "wof:placetype":"postalcode"
},
  "geometry": {"coordinates":[-1.41718354125287,54.89513099433113],"type":"Point"}
}