{
  "type": "Feature",
  "properties": {
    "date:inception_lower": "1980-01-01",
    "date:inception_upper": "1980-01-01",
    "iso:country": "GB",
    "wof:name": "CA25 5SG",
    "wof:placetype": "postalcode"
  },
  "geometry": {"coordinates":[-3.530218,54.529125],"type":"Point"}
}
