{
  "type": "Feature",
  "properties": {
    "iso:country": "GB",
    "wof:name": "DL1 2DF",
    "wof:placetype": "postalcode"
  },
  "geometry": {"coordinates":[-1.521216,54.537601],"type":"Point"}
}
