{
  "type": "Feature",
  "properties": {
    "iso:country":"GB",
    "wof:name":"NG23 7LL",
    "wof:placetype":"postalcode"
},
  "geometry": {"coordinates":[-0.76722431202796,53.14163500954403],"type":"Point"}
}