{
  "type": "Feature",
  "properties": {
    "iso:country":"GB",
    "wof:name":"BH21 6QY",
    "wof:placetype":"postalcode"
},
  "geometry": {"coordinates":[-1.87724996480008,50.84828071712416],"type":"Point"}
}