{
  "type": "Feature",
  "properties": {
    "date:inception_lower": "1994-05-01",
    "date:inception_upper": "1994-05-01",
    "iso:country": "GB",
    "wof:name": "NN29 7TQ",
    "wof:placetype": "postalcode"
  },
  "geometry": {"coordinates":[-0.70751,52.274543],"type":"Point"}
}
