{
  "type": "Feature",
  "properties": {
    "iso:country":"GB",
    "wof:name":"IP14 5PD",
    "wof:placetype":"postalcode"
},
  "geometry": {"coordinates":[1.10222614045275,52.25953665238168],"type":"Point"}
}