{
  "type": "Feature",
  "properties": {
    "iso:country":"GB",
    "wof:name":"PE27 3DF",
    "wof:placetype":"postalcode"
},
  "geometry": {"coordinates":[-0.07992102807718,52.34445589129709],"type":"Point"}
}