{
  "type": "Feature",
  "properties": {
    "iso:country":"GB",
    "wof:name":"SN2 2LF",
    "wof:placetype":"postalcode"
},
  "geometry": {"coordinates":[-1.80313767682656,51.57957297781307],"type":"Point"}
}