{
  "type": "Feature",
  "properties": {
    "iso:country":"GB",
    "wof:name":"G77 5PE",
    "wof:placetype":"postalcode"
},
  "geometry": {"coordinates":[-4.31641083441982,55.78066704110754],"type":"Point"}
}