{
  "type": "Feature",
  "properties": {
    "date:inception_lower": "2009-06-01",
    "date:inception_upper": "2009-06-01",
    "iso:country": "GB",
    "wof:name": "MK18 4FG",
    "wof:placetype": "postalcode"
  },
  "geometry": {"coordinates":[-1.015346,51.981452],"type":"Point"}
}
