{
  "type": "Feature",
  "properties": {
    "iso:country":"GB",
    "wof:name":"MK18 4FG",
    "wof:placetype":"postalcode"
},
  "geometry": {"coordinates":[-1.01534574459675,51.98145184068508],"type":"Point"}
}