{
  "type": "Feature",
  "properties": {
    "iso:country": "GB",
    "wof:name": "MK18 4FG",
    "wof:placetype": "postalcode"
  },
  "geometry": {"coordinates":[-1.015346,51.981452],"type":"Point"}
}
