{
  "type": "Feature",
  "properties": {
    "iso:country":"GB",
    "wof:name":"NR8 5HP",
    "wof:placetype":"postalcode"
},
  "geometry": {"coordinates":[1.17741110214982,52.66325230667114],"type":"Point"}
}