{
  "type": "Feature",
  "properties": {
    "iso:country":"GB",
    "wof:name":"SA6 6BS",
    "wof:placetype":"postalcode"
},
  "geometry": {"coordinates":[-3.93946061781772,51.67107591169764],"type":"Point"}
}