{
  "type": "Feature",
  "properties": {
    "date:inception_lower":"1980-01-01",
    "date:inception_upper":"1980-01-31",
    "iso:country":"GB",
    "wof:name":"SL0 0PZ",
    "wof:placetype":"postalcode"
},
  "geometry": {"coordinates":[-0.523769,51.542941],"type":"Point"}
}