{
  "type": "Feature",
  "properties": {
    "iso:country":"GB",
    "wof:name":"SL0 0PZ",
    "wof:placetype":"postalcode"
},
  "geometry": {"coordinates":[-0.52376923181739,51.54294076235521],"type":"Point"}
}