{
  "type": "Feature",
  "properties": {
    "iso:country": "GB",
    "wof:name": "SL0 0PZ",
    "wof:placetype": "postalcode"
  },
  "geometry": {"coordinates":[-0.523769,51.542941],"type":"Point"}
}
