{
  "type": "Feature",
  "properties": {
    "date:inception_lower":"2004-03-01",
    "date:inception_upper":"2004-03-31",
    "iso:country":"GB",
    "wof:name":"SE1 2JT",
    "wof:placetype":"postalcode"
},
  "geometry": {"coordinates":[-0.080462,51.505258],"type":"Point"}
}