{
  "type": "Feature",
  "properties": {
    "iso:country":"GB",
    "wof:name":"ST4 6AX",
    "wof:placetype":"postalcode"
},
  "geometry": {"coordinates":[-2.20974258048483,53.00943233745836],"type":"Point"}
}