{
  "type": "Feature",
  "properties": {
    "date:inception_lower": "1980-01-01",
    "date:inception_upper": "1980-01-01",
    "iso:country": "GB",
    "wof:name": "BN2 5PL",
    "wof:placetype": "postalcode"
  },
  "geometry": {"coordinates":[-0.102375,50.826821],"type":"Point"}
}
