{
  "type": "Feature",
  "properties": {
    "iso:country":"GB",
    "wof:name":"E14 3AG",
    "wof:placetype":"postalcode"
},
  "geometry": {"coordinates":[-0.01862692615063,51.48806082485081],"type":"Point"}
}