{
  "type": "Feature",
  "properties": {
    "date:inception_lower":"1991-01-01",
    "date:inception_upper":"1991-01-31",
    "iso:country":"GB",
    "wof:name":"E14 3AG",
    "wof:placetype":"postalcode"
},
  "geometry": {"coordinates":[-0.018627,51.488061],"type":"Point"}
}