{
  "type": "Feature",
  "properties": {
    "date:inception_lower": "1980-01-01",
    "date:inception_upper": "1980-01-01",
    "iso:country": "GB",
    "wof:name": "HD8 0LL",
    "wof:placetype": "postalcode"
  },
  "geometry": {"coordinates":[-1.734478,53.634324],"type":"Point"}
}
