{
  "type": "Feature",
  "properties": {
    "iso:country": "GB",
    "wof:name": "HD8 0LL",
    "wof:placetype": "postalcode"
  },
  "geometry": {"coordinates":[-1.734478,53.634324],"type":"Point"}
}
