{
  "type": "Feature",
  "properties": {
    "iso:country": "GB",
    "wof:name": "EX16 9JL",
    "wof:placetype": "postalcode"
  },
  "geometry": {"coordinates":[-3.609338,51.025693],"type":"Point"}
}
