{
  "type": "Feature",
  "properties": {
    "iso:country":"GB",
    "wof:name":"CO4 5TH",
    "wof:placetype":"postalcode"
},
  "geometry": {"coordinates":[0.89527803058332,51.95861855345738],"type":"Point"}
}