{
  "type": "Feature",
  "properties": {
    "date:inception_lower": "1980-01-01",
    "date:inception_upper": "1980-01-01",
    "iso:country": "GB",
    "wof:name": "RH10 3AU",
    "wof:placetype": "postalcode"
  },
  "geometry": {"coordinates":[-0.155196,51.12234],"type":"Point"}
}
