{
  "type": "Feature",
  "properties": {
    "iso:country":"GB",
    "wof:name":"RH10 3AU",
    "wof:placetype":"postalcode"
},
  "geometry": {"coordinates":[-0.15519580273436,51.12234044288599],"type":"Point"}
}