{
  "type": "Feature",
  "properties": {
    "iso:country":"GB",
    "wof:name":"HR1 4PT",
    "wof:placetype":"postalcode"
},
  "geometry": {"coordinates":[-2.5881019495854,52.00078305673652],"type":"Point"}
}