{
  "type": "Feature",
  "properties": {
    "iso:country":"GB",
    "wof:name":"WF10 5EG",
    "wof:placetype":"postalcode"
},
  "geometry": {"coordinates":[-1.36290659033475,53.72044358645473],"type":"Point"}
}