{
  "type": "Feature",
  "properties": {
    "date:inception_lower": "2001-12-01",
    "date:inception_upper": "2001-12-01",
    "iso:country": "GB",
    "wof:name": "SL7 3DX",
    "wof:placetype": "postalcode"
  },
  "geometry": {"coordinates":[-0.779349,51.575677],"type":"Point"}
}
