{
  "type": "Feature",
  "properties": {
    "iso:country":"GB",
    "wof:name":"SL7 3DX",
    "wof:placetype":"postalcode"
},
  "geometry": {"coordinates":[-0.77934940479697,51.57567664559119],"type":"Point"}
}