{
  "type": "Feature",
  "properties": {
    "iso:country":"GB",
    "wof:name":"L13 5XR",
    "wof:placetype":"postalcode"
},
  "geometry": {"coordinates":[-2.91177039569055,53.41539722990509],"type":"Point"}
}