{
  "type": "Feature",
  "properties": {
    "iso:country":"GB",
    "wof:name":"LN2 2QW",
    "wof:placetype":"postalcode"
},
  "geometry": {"coordinates":[-0.45038357684962,53.26678421765503],"type":"Point"}
}