{
  "type": "Feature",
  "properties": {
    "date:inception_lower": "1983-07-01",
    "date:inception_upper": "1983-07-01",
    "iso:country": "GB",
    "wof:name": "BN16 2PQ",
    "wof:placetype": "postalcode"
  },
  "geometry": {"coordinates":[-0.514899,50.810021],"type":"Point"}
}
