{
  "type": "Feature",
  "properties": {
    "iso:country": "GB",
    "wof:name": "WA10 5BH",
    "wof:placetype": "postalcode"
  },
  "geometry": {"coordinates":[-2.784004,53.454731],"type":"Point"}
}
