{
  "type": "Feature",
  "properties": {
    "date:inception_lower": "1980-01-01",
    "date:inception_upper": "1980-01-01",
    "iso:country": "GB",
    "wof:name": "WA10 5BH",
    "wof:placetype": "postalcode"
  },
  "geometry": {"coordinates":[-2.784004,53.454731],"type":"Point"}
}
