{
  "type": "Feature",
  "properties": {
    "iso:country":"GB",
    "wof:name":"CA1 2TS",
    "wof:placetype":"postalcode"
},
  "geometry": {"coordinates":[-2.90717147247751,54.88928374895067],"type":"Point"}
}