{
  "type": "Feature",
  "properties": {
    "iso:country":"GB",
    "wof:name":"TR7 2LF",
    "wof:placetype":"postalcode"
},
  "geometry": {"coordinates":[-5.07300541676407,50.4063658178279],"type":"Point"}
}