{
  "type": "Feature",
  "properties": {
    "iso:country":"GB",
    "wof:name":"BS32 8FD",
    "wof:placetype":"postalcode"
},
  "geometry": {"coordinates":[-2.55082427885321,51.53413393520348],"type":"Point"}
}