{
  "type": "Feature",
  "properties": {
    "date:inception_lower": "2009-02-01",
    "date:inception_upper": "2009-02-01",
    "iso:country": "GB",
    "wof:name": "BS32 8FD",
    "wof:placetype": "postalcode"
  },
  "geometry": {"coordinates":[-2.550824,51.534134],"type":"Point"}
}
