{
  "type": "Feature",
  "properties": {
    "date:inception_lower": "1980-01-01",
    "date:inception_upper": "1980-01-01",
    "iso:country": "GB",
    "wof:name": "PE32 2NU",
    "wof:placetype": "postalcode"
  },
  "geometry": {"coordinates":[0.795805,52.720662],"type":"Point"}
}
