{
  "type": "Feature",
  "properties": {
    "iso:country":"GB",
    "wof:name":"LN4 4JJ",
    "wof:placetype":"postalcode"
},
  "geometry": {"coordinates":[-0.22159119042521,53.08849069679096],"type":"Point"}
}