{
  "type": "Feature",
  "properties": {
    "iso:country": "GB",
    "wof:name": "LN4 4JJ",
    "wof:placetype": "postalcode"
  },
  "geometry": {"coordinates":[-0.221591,53.088491],"type":"Point"}
}
