{
  "type": "Feature",
  "properties": {
    "iso:country":"GB",
    "wof:name":"YO32 3JP",
    "wof:placetype":"postalcode"
},
  "geometry": {"coordinates":[-1.0764496029293,54.01719382078684],"type":"Point"}
}