{
  "type": "Feature",
  "properties": {
    "date:inception_lower": "1998-06-01",
    "date:inception_upper": "1998-06-01",
    "iso:country": "GB",
    "wof:name": "YO32 3JP",
    "wof:placetype": "postalcode"
  },
  "geometry": {"coordinates":[-1.076121,54.017271],"type":"Point"}
}
