{
  "type": "Feature",
  "properties": {
    "date:inception_lower": "1980-01-01",
    "date:inception_upper": "1980-01-01",
    "iso:country": "GB",
    "wof:name": "CT10 2PR",
    "wof:placetype": "postalcode"
  },
  "geometry": {"coordinates":[1.395276,51.362734],"type":"Point"}
}
