{
  "type": "Feature",
  "properties": {
    "iso:country": "GB",
    "wof:name": "GU9 9JT",
    "wof:placetype": "postalcode"
  },
  "geometry": {"coordinates":[-0.765758,51.228268],"type":"Point"}
}
