{
  "type": "Feature",
  "properties": {
    "iso:country":"GB",
    "wof:name":"GU9 9JT",
    "wof:placetype":"postalcode"
},
  "geometry": {"coordinates":[-0.76577560076951,51.22826974868086],"type":"Point"}
}