{
  "type": "Feature",
  "properties": {
    "date:inception_lower": "1997-12-01",
    "date:inception_upper": "1997-12-01",
    "iso:country": "GB",
    "wof:name": "DN14 0FB",
    "wof:placetype": "postalcode"
  },
  "geometry": {"coordinates":[-1.05809,53.669709],"type":"Point"}
}
