{
  "type": "Feature",
  "properties": {
    "iso:country":"GB",
    "wof:name":"DN14 0FB",
    "wof:placetype":"postalcode"
},
  "geometry": {"coordinates":[-1.05808999241433,53.6697093174589],"type":"Point"}
}