{
  "type": "Feature",
  "properties": {
    "date:inception_lower": "1980-01-01",
    "date:inception_upper": "1980-01-01",
    "iso:country": "GB",
    "wof:name": "CF45 4AN",
    "wof:placetype": "postalcode"
  },
  "geometry": {"coordinates":[-3.378775,51.686686],"type":"Point"}
}
