{
  "type": "Feature",
  "properties": {
    "iso:country":"GB",
    "wof:name":"CF45 4AN",
    "wof:placetype":"postalcode"
},
  "geometry": {"coordinates":[-3.37877490614495,51.68668638765526],"type":"Point"}
}