{
  "type": "Feature",
  "properties": {
    "iso:country":"GB",
    "wof:name":"TQ5 9HG",
    "wof:placetype":"postalcode"
},
  "geometry": {"coordinates":[-3.51377667795339,50.39107202152832],"type":"Point"}
}