{
  "type": "Feature",
  "properties": {
    "iso:country": "GB",
    "wof:name": "PR1 0PS",
    "wof:placetype": "postalcode"
  },
  "geometry": {"coordinates":[-2.7357,53.739407],"type":"Point"}
}
