{
  "type": "Feature",
  "properties": {
    "date:inception_lower": "1981-06-01",
    "date:inception_upper": "1981-06-01",
    "iso:country": "GB",
    "wof:name": "PR1 0PS",
    "wof:placetype": "postalcode"
  },
  "geometry": {"coordinates":[-2.7357,53.739407],"type":"Point"}
}
