{
  "type": "Feature",
  "properties": {
    "iso:country":"GB",
    "wof:name":"HA0 1DD",
    "wof:placetype":"postalcode"
},
  "geometry": {"coordinates":[-0.30618859631749,51.53548730907752],"type":"Point"}
}