{
  "type": "Feature",
  "properties": {
    "iso:country": "GB",
    "wof:name": "HA0 1DD",
    "wof:placetype": "postalcode"
  },
  "geometry": {"coordinates":[-0.306189,51.535487],"type":"Point"}
}
