{
  "type": "Feature",
  "properties": {
    "iso:country":"GB",
    "wof:name":"BA9 9RF",
    "wof:placetype":"postalcode"
},
  "geometry": {"coordinates":[-2.40072529397427,51.05466918644258],"type":"Point"}
}