{
  "type": "Feature",
  "properties": {
    "iso:country":"GB",
    "wof:name":"KW14 7GY",
    "wof:placetype":"postalcode"
},
  "geometry": {"coordinates":[-3.53983709752377,58.58716328952793],"type":"Point"}
}