{
  "type": "Feature",
  "properties": {
    "date:inception_lower": "2009-04-01",
    "date:inception_upper": "2009-04-01",
    "iso:country": "GB",
    "wof:name": "KW14 7GY",
    "wof:placetype": "postalcode"
  },
  "geometry": {"coordinates":[-3.539837,58.587163],"type":"Point"}
}
