{
  "type": "Feature",
  "properties": {
    "iso:country":"GB",
    "wof:name":"PE28 4QJ",
    "wof:placetype":"postalcode"
},
  "geometry": {"coordinates":[-0.22477914629389,52.31437071745005],"type":"Point"}
}