{
  "type": "Feature",
  "properties": {
    "date:inception_lower": "2015-11-01",
    "date:inception_upper": "2015-11-01",
    "iso:country": "GB",
    "wof:name": "PE28 4QJ",
    "wof:placetype": "postalcode"
  },
  "geometry": {"coordinates":[-0.224779,52.314371],"type":"Point"}
}
