{
  "type": "Feature",
  "properties": {
    "iso:country":"GB",
    "wof:name":"HU9 1JJ",
    "wof:placetype":"postalcode"
},
  "geometry": {"coordinates":[-0.31695031695042,53.74929512264467],"type":"Point"}
}