{
  "type": "Feature",
  "properties": {
    "iso:country":"GB",
    "wof:name":"DN14 9DR",
    "wof:placetype":"postalcode"
},
  "geometry": {"coordinates":[-1.02608663665698,53.69028877856183],"type":"Point"}
}