{
  "type": "Feature",
  "properties": {
    "date:inception_lower": "1980-01-01",
    "date:inception_upper": "1980-01-01",
    "iso:country": "GB",
    "wof:name": "DN14 9DR",
    "wof:placetype": "postalcode"
  },
  "geometry": {"coordinates":[-1.026087,53.690289],"type":"Point"}
}
