{
  "type": "Feature",
  "properties": {
    "iso:country": "GB",
    "wof:name": "SE19 2NT",
    "wof:placetype": "postalcode"
  },
  "geometry": {"coordinates":[-0.08482,51.413308],"type":"Point"}
}
