{
  "type": "Feature",
  "properties": {
    "iso:country":"GB",
    "wof:name":"SE19 2NT",
    "wof:placetype":"postalcode"
},
  "geometry": {"coordinates":[-0.08481962506235,51.41330756022482],"type":"Point"}
}