{
  "type": "Feature",
  "properties": {
    "iso:country": "GB",
    "wof:name": "SS6 7XU",
    "wof:placetype": "postalcode"
  },
  "geometry": {"coordinates":[0.628507,51.570962],"type":"Point"}
}
