{
  "type": "Feature",
  "properties": {
    "iso:country":"GB",
    "wof:name":"SS6 7XU",
    "wof:placetype":"postalcode"
},
  "geometry": {"coordinates":[0.62842187965194,51.57096767098534],"type":"Point"}
}