{
  "type": "Feature",
  "properties": {
    "iso:country":"GB",
    "wof:name":"TA2 7HQ",
    "wof:placetype":"postalcode"
},
  "geometry": {"coordinates":[-3.08916889910333,51.02944406561497],"type":"Point"}
}