{
  "type": "Feature",
  "properties": {
    "iso:country": "GB",
    "wof:name": "G20 8BB",
    "wof:placetype": "postalcode"
  },
  "geometry": {"coordinates":[-4.28329,55.883152],"type":"Point"}
}
