{
  "type": "Feature",
  "properties": {
    "iso:country":"GB",
    "wof:name":"DE55 6AL",
    "wof:placetype":"postalcode"
},
  "geometry": {"coordinates":[-1.43749038881778,53.12081534547427],"type":"Point"}
}