{
  "type": "Feature",
  "properties": {
    "iso:country": "GB",
    "wof:name": "DE55 6AL",
    "wof:placetype": "postalcode"
  },
  "geometry": {"coordinates":[-1.43749,53.120815],"type":"Point"}
}
