{
  "type": "Feature",
  "properties": {
    "iso:country":"GB",
    "wof:name":"TQ12 4RR",
    "wof:placetype":"postalcode"
},
  "geometry": {"coordinates":[-3.54965788179686,50.5378170966062],"type":"Point"}
}