{
  "type": "Feature",
  "properties": {
    "date:inception_lower": "1995-07-01",
    "date:inception_upper": "1995-07-01",
    "iso:country": "GB",
    "wof:name": "CT18 7FD",
    "wof:placetype": "postalcode"
  },
  "geometry": {"coordinates":[1.157982,51.115084],"type":"Point"}
}
