{
  "type": "Feature",
  "properties": {
    "iso:country": "GB",
    "wof:name": "LL48 6RD",
    "wof:placetype": "postalcode"
  },
  "geometry": {"coordinates":[-4.065274,52.93533],"type":"Point"}
}
