{
  "type": "Feature",
  "properties": {
    "date:inception_lower": "1980-01-01",
    "date:inception_upper": "1980-01-01",
    "iso:country": "GB",
    "wof:name": "LL48 6RD",
    "wof:placetype": "postalcode"
  },
  "geometry": {"coordinates":[-4.065274,52.93533],"type":"Point"}
}
