{
  "type": "Feature",
  "properties": {
    "iso:country":"GB",
    "wof:name":"RH10 4PL",
    "wof:placetype":"postalcode"
},
  "geometry": {"coordinates":[-0.08356205604149,51.10191600443371],"type":"Point"}
}