{
  "type": "Feature",
  "properties": {
    "iso:country":"GB",
    "wof:name":"TN10 3RS",
    "wof:placetype":"postalcode"
},
  "geometry": {"coordinates":[0.28997683441761,51.22050160021789],"type":"Point"}
}