{
  "type": "Feature",
  "properties": {
    "iso:country":"GB",
    "wof:name":"LA7 7BJ",
    "wof:placetype":"postalcode"
},
  "geometry": {"coordinates":[-2.75808395663172,54.20238013473142],"type":"Point"}
}