{
  "type": "Feature",
  "properties": {
    "iso:country":"GB",
    "wof:name":"S36 1LL",
    "wof:placetype":"postalcode"
},
  "geometry": {"coordinates":[-1.61798344709969,53.4853239672529],"type":"Point"}
}