{
  "type": "Feature",
  "properties": {
    "iso:country": "GB",
    "wof:name": "S36 1LL",
    "wof:placetype": "postalcode"
  },
  "geometry": {"coordinates":[-1.617983,53.485324],"type":"Point"}
}
