{
  "type": "Feature",
  "properties": {
    "iso:country": "GB",
    "wof:name": "BN25 3HX",
    "wof:placetype": "postalcode"
  },
  "geometry": {"coordinates":[0.121325,50.780706],"type":"Point"}
}
