{
  "type": "Feature",
  "properties": {
    "iso:country": "GB",
    "wof:name": "RG19 8HR",
    "wof:placetype": "postalcode"
  },
  "geometry": {"coordinates":[-1.278466,51.369436],"type":"Point"}
}
