{
  "type": "Feature",
  "properties": {
    "iso:country":"GB",
    "wof:name":"RG19 8HR",
    "wof:placetype":"postalcode"
},
  "geometry": {"coordinates":[-1.27684911827596,51.3693814856016],"type":"Point"}
}