{
  "type": "Feature",
  "properties": {
    "iso:country": "GB",
    "wof:name": "TN18 4EP",
    "wof:placetype": "postalcode"
  },
  "geometry": {"coordinates":[0.510296,51.047085],"type":"Point"}
}
