{
  "type": "Feature",
  "properties": {
    "iso:country":"GB",
    "wof:name":"WA6 9JD",
    "wof:placetype":"postalcode"
},
  "geometry": {"coordinates":[-2.74257166114035,53.2410526169017],"type":"Point"}
}