{
  "type": "Feature",
  "properties": {
    "iso:country":"GB",
    "wof:name":"WF3 1DP",
    "wof:placetype":"postalcode"
},
  "geometry": {"coordinates":[-1.58299613682379,53.71354650838719],"type":"Point"}
}