{
  "type": "Feature",
  "properties": {
    "iso:country":"GB",
    "wof:name":"WF1 2AE",
    "wof:placetype":"postalcode"
},
  "geometry": {"coordinates":[-1.511379853252,53.69350198947631],"type":"Point"}
}