{
  "type": "Feature",
  "properties": {
    "iso:country":"GB",
    "wof:name":"TQ6 0RU",
    "wof:placetype":"postalcode"
},
  "geometry": {"coordinates":[-3.63102490784998,50.3119679916348],"type":"Point"}
}