{
  "type": "Feature",
  "properties": {
    "iso:country": "GB",
    "wof:name": "TQ6 0RU",
    "wof:placetype": "postalcode"
  },
  "geometry": {"coordinates":[-3.631025,50.311968],"type":"Point"}
}
