{
  "type": "Feature",
  "properties": {
    "date:inception_lower": "1980-01-01",
    "date:inception_upper": "1980-01-01",
    "iso:country": "GB",
    "wof:name": "TS16 0QR",
    "wof:placetype": "postalcode"
  },
  "geometry": {"coordinates":[-1.399664,54.494939],"type":"Point"}
}
