{
  "type": "Feature",
  "properties": {
    "iso:country": "GB",
    "wof:name": "TS16 0QR",
    "wof:placetype": "postalcode"
  },
  "geometry": {"coordinates":[-1.404278,54.495364],"type":"Point"}
}
