{
  "type": "Feature",
  "properties": {
    "iso:country": "GB",
    "wof:name": "CO11 2JW",
    "wof:placetype": "postalcode"
  },
  "geometry": {"coordinates":[1.053398,51.945097],"type":"Point"}
}
