{
  "type": "Feature",
  "properties": {
    "iso:country":"GB",
    "wof:name":"CO11 2JW",
    "wof:placetype":"postalcode"
},
  "geometry": {"coordinates":[1.0533982887914,51.94509690876102],"type":"Point"}
}