{
  "type": "Feature",
  "properties": {
    "iso:country":"GB",
    "wof:name":"DN22 6RU",
    "wof:placetype":"postalcode"
},
  "geometry": {"coordinates":[-0.93911126592782,53.32570878725544],"type":"Point"}
}