{
  "type": "Feature",
  "properties": {
    "iso:country": "GB",
    "wof:name": "S3 7LU",
    "wof:placetype": "postalcode"
  },
  "geometry": {"coordinates":[-1.480317,53.387935],"type":"Point"}
}
