{
  "type": "Feature",
  "properties": {
    "iso:country":"GB",
    "wof:name":"BR6 7RJ",
    "wof:placetype":"postalcode"
},
  "geometry": {"coordinates":[0.13081215357703,51.35741650145266],"type":"Point"}
}