{
  "type": "Feature",
  "properties": {
    "iso:country":"GB",
    "wof:name":"SA15 2RU",
    "wof:placetype":"postalcode"
},
  "geometry": {"coordinates":[-4.16324769219701,51.67672481477363],"type":"Point"}
}