{
  "type": "Feature",
  "properties": {
    "iso:country":"GB",
    "wof:name":"BN22 7HL",
    "wof:placetype":"postalcode"
},
  "geometry": {"coordinates":[0.29860649035843,50.77400002970522],"type":"Point"}
}