{
  "type": "Feature",
  "properties": {
    "date:inception_lower":"1980-01-01",
    "date:inception_upper":"1980-01-31",
    "iso:country":"GB",
    "wof:name":"LN1 3JN",
    "wof:placetype":"postalcode"
},
  "geometry": {"coordinates":[-0.543719,53.239562],"type":"Point"}
}