{
  "type": "Feature",
  "properties": {
    "iso:country": "GB",
    "wof:name": "LN1 3JN",
    "wof:placetype": "postalcode"
  },
  "geometry": {"coordinates":[-0.543719,53.239562],"type":"Point"}
}
