{
  "type": "Feature",
  "properties": {
    "iso:country":"GB",
    "wof:name":"LN1 3JN",
    "wof:placetype":"postalcode"
},
  "geometry": {"coordinates":[-0.54371901157244,53.2395624934986],"type":"Point"}
}