{
  "type": "Feature",
  "properties": {
    "date:inception_lower": "1982-03-01",
    "date:inception_upper": "1982-03-01",
    "iso:country": "GB",
    "wof:name": "OL9 9LE",
    "wof:placetype": "postalcode"
  },
  "geometry": {"coordinates":[-2.139325,53.543944],"type":"Point"}
}
