{
  "type": "Feature",
  "properties": {
    "iso:country":"GB",
    "wof:name":"OL9 9LE",
    "wof:placetype":"postalcode"
},
  "geometry": {"coordinates":[-2.13932458291066,53.54394407999344],"type":"Point"}
}