{
  "type": "Feature",
  "properties": {
    "date:inception_lower": "2010-07-01",
    "date:inception_upper": "2010-07-01",
    "iso:country": "GB",
    "wof:name": "SO31 7NJ",
    "wof:placetype": "postalcode"
  },
  "geometry": {"coordinates":[-1.281686,50.870074],"type":"Point"}
}
