{
  "type": "Feature",
  "properties": {
    "iso:country":"GB",
    "wof:name":"NG21 0JU",
    "wof:placetype":"postalcode"
},
  "geometry": {"coordinates":[-1.11210604101296,53.11850150227372],"type":"Point"}
}