{
  "type": "Feature",
  "properties": {
    "iso:country":"GB",
    "wof:name":"HG4 1DB",
    "wof:placetype":"postalcode"
},
  "geometry": {"coordinates":[-1.52368490114217,54.13586276936487],"type":"Point"}
}