{
  "type": "Feature",
  "properties": {
    "date:inception_lower":"1999-12-01",
    "date:inception_upper":"1999-12-31",
    "iso:country":"GB",
    "wof:name":"EX37 9YU",
    "wof:placetype":"postalcode"
},
  "geometry": {"coordinates":[-4.055789,51.079988],"type":"Point"}
}