{
  "type": "Feature",
  "properties": {
    "iso:country":"GB",
    "wof:name":"NE22 5BX",
    "wof:placetype":"postalcode"
},
  "geometry": {"coordinates":[-1.58837547942318,55.13249202729749],"type":"Point"}
}