{
  "type": "Feature",
  "properties": {
    "iso:country":"GB",
    "wof:name":"SA3 3DJ",
    "wof:placetype":"postalcode"
},
  "geometry": {"coordinates":[-4.04402569958228,51.58082397512292],"type":"Point"}
}