{
  "type": "Feature",
  "properties": {
    "iso:country":"GB",
    "wof:name":"EH15 2AJ",
    "wof:placetype":"postalcode"
},
  "geometry": {"coordinates":[-3.11306538344917,55.95169160571255],"type":"Point"}
}