{
  "type": "Feature",
  "properties": {
    "iso:country":"GB",
    "wof:name":"CT9 1LT",
    "wof:placetype":"postalcode"
},
  "geometry": {"coordinates":[1.38381636976793,51.38498732548093],"type":"Point"}
}