{
  "type": "Feature",
  "properties": {
    "iso:country": "GB",
    "wof:name": "MK15 9DD",
    "wof:placetype": "postalcode"
  },
  "geometry": {"coordinates":[-0.737949,52.059125],"type":"Point"}
}
