{
  "type": "Feature",
  "properties": {
    "iso:country": "GB",
    "wof:name": "NG32 3RA",
    "wof:placetype": "postalcode"
  },
  "geometry": {"coordinates":[-0.534358,52.988983],"type":"Point"}
}
