{
  "type": "Feature",
  "properties": {
    "date:inception_lower": "1980-01-01",
    "date:inception_upper": "1980-01-01",
    "iso:country": "GB",
    "wof:name": "SA41 3QQ",
    "wof:placetype": "postalcode"
  },
  "geometry": {"coordinates":[-4.647074,51.97317],"type":"Point"}
}
