{
  "type": "Feature",
  "properties": {
    "iso:country":"GB",
    "wof:name":"SA41 3QQ",
    "wof:placetype":"postalcode"
},
  "geometry": {"coordinates":[-4.6469907807898,51.97315866793075],"type":"Point"}
}