{
  "type": "Feature",
  "properties": {
    "iso:country":"GB",
    "wof:name":"WS7 9EE",
    "wof:placetype":"postalcode"
},
  "geometry": {"coordinates":[-1.90466012192461,52.67861681505656],"type":"Point"}
}