{
  "type": "Feature",
  "properties": {
    "date:inception_lower": "2001-12-01",
    "date:inception_upper": "2001-12-01",
    "iso:country": "GB",
    "wof:name": "NP23 6HB",
    "wof:placetype": "postalcode"
  },
  "geometry": {"coordinates":[-3.21382,51.78246],"type":"Point"}
}
