{
  "type": "Feature",
  "properties": {
    "iso:country":"GB",
    "wof:name":"OX39 4EG",
    "wof:placetype":"postalcode"
},
  "geometry": {"coordinates":[-0.90714344913439,51.70753923295445],"type":"Point"}
}