{
  "type": "Feature",
  "properties": {
    "date:inception_lower": "2000-10-01",
    "date:inception_upper": "2000-10-01",
    "iso:country": "GB",
    "wof:name": "OX39 4EG",
    "wof:placetype": "postalcode"
  },
  "geometry": {"coordinates":[-0.907143,51.707539],"type":"Point"}
}
