{
  "type": "Feature",
  "properties": {
    "iso:country": "GB",
    "wof:name": "OX39 4EG",
    "wof:placetype": "postalcode"
  },
  "geometry": {"coordinates":[-0.907143,51.707539],"type":"Point"}
}
