{
  "type": "Feature",
  "properties": {
    "iso:country":"GB",
    "wof:name":"NN6 9WD",
    "wof:placetype":"postalcode"
},
  "geometry": {"coordinates":[-0.90148825444516,52.3203179297553],"type":"Point"}
}