{
  "type": "Feature",
  "properties": {
    "iso:country": "GB",
    "wof:name": "NN6 9WD",
    "wof:placetype": "postalcode"
  },
  "geometry": {"coordinates":[-0.901474,52.320333],"type":"Point"}
}
