{
  "type": "Feature",
  "properties": {
    "date:inception_lower": "2014-05-01",
    "date:inception_upper": "2014-05-01",
    "iso:country": "GB",
    "wof:name": "NN6 9WD",
    "wof:placetype": "postalcode"
  },
  "geometry": {"coordinates":[-0.901474,52.320333],"type":"Point"}
}
