{
  "type": "Feature",
  "properties": {
    "iso:country":"GB",
    "wof:name":"TR3 7NJ",
    "wof:placetype":"postalcode"
},
  "geometry": {"coordinates":[-5.11186312798073,50.21578246579843],"type":"Point"}
}