{
  "type": "Feature",
  "properties": {
    "iso:country": "GB",
    "wof:name": "TR3 7NJ",
    "wof:placetype": "postalcode"
  },
  "geometry": {"coordinates":[-5.11191,50.215771],"type":"Point"}
}
