{
  "type": "Feature",
  "properties": {
    "iso:country": "GB",
    "wof:name": "EX8 2BS",
    "wof:placetype": "postalcode"
  },
  "geometry": {"coordinates":[-3.403238,50.616415],"type":"Point"}
}
