{
  "type": "Feature",
  "properties": {
    "iso:country":"GB",
    "wof:name":"EX8 2BS",
    "wof:placetype":"postalcode"
},
  "geometry": {"coordinates":[-3.40323810561372,50.61641503300124],"type":"Point"}
}