{
  "type": "Feature",
  "properties": {
    "date:inception_lower": "2023-07-01",
    "date:inception_upper": "2023-07-01",
    "iso:country": "GB",
    "wof:name": "HU14 9BN",
    "wof:placetype": "postalcode"
  },
  "geometry": {"coordinates":[-0.429221,53.720652],"type":"Point"}
}
