{
  "type": "Feature",
  "properties": {
    "iso:country": "GB",
    "wof:name": "BN21 3EE",
    "wof:placetype": "postalcode"
  },
  "geometry": {"coordinates":[0.292377,50.768438],"type":"Point"}
}
