{
  "type": "Feature",
  "properties": {
    "iso:country": "GB",
    "wof:name": "DH1 1QT",
    "wof:placetype": "postalcode"
  },
  "geometry": {"coordinates":[-1.571237,54.778382],"type":"Point"}
}
