{
  "type": "Feature",
  "properties": {
    "date:inception_lower": "2016-08-01",
    "date:inception_upper": "2016-08-01",
    "iso:country": "GB",
    "wof:name": "EH8 8FN",
    "wof:placetype": "postalcode"
  },
  "geometry": {"coordinates":[-3.18189,55.950372],"type":"Point"}
}
