{
  "type": "Feature",
  "properties": {
    "iso:country":"GB",
    "wof:name":"SP4 7LP",
    "wof:placetype":"postalcode"
},
  "geometry": {"coordinates":[-1.76047666441769,51.16375448843563],"type":"Point"}
}