{
  "type": "Feature",
  "properties": {
    "date:inception_lower": "2001-12-01",
    "date:inception_upper": "2001-12-01",
    "iso:country": "GB",
    "wof:name": "W14 8DG",
    "wof:placetype": "postalcode"
  },
  "geometry": {"coordinates":[-0.203213,51.49179],"type":"Point"}
}
