{
  "type": "Feature",
  "properties": {
    "date:inception_lower": "2023-12-01",
    "date:inception_upper": "2023-12-01",
    "iso:country": "GB",
    "wof:name": "EH33 2FG",
    "wof:placetype": "postalcode"
  },
  "geometry": {"coordinates":[-2.94317,55.932484],"type":"Point"}
}
