{
  "type": "Feature",
  "properties": {
    "date:inception_lower": "1980-01-01",
    "date:inception_upper": "1980-01-01",
    "iso:country": "GB",
    "wof:name": "SA6 5LP",
    "wof:placetype": "postalcode"
  },
  "geometry": {"coordinates":[-3.891152,51.696997],"type":"Point"}
}
