{
  "type": "Feature",
  "properties": {
    "iso:country":"GB",
    "wof:name":"CR8 3EP",
    "wof:placetype":"postalcode"
},
  "geometry": {"coordinates":[-0.11898421660384,51.33978787858507],"type":"Point"}
}