{
  "type": "Feature",
  "properties": {
    "date:inception_lower": "2019-08-01",
    "date:inception_upper": "2019-08-01",
    "iso:country": "GB",
    "wof:name": "LE14 2PH",
    "wof:placetype": "postalcode"
  },
  "geometry": {"coordinates":[-0.96512,52.752139],"type":"Point"}
}
