{
  "type": "Feature",
  "properties": {
    "iso:country":"GB",
    "wof:name":"TN17 3JU",
    "wof:placetype":"postalcode"
},
  "geometry": {"coordinates":[0.53463404677108,51.09769070566671],"type":"Point"}
}