{
  "type": "Feature",
  "properties": {
    "iso:country":"GB",
    "wof:name":"SS0 0DW",
    "wof:placetype":"postalcode"
},
  "geometry": {"coordinates":[0.67757814300383,51.55894662886422],"type":"Point"}
}