{
  "type": "Feature",
  "properties": {
    "iso:country":"GB",
    "wof:name":"LE11 2NS",
    "wof:placetype":"postalcode"
},
  "geometry": {"coordinates":[-1.19431437890164,52.76600567154892],"type":"Point"}
}