{
  "type": "Feature",
  "properties": {
    "iso:country": "GB",
    "wof:name": "LE11 2NS",
    "wof:placetype": "postalcode"
  },
  "geometry": {"coordinates":[-1.194314,52.766006],"type":"Point"}
}
