{
  "type": "Feature",
  "properties": {
    "date:inception_lower":"1980-01-01",
    "date:inception_upper":"1980-01-31",
    "iso:country":"GB",
    "wof:name":"LE11 2NS",
    "wof:placetype":"postalcode"
},
  "geometry": {"coordinates":[-1.194314,52.766006],"type":"Point"}
}