{
  "type": "Feature",
  "properties": {
    "date:inception_lower": "2022-07-01",
    "date:inception_upper": "2022-07-01",
    "iso:country": "GB",
    "wof:name": "PR25 1FP",
    "wof:placetype": "postalcode"
  },
  "geometry": {"coordinates":[-2.714303,53.678531],"type":"Point"}
}
