{
  "type": "Feature",
  "properties": {
    "iso:country":"GB",
    "wof:name":"BN8 4BT",
    "wof:placetype":"postalcode"
},
  "geometry": {"coordinates":[-0.01918129781485,50.94677832766907],"type":"Point"}
}