{
  "type": "Feature",
  "properties": {
    "iso:country":"GB",
    "wof:name":"SM4 9SQ",
    "wof:placetype":"postalcode"
},
  "geometry": {"coordinates":[-0.19613348942122,51.40140504529685],"type":"Point"}
}