{
  "type": "Feature",
  "properties": {
    "iso:country":"GB",
    "wof:name":"CV8 2EL",
    "wof:placetype":"postalcode"
},
  "geometry": {"coordinates":[-1.55880433761669,52.35490613085116],"type":"Point"}
}