{
  "type": "Feature",
  "properties": {
    "iso:country":"GB",
    "wof:name":"FK5 4QS",
    "wof:placetype":"postalcode"
},
  "geometry": {"coordinates":[-3.81253694314239,56.02561116024278],"type":"Point"}
}