{
  "type": "Feature",
  "properties": {
    "date:inception_lower":"2002-06-01",
    "date:inception_upper":"2002-06-30",
    "iso:country":"GB",
    "wof:name":"FK5 4QS",
    "wof:placetype":"postalcode"
},
  "geometry": {"coordinates":[-3.81253,56.025606],"type":"Point"}
}