{
  "type": "Feature",
  "properties": {
    "date:inception_lower": "1980-01-01",
    "date:inception_upper": "1980-01-01",
    "iso:country": "GB",
    "wof:name": "SE3 8PE",
    "wof:placetype": "postalcode"
  },
  "geometry": {"coordinates":[0.032074,51.468884],"type":"Point"}
}
