{
  "type": "Feature",
  "properties": {
    "iso:country":"GB",
    "wof:name":"SE3 8PE",
    "wof:placetype":"postalcode"
},
  "geometry": {"coordinates":[0.0320737276973,51.46888386967914],"type":"Point"}
}