{
  "type": "Feature",
  "properties": {
    "date:inception_lower": "2005-11-01",
    "date:inception_upper": "2005-11-01",
    "iso:country": "GB",
    "wof:name": "NE32 3PE",
    "wof:placetype": "postalcode"
  },
  "geometry": {"coordinates":[-1.489571,54.983127],"type":"Point"}
}
