{
  "type": "Feature",
  "properties": {
    "iso:country":"GB",
    "wof:name":"NE32 3PE",
    "wof:placetype":"postalcode"
},
  "geometry": {"coordinates":[-1.48957058528249,54.98312745758089],"type":"Point"}
}