{
  "type": "Feature",
  "properties": {
    "iso:country": "GB",
    "wof:name": "NR33 0JS",
    "wof:placetype": "postalcode"
  },
  "geometry": {"coordinates":[1.736629,52.4557],"type":"Point"}
}
