{
  "type": "Feature",
  "properties": {
    "date:inception_lower":"2001-06-01",
    "date:inception_upper":"2001-06-30",
    "iso:country":"GB",
    "wof:name":"B1 1RQ",
    "wof:placetype":"postalcode"
},
  "geometry": {"coordinates":[-1.906159,52.475223],"type":"Point"}
}