{
  "type": "Feature",
  "properties": {
    "iso:country":"GB",
    "wof:name":"B1 1RQ",
    "wof:placetype":"postalcode"
},
  "geometry": {"coordinates":[-1.90615910441777,52.47522349404596],"type":"Point"}
}