{
  "type": "Feature",
  "properties": {
    "date:inception_lower": "2006-11-01",
    "date:inception_upper": "2006-11-01",
    "iso:country": "GB",
    "wof:name": "DN10 4JZ",
    "wof:placetype": "postalcode"
  },
  "geometry": {"coordinates":[-0.833973,53.422407],"type":"Point"}
}
