{
  "type": "Feature",
  "properties": {
    "iso:country": "GB",
    "wof:name": "DN10 4JZ",
    "wof:placetype": "postalcode"
  },
  "geometry": {"coordinates":[-0.833937,53.422511],"type":"Point"}
}
