{
  "type": "Feature",
  "properties": {
    "date:inception_lower": "2005-07-01",
    "date:inception_upper": "2005-07-01",
    "iso:country": "GB",
    "wof:name": "TF1 3BG",
    "wof:placetype": "postalcode"
  },
  "geometry": {"coordinates":[-2.509765,52.701183],"type":"Point"}
}
