{
  "type": "Feature",
  "properties": {
    "iso:country":"GB",
    "wof:name":"TF1 3BG",
    "wof:placetype":"postalcode"
},
  "geometry": {"coordinates":[-2.50976467404597,52.70118273375375],"type":"Point"}
}