{
  "type": "Feature",
  "properties": {
    "iso:country": "GB",
    "wof:name": "TF1 3BG",
    "wof:placetype": "postalcode"
  },
  "geometry": {"coordinates":[-2.509765,52.701183],"type":"Point"}
}
