{
  "type": "Feature",
  "properties": {
    "iso:country": "GB",
    "wof:name": "HU17 9TD",
    "wof:placetype": "postalcode"
  },
  "geometry": {"coordinates":[-0.387679,53.861057],"type":"Point"}
}
