{
  "type": "Feature",
  "properties": {
    "date:inception_lower": "2000-06-01",
    "date:inception_upper": "2000-06-01",
    "iso:country": "GB",
    "wof:name": "HU17 9TD",
    "wof:placetype": "postalcode"
  },
  "geometry": {"coordinates":[-0.387679,53.861057],"type":"Point"}
}
