{
  "type": "Feature",
  "properties": {
    "iso:country":"GB",
    "wof:name":"B20 2DT",
    "wof:placetype":"postalcode"
},
  "geometry": {"coordinates":[-1.92456517491466,52.51668921245027],"type":"Point"}
}