{
  "type": "Feature",
  "properties": {
    "iso:country":"GB",
    "wof:name":"LL36 9NS",
    "wof:placetype":"postalcode"
},
  "geometry": {"coordinates":[-4.05566608505195,52.60672073673877],"type":"Point"}
}