{
  "type": "Feature",
  "properties": {
    "iso:country":"GB",
    "wof:name":"PE24 4EA",
    "wof:placetype":"postalcode"
},
  "geometry": {"coordinates":[0.23811206745016,53.10787553930569],"type":"Point"}
}