{
  "type": "Feature",
  "properties": {
    "iso:country":"GB",
    "wof:name":"PO5 1PF",
    "wof:placetype":"postalcode"
},
  "geometry": {"coordinates":[-1.07692798576856,50.78727777019908],"type":"Point"}
}