{
  "type": "Feature",
  "properties": {
    "iso:country": "GB",
    "wof:name": "DT8 3HQ",
    "wof:placetype": "postalcode"
  },
  "geometry": {"coordinates":[-2.770427,50.847815],"type":"Point"}
}
