{
  "type": "Feature",
  "properties": {
    "iso:country":"GB",
    "wof:name":"DT8 3HQ",
    "wof:placetype":"postalcode"
},
  "geometry": {"coordinates":[-2.77052310437656,50.84769705030114],"type":"Point"}
}