{
  "type": "Feature",
  "properties": {
    "iso:country":"GB",
    "wof:name":"BA12 9LX",
    "wof:placetype":"postalcode"
},
  "geometry": {"coordinates":[-2.16771733443687,51.19929789196617],"type":"Point"}
}