{
  "type": "Feature",
  "properties": {
    "date:inception_lower":"1980-01-01",
    "date:inception_upper":"1980-01-31",
    "iso:country":"GB",
    "wof:name":"GU10 3AF",
    "wof:placetype":"postalcode"
},
  "geometry": {"coordinates":[-0.792904,51.18217],"type":"Point"}
}