{
  "type": "Feature",
  "properties": {
    "date:inception_lower": "1980-01-01",
    "date:inception_upper": "1980-01-01",
    "iso:country": "GB",
    "wof:name": "GU10 3AF",
    "wof:placetype": "postalcode"
  },
  "geometry": {"coordinates":[-0.79218,51.182349],"type":"Point"}
}
