{
  "type": "Feature",
  "properties": {
    "iso:country":"GB",
    "wof:name":"PO6 1LD",
    "wof:placetype":"postalcode"
},
  "geometry": {"coordinates":[-1.02998375134278,50.84286801735328],"type":"Point"}
}