{
  "type": "Feature",
  "properties": {
    "iso:country":"GB",
    "wof:name":"TW11 8TG",
    "wof:placetype":"postalcode"
},
  "geometry": {"coordinates":[-0.3400858947157,51.42683183261377],"type":"Point"}
}