{
  "type": "Feature",
  "properties": {
    "date:inception_lower": "1990-07-01",
    "date:inception_upper": "1990-07-01",
    "iso:country": "GB",
    "wof:name": "TW11 8TG",
    "wof:placetype": "postalcode"
  },
  "geometry": {"coordinates":[-0.340165,51.426833],"type":"Point"}
}
