{
  "type": "Feature",
  "properties": {
    "date:inception_lower": "1980-01-01",
    "date:inception_upper": "1980-01-01",
    "iso:country": "GB",
    "wof:name": "SE23 1PZ",
    "wof:placetype": "postalcode"
  },
  "geometry": {"coordinates":[-0.039967,51.445974],"type":"Point"}
}
