{
  "type": "Feature",
  "properties": {
    "date:inception_lower":"1980-01-01",
    "date:inception_upper":"1980-01-31",
    "iso:country":"GB",
    "wof:name":"SE23 1PZ",
    "wof:placetype":"postalcode"
},
  "geometry": {"coordinates":[-0.039708,51.445952],"type":"Point"}
}