{
  "type": "Feature",
  "properties": {
    "iso:country":"GB",
    "wof:name":"HS6 5JB",
    "wof:placetype":"postalcode"
},
  "geometry": {"coordinates":[-7.25651106511158,57.48937423389795],"type":"Point"}
}