{
  "type": "Feature",
  "properties": {
    "iso:country":"GB",
    "wof:name":"LL41 3LW",
    "wof:placetype":"postalcode"
},
  "geometry": {"coordinates":[-3.94538257458326,52.99869737545689],"type":"Point"}
}