{
  "type": "Feature",
  "properties": {
    "date:inception_lower": "1990-02-01",
    "date:inception_upper": "1990-02-01",
    "iso:country": "GB",
    "wof:name": "DT1 2TL",
    "wof:placetype": "postalcode"
  },
  "geometry": {"coordinates":[-2.426466,50.70808],"type":"Point"}
}
