{
  "type": "Feature",
  "properties": {
    "iso:country":"GB",
    "wof:name":"DT1 2TL",
    "wof:placetype":"postalcode"
},
  "geometry": {"coordinates":[-2.42649640652164,50.70807102735516],"type":"Point"}
}