{
  "type": "Feature",
  "properties": {
    "iso:country":"GB",
    "wof:name":"TR3 6JX",
    "wof:placetype":"postalcode"
},
  "geometry": {"coordinates":[-5.07308788012738,50.22890585352313],"type":"Point"}
}