{
  "type": "Feature",
  "properties": {
    "iso:country":"GB",
    "wof:name":"NR19 2PS",
    "wof:placetype":"postalcode"
},
  "geometry": {"coordinates":[0.92392636117352,52.67906265349785],"type":"Point"}
}