{
  "type": "Feature",
  "properties": {
    "iso:country": "GB",
    "wof:name": "KT3 5QX",
    "wof:placetype": "postalcode"
  },
  "geometry": {"coordinates":[-0.263025,51.392002],"type":"Point"}
}
