{
  "type": "Feature",
  "properties": {
    "iso:country":"GB",
    "wof:name":"KT3 5QX",
    "wof:placetype":"postalcode"
},
  "geometry": {"coordinates":[-0.26302492827629,51.39200226220764],"type":"Point"}
}