{
  "type": "Feature",
  "properties": {
    "iso:country":"GB",
    "wof:name":"BA2 1DT",
    "wof:placetype":"postalcode"
},
  "geometry": {"coordinates":[-2.39587092647724,51.37794627672054],"type":"Point"}
}