{
  "type": "Feature",
  "properties": {
    "iso:country":"GB",
    "wof:name":"WV8 1TH",
    "wof:placetype":"postalcode"
},
  "geometry": {"coordinates":[-2.15889355242919,52.62008802590881],"type":"Point"}
}