{
  "type": "Feature",
  "properties": {
    "iso:country":"GB",
    "wof:name":"HU11 5RQ",
    "wof:placetype":"postalcode"
},
  "geometry": {"coordinates":[-0.21574306773868,53.90452242807011],"type":"Point"}
}