{
  "type": "Feature",
  "properties": {
    "iso:country":"GB",
    "wof:name":"B68 0DE",
    "wof:placetype":"postalcode"
},
  "geometry": {"coordinates":[-1.99708594143699,52.46457139283707],"type":"Point"}
}