{
  "type": "Feature",
  "properties": {
    "iso:country":"GB",
    "wof:name":"DY13 8YZ",
    "wof:placetype":"postalcode"
},
  "geometry": {"coordinates":[-2.27769162735266,52.3434808482769],"type":"Point"}
}