{
  "type": "Feature",
  "properties": {
    "date:inception_lower": "1980-01-01",
    "date:inception_upper": "1980-01-01",
    "iso:country": "GB",
    "wof:name": "DY13 8YZ",
    "wof:placetype": "postalcode"
  },
  "geometry": {"coordinates":[-2.277692,52.343481],"type":"Point"}
}
