{
  "type": "Feature",
  "properties": {
    "iso:country":"GB",
    "wof:name":"W1H 2LG",
    "wof:placetype":"postalcode"
},
  "geometry": {"coordinates":[-0.15927147195708,51.51876023453105],"type":"Point"}
}