{
  "type": "Feature",
  "properties": {
    "date:inception_lower":"1980-01-01",
    "date:inception_upper":"1980-01-31",
    "iso:country":"GB",
    "wof:name":"HU12 8NJ",
    "wof:placetype":"postalcode"
},
  "geometry": {"coordinates":[-0.202207,53.738172],"type":"Point"}
}