{
  "type": "Feature",
  "properties": {
    "iso:country":"GB",
    "wof:name":"CB5 8HL",
    "wof:placetype":"postalcode"
},
  "geometry": {"coordinates":[0.13893392561893,52.21081777482534],"type":"Point"}
}