{
  "type": "Feature",
  "properties": {
    "date:inception_lower": "2020-12-01",
    "date:inception_upper": "2020-12-01",
    "iso:country": "GB",
    "wof:name": "E16 1RW",
    "wof:placetype": "postalcode"
  },
  "geometry": {"coordinates":[0.010827,51.510951],"type":"Point"}
}
