{
  "type": "Feature",
  "properties": {
    "iso:country": "GB",
    "wof:name": "G72 0RF",
    "wof:placetype": "postalcode"
  },
  "geometry": {"coordinates":[-4.101795,55.789387],"type":"Point"}
}
