{
  "type": "Feature",
  "properties": {
    "iso:country": "GB",
    "wof:name": "NG3 7GW",
    "wof:placetype": "postalcode"
  },
  "geometry": {"coordinates":[-1.105269,52.957513],"type":"Point"}
}
