{
  "type": "Feature",
  "properties": {
    "iso:country":"GB",
    "wof:name":"NG3 7GW",
    "wof:placetype":"postalcode"
},
  "geometry": {"coordinates":[-1.10526882391681,52.95751294231048],"type":"Point"}
}