{
  "type": "Feature",
  "properties": {
    "date:inception_lower":"2014-10-01",
    "date:inception_upper":"2014-10-31",
    "iso:country":"GB",
    "wof:name":"DH8 5SP",
    "wof:placetype":"postalcode"
},
  "geometry": {"coordinates":[-1.846749,54.856989],"type":"Point"}
}