{
  "type": "Feature",
  "properties": {
    "iso:country":"GB",
    "wof:name":"DH8 5SP",
    "wof:placetype":"postalcode"
},
  "geometry": {"coordinates":[-1.84673922285196,54.85698104345656],"type":"Point"}
}