{
  "type": "Feature",
  "properties": {
    "iso:country":"GB",
    "wof:name":"DT3 5SA",
    "wof:placetype":"postalcode"
},
  "geometry": {"coordinates":[-2.46696447462396,50.64602744677654],"type":"Point"}
}