{
  "type": "Feature",
  "properties": {
    "iso:country":"GB",
    "wof:name":"WA14 5BF",
    "wof:placetype":"postalcode"
},
  "geometry": {"coordinates":[-2.36630886285509,53.39579161715024],"type":"Point"}
}