{
  "type": "Feature",
  "properties": {
    "iso:country": "GB",
    "wof:name": "WA14 5BF",
    "wof:placetype": "postalcode"
  },
  "geometry": {"coordinates":[-2.366309,53.395792],"type":"Point"}
}
