{
  "type": "Feature",
  "properties": {
    "iso:country": "GB",
    "wof:name": "SS7 3PR",
    "wof:placetype": "postalcode"
  },
  "geometry": {"coordinates":[0.582273,51.56978],"type":"Point"}
}
