{
  "type": "Feature",
  "properties": {
    "iso:country":"GB",
    "wof:name":"SS7 3PR",
    "wof:placetype":"postalcode"
},
  "geometry": {"coordinates":[0.58227332687153,51.56978029233436],"type":"Point"}
}