{
  "type": "Feature",
  "properties": {
    "date:inception_lower":"1980-01-01",
    "date:inception_upper":"1980-01-31",
    "iso:country":"GB",
    "wof:name":"SS7 3PR",
    "wof:placetype":"postalcode"
},
  "geometry": {"coordinates":[0.582273,51.56978],"type":"Point"}
}