{
  "type": "Feature",
  "properties": {
    "iso:country":"GB",
    "wof:name":"LN11 8PD",
    "wof:placetype":"postalcode"
},
  "geometry": {"coordinates":[0.07883224189088,53.298783132456],"type":"Point"}
}