{
  "type": "Feature",
  "properties": {
    "iso:country": "GB",
    "wof:name": "LN11 8PD",
    "wof:placetype": "postalcode"
  },
  "geometry": {"coordinates":[0.078832,53.298783],"type":"Point"}
}
