{
  "type": "Feature",
  "properties": {
    "iso:country":"GB",
    "wof:name":"S70 2NR",
    "wof:placetype":"postalcode"
},
  "geometry": {"coordinates":[-1.48818698353937,53.55403224039733],"type":"Point"}
}