{
  "type": "Feature",
  "properties": {
    "iso:country":"GB",
    "wof:name":"ME6 5SL",
    "wof:placetype":"postalcode"
},
  "geometry": {"coordinates":[0.44674297670849,51.33633094687879],"type":"Point"}
}