{
  "type": "Feature",
  "properties": {
    "iso:country": "GB",
    "wof:name": "ME6 5SL",
    "wof:placetype": "postalcode"
  },
  "geometry": {"coordinates":[0.446743,51.336331],"type":"Point"}
}
