{
  "type": "Feature",
  "properties": {
    "date:inception_lower":"1995-12-01",
    "date:inception_upper":"1995-12-31",
    "iso:country":"GB",
    "wof:name":"ME6 5SL",
    "wof:placetype":"postalcode"
},
  "geometry": {"coordinates":[0.446743,51.336331],"type":"Point"}
}