{
  "type": "Feature",
  "properties": {
    "iso:country": "GB",
    "wof:name": "OX10 6PY",
    "wof:placetype": "postalcode"
  },
  "geometry": {"coordinates":[-1.06904,51.602735],"type":"Point"}
}
