{
  "type": "Feature",
  "properties": {
    "iso:country":"GB",
    "wof:name":"OX10 6PY",
    "wof:placetype":"postalcode"
},
  "geometry": {"coordinates":[-1.06904018839498,51.60273467516605],"type":"Point"}
}