{
  "type": "Feature",
  "properties": {
    "iso:country":"GB",
    "wof:name":"WD6 1JU",
    "wof:placetype":"postalcode"
},
  "geometry": {"coordinates":[-0.26759287081987,51.65947535105318],"type":"Point"}
}