{
  "type": "Feature",
  "properties": {
    "iso:country":"GB",
    "wof:name":"CF63 4AR",
    "wof:placetype":"postalcode"
},
  "geometry": {"coordinates":[-3.26726061422926,51.40198255768996],"type":"Point"}
}