{
  "type": "Feature",
  "properties": {
    "date:inception_lower":"2006-07-01",
    "date:inception_upper":"2006-07-31",
    "iso:country":"GB",
    "wof:name":"CF63 4AR",
    "wof:placetype":"postalcode"
},
  "geometry": {"coordinates":[-3.267261,51.401983],"type":"Point"}
}