{
  "type": "Feature",
  "properties": {
    "iso:country":"GB",
    "wof:name":"RH12 4AH",
    "wof:placetype":"postalcode"
},
  "geometry": {"coordinates":[-0.31305734896398,51.07323107732859],"type":"Point"}
}