{
  "type": "Feature",
  "properties": {
    "iso:country": "GB",
    "wof:name": "RH12 4AH",
    "wof:placetype": "postalcode"
  },
  "geometry": {"coordinates":[-0.313057,51.073231],"type":"Point"}
}
