{
  "type": "Feature",
  "properties": {
    "date:inception_lower": "2003-08-01",
    "date:inception_upper": "2003-08-01",
    "iso:country": "GB",
    "wof:name": "TF1 5LT",
    "wof:placetype": "postalcode"
  },
  "geometry": {"coordinates":[-2.471887,52.704522],"type":"Point"}
}
