{
  "type": "Feature",
  "properties": {
    "iso:country":"GB",
    "wof:name":"TF1 5LT",
    "wof:placetype":"postalcode"
},
  "geometry": {"coordinates":[-2.47188678881594,52.70452197505078],"type":"Point"}
}