{
  "type": "Feature",
  "properties": {
    "iso:country":"GB",
    "wof:name":"BB8 8BN",
    "wof:placetype":"postalcode"
},
  "geometry": {"coordinates":[-2.13965159603075,53.85299997462911],"type":"Point"}
}