{
  "type": "Feature",
  "properties": {
    "iso:country":"GB",
    "wof:name":"PE9 1ED",
    "wof:placetype":"postalcode"
},
  "geometry": {"coordinates":[-0.48277616759282,52.65422973851382],"type":"Point"}
}