{
  "type": "Feature",
  "properties": {
    "date:inception_lower": "1980-01-01",
    "date:inception_upper": "1980-01-01",
    "iso:country": "GB",
    "wof:name": "PE9 1ED",
    "wof:placetype": "postalcode"
  },
  "geometry": {"coordinates":[-0.482776,52.65423],"type":"Point"}
}
