{
  "type": "Feature",
  "properties": {
    "iso:country":"GB",
    "wof:name":"PO11 0EL",
    "wof:placetype":"postalcode"
},
  "geometry": {"coordinates":[-0.99304778886717,50.79237540806538],"type":"Point"}
}