{
  "type": "Feature",
  "properties": {
    "iso:country":"GB",
    "wof:name":"WD3 1NJ",
    "wof:placetype":"postalcode"
},
  "geometry": {"coordinates":[-0.46793806231564,51.63158813225481],"type":"Point"}
}