{
  "type": "Feature",
  "properties": {
    "iso:country":"GB",
    "wof:name":"SK2 7BF",
    "wof:placetype":"postalcode"
},
  "geometry": {"coordinates":[-2.12779701067366,53.3943800386398],"type":"Point"}
}