{
  "type": "Feature",
  "properties": {
    "date:inception_lower": "1999-06-01",
    "date:inception_upper": "1999-06-01",
    "iso:country": "GB",
    "wof:name": "CH61 5XL",
    "wof:placetype": "postalcode"
  },
  "geometry": {"coordinates":[-3.100269,53.345016],"type":"Point"}
}
