{
  "type": "Feature",
  "properties": {
    "date:inception_lower": "1980-04-01",
    "date:inception_upper": "1980-04-01",
    "iso:country": "GB",
    "wof:name": "KA11 1BN",
    "wof:placetype": "postalcode"
  },
  "geometry": {"coordinates":[-4.63857,55.629274],"type":"Point"}
}
