{
  "type": "Feature",
  "properties": {
    "iso:country":"GB",
    "wof:name":"KA11 1BN",
    "wof:placetype":"postalcode"
},
  "geometry": {"coordinates":[-4.63857053645157,55.6292743041294],"type":"Point"}
}