{
  "type": "Feature",
  "properties": {
    "date:inception_lower": "1981-06-01",
    "date:inception_upper": "1981-06-01",
    "iso:country": "GB",
    "wof:name": "CT9 1TY",
    "wof:placetype": "postalcode"
  },
  "geometry": {"coordinates":[1.386597,51.384132],"type":"Point"}
}
