{
  "type": "Feature",
  "properties": {
    "iso:country":"GB",
    "wof:name":"GU31 4AG",
    "wof:placetype":"postalcode"
},
  "geometry": {"coordinates":[-0.93352724974552,51.00664642166664],"type":"Point"}
}