{
  "type": "Feature",
  "properties": {
    "date:inception_lower": "1980-01-01",
    "date:inception_upper": "1980-01-01",
    "iso:country": "GB",
    "wof:name": "TA1 5LD",
    "wof:placetype": "postalcode"
  },
  "geometry": {"coordinates":[-3.12524,51.012052],"type":"Point"}
}
