{
  "type": "Feature",
  "properties": {
    "iso:country":"GB",
    "wof:name":"TA1 5LD",
    "wof:placetype":"postalcode"
},
  "geometry": {"coordinates":[-3.12523992617343,51.01205229680377],"type":"Point"}
}