{
  "type": "Feature",
  "properties": {
    "iso:country": "GB",
    "wof:name": "LN1 1UX",
    "wof:placetype": "postalcode"
  },
  "geometry": {"coordinates":[-0.542201,53.229556],"type":"Point"}
}
