{
  "type": "Feature",
  "properties": {
    "iso:country":"GB",
    "wof:name":"LN1 1UX",
    "wof:placetype":"postalcode"
},
  "geometry": {"coordinates":[-0.54220086553389,53.22955645872234],"type":"Point"}
}