{
  "type": "Feature",
  "properties": {
    "iso:country": "GB",
    "wof:name": "IV9 8RA",
    "wof:placetype": "postalcode"
  },
  "geometry": {"coordinates":[-4.180778,57.571947],"type":"Point"}
}
