{
  "type": "Feature",
  "properties": {
    "iso:country": "GB",
    "wof:name": "BS37 5XL",
    "wof:placetype": "postalcode"
  },
  "geometry": {"coordinates":[-2.426315,51.542952],"type":"Point"}
}
