{
  "type": "Feature",
  "properties": {
    "iso:country":"GB",
    "wof:name":"NN5 6QS",
    "wof:placetype":"postalcode"
},
  "geometry": {"coordinates":[-0.95907963725057,52.25816570667089],"type":"Point"}
}