{
  "type": "Feature",
  "properties": {
    "iso:country":"GB",
    "wof:name":"ST7 1UT",
    "wof:placetype":"postalcode"
},
  "geometry": {"coordinates":[-2.25146672432549,53.07239208410225],"type":"Point"}
}