{
  "type": "Feature",
  "properties": {
    "date:inception_lower":"1980-01-01",
    "date:inception_upper":"1980-01-31",
    "iso:country":"GB",
    "wof:name":"ST7 1UT",
    "wof:placetype":"postalcode"
},
  "geometry": {"coordinates":[-2.251467,53.072392],"type":"Point"}
}