{
  "type": "Feature",
  "properties": {
    "iso:country":"GB",
    "wof:name":"SM5 2NE",
    "wof:placetype":"postalcode"
},
  "geometry": {"coordinates":[-0.15856437498705,51.37533550636097],"type":"Point"}
}