{
  "type": "Feature",
  "properties": {
    "date:inception_lower": "1993-08-01",
    "date:inception_upper": "1993-08-01",
    "iso:country": "GB",
    "wof:name": "CW10 9QJ",
    "wof:placetype": "postalcode"
  },
  "geometry": {"coordinates":[-2.456666,53.198212],"type":"Point"}
}
