{
  "type": "Feature",
  "properties": {
    "iso:country": "GB",
    "wof:name": "BS9 4DR",
    "wof:placetype": "postalcode"
  },
  "geometry": {"coordinates":[-2.613118,51.487616],"type":"Point"}
}
