{
  "type": "Feature",
  "properties": {
    "iso:country":"GB",
    "wof:name":"ML3 8UP",
    "wof:placetype":"postalcode"
},
  "geometry": {"coordinates":[-4.07229333102567,55.7621900167825],"type":"Point"}
}