{
  "type": "Feature",
  "properties": {
    "iso:country":"GB",
    "wof:name":"S42 5UY",
    "wof:placetype":"postalcode"
},
  "geometry": {"coordinates":[-1.35944584916555,53.19221702848477],"type":"Point"}
}