{
  "type": "Feature",
  "properties": {
    "iso:country": "GB",
    "wof:name": "SW16 4RG",
    "wof:placetype": "postalcode"
  },
  "geometry": {"coordinates":[-0.115642,51.402351],"type":"Point"}
}
