{
  "type": "Feature",
  "properties": {
    "iso:country":"GB",
    "wof:name":"SW16 4RG",
    "wof:placetype":"postalcode"
},
  "geometry": {"coordinates":[-0.11564204261589,51.40235054266964],"type":"Point"}
}