{
  "type": "Feature",
  "properties": {
    "iso:country": "GB",
    "wof:name": "DL16 7SL",
    "wof:placetype": "postalcode"
  },
  "geometry": {"coordinates":[-1.610058,54.694128],"type":"Point"}
}
