{
  "type": "Feature",
  "properties": {
    "iso:country":"GB",
    "wof:name":"CT3 4BY",
    "wof:placetype":"postalcode"
},
  "geometry": {"coordinates":[1.16896829874031,51.32242427376267],"type":"Point"}
}