{
  "type": "Feature",
  "properties": {
    "iso:country":"GB",
    "wof:name":"SA66 7LS",
    "wof:placetype":"postalcode"
},
  "geometry": {"coordinates":[-4.74792790574688,51.86721516115417],"type":"Point"}
}