{
  "type": "Feature",
  "properties": {
    "date:inception_lower": "1985-10-01",
    "date:inception_upper": "1985-10-01",
    "iso:country": "GB",
    "wof:name": "B42 1TQ",
    "wof:placetype": "postalcode"
  },
  "geometry": {"coordinates":[-1.933143,52.545183],"type":"Point"}
}
