{
  "type": "Feature",
  "properties": {
    "iso:country": "GB",
    "wof:name": "B42 1TQ",
    "wof:placetype": "postalcode"
  },
  "geometry": {"coordinates":[-1.933143,52.545183],"type":"Point"}
}
