{
  "type": "Feature",
  "properties": {
    "iso:country": "GB",
    "wof:name": "DN17 4EQ",
    "wof:placetype": "postalcode"
  },
  "geometry": {"coordinates":[-0.839367,53.604221],"type":"Point"}
}
