{
  "type": "Feature",
  "properties": {
    "date:inception_lower": "2015-11-01",
    "date:inception_upper": "2015-11-01",
    "iso:country": "GB",
    "wof:name": "SN5 5EN",
    "wof:placetype": "postalcode"
  },
  "geometry": {"coordinates":[-1.832346,51.567965],"type":"Point"}
}
