{
  "type": "Feature",
  "properties": {
    "iso:country":"GB",
    "wof:name":"SN5 5EN",
    "wof:placetype":"postalcode"
},
  "geometry": {"coordinates":[-1.83234600525368,51.56796546469304],"type":"Point"}
}