{
  "type": "Feature",
  "properties": {
    "iso:country": "GB",
    "wof:name": "LN2 4HU",
    "wof:placetype": "postalcode"
  },
  "geometry": {"coordinates":[-0.507647,53.237085],"type":"Point"}
}
