{
  "type": "Feature",
  "properties": {
    "iso:country":"GB",
    "wof:name":"LN2 4HU",
    "wof:placetype":"postalcode"
},
  "geometry": {"coordinates":[-0.50764674447058,53.23708470061016],"type":"Point"}
}