{
  "type": "Feature",
  "properties": {
    "date:inception_lower": "1980-01-01",
    "date:inception_upper": "1980-01-01",
    "iso:country": "GB",
    "wof:name": "SA63 4UX",
    "wof:placetype": "postalcode"
  },
  "geometry": {"coordinates":[-4.880156,51.848365],"type":"Point"}
}
