{
  "type": "Feature",
  "properties": {
    "iso:country":"GB",
    "wof:name":"SA63 4UX",
    "wof:placetype":"postalcode"
},
  "geometry": {"coordinates":[-4.88015645997111,51.84836502546287],"type":"Point"}
}