{
  "type": "Feature",
  "properties": {
    "iso:country": "GB",
    "wof:name": "ST17 4HH",
    "wof:placetype": "postalcode"
  },
  "geometry": {"coordinates":[-2.106017,52.780226],"type":"Point"}
}
