{
  "type": "Feature",
  "properties": {
    "iso:country": "GB",
    "wof:name": "GL10 2AX",
    "wof:placetype": "postalcode"
  },
  "geometry": {"coordinates":[-2.285383,51.740077],"type":"Point"}
}
