{
  "type": "Feature",
  "properties": {
    "date:inception_lower":"1980-01-01",
    "date:inception_upper":"1980-01-31",
    "iso:country":"GB",
    "wof:name":"GL10 2AX",
    "wof:placetype":"postalcode"
},
  "geometry": {"coordinates":[-2.285383,51.740077],"type":"Point"}
}