{
  "type": "Feature",
  "properties": {
    "iso:country":"GB",
    "wof:name":"GL10 2AX",
    "wof:placetype":"postalcode"
},
  "geometry": {"coordinates":[-2.28521212627078,51.74007296362984],"type":"Point"}
}