{
  "type": "Feature",
  "properties": {
    "iso:country":"GB",
    "wof:name":"OL15 9BY",
    "wof:placetype":"postalcode"
},
  "geometry": {"coordinates":[-2.09580490144768,53.64473643248776],"type":"Point"}
}