{
  "type": "Feature",
  "properties": {
    "date:inception_lower": "2020-10-01",
    "date:inception_upper": "2020-10-01",
    "iso:country": "GB",
    "wof:name": "MK42 6FD",
    "wof:placetype": "postalcode"
  },
  "geometry": {"coordinates":[-0.461998,52.081151],"type":"Point"}
}
