{
  "type": "Feature",
  "properties": {
    "date:inception_lower":"2013-09-01",
    "date:inception_upper":"2013-09-30",
    "iso:country":"GB",
    "wof:name":"CW8 4QN",
    "wof:placetype":"postalcode"
},
  "geometry": {"coordinates":[-2.53679,53.264737],"type":"Point"}
}