{
  "type": "Feature",
  "properties": {
    "date:inception_lower": "1993-01-01",
    "date:inception_upper": "1993-01-01",
    "iso:country": "GB",
    "wof:name": "CF31 2PT",
    "wof:placetype": "postalcode"
  },
  "geometry": {"coordinates":[-3.555338,51.50544],"type":"Point"}
}
