{
  "type": "Feature",
  "properties": {
    "iso:country": "GB",
    "wof:name": "CF31 2PT",
    "wof:placetype": "postalcode"
  },
  "geometry": {"coordinates":[-3.555338,51.50544],"type":"Point"}
}
