{
  "type": "Feature",
  "properties": {
    "iso:country":"GB",
    "wof:name":"E8 4BH",
    "wof:placetype":"postalcode"
},
  "geometry": {"coordinates":[-0.07629032657036,51.5375899341611],"type":"Point"}
}