{
  "type": "Feature",
  "properties": {
    "iso:country": "GB",
    "wof:name": "SO21 1WG",
    "wof:placetype": "postalcode"
  },
  "geometry": {"coordinates":[-1.310778,50.992314],"type":"Point"}
}
