{
  "type": "Feature",
  "properties": {
    "iso:country":"GB",
    "wof:name":"SO21 1WG",
    "wof:placetype":"postalcode"
},
  "geometry": {"coordinates":[-1.31077830898522,50.99231355001166],"type":"Point"}
}