{
  "type": "Feature",
  "properties": {
    "date:inception_lower": "1980-01-01",
    "date:inception_upper": "1980-01-01",
    "iso:country": "GB",
    "wof:name": "BA22 8NB",
    "wof:placetype": "postalcode"
  },
  "geometry": {"coordinates":[-2.686351,51.001679],"type":"Point"}
}
