{
  "type": "Feature",
  "properties": {
    "iso:country":"GB",
    "wof:name":"BA22 8NB",
    "wof:placetype":"postalcode"
},
  "geometry": {"coordinates":[-2.68635133180444,51.00167938923666],"type":"Point"}
}