{
  "type": "Feature",
  "properties": {
    "iso:country": "GB",
    "wof:name": "BA22 8NB",
    "wof:placetype": "postalcode"
  },
  "geometry": {"coordinates":[-2.686351,51.001679],"type":"Point"}
}
