{
  "type": "Feature",
  "properties": {
    "iso:country":"GB",
    "wof:name":"DH7 6BL",
    "wof:placetype":"postalcode"
},
  "geometry": {"coordinates":[-1.63043188076804,54.83208178019182],"type":"Point"}
}