{
  "type": "Feature",
  "properties": {
    "iso:country":"GB",
    "wof:name":"PE24 4SA",
    "wof:placetype":"postalcode"
},
  "geometry": {"coordinates":[0.27387584854623,53.14062590803337],"type":"Point"}
}