{
  "type": "Feature",
  "properties": {
    "iso:country":"GB",
    "wof:name":"AB55 5HD",
    "wof:placetype":"postalcode"
},
  "geometry": {"coordinates":[-2.94847244627228,57.54259479617006],"type":"Point"}
}