{
  "type": "Feature",
  "properties": {
    "iso:country": "GB",
    "wof:name": "AB55 5HD",
    "wof:placetype": "postalcode"
  },
  "geometry": {"coordinates":[-2.948472,57.542595],"type":"Point"}
}
