{
  "type": "Feature",
  "properties": {
    "iso:country": "GB",
    "wof:name": "CT16 2LA",
    "wof:placetype": "postalcode"
  },
  "geometry": {"coordinates":[1.304924,51.131133],"type":"Point"}
}
