{
  "type": "Feature",
  "properties": {
    "iso:country":"GB",
    "wof:name":"LE2 4SH",
    "wof:placetype":"postalcode"
},
  "geometry": {"coordinates":[-1.06370856419351,52.59185527788598],"type":"Point"}
}