{
  "type": "Feature",
  "properties": {
    "date:inception_lower": "1980-01-01",
    "date:inception_upper": "1980-01-01",
    "iso:country": "GB",
    "wof:name": "BS5 8RJ",
    "wof:placetype": "postalcode"
  },
  "geometry": {"coordinates":[-2.52214,51.451489],"type":"Point"}
}
