{
  "type": "Feature",
  "properties": {
    "iso:country":"GB",
    "wof:name":"NR25 6EP",
    "wof:placetype":"postalcode"
},
  "geometry": {"coordinates":[1.09851034415218,52.90042967966963],"type":"Point"}
}