{
  "type": "Feature",
  "properties": {
    "iso:country":"GB",
    "wof:name":"DA1 1JL",
    "wof:placetype":"postalcode"
},
  "geometry": {"coordinates":[0.21711670857737,51.43843424943978],"type":"Point"}
}