{
  "type": "Feature",
  "properties": {
    "date:inception_lower": "1980-01-01",
    "date:inception_upper": "1980-01-01",
    "iso:country": "GB",
    "wof:name": "TA18 8QR",
    "wof:placetype": "postalcode"
  },
  "geometry": {"coordinates":[-2.82649,50.873331],"type":"Point"}
}
