{
  "type": "Feature",
  "properties": {
    "date:inception_lower":"2007-07-01",
    "date:inception_upper":"2007-07-31",
    "iso:country":"GB",
    "wof:name":"AB51 5QW",
    "wof:placetype":"postalcode"
},
  "geometry": {"coordinates":[-2.402699,57.284137],"type":"Point"}
}