{
  "type": "Feature",
  "properties": {
    "date:inception_lower":"1993-01-01",
    "date:inception_upper":"1993-01-31",
    "iso:country":"GB",
    "wof:name":"L12 0PW",
    "wof:placetype":"postalcode"
},
  "geometry": {"coordinates":[-2.881853,53.441959],"type":"Point"}
}