{
  "type": "Feature",
  "properties": {
    "iso:country":"GB",
    "wof:name":"L12 0PW",
    "wof:placetype":"postalcode"
},
  "geometry": {"coordinates":[-2.88185259567831,53.44195920779736],"type":"Point"}
}