{
  "type": "Feature",
  "properties": {
    "iso:country":"GB",
    "wof:name":"WA2 7BT",
    "wof:placetype":"postalcode"
},
  "geometry": {"coordinates":[-2.58945015282595,53.39479021845067],"type":"Point"}
}