{
  "type": "Feature",
  "properties": {
    "iso:country": "GB",
    "wof:name": "WA2 7BT",
    "wof:placetype": "postalcode"
  },
  "geometry": {"coordinates":[-2.58945,53.39479],"type":"Point"}
}
