{
  "type": "Feature",
  "properties": {
    "iso:country":"GB",
    "wof:name":"SS14 3WF",
    "wof:placetype":"postalcode"
},
  "geometry": {"coordinates":[0.46565448048709,51.58872911854373],"type":"Point"}
}