{
  "type": "Feature",
  "properties": {
    "iso:country": "GB",
    "wof:name": "SS14 3WF",
    "wof:placetype": "postalcode"
  },
  "geometry": {"coordinates":[0.469396,51.590102],"type":"Point"}
}
