{
  "type": "Feature",
  "properties": {
    "iso:country":"GB",
    "wof:name":"CR0 7ET",
    "wof:placetype":"postalcode"
},
  "geometry": {"coordinates":[-0.06051486218657,51.38071375776555],"type":"Point"}
}