{
  "type": "Feature",
  "properties": {
    "iso:country":"GB",
    "wof:name":"S66 7ET",
    "wof:placetype":"postalcode"
},
  "geometry": {"coordinates":[-1.19887083651776,53.43071132576225],"type":"Point"}
}