{
  "type": "Feature",
  "properties": {
    "date:inception_lower": "1980-01-01",
    "date:inception_upper": "1980-01-01",
    "iso:country": "GB",
    "wof:name": "S66 7ET",
    "wof:placetype": "postalcode"
  },
  "geometry": {"coordinates":[-1.198871,53.430711],"type":"Point"}
}
