{
  "type": "Feature",
  "properties": {
    "iso:country": "GB",
    "wof:name": "N1 9LG",
    "wof:placetype": "postalcode"
  },
  "geometry": {"coordinates":[-0.112225,51.531294],"type":"Point"}
}
