{
  "type": "Feature",
  "properties": {
    "iso:country": "GB",
    "wof:name": "SK13 2RD",
    "wof:placetype": "postalcode"
  },
  "geometry": {"coordinates":[-1.982613,53.456226],"type":"Point"}
}
