{
  "type": "Feature",
  "properties": {
    "iso:country": "GB",
    "wof:name": "LE19 1WH",
    "wof:placetype": "postalcode"
  },
  "geometry": {"coordinates":[-1.194698,52.60882],"type":"Point"}
}
