{
  "type": "Feature",
  "properties": {
    "iso:country":"GB",
    "wof:name":"LE19 1WH",
    "wof:placetype":"postalcode"
},
  "geometry": {"coordinates":[-1.19470599418088,52.60880238087307],"type":"Point"}
}