{
  "type": "Feature",
  "properties": {
    "iso:country":"GB",
    "wof:name":"NE31 2AP",
    "wof:placetype":"postalcode"
},
  "geometry": {"coordinates":[-1.49734102045642,54.95774649658502],"type":"Point"}
}