{
  "type": "Feature",
  "properties": {
    "iso:country":"GB",
    "wof:name":"EH3 7BR",
    "wof:placetype":"postalcode"
},
  "geometry": {"coordinates":[-3.21088472190402,55.94969076114219],"type":"Point"}
}