{
  "type": "Feature",
  "properties": {
    "iso:country":"GB",
    "wof:name":"WA3 3PU",
    "wof:placetype":"postalcode"
},
  "geometry": {"coordinates":[-2.60040687312811,53.47015038136543],"type":"Point"}
}