{
  "type": "Feature",
  "properties": {
    "iso:country": "GB",
    "wof:name": "B65 8LE",
    "wof:placetype": "postalcode"
  },
  "geometry": {"coordinates":[-2.060021,52.494672],"type":"Point"}
}
