{
  "type": "Feature",
  "properties": {
    "iso:country":"GB",
    "wof:name":"ML1 1PU",
    "wof:placetype":"postalcode"
},
  "geometry": {"coordinates":[-3.98222737972962,55.78839941262618],"type":"Point"}
}