{
  "type": "Feature",
  "properties": {
    "iso:country":"GB",
    "wof:name":"S41 7DB",
    "wof:placetype":"postalcode"
},
  "geometry": {"coordinates":[-1.43952502004634,53.24809126285083],"type":"Point"}
}