{
  "type": "Feature",
  "properties": {
    "iso:country":"GB",
    "wof:name":"KT10 9TB",
    "wof:placetype":"postalcode"
},
  "geometry": {"coordinates":[-0.34492003528312,51.37542743964021],"type":"Point"}
}