{
  "type": "Feature",
  "properties": {
    "iso:country":"GB",
    "wof:name":"NW3 4UY",
    "wof:placetype":"postalcode"
},
  "geometry": {"coordinates":[-0.16475127781809,51.54880894695832],"type":"Point"}
}