{
  "type": "Feature",
  "properties": {
    "iso:country": "GB",
    "wof:name": "SN9 5LR",
    "wof:placetype": "postalcode"
  },
  "geometry": {"coordinates":[-1.717202,51.348342],"type":"Point"}
}
