{
  "type": "Feature",
  "properties": {
    "iso:country": "GB",
    "wof:name": "SY13 2BZ",
    "wof:placetype": "postalcode"
  },
  "geometry": {"coordinates":[-2.671865,52.896214],"type":"Point"}
}
