{
  "type": "Feature",
  "properties": {
    "date:inception_lower": "1999-06-01",
    "date:inception_upper": "1999-06-01",
    "iso:country": "GB",
    "wof:name": "NP16 7JB",
    "wof:placetype": "postalcode"
  },
  "geometry": {"coordinates":[-2.66421,51.666029],"type":"Point"}
}
