{
  "type": "Feature",
  "properties": {
    "date:inception_lower": "2008-02-01",
    "date:inception_upper": "2008-02-01",
    "iso:country": "GB",
    "wof:name": "TN24 0ST",
    "wof:placetype": "postalcode"
  },
  "geometry": {"coordinates":[0.910665,51.140647],"type":"Point"}
}
