{
  "type": "Feature",
  "properties": {
    "iso:country": "GB",
    "wof:name": "TN24 0ST",
    "wof:placetype": "postalcode"
  },
  "geometry": {"coordinates":[0.910665,51.140647],"type":"Point"}
}
