{
  "type": "Feature",
  "properties": {
    "date:inception_lower": "2008-04-01",
    "date:inception_upper": "2008-04-01",
    "iso:country": "GB",
    "wof:name": "LE9 7JN",
    "wof:placetype": "postalcode"
  },
  "geometry": {"coordinates":[-1.300293,52.576408],"type":"Point"}
}
