{
  "type": "Feature",
  "properties": {
    "iso:country": "GB",
    "wof:name": "LE9 7JN",
    "wof:placetype": "postalcode"
  },
  "geometry": {"coordinates":[-1.300293,52.576408],"type":"Point"}
}
