{
  "type": "Feature",
  "properties": {
    "iso:country":"GB",
    "wof:name":"SK5 7LR",
    "wof:placetype":"postalcode"
},
  "geometry": {"coordinates":[-2.15827556084587,53.42592923146982],"type":"Point"}
}