{
  "type": "Feature",
  "properties": {
    "iso:country":"GB",
    "wof:name":"KY8 3HL",
    "wof:placetype":"postalcode"
},
  "geometry": {"coordinates":[-3.01216213214949,56.18471002926103],"type":"Point"}
}