{
  "type": "Feature",
  "properties": {
    "iso:country":"GB",
    "wof:name":"LL12 8XS",
    "wof:placetype":"postalcode"
},
  "geometry": {"coordinates":[-2.96195882530988,53.08724130738118],"type":"Point"}
}