{
  "type": "Feature",
  "properties": {
    "iso:country":"GB",
    "wof:name":"HP1 1US",
    "wof:placetype":"postalcode"
},
  "geometry": {"coordinates":[-0.48074151016132,51.74562792400582],"type":"Point"}
}