{
  "type": "Feature",
  "properties": {
    "iso:country":"GB",
    "wof:name":"SE6 1PW",
    "wof:placetype":"postalcode"
},
  "geometry": {"coordinates":[0.00000094951937,51.43412983380617],"type":"Point"}
}