{
  "type": "Feature",
  "properties": {
    "iso:country":"GB",
    "wof:name":"EN8 8JH",
    "wof:placetype":"postalcode"
},
  "geometry": {"coordinates":[-0.03431822729717,51.6969514653876],"type":"Point"}
}