{
  "type": "Feature",
  "properties": {
    "date:inception_lower": "1980-01-01",
    "date:inception_upper": "1980-01-01",
    "iso:country": "GB",
    "wof:name": "EN8 8JH",
    "wof:placetype": "postalcode"
  },
  "geometry": {"coordinates":[-0.034132,51.696961],"type":"Point"}
}
