{
  "type": "Feature",
  "properties": {
    "date:inception_lower": "1980-01-01",
    "date:inception_upper": "1980-01-01",
    "iso:country": "GB",
    "wof:name": "TR13 9RJ",
    "wof:placetype": "postalcode"
  },
  "geometry": {"coordinates":[-5.353152,50.13191],"type":"Point"}
}
