{
  "type": "Feature",
  "properties": {
    "iso:country":"GB",
    "wof:name":"DH4 7QR",
    "wof:placetype":"postalcode"
},
  "geometry": {"coordinates":[-1.49133655818334,54.87297979100849],"type":"Point"}
}