{
  "type": "Feature",
  "properties": {
    "iso:country": "GB",
    "wof:name": "TA20 3HQ",
    "wof:placetype": "postalcode"
  },
  "geometry": {"coordinates":[-2.991713,50.901008],"type":"Point"}
}
