{
  "type": "Feature",
  "properties": {
    "date:inception_lower":"1980-01-01",
    "date:inception_upper":"1980-01-31",
    "iso:country":"GB",
    "wof:name":"TA20 3HQ",
    "wof:placetype":"postalcode"
},
  "geometry": {"coordinates":[-2.991713,50.901008],"type":"Point"}
}