{
  "type": "Feature",
  "properties": {
    "iso:country": "GB",
    "wof:name": "CF11 8EQ",
    "wof:placetype": "postalcode"
  },
  "geometry": {"coordinates":[-3.196312,51.462103],"type":"Point"}
}
