{
  "type": "Feature",
  "properties": {
    "iso:country":"GB",
    "wof:name":"CF11 8EQ",
    "wof:placetype":"postalcode"
},
  "geometry": {"coordinates":[-3.19630301102786,51.46210275161904],"type":"Point"}
}