{
  "type": "Feature",
  "properties": {
    "iso:country":"GB",
    "wof:name":"WF12 9HB",
    "wof:placetype":"postalcode"
},
  "geometry": {"coordinates":[-1.63912690974215,53.67164598855291],"type":"Point"}
}