{
  "type": "Feature",
  "properties": {
    "iso:country": "GB",
    "wof:name": "SN2 2DF",
    "wof:placetype": "postalcode"
  },
  "geometry": {"coordinates":[-1.803194,51.559738],"type":"Point"}
}
