{
  "type": "Feature",
  "properties": {
    "iso:country":"GB",
    "wof:name":"SW19 8TA",
    "wof:placetype":"postalcode"
},
  "geometry": {"coordinates":[-0.19073960534324,51.42114156339267],"type":"Point"}
}