{
  "type": "Feature",
  "properties": {
    "date:inception_lower":"1980-01-01",
    "date:inception_upper":"1980-01-31",
    "iso:country":"GB",
    "wof:name":"G15 6LG",
    "wof:placetype":"postalcode"
},
  "geometry": {"coordinates":[-4.352516,55.904892],"type":"Point"}
}