{
  "type": "Feature",
  "properties": {
    "iso:country":"GB",
    "wof:name":"G15 6LG",
    "wof:placetype":"postalcode"
},
  "geometry": {"coordinates":[-4.35251623116303,55.90489219719483],"type":"Point"}
}