{
  "type": "Feature",
  "properties": {
    "iso:country":"GB",
    "wof:name":"EX6 6QR",
    "wof:placetype":"postalcode"
},
  "geometry": {"coordinates":[-3.79249454202342,50.70345697115694],"type":"Point"}
}