{
  "type": "Feature",
  "properties": {
    "iso:country": "GB",
    "wof:name": "IV30 1DA",
    "wof:placetype": "postalcode"
  },
  "geometry": {"coordinates":[-3.310366,57.64731],"type":"Point"}
}
