{
  "type": "Feature",
  "properties": {
    "iso:country":"GB",
    "wof:name":"GL51 8LJ",
    "wof:placetype":"postalcode"
},
  "geometry": {"coordinates":[-2.09888683380535,51.90765478792873],"type":"Point"}
}