{
  "type": "Feature",
  "properties": {
    "iso:country":"GB",
    "wof:name":"WS11 6NE",
    "wof:placetype":"postalcode"
},
  "geometry": {"coordinates":[-2.01639705156383,52.69772079784592],"type":"Point"}
}