{
  "type": "Feature",
  "properties": {
    "iso:country":"GB",
    "wof:name":"NR32 4JL",
    "wof:placetype":"postalcode"
},
  "geometry": {"coordinates":[1.73589959773594,52.4953818181997],"type":"Point"}
}