{
  "type": "Feature",
  "properties": {
    "iso:country":"GB",
    "wof:name":"W1U 2DL",
    "wof:placetype":"postalcode"
},
  "geometry": {"coordinates":[-0.15025603144381,51.51857344426543],"type":"Point"}
}