{
  "type": "Feature",
  "properties": {
    "date:inception_lower": "1985-10-01",
    "date:inception_upper": "1985-10-01",
    "iso:country": "GB",
    "wof:name": "TS19 0SL",
    "wof:placetype": "postalcode"
  },
  "geometry": {"coordinates":[-1.348127,54.569954],"type":"Point"}
}
