{
  "type": "Feature",
  "properties": {
    "iso:country":"GB",
    "wof:name":"TS19 0SL",
    "wof:placetype":"postalcode"
},
  "geometry": {"coordinates":[-1.34812705101704,54.56995435103747],"type":"Point"}
}