{
  "type": "Feature",
  "properties": {
    "iso:country": "GB",
    "wof:name": "BH23 8HE",
    "wof:placetype": "postalcode"
  },
  "geometry": {"coordinates":[-1.753691,50.780837],"type":"Point"}
}
