{
  "type": "Feature",
  "properties": {
    "date:inception_lower":"1980-01-01",
    "date:inception_upper":"1980-01-31",
    "iso:country":"GB",
    "wof:name":"SS8 9AT",
    "wof:placetype":"postalcode"
},
  "geometry": {"coordinates":[0.585044,51.524752],"type":"Point"}
}