{
  "type": "Feature",
  "properties": {
    "date:inception_lower": "2017-10-01",
    "date:inception_upper": "2017-10-01",
    "iso:country": "GB",
    "wof:name": "MK9 3DX",
    "wof:placetype": "postalcode"
  },
  "geometry": {"coordinates":[-0.758303,52.040785],"type":"Point"}
}
