{
  "type": "Feature",
  "properties": {
    "iso:country":"GB",
    "wof:name":"SW18 5EQ",
    "wof:placetype":"postalcode"
},
  "geometry": {"coordinates":[-0.19831120317219,51.45096958199741],"type":"Point"}
}