{
  "type": "Feature",
  "properties": {
    "iso:country": "GB",
    "wof:name": "HD4 5BX",
    "wof:placetype": "postalcode"
  },
  "geometry": {"coordinates":[-1.836872,53.635601],"type":"Point"}
}
