{
  "type": "Feature",
  "properties": {
    "iso:country":"GB",
    "wof:name":"OX7 6QJ",
    "wof:placetype":"postalcode"
},
  "geometry": {"coordinates":[-1.59708056447726,51.88176134923553],"type":"Point"}
}