{
  "type": "Feature",
  "properties": {
    "iso:country": "GB",
    "wof:name": "OX7 6QJ",
    "wof:placetype": "postalcode"
  },
  "geometry": {"coordinates":[-1.597081,51.881761],"type":"Point"}
}
