{
  "type": "Feature",
  "properties": {
    "iso:country":"GB",
    "wof:name":"NW6 2BT",
    "wof:placetype":"postalcode"
},
  "geometry": {"coordinates":[-0.19854166489459,51.54304695996287],"type":"Point"}
}