{
  "type": "Feature",
  "properties": {
    "date:inception_lower": "1980-01-01",
    "date:inception_upper": "1980-01-01",
    "iso:country": "GB",
    "wof:name": "L8 2UP",
    "wof:placetype": "postalcode"
  },
  "geometry": {"coordinates":[-2.957549,53.391738],"type":"Point"}
}
