{
  "type": "Feature",
  "properties": {
    "iso:country":"GB",
    "wof:name":"TR1 2AR",
    "wof:placetype":"postalcode"
},
  "geometry": {"coordinates":[-5.05284481478186,50.26410950518295],"type":"Point"}
}