{
  "type": "Feature",
  "properties": {
    "date:inception_lower": "2016-02-01",
    "date:inception_upper": "2016-02-01",
    "iso:country": "GB",
    "wof:name": "DL1 3AH",
    "wof:placetype": "postalcode"
  },
  "geometry": {"coordinates":[-1.540731,54.553936],"type":"Point"}
}
