{
  "type": "Feature",
  "properties": {
    "iso:country":"GB",
    "wof:name":"DL1 3AH",
    "wof:placetype":"postalcode"
},
  "geometry": {"coordinates":[-1.54070280500587,54.55430212630915],"type":"Point"}
}