{
  "type": "Feature",
  "properties": {
    "iso:country": "GB",
    "wof:name": "BA21 5UA",
    "wof:placetype": "postalcode"
  },
  "geometry": {"coordinates":[-2.611388,50.956118],"type":"Point"}
}
