{
  "type": "Feature",
  "properties": {
    "iso:country":"GB",
    "wof:name":"SG2 7AR",
    "wof:placetype":"postalcode"
},
  "geometry": {"coordinates":[-0.08406429488447,51.92928557426487],"type":"Point"}
}