{
  "type": "Feature",
  "properties": {
    "iso:country":"GB",
    "wof:name":"YO11 3DB",
    "wof:placetype":"postalcode"
},
  "geometry": {"coordinates":[-0.41546363810076,54.24077468920237],"type":"Point"}
}