{
  "type": "Feature",
  "properties": {
    "iso:country":"GB",
    "wof:name":"AB45 2RZ",
    "wof:placetype":"postalcode"
},
  "geometry": {"coordinates":[-2.59541025603631,57.66285655452513],"type":"Point"}
}