{
  "type": "Feature",
  "properties": {
    "iso:country": "GB",
    "wof:name": "EH22 1QB",
    "wof:placetype": "postalcode"
  },
  "geometry": {"coordinates":[-3.108059,55.911451],"type":"Point"}
}
