{
  "type": "Feature",
  "properties": {
    "iso:country":"GB",
    "wof:name":"EH22 1QB",
    "wof:placetype":"postalcode"
},
  "geometry": {"coordinates":[-3.10805686822293,55.91146417831186],"type":"Point"}
}