{
  "type": "Feature",
  "properties": {
    "iso:country": "GB",
    "wof:name": "TS19 0QF",
    "wof:placetype": "postalcode"
  },
  "geometry": {"coordinates":[-1.342067,54.572618],"type":"Point"}
}
