{
  "type": "Feature",
  "properties": {
    "iso:country":"GB",
    "wof:name":"TS19 0QF",
    "wof:placetype":"postalcode"
},
  "geometry": {"coordinates":[-1.34206729351633,54.5726176671205],"type":"Point"}
}