{
  "type": "Feature",
  "properties": {
    "iso:country":"GB",
    "wof:name":"KT14 7PE",
    "wof:placetype":"postalcode"
},
  "geometry": {"coordinates":[-0.47598256046538,51.33790871751599],"type":"Point"}
}