{
  "type": "Feature",
  "properties": {
    "iso:country": "GB",
    "wof:name": "KT14 7PE",
    "wof:placetype": "postalcode"
  },
  "geometry": {"coordinates":[-0.475983,51.337909],"type":"Point"}
}
