{
  "type": "Feature",
  "properties": {
    "iso:country":"GB",
    "wof:name":"NE37 2NN",
    "wof:placetype":"postalcode"
},
  "geometry": {"coordinates":[-1.5198748851931,54.92104738108765],"type":"Point"}
}