{
  "type": "Feature",
  "properties": {
    "date:inception_lower": "1980-01-01",
    "date:inception_upper": "1980-01-01",
    "iso:country": "GB",
    "wof:name": "NE37 2NN",
    "wof:placetype": "postalcode"
  },
  "geometry": {"coordinates":[-1.519875,54.921047],"type":"Point"}
}
