{
  "type": "Feature",
  "properties": {
    "date:inception_lower": "2016-09-01",
    "date:inception_upper": "2016-09-01",
    "iso:country": "GB",
    "wof:name": "ZE1 0GR",
    "wof:placetype": "postalcode"
  },
  "geometry": {"coordinates":[-1.162915,60.156609],"type":"Point"}
}
