{
  "type": "Feature",
  "properties": {
    "iso:country": "GB",
    "wof:name": "GU12 5GN",
    "wof:placetype": "postalcode"
  },
  "geometry": {"coordinates":[-0.728272,51.274296],"type":"Point"}
}
