{
  "type": "Feature",
  "properties": {
    "date:inception_lower": "2001-06-01",
    "date:inception_upper": "2001-06-01",
    "iso:country": "GB",
    "wof:name": "GU12 5GN",
    "wof:placetype": "postalcode"
  },
  "geometry": {"coordinates":[-0.728272,51.274296],"type":"Point"}
}
