{
  "type": "Feature",
  "properties": {
    "iso:country":"GB",
    "wof:name":"GU12 5GN",
    "wof:placetype":"postalcode"
},
  "geometry": {"coordinates":[-0.72827234996807,51.27429567198089],"type":"Point"}
}