{
  "type": "Feature",
  "properties": {
    "iso:country":"GB",
    "wof:name":"BD13 4NP",
    "wof:placetype":"postalcode"
},
  "geometry": {"coordinates":[-1.90206426146661,53.80085795203902],"type":"Point"}
}