{
  "type": "Feature",
  "properties": {
    "date:inception_lower": "2003-11-01",
    "date:inception_upper": "2003-11-01",
    "iso:country": "GB",
    "wof:name": "BD13 4NP",
    "wof:placetype": "postalcode"
  },
  "geometry": {"coordinates":[-1.902064,53.800858],"type":"Point"}
}
