{
  "type": "Feature",
  "properties": {
    "iso:country": "GB",
    "wof:name": "TS7 0LQ",
    "wof:placetype": "postalcode"
  },
  "geometry": {"coordinates":[-1.169427,54.535806],"type":"Point"}
}
