{
  "type": "Feature",
  "properties": {
    "iso:country":"GB",
    "wof:name":"TS7 0LQ",
    "wof:placetype":"postalcode"
},
  "geometry": {"coordinates":[-1.16942704682134,54.53580552988422],"type":"Point"}
}