{
  "type": "Feature",
  "properties": {
    "iso:country":"GB",
    "wof:name":"G75 0ZY",
    "wof:placetype":"postalcode"
},
  "geometry": {"coordinates":[-4.16933309958917,55.73547582298875],"type":"Point"}
}