{
  "type": "Feature",
  "properties": {
    "iso:country": "GB",
    "wof:name": "G75 0ZY",
    "wof:placetype": "postalcode"
  },
  "geometry": {"coordinates":[-4.169296,55.73505],"type":"Point"}
}
