{
  "type": "Feature",
  "properties": {
    "iso:country":"GB",
    "wof:name":"WS6 6EL",
    "wof:placetype":"postalcode"
},
  "geometry": {"coordinates":[-2.0138538686888,52.65786998466515],"type":"Point"}
}