{
  "type": "Feature",
  "properties": {
    "iso:country":"GB",
    "wof:name":"DN17 2RH",
    "wof:placetype":"postalcode"
},
  "geometry": {"coordinates":[-0.65994448197321,53.54921272347374],"type":"Point"}
}