{
  "type": "Feature",
  "properties": {
    "date:inception_lower": "1980-01-01",
    "date:inception_upper": "1980-01-01",
    "iso:country": "GB",
    "wof:name": "DN17 2RH",
    "wof:placetype": "postalcode"
  },
  "geometry": {"coordinates":[-0.659944,53.549213],"type":"Point"}
}
