{
  "type": "Feature",
  "properties": {
    "iso:country": "GB",
    "wof:name": "SS0 7AU",
    "wof:placetype": "postalcode"
  },
  "geometry": {"coordinates":[0.69996,51.541705],"type":"Point"}
}
