{
  "type": "Feature",
  "properties": {
    "iso:country":"GB",
    "wof:name":"RG19 4GW",
    "wof:placetype":"postalcode"
},
  "geometry": {"coordinates":[-1.24368959929459,51.40190241221943],"type":"Point"}
}