{
  "type": "Feature",
  "properties": {
    "iso:country":"GB",
    "wof:name":"SL7 1NU",
    "wof:placetype":"postalcode"
},
  "geometry": {"coordinates":[-0.77310808631629,51.56897561353152],"type":"Point"}
}