{
  "type": "Feature",
  "properties": {
    "date:inception_lower": "1981-09-01",
    "date:inception_upper": "1981-09-01",
    "iso:country": "GB",
    "wof:name": "SL7 1NU",
    "wof:placetype": "postalcode"
  },
  "geometry": {"coordinates":[-0.773108,51.568976],"type":"Point"}
}
