{
  "type": "Feature",
  "properties": {
    "iso:country": "GB",
    "wof:name": "SL7 1NU",
    "wof:placetype": "postalcode"
  },
  "geometry": {"coordinates":[-0.773108,51.568976],"type":"Point"}
}
