{
  "type": "Feature",
  "properties": {
    "date:inception_lower": "1980-01-01",
    "date:inception_upper": "1980-01-01",
    "iso:country": "GB",
    "wof:name": "BA14 9DT",
    "wof:placetype": "postalcode"
  },
  "geometry": {"coordinates":[-2.226832,51.316713],"type":"Point"}
}
