{
  "type": "Feature",
  "properties": {
    "iso:country":"GB",
    "wof:name":"BA14 9DT",
    "wof:placetype":"postalcode"
},
  "geometry": {"coordinates":[-2.22683194202555,51.31671262618209],"type":"Point"}
}