{
  "type": "Feature",
  "properties": {
    "iso:country": "GB",
    "wof:name": "NN6 7DB",
    "wof:placetype": "postalcode"
  },
  "geometry": {"coordinates":[-1.068067,52.342138],"type":"Point"}
}
