{
  "type": "Feature",
  "properties": {
    "date:inception_lower": "2017-03-01",
    "date:inception_upper": "2017-03-01",
    "iso:country": "GB",
    "wof:name": "NN6 7DB",
    "wof:placetype": "postalcode"
  },
  "geometry": {"coordinates":[-1.068067,52.342138],"type":"Point"}
}
