{
  "type": "Feature",
  "properties": {
    "iso:country":"GB",
    "wof:name":"L15 4HF",
    "wof:placetype":"postalcode"
},
  "geometry": {"coordinates":[-2.92296888227189,53.40240315092212],"type":"Point"}
}