{
  "type": "Feature",
  "properties": {
    "iso:country":"GB",
    "wof:name":"N7 8QG",
    "wof:placetype":"postalcode"
},
  "geometry": {"coordinates":[-0.11053271218682,51.54953995890005],"type":"Point"}
}