{
  "type": "Feature",
  "properties": {
    "date:inception_lower": "2004-09-01",
    "date:inception_upper": "2004-09-01",
    "iso:country": "GB",
    "wof:name": "EX4 3DS",
    "wof:placetype": "postalcode"
  },
  "geometry": {"coordinates":[-3.536232,50.719824],"type":"Point"}
}
