{
  "type": "Feature",
  "properties": {
    "iso:country":"GB",
    "wof:name":"HU18 1BT",
    "wof:placetype":"postalcode"
},
  "geometry": {"coordinates":[-0.18254456691398,53.91043372513386],"type":"Point"}
}