{
  "type": "Feature",
  "properties": {
    "date:inception_lower":"2002-06-01",
    "date:inception_upper":"2002-06-30",
    "iso:country":"GB",
    "wof:name":"PE31 7UG",
    "wof:placetype":"postalcode"
},
  "geometry": {"coordinates":[0.49239,52.873376],"type":"Point"}
}