{
  "type": "Feature",
  "properties": {
    "iso:country":"GB",
    "wof:name":"PE31 7UG",
    "wof:placetype":"postalcode"
},
  "geometry": {"coordinates":[0.49239014617159,52.87337559311763],"type":"Point"}
}