{
  "type": "Feature",
  "properties": {
    "iso:country":"GB",
    "wof:name":"HU3 1HH",
    "wof:placetype":"postalcode"
},
  "geometry": {"coordinates":[-0.36032514958469,53.74696590098051],"type":"Point"}
}