{
  "type": "Feature",
  "properties": {
    "date:inception_lower": "2008-08-01",
    "date:inception_upper": "2008-08-01",
    "iso:country": "GB",
    "wof:name": "CB6 3GG",
    "wof:placetype": "postalcode"
  },
  "geometry": {"coordinates":[0.245885,52.393561],"type":"Point"}
}
