{
  "type": "Feature",
  "properties": {
    "iso:country":"GB",
    "wof:name":"CB6 3GG",
    "wof:placetype":"postalcode"
},
  "geometry": {"coordinates":[0.24588462358762,52.39356127837155],"type":"Point"}
}