{
  "type": "Feature",
  "properties": {
    "iso:country":"GB",
    "wof:name":"L17 4JA",
    "wof:placetype":"postalcode"
},
  "geometry": {"coordinates":[-2.94302136177767,53.38143707562499],"type":"Point"}
}