{
  "type": "Feature",
  "properties": {
    "iso:country": "GB",
    "wof:name": "TN11 9PQ",
    "wof:placetype": "postalcode"
  },
  "geometry": {"coordinates":[0.284182,51.246345],"type":"Point"}
}
