{
  "type": "Feature",
  "properties": {
    "iso:country":"GB",
    "wof:name":"TN11 9PQ",
    "wof:placetype":"postalcode"
},
  "geometry": {"coordinates":[0.28418189780321,51.24634504214391],"type":"Point"}
}