{
  "type": "Feature",
  "properties": {
    "date:inception_lower":"1996-06-01",
    "date:inception_upper":"1996-06-30",
    "iso:country":"GB",
    "wof:name":"TD7 5DZ",
    "wof:placetype":"postalcode"
},
  "geometry": {"coordinates":[-2.841678,55.553365],"type":"Point"}
}