{
  "type": "Feature",
  "properties": {
    "iso:country":"GB",
    "wof:name":"TD7 5DZ",
    "wof:placetype":"postalcode"
},
  "geometry": {"coordinates":[-2.84167824460273,55.55336548486832],"type":"Point"}
}