{
  "type": "Feature",
  "properties": {
    "iso:country": "GB",
    "wof:name": "CV4 8AQ",
    "wof:placetype": "postalcode"
  },
  "geometry": {"coordinates":[-1.596676,52.39147],"type":"Point"}
}
