{
  "type": "Feature",
  "properties": {
    "date:inception_lower": "1980-01-01",
    "date:inception_upper": "1980-01-01",
    "iso:country": "GB",
    "wof:name": "CV4 8AQ",
    "wof:placetype": "postalcode"
  },
  "geometry": {"coordinates":[-1.596338,52.391961],"type":"Point"}
}
