{
  "type": "Feature",
  "properties": {
    "iso:country":"GB",
    "wof:name":"G20 0JD",
    "wof:placetype":"postalcode"
},
  "geometry": {"coordinates":[-4.29526489219047,55.89801020256716],"type":"Point"}
}