{
  "type": "Feature",
  "properties": {
    "iso:country": "GB",
    "wof:name": "ST10 2DW",
    "wof:placetype": "postalcode"
  },
  "geometry": {"coordinates":[-1.983167,52.998812],"type":"Point"}
}
