{
  "type": "Feature",
  "properties": {
    "iso:country":"GB",
    "wof:name":"N19 3BP",
    "wof:placetype":"postalcode"
},
  "geometry": {"coordinates":[-0.13109335133723,51.57294391336342],"type":"Point"}
}