{
  "type": "Feature",
  "properties": {
    "iso:country": "GB",
    "wof:name": "N19 3BP",
    "wof:placetype": "postalcode"
  },
  "geometry": {"coordinates":[-0.131093,51.572944],"type":"Point"}
}
