{
  "type": "Feature",
  "properties": {
    "iso:country":"GB",
    "wof:name":"E15 2LX",
    "wof:placetype":"postalcode"
},
  "geometry": {"coordinates":[-0.00611551111577,51.53710158174496],"type":"Point"}
}