{
  "type": "Feature",
  "properties": {
    "iso:country":"GB",
    "wof:name":"LL11 5AT",
    "wof:placetype":"postalcode"
},
  "geometry": {"coordinates":[-3.05996772795099,53.07634034080587],"type":"Point"}
}