{
  "type": "Feature",
  "properties": {
    "iso:country":"GB",
    "wof:name":"B63 2UA",
    "wof:placetype":"postalcode"
},
  "geometry": {"coordinates":[-2.08685980040505,52.4660766275416],"type":"Point"}
}