{
  "type": "Feature",
  "properties": {
    "iso:country":"GB",
    "wof:name":"WA16 0AR",
    "wof:placetype":"postalcode"
},
  "geometry": {"coordinates":[-2.3877507352222,53.30283471551294],"type":"Point"}
}