{
  "type": "Feature",
  "properties": {
    "iso:country": "GB",
    "wof:name": "WA16 0AR",
    "wof:placetype": "postalcode"
  },
  "geometry": {"coordinates":[-2.387751,53.302835],"type":"Point"}
}
