{
  "type": "Feature",
  "properties": {
    "iso:country":"GB",
    "wof:name":"BS4 2TS",
    "wof:placetype":"postalcode"
},
  "geometry": {"coordinates":[-2.57282105121999,51.43043642782565],"type":"Point"}
}