{
  "type": "Feature",
  "properties": {
    "iso:country":"GB",
    "wof:name":"DG8 0NY",
    "wof:placetype":"postalcode"
},
  "geometry": {"coordinates":[-4.80933431062074,54.88422756408261],"type":"Point"}
}