{
  "type": "Feature",
  "properties": {
    "date:inception_lower": "1980-01-01",
    "date:inception_upper": "1980-01-01",
    "iso:country": "GB",
    "wof:name": "G41 1HJ",
    "wof:placetype": "postalcode"
  },
  "geometry": {"coordinates":[-4.277758,55.852311],"type":"Point"}
}
