{
  "type": "Feature",
  "properties": {
    "iso:country":"GB",
    "wof:name":"ST7 3PA",
    "wof:placetype":"postalcode"
},
  "geometry": {"coordinates":[-2.21580824413104,53.11378478785126],"type":"Point"}
}