{
  "type": "Feature",
  "properties": {
    "iso:country": "GB",
    "wof:name": "AB31 5QW",
    "wof:placetype": "postalcode"
  },
  "geometry": {"coordinates":[-2.491682,57.054257],"type":"Point"}
}
