{
  "type": "Feature",
  "properties": {
    "date:inception_lower":"2000-06-01",
    "date:inception_upper":"2000-06-30",
    "iso:country":"GB",
    "wof:name":"AB31 5QW",
    "wof:placetype":"postalcode"
},
  "geometry": {"coordinates":[-2.491682,57.054257],"type":"Point"}
}