{
  "type": "Feature",
  "properties": {
    "iso:country":"GB",
    "wof:name":"AB31 5QW",
    "wof:placetype":"postalcode"
},
  "geometry": {"coordinates":[-2.4916825074151,57.05425662451729],"type":"Point"}
}