{
  "type": "Feature",
  "properties": {
    "iso:country": "GB",
    "wof:name": "CM6 3NG",
    "wof:placetype": "postalcode"
  },
  "geometry": {"coordinates":[0.459165,51.860167],"type":"Point"}
}
