{
  "type": "Feature",
  "properties": {
    "iso:country":"GB",
    "wof:name":"CM6 3NG",
    "wof:placetype":"postalcode"
},
  "geometry": {"coordinates":[0.45916509869554,51.86016731322352],"type":"Point"}
}