{
  "type": "Feature",
  "properties": {
    "iso:country":"GB",
    "wof:name":"SW11 5HN",
    "wof:placetype":"postalcode"
},
  "geometry": {"coordinates":[-0.15395886478448,51.47403789986358],"type":"Point"}
}