{
  "type": "Feature",
  "properties": {
    "date:inception_lower":"1980-01-01",
    "date:inception_upper":"1980-01-31",
    "iso:country":"GB",
    "wof:name":"SW11 5HN",
    "wof:placetype":"postalcode"
},
  "geometry": {"coordinates":[-0.153959,51.474038],"type":"Point"}
}