{
  "type": "Feature",
  "properties": {
    "iso:country": "GB",
    "wof:name": "EX39 1FJ",
    "wof:placetype": "postalcode"
  },
  "geometry": {"coordinates":[-4.197157,51.057005],"type":"Point"}
}
