{
  "type": "Feature",
  "properties": {
    "iso:country": "GB",
    "wof:name": "GL6 0YQ",
    "wof:placetype": "postalcode"
  },
  "geometry": {"coordinates":[-2.221567,51.752852],"type":"Point"}
}
