{
  "type": "Feature",
  "properties": {
    "date:inception_lower": "2000-06-01",
    "date:inception_upper": "2000-06-01",
    "iso:country": "GB",
    "wof:name": "PE29 1UT",
    "wof:placetype": "postalcode"
  },
  "geometry": {"coordinates":[-0.171245,52.334297],"type":"Point"}
}
