{
  "type": "Feature",
  "properties": {
    "iso:country":"GB",
    "wof:name":"ST10 3DN",
    "wof:placetype":"postalcode"
},
  "geometry": {"coordinates":[-1.90502365161673,53.00901372009729],"type":"Point"}
}