{
  "type": "Feature",
  "properties": {
    "iso:country":"GB",
    "wof:name":"PO40 9QX",
    "wof:placetype":"postalcode"
},
  "geometry": {"coordinates":[-1.51147976166813,50.67147190549071],"type":"Point"}
}