{
  "type": "Feature",
  "properties": {
    "iso:country": "GB",
    "wof:name": "ST15 8XJ",
    "wof:placetype": "postalcode"
  },
  "geometry": {"coordinates":[-2.124781,52.897375],"type":"Point"}
}
