{
  "type": "Feature",
  "properties": {
    "iso:country":"GB",
    "wof:name":"ST15 8XJ",
    "wof:placetype":"postalcode"
},
  "geometry": {"coordinates":[-2.12478112266978,52.89737527440244],"type":"Point"}
}