{
  "type": "Feature",
  "properties": {
    "date:inception_lower":"1991-01-01",
    "date:inception_upper":"1991-01-31",
    "iso:country":"GB",
    "wof:name":"ST15 8XJ",
    "wof:placetype":"postalcode"
},
  "geometry": {"coordinates":[-2.124781,52.897375],"type":"Point"}
}