{
  "type": "Feature",
  "properties": {
    "date:inception_lower": "2022-06-01",
    "date:inception_upper": "2022-06-01",
    "iso:country": "GB",
    "wof:name": "BB9 6ET",
    "wof:placetype": "postalcode"
  },
  "geometry": {"coordinates":[-2.228806,53.843682],"type":"Point"}
}
