{
  "type": "Feature",
  "properties": {
    "iso:country":"GB",
    "wof:name":"SA3 4TB",
    "wof:placetype":"postalcode"
},
  "geometry": {"coordinates":[-4.01422517478229,51.57115079715524],"type":"Point"}
}