{
  "type": "Feature",
  "properties": {
    "iso:country": "GB",
    "wof:name": "EX10 9LJ",
    "wof:placetype": "postalcode"
  },
  "geometry": {"coordinates":[-3.234308,50.696299],"type":"Point"}
}
