{
  "type": "Feature",
  "properties": {
    "date:inception_lower": "1980-01-01",
    "date:inception_upper": "1980-01-01",
    "iso:country": "GB",
    "wof:name": "EX10 9LJ",
    "wof:placetype": "postalcode"
  },
  "geometry": {"coordinates":[-3.234308,50.696299],"type":"Point"}
}
