{
  "type": "Feature",
  "properties": {
    "iso:country":"GB",
    "wof:name":"WV13 1EX",
    "wof:placetype":"postalcode"
},
  "geometry": {"coordinates":[-2.05342066310619,52.58981533255572],"type":"Point"}
}