{
  "type": "Feature",
  "properties": {
    "iso:country": "GB",
    "wof:name": "PE11 2FE",
    "wof:placetype": "postalcode"
  },
  "geometry": {"coordinates":[-0.159644,52.77894],"type":"Point"}
}
