{
  "type": "Feature",
  "properties": {
    "date:inception_lower": "1998-12-01",
    "date:inception_upper": "1998-12-01",
    "iso:country": "GB",
    "wof:name": "PE11 2FE",
    "wof:placetype": "postalcode"
  },
  "geometry": {"coordinates":[-0.159644,52.77894],"type":"Point"}
}
