{
  "type": "Feature",
  "properties": {
    "date:inception_lower": "1980-01-01",
    "date:inception_upper": "1980-01-01",
    "iso:country": "GB",
    "wof:name": "SA10 7PH",
    "wof:placetype": "postalcode"
  },
  "geometry": {"coordinates":[-3.813683,51.675406],"type":"Point"}
}
