{
  "type": "Feature",
  "properties": {
    "iso:country": "GB",
    "wof:name": "SA10 7PH",
    "wof:placetype": "postalcode"
  },
  "geometry": {"coordinates":[-3.813683,51.675406],"type":"Point"}
}
