{
  "type": "Feature",
  "properties": {
    "date:inception_lower": "2018-08-01",
    "date:inception_upper": "2018-08-01",
    "iso:country": "GB",
    "wof:name": "WD19 4FT",
    "wof:placetype": "postalcode"
  },
  "geometry": {"coordinates":[-0.378865,51.639722],"type":"Point"}
}
