{
  "type": "Feature",
  "properties": {
    "date:inception_lower":"2008-03-01",
    "date:inception_upper":"2008-03-31",
    "iso:country":"GB",
    "wof:name":"KT16 8EU",
    "wof:placetype":"postalcode"
},
  "geometry": {"coordinates":[-0.505037,51.386077],"type":"Point"}
}