{
  "type": "Feature",
  "properties": {
    "iso:country":"GB",
    "wof:name":"KT16 8EU",
    "wof:placetype":"postalcode"
},
  "geometry": {"coordinates":[-0.50503733935878,51.38607744914125],"type":"Point"}
}