{
  "type": "Feature",
  "properties": {
    "iso:country": "GB",
    "wof:name": "PH1 5NQ",
    "wof:placetype": "postalcode"
  },
  "geometry": {"coordinates":[-3.426406,56.395355],"type":"Point"}
}
