{
  "type": "Feature",
  "properties": {
    "date:inception_lower": "1980-01-01",
    "date:inception_upper": "1980-01-01",
    "iso:country": "GB",
    "wof:name": "S3 9AS",
    "wof:placetype": "postalcode"
  },
  "geometry": {"coordinates":[-1.4667,53.399506],"type":"Point"}
}
