{
  "type": "Feature",
  "properties": {
    "iso:country": "GB",
    "wof:name": "BN16 1JJ",
    "wof:placetype": "postalcode"
  },
  "geometry": {"coordinates":[-0.48189,50.811143],"type":"Point"}
}
