{
  "type": "Feature",
  "properties": {
    "iso:country":"GB",
    "wof:name":"SY13 3DG",
    "wof:placetype":"postalcode"
},
  "geometry": {"coordinates":[-2.81387125323264,52.95251685093415],"type":"Point"}
}