{
  "type": "Feature",
  "properties": {
    "iso:country": "GB",
    "wof:name": "SY13 3DG",
    "wof:placetype": "postalcode"
  },
  "geometry": {"coordinates":[-2.813871,52.952517],"type":"Point"}
}
