{
  "type": "Feature",
  "properties": {
    "date:inception_lower": "1980-01-01",
    "date:inception_upper": "1980-01-01",
    "iso:country": "GB",
    "wof:name": "NW4 4TE",
    "wof:placetype": "postalcode"
  },
  "geometry": {"coordinates":[-0.233972,51.597202],"type":"Point"}
}
