{
  "type": "Feature",
  "properties": {
    "iso:country":"GB",
    "wof:name":"NW4 4TE",
    "wof:placetype":"postalcode"
},
  "geometry": {"coordinates":[-0.23411019741475,51.59727188279787],"type":"Point"}
}