{
  "type": "Feature",
  "properties": {
    "iso:country": "GB",
    "wof:name": "NW4 4TE",
    "wof:placetype": "postalcode"
  },
  "geometry": {"coordinates":[-0.233972,51.597202],"type":"Point"}
}
