{
  "type": "Feature",
  "properties": {
    "iso:country":"GB",
    "wof:name":"PO19 7NU",
    "wof:placetype":"postalcode"
},
  "geometry": {"coordinates":[-0.76583507112007,50.83726226601686],"type":"Point"}
}