{
  "type": "Feature",
  "properties": {
    "date:inception_lower": "1986-02-01",
    "date:inception_upper": "1986-02-01",
    "iso:country": "GB",
    "wof:name": "FK2 8QB",
    "wof:placetype": "postalcode"
  },
  "geometry": {"coordinates":[-3.798992,56.037303],"type":"Point"}
}
