{
  "type": "Feature",
  "properties": {
    "iso:country": "GB",
    "wof:name": "FK2 8QB",
    "wof:placetype": "postalcode"
  },
  "geometry": {"coordinates":[-3.798992,56.037303],"type":"Point"}
}
