{
  "type": "Feature",
  "properties": {
    "date:inception_lower": "2017-03-01",
    "date:inception_upper": "2017-03-01",
    "iso:country": "GB",
    "wof:name": "EX37 9ER",
    "wof:placetype": "postalcode"
  },
  "geometry": {"coordinates":[-3.952153,50.944764],"type":"Point"}
}
