{
  "type": "Feature",
  "properties": {
    "iso:country":"GB",
    "wof:name":"EX34 0AA",
    "wof:placetype":"postalcode"
},
  "geometry": {"coordinates":[-4.02965724623339,51.20240143332684],"type":"Point"}
}