{
  "type": "Feature",
  "properties": {
    "iso:country": "GB",
    "wof:name": "BS32 0HW",
    "wof:placetype": "postalcode"
  },
  "geometry": {"coordinates":[-2.560874,51.543473],"type":"Point"}
}
