{
  "type": "Feature",
  "properties": {
    "iso:country":"GB",
    "wof:name":"BS32 0HW",
    "wof:placetype":"postalcode"
},
  "geometry": {"coordinates":[-2.56078608491559,51.54348284089598],"type":"Point"}
}