{
  "type": "Feature",
  "properties": {
    "date:inception_lower": "2013-08-01",
    "date:inception_upper": "2013-08-01",
    "iso:country": "GB",
    "wof:name": "DN2 4BG",
    "wof:placetype": "postalcode"
  },
  "geometry": {"coordinates":[-1.10788,53.541152],"type":"Point"}
}
