{
  "type": "Feature",
  "properties": {
    "iso:country": "GB",
    "wof:name": "DN2 4BG",
    "wof:placetype": "postalcode"
  },
  "geometry": {"coordinates":[-1.10788,53.541152],"type":"Point"}
}
