{
  "type": "Feature",
  "properties": {
    "iso:country": "GB",
    "wof:name": "GL17 9US",
    "wof:placetype": "postalcode"
  },
  "geometry": {"coordinates":[-2.552138,51.856247],"type":"Point"}
}
