{
  "type": "Feature",
  "properties": {
    "iso:country":"GB",
    "wof:name":"GL17 9US",
    "wof:placetype":"postalcode"
},
  "geometry": {"coordinates":[-2.55200650334948,51.85626721014724],"type":"Point"}
}