{
  "type": "Feature",
  "properties": {
    "iso:country": "GB",
    "wof:name": "SA11 5NX",
    "wof:placetype": "postalcode"
  },
  "geometry": {"coordinates":[-3.591701,51.755767],"type":"Point"}
}
