{
  "type": "Feature",
  "properties": {
    "iso:country":"GB",
    "wof:name":"SA11 5NX",
    "wof:placetype":"postalcode"
},
  "geometry": {"coordinates":[-3.5917009633288,51.75576697761883],"type":"Point"}
}