{
  "type": "Feature",
  "properties": {
    "date:inception_lower":"1994-12-01",
    "date:inception_upper":"1994-12-31",
    "iso:country":"GB",
    "wof:name":"SA11 5NX",
    "wof:placetype":"postalcode"
},
  "geometry": {"coordinates":[-3.591701,51.755767],"type":"Point"}
}