{
  "type": "Feature",
  "properties": {
    "iso:country":"GB",
    "wof:name":"LA12 8HW",
    "wof:placetype":"postalcode"
},
  "geometry": {"coordinates":[-3.05716961069843,54.28369463116587],"type":"Point"}
}