{
  "type": "Feature",
  "properties": {
    "date:inception_lower": "1980-01-01",
    "date:inception_upper": "1980-01-01",
    "iso:country": "GB",
    "wof:name": "LA12 8HW",
    "wof:placetype": "postalcode"
  },
  "geometry": {"coordinates":[-3.056304,54.280475],"type":"Point"}
}
