{
  "type": "Feature",
  "properties": {
    "date:inception_lower": "1980-01-01",
    "date:inception_upper": "1980-01-01",
    "iso:country": "GB",
    "wof:name": "LE9 7DS",
    "wof:placetype": "postalcode"
  },
  "geometry": {"coordinates":[-1.315119,52.578931],"type":"Point"}
}
