{
  "type": "Feature",
  "properties": {
    "iso:country": "GB",
    "wof:name": "CA15 8ER",
    "wof:placetype": "postalcode"
  },
  "geometry": {"coordinates":[-3.496083,54.704732],"type":"Point"}
}
