{
  "type": "Feature",
  "properties": {
    "iso:country": "GB",
    "wof:name": "DN3 2AD",
    "wof:placetype": "postalcode"
  },
  "geometry": {"coordinates":[-1.068457,53.539258],"type":"Point"}
}
