{
  "type": "Feature",
  "properties": {
    "iso:country":"GB",
    "wof:name":"DN3 2AD",
    "wof:placetype":"postalcode"
},
  "geometry": {"coordinates":[-1.06845672605573,53.53925797163643],"type":"Point"}
}