{
  "type": "Feature",
  "properties": {
    "iso:country":"GB",
    "wof:name":"NG18 1JA",
    "wof:placetype":"postalcode"
},
  "geometry": {"coordinates":[-1.19618638999505,53.14478085707321],"type":"Point"}
}