{
  "type": "Feature",
  "properties": {
    "iso:country":"GB",
    "wof:name":"SK5 8PB",
    "wof:placetype":"postalcode"
},
  "geometry": {"coordinates":[-2.13926519043479,53.43402464068046],"type":"Point"}
}