{
  "type": "Feature",
  "properties": {
    "iso:country":"GB",
    "wof:name":"OL6 6SE",
    "wof:placetype":"postalcode"
},
  "geometry": {"coordinates":[-2.07546285335615,53.48599951633447],"type":"Point"}
}