{
  "type": "Feature",
  "properties": {
    "iso:country": "GB",
    "wof:name": "SN10 5QP",
    "wof:placetype": "postalcode"
  },
  "geometry": {"coordinates":[-1.999334,51.320601],"type":"Point"}
}
