{
  "type": "Feature",
  "properties": {
    "iso:country": "GB",
    "wof:name": "MK42 9QZ",
    "wof:placetype": "postalcode"
  },
  "geometry": {"coordinates":[-0.478068,52.116045],"type":"Point"}
}
