{
  "type": "Feature",
  "properties": {
    "iso:country": "GB",
    "wof:name": "S74 0FJ",
    "wof:placetype": "postalcode"
  },
  "geometry": {"coordinates":[-1.436775,53.509758],"type":"Point"}
}
