{
  "type": "Feature",
  "properties": {
    "iso:country": "GB",
    "wof:name": "CT5 2SB",
    "wof:placetype": "postalcode"
  },
  "geometry": {"coordinates":[1.049926,51.36421],"type":"Point"}
}
