{
  "type": "Feature",
  "properties": {
    "iso:country":"GB",
    "wof:name":"CT5 2SB",
    "wof:placetype":"postalcode"
},
  "geometry": {"coordinates":[1.04992563105274,51.36420960511503],"type":"Point"}
}