{
  "type": "Feature",
  "properties": {
    "iso:country":"GB",
    "wof:name":"S62 6HJ",
    "wof:placetype":"postalcode"
},
  "geometry": {"coordinates":[-1.34643693629827,53.45382953456793],"type":"Point"}
}