{
  "type": "Feature",
  "properties": {
    "iso:country":"GB",
    "wof:name":"SW19 3HW",
    "wof:placetype":"postalcode"
},
  "geometry": {"coordinates":[-0.20539763971289,51.41154703623201],"type":"Point"}
}