{
  "type": "Feature",
  "properties": {
    "date:inception_lower": "2016-01-01",
    "date:inception_upper": "2016-01-01",
    "iso:country": "GB",
    "wof:name": "EH8 8FS",
    "wof:placetype": "postalcode"
  },
  "geometry": {"coordinates":[-3.184673,55.951325],"type":"Point"}
}
