{
  "type": "Feature",
  "properties": {
    "iso:country": "GB",
    "wof:name": "EH8 8FS",
    "wof:placetype": "postalcode"
  },
  "geometry": {"coordinates":[-3.184673,55.951325],"type":"Point"}
}
