{
  "type": "Feature",
  "properties": {
    "iso:country":"GB",
    "wof:name":"LL22 7TW",
    "wof:placetype":"postalcode"
},
  "geometry": {"coordinates":[-3.59124747271441,53.28644678273447],"type":"Point"}
}