{
  "type": "Feature",
  "properties": {
    "iso:country":"GB",
    "wof:name":"ME3 9HQ",
    "wof:placetype":"postalcode"
},
  "geometry": {"coordinates":[0.63457728095532,51.45122391019245],"type":"Point"}
}