{
  "type": "Feature",
  "properties": {
    "iso:country": "GB",
    "wof:name": "ME3 9HQ",
    "wof:placetype": "postalcode"
  },
  "geometry": {"coordinates":[0.634577,51.451224],"type":"Point"}
}
