{
  "type": "Feature",
  "properties": {
    "date:inception_lower": "1995-12-01",
    "date:inception_upper": "1995-12-01",
    "iso:country": "GB",
    "wof:name": "DG7 1TZ",
    "wof:placetype": "postalcode"
  },
  "geometry": {"coordinates":[-4.006139,54.900838],"type":"Point"}
}
