{
  "type": "Feature",
  "properties": {
    "iso:country":"GB",
    "wof:name":"TQ9 6BX",
    "wof:placetype":"postalcode"
},
  "geometry": {"coordinates":[-3.70332634356839,50.48378485556405],"type":"Point"}
}