{
  "type": "Feature",
  "properties": {
    "iso:country": "GB",
    "wof:name": "PA5 8UU",
    "wof:placetype": "postalcode"
  },
  "geometry": {"coordinates":[-4.537097,55.846964],"type":"Point"}
}
