{
  "type": "Feature",
  "properties": {
    "iso:country":"GB",
    "wof:name":"LE15 7FH",
    "wof:placetype":"postalcode"
},
  "geometry": {"coordinates":[-0.69411657643789,52.68227931801258],"type":"Point"}
}