{
  "type": "Feature",
  "properties": {
    "iso:country": "GB",
    "wof:name": "LE15 7FH",
    "wof:placetype": "postalcode"
  },
  "geometry": {"coordinates":[-0.694117,52.682279],"type":"Point"}
}
