{
  "type": "Feature",
  "properties": {
    "iso:country": "GB",
    "wof:name": "CO15 2AD",
    "wof:placetype": "postalcode"
  },
  "geometry": {"coordinates":[1.13361,51.794405],"type":"Point"}
}
