{
  "type": "Feature",
  "properties": {
    "iso:country": "GB",
    "wof:name": "BL6 5LA",
    "wof:placetype": "postalcode"
  },
  "geometry": {"coordinates":[-2.593597,53.601677],"type":"Point"}
}
