{
  "type": "Feature",
  "properties": {
    "date:inception_lower": "2011-07-01",
    "date:inception_upper": "2011-07-01",
    "iso:country": "GB",
    "wof:name": "FK16 6EF",
    "wof:placetype": "postalcode"
  },
  "geometry": {"coordinates":[-4.053179,56.193979],"type":"Point"}
}
