{
  "type": "Feature",
  "properties": {
    "iso:country": "GB",
    "wof:name": "GU4 7QG",
    "wof:placetype": "postalcode"
  },
  "geometry": {"coordinates":[-0.557148,51.287293],"type":"Point"}
}
