{
  "type": "Feature",
  "properties": {
    "date:inception_lower": "1980-01-01",
    "date:inception_upper": "1980-01-01",
    "iso:country": "GB",
    "wof:name": "S63 6JA",
    "wof:placetype": "postalcode"
  },
  "geometry": {"coordinates":[-1.352149,53.498067],"type":"Point"}
}
