{
  "type": "Feature",
  "properties": {
    "iso:country":"GB",
    "wof:name":"WA6 6AD",
    "wof:placetype":"postalcode"
},
  "geometry": {"coordinates":[-2.71869702641023,53.28993714788344],"type":"Point"}
}