{
  "type": "Feature",
  "properties": {
    "date:inception_lower": "1980-01-01",
    "date:inception_upper": "1980-01-01",
    "iso:country": "GB",
    "wof:name": "WA6 6AD",
    "wof:placetype": "postalcode"
  },
  "geometry": {"coordinates":[-2.718697,53.289937],"type":"Point"}
}
