{
  "type": "Feature",
  "properties": {
    "date:inception_lower": "2022-02-01",
    "date:inception_upper": "2022-02-01",
    "iso:country": "GB",
    "wof:name": "M24 0DP",
    "wof:placetype": "postalcode"
  },
  "geometry": {"coordinates":[-2.198784,53.547903],"type":"Point"}
}
