{
  "type": "Feature",
  "properties": {
    "date:inception_lower":"1980-01-01",
    "date:inception_upper":"1980-01-31",
    "iso:country":"GB",
    "wof:name":"NG3 6JQ",
    "wof:placetype":"postalcode"
},
  "geometry": {"coordinates":[-1.118823,52.965938],"type":"Point"}
}