{
  "type": "Feature",
  "properties": {
    "iso:country": "GB",
    "wof:name": "NG3 6JQ",
    "wof:placetype": "postalcode"
  },
  "geometry": {"coordinates":[-1.118823,52.965938],"type":"Point"}
}
