{
  "type": "Feature",
  "properties": {
    "iso:country":"GB",
    "wof:name":"NG3 6JQ",
    "wof:placetype":"postalcode"
},
  "geometry": {"coordinates":[-1.11882271549766,52.96593845739721],"type":"Point"}
}