{
  "type": "Feature",
  "properties": {
    "iso:country":"GB",
    "wof:name":"N17 9EU",
    "wof:placetype":"postalcode"
},
  "geometry": {"coordinates":[-0.06457644894979,51.59037222688271],"type":"Point"}
}