{
  "type": "Feature",
  "properties": {
    "iso:country":"GB",
    "wof:name":"BH20 4LZ",
    "wof:placetype":"postalcode"
},
  "geometry": {"coordinates":[-2.10898412770312,50.68474539725335],"type":"Point"}
}