{
  "type": "Feature",
  "properties": {
    "iso:country": "GB",
    "wof:name": "HP3 9QX",
    "wof:placetype": "postalcode"
  },
  "geometry": {"coordinates":[-0.467974,51.74067],"type":"Point"}
}
