{
  "type": "Feature",
  "properties": {
    "iso:country":"GB",
    "wof:name":"HP3 9QX",
    "wof:placetype":"postalcode"
},
  "geometry": {"coordinates":[-0.46797382468758,51.74066954420299],"type":"Point"}
}