{
  "type": "Feature",
  "properties": {
    "iso:country": "GB",
    "wof:name": "CW6 9EG",
    "wof:placetype": "postalcode"
  },
  "geometry": {"coordinates":[-2.631777,53.200288],"type":"Point"}
}
