{
  "type": "Feature",
  "properties": {
    "iso:country":"GB",
    "wof:name":"CW6 9EG",
    "wof:placetype":"postalcode"
},
  "geometry": {"coordinates":[-2.6317768690836,53.20028827510961],"type":"Point"}
}