{
  "type": "Feature",
  "properties": {
    "iso:country": "GB",
    "wof:name": "SO24 0LN",
    "wof:placetype": "postalcode"
  },
  "geometry": {"coordinates":[-1.125501,51.045478],"type":"Point"}
}
