{
  "type": "Feature",
  "properties": {
    "iso:country":"GB",
    "wof:name":"WD6 2RW",
    "wof:placetype":"postalcode"
},
  "geometry": {"coordinates":[-0.25662722649106,51.6423088539902],"type":"Point"}
}