{
  "type": "Feature",
  "properties": {
    "date:inception_lower": "1980-01-01",
    "date:inception_upper": "1980-01-01",
    "iso:country": "GB",
    "wof:name": "WD6 2RW",
    "wof:placetype": "postalcode"
  },
  "geometry": {"coordinates":[-0.256589,51.642312],"type":"Point"}
}
