{
  "type": "Feature",
  "properties": {
    "date:inception_lower": "1980-01-01",
    "date:inception_upper": "1980-01-01",
    "iso:country": "GB",
    "wof:name": "RH4 2HS",
    "wof:placetype": "postalcode"
  },
  "geometry": {"coordinates":[-0.329424,51.22745],"type":"Point"}
}
