{
  "type": "Feature",
  "properties": {
    "iso:country": "GB",
    "wof:name": "SL7 1NL",
    "wof:placetype": "postalcode"
  },
  "geometry": {"coordinates":[-0.771825,51.570386],"type":"Point"}
}
