{
  "type": "Feature",
  "properties": {
    "iso:country": "GB",
    "wof:name": "TN15 8FU",
    "wof:placetype": "postalcode"
  },
  "geometry": {"coordinates":[0.31665,51.277398],"type":"Point"}
}
