{
  "type": "Feature",
  "properties": {
    "iso:country": "GB",
    "wof:name": "MK45 4RW",
    "wof:placetype": "postalcode"
  },
  "geometry": {"coordinates":[-0.430354,51.97117],"type":"Point"}
}
