{
  "type": "Feature",
  "properties": {
    "date:inception_lower":"1996-06-01",
    "date:inception_upper":"1996-06-30",
    "iso:country":"GB",
    "wof:name":"MK45 4RW",
    "wof:placetype":"postalcode"
},
  "geometry": {"coordinates":[-0.430354,51.97117],"type":"Point"}
}