{
  "type": "Feature",
  "properties": {
    "date:inception_lower": "1980-01-01",
    "date:inception_upper": "1980-01-01",
    "iso:country": "GB",
    "wof:name": "WA4 1PT",
    "wof:placetype": "postalcode"
  },
  "geometry": {"coordinates":[-2.561841,53.383445],"type":"Point"}
}
