{
  "type": "Feature",
  "properties": {
    "iso:country":"GB",
    "wof:name":"WA4 1PT",
    "wof:placetype":"postalcode"
},
  "geometry": {"coordinates":[-2.56184104242213,53.38344481516327],"type":"Point"}
}