{
  "type": "Feature",
  "properties": {
    "iso:country":"GB",
    "wof:name":"LL65 1DU",
    "wof:placetype":"postalcode"
},
  "geometry": {"coordinates":[-4.63206818665927,53.3142673741115],"type":"Point"}
}