{
  "type": "Feature",
  "properties": {
    "date:inception_lower": "1990-07-01",
    "date:inception_upper": "1990-07-01",
    "iso:country": "GB",
    "wof:name": "BA14 0XB",
    "wof:placetype": "postalcode"
  },
  "geometry": {"coordinates":[-2.199316,51.302282],"type":"Point"}
}
