{
  "type": "Feature",
  "properties": {
    "iso:country":"GB",
    "wof:name":"TF7 5ES",
    "wof:placetype":"postalcode"
},
  "geometry": {"coordinates":[-2.45090411365765,52.6373604219295],"type":"Point"}
}