{
  "type": "Feature",
  "properties": {
    "date:inception_lower": "1980-01-01",
    "date:inception_upper": "1980-01-01",
    "iso:country": "GB",
    "wof:name": "TF7 5ES",
    "wof:placetype": "postalcode"
  },
  "geometry": {"coordinates":[-2.450904,52.63736],"type":"Point"}
}
