{
  "type": "Feature",
  "properties": {
    "iso:country": "GB",
    "wof:name": "LS22 4DY",
    "wof:placetype": "postalcode"
  },
  "geometry": {"coordinates":[-1.393449,53.945124],"type":"Point"}
}
