{
  "type": "Feature",
  "properties": {
    "iso:country":"GB",
    "wof:name":"LS22 4DY",
    "wof:placetype":"postalcode"
},
  "geometry": {"coordinates":[-1.39344889495574,53.94512362010812],"type":"Point"}
}