{
  "type": "Feature",
  "properties": {
    "date:inception_lower": "1980-01-01",
    "date:inception_upper": "1980-01-01",
    "iso:country": "GB",
    "wof:name": "G12 9XQ",
    "wof:placetype": "postalcode"
  },
  "geometry": {"coordinates":[-4.303691,55.880417],"type":"Point"}
}
