{
  "type": "Feature",
  "properties": {
    "iso:country":"GB",
    "wof:name":"G12 9XQ",
    "wof:placetype":"postalcode"
},
  "geometry": {"coordinates":[-4.30369153210345,55.8804169449319],"type":"Point"}
}