{
  "type": "Feature",
  "properties": {
    "iso:country":"GB",
    "wof:name":"MK40 4DH",
    "wof:placetype":"postalcode"
},
  "geometry": {"coordinates":[-0.5042572033031,52.13693460361089],"type":"Point"}
}