{
  "type": "Feature",
  "properties": {
    "date:inception_lower": "1980-01-01",
    "date:inception_upper": "1980-01-01",
    "iso:country": "GB",
    "wof:name": "PL3 4AU",
    "wof:placetype": "postalcode"
  },
  "geometry": {"coordinates":[-4.160688,50.38085],"type":"Point"}
}
