{
  "type": "Feature",
  "properties": {
    "date:inception_lower": "1980-01-01",
    "date:inception_upper": "1980-01-01",
    "iso:country": "GB",
    "wof:name": "BL4 8RW",
    "wof:placetype": "postalcode"
  },
  "geometry": {"coordinates":[-2.353322,53.530739],"type":"Point"}
}
