{
  "type": "Feature",
  "properties": {
    "iso:country": "GB",
    "wof:name": "HU13 0HN",
    "wof:placetype": "postalcode"
  },
  "geometry": {"coordinates":[-0.444879,53.724164],"type":"Point"}
}
