{
  "type": "Feature",
  "properties": {
    "iso:country":"GB",
    "wof:name":"HU13 0HN",
    "wof:placetype":"postalcode"
},
  "geometry": {"coordinates":[-0.44487867411392,53.72416397782757],"type":"Point"}
}