{
  "type": "Feature",
  "properties": {
    "iso:country": "GB",
    "wof:name": "NR1 2HZ",
    "wof:placetype": "postalcode"
  },
  "geometry": {"coordinates":[1.303292,52.610936],"type":"Point"}
}
