{
  "type": "Feature",
  "properties": {
    "iso:country":"GB",
    "wof:name":"SK4 5NJ",
    "wof:placetype":"postalcode"
},
  "geometry": {"coordinates":[-2.17130266075328,53.43583455867984],"type":"Point"}
}