{
  "type": "Feature",
  "properties": {
    "iso:country": "GB",
    "wof:name": "SK4 5NJ",
    "wof:placetype": "postalcode"
  },
  "geometry": {"coordinates":[-2.171331,53.435896],"type":"Point"}
}
