{
  "type": "Feature",
  "properties": {
    "iso:country":"GB",
    "wof:name":"PE9 3SG",
    "wof:placetype":"postalcode"
},
  "geometry": {"coordinates":[-0.55949880941116,52.6274066388513],"type":"Point"}
}