{
  "type": "Feature",
  "properties": {
    "iso:country":"GB",
    "wof:name":"M30 8FB",
    "wof:placetype":"postalcode"
},
  "geometry": {"coordinates":[-2.36217818600867,53.48835028807186],"type":"Point"}
}