{
  "type": "Feature",
  "properties": {
    "iso:country":"GB",
    "wof:name":"W4 5UQ",
    "wof:placetype":"postalcode"
},
  "geometry": {"coordinates":[-0.26200003326111,51.49370090206895],"type":"Point"}
}