{
  "type": "Feature",
  "properties": {
    "iso:country": "GB",
    "wof:name": "BL8 1DJ",
    "wof:placetype": "postalcode"
  },
  "geometry": {"coordinates":[-2.311161,53.603294],"type":"Point"}
}
