{
  "type": "Feature",
  "properties": {
    "iso:country":"GB",
    "wof:name":"OX10 9JW",
    "wof:placetype":"postalcode"
},
  "geometry": {"coordinates":[-1.17336641084497,51.55237146719637],"type":"Point"}
}