{
  "type": "Feature",
  "properties": {
    "date:inception_lower": "1980-01-01",
    "date:inception_upper": "1980-01-01",
    "iso:country": "GB",
    "wof:name": "TF12 5JY",
    "wof:placetype": "postalcode"
  },
  "geometry": {"coordinates":[-2.465803,52.590403],"type":"Point"}
}
