{
  "type": "Feature",
  "properties": {
    "iso:country": "GB",
    "wof:name": "DY9 8ND",
    "wof:placetype": "postalcode"
  },
  "geometry": {"coordinates":[-2.101216,52.457935],"type":"Point"}
}
