{
  "type": "Feature",
  "properties": {
    "iso:country":"GB",
    "wof:name":"L13 9BT",
    "wof:placetype":"postalcode"
},
  "geometry": {"coordinates":[-2.9284358449798,53.43241954299373],"type":"Point"}
}