{
  "type": "Feature",
  "properties": {
    "date:inception_lower":"2001-06-01",
    "date:inception_upper":"2001-06-30",
    "iso:country":"GB",
    "wof:name":"OX29 5SQ",
    "wof:placetype":"postalcode"
},
  "geometry": {"coordinates":[-1.409135,51.74835],"type":"Point"}
}