{
  "type": "Feature",
  "properties": {
    "iso:country": "GB",
    "wof:name": "OX29 5SQ",
    "wof:placetype": "postalcode"
  },
  "geometry": {"coordinates":[-1.409135,51.74835],"type":"Point"}
}
