{
  "type": "Feature",
  "properties": {
    "iso:country": "GB",
    "wof:name": "BR3 4TJ",
    "wof:placetype": "postalcode"
  },
  "geometry": {"coordinates":[-0.056378,51.40542],"type":"Point"}
}
