{
  "type": "Feature",
  "properties": {
    "iso:country":"GB",
    "wof:name":"BR3 4TJ",
    "wof:placetype":"postalcode"
},
  "geometry": {"coordinates":[-0.05637836291118,51.40542028743263],"type":"Point"}
}