{
  "type": "Feature",
  "properties": {
    "iso:country":"GB",
    "wof:name":"B37 7RN",
    "wof:placetype":"postalcode"
},
  "geometry": {"coordinates":[-1.74180648079485,52.47357690635808],"type":"Point"}
}