{
  "type": "Feature",
  "properties": {
    "date:inception_lower": "1980-01-01",
    "date:inception_upper": "1980-01-01",
    "iso:country": "GB",
    "wof:name": "TN38 0BP",
    "wof:placetype": "postalcode"
  },
  "geometry": {"coordinates":[0.547354,50.850832],"type":"Point"}
}
