{
  "type": "Feature",
  "properties": {
    "iso:country":"GB",
    "wof:name":"TN38 0BP",
    "wof:placetype":"postalcode"
},
  "geometry": {"coordinates":[0.54735363659734,50.85083157756194],"type":"Point"}
}