{
  "type": "Feature",
  "properties": {
    "iso:country": "GB",
    "wof:name": "TN38 0BP",
    "wof:placetype": "postalcode"
  },
  "geometry": {"coordinates":[0.547354,50.850832],"type":"Point"}
}
