{
  "type": "Feature",
  "properties": {
    "iso:country":"GB",
    "wof:name":"B21 8JE",
    "wof:placetype":"postalcode"
},
  "geometry": {"coordinates":[-1.95704823900861,52.51243518031585],"type":"Point"}
}