{
  "type": "Feature",
  "properties": {
    "iso:country":"GB",
    "wof:name":"BS21 7NL",
    "wof:placetype":"postalcode"
},
  "geometry": {"coordinates":[-2.85241783451679,51.43688269387286],"type":"Point"}
}