{
  "type": "Feature",
  "properties": {
    "iso:country": "GB",
    "wof:name": "BS21 7NL",
    "wof:placetype": "postalcode"
  },
  "geometry": {"coordinates":[-2.852349,51.436819],"type":"Point"}
}
