{
  "type": "Feature",
  "properties": {
    "iso:country":"GB",
    "wof:name":"CH1 5HG",
    "wof:placetype":"postalcode"
},
  "geometry": {"coordinates":[-2.93154695593546,53.20962052527313],"type":"Point"}
}