{
  "type": "Feature",
  "properties": {
    "iso:country": "GB",
    "wof:name": "CH1 5HG",
    "wof:placetype": "postalcode"
  },
  "geometry": {"coordinates":[-2.931547,53.209621],"type":"Point"}
}
