{
  "type": "Feature",
  "properties": {
    "date:inception_lower": "1980-01-01",
    "date:inception_upper": "1980-01-01",
    "iso:country": "GB",
    "wof:name": "CH1 5HG",
    "wof:placetype": "postalcode"
  },
  "geometry": {"coordinates":[-2.931547,53.209621],"type":"Point"}
}
