{
  "type": "Feature",
  "properties": {
    "iso:country":"GB",
    "wof:name":"CO9 1BG",
    "wof:placetype":"postalcode"
},
  "geometry": {"coordinates":[0.63526097234866,51.93372948359601],"type":"Point"}
}