{
  "type": "Feature",
  "properties": {
    "date:inception_lower": "1980-01-01",
    "date:inception_upper": "1980-01-01",
    "iso:country": "GB",
    "wof:name": "UB3 2BE",
    "wof:placetype": "postalcode"
  },
  "geometry": {"coordinates":[-0.427314,51.518928],"type":"Point"}
}
