{
  "type": "Feature",
  "properties": {
    "iso:country":"GB",
    "wof:name":"UB3 2BE",
    "wof:placetype":"postalcode"
},
  "geometry": {"coordinates":[-0.42731375618106,51.51892835823076],"type":"Point"}
}