{
  "type": "Feature",
  "properties": {
    "iso:country": "GB",
    "wof:name": "NN8 4SZ",
    "wof:placetype": "postalcode"
  },
  "geometry": {"coordinates":[-0.70126,52.318368],"type":"Point"}
}
