{
  "type": "Feature",
  "properties": {
    "iso:country":"GB",
    "wof:name":"NN8 4SZ",
    "wof:placetype":"postalcode"
},
  "geometry": {"coordinates":[-0.70125990330667,52.31836750559073],"type":"Point"}
}