{
  "type": "Feature",
  "properties": {
    "iso:country":"GB",
    "wof:name":"SY11 4NF",
    "wof:placetype":"postalcode"
},
  "geometry": {"coordinates":[-3.01060412265703,52.88560656177011],"type":"Point"}
}