{
  "type": "Feature",
  "properties": {
    "iso:country": "GB",
    "wof:name": "SY11 4NF",
    "wof:placetype": "postalcode"
  },
  "geometry": {"coordinates":[-3.010604,52.885607],"type":"Point"}
}
