{
  "type": "Feature",
  "properties": {
    "iso:country":"GB",
    "wof:name":"PA5 9BB",
    "wof:placetype":"postalcode"
},
  "geometry": {"coordinates":[-4.4694033654745,55.83835656792445],"type":"Point"}
}