{
  "type": "Feature",
  "properties": {
    "iso:country": "GB",
    "wof:name": "WS1 4HX",
    "wof:placetype": "postalcode"
  },
  "geometry": {"coordinates":[-1.984625,52.574688],"type":"Point"}
}
