{
  "type": "Feature",
  "properties": {
    "iso:country":"GB",
    "wof:name":"RG2 0BU",
    "wof:placetype":"postalcode"
},
  "geometry": {"coordinates":[-0.96915623999792,51.43965297266902],"type":"Point"}
}