{
  "type": "Feature",
  "properties": {
    "iso:country": "GB",
    "wof:name": "WV6 0TR",
    "wof:placetype": "postalcode"
  },
  "geometry": {"coordinates":[-2.148579,52.598622],"type":"Point"}
}
