{
  "type": "Feature",
  "properties": {
    "iso:country":"GB",
    "wof:name":"WV6 0TR",
    "wof:placetype":"postalcode"
},
  "geometry": {"coordinates":[-2.14862860842923,52.59859784594394],"type":"Point"}
}