{
  "type": "Feature",
  "properties": {
    "iso:country":"GB",
    "wof:name":"B24 9JQ",
    "wof:placetype":"postalcode"
},
  "geometry": {"coordinates":[-1.83174260238163,52.52780427037643],"type":"Point"}
}