{
  "type": "Feature",
  "properties": {
    "iso:country":"GB",
    "wof:name":"DD8 1BL",
    "wof:placetype":"postalcode"
},
  "geometry": {"coordinates":[-2.89292776284035,56.64217594334281],"type":"Point"}
}