{
  "type": "Feature",
  "properties": {
    "iso:country":"GB",
    "wof:name":"BB2 2BU",
    "wof:placetype":"postalcode"
},
  "geometry": {"coordinates":[-2.48124528693201,53.7452206734481],"type":"Point"}
}