{
  "type": "Feature",
  "properties": {
    "iso:country":"GB",
    "wof:name":"EX14 9TH",
    "wof:placetype":"postalcode"
},
  "geometry": {"coordinates":[-3.16675344546803,50.80114243503962],"type":"Point"}
}