{
  "type": "Feature",
  "properties": {
    "iso:country": "GB",
    "wof:name": "PA20 9BD",
    "wof:placetype": "postalcode"
  },
  "geometry": {"coordinates":[-5.054525,55.834533],"type":"Point"}
}
