{
  "type": "Feature",
  "properties": {
    "date:inception_lower":"2014-10-01",
    "date:inception_upper":"2014-10-31",
    "iso:country":"GB",
    "wof:name":"RG14 7GH",
    "wof:placetype":"postalcode"
},
  "geometry": {"coordinates":[-1.310363,51.396199],"type":"Point"}
}