{
  "type": "Feature",
  "properties": {
    "iso:country": "GB",
    "wof:name": "RG14 7GH",
    "wof:placetype": "postalcode"
  },
  "geometry": {"coordinates":[-1.310363,51.396199],"type":"Point"}
}
