{
  "type": "Feature",
  "properties": {
    "iso:country":"GB",
    "wof:name":"RG14 7GH",
    "wof:placetype":"postalcode"
},
  "geometry": {"coordinates":[-1.31036296547479,51.39619914823253],"type":"Point"}
}