{
  "type": "Feature",
  "properties": {
    "iso:country": "GB",
    "wof:name": "DT10 2ST",
    "wof:placetype": "postalcode"
  },
  "geometry": {"coordinates":[-2.375759,50.96152],"type":"Point"}
}
