{
  "type": "Feature",
  "properties": {
    "iso:country":"GB",
    "wof:name":"BB5 2EY",
    "wof:placetype":"postalcode"
},
  "geometry": {"coordinates":[-2.36503024918735,53.74968481727544],"type":"Point"}
}