{
  "type": "Feature",
  "properties": {
    "iso:country": "GB",
    "wof:name": "BB5 2EY",
    "wof:placetype": "postalcode"
  },
  "geometry": {"coordinates":[-2.36503,53.749685],"type":"Point"}
}
