{
  "type": "Feature",
  "properties": {
    "date:inception_lower": "2016-02-01",
    "date:inception_upper": "2016-02-01",
    "iso:country": "GB",
    "wof:name": "NG34 7BZ",
    "wof:placetype": "postalcode"
  },
  "geometry": {"coordinates":[-0.410174,53.000989],"type":"Point"}
}
