{
  "type": "Feature",
  "properties": {
    "iso:country": "GB",
    "wof:name": "DN38 6JE",
    "wof:placetype": "postalcode"
  },
  "geometry": {"coordinates":[-0.40132,53.572913],"type":"Point"}
}
