{
  "type": "Feature",
  "properties": {
    "iso:country":"GB",
    "wof:name":"PE7 8WA",
    "wof:placetype":"postalcode"
},
  "geometry": {"coordinates":[-0.2805939405797,52.53077549878157],"type":"Point"}
}