{
  "type": "Feature",
  "properties": {
    "date:inception_lower": "2010-12-01",
    "date:inception_upper": "2010-12-01",
    "iso:country": "GB",
    "wof:name": "PE7 8WA",
    "wof:placetype": "postalcode"
  },
  "geometry": {"coordinates":[-0.280594,52.530775],"type":"Point"}
}
