{
  "type": "Feature",
  "properties": {
    "date:inception_lower": "2017-04-01",
    "date:inception_upper": "2017-04-01",
    "iso:country": "GB",
    "wof:name": "EX16 7FH",
    "wof:placetype": "postalcode"
  },
  "geometry": {"coordinates":[-3.426731,50.901224],"type":"Point"}
}
