{
  "type": "Feature",
  "properties": {
    "iso:country":"GB",
    "wof:name":"NR15 1JF",
    "wof:placetype":"postalcode"
},
  "geometry": {"coordinates":[1.37712143433462,52.54396100119261],"type":"Point"}
}