{
  "type": "Feature",
  "properties": {
    "date:inception_lower": "1985-04-01",
    "date:inception_upper": "1985-04-01",
    "iso:country": "GB",
    "wof:name": "NR15 1JF",
    "wof:placetype": "postalcode"
  },
  "geometry": {"coordinates":[1.377147,52.543985],"type":"Point"}
}
