{
  "type": "Feature",
  "properties": {
    "iso:country": "GB",
    "wof:name": "SK22 2HW",
    "wof:placetype": "postalcode"
  },
  "geometry": {"coordinates":[-1.945,53.380648],"type":"Point"}
}
