{
  "type": "Feature",
  "properties": {
    "iso:country":"GB",
    "wof:name":"SM7 3DD",
    "wof:placetype":"postalcode"
},
  "geometry": {"coordinates":[-0.19509306326643,51.32261336275266],"type":"Point"}
}