{
  "type": "Feature",
  "properties": {
    "date:inception_lower":"1991-01-01",
    "date:inception_upper":"1991-01-31",
    "iso:country":"GB",
    "wof:name":"S43 4UN",
    "wof:placetype":"postalcode"
},
  "geometry": {"coordinates":[-1.260098,53.269229],"type":"Point"}
}