{
  "type": "Feature",
  "properties": {
    "iso:country":"GB",
    "wof:name":"S43 4UN",
    "wof:placetype":"postalcode"
},
  "geometry": {"coordinates":[-1.26008449286663,53.26921693085657],"type":"Point"}
}