{
  "type": "Feature",
  "properties": {
    "iso:country":"GB",
    "wof:name":"HX5 0LA",
    "wof:placetype":"postalcode"
},
  "geometry": {"coordinates":[-1.84058121089082,53.68253634451742],"type":"Point"}
}