{
  "type": "Feature",
  "properties": {
    "date:inception_lower": "1980-01-01",
    "date:inception_upper": "1980-01-01",
    "iso:country": "GB",
    "wof:name": "BB1 7HA",
    "wof:placetype": "postalcode"
  },
  "geometry": {"coordinates":[-2.485476,53.754452],"type":"Point"}
}
