{
  "type": "Feature",
  "properties": {
    "iso:country":"GB",
    "wof:name":"BB1 7HA",
    "wof:placetype":"postalcode"
},
  "geometry": {"coordinates":[-2.48547607643911,53.75445238302397],"type":"Point"}
}