{
  "type": "Feature",
  "properties": {
    "date:inception_lower": "1990-02-01",
    "date:inception_upper": "1990-02-01",
    "iso:country": "GB",
    "wof:name": "LA4 4QJ",
    "wof:placetype": "postalcode"
  },
  "geometry": {"coordinates":[-2.863748,54.066735],"type":"Point"}
}
