{
  "type": "Feature",
  "properties": {
    "iso:country":"GB",
    "wof:name":"LA4 4QJ",
    "wof:placetype":"postalcode"
},
  "geometry": {"coordinates":[-2.86374758888615,54.06673536456898],"type":"Point"}
}