{
  "type": "Feature",
  "properties": {
    "iso:country":"GB",
    "wof:name":"OL16 1NL",
    "wof:placetype":"postalcode"
},
  "geometry": {"coordinates":[-2.15600739761866,53.61561408274102],"type":"Point"}
}