{
  "type": "Feature",
  "properties": {
    "iso:country": "GB",
    "wof:name": "OL16 1NL",
    "wof:placetype": "postalcode"
  },
  "geometry": {"coordinates":[-2.155552,53.615712],"type":"Point"}
}
