{
  "type": "Feature",
  "properties": {
    "iso:country":"GB",
    "wof:name":"G76 8PD",
    "wof:placetype":"postalcode"
},
  "geometry": {"coordinates":[-4.26523601892534,55.79334093087357],"type":"Point"}
}