{
  "type": "Feature",
  "properties": {
    "date:inception_lower": "1980-01-01",
    "date:inception_upper": "1980-01-01",
    "iso:country": "GB",
    "wof:name": "G76 8PD",
    "wof:placetype": "postalcode"
  },
  "geometry": {"coordinates":[-4.265236,55.793341],"type":"Point"}
}
