{
  "type": "Feature",
  "properties": {
    "iso:country": "GB",
    "wof:name": "WA10 4PA",
    "wof:placetype": "postalcode"
  },
  "geometry": {"coordinates":[-2.760025,53.451093],"type":"Point"}
}
