{
  "type": "Feature",
  "properties": {
    "iso:country": "GB",
    "wof:name": "G12 0DH",
    "wof:placetype": "postalcode"
  },
  "geometry": {"coordinates":[-4.3162,55.891237],"type":"Point"}
}
