{
  "type": "Feature",
  "properties": {
    "iso:country":"GB",
    "wof:name":"G12 0DH",
    "wof:placetype":"postalcode"
},
  "geometry": {"coordinates":[-4.31619997364792,55.89123682386504],"type":"Point"}
}