{
  "type": "Feature",
  "properties": {
    "date:inception_lower": "1984-02-01",
    "date:inception_upper": "1984-02-01",
    "iso:country": "GB",
    "wof:name": "NN16 0SS",
    "wof:placetype": "postalcode"
  },
  "geometry": {"coordinates":[-0.720471,52.401022],"type":"Point"}
}
