{
  "type": "Feature",
  "properties": {
    "iso:country":"GB",
    "wof:name":"CW11 4NR",
    "wof:placetype":"postalcode"
},
  "geometry": {"coordinates":[-2.3665406942238,53.14249529425907],"type":"Point"}
}