{
  "type": "Feature",
  "properties": {
    "date:inception_lower": "2013-10-01",
    "date:inception_upper": "2013-10-01",
    "iso:country": "GB",
    "wof:name": "CH2 1EZ",
    "wof:placetype": "postalcode"
  },
  "geometry": {"coordinates":[-2.903775,53.214778],"type":"Point"}
}
