{
  "type": "Feature",
  "properties": {
    "date:inception_lower": "1980-01-01",
    "date:inception_upper": "1980-01-01",
    "iso:country": "GB",
    "wof:name": "CF32 9RJ",
    "wof:placetype": "postalcode"
  },
  "geometry": {"coordinates":[-3.579004,51.542245],"type":"Point"}
}
