{
  "type": "Feature",
  "properties": {
    "iso:country":"GB",
    "wof:name":"CF32 9RJ",
    "wof:placetype":"postalcode"
},
  "geometry": {"coordinates":[-3.57894362992556,51.54219886170694],"type":"Point"}
}