{
  "type": "Feature",
  "properties": {
    "date:inception_lower": "1997-12-01",
    "date:inception_upper": "1997-12-01",
    "iso:country": "GB",
    "wof:name": "BH21 8LQ",
    "wof:placetype": "postalcode"
  },
  "geometry": {"coordinates":[-1.914209,50.879643],"type":"Point"}
}
