{
  "type": "Feature",
  "properties": {
    "iso:country":"GB",
    "wof:name":"PH1 4AX",
    "wof:placetype":"postalcode"
},
  "geometry": {"coordinates":[-3.51279115260555,56.50147128803199],"type":"Point"}
}