{
  "type": "Feature",
  "properties": {
    "iso:country":"GB",
    "wof:name":"DN17 1EZ",
    "wof:placetype":"postalcode"
},
  "geometry": {"coordinates":[-0.6620950451079,53.57195208465522],"type":"Point"}
}