{
  "type": "Feature",
  "properties": {
    "date:inception_lower": "1980-01-01",
    "date:inception_upper": "1980-01-01",
    "iso:country": "GB",
    "wof:name": "HA0 1AF",
    "wof:placetype": "postalcode"
  },
  "geometry": {"coordinates":[-0.30617,51.542582],"type":"Point"}
}
