{
  "type": "Feature",
  "properties": {
    "iso:country":"GB",
    "wof:name":"TA2 6DT",
    "wof:placetype":"postalcode"
},
  "geometry": {"coordinates":[-3.11150436116757,51.03198541113395],"type":"Point"}
}