{
  "type": "Feature",
  "properties": {
    "date:inception_lower": "1980-01-01",
    "date:inception_upper": "1980-01-01",
    "iso:country": "GB",
    "wof:name": "FY1 4DY",
    "wof:placetype": "postalcode"
  },
  "geometry": {"coordinates":[-3.03953,53.813204],"type":"Point"}
}
