{
  "type": "Feature",
  "properties": {
    "iso:country":"GB",
    "wof:name":"FY1 4DY",
    "wof:placetype":"postalcode"
},
  "geometry": {"coordinates":[-3.0395337579431,53.81318945624189],"type":"Point"}
}