{
  "type": "Feature",
  "properties": {
    "iso:country":"GB",
    "wof:name":"HX1 1PF",
    "wof:placetype":"postalcode"
},
  "geometry": {"coordinates":[-1.85789053040454,53.72188106485229],"type":"Point"}
}