{
  "type": "Feature",
  "properties": {
    "date:inception_lower": "1980-01-01",
    "date:inception_upper": "1980-01-01",
    "iso:country": "GB",
    "wof:name": "TW13 6PX",
    "wof:placetype": "postalcode"
  },
  "geometry": {"coordinates":[-0.391158,51.43829],"type":"Point"}
}
