{
  "type": "Feature",
  "properties": {
    "iso:country":"GB",
    "wof:name":"G81 2JE",
    "wof:placetype":"postalcode"
},
  "geometry": {"coordinates":[-4.40390867390161,55.90855482358604],"type":"Point"}
}