{
  "type": "Feature",
  "properties": {
    "date:inception_lower":"1980-01-01",
    "date:inception_upper":"1980-01-31",
    "iso:country":"GB",
    "wof:name":"G81 2JE",
    "wof:placetype":"postalcode"
},
  "geometry": {"coordinates":[-4.403909,55.908555],"type":"Point"}
}