{
  "type": "Feature",
  "properties": {
    "iso:country":"GB",
    "wof:name":"NN4 8HU",
    "wof:placetype":"postalcode"
},
  "geometry": {"coordinates":[-0.91709399678444,52.2236773431603],"type":"Point"}
}