{
  "type": "Feature",
  "properties": {
    "date:inception_lower": "1993-08-01",
    "date:inception_upper": "1993-08-01",
    "iso:country": "GB",
    "wof:name": "NN4 8HU",
    "wof:placetype": "postalcode"
  },
  "geometry": {"coordinates":[-0.917094,52.223677],"type":"Point"}
}
