{
  "type": "Feature",
  "properties": {
    "iso:country":"GB",
    "wof:name":"BB9 0BG",
    "wof:placetype":"postalcode"
},
  "geometry": {"coordinates":[-2.21422749331809,53.8314716736667],"type":"Point"}
}