{
  "type": "Feature",
  "properties": {
    "iso:country": "GB",
    "wof:name": "BN11 4NF",
    "wof:placetype": "postalcode"
  },
  "geometry": {"coordinates":[-0.392095,50.813268],"type":"Point"}
}
