{
  "type": "Feature",
  "properties": {
    "iso:country":"GB",
    "wof:name":"BN11 4NF",
    "wof:placetype":"postalcode"
},
  "geometry": {"coordinates":[-0.39209505707242,50.81326776108258],"type":"Point"}
}