{
  "type": "Feature",
  "properties": {
    "date:inception_lower": "2016-11-01",
    "date:inception_upper": "2016-11-01",
    "iso:country": "GB",
    "wof:name": "SS5 4FW",
    "wof:placetype": "postalcode"
  },
  "geometry": {"coordinates":[0.64268,51.601078],"type":"Point"}
}
