{
  "type": "Feature",
  "properties": {
    "iso:country":"GB",
    "wof:name":"EX18 7JN",
    "wof:placetype":"postalcode"
},
  "geometry": {"coordinates":[-3.87741175176864,50.91373693377256],"type":"Point"}
}