{
  "type": "Feature",
  "properties": {
    "iso:country":"GB",
    "wof:name":"RH15 0RA",
    "wof:placetype":"postalcode"
},
  "geometry": {"coordinates":[-0.1184432940241,50.96668540119982],"type":"Point"}
}