{
  "type": "Feature",
  "properties": {
    "iso:country":"GB",
    "wof:name":"DE14 1EE",
    "wof:placetype":"postalcode"
},
  "geometry": {"coordinates":[-1.63930192055775,52.80380864203797],"type":"Point"}
}