{
  "type": "Feature",
  "properties": {
    "iso:country":"GB",
    "wof:name":"IP31 3PS",
    "wof:placetype":"postalcode"
},
  "geometry": {"coordinates":[0.80087839486754,52.25335203392045],"type":"Point"}
}