{
  "type": "Feature",
  "properties": {
    "iso:country":"GB",
    "wof:name":"RM10 8DX",
    "wof:placetype":"postalcode"
},
  "geometry": {"coordinates":[0.15529039250563,51.54326670127919],"type":"Point"}
}