{
  "type": "Feature",
  "properties": {
    "iso:country": "GB",
    "wof:name": "IP29 4AF",
    "wof:placetype": "postalcode"
  },
  "geometry": {"coordinates":[0.672019,52.160936],"type":"Point"}
}
