{
  "type": "Feature",
  "properties": {
    "iso:country":"GB",
    "wof:name":"RG42 1XH",
    "wof:placetype":"postalcode"
},
  "geometry": {"coordinates":[-0.76676745277774,51.42079396804127],"type":"Point"}
}