{
  "type": "Feature",
  "properties": {
    "date:inception_lower": "1995-07-01",
    "date:inception_upper": "1995-07-01",
    "iso:country": "GB",
    "wof:name": "RG42 1XH",
    "wof:placetype": "postalcode"
  },
  "geometry": {"coordinates":[-0.766767,51.420794],"type":"Point"}
}
