{
  "type": "Feature",
  "properties": {
    "iso:country": "GB",
    "wof:name": "WS9 8YB",
    "wof:placetype": "postalcode"
  },
  "geometry": {"coordinates":[-1.925421,52.611739],"type":"Point"}
}
