{
  "type": "Feature",
  "properties": {
    "date:inception_lower":"1986-04-01",
    "date:inception_upper":"1986-04-30",
    "iso:country":"GB",
    "wof:name":"WS9 8YB",
    "wof:placetype":"postalcode"
},
  "geometry": {"coordinates":[-1.925421,52.611739],"type":"Point"}
}