{
  "type": "Feature",
  "properties": {
    "iso:country":"GB",
    "wof:name":"SL4 1QN",
    "wof:placetype":"postalcode"
},
  "geometry": {"coordinates":[-0.60686451654578,51.48614694557227],"type":"Point"}
}