{
  "type": "Feature",
  "properties": {
    "iso:country":"GB",
    "wof:name":"BR1 3HQ",
    "wof:placetype":"postalcode"
},
  "geometry": {"coordinates":[0.01963393166549,51.40855031576484],"type":"Point"}
}