{
  "type": "Feature",
  "properties": {
    "date:inception_lower": "1980-01-01",
    "date:inception_upper": "1980-01-01",
    "iso:country": "GB",
    "wof:name": "ST18 9PP",
    "wof:placetype": "postalcode"
  },
  "geometry": {"coordinates":[-2.183283,52.828647],"type":"Point"}
}
