{
  "type": "Feature",
  "properties": {
    "iso:country":"GB",
    "wof:name":"ST18 9PP",
    "wof:placetype":"postalcode"
},
  "geometry": {"coordinates":[-2.1832826590672,52.82864735430864],"type":"Point"}
}