{
  "type": "Feature",
  "properties": {
    "iso:country": "GB",
    "wof:name": "ST18 9PP",
    "wof:placetype": "postalcode"
  },
  "geometry": {"coordinates":[-2.183283,52.828647],"type":"Point"}
}
