{
  "type": "Feature",
  "properties": {
    "iso:country":"GB",
    "wof:name":"SP1 1RD",
    "wof:placetype":"postalcode"
},
  "geometry": {"coordinates":[-1.77137182661515,51.08018604501486],"type":"Point"}
}