{
  "type": "Feature",
  "properties": {
    "iso:country":"GB",
    "wof:name":"PO20 8DW",
    "wof:placetype":"postalcode"
},
  "geometry": {"coordinates":[-0.86534917902929,50.76449443775739],"type":"Point"}
}