{
  "type": "Feature",
  "properties": {
    "date:inception_lower": "2024-04-01",
    "date:inception_upper": "2024-04-01",
    "iso:country": "GB",
    "wof:name": "NR6 7GQ",
    "wof:placetype": "postalcode"
  },
  "geometry": {"coordinates":[1.311689,52.671731],"type":"Point"}
}
