{
  "type": "Feature",
  "properties": {
    "iso:country":"GB",
    "wof:name":"CR8 5EP",
    "wof:placetype":"postalcode"
},
  "geometry": {"coordinates":[-0.10357045463855,51.30310043553302],"type":"Point"}
}