{
  "type": "Feature",
  "properties": {
    "iso:country":"GB",
    "wof:name":"SO14 7FH",
    "wof:placetype":"postalcode"
},
  "geometry": {"coordinates":[-1.4048604265708,50.90654826611827],"type":"Point"}
}