{
  "type": "Feature",
  "properties": {
    "iso:country":"GB",
    "wof:name":"W2 6EP",
    "wof:placetype":"postalcode"
},
  "geometry": {"coordinates":[-0.17966438643916,51.51954609728231],"type":"Point"}
}