{
  "type": "Feature",
  "properties": {
    "date:inception_lower": "2008-11-01",
    "date:inception_upper": "2008-11-01",
    "iso:country": "GB",
    "wof:name": "W2 6EP",
    "wof:placetype": "postalcode"
  },
  "geometry": {"coordinates":[-0.179217,51.519289],"type":"Point"}
}
