{
  "type": "Feature",
  "properties": {
    "iso:country":"GB",
    "wof:name":"IV15 9PW",
    "wof:placetype":"postalcode"
},
  "geometry": {"coordinates":[-4.4346477017147,57.59871217129007],"type":"Point"}
}