{
  "type": "Feature",
  "properties": {
    "iso:country":"GB",
    "wof:name":"CV34 5TF",
    "wof:placetype":"postalcode"
},
  "geometry": {"coordinates":[-1.58021724149183,52.29380538845003],"type":"Point"}
}