{
  "type": "Feature",
  "properties": {
    "iso:country":"GB",
    "wof:name":"GL20 5NJ",
    "wof:placetype":"postalcode"
},
  "geometry": {"coordinates":[-2.15320237078047,51.99531950400751],"type":"Point"}
}