{
  "type": "Feature",
  "properties": {
    "iso:country":"GB",
    "wof:name":"IV16 9XE",
    "wof:placetype":"postalcode"
},
  "geometry": {"coordinates":[-4.33280454510666,57.66399081503413],"type":"Point"}
}