{
  "type": "Feature",
  "properties": {
    "date:inception_lower": "1998-12-01",
    "date:inception_upper": "1998-12-01",
    "iso:country": "GB",
    "wof:name": "IV16 9XE",
    "wof:placetype": "postalcode"
  },
  "geometry": {"coordinates":[-4.332867,57.663919],"type":"Point"}
}
