{
  "type": "Feature",
  "properties": {
    "iso:country":"GB",
    "wof:name":"HP10 0SY",
    "wof:placetype":"postalcode"
},
  "geometry": {"coordinates":[-0.68214694895145,51.5979954303282],"type":"Point"}
}