{
  "type": "Feature",
  "properties": {
    "date:inception_lower":"1990-07-01",
    "date:inception_upper":"1990-07-31",
    "iso:country":"GB",
    "wof:name":"HP10 0SY",
    "wof:placetype":"postalcode"
},
  "geometry": {"coordinates":[-0.682147,51.597995],"type":"Point"}
}