{
  "type": "Feature",
  "properties": {
    "iso:country": "GB",
    "wof:name": "HP10 0SY",
    "wof:placetype": "postalcode"
  },
  "geometry": {"coordinates":[-0.682147,51.597995],"type":"Point"}
}
