{
  "type": "Feature",
  "properties": {
    "iso:country":"GB",
    "wof:name":"HR1 3AA",
    "wof:placetype":"postalcode"
},
  "geometry": {"coordinates":[-2.72636252250703,52.09304809958047],"type":"Point"}
}