{
  "type": "Feature",
  "properties": {
    "iso:country": "GB",
    "wof:name": "HR1 3AA",
    "wof:placetype": "postalcode"
  },
  "geometry": {"coordinates":[-2.726362,52.093048],"type":"Point"}
}
