{
  "type": "Feature",
  "properties": {
    "date:inception_lower": "1999-06-01",
    "date:inception_upper": "1999-06-01",
    "iso:country": "GB",
    "wof:name": "NP22 3EN",
    "wof:placetype": "postalcode"
  },
  "geometry": {"coordinates":[-3.248124,51.778423],"type":"Point"}
}
