{
  "type": "Feature",
  "properties": {
    "iso:country":"GB",
    "wof:name":"NP22 3EN",
    "wof:placetype":"postalcode"
},
  "geometry": {"coordinates":[-3.24812419936925,51.77842326287448],"type":"Point"}
}