{
  "type": "Feature",
  "properties": {
    "iso:country":"GB",
    "wof:name":"PE14 9HP",
    "wof:placetype":"postalcode"
},
  "geometry": {"coordinates":[0.22716838488666,52.59050083490862],"type":"Point"}
}