{
  "type": "Feature",
  "properties": {
    "date:inception_lower":"1980-01-01",
    "date:inception_upper":"1980-01-31",
    "iso:country":"GB",
    "wof:name":"PE14 9HP",
    "wof:placetype":"postalcode"
},
  "geometry": {"coordinates":[0.227168,52.590501],"type":"Point"}
}