{
  "type": "Feature",
  "properties": {
    "date:inception_lower": "1980-01-01",
    "date:inception_upper": "1980-01-01",
    "iso:country": "GB",
    "wof:name": "SP2 0JF",
    "wof:placetype": "postalcode"
  },
  "geometry": {"coordinates":[-1.881967,51.08998],"type":"Point"}
}
