{
  "type": "Feature",
  "properties": {
    "iso:country":"GB",
    "wof:name":"SP2 0JF",
    "wof:placetype":"postalcode"
},
  "geometry": {"coordinates":[-1.88196705568023,51.08998030864883],"type":"Point"}
}