{
  "type": "Feature",
  "properties": {
    "iso:country": "GB",
    "wof:name": "NE21 5NX",
    "wof:placetype": "postalcode"
  },
  "geometry": {"coordinates":[-1.696138,54.956914],"type":"Point"}
}
