{
  "type": "Feature",
  "properties": {
    "iso:country":"GB",
    "wof:name":"TQ6 9JX",
    "wof:placetype":"postalcode"
},
  "geometry": {"coordinates":[-3.59570489032886,50.35023275122919],"type":"Point"}
}