{
  "type": "Feature",
  "properties": {
    "iso:country":"GB",
    "wof:name":"GL51 0DZ",
    "wof:placetype":"postalcode"
},
  "geometry": {"coordinates":[-2.11420312165046,51.91145300421442],"type":"Point"}
}