{
  "type": "Feature",
  "properties": {
    "date:inception_lower": "1998-12-01",
    "date:inception_upper": "1998-12-01",
    "iso:country": "GB",
    "wof:name": "EC2M 4WY",
    "wof:placetype": "postalcode"
  },
  "geometry": {"coordinates":[-0.078345,51.516887],"type":"Point"}
}
