{
  "type": "Feature",
  "properties": {
    "iso:country":"GB",
    "wof:name":"EC2M 4WY",
    "wof:placetype":"postalcode"
},
  "geometry": {"coordinates":[-0.0783446722708,51.5168867619869],"type":"Point"}
}