{
  "type": "Feature",
  "properties": {
    "iso:country": "GB",
    "wof:name": "LL48 6LR",
    "wof:placetype": "postalcode"
  },
  "geometry": {"coordinates":[-4.065546,52.930425],"type":"Point"}
}
