{
  "type": "Feature",
  "properties": {
    "iso:country":"GB",
    "wof:name":"LL48 6LR",
    "wof:placetype":"postalcode"
},
  "geometry": {"coordinates":[-4.06554628596652,52.93042542660078],"type":"Point"}
}