{
  "type": "Feature",
  "properties": {
    "iso:country":"GB",
    "wof:name":"DT10 2ND",
    "wof:placetype":"postalcode"
},
  "geometry": {"coordinates":[-2.37676480450814,50.95908919692521],"type":"Point"}
}