{
  "type": "Feature",
  "properties": {
    "iso:country": "GB",
    "wof:name": "NG34 9PN",
    "wof:placetype": "postalcode"
  },
  "geometry": {"coordinates":[-0.33266,53.008126],"type":"Point"}
}
