{
  "type": "Feature",
  "properties": {
    "iso:country":"GB",
    "wof:name":"NG34 9PN",
    "wof:placetype":"postalcode"
},
  "geometry": {"coordinates":[-0.33266005621807,53.0081264924275],"type":"Point"}
}