{
  "type": "Feature",
  "properties": {
    "iso:country": "GB",
    "wof:name": "DH1 4DZ",
    "wof:placetype": "postalcode"
  },
  "geometry": {"coordinates":[-1.59151,54.773293],"type":"Point"}
}
