{
  "type": "Feature",
  "properties": {
    "iso:country": "GB",
    "wof:name": "SG19 2QR",
    "wof:placetype": "postalcode"
  },
  "geometry": {"coordinates":[-0.213003,52.131181],"type":"Point"}
}
