{
  "type": "Feature",
  "properties": {
    "iso:country":"GB",
    "wof:name":"SG19 2QR",
    "wof:placetype":"postalcode"
},
  "geometry": {"coordinates":[-0.21300334087627,52.13118138995819],"type":"Point"}
}