{
  "type": "Feature",
  "properties": {
    "iso:country": "GB",
    "wof:name": "CB23 2UG",
    "wof:placetype": "postalcode"
  },
  "geometry": {"coordinates":[-0.088074,52.1839],"type":"Point"}
}
