{
  "type": "Feature",
  "properties": {
    "iso:country":"GB",
    "wof:name":"LS6 3NQ",
    "wof:placetype":"postalcode"
},
  "geometry": {"coordinates":[-1.59370545325015,53.81918411757252],"type":"Point"}
}