{
  "type": "Feature",
  "properties": {
    "date:inception_lower":"2003-04-01",
    "date:inception_upper":"2003-04-30",
    "iso:country":"GB",
    "wof:name":"LS6 3NQ",
    "wof:placetype":"postalcode"
},
  "geometry": {"coordinates":[-1.593705,53.819184],"type":"Point"}
}