{
  "type": "Feature",
  "properties": {
    "iso:country":"GB",
    "wof:name":"PE11 4BS",
    "wof:placetype":"postalcode"
},
  "geometry": {"coordinates":[-0.14344756382972,52.83338710201419],"type":"Point"}
}