{
  "type": "Feature",
  "properties": {
    "iso:country":"GB",
    "wof:name":"G78 2PQ",
    "wof:placetype":"postalcode"
},
  "geometry": {"coordinates":[-4.3742958276966,55.79287308163926],"type":"Point"}
}