{
  "type": "Feature",
  "properties": {
    "iso:country":"GB",
    "wof:name":"CV34 4DX",
    "wof:placetype":"postalcode"
},
  "geometry": {"coordinates":[-1.59445078598224,52.28134956803962],"type":"Point"}
}