{
  "type": "Feature",
  "properties": {
    "iso:country":"GB",
    "wof:name":"CO13 9BT",
    "wof:placetype":"postalcode"
},
  "geometry": {"coordinates":[1.24902302409747,51.83286003120919],"type":"Point"}
}