{
  "type": "Feature",
  "properties": {
    "date:inception_lower":"2004-11-01",
    "date:inception_upper":"2004-11-30",
    "iso:country":"GB",
    "wof:name":"DG7 3PE",
    "wof:placetype":"postalcode"
},
  "geometry": {"coordinates":[-4.127651,55.080297],"type":"Point"}
}