{
  "type": "Feature",
  "properties": {
    "iso:country":"GB",
    "wof:name":"DG7 3PE",
    "wof:placetype":"postalcode"
},
  "geometry": {"coordinates":[-4.12765154735484,55.08029707406943],"type":"Point"}
}