{
  "type": "Feature",
  "properties": {
    "iso:country": "GB",
    "wof:name": "DG7 3PE",
    "wof:placetype": "postalcode"
  },
  "geometry": {"coordinates":[-4.127651,55.080297],"type":"Point"}
}
