{
  "type": "Feature",
  "properties": {
    "iso:country":"GB",
    "wof:name":"PL5 3AD",
    "wof:placetype":"postalcode"
},
  "geometry": {"coordinates":[-4.13575379191983,50.40444420685141],"type":"Point"}
}