{
  "type": "Feature",
  "properties": {
    "iso:country":"GB",
    "wof:name":"UB3 2NB",
    "wof:placetype":"postalcode"
},
  "geometry": {"coordinates":[-0.41663584351387,51.52010657377032],"type":"Point"}
}