{
  "type": "Feature",
  "properties": {
    "iso:country": "GB",
    "wof:name": "HP22 5DJ",
    "wof:placetype": "postalcode"
  },
  "geometry": {"coordinates":[-0.784468,51.829159],"type":"Point"}
}
