{
  "type": "Feature",
  "properties": {
    "iso:country":"GB",
    "wof:name":"HP22 5DJ",
    "wof:placetype":"postalcode"
},
  "geometry": {"coordinates":[-0.78446754384519,51.82915852645194],"type":"Point"}
}