{
  "type": "Feature",
  "properties": {
    "iso:country":"GB",
    "wof:name":"NR17 1EW",
    "wof:placetype":"postalcode"
},
  "geometry": {"coordinates":[0.88512348270538,52.51135483540898],"type":"Point"}
}