{
  "type": "Feature",
  "properties": {
    "iso:country": "GB",
    "wof:name": "AL7 2BD",
    "wof:placetype": "postalcode"
  },
  "geometry": {"coordinates":[-0.173923,51.799476],"type":"Point"}
}
