{
  "type": "Feature",
  "properties": {
    "date:inception_lower":"1997-06-01",
    "date:inception_upper":"1997-06-30",
    "iso:country":"GB",
    "wof:name":"RH13 8DS",
    "wof:placetype":"postalcode"
},
  "geometry": {"coordinates":[-0.270633,50.991242],"type":"Point"}
}