{
  "type": "Feature",
  "properties": {
    "iso:country":"GB",
    "wof:name":"RH13 8DS",
    "wof:placetype":"postalcode"
},
  "geometry": {"coordinates":[-0.27063303733989,50.99124208643466],"type":"Point"}
}