{
  "type": "Feature",
  "properties": {
    "date:inception_lower": "1981-06-01",
    "date:inception_upper": "1981-06-01",
    "iso:country": "GB",
    "wof:name": "HU9 4AF",
    "wof:placetype": "postalcode"
  },
  "geometry": {"coordinates":[-0.283019,53.766873],"type":"Point"}
}
