{
  "type": "Feature",
  "properties": {
    "iso:country": "GB",
    "wof:name": "HU9 4AF",
    "wof:placetype": "postalcode"
  },
  "geometry": {"coordinates":[-0.283019,53.766873],"type":"Point"}
}
