{
  "type": "Feature",
  "properties": {
    "iso:country":"GB",
    "wof:name":"AB56 1TL",
    "wof:placetype":"postalcode"
},
  "geometry": {"coordinates":[-2.93716080795479,57.68424901498163],"type":"Point"}
}