{
  "type": "Feature",
  "properties": {
    "date:inception_lower": "1980-01-01",
    "date:inception_upper": "1980-01-01",
    "iso:country": "GB",
    "wof:name": "PL3 6SZ",
    "wof:placetype": "postalcode"
  },
  "geometry": {"coordinates":[-4.101256,50.391617],"type":"Point"}
}
