{
  "type": "Feature",
  "properties": {
    "iso:country":"GB",
    "wof:name":"PL3 6SZ",
    "wof:placetype":"postalcode"
},
  "geometry": {"coordinates":[-4.10125587266093,50.39161727136045],"type":"Point"}
}