{
  "type": "Feature",
  "properties": {
    "iso:country": "GB",
    "wof:name": "PE31 6UA",
    "wof:placetype": "postalcode"
  },
  "geometry": {"coordinates":[0.495534,52.844779],"type":"Point"}
}
