{
  "type": "Feature",
  "properties": {
    "date:inception_lower":"2011-05-01",
    "date:inception_upper":"2011-05-31",
    "iso:country":"GB",
    "wof:name":"HR1 1GB",
    "wof:placetype":"postalcode"
},
  "geometry": {"coordinates":[-2.711328,52.07559],"type":"Point"}
}