{
  "type": "Feature",
  "properties": {
    "iso:country":"GB",
    "wof:name":"HR1 1GB",
    "wof:placetype":"postalcode"
},
  "geometry": {"coordinates":[-2.71132757207032,52.07558989837818],"type":"Point"}
}