{
  "type": "Feature",
  "properties": {
    "iso:country": "GB",
    "wof:name": "HR1 1GB",
    "wof:placetype": "postalcode"
  },
  "geometry": {"coordinates":[-2.711328,52.07559],"type":"Point"}
}
