{
  "type": "Feature",
  "properties": {
    "iso:country":"GB",
    "wof:name":"BN2 6BB",
    "wof:placetype":"postalcode"
},
  "geometry": {"coordinates":[-0.07816382165094,50.8361824944887],"type":"Point"}
}