{
  "type": "Feature",
  "properties": {
    "iso:country":"GB",
    "wof:name":"SK13 1DG",
    "wof:placetype":"postalcode"
},
  "geometry": {"coordinates":[-1.97018316287828,53.46372851035937],"type":"Point"}
}