{
  "type": "Feature",
  "properties": {
    "iso:country":"GB",
    "wof:name":"CW11 1TD",
    "wof:placetype":"postalcode"
},
  "geometry": {"coordinates":[-2.38446128560041,53.14705010756189],"type":"Point"}
}