{
  "type": "Feature",
  "properties": {
    "date:inception_lower": "1995-12-01",
    "date:inception_upper": "1995-12-01",
    "iso:country": "GB",
    "wof:name": "CW11 1TD",
    "wof:placetype": "postalcode"
  },
  "geometry": {"coordinates":[-2.384461,53.14705],"type":"Point"}
}
