{
  "type": "Feature",
  "properties": {
    "iso:country":"GB",
    "wof:name":"BB10 2AR",
    "wof:placetype":"postalcode"
},
  "geometry": {"coordinates":[-2.22331059529175,53.80239705862359],"type":"Point"}
}