{
  "type": "Feature",
  "properties": {
    "iso:country":"GB",
    "wof:name":"SE23 3EL",
    "wof:placetype":"postalcode"
},
  "geometry": {"coordinates":[-0.05377508414406,51.44098829551307],"type":"Point"}
}