{
  "type": "Feature",
  "properties": {
    "date:inception_lower":"1985-04-01",
    "date:inception_upper":"1985-04-30",
    "iso:country":"GB",
    "wof:name":"SE23 3EL",
    "wof:placetype":"postalcode"
},
  "geometry": {"coordinates":[-0.053775,51.440988],"type":"Point"}
}