{
  "type": "Feature",
  "properties": {
    "iso:country": "GB",
    "wof:name": "S71 5EL",
    "wof:placetype": "postalcode"
  },
  "geometry": {"coordinates":[-1.422475,53.546659],"type":"Point"}
}
