{
  "type": "Feature",
  "properties": {
    "date:inception_lower": "2007-01-01",
    "date:inception_upper": "2007-01-01",
    "iso:country": "GB",
    "wof:name": "AB21 0EN",
    "wof:placetype": "postalcode"
  },
  "geometry": {"coordinates":[-2.286941,57.21048],"type":"Point"}
}
