{
  "type": "Feature",
  "properties": {
    "iso:country":"GB",
    "wof:name":"AB21 0EN",
    "wof:placetype":"postalcode"
},
  "geometry": {"coordinates":[-2.28694059026973,57.21048011380689],"type":"Point"}
}