{
  "type": "Feature",
  "properties": {
    "iso:country": "GB",
    "wof:name": "BN1 5NJ",
    "wof:placetype": "postalcode"
  },
  "geometry": {"coordinates":[-0.155107,50.843882],"type":"Point"}
}
