{
  "type": "Feature",
  "properties": {
    "iso:country":"GB",
    "wof:name":"DT8 3QU",
    "wof:placetype":"postalcode"
},
  "geometry": {"coordinates":[-2.79594034357701,50.83632155567624],"type":"Point"}
}