{
  "type": "Feature",
  "properties": {
    "iso:country": "GB",
    "wof:name": "DT8 3QU",
    "wof:placetype": "postalcode"
  },
  "geometry": {"coordinates":[-2.79594,50.836322],"type":"Point"}
}
