{
  "type": "Feature",
  "properties": {
    "iso:country": "GB",
    "wof:name": "OX11 9JY",
    "wof:placetype": "postalcode"
  },
  "geometry": {"coordinates":[-1.236541,51.597083],"type":"Point"}
}
