{
  "type": "Feature",
  "properties": {
    "iso:country":"GB",
    "wof:name":"OX11 9JY",
    "wof:placetype":"postalcode"
},
  "geometry": {"coordinates":[-1.23654070594315,51.59708263357208],"type":"Point"}
}