{
  "type": "Feature",
  "properties": {
    "iso:country":"GB",
    "wof:name":"OL4 5RW",
    "wof:placetype":"postalcode"
},
  "geometry": {"coordinates":[-2.06463829829573,53.53261070182452],"type":"Point"}
}