{
  "type": "Feature",
  "properties": {
    "date:inception_lower":"1980-01-01",
    "date:inception_upper":"1980-01-31",
    "iso:country":"GB",
    "wof:name":"G31 4JU",
    "wof:placetype":"postalcode"
},
  "geometry": {"coordinates":[-4.202219,55.848078],"type":"Point"}
}