{
  "type": "Feature",
  "properties": {
    "iso:country":"GB",
    "wof:name":"EH8 9TN",
    "wof:placetype":"postalcode"
},
  "geometry": {"coordinates":[-3.18238857962698,55.94787393273464],"type":"Point"}
}