{
  "type": "Feature",
  "properties": {
    "date:inception_lower": "1992-08-01",
    "date:inception_upper": "1992-08-01",
    "iso:country": "GB",
    "wof:name": "TF9 1NQ",
    "wof:placetype": "postalcode"
  },
  "geometry": {"coordinates":[-2.503637,52.896175],"type":"Point"}
}
