{
  "type": "Feature",
  "properties": {
    "iso:country":"GB",
    "wof:name":"TF9 1NQ",
    "wof:placetype":"postalcode"
},
  "geometry": {"coordinates":[-2.50363734043141,52.89617460308074],"type":"Point"}
}