{
  "type": "Feature",
  "properties": {
    "iso:country": "GB",
    "wof:name": "CM13 1EB",
    "wof:placetype": "postalcode"
  },
  "geometry": {"coordinates":[0.336767,51.633601],"type":"Point"}
}
