{
  "type": "Feature",
  "properties": {
    "iso:country":"GB",
    "wof:name":"CM13 1EB",
    "wof:placetype":"postalcode"
},
  "geometry": {"coordinates":[0.33672781511114,51.6336526774921],"type":"Point"}
}