{
  "type": "Feature",
  "properties": {
    "iso:country":"GB",
    "wof:name":"MK18 1UQ",
    "wof:placetype":"postalcode"
},
  "geometry": {"coordinates":[-0.98080290688608,52.0041301668207],"type":"Point"}
}