{
  "type": "Feature",
  "properties": {
    "date:inception_lower": "1980-01-01",
    "date:inception_upper": "1980-01-01",
    "iso:country": "GB",
    "wof:name": "MK18 1UQ",
    "wof:placetype": "postalcode"
  },
  "geometry": {"coordinates":[-0.980803,52.00413],"type":"Point"}
}
