{
  "type": "Feature",
  "properties": {
    "iso:country":"GB",
    "wof:name":"SA33 5EL",
    "wof:placetype":"postalcode"
},
  "geometry": {"coordinates":[-4.40276978866247,51.86521615591084],"type":"Point"}
}