{
  "type": "Feature",
  "properties": {
    "date:inception_lower": "1980-01-01",
    "date:inception_upper": "1980-01-01",
    "iso:country": "GB",
    "wof:name": "SA33 5EL",
    "wof:placetype": "postalcode"
  },
  "geometry": {"coordinates":[-4.402794,51.865226],"type":"Point"}
}
