{
  "type": "Feature",
  "properties": {
    "iso:country": "GB",
    "wof:name": "CH3 5QS",
    "wof:placetype": "postalcode"
  },
  "geometry": {"coordinates":[-2.849797,53.186381],"type":"Point"}
}
