{
  "type": "Feature",
  "properties": {
    "iso:country":"GB",
    "wof:name":"CH3 5QS",
    "wof:placetype":"postalcode"
},
  "geometry": {"coordinates":[-2.84970522064683,53.18633923644117],"type":"Point"}
}