{
  "type": "Feature",
  "properties": {
    "iso:country":"GB",
    "wof:name":"PL14 3FW",
    "wof:placetype":"postalcode"
},
  "geometry": {"coordinates":[-4.45543634569284,50.46217431457285],"type":"Point"}
}