{
  "type": "Feature",
  "properties": {
    "iso:country":"GB",
    "wof:name":"NW7 4JS",
    "wof:placetype":"postalcode"
},
  "geometry": {"coordinates":[-0.23798041934987,51.62410900116641],"type":"Point"}
}