{
  "type": "Feature",
  "properties": {
    "date:inception_lower":"1980-01-01",
    "date:inception_upper":"1980-01-31",
    "iso:country":"GB",
    "wof:name":"NW7 4JS",
    "wof:placetype":"postalcode"
},
  "geometry": {"coordinates":[-0.23798,51.624109],"type":"Point"}
}