{
  "type": "Feature",
  "properties": {
    "iso:country":"GB",
    "wof:name":"PO19 7DU",
    "wof:placetype":"postalcode"
},
  "geometry": {"coordinates":[-0.77292475327009,50.83227401633833],"type":"Point"}
}