{
  "type": "Feature",
  "properties": {
    "iso:country":"GB",
    "wof:name":"TN2 4BL",
    "wof:placetype":"postalcode"
},
  "geometry": {"coordinates":[0.3335178556894,51.13616305462837],"type":"Point"}
}