{
  "type": "Feature",
  "properties": {
    "date:inception_lower":"1980-01-01",
    "date:inception_upper":"1980-01-31",
    "iso:country":"GB",
    "wof:name":"TN2 4BL",
    "wof:placetype":"postalcode"
},
  "geometry": {"coordinates":[0.336075,51.137846],"type":"Point"}
}