{
  "type": "Feature",
  "properties": {
    "iso:country": "GB",
    "wof:name": "TN2 4BL",
    "wof:placetype": "postalcode"
  },
  "geometry": {"coordinates":[0.336075,51.137846],"type":"Point"}
}
