{
  "type": "Feature",
  "properties": {
    "date:inception_lower": "1980-01-01",
    "date:inception_upper": "1980-01-01",
    "iso:country": "GB",
    "wof:name": "M24 2JJ",
    "wof:placetype": "postalcode"
  },
  "geometry": {"coordinates":[-2.182261,53.551715],"type":"Point"}
}
