{
  "type": "Feature",
  "properties": {
    "iso:country":"GB",
    "wof:name":"TR16 5EL",
    "wof:placetype":"postalcode"
},
  "geometry": {"coordinates":[-5.21173889554377,50.2528960235936],"type":"Point"}
}