{
  "type": "Feature",
  "properties": {
    "iso:country": "GB",
    "wof:name": "TR16 5EL",
    "wof:placetype": "postalcode"
  },
  "geometry": {"coordinates":[-5.213031,50.252609],"type":"Point"}
}
