{
  "type": "Feature",
  "properties": {
    "iso:country":"GB",
    "wof:name":"IP7 5RN",
    "wof:placetype":"postalcode"
},
  "geometry": {"coordinates":[0.94446858187811,52.02234047281492],"type":"Point"}
}