{
  "type": "Feature",
  "properties": {
    "iso:country": "GB",
    "wof:name": "IP7 5RN",
    "wof:placetype": "postalcode"
  },
  "geometry": {"coordinates":[0.9445,52.022354],"type":"Point"}
}
