{
  "type": "Feature",
  "properties": {
    "iso:country":"GB",
    "wof:name":"N16 5UE",
    "wof:placetype":"postalcode"
},
  "geometry": {"coordinates":[-0.0915956775255,51.5643318614877],"type":"Point"}
}