{
  "type": "Feature",
  "properties": {
    "iso:country":"GB",
    "wof:name":"BN2 5PW",
    "wof:placetype":"postalcode"
},
  "geometry": {"coordinates":[-0.10342404011905,50.82020970445519],"type":"Point"}
}