{
  "type": "Feature",
  "properties": {
    "iso:country":"GB",
    "wof:name":"BS13 9PU",
    "wof:placetype":"postalcode"
},
  "geometry": {"coordinates":[-2.60656325513946,51.41061076837659],"type":"Point"}
}