{
  "type": "Feature",
  "properties": {
    "iso:country":"GB",
    "wof:name":"ML12 6ED",
    "wof:placetype":"postalcode"
},
  "geometry": {"coordinates":[-3.5235261868408,55.62558591380073],"type":"Point"}
}