{
  "type": "Feature",
  "properties": {
    "iso:country": "GB",
    "wof:name": "S42 6RY",
    "wof:placetype": "postalcode"
  },
  "geometry": {"coordinates":[-1.448048,53.206379],"type":"Point"}
}
