{
  "type": "Feature",
  "properties": {
    "iso:country":"GB",
    "wof:name":"S42 6RY",
    "wof:placetype":"postalcode"
},
  "geometry": {"coordinates":[-1.44803445145556,53.20636834565904],"type":"Point"}
}