{
  "type": "Feature",
  "properties": {
    "iso:country":"GB",
    "wof:name":"LE5 2ET",
    "wof:placetype":"postalcode"
},
  "geometry": {"coordinates":[-1.06979825695961,52.63958653070542],"type":"Point"}
}