{
  "type": "Feature",
  "properties": {
    "date:inception_lower":"1980-01-01",
    "date:inception_upper":"1980-01-31",
    "iso:country":"GB",
    "wof:name":"LU1 2TB",
    "wof:placetype":"postalcode"
},
  "geometry": {"coordinates":[-0.41136,51.879596],"type":"Point"}
}