{
  "type": "Feature",
  "properties": {
    "iso:country":"GB",
    "wof:name":"LU1 2TB",
    "wof:placetype":"postalcode"
},
  "geometry": {"coordinates":[-0.41136051738704,51.87959649219923],"type":"Point"}
}