{
  "type": "Feature",
  "properties": {
    "iso:country":"GB",
    "wof:name":"SO19 6HY",
    "wof:placetype":"postalcode"
},
  "geometry": {"coordinates":[-1.33065102077125,50.90633542107343],"type":"Point"}
}