{
  "type": "Feature",
  "properties": {
    "iso:country":"GB",
    "wof:name":"TS17 0FP",
    "wof:placetype":"postalcode"
},
  "geometry": {"coordinates":[-1.31968958864656,54.51373670915202],"type":"Point"}
}