{
  "type": "Feature",
  "properties": {
    "iso:country": "GB",
    "wof:name": "TS17 0FP",
    "wof:placetype": "postalcode"
  },
  "geometry": {"coordinates":[-1.31969,54.513737],"type":"Point"}
}
