{
  "type": "Feature",
  "properties": {
    "iso:country":"GB",
    "wof:name":"LN5 7UB",
    "wof:placetype":"postalcode"
},
  "geometry": {"coordinates":[-0.53646036448053,53.22084705908183],"type":"Point"}
}