{
  "type": "Feature",
  "properties": {
    "iso:country": "GB",
    "wof:name": "NR19 1PA",
    "wof:placetype": "postalcode"
  },
  "geometry": {"coordinates":[0.938415,52.672274],"type":"Point"}
}
