{
  "type": "Feature",
  "properties": {
    "iso:country":"GB",
    "wof:name":"SW1X 8AS",
    "wof:placetype":"postalcode"
},
  "geometry": {"coordinates":[-0.15293150814551,51.49626025027459],"type":"Point"}
}