{
  "type": "Feature",
  "properties": {
    "iso:country": "GB",
    "wof:name": "SW1X 8AS",
    "wof:placetype": "postalcode"
  },
  "geometry": {"coordinates":[-0.152931,51.49626],"type":"Point"}
}
