{
  "type": "Feature",
  "properties": {
    "date:inception_lower": "2022-07-01",
    "date:inception_upper": "2022-07-01",
    "iso:country": "GB",
    "wof:name": "LA14 2FE",
    "wof:placetype": "postalcode"
  },
  "geometry": {"coordinates":[-3.220366,54.109196],"type":"Point"}
}
