{
  "type": "Feature",
  "properties": {
    "iso:country":"GB",
    "wof:name":"IG9 5EB",
    "wof:placetype":"postalcode"
},
  "geometry": {"coordinates":[0.04271019492297,51.62496485111964],"type":"Point"}
}