{
  "type": "Feature",
  "properties": {
    "iso:country":"GB",
    "wof:name":"ML2 8DF",
    "wof:placetype":"postalcode"
},
  "geometry": {"coordinates":[-3.91257229328549,55.77143057851963],"type":"Point"}
}