{
  "type": "Feature",
  "properties": {
    "date:inception_lower": "1980-01-01",
    "date:inception_upper": "1980-01-01",
    "iso:country": "GB",
    "wof:name": "ML2 8DF",
    "wof:placetype": "postalcode"
  },
  "geometry": {"coordinates":[-3.912572,55.771431],"type":"Point"}
}
