{
  "type": "Feature",
  "properties": {
    "iso:country":"GB",
    "wof:name":"WS12 4SX",
    "wof:placetype":"postalcode"
},
  "geometry": {"coordinates":[-2.01653915128048,52.72095891311606],"type":"Point"}
}