{
  "type": "Feature",
  "properties": {
    "iso:country":"GB",
    "wof:name":"CV9 3PE",
    "wof:placetype":"postalcode"
},
  "geometry": {"coordinates":[-1.5285286760753,52.59474255295722],"type":"Point"}
}