{
  "type": "Feature",
  "properties": {
    "iso:country": "GB",
    "wof:name": "CV9 3PE",
    "wof:placetype": "postalcode"
  },
  "geometry": {"coordinates":[-1.528529,52.594743],"type":"Point"}
}
