{
  "type": "Feature",
  "properties": {
    "date:inception_lower": "1980-01-01",
    "date:inception_upper": "1980-01-01",
    "iso:country": "GB",
    "wof:name": "LL53 6EA",
    "wof:placetype": "postalcode"
  },
  "geometry": {"coordinates":[-4.523841,52.935768],"type":"Point"}
}
