{
  "type": "Feature",
  "properties": {
    "iso:country":"GB",
    "wof:name":"LL53 6EA",
    "wof:placetype":"postalcode"
},
  "geometry": {"coordinates":[-4.52384107327506,52.93576752204992],"type":"Point"}
}