{
  "type": "Feature",
  "properties": {
    "iso:country":"GB",
    "wof:name":"LU2 0AL",
    "wof:placetype":"postalcode"
},
  "geometry": {"coordinates":[-0.40679552329537,51.8817377365924],"type":"Point"}
}