{
  "type": "Feature",
  "properties": {
    "date:inception_lower":"1980-01-01",
    "date:inception_upper":"1980-01-31",
    "iso:country":"GB",
    "wof:name":"SA5 9JT",
    "wof:placetype":"postalcode"
},
  "geometry": {"coordinates":[-3.947421,51.64189],"type":"Point"}
}