{
  "type": "Feature",
  "properties": {
    "iso:country":"GB",
    "wof:name":"NG7 2EH",
    "wof:placetype":"postalcode"
},
  "geometry": {"coordinates":[-1.17974414180769,52.9528181847822],"type":"Point"}
}