{
  "type": "Feature",
  "properties": {
    "iso:country":"GB",
    "wof:name":"TW10 7QW",
    "wof:placetype":"postalcode"
},
  "geometry": {"coordinates":[-0.31970527225638,51.43735933568397],"type":"Point"}
}