{
  "type": "Feature",
  "properties": {
    "iso:country": "GB",
    "wof:name": "KY13 8TP",
    "wof:placetype": "postalcode"
  },
  "geometry": {"coordinates":[-3.428152,56.207741],"type":"Point"}
}
