{
  "type": "Feature",
  "properties": {
    "iso:country":"GB",
    "wof:name":"SY5 8AT",
    "wof:placetype":"postalcode"
},
  "geometry": {"coordinates":[-2.81639730316311,52.66173655812607],"type":"Point"}
}