{
  "type": "Feature",
  "properties": {
    "iso:country": "GB",
    "wof:name": "SY5 8AT",
    "wof:placetype": "postalcode"
  },
  "geometry": {"coordinates":[-2.816397,52.661737],"type":"Point"}
}
