{
  "type": "Feature",
  "properties": {
    "iso:country": "GB",
    "wof:name": "SK17 0AX",
    "wof:placetype": "postalcode"
  },
  "geometry": {"coordinates":[-1.800407,53.120762],"type":"Point"}
}
