{
  "type": "Feature",
  "properties": {
    "iso:country": "GB",
    "wof:name": "SR3 3RH",
    "wof:placetype": "postalcode"
  },
  "geometry": {"coordinates":[-1.442649,54.86883],"type":"Point"}
}
