{
  "type": "Feature",
  "properties": {
    "iso:country":"GB",
    "wof:name":"SR3 3RH",
    "wof:placetype":"postalcode"
},
  "geometry": {"coordinates":[-1.44264934418434,54.86883018578362],"type":"Point"}
}