{
  "type": "Feature",
  "properties": {
    "iso:country": "GB",
    "wof:name": "G43 2AS",
    "wof:placetype": "postalcode"
  },
  "geometry": {"coordinates":[-4.266381,55.821239],"type":"Point"}
}
