{
  "type": "Feature",
  "properties": {
    "date:inception_lower": "2020-01-01",
    "date:inception_upper": "2020-01-01",
    "iso:country": "GB",
    "wof:name": "G43 2AS",
    "wof:placetype": "postalcode"
  },
  "geometry": {"coordinates":[-4.266381,55.821239],"type":"Point"}
}
