{
  "type": "Feature",
  "properties": {
    "date:inception_lower": "1995-12-01",
    "date:inception_upper": "1995-12-01",
    "iso:country": "GB",
    "wof:name": "BR1 3BH",
    "wof:placetype": "postalcode"
  },
  "geometry": {"coordinates":[0.029744,51.404365],"type":"Point"}
}
