{
  "type": "Feature",
  "properties": {
    "iso:country":"GB",
    "wof:name":"BR1 3BH",
    "wof:placetype":"postalcode"
},
  "geometry": {"coordinates":[0.02974421227991,51.40436481195281],"type":"Point"}
}