{
  "type": "Feature",
  "properties": {
    "iso:country":"GB",
    "wof:name":"N18 1BS",
    "wof:placetype":"postalcode"
},
  "geometry": {"coordinates":[-0.08651687944595,51.61414833597873],"type":"Point"}
}