{
  "type": "Feature",
  "properties": {
    "iso:country":"GB",
    "wof:name":"NN1 4RR",
    "wof:placetype":"postalcode"
},
  "geometry": {"coordinates":[-0.87236721004576,52.24514210365304],"type":"Point"}
}