{
  "type": "Feature",
  "properties": {
    "iso:country": "GB",
    "wof:name": "NN1 4RR",
    "wof:placetype": "postalcode"
  },
  "geometry": {"coordinates":[-0.872367,52.245142],"type":"Point"}
}
