{
  "type": "Feature",
  "properties": {
    "date:inception_lower": "2002-11-01",
    "date:inception_upper": "2002-11-01",
    "iso:country": "GB",
    "wof:name": "SK17 6NW",
    "wof:placetype": "postalcode"
  },
  "geometry": {"coordinates":[-1.923521,53.261338],"type":"Point"}
}
