{
  "type": "Feature",
  "properties": {
    "iso:country":"GB",
    "wof:name":"SK17 6NW",
    "wof:placetype":"postalcode"
},
  "geometry": {"coordinates":[-1.92352077053115,53.26133815913582],"type":"Point"}
}