{
  "type": "Feature",
  "properties": {
    "date:inception_lower":"1980-01-01",
    "date:inception_upper":"1980-01-31",
    "iso:country":"GB",
    "wof:name":"WV14 8RF",
    "wof:placetype":"postalcode"
},
  "geometry": {"coordinates":[-2.079038,52.547645],"type":"Point"}
}