{
  "type": "Feature",
  "properties": {
    "iso:country": "GB",
    "wof:name": "WV14 8RF",
    "wof:placetype": "postalcode"
  },
  "geometry": {"coordinates":[-2.079038,52.547645],"type":"Point"}
}
