{
  "type": "Feature",
  "properties": {
    "iso:country":"GB",
    "wof:name":"LU3 3AZ",
    "wof:placetype":"postalcode"
},
  "geometry": {"coordinates":[-0.47162534759354,51.91983189407119],"type":"Point"}
}