{
  "type": "Feature",
  "properties": {
    "iso:country":"GB",
    "wof:name":"SN5 5BH",
    "wof:placetype":"postalcode"
},
  "geometry": {"coordinates":[-1.8330968857369,51.57962832519839],"type":"Point"}
}