{
  "type": "Feature",
  "properties": {
    "date:inception_lower": "1995-01-01",
    "date:inception_upper": "1995-01-01",
    "iso:country": "GB",
    "wof:name": "SN5 5BH",
    "wof:placetype": "postalcode"
  },
  "geometry": {"coordinates":[-1.833097,51.579628],"type":"Point"}
}
