{
  "type": "Feature",
  "properties": {
    "iso:country": "GB",
    "wof:name": "OX12 9QA",
    "wof:placetype": "postalcode"
  },
  "geometry": {"coordinates":[-1.512716,51.585417],"type":"Point"}
}
