{
  "type": "Feature",
  "properties": {
    "iso:country":"GB",
    "wof:name":"LL51 9DZ",
    "wof:placetype":"postalcode"
},
  "geometry": {"coordinates":[-4.29112827304444,52.99817236915003],"type":"Point"}
}