{
  "type": "Feature",
  "properties": {
    "iso:country":"GB",
    "wof:name":"BA13 3LU",
    "wof:placetype":"postalcode"
},
  "geometry": {"coordinates":[-2.19097636226609,51.25845582620735],"type":"Point"}
}