{
  "type": "Feature",
  "properties": {
    "date:inception_lower": "1983-03-01",
    "date:inception_upper": "1983-03-01",
    "iso:country": "GB",
    "wof:name": "NE24 3ST",
    "wof:placetype": "postalcode"
  },
  "geometry": {"coordinates":[-1.513784,55.111648],"type":"Point"}
}
