{
  "type": "Feature",
  "properties": {
    "iso:country":"GB",
    "wof:name":"NE24 3ST",
    "wof:placetype":"postalcode"
},
  "geometry": {"coordinates":[-1.51378403543856,55.11164830089617],"type":"Point"}
}