{
  "type": "Feature",
  "properties": {
    "iso:country":"GB",
    "wof:name":"NW6 2AE",
    "wof:placetype":"postalcode"
},
  "geometry": {"coordinates":[-0.19659356848479,51.54453674639073],"type":"Point"}
}