{
  "type": "Feature",
  "properties": {
    "iso:country":"GB",
    "wof:name":"SA11 5EA",
    "wof:placetype":"postalcode"
},
  "geometry": {"coordinates":[-3.63128715883621,51.74580052087297],"type":"Point"}
}