{
  "type": "Feature",
  "properties": {
    "iso:country": "GB",
    "wof:name": "RG23 7DR",
    "wof:placetype": "postalcode"
  },
  "geometry": {"coordinates":[-1.169594,51.251056],"type":"Point"}
}
