{
  "type": "Feature",
  "properties": {
    "iso:country":"GB",
    "wof:name":"RG23 7DR",
    "wof:placetype":"postalcode"
},
  "geometry": {"coordinates":[-1.16959438915762,51.25105580628335],"type":"Point"}
}