{
  "type": "Feature",
  "properties": {
    "iso:country": "GB",
    "wof:name": "LA14 2BL",
    "wof:placetype": "postalcode"
  },
  "geometry": {"coordinates":[-3.218651,54.112252],"type":"Point"}
}
