{
  "type": "Feature",
  "properties": {
    "iso:country":"GB",
    "wof:name":"RG1 8EG",
    "wof:placetype":"postalcode"
},
  "geometry": {"coordinates":[-0.97846469363476,51.46288846448037],"type":"Point"}
}