{
  "type": "Feature",
  "properties": {
    "date:inception_lower": "1985-04-01",
    "date:inception_upper": "1985-04-01",
    "iso:country": "GB",
    "wof:name": "SN11 0BX",
    "wof:placetype": "postalcode"
  },
  "geometry": {"coordinates":[-2.003368,51.432447],"type":"Point"}
}
