{
  "type": "Feature",
  "properties": {
    "iso:country":"GB",
    "wof:name":"CO10 9SG",
    "wof:placetype":"postalcode"
},
  "geometry": {"coordinates":[0.78507374701347,52.098739906897],"type":"Point"}
}