{
  "type": "Feature",
  "properties": {
    "iso:country":"GB",
    "wof:name":"EH11 2EG",
    "wof:placetype":"postalcode"
},
  "geometry": {"coordinates":[-3.22339004783843,55.94151618867085],"type":"Point"}
}