{
  "type": "Feature",
  "properties": {
    "date:inception_lower": "1982-03-01",
    "date:inception_upper": "1982-03-01",
    "iso:country": "GB",
    "wof:name": "DY4 0BG",
    "wof:placetype": "postalcode"
  },
  "geometry": {"coordinates":[-2.048856,52.546855],"type":"Point"}
}
