{
  "type": "Feature",
  "properties": {
    "date:inception_lower": "2016-03-01",
    "date:inception_upper": "2016-03-01",
    "iso:country": "GB",
    "wof:name": "DT4 9GX",
    "wof:placetype": "postalcode"
  },
  "geometry": {"coordinates":[-2.481146,50.597424],"type":"Point"}
}
