{
  "type": "Feature",
  "properties": {
    "iso:country":"GB",
    "wof:name":"DT4 9GX",
    "wof:placetype":"postalcode"
},
  "geometry": {"coordinates":[-2.4810786344759,50.59745338666867],"type":"Point"}
}