{
  "type": "Feature",
  "properties": {
    "date:inception_lower":"2011-05-01",
    "date:inception_upper":"2011-05-31",
    "iso:country":"GB",
    "wof:name":"OX5 2FA",
    "wof:placetype":"postalcode"
},
  "geometry": {"coordinates":[-1.283873,51.822136],"type":"Point"}
}