{
  "type": "Feature",
  "properties": {
    "date:inception_lower":"1990-07-01",
    "date:inception_upper":"1990-07-31",
    "iso:country":"GB",
    "wof:name":"TS17 0XP",
    "wof:placetype":"postalcode"
},
  "geometry": {"coordinates":[-1.304274,54.517406],"type":"Point"}
}