{
  "type": "Feature",
  "properties": {
    "iso:country":"GB",
    "wof:name":"TS17 0XP",
    "wof:placetype":"postalcode"
},
  "geometry": {"coordinates":[-1.30427358849956,54.51740564240849],"type":"Point"}
}