{
  "type": "Feature",
  "properties": {
    "iso:country":"GB",
    "wof:name":"N14 4RR",
    "wof:placetype":"postalcode"
},
  "geometry": {"coordinates":[-0.12882434479868,51.64397460197728],"type":"Point"}
}