{
  "type": "Feature",
  "properties": {
    "iso:country":"GB",
    "wof:name":"WD18 0TG",
    "wof:placetype":"postalcode"
},
  "geometry": {"coordinates":[-0.39951084919284,51.65570921496467],"type":"Point"}
}