{
  "type": "Feature",
  "properties": {
    "iso:country": "GB",
    "wof:name": "WD18 0TG",
    "wof:placetype": "postalcode"
  },
  "geometry": {"coordinates":[-0.399511,51.655709],"type":"Point"}
}
