{
  "type": "Feature",
  "properties": {
    "date:inception_lower": "2005-09-01",
    "date:inception_upper": "2005-09-01",
    "iso:country": "GB",
    "wof:name": "WD18 0TG",
    "wof:placetype": "postalcode"
  },
  "geometry": {"coordinates":[-0.399511,51.655709],"type":"Point"}
}
