{
  "type": "Feature",
  "properties": {
    "iso:country":"GB",
    "wof:name":"CV21 3UF",
    "wof:placetype":"postalcode"
},
  "geometry": {"coordinates":[-1.24370266591638,52.36931310949353],"type":"Point"}
}