{
  "type": "Feature",
  "properties": {
    "iso:country":"GB",
    "wof:name":"N22 5QF",
    "wof:placetype":"postalcode"
},
  "geometry": {"coordinates":[-0.09712426236912,51.60434816961823],"type":"Point"}
}