{
  "type": "Feature",
  "properties": {
    "iso:country":"GB",
    "wof:name":"WF4 3EX",
    "wof:placetype":"postalcode"
},
  "geometry": {"coordinates":[-1.5174643264988,53.65139876246258],"type":"Point"}
}