{
  "type": "Feature",
  "properties": {
    "iso:country":"GB",
    "wof:name":"PO8 9QJ",
    "wof:placetype":"postalcode"
},
  "geometry": {"coordinates":[-1.01985353111551,50.90605601562644],"type":"Point"}
}