{
  "type": "Feature",
  "properties": {
    "iso:country": "GB",
    "wof:name": "PO8 9QJ",
    "wof:placetype": "postalcode"
  },
  "geometry": {"coordinates":[-1.019853,50.906056],"type":"Point"}
}
