{
  "type": "Feature",
  "properties": {
    "iso:country":"GB",
    "wof:name":"TS27 4HG",
    "wof:placetype":"postalcode"
},
  "geometry": {"coordinates":[-1.28708470414791,54.74662510946671],"type":"Point"}
}