{
  "type": "Feature",
  "properties": {
    "iso:country":"GB",
    "wof:name":"NR12 0DX",
    "wof:placetype":"postalcode"
},
  "geometry": {"coordinates":[1.60968096466731,52.78282637009275],"type":"Point"}
}