{
  "type": "Feature",
  "properties": {
    "iso:country": "GB",
    "wof:name": "NR12 0DX",
    "wof:placetype": "postalcode"
  },
  "geometry": {"coordinates":[1.609681,52.782826],"type":"Point"}
}
