{
  "type": "Feature",
  "properties": {
    "iso:country": "GB",
    "wof:name": "CO5 7JA",
    "wof:placetype": "postalcode"
  },
  "geometry": {"coordinates":[0.939066,51.855545],"type":"Point"}
}
