{
  "type": "Feature",
  "properties": {
    "iso:country": "GB",
    "wof:name": "WD18 7NQ",
    "wof:placetype": "postalcode"
  },
  "geometry": {"coordinates":[-0.407445,51.654136],"type":"Point"}
}
