{
  "type": "Feature",
  "properties": {
    "iso:country":"GB",
    "wof:name":"S63 0QZ",
    "wof:placetype":"postalcode"
},
  "geometry": {"coordinates":[-1.32208474130806,53.54469437958187],"type":"Point"}
}