{
  "type": "Feature",
  "properties": {
    "iso:country": "GB",
    "wof:name": "S63 0QZ",
    "wof:placetype": "postalcode"
  },
  "geometry": {"coordinates":[-1.322085,53.544694],"type":"Point"}
}
