{
  "type": "Feature",
  "properties": {
    "iso:country":"GB",
    "wof:name":"SA6 8LZ",
    "wof:placetype":"postalcode"
},
  "geometry": {"coordinates":[-3.93432110800674,51.65160224687954],"type":"Point"}
}