{
  "type": "Feature",
  "properties": {
    "iso:country": "GB",
    "wof:name": "SA6 8LZ",
    "wof:placetype": "postalcode"
  },
  "geometry": {"coordinates":[-3.934321,51.651602],"type":"Point"}
}
