{
  "type": "Feature",
  "properties": {
    "iso:country":"GB",
    "wof:name":"BD2 4DH",
    "wof:placetype":"postalcode"
},
  "geometry": {"coordinates":[-1.74525073047178,53.81425349424369],"type":"Point"}
}