{
  "type": "Feature",
  "properties": {
    "date:inception_lower": "1980-01-01",
    "date:inception_upper": "1980-01-01",
    "iso:country": "GB",
    "wof:name": "BD2 4DH",
    "wof:placetype": "postalcode"
  },
  "geometry": {"coordinates":[-1.745251,53.814253],"type":"Point"}
}
