{
  "type": "Feature",
  "properties": {
    "date:inception_lower": "1980-01-01",
    "date:inception_upper": "1980-01-01",
    "iso:country": "GB",
    "wof:name": "TS10 3PL",
    "wof:placetype": "postalcode"
  },
  "geometry": {"coordinates":[-1.049851,54.607704],"type":"Point"}
}
