{
  "type": "Feature",
  "properties": {
    "iso:country":"GB",
    "wof:name":"WD4 8QP",
    "wof:placetype":"postalcode"
},
  "geometry": {"coordinates":[-0.44165907930079,51.70017476510251],"type":"Point"}
}