{
  "type": "Feature",
  "properties": {
    "date:inception_lower": "1980-01-01",
    "date:inception_upper": "1980-01-01",
    "iso:country": "GB",
    "wof:name": "WD4 8QP",
    "wof:placetype": "postalcode"
  },
  "geometry": {"coordinates":[-0.44161,51.700135],"type":"Point"}
}
