{
  "type": "Feature",
  "properties": {
    "iso:country":"GB",
    "wof:name":"DL6 1LP",
    "wof:placetype":"postalcode"
},
  "geometry": {"coordinates":[-1.4305996218356,54.34092041177052],"type":"Point"}
}