{
  "type": "Feature",
  "properties": {
    "iso:country":"GB",
    "wof:name":"NP10 9NJ",
    "wof:placetype":"postalcode"
},
  "geometry": {"coordinates":[-3.05923863197891,51.58645582579066],"type":"Point"}
}