{
  "type": "Feature",
  "properties": {
    "date:inception_lower": "1980-01-01",
    "date:inception_upper": "1980-01-01",
    "iso:country": "GB",
    "wof:name": "NR20 5JW",
    "wof:placetype": "postalcode"
  },
  "geometry": {"coordinates":[0.944163,52.74927],"type":"Point"}
}
