{
  "type": "Feature",
  "properties": {
    "iso:country":"GB",
    "wof:name":"NR20 5JW",
    "wof:placetype":"postalcode"
},
  "geometry": {"coordinates":[0.94399850062905,52.74952729234342],"type":"Point"}
}