{
  "type": "Feature",
  "properties": {
    "iso:country": "GB",
    "wof:name": "BH20 9BY",
    "wof:placetype": "postalcode"
  },
  "geometry": {"coordinates":[-2.106415,50.696536],"type":"Point"}
}
