{
  "type": "Feature",
  "properties": {
    "iso:country":"GB",
    "wof:name":"RM15 4HR",
    "wof:placetype":"postalcode"
},
  "geometry": {"coordinates":[0.2504302710087,51.49466242468569],"type":"Point"}
}