{
  "type": "Feature",
  "properties": {
    "iso:country":"GB",
    "wof:name":"PE14 9AH",
    "wof:placetype":"postalcode"
},
  "geometry": {"coordinates":[0.22727482820923,52.60627900833619],"type":"Point"}
}