{
  "type": "Feature",
  "properties": {
    "iso:country": "GB",
    "wof:name": "DN14 5EB",
    "wof:placetype": "postalcode"
  },
  "geometry": {"coordinates":[-0.868839,53.70364],"type":"Point"}
}
