{
  "type": "Feature",
  "properties": {
    "date:inception_lower": "1994-05-01",
    "date:inception_upper": "1994-05-01",
    "iso:country": "GB",
    "wof:name": "SA11 3BN",
    "wof:placetype": "postalcode"
  },
  "geometry": {"coordinates":[-3.799453,51.661597],"type":"Point"}
}
