{
  "type": "Feature",
  "properties": {
    "date:inception_lower": "1980-01-01",
    "date:inception_upper": "1980-01-01",
    "iso:country": "GB",
    "wof:name": "N1 0DF",
    "wof:placetype": "postalcode"
  },
  "geometry": {"coordinates":[-0.121574,51.54095],"type":"Point"}
}
