{
  "type": "Feature",
  "properties": {
    "iso:country":"GB",
    "wof:name":"N1 0DF",
    "wof:placetype":"postalcode"
},
  "geometry": {"coordinates":[-0.12157438822382,51.54094959282882],"type":"Point"}
}