{
  "type": "Feature",
  "properties": {
    "iso:country":"GB",
    "wof:name":"G20 8PT",
    "wof:placetype":"postalcode"
},
  "geometry": {"coordinates":[-4.28521749462911,55.88274767770567],"type":"Point"}
}