{
  "type": "Feature",
  "properties": {
    "date:inception_lower":"1980-01-01",
    "date:inception_upper":"1980-01-31",
    "iso:country":"GB",
    "wof:name":"SY14 8BG",
    "wof:placetype":"postalcode"
},
  "geometry": {"coordinates":[-2.71169,53.086583],"type":"Point"}
}