{
  "type": "Feature",
  "properties": {
    "iso:country":"GB",
    "wof:name":"NW9 5TJ",
    "wof:placetype":"postalcode"
},
  "geometry": {"coordinates":[-0.24781810562361,51.60424849087693],"type":"Point"}
}