{
  "type": "Feature",
  "properties": {
    "iso:country":"GB",
    "wof:name":"TA4 3LH",
    "wof:placetype":"postalcode"
},
  "geometry": {"coordinates":[-3.18710497187896,51.05773378382627],"type":"Point"}
}