{
  "type": "Feature",
  "properties": {
    "iso:country":"GB",
    "wof:name":"GL1 1LH",
    "wof:placetype":"postalcode"
},
  "geometry": {"coordinates":[-2.24480951607589,51.86104841289666],"type":"Point"}
}