{
  "type": "Feature",
  "properties": {
    "date:inception_lower":"2010-05-01",
    "date:inception_upper":"2010-05-31",
    "iso:country":"GB",
    "wof:name":"LA6 1GR",
    "wof:placetype":"postalcode"
},
  "geometry": {"coordinates":[-2.735707,54.155208],"type":"Point"}
}