{
  "type": "Feature",
  "properties": {
    "iso:country": "GB",
    "wof:name": "LA6 1GR",
    "wof:placetype": "postalcode"
  },
  "geometry": {"coordinates":[-2.735707,54.155208],"type":"Point"}
}
