{
  "type": "Feature",
  "properties": {
    "iso:country":"GB",
    "wof:name":"FY4 2QB",
    "wof:placetype":"postalcode"
},
  "geometry": {"coordinates":[-3.04292621792289,53.78099049464159],"type":"Point"}
}