{
  "type": "Feature",
  "properties": {
    "date:inception_lower": "1980-01-01",
    "date:inception_upper": "1980-01-01",
    "iso:country": "GB",
    "wof:name": "FY4 2QB",
    "wof:placetype": "postalcode"
  },
  "geometry": {"coordinates":[-3.042926,53.78099],"type":"Point"}
}
