{
  "type": "Feature",
  "properties": {
    "iso:country": "GB",
    "wof:name": "EX16 4BT",
    "wof:placetype": "postalcode"
  },
  "geometry": {"coordinates":[-3.482299,50.903155],"type":"Point"}
}
