{
  "type": "Feature",
  "properties": {
    "iso:country":"GB",
    "wof:name":"LS10 4SF",
    "wof:placetype":"postalcode"
},
  "geometry": {"coordinates":[-1.51845659586932,53.75815549125714],"type":"Point"}
}