{
  "type": "Feature",
  "properties": {
    "iso:country":"GB",
    "wof:name":"IP3 8QX",
    "wof:placetype":"postalcode"
},
  "geometry": {"coordinates":[1.20460193676112,52.04754709475981],"type":"Point"}
}