{
  "type": "Feature",
  "properties": {
    "date:inception_lower":"1980-01-01",
    "date:inception_upper":"1980-01-31",
    "iso:country":"GB",
    "wof:name":"TD9 7PH",
    "wof:placetype":"postalcode"
},
  "geometry": {"coordinates":[-2.919233,55.40012],"type":"Point"}
}