{
  "type": "Feature",
  "properties": {
    "iso:country":"GB",
    "wof:name":"TD9 7PH",
    "wof:placetype":"postalcode"
},
  "geometry": {"coordinates":[-2.91923300830229,55.40012041510288],"type":"Point"}
}