{
  "type": "Feature",
  "properties": {
    "iso:country": "GB",
    "wof:name": "TD9 7PH",
    "wof:placetype": "postalcode"
  },
  "geometry": {"coordinates":[-2.919233,55.40012],"type":"Point"}
}
