{
  "type": "Feature",
  "properties": {
    "date:inception_lower": "1995-01-01",
    "date:inception_upper": "1995-01-01",
    "iso:country": "GB",
    "wof:name": "YO21 1ED",
    "wof:placetype": "postalcode"
  },
  "geometry": {"coordinates":[-0.61571,54.484189],"type":"Point"}
}
