{
  "type": "Feature",
  "properties": {
    "date:inception_lower":"2001-12-01",
    "date:inception_upper":"2001-12-31",
    "iso:country":"GB",
    "wof:name":"LU7 4BQ",
    "wof:placetype":"postalcode"
},
  "geometry": {"coordinates":[-0.636099,51.907907],"type":"Point"}
}