{
  "type": "Feature",
  "properties": {
    "iso:country": "GB",
    "wof:name": "LU7 4BQ",
    "wof:placetype": "postalcode"
  },
  "geometry": {"coordinates":[-0.636099,51.907907],"type":"Point"}
}
