{
  "type": "Feature",
  "properties": {
    "iso:country":"GB",
    "wof:name":"LU7 4BQ",
    "wof:placetype":"postalcode"
},
  "geometry": {"coordinates":[-0.63609916100864,51.90790677155901],"type":"Point"}
}