{
  "type": "Feature",
  "properties": {
    "iso:country":"GB",
    "wof:name":"ME10 3JX",
    "wof:placetype":"postalcode"
},
  "geometry": {"coordinates":[0.75221565714953,51.34001728676301],"type":"Point"}
}