{
  "type": "Feature",
  "properties": {
    "date:inception_lower": "1980-01-01",
    "date:inception_upper": "1980-01-01",
    "iso:country": "GB",
    "wof:name": "ME10 3JX",
    "wof:placetype": "postalcode"
  },
  "geometry": {"coordinates":[0.752216,51.340017],"type":"Point"}
}
