{
  "type": "Feature",
  "properties": {
    "iso:country": "GB",
    "wof:name": "TQ7 4BJ",
    "wof:placetype": "postalcode"
  },
  "geometry": {"coordinates":[-3.887589,50.283197],"type":"Point"}
}
