{
  "type": "Feature",
  "properties": {
    "iso:country":"GB",
    "wof:name":"TQ7 4BJ",
    "wof:placetype":"postalcode"
},
  "geometry": {"coordinates":[-3.88758885854205,50.28319703390487],"type":"Point"}
}