{
  "type": "Feature",
  "properties": {
    "date:inception_lower": "2009-03-01",
    "date:inception_upper": "2009-03-01",
    "iso:country": "GB",
    "wof:name": "TQ7 4BJ",
    "wof:placetype": "postalcode"
  },
  "geometry": {"coordinates":[-3.887589,50.283197],"type":"Point"}
}
