{
  "type": "Feature",
  "properties": {
    "iso:country": "GB",
    "wof:name": "LS27 9EZ",
    "wof:placetype": "postalcode"
  },
  "geometry": {"coordinates":[-1.59439,53.740343],"type":"Point"}
}
