{
  "type": "Feature",
  "properties": {
    "iso:country":"GB",
    "wof:name":"AL1 4RZ",
    "wof:placetype":"postalcode"
},
  "geometry": {"coordinates":[-0.31509574009446,51.76093126287405],"type":"Point"}
}