{
  "type": "Feature",
  "properties": {
    "iso:country":"GB",
    "wof:name":"LL24 0YE",
    "wof:placetype":"postalcode"
},
  "geometry": {"coordinates":[-3.80327879699218,53.03915626423155],"type":"Point"}
}