{
  "type": "Feature",
  "properties": {
    "iso:country": "GB",
    "wof:name": "LL24 0YE",
    "wof:placetype": "postalcode"
  },
  "geometry": {"coordinates":[-3.803279,53.039156],"type":"Point"}
}
