{
  "type": "Feature",
  "properties": {
    "iso:country":"GB",
    "wof:name":"G69 7SL",
    "wof:placetype":"postalcode"
},
  "geometry": {"coordinates":[-4.07644754048721,55.8534650818045],"type":"Point"}
}