{
  "type": "Feature",
  "properties": {
    "iso:country":"GB",
    "wof:name":"PR9 7JX",
    "wof:placetype":"postalcode"
},
  "geometry": {"coordinates":[-2.97513949706722,53.65550688754767],"type":"Point"}
}