{
  "type": "Feature",
  "properties": {
    "iso:country":"GB",
    "wof:name":"W2 1NH",
    "wof:placetype":"postalcode"
},
  "geometry": {"coordinates":[-0.17136204815313,51.51810405875089],"type":"Point"}
}