{
  "type": "Feature",
  "properties": {
    "iso:country": "GB",
    "wof:name": "W2 1NH",
    "wof:placetype": "postalcode"
  },
  "geometry": {"coordinates":[-0.171362,51.518104],"type":"Point"}
}
