{
  "type": "Feature",
  "properties": {
    "iso:country": "GB",
    "wof:name": "BA2 2HB",
    "wof:placetype": "postalcode"
  },
  "geometry": {"coordinates":[-2.38402,51.369722],"type":"Point"}
}
