{
  "type": "Feature",
  "properties": {
    "iso:country":"GB",
    "wof:name":"BA2 2HB",
    "wof:placetype":"postalcode"
},
  "geometry": {"coordinates":[-2.38402040576231,51.36972236314862],"type":"Point"}
}