{
  "type": "Feature",
  "properties": {
    "iso:country": "GB",
    "wof:name": "NR7 8GB",
    "wof:placetype": "postalcode"
  },
  "geometry": {"coordinates":[1.348208,52.656899],"type":"Point"}
}
