{
  "type": "Feature",
  "properties": {
    "date:inception_lower":"1980-01-01",
    "date:inception_upper":"1980-01-31",
    "iso:country":"GB",
    "wof:name":"LL54 5LW",
    "wof:placetype":"postalcode"
},
  "geometry": {"coordinates":[-4.427298,52.993517],"type":"Point"}
}