{
  "type": "Feature",
  "properties": {
    "iso:country":"GB",
    "wof:name":"LS6 1NG",
    "wof:placetype":"postalcode"
},
  "geometry": {"coordinates":[-1.57435287171266,53.81179183108707],"type":"Point"}
}