{
  "type": "Feature",
  "properties": {
    "iso:country": "GB",
    "wof:name": "LS6 1NG",
    "wof:placetype": "postalcode"
  },
  "geometry": {"coordinates":[-1.574353,53.811792],"type":"Point"}
}
