{
  "type": "Feature",
  "properties": {
    "date:inception_lower": "1980-01-01",
    "date:inception_upper": "1980-01-01",
    "iso:country": "GB",
    "wof:name": "PL20 6RQ",
    "wof:placetype": "postalcode"
  },
  "geometry": {"coordinates":[-3.994809,50.547074],"type":"Point"}
}
