{
  "type": "Feature",
  "properties": {
    "iso:country":"GB",
    "wof:name":"PL20 6RQ",
    "wof:placetype":"postalcode"
},
  "geometry": {"coordinates":[-3.99450555129828,50.54681073700816],"type":"Point"}
}