{
  "type": "Feature",
  "properties": {
    "iso:country":"GB",
    "wof:name":"CF31 3HT",
    "wof:placetype":"postalcode"
},
  "geometry": {"coordinates":[-3.57453211348692,51.49878089897547],"type":"Point"}
}