{
  "type": "Feature",
  "properties": {
    "date:inception_lower": "1980-01-01",
    "date:inception_upper": "1980-01-01",
    "iso:country": "GB",
    "wof:name": "CF31 3HT",
    "wof:placetype": "postalcode"
  },
  "geometry": {"coordinates":[-3.574532,51.498781],"type":"Point"}
}
