{
  "type": "Feature",
  "properties": {
    "iso:country": "GB",
    "wof:name": "HR4 7BJ",
    "wof:placetype": "postalcode"
  },
  "geometry": {"coordinates":[-2.909887,52.129598],"type":"Point"}
}
