{
  "type": "Feature",
  "properties": {
    "iso:country":"GB",
    "wof:name":"HR4 7BJ",
    "wof:placetype":"postalcode"
},
  "geometry": {"coordinates":[-2.90988695247103,52.12959835806503],"type":"Point"}
}