{
  "type": "Feature",
  "properties": {
    "iso:country":"GB",
    "wof:name":"KT21 2AH",
    "wof:placetype":"postalcode"
},
  "geometry": {"coordinates":[-0.30098255724699,51.30861321385083],"type":"Point"}
}