{
  "type": "Feature",
  "properties": {
    "iso:country": "GB",
    "wof:name": "KT21 2AH",
    "wof:placetype": "postalcode"
  },
  "geometry": {"coordinates":[-0.300983,51.308613],"type":"Point"}
}
