{
  "type": "Feature",
  "properties": {
    "date:inception_lower":"1980-01-01",
    "date:inception_upper":"1980-01-31",
    "iso:country":"GB",
    "wof:name":"SA10 6RU",
    "wof:placetype":"postalcode"
},
  "geometry": {"coordinates":[-3.863893,51.659387],"type":"Point"}
}