{
  "type": "Feature",
  "properties": {
    "iso:country":"GB",
    "wof:name":"SA10 6RU",
    "wof:placetype":"postalcode"
},
  "geometry": {"coordinates":[-3.86389298301074,51.65938695196194],"type":"Point"}
}