{
  "type": "Feature",
  "properties": {
    "date:inception_lower":"2016-02-01",
    "date:inception_upper":"2016-02-29",
    "iso:country":"GB",
    "wof:name":"NE13 6BB",
    "wof:placetype":"postalcode"
},
  "geometry": {"coordinates":[-1.630347,55.057566],"type":"Point"}
}