{
  "type": "Feature",
  "properties": {
    "date:inception_lower": "2007-01-01",
    "date:inception_upper": "2007-01-01",
    "iso:country": "GB",
    "wof:name": "B73 5PU",
    "wof:placetype": "postalcode"
  },
  "geometry": {"coordinates":[-1.829107,52.553664],"type":"Point"}
}
