{
  "type": "Feature",
  "properties": {
    "date:inception_lower":"1980-01-01",
    "date:inception_upper":"1980-01-31",
    "iso:country":"GB",
    "wof:name":"B27 7LG",
    "wof:placetype":"postalcode"
},
  "geometry": {"coordinates":[-1.81921,52.431485],"type":"Point"}
}