{
  "type": "Feature",
  "properties": {
    "iso:country":"GB",
    "wof:name":"B27 7LG",
    "wof:placetype":"postalcode"
},
  "geometry": {"coordinates":[-1.81921019210633,52.43148526364616],"type":"Point"}
}