{
  "type": "Feature",
  "properties": {
    "iso:country":"GB",
    "wof:name":"CB9 0NP",
    "wof:placetype":"postalcode"
},
  "geometry": {"coordinates":[0.46225749576962,52.07787970433836],"type":"Point"}
}