{
  "type": "Feature",
  "properties": {
    "date:inception_lower": "1987-04-01",
    "date:inception_upper": "1987-04-01",
    "iso:country": "GB",
    "wof:name": "CB9 0NP",
    "wof:placetype": "postalcode"
  },
  "geometry": {"coordinates":[0.462258,52.07788],"type":"Point"}
}
