{
  "type": "Feature",
  "properties": {
    "date:inception_lower":"1980-01-01",
    "date:inception_upper":"1980-01-31",
    "iso:country":"GB",
    "wof:name":"CW5 8DE",
    "wof:placetype":"postalcode"
},
  "geometry": {"coordinates":[-2.57723,53.012135],"type":"Point"}
}