{
  "type": "Feature",
  "properties": {
    "iso:country":"GB",
    "wof:name":"HA6 2LS",
    "wof:placetype":"postalcode"
},
  "geometry": {"coordinates":[-0.43947237263759,51.62783226557189],"type":"Point"}
}