{
  "type": "Feature",
  "properties": {
    "iso:country": "GB",
    "wof:name": "HA6 2LS",
    "wof:placetype": "postalcode"
  },
  "geometry": {"coordinates":[-0.439472,51.627832],"type":"Point"}
}
