{
  "type": "Feature",
  "properties": {
    "iso:country":"GB",
    "wof:name":"PL7 1NW",
    "wof:placetype":"postalcode"
},
  "geometry": {"coordinates":[-4.04404383251073,50.38198796082904],"type":"Point"}
}