{
  "type": "Feature",
  "properties": {
    "iso:country": "GB",
    "wof:name": "PL7 1NW",
    "wof:placetype": "postalcode"
  },
  "geometry": {"coordinates":[-4.044044,50.381988],"type":"Point"}
}
