{
  "type": "Feature",
  "properties": {
    "iso:country": "GB",
    "wof:name": "CF39 8JF",
    "wof:placetype": "postalcode"
  },
  "geometry": {"coordinates":[-3.453988,51.581959],"type":"Point"}
}
