{
  "type": "Feature",
  "properties": {
    "date:inception_lower": "1997-12-01",
    "date:inception_upper": "1997-12-01",
    "iso:country": "GB",
    "wof:name": "CF39 8JF",
    "wof:placetype": "postalcode"
  },
  "geometry": {"coordinates":[-3.453988,51.581959],"type":"Point"}
}
