{
  "type": "Feature",
  "properties": {
    "iso:country":"GB",
    "wof:name":"AB39 2GU",
    "wof:placetype":"postalcode"
},
  "geometry": {"coordinates":[-2.2298027686567,56.96405590581264],"type":"Point"}
}