{
  "type": "Feature",
  "properties": {
    "iso:country":"GB",
    "wof:name":"G40 4AB",
    "wof:placetype":"postalcode"
},
  "geometry": {"coordinates":[-4.22527953065319,55.84795061016044],"type":"Point"}
}