{
  "type": "Feature",
  "properties": {
    "iso:country": "GB",
    "wof:name": "OL10 3LN",
    "wof:placetype": "postalcode"
  },
  "geometry": {"coordinates":[-2.247046,53.59112],"type":"Point"}
}
