{
  "type": "Feature",
  "properties": {
    "iso:country": "GB",
    "wof:name": "SA1 3TD",
    "wof:placetype": "postalcode"
  },
  "geometry": {"coordinates":[-3.952193,51.616371],"type":"Point"}
}
