{
  "type": "Feature",
  "properties": {
    "iso:country": "GB",
    "wof:name": "GL50 2DL",
    "wof:placetype": "postalcode"
  },
  "geometry": {"coordinates":[-2.082418,51.888003],"type":"Point"}
}
