{
  "type": "Feature",
  "properties": {
    "date:inception_lower": "2002-07-01",
    "date:inception_upper": "2002-07-01",
    "iso:country": "GB",
    "wof:name": "GL50 2DL",
    "wof:placetype": "postalcode"
  },
  "geometry": {"coordinates":[-2.082418,51.888057],"type":"Point"}
}
