{
  "type": "Feature",
  "properties": {
    "iso:country":"GB",
    "wof:name":"GU10 1NZ",
    "wof:placetype":"postalcode"
},
  "geometry": {"coordinates":[-0.76682863017441,51.22048449173781],"type":"Point"}
}