{
  "type": "Feature",
  "properties": {
    "iso:country":"GB",
    "wof:name":"G83 7AX",
    "wof:placetype":"postalcode"
},
  "geometry": {"coordinates":[-4.75157952836038,56.19307556193573],"type":"Point"}
}