{
  "type": "Feature",
  "properties": {
    "date:inception_lower":"1991-09-01",
    "date:inception_upper":"1991-09-30",
    "iso:country":"GB",
    "wof:name":"DN3 2DD",
    "wof:placetype":"postalcode"
},
  "geometry": {"coordinates":[-1.061678,53.538054],"type":"Point"}
}