{
  "type": "Feature",
  "properties": {
    "iso:country":"GB",
    "wof:name":"DN3 2DD",
    "wof:placetype":"postalcode"
},
  "geometry": {"coordinates":[-1.06167790108398,53.53805443425777],"type":"Point"}
}