{
  "type": "Feature",
  "properties": {
    "iso:country":"GB",
    "wof:name":"W1K 3NT",
    "wof:placetype":"postalcode"
},
  "geometry": {"coordinates":[-0.14805090893257,51.51004073923089],"type":"Point"}
}