{
  "type": "Feature",
  "properties": {
    "iso:country": "GB",
    "wof:name": "WS11 1RL",
    "wof:placetype": "postalcode"
  },
  "geometry": {"coordinates":[-2.056343,52.696862],"type":"Point"}
}
