{
  "type": "Feature",
  "properties": {
    "iso:country":"GB",
    "wof:name":"WS11 1RL",
    "wof:placetype":"postalcode"
},
  "geometry": {"coordinates":[-2.05443519351291,52.69325049454144],"type":"Point"}
}