{
  "type": "Feature",
  "properties": {
    "date:inception_lower": "1999-06-01",
    "date:inception_upper": "1999-06-01",
    "iso:country": "GB",
    "wof:name": "CH62 8BS",
    "wof:placetype": "postalcode"
  },
  "geometry": {"coordinates":[-2.968058,53.312722],"type":"Point"}
}
