{
  "type": "Feature",
  "properties": {
    "iso:country":"GB",
    "wof:name":"CH62 8BS",
    "wof:placetype":"postalcode"
},
  "geometry": {"coordinates":[-2.96805783610345,53.31272242771728],"type":"Point"}
}