{
  "type": "Feature",
  "properties": {
    "iso:country": "GB",
    "wof:name": "CH62 8BS",
    "wof:placetype": "postalcode"
  },
  "geometry": {"coordinates":[-2.968058,53.312722],"type":"Point"}
}
