{
  "type": "Feature",
  "properties": {
    "iso:country":"GB",
    "wof:name":"B60 1JE",
    "wof:placetype":"postalcode"
},
  "geometry": {"coordinates":[-2.04539375942531,52.35088318699827],"type":"Point"}
}