{
  "type": "Feature",
  "properties": {
    "iso:country": "GB",
    "wof:name": "LE17 5NE",
    "wof:placetype": "postalcode"
  },
  "geometry": {"coordinates":[-1.172283,52.507411],"type":"Point"}
}
