{
  "type": "Feature",
  "properties": {
    "iso:country": "GB",
    "wof:name": "RG14 6BW",
    "wof:placetype": "postalcode"
  },
  "geometry": {"coordinates":[-1.34212,51.395851],"type":"Point"}
}
