{
  "type": "Feature",
  "properties": {
    "iso:country":"GB",
    "wof:name":"TW15 3LL",
    "wof:placetype":"postalcode"
},
  "geometry": {"coordinates":[-0.47739642251808,51.43210387979993],"type":"Point"}
}