{
  "type": "Feature",
  "properties": {
    "iso:country":"GB",
    "wof:name":"RG20 9LP",
    "wof:placetype":"postalcode"
},
  "geometry": {"coordinates":[-1.34251393953658,51.31713000365399],"type":"Point"}
}