{
  "type": "Feature",
  "properties": {
    "date:inception_lower": "1995-07-01",
    "date:inception_upper": "1995-07-01",
    "iso:country": "GB",
    "wof:name": "RG20 9LP",
    "wof:placetype": "postalcode"
  },
  "geometry": {"coordinates":[-1.342514,51.31713],"type":"Point"}
}
