{
  "type": "Feature",
  "properties": {
    "date:inception_lower": "1980-01-01",
    "date:inception_upper": "1980-01-01",
    "iso:country": "GB",
    "wof:name": "DL17 0QE",
    "wof:placetype": "postalcode"
  },
  "geometry": {"coordinates":[-1.549475,54.660416],"type":"Point"}
}
