{
  "type": "Feature",
  "properties": {
    "iso:country":"GB",
    "wof:name":"DL17 0QE",
    "wof:placetype":"postalcode"
},
  "geometry": {"coordinates":[-1.54947494467615,54.66041563641978],"type":"Point"}
}