{
  "type": "Feature",
  "properties": {
    "iso:country":"GB",
    "wof:name":"DG3 4BU",
    "wof:placetype":"postalcode"
},
  "geometry": {"coordinates":[-3.81754748512947,55.23149424867822],"type":"Point"}
}