{
  "type": "Feature",
  "properties": {
    "iso:country":"GB",
    "wof:name":"SW1X 8GG",
    "wof:placetype":"postalcode"
},
  "geometry": {"coordinates":[-0.15709991337014,51.49899660449493],"type":"Point"}
}