{
  "type": "Feature",
  "properties": {
    "date:inception_lower": "1980-01-01",
    "date:inception_upper": "1980-01-01",
    "iso:country": "GB",
    "wof:name": "HP23 5RJ",
    "wof:placetype": "postalcode"
  },
  "geometry": {"coordinates":[-0.602347,51.800008],"type":"Point"}
}
