{
  "type": "Feature",
  "properties": {
    "iso:country":"GB",
    "wof:name":"HP23 5RJ",
    "wof:placetype":"postalcode"
},
  "geometry": {"coordinates":[-0.60234663106067,51.8000078531186],"type":"Point"}
}