{
  "type": "Feature",
  "properties": {
    "iso:country":"GB",
    "wof:name":"M3 4EP",
    "wof:placetype":"postalcode"
},
  "geometry": {"coordinates":[-2.24813095691581,53.47724434192541],"type":"Point"}
}