{
  "type": "Feature",
  "properties": {
    "date:inception_lower":"1980-01-01",
    "date:inception_upper":"1980-01-31",
    "iso:country":"GB",
    "wof:name":"SK6 3HQ",
    "wof:placetype":"postalcode"
},
  "geometry": {"coordinates":[-2.102177,53.408634],"type":"Point"}
}