{
  "type": "Feature",
  "properties": {
    "date:inception_lower": "2018-11-01",
    "date:inception_upper": "2018-11-01",
    "iso:country": "GB",
    "wof:name": "SN3 6FP",
    "wof:placetype": "postalcode"
  },
  "geometry": {"coordinates":[-1.724651,51.533668],"type":"Point"}
}
