{
  "type": "Feature",
  "properties": {
    "iso:country":"GB",
    "wof:name":"N15 6TB",
    "wof:placetype":"postalcode"
},
  "geometry": {"coordinates":[-0.07149027935601,51.57813036138869],"type":"Point"}
}