{
  "type": "Feature",
  "properties": {
    "iso:country": "GB",
    "wof:name": "N15 6TB",
    "wof:placetype": "postalcode"
  },
  "geometry": {"coordinates":[-0.07149,51.57813],"type":"Point"}
}
