{
  "type": "Feature",
  "properties": {
    "iso:country": "GB",
    "wof:name": "E15 4PT",
    "wof:placetype": "postalcode"
  },
  "geometry": {"coordinates":[0.005613,51.53754],"type":"Point"}
}
