{
  "type": "Feature",
  "properties": {
    "date:inception_lower": "1980-01-01",
    "date:inception_upper": "1980-01-01",
    "iso:country": "GB",
    "wof:name": "WA15 8NW",
    "wof:placetype": "postalcode"
  },
  "geometry": {"coordinates":[-2.314384,53.38181],"type":"Point"}
}
