{
  "type": "Feature",
  "properties": {
    "date:inception_lower": "1992-08-01",
    "date:inception_upper": "1992-08-01",
    "iso:country": "GB",
    "wof:name": "DE21 6JA",
    "wof:placetype": "postalcode"
  },
  "geometry": {"coordinates":[-1.444236,52.93228],"type":"Point"}
}
