{
  "type": "Feature",
  "properties": {
    "iso:country": "GB",
    "wof:name": "DG1 4TZ",
    "wof:placetype": "postalcode"
  },
  "geometry": {"coordinates":[-3.584825,55.026732],"type":"Point"}
}
