{
  "type": "Feature",
  "properties": {
    "iso:country":"GB",
    "wof:name":"M30 0RW",
    "wof:placetype":"postalcode"
},
  "geometry": {"coordinates":[-2.35776847848166,53.48370754692613],"type":"Point"}
}