{
  "type": "Feature",
  "properties": {
    "iso:country":"GB",
    "wof:name":"G44 4DA",
    "wof:placetype":"postalcode"
},
  "geometry": {"coordinates":[-4.26203356021787,55.81926605802286],"type":"Point"}
}