{
  "type": "Feature",
  "properties": {
    "iso:country": "GB",
    "wof:name": "PR7 6PH",
    "wof:placetype": "postalcode"
  },
  "geometry": {"coordinates":[-2.661438,53.662108],"type":"Point"}
}
