{
  "type": "Feature",
  "properties": {
    "iso:country": "GB",
    "wof:name": "WS13 7TE",
    "wof:placetype": "postalcode"
  },
  "geometry": {"coordinates":[-1.820887,52.701748],"type":"Point"}
}
