{
  "type": "Feature",
  "properties": {
    "iso:country": "GB",
    "wof:name": "NE23 6ES",
    "wof:placetype": "postalcode"
  },
  "geometry": {"coordinates":[-1.587999,55.074557],"type":"Point"}
}
