{
  "type": "Feature",
  "properties": {
    "iso:country": "GB",
    "wof:name": "DD6 8BQ",
    "wof:placetype": "postalcode"
  },
  "geometry": {"coordinates":[-3.042084,56.410393],"type":"Point"}
}
