{
  "type": "Feature",
  "properties": {
    "date:inception_lower":"1993-01-01",
    "date:inception_upper":"1993-01-31",
    "iso:country":"GB",
    "wof:name":"ME2 1NQ",
    "wof:placetype":"postalcode"
},
  "geometry": {"coordinates":[0.449132,51.349358],"type":"Point"}
}