{
  "type": "Feature",
  "properties": {
    "iso:country":"GB",
    "wof:name":"ME2 1NQ",
    "wof:placetype":"postalcode"
},
  "geometry": {"coordinates":[0.44913170123062,51.34935756238693],"type":"Point"}
}