{
  "type": "Feature",
  "properties": {
    "iso:country": "GB",
    "wof:name": "NE35 9LP",
    "wof:placetype": "postalcode"
  },
  "geometry": {"coordinates":[-1.465474,54.949074],"type":"Point"}
}
