{
  "type": "Feature",
  "properties": {
    "iso:country":"GB",
    "wof:name":"NE35 9LP",
    "wof:placetype":"postalcode"
},
  "geometry": {"coordinates":[-1.46547444126503,54.94907363185209],"type":"Point"}
}