{
  "type": "Feature",
  "properties": {
    "iso:country":"GB",
    "wof:name":"SA44 5JB",
    "wof:placetype":"postalcode"
},
  "geometry": {"coordinates":[-4.39818752978111,51.9976280396351],"type":"Point"}
}