{
  "type": "Feature",
  "properties": {
    "date:inception_lower":"1980-01-01",
    "date:inception_upper":"1980-01-31",
    "iso:country":"GB",
    "wof:name":"SA44 5JB",
    "wof:placetype":"postalcode"
},
  "geometry": {"coordinates":[-4.398187,51.997628],"type":"Point"}
}