{
  "type": "Feature",
  "properties": {
    "iso:country": "GB",
    "wof:name": "SA44 5JB",
    "wof:placetype": "postalcode"
  },
  "geometry": {"coordinates":[-4.398187,51.997628],"type":"Point"}
}
