{
  "type": "Feature",
  "properties": {
    "date:inception_lower": "2024-08-01",
    "date:inception_upper": "2024-08-01",
    "iso:country": "GB",
    "wof:name": "TR5 0BB",
    "wof:placetype": "postalcode"
  },
  "geometry": {"coordinates":[-5.203611,50.305415],"type":"Point"}
}
