{
  "type": "Feature",
  "properties": {
    "iso:country":"GB",
    "wof:name":"TR19 7BZ",
    "wof:placetype":"postalcode"
},
  "geometry": {"coordinates":[-5.70449258032339,50.07682851811053],"type":"Point"}
}