{
  "type": "Feature",
  "properties": {
    "date:inception_lower":"1980-01-01",
    "date:inception_upper":"1980-01-31",
    "iso:country":"GB",
    "wof:name":"TR19 7BZ",
    "wof:placetype":"postalcode"
},
  "geometry": {"coordinates":[-5.704493,50.076829],"type":"Point"}
}