{
  "type": "Feature",
  "properties": {
    "iso:country":"GB",
    "wof:name":"PO9 1RB",
    "wof:placetype":"postalcode"
},
  "geometry": {"coordinates":[-0.98393370162805,50.84300681417819],"type":"Point"}
}