{
  "type": "Feature",
  "properties": {
    "date:inception_lower": "1980-01-01",
    "date:inception_upper": "1980-01-01",
    "iso:country": "GB",
    "wof:name": "NG34 9LN",
    "wof:placetype": "postalcode"
  },
  "geometry": {"coordinates":[-0.273053,52.968416],"type":"Point"}
}
