{
  "type": "Feature",
  "properties": {
    "iso:country":"GB",
    "wof:name":"NG34 9LN",
    "wof:placetype":"postalcode"
},
  "geometry": {"coordinates":[-0.27270626343953,52.96794714288787],"type":"Point"}
}