{
  "type": "Feature",
  "properties": {
    "date:inception_lower": "2023-07-01",
    "date:inception_upper": "2023-07-01",
    "iso:country": "GB",
    "wof:name": "SY4 2FS",
    "wof:placetype": "postalcode"
  },
  "geometry": {"coordinates":[-2.848103,52.79643],"type":"Point"}
}
