{
  "type": "Feature",
  "properties": {
    "iso:country":"GB",
    "wof:name":"SE25 5LE",
    "wof:placetype":"postalcode"
},
  "geometry": {"coordinates":[-0.06995133455565,51.39483534987813],"type":"Point"}
}