{
  "type": "Feature",
  "properties": {
    "iso:country":"GB",
    "wof:name":"SS8 8DQ",
    "wof:placetype":"postalcode"
},
  "geometry": {"coordinates":[0.58907145884908,51.529411673109],"type":"Point"}
}