{
  "type": "Feature",
  "properties": {
    "iso:country": "GB",
    "wof:name": "SS8 8DQ",
    "wof:placetype": "postalcode"
  },
  "geometry": {"coordinates":[0.589072,51.529412],"type":"Point"}
}
