{
  "type": "Feature",
  "properties": {
    "iso:country":"GB",
    "wof:name":"KA16 9AW",
    "wof:placetype":"postalcode"
},
  "geometry": {"coordinates":[-4.34188575022145,55.60332089931818],"type":"Point"}
}