{
  "type": "Feature",
  "properties": {
    "date:inception_lower": "1995-07-01",
    "date:inception_upper": "1995-07-01",
    "iso:country": "GB",
    "wof:name": "RG4 6TX",
    "wof:placetype": "postalcode"
  },
  "geometry": {"coordinates":[-0.926257,51.479947],"type":"Point"}
}
