{
  "type": "Feature",
  "properties": {
    "iso:country":"GB",
    "wof:name":"RG4 6TX",
    "wof:placetype":"postalcode"
},
  "geometry": {"coordinates":[-0.92625676697921,51.47994724148707],"type":"Point"}
}