{
  "type": "Feature",
  "properties": {
    "iso:country":"GB",
    "wof:name":"IP28 8DS",
    "wof:placetype":"postalcode"
},
  "geometry": {"coordinates":[0.45884547379407,52.38236179768856],"type":"Point"}
}