{
  "type": "Feature",
  "properties": {
    "iso:country": "GB",
    "wof:name": "RH8 0AW",
    "wof:placetype": "postalcode"
  },
  "geometry": {"coordinates":[0.005264,51.263669],"type":"Point"}
}
