{
  "type": "Feature",
  "properties": {
    "iso:country":"GB",
    "wof:name":"RH8 0AW",
    "wof:placetype":"postalcode"
},
  "geometry": {"coordinates":[0.00526345996007,51.26366936590798],"type":"Point"}
}