{
  "type": "Feature",
  "properties": {
    "iso:country":"GB",
    "wof:name":"EN3 7AX",
    "wof:placetype":"postalcode"
},
  "geometry": {"coordinates":[-0.03600871583421,51.64753046362206],"type":"Point"}
}