{
  "type": "Feature",
  "properties": {
    "date:inception_lower":"1980-01-01",
    "date:inception_upper":"1980-01-31",
    "iso:country":"GB",
    "wof:name":"EN3 7AX",
    "wof:placetype":"postalcode"
},
  "geometry": {"coordinates":[-0.036009,51.64753],"type":"Point"}
}