{
  "type": "Feature",
  "properties": {
    "iso:country":"GB",
    "wof:name":"SM6 8AZ",
    "wof:placetype":"postalcode"
},
  "geometry": {"coordinates":[-0.15006441215235,51.3659121476852],"type":"Point"}
}