{
  "type": "Feature",
  "properties": {
    "date:inception_lower": "1998-12-01",
    "date:inception_upper": "1998-12-01",
    "iso:country": "GB",
    "wof:name": "CW9 5NF",
    "wof:placetype": "postalcode"
  },
  "geometry": {"coordinates":[-2.499758,53.263415],"type":"Point"}
}
