{
  "type": "Feature",
  "properties": {
    "iso:country":"GB",
    "wof:name":"CW9 5NF",
    "wof:placetype":"postalcode"
},
  "geometry": {"coordinates":[-2.49975824372755,53.263415261463],"type":"Point"}
}