{
  "type": "Feature",
  "properties": {
    "iso:country":"GB",
    "wof:name":"SG1 3TL",
    "wof:placetype":"postalcode"
},
  "geometry": {"coordinates":[-0.19505088047541,51.90696859462902],"type":"Point"}
}