{
  "type": "Feature",
  "properties": {
    "date:inception_lower": "2022-03-01",
    "date:inception_upper": "2022-03-01",
    "iso:country": "GB",
    "wof:name": "L40 9AD",
    "wof:placetype": "postalcode"
  },
  "geometry": {"coordinates":[-2.921456,53.612641],"type":"Point"}
}
