{
  "type": "Feature",
  "properties": {
    "iso:country":"GB",
    "wof:name":"CV6 2FD",
    "wof:placetype":"postalcode"
},
  "geometry": {"coordinates":[-1.52449515552297,52.43661061392653],"type":"Point"}
}