{
  "type": "Feature",
  "properties": {
    "iso:country":"GB",
    "wof:name":"SK8 5ER",
    "wof:placetype":"postalcode"
},
  "geometry": {"coordinates":[-2.20213906972965,53.38069540451708],"type":"Point"}
}