{
  "type": "Feature",
  "properties": {
    "iso:country": "GB",
    "wof:name": "SK8 5ER",
    "wof:placetype": "postalcode"
  },
  "geometry": {"coordinates":[-2.202139,53.380695],"type":"Point"}
}
