{
  "type": "Feature",
  "properties": {
    "iso:country":"GB",
    "wof:name":"HA3 5DJ",
    "wof:placetype":"postalcode"
},
  "geometry": {"coordinates":[-0.3354092186497,51.59413018256679],"type":"Point"}
}