{
  "type": "Feature",
  "properties": {
    "date:inception_lower":"2013-08-01",
    "date:inception_upper":"2013-08-31",
    "iso:country":"GB",
    "wof:name":"RG12 8FN",
    "wof:placetype":"postalcode"
},
  "geometry": {"coordinates":[-0.777405,51.404819],"type":"Point"}
}