{
  "type": "Feature",
  "properties": {
    "iso:country": "GB",
    "wof:name": "RG12 8FN",
    "wof:placetype": "postalcode"
  },
  "geometry": {"coordinates":[-0.777405,51.404819],"type":"Point"}
}
