{
  "type": "Feature",
  "properties": {
    "iso:country":"GB",
    "wof:name":"RG12 8FN",
    "wof:placetype":"postalcode"
},
  "geometry": {"coordinates":[-0.77740479607481,51.40481860735454],"type":"Point"}
}