{
  "type": "Feature",
  "properties": {
    "iso:country": "GB",
    "wof:name": "B77 2LS",
    "wof:placetype": "postalcode"
  },
  "geometry": {"coordinates":[-1.675786,52.614754],"type":"Point"}
}
