{
  "type": "Feature",
  "properties": {
    "date:inception_lower": "1980-01-01",
    "date:inception_upper": "1980-01-01",
    "iso:country": "GB",
    "wof:name": "B77 2LS",
    "wof:placetype": "postalcode"
  },
  "geometry": {"coordinates":[-1.675786,52.614754],"type":"Point"}
}
