{
  "type": "Feature",
  "properties": {
    "iso:country":"GB",
    "wof:name":"B77 2LS",
    "wof:placetype":"postalcode"
},
  "geometry": {"coordinates":[-1.67578589319423,52.61475371263035],"type":"Point"}
}