{
  "type": "Feature",
  "properties": {
    "iso:country": "GB",
    "wof:name": "M5 5HH",
    "wof:placetype": "postalcode"
  },
  "geometry": {"coordinates":[-2.309118,53.484877],"type":"Point"}
}
