{
  "type": "Feature",
  "properties": {
    "date:inception_lower": "2009-09-01",
    "date:inception_upper": "2009-09-01",
    "iso:country": "GB",
    "wof:name": "DN1 1QH",
    "wof:placetype": "postalcode"
  },
  "geometry": {"coordinates":[-1.133307,53.525453],"type":"Point"}
}
