{
  "type": "Feature",
  "properties": {
    "iso:country":"GB",
    "wof:name":"DN1 1QH",
    "wof:placetype":"postalcode"
},
  "geometry": {"coordinates":[-1.13330698302356,53.52545345512068],"type":"Point"}
}