{
  "type": "Feature",
  "properties": {
    "date:inception_lower": "1980-01-01",
    "date:inception_upper": "1980-01-01",
    "iso:country": "GB",
    "wof:name": "WN2 4PW",
    "wof:placetype": "postalcode"
  },
  "geometry": {"coordinates":[-2.55472,53.527035],"type":"Point"}
}
