{
  "type": "Feature",
  "properties": {
    "iso:country":"GB",
    "wof:name":"WN2 4PW",
    "wof:placetype":"postalcode"
},
  "geometry": {"coordinates":[-2.55471962693288,53.52703498992069],"type":"Point"}
}