{
  "type": "Feature",
  "properties": {
    "iso:country":"GB",
    "wof:name":"B93 8LP",
    "wof:placetype":"postalcode"
},
  "geometry": {"coordinates":[-1.75139995527897,52.36982507118134],"type":"Point"}
}