{
  "type": "Feature",
  "properties": {
    "date:inception_lower": "1980-01-01",
    "date:inception_upper": "1980-01-01",
    "iso:country": "GB",
    "wof:name": "B93 8LP",
    "wof:placetype": "postalcode"
  },
  "geometry": {"coordinates":[-1.7514,52.369825],"type":"Point"}
}
