{
  "type": "Feature",
  "properties": {
    "iso:country":"GB",
    "wof:name":"TA2 7SL",
    "wof:placetype":"postalcode"
},
  "geometry": {"coordinates":[-3.10552796270598,51.02715017722387],"type":"Point"}
}