{
  "type": "Feature",
  "properties": {
    "iso:country":"GB",
    "wof:name":"PH2 8NS",
    "wof:placetype":"postalcode"
},
  "geometry": {"coordinates":[-3.42686747596298,56.39208824653485],"type":"Point"}
}