{
  "type": "Feature",
  "properties": {
    "date:inception_lower": "2024-10-01",
    "date:inception_upper": "2024-10-01",
    "iso:country": "GB",
    "wof:name": "DE55 6PH",
    "wof:placetype": "postalcode"
  },
  "geometry": {"coordinates":[-1.398651,53.11989],"type":"Point"}
}
