{
  "type": "Feature",
  "properties": {
    "iso:country": "GB",
    "wof:name": "TS17 0NN",
    "wof:placetype": "postalcode"
  },
  "geometry": {"coordinates":[-1.31176,54.505774],"type":"Point"}
}
