{
  "type": "Feature",
  "properties": {
    "date:inception_lower": "1995-01-01",
    "date:inception_upper": "1995-01-01",
    "iso:country": "GB",
    "wof:name": "TS17 0NN",
    "wof:placetype": "postalcode"
  },
  "geometry": {"coordinates":[-1.31176,54.505774],"type":"Point"}
}
