{
  "type": "Feature",
  "properties": {
    "date:inception_lower": "1980-01-01",
    "date:inception_upper": "1980-01-01",
    "iso:country": "GB",
    "wof:name": "LA23 1LF",
    "wof:placetype": "postalcode"
  },
  "geometry": {"coordinates":[-2.929728,54.393484],"type":"Point"}
}
