{
  "type": "Feature",
  "properties": {
    "iso:country":"GB",
    "wof:name":"KT3 3EB",
    "wof:placetype":"postalcode"
},
  "geometry": {"coordinates":[-0.26905453238522,51.40895246494713],"type":"Point"}
}