{
  "type": "Feature",
  "properties": {
    "iso:country":"GB",
    "wof:name":"KT16 8RP",
    "wof:placetype":"postalcode"
},
  "geometry": {"coordinates":[-0.49385607820568,51.40884667276693],"type":"Point"}
}