{
  "type": "Feature",
  "properties": {
    "date:inception_lower": "1980-01-01",
    "date:inception_upper": "1980-01-01",
    "iso:country": "GB",
    "wof:name": "KT16 8RP",
    "wof:placetype": "postalcode"
  },
  "geometry": {"coordinates":[-0.493476,51.408428],"type":"Point"}
}
