{
  "type": "Feature",
  "properties": {
    "iso:country": "GB",
    "wof:name": "N18 1DX",
    "wof:placetype": "postalcode"
  },
  "geometry": {"coordinates":[-0.080763,51.610511],"type":"Point"}
}
