{
  "type": "Feature",
  "properties": {
    "date:inception_lower":"1980-01-01",
    "date:inception_upper":"1980-01-31",
    "iso:country":"GB",
    "wof:name":"N18 1DX",
    "wof:placetype":"postalcode"
},
  "geometry": {"coordinates":[-0.080763,51.610511],"type":"Point"}
}