{
  "type": "Feature",
  "properties": {
    "iso:country":"GB",
    "wof:name":"N18 1DX",
    "wof:placetype":"postalcode"
},
  "geometry": {"coordinates":[-0.08076265992109,51.61051137283446],"type":"Point"}
}