{
  "type": "Feature",
  "properties": {
    "iso:country":"GB",
    "wof:name":"LA4 4UA",
    "wof:placetype":"postalcode"
},
  "geometry": {"coordinates":[-2.86373365038679,54.06091132379938],"type":"Point"}
}