{
  "type": "Feature",
  "properties": {
    "iso:country":"GB",
    "wof:name":"SL6 2ES",
    "wof:placetype":"postalcode"
},
  "geometry": {"coordinates":[-0.70971488386008,51.50550526683238],"type":"Point"}
}