{
  "type": "Feature",
  "properties": {
    "iso:country":"GB",
    "wof:name":"EX31 3SP",
    "wof:placetype":"postalcode"
},
  "geometry": {"coordinates":[-4.0890913840143,51.06874878557297],"type":"Point"}
}