{
  "type": "Feature",
  "properties": {
    "iso:country": "GB",
    "wof:name": "G82 3PE",
    "wof:placetype": "postalcode"
  },
  "geometry": {"coordinates":[-4.578921,55.969351],"type":"Point"}
}
