{
  "type": "Feature",
  "properties": {
    "iso:country":"GB",
    "wof:name":"G82 3PE",
    "wof:placetype":"postalcode"
},
  "geometry": {"coordinates":[-4.57643798403296,55.96959907073684],"type":"Point"}
}