{
  "type": "Feature",
  "properties": {
    "date:inception_lower":"2015-07-01",
    "date:inception_upper":"2015-07-31",
    "iso:country":"GB",
    "wof:name":"G82 3PE",
    "wof:placetype":"postalcode"
},
  "geometry": {"coordinates":[-4.578921,55.969351],"type":"Point"}
}