{
  "type": "Feature",
  "properties": {
    "iso:country":"GB",
    "wof:name":"BS7 0RH",
    "wof:placetype":"postalcode"
},
  "geometry": {"coordinates":[-2.57756982260031,51.5023910153989],"type":"Point"}
}