{
  "type": "Feature",
  "properties": {
    "date:inception_lower":"2003-01-01",
    "date:inception_upper":"2003-01-31",
    "iso:country":"GB",
    "wof:name":"NP13 3JL",
    "wof:placetype":"postalcode"
},
  "geometry": {"coordinates":[-3.149535,51.766202],"type":"Point"}
}