{
  "type": "Feature",
  "properties": {
    "iso:country": "GB",
    "wof:name": "NP13 3JL",
    "wof:placetype": "postalcode"
  },
  "geometry": {"coordinates":[-3.149535,51.766202],"type":"Point"}
}
