{
  "type": "Feature",
  "properties": {
    "iso:country":"GB",
    "wof:name":"BN12 6NB",
    "wof:placetype":"postalcode"
},
  "geometry": {"coordinates":[-0.4326876695908,50.82105066646939],"type":"Point"}
}