{
  "type": "Feature",
  "properties": {
    "iso:country":"GB",
    "wof:name":"CB22 5AL",
    "wof:placetype":"postalcode"
},
  "geometry": {"coordinates":[0.14806012092054,52.15390360165345],"type":"Point"}
}