{
  "type": "Feature",
  "properties": {
    "iso:country": "GB",
    "wof:name": "CB22 5AL",
    "wof:placetype": "postalcode"
  },
  "geometry": {"coordinates":[0.14806,52.153904],"type":"Point"}
}
