{
  "type": "Feature",
  "properties": {
    "date:inception_lower": "1980-01-01",
    "date:inception_upper": "1980-01-01",
    "iso:country": "GB",
    "wof:name": "IP12 3EW",
    "wof:placetype": "postalcode"
  },
  "geometry": {"coordinates":[1.377413,52.044171],"type":"Point"}
}
