{
  "type": "Feature",
  "properties": {
    "iso:country":"GB",
    "wof:name":"GL56 9QB",
    "wof:placetype":"postalcode"
},
  "geometry": {"coordinates":[-1.72931484514901,52.00252641618535],"type":"Point"}
}