{
  "type": "Feature",
  "properties": {
    "iso:country":"GB",
    "wof:name":"HA9 6QJ",
    "wof:placetype":"postalcode"
},
  "geometry": {"coordinates":[-0.27999953780862,51.55014141799165],"type":"Point"}
}