{
  "type": "Feature",
  "properties": {
    "iso:country": "GB",
    "wof:name": "W10 6ED",
    "wof:placetype": "postalcode"
  },
  "geometry": {"coordinates":[-0.215537,51.521851],"type":"Point"}
}
