{
  "type": "Feature",
  "properties": {
    "iso:country":"GB",
    "wof:name":"W10 6ED",
    "wof:placetype":"postalcode"
},
  "geometry": {"coordinates":[-0.21553703827849,51.52185083706633],"type":"Point"}
}