{
  "type": "Feature",
  "properties": {
    "date:inception_lower": "1995-07-01",
    "date:inception_upper": "1995-07-01",
    "iso:country": "GB",
    "wof:name": "RG4 5BA",
    "wof:placetype": "postalcode"
  },
  "geometry": {"coordinates":[-0.959771,51.467733],"type":"Point"}
}
