{
  "type": "Feature",
  "properties": {
    "iso:country":"GB",
    "wof:name":"N2 9EX",
    "wof:placetype":"postalcode"
},
  "geometry": {"coordinates":[-0.15820049561924,51.59064688504079],"type":"Point"}
}