{
  "type": "Feature",
  "properties": {
    "date:inception_lower":"1994-05-01",
    "date:inception_upper":"1994-05-31",
    "iso:country":"GB",
    "wof:name":"M34 6BR",
    "wof:placetype":"postalcode"
},
  "geometry": {"coordinates":[-2.111125,53.448148],"type":"Point"}
}