{
  "type": "Feature",
  "properties": {
    "iso:country": "GB",
    "wof:name": "NE5 4SL",
    "wof:placetype": "postalcode"
  },
  "geometry": {"coordinates":[-1.677546,55.004987],"type":"Point"}
}
