{
  "type": "Feature",
  "properties": {
    "date:inception_lower":"1990-02-01",
    "date:inception_upper":"1990-02-28",
    "iso:country":"GB",
    "wof:name":"NE5 4SL",
    "wof:placetype":"postalcode"
},
  "geometry": {"coordinates":[-1.677546,55.004987],"type":"Point"}
}