{
  "type": "Feature",
  "properties": {
    "iso:country":"GB",
    "wof:name":"NE5 4SL",
    "wof:placetype":"postalcode"
},
  "geometry": {"coordinates":[-1.67754586359597,55.00498699906733],"type":"Point"}
}