{
  "type": "Feature",
  "properties": {
    "date:inception_lower": "1994-12-01",
    "date:inception_upper": "1994-12-01",
    "iso:country": "GB",
    "wof:name": "SO31 9PU",
    "wof:placetype": "postalcode"
  },
  "geometry": {"coordinates":[-1.292268,50.848853],"type":"Point"}
}
