{
  "type": "Feature",
  "properties": {
    "iso:country":"GB",
    "wof:name":"SO31 9PU",
    "wof:placetype":"postalcode"
},
  "geometry": {"coordinates":[-1.29226820368812,50.84885348367013],"type":"Point"}
}