{
  "type": "Feature",
  "properties": {
    "iso:country":"GB",
    "wof:name":"B31 2YP",
    "wof:placetype":"postalcode"
},
  "geometry": {"coordinates":[-1.97883523921818,52.40070439988679],"type":"Point"}
}