{
  "type": "Feature",
  "properties": {
    "iso:country":"GB",
    "wof:name":"PE19 2NF",
    "wof:placetype":"postalcode"
},
  "geometry": {"coordinates":[-0.26511437155584,52.2196351460483],"type":"Point"}
}