{
  "type": "Feature",
  "properties": {
    "date:inception_lower": "2005-09-01",
    "date:inception_upper": "2005-09-01",
    "iso:country": "GB",
    "wof:name": "SN25 1TT",
    "wof:placetype": "postalcode"
  },
  "geometry": {"coordinates":[-1.817339,51.597417],"type":"Point"}
}
