{
  "type": "Feature",
  "properties": {
    "iso:country": "GB",
    "wof:name": "SS8 0NJ",
    "wof:placetype": "postalcode"
  },
  "geometry": {"coordinates":[0.560805,51.517747],"type":"Point"}
}
