{
  "type": "Feature",
  "properties": {
    "iso:country":"GB",
    "wof:name":"SS8 0NJ",
    "wof:placetype":"postalcode"
},
  "geometry": {"coordinates":[0.56080491645721,51.51774732331069],"type":"Point"}
}