{
  "type": "Feature",
  "properties": {
    "iso:country":"GB",
    "wof:name":"SK6 6QA",
    "wof:placetype":"postalcode"
},
  "geometry": {"coordinates":[-2.06382751400932,53.40519081335426],"type":"Point"}
}