{
  "type": "Feature",
  "properties": {
    "iso:country": "GB",
    "wof:name": "SK6 6QA",
    "wof:placetype": "postalcode"
  },
  "geometry": {"coordinates":[-2.063827,53.405191],"type":"Point"}
}
