{
  "type": "Feature",
  "properties": {
    "iso:country":"GB",
    "wof:name":"KY15 5PA",
    "wof:placetype":"postalcode"
},
  "geometry": {"coordinates":[-3.01845581854934,56.28963758103949],"type":"Point"}
}