{
  "type": "Feature",
  "properties": {
    "iso:country": "GB",
    "wof:name": "GU34 5NA",
    "wof:placetype": "postalcode"
  },
  "geometry": {"coordinates":[-1.074949,51.123314],"type":"Point"}
}
