{
  "type": "Feature",
  "properties": {
    "iso:country": "GB",
    "wof:name": "HG4 1EG",
    "wof:placetype": "postalcode"
  },
  "geometry": {"coordinates":[-1.522936,54.137091],"type":"Point"}
}
