{
  "type": "Feature",
  "properties": {
    "iso:country": "GB",
    "wof:name": "S5 0RL",
    "wof:placetype": "postalcode"
  },
  "geometry": {"coordinates":[-1.444494,53.430137],"type":"Point"}
}
