{
  "type": "Feature",
  "properties": {
    "iso:country": "GB",
    "wof:name": "BS40 6ND",
    "wof:placetype": "postalcode"
  },
  "geometry": {"coordinates":[-2.657565,51.312487],"type":"Point"}
}
