{
  "type": "Feature",
  "properties": {
    "iso:country": "GB",
    "wof:name": "NN4 5DL",
    "wof:placetype": "postalcode"
  },
  "geometry": {"coordinates":[-0.878325,52.187154],"type":"Point"}
}
