{
  "type": "Feature",
  "properties": {
    "date:inception_lower": "2003-04-01",
    "date:inception_upper": "2003-04-01",
    "iso:country": "GB",
    "wof:name": "NN4 5DL",
    "wof:placetype": "postalcode"
  },
  "geometry": {"coordinates":[-0.878325,52.187154],"type":"Point"}
}
