{
  "type": "Feature",
  "properties": {
    "iso:country":"GB",
    "wof:name":"TR13 9AU",
    "wof:placetype":"postalcode"
},
  "geometry": {"coordinates":[-5.31104993668203,50.08545715581852],"type":"Point"}
}