{
  "type": "Feature",
  "properties": {
    "iso:country": "GB",
    "wof:name": "TR13 9AU",
    "wof:placetype": "postalcode"
  },
  "geometry": {"coordinates":[-5.311132,50.085472],"type":"Point"}
}
