{
  "type": "Feature",
  "properties": {
    "iso:country":"GB",
    "wof:name":"KT5 9RF",
    "wof:placetype":"postalcode"
},
  "geometry": {"coordinates":[-0.27650447962507,51.38175197152412],"type":"Point"}
}