{
  "type": "Feature",
  "properties": {
    "iso:country":"GB",
    "wof:name":"PR8 5EF",
    "wof:placetype":"postalcode"
},
  "geometry": {"coordinates":[-2.99902968454727,53.6362271068908],"type":"Point"}
}