{
  "type": "Feature",
  "properties": {
    "iso:country": "GB",
    "wof:name": "PO19 1LA",
    "wof:placetype": "postalcode"
  },
  "geometry": {"coordinates":[-0.77582,50.838294],"type":"Point"}
}
