{
  "type": "Feature",
  "properties": {
    "iso:country":"GB",
    "wof:name":"PO19 1LA",
    "wof:placetype":"postalcode"
},
  "geometry": {"coordinates":[-0.7758203627188,50.83829370123748],"type":"Point"}
}