{
  "type": "Feature",
  "properties": {
    "date:inception_lower": "2003-03-01",
    "date:inception_upper": "2003-03-01",
    "iso:country": "GB",
    "wof:name": "MK4 4EH",
    "wof:placetype": "postalcode"
  },
  "geometry": {"coordinates":[-0.804769,52.001118],"type":"Point"}
}
