{
  "type": "Feature",
  "properties": {
    "iso:country":"GB",
    "wof:name":"MK4 4EH",
    "wof:placetype":"postalcode"
},
  "geometry": {"coordinates":[-0.80476941888513,52.00111817399674],"type":"Point"}
}