{
  "type": "Feature",
  "properties": {
    "date:inception_lower":"1980-01-01",
    "date:inception_upper":"1980-01-31",
    "iso:country":"GB",
    "wof:name":"CR2 0JS",
    "wof:placetype":"postalcode"
},
  "geometry": {"coordinates":[-0.078211,51.343514],"type":"Point"}
}