{
  "type": "Feature",
  "properties": {
    "iso:country":"GB",
    "wof:name":"AL4 0TA",
    "wof:placetype":"postalcode"
},
  "geometry": {"coordinates":[-0.29096856624891,51.75019716764577],"type":"Point"}
}