{
  "type": "Feature",
  "properties": {
    "iso:country": "GB",
    "wof:name": "LD2 3NL",
    "wof:placetype": "postalcode"
  },
  "geometry": {"coordinates":[-3.413975,52.149041],"type":"Point"}
}
