{
  "type": "Feature",
  "properties": {
    "iso:country":"GB",
    "wof:name":"FK8 1EB",
    "wof:placetype":"postalcode"
},
  "geometry": {"coordinates":[-3.94268183514805,56.11982120918233],"type":"Point"}
}