{
  "type": "Feature",
  "properties": {
    "iso:country":"GB",
    "wof:name":"NE40 4QB",
    "wof:placetype":"postalcode"
},
  "geometry": {"coordinates":[-1.77120727616936,54.95603540869368],"type":"Point"}
}