{
  "type": "Feature",
  "properties": {
    "date:inception_lower":"1985-10-01",
    "date:inception_upper":"1985-10-31",
    "iso:country":"GB",
    "wof:name":"NE40 4QB",
    "wof:placetype":"postalcode"
},
  "geometry": {"coordinates":[-1.771207,54.956035],"type":"Point"}
}