{
  "type": "Feature",
  "properties": {
    "iso:country":"GB",
    "wof:name":"PL31 2RX",
    "wof:placetype":"postalcode"
},
  "geometry": {"coordinates":[-4.7510484460006,50.47318732370585],"type":"Point"}
}