{
  "type": "Feature",
  "properties": {
    "date:inception_lower":"2005-12-01",
    "date:inception_upper":"2005-12-31",
    "iso:country":"GB",
    "wof:name":"PL31 2RX",
    "wof:placetype":"postalcode"
},
  "geometry": {"coordinates":[-4.751048,50.473187],"type":"Point"}
}