{
  "type": "Feature",
  "properties": {
    "iso:country":"GB",
    "wof:name":"AB42 1NR",
    "wof:placetype":"postalcode"
},
  "geometry": {"coordinates":[-1.78858758979326,57.51330391062605],"type":"Point"}
}