{
  "type": "Feature",
  "properties": {
    "iso:country":"GB",
    "wof:name":"DL4 1NJ",
    "wof:placetype":"postalcode"
},
  "geometry": {"coordinates":[-1.64461602793452,54.62759774702972],"type":"Point"}
}