{
  "type": "Feature",
  "properties": {
    "iso:country": "GB",
    "wof:name": "DL4 1NJ",
    "wof:placetype": "postalcode"
  },
  "geometry": {"coordinates":[-1.644626,54.627607],"type":"Point"}
}
