{
  "type": "Feature",
  "properties": {
    "iso:country": "GB",
    "wof:name": "BA6 8AD",
    "wof:placetype": "postalcode"
  },
  "geometry": {"coordinates":[-2.731053,51.138963],"type":"Point"}
}
