{
  "type": "Feature",
  "properties": {
    "iso:country":"GB",
    "wof:name":"BA6 8AD",
    "wof:placetype":"postalcode"
},
  "geometry": {"coordinates":[-2.73105255210983,51.1389630713425],"type":"Point"}
}