{
  "type": "Feature",
  "properties": {
    "iso:country": "GB",
    "wof:name": "HU12 0TS",
    "wof:placetype": "postalcode"
  },
  "geometry": {"coordinates":[0.114883,53.649119],"type":"Point"}
}
