{
  "type": "Feature",
  "properties": {
    "date:inception_lower": "1980-01-01",
    "date:inception_upper": "1980-01-01",
    "iso:country": "GB",
    "wof:name": "PO21 5AN",
    "wof:placetype": "postalcode"
  },
  "geometry": {"coordinates":[-0.691879,50.798389],"type":"Point"}
}
