{
  "type": "Feature",
  "properties": {
    "iso:country":"GB",
    "wof:name":"PO21 5AN",
    "wof:placetype":"postalcode"
},
  "geometry": {"coordinates":[-0.69187884795962,50.79838940879392],"type":"Point"}
}