{
  "type": "Feature",
  "properties": {
    "iso:country": "GB",
    "wof:name": "NR35 2BB",
    "wof:placetype": "postalcode"
  },
  "geometry": {"coordinates":[1.326697,52.473538],"type":"Point"}
}
