{
  "type": "Feature",
  "properties": {
    "date:inception_lower":"1980-01-01",
    "date:inception_upper":"1980-01-31",
    "iso:country":"GB",
    "wof:name":"NR35 2BB",
    "wof:placetype":"postalcode"
},
  "geometry": {"coordinates":[1.326697,52.473538],"type":"Point"}
}