{
  "type": "Feature",
  "properties": {
    "iso:country":"GB",
    "wof:name":"SK9 7SE",
    "wof:placetype":"postalcode"
},
  "geometry": {"coordinates":[-2.25857124059947,53.31097817323736],"type":"Point"}
}