{
  "type": "Feature",
  "properties": {
    "iso:country": "GB",
    "wof:name": "SK9 7SE",
    "wof:placetype": "postalcode"
  },
  "geometry": {"coordinates":[-2.258571,53.310978],"type":"Point"}
}
