{
  "type": "Feature",
  "properties": {
    "iso:country":"GB",
    "wof:name":"W1B 5TE",
    "wof:placetype":"postalcode"
},
  "geometry": {"coordinates":[-0.13910595846222,51.51205735921784],"type":"Point"}
}