{
  "type": "Feature",
  "properties": {
    "iso:country":"GB",
    "wof:name":"NG9 5BN",
    "wof:placetype":"postalcode"
},
  "geometry": {"coordinates":[-1.23009446286857,52.91699019443989],"type":"Point"}
}