{
  "type": "Feature",
  "properties": {
    "iso:country":"GB",
    "wof:name":"W11 3ND",
    "wof:placetype":"postalcode"
},
  "geometry": {"coordinates":[-0.20022072621734,51.51071800181679],"type":"Point"}
}