{
  "type": "Feature",
  "properties": {
    "iso:country":"GB",
    "wof:name":"WD24 7XG",
    "wof:placetype":"postalcode"
},
  "geometry": {"coordinates":[-0.39210341898309,51.67343022137319],"type":"Point"}
}