{
  "type": "Feature",
  "properties": {
    "date:inception_lower": "2000-12-01",
    "date:inception_upper": "2000-12-01",
    "iso:country": "GB",
    "wof:name": "WD24 7XG",
    "wof:placetype": "postalcode"
  },
  "geometry": {"coordinates":[-0.392103,51.67343],"type":"Point"}
}
