{
  "type": "Feature",
  "properties": {
    "date:inception_lower":"1980-01-01",
    "date:inception_upper":"1980-01-31",
    "iso:country":"GB",
    "wof:name":"B60 4AH",
    "wof:placetype":"postalcode"
},
  "geometry": {"coordinates":[-2.073991,52.292303],"type":"Point"}
}