{
  "type": "Feature",
  "properties": {
    "iso:country":"GB",
    "wof:name":"DN37 7JF",
    "wof:placetype":"postalcode"
},
  "geometry": {"coordinates":[-0.17194657756274,53.53553017652208],"type":"Point"}
}