{
  "type": "Feature",
  "properties": {
    "iso:country": "GB",
    "wof:name": "MK18 4LX",
    "wof:placetype": "postalcode"
  },
  "geometry": {"coordinates":[-1.042795,51.96357],"type":"Point"}
}
