{
  "type": "Feature",
  "properties": {
    "iso:country":"GB",
    "wof:name":"MK18 4LX",
    "wof:placetype":"postalcode"
},
  "geometry": {"coordinates":[-1.0427204041616,51.9636504454142],"type":"Point"}
}