{
  "type": "Feature",
  "properties": {
    "iso:country":"GB",
    "wof:name":"SS15 6QX",
    "wof:placetype":"postalcode"
},
  "geometry": {"coordinates":[0.41528706599077,51.57056740416184],"type":"Point"}
}