{
  "type": "Feature",
  "properties": {
    "iso:country": "GB",
    "wof:name": "TF7 5QX",
    "wof:placetype": "postalcode"
  },
  "geometry": {"coordinates":[-2.472902,52.643987],"type":"Point"}
}
