{
  "type": "Feature",
  "properties": {
    "date:inception_lower":"2015-12-01",
    "date:inception_upper":"2015-12-31",
    "iso:country":"GB",
    "wof:name":"TF7 5QX",
    "wof:placetype":"postalcode"
},
  "geometry": {"coordinates":[-2.472902,52.643987],"type":"Point"}
}