{
  "type": "Feature",
  "properties": {
    "iso:country":"GB",
    "wof:name":"TF7 5QX",
    "wof:placetype":"postalcode"
},
  "geometry": {"coordinates":[-2.47334399565808,52.6436106595307],"type":"Point"}
}