{
  "type": "Feature",
  "properties": {
    "date:inception_lower":"1980-01-01",
    "date:inception_upper":"1980-01-31",
    "iso:country":"GB",
    "wof:name":"KT13 9DA",
    "wof:placetype":"postalcode"
},
  "geometry": {"coordinates":[-0.449414,51.36924],"type":"Point"}
}