{
  "type": "Feature",
  "properties": {
    "iso:country":"GB",
    "wof:name":"CB22 4WL",
    "wof:placetype":"postalcode"
},
  "geometry": {"coordinates":[0.16632173152142,52.10486845732846],"type":"Point"}
}