{
  "type": "Feature",
  "properties": {
    "iso:country":"GB",
    "wof:name":"WD25 8NR",
    "wof:placetype":"postalcode"
},
  "geometry": {"coordinates":[-0.34189612354849,51.68038442489102],"type":"Point"}
}