{
  "type": "Feature",
  "properties": {
    "iso:country":"GB",
    "wof:name":"BS8 1UD",
    "wof:placetype":"postalcode"
},
  "geometry": {"coordinates":[-2.6021722354193,51.45939526935173],"type":"Point"}
}