{
  "type": "Feature",
  "properties": {
    "iso:country":"GB",
    "wof:name":"OL3 5HE",
    "wof:placetype":"postalcode"
},
  "geometry": {"coordinates":[-2.02810868109013,53.57068152668744],"type":"Point"}
}