{
  "type": "Feature",
  "properties": {
    "iso:country": "GB",
    "wof:name": "OL3 5HE",
    "wof:placetype": "postalcode"
  },
  "geometry": {"coordinates":[-2.028109,53.570682],"type":"Point"}
}
