{
  "type": "Feature",
  "properties": {
    "iso:country":"GB",
    "wof:name":"B20 1LN",
    "wof:placetype":"postalcode"
},
  "geometry": {"coordinates":[-1.9419248904948,52.52770259559315],"type":"Point"}
}