{
  "type": "Feature",
  "properties": {
    "date:inception_lower": "1980-01-01",
    "date:inception_upper": "1980-01-01",
    "iso:country": "GB",
    "wof:name": "B20 1LN",
    "wof:placetype": "postalcode"
  },
  "geometry": {"coordinates":[-1.941925,52.527703],"type":"Point"}
}
