{
  "type": "Feature",
  "properties": {
    "iso:country":"GB",
    "wof:name":"WS1 2JQ",
    "wof:placetype":"postalcode"
},
  "geometry": {"coordinates":[-1.97241753390368,52.582470695715],"type":"Point"}
}