{
  "type": "Feature",
  "properties": {
    "iso:country": "GB",
    "wof:name": "WS1 2JQ",
    "wof:placetype": "postalcode"
  },
  "geometry": {"coordinates":[-1.974197,52.582945],"type":"Point"}
}
