{
  "type": "Feature",
  "properties": {
    "iso:country":"GB",
    "wof:name":"NR32 5PD",
    "wof:placetype":"postalcode"
},
  "geometry": {"coordinates":[1.70318076174784,52.50096299377481],"type":"Point"}
}