{
  "type": "Feature",
  "properties": {
    "date:inception_lower":"1980-01-01",
    "date:inception_upper":"1980-01-31",
    "iso:country":"GB",
    "wof:name":"NR32 5PD",
    "wof:placetype":"postalcode"
},
  "geometry": {"coordinates":[1.703153,52.500892],"type":"Point"}
}