{
  "type": "Feature",
  "properties": {
    "iso:country": "GB",
    "wof:name": "NR32 5PD",
    "wof:placetype": "postalcode"
  },
  "geometry": {"coordinates":[1.703153,52.500892],"type":"Point"}
}
