{
  "type": "Feature",
  "properties": {
    "iso:country":"GB",
    "wof:name":"BH24 1TA",
    "wof:placetype":"postalcode"
},
  "geometry": {"coordinates":[-1.7679055968456,50.85648673877916],"type":"Point"}
}