{
  "type": "Feature",
  "properties": {
    "iso:country": "GB",
    "wof:name": "LL11 4ED",
    "wof:placetype": "postalcode"
  },
  "geometry": {"coordinates":[-3.022622,53.071435],"type":"Point"}
}
