{
  "type": "Feature",
  "properties": {
    "iso:country":"GB",
    "wof:name":"LS13 3ST",
    "wof:placetype":"postalcode"
},
  "geometry": {"coordinates":[-1.62466983866442,53.80636918340062],"type":"Point"}
}