{
  "type": "Feature",
  "properties": {
    "date:inception_lower": "2013-08-01",
    "date:inception_upper": "2013-08-01",
    "iso:country": "GB",
    "wof:name": "LE13 0RN",
    "wof:placetype": "postalcode"
  },
  "geometry": {"coordinates":[-0.906088,52.763177],"type":"Point"}
}
