{
  "type": "Feature",
  "properties": {
    "iso:country":"GB",
    "wof:name":"LE13 0RN",
    "wof:placetype":"postalcode"
},
  "geometry": {"coordinates":[-0.90608845022777,52.76317725119534],"type":"Point"}
}