{
  "type": "Feature",
  "properties": {
    "date:inception_lower": "1999-06-01",
    "date:inception_upper": "1999-06-01",
    "iso:country": "GB",
    "wof:name": "CH61 9PE",
    "wof:placetype": "postalcode"
  },
  "geometry": {"coordinates":[-3.094623,53.348618],"type":"Point"}
}
