{
  "type": "Feature",
  "properties": {
    "iso:country":"GB",
    "wof:name":"EN2 7EJ",
    "wof:placetype":"postalcode"
},
  "geometry": {"coordinates":[-0.10080791790473,51.65413576512415],"type":"Point"}
}