{
  "type": "Feature",
  "properties": {
    "iso:country":"GB",
    "wof:name":"B14 7HT",
    "wof:placetype":"postalcode"
},
  "geometry": {"coordinates":[-1.88849052366893,52.42912543567989],"type":"Point"}
}