{
  "type": "Feature",
  "properties": {
    "date:inception_lower": "1980-01-01",
    "date:inception_upper": "1980-01-01",
    "iso:country": "GB",
    "wof:name": "B14 7HT",
    "wof:placetype": "postalcode"
  },
  "geometry": {"coordinates":[-1.888484,52.42914],"type":"Point"}
}
