{
  "type": "Feature",
  "properties": {
    "date:inception_lower": "1999-06-01",
    "date:inception_upper": "1999-06-01",
    "iso:country": "GB",
    "wof:name": "CH49 9AH",
    "wof:placetype": "postalcode"
  },
  "geometry": {"coordinates":[-3.094355,53.378617],"type":"Point"}
}
