{
  "type": "Feature",
  "properties": {
    "iso:country":"GB",
    "wof:name":"HP10 0LD",
    "wof:placetype":"postalcode"
},
  "geometry": {"coordinates":[-0.67014070894535,51.58097329746378],"type":"Point"}
}