{
  "type": "Feature",
  "properties": {
    "date:inception_lower": "1980-01-01",
    "date:inception_upper": "1980-01-01",
    "iso:country": "GB",
    "wof:name": "HP10 0LD",
    "wof:placetype": "postalcode"
  },
  "geometry": {"coordinates":[-0.670141,51.580973],"type":"Point"}
}
