{
  "type": "Feature",
  "properties": {
    "iso:country": "GB",
    "wof:name": "PE28 5AQ",
    "wof:placetype": "postalcode"
  },
  "geometry": {"coordinates":[-0.31422,52.373224],"type":"Point"}
}
