{
  "type": "Feature",
  "properties": {
    "date:inception_lower": "2022-03-01",
    "date:inception_upper": "2022-03-01",
    "iso:country": "GB",
    "wof:name": "AB10 6TH",
    "wof:placetype": "postalcode"
  },
  "geometry": {"coordinates":[-2.121369,57.140029],"type":"Point"}
}
