{
  "type": "Feature",
  "properties": {
    "iso:country":"GB",
    "wof:name":"SA1 7DL",
    "wof:placetype":"postalcode"
},
  "geometry": {"coordinates":[-3.91202245873886,51.64661710163713],"type":"Point"}
}