{
  "type": "Feature",
  "properties": {
    "iso:country":"GB",
    "wof:name":"TD8 6NP",
    "wof:placetype":"postalcode"
},
  "geometry": {"coordinates":[-2.54522582262246,55.47458691839265],"type":"Point"}
}