{
  "type": "Feature",
  "properties": {
    "iso:country":"GB",
    "wof:name":"CA11 7NN",
    "wof:placetype":"postalcode"
},
  "geometry": {"coordinates":[-2.7589815512834,54.66887573512886],"type":"Point"}
}