{
  "type": "Feature",
  "properties": {
    "iso:country":"GB",
    "wof:name":"W7 2AL",
    "wof:placetype":"postalcode"
},
  "geometry": {"coordinates":[-0.32646383110672,51.49609526141226],"type":"Point"}
}