{
  "type": "Feature",
  "properties": {
    "iso:country":"GB",
    "wof:name":"TN15 7DT",
    "wof:placetype":"postalcode"
},
  "geometry": {"coordinates":[0.30744300518332,51.31252963912937],"type":"Point"}
}