{
  "type": "Feature",
  "properties": {
    "iso:country": "GB",
    "wof:name": "TN15 7DT",
    "wof:placetype": "postalcode"
  },
  "geometry": {"coordinates":[0.307443,51.31253],"type":"Point"}
}
