{
  "type": "Feature",
  "properties": {
    "iso:country": "GB",
    "wof:name": "LA7 7QH",
    "wof:placetype": "postalcode"
  },
  "geometry": {"coordinates":[-2.770851,54.226107],"type":"Point"}
}
