{
  "type": "Feature",
  "properties": {
    "date:inception_lower": "1980-01-01",
    "date:inception_upper": "1980-01-01",
    "iso:country": "GB",
    "wof:name": "LA14 2JZ",
    "wof:placetype": "postalcode"
  },
  "geometry": {"coordinates":[-3.220526,54.11048],"type":"Point"}
}
