{
  "type": "Feature",
  "properties": {
    "iso:country":"GB",
    "wof:name":"LA14 2JZ",
    "wof:placetype":"postalcode"
},
  "geometry": {"coordinates":[-3.2205300207521,54.11047175532302],"type":"Point"}
}