{
  "type": "Feature",
  "properties": {
    "iso:country":"GB",
    "wof:name":"PL6 8LQ",
    "wof:placetype":"postalcode"
},
  "geometry": {"coordinates":[-4.09315316009796,50.39611666651093],"type":"Point"}
}