{
  "type": "Feature",
  "properties": {
    "iso:country": "GB",
    "wof:name": "PL6 8LQ",
    "wof:placetype": "postalcode"
  },
  "geometry": {"coordinates":[-4.093153,50.396117],"type":"Point"}
}
