{
  "type": "Feature",
  "properties": {
    "iso:country": "GB",
    "wof:name": "CA2 7JL",
    "wof:placetype": "postalcode"
  },
  "geometry": {"coordinates":[-2.959964,54.894737],"type":"Point"}
}
