{
  "type": "Feature",
  "properties": {
    "iso:country":"GB",
    "wof:name":"CA2 7JL",
    "wof:placetype":"postalcode"
},
  "geometry": {"coordinates":[-2.95996429450428,54.89473732610318],"type":"Point"}
}