{
  "type": "Feature",
  "properties": {
    "date:inception_lower": "2005-11-01",
    "date:inception_upper": "2005-11-01",
    "iso:country": "GB",
    "wof:name": "CR2 7EX",
    "wof:placetype": "postalcode"
  },
  "geometry": {"coordinates":[-0.085741,51.362657],"type":"Point"}
}
