{
  "type": "Feature",
  "properties": {
    "iso:country":"GB",
    "wof:name":"CR2 7EX",
    "wof:placetype":"postalcode"
},
  "geometry": {"coordinates":[-0.08574103252528,51.36265750514808],"type":"Point"}
}