{
  "type": "Feature",
  "properties": {
    "iso:country":"GB",
    "wof:name":"SW9 6BL",
    "wof:placetype":"postalcode"
},
  "geometry": {"coordinates":[-0.10769737176826,51.47322846961477],"type":"Point"}
}