{
  "type": "Feature",
  "properties": {
    "iso:country":"GB",
    "wof:name":"PR5 8BT",
    "wof:placetype":"postalcode"
},
  "geometry": {"coordinates":[-2.63325862373007,53.70721245322048],"type":"Point"}
}