{
  "type": "Feature",
  "properties": {
    "date:inception_lower":"1980-01-01",
    "date:inception_upper":"1980-01-31",
    "iso:country":"GB",
    "wof:name":"CW12 3HU",
    "wof:placetype":"postalcode"
},
  "geometry": {"coordinates":[-2.191859,53.153791],"type":"Point"}
}