{
  "type": "Feature",
  "properties": {
    "iso:country": "GB",
    "wof:name": "IP13 9HX",
    "wof:placetype": "postalcode"
  },
  "geometry": {"coordinates":[1.359487,52.230321],"type":"Point"}
}
