{
  "type": "Feature",
  "properties": {
    "iso:country":"GB",
    "wof:name":"IP13 9HX",
    "wof:placetype":"postalcode"
},
  "geometry": {"coordinates":[1.35940257585961,52.23037580118167],"type":"Point"}
}