{
  "type": "Feature",
  "properties": {
    "iso:country":"GB",
    "wof:name":"NE23 3FU",
    "wof:placetype":"postalcode"
},
  "geometry": {"coordinates":[-1.58691573006144,55.10219508229421],"type":"Point"}
}