{
  "type": "Feature",
  "properties": {
    "iso:country": "GB",
    "wof:name": "NE23 3FU",
    "wof:placetype": "postalcode"
  },
  "geometry": {"coordinates":[-1.586916,55.102195],"type":"Point"}
}
