{
  "type": "Feature",
  "properties": {
    "iso:country":"GB",
    "wof:name":"CW1 3QR",
    "wof:placetype":"postalcode"
},
  "geometry": {"coordinates":[-2.45887503778106,53.10927516983897],"type":"Point"}
}