{
  "type": "Feature",
  "properties": {
    "date:inception_lower": "2021-06-01",
    "date:inception_upper": "2021-06-01",
    "iso:country": "GB",
    "wof:name": "TS26 0FZ",
    "wof:placetype": "postalcode"
  },
  "geometry": {"coordinates":[-1.255673,54.693982],"type":"Point"}
}
