{
  "type": "Feature",
  "properties": {
    "iso:country":"GB",
    "wof:name":"SE1 5TS",
    "wof:placetype":"postalcode"
},
  "geometry": {"coordinates":[-0.07785679538127,51.49389370672654],"type":"Point"}
}