{
  "type": "Feature",
  "properties": {
    "iso:country":"GB",
    "wof:name":"B20 3JE",
    "wof:placetype":"postalcode"
},
  "geometry": {"coordinates":[-1.90170991155583,52.51631289379284],"type":"Point"}
}