{
  "type": "Feature",
  "properties": {
    "iso:country":"GB",
    "wof:name":"PL21 0EL",
    "wof:placetype":"postalcode"
},
  "geometry": {"coordinates":[-3.8763937046965,50.39746018320088],"type":"Point"}
}