{
  "type": "Feature",
  "properties": {
    "date:inception_lower": "1980-01-01",
    "date:inception_upper": "1980-01-01",
    "iso:country": "GB",
    "wof:name": "EH6 7DL",
    "wof:placetype": "postalcode"
  },
  "geometry": {"coordinates":[-3.166598,55.97764],"type":"Point"}
}
