{
  "type": "Feature",
  "properties": {
    "iso:country":"GB",
    "wof:name":"S10 5BE",
    "wof:placetype":"postalcode"
},
  "geometry": {"coordinates":[-1.501532830689,53.38016005710713],"type":"Point"}
}