{
  "type": "Feature",
  "properties": {
    "iso:country":"GB",
    "wof:name":"GU35 0NF",
    "wof:placetype":"postalcode"
},
  "geometry": {"coordinates":[-0.86114269902934,51.12671478099661],"type":"Point"}
}