{
  "type": "Feature",
  "properties": {
    "iso:country":"GB",
    "wof:name":"LE8 6HW",
    "wof:placetype":"postalcode"
},
  "geometry": {"coordinates":[-1.18167827071499,52.57248331421136],"type":"Point"}
}