{
  "type": "Feature",
  "properties": {
    "iso:country": "GB",
    "wof:name": "LE8 6HW",
    "wof:placetype": "postalcode"
  },
  "geometry": {"coordinates":[-1.181678,52.572483],"type":"Point"}
}
