{
  "type": "Feature",
  "properties": {
    "iso:country":"GB",
    "wof:name":"CF24 2BD",
    "wof:placetype":"postalcode"
},
  "geometry": {"coordinates":[-3.1544453858921,51.48216978821846],"type":"Point"}
}