{
  "type": "Feature",
  "properties": {
    "iso:country":"GB",
    "wof:name":"TA4 2RW",
    "wof:placetype":"postalcode"
},
  "geometry": {"coordinates":[-3.2899362167523,51.062111346239],"type":"Point"}
}