{
  "type": "Feature",
  "properties": {
    "iso:country": "GB",
    "wof:name": "TA4 2RW",
    "wof:placetype": "postalcode"
  },
  "geometry": {"coordinates":[-3.287327,51.062801],"type":"Point"}
}
