{
  "type": "Feature",
  "properties": {
    "date:inception_lower": "1980-01-01",
    "date:inception_upper": "1980-01-01",
    "iso:country": "GB",
    "wof:name": "TA4 2RW",
    "wof:placetype": "postalcode"
  },
  "geometry": {"coordinates":[-3.287327,51.062801],"type":"Point"}
}
