{
  "type": "Feature",
  "properties": {
    "date:inception_lower": "2022-02-01",
    "date:inception_upper": "2022-02-01",
    "iso:country": "GB",
    "wof:name": "ME16 9QG",
    "wof:placetype": "postalcode"
  },
  "geometry": {"coordinates":[0.484957,51.277499],"type":"Point"}
}
