{
  "type": "Feature",
  "properties": {
    "date:inception_lower": "1980-01-01",
    "date:inception_upper": "1980-01-01",
    "iso:country": "GB",
    "wof:name": "HU4 7DP",
    "wof:placetype": "postalcode"
  },
  "geometry": {"coordinates":[-0.419408,53.726915],"type":"Point"}
}
