{
  "type": "Feature",
  "properties": {
    "date:inception_lower": "2023-01-01",
    "date:inception_upper": "2023-01-01",
    "iso:country": "GB",
    "wof:name": "PO20 2LR",
    "wof:placetype": "postalcode"
  },
  "geometry": {"coordinates":[-0.745431,50.839023],"type":"Point"}
}
