{
  "type": "Feature",
  "properties": {
    "iso:country": "GB",
    "wof:name": "DN6 9DT",
    "wof:placetype": "postalcode"
  },
  "geometry": {"coordinates":[-1.186616,53.631722],"type":"Point"}
}
