{
  "type": "Feature",
  "properties": {
    "iso:country":"GB",
    "wof:name":"LS22 6SY",
    "wof:placetype":"postalcode"
},
  "geometry": {"coordinates":[-1.38390639511901,53.93202464673131],"type":"Point"}
}