{
  "type": "Feature",
  "properties": {
    "iso:country": "GB",
    "wof:name": "AB45 1JQ",
    "wof:placetype": "postalcode"
  },
  "geometry": {"coordinates":[-2.52732,57.667964],"type":"Point"}
}
