{
  "type": "Feature",
  "properties": {
    "iso:country":"GB",
    "wof:name":"AB45 1JQ",
    "wof:placetype":"postalcode"
},
  "geometry": {"coordinates":[-2.5273196751662,57.66796438924592],"type":"Point"}
}