{
  "type": "Feature",
  "properties": {
    "date:inception_lower":"1980-01-01",
    "date:inception_upper":"1980-01-31",
    "iso:country":"GB",
    "wof:name":"BN27 3PF",
    "wof:placetype":"postalcode"
},
  "geometry": {"coordinates":[0.243951,50.847969],"type":"Point"}
}