{
  "type": "Feature",
  "properties": {
    "iso:country": "GB",
    "wof:name": "BN27 3PF",
    "wof:placetype": "postalcode"
  },
  "geometry": {"coordinates":[0.243951,50.847969],"type":"Point"}
}
