{
  "type": "Feature",
  "properties": {
    "iso:country": "GB",
    "wof:name": "SW9 9QH",
    "wof:placetype": "postalcode"
  },
  "geometry": {"coordinates":[-0.118626,51.466237],"type":"Point"}
}
