{
  "type": "Feature",
  "properties": {
    "iso:country":"GB",
    "wof:name":"SW9 9QH",
    "wof:placetype":"postalcode"
},
  "geometry": {"coordinates":[-0.11862619602252,51.46623724732289],"type":"Point"}
}