{
  "type": "Feature",
  "properties": {
    "iso:country":"GB",
    "wof:name":"EX10 8LF",
    "wof:placetype":"postalcode"
},
  "geometry": {"coordinates":[-3.23795184040081,50.68035112169296],"type":"Point"}
}