{
  "type": "Feature",
  "properties": {
    "iso:country":"GB",
    "wof:name":"M9 6RA",
    "wof:placetype":"postalcode"
},
  "geometry": {"coordinates":[-2.21034665705495,53.53279339971652],"type":"Point"}
}