{
  "type": "Feature",
  "properties": {
    "iso:country": "GB",
    "wof:name": "M9 6RA",
    "wof:placetype": "postalcode"
  },
  "geometry": {"coordinates":[-2.210347,53.532793],"type":"Point"}
}
