{
  "type": "Feature",
  "properties": {
    "iso:country": "GB",
    "wof:name": "PO14 3RE",
    "wof:placetype": "postalcode"
  },
  "geometry": {"coordinates":[-1.221412,50.826784],"type":"Point"}
}
