{
  "type": "Feature",
  "properties": {
    "iso:country": "GB",
    "wof:name": "PL23 1LF",
    "wof:placetype": "postalcode"
  },
  "geometry": {"coordinates":[-4.643211,50.36326],"type":"Point"}
}
