{
  "type": "Feature",
  "properties": {
    "iso:country":"GB",
    "wof:name":"L34 0HJ",
    "wof:placetype":"postalcode"
},
  "geometry": {"coordinates":[-2.85390329816095,53.45211289624525],"type":"Point"}
}