{
  "type": "Feature",
  "properties": {
    "iso:country": "GB",
    "wof:name": "L34 0HJ",
    "wof:placetype": "postalcode"
  },
  "geometry": {"coordinates":[-2.853903,53.452113],"type":"Point"}
}
