{
  "type": "Feature",
  "properties": {
    "date:inception_lower": "1980-01-01",
    "date:inception_upper": "1980-01-01",
    "iso:country": "GB",
    "wof:name": "WF15 8EA",
    "wof:placetype": "postalcode"
  },
  "geometry": {"coordinates":[-1.715792,53.712254],"type":"Point"}
}
