{
  "type": "Feature",
  "properties": {
    "iso:country":"GB",
    "wof:name":"WF15 8EA",
    "wof:placetype":"postalcode"
},
  "geometry": {"coordinates":[-1.71579208586189,53.71225401167403],"type":"Point"}
}