{
  "type": "Feature",
  "properties": {
    "iso:country": "GB",
    "wof:name": "WF15 8EA",
    "wof:placetype": "postalcode"
  },
  "geometry": {"coordinates":[-1.715792,53.712254],"type":"Point"}
}
