{
  "type": "Feature",
  "properties": {
    "date:inception_lower": "1994-05-01",
    "date:inception_upper": "1994-05-01",
    "iso:country": "GB",
    "wof:name": "M34 7PU",
    "wof:placetype": "postalcode"
  },
  "geometry": {"coordinates":[-2.097268,53.439325],"type":"Point"}
}
