{
  "type": "Feature",
  "properties": {
    "iso:country": "GB",
    "wof:name": "BH23 8BJ",
    "wof:placetype": "postalcode"
  },
  "geometry": {"coordinates":[-1.745837,50.78011],"type":"Point"}
}
