{
  "type": "Feature",
  "properties": {
    "iso:country":"GB",
    "wof:name":"PL31 2NX",
    "wof:placetype":"postalcode"
},
  "geometry": {"coordinates":[-4.72603402020925,50.47423509554243],"type":"Point"}
}