{
  "type": "Feature",
  "properties": {
    "iso:country":"GB",
    "wof:name":"BR3 4EF",
    "wof:placetype":"postalcode"
},
  "geometry": {"coordinates":[-0.05064565208471,51.40160205824555],"type":"Point"}
}