{
  "type": "Feature",
  "properties": {
    "date:inception_lower":"1991-09-01",
    "date:inception_upper":"1991-09-30",
    "iso:country":"GB",
    "wof:name":"SL4 6DD",
    "wof:placetype":"postalcode"
},
  "geometry": {"coordinates":[-0.609945,51.49087],"type":"Point"}
}