{
  "type": "Feature",
  "properties": {
    "iso:country":"GB",
    "wof:name":"SL4 6DD",
    "wof:placetype":"postalcode"
},
  "geometry": {"coordinates":[-0.60997733141136,51.49082378816502],"type":"Point"}
}