{
  "type": "Feature",
  "properties": {
    "iso:country":"GB",
    "wof:name":"WA2 9AS",
    "wof:placetype":"postalcode"
},
  "geometry": {"coordinates":[-2.58321172215393,53.41255554272092],"type":"Point"}
}