{
  "type": "Feature",
  "properties": {
    "iso:country": "GB",
    "wof:name": "WA2 9AS",
    "wof:placetype": "postalcode"
  },
  "geometry": {"coordinates":[-2.583212,53.412556],"type":"Point"}
}
