{
  "type": "Feature",
  "properties": {
    "iso:country": "GB",
    "wof:name": "TN11 9NS",
    "wof:placetype": "postalcode"
  },
  "geometry": {"coordinates":[0.286827,51.230627],"type":"Point"}
}
