{
  "type": "Feature",
  "properties": {
    "iso:country": "GB",
    "wof:name": "G66 4HW",
    "wof:placetype": "postalcode"
  },
  "geometry": {"coordinates":[-4.160445,55.925151],"type":"Point"}
}
