{
  "type": "Feature",
  "properties": {
    "date:inception_lower": "2016-06-01",
    "date:inception_upper": "2016-06-01",
    "iso:country": "GB",
    "wof:name": "MK45 1GS",
    "wof:placetype": "postalcode"
  },
  "geometry": {"coordinates":[-0.511076,52.011369],"type":"Point"}
}
