{
  "type": "Feature",
  "properties": {
    "iso:country": "GB",
    "wof:name": "MK45 1GS",
    "wof:placetype": "postalcode"
  },
  "geometry": {"coordinates":[-0.511091,52.01136],"type":"Point"}
}
