{
  "type": "Feature",
  "properties": {
    "iso:country": "GB",
    "wof:name": "LU7 3JB",
    "wof:placetype": "postalcode"
  },
  "geometry": {"coordinates":[-0.663485,51.932148],"type":"Point"}
}
