{
  "type": "Feature",
  "properties": {
    "iso:country":"GB",
    "wof:name":"CR8 5AH",
    "wof:placetype":"postalcode"
},
  "geometry": {"coordinates":[-0.09222963114177,51.32161231491578],"type":"Point"}
}