{
  "type": "Feature",
  "properties": {
    "iso:country":"GB",
    "wof:name":"HA0 2PX",
    "wof:placetype":"postalcode"
},
  "geometry": {"coordinates":[-0.32098101575021,51.55746122055682],"type":"Point"}
}