{
  "type": "Feature",
  "properties": {
    "iso:country":"GB",
    "wof:name":"OX4 2QN",
    "wof:placetype":"postalcode"
},
  "geometry": {"coordinates":[-1.20342459059958,51.73877399132146],"type":"Point"}
}