{
  "type": "Feature",
  "properties": {
    "date:inception_lower": "1990-02-01",
    "date:inception_upper": "1990-02-01",
    "iso:country": "GB",
    "wof:name": "SL5 8LZ",
    "wof:placetype": "postalcode"
  },
  "geometry": {"coordinates":[-0.697518,51.417743],"type":"Point"}
}
