{
  "type": "Feature",
  "properties": {
    "iso:country": "GB",
    "wof:name": "CF44 6LA",
    "wof:placetype": "postalcode"
  },
  "geometry": {"coordinates":[-3.45103,51.685636],"type":"Point"}
}
