{
  "type": "Feature",
  "properties": {
    "iso:country":"GB",
    "wof:name":"CF44 6LA",
    "wof:placetype":"postalcode"
},
  "geometry": {"coordinates":[-3.45102965177363,51.68563600243281],"type":"Point"}
}