{
  "type": "Feature",
  "properties": {
    "date:inception_lower": "1980-01-01",
    "date:inception_upper": "1980-01-01",
    "iso:country": "GB",
    "wof:name": "WF12 7HQ",
    "wof:placetype": "postalcode"
  },
  "geometry": {"coordinates":[-1.607477,53.702574],"type":"Point"}
}
