{
  "type": "Feature",
  "properties": {
    "iso:country":"GB",
    "wof:name":"LD2 3ES",
    "wof:placetype":"postalcode"
},
  "geometry": {"coordinates":[-3.3956554325706,52.14978073288979],"type":"Point"}
}