{
  "type": "Feature",
  "properties": {
    "date:inception_lower": "1980-01-01",
    "date:inception_upper": "1980-01-01",
    "iso:country": "GB",
    "wof:name": "LD2 3ES",
    "wof:placetype": "postalcode"
  },
  "geometry": {"coordinates":[-3.395655,52.149781],"type":"Point"}
}
