{
  "type": "Feature",
  "properties": {
    "iso:country":"GB",
    "wof:name":"NG8 5JU",
    "wof:placetype":"postalcode"
},
  "geometry": {"coordinates":[-1.19811795837176,52.98064902904834],"type":"Point"}
}