{
  "type": "Feature",
  "properties": {
    "date:inception_lower": "1980-01-01",
    "date:inception_upper": "1980-01-01",
    "iso:country": "GB",
    "wof:name": "NG8 5JU",
    "wof:placetype": "postalcode"
  },
  "geometry": {"coordinates":[-1.198118,52.980649],"type":"Point"}
}
