{
  "type": "Feature",
  "properties": {
    "date:inception_lower": "2002-09-01",
    "date:inception_upper": "2002-09-01",
    "iso:country": "GB",
    "wof:name": "OL15 8SA",
    "wof:placetype": "postalcode"
  },
  "geometry": {"coordinates":[-2.10582,53.639164],"type":"Point"}
}
