{
  "type": "Feature",
  "properties": {
    "iso:country": "GB",
    "wof:name": "NN11 3UP",
    "wof:placetype": "postalcode"
  },
  "geometry": {"coordinates":[-1.215953,52.174317],"type":"Point"}
}
