{
  "type": "Feature",
  "properties": {
    "iso:country":"GB",
    "wof:name":"YO17 9TS",
    "wof:placetype":"postalcode"
},
  "geometry": {"coordinates":[-0.70111127364605,54.08106546396063],"type":"Point"}
}