{
  "type": "Feature",
  "properties": {
    "iso:country": "GB",
    "wof:name": "YO17 9TS",
    "wof:placetype": "postalcode"
  },
  "geometry": {"coordinates":[-0.701111,54.081065],"type":"Point"}
}
