{
  "type": "Feature",
  "properties": {
    "iso:country":"GB",
    "wof:name":"BL1 5ER",
    "wof:placetype":"postalcode"
},
  "geometry": {"coordinates":[-2.47945362326904,53.58509320947257],"type":"Point"}
}