{
  "type": "Feature",
  "properties": {
    "iso:country":"GB",
    "wof:name":"SE11 6DQ",
    "wof:placetype":"postalcode"
},
  "geometry": {"coordinates":[-0.11320497148394,51.49469258744612],"type":"Point"}
}