{
  "type": "Feature",
  "properties": {
    "iso:country":"GB",
    "wof:name":"BH1 3PP",
    "wof:placetype":"postalcode"
},
  "geometry": {"coordinates":[-1.85642059232217,50.72481594059025],"type":"Point"}
}