{
  "type": "Feature",
  "properties": {
    "date:inception_lower":"1980-01-01",
    "date:inception_upper":"1980-01-31",
    "iso:country":"GB",
    "wof:name":"E5 8RR",
    "wof:placetype":"postalcode"
},
  "geometry": {"coordinates":[-0.064322,51.563806],"type":"Point"}
}