{
  "type": "Feature",
  "properties": {
    "iso:country":"GB",
    "wof:name":"BL5 1BP",
    "wof:placetype":"postalcode"
},
  "geometry": {"coordinates":[-2.46434501313476,53.54485786114376],"type":"Point"}
}