{
  "type": "Feature",
  "properties": {
    "iso:country": "GB",
    "wof:name": "NR3 1AY",
    "wof:placetype": "postalcode"
  },
  "geometry": {"coordinates":[1.29735,52.631328],"type":"Point"}
}
