{
  "type": "Feature",
  "properties": {
    "iso:country":"GB",
    "wof:name":"BH15 2LJ",
    "wof:placetype":"postalcode"
},
  "geometry": {"coordinates":[-1.97086221467695,50.72563783470968],"type":"Point"}
}