{
  "type": "Feature",
  "properties": {
    "iso:country": "GB",
    "wof:name": "BH15 2LJ",
    "wof:placetype": "postalcode"
  },
  "geometry": {"coordinates":[-1.970862,50.725638],"type":"Point"}
}
