{
  "type": "Feature",
  "properties": {
    "date:inception_lower": "2015-07-01",
    "date:inception_upper": "2015-07-01",
    "iso:country": "GB",
    "wof:name": "WF2 9EA",
    "wof:placetype": "postalcode"
  },
  "geometry": {"coordinates":[-1.540269,53.681813],"type":"Point"}
}
