{
  "type": "Feature",
  "properties": {
    "date:inception_lower":"2014-09-01",
    "date:inception_upper":"2014-09-30",
    "iso:country":"GB",
    "wof:name":"BS16 1ZU",
    "wof:placetype":"postalcode"
},
  "geometry": {"coordinates":[-2.55069,51.499066],"type":"Point"}
}