{
  "type": "Feature",
  "properties": {
    "iso:country":"GB",
    "wof:name":"BS16 1ZU",
    "wof:placetype":"postalcode"
},
  "geometry": {"coordinates":[-2.55096069785175,51.49886850681581],"type":"Point"}
}