{
  "type": "Feature",
  "properties": {
    "iso:country": "GB",
    "wof:name": "BS16 1ZU",
    "wof:placetype": "postalcode"
  },
  "geometry": {"coordinates":[-2.55069,51.499066],"type":"Point"}
}
