{
  "type": "Feature",
  "properties": {
    "iso:country":"GB",
    "wof:name":"TF10 7HH",
    "wof:placetype":"postalcode"
},
  "geometry": {"coordinates":[-2.38106461324936,52.76430620860172],"type":"Point"}
}