{
  "type": "Feature",
  "properties": {
    "iso:country":"GB",
    "wof:name":"S17 4JB",
    "wof:placetype":"postalcode"
},
  "geometry": {"coordinates":[-1.51556213286016,53.31753040051534],"type":"Point"}
}