{
  "type": "Feature",
  "properties": {
    "iso:country":"GB",
    "wof:name":"B61 0NG",
    "wof:placetype":"postalcode"
},
  "geometry": {"coordinates":[-2.05563986143081,52.36145119868981],"type":"Point"}
}