{
  "type": "Feature",
  "properties": {
    "date:inception_lower":"1980-01-01",
    "date:inception_upper":"1980-01-31",
    "iso:country":"GB",
    "wof:name":"SK17 7LB",
    "wof:placetype":"postalcode"
},
  "geometry": {"coordinates":[-1.89808,53.261787],"type":"Point"}
}