{
  "type": "Feature",
  "properties": {
    "date:inception_lower": "1980-01-01",
    "date:inception_upper": "1980-01-01",
    "iso:country": "GB",
    "wof:name": "NE34 8TN",
    "wof:placetype": "postalcode"
  },
  "geometry": {"coordinates":[-1.421243,54.962171],"type":"Point"}
}
