{
  "type": "Feature",
  "properties": {
    "iso:country":"GB",
    "wof:name":"NE34 8TN",
    "wof:placetype":"postalcode"
},
  "geometry": {"coordinates":[-1.42124289866707,54.96217107573601],"type":"Point"}
}