{
  "type": "Feature",
  "properties": {
    "iso:country":"GB",
    "wof:name":"SS11 8LN",
    "wof:placetype":"postalcode"
},
  "geometry": {"coordinates":[0.53924979756455,51.61760173849022],"type":"Point"}
}