{
  "type": "Feature",
  "properties": {
    "date:inception_lower":"1991-03-01",
    "date:inception_upper":"1991-03-31",
    "iso:country":"GB",
    "wof:name":"FK2 7EP",
    "wof:placetype":"postalcode"
},
  "geometry": {"coordinates":[-3.795386,56.013596],"type":"Point"}
}