{
  "type": "Feature",
  "properties": {
    "iso:country":"GB",
    "wof:name":"PE21 8RS",
    "wof:placetype":"postalcode"
},
  "geometry": {"coordinates":[-0.02920471277381,52.97636826247535],"type":"Point"}
}