{
  "type": "Feature",
  "properties": {
    "date:inception_lower": "2002-09-01",
    "date:inception_upper": "2002-09-01",
    "iso:country": "GB",
    "wof:name": "PE21 8RS",
    "wof:placetype": "postalcode"
  },
  "geometry": {"coordinates":[-0.029033,52.976399],"type":"Point"}
}
