{
  "type": "Feature",
  "properties": {
    "iso:country": "GB",
    "wof:name": "PE21 8RS",
    "wof:placetype": "postalcode"
  },
  "geometry": {"coordinates":[-0.029197,52.976392],"type":"Point"}
}
