{
  "type": "Feature",
  "properties": {
    "iso:country":"GB",
    "wof:name":"SW15 5HR",
    "wof:placetype":"postalcode"
},
  "geometry": {"coordinates":[-0.23631886997615,51.45849872594329],"type":"Point"}
}