{
  "type": "Feature",
  "properties": {
    "date:inception_lower": "1980-01-01",
    "date:inception_upper": "1980-01-01",
    "iso:country": "GB",
    "wof:name": "WV12 5TL",
    "wof:placetype": "postalcode"
  },
  "geometry": {"coordinates":[-2.042796,52.608132],"type":"Point"}
}
