{
  "type": "Feature",
  "properties": {
    "iso:country":"GB",
    "wof:name":"WV12 5TL",
    "wof:placetype":"postalcode"
},
  "geometry": {"coordinates":[-2.04279602512498,52.60813184668384],"type":"Point"}
}