{
  "type": "Feature",
  "properties": {
    "iso:country":"GB",
    "wof:name":"SS16 5UY",
    "wof:placetype":"postalcode"
},
  "geometry": {"coordinates":[0.46675852433719,51.56753583642519],"type":"Point"}
}