{
  "type": "Feature",
  "properties": {
    "iso:country": "GB",
    "wof:name": "BD3 7JR",
    "wof:placetype": "postalcode"
  },
  "geometry": {"coordinates":[-1.725977,53.805034],"type":"Point"}
}
