{
  "type": "Feature",
  "properties": {
    "iso:country":"GB",
    "wof:name":"BD3 7JR",
    "wof:placetype":"postalcode"
},
  "geometry": {"coordinates":[-1.72597685768645,53.80503434045451],"type":"Point"}
}