{
  "type": "Feature",
  "properties": {
    "date:inception_lower":"1980-01-01",
    "date:inception_upper":"1980-01-31",
    "iso:country":"GB",
    "wof:name":"BD3 7JR",
    "wof:placetype":"postalcode"
},
  "geometry": {"coordinates":[-1.725977,53.805034],"type":"Point"}
}