{
  "type": "Feature",
  "properties": {
    "iso:country":"GB",
    "wof:name":"L23 0TE",
    "wof:placetype":"postalcode"
},
  "geometry": {"coordinates":[-3.01344245274851,53.48464587243063],"type":"Point"}
}