{
  "type": "Feature",
  "properties": {
    "iso:country":"GB",
    "wof:name":"HP15 6BQ",
    "wof:placetype":"postalcode"
},
  "geometry": {"coordinates":[-0.71917706604939,51.66378446186832],"type":"Point"}
}