{
  "type": "Feature",
  "properties": {
    "iso:country":"GB",
    "wof:name":"SL3 7QF",
    "wof:placetype":"postalcode"
},
  "geometry": {"coordinates":[-0.55644956410056,51.50136338691288],"type":"Point"}
}