{
  "type": "Feature",
  "properties": {
    "iso:country":"GB",
    "wof:name":"L35 0QX",
    "wof:placetype":"postalcode"
},
  "geometry": {"coordinates":[-2.7552578855819,53.40732138261132],"type":"Point"}
}