{
  "type": "Feature",
  "properties": {
    "date:inception_lower":"2016-06-01",
    "date:inception_upper":"2016-06-30",
    "iso:country":"GB",
    "wof:name":"W1F 8GS",
    "wof:placetype":"postalcode"
},
  "geometry": {"coordinates":[-0.135943,51.515038],"type":"Point"}
}