{
  "type": "Feature",
  "properties": {
    "iso:country":"GB",
    "wof:name":"GU10 4ST",
    "wof:placetype":"postalcode"
},
  "geometry": {"coordinates":[-0.80986402022547,51.19249623512997],"type":"Point"}
}