{
  "type": "Feature",
  "properties": {
    "iso:country":"GB",
    "wof:name":"CH8 9EN",
    "wof:placetype":"postalcode"
},
  "geometry": {"coordinates":[-3.27080408323288,53.28937600535748],"type":"Point"}
}