{
  "type": "Feature",
  "properties": {
    "iso:country": "GB",
    "wof:name": "CH8 9EN",
    "wof:placetype": "postalcode"
  },
  "geometry": {"coordinates":[-3.270804,53.289376],"type":"Point"}
}
