{
  "type": "Feature",
  "properties": {
    "iso:country": "GB",
    "wof:name": "EH12 5RD",
    "wof:placetype": "postalcode"
  },
  "geometry": {"coordinates":[-3.248402,55.943125],"type":"Point"}
}
