{
  "type": "Feature",
  "properties": {
    "date:inception_lower": "2007-11-01",
    "date:inception_upper": "2007-11-01",
    "iso:country": "GB",
    "wof:name": "PA3 3BB",
    "wof:placetype": "postalcode"
  },
  "geometry": {"coordinates":[-4.47683,55.84413],"type":"Point"}
}
