{
  "type": "Feature",
  "properties": {
    "iso:country":"GB",
    "wof:name":"EH49 7HN",
    "wof:placetype":"postalcode"
},
  "geometry": {"coordinates":[-3.60643548155808,55.97621454482263],"type":"Point"}
}