{
  "type": "Feature",
  "properties": {
    "iso:country":"GB",
    "wof:name":"NW3 1RX",
    "wof:placetype":"postalcode"
},
  "geometry": {"coordinates":[-0.17220427791188,51.55646093853371],"type":"Point"}
}