{
  "type": "Feature",
  "properties": {
    "iso:country":"GB",
    "wof:name":"LS22 6WQ",
    "wof:placetype":"postalcode"
},
  "geometry": {"coordinates":[-1.39720207140712,53.93418626137287],"type":"Point"}
}