{
  "type": "Feature",
  "properties": {
    "iso:country":"GB",
    "wof:name":"ME1 2RR",
    "wof:placetype":"postalcode"
},
  "geometry": {"coordinates":[0.513468567744,51.36423666006579],"type":"Point"}
}