{
  "type": "Feature",
  "properties": {
    "date:inception_lower": "1980-01-01",
    "date:inception_upper": "1980-01-01",
    "iso:country": "GB",
    "wof:name": "SY4 5RB",
    "wof:placetype": "postalcode"
  },
  "geometry": {"coordinates":[-2.723936,52.88637],"type":"Point"}
}
