{
  "type": "Feature",
  "properties": {
    "iso:country": "GB",
    "wof:name": "RG41 5EB",
    "wof:placetype": "postalcode"
  },
  "geometry": {"coordinates":[-0.884294,51.429156],"type":"Point"}
}
