{
  "type": "Feature",
  "properties": {
    "iso:country":"GB",
    "wof:name":"DE1 3HN",
    "wof:placetype":"postalcode"
},
  "geometry": {"coordinates":[-1.48645524383193,52.92999749361616],"type":"Point"}
}