{
  "type": "Feature",
  "properties": {
    "iso:country":"GB",
    "wof:name":"BA2 5AE",
    "wof:placetype":"postalcode"
},
  "geometry": {"coordinates":[-2.34558994600109,51.36356588636335],"type":"Point"}
}