{
  "type": "Feature",
  "properties": {
    "iso:country": "GB",
    "wof:name": "BA2 5AE",
    "wof:placetype": "postalcode"
  },
  "geometry": {"coordinates":[-2.34559,51.363566],"type":"Point"}
}
