{
  "type": "Feature",
  "properties": {
    "date:inception_lower": "1980-01-01",
    "date:inception_upper": "1980-01-01",
    "iso:country": "GB",
    "wof:name": "G51 1AQ",
    "wof:placetype": "postalcode"
  },
  "geometry": {"coordinates":[-4.297375,55.85226],"type":"Point"}
}
