{
  "type": "Feature",
  "properties": {
    "date:inception_lower": "2024-01-01",
    "date:inception_upper": "2024-01-01",
    "iso:country": "GB",
    "wof:name": "TN17 3FD",
    "wof:placetype": "postalcode"
  },
  "geometry": {"coordinates":[0.524589,51.092619],"type":"Point"}
}
