{
  "type": "Feature",
  "properties": {
    "iso:country":"GB",
    "wof:name":"TN22 1ES",
    "wof:placetype":"postalcode"
},
  "geometry": {"coordinates":[0.09845246777864,50.97646160845601],"type":"Point"}
}