{
  "type": "Feature",
  "properties": {
    "iso:country": "GB",
    "wof:name": "TN22 1ES",
    "wof:placetype": "postalcode"
  },
  "geometry": {"coordinates":[0.098453,50.976462],"type":"Point"}
}
