{
  "type": "Feature",
  "properties": {
    "iso:country": "GB",
    "wof:name": "SA48 8DJ",
    "wof:placetype": "postalcode"
  },
  "geometry": {"coordinates":[-4.201267,52.232883],"type":"Point"}
}
