{
  "type": "Feature",
  "properties": {
    "iso:country":"GB",
    "wof:name":"SA48 8DJ",
    "wof:placetype":"postalcode"
},
  "geometry": {"coordinates":[-4.20160595521737,52.23589369988369],"type":"Point"}
}