{
  "type": "Feature",
  "properties": {
    "date:inception_lower": "2022-02-01",
    "date:inception_upper": "2022-02-01",
    "iso:country": "GB",
    "wof:name": "RG42 6EZ",
    "wof:placetype": "postalcode"
  },
  "geometry": {"coordinates":[-0.753797,51.433319],"type":"Point"}
}
