{
  "type": "Feature",
  "properties": {
    "iso:country":"GB",
    "wof:name":"SE8 5JG",
    "wof:placetype":"postalcode"
},
  "geometry": {"coordinates":[-0.04287347224523,51.48628280771631],"type":"Point"}
}