{
  "type": "Feature",
  "properties": {
    "iso:country":"GB",
    "wof:name":"HU12 9EF",
    "wof:placetype":"postalcode"
},
  "geometry": {"coordinates":[-0.13728588443276,53.73942782420427],"type":"Point"}
}