{
  "type": "Feature",
  "properties": {
    "date:inception_lower":"1980-01-01",
    "date:inception_upper":"1980-01-31",
    "iso:country":"GB",
    "wof:name":"HU12 9EF",
    "wof:placetype":"postalcode"
},
  "geometry": {"coordinates":[-0.137286,53.739428],"type":"Point"}
}