{
  "type": "Feature",
  "properties": {
    "iso:country": "GB",
    "wof:name": "HU12 9EF",
    "wof:placetype": "postalcode"
  },
  "geometry": {"coordinates":[-0.137286,53.739428],"type":"Point"}
}
