{
  "type": "Feature",
  "properties": {
    "iso:country":"GB",
    "wof:name":"SL7 2AH",
    "wof:placetype":"postalcode"
},
  "geometry": {"coordinates":[-0.78331608413397,51.56709468015707],"type":"Point"}
}