{
  "type": "Feature",
  "properties": {
    "iso:country":"GB",
    "wof:name":"LL17 0AZ",
    "wof:placetype":"postalcode"
},
  "geometry": {"coordinates":[-3.42871191025003,53.23304869880736],"type":"Point"}
}