{
  "type": "Feature",
  "properties": {
    "iso:country":"GB",
    "wof:name":"CO16 0BA",
    "wof:placetype":"postalcode"
},
  "geometry": {"coordinates":[1.16841371207764,51.87902453955014],"type":"Point"}
}