{
  "type": "Feature",
  "properties": {
    "iso:country": "GB",
    "wof:name": "CO16 0BA",
    "wof:placetype": "postalcode"
  },
  "geometry": {"coordinates":[1.168414,51.879025],"type":"Point"}
}
