{
  "type": "Feature",
  "properties": {
    "date:inception_lower": "1980-01-01",
    "date:inception_upper": "1980-01-01",
    "iso:country": "GB",
    "wof:name": "CO16 0BA",
    "wof:placetype": "postalcode"
  },
  "geometry": {"coordinates":[1.168414,51.879025],"type":"Point"}
}
