{
  "type": "Feature",
  "properties": {
    "iso:country": "GB",
    "wof:name": "SE23 3RA",
    "wof:placetype": "postalcode"
  },
  "geometry": {"coordinates":[-0.054291,51.450844],"type":"Point"}
}
