{
  "type": "Feature",
  "properties": {
    "iso:country":"GB",
    "wof:name":"SE23 3RA",
    "wof:placetype":"postalcode"
},
  "geometry": {"coordinates":[-0.05429149371539,51.45084387492071],"type":"Point"}
}