{
  "type": "Feature",
  "properties": {
    "iso:country":"GB",
    "wof:name":"OL4 2LA",
    "wof:placetype":"postalcode"
},
  "geometry": {"coordinates":[-2.07049712594916,53.5719133383262],"type":"Point"}
}