{
  "type": "Feature",
  "properties": {
    "date:inception_lower":"1980-01-01",
    "date:inception_upper":"1980-01-31",
    "iso:country":"GB",
    "wof:name":"WR7 4QH",
    "wof:placetype":"postalcode"
},
  "geometry": {"coordinates":[-2.115461,52.168647],"type":"Point"}
}