{
  "type": "Feature",
  "properties": {
    "iso:country":"GB",
    "wof:name":"WR7 4QH",
    "wof:placetype":"postalcode"
},
  "geometry": {"coordinates":[-2.11546142349005,52.16864691901198],"type":"Point"}
}