{
  "type": "Feature",
  "properties": {
    "iso:country": "GB",
    "wof:name": "WR7 4QH",
    "wof:placetype": "postalcode"
  },
  "geometry": {"coordinates":[-2.115461,52.168647],"type":"Point"}
}
