{
  "type": "Feature",
  "properties": {
    "iso:country":"GB",
    "wof:name":"LE67 5AG",
    "wof:placetype":"postalcode"
},
  "geometry": {"coordinates":[-1.35501326731241,52.74105255528235],"type":"Point"}
}