{
  "type": "Feature",
  "properties": {
    "date:inception_lower":"1980-01-01",
    "date:inception_upper":"1980-01-31",
    "iso:country":"GB",
    "wof:name":"GU19 5AE",
    "wof:placetype":"postalcode"
},
  "geometry": {"coordinates":[-0.694238,51.360238],"type":"Point"}
}