{
  "type": "Feature",
  "properties": {
    "iso:country":"GB",
    "wof:name":"B31 1TN",
    "wof:placetype":"postalcode"
},
  "geometry": {"coordinates":[-1.98304436913331,52.42483439224598],"type":"Point"}
}