{
  "type": "Feature",
  "properties": {
    "iso:country": "GB",
    "wof:name": "B31 1TN",
    "wof:placetype": "postalcode"
  },
  "geometry": {"coordinates":[-1.983044,52.424834],"type":"Point"}
}
