{
  "type": "Feature",
  "properties": {
    "date:inception_lower":"1980-01-01",
    "date:inception_upper":"1980-01-31",
    "iso:country":"GB",
    "wof:name":"MK45 2EE",
    "wof:placetype":"postalcode"
},
  "geometry": {"coordinates":[-0.464887,52.031617],"type":"Point"}
}