{
  "type": "Feature",
  "properties": {
    "iso:country": "GB",
    "wof:name": "NR17 2BD",
    "wof:placetype": "postalcode"
  },
  "geometry": {"coordinates":[1.025363,52.512621],"type":"Point"}
}
