{
  "type": "Feature",
  "properties": {
    "iso:country":"GB",
    "wof:name":"TA19 9BP",
    "wof:placetype":"postalcode"
},
  "geometry": {"coordinates":[-2.91638886364242,50.92729750132268],"type":"Point"}
}