{
  "type": "Feature",
  "properties": {
    "iso:country":"GB",
    "wof:name":"B24 8DX",
    "wof:placetype":"postalcode"
},
  "geometry": {"coordinates":[-1.83434446958839,52.51007983597959],"type":"Point"}
}