{
  "type": "Feature",
  "properties": {
    "iso:country":"GB",
    "wof:name":"ST4 4JX",
    "wof:placetype":"postalcode"
},
  "geometry": {"coordinates":[-2.1731800922105,52.99360740950049],"type":"Point"}
}