{
  "type": "Feature",
  "properties": {
    "date:inception_lower":"1980-01-01",
    "date:inception_upper":"1980-01-31",
    "iso:country":"GB",
    "wof:name":"ST4 4JX",
    "wof:placetype":"postalcode"
},
  "geometry": {"coordinates":[-2.173224,52.993688],"type":"Point"}
}