{
  "type": "Feature",
  "properties": {
    "iso:country": "GB",
    "wof:name": "CF72 9TX",
    "wof:placetype": "postalcode"
  },
  "geometry": {"coordinates":[-3.445012,51.532856],"type":"Point"}
}
