{
  "type": "Feature",
  "properties": {
    "date:inception_lower": "1995-12-01",
    "date:inception_upper": "1995-12-01",
    "iso:country": "GB",
    "wof:name": "CF72 9TX",
    "wof:placetype": "postalcode"
  },
  "geometry": {"coordinates":[-3.445012,51.532856],"type":"Point"}
}
