{
  "type": "Feature",
  "properties": {
    "iso:country": "GB",
    "wof:name": "LD1 6YN",
    "wof:placetype": "postalcode"
  },
  "geometry": {"coordinates":[-3.358628,52.40453],"type":"Point"}
}
