{
  "type": "Feature",
  "properties": {
    "date:inception_lower": "1980-01-01",
    "date:inception_upper": "1980-01-01",
    "iso:country": "GB",
    "wof:name": "LD1 6YN",
    "wof:placetype": "postalcode"
  },
  "geometry": {"coordinates":[-3.358628,52.40453],"type":"Point"}
}
