{
  "type": "Feature",
  "properties": {
    "date:inception_lower": "1980-01-01",
    "date:inception_upper": "1980-01-01",
    "iso:country": "GB",
    "wof:name": "EX8 2PN",
    "wof:placetype": "postalcode"
  },
  "geometry": {"coordinates":[-3.37775,50.627466],"type":"Point"}
}
