{
  "type": "Feature",
  "properties": {
    "date:inception_lower": "2023-01-01",
    "date:inception_upper": "2023-01-01",
    "iso:country": "GB",
    "wof:name": "EH19 3SQ",
    "wof:placetype": "postalcode"
  },
  "geometry": {"coordinates":[-3.088118,55.868885],"type":"Point"}
}
