{
  "type": "Feature",
  "properties": {
    "iso:country":"GB",
    "wof:name":"CO9 2JJ",
    "wof:placetype":"postalcode"
},
  "geometry": {"coordinates":[0.64058016606528,51.94329576784305],"type":"Point"}
}