{
  "type": "Feature",
  "properties": {
    "iso:country": "GB",
    "wof:name": "CM18 7DY",
    "wof:placetype": "postalcode"
  },
  "geometry": {"coordinates":[0.111971,51.753907],"type":"Point"}
}
