{
  "type": "Feature",
  "properties": {
    "iso:country":"GB",
    "wof:name":"BN3 5QU",
    "wof:placetype":"postalcode"
},
  "geometry": {"coordinates":[-0.19183960214434,50.83397051635148],"type":"Point"}
}