{
  "type": "Feature",
  "properties": {
    "date:inception_lower": "1980-01-01",
    "date:inception_upper": "1980-01-01",
    "iso:country": "GB",
    "wof:name": "PA3 1LE",
    "wof:placetype": "postalcode"
  },
  "geometry": {"coordinates":[-4.447131,55.849663],"type":"Point"}
}
