{
  "type": "Feature",
  "properties": {
    "iso:country":"GB",
    "wof:name":"PA3 1LE",
    "wof:placetype":"postalcode"
},
  "geometry": {"coordinates":[-4.44711031662692,55.8496057473286],"type":"Point"}
}