{
  "type": "Feature",
  "properties": {
    "iso:country":"GB",
    "wof:name":"DT5 1EJ",
    "wof:placetype":"postalcode"
},
  "geometry": {"coordinates":[-2.44241881752051,50.5624802829747],"type":"Point"}
}