{
  "type": "Feature",
  "properties": {
    "iso:country": "GB",
    "wof:name": "W13 9HP",
    "wof:placetype": "postalcode"
  },
  "geometry": {"coordinates":[-0.321859,51.508906],"type":"Point"}
}
