{
  "type": "Feature",
  "properties": {
    "iso:country":"GB",
    "wof:name":"BN26 6TR",
    "wof:placetype":"postalcode"
},
  "geometry": {"coordinates":[0.16720559192286,50.85528416845346],"type":"Point"}
}