{
  "type": "Feature",
  "properties": {
    "date:inception_lower":"2009-09-01",
    "date:inception_upper":"2009-09-30",
    "iso:country":"GB",
    "wof:name":"SA65 0AA",
    "wof:placetype":"postalcode"
},
  "geometry": {"coordinates":[-4.97756,51.99607],"type":"Point"}
}