{
  "type": "Feature",
  "properties": {
    "iso:country":"GB",
    "wof:name":"SA65 0AA",
    "wof:placetype":"postalcode"
},
  "geometry": {"coordinates":[-4.97756000405085,51.99606983252085],"type":"Point"}
}