{
  "type": "Feature",
  "properties": {
    "date:inception_lower": "2002-11-01",
    "date:inception_upper": "2002-11-01",
    "iso:country": "GB",
    "wof:name": "TD1 3LE",
    "wof:placetype": "postalcode"
  },
  "geometry": {"coordinates":[-2.877908,55.616272],"type":"Point"}
}
