{
  "type": "Feature",
  "properties": {
    "iso:country": "GB",
    "wof:name": "DA11 8DH",
    "wof:placetype": "postalcode"
  },
  "geometry": {"coordinates":[0.343517,51.437117],"type":"Point"}
}
