{
  "type": "Feature",
  "properties": {
    "iso:country":"GB",
    "wof:name":"DA11 8DH",
    "wof:placetype":"postalcode"
},
  "geometry": {"coordinates":[0.34351691978107,51.43711689927006],"type":"Point"}
}