{
  "type": "Feature",
  "properties": {
    "iso:country": "GB",
    "wof:name": "DY4 9HT",
    "wof:placetype": "postalcode"
  },
  "geometry": {"coordinates":[-2.068297,52.540633],"type":"Point"}
}
