{
  "type": "Feature",
  "properties": {
    "date:inception_lower":"2013-03-01",
    "date:inception_upper":"2013-03-31",
    "iso:country":"GB",
    "wof:name":"DY4 9HT",
    "wof:placetype":"postalcode"
},
  "geometry": {"coordinates":[-2.068297,52.540633],"type":"Point"}
}