{
  "type": "Feature",
  "properties": {
    "iso:country":"GB",
    "wof:name":"B76 1QU",
    "wof:placetype":"postalcode"
},
  "geometry": {"coordinates":[-1.80653588935648,52.54821779489894],"type":"Point"}
}