{
  "type": "Feature",
  "properties": {
    "iso:country":"GB",
    "wof:name":"SS4 3DF",
    "wof:placetype":"postalcode"
},
  "geometry": {"coordinates":[0.69480076888883,51.59764735585268],"type":"Point"}
}