{
  "type": "Feature",
  "properties": {
    "iso:country": "GB",
    "wof:name": "PH1 3HD",
    "wof:placetype": "postalcode"
  },
  "geometry": {"coordinates":[-3.487798,56.406324],"type":"Point"}
}
