{
  "type": "Feature",
  "properties": {
    "date:inception_lower": "2019-07-01",
    "date:inception_upper": "2019-07-01",
    "iso:country": "GB",
    "wof:name": "PH1 3HD",
    "wof:placetype": "postalcode"
  },
  "geometry": {"coordinates":[-3.488302,56.405967],"type":"Point"}
}
