{
  "type": "Feature",
  "properties": {
    "date:inception_lower": "1986-04-01",
    "date:inception_upper": "1986-04-01",
    "iso:country": "GB",
    "wof:name": "OX2 9SF",
    "wof:placetype": "postalcode"
  },
  "geometry": {"coordinates":[-1.312221,51.751734],"type":"Point"}
}
