{
  "type": "Feature",
  "properties": {
    "iso:country": "GB",
    "wof:name": "BN12 4DG",
    "wof:placetype": "postalcode"
  },
  "geometry": {"coordinates":[-0.406221,50.806123],"type":"Point"}
}
