{
  "type": "Feature",
  "properties": {
    "iso:country":"GB",
    "wof:name":"BN12 4DG",
    "wof:placetype":"postalcode"
},
  "geometry": {"coordinates":[-0.4062208995853,50.80612311153364],"type":"Point"}
}