{
  "type": "Feature",
  "properties": {
    "iso:country":"GB",
    "wof:name":"WA6 7NR",
    "wof:placetype":"postalcode"
},
  "geometry": {"coordinates":[-2.7228007718426,53.30020465297493],"type":"Point"}
}