{
  "type": "Feature",
  "properties": {
    "date:inception_lower": "2005-01-01",
    "date:inception_upper": "2005-01-01",
    "iso:country": "GB",
    "wof:name": "WA6 7NR",
    "wof:placetype": "postalcode"
  },
  "geometry": {"coordinates":[-2.722801,53.300205],"type":"Point"}
}
