{
  "type": "Feature",
  "properties": {
    "iso:country":"GB",
    "wof:name":"EX39 5EJ",
    "wof:placetype":"postalcode"
},
  "geometry": {"coordinates":[-4.23988693455225,50.97095523653495],"type":"Point"}
}