{
  "type": "Feature",
  "properties": {
    "iso:country":"GB",
    "wof:name":"SM1 2BW",
    "wof:placetype":"postalcode"
},
  "geometry": {"coordinates":[-0.2076884666973,51.35883144574512],"type":"Point"}
}