{
  "type": "Feature",
  "properties": {
    "iso:country":"GB",
    "wof:name":"N20 0RU",
    "wof:placetype":"postalcode"
},
  "geometry": {"coordinates":[-0.15350271202418,51.62353906742108],"type":"Point"}
}