{
  "type": "Feature",
  "properties": {
    "iso:country":"GB",
    "wof:name":"NN13 5GJ",
    "wof:placetype":"postalcode"
},
  "geometry": {"coordinates":[-1.12783044165191,52.05167629923378],"type":"Point"}
}