{
  "type": "Feature",
  "properties": {
    "iso:country": "GB",
    "wof:name": "NN13 5GJ",
    "wof:placetype": "postalcode"
  },
  "geometry": {"coordinates":[-1.127538,52.051604],"type":"Point"}
}
