{
  "type": "Feature",
  "properties": {
    "date:inception_lower": "2012-09-01",
    "date:inception_upper": "2012-09-01",
    "iso:country": "GB",
    "wof:name": "NN13 5GJ",
    "wof:placetype": "postalcode"
  },
  "geometry": {"coordinates":[-1.131926,52.052473],"type":"Point"}
}
