{
  "type": "Feature",
  "properties": {
    "iso:country":"GB",
    "wof:name":"GU51 3RS",
    "wof:placetype":"postalcode"
},
  "geometry": {"coordinates":[-0.83930334695216,51.28065537299434],"type":"Point"}
}