{
  "type": "Feature",
  "properties": {
    "iso:country": "GB",
    "wof:name": "CV7 8AT",
    "wof:placetype": "postalcode"
  },
  "geometry": {"coordinates":[-1.542688,52.472974],"type":"Point"}
}
