{
  "type": "Feature",
  "properties": {
    "date:inception_lower": "1980-01-01",
    "date:inception_upper": "1980-01-01",
    "iso:country": "GB",
    "wof:name": "LS19 7EB",
    "wof:placetype": "postalcode"
  },
  "geometry": {"coordinates":[-1.701604,53.858769],"type":"Point"}
}
