{
  "type": "Feature",
  "properties": {
    "iso:country": "GB",
    "wof:name": "GU33 7JY",
    "wof:placetype": "postalcode"
  },
  "geometry": {"coordinates":[-0.89332,51.0424],"type":"Point"}
}
