{
  "type": "Feature",
  "properties": {
    "iso:country":"GB",
    "wof:name":"GU33 7JY",
    "wof:placetype":"postalcode"
},
  "geometry": {"coordinates":[-0.89330728675365,51.04245846399663],"type":"Point"}
}