{
  "type": "Feature",
  "properties": {
    "date:inception_lower": "1991-09-01",
    "date:inception_upper": "1991-09-01",
    "iso:country": "GB",
    "wof:name": "GU33 7JY",
    "wof:placetype": "postalcode"
  },
  "geometry": {"coordinates":[-0.89332,51.0424],"type":"Point"}
}
