{
  "type": "Feature",
  "properties": {
    "iso:country":"GB",
    "wof:name":"LL11 3PT",
    "wof:placetype":"postalcode"
},
  "geometry": {"coordinates":[-3.07296846641737,53.05768745092804],"type":"Point"}
}