{
  "type": "Feature",
  "properties": {
    "iso:country":"GB",
    "wof:name":"WF2 6QB",
    "wof:placetype":"postalcode"
},
  "geometry": {"coordinates":[-1.49683963107749,53.63898198300507],"type":"Point"}
}