{
  "type": "Feature",
  "properties": {
    "date:inception_lower": "1980-01-01",
    "date:inception_upper": "1980-01-01",
    "iso:country": "GB",
    "wof:name": "DL13 5BQ",
    "wof:placetype": "postalcode"
  },
  "geometry": {"coordinates":[-1.791833,54.630743],"type":"Point"}
}
