{
  "type": "Feature",
  "properties": {
    "iso:country":"GB",
    "wof:name":"N19 3FA",
    "wof:placetype":"postalcode"
},
  "geometry": {"coordinates":[-0.12474866636135,51.56861624353654],"type":"Point"}
}