{
  "type": "Feature",
  "properties": {
    "iso:country": "GB",
    "wof:name": "SW1X 7BA",
    "wof:placetype": "postalcode"
  },
  "geometry": {"coordinates":[-0.150871,51.499474],"type":"Point"}
}
