{
  "type": "Feature",
  "properties": {
    "iso:country": "GB",
    "wof:name": "NR29 4SJ",
    "wof:placetype": "postalcode"
  },
  "geometry": {"coordinates":[1.632961,52.699592],"type":"Point"}
}
