{
  "type": "Feature",
  "properties": {
    "iso:country":"GB",
    "wof:name":"NR29 4SJ",
    "wof:placetype":"postalcode"
},
  "geometry": {"coordinates":[1.6329613491644,52.69959150840548],"type":"Point"}
}