{
  "type": "Feature",
  "properties": {
    "date:inception_lower": "1980-01-01",
    "date:inception_upper": "1980-01-01",
    "iso:country": "GB",
    "wof:name": "NE22 7DR",
    "wof:placetype": "postalcode"
  },
  "geometry": {"coordinates":[-1.567326,55.139914],"type":"Point"}
}
