{
  "type": "Feature",
  "properties": {
    "iso:country": "GB",
    "wof:name": "NE22 7DR",
    "wof:placetype": "postalcode"
  },
  "geometry": {"coordinates":[-1.567326,55.139914],"type":"Point"}
}
