{
  "type": "Feature",
  "properties": {
    "iso:country":"GB",
    "wof:name":"NE22 7DR",
    "wof:placetype":"postalcode"
},
  "geometry": {"coordinates":[-1.56732563350156,55.13991352215633],"type":"Point"}
}