{
  "type": "Feature",
  "properties": {
    "iso:country":"GB",
    "wof:name":"S43 4UD",
    "wof:placetype":"postalcode"
},
  "geometry": {"coordinates":[-1.2629363235592,53.26817388822496],"type":"Point"}
}