{
  "type": "Feature",
  "properties": {
    "date:inception_lower": "1990-07-01",
    "date:inception_upper": "1990-07-01",
    "iso:country": "GB",
    "wof:name": "S43 4UD",
    "wof:placetype": "postalcode"
  },
  "geometry": {"coordinates":[-1.262936,53.268174],"type":"Point"}
}
