{
  "type": "Feature",
  "properties": {
    "iso:country": "GB",
    "wof:name": "DT2 7HL",
    "wof:placetype": "postalcode"
  },
  "geometry": {"coordinates":[-2.265475,50.75862],"type":"Point"}
}
