{
  "type": "Feature",
  "properties": {
    "iso:country":"GB",
    "wof:name":"TA3 6LJ",
    "wof:placetype":"postalcode"
},
  "geometry": {"coordinates":[-2.97107802079719,51.02459529348087],"type":"Point"}
}