{
  "type": "Feature",
  "properties": {
    "date:inception_lower": "2010-08-01",
    "date:inception_upper": "2010-08-01",
    "iso:country": "GB",
    "wof:name": "SG9 9FH",
    "wof:placetype": "postalcode"
  },
  "geometry": {"coordinates":[-0.015995,51.941763],"type":"Point"}
}
