{
  "type": "Feature",
  "properties": {
    "iso:country": "GB",
    "wof:name": "SG9 9FH",
    "wof:placetype": "postalcode"
  },
  "geometry": {"coordinates":[-0.015995,51.941763],"type":"Point"}
}
