{
  "type": "Feature",
  "properties": {
    "date:inception_lower":"1980-01-01",
    "date:inception_upper":"1980-01-31",
    "iso:country":"GB",
    "wof:name":"SK10 3EQ",
    "wof:placetype":"postalcode"
},
  "geometry": {"coordinates":[-2.15785,53.270597],"type":"Point"}
}