{
  "type": "Feature",
  "properties": {
    "iso:country": "GB",
    "wof:name": "SK10 3EQ",
    "wof:placetype": "postalcode"
  },
  "geometry": {"coordinates":[-2.15785,53.270597],"type":"Point"}
}
