{
  "type": "Feature",
  "properties": {
    "iso:country":"GB",
    "wof:name":"IG7 5BE",
    "wof:placetype":"postalcode"
},
  "geometry": {"coordinates":[0.07173399152967,51.61667758347075],"type":"Point"}
}