{
  "type": "Feature",
  "properties": {
    "iso:country":"GB",
    "wof:name":"N11 3AG",
    "wof:placetype":"postalcode"
},
  "geometry": {"coordinates":[-0.14802102536121,51.61766164585917],"type":"Point"}
}