{
  "type": "Feature",
  "properties": {
    "iso:country":"GB",
    "wof:name":"NE12 6QJ",
    "wof:placetype":"postalcode"
},
  "geometry": {"coordinates":[-1.57177225689368,55.03948250902918],"type":"Point"}
}