{
  "type": "Feature",
  "properties": {
    "iso:country": "GB",
    "wof:name": "NE12 6QJ",
    "wof:placetype": "postalcode"
  },
  "geometry": {"coordinates":[-1.571772,55.039483],"type":"Point"}
}
