{
  "type": "Feature",
  "properties": {
    "date:inception_lower": "1980-01-01",
    "date:inception_upper": "1980-01-01",
    "iso:country": "GB",
    "wof:name": "EX23 9BP",
    "wof:placetype": "postalcode"
  },
  "geometry": {"coordinates":[-4.516205,50.830225],"type":"Point"}
}
