{
  "type": "Feature",
  "properties": {
    "iso:country":"GB",
    "wof:name":"EX23 9BP",
    "wof:placetype":"postalcode"
},
  "geometry": {"coordinates":[-4.51620491747635,50.83022480771788],"type":"Point"}
}