{
  "type": "Feature",
  "properties": {
    "date:inception_lower": "1983-03-01",
    "date:inception_upper": "1983-03-01",
    "iso:country": "GB",
    "wof:name": "NN12 8EP",
    "wof:placetype": "postalcode"
  },
  "geometry": {"coordinates":[-1.045694,52.148919],"type":"Point"}
}
