{
  "type": "Feature",
  "properties": {
    "iso:country": "GB",
    "wof:name": "NN12 8EP",
    "wof:placetype": "postalcode"
  },
  "geometry": {"coordinates":[-1.046592,52.151354],"type":"Point"}
}
