{
  "type": "Feature",
  "properties": {
    "iso:country":"GB",
    "wof:name":"TQ13 0LR",
    "wof:placetype":"postalcode"
},
  "geometry": {"coordinates":[-3.59483920094098,50.60330060196507],"type":"Point"}
}