{
  "type": "Feature",
  "properties": {
    "iso:country":"GB",
    "wof:name":"WA9 5HF",
    "wof:placetype":"postalcode"
},
  "geometry": {"coordinates":[-2.74454194226182,53.43283583805303],"type":"Point"}
}