{
  "type": "Feature",
  "properties": {
    "date:inception_lower": "1980-01-01",
    "date:inception_upper": "1980-01-01",
    "iso:country": "GB",
    "wof:name": "DN14 9BL",
    "wof:placetype": "postalcode"
  },
  "geometry": {"coordinates":[-1.045236,53.649277],"type":"Point"}
}
