{
  "type": "Feature",
  "properties": {
    "iso:country":"GB",
    "wof:name":"DN14 9BL",
    "wof:placetype":"postalcode"
},
  "geometry": {"coordinates":[-1.04669163335812,53.64961966095164],"type":"Point"}
}