{
  "type": "Feature",
  "properties": {
    "iso:country":"GB",
    "wof:name":"HU8 9DP",
    "wof:placetype":"postalcode"
},
  "geometry": {"coordinates":[-0.27497691047784,53.77652002638066],"type":"Point"}
}