{
  "type": "Feature",
  "properties": {
    "date:inception_lower":"1980-01-01",
    "date:inception_upper":"1980-01-31",
    "iso:country":"GB",
    "wof:name":"W2 1PN",
    "wof:placetype":"postalcode"
},
  "geometry": {"coordinates":[-0.168583,51.518034],"type":"Point"}
}