{
  "type": "Feature",
  "properties": {
    "iso:country":"GB",
    "wof:name":"ST2 8LW",
    "wof:placetype":"postalcode"
},
  "geometry": {"coordinates":[-2.13399234159058,53.03026194196671],"type":"Point"}
}