{
  "type": "Feature",
  "properties": {
    "iso:country":"GB",
    "wof:name":"SK8 4PL",
    "wof:placetype":"postalcode"
},
  "geometry": {"coordinates":[-2.22984450064927,53.38899563076069],"type":"Point"}
}