{
  "type": "Feature",
  "properties": {
    "date:inception_lower":"1995-12-01",
    "date:inception_upper":"1995-12-31",
    "iso:country":"GB",
    "wof:name":"CW1 6GH",
    "wof:placetype":"postalcode"
},
  "geometry": {"coordinates":[-2.423808,53.082771],"type":"Point"}
}