{
  "type": "Feature",
  "properties": {
    "iso:country":"GB",
    "wof:name":"CW1 6GH",
    "wof:placetype":"postalcode"
},
  "geometry": {"coordinates":[-2.42380821967986,53.08277058309937],"type":"Point"}
}