{
  "type": "Feature",
  "properties": {
    "iso:country":"GB",
    "wof:name":"E14 3GG",
    "wof:placetype":"postalcode"
},
  "geometry": {"coordinates":[-0.00594846964125,51.49340338994927],"type":"Point"}
}