{
  "type": "Feature",
  "properties": {
    "date:inception_lower": "2000-06-01",
    "date:inception_upper": "2000-06-01",
    "iso:country": "GB",
    "wof:name": "SK14 4QX",
    "wof:placetype": "postalcode"
  },
  "geometry": {"coordinates":[-2.088209,53.462953],"type":"Point"}
}
