{
  "type": "Feature",
  "properties": {
    "iso:country":"GB",
    "wof:name":"PA5 0LG",
    "wof:placetype":"postalcode"
},
  "geometry": {"coordinates":[-4.52910763855879,55.82629431250066],"type":"Point"}
}