{
  "type": "Feature",
  "properties": {
    "iso:country":"GB",
    "wof:name":"SY25 6HN",
    "wof:placetype":"postalcode"
},
  "geometry": {"coordinates":[-3.88893222054112,52.23160297617023],"type":"Point"}
}