{
  "type": "Feature",
  "properties": {
    "iso:country": "GB",
    "wof:name": "SY25 6HN",
    "wof:placetype": "postalcode"
  },
  "geometry": {"coordinates":[-3.888932,52.231603],"type":"Point"}
}
