{
  "type": "Feature",
  "properties": {
    "iso:country":"GB",
    "wof:name":"B98 7PH",
    "wof:placetype":"postalcode"
},
  "geometry": {"coordinates":[-1.92585281555892,52.29338556354237],"type":"Point"}
}