{
  "type": "Feature",
  "properties": {
    "iso:country":"GB",
    "wof:name":"PA15 1RJ",
    "wof:placetype":"postalcode"
},
  "geometry": {"coordinates":[-4.76096365310075,55.94894514406521],"type":"Point"}
}