{
  "type": "Feature",
  "properties": {
    "iso:country": "GB",
    "wof:name": "PR9 8DG",
    "wof:placetype": "postalcode"
  },
  "geometry": {"coordinates":[-2.913599,53.67432],"type":"Point"}
}
