{
  "type": "Feature",
  "properties": {
    "iso:country":"GB",
    "wof:name":"PR9 8DG",
    "wof:placetype":"postalcode"
},
  "geometry": {"coordinates":[-2.91359951843289,53.67431994099672],"type":"Point"}
}