{
  "type": "Feature",
  "properties": {
    "date:inception_lower": "1997-06-01",
    "date:inception_upper": "1997-06-01",
    "iso:country": "GB",
    "wof:name": "PR9 8DG",
    "wof:placetype": "postalcode"
  },
  "geometry": {"coordinates":[-2.913599,53.67432],"type":"Point"}
}
