{
  "type": "Feature",
  "properties": {
    "iso:country":"GB",
    "wof:name":"PE1 4JA",
    "wof:placetype":"postalcode"
},
  "geometry": {"coordinates":[-0.23295093556431,52.59670564655857],"type":"Point"}
}