{
  "type": "Feature",
  "properties": {
    "date:inception_lower": "1980-01-01",
    "date:inception_upper": "1980-01-01",
    "iso:country": "GB",
    "wof:name": "NG9 3HX",
    "wof:placetype": "postalcode"
  },
  "geometry": {"coordinates":[-1.254405,52.934648],"type":"Point"}
}
