{
  "type": "Feature",
  "properties": {
    "iso:country":"GB",
    "wof:name":"NG9 3HX",
    "wof:placetype":"postalcode"
},
  "geometry": {"coordinates":[-1.25440479613458,52.93464770867522],"type":"Point"}
}