{
  "type": "Feature",
  "properties": {
    "iso:country":"GB",
    "wof:name":"IV2 4AN",
    "wof:placetype":"postalcode"
},
  "geometry": {"coordinates":[-4.21968482015957,57.46986963675234],"type":"Point"}
}