{
  "type": "Feature",
  "properties": {
    "iso:country": "GB",
    "wof:name": "HR3 6EG",
    "wof:placetype": "postalcode"
  },
  "geometry": {"coordinates":[-3.067862,52.120847],"type":"Point"}
}
