{
  "type": "Feature",
  "properties": {
    "iso:country":"GB",
    "wof:name":"HR3 6EG",
    "wof:placetype":"postalcode"
},
  "geometry": {"coordinates":[-3.06786237039924,52.12084678628898],"type":"Point"}
}