{
  "type": "Feature",
  "properties": {
    "iso:country":"GB",
    "wof:name":"LS13 2UQ",
    "wof:placetype":"postalcode"
},
  "geometry": {"coordinates":[-1.62487186885133,53.80925496241107],"type":"Point"}
}