{
  "type": "Feature",
  "properties": {
    "iso:country":"GB",
    "wof:name":"PE23 5DF",
    "wof:placetype":"postalcode"
},
  "geometry": {"coordinates":[0.08182658829968,53.13278404141959],"type":"Point"}
}