{
  "type": "Feature",
  "properties": {
    "date:inception_lower": "1980-01-01",
    "date:inception_upper": "1980-01-01",
    "iso:country": "GB",
    "wof:name": "PE23 5DF",
    "wof:placetype": "postalcode"
  },
  "geometry": {"coordinates":[0.081827,53.132784],"type":"Point"}
}
