{
  "type": "Feature",
  "properties": {
    "iso:country":"GB",
    "wof:name":"PE14 8JD",
    "wof:placetype":"postalcode"
},
  "geometry": {"coordinates":[0.2572518987289,52.66589182355494],"type":"Point"}
}