{
  "type": "Feature",
  "properties": {
    "iso:country": "GB",
    "wof:name": "SE19 3BS",
    "wof:placetype": "postalcode"
  },
  "geometry": {"coordinates":[-0.089456,51.410056],"type":"Point"}
}
