{
  "type": "Feature",
  "properties": {
    "date:inception_lower":"2007-01-01",
    "date:inception_upper":"2007-01-31",
    "iso:country":"GB",
    "wof:name":"PL1 4FF",
    "wof:placetype":"postalcode"
},
  "geometry": {"coordinates":[-4.177149,50.368643],"type":"Point"}
}