{
  "type": "Feature",
  "properties": {
    "iso:country":"GB",
    "wof:name":"YO31 9HB",
    "wof:placetype":"postalcode"
},
  "geometry": {"coordinates":[-1.0618335530885,53.983717149031],"type":"Point"}
}