{
  "type": "Feature",
  "properties": {
    "iso:country": "GB",
    "wof:name": "YO31 9HB",
    "wof:placetype": "postalcode"
  },
  "geometry": {"coordinates":[-1.061834,53.983717],"type":"Point"}
}
