{
  "type": "Feature",
  "properties": {
    "date:inception_lower":"1980-01-01",
    "date:inception_upper":"1980-01-31",
    "iso:country":"GB",
    "wof:name":"SR7 8BW",
    "wof:placetype":"postalcode"
},
  "geometry": {"coordinates":[-1.360327,54.834608],"type":"Point"}
}