{
  "type": "Feature",
  "properties": {
    "iso:country": "GB",
    "wof:name": "DL6 2JN",
    "wof:placetype": "postalcode"
  },
  "geometry": {"coordinates":[-1.423827,54.434367],"type":"Point"}
}
