{
  "type": "Feature",
  "properties": {
    "iso:country":"GB",
    "wof:name":"N21 2EU",
    "wof:placetype":"postalcode"
},
  "geometry": {"coordinates":[-0.09401709273767,51.6402584056706],"type":"Point"}
}