{
  "type": "Feature",
  "properties": {
    "iso:country":"GB",
    "wof:name":"IP14 1QT",
    "wof:placetype":"postalcode"
},
  "geometry": {"coordinates":[0.99016155640804,52.18585143305875],"type":"Point"}
}