{
  "type": "Feature",
  "properties": {
    "iso:country": "GB",
    "wof:name": "WF10 2EA",
    "wof:placetype": "postalcode"
  },
  "geometry": {"coordinates":[-1.379917,53.751074],"type":"Point"}
}
