{
  "type": "Feature",
  "properties": {
    "iso:country": "GB",
    "wof:name": "WF10 2EA",
    "wof:placetype": "postalcode"
  },
  "geometry": {"coordinates":[-1.379765,53.751082],"type":"Point"}
}
