{
  "type": "Feature",
  "properties": {
    "date:inception_lower":"1984-02-01",
    "date:inception_upper":"1984-02-29",
    "iso:country":"GB",
    "wof:name":"RM11 2SJ",
    "wof:placetype":"postalcode"
},
  "geometry": {"coordinates":[0.219613,51.586816],"type":"Point"}
}