{
  "type": "Feature",
  "properties": {
    "iso:country": "GB",
    "wof:name": "SG12 0GN",
    "wof:placetype": "postalcode"
  },
  "geometry": {"coordinates":[-0.046274,51.813734],"type":"Point"}
}
