{
  "type": "Feature",
  "properties": {
    "iso:country":"GB",
    "wof:name":"DN40 1NL",
    "wof:placetype":"postalcode"
},
  "geometry": {"coordinates":[-0.22354161399585,53.61148760273328],"type":"Point"}
}