{
  "type": "Feature",
  "properties": {
    "iso:country":"GB",
    "wof:name":"TN38 0HW",
    "wof:placetype":"postalcode"
},
  "geometry": {"coordinates":[0.55453844981238,50.85438908670026],"type":"Point"}
}