{
  "type": "Feature",
  "properties": {
    "iso:country": "GB",
    "wof:name": "B23 7SE",
    "wof:placetype": "postalcode"
  },
  "geometry": {"coordinates":[-1.861725,52.517963],"type":"Point"}
}
