{
  "type": "Feature",
  "properties": {
    "date:inception_lower": "1980-01-01",
    "date:inception_upper": "1980-01-01",
    "iso:country": "GB",
    "wof:name": "B23 7SE",
    "wof:placetype": "postalcode"
  },
  "geometry": {"coordinates":[-1.861725,52.517963],"type":"Point"}
}
