{
  "type": "Feature",
  "properties": {
    "iso:country":"GB",
    "wof:name":"B23 7SE",
    "wof:placetype":"postalcode"
},
  "geometry": {"coordinates":[-1.861725316388,52.51796312632486],"type":"Point"}
}