{
  "type": "Feature",
  "properties": {
    "iso:country":"GB",
    "wof:name":"TQ6 9JE",
    "wof:placetype":"postalcode"
},
  "geometry": {"coordinates":[-3.59000647965702,50.35343170713688],"type":"Point"}
}