{
  "type": "Feature",
  "properties": {
    "iso:country":"GB",
    "wof:name":"TS17 8JB",
    "wof:placetype":"postalcode"
},
  "geometry": {"coordinates":[-1.29503545425596,54.54523905833815],"type":"Point"}
}