{
  "type": "Feature",
  "properties": {
    "iso:country": "GB",
    "wof:name": "M23 2GH",
    "wof:placetype": "postalcode"
  },
  "geometry": {"coordinates":[-2.28325,53.390948],"type":"Point"}
}
