{
  "type": "Feature",
  "properties": {
    "iso:country":"GB",
    "wof:name":"NR27 9HG",
    "wof:placetype":"postalcode"
},
  "geometry": {"coordinates":[1.30049839361069,52.93176728215608],"type":"Point"}
}