{
  "type": "Feature",
  "properties": {
    "date:inception_lower": "1980-01-01",
    "date:inception_upper": "1980-01-01",
    "iso:country": "GB",
    "wof:name": "S42 6NQ",
    "wof:placetype": "postalcode"
  },
  "geometry": {"coordinates":[-1.413657,53.197585],"type":"Point"}
}
