{
  "type": "Feature",
  "properties": {
    "iso:country":"GB",
    "wof:name":"S42 6NQ",
    "wof:placetype":"postalcode"
},
  "geometry": {"coordinates":[-1.41364366214203,53.19758372557603],"type":"Point"}
}