{
  "type": "Feature",
  "properties": {
    "date:inception_lower":"1985-10-01",
    "date:inception_upper":"1985-10-31",
    "iso:country":"GB",
    "wof:name":"ME16 0TY",
    "wof:placetype":"postalcode"
},
  "geometry": {"coordinates":[0.498854,51.286017],"type":"Point"}
}