{
  "type": "Feature",
  "properties": {
    "iso:country":"GB",
    "wof:name":"BH21 2EH",
    "wof:placetype":"postalcode"
},
  "geometry": {"coordinates":[-1.93775166404633,50.80181028035872],"type":"Point"}
}