{
  "type": "Feature",
  "properties": {
    "iso:country":"GB",
    "wof:name":"NG33 5BF",
    "wof:placetype":"postalcode"
},
  "geometry": {"coordinates":[-0.6513990751997,52.79442161649735],"type":"Point"}
}