{
  "type": "Feature",
  "properties": {
    "iso:country":"GB",
    "wof:name":"SG1 3TR",
    "wof:placetype":"postalcode"
},
  "geometry": {"coordinates":[-0.19324982871939,51.90620362126094],"type":"Point"}
}