{
  "type": "Feature",
  "properties": {
    "iso:country": "GB",
    "wof:name": "SG1 3TR",
    "wof:placetype": "postalcode"
  },
  "geometry": {"coordinates":[-0.193197,51.90621],"type":"Point"}
}
