{
  "type": "Feature",
  "properties": {
    "iso:country":"GB",
    "wof:name":"FY4 3BU",
    "wof:placetype":"postalcode"
},
  "geometry": {"coordinates":[-3.03951783475281,53.79597682406823],"type":"Point"}
}