{
  "type": "Feature",
  "properties": {
    "iso:country":"GB",
    "wof:name":"DD4 8SF",
    "wof:placetype":"postalcode"
},
  "geometry": {"coordinates":[-2.90226558250756,56.47929519647498],"type":"Point"}
}