{
  "type": "Feature",
  "properties": {
    "date:inception_lower":"1980-01-01",
    "date:inception_upper":"1980-01-31",
    "iso:country":"GB",
    "wof:name":"BL1 5PP",
    "wof:placetype":"postalcode"
},
  "geometry": {"coordinates":[-2.471702,53.588908],"type":"Point"}
}