{
  "type": "Feature",
  "properties": {
    "iso:country": "GB",
    "wof:name": "BL1 5PP",
    "wof:placetype": "postalcode"
  },
  "geometry": {"coordinates":[-2.471702,53.588908],"type":"Point"}
}
