{
  "type": "Feature",
  "properties": {
    "iso:country":"GB",
    "wof:name":"BL1 5PP",
    "wof:placetype":"postalcode"
},
  "geometry": {"coordinates":[-2.47170166952215,53.58890813943861],"type":"Point"}
}