{
  "type": "Feature",
  "properties": {
    "date:inception_lower": "1991-01-01",
    "date:inception_upper": "1991-01-01",
    "iso:country": "GB",
    "wof:name": "WV9 5RS",
    "wof:placetype": "postalcode"
  },
  "geometry": {"coordinates":[-2.14636,52.626712],"type":"Point"}
}
