{
  "type": "Feature",
  "properties": {
    "iso:country":"GB",
    "wof:name":"WV9 5RS",
    "wof:placetype":"postalcode"
},
  "geometry": {"coordinates":[-2.14636027376701,52.62671166360128],"type":"Point"}
}