{
  "type": "Feature",
  "properties": {
    "iso:country":"GB",
    "wof:name":"PE19 6ES",
    "wof:placetype":"postalcode"
},
  "geometry": {"coordinates":[-0.26082831552176,52.24839837889308],"type":"Point"}
}