{
  "type": "Feature",
  "properties": {
    "date:inception_lower": "2007-11-01",
    "date:inception_upper": "2007-11-01",
    "iso:country": "GB",
    "wof:name": "BD8 0DZ",
    "wof:placetype": "postalcode"
  },
  "geometry": {"coordinates":[-1.808028,53.799504],"type":"Point"}
}
