{
  "type": "Feature",
  "properties": {
    "iso:country": "GB",
    "wof:name": "BD8 0DZ",
    "wof:placetype": "postalcode"
  },
  "geometry": {"coordinates":[-1.808028,53.799504],"type":"Point"}
}
