{
  "type": "Feature",
  "properties": {
    "date:inception_lower":"1980-01-01",
    "date:inception_upper":"1980-01-31",
    "iso:country":"GB",
    "wof:name":"NE31 1ND",
    "wof:placetype":"postalcode"
},
  "geometry": {"coordinates":[-1.522997,54.972327],"type":"Point"}
}