{
  "type": "Feature",
  "properties": {
    "iso:country":"GB",
    "wof:name":"S61 2EW",
    "wof:placetype":"postalcode"
},
  "geometry": {"coordinates":[-1.40126320635922,53.4315912237534],"type":"Point"}
}