{
  "type": "Feature",
  "properties": {
    "iso:country":"GB",
    "wof:name":"BA12 9AG",
    "wof:placetype":"postalcode"
},
  "geometry": {"coordinates":[-2.18242374110353,51.20488682325802],"type":"Point"}
}