{
  "type": "Feature",
  "properties": {
    "iso:country":"GB",
    "wof:name":"BS4 4ER",
    "wof:placetype":"postalcode"
},
  "geometry": {"coordinates":[-2.54959745045387,51.44661573662086],"type":"Point"}
}