{
  "type": "Feature",
  "properties": {
    "iso:country": "GB",
    "wof:name": "BS4 4ER",
    "wof:placetype": "postalcode"
  },
  "geometry": {"coordinates":[-2.549597,51.446616],"type":"Point"}
}
