{
  "type": "Feature",
  "properties": {
    "iso:country":"GB",
    "wof:name":"SY13 3PG",
    "wof:placetype":"postalcode"
},
  "geometry": {"coordinates":[-2.68314310153473,52.93656614742747],"type":"Point"}
}