{
  "type": "Feature",
  "properties": {
    "date:inception_lower": "2012-07-01",
    "date:inception_upper": "2012-07-01",
    "iso:country": "GB",
    "wof:name": "AL1 5FT",
    "wof:placetype": "postalcode"
  },
  "geometry": {"coordinates":[-0.316215,51.747348],"type":"Point"}
}
