{
  "type": "Feature",
  "properties": {
    "iso:country": "GB",
    "wof:name": "AL1 5FT",
    "wof:placetype": "postalcode"
  },
  "geometry": {"coordinates":[-0.31617,51.747393],"type":"Point"}
}
