{
  "type": "Feature",
  "properties": {
    "iso:country":"GB",
    "wof:name":"EH19 3HH",
    "wof:placetype":"postalcode"
},
  "geometry": {"coordinates":[-3.10960883535319,55.87337880921002],"type":"Point"}
}