{
  "type": "Feature",
  "properties": {
    "date:inception_lower":"1980-01-01",
    "date:inception_upper":"1980-01-31",
    "iso:country":"GB",
    "wof:name":"CF40 1TR",
    "wof:placetype":"postalcode"
},
  "geometry": {"coordinates":[-3.438785,51.61422],"type":"Point"}
}