{
  "type": "Feature",
  "properties": {
    "iso:country":"GB",
    "wof:name":"CF40 1TR",
    "wof:placetype":"postalcode"
},
  "geometry": {"coordinates":[-3.43878457163694,51.61422027251634],"type":"Point"}
}