{
  "type": "Feature",
  "properties": {
    "iso:country":"GB",
    "wof:name":"NR7 0EL",
    "wof:placetype":"postalcode"
},
  "geometry": {"coordinates":[1.33377700487516,52.62790657743592],"type":"Point"}
}