{
  "type": "Feature",
  "properties": {
    "iso:country": "GB",
    "wof:name": "NR7 0EL",
    "wof:placetype": "postalcode"
  },
  "geometry": {"coordinates":[1.333777,52.627907],"type":"Point"}
}
