{
  "type": "Feature",
  "properties": {
    "iso:country":"GB",
    "wof:name":"PE7 0LS",
    "wof:placetype":"postalcode"
},
  "geometry": {"coordinates":[-0.24758510902772,52.54928025991548],"type":"Point"}
}