{
  "type": "Feature",
  "properties": {
    "date:inception_lower": "2013-02-01",
    "date:inception_upper": "2013-02-01",
    "iso:country": "GB",
    "wof:name": "PE7 0LS",
    "wof:placetype": "postalcode"
  },
  "geometry": {"coordinates":[-0.247585,52.54928],"type":"Point"}
}
