{
  "type": "Feature",
  "properties": {
    "iso:country":"GB",
    "wof:name":"UB7 8DG",
    "wof:placetype":"postalcode"
},
  "geometry": {"coordinates":[-0.46363705259024,51.51973341189687],"type":"Point"}
}