{
  "type": "Feature",
  "properties": {
    "date:inception_lower":"2019-01-01",
    "date:inception_upper":"2019-01-31",
    "iso:country":"GB",
    "wof:name":"M7 4AT",
    "wof:placetype":"postalcode"
},
  "geometry": {"coordinates":[-2.254615,53.503789],"type":"Point"}
}