{
  "type": "Feature",
  "properties": {
    "iso:country":"GB",
    "wof:name":"E13 8LH",
    "wof:placetype":"postalcode"
},
  "geometry": {"coordinates":[0.02625796331724,51.52218552164685],"type":"Point"}
}