{
  "type": "Feature",
  "properties": {
    "date:inception_lower": "1998-06-01",
    "date:inception_upper": "1998-06-01",
    "iso:country": "GB",
    "wof:name": "YO61 1JS",
    "wof:placetype": "postalcode"
  },
  "geometry": {"coordinates":[-1.109788,54.102686],"type":"Point"}
}
