{
  "type": "Feature",
  "properties": {
    "iso:country":"GB",
    "wof:name":"YO61 1JS",
    "wof:placetype":"postalcode"
},
  "geometry": {"coordinates":[-1.10971078042762,54.10270384501299],"type":"Point"}
}