{
  "type": "Feature",
  "properties": {
    "iso:country":"GB",
    "wof:name":"CM9 8SX",
    "wof:placetype":"postalcode"
},
  "geometry": {"coordinates":[0.845347608771,51.75567422698689],"type":"Point"}
}