{
  "type": "Feature",
  "properties": {
    "iso:country":"GB",
    "wof:name":"DL6 3JW",
    "wof:placetype":"postalcode"
},
  "geometry": {"coordinates":[-1.31593396305087,54.39540836020698],"type":"Point"}
}