{
  "type": "Feature",
  "properties": {
    "iso:country":"GB",
    "wof:name":"EH11 3DA",
    "wof:placetype":"postalcode"
},
  "geometry": {"coordinates":[-3.26082260175302,55.93460622637365],"type":"Point"}
}