{
  "type": "Feature",
  "properties": {
    "iso:country": "GB",
    "wof:name": "PE1 4FU",
    "wof:placetype": "postalcode"
  },
  "geometry": {"coordinates":[-0.226188,52.602243],"type":"Point"}
}
