{
  "type": "Feature",
  "properties": {
    "iso:country":"GB",
    "wof:name":"TR7 1PQ",
    "wof:placetype":"postalcode"
},
  "geometry": {"coordinates":[-5.10812640475401,50.41047843358357],"type":"Point"}
}