{
  "type": "Feature",
  "properties": {
    "date:inception_lower":"1980-01-01",
    "date:inception_upper":"1980-01-31",
    "iso:country":"GB",
    "wof:name":"TR7 1PQ",
    "wof:placetype":"postalcode"
},
  "geometry": {"coordinates":[-5.108116,50.410542],"type":"Point"}
}