{
  "type": "Feature",
  "properties": {
    "iso:country":"GB",
    "wof:name":"YO41 1DB",
    "wof:placetype":"postalcode"
},
  "geometry": {"coordinates":[-0.90861695264449,53.98722336757744],"type":"Point"}
}