{
  "type": "Feature",
  "properties": {
    "iso:country": "GB",
    "wof:name": "YO41 1DB",
    "wof:placetype": "postalcode"
  },
  "geometry": {"coordinates":[-0.908617,53.987223],"type":"Point"}
}
