{
  "type": "Feature",
  "properties": {
    "iso:country":"GB",
    "wof:name":"BN25 2HZ",
    "wof:placetype":"postalcode"
},
  "geometry": {"coordinates":[0.10555080286471,50.7854525233926],"type":"Point"}
}