{
  "type": "Feature",
  "properties": {
    "iso:country":"GB",
    "wof:name":"B35 7LW",
    "wof:placetype":"postalcode"
},
  "geometry": {"coordinates":[-1.7836318084979,52.51560781362373],"type":"Point"}
}