{
  "type": "Feature",
  "properties": {
    "date:inception_lower": "2003-10-01",
    "date:inception_upper": "2003-10-01",
    "iso:country": "GB",
    "wof:name": "B35 7LW",
    "wof:placetype": "postalcode"
  },
  "geometry": {"coordinates":[-1.783632,52.515608],"type":"Point"}
}
