{
  "type": "Feature",
  "properties": {
    "iso:country":"GB",
    "wof:name":"M18 7EG",
    "wof:placetype":"postalcode"
},
  "geometry": {"coordinates":[-2.17029940877437,53.4597004523017],"type":"Point"}
}