{
  "type": "Feature",
  "properties": {
    "iso:country":"GB",
    "wof:name":"CR8 5DX",
    "wof:placetype":"postalcode"
},
  "geometry": {"coordinates":[-0.09727350494334,51.31972494874857],"type":"Point"}
}