{
  "type": "Feature",
  "properties": {
    "iso:country":"GB",
    "wof:name":"GL7 1JN",
    "wof:placetype":"postalcode"
},
  "geometry": {"coordinates":[-1.96699456514801,51.71470051358752],"type":"Point"}
}