{
  "type": "Feature",
  "properties": {
    "iso:country":"GB",
    "wof:name":"HP15 6JS",
    "wof:placetype":"postalcode"
},
  "geometry": {"coordinates":[-0.74529782682303,51.660874318895],"type":"Point"}
}