{
  "type": "Feature",
  "properties": {
    "iso:country":"GB",
    "wof:name":"YO12 6NN",
    "wof:placetype":"postalcode"
},
  "geometry": {"coordinates":[-0.4318211546977,54.28894129703018],"type":"Point"}
}