{
  "type": "Feature",
  "properties": {
    "iso:country": "GB",
    "wof:name": "YO12 6NN",
    "wof:placetype": "postalcode"
  },
  "geometry": {"coordinates":[-0.431821,54.288941],"type":"Point"}
}
