{
  "type": "Feature",
  "properties": {
    "date:inception_lower":"2002-09-01",
    "date:inception_upper":"2002-09-30",
    "iso:country":"GB",
    "wof:name":"TQ1 4GF",
    "wof:placetype":"postalcode"
},
  "geometry": {"coordinates":[-3.522354,50.484382],"type":"Point"}
}