{
  "type": "Feature",
  "properties": {
    "date:inception_lower": "2002-09-01",
    "date:inception_upper": "2002-09-01",
    "iso:country": "GB",
    "wof:name": "TQ1 4GF",
    "wof:placetype": "postalcode"
  },
  "geometry": {"coordinates":[-3.522324,50.484347],"type":"Point"}
}
