{
  "type": "Feature",
  "properties": {
    "iso:country":"GB",
    "wof:name":"BA5 2HE",
    "wof:placetype":"postalcode"
},
  "geometry": {"coordinates":[-2.65692501905208,51.2053601070893],"type":"Point"}
}