{
  "type": "Feature",
  "properties": {
    "iso:country": "GB",
    "wof:name": "BA5 2HE",
    "wof:placetype": "postalcode"
  },
  "geometry": {"coordinates":[-2.656925,51.20536],"type":"Point"}
}
