{
  "type": "Feature",
  "properties": {
    "date:inception_lower": "1985-10-01",
    "date:inception_upper": "1985-10-01",
    "iso:country": "GB",
    "wof:name": "BA5 2HE",
    "wof:placetype": "postalcode"
  },
  "geometry": {"coordinates":[-2.656925,51.20536],"type":"Point"}
}
