{
  "type": "Feature",
  "properties": {
    "iso:country":"GB",
    "wof:name":"DD3 8JE",
    "wof:placetype":"postalcode"
},
  "geometry": {"coordinates":[-2.97770745720441,56.48033221242461],"type":"Point"}
}