{
  "type": "Feature",
  "properties": {
    "iso:country":"GB",
    "wof:name":"SS0 7FL",
    "wof:placetype":"postalcode"
},
  "geometry": {"coordinates":[0.70201403897399,51.5442481931314],"type":"Point"}
}