{
  "type": "Feature",
  "properties": {
    "iso:country": "GB",
    "wof:name": "SS0 7FL",
    "wof:placetype": "postalcode"
  },
  "geometry": {"coordinates":[0.702014,51.544248],"type":"Point"}
}
