{
  "type": "Feature",
  "properties": {
    "iso:country":"GB",
    "wof:name":"ME14 1DS",
    "wof:placetype":"postalcode"
},
  "geometry": {"coordinates":[0.52364583005866,51.27545735816499],"type":"Point"}
}