{
  "type": "Feature",
  "properties": {
    "iso:country":"GB",
    "wof:name":"G53 6EQ",
    "wof:placetype":"postalcode"
},
  "geometry": {"coordinates":[-4.34645200934607,55.82274385018805],"type":"Point"}
}