{
  "type": "Feature",
  "properties": {
    "iso:country": "GB",
    "wof:name": "HX7 6PU",
    "wof:placetype": "postalcode"
  },
  "geometry": {"coordinates":[-2.046347,53.732562],"type":"Point"}
}
