{
  "type": "Feature",
  "properties": {
    "iso:country":"GB",
    "wof:name":"HX7 6PU",
    "wof:placetype":"postalcode"
},
  "geometry": {"coordinates":[-2.04634676390589,53.73256186646882],"type":"Point"}
}