{
  "type": "Feature",
  "properties": {
    "iso:country": "GB",
    "wof:name": "LA7 7EZ",
    "wof:placetype": "postalcode"
  },
  "geometry": {"coordinates":[-2.793957,54.251941],"type":"Point"}
}
