{
  "type": "Feature",
  "properties": {
    "iso:country":"GB",
    "wof:name":"B76 2BG",
    "wof:placetype":"postalcode"
},
  "geometry": {"coordinates":[-1.79070574639395,52.54651878816733],"type":"Point"}
}