{
  "type": "Feature",
  "properties": {
    "date:inception_lower":"1997-12-01",
    "date:inception_upper":"1997-12-31",
    "iso:country":"GB",
    "wof:name":"WF15 7QX",
    "wof:placetype":"postalcode"
},
  "geometry": {"coordinates":[-1.692861,53.704926],"type":"Point"}
}