{
  "type": "Feature",
  "properties": {
    "iso:country":"GB",
    "wof:name":"E14 6QR",
    "wof:placetype":"postalcode"
},
  "geometry": {"coordinates":[-0.01071500862522,51.51825915549323],"type":"Point"}
}