{
  "type": "Feature",
  "properties": {
    "iso:country":"GB",
    "wof:name":"RG20 8BE",
    "wof:placetype":"postalcode"
},
  "geometry": {"coordinates":[-1.35254019195519,51.4213287646816],"type":"Point"}
}