{
  "type": "Feature",
  "properties": {
    "iso:country":"GB",
    "wof:name":"IG10 4EL",
    "wof:placetype":"postalcode"
},
  "geometry": {"coordinates":[0.04703264472913,51.64523973595588],"type":"Point"}
}