{
  "type": "Feature",
  "properties": {
    "iso:country": "GB",
    "wof:name": "WA16 8AW",
    "wof:placetype": "postalcode"
  },
  "geometry": {"coordinates":[-2.357363,53.302633],"type":"Point"}
}
