{
  "type": "Feature",
  "properties": {
    "iso:country": "GB",
    "wof:name": "CF48 1JE",
    "wof:placetype": "postalcode"
  },
  "geometry": {"coordinates":[-3.418934,51.753296],"type":"Point"}
}
