{
  "type": "Feature",
  "properties": {
    "iso:country":"GB",
    "wof:name":"CF48 1JE",
    "wof:placetype":"postalcode"
},
  "geometry": {"coordinates":[-3.41893437725513,51.75329557238695],"type":"Point"}
}