{
  "type": "Feature",
  "properties": {
    "iso:country": "GB",
    "wof:name": "DD10 8NU",
    "wof:placetype": "postalcode"
  },
  "geometry": {"coordinates":[-2.464042,56.717184],"type":"Point"}
}
