{
  "type": "Feature",
  "properties": {
    "iso:country": "GB",
    "wof:name": "NG3 2HN",
    "wof:placetype": "postalcode"
  },
  "geometry": {"coordinates":[-1.126449,52.96283],"type":"Point"}
}
