{
  "type": "Feature",
  "properties": {
    "date:inception_lower": "1980-01-01",
    "date:inception_upper": "1980-01-01",
    "iso:country": "GB",
    "wof:name": "NG3 2HN",
    "wof:placetype": "postalcode"
  },
  "geometry": {"coordinates":[-1.126449,52.96283],"type":"Point"}
}
