{
  "type": "Feature",
  "properties": {
    "iso:country":"GB",
    "wof:name":"NG3 2HN",
    "wof:placetype":"postalcode"
},
  "geometry": {"coordinates":[-1.12644904003396,52.96283042410841],"type":"Point"}
}