{
  "type": "Feature",
  "properties": {
    "iso:country":"GB",
    "wof:name":"AL9 7TP",
    "wof:placetype":"postalcode"
},
  "geometry": {"coordinates":[-0.22544052459807,51.72327480813651],"type":"Point"}
}