{
  "type": "Feature",
  "properties": {
    "iso:country": "GB",
    "wof:name": "AL9 7TP",
    "wof:placetype": "postalcode"
  },
  "geometry": {"coordinates":[-0.22544,51.723275],"type":"Point"}
}
