{
  "type": "Feature",
  "properties": {
    "iso:country":"GB",
    "wof:name":"LN4 1NW",
    "wof:placetype":"postalcode"
},
  "geometry": {"coordinates":[-0.46599654639621,53.19668647217856],"type":"Point"}
}