{
  "type": "Feature",
  "properties": {
    "iso:country": "GB",
    "wof:name": "LN4 1NW",
    "wof:placetype": "postalcode"
  },
  "geometry": {"coordinates":[-0.465997,53.196686],"type":"Point"}
}
