{
  "type": "Feature",
  "properties": {
    "iso:country":"GB",
    "wof:name":"HR6 8FB",
    "wof:placetype":"postalcode"
},
  "geometry": {"coordinates":[-2.73939548554105,52.23137779001824],"type":"Point"}
}