{
  "type": "Feature",
  "properties": {
    "date:inception_lower":"1999-12-01",
    "date:inception_upper":"1999-12-31",
    "iso:country":"GB",
    "wof:name":"HR6 8FB",
    "wof:placetype":"postalcode"
},
  "geometry": {"coordinates":[-2.739395,52.231378],"type":"Point"}
}