{
  "type": "Feature",
  "properties": {
    "iso:country": "GB",
    "wof:name": "HR6 8FB",
    "wof:placetype": "postalcode"
  },
  "geometry": {"coordinates":[-2.739395,52.231378],"type":"Point"}
}
