{
  "type": "Feature",
  "properties": {
    "iso:country": "GB",
    "wof:name": "SW10 9LN",
    "wof:placetype": "postalcode"
  },
  "geometry": {"coordinates":[-0.186869,51.48947],"type":"Point"}
}
