{
  "type": "Feature",
  "properties": {
    "iso:country":"GB",
    "wof:name":"SW10 9LN",
    "wof:placetype":"postalcode"
},
  "geometry": {"coordinates":[-0.18686921792912,51.48946997909268],"type":"Point"}
}