{
  "type": "Feature",
  "properties": {
    "iso:country":"GB",
    "wof:name":"SE14 6HW",
    "wof:placetype":"postalcode"
},
  "geometry": {"coordinates":[-0.04051422483869,51.48184599335701],"type":"Point"}
}