{
  "type": "Feature",
  "properties": {
    "date:inception_lower":"2006-10-01",
    "date:inception_upper":"2006-10-31",
    "iso:country":"GB",
    "wof:name":"NR27 9GY",
    "wof:placetype":"postalcode"
},
  "geometry": {"coordinates":[1.298836,52.931831],"type":"Point"}
}