{
  "type": "Feature",
  "properties": {
    "iso:country":"GB",
    "wof:name":"GU5 0HP",
    "wof:placetype":"postalcode"
},
  "geometry": {"coordinates":[-0.55621466803236,51.1912331743758],"type":"Point"}
}