{
  "type": "Feature",
  "properties": {
    "iso:country": "GB",
    "wof:name": "AB23 8FB",
    "wof:placetype": "postalcode"
  },
  "geometry": {"coordinates":[-2.08817,57.18311],"type":"Point"}
}
