{
  "type": "Feature",
  "properties": {
    "iso:country":"GB",
    "wof:name":"M24 6JB",
    "wof:placetype":"postalcode"
},
  "geometry": {"coordinates":[-2.1957936605428,53.56669521886663],"type":"Point"}
}