{
  "type": "Feature",
  "properties": {
    "iso:country":"GB",
    "wof:name":"NP4 8DE",
    "wof:placetype":"postalcode"
},
  "geometry": {"coordinates":[-3.04052850231199,51.70495240551842],"type":"Point"}
}