{
  "type": "Feature",
  "properties": {
    "date:inception_lower": "1980-01-01",
    "date:inception_upper": "1980-01-01",
    "iso:country": "GB",
    "wof:name": "NP4 8DE",
    "wof:placetype": "postalcode"
  },
  "geometry": {"coordinates":[-3.040533,51.704874],"type":"Point"}
}
