{
  "type": "Feature",
  "properties": {
    "date:inception_lower": "1980-01-01",
    "date:inception_upper": "1980-01-01",
    "iso:country": "GB",
    "wof:name": "NP4 8DE",
    "wof:placetype": "postalcode"
  },
  "geometry": {"coordinates":[-3.040535,51.704955],"type":"Point"}
}
