{
  "type": "Feature",
  "properties": {
    "date:inception_lower": "2011-01-01",
    "date:inception_upper": "2011-01-01",
    "iso:country": "GB",
    "wof:name": "SL2 5GE",
    "wof:placetype": "postalcode"
  },
  "geometry": {"coordinates":[-0.591464,51.512921],"type":"Point"}
}
