{
  "type": "Feature",
  "properties": {
    "iso:country": "GB",
    "wof:name": "SL2 5GE",
    "wof:placetype": "postalcode"
  },
  "geometry": {"coordinates":[-0.591464,51.512921],"type":"Point"}
}
