{
  "type": "Feature",
  "properties": {
    "iso:country":"GB",
    "wof:name":"TA23 0AL",
    "wof:placetype":"postalcode"
},
  "geometry": {"coordinates":[-3.33034843421239,51.18188877566234],"type":"Point"}
}