{
  "type": "Feature",
  "properties": {
    "iso:country":"GB",
    "wof:name":"WF17 7LE",
    "wof:placetype":"postalcode"
},
  "geometry": {"coordinates":[-1.63762128050333,53.70247987725018],"type":"Point"}
}