{
  "type": "Feature",
  "properties": {
    "iso:country":"GB",
    "wof:name":"S43 3SA",
    "wof:placetype":"postalcode"
},
  "geometry": {"coordinates":[-1.37062414854732,53.25981972274268],"type":"Point"}
}