{
  "type": "Feature",
  "properties": {
    "iso:country": "GB",
    "wof:name": "S43 3SA",
    "wof:placetype": "postalcode"
  },
  "geometry": {"coordinates":[-1.370624,53.25982],"type":"Point"}
}
