{
  "type": "Feature",
  "properties": {
    "iso:country":"GB",
    "wof:name":"BL8 1ER",
    "wof:placetype":"postalcode"
},
  "geometry": {"coordinates":[-2.31131590440337,53.60582791748134],"type":"Point"}
}