{
  "type": "Feature",
  "properties": {
    "iso:country":"GB",
    "wof:name":"AB16 5YL",
    "wof:placetype":"postalcode"
},
  "geometry": {"coordinates":[-2.13038440174038,57.15913339410408],"type":"Point"}
}