{
  "type": "Feature",
  "properties": {
    "iso:country": "GB",
    "wof:name": "WF3 1AB",
    "wof:placetype": "postalcode"
  },
  "geometry": {"coordinates":[-1.566926,53.724842],"type":"Point"}
}
