{
  "type": "Feature",
  "properties": {
    "iso:country":"GB",
    "wof:name":"WF3 1AB",
    "wof:placetype":"postalcode"
},
  "geometry": {"coordinates":[-1.56692567966018,53.72484157083176],"type":"Point"}
}