{
  "type": "Feature",
  "properties": {
    "iso:country":"GB",
    "wof:name":"CT3 1RQ",
    "wof:placetype":"postalcode"
},
  "geometry": {"coordinates":[1.18284306159939,51.2841886399294],"type":"Point"}
}