{
  "type": "Feature",
  "properties": {
    "iso:country": "GB",
    "wof:name": "NN6 9AY",
    "wof:placetype": "postalcode"
  },
  "geometry": {"coordinates":[-0.89048,52.304685],"type":"Point"}
}
