{
  "type": "Feature",
  "properties": {
    "date:inception_lower": "1980-01-01",
    "date:inception_upper": "1980-01-01",
    "iso:country": "GB",
    "wof:name": "SG5 2UL",
    "wof:placetype": "postalcode"
  },
  "geometry": {"coordinates":[-0.288441,51.958951],"type":"Point"}
}
