{
  "type": "Feature",
  "properties": {
    "iso:country":"GB",
    "wof:name":"SG5 2UL",
    "wof:placetype":"postalcode"
},
  "geometry": {"coordinates":[-0.28844078413784,51.95895147853489],"type":"Point"}
}