{
  "type": "Feature",
  "properties": {
    "iso:country":"GB",
    "wof:name":"WN2 1AF",
    "wof:placetype":"postalcode"
},
  "geometry": {"coordinates":[-2.60850575761128,53.55496116414488],"type":"Point"}
}