{
  "type": "Feature",
  "properties": {
    "iso:country": "GB",
    "wof:name": "IP13 9QD",
    "wof:placetype": "postalcode"
  },
  "geometry": {"coordinates":[1.306044,52.231596],"type":"Point"}
}
