{
  "type": "Feature",
  "properties": {
    "iso:country":"GB",
    "wof:name":"IP13 9QD",
    "wof:placetype":"postalcode"
},
  "geometry": {"coordinates":[1.30604436843459,52.23159603580951],"type":"Point"}
}