{
  "type": "Feature",
  "properties": {
    "iso:country":"GB",
    "wof:name":"G67 2RF",
    "wof:placetype":"postalcode"
},
  "geometry": {"coordinates":[-3.98304118213939,55.95989142301499],"type":"Point"}
}