{
  "type": "Feature",
  "properties": {
    "iso:country":"GB",
    "wof:name":"G22 6RL",
    "wof:placetype":"postalcode"
},
  "geometry": {"coordinates":[-4.25638887063737,55.88469072240178],"type":"Point"}
}