{
  "type": "Feature",
  "properties": {
    "iso:country":"GB",
    "wof:name":"BS6 7PT",
    "wof:placetype":"postalcode"
},
  "geometry": {"coordinates":[-2.61417286871164,51.47949222509669],"type":"Point"}
}