{
  "type": "Feature",
  "properties": {
    "iso:country": "GB",
    "wof:name": "OX9 3YT",
    "wof:placetype": "postalcode"
  },
  "geometry": {"coordinates":[-0.964878,51.748586],"type":"Point"}
}
