{
  "type": "Feature",
  "properties": {
    "iso:country": "GB",
    "wof:name": "PE29 6LE",
    "wof:placetype": "postalcode"
  },
  "geometry": {"coordinates":[-0.208823,52.3337],"type":"Point"}
}
