{
  "type": "Feature",
  "properties": {
    "iso:country":"GB",
    "wof:name":"DL8 3HJ",
    "wof:placetype":"postalcode"
},
  "geometry": {"coordinates":[-2.07802420165276,54.31607536981993],"type":"Point"}
}