{
  "type": "Feature",
  "properties": {
    "iso:country": "GB",
    "wof:name": "DL8 3HJ",
    "wof:placetype": "postalcode"
  },
  "geometry": {"coordinates":[-2.078024,54.316075],"type":"Point"}
}
