{
  "type": "Feature",
  "properties": {
    "iso:country": "GB",
    "wof:name": "TR2 4EH",
    "wof:placetype": "postalcode"
  },
  "geometry": {"coordinates":[-4.907739,50.319135],"type":"Point"}
}
