{
  "type": "Feature",
  "properties": {
    "iso:country":"GB",
    "wof:name":"TR2 4EH",
    "wof:placetype":"postalcode"
},
  "geometry": {"coordinates":[-4.9077393340633,50.31913480508523],"type":"Point"}
}