{
  "type": "Feature",
  "properties": {
    "iso:country": "GB",
    "wof:name": "WS12 2YT",
    "wof:placetype": "postalcode"
  },
  "geometry": {"coordinates":[-1.990443,52.693946],"type":"Point"}
}
