{
  "type": "Feature",
  "properties": {
    "iso:country":"GB",
    "wof:name":"WS12 2YT",
    "wof:placetype":"postalcode"
},
  "geometry": {"coordinates":[-1.99044347813872,52.69394596053419],"type":"Point"}
}