{
  "type": "Feature",
  "properties": {
    "date:inception_lower":"1980-01-01",
    "date:inception_upper":"1980-01-31",
    "iso:country":"GB",
    "wof:name":"NG22 9JJ",
    "wof:placetype":"postalcode"
},
  "geometry": {"coordinates":[-0.993636,53.208398],"type":"Point"}
}