{
  "type": "Feature",
  "properties": {
    "iso:country":"GB",
    "wof:name":"TR20 9TB",
    "wof:placetype":"postalcode"
},
  "geometry": {"coordinates":[-5.38708575056428,50.10410580874905],"type":"Point"}
}