{
  "type": "Feature",
  "properties": {
    "iso:country": "GB",
    "wof:name": "TR20 9TB",
    "wof:placetype": "postalcode"
  },
  "geometry": {"coordinates":[-5.387086,50.104106],"type":"Point"}
}
