{
  "type": "Feature",
  "properties": {
    "iso:country":"GB",
    "wof:name":"HA8 0ED",
    "wof:placetype":"postalcode"
},
  "geometry": {"coordinates":[-0.27421477840934,51.60655489201875],"type":"Point"}
}