{
  "type": "Feature",
  "properties": {
    "iso:country":"GB",
    "wof:name":"BD18 3ER",
    "wof:placetype":"postalcode"
},
  "geometry": {"coordinates":[-1.78143632166163,53.83307363855415],"type":"Point"}
}