{
  "type": "Feature",
  "properties": {
    "iso:country":"GB",
    "wof:name":"WS15 4SE",
    "wof:placetype":"postalcode"
},
  "geometry": {"coordinates":[-1.93986487101361,52.70912366632512],"type":"Point"}
}