{
  "type": "Feature",
  "properties": {
    "date:inception_lower": "1980-01-01",
    "date:inception_upper": "1980-01-01",
    "iso:country": "GB",
    "wof:name": "WS15 4SE",
    "wof:placetype": "postalcode"
  },
  "geometry": {"coordinates":[-1.939865,52.709124],"type":"Point"}
}
