{
  "type": "Feature",
  "properties": {
    "iso:country": "GB",
    "wof:name": "TN3 0NR",
    "wof:placetype": "postalcode"
  },
  "geometry": {"coordinates":[0.218473,51.146081],"type":"Point"}
}
