{
  "type": "Feature",
  "properties": {
    "iso:country":"GB",
    "wof:name":"TN3 0NR",
    "wof:placetype":"postalcode"
},
  "geometry": {"coordinates":[0.21800869188437,51.14589400055863],"type":"Point"}
}