{
  "type": "Feature",
  "properties": {
    "iso:country":"GB",
    "wof:name":"OL9 9XP",
    "wof:placetype":"postalcode"
},
  "geometry": {"coordinates":[-2.16710608333668,53.5361514775607],"type":"Point"}
}