{
  "type": "Feature",
  "properties": {
    "iso:country":"GB",
    "wof:name":"NE1 7XJ",
    "wof:placetype":"postalcode"
},
  "geometry": {"coordinates":[-1.616454921069,54.9746520910324],"type":"Point"}
}