{
  "type": "Feature",
  "properties": {
    "date:inception_lower": "1980-01-01",
    "date:inception_upper": "1980-01-01",
    "iso:country": "GB",
    "wof:name": "NE1 7XJ",
    "wof:placetype": "postalcode"
  },
  "geometry": {"coordinates":[-1.616469,54.974605],"type":"Point"}
}
