{
  "type": "Feature",
  "properties": {
    "iso:country":"GB",
    "wof:name":"EC2M 1NB",
    "wof:placetype":"postalcode"
},
  "geometry": {"coordinates":[-0.08498179089024,51.51775069195808],"type":"Point"}
}