{
  "type": "Feature",
  "properties": {
    "date:inception_lower": "2022-12-01",
    "date:inception_upper": "2022-12-01",
    "iso:country": "GB",
    "wof:name": "WR10 2FH",
    "wof:placetype": "postalcode"
  },
  "geometry": {"coordinates":[-2.076259,52.128576],"type":"Point"}
}
