{
  "type": "Feature",
  "properties": {
    "date:inception_lower":"1992-05-01",
    "date:inception_upper":"1992-05-31",
    "iso:country":"GB",
    "wof:name":"ML5 2RG",
    "wof:placetype":"postalcode"
},
  "geometry": {"coordinates":[-4.042138,55.89626],"type":"Point"}
}