{
  "type": "Feature",
  "properties": {
    "iso:country":"GB",
    "wof:name":"ML5 2RG",
    "wof:placetype":"postalcode"
},
  "geometry": {"coordinates":[-4.04213846591955,55.89626025841148],"type":"Point"}
}