{
  "type": "Feature",
  "properties": {
    "iso:country": "GB",
    "wof:name": "ML5 2RG",
    "wof:placetype": "postalcode"
  },
  "geometry": {"coordinates":[-4.042138,55.89626],"type":"Point"}
}
