{
  "type": "Feature",
  "properties": {
    "iso:country":"GB",
    "wof:name":"PO9 5LE",
    "wof:placetype":"postalcode"
},
  "geometry": {"coordinates":[-0.97038899799121,50.87116133306269],"type":"Point"}
}