{
  "type": "Feature",
  "properties": {
    "iso:country": "GB",
    "wof:name": "PO9 5LE",
    "wof:placetype": "postalcode"
  },
  "geometry": {"coordinates":[-0.970389,50.871161],"type":"Point"}
}
