{
  "type": "Feature",
  "properties": {
    "iso:country": "GB",
    "wof:name": "LN1 1LY",
    "wof:placetype": "postalcode"
  },
  "geometry": {"coordinates":[-0.552425,53.23471],"type":"Point"}
}
