{
  "type": "Feature",
  "properties": {
    "iso:country":"GB",
    "wof:name":"LN1 1LY",
    "wof:placetype":"postalcode"
},
  "geometry": {"coordinates":[-0.55229122784331,53.23465069985648],"type":"Point"}
}