{
  "type": "Feature",
  "properties": {
    "iso:country":"GB",
    "wof:name":"TS23 3PD",
    "wof:placetype":"postalcode"
},
  "geometry": {"coordinates":[-1.27331898357392,54.61729431751974],"type":"Point"}
}