{
  "type": "Feature",
  "properties": {
    "iso:country":"GB",
    "wof:name":"G33 6EP",
    "wof:placetype":"postalcode"
},
  "geometry": {"coordinates":[-4.15060151501552,55.88910140221367],"type":"Point"}
}