{
  "type": "Feature",
  "properties": {
    "iso:country": "GB",
    "wof:name": "G33 6EP",
    "wof:placetype": "postalcode"
  },
  "geometry": {"coordinates":[-4.150601,55.889101],"type":"Point"}
}
