{
  "type": "Feature",
  "properties": {
    "date:inception_lower":"1980-01-01",
    "date:inception_upper":"1980-01-31",
    "iso:country":"GB",
    "wof:name":"TN31 7UJ",
    "wof:placetype":"postalcode"
},
  "geometry": {"coordinates":[0.734789,50.962922],"type":"Point"}
}