{
  "type": "Feature",
  "properties": {
    "iso:country":"GB",
    "wof:name":"TN31 7UJ",
    "wof:placetype":"postalcode"
},
  "geometry": {"coordinates":[0.73478932491487,50.9629219608594],"type":"Point"}
}