{
  "type": "Feature",
  "properties": {
    "iso:country":"GB",
    "wof:name":"NG34 8DF",
    "wof:placetype":"postalcode"
},
  "geometry": {"coordinates":[-0.46284798022121,53.03721921835036],"type":"Point"}
}