{
  "type": "Feature",
  "properties": {
    "date:inception_lower": "1980-01-01",
    "date:inception_upper": "1980-01-01",
    "iso:country": "GB",
    "wof:name": "NG34 8DF",
    "wof:placetype": "postalcode"
  },
  "geometry": {"coordinates":[-0.462848,53.037219],"type":"Point"}
}
