{
  "type": "Feature",
  "properties": {
    "iso:country":"GB",
    "wof:name":"DN12 3DU",
    "wof:placetype":"postalcode"
},
  "geometry": {"coordinates":[-1.22616831092959,53.48567739507286],"type":"Point"}
}