{
  "type": "Feature",
  "properties": {
    "iso:country":"GB",
    "wof:name":"M9 0PP",
    "wof:placetype":"postalcode"
},
  "geometry": {"coordinates":[-2.23957200622053,53.53585732416863],"type":"Point"}
}