{
  "type": "Feature",
  "properties": {
    "iso:country":"GB",
    "wof:name":"TQ12 1DW",
    "wof:placetype":"postalcode"
},
  "geometry": {"coordinates":[-3.5950707157412,50.52234617260442],"type":"Point"}
}