{
  "type": "Feature",
  "properties": {
    "iso:country": "GB",
    "wof:name": "WF14 9PQ",
    "wof:placetype": "postalcode"
  },
  "geometry": {"coordinates":[-1.689219,53.679085],"type":"Point"}
}
