{
  "type": "Feature",
  "properties": {
    "iso:country":"GB",
    "wof:name":"YO18 7RB",
    "wof:placetype":"postalcode"
},
  "geometry": {"coordinates":[-0.74316306280759,54.21403267623332],"type":"Point"}
}