{
  "type": "Feature",
  "properties": {
    "date:inception_lower": "1980-01-01",
    "date:inception_upper": "1980-01-01",
    "iso:country": "GB",
    "wof:name": "YO18 7RB",
    "wof:placetype": "postalcode"
  },
  "geometry": {"coordinates":[-0.743163,54.214033],"type":"Point"}
}
