{
  "type": "Feature",
  "properties": {
    "date:inception_lower": "1980-01-01",
    "date:inception_upper": "1980-01-01",
    "iso:country": "GB",
    "wof:name": "NN5 5LW",
    "wof:placetype": "postalcode"
  },
  "geometry": {"coordinates":[-0.917086,52.239645],"type":"Point"}
}
