{
  "type": "Feature",
  "properties": {
    "iso:country":"GB",
    "wof:name":"HG3 2AU",
    "wof:placetype":"postalcode"
},
  "geometry": {"coordinates":[-1.555961357852,54.02000985731917],"type":"Point"}
}