{
  "type": "Feature",
  "properties": {
    "iso:country":"GB",
    "wof:name":"CV11 4BJ",
    "wof:placetype":"postalcode"
},
  "geometry": {"coordinates":[-1.46024408857157,52.52317895786981],"type":"Point"}
}