{
  "type": "Feature",
  "properties": {
    "iso:country":"GB",
    "wof:name":"SG5 1AU",
    "wof:placetype":"postalcode"
},
  "geometry": {"coordinates":[-0.28135269879476,51.94753662546445],"type":"Point"}
}