{
  "type": "Feature",
  "properties": {
    "iso:country":"GB",
    "wof:name":"SP6 1DL",
    "wof:placetype":"postalcode"
},
  "geometry": {"coordinates":[-1.80786257116662,50.93094449569777],"type":"Point"}
}