{
  "type": "Feature",
  "properties": {
    "iso:country":"GB",
    "wof:name":"N6 5RS",
    "wof:placetype":"postalcode"
},
  "geometry": {"coordinates":[-0.13580262557606,51.57811752661665],"type":"Point"}
}