{
  "type": "Feature",
  "properties": {
    "iso:country":"GB",
    "wof:name":"BA2 7FP",
    "wof:placetype":"postalcode"
},
  "geometry": {"coordinates":[-2.31487392628703,51.34787206400414],"type":"Point"}
}