{
  "type": "Feature",
  "properties": {
    "iso:country":"GB",
    "wof:name":"E15 2AD",
    "wof:placetype":"postalcode"
},
  "geometry": {"coordinates":[0.00412798080267,51.5516659509316],"type":"Point"}
}