{
  "type": "Feature",
  "properties": {
    "iso:country":"GB",
    "wof:name":"WA8 7DU",
    "wof:placetype":"postalcode"
},
  "geometry": {"coordinates":[-2.73990087150633,53.36840620144],"type":"Point"}
}