{
  "type": "Feature",
  "properties": {
    "date:inception_lower": "1980-01-01",
    "date:inception_upper": "1980-01-01",
    "iso:country": "GB",
    "wof:name": "HU17 8BS",
    "wof:placetype": "postalcode"
  },
  "geometry": {"coordinates":[-0.435207,53.842908],"type":"Point"}
}
