{
  "type": "Feature",
  "properties": {
    "iso:country":"GB",
    "wof:name":"E1 5BS",
    "wof:placetype":"postalcode"
},
  "geometry": {"coordinates":[-0.0644141412445,51.52147772302487],"type":"Point"}
}