{
  "type": "Feature",
  "properties": {
    "iso:country":"GB",
    "wof:name":"BA15 1SZ",
    "wof:placetype":"postalcode"
},
  "geometry": {"coordinates":[-2.24669787649405,51.3528102152306],"type":"Point"}
}