{
  "type": "Feature",
  "properties": {
    "date:inception_lower": "1994-12-01",
    "date:inception_upper": "1994-12-01",
    "iso:country": "GB",
    "wof:name": "DE74 2NW",
    "wof:placetype": "postalcode"
  },
  "geometry": {"coordinates":[-1.33671,52.851956],"type":"Point"}
}
