{
  "type": "Feature",
  "properties": {
    "iso:country":"GB",
    "wof:name":"NN17 3HY",
    "wof:placetype":"postalcode"
},
  "geometry": {"coordinates":[-0.64125105745384,52.49740793059217],"type":"Point"}
}