{
  "type": "Feature",
  "properties": {
    "date:inception_lower": "2003-07-01",
    "date:inception_upper": "2003-07-01",
    "iso:country": "GB",
    "wof:name": "NN17 3HY",
    "wof:placetype": "postalcode"
  },
  "geometry": {"coordinates":[-0.641235,52.497425],"type":"Point"}
}
