{
  "type": "Feature",
  "properties": {
    "iso:country": "GB",
    "wof:name": "WR14 4AX",
    "wof:placetype": "postalcode"
  },
  "geometry": {"coordinates":[-2.327316,52.094203],"type":"Point"}
}
