{
  "type": "Feature",
  "properties": {
    "iso:country":"GB",
    "wof:name":"WR14 4AX",
    "wof:placetype":"postalcode"
},
  "geometry": {"coordinates":[-2.32731621687995,52.09420289487406],"type":"Point"}
}