{
  "type": "Feature",
  "properties": {
    "date:inception_lower": "1980-01-01",
    "date:inception_upper": "1980-01-01",
    "iso:country": "GB",
    "wof:name": "SE15 3PY",
    "wof:placetype": "postalcode"
  },
  "geometry": {"coordinates":[-0.059112,51.461715],"type":"Point"}
}
