{
  "type": "Feature",
  "properties": {
    "date:inception_lower": "2007-01-01",
    "date:inception_upper": "2007-01-01",
    "iso:country": "GB",
    "wof:name": "WS14 0GE",
    "wof:placetype": "postalcode"
  },
  "geometry": {"coordinates":[-1.83847,52.670814],"type":"Point"}
}
