{
  "type": "Feature",
  "properties": {
    "iso:country": "GB",
    "wof:name": "BS8 2SS",
    "wof:placetype": "postalcode"
  },
  "geometry": {"coordinates":[-2.615413,51.46679],"type":"Point"}
}
