{
  "type": "Feature",
  "properties": {
    "date:inception_lower": "1980-01-01",
    "date:inception_upper": "1980-01-01",
    "iso:country": "GB",
    "wof:name": "NW7 2EH",
    "wof:placetype": "postalcode"
  },
  "geometry": {"coordinates":[-0.235826,51.605166],"type":"Point"}
}
