{
  "type": "Feature",
  "properties": {
    "iso:country":"GB",
    "wof:name":"NW7 2EH",
    "wof:placetype":"postalcode"
},
  "geometry": {"coordinates":[-0.23582567360844,51.60516592201599],"type":"Point"}
}