{
  "type": "Feature",
  "properties": {
    "iso:country":"GB",
    "wof:name":"CB2 0QJ",
    "wof:placetype":"postalcode"
},
  "geometry": {"coordinates":[0.14531974624709,52.17565117575144],"type":"Point"}
}