{
  "type": "Feature",
  "properties": {
    "iso:country":"GB",
    "wof:name":"LE8 9GU",
    "wof:placetype":"postalcode"
},
  "geometry": {"coordinates":[-1.03160318804666,52.57367085034164],"type":"Point"}
}