{
  "type": "Feature",
  "properties": {
    "iso:country":"GB",
    "wof:name":"SK6 6DN",
    "wof:placetype":"postalcode"
},
  "geometry": {"coordinates":[-2.07312208325455,53.39579242010875],"type":"Point"}
}