{
  "type": "Feature",
  "properties": {
    "iso:country": "GB",
    "wof:name": "NG12 3AW",
    "wof:placetype": "postalcode"
  },
  "geometry": {"coordinates":[-0.984725,52.929306],"type":"Point"}
}
