{
  "type": "Feature",
  "properties": {
    "date:inception_lower":"1985-04-01",
    "date:inception_upper":"1985-04-30",
    "iso:country":"GB",
    "wof:name":"NG12 3AW",
    "wof:placetype":"postalcode"
},
  "geometry": {"coordinates":[-0.984725,52.929306],"type":"Point"}
}