{
  "type": "Feature",
  "properties": {
    "date:inception_lower": "1980-01-01",
    "date:inception_upper": "1980-01-01",
    "iso:country": "GB",
    "wof:name": "OX16 0QR",
    "wof:placetype": "postalcode"
  },
  "geometry": {"coordinates":[-1.3642,52.061585],"type":"Point"}
}
