{
  "type": "Feature",
  "properties": {
    "iso:country":"GB",
    "wof:name":"OX16 0QR",
    "wof:placetype":"postalcode"
},
  "geometry": {"coordinates":[-1.36420024763386,52.06158541041327],"type":"Point"}
}