{
  "type": "Feature",
  "properties": {
    "date:inception_lower": "1980-01-01",
    "date:inception_upper": "1980-01-01",
    "iso:country": "GB",
    "wof:name": "DT8 3LJ",
    "wof:placetype": "postalcode"
  },
  "geometry": {"coordinates":[-2.822779,50.823204],"type":"Point"}
}
