{
  "type": "Feature",
  "properties": {
    "date:inception_lower": "1994-12-01",
    "date:inception_upper": "1994-12-01",
    "iso:country": "GB",
    "wof:name": "SO40 9HG",
    "wof:placetype": "postalcode"
  },
  "geometry": {"coordinates":[-1.485853,50.916493],"type":"Point"}
}
