{
  "type": "Feature",
  "properties": {
    "iso:country":"GB",
    "wof:name":"SO40 9HG",
    "wof:placetype":"postalcode"
},
  "geometry": {"coordinates":[-1.48593126562891,50.91657308180077],"type":"Point"}
}