{
  "type": "Feature",
  "properties": {
    "iso:country":"GB",
    "wof:name":"CF14 4JR",
    "wof:placetype":"postalcode"
},
  "geometry": {"coordinates":[-3.19414616764258,51.51675963186572],"type":"Point"}
}