{
  "type": "Feature",
  "properties": {
    "iso:country":"GB",
    "wof:name":"BH4 8BU",
    "wof:placetype":"postalcode"
},
  "geometry": {"coordinates":[-1.89648404487606,50.71892313528247],"type":"Point"}
}