{
  "type": "Feature",
  "properties": {
    "date:inception_lower": "1980-01-01",
    "date:inception_upper": "1980-01-01",
    "iso:country": "GB",
    "wof:name": "BH4 8BU",
    "wof:placetype": "postalcode"
  },
  "geometry": {"coordinates":[-1.896484,50.718923],"type":"Point"}
}
