{
  "type": "Feature",
  "properties": {
    "iso:country":"GB",
    "wof:name":"BL1 2NF",
    "wof:placetype":"postalcode"
},
  "geometry": {"coordinates":[-2.43378819579155,53.5849529895639],"type":"Point"}
}