{
  "type": "Feature",
  "properties": {
    "iso:country": "GB",
    "wof:name": "S43 4FS",
    "wof:placetype": "postalcode"
  },
  "geometry": {"coordinates":[-1.258792,53.272867],"type":"Point"}
}
