{
  "type": "Feature",
  "properties": {
    "iso:country":"GB",
    "wof:name":"S43 4FS",
    "wof:placetype":"postalcode"
},
  "geometry": {"coordinates":[-1.2587918549347,53.27286741482485],"type":"Point"}
}