{
  "type": "Feature",
  "properties": {
    "date:inception_lower":"1997-12-01",
    "date:inception_upper":"1997-12-31",
    "iso:country":"GB",
    "wof:name":"S43 4FS",
    "wof:placetype":"postalcode"
},
  "geometry": {"coordinates":[-1.258792,53.272867],"type":"Point"}
}