{
  "type": "Feature",
  "properties": {
    "iso:country":"GB",
    "wof:name":"SN7 7JP",
    "wof:placetype":"postalcode"
},
  "geometry": {"coordinates":[-1.58559781648052,51.65751935674025],"type":"Point"}
}