{
  "type": "Feature",
  "properties": {
    "iso:country":"GB",
    "wof:name":"L15 7LB",
    "wof:placetype":"postalcode"
},
  "geometry": {"coordinates":[-2.90315242232992,53.40064009182329],"type":"Point"}
}