{
  "type": "Feature",
  "properties": {
    "date:inception_lower": "2001-12-01",
    "date:inception_upper": "2001-12-01",
    "iso:country": "GB",
    "wof:name": "AB31 4LF",
    "wof:placetype": "postalcode"
  },
  "geometry": {"coordinates":[-2.618378,57.10291],"type":"Point"}
}
