{
  "type": "Feature",
  "properties": {
    "iso:country":"GB",
    "wof:name":"AB31 4LF",
    "wof:placetype":"postalcode"
},
  "geometry": {"coordinates":[-2.61837377709635,57.10292372220186],"type":"Point"}
}