{
  "type": "Feature",
  "properties": {
    "iso:country":"GB",
    "wof:name":"BB5 6PH",
    "wof:placetype":"postalcode"
},
  "geometry": {"coordinates":[-2.35874959634955,53.75471913968416],"type":"Point"}
}