{
  "type": "Feature",
  "properties": {
    "iso:country": "GB",
    "wof:name": "BB5 6PH",
    "wof:placetype": "postalcode"
  },
  "geometry": {"coordinates":[-2.35875,53.754719],"type":"Point"}
}
