{
  "type": "Feature",
  "properties": {
    "iso:country": "GB",
    "wof:name": "G62 6BT",
    "wof:placetype": "postalcode"
  },
  "geometry": {"coordinates":[-4.318352,55.939615],"type":"Point"}
}
