{
  "type": "Feature",
  "properties": {
    "iso:country":"GB",
    "wof:name":"DL13 2DB",
    "wof:placetype":"postalcode"
},
  "geometry": {"coordinates":[-2.1050254250462,54.78155476398878],"type":"Point"}
}