{
  "type": "Feature",
  "properties": {
    "date:inception_lower": "1980-01-01",
    "date:inception_upper": "1980-01-01",
    "iso:country": "GB",
    "wof:name": "NG9 5AL",
    "wof:placetype": "postalcode"
  },
  "geometry": {"coordinates":[-1.231625,52.912011],"type":"Point"}
}
