{
  "type": "Feature",
  "properties": {
    "iso:country":"GB",
    "wof:name":"NG9 5AL",
    "wof:placetype":"postalcode"
},
  "geometry": {"coordinates":[-1.23162517350242,52.91201091980221],"type":"Point"}
}