{
  "type": "Feature",
  "properties": {
    "iso:country": "GB",
    "wof:name": "SK2 7LR",
    "wof:placetype": "postalcode"
  },
  "geometry": {"coordinates":[-2.129727,53.391268],"type":"Point"}
}
