{
  "type": "Feature",
  "properties": {
    "iso:country":"GB",
    "wof:name":"SK2 7LR",
    "wof:placetype":"postalcode"
},
  "geometry": {"coordinates":[-2.12972740209408,53.39126790601679],"type":"Point"}
}