{
  "type": "Feature",
  "properties": {
    "date:inception_lower": "1980-01-01",
    "date:inception_upper": "1980-01-01",
    "iso:country": "GB",
    "wof:name": "LN4 4TG",
    "wof:placetype": "postalcode"
  },
  "geometry": {"coordinates":[-0.167642,53.1014],"type":"Point"}
}
