{
  "type": "Feature",
  "properties": {
    "iso:country":"GB",
    "wof:name":"LN4 4TG",
    "wof:placetype":"postalcode"
},
  "geometry": {"coordinates":[-0.16764234655781,53.10140043979025],"type":"Point"}
}