{
  "type": "Feature",
  "properties": {
    "iso:country":"GB",
    "wof:name":"BH6 3LF",
    "wof:placetype":"postalcode"
},
  "geometry": {"coordinates":[-1.8075458899023,50.72780313603815],"type":"Point"}
}