{
  "type": "Feature",
  "properties": {
    "iso:country":"GB",
    "wof:name":"DY4 9JU",
    "wof:placetype":"postalcode"
},
  "geometry": {"coordinates":[-2.06362582005963,52.54275751096651],"type":"Point"}
}