{
  "type": "Feature",
  "properties": {
    "iso:country": "GB",
    "wof:name": "OX12 9BZ",
    "wof:placetype": "postalcode"
  },
  "geometry": {"coordinates":[-1.431954,51.584883],"type":"Point"}
}
