{
  "type": "Feature",
  "properties": {
    "iso:country":"GB",
    "wof:name":"OX12 9BZ",
    "wof:placetype":"postalcode"
},
  "geometry": {"coordinates":[-1.43195419407214,51.58488313982814],"type":"Point"}
}