{
  "type": "Feature",
  "properties": {
    "date:inception_lower":"1980-01-01",
    "date:inception_upper":"1980-01-31",
    "iso:country":"GB",
    "wof:name":"WA13 9RA",
    "wof:placetype":"postalcode"
},
  "geometry": {"coordinates":[-2.459208,53.388037],"type":"Point"}
}