{
  "type": "Feature",
  "properties": {
    "iso:country":"GB",
    "wof:name":"WA13 9RA",
    "wof:placetype":"postalcode"
},
  "geometry": {"coordinates":[-2.45920764905261,53.38803667088452],"type":"Point"}
}