{
  "type": "Feature",
  "properties": {
    "iso:country": "GB",
    "wof:name": "WA13 9RA",
    "wof:placetype": "postalcode"
  },
  "geometry": {"coordinates":[-2.459208,53.388037],"type":"Point"}
}
