{
  "type": "Feature",
  "properties": {
    "iso:country":"GB",
    "wof:name":"HA7 4LP",
    "wof:placetype":"postalcode"
},
  "geometry": {"coordinates":[-0.3104354053247,51.632565619532],"type":"Point"}
}