{
  "type": "Feature",
  "properties": {
    "iso:country":"GB",
    "wof:name":"WN8 6NN",
    "wof:placetype":"postalcode"
},
  "geometry": {"coordinates":[-2.7705634469678,53.54987383178842],"type":"Point"}
}