{
  "type": "Feature",
  "properties": {
    "date:inception_lower": "1981-09-01",
    "date:inception_upper": "1981-09-01",
    "iso:country": "GB",
    "wof:name": "WN8 6NN",
    "wof:placetype": "postalcode"
  },
  "geometry": {"coordinates":[-2.770563,53.549874],"type":"Point"}
}
