{
  "type": "Feature",
  "properties": {
    "date:inception_lower": "2011-02-01",
    "date:inception_upper": "2011-02-01",
    "iso:country": "GB",
    "wof:name": "KT23 4ET",
    "wof:placetype": "postalcode"
  },
  "geometry": {"coordinates":[-0.356346,51.281391],"type":"Point"}
}
