{
  "type": "Feature",
  "properties": {
    "iso:country":"GB",
    "wof:name":"SO45 2QE",
    "wof:placetype":"postalcode"
},
  "geometry": {"coordinates":[-1.39085493132609,50.83209874984544],"type":"Point"}
}