{
  "type": "Feature",
  "properties": {
    "iso:country": "GB",
    "wof:name": "SO45 2QE",
    "wof:placetype": "postalcode"
  },
  "geometry": {"coordinates":[-1.390855,50.832099],"type":"Point"}
}
