{
  "type": "Feature",
  "properties": {
    "iso:country":"GB",
    "wof:name":"BN3 5SS",
    "wof:placetype":"postalcode"
},
  "geometry": {"coordinates":[-0.20253624938752,50.83278678788952],"type":"Point"}
}