{
  "type": "Feature",
  "properties": {
    "date:inception_lower":"1980-01-01",
    "date:inception_upper":"1980-01-31",
    "iso:country":"GB",
    "wof:name":"BS27 3SD",
    "wof:placetype":"postalcode"
},
  "geometry": {"coordinates":[-2.752753,51.258519],"type":"Point"}
}