{
  "type": "Feature",
  "properties": {
    "iso:country":"GB",
    "wof:name":"NP44 1EJ",
    "wof:placetype":"postalcode"
},
  "geometry": {"coordinates":[-3.027015931462,51.66166929609111],"type":"Point"}
}