{
  "type": "Feature",
  "properties": {
    "date:inception_lower":"1980-01-01",
    "date:inception_upper":"1980-01-31",
    "iso:country":"GB",
    "wof:name":"TA18 8QA",
    "wof:placetype":"postalcode"
},
  "geometry": {"coordinates":[-2.8601,50.843996],"type":"Point"}
}