{
  "type": "Feature",
  "properties": {
    "iso:country": "GB",
    "wof:name": "LS12 2HX",
    "wof:placetype": "postalcode"
  },
  "geometry": {"coordinates":[-1.608812,53.806903],"type":"Point"}
}
