{
  "type": "Feature",
  "properties": {
    "date:inception_lower": "1994-12-01",
    "date:inception_upper": "1994-12-01",
    "iso:country": "GB",
    "wof:name": "LS12 2HX",
    "wof:placetype": "postalcode"
  },
  "geometry": {"coordinates":[-1.608812,53.806903],"type":"Point"}
}
