{
  "type": "Feature",
  "properties": {
    "iso:country":"GB",
    "wof:name":"SA33 4QY",
    "wof:placetype":"postalcode"
},
  "geometry": {"coordinates":[-4.50792630544335,51.79401695043575],"type":"Point"}
}