{
  "type": "Feature",
  "properties": {
    "iso:country": "GB",
    "wof:name": "SA33 4QY",
    "wof:placetype": "postalcode"
  },
  "geometry": {"coordinates":[-4.507732,51.793986],"type":"Point"}
}
