{
  "type": "Feature",
  "properties": {
    "date:inception_lower": "2023-07-01",
    "date:inception_upper": "2023-07-01",
    "iso:country": "GB",
    "wof:name": "NE15 9FS",
    "wof:placetype": "postalcode"
  },
  "geometry": {"coordinates":[-1.761995,55.000497],"type":"Point"}
}
