{
  "type": "Feature",
  "properties": {
    "iso:country":"GB",
    "wof:name":"WA3 1ES",
    "wof:placetype":"postalcode"
},
  "geometry": {"coordinates":[-2.54339168129347,53.47525022574834],"type":"Point"}
}