{
  "type": "Feature",
  "properties": {
    "iso:country":"GB",
    "wof:name":"LA9 6QG",
    "wof:placetype":"postalcode"
},
  "geometry": {"coordinates":[-2.76115632636552,54.35349430319853],"type":"Point"}
}