{
  "type": "Feature",
  "properties": {
    "iso:country": "GB",
    "wof:name": "LA9 6QG",
    "wof:placetype": "postalcode"
  },
  "geometry": {"coordinates":[-2.761156,54.353494],"type":"Point"}
}
