{
  "type": "Feature",
  "properties": {
    "iso:country":"GB",
    "wof:name":"TS5 8SU",
    "wof:placetype":"postalcode"
},
  "geometry": {"coordinates":[-1.25792850270217,54.53625481330613],"type":"Point"}
}