{
  "type": "Feature",
  "properties": {
    "date:inception_lower": "1988-03-01",
    "date:inception_upper": "1988-03-01",
    "iso:country": "GB",
    "wof:name": "BR5 3NT",
    "wof:placetype": "postalcode"
  },
  "geometry": {"coordinates":[0.122776,51.3967],"type":"Point"}
}
