{
  "type": "Feature",
  "properties": {
    "iso:country":"GB",
    "wof:name":"NN15 5JE",
    "wof:placetype":"postalcode"
},
  "geometry": {"coordinates":[-0.69384915375523,52.39214473318672],"type":"Point"}
}