{
  "type": "Feature",
  "properties": {
    "iso:country":"GB",
    "wof:name":"WA6 0FJ",
    "wof:placetype":"postalcode"
},
  "geometry": {"coordinates":[-2.77610519218683,53.26746439173129],"type":"Point"}
}