{
  "type": "Feature",
  "properties": {
    "date:inception_lower": "2007-07-01",
    "date:inception_upper": "2007-07-01",
    "iso:country": "GB",
    "wof:name": "WA6 0FJ",
    "wof:placetype": "postalcode"
  },
  "geometry": {"coordinates":[-2.776105,53.267464],"type":"Point"}
}
