{
  "type": "Feature",
  "properties": {
    "date:inception_lower": "1980-01-01",
    "date:inception_upper": "1980-01-01",
    "iso:country": "GB",
    "wof:name": "WR11 4TP",
    "wof:placetype": "postalcode"
  },
  "geometry": {"coordinates":[-1.943843,52.112044],"type":"Point"}
}
