{
  "type": "Feature",
  "properties": {
    "iso:country":"GB",
    "wof:name":"UB6 0SY",
    "wof:placetype":"postalcode"
},
  "geometry": {"coordinates":[-0.34824358568865,51.55472784850159],"type":"Point"}
}