{
  "type": "Feature",
  "properties": {
    "iso:country":"GB",
    "wof:name":"CF48 1JN",
    "wof:placetype":"postalcode"
},
  "geometry": {"coordinates":[-3.41937547168938,51.75165375252801],"type":"Point"}
}