{
  "type": "Feature",
  "properties": {
    "date:inception_lower": "2009-01-01",
    "date:inception_upper": "2009-01-01",
    "iso:country": "GB",
    "wof:name": "SO40 0EN",
    "wof:placetype": "postalcode"
  },
  "geometry": {"coordinates":[-1.507993,50.934266],"type":"Point"}
}
