{
  "type": "Feature",
  "properties": {
    "iso:country":"GB",
    "wof:name":"PO20 7AA",
    "wof:placetype":"postalcode"
},
  "geometry": {"coordinates":[-0.86669321280814,50.80159432209973],"type":"Point"}
}