{
  "type": "Feature",
  "properties": {
    "date:inception_lower": "1980-01-01",
    "date:inception_upper": "1980-01-01",
    "iso:country": "GB",
    "wof:name": "PO20 7AA",
    "wof:placetype": "postalcode"
  },
  "geometry": {"coordinates":[-0.866693,50.801594],"type":"Point"}
}
