{
  "type": "Feature",
  "properties": {
    "iso:country":"GB",
    "wof:name":"MK42 9HS",
    "wof:placetype":"postalcode"
},
  "geometry": {"coordinates":[-0.47034891101855,52.12566519099139],"type":"Point"}
}