{
  "type": "Feature",
  "properties": {
    "iso:country": "GB",
    "wof:name": "MK42 9HS",
    "wof:placetype": "postalcode"
  },
  "geometry": {"coordinates":[-0.470349,52.125665],"type":"Point"}
}
