{
  "type": "Feature",
  "properties": {
    "iso:country":"GB",
    "wof:name":"PO9 2NX",
    "wof:placetype":"postalcode"
},
  "geometry": {"coordinates":[-0.95288723304637,50.85941401445456],"type":"Point"}
}