{
  "type": "Feature",
  "properties": {
    "iso:country": "GB",
    "wof:name": "FY3 9QT",
    "wof:placetype": "postalcode"
  },
  "geometry": {"coordinates":[-3.017414,53.804804],"type":"Point"}
}
