{
  "type": "Feature",
  "properties": {
    "iso:country":"GB",
    "wof:name":"HA6 3ET",
    "wof:placetype":"postalcode"
},
  "geometry": {"coordinates":[-0.40455593985415,51.61577222539898],"type":"Point"}
}