{
  "type": "Feature",
  "properties": {
    "iso:country": "GB",
    "wof:name": "HA6 3ET",
    "wof:placetype": "postalcode"
  },
  "geometry": {"coordinates":[-0.404556,51.615772],"type":"Point"}
}
