{
  "type": "Feature",
  "properties": {
    "date:inception_lower":"1980-01-01",
    "date:inception_upper":"1980-01-31",
    "iso:country":"GB",
    "wof:name":"HA6 3ET",
    "wof:placetype":"postalcode"
},
  "geometry": {"coordinates":[-0.404556,51.615772],"type":"Point"}
}