{
  "type": "Feature",
  "properties": {
    "iso:country": "GB",
    "wof:name": "BB2 3AN",
    "wof:placetype": "postalcode"
  },
  "geometry": {"coordinates":[-2.477368,53.737809],"type":"Point"}
}
