{
  "type": "Feature",
  "properties": {
    "iso:country":"GB",
    "wof:name":"HD8 8RP",
    "wof:placetype":"postalcode"
},
  "geometry": {"coordinates":[-1.65788062411709,53.57251545065205],"type":"Point"}
}