{
  "type": "Feature",
  "properties": {
    "date:inception_lower": "2020-10-01",
    "date:inception_upper": "2020-10-01",
    "iso:country": "GB",
    "wof:name": "FK4 1AW",
    "wof:placetype": "postalcode"
  },
  "geometry": {"coordinates":[-3.879023,56.004687],"type":"Point"}
}
