{
  "type": "Feature",
  "properties": {
    "date:inception_lower": "1980-01-01",
    "date:inception_upper": "1980-01-01",
    "iso:country": "GB",
    "wof:name": "GU14 7BX",
    "wof:placetype": "postalcode"
  },
  "geometry": {"coordinates":[-0.74751,51.292263],"type":"Point"}
}
