{
  "type": "Feature",
  "properties": {
    "iso:country": "GB",
    "wof:name": "PO12 2NN",
    "wof:placetype": "postalcode"
  },
  "geometry": {"coordinates":[-1.157505,50.785783],"type":"Point"}
}
