{
  "type": "Feature",
  "properties": {
    "date:inception_lower": "1980-01-01",
    "date:inception_upper": "1980-01-01",
    "iso:country": "GB",
    "wof:name": "PO12 2NN",
    "wof:placetype": "postalcode"
  },
  "geometry": {"coordinates":[-1.157505,50.785783],"type":"Point"}
}
