{
  "type": "Feature",
  "properties": {
    "date:inception_lower":"2016-05-01",
    "date:inception_upper":"2016-05-31",
    "iso:country":"GB",
    "wof:name":"DD5 2HW",
    "wof:placetype":"postalcode"
},
  "geometry": {"coordinates":[-2.86843,56.46792],"type":"Point"}
}