{
  "type": "Feature",
  "properties": {
    "date:inception_lower": "2000-12-01",
    "date:inception_upper": "2000-12-01",
    "iso:country": "GB",
    "wof:name": "WR6 6WQ",
    "wof:placetype": "postalcode"
  },
  "geometry": {"coordinates":[-2.362951,52.292194],"type":"Point"}
}
