{
  "type": "Feature",
  "properties": {
    "iso:country":"GB",
    "wof:name":"WV4 6SG",
    "wof:placetype":"postalcode"
},
  "geometry": {"coordinates":[-2.11584271997093,52.56123691169974],"type":"Point"}
}