{
  "type": "Feature",
  "properties": {
    "iso:country":"GB",
    "wof:name":"CM6 1WP",
    "wof:placetype":"postalcode"
},
  "geometry": {"coordinates":[0.34477338034916,51.87466183862688],"type":"Point"}
}