{
  "type": "Feature",
  "properties": {
    "date:inception_lower":"1997-12-01",
    "date:inception_upper":"1997-12-31",
    "iso:country":"GB",
    "wof:name":"CM6 1WP",
    "wof:placetype":"postalcode"
},
  "geometry": {"coordinates":[0.344773,51.874662],"type":"Point"}
}