{
  "type": "Feature",
  "properties": {
    "iso:country":"GB",
    "wof:name":"CH66 3NP",
    "wof:placetype":"postalcode"
},
  "geometry": {"coordinates":[-2.92481902290009,53.28374330203984],"type":"Point"}
}