{
  "type": "Feature",
  "properties": {
    "iso:country":"GB",
    "wof:name":"HD3 4UU",
    "wof:placetype":"postalcode"
},
  "geometry": {"coordinates":[-1.83934772061919,53.6485414573997],"type":"Point"}
}