{
  "type": "Feature",
  "properties": {
    "iso:country": "GB",
    "wof:name": "ST6 4RB",
    "wof:placetype": "postalcode"
  },
  "geometry": {"coordinates":[-2.212188,53.045959],"type":"Point"}
}
