{
  "type": "Feature",
  "properties": {
    "date:inception_lower": "1990-07-01",
    "date:inception_upper": "1990-07-01",
    "iso:country": "GB",
    "wof:name": "ST6 4RB",
    "wof:placetype": "postalcode"
  },
  "geometry": {"coordinates":[-2.212453,53.045239],"type":"Point"}
}
