{
  "type": "Feature",
  "properties": {
    "iso:country":"GB",
    "wof:name":"L36 5XF",
    "wof:placetype":"postalcode"
},
  "geometry": {"coordinates":[-2.84553505433236,53.40836104824174],"type":"Point"}
}