{
  "type": "Feature",
  "properties": {
    "date:inception_lower":"1980-01-01",
    "date:inception_upper":"1980-01-31",
    "iso:country":"GB",
    "wof:name":"PR7 6EF",
    "wof:placetype":"postalcode"
},
  "geometry": {"coordinates":[-2.700275,53.660433],"type":"Point"}
}