{
  "type": "Feature",
  "properties": {
    "iso:country":"GB",
    "wof:name":"PR7 6EF",
    "wof:placetype":"postalcode"
},
  "geometry": {"coordinates":[-2.70027533514824,53.6604326025107],"type":"Point"}
}