{
  "type": "Feature",
  "properties": {
    "iso:country": "GB",
    "wof:name": "TA24 8TW",
    "wof:placetype": "postalcode"
  },
  "geometry": {"coordinates":[-3.550012,51.209523],"type":"Point"}
}
