{
  "type": "Feature",
  "properties": {
    "iso:country":"GB",
    "wof:name":"TA24 8TW",
    "wof:placetype":"postalcode"
},
  "geometry": {"coordinates":[-3.5498953974362,51.20944563935906],"type":"Point"}
}