{
  "type": "Feature",
  "properties": {
    "date:inception_lower": "1980-01-01",
    "date:inception_upper": "1980-01-01",
    "iso:country": "GB",
    "wof:name": "TA24 8TW",
    "wof:placetype": "postalcode"
  },
  "geometry": {"coordinates":[-3.550012,51.209523],"type":"Point"}
}
