{
  "type": "Feature",
  "properties": {
    "iso:country":"GB",
    "wof:name":"S11 9EJ",
    "wof:placetype":"postalcode"
},
  "geometry": {"coordinates":[-1.49475794224142,53.35813623474435],"type":"Point"}
}