{
  "type": "Feature",
  "properties": {
    "iso:country":"GB",
    "wof:name":"MK14 5DL",
    "wof:placetype":"postalcode"
},
  "geometry": {"coordinates":[-0.76194800027699,52.06845122359233],"type":"Point"}
}