{
  "type": "Feature",
  "properties": {
    "date:inception_lower": "1980-01-01",
    "date:inception_upper": "1980-01-01",
    "iso:country": "GB",
    "wof:name": "MK14 5DL",
    "wof:placetype": "postalcode"
  },
  "geometry": {"coordinates":[-0.761948,52.068451],"type":"Point"}
}
