{
  "type": "Feature",
  "properties": {
    "date:inception_lower": "2024-06-01",
    "date:inception_upper": "2024-06-01",
    "iso:country": "GB",
    "wof:name": "PO11 0FW",
    "wof:placetype": "postalcode"
  },
  "geometry": {"coordinates":[-0.995629,50.794329],"type":"Point"}
}
