{
  "type": "Feature",
  "properties": {
    "iso:country":"GB",
    "wof:name":"SK16 4BJ",
    "wof:placetype":"postalcode"
},
  "geometry": {"coordinates":[-2.08510099590708,53.47512600019459],"type":"Point"}
}