{
  "type": "Feature",
  "properties": {
    "date:inception_lower":"1980-01-01",
    "date:inception_upper":"1980-01-31",
    "iso:country":"GB",
    "wof:name":"SK16 4BJ",
    "wof:placetype":"postalcode"
},
  "geometry": {"coordinates":[-2.085101,53.475126],"type":"Point"}
}