{
  "type": "Feature",
  "properties": {
    "iso:country": "GB",
    "wof:name": "BS40 7RP",
    "wof:placetype": "postalcode"
  },
  "geometry": {"coordinates":[-2.715562,51.323599],"type":"Point"}
}
