{
  "type": "Feature",
  "properties": {
    "iso:country":"GB",
    "wof:name":"IV9 8QD",
    "wof:placetype":"postalcode"
},
  "geometry": {"coordinates":[-4.1710304474421,57.56609494577778],"type":"Point"}
}