{
  "type": "Feature",
  "properties": {
    "iso:country":"GB",
    "wof:name":"BD4 0PR",
    "wof:placetype":"postalcode"
},
  "geometry": {"coordinates":[-1.7092250012758,53.7681890473112],"type":"Point"}
}