{
  "type": "Feature",
  "properties": {
    "date:inception_lower": "2023-04-01",
    "date:inception_upper": "2023-04-01",
    "iso:country": "GB",
    "wof:name": "M31 4SJ",
    "wof:placetype": "postalcode"
  },
  "geometry": {"coordinates":[-2.437649,53.419181],"type":"Point"}
}
