{
  "type": "Feature",
  "properties": {
    "iso:country": "GB",
    "wof:name": "TN26 3NH",
    "wof:placetype": "postalcode"
  },
  "geometry": {"coordinates":[0.697796,51.106655],"type":"Point"}
}
