{
  "type": "Feature",
  "properties": {
    "iso:country": "GB",
    "wof:name": "MK45 1FN",
    "wof:placetype": "postalcode"
  },
  "geometry": {"coordinates":[-0.495541,52.006503],"type":"Point"}
}
