{
  "type": "Feature",
  "properties": {
    "date:inception_lower": "2007-05-01",
    "date:inception_upper": "2007-05-01",
    "iso:country": "GB",
    "wof:name": "MK45 1FN",
    "wof:placetype": "postalcode"
  },
  "geometry": {"coordinates":[-0.495541,52.006503],"type":"Point"}
}
