{
  "type": "Feature",
  "properties": {
    "iso:country":"GB",
    "wof:name":"EH54 8PB",
    "wof:placetype":"postalcode"
},
  "geometry": {"coordinates":[-3.54548203078269,55.90489049747217],"type":"Point"}
}