{
  "type": "Feature",
  "properties": {
    "iso:country":"GB",
    "wof:name":"S42 5BY",
    "wof:placetype":"postalcode"
},
  "geometry": {"coordinates":[-1.38731653912658,53.18368913442347],"type":"Point"}
}