{
  "type": "Feature",
  "properties": {
    "date:inception_lower":"2010-02-01",
    "date:inception_upper":"2010-02-28",
    "iso:country":"GB",
    "wof:name":"S42 5BY",
    "wof:placetype":"postalcode"
},
  "geometry": {"coordinates":[-1.387316,53.183689],"type":"Point"}
}