{
  "type": "Feature",
  "properties": {
    "iso:country": "GB",
    "wof:name": "S42 5BY",
    "wof:placetype": "postalcode"
  },
  "geometry": {"coordinates":[-1.387316,53.183689],"type":"Point"}
}
