{
  "type": "Feature",
  "properties": {
    "iso:country":"GB",
    "wof:name":"CB1 8NR",
    "wof:placetype":"postalcode"
},
  "geometry": {"coordinates":[0.159845291158,52.1820311568933],"type":"Point"}
}