{
  "type": "Feature",
  "properties": {
    "iso:country":"GB",
    "wof:name":"BA2 2SY",
    "wof:placetype":"postalcode"
},
  "geometry": {"coordinates":[-2.38234860239877,51.3570045520343],"type":"Point"}
}