{
  "type": "Feature",
  "properties": {
    "iso:country":"GB",
    "wof:name":"NE37 3HW",
    "wof:placetype":"postalcode"
},
  "geometry": {"coordinates":[-1.51708703573054,54.92194396740409],"type":"Point"}
}