{
  "type": "Feature",
  "properties": {
    "iso:country":"GB",
    "wof:name":"LE7 9EG",
    "wof:placetype":"postalcode"
},
  "geometry": {"coordinates":[-0.95752195404522,52.5869857659985],"type":"Point"}
}