{
  "type": "Feature",
  "properties": {
    "date:inception_lower":"1980-01-01",
    "date:inception_upper":"1980-01-31",
    "iso:country":"GB",
    "wof:name":"LE7 9EG",
    "wof:placetype":"postalcode"
},
  "geometry": {"coordinates":[-0.957522,52.586986],"type":"Point"}
}