{
  "type": "Feature",
  "properties": {
    "iso:country":"GB",
    "wof:name":"RH2 7RW",
    "wof:placetype":"postalcode"
},
  "geometry": {"coordinates":[-0.20213164170576,51.23725441651347],"type":"Point"}
}