{
  "type": "Feature",
  "properties": {
    "iso:country": "GB",
    "wof:name": "RH2 7RW",
    "wof:placetype": "postalcode"
  },
  "geometry": {"coordinates":[-0.202132,51.237254],"type":"Point"}
}
