{
  "type": "Feature",
  "properties": {
    "iso:country":"GB",
    "wof:name":"CV36 4LH",
    "wof:placetype":"postalcode"
},
  "geometry": {"coordinates":[-1.69733266238685,52.0879228116226],"type":"Point"}
}