{
  "type": "Feature",
  "properties": {
    "iso:country":"GB",
    "wof:name":"IG1 3PP",
    "wof:placetype":"postalcode"
},
  "geometry": {"coordinates":[0.0532713393137,51.57502440914506],"type":"Point"}
}