{
  "type": "Feature",
  "properties": {
    "iso:country": "GB",
    "wof:name": "WA8 9WH",
    "wof:placetype": "postalcode"
  },
  "geometry": {"coordinates":[-2.756728,53.380831],"type":"Point"}
}
