{
  "type": "Feature",
  "properties": {
    "iso:country":"GB",
    "wof:name":"WA8 9WH",
    "wof:placetype":"postalcode"
},
  "geometry": {"coordinates":[-2.7567281909102,53.38083109058535],"type":"Point"}
}