{
  "type": "Feature",
  "properties": {
    "iso:country": "GB",
    "wof:name": "PR4 0PU",
    "wof:placetype": "postalcode"
  },
  "geometry": {"coordinates":[-2.778345,53.784509],"type":"Point"}
}
