{
  "type": "Feature",
  "properties": {
    "date:inception_lower": "1999-06-01",
    "date:inception_upper": "1999-06-01",
    "iso:country": "GB",
    "wof:name": "NP11 6AW",
    "wof:placetype": "postalcode"
  },
  "geometry": {"coordinates":[-3.097849,51.604662],"type":"Point"}
}
