{
  "type": "Feature",
  "properties": {
    "iso:country": "GB",
    "wof:name": "OX5 3HD",
    "wof:placetype": "postalcode"
  },
  "geometry": {"coordinates":[-1.277403,51.871952],"type":"Point"}
}
