{
  "type": "Feature",
  "properties": {
    "iso:country": "GB",
    "wof:name": "OL2 8DZ",
    "wof:placetype": "postalcode"
  },
  "geometry": {"coordinates":[-2.084611,53.584146],"type":"Point"}
}
