{
  "type": "Feature",
  "properties": {
    "iso:country":"GB",
    "wof:name":"OL2 8DZ",
    "wof:placetype":"postalcode"
},
  "geometry": {"coordinates":[-2.08461056336052,53.58414620958643],"type":"Point"}
}