{
  "type": "Feature",
  "properties": {
    "iso:country":"GB",
    "wof:name":"TS17 7HD",
    "wof:placetype":"postalcode"
},
  "geometry": {"coordinates":[-1.2931204250717,54.55408013140283],"type":"Point"}
}