{
  "type": "Feature",
  "properties": {
    "iso:country":"GB",
    "wof:name":"PL24 2PA",
    "wof:placetype":"postalcode"
},
  "geometry": {"coordinates":[-4.70389607560174,50.35200579219755],"type":"Point"}
}