{
  "type": "Feature",
  "properties": {
    "date:inception_lower": "1980-01-01",
    "date:inception_upper": "1980-01-01",
    "iso:country": "GB",
    "wof:name": "BA4 6JH",
    "wof:placetype": "postalcode"
  },
  "geometry": {"coordinates":[-2.506525,51.144018],"type":"Point"}
}
