{
  "type": "Feature",
  "properties": {
    "iso:country": "GB",
    "wof:name": "GL56 9RL",
    "wof:placetype": "postalcode"
  },
  "geometry": {"coordinates":[-1.755912,52.026958],"type":"Point"}
}
