{
  "type": "Feature",
  "properties": {
    "iso:country":"GB",
    "wof:name":"GL56 9RL",
    "wof:placetype":"postalcode"
},
  "geometry": {"coordinates":[-1.75591243403661,52.02695823252547],"type":"Point"}
}