{
  "type": "Feature",
  "properties": {
    "iso:country":"GB",
    "wof:name":"DL3 0AY",
    "wof:placetype":"postalcode"
},
  "geometry": {"coordinates":[-1.5510656069726,54.55397253331142],"type":"Point"}
}