{
  "type": "Feature",
  "properties": {
    "iso:country": "GB",
    "wof:name": "DL3 0AY",
    "wof:placetype": "postalcode"
  },
  "geometry": {"coordinates":[-1.551066,54.553973],"type":"Point"}
}
