{
  "type": "Feature",
  "properties": {
    "iso:country":"GB",
    "wof:name":"DG7 2JJ",
    "wof:placetype":"postalcode"
},
  "geometry": {"coordinates":[-4.18365465761054,54.88474225819893],"type":"Point"}
}