{
  "type": "Feature",
  "properties": {
    "iso:country":"GB",
    "wof:name":"DE24 8RW",
    "wof:placetype":"postalcode"
},
  "geometry": {"coordinates":[-1.4360794017259,52.89937601976018],"type":"Point"}
}