{
  "type": "Feature",
  "properties": {
    "iso:country": "GB",
    "wof:name": "DE24 8RW",
    "wof:placetype": "postalcode"
  },
  "geometry": {"coordinates":[-1.43603,52.899394],"type":"Point"}
}
