{
  "type": "Feature",
  "properties": {
    "iso:country":"GB",
    "wof:name":"NP20 5FX",
    "wof:placetype":"postalcode"
},
  "geometry": {"coordinates":[-3.00414242711082,51.59620162982412],"type":"Point"}
}