{
  "type": "Feature",
  "properties": {
    "date:inception_lower":"1980-01-01",
    "date:inception_upper":"1980-01-31",
    "iso:country":"GB",
    "wof:name":"NE12 9DL",
    "wof:placetype":"postalcode"
},
  "geometry": {"coordinates":[-1.55851,55.026064],"type":"Point"}
}