{
  "type": "Feature",
  "properties": {
    "iso:country":"GB",
    "wof:name":"NE12 9DL",
    "wof:placetype":"postalcode"
},
  "geometry": {"coordinates":[-1.55850960043282,55.02606370039817],"type":"Point"}
}