{
  "type": "Feature",
  "properties": {
    "date:inception_lower": "1980-01-01",
    "date:inception_upper": "1980-01-01",
    "iso:country": "GB",
    "wof:name": "PO36 8HE",
    "wof:placetype": "postalcode"
  },
  "geometry": {"coordinates":[-1.154597,50.656829],"type":"Point"}
}
