{
  "type": "Feature",
  "properties": {
    "iso:country": "GB",
    "wof:name": "PO36 8HE",
    "wof:placetype": "postalcode"
  },
  "geometry": {"coordinates":[-1.154597,50.656829],"type":"Point"}
}
