{
  "type": "Feature",
  "properties": {
    "iso:country":"GB",
    "wof:name":"LS9 6EN",
    "wof:placetype":"postalcode"
},
  "geometry": {"coordinates":[-1.50881076459817,53.80489932959541],"type":"Point"}
}