{
  "type": "Feature",
  "properties": {
    "date:inception_lower": "2003-09-01",
    "date:inception_upper": "2003-09-01",
    "iso:country": "GB",
    "wof:name": "CB3 0FA",
    "wof:placetype": "postalcode"
  },
  "geometry": {"coordinates":[0.090464,52.20885],"type":"Point"}
}
