{
  "type": "Feature",
  "properties": {
    "iso:country": "GB",
    "wof:name": "CB3 0FA",
    "wof:placetype": "postalcode"
  },
  "geometry": {"coordinates":[0.090435,52.208837],"type":"Point"}
}
