{
  "type": "Feature",
  "properties": {
    "date:inception_lower":"2003-09-01",
    "date:inception_upper":"2003-09-30",
    "iso:country":"GB",
    "wof:name":"CB3 0FA",
    "wof:placetype":"postalcode"
},
  "geometry": {"coordinates":[0.090435,52.208837],"type":"Point"}
}