{
  "type": "Feature",
  "properties": {
    "iso:country":"GB",
    "wof:name":"CB3 0FA",
    "wof:placetype":"postalcode"
},
  "geometry": {"coordinates":[0.09043495999917,52.20883663041828],"type":"Point"}
}