{
  "type": "Feature",
  "properties": {
    "iso:country": "GB",
    "wof:name": "KT21 1ED",
    "wof:placetype": "postalcode"
  },
  "geometry": {"coordinates":[-0.297905,51.306878],"type":"Point"}
}
