{
  "type": "Feature",
  "properties": {
    "iso:country":"GB",
    "wof:name":"PR4 2JQ",
    "wof:placetype":"postalcode"
},
  "geometry": {"coordinates":[-2.88213076442297,53.78375574005489],"type":"Point"}
}