{
  "type": "Feature",
  "properties": {
    "date:inception_lower":"1980-01-01",
    "date:inception_upper":"1980-01-31",
    "iso:country":"GB",
    "wof:name":"PR4 2JQ",
    "wof:placetype":"postalcode"
},
  "geometry": {"coordinates":[-2.882131,53.783756],"type":"Point"}
}