{
  "type": "Feature",
  "properties": {
    "iso:country":"GB",
    "wof:name":"RG7 1BJ",
    "wof:placetype":"postalcode"
},
  "geometry": {"coordinates":[-0.9773438308126,51.40351427715382],"type":"Point"}
}