{
  "type": "Feature",
  "properties": {
    "iso:country": "GB",
    "wof:name": "RG7 1BJ",
    "wof:placetype": "postalcode"
  },
  "geometry": {"coordinates":[-0.977162,51.403577],"type":"Point"}
}
