{
  "type": "Feature",
  "properties": {
    "date:inception_lower":"1980-01-01",
    "date:inception_upper":"1980-01-31",
    "iso:country":"GB",
    "wof:name":"RG7 1BJ",
    "wof:placetype":"postalcode"
},
  "geometry": {"coordinates":[-0.977162,51.403577],"type":"Point"}
}