{
  "type": "Feature",
  "properties": {
    "iso:country":"GB",
    "wof:name":"DY5 2YX",
    "wof:placetype":"postalcode"
},
  "geometry": {"coordinates":[-2.1108440795459,52.47441721152151],"type":"Point"}
}