{
  "type": "Feature",
  "properties": {
    "iso:country": "GB",
    "wof:name": "RG4 7RA",
    "wof:placetype": "postalcode"
  },
  "geometry": {"coordinates":[-0.975002,51.472893],"type":"Point"}
}
