{
  "type": "Feature",
  "properties": {
    "iso:country":"GB",
    "wof:name":"RG4 7RA",
    "wof:placetype":"postalcode"
},
  "geometry": {"coordinates":[-0.97500172078826,51.47289313728213],"type":"Point"}
}