{
  "type": "Feature",
  "properties": {
    "date:inception_lower": "1980-01-01",
    "date:inception_upper": "1980-01-01",
    "iso:country": "GB",
    "wof:name": "BB12 8QS",
    "wof:placetype": "postalcode"
  },
  "geometry": {"coordinates":[-2.310086,53.7986],"type":"Point"}
}
