{
  "type": "Feature",
  "properties": {
    "iso:country":"GB",
    "wof:name":"CR8 3EJ",
    "wof:placetype":"postalcode"
},
  "geometry": {"coordinates":[-0.12737107673385,51.34079457003247],"type":"Point"}
}