{
  "type": "Feature",
  "properties": {
    "iso:country":"GB",
    "wof:name":"BD18 3AW",
    "wof:placetype":"postalcode"
},
  "geometry": {"coordinates":[-1.77708102032331,53.82057240968787],"type":"Point"}
}