{
  "type": "Feature",
  "properties": {
    "iso:country": "GB",
    "wof:name": "BD18 3AW",
    "wof:placetype": "postalcode"
  },
  "geometry": {"coordinates":[-1.777081,53.820572],"type":"Point"}
}
