{
  "type": "Feature",
  "properties": {
    "iso:country":"GB",
    "wof:name":"B14 5QJ",
    "wof:placetype":"postalcode"
},
  "geometry": {"coordinates":[-1.91191845261549,52.40720042881971],"type":"Point"}
}