{
  "type": "Feature",
  "properties": {
    "date:inception_lower":"2013-04-01",
    "date:inception_upper":"2013-04-30",
    "iso:country":"GB",
    "wof:name":"NP19 0NU",
    "wof:placetype":"postalcode"
},
  "geometry": {"coordinates":[-2.988449,51.587273],"type":"Point"}
}