{
  "type": "Feature",
  "properties": {
    "iso:country":"GB",
    "wof:name":"NP19 0NU",
    "wof:placetype":"postalcode"
},
  "geometry": {"coordinates":[-2.98837115230464,51.58728095408039],"type":"Point"}
}