{
  "type": "Feature",
  "properties": {
    "iso:country":"GB",
    "wof:name":"SS17 7LW",
    "wof:placetype":"postalcode"
},
  "geometry": {"coordinates":[0.4473623030358,51.52585371921211],"type":"Point"}
}