{
  "type": "Feature",
  "properties": {
    "date:inception_lower":"2010-01-01",
    "date:inception_upper":"2010-01-31",
    "iso:country":"GB",
    "wof:name":"SO51 0AH",
    "wof:placetype":"postalcode"
},
  "geometry": {"coordinates":[-1.500499,51.025417],"type":"Point"}
}