{
  "type": "Feature",
  "properties": {
    "iso:country":"GB",
    "wof:name":"NN7 3JT",
    "wof:placetype":"postalcode"
},
  "geometry": {"coordinates":[-1.03838391118357,52.21962991372305],"type":"Point"}
}