{
  "type": "Feature",
  "properties": {
    "date:inception_lower": "1980-01-01",
    "date:inception_upper": "1980-01-01",
    "iso:country": "GB",
    "wof:name": "NN7 3JT",
    "wof:placetype": "postalcode"
  },
  "geometry": {"coordinates":[-1.038384,52.21963],"type":"Point"}
}
