{
  "type": "Feature",
  "properties": {
    "iso:country": "GB",
    "wof:name": "DL16 6TW",
    "wof:placetype": "postalcode"
  },
  "geometry": {"coordinates":[-1.580875,54.710746],"type":"Point"}
}
