{
  "type": "Feature",
  "properties": {
    "date:inception_lower": "1995-12-01",
    "date:inception_upper": "1995-12-01",
    "iso:country": "GB",
    "wof:name": "DL16 6TW",
    "wof:placetype": "postalcode"
  },
  "geometry": {"coordinates":[-1.580875,54.710746],"type":"Point"}
}
