{
  "type": "Feature",
  "properties": {
    "iso:country":"GB",
    "wof:name":"EH6 8DP",
    "wof:placetype":"postalcode"
},
  "geometry": {"coordinates":[-3.16418295349645,55.96712338893946],"type":"Point"}
}