{
  "type": "Feature",
  "properties": {
    "date:inception_lower": "2024-09-01",
    "date:inception_upper": "2024-09-01",
    "iso:country": "GB",
    "wof:name": "EX7 0TJ",
    "wof:placetype": "postalcode"
  },
  "geometry": {"coordinates":[-3.47297,50.59116],"type":"Point"}
}
