{
  "type": "Feature",
  "properties": {
    "iso:country": "GB",
    "wof:name": "EC4M 7LS",
    "wof:placetype": "postalcode"
  },
  "geometry": {"coordinates":[-0.099382,51.514954],"type":"Point"}
}
