{
  "type": "Feature",
  "properties": {
    "date:inception_lower":"1980-01-01",
    "date:inception_upper":"1980-01-31",
    "iso:country":"GB",
    "wof:name":"SN13 9SZ",
    "wof:placetype":"postalcode"
},
  "geometry": {"coordinates":[-2.20352,51.411537],"type":"Point"}
}