{
  "type": "Feature",
  "properties": {
    "iso:country":"GB",
    "wof:name":"SN13 9SZ",
    "wof:placetype":"postalcode"
},
  "geometry": {"coordinates":[-2.20351959767192,51.41153686905831],"type":"Point"}
}