{
  "type": "Feature",
  "properties": {
    "iso:country": "GB",
    "wof:name": "SY12 9ES",
    "wof:placetype": "postalcode"
  },
  "geometry": {"coordinates":[-2.904853,52.910812],"type":"Point"}
}
