{
  "type": "Feature",
  "properties": {
    "iso:country": "GB",
    "wof:name": "M22 1UU",
    "wof:placetype": "postalcode"
  },
  "geometry": {"coordinates":[-2.272266,53.378048],"type":"Point"}
}
