{
  "type": "Feature",
  "properties": {
    "iso:country":"GB",
    "wof:name":"B45 8UA",
    "wof:placetype":"postalcode"
},
  "geometry": {"coordinates":[-2.00039646706465,52.38180906862213],"type":"Point"}
}