{
  "type": "Feature",
  "properties": {
    "iso:country":"GB",
    "wof:name":"WC1V 7LL",
    "wof:placetype":"postalcode"
},
  "geometry": {"coordinates":[-0.11412755128566,51.51806107074981],"type":"Point"}
}