{
  "type": "Feature",
  "properties": {
    "iso:country": "GB",
    "wof:name": "NW9 8BB",
    "wof:placetype": "postalcode"
  },
  "geometry": {"coordinates":[-0.26183,51.581538],"type":"Point"}
}
