{
  "type": "Feature",
  "properties": {
    "date:inception_lower": "2018-12-01",
    "date:inception_upper": "2018-12-01",
    "iso:country": "GB",
    "wof:name": "NW9 8BB",
    "wof:placetype": "postalcode"
  },
  "geometry": {"coordinates":[-0.26183,51.581538],"type":"Point"}
}
