{
  "type": "Feature",
  "properties": {
    "iso:country": "GB",
    "wof:name": "DL1 4ST",
    "wof:placetype": "postalcode"
  },
  "geometry": {"coordinates":[-1.525385,54.51657],"type":"Point"}
}
