{
  "type": "Feature",
  "properties": {
    "date:inception_lower":"1980-01-01",
    "date:inception_upper":"1980-01-31",
    "iso:country":"GB",
    "wof:name":"BD12 9BE",
    "wof:placetype":"postalcode"
},
  "geometry": {"coordinates":[-1.763242,53.736984],"type":"Point"}
}