{
  "type": "Feature",
  "properties": {
    "iso:country":"GB",
    "wof:name":"BD12 9BE",
    "wof:placetype":"postalcode"
},
  "geometry": {"coordinates":[-1.7632424681512,53.7369844253726],"type":"Point"}
}