{
  "type": "Feature",
  "properties": {
    "iso:country": "GB",
    "wof:name": "CM23 2WJ",
    "wof:placetype": "postalcode"
  },
  "geometry": {"coordinates":[0.136281,51.876915],"type":"Point"}
}
