{
  "type": "Feature",
  "properties": {
    "date:inception_lower": "1983-01-01",
    "date:inception_upper": "1983-01-01",
    "iso:country": "GB",
    "wof:name": "PO32 6EX",
    "wof:placetype": "postalcode"
  },
  "geometry": {"coordinates":[-1.279633,50.751716],"type":"Point"}
}
