{
  "type": "Feature",
  "properties": {
    "iso:country":"GB",
    "wof:name":"SE4 2LA",
    "wof:placetype":"postalcode"
},
  "geometry": {"coordinates":[-0.04111406889538,51.45809734897109],"type":"Point"}
}