{
  "type": "Feature",
  "properties": {
    "iso:country": "GB",
    "wof:name": "TN24 9AB",
    "wof:placetype": "postalcode"
  },
  "geometry": {"coordinates":[0.88425,51.171712],"type":"Point"}
}
