{
  "type": "Feature",
  "properties": {
    "iso:country":"GB",
    "wof:name":"TN24 9AB",
    "wof:placetype":"postalcode"
},
  "geometry": {"coordinates":[0.88434730842794,51.17166480771338],"type":"Point"}
}