{
  "type": "Feature",
  "properties": {
    "iso:country":"GB",
    "wof:name":"TN36 4LW",
    "wof:placetype":"postalcode"
},
  "geometry": {"coordinates":[0.72596676167291,50.91512510053088],"type":"Point"}
}