{
  "type": "Feature",
  "properties": {
    "iso:country":"GB",
    "wof:name":"CH7 6SD",
    "wof:placetype":"postalcode"
},
  "geometry": {"coordinates":[-3.10311090632217,53.1657257205335],"type":"Point"}
}