{
  "type": "Feature",
  "properties": {
    "iso:country": "GB",
    "wof:name": "CH7 6SD",
    "wof:placetype": "postalcode"
  },
  "geometry": {"coordinates":[-3.103111,53.165726],"type":"Point"}
}
