{
  "type": "Feature",
  "properties": {
    "iso:country":"GB",
    "wof:name":"RG42 3DJ",
    "wof:placetype":"postalcode"
},
  "geometry": {"coordinates":[-0.73177867223957,51.43057271855093],"type":"Point"}
}