{
  "type": "Feature",
  "properties": {
    "iso:country": "GB",
    "wof:name": "RG42 3DJ",
    "wof:placetype": "postalcode"
  },
  "geometry": {"coordinates":[-0.731779,51.430573],"type":"Point"}
}
