{
  "type": "Feature",
  "properties": {
    "iso:country":"GB",
    "wof:name":"RG19 8BQ",
    "wof:placetype":"postalcode"
},
  "geometry": {"coordinates":[-1.20353593959761,51.35236119878579],"type":"Point"}
}