{
  "type": "Feature",
  "properties": {
    "iso:country": "GB",
    "wof:name": "NP13 2LN",
    "wof:placetype": "postalcode"
  },
  "geometry": {"coordinates":[-3.143501,51.701992],"type":"Point"}
}
