{
  "type": "Feature",
  "properties": {
    "iso:country":"GB",
    "wof:name":"M29 8FP",
    "wof:placetype":"postalcode"
},
  "geometry": {"coordinates":[-2.47308818570578,53.51557516210313],"type":"Point"}
}