{
  "type": "Feature",
  "properties": {
    "iso:country":"GB",
    "wof:name":"NN3 9SX",
    "wof:placetype":"postalcode"
},
  "geometry": {"coordinates":[-0.82717829723118,52.24970075286546],"type":"Point"}
}