{
  "type": "Feature",
  "properties": {
    "date:inception_lower": "2000-06-01",
    "date:inception_upper": "2000-06-01",
    "iso:country": "GB",
    "wof:name": "OX4 6AF",
    "wof:placetype": "postalcode"
  },
  "geometry": {"coordinates":[-1.199926,51.724481],"type":"Point"}
}
