{
  "type": "Feature",
  "properties": {
    "iso:country":"GB",
    "wof:name":"OX4 6AF",
    "wof:placetype":"postalcode"
},
  "geometry": {"coordinates":[-1.19992600470186,51.72448102573139],"type":"Point"}
}