{
  "type": "Feature",
  "properties": {
    "iso:country":"GB",
    "wof:name":"W2 4NP",
    "wof:placetype":"postalcode"
},
  "geometry": {"coordinates":[-0.19271885843885,51.51274285005753],"type":"Point"}
}