{
  "type": "Feature",
  "properties": {
    "date:inception_lower":"1997-06-01",
    "date:inception_upper":"1997-06-30",
    "iso:country":"GB",
    "wof:name":"PO9 2YJ",
    "wof:placetype":"postalcode"
},
  "geometry": {"coordinates":[-0.976675,50.856666],"type":"Point"}
}