{
  "type": "Feature",
  "properties": {
    "iso:country":"GB",
    "wof:name":"PO9 2YJ",
    "wof:placetype":"postalcode"
},
  "geometry": {"coordinates":[-0.97667529506875,50.85666635440722],"type":"Point"}
}