{
  "type": "Feature",
  "properties": {
    "date:inception_lower":"1980-01-01",
    "date:inception_upper":"1980-01-31",
    "iso:country":"GB",
    "wof:name":"TF8 7PX",
    "wof:placetype":"postalcode"
},
  "geometry": {"coordinates":[-2.484114,52.628536],"type":"Point"}
}