{
  "type": "Feature",
  "properties": {
    "iso:country":"GB",
    "wof:name":"TF8 7PX",
    "wof:placetype":"postalcode"
},
  "geometry": {"coordinates":[-2.48411402203655,52.62853617352706],"type":"Point"}
}