{
  "type": "Feature",
  "properties": {
    "date:inception_lower": "2016-05-01",
    "date:inception_upper": "2016-05-01",
    "iso:country": "GB",
    "wof:name": "CF40 2QP",
    "wof:placetype": "postalcode"
  },
  "geometry": {"coordinates":[-3.441502,51.618956],"type":"Point"}
}
