{
  "type": "Feature",
  "properties": {
    "iso:country":"GB",
    "wof:name":"KA13 7JT",
    "wof:placetype":"postalcode"
},
  "geometry": {"coordinates":[-4.68565880253252,55.65498443893476],"type":"Point"}
}