{
  "type": "Feature",
  "properties": {
    "iso:country":"GB",
    "wof:name":"TN2 5HT",
    "wof:placetype":"postalcode"
},
  "geometry": {"coordinates":[0.26252024351171,51.11552443369283],"type":"Point"}
}