{
  "type": "Feature",
  "properties": {
    "iso:country": "GB",
    "wof:name": "GL7 1BD",
    "wof:placetype": "postalcode"
  },
  "geometry": {"coordinates":[-1.957193,51.717305],"type":"Point"}
}
