{
  "type": "Feature",
  "properties": {
    "iso:country":"GB",
    "wof:name":"GL7 1BD",
    "wof:placetype":"postalcode"
},
  "geometry": {"coordinates":[-1.95719304332477,51.7173048019962],"type":"Point"}
}