{
  "type": "Feature",
  "properties": {
    "date:inception_lower": "1995-12-01",
    "date:inception_upper": "1995-12-01",
    "iso:country": "GB",
    "wof:name": "WA2 0FG",
    "wof:placetype": "postalcode"
  },
  "geometry": {"coordinates":[-2.573652,53.413195],"type":"Point"}
}
