{
  "type": "Feature",
  "properties": {
    "iso:country": "GB",
    "wof:name": "TF6 6ET",
    "wof:placetype": "postalcode"
  },
  "geometry": {"coordinates":[-2.5173,52.729069],"type":"Point"}
}
