{
  "type": "Feature",
  "properties": {
    "iso:country":"GB",
    "wof:name":"TF6 6ET",
    "wof:placetype":"postalcode"
},
  "geometry": {"coordinates":[-2.51731689360411,52.7291169495651],"type":"Point"}
}