{
  "type": "Feature",
  "properties": {
    "date:inception_lower": "1981-06-01",
    "date:inception_upper": "1981-06-01",
    "iso:country": "GB",
    "wof:name": "IP30 9AS",
    "wof:placetype": "postalcode"
  },
  "geometry": {"coordinates":[0.833225,52.221733],"type":"Point"}
}
