{
  "type": "Feature",
  "properties": {
    "iso:country": "GB",
    "wof:name": "IP30 9AS",
    "wof:placetype": "postalcode"
  },
  "geometry": {"coordinates":[0.833225,52.221733],"type":"Point"}
}
