{
  "type": "Feature",
  "properties": {
    "iso:country":"GB",
    "wof:name":"IP30 9AS",
    "wof:placetype":"postalcode"
},
  "geometry": {"coordinates":[0.83322507953158,52.22173345903114],"type":"Point"}
}