{
  "type": "Feature",
  "properties": {
    "date:inception_lower":"1980-01-01",
    "date:inception_upper":"1980-01-31",
    "iso:country":"GB",
    "wof:name":"HD1 3TG",
    "wof:placetype":"postalcode"
},
  "geometry": {"coordinates":[-1.794383,53.633876],"type":"Point"}
}