{
  "type": "Feature",
  "properties": {
    "iso:country":"GB",
    "wof:name":"HD1 3TG",
    "wof:placetype":"postalcode"
},
  "geometry": {"coordinates":[-1.79438270685479,53.63387593125648],"type":"Point"}
}