{
  "type": "Feature",
  "properties": {
    "iso:country":"GB",
    "wof:name":"PE30 2AN",
    "wof:placetype":"postalcode"
},
  "geometry": {"coordinates":[0.40158155436271,52.76204363391216],"type":"Point"}
}