{
  "type": "Feature",
  "properties": {
    "date:inception_lower": "2023-02-01",
    "date:inception_upper": "2023-02-01",
    "iso:country": "GB",
    "wof:name": "BB7 1RE",
    "wof:placetype": "postalcode"
  },
  "geometry": {"coordinates":[-2.378093,53.861658],"type":"Point"}
}
