{
  "type": "Feature",
  "properties": {
    "iso:country":"GB",
    "wof:name":"PL5 2HB",
    "wof:placetype":"postalcode"
},
  "geometry": {"coordinates":[-4.17065596564088,50.40568669454166],"type":"Point"}
}