{
  "type": "Feature",
  "properties": {
    "date:inception_lower": "1992-08-01",
    "date:inception_upper": "1992-08-01",
    "iso:country": "GB",
    "wof:name": "PL5 2HB",
    "wof:placetype": "postalcode"
  },
  "geometry": {"coordinates":[-4.170656,50.405687],"type":"Point"}
}
