{
  "type": "Feature",
  "properties": {
    "iso:country":"GB",
    "wof:name":"M19 1TD",
    "wof:placetype":"postalcode"
},
  "geometry": {"coordinates":[-2.21486956456084,53.41301405424366],"type":"Point"}
}