{
  "type": "Feature",
  "properties": {
    "date:inception_lower": "1999-06-01",
    "date:inception_upper": "1999-06-01",
    "iso:country": "GB",
    "wof:name": "CH62 8AR",
    "wof:placetype": "postalcode"
  },
  "geometry": {"coordinates":[-2.976788,53.317074],"type":"Point"}
}
