{
  "type": "Feature",
  "properties": {
    "iso:country":"GB",
    "wof:name":"CH62 8AR",
    "wof:placetype":"postalcode"
},
  "geometry": {"coordinates":[-2.97678777050304,53.3170738629715],"type":"Point"}
}