{
  "type": "Feature",
  "properties": {
    "iso:country":"GB",
    "wof:name":"SA19 6SZ",
    "wof:placetype":"postalcode"
},
  "geometry": {"coordinates":[-3.99211751722087,51.87475137963236],"type":"Point"}
}