{
  "type": "Feature",
  "properties": {
    "date:inception_lower":"1991-01-01",
    "date:inception_upper":"1991-01-31",
    "iso:country":"GB",
    "wof:name":"SA19 6SZ",
    "wof:placetype":"postalcode"
},
  "geometry": {"coordinates":[-3.992117,51.874751],"type":"Point"}
}