{
  "type": "Feature",
  "properties": {
    "date:inception_lower": "1980-01-01",
    "date:inception_upper": "1980-01-01",
    "iso:country": "GB",
    "wof:name": "B90 4HH",
    "wof:placetype": "postalcode"
  },
  "geometry": {"coordinates":[-1.813835,52.378702],"type":"Point"}
}
