{
  "type": "Feature",
  "properties": {
    "iso:country": "GB",
    "wof:name": "B90 4HH",
    "wof:placetype": "postalcode"
  },
  "geometry": {"coordinates":[-1.813835,52.378702],"type":"Point"}
}
