{
  "type": "Feature",
  "properties": {
    "iso:country":"GB",
    "wof:name":"AB10 7AE",
    "wof:placetype":"postalcode"
},
  "geometry": {"coordinates":[-2.13657928636211,57.1220987473974],"type":"Point"}
}