{
  "type": "Feature",
  "properties": {
    "date:inception_lower": "1980-01-01",
    "date:inception_upper": "1980-01-01",
    "iso:country": "GB",
    "wof:name": "CV31 2ND",
    "wof:placetype": "postalcode"
  },
  "geometry": {"coordinates":[-1.528503,52.269297],"type":"Point"}
}
