{
  "type": "Feature",
  "properties": {
    "iso:country": "GB",
    "wof:name": "KT22 8NT",
    "wof:placetype": "postalcode"
  },
  "geometry": {"coordinates":[-0.322035,51.293277],"type":"Point"}
}
