{
  "type": "Feature",
  "properties": {
    "date:inception_lower": "2004-01-01",
    "date:inception_upper": "2004-01-01",
    "iso:country": "GB",
    "wof:name": "KT22 8NT",
    "wof:placetype": "postalcode"
  },
  "geometry": {"coordinates":[-0.322035,51.293277],"type":"Point"}
}
