{
  "type": "Feature",
  "properties": {
    "date:inception_lower": "2015-10-01",
    "date:inception_upper": "2015-10-01",
    "iso:country": "GB",
    "wof:name": "AB15 9QU",
    "wof:placetype": "postalcode"
  },
  "geometry": {"coordinates":[-2.178328,57.123729],"type":"Point"}
}
