{
  "type": "Feature",
  "properties": {
    "iso:country": "GB",
    "wof:name": "AB15 9QU",
    "wof:placetype": "postalcode"
  },
  "geometry": {"coordinates":[-2.178328,57.123729],"type":"Point"}
}
