{
  "type": "Feature",
  "properties": {
    "iso:country":"GB",
    "wof:name":"WA4 1NT",
    "wof:placetype":"postalcode"
},
  "geometry": {"coordinates":[-2.55261054663573,53.38231938531659],"type":"Point"}
}