{
  "type": "Feature",
  "properties": {
    "date:inception_lower": "1980-01-01",
    "date:inception_upper": "1980-01-01",
    "iso:country": "GB",
    "wof:name": "EH42 1DB",
    "wof:placetype": "postalcode"
  },
  "geometry": {"coordinates":[-2.51962,56.002264],"type":"Point"}
}
