{
  "type": "Feature",
  "properties": {
    "date:inception_lower": "2018-05-01",
    "date:inception_upper": "2018-05-01",
    "iso:country": "GB",
    "wof:name": "PE2 8WG",
    "wof:placetype": "postalcode"
  },
  "geometry": {"coordinates":[-0.206323,52.545867],"type":"Point"}
}
