{
  "type": "Feature",
  "properties": {
    "iso:country": "GB",
    "wof:name": "GU14 9JB",
    "wof:placetype": "postalcode"
  },
  "geometry": {"coordinates":[-0.783293,51.307459],"type":"Point"}
}
