{
  "type": "Feature",
  "properties": {
    "date:inception_lower":"1980-01-01",
    "date:inception_upper":"1980-01-31",
    "iso:country":"GB",
    "wof:name":"GU14 9JB",
    "wof:placetype":"postalcode"
},
  "geometry": {"coordinates":[-0.783293,51.307459],"type":"Point"}
}