{
  "type": "Feature",
  "properties": {
    "iso:country":"GB",
    "wof:name":"NE48 1LH",
    "wof:placetype":"postalcode"
},
  "geometry": {"coordinates":[-2.35395533228343,55.15345612481846],"type":"Point"}
}