{
  "type": "Feature",
  "properties": {
    "date:inception_lower": "1987-10-01",
    "date:inception_upper": "1987-10-01",
    "iso:country": "GB",
    "wof:name": "OX12 9NE",
    "wof:placetype": "postalcode"
  },
  "geometry": {"coordinates":[-1.433246,51.562276],"type":"Point"}
}
