{
  "type": "Feature",
  "properties": {
    "iso:country":"GB",
    "wof:name":"S44 5UZ",
    "wof:placetype":"postalcode"
},
  "geometry": {"coordinates":[-1.37760393894216,53.22819728758832],"type":"Point"}
}