{
  "type": "Feature",
  "properties": {
    "iso:country":"GB",
    "wof:name":"PL13 2LF",
    "wof:placetype":"postalcode"
},
  "geometry": {"coordinates":[-4.53177379883429,50.36754044476642],"type":"Point"}
}