{
  "type": "Feature",
  "properties": {
    "iso:country":"GB",
    "wof:name":"IP32 6ND",
    "wof:placetype":"postalcode"
},
  "geometry": {"coordinates":[0.69647133034302,52.26223212065165],"type":"Point"}
}