{
  "type": "Feature",
  "properties": {
    "iso:country":"GB",
    "wof:name":"S43 2NB",
    "wof:placetype":"postalcode"
},
  "geometry": {"coordinates":[-1.375291858481,53.27281525818903],"type":"Point"}
}