{
  "type": "Feature",
  "properties": {
    "iso:country":"GB",
    "wof:name":"PE24 5XS",
    "wof:placetype":"postalcode"
},
  "geometry": {"coordinates":[0.3215238725482,53.26019379355703],"type":"Point"}
}