{
  "type": "Feature",
  "properties": {
    "iso:country": "GB",
    "wof:name": "PE24 5XS",
    "wof:placetype": "postalcode"
  },
  "geometry": {"coordinates":[0.32154,53.260229],"type":"Point"}
}
