{
  "type": "Feature",
  "properties": {
    "iso:country":"GB",
    "wof:name":"GL11 6AF",
    "wof:placetype":"postalcode"
},
  "geometry": {"coordinates":[-2.36119254146805,51.67903850858586],"type":"Point"}
}