{
  "type": "Feature",
  "properties": {
    "date:inception_lower":"1983-01-01",
    "date:inception_upper":"1983-01-31",
    "iso:country":"GB",
    "wof:name":"WV9 5PS",
    "wof:placetype":"postalcode"
},
  "geometry": {"coordinates":[-2.148674,52.620596],"type":"Point"}
}