{
  "type": "Feature",
  "properties": {
    "iso:country":"GB",
    "wof:name":"RG25 3DD",
    "wof:placetype":"postalcode"
},
  "geometry": {"coordinates":[-1.27678385097849,51.24205550534074],"type":"Point"}
}