{
  "type": "Feature",
  "properties": {
    "iso:country": "GB",
    "wof:name": "RG25 3DD",
    "wof:placetype": "postalcode"
  },
  "geometry": {"coordinates":[-1.276784,51.242056],"type":"Point"}
}
