{
  "type": "Feature",
  "properties": {
    "iso:country":"GB",
    "wof:name":"CF33 4ND",
    "wof:placetype":"postalcode"
},
  "geometry": {"coordinates":[-3.70184979585865,51.52358335558142],"type":"Point"}
}