{
  "type": "Feature",
  "properties": {
    "iso:country":"GB",
    "wof:name":"YO7 3PA",
    "wof:placetype":"postalcode"
},
  "geometry": {"coordinates":[-1.3887463562197,54.17897813377347],"type":"Point"}
}