{
  "type": "Feature",
  "properties": {
    "date:inception_lower":"1993-01-01",
    "date:inception_upper":"1993-01-31",
    "iso:country":"GB",
    "wof:name":"IP12 4UU",
    "wof:placetype":"postalcode"
},
  "geometry": {"coordinates":[1.300086,52.0914],"type":"Point"}
}