{
  "type": "Feature",
  "properties": {
    "iso:country":"GB",
    "wof:name":"IP12 4UU",
    "wof:placetype":"postalcode"
},
  "geometry": {"coordinates":[1.30008630207734,52.09140047572672],"type":"Point"}
}