{
  "type": "Feature",
  "properties": {
    "iso:country": "GB",
    "wof:name": "LN10 5EQ",
    "wof:placetype": "postalcode"
  },
  "geometry": {"coordinates":[-0.237922,53.204362],"type":"Point"}
}
