{
  "type": "Feature",
  "properties": {
    "date:inception_lower": "1996-12-01",
    "date:inception_upper": "1996-12-01",
    "iso:country": "GB",
    "wof:name": "LN10 5EQ",
    "wof:placetype": "postalcode"
  },
  "geometry": {"coordinates":[-0.238242,53.204241],"type":"Point"}
}
