{
  "type": "Feature",
  "properties": {
    "iso:country":"GB",
    "wof:name":"LN10 5EQ",
    "wof:placetype":"postalcode"
},
  "geometry": {"coordinates":[-0.23789516177377,53.20434630609176],"type":"Point"}
}