{
  "type": "Feature",
  "properties": {
    "iso:country": "GB",
    "wof:name": "DN12 3GE",
    "wof:placetype": "postalcode"
  },
  "geometry": {"coordinates":[-1.230943,53.488324],"type":"Point"}
}
