{
  "type": "Feature",
  "properties": {
    "date:inception_lower": "2004-01-01",
    "date:inception_upper": "2004-01-01",
    "iso:country": "GB",
    "wof:name": "DN12 3GE",
    "wof:placetype": "postalcode"
  },
  "geometry": {"coordinates":[-1.230943,53.488324],"type":"Point"}
}
