{
  "type": "Feature",
  "properties": {
    "iso:country":"GB",
    "wof:name":"TN26 3LS",
    "wof:placetype":"postalcode"
},
  "geometry": {"coordinates":[0.71337003189424,51.10331896030325],"type":"Point"}
}