{
  "type": "Feature",
  "properties": {
    "date:inception_lower":"2004-04-01",
    "date:inception_upper":"2004-04-30",
    "iso:country":"GB",
    "wof:name":"WD18 7AQ",
    "wof:placetype":"postalcode"
},
  "geometry": {"coordinates":[-0.418236,51.655199],"type":"Point"}
}