{
  "type": "Feature",
  "properties": {
    "iso:country":"GB",
    "wof:name":"WD18 7AQ",
    "wof:placetype":"postalcode"
},
  "geometry": {"coordinates":[-0.41823565394464,51.65519858375816],"type":"Point"}
}