{
  "type": "Feature",
  "properties": {
    "iso:country": "GB",
    "wof:name": "WD18 7AQ",
    "wof:placetype": "postalcode"
  },
  "geometry": {"coordinates":[-0.418236,51.655199],"type":"Point"}
}
