{
  "type": "Feature",
  "properties": {
    "iso:country":"GB",
    "wof:name":"OX16 4FB",
    "wof:placetype":"postalcode"
},
  "geometry": {"coordinates":[-1.31490386057479,52.06504043923312],"type":"Point"}
}