{
  "type": "Feature",
  "properties": {
    "iso:country": "GB",
    "wof:name": "OX16 4FB",
    "wof:placetype": "postalcode"
  },
  "geometry": {"coordinates":[-1.314904,52.06504],"type":"Point"}
}
