{
  "type": "Feature",
  "properties": {
    "date:inception_lower": "2014-07-01",
    "date:inception_upper": "2014-07-01",
    "iso:country": "GB",
    "wof:name": "SK11 6AD",
    "wof:placetype": "postalcode"
  },
  "geometry": {"coordinates":[-2.129659,53.255],"type":"Point"}
}
