{
  "type": "Feature",
  "properties": {
    "iso:country": "GB",
    "wof:name": "TR1 2FS",
    "wof:placetype": "postalcode"
  },
  "geometry": {"coordinates":[-5.058542,50.255251],"type":"Point"}
}
