{
  "type": "Feature",
  "properties": {
    "iso:country":"GB",
    "wof:name":"CF48 2RP",
    "wof:placetype":"postalcode"
},
  "geometry": {"coordinates":[-3.40156503542669,51.7603557081622],"type":"Point"}
}