{
  "type": "Feature",
  "properties": {
    "iso:country":"GB",
    "wof:name":"HA7 3LZ",
    "wof:placetype":"postalcode"
},
  "geometry": {"coordinates":[-0.32957365339876,51.61703126813435],"type":"Point"}
}