{
  "type": "Feature",
  "properties": {
    "iso:country":"GB",
    "wof:name":"CF24 2HG",
    "wof:placetype":"postalcode"
},
  "geometry": {"coordinates":[-3.13414109818659,51.4874483752564],"type":"Point"}
}