{
  "type": "Feature",
  "properties": {
    "date:inception_lower":"1994-05-01",
    "date:inception_upper":"1994-05-31",
    "iso:country":"GB",
    "wof:name":"M9 8JF",
    "wof:placetype":"postalcode"
},
  "geometry": {"coordinates":[-2.23062,53.526689],"type":"Point"}
}