{
  "type": "Feature",
  "properties": {
    "iso:country": "GB",
    "wof:name": "M9 8JF",
    "wof:placetype": "postalcode"
  },
  "geometry": {"coordinates":[-2.23062,53.526689],"type":"Point"}
}
