{
  "type": "Feature",
  "properties": {
    "date:inception_lower": "2016-03-01",
    "date:inception_upper": "2016-03-01",
    "iso:country": "GB",
    "wof:name": "DE11 0BP",
    "wof:placetype": "postalcode"
  },
  "geometry": {"coordinates":[-1.558157,52.77759],"type":"Point"}
}
