{
  "type": "Feature",
  "properties": {
    "date:inception_lower": "1999-06-01",
    "date:inception_upper": "1999-06-01",
    "iso:country": "GB",
    "wof:name": "TN12 0ST",
    "wof:placetype": "postalcode"
  },
  "geometry": {"coordinates":[0.546489,51.167298],"type":"Point"}
}
