{
  "type": "Feature",
  "properties": {
    "iso:country":"GB",
    "wof:name":"TN12 0ST",
    "wof:placetype":"postalcode"
},
  "geometry": {"coordinates":[0.54648902259754,51.16729769959447],"type":"Point"}
}