{
  "type": "Feature",
  "properties": {
    "iso:country":"GB",
    "wof:name":"ME12 3BB",
    "wof:placetype":"postalcode"
},
  "geometry": {"coordinates":[0.77858125478933,51.42069105777865],"type":"Point"}
}