{
  "type": "Feature",
  "properties": {
    "iso:country": "GB",
    "wof:name": "ME12 3BB",
    "wof:placetype": "postalcode"
  },
  "geometry": {"coordinates":[0.778756,51.4207],"type":"Point"}
}
