{
  "type": "Feature",
  "properties": {
    "iso:country":"GB",
    "wof:name":"B46 1AF",
    "wof:placetype":"postalcode"
},
  "geometry": {"coordinates":[-1.70488979804012,52.50129666232277],"type":"Point"}
}