{
  "type": "Feature",
  "properties": {
    "iso:country":"GB",
    "wof:name":"L39 0HR",
    "wof:placetype":"postalcode"
},
  "geometry": {"coordinates":[-2.83934668908699,53.51113710158047],"type":"Point"}
}