{
  "type": "Feature",
  "properties": {
    "iso:country":"GB",
    "wof:name":"SL4 4SH",
    "wof:placetype":"postalcode"
},
  "geometry": {"coordinates":[-0.69654304592375,51.44394414143424],"type":"Point"}
}