{
  "type": "Feature",
  "properties": {
    "iso:country": "GB",
    "wof:name": "TS17 0NY",
    "wof:placetype": "postalcode"
  },
  "geometry": {"coordinates":[-1.310219,54.506529],"type":"Point"}
}
