{
  "type": "Feature",
  "properties": {
    "iso:country":"GB",
    "wof:name":"AB16 5XU",
    "wof:placetype":"postalcode"
},
  "geometry": {"coordinates":[-2.15738649160284,57.16441133454035],"type":"Point"}
}