{
  "type": "Feature",
  "properties": {
    "date:inception_lower": "1980-01-01",
    "date:inception_upper": "1980-01-01",
    "iso:country": "GB",
    "wof:name": "BN7 2DH",
    "wof:placetype": "postalcode"
  },
  "geometry": {"coordinates":[0.009221,50.874795],"type":"Point"}
}
