{
  "type": "Feature",
  "properties": {
    "iso:country":"GB",
    "wof:name":"EX16 4NY",
    "wof:placetype":"postalcode"
},
  "geometry": {"coordinates":[-3.43795255862527,50.89293660466473],"type":"Point"}
}