{
  "type": "Feature",
  "properties": {
    "date:inception_lower": "1980-01-01",
    "date:inception_upper": "1980-01-01",
    "iso:country": "GB",
    "wof:name": "EX16 4NY",
    "wof:placetype": "postalcode"
  },
  "geometry": {"coordinates":[-3.437953,50.892937],"type":"Point"}
}
