{
  "type": "Feature",
  "properties": {
    "iso:country":"GB",
    "wof:name":"DT4 9RS",
    "wof:placetype":"postalcode"
},
  "geometry": {"coordinates":[-2.4771495931514,50.62666050600588],"type":"Point"}
}