{
  "type": "Feature",
  "properties": {
    "iso:country":"GB",
    "wof:name":"BS7 0XT",
    "wof:placetype":"postalcode"
},
  "geometry": {"coordinates":[-2.58608041795496,51.495344348033],"type":"Point"}
}