{
  "type": "Feature",
  "properties": {
    "iso:country":"GB",
    "wof:name":"L20 6NE",
    "wof:placetype":"postalcode"
},
  "geometry": {"coordinates":[-2.99006384417397,53.4676282726506],"type":"Point"}
}