{
  "type": "Feature",
  "properties": {
    "date:inception_lower": "1980-01-01",
    "date:inception_upper": "1980-01-01",
    "iso:country": "GB",
    "wof:name": "SP3 5SA",
    "wof:placetype": "postalcode"
  },
  "geometry": {"coordinates":[-2.077475,51.0863],"type":"Point"}
}
