{
  "type": "Feature",
  "properties": {
    "iso:country":"GB",
    "wof:name":"SP3 5SA",
    "wof:placetype":"postalcode"
},
  "geometry": {"coordinates":[-2.07747508873709,51.08630003555939],"type":"Point"}
}