{
  "type": "Feature",
  "properties": {
    "iso:country":"GB",
    "wof:name":"W3 0RA",
    "wof:placetype":"postalcode"
},
  "geometry": {"coordinates":[-0.27490993013202,51.52339546049223],"type":"Point"}
}