{
  "type": "Feature",
  "properties": {
    "date:inception_lower": "2018-09-01",
    "date:inception_upper": "2018-09-01",
    "iso:country": "GB",
    "wof:name": "IP9 2FN",
    "wof:placetype": "postalcode"
  },
  "geometry": {"coordinates":[1.164981,52.004797],"type":"Point"}
}
