{
  "type": "Feature",
  "properties": {
    "iso:country":"GB",
    "wof:name":"HR1 1AZ",
    "wof:placetype":"postalcode"
},
  "geometry": {"coordinates":[-2.67727960996119,52.05197403398211],"type":"Point"}
}