{
  "type": "Feature",
  "properties": {
    "iso:country":"GB",
    "wof:name":"KT14 7DD",
    "wof:placetype":"postalcode"
},
  "geometry": {"coordinates":[-0.46660718245103,51.34007943209027],"type":"Point"}
}