{
  "type": "Feature",
  "properties": {
    "iso:country": "GB",
    "wof:name": "KT14 7DD",
    "wof:placetype": "postalcode"
  },
  "geometry": {"coordinates":[-0.466607,51.340079],"type":"Point"}
}
