{
  "type": "Feature",
  "properties": {
    "iso:country": "GB",
    "wof:name": "DN20 9PF",
    "wof:placetype": "postalcode"
  },
  "geometry": {"coordinates":[-0.521783,53.511718],"type":"Point"}
}
