{
  "type": "Feature",
  "properties": {
    "date:inception_lower":"1980-01-01",
    "date:inception_upper":"1980-01-31",
    "iso:country":"GB",
    "wof:name":"DN20 9PF",
    "wof:placetype":"postalcode"
},
  "geometry": {"coordinates":[-0.521783,53.511718],"type":"Point"}
}