{
  "type": "Feature",
  "properties": {
    "iso:country":"GB",
    "wof:name":"DN20 9PF",
    "wof:placetype":"postalcode"
},
  "geometry": {"coordinates":[-0.52178275295383,53.51171788994626],"type":"Point"}
}