{
  "type": "Feature",
  "properties": {
    "iso:country": "GB",
    "wof:name": "SL1 1EE",
    "wof:placetype": "postalcode"
  },
  "geometry": {"coordinates":[-0.59938,51.510417],"type":"Point"}
}
