{
  "type": "Feature",
  "properties": {
    "date:inception_lower": "2024-04-01",
    "date:inception_upper": "2024-04-01",
    "iso:country": "GB",
    "wof:name": "NN4 0BE",
    "wof:placetype": "postalcode"
  },
  "geometry": {"coordinates":[-0.910181,52.198652],"type":"Point"}
}
