{
  "type": "Feature",
  "properties": {
    "date:inception_lower": "2006-09-01",
    "date:inception_upper": "2006-09-01",
    "iso:country": "GB",
    "wof:name": "CB22 6SL",
    "wof:placetype": "postalcode"
  },
  "geometry": {"coordinates":[0.053508,52.123433],"type":"Point"}
}
