{
  "type": "Feature",
  "properties": {
    "date:inception_lower": "2018-08-01",
    "date:inception_upper": "2018-08-01",
    "iso:country": "GB",
    "wof:name": "DT2 8GH",
    "wof:placetype": "postalcode"
  },
  "geometry": {"coordinates":[-2.346031,50.693634],"type":"Point"}
}
