{
  "type": "Feature",
  "properties": {
    "iso:country": "GB",
    "wof:name": "DT2 8GH",
    "wof:placetype": "postalcode"
  },
  "geometry": {"coordinates":[-2.347612,50.691129],"type":"Point"}
}
