{
  "type": "Feature",
  "properties": {
    "date:inception_lower":"1991-09-01",
    "date:inception_upper":"1991-09-30",
    "iso:country":"GB",
    "wof:name":"OX11 7RW",
    "wof:placetype":"postalcode"
},
  "geometry": {"coordinates":[-1.232971,51.616166],"type":"Point"}
}