{
  "type": "Feature",
  "properties": {
    "iso:country":"GB",
    "wof:name":"WV5 0JW",
    "wof:placetype":"postalcode"
},
  "geometry": {"coordinates":[-2.18980544214368,52.52703370910266],"type":"Point"}
}