{
  "type": "Feature",
  "properties": {
    "iso:country": "GB",
    "wof:name": "BA1 3NH",
    "wof:placetype": "postalcode"
  },
  "geometry": {"coordinates":[-2.389227,51.390976],"type":"Point"}
}
