{
  "type": "Feature",
  "properties": {
    "iso:country": "GB",
    "wof:name": "SG1 4GP",
    "wof:placetype": "postalcode"
  },
  "geometry": {"coordinates":[-0.169173,51.923078],"type":"Point"}
}
