{
  "type": "Feature",
  "properties": {
    "iso:country": "GB",
    "wof:name": "BH15 1UT",
    "wof:placetype": "postalcode"
  },
  "geometry": {"coordinates":[-1.977782,50.712537],"type":"Point"}
}
