{
  "type": "Feature",
  "properties": {
    "iso:country":"GB",
    "wof:name":"G75 0QL",
    "wof:placetype":"postalcode"
},
  "geometry": {"coordinates":[-4.16127500684175,55.72052803985775],"type":"Point"}
}