{
  "type": "Feature",
  "properties": {
    "date:inception_lower": "1980-01-01",
    "date:inception_upper": "1980-01-01",
    "iso:country": "GB",
    "wof:name": "G75 0QL",
    "wof:placetype": "postalcode"
  },
  "geometry": {"coordinates":[-4.161897,55.720513],"type":"Point"}
}
