{
  "type": "Feature",
  "properties": {
    "date:inception_lower": "1980-01-01",
    "date:inception_upper": "1980-01-01",
    "iso:country": "GB",
    "wof:name": "DY2 8LB",
    "wof:placetype": "postalcode"
  },
  "geometry": {"coordinates":[-2.078249,52.502103],"type":"Point"}
}
