{
  "type": "Feature",
  "properties": {
    "iso:country":"GB",
    "wof:name":"WN2 4TG",
    "wof:placetype":"postalcode"
},
  "geometry": {"coordinates":[-2.53918412196616,53.52362754289895],"type":"Point"}
}