{
  "type": "Feature",
  "properties": {
    "date:inception_lower": "1980-01-01",
    "date:inception_upper": "1980-01-01",
    "iso:country": "GB",
    "wof:name": "WN2 4TG",
    "wof:placetype": "postalcode"
  },
  "geometry": {"coordinates":[-2.539184,53.523628],"type":"Point"}
}
