{
  "type": "Feature",
  "properties": {
    "date:inception_lower": "2017-04-01",
    "date:inception_upper": "2017-04-01",
    "iso:country": "GB",
    "wof:name": "PA34 4QQ",
    "wof:placetype": "postalcode"
  },
  "geometry": {"coordinates":[-5.446683,56.377028],"type":"Point"}
}
