{
  "type": "Feature",
  "properties": {
    "iso:country":"GB",
    "wof:name":"KW15 1SZ",
    "wof:placetype":"postalcode"
},
  "geometry": {"coordinates":[-2.93686264665099,58.9786269002301],"type":"Point"}
}