{
  "type": "Feature",
  "properties": {
    "date:inception_lower": "1980-01-01",
    "date:inception_upper": "1980-01-01",
    "iso:country": "GB",
    "wof:name": "KW15 1SZ",
    "wof:placetype": "postalcode"
  },
  "geometry": {"coordinates":[-2.936863,58.978627],"type":"Point"}
}
