{
  "type": "Feature",
  "properties": {
    "iso:country":"GB",
    "wof:name":"SP6 2LD",
    "wof:placetype":"postalcode"
},
  "geometry": {"coordinates":[-1.75924865895407,50.93197854826592],"type":"Point"}
}