{
  "type": "Feature",
  "properties": {
    "date:inception_lower":"1980-01-01",
    "date:inception_upper":"1980-01-31",
    "iso:country":"GB",
    "wof:name":"SP6 2LD",
    "wof:placetype":"postalcode"
},
  "geometry": {"coordinates":[-1.759249,50.931979],"type":"Point"}
}