{
  "type": "Feature",
  "properties": {
    "iso:country":"GB",
    "wof:name":"CO9 1NN",
    "wof:placetype":"postalcode"
},
  "geometry": {"coordinates":[0.63260394764285,51.93680164017454],"type":"Point"}
}