{
  "type": "Feature",
  "properties": {
    "iso:country": "GB",
    "wof:name": "CO9 1NN",
    "wof:placetype": "postalcode"
  },
  "geometry": {"coordinates":[0.632604,51.936802],"type":"Point"}
}
