{
  "type": "Feature",
  "properties": {
    "date:inception_lower": "1980-01-01",
    "date:inception_upper": "1980-01-01",
    "iso:country": "GB",
    "wof:name": "HU7 5AL",
    "wof:placetype": "postalcode"
  },
  "geometry": {"coordinates":[-0.328166,53.803128],"type":"Point"}
}
