{
  "type": "Feature",
  "properties": {
    "iso:country":"GB",
    "wof:name":"HU7 5AL",
    "wof:placetype":"postalcode"
},
  "geometry": {"coordinates":[-0.32789931633826,53.80314949125524],"type":"Point"}
}