{
  "type": "Feature",
  "properties": {
    "iso:country": "GB",
    "wof:name": "TR14 8TT",
    "wof:placetype": "postalcode"
  },
  "geometry": {"coordinates":[-5.300879,50.212846],"type":"Point"}
}
