{
  "type": "Feature",
  "properties": {
    "iso:country":"GB",
    "wof:name":"TR14 8TT",
    "wof:placetype":"postalcode"
},
  "geometry": {"coordinates":[-5.30082959811099,50.21284718194826],"type":"Point"}
}