{
  "type": "Feature",
  "properties": {
    "iso:country":"GB",
    "wof:name":"CV21 4LB",
    "wof:placetype":"postalcode"
},
  "geometry": {"coordinates":[-1.22252083303581,52.36023931102889],"type":"Point"}
}