{
  "type": "Feature",
  "properties": {
    "iso:country": "GB",
    "wof:name": "NR2 1AR",
    "wof:placetype": "postalcode"
  },
  "geometry": {"coordinates":[1.294544,52.629788],"type":"Point"}
}
