{
  "type": "Feature",
  "properties": {
    "iso:country":"GB",
    "wof:name":"NR2 1AR",
    "wof:placetype":"postalcode"
},
  "geometry": {"coordinates":[1.29454397549893,52.62978756462768],"type":"Point"}
}