{
  "type": "Feature",
  "properties": {
    "iso:country":"GB",
    "wof:name":"WV4 4YH",
    "wof:placetype":"postalcode"
},
  "geometry": {"coordinates":[-2.17674985511203,52.56832642525211],"type":"Point"}
}