{
  "type": "Feature",
  "properties": {
    "iso:country":"GB",
    "wof:name":"IP17 1JY",
    "wof:placetype":"postalcode"
},
  "geometry": {"coordinates":[1.46312273009634,52.1916131019386],"type":"Point"}
}