{
  "type": "Feature",
  "properties": {
    "iso:country": "GB",
    "wof:name": "NN11 4GD",
    "wof:placetype": "postalcode"
  },
  "geometry": {"coordinates":[-1.156814,52.257945],"type":"Point"}
}
