{
  "type": "Feature",
  "properties": {
    "iso:country":"GB",
    "wof:name":"NN11 4GD",
    "wof:placetype":"postalcode"
},
  "geometry": {"coordinates":[-1.15681400074034,52.25794492552868],"type":"Point"}
}