{
  "type": "Feature",
  "properties": {
    "date:inception_lower": "1980-01-01",
    "date:inception_upper": "1980-01-01",
    "iso:country": "GB",
    "wof:name": "BL8 3LT",
    "wof:placetype": "postalcode"
  },
  "geometry": {"coordinates":[-2.33932,53.611718],"type":"Point"}
}
