{
  "type": "Feature",
  "properties": {
    "date:inception_lower": "2007-01-01",
    "date:inception_upper": "2007-01-01",
    "iso:country": "GB",
    "wof:name": "HA9 6JA",
    "wof:placetype": "postalcode"
  },
  "geometry": {"coordinates":[-0.273199,51.548054],"type":"Point"}
}
