{
  "type": "Feature",
  "properties": {
    "iso:country":"GB",
    "wof:name":"HA9 6JA",
    "wof:placetype":"postalcode"
},
  "geometry": {"coordinates":[-0.27319857662077,51.54805422259749],"type":"Point"}
}