{
  "type": "Feature",
  "properties": {
    "date:inception_lower": "2021-04-01",
    "date:inception_upper": "2021-04-01",
    "iso:country": "GB",
    "wof:name": "PE21 9FA",
    "wof:placetype": "postalcode"
  },
  "geometry": {"coordinates":[-0.002661,52.978512],"type":"Point"}
}
