{
  "type": "Feature",
  "properties": {
    "date:inception_lower":"1982-03-01",
    "date:inception_upper":"1982-03-31",
    "iso:country":"GB",
    "wof:name":"NG31 8BS",
    "wof:placetype":"postalcode"
},
  "geometry": {"coordinates":[-0.643339,52.930385],"type":"Point"}
}