{
  "type": "Feature",
  "properties": {
    "iso:country":"GB",
    "wof:name":"NG31 8BS",
    "wof:placetype":"postalcode"
},
  "geometry": {"coordinates":[-0.64333875165998,52.9303852346721],"type":"Point"}
}