{
  "type": "Feature",
  "properties": {
    "iso:country":"GB",
    "wof:name":"DG6 4XY",
    "wof:placetype":"postalcode"
},
  "geometry": {"coordinates":[-4.04036588313296,54.83711581243264],"type":"Point"}
}