{
  "type": "Feature",
  "properties": {
    "iso:country":"GB",
    "wof:name":"SA17 5UT",
    "wof:placetype":"postalcode"
},
  "geometry": {"coordinates":[-4.35630387081271,51.76737998893569],"type":"Point"}
}