{
  "type": "Feature",
  "properties": {
    "date:inception_lower":"2018-10-01",
    "date:inception_upper":"2018-10-31",
    "iso:country":"GB",
    "wof:name":"NG1 3EU",
    "wof:placetype":"postalcode"
},
  "geometry": {"coordinates":[-1.148355,52.955584],"type":"Point"}
}