{
  "type": "Feature",
  "properties": {
    "iso:country":"GB",
    "wof:name":"TW8 8HE",
    "wof:placetype":"postalcode"
},
  "geometry": {"coordinates":[-0.30969714830048,51.48123324020101],"type":"Point"}
}