{
  "type": "Feature",
  "properties": {
    "date:inception_lower": "1980-01-01",
    "date:inception_upper": "1980-01-01",
    "iso:country": "GB",
    "wof:name": "HA5 1EQ",
    "wof:placetype": "postalcode"
  },
  "geometry": {"coordinates":[-0.385737,51.588236],"type":"Point"}
}
