{
  "type": "Feature",
  "properties": {
    "iso:country": "GB",
    "wof:name": "PH1 2RD",
    "wof:placetype": "postalcode"
  },
  "geometry": {"coordinates":[-3.459575,56.413263],"type":"Point"}
}
