{
  "type": "Feature",
  "properties": {
    "iso:country":"GB",
    "wof:name":"PH1 2RD",
    "wof:placetype":"postalcode"
},
  "geometry": {"coordinates":[-3.45957526044895,56.41326305477648],"type":"Point"}
}