{
  "type": "Feature",
  "properties": {
    "iso:country":"GB",
    "wof:name":"G72 8XL",
    "wof:placetype":"postalcode"
},
  "geometry": {"coordinates":[-4.13805436395713,55.80777905853179],"type":"Point"}
}