{
  "type": "Feature",
  "properties": {
    "date:inception_lower": "1980-01-01",
    "date:inception_upper": "1980-01-01",
    "iso:country": "GB",
    "wof:name": "TD2 6QA",
    "wof:placetype": "postalcode"
  },
  "geometry": {"coordinates":[-2.797249,55.721656],"type":"Point"}
}
