{
  "type": "Feature",
  "properties": {
    "iso:country":"GB",
    "wof:name":"TS6 9LL",
    "wof:placetype":"postalcode"
},
  "geometry": {"coordinates":[-1.13442119218736,54.56139827036601],"type":"Point"}
}