{
  "type": "Feature",
  "properties": {
    "iso:country": "GB",
    "wof:name": "TS6 9LL",
    "wof:placetype": "postalcode"
  },
  "geometry": {"coordinates":[-1.134421,54.561398],"type":"Point"}
}
