{
  "type": "Feature",
  "properties": {
    "iso:country":"GB",
    "wof:name":"BA13 3HD",
    "wof:placetype":"postalcode"
},
  "geometry": {"coordinates":[-2.18421652599151,51.25950073572753],"type":"Point"}
}