{
  "type": "Feature",
  "properties": {
    "date:inception_lower": "1980-01-01",
    "date:inception_upper": "1980-01-01",
    "iso:country": "GB",
    "wof:name": "BA13 3HD",
    "wof:placetype": "postalcode"
  },
  "geometry": {"coordinates":[-2.184216,51.259501],"type":"Point"}
}
