{
  "type": "Feature",
  "properties": {
    "iso:country":"GB",
    "wof:name":"CO6 4DW",
    "wof:placetype":"postalcode"
},
  "geometry": {"coordinates":[0.83662361544256,51.95048714158518],"type":"Point"}
}