{
  "type": "Feature",
  "properties": {
    "iso:country": "GB",
    "wof:name": "CO6 4DW",
    "wof:placetype": "postalcode"
  },
  "geometry": {"coordinates":[0.837979,51.951168],"type":"Point"}
}
