{
  "type": "Feature",
  "properties": {
    "iso:country": "GB",
    "wof:name": "SE10 8AD",
    "wof:placetype": "postalcode"
  },
  "geometry": {"coordinates":[-0.011132,51.472269],"type":"Point"}
}
