{
  "type": "Feature",
  "properties": {
    "iso:country":"GB",
    "wof:name":"N16 8BU",
    "wof:placetype":"postalcode"
},
  "geometry": {"coordinates":[-0.07510190252231,51.55515984272071],"type":"Point"}
}