{
  "type": "Feature",
  "properties": {
    "iso:country":"GB",
    "wof:name":"W13 9HZ",
    "wof:placetype":"postalcode"
},
  "geometry": {"coordinates":[-0.3221165392159,51.50816379342371],"type":"Point"}
}