{
  "type": "Feature",
  "properties": {
    "date:inception_lower": "1999-06-01",
    "date:inception_upper": "1999-06-01",
    "iso:country": "GB",
    "wof:name": "CH65 7BP",
    "wof:placetype": "postalcode"
  },
  "geometry": {"coordinates":[-2.921588,53.274402],"type":"Point"}
}
