{
  "type": "Feature",
  "properties": {
    "iso:country": "GB",
    "wof:name": "HP11 2AT",
    "wof:placetype": "postalcode"
  },
  "geometry": {"coordinates":[-0.759351,51.630155],"type":"Point"}
}
