{
  "type": "Feature",
  "properties": {
    "iso:country":"GB",
    "wof:name":"LA1 1RE",
    "wof:placetype":"postalcode"
},
  "geometry": {"coordinates":[-2.80165189267885,54.04705056109728],"type":"Point"}
}