{
  "type": "Feature",
  "properties": {
    "date:inception_lower": "2019-02-01",
    "date:inception_upper": "2019-02-01",
    "iso:country": "GB",
    "wof:name": "GL51 0QX",
    "wof:placetype": "postalcode"
  },
  "geometry": {"coordinates":[-2.117083,51.914254],"type":"Point"}
}
