{
  "type": "Feature",
  "properties": {
    "iso:country":"GB",
    "wof:name":"CV35 0EG",
    "wof:placetype":"postalcode"
},
  "geometry": {"coordinates":[-1.49628090826205,52.1716212288315],"type":"Point"}
}