{
  "type": "Feature",
  "properties": {
    "iso:country": "GB",
    "wof:name": "CV35 0EG",
    "wof:placetype": "postalcode"
  },
  "geometry": {"coordinates":[-1.496281,52.171621],"type":"Point"}
}
