{
  "type": "Feature",
  "properties": {
    "iso:country":"GB",
    "wof:name":"E15 2FY",
    "wof:placetype":"postalcode"
},
  "geometry": {"coordinates":[-0.00663691095595,51.53506911509373],"type":"Point"}
}