{
  "type": "Feature",
  "properties": {
    "iso:country":"GB",
    "wof:name":"CW6 0JF",
    "wof:placetype":"postalcode"
},
  "geometry": {"coordinates":[-2.67352420720216,53.17043159364076],"type":"Point"}
}