{
  "type": "Feature",
  "properties": {
    "iso:country": "GB",
    "wof:name": "CW6 0JF",
    "wof:placetype": "postalcode"
  },
  "geometry": {"coordinates":[-2.673524,53.170432],"type":"Point"}
}
