{
  "type": "Feature",
  "properties": {
    "date:inception_lower":"1990-08-01",
    "date:inception_upper":"1990-08-31",
    "iso:country":"GB",
    "wof:name":"AB41 9GR",
    "wof:placetype":"postalcode"
},
  "geometry": {"coordinates":[-2.059038,57.368299],"type":"Point"}
}