{
  "type": "Feature",
  "properties": {
    "iso:country":"GB",
    "wof:name":"RH13 5PW",
    "wof:placetype":"postalcode"
},
  "geometry": {"coordinates":[-0.30842416948482,51.05779515938431],"type":"Point"}
}