{
  "type": "Feature",
  "properties": {
    "iso:country": "GB",
    "wof:name": "RH13 5PW",
    "wof:placetype": "postalcode"
  },
  "geometry": {"coordinates":[-0.308424,51.057795],"type":"Point"}
}
