{
  "type": "Feature",
  "properties": {
    "iso:country": "GB",
    "wof:name": "TR10 9BL",
    "wof:placetype": "postalcode"
  },
  "geometry": {"coordinates":[-5.139126,50.141381],"type":"Point"}
}
