{
  "type": "Feature",
  "properties": {
    "iso:country":"GB",
    "wof:name":"TR10 9BL",
    "wof:placetype":"postalcode"
},
  "geometry": {"coordinates":[-5.13912564916839,50.14138063722218],"type":"Point"}
}