{
  "type": "Feature",
  "properties": {
    "iso:country": "GB",
    "wof:name": "G31 1RE",
    "wof:placetype": "postalcode"
  },
  "geometry": {"coordinates":[-4.219203,55.858216],"type":"Point"}
}
