{
  "type": "Feature",
  "properties": {
    "iso:country":"GB",
    "wof:name":"G31 1RE",
    "wof:placetype":"postalcode"
},
  "geometry": {"coordinates":[-4.21920313468182,55.85821614531743],"type":"Point"}
}