{
  "type": "Feature",
  "properties": {
    "iso:country":"GB",
    "wof:name":"CM2 9TR",
    "wof:placetype":"postalcode"
},
  "geometry": {"coordinates":[0.4827126613642,51.71979549345529],"type":"Point"}
}