{
  "type": "Feature",
  "properties": {
    "iso:country":"GB",
    "wof:name":"B32 4DU",
    "wof:placetype":"postalcode"
},
  "geometry": {"coordinates":[-2.01248781825276,52.43388784829063],"type":"Point"}
}