{
  "type": "Feature",
  "properties": {
    "iso:country":"GB",
    "wof:name":"TN3 0AQ",
    "wof:placetype":"postalcode"
},
  "geometry": {"coordinates":[0.21861180445647,51.14535194532698],"type":"Point"}
}