{
  "type": "Feature",
  "properties": {
    "date:inception_lower": "2008-05-01",
    "date:inception_upper": "2008-05-01",
    "iso:country": "GB",
    "wof:name": "TN3 0AQ",
    "wof:placetype": "postalcode"
  },
  "geometry": {"coordinates":[0.218639,51.145349],"type":"Point"}
}
