{
  "type": "Feature",
  "properties": {
    "iso:country": "GB",
    "wof:name": "EN8 7JU",
    "wof:placetype": "postalcode"
  },
  "geometry": {"coordinates":[-0.032928,51.687022],"type":"Point"}
}
