{
  "type": "Feature",
  "properties": {
    "iso:country": "GB",
    "wof:name": "PA23 7RR",
    "wof:placetype": "postalcode"
  },
  "geometry": {"coordinates":[-4.929744,55.959922],"type":"Point"}
}
