{
  "type": "Feature",
  "properties": {
    "iso:country":"GB",
    "wof:name":"CM6 1GH",
    "wof:placetype":"postalcode"
},
  "geometry": {"coordinates":[0.27825271014436,51.86814558045099],"type":"Point"}
}