{
  "type": "Feature",
  "properties": {
    "iso:country":"GB",
    "wof:name":"W1T 4PY",
    "wof:placetype":"postalcode"
},
  "geometry": {"coordinates":[-0.1371601092457,51.52054237336205],"type":"Point"}
}