{
  "type": "Feature",
  "properties": {
    "iso:country": "GB",
    "wof:name": "W1T 4PY",
    "wof:placetype": "postalcode"
  },
  "geometry": {"coordinates":[-0.137135,51.520544],"type":"Point"}
}
