{
  "type": "Feature",
  "properties": {
    "iso:country":"GB",
    "wof:name":"LS27 8LL",
    "wof:placetype":"postalcode"
},
  "geometry": {"coordinates":[-1.59791318323548,53.75403500509265],"type":"Point"}
}