{
  "type": "Feature",
  "properties": {
    "date:inception_lower": "2023-03-01",
    "date:inception_upper": "2023-03-01",
    "iso:country": "GB",
    "wof:name": "IV30 8BJ",
    "wof:placetype": "postalcode"
  },
  "geometry": {"coordinates":[-3.304626,57.62751],"type":"Point"}
}
