{
  "type": "Feature",
  "properties": {
    "date:inception_lower": "2018-01-01",
    "date:inception_upper": "2018-01-01",
    "iso:country": "GB",
    "wof:name": "LA12 7FT",
    "wof:placetype": "postalcode"
  },
  "geometry": {"coordinates":[-3.08818,54.197909],"type":"Point"}
}
