{
  "type": "Feature",
  "properties": {
    "iso:country":"GB",
    "wof:name":"CV23 9PU",
    "wof:placetype":"postalcode"
},
  "geometry": {"coordinates":[-1.41501673419777,52.33380228980125],"type":"Point"}
}