{
  "type": "Feature",
  "properties": {
    "iso:country":"GB",
    "wof:name":"SG1 4HN",
    "wof:placetype":"postalcode"
},
  "geometry": {"coordinates":[-0.18750832936095,51.92098793135603],"type":"Point"}
}