{
  "type": "Feature",
  "properties": {
    "iso:country":"GB",
    "wof:name":"HD9 2SQ",
    "wof:placetype":"postalcode"
},
  "geometry": {"coordinates":[-1.78995684944633,53.55658703435612],"type":"Point"}
}