{
  "type": "Feature",
  "properties": {
    "iso:country":"GB",
    "wof:name":"BN24 5BP",
    "wof:placetype":"postalcode"
},
  "geometry": {"coordinates":[0.27822752244662,50.8338860901853],"type":"Point"}
}