{
  "type": "Feature",
  "properties": {
    "iso:country":"GB",
    "wof:name":"ME5 9TX",
    "wof:placetype":"postalcode"
},
  "geometry": {"coordinates":[0.51472306725612,51.35357031957848],"type":"Point"}
}