{
  "type": "Feature",
  "properties": {
    "iso:country":"GB",
    "wof:name":"BS13 8HP",
    "wof:placetype":"postalcode"
},
  "geometry": {"coordinates":[-2.6251487517076,51.41231141699062],"type":"Point"}
}