{
  "type": "Feature",
  "properties": {
    "iso:country": "GB",
    "wof:name": "NG21 9JU",
    "wof:placetype": "postalcode"
  },
  "geometry": {"coordinates":[-1.065922,53.194925],"type":"Point"}
}
