{
  "type": "Feature",
  "properties": {
    "iso:country":"GB",
    "wof:name":"HD4 5EX",
    "wof:placetype":"postalcode"
},
  "geometry": {"coordinates":[-1.80716594088506,53.63289948407766],"type":"Point"}
}