{
  "type": "Feature",
  "properties": {
    "iso:country":"GB",
    "wof:name":"HD4 6TD",
    "wof:placetype":"postalcode"
},
  "geometry": {"coordinates":[-1.76964347891289,53.62522021371161],"type":"Point"}
}