{
  "type": "Feature",
  "properties": {
    "iso:country": "GB",
    "wof:name": "DY8 2XE",
    "wof:placetype": "postalcode"
  },
  "geometry": {"coordinates":[-2.152691,52.420916],"type":"Point"}
}
