{
  "type": "Feature",
  "properties": {
    "date:inception_lower": "1980-01-01",
    "date:inception_upper": "1980-01-01",
    "iso:country": "GB",
    "wof:name": "DY8 2XE",
    "wof:placetype": "postalcode"
  },
  "geometry": {"coordinates":[-2.152691,52.420916],"type":"Point"}
}
