{
  "type": "Feature",
  "properties": {
    "iso:country":"GB",
    "wof:name":"DY8 2XE",
    "wof:placetype":"postalcode"
},
  "geometry": {"coordinates":[-2.15269066045764,52.42091587924463],"type":"Point"}
}