{
  "type": "Feature",
  "properties": {
    "iso:country":"GB",
    "wof:name":"E16 3TE",
    "wof:placetype":"postalcode"
},
  "geometry": {"coordinates":[0.04118252369403,51.51552392038234],"type":"Point"}
}