{
  "type": "Feature",
  "properties": {
    "iso:country": "GB",
    "wof:name": "SW19 1HZ",
    "wof:placetype": "postalcode"
  },
  "geometry": {"coordinates":[-0.189943,51.416543],"type":"Point"}
}
