{
  "type": "Feature",
  "properties": {
    "iso:country":"GB",
    "wof:name":"RG1 4PZ",
    "wof:placetype":"postalcode"
},
  "geometry": {"coordinates":[-0.95395853203429,51.45243971430742],"type":"Point"}
}