{
  "type": "Feature",
  "properties": {
    "iso:country": "GB",
    "wof:name": "RG1 4PZ",
    "wof:placetype": "postalcode"
  },
  "geometry": {"coordinates":[-0.953958,51.45244],"type":"Point"}
}
