{
  "type": "Feature",
  "properties": {
    "iso:country": "GB",
    "wof:name": "B12 9TS",
    "wof:placetype": "postalcode"
  },
  "geometry": {"coordinates":[-1.890463,52.458093],"type":"Point"}
}
