{
  "type": "Feature",
  "properties": {
    "iso:country":"GB",
    "wof:name":"B12 9TS",
    "wof:placetype":"postalcode"
},
  "geometry": {"coordinates":[-1.89046316871653,52.45809311182404],"type":"Point"}
}