{
  "type": "Feature",
  "properties": {
    "iso:country":"GB",
    "wof:name":"OX4 2PG",
    "wof:placetype":"postalcode"
},
  "geometry": {"coordinates":[-1.18490611671023,51.72967372733554],"type":"Point"}
}