{
  "type": "Feature",
  "properties": {
    "iso:country": "GB",
    "wof:name": "CH4 8DB",
    "wof:placetype": "postalcode"
  },
  "geometry": {"coordinates":[-2.920079,53.175479],"type":"Point"}
}
