{
  "type": "Feature",
  "properties": {
    "iso:country":"GB",
    "wof:name":"CH4 8DB",
    "wof:placetype":"postalcode"
},
  "geometry": {"coordinates":[-2.92007944572077,53.17547877817245],"type":"Point"}
}