{
  "type": "Feature",
  "properties": {
    "date:inception_lower":"1983-07-01",
    "date:inception_upper":"1983-07-31",
    "iso:country":"GB",
    "wof:name":"CH4 8DB",
    "wof:placetype":"postalcode"
},
  "geometry": {"coordinates":[-2.920079,53.175479],"type":"Point"}
}