{
  "type": "Feature",
  "properties": {
    "iso:country":"GB",
    "wof:name":"LL75 8YF",
    "wof:placetype":"postalcode"
},
  "geometry": {"coordinates":[-4.21128544011993,53.28375886007109],"type":"Point"}
}