{
  "type": "Feature",
  "properties": {
    "iso:country":"GB",
    "wof:name":"SO15 2TE",
    "wof:placetype":"postalcode"
},
  "geometry": {"coordinates":[-1.40843577028269,50.91621535025214],"type":"Point"}
}