{
  "type": "Feature",
  "properties": {
    "iso:country":"GB",
    "wof:name":"YO25 5HG",
    "wof:placetype":"postalcode"
},
  "geometry": {"coordinates":[-0.44089725120788,54.01154005416212],"type":"Point"}
}