{
  "type": "Feature",
  "properties": {
    "date:inception_lower": "1998-06-01",
    "date:inception_upper": "1998-06-01",
    "iso:country": "GB",
    "wof:name": "YO25 5HG",
    "wof:placetype": "postalcode"
  },
  "geometry": {"coordinates":[-0.440897,54.01154],"type":"Point"}
}
