{
  "type": "Feature",
  "properties": {
    "iso:country":"GB",
    "wof:name":"DN6 8PA",
    "wof:placetype":"postalcode"
},
  "geometry": {"coordinates":[-1.20494665294506,53.59054299120474],"type":"Point"}
}