{
  "type": "Feature",
  "properties": {
    "iso:country":"GB",
    "wof:name":"CH63 0LR",
    "wof:placetype":"postalcode"
},
  "geometry": {"coordinates":[-2.98816746545351,53.31907457233977],"type":"Point"}
}