{
  "type": "Feature",
  "properties": {
    "date:inception_lower":"1980-01-01",
    "date:inception_upper":"1980-01-31",
    "iso:country":"GB",
    "wof:name":"SK17 6TX",
    "wof:placetype":"postalcode"
},
  "geometry": {"coordinates":[-1.944043,53.249889],"type":"Point"}
}