{
  "type": "Feature",
  "properties": {
    "iso:country":"GB",
    "wof:name":"ML9 2SL",
    "wof:placetype":"postalcode"
},
  "geometry": {"coordinates":[-3.95462077515952,55.73080386929873],"type":"Point"}
}