{
  "type": "Feature",
  "properties": {
    "date:inception_lower": "1980-01-01",
    "date:inception_upper": "1980-01-01",
    "iso:country": "GB",
    "wof:name": "ML9 2SL",
    "wof:placetype": "postalcode"
  },
  "geometry": {"coordinates":[-3.954621,55.730804],"type":"Point"}
}
