{
  "type": "Feature",
  "properties": {
    "iso:country":"GB",
    "wof:name":"LS27 0FL",
    "wof:placetype":"postalcode"
},
  "geometry": {"coordinates":[-1.61728323994676,53.73700301446502],"type":"Point"}
}