{
  "type": "Feature",
  "properties": {
    "iso:country": "GB",
    "wof:name": "LS27 0FL",
    "wof:placetype": "postalcode"
  },
  "geometry": {"coordinates":[-1.616789,53.736702],"type":"Point"}
}
