{
  "type": "Feature",
  "properties": {
    "iso:country":"GB",
    "wof:name":"ST2 8LY",
    "wof:placetype":"postalcode"
},
  "geometry": {"coordinates":[-2.12146083002606,53.033277791781],"type":"Point"}
}