{
  "type": "Feature",
  "properties": {
    "iso:country":"GB",
    "wof:name":"B79 8TS",
    "wof:placetype":"postalcode"
},
  "geometry": {"coordinates":[-1.6854715947278,52.64404148691558],"type":"Point"}
}