{
  "type": "Feature",
  "properties": {
    "date:inception_lower":"2000-12-01",
    "date:inception_upper":"2000-12-31",
    "iso:country":"GB",
    "wof:name":"ST5 7XE",
    "wof:placetype":"postalcode"
},
  "geometry": {"coordinates":[-2.243712,53.054987],"type":"Point"}
}