{
  "type": "Feature",
  "properties": {
    "date:inception_lower": "2000-12-01",
    "date:inception_upper": "2000-12-01",
    "iso:country": "GB",
    "wof:name": "ST5 7XE",
    "wof:placetype": "postalcode"
  },
  "geometry": {"coordinates":[-2.243711,53.054923],"type":"Point"}
}
