{
  "type": "Feature",
  "properties": {
    "iso:country": "GB",
    "wof:name": "GL3 4TB",
    "wof:placetype": "postalcode"
  },
  "geometry": {"coordinates":[-2.140221,51.841986],"type":"Point"}
}
