{
  "type": "Feature",
  "properties": {
    "iso:country":"GB",
    "wof:name":"GL3 4TB",
    "wof:placetype":"postalcode"
},
  "geometry": {"coordinates":[-2.14028452162333,51.84196113681624],"type":"Point"}
}