{
  "type": "Feature",
  "properties": {
    "iso:country":"GB",
    "wof:name":"CV6 1DF",
    "wof:placetype":"postalcode"
},
  "geometry": {"coordinates":[-1.53692158494796,52.41726822006128],"type":"Point"}
}