{
  "type": "Feature",
  "properties": {
    "iso:country":"GB",
    "wof:name":"NP26 5BB",
    "wof:placetype":"postalcode"
},
  "geometry": {"coordinates":[-2.7583288635029,51.60340649397442],"type":"Point"}
}