{
  "type": "Feature",
  "properties": {
    "iso:country": "GB",
    "wof:name": "CV9 2RF",
    "wof:placetype": "postalcode"
  },
  "geometry": {"coordinates":[-1.543878,52.558115],"type":"Point"}
}
