{
  "type": "Feature",
  "properties": {
    "iso:country":"GB",
    "wof:name":"CV9 2RF",
    "wof:placetype":"postalcode"
},
  "geometry": {"coordinates":[-1.54387806488357,52.55811490515996],"type":"Point"}
}