{
  "type": "Feature",
  "properties": {
    "iso:country":"GB",
    "wof:name":"M28 2PX",
    "wof:placetype":"postalcode"
},
  "geometry": {"coordinates":[-2.38149373922571,53.49779996204666],"type":"Point"}
}