{
  "type": "Feature",
  "properties": {
    "iso:country":"GB",
    "wof:name":"ME12 1QZ",
    "wof:placetype":"postalcode"
},
  "geometry": {"coordinates":[0.76057945206661,51.43585765185509],"type":"Point"}
}