{
  "type": "Feature",
  "properties": {
    "date:inception_lower": "1993-01-01",
    "date:inception_upper": "1993-01-01",
    "iso:country": "GB",
    "wof:name": "ME12 1QZ",
    "wof:placetype": "postalcode"
  },
  "geometry": {"coordinates":[0.760594,51.435852],"type":"Point"}
}
