{
  "type": "Feature",
  "properties": {
    "date:inception_lower":"2009-04-01",
    "date:inception_upper":"2009-04-30",
    "iso:country":"GB",
    "wof:name":"SW11 2BL",
    "wof:placetype":"postalcode"
},
  "geometry": {"coordinates":[-0.176209,51.463865],"type":"Point"}
}