{
  "type": "Feature",
  "properties": {
    "iso:country":"GB",
    "wof:name":"SW11 2BL",
    "wof:placetype":"postalcode"
},
  "geometry": {"coordinates":[-0.17620879911414,51.46386483841812],"type":"Point"}
}