{
  "type": "Feature",
  "properties": {
    "iso:country":"GB",
    "wof:name":"EX34 0LH",
    "wof:placetype":"postalcode"
},
  "geometry": {"coordinates":[-4.0251229277735,51.19987202573719],"type":"Point"}
}