{
  "type": "Feature",
  "properties": {
    "iso:country": "GB",
    "wof:name": "DN6 8RB",
    "wof:placetype": "postalcode"
  },
  "geometry": {"coordinates":[-1.207577,53.588826],"type":"Point"}
}
