{
  "type": "Feature",
  "properties": {
    "iso:country":"GB",
    "wof:name":"DN6 8RB",
    "wof:placetype":"postalcode"
},
  "geometry": {"coordinates":[-1.20757730511513,53.58882565147343],"type":"Point"}
}