{
  "type": "Feature",
  "properties": {
    "iso:country":"GB",
    "wof:name":"IG11 8AS",
    "wof:placetype":"postalcode"
},
  "geometry": {"coordinates":[0.07582095322109,51.53557229582743],"type":"Point"}
}