{
  "type": "Feature",
  "properties": {
    "iso:country":"GB",
    "wof:name":"SW1P 1QF",
    "wof:placetype":"postalcode"
},
  "geometry": {"coordinates":[-0.13852704270964,51.49585264107778],"type":"Point"}
}