{
  "type": "Feature",
  "properties": {
    "date:inception_lower":"2008-01-01",
    "date:inception_upper":"2008-01-31",
    "iso:country":"GB",
    "wof:name":"NN6 0FG",
    "wof:placetype":"postalcode"
},
  "geometry": {"coordinates":[-0.755766,52.265962],"type":"Point"}
}