{
  "type": "Feature",
  "properties": {
    "iso:country":"GB",
    "wof:name":"NN6 0FG",
    "wof:placetype":"postalcode"
},
  "geometry": {"coordinates":[-0.75576577286168,52.2659624714348],"type":"Point"}
}