{
  "type": "Feature",
  "properties": {
    "iso:country":"GB",
    "wof:name":"CV9 1AZ",
    "wof:placetype":"postalcode"
},
  "geometry": {"coordinates":[-1.54830933460214,52.57763096742673],"type":"Point"}
}