{
  "type": "Feature",
  "properties": {
    "iso:country": "GB",
    "wof:name": "EH14 1LS",
    "wof:placetype": "postalcode"
  },
  "geometry": {"coordinates":[-3.244672,55.92317],"type":"Point"}
}
