{
  "type": "Feature",
  "properties": {
    "date:inception_lower": "1980-01-01",
    "date:inception_upper": "1980-01-01",
    "iso:country": "GB",
    "wof:name": "EH14 1LS",
    "wof:placetype": "postalcode"
  },
  "geometry": {"coordinates":[-3.244672,55.92317],"type":"Point"}
}
