{
  "type": "Feature",
  "properties": {
    "iso:country":"GB",
    "wof:name":"NN7 1BA",
    "wof:placetype":"postalcode"
},
  "geometry": {"coordinates":[-0.79811114489779,52.22167175691848],"type":"Point"}
}