{
  "type": "Feature",
  "properties": {
    "iso:country":"GB",
    "wof:name":"DT4 8PN",
    "wof:placetype":"postalcode"
},
  "geometry": {"coordinates":[-2.45392452740169,50.60937909815443],"type":"Point"}
}