{
  "type": "Feature",
  "properties": {
    "iso:country": "GB",
    "wof:name": "DT4 8PN",
    "wof:placetype": "postalcode"
  },
  "geometry": {"coordinates":[-2.453949,50.609377],"type":"Point"}
}
