{
  "type": "Feature",
  "properties": {
    "iso:country": "GB",
    "wof:name": "TS3 9GY",
    "wof:placetype": "postalcode"
  },
  "geometry": {"coordinates":[-1.183827,54.563898],"type":"Point"}
}
