{
  "type": "Feature",
  "properties": {
    "iso:country":"GB",
    "wof:name":"YO32 3EB",
    "wof:placetype":"postalcode"
},
  "geometry": {"coordinates":[-1.0727878230452,54.01439734226894],"type":"Point"}
}