{
  "type": "Feature",
  "properties": {
    "iso:country": "GB",
    "wof:name": "YO32 3EB",
    "wof:placetype": "postalcode"
  },
  "geometry": {"coordinates":[-1.072788,54.014397],"type":"Point"}
}
