{
  "type": "Feature",
  "properties": {
    "iso:country":"GB",
    "wof:name":"BR1 2PE",
    "wof:placetype":"postalcode"
},
  "geometry": {"coordinates":[0.03691582854456,51.40753175206868],"type":"Point"}
}