{
  "type": "Feature",
  "properties": {
    "iso:country": "GB",
    "wof:name": "LE7 7LT",
    "wof:placetype": "postalcode"
  },
  "geometry": {"coordinates":[-1.130899,52.723387],"type":"Point"}
}
