{
  "type": "Feature",
  "properties": {
    "date:inception_lower":"1996-12-01",
    "date:inception_upper":"1996-12-31",
    "iso:country":"GB",
    "wof:name":"LE7 7LT",
    "wof:placetype":"postalcode"
},
  "geometry": {"coordinates":[-1.130899,52.723387],"type":"Point"}
}