{
  "type": "Feature",
  "properties": {
    "iso:country":"GB",
    "wof:name":"LE7 7LT",
    "wof:placetype":"postalcode"
},
  "geometry": {"coordinates":[-1.13089946173059,52.72338690394602],"type":"Point"}
}