{
  "type": "Feature",
  "properties": {
    "iso:country":"GB",
    "wof:name":"SK3 0JJ",
    "wof:placetype":"postalcode"
},
  "geometry": {"coordinates":[-2.1857097990972,53.40180035560863],"type":"Point"}
}