{
  "type": "Feature",
  "properties": {
    "iso:country": "GB",
    "wof:name": "CT3 1BQ",
    "wof:placetype": "postalcode"
  },
  "geometry": {"coordinates":[1.212825,51.27008],"type":"Point"}
}
