{
  "type": "Feature",
  "properties": {
    "iso:country":"GB",
    "wof:name":"CO5 9NT",
    "wof:placetype":"postalcode"
},
  "geometry": {"coordinates":[0.70237181434132,51.84240966316735],"type":"Point"}
}