{
  "type": "Feature",
  "properties": {
    "iso:country":"GB",
    "wof:name":"NN15 5RR",
    "wof:placetype":"postalcode"
},
  "geometry": {"coordinates":[-0.68499801325936,52.36013855587775],"type":"Point"}
}