{
  "type": "Feature",
  "properties": {
    "iso:country":"GB",
    "wof:name":"PE20 1AX",
    "wof:placetype":"postalcode"
},
  "geometry": {"coordinates":[-0.0207212339977,52.93352147337618],"type":"Point"}
}