{
  "type": "Feature",
  "properties": {
    "iso:country":"GB",
    "wof:name":"NE32 4PD",
    "wof:placetype":"postalcode"
},
  "geometry": {"coordinates":[-1.48416229823673,54.95155366322464],"type":"Point"}
}