{
  "type": "Feature",
  "properties": {
    "date:inception_lower": "1980-01-01",
    "date:inception_upper": "1980-01-01",
    "iso:country": "GB",
    "wof:name": "BH23 8AZ",
    "wof:placetype": "postalcode"
  },
  "geometry": {"coordinates":[-1.740823,50.776412],"type":"Point"}
}
