{
  "type": "Feature",
  "properties": {
    "iso:country":"GB",
    "wof:name":"BH23 8AZ",
    "wof:placetype":"postalcode"
},
  "geometry": {"coordinates":[-1.74092922805703,50.77636945503512],"type":"Point"}
}