{
  "type": "Feature",
  "properties": {
    "date:inception_lower":"2004-08-01",
    "date:inception_upper":"2004-08-31",
    "iso:country":"GB",
    "wof:name":"L40 1RZ",
    "wof:placetype":"postalcode"
},
  "geometry": {"coordinates":[-2.829332,53.643743],"type":"Point"}
}