{
  "type": "Feature",
  "properties": {
    "date:inception_lower":"1980-01-01",
    "date:inception_upper":"1980-01-31",
    "iso:country":"GB",
    "wof:name":"TS25 2HP",
    "wof:placetype":"postalcode"
},
  "geometry": {"coordinates":[-1.237718,54.640478],"type":"Point"}
}