{
  "type": "Feature",
  "properties": {
    "iso:country":"GB",
    "wof:name":"TS25 2HP",
    "wof:placetype":"postalcode"
},
  "geometry": {"coordinates":[-1.23771790948175,54.64047757365277],"type":"Point"}
}