{
  "type": "Feature",
  "properties": {
    "date:inception_lower": "2021-10-01",
    "date:inception_upper": "2021-10-01",
    "iso:country": "GB",
    "wof:name": "DT9 6FJ",
    "wof:placetype": "postalcode"
  },
  "geometry": {"coordinates":[-2.554006,50.881399],"type":"Point"}
}
