{
  "type": "Feature",
  "properties": {
    "iso:country": "GB",
    "wof:name": "ML9 3EX",
    "wof:placetype": "postalcode"
  },
  "geometry": {"coordinates":[-3.986719,55.694251],"type":"Point"}
}
