{
  "type": "Feature",
  "properties": {
    "iso:country": "GB",
    "wof:name": "SY13 1EE",
    "wof:placetype": "postalcode"
  },
  "geometry": {"coordinates":[-2.681438,52.966268],"type":"Point"}
}
