{
  "type": "Feature",
  "properties": {
    "date:inception_lower": "1980-01-01",
    "date:inception_upper": "1980-01-01",
    "iso:country": "GB",
    "wof:name": "SY13 1EE",
    "wof:placetype": "postalcode"
  },
  "geometry": {"coordinates":[-2.681438,52.966268],"type":"Point"}
}
