{
  "type": "Feature",
  "properties": {
    "iso:country":"GB",
    "wof:name":"NP10 8AU",
    "wof:placetype":"postalcode"
},
  "geometry": {"coordinates":[-3.02876256202242,51.55744107075935],"type":"Point"}
}