{
  "type": "Feature",
  "properties": {
    "iso:country": "GB",
    "wof:name": "NP10 8AU",
    "wof:placetype": "postalcode"
  },
  "geometry": {"coordinates":[-3.028674,51.557361],"type":"Point"}
}
