{
  "type": "Feature",
  "properties": {
    "iso:country":"GB",
    "wof:name":"GU1 4EZ",
    "wof:placetype":"postalcode"
},
  "geometry": {"coordinates":[-0.57904699389935,51.23566584388309],"type":"Point"}
}