{
  "type": "Feature",
  "properties": {
    "date:inception_lower":"2010-03-01",
    "date:inception_upper":"2010-03-31",
    "iso:country":"GB",
    "wof:name":"GU1 4EZ",
    "wof:placetype":"postalcode"
},
  "geometry": {"coordinates":[-0.579047,51.235666],"type":"Point"}
}