{
  "type": "Feature",
  "properties": {
    "date:inception_lower": "1980-01-01",
    "date:inception_upper": "1980-01-01",
    "iso:country": "GB",
    "wof:name": "GL9 1AE",
    "wof:placetype": "postalcode"
  },
  "geometry": {"coordinates":[-2.2942,51.57026],"type":"Point"}
}
