{
  "type": "Feature",
  "properties": {
    "iso:country": "GB",
    "wof:name": "GL9 1AE",
    "wof:placetype": "postalcode"
  },
  "geometry": {"coordinates":[-2.294272,51.570305],"type":"Point"}
}
