{
  "type": "Feature",
  "properties": {
    "iso:country":"GB",
    "wof:name":"GL9 1AE",
    "wof:placetype":"postalcode"
},
  "geometry": {"coordinates":[-2.29427628085898,51.57030475722426],"type":"Point"}
}