{
  "type": "Feature",
  "properties": {
    "date:inception_lower": "1980-01-01",
    "date:inception_upper": "1980-01-01",
    "iso:country": "GB",
    "wof:name": "ST10 3BB",
    "wof:placetype": "postalcode"
  },
  "geometry": {"coordinates":[-1.918301,53.000744],"type":"Point"}
}
