{
  "type": "Feature",
  "properties": {
    "iso:country":"GB",
    "wof:name":"RG27 0FB",
    "wof:placetype":"postalcode"
},
  "geometry": {"coordinates":[-1.04962170306875,51.30245041603587],"type":"Point"}
}