{
  "type": "Feature",
  "properties": {
    "iso:country": "GB",
    "wof:name": "RG27 0FB",
    "wof:placetype": "postalcode"
  },
  "geometry": {"coordinates":[-1.049622,51.30245],"type":"Point"}
}
