{
  "type": "Feature",
  "properties": {
    "iso:country": "GB",
    "wof:name": "NR3 2NL",
    "wof:placetype": "postalcode"
  },
  "geometry": {"coordinates":[1.27133,52.650469],"type":"Point"}
}
