{
  "type": "Feature",
  "properties": {
    "iso:country":"GB",
    "wof:name":"NE9 6PR",
    "wof:placetype":"postalcode"
},
  "geometry": {"coordinates":[-1.59217968531435,54.92660427920654],"type":"Point"}
}