{
  "type": "Feature",
  "properties": {
    "iso:country":"GB",
    "wof:name":"BB10 3RD",
    "wof:placetype":"postalcode"
},
  "geometry": {"coordinates":[-2.15302803179418,53.82358420002232],"type":"Point"}
}