{
  "type": "Feature",
  "properties": {
    "date:inception_lower": "1980-01-01",
    "date:inception_upper": "1980-01-01",
    "iso:country": "GB",
    "wof:name": "BB10 3RD",
    "wof:placetype": "postalcode"
  },
  "geometry": {"coordinates":[-2.153028,53.823584],"type":"Point"}
}
