{
  "type": "Feature",
  "properties": {
    "date:inception_lower": "1995-07-01",
    "date:inception_upper": "1995-07-01",
    "iso:country": "GB",
    "wof:name": "RG40 1DJ",
    "wof:placetype": "postalcode"
  },
  "geometry": {"coordinates":[-0.834182,51.412627],"type":"Point"}
}
