{
  "type": "Feature",
  "properties": {
    "iso:country":"GB",
    "wof:name":"RG40 1DJ",
    "wof:placetype":"postalcode"
},
  "geometry": {"coordinates":[-0.83418199930756,51.41262662315689],"type":"Point"}
}