{
  "type": "Feature",
  "properties": {
    "date:inception_lower": "1997-06-01",
    "date:inception_upper": "1997-06-01",
    "iso:country": "GB",
    "wof:name": "UB9 5HN",
    "wof:placetype": "postalcode"
  },
  "geometry": {"coordinates":[-0.487355,51.537324],"type":"Point"}
}
