{
  "type": "Feature",
  "properties": {
    "iso:country":"GB",
    "wof:name":"SR6 7AA",
    "wof:placetype":"postalcode"
},
  "geometry": {"coordinates":[-1.36493490474737,54.95163670096078],"type":"Point"}
}