{
  "type": "Feature",
  "properties": {
    "date:inception_lower": "1980-01-01",
    "date:inception_upper": "1980-01-01",
    "iso:country": "GB",
    "wof:name": "HA8 8TU",
    "wof:placetype": "postalcode"
  },
  "geometry": {"coordinates":[-0.270297,51.622785],"type":"Point"}
}
