{
  "type": "Feature",
  "properties": {
    "date:inception_lower":"1980-01-01",
    "date:inception_upper":"1980-01-31",
    "iso:country":"GB",
    "wof:name":"IP1 6SW",
    "wof:placetype":"postalcode"
},
  "geometry": {"coordinates":[1.13436,52.084334],"type":"Point"}
}