{
  "type": "Feature",
  "properties": {
    "iso:country": "GB",
    "wof:name": "WS12 4FA",
    "wof:placetype": "postalcode"
  },
  "geometry": {"coordinates":[-2.002518,52.709912],"type":"Point"}
}
