{
  "type": "Feature",
  "properties": {
    "iso:country":"GB",
    "wof:name":"TS12 3JW",
    "wof:placetype":"postalcode"
},
  "geometry": {"coordinates":[-0.91954011763704,54.53033601015083],"type":"Point"}
}