{
  "type": "Feature",
  "properties": {
    "date:inception_lower": "1980-01-01",
    "date:inception_upper": "1980-01-01",
    "iso:country": "GB",
    "wof:name": "SK17 8RB",
    "wof:placetype": "postalcode"
  },
  "geometry": {"coordinates":[-1.761777,53.283559],"type":"Point"}
}
