{
  "type": "Feature",
  "properties": {
    "iso:country":"GB",
    "wof:name":"SK17 8RB",
    "wof:placetype":"postalcode"
},
  "geometry": {"coordinates":[-1.76107814513847,53.28275066740254],"type":"Point"}
}