{
  "type": "Feature",
  "properties": {
    "iso:country":"GB",
    "wof:name":"CR0 4SZ",
    "wof:placetype":"postalcode"
},
  "geometry": {"coordinates":[-0.12508054589019,51.37123432613505],"type":"Point"}
}