{
  "type": "Feature",
  "properties": {
    "iso:country":"GB",
    "wof:name":"SA70 7AZ",
    "wof:placetype":"postalcode"
},
  "geometry": {"coordinates":[-4.70027544512217,51.6720028022418],"type":"Point"}
}