{
  "type": "Feature",
  "properties": {
    "iso:country": "GB",
    "wof:name": "SA70 7AZ",
    "wof:placetype": "postalcode"
  },
  "geometry": {"coordinates":[-4.700275,51.672003],"type":"Point"}
}
