{
  "type": "Feature",
  "properties": {
    "date:inception_lower":"1980-01-01",
    "date:inception_upper":"1980-01-31",
    "iso:country":"GB",
    "wof:name":"NE46 2JT",
    "wof:placetype":"postalcode"
},
  "geometry": {"coordinates":[-2.115845,54.948961],"type":"Point"}
}