{
  "type": "Feature",
  "properties": {
    "iso:country": "GB",
    "wof:name": "NE46 2JT",
    "wof:placetype": "postalcode"
  },
  "geometry": {"coordinates":[-2.115845,54.948961],"type":"Point"}
}
