{
  "type": "Feature",
  "properties": {
    "iso:country": "GB",
    "wof:name": "WA9 1SQ",
    "wof:placetype": "postalcode"
  },
  "geometry": {"coordinates":[-2.707393,53.451758],"type":"Point"}
}
