{
  "type": "Feature",
  "properties": {
    "iso:country": "GB",
    "wof:name": "YO26 6NU",
    "wof:placetype": "postalcode"
  },
  "geometry": {"coordinates":[-1.143509,53.98278],"type":"Point"}
}
