{
  "type": "Feature",
  "properties": {
    "iso:country":"GB",
    "wof:name":"YO26 6NU",
    "wof:placetype":"postalcode"
},
  "geometry": {"coordinates":[-1.14354671378315,53.982745200499],"type":"Point"}
}