{
  "type": "Feature",
  "properties": {
    "iso:country": "GB",
    "wof:name": "WF17 9LX",
    "wof:placetype": "postalcode"
  },
  "geometry": {"coordinates":[-1.646448,53.741404],"type":"Point"}
}
