{
  "type": "Feature",
  "properties": {
    "iso:country":"GB",
    "wof:name":"SA3 4QG",
    "wof:placetype":"postalcode"
},
  "geometry": {"coordinates":[-4.00921594148875,51.56947415154551],"type":"Point"}
}