{
  "type": "Feature",
  "properties": {
    "date:inception_lower": "1980-01-01",
    "date:inception_upper": "1980-01-01",
    "iso:country": "GB",
    "wof:name": "SA3 4QG",
    "wof:placetype": "postalcode"
  },
  "geometry": {"coordinates":[-4.009216,51.569474],"type":"Point"}
}
