{
  "type": "Feature",
  "properties": {
    "date:inception_lower": "2024-06-01",
    "date:inception_upper": "2024-06-01",
    "iso:country": "GB",
    "wof:name": "MK17 8YP",
    "wof:placetype": "postalcode"
  },
  "geometry": {"coordinates":[-0.656971,52.019317],"type":"Point"}
}
