{
  "type": "Feature",
  "properties": {
    "iso:country":"GB",
    "wof:name":"KA26 0QR",
    "wof:placetype":"postalcode"
},
  "geometry": {"coordinates":[-4.76696188826262,55.10237506931757],"type":"Point"}
}