{
  "type": "Feature",
  "properties": {
    "date:inception_lower":"1980-01-01",
    "date:inception_upper":"1980-01-31",
    "iso:country":"GB",
    "wof:name":"KA26 0QR",
    "wof:placetype":"postalcode"
},
  "geometry": {"coordinates":[-4.766962,55.102375],"type":"Point"}
}