{
  "type": "Feature",
  "properties": {
    "iso:country":"GB",
    "wof:name":"WV3 9QP",
    "wof:placetype":"postalcode"
},
  "geometry": {"coordinates":[-2.14377298545402,52.58560460807537],"type":"Point"}
}