{
  "type": "Feature",
  "properties": {
    "iso:country":"GB",
    "wof:name":"OX13 6NU",
    "wof:placetype":"postalcode"
},
  "geometry": {"coordinates":[-1.33831692315901,51.66698790710544],"type":"Point"}
}