{
  "type": "Feature",
  "properties": {
    "iso:country":"GB",
    "wof:name":"BD2 4RW",
    "wof:placetype":"postalcode"
},
  "geometry": {"coordinates":[-1.72887558239121,53.80526562088573],"type":"Point"}
}