{
  "type": "Feature",
  "properties": {
    "iso:country": "GB",
    "wof:name": "L39 4AW",
    "wof:placetype": "postalcode"
  },
  "geometry": {"coordinates":[-2.868329,53.5583],"type":"Point"}
}
