{
  "type": "Feature",
  "properties": {
    "date:inception_lower":"2013-04-01",
    "date:inception_upper":"2013-04-30",
    "iso:country":"GB",
    "wof:name":"L39 4AW",
    "wof:placetype":"postalcode"
},
  "geometry": {"coordinates":[-2.868329,53.5583],"type":"Point"}
}