{
  "type": "Feature",
  "properties": {
    "date:inception_lower": "1980-01-01",
    "date:inception_upper": "1980-01-01",
    "iso:country": "GB",
    "wof:name": "DH7 9HZ",
    "wof:placetype": "postalcode"
  },
  "geometry": {"coordinates":[-1.708583,54.771006],"type":"Point"}
}
