{
  "type": "Feature",
  "properties": {
    "iso:country":"GB",
    "wof:name":"DH7 9HZ",
    "wof:placetype":"postalcode"
},
  "geometry": {"coordinates":[-1.70858350362471,54.7710064887032],"type":"Point"}
}