{
  "type": "Feature",
  "properties": {
    "iso:country": "GB",
    "wof:name": "M20 2PZ",
    "wof:placetype": "postalcode"
  },
  "geometry": {"coordinates":[-2.242841,53.421803],"type":"Point"}
}
