{
  "type": "Feature",
  "properties": {
    "date:inception_lower": "1980-01-01",
    "date:inception_upper": "1980-01-01",
    "iso:country": "GB",
    "wof:name": "PE22 0BT",
    "wof:placetype": "postalcode"
  },
  "geometry": {"coordinates":[0.081229,52.997969],"type":"Point"}
}
