{
  "type": "Feature",
  "properties": {
    "iso:country": "GB",
    "wof:name": "PE22 0BT",
    "wof:placetype": "postalcode"
  },
  "geometry": {"coordinates":[0.08128,52.997806],"type":"Point"}
}
