{
  "type": "Feature",
  "properties": {
    "iso:country":"GB",
    "wof:name":"BB1 4AN",
    "wof:placetype":"postalcode"
},
  "geometry": {"coordinates":[-2.40801790549428,53.77589914729466],"type":"Point"}
}