{
  "type": "Feature",
  "properties": {
    "iso:country":"GB",
    "wof:name":"TS12 3EG",
    "wof:placetype":"postalcode"
},
  "geometry": {"coordinates":[-0.95768522913579,54.53734825356148],"type":"Point"}
}