{
  "type": "Feature",
  "properties": {
    "date:inception_lower":"1994-12-01",
    "date:inception_upper":"1994-12-31",
    "iso:country":"GB",
    "wof:name":"SO45 1XG",
    "wof:placetype":"postalcode"
},
  "geometry": {"coordinates":[-1.387893,50.820042],"type":"Point"}
}