{
  "type": "Feature",
  "properties": {
    "iso:country": "GB",
    "wof:name": "SO45 1XG",
    "wof:placetype": "postalcode"
  },
  "geometry": {"coordinates":[-1.387893,50.820042],"type":"Point"}
}
