{
  "type": "Feature",
  "properties": {
    "iso:country":"GB",
    "wof:name":"SO45 1XG",
    "wof:placetype":"postalcode"
},
  "geometry": {"coordinates":[-1.38793200537274,50.81997940918895],"type":"Point"}
}