{
  "type": "Feature",
  "properties": {
    "iso:country":"GB",
    "wof:name":"N17 6RA",
    "wof:placetype":"postalcode"
},
  "geometry": {"coordinates":[-0.07110358261901,51.59476010729789],"type":"Point"}
}