{
  "type": "Feature",
  "properties": {
    "date:inception_lower":"1980-01-01",
    "date:inception_upper":"1980-01-31",
    "iso:country":"GB",
    "wof:name":"NG5 2NU",
    "wof:placetype":"postalcode"
},
  "geometry": {"coordinates":[-1.156965,52.982074],"type":"Point"}
}