{
  "type": "Feature",
  "properties": {
    "iso:country": "GB",
    "wof:name": "NG5 2NU",
    "wof:placetype": "postalcode"
  },
  "geometry": {"coordinates":[-1.157054,52.982066],"type":"Point"}
}
