{
  "type": "Feature",
  "properties": {
    "iso:country":"GB",
    "wof:name":"BB1 5HR",
    "wof:placetype":"postalcode"
},
  "geometry": {"coordinates":[-2.47022665770533,53.75515136091916],"type":"Point"}
}