{
  "type": "Feature",
  "properties": {
    "iso:country":"GB",
    "wof:name":"ME8 9TS",
    "wof:placetype":"postalcode"
},
  "geometry": {"coordinates":[0.59113080735682,51.3430456587732],"type":"Point"}
}