{
  "type": "Feature",
  "properties": {
    "iso:country": "GB",
    "wof:name": "ME8 9TS",
    "wof:placetype": "postalcode"
  },
  "geometry": {"coordinates":[0.591131,51.343046],"type":"Point"}
}
