{
  "type": "Feature",
  "properties": {
    "iso:country": "GB",
    "wof:name": "N16 6TZ",
    "wof:placetype": "postalcode"
  },
  "geometry": {"coordinates":[-0.072093,51.575562],"type":"Point"}
}
