{
  "type": "Feature",
  "properties": {
    "iso:country":"GB",
    "wof:name":"BS7 8SY",
    "wof:placetype":"postalcode"
},
  "geometry": {"coordinates":[-2.58609253912327,51.48842976115875],"type":"Point"}
}