{
  "type": "Feature",
  "properties": {
    "iso:country": "GB",
    "wof:name": "BS7 8SY",
    "wof:placetype": "postalcode"
  },
  "geometry": {"coordinates":[-2.586092,51.48843],"type":"Point"}
}
