{
  "type": "Feature",
  "properties": {
    "date:inception_lower": "1980-01-01",
    "date:inception_upper": "1980-01-01",
    "iso:country": "GB",
    "wof:name": "SP11 7EQ",
    "wof:placetype": "postalcode"
  },
  "geometry": {"coordinates":[-1.622587,51.16519],"type":"Point"}
}
