{
  "type": "Feature",
  "properties": {
    "iso:country":"GB",
    "wof:name":"SP11 7EQ",
    "wof:placetype":"postalcode"
},
  "geometry": {"coordinates":[-1.62258697307962,51.16518961807589],"type":"Point"}
}