{
  "type": "Feature",
  "properties": {
    "iso:country":"GB",
    "wof:name":"NE11 9ET",
    "wof:placetype":"postalcode"
},
  "geometry": {"coordinates":[-1.64443520262571,54.95513799703077],"type":"Point"}
}