{
  "type": "Feature",
  "properties": {
    "iso:country": "GB",
    "wof:name": "EX4 7AW",
    "wof:placetype": "postalcode"
  },
  "geometry": {"coordinates":[-3.513619,50.732459],"type":"Point"}
}
