{
  "type": "Feature",
  "properties": {
    "iso:country":"GB",
    "wof:name":"NG2 7LY",
    "wof:placetype":"postalcode"
},
  "geometry": {"coordinates":[-1.14863047275555,52.91742341064106],"type":"Point"}
}