{
  "type": "Feature",
  "properties": {
    "iso:country": "GB",
    "wof:name": "NG2 7LY",
    "wof:placetype": "postalcode"
  },
  "geometry": {"coordinates":[-1.14863,52.917423],"type":"Point"}
}
