{
  "type": "Feature",
  "properties": {
    "iso:country": "GB",
    "wof:name": "GL50 2TN",
    "wof:placetype": "postalcode"
  },
  "geometry": {"coordinates":[-2.088391,51.892478],"type":"Point"}
}
