{
  "type": "Feature",
  "properties": {
    "iso:country":"GB",
    "wof:name":"HP5 3AY",
    "wof:placetype":"postalcode"
},
  "geometry": {"coordinates":[-0.60570464551021,51.71083217553541],"type":"Point"}
}