{
  "type": "Feature",
  "properties": {
    "iso:country":"GB",
    "wof:name":"PE30 3RE",
    "wof:placetype":"postalcode"
},
  "geometry": {"coordinates":[0.44074086498179,52.79327246866218],"type":"Point"}
}