{
  "type": "Feature",
  "properties": {
    "iso:country":"GB",
    "wof:name":"ML11 9FN",
    "wof:placetype":"postalcode"
},
  "geometry": {"coordinates":[-3.76528693830253,55.66786196418097],"type":"Point"}
}