{
  "type": "Feature",
  "properties": {
    "iso:country": "GB",
    "wof:name": "IP13 6JQ",
    "wof:placetype": "postalcode"
  },
  "geometry": {"coordinates":[1.279517,52.110168],"type":"Point"}
}
