{
  "type": "Feature",
  "properties": {
    "iso:country":"GB",
    "wof:name":"B68 9JN",
    "wof:placetype":"postalcode"
},
  "geometry": {"coordinates":[-1.99031368295409,52.4717899979693],"type":"Point"}
}