{
  "type": "Feature",
  "properties": {
    "iso:country": "GB",
    "wof:name": "BD20 8HB",
    "wof:placetype": "postalcode"
  },
  "geometry": {"coordinates":[-2.075041,53.910247],"type":"Point"}
}
