{
  "type": "Feature",
  "properties": {
    "iso:country":"GB",
    "wof:name":"BD20 8HB",
    "wof:placetype":"postalcode"
},
  "geometry": {"coordinates":[-2.07504081640252,53.91024747956524],"type":"Point"}
}