{
  "type": "Feature",
  "properties": {
    "iso:country":"GB",
    "wof:name":"WF10 5JF",
    "wof:placetype":"postalcode"
},
  "geometry": {"coordinates":[-1.3662619201809,53.7119584943185],"type":"Point"}
}