{
  "type": "Feature",
  "properties": {
    "iso:country":"GB",
    "wof:name":"DE72 3HW",
    "wof:placetype":"postalcode"
},
  "geometry": {"coordinates":[-1.37006578163573,52.90712598164819],"type":"Point"}
}