{
  "type": "Feature",
  "properties": {
    "iso:country": "GB",
    "wof:name": "DE72 3HW",
    "wof:placetype": "postalcode"
  },
  "geometry": {"coordinates":[-1.370066,52.907126],"type":"Point"}
}
