{
  "type": "Feature",
  "properties": {
    "iso:country": "GB",
    "wof:name": "SG9 0ER",
    "wof:placetype": "postalcode"
  },
  "geometry": {"coordinates":[0.014132,51.974135],"type":"Point"}
}
