{
  "type": "Feature",
  "properties": {
    "iso:country":"GB",
    "wof:name":"SG9 0ER",
    "wof:placetype":"postalcode"
},
  "geometry": {"coordinates":[0.01413221371504,51.97413524461325],"type":"Point"}
}