{
  "type": "Feature",
  "properties": {
    "date:inception_lower":"1980-01-01",
    "date:inception_upper":"1980-01-31",
    "iso:country":"GB",
    "wof:name":"HA4 8ND",
    "wof:placetype":"postalcode"
},
  "geometry": {"coordinates":[-0.415681,51.572932],"type":"Point"}
}