{
  "type": "Feature",
  "properties": {
    "iso:country":"GB",
    "wof:name":"HA4 8ND",
    "wof:placetype":"postalcode"
},
  "geometry": {"coordinates":[-0.4156813660514,51.57293166260281],"type":"Point"}
}