{
  "type": "Feature",
  "properties": {
    "iso:country": "GB",
    "wof:name": "HA4 8ND",
    "wof:placetype": "postalcode"
  },
  "geometry": {"coordinates":[-0.415681,51.572932],"type":"Point"}
}
