{
  "type": "Feature",
  "properties": {
    "date:inception_lower":"1980-01-01",
    "date:inception_upper":"1980-01-31",
    "iso:country":"GB",
    "wof:name":"LS18 5PY",
    "wof:placetype":"postalcode"
},
  "geometry": {"coordinates":[-1.630805,53.842619],"type":"Point"}
}