{
  "type": "Feature",
  "properties": {
    "date:inception_lower": "1980-01-01",
    "date:inception_upper": "1980-01-01",
    "iso:country": "GB",
    "wof:name": "CO4 5EA",
    "wof:placetype": "postalcode"
  },
  "geometry": {"coordinates":[0.890945,51.910511],"type":"Point"}
}
