{
  "type": "Feature",
  "properties": {
    "iso:country": "GB",
    "wof:name": "WR9 0JQ",
    "wof:placetype": "postalcode"
  },
  "geometry": {"coordinates":[-2.230986,52.284722],"type":"Point"}
}
