{
  "type": "Feature",
  "properties": {
    "date:inception_lower": "1980-01-01",
    "date:inception_upper": "1980-01-01",
    "iso:country": "GB",
    "wof:name": "WR9 0JQ",
    "wof:placetype": "postalcode"
  },
  "geometry": {"coordinates":[-2.230986,52.284722],"type":"Point"}
}
