{
  "type": "Feature",
  "properties": {
    "iso:country": "GB",
    "wof:name": "IP10 0JB",
    "wof:placetype": "postalcode"
  },
  "geometry": {"coordinates":[1.223612,52.016394],"type":"Point"}
}
