{
  "type": "Feature",
  "properties": {
    "iso:country": "GB",
    "wof:name": "HP19 0GA",
    "wof:placetype": "postalcode"
  },
  "geometry": {"coordinates":[-0.804371,51.831583],"type":"Point"}
}
