{
  "type": "Feature",
  "properties": {
    "iso:country":"GB",
    "wof:name":"TD5 8EJ",
    "wof:placetype":"postalcode"
},
  "geometry": {"coordinates":[-2.39406657071266,55.53931440131829],"type":"Point"}
}