{
  "type": "Feature",
  "properties": {
    "date:inception_lower": "1991-08-01",
    "date:inception_upper": "1991-08-01",
    "iso:country": "GB",
    "wof:name": "TD5 8EJ",
    "wof:placetype": "postalcode"
  },
  "geometry": {"coordinates":[-2.394067,55.539314],"type":"Point"}
}
