{
  "type": "Feature",
  "properties": {
    "iso:country": "GB",
    "wof:name": "TD5 8EJ",
    "wof:placetype": "postalcode"
  },
  "geometry": {"coordinates":[-2.394067,55.539314],"type":"Point"}
}
