{
  "type": "Feature",
  "properties": {
    "iso:country":"GB",
    "wof:name":"DE75 7BQ",
    "wof:placetype":"postalcode"
},
  "geometry": {"coordinates":[-1.34518018234286,53.00933566551832],"type":"Point"}
}