{
  "type": "Feature",
  "properties": {
    "iso:country":"GB",
    "wof:name":"MK7 8BJ",
    "wof:placetype":"postalcode"
},
  "geometry": {"coordinates":[-0.69285974426066,52.00824652094948],"type":"Point"}
}