{
  "type": "Feature",
  "properties": {
    "iso:country":"GB",
    "wof:name":"SY7 0JH",
    "wof:placetype":"postalcode"
},
  "geometry": {"coordinates":[-2.92684030909013,52.41863891761105],"type":"Point"}
}