{
  "type": "Feature",
  "properties": {
    "iso:country": "GB",
    "wof:name": "SY7 0JH",
    "wof:placetype": "postalcode"
  },
  "geometry": {"coordinates":[-2.92684,52.418639],"type":"Point"}
}
