{
  "type": "Feature",
  "properties": {
    "iso:country": "GB",
    "wof:name": "IV10 8SN",
    "wof:placetype": "postalcode"
  },
  "geometry": {"coordinates":[-4.152225,57.602989],"type":"Point"}
}
