{
  "type": "Feature",
  "properties": {
    "iso:country":"GB",
    "wof:name":"TS11 8BJ",
    "wof:placetype":"postalcode"
},
  "geometry": {"coordinates":[-1.04186544288978,54.57920562493937],"type":"Point"}
}