{
  "type": "Feature",
  "properties": {
    "iso:country": "GB",
    "wof:name": "TS11 8BJ",
    "wof:placetype": "postalcode"
  },
  "geometry": {"coordinates":[-1.041865,54.579206],"type":"Point"}
}
