{
  "type": "Feature",
  "properties": {
    "date:inception_lower":"1994-05-01",
    "date:inception_upper":"1994-05-31",
    "iso:country":"GB",
    "wof:name":"M12 6WL",
    "wof:placetype":"postalcode"
},
  "geometry": {"coordinates":[-2.211686,53.477683],"type":"Point"}
}