{
  "type": "Feature",
  "properties": {
    "iso:country": "GB",
    "wof:name": "M12 6WL",
    "wof:placetype": "postalcode"
  },
  "geometry": {"coordinates":[-2.211686,53.477683],"type":"Point"}
}
