{
  "type": "Feature",
  "properties": {
    "iso:country":"GB",
    "wof:name":"TQ6 0DP",
    "wof:placetype":"postalcode"
},
  "geometry": {"coordinates":[-3.56811763387358,50.34996958195307],"type":"Point"}
}