{
  "type": "Feature",
  "properties": {
    "date:inception_lower":"2003-09-01",
    "date:inception_upper":"2003-09-30",
    "iso:country":"GB",
    "wof:name":"PE31 7UJ",
    "wof:placetype":"postalcode"
},
  "geometry": {"coordinates":[0.492413,52.874553],"type":"Point"}
}