{
  "type": "Feature",
  "properties": {
    "iso:country":"GB",
    "wof:name":"PE31 7UJ",
    "wof:placetype":"postalcode"
},
  "geometry": {"coordinates":[0.49241309217662,52.87455301889231],"type":"Point"}
}