{
  "type": "Feature",
  "properties": {
    "iso:country": "GB",
    "wof:name": "PE31 7UJ",
    "wof:placetype": "postalcode"
  },
  "geometry": {"coordinates":[0.492413,52.874553],"type":"Point"}
}
