{
  "type": "Feature",
  "properties": {
    "iso:country":"GB",
    "wof:name":"EH41 3NP",
    "wof:placetype":"postalcode"
},
  "geometry": {"coordinates":[-2.78128234168775,55.9557158651014],"type":"Point"}
}