{
  "type": "Feature",
  "properties": {
    "iso:country":"GB",
    "wof:name":"SE8 4PP",
    "wof:placetype":"postalcode"
},
  "geometry": {"coordinates":[-0.02777230571034,51.47340405244436],"type":"Point"}
}