{
  "type": "Feature",
  "properties": {
    "date:inception_lower": "1980-01-01",
    "date:inception_upper": "1980-01-01",
    "iso:country": "GB",
    "wof:name": "SE8 4PP",
    "wof:placetype": "postalcode"
  },
  "geometry": {"coordinates":[-0.027772,51.473404],"type":"Point"}
}
