{
  "type": "Feature",
  "properties": {
    "iso:country": "GB",
    "wof:name": "LE7 9LP",
    "wof:placetype": "postalcode"
  },
  "geometry": {"coordinates":[-0.975287,52.601192],"type":"Point"}
}
