{
  "type": "Feature",
  "properties": {
    "iso:country":"GB",
    "wof:name":"LE7 9LP",
    "wof:placetype":"postalcode"
},
  "geometry": {"coordinates":[-0.97528706900348,52.60119239612821],"type":"Point"}
}