{
  "type": "Feature",
  "properties": {
    "iso:country": "GB",
    "wof:name": "SA2 7UW",
    "wof:placetype": "postalcode"
  },
  "geometry": {"coordinates":[-4.038255,51.624089],"type":"Point"}
}
