{
  "type": "Feature",
  "properties": {
    "iso:country":"GB",
    "wof:name":"SA2 7UW",
    "wof:placetype":"postalcode"
},
  "geometry": {"coordinates":[-4.03825521767924,51.62408886498922],"type":"Point"}
}