{
  "type": "Feature",
  "properties": {
    "iso:country":"GB",
    "wof:name":"LE12 9RA",
    "wof:placetype":"postalcode"
},
  "geometry": {"coordinates":[-1.28623093746415,52.77607821849135],"type":"Point"}
}