{
  "type": "Feature",
  "properties": {
    "iso:country":"GB",
    "wof:name":"SA64 0DT",
    "wof:placetype":"postalcode"
},
  "geometry": {"coordinates":[-4.99215654138691,52.00913611703052],"type":"Point"}
}