{
  "type": "Feature",
  "properties": {
    "date:inception_lower": "1980-01-01",
    "date:inception_upper": "1980-01-01",
    "iso:country": "GB",
    "wof:name": "SA64 0DT",
    "wof:placetype": "postalcode"
  },
  "geometry": {"coordinates":[-4.992156,52.009136],"type":"Point"}
}
