{
  "type": "Feature",
  "properties": {
    "iso:country": "GB",
    "wof:name": "CO4 5FR",
    "wof:placetype": "postalcode"
  },
  "geometry": {"coordinates":[0.920713,51.919048],"type":"Point"}
}
