{
  "type": "Feature",
  "properties": {
    "iso:country":"GB",
    "wof:name":"SL4 5AD",
    "wof:placetype":"postalcode"
},
  "geometry": {"coordinates":[-0.61277181312327,51.47990452494238],"type":"Point"}
}