{
  "type": "Feature",
  "properties": {
    "iso:country": "GB",
    "wof:name": "B28 8QH",
    "wof:placetype": "postalcode"
  },
  "geometry": {"coordinates":[-1.834339,52.433099],"type":"Point"}
}
