{
  "type": "Feature",
  "properties": {
    "date:inception_lower":"1980-01-01",
    "date:inception_upper":"1980-01-31",
    "iso:country":"GB",
    "wof:name":"WF6 2LG",
    "wof:placetype":"postalcode"
},
  "geometry": {"coordinates":[-1.437458,53.706202],"type":"Point"}
}