{
  "type": "Feature",
  "properties": {
    "iso:country": "GB",
    "wof:name": "WF6 2LG",
    "wof:placetype": "postalcode"
  },
  "geometry": {"coordinates":[-1.437458,53.706202],"type":"Point"}
}
