{
  "type": "Feature",
  "properties": {
    "iso:country":"GB",
    "wof:name":"WF6 2LG",
    "wof:placetype":"postalcode"
},
  "geometry": {"coordinates":[-1.43745763000292,53.70620177038516],"type":"Point"}
}