{
  "type": "Feature",
  "properties": {
    "iso:country":"GB",
    "wof:name":"BH14 9DL",
    "wof:placetype":"postalcode"
},
  "geometry": {"coordinates":[-1.93232314003457,50.728283751436],"type":"Point"}
}