{
  "type": "Feature",
  "properties": {
    "date:inception_lower": "2022-09-01",
    "date:inception_upper": "2022-09-01",
    "iso:country": "GB",
    "wof:name": "G69 0DH",
    "wof:placetype": "postalcode"
  },
  "geometry": {"coordinates":[-4.089708,55.920288],"type":"Point"}
}
