{
  "type": "Feature",
  "properties": {
    "date:inception_lower": "1998-12-01",
    "date:inception_upper": "1998-12-01",
    "iso:country": "GB",
    "wof:name": "CB1 8NY",
    "wof:placetype": "postalcode"
  },
  "geometry": {"coordinates":[0.158805,52.178372],"type":"Point"}
}
