{
  "type": "Feature",
  "properties": {
    "iso:country": "GB",
    "wof:name": "BN44 3PG",
    "wof:placetype": "postalcode"
  },
  "geometry": {"coordinates":[-0.32887,50.88562],"type":"Point"}
}
