{
  "type": "Feature",
  "properties": {
    "date:inception_lower": "1995-01-01",
    "date:inception_upper": "1995-01-01",
    "iso:country": "GB",
    "wof:name": "N13 4AD",
    "wof:placetype": "postalcode"
  },
  "geometry": {"coordinates":[-0.1114,51.626421],"type":"Point"}
}
