{
  "type": "Feature",
  "properties": {
    "date:inception_lower":"1980-01-01",
    "date:inception_upper":"1980-01-31",
    "iso:country":"GB",
    "wof:name":"ML11 7ND",
    "wof:placetype":"postalcode"
},
  "geometry": {"coordinates":[-3.781819,55.674426],"type":"Point"}
}