{
  "type": "Feature",
  "properties": {
    "iso:country": "GB",
    "wof:name": "ML11 7ND",
    "wof:placetype": "postalcode"
  },
  "geometry": {"coordinates":[-3.781819,55.674426],"type":"Point"}
}
