{
  "type": "Feature",
  "properties": {
    "iso:country":"GB",
    "wof:name":"SE17 1NH",
    "wof:placetype":"postalcode"
},
  "geometry": {"coordinates":[-0.09611383561699,51.49101715632142],"type":"Point"}
}