{
  "type": "Feature",
  "properties": {
    "iso:country": "GB",
    "wof:name": "LE18 9SB",
    "wof:placetype": "postalcode"
  },
  "geometry": {"coordinates":[-1.114843,52.58343],"type":"Point"}
}
