{
  "type": "Feature",
  "properties": {
    "iso:country":"GB",
    "wof:name":"YO41 1HP",
    "wof:placetype":"postalcode"
},
  "geometry": {"coordinates":[-0.86432120814395,53.98911401013044],"type":"Point"}
}