{
  "type": "Feature",
  "properties": {
    "date:inception_lower": "1998-06-01",
    "date:inception_upper": "1998-06-01",
    "iso:country": "GB",
    "wof:name": "YO41 1HP",
    "wof:placetype": "postalcode"
  },
  "geometry": {"coordinates":[-0.864321,53.989114],"type":"Point"}
}
