{
  "type": "Feature",
  "properties": {
    "date:inception_lower": "1983-01-01",
    "date:inception_upper": "1983-01-01",
    "iso:country": "GB",
    "wof:name": "CB1 2EF",
    "wof:placetype": "postalcode"
  },
  "geometry": {"coordinates":[0.136224,52.198004],"type":"Point"}
}
