{
  "type": "Feature",
  "properties": {
    "date:inception_lower":"2013-01-01",
    "date:inception_upper":"2013-01-31",
    "iso:country":"GB",
    "wof:name":"PL15 8FG",
    "wof:placetype":"postalcode"
},
  "geometry": {"coordinates":[-4.366987,50.643896],"type":"Point"}
}