{
  "type": "Feature",
  "properties": {
    "iso:country": "GB",
    "wof:name": "PL15 8FG",
    "wof:placetype": "postalcode"
  },
  "geometry": {"coordinates":[-4.366987,50.643896],"type":"Point"}
}
