{
  "type": "Feature",
  "properties": {
    "iso:country": "GB",
    "wof:name": "SA68 0RX",
    "wof:placetype": "postalcode"
  },
  "geometry": {"coordinates":[-4.784884,51.717566],"type":"Point"}
}
