{
  "type": "Feature",
  "properties": {
    "date:inception_lower": "1980-01-01",
    "date:inception_upper": "1980-01-01",
    "iso:country": "GB",
    "wof:name": "SA68 0RX",
    "wof:placetype": "postalcode"
  },
  "geometry": {"coordinates":[-4.784884,51.717566],"type":"Point"}
}
