{
  "type": "Feature",
  "properties": {
    "iso:country":"GB",
    "wof:name":"SA68 0RX",
    "wof:placetype":"postalcode"
},
  "geometry": {"coordinates":[-4.7848839449296,51.71756595796859],"type":"Point"}
}