{
  "type": "Feature",
  "properties": {
    "iso:country":"GB",
    "wof:name":"EX16 7AS",
    "wof:placetype":"postalcode"
},
  "geometry": {"coordinates":[-3.4140783877029,50.90606127112245],"type":"Point"}
}