{
  "type": "Feature",
  "properties": {
    "iso:country": "GB",
    "wof:name": "EX16 7AS",
    "wof:placetype": "postalcode"
  },
  "geometry": {"coordinates":[-3.414078,50.906061],"type":"Point"}
}
