{
  "type": "Feature",
  "properties": {
    "iso:country":"GB",
    "wof:name":"PR1 5DY",
    "wof:placetype":"postalcode"
},
  "geometry": {"coordinates":[-2.68141728857574,53.76616263486232],"type":"Point"}
}