{
  "type": "Feature",
  "properties": {
    "iso:country": "GB",
    "wof:name": "PR1 5DY",
    "wof:placetype": "postalcode"
  },
  "geometry": {"coordinates":[-2.681595,53.76606],"type":"Point"}
}
