{
  "type": "Feature",
  "properties": {
    "iso:country": "GB",
    "wof:name": "S40 4QF",
    "wof:placetype": "postalcode"
  },
  "geometry": {"coordinates":[-1.463931,53.243853],"type":"Point"}
}
