{
  "type": "Feature",
  "properties": {
    "iso:country":"GB",
    "wof:name":"S40 4QF",
    "wof:placetype":"postalcode"
},
  "geometry": {"coordinates":[-1.46391613721696,53.24386174146377],"type":"Point"}
}