{
  "type": "Feature",
  "properties": {
    "iso:country": "GB",
    "wof:name": "DE14 3BG",
    "wof:placetype": "postalcode"
  },
  "geometry": {"coordinates":[-1.641083,52.797701],"type":"Point"}
}
