{
  "type": "Feature",
  "properties": {
    "date:inception_lower": "2017-01-01",
    "date:inception_upper": "2017-01-01",
    "iso:country": "GB",
    "wof:name": "DE14 3BG",
    "wof:placetype": "postalcode"
  },
  "geometry": {"coordinates":[-1.641083,52.797701],"type":"Point"}
}
