{
  "type": "Feature",
  "properties": {
    "iso:country":"GB",
    "wof:name":"NP19 9TH",
    "wof:placetype":"postalcode"
},
  "geometry": {"coordinates":[-2.9380231329262,51.59491448811085],"type":"Point"}
}