{
  "type": "Feature",
  "properties": {
    "iso:country": "GB",
    "wof:name": "PO30 5SN",
    "wof:placetype": "postalcode"
  },
  "geometry": {"coordinates":[-1.314359,50.695658],"type":"Point"}
}
