{
  "type": "Feature",
  "properties": {
    "iso:country": "GB",
    "wof:name": "LE4 4GB",
    "wof:placetype": "postalcode"
  },
  "geometry": {"coordinates":[-1.117417,52.678293],"type":"Point"}
}
