{
  "type": "Feature",
  "properties": {
    "date:inception_lower": "1980-01-01",
    "date:inception_upper": "1980-01-01",
    "iso:country": "GB",
    "wof:name": "LE4 4GB",
    "wof:placetype": "postalcode"
  },
  "geometry": {"coordinates":[-1.117417,52.678293],"type":"Point"}
}
