{
  "type": "Feature",
  "properties": {
    "iso:country":"GB",
    "wof:name":"LE4 4GB",
    "wof:placetype":"postalcode"
},
  "geometry": {"coordinates":[-1.11741751559243,52.67829289667124],"type":"Point"}
}