{
  "type": "Feature",
  "properties": {
    "iso:country":"GB",
    "wof:name":"BS9 3DZ",
    "wof:placetype":"postalcode"
},
  "geometry": {"coordinates":[-2.61803371285603,51.49452387353531],"type":"Point"}
}