{
  "type": "Feature",
  "properties": {
    "date:inception_lower":"1990-02-01",
    "date:inception_upper":"1990-02-28",
    "iso:country":"GB",
    "wof:name":"L32 3YG",
    "wof:placetype":"postalcode"
},
  "geometry": {"coordinates":[-2.881272,53.469164],"type":"Point"}
}