{
  "type": "Feature",
  "properties": {
    "iso:country": "GB",
    "wof:name": "L32 3YG",
    "wof:placetype": "postalcode"
  },
  "geometry": {"coordinates":[-2.881272,53.469164],"type":"Point"}
}
