{
  "type": "Feature",
  "properties": {
    "iso:country": "GB",
    "wof:name": "PL9 8GR",
    "wof:placetype": "postalcode"
  },
  "geometry": {"coordinates":[-4.061827,50.364229],"type":"Point"}
}
