{
  "type": "Feature",
  "properties": {
    "iso:country": "GB",
    "wof:name": "SK3 9PL",
    "wof:placetype": "postalcode"
  },
  "geometry": {"coordinates":[-2.175915,53.404969],"type":"Point"}
}
