{
  "type": "Feature",
  "properties": {
    "iso:country":"GB",
    "wof:name":"SK3 9PL",
    "wof:placetype":"postalcode"
},
  "geometry": {"coordinates":[-2.17591647297684,53.40495221444273],"type":"Point"}
}