{
  "type": "Feature",
  "properties": {
    "date:inception_lower": "1980-01-01",
    "date:inception_upper": "1980-01-01",
    "iso:country": "GB",
    "wof:name": "SK3 9PL",
    "wof:placetype": "postalcode"
  },
  "geometry": {"coordinates":[-2.175915,53.404969],"type":"Point"}
}
