{
  "type": "Feature",
  "properties": {
    "iso:country":"GB",
    "wof:name":"SS9 3DT",
    "wof:placetype":"postalcode"
},
  "geometry": {"coordinates":[0.6570320056856,51.54953895777995],"type":"Point"}
}