{
  "type": "Feature",
  "properties": {
    "date:inception_lower": "1980-01-01",
    "date:inception_upper": "1980-01-01",
    "iso:country": "GB",
    "wof:name": "TA20 1NN",
    "wof:placetype": "postalcode"
  },
  "geometry": {"coordinates":[-2.95161,50.878698],"type":"Point"}
}
