{
  "type": "Feature",
  "properties": {
    "date:inception_lower": "2018-01-01",
    "date:inception_upper": "2018-01-01",
    "iso:country": "GB",
    "wof:name": "LL57 2QL",
    "wof:placetype": "postalcode"
  },
  "geometry": {"coordinates":[-4.16533,53.207021],"type":"Point"}
}
