{
  "type": "Feature",
  "properties": {
    "iso:country":"GB",
    "wof:name":"ST6 7PJ",
    "wof:placetype":"postalcode"
},
  "geometry": {"coordinates":[-2.18224256090405,53.05469303167469],"type":"Point"}
}