{
  "type": "Feature",
  "properties": {
    "iso:country":"GB",
    "wof:name":"CF3 5TP",
    "wof:placetype":"postalcode"
},
  "geometry": {"coordinates":[-3.11768595687146,51.52307020878231],"type":"Point"}
}