{
  "type": "Feature",
  "properties": {
    "date:inception_lower": "1999-06-01",
    "date:inception_upper": "1999-06-01",
    "iso:country": "GB",
    "wof:name": "CF3 5TP",
    "wof:placetype": "postalcode"
  },
  "geometry": {"coordinates":[-3.117686,51.52307],"type":"Point"}
}
