{
  "type": "Feature",
  "properties": {
    "iso:country":"GB",
    "wof:name":"DL7 9JU",
    "wof:placetype":"postalcode"
},
  "geometry": {"coordinates":[-1.45910094302823,54.30929037402441],"type":"Point"}
}