{
  "type": "Feature",
  "properties": {
    "iso:country": "GB",
    "wof:name": "DL7 9JU",
    "wof:placetype": "postalcode"
  },
  "geometry": {"coordinates":[-1.459111,54.309249],"type":"Point"}
}
