{
  "type": "Feature",
  "properties": {
    "iso:country": "GB",
    "wof:name": "MK42 7GG",
    "wof:placetype": "postalcode"
  },
  "geometry": {"coordinates":[-0.518459,52.112544],"type":"Point"}
}
