{
  "type": "Feature",
  "properties": {
    "date:inception_lower":"2016-05-01",
    "date:inception_upper":"2016-05-31",
    "iso:country":"GB",
    "wof:name":"CW8 4GB",
    "wof:placetype":"postalcode"
},
  "geometry": {"coordinates":[-2.535529,53.259941],"type":"Point"}
}