{
  "type": "Feature",
  "properties": {
    "iso:country": "GB",
    "wof:name": "CW8 4GB",
    "wof:placetype": "postalcode"
  },
  "geometry": {"coordinates":[-2.535469,53.259941],"type":"Point"}
}
