{
  "type": "Feature",
  "properties": {
    "date:inception_lower": "1993-08-01",
    "date:inception_upper": "1993-08-01",
    "iso:country": "GB",
    "wof:name": "KT16 8BB",
    "wof:placetype": "postalcode"
  },
  "geometry": {"coordinates":[-0.505878,51.386286],"type":"Point"}
}
