{
  "type": "Feature",
  "properties": {
    "iso:country": "GB",
    "wof:name": "ME15 9FY",
    "wof:placetype": "postalcode"
  },
  "geometry": {"coordinates":[0.548755,51.245692],"type":"Point"}
}
