{
  "type": "Feature",
  "properties": {
    "iso:country":"GB",
    "wof:name":"ME15 9FY",
    "wof:placetype":"postalcode"
},
  "geometry": {"coordinates":[0.54875468259212,51.24569247070743],"type":"Point"}
}