{
  "type": "Feature",
  "properties": {
    "date:inception_lower": "1980-01-01",
    "date:inception_upper": "1980-01-01",
    "iso:country": "GB",
    "wof:name": "DT2 7JG",
    "wof:placetype": "postalcode"
  },
  "geometry": {"coordinates":[-2.474324,50.809243],"type":"Point"}
}
