{
  "type": "Feature",
  "properties": {
    "iso:country":"GB",
    "wof:name":"M28 7JF",
    "wof:placetype":"postalcode"
},
  "geometry": {"coordinates":[-2.38559867966228,53.51491877778525],"type":"Point"}
}