{
  "type": "Feature",
  "properties": {
    "iso:country":"GB",
    "wof:name":"NR2 3NE",
    "wof:placetype":"postalcode"
},
  "geometry": {"coordinates":[1.26964382665801,52.62173624229323],"type":"Point"}
}