{
  "type": "Feature",
  "properties": {
    "iso:country":"GB",
    "wof:name":"WN3 6XP",
    "wof:placetype":"postalcode"
},
  "geometry": {"coordinates":[-2.65532792777017,53.51769895355701],"type":"Point"}
}