{
  "type": "Feature",
  "properties": {
    "iso:country":"GB",
    "wof:name":"SS15 5PB",
    "wof:placetype":"postalcode"
},
  "geometry": {"coordinates":[0.43670167686757,51.57755292662645],"type":"Point"}
}