{
  "type": "Feature",
  "properties": {
    "iso:country": "GB",
    "wof:name": "SS15 5PB",
    "wof:placetype": "postalcode"
  },
  "geometry": {"coordinates":[0.436702,51.577553],"type":"Point"}
}
