{
  "type": "Feature",
  "properties": {
    "date:inception_lower": "1980-01-01",
    "date:inception_upper": "1980-01-01",
    "iso:country": "GB",
    "wof:name": "B78 3PB",
    "wof:placetype": "postalcode"
  },
  "geometry": {"coordinates":[-1.729226,52.618735],"type":"Point"}
}
