{
  "type": "Feature",
  "properties": {
    "iso:country":"GB",
    "wof:name":"B78 3PB",
    "wof:placetype":"postalcode"
},
  "geometry": {"coordinates":[-1.72922627183494,52.61873541574563],"type":"Point"}
}