{
  "type": "Feature",
  "properties": {
    "date:inception_lower":"2008-01-01",
    "date:inception_upper":"2008-01-31",
    "iso:country":"GB",
    "wof:name":"SW6 1UF",
    "wof:placetype":"postalcode"
},
  "geometry": {"coordinates":[-0.199912,51.485642],"type":"Point"}
}