{
  "type": "Feature",
  "properties": {
    "iso:country": "GB",
    "wof:name": "OL1 1ET",
    "wof:placetype": "postalcode"
  },
  "geometry": {"coordinates":[-2.114515,53.539232],"type":"Point"}
}
