{
  "type": "Feature",
  "properties": {
    "date:inception_lower": "2023-01-01",
    "date:inception_upper": "2023-01-01",
    "iso:country": "GB",
    "wof:name": "ML10 6ZF",
    "wof:placetype": "postalcode"
  },
  "geometry": {"coordinates":[-4.111442,55.629677],"type":"Point"}
}
