{
  "type": "Feature",
  "properties": {
    "iso:country": "GB",
    "wof:name": "ML6 8TZ",
    "wof:placetype": "postalcode"
  },
  "geometry": {"coordinates":[-3.958262,55.84319],"type":"Point"}
}
