{
  "type": "Feature",
  "properties": {
    "date:inception_lower": "2016-04-01",
    "date:inception_upper": "2016-04-01",
    "iso:country": "GB",
    "wof:name": "RG24 8YJ",
    "wof:placetype": "postalcode"
  },
  "geometry": {"coordinates":[-1.061661,51.298717],"type":"Point"}
}
