{
  "type": "Feature",
  "properties": {
    "iso:country":"GB",
    "wof:name":"NE38 8JJ",
    "wof:placetype":"postalcode"
},
  "geometry": {"coordinates":[-1.50713243533661,54.89259936749077],"type":"Point"}
}