{
  "type": "Feature",
  "properties": {
    "iso:country": "GB",
    "wof:name": "S40 4RR",
    "wof:placetype": "postalcode"
  },
  "geometry": {"coordinates":[-1.464921,53.24739],"type":"Point"}
}
