{
  "type": "Feature",
  "properties": {
    "date:inception_lower": "2002-08-01",
    "date:inception_upper": "2002-08-01",
    "iso:country": "GB",
    "wof:name": "DD3 0GA",
    "wof:placetype": "postalcode"
  },
  "geometry": {"coordinates":[-2.975836,56.496627],"type":"Point"}
}
