{
  "type": "Feature",
  "properties": {
    "iso:country":"GB",
    "wof:name":"DD3 0GA",
    "wof:placetype":"postalcode"
},
  "geometry": {"coordinates":[-2.97583645047391,56.49662679513319],"type":"Point"}
}