{
  "type": "Feature",
  "properties": {
    "iso:country": "GB",
    "wof:name": "M26 4AF",
    "wof:placetype": "postalcode"
  },
  "geometry": {"coordinates":[-2.338721,53.576503],"type":"Point"}
}
