{
  "type": "Feature",
  "properties": {
    "iso:country":"GB",
    "wof:name":"EH48 3HY",
    "wof:placetype":"postalcode"
},
  "geometry": {"coordinates":[-3.70701732460383,55.89765244852516],"type":"Point"}
}