{
  "type": "Feature",
  "properties": {
    "iso:country": "GB",
    "wof:name": "EH48 3HY",
    "wof:placetype": "postalcode"
  },
  "geometry": {"coordinates":[-3.707017,55.897652],"type":"Point"}
}
