{
  "type": "Feature",
  "properties": {
    "iso:country":"GB",
    "wof:name":"B44 9UL",
    "wof:placetype":"postalcode"
},
  "geometry": {"coordinates":[-1.89048622734088,52.54386605470243],"type":"Point"}
}