{
  "type": "Feature",
  "properties": {
    "iso:country":"GB",
    "wof:name":"ML9 2LU",
    "wof:placetype":"postalcode"
},
  "geometry": {"coordinates":[-3.96188022532378,55.73042748427472],"type":"Point"}
}