{
  "type": "Feature",
  "properties": {
    "iso:country":"GB",
    "wof:name":"BS8 2AH",
    "wof:placetype":"postalcode"
},
  "geometry": {"coordinates":[-2.615379632748,51.46002801728638],"type":"Point"}
}