{
  "type": "Feature",
  "properties": {
    "iso:country":"GB",
    "wof:name":"W1J 5DW",
    "wof:placetype":"postalcode"
},
  "geometry": {"coordinates":[-0.14697096470629,51.50824316590988],"type":"Point"}
}