{
  "type": "Feature",
  "properties": {
    "date:inception_lower": "1998-06-01",
    "date:inception_upper": "1998-06-01",
    "iso:country": "GB",
    "wof:name": "KT16 0HF",
    "wof:placetype": "postalcode"
  },
  "geometry": {"coordinates":[-0.520486,51.364251],"type":"Point"}
}
