{
  "type": "Feature",
  "properties": {
    "iso:country": "GB",
    "wof:name": "GU21 4RX",
    "wof:placetype": "postalcode"
  },
  "geometry": {"coordinates":[-0.575521,51.322436],"type":"Point"}
}
