{
  "type": "Feature",
  "properties": {
    "iso:country":"GB",
    "wof:name":"FK8 3ET",
    "wof:placetype":"postalcode"
},
  "geometry": {"coordinates":[-4.25145784491927,56.11837824619149],"type":"Point"}
}