{
  "type": "Feature",
  "properties": {
    "date:inception_lower": "1990-02-01",
    "date:inception_upper": "1990-02-01",
    "iso:country": "GB",
    "wof:name": "CV10 8JL",
    "wof:placetype": "postalcode"
  },
  "geometry": {"coordinates":[-1.49972,52.51874],"type":"Point"}
}
