{
  "type": "Feature",
  "properties": {
    "iso:country":"GB",
    "wof:name":"CV10 8JL",
    "wof:placetype":"postalcode"
},
  "geometry": {"coordinates":[-1.49972047549476,52.51874044601502],"type":"Point"}
}