{
  "type": "Feature",
  "properties": {
    "iso:country":"GB",
    "wof:name":"TS9 6PX",
    "wof:placetype":"postalcode"
},
  "geometry": {"coordinates":[-1.1455116011756,54.48505000549341],"type":"Point"}
}