{
  "type": "Feature",
  "properties": {
    "iso:country": "GB",
    "wof:name": "TS9 6PX",
    "wof:placetype": "postalcode"
  },
  "geometry": {"coordinates":[-1.145512,54.48505],"type":"Point"}
}
