{
  "type": "Feature",
  "properties": {
    "date:inception_lower": "2022-05-01",
    "date:inception_upper": "2022-05-01",
    "iso:country": "GB",
    "wof:name": "DT9 4GA",
    "wof:placetype": "postalcode"
  },
  "geometry": {"coordinates":[-2.525609,50.949974],"type":"Point"}
}
