{
  "type": "Feature",
  "properties": {
    "iso:country":"GB",
    "wof:name":"LS27 0RT",
    "wof:placetype":"postalcode"
},
  "geometry": {"coordinates":[-1.60457145596116,53.73783362288027],"type":"Point"}
}