{
  "type": "Feature",
  "properties": {
    "iso:country": "GB",
    "wof:name": "SR6 7XH",
    "wof:placetype": "postalcode"
  },
  "geometry": {"coordinates":[-1.399066,54.95899],"type":"Point"}
}
