{
  "type": "Feature",
  "properties": {
    "iso:country":"GB",
    "wof:name":"WV6 8AS",
    "wof:placetype":"postalcode"
},
  "geometry": {"coordinates":[-2.17926632695335,52.58843286165671],"type":"Point"}
}