{
  "type": "Feature",
  "properties": {
    "iso:country":"GB",
    "wof:name":"RG1 3LH",
    "wof:placetype":"postalcode"
},
  "geometry": {"coordinates":[-0.95168156210053,51.45383110570697],"type":"Point"}
}