{
  "type": "Feature",
  "properties": {
    "date:inception_lower":"1999-06-01",
    "date:inception_upper":"1999-06-30",
    "iso:country":"GB",
    "wof:name":"CH48 2HW",
    "wof:placetype":"postalcode"
},
  "geometry": {"coordinates":[-3.167994,53.358539],"type":"Point"}
}