{
  "type": "Feature",
  "properties": {
    "iso:country":"GB",
    "wof:name":"L39 2YA",
    "wof:placetype":"postalcode"
},
  "geometry": {"coordinates":[-2.87019993861977,53.56559439799236],"type":"Point"}
}