{
  "type": "Feature",
  "properties": {
    "date:inception_lower":"1981-09-01",
    "date:inception_upper":"1981-09-30",
    "iso:country":"GB",
    "wof:name":"L39 2YA",
    "wof:placetype":"postalcode"
},
  "geometry": {"coordinates":[-2.8702,53.565594],"type":"Point"}
}