{
  "type": "Feature",
  "properties": {
    "iso:country": "GB",
    "wof:name": "L39 2YA",
    "wof:placetype": "postalcode"
  },
  "geometry": {"coordinates":[-2.8702,53.565594],"type":"Point"}
}
