{
  "type": "Feature",
  "properties": {
    "iso:country":"GB",
    "wof:name":"IV1 1PX",
    "wof:placetype":"postalcode"
},
  "geometry": {"coordinates":[-4.22575889429352,57.47870300069619],"type":"Point"}
}