{
  "type": "Feature",
  "properties": {
    "iso:country":"GB",
    "wof:name":"CA10 1RU",
    "wof:placetype":"postalcode"
},
  "geometry": {"coordinates":[-2.60244614211573,54.63567741886562],"type":"Point"}
}