{
  "type": "Feature",
  "properties": {
    "date:inception_lower":"2000-06-01",
    "date:inception_upper":"2000-06-30",
    "iso:country":"GB",
    "wof:name":"CA10 1RU",
    "wof:placetype":"postalcode"
},
  "geometry": {"coordinates":[-2.602446,54.635677],"type":"Point"}
}