{
  "type": "Feature",
  "properties": {
    "iso:country":"GB",
    "wof:name":"CW9 7PB",
    "wof:placetype":"postalcode"
},
  "geometry": {"coordinates":[-2.45922272262162,53.26925930100476],"type":"Point"}
}