{
  "type": "Feature",
  "properties": {
    "date:inception_lower": "2019-06-01",
    "date:inception_upper": "2019-06-01",
    "iso:country": "GB",
    "wof:name": "WF17 6WH",
    "wof:placetype": "postalcode"
  },
  "geometry": {"coordinates":[-1.611625,53.708121],"type":"Point"}
}
