{
  "type": "Feature",
  "properties": {
    "iso:country":"GB",
    "wof:name":"LL32 8EQ",
    "wof:placetype":"postalcode"
},
  "geometry": {"coordinates":[-3.86619234638911,53.25528272072342],"type":"Point"}
}