{
  "type": "Feature",
  "properties": {
    "date:inception_lower": "1980-01-01",
    "date:inception_upper": "1980-01-01",
    "iso:country": "GB",
    "wof:name": "SA18 3HD",
    "wof:placetype": "postalcode"
  },
  "geometry": {"coordinates":[-3.994879,51.784818],"type":"Point"}
}
