{
  "type": "Feature",
  "properties": {
    "iso:country":"GB",
    "wof:name":"SA18 3HD",
    "wof:placetype":"postalcode"
},
  "geometry": {"coordinates":[-3.9950055998575,51.78472607539184],"type":"Point"}
}