{
  "type": "Feature",
  "properties": {
    "iso:country":"GB",
    "wof:name":"BS20 0DS",
    "wof:placetype":"postalcode"
},
  "geometry": {"coordinates":[-2.69027403365568,51.47838545397018],"type":"Point"}
}