{
  "type": "Feature",
  "properties": {
    "iso:country": "GB",
    "wof:name": "PE15 9JJ",
    "wof:placetype": "postalcode"
  },
  "geometry": {"coordinates":[0.087813,52.548569],"type":"Point"}
}
