{
  "type": "Feature",
  "properties": {
    "iso:country":"GB",
    "wof:name":"BS16 2PW",
    "wof:placetype":"postalcode"
},
  "geometry": {"coordinates":[-2.51783122045654,51.49034266856855],"type":"Point"}
}