{
  "type": "Feature",
  "properties": {
    "iso:country": "GB",
    "wof:name": "KA6 7LY",
    "wof:placetype": "postalcode"
  },
  "geometry": {"coordinates":[-4.50112,55.362289],"type":"Point"}
}
