{
  "type": "Feature",
  "properties": {
    "iso:country":"GB",
    "wof:name":"KA6 7LY",
    "wof:placetype":"postalcode"
},
  "geometry": {"coordinates":[-4.50107151796192,55.36223218750025],"type":"Point"}
}