{
  "type": "Feature",
  "properties": {
    "iso:country": "GB",
    "wof:name": "PE32 2PQ",
    "wof:placetype": "postalcode"
  },
  "geometry": {"coordinates":[0.79332,52.754055],"type":"Point"}
}
