{
  "type": "Feature",
  "properties": {
    "iso:country":"GB",
    "wof:name":"PE32 2PQ",
    "wof:placetype":"postalcode"
},
  "geometry": {"coordinates":[0.79331946915658,52.75405505290085],"type":"Point"}
}