{
  "type": "Feature",
  "properties": {
    "date:inception_lower": "1980-01-01",
    "date:inception_upper": "1980-01-01",
    "iso:country": "GB",
    "wof:name": "NG34 0PB",
    "wof:placetype": "postalcode"
  },
  "geometry": {"coordinates":[-0.33872,52.900126],"type":"Point"}
}
