{
  "type": "Feature",
  "properties": {
    "iso:country": "GB",
    "wof:name": "NG34 0PB",
    "wof:placetype": "postalcode"
  },
  "geometry": {"coordinates":[-0.339344,52.902067],"type":"Point"}
}
