{
  "type": "Feature",
  "properties": {
    "iso:country": "GB",
    "wof:name": "LA23 1EZ",
    "wof:placetype": "postalcode"
  },
  "geometry": {"coordinates":[-2.920935,54.386129],"type":"Point"}
}
