{
  "type": "Feature",
  "properties": {
    "iso:country":"GB",
    "wof:name":"CT5 4UN",
    "wof:placetype":"postalcode"
},
  "geometry": {"coordinates":[1.00808570364034,51.34053050517774],"type":"Point"}
}