{
  "type": "Feature",
  "properties": {
    "date:inception_lower": "2004-02-01",
    "date:inception_upper": "2004-02-01",
    "iso:country": "GB",
    "wof:name": "CT5 4UN",
    "wof:placetype": "postalcode"
  },
  "geometry": {"coordinates":[1.008086,51.34053],"type":"Point"}
}
