{
  "type": "Feature",
  "properties": {
    "iso:country":"GB",
    "wof:name":"BH11 8AL",
    "wof:placetype":"postalcode"
},
  "geometry": {"coordinates":[-1.90814611060431,50.76047888933645],"type":"Point"}
}