{
  "type": "Feature",
  "properties": {
    "iso:country":"GB",
    "wof:name":"BH21 3LJ",
    "wof:placetype":"postalcode"
},
  "geometry": {"coordinates":[-2.0207356249784,50.76678080321673],"type":"Point"}
}