{
  "type": "Feature",
  "properties": {
    "iso:country": "GB",
    "wof:name": "BH21 3LJ",
    "wof:placetype": "postalcode"
  },
  "geometry": {"coordinates":[-2.020736,50.766781],"type":"Point"}
}
