{
  "type": "Feature",
  "properties": {
    "iso:country":"GB",
    "wof:name":"CR2 0LJ",
    "wof:placetype":"postalcode"
},
  "geometry": {"coordinates":[-0.08373092041116,51.34370380501239],"type":"Point"}
}