{
  "type": "Feature",
  "properties": {
    "iso:country":"GB",
    "wof:name":"SK2 5QB",
    "wof:placetype":"postalcode"
},
  "geometry": {"coordinates":[-2.12871742813488,53.40038341100342],"type":"Point"}
}