{
  "type": "Feature",
  "properties": {
    "iso:country":"GB",
    "wof:name":"DN34 5PX",
    "wof:placetype":"postalcode"
},
  "geometry": {"coordinates":[-0.13041684435249,53.55235506992706],"type":"Point"}
}