{
  "type": "Feature",
  "properties": {
    "date:inception_lower": "1999-06-01",
    "date:inception_upper": "1999-06-01",
    "iso:country": "GB",
    "wof:name": "NP18 2AH",
    "wof:placetype": "postalcode"
  },
  "geometry": {"coordinates":[-2.865938,51.607661],"type":"Point"}
}
