{
  "type": "Feature",
  "properties": {
    "iso:country":"GB",
    "wof:name":"NP18 2AH",
    "wof:placetype":"postalcode"
},
  "geometry": {"coordinates":[-2.86593842649358,51.60766108731239],"type":"Point"}
}