{
  "type": "Feature",
  "properties": {
    "date:inception_lower": "2003-07-01",
    "date:inception_upper": "2003-07-01",
    "iso:country": "GB",
    "wof:name": "IP2 8SN",
    "wof:placetype": "postalcode"
  },
  "geometry": {"coordinates":[1.157735,52.05025],"type":"Point"}
}
