{
  "type": "Feature",
  "properties": {
    "iso:country":"GB",
    "wof:name":"IP2 8SN",
    "wof:placetype":"postalcode"
},
  "geometry": {"coordinates":[1.15757554252317,52.05047255579568],"type":"Point"}
}