{
  "type": "Feature",
  "properties": {
    "iso:country": "GB",
    "wof:name": "TD9 9LD",
    "wof:placetype": "postalcode"
  },
  "geometry": {"coordinates":[-2.783613,55.42583],"type":"Point"}
}
