{
  "type": "Feature",
  "properties": {
    "date:inception_lower":"2012-04-01",
    "date:inception_upper":"2012-04-30",
    "iso:country":"GB",
    "wof:name":"TD9 9LD",
    "wof:placetype":"postalcode"
},
  "geometry": {"coordinates":[-2.783613,55.42583],"type":"Point"}
}