{
  "type": "Feature",
  "properties": {
    "iso:country":"GB",
    "wof:name":"TD9 9LD",
    "wof:placetype":"postalcode"
},
  "geometry": {"coordinates":[-2.78361321285005,55.4258297776141],"type":"Point"}
}