{
  "type": "Feature",
  "properties": {
    "iso:country":"GB",
    "wof:name":"OL1 4JG",
    "wof:placetype":"postalcode"
},
  "geometry": {"coordinates":[-2.08461141212493,53.55440391282038],"type":"Point"}
}