{
  "type": "Feature",
  "properties": {
    "iso:country": "GB",
    "wof:name": "CO16 8XU",
    "wof:placetype": "postalcode"
  },
  "geometry": {"coordinates":[1.123278,51.800626],"type":"Point"}
}
