{
  "type": "Feature",
  "properties": {
    "iso:country":"GB",
    "wof:name":"WA8 8EJ",
    "wof:placetype":"postalcode"
},
  "geometry": {"coordinates":[-2.75728855209942,53.36581620157696],"type":"Point"}
}