{
  "type": "Feature",
  "properties": {
    "date:inception_lower": "2002-11-01",
    "date:inception_upper": "2002-11-01",
    "iso:country": "GB",
    "wof:name": "NN12 8TZ",
    "wof:placetype": "postalcode"
  },
  "geometry": {"coordinates":[-1.029624,52.085434],"type":"Point"}
}
