{
  "type": "Feature",
  "properties": {
    "iso:country":"GB",
    "wof:name":"NN12 8TZ",
    "wof:placetype":"postalcode"
},
  "geometry": {"coordinates":[-1.02962400048408,52.08543382572161],"type":"Point"}
}