{
  "type": "Feature",
  "properties": {
    "iso:country":"GB",
    "wof:name":"EX32 9DB",
    "wof:placetype":"postalcode"
},
  "geometry": {"coordinates":[-4.04031533118591,51.06869342608817],"type":"Point"}
}