{
  "type": "Feature",
  "properties": {
    "iso:country": "GB",
    "wof:name": "NR15 1JB",
    "wof:placetype": "postalcode"
  },
  "geometry": {"coordinates":[1.361079,52.538851],"type":"Point"}
}
