{
  "type": "Feature",
  "properties": {
    "date:inception_lower":"1980-01-01",
    "date:inception_upper":"1980-01-31",
    "iso:country":"GB",
    "wof:name":"NR15 1JB",
    "wof:placetype":"postalcode"
},
  "geometry": {"coordinates":[1.361079,52.538851],"type":"Point"}
}