{
  "type": "Feature",
  "properties": {
    "iso:country":"GB",
    "wof:name":"NR15 1JB",
    "wof:placetype":"postalcode"
},
  "geometry": {"coordinates":[1.36107870427436,52.53885082003084],"type":"Point"}
}