{
  "type": "Feature",
  "properties": {
    "iso:country":"GB",
    "wof:name":"DL11 7AY",
    "wof:placetype":"postalcode"
},
  "geometry": {"coordinates":[-1.7273156344626,54.51349956247649],"type":"Point"}
}