{
  "type": "Feature",
  "properties": {
    "iso:country": "GB",
    "wof:name": "PO9 5NZ",
    "wof:placetype": "postalcode"
  },
  "geometry": {"coordinates":[-0.967406,50.873671],"type":"Point"}
}
