{
  "type": "Feature",
  "properties": {
    "iso:country":"GB",
    "wof:name":"PO9 5NZ",
    "wof:placetype":"postalcode"
},
  "geometry": {"coordinates":[-0.96740590404381,50.87367093628969],"type":"Point"}
}