{
  "type": "Feature",
  "properties": {
    "iso:country":"GB",
    "wof:name":"DH7 6SD",
    "wof:placetype":"postalcode"
},
  "geometry": {"coordinates":[-1.6306793033221,54.80665976466507],"type":"Point"}
}