{
  "type": "Feature",
  "properties": {
    "iso:country":"GB",
    "wof:name":"BH12 2NL",
    "wof:placetype":"postalcode"
},
  "geometry": {"coordinates":[-1.93526433091657,50.73250297043066],"type":"Point"}
}