{
  "type": "Feature",
  "properties": {
    "iso:country":"GB",
    "wof:name":"NG10 5LS",
    "wof:placetype":"postalcode"
},
  "geometry": {"coordinates":[-1.29498995976276,52.91832775018698],"type":"Point"}
}