{
  "type": "Feature",
  "properties": {
    "date:inception_lower": "1980-01-01",
    "date:inception_upper": "1980-01-01",
    "iso:country": "GB",
    "wof:name": "NG10 5LS",
    "wof:placetype": "postalcode"
  },
  "geometry": {"coordinates":[-1.29499,52.918328],"type":"Point"}
}
