{
  "type": "Feature",
  "properties": {
    "iso:country": "GB",
    "wof:name": "NG10 5LS",
    "wof:placetype": "postalcode"
  },
  "geometry": {"coordinates":[-1.29499,52.918328],"type":"Point"}
}
