{
  "type": "Feature",
  "properties": {
    "date:inception_lower": "2023-02-01",
    "date:inception_upper": "2023-02-01",
    "iso:country": "GB",
    "wof:name": "DE6 4AT",
    "wof:placetype": "postalcode"
  },
  "geometry": {"coordinates":[-1.568126,52.946143],"type":"Point"}
}
