{
  "type": "Feature",
  "properties": {
    "date:inception_lower":"1996-12-01",
    "date:inception_upper":"1996-12-31",
    "iso:country":"GB",
    "wof:name":"PA35 1JP",
    "wof:placetype":"postalcode"
},
  "geometry": {"coordinates":[-5.235437,56.433253],"type":"Point"}
}