{
  "type": "Feature",
  "properties": {
    "iso:country": "GB",
    "wof:name": "CM8 3GA",
    "wof:placetype": "postalcode"
  },
  "geometry": {"coordinates":[0.689949,51.805759],"type":"Point"}
}
