{
  "type": "Feature",
  "properties": {
    "date:inception_lower": "2006-04-01",
    "date:inception_upper": "2006-04-01",
    "iso:country": "GB",
    "wof:name": "CM8 3GA",
    "wof:placetype": "postalcode"
  },
  "geometry": {"coordinates":[0.689949,51.805759],"type":"Point"}
}
