{
  "type": "Feature",
  "properties": {
    "iso:country":"GB",
    "wof:name":"CM8 3GA",
    "wof:placetype":"postalcode"
},
  "geometry": {"coordinates":[0.68992073884717,51.80574175331166],"type":"Point"}
}