{
  "type": "Feature",
  "properties": {
    "iso:country": "GB",
    "wof:name": "CM8 3GA",
    "wof:placetype": "postalcode"
  },
  "geometry": {"coordinates":[0.689964,51.805768],"type":"Point"}
}
