{
  "type": "Feature",
  "properties": {
    "iso:country": "GB",
    "wof:name": "MK42 7JA",
    "wof:placetype": "postalcode"
  },
  "geometry": {"coordinates":[-0.494672,52.112653],"type":"Point"}
}
