{
  "type": "Feature",
  "properties": {
    "iso:country":"GB",
    "wof:name":"MK42 7JA",
    "wof:placetype":"postalcode"
},
  "geometry": {"coordinates":[-0.49467188691522,52.11265312377218],"type":"Point"}
}