{
  "type": "Feature",
  "properties": {
    "iso:country":"GB",
    "wof:name":"SS15 6TL",
    "wof:placetype":"postalcode"
},
  "geometry": {"coordinates":[0.39965589048817,51.57819960693102],"type":"Point"}
}