{
  "type": "Feature",
  "properties": {
    "date:inception_lower": "1980-01-01",
    "date:inception_upper": "1980-01-01",
    "iso:country": "GB",
    "wof:name": "LS15 8HY",
    "wof:placetype": "postalcode"
  },
  "geometry": {"coordinates":[-1.440278,53.80761],"type":"Point"}
}
