{
  "type": "Feature",
  "properties": {
    "iso:country":"GB",
    "wof:name":"LS15 8HY",
    "wof:placetype":"postalcode"
},
  "geometry": {"coordinates":[-1.44027754854112,53.80761024154256],"type":"Point"}
}