{
  "type": "Feature",
  "properties": {
    "iso:country":"GB",
    "wof:name":"CT19 5TQ",
    "wof:placetype":"postalcode"
},
  "geometry": {"coordinates":[1.1822664559705,51.08978821601251],"type":"Point"}
}