{
  "type": "Feature",
  "properties": {
    "iso:country": "GB",
    "wof:name": "CT19 5TQ",
    "wof:placetype": "postalcode"
  },
  "geometry": {"coordinates":[1.182266,51.089788],"type":"Point"}
}
