{
  "type": "Feature",
  "properties": {
    "iso:country":"GB",
    "wof:name":"WS4 2HE",
    "wof:placetype":"postalcode"
},
  "geometry": {"coordinates":[-1.96461548782165,52.59448799147862],"type":"Point"}
}