{
  "type": "Feature",
  "properties": {
    "iso:country": "GB",
    "wof:name": "WS4 2HE",
    "wof:placetype": "postalcode"
  },
  "geometry": {"coordinates":[-1.964615,52.594488],"type":"Point"}
}
