{
  "type": "Feature",
  "properties": {
    "date:inception_lower":"1980-01-01",
    "date:inception_upper":"1980-01-31",
    "iso:country":"GB",
    "wof:name":"WS4 2HE",
    "wof:placetype":"postalcode"
},
  "geometry": {"coordinates":[-1.964615,52.594488],"type":"Point"}
}