{
  "type": "Feature",
  "properties": {
    "iso:country": "GB",
    "wof:name": "RH14 9XP",
    "wof:placetype": "postalcode"
  },
  "geometry": {"coordinates":[-0.452168,51.008055],"type":"Point"}
}
