{
  "type": "Feature",
  "properties": {
    "iso:country":"GB",
    "wof:name":"SW18 4FU",
    "wof:placetype":"postalcode"
},
  "geometry": {"coordinates":[-0.19364011244967,51.44424322275772],"type":"Point"}
}