{
  "type": "Feature",
  "properties": {
    "date:inception_lower":"2016-01-01",
    "date:inception_upper":"2016-01-31",
    "iso:country":"GB",
    "wof:name":"SW18 4FU",
    "wof:placetype":"postalcode"
},
  "geometry": {"coordinates":[-0.193211,51.443922],"type":"Point"}
}