{
  "type": "Feature",
  "properties": {
    "iso:country": "GB",
    "wof:name": "SW18 4FU",
    "wof:placetype": "postalcode"
  },
  "geometry": {"coordinates":[-0.193211,51.443922],"type":"Point"}
}
