{
  "type": "Feature",
  "properties": {
    "iso:country":"GB",
    "wof:name":"PO16 8QP",
    "wof:placetype":"postalcode"
},
  "geometry": {"coordinates":[-1.14108469973527,50.84887321409631],"type":"Point"}
}