{
  "type": "Feature",
  "properties": {
    "iso:country":"GB",
    "wof:name":"B44 0PS",
    "wof:placetype":"postalcode"
},
  "geometry": {"coordinates":[-1.88413734696721,52.54142377176607],"type":"Point"}
}