{
  "type": "Feature",
  "properties": {
    "iso:country":"GB",
    "wof:name":"SK9 7EP",
    "wof:placetype":"postalcode"
},
  "geometry": {"coordinates":[-2.23747086539951,53.30045134932468],"type":"Point"}
}