{
  "type": "Feature",
  "properties": {
    "iso:country":"GB",
    "wof:name":"HR4 8SJ",
    "wof:placetype":"postalcode"
},
  "geometry": {"coordinates":[-2.87443565018368,52.15889770829979],"type":"Point"}
}