{
  "type": "Feature",
  "properties": {
    "iso:country":"GB",
    "wof:name":"WA7 2JU",
    "wof:placetype":"postalcode"
},
  "geometry": {"coordinates":[-2.70034729681531,53.33833460535533],"type":"Point"}
}