{
  "type": "Feature",
  "properties": {
    "iso:country": "GB",
    "wof:name": "RH4 3HA",
    "wof:placetype": "postalcode"
  },
  "geometry": {"coordinates":[-0.33538,51.231465],"type":"Point"}
}
