{
  "type": "Feature",
  "properties": {
    "iso:country":"GB",
    "wof:name":"RH4 3HA",
    "wof:placetype":"postalcode"
},
  "geometry": {"coordinates":[-0.33538012152126,51.2314647750003],"type":"Point"}
}