{
  "type": "Feature",
  "properties": {
    "date:inception_lower": "1991-09-01",
    "date:inception_upper": "1991-09-01",
    "iso:country": "GB",
    "wof:name": "IP2 9UU",
    "wof:placetype": "postalcode"
  },
  "geometry": {"coordinates":[1.125083,52.037228],"type":"Point"}
}
