{
  "type": "Feature",
  "properties": {
    "iso:country":"GB",
    "wof:name":"IP2 9UU",
    "wof:placetype":"postalcode"
},
  "geometry": {"coordinates":[1.12508275431754,52.03722804575671],"type":"Point"}
}