{
  "type": "Feature",
  "properties": {
    "iso:country":"GB",
    "wof:name":"IP3 9SN",
    "wof:placetype":"postalcode"
},
  "geometry": {"coordinates":[1.20726546118009,52.03341685694944],"type":"Point"}
}