{
  "type": "Feature",
  "properties": {
    "iso:country":"GB",
    "wof:name":"WV14 6LP",
    "wof:placetype":"postalcode"
},
  "geometry": {"coordinates":[-2.07411683991455,52.57321795404694],"type":"Point"}
}