{
  "type": "Feature",
  "properties": {
    "iso:country":"GB",
    "wof:name":"IG8 7DG",
    "wof:placetype":"postalcode"
},
  "geometry": {"coordinates":[0.03402280038029,51.60096163013536],"type":"Point"}
}