{
  "type": "Feature",
  "properties": {
    "date:inception_lower": "1980-01-01",
    "date:inception_upper": "1980-01-01",
    "iso:country": "GB",
    "wof:name": "E17 5AL",
    "wof:placetype": "postalcode"
  },
  "geometry": {"coordinates":[-0.01507,51.598403],"type":"Point"}
}
