{
  "type": "Feature",
  "properties": {
    "date:inception_lower": "1995-12-01",
    "date:inception_upper": "1995-12-01",
    "iso:country": "GB",
    "wof:name": "MK44 3UP",
    "wof:placetype": "postalcode"
  },
  "geometry": {"coordinates":[-0.419264,52.128957],"type":"Point"}
}
