{
  "type": "Feature",
  "properties": {
    "iso:country":"GB",
    "wof:name":"SY5 9GH",
    "wof:placetype":"postalcode"
},
  "geometry": {"coordinates":[-2.86473263822353,52.68876796614833],"type":"Point"}
}