{
  "type": "Feature",
  "properties": {
    "iso:country":"GB",
    "wof:name":"AB43 6TJ",
    "wof:placetype":"postalcode"
},
  "geometry": {"coordinates":[-2.12306923451551,57.58282760596078],"type":"Point"}
}