{
  "type": "Feature",
  "properties": {
    "date:inception_lower": "2021-05-01",
    "date:inception_upper": "2021-05-01",
    "iso:country": "GB",
    "wof:name": "ML5 4GE",
    "wof:placetype": "postalcode"
  },
  "geometry": {"coordinates":[-3.996842,55.841667],"type":"Point"}
}
