{
  "type": "Feature",
  "properties": {
    "iso:country":"GB",
    "wof:name":"L15 8LW",
    "wof:placetype":"postalcode"
},
  "geometry": {"coordinates":[-2.91345213356711,53.40119993144438],"type":"Point"}
}