{
  "type": "Feature",
  "properties": {
    "date:inception_lower": "1980-01-01",
    "date:inception_upper": "1980-01-01",
    "iso:country": "GB",
    "wof:name": "PE24 4AY",
    "wof:placetype": "postalcode"
  },
  "geometry": {"coordinates":[0.279515,53.098845],"type":"Point"}
}
