{
  "type": "Feature",
  "properties": {
    "iso:country":"GB",
    "wof:name":"PE24 4AY",
    "wof:placetype":"postalcode"
},
  "geometry": {"coordinates":[0.27951226588216,53.09881800117717],"type":"Point"}
}