{
  "type": "Feature",
  "properties": {
    "iso:country": "GB",
    "wof:name": "PE24 4AY",
    "wof:placetype": "postalcode"
  },
  "geometry": {"coordinates":[0.279442,53.098874],"type":"Point"}
}
