{
  "type": "Feature",
  "properties": {
    "date:inception_lower": "1980-01-01",
    "date:inception_upper": "1980-01-01",
    "iso:country": "GB",
    "wof:name": "B60 3HD",
    "wof:placetype": "postalcode"
  },
  "geometry": {"coordinates":[-2.039071,52.313446],"type":"Point"}
}
