{
  "type": "Feature",
  "properties": {
    "iso:country":"GB",
    "wof:name":"B60 3HD",
    "wof:placetype":"postalcode"
},
  "geometry": {"coordinates":[-2.03909167542137,52.31345931507814],"type":"Point"}
}