{
  "type": "Feature",
  "properties": {
    "date:inception_lower": "1980-01-01",
    "date:inception_upper": "1980-01-01",
    "iso:country": "GB",
    "wof:name": "B60 3HD",
    "wof:placetype": "postalcode"
  },
  "geometry": {"coordinates":[-2.039092,52.313459],"type":"Point"}
}
