{
  "type": "Feature",
  "properties": {
    "date:inception_lower":"1980-01-01",
    "date:inception_upper":"1980-01-31",
    "iso:country":"GB",
    "wof:name":"DT9 4LU",
    "wof:placetype":"postalcode"
},
  "geometry": {"coordinates":[-2.529676,51.009644],"type":"Point"}
}