{
  "type": "Feature",
  "properties": {
    "iso:country":"GB",
    "wof:name":"DT9 4LU",
    "wof:placetype":"postalcode"
},
  "geometry": {"coordinates":[-2.52967611554364,51.00964395183449],"type":"Point"}
}