{
  "type": "Feature",
  "properties": {
    "iso:country":"GB",
    "wof:name":"IP30 0PH",
    "wof:placetype":"postalcode"
},
  "geometry": {"coordinates":[0.81486691000109,52.16878105393469],"type":"Point"}
}