{
  "type": "Feature",
  "properties": {
    "date:inception_lower": "2019-07-01",
    "date:inception_upper": "2019-07-01",
    "iso:country": "GB",
    "wof:name": "EX7 0GE",
    "wof:placetype": "postalcode"
  },
  "geometry": {"coordinates":[-3.454031,50.600995],"type":"Point"}
}
