{
  "type": "Feature",
  "properties": {
    "iso:country":"GB",
    "wof:name":"SE1 1EW",
    "wof:placetype":"postalcode"
},
  "geometry": {"coordinates":[-0.0957608839868,51.50225215193884],"type":"Point"}
}