{
  "type": "Feature",
  "properties": {
    "iso:country":"GB",
    "wof:name":"EX22 6LH",
    "wof:placetype":"postalcode"
},
  "geometry": {"coordinates":[-4.43173645903127,50.79094057337855],"type":"Point"}
}