{
  "type": "Feature",
  "properties": {
    "iso:country": "GB",
    "wof:name": "LE67 0EF",
    "wof:placetype": "postalcode"
  },
  "geometry": {"coordinates":[-1.375273,52.725708],"type":"Point"}
}
