{
  "type": "Feature",
  "properties": {
    "iso:country":"GB",
    "wof:name":"HP18 0SP",
    "wof:placetype":"postalcode"
},
  "geometry": {"coordinates":[-1.01153619210255,51.88123190398548],"type":"Point"}
}