{
  "type": "Feature",
  "properties": {
    "date:inception_lower": "1980-01-01",
    "date:inception_upper": "1980-01-01",
    "iso:country": "GB",
    "wof:name": "LE10 2DY",
    "wof:placetype": "postalcode"
  },
  "geometry": {"coordinates":[-1.364116,52.526397],"type":"Point"}
}
