{
  "type": "Feature",
  "properties": {
    "iso:country":"GB",
    "wof:name":"LE10 2DY",
    "wof:placetype":"postalcode"
},
  "geometry": {"coordinates":[-1.36411584753774,52.52639666938109],"type":"Point"}
}