{
  "type": "Feature",
  "properties": {
    "iso:country":"GB",
    "wof:name":"LS7 2JD",
    "wof:placetype":"postalcode"
},
  "geometry": {"coordinates":[-1.54703353476087,53.81584430016315],"type":"Point"}
}