{
  "type": "Feature",
  "properties": {
    "date:inception_lower": "2005-10-01",
    "date:inception_upper": "2005-10-01",
    "iso:country": "GB",
    "wof:name": "CO4 5FJ",
    "wof:placetype": "postalcode"
  },
  "geometry": {"coordinates":[0.913478,51.919398],"type":"Point"}
}
