{
  "type": "Feature",
  "properties": {
    "iso:country":"GB",
    "wof:name":"CO4 5FJ",
    "wof:placetype":"postalcode"
},
  "geometry": {"coordinates":[0.91347838941435,51.91939802130481],"type":"Point"}
}