{
  "type": "Feature",
  "properties": {
    "iso:country":"GB",
    "wof:name":"G74 2BN",
    "wof:placetype":"postalcode"
},
  "geometry": {"coordinates":[-4.15533269430494,55.76005117477921],"type":"Point"}
}