{
  "type": "Feature",
  "properties": {
    "iso:country": "GB",
    "wof:name": "G61 1PD",
    "wof:placetype": "postalcode"
  },
  "geometry": {"coordinates":[-4.335676,55.907927],"type":"Point"}
}
