{
  "type": "Feature",
  "properties": {
    "iso:country":"GB",
    "wof:name":"G61 1PD",
    "wof:placetype":"postalcode"
},
  "geometry": {"coordinates":[-4.33567564376795,55.90792717490436],"type":"Point"}
}