{
  "type": "Feature",
  "properties": {
    "date:inception_lower":"1980-01-01",
    "date:inception_upper":"1980-01-31",
    "iso:country":"GB",
    "wof:name":"PA14 6BE",
    "wof:placetype":"postalcode"
},
  "geometry": {"coordinates":[-4.649036,55.924753],"type":"Point"}
}