{
  "type": "Feature",
  "properties": {
    "iso:country":"GB",
    "wof:name":"SY1 2UG",
    "wof:placetype":"postalcode"
},
  "geometry": {"coordinates":[-2.73630771458916,52.72083012400743],"type":"Point"}
}