{
  "type": "Feature",
  "properties": {
    "iso:country": "GB",
    "wof:name": "SK5 6RL",
    "wof:placetype": "postalcode"
  },
  "geometry": {"coordinates":[-2.156375,53.449401],"type":"Point"}
}
