{
  "type": "Feature",
  "properties": {
    "iso:country":"GB",
    "wof:name":"SK5 6RL",
    "wof:placetype":"postalcode"
},
  "geometry": {"coordinates":[-2.15637539407421,53.44940073674898],"type":"Point"}
}