{
  "type": "Feature",
  "properties": {
    "date:inception_lower":"2016-11-01",
    "date:inception_upper":"2016-11-30",
    "iso:country":"GB",
    "wof:name":"PO7 7TZ",
    "wof:placetype":"postalcode"
},
  "geometry": {"coordinates":[-1.039308,50.885292],"type":"Point"}
}