{
  "type": "Feature",
  "properties": {
    "iso:country":"GB",
    "wof:name":"SO18 6TA",
    "wof:placetype":"postalcode"
},
  "geometry": {"coordinates":[-1.35178852152452,50.91840565963975],"type":"Point"}
}