{
  "type": "Feature",
  "properties": {
    "iso:country": "GB",
    "wof:name": "EX2 6LS",
    "wof:placetype": "postalcode"
  },
  "geometry": {"coordinates":[-3.49828,50.697619],"type":"Point"}
}
