{
  "type": "Feature",
  "properties": {
    "date:inception_lower": "1992-08-01",
    "date:inception_upper": "1992-08-01",
    "iso:country": "GB",
    "wof:name": "EX2 6LS",
    "wof:placetype": "postalcode"
  },
  "geometry": {"coordinates":[-3.49828,50.697619],"type":"Point"}
}
