{
  "type": "Feature",
  "properties": {
    "iso:country":"GB",
    "wof:name":"SS15 6SS",
    "wof:placetype":"postalcode"
},
  "geometry": {"coordinates":[0.4018045719005,51.57515193002295],"type":"Point"}
}