{
  "type": "Feature",
  "properties": {
    "date:inception_lower": "1987-04-01",
    "date:inception_upper": "1987-04-01",
    "iso:country": "GB",
    "wof:name": "SS15 6SS",
    "wof:placetype": "postalcode"
  },
  "geometry": {"coordinates":[0.401863,51.574875],"type":"Point"}
}
