{
  "type": "Feature",
  "properties": {
    "iso:country":"GB",
    "wof:name":"AB10 1UX",
    "wof:placetype":"postalcode"
},
  "geometry": {"coordinates":[-2.11456987740329,57.14514434914221],"type":"Point"}
}