{
  "type": "Feature",
  "properties": {
    "date:inception_lower": "2011-05-01",
    "date:inception_upper": "2011-05-01",
    "iso:country": "GB",
    "wof:name": "EC1M 5AD",
    "wof:placetype": "postalcode"
  },
  "geometry": {"coordinates":[-0.102894,51.520973],"type":"Point"}
}
