{
  "type": "Feature",
  "properties": {
    "iso:country":"GB",
    "wof:name":"EC1M 5AD",
    "wof:placetype":"postalcode"
},
  "geometry": {"coordinates":[-0.10289363558885,51.52097334213559],"type":"Point"}
}