{
  "type": "Feature",
  "properties": {
    "iso:country":"GB",
    "wof:name":"W1T 1NZ",
    "wof:placetype":"postalcode"
},
  "geometry": {"coordinates":[-0.13601750928951,51.51851889326509],"type":"Point"}
}