{
  "type": "Feature",
  "properties": {
    "iso:country":"GB",
    "wof:name":"CA6 6PR",
    "wof:placetype":"postalcode"
},
  "geometry": {"coordinates":[-2.7059695268151,55.06291653178609],"type":"Point"}
}