{
  "type": "Feature",
  "properties": {
    "iso:country":"GB",
    "wof:name":"RH20 1AB",
    "wof:placetype":"postalcode"
},
  "geometry": {"coordinates":[-0.51020891984216,50.95864329643968],"type":"Point"}
}