{
  "type": "Feature",
  "properties": {
    "iso:country": "GB",
    "wof:name": "SR7 8HT",
    "wof:placetype": "postalcode"
  },
  "geometry": {"coordinates":[-1.368883,54.834024],"type":"Point"}
}
