{
  "type": "Feature",
  "properties": {
    "iso:country":"GB",
    "wof:name":"SR7 8HT",
    "wof:placetype":"postalcode"
},
  "geometry": {"coordinates":[-1.36888349227054,54.8340239966675],"type":"Point"}
}