{
  "type": "Feature",
  "properties": {
    "date:inception_lower": "1997-06-01",
    "date:inception_upper": "1997-06-01",
    "iso:country": "GB",
    "wof:name": "MK18 4AD",
    "wof:placetype": "postalcode"
  },
  "geometry": {"coordinates":[-1.077187,51.99195],"type":"Point"}
}
