{
  "type": "Feature",
  "properties": {
    "iso:country": "GB",
    "wof:name": "MK18 4AD",
    "wof:placetype": "postalcode"
  },
  "geometry": {"coordinates":[-1.077187,51.99195],"type":"Point"}
}
