{
  "type": "Feature",
  "properties": {
    "iso:country":"GB",
    "wof:name":"MK18 4AD",
    "wof:placetype":"postalcode"
},
  "geometry": {"coordinates":[-1.07718717218218,51.99195049752183],"type":"Point"}
}