{
  "type": "Feature",
  "properties": {
    "iso:country": "GB",
    "wof:name": "MK42 6EU",
    "wof:placetype": "postalcode"
  },
  "geometry": {"coordinates":[-0.46874,52.086274],"type":"Point"}
}
