{
  "type": "Feature",
  "properties": {
    "iso:country": "GB",
    "wof:name": "S44 5JF",
    "wof:placetype": "postalcode"
  },
  "geometry": {"coordinates":[-1.348724,53.237887],"type":"Point"}
}
