{
  "type": "Feature",
  "properties": {
    "iso:country":"GB",
    "wof:name":"S44 5JF",
    "wof:placetype":"postalcode"
},
  "geometry": {"coordinates":[-1.34869653951252,53.2378408818464],"type":"Point"}
}