{
  "type": "Feature",
  "properties": {
    "iso:country": "GB",
    "wof:name": "SL5 9LS",
    "wof:placetype": "postalcode"
  },
  "geometry": {"coordinates":[-0.671242,51.395868],"type":"Point"}
}
