{
  "type": "Feature",
  "properties": {
    "iso:country":"GB",
    "wof:name":"SL5 9LS",
    "wof:placetype":"postalcode"
},
  "geometry": {"coordinates":[-0.67108584708361,51.3954246247897],"type":"Point"}
}