{
  "type": "Feature",
  "properties": {
    "iso:country": "GB",
    "wof:name": "TW9 4NB",
    "wof:placetype": "postalcode"
  },
  "geometry": {"coordinates":[-0.282341,51.468777],"type":"Point"}
}
