{
  "type": "Feature",
  "properties": {
    "iso:country":"GB",
    "wof:name":"TW9 4NB",
    "wof:placetype":"postalcode"
},
  "geometry": {"coordinates":[-0.28234107918924,51.46877691671728],"type":"Point"}
}