{
  "type": "Feature",
  "properties": {
    "date:inception_lower": "2008-01-01",
    "date:inception_upper": "2008-01-01",
    "iso:country": "GB",
    "wof:name": "TW9 4NB",
    "wof:placetype": "postalcode"
  },
  "geometry": {"coordinates":[-0.282341,51.468777],"type":"Point"}
}
