{
  "type": "Feature",
  "properties": {
    "iso:country": "GB",
    "wof:name": "PA1 1EG",
    "wof:placetype": "postalcode"
  },
  "geometry": {"coordinates":[-4.417877,55.845052],"type":"Point"}
}
