{
  "type": "Feature",
  "properties": {
    "date:inception_lower":"2011-07-01",
    "date:inception_upper":"2011-07-31",
    "iso:country":"GB",
    "wof:name":"PA1 1EG",
    "wof:placetype":"postalcode"
},
  "geometry": {"coordinates":[-4.417877,55.845052],"type":"Point"}
}