{
  "type": "Feature",
  "properties": {
    "date:inception_lower": "1980-01-01",
    "date:inception_upper": "1980-01-01",
    "iso:country": "GB",
    "wof:name": "SW18 3RG",
    "wof:placetype": "postalcode"
  },
  "geometry": {"coordinates":[-0.17328,51.449702],"type":"Point"}
}
