{
  "type": "Feature",
  "properties": {
    "iso:country":"GB",
    "wof:name":"BN8 4SP",
    "wof:placetype":"postalcode"
},
  "geometry": {"coordinates":[-0.01058234840669,50.90208751465718],"type":"Point"}
}