{
  "type": "Feature",
  "properties": {
    "iso:country": "GB",
    "wof:name": "BN8 4SP",
    "wof:placetype": "postalcode"
  },
  "geometry": {"coordinates":[-0.010582,50.902088],"type":"Point"}
}
