{
  "type": "Feature",
  "properties": {
    "iso:country":"GB",
    "wof:name":"L23 2XA",
    "wof:placetype":"postalcode"
},
  "geometry": {"coordinates":[-3.01762419607791,53.49313174505833],"type":"Point"}
}