{
  "type": "Feature",
  "properties": {
    "iso:country":"GB",
    "wof:name":"GU46 6EH",
    "wof:placetype":"postalcode"
},
  "geometry": {"coordinates":[-0.83372605131557,51.33668408778051],"type":"Point"}
}