{
  "type": "Feature",
  "properties": {
    "iso:country": "GB",
    "wof:name": "GU46 6EH",
    "wof:placetype": "postalcode"
  },
  "geometry": {"coordinates":[-0.833726,51.336684],"type":"Point"}
}
