{
  "type": "Feature",
  "properties": {
    "iso:country":"GB",
    "wof:name":"B71 3LJ",
    "wof:placetype":"postalcode"
},
  "geometry": {"coordinates":[-1.98215825607182,52.54513777893516],"type":"Point"}
}