{
  "type": "Feature",
  "properties": {
    "iso:country": "GB",
    "wof:name": "B71 3LJ",
    "wof:placetype": "postalcode"
  },
  "geometry": {"coordinates":[-1.982158,52.545138],"type":"Point"}
}
