{
  "type": "Feature",
  "properties": {
    "date:inception_lower": "1980-01-01",
    "date:inception_upper": "1980-01-01",
    "iso:country": "GB",
    "wof:name": "N15 4EG",
    "wof:placetype": "postalcode"
  },
  "geometry": {"coordinates":[-0.078862,51.587118],"type":"Point"}
}
