{
  "type": "Feature",
  "properties": {
    "date:inception_lower": "2020-09-01",
    "date:inception_upper": "2020-09-01",
    "iso:country": "GB",
    "wof:name": "PE1 1EN",
    "wof:placetype": "postalcode"
  },
  "geometry": {"coordinates":[-0.241417,52.568925],"type":"Point"}
}
