{
  "type": "Feature",
  "properties": {
    "date:inception_lower":"1980-01-01",
    "date:inception_upper":"1980-01-31",
    "iso:country":"GB",
    "wof:name":"HU3 6XW",
    "wof:placetype":"postalcode"
},
  "geometry": {"coordinates":[-0.388225,53.745088],"type":"Point"}
}