{
  "type": "Feature",
  "properties": {
    "iso:country":"GB",
    "wof:name":"DD11 2LQ",
    "wof:placetype":"postalcode"
},
  "geometry": {"coordinates":[-2.61361910824893,56.55496084393117],"type":"Point"}
}