{
  "type": "Feature",
  "properties": {
    "iso:country":"GB",
    "wof:name":"HR8 1PQ",
    "wof:placetype":"postalcode"
},
  "geometry": {"coordinates":[-2.39078031151681,51.99530084380261],"type":"Point"}
}