{
  "type": "Feature",
  "properties": {
    "date:inception_lower":"1980-01-01",
    "date:inception_upper":"1980-01-31",
    "iso:country":"GB",
    "wof:name":"HR8 1PQ",
    "wof:placetype":"postalcode"
},
  "geometry": {"coordinates":[-2.39078,51.995301],"type":"Point"}
}