{
  "type": "Feature",
  "properties": {
    "date:inception_lower": "2008-11-01",
    "date:inception_upper": "2008-11-01",
    "iso:country": "GB",
    "wof:name": "E8 2PE",
    "wof:placetype": "postalcode"
  },
  "geometry": {"coordinates":[-0.071903,51.546555],"type":"Point"}
}
