{
  "type": "Feature",
  "properties": {
    "date:inception_lower": "2008-08-01",
    "date:inception_upper": "2008-08-01",
    "iso:country": "GB",
    "wof:name": "RG8 8AH",
    "wof:placetype": "postalcode"
  },
  "geometry": {"coordinates":[-1.143375,51.481985],"type":"Point"}
}
