{
  "type": "Feature",
  "properties": {
    "iso:country":"GB",
    "wof:name":"RG8 8AH",
    "wof:placetype":"postalcode"
},
  "geometry": {"coordinates":[-1.14337502073283,51.4819854867722],"type":"Point"}
}