{
  "type": "Feature",
  "properties": {
    "iso:country":"GB",
    "wof:name":"BS5 0XE",
    "wof:placetype":"postalcode"
},
  "geometry": {"coordinates":[-2.56886766389749,51.45956164949979],"type":"Point"}
}