{
  "type": "Feature",
  "properties": {
    "iso:country": "GB",
    "wof:name": "DG11 1DB",
    "wof:placetype": "postalcode"
  },
  "geometry": {"coordinates":[-3.37407,55.071727],"type":"Point"}
}
