{
  "type": "Feature",
  "properties": {
    "date:inception_lower": "2015-03-01",
    "date:inception_upper": "2015-03-01",
    "iso:country": "GB",
    "wof:name": "TW8 9FY",
    "wof:placetype": "postalcode"
  },
  "geometry": {"coordinates":[-0.312478,51.488215],"type":"Point"}
}
