{
  "type": "Feature",
  "properties": {
    "iso:country":"GB",
    "wof:name":"PE11 3RB",
    "wof:placetype":"postalcode"
},
  "geometry": {"coordinates":[-0.16148689559295,52.81645973162719],"type":"Point"}
}