{
  "type": "Feature",
  "properties": {
    "iso:country": "GB",
    "wof:name": "BB12 7BD",
    "wof:placetype": "postalcode"
  },
  "geometry": {"coordinates":[-2.313208,53.795787],"type":"Point"}
}
