{
  "type": "Feature",
  "properties": {
    "date:inception_lower": "1980-01-01",
    "date:inception_upper": "1980-01-01",
    "iso:country": "GB",
    "wof:name": "BB12 7BD",
    "wof:placetype": "postalcode"
  },
  "geometry": {"coordinates":[-2.313208,53.795787],"type":"Point"}
}
