{
  "type": "Feature",
  "properties": {
    "iso:country":"GB",
    "wof:name":"LS23 7BQ",
    "wof:placetype":"postalcode"
},
  "geometry": {"coordinates":[-1.32143129902695,53.91974308439199],"type":"Point"}
}