{
  "type": "Feature",
  "properties": {
    "iso:country": "GB",
    "wof:name": "LS23 7BQ",
    "wof:placetype": "postalcode"
  },
  "geometry": {"coordinates":[-1.321431,53.919743],"type":"Point"}
}
