{
  "type": "Feature",
  "properties": {
    "iso:country":"GB",
    "wof:name":"BD12 0DJ",
    "wof:placetype":"postalcode"
},
  "geometry": {"coordinates":[-1.77321932824042,53.75922215950126],"type":"Point"}
}