{
  "type": "Feature",
  "properties": {
    "iso:country":"GB",
    "wof:name":"CW6 9RF",
    "wof:placetype":"postalcode"
},
  "geometry": {"coordinates":[-2.64652461644293,53.10491576628979],"type":"Point"}
}