{
  "type": "Feature",
  "properties": {
    "iso:country":"GB",
    "wof:name":"BS14 8NH",
    "wof:placetype":"postalcode"
},
  "geometry": {"coordinates":[-2.53522680575561,51.41500464208666],"type":"Point"}
}