{
  "type": "Feature",
  "properties": {
    "iso:country":"GB",
    "wof:name":"KT12 1NH",
    "wof:placetype":"postalcode"
},
  "geometry": {"coordinates":[-0.41927126526976,51.37264130787743],"type":"Point"}
}