{
  "type": "Feature",
  "properties": {
    "iso:country": "GB",
    "wof:name": "KT12 1NH",
    "wof:placetype": "postalcode"
  },
  "geometry": {"coordinates":[-0.419271,51.372641],"type":"Point"}
}
