{
  "type": "Feature",
  "properties": {
    "iso:country": "GB",
    "wof:name": "CV7 8QN",
    "wof:placetype": "postalcode"
  },
  "geometry": {"coordinates":[-1.580781,52.464538],"type":"Point"}
}
