{
  "type": "Feature",
  "properties": {
    "iso:country": "GB",
    "wof:name": "HU13 0RP",
    "wof:placetype": "postalcode"
  },
  "geometry": {"coordinates":[-0.441455,53.721243],"type":"Point"}
}
