{
  "type": "Feature",
  "properties": {
    "iso:country":"GB",
    "wof:name":"HU13 0RP",
    "wof:placetype":"postalcode"
},
  "geometry": {"coordinates":[-0.44145514155598,53.72124299791375],"type":"Point"}
}