{
  "type": "Feature",
  "properties": {
    "iso:country": "GB",
    "wof:name": "HP6 6DE",
    "wof:placetype": "postalcode"
  },
  "geometry": {"coordinates":[-0.598288,51.687608],"type":"Point"}
}
