{
  "type": "Feature",
  "properties": {
    "iso:country":"GB",
    "wof:name":"HP6 6DE",
    "wof:placetype":"postalcode"
},
  "geometry": {"coordinates":[-0.59828797306952,51.6876080930161],"type":"Point"}
}