{
  "type": "Feature",
  "properties": {
    "iso:country":"GB",
    "wof:name":"EH39 4HP",
    "wof:placetype":"postalcode"
},
  "geometry": {"coordinates":[-2.7168705950685,56.05891305068035],"type":"Point"}
}