{
  "type": "Feature",
  "properties": {
    "iso:country": "GB",
    "wof:name": "CF15 7PY",
    "wof:placetype": "postalcode"
  },
  "geometry": {"coordinates":[-3.2684,51.547425],"type":"Point"}
}
