{
  "type": "Feature",
  "properties": {
    "date:inception_lower":"1990-02-01",
    "date:inception_upper":"1990-02-28",
    "iso:country":"GB",
    "wof:name":"BS2 0ET",
    "wof:placetype":"postalcode"
},
  "geometry": {"coordinates":[-2.584464,51.454566],"type":"Point"}
}