{
  "type": "Feature",
  "properties": {
    "iso:country":"GB",
    "wof:name":"TW19 7TA",
    "wof:placetype":"postalcode"
},
  "geometry": {"coordinates":[-0.47242083340423,51.45188507333356],"type":"Point"}
}