{
  "type": "Feature",
  "properties": {
    "iso:country":"GB",
    "wof:name":"CT3 3BS",
    "wof:placetype":"postalcode"
},
  "geometry": {"coordinates":[1.19880530131858,51.22699560894763],"type":"Point"}
}