{
  "type": "Feature",
  "properties": {
    "date:inception_lower": "1980-01-01",
    "date:inception_upper": "1980-01-01",
    "iso:country": "GB",
    "wof:name": "CT3 3BS",
    "wof:placetype": "postalcode"
  },
  "geometry": {"coordinates":[1.198805,51.226996],"type":"Point"}
}
