{
  "type": "Feature",
  "properties": {
    "date:inception_lower": "1984-10-01",
    "date:inception_upper": "1984-10-01",
    "iso:country": "GB",
    "wof:name": "SK7 3PY",
    "wof:placetype": "postalcode"
  },
  "geometry": {"coordinates":[-2.150892,53.380798],"type":"Point"}
}
