{
  "type": "Feature",
  "properties": {
    "iso:country":"GB",
    "wof:name":"MK6 2JH",
    "wof:placetype":"postalcode"
},
  "geometry": {"coordinates":[-0.74609909899206,52.03372176525109],"type":"Point"}
}