{
  "type": "Feature",
  "properties": {
    "date:inception_lower":"1980-01-01",
    "date:inception_upper":"1980-01-31",
    "iso:country":"GB",
    "wof:name":"PL3 5LF",
    "wof:placetype":"postalcode"
},
  "geometry": {"coordinates":[-4.119584,50.391833],"type":"Point"}
}