{
  "type": "Feature",
  "properties": {
    "iso:country": "GB",
    "wof:name": "SL7 1LP",
    "wof:placetype": "postalcode"
  },
  "geometry": {"coordinates":[-0.771226,51.570817],"type":"Point"}
}
