{
  "type": "Feature",
  "properties": {
    "date:inception_lower":"1990-02-01",
    "date:inception_upper":"1990-02-28",
    "iso:country":"GB",
    "wof:name":"SL7 1LP",
    "wof:placetype":"postalcode"
},
  "geometry": {"coordinates":[-0.771226,51.570817],"type":"Point"}
}