{
  "type": "Feature",
  "properties": {
    "iso:country":"GB",
    "wof:name":"DD2 3ED",
    "wof:placetype":"postalcode"
},
  "geometry": {"coordinates":[-3.0110805728533,56.48061296440628],"type":"Point"}
}