{
  "type": "Feature",
  "properties": {
    "iso:country": "GB",
    "wof:name": "DD2 3ED",
    "wof:placetype": "postalcode"
  },
  "geometry": {"coordinates":[-3.011081,56.480613],"type":"Point"}
}
