{
  "type": "Feature",
  "properties": {
    "iso:country":"GB",
    "wof:name":"NG3 5NJ",
    "wof:placetype":"postalcode"
},
  "geometry": {"coordinates":[-1.1007979256969,52.99363500018084],"type":"Point"}
}