{
  "type": "Feature",
  "properties": {
    "date:inception_lower": "1980-01-01",
    "date:inception_upper": "1980-01-01",
    "iso:country": "GB",
    "wof:name": "L20 8LY",
    "wof:placetype": "postalcode"
  },
  "geometry": {"coordinates":[-2.997978,53.44474],"type":"Point"}
}
