{
  "type": "Feature",
  "properties": {
    "iso:country":"GB",
    "wof:name":"IP3 0JU",
    "wof:placetype":"postalcode"
},
  "geometry": {"coordinates":[1.17843684936988,52.03404584659204],"type":"Point"}
}