{
  "type": "Feature",
  "properties": {
    "iso:country":"GB",
    "wof:name":"CF47 8SB",
    "wof:placetype":"postalcode"
},
  "geometry": {"coordinates":[-3.38026080888327,51.75119359132688],"type":"Point"}
}