{
  "type": "Feature",
  "properties": {
    "iso:country": "GB",
    "wof:name": "CF47 8SB",
    "wof:placetype": "postalcode"
  },
  "geometry": {"coordinates":[-3.380261,51.751194],"type":"Point"}
}
