{
  "type": "Feature",
  "properties": {
    "iso:country": "GB",
    "wof:name": "YO12 5SA",
    "wof:placetype": "postalcode"
  },
  "geometry": {"coordinates":[-0.444407,54.296205],"type":"Point"}
}
