{
  "type": "Feature",
  "properties": {
    "iso:country":"GB",
    "wof:name":"DN12 4TA",
    "wof:placetype":"postalcode"
},
  "geometry": {"coordinates":[-1.24847941128302,53.49211177257889],"type":"Point"}
}