{
  "type": "Feature",
  "properties": {
    "iso:country":"GB",
    "wof:name":"EX31 4QW",
    "wof:placetype":"postalcode"
},
  "geometry": {"coordinates":[-3.90921763068169,51.20151571686288],"type":"Point"}
}