{
  "type": "Feature",
  "properties": {
    "date:inception_lower": "1980-01-01",
    "date:inception_upper": "1980-01-01",
    "iso:country": "GB",
    "wof:name": "EX31 4QW",
    "wof:placetype": "postalcode"
  },
  "geometry": {"coordinates":[-3.909218,51.201516],"type":"Point"}
}
