{
  "type": "Feature",
  "properties": {
    "iso:country":"GB",
    "wof:name":"NG17 4DR",
    "wof:placetype":"postalcode"
},
  "geometry": {"coordinates":[-1.25912164256927,53.13566936074834],"type":"Point"}
}