{
  "type": "Feature",
  "properties": {
    "date:inception_lower":"2011-10-01",
    "date:inception_upper":"2011-10-31",
    "iso:country":"GB",
    "wof:name":"SW9 6AF",
    "wof:placetype":"postalcode"
},
  "geometry": {"coordinates":[-0.105204,51.475715],"type":"Point"}
}