{
  "type": "Feature",
  "properties": {
    "iso:country":"GB",
    "wof:name":"SW9 6AF",
    "wof:placetype":"postalcode"
},
  "geometry": {"coordinates":[-0.10520401988352,51.4757151230332],"type":"Point"}
}