{
  "type": "Feature",
  "properties": {
    "iso:country":"GB",
    "wof:name":"TN12 0AW",
    "wof:placetype":"postalcode"
},
  "geometry": {"coordinates":[0.55189500023838,51.15949906280756],"type":"Point"}
}