{
  "type": "Feature",
  "properties": {
    "date:inception_lower": "1981-09-01",
    "date:inception_upper": "1981-09-01",
    "iso:country": "GB",
    "wof:name": "TN12 0AW",
    "wof:placetype": "postalcode"
  },
  "geometry": {"coordinates":[0.551895,51.159499],"type":"Point"}
}
