{
  "type": "Feature",
  "properties": {
    "iso:country":"GB",
    "wof:name":"LS8 1BD",
    "wof:placetype":"postalcode"
},
  "geometry": {"coordinates":[-1.51445598076928,53.84463134017791],"type":"Point"}
}