{
  "type": "Feature",
  "properties": {
    "date:inception_lower":"1982-04-01",
    "date:inception_upper":"1982-04-30",
    "iso:country":"GB",
    "wof:name":"EH4 3JF",
    "wof:placetype":"postalcode"
},
  "geometry": {"coordinates":[-3.231827,55.955099],"type":"Point"}
}