{
  "type": "Feature",
  "properties": {
    "iso:country": "GB",
    "wof:name": "PH2 0AD",
    "wof:placetype": "postalcode"
  },
  "geometry": {"coordinates":[-3.437078,56.380604],"type":"Point"}
}
