{
  "type": "Feature",
  "properties": {
    "date:inception_lower": "1980-01-01",
    "date:inception_upper": "1980-01-01",
    "iso:country": "GB",
    "wof:name": "S13 7GG",
    "wof:placetype": "postalcode"
  },
  "geometry": {"coordinates":[-1.38291,53.3602],"type":"Point"}
}
