{
  "type": "Feature",
  "properties": {
    "iso:country":"GB",
    "wof:name":"RH10 7PD",
    "wof:placetype":"postalcode"
},
  "geometry": {"coordinates":[-0.14552820792904,51.10682737720009],"type":"Point"}
}