{
  "type": "Feature",
  "properties": {
    "date:inception_lower": "2009-12-01",
    "date:inception_upper": "2009-12-01",
    "iso:country": "GB",
    "wof:name": "RH10 7PD",
    "wof:placetype": "postalcode"
  },
  "geometry": {"coordinates":[-0.145528,51.106827],"type":"Point"}
}
