{
  "type": "Feature",
  "properties": {
    "date:inception_lower": "1980-01-01",
    "date:inception_upper": "1980-01-01",
    "iso:country": "GB",
    "wof:name": "BL3 5QD",
    "wof:placetype": "postalcode"
  },
  "geometry": {"coordinates":[-2.454004,53.571306],"type":"Point"}
}
