{
  "type": "Feature",
  "properties": {
    "iso:country":"GB",
    "wof:name":"SY23 4RL",
    "wof:placetype":"postalcode"
},
  "geometry": {"coordinates":[-3.88131853180888,52.36135446060634],"type":"Point"}
}