{
  "type": "Feature",
  "properties": {
    "date:inception_lower": "2020-10-01",
    "date:inception_upper": "2020-10-01",
    "iso:country": "GB",
    "wof:name": "FY6 0FW",
    "wof:placetype": "postalcode"
  },
  "geometry": {"coordinates":[-2.967457,53.926356],"type":"Point"}
}
