{
  "type": "Feature",
  "properties": {
    "date:inception_lower": "2000-10-01",
    "date:inception_upper": "2000-10-01",
    "iso:country": "GB",
    "wof:name": "WD17 4NX",
    "wof:placetype": "postalcode"
  },
  "geometry": {"coordinates":[-0.406105,51.662651],"type":"Point"}
}
