{
  "type": "Feature",
  "properties": {
    "iso:country":"GB",
    "wof:name":"NG20 8BH",
    "wof:placetype":"postalcode"
},
  "geometry": {"coordinates":[-1.21815750456644,53.19865515669068],"type":"Point"}
}