{
  "type": "Feature",
  "properties": {
    "iso:country":"GB",
    "wof:name":"WF1 1QR",
    "wof:placetype":"postalcode"
},
  "geometry": {"coordinates":[-1.49661044364452,53.68492003375846],"type":"Point"}
}