{
  "type": "Feature",
  "properties": {
    "date:inception_lower":"1980-01-01",
    "date:inception_upper":"1980-01-31",
    "iso:country":"GB",
    "wof:name":"TQ7 3NQ",
    "wof:placetype":"postalcode"
},
  "geometry": {"coordinates":[-3.858096,50.274148],"type":"Point"}
}