{
  "type": "Feature",
  "properties": {
    "iso:country":"GB",
    "wof:name":"TQ7 3NQ",
    "wof:placetype":"postalcode"
},
  "geometry": {"coordinates":[-3.85809560522359,50.27414754417383],"type":"Point"}
}