{
  "type": "Feature",
  "properties": {
    "iso:country":"GB",
    "wof:name":"NN8 5EX",
    "wof:placetype":"postalcode"
},
  "geometry": {"coordinates":[-0.70701081354015,52.30578953396218],"type":"Point"}
}