{
  "type": "Feature",
  "properties": {
    "iso:country":"GB",
    "wof:name":"LE13 1SQ",
    "wof:placetype":"postalcode"
},
  "geometry": {"coordinates":[-0.87470358091445,52.76761248134452],"type":"Point"}
}