{
  "type": "Feature",
  "properties": {
    "date:inception_lower": "1980-01-01",
    "date:inception_upper": "1980-01-01",
    "iso:country": "GB",
    "wof:name": "LE13 1SQ",
    "wof:placetype": "postalcode"
  },
  "geometry": {"coordinates":[-0.875936,52.767267],"type":"Point"}
}
