{
  "type": "Feature",
  "properties": {
    "date:inception_lower":"1994-09-01",
    "date:inception_upper":"1994-09-30",
    "iso:country":"GB",
    "wof:name":"EH15 2BJ",
    "wof:placetype":"postalcode"
},
  "geometry": {"coordinates":[-3.108933,55.952807],"type":"Point"}
}