{
  "type": "Feature",
  "properties": {
    "iso:country":"GB",
    "wof:name":"EH15 2BJ",
    "wof:placetype":"postalcode"
},
  "geometry": {"coordinates":[-3.10893348558033,55.95280711078649],"type":"Point"}
}