{
  "type": "Feature",
  "properties": {
    "iso:country": "GB",
    "wof:name": "GL14 2LP",
    "wof:placetype": "postalcode"
  },
  "geometry": {"coordinates":[-2.503501,51.828071],"type":"Point"}
}
