{
  "type": "Feature",
  "properties": {
    "iso:country":"GB",
    "wof:name":"CF41 7RH",
    "wof:placetype":"postalcode"
},
  "geometry": {"coordinates":[-3.46434799450007,51.6446834981361],"type":"Point"}
}