{
  "type": "Feature",
  "properties": {
    "iso:country": "GB",
    "wof:name": "B23 5BJ",
    "wof:placetype": "postalcode"
  },
  "geometry": {"coordinates":[-1.844172,52.53314],"type":"Point"}
}
