{
  "type": "Feature",
  "properties": {
    "iso:country":"GB",
    "wof:name":"NE3 1NF",
    "wof:placetype":"postalcode"
},
  "geometry": {"coordinates":[-1.61629196861095,55.00322781830996],"type":"Point"}
}