{
  "type": "Feature",
  "properties": {
    "date:inception_lower":"2008-08-01",
    "date:inception_upper":"2008-08-31",
    "iso:country":"GB",
    "wof:name":"NE3 1NF",
    "wof:placetype":"postalcode"
},
  "geometry": {"coordinates":[-1.616292,55.003228],"type":"Point"}
}