{
  "type": "Feature",
  "properties": {
    "iso:country": "GB",
    "wof:name": "NE3 1NF",
    "wof:placetype": "postalcode"
  },
  "geometry": {"coordinates":[-1.616292,55.003228],"type":"Point"}
}
