{
  "type": "Feature",
  "properties": {
    "iso:country":"GB",
    "wof:name":"UB2 5AU",
    "wof:placetype":"postalcode"
},
  "geometry": {"coordinates":[-0.38532554071998,51.50308908950721],"type":"Point"}
}