{
  "type": "Feature",
  "properties": {
    "iso:country":"GB",
    "wof:name":"PH2 9ET",
    "wof:placetype":"postalcode"
},
  "geometry": {"coordinates":[-3.47634751355665,56.3461871344798],"type":"Point"}
}