{
  "type": "Feature",
  "properties": {
    "iso:country":"GB",
    "wof:name":"LN6 8EL",
    "wof:placetype":"postalcode"
},
  "geometry": {"coordinates":[-0.57637301359152,53.18935435283536],"type":"Point"}
}