{
  "type": "Feature",
  "properties": {
    "iso:country":"GB",
    "wof:name":"SK16 5BP",
    "wof:placetype":"postalcode"
},
  "geometry": {"coordinates":[-2.07084221709456,53.47150400141853],"type":"Point"}
}