{
  "type": "Feature",
  "properties": {
    "iso:country":"GB",
    "wof:name":"G3 6BQ",
    "wof:placetype":"postalcode"
},
  "geometry": {"coordinates":[-4.28030096648393,55.86925878255926],"type":"Point"}
}