{
  "type": "Feature",
  "properties": {
    "iso:country": "GB",
    "wof:name": "ME8 1AR",
    "wof:placetype": "postalcode"
  },
  "geometry": {"coordinates":[0.575512,51.36618],"type":"Point"}
}
