{
  "type": "Feature",
  "properties": {
    "iso:country": "GB",
    "wof:name": "YO16 6XH",
    "wof:placetype": "postalcode"
  },
  "geometry": {"coordinates":[-0.228265,54.134906],"type":"Point"}
}
