{
  "type": "Feature",
  "properties": {
    "iso:country":"GB",
    "wof:name":"YO16 6XH",
    "wof:placetype":"postalcode"
},
  "geometry": {"coordinates":[-0.22826454890153,54.13490584779056],"type":"Point"}
}