{
  "type": "Feature",
  "properties": {
    "date:inception_lower":"2013-07-01",
    "date:inception_upper":"2013-07-31",
    "iso:country":"GB",
    "wof:name":"DT1 1WF",
    "wof:placetype":"postalcode"
},
  "geometry": {"coordinates":[-2.438392,50.709484],"type":"Point"}
}