{
  "type": "Feature",
  "properties": {
    "iso:country": "GB",
    "wof:name": "DT1 1WF",
    "wof:placetype": "postalcode"
  },
  "geometry": {"coordinates":[-2.438392,50.709484],"type":"Point"}
}
