{
  "type": "Feature",
  "properties": {
    "iso:country":"GB",
    "wof:name":"ME13 0PA",
    "wof:placetype":"postalcode"
},
  "geometry": {"coordinates":[0.88123003443898,51.2760040212917],"type":"Point"}
}