{
  "type": "Feature",
  "properties": {
    "date:inception_lower": "1983-01-01",
    "date:inception_upper": "1983-01-01",
    "iso:country": "GB",
    "wof:name": "ME13 0PA",
    "wof:placetype": "postalcode"
  },
  "geometry": {"coordinates":[0.881194,51.276089],"type":"Point"}
}
