{
  "type": "Feature",
  "properties": {
    "iso:country":"GB",
    "wof:name":"SA43 2PH",
    "wof:placetype":"postalcode"
},
  "geometry": {"coordinates":[-4.59727238369851,52.04874579793074],"type":"Point"}
}