{
  "type": "Feature",
  "properties": {
    "iso:country": "GB",
    "wof:name": "SA43 2PH",
    "wof:placetype": "postalcode"
  },
  "geometry": {"coordinates":[-4.597683,52.048652],"type":"Point"}
}
