{
  "type": "Feature",
  "properties": {
    "iso:country":"GB",
    "wof:name":"NP19 8DP",
    "wof:placetype":"postalcode"
},
  "geometry": {"coordinates":[-2.98483433285347,51.59193238796446],"type":"Point"}
}