{
  "type": "Feature",
  "properties": {
    "iso:country": "GB",
    "wof:name": "L8 6XE",
    "wof:placetype": "postalcode"
  },
  "geometry": {"coordinates":[-2.97774,53.388223],"type":"Point"}
}
