{
  "type": "Feature",
  "properties": {
    "iso:country": "GB",
    "wof:name": "AL8 7DU",
    "wof:placetype": "postalcode"
  },
  "geometry": {"coordinates":[-0.215983,51.816476],"type":"Point"}
}
