{
  "type": "Feature",
  "properties": {
    "iso:country": "GB",
    "wof:name": "CV7 7QE",
    "wof:placetype": "postalcode"
  },
  "geometry": {"coordinates":[-1.651959,52.389344],"type":"Point"}
}
