{
  "type": "Feature",
  "properties": {
    "iso:country":"GB",
    "wof:name":"SG2 8AD",
    "wof:placetype":"postalcode"
},
  "geometry": {"coordinates":[-0.1838067549039,51.88117759261446],"type":"Point"}
}