{
  "type": "Feature",
  "properties": {
    "date:inception_lower": "1980-01-01",
    "date:inception_upper": "1980-01-01",
    "iso:country": "GB",
    "wof:name": "SG2 8AD",
    "wof:placetype": "postalcode"
  },
  "geometry": {"coordinates":[-0.183807,51.881178],"type":"Point"}
}
