{
  "type": "Feature",
  "properties": {
    "iso:country":"GB",
    "wof:name":"CR4 1NH",
    "wof:placetype":"postalcode"
},
  "geometry": {"coordinates":[-0.14289504341589,51.40001587757212],"type":"Point"}
}