{
  "type": "Feature",
  "properties": {
    "date:inception_lower": "1980-01-01",
    "date:inception_upper": "1980-01-01",
    "iso:country": "GB",
    "wof:name": "PA2 7NH",
    "wof:placetype": "postalcode"
  },
  "geometry": {"coordinates":[-4.385364,55.831944],"type":"Point"}
}
