{
  "type": "Feature",
  "properties": {
    "iso:country":"GB",
    "wof:name":"GU25 4RG",
    "wof:placetype":"postalcode"
},
  "geometry": {"coordinates":[-0.57859661937254,51.39885351378951],"type":"Point"}
}