{
  "type": "Feature",
  "properties": {
    "iso:country": "GB",
    "wof:name": "DY14 8EX",
    "wof:placetype": "postalcode"
  },
  "geometry": {"coordinates":[-2.483123,52.382655],"type":"Point"}
}
