{
  "type": "Feature",
  "properties": {
    "date:inception_lower": "2019-04-01",
    "date:inception_upper": "2019-04-01",
    "iso:country": "GB",
    "wof:name": "S70 5FB",
    "wof:placetype": "postalcode"
  },
  "geometry": {"coordinates":[-1.480427,53.502369],"type":"Point"}
}
