{
  "type": "Feature",
  "properties": {
    "iso:country":"GB",
    "wof:name":"NW7 4SL",
    "wof:placetype":"postalcode"
},
  "geometry": {"coordinates":[-0.24063959445524,51.61512066614942],"type":"Point"}
}