{
  "type": "Feature",
  "properties": {
    "date:inception_lower": "1980-01-01",
    "date:inception_upper": "1980-01-01",
    "iso:country": "GB",
    "wof:name": "NW7 4SL",
    "wof:placetype": "postalcode"
  },
  "geometry": {"coordinates":[-0.240434,51.615319],"type":"Point"}
}
