{
  "type": "Feature",
  "properties": {
    "iso:country": "GB",
    "wof:name": "SO30 2EU",
    "wof:placetype": "postalcode"
  },
  "geometry": {"coordinates":[-1.286307,50.915749],"type":"Point"}
}
