{
  "type": "Feature",
  "properties": {
    "iso:country":"GB",
    "wof:name":"IP31 1SJ",
    "wof:placetype":"postalcode"
},
  "geometry": {"coordinates":[0.72803571887985,52.26287351923556],"type":"Point"}
}