{
  "type": "Feature",
  "properties": {
    "date:inception_lower": "1980-01-01",
    "date:inception_upper": "1980-01-01",
    "iso:country": "GB",
    "wof:name": "IP31 1SJ",
    "wof:placetype": "postalcode"
  },
  "geometry": {"coordinates":[0.728227,52.262679],"type":"Point"}
}
