{
  "type": "Feature",
  "properties": {
    "iso:country":"GB",
    "wof:name":"NG9 4GG",
    "wof:placetype":"postalcode"
},
  "geometry": {"coordinates":[-1.24920623892548,52.92037564585564],"type":"Point"}
}