{
  "type": "Feature",
  "properties": {
    "iso:country":"GB",
    "wof:name":"CV5 6RE",
    "wof:placetype":"postalcode"
},
  "geometry": {"coordinates":[-1.52048580435713,52.39804474047983],"type":"Point"}
}