{
  "type": "Feature",
  "properties": {
    "iso:country":"GB",
    "wof:name":"NR19 2JU",
    "wof:placetype":"postalcode"
},
  "geometry": {"coordinates":[0.82256930174345,52.67072113219365],"type":"Point"}
}