{
  "type": "Feature",
  "properties": {
    "iso:country": "GB",
    "wof:name": "TS9 7DY",
    "wof:placetype": "postalcode"
  },
  "geometry": {"coordinates":[-1.252119,54.442258],"type":"Point"}
}
