{
  "type": "Feature",
  "properties": {
    "iso:country":"GB",
    "wof:name":"TS9 7DY",
    "wof:placetype":"postalcode"
},
  "geometry": {"coordinates":[-1.25211893915166,54.44225824377498],"type":"Point"}
}