{
  "type": "Feature",
  "properties": {
    "iso:country":"GB",
    "wof:name":"BS23 2UG",
    "wof:placetype":"postalcode"
},
  "geometry": {"coordinates":[-2.95553703185495,51.35596946315454],"type":"Point"}
}