{
  "type": "Feature",
  "properties": {
    "iso:country":"GB",
    "wof:name":"HP27 0RB",
    "wof:placetype":"postalcode"
},
  "geometry": {"coordinates":[-0.80755894612291,51.69040401123083],"type":"Point"}
}