{
  "type": "Feature",
  "properties": {
    "date:inception_lower": "1992-08-01",
    "date:inception_upper": "1992-08-01",
    "iso:country": "GB",
    "wof:name": "HP27 0RB",
    "wof:placetype": "postalcode"
  },
  "geometry": {"coordinates":[-0.807559,51.690404],"type":"Point"}
}
