{
  "type": "Feature",
  "properties": {
    "iso:country": "GB",
    "wof:name": "CF62 5BB",
    "wof:placetype": "postalcode"
  },
  "geometry": {"coordinates":[-3.279508,51.394898],"type":"Point"}
}
