{
  "type": "Feature",
  "properties": {
    "iso:country":"GB",
    "wof:name":"CF62 5BB",
    "wof:placetype":"postalcode"
},
  "geometry": {"coordinates":[-3.2798234667122,51.39470626195294],"type":"Point"}
}