{
  "type": "Feature",
  "properties": {
    "date:inception_lower":"2016-04-01",
    "date:inception_upper":"2016-04-30",
    "iso:country":"GB",
    "wof:name":"CF62 5BB",
    "wof:placetype":"postalcode"
},
  "geometry": {"coordinates":[-3.279508,51.394898],"type":"Point"}
}