{
  "type": "Feature",
  "properties": {
    "iso:country":"GB",
    "wof:name":"WC2A 3BP",
    "wof:placetype":"postalcode"
},
  "geometry": {"coordinates":[-0.1179783828697,51.51695389454169],"type":"Point"}
}