{
  "type": "Feature",
  "properties": {
    "iso:country": "GB",
    "wof:name": "NP15 1EZ",
    "wof:placetype": "postalcode"
  },
  "geometry": {"coordinates":[-2.853657,51.700797],"type":"Point"}
}
