{
  "type": "Feature",
  "properties": {
    "iso:country":"GB",
    "wof:name":"NP15 1EZ",
    "wof:placetype":"postalcode"
},
  "geometry": {"coordinates":[-2.85365064200433,51.70079468377056],"type":"Point"}
}