{
  "type": "Feature",
  "properties": {
    "iso:country":"GB",
    "wof:name":"CA11 0TW",
    "wof:placetype":"postalcode"
},
  "geometry": {"coordinates":[-2.8686422469142,54.66920838562778],"type":"Point"}
}