{
  "type": "Feature",
  "properties": {
    "iso:country": "GB",
    "wof:name": "NE10 9XD",
    "wof:placetype": "postalcode"
  },
  "geometry": {"coordinates":[-1.556641,54.945828],"type":"Point"}
}
