{
  "type": "Feature",
  "properties": {
    "iso:country": "GB",
    "wof:name": "CB5 8NY",
    "wof:placetype": "postalcode"
  },
  "geometry": {"coordinates":[0.13591,52.209713],"type":"Point"}
}
