{
  "type": "Feature",
  "properties": {
    "iso:country":"GB",
    "wof:name":"CB5 8NY",
    "wof:placetype":"postalcode"
},
  "geometry": {"coordinates":[0.1359095008136,52.20971260897217],"type":"Point"}
}