{
  "type": "Feature",
  "properties": {
    "date:inception_lower": "1980-01-01",
    "date:inception_upper": "1980-01-01",
    "iso:country": "GB",
    "wof:name": "B94 6ES",
    "wof:placetype": "postalcode"
  },
  "geometry": {"coordinates":[-1.73165,52.347226],"type":"Point"}
}
