{
  "type": "Feature",
  "properties": {
    "iso:country":"GB",
    "wof:name":"B94 6ES",
    "wof:placetype":"postalcode"
},
  "geometry": {"coordinates":[-1.73164990841666,52.3472255912425],"type":"Point"}
}