{
  "type": "Feature",
  "properties": {
    "iso:country": "GB",
    "wof:name": "LL33 0NL",
    "wof:placetype": "postalcode"
  },
  "geometry": {"coordinates":[-3.976526,53.253612],"type":"Point"}
}
