{
  "type": "Feature",
  "properties": {
    "date:inception_lower": "1980-01-01",
    "date:inception_upper": "1980-01-01",
    "iso:country": "GB",
    "wof:name": "LL33 0NL",
    "wof:placetype": "postalcode"
  },
  "geometry": {"coordinates":[-3.976526,53.253612],"type":"Point"}
}
