{
  "type": "Feature",
  "properties": {
    "iso:country": "GB",
    "wof:name": "LS9 0RF",
    "wof:placetype": "postalcode"
  },
  "geometry": {"coordinates":[-1.521535,53.790228],"type":"Point"}
}
