{
  "type": "Feature",
  "properties": {
    "iso:country": "GB",
    "wof:name": "HR4 8DT",
    "wof:placetype": "postalcode"
  },
  "geometry": {"coordinates":[-2.73185,52.120616],"type":"Point"}
}
