{
  "type": "Feature",
  "properties": {
    "date:inception_lower": "1980-01-01",
    "date:inception_upper": "1980-01-01",
    "iso:country": "GB",
    "wof:name": "HR4 8DT",
    "wof:placetype": "postalcode"
  },
  "geometry": {"coordinates":[-2.73185,52.120616],"type":"Point"}
}
