{
  "type": "Feature",
  "properties": {
    "iso:country":"GB",
    "wof:name":"HR4 8DT",
    "wof:placetype":"postalcode"
},
  "geometry": {"coordinates":[-2.7318497076302,52.12061562869354],"type":"Point"}
}