{
  "type": "Feature",
  "properties": {
    "iso:country":"GB",
    "wof:name":"W5 2PL",
    "wof:placetype":"postalcode"
},
  "geometry": {"coordinates":[-0.30142845398381,51.51423259514124],"type":"Point"}
}