{
  "type": "Feature",
  "properties": {
    "iso:country": "GB",
    "wof:name": "CF38 2LP",
    "wof:placetype": "postalcode"
  },
  "geometry": {"coordinates":[-3.353675,51.551732],"type":"Point"}
}
