{
  "type": "Feature",
  "properties": {
    "date:inception_lower": "1980-01-01",
    "date:inception_upper": "1980-01-01",
    "iso:country": "GB",
    "wof:name": "CF38 2LP",
    "wof:placetype": "postalcode"
  },
  "geometry": {"coordinates":[-3.353675,51.551732],"type":"Point"}
}
