{
  "type": "Feature",
  "properties": {
    "iso:country":"GB",
    "wof:name":"EX6 6DW",
    "wof:placetype":"postalcode"
},
  "geometry": {"coordinates":[-3.68896100400949,50.72565247331875],"type":"Point"}
}