{
  "type": "Feature",
  "properties": {
    "iso:country": "GB",
    "wof:name": "SR4 8AW",
    "wof:placetype": "postalcode"
  },
  "geometry": {"coordinates":[-1.435996,54.895453],"type":"Point"}
}
