{
  "type": "Feature",
  "properties": {
    "date:inception_lower": "1995-12-01",
    "date:inception_upper": "1995-12-01",
    "iso:country": "GB",
    "wof:name": "SO51 0DR",
    "wof:placetype": "postalcode"
  },
  "geometry": {"coordinates":[-1.529278,51.047414],"type":"Point"}
}
