{
  "type": "Feature",
  "properties": {
    "iso:country":"GB",
    "wof:name":"SO51 0DR",
    "wof:placetype":"postalcode"
},
  "geometry": {"coordinates":[-1.5292784862935,51.04741429137538],"type":"Point"}
}