{
  "type": "Feature",
  "properties": {
    "iso:country": "GB",
    "wof:name": "SO51 0DR",
    "wof:placetype": "postalcode"
  },
  "geometry": {"coordinates":[-1.529278,51.047414],"type":"Point"}
}
