{
  "type": "Feature",
  "properties": {
    "iso:country":"GB",
    "wof:name":"M40 3AZ",
    "wof:placetype":"postalcode"
},
  "geometry": {"coordinates":[-2.18463070626313,53.50322816241744],"type":"Point"}
}