{
  "type": "Feature",
  "properties": {
    "date:inception_lower":"2015-02-01",
    "date:inception_upper":"2015-02-28",
    "iso:country":"GB",
    "wof:name":"M40 3AZ",
    "wof:placetype":"postalcode"
},
  "geometry": {"coordinates":[-2.184613,53.503172],"type":"Point"}
}