{
  "type": "Feature",
  "properties": {
    "iso:country":"GB",
    "wof:name":"WS5 3EX",
    "wof:placetype":"postalcode"
},
  "geometry": {"coordinates":[-1.94273452739252,52.57405465784739],"type":"Point"}
}