{
  "type": "Feature",
  "properties": {
    "iso:country":"GB",
    "wof:name":"CO2 0BQ",
    "wof:placetype":"postalcode"
},
  "geometry": {"coordinates":[0.90841806858385,51.85798890798879],"type":"Point"}
}