{
  "type": "Feature",
  "properties": {
    "date:inception_lower":"1994-05-01",
    "date:inception_upper":"1994-05-31",
    "iso:country":"GB",
    "wof:name":"CO2 0BQ",
    "wof:placetype":"postalcode"
},
  "geometry": {"coordinates":[0.908418,51.857989],"type":"Point"}
}