{
  "type": "Feature",
  "properties": {
    "iso:country":"GB",
    "wof:name":"BS41 9BE",
    "wof:placetype":"postalcode"
},
  "geometry": {"coordinates":[-2.66339060967327,51.42879875337466],"type":"Point"}
}