{
  "type": "Feature",
  "properties": {
    "iso:country": "GB",
    "wof:name": "NR21 7EE",
    "wof:placetype": "postalcode"
  },
  "geometry": {"coordinates":[0.801303,52.79505],"type":"Point"}
}
