{
  "type": "Feature",
  "properties": {
    "iso:country":"GB",
    "wof:name":"NR21 7EE",
    "wof:placetype":"postalcode"
},
  "geometry": {"coordinates":[0.80094579897309,52.79596845336675],"type":"Point"}
}