{
  "type": "Feature",
  "properties": {
    "date:inception_lower":"1980-01-01",
    "date:inception_upper":"1980-01-31",
    "iso:country":"GB",
    "wof:name":"NN15 6PS",
    "wof:placetype":"postalcode"
},
  "geometry": {"coordinates":[-0.709621,52.388991],"type":"Point"}
}