{
  "type": "Feature",
  "properties": {
    "iso:country": "GB",
    "wof:name": "BA11 1PJ",
    "wof:placetype": "postalcode"
  },
  "geometry": {"coordinates":[-2.319383,51.223979],"type":"Point"}
}
