{
  "type": "Feature",
  "properties": {
    "iso:country":"GB",
    "wof:name":"BA11 1PJ",
    "wof:placetype":"postalcode"
},
  "geometry": {"coordinates":[-2.31938278640373,51.22397947865637],"type":"Point"}
}