{
  "type": "Feature",
  "properties": {
    "iso:country": "GB",
    "wof:name": "LL14 4BN",
    "wof:placetype": "postalcode"
  },
  "geometry": {"coordinates":[-3.02436,53.032712],"type":"Point"}
}
