{
  "type": "Feature",
  "properties": {
    "iso:country":"GB",
    "wof:name":"LL14 4BN",
    "wof:placetype":"postalcode"
},
  "geometry": {"coordinates":[-3.02436029763584,53.0327116873955],"type":"Point"}
}