{
  "type": "Feature",
  "properties": {
    "iso:country": "GB",
    "wof:name": "AB33 8QE",
    "wof:placetype": "postalcode"
  },
  "geometry": {"coordinates":[-2.720121,57.238836],"type":"Point"}
}
