{
  "type": "Feature",
  "properties": {
    "date:inception_lower": "1980-01-01",
    "date:inception_upper": "1980-01-01",
    "iso:country": "GB",
    "wof:name": "NN7 4LA",
    "wof:placetype": "postalcode"
  },
  "geometry": {"coordinates":[-1.098273,52.261387],"type":"Point"}
}
