{
  "type": "Feature",
  "properties": {
    "iso:country":"GB",
    "wof:name":"NN7 4LA",
    "wof:placetype":"postalcode"
},
  "geometry": {"coordinates":[-1.09827255248635,52.26138738806364],"type":"Point"}
}