{
  "type": "Feature",
  "properties": {
    "iso:country": "GB",
    "wof:name": "NN7 4LA",
    "wof:placetype": "postalcode"
  },
  "geometry": {"coordinates":[-1.098273,52.261387],"type":"Point"}
}
