{
  "type": "Feature",
  "properties": {
    "iso:country":"GB",
    "wof:name":"NG5 6EP",
    "wof:placetype":"postalcode"
},
  "geometry": {"coordinates":[-1.15260114033738,52.99513005188327],"type":"Point"}
}