{
  "type": "Feature",
  "properties": {
    "iso:country": "GB",
    "wof:name": "NG5 6EP",
    "wof:placetype": "postalcode"
  },
  "geometry": {"coordinates":[-1.152601,52.99513],"type":"Point"}
}
