{
  "type": "Feature",
  "properties": {
    "iso:country":"GB",
    "wof:name":"HD7 5AP",
    "wof:placetype":"postalcode"
},
  "geometry": {"coordinates":[-1.8818243853704,53.62247109497427],"type":"Point"}
}