{
  "type": "Feature",
  "properties": {
    "iso:country":"GB",
    "wof:name":"YO26 8AJ",
    "wof:placetype":"postalcode"
},
  "geometry": {"coordinates":[-1.32175969614446,54.0121944264962],"type":"Point"}
}