{
  "type": "Feature",
  "properties": {
    "iso:country": "GB",
    "wof:name": "YO26 8AJ",
    "wof:placetype": "postalcode"
  },
  "geometry": {"coordinates":[-1.32176,54.012194],"type":"Point"}
}
