{
  "type": "Feature",
  "properties": {
    "iso:country":"GB",
    "wof:name":"S63 8DZ",
    "wof:placetype":"postalcode"
},
  "geometry": {"coordinates":[-1.33223003827377,53.51854086400834],"type":"Point"}
}