{
  "type": "Feature",
  "properties": {
    "iso:country":"GB",
    "wof:name":"BR7 5JX",
    "wof:placetype":"postalcode"
},
  "geometry": {"coordinates":[0.05812491487162,51.40913059353872],"type":"Point"}
}