{
  "type": "Feature",
  "properties": {
    "iso:country":"GB",
    "wof:name":"BA2 4PZ",
    "wof:placetype":"postalcode"
},
  "geometry": {"coordinates":[-2.3600565621108,51.37672211197468],"type":"Point"}
}