{
  "type": "Feature",
  "properties": {
    "date:inception_lower": "2016-01-01",
    "date:inception_upper": "2016-01-01",
    "iso:country": "GB",
    "wof:name": "SW4 8AA",
    "wof:placetype": "postalcode"
  },
  "geometry": {"coordinates":[-0.129813,51.457792],"type":"Point"}
}
