{
  "type": "Feature",
  "properties": {
    "iso:country":"GB",
    "wof:name":"SW4 8AA",
    "wof:placetype":"postalcode"
},
  "geometry": {"coordinates":[-0.12981258683299,51.4577923264897],"type":"Point"}
}