{
  "type": "Feature",
  "properties": {
    "date:inception_lower": "1990-02-01",
    "date:inception_upper": "1990-02-01",
    "iso:country": "GB",
    "wof:name": "TR27 4QB",
    "wof:placetype": "postalcode"
  },
  "geometry": {"coordinates":[-5.40146,50.194333],"type":"Point"}
}
