{
  "type": "Feature",
  "properties": {
    "iso:country":"GB",
    "wof:name":"RH5 5HT",
    "wof:placetype":"postalcode"
},
  "geometry": {"coordinates":[-0.33601305660544,51.15152822815501],"type":"Point"}
}