{
  "type": "Feature",
  "properties": {
    "date:inception_lower": "1980-01-01",
    "date:inception_upper": "1980-01-01",
    "iso:country": "GB",
    "wof:name": "RH5 5HT",
    "wof:placetype": "postalcode"
  },
  "geometry": {"coordinates":[-0.336013,51.151528],"type":"Point"}
}
