{
  "type": "Feature",
  "properties": {
    "date:inception_lower": "2005-07-01",
    "date:inception_upper": "2005-07-01",
    "iso:country": "GB",
    "wof:name": "MK45 5ET",
    "wof:placetype": "postalcode"
  },
  "geometry": {"coordinates":[-0.498207,51.984447],"type":"Point"}
}
