{
  "type": "Feature",
  "properties": {
    "iso:country":"GB",
    "wof:name":"DH7 6TN",
    "wof:placetype":"postalcode"
},
  "geometry": {"coordinates":[-1.65865337981516,54.8064809908298],"type":"Point"}
}