{
  "type": "Feature",
  "properties": {
    "date:inception_lower":"1980-01-01",
    "date:inception_upper":"1980-01-31",
    "iso:country":"GB",
    "wof:name":"SW20 8AT",
    "wof:placetype":"postalcode"
},
  "geometry": {"coordinates":[-0.224759,51.41659],"type":"Point"}
}