{
  "type": "Feature",
  "properties": {
    "iso:country":"GB",
    "wof:name":"PO10 8FG",
    "wof:placetype":"postalcode"
},
  "geometry": {"coordinates":[-0.92124052618279,50.8614639735019],"type":"Point"}
}