{
  "type": "Feature",
  "properties": {
    "iso:country": "GB",
    "wof:name": "LU7 9GE",
    "wof:placetype": "postalcode"
  },
  "geometry": {"coordinates":[-0.637406,51.826378],"type":"Point"}
}
