{
  "type": "Feature",
  "properties": {
    "iso:country": "GB",
    "wof:name": "EX2 7GP",
    "wof:placetype": "postalcode"
  },
  "geometry": {"coordinates":[-3.484467,50.699197],"type":"Point"}
}
