{
  "type": "Feature",
  "properties": {
    "iso:country": "GB",
    "wof:name": "GL1 2QQ",
    "wof:placetype": "postalcode"
  },
  "geometry": {"coordinates":[-2.243216,51.872533],"type":"Point"}
}
