{
  "type": "Feature",
  "properties": {
    "date:inception_lower":"1980-01-01",
    "date:inception_upper":"1980-01-31",
    "iso:country":"GB",
    "wof:name":"GL1 2QQ",
    "wof:placetype":"postalcode"
},
  "geometry": {"coordinates":[-2.243216,51.872533],"type":"Point"}
}