{
  "type": "Feature",
  "properties": {
    "iso:country":"GB",
    "wof:name":"TQ7 2SU",
    "wof:placetype":"postalcode"
},
  "geometry": {"coordinates":[-3.67720190899095,50.27354479727402],"type":"Point"}
}