{
  "type": "Feature",
  "properties": {
    "iso:country":"GB",
    "wof:name":"LL53 6AD",
    "wof:placetype":"postalcode"
},
  "geometry": {"coordinates":[-4.5436370571595,52.92997711265435],"type":"Point"}
}