{
  "type": "Feature",
  "properties": {
    "iso:country": "GB",
    "wof:name": "LL53 6AD",
    "wof:placetype": "postalcode"
  },
  "geometry": {"coordinates":[-4.543637,52.929977],"type":"Point"}
}
