{
  "type": "Feature",
  "properties": {
    "date:inception_lower":"1992-08-01",
    "date:inception_upper":"1992-08-31",
    "iso:country":"GB",
    "wof:name":"DE74 2DZ",
    "wof:placetype":"postalcode"
},
  "geometry": {"coordinates":[-1.280573,52.83295],"type":"Point"}
}