{
  "type": "Feature",
  "properties": {
    "iso:country":"GB",
    "wof:name":"CF10 3WT",
    "wof:placetype":"postalcode"
},
  "geometry": {"coordinates":[-3.18171503047858,51.48582756446532],"type":"Point"}
}