{
  "type": "Feature",
  "properties": {
    "date:inception_lower":"2000-06-01",
    "date:inception_upper":"2000-06-30",
    "iso:country":"GB",
    "wof:name":"CF10 3WT",
    "wof:placetype":"postalcode"
},
  "geometry": {"coordinates":[-3.181715,51.485828],"type":"Point"}
}