{
  "type": "Feature",
  "properties": {
    "date:inception_lower": "2017-10-01",
    "date:inception_upper": "2017-10-01",
    "iso:country": "GB",
    "wof:name": "TW8 0RS",
    "wof:placetype": "postalcode"
  },
  "geometry": {"coordinates":[-0.29756,51.489835],"type":"Point"}
}
