{
  "type": "Feature",
  "properties": {
    "iso:country":"GB",
    "wof:name":"BL1 8RA",
    "wof:placetype":"postalcode"
},
  "geometry": {"coordinates":[-2.43090294195427,53.60423441660421],"type":"Point"}
}