{
  "type": "Feature",
  "properties": {
    "iso:country":"GB",
    "wof:name":"N19 3LY",
    "wof:placetype":"postalcode"
},
  "geometry": {"coordinates":[-0.12835759415702,51.5713895805444],"type":"Point"}
}