{
  "type": "Feature",
  "properties": {
    "date:inception_lower": "1980-01-01",
    "date:inception_upper": "1980-01-01",
    "iso:country": "GB",
    "wof:name": "CA28 8SS",
    "wof:placetype": "postalcode"
  },
  "geometry": {"coordinates":[-3.560972,54.534835],"type":"Point"}
}
