{
  "type": "Feature",
  "properties": {
    "iso:country":"GB",
    "wof:name":"W1T 7PE",
    "wof:placetype":"postalcode"
},
  "geometry": {"coordinates":[-0.13542746398594,51.52202558355174],"type":"Point"}
}