{
  "type": "Feature",
  "properties": {
    "iso:country":"GB",
    "wof:name":"GL17 0DX",
    "wof:placetype":"postalcode"
},
  "geometry": {"coordinates":[-2.47856850940009,51.85381979967501],"type":"Point"}
}