{
  "type": "Feature",
  "properties": {
    "iso:country":"GB",
    "wof:name":"BN11 5QW",
    "wof:placetype":"postalcode"
},
  "geometry": {"coordinates":[-0.40090979325929,50.81203093414616],"type":"Point"}
}