{
  "type": "Feature",
  "properties": {
    "date:inception_lower": "1980-01-01",
    "date:inception_upper": "1980-01-01",
    "iso:country": "GB",
    "wof:name": "BN11 5QW",
    "wof:placetype": "postalcode"
  },
  "geometry": {"coordinates":[-0.40091,50.812031],"type":"Point"}
}
