{
  "type": "Feature",
  "properties": {
    "iso:country":"GB",
    "wof:name":"B18 4QA",
    "wof:placetype":"postalcode"
},
  "geometry": {"coordinates":[-1.9378412949967,52.4966673616203],"type":"Point"}
}