{
  "type": "Feature",
  "properties": {
    "date:inception_lower": "1980-01-01",
    "date:inception_upper": "1980-01-01",
    "iso:country": "GB",
    "wof:name": "CB5 8QD",
    "wof:placetype": "postalcode"
  },
  "geometry": {"coordinates":[0.155551,52.215119],"type":"Point"}
}
