{
  "type": "Feature",
  "properties": {
    "iso:country":"GB",
    "wof:name":"CB5 8QD",
    "wof:placetype":"postalcode"
},
  "geometry": {"coordinates":[0.15555081868117,52.21511922623028],"type":"Point"}
}