{
  "type": "Feature",
  "properties": {
    "iso:country": "GB",
    "wof:name": "S40 2DE",
    "wof:placetype": "postalcode"
  },
  "geometry": {"coordinates":[-1.451528,53.230548],"type":"Point"}
}
