{
  "type": "Feature",
  "properties": {
    "iso:country":"GB",
    "wof:name":"S40 2DE",
    "wof:placetype":"postalcode"
},
  "geometry": {"coordinates":[-1.45154371418599,53.23054683342151],"type":"Point"}
}