{
  "type": "Feature",
  "properties": {
    "iso:country":"GB",
    "wof:name":"SR7 8EN",
    "wof:placetype":"postalcode"
},
  "geometry": {"coordinates":[-1.36719044608246,54.83477006115363],"type":"Point"}
}