{
  "type": "Feature",
  "properties": {
    "iso:country":"GB",
    "wof:name":"EX16 6PA",
    "wof:placetype":"postalcode"
},
  "geometry": {"coordinates":[-3.4894182211924,50.90340647498355],"type":"Point"}
}