{
  "type": "Feature",
  "properties": {
    "iso:country": "GB",
    "wof:name": "DT2 7TQ",
    "wof:placetype": "postalcode"
  },
  "geometry": {"coordinates":[-2.402223,50.774326],"type":"Point"}
}
