{
  "type": "Feature",
  "properties": {
    "iso:country":"GB",
    "wof:name":"DT2 7TQ",
    "wof:placetype":"postalcode"
},
  "geometry": {"coordinates":[-2.4022235209984,50.77432550555896],"type":"Point"}
}