{
  "type": "Feature",
  "properties": {
    "date:inception_lower":"1980-01-01",
    "date:inception_upper":"1980-01-31",
    "iso:country":"GB",
    "wof:name":"DT2 7TQ",
    "wof:placetype":"postalcode"
},
  "geometry": {"coordinates":[-2.402223,50.774326],"type":"Point"}
}