{
  "type": "Feature",
  "properties": {
    "date:inception_lower":"1995-12-01",
    "date:inception_upper":"1995-12-31",
    "iso:country":"GB",
    "wof:name":"SW11 5GZ",
    "wof:placetype":"postalcode"
},
  "geometry": {"coordinates":[-0.151982,51.466032],"type":"Point"}
}