{
  "type": "Feature",
  "properties": {
    "iso:country": "GB",
    "wof:name": "ME16 0GJ",
    "wof:placetype": "postalcode"
  },
  "geometry": {"coordinates":[0.484141,51.270106],"type":"Point"}
}
