{
  "type": "Feature",
  "properties": {
    "iso:country":"GB",
    "wof:name":"W1D 6DQ",
    "wof:placetype":"postalcode"
},
  "geometry": {"coordinates":[-0.13254828927522,51.51100891649618],"type":"Point"}
}