{
  "type": "Feature",
  "properties": {
    "iso:country": "GB",
    "wof:name": "BL5 2EQ",
    "wof:placetype": "postalcode"
  },
  "geometry": {"coordinates":[-2.523831,53.533547],"type":"Point"}
}
