{
  "type": "Feature",
  "properties": {
    "date:inception_lower":"1996-06-01",
    "date:inception_upper":"1996-06-30",
    "iso:country":"GB",
    "wof:name":"BR5 3WG",
    "wof:placetype":"postalcode"
},
  "geometry": {"coordinates":[0.1207,51.395658],"type":"Point"}
}