{
  "type": "Feature",
  "properties": {
    "iso:country": "GB",
    "wof:name": "BR5 3WG",
    "wof:placetype": "postalcode"
  },
  "geometry": {"coordinates":[0.1207,51.395658],"type":"Point"}
}
