{
  "type": "Feature",
  "properties": {
    "iso:country":"GB",
    "wof:name":"BR5 3WG",
    "wof:placetype":"postalcode"
},
  "geometry": {"coordinates":[0.12070031668937,51.39565843901855],"type":"Point"}
}