{
  "type": "Feature",
  "properties": {
    "iso:country": "GB",
    "wof:name": "KT10 9EF",
    "wof:placetype": "postalcode"
  },
  "geometry": {"coordinates":[-0.356694,51.363624],"type":"Point"}
}
