{
  "type": "Feature",
  "properties": {
    "date:inception_lower":"1992-01-01",
    "date:inception_upper":"1992-01-31",
    "iso:country":"GB",
    "wof:name":"PL26 7PS",
    "wof:placetype":"postalcode"
},
  "geometry": {"coordinates":[-4.889937,50.348742],"type":"Point"}
}