{
  "type": "Feature",
  "properties": {
    "iso:country": "GB",
    "wof:name": "TQ5 9JX",
    "wof:placetype": "postalcode"
  },
  "geometry": {"coordinates":[-3.5162,50.387227],"type":"Point"}
}
