{
  "type": "Feature",
  "properties": {
    "date:inception_lower": "1980-01-01",
    "date:inception_upper": "1980-01-01",
    "iso:country": "GB",
    "wof:name": "TQ5 9JX",
    "wof:placetype": "postalcode"
  },
  "geometry": {"coordinates":[-3.5162,50.387227],"type":"Point"}
}
