{
  "type": "Feature",
  "properties": {
    "iso:country":"GB",
    "wof:name":"TQ5 9JX",
    "wof:placetype":"postalcode"
},
  "geometry": {"coordinates":[-3.51620038877224,50.38722708583779],"type":"Point"}
}