{
  "type": "Feature",
  "properties": {
    "date:inception_lower": "1991-09-01",
    "date:inception_upper": "1991-09-01",
    "iso:country": "GB",
    "wof:name": "NN6 9SF",
    "wof:placetype": "postalcode"
  },
  "geometry": {"coordinates":[-0.838166,52.319155],"type":"Point"}
}
