{
  "type": "Feature",
  "properties": {
    "iso:country":"GB",
    "wof:name":"NN6 9SF",
    "wof:placetype":"postalcode"
},
  "geometry": {"coordinates":[-0.83816605209881,52.31915480710256],"type":"Point"}
}