{
  "type": "Feature",
  "properties": {
    "iso:country":"GB",
    "wof:name":"S21 1DT",
    "wof:placetype":"postalcode"
},
  "geometry": {"coordinates":[-1.31824468108816,53.32401822771375],"type":"Point"}
}