{
  "type": "Feature",
  "properties": {
    "iso:country": "GB",
    "wof:name": "S21 1DT",
    "wof:placetype": "postalcode"
  },
  "geometry": {"coordinates":[-1.318245,53.324018],"type":"Point"}
}
