{
  "type": "Feature",
  "properties": {
    "date:inception_lower": "2013-12-01",
    "date:inception_upper": "2013-12-01",
    "iso:country": "GB",
    "wof:name": "S21 1DT",
    "wof:placetype": "postalcode"
  },
  "geometry": {"coordinates":[-1.318245,53.324018],"type":"Point"}
}
