{
  "type": "Feature",
  "properties": {
    "iso:country": "GB",
    "wof:name": "NG9 2SE",
    "wof:placetype": "postalcode"
  },
  "geometry": {"coordinates":[-1.214051,52.937327],"type":"Point"}
}
