{
  "type": "Feature",
  "properties": {
    "date:inception_lower": "1980-01-01",
    "date:inception_upper": "1980-01-01",
    "iso:country": "GB",
    "wof:name": "NG9 2SE",
    "wof:placetype": "postalcode"
  },
  "geometry": {"coordinates":[-1.214051,52.937327],"type":"Point"}
}
