{
  "type": "Feature",
  "properties": {
    "date:inception_lower": "2023-06-01",
    "date:inception_upper": "2023-06-01",
    "iso:country": "GB",
    "wof:name": "OX14 1RS",
    "wof:placetype": "postalcode"
  },
  "geometry": {"coordinates":[-1.287727,51.685992],"type":"Point"}
}
