{
  "type": "Feature",
  "properties": {
    "iso:country":"GB",
    "wof:name":"WA9 3WF",
    "wof:placetype":"postalcode"
},
  "geometry": {"coordinates":[-2.71291223285167,53.43337044099215],"type":"Point"}
}