{
  "type": "Feature",
  "properties": {
    "date:inception_lower": "1994-05-01",
    "date:inception_upper": "1994-05-01",
    "iso:country": "GB",
    "wof:name": "M25 9GE",
    "wof:placetype": "postalcode"
  },
  "geometry": {"coordinates":[-2.288168,53.526922],"type":"Point"}
}
