{
  "type": "Feature",
  "properties": {
    "iso:country":"GB",
    "wof:name":"M25 9GE",
    "wof:placetype":"postalcode"
},
  "geometry": {"coordinates":[-2.28813959685726,53.52692345913717],"type":"Point"}
}