{
  "type": "Feature",
  "properties": {
    "iso:country": "GB",
    "wof:name": "M25 9GE",
    "wof:placetype": "postalcode"
  },
  "geometry": {"coordinates":[-2.28814,53.526923],"type":"Point"}
}
