{
  "type": "Feature",
  "properties": {
    "iso:country":"GB",
    "wof:name":"SE8 5BE",
    "wof:placetype":"postalcode"
},
  "geometry": {"coordinates":[-0.04334665115124,51.48902447186112],"type":"Point"}
}