{
  "type": "Feature",
  "properties": {
    "iso:country":"GB",
    "wof:name":"B25 8QY",
    "wof:placetype":"postalcode"
},
  "geometry": {"coordinates":[-1.81942165590987,52.47336105939822],"type":"Point"}
}