{
  "type": "Feature",
  "properties": {
    "iso:country":"GB",
    "wof:name":"SN16 9QW",
    "wof:placetype":"postalcode"
},
  "geometry": {"coordinates":[-1.96928576378298,51.62207374210777],"type":"Point"}
}