{
  "type": "Feature",
  "properties": {
    "iso:country": "GB",
    "wof:name": "CA25 5DF",
    "wof:placetype": "postalcode"
  },
  "geometry": {"coordinates":[-3.534359,54.529504],"type":"Point"}
}
