{
  "type": "Feature",
  "properties": {
    "iso:country": "GB",
    "wof:name": "SN10 5QA",
    "wof:placetype": "postalcode"
  },
  "geometry": {"coordinates":[-2.008575,51.322534],"type":"Point"}
}
