{
  "type": "Feature",
  "properties": {
    "date:inception_lower": "1980-01-01",
    "date:inception_upper": "1980-01-01",
    "iso:country": "GB",
    "wof:name": "CA4 9TJ",
    "wof:placetype": "postalcode"
  },
  "geometry": {"coordinates":[-2.793228,54.800547],"type":"Point"}
}
