{
  "type": "Feature",
  "properties": {
    "iso:country":"GB",
    "wof:name":"CA4 9TJ",
    "wof:placetype":"postalcode"
},
  "geometry": {"coordinates":[-2.79322778291419,54.80054710612647],"type":"Point"}
}