{
  "type": "Feature",
  "properties": {
    "iso:country": "GB",
    "wof:name": "BS36 2FN",
    "wof:placetype": "postalcode"
  },
  "geometry": {"coordinates":[-2.48219,51.525049],"type":"Point"}
}
