{
  "type": "Feature",
  "properties": {
    "iso:country": "GB",
    "wof:name": "GU28 0HH",
    "wof:placetype": "postalcode"
  },
  "geometry": {"coordinates":[-0.598359,50.986437],"type":"Point"}
}
