{
  "type": "Feature",
  "properties": {
    "iso:country":"GB",
    "wof:name":"PL2 3DU",
    "wof:placetype":"postalcode"
},
  "geometry": {"coordinates":[-4.15579776703434,50.38747071465227],"type":"Point"}
}