{
  "type": "Feature",
  "properties": {
    "iso:country":"GB",
    "wof:name":"BS6 5TD",
    "wof:placetype":"postalcode"
},
  "geometry": {"coordinates":[-2.5939086263028,51.46480543750224],"type":"Point"}
}