{
  "type": "Feature",
  "properties": {
    "date:inception_lower":"2003-06-01",
    "date:inception_upper":"2003-06-30",
    "iso:country":"GB",
    "wof:name":"SK12 1PL",
    "wof:placetype":"postalcode"
},
  "geometry": {"coordinates":[-2.115308,53.346987],"type":"Point"}
}