{
  "type": "Feature",
  "properties": {
    "iso:country":"GB",
    "wof:name":"GL54 2LU",
    "wof:placetype":"postalcode"
},
  "geometry": {"coordinates":[-1.75531483427235,51.88512742545225],"type":"Point"}
}