{
  "type": "Feature",
  "properties": {
    "date:inception_lower":"1991-09-01",
    "date:inception_upper":"1991-09-30",
    "iso:country":"GB",
    "wof:name":"GL54 2LU",
    "wof:placetype":"postalcode"
},
  "geometry": {"coordinates":[-1.755315,51.885127],"type":"Point"}
}