{
  "type": "Feature",
  "properties": {
    "iso:country":"GB",
    "wof:name":"DH9 0HG",
    "wof:placetype":"postalcode"
},
  "geometry": {"coordinates":[-1.68748999559597,54.87798277635923],"type":"Point"}
}