{
  "type": "Feature",
  "properties": {
    "iso:country":"GB",
    "wof:name":"NR30 5SX",
    "wof:placetype":"postalcode"
},
  "geometry": {"coordinates":[1.69266605264498,52.64148337415571],"type":"Point"}
}