{
  "type": "Feature",
  "properties": {
    "iso:country": "GB",
    "wof:name": "NR30 5SX",
    "wof:placetype": "postalcode"
  },
  "geometry": {"coordinates":[1.692666,52.641483],"type":"Point"}
}
