{
  "type": "Feature",
  "properties": {
    "iso:country":"GB",
    "wof:name":"EX18 7BN",
    "wof:placetype":"postalcode"
},
  "geometry": {"coordinates":[-3.87138439526777,50.91420246470584],"type":"Point"}
}