{
  "type": "Feature",
  "properties": {
    "iso:country": "GB",
    "wof:name": "EX18 7BN",
    "wof:placetype": "postalcode"
  },
  "geometry": {"coordinates":[-3.871384,50.914202],"type":"Point"}
}
