{
  "type": "Feature",
  "properties": {
    "iso:country":"GB",
    "wof:name":"PA3 4NY",
    "wof:placetype":"postalcode"
},
  "geometry": {"coordinates":[-4.40625282285634,55.8583122329529],"type":"Point"}
}