{
  "type": "Feature",
  "properties": {
    "iso:country":"GB",
    "wof:name":"HU7 4HR",
    "wof:placetype":"postalcode"
},
  "geometry": {"coordinates":[-0.32546327091982,53.79225665282985],"type":"Point"}
}