{
  "type": "Feature",
  "properties": {
    "iso:country": "GB",
    "wof:name": "HU7 4HR",
    "wof:placetype": "postalcode"
  },
  "geometry": {"coordinates":[-0.325463,53.792257],"type":"Point"}
}
