{
  "type": "Feature",
  "properties": {
    "iso:country":"GB",
    "wof:name":"ME16 0XD",
    "wof:placetype":"postalcode"
},
  "geometry": {"coordinates":[0.48620900296635,51.27017897599147],"type":"Point"}
}