{
  "type": "Feature",
  "properties": {
    "iso:country":"GB",
    "wof:name":"WC1X 9EY",
    "wof:placetype":"postalcode"
},
  "geometry": {"coordinates":[-0.11411759481752,51.5301648453492],"type":"Point"}
}