{
  "type": "Feature",
  "properties": {
    "iso:country":"GB",
    "wof:name":"DT6 6LL",
    "wof:placetype":"postalcode"
},
  "geometry": {"coordinates":[-2.90062707611653,50.7371881595048],"type":"Point"}
}