{
  "type": "Feature",
  "properties": {
    "iso:country": "GB",
    "wof:name": "NP44 3FG",
    "wof:placetype": "postalcode"
  },
  "geometry": {"coordinates":[-3.007669,51.635827],"type":"Point"}
}
