{
  "type": "Feature",
  "properties": {
    "iso:country": "GB",
    "wof:name": "PL19 0DW",
    "wof:placetype": "postalcode"
  },
  "geometry": {"coordinates":[-4.148463,50.553326],"type":"Point"}
}
