{
  "type": "Feature",
  "properties": {
    "date:inception_lower": "1980-01-01",
    "date:inception_upper": "1980-01-01",
    "iso:country": "GB",
    "wof:name": "PL19 0DW",
    "wof:placetype": "postalcode"
  },
  "geometry": {"coordinates":[-4.148463,50.553326],"type":"Point"}
}
