{
  "type": "Feature",
  "properties": {
    "iso:country":"GB",
    "wof:name":"S75 5FF",
    "wof:placetype":"postalcode"
},
  "geometry": {"coordinates":[-1.55162781156276,53.58271699418777],"type":"Point"}
}