{
  "type": "Feature",
  "properties": {
    "iso:country":"GB",
    "wof:name":"SA14 9AL",
    "wof:placetype":"postalcode"
},
  "geometry": {"coordinates":[-4.11402348408402,51.68290014386737],"type":"Point"}
}