{
  "type": "Feature",
  "properties": {
    "iso:country":"GB",
    "wof:name":"HA8 6QN",
    "wof:placetype":"postalcode"
},
  "geometry": {"coordinates":[-0.28385813930949,51.60894432448418],"type":"Point"}
}