{
  "type": "Feature",
  "properties": {
    "iso:country":"GB",
    "wof:name":"GU1 3TJ",
    "wof:placetype":"postalcode"
},
  "geometry": {"coordinates":[-0.56338942217426,51.23017814505277],"type":"Point"}
}