{
  "type": "Feature",
  "properties": {
    "iso:country":"GB",
    "wof:name":"KT12 3NH",
    "wof:placetype":"postalcode"
},
  "geometry": {"coordinates":[-0.40258912694769,51.3830081327444],"type":"Point"}
}