{
  "type": "Feature",
  "properties": {
    "iso:country":"GB",
    "wof:name":"M30 0QU",
    "wof:placetype":"postalcode"
},
  "geometry": {"coordinates":[-2.34846707815837,53.4851102850213],"type":"Point"}
}