{
  "type": "Feature",
  "properties": {
    "date:inception_lower": "1980-01-01",
    "date:inception_upper": "1980-01-01",
    "iso:country": "GB",
    "wof:name": "M30 0QU",
    "wof:placetype": "postalcode"
  },
  "geometry": {"coordinates":[-2.348467,53.48511],"type":"Point"}
}
