{
  "type": "Feature",
  "properties": {
    "iso:country": "GB",
    "wof:name": "DG1 3ND",
    "wof:placetype": "postalcode"
  },
  "geometry": {"coordinates":[-3.540107,55.176245],"type":"Point"}
}
