{
  "type": "Feature",
  "properties": {
    "iso:country":"GB",
    "wof:name":"DG1 3ND",
    "wof:placetype":"postalcode"
},
  "geometry": {"coordinates":[-3.54007800755672,55.17620535558709],"type":"Point"}
}