{
  "type": "Feature",
  "properties": {
    "iso:country":"GB",
    "wof:name":"LL65 2EQ",
    "wof:placetype":"postalcode"
},
  "geometry": {"coordinates":[-4.60412001713739,53.25842432083575],"type":"Point"}
}