{
  "type": "Feature",
  "properties": {
    "iso:country": "GB",
    "wof:name": "LL65 2EQ",
    "wof:placetype": "postalcode"
  },
  "geometry": {"coordinates":[-4.60412,53.258424],"type":"Point"}
}
