{
  "type": "Feature",
  "properties": {
    "iso:country":"GB",
    "wof:name":"ST6 4PP",
    "wof:placetype":"postalcode"
},
  "geometry": {"coordinates":[-2.21743052607113,53.05338437048353],"type":"Point"}
}