{
  "type": "Feature",
  "properties": {
    "iso:country":"GB",
    "wof:name":"BN16 4LZ",
    "wof:placetype":"postalcode"
},
  "geometry": {"coordinates":[-0.48409218009629,50.83432024064199],"type":"Point"}
}