{
  "type": "Feature",
  "properties": {
    "iso:country": "GB",
    "wof:name": "BN16 4LZ",
    "wof:placetype": "postalcode"
  },
  "geometry": {"coordinates":[-0.484092,50.83432],"type":"Point"}
}
