{
  "type": "Feature",
  "properties": {
    "iso:country":"GB",
    "wof:name":"PE28 9BY",
    "wof:placetype":"postalcode"
},
  "geometry": {"coordinates":[-0.10392569841559,52.31766250538325],"type":"Point"}
}