{
  "type": "Feature",
  "properties": {
    "date:inception_lower": "1988-03-01",
    "date:inception_upper": "1988-03-01",
    "iso:country": "GB",
    "wof:name": "OX14 1YH",
    "wof:placetype": "postalcode"
  },
  "geometry": {"coordinates":[-1.280085,51.688243],"type":"Point"}
}
