{
  "type": "Feature",
  "properties": {
    "iso:country": "GB",
    "wof:name": "OX14 1YH",
    "wof:placetype": "postalcode"
  },
  "geometry": {"coordinates":[-1.280085,51.688243],"type":"Point"}
}
