{
  "type": "Feature",
  "properties": {
    "iso:country":"GB",
    "wof:name":"OX14 1YH",
    "wof:placetype":"postalcode"
},
  "geometry": {"coordinates":[-1.28008506682043,51.68824278939617],"type":"Point"}
}