{
  "type": "Feature",
  "properties": {
    "date:inception_lower": "2017-12-01",
    "date:inception_upper": "2017-12-01",
    "iso:country": "GB",
    "wof:name": "TQ12 4FS",
    "wof:placetype": "postalcode"
  },
  "geometry": {"coordinates":[-3.594436,50.527325],"type":"Point"}
}
