{
  "type": "Feature",
  "properties": {
    "iso:country":"GB",
    "wof:name":"HA4 9SR",
    "wof:placetype":"postalcode"
},
  "geometry": {"coordinates":[-0.3940632331714,51.57542539976797],"type":"Point"}
}