{
  "type": "Feature",
  "properties": {
    "iso:country":"GB",
    "wof:name":"SW12 0JJ",
    "wof:placetype":"postalcode"
},
  "geometry": {"coordinates":[-0.13590714142069,51.44705331323204],"type":"Point"}
}