{
  "type": "Feature",
  "properties": {
    "date:inception_lower": "2015-09-01",
    "date:inception_upper": "2015-09-01",
    "iso:country": "GB",
    "wof:name": "OL2 5HH",
    "wof:placetype": "postalcode"
  },
  "geometry": {"coordinates":[-2.132708,53.560993],"type":"Point"}
}
