{
  "type": "Feature",
  "properties": {
    "date:inception_lower": "1990-07-01",
    "date:inception_upper": "1990-07-01",
    "iso:country": "GB",
    "wof:name": "DN36 5YJ",
    "wof:placetype": "postalcode"
  },
  "geometry": {"coordinates":[-0.056954,53.502826],"type":"Point"}
}
