{
  "type": "Feature",
  "properties": {
    "iso:country":"GB",
    "wof:name":"LS14 2BS",
    "wof:placetype":"postalcode"
},
  "geometry": {"coordinates":[-1.45459458092565,53.82889694623844],"type":"Point"}
}