{
  "type": "Feature",
  "properties": {
    "date:inception_lower":"1980-01-01",
    "date:inception_upper":"1980-01-31",
    "iso:country":"GB",
    "wof:name":"LS14 2BS",
    "wof:placetype":"postalcode"
},
  "geometry": {"coordinates":[-1.454595,53.828897],"type":"Point"}
}