{
  "type": "Feature",
  "properties": {
    "date:inception_lower": "1980-01-01",
    "date:inception_upper": "1980-01-01",
    "iso:country": "GB",
    "wof:name": "NE29 7QJ",
    "wof:placetype": "postalcode"
  },
  "geometry": {"coordinates":[-1.463443,55.006658],"type":"Point"}
}
