{
  "type": "Feature",
  "properties": {
    "iso:country": "GB",
    "wof:name": "RM2 5UQ",
    "wof:placetype": "postalcode"
  },
  "geometry": {"coordinates":[0.200203,51.575637],"type":"Point"}
}
