{
  "type": "Feature",
  "properties": {
    "iso:country":"GB",
    "wof:name":"RM2 5UQ",
    "wof:placetype":"postalcode"
},
  "geometry": {"coordinates":[0.20029841567822,51.57547088976934],"type":"Point"}
}