{
  "type": "Feature",
  "properties": {
    "date:inception_lower":"1980-01-01",
    "date:inception_upper":"1980-01-31",
    "iso:country":"GB",
    "wof:name":"KA13 6QU",
    "wof:placetype":"postalcode"
},
  "geometry": {"coordinates":[-4.726896,55.651962],"type":"Point"}
}