{
  "type": "Feature",
  "properties": {
    "iso:country": "GB",
    "wof:name": "KA13 6QU",
    "wof:placetype": "postalcode"
  },
  "geometry": {"coordinates":[-4.726896,55.651962],"type":"Point"}
}
