{
  "type": "Feature",
  "properties": {
    "iso:country":"GB",
    "wof:name":"KA13 6QU",
    "wof:placetype":"postalcode"
},
  "geometry": {"coordinates":[-4.72689619335123,55.65196202824809],"type":"Point"}
}