{
  "type": "Feature",
  "properties": {
    "date:inception_lower":"1994-05-01",
    "date:inception_upper":"1994-05-31",
    "iso:country":"GB",
    "wof:name":"M21 8ET",
    "wof:placetype":"postalcode"
},
  "geometry": {"coordinates":[-2.275455,53.431909],"type":"Point"}
}