{
  "type": "Feature",
  "properties": {
    "iso:country":"GB",
    "wof:name":"M21 8ET",
    "wof:placetype":"postalcode"
},
  "geometry": {"coordinates":[-2.27545515091837,53.43190933127428],"type":"Point"}
}