{
  "type": "Feature",
  "properties": {
    "iso:country":"GB",
    "wof:name":"ML12 6SE",
    "wof:placetype":"postalcode"
},
  "geometry": {"coordinates":[-3.69331813304414,55.49825464173401],"type":"Point"}
}