{
  "type": "Feature",
  "properties": {
    "iso:country": "GB",
    "wof:name": "NR32 5PE",
    "wof:placetype": "postalcode"
  },
  "geometry": {"coordinates":[1.709155,52.500416],"type":"Point"}
}
