{
  "type": "Feature",
  "properties": {
    "iso:country": "GB",
    "wof:name": "PO22 9BE",
    "wof:placetype": "postalcode"
  },
  "geometry": {"coordinates":[-0.688598,50.802552],"type":"Point"}
}
