{
  "type": "Feature",
  "properties": {
    "date:inception_lower":"2012-02-01",
    "date:inception_upper":"2012-02-29",
    "iso:country":"GB",
    "wof:name":"SE16 7BX",
    "wof:placetype":"postalcode"
},
  "geometry": {"coordinates":[-0.048976,51.499559],"type":"Point"}
}