{
  "type": "Feature",
  "properties": {
    "iso:country":"GB",
    "wof:name":"AL5 1JB",
    "wof:placetype":"postalcode"
},
  "geometry": {"coordinates":[-0.32373473637743,51.81092398417957],"type":"Point"}
}