{
  "type": "Feature",
  "properties": {
    "iso:country": "GB",
    "wof:name": "AL5 1JB",
    "wof:placetype": "postalcode"
  },
  "geometry": {"coordinates":[-0.324037,51.810738],"type":"Point"}
}
