{
  "type": "Feature",
  "properties": {
    "iso:country": "GB",
    "wof:name": "WA12 8TD",
    "wof:placetype": "postalcode"
  },
  "geometry": {"coordinates":[-2.625268,53.440808],"type":"Point"}
}
