{
  "type": "Feature",
  "properties": {
    "iso:country":"GB",
    "wof:name":"HR1 1XZ",
    "wof:placetype":"postalcode"
},
  "geometry": {"coordinates":[-2.68041674587684,52.05112880518121],"type":"Point"}
}