{
  "type": "Feature",
  "properties": {
    "iso:country":"GB",
    "wof:name":"LN5 9AU",
    "wof:placetype":"postalcode"
},
  "geometry": {"coordinates":[-0.55863311111921,53.18946469663052],"type":"Point"}
}