{
  "type": "Feature",
  "properties": {
    "date:inception_lower":"1980-01-01",
    "date:inception_upper":"1980-01-31",
    "iso:country":"GB",
    "wof:name":"LN5 9AU",
    "wof:placetype":"postalcode"
},
  "geometry": {"coordinates":[-0.558633,53.189465],"type":"Point"}
}