{
  "type": "Feature",
  "properties": {
    "iso:country": "GB",
    "wof:name": "CF5 6AA",
    "wof:placetype": "postalcode"
  },
  "geometry": {"coordinates":[-3.258425,51.458728],"type":"Point"}
}
