{
  "type": "Feature",
  "properties": {
    "date:inception_lower": "1980-01-01",
    "date:inception_upper": "1980-01-01",
    "iso:country": "GB",
    "wof:name": "CF5 6AA",
    "wof:placetype": "postalcode"
  },
  "geometry": {"coordinates":[-3.258425,51.458728],"type":"Point"}
}
