{
  "type": "Feature",
  "properties": {
    "date:inception_lower": "1992-08-01",
    "date:inception_upper": "1992-08-01",
    "iso:country": "GB",
    "wof:name": "MK46 5LQ",
    "wof:placetype": "postalcode"
  },
  "geometry": {"coordinates":[-0.6804,52.152202],"type":"Point"}
}
