{
  "type": "Feature",
  "properties": {
    "iso:country": "GB",
    "wof:name": "MK46 5LQ",
    "wof:placetype": "postalcode"
  },
  "geometry": {"coordinates":[-0.680549,52.152246],"type":"Point"}
}
