{
  "type": "Feature",
  "properties": {
    "iso:country":"GB",
    "wof:name":"MK46 5LQ",
    "wof:placetype":"postalcode"
},
  "geometry": {"coordinates":[-0.68054914833882,52.15224643755556],"type":"Point"}
}