{
  "type": "Feature",
  "properties": {
    "iso:country": "GB",
    "wof:name": "NW8 8TY",
    "wof:placetype": "postalcode"
  },
  "geometry": {"coordinates":[-0.1673,51.527744],"type":"Point"}
}
