{
  "type": "Feature",
  "properties": {
    "iso:country":"GB",
    "wof:name":"NW8 8TY",
    "wof:placetype":"postalcode"
},
  "geometry": {"coordinates":[-0.16729963046941,51.5277435221002],"type":"Point"}
}