{
  "type": "Feature",
  "properties": {
    "iso:country": "GB",
    "wof:name": "S60 5EH",
    "wof:placetype": "postalcode"
  },
  "geometry": {"coordinates":[-1.375719,53.40196],"type":"Point"}
}
