{
  "type": "Feature",
  "properties": {
    "iso:country":"GB",
    "wof:name":"S60 5EH",
    "wof:placetype":"postalcode"
},
  "geometry": {"coordinates":[-1.37571886345088,53.4019596440423],"type":"Point"}
}