{
  "type": "Feature",
  "properties": {
    "iso:country":"GB",
    "wof:name":"YO24 1HJ",
    "wof:placetype":"postalcode"
},
  "geometry": {"coordinates":[-1.10842460740248,53.9414324674738],"type":"Point"}
}