{
  "type": "Feature",
  "properties": {
    "date:inception_lower": "1990-02-01",
    "date:inception_upper": "1990-02-01",
    "iso:country": "GB",
    "wof:name": "NR31 9JB",
    "wof:placetype": "postalcode"
  },
  "geometry": {"coordinates":[1.693965,52.586322],"type":"Point"}
}
