{
  "type": "Feature",
  "properties": {
    "iso:country":"GB",
    "wof:name":"NR31 9JB",
    "wof:placetype":"postalcode"
},
  "geometry": {"coordinates":[1.69404393849304,52.58645598757627],"type":"Point"}
}