{
  "type": "Feature",
  "properties": {
    "iso:country": "GB",
    "wof:name": "N2 9LG",
    "wof:placetype": "postalcode"
  },
  "geometry": {"coordinates":[-0.158387,51.588186],"type":"Point"}
}
