{
  "type": "Feature",
  "properties": {
    "iso:country":"GB",
    "wof:name":"N2 9LG",
    "wof:placetype":"postalcode"
},
  "geometry": {"coordinates":[-0.15838664143115,51.58818589376099],"type":"Point"}
}