{
  "type": "Feature",
  "properties": {
    "iso:country":"GB",
    "wof:name":"GU52 0YB",
    "wof:placetype":"postalcode"
},
  "geometry": {"coordinates":[-0.84827153340184,51.25571858692985],"type":"Point"}
}