{
  "type": "Feature",
  "properties": {
    "date:inception_lower": "1995-07-01",
    "date:inception_upper": "1995-07-01",
    "iso:country": "GB",
    "wof:name": "CF82 7JD",
    "wof:placetype": "postalcode"
  },
  "geometry": {"coordinates":[-3.236038,51.660167],"type":"Point"}
}
