{
  "type": "Feature",
  "properties": {
    "iso:country": "GB",
    "wof:name": "AB51 3TW",
    "wof:placetype": "postalcode"
  },
  "geometry": {"coordinates":[-2.376581,57.276753],"type":"Point"}
}
