{
  "type": "Feature",
  "properties": {
    "iso:country": "GB",
    "wof:name": "TW15 1AJ",
    "wof:placetype": "postalcode"
  },
  "geometry": {"coordinates":[-0.442988,51.431607],"type":"Point"}
}
