{
  "type": "Feature",
  "properties": {
    "iso:country":"GB",
    "wof:name":"TW15 1AJ",
    "wof:placetype":"postalcode"
},
  "geometry": {"coordinates":[-0.4429877555804,51.43160695240053],"type":"Point"}
}