{
  "type": "Feature",
  "properties": {
    "iso:country":"GB",
    "wof:name":"ST5 5DS",
    "wof:placetype":"postalcode"
},
  "geometry": {"coordinates":[-2.30481247887906,52.95436521302094],"type":"Point"}
}