{
  "type": "Feature",
  "properties": {
    "iso:country": "GB",
    "wof:name": "ST5 5DS",
    "wof:placetype": "postalcode"
  },
  "geometry": {"coordinates":[-2.304812,52.954365],"type":"Point"}
}
