{
  "type": "Feature",
  "properties": {
    "iso:country":"GB",
    "wof:name":"CA28 6EU",
    "wof:placetype":"postalcode"
},
  "geometry": {"coordinates":[-3.58128853341235,54.5618042460486],"type":"Point"}
}