{
  "type": "Feature",
  "properties": {
    "date:inception_lower": "1980-01-01",
    "date:inception_upper": "1980-01-01",
    "iso:country": "GB",
    "wof:name": "CA28 6EU",
    "wof:placetype": "postalcode"
  },
  "geometry": {"coordinates":[-3.581288,54.561804],"type":"Point"}
}
