{
  "type": "Feature",
  "properties": {
    "iso:country":"GB",
    "wof:name":"L20 3JF",
    "wof:placetype":"postalcode"
},
  "geometry": {"coordinates":[-2.98643299841221,53.45072330885669],"type":"Point"}
}