{
  "type": "Feature",
  "properties": {
    "iso:country": "GB",
    "wof:name": "L20 3JF",
    "wof:placetype": "postalcode"
  },
  "geometry": {"coordinates":[-2.986432,53.450739],"type":"Point"}
}
