{
  "type": "Feature",
  "properties": {
    "date:inception_lower": "2011-03-01",
    "date:inception_upper": "2011-03-01",
    "iso:country": "GB",
    "wof:name": "L20 3JF",
    "wof:placetype": "postalcode"
  },
  "geometry": {"coordinates":[-2.986523,53.450766],"type":"Point"}
}
