{
  "type": "Feature",
  "properties": {
    "iso:country":"GB",
    "wof:name":"DT2 7QU",
    "wof:placetype":"postalcode"
},
  "geometry": {"coordinates":[-2.41221057510817,50.78270771570136],"type":"Point"}
}