{
  "type": "Feature",
  "properties": {
    "iso:country":"GB",
    "wof:name":"S81 0UF",
    "wof:placetype":"postalcode"
},
  "geometry": {"coordinates":[-1.05951802063725,53.3110325626536],"type":"Point"}
}