{
  "type": "Feature",
  "properties": {
    "date:inception_lower": "1980-01-01",
    "date:inception_upper": "1980-01-01",
    "iso:country": "GB",
    "wof:name": "S81 0UF",
    "wof:placetype": "postalcode"
  },
  "geometry": {"coordinates":[-1.059518,53.311033],"type":"Point"}
}
