{
  "type": "Feature",
  "properties": {
    "iso:country":"GB",
    "wof:name":"DN22 7HS",
    "wof:placetype":"postalcode"
},
  "geometry": {"coordinates":[-0.94593993990412,53.31180920380051],"type":"Point"}
}