{
  "type": "Feature",
  "properties": {
    "date:inception_lower": "2011-12-01",
    "date:inception_upper": "2011-12-01",
    "iso:country": "GB",
    "wof:name": "DN22 7HS",
    "wof:placetype": "postalcode"
  },
  "geometry": {"coordinates":[-0.94594,53.311809],"type":"Point"}
}
