{
  "type": "Feature",
  "properties": {
    "iso:country": "GB",
    "wof:name": "DN22 7HS",
    "wof:placetype": "postalcode"
  },
  "geometry": {"coordinates":[-0.94594,53.311809],"type":"Point"}
}
