{
  "type": "Feature",
  "properties": {
    "date:inception_lower":"1980-01-01",
    "date:inception_upper":"1980-01-31",
    "iso:country":"GB",
    "wof:name":"CH4 9AN",
    "wof:placetype":"postalcode"
},
  "geometry": {"coordinates":[-3.016938,53.134221],"type":"Point"}
}