{
  "type": "Feature",
  "properties": {
    "iso:country": "GB",
    "wof:name": "CH4 9AN",
    "wof:placetype": "postalcode"
  },
  "geometry": {"coordinates":[-3.016938,53.134221],"type":"Point"}
}
