{
  "type": "Feature",
  "properties": {
    "iso:country":"GB",
    "wof:name":"CH4 9AN",
    "wof:placetype":"postalcode"
},
  "geometry": {"coordinates":[-3.01693840376563,53.13422111432396],"type":"Point"}
}