{
  "type": "Feature",
  "properties": {
    "iso:country":"GB",
    "wof:name":"HP4 2QW",
    "wof:placetype":"postalcode"
},
  "geometry": {"coordinates":[-0.52628620244505,51.7700179869726],"type":"Point"}
}