{
  "type": "Feature",
  "properties": {
    "date:inception_lower": "1980-01-01",
    "date:inception_upper": "1980-01-01",
    "iso:country": "GB",
    "wof:name": "LS17 5JQ",
    "wof:placetype": "postalcode"
  },
  "geometry": {"coordinates":[-1.561309,53.849476],"type":"Point"}
}
