{
  "type": "Feature",
  "properties": {
    "iso:country":"GB",
    "wof:name":"LS17 5JQ",
    "wof:placetype":"postalcode"
},
  "geometry": {"coordinates":[-1.56130884199835,53.84947642618166],"type":"Point"}
}