{
  "type": "Feature",
  "properties": {
    "date:inception_lower":"2015-03-01",
    "date:inception_upper":"2015-03-31",
    "iso:country":"GB",
    "wof:name":"IP14 3QA",
    "wof:placetype":"postalcode"
},
  "geometry": {"coordinates":[0.973158,52.217578],"type":"Point"}
}