{
  "type": "Feature",
  "properties": {
    "iso:country": "GB",
    "wof:name": "IP14 3QA",
    "wof:placetype": "postalcode"
  },
  "geometry": {"coordinates":[0.973158,52.217578],"type":"Point"}
}
