{
  "type": "Feature",
  "properties": {
    "iso:country":"GB",
    "wof:name":"IP14 3QA",
    "wof:placetype":"postalcode"
},
  "geometry": {"coordinates":[0.97315558037258,52.21756952126639],"type":"Point"}
}