{
  "type": "Feature",
  "properties": {
    "iso:country":"GB",
    "wof:name":"N14 4DG",
    "wof:placetype":"postalcode"
},
  "geometry": {"coordinates":[-0.13443605353735,51.63965765385161],"type":"Point"}
}