{
  "type": "Feature",
  "properties": {
    "iso:country":"GB",
    "wof:name":"HA1 4RY",
    "wof:placetype":"postalcode"
},
  "geometry": {"coordinates":[-0.34800674116304,51.59072028305451],"type":"Point"}
}