{
  "type": "Feature",
  "properties": {
    "iso:country": "GB",
    "wof:name": "HA1 4RY",
    "wof:placetype": "postalcode"
  },
  "geometry": {"coordinates":[-0.348007,51.59072],"type":"Point"}
}
