{
  "type": "Feature",
  "properties": {
    "iso:country": "GB",
    "wof:name": "M6 8FB",
    "wof:placetype": "postalcode"
  },
  "geometry": {"coordinates":[-2.322944,53.491824],"type":"Point"}
}
