{
  "type": "Feature",
  "properties": {
    "date:inception_lower": "1980-01-01",
    "date:inception_upper": "1980-01-01",
    "iso:country": "GB",
    "wof:name": "DL5 4PL",
    "wof:placetype": "postalcode"
  },
  "geometry": {"coordinates":[-1.594767,54.635315],"type":"Point"}
}
