{
  "type": "Feature",
  "properties": {
    "iso:country":"GB",
    "wof:name":"GU12 6PB",
    "wof:placetype":"postalcode"
},
  "geometry": {"coordinates":[-0.73421413386383,51.24326464735296],"type":"Point"}
}