{
  "type": "Feature",
  "properties": {
    "date:inception_lower":"1980-01-01",
    "date:inception_upper":"1980-01-31",
    "iso:country":"GB",
    "wof:name":"BA12 7EZ",
    "wof:placetype":"postalcode"
},
  "geometry": {"coordinates":[-2.206916,51.134969],"type":"Point"}
}