{
  "type": "Feature",
  "properties": {
    "iso:country": "GB",
    "wof:name": "BA12 7EZ",
    "wof:placetype": "postalcode"
  },
  "geometry": {"coordinates":[-2.206916,51.134969],"type":"Point"}
}
