{
  "type": "Feature",
  "properties": {
    "date:inception_lower": "2020-11-01",
    "date:inception_upper": "2020-11-01",
    "iso:country": "GB",
    "wof:name": "S65 4FS",
    "wof:placetype": "postalcode"
  },
  "geometry": {"coordinates":[-1.268268,53.434439],"type":"Point"}
}
