{
  "type": "Feature",
  "properties": {
    "iso:country":"GB",
    "wof:name":"SM5 4AD",
    "wof:placetype":"postalcode"
},
  "geometry": {"coordinates":[-0.15684762426324,51.35368108162792],"type":"Point"}
}