{
  "type": "Feature",
  "properties": {
    "iso:country":"GB",
    "wof:name":"SO22 4PH",
    "wof:placetype":"postalcode"
},
  "geometry": {"coordinates":[-1.33276158263565,51.06103455313396],"type":"Point"}
}