{
  "type": "Feature",
  "properties": {
    "date:inception_lower": "1980-01-01",
    "date:inception_upper": "1980-01-01",
    "iso:country": "GB",
    "wof:name": "SO22 4PH",
    "wof:placetype": "postalcode"
  },
  "geometry": {"coordinates":[-1.332762,51.061035],"type":"Point"}
}
