{
  "type": "Feature",
  "properties": {
    "iso:country":"GB",
    "wof:name":"EX31 2HF",
    "wof:placetype":"postalcode"
},
  "geometry": {"coordinates":[-4.08403003113561,51.07237357282246],"type":"Point"}
}