{
  "type": "Feature",
  "properties": {
    "date:inception_lower": "1980-01-01",
    "date:inception_upper": "1980-01-01",
    "iso:country": "GB",
    "wof:name": "LL18 3RU",
    "wof:placetype": "postalcode"
  },
  "geometry": {"coordinates":[-3.472382,53.324121],"type":"Point"}
}
