{
  "type": "Feature",
  "properties": {
    "iso:country": "GB",
    "wof:name": "WA6 6QL",
    "wof:placetype": "postalcode"
  },
  "geometry": {"coordinates":[-2.72487,53.29485],"type":"Point"}
}
