{
  "type": "Feature",
  "properties": {
    "iso:country":"GB",
    "wof:name":"WA6 6QL",
    "wof:placetype":"postalcode"
},
  "geometry": {"coordinates":[-2.72506783674676,53.29496832801669],"type":"Point"}
}