{
  "type": "Feature",
  "properties": {
    "date:inception_lower": "2004-03-01",
    "date:inception_upper": "2004-03-01",
    "iso:country": "GB",
    "wof:name": "L7 7DL",
    "wof:placetype": "postalcode"
  },
  "geometry": {"coordinates":[-2.969113,53.401659],"type":"Point"}
}
