{
  "type": "Feature",
  "properties": {
    "iso:country": "GB",
    "wof:name": "L7 7DL",
    "wof:placetype": "postalcode"
  },
  "geometry": {"coordinates":[-2.969141,53.40157],"type":"Point"}
}
