{
  "type": "Feature",
  "properties": {
    "iso:country":"GB",
    "wof:name":"ME16 8GF",
    "wof:placetype":"postalcode"
},
  "geometry": {"coordinates":[0.51178850108157,51.2667997137914],"type":"Point"}
}