{
  "type": "Feature",
  "properties": {
    "date:inception_lower": "2007-08-01",
    "date:inception_upper": "2007-08-01",
    "iso:country": "GB",
    "wof:name": "ME16 8GF",
    "wof:placetype": "postalcode"
  },
  "geometry": {"coordinates":[0.511789,51.2668],"type":"Point"}
}
