{
  "type": "Feature",
  "properties": {
    "iso:country": "GB",
    "wof:name": "ME16 8GF",
    "wof:placetype": "postalcode"
  },
  "geometry": {"coordinates":[0.511789,51.2668],"type":"Point"}
}
