{
  "type": "Feature",
  "properties": {
    "date:inception_lower":"1980-01-01",
    "date:inception_upper":"1980-01-31",
    "iso:country":"GB",
    "wof:name":"BH1 4PD",
    "wof:placetype":"postalcode"
},
  "geometry": {"coordinates":[-1.846796,50.730775],"type":"Point"}
}