{
  "type": "Feature",
  "properties": {
    "iso:country":"GB",
    "wof:name":"BH1 4PD",
    "wof:placetype":"postalcode"
},
  "geometry": {"coordinates":[-1.84690928079796,50.73075700727382],"type":"Point"}
}