{
  "type": "Feature",
  "properties": {
    "iso:country":"GB",
    "wof:name":"PR3 3SZ",
    "wof:placetype":"postalcode"
},
  "geometry": {"coordinates":[-2.59489638898162,53.82920752211038],"type":"Point"}
}