{
  "type": "Feature",
  "properties": {
    "iso:country": "GB",
    "wof:name": "PR3 3SZ",
    "wof:placetype": "postalcode"
  },
  "geometry": {"coordinates":[-2.594896,53.829208],"type":"Point"}
}
