{
  "type": "Feature",
  "properties": {
    "iso:country":"GB",
    "wof:name":"DH8 5TP",
    "wof:placetype":"postalcode"
},
  "geometry": {"coordinates":[-1.84175438162982,54.86102751704183],"type":"Point"}
}