{
  "type": "Feature",
  "properties": {
    "date:inception_lower": "1980-01-01",
    "date:inception_upper": "1980-01-01",
    "iso:country": "GB",
    "wof:name": "DH8 5TP",
    "wof:placetype": "postalcode"
  },
  "geometry": {"coordinates":[-1.841754,54.861028],"type":"Point"}
}
