{
  "type": "Feature",
  "properties": {
    "date:inception_lower": "1980-01-01",
    "date:inception_upper": "1980-01-01",
    "iso:country": "GB",
    "wof:name": "CT19 5RJ",
    "wof:placetype": "postalcode"
  },
  "geometry": {"coordinates":[1.176074,51.087384],"type":"Point"}
}
