{
  "type": "Feature",
  "properties": {
    "iso:country":"GB",
    "wof:name":"DT1 1RZ",
    "wof:placetype":"postalcode"
},
  "geometry": {"coordinates":[-2.44132382009133,50.71104636325484],"type":"Point"}
}