{
  "type": "Feature",
  "properties": {
    "iso:country":"GB",
    "wof:name":"DH7 8AQ",
    "wof:placetype":"postalcode"
},
  "geometry": {"coordinates":[-1.63688561463622,54.74947013231509],"type":"Point"}
}