{
  "type": "Feature",
  "properties": {
    "iso:country":"GB",
    "wof:name":"SG3 6QF",
    "wof:placetype":"postalcode"
},
  "geometry": {"coordinates":[-0.21674002405287,51.86661090147886],"type":"Point"}
}