{
  "type": "Feature",
  "properties": {
    "iso:country": "GB",
    "wof:name": "SG3 6QF",
    "wof:placetype": "postalcode"
  },
  "geometry": {"coordinates":[-0.216844,51.8667],"type":"Point"}
}
