{
  "type": "Feature",
  "properties": {
    "iso:country":"GB",
    "wof:name":"SL7 1QT",
    "wof:placetype":"postalcode"
},
  "geometry": {"coordinates":[-0.7641050804441,51.57055364147303],"type":"Point"}
}