{
  "type": "Feature",
  "properties": {
    "iso:country":"GB",
    "wof:name":"TQ6 9RR",
    "wof:placetype":"postalcode"
},
  "geometry": {"coordinates":[-3.57793210820438,50.35472944806558],"type":"Point"}
}