{
  "type": "Feature",
  "properties": {
    "date:inception_lower": "2012-06-01",
    "date:inception_upper": "2012-06-01",
    "iso:country": "GB",
    "wof:name": "TQ6 9RR",
    "wof:placetype": "postalcode"
  },
  "geometry": {"coordinates":[-3.57727,50.354596],"type":"Point"}
}
