{
  "type": "Feature",
  "properties": {
    "iso:country": "GB",
    "wof:name": "TQ6 9RR",
    "wof:placetype": "postalcode"
  },
  "geometry": {"coordinates":[-3.57727,50.354596],"type":"Point"}
}
