{
  "type": "Feature",
  "properties": {
    "iso:country":"GB",
    "wof:name":"SG5 3AN",
    "wof:placetype":"postalcode"
},
  "geometry": {"coordinates":[-0.33820662184272,51.92929947008544],"type":"Point"}
}