{
  "type": "Feature",
  "properties": {
    "iso:country":"GB",
    "wof:name":"B15 2UD",
    "wof:placetype":"postalcode"
},
  "geometry": {"coordinates":[-1.92629702277744,52.45017362657681],"type":"Point"}
}