{
  "type": "Feature",
  "properties": {
    "iso:country":"GB",
    "wof:name":"SR7 8AH",
    "wof:placetype":"postalcode"
},
  "geometry": {"coordinates":[-1.35884412397594,54.83584961553507],"type":"Point"}
}