{
  "type": "Feature",
  "properties": {
    "iso:country": "GB",
    "wof:name": "SR7 8AH",
    "wof:placetype": "postalcode"
  },
  "geometry": {"coordinates":[-1.358844,54.83585],"type":"Point"}
}
