{
  "type": "Feature",
  "properties": {
    "iso:country":"GB",
    "wof:name":"SP10 3BU",
    "wof:placetype":"postalcode"
},
  "geometry": {"coordinates":[-1.50769378137512,51.20756481001907],"type":"Point"}
}