{
  "type": "Feature",
  "properties": {
    "iso:country": "GB",
    "wof:name": "IG8 7AX",
    "wof:placetype": "postalcode"
  },
  "geometry": {"coordinates":[0.037379,51.601731],"type":"Point"}
}
