{
  "type": "Feature",
  "properties": {
    "iso:country": "GB",
    "wof:name": "SY14 8QS",
    "wof:placetype": "postalcode"
  },
  "geometry": {"coordinates":[-2.762384,53.022607],"type":"Point"}
}
