{
  "type": "Feature",
  "properties": {
    "date:inception_lower": "1981-09-01",
    "date:inception_upper": "1981-09-01",
    "iso:country": "GB",
    "wof:name": "SY14 8QS",
    "wof:placetype": "postalcode"
  },
  "geometry": {"coordinates":[-2.762384,53.022607],"type":"Point"}
}
