{
  "type": "Feature",
  "properties": {
    "iso:country":"GB",
    "wof:name":"SY14 8QS",
    "wof:placetype":"postalcode"
},
  "geometry": {"coordinates":[-2.76238410675889,53.02260714152554],"type":"Point"}
}