{
  "type": "Feature",
  "properties": {
    "iso:country":"GB",
    "wof:name":"LS21 1LP",
    "wof:placetype":"postalcode"
},
  "geometry": {"coordinates":[-1.63117673591744,53.90238040732876],"type":"Point"}
}