{
  "type": "Feature",
  "properties": {
    "date:inception_lower":"1980-01-01",
    "date:inception_upper":"1980-01-31",
    "iso:country":"GB",
    "wof:name":"LS21 1LP",
    "wof:placetype":"postalcode"
},
  "geometry": {"coordinates":[-1.631177,53.90238],"type":"Point"}
}