{
  "type": "Feature",
  "properties": {
    "iso:country": "GB",
    "wof:name": "LS21 1LP",
    "wof:placetype": "postalcode"
  },
  "geometry": {"coordinates":[-1.631177,53.90238],"type":"Point"}
}
