{
  "type": "Feature",
  "properties": {
    "iso:country":"GB",
    "wof:name":"W1U 4AU",
    "wof:placetype":"postalcode"
},
  "geometry": {"coordinates":[-0.15206132384716,51.51848499774545],"type":"Point"}
}