{
  "type": "Feature",
  "properties": {
    "iso:country":"GB",
    "wof:name":"W3 7DN",
    "wof:placetype":"postalcode"
},
  "geometry": {"coordinates":[-0.25028965983478,51.51661025288028],"type":"Point"}
}