{
  "type": "Feature",
  "properties": {
    "iso:country": "GB",
    "wof:name": "W3 7DN",
    "wof:placetype": "postalcode"
  },
  "geometry": {"coordinates":[-0.25029,51.51661],"type":"Point"}
}
