{
  "type": "Feature",
  "properties": {
    "iso:country":"GB",
    "wof:name":"ST5 0AR",
    "wof:placetype":"postalcode"
},
  "geometry": {"coordinates":[-2.21846114485657,53.03889203140815],"type":"Point"}
}