{
  "type": "Feature",
  "properties": {
    "iso:country":"GB",
    "wof:name":"NE16 5PS",
    "wof:placetype":"postalcode"
},
  "geometry": {"coordinates":[-1.6803346020676,54.92353395082709],"type":"Point"}
}