{
  "type": "Feature",
  "properties": {
    "date:inception_lower": "1995-12-01",
    "date:inception_upper": "1995-12-01",
    "iso:country": "GB",
    "wof:name": "PO12 4LS",
    "wof:placetype": "postalcode"
  },
  "geometry": {"coordinates":[-1.136063,50.813855],"type":"Point"}
}
