{
  "type": "Feature",
  "properties": {
    "iso:country":"GB",
    "wof:name":"PO12 4LS",
    "wof:placetype":"postalcode"
},
  "geometry": {"coordinates":[-1.13606340709535,50.81385454304086],"type":"Point"}
}