{
  "type": "Feature",
  "properties": {
    "iso:country":"GB",
    "wof:name":"KT8 2TN",
    "wof:placetype":"postalcode"
},
  "geometry": {"coordinates":[-0.38125971749402,51.40387458325088],"type":"Point"}
}