{
  "type": "Feature",
  "properties": {
    "iso:country": "GB",
    "wof:name": "WF4 4FJ",
    "wof:placetype": "postalcode"
  },
  "geometry": {"coordinates":[-1.64635,53.630022],"type":"Point"}
}
