{
  "type": "Feature",
  "properties": {
    "iso:country":"GB",
    "wof:name":"DD10 0QB",
    "wof:placetype":"postalcode"
},
  "geometry": {"coordinates":[-2.27555455637934,56.8461640804118],"type":"Point"}
}