{
  "type": "Feature",
  "properties": {
    "iso:country":"GB",
    "wof:name":"BN1 6FA",
    "wof:placetype":"postalcode"
},
  "geometry": {"coordinates":[-0.13578016339969,50.84266628032528],"type":"Point"}
}