{
  "type": "Feature",
  "properties": {
    "iso:country":"GB",
    "wof:name":"S45 9BW",
    "wof:placetype":"postalcode"
},
  "geometry": {"coordinates":[-1.4021962396094,53.16500457355522],"type":"Point"}
}