{
  "type": "Feature",
  "properties": {
    "iso:country":"GB",
    "wof:name":"WR8 0DJ",
    "wof:placetype":"postalcode"
},
  "geometry": {"coordinates":[-2.27229782944164,52.08172913920205],"type":"Point"}
}