{
  "type": "Feature",
  "properties": {
    "iso:country": "GB",
    "wof:name": "GU10 1LA",
    "wof:placetype": "postalcode"
  },
  "geometry": {"coordinates":[-0.737639,51.224921],"type":"Point"}
}
