{
  "type": "Feature",
  "properties": {
    "iso:country": "GB",
    "wof:name": "NN2 7TQ",
    "wof:placetype": "postalcode"
  },
  "geometry": {"coordinates":[-0.895448,52.264717],"type":"Point"}
}
