{
  "type": "Feature",
  "properties": {
    "iso:country":"GB",
    "wof:name":"BL9 7JJ",
    "wof:placetype":"postalcode"
},
  "geometry": {"coordinates":[-2.25945899953302,53.58780433986757],"type":"Point"}
}