{
  "type": "Feature",
  "properties": {
    "iso:country":"GB",
    "wof:name":"LN13 9FB",
    "wof:placetype":"postalcode"
},
  "geometry": {"coordinates":[0.18190161174118,53.25491970233297],"type":"Point"}
}