{
  "type": "Feature",
  "properties": {
    "date:inception_lower": "1980-01-01",
    "date:inception_upper": "1980-01-01",
    "iso:country": "GB",
    "wof:name": "ST4 8SE",
    "wof:placetype": "postalcode"
  },
  "geometry": {"coordinates":[-2.221134,52.949229],"type":"Point"}
}
