{
  "type": "Feature",
  "properties": {
    "iso:country":"GB",
    "wof:name":"ST4 8SE",
    "wof:placetype":"postalcode"
},
  "geometry": {"coordinates":[-2.22113401097411,52.94922888771417],"type":"Point"}
}