{
  "type": "Feature",
  "properties": {
    "iso:country": "GB",
    "wof:name": "ST4 8SE",
    "wof:placetype": "postalcode"
  },
  "geometry": {"coordinates":[-2.221134,52.949229],"type":"Point"}
}
