{
  "type": "Feature",
  "properties": {
    "date:inception_lower":"2007-01-01",
    "date:inception_upper":"2007-01-31",
    "iso:country":"GB",
    "wof:name":"EH48 3AZ",
    "wof:placetype":"postalcode"
},
  "geometry": {"coordinates":[-3.764967,55.882785],"type":"Point"}
}