{
  "type": "Feature",
  "properties": {
    "iso:country":"GB",
    "wof:name":"EH48 3AZ",
    "wof:placetype":"postalcode"
},
  "geometry": {"coordinates":[-3.76462127384778,55.88272248989794],"type":"Point"}
}