{
  "type": "Feature",
  "properties": {
    "iso:country":"GB",
    "wof:name":"ME3 7DB",
    "wof:placetype":"postalcode"
},
  "geometry": {"coordinates":[0.46142999988182,51.41585824847893],"type":"Point"}
}