{
  "type": "Feature",
  "properties": {
    "iso:country": "GB",
    "wof:name": "ME3 7DB",
    "wof:placetype": "postalcode"
  },
  "geometry": {"coordinates":[0.46146,51.415876],"type":"Point"}
}
