{
  "type": "Feature",
  "properties": {
    "iso:country":"GB",
    "wof:name":"CM11 2YW",
    "wof:placetype":"postalcode"
},
  "geometry": {"coordinates":[0.47849708217196,51.60080622957521],"type":"Point"}
}