{
  "type": "Feature",
  "properties": {
    "iso:country":"GB",
    "wof:name":"HU3 2EJ",
    "wof:placetype":"postalcode"
},
  "geometry": {"coordinates":[-0.348643519451,53.74205025503839],"type":"Point"}
}