{
  "type": "Feature",
  "properties": {
    "date:inception_lower": "1984-10-01",
    "date:inception_upper": "1984-10-01",
    "iso:country": "GB",
    "wof:name": "NN8 2QY",
    "wof:placetype": "postalcode"
  },
  "geometry": {"coordinates":[-0.689358,52.289614],"type":"Point"}
}
