{
  "type": "Feature",
  "properties": {
    "iso:country": "GB",
    "wof:name": "NN8 2QY",
    "wof:placetype": "postalcode"
  },
  "geometry": {"coordinates":[-0.690055,52.289343],"type":"Point"}
}
