{
  "type": "Feature",
  "properties": {
    "iso:country":"GB",
    "wof:name":"NN8 2QY",
    "wof:placetype":"postalcode"
},
  "geometry": {"coordinates":[-0.69010174146722,52.28931186444417],"type":"Point"}
}