{
  "type": "Feature",
  "properties": {
    "date:inception_lower": "1980-01-01",
    "date:inception_upper": "1980-01-01",
    "iso:country": "GB",
    "wof:name": "GU35 8NG",
    "wof:placetype": "postalcode"
  },
  "geometry": {"coordinates":[-0.821273,51.114733],"type":"Point"}
}
