{
  "type": "Feature",
  "properties": {
    "iso:country":"GB",
    "wof:name":"GU35 8NG",
    "wof:placetype":"postalcode"
},
  "geometry": {"coordinates":[-0.82110571662327,51.11474481095309],"type":"Point"}
}