{
  "type": "Feature",
  "properties": {
    "date:inception_lower": "1990-07-01",
    "date:inception_upper": "1990-07-01",
    "iso:country": "GB",
    "wof:name": "CH2 2HF",
    "wof:placetype": "postalcode"
  },
  "geometry": {"coordinates":[-2.892189,53.19775],"type":"Point"}
}
