{
  "type": "Feature",
  "properties": {
    "iso:country":"GB",
    "wof:name":"CH2 2HF",
    "wof:placetype":"postalcode"
},
  "geometry": {"coordinates":[-2.89218943069182,53.19775045460082],"type":"Point"}
}