{
  "type": "Feature",
  "properties": {
    "iso:country":"GB",
    "wof:name":"CO9 3PP",
    "wof:placetype":"postalcode"
},
  "geometry": {"coordinates":[0.59270178013127,51.9780210965598],"type":"Point"}
}