{
  "type": "Feature",
  "properties": {
    "iso:country":"GB",
    "wof:name":"HU15 1DW",
    "wof:placetype":"postalcode"
},
  "geometry": {"coordinates":[-0.57555580214393,53.73011225651754],"type":"Point"}
}