{
  "type": "Feature",
  "properties": {
    "iso:country": "GB",
    "wof:name": "CO5 0DP",
    "wof:placetype": "postalcode"
  },
  "geometry": {"coordinates":[0.750862,51.815915],"type":"Point"}
}
