{
  "type": "Feature",
  "properties": {
    "iso:country":"GB",
    "wof:name":"CO5 0DP",
    "wof:placetype":"postalcode"
},
  "geometry": {"coordinates":[0.75086151435895,51.81591463817034],"type":"Point"}
}