{
  "type": "Feature",
  "properties": {
    "iso:country": "GB",
    "wof:name": "N1 9FB",
    "wof:placetype": "postalcode"
  },
  "geometry": {"coordinates":[-0.121312,51.533302],"type":"Point"}
}
