{
  "type": "Feature",
  "properties": {
    "date:inception_lower": "2021-04-01",
    "date:inception_upper": "2021-04-01",
    "iso:country": "GB",
    "wof:name": "NE61 6GH",
    "wof:placetype": "postalcode"
  },
  "geometry": {"coordinates":[-1.66349,55.128181],"type":"Point"}
}
