{
  "type": "Feature",
  "properties": {
    "iso:country":"GB",
    "wof:name":"DD4 8RE",
    "wof:placetype":"postalcode"
},
  "geometry": {"coordinates":[-2.90714626822834,56.47835220339275],"type":"Point"}
}