{
  "type": "Feature",
  "properties": {
    "iso:country": "GB",
    "wof:name": "EH6 7QR",
    "wof:placetype": "postalcode"
  },
  "geometry": {"coordinates":[-3.156726,55.971115],"type":"Point"}
}
