{
  "type": "Feature",
  "properties": {
    "iso:country": "GB",
    "wof:name": "FY8 4NG",
    "wof:placetype": "postalcode"
  },
  "geometry": {"coordinates":[-2.9627,53.771532],"type":"Point"}
}
