{
  "type": "Feature",
  "properties": {
    "date:inception_lower": "1980-01-01",
    "date:inception_upper": "1980-01-01",
    "iso:country": "GB",
    "wof:name": "FY8 4NG",
    "wof:placetype": "postalcode"
  },
  "geometry": {"coordinates":[-2.9627,53.771532],"type":"Point"}
}
