{
  "type": "Feature",
  "properties": {
    "iso:country":"GB",
    "wof:name":"PO14 2EW",
    "wof:placetype":"postalcode"
},
  "geometry": {"coordinates":[-1.21272269750487,50.82931569603144],"type":"Point"}
}