{
  "type": "Feature",
  "properties": {
    "iso:country":"GB",
    "wof:name":"NG2 7TR",
    "wof:placetype":"postalcode"
},
  "geometry": {"coordinates":[-1.15613994378213,52.92054240445758],"type":"Point"}
}