{
  "type": "Feature",
  "properties": {
    "iso:country": "GB",
    "wof:name": "NG2 7TR",
    "wof:placetype": "postalcode"
  },
  "geometry": {"coordinates":[-1.15614,52.920542],"type":"Point"}
}
