{
  "type": "Feature",
  "properties": {
    "iso:country":"GB",
    "wof:name":"CM22 6PA",
    "wof:placetype":"postalcode"
},
  "geometry": {"coordinates":[0.2844978363839,51.88331182857616],"type":"Point"}
}