{
  "type": "Feature",
  "properties": {
    "iso:country":"GB",
    "wof:name":"LE67 2GQ",
    "wof:placetype":"postalcode"
},
  "geometry": {"coordinates":[-1.37701908250423,52.71230413429161],"type":"Point"}
}