{
  "type": "Feature",
  "properties": {
    "iso:country":"GB",
    "wof:name":"N16 7HA",
    "wof:placetype":"postalcode"
},
  "geometry": {"coordinates":[-0.0726010496859,51.56381455503386],"type":"Point"}
}