{
  "type": "Feature",
  "properties": {
    "iso:country":"GB",
    "wof:name":"SA43 3LA",
    "wof:placetype":"postalcode"
},
  "geometry": {"coordinates":[-4.68317559553009,52.0873151707641],"type":"Point"}
}