{
  "type": "Feature",
  "properties": {
    "date:inception_lower": "1980-01-01",
    "date:inception_upper": "1980-01-01",
    "iso:country": "GB",
    "wof:name": "SA43 3LA",
    "wof:placetype": "postalcode"
  },
  "geometry": {"coordinates":[-4.683156,52.087349],"type":"Point"}
}
