{
  "type": "Feature",
  "properties": {
    "iso:country":"GB",
    "wof:name":"OX7 3SX",
    "wof:placetype":"postalcode"
},
  "geometry": {"coordinates":[-1.47728746413675,51.86883797289332],"type":"Point"}
}