{
  "type": "Feature",
  "properties": {
    "iso:country":"GB",
    "wof:name":"KW17 2AU",
    "wof:placetype":"postalcode"
},
  "geometry": {"coordinates":[-2.57512967906469,59.03806248398077],"type":"Point"}
}