{
  "type": "Feature",
  "properties": {
    "date:inception_lower": "1986-01-01",
    "date:inception_upper": "1986-01-01",
    "iso:country": "GB",
    "wof:name": "KW17 2AU",
    "wof:placetype": "postalcode"
  },
  "geometry": {"coordinates":[-2.57513,59.038062],"type":"Point"}
}
