{
  "type": "Feature",
  "properties": {
    "date:inception_lower":"1980-01-01",
    "date:inception_upper":"1980-01-31",
    "iso:country":"GB",
    "wof:name":"WR13 6DL",
    "wof:placetype":"postalcode"
},
  "geometry": {"coordinates":[-2.342711,52.080287],"type":"Point"}
}