{
  "type": "Feature",
  "properties": {
    "iso:country":"GB",
    "wof:name":"WR13 6DL",
    "wof:placetype":"postalcode"
},
  "geometry": {"coordinates":[-2.3427113331197,52.08028661931707],"type":"Point"}
}