{
  "type": "Feature",
  "properties": {
    "iso:country": "GB",
    "wof:name": "S43 4LW",
    "wof:placetype": "postalcode"
  },
  "geometry": {"coordinates":[-1.248191,53.280505],"type":"Point"}
}
