{
  "type": "Feature",
  "properties": {
    "date:inception_lower": "2008-10-01",
    "date:inception_upper": "2008-10-01",
    "iso:country": "GB",
    "wof:name": "S43 4LW",
    "wof:placetype": "postalcode"
  },
  "geometry": {"coordinates":[-1.248191,53.280505],"type":"Point"}
}
