{
  "type": "Feature",
  "properties": {
    "iso:country":"GB",
    "wof:name":"S43 4LW",
    "wof:placetype":"postalcode"
},
  "geometry": {"coordinates":[-1.24819107114894,53.28050461748799],"type":"Point"}
}