{
  "type": "Feature",
  "properties": {
    "iso:country":"GB",
    "wof:name":"IP33 2DP",
    "wof:placetype":"postalcode"
},
  "geometry": {"coordinates":[0.69884099061621,52.23706104711445],"type":"Point"}
}