{
  "type": "Feature",
  "properties": {
    "iso:country":"GB",
    "wof:name":"M27 8TA",
    "wof:placetype":"postalcode"
},
  "geometry": {"coordinates":[-2.3249188936614,53.51545875017727],"type":"Point"}
}