{
  "type": "Feature",
  "properties": {
    "iso:country":"GB",
    "wof:name":"B20 2BU",
    "wof:placetype":"postalcode"
},
  "geometry": {"coordinates":[-1.92176991257409,52.50573769103858],"type":"Point"}
}