{
  "type": "Feature",
  "properties": {
    "date:inception_lower": "1980-01-01",
    "date:inception_upper": "1980-01-01",
    "iso:country": "GB",
    "wof:name": "BA21 4BE",
    "wof:placetype": "postalcode"
  },
  "geometry": {"coordinates":[-2.635027,50.947053],"type":"Point"}
}
