{
  "type": "Feature",
  "properties": {
    "date:inception_lower": "2003-04-01",
    "date:inception_upper": "2003-04-01",
    "iso:country": "GB",
    "wof:name": "B3 2PT",
    "wof:placetype": "postalcode"
  },
  "geometry": {"coordinates":[-1.897355,52.481401],"type":"Point"}
}
