{
  "type": "Feature",
  "properties": {
    "date:inception_lower": "2015-09-01",
    "date:inception_upper": "2015-09-01",
    "iso:country": "GB",
    "wof:name": "S36 2BN",
    "wof:placetype": "postalcode"
  },
  "geometry": {"coordinates":[-1.586722,53.486118],"type":"Point"}
}
