{
  "type": "Feature",
  "properties": {
    "iso:country":"GB",
    "wof:name":"S36 2BN",
    "wof:placetype":"postalcode"
},
  "geometry": {"coordinates":[-1.58670552314849,53.48610983391646],"type":"Point"}
}