{
  "type": "Feature",
  "properties": {
    "iso:country":"GB",
    "wof:name":"GL50 1DE",
    "wof:placetype":"postalcode"
},
  "geometry": {"coordinates":[-2.07442590684282,51.90101063719955],"type":"Point"}
}