{
  "type": "Feature",
  "properties": {
    "date:inception_lower": "1980-01-01",
    "date:inception_upper": "1980-01-01",
    "iso:country": "GB",
    "wof:name": "GL50 1DE",
    "wof:placetype": "postalcode"
  },
  "geometry": {"coordinates":[-2.07436,51.900964],"type":"Point"}
}
