{
  "type": "Feature",
  "properties": {
    "iso:country":"GB",
    "wof:name":"ML3 7FG",
    "wof:placetype":"postalcode"
},
  "geometry": {"coordinates":[-4.03109775410122,55.74119210788692],"type":"Point"}
}