{
  "type": "Feature",
  "properties": {
    "iso:country":"GB",
    "wof:name":"IP23 7HZ",
    "wof:placetype":"postalcode"
},
  "geometry": {"coordinates":[1.15699775597267,52.3123155048226],"type":"Point"}
}