{
  "type": "Feature",
  "properties": {
    "iso:country": "GB",
    "wof:name": "IP23 7HZ",
    "wof:placetype": "postalcode"
  },
  "geometry": {"coordinates":[1.157114,52.312125],"type":"Point"}
}
