{
  "type": "Feature",
  "properties": {
    "date:inception_lower": "1981-06-01",
    "date:inception_upper": "1981-06-01",
    "iso:country": "GB",
    "wof:name": "ME5 9BZ",
    "wof:placetype": "postalcode"
  },
  "geometry": {"coordinates":[0.513199,51.34094],"type":"Point"}
}
