{
  "type": "Feature",
  "properties": {
    "iso:country":"GB",
    "wof:name":"BA11 4BE",
    "wof:placetype":"postalcode"
},
  "geometry": {"coordinates":[-2.32487435446243,51.22091608972829],"type":"Point"}
}