{
  "type": "Feature",
  "properties": {
    "iso:country":"GB",
    "wof:name":"TD5 7EG",
    "wof:placetype":"postalcode"
},
  "geometry": {"coordinates":[-2.43922642811885,55.6032087154788],"type":"Point"}
}