{
  "type": "Feature",
  "properties": {
    "iso:country":"GB",
    "wof:name":"G73 4NQ",
    "wof:placetype":"postalcode"
},
  "geometry": {"coordinates":[-4.20915677677381,55.81240853585951],"type":"Point"}
}