{
  "type": "Feature",
  "properties": {
    "iso:country":"GB",
    "wof:name":"BN8 6EJ",
    "wof:placetype":"postalcode"
},
  "geometry": {"coordinates":[0.15477247285877,50.92859723882958],"type":"Point"}
}