{
  "type": "Feature",
  "properties": {
    "iso:country":"GB",
    "wof:name":"HR5 3UA",
    "wof:placetype":"postalcode"
},
  "geometry": {"coordinates":[-3.03441625986839,52.20538885656241],"type":"Point"}
}