{
  "type": "Feature",
  "properties": {
    "iso:country": "GB",
    "wof:name": "HR5 3UA",
    "wof:placetype": "postalcode"
  },
  "geometry": {"coordinates":[-3.034416,52.205389],"type":"Point"}
}
