{
  "type": "Feature",
  "properties": {
    "iso:country":"GB",
    "wof:name":"CB6 2HY",
    "wof:placetype":"postalcode"
},
  "geometry": {"coordinates":[0.20416878006735,52.39056116835214],"type":"Point"}
}