{
  "type": "Feature",
  "properties": {
    "date:inception_lower": "1980-01-01",
    "date:inception_upper": "1980-01-01",
    "iso:country": "GB",
    "wof:name": "CB6 2HY",
    "wof:placetype": "postalcode"
  },
  "geometry": {"coordinates":[0.204169,52.390561],"type":"Point"}
}
