{
  "type": "Feature",
  "properties": {
    "iso:country":"GB",
    "wof:name":"LE19 4LX",
    "wof:placetype":"postalcode"
},
  "geometry": {"coordinates":[-1.2043241158176,52.58573607437096],"type":"Point"}
}