{
  "type": "Feature",
  "properties": {
    "iso:country": "GB",
    "wof:name": "LE19 4LX",
    "wof:placetype": "postalcode"
  },
  "geometry": {"coordinates":[-1.204324,52.585736],"type":"Point"}
}
