{
  "type": "Feature",
  "properties": {
    "date:inception_lower": "1986-04-01",
    "date:inception_upper": "1986-04-01",
    "iso:country": "GB",
    "wof:name": "SL7 1UA",
    "wof:placetype": "postalcode"
  },
  "geometry": {"coordinates":[-0.767238,51.567269],"type":"Point"}
}
