{
  "type": "Feature",
  "properties": {
    "iso:country":"GB",
    "wof:name":"SL7 1UA",
    "wof:placetype":"postalcode"
},
  "geometry": {"coordinates":[-0.76723848425424,51.56726860796797],"type":"Point"}
}