{
  "type": "Feature",
  "properties": {
    "iso:country": "GB",
    "wof:name": "IP19 0NS",
    "wof:placetype": "postalcode"
  },
  "geometry": {"coordinates":[1.446044,52.378566],"type":"Point"}
}
