{
  "type": "Feature",
  "properties": {
    "iso:country":"GB",
    "wof:name":"IP19 0NS",
    "wof:placetype":"postalcode"
},
  "geometry": {"coordinates":[1.44604432972337,52.37856646396901],"type":"Point"}
}