{
  "type": "Feature",
  "properties": {
    "date:inception_lower":"1980-01-01",
    "date:inception_upper":"1980-01-31",
    "iso:country":"GB",
    "wof:name":"IP19 0NS",
    "wof:placetype":"postalcode"
},
  "geometry": {"coordinates":[1.446044,52.378566],"type":"Point"}
}