{
  "type": "Feature",
  "properties": {
    "iso:country":"GB",
    "wof:name":"LN6 7AN",
    "wof:placetype":"postalcode"
},
  "geometry": {"coordinates":[-0.55247103785993,53.22310121322453],"type":"Point"}
}