{
  "type": "Feature",
  "properties": {
    "iso:country":"GB",
    "wof:name":"MK41 0DX",
    "wof:placetype":"postalcode"
},
  "geometry": {"coordinates":[-0.4219620260714,52.144799524122],"type":"Point"}
}