{
  "type": "Feature",
  "properties": {
    "date:inception_lower": "1980-01-01",
    "date:inception_upper": "1980-01-01",
    "iso:country": "GB",
    "wof:name": "MK41 0DX",
    "wof:placetype": "postalcode"
  },
  "geometry": {"coordinates":[-0.421962,52.1448],"type":"Point"}
}
