{
  "type": "Feature",
  "properties": {
    "iso:country":"GB",
    "wof:name":"CW11 4PD",
    "wof:placetype":"postalcode"
},
  "geometry": {"coordinates":[-2.36843975623575,53.13905563108442],"type":"Point"}
}