{
  "type": "Feature",
  "properties": {
    "iso:country":"GB",
    "wof:name":"TW7 7ES",
    "wof:placetype":"postalcode"
},
  "geometry": {"coordinates":[-0.33210428293726,51.46351541175688],"type":"Point"}
}