{
  "type": "Feature",
  "properties": {
    "iso:country":"GB",
    "wof:name":"LD3 0SU",
    "wof:placetype":"postalcode"
},
  "geometry": {"coordinates":[-3.18925914251079,52.02222152897112],"type":"Point"}
}