{
  "type": "Feature",
  "properties": {
    "iso:country":"GB",
    "wof:name":"YO10 4DT",
    "wof:placetype":"postalcode"
},
  "geometry": {"coordinates":[-1.07787484598397,53.9464868929408],"type":"Point"}
}