{
  "type": "Feature",
  "properties": {
    "iso:country": "GB",
    "wof:name": "CW9 7PY",
    "wof:placetype": "postalcode"
  },
  "geometry": {"coordinates":[-2.463767,53.270921],"type":"Point"}
}
