{
  "type": "Feature",
  "properties": {
    "date:inception_lower":"1980-01-01",
    "date:inception_upper":"1980-01-31",
    "iso:country":"GB",
    "wof:name":"SL4 6QS",
    "wof:placetype":"postalcode"
},
  "geometry": {"coordinates":[-0.662966,51.508704],"type":"Point"}
}