{
  "type": "Feature",
  "properties": {
    "iso:country": "GB",
    "wof:name": "SL4 6QS",
    "wof:placetype": "postalcode"
  },
  "geometry": {"coordinates":[-0.662966,51.508704],"type":"Point"}
}
