{
  "type": "Feature",
  "properties": {
    "iso:country":"GB",
    "wof:name":"SL4 6QS",
    "wof:placetype":"postalcode"
},
  "geometry": {"coordinates":[-0.66296575947665,51.50870444303364],"type":"Point"}
}