{
  "type": "Feature",
  "properties": {
    "iso:country":"GB",
    "wof:name":"LL65 2RY",
    "wof:placetype":"postalcode"
},
  "geometry": {"coordinates":[-4.63060055310733,53.30188264096921],"type":"Point"}
}