{
  "type": "Feature",
  "properties": {
    "iso:country":"GB",
    "wof:name":"N1 7AS",
    "wof:placetype":"postalcode"
},
  "geometry": {"coordinates":[-0.09124752466338,51.53680911013367],"type":"Point"}
}