{
  "type": "Feature",
  "properties": {
    "iso:country": "GB",
    "wof:name": "N1 7AS",
    "wof:placetype": "postalcode"
  },
  "geometry": {"coordinates":[-0.091247,51.536809],"type":"Point"}
}
