{
  "type": "Feature",
  "properties": {
    "iso:country":"GB",
    "wof:name":"EX6 8ES",
    "wof:placetype":"postalcode"
},
  "geometry": {"coordinates":[-3.50977597883722,50.65566096978892],"type":"Point"}
}