{
  "type": "Feature",
  "properties": {
    "iso:country": "GB",
    "wof:name": "EX6 8ES",
    "wof:placetype": "postalcode"
  },
  "geometry": {"coordinates":[-3.510301,50.656128],"type":"Point"}
}
