{
  "type": "Feature",
  "properties": {
    "date:inception_lower":"1980-01-01",
    "date:inception_upper":"1980-01-31",
    "iso:country":"GB",
    "wof:name":"CH7 4EU",
    "wof:placetype":"postalcode"
},
  "geometry": {"coordinates":[-3.147966,53.138073],"type":"Point"}
}