{
  "type": "Feature",
  "properties": {
    "iso:country":"GB",
    "wof:name":"CH7 4EU",
    "wof:placetype":"postalcode"
},
  "geometry": {"coordinates":[-3.1479664834525,53.1380727301488],"type":"Point"}
}