{
  "type": "Feature",
  "properties": {
    "iso:country": "GB",
    "wof:name": "CH7 4EU",
    "wof:placetype": "postalcode"
  },
  "geometry": {"coordinates":[-3.147966,53.138073],"type":"Point"}
}
