{
  "type": "Feature",
  "properties": {
    "iso:country":"GB",
    "wof:name":"YO60 7RD",
    "wof:placetype":"postalcode"
},
  "geometry": {"coordinates":[-0.95678535578893,54.03340943266008],"type":"Point"}
}