{
  "type": "Feature",
  "properties": {
    "iso:country":"GB",
    "wof:name":"B32 4JA",
    "wof:placetype":"postalcode"
},
  "geometry": {"coordinates":[-2.00213270550639,52.43075998078346],"type":"Point"}
}