{
  "type": "Feature",
  "properties": {
    "iso:country": "GB",
    "wof:name": "MK10 9TL",
    "wof:placetype": "postalcode"
  },
  "geometry": {"coordinates":[-0.718609,52.039003],"type":"Point"}
}
