{
  "type": "Feature",
  "properties": {
    "iso:country":"GB",
    "wof:name":"MK10 9TL",
    "wof:placetype":"postalcode"
},
  "geometry": {"coordinates":[-0.71874628884774,52.03898408765963],"type":"Point"}
}