{
  "type": "Feature",
  "properties": {
    "date:inception_lower":"2016-04-01",
    "date:inception_upper":"2016-04-30",
    "iso:country":"GB",
    "wof:name":"MK10 9TL",
    "wof:placetype":"postalcode"
},
  "geometry": {"coordinates":[-0.718609,52.039003],"type":"Point"}
}