{
  "type": "Feature",
  "properties": {
    "iso:country":"GB",
    "wof:name":"CF38 1DW",
    "wof:placetype":"postalcode"
},
  "geometry": {"coordinates":[-3.32175896896669,51.56874892040107],"type":"Point"}
}