{
  "type": "Feature",
  "properties": {
    "date:inception_lower": "2013-03-01",
    "date:inception_upper": "2013-03-01",
    "iso:country": "GB",
    "wof:name": "L1 6RA",
    "wof:placetype": "postalcode"
  },
  "geometry": {"coordinates":[-2.982645,53.408597],"type":"Point"}
}
