{
  "type": "Feature",
  "properties": {
    "iso:country":"GB",
    "wof:name":"G64 2EE",
    "wof:placetype":"postalcode"
},
  "geometry": {"coordinates":[-4.23689510911426,55.90939341389756],"type":"Point"}
}