{
  "type": "Feature",
  "properties": {
    "date:inception_lower": "1981-06-01",
    "date:inception_upper": "1981-06-01",
    "iso:country": "GB",
    "wof:name": "SA31 2HL",
    "wof:placetype": "postalcode"
  },
  "geometry": {"coordinates":[-4.293185,51.868259],"type":"Point"}
}
