{
  "type": "Feature",
  "properties": {
    "iso:country":"GB",
    "wof:name":"SA31 2HL",
    "wof:placetype":"postalcode"
},
  "geometry": {"coordinates":[-4.29318511186832,51.86825871967331],"type":"Point"}
}