{
  "type": "Feature",
  "properties": {
    "date:inception_lower": "1995-01-01",
    "date:inception_upper": "1995-01-01",
    "iso:country": "GB",
    "wof:name": "WV8 1HH",
    "wof:placetype": "postalcode"
  },
  "geometry": {"coordinates":[-2.184353,52.625616],"type":"Point"}
}
