{
  "type": "Feature",
  "properties": {
    "iso:country":"GB",
    "wof:name":"WV8 1HH",
    "wof:placetype":"postalcode"
},
  "geometry": {"coordinates":[-2.18435260023661,52.62561574528036],"type":"Point"}
}