{
  "type": "Feature",
  "properties": {
    "iso:country":"GB",
    "wof:name":"CT3 1NL",
    "wof:placetype":"postalcode"
},
  "geometry": {"coordinates":[1.19972551413302,51.26851779984624],"type":"Point"}
}