{
  "type": "Feature",
  "properties": {
    "iso:country":"GB",
    "wof:name":"NE12 6QW",
    "wof:placetype":"postalcode"
},
  "geometry": {"coordinates":[-1.57854569380489,55.03072662996494],"type":"Point"}
}