{
  "type": "Feature",
  "properties": {
    "date:inception_lower": "1980-01-01",
    "date:inception_upper": "1980-01-01",
    "iso:country": "GB",
    "wof:name": "SY8 4NL",
    "wof:placetype": "postalcode"
  },
  "geometry": {"coordinates":[-2.705259,52.308554],"type":"Point"}
}
