{
  "type": "Feature",
  "properties": {
    "iso:country":"GB",
    "wof:name":"SY8 4NL",
    "wof:placetype":"postalcode"
},
  "geometry": {"coordinates":[-2.70525921470212,52.3085540026258],"type":"Point"}
}