{
  "type": "Feature",
  "properties": {
    "iso:country":"GB",
    "wof:name":"LU3 2EB",
    "wof:placetype":"postalcode"
},
  "geometry": {"coordinates":[-0.42961312784151,51.91489097653321],"type":"Point"}
}