{
  "type": "Feature",
  "properties": {
    "iso:country":"GB",
    "wof:name":"M20 6WL",
    "wof:placetype":"postalcode"
},
  "geometry": {"coordinates":[-2.2254055102485,53.41677879236597],"type":"Point"}
}