{
  "type": "Feature",
  "properties": {
    "iso:country":"GB",
    "wof:name":"DH8 5LA",
    "wof:placetype":"postalcode"
},
  "geometry": {"coordinates":[-1.83296754619871,54.85361997994487],"type":"Point"}
}