{
  "type": "Feature",
  "properties": {
    "date:inception_lower": "2004-03-01",
    "date:inception_upper": "2004-03-01",
    "iso:country": "GB",
    "wof:name": "BH10 5BB",
    "wof:placetype": "postalcode"
  },
  "geometry": {"coordinates":[-1.887257,50.756468],"type":"Point"}
}
