{
  "type": "Feature",
  "properties": {
    "iso:country": "GB",
    "wof:name": "SW17 9JN",
    "wof:placetype": "postalcode"
  },
  "geometry": {"coordinates":[-0.158294,51.420717],"type":"Point"}
}
