{
  "type": "Feature",
  "properties": {
    "iso:country":"GB",
    "wof:name":"E18 2AZ",
    "wof:placetype":"postalcode"
},
  "geometry": {"coordinates":[0.02362568150193,51.58893841290548],"type":"Point"}
}