{
  "type": "Feature",
  "properties": {
    "date:inception_lower": "2009-04-01",
    "date:inception_upper": "2009-04-01",
    "iso:country": "GB",
    "wof:name": "TF1 5PF",
    "wof:placetype": "postalcode"
  },
  "geometry": {"coordinates":[-2.479665,52.706666],"type":"Point"}
}
