{
  "type": "Feature",
  "properties": {
    "iso:country":"GB",
    "wof:name":"GL52 6HY",
    "wof:placetype":"postalcode"
},
  "geometry": {"coordinates":[-2.05419420942541,51.88875820929317],"type":"Point"}
}