{
  "type": "Feature",
  "properties": {
    "date:inception_lower": "1980-01-01",
    "date:inception_upper": "1980-01-01",
    "iso:country": "GB",
    "wof:name": "B19 2XY",
    "wof:placetype": "postalcode"
  },
  "geometry": {"coordinates":[-1.909231,52.499058],"type":"Point"}
}
