{
  "type": "Feature",
  "properties": {
    "iso:country": "GB",
    "wof:name": "RH12 2HB",
    "wof:placetype": "postalcode"
  },
  "geometry": {"coordinates":[-0.333932,51.072753],"type":"Point"}
}
