{
  "type": "Feature",
  "properties": {
    "iso:country":"GB",
    "wof:name":"MK41 6ED",
    "wof:placetype":"postalcode"
},
  "geometry": {"coordinates":[-0.49526094867946,52.16410853486977],"type":"Point"}
}