{
  "type": "Feature",
  "properties": {
    "iso:country": "GB",
    "wof:name": "LE4 1HB",
    "wof:placetype": "postalcode"
  },
  "geometry": {"coordinates":[-1.172608,52.667094],"type":"Point"}
}
