{
  "type": "Feature",
  "properties": {
    "date:inception_lower": "1993-08-01",
    "date:inception_upper": "1993-08-01",
    "iso:country": "GB",
    "wof:name": "LE4 1HB",
    "wof:placetype": "postalcode"
  },
  "geometry": {"coordinates":[-1.17279,52.667285],"type":"Point"}
}
