{
  "type": "Feature",
  "properties": {
    "iso:country":"GB",
    "wof:name":"LS15 0AW",
    "wof:placetype":"postalcode"
},
  "geometry": {"coordinates":[-1.48085066561737,53.78935810409338],"type":"Point"}
}