{
  "type": "Feature",
  "properties": {
    "iso:country":"GB",
    "wof:name":"LL33 0LB",
    "wof:placetype":"postalcode"
},
  "geometry": {"coordinates":[-4.02332477205229,53.23765953519494],"type":"Point"}
}