{
  "type": "Feature",
  "properties": {
    "date:inception_lower":"1980-01-01",
    "date:inception_upper":"1980-01-31",
    "iso:country":"GB",
    "wof:name":"LL33 0LB",
    "wof:placetype":"postalcode"
},
  "geometry": {"coordinates":[-4.023325,53.23766],"type":"Point"}
}