{
  "type": "Feature",
  "properties": {
    "iso:country": "GB",
    "wof:name": "LL33 0LB",
    "wof:placetype": "postalcode"
  },
  "geometry": {"coordinates":[-4.023325,53.23766],"type":"Point"}
}
