{
  "type": "Feature",
  "properties": {
    "iso:country":"GB",
    "wof:name":"TQ2 5DF",
    "wof:placetype":"postalcode"
},
  "geometry": {"coordinates":[-3.54462600544364,50.47275213589928],"type":"Point"}
}