{
  "type": "Feature",
  "properties": {
    "date:inception_lower":"2008-11-01",
    "date:inception_upper":"2008-11-30",
    "iso:country":"GB",
    "wof:name":"TQ2 5DF",
    "wof:placetype":"postalcode"
},
  "geometry": {"coordinates":[-3.544626,50.472752],"type":"Point"}
}