{
  "type": "Feature",
  "properties": {
    "date:inception_lower":"1985-10-01",
    "date:inception_upper":"1985-10-31",
    "iso:country":"GB",
    "wof:name":"TW4 5BH",
    "wof:placetype":"postalcode"
},
  "geometry": {"coordinates":[-0.381002,51.46367],"type":"Point"}
}