{
  "type": "Feature",
  "properties": {
    "iso:country": "GB",
    "wof:name": "TW4 5BH",
    "wof:placetype": "postalcode"
  },
  "geometry": {"coordinates":[-0.381002,51.46367],"type":"Point"}
}
