{
  "type": "Feature",
  "properties": {
    "iso:country":"GB",
    "wof:name":"UB9 5NW",
    "wof:placetype":"postalcode"
},
  "geometry": {"coordinates":[-0.50018093274275,51.58491330485401],"type":"Point"}
}