{
  "type": "Feature",
  "properties": {
    "date:inception_lower":"2007-08-01",
    "date:inception_upper":"2007-08-31",
    "iso:country":"GB",
    "wof:name":"UB9 5NW",
    "wof:placetype":"postalcode"
},
  "geometry": {"coordinates":[-0.500181,51.584913],"type":"Point"}
}