{
  "type": "Feature",
  "properties": {
    "date:inception_lower":"1980-01-01",
    "date:inception_upper":"1980-01-31",
    "iso:country":"GB",
    "wof:name":"LU1 5NG",
    "wof:placetype":"postalcode"
},
  "geometry": {"coordinates":[-0.426999,51.871516],"type":"Point"}
}