{
  "type": "Feature",
  "properties": {
    "iso:country":"GB",
    "wof:name":"LU1 5NG",
    "wof:placetype":"postalcode"
},
  "geometry": {"coordinates":[-0.42699909758596,51.87151625880032],"type":"Point"}
}