{
  "type": "Feature",
  "properties": {
    "date:inception_lower": "1980-01-01",
    "date:inception_upper": "1980-01-01",
    "iso:country": "GB",
    "wof:name": "HR4 9JN",
    "wof:placetype": "postalcode"
  },
  "geometry": {"coordinates":[-2.721437,52.059165],"type":"Point"}
}
