{
  "type": "Feature",
  "properties": {
    "date:inception_lower":"1980-01-01",
    "date:inception_upper":"1980-01-31",
    "iso:country":"GB",
    "wof:name":"KY16 8NY",
    "wof:placetype":"postalcode"
},
  "geometry": {"coordinates":[-2.848875,56.323207],"type":"Point"}
}