{
  "type": "Feature",
  "properties": {
    "iso:country":"GB",
    "wof:name":"KY16 8NY",
    "wof:placetype":"postalcode"
},
  "geometry": {"coordinates":[-2.84887501956618,56.32320716079477],"type":"Point"}
}