{
  "type": "Feature",
  "properties": {
    "iso:country": "GB",
    "wof:name": "ME16 9BZ",
    "wof:placetype": "postalcode"
  },
  "geometry": {"coordinates":[0.481267,51.269699],"type":"Point"}
}
