{
  "type": "Feature",
  "properties": {
    "iso:country":"GB",
    "wof:name":"GU10 2JD",
    "wof:placetype":"postalcode"
},
  "geometry": {"coordinates":[-0.77972074187768,51.13684646398517],"type":"Point"}
}