{
  "type": "Feature",
  "properties": {
    "date:inception_lower": "1980-01-01",
    "date:inception_upper": "1980-01-01",
    "iso:country": "GB",
    "wof:name": "GU10 2JD",
    "wof:placetype": "postalcode"
  },
  "geometry": {"coordinates":[-0.779572,51.136895],"type":"Point"}
}
