{
  "type": "Feature",
  "properties": {
    "date:inception_lower": "1991-01-01",
    "date:inception_upper": "1991-01-01",
    "iso:country": "GB",
    "wof:name": "MK18 1TF",
    "wof:placetype": "postalcode"
  },
  "geometry": {"coordinates":[-0.980597,51.986696],"type":"Point"}
}
