{
  "type": "Feature",
  "properties": {
    "iso:country":"GB",
    "wof:name":"NE42 6EL",
    "wof:placetype":"postalcode"
},
  "geometry": {"coordinates":[-1.89736077128929,54.9689135558782],"type":"Point"}
}