{
  "type": "Feature",
  "properties": {
    "date:inception_lower":"2001-12-01",
    "date:inception_upper":"2001-12-31",
    "iso:country":"GB",
    "wof:name":"DD7 7LG",
    "wof:placetype":"postalcode"
},
  "geometry": {"coordinates":[-2.730869,56.498534],"type":"Point"}
}