{
  "type": "Feature",
  "properties": {
    "iso:country": "GB",
    "wof:name": "DD7 7LG",
    "wof:placetype": "postalcode"
  },
  "geometry": {"coordinates":[-2.730886,56.498597],"type":"Point"}
}
