{
  "type": "Feature",
  "properties": {
    "date:inception_lower": "2001-12-01",
    "date:inception_upper": "2001-12-01",
    "iso:country": "GB",
    "wof:name": "DD7 7LG",
    "wof:placetype": "postalcode"
  },
  "geometry": {"coordinates":[-2.730886,56.498597],"type":"Point"}
}
