{
  "type": "Feature",
  "properties": {
    "iso:country": "GB",
    "wof:name": "TA4 4HT",
    "wof:placetype": "postalcode"
  },
  "geometry": {"coordinates":[-3.349729,51.131219],"type":"Point"}
}
