{
  "type": "Feature",
  "properties": {
    "date:inception_lower":"1980-01-01",
    "date:inception_upper":"1980-01-31",
    "iso:country":"GB",
    "wof:name":"TA4 4HT",
    "wof:placetype":"postalcode"
},
  "geometry": {"coordinates":[-3.349729,51.131219],"type":"Point"}
}