{
  "type": "Feature",
  "properties": {
    "iso:country":"GB",
    "wof:name":"M18 8WA",
    "wof:placetype":"postalcode"
},
  "geometry": {"coordinates":[-2.17080913193481,53.46286366706216],"type":"Point"}
}