{
  "type": "Feature",
  "properties": {
    "iso:country":"GB",
    "wof:name":"IG2 6EH",
    "wof:placetype":"postalcode"
},
  "geometry": {"coordinates":[0.07118334244101,51.57538405161274],"type":"Point"}
}