{
  "type": "Feature",
  "properties": {
    "date:inception_lower": "1980-01-01",
    "date:inception_upper": "1980-01-01",
    "iso:country": "GB",
    "wof:name": "IG2 6EH",
    "wof:placetype": "postalcode"
  },
  "geometry": {"coordinates":[0.071183,51.575384],"type":"Point"}
}
