{
  "type": "Feature",
  "properties": {
    "iso:country": "GB",
    "wof:name": "IG2 6EH",
    "wof:placetype": "postalcode"
  },
  "geometry": {"coordinates":[0.071183,51.575384],"type":"Point"}
}
