{
  "type": "Feature",
  "properties": {
    "iso:country":"GB",
    "wof:name":"NR23 1NG",
    "wof:placetype":"postalcode"
},
  "geometry": {"coordinates":[0.88746940238302,52.938033459491],"type":"Point"}
}