{
  "type": "Feature",
  "properties": {
    "iso:country": "GB",
    "wof:name": "NR23 1NG",
    "wof:placetype": "postalcode"
  },
  "geometry": {"coordinates":[0.887455,52.93806],"type":"Point"}
}
