{
  "type": "Feature",
  "properties": {
    "iso:country":"GB",
    "wof:name":"B74 4PW",
    "wof:placetype":"postalcode"
},
  "geometry": {"coordinates":[-1.8607869338151,52.59115739249714],"type":"Point"}
}