{
  "type": "Feature",
  "properties": {
    "date:inception_lower":"1980-01-01",
    "date:inception_upper":"1980-01-31",
    "iso:country":"GB",
    "wof:name":"B74 4PW",
    "wof:placetype":"postalcode"
},
  "geometry": {"coordinates":[-1.860787,52.591157],"type":"Point"}
}