{
  "type": "Feature",
  "properties": {
    "iso:country":"GB",
    "wof:name":"WS11 0ES",
    "wof:placetype":"postalcode"
},
  "geometry": {"coordinates":[-2.0266680115599,52.67638649000816],"type":"Point"}
}