{
  "type": "Feature",
  "properties": {
    "date:inception_lower":"2009-02-01",
    "date:inception_upper":"2009-02-28",
    "iso:country":"GB",
    "wof:name":"WS11 0ES",
    "wof:placetype":"postalcode"
},
  "geometry": {"coordinates":[-2.026668,52.676386],"type":"Point"}
}