{
  "type": "Feature",
  "properties": {
    "date:inception_lower": "1980-01-01",
    "date:inception_upper": "1980-01-01",
    "iso:country": "GB",
    "wof:name": "G62 8PN",
    "wof:placetype": "postalcode"
  },
  "geometry": {"coordinates":[-4.32061,55.943111],"type":"Point"}
}
