{
  "type": "Feature",
  "properties": {
    "iso:country":"GB",
    "wof:name":"G62 8PN",
    "wof:placetype":"postalcode"
},
  "geometry": {"coordinates":[-4.32061003381273,55.94311070389005],"type":"Point"}
}