{
  "type": "Feature",
  "properties": {
    "iso:country":"GB",
    "wof:name":"N11 2BJ",
    "wof:placetype":"postalcode"
},
  "geometry": {"coordinates":[-0.12313000469424,51.60965875541427],"type":"Point"}
}