{
  "type": "Feature",
  "properties": {
    "iso:country":"GB",
    "wof:name":"TS4 2UR",
    "wof:placetype":"postalcode"
},
  "geometry": {"coordinates":[-1.23104091867917,54.55577766599505],"type":"Point"}
}