{
  "type": "Feature",
  "properties": {
    "date:inception_lower": "1980-01-01",
    "date:inception_upper": "1980-01-01",
    "iso:country": "GB",
    "wof:name": "L10 1LA",
    "wof:placetype": "postalcode"
  },
  "geometry": {"coordinates":[-2.930028,53.469459],"type":"Point"}
}
