{
  "type": "Feature",
  "properties": {
    "iso:country":"GB",
    "wof:name":"L10 1LA",
    "wof:placetype":"postalcode"
},
  "geometry": {"coordinates":[-2.93002760669764,53.46945908581351],"type":"Point"}
}