{
  "type": "Feature",
  "properties": {
    "iso:country":"GB",
    "wof:name":"CA13 0UU",
    "wof:placetype":"postalcode"
},
  "geometry": {"coordinates":[-3.43459404578843,54.6586235370219],"type":"Point"}
}