{
  "type": "Feature",
  "properties": {
    "date:inception_lower": "1990-07-01",
    "date:inception_upper": "1990-07-01",
    "iso:country": "GB",
    "wof:name": "CA13 0UU",
    "wof:placetype": "postalcode"
  },
  "geometry": {"coordinates":[-3.434594,54.658624],"type":"Point"}
}
