{
  "type": "Feature",
  "properties": {
    "iso:country":"GB",
    "wof:name":"SE16 2UE",
    "wof:placetype":"postalcode"
},
  "geometry": {"coordinates":[-0.04864844106071,51.49372604641202],"type":"Point"}
}