{
  "type": "Feature",
  "properties": {
    "iso:country":"GB",
    "wof:name":"NW3 2YE",
    "wof:placetype":"postalcode"
},
  "geometry": {"coordinates":[-0.15894526113005,51.55007583989741],"type":"Point"}
}