{
  "type": "Feature",
  "properties": {
    "iso:country":"GB",
    "wof:name":"BD22 0ED",
    "wof:placetype":"postalcode"
},
  "geometry": {"coordinates":[-1.94377969687958,53.84027873206256],"type":"Point"}
}