{
  "type": "Feature",
  "properties": {
    "date:inception_lower": "1991-09-01",
    "date:inception_upper": "1991-09-01",
    "iso:country": "GB",
    "wof:name": "BD22 0ED",
    "wof:placetype": "postalcode"
  },
  "geometry": {"coordinates":[-1.94378,53.840279],"type":"Point"}
}
