{
  "type": "Feature",
  "properties": {
    "iso:country": "GB",
    "wof:name": "N1 9NL",
    "wof:placetype": "postalcode"
  },
  "geometry": {"coordinates":[-0.120263,51.530767],"type":"Point"}
}
