{
  "type": "Feature",
  "properties": {
    "iso:country":"GB",
    "wof:name":"N1 9NL",
    "wof:placetype":"postalcode"
},
  "geometry": {"coordinates":[-0.1207038314106,51.53057629219142],"type":"Point"}
}