{
  "type": "Feature",
  "properties": {
    "date:inception_lower":"1983-01-01",
    "date:inception_upper":"1983-01-31",
    "iso:country":"GB",
    "wof:name":"WA7 6HG",
    "wof:placetype":"postalcode"
},
  "geometry": {"coordinates":[-2.676032,53.316479],"type":"Point"}
}