{
  "type": "Feature",
  "properties": {
    "iso:country":"GB",
    "wof:name":"WA7 6HG",
    "wof:placetype":"postalcode"
},
  "geometry": {"coordinates":[-2.67603228211487,53.31647917951916],"type":"Point"}
}