{
  "type": "Feature",
  "properties": {
    "iso:country":"GB",
    "wof:name":"PO21 1UF",
    "wof:placetype":"postalcode"
},
  "geometry": {"coordinates":[-0.67825626793708,50.78279482559653],"type":"Point"}
}