{
  "type": "Feature",
  "properties": {
    "iso:country":"GB",
    "wof:name":"DL3 0DG",
    "wof:placetype":"postalcode"
},
  "geometry": {"coordinates":[-1.58749072272318,54.53881539154284],"type":"Point"}
}