{
  "type": "Feature",
  "properties": {
    "iso:country":"GB",
    "wof:name":"CF46 6AS",
    "wof:placetype":"postalcode"
},
  "geometry": {"coordinates":[-3.29649335576485,51.67006276154347],"type":"Point"}
}