{
  "type": "Feature",
  "properties": {
    "iso:country":"GB",
    "wof:name":"NG23 7HE",
    "wof:placetype":"postalcode"
},
  "geometry": {"coordinates":[-0.74881995657527,53.21210952191575],"type":"Point"}
}