{
  "type": "Feature",
  "properties": {
    "date:inception_lower":"1980-01-01",
    "date:inception_upper":"1980-01-31",
    "iso:country":"GB",
    "wof:name":"NG23 7HE",
    "wof:placetype":"postalcode"
},
  "geometry": {"coordinates":[-0.74882,53.21211],"type":"Point"}
}