{
  "type": "Feature",
  "properties": {
    "iso:country": "GB",
    "wof:name": "TN26 3QX",
    "wof:placetype": "postalcode"
  },
  "geometry": {"coordinates":[0.771413,51.082043],"type":"Point"}
}
