{
  "type": "Feature",
  "properties": {
    "iso:country":"GB",
    "wof:name":"B13 9AY",
    "wof:placetype":"postalcode"
},
  "geometry": {"coordinates":[-1.87787413591123,52.44966616997418],"type":"Point"}
}