{
  "type": "Feature",
  "properties": {
    "iso:country":"GB",
    "wof:name":"GL5 1AE",
    "wof:placetype":"postalcode"
},
  "geometry": {"coordinates":[-2.21710999090572,51.7448850291505],"type":"Point"}
}