{
  "type": "Feature",
  "properties": {
    "date:inception_lower": "1980-01-01",
    "date:inception_upper": "1980-01-01",
    "iso:country": "GB",
    "wof:name": "KT13 9QL",
    "wof:placetype": "postalcode"
  },
  "geometry": {"coordinates":[-0.434895,51.37456],"type":"Point"}
}
