{
  "type": "Feature",
  "properties": {
    "date:inception_lower":"1980-01-01",
    "date:inception_upper":"1980-01-31",
    "iso:country":"GB",
    "wof:name":"NG3 3HR",
    "wof:placetype":"postalcode"
},
  "geometry": {"coordinates":[-1.13666,52.962186],"type":"Point"}
}