{
  "type": "Feature",
  "properties": {
    "iso:country": "GB",
    "wof:name": "NG3 3HR",
    "wof:placetype": "postalcode"
  },
  "geometry": {"coordinates":[-1.13666,52.962186],"type":"Point"}
}
