{
  "type": "Feature",
  "properties": {
    "iso:country":"GB",
    "wof:name":"WC2H 0BB",
    "wof:placetype":"postalcode"
},
  "geometry": {"coordinates":[-0.12828988311472,51.51223595912528],"type":"Point"}
}