{
  "type": "Feature",
  "properties": {
    "date:inception_lower":"1980-01-01",
    "date:inception_upper":"1980-01-31",
    "iso:country":"GB",
    "wof:name":"WC2H 0BB",
    "wof:placetype":"postalcode"
},
  "geometry": {"coordinates":[-0.12829,51.512236],"type":"Point"}
}