{
  "type": "Feature",
  "properties": {
    "iso:country": "GB",
    "wof:name": "WS13 6WH",
    "wof:placetype": "postalcode"
  },
  "geometry": {"coordinates":[-1.850144,52.675853],"type":"Point"}
}
