{
  "type": "Feature",
  "properties": {
    "iso:country":"GB",
    "wof:name":"BR4 0NP",
    "wof:placetype":"postalcode"
},
  "geometry": {"coordinates":[-0.01712407575726,51.37586868534283],"type":"Point"}
}