{
  "type": "Feature",
  "properties": {
    "iso:country":"GB",
    "wof:name":"DG8 8LN",
    "wof:placetype":"postalcode"
},
  "geometry": {"coordinates":[-4.36603883183865,54.70037592064168],"type":"Point"}
}