{
  "type": "Feature",
  "properties": {
    "date:inception_lower": "1980-01-01",
    "date:inception_upper": "1980-01-01",
    "iso:country": "GB",
    "wof:name": "DG8 8LN",
    "wof:placetype": "postalcode"
  },
  "geometry": {"coordinates":[-4.366029,54.700389],"type":"Point"}
}
