{
  "type": "Feature",
  "properties": {
    "date:inception_lower": "1990-02-01",
    "date:inception_upper": "1990-02-01",
    "iso:country": "GB",
    "wof:name": "WV11 2SA",
    "wof:placetype": "postalcode"
  },
  "geometry": {"coordinates":[-2.058235,52.62472],"type":"Point"}
}
