{
  "type": "Feature",
  "properties": {
    "iso:country": "GB",
    "wof:name": "WV11 2SA",
    "wof:placetype": "postalcode"
  },
  "geometry": {"coordinates":[-2.058235,52.62472],"type":"Point"}
}
