{
  "type": "Feature",
  "properties": {
    "date:inception_lower":"1980-01-01",
    "date:inception_upper":"1980-01-31",
    "iso:country":"GB",
    "wof:name":"G44 3NN",
    "wof:placetype":"postalcode"
},
  "geometry": {"coordinates":[-4.264893,55.811889],"type":"Point"}
}