{
  "type": "Feature",
  "properties": {
    "iso:country":"GB",
    "wof:name":"RG7 1BY",
    "wof:placetype":"postalcode"
},
  "geometry": {"coordinates":[-0.96005271803868,51.39194238361446],"type":"Point"}
}