{
  "type": "Feature",
  "properties": {
    "iso:country":"GB",
    "wof:name":"GU34 4BN",
    "wof:placetype":"postalcode"
},
  "geometry": {"coordinates":[-0.98075302172657,51.16238465340204],"type":"Point"}
}