{
  "type": "Feature",
  "properties": {
    "iso:country":"GB",
    "wof:name":"SL0 0JG",
    "wof:placetype":"postalcode"
},
  "geometry": {"coordinates":[-0.52518875517864,51.51865300336599],"type":"Point"}
}