{
  "type": "Feature",
  "properties": {
    "iso:country": "GB",
    "wof:name": "TS22 5ET",
    "wof:placetype": "postalcode"
  },
  "geometry": {"coordinates":[-1.300391,54.609887],"type":"Point"}
}
