{
  "type": "Feature",
  "properties": {
    "iso:country":"GB",
    "wof:name":"TS22 5ET",
    "wof:placetype":"postalcode"
},
  "geometry": {"coordinates":[-1.3003909091307,54.6098866878262],"type":"Point"}
}