{
  "type": "Feature",
  "properties": {
    "iso:country": "GB",
    "wof:name": "BN8 6SP",
    "wof:placetype": "postalcode"
  },
  "geometry": {"coordinates":[0.069254,50.854377],"type":"Point"}
}
