{
  "type": "Feature",
  "properties": {
    "iso:country":"GB",
    "wof:name":"BN8 6SP",
    "wof:placetype":"postalcode"
},
  "geometry": {"coordinates":[0.06920854321031,50.85431119470557],"type":"Point"}
}