{
  "type": "Feature",
  "properties": {
    "iso:country": "GB",
    "wof:name": "KY16 9BH",
    "wof:placetype": "postalcode"
  },
  "geometry": {"coordinates":[-2.785518,56.336311],"type":"Point"}
}
