{
  "type": "Feature",
  "properties": {
    "date:inception_lower":"1998-12-01",
    "date:inception_upper":"1998-12-31",
    "iso:country":"GB",
    "wof:name":"LL11 4RH",
    "wof:placetype":"postalcode"
},
  "geometry": {"coordinates":[-3.016719,53.069212],"type":"Point"}
}