{
  "type": "Feature",
  "properties": {
    "iso:country":"GB",
    "wof:name":"LL11 4RH",
    "wof:placetype":"postalcode"
},
  "geometry": {"coordinates":[-3.01671924702085,53.06921161898367],"type":"Point"}
}