{
  "type": "Feature",
  "properties": {
    "iso:country":"GB",
    "wof:name":"B9 4PT",
    "wof:placetype":"postalcode"
},
  "geometry": {"coordinates":[-1.86705179121293,52.47666045432194],"type":"Point"}
}