{
  "type": "Feature",
  "properties": {
    "iso:country": "GB",
    "wof:name": "B9 4PT",
    "wof:placetype": "postalcode"
  },
  "geometry": {"coordinates":[-1.867052,52.47666],"type":"Point"}
}
