{
  "type": "Feature",
  "properties": {
    "date:inception_lower": "1980-01-01",
    "date:inception_upper": "1980-01-01",
    "iso:country": "GB",
    "wof:name": "B9 4PT",
    "wof:placetype": "postalcode"
  },
  "geometry": {"coordinates":[-1.867052,52.47666],"type":"Point"}
}
