{
  "type": "Feature",
  "properties": {
    "date:inception_lower": "1992-01-01",
    "date:inception_upper": "1992-01-01",
    "iso:country": "GB",
    "wof:name": "BB11 1LZ",
    "wof:placetype": "postalcode"
  },
  "geometry": {"coordinates":[-2.248797,53.788451],"type":"Point"}
}
