{
  "type": "Feature",
  "properties": {
    "iso:country":"GB",
    "wof:name":"NR31 6SY",
    "wof:placetype":"postalcode"
},
  "geometry": {"coordinates":[1.72331299454291,52.56416665047527],"type":"Point"}
}