{
  "type": "Feature",
  "properties": {
    "date:inception_lower": "1992-01-01",
    "date:inception_upper": "1992-01-01",
    "iso:country": "GB",
    "wof:name": "WR5 3TJ",
    "wof:placetype": "postalcode"
  },
  "geometry": {"coordinates":[-2.197752,52.169248],"type":"Point"}
}
