{
  "type": "Feature",
  "properties": {
    "iso:country":"GB",
    "wof:name":"WR5 3TJ",
    "wof:placetype":"postalcode"
},
  "geometry": {"coordinates":[-2.1977517496594,52.16924774460184],"type":"Point"}
}