{
  "type": "Feature",
  "properties": {
    "iso:country": "GB",
    "wof:name": "LD3 7HZ",
    "wof:placetype": "postalcode"
  },
  "geometry": {"coordinates":[-3.234421,51.891779],"type":"Point"}
}
