{
  "type": "Feature",
  "properties": {
    "iso:country":"GB",
    "wof:name":"LD3 7HZ",
    "wof:placetype":"postalcode"
},
  "geometry": {"coordinates":[-3.23442067083528,51.8917791967303],"type":"Point"}
}