{
  "type": "Feature",
  "properties": {
    "iso:country":"GB",
    "wof:name":"S63 8LH",
    "wof:placetype":"postalcode"
},
  "geometry": {"coordinates":[-1.31710583921939,53.51741279594789],"type":"Point"}
}