{
  "type": "Feature",
  "properties": {
    "iso:country":"GB",
    "wof:name":"DY6 9TX",
    "wof:placetype":"postalcode"
},
  "geometry": {"coordinates":[-2.17041399037158,52.48678838557632],"type":"Point"}
}