{
  "type": "Feature",
  "properties": {
    "date:inception_lower": "1999-06-01",
    "date:inception_upper": "1999-06-01",
    "iso:country": "GB",
    "wof:name": "NP11 5BG",
    "wof:placetype": "postalcode"
  },
  "geometry": {"coordinates":[-3.11632,51.689214],"type":"Point"}
}
