{
  "type": "Feature",
  "properties": {
    "iso:country":"GB",
    "wof:name":"NP11 5BG",
    "wof:placetype":"postalcode"
},
  "geometry": {"coordinates":[-3.1163203398955,51.6892136566477],"type":"Point"}
}