{
  "type": "Feature",
  "properties": {
    "iso:country": "GB",
    "wof:name": "NP11 5BG",
    "wof:placetype": "postalcode"
  },
  "geometry": {"coordinates":[-3.11632,51.689214],"type":"Point"}
}
