{
  "type": "Feature",
  "properties": {
    "iso:country":"GB",
    "wof:name":"CH66 1JR",
    "wof:placetype":"postalcode"
},
  "geometry": {"coordinates":[-2.92637449780971,53.28700324576082],"type":"Point"}
}