{
  "type": "Feature",
  "properties": {
    "iso:country": "GB",
    "wof:name": "CW12 1EW",
    "wof:placetype": "postalcode"
  },
  "geometry": {"coordinates":[-2.21399,53.165915],"type":"Point"}
}
