{
  "type": "Feature",
  "properties": {
    "iso:country":"GB",
    "wof:name":"CW12 1EW",
    "wof:placetype":"postalcode"
},
  "geometry": {"coordinates":[-2.21391592414238,53.1658882729119],"type":"Point"}
}