{
  "type": "Feature",
  "properties": {
    "iso:country":"GB",
    "wof:name":"GU28 9AJ",
    "wof:placetype":"postalcode"
},
  "geometry": {"coordinates":[-0.63131367246939,50.98959459884787],"type":"Point"}
}