{
  "type": "Feature",
  "properties": {
    "iso:country": "GB",
    "wof:name": "GU28 9AJ",
    "wof:placetype": "postalcode"
  },
  "geometry": {"coordinates":[-0.631314,50.989595],"type":"Point"}
}
