{
  "type": "Feature",
  "properties": {
    "iso:country":"GB",
    "wof:name":"RG26 4LN",
    "wof:placetype":"postalcode"
},
  "geometry": {"coordinates":[-1.14330511442677,51.35182846741041],"type":"Point"}
}