{
  "type": "Feature",
  "properties": {
    "date:inception_lower": "1980-01-01",
    "date:inception_upper": "1980-01-01",
    "iso:country": "GB",
    "wof:name": "WF6 1JR",
    "wof:placetype": "postalcode"
  },
  "geometry": {"coordinates":[-1.41662,53.688117],"type":"Point"}
}
