{
  "type": "Feature",
  "properties": {
    "date:inception_lower":"1980-01-01",
    "date:inception_upper":"1980-01-31",
    "iso:country":"GB",
    "wof:name":"SW8 3JD",
    "wof:placetype":"postalcode"
},
  "geometry": {"coordinates":[-0.140798,51.469433],"type":"Point"}
}