{
  "type": "Feature",
  "properties": {
    "iso:country":"GB",
    "wof:name":"SW8 3JD",
    "wof:placetype":"postalcode"
},
  "geometry": {"coordinates":[-0.14079725682913,51.46944156940271],"type":"Point"}
}