{
  "type": "Feature",
  "properties": {
    "iso:country":"GB",
    "wof:name":"SS5 4HL",
    "wof:placetype":"postalcode"
},
  "geometry": {"coordinates":[0.66632750842756,51.59795616385836],"type":"Point"}
}