{
  "type": "Feature",
  "properties": {
    "iso:country":"GB",
    "wof:name":"ST6 4BE",
    "wof:placetype":"postalcode"
},
  "geometry": {"coordinates":[-2.20248569726315,53.04466437565664],"type":"Point"}
}