{
  "type": "Feature",
  "properties": {
    "iso:country": "GB",
    "wof:name": "EH11 3JE",
    "wof:placetype": "postalcode"
  },
  "geometry": {"coordinates":[-3.256818,55.930586],"type":"Point"}
}
