{
  "type": "Feature",
  "properties": {
    "date:inception_lower":"1980-01-01",
    "date:inception_upper":"1980-01-31",
    "iso:country":"GB",
    "wof:name":"WA10 1NY",
    "wof:placetype":"postalcode"
},
  "geometry": {"coordinates":[-2.738963,53.451378],"type":"Point"}
}