{
  "type": "Feature",
  "properties": {
    "iso:country":"GB",
    "wof:name":"WA10 1NY",
    "wof:placetype":"postalcode"
},
  "geometry": {"coordinates":[-2.738963473038,53.45137824449898],"type":"Point"}
}