{
  "type": "Feature",
  "properties": {
    "iso:country":"GB",
    "wof:name":"OL2 7UE",
    "wof:placetype":"postalcode"
},
  "geometry": {"coordinates":[-2.09066935616358,53.58492373889376],"type":"Point"}
}