{
  "type": "Feature",
  "properties": {
    "iso:country":"GB",
    "wof:name":"SG7 6BN",
    "wof:placetype":"postalcode"
},
  "geometry": {"coordinates":[-0.18630538208065,51.98508125325473],"type":"Point"}
}