{
  "type": "Feature",
  "properties": {
    "iso:country":"GB",
    "wof:name":"LN2 1RG",
    "wof:placetype":"postalcode"
},
  "geometry": {"coordinates":[-0.53100775355558,53.23793223132689],"type":"Point"}
}