{
  "type": "Feature",
  "properties": {
    "date:inception_lower": "1980-01-01",
    "date:inception_upper": "1980-01-01",
    "iso:country": "GB",
    "wof:name": "LN2 1RG",
    "wof:placetype": "postalcode"
  },
  "geometry": {"coordinates":[-0.531008,53.237932],"type":"Point"}
}
