{
  "type": "Feature",
  "properties": {
    "iso:country":"GB",
    "wof:name":"BS16 1XS",
    "wof:placetype":"postalcode"
},
  "geometry": {"coordinates":[-2.54295896154322,51.48499588413613],"type":"Point"}
}