{
  "type": "Feature",
  "properties": {
    "iso:country":"GB",
    "wof:name":"WD5 0DZ",
    "wof:placetype":"postalcode"
},
  "geometry": {"coordinates":[-0.41296539461936,51.70962785208189],"type":"Point"}
}