{
  "type": "Feature",
  "properties": {
    "iso:country":"GB",
    "wof:name":"SK8 2NW",
    "wof:placetype":"postalcode"
},
  "geometry": {"coordinates":[-2.22043052396141,53.39742671904143],"type":"Point"}
}