{
  "type": "Feature",
  "properties": {
    "date:inception_lower": "2011-02-01",
    "date:inception_upper": "2011-02-01",
    "iso:country": "GB",
    "wof:name": "SK8 2NW",
    "wof:placetype": "postalcode"
  },
  "geometry": {"coordinates":[-2.22043,53.397427],"type":"Point"}
}
