{
  "type": "Feature",
  "properties": {
    "date:inception_lower": "1980-01-01",
    "date:inception_upper": "1980-01-01",
    "iso:country": "GB",
    "wof:name": "DH7 0PT",
    "wof:placetype": "postalcode"
  },
  "geometry": {"coordinates":[-1.751983,54.824177],"type":"Point"}
}
