{
  "type": "Feature",
  "properties": {
    "iso:country":"GB",
    "wof:name":"DH7 0PT",
    "wof:placetype":"postalcode"
},
  "geometry": {"coordinates":[-1.75198347786909,54.82417705092637],"type":"Point"}
}