{
  "type": "Feature",
  "properties": {
    "iso:country":"GB",
    "wof:name":"HX2 6EX",
    "wof:placetype":"postalcode"
},
  "geometry": {"coordinates":[-1.9460481812013,53.71816002262837],"type":"Point"}
}