{
  "type": "Feature",
  "properties": {
    "iso:country":"GB",
    "wof:name":"SW6 2SN",
    "wof:placetype":"postalcode"
},
  "geometry": {"coordinates":[-0.18841528227218,51.46681478520028],"type":"Point"}
}