{
  "type": "Feature",
  "properties": {
    "date:inception_lower": "1980-01-01",
    "date:inception_upper": "1980-01-01",
    "iso:country": "GB",
    "wof:name": "HD1 4NZ",
    "wof:placetype": "postalcode"
  },
  "geometry": {"coordinates":[-1.805081,53.65214],"type":"Point"}
}
