{
  "type": "Feature",
  "properties": {
    "iso:country":"GB",
    "wof:name":"HD1 4NZ",
    "wof:placetype":"postalcode"
},
  "geometry": {"coordinates":[-1.80508120461549,53.65213985971603],"type":"Point"}
}