{
  "type": "Feature",
  "properties": {
    "iso:country":"GB",
    "wof:name":"RM9 6DS",
    "wof:placetype":"postalcode"
},
  "geometry": {"coordinates":[0.13414397749564,51.53825765292179],"type":"Point"}
}