{
  "type": "Feature",
  "properties": {
    "date:inception_lower": "2016-09-01",
    "date:inception_upper": "2016-09-01",
    "iso:country": "GB",
    "wof:name": "B24 0LD",
    "wof:placetype": "postalcode"
  },
  "geometry": {"coordinates":[-1.820909,52.522193],"type":"Point"}
}
