{
  "type": "Feature",
  "properties": {
    "date:inception_lower": "1980-01-01",
    "date:inception_upper": "1980-01-01",
    "iso:country": "GB",
    "wof:name": "DH2 3SD",
    "wof:placetype": "postalcode"
  },
  "geometry": {"coordinates":[-1.610344,54.845642],"type":"Point"}
}
