{
  "type": "Feature",
  "properties": {
    "iso:country":"GB",
    "wof:name":"DH2 3SD",
    "wof:placetype":"postalcode"
},
  "geometry": {"coordinates":[-1.6103439612792,54.84564249655978],"type":"Point"}
}