{
  "type": "Feature",
  "properties": {
    "iso:country": "GB",
    "wof:name": "BH25 6TJ",
    "wof:placetype": "postalcode"
  },
  "geometry": {"coordinates":[-1.67181,50.75295],"type":"Point"}
}
