{
  "type": "Feature",
  "properties": {
    "iso:country":"GB",
    "wof:name":"BH25 6TJ",
    "wof:placetype":"postalcode"
},
  "geometry": {"coordinates":[-1.67181029191848,50.75294967027627],"type":"Point"}
}