{
  "type": "Feature",
  "properties": {
    "iso:country":"GB",
    "wof:name":"DD9 7EE",
    "wof:placetype":"postalcode"
},
  "geometry": {"coordinates":[-2.64427619139827,56.7275763360019],"type":"Point"}
}