{
  "type": "Feature",
  "properties": {
    "date:inception_lower": "1999-06-01",
    "date:inception_upper": "1999-06-01",
    "iso:country": "GB",
    "wof:name": "CF44 0AH",
    "wof:placetype": "postalcode"
  },
  "geometry": {"coordinates":[-3.420219,51.70196],"type":"Point"}
}
