{
  "type": "Feature",
  "properties": {
    "date:inception_lower": "1999-06-01",
    "date:inception_upper": "1999-06-01",
    "iso:country": "GB",
    "wof:name": "CF44 0AH",
    "wof:placetype": "postalcode"
  },
  "geometry": {"coordinates":[-3.42038,51.702039],"type":"Point"}
}
