{
  "type": "Feature",
  "properties": {
    "iso:country": "GB",
    "wof:name": "CF44 0AH",
    "wof:placetype": "postalcode"
  },
  "geometry": {"coordinates":[-3.42038,51.702039],"type":"Point"}
}
