{
  "type": "Feature",
  "properties": {
    "iso:country":"GB",
    "wof:name":"TS4 2JA",
    "wof:placetype":"postalcode"
},
  "geometry": {"coordinates":[-1.22518252673315,54.56873561590011],"type":"Point"}
}