{
  "type": "Feature",
  "properties": {
    "iso:country": "GB",
    "wof:name": "W13 8HL",
    "wof:placetype": "postalcode"
  },
  "geometry": {"coordinates":[-0.315438,51.518886],"type":"Point"}
}
