{
  "type": "Feature",
  "properties": {
    "iso:country": "GB",
    "wof:name": "BL0 9XA",
    "wof:placetype": "postalcode"
  },
  "geometry": {"coordinates":[-2.325963,53.625743],"type":"Point"}
}
