{
  "type": "Feature",
  "properties": {
    "iso:country":"GB",
    "wof:name":"BL0 9XA",
    "wof:placetype":"postalcode"
},
  "geometry": {"coordinates":[-2.325962611947,53.62574285593912],"type":"Point"}
}