{
  "type": "Feature",
  "properties": {
    "iso:country": "GB",
    "wof:name": "PO5 3DH",
    "wof:placetype": "postalcode"
  },
  "geometry": {"coordinates":[-1.090796,50.789077],"type":"Point"}
}
