{
  "type": "Feature",
  "properties": {
    "iso:country":"GB",
    "wof:name":"HA6 1HL",
    "wof:placetype":"postalcode"
},
  "geometry": {"coordinates":[-0.41996000773832,51.60393117231748],"type":"Point"}
}