{
  "type": "Feature",
  "properties": {
    "iso:country": "GB",
    "wof:name": "G72 7HB",
    "wof:placetype": "postalcode"
  },
  "geometry": {"coordinates":[-4.167753,55.819257],"type":"Point"}
}
