{
  "type": "Feature",
  "properties": {
    "date:inception_lower": "2021-08-01",
    "date:inception_upper": "2021-08-01",
    "iso:country": "GB",
    "wof:name": "L32 1BY",
    "wof:placetype": "postalcode"
  },
  "geometry": {"coordinates":[-2.876969,53.491422],"type":"Point"}
}
