{
  "type": "Feature",
  "properties": {
    "date:inception_lower": "1980-01-01",
    "date:inception_upper": "1980-01-01",
    "iso:country": "GB",
    "wof:name": "WF7 7LE",
    "wof:placetype": "postalcode"
  },
  "geometry": {"coordinates":[-1.34383,53.644309],"type":"Point"}
}
