{
  "type": "Feature",
  "properties": {
    "iso:country":"GB",
    "wof:name":"WF7 7LE",
    "wof:placetype":"postalcode"
},
  "geometry": {"coordinates":[-1.34382958390977,53.6443086097189],"type":"Point"}
}