{
  "type": "Feature",
  "properties": {
    "iso:country": "GB",
    "wof:name": "LE10 9ZZ",
    "wof:placetype": "postalcode"
  },
  "geometry": {"coordinates":[-1.369606,52.540352],"type":"Point"}
}
