{
  "type": "Feature",
  "properties": {
    "date:inception_lower":"2005-01-01",
    "date:inception_upper":"2005-01-31",
    "iso:country":"GB",
    "wof:name":"LE10 9ZZ",
    "wof:placetype":"postalcode"
},
  "geometry": {"coordinates":[-1.369606,52.540352],"type":"Point"}
}