{
  "type": "Feature",
  "properties": {
    "date:inception_lower": "1980-01-01",
    "date:inception_upper": "1980-01-01",
    "iso:country": "GB",
    "wof:name": "BA21 3PZ",
    "wof:placetype": "postalcode"
  },
  "geometry": {"coordinates":[-2.676938,50.958103],"type":"Point"}
}
