{
  "type": "Feature",
  "properties": {
    "iso:country":"GB",
    "wof:name":"BA21 3PZ",
    "wof:placetype":"postalcode"
},
  "geometry": {"coordinates":[-2.67693821220216,50.95810321506679],"type":"Point"}
}