{
  "type": "Feature",
  "properties": {
    "iso:country":"GB",
    "wof:name":"WF13 4AH",
    "wof:placetype":"postalcode"
},
  "geometry": {"coordinates":[-1.65267837278545,53.70425915381156],"type":"Point"}
}