{
  "type": "Feature",
  "properties": {
    "date:inception_lower":"2009-05-01",
    "date:inception_upper":"2009-05-31",
    "iso:country":"GB",
    "wof:name":"IP25 7DQ",
    "wof:placetype":"postalcode"
},
  "geometry": {"coordinates":[0.791139,52.634821],"type":"Point"}
}