{
  "type": "Feature",
  "properties": {
    "iso:country":"GB",
    "wof:name":"IP25 7DQ",
    "wof:placetype":"postalcode"
},
  "geometry": {"coordinates":[0.79113883775697,52.63482147100572],"type":"Point"}
}