{
  "type": "Feature",
  "properties": {
    "iso:country":"GB",
    "wof:name":"CF63 2HF",
    "wof:placetype":"postalcode"
},
  "geometry": {"coordinates":[-3.2559378178907,51.41267917079319],"type":"Point"}
}