{
  "type": "Feature",
  "properties": {
    "iso:country":"GB",
    "wof:name":"PE25 1SD",
    "wof:placetype":"postalcode"
},
  "geometry": {"coordinates":[0.34068126029189,53.15241301685795],"type":"Point"}
}