{
  "type": "Feature",
  "properties": {
    "iso:country":"GB",
    "wof:name":"ST7 1ET",
    "wof:placetype":"postalcode"
},
  "geometry": {"coordinates":[-2.2415550546463,53.08816147802528],"type":"Point"}
}