{
  "type": "Feature",
  "properties": {
    "iso:country":"GB",
    "wof:name":"S64 8AJ",
    "wof:placetype":"postalcode"
},
  "geometry": {"coordinates":[-1.29947659636811,53.48623725646448],"type":"Point"}
}