{
  "type": "Feature",
  "properties": {
    "iso:country": "GB",
    "wof:name": "S64 8AJ",
    "wof:placetype": "postalcode"
  },
  "geometry": {"coordinates":[-1.299477,53.486237],"type":"Point"}
}
