{
  "type": "Feature",
  "properties": {
    "date:inception_lower":"2010-10-01",
    "date:inception_upper":"2010-10-31",
    "iso:country":"GB",
    "wof:name":"LE17 4LB",
    "wof:placetype":"postalcode"
},
  "geometry": {"coordinates":[-1.163852,52.448331],"type":"Point"}
}