{
  "type": "Feature",
  "properties": {
    "iso:country": "GB",
    "wof:name": "LE17 4LB",
    "wof:placetype": "postalcode"
  },
  "geometry": {"coordinates":[-1.163852,52.448331],"type":"Point"}
}
