{
  "type": "Feature",
  "properties": {
    "iso:country":"GB",
    "wof:name":"LE17 4LB",
    "wof:placetype":"postalcode"
},
  "geometry": {"coordinates":[-1.16385176557185,52.44833059152278],"type":"Point"}
}