{
  "type": "Feature",
  "properties": {
    "iso:country": "GB",
    "wof:name": "LL28 5RY",
    "wof:placetype": "postalcode"
  },
  "geometry": {"coordinates":[-3.816814,53.223511],"type":"Point"}
}
