{
  "type": "Feature",
  "properties": {
    "iso:country": "GB",
    "wof:name": "DY3 1AE",
    "wof:placetype": "postalcode"
  },
  "geometry": {"coordinates":[-2.118058,52.537121],"type":"Point"}
}
