{
  "type": "Feature",
  "properties": {
    "iso:country":"GB",
    "wof:name":"GL11 6LZ",
    "wof:placetype":"postalcode"
},
  "geometry": {"coordinates":[-2.37072476676828,51.69687434067077],"type":"Point"}
}