{
  "type": "Feature",
  "properties": {
    "iso:country": "GB",
    "wof:name": "GL11 6LZ",
    "wof:placetype": "postalcode"
  },
  "geometry": {"coordinates":[-2.370725,51.696874],"type":"Point"}
}
