{
  "type": "Feature",
  "properties": {
    "iso:country":"GB",
    "wof:name":"BB9 0PF",
    "wof:placetype":"postalcode"
},
  "geometry": {"coordinates":[-2.1990076202187,53.83560539575437],"type":"Point"}
}