{
  "type": "Feature",
  "properties": {
    "iso:country": "GB",
    "wof:name": "WF15 7EG",
    "wof:placetype": "postalcode"
  },
  "geometry": {"coordinates":[-1.680475,53.704675],"type":"Point"}
}
