{
  "type": "Feature",
  "properties": {
    "iso:country": "GB",
    "wof:name": "EH32 9JR",
    "wof:placetype": "postalcode"
  },
  "geometry": {"coordinates":[-2.983503,55.957817],"type":"Point"}
}
