{
  "type": "Feature",
  "properties": {
    "date:inception_lower":"1980-01-01",
    "date:inception_upper":"1980-01-31",
    "iso:country":"GB",
    "wof:name":"EH32 9JR",
    "wof:placetype":"postalcode"
},
  "geometry": {"coordinates":[-2.983503,55.957817],"type":"Point"}
}