{
  "type": "Feature",
  "properties": {
    "iso:country":"GB",
    "wof:name":"SY23 3TW",
    "wof:placetype":"postalcode"
},
  "geometry": {"coordinates":[-3.98827191198635,52.43761254431849],"type":"Point"}
}