{
  "type": "Feature",
  "properties": {
    "iso:country": "GB",
    "wof:name": "SY23 3TW",
    "wof:placetype": "postalcode"
  },
  "geometry": {"coordinates":[-3.988272,52.437613],"type":"Point"}
}
