{
  "type": "Feature",
  "properties": {
    "iso:country": "GB",
    "wof:name": "SS14 1PB",
    "wof:placetype": "postalcode"
  },
  "geometry": {"coordinates":[0.484922,51.570885],"type":"Point"}
}
