{
  "type": "Feature",
  "properties": {
    "iso:country": "GB",
    "wof:name": "CH7 4AZ",
    "wof:placetype": "postalcode"
  },
  "geometry": {"coordinates":[-3.175776,53.1377],"type":"Point"}
}
