{
  "type": "Feature",
  "properties": {
    "date:inception_lower": "2018-09-01",
    "date:inception_upper": "2018-09-01",
    "iso:country": "GB",
    "wof:name": "CH7 4AZ",
    "wof:placetype": "postalcode"
  },
  "geometry": {"coordinates":[-3.175776,53.1377],"type":"Point"}
}
