{
  "type": "Feature",
  "properties": {
    "iso:country": "GB",
    "wof:name": "RH14 9XF",
    "wof:placetype": "postalcode"
  },
  "geometry": {"coordinates":[-0.45248,51.015295],"type":"Point"}
}
