{
  "type": "Feature",
  "properties": {
    "iso:country":"GB",
    "wof:name":"RH14 9XF",
    "wof:placetype":"postalcode"
},
  "geometry": {"coordinates":[-0.45248041014909,51.01529458432157],"type":"Point"}
}