{
  "type": "Feature",
  "properties": {
    "date:inception_lower": "1980-01-01",
    "date:inception_upper": "1980-01-01",
    "iso:country": "GB",
    "wof:name": "KA3 1DS",
    "wof:placetype": "postalcode"
  },
  "geometry": {"coordinates":[-4.493656,55.614699],"type":"Point"}
}
