{
  "type": "Feature",
  "properties": {
    "date:inception_lower":"1980-01-01",
    "date:inception_upper":"1980-01-31",
    "iso:country":"GB",
    "wof:name":"CA5 6HU",
    "wof:placetype":"postalcode"
},
  "geometry": {"coordinates":[-3.077907,54.898933],"type":"Point"}
}