{
  "type": "Feature",
  "properties": {
    "iso:country":"GB",
    "wof:name":"CA5 6HU",
    "wof:placetype":"postalcode"
},
  "geometry": {"coordinates":[-3.07790713585597,54.89893337404811],"type":"Point"}
}