{
  "type": "Feature",
  "properties": {
    "iso:country": "GB",
    "wof:name": "CA5 6HU",
    "wof:placetype": "postalcode"
  },
  "geometry": {"coordinates":[-3.077907,54.898933],"type":"Point"}
}
