{
  "type": "Feature",
  "properties": {
    "iso:country": "GB",
    "wof:name": "RG8 8SA",
    "wof:placetype": "postalcode"
  },
  "geometry": {"coordinates":[-1.174551,51.497712],"type":"Point"}
}
