{
  "type": "Feature",
  "properties": {
    "iso:country":"GB",
    "wof:name":"RG8 8SA",
    "wof:placetype":"postalcode"
},
  "geometry": {"coordinates":[-1.17457138245723,51.49771080808749],"type":"Point"}
}