{
  "type": "Feature",
  "properties": {
    "date:inception_lower": "1980-01-01",
    "date:inception_upper": "1980-01-01",
    "iso:country": "GB",
    "wof:name": "RG8 8SA",
    "wof:placetype": "postalcode"
  },
  "geometry": {"coordinates":[-1.179505,51.496991],"type":"Point"}
}
