{
  "type": "Feature",
  "properties": {
    "iso:country":"GB",
    "wof:name":"BN1 5LA",
    "wof:placetype":"postalcode"
},
  "geometry": {"coordinates":[-0.16023447317839,50.84677770068053],"type":"Point"}
}