{
  "type": "Feature",
  "properties": {
    "date:inception_lower": "1983-07-01",
    "date:inception_upper": "1983-07-01",
    "iso:country": "GB",
    "wof:name": "SL6 4UZ",
    "wof:placetype": "postalcode"
  },
  "geometry": {"coordinates":[-0.725126,51.522255],"type":"Point"}
}
