{
  "type": "Feature",
  "properties": {
    "iso:country":"GB",
    "wof:name":"PO17 6EF",
    "wof:placetype":"postalcode"
},
  "geometry": {"coordinates":[-1.11238497492108,50.87462035678785],"type":"Point"}
}