{
  "type": "Feature",
  "properties": {
    "date:inception_lower":"2003-03-01",
    "date:inception_upper":"2003-03-31",
    "iso:country":"GB",
    "wof:name":"EX2 7HA",
    "wof:placetype":"postalcode"
},
  "geometry": {"coordinates":[-3.470735,50.71423],"type":"Point"}
}