{
  "type": "Feature",
  "properties": {
    "iso:country":"GB",
    "wof:name":"EX2 7HA",
    "wof:placetype":"postalcode"
},
  "geometry": {"coordinates":[-3.4707350264758,50.7142301606439],"type":"Point"}
}