{
  "type": "Feature",
  "properties": {
    "iso:country":"GB",
    "wof:name":"CA28 9PE",
    "wof:placetype":"postalcode"
},
  "geometry": {"coordinates":[-3.59793411785062,54.53264422735236],"type":"Point"}
}