{
  "type": "Feature",
  "properties": {
    "date:inception_lower": "2015-08-01",
    "date:inception_upper": "2015-08-01",
    "iso:country": "GB",
    "wof:name": "CA28 9PE",
    "wof:placetype": "postalcode"
  },
  "geometry": {"coordinates":[-3.598158,54.532435],"type":"Point"}
}
