{
  "type": "Feature",
  "properties": {
    "iso:country":"GB",
    "wof:name":"PO5 2PH",
    "wof:placetype":"postalcode"
},
  "geometry": {"coordinates":[-1.07994371711537,50.78179799406529],"type":"Point"}
}