{
  "type": "Feature",
  "properties": {
    "iso:country": "GB",
    "wof:name": "OL12 0BP",
    "wof:placetype": "postalcode"
  },
  "geometry": {"coordinates":[-2.153788,53.633063],"type":"Point"}
}
