{
  "type": "Feature",
  "properties": {
    "iso:country":"GB",
    "wof:name":"FY3 0DH",
    "wof:placetype":"postalcode"
},
  "geometry": {"coordinates":[-2.98717483256097,53.81681380236581],"type":"Point"}
}