{
  "type": "Feature",
  "properties": {
    "date:inception_lower":"2010-03-01",
    "date:inception_upper":"2010-03-31",
    "iso:country":"GB",
    "wof:name":"ME3 9FR",
    "wof:placetype":"postalcode"
},
  "geometry": {"coordinates":[0.562956,51.42585],"type":"Point"}
}