{
  "type": "Feature",
  "properties": {
    "iso:country":"GB",
    "wof:name":"BL1 3LB",
    "wof:placetype":"postalcode"
},
  "geometry": {"coordinates":[-2.44913313026506,53.59471161871537],"type":"Point"}
}