{
  "type": "Feature",
  "properties": {
    "iso:country":"GB",
    "wof:name":"SW1V 3RZ",
    "wof:placetype":"postalcode"
},
  "geometry": {"coordinates":[-0.13362252180812,51.48683609862614],"type":"Point"}
}