{
  "type": "Feature",
  "properties": {
    "iso:country":"GB",
    "wof:name":"SS7 5EJ",
    "wof:placetype":"postalcode"
},
  "geometry": {"coordinates":[0.55424351501211,51.55066248738704],"type":"Point"}
}