{
  "type": "Feature",
  "properties": {
    "iso:country":"GB",
    "wof:name":"EX8 5PH",
    "wof:placetype":"postalcode"
},
  "geometry": {"coordinates":[-3.39638409101164,50.64175967776725],"type":"Point"}
}