{
  "type": "Feature",
  "properties": {
    "iso:country":"GB",
    "wof:name":"HG4 3JE",
    "wof:placetype":"postalcode"
},
  "geometry": {"coordinates":[-1.60919681223314,54.18772266333223],"type":"Point"}
}