{
  "type": "Feature",
  "properties": {
    "iso:country": "GB",
    "wof:name": "EH33 1HD",
    "wof:placetype": "postalcode"
  },
  "geometry": {"coordinates":[-2.894078,55.943744],"type":"Point"}
}
