{
  "type": "Feature",
  "properties": {
    "iso:country":"GB",
    "wof:name":"EH33 1HD",
    "wof:placetype":"postalcode"
},
  "geometry": {"coordinates":[-2.89407765362519,55.9437444732593],"type":"Point"}
}