{
  "type": "Feature",
  "properties": {
    "iso:country":"GB",
    "wof:name":"WV12 4LW",
    "wof:placetype":"postalcode"
},
  "geometry": {"coordinates":[-2.04926767622153,52.59831248831134],"type":"Point"}
}