{
  "type": "Feature",
  "properties": {
    "iso:country":"GB",
    "wof:name":"GU22 8AP",
    "wof:placetype":"postalcode"
},
  "geometry": {"coordinates":[-0.54330574763526,51.32230923005387],"type":"Point"}
}