{
  "type": "Feature",
  "properties": {
    "date:inception_lower": "1993-08-01",
    "date:inception_upper": "1993-08-01",
    "iso:country": "GB",
    "wof:name": "GU22 8AP",
    "wof:placetype": "postalcode"
  },
  "geometry": {"coordinates":[-0.543306,51.322309],"type":"Point"}
}
