{
  "type": "Feature",
  "properties": {
    "iso:country":"GB",
    "wof:name":"KT6 7TH",
    "wof:placetype":"postalcode"
},
  "geometry": {"coordinates":[-0.29801547611285,51.37908088927363],"type":"Point"}
}