{
  "type": "Feature",
  "properties": {
    "date:inception_lower":"1990-02-01",
    "date:inception_upper":"1990-02-28",
    "iso:country":"GB",
    "wof:name":"L34 9GP",
    "wof:placetype":"postalcode"
},
  "geometry": {"coordinates":[-2.865987,53.461329],"type":"Point"}
}