{
  "type": "Feature",
  "properties": {
    "iso:country":"GB",
    "wof:name":"L34 9GP",
    "wof:placetype":"postalcode"
},
  "geometry": {"coordinates":[-2.86598718670684,53.46132926746798],"type":"Point"}
}