{
  "type": "Feature",
  "properties": {
    "iso:country":"GB",
    "wof:name":"IP21 5ED",
    "wof:placetype":"postalcode"
},
  "geometry": {"coordinates":[1.23432829901202,52.29941096519224],"type":"Point"}
}