{
  "type": "Feature",
  "properties": {
    "iso:country": "GB",
    "wof:name": "IP21 5ED",
    "wof:placetype": "postalcode"
  },
  "geometry": {"coordinates":[1.234328,52.299411],"type":"Point"}
}
