{
  "type": "Feature",
  "properties": {
    "date:inception_lower": "1980-01-01",
    "date:inception_upper": "1980-01-01",
    "iso:country": "GB",
    "wof:name": "BH15 3JU",
    "wof:placetype": "postalcode"
  },
  "geometry": {"coordinates":[-1.975732,50.733265],"type":"Point"}
}
