{
  "type": "Feature",
  "properties": {
    "iso:country":"GB",
    "wof:name":"BH15 3JU",
    "wof:placetype":"postalcode"
},
  "geometry": {"coordinates":[-1.9757318969374,50.73326471169447],"type":"Point"}
}