{
  "type": "Feature",
  "properties": {
    "iso:country": "GB",
    "wof:name": "YO30 2BG",
    "wof:placetype": "postalcode"
  },
  "geometry": {"coordinates":[-1.227249,54.05489],"type":"Point"}
}
