{
  "type": "Feature",
  "properties": {
    "date:inception_lower": "1998-06-01",
    "date:inception_upper": "1998-06-01",
    "iso:country": "GB",
    "wof:name": "YO30 2BG",
    "wof:placetype": "postalcode"
  },
  "geometry": {"coordinates":[-1.227249,54.05489],"type":"Point"}
}
