{
  "type": "Feature",
  "properties": {
    "iso:country":"GB",
    "wof:name":"YO32 5WZ",
    "wof:placetype":"postalcode"
},
  "geometry": {"coordinates":[-1.0375179299775,54.03628463580026],"type":"Point"}
}