{
  "type": "Feature",
  "properties": {
    "iso:country": "GB",
    "wof:name": "YO32 5WZ",
    "wof:placetype": "postalcode"
  },
  "geometry": {"coordinates":[-1.037518,54.036285],"type":"Point"}
}
