{
  "type": "Feature",
  "properties": {
    "iso:country":"GB",
    "wof:name":"SL6 5HT",
    "wof:placetype":"postalcode"
},
  "geometry": {"coordinates":[-0.75174540731715,51.52869158776441],"type":"Point"}
}