{
  "type": "Feature",
  "properties": {
    "iso:country": "GB",
    "wof:name": "SL6 5HT",
    "wof:placetype": "postalcode"
  },
  "geometry": {"coordinates":[-0.751745,51.528692],"type":"Point"}
}
