{
  "type": "Feature",
  "properties": {
    "date:inception_lower":"1998-12-01",
    "date:inception_upper":"1998-12-31",
    "iso:country":"GB",
    "wof:name":"SL6 5HT",
    "wof:placetype":"postalcode"
},
  "geometry": {"coordinates":[-0.751745,51.528692],"type":"Point"}
}