{
  "type": "Feature",
  "properties": {
    "iso:country":"GB",
    "wof:name":"SM1 3BL",
    "wof:placetype":"postalcode"
},
  "geometry": {"coordinates":[-0.17581136181015,51.37160358072796],"type":"Point"}
}