{
  "type": "Feature",
  "properties": {
    "iso:country":"GB",
    "wof:name":"MK45 3QH",
    "wof:placetype":"postalcode"
},
  "geometry": {"coordinates":[-0.39819285945014,52.06630794368628],"type":"Point"}
}