{
  "type": "Feature",
  "properties": {
    "date:inception_lower": "1980-01-01",
    "date:inception_upper": "1980-01-01",
    "iso:country": "GB",
    "wof:name": "MK45 3QH",
    "wof:placetype": "postalcode"
  },
  "geometry": {"coordinates":[-0.398193,52.066308],"type":"Point"}
}
