{
  "type": "Feature",
  "properties": {
    "date:inception_lower": "2016-02-01",
    "date:inception_upper": "2016-02-01",
    "iso:country": "GB",
    "wof:name": "L3 1DD",
    "wof:placetype": "postalcode"
  },
  "geometry": {"coordinates":[-2.994018,53.404763],"type":"Point"}
}
