{
  "type": "Feature",
  "properties": {
    "iso:country": "GB",
    "wof:name": "BN27 4JP",
    "wof:placetype": "postalcode"
  },
  "geometry": {"coordinates":[0.322235,50.888673],"type":"Point"}
}
