{
  "type": "Feature",
  "properties": {
    "iso:country":"GB",
    "wof:name":"M21 9NH",
    "wof:placetype":"postalcode"
},
  "geometry": {"coordinates":[-2.28245924357511,53.4440544419539],"type":"Point"}
}