{
  "type": "Feature",
  "properties": {
    "date:inception_lower": "1994-05-01",
    "date:inception_upper": "1994-05-01",
    "iso:country": "GB",
    "wof:name": "M21 9NH",
    "wof:placetype": "postalcode"
  },
  "geometry": {"coordinates":[-2.282459,53.444054],"type":"Point"}
}
