{
  "type": "Feature",
  "properties": {
    "date:inception_lower": "1980-01-01",
    "date:inception_upper": "1980-01-01",
    "iso:country": "GB",
    "wof:name": "CM18 6TE",
    "wof:placetype": "postalcode"
  },
  "geometry": {"coordinates":[0.097853,51.756944],"type":"Point"}
}
