{
  "type": "Feature",
  "properties": {
    "iso:country":"GB",
    "wof:name":"CM18 6TE",
    "wof:placetype":"postalcode"
},
  "geometry": {"coordinates":[0.09778454094793,51.75699350068772],"type":"Point"}
}