{
  "type": "Feature",
  "properties": {
    "iso:country": "GB",
    "wof:name": "CM18 6TE",
    "wof:placetype": "postalcode"
  },
  "geometry": {"coordinates":[0.097785,51.756993],"type":"Point"}
}
