{
  "type": "Feature",
  "properties": {
    "iso:country":"GB",
    "wof:name":"G20 7SW",
    "wof:placetype":"postalcode"
},
  "geometry": {"coordinates":[-4.26982658054442,55.88341901202303],"type":"Point"}
}