{
  "type": "Feature",
  "properties": {
    "date:inception_lower": "2015-10-01",
    "date:inception_upper": "2015-10-01",
    "iso:country": "GB",
    "wof:name": "G20 7SW",
    "wof:placetype": "postalcode"
  },
  "geometry": {"coordinates":[-4.269827,55.883419],"type":"Point"}
}
