{
  "type": "Feature",
  "properties": {
    "iso:country":"GB",
    "wof:name":"NR12 0QN",
    "wof:placetype":"postalcode"
},
  "geometry": {"coordinates":[1.5602504368822,52.81163677889202],"type":"Point"}
}