{
  "type": "Feature",
  "properties": {
    "iso:country": "GB",
    "wof:name": "NR12 0QN",
    "wof:placetype": "postalcode"
  },
  "geometry": {"coordinates":[1.560285,52.811646],"type":"Point"}
}
