{
  "type": "Feature",
  "properties": {
    "iso:country":"GB",
    "wof:name":"M28 3PY",
    "wof:placetype":"postalcode"
},
  "geometry": {"coordinates":[-2.40487961906817,53.52682759838175],"type":"Point"}
}