{
  "type": "Feature",
  "properties": {
    "iso:country":"GB",
    "wof:name":"CT7 0HH",
    "wof:placetype":"postalcode"
},
  "geometry": {"coordinates":[1.34261631445505,51.35718897009536],"type":"Point"}
}