{
  "type": "Feature",
  "properties": {
    "iso:country": "GB",
    "wof:name": "B66 2BQ",
    "wof:placetype": "postalcode"
  },
  "geometry": {"coordinates":[-1.948724,52.493811],"type":"Point"}
}
