{
  "type": "Feature",
  "properties": {
    "iso:country":"GB",
    "wof:name":"TN6 2DJ",
    "wof:placetype":"postalcode"
},
  "geometry": {"coordinates":[0.18073378526914,51.05331503002257],"type":"Point"}
}