{
  "type": "Feature",
  "properties": {
    "iso:country":"GB",
    "wof:name":"EX8 1HU",
    "wof:placetype":"postalcode"
},
  "geometry": {"coordinates":[-3.41008191466114,50.61932716484077],"type":"Point"}
}