{
  "type": "Feature",
  "properties": {
    "iso:country":"GB",
    "wof:name":"WR2 4DS",
    "wof:placetype":"postalcode"
},
  "geometry": {"coordinates":[-2.24054160561331,52.17611778144258],"type":"Point"}
}