{
  "type": "Feature",
  "properties": {
    "iso:country": "GB",
    "wof:name": "WR2 4DS",
    "wof:placetype": "postalcode"
  },
  "geometry": {"coordinates":[-2.240542,52.176118],"type":"Point"}
}
