{
  "type": "Feature",
  "properties": {
    "iso:country":"GB",
    "wof:name":"PL25 4EL",
    "wof:placetype":"postalcode"
},
  "geometry": {"coordinates":[-4.78035412992462,50.3573976989747],"type":"Point"}
}