{
  "type": "Feature",
  "properties": {
    "iso:country":"GB",
    "wof:name":"DT3 5EN",
    "wof:placetype":"postalcode"
},
  "geometry": {"coordinates":[-2.46312687795306,50.62972972888635],"type":"Point"}
}