{
  "type": "Feature",
  "properties": {
    "date:inception_lower": "1980-01-01",
    "date:inception_upper": "1980-01-01",
    "iso:country": "GB",
    "wof:name": "LN4 3DT",
    "wof:placetype": "postalcode"
  },
  "geometry": {"coordinates":[-0.405597,53.139257],"type":"Point"}
}
