{
  "type": "Feature",
  "properties": {
    "iso:country":"GB",
    "wof:name":"LN4 3DT",
    "wof:placetype":"postalcode"
},
  "geometry": {"coordinates":[-0.40559678026928,53.13925726206302],"type":"Point"}
}