{
  "type": "Feature",
  "properties": {
    "iso:country":"GB",
    "wof:name":"BA3 5HF",
    "wof:placetype":"postalcode"
},
  "geometry": {"coordinates":[-2.48267777998603,51.22173808912951],"type":"Point"}
}