{
  "type": "Feature",
  "properties": {
    "date:inception_lower":"2000-12-01",
    "date:inception_upper":"2000-12-31",
    "iso:country":"GB",
    "wof:name":"BA3 5HF",
    "wof:placetype":"postalcode"
},
  "geometry": {"coordinates":[-2.482678,51.221738],"type":"Point"}
}