{
  "type": "Feature",
  "properties": {
    "iso:country": "GB",
    "wof:name": "BA3 5HF",
    "wof:placetype": "postalcode"
  },
  "geometry": {"coordinates":[-2.482678,51.221738],"type":"Point"}
}
