{
  "type": "Feature",
  "properties": {
    "iso:country": "GB",
    "wof:name": "BR6 6EY",
    "wof:placetype": "postalcode"
  },
  "geometry": {"coordinates":[0.105324,51.35635],"type":"Point"}
}
