{
  "type": "Feature",
  "properties": {
    "iso:country":"GB",
    "wof:name":"BR6 6EY",
    "wof:placetype":"postalcode"
},
  "geometry": {"coordinates":[0.10523760278467,51.35631418656368],"type":"Point"}
}