{
  "type": "Feature",
  "properties": {
    "iso:country": "GB",
    "wof:name": "TN24 0EN",
    "wof:placetype": "postalcode"
  },
  "geometry": {"coordinates":[0.898419,51.138478],"type":"Point"}
}
