{
  "type": "Feature",
  "properties": {
    "iso:country":"GB",
    "wof:name":"TN24 0EN",
    "wof:placetype":"postalcode"
},
  "geometry": {"coordinates":[0.89841899290113,51.13847805724063],"type":"Point"}
}