{
  "type": "Feature",
  "properties": {
    "iso:country":"GB",
    "wof:name":"M34 3EP",
    "wof:placetype":"postalcode"
},
  "geometry": {"coordinates":[-2.11601063715599,53.46175206392862],"type":"Point"}
}