{
  "type": "Feature",
  "properties": {
    "iso:country":"GB",
    "wof:name":"UB6 0NF",
    "wof:placetype":"postalcode"
},
  "geometry": {"coordinates":[-0.32436128804483,51.553409075388],"type":"Point"}
}