{
  "type": "Feature",
  "properties": {
    "iso:country":"GB",
    "wof:name":"HU19 2HD",
    "wof:placetype":"postalcode"
},
  "geometry": {"coordinates":[0.03089640807063,53.72980919974974],"type":"Point"}
}