{
  "type": "Feature",
  "properties": {
    "date:inception_lower": "1990-02-01",
    "date:inception_upper": "1990-02-01",
    "iso:country": "GB",
    "wof:name": "HU19 2HD",
    "wof:placetype": "postalcode"
  },
  "geometry": {"coordinates":[0.030896,53.729809],"type":"Point"}
}
