{
  "type": "Feature",
  "properties": {
    "iso:country": "GB",
    "wof:name": "SY15 6HF",
    "wof:placetype": "postalcode"
  },
  "geometry": {"coordinates":[-3.174934,52.573969],"type":"Point"}
}
