{
  "type": "Feature",
  "properties": {
    "date:inception_lower": "1980-01-01",
    "date:inception_upper": "1980-01-01",
    "iso:country": "GB",
    "wof:name": "NP4 6JN",
    "wof:placetype": "postalcode"
  },
  "geometry": {"coordinates":[-3.041166,51.702198],"type":"Point"}
}
