{
  "type": "Feature",
  "properties": {
    "iso:country":"GB",
    "wof:name":"NP4 6JN",
    "wof:placetype":"postalcode"
},
  "geometry": {"coordinates":[-3.04113069667339,51.70218668094081],"type":"Point"}
}