{
  "type": "Feature",
  "properties": {
    "date:inception_lower": "1980-01-01",
    "date:inception_upper": "1980-01-01",
    "iso:country": "GB",
    "wof:name": "PL25 5LJ",
    "wof:placetype": "postalcode"
  },
  "geometry": {"coordinates":[-4.793992,50.337758],"type":"Point"}
}
