{
  "type": "Feature",
  "properties": {
    "date:inception_lower": "2012-11-01",
    "date:inception_upper": "2012-11-01",
    "iso:country": "GB",
    "wof:name": "LL17 0LP",
    "wof:placetype": "postalcode"
  },
  "geometry": {"coordinates":[-3.473291,53.255437],"type":"Point"}
}
