{
  "type": "Feature",
  "properties": {
    "iso:country":"GB",
    "wof:name":"LL17 0LP",
    "wof:placetype":"postalcode"
},
  "geometry": {"coordinates":[-3.47293834653581,53.25480450637024],"type":"Point"}
}