{
  "type": "Feature",
  "properties": {
    "iso:country": "GB",
    "wof:name": "HP27 9JY",
    "wof:placetype": "postalcode"
  },
  "geometry": {"coordinates":[-0.827738,51.730826],"type":"Point"}
}
