{
  "type": "Feature",
  "properties": {
    "iso:country":"GB",
    "wof:name":"HP27 9JY",
    "wof:placetype":"postalcode"
},
  "geometry": {"coordinates":[-0.82773802415855,51.73082638125747],"type":"Point"}
}