{
  "type": "Feature",
  "properties": {
    "iso:country":"GB",
    "wof:name":"WA4 6TL",
    "wof:placetype":"postalcode"
},
  "geometry": {"coordinates":[-2.61424481955963,53.36428325791924],"type":"Point"}
}