{
  "type": "Feature",
  "properties": {
    "date:inception_lower": "1998-06-01",
    "date:inception_upper": "1998-06-01",
    "iso:country": "GB",
    "wof:name": "SL5 7SH",
    "wof:placetype": "postalcode"
  },
  "geometry": {"coordinates":[-0.63817,51.412699],"type":"Point"}
}
