{
  "type": "Feature",
  "properties": {
    "iso:country":"GB",
    "wof:name":"SL5 7SH",
    "wof:placetype":"postalcode"
},
  "geometry": {"coordinates":[-0.63820230823482,51.41269879190639],"type":"Point"}
}