{
  "type": "Feature",
  "properties": {
    "date:inception_lower":"2008-10-01",
    "date:inception_upper":"2008-10-31",
    "iso:country":"GB",
    "wof:name":"NW10 3SQ",
    "wof:placetype":"postalcode"
},
  "geometry": {"coordinates":[-0.232756,51.539152],"type":"Point"}
}