{
  "type": "Feature",
  "properties": {
    "iso:country":"GB",
    "wof:name":"KA21 6BH",
    "wof:placetype":"postalcode"
},
  "geometry": {"coordinates":[-4.78972585540672,55.64551487329209],"type":"Point"}
}