{
  "type": "Feature",
  "properties": {
    "iso:country":"GB",
    "wof:name":"SK4 1AW",
    "wof:placetype":"postalcode"
},
  "geometry": {"coordinates":[-2.16454765030754,53.4095076666258],"type":"Point"}
}