{
  "type": "Feature",
  "properties": {
    "iso:country": "GB",
    "wof:name": "SK4 1AW",
    "wof:placetype": "postalcode"
  },
  "geometry": {"coordinates":[-2.164548,53.409508],"type":"Point"}
}
