{
  "type": "Feature",
  "properties": {
    "date:inception_lower":"1980-01-01",
    "date:inception_upper":"1980-01-31",
    "iso:country":"GB",
    "wof:name":"BL8 1HA",
    "wof:placetype":"postalcode"
},
  "geometry": {"coordinates":[-2.310735,53.609083],"type":"Point"}
}