{
  "type": "Feature",
  "properties": {
    "iso:country": "GB",
    "wof:name": "BL8 1HA",
    "wof:placetype": "postalcode"
  },
  "geometry": {"coordinates":[-2.310735,53.609083],"type":"Point"}
}
