{
  "type": "Feature",
  "properties": {
    "iso:country":"GB",
    "wof:name":"BL8 1HA",
    "wof:placetype":"postalcode"
},
  "geometry": {"coordinates":[-2.31073530589363,53.60908318568506],"type":"Point"}
}