{
  "type": "Feature",
  "properties": {
    "iso:country": "GB",
    "wof:name": "CV12 8HS",
    "wof:placetype": "postalcode"
  },
  "geometry": {"coordinates":[-1.471624,52.479376],"type":"Point"}
}
