{
  "type": "Feature",
  "properties": {
    "iso:country":"GB",
    "wof:name":"CV12 8HS",
    "wof:placetype":"postalcode"
},
  "geometry": {"coordinates":[-1.47155856736033,52.47933170247961],"type":"Point"}
}