{
  "type": "Feature",
  "properties": {
    "iso:country":"GB",
    "wof:name":"TF12 5JP",
    "wof:placetype":"postalcode"
},
  "geometry": {"coordinates":[-2.48389444236151,52.58587125566345],"type":"Point"}
}