{
  "type": "Feature",
  "properties": {
    "iso:country":"GB",
    "wof:name":"GU2 4HA",
    "wof:placetype":"postalcode"
},
  "geometry": {"coordinates":[-0.58624269298332,51.2289636647842],"type":"Point"}
}