{
  "type": "Feature",
  "properties": {
    "date:inception_lower":"1990-07-01",
    "date:inception_upper":"1990-07-31",
    "iso:country":"GB",
    "wof:name":"LN12 2SS",
    "wof:placetype":"postalcode"
},
  "geometry": {"coordinates":[0.283895,53.308689],"type":"Point"}
}