{
  "type": "Feature",
  "properties": {
    "iso:country":"GB",
    "wof:name":"S75 2JY",
    "wof:placetype":"postalcode"
},
  "geometry": {"coordinates":[-1.51334246630407,53.55332822297515],"type":"Point"}
}