{
  "type": "Feature",
  "properties": {
    "iso:country":"GB",
    "wof:name":"CA16 6SG",
    "wof:placetype":"postalcode"
},
  "geometry": {"coordinates":[-2.48910926285599,54.58321992473476],"type":"Point"}
}