{
  "type": "Feature",
  "properties": {
    "iso:country": "GB",
    "wof:name": "CA16 6SG",
    "wof:placetype": "postalcode"
  },
  "geometry": {"coordinates":[-2.489109,54.58322],"type":"Point"}
}
