{
  "type": "Feature",
  "properties": {
    "iso:country":"GB",
    "wof:name":"HG2 9NS",
    "wof:placetype":"postalcode"
},
  "geometry": {"coordinates":[-1.54269514921018,53.97432040218613],"type":"Point"}
}