{
  "type": "Feature",
  "properties": {
    "iso:country":"GB",
    "wof:name":"GU35 8LT",
    "wof:placetype":"postalcode"
},
  "geometry": {"coordinates":[-0.82083875150114,51.11625285278325],"type":"Point"}
}