{
  "type": "Feature",
  "properties": {
    "iso:country":"GB",
    "wof:name":"FK1 2JQ",
    "wof:placetype":"postalcode"
},
  "geometry": {"coordinates":[-3.78193527819251,55.94477585535279],"type":"Point"}
}