{
  "type": "Feature",
  "properties": {
    "iso:country": "GB",
    "wof:name": "TD5 8RZ",
    "wof:placetype": "postalcode"
  },
  "geometry": {"coordinates":[-2.286918,55.543611],"type":"Point"}
}
