{
  "type": "Feature",
  "properties": {
    "iso:country":"GB",
    "wof:name":"E9 6DB",
    "wof:placetype":"postalcode"
},
  "geometry": {"coordinates":[-0.04326958847061,51.55101825057692],"type":"Point"}
}