{
  "type": "Feature",
  "properties": {
    "iso:country":"GB",
    "wof:name":"YO25 9AU",
    "wof:placetype":"postalcode"
},
  "geometry": {"coordinates":[-0.45997948965792,53.91833949352066],"type":"Point"}
}