{
  "type": "Feature",
  "properties": {
    "iso:country": "GB",
    "wof:name": "PE7 3ZE",
    "wof:placetype": "postalcode"
  },
  "geometry": {"coordinates":[-0.236014,52.525157],"type":"Point"}
}
