{
  "type": "Feature",
  "properties": {
    "date:inception_lower": "2019-04-01",
    "date:inception_upper": "2019-04-01",
    "iso:country": "GB",
    "wof:name": "PE7 3ZE",
    "wof:placetype": "postalcode"
  },
  "geometry": {"coordinates":[-0.236108,52.525014],"type":"Point"}
}
