{
  "type": "Feature",
  "properties": {
    "iso:country": "GB",
    "wof:name": "LU5 6JH",
    "wof:placetype": "postalcode"
  },
  "geometry": {"coordinates":[-0.542602,51.913646],"type":"Point"}
}
