{
  "type": "Feature",
  "properties": {
    "iso:country":"GB",
    "wof:name":"NE3 3JX",
    "wof:placetype":"postalcode"
},
  "geometry": {"coordinates":[-1.65138109907414,55.00779049108827],"type":"Point"}
}