{
  "type": "Feature",
  "properties": {
    "date:inception_lower": "1999-06-01",
    "date:inception_upper": "1999-06-01",
    "iso:country": "GB",
    "wof:name": "CH63 5JN",
    "wof:placetype": "postalcode"
  },
  "geometry": {"coordinates":[-3.020344,53.358311],"type":"Point"}
}
