{
  "type": "Feature",
  "properties": {
    "iso:country":"GB",
    "wof:name":"CH63 5JN",
    "wof:placetype":"postalcode"
},
  "geometry": {"coordinates":[-3.02034371698024,53.35831055573873],"type":"Point"}
}