{
  "type": "Feature",
  "properties": {
    "iso:country":"GB",
    "wof:name":"LE12 6NG",
    "wof:placetype":"postalcode"
},
  "geometry": {"coordinates":[-1.17517076663323,52.82926967971494],"type":"Point"}
}