{
  "type": "Feature",
  "properties": {
    "iso:country":"GB",
    "wof:name":"TR3 6BX",
    "wof:placetype":"postalcode"
},
  "geometry": {"coordinates":[-5.11262637872069,50.26386269267929],"type":"Point"}
}