{
  "type": "Feature",
  "properties": {
    "iso:country": "GB",
    "wof:name": "TR3 6BX",
    "wof:placetype": "postalcode"
  },
  "geometry": {"coordinates":[-5.112626,50.263863],"type":"Point"}
}
