{
  "type": "Feature",
  "properties": {
    "iso:country":"GB",
    "wof:name":"SM4 4RJ",
    "wof:placetype":"postalcode"
},
  "geometry": {"coordinates":[-0.21491752930277,51.38457978708086],"type":"Point"}
}