{
  "type": "Feature",
  "properties": {
    "iso:country":"GB",
    "wof:name":"ME10 1GE",
    "wof:placetype":"postalcode"
},
  "geometry": {"coordinates":[0.70836567853678,51.34398094113259],"type":"Point"}
}