{
  "type": "Feature",
  "properties": {
    "iso:country": "GB",
    "wof:name": "ME10 1GE",
    "wof:placetype": "postalcode"
  },
  "geometry": {"coordinates":[0.708366,51.343981],"type":"Point"}
}
