{
  "type": "Feature",
  "properties": {
    "date:inception_lower": "2003-03-01",
    "date:inception_upper": "2003-03-01",
    "iso:country": "GB",
    "wof:name": "ME10 1GE",
    "wof:placetype": "postalcode"
  },
  "geometry": {"coordinates":[0.708366,51.343981],"type":"Point"}
}
