{
  "type": "Feature",
  "properties": {
    "date:inception_lower": "1980-01-01",
    "date:inception_upper": "1980-01-01",
    "iso:country": "GB",
    "wof:name": "TS19 9HU",
    "wof:placetype": "postalcode"
  },
  "geometry": {"coordinates":[-1.340831,54.592706],"type":"Point"}
}
