{
  "type": "Feature",
  "properties": {
    "iso:country":"GB",
    "wof:name":"NG5 4BX",
    "wof:placetype":"postalcode"
},
  "geometry": {"coordinates":[-1.14489587559674,52.9801613961813],"type":"Point"}
}