{
  "type": "Feature",
  "properties": {
    "date:inception_lower": "2005-07-01",
    "date:inception_upper": "2005-07-01",
    "iso:country": "GB",
    "wof:name": "NG5 4BX",
    "wof:placetype": "postalcode"
  },
  "geometry": {"coordinates":[-1.144955,52.98018],"type":"Point"}
}
