{
  "type": "Feature",
  "properties": {
    "iso:country":"GB",
    "wof:name":"G41 3PG",
    "wof:placetype":"postalcode"
},
  "geometry": {"coordinates":[-4.28535386879767,55.82684268640517],"type":"Point"}
}