{
  "type": "Feature",
  "properties": {
    "iso:country":"GB",
    "wof:name":"LL37 2QH",
    "wof:placetype":"postalcode"
},
  "geometry": {"coordinates":[-4.09235032438242,52.65466709857516],"type":"Point"}
}