{
  "type": "Feature",
  "properties": {
    "iso:country": "GB",
    "wof:name": "LL37 2QH",
    "wof:placetype": "postalcode"
  },
  "geometry": {"coordinates":[-4.09235,52.654667],"type":"Point"}
}
