{
  "type": "Feature",
  "properties": {
    "iso:country":"GB",
    "wof:name":"M15 4GY",
    "wof:placetype":"postalcode"
},
  "geometry": {"coordinates":[-2.26449039259128,53.4718520917546],"type":"Point"}
}