{
  "type": "Feature",
  "properties": {
    "iso:country":"GB",
    "wof:name":"GU4 7QY",
    "wof:placetype":"postalcode"
},
  "geometry": {"coordinates":[-0.55539238895475,51.28109392719927],"type":"Point"}
}