{
  "type": "Feature",
  "properties": {
    "date:inception_lower": "1992-01-01",
    "date:inception_upper": "1992-01-01",
    "iso:country": "GB",
    "wof:name": "GU4 7QY",
    "wof:placetype": "postalcode"
  },
  "geometry": {"coordinates":[-0.556365,51.280042],"type":"Point"}
}
