{
  "type": "Feature",
  "properties": {
    "iso:country": "GB",
    "wof:name": "NP19 9DG",
    "wof:placetype": "postalcode"
  },
  "geometry": {"coordinates":[-2.958779,51.588561],"type":"Point"}
}
