{
  "type": "Feature",
  "properties": {
    "iso:country":"GB",
    "wof:name":"L7 8TF",
    "wof:placetype":"postalcode"
},
  "geometry": {"coordinates":[-2.95744442954527,53.40781260771671],"type":"Point"}
}