{
  "type": "Feature",
  "properties": {
    "iso:country": "GB",
    "wof:name": "WS5 4JL",
    "wof:placetype": "postalcode"
  },
  "geometry": {"coordinates":[-1.964213,52.5627],"type":"Point"}
}
