{
  "type": "Feature",
  "properties": {
    "date:inception_lower":"2013-11-01",
    "date:inception_upper":"2013-11-30",
    "iso:country":"GB",
    "wof:name":"TS10 4FN",
    "wof:placetype":"postalcode"
},
  "geometry": {"coordinates":[-1.075923,54.604266],"type":"Point"}
}