{
  "type": "Feature",
  "properties": {
    "iso:country":"GB",
    "wof:name":"TS10 4FN",
    "wof:placetype":"postalcode"
},
  "geometry": {"coordinates":[-1.07592349193633,54.60426592372198],"type":"Point"}
}