{
  "type": "Feature",
  "properties": {
    "iso:country":"GB",
    "wof:name":"OX4 4YR",
    "wof:placetype":"postalcode"
},
  "geometry": {"coordinates":[-1.22508800836023,51.70246799166003],"type":"Point"}
}