{
  "type": "Feature",
  "properties": {
    "iso:country":"GB",
    "wof:name":"KA20 4LB",
    "wof:placetype":"postalcode"
},
  "geometry": {"coordinates":[-4.74547584502125,55.65643744169076],"type":"Point"}
}