{
  "type": "Feature",
  "properties": {
    "iso:country":"GB",
    "wof:name":"SN3 4QS",
    "wof:placetype":"postalcode"
},
  "geometry": {"coordinates":[-1.74631301536287,51.59148548286133],"type":"Point"}
}