{
  "type": "Feature",
  "properties": {
    "iso:country":"GB",
    "wof:name":"NW3 3QA",
    "wof:placetype":"postalcode"
},
  "geometry": {"coordinates":[-0.15633060930416,51.54410876271046],"type":"Point"}
}