{
  "type": "Feature",
  "properties": {
    "iso:country":"GB",
    "wof:name":"L36 3XA",
    "wof:placetype":"postalcode"
},
  "geometry": {"coordinates":[-2.84791685435434,53.42297794979669],"type":"Point"}
}