{
  "type": "Feature",
  "properties": {
    "date:inception_lower":"1980-01-01",
    "date:inception_upper":"1980-01-31",
    "iso:country":"GB",
    "wof:name":"L36 3XA",
    "wof:placetype":"postalcode"
},
  "geometry": {"coordinates":[-2.847917,53.422978],"type":"Point"}
}