{
  "type": "Feature",
  "properties": {
    "date:inception_lower": "1980-01-01",
    "date:inception_upper": "1980-01-01",
    "iso:country": "GB",
    "wof:name": "LA15 8NG",
    "wof:placetype": "postalcode"
  },
  "geometry": {"coordinates":[-3.184235,54.148692],"type":"Point"}
}
