{
  "type": "Feature",
  "properties": {
    "iso:country":"GB",
    "wof:name":"LA15 8NG",
    "wof:placetype":"postalcode"
},
  "geometry": {"coordinates":[-3.18423459544427,54.14869215829651],"type":"Point"}
}