{
  "type": "Feature",
  "properties": {
    "iso:country":"GB",
    "wof:name":"CR8 3HG",
    "wof:placetype":"postalcode"
},
  "geometry": {"coordinates":[-0.13328089597725,51.33633857449679],"type":"Point"}
}