{
  "type": "Feature",
  "properties": {
    "iso:country":"GB",
    "wof:name":"W1D 3RZ",
    "wof:placetype":"postalcode"
},
  "geometry": {"coordinates":[-0.13250049103029,51.51393971591996],"type":"Point"}
}