{
  "type": "Feature",
  "properties": {
    "date:inception_lower": "1980-01-01",
    "date:inception_upper": "1980-01-01",
    "iso:country": "GB",
    "wof:name": "SA70 7SH",
    "wof:placetype": "postalcode"
  },
  "geometry": {"coordinates":[-4.786366,51.640869],"type":"Point"}
}
