{
  "type": "Feature",
  "properties": {
    "iso:country":"GB",
    "wof:name":"SA70 7SH",
    "wof:placetype":"postalcode"
},
  "geometry": {"coordinates":[-4.78636577542479,51.64086900695371],"type":"Point"}
}