{
  "type": "Feature",
  "properties": {
    "iso:country":"GB",
    "wof:name":"SP4 0JU",
    "wof:placetype":"postalcode"
},
  "geometry": {"coordinates":[-1.7278770836101,51.12603362770366],"type":"Point"}
}