{
  "type": "Feature",
  "properties": {
    "iso:country":"GB",
    "wof:name":"LL12 0DD",
    "wof:placetype":"postalcode"
},
  "geometry": {"coordinates":[-2.93801462558183,53.11768162717636],"type":"Point"}
}