{
  "type": "Feature",
  "properties": {
    "date:inception_lower": "1995-12-01",
    "date:inception_upper": "1995-12-01",
    "iso:country": "GB",
    "wof:name": "LL12 0DD",
    "wof:placetype": "postalcode"
  },
  "geometry": {"coordinates":[-2.938015,53.117682],"type":"Point"}
}
