{
  "type": "Feature",
  "properties": {
    "iso:country": "GB",
    "wof:name": "NW2 9SW",
    "wof:placetype": "postalcode"
  },
  "geometry": {"coordinates":[-0.213473,51.562153],"type":"Point"}
}
