{
  "type": "Feature",
  "properties": {
    "iso:country":"GB",
    "wof:name":"HA5 4TN",
    "wof:placetype":"postalcode"
},
  "geometry": {"coordinates":[-0.38542641168017,51.60453133924381],"type":"Point"}
}