{
  "type": "Feature",
  "properties": {
    "iso:country":"GB",
    "wof:name":"GL20 5BD",
    "wof:placetype":"postalcode"
},
  "geometry": {"coordinates":[-2.15315277845015,51.99785494792453],"type":"Point"}
}