{
  "type": "Feature",
  "properties": {
    "date:inception_lower": "2017-07-01",
    "date:inception_upper": "2017-07-01",
    "iso:country": "GB",
    "wof:name": "NR13 5FT",
    "wof:placetype": "postalcode"
  },
  "geometry": {"coordinates":[1.389028,52.61236],"type":"Point"}
}
