{
  "type": "Feature",
  "properties": {
    "iso:country":"GB",
    "wof:name":"BS13 9AX",
    "wof:placetype":"postalcode"
},
  "geometry": {"coordinates":[-2.62023564752326,51.40839016456775],"type":"Point"}
}