{
  "type": "Feature",
  "properties": {
    "date:inception_lower": "1997-12-01",
    "date:inception_upper": "1997-12-01",
    "iso:country": "GB",
    "wof:name": "LE7 1JA",
    "wof:placetype": "postalcode"
  },
  "geometry": {"coordinates":[-1.092135,52.689933],"type":"Point"}
}
