{
  "type": "Feature",
  "properties": {
    "date:inception_lower": "2023-10-01",
    "date:inception_upper": "2023-10-01",
    "iso:country": "GB",
    "wof:name": "TN12 6GZ",
    "wof:placetype": "postalcode"
  },
  "geometry": {"coordinates":[0.394039,51.171965],"type":"Point"}
}
