{
  "type": "Feature",
  "properties": {
    "iso:country": "GB",
    "wof:name": "MK41 0PZ",
    "wof:placetype": "postalcode"
  },
  "geometry": {"coordinates":[-0.420792,52.151428],"type":"Point"}
}
