{
  "type": "Feature",
  "properties": {
    "date:inception_lower":"1981-09-01",
    "date:inception_upper":"1981-09-30",
    "iso:country":"GB",
    "wof:name":"TN29 0XJ",
    "wof:placetype":"postalcode"
},
  "geometry": {"coordinates":[0.97353,51.006798],"type":"Point"}
}