{
  "type": "Feature",
  "properties": {
    "iso:country": "GB",
    "wof:name": "TN29 0XJ",
    "wof:placetype": "postalcode"
  },
  "geometry": {"coordinates":[0.97353,51.006798],"type":"Point"}
}
