{
  "type": "Feature",
  "properties": {
    "iso:country": "GB",
    "wof:name": "TA21 8ED",
    "wof:placetype": "postalcode"
  },
  "geometry": {"coordinates":[-3.218011,50.972849],"type":"Point"}
}
