{
  "type": "Feature",
  "properties": {
    "iso:country": "GB",
    "wof:name": "EX20 4DE",
    "wof:placetype": "postalcode"
  },
  "geometry": {"coordinates":[-4.229136,50.667617],"type":"Point"}
}
