{
  "type": "Feature",
  "properties": {
    "iso:country":"GB",
    "wof:name":"LL14 3UN",
    "wof:placetype":"postalcode"
},
  "geometry": {"coordinates":[-3.0661413397168,52.97997112683048],"type":"Point"}
}