{
  "type": "Feature",
  "properties": {
    "iso:country":"GB",
    "wof:name":"ML6 0JA",
    "wof:placetype":"postalcode"
},
  "geometry": {"coordinates":[-3.98744840831493,55.86956585647377],"type":"Point"}
}