{
  "type": "Feature",
  "properties": {
    "iso:country": "GB",
    "wof:name": "ML6 0JA",
    "wof:placetype": "postalcode"
  },
  "geometry": {"coordinates":[-3.987448,55.869566],"type":"Point"}
}
