{
  "type": "Feature",
  "properties": {
    "iso:country": "GB",
    "wof:name": "BB2 3JT",
    "wof:placetype": "postalcode"
  },
  "geometry": {"coordinates":[-2.4746,53.730102],"type":"Point"}
}
