{
  "type": "Feature",
  "properties": {
    "iso:country":"GB",
    "wof:name":"BB2 3JT",
    "wof:placetype":"postalcode"
},
  "geometry": {"coordinates":[-2.47460028136981,53.73010217018327],"type":"Point"}
}