{
  "type": "Feature",
  "properties": {
    "date:inception_lower": "1980-01-01",
    "date:inception_upper": "1980-01-01",
    "iso:country": "GB",
    "wof:name": "AL10 0RJ",
    "wof:placetype": "postalcode"
  },
  "geometry": {"coordinates":[-0.226044,51.770849],"type":"Point"}
}
