{
  "type": "Feature",
  "properties": {
    "iso:country":"GB",
    "wof:name":"EH14 7HL",
    "wof:placetype":"postalcode"
},
  "geometry": {"coordinates":[-3.34015998266203,55.88365516245804],"type":"Point"}
}