{
  "type": "Feature",
  "properties": {
    "iso:country": "GB",
    "wof:name": "EH14 7HL",
    "wof:placetype": "postalcode"
  },
  "geometry": {"coordinates":[-3.34016,55.883655],"type":"Point"}
}
