{
  "type": "Feature",
  "properties": {
    "date:inception_lower": "1987-06-01",
    "date:inception_upper": "1987-06-01",
    "iso:country": "GB",
    "wof:name": "EH14 7HL",
    "wof:placetype": "postalcode"
  },
  "geometry": {"coordinates":[-3.34016,55.883655],"type":"Point"}
}
