{
  "type": "Feature",
  "properties": {
    "iso:country":"GB",
    "wof:name":"N3 3PR",
    "wof:placetype":"postalcode"
},
  "geometry": {"coordinates":[-0.20867953607408,51.59261517307062],"type":"Point"}
}