{
  "type": "Feature",
  "properties": {
    "date:inception_lower":"1980-01-01",
    "date:inception_upper":"1980-01-31",
    "iso:country":"GB",
    "wof:name":"HR3 6DE",
    "wof:placetype":"postalcode"
},
  "geometry": {"coordinates":[-3.011908,52.104779],"type":"Point"}
}