{
  "type": "Feature",
  "properties": {
    "iso:country":"GB",
    "wof:name":"HR3 6DE",
    "wof:placetype":"postalcode"
},
  "geometry": {"coordinates":[-3.01190778480277,52.10477920749208],"type":"Point"}
}