{
  "type": "Feature",
  "properties": {
    "date:inception_lower": "1985-10-01",
    "date:inception_upper": "1985-10-01",
    "iso:country": "GB",
    "wof:name": "SP10 3NL",
    "wof:placetype": "postalcode"
  },
  "geometry": {"coordinates":[-1.512792,51.210104],"type":"Point"}
}
