{
  "type": "Feature",
  "properties": {
    "iso:country":"GB",
    "wof:name":"YO31 7QJ",
    "wof:placetype":"postalcode"
},
  "geometry": {"coordinates":[-1.07913192478421,53.96619838755593],"type":"Point"}
}