{
  "type": "Feature",
  "properties": {
    "iso:country":"GB",
    "wof:name":"SO23 9QA",
    "wof:placetype":"postalcode"
},
  "geometry": {"coordinates":[-1.32197828261899,51.0509461321103],"type":"Point"}
}