{
  "type": "Feature",
  "properties": {
    "iso:country":"GB",
    "wof:name":"YO19 4SA",
    "wof:placetype":"postalcode"
},
  "geometry": {"coordinates":[-1.09070446140219,53.90300132081894],"type":"Point"}
}