{
  "type": "Feature",
  "properties": {
    "date:inception_lower": "1998-06-01",
    "date:inception_upper": "1998-06-01",
    "iso:country": "GB",
    "wof:name": "YO19 4SA",
    "wof:placetype": "postalcode"
  },
  "geometry": {"coordinates":[-1.090727,53.903011],"type":"Point"}
}
