{
  "type": "Feature",
  "properties": {
    "iso:country": "GB",
    "wof:name": "CA14 5XD",
    "wof:placetype": "postalcode"
  },
  "geometry": {"coordinates":[-3.539119,54.594794],"type":"Point"}
}
