{
  "type": "Feature",
  "properties": {
    "date:inception_lower":"1980-01-01",
    "date:inception_upper":"1980-01-31",
    "iso:country":"GB",
    "wof:name":"NE16 4AY",
    "wof:placetype":"postalcode"
},
  "geometry": {"coordinates":[-1.680597,54.947564],"type":"Point"}
}