{
  "type": "Feature",
  "properties": {
    "date:inception_lower": "2021-04-01",
    "date:inception_upper": "2021-04-01",
    "iso:country": "GB",
    "wof:name": "ST7 2AJ",
    "wof:placetype": "postalcode"
  },
  "geometry": {"coordinates":[-2.321028,53.09964],"type":"Point"}
}
