{
  "type": "Feature",
  "properties": {
    "date:inception_lower":"1980-01-01",
    "date:inception_upper":"1980-01-31",
    "iso:country":"GB",
    "wof:name":"IV5 7PP",
    "wof:placetype":"postalcode"
},
  "geometry": {"coordinates":[-4.407348,57.461636],"type":"Point"}
}