{
  "type": "Feature",
  "properties": {
    "iso:country": "GB",
    "wof:name": "SO30 3JL",
    "wof:placetype": "postalcode"
  },
  "geometry": {"coordinates":[-1.343885,50.933361],"type":"Point"}
}
