{
  "type": "Feature",
  "properties": {
    "date:inception_lower":"1980-01-01",
    "date:inception_upper":"1980-01-31",
    "iso:country":"GB",
    "wof:name":"ME18 5JH",
    "wof:placetype":"postalcode"
},
  "geometry": {"coordinates":[0.359006,51.249069],"type":"Point"}
}