{
  "type": "Feature",
  "properties": {
    "iso:country":"GB",
    "wof:name":"ME18 5JH",
    "wof:placetype":"postalcode"
},
  "geometry": {"coordinates":[0.35900566369802,51.24906943100505],"type":"Point"}
}