{
  "type": "Feature",
  "properties": {
    "iso:country":"GB",
    "wof:name":"YO31 9JQ",
    "wof:placetype":"postalcode"
},
  "geometry": {"coordinates":[-1.06388173353374,53.98758898604616],"type":"Point"}
}