{
  "type": "Feature",
  "properties": {
    "iso:country":"GB",
    "wof:name":"PA5 8YX",
    "wof:placetype":"postalcode"
},
  "geometry": {"coordinates":[-4.50976857958299,55.84410059297947],"type":"Point"}
}