{
  "type": "Feature",
  "properties": {
    "iso:country":"GB",
    "wof:name":"WA3 5SJ",
    "wof:placetype":"postalcode"
},
  "geometry": {"coordinates":[-2.51698872280801,53.45241960922149],"type":"Point"}
}