{
  "type": "Feature",
  "properties": {
    "date:inception_lower": "1980-01-01",
    "date:inception_upper": "1980-01-01",
    "iso:country": "GB",
    "wof:name": "NE31 1SX",
    "wof:placetype": "postalcode"
  },
  "geometry": {"coordinates":[-1.506397,54.982056],"type":"Point"}
}
