{
  "type": "Feature",
  "properties": {
    "iso:country": "GB",
    "wof:name": "DN14 6TQ",
    "wof:placetype": "postalcode"
  },
  "geometry": {"coordinates":[-0.881543,53.705026],"type":"Point"}
}
