{
  "type": "Feature",
  "properties": {
    "iso:country":"GB",
    "wof:name":"W10 4DT",
    "wof:placetype":"postalcode"
},
  "geometry": {"coordinates":[-0.21121190323542,51.53143381450823],"type":"Point"}
}