{
  "type": "Feature",
  "properties": {
    "iso:country": "GB",
    "wof:name": "W10 4DT",
    "wof:placetype": "postalcode"
  },
  "geometry": {"coordinates":[-0.211212,51.531434],"type":"Point"}
}
