{
  "type": "Feature",
  "properties": {
    "iso:country":"GB",
    "wof:name":"LE7 9JA",
    "wof:placetype":"postalcode"
},
  "geometry": {"coordinates":[-0.98867711345573,52.66089379875805],"type":"Point"}
}