{
  "type": "Feature",
  "properties": {
    "date:inception_lower":"1980-01-01",
    "date:inception_upper":"1980-01-31",
    "iso:country":"GB",
    "wof:name":"LE7 9JA",
    "wof:placetype":"postalcode"
},
  "geometry": {"coordinates":[-0.988677,52.660894],"type":"Point"}
}