{
  "type": "Feature",
  "properties": {
    "iso:country": "GB",
    "wof:name": "LE7 9JA",
    "wof:placetype": "postalcode"
  },
  "geometry": {"coordinates":[-0.988677,52.660894],"type":"Point"}
}
