{
  "type": "Feature",
  "properties": {
    "iso:country":"GB",
    "wof:name":"WF5 9TJ",
    "wof:placetype":"postalcode"
},
  "geometry": {"coordinates":[-1.5479114428657,53.6832729598214],"type":"Point"}
}