{
  "type": "Feature",
  "properties": {
    "date:inception_lower": "2003-05-01",
    "date:inception_upper": "2003-05-01",
    "iso:country": "GB",
    "wof:name": "WF5 9TJ",
    "wof:placetype": "postalcode"
  },
  "geometry": {"coordinates":[-1.548191,53.682859],"type":"Point"}
}
