{
  "type": "Feature",
  "properties": {
    "iso:country":"GB",
    "wof:name":"WF7 5PW",
    "wof:placetype":"postalcode"
},
  "geometry": {"coordinates":[-1.35916351379604,53.66956795873416],"type":"Point"}
}