{
  "type": "Feature",
  "properties": {
    "iso:country": "GB",
    "wof:name": "WF7 5PW",
    "wof:placetype": "postalcode"
  },
  "geometry": {"coordinates":[-1.359163,53.669568],"type":"Point"}
}
