{
  "type": "Feature",
  "properties": {
    "date:inception_lower":"1993-01-01",
    "date:inception_upper":"1993-01-31",
    "iso:country":"GB",
    "wof:name":"CF37 2EE",
    "wof:placetype":"postalcode"
},
  "geometry": {"coordinates":[-3.352784,51.608706],"type":"Point"}
}