{
  "type": "Feature",
  "properties": {
    "iso:country":"GB",
    "wof:name":"EH26 0BA",
    "wof:placetype":"postalcode"
},
  "geometry": {"coordinates":[-3.20674294047503,55.85923785495208],"type":"Point"}
}