{
  "type": "Feature",
  "properties": {
    "date:inception_lower":"2007-01-01",
    "date:inception_upper":"2007-01-31",
    "iso:country":"GB",
    "wof:name":"EH26 0BA",
    "wof:placetype":"postalcode"
},
  "geometry": {"coordinates":[-3.206743,55.859238],"type":"Point"}
}