{
  "type": "Feature",
  "properties": {
    "iso:country": "GB",
    "wof:name": "EH26 0BA",
    "wof:placetype": "postalcode"
  },
  "geometry": {"coordinates":[-3.206743,55.859238],"type":"Point"}
}
