{
  "type": "Feature",
  "properties": {
    "iso:country":"GB",
    "wof:name":"WF8 3NS",
    "wof:placetype":"postalcode"
},
  "geometry": {"coordinates":[-1.29745654163939,53.67672726483419],"type":"Point"}
}