{
  "type": "Feature",
  "properties": {
    "iso:country":"GB",
    "wof:name":"SR2 9BQ",
    "wof:placetype":"postalcode"
},
  "geometry": {"coordinates":[-1.39316826474689,54.88812084963123],"type":"Point"}
}