{
  "type": "Feature",
  "properties": {
    "date:inception_lower":"1990-07-01",
    "date:inception_upper":"1990-07-31",
    "iso:country":"GB",
    "wof:name":"KT21 2NH",
    "wof:placetype":"postalcode"
},
  "geometry": {"coordinates":[-0.309988,51.302871],"type":"Point"}
}