{
  "type": "Feature",
  "properties": {
    "iso:country":"GB",
    "wof:name":"KT21 2NH",
    "wof:placetype":"postalcode"
},
  "geometry": {"coordinates":[-0.30998851022041,51.30287135458118],"type":"Point"}
}