{
  "type": "Feature",
  "properties": {
    "date:inception_lower": "1980-01-01",
    "date:inception_upper": "1980-01-01",
    "iso:country": "GB",
    "wof:name": "WV2 1EN",
    "wof:placetype": "postalcode"
  },
  "geometry": {"coordinates":[-2.117641,52.577246],"type":"Point"}
}
