{
  "type": "Feature",
  "properties": {
    "iso:country": "GB",
    "wof:name": "WV2 1EN",
    "wof:placetype": "postalcode"
  },
  "geometry": {"coordinates":[-2.117641,52.577246],"type":"Point"}
}
