{
  "type": "Feature",
  "properties": {
    "iso:country":"GB",
    "wof:name":"WV2 1EN",
    "wof:placetype":"postalcode"
},
  "geometry": {"coordinates":[-2.11764104980157,52.57724601534651],"type":"Point"}
}