{
  "type": "Feature",
  "properties": {
    "iso:country":"GB",
    "wof:name":"DH9 8HL",
    "wof:placetype":"postalcode"
},
  "geometry": {"coordinates":[-1.73918781683855,54.85829866672438],"type":"Point"}
}