{
  "type": "Feature",
  "properties": {
    "date:inception_lower": "2003-11-01",
    "date:inception_upper": "2003-11-01",
    "iso:country": "GB",
    "wof:name": "DH9 8HL",
    "wof:placetype": "postalcode"
  },
  "geometry": {"coordinates":[-1.739188,54.858299],"type":"Point"}
}
