{
  "type": "Feature",
  "properties": {
    "date:inception_lower": "1990-02-01",
    "date:inception_upper": "1990-02-01",
    "iso:country": "GB",
    "wof:name": "HP3 9QT",
    "wof:placetype": "postalcode"
  },
  "geometry": {"coordinates":[-0.462134,51.7416],"type":"Point"}
}
