{
  "type": "Feature",
  "properties": {
    "iso:country": "GB",
    "wof:name": "HP3 9QT",
    "wof:placetype": "postalcode"
  },
  "geometry": {"coordinates":[-0.462134,51.7416],"type":"Point"}
}
