{
  "type": "Feature",
  "properties": {
    "iso:country":"GB",
    "wof:name":"HP3 9QT",
    "wof:placetype":"postalcode"
},
  "geometry": {"coordinates":[-0.46213423173045,51.74160036393024],"type":"Point"}
}