{
  "type": "Feature",
  "properties": {
    "iso:country":"GB",
    "wof:name":"B63 4EX",
    "wof:placetype":"postalcode"
},
  "geometry": {"coordinates":[-2.06797471474427,52.44702124816582],"type":"Point"}
}