{
  "type": "Feature",
  "properties": {
    "date:inception_lower":"1980-01-01",
    "date:inception_upper":"1980-01-31",
    "iso:country":"GB",
    "wof:name":"SR4 7RZ",
    "wof:placetype":"postalcode"
},
  "geometry": {"coordinates":[-1.413272,54.898239],"type":"Point"}
}