{
  "type": "Feature",
  "properties": {
    "iso:country":"GB",
    "wof:name":"SR4 7RZ",
    "wof:placetype":"postalcode"
},
  "geometry": {"coordinates":[-1.41327159529236,54.89823946677315],"type":"Point"}
}