{
  "type": "Feature",
  "properties": {
    "iso:country":"GB",
    "wof:name":"HP3 9LW",
    "wof:placetype":"postalcode"
},
  "geometry": {"coordinates":[-0.45469119133994,51.74536923016297],"type":"Point"}
}