{
  "type": "Feature",
  "properties": {
    "date:inception_lower": "1993-08-01",
    "date:inception_upper": "1993-08-01",
    "iso:country": "GB",
    "wof:name": "CF35 6PJ",
    "wof:placetype": "postalcode"
  },
  "geometry": {"coordinates":[-3.478778,51.531959],"type":"Point"}
}
