{
  "type": "Feature",
  "properties": {
    "iso:country":"GB",
    "wof:name":"CF35 6PJ",
    "wof:placetype":"postalcode"
},
  "geometry": {"coordinates":[-3.47877757364106,51.53195864601554],"type":"Point"}
}