{
  "type": "Feature",
  "properties": {
    "iso:country": "GB",
    "wof:name": "KA8 0EQ",
    "wof:placetype": "postalcode"
  },
  "geometry": {"coordinates":[-4.622188,55.463361],"type":"Point"}
}
