{
  "type": "Feature",
  "properties": {
    "date:inception_lower": "1980-01-01",
    "date:inception_upper": "1980-01-01",
    "iso:country": "GB",
    "wof:name": "KA8 0EQ",
    "wof:placetype": "postalcode"
  },
  "geometry": {"coordinates":[-4.622188,55.463361],"type":"Point"}
}
