{
  "type": "Feature",
  "properties": {
    "iso:country":"GB",
    "wof:name":"KA8 0EQ",
    "wof:placetype":"postalcode"
},
  "geometry": {"coordinates":[-4.62218836194475,55.46336123178367],"type":"Point"}
}