{
  "type": "Feature",
  "properties": {
    "iso:country":"GB",
    "wof:name":"TQ2 7JA",
    "wof:placetype":"postalcode"
},
  "geometry": {"coordinates":[-3.56477405659503,50.48499312102722],"type":"Point"}
}