{
  "type": "Feature",
  "properties": {
    "iso:country":"GB",
    "wof:name":"NN29 7JP",
    "wof:placetype":"postalcode"
},
  "geometry": {"coordinates":[-0.67092957603274,52.22148606824553],"type":"Point"}
}