{
  "type": "Feature",
  "properties": {
    "iso:country":"GB",
    "wof:name":"OX33 1HG",
    "wof:placetype":"postalcode"
},
  "geometry": {"coordinates":[-1.16669397434939,51.78147973398246],"type":"Point"}
}