{
  "type": "Feature",
  "properties": {
    "iso:country":"GB",
    "wof:name":"DN3 3AE",
    "wof:placetype":"postalcode"
},
  "geometry": {"coordinates":[-1.0540094524541,53.53548618337302],"type":"Point"}
}