{
  "type": "Feature",
  "properties": {
    "iso:country":"GB",
    "wof:name":"TS19 8ND",
    "wof:placetype":"postalcode"
},
  "geometry": {"coordinates":[-1.35893958610244,54.58568535878018],"type":"Point"}
}