{
  "type": "Feature",
  "properties": {
    "iso:country": "GB",
    "wof:name": "TS19 8ND",
    "wof:placetype": "postalcode"
  },
  "geometry": {"coordinates":[-1.35894,54.585685],"type":"Point"}
}
