{
  "type": "Feature",
  "properties": {
    "iso:country": "GB",
    "wof:name": "TS18 2AD",
    "wof:placetype": "postalcode"
  },
  "geometry": {"coordinates":[-1.284928,54.576922],"type":"Point"}
}
