{
  "type": "Feature",
  "properties": {
    "date:inception_lower":"2007-11-01",
    "date:inception_upper":"2007-11-30",
    "iso:country":"GB",
    "wof:name":"TS18 2AD",
    "wof:placetype":"postalcode"
},
  "geometry": {"coordinates":[-1.284928,54.576922],"type":"Point"}
}