{
  "type": "Feature",
  "properties": {
    "iso:country":"GB",
    "wof:name":"BH21 3RP",
    "wof:placetype":"postalcode"
},
  "geometry": {"coordinates":[-2.07095298838908,50.78051961290949],"type":"Point"}
}