{
  "type": "Feature",
  "properties": {
    "iso:country":"GB",
    "wof:name":"SA14 6HD",
    "wof:placetype":"postalcode"
},
  "geometry": {"coordinates":[-4.11537381004931,51.78593916566701],"type":"Point"}
}