{
  "type": "Feature",
  "properties": {
    "date:inception_lower": "2012-04-01",
    "date:inception_upper": "2012-04-01",
    "iso:country": "GB",
    "wof:name": "WR2 5GH",
    "wof:placetype": "postalcode"
  },
  "geometry": {"coordinates":[-2.257888,52.18918],"type":"Point"}
}
