{
  "type": "Feature",
  "properties": {
    "iso:country":"GB",
    "wof:name":"WR2 5GH",
    "wof:placetype":"postalcode"
},
  "geometry": {"coordinates":[-2.25788768812429,52.18918016808523],"type":"Point"}
}