{
  "type": "Feature",
  "properties": {
    "iso:country":"GB",
    "wof:name":"SW19 4PR",
    "wof:placetype":"postalcode"
},
  "geometry": {"coordinates":[-0.21858037096065,51.42236836601202],"type":"Point"}
}