{
  "type": "Feature",
  "properties": {
    "date:inception_lower": "1980-01-01",
    "date:inception_upper": "1980-01-01",
    "iso:country": "GB",
    "wof:name": "L6 8PQ",
    "wof:placetype": "postalcode"
  },
  "geometry": {"coordinates":[-2.937555,53.4166],"type":"Point"}
}
