{
  "type": "Feature",
  "properties": {
    "iso:country":"GB",
    "wof:name":"KW16 3AH",
    "wof:placetype":"postalcode"
},
  "geometry": {"coordinates":[-3.2943785340661,58.97056101732864],"type":"Point"}
}