{
  "type": "Feature",
  "properties": {
    "date:inception_lower":"1983-01-01",
    "date:inception_upper":"1983-01-31",
    "iso:country":"GB",
    "wof:name":"S66 7SG",
    "wof:placetype":"postalcode"
},
  "geometry": {"coordinates":[-1.188359,53.421562],"type":"Point"}
}