{
  "type": "Feature",
  "properties": {
    "iso:country": "GB",
    "wof:name": "S66 7SG",
    "wof:placetype": "postalcode"
  },
  "geometry": {"coordinates":[-1.188359,53.421562],"type":"Point"}
}
