{
  "type": "Feature",
  "properties": {
    "iso:country":"GB",
    "wof:name":"NG5 5LJ",
    "wof:placetype":"postalcode"
},
  "geometry": {"coordinates":[-1.16144863790532,53.00064934130636],"type":"Point"}
}