{
  "type": "Feature",
  "properties": {
    "iso:country": "GB",
    "wof:name": "NG5 5LJ",
    "wof:placetype": "postalcode"
  },
  "geometry": {"coordinates":[-1.161449,53.000649],"type":"Point"}
}
