{
  "type": "Feature",
  "properties": {
    "iso:country": "GB",
    "wof:name": "SG2 9PA",
    "wof:placetype": "postalcode"
  },
  "geometry": {"coordinates":[-0.160822,51.889336],"type":"Point"}
}
