{
  "type": "Feature",
  "properties": {
    "iso:country":"GB",
    "wof:name":"SG2 9PA",
    "wof:placetype":"postalcode"
},
  "geometry": {"coordinates":[-0.16082240141674,51.88933593928366],"type":"Point"}
}