{
  "type": "Feature",
  "properties": {
    "iso:country": "GB",
    "wof:name": "NP7 8LF",
    "wof:placetype": "postalcode"
  },
  "geometry": {"coordinates":[-2.841827,51.906231],"type":"Point"}
}
