{
  "type": "Feature",
  "properties": {
    "iso:country":"GB",
    "wof:name":"NP7 8LF",
    "wof:placetype":"postalcode"
},
  "geometry": {"coordinates":[-2.84182746531146,51.90623057497447],"type":"Point"}
}