{
  "type": "Feature",
  "properties": {
    "date:inception_lower": "2002-06-01",
    "date:inception_upper": "2002-06-01",
    "iso:country": "GB",
    "wof:name": "CV47 2DR",
    "wof:placetype": "postalcode"
  },
  "geometry": {"coordinates":[-1.431175,52.216952],"type":"Point"}
}
