{
  "type": "Feature",
  "properties": {
    "iso:country": "GB",
    "wof:name": "EN10 6NA",
    "wof:placetype": "postalcode"
  },
  "geometry": {"coordinates":[-0.023535,51.731211],"type":"Point"}
}
