{
  "type": "Feature",
  "properties": {
    "iso:country":"GB",
    "wof:name":"NW2 3AQ",
    "wof:placetype":"postalcode"
},
  "geometry": {"coordinates":[-0.21728380503458,51.55352160471521],"type":"Point"}
}