{
  "type": "Feature",
  "properties": {
    "iso:country":"GB",
    "wof:name":"SL1 3FN",
    "wof:placetype":"postalcode"
},
  "geometry": {"coordinates":[-0.60094002401649,51.51218938176157],"type":"Point"}
}