{
  "type": "Feature",
  "properties": {
    "iso:country": "GB",
    "wof:name": "TW15 1UE",
    "wof:placetype": "postalcode"
  },
  "geometry": {"coordinates":[-0.446269,51.420545],"type":"Point"}
}
