{
  "type": "Feature",
  "properties": {
    "iso:country":"GB",
    "wof:name":"TW15 1UE",
    "wof:placetype":"postalcode"
},
  "geometry": {"coordinates":[-0.44626890039787,51.42054498415045],"type":"Point"}
}