{
  "type": "Feature",
  "properties": {
    "iso:country":"GB",
    "wof:name":"GU2 7PT",
    "wof:placetype":"postalcode"
},
  "geometry": {"coordinates":[-0.58967308012614,51.23481418055194],"type":"Point"}
}