{
  "type": "Feature",
  "properties": {
    "iso:country":"GB",
    "wof:name":"BS4 5HJ",
    "wof:placetype":"postalcode"
},
  "geometry": {"coordinates":[-2.54494518261976,51.42811466207596],"type":"Point"}
}