{
  "type": "Feature",
  "properties": {
    "date:inception_lower": "2005-10-01",
    "date:inception_upper": "2005-10-01",
    "iso:country": "GB",
    "wof:name": "BN22 8UY",
    "wof:placetype": "postalcode"
  },
  "geometry": {"coordinates":[0.287163,50.780166],"type":"Point"}
}
