{
  "type": "Feature",
  "properties": {
    "iso:country":"GB",
    "wof:name":"BA2 8QU",
    "wof:placetype":"postalcode"
},
  "geometry": {"coordinates":[-2.37348246298861,51.3245909311328],"type":"Point"}
}