{
  "type": "Feature",
  "properties": {
    "date:inception_lower": "1980-01-01",
    "date:inception_upper": "1980-01-01",
    "iso:country": "GB",
    "wof:name": "ME9 8RA",
    "wof:placetype": "postalcode"
  },
  "geometry": {"coordinates":[0.729394,51.369413],"type":"Point"}
}
