{
  "type": "Feature",
  "properties": {
    "iso:country":"GB",
    "wof:name":"ME9 8RA",
    "wof:placetype":"postalcode"
},
  "geometry": {"coordinates":[0.72939378529808,51.36941309339377],"type":"Point"}
}