{
  "type": "Feature",
  "properties": {
    "iso:country":"GB",
    "wof:name":"B6 4AN",
    "wof:placetype":"postalcode"
},
  "geometry": {"coordinates":[-1.8851871485442,52.49496496812318],"type":"Point"}
}