{
  "type": "Feature",
  "properties": {
    "date:inception_lower": "1980-01-01",
    "date:inception_upper": "1980-01-01",
    "iso:country": "GB",
    "wof:name": "DH4 4QS",
    "wof:placetype": "postalcode"
  },
  "geometry": {"coordinates":[-1.494959,54.867396],"type":"Point"}
}
