{
  "type": "Feature",
  "properties": {
    "iso:country":"GB",
    "wof:name":"DH4 4QS",
    "wof:placetype":"postalcode"
},
  "geometry": {"coordinates":[-1.49495930104628,54.86739633120077],"type":"Point"}
}