{
  "type": "Feature",
  "properties": {
    "iso:country":"GB",
    "wof:name":"BL2 1NU",
    "wof:placetype":"postalcode"
},
  "geometry": {"coordinates":[-2.4133890507291,53.57652227044184],"type":"Point"}
}