{
  "type": "Feature",
  "properties": {
    "iso:country": "GB",
    "wof:name": "BL2 1NU",
    "wof:placetype": "postalcode"
  },
  "geometry": {"coordinates":[-2.413389,53.576522],"type":"Point"}
}
