{
  "type": "Feature",
  "properties": {
    "iso:country":"GB",
    "wof:name":"CR3 0DA",
    "wof:placetype":"postalcode"
},
  "geometry": {"coordinates":[-0.08248053286218,51.30932173584042],"type":"Point"}
}