{
  "type": "Feature",
  "properties": {
    "date:inception_lower":"1980-01-01",
    "date:inception_upper":"1980-01-31",
    "iso:country":"GB",
    "wof:name":"CR3 0DA",
    "wof:placetype":"postalcode"
},
  "geometry": {"coordinates":[-0.08248,51.309322],"type":"Point"}
}