{
  "type": "Feature",
  "properties": {
    "date:inception_lower": "2024-01-01",
    "date:inception_upper": "2024-01-01",
    "iso:country": "GB",
    "wof:name": "SY8 4FB",
    "wof:placetype": "postalcode"
  },
  "geometry": {"coordinates":[-2.701812,52.309523],"type":"Point"}
}
