{
  "type": "Feature",
  "properties": {
    "iso:country":"GB",
    "wof:name":"L24 9GB",
    "wof:placetype":"postalcode"
},
  "geometry": {"coordinates":[-2.86703072172476,53.35800397716105],"type":"Point"}
}