{
  "type": "Feature",
  "properties": {
    "iso:country":"GB",
    "wof:name":"CH64 8TR",
    "wof:placetype":"postalcode"
},
  "geometry": {"coordinates":[-3.0478332651997,53.27712536770383],"type":"Point"}
}