{
  "type": "Feature",
  "properties": {
    "iso:country":"GB",
    "wof:name":"NG10 4GA",
    "wof:placetype":"postalcode"
},
  "geometry": {"coordinates":[-1.2844203846811,52.90449268947178],"type":"Point"}
}