{
  "type": "Feature",
  "properties": {
    "date:inception_lower": "1992-08-01",
    "date:inception_upper": "1992-08-01",
    "iso:country": "GB",
    "wof:name": "N17 0DP",
    "wof:placetype": "postalcode"
  },
  "geometry": {"coordinates":[-0.066866,51.608539],"type":"Point"}
}
