{
  "type": "Feature",
  "properties": {
    "iso:country":"GB",
    "wof:name":"N17 0DP",
    "wof:placetype":"postalcode"
},
  "geometry": {"coordinates":[-0.06686567116056,51.60853878605818],"type":"Point"}
}