{
  "type": "Feature",
  "properties": {
    "iso:country":"GB",
    "wof:name":"W4 5EN",
    "wof:placetype":"postalcode"
},
  "geometry": {"coordinates":[-0.26760820328153,51.49662547504559],"type":"Point"}
}