{
  "type": "Feature",
  "properties": {
    "iso:country": "GB",
    "wof:name": "PE7 1BN",
    "wof:placetype": "postalcode"
  },
  "geometry": {"coordinates":[-0.131851,52.554083],"type":"Point"}
}
