{
  "type": "Feature",
  "properties": {
    "iso:country":"GB",
    "wof:name":"PE7 1BN",
    "wof:placetype":"postalcode"
},
  "geometry": {"coordinates":[-0.13185076312904,52.55408279089745],"type":"Point"}
}