{
  "type": "Feature",
  "properties": {
    "date:inception_lower": "2021-06-01",
    "date:inception_upper": "2021-06-01",
    "iso:country": "GB",
    "wof:name": "MK19 7FF",
    "wof:placetype": "postalcode"
  },
  "geometry": {"coordinates":[-0.835571,52.11354],"type":"Point"}
}
