{
  "type": "Feature",
  "properties": {
    "date:inception_lower": "1980-01-01",
    "date:inception_upper": "1980-01-01",
    "iso:country": "GB",
    "wof:name": "SN4 8DJ",
    "wof:placetype": "postalcode"
  },
  "geometry": {"coordinates":[-1.892568,51.542968],"type":"Point"}
}
