{
  "type": "Feature",
  "properties": {
    "iso:country":"GB",
    "wof:name":"BA11 1LB",
    "wof:placetype":"postalcode"
},
  "geometry": {"coordinates":[-2.32175035106133,51.22466536653214],"type":"Point"}
}