{
  "type": "Feature",
  "properties": {
    "iso:country":"GB",
    "wof:name":"AB16 6WA",
    "wof:placetype":"postalcode"
},
  "geometry": {"coordinates":[-2.18300443577718,57.15575285410233],"type":"Point"}
}