{
  "type": "Feature",
  "properties": {
    "date:inception_lower": "2019-05-01",
    "date:inception_upper": "2019-05-01",
    "iso:country": "GB",
    "wof:name": "LE8 8EJ",
    "wof:placetype": "postalcode"
  },
  "geometry": {"coordinates":[-1.054805,52.539318],"type":"Point"}
}
