{
  "type": "Feature",
  "properties": {
    "iso:country":"GB",
    "wof:name":"NW9 0PA",
    "wof:placetype":"postalcode"
},
  "geometry": {"coordinates":[-0.26466889753073,51.58534531223063],"type":"Point"}
}