{
  "type": "Feature",
  "properties": {
    "iso:country": "GB",
    "wof:name": "TW4 7RH",
    "wof:placetype": "postalcode"
  },
  "geometry": {"coordinates":[-0.390978,51.475129],"type":"Point"}
}
