{
  "type": "Feature",
  "properties": {
    "date:inception_lower":"1980-01-01",
    "date:inception_upper":"1980-01-31",
    "iso:country":"GB",
    "wof:name":"TW4 7RH",
    "wof:placetype":"postalcode"
},
  "geometry": {"coordinates":[-0.390978,51.475129],"type":"Point"}
}