{
  "type": "Feature",
  "properties": {
    "iso:country":"GB",
    "wof:name":"TW4 7RH",
    "wof:placetype":"postalcode"
},
  "geometry": {"coordinates":[-0.39097842969671,51.47512886438573],"type":"Point"}
}