{
  "type": "Feature",
  "properties": {
    "iso:country":"GB",
    "wof:name":"CH45 3NS",
    "wof:placetype":"postalcode"
},
  "geometry": {"coordinates":[-3.06961615344502,53.43277550895579],"type":"Point"}
}