{
  "type": "Feature",
  "properties": {
    "date:inception_lower": "2009-02-01",
    "date:inception_upper": "2009-02-01",
    "iso:country": "GB",
    "wof:name": "WR1 2PD",
    "wof:placetype": "postalcode"
  },
  "geometry": {"coordinates":[-2.217722,52.186735],"type":"Point"}
}
