{
  "type": "Feature",
  "properties": {
    "iso:country":"GB",
    "wof:name":"DH4 4LA",
    "wof:placetype":"postalcode"
},
  "geometry": {"coordinates":[-1.48754412286052,54.86728441166316],"type":"Point"}
}