{
  "type": "Feature",
  "properties": {
    "iso:country":"GB",
    "wof:name":"ME8 6SN",
    "wof:placetype":"postalcode"
},
  "geometry": {"coordinates":[0.59126446459394,51.37264097482041],"type":"Point"}
}