{
  "type": "Feature",
  "properties": {
    "iso:country":"GB",
    "wof:name":"DD8 3SA",
    "wof:placetype":"postalcode"
},
  "geometry": {"coordinates":[-2.87219253589287,56.69325393401209],"type":"Point"}
}