{
  "type": "Feature",
  "properties": {
    "iso:country":"GB",
    "wof:name":"SK6 7NU",
    "wof:placetype":"postalcode"
},
  "geometry": {"coordinates":[-2.06707837689062,53.38732874713055],"type":"Point"}
}