{
  "type": "Feature",
  "properties": {
    "date:inception_lower": "1997-06-01",
    "date:inception_upper": "1997-06-01",
    "iso:country": "GB",
    "wof:name": "BS16 7BL",
    "wof:placetype": "postalcode"
  },
  "geometry": {"coordinates":[-2.475167,51.4943],"type":"Point"}
}
