{
  "type": "Feature",
  "properties": {
    "iso:country":"GB",
    "wof:name":"B32 3HS",
    "wof:placetype":"postalcode"
},
  "geometry": {"coordinates":[-1.99311551139686,52.43999257659254],"type":"Point"}
}