{
  "type": "Feature",
  "properties": {
    "date:inception_lower": "1980-01-01",
    "date:inception_upper": "1980-01-01",
    "iso:country": "GB",
    "wof:name": "RG25 3LL",
    "wof:placetype": "postalcode"
  },
  "geometry": {"coordinates":[-1.265525,51.239252],"type":"Point"}
}
