{
  "type": "Feature",
  "properties": {
    "iso:country": "GB",
    "wof:name": "EX12 3AQ",
    "wof:placetype": "postalcode"
  },
  "geometry": {"coordinates":[-3.097798,50.69378],"type":"Point"}
}
