{
  "type": "Feature",
  "properties": {
    "iso:country":"GB",
    "wof:name":"NW7 3PP",
    "wof:placetype":"postalcode"
},
  "geometry": {"coordinates":[-0.25264894568721,51.61458065626923],"type":"Point"}
}