{
  "type": "Feature",
  "properties": {
    "date:inception_lower": "1998-06-01",
    "date:inception_upper": "1998-06-01",
    "iso:country": "GB",
    "wof:name": "SS6 9GB",
    "wof:placetype": "postalcode"
  },
  "geometry": {"coordinates":[0.591984,51.598399],"type":"Point"}
}
