{
  "type": "Feature",
  "properties": {
    "date:inception_lower": "2021-06-01",
    "date:inception_upper": "2021-06-01",
    "iso:country": "GB",
    "wof:name": "OX12 9YQ",
    "wof:placetype": "postalcode"
  },
  "geometry": {"coordinates":[-1.449561,51.593276],"type":"Point"}
}
