{
  "type": "Feature",
  "properties": {
    "iso:country":"GB",
    "wof:name":"PO21 1EQ",
    "wof:placetype":"postalcode"
},
  "geometry": {"coordinates":[-0.6717475268537,50.78421374515974],"type":"Point"}
}