{
  "type": "Feature",
  "properties": {
    "iso:country": "GB",
    "wof:name": "DA17 5AU",
    "wof:placetype": "postalcode"
  },
  "geometry": {"coordinates":[0.150196,51.489952],"type":"Point"}
}
