{
  "type": "Feature",
  "properties": {
    "iso:country":"GB",
    "wof:name":"DA17 5AU",
    "wof:placetype":"postalcode"
},
  "geometry": {"coordinates":[0.15019620351985,51.48995158853216],"type":"Point"}
}