{
  "type": "Feature",
  "properties": {
    "iso:country":"GB",
    "wof:name":"B21 0HD",
    "wof:placetype":"postalcode"
},
  "geometry": {"coordinates":[-1.95567178700039,52.50380435697581],"type":"Point"}
}