{
  "type": "Feature",
  "properties": {
    "iso:country":"GB",
    "wof:name":"DN16 3AL",
    "wof:placetype":"postalcode"
},
  "geometry": {"coordinates":[-0.61951853475509,53.56187703297106],"type":"Point"}
}