{
  "type": "Feature",
  "properties": {
    "date:inception_lower":"2013-11-01",
    "date:inception_upper":"2013-11-30",
    "iso:country":"GB",
    "wof:name":"DN16 3AL",
    "wof:placetype":"postalcode"
},
  "geometry": {"coordinates":[-0.619518,53.561877],"type":"Point"}
}