{
  "type": "Feature",
  "properties": {
    "iso:country":"GB",
    "wof:name":"SY22 5AA",
    "wof:placetype":"postalcode"
},
  "geometry": {"coordinates":[-3.27436949347773,52.76680059158029],"type":"Point"}
}