{
  "type": "Feature",
  "properties": {
    "iso:country":"GB",
    "wof:name":"B95 5JZ",
    "wof:placetype":"postalcode"
},
  "geometry": {"coordinates":[-1.77718909244591,52.29128408257409],"type":"Point"}
}