{
  "type": "Feature",
  "properties": {
    "iso:country":"GB",
    "wof:name":"RG14 7PX",
    "wof:placetype":"postalcode"
},
  "geometry": {"coordinates":[-1.32304133630759,51.39517604414431],"type":"Point"}
}