{
  "type": "Feature",
  "properties": {
    "date:inception_lower":"2001-06-01",
    "date:inception_upper":"2001-06-30",
    "iso:country":"GB",
    "wof:name":"BS11 0GA",
    "wof:placetype":"postalcode"
},
  "geometry": {"coordinates":[-2.646304,51.503291],"type":"Point"}
}