{
  "type": "Feature",
  "properties": {
    "iso:country": "GB",
    "wof:name": "BS11 0GA",
    "wof:placetype": "postalcode"
  },
  "geometry": {"coordinates":[-2.646304,51.503291],"type":"Point"}
}
