{
  "type": "Feature",
  "properties": {
    "iso:country":"GB",
    "wof:name":"BH22 9PN",
    "wof:placetype":"postalcode"
},
  "geometry": {"coordinates":[-1.90442978264109,50.81016886662591],"type":"Point"}
}