{
  "type": "Feature",
  "properties": {
    "date:inception_lower": "1980-01-01",
    "date:inception_upper": "1980-01-01",
    "iso:country": "GB",
    "wof:name": "BH22 9PN",
    "wof:placetype": "postalcode"
  },
  "geometry": {"coordinates":[-1.90443,50.810169],"type":"Point"}
}
