{
  "type": "Feature",
  "properties": {
    "iso:country":"GB",
    "wof:name":"M26 4QG",
    "wof:placetype":"postalcode"
},
  "geometry": {"coordinates":[-2.34008562259968,53.56946371278117],"type":"Point"}
}