{
  "type": "Feature",
  "properties": {
    "iso:country": "GB",
    "wof:name": "TF9 3QW",
    "wof:placetype": "postalcode"
  },
  "geometry": {"coordinates":[-2.573247,52.888056],"type":"Point"}
}
