{
  "type": "Feature",
  "properties": {
    "iso:country":"GB",
    "wof:name":"TF9 3QW",
    "wof:placetype":"postalcode"
},
  "geometry": {"coordinates":[-2.57324669646572,52.88805609083615],"type":"Point"}
}