{
  "type": "Feature",
  "properties": {
    "iso:country":"GB",
    "wof:name":"PE6 7EG",
    "wof:placetype":"postalcode"
},
  "geometry": {"coordinates":[-0.34435498498276,52.63030447578194],"type":"Point"}
}