{
  "type": "Feature",
  "properties": {
    "iso:country": "GB",
    "wof:name": "GL2 7LL",
    "wof:placetype": "postalcode"
  },
  "geometry": {"coordinates":[-2.356526,51.791802],"type":"Point"}
}
