{
  "type": "Feature",
  "properties": {
    "iso:country":"GB",
    "wof:name":"RG7 1DY",
    "wof:placetype":"postalcode"
},
  "geometry": {"coordinates":[-0.97057168008971,51.39779008245406],"type":"Point"}
}