{
  "type": "Feature",
  "properties": {
    "iso:country":"GB",
    "wof:name":"CR8 1HA",
    "wof:placetype":"postalcode"
},
  "geometry": {"coordinates":[-0.10550571498457,51.34388717121971],"type":"Point"}
}