{
  "type": "Feature",
  "properties": {
    "date:inception_lower": "1990-07-01",
    "date:inception_upper": "1990-07-01",
    "iso:country": "GB",
    "wof:name": "CR8 1HA",
    "wof:placetype": "postalcode"
  },
  "geometry": {"coordinates":[-0.105506,51.343887],"type":"Point"}
}
