{
  "type": "Feature",
  "properties": {
    "iso:country": "GB",
    "wof:name": "AL3 7NH",
    "wof:placetype": "postalcode"
  },
  "geometry": {"coordinates":[-0.398643,51.793409],"type":"Point"}
}
