{
  "type": "Feature",
  "properties": {
    "iso:country":"GB",
    "wof:name":"AL3 7NH",
    "wof:placetype":"postalcode"
},
  "geometry": {"coordinates":[-0.39864302848658,51.79340880850352],"type":"Point"}
}