{
  "type": "Feature",
  "properties": {
    "iso:country": "GB",
    "wof:name": "NW9 6FP",
    "wof:placetype": "postalcode"
  },
  "geometry": {"coordinates":[-0.247709,51.584296],"type":"Point"}
}
