{
  "type": "Feature",
  "properties": {
    "date:inception_lower":"1988-03-01",
    "date:inception_upper":"1988-03-31",
    "iso:country":"GB",
    "wof:name":"SN9 5AX",
    "wof:placetype":"postalcode"
},
  "geometry": {"coordinates":[-1.763122,51.342401],"type":"Point"}
}