{
  "type": "Feature",
  "properties": {
    "iso:country": "GB",
    "wof:name": "SN9 5AX",
    "wof:placetype": "postalcode"
  },
  "geometry": {"coordinates":[-1.763122,51.342401],"type":"Point"}
}
