{
  "type": "Feature",
  "properties": {
    "iso:country":"GB",
    "wof:name":"B74 4SL",
    "wof:placetype":"postalcode"
},
  "geometry": {"coordinates":[-1.84098495049881,52.59310127177039],"type":"Point"}
}