{
  "type": "Feature",
  "properties": {
    "iso:country": "GB",
    "wof:name": "LS25 5EU",
    "wof:placetype": "postalcode"
  },
  "geometry": {"coordinates":[-1.228338,53.76179],"type":"Point"}
}
