{
  "type": "Feature",
  "properties": {
    "iso:country":"GB",
    "wof:name":"LS25 5EU",
    "wof:placetype":"postalcode"
},
  "geometry": {"coordinates":[-1.22833835819896,53.76178991731659],"type":"Point"}
}