{
  "type": "Feature",
  "properties": {
    "iso:country":"GB",
    "wof:name":"BH18 8HU",
    "wof:placetype":"postalcode"
},
  "geometry": {"coordinates":[-2.0026412104633,50.75085674362575],"type":"Point"}
}