{
  "type": "Feature",
  "properties": {
    "date:inception_lower": "1980-01-01",
    "date:inception_upper": "1980-01-01",
    "iso:country": "GB",
    "wof:name": "BH18 8HU",
    "wof:placetype": "postalcode"
  },
  "geometry": {"coordinates":[-2.002641,50.750857],"type":"Point"}
}
