{
  "type": "Feature",
  "properties": {
    "iso:country":"GB",
    "wof:name":"BR5 4EQ",
    "wof:placetype":"postalcode"
},
  "geometry": {"coordinates":[0.11870771932014,51.37991178874433],"type":"Point"}
}