{
  "type": "Feature",
  "properties": {
    "iso:country":"GB",
    "wof:name":"WS3 2UB",
    "wof:placetype":"postalcode"
},
  "geometry": {"coordinates":[-2.01823074087632,52.6248951215736],"type":"Point"}
}