{
  "type": "Feature",
  "properties": {
    "iso:country":"GB",
    "wof:name":"SN2 2PL",
    "wof:placetype":"postalcode"
},
  "geometry": {"coordinates":[-1.80272584039238,51.57135418483479],"type":"Point"}
}