{
  "type": "Feature",
  "properties": {
    "iso:country":"GB",
    "wof:name":"MK44 2BZ",
    "wof:placetype":"postalcode"
},
  "geometry": {"coordinates":[-0.37673487406199,52.23863924500175],"type":"Point"}
}