{
  "type": "Feature",
  "properties": {
    "iso:country": "GB",
    "wof:name": "MK44 2BZ",
    "wof:placetype": "postalcode"
  },
  "geometry": {"coordinates":[-0.376735,52.238639],"type":"Point"}
}
