{
  "type": "Feature",
  "properties": {
    "date:inception_lower": "1980-01-01",
    "date:inception_upper": "1980-01-01",
    "iso:country": "GB",
    "wof:name": "MK44 2BZ",
    "wof:placetype": "postalcode"
  },
  "geometry": {"coordinates":[-0.376935,52.239033],"type":"Point"}
}
