{
  "type": "Feature",
  "properties": {
    "iso:country":"GB",
    "wof:name":"WN2 3QQ",
    "wof:placetype":"postalcode"
},
  "geometry": {"coordinates":[-2.57000805538173,53.53207750519066],"type":"Point"}
}