{
  "type": "Feature",
  "properties": {
    "date:inception_lower": "1980-01-01",
    "date:inception_upper": "1980-01-01",
    "iso:country": "GB",
    "wof:name": "WN2 3QQ",
    "wof:placetype": "postalcode"
  },
  "geometry": {"coordinates":[-2.570008,53.532078],"type":"Point"}
}
