{
  "type": "Feature",
  "properties": {
    "iso:country": "GB",
    "wof:name": "EX10 9BG",
    "wof:placetype": "postalcode"
  },
  "geometry": {"coordinates":[-3.239003,50.687463],"type":"Point"}
}
