{
  "type": "Feature",
  "properties": {
    "date:inception_lower": "1980-01-01",
    "date:inception_upper": "1980-01-01",
    "iso:country": "GB",
    "wof:name": "FK5 4NA",
    "wof:placetype": "postalcode"
  },
  "geometry": {"coordinates":[-3.83385,56.020938],"type":"Point"}
}
