{
  "type": "Feature",
  "properties": {
    "iso:country": "GB",
    "wof:name": "BS35 1FL",
    "wof:placetype": "postalcode"
  },
  "geometry": {"coordinates":[-2.519417,51.620785],"type":"Point"}
}
