{
  "type": "Feature",
  "properties": {
    "iso:country":"GB",
    "wof:name":"IV2 4SX",
    "wof:placetype":"postalcode"
},
  "geometry": {"coordinates":[-4.22678077109207,57.47110127820815],"type":"Point"}
}