{
  "type": "Feature",
  "properties": {
    "iso:country": "GB",
    "wof:name": "GL1 5PW",
    "wof:placetype": "postalcode"
  },
  "geometry": {"coordinates":[-2.251078,51.855083],"type":"Point"}
}
