{
  "type": "Feature",
  "properties": {
    "iso:country":"GB",
    "wof:name":"LE10 0GL",
    "wof:placetype":"postalcode"
},
  "geometry": {"coordinates":[-1.38729392724758,52.55449574227143],"type":"Point"}
}