{
  "type": "Feature",
  "properties": {
    "date:inception_lower": "1998-12-01",
    "date:inception_upper": "1998-12-01",
    "iso:country": "GB",
    "wof:name": "LE10 0GL",
    "wof:placetype": "postalcode"
  },
  "geometry": {"coordinates":[-1.387294,52.554496],"type":"Point"}
}
