{
  "type": "Feature",
  "properties": {
    "date:inception_lower": "2021-12-01",
    "date:inception_upper": "2021-12-01",
    "iso:country": "GB",
    "wof:name": "GL53 9FF",
    "wof:placetype": "postalcode"
  },
  "geometry": {"coordinates":[-2.061274,51.84405],"type":"Point"}
}
