{
  "type": "Feature",
  "properties": {
    "iso:country":"GB",
    "wof:name":"CT6 6BZ",
    "wof:placetype":"postalcode"
},
  "geometry": {"coordinates":[1.13735294198047,51.36858223472859],"type":"Point"}
}