{
  "type": "Feature",
  "properties": {
    "date:inception_lower": "1980-01-01",
    "date:inception_upper": "1980-01-01",
    "iso:country": "GB",
    "wof:name": "CT6 6BZ",
    "wof:placetype": "postalcode"
  },
  "geometry": {"coordinates":[1.137353,51.368582],"type":"Point"}
}
