{
  "type": "Feature",
  "properties": {
    "date:inception_lower": "2005-06-01",
    "date:inception_upper": "2005-06-01",
    "iso:country": "GB",
    "wof:name": "SL5 0EZ",
    "wof:placetype": "postalcode"
  },
  "geometry": {"coordinates":[-0.63559,51.389334],"type":"Point"}
}
