{
  "type": "Feature",
  "properties": {
    "iso:country":"GB",
    "wof:name":"ST1 6LT",
    "wof:placetype":"postalcode"
},
  "geometry": {"coordinates":[-2.16214241481977,53.03381350167561],"type":"Point"}
}