{
  "type": "Feature",
  "properties": {
    "iso:country": "GB",
    "wof:name": "NG17 7HZ",
    "wof:placetype": "postalcode"
  },
  "geometry": {"coordinates":[-1.235936,53.099548],"type":"Point"}
}
