{
  "type": "Feature",
  "properties": {
    "date:inception_lower":"1980-01-01",
    "date:inception_upper":"1980-01-31",
    "iso:country":"GB",
    "wof:name":"B32 3LX",
    "wof:placetype":"postalcode"
},
  "geometry": {"coordinates":[-1.991219,52.435632],"type":"Point"}
}