{
  "type": "Feature",
  "properties": {
    "date:inception_lower": "1980-01-01",
    "date:inception_upper": "1980-01-01",
    "iso:country": "GB",
    "wof:name": "B32 3LX",
    "wof:placetype": "postalcode"
  },
  "geometry": {"coordinates":[-1.991051,52.435638],"type":"Point"}
}
