{
  "type": "Feature",
  "properties": {
    "iso:country":"GB",
    "wof:name":"B32 3LX",
    "wof:placetype":"postalcode"
},
  "geometry": {"coordinates":[-1.99121866426965,52.43563229434083],"type":"Point"}
}