{
  "type": "Feature",
  "properties": {
    "iso:country":"GB",
    "wof:name":"BA2 8EL",
    "wof:placetype":"postalcode"
},
  "geometry": {"coordinates":[-2.42012901033693,51.31730231079995],"type":"Point"}
}