{
  "type": "Feature",
  "properties": {
    "date:inception_lower": "1980-01-01",
    "date:inception_upper": "1980-01-01",
    "iso:country": "GB",
    "wof:name": "CO13 0EG",
    "wof:placetype": "postalcode"
  },
  "geometry": {"coordinates":[1.217071,51.854241],"type":"Point"}
}
