{
  "type": "Feature",
  "properties": {
    "iso:country": "GB",
    "wof:name": "CO13 0EG",
    "wof:placetype": "postalcode"
  },
  "geometry": {"coordinates":[1.217071,51.854241],"type":"Point"}
}
