{
  "type": "Feature",
  "properties": {
    "iso:country": "GB",
    "wof:name": "WS12 3YY",
    "wof:placetype": "postalcode"
  },
  "geometry": {"coordinates":[-1.998951,52.692148],"type":"Point"}
}
