{
  "type": "Feature",
  "properties": {
    "iso:country": "GB",
    "wof:name": "BN23 7DP",
    "wof:placetype": "postalcode"
  },
  "geometry": {"coordinates":[0.312944,50.797515],"type":"Point"}
}
