{
  "type": "Feature",
  "properties": {
    "date:inception_lower": "2008-11-01",
    "date:inception_upper": "2008-11-01",
    "iso:country": "GB",
    "wof:name": "BN8 5GL",
    "wof:placetype": "postalcode"
  },
  "geometry": {"coordinates":[0.076781,50.897787],"type":"Point"}
}
