{
  "type": "Feature",
  "properties": {
    "date:inception_lower":"1987-04-01",
    "date:inception_upper":"1987-04-30",
    "iso:country":"GB",
    "wof:name":"HU3 5LA",
    "wof:placetype":"postalcode"
},
  "geometry": {"coordinates":[-0.379397,53.738047],"type":"Point"}
}