{
  "type": "Feature",
  "properties": {
    "iso:country":"GB",
    "wof:name":"HU3 5LA",
    "wof:placetype":"postalcode"
},
  "geometry": {"coordinates":[-0.37939739878468,53.73804741670576],"type":"Point"}
}