{
  "type": "Feature",
  "properties": {
    "date:inception_lower": "1980-01-01",
    "date:inception_upper": "1980-01-01",
    "iso:country": "GB",
    "wof:name": "RH9 8HN",
    "wof:placetype": "postalcode"
  },
  "geometry": {"coordinates":[-0.041071,51.218662],"type":"Point"}
}
