{
  "type": "Feature",
  "properties": {
    "iso:country":"GB",
    "wof:name":"OL2 6RW",
    "wof:placetype":"postalcode"
},
  "geometry": {"coordinates":[-2.11578698685602,53.56745573229475],"type":"Point"}
}