{
  "type": "Feature",
  "properties": {
    "iso:country": "GB",
    "wof:name": "HA1 2AF",
    "wof:placetype": "postalcode"
  },
  "geometry": {"coordinates":[-0.332205,51.580104],"type":"Point"}
}
