{
  "type": "Feature",
  "properties": {
    "date:inception_lower":"2016-08-01",
    "date:inception_upper":"2016-08-31",
    "iso:country":"GB",
    "wof:name":"HA1 2AF",
    "wof:placetype":"postalcode"
},
  "geometry": {"coordinates":[-0.332205,51.580104],"type":"Point"}
}