{
  "type": "Feature",
  "properties": {
    "iso:country":"GB",
    "wof:name":"M22 9PQ",
    "wof:placetype":"postalcode"
},
  "geometry": {"coordinates":[-2.26428924302641,53.38131093044525],"type":"Point"}
}