{
  "type": "Feature",
  "properties": {
    "iso:country":"GB",
    "wof:name":"SA17 4RN",
    "wof:placetype":"postalcode"
},
  "geometry": {"coordinates":[-4.26505300115833,51.7399303970906],"type":"Point"}
}