{
  "type": "Feature",
  "properties": {
    "iso:country":"GB",
    "wof:name":"TW8 9QB",
    "wof:placetype":"postalcode"
},
  "geometry": {"coordinates":[-0.30364439861014,51.49376212552831],"type":"Point"}
}