{
  "type": "Feature",
  "properties": {
    "date:inception_lower": "2018-09-01",
    "date:inception_upper": "2018-09-01",
    "iso:country": "GB",
    "wof:name": "G72 8ZB",
    "wof:placetype": "postalcode"
  },
  "geometry": {"coordinates":[-4.178664,55.80308],"type":"Point"}
}
