{
  "type": "Feature",
  "properties": {
    "iso:country": "GB",
    "wof:name": "G72 8ZB",
    "wof:placetype": "postalcode"
  },
  "geometry": {"coordinates":[-4.178648,55.80309],"type":"Point"}
}
