{
  "type": "Feature",
  "properties": {
    "date:inception_lower":"1987-04-01",
    "date:inception_upper":"1987-04-30",
    "iso:country":"GB",
    "wof:name":"SO22 4QF",
    "wof:placetype":"postalcode"
},
  "geometry": {"coordinates":[-1.333147,51.049077],"type":"Point"}
}