{
  "type": "Feature",
  "properties": {
    "iso:country": "GB",
    "wof:name": "HG4 4JY",
    "wof:placetype": "postalcode"
  },
  "geometry": {"coordinates":[-1.710673,54.20105],"type":"Point"}
}
