{
  "type": "Feature",
  "properties": {
    "date:inception_lower": "1980-01-01",
    "date:inception_upper": "1980-01-01",
    "iso:country": "GB",
    "wof:name": "HG4 4JY",
    "wof:placetype": "postalcode"
  },
  "geometry": {"coordinates":[-1.710673,54.20105],"type":"Point"}
}
