{
  "type": "Feature",
  "properties": {
    "iso:country":"GB",
    "wof:name":"HG4 4JY",
    "wof:placetype":"postalcode"
},
  "geometry": {"coordinates":[-1.7106732744209,54.20104960194464],"type":"Point"}
}