{
  "type": "Feature",
  "properties": {
    "iso:country":"GB",
    "wof:name":"NG7 5FZ",
    "wof:placetype":"postalcode"
},
  "geometry": {"coordinates":[-1.17505005280562,52.96562268593765],"type":"Point"}
}