{
  "type": "Feature",
  "properties": {
    "iso:country":"GB",
    "wof:name":"SK3 0HW",
    "wof:placetype":"postalcode"
},
  "geometry": {"coordinates":[-2.16757403214162,53.40637543434573],"type":"Point"}
}