{
  "type": "Feature",
  "properties": {
    "date:inception_lower": "1980-01-01",
    "date:inception_upper": "1980-01-01",
    "iso:country": "GB",
    "wof:name": "SK3 0HW",
    "wof:placetype": "postalcode"
  },
  "geometry": {"coordinates":[-2.167574,53.406375],"type":"Point"}
}
