{
  "type": "Feature",
  "properties": {
    "iso:country":"GB",
    "wof:name":"CF35 6SR",
    "wof:placetype":"postalcode"
},
  "geometry": {"coordinates":[-3.50017759392441,51.52859358364109],"type":"Point"}
}