{
  "type": "Feature",
  "properties": {
    "iso:country":"GB",
    "wof:name":"RG42 4PZ",
    "wof:placetype":"postalcode"
},
  "geometry": {"coordinates":[-0.79012194459757,51.43066777549888],"type":"Point"}
}