{
  "type": "Feature",
  "properties": {
    "iso:country": "GB",
    "wof:name": "LL16 4BU",
    "wof:placetype": "postalcode"
  },
  "geometry": {"coordinates":[-3.353734,53.212925],"type":"Point"}
}
