{
  "type": "Feature",
  "properties": {
    "date:inception_lower":"2000-12-01",
    "date:inception_upper":"2000-12-31",
    "iso:country":"GB",
    "wof:name":"ST15 0XR",
    "wof:placetype":"postalcode"
},
  "geometry": {"coordinates":[-2.158262,52.890423],"type":"Point"}
}