{
  "type": "Feature",
  "properties": {
    "iso:country":"GB",
    "wof:name":"B29 6QP",
    "wof:placetype":"postalcode"
},
  "geometry": {"coordinates":[-1.95035179800205,52.43957790091334],"type":"Point"}
}