{
  "type": "Feature",
  "properties": {
    "date:inception_lower": "2002-09-01",
    "date:inception_upper": "2002-09-01",
    "iso:country": "GB",
    "wof:name": "YO17 8AS",
    "wof:placetype": "postalcode"
  },
  "geometry": {"coordinates":[-0.77525,54.13605],"type":"Point"}
}
