{
  "type": "Feature",
  "properties": {
    "iso:country":"GB",
    "wof:name":"CF40 2UT",
    "wof:placetype":"postalcode"
},
  "geometry": {"coordinates":[-3.43383086792212,51.61973000293771],"type":"Point"}
}