{
  "type": "Feature",
  "properties": {
    "iso:country":"GB",
    "wof:name":"HR3 5LP",
    "wof:placetype":"postalcode"
},
  "geometry": {"coordinates":[-3.20845512600555,52.04715633117671],"type":"Point"}
}