{
  "type": "Feature",
  "properties": {
    "iso:country":"GB",
    "wof:name":"NE13 7AW",
    "wof:placetype":"postalcode"
},
  "geometry": {"coordinates":[-1.6636718875424,55.01884212117564],"type":"Point"}
}