{
  "type": "Feature",
  "properties": {
    "iso:country":"GB",
    "wof:name":"G64 1UX",
    "wof:placetype":"postalcode"
},
  "geometry": {"coordinates":[-4.21015491355368,55.90174292169488],"type":"Point"}
}