{
  "type": "Feature",
  "properties": {
    "iso:country":"GB",
    "wof:name":"CR5 2JL",
    "wof:placetype":"postalcode"
},
  "geometry": {"coordinates":[-0.13077286207867,51.32281840908434],"type":"Point"}
}