{
  "type": "Feature",
  "properties": {
    "iso:country":"GB",
    "wof:name":"HU6 8BY",
    "wof:placetype":"postalcode"
},
  "geometry": {"coordinates":[-0.38162170835841,53.78038013279896],"type":"Point"}
}