{
  "type": "Feature",
  "properties": {
    "date:inception_lower": "1980-01-01",
    "date:inception_upper": "1980-01-01",
    "iso:country": "GB",
    "wof:name": "LS27 9JS",
    "wof:placetype": "postalcode"
  },
  "geometry": {"coordinates":[-1.604321,53.748742],"type":"Point"}
}
