{
  "type": "Feature",
  "properties": {
    "iso:country":"GB",
    "wof:name":"LS27 9JS",
    "wof:placetype":"postalcode"
},
  "geometry": {"coordinates":[-1.60380170448782,53.74876061429539],"type":"Point"}
}