{
  "type": "Feature",
  "properties": {
    "date:inception_lower":"1980-01-01",
    "date:inception_upper":"1980-01-31",
    "iso:country":"GB",
    "wof:name":"NE23 7EX",
    "wof:placetype":"postalcode"
},
  "geometry": {"coordinates":[-1.54275,55.066623],"type":"Point"}
}