{
  "type": "Feature",
  "properties": {
    "iso:country":"GB",
    "wof:name":"NE23 7EX",
    "wof:placetype":"postalcode"
},
  "geometry": {"coordinates":[-1.54274965176643,55.0666230971142],"type":"Point"}
}