{
  "type": "Feature",
  "properties": {
    "date:inception_lower": "1983-07-01",
    "date:inception_upper": "1983-07-01",
    "iso:country": "GB",
    "wof:name": "BB12 6NZ",
    "wof:placetype": "postalcode"
  },
  "geometry": {"coordinates":[-2.291749,53.790215],"type":"Point"}
}
