{
  "type": "Feature",
  "properties": {
    "iso:country":"GB",
    "wof:name":"BB12 6NZ",
    "wof:placetype":"postalcode"
},
  "geometry": {"coordinates":[-2.29174871845546,53.79021503871834],"type":"Point"}
}