{
  "type": "Feature",
  "properties": {
    "iso:country":"GB",
    "wof:name":"ST14 8QU",
    "wof:placetype":"postalcode"
},
  "geometry": {"coordinates":[-1.92164928512604,52.87220031663157],"type":"Point"}
}