{
  "type": "Feature",
  "properties": {
    "date:inception_lower":"1980-01-01",
    "date:inception_upper":"1980-01-31",
    "iso:country":"GB",
    "wof:name":"ST14 8QU",
    "wof:placetype":"postalcode"
},
  "geometry": {"coordinates":[-1.921649,52.8722],"type":"Point"}
}