{
  "type": "Feature",
  "properties": {
    "date:inception_lower": "1980-01-01",
    "date:inception_upper": "1980-01-01",
    "iso:country": "GB",
    "wof:name": "HX3 7TB",
    "wof:placetype": "postalcode"
  },
  "geometry": {"coordinates":[-1.844675,53.750824],"type":"Point"}
}
