{
  "type": "Feature",
  "properties": {
    "iso:country":"GB",
    "wof:name":"HX3 7TB",
    "wof:placetype":"postalcode"
},
  "geometry": {"coordinates":[-1.84467551469701,53.75082421609299],"type":"Point"}
}