{
  "type": "Feature",
  "properties": {
    "iso:country":"GB",
    "wof:name":"CA25 5EF",
    "wof:placetype":"postalcode"
},
  "geometry": {"coordinates":[-3.50431479074085,54.51980610773694],"type":"Point"}
}