{
  "type": "Feature",
  "properties": {
    "date:inception_lower": "1985-04-01",
    "date:inception_upper": "1985-04-01",
    "iso:country": "GB",
    "wof:name": "IP25 6XB",
    "wof:placetype": "postalcode"
  },
  "geometry": {"coordinates":[0.819321,52.567617],"type":"Point"}
}
