{
  "type": "Feature",
  "properties": {
    "iso:country": "GB",
    "wof:name": "IP25 6XB",
    "wof:placetype": "postalcode"
  },
  "geometry": {"coordinates":[0.819321,52.567617],"type":"Point"}
}
