{
  "type": "Feature",
  "properties": {
    "date:inception_lower": "1980-01-01",
    "date:inception_upper": "1980-01-01",
    "iso:country": "GB",
    "wof:name": "M12 4NF",
    "wof:placetype": "postalcode"
  },
  "geometry": {"coordinates":[-2.194634,53.458872],"type":"Point"}
}
