{
  "type": "Feature",
  "properties": {
    "iso:country":"GB",
    "wof:name":"ME17 1QQ",
    "wof:placetype":"postalcode"
},
  "geometry": {"coordinates":[0.63985282327648,51.2622717718684],"type":"Point"}
}