{
  "type": "Feature",
  "properties": {
    "iso:country": "GB",
    "wof:name": "ME17 1QQ",
    "wof:placetype": "postalcode"
  },
  "geometry": {"coordinates":[0.640964,51.261609],"type":"Point"}
}
