{
  "type": "Feature",
  "properties": {
    "iso:country": "GB",
    "wof:name": "NG9 2JN",
    "wof:placetype": "postalcode"
  },
  "geometry": {"coordinates":[-1.198749,52.929433],"type":"Point"}
}
