{
  "type": "Feature",
  "properties": {
    "iso:country": "GB",
    "wof:name": "BD7 1RD",
    "wof:placetype": "postalcode"
  },
  "geometry": {"coordinates":[-1.76723,53.789105],"type":"Point"}
}
