{
  "type": "Feature",
  "properties": {
    "iso:country":"GB",
    "wof:name":"UB3 3AB",
    "wof:placetype":"postalcode"
},
  "geometry": {"coordinates":[-0.40880756740727,51.5139488899102],"type":"Point"}
}