{
  "type": "Feature",
  "properties": {
    "date:inception_lower":"1980-01-01",
    "date:inception_upper":"1980-01-31",
    "iso:country":"GB",
    "wof:name":"UB3 3AB",
    "wof:placetype":"postalcode"
},
  "geometry": {"coordinates":[-0.408808,51.513949],"type":"Point"}
}