{
  "type": "Feature",
  "properties": {
    "iso:country": "GB",
    "wof:name": "HP4 2EN",
    "wof:placetype": "postalcode"
  },
  "geometry": {"coordinates":[-0.55301,51.757815],"type":"Point"}
}
