{
  "type": "Feature",
  "properties": {
    "iso:country":"GB",
    "wof:name":"HP4 2EN",
    "wof:placetype":"postalcode"
},
  "geometry": {"coordinates":[-0.55301023728063,51.75781549124856],"type":"Point"}
}