{
  "type": "Feature",
  "properties": {
    "iso:country": "GB",
    "wof:name": "TR18 5DE",
    "wof:placetype": "postalcode"
  },
  "geometry": {"coordinates":[-5.549048,50.098407],"type":"Point"}
}
