{
  "type": "Feature",
  "properties": {
    "iso:country":"GB",
    "wof:name":"TQ3 1QR",
    "wof:placetype":"postalcode"
},
  "geometry": {"coordinates":[-3.57792314910033,50.45274399618918],"type":"Point"}
}