{
  "type": "Feature",
  "properties": {
    "iso:country": "GB",
    "wof:name": "CA10 2HU",
    "wof:placetype": "postalcode"
  },
  "geometry": {"coordinates":[-2.715141,54.604904],"type":"Point"}
}
