{
  "type": "Feature",
  "properties": {
    "iso:country":"GB",
    "wof:name":"CA10 2HU",
    "wof:placetype":"postalcode"
},
  "geometry": {"coordinates":[-2.71514076055231,54.60490397444545],"type":"Point"}
}