{
  "type": "Feature",
  "properties": {
    "iso:country":"GB",
    "wof:name":"ML3 7QD",
    "wof:placetype":"postalcode"
},
  "geometry": {"coordinates":[-4.04642908200721,55.76138335511502],"type":"Point"}
}