{
  "type": "Feature",
  "properties": {
    "date:inception_lower":"2003-06-01",
    "date:inception_upper":"2003-06-30",
    "iso:country":"GB",
    "wof:name":"ML3 7QD",
    "wof:placetype":"postalcode"
},
  "geometry": {"coordinates":[-4.046429,55.761383],"type":"Point"}
}