{
  "type": "Feature",
  "properties": {
    "iso:country": "GB",
    "wof:name": "EN4 9BU",
    "wof:placetype": "postalcode"
  },
  "geometry": {"coordinates":[-0.167119,51.654626],"type":"Point"}
}
