{
  "type": "Feature",
  "properties": {
    "iso:country":"GB",
    "wof:name":"EN4 9BU",
    "wof:placetype":"postalcode"
},
  "geometry": {"coordinates":[-0.16720493965279,51.65456141210966],"type":"Point"}
}