{
  "type": "Feature",
  "properties": {
    "iso:country":"GB",
    "wof:name":"SE11 5LN",
    "wof:placetype":"postalcode"
},
  "geometry": {"coordinates":[-0.11567422091775,51.48756521541674],"type":"Point"}
}