{
  "type": "Feature",
  "properties": {
    "iso:country":"GB",
    "wof:name":"LL65 3UN",
    "wof:placetype":"postalcode"
},
  "geometry": {"coordinates":[-4.46109292453458,53.29030796352625],"type":"Point"}
}