{
  "type": "Feature",
  "properties": {
    "iso:country":"GB",
    "wof:name":"HX7 7HZ",
    "wof:placetype":"postalcode"
},
  "geometry": {"coordinates":[-2.06268188027877,53.74922721983657],"type":"Point"}
}