{
  "type": "Feature",
  "properties": {
    "iso:country":"GB",
    "wof:name":"CM18 7HN",
    "wof:placetype":"postalcode"
},
  "geometry": {"coordinates":[0.11654913346468,51.75203488214451],"type":"Point"}
}