{
  "type": "Feature",
  "properties": {
    "date:inception_lower":"1980-01-01",
    "date:inception_upper":"1980-01-31",
    "iso:country":"GB",
    "wof:name":"CM18 7HN",
    "wof:placetype":"postalcode"
},
  "geometry": {"coordinates":[0.116549,51.752035],"type":"Point"}
}