{
  "type": "Feature",
  "properties": {
    "date:inception_lower":"2001-06-01",
    "date:inception_upper":"2001-06-30",
    "iso:country":"GB",
    "wof:name":"LL16 5BF",
    "wof:placetype":"postalcode"
},
  "geometry": {"coordinates":[-3.463573,53.200443],"type":"Point"}
}