{
  "type": "Feature",
  "properties": {
    "iso:country":"GB",
    "wof:name":"LL16 5BF",
    "wof:placetype":"postalcode"
},
  "geometry": {"coordinates":[-3.4635727547678,53.20044262025431],"type":"Point"}
}