{
  "type": "Feature",
  "properties": {
    "iso:country":"GB",
    "wof:name":"AB15 8BX",
    "wof:placetype":"postalcode"
},
  "geometry": {"coordinates":[-2.14970921354528,57.13854067551045],"type":"Point"}
}