{
  "type": "Feature",
  "properties": {
    "iso:country":"GB",
    "wof:name":"WF4 1AR",
    "wof:placetype":"postalcode"
},
  "geometry": {"coordinates":[-1.41269352099819,53.66995916611803],"type":"Point"}
}