{
  "type": "Feature",
  "properties": {
    "iso:country":"GB",
    "wof:name":"WD6 3FG",
    "wof:placetype":"postalcode"
},
  "geometry": {"coordinates":[-0.31011843807306,51.63953896494216],"type":"Point"}
}