{
  "type": "Feature",
  "properties": {
    "iso:country": "GB",
    "wof:name": "M13 9YG",
    "wof:placetype": "postalcode"
  },
  "geometry": {"coordinates":[-2.228046,53.468664],"type":"Point"}
}
