{
  "type": "Feature",
  "properties": {
    "iso:country":"GB",
    "wof:name":"SA4 4AG",
    "wof:placetype":"postalcode"
},
  "geometry": {"coordinates":[-4.04048010954513,51.66399510306503],"type":"Point"}
}