{
  "type": "Feature",
  "properties": {
    "date:inception_lower":"1993-01-01",
    "date:inception_upper":"1993-01-31",
    "iso:country":"GB",
    "wof:name":"SA4 4AG",
    "wof:placetype":"postalcode"
},
  "geometry": {"coordinates":[-4.04048,51.663995],"type":"Point"}
}