{
  "type": "Feature",
  "properties": {
    "iso:country":"GB",
    "wof:name":"B62 9RR",
    "wof:placetype":"postalcode"
},
  "geometry": {"coordinates":[-2.01999041838062,52.46847133929359],"type":"Point"}
}