{
  "type": "Feature",
  "properties": {
    "iso:country": "GB",
    "wof:name": "AB53 6TF",
    "wof:placetype": "postalcode"
  },
  "geometry": {"coordinates":[-2.191043,57.511404],"type":"Point"}
}
