{
  "type": "Feature",
  "properties": {
    "iso:country":"GB",
    "wof:name":"AB53 6TF",
    "wof:placetype":"postalcode"
},
  "geometry": {"coordinates":[-2.19104279503805,57.51140432108337],"type":"Point"}
}