{
  "type": "Feature",
  "properties": {
    "iso:country":"GB",
    "wof:name":"DD4 6JA",
    "wof:placetype":"postalcode"
},
  "geometry": {"coordinates":[-2.94809372287589,56.46801059775731],"type":"Point"}
}