{
  "type": "Feature",
  "properties": {
    "iso:country":"GB",
    "wof:name":"SS8 7BT",
    "wof:placetype":"postalcode"
},
  "geometry": {"coordinates":[0.59657351616304,51.5163131256333],"type":"Point"}
}