{
  "type": "Feature",
  "properties": {
    "iso:country":"GB",
    "wof:name":"WD24 6NA",
    "wof:placetype":"postalcode"
},
  "geometry": {"coordinates":[-0.40232473995266,51.67476563371279],"type":"Point"}
}