{
  "type": "Feature",
  "properties": {
    "iso:country":"GB",
    "wof:name":"BL1 8JU",
    "wof:placetype":"postalcode"
},
  "geometry": {"coordinates":[-2.43023958609044,53.59547318377034],"type":"Point"}
}