{
  "type": "Feature",
  "properties": {
    "iso:country":"GB",
    "wof:name":"IG3 8AA",
    "wof:placetype":"postalcode"
},
  "geometry": {"coordinates":[0.09294583367306,51.56122104466102],"type":"Point"}
}