{
  "type": "Feature",
  "properties": {
    "iso:country": "GB",
    "wof:name": "S1 2FR",
    "wof:placetype": "postalcode"
  },
  "geometry": {"coordinates":[-1.470341,53.384844],"type":"Point"}
}
