{
  "type": "Feature",
  "properties": {
    "date:inception_lower": "2013-02-01",
    "date:inception_upper": "2013-02-01",
    "iso:country": "GB",
    "wof:name": "KY8 4FW",
    "wof:placetype": "postalcode"
  },
  "geometry": {"coordinates":[-3.021346,56.198058],"type":"Point"}
}
