{
  "type": "Feature",
  "properties": {
    "iso:country": "GB",
    "wof:name": "KY8 4FW",
    "wof:placetype": "postalcode"
  },
  "geometry": {"coordinates":[-3.021346,56.198058],"type":"Point"}
}
