{
  "type": "Feature",
  "properties": {
    "date:inception_lower": "2013-12-01",
    "date:inception_upper": "2013-12-01",
    "iso:country": "GB",
    "wof:name": "B45 8JQ",
    "wof:placetype": "postalcode"
  },
  "geometry": {"coordinates":[-1.991154,52.392201],"type":"Point"}
}
