{
  "type": "Feature",
  "properties": {
    "iso:country":"GB",
    "wof:name":"TD15 2EJ",
    "wof:placetype":"postalcode"
},
  "geometry": {"coordinates":[-2.01464871266691,55.75620360501502],"type":"Point"}
}