{
  "type": "Feature",
  "properties": {
    "iso:country": "GB",
    "wof:name": "TD15 2EJ",
    "wof:placetype": "postalcode"
  },
  "geometry": {"coordinates":[-2.014649,55.756204],"type":"Point"}
}
