{
  "type": "Feature",
  "properties": {
    "date:inception_lower": "2008-06-01",
    "date:inception_upper": "2008-06-01",
    "iso:country": "GB",
    "wof:name": "M11 2HW",
    "wof:placetype": "postalcode"
  },
  "geometry": {"coordinates":[-2.182055,53.475701],"type":"Point"}
}
