{
  "type": "Feature",
  "properties": {
    "iso:country":"GB",
    "wof:name":"M11 2HW",
    "wof:placetype":"postalcode"
},
  "geometry": {"coordinates":[-2.18205518379128,53.47570054284657],"type":"Point"}
}