{
  "type": "Feature",
  "properties": {
    "date:inception_lower": "1993-08-01",
    "date:inception_upper": "1993-08-01",
    "iso:country": "GB",
    "wof:name": "WR4 0DF",
    "wof:placetype": "postalcode"
  },
  "geometry": {"coordinates":[-2.174546,52.196142],"type":"Point"}
}
