{
  "type": "Feature",
  "properties": {
    "iso:country":"GB",
    "wof:name":"WR4 0DF",
    "wof:placetype":"postalcode"
},
  "geometry": {"coordinates":[-2.17456536758881,52.19612978775593],"type":"Point"}
}