{
  "type": "Feature",
  "properties": {
    "iso:country":"GB",
    "wof:name":"NG33 5GY",
    "wof:placetype":"postalcode"
},
  "geometry": {"coordinates":[-0.61655709617123,52.8034152987701],"type":"Point"}
}