{
  "type": "Feature",
  "properties": {
    "date:inception_lower": "1994-12-01",
    "date:inception_upper": "1994-12-01",
    "iso:country": "GB",
    "wof:name": "NG33 5GY",
    "wof:placetype": "postalcode"
  },
  "geometry": {"coordinates":[-0.616557,52.803415],"type":"Point"}
}
