{
  "type": "Feature",
  "properties": {
    "iso:country":"GB",
    "wof:name":"IP1 3ES",
    "wof:placetype":"postalcode"
},
  "geometry": {"coordinates":[1.14776008508386,52.06004407415404],"type":"Point"}
}