{
  "type": "Feature",
  "properties": {
    "date:inception_lower": "2019-08-01",
    "date:inception_upper": "2019-08-01",
    "iso:country": "GB",
    "wof:name": "PR7 6QS",
    "wof:placetype": "postalcode"
  },
  "geometry": {"coordinates":[-2.667547,53.670451],"type":"Point"}
}
