{
  "type": "Feature",
  "properties": {
    "iso:country": "GB",
    "wof:name": "PR7 6QS",
    "wof:placetype": "postalcode"
  },
  "geometry": {"coordinates":[-2.667687,53.670702],"type":"Point"}
}
