{
  "type": "Feature",
  "properties": {
    "iso:country": "GB",
    "wof:name": "TQ11 0FB",
    "wof:placetype": "postalcode"
  },
  "geometry": {"coordinates":[-3.779954,50.480434],"type":"Point"}
}
