{
  "type": "Feature",
  "properties": {
    "iso:country":"GB",
    "wof:name":"TQ11 0FB",
    "wof:placetype":"postalcode"
},
  "geometry": {"coordinates":[-3.7799541426782,50.4804343464719],"type":"Point"}
}