{
  "type": "Feature",
  "properties": {
    "date:inception_lower":"2006-11-01",
    "date:inception_upper":"2006-11-30",
    "iso:country":"GB",
    "wof:name":"TQ11 0FB",
    "wof:placetype":"postalcode"
},
  "geometry": {"coordinates":[-3.779954,50.480434],"type":"Point"}
}