{
  "type": "Feature",
  "properties": {
    "iso:country":"GB",
    "wof:name":"CH5 4WE",
    "wof:placetype":"postalcode"
},
  "geometry": {"coordinates":[-3.07644089561423,53.22072372705662],"type":"Point"}
}