{
  "type": "Feature",
  "properties": {
    "iso:country":"GB",
    "wof:name":"EH55 8PZ",
    "wof:placetype":"postalcode"
},
  "geometry": {"coordinates":[-3.57212728380265,55.85376365050777],"type":"Point"}
}