{
  "type": "Feature",
  "properties": {
    "iso:country": "GB",
    "wof:name": "GL55 6LD",
    "wof:placetype": "postalcode"
  },
  "geometry": {"coordinates":[-1.754067,52.055131],"type":"Point"}
}
