{
  "type": "Feature",
  "properties": {
    "iso:country": "GB",
    "wof:name": "GU6 8US",
    "wof:placetype": "postalcode"
  },
  "geometry": {"coordinates":[-0.503328,51.142616],"type":"Point"}
}
