{
  "type": "Feature",
  "properties": {
    "date:inception_lower": "2019-10-01",
    "date:inception_upper": "2019-10-01",
    "iso:country": "GB",
    "wof:name": "GU6 8US",
    "wof:placetype": "postalcode"
  },
  "geometry": {"coordinates":[-0.504358,51.142611],"type":"Point"}
}
