{
  "type": "Feature",
  "properties": {
    "date:inception_lower": "2004-09-01",
    "date:inception_upper": "2004-09-01",
    "iso:country": "GB",
    "wof:name": "AL1 5JS",
    "wof:placetype": "postalcode"
  },
  "geometry": {"coordinates":[-0.312213,51.745115],"type":"Point"}
}
