{
  "type": "Feature",
  "properties": {
    "iso:country":"GB",
    "wof:name":"AL1 5JS",
    "wof:placetype":"postalcode"
},
  "geometry": {"coordinates":[-0.31225072959858,51.745127503003],"type":"Point"}
}