{
  "type": "Feature",
  "properties": {
    "iso:country":"GB",
    "wof:name":"TF1 6ZU",
    "wof:placetype":"postalcode"
},
  "geometry": {"coordinates":[-2.48829039960253,52.71562071843944],"type":"Point"}
}