{
  "type": "Feature",
  "properties": {
    "date:inception_lower": "1993-01-01",
    "date:inception_upper": "1993-01-01",
    "iso:country": "GB",
    "wof:name": "MK42 9YY",
    "wof:placetype": "postalcode"
  },
  "geometry": {"coordinates":[-0.473558,52.116206],"type":"Point"}
}
