{
  "type": "Feature",
  "properties": {
    "iso:country":"GB",
    "wof:name":"MK42 9YY",
    "wof:placetype":"postalcode"
},
  "geometry": {"coordinates":[-0.47350563842435,52.11622028536615],"type":"Point"}
}