{
  "type": "Feature",
  "properties": {
    "iso:country":"GB",
    "wof:name":"NG18 2DL",
    "wof:placetype":"postalcode"
},
  "geometry": {"coordinates":[-1.17741303721336,53.1500012768044],"type":"Point"}
}