{
  "type": "Feature",
  "properties": {
    "date:inception_lower":"1980-01-01",
    "date:inception_upper":"1980-01-31",
    "iso:country":"GB",
    "wof:name":"NE33 3PT",
    "wof:placetype":"postalcode"
},
  "geometry": {"coordinates":[-1.423712,54.987156],"type":"Point"}
}