{
  "type": "Feature",
  "properties": {
    "date:inception_lower": "1990-02-01",
    "date:inception_upper": "1990-02-01",
    "iso:country": "GB",
    "wof:name": "CR4 1HR",
    "wof:placetype": "postalcode"
  },
  "geometry": {"coordinates":[-0.150868,51.404863],"type":"Point"}
}
