{
  "type": "Feature",
  "properties": {
    "iso:country":"GB",
    "wof:name":"WS4 1RY",
    "wof:placetype":"postalcode"
},
  "geometry": {"coordinates":[-1.94910146211537,52.61896150545962],"type":"Point"}
}