{
  "type": "Feature",
  "properties": {
    "iso:country":"GB",
    "wof:name":"N12 8HQ",
    "wof:placetype":"postalcode"
},
  "geometry": {"coordinates":[-0.18495621885269,51.61333771841613],"type":"Point"}
}