{
  "type": "Feature",
  "properties": {
    "iso:country":"GB",
    "wof:name":"M32 0XP",
    "wof:placetype":"postalcode"
},
  "geometry": {"coordinates":[-2.28748333927062,53.4589993303835],"type":"Point"}
}