{
  "type": "Feature",
  "properties": {
    "date:inception_lower": "2007-02-01",
    "date:inception_upper": "2007-02-01",
    "iso:country": "GB",
    "wof:name": "M32 0XP",
    "wof:placetype": "postalcode"
  },
  "geometry": {"coordinates":[-2.287483,53.458999],"type":"Point"}
}
