{
  "type": "Feature",
  "properties": {
    "date:inception_lower":"1984-02-01",
    "date:inception_upper":"1984-02-29",
    "iso:country":"GB",
    "wof:name":"SW13 0NL",
    "wof:placetype":"postalcode"
},
  "geometry": {"coordinates":[-0.252404,51.472642],"type":"Point"}
}