{
  "type": "Feature",
  "properties": {
    "iso:country":"GB",
    "wof:name":"G46 7BX",
    "wof:placetype":"postalcode"
},
  "geometry": {"coordinates":[-4.30831798308526,55.80372890009152],"type":"Point"}
}