{
  "type": "Feature",
  "properties": {
    "iso:country": "GB",
    "wof:name": "IV17 0NZ",
    "wof:placetype": "postalcode"
  },
  "geometry": {"coordinates":[-4.259336,57.695551],"type":"Point"}
}
