{
  "type": "Feature",
  "properties": {
    "date:inception_lower": "2010-08-01",
    "date:inception_upper": "2010-08-01",
    "iso:country": "GB",
    "wof:name": "IV17 0NZ",
    "wof:placetype": "postalcode"
  },
  "geometry": {"coordinates":[-4.259336,57.695551],"type":"Point"}
}
