{
  "type": "Feature",
  "properties": {
    "iso:country":"GB",
    "wof:name":"NG7 1QD",
    "wof:placetype":"postalcode"
},
  "geometry": {"coordinates":[-1.17374043486239,52.95387333084729],"type":"Point"}
}