{
  "type": "Feature",
  "properties": {
    "iso:country": "GB",
    "wof:name": "SL9 8SB",
    "wof:placetype": "postalcode"
  },
  "geometry": {"coordinates":[-0.564618,51.599917],"type":"Point"}
}
