{
  "type": "Feature",
  "properties": {
    "date:inception_lower": "1980-01-01",
    "date:inception_upper": "1980-01-01",
    "iso:country": "GB",
    "wof:name": "SL9 8SB",
    "wof:placetype": "postalcode"
  },
  "geometry": {"coordinates":[-0.564618,51.599917],"type":"Point"}
}
