{
  "type": "Feature",
  "properties": {
    "iso:country":"GB",
    "wof:name":"SL9 8SB",
    "wof:placetype":"postalcode"
},
  "geometry": {"coordinates":[-0.56461810584441,51.5999172816809],"type":"Point"}
}