{
  "type": "Feature",
  "properties": {
    "iso:country": "GB",
    "wof:name": "S25 1XZ",
    "wof:placetype": "postalcode"
  },
  "geometry": {"coordinates":[-1.235111,53.397286],"type":"Point"}
}
