{
  "type": "Feature",
  "properties": {
    "iso:country":"GB",
    "wof:name":"S25 1XZ",
    "wof:placetype":"postalcode"
},
  "geometry": {"coordinates":[-1.23511137043433,53.39728588315529],"type":"Point"}
}