{
  "type": "Feature",
  "properties": {
    "iso:country": "GB",
    "wof:name": "IV30 1TG",
    "wof:placetype": "postalcode"
  },
  "geometry": {"coordinates":[-3.323213,57.644445],"type":"Point"}
}
