{
  "type": "Feature",
  "properties": {
    "iso:country":"GB",
    "wof:name":"LE3 8QZ",
    "wof:placetype":"postalcode"
},
  "geometry": {"coordinates":[-1.2074334358712,52.64573803195177],"type":"Point"}
}