{
  "type": "Feature",
  "properties": {
    "iso:country": "GB",
    "wof:name": "LE3 8QZ",
    "wof:placetype": "postalcode"
  },
  "geometry": {"coordinates":[-1.207433,52.645738],"type":"Point"}
}
