{
  "type": "Feature",
  "properties": {
    "date:inception_lower":"1987-04-01",
    "date:inception_upper":"1987-04-30",
    "iso:country":"GB",
    "wof:name":"LE3 8QZ",
    "wof:placetype":"postalcode"
},
  "geometry": {"coordinates":[-1.207433,52.645738],"type":"Point"}
}