{
  "type": "Feature",
  "properties": {
    "iso:country":"GB",
    "wof:name":"TS17 9EJ",
    "wof:placetype":"postalcode"
},
  "geometry": {"coordinates":[-1.28854878349699,54.54579424578938],"type":"Point"}
}