{
  "type": "Feature",
  "properties": {
    "iso:country":"GB",
    "wof:name":"S11 8UD",
    "wof:placetype":"postalcode"
},
  "geometry": {"coordinates":[-1.50367157184288,53.36558031146726],"type":"Point"}
}