{
  "type": "Feature",
  "properties": {
    "iso:country": "GB",
    "wof:name": "DY10 4EG",
    "wof:placetype": "postalcode"
  },
  "geometry": {"coordinates":[-2.227438,52.373319],"type":"Point"}
}
