{
  "type": "Feature",
  "properties": {
    "iso:country":"GB",
    "wof:name":"LL13 0PJ",
    "wof:placetype":"postalcode"
},
  "geometry": {"coordinates":[-2.96122398355495,53.03549514684936],"type":"Point"}
}