{
  "type": "Feature",
  "properties": {
    "date:inception_lower":"1997-12-01",
    "date:inception_upper":"1997-12-31",
    "iso:country":"GB",
    "wof:name":"LL13 0PJ",
    "wof:placetype":"postalcode"
},
  "geometry": {"coordinates":[-2.961224,53.035495],"type":"Point"}
}