{
  "type": "Feature",
  "properties": {
    "iso:country":"GB",
    "wof:name":"NE65 0YF",
    "wof:placetype":"postalcode"
},
  "geometry": {"coordinates":[-1.65999728866622,55.35653217137305],"type":"Point"}
}