{
  "type": "Feature",
  "properties": {
    "date:inception_lower": "2008-10-01",
    "date:inception_upper": "2008-10-01",
    "iso:country": "GB",
    "wof:name": "NE65 0YF",
    "wof:placetype": "postalcode"
  },
  "geometry": {"coordinates":[-1.66028,55.356544],"type":"Point"}
}
