{
  "type": "Feature",
  "properties": {
    "iso:country":"GB",
    "wof:name":"SS7 5RH",
    "wof:placetype":"postalcode"
},
  "geometry": {"coordinates":[0.55223534081166,51.56452005823635],"type":"Point"}
}