{
  "type": "Feature",
  "properties": {
    "iso:country": "GB",
    "wof:name": "MK17 7BG",
    "wof:placetype": "postalcode"
  },
  "geometry": {"coordinates":[-0.649828,52.034899],"type":"Point"}
}
