{
  "type": "Feature",
  "properties": {
    "date:inception_lower": "1980-01-01",
    "date:inception_upper": "1980-01-01",
    "iso:country": "GB",
    "wof:name": "GL53 8JR",
    "wof:placetype": "postalcode"
  },
  "geometry": {"coordinates":[-2.053067,51.881548],"type":"Point"}
}
