{
  "type": "Feature",
  "properties": {
    "iso:country": "GB",
    "wof:name": "OL6 0FZ",
    "wof:placetype": "postalcode"
  },
  "geometry": {"coordinates":[-2.094211,53.486488],"type":"Point"}
}
