{
  "type": "Feature",
  "properties": {
    "date:inception_lower": "1980-01-01",
    "date:inception_upper": "1980-01-01",
    "iso:country": "GB",
    "wof:name": "IP12 2PT",
    "wof:placetype": "postalcode"
  },
  "geometry": {"coordinates":[1.363275,52.102537],"type":"Point"}
}
