{
  "type": "Feature",
  "properties": {
    "iso:country":"GB",
    "wof:name":"IP12 2PT",
    "wof:placetype":"postalcode"
},
  "geometry": {"coordinates":[1.36324421392659,52.10252064921885],"type":"Point"}
}