{
  "type": "Feature",
  "properties": {
    "iso:country":"GB",
    "wof:name":"EH52 5DF",
    "wof:placetype":"postalcode"
},
  "geometry": {"coordinates":[-3.50199217337894,55.92940325153519],"type":"Point"}
}