{
  "type": "Feature",
  "properties": {
    "date:inception_lower": "1980-01-01",
    "date:inception_upper": "1980-01-01",
    "iso:country": "GB",
    "wof:name": "ST16 3UT",
    "wof:placetype": "postalcode"
  },
  "geometry": {"coordinates":[-2.100817,52.807261],"type":"Point"}
}
