{
  "type": "Feature",
  "properties": {
    "iso:country": "GB",
    "wof:name": "DT11 8UU",
    "wof:placetype": "postalcode"
  },
  "geometry": {"coordinates":[-2.134089,50.885694],"type":"Point"}
}
