{
  "type": "Feature",
  "properties": {
    "iso:country":"GB",
    "wof:name":"DT11 8UU",
    "wof:placetype":"postalcode"
},
  "geometry": {"coordinates":[-2.1340895383346,50.88569422391143],"type":"Point"}
}