{
  "type": "Feature",
  "properties": {
    "date:inception_lower": "2013-12-01",
    "date:inception_upper": "2013-12-01",
    "iso:country": "GB",
    "wof:name": "BN14 9FG",
    "wof:placetype": "postalcode"
  },
  "geometry": {"coordinates":[-0.378521,50.83755],"type":"Point"}
}
