{
  "type": "Feature",
  "properties": {
    "iso:country":"GB",
    "wof:name":"BN14 9FG",
    "wof:placetype":"postalcode"
},
  "geometry": {"coordinates":[-0.37852118142394,50.83755047924465],"type":"Point"}
}