{
  "type": "Feature",
  "properties": {
    "date:inception_lower":"1990-02-01",
    "date:inception_upper":"1990-02-28",
    "iso:country":"GB",
    "wof:name":"SG14 3HZ",
    "wof:placetype":"postalcode"
},
  "geometry": {"coordinates":[-0.076894,51.808045],"type":"Point"}
}