{
  "type": "Feature",
  "properties": {
    "iso:country":"GB",
    "wof:name":"CR8 3NB",
    "wof:placetype":"postalcode"
},
  "geometry": {"coordinates":[-0.13359547792302,51.3434388709323],"type":"Point"}
}