{
  "type": "Feature",
  "properties": {
    "iso:country":"GB",
    "wof:name":"WA5 2BG",
    "wof:placetype":"postalcode"
},
  "geometry": {"coordinates":[-2.6547127706554,53.38773547331605],"type":"Point"}
}