{
  "type": "Feature",
  "properties": {
    "date:inception_lower":"1980-01-01",
    "date:inception_upper":"1980-01-31",
    "iso:country":"GB",
    "wof:name":"WA5 2BG",
    "wof:placetype":"postalcode"
},
  "geometry": {"coordinates":[-2.654713,53.387735],"type":"Point"}
}