{
  "type": "Feature",
  "properties": {
    "date:inception_lower":"2007-07-01",
    "date:inception_upper":"2007-07-31",
    "iso:country":"GB",
    "wof:name":"SR1 2BJ",
    "wof:placetype":"postalcode"
},
  "geometry": {"coordinates":[-1.368524,54.90781],"type":"Point"}
}