{
  "type": "Feature",
  "properties": {
    "iso:country":"GB",
    "wof:name":"DN10 6PD",
    "wof:placetype":"postalcode"
},
  "geometry": {"coordinates":[-1.01904976593802,53.43617485693255],"type":"Point"}
}