{
  "type": "Feature",
  "properties": {
    "iso:country": "GB",
    "wof:name": "SE9 2RJ",
    "wof:placetype": "postalcode"
  },
  "geometry": {"coordinates":[0.083015,51.458754],"type":"Point"}
}
