{
  "type": "Feature",
  "properties": {
    "iso:country":"GB",
    "wof:name":"SW16 3EF",
    "wof:placetype":"postalcode"
},
  "geometry": {"coordinates":[-0.1117445520081,51.41983252325343],"type":"Point"}
}