{
  "type": "Feature",
  "properties": {
    "iso:country": "GB",
    "wof:name": "TS15 0DJ",
    "wof:placetype": "postalcode"
  },
  "geometry": {"coordinates":[-1.282341,54.450206],"type":"Point"}
}
