{
  "type": "Feature",
  "properties": {
    "iso:country":"GB",
    "wof:name":"AL4 9DX",
    "wof:placetype":"postalcode"
},
  "geometry": {"coordinates":[-0.29981795909662,51.78150069963026],"type":"Point"}
}