{
  "type": "Feature",
  "properties": {
    "iso:country": "GB",
    "wof:name": "YO8 5SB",
    "wof:placetype": "postalcode"
  },
  "geometry": {"coordinates":[-0.964534,53.824745],"type":"Point"}
}
