{
  "type": "Feature",
  "properties": {
    "iso:country":"GB",
    "wof:name":"YO8 5SB",
    "wof:placetype":"postalcode"
},
  "geometry": {"coordinates":[-0.96456584162406,53.82441997812442],"type":"Point"}
}