{
  "type": "Feature",
  "properties": {
    "iso:country": "GB",
    "wof:name": "CH7 4ER",
    "wof:placetype": "postalcode"
  },
  "geometry": {"coordinates":[-3.151888,53.141595],"type":"Point"}
}
