{
  "type": "Feature",
  "properties": {
    "iso:country":"GB",
    "wof:name":"CH7 4ER",
    "wof:placetype":"postalcode"
},
  "geometry": {"coordinates":[-3.15188765977534,53.14159467902601],"type":"Point"}
}