{
  "type": "Feature",
  "properties": {
    "date:inception_lower": "1980-01-01",
    "date:inception_upper": "1980-01-01",
    "iso:country": "GB",
    "wof:name": "CH7 4ER",
    "wof:placetype": "postalcode"
  },
  "geometry": {"coordinates":[-3.151888,53.141595],"type":"Point"}
}
