{
  "type": "Feature",
  "properties": {
    "iso:country":"GB",
    "wof:name":"S9 4GF",
    "wof:placetype":"postalcode"
},
  "geometry": {"coordinates":[-1.41730955686339,53.37859236869377],"type":"Point"}
}