{
  "type": "Feature",
  "properties": {
    "date:inception_lower":"2000-12-01",
    "date:inception_upper":"2000-12-31",
    "iso:country":"GB",
    "wof:name":"TF2 8SS",
    "wof:placetype":"postalcode"
},
  "geometry": {"coordinates":[-2.419284,52.71637],"type":"Point"}
}