{
  "type": "Feature",
  "properties": {
    "iso:country":"GB",
    "wof:name":"TF2 8SS",
    "wof:placetype":"postalcode"
},
  "geometry": {"coordinates":[-2.41928400731857,52.71637038583234],"type":"Point"}
}