{
  "type": "Feature",
  "properties": {
    "date:inception_lower": "1980-01-01",
    "date:inception_upper": "1980-01-01",
    "iso:country": "GB",
    "wof:name": "BA21 4RB",
    "wof:placetype": "postalcode"
  },
  "geometry": {"coordinates":[-2.623553,50.949147],"type":"Point"}
}
