{
  "type": "Feature",
  "properties": {
    "iso:country":"GB",
    "wof:name":"KA11 4AN",
    "wof:placetype":"postalcode"
},
  "geometry": {"coordinates":[-4.61589064806752,55.60865502705166],"type":"Point"}
}