{
  "type": "Feature",
  "properties": {
    "iso:country":"GB",
    "wof:name":"B43 5DN",
    "wof:placetype":"postalcode"
},
  "geometry": {"coordinates":[-1.95273196764124,52.53905260507805],"type":"Point"}
}