{
  "type": "Feature",
  "properties": {
    "iso:country": "GB",
    "wof:name": "NP20 6JZ",
    "wof:placetype": "postalcode"
  },
  "geometry": {"coordinates":[-3.003721,51.615043],"type":"Point"}
}
