{
  "type": "Feature",
  "properties": {
    "iso:country": "GB",
    "wof:name": "SW1V 2AR",
    "wof:placetype": "postalcode"
  },
  "geometry": {"coordinates":[-0.139974,51.491451],"type":"Point"}
}
