{
  "type": "Feature",
  "properties": {
    "iso:country":"GB",
    "wof:name":"NE3 1UA",
    "wof:placetype":"postalcode"
},
  "geometry": {"coordinates":[-1.61923331244062,55.0095992901079],"type":"Point"}
}