{
  "type": "Feature",
  "properties": {
    "date:inception_lower": "1980-01-01",
    "date:inception_upper": "1980-01-01",
    "iso:country": "GB",
    "wof:name": "LN6 7NA",
    "wof:placetype": "postalcode"
  },
  "geometry": {"coordinates":[-0.569642,53.208557],"type":"Point"}
}
