{
  "type": "Feature",
  "properties": {
    "iso:country":"GB",
    "wof:name":"CF42 5BA",
    "wof:placetype":"postalcode"
},
  "geometry": {"coordinates":[-3.52373154197826,51.66825995709396],"type":"Point"}
}