{
  "type": "Feature",
  "properties": {
    "iso:country": "GB",
    "wof:name": "CF42 5BA",
    "wof:placetype": "postalcode"
  },
  "geometry": {"coordinates":[-3.523732,51.66826],"type":"Point"}
}
