{
  "type": "Feature",
  "properties": {
    "iso:country":"GB",
    "wof:name":"L12 1LQ",
    "wof:placetype":"postalcode"
},
  "geometry": {"coordinates":[-2.90659325972996,53.42240301643802],"type":"Point"}
}