{
  "type": "Feature",
  "properties": {
    "iso:country": "GB",
    "wof:name": "CM7 5LS",
    "wof:placetype": "postalcode"
  },
  "geometry": {"coordinates":[0.560348,51.898675],"type":"Point"}
}
