{
  "type": "Feature",
  "properties": {
    "iso:country":"GB",
    "wof:name":"HR1 2QQ",
    "wof:placetype":"postalcode"
},
  "geometry": {"coordinates":[-2.70956215862848,52.05259318009529],"type":"Point"}
}