{
  "type": "Feature",
  "properties": {
    "iso:country":"GB",
    "wof:name":"LS25 1EB",
    "wof:placetype":"postalcode"
},
  "geometry": {"coordinates":[-1.39015201175097,53.79283219745729],"type":"Point"}
}