{
  "type": "Feature",
  "properties": {
    "iso:country":"GB",
    "wof:name":"WF5 8QG",
    "wof:placetype":"postalcode"
},
  "geometry": {"coordinates":[-1.58996131334512,53.68282198738027],"type":"Point"}
}