{
  "type": "Feature",
  "properties": {
    "iso:country":"GB",
    "wof:name":"M41 8UW",
    "wof:placetype":"postalcode"
},
  "geometry": {"coordinates":[-2.38721613909252,53.4508435818673],"type":"Point"}
}