{
  "type": "Feature",
  "properties": {
    "date:inception_lower": "1980-01-01",
    "date:inception_upper": "1980-01-01",
    "iso:country": "GB",
    "wof:name": "DN22 9LQ",
    "wof:placetype": "postalcode"
  },
  "geometry": {"coordinates":[-0.903227,53.361443],"type":"Point"}
}
