{
  "type": "Feature",
  "properties": {
    "iso:country":"GB",
    "wof:name":"SK15 2HR",
    "wof:placetype":"postalcode"
},
  "geometry": {"coordinates":[-2.05401125555554,53.48069901898153],"type":"Point"}
}