{
  "type": "Feature",
  "properties": {
    "date:inception_lower": "1980-01-01",
    "date:inception_upper": "1980-01-01",
    "iso:country": "GB",
    "wof:name": "SK15 2HR",
    "wof:placetype": "postalcode"
  },
  "geometry": {"coordinates":[-2.054011,53.480699],"type":"Point"}
}
