{
  "type": "Feature",
  "properties": {
    "iso:country": "GB",
    "wof:name": "TA19 9NS",
    "wof:placetype": "postalcode"
  },
  "geometry": {"coordinates":[-2.98316,50.946189],"type":"Point"}
}
