{
  "type": "Feature",
  "properties": {
    "iso:country":"GB",
    "wof:name":"TA19 9NS",
    "wof:placetype":"postalcode"
},
  "geometry": {"coordinates":[-2.98314932073872,50.94610641348545],"type":"Point"}
}