{
  "type": "Feature",
  "properties": {
    "iso:country": "GB",
    "wof:name": "PE31 7LE",
    "wof:placetype": "postalcode"
  },
  "geometry": {"coordinates":[0.494174,52.897975],"type":"Point"}
}
