{
  "type": "Feature",
  "properties": {
    "iso:country":"GB",
    "wof:name":"PE31 7LE",
    "wof:placetype":"postalcode"
},
  "geometry": {"coordinates":[0.49417373544457,52.89797525069695],"type":"Point"}
}