{
  "type": "Feature",
  "properties": {
    "iso:country":"GB",
    "wof:name":"B29 4BS",
    "wof:placetype":"postalcode"
},
  "geometry": {"coordinates":[-1.95800626981673,52.43433966516533],"type":"Point"}
}