{
  "type": "Feature",
  "properties": {
    "iso:country": "GB",
    "wof:name": "PE32 2AJ",
    "wof:placetype": "postalcode"
  },
  "geometry": {"coordinates":[0.68955,52.703158],"type":"Point"}
}
