{
  "type": "Feature",
  "properties": {
    "date:inception_lower": "2009-12-01",
    "date:inception_upper": "2009-12-01",
    "iso:country": "GB",
    "wof:name": "E14 3GP",
    "wof:placetype": "postalcode"
  },
  "geometry": {"coordinates":[-0.025233,51.492525],"type":"Point"}
}
