{
  "type": "Feature",
  "properties": {
    "iso:country":"GB",
    "wof:name":"E14 3GP",
    "wof:placetype":"postalcode"
},
  "geometry": {"coordinates":[-0.0252328723857,51.49252471730814],"type":"Point"}
}