{
  "type": "Feature",
  "properties": {
    "iso:country": "GB",
    "wof:name": "LE7 7JA",
    "wof:placetype": "postalcode"
  },
  "geometry": {"coordinates":[-1.163279,52.691437],"type":"Point"}
}
