{
  "type": "Feature",
  "properties": {
    "iso:country":"GB",
    "wof:name":"LE7 7JA",
    "wof:placetype":"postalcode"
},
  "geometry": {"coordinates":[-1.16306083583277,52.69156032535255],"type":"Point"}
}