{
  "type": "Feature",
  "properties": {
    "date:inception_lower":"2010-02-01",
    "date:inception_upper":"2010-02-28",
    "iso:country":"GB",
    "wof:name":"M8 5EL",
    "wof:placetype":"postalcode"
},
  "geometry": {"coordinates":[-2.24484,53.513248],"type":"Point"}
}