{
  "type": "Feature",
  "properties": {
    "iso:country": "GB",
    "wof:name": "M8 5EL",
    "wof:placetype": "postalcode"
  },
  "geometry": {"coordinates":[-2.24484,53.513248],"type":"Point"}
}
