{
  "type": "Feature",
  "properties": {
    "iso:country":"GB",
    "wof:name":"OL12 9LG",
    "wof:placetype":"postalcode"
},
  "geometry": {"coordinates":[-2.13314157919115,53.64600394138628],"type":"Point"}
}