{
  "type": "Feature",
  "properties": {
    "date:inception_lower": "1980-01-01",
    "date:inception_upper": "1980-01-01",
    "iso:country": "GB",
    "wof:name": "OL12 9LG",
    "wof:placetype": "postalcode"
  },
  "geometry": {"coordinates":[-2.133065,53.646065],"type":"Point"}
}
