{
  "type": "Feature",
  "properties": {
    "date:inception_lower":"1980-01-01",
    "date:inception_upper":"1980-01-31",
    "iso:country":"GB",
    "wof:name":"IP22 2EH",
    "wof:placetype":"postalcode"
},
  "geometry": {"coordinates":[1.078357,52.435588],"type":"Point"}
}