{
  "type": "Feature",
  "properties": {
    "iso:country": "GB",
    "wof:name": "IP22 2EH",
    "wof:placetype": "postalcode"
  },
  "geometry": {"coordinates":[1.078357,52.435588],"type":"Point"}
}
