{
  "type": "Feature",
  "properties": {
    "date:inception_lower": "1980-01-01",
    "date:inception_upper": "1980-01-01",
    "iso:country": "GB",
    "wof:name": "IP22 2EH",
    "wof:placetype": "postalcode"
  },
  "geometry": {"coordinates":[1.079545,52.434733],"type":"Point"}
}
