{
  "type": "Feature",
  "properties": {
    "iso:country":"GB",
    "wof:name":"IP22 2EH",
    "wof:placetype":"postalcode"
},
  "geometry": {"coordinates":[1.07835723342268,52.43558813114644],"type":"Point"}
}