{
  "type": "Feature",
  "properties": {
    "iso:country":"GB",
    "wof:name":"PO30 1HD",
    "wof:placetype":"postalcode"
},
  "geometry": {"coordinates":[-1.2924834822804,50.69447663797344],"type":"Point"}
}