{
  "type": "Feature",
  "properties": {
    "iso:country": "GB",
    "wof:name": "PO30 1HD",
    "wof:placetype": "postalcode"
  },
  "geometry": {"coordinates":[-1.292815,50.694387],"type":"Point"}
}
