{
  "type": "Feature",
  "properties": {
    "iso:country":"GB",
    "wof:name":"PE9 1HJ",
    "wof:placetype":"postalcode"
},
  "geometry": {"coordinates":[-0.48368814027128,52.66120006939052],"type":"Point"}
}