{
  "type": "Feature",
  "properties": {
    "iso:country":"GB",
    "wof:name":"YO30 6ND",
    "wof:placetype":"postalcode"
},
  "geometry": {"coordinates":[-1.09757418789724,53.97406798854749],"type":"Point"}
}