{
  "type": "Feature",
  "properties": {
    "iso:country":"GB",
    "wof:name":"LS21 2LW",
    "wof:placetype":"postalcode"
},
  "geometry": {"coordinates":[-1.62813459829918,53.93647085677942],"type":"Point"}
}