{
  "type": "Feature",
  "properties": {
    "iso:country": "GB",
    "wof:name": "G65 0EH",
    "wof:placetype": "postalcode"
  },
  "geometry": {"coordinates":[-4.043267,55.974868],"type":"Point"}
}
