{
  "type": "Feature",
  "properties": {
    "iso:country":"GB",
    "wof:name":"G65 0EH",
    "wof:placetype":"postalcode"
},
  "geometry": {"coordinates":[-4.04326684216717,55.97486791140479],"type":"Point"}
}