{
  "type": "Feature",
  "properties": {
    "date:inception_lower":"2006-05-01",
    "date:inception_upper":"2006-05-31",
    "iso:country":"GB",
    "wof:name":"TA1 1TF",
    "wof:placetype":"postalcode"
},
  "geometry": {"coordinates":[-3.093714,51.016569],"type":"Point"}
}