{
  "type": "Feature",
  "properties": {
    "iso:country": "GB",
    "wof:name": "DA4 0JX",
    "wof:placetype": "postalcode"
  },
  "geometry": {"coordinates":[0.237857,51.370511],"type":"Point"}
}
