{
  "type": "Feature",
  "properties": {
    "iso:country":"GB",
    "wof:name":"DA4 0JX",
    "wof:placetype":"postalcode"
},
  "geometry": {"coordinates":[0.23785657276119,51.37051066614023],"type":"Point"}
}