{
  "type": "Feature",
  "properties": {
    "iso:country":"GB",
    "wof:name":"GL55 6SZ",
    "wof:placetype":"postalcode"
},
  "geometry": {"coordinates":[-1.75941787415466,52.09351400675485],"type":"Point"}
}