{
  "type": "Feature",
  "properties": {
    "date:inception_lower": "2003-03-01",
    "date:inception_upper": "2003-03-01",
    "iso:country": "GB",
    "wof:name": "WS7 4RZ",
    "wof:placetype": "postalcode"
  },
  "geometry": {"coordinates":[-1.925059,52.677076],"type":"Point"}
}
