{
  "type": "Feature",
  "properties": {
    "date:inception_lower": "1980-01-01",
    "date:inception_upper": "1980-01-01",
    "iso:country": "GB",
    "wof:name": "B27 7BU",
    "wof:placetype": "postalcode"
  },
  "geometry": {"coordinates":[-1.821061,52.439363],"type":"Point"}
}
