{
  "type": "Feature",
  "properties": {
    "iso:country":"GB",
    "wof:name":"PR4 5DG",
    "wof:placetype":"postalcode"
},
  "geometry": {"coordinates":[-2.76795654219943,53.72408652338562],"type":"Point"}
}