{
  "type": "Feature",
  "properties": {
    "date:inception_lower": "2014-09-01",
    "date:inception_upper": "2014-09-01",
    "iso:country": "GB",
    "wof:name": "PR4 5DG",
    "wof:placetype": "postalcode"
  },
  "geometry": {"coordinates":[-2.767956,53.724087],"type":"Point"}
}
