{
  "type": "Feature",
  "properties": {
    "iso:country": "GB",
    "wof:name": "IP3 9HH",
    "wof:placetype": "postalcode"
  },
  "geometry": {"coordinates":[1.189575,52.038098],"type":"Point"}
}
