{
  "type": "Feature",
  "properties": {
    "iso:country":"GB",
    "wof:name":"LE1 5XX",
    "wof:placetype":"postalcode"
},
  "geometry": {"coordinates":[-1.1358894639471,52.63040459067442],"type":"Point"}
}