{
  "type": "Feature",
  "properties": {
    "iso:country":"GB",
    "wof:name":"HU15 2NJ",
    "wof:placetype":"postalcode"
},
  "geometry": {"coordinates":[-0.64912279464515,53.77968320925582],"type":"Point"}
}