{
  "type": "Feature",
  "properties": {
    "date:inception_lower": "1983-03-01",
    "date:inception_upper": "1983-03-01",
    "iso:country": "GB",
    "wof:name": "CB10 2SX",
    "wof:placetype": "postalcode"
  },
  "geometry": {"coordinates":[0.339893,52.010529],"type":"Point"}
}
