{
  "type": "Feature",
  "properties": {
    "iso:country": "GB",
    "wof:name": "CB10 2SX",
    "wof:placetype": "postalcode"
  },
  "geometry": {"coordinates":[0.339893,52.010529],"type":"Point"}
}
