{
  "type": "Feature",
  "properties": {
    "date:inception_lower": "2015-07-01",
    "date:inception_upper": "2015-07-01",
    "iso:country": "GB",
    "wof:name": "NW7 1FX",
    "wof:placetype": "postalcode"
  },
  "geometry": {"coordinates":[-0.210343,51.614298],"type":"Point"}
}
