{
  "type": "Feature",
  "properties": {
    "iso:country":"GB",
    "wof:name":"NW7 1FX",
    "wof:placetype":"postalcode"
},
  "geometry": {"coordinates":[-0.21160515908989,51.61406146509191],"type":"Point"}
}