{
  "type": "Feature",
  "properties": {
    "date:inception_lower":"2015-07-01",
    "date:inception_upper":"2015-07-31",
    "iso:country":"GB",
    "wof:name":"NW7 1FX",
    "wof:placetype":"postalcode"
},
  "geometry": {"coordinates":[-0.210576,51.614256],"type":"Point"}
}