{
  "type": "Feature",
  "properties": {
    "iso:country": "GB",
    "wof:name": "WA9 1DH",
    "wof:placetype": "postalcode"
  },
  "geometry": {"coordinates":[-2.71811,53.455973],"type":"Point"}
}
