{
  "type": "Feature",
  "properties": {
    "date:inception_lower":"1980-01-01",
    "date:inception_upper":"1980-01-31",
    "iso:country":"GB",
    "wof:name":"WA9 1DH",
    "wof:placetype":"postalcode"
},
  "geometry": {"coordinates":[-2.71811,53.455973],"type":"Point"}
}