{
  "type": "Feature",
  "properties": {
    "iso:country":"GB",
    "wof:name":"GU35 0QW",
    "wof:placetype":"postalcode"
},
  "geometry": {"coordinates":[-0.85245773706881,51.15655660038401],"type":"Point"}
}