{
  "type": "Feature",
  "properties": {
    "date:inception_lower": "2004-03-01",
    "date:inception_upper": "2004-03-01",
    "iso:country": "GB",
    "wof:name": "GU35 0QW",
    "wof:placetype": "postalcode"
  },
  "geometry": {"coordinates":[-0.852458,51.156557],"type":"Point"}
}
