{
  "type": "Feature",
  "properties": {
    "iso:country":"GB",
    "wof:name":"NN4 8LH",
    "wof:placetype":"postalcode"
},
  "geometry": {"coordinates":[-0.90673008857282,52.22422915183219],"type":"Point"}
}