{
  "type": "Feature",
  "properties": {
    "date:inception_lower": "1980-01-01",
    "date:inception_upper": "1980-01-01",
    "iso:country": "GB",
    "wof:name": "HR9 6LQ",
    "wof:placetype": "postalcode"
  },
  "geometry": {"coordinates":[-2.647969,51.920835],"type":"Point"}
}
