{
  "type": "Feature",
  "properties": {
    "iso:country":"GB",
    "wof:name":"HR9 6LQ",
    "wof:placetype":"postalcode"
},
  "geometry": {"coordinates":[-2.64800559953337,51.92149262495751],"type":"Point"}
}