{
  "type": "Feature",
  "properties": {
    "date:inception_lower":"1993-01-01",
    "date:inception_upper":"1993-01-31",
    "iso:country":"GB",
    "wof:name":"SK17 9EG",
    "wof:placetype":"postalcode"
},
  "geometry": {"coordinates":[-1.911098,53.250838],"type":"Point"}
}