{
  "type": "Feature",
  "properties": {
    "iso:country":"GB",
    "wof:name":"ST7 4JL",
    "wof:placetype":"postalcode"
},
  "geometry": {"coordinates":[-2.20865377304905,53.0956307443042],"type":"Point"}
}