{
  "type": "Feature",
  "properties": {
    "iso:country": "GB",
    "wof:name": "DN35 8LT",
    "wof:placetype": "postalcode"
  },
  "geometry": {"coordinates":[-0.031234,53.56049],"type":"Point"}
}
