{
  "type": "Feature",
  "properties": {
    "iso:country":"GB",
    "wof:name":"DN35 8LT",
    "wof:placetype":"postalcode"
},
  "geometry": {"coordinates":[-0.03123447587761,53.56049032684387],"type":"Point"}
}