{
  "type": "Feature",
  "properties": {
    "iso:country":"GB",
    "wof:name":"EN2 7AJ",
    "wof:placetype":"postalcode"
},
  "geometry": {"coordinates":[-0.09647758592269,51.6539757231541],"type":"Point"}
}