{
  "type": "Feature",
  "properties": {
    "iso:country":"GB",
    "wof:name":"N7 0BU",
    "wof:placetype":"postalcode"
},
  "geometry": {"coordinates":[-0.13117793931799,51.55117453924166],"type":"Point"}
}