{
  "type": "Feature",
  "properties": {
    "iso:country":"GB",
    "wof:name":"SP6 1PQ",
    "wof:placetype":"postalcode"
},
  "geometry": {"coordinates":[-1.82405286112735,50.93176130130681],"type":"Point"}
}