{
  "type": "Feature",
  "properties": {
    "date:inception_lower":"1980-01-01",
    "date:inception_upper":"1980-01-31",
    "iso:country":"GB",
    "wof:name":"SP6 1PQ",
    "wof:placetype":"postalcode"
},
  "geometry": {"coordinates":[-1.823988,50.931826],"type":"Point"}
}