{
  "type": "Feature",
  "properties": {
    "iso:country": "GB",
    "wof:name": "SP6 1PQ",
    "wof:placetype": "postalcode"
  },
  "geometry": {"coordinates":[-1.823988,50.931826],"type":"Point"}
}
