{
  "type": "Feature",
  "properties": {
    "iso:country":"GB",
    "wof:name":"DH9 0TE",
    "wof:placetype":"postalcode"
},
  "geometry": {"coordinates":[-1.70245832625965,54.86860259644543],"type":"Point"}
}