{
  "type": "Feature",
  "properties": {
    "iso:country":"GB",
    "wof:name":"SW19 5NE",
    "wof:placetype":"postalcode"
},
  "geometry": {"coordinates":[-0.22388672794133,51.43538015692869],"type":"Point"}
}