{
  "type": "Feature",
  "properties": {
    "iso:country":"GB",
    "wof:name":"WF9 4TJ",
    "wof:placetype":"postalcode"
},
  "geometry": {"coordinates":[-1.34230125074277,53.60834667017811],"type":"Point"}
}