{
  "type": "Feature",
  "properties": {
    "iso:country": "GB",
    "wof:name": "WF9 4TJ",
    "wof:placetype": "postalcode"
  },
  "geometry": {"coordinates":[-1.342301,53.608347],"type":"Point"}
}
