{
  "type": "Feature",
  "properties": {
    "iso:country": "GB",
    "wof:name": "SL4 1BN",
    "wof:placetype": "postalcode"
  },
  "geometry": {"coordinates":[-0.605732,51.480307],"type":"Point"}
}
