{
  "type": "Feature",
  "properties": {
    "iso:country":"GB",
    "wof:name":"SL4 1BN",
    "wof:placetype":"postalcode"
},
  "geometry": {"coordinates":[-0.6057145667604,51.4804053230834],"type":"Point"}
}