{
  "type": "Feature",
  "properties": {
    "date:inception_lower": "1980-01-01",
    "date:inception_upper": "1980-01-01",
    "iso:country": "GB",
    "wof:name": "SP8 5BQ",
    "wof:placetype": "postalcode"
  },
  "geometry": {"coordinates":[-2.325718,51.074577],"type":"Point"}
}
