{
  "type": "Feature",
  "properties": {
    "iso:country":"GB",
    "wof:name":"SP8 5BQ",
    "wof:placetype":"postalcode"
},
  "geometry": {"coordinates":[-2.32571762807293,51.0745773005814],"type":"Point"}
}