{
  "type": "Feature",
  "properties": {
    "iso:country":"GB",
    "wof:name":"SW1X 0BD",
    "wof:placetype":"postalcode"
},
  "geometry": {"coordinates":[-0.16222473181569,51.49659509422567],"type":"Point"}
}