{
  "type": "Feature",
  "properties": {
    "date:inception_lower": "2016-05-01",
    "date:inception_upper": "2016-05-01",
    "iso:country": "GB",
    "wof:name": "B66 1AR",
    "wof:placetype": "postalcode"
  },
  "geometry": {"coordinates":[-1.972488,52.50654],"type":"Point"}
}
