{
  "type": "Feature",
  "properties": {
    "iso:country":"GB",
    "wof:name":"BS21 7XE",
    "wof:placetype":"postalcode"
},
  "geometry": {"coordinates":[-2.87041947152645,51.42876566014142],"type":"Point"}
}