{
  "type": "Feature",
  "properties": {
    "date:inception_lower": "2020-11-01",
    "date:inception_upper": "2020-11-01",
    "iso:country": "GB",
    "wof:name": "CM8 3GJ",
    "wof:placetype": "postalcode"
  },
  "geometry": {"coordinates":[0.633073,51.845161],"type":"Point"}
}
