{
  "type": "Feature",
  "properties": {
    "iso:country":"GB",
    "wof:name":"SL6 8NP",
    "wof:placetype":"postalcode"
},
  "geometry": {"coordinates":[-0.70209911023632,51.52809896627542],"type":"Point"}
}