{
  "type": "Feature",
  "properties": {
    "date:inception_lower": "1980-01-01",
    "date:inception_upper": "1980-01-01",
    "iso:country": "GB",
    "wof:name": "SL6 8NP",
    "wof:placetype": "postalcode"
  },
  "geometry": {"coordinates":[-0.702115,51.527922],"type":"Point"}
}
