{
  "type": "Feature",
  "properties": {
    "date:inception_lower":"1980-01-01",
    "date:inception_upper":"1980-01-31",
    "iso:country":"GB",
    "wof:name":"HP1 1QR",
    "wof:placetype":"postalcode"
},
  "geometry": {"coordinates":[-0.491492,51.749471],"type":"Point"}
}