{
  "type": "Feature",
  "properties": {
    "iso:country":"GB",
    "wof:name":"HP1 1QR",
    "wof:placetype":"postalcode"
},
  "geometry": {"coordinates":[-0.49149197831015,51.74947101862195],"type":"Point"}
}