{
  "type": "Feature",
  "properties": {
    "date:inception_lower": "2005-01-01",
    "date:inception_upper": "2005-01-01",
    "iso:country": "GB",
    "wof:name": "E10 5NZ",
    "wof:placetype": "postalcode"
  },
  "geometry": {"coordinates":[-0.012535,51.56087],"type":"Point"}
}
