{
  "type": "Feature",
  "properties": {
    "iso:country":"GB",
    "wof:name":"HA7 2LD",
    "wof:placetype":"postalcode"
},
  "geometry": {"coordinates":[-0.30977588553235,51.59587702797791],"type":"Point"}
}