{
  "type": "Feature",
  "properties": {
    "iso:country": "GB",
    "wof:name": "HA7 2LD",
    "wof:placetype": "postalcode"
  },
  "geometry": {"coordinates":[-0.309776,51.595877],"type":"Point"}
}
