{
  "type": "Feature",
  "properties": {
    "iso:country": "GB",
    "wof:name": "DT10 1EB",
    "wof:placetype": "postalcode"
  },
  "geometry": {"coordinates":[-2.305753,50.932221],"type":"Point"}
}
