{
  "type": "Feature",
  "properties": {
    "iso:country":"GB",
    "wof:name":"BL3 5RJ",
    "wof:placetype":"postalcode"
},
  "geometry": {"coordinates":[-2.45497567449604,53.56757163374417],"type":"Point"}
}