{
  "type": "Feature",
  "properties": {
    "iso:country":"GB",
    "wof:name":"NP23 6PU",
    "wof:placetype":"postalcode"
},
  "geometry": {"coordinates":[-3.21507523358122,51.77952487003887],"type":"Point"}
}