{
  "type": "Feature",
  "properties": {
    "iso:country":"GB",
    "wof:name":"PO33 4ET",
    "wof:placetype":"postalcode"
},
  "geometry": {"coordinates":[-1.21111298209314,50.73180546494123],"type":"Point"}
}