{
  "type": "Feature",
  "properties": {
    "date:inception_lower":"1980-01-01",
    "date:inception_upper":"1980-01-31",
    "iso:country":"GB",
    "wof:name":"PO33 4ET",
    "wof:placetype":"postalcode"
},
  "geometry": {"coordinates":[-1.211113,50.731805],"type":"Point"}
}