{
  "type": "Feature",
  "properties": {
    "iso:country": "GB",
    "wof:name": "BN1 8DE",
    "wof:placetype": "postalcode"
  },
  "geometry": {"coordinates":[-0.133851,50.859696],"type":"Point"}
}
