{
  "type": "Feature",
  "properties": {
    "iso:country":"GB",
    "wof:name":"BN1 8DE",
    "wof:placetype":"postalcode"
},
  "geometry": {"coordinates":[-0.13385066744745,50.85969597442038],"type":"Point"}
}