{
  "type": "Feature",
  "properties": {
    "iso:country":"GB",
    "wof:name":"DT9 6LJ",
    "wof:placetype":"postalcode"
},
  "geometry": {"coordinates":[-2.57548992681486,50.89572723392187],"type":"Point"}
}