{
  "type": "Feature",
  "properties": {
    "iso:country": "GB",
    "wof:name": "DT9 6LJ",
    "wof:placetype": "postalcode"
  },
  "geometry": {"coordinates":[-2.57549,50.895727],"type":"Point"}
}
