{
  "type": "Feature",
  "properties": {
    "iso:country":"GB",
    "wof:name":"RH10 1QW",
    "wof:placetype":"postalcode"
},
  "geometry": {"coordinates":[-0.17235123932463,51.11961517972444],"type":"Point"}
}