{
  "type": "Feature",
  "properties": {
    "iso:country": "GB",
    "wof:name": "RH10 1QW",
    "wof:placetype": "postalcode"
  },
  "geometry": {"coordinates":[-0.172351,51.119615],"type":"Point"}
}
