{
  "type": "Feature",
  "properties": {
    "date:inception_lower": "1980-01-01",
    "date:inception_upper": "1980-01-01",
    "iso:country": "GB",
    "wof:name": "NE46 1LL",
    "wof:placetype": "postalcode"
  },
  "geometry": {"coordinates":[-2.082726,54.969144],"type":"Point"}
}
