{
  "type": "Feature",
  "properties": {
    "date:inception_lower":"1980-01-01",
    "date:inception_upper":"1980-01-31",
    "iso:country":"GB",
    "wof:name":"NE48 1RY",
    "wof:placetype":"postalcode"
},
  "geometry": {"coordinates":[-2.439188,55.239785],"type":"Point"}
}