{
  "type": "Feature",
  "properties": {
    "iso:country":"GB",
    "wof:name":"NE48 1RY",
    "wof:placetype":"postalcode"
},
  "geometry": {"coordinates":[-2.43918813835824,55.23978532186921],"type":"Point"}
}