{
  "type": "Feature",
  "properties": {
    "iso:country":"GB",
    "wof:name":"DH4 5HP",
    "wof:placetype":"postalcode"
},
  "geometry": {"coordinates":[-1.48329718900301,54.84725351715736],"type":"Point"}
}