{
  "type": "Feature",
  "properties": {
    "date:inception_lower":"1980-01-01",
    "date:inception_upper":"1980-01-31",
    "iso:country":"GB",
    "wof:name":"DH4 5HP",
    "wof:placetype":"postalcode"
},
  "geometry": {"coordinates":[-1.483297,54.847254],"type":"Point"}
}