{
  "type": "Feature",
  "properties": {
    "iso:country":"GB",
    "wof:name":"HU12 9SJ",
    "wof:placetype":"postalcode"
},
  "geometry": {"coordinates":[-0.10943189456803,53.70934413558925],"type":"Point"}
}