{
  "type": "Feature",
  "properties": {
    "date:inception_lower":"1980-01-01",
    "date:inception_upper":"1980-01-31",
    "iso:country":"GB",
    "wof:name":"SN11 8PN",
    "wof:placetype":"postalcode"
},
  "geometry": {"coordinates":[-1.993635,51.438095],"type":"Point"}
}