{
  "type": "Feature",
  "properties": {
    "iso:country":"GB",
    "wof:name":"SN11 8PN",
    "wof:placetype":"postalcode"
},
  "geometry": {"coordinates":[-1.99363540273408,51.43809514948433],"type":"Point"}
}