{
  "type": "Feature",
  "properties": {
    "iso:country":"GB",
    "wof:name":"HR6 8UQ",
    "wof:placetype":"postalcode"
},
  "geometry": {"coordinates":[-2.76087950134061,52.22648521345905],"type":"Point"}
}