{
  "type": "Feature",
  "properties": {
    "date:inception_lower":"1986-04-01",
    "date:inception_upper":"1986-04-30",
    "iso:country":"GB",
    "wof:name":"HR6 8UQ",
    "wof:placetype":"postalcode"
},
  "geometry": {"coordinates":[-2.760879,52.226485],"type":"Point"}
}