{
  "type": "Feature",
  "properties": {
    "iso:country": "GB",
    "wof:name": "SG19 2LQ",
    "wof:placetype": "postalcode"
  },
  "geometry": {"coordinates":[-0.220882,52.127057],"type":"Point"}
}
