{
  "type": "Feature",
  "properties": {
    "date:inception_lower":"2005-09-01",
    "date:inception_upper":"2005-09-30",
    "iso:country":"GB",
    "wof:name":"SG19 2LQ",
    "wof:placetype":"postalcode"
},
  "geometry": {"coordinates":[-0.220882,52.127057],"type":"Point"}
}