{
  "type": "Feature",
  "properties": {
    "iso:country":"GB",
    "wof:name":"WA8 8UZ",
    "wof:placetype":"postalcode"
},
  "geometry": {"coordinates":[-2.77762819357551,53.35050320078365],"type":"Point"}
}