{
  "type": "Feature",
  "properties": {
    "date:inception_lower":"1980-01-01",
    "date:inception_upper":"1980-01-31",
    "iso:country":"GB",
    "wof:name":"DY2 0PP",
    "wof:placetype":"postalcode"
},
  "geometry": {"coordinates":[-2.084951,52.491403],"type":"Point"}
}