{
  "type": "Feature",
  "properties": {
    "iso:country":"GB",
    "wof:name":"DY2 0PP",
    "wof:placetype":"postalcode"
},
  "geometry": {"coordinates":[-2.08495102711203,52.4914027417178],"type":"Point"}
}