{
  "type": "Feature",
  "properties": {
    "date:inception_lower": "1984-02-01",
    "date:inception_upper": "1984-02-01",
    "iso:country": "GB",
    "wof:name": "NE34 0YH",
    "wof:placetype": "postalcode"
  },
  "geometry": {"coordinates":[-1.430564,54.970114],"type":"Point"}
}
