{
  "type": "Feature",
  "properties": {
    "iso:country":"GB",
    "wof:name":"NE34 0YH",
    "wof:placetype":"postalcode"
},
  "geometry": {"coordinates":[-1.43056375869209,54.97011406277591],"type":"Point"}
}