{
  "type": "Feature",
  "properties": {
    "iso:country": "GB",
    "wof:name": "WA9 1DL",
    "wof:placetype": "postalcode"
  },
  "geometry": {"coordinates":[-2.718109,53.455989],"type":"Point"}
}
