{
  "type": "Feature",
  "properties": {
    "iso:country":"GB",
    "wof:name":"HP12 3JW",
    "wof:placetype":"postalcode"
},
  "geometry": {"coordinates":[-0.77741918567713,51.63146847038251],"type":"Point"}
}