{
  "type": "Feature",
  "properties": {
    "iso:country":"GB",
    "wof:name":"IG11 7JT",
    "wof:placetype":"postalcode"
},
  "geometry": {"coordinates":[0.07996526113105,51.53095754335882],"type":"Point"}
}