{
  "type": "Feature",
  "properties": {
    "iso:country": "GB",
    "wof:name": "HP10 9SY",
    "wof:placetype": "postalcode"
  },
  "geometry": {"coordinates":[-0.700223,51.607099],"type":"Point"}
}
