{
  "type": "Feature",
  "properties": {
    "iso:country":"GB",
    "wof:name":"PE33 9DG",
    "wof:placetype":"postalcode"
},
  "geometry": {"coordinates":[0.42438321875622,52.60829688249095],"type":"Point"}
}