{
  "type": "Feature",
  "properties": {
    "iso:country": "GB",
    "wof:name": "PE33 9DG",
    "wof:placetype": "postalcode"
  },
  "geometry": {"coordinates":[0.424383,52.608297],"type":"Point"}
}
