{
  "type": "Feature",
  "properties": {
    "iso:country":"GB",
    "wof:name":"WN5 9JR",
    "wof:placetype":"postalcode"
},
  "geometry": {"coordinates":[-2.66758248413989,53.53260604708522],"type":"Point"}
}