{
  "type": "Feature",
  "properties": {
    "iso:country":"GB",
    "wof:name":"UB5 4TD",
    "wof:placetype":"postalcode"
},
  "geometry": {"coordinates":[-0.35493857065243,51.55147679566963],"type":"Point"}
}