{
  "type": "Feature",
  "properties": {
    "date:inception_lower":"1981-06-01",
    "date:inception_upper":"1981-06-30",
    "iso:country":"GB",
    "wof:name":"UB5 4TD",
    "wof:placetype":"postalcode"
},
  "geometry": {"coordinates":[-0.354939,51.551477],"type":"Point"}
}