{
  "type": "Feature",
  "properties": {
    "iso:country": "GB",
    "wof:name": "UB5 4TD",
    "wof:placetype": "postalcode"
  },
  "geometry": {"coordinates":[-0.354939,51.551477],"type":"Point"}
}
