{
  "type": "Feature",
  "properties": {
    "iso:country":"GB",
    "wof:name":"TS3 6EA",
    "wof:placetype":"postalcode"
},
  "geometry": {"coordinates":[-1.21703878095335,54.56995938133825],"type":"Point"}
}