{
  "type": "Feature",
  "properties": {
    "iso:country": "GB",
    "wof:name": "BH1 3AW",
    "wof:placetype": "postalcode"
  },
  "geometry": {"coordinates":[-1.862799,50.718933],"type":"Point"}
}
