{
  "type": "Feature",
  "properties": {
    "date:inception_lower":"2002-05-01",
    "date:inception_upper":"2002-05-31",
    "iso:country":"GB",
    "wof:name":"DA9 9GJ",
    "wof:placetype":"postalcode"
},
  "geometry": {"coordinates":[0.286381,51.4533],"type":"Point"}
}