{
  "type": "Feature",
  "properties": {
    "iso:country":"GB",
    "wof:name":"DA9 9GJ",
    "wof:placetype":"postalcode"
},
  "geometry": {"coordinates":[0.2863808726471,51.45330006646274],"type":"Point"}
}