{
  "type": "Feature",
  "properties": {
    "iso:country": "GB",
    "wof:name": "HX2 8BQ",
    "wof:placetype": "postalcode"
  },
  "geometry": {"coordinates":[-1.887276,53.74405],"type":"Point"}
}
