{
  "type": "Feature",
  "properties": {
    "iso:country": "GB",
    "wof:name": "YO30 7AX",
    "wof:placetype": "postalcode"
  },
  "geometry": {"coordinates":[-1.08628,53.971124],"type":"Point"}
}
