{
  "type": "Feature",
  "properties": {
    "iso:country": "GB",
    "wof:name": "SP4 6GX",
    "wof:placetype": "postalcode"
  },
  "geometry": {"coordinates":[-1.78614,51.10107],"type":"Point"}
}
