{
  "type": "Feature",
  "properties": {
    "date:inception_lower": "1980-01-01",
    "date:inception_upper": "1980-01-01",
    "iso:country": "GB",
    "wof:name": "HX1 3EY",
    "wof:placetype": "postalcode"
  },
  "geometry": {"coordinates":[-1.876723,53.71313],"type":"Point"}
}
