{
  "type": "Feature",
  "properties": {
    "iso:country":"GB",
    "wof:name":"HX1 3EY",
    "wof:placetype":"postalcode"
},
  "geometry": {"coordinates":[-1.87672263511402,53.71312950802697],"type":"Point"}
}