{
  "type": "Feature",
  "properties": {
    "date:inception_lower":"2002-06-01",
    "date:inception_upper":"2002-06-30",
    "iso:country":"GB",
    "wof:name":"SG4 8WH",
    "wof:placetype":"postalcode"
},
  "geometry": {"coordinates":[-0.238612,51.843606],"type":"Point"}
}