{
  "type": "Feature",
  "properties": {
    "iso:country":"GB",
    "wof:name":"SG4 8WH",
    "wof:placetype":"postalcode"
},
  "geometry": {"coordinates":[-0.23861246314313,51.84359739375844],"type":"Point"}
}