{
  "type": "Feature",
  "properties": {
    "iso:country":"GB",
    "wof:name":"CT18 7TS",
    "wof:placetype":"postalcode"
},
  "geometry": {"coordinates":[1.16115226601151,51.11735541410202],"type":"Point"}
}