{
  "type": "Feature",
  "properties": {
    "iso:country":"GB",
    "wof:name":"EX2 9BA",
    "wof:placetype":"postalcode"
},
  "geometry": {"coordinates":[-3.53992187719113,50.71569279393128],"type":"Point"}
}