{
  "type": "Feature",
  "properties": {
    "date:inception_lower": "2021-08-01",
    "date:inception_upper": "2021-08-01",
    "iso:country": "GB",
    "wof:name": "ME12 3XG",
    "wof:placetype": "postalcode"
  },
  "geometry": {"coordinates":[0.801885,51.412441],"type":"Point"}
}
