{
  "type": "Feature",
  "properties": {
    "date:inception_lower":"1980-01-01",
    "date:inception_upper":"1980-01-31",
    "iso:country":"GB",
    "wof:name":"PH7 4JZ",
    "wof:placetype":"postalcode"
},
  "geometry": {"coordinates":[-3.939975,56.38433],"type":"Point"}
}