{
  "type": "Feature",
  "properties": {
    "iso:country":"GB",
    "wof:name":"PH7 4JZ",
    "wof:placetype":"postalcode"
},
  "geometry": {"coordinates":[-3.94310781954758,56.38402027054025],"type":"Point"}
}