{
  "type": "Feature",
  "properties": {
    "iso:country": "GB",
    "wof:name": "FY7 8AN",
    "wof:placetype": "postalcode"
  },
  "geometry": {"coordinates":[-3.036885,53.919301],"type":"Point"}
}
