{
  "type": "Feature",
  "properties": {
    "iso:country":"GB",
    "wof:name":"FY7 8AN",
    "wof:placetype":"postalcode"
},
  "geometry": {"coordinates":[-3.03688513986584,53.91930128742141],"type":"Point"}
}