{
  "type": "Feature",
  "properties": {
    "iso:country":"GB",
    "wof:name":"HA2 0TX",
    "wof:placetype":"postalcode"
},
  "geometry": {"coordinates":[-0.36420785901096,51.57212657829361],"type":"Point"}
}