{
  "type": "Feature",
  "properties": {
    "date:inception_lower":"2018-10-01",
    "date:inception_upper":"2018-10-31",
    "iso:country":"GB",
    "wof:name":"SL1 0JX",
    "wof:placetype":"postalcode"
},
  "geometry": {"coordinates":[-0.584601,51.508272],"type":"Point"}
}