{
  "type": "Feature",
  "properties": {
    "iso:country": "GB",
    "wof:name": "G66 7BL",
    "wof:placetype": "postalcode"
  },
  "geometry": {"coordinates":[-4.188128,55.969334],"type":"Point"}
}
