{
  "type": "Feature",
  "properties": {
    "iso:country": "GB",
    "wof:name": "BH23 1BY",
    "wof:placetype": "postalcode"
  },
  "geometry": {"coordinates":[-1.775079,50.730999],"type":"Point"}
}
