{
  "type": "Feature",
  "properties": {
    "iso:country":"GB",
    "wof:name":"BH23 1BY",
    "wof:placetype":"postalcode"
},
  "geometry": {"coordinates":[-1.77603336259682,50.73136199303492],"type":"Point"}
}