{
  "type": "Feature",
  "properties": {
    "date:inception_lower":"1980-01-01",
    "date:inception_upper":"1980-01-31",
    "iso:country":"GB",
    "wof:name":"BH23 1BY",
    "wof:placetype":"postalcode"
},
  "geometry": {"coordinates":[-1.775079,50.730999],"type":"Point"}
}