{
  "type": "Feature",
  "properties": {
    "iso:country":"GB",
    "wof:name":"MK43 8EP",
    "wof:placetype":"postalcode"
},
  "geometry": {"coordinates":[-0.62620330099325,52.16272103525703],"type":"Point"}
}