{
  "type": "Feature",
  "properties": {
    "iso:country": "GB",
    "wof:name": "KT1 1ER",
    "wof:placetype": "postalcode"
  },
  "geometry": {"coordinates":[-0.304172,51.40863],"type":"Point"}
}
