{
  "type": "Feature",
  "properties": {
    "iso:country":"GB",
    "wof:name":"KT1 1ER",
    "wof:placetype":"postalcode"
},
  "geometry": {"coordinates":[-0.30420494324932,51.40872896580839],"type":"Point"}
}