{
  "type": "Feature",
  "properties": {
    "iso:country": "GB",
    "wof:name": "CM16 6JT",
    "wof:placetype": "postalcode"
  },
  "geometry": {"coordinates":[0.162944,51.713921],"type":"Point"}
}
