{
  "type": "Feature",
  "properties": {
    "iso:country":"GB",
    "wof:name":"S60 5AS",
    "wof:placetype":"postalcode"
},
  "geometry": {"coordinates":[-1.37350168447484,53.40750305642933],"type":"Point"}
}