{
  "type": "Feature",
  "properties": {
    "iso:country":"GB",
    "wof:name":"MK18 7RY",
    "wof:placetype":"postalcode"
},
  "geometry": {"coordinates":[-0.96804164951473,51.98954349635301],"type":"Point"}
}