{
  "type": "Feature",
  "properties": {
    "date:inception_lower": "2015-06-01",
    "date:inception_upper": "2015-06-01",
    "iso:country": "GB",
    "wof:name": "MK18 7RY",
    "wof:placetype": "postalcode"
  },
  "geometry": {"coordinates":[-0.968195,51.989681],"type":"Point"}
}
