{
  "type": "Feature",
  "properties": {
    "iso:country":"GB",
    "wof:name":"TA4 1PU",
    "wof:placetype":"postalcode"
},
  "geometry": {"coordinates":[-3.24730652139567,51.02162178744845],"type":"Point"}
}