{
  "type": "Feature",
  "properties": {
    "iso:country":"GB",
    "wof:name":"E17 4LH",
    "wof:placetype":"postalcode"
},
  "geometry": {"coordinates":[-0.01357365219545,51.59694786366338],"type":"Point"}
}