{
  "type": "Feature",
  "properties": {
    "iso:country":"GB",
    "wof:name":"NE61 2YG",
    "wof:placetype":"postalcode"
},
  "geometry": {"coordinates":[-1.70444760587774,55.16298544376092],"type":"Point"}
}