{
  "type": "Feature",
  "properties": {
    "iso:country": "GB",
    "wof:name": "DH5 9RR",
    "wof:placetype": "postalcode"
  },
  "geometry": {"coordinates":[-1.482159,54.820568],"type":"Point"}
}
