{
  "type": "Feature",
  "properties": {
    "date:inception_lower":"1981-06-01",
    "date:inception_upper":"1981-06-30",
    "iso:country":"GB",
    "wof:name":"DH5 9RR",
    "wof:placetype":"postalcode"
},
  "geometry": {"coordinates":[-1.482159,54.820568],"type":"Point"}
}