{
  "type": "Feature",
  "properties": {
    "iso:country":"GB",
    "wof:name":"DH5 9RR",
    "wof:placetype":"postalcode"
},
  "geometry": {"coordinates":[-1.48215924247333,54.82056768096458],"type":"Point"}
}