{
  "type": "Feature",
  "properties": {
    "iso:country":"GB",
    "wof:name":"IP14 1LP",
    "wof:placetype":"postalcode"
},
  "geometry": {"coordinates":[0.98282893618398,52.19193686311102],"type":"Point"}
}