{
  "type": "Feature",
  "properties": {
    "iso:country":"GB",
    "wof:name":"IP29 5EA",
    "wof:placetype":"postalcode"
},
  "geometry": {"coordinates":[0.58428020498895,52.23700921351085],"type":"Point"}
}