{
  "type": "Feature",
  "properties": {
    "date:inception_lower": "2015-07-01",
    "date:inception_upper": "2015-07-01",
    "iso:country": "GB",
    "wof:name": "IP29 5EA",
    "wof:placetype": "postalcode"
  },
  "geometry": {"coordinates":[0.58428,52.237009],"type":"Point"}
}
