{
  "type": "Feature",
  "properties": {
    "iso:country":"GB",
    "wof:name":"TW9 2QE",
    "wof:placetype":"postalcode"
},
  "geometry": {"coordinates":[-0.30106595750049,51.46391506478198],"type":"Point"}
}