{
  "type": "Feature",
  "properties": {
    "iso:country":"GB",
    "wof:name":"TN28 8AG",
    "wof:placetype":"postalcode"
},
  "geometry": {"coordinates":[0.94499835336592,50.98311862336282],"type":"Point"}
}