{
  "type": "Feature",
  "properties": {
    "date:inception_lower":"2015-08-01",
    "date:inception_upper":"2015-08-31",
    "iso:country":"GB",
    "wof:name":"TN28 8AG",
    "wof:placetype":"postalcode"
},
  "geometry": {"coordinates":[0.944998,50.983119],"type":"Point"}
}