{
  "type": "Feature",
  "properties": {
    "iso:country": "GB",
    "wof:name": "TN28 8AG",
    "wof:placetype": "postalcode"
  },
  "geometry": {"coordinates":[0.944998,50.983119],"type":"Point"}
}
