{
  "type": "Feature",
  "properties": {
    "date:inception_lower": "2017-11-01",
    "date:inception_upper": "2017-11-01",
    "iso:country": "GB",
    "wof:name": "TN3 9ES",
    "wof:placetype": "postalcode"
  },
  "geometry": {"coordinates":[0.247723,51.104467],"type":"Point"}
}
