{
  "type": "Feature",
  "properties": {
    "iso:country":"GB",
    "wof:name":"WA13 9PQ",
    "wof:placetype":"postalcode"
},
  "geometry": {"coordinates":[-2.4748090755466,53.38348127949403],"type":"Point"}
}