{
  "type": "Feature",
  "properties": {
    "iso:country":"GB",
    "wof:name":"BR6 6EE",
    "wof:placetype":"postalcode"
},
  "geometry": {"coordinates":[0.10220337524591,51.3540394940478],"type":"Point"}
}