{
  "type": "Feature",
  "properties": {
    "iso:country":"GB",
    "wof:name":"SM2 6RR",
    "wof:placetype":"postalcode"
},
  "geometry": {"coordinates":[-0.19376820211171,51.35596480399595],"type":"Point"}
}