{
  "type": "Feature",
  "properties": {
    "date:inception_lower": "1980-01-01",
    "date:inception_upper": "1980-01-01",
    "iso:country": "GB",
    "wof:name": "DE55 2BZ",
    "wof:placetype": "postalcode"
  },
  "geometry": {"coordinates":[-1.335954,53.104544],"type":"Point"}
}
