{
  "type": "Feature",
  "properties": {
    "iso:country":"GB",
    "wof:name":"DE55 2BZ",
    "wof:placetype":"postalcode"
},
  "geometry": {"coordinates":[-1.33595361598703,53.10454355057286],"type":"Point"}
}