{
  "type": "Feature",
  "properties": {
    "iso:country":"GB",
    "wof:name":"PR26 9RJ",
    "wof:placetype":"postalcode"
},
  "geometry": {"coordinates":[-2.77657507807043,53.66623582725534],"type":"Point"}
}