{
  "type": "Feature",
  "properties": {
    "iso:country": "GB",
    "wof:name": "PA2 7FF",
    "wof:placetype": "postalcode"
  },
  "geometry": {"coordinates":[-4.391402,55.833763],"type":"Point"}
}
