{
  "type": "Feature",
  "properties": {
    "date:inception_lower":"2015-10-01",
    "date:inception_upper":"2015-10-31",
    "iso:country":"GB",
    "wof:name":"PA2 7FF",
    "wof:placetype":"postalcode"
},
  "geometry": {"coordinates":[-4.391402,55.833763],"type":"Point"}
}