{
  "type": "Feature",
  "properties": {
    "iso:country":"GB",
    "wof:name":"PA2 7FF",
    "wof:placetype":"postalcode"
},
  "geometry": {"coordinates":[-4.39138896509011,55.83383175427341],"type":"Point"}
}