{
  "type": "Feature",
  "properties": {
    "iso:country":"GB",
    "wof:name":"BN6 9EN",
    "wof:placetype":"postalcode"
},
  "geometry": {"coordinates":[-0.14945904161635,50.93056933979133],"type":"Point"}
}