{
  "type": "Feature",
  "properties": {
    "date:inception_lower": "1994-12-01",
    "date:inception_upper": "1994-12-01",
    "iso:country": "GB",
    "wof:name": "BN6 9EN",
    "wof:placetype": "postalcode"
  },
  "geometry": {"coordinates":[-0.149459,50.930569],"type":"Point"}
}
