{
  "type": "Feature",
  "properties": {
    "iso:country":"GB",
    "wof:name":"OX4 2RB",
    "wof:placetype":"postalcode"
},
  "geometry": {"coordinates":[-1.19901024971777,51.73861812038842],"type":"Point"}
}