{
  "type": "Feature",
  "properties": {
    "date:inception_lower": "1994-09-01",
    "date:inception_upper": "1994-09-01",
    "iso:country": "GB",
    "wof:name": "FK10 4EB",
    "wof:placetype": "postalcode"
  },
  "geometry": {"coordinates":[-3.71328,56.099111],"type":"Point"}
}
