{
  "type": "Feature",
  "properties": {
    "date:inception_lower": "2020-11-01",
    "date:inception_upper": "2020-11-01",
    "iso:country": "GB",
    "wof:name": "NR5 9FH",
    "wof:placetype": "postalcode"
  },
  "geometry": {"coordinates":[1.230664,52.637572],"type":"Point"}
}
