{
  "type": "Feature",
  "properties": {
    "iso:country": "GB",
    "wof:name": "CA8 7DG",
    "wof:placetype": "postalcode"
  },
  "geometry": {"coordinates":[-2.636033,54.994036],"type":"Point"}
}
