{
  "type": "Feature",
  "properties": {
    "date:inception_lower": "2000-06-01",
    "date:inception_upper": "2000-06-01",
    "iso:country": "GB",
    "wof:name": "CA8 7DG",
    "wof:placetype": "postalcode"
  },
  "geometry": {"coordinates":[-2.636033,54.994036],"type":"Point"}
}
