{
  "type": "Feature",
  "properties": {
    "iso:country":"GB",
    "wof:name":"G75 9JL",
    "wof:placetype":"postalcode"
},
  "geometry": {"coordinates":[-4.18398725569547,55.74858040741073],"type":"Point"}
}