{
  "type": "Feature",
  "properties": {
    "iso:country": "GB",
    "wof:name": "M4 3AQ",
    "wof:placetype": "postalcode"
  },
  "geometry": {"coordinates":[-2.241703,53.483469],"type":"Point"}
}
