{
  "type": "Feature",
  "properties": {
    "iso:country": "GB",
    "wof:name": "CT21 4JT",
    "wof:placetype": "postalcode"
  },
  "geometry": {"coordinates":[1.025687,51.078381],"type":"Point"}
}
