{
  "type": "Feature",
  "properties": {
    "iso:country":"GB",
    "wof:name":"CT21 4JT",
    "wof:placetype":"postalcode"
},
  "geometry": {"coordinates":[1.02569651378222,51.07837857071527],"type":"Point"}
}