{
  "type": "Feature",
  "properties": {
    "date:inception_lower": "2019-03-01",
    "date:inception_upper": "2019-03-01",
    "iso:country": "GB",
    "wof:name": "G66 5BL",
    "wof:placetype": "postalcode"
  },
  "geometry": {"coordinates":[-4.145996,55.913945],"type":"Point"}
}
