{
  "type": "Feature",
  "properties": {
    "iso:country": "GB",
    "wof:name": "SG8 8DS",
    "wof:placetype": "postalcode"
  },
  "geometry": {"coordinates":[0.036751,52.026592],"type":"Point"}
}
