{
  "type": "Feature",
  "properties": {
    "iso:country":"GB",
    "wof:name":"SG8 8DS",
    "wof:placetype":"postalcode"
},
  "geometry": {"coordinates":[0.03675047459356,52.02659250351931],"type":"Point"}
}