{
  "type": "Feature",
  "properties": {
    "iso:country":"GB",
    "wof:name":"IP12 2QY",
    "wof:placetype":"postalcode"
},
  "geometry": {"coordinates":[1.39581157999347,52.12629377702023],"type":"Point"}
}