{
  "type": "Feature",
  "properties": {
    "iso:country": "GB",
    "wof:name": "TN23 7UY",
    "wof:placetype": "postalcode"
  },
  "geometry": {"coordinates":[0.865392,51.142387],"type":"Point"}
}
