{
  "type": "Feature",
  "properties": {
    "date:inception_lower": "1980-01-01",
    "date:inception_upper": "1980-01-01",
    "iso:country": "GB",
    "wof:name": "IP7 6EE",
    "wof:placetype": "postalcode"
  },
  "geometry": {"coordinates":[0.918209,52.058281],"type":"Point"}
}
