{
  "type": "Feature",
  "properties": {
    "iso:country":"GB",
    "wof:name":"KY16 8EL",
    "wof:placetype":"postalcode"
},
  "geometry": {"coordinates":[-2.7996882450089,56.33094673581957],"type":"Point"}
}