{
  "type": "Feature",
  "properties": {
    "iso:country": "GB",
    "wof:name": "EX14 9BG",
    "wof:placetype": "postalcode"
  },
  "geometry": {"coordinates":[-3.065058,50.85985],"type":"Point"}
}
