{
  "type": "Feature",
  "properties": {
    "iso:country":"GB",
    "wof:name":"EX14 9BG",
    "wof:placetype":"postalcode"
},
  "geometry": {"coordinates":[-3.06485997623481,50.86023782443058],"type":"Point"}
}