{
  "type": "Feature",
  "properties": {
    "iso:country":"GB",
    "wof:name":"SE16 5SN",
    "wof:placetype":"postalcode"
},
  "geometry": {"coordinates":[-0.04385827636831,51.50601111535232],"type":"Point"}
}