{
  "type": "Feature",
  "properties": {
    "iso:country":"GB",
    "wof:name":"NE7 7EB",
    "wof:placetype":"postalcode"
},
  "geometry": {"coordinates":[-1.57891894744962,55.00256513157493],"type":"Point"}
}