{
  "type": "Feature",
  "properties": {
    "iso:country":"GB",
    "wof:name":"DT2 7RW",
    "wof:placetype":"postalcode"
},
  "geometry": {"coordinates":[-2.42641411682143,50.81905865470406],"type":"Point"}
}