{
  "type": "Feature",
  "properties": {
    "iso:country": "GB",
    "wof:name": "DT2 7RW",
    "wof:placetype": "postalcode"
  },
  "geometry": {"coordinates":[-2.426577,50.81993],"type":"Point"}
}
