{
  "type": "Feature",
  "properties": {
    "date:inception_lower": "1980-01-01",
    "date:inception_upper": "1980-01-01",
    "iso:country": "GB",
    "wof:name": "TN22 1TP",
    "wof:placetype": "postalcode"
  },
  "geometry": {"coordinates":[0.101744,50.977104],"type":"Point"}
}
