{
  "type": "Feature",
  "properties": {
    "iso:country":"GB",
    "wof:name":"BA9 8DG",
    "wof:placetype":"postalcode"
},
  "geometry": {"coordinates":[-2.49542260691296,51.06163461479647],"type":"Point"}
}