{
  "type": "Feature",
  "properties": {
    "iso:country":"GB",
    "wof:name":"AB16 6XS",
    "wof:placetype":"postalcode"
},
  "geometry": {"coordinates":[-2.15351747826798,57.15643024477414],"type":"Point"}
}