{
  "type": "Feature",
  "properties": {
    "date:inception_lower": "2009-05-01",
    "date:inception_upper": "2009-05-01",
    "iso:country": "GB",
    "wof:name": "AB12 9EL",
    "wof:placetype": "postalcode"
  },
  "geometry": {"coordinates":[-2.094009,57.11134],"type":"Point"}
}
