{
  "type": "Feature",
  "properties": {
    "iso:country": "GB",
    "wof:name": "SY13 3NS",
    "wof:placetype": "postalcode"
  },
  "geometry": {"coordinates":[-2.684215,52.936605],"type":"Point"}
}
