{
  "type": "Feature",
  "properties": {
    "iso:country":"GB",
    "wof:name":"EH11 1UU",
    "wof:placetype":"postalcode"
},
  "geometry": {"coordinates":[-3.2335348803671,55.93528687814666],"type":"Point"}
}