{
  "type": "Feature",
  "properties": {
    "iso:country":"GB",
    "wof:name":"OX33 1EZ",
    "wof:placetype":"postalcode"
},
  "geometry": {"coordinates":[-1.16103482686001,51.77787896130029],"type":"Point"}
}