{
  "type": "Feature",
  "properties": {
    "iso:country": "GB",
    "wof:name": "OX33 1EZ",
    "wof:placetype": "postalcode"
  },
  "geometry": {"coordinates":[-1.161035,51.777879],"type":"Point"}
}
