{
  "type": "Feature",
  "properties": {
    "iso:country":"GB",
    "wof:name":"BD10 9RQ",
    "wof:placetype":"postalcode"
},
  "geometry": {"coordinates":[-1.72940810291594,53.83578091670041],"type":"Point"}
}