{
  "type": "Feature",
  "properties": {
    "date:inception_lower": "2005-07-01",
    "date:inception_upper": "2005-07-01",
    "iso:country": "GB",
    "wof:name": "DE74 2DG",
    "wof:placetype": "postalcode"
  },
  "geometry": {"coordinates":[-1.286163,52.838241],"type":"Point"}
}
