{
  "type": "Feature",
  "properties": {
    "iso:country":"GB",
    "wof:name":"TR3 7AR",
    "wof:placetype":"postalcode"
},
  "geometry": {"coordinates":[-5.20062637316108,50.18905253515717],"type":"Point"}
}