{
  "type": "Feature",
  "properties": {
    "iso:country": "GB",
    "wof:name": "YO30 1ZB",
    "wof:placetype": "postalcode"
  },
  "geometry": {"coordinates":[-1.134237,53.996016],"type":"Point"}
}
