{
  "type": "Feature",
  "properties": {
    "iso:country":"GB",
    "wof:name":"TS14 6JD",
    "wof:placetype":"postalcode"
},
  "geometry": {"coordinates":[-1.05686689506727,54.53790137524749],"type":"Point"}
}