{
  "type": "Feature",
  "properties": {
    "iso:country": "GB",
    "wof:name": "TS14 6JD",
    "wof:placetype": "postalcode"
  },
  "geometry": {"coordinates":[-1.056867,54.537901],"type":"Point"}
}
