{
  "type": "Feature",
  "properties": {
    "date:inception_lower":"1980-01-01",
    "date:inception_upper":"1980-01-31",
    "iso:country":"GB",
    "wof:name":"WA7 3ET",
    "wof:placetype":"postalcode"
},
  "geometry": {"coordinates":[-2.683238,53.313688],"type":"Point"}
}