{
  "type": "Feature",
  "properties": {
    "iso:country":"GB",
    "wof:name":"WA7 3ET",
    "wof:placetype":"postalcode"
},
  "geometry": {"coordinates":[-2.68323783959928,53.3136875221638],"type":"Point"}
}