{
  "type": "Feature",
  "properties": {
    "iso:country":"GB",
    "wof:name":"G33 2QH",
    "wof:placetype":"postalcode"
},
  "geometry": {"coordinates":[-4.18980880211669,55.86715505216889],"type":"Point"}
}