{
  "type": "Feature",
  "properties": {
    "date:inception_lower": "1980-01-01",
    "date:inception_upper": "1980-01-01",
    "iso:country": "GB",
    "wof:name": "G33 2QH",
    "wof:placetype": "postalcode"
  },
  "geometry": {"coordinates":[-4.189809,55.867155],"type":"Point"}
}
