{
  "type": "Feature",
  "properties": {
    "iso:country": "GB",
    "wof:name": "LS11 9ET",
    "wof:placetype": "postalcode"
  },
  "geometry": {"coordinates":[-1.549184,53.7885],"type":"Point"}
}
