{
  "type": "Feature",
  "properties": {
    "iso:country":"GB",
    "wof:name":"DN41 8HP",
    "wof:placetype":"postalcode"
},
  "geometry": {"coordinates":[-0.24962920956369,53.57503305475066],"type":"Point"}
}