{
  "type": "Feature",
  "properties": {
    "date:inception_lower": "1980-01-01",
    "date:inception_upper": "1980-01-01",
    "iso:country": "GB",
    "wof:name": "G13 4PW",
    "wof:placetype": "postalcode"
  },
  "geometry": {"coordinates":[-4.36741,55.897515],"type":"Point"}
}
