{
  "type": "Feature",
  "properties": {
    "date:inception_lower": "1997-06-01",
    "date:inception_upper": "1997-06-01",
    "iso:country": "GB",
    "wof:name": "S33 7ZD",
    "wof:placetype": "postalcode"
  },
  "geometry": {"coordinates":[-1.817202,53.370858],"type":"Point"}
}
