{
  "type": "Feature",
  "properties": {
    "iso:country": "GB",
    "wof:name": "OX11 9QL",
    "wof:placetype": "postalcode"
  },
  "geometry": {"coordinates":[-1.233044,51.570697],"type":"Point"}
}
