{
  "type": "Feature",
  "properties": {
    "iso:country":"GB",
    "wof:name":"OX11 9QL",
    "wof:placetype":"postalcode"
},
  "geometry": {"coordinates":[-1.23304357886945,51.57069671740081],"type":"Point"}
}