{
  "type": "Feature",
  "properties": {
    "date:inception_lower": "1999-06-01",
    "date:inception_upper": "1999-06-01",
    "iso:country": "GB",
    "wof:name": "CF31 3PE",
    "wof:placetype": "postalcode"
  },
  "geometry": {"coordinates":[-3.584209,51.499891],"type":"Point"}
}
