{
  "type": "Feature",
  "properties": {
    "iso:country": "GB",
    "wof:name": "DE21 2LR",
    "wof:placetype": "postalcode"
  },
  "geometry": {"coordinates":[-1.424342,52.942604],"type":"Point"}
}
