{
  "type": "Feature",
  "properties": {
    "iso:country":"GB",
    "wof:name":"HX2 8UL",
    "wof:placetype":"postalcode"
},
  "geometry": {"coordinates":[-1.90742510751381,53.75877145970825],"type":"Point"}
}