{
  "type": "Feature",
  "properties": {
    "iso:country":"GB",
    "wof:name":"PO33 3PR",
    "wof:placetype":"postalcode"
},
  "geometry": {"coordinates":[-1.17367523279853,50.72546708929309],"type":"Point"}
}