{
  "type": "Feature",
  "properties": {
    "date:inception_lower": "1990-02-01",
    "date:inception_upper": "1990-02-01",
    "iso:country": "GB",
    "wof:name": "HP13 6NB",
    "wof:placetype": "postalcode"
  },
  "geometry": {"coordinates":[-0.745536,51.633398],"type":"Point"}
}
