{
  "type": "Feature",
  "properties": {
    "iso:country": "GB",
    "wof:name": "HP13 6NB",
    "wof:placetype": "postalcode"
  },
  "geometry": {"coordinates":[-0.745536,51.633398],"type":"Point"}
}
