{
  "type": "Feature",
  "properties": {
    "iso:country":"GB",
    "wof:name":"DN35 8DZ",
    "wof:placetype":"postalcode"
},
  "geometry": {"coordinates":[-0.03666351007764,53.5580264578314],"type":"Point"}
}