{
  "type": "Feature",
  "properties": {
    "iso:country":"GB",
    "wof:name":"WS8 6BD",
    "wof:placetype":"postalcode"
},
  "geometry": {"coordinates":[-1.92437309184506,52.64607036155723],"type":"Point"}
}