{
  "type": "Feature",
  "properties": {
    "iso:country":"GB",
    "wof:name":"G82 5DY",
    "wof:placetype":"postalcode"
},
  "geometry": {"coordinates":[-4.59632650381634,55.94925468319765],"type":"Point"}
}