{
  "type": "Feature",
  "properties": {
    "iso:country":"GB",
    "wof:name":"LE4 0JS",
    "wof:placetype":"postalcode"
},
  "geometry": {"coordinates":[-1.14269188689343,52.65505056005501],"type":"Point"}
}