{
  "type": "Feature",
  "properties": {
    "iso:country":"GB",
    "wof:name":"TN6 3QP",
    "wof:placetype":"postalcode"
},
  "geometry": {"coordinates":[0.23975318003583,51.0441763124805],"type":"Point"}
}