{
  "type": "Feature",
  "properties": {
    "date:inception_lower": "1980-01-01",
    "date:inception_upper": "1980-01-01",
    "iso:country": "GB",
    "wof:name": "EX34 9PL",
    "wof:placetype": "postalcode"
  },
  "geometry": {"coordinates":[-4.107831,51.205201],"type":"Point"}
}
