{
  "type": "Feature",
  "properties": {
    "iso:country": "GB",
    "wof:name": "EX34 9PL",
    "wof:placetype": "postalcode"
  },
  "geometry": {"coordinates":[-4.107831,51.205201],"type":"Point"}
}
