{
  "type": "Feature",
  "properties": {
    "iso:country": "GB",
    "wof:name": "SY1 4DB",
    "wof:placetype": "postalcode"
  },
  "geometry": {"coordinates":[-2.741019,52.725413],"type":"Point"}
}
