{
  "type": "Feature",
  "properties": {
    "iso:country":"GB",
    "wof:name":"SY1 4DB",
    "wof:placetype":"postalcode"
},
  "geometry": {"coordinates":[-2.74101950080392,52.72541252388562],"type":"Point"}
}