{
  "type": "Feature",
  "properties": {
    "iso:country":"GB",
    "wof:name":"TS23 3ET",
    "wof:placetype":"postalcode"
},
  "geometry": {"coordinates":[-1.28374965491111,54.61767098695029],"type":"Point"}
}