{
  "type": "Feature",
  "properties": {
    "date:inception_lower": "1980-01-01",
    "date:inception_upper": "1980-01-01",
    "iso:country": "GB",
    "wof:name": "TS23 3ET",
    "wof:placetype": "postalcode"
  },
  "geometry": {"coordinates":[-1.28375,54.617671],"type":"Point"}
}
