{
  "type": "Feature",
  "properties": {
    "iso:country":"GB",
    "wof:name":"DG9 8LA",
    "wof:placetype":"postalcode"
},
  "geometry": {"coordinates":[-5.10834242518063,54.8453714803242],"type":"Point"}
}