{
  "type": "Feature",
  "properties": {
    "iso:country":"GB",
    "wof:name":"B34 6RX",
    "wof:placetype":"postalcode"
},
  "geometry": {"coordinates":[-1.7800141789304,52.49638966165747],"type":"Point"}
}