{
  "type": "Feature",
  "properties": {
    "iso:country":"GB",
    "wof:name":"PE21 8BZ",
    "wof:placetype":"postalcode"
},
  "geometry": {"coordinates":[-0.04403892637758,52.97209999742681],"type":"Point"}
}