{
  "type": "Feature",
  "properties": {
    "iso:country":"GB",
    "wof:name":"E14 9WJ",
    "wof:placetype":"postalcode"
},
  "geometry": {"coordinates":[-0.02172938846259,51.49225883263459],"type":"Point"}
}