{
  "type": "Feature",
  "properties": {
    "iso:country":"GB",
    "wof:name":"SR5 2EH",
    "wof:placetype":"postalcode"
},
  "geometry": {"coordinates":[-1.40994290523812,54.92114778890234],"type":"Point"}
}