{
  "type": "Feature",
  "properties": {
    "iso:country": "GB",
    "wof:name": "AB32 6AL",
    "wof:placetype": "postalcode"
  },
  "geometry": {"coordinates":[-2.312103,57.14965],"type":"Point"}
}
