{
  "type": "Feature",
  "properties": {
    "iso:country":"GB",
    "wof:name":"AB32 6AL",
    "wof:placetype":"postalcode"
},
  "geometry": {"coordinates":[-2.31210325410211,57.14964994958075],"type":"Point"}
}