{
  "type": "Feature",
  "properties": {
    "date:inception_lower": "2010-09-01",
    "date:inception_upper": "2010-09-01",
    "iso:country": "GB",
    "wof:name": "AB32 6AL",
    "wof:placetype": "postalcode"
  },
  "geometry": {"coordinates":[-2.312103,57.14965],"type":"Point"}
}
