{
  "type": "Feature",
  "properties": {
    "iso:country":"GB",
    "wof:name":"TW15 3EY",
    "wof:placetype":"postalcode"
},
  "geometry": {"coordinates":[-0.4740724307162,51.44119680464168],"type":"Point"}
}