{
  "type": "Feature",
  "properties": {
    "iso:country": "GB",
    "wof:name": "TW15 3EY",
    "wof:placetype": "postalcode"
  },
  "geometry": {"coordinates":[-0.474072,51.441197],"type":"Point"}
}
