{
  "type": "Feature",
  "properties": {
    "date:inception_lower":"1992-01-01",
    "date:inception_upper":"1992-01-31",
    "iso:country":"GB",
    "wof:name":"TW15 3EY",
    "wof:placetype":"postalcode"
},
  "geometry": {"coordinates":[-0.474072,51.441197],"type":"Point"}
}