{
  "type": "Feature",
  "properties": {
    "iso:country":"GB",
    "wof:name":"WS8 6JH",
    "wof:placetype":"postalcode"
},
  "geometry": {"coordinates":[-1.92622711628937,52.65097990350407],"type":"Point"}
}