{
  "type": "Feature",
  "properties": {
    "date:inception_lower": "1995-07-01",
    "date:inception_upper": "1995-07-01",
    "iso:country": "GB",
    "wof:name": "CM6 3DD",
    "wof:placetype": "postalcode"
  },
  "geometry": {"coordinates":[0.435437,51.855131],"type":"Point"}
}
