{
  "type": "Feature",
  "properties": {
    "iso:country":"GB",
    "wof:name":"RH4 1ND",
    "wof:placetype":"postalcode"
},
  "geometry": {"coordinates":[-0.33593906969151,51.2389996037133],"type":"Point"}
}