{
  "type": "Feature",
  "properties": {
    "iso:country":"GB",
    "wof:name":"CF34 9LU",
    "wof:placetype":"postalcode"
},
  "geometry": {"coordinates":[-3.66109062861336,51.59975640446755],"type":"Point"}
}