{
  "type": "Feature",
  "properties": {
    "date:inception_lower": "1980-01-01",
    "date:inception_upper": "1980-01-01",
    "iso:country": "GB",
    "wof:name": "CF34 9LU",
    "wof:placetype": "postalcode"
  },
  "geometry": {"coordinates":[-3.661091,51.599756],"type":"Point"}
}
