{
  "type": "Feature",
  "properties": {
    "iso:country":"GB",
    "wof:name":"PO14 1PZ",
    "wof:placetype":"postalcode"
},
  "geometry": {"coordinates":[-1.20473839313694,50.84796630653315],"type":"Point"}
}