{
  "type": "Feature",
  "properties": {
    "date:inception_lower": "1980-01-01",
    "date:inception_upper": "1980-01-01",
    "iso:country": "GB",
    "wof:name": "PO14 1PZ",
    "wof:placetype": "postalcode"
  },
  "geometry": {"coordinates":[-1.204738,50.847966],"type":"Point"}
}
