{
  "type": "Feature",
  "properties": {
    "date:inception_lower":"2007-11-01",
    "date:inception_upper":"2007-11-30",
    "iso:country":"GB",
    "wof:name":"CB24 5AB",
    "wof:placetype":"postalcode"
},
  "geometry": {"coordinates":[0.070141,52.308479],"type":"Point"}
}