{
  "type": "Feature",
  "properties": {
    "iso:country": "GB",
    "wof:name": "CB24 5AB",
    "wof:placetype": "postalcode"
  },
  "geometry": {"coordinates":[0.070141,52.308479],"type":"Point"}
}
