{
  "type": "Feature",
  "properties": {
    "date:inception_lower": "1980-01-01",
    "date:inception_upper": "1980-01-01",
    "iso:country": "GB",
    "wof:name": "SG8 9PH",
    "wof:placetype": "postalcode"
  },
  "geometry": {"coordinates":[-0.054053,52.017085],"type":"Point"}
}
