{
  "type": "Feature",
  "properties": {
    "iso:country":"GB",
    "wof:name":"SG8 9PH",
    "wof:placetype":"postalcode"
},
  "geometry": {"coordinates":[-0.0540533747359,52.01708547816646],"type":"Point"}
}