{
  "type": "Feature",
  "properties": {
    "iso:country": "GB",
    "wof:name": "B37 5SA",
    "wof:placetype": "postalcode"
  },
  "geometry": {"coordinates":[-1.741076,52.475194],"type":"Point"}
}
