{
  "type": "Feature",
  "properties": {
    "iso:country":"GB",
    "wof:name":"S45 8HE",
    "wof:placetype":"postalcode"
},
  "geometry": {"coordinates":[-1.36825303949559,53.15713481676338],"type":"Point"}
}