{
  "type": "Feature",
  "properties": {
    "date:inception_lower": "1990-02-01",
    "date:inception_upper": "1990-02-01",
    "iso:country": "GB",
    "wof:name": "PR1 9XW",
    "wof:placetype": "postalcode"
  },
  "geometry": {"coordinates":[-2.713028,53.743481],"type":"Point"}
}
