{
  "type": "Feature",
  "properties": {
    "iso:country":"GB",
    "wof:name":"SA4 6QZ",
    "wof:placetype":"postalcode"
},
  "geometry": {"coordinates":[-4.0592194106921,51.66428837661967],"type":"Point"}
}