{
  "type": "Feature",
  "properties": {
    "date:inception_lower": "1993-01-01",
    "date:inception_upper": "1993-01-01",
    "iso:country": "GB",
    "wof:name": "SA4 6QZ",
    "wof:placetype": "postalcode"
  },
  "geometry": {"coordinates":[-4.059255,51.664302],"type":"Point"}
}
