{
  "type": "Feature",
  "properties": {
    "iso:country":"GB",
    "wof:name":"OL2 7BH",
    "wof:placetype":"postalcode"
},
  "geometry": {"coordinates":[-2.10226170831862,53.57515308619176],"type":"Point"}
}