{
  "type": "Feature",
  "properties": {
    "date:inception_lower":"1980-01-01",
    "date:inception_upper":"1980-01-31",
    "iso:country":"GB",
    "wof:name":"S3 7TW",
    "wof:placetype":"postalcode"
},
  "geometry": {"coordinates":[-1.480683,53.373842],"type":"Point"}
}