{
  "type": "Feature",
  "properties": {
    "iso:country":"GB",
    "wof:name":"S3 7TW",
    "wof:placetype":"postalcode"
},
  "geometry": {"coordinates":[-1.4807139877546,53.37383320787085],"type":"Point"}
}