{
  "type": "Feature",
  "properties": {
    "date:inception_lower":"1980-01-01",
    "date:inception_upper":"1980-01-31",
    "iso:country":"GB",
    "wof:name":"L7 5PN",
    "wof:placetype":"postalcode"
},
  "geometry": {"coordinates":[-2.946745,53.406981],"type":"Point"}
}