{
  "type": "Feature",
  "properties": {
    "iso:country":"GB",
    "wof:name":"L7 5PN",
    "wof:placetype":"postalcode"
},
  "geometry": {"coordinates":[-2.94674535515079,53.40698106798523],"type":"Point"}
}