{
  "type": "Feature",
  "properties": {
    "iso:country": "GB",
    "wof:name": "LE15 9PY",
    "wof:placetype": "postalcode"
  },
  "geometry": {"coordinates":[-0.720602,52.588368],"type":"Point"}
}
