{
  "type": "Feature",
  "properties": {
    "iso:country":"GB",
    "wof:name":"LE15 9PY",
    "wof:placetype":"postalcode"
},
  "geometry": {"coordinates":[-0.72060169327119,52.58836765480083],"type":"Point"}
}