{
  "type": "Feature",
  "properties": {
    "iso:country":"GB",
    "wof:name":"SA12 9PS",
    "wof:placetype":"postalcode"
},
  "geometry": {"coordinates":[-3.75934878444457,51.62066111264306],"type":"Point"}
}