{
  "type": "Feature",
  "properties": {
    "date:inception_lower":"1980-01-01",
    "date:inception_upper":"1980-01-31",
    "iso:country":"GB",
    "wof:name":"SA12 9PS",
    "wof:placetype":"postalcode"
},
  "geometry": {"coordinates":[-3.759349,51.620661],"type":"Point"}
}