{
  "type": "Feature",
  "properties": {
    "iso:country":"GB",
    "wof:name":"B61 0AF",
    "wof:placetype":"postalcode"
},
  "geometry": {"coordinates":[-2.05300362787632,52.34285178659714],"type":"Point"}
}