{
  "type": "Feature",
  "properties": {
    "date:inception_lower": "1997-12-01",
    "date:inception_upper": "1997-12-01",
    "iso:country": "GB",
    "wof:name": "B61 0AF",
    "wof:placetype": "postalcode"
  },
  "geometry": {"coordinates":[-2.053004,52.342852],"type":"Point"}
}
