{
  "type": "Feature",
  "properties": {
    "iso:country":"GB",
    "wof:name":"RG24 9BB",
    "wof:placetype":"postalcode"
},
  "geometry": {"coordinates":[-1.0757999778477,51.28605159711731],"type":"Point"}
}