{
  "type": "Feature",
  "properties": {
    "date:inception_lower": "1980-01-01",
    "date:inception_upper": "1980-01-01",
    "iso:country": "GB",
    "wof:name": "RG24 9BB",
    "wof:placetype": "postalcode"
  },
  "geometry": {"coordinates":[-1.0758,51.286052],"type":"Point"}
}
