{
  "type": "Feature",
  "properties": {
    "iso:country": "GB",
    "wof:name": "RG24 9BB",
    "wof:placetype": "postalcode"
  },
  "geometry": {"coordinates":[-1.0758,51.286052],"type":"Point"}
}
