{
  "type": "Feature",
  "properties": {
    "iso:country": "GB",
    "wof:name": "CF43 4BH",
    "wof:placetype": "postalcode"
  },
  "geometry": {"coordinates":[-3.481173,51.673103],"type":"Point"}
}
