{
  "type": "Feature",
  "properties": {
    "iso:country":"GB",
    "wof:name":"CH7 6BU",
    "wof:placetype":"postalcode"
},
  "geometry": {"coordinates":[-3.12848534022789,53.20807959342328],"type":"Point"}
}