{
  "type": "Feature",
  "properties": {
    "iso:country":"GB",
    "wof:name":"TA4 2LJ",
    "wof:placetype":"postalcode"
},
  "geometry": {"coordinates":[-3.31456428546345,51.04336597634259],"type":"Point"}
}