{
  "type": "Feature",
  "properties": {
    "date:inception_lower": "1984-02-01",
    "date:inception_upper": "1984-02-01",
    "iso:country": "GB",
    "wof:name": "TA4 2LJ",
    "wof:placetype": "postalcode"
  },
  "geometry": {"coordinates":[-3.314564,51.043366],"type":"Point"}
}
