{
  "type": "Feature",
  "properties": {
    "iso:country":"GB",
    "wof:name":"B66 3EB",
    "wof:placetype":"postalcode"
},
  "geometry": {"coordinates":[-1.95874444789406,52.49477957254761],"type":"Point"}
}