{
  "type": "Feature",
  "properties": {
    "iso:country": "GB",
    "wof:name": "B66 3EB",
    "wof:placetype": "postalcode"
  },
  "geometry": {"coordinates":[-1.958856,52.49484],"type":"Point"}
}
