{
  "type": "Feature",
  "properties": {
    "iso:country":"GB",
    "wof:name":"ME20 6PJ",
    "wof:placetype":"postalcode"
},
  "geometry": {"coordinates":[0.45021132000638,51.29528384492222],"type":"Point"}
}