{
  "type": "Feature",
  "properties": {
    "iso:country":"GB",
    "wof:name":"DN35 8TS",
    "wof:placetype":"postalcode"
},
  "geometry": {"coordinates":[-0.03113700214747,53.55153480293887],"type":"Point"}
}