{
  "type": "Feature",
  "properties": {
    "date:inception_lower": "2016-10-01",
    "date:inception_upper": "2016-10-01",
    "iso:country": "GB",
    "wof:name": "CB2 9EJ",
    "wof:placetype": "postalcode"
  },
  "geometry": {"coordinates":[0.117063,52.16676],"type":"Point"}
}
