{
  "type": "Feature",
  "properties": {
    "date:inception_lower":"1980-01-01",
    "date:inception_upper":"1980-01-31",
    "iso:country":"GB",
    "wof:name":"OL6 6SF",
    "wof:placetype":"postalcode"
},
  "geometry": {"coordinates":[-2.076759,53.486116],"type":"Point"}
}