{
  "type": "Feature",
  "properties": {
    "iso:country":"GB",
    "wof:name":"OL6 6SF",
    "wof:placetype":"postalcode"
},
  "geometry": {"coordinates":[-2.07675909704262,53.4861155376355],"type":"Point"}
}