{
  "type": "Feature",
  "properties": {
    "date:inception_lower": "1980-01-01",
    "date:inception_upper": "1980-01-01",
    "iso:country": "GB",
    "wof:name": "G46 6RW",
    "wof:placetype": "postalcode"
  },
  "geometry": {"coordinates":[-4.30358,55.792412],"type":"Point"}
}
