{
  "type": "Feature",
  "properties": {
    "iso:country": "GB",
    "wof:name": "G46 6RW",
    "wof:placetype": "postalcode"
  },
  "geometry": {"coordinates":[-4.30358,55.792412],"type":"Point"}
}
