{
  "type": "Feature",
  "properties": {
    "iso:country":"GB",
    "wof:name":"BH21 4BW",
    "wof:placetype":"postalcode"
},
  "geometry": {"coordinates":[-2.07284385853436,50.80153406168148],"type":"Point"}
}