{
  "type": "Feature",
  "properties": {
    "iso:country":"GB",
    "wof:name":"CF32 7NB",
    "wof:placetype":"postalcode"
},
  "geometry": {"coordinates":[-3.53752007644128,51.62021588341263],"type":"Point"}
}