{
  "type": "Feature",
  "properties": {
    "iso:country":"GB",
    "wof:name":"ST15 8JQ",
    "wof:placetype":"postalcode"
},
  "geometry": {"coordinates":[-2.14736850091889,52.90823541889737],"type":"Point"}
}