{
  "type": "Feature",
  "properties": {
    "date:inception_lower":"2019-03-01",
    "date:inception_upper":"2019-03-31",
    "iso:country":"GB",
    "wof:name":"LN1 2GB",
    "wof:placetype":"postalcode"
},
  "geometry": {"coordinates":[-0.742308,53.290755],"type":"Point"}
}