{
  "type": "Feature",
  "properties": {
    "date:inception_lower": "2019-03-01",
    "date:inception_upper": "2019-03-01",
    "iso:country": "GB",
    "wof:name": "LN1 2GB",
    "wof:placetype": "postalcode"
  },
  "geometry": {"coordinates":[-0.575686,53.336042],"type":"Point"}
}
