{
  "type": "Feature",
  "properties": {
    "iso:country": "GB",
    "wof:name": "LN1 2GB",
    "wof:placetype": "postalcode"
  },
  "geometry": {"coordinates":[-0.575686,53.336042],"type":"Point"}
}
