{
  "type": "Feature",
  "properties": {
    "iso:country": "GB",
    "wof:name": "LN1 2GB",
    "wof:placetype": "postalcode"
  },
  "geometry": {"coordinates":[-0.742308,53.290755],"type":"Point"}
}
