{
  "type": "Feature",
  "properties": {
    "date:inception_lower": "2013-11-01",
    "date:inception_upper": "2013-11-01",
    "iso:country": "GB",
    "wof:name": "TN34 3FQ",
    "wof:placetype": "postalcode"
  },
  "geometry": {"coordinates":[0.592258,50.870157],"type":"Point"}
}
