{
  "type": "Feature",
  "properties": {
    "iso:country": "GB",
    "wof:name": "TN34 3FQ",
    "wof:placetype": "postalcode"
  },
  "geometry": {"coordinates":[0.592258,50.870157],"type":"Point"}
}
