{
  "type": "Feature",
  "properties": {
    "date:inception_lower": "1998-12-01",
    "date:inception_upper": "1998-12-01",
    "iso:country": "GB",
    "wof:name": "HX3 0NH",
    "wof:placetype": "postalcode"
  },
  "geometry": {"coordinates":[-1.857509,53.704821],"type":"Point"}
}
