{
  "type": "Feature",
  "properties": {
    "iso:country":"GB",
    "wof:name":"SW8 4DY",
    "wof:placetype":"postalcode"
},
  "geometry": {"coordinates":[-0.14162635358922,51.47844727323479],"type":"Point"}
}