{
  "type": "Feature",
  "properties": {
    "iso:country": "GB",
    "wof:name": "NG2 7UJ",
    "wof:placetype": "postalcode"
  },
  "geometry": {"coordinates":[-1.14965,52.919301],"type":"Point"}
}
