{
  "type": "Feature",
  "properties": {
    "iso:country":"GB",
    "wof:name":"NG2 7UJ",
    "wof:placetype":"postalcode"
},
  "geometry": {"coordinates":[-1.14964965709606,52.91930053515102],"type":"Point"}
}