{
  "type": "Feature",
  "properties": {
    "iso:country": "GB",
    "wof:name": "SA14 6HE",
    "wof:placetype": "postalcode"
  },
  "geometry": {"coordinates":[-4.11499,51.786099],"type":"Point"}
}
