{
  "type": "Feature",
  "properties": {
    "iso:country": "GB",
    "wof:name": "WS9 8EQ",
    "wof:placetype": "postalcode"
  },
  "geometry": {"coordinates":[-1.930104,52.607416],"type":"Point"}
}
