{
  "type": "Feature",
  "properties": {
    "date:inception_lower":"1990-02-01",
    "date:inception_upper":"1990-02-28",
    "iso:country":"GB",
    "wof:name":"GL6 8HJ",
    "wof:placetype":"postalcode"
},
  "geometry": {"coordinates":[-2.160152,51.727781],"type":"Point"}
}