{
  "type": "Feature",
  "properties": {
    "iso:country":"GB",
    "wof:name":"GL6 8HJ",
    "wof:placetype":"postalcode"
},
  "geometry": {"coordinates":[-2.16041698540536,51.72773125920917],"type":"Point"}
}