{
  "type": "Feature",
  "properties": {
    "iso:country":"GB",
    "wof:name":"OL3 6DN",
    "wof:placetype":"postalcode"
},
  "geometry": {"coordinates":[-2.00649693062684,53.54997562419598],"type":"Point"}
}