{
  "type": "Feature",
  "properties": {
    "date:inception_lower": "1996-06-01",
    "date:inception_upper": "1996-06-01",
    "iso:country": "GB",
    "wof:name": "OL3 6DN",
    "wof:placetype": "postalcode"
  },
  "geometry": {"coordinates":[-2.006497,53.549976],"type":"Point"}
}
