{
  "type": "Feature",
  "properties": {
    "date:inception_lower": "2023-05-01",
    "date:inception_upper": "2023-05-01",
    "iso:country": "GB",
    "wof:name": "KA9 2FJ",
    "wof:placetype": "postalcode"
  },
  "geometry": {"coordinates":[-4.590646,55.518927],"type":"Point"}
}
