{
  "type": "Feature",
  "properties": {
    "iso:country": "GB",
    "wof:name": "CF64 4AS",
    "wof:placetype": "postalcode"
  },
  "geometry": {"coordinates":[-3.22593,51.434263],"type":"Point"}
}
