{
  "type": "Feature",
  "properties": {
    "iso:country":"GB",
    "wof:name":"S26 3XS",
    "wof:placetype":"postalcode"
},
  "geometry": {"coordinates":[-1.32379842567827,53.37252649620635],"type":"Point"}
}