{
  "type": "Feature",
  "properties": {
    "iso:country":"GB",
    "wof:name":"PA12 4JG",
    "wof:placetype":"postalcode"
},
  "geometry": {"coordinates":[-4.60753020599676,55.78436993898202],"type":"Point"}
}