{
  "type": "Feature",
  "properties": {
    "iso:country": "GB",
    "wof:name": "HA3 9PQ",
    "wof:placetype": "postalcode"
  },
  "geometry": {"coordinates":[-0.291941,51.592508],"type":"Point"}
}
