{
  "type": "Feature",
  "properties": {
    "iso:country":"GB",
    "wof:name":"CF71 7PE",
    "wof:placetype":"postalcode"
},
  "geometry": {"coordinates":[-3.52419291395196,51.44820844707704],"type":"Point"}
}