{
  "type": "Feature",
  "properties": {
    "iso:country":"GB",
    "wof:name":"SS3 0PY",
    "wof:placetype":"postalcode"
},
  "geometry": {"coordinates":[0.75996691248147,51.55183830672185],"type":"Point"}
}