{
  "type": "Feature",
  "properties": {
    "iso:country": "GB",
    "wof:name": "FY4 5BD",
    "wof:placetype": "postalcode"
  },
  "geometry": {"coordinates":[-3.018209,53.791225],"type":"Point"}
}
