{
  "type": "Feature",
  "properties": {
    "iso:country":"GB",
    "wof:name":"RG27 9BU",
    "wof:placetype":"postalcode"
},
  "geometry": {"coordinates":[-0.9722368639086,51.3067336335697],"type":"Point"}
}