{
  "type": "Feature",
  "properties": {
    "date:inception_lower": "1980-01-01",
    "date:inception_upper": "1980-01-01",
    "iso:country": "GB",
    "wof:name": "RG27 9BU",
    "wof:placetype": "postalcode"
  },
  "geometry": {"coordinates":[-0.972219,51.306734],"type":"Point"}
}
