{
  "type": "Feature",
  "properties": {
    "iso:country": "GB",
    "wof:name": "WN8 0AX",
    "wof:placetype": "postalcode"
  },
  "geometry": {"coordinates":[-2.741751,53.542164],"type":"Point"}
}
