{
  "type": "Feature",
  "properties": {
    "date:inception_lower": "1980-01-01",
    "date:inception_upper": "1980-01-01",
    "iso:country": "GB",
    "wof:name": "WN8 0AX",
    "wof:placetype": "postalcode"
  },
  "geometry": {"coordinates":[-2.741751,53.542164],"type":"Point"}
}
