{
  "type": "Feature",
  "properties": {
    "iso:country":"GB",
    "wof:name":"NN18 9AJ",
    "wof:placetype":"postalcode"
},
  "geometry": {"coordinates":[-0.72844496979731,52.47845396806832],"type":"Point"}
}