{
  "type": "Feature",
  "properties": {
    "iso:country":"GB",
    "wof:name":"CV31 2TE",
    "wof:placetype":"postalcode"
},
  "geometry": {"coordinates":[-1.53189636986224,52.26953875833319],"type":"Point"}
}