{
  "type": "Feature",
  "properties": {
    "iso:country": "GB",
    "wof:name": "YO61 1ES",
    "wof:placetype": "postalcode"
  },
  "geometry": {"coordinates":[-1.102631,54.049226],"type":"Point"}
}
