{
  "type": "Feature",
  "properties": {
    "date:inception_lower": "2023-10-01",
    "date:inception_upper": "2023-10-01",
    "iso:country": "GB",
    "wof:name": "CB6 3NY",
    "wof:placetype": "postalcode"
  },
  "geometry": {"coordinates":[0.223775,52.349162],"type":"Point"}
}
