{
  "type": "Feature",
  "properties": {
    "iso:country": "GB",
    "wof:name": "DN33 1LX",
    "wof:placetype": "postalcode"
  },
  "geometry": {"coordinates":[-0.108654,53.544093],"type":"Point"}
}
