{
  "type": "Feature",
  "properties": {
    "iso:country":"GB",
    "wof:name":"PL26 7XH",
    "wof:placetype":"postalcode"
},
  "geometry": {"coordinates":[-4.85996250578544,50.38142606808705],"type":"Point"}
}