{
  "type": "Feature",
  "properties": {
    "iso:country": "GB",
    "wof:name": "DE55 4QJ",
    "wof:placetype": "postalcode"
  },
  "geometry": {"coordinates":[-1.372076,53.0857],"type":"Point"}
}
