{
  "type": "Feature",
  "properties": {
    "date:inception_lower":"1985-10-01",
    "date:inception_upper":"1985-10-31",
    "iso:country":"GB",
    "wof:name":"DE55 4QJ",
    "wof:placetype":"postalcode"
},
  "geometry": {"coordinates":[-1.372076,53.0857],"type":"Point"}
}