{
  "type": "Feature",
  "properties": {
    "date:inception_lower": "2024-05-01",
    "date:inception_upper": "2024-05-01",
    "iso:country": "GB",
    "wof:name": "NR10 4FT",
    "wof:placetype": "postalcode"
  },
  "geometry": {"coordinates":[1.165258,52.768529],"type":"Point"}
}
