{
  "type": "Feature",
  "properties": {
    "iso:country":"GB",
    "wof:name":"DD4 6SS",
    "wof:placetype":"postalcode"
},
  "geometry": {"coordinates":[-2.95959944416394,56.47243239272947],"type":"Point"}
}