{
  "type": "Feature",
  "properties": {
    "date:inception_lower": "2007-09-01",
    "date:inception_upper": "2007-09-01",
    "iso:country": "GB",
    "wof:name": "DD4 6SS",
    "wof:placetype": "postalcode"
  },
  "geometry": {"coordinates":[-2.959599,56.472432],"type":"Point"}
}
