{
  "type": "Feature",
  "properties": {
    "iso:country":"GB",
    "wof:name":"DL5 4RY",
    "wof:placetype":"postalcode"
},
  "geometry": {"coordinates":[-1.56919047780751,54.63280806887693],"type":"Point"}
}