{
  "type": "Feature",
  "properties": {
    "date:inception_lower": "2020-02-01",
    "date:inception_upper": "2020-02-01",
    "iso:country": "GB",
    "wof:name": "HP20 1BW",
    "wof:placetype": "postalcode"
  },
  "geometry": {"coordinates":[-0.811317,51.816061],"type":"Point"}
}
