{
  "type": "Feature",
  "properties": {
    "iso:country":"GB",
    "wof:name":"WF9 3RF",
    "wof:placetype":"postalcode"
},
  "geometry": {"coordinates":[-1.3278929133727,53.58864489122766],"type":"Point"}
}