{
  "type": "Feature",
  "properties": {
    "iso:country": "GB",
    "wof:name": "WF9 3RF",
    "wof:placetype": "postalcode"
  },
  "geometry": {"coordinates":[-1.327893,53.588645],"type":"Point"}
}
