{
  "type": "Feature",
  "properties": {
    "date:inception_lower": "1981-09-01",
    "date:inception_upper": "1981-09-01",
    "iso:country": "GB",
    "wof:name": "WF4 2EH",
    "wof:placetype": "postalcode"
  },
  "geometry": {"coordinates":[-1.401075,53.626803],"type":"Point"}
}
