{
  "type": "Feature",
  "properties": {
    "iso:country": "GB",
    "wof:name": "WF4 2EH",
    "wof:placetype": "postalcode"
  },
  "geometry": {"coordinates":[-1.401075,53.626803],"type":"Point"}
}
