{
  "type": "Feature",
  "properties": {
    "iso:country":"GB",
    "wof:name":"ST7 3NQ",
    "wof:placetype":"postalcode"
},
  "geometry": {"coordinates":[-2.22212890383524,53.10821793809498],"type":"Point"}
}