{
  "type": "Feature",
  "properties": {
    "iso:country": "GB",
    "wof:name": "KY7 4SR",
    "wof:placetype": "postalcode"
  },
  "geometry": {"coordinates":[-3.161118,56.176904],"type":"Point"}
}
