{
  "type": "Feature",
  "properties": {
    "iso:country":"GB",
    "wof:name":"SK8 1NS",
    "wof:placetype":"postalcode"
},
  "geometry": {"coordinates":[-2.22226180244321,53.3909964820566],"type":"Point"}
}