{
  "type": "Feature",
  "properties": {
    "iso:country": "GB",
    "wof:name": "DE15 9EQ",
    "wof:placetype": "postalcode"
  },
  "geometry": {"coordinates":[-1.618043,52.793998],"type":"Point"}
}
