{
  "type": "Feature",
  "properties": {
    "iso:country":"GB",
    "wof:name":"DE15 9EQ",
    "wof:placetype":"postalcode"
},
  "geometry": {"coordinates":[-1.61804267839827,52.79399753178925],"type":"Point"}
}