{
  "type": "Feature",
  "properties": {
    "iso:country":"GB",
    "wof:name":"TW19 7QJ",
    "wof:placetype":"postalcode"
},
  "geometry": {"coordinates":[-0.47760663928381,51.45174570145821],"type":"Point"}
}