{
  "type": "Feature",
  "properties": {
    "iso:country": "GB",
    "wof:name": "TW19 7QJ",
    "wof:placetype": "postalcode"
  },
  "geometry": {"coordinates":[-0.477607,51.451746],"type":"Point"}
}
