{
  "type": "Feature",
  "properties": {
    "iso:country":"GB",
    "wof:name":"BH14 0AL",
    "wof:placetype":"postalcode"
},
  "geometry": {"coordinates":[-1.95014432775495,50.73054085639665],"type":"Point"}
}