{
  "type": "Feature",
  "properties": {
    "date:inception_lower": "1980-01-01",
    "date:inception_upper": "1980-01-01",
    "iso:country": "GB",
    "wof:name": "LA2 6DD",
    "wof:placetype": "postalcode"
  },
  "geometry": {"coordinates":[-2.810927,54.087281],"type":"Point"}
}
