{
  "type": "Feature",
  "properties": {
    "iso:country":"GB",
    "wof:name":"LA2 6DD",
    "wof:placetype":"postalcode"
},
  "geometry": {"coordinates":[-2.81092735612245,54.08728079476903],"type":"Point"}
}