{
  "type": "Feature",
  "properties": {
    "iso:country":"GB",
    "wof:name":"SL3 7NH",
    "wof:placetype":"postalcode"
},
  "geometry": {"coordinates":[-0.56904458456903,51.49851435422359],"type":"Point"}
}