{
  "type": "Feature",
  "properties": {
    "iso:country":"GB",
    "wof:name":"SA11 2DG",
    "wof:placetype":"postalcode"
},
  "geometry": {"coordinates":[-3.81461672239936,51.65028545326317],"type":"Point"}
}