{
  "type": "Feature",
  "properties": {
    "date:inception_lower": "1980-01-01",
    "date:inception_upper": "1980-01-01",
    "iso:country": "GB",
    "wof:name": "YO7 1BZ",
    "wof:placetype": "postalcode"
  },
  "geometry": {"coordinates":[-1.332538,54.236676],"type":"Point"}
}
