{
  "type": "Feature",
  "properties": {
    "iso:country": "GB",
    "wof:name": "YO7 1BZ",
    "wof:placetype": "postalcode"
  },
  "geometry": {"coordinates":[-1.332538,54.236676],"type":"Point"}
}
