{
  "type": "Feature",
  "properties": {
    "iso:country":"GB",
    "wof:name":"GU32 1JU",
    "wof:placetype":"postalcode"
},
  "geometry": {"coordinates":[-1.05163027041695,51.025496569674],"type":"Point"}
}