{
  "type": "Feature",
  "properties": {
    "iso:country": "GB",
    "wof:name": "GU32 1JU",
    "wof:placetype": "postalcode"
  },
  "geometry": {"coordinates":[-1.05163,51.025497],"type":"Point"}
}
