{
  "type": "Feature",
  "properties": {
    "iso:country":"GB",
    "wof:name":"HU8 9LF",
    "wof:placetype":"postalcode"
},
  "geometry": {"coordinates":[-0.29145511572906,53.78257199455267],"type":"Point"}
}