{
  "type": "Feature",
  "properties": {
    "iso:country":"GB",
    "wof:name":"EH26 9EF",
    "wof:placetype":"postalcode"
},
  "geometry": {"coordinates":[-3.226312360957,55.82569855392443],"type":"Point"}
}