{
  "type": "Feature",
  "properties": {
    "iso:country": "GB",
    "wof:name": "EH26 9EF",
    "wof:placetype": "postalcode"
  },
  "geometry": {"coordinates":[-3.226312,55.825699],"type":"Point"}
}
