{
  "type": "Feature",
  "properties": {
    "iso:country":"GB",
    "wof:name":"HX2 7PL",
    "wof:placetype":"postalcode"
},
  "geometry": {"coordinates":[-1.89016880076859,53.71625243570949],"type":"Point"}
}