{
  "type": "Feature",
  "properties": {
    "iso:country": "GB",
    "wof:name": "LS15 8AG",
    "wof:placetype": "postalcode"
  },
  "geometry": {"coordinates":[-1.432987,53.807747],"type":"Point"}
}
