{
  "type": "Feature",
  "properties": {
    "iso:country":"GB",
    "wof:name":"LS15 8AG",
    "wof:placetype":"postalcode"
},
  "geometry": {"coordinates":[-1.43298667933608,53.80774678616042],"type":"Point"}
}