{
  "type": "Feature",
  "properties": {
    "iso:country":"GB",
    "wof:name":"HA6 3QL",
    "wof:placetype":"postalcode"
},
  "geometry": {"coordinates":[-0.4114675686995,51.61225113409414],"type":"Point"}
}