{
  "type": "Feature",
  "properties": {
    "iso:country":"GB",
    "wof:name":"EX10 0QD",
    "wof:placetype":"postalcode"
},
  "geometry": {"coordinates":[-3.23044325408418,50.71741932049908],"type":"Point"}
}