{
  "type": "Feature",
  "properties": {
    "iso:country": "GB",
    "wof:name": "CH66 1RA",
    "wof:placetype": "postalcode"
  },
  "geometry": {"coordinates":[-2.949123,53.289359],"type":"Point"}
}
