{
  "type": "Feature",
  "properties": {
    "date:inception_lower": "1980-01-01",
    "date:inception_upper": "1980-01-01",
    "iso:country": "GB",
    "wof:name": "SO21 1JS",
    "wof:placetype": "postalcode"
  },
  "geometry": {"coordinates":[-1.221058,51.013395],"type":"Point"}
}
