{
  "type": "Feature",
  "properties": {
    "iso:country":"GB",
    "wof:name":"SO21 1JS",
    "wof:placetype":"postalcode"
},
  "geometry": {"coordinates":[-1.22105790127779,51.01339471611857],"type":"Point"}
}