{
  "type": "Feature",
  "properties": {
    "iso:country":"GB",
    "wof:name":"PE3 9UW",
    "wof:placetype":"postalcode"
},
  "geometry": {"coordinates":[-0.27580328485867,52.58192695777425],"type":"Point"}
}