{
  "type": "Feature",
  "properties": {
    "iso:country": "GB",
    "wof:name": "BS36 2RQ",
    "wof:placetype": "postalcode"
  },
  "geometry": {"coordinates":[-2.474843,51.528235],"type":"Point"}
}
