{
  "type": "Feature",
  "properties": {
    "iso:country":"GB",
    "wof:name":"BS36 2RQ",
    "wof:placetype":"postalcode"
},
  "geometry": {"coordinates":[-2.47484265042162,51.5282351127757],"type":"Point"}
}