{
  "type": "Feature",
  "properties": {
    "iso:country":"GB",
    "wof:name":"NR7 0DR",
    "wof:placetype":"postalcode"
},
  "geometry": {"coordinates":[1.338838259804,52.63439229988101],"type":"Point"}
}