{
  "type": "Feature",
  "properties": {
    "iso:country": "GB",
    "wof:name": "NR7 0DR",
    "wof:placetype": "postalcode"
  },
  "geometry": {"coordinates":[1.338838,52.634392],"type":"Point"}
}
