{
  "type": "Feature",
  "properties": {
    "date:inception_lower": "2008-04-01",
    "date:inception_upper": "2008-04-01",
    "iso:country": "GB",
    "wof:name": "RG40 3GZ",
    "wof:placetype": "postalcode"
  },
  "geometry": {"coordinates":[-0.784005,51.383081],"type":"Point"}
}
