{
  "type": "Feature",
  "properties": {
    "iso:country":"GB",
    "wof:name":"RG40 3GZ",
    "wof:placetype":"postalcode"
},
  "geometry": {"coordinates":[-0.78400509034655,51.38308148535688],"type":"Point"}
}