{
  "type": "Feature",
  "properties": {
    "date:inception_lower": "1982-03-01",
    "date:inception_upper": "1982-03-01",
    "iso:country": "GB",
    "wof:name": "CV11 6TP",
    "wof:placetype": "postalcode"
  },
  "geometry": {"coordinates":[-1.424362,52.506846],"type":"Point"}
}
