{
  "type": "Feature",
  "properties": {
    "iso:country":"GB",
    "wof:name":"CV11 6TP",
    "wof:placetype":"postalcode"
},
  "geometry": {"coordinates":[-1.42436236618324,52.50684591107461],"type":"Point"}
}