{
  "type": "Feature",
  "properties": {
    "iso:country":"GB",
    "wof:name":"IP19 0AT",
    "wof:placetype":"postalcode"
},
  "geometry": {"coordinates":[1.46190935086089,52.34729684319456],"type":"Point"}
}