{
  "type": "Feature",
  "properties": {
    "iso:country": "GB",
    "wof:name": "IP19 0AT",
    "wof:placetype": "postalcode"
  },
  "geometry": {"coordinates":[1.461909,52.347297],"type":"Point"}
}
