{
  "type": "Feature",
  "properties": {
    "iso:country":"GB",
    "wof:name":"S74 0PT",
    "wof:placetype":"postalcode"
},
  "geometry": {"coordinates":[-1.4666085672089,53.49944086002208],"type":"Point"}
}