{
  "type": "Feature",
  "properties": {
    "iso:country":"GB",
    "wof:name":"CB25 0BL",
    "wof:placetype":"postalcode"
},
  "geometry": {"coordinates":[0.32707254040554,52.28779053560476],"type":"Point"}
}