{
  "type": "Feature",
  "properties": {
    "iso:country":"GB",
    "wof:name":"FK10 1RU",
    "wof:placetype":"postalcode"
},
  "geometry": {"coordinates":[-3.7825991997778,56.1172485999932],"type":"Point"}
}