{
  "type": "Feature",
  "properties": {
    "iso:country":"GB",
    "wof:name":"PR2 2HJ",
    "wof:placetype":"postalcode"
},
  "geometry": {"coordinates":[-2.72099277609983,53.77473952036978],"type":"Point"}
}