{
  "type": "Feature",
  "properties": {
    "date:inception_lower": "1985-10-01",
    "date:inception_upper": "1985-10-01",
    "iso:country": "GB",
    "wof:name": "BA1 3DL",
    "wof:placetype": "postalcode"
  },
  "geometry": {"coordinates":[-2.382214,51.383971],"type":"Point"}
}
