{
  "type": "Feature",
  "properties": {
    "iso:country":"GB",
    "wof:name":"BA1 3DL",
    "wof:placetype":"postalcode"
},
  "geometry": {"coordinates":[-2.38221417883616,51.3839711224841],"type":"Point"}
}