{
  "type": "Feature",
  "properties": {
    "date:inception_lower": "1995-12-01",
    "date:inception_upper": "1995-12-01",
    "iso:country": "GB",
    "wof:name": "BD10 8WG",
    "wof:placetype": "postalcode"
  },
  "geometry": {"coordinates":[-1.748314,53.837898],"type":"Point"}
}
