{
  "type": "Feature",
  "properties": {
    "iso:country":"GB",
    "wof:name":"BD10 8WG",
    "wof:placetype":"postalcode"
},
  "geometry": {"coordinates":[-1.74831380514657,53.83789823247737],"type":"Point"}
}