{
  "type": "Feature",
  "properties": {
    "iso:country": "GB",
    "wof:name": "BD10 8WG",
    "wof:placetype": "postalcode"
  },
  "geometry": {"coordinates":[-1.748314,53.837898],"type":"Point"}
}
