{
  "type": "Feature",
  "properties": {
    "iso:country":"GB",
    "wof:name":"TW8 8JN",
    "wof:placetype":"postalcode"
},
  "geometry": {"coordinates":[-0.31486769299525,51.48239573090314],"type":"Point"}
}