{
  "type": "Feature",
  "properties": {
    "iso:country": "GB",
    "wof:name": "EX12 3JT",
    "wof:placetype": "postalcode"
  },
  "geometry": {"coordinates":[-3.097584,50.700373],"type":"Point"}
}
