{
  "type": "Feature",
  "properties": {
    "iso:country":"GB",
    "wof:name":"LS15 4PF",
    "wof:placetype":"postalcode"
},
  "geometry": {"coordinates":[-1.39329642469218,53.83056214973634],"type":"Point"}
}