{
  "type": "Feature",
  "properties": {
    "date:inception_lower": "1995-07-01",
    "date:inception_upper": "1995-07-01",
    "iso:country": "GB",
    "wof:name": "LS15 4PF",
    "wof:placetype": "postalcode"
  },
  "geometry": {"coordinates":[-1.393296,53.830562],"type":"Point"}
}
