{
  "type": "Feature",
  "properties": {
    "iso:country":"GB",
    "wof:name":"PR26 7XH",
    "wof:placetype":"postalcode"
},
  "geometry": {"coordinates":[-2.72500964639206,53.69083676238947],"type":"Point"}
}