{
  "type": "Feature",
  "properties": {
    "date:inception_lower":"2001-06-01",
    "date:inception_upper":"2001-06-30",
    "iso:country":"GB",
    "wof:name":"PR26 7XH",
    "wof:placetype":"postalcode"
},
  "geometry": {"coordinates":[-2.72501,53.690837],"type":"Point"}
}