{
  "type": "Feature",
  "properties": {
    "iso:country": "GB",
    "wof:name": "LL40 2YL",
    "wof:placetype": "postalcode"
  },
  "geometry": {"coordinates":[-3.882851,52.746563],"type":"Point"}
}
