{
  "type": "Feature",
  "properties": {
    "iso:country":"GB",
    "wof:name":"LL40 2YL",
    "wof:placetype":"postalcode"
},
  "geometry": {"coordinates":[-3.88285081486664,52.74656303068245],"type":"Point"}
}