{
  "type": "Feature",
  "properties": {
    "iso:country":"GB",
    "wof:name":"CA99 1AE",
    "wof:placetype":"postalcode"
},
  "geometry": {"coordinates":[-2.94377568493376,54.89056853056803],"type":"Point"}
}