{
  "type": "Feature",
  "properties": {
    "iso:country":"GB",
    "wof:name":"SW9 9UU",
    "wof:placetype":"postalcode"
},
  "geometry": {"coordinates":[-0.11838212327834,51.46447078123847],"type":"Point"}
}