{
  "type": "Feature",
  "properties": {
    "iso:country": "GB",
    "wof:name": "PO31 7TT",
    "wof:placetype": "postalcode"
  },
  "geometry": {"coordinates":[-1.29868,50.764073],"type":"Point"}
}
