{
  "type": "Feature",
  "properties": {
    "date:inception_lower": "1980-01-01",
    "date:inception_upper": "1980-01-01",
    "iso:country": "GB",
    "wof:name": "PO31 7TT",
    "wof:placetype": "postalcode"
  },
  "geometry": {"coordinates":[-1.29868,50.764073],"type":"Point"}
}
