{
  "type": "Feature",
  "properties": {
    "date:inception_lower":"2000-12-01",
    "date:inception_upper":"2000-12-31",
    "iso:country":"GB",
    "wof:name":"CT6 5RJ",
    "wof:placetype":"postalcode"
},
  "geometry": {"coordinates":[1.122222,51.360136],"type":"Point"}
}