{
  "type": "Feature",
  "properties": {
    "iso:country": "GB",
    "wof:name": "CT6 5RJ",
    "wof:placetype": "postalcode"
  },
  "geometry": {"coordinates":[1.122222,51.360136],"type":"Point"}
}
