{
  "type": "Feature",
  "properties": {
    "iso:country":"GB",
    "wof:name":"CT6 5RJ",
    "wof:placetype":"postalcode"
},
  "geometry": {"coordinates":[1.12222165686026,51.3601360660823],"type":"Point"}
}