{
  "type": "Feature",
  "properties": {
    "iso:country":"GB",
    "wof:name":"ME15 6QB",
    "wof:placetype":"postalcode"
},
  "geometry": {"coordinates":[0.52556395261164,51.26755547691424],"type":"Point"}
}