{
  "type": "Feature",
  "properties": {
    "iso:country": "GB",
    "wof:name": "ME15 6QB",
    "wof:placetype": "postalcode"
  },
  "geometry": {"coordinates":[0.525564,51.267555],"type":"Point"}
}
