{
  "type": "Feature",
  "properties": {
    "iso:country":"GB",
    "wof:name":"S73 0YA",
    "wof:placetype":"postalcode"
},
  "geometry": {"coordinates":[-1.37201702098092,53.51339021492166],"type":"Point"}
}