{
  "type": "Feature",
  "properties": {
    "iso:country": "GB",
    "wof:name": "S73 0YA",
    "wof:placetype": "postalcode"
  },
  "geometry": {"coordinates":[-1.372017,53.51339],"type":"Point"}
}
