{
  "type": "Feature",
  "properties": {
    "date:inception_lower": "1995-01-01",
    "date:inception_upper": "1995-01-01",
    "iso:country": "GB",
    "wof:name": "SA31 1GY",
    "wof:placetype": "postalcode"
  },
  "geometry": {"coordinates":[-4.304249,51.860057],"type":"Point"}
}
