{
  "type": "Feature",
  "properties": {
    "iso:country":"GB",
    "wof:name":"ME15 6LL",
    "wof:placetype":"postalcode"
},
  "geometry": {"coordinates":[0.52330970742746,51.27141743989276],"type":"Point"}
}