{
  "type": "Feature",
  "properties": {
    "iso:country": "GB",
    "wof:name": "ME15 6LL",
    "wof:placetype": "postalcode"
  },
  "geometry": {"coordinates":[0.52331,51.271417],"type":"Point"}
}
