{
  "type": "Feature",
  "properties": {
    "iso:country":"GB",
    "wof:name":"ME12 4PH",
    "wof:placetype":"postalcode"
},
  "geometry": {"coordinates":[0.90163045000963,51.41068319751723],"type":"Point"}
}