{
  "type": "Feature",
  "properties": {
    "date:inception_lower": "1980-01-01",
    "date:inception_upper": "1980-01-01",
    "iso:country": "GB",
    "wof:name": "BA14 7AX",
    "wof:placetype": "postalcode"
  },
  "geometry": {"coordinates":[-2.206361,51.314476],"type":"Point"}
}
