{
  "type": "Feature",
  "properties": {
    "date:inception_lower":"1984-10-01",
    "date:inception_upper":"1984-10-31",
    "iso:country":"GB",
    "wof:name":"MK15 9BH",
    "wof:placetype":"postalcode"
},
  "geometry": {"coordinates":[-0.739202,52.054004],"type":"Point"}
}