{
  "type": "Feature",
  "properties": {
    "date:inception_lower": "1997-12-01",
    "date:inception_upper": "1997-12-01",
    "iso:country": "GB",
    "wof:name": "BS39 4LL",
    "wof:placetype": "postalcode"
  },
  "geometry": {"coordinates":[-2.511645,51.381604],"type":"Point"}
}
