{
  "type": "Feature",
  "properties": {
    "iso:country": "GB",
    "wof:name": "WD19 5AN",
    "wof:placetype": "postalcode"
  },
  "geometry": {"coordinates":[-0.382882,51.633478],"type":"Point"}
}
