{
  "type": "Feature",
  "properties": {
    "date:inception_lower":"2000-10-01",
    "date:inception_upper":"2000-10-31",
    "iso:country":"GB",
    "wof:name":"WD19 5AN",
    "wof:placetype":"postalcode"
},
  "geometry": {"coordinates":[-0.382882,51.633478],"type":"Point"}
}