{
  "type": "Feature",
  "properties": {
    "iso:country":"GB",
    "wof:name":"CA14 5BD",
    "wof:placetype":"postalcode"
},
  "geometry": {"coordinates":[-3.55472021227146,54.62726558293643],"type":"Point"}
}