{
  "type": "Feature",
  "properties": {
    "date:inception_lower": "2018-04-01",
    "date:inception_upper": "2018-04-01",
    "iso:country": "GB",
    "wof:name": "BB5 5SJ",
    "wof:placetype": "postalcode"
  },
  "geometry": {"coordinates":[-2.387902,53.784654],"type":"Point"}
}
