{
  "type": "Feature",
  "properties": {
    "iso:country":"GB",
    "wof:name":"TN8 5DH",
    "wof:placetype":"postalcode"
},
  "geometry": {"coordinates":[0.06806378904743,51.19312254065287],"type":"Point"}
}