{
  "type": "Feature",
  "properties": {
    "date:inception_lower": "1980-01-01",
    "date:inception_upper": "1980-01-01",
    "iso:country": "GB",
    "wof:name": "S9 1NS",
    "wof:placetype": "postalcode"
  },
  "geometry": {"coordinates":[-1.421775,53.422947],"type":"Point"}
}
