{
  "type": "Feature",
  "properties": {
    "date:inception_lower":"1990-07-01",
    "date:inception_upper":"1990-07-31",
    "iso:country":"GB",
    "wof:name":"NG31 8FJ",
    "wof:placetype":"postalcode"
},
  "geometry": {"coordinates":[-0.639802,52.917912],"type":"Point"}
}