{
  "type": "Feature",
  "properties": {
    "iso:country":"GB",
    "wof:name":"NG31 8FJ",
    "wof:placetype":"postalcode"
},
  "geometry": {"coordinates":[-0.63980204338239,52.91791167897033],"type":"Point"}
}