{
  "type": "Feature",
  "properties": {
    "date:inception_lower": "2010-06-01",
    "date:inception_upper": "2010-06-01",
    "iso:country": "GB",
    "wof:name": "KT1 2BF",
    "wof:placetype": "postalcode"
  },
  "geometry": {"coordinates":[-0.308454,51.399753],"type":"Point"}
}
