{
  "type": "Feature",
  "properties": {
    "iso:country":"GB",
    "wof:name":"OX10 6NY",
    "wof:placetype":"postalcode"
},
  "geometry": {"coordinates":[-1.10537057183737,51.62616130436513],"type":"Point"}
}