{
  "type": "Feature",
  "properties": {
    "date:inception_lower": "1990-07-01",
    "date:inception_upper": "1990-07-01",
    "iso:country": "GB",
    "wof:name": "CM7 4LR",
    "wof:placetype": "postalcode"
  },
  "geometry": {"coordinates":[0.449545,51.966915],"type":"Point"}
}
