{
  "type": "Feature",
  "properties": {
    "iso:country":"GB",
    "wof:name":"TQ7 3QF",
    "wof:placetype":"postalcode"
},
  "geometry": {"coordinates":[-3.79171393788763,50.2793904538534],"type":"Point"}
}