{
  "type": "Feature",
  "properties": {
    "date:inception_lower":"1990-02-01",
    "date:inception_upper":"1990-02-28",
    "iso:country":"GB",
    "wof:name":"BD23 4NP",
    "wof:placetype":"postalcode"
},
  "geometry": {"coordinates":[-2.2505,54.015157],"type":"Point"}
}