{
  "type": "Feature",
  "properties": {
    "date:inception_lower":"1998-06-01",
    "date:inception_upper":"1998-06-30",
    "iso:country":"GB",
    "wof:name":"YO1 7HU",
    "wof:placetype":"postalcode"
},
  "geometry": {"coordinates":[-1.082162,53.960784],"type":"Point"}
}