{
  "type": "Feature",
  "properties": {
    "iso:country":"GB",
    "wof:name":"YO1 7HU",
    "wof:placetype":"postalcode"
},
  "geometry": {"coordinates":[-1.08206874811979,53.96088194631309],"type":"Point"}
}