{
  "type": "Feature",
  "properties": {
    "iso:country":"GB",
    "wof:name":"EX16 6PG",
    "wof:placetype":"postalcode"
},
  "geometry": {"coordinates":[-3.48888536668571,50.90230713417556],"type":"Point"}
}