{
  "type": "Feature",
  "properties": {
    "iso:country":"GB",
    "wof:name":"LL29 9DW",
    "wof:placetype":"postalcode"
},
  "geometry": {"coordinates":[-3.68925047076477,53.29018667736867],"type":"Point"}
}