{
  "type": "Feature",
  "properties": {
    "iso:country": "GB",
    "wof:name": "LL29 9DW",
    "wof:placetype": "postalcode"
  },
  "geometry": {"coordinates":[-3.68925,53.290187],"type":"Point"}
}
