{
  "type": "Feature",
  "properties": {
    "iso:country": "GB",
    "wof:name": "AB43 9SP",
    "wof:placetype": "postalcode"
  },
  "geometry": {"coordinates":[-2.02524,57.682077],"type":"Point"}
}
