{
  "type": "Feature",
  "properties": {
    "iso:country": "GB",
    "wof:name": "LS98 1FD",
    "wof:placetype": "postalcode"
  },
  "geometry": {"coordinates":[-1.517535,53.773728],"type":"Point"}
}
