{
  "type": "Feature",
  "properties": {
    "iso:country":"GB",
    "wof:name":"LS98 1FD",
    "wof:placetype":"postalcode"
},
  "geometry": {"coordinates":[-1.5175349871152,53.77372816320449],"type":"Point"}
}