{
  "type": "Feature",
  "properties": {
    "iso:country":"GB",
    "wof:name":"B24 9LY",
    "wof:placetype":"postalcode"
},
  "geometry": {"coordinates":[-1.82199279423231,52.51848548206047],"type":"Point"}
}