{
  "type": "Feature",
  "properties": {
    "date:inception_lower": "1980-01-01",
    "date:inception_upper": "1980-01-01",
    "iso:country": "GB",
    "wof:name": "B24 9LY",
    "wof:placetype": "postalcode"
  },
  "geometry": {"coordinates":[-1.821993,52.518485],"type":"Point"}
}
