{
  "type": "Feature",
  "properties": {
    "iso:country":"GB",
    "wof:name":"SN4 0ND",
    "wof:placetype":"postalcode"
},
  "geometry": {"coordinates":[-1.73526615385938,51.51756078763641],"type":"Point"}
}