{
  "type": "Feature",
  "properties": {
    "date:inception_lower": "1985-04-01",
    "date:inception_upper": "1985-04-01",
    "iso:country": "GB",
    "wof:name": "SN4 0ND",
    "wof:placetype": "postalcode"
  },
  "geometry": {"coordinates":[-1.735266,51.517561],"type":"Point"}
}
