{
  "type": "Feature",
  "properties": {
    "iso:country": "GB",
    "wof:name": "CW11 4DD",
    "wof:placetype": "postalcode"
  },
  "geometry": {"coordinates":[-2.364871,53.141385],"type":"Point"}
}
