{
  "type": "Feature",
  "properties": {
    "iso:country": "GB",
    "wof:name": "BS35 3RR",
    "wof:placetype": "postalcode"
  },
  "geometry": {"coordinates":[-2.528276,51.588879],"type":"Point"}
}
