{
  "type": "Feature",
  "properties": {
    "date:inception_lower": "2022-08-01",
    "date:inception_upper": "2022-08-01",
    "iso:country": "GB",
    "wof:name": "CB9 7YZ",
    "wof:placetype": "postalcode"
  },
  "geometry": {"coordinates":[0.453817,52.093752],"type":"Point"}
}
