{
  "type": "Feature",
  "properties": {
    "iso:country":"GB",
    "wof:name":"DN1 1SF",
    "wof:placetype":"postalcode"
},
  "geometry": {"coordinates":[-1.13743060352414,53.52221139076415],"type":"Point"}
}