{
  "type": "Feature",
  "properties": {
    "iso:country":"GB",
    "wof:name":"LS21 2NS",
    "wof:placetype":"postalcode"
},
  "geometry": {"coordinates":[-1.74610733773965,53.97910115407796],"type":"Point"}
}