{
  "type": "Feature",
  "properties": {
    "iso:country": "GB",
    "wof:name": "LS21 2NS",
    "wof:placetype": "postalcode"
  },
  "geometry": {"coordinates":[-1.746107,53.979101],"type":"Point"}
}
