{
  "type": "Feature",
  "properties": {
    "iso:country":"GB",
    "wof:name":"CF24 2BT",
    "wof:placetype":"postalcode"
},
  "geometry": {"coordinates":[-3.15807650589719,51.47997592014526],"type":"Point"}
}