{
  "type": "Feature",
  "properties": {
    "iso:country":"GB",
    "wof:name":"E15 3HH",
    "wof:placetype":"postalcode"
},
  "geometry": {"coordinates":[0.01301913632229,51.53316871993874],"type":"Point"}
}