{
  "type": "Feature",
  "properties": {
    "iso:country": "GB",
    "wof:name": "BB9 7RA",
    "wof:placetype": "postalcode"
  },
  "geometry": {"coordinates":[-2.207147,53.840715],"type":"Point"}
}
