{
  "type": "Feature",
  "properties": {
    "iso:country":"GB",
    "wof:name":"BB9 7RA",
    "wof:placetype":"postalcode"
},
  "geometry": {"coordinates":[-2.20714721324039,53.84071471145736],"type":"Point"}
}