{
  "type": "Feature",
  "properties": {
    "date:inception_lower": "1980-01-01",
    "date:inception_upper": "1980-01-01",
    "iso:country": "GB",
    "wof:name": "PL8 1DY",
    "wof:placetype": "postalcode"
  },
  "geometry": {"coordinates":[-4.036085,50.311724],"type":"Point"}
}
