{
  "type": "Feature",
  "properties": {
    "iso:country": "GB",
    "wof:name": "PL8 1DY",
    "wof:placetype": "postalcode"
  },
  "geometry": {"coordinates":[-4.036375,50.311616],"type":"Point"}
}
