{
  "type": "Feature",
  "properties": {
    "iso:country":"GB",
    "wof:name":"PL8 1DY",
    "wof:placetype":"postalcode"
},
  "geometry": {"coordinates":[-4.03637462369733,50.31161621623338],"type":"Point"}
}