{
  "type": "Feature",
  "properties": {
    "date:inception_lower":"1980-01-01",
    "date:inception_upper":"1980-01-31",
    "iso:country":"GB",
    "wof:name":"EX20 2TH",
    "wof:placetype":"postalcode"
},
  "geometry": {"coordinates":[-3.964718,50.781068],"type":"Point"}
}