{
  "type": "Feature",
  "properties": {
    "iso:country":"GB",
    "wof:name":"EX20 2TH",
    "wof:placetype":"postalcode"
},
  "geometry": {"coordinates":[-3.96021202748679,50.78340826163237],"type":"Point"}
}