{
  "type": "Feature",
  "properties": {
    "date:inception_lower": "1980-01-01",
    "date:inception_upper": "1980-01-01",
    "iso:country": "GB",
    "wof:name": "EX32 8DY",
    "wof:placetype": "postalcode"
  },
  "geometry": {"coordinates":[-4.043992,51.077431],"type":"Point"}
}
