{
  "type": "Feature",
  "properties": {
    "date:inception_lower":"1980-01-01",
    "date:inception_upper":"1980-01-31",
    "iso:country":"GB",
    "wof:name":"EX32 8DY",
    "wof:placetype":"postalcode"
},
  "geometry": {"coordinates":[-4.043955,51.077425],"type":"Point"}
}