{
  "type": "Feature",
  "properties": {
    "date:inception_lower":"1980-01-01",
    "date:inception_upper":"1980-01-31",
    "iso:country":"GB",
    "wof:name":"PE34 4DX",
    "wof:placetype":"postalcode"
},
  "geometry": {"coordinates":[0.355053,52.754893],"type":"Point"}
}