{
  "type": "Feature",
  "properties": {
    "iso:country":"GB",
    "wof:name":"B37 7QW",
    "wof:placetype":"postalcode"
},
  "geometry": {"coordinates":[-1.73151811500658,52.47804003372007],"type":"Point"}
}