{
  "type": "Feature",
  "properties": {
    "date:inception_lower": "2016-02-01",
    "date:inception_upper": "2016-02-01",
    "iso:country": "GB",
    "wof:name": "B37 7QW",
    "wof:placetype": "postalcode"
  },
  "geometry": {"coordinates":[-1.731261,52.477901],"type":"Point"}
}
