{
  "type": "Feature",
  "properties": {
    "iso:country":"GB",
    "wof:name":"ST4 4QY",
    "wof:placetype":"postalcode"
},
  "geometry": {"coordinates":[-2.19905871208244,52.9775211228857],"type":"Point"}
}