{
  "type": "Feature",
  "properties": {
    "iso:country":"GB",
    "wof:name":"G76 0LP",
    "wof:placetype":"postalcode"
},
  "geometry": {"coordinates":[-4.27811916593862,55.74322147385494],"type":"Point"}
}