{
  "type": "Feature",
  "properties": {
    "iso:country":"GB",
    "wof:name":"NN14 6EN",
    "wof:placetype":"postalcode"
},
  "geometry": {"coordinates":[-0.81238135160793,52.4212925555941],"type":"Point"}
}