{
  "type": "Feature",
  "properties": {
    "iso:country":"GB",
    "wof:name":"RG12 9JU",
    "wof:placetype":"postalcode"
},
  "geometry": {"coordinates":[-0.72850506713766,51.40702297525137],"type":"Point"}
}