{
  "type": "Feature",
  "properties": {
    "iso:country":"GB",
    "wof:name":"ST16 3QS",
    "wof:placetype":"postalcode"
},
  "geometry": {"coordinates":[-2.09923766034525,52.81722308716503],"type":"Point"}
}