{
  "type": "Feature",
  "properties": {
    "iso:country":"GB",
    "wof:name":"HD2 2TW",
    "wof:placetype":"postalcode"
},
  "geometry": {"coordinates":[-1.79313261757635,53.66068558075284],"type":"Point"}
}