{
  "type": "Feature",
  "properties": {
    "date:inception_lower": "2021-01-01",
    "date:inception_upper": "2021-01-01",
    "iso:country": "GB",
    "wof:name": "G77 6GX",
    "wof:placetype": "postalcode"
  },
  "geometry": {"coordinates":[-4.347721,55.76904],"type":"Point"}
}
