{
  "type": "Feature",
  "properties": {
    "iso:country": "GB",
    "wof:name": "LU5 6QJ",
    "wof:placetype": "postalcode"
  },
  "geometry": {"coordinates":[-0.532223,51.949592],"type":"Point"}
}
