{
  "type": "Feature",
  "properties": {
    "date:inception_lower": "1994-12-01",
    "date:inception_upper": "1994-12-01",
    "iso:country": "GB",
    "wof:name": "LU5 6QJ",
    "wof:placetype": "postalcode"
  },
  "geometry": {"coordinates":[-0.532223,51.949592],"type":"Point"}
}
