{
  "type": "Feature",
  "properties": {
    "iso:country":"GB",
    "wof:name":"LU5 6QJ",
    "wof:placetype":"postalcode"
},
  "geometry": {"coordinates":[-0.53222258140543,51.94959168753067],"type":"Point"}
}