{
  "type": "Feature",
  "properties": {
    "iso:country": "GB",
    "wof:name": "HA3 5HE",
    "wof:placetype": "postalcode"
  },
  "geometry": {"coordinates":[-0.342187,51.602034],"type":"Point"}
}
