{
  "type": "Feature",
  "properties": {
    "date:inception_lower":"1990-07-01",
    "date:inception_upper":"1990-07-31",
    "iso:country":"GB",
    "wof:name":"HD8 9DB",
    "wof:placetype":"postalcode"
},
  "geometry": {"coordinates":[-1.645377,53.588775],"type":"Point"}
}