{
  "type": "Feature",
  "properties": {
    "iso:country":"GB",
    "wof:name":"BA20 1DY",
    "wof:placetype":"postalcode"
},
  "geometry": {"coordinates":[-2.6355696910357,50.94300365678894],"type":"Point"}
}