{
  "type": "Feature",
  "properties": {
    "date:inception_lower": "1980-01-01",
    "date:inception_upper": "1980-01-01",
    "iso:country": "GB",
    "wof:name": "BA20 1DY",
    "wof:placetype": "postalcode"
  },
  "geometry": {"coordinates":[-2.63557,50.942996],"type":"Point"}
}
