{
  "type": "Feature",
  "properties": {
    "iso:country": "GB",
    "wof:name": "DN37 7JZ",
    "wof:placetype": "postalcode"
  },
  "geometry": {"coordinates":[-0.197152,53.525467],"type":"Point"}
}
