{
  "type": "Feature",
  "properties": {
    "iso:country":"GB",
    "wof:name":"DN37 7JZ",
    "wof:placetype":"postalcode"
},
  "geometry": {"coordinates":[-0.1971517921984,53.52546689701247],"type":"Point"}
}