{
  "type": "Feature",
  "properties": {
    "iso:country": "GB",
    "wof:name": "TN30 7NY",
    "wof:placetype": "postalcode"
  },
  "geometry": {"coordinates":[0.705131,51.015996],"type":"Point"}
}
