{
  "type": "Feature",
  "properties": {
    "iso:country": "GB",
    "wof:name": "NN5 7AW",
    "wof:placetype": "postalcode"
  },
  "geometry": {"coordinates":[-0.924519,52.242967],"type":"Point"}
}
