{
  "type": "Feature",
  "properties": {
    "date:inception_lower": "2002-06-01",
    "date:inception_upper": "2002-06-01",
    "iso:country": "GB",
    "wof:name": "HP19 7EZ",
    "wof:placetype": "postalcode"
  },
  "geometry": {"coordinates":[-0.838907,51.813686],"type":"Point"}
}
