{
  "type": "Feature",
  "properties": {
    "iso:country":"GB",
    "wof:name":"HP19 7EZ",
    "wof:placetype":"postalcode"
},
  "geometry": {"coordinates":[-0.83890672715471,51.81368578167324],"type":"Point"}
}