{
  "type": "Feature",
  "properties": {
    "date:inception_lower":"1980-01-01",
    "date:inception_upper":"1980-01-31",
    "iso:country":"GB",
    "wof:name":"WN4 0UD",
    "wof:placetype":"postalcode"
},
  "geometry": {"coordinates":[-2.674424,53.488434],"type":"Point"}
}