{
  "type": "Feature",
  "properties": {
    "iso:country":"GB",
    "wof:name":"WN4 0UD",
    "wof:placetype":"postalcode"
},
  "geometry": {"coordinates":[-2.6744240466587,53.4884337558186],"type":"Point"}
}