{
  "type": "Feature",
  "properties": {
    "iso:country": "GB",
    "wof:name": "WN4 0UD",
    "wof:placetype": "postalcode"
  },
  "geometry": {"coordinates":[-2.674424,53.488434],"type":"Point"}
}
