{
  "type": "Feature",
  "properties": {
    "iso:country":"GB",
    "wof:name":"B32 3XD",
    "wof:placetype":"postalcode"
},
  "geometry": {"coordinates":[-1.97603266460045,52.44680481730545],"type":"Point"}
}