{
  "type": "Feature",
  "properties": {
    "iso:country": "GB",
    "wof:name": "HA2 8PL",
    "wof:placetype": "postalcode"
  },
  "geometry": {"coordinates":[-0.367312,51.558789],"type":"Point"}
}
