{
  "type": "Feature",
  "properties": {
    "iso:country":"GB",
    "wof:name":"HA2 8PL",
    "wof:placetype":"postalcode"
},
  "geometry": {"coordinates":[-0.36731195638468,51.5587894273245],"type":"Point"}
}