{
  "type": "Feature",
  "properties": {
    "date:inception_lower": "2000-06-01",
    "date:inception_upper": "2000-06-01",
    "iso:country": "GB",
    "wof:name": "BN23 5PE",
    "wof:placetype": "postalcode"
  },
  "geometry": {"coordinates":[0.330052,50.798523],"type":"Point"}
}
