{
  "type": "Feature",
  "properties": {
    "date:inception_lower": "2021-05-01",
    "date:inception_upper": "2021-05-01",
    "iso:country": "GB",
    "wof:name": "CV35 9AW",
    "wof:placetype": "postalcode"
  },
  "geometry": {"coordinates":[-1.591868,52.198931],"type":"Point"}
}
