{
  "type": "Feature",
  "properties": {
    "iso:country":"GB",
    "wof:name":"KY2 6EZ",
    "wof:placetype":"postalcode"
},
  "geometry": {"coordinates":[-3.18819873095643,56.12534157086815],"type":"Point"}
}