{
  "type": "Feature",
  "properties": {
    "date:inception_lower":"1980-01-01",
    "date:inception_upper":"1980-01-31",
    "iso:country":"GB",
    "wof:name":"DT6 6RW",
    "wof:placetype":"postalcode"
},
  "geometry": {"coordinates":[-2.846259,50.776094],"type":"Point"}
}