{
  "type": "Feature",
  "properties": {
    "iso:country":"GB",
    "wof:name":"DT6 6RW",
    "wof:placetype":"postalcode"
},
  "geometry": {"coordinates":[-2.84625939654863,50.77609374312758],"type":"Point"}
}