{
  "type": "Feature",
  "properties": {
    "iso:country":"GB",
    "wof:name":"BR5 2JY",
    "wof:placetype":"postalcode"
},
  "geometry": {"coordinates":[0.10666174094858,51.39892434560832],"type":"Point"}
}