{
  "type": "Feature",
  "properties": {
    "iso:country":"GB",
    "wof:name":"TS6 0TY",
    "wof:placetype":"postalcode"
},
  "geometry": {"coordinates":[-1.14837617646204,54.55220456012621],"type":"Point"}
}