{
  "type": "Feature",
  "properties": {
    "date:inception_lower": "1981-09-01",
    "date:inception_upper": "1981-09-01",
    "iso:country": "GB",
    "wof:name": "TS6 0TY",
    "wof:placetype": "postalcode"
  },
  "geometry": {"coordinates":[-1.148376,54.552205],"type":"Point"}
}
