{
  "type": "Feature",
  "properties": {
    "iso:country":"GB",
    "wof:name":"DG10 9BJ",
    "wof:placetype":"postalcode"
},
  "geometry": {"coordinates":[-3.43904978679991,55.33346806457788],"type":"Point"}
}