{
  "type": "Feature",
  "properties": {
    "iso:country":"GB",
    "wof:name":"SY5 0AJ",
    "wof:placetype":"postalcode"
},
  "geometry": {"coordinates":[-2.9342730993684,52.64951128755794],"type":"Point"}
}