{
  "type": "Feature",
  "properties": {
    "iso:country": "GB",
    "wof:name": "TA24 7LH",
    "wof:placetype": "postalcode"
  },
  "geometry": {"coordinates":[-3.809427,51.15061],"type":"Point"}
}
