{
  "type": "Feature",
  "properties": {
    "iso:country":"GB",
    "wof:name":"TA24 7LH",
    "wof:placetype":"postalcode"
},
  "geometry": {"coordinates":[-3.80920713595624,51.15084759126906],"type":"Point"}
}