{
  "type": "Feature",
  "properties": {
    "iso:country":"GB",
    "wof:name":"EX38 8AT",
    "wof:placetype":"postalcode"
},
  "geometry": {"coordinates":[-4.15399671327893,50.94728152849667],"type":"Point"}
}