{
  "type": "Feature",
  "properties": {
    "date:inception_lower": "1996-06-01",
    "date:inception_upper": "1996-06-01",
    "iso:country": "GB",
    "wof:name": "AB15 8TA",
    "wof:placetype": "postalcode"
  },
  "geometry": {"coordinates":[-2.215174,57.147626],"type":"Point"}
}
