{
  "type": "Feature",
  "properties": {
    "iso:country":"GB",
    "wof:name":"TR2 4DT",
    "wof:placetype":"postalcode"
},
  "geometry": {"coordinates":[-4.92895014568371,50.31792728114619],"type":"Point"}
}