{
  "type": "Feature",
  "properties": {
    "iso:country":"GB",
    "wof:name":"BH25 5JY",
    "wof:placetype":"postalcode"
},
  "geometry": {"coordinates":[-1.65730042664215,50.75795284532172],"type":"Point"}
}