{
  "type": "Feature",
  "properties": {
    "date:inception_lower": "1980-01-01",
    "date:inception_upper": "1980-01-01",
    "iso:country": "GB",
    "wof:name": "NE65 7JQ",
    "wof:placetype": "postalcode"
  },
  "geometry": {"coordinates":[-1.951063,55.326005],"type":"Point"}
}
