{
  "type": "Feature",
  "properties": {
    "iso:country":"GB",
    "wof:name":"SA31 2HF",
    "wof:placetype":"postalcode"
},
  "geometry": {"coordinates":[-4.28649300932413,51.86548442999351],"type":"Point"}
}