{
  "type": "Feature",
  "properties": {
    "iso:country": "GB",
    "wof:name": "DE12 7QY",
    "wof:placetype": "postalcode"
  },
  "geometry": {"coordinates":[-1.527276,52.71387],"type":"Point"}
}
