{
  "type": "Feature",
  "properties": {
    "iso:country":"GB",
    "wof:name":"DE12 7QY",
    "wof:placetype":"postalcode"
},
  "geometry": {"coordinates":[-1.5272757536196,52.71387001731183],"type":"Point"}
}