{
  "type": "Feature",
  "properties": {
    "iso:country":"GB",
    "wof:name":"NE46 3EY",
    "wof:placetype":"postalcode"
},
  "geometry": {"coordinates":[-2.10629697568441,54.97521827817788],"type":"Point"}
}