{
  "type": "Feature",
  "properties": {
    "iso:country": "GB",
    "wof:name": "PR4 4XE",
    "wof:placetype": "postalcode"
  },
  "geometry": {"coordinates":[-2.740492,53.722183],"type":"Point"}
}
