{
  "type": "Feature",
  "properties": {
    "iso:country":"GB",
    "wof:name":"PR4 4XE",
    "wof:placetype":"postalcode"
},
  "geometry": {"coordinates":[-2.74049156533557,53.72218315687935],"type":"Point"}
}