{
  "type": "Feature",
  "properties": {
    "iso:country": "GB",
    "wof:name": "PO9 4RN",
    "wof:placetype": "postalcode"
  },
  "geometry": {"coordinates":[-0.995124,50.868886],"type":"Point"}
}
