{
  "type": "Feature",
  "properties": {
    "iso:country":"GB",
    "wof:name":"PO9 4RN",
    "wof:placetype":"postalcode"
},
  "geometry": {"coordinates":[-0.99512398512162,50.86888587188902],"type":"Point"}
}