{
  "type": "Feature",
  "properties": {
    "iso:country":"GB",
    "wof:name":"WA9 2HT",
    "wof:placetype":"postalcode"
},
  "geometry": {"coordinates":[-2.6938238063406,53.4535276426618],"type":"Point"}
}