{
  "type": "Feature",
  "properties": {
    "iso:country":"GB",
    "wof:name":"CT19 5AE",
    "wof:placetype":"postalcode"
},
  "geometry": {"coordinates":[1.17734719802791,51.08491190590198],"type":"Point"}
}