{
  "type": "Feature",
  "properties": {
    "iso:country":"GB",
    "wof:name":"PL9 8UA",
    "wof:placetype":"postalcode"
},
  "geometry": {"coordinates":[-4.08431992264108,50.36282552218248],"type":"Point"}
}