{
  "type": "Feature",
  "properties": {
    "iso:country":"GB",
    "wof:name":"DE5 3TF",
    "wof:placetype":"postalcode"
},
  "geometry": {"coordinates":[-1.4035118951224,53.0419138508985],"type":"Point"}
}