{
  "type": "Feature",
  "properties": {
    "iso:country": "GB",
    "wof:name": "IP28 8TW",
    "wof:placetype": "postalcode"
  },
  "geometry": {"coordinates":[0.49147,52.301458],"type":"Point"}
}
