{
  "type": "Feature",
  "properties": {
    "iso:country":"GB",
    "wof:name":"IP28 8TW",
    "wof:placetype":"postalcode"
},
  "geometry": {"coordinates":[0.4914692316944,52.30143986590659],"type":"Point"}
}