{
  "type": "Feature",
  "properties": {
    "date:inception_lower": "1980-01-01",
    "date:inception_upper": "1980-01-01",
    "iso:country": "GB",
    "wof:name": "IP28 8TW",
    "wof:placetype": "postalcode"
  },
  "geometry": {"coordinates":[0.49147,52.301458],"type":"Point"}
}
