{
  "type": "Feature",
  "properties": {
    "iso:country":"GB",
    "wof:name":"PR3 0ZL",
    "wof:placetype":"postalcode"
},
  "geometry": {"coordinates":[-2.87474144335288,53.85457430295711],"type":"Point"}
}