{
  "type": "Feature",
  "properties": {
    "iso:country":"GB",
    "wof:name":"EX21 5UH",
    "wof:placetype":"postalcode"
},
  "geometry": {"coordinates":[-4.23132529771176,50.77338109129365],"type":"Point"}
}