{
  "type": "Feature",
  "properties": {
    "iso:country": "GB",
    "wof:name": "SY5 0PP",
    "wof:placetype": "postalcode"
  },
  "geometry": {"coordinates":[-2.88953,52.648909],"type":"Point"}
}
