{
  "type": "Feature",
  "properties": {
    "iso:country":"GB",
    "wof:name":"RH11 8GH",
    "wof:placetype":"postalcode"
},
  "geometry": {"coordinates":[-0.22985472080814,51.09968113679157],"type":"Point"}
}