{
  "type": "Feature",
  "properties": {
    "iso:country": "GB",
    "wof:name": "PO20 3AN",
    "wof:placetype": "postalcode"
  },
  "geometry": {"coordinates":[-0.672207,50.834346],"type":"Point"}
}
