{
  "type": "Feature",
  "properties": {
    "iso:country":"GB",
    "wof:name":"PO16 9NY",
    "wof:placetype":"postalcode"
},
  "geometry": {"coordinates":[-1.12592461968064,50.84296939564673],"type":"Point"}
}