{
  "type": "Feature",
  "properties": {
    "iso:country": "GB",
    "wof:name": "PO16 9NY",
    "wof:placetype": "postalcode"
  },
  "geometry": {"coordinates":[-1.125925,50.842969],"type":"Point"}
}
