{
  "type": "Feature",
  "properties": {
    "iso:country":"GB",
    "wof:name":"NP22 5QA",
    "wof:placetype":"postalcode"
},
  "geometry": {"coordinates":[-3.27762043107133,51.75525873152623],"type":"Point"}
}