{
  "type": "Feature",
  "properties": {
    "iso:country":"GB",
    "wof:name":"GU35 9PH",
    "wof:placetype":"postalcode"
},
  "geometry": {"coordinates":[-0.87045480440838,51.13981708177645],"type":"Point"}
}