{
  "type": "Feature",
  "properties": {
    "date:inception_lower": "1980-01-01",
    "date:inception_upper": "1980-01-01",
    "iso:country": "GB",
    "wof:name": "GL14 2EH",
    "wof:placetype": "postalcode"
  },
  "geometry": {"coordinates":[-2.500897,51.815665],"type":"Point"}
}
