{
  "type": "Feature",
  "properties": {
    "iso:country":"GB",
    "wof:name":"DL9 4QP",
    "wof:placetype":"postalcode"
},
  "geometry": {"coordinates":[-1.71278699840741,54.373681839109],"type":"Point"}
}