{
  "type": "Feature",
  "properties": {
    "iso:country": "GB",
    "wof:name": "DL9 4QP",
    "wof:placetype": "postalcode"
  },
  "geometry": {"coordinates":[-1.712787,54.373682],"type":"Point"}
}
