{
  "type": "Feature",
  "properties": {
    "date:inception_lower":"1998-06-01",
    "date:inception_upper":"1998-06-30",
    "iso:country":"GB",
    "wof:name":"CM8 2TH",
    "wof:placetype":"postalcode"
},
  "geometry": {"coordinates":[0.64029,51.800995],"type":"Point"}
}