{
  "type": "Feature",
  "properties": {
    "iso:country": "GB",
    "wof:name": "NR12 0TD",
    "wof:placetype": "postalcode"
  },
  "geometry": {"coordinates":[1.547102,52.791571],"type":"Point"}
}
