{
  "type": "Feature",
  "properties": {
    "iso:country": "GB",
    "wof:name": "M11 1PA",
    "wof:placetype": "postalcode"
  },
  "geometry": {"coordinates":[-2.167454,53.471693],"type":"Point"}
}
