{
  "type": "Feature",
  "properties": {
    "iso:country": "GB",
    "wof:name": "WV10 0NX",
    "wof:placetype": "postalcode"
  },
  "geometry": {"coordinates":[-2.107173,52.599191],"type":"Point"}
}
