{
  "type": "Feature",
  "properties": {
    "iso:country": "GB",
    "wof:name": "TQ2 6LZ",
    "wof:placetype": "postalcode"
  },
  "geometry": {"coordinates":[-3.553998,50.466736],"type":"Point"}
}
