{
  "type": "Feature",
  "properties": {
    "iso:country":"GB",
    "wof:name":"TQ2 6LZ",
    "wof:placetype":"postalcode"
},
  "geometry": {"coordinates":[-3.55399763900369,50.46673647944951],"type":"Point"}
}