{
  "type": "Feature",
  "properties": {
    "iso:country": "GB",
    "wof:name": "PH26 3QB",
    "wof:placetype": "postalcode"
  },
  "geometry": {"coordinates":[-3.609234,57.331584],"type":"Point"}
}
