{
  "type": "Feature",
  "properties": {
    "iso:country":"GB",
    "wof:name":"PH26 3QB",
    "wof:placetype":"postalcode"
},
  "geometry": {"coordinates":[-3.60923422156243,57.33158419867149],"type":"Point"}
}