{
  "type": "Feature",
  "properties": {
    "date:inception_lower": "2024-09-01",
    "date:inception_upper": "2024-09-01",
    "iso:country": "GB",
    "wof:name": "KT13 3JZ",
    "wof:placetype": "postalcode"
  },
  "geometry": {"coordinates":[-0.457529,51.373411],"type":"Point"}
}
