{
  "type": "Feature",
  "properties": {
    "iso:country": "GB",
    "wof:name": "B42 2TN",
    "wof:placetype": "postalcode"
  },
  "geometry": {"coordinates":[-1.898308,52.515294],"type":"Point"}
}
