{
  "type": "Feature",
  "properties": {
    "iso:country":"GB",
    "wof:name":"B42 2TN",
    "wof:placetype":"postalcode"
},
  "geometry": {"coordinates":[-1.89830818593034,52.51529416806836],"type":"Point"}
}