{
  "type": "Feature",
  "properties": {
    "date:inception_lower":"1980-01-01",
    "date:inception_upper":"1980-01-31",
    "iso:country":"GB",
    "wof:name":"WA6 6JL",
    "wof:placetype":"postalcode"
},
  "geometry": {"coordinates":[-2.695673,53.256047],"type":"Point"}
}