{
  "type": "Feature",
  "properties": {
    "iso:country":"GB",
    "wof:name":"GU12 6ST",
    "wof:placetype":"postalcode"
},
  "geometry": {"coordinates":[-0.71923820849384,51.25220200413435],"type":"Point"}
}