{
  "type": "Feature",
  "properties": {
    "iso:country": "GB",
    "wof:name": "SP7 8EN",
    "wof:placetype": "postalcode"
  },
  "geometry": {"coordinates":[-2.185612,51.008135],"type":"Point"}
}
