{
  "type": "Feature",
  "properties": {
    "iso:country":"GB",
    "wof:name":"SP7 8EN",
    "wof:placetype":"postalcode"
},
  "geometry": {"coordinates":[-2.18561219566316,51.00813504811385],"type":"Point"}
}