{
  "type": "Feature",
  "properties": {
    "date:inception_lower":"2003-05-01",
    "date:inception_upper":"2003-05-31",
    "iso:country":"GB",
    "wof:name":"SP7 8EN",
    "wof:placetype":"postalcode"
},
  "geometry": {"coordinates":[-2.185612,51.008135],"type":"Point"}
}