{
  "type": "Feature",
  "properties": {
    "date:inception_lower": "1980-01-01",
    "date:inception_upper": "1980-01-01",
    "iso:country": "GB",
    "wof:name": "DY14 0RX",
    "wof:placetype": "postalcode"
  },
  "geometry": {"coordinates":[-2.5453,52.428009],"type":"Point"}
}
