{
  "type": "Feature",
  "properties": {
    "date:inception_lower": "2002-06-01",
    "date:inception_upper": "2002-06-01",
    "iso:country": "GB",
    "wof:name": "RH13 9DD",
    "wof:placetype": "postalcode"
  },
  "geometry": {"coordinates":[-0.356384,51.021941],"type":"Point"}
}
