{
  "type": "Feature",
  "properties": {
    "date:inception_lower": "1980-01-01",
    "date:inception_upper": "1980-01-01",
    "iso:country": "GB",
    "wof:name": "LE5 6AE",
    "wof:placetype": "postalcode"
  },
  "geometry": {"coordinates":[-1.08305,52.623841],"type":"Point"}
}
