{
  "type": "Feature",
  "properties": {
    "iso:country":"GB",
    "wof:name":"CA3 9TB",
    "wof:placetype":"postalcode"
},
  "geometry": {"coordinates":[-2.94425564213786,54.91241150132894],"type":"Point"}
}