{
  "type": "Feature",
  "properties": {
    "iso:country": "GB",
    "wof:name": "CA3 9TB",
    "wof:placetype": "postalcode"
  },
  "geometry": {"coordinates":[-2.944274,54.9124],"type":"Point"}
}
