{
  "type": "Feature",
  "properties": {
    "iso:country": "GB",
    "wof:name": "CF47 9DX",
    "wof:placetype": "postalcode"
  },
  "geometry": {"coordinates":[-3.36571,51.75915],"type":"Point"}
}
