{
  "type": "Feature",
  "properties": {
    "date:inception_lower": "1980-01-01",
    "date:inception_upper": "1980-01-01",
    "iso:country": "GB",
    "wof:name": "CF47 9DX",
    "wof:placetype": "postalcode"
  },
  "geometry": {"coordinates":[-3.36571,51.75915],"type":"Point"}
}
