{
  "type": "Feature",
  "properties": {
    "iso:country":"GB",
    "wof:name":"SR3 1QT",
    "wof:placetype":"postalcode"
},
  "geometry": {"coordinates":[-1.41760149769722,54.88452895722105],"type":"Point"}
}