{
  "type": "Feature",
  "properties": {
    "iso:country":"GB",
    "wof:name":"PL25 3ER",
    "wof:placetype":"postalcode"
},
  "geometry": {"coordinates":[-4.76723390331061,50.34987607136974],"type":"Point"}
}