{
  "type": "Feature",
  "properties": {
    "iso:country": "GB",
    "wof:name": "OX25 2AZ",
    "wof:placetype": "postalcode"
  },
  "geometry": {"coordinates":[-1.144202,51.882755],"type":"Point"}
}
