{
  "type": "Feature",
  "properties": {
    "iso:country": "GB",
    "wof:name": "NR6 6AU",
    "wof:placetype": "postalcode"
  },
  "geometry": {"coordinates":[1.284914,52.662125],"type":"Point"}
}
