{
  "type": "Feature",
  "properties": {
    "date:inception_lower": "1987-04-01",
    "date:inception_upper": "1987-04-01",
    "iso:country": "GB",
    "wof:name": "NR6 6AU",
    "wof:placetype": "postalcode"
  },
  "geometry": {"coordinates":[1.28605,52.662876],"type":"Point"}
}
