{
  "type": "Feature",
  "properties": {
    "iso:country":"GB",
    "wof:name":"CB4 1DU",
    "wof:placetype":"postalcode"
},
  "geometry": {"coordinates":[0.12720330934439,52.21314295789001],"type":"Point"}
}