{
  "type": "Feature",
  "properties": {
    "iso:country": "GB",
    "wof:name": "B70 0JQ",
    "wof:placetype": "postalcode"
  },
  "geometry": {"coordinates":[-2.015435,52.533406],"type":"Point"}
}
