{
  "type": "Feature",
  "properties": {
    "date:inception_lower":"1980-01-01",
    "date:inception_upper":"1980-01-31",
    "iso:country":"GB",
    "wof:name":"B70 0JQ",
    "wof:placetype":"postalcode"
},
  "geometry": {"coordinates":[-2.015435,52.533406],"type":"Point"}
}