{
  "type": "Feature",
  "properties": {
    "iso:country":"GB",
    "wof:name":"B70 0JQ",
    "wof:placetype":"postalcode"
},
  "geometry": {"coordinates":[-2.01543553406328,52.53340626611092],"type":"Point"}
}