{
  "type": "Feature",
  "properties": {
    "iso:country":"GB",
    "wof:name":"GL8 8GW",
    "wof:placetype":"postalcode"
},
  "geometry": {"coordinates":[-2.15275186592135,51.64442018516981],"type":"Point"}
}