{
  "type": "Feature",
  "properties": {
    "date:inception_lower": "2015-08-01",
    "date:inception_upper": "2015-08-01",
    "iso:country": "GB",
    "wof:name": "GL8 8GW",
    "wof:placetype": "postalcode"
  },
  "geometry": {"coordinates":[-2.152675,51.644378],"type":"Point"}
}
