{
  "type": "Feature",
  "properties": {
    "date:inception_lower": "2002-09-01",
    "date:inception_upper": "2002-09-01",
    "iso:country": "GB",
    "wof:name": "NG19 9DZ",
    "wof:placetype": "postalcode"
  },
  "geometry": {"coordinates":[-1.174809,53.176618],"type":"Point"}
}
