{
  "type": "Feature",
  "properties": {
    "date:inception_lower": "1980-01-01",
    "date:inception_upper": "1980-01-01",
    "iso:country": "GB",
    "wof:name": "LL11 3UE",
    "wof:placetype": "postalcode"
  },
  "geometry": {"coordinates":[-3.072346,53.054241],"type":"Point"}
}
