{
  "type": "Feature",
  "properties": {
    "iso:country":"GB",
    "wof:name":"LL11 3UE",
    "wof:placetype":"postalcode"
},
  "geometry": {"coordinates":[-3.07234571342012,53.05424109310041],"type":"Point"}
}