{
  "type": "Feature",
  "properties": {
    "iso:country":"GB",
    "wof:name":"YO7 1NP",
    "wof:placetype":"postalcode"
},
  "geometry": {"coordinates":[-1.34242794967374,54.22354612738518],"type":"Point"}
}