{
  "type": "Feature",
  "properties": {
    "iso:country": "GB",
    "wof:name": "B32 4LF",
    "wof:placetype": "postalcode"
  },
  "geometry": {"coordinates":[-2.011121,52.439588],"type":"Point"}
}
