{
  "type": "Feature",
  "properties": {
    "iso:country":"GB",
    "wof:name":"B32 4LF",
    "wof:placetype":"postalcode"
},
  "geometry": {"coordinates":[-2.01112137566572,52.43958766299141],"type":"Point"}
}