{
  "type": "Feature",
  "properties": {
    "date:inception_lower": "1980-01-01",
    "date:inception_upper": "1980-01-01",
    "iso:country": "GB",
    "wof:name": "B32 4LF",
    "wof:placetype": "postalcode"
  },
  "geometry": {"coordinates":[-2.011121,52.439588],"type":"Point"}
}
