{
  "type": "Feature",
  "properties": {
    "date:inception_lower": "1980-01-01",
    "date:inception_upper": "1980-01-01",
    "iso:country": "GB",
    "wof:name": "N15 5EY",
    "wof:placetype": "postalcode"
  },
  "geometry": {"coordinates":[-0.078414,51.584469],"type":"Point"}
}
