{
  "type": "Feature",
  "properties": {
    "iso:country": "GB",
    "wof:name": "N15 5EY",
    "wof:placetype": "postalcode"
  },
  "geometry": {"coordinates":[-0.078414,51.584469],"type":"Point"}
}
