{
  "type": "Feature",
  "properties": {
    "iso:country":"GB",
    "wof:name":"N15 5EY",
    "wof:placetype":"postalcode"
},
  "geometry": {"coordinates":[-0.07837896885264,51.58452911642194],"type":"Point"}
}