{
  "type": "Feature",
  "properties": {
    "iso:country":"GB",
    "wof:name":"WR7 4BY",
    "wof:placetype":"postalcode"
},
  "geometry": {"coordinates":[-2.0246698683755,52.17853657058939],"type":"Point"}
}