{
  "type": "Feature",
  "properties": {
    "iso:country": "GB",
    "wof:name": "WR7 4BY",
    "wof:placetype": "postalcode"
  },
  "geometry": {"coordinates":[-2.02459,52.17774],"type":"Point"}
}
