{
  "type": "Feature",
  "properties": {
    "date:inception_lower": "1999-12-01",
    "date:inception_upper": "1999-12-01",
    "iso:country": "GB",
    "wof:name": "RG7 1BF",
    "wof:placetype": "postalcode"
  },
  "geometry": {"coordinates":[-0.972657,51.395183],"type":"Point"}
}
