{
  "type": "Feature",
  "properties": {
    "iso:country": "GB",
    "wof:name": "NP4 8RE",
    "wof:placetype": "postalcode"
  },
  "geometry": {"coordinates":[-2.997044,51.731777],"type":"Point"}
}
