{
  "type": "Feature",
  "properties": {
    "iso:country":"GB",
    "wof:name":"NP4 8RE",
    "wof:placetype":"postalcode"
},
  "geometry": {"coordinates":[-2.99708265332657,51.7318450103182],"type":"Point"}
}