{
  "type": "Feature",
  "properties": {
    "date:inception_lower": "1980-01-01",
    "date:inception_upper": "1980-01-01",
    "iso:country": "GB",
    "wof:name": "NP4 8RE",
    "wof:placetype": "postalcode"
  },
  "geometry": {"coordinates":[-2.997044,51.731777],"type":"Point"}
}
