{
  "type": "Feature",
  "properties": {
    "iso:country":"GB",
    "wof:name":"TW20 8QL",
    "wof:placetype":"postalcode"
},
  "geometry": {"coordinates":[-0.54965233304979,51.40406510993301],"type":"Point"}
}