{
  "type": "Feature",
  "properties": {
    "iso:country": "GB",
    "wof:name": "M3 2PB",
    "wof:placetype": "postalcode"
  },
  "geometry": {"coordinates":[-2.249677,53.481304],"type":"Point"}
}
