{
  "type": "Feature",
  "properties": {
    "iso:country": "GB",
    "wof:name": "OX15 6EP",
    "wof:placetype": "postalcode"
  },
  "geometry": {"coordinates":[-1.447932,52.094185],"type":"Point"}
}
