{
  "type": "Feature",
  "properties": {
    "iso:country":"GB",
    "wof:name":"OX15 6EP",
    "wof:placetype":"postalcode"
},
  "geometry": {"coordinates":[-1.44793228464372,52.09418480259571],"type":"Point"}
}