{
  "type": "Feature",
  "properties": {
    "date:inception_lower": "2010-02-01",
    "date:inception_upper": "2010-02-01",
    "iso:country": "GB",
    "wof:name": "OX15 6EP",
    "wof:placetype": "postalcode"
  },
  "geometry": {"coordinates":[-1.447932,52.094185],"type":"Point"}
}
