{
  "type": "Feature",
  "properties": {
    "iso:country":"GB",
    "wof:name":"ML6 0LP",
    "wof:placetype":"postalcode"
},
  "geometry": {"coordinates":[-3.9927028510536,55.87572674792326],"type":"Point"}
}