{
  "type": "Feature",
  "properties": {
    "date:inception_lower":"1980-01-01",
    "date:inception_upper":"1980-01-31",
    "iso:country":"GB",
    "wof:name":"OL16 4ES",
    "wof:placetype":"postalcode"
},
  "geometry": {"coordinates":[-2.115523,53.603553],"type":"Point"}
}