{
  "type": "Feature",
  "properties": {
    "iso:country":"GB",
    "wof:name":"OL16 4ES",
    "wof:placetype":"postalcode"
},
  "geometry": {"coordinates":[-2.11552322229888,53.60355292607242],"type":"Point"}
}