{
  "type": "Feature",
  "properties": {
    "iso:country": "GB",
    "wof:name": "BD19 4QZ",
    "wof:placetype": "postalcode"
  },
  "geometry": {"coordinates":[-1.680956,53.728875],"type":"Point"}
}
