{
  "type": "Feature",
  "properties": {
    "iso:country":"GB",
    "wof:name":"BD19 4QZ",
    "wof:placetype":"postalcode"
},
  "geometry": {"coordinates":[-1.68095557995059,53.72887529563382],"type":"Point"}
}