{
  "type": "Feature",
  "properties": {
    "iso:country":"GB",
    "wof:name":"BA1 7EJ",
    "wof:placetype":"postalcode"
},
  "geometry": {"coordinates":[-2.31838967075336,51.41378953998763],"type":"Point"}
}