{
  "type": "Feature",
  "properties": {
    "iso:country":"GB",
    "wof:name":"UB2 5RS",
    "wof:placetype":"postalcode"
},
  "geometry": {"coordinates":[-0.37638255329257,51.49282234931456],"type":"Point"}
}