{
  "type": "Feature",
  "properties": {
    "iso:country":"GB",
    "wof:name":"GL8 8JJ",
    "wof:placetype":"postalcode"
},
  "geometry": {"coordinates":[-2.16092972451722,51.63980572381377],"type":"Point"}
}