{
  "type": "Feature",
  "properties": {
    "iso:country": "GB",
    "wof:name": "SO18 2GJ",
    "wof:placetype": "postalcode"
  },
  "geometry": {"coordinates":[-1.358081,50.928422],"type":"Point"}
}
