{
  "type": "Feature",
  "properties": {
    "iso:country":"GB",
    "wof:name":"SO18 2GJ",
    "wof:placetype":"postalcode"
},
  "geometry": {"coordinates":[-1.35808091576276,50.9284220501429],"type":"Point"}
}