{
  "type": "Feature",
  "properties": {
    "iso:country": "GB",
    "wof:name": "LL57 4HY",
    "wof:placetype": "postalcode"
  },
  "geometry": {"coordinates":[-4.097193,53.216494],"type":"Point"}
}
