{
  "type": "Feature",
  "properties": {
    "date:inception_lower":"1993-08-01",
    "date:inception_upper":"1993-08-31",
    "iso:country":"GB",
    "wof:name":"LL57 4HY",
    "wof:placetype":"postalcode"
},
  "geometry": {"coordinates":[-4.097117,53.21646],"type":"Point"}
}