{
  "type": "Feature",
  "properties": {
    "iso:country":"GB",
    "wof:name":"LL57 4HY",
    "wof:placetype":"postalcode"
},
  "geometry": {"coordinates":[-4.09718668987738,53.21647727619833],"type":"Point"}
}