{
  "type": "Feature",
  "properties": {
    "iso:country":"GB",
    "wof:name":"RH10 3ZJ",
    "wof:placetype":"postalcode"
},
  "geometry": {"coordinates":[-0.15037428563174,51.13965678204147],"type":"Point"}
}