{
  "type": "Feature",
  "properties": {
    "iso:country":"GB",
    "wof:name":"EH3 6SD",
    "wof:placetype":"postalcode"
},
  "geometry": {"coordinates":[-3.19985222555009,55.9590447600108],"type":"Point"}
}