{
  "type": "Feature",
  "properties": {
    "iso:country": "GB",
    "wof:name": "S42 7AA",
    "wof:placetype": "postalcode"
  },
  "geometry": {"coordinates":[-1.475723,53.221918],"type":"Point"}
}
