{
  "type": "Feature",
  "properties": {
    "iso:country": "GB",
    "wof:name": "LL68 9EE",
    "wof:placetype": "postalcode"
  },
  "geometry": {"coordinates":[-4.357315,53.411363],"type":"Point"}
}
