{
  "type": "Feature",
  "properties": {
    "iso:country":"GB",
    "wof:name":"LL68 9EE",
    "wof:placetype":"postalcode"
},
  "geometry": {"coordinates":[-4.35731464228401,53.411363036422],"type":"Point"}
}