{
  "type": "Feature",
  "properties": {
    "iso:country":"GB",
    "wof:name":"ME1 3PW",
    "wof:placetype":"postalcode"
},
  "geometry": {"coordinates":[0.49947880662039,51.36482387480565],"type":"Point"}
}