{
  "type": "Feature",
  "properties": {
    "iso:country":"GB",
    "wof:name":"PO21 4EP",
    "wof:placetype":"postalcode"
},
  "geometry": {"coordinates":[-0.72083273165265,50.77424944813059],"type":"Point"}
}