{
  "type": "Feature",
  "properties": {
    "iso:country":"GB",
    "wof:name":"UB8 3SQ",
    "wof:placetype":"postalcode"
},
  "geometry": {"coordinates":[-0.47640464012835,51.52197711238755],"type":"Point"}
}