{
  "type": "Feature",
  "properties": {
    "date:inception_lower":"1980-01-01",
    "date:inception_upper":"1980-01-31",
    "iso:country":"GB",
    "wof:name":"BB9 0RZ",
    "wof:placetype":"postalcode"
},
  "geometry": {"coordinates":[-2.210379,53.827533],"type":"Point"}
}