{
  "type": "Feature",
  "properties": {
    "iso:country":"GB",
    "wof:name":"BB9 0RZ",
    "wof:placetype":"postalcode"
},
  "geometry": {"coordinates":[-2.21037886558393,53.82753279278587],"type":"Point"}
}