{
  "type": "Feature",
  "properties": {
    "iso:country":"GB",
    "wof:name":"HP22 5QP",
    "wof:placetype":"postalcode"
},
  "geometry": {"coordinates":[-0.71869433022908,51.8022592246904],"type":"Point"}
}