{
  "type": "Feature",
  "properties": {
    "iso:country":"GB",
    "wof:name":"NN2 7JG",
    "wof:placetype":"postalcode"
},
  "geometry": {"coordinates":[-0.88049036990029,52.25294244882512],"type":"Point"}
}