{
  "type": "Feature",
  "properties": {
    "iso:country": "GB",
    "wof:name": "NN2 7JG",
    "wof:placetype": "postalcode"
  },
  "geometry": {"coordinates":[-0.88049,52.252942],"type":"Point"}
}
