{
  "type": "Feature",
  "properties": {
    "iso:country": "GB",
    "wof:name": "MK8 0NE",
    "wof:placetype": "postalcode"
  },
  "geometry": {"coordinates":[-0.807768,52.024768],"type":"Point"}
}
