{
  "type": "Feature",
  "properties": {
    "date:inception_lower": "2006-01-01",
    "date:inception_upper": "2006-01-01",
    "iso:country": "GB",
    "wof:name": "MK8 0NE",
    "wof:placetype": "postalcode"
  },
  "geometry": {"coordinates":[-0.807768,52.024768],"type":"Point"}
}
