{
  "type": "Feature",
  "properties": {
    "iso:country":"GB",
    "wof:name":"MK8 0NE",
    "wof:placetype":"postalcode"
},
  "geometry": {"coordinates":[-0.80776830167543,52.02476829490227],"type":"Point"}
}