{
  "type": "Feature",
  "properties": {
    "iso:country":"GB",
    "wof:name":"WF10 4BZ",
    "wof:placetype":"postalcode"
},
  "geometry": {"coordinates":[-1.33907525682927,53.72005390271747],"type":"Point"}
}