{
  "type": "Feature",
  "properties": {
    "iso:country":"GB",
    "wof:name":"UB1 3HR",
    "wof:placetype":"postalcode"
},
  "geometry": {"coordinates":[-0.36439493866681,51.51140468894972],"type":"Point"}
}