{
  "type": "Feature",
  "properties": {
    "iso:country":"GB",
    "wof:name":"BD8 9QT",
    "wof:placetype":"postalcode"
},
  "geometry": {"coordinates":[-1.78938996221752,53.8013604029335],"type":"Point"}
}