{
  "type": "Feature",
  "properties": {
    "iso:country": "GB",
    "wof:name": "CV5 8AE",
    "wof:placetype": "postalcode"
  },
  "geometry": {"coordinates":[-1.554612,52.409721],"type":"Point"}
}
