{
  "type": "Feature",
  "properties": {
    "date:inception_lower":"1996-06-01",
    "date:inception_upper":"1996-06-30",
    "iso:country":"GB",
    "wof:name":"CV5 8AE",
    "wof:placetype":"postalcode"
},
  "geometry": {"coordinates":[-1.554612,52.409721],"type":"Point"}
}