{
  "type": "Feature",
  "properties": {
    "date:inception_lower": "2012-08-01",
    "date:inception_upper": "2012-08-01",
    "iso:country": "GB",
    "wof:name": "MK10 7EG",
    "wof:placetype": "postalcode"
  },
  "geometry": {"coordinates":[-0.690563,52.051487],"type":"Point"}
}
