{
  "type": "Feature",
  "properties": {
    "iso:country":"GB",
    "wof:name":"MK10 7EG",
    "wof:placetype":"postalcode"
},
  "geometry": {"coordinates":[-0.69056295741908,52.05148674626278],"type":"Point"}
}