{
  "type": "Feature",
  "properties": {
    "date:inception_lower": "2023-08-01",
    "date:inception_upper": "2023-08-01",
    "iso:country": "GB",
    "wof:name": "IV30 4FT",
    "wof:placetype": "postalcode"
  },
  "geometry": {"coordinates":[-3.31302,57.667542],"type":"Point"}
}
