{
  "type": "Feature",
  "properties": {
    "iso:country":"GB",
    "wof:name":"YO24 4QZ",
    "wof:placetype":"postalcode"
},
  "geometry": {"coordinates":[-1.12109723798539,53.94806913858692],"type":"Point"}
}