{
  "type": "Feature",
  "properties": {
    "iso:country": "GB",
    "wof:name": "YO24 4QZ",
    "wof:placetype": "postalcode"
  },
  "geometry": {"coordinates":[-1.121097,53.948069],"type":"Point"}
}
