{
  "type": "Feature",
  "properties": {
    "iso:country": "GB",
    "wof:name": "SO50 6PQ",
    "wof:placetype": "postalcode"
  },
  "geometry": {"coordinates":[-1.343433,50.968303],"type":"Point"}
}
