{
  "type": "Feature",
  "properties": {
    "iso:country":"GB",
    "wof:name":"SO50 6PQ",
    "wof:placetype":"postalcode"
},
  "geometry": {"coordinates":[-1.34343276603438,50.96830303604093],"type":"Point"}
}