{
  "type": "Feature",
  "properties": {
    "iso:country":"GB",
    "wof:name":"KT15 3AH",
    "wof:placetype":"postalcode"
},
  "geometry": {"coordinates":[-0.49385237380076,51.34941629398823],"type":"Point"}
}