{
  "type": "Feature",
  "properties": {
    "iso:country": "GB",
    "wof:name": "KT15 3AH",
    "wof:placetype": "postalcode"
  },
  "geometry": {"coordinates":[-0.493852,51.349416],"type":"Point"}
}
