{
  "type": "Feature",
  "properties": {
    "date:inception_lower": "1980-01-01",
    "date:inception_upper": "1980-01-01",
    "iso:country": "GB",
    "wof:name": "NN10 0AX",
    "wof:placetype": "postalcode"
  },
  "geometry": {"coordinates":[-0.596159,52.29271],"type":"Point"}
}
