{
  "type": "Feature",
  "properties": {
    "iso:country":"GB",
    "wof:name":"NN10 0AX",
    "wof:placetype":"postalcode"
},
  "geometry": {"coordinates":[-0.59615862193142,52.29271008117126],"type":"Point"}
}