{
  "type": "Feature",
  "properties": {
    "iso:country": "GB",
    "wof:name": "HX7 7PE",
    "wof:placetype": "postalcode"
  },
  "geometry": {"coordinates":[-2.060114,53.756194],"type":"Point"}
}
