{
  "type": "Feature",
  "properties": {
    "iso:country":"GB",
    "wof:name":"HX7 7PE",
    "wof:placetype":"postalcode"
},
  "geometry": {"coordinates":[-2.06011395655722,53.75619426003588],"type":"Point"}
}