{
  "type": "Feature",
  "properties": {
    "iso:country":"GB",
    "wof:name":"CR9 3NG",
    "wof:placetype":"postalcode"
},
  "geometry": {"coordinates":[-0.09398428471599,51.37239618834514],"type":"Point"}
}