{
  "type": "Feature",
  "properties": {
    "iso:country": "GB",
    "wof:name": "CR9 3NG",
    "wof:placetype": "postalcode"
  },
  "geometry": {"coordinates":[-0.093984,51.372396],"type":"Point"}
}
