{
  "type": "Feature",
  "properties": {
    "iso:country":"GB",
    "wof:name":"M5 4BJ",
    "wof:placetype":"postalcode"
},
  "geometry": {"coordinates":[-2.28831416656346,53.48379654816527],"type":"Point"}
}