{
  "type": "Feature",
  "properties": {
    "iso:country": "GB",
    "wof:name": "OX28 6NF",
    "wof:placetype": "postalcode"
  },
  "geometry": {"coordinates":[-1.489434,51.784969],"type":"Point"}
}
