{
  "type": "Feature",
  "properties": {
    "date:inception_lower":"2015-09-01",
    "date:inception_upper":"2015-09-30",
    "iso:country":"GB",
    "wof:name":"EH16 4WF",
    "wof:placetype":"postalcode"
},
  "geometry": {"coordinates":[-3.119711,55.924486],"type":"Point"}
}