{
  "type": "Feature",
  "properties": {
    "date:inception_lower": "2015-09-01",
    "date:inception_upper": "2015-09-01",
    "iso:country": "GB",
    "wof:name": "EH16 4WF",
    "wof:placetype": "postalcode"
  },
  "geometry": {"coordinates":[-3.119682,55.924509],"type":"Point"}
}
