{
  "type": "Feature",
  "properties": {
    "iso:country":"GB",
    "wof:name":"SE3 8QH",
    "wof:placetype":"postalcode"
},
  "geometry": {"coordinates":[0.02911990857651,51.46915985051197],"type":"Point"}
}