{
  "type": "Feature",
  "properties": {
    "iso:country": "GB",
    "wof:name": "SW16 5PH",
    "wof:placetype": "postalcode"
  },
  "geometry": {"coordinates":[-0.13656,51.419699],"type":"Point"}
}
