{
  "type": "Feature",
  "properties": {
    "iso:country":"GB",
    "wof:name":"SW16 5PH",
    "wof:placetype":"postalcode"
},
  "geometry": {"coordinates":[-0.13656003829168,51.41969914662226],"type":"Point"}
}