{
  "type": "Feature",
  "properties": {
    "iso:country":"GB",
    "wof:name":"EH41 4EJ",
    "wof:placetype":"postalcode"
},
  "geometry": {"coordinates":[-2.79670052289711,55.95313725007571],"type":"Point"}
}