{
  "type": "Feature",
  "properties": {
    "iso:country": "GB",
    "wof:name": "S40 1XR",
    "wof:placetype": "postalcode"
  },
  "geometry": {"coordinates":[-1.424647,53.236667],"type":"Point"}
}
