{
  "type": "Feature",
  "properties": {
    "iso:country":"GB",
    "wof:name":"DH5 8HH",
    "wof:placetype":"postalcode"
},
  "geometry": {"coordinates":[-1.46145375755853,54.83627597830412],"type":"Point"}
}