{
  "type": "Feature",
  "properties": {
    "iso:country":"GB",
    "wof:name":"ST4 7PH",
    "wof:placetype":"postalcode"
},
  "geometry": {"coordinates":[-2.20636424290106,53.01043605224761],"type":"Point"}
}