{
  "type": "Feature",
  "properties": {
    "iso:country": "GB",
    "wof:name": "TA18 7JQ",
    "wof:placetype": "postalcode"
  },
  "geometry": {"coordinates":[-2.793763,50.882821],"type":"Point"}
}
