{
  "type": "Feature",
  "properties": {
    "date:inception_lower": "2021-08-01",
    "date:inception_upper": "2021-08-01",
    "iso:country": "GB",
    "wof:name": "MK17 8YB",
    "wof:placetype": "postalcode"
  },
  "geometry": {"coordinates":[-0.671048,52.030186],"type":"Point"}
}
