{
  "type": "Feature",
  "properties": {
    "iso:country":"GB",
    "wof:name":"PE30 4BB",
    "wof:placetype":"postalcode"
},
  "geometry": {"coordinates":[0.42554929521036,52.76017108040651],"type":"Point"}
}