{
  "type": "Feature",
  "properties": {
    "iso:country": "GB",
    "wof:name": "PE30 4BB",
    "wof:placetype": "postalcode"
  },
  "geometry": {"coordinates":[0.425549,52.760171],"type":"Point"}
}
