{
  "type": "Feature",
  "properties": {
    "iso:country":"GB",
    "wof:name":"HU4 6TX",
    "wof:placetype":"postalcode"
},
  "geometry": {"coordinates":[-0.40621046493698,53.74187678918365],"type":"Point"}
}