{
  "type": "Feature",
  "properties": {
    "iso:country":"GB",
    "wof:name":"M24 1GD",
    "wof:placetype":"postalcode"
},
  "geometry": {"coordinates":[-2.19799630051885,53.53401895475254],"type":"Point"}
}