{
  "type": "Feature",
  "properties": {
    "iso:country":"GB",
    "wof:name":"TQ9 6RA",
    "wof:placetype":"postalcode"
},
  "geometry": {"coordinates":[-3.62460907441992,50.40551348969949],"type":"Point"}
}