{
  "type": "Feature",
  "properties": {
    "iso:country":"GB",
    "wof:name":"CW5 7PU",
    "wof:placetype":"postalcode"
},
  "geometry": {"coordinates":[-2.43131781386166,53.0111179344316],"type":"Point"}
}