{
  "type": "Feature",
  "properties": {
    "iso:country": "GB",
    "wof:name": "CW5 7PU",
    "wof:placetype": "postalcode"
  },
  "geometry": {"coordinates":[-2.431187,53.011458],"type":"Point"}
}
