{
  "type": "Feature",
  "properties": {
    "iso:country":"GB",
    "wof:name":"DL2 2AS",
    "wof:placetype":"postalcode"
},
  "geometry": {"coordinates":[-1.52448432011813,54.48772695030487],"type":"Point"}
}