{
  "type": "Feature",
  "properties": {
    "date:inception_lower": "2005-01-01",
    "date:inception_upper": "2005-01-01",
    "iso:country": "GB",
    "wof:name": "NN11 8AJ",
    "wof:placetype": "postalcode"
  },
  "geometry": {"coordinates":[-1.171486,52.281172],"type":"Point"}
}
