{
  "type": "Feature",
  "properties": {
    "iso:country": "GB",
    "wof:name": "RG12 7RB",
    "wof:placetype": "postalcode"
  },
  "geometry": {"coordinates":[-0.763399,51.39157],"type":"Point"}
}
