{
  "type": "Feature",
  "properties": {
    "date:inception_lower": "1991-09-01",
    "date:inception_upper": "1991-09-01",
    "iso:country": "GB",
    "wof:name": "MK7 7SQ",
    "wof:placetype": "postalcode"
  },
  "geometry": {"coordinates":[-0.686253,52.02389],"type":"Point"}
}
