{
  "type": "Feature",
  "properties": {
    "date:inception_lower": "1980-01-01",
    "date:inception_upper": "1980-01-01",
    "iso:country": "GB",
    "wof:name": "LS29 7QB",
    "wof:placetype": "postalcode"
  },
  "geometry": {"coordinates":[-1.74601,53.904709],"type":"Point"}
}
