{
  "type": "Feature",
  "properties": {
    "date:inception_lower": "1980-01-01",
    "date:inception_upper": "1980-01-01",
    "iso:country": "GB",
    "wof:name": "IV27 4BL",
    "wof:placetype": "postalcode"
  },
  "geometry": {"coordinates":[-4.398982,58.024685],"type":"Point"}
}
