{
  "type": "Feature",
  "properties": {
    "iso:country":"GB",
    "wof:name":"SA32 8DZ",
    "wof:placetype":"postalcode"
},
  "geometry": {"coordinates":[-4.31750479201411,51.7928548424399],"type":"Point"}
}