{
  "type": "Feature",
  "properties": {
    "iso:country":"GB",
    "wof:name":"BD12 0HU",
    "wof:placetype":"postalcode"
},
  "geometry": {"coordinates":[-1.75802206504726,53.75378167986936],"type":"Point"}
}