{
  "type": "Feature",
  "properties": {
    "date:inception_lower":"1980-01-01",
    "date:inception_upper":"1980-01-31",
    "iso:country":"GB",
    "wof:name":"BD12 0HU",
    "wof:placetype":"postalcode"
},
  "geometry": {"coordinates":[-1.758022,53.753782],"type":"Point"}
}