{
  "type": "Feature",
  "properties": {
    "iso:country": "GB",
    "wof:name": "OX11 7RR",
    "wof:placetype": "postalcode"
  },
  "geometry": {"coordinates":[-1.231576,51.61578],"type":"Point"}
}
