{
  "type": "Feature",
  "properties": {
    "iso:country":"GB",
    "wof:name":"OX11 7RR",
    "wof:placetype":"postalcode"
},
  "geometry": {"coordinates":[-1.2315764789773,51.61577951359563],"type":"Point"}
}