{
  "type": "Feature",
  "properties": {
    "date:inception_lower":"1991-09-01",
    "date:inception_upper":"1991-09-30",
    "iso:country":"GB",
    "wof:name":"OX11 7RR",
    "wof:placetype":"postalcode"
},
  "geometry": {"coordinates":[-1.231576,51.61578],"type":"Point"}
}