{
  "type": "Feature",
  "properties": {
    "iso:country":"GB",
    "wof:name":"WC1A 1NP",
    "wof:placetype":"postalcode"
},
  "geometry": {"coordinates":[-0.12646040781179,51.51783606704024],"type":"Point"}
}