{
  "type": "Feature",
  "properties": {
    "iso:country":"GB",
    "wof:name":"MK18 1FE",
    "wof:placetype":"postalcode"
},
  "geometry": {"coordinates":[-0.98305969258276,52.00675706484429],"type":"Point"}
}