{
  "type": "Feature",
  "properties": {
    "iso:country": "GB",
    "wof:name": "MK18 1FE",
    "wof:placetype": "postalcode"
  },
  "geometry": {"coordinates":[-0.98306,52.006757],"type":"Point"}
}
