{
  "type": "Feature",
  "properties": {
    "date:inception_lower":"2010-08-01",
    "date:inception_upper":"2010-08-31",
    "iso:country":"GB",
    "wof:name":"MK18 1FE",
    "wof:placetype":"postalcode"
},
  "geometry": {"coordinates":[-0.98306,52.006757],"type":"Point"}
}