{
  "type": "Feature",
  "properties": {
    "iso:country":"GB",
    "wof:name":"SA9 1HY",
    "wof:placetype":"postalcode"
},
  "geometry": {"coordinates":[-3.75201322952223,51.78328550339467],"type":"Point"}
}