{
  "type": "Feature",
  "properties": {
    "iso:country":"GB",
    "wof:name":"LE16 8YH",
    "wof:placetype":"postalcode"
},
  "geometry": {"coordinates":[-0.76803380024255,52.47653526280155],"type":"Point"}
}