{
  "type": "Feature",
  "properties": {
    "iso:country": "GB",
    "wof:name": "LE16 8YH",
    "wof:placetype": "postalcode"
  },
  "geometry": {"coordinates":[-0.76802,52.476552],"type":"Point"}
}
