{
  "type": "Feature",
  "properties": {
    "iso:country": "GB",
    "wof:name": "W1B 2HP",
    "wof:placetype": "postalcode"
  },
  "geometry": {"coordinates":[-0.143093,51.517138],"type":"Point"}
}
