{
  "type": "Feature",
  "properties": {
    "iso:country":"GB",
    "wof:name":"DG3 5BN",
    "wof:placetype":"postalcode"
},
  "geometry": {"coordinates":[-3.76059729888503,55.31881364087966],"type":"Point"}
}