{
  "type": "Feature",
  "properties": {
    "iso:country":"GB",
    "wof:name":"DG9 7JJ",
    "wof:placetype":"postalcode"
},
  "geometry": {"coordinates":[-5.02964407208782,54.90325689744485],"type":"Point"}
}