{
  "type": "Feature",
  "properties": {
    "iso:country":"GB",
    "wof:name":"HU18 1SQ",
    "wof:placetype":"postalcode"
},
  "geometry": {"coordinates":[-0.1687660079555,53.90486680353369],"type":"Point"}
}