{
  "type": "Feature",
  "properties": {
    "iso:country":"GB",
    "wof:name":"AB45 3EP",
    "wof:placetype":"postalcode"
},
  "geometry": {"coordinates":[-2.43094776068571,57.66064057845014],"type":"Point"}
}