{
  "type": "Feature",
  "properties": {
    "date:inception_lower": "1990-08-01",
    "date:inception_upper": "1990-08-01",
    "iso:country": "GB",
    "wof:name": "AB45 3EP",
    "wof:placetype": "postalcode"
  },
  "geometry": {"coordinates":[-2.427857,57.663977],"type":"Point"}
}
