{
  "type": "Feature",
  "properties": {
    "iso:country": "GB",
    "wof:name": "AB45 3EP",
    "wof:placetype": "postalcode"
  },
  "geometry": {"coordinates":[-2.427857,57.663977],"type":"Point"}
}
