{
  "type": "Feature",
  "properties": {
    "iso:country":"GB",
    "wof:name":"W3 0DQ",
    "wof:placetype":"postalcode"
},
  "geometry": {"coordinates":[-0.26613861211403,51.52016377863396],"type":"Point"}
}