{
  "type": "Feature",
  "properties": {
    "iso:country": "GB",
    "wof:name": "BH15 4HA",
    "wof:placetype": "postalcode"
  },
  "geometry": {"coordinates":[-2.00863,50.713285],"type":"Point"}
}
