{
  "type": "Feature",
  "properties": {
    "date:inception_lower":"1997-06-01",
    "date:inception_upper":"1997-06-30",
    "iso:country":"GB",
    "wof:name":"SG12 9UT",
    "wof:placetype":"postalcode"
},
  "geometry": {"coordinates":[-0.029144,51.808322],"type":"Point"}
}