{
  "type": "Feature",
  "properties": {
    "iso:country":"GB",
    "wof:name":"SG12 9UT",
    "wof:placetype":"postalcode"
},
  "geometry": {"coordinates":[-0.02917197371952,51.80831595052017],"type":"Point"}
}