{
  "type": "Feature",
  "properties": {
    "iso:country":"GB",
    "wof:name":"BN44 3FF",
    "wof:placetype":"postalcode"
},
  "geometry": {"coordinates":[-0.3192129182616,50.88731617669998],"type":"Point"}
}