{
  "type": "Feature",
  "properties": {
    "iso:country": "GB",
    "wof:name": "BN44 3FF",
    "wof:placetype": "postalcode"
  },
  "geometry": {"coordinates":[-0.319213,50.887316],"type":"Point"}
}
