{
  "type": "Feature",
  "properties": {
    "iso:country": "GB",
    "wof:name": "NP19 9JD",
    "wof:placetype": "postalcode"
  },
  "geometry": {"coordinates":[-2.924281,51.591418],"type":"Point"}
}
