{
  "type": "Feature",
  "properties": {
    "iso:country": "GB",
    "wof:name": "WF12 7RE",
    "wof:placetype": "postalcode"
  },
  "geometry": {"coordinates":[-1.601493,53.701392],"type":"Point"}
}
