{
  "type": "Feature",
  "properties": {
    "iso:country":"GB",
    "wof:name":"WF12 7RE",
    "wof:placetype":"postalcode"
},
  "geometry": {"coordinates":[-1.60158102492497,53.70134087286738],"type":"Point"}
}