{
  "type": "Feature",
  "properties": {
    "iso:country": "GB",
    "wof:name": "WF4 3PU",
    "wof:placetype": "postalcode"
  },
  "geometry": {"coordinates":[-1.530359,53.640044],"type":"Point"}
}
