{
  "type": "Feature",
  "properties": {
    "iso:country":"GB",
    "wof:name":"WF4 3PU",
    "wof:placetype":"postalcode"
},
  "geometry": {"coordinates":[-1.53035949326044,53.64004388663248],"type":"Point"}
}