{
  "type": "Feature",
  "properties": {
    "date:inception_lower": "1980-01-01",
    "date:inception_upper": "1980-01-01",
    "iso:country": "GB",
    "wof:name": "PA2 7JU",
    "wof:placetype": "postalcode"
  },
  "geometry": {"coordinates":[-4.409491,55.836534],"type":"Point"}
}
