{
  "type": "Feature",
  "properties": {
    "iso:country":"GB",
    "wof:name":"PA2 7JU",
    "wof:placetype":"postalcode"
},
  "geometry": {"coordinates":[-4.40949067670335,55.83653423128268],"type":"Point"}
}