{
  "type": "Feature",
  "properties": {
    "date:inception_lower": "1996-06-01",
    "date:inception_upper": "1996-06-01",
    "iso:country": "GB",
    "wof:name": "GU47 0SS",
    "wof:placetype": "postalcode"
  },
  "geometry": {"coordinates":[-0.781104,51.35487],"type":"Point"}
}
