{
  "type": "Feature",
  "properties": {
    "iso:country":"GB",
    "wof:name":"S13 8JP",
    "wof:placetype":"postalcode"
},
  "geometry": {"coordinates":[-1.39987882190735,53.37382292740828],"type":"Point"}
}