{
  "type": "Feature",
  "properties": {
    "iso:country": "GB",
    "wof:name": "BH19 2QL",
    "wof:placetype": "postalcode"
  },
  "geometry": {"coordinates":[-1.971004,50.608687],"type":"Point"}
}
