{
  "type": "Feature",
  "properties": {
    "iso:country":"GB",
    "wof:name":"WR11 7ST",
    "wof:placetype":"postalcode"
},
  "geometry": {"coordinates":[-2.00340914488764,52.03825995050352],"type":"Point"}
}