{
  "type": "Feature",
  "properties": {
    "date:inception_lower": "1980-01-01",
    "date:inception_upper": "1980-01-01",
    "iso:country": "GB",
    "wof:name": "S73 9NF",
    "wof:placetype": "postalcode"
  },
  "geometry": {"coordinates":[-1.377184,53.534343],"type":"Point"}
}
