{
  "type": "Feature",
  "properties": {
    "date:inception_lower":"2004-08-01",
    "date:inception_upper":"2004-08-31",
    "iso:country":"GB",
    "wof:name":"SW6 4SS",
    "wof:placetype":"postalcode"
},
  "geometry": {"coordinates":[-0.197198,51.473138],"type":"Point"}
}