{
  "type": "Feature",
  "properties": {
    "iso:country":"GB",
    "wof:name":"SW6 4SS",
    "wof:placetype":"postalcode"
},
  "geometry": {"coordinates":[-0.19722197933406,51.47313736884435],"type":"Point"}
}