{
  "type": "Feature",
  "properties": {
    "iso:country": "GB",
    "wof:name": "TW20 9LD",
    "wof:placetype": "postalcode"
  },
  "geometry": {"coordinates":[-0.548275,51.431205],"type":"Point"}
}
