{
  "type": "Feature",
  "properties": {
    "iso:country":"GB",
    "wof:name":"CM9 6AB",
    "wof:placetype":"postalcode"
},
  "geometry": {"coordinates":[0.67660156398873,51.72929665959123],"type":"Point"}
}