{
  "type": "Feature",
  "properties": {
    "iso:country":"GB",
    "wof:name":"LL15 2ER",
    "wof:placetype":"postalcode"
},
  "geometry": {"coordinates":[-3.28216016374067,53.09275278529584],"type":"Point"}
}