{
  "type": "Feature",
  "properties": {
    "iso:country":"GB",
    "wof:name":"SL5 7HL",
    "wof:placetype":"postalcode"
},
  "geometry": {"coordinates":[-0.6728362275945,51.41143249225897],"type":"Point"}
}