{
  "type": "Feature",
  "properties": {
    "date:inception_lower": "1980-01-01",
    "date:inception_upper": "1980-01-01",
    "iso:country": "GB",
    "wof:name": "SL5 7HL",
    "wof:placetype": "postalcode"
  },
  "geometry": {"coordinates":[-0.672836,51.411432],"type":"Point"}
}
