{
  "type": "Feature",
  "properties": {
    "iso:country":"GB",
    "wof:name":"L37 7AT",
    "wof:placetype":"postalcode"
},
  "geometry": {"coordinates":[-3.0615394783503,53.5699815291369],"type":"Point"}
}