{
  "type": "Feature",
  "properties": {
    "iso:country":"GB",
    "wof:name":"TN5 7LZ",
    "wof:placetype":"postalcode"
},
  "geometry": {"coordinates":[0.41473702411126,51.04558320502037],"type":"Point"}
}