{
  "type": "Feature",
  "properties": {
    "date:inception_lower":"1994-05-01",
    "date:inception_upper":"1994-05-31",
    "iso:country":"GB",
    "wof:name":"TN5 7LZ",
    "wof:placetype":"postalcode"
},
  "geometry": {"coordinates":[0.41478,51.045598],"type":"Point"}
}