{
  "type": "Feature",
  "properties": {
    "iso:country": "GB",
    "wof:name": "NP4 7AS",
    "wof:placetype": "postalcode"
  },
  "geometry": {"coordinates":[-3.07041,51.726902],"type":"Point"}
}
