{
  "type": "Feature",
  "properties": {
    "iso:country":"GB",
    "wof:name":"EX5 5HP",
    "wof:placetype":"postalcode"
},
  "geometry": {"coordinates":[-3.52869281221445,50.77543000281642],"type":"Point"}
}