{
  "type": "Feature",
  "properties": {
    "iso:country": "GB",
    "wof:name": "EX5 5HP",
    "wof:placetype": "postalcode"
  },
  "geometry": {"coordinates":[-3.528693,50.77543],"type":"Point"}
}
