{
  "type": "Feature",
  "properties": {
    "iso:country":"GB",
    "wof:name":"SA14 8XT",
    "wof:placetype":"postalcode"
},
  "geometry": {"coordinates":[-4.08004534949022,51.69937884101788],"type":"Point"}
}