{
  "type": "Feature",
  "properties": {
    "iso:country":"GB",
    "wof:name":"WA15 0NL",
    "wof:placetype":"postalcode"
},
  "geometry": {"coordinates":[-2.33000465009863,53.37226645650513],"type":"Point"}
}