{
  "type": "Feature",
  "properties": {
    "iso:country": "GB",
    "wof:name": "SY3 7DQ",
    "wof:placetype": "postalcode"
  },
  "geometry": {"coordinates":[-2.747465,52.704012],"type":"Point"}
}
