{
  "type": "Feature",
  "properties": {
    "date:inception_lower": "1980-01-01",
    "date:inception_upper": "1980-01-01",
    "iso:country": "GB",
    "wof:name": "SE7 8DS",
    "wof:placetype": "postalcode"
  },
  "geometry": {"coordinates":[0.049992,51.486063],"type":"Point"}
}
