{
  "type": "Feature",
  "properties": {
    "iso:country":"GB",
    "wof:name":"OL12 7HG",
    "wof:placetype":"postalcode"
},
  "geometry": {"coordinates":[-2.1749151590535,53.63321382173433],"type":"Point"}
}