{
  "type": "Feature",
  "properties": {
    "date:inception_lower": "1980-01-01",
    "date:inception_upper": "1980-01-01",
    "iso:country": "GB",
    "wof:name": "NR30 1EF",
    "wof:placetype": "postalcode"
  },
  "geometry": {"coordinates":[1.737398,52.61251],"type":"Point"}
}
