{
  "type": "Feature",
  "properties": {
    "iso:country":"GB",
    "wof:name":"W2 3TS",
    "wof:placetype":"postalcode"
},
  "geometry": {"coordinates":[-0.18411351071137,51.51278079477085],"type":"Point"}
}