{
  "type": "Feature",
  "properties": {
    "iso:country":"GB",
    "wof:name":"BA5 2ED",
    "wof:placetype":"postalcode"
},
  "geometry": {"coordinates":[-2.65789450530084,51.20609200609181],"type":"Point"}
}