{
  "type": "Feature",
  "properties": {
    "date:inception_lower":"1980-01-01",
    "date:inception_upper":"1980-01-31",
    "iso:country":"GB",
    "wof:name":"BA5 2ED",
    "wof:placetype":"postalcode"
},
  "geometry": {"coordinates":[-2.657894,51.206092],"type":"Point"}
}