{
  "type": "Feature",
  "properties": {
    "iso:country":"GB",
    "wof:name":"M11 2AE",
    "wof:placetype":"postalcode"
},
  "geometry": {"coordinates":[-2.19239144041817,53.47583713133626],"type":"Point"}
}