{
  "type": "Feature",
  "properties": {
    "iso:country":"GB",
    "wof:name":"SW4 9LZ",
    "wof:placetype":"postalcode"
},
  "geometry": {"coordinates":[-0.1360927963411,51.45592296593105],"type":"Point"}
}