{
  "type": "Feature",
  "properties": {
    "date:inception_lower": "2020-08-01",
    "date:inception_upper": "2020-08-01",
    "iso:country": "GB",
    "wof:name": "KA1 5FG",
    "wof:placetype": "postalcode"
  },
  "geometry": {"coordinates":[-4.570159,55.550225],"type":"Point"}
}
