{
  "type": "Feature",
  "properties": {
    "iso:country":"GB",
    "wof:name":"PO21 5NL",
    "wof:placetype":"postalcode"
},
  "geometry": {"coordinates":[-0.69203936738789,50.78857082491989],"type":"Point"}
}