{
  "type": "Feature",
  "properties": {
    "iso:country": "GB",
    "wof:name": "PO21 5NL",
    "wof:placetype": "postalcode"
  },
  "geometry": {"coordinates":[-0.692039,50.788571],"type":"Point"}
}
