{
  "type": "Feature",
  "properties": {
    "iso:country":"GB",
    "wof:name":"WV6 0RB",
    "wof:placetype":"postalcode"
},
  "geometry": {"coordinates":[-2.14692013870503,52.59542658648567],"type":"Point"}
}