{
  "type": "Feature",
  "properties": {
    "iso:country":"GB",
    "wof:name":"TS4 2HP",
    "wof:placetype":"postalcode"
},
  "geometry": {"coordinates":[-1.22643235441623,54.56726074314349],"type":"Point"}
}