{
  "type": "Feature",
  "properties": {
    "iso:country":"GB",
    "wof:name":"CA10 1SG",
    "wof:placetype":"postalcode"
},
  "geometry": {"coordinates":[-2.61152426553447,54.65731717244041],"type":"Point"}
}