{
  "type": "Feature",
  "properties": {
    "date:inception_lower": "2007-10-01",
    "date:inception_upper": "2007-10-01",
    "iso:country": "GB",
    "wof:name": "CA10 1SG",
    "wof:placetype": "postalcode"
  },
  "geometry": {"coordinates":[-2.611354,54.656967],"type":"Point"}
}
