{
  "type": "Feature",
  "properties": {
    "date:inception_lower":"2007-10-01",
    "date:inception_upper":"2007-10-31",
    "iso:country":"GB",
    "wof:name":"CA10 1SG",
    "wof:placetype":"postalcode"
},
  "geometry": {"coordinates":[-2.611083,54.657462],"type":"Point"}
}