{
  "type": "Feature",
  "properties": {
    "iso:country":"GB",
    "wof:name":"WS11 0EH",
    "wof:placetype":"postalcode"
},
  "geometry": {"coordinates":[-2.02697172949895,52.68911576251065],"type":"Point"}
}