{
  "type": "Feature",
  "properties": {
    "iso:country":"GB",
    "wof:name":"S13 8JL",
    "wof:placetype":"postalcode"
},
  "geometry": {"coordinates":[-1.39561608993801,53.3723362667074],"type":"Point"}
}