{
  "type": "Feature",
  "properties": {
    "date:inception_lower":"1980-01-01",
    "date:inception_upper":"1980-01-31",
    "iso:country":"GB",
    "wof:name":"DN21 3NT",
    "wof:placetype":"postalcode"
},
  "geometry": {"coordinates":[-0.698914,53.437486],"type":"Point"}
}