{
  "type": "Feature",
  "properties": {
    "iso:country": "GB",
    "wof:name": "DN21 3NT",
    "wof:placetype": "postalcode"
  },
  "geometry": {"coordinates":[-0.698914,53.437486],"type":"Point"}
}
