{
  "type": "Feature",
  "properties": {
    "iso:country":"GB",
    "wof:name":"FY3 8RA",
    "wof:placetype":"postalcode"
},
  "geometry": {"coordinates":[-3.03567021638988,53.82588749622199],"type":"Point"}
}