{
  "type": "Feature",
  "properties": {
    "iso:country": "GB",
    "wof:name": "FY3 8RA",
    "wof:placetype": "postalcode"
  },
  "geometry": {"coordinates":[-3.03567,53.825887],"type":"Point"}
}
