{
  "type": "Feature",
  "properties": {
    "date:inception_lower": "1980-01-01",
    "date:inception_upper": "1980-01-01",
    "iso:country": "GB",
    "wof:name": "FY3 8RA",
    "wof:placetype": "postalcode"
  },
  "geometry": {"coordinates":[-3.03567,53.825887],"type":"Point"}
}
