{
  "type": "Feature",
  "properties": {
    "iso:country":"GB",
    "wof:name":"WR9 7GA",
    "wof:placetype":"postalcode"
},
  "geometry": {"coordinates":[-2.07501472610643,52.2611006214763],"type":"Point"}
}