{
  "type": "Feature",
  "properties": {
    "date:inception_lower": "2010-04-01",
    "date:inception_upper": "2010-04-01",
    "iso:country": "GB",
    "wof:name": "WR9 7GA",
    "wof:placetype": "postalcode"
  },
  "geometry": {"coordinates":[-2.075015,52.261101],"type":"Point"}
}
