{
  "type": "Feature",
  "properties": {
    "iso:country": "GB",
    "wof:name": "EH3 9FN",
    "wof:placetype": "postalcode"
  },
  "geometry": {"coordinates":[-3.212875,55.942128],"type":"Point"}
}
