{
  "type": "Feature",
  "properties": {
    "date:inception_lower": "2018-09-01",
    "date:inception_upper": "2018-09-01",
    "iso:country": "GB",
    "wof:name": "EH3 9FN",
    "wof:placetype": "postalcode"
  },
  "geometry": {"coordinates":[-3.212875,55.942128],"type":"Point"}
}
