{
  "type": "Feature",
  "properties": {
    "iso:country":"GB",
    "wof:name":"B6 7TG",
    "wof:placetype":"postalcode"
},
  "geometry": {"coordinates":[-1.86474624383107,52.50838336247129],"type":"Point"}
}