{
  "type": "Feature",
  "properties": {
    "date:inception_lower":"1993-01-01",
    "date:inception_upper":"1993-01-31",
    "iso:country":"GB",
    "wof:name":"TN40 2DX",
    "wof:placetype":"postalcode"
},
  "geometry": {"coordinates":[0.476609,50.84864],"type":"Point"}
}