{
  "type": "Feature",
  "properties": {
    "iso:country":"GB",
    "wof:name":"TN40 2DX",
    "wof:placetype":"postalcode"
},
  "geometry": {"coordinates":[0.47660943663917,50.84864042771623],"type":"Point"}
}