{
  "type": "Feature",
  "properties": {
    "iso:country":"GB",
    "wof:name":"LL60 6NW",
    "wof:placetype":"postalcode"
},
  "geometry": {"coordinates":[-4.28883141334157,53.21076398573116],"type":"Point"}
}