{
  "type": "Feature",
  "properties": {
    "iso:country":"GB",
    "wof:name":"TN28 8QU",
    "wof:placetype":"postalcode"
},
  "geometry": {"coordinates":[0.96901506856506,50.98388644076513],"type":"Point"}
}