{
  "type": "Feature",
  "properties": {
    "date:inception_lower": "1980-01-01",
    "date:inception_upper": "1980-01-01",
    "iso:country": "GB",
    "wof:name": "TN28 8QU",
    "wof:placetype": "postalcode"
  },
  "geometry": {"coordinates":[0.969015,50.983886],"type":"Point"}
}
