{
  "type": "Feature",
  "properties": {
    "iso:country": "GB",
    "wof:name": "TA1 5NZ",
    "wof:placetype": "postalcode"
  },
  "geometry": {"coordinates":[-3.124931,51.008126],"type":"Point"}
}
