{
  "type": "Feature",
  "properties": {
    "iso:country":"GB",
    "wof:name":"LD8 2LA",
    "wof:placetype":"postalcode"
},
  "geometry": {"coordinates":[-3.00222698509551,52.26735171889938],"type":"Point"}
}