{
  "type": "Feature",
  "properties": {
    "iso:country": "GB",
    "wof:name": "LD8 2LA",
    "wof:placetype": "postalcode"
  },
  "geometry": {"coordinates":[-3.003129,52.26838],"type":"Point"}
}
