{
  "type": "Feature",
  "properties": {
    "iso:country":"GB",
    "wof:name":"HP6 6DQ",
    "wof:placetype":"postalcode"
},
  "geometry": {"coordinates":[-0.60220663419415,51.68907548519815],"type":"Point"}
}