{
  "type": "Feature",
  "properties": {
    "iso:country": "GB",
    "wof:name": "EX33 2JT",
    "wof:placetype": "postalcode"
  },
  "geometry": {"coordinates":[-4.160785,51.10794],"type":"Point"}
}
