{
  "type": "Feature",
  "properties": {
    "date:inception_lower":"2017-06-01",
    "date:inception_upper":"2017-06-30",
    "iso:country":"GB",
    "wof:name":"EX33 2JT",
    "wof:placetype":"postalcode"
},
  "geometry": {"coordinates":[-4.160785,51.10794],"type":"Point"}
}