{
  "type": "Feature",
  "properties": {
    "iso:country":"GB",
    "wof:name":"M23 0DS",
    "wof:placetype":"postalcode"
},
  "geometry": {"coordinates":[-2.26887497389372,53.41001024396632],"type":"Point"}
}