{
  "type": "Feature",
  "properties": {
    "iso:country":"GB",
    "wof:name":"SN12 6LN",
    "wof:placetype":"postalcode"
},
  "geometry": {"coordinates":[-2.13885019592274,51.37508046688815],"type":"Point"}
}