{
  "type": "Feature",
  "properties": {
    "date:inception_lower":"1987-04-01",
    "date:inception_upper":"1987-04-30",
    "iso:country":"GB",
    "wof:name":"OL11 1HF",
    "wof:placetype":"postalcode"
},
  "geometry": {"coordinates":[-2.156671,53.611128],"type":"Point"}
}