{
  "type": "Feature",
  "properties": {
    "iso:country": "GB",
    "wof:name": "OL11 1HF",
    "wof:placetype": "postalcode"
  },
  "geometry": {"coordinates":[-2.156671,53.611128],"type":"Point"}
}
