{
  "type": "Feature",
  "properties": {
    "iso:country":"GB",
    "wof:name":"RM5 2SR",
    "wof:placetype":"postalcode"
},
  "geometry": {"coordinates":[0.17062403496403,51.60814586174929],"type":"Point"}
}