{
  "type": "Feature",
  "properties": {
    "iso:country":"GB",
    "wof:name":"LS29 8PL",
    "wof:placetype":"postalcode"
},
  "geometry": {"coordinates":[-1.79727940349233,53.92537966955403],"type":"Point"}
}