{
  "type": "Feature",
  "properties": {
    "date:inception_lower": "2012-02-01",
    "date:inception_upper": "2012-02-01",
    "iso:country": "GB",
    "wof:name": "S63 8FD",
    "wof:placetype": "postalcode"
  },
  "geometry": {"coordinates":[-1.327698,53.5144],"type":"Point"}
}
