{
  "type": "Feature",
  "properties": {
    "iso:country": "GB",
    "wof:name": "S63 8FD",
    "wof:placetype": "postalcode"
  },
  "geometry": {"coordinates":[-1.327698,53.5144],"type":"Point"}
}
