{
  "type": "Feature",
  "properties": {
    "date:inception_lower":"2014-09-01",
    "date:inception_upper":"2014-09-30",
    "iso:country":"GB",
    "wof:name":"L1 0AA",
    "wof:placetype":"postalcode"
},
  "geometry": {"coordinates":[-2.981033,53.396727],"type":"Point"}
}