{
  "type": "Feature",
  "properties": {
    "iso:country": "GB",
    "wof:name": "L1 0AA",
    "wof:placetype": "postalcode"
  },
  "geometry": {"coordinates":[-2.981033,53.396727],"type":"Point"}
}
