{
  "type": "Feature",
  "properties": {
    "iso:country": "GB",
    "wof:name": "CT1 3PZ",
    "wof:placetype": "postalcode"
  },
  "geometry": {"coordinates":[1.072305,51.270944],"type":"Point"}
}
