{
  "type": "Feature",
  "properties": {
    "iso:country": "GB",
    "wof:name": "DL16 6RT",
    "wof:placetype": "postalcode"
  },
  "geometry": {"coordinates":[-1.603578,54.701584],"type":"Point"}
}
