{
  "type": "Feature",
  "properties": {
    "iso:country": "GB",
    "wof:name": "M18 8TP",
    "wof:placetype": "postalcode"
  },
  "geometry": {"coordinates":[-2.156565,53.46815],"type":"Point"}
}
