{
  "type": "Feature",
  "properties": {
    "iso:country":"GB",
    "wof:name":"M18 8TP",
    "wof:placetype":"postalcode"
},
  "geometry": {"coordinates":[-2.15656492354347,53.46815045238689],"type":"Point"}
}