{
  "type": "Feature",
  "properties": {
    "date:inception_lower": "1998-12-01",
    "date:inception_upper": "1998-12-01",
    "iso:country": "GB",
    "wof:name": "CW12 3DR",
    "wof:placetype": "postalcode"
  },
  "geometry": {"coordinates":[-2.197363,53.160685],"type":"Point"}
}
