{
  "type": "Feature",
  "properties": {
    "iso:country":"GB",
    "wof:name":"SN11 0LP",
    "wof:placetype":"postalcode"
},
  "geometry": {"coordinates":[-2.01958998056768,51.44044941496097],"type":"Point"}
}