{
  "type": "Feature",
  "properties": {
    "date:inception_lower": "1980-01-01",
    "date:inception_upper": "1980-01-01",
    "iso:country": "GB",
    "wof:name": "SN11 0LP",
    "wof:placetype": "postalcode"
  },
  "geometry": {"coordinates":[-2.020273,51.440052],"type":"Point"}
}
