{
  "type": "Feature",
  "properties": {
    "iso:country":"GB",
    "wof:name":"EN3 4FE",
    "wof:placetype":"postalcode"
},
  "geometry": {"coordinates":[-0.05244249159835,51.64756140737183],"type":"Point"}
}