{
  "type": "Feature",
  "properties": {
    "iso:country":"GB",
    "wof:name":"SY8 4JF",
    "wof:placetype":"postalcode"
},
  "geometry": {"coordinates":[-2.7640398012476,52.30561702577904],"type":"Point"}
}