{
  "type": "Feature",
  "properties": {
    "iso:country": "GB",
    "wof:name": "SY8 4JF",
    "wof:placetype": "postalcode"
  },
  "geometry": {"coordinates":[-2.76404,52.305617],"type":"Point"}
}
