{
  "type": "Feature",
  "properties": {
    "iso:country": "GB",
    "wof:name": "PE26 1DT",
    "wof:placetype": "postalcode"
  },
  "geometry": {"coordinates":[-0.104087,52.449352],"type":"Point"}
}
