{
  "type": "Feature",
  "properties": {
    "date:inception_lower": "1987-04-01",
    "date:inception_upper": "1987-04-01",
    "iso:country": "GB",
    "wof:name": "LE11 1HY",
    "wof:placetype": "postalcode"
  },
  "geometry": {"coordinates":[-1.204188,52.778865],"type":"Point"}
}
