{
  "type": "Feature",
  "properties": {
    "date:inception_lower":"1980-01-01",
    "date:inception_upper":"1980-01-31",
    "iso:country":"GB",
    "wof:name":"AL2 2QY",
    "wof:placetype":"postalcode"
},
  "geometry": {"coordinates":[-0.349821,51.719404],"type":"Point"}
}