{
  "type": "Feature",
  "properties": {
    "iso:country":"GB",
    "wof:name":"AL2 2QY",
    "wof:placetype":"postalcode"
},
  "geometry": {"coordinates":[-0.34982145891758,51.71940448643353],"type":"Point"}
}