{
  "type": "Feature",
  "properties": {
    "date:inception_lower": "2019-09-01",
    "date:inception_upper": "2019-09-01",
    "iso:country": "GB",
    "wof:name": "NN11 4GS",
    "wof:placetype": "postalcode"
  },
  "geometry": {"coordinates":[-1.173421,52.251182],"type":"Point"}
}
