{
  "type": "Feature",
  "properties": {
    "iso:country":"GB",
    "wof:name":"E1 0HY",
    "wof:placetype":"postalcode"
},
  "geometry": {"coordinates":[-0.04256968060328,51.5128779670076],"type":"Point"}
}