{
  "type": "Feature",
  "properties": {
    "iso:country": "GB",
    "wof:name": "TQ1 1NR",
    "wof:placetype": "postalcode"
  },
  "geometry": {"coordinates":[-3.525749,50.469453],"type":"Point"}
}
