{
  "type": "Feature",
  "properties": {
    "iso:country":"GB",
    "wof:name":"TW4 6LD",
    "wof:placetype":"postalcode"
},
  "geometry": {"coordinates":[-0.41086200102059,51.47519318230798],"type":"Point"}
}