{
  "type": "Feature",
  "properties": {
    "iso:country":"GB",
    "wof:name":"AB25 3XN",
    "wof:placetype":"postalcode"
},
  "geometry": {"coordinates":[-2.108886804551,57.15693513059787],"type":"Point"}
}