{
  "type": "Feature",
  "properties": {
    "iso:country":"GB",
    "wof:name":"B98 7SF",
    "wof:placetype":"postalcode"
},
  "geometry": {"coordinates":[-1.90914718128906,52.28886981695231],"type":"Point"}
}