{
  "type": "Feature",
  "properties": {
    "date:inception_lower": "1991-09-01",
    "date:inception_upper": "1991-09-01",
    "iso:country": "GB",
    "wof:name": "B98 7SF",
    "wof:placetype": "postalcode"
  },
  "geometry": {"coordinates":[-1.90887,52.288402],"type":"Point"}
}
