{
  "type": "Feature",
  "properties": {
    "iso:country": "GB",
    "wof:name": "B98 7SF",
    "wof:placetype": "postalcode"
  },
  "geometry": {"coordinates":[-1.90887,52.288402],"type":"Point"}
}
