{
  "type": "Feature",
  "properties": {
    "iso:country":"GB",
    "wof:name":"WA12 0NR",
    "wof:placetype":"postalcode"
},
  "geometry": {"coordinates":[-2.63870566711586,53.45637891227588],"type":"Point"}
}