{
  "type": "Feature",
  "properties": {
    "date:inception_lower":"2014-01-01",
    "date:inception_upper":"2014-01-31",
    "iso:country":"GB",
    "wof:name":"WA12 0NR",
    "wof:placetype":"postalcode"
},
  "geometry": {"coordinates":[-2.638706,53.456379],"type":"Point"}
}