{
  "type": "Feature",
  "properties": {
    "iso:country": "GB",
    "wof:name": "WA12 0NR",
    "wof:placetype": "postalcode"
  },
  "geometry": {"coordinates":[-2.638706,53.456379],"type":"Point"}
}
