{
  "type": "Feature",
  "properties": {
    "date:inception_lower": "2000-06-01",
    "date:inception_upper": "2000-06-01",
    "iso:country": "GB",
    "wof:name": "BB10 3AW",
    "wof:placetype": "postalcode"
  },
  "geometry": {"coordinates":[-2.227887,53.803566],"type":"Point"}
}
