{
  "type": "Feature",
  "properties": {
    "date:inception_lower": "1992-08-01",
    "date:inception_upper": "1992-08-01",
    "iso:country": "GB",
    "wof:name": "EN8 7TJ",
    "wof:placetype": "postalcode"
  },
  "geometry": {"coordinates":[-0.031042,51.683084],"type":"Point"}
}
