{
  "type": "Feature",
  "properties": {
    "iso:country":"GB",
    "wof:name":"EN8 7TJ",
    "wof:placetype":"postalcode"
},
  "geometry": {"coordinates":[-0.03104199234018,51.68308427416505],"type":"Point"}
}