{
  "type": "Feature",
  "properties": {
    "iso:country": "GB",
    "wof:name": "EN8 7TJ",
    "wof:placetype": "postalcode"
  },
  "geometry": {"coordinates":[-0.031042,51.683084],"type":"Point"}
}
