{
  "type": "Feature",
  "properties": {
    "iso:country":"GB",
    "wof:name":"IG10 4HZ",
    "wof:placetype":"postalcode"
},
  "geometry": {"coordinates":[0.05016245337884,51.64284705889312],"type":"Point"}
}