{
  "type": "Feature",
  "properties": {
    "iso:country": "GB",
    "wof:name": "HR4 9NW",
    "wof:placetype": "postalcode"
  },
  "geometry": {"coordinates":[-2.726673,52.067225],"type":"Point"}
}
