{
  "type": "Feature",
  "properties": {
    "iso:country":"GB",
    "wof:name":"SS8 0JB",
    "wof:placetype":"postalcode"
},
  "geometry": {"coordinates":[0.58559563772163,51.5199822498406],"type":"Point"}
}