{
  "type": "Feature",
  "properties": {
    "iso:country": "GB",
    "wof:name": "RG30 2EZ",
    "wof:placetype": "postalcode"
  },
  "geometry": {"coordinates":[-1.001695,51.447874],"type":"Point"}
}
