{
  "type": "Feature",
  "properties": {
    "date:inception_lower": "1980-01-01",
    "date:inception_upper": "1980-01-01",
    "iso:country": "GB",
    "wof:name": "TS18 2HL",
    "wof:placetype": "postalcode"
  },
  "geometry": {"coordinates":[-1.305158,54.569032],"type":"Point"}
}
