{
  "type": "Feature",
  "properties": {
    "iso:country":"GB",
    "wof:name":"TS18 2HL",
    "wof:placetype":"postalcode"
},
  "geometry": {"coordinates":[-1.30515831356153,54.56903234673338],"type":"Point"}
}