{
  "type": "Feature",
  "properties": {
    "iso:country": "GB",
    "wof:name": "TS18 2HL",
    "wof:placetype": "postalcode"
  },
  "geometry": {"coordinates":[-1.305158,54.569032],"type":"Point"}
}
