{
  "type": "Feature",
  "properties": {
    "date:inception_lower": "1980-01-01",
    "date:inception_upper": "1980-01-01",
    "iso:country": "GB",
    "wof:name": "PO21 5LS",
    "wof:placetype": "postalcode"
  },
  "geometry": {"coordinates":[-0.686461,50.790199],"type":"Point"}
}
