{
  "type": "Feature",
  "properties": {
    "iso:country":"GB",
    "wof:name":"KY12 8JG",
    "wof:placetype":"postalcode"
},
  "geometry": {"coordinates":[-3.63016992974719,56.05502475647808],"type":"Point"}
}