{
  "type": "Feature",
  "properties": {
    "iso:country":"GB",
    "wof:name":"WF12 7TQ",
    "wof:placetype":"postalcode"
},
  "geometry": {"coordinates":[-1.615711069229,53.69492450801904],"type":"Point"}
}