{
  "type": "Feature",
  "properties": {
    "date:inception_lower": "1980-01-01",
    "date:inception_upper": "1980-01-01",
    "iso:country": "GB",
    "wof:name": "N1 9LJ",
    "wof:placetype": "postalcode"
  },
  "geometry": {"coordinates":[-0.106545,51.532687],"type":"Point"}
}
