{
  "type": "Feature",
  "properties": {
    "iso:country":"GB",
    "wof:name":"DN35 8EZ",
    "wof:placetype":"postalcode"
},
  "geometry": {"coordinates":[-0.02598747039602,53.55741020102462],"type":"Point"}
}