{
  "type": "Feature",
  "properties": {
    "iso:country":"GB",
    "wof:name":"NR1 1PD",
    "wof:placetype":"postalcode"
},
  "geometry": {"coordinates":[1.29920490811127,52.6284795721792],"type":"Point"}
}