{
  "type": "Feature",
  "properties": {
    "date:inception_lower": "1980-01-01",
    "date:inception_upper": "1980-01-01",
    "iso:country": "GB",
    "wof:name": "LS26 8EN",
    "wof:placetype": "postalcode"
  },
  "geometry": {"coordinates":[-1.451136,53.741229],"type":"Point"}
}
