{
  "type": "Feature",
  "properties": {
    "iso:country":"GB",
    "wof:name":"LS26 8EN",
    "wof:placetype":"postalcode"
},
  "geometry": {"coordinates":[-1.45113586825278,53.74122924354864],"type":"Point"}
}