{
  "type": "Feature",
  "properties": {
    "iso:country":"GB",
    "wof:name":"S42 5BL",
    "wof:placetype":"postalcode"
},
  "geometry": {"coordinates":[-1.40243337329397,53.20285853394507],"type":"Point"}
}