{
  "type": "Feature",
  "properties": {
    "iso:country":"GB",
    "wof:name":"DY7 5EG",
    "wof:placetype":"postalcode"
},
  "geometry": {"coordinates":[-2.25353898154582,52.52164612246488],"type":"Point"}
}