{
  "type": "Feature",
  "properties": {
    "iso:country": "GB",
    "wof:name": "DY7 5EG",
    "wof:placetype": "postalcode"
  },
  "geometry": {"coordinates":[-2.253539,52.521646],"type":"Point"}
}
