{
  "type": "Feature",
  "properties": {
    "date:inception_lower": "1980-01-01",
    "date:inception_upper": "1980-01-01",
    "iso:country": "GB",
    "wof:name": "DY7 5EG",
    "wof:placetype": "postalcode"
  },
  "geometry": {"coordinates":[-2.249165,52.52051],"type":"Point"}
}
