{
  "type": "Feature",
  "properties": {
    "iso:country": "GB",
    "wof:name": "S62 7HP",
    "wof:placetype": "postalcode"
  },
  "geometry": {"coordinates":[-1.342835,53.47158],"type":"Point"}
}
