{
  "type": "Feature",
  "properties": {
    "iso:country":"GB",
    "wof:name":"S62 7HP",
    "wof:placetype":"postalcode"
},
  "geometry": {"coordinates":[-1.34283492755878,53.4715803127612],"type":"Point"}
}