{
  "type": "Feature",
  "properties": {
    "date:inception_lower": "1995-12-01",
    "date:inception_upper": "1995-12-01",
    "iso:country": "GB",
    "wof:name": "TA2 6PH",
    "wof:placetype": "postalcode"
  },
  "geometry": {"coordinates":[-3.156317,51.044369],"type":"Point"}
}
