{
  "type": "Feature",
  "properties": {
    "iso:country":"GB",
    "wof:name":"TA2 6PH",
    "wof:placetype":"postalcode"
},
  "geometry": {"coordinates":[-3.15591558800485,51.04409905406772],"type":"Point"}
}