{
  "type": "Feature",
  "properties": {
    "iso:country":"GB",
    "wof:name":"BH23 7AE",
    "wof:placetype":"postalcode"
},
  "geometry": {"coordinates":[-1.76524011187632,50.76468550707394],"type":"Point"}
}