{
  "type": "Feature",
  "properties": {
    "date:inception_lower": "1994-05-01",
    "date:inception_upper": "1994-05-01",
    "iso:country": "GB",
    "wof:name": "M33 4BY",
    "wof:placetype": "postalcode"
  },
  "geometry": {"coordinates":[-2.355028,53.418998],"type":"Point"}
}
