{
  "type": "Feature",
  "properties": {
    "date:inception_lower": "1980-01-01",
    "date:inception_upper": "1980-01-01",
    "iso:country": "GB",
    "wof:name": "EH51 0ND",
    "wof:placetype": "postalcode"
  },
  "geometry": {"coordinates":[-3.626159,56.005888],"type":"Point"}
}
