{
  "type": "Feature",
  "properties": {
    "date:inception_lower": "1980-01-01",
    "date:inception_upper": "1980-01-01",
    "iso:country": "GB",
    "wof:name": "L34 1ND",
    "wof:placetype": "postalcode"
  },
  "geometry": {"coordinates":[-2.805295,53.426707],"type":"Point"}
}
