{
  "type": "Feature",
  "properties": {
    "iso:country":"GB",
    "wof:name":"L34 1ND",
    "wof:placetype":"postalcode"
},
  "geometry": {"coordinates":[-2.80529528078335,53.42670673623159],"type":"Point"}
}