{
  "type": "Feature",
  "properties": {
    "iso:country":"GB",
    "wof:name":"PR8 6BP",
    "wof:placetype":"postalcode"
},
  "geometry": {"coordinates":[-2.98802261736347,53.64349137978491],"type":"Point"}
}