{
  "type": "Feature",
  "properties": {
    "iso:country":"GB",
    "wof:name":"EX6 8AX",
    "wof:placetype":"postalcode"
},
  "geometry": {"coordinates":[-3.5014765121868,50.67621913025035],"type":"Point"}
}