{
  "type": "Feature",
  "properties": {
    "date:inception_lower": "1980-01-01",
    "date:inception_upper": "1980-01-01",
    "iso:country": "GB",
    "wof:name": "EX6 8AX",
    "wof:placetype": "postalcode"
  },
  "geometry": {"coordinates":[-3.501448,50.676208],"type":"Point"}
}
