{
  "type": "Feature",
  "properties": {
    "iso:country":"GB",
    "wof:name":"TN27 8NJ",
    "wof:placetype":"postalcode"
},
  "geometry": {"coordinates":[0.70017138784532,51.15405489312559],"type":"Point"}
}