{
  "type": "Feature",
  "properties": {
    "iso:country": "GB",
    "wof:name": "B61 0AT",
    "wof:placetype": "postalcode"
  },
  "geometry": {"coordinates":[-2.061744,52.34799],"type":"Point"}
}
