{
  "type": "Feature",
  "properties": {
    "date:inception_lower": "1980-01-01",
    "date:inception_upper": "1980-01-01",
    "iso:country": "GB",
    "wof:name": "B61 0AT",
    "wof:placetype": "postalcode"
  },
  "geometry": {"coordinates":[-2.061744,52.34799],"type":"Point"}
}
