{
  "type": "Feature",
  "properties": {
    "date:inception_lower":"2007-10-01",
    "date:inception_upper":"2007-10-31",
    "iso:country":"GB",
    "wof:name":"SY6 6BF",
    "wof:placetype":"postalcode"
},
  "geometry": {"coordinates":[-2.808538,52.538645],"type":"Point"}
}