{
  "type": "Feature",
  "properties": {
    "iso:country":"GB",
    "wof:name":"DA5 2DH",
    "wof:placetype":"postalcode"
},
  "geometry": {"coordinates":[0.16396439463738,51.44058780224221],"type":"Point"}
}