{
  "type": "Feature",
  "properties": {
    "iso:country": "GB",
    "wof:name": "DT7 3RD",
    "wof:placetype": "postalcode"
  },
  "geometry": {"coordinates":[-3.01327,50.721875],"type":"Point"}
}
