{
  "type": "Feature",
  "properties": {
    "iso:country":"GB",
    "wof:name":"DT7 3RD",
    "wof:placetype":"postalcode"
},
  "geometry": {"coordinates":[-3.01326983538647,50.72187476272321],"type":"Point"}
}