{
  "type": "Feature",
  "properties": {
    "date:inception_lower": "1980-01-01",
    "date:inception_upper": "1980-01-01",
    "iso:country": "GB",
    "wof:name": "DT7 3RD",
    "wof:placetype": "postalcode"
  },
  "geometry": {"coordinates":[-3.01327,50.721875],"type":"Point"}
}
