{
  "type": "Feature",
  "properties": {
    "iso:country":"GB",
    "wof:name":"PO8 8XA",
    "wof:placetype":"postalcode"
},
  "geometry": {"coordinates":[-1.02078515511665,50.89554242165976],"type":"Point"}
}