{
  "type": "Feature",
  "properties": {
    "iso:country":"GB",
    "wof:name":"LA1 1AU",
    "wof:placetype":"postalcode"
},
  "geometry": {"coordinates":[-2.79730285837875,54.04565041279509],"type":"Point"}
}