{
  "type": "Feature",
  "properties": {
    "date:inception_lower": "2008-10-01",
    "date:inception_upper": "2008-10-01",
    "iso:country": "GB",
    "wof:name": "LA1 1AU",
    "wof:placetype": "postalcode"
  },
  "geometry": {"coordinates":[-2.797303,54.04565],"type":"Point"}
}
