{
  "type": "Feature",
  "properties": {
    "iso:country":"GB",
    "wof:name":"EN2 8EX",
    "wof:placetype":"postalcode"
},
  "geometry": {"coordinates":[-0.09624496783287,51.65883681944911],"type":"Point"}
}