{
  "type": "Feature",
  "properties": {
    "iso:country": "GB",
    "wof:name": "G82 1AW",
    "wof:placetype": "postalcode"
  },
  "geometry": {"coordinates":[-4.568006,55.94275],"type":"Point"}
}
