{
  "type": "Feature",
  "properties": {
    "iso:country":"GB",
    "wof:name":"NG1 5AA",
    "wof:placetype":"postalcode"
},
  "geometry": {"coordinates":[-1.15620819070179,52.95452329356306],"type":"Point"}
}