{
  "type": "Feature",
  "properties": {
    "iso:country":"GB",
    "wof:name":"TA6 4QF",
    "wof:placetype":"postalcode"
},
  "geometry": {"coordinates":[-2.97892255203684,51.13560380149896],"type":"Point"}
}