{
  "type": "Feature",
  "properties": {
    "iso:country": "GB",
    "wof:name": "TA6 4QF",
    "wof:placetype": "postalcode"
  },
  "geometry": {"coordinates":[-2.978923,51.135604],"type":"Point"}
}
