{
  "type": "Feature",
  "properties": {
    "iso:country":"GB",
    "wof:name":"CM6 3QA",
    "wof:placetype":"postalcode"
},
  "geometry": {"coordinates":[0.38795748272917,51.94929563261135],"type":"Point"}
}