{
  "type": "Feature",
  "properties": {
    "iso:country": "GB",
    "wof:name": "NG20 0NW",
    "wof:placetype": "postalcode"
  },
  "geometry": {"coordinates":[-1.154824,53.202295],"type":"Point"}
}
