{
  "type": "Feature",
  "properties": {
    "iso:country": "GB",
    "wof:name": "SY23 5AP",
    "wof:placetype": "postalcode"
  },
  "geometry": {"coordinates":[-4.078248,52.331492],"type":"Point"}
}
