{
  "type": "Feature",
  "properties": {
    "iso:country":"GB",
    "wof:name":"SY23 5AP",
    "wof:placetype":"postalcode"
},
  "geometry": {"coordinates":[-4.07824829573558,52.33149240880753],"type":"Point"}
}