{
  "type": "Feature",
  "properties": {
    "date:inception_lower": "1980-01-01",
    "date:inception_upper": "1980-01-01",
    "iso:country": "GB",
    "wof:name": "GL52 3EF",
    "wof:placetype": "postalcode"
  },
  "geometry": {"coordinates":[-2.055855,51.915766],"type":"Point"}
}
