{
  "type": "Feature",
  "properties": {
    "iso:country":"GB",
    "wof:name":"GL52 3EF",
    "wof:placetype":"postalcode"
},
  "geometry": {"coordinates":[-2.05585522536799,51.91576592749424],"type":"Point"}
}