{
  "type": "Feature",
  "properties": {
    "iso:country":"GB",
    "wof:name":"B26 3QZ",
    "wof:placetype":"postalcode"
},
  "geometry": {"coordinates":[-1.73362749384414,52.45298066335811],"type":"Point"}
}