{
  "type": "Feature",
  "properties": {
    "date:inception_lower":"1980-01-01",
    "date:inception_upper":"1980-01-31",
    "iso:country":"GB",
    "wof:name":"ME5 7AP",
    "wof:placetype":"postalcode"
},
  "geometry": {"coordinates":[0.541315,51.376757],"type":"Point"}
}