{
  "type": "Feature",
  "properties": {
    "iso:country":"GB",
    "wof:name":"CT3 4BD",
    "wof:placetype":"postalcode"
},
  "geometry": {"coordinates":[1.18298643735236,51.30077115757926],"type":"Point"}
}