{
  "type": "Feature",
  "properties": {
    "iso:country":"GB",
    "wof:name":"G46 7DJ",
    "wof:placetype":"postalcode"
},
  "geometry": {"coordinates":[-4.31237698140246,55.8054411469751],"type":"Point"}
}