{
  "type": "Feature",
  "properties": {
    "iso:country":"GB",
    "wof:name":"SA38 9BX",
    "wof:placetype":"postalcode"
},
  "geometry": {"coordinates":[-4.46073330654046,52.03591393136122],"type":"Point"}
}