{
  "type": "Feature",
  "properties": {
    "date:inception_lower": "1980-01-01",
    "date:inception_upper": "1980-01-01",
    "iso:country": "GB",
    "wof:name": "SA38 9BX",
    "wof:placetype": "postalcode"
  },
  "geometry": {"coordinates":[-4.460841,52.035889],"type":"Point"}
}
