{
  "type": "Feature",
  "properties": {
    "iso:country":"GB",
    "wof:name":"DL11 7JY",
    "wof:placetype":"postalcode"
},
  "geometry": {"coordinates":[-1.7861604560814,54.46692168419323],"type":"Point"}
}