{
  "type": "Feature",
  "properties": {
    "iso:country": "GB",
    "wof:name": "LL53 6HG",
    "wof:placetype": "postalcode"
  },
  "geometry": {"coordinates":[-4.519947,52.934582],"type":"Point"}
}
