{
  "type": "Feature",
  "properties": {
    "date:inception_lower": "1980-01-01",
    "date:inception_upper": "1980-01-01",
    "iso:country": "GB",
    "wof:name": "PO16 8JL",
    "wof:placetype": "postalcode"
  },
  "geometry": {"coordinates":[-1.123166,50.853758],"type":"Point"}
}
