{
  "type": "Feature",
  "properties": {
    "date:inception_lower": "1980-01-01",
    "date:inception_upper": "1980-01-01",
    "iso:country": "GB",
    "wof:name": "TN31 6XP",
    "wof:placetype": "postalcode"
  },
  "geometry": {"coordinates":[0.633861,50.954249],"type":"Point"}
}
