{
  "type": "Feature",
  "properties": {
    "iso:country":"GB",
    "wof:name":"TN31 6XP",
    "wof:placetype":"postalcode"
},
  "geometry": {"coordinates":[0.63312983377571,50.95393553716303],"type":"Point"}
}