{
  "type": "Feature",
  "properties": {
    "iso:country":"GB",
    "wof:name":"HP15 6BH",
    "wof:placetype":"postalcode"
},
  "geometry": {"coordinates":[-0.71741337381053,51.66377420913697],"type":"Point"}
}