{
  "type": "Feature",
  "properties": {
    "iso:country": "GB",
    "wof:name": "PL32 9UL",
    "wof:placetype": "postalcode"
  },
  "geometry": {"coordinates":[-4.682303,50.621769],"type":"Point"}
}
