{
  "type": "Feature",
  "properties": {
    "date:inception_lower": "1980-01-01",
    "date:inception_upper": "1980-01-01",
    "iso:country": "GB",
    "wof:name": "ML3 7XU",
    "wof:placetype": "postalcode"
  },
  "geometry": {"coordinates":[-4.03072,55.73852],"type":"Point"}
}
