{
  "type": "Feature",
  "properties": {
    "iso:country":"GB",
    "wof:name":"ML3 7XU",
    "wof:placetype":"postalcode"
},
  "geometry": {"coordinates":[-4.03071997456692,55.73852019168093],"type":"Point"}
}