{
  "type": "Feature",
  "properties": {
    "date:inception_lower": "2023-12-01",
    "date:inception_upper": "2023-12-01",
    "iso:country": "GB",
    "wof:name": "SK11 0BT",
    "wof:placetype": "postalcode"
  },
  "geometry": {"coordinates":[-2.127754,53.235298],"type":"Point"}
}
