{
  "type": "Feature",
  "properties": {
    "iso:country":"GB",
    "wof:name":"BL0 0JS",
    "wof:placetype":"postalcode"
},
  "geometry": {"coordinates":[-2.30427390500257,53.66890750195672],"type":"Point"}
}