{
  "type": "Feature",
  "properties": {
    "iso:country": "GB",
    "wof:name": "SG5 4PR",
    "wof:placetype": "postalcode"
  },
  "geometry": {"coordinates":[-0.219768,52.013421],"type":"Point"}
}
