{
  "type": "Feature",
  "properties": {
    "iso:country":"GB",
    "wof:name":"SG5 4PR",
    "wof:placetype":"postalcode"
},
  "geometry": {"coordinates":[-0.21976847465207,52.01342130935164],"type":"Point"}
}