{
  "type": "Feature",
  "properties": {
    "iso:country": "GB",
    "wof:name": "SN7 7RU",
    "wof:placetype": "postalcode"
  },
  "geometry": {"coordinates":[-1.557958,51.600962],"type":"Point"}
}
