{
  "type": "Feature",
  "properties": {
    "iso:country":"GB",
    "wof:name":"SN7 7RU",
    "wof:placetype":"postalcode"
},
  "geometry": {"coordinates":[-1.55795805112969,51.60096211285467],"type":"Point"}
}