{
  "type": "Feature",
  "properties": {
    "iso:country":"GB",
    "wof:name":"SN7 8DS",
    "wof:placetype":"postalcode"
},
  "geometry": {"coordinates":[-1.58830998205327,51.65653984839949],"type":"Point"}
}