{
  "type": "Feature",
  "properties": {
    "iso:country":"GB",
    "wof:name":"DG12 5LH",
    "wof:placetype":"postalcode"
},
  "geometry": {"coordinates":[-3.27624140747299,55.02379972446242],"type":"Point"}
}