{
  "type": "Feature",
  "properties": {
    "date:inception_lower": "2003-09-01",
    "date:inception_upper": "2003-09-01",
    "iso:country": "GB",
    "wof:name": "DG12 5LH",
    "wof:placetype": "postalcode"
  },
  "geometry": {"coordinates":[-3.276241,55.0238],"type":"Point"}
}
