{
  "type": "Feature",
  "properties": {
    "iso:country":"GB",
    "wof:name":"NR9 3NJ",
    "wof:placetype":"postalcode"
},
  "geometry": {"coordinates":[1.203289600378,52.61078894634427],"type":"Point"}
}