{
  "type": "Feature",
  "properties": {
    "date:inception_lower":"1980-01-01",
    "date:inception_upper":"1980-01-31",
    "iso:country":"GB",
    "wof:name":"DL12 9JG",
    "wof:placetype":"postalcode"
},
  "geometry": {"coordinates":[-2.016721,54.539067],"type":"Point"}
}