{
  "type": "Feature",
  "properties": {
    "iso:country":"GB",
    "wof:name":"DL12 9JG",
    "wof:placetype":"postalcode"
},
  "geometry": {"coordinates":[-2.01672092118015,54.53906725824999],"type":"Point"}
}