{
  "type": "Feature",
  "properties": {
    "iso:country": "GB",
    "wof:name": "DL12 9JG",
    "wof:placetype": "postalcode"
  },
  "geometry": {"coordinates":[-2.016721,54.539067],"type":"Point"}
}
