{
  "type": "Feature",
  "properties": {
    "iso:country": "GB",
    "wof:name": "S75 3AZ",
    "wof:placetype": "postalcode"
  },
  "geometry": {"coordinates":[-1.492557,53.497855],"type":"Point"}
}
