{
  "type": "Feature",
  "properties": {
    "iso:country":"GB",
    "wof:name":"EX5 2LT",
    "wof:placetype":"postalcode"
},
  "geometry": {"coordinates":[-3.38056406679199,50.74322096875015],"type":"Point"}
}