{
  "type": "Feature",
  "properties": {
    "date:inception_lower": "1980-01-01",
    "date:inception_upper": "1980-01-01",
    "iso:country": "GB",
    "wof:name": "EX5 2LT",
    "wof:placetype": "postalcode"
  },
  "geometry": {"coordinates":[-3.380564,50.743221],"type":"Point"}
}
