{
  "type": "Feature",
  "properties": {
    "iso:country": "GB",
    "wof:name": "EX5 2LT",
    "wof:placetype": "postalcode"
  },
  "geometry": {"coordinates":[-3.380564,50.743221],"type":"Point"}
}
