{
  "type": "Feature",
  "properties": {
    "iso:country": "GB",
    "wof:name": "PO33 4EZ",
    "wof:placetype": "postalcode"
  },
  "geometry": {"coordinates":[-1.215189,50.72809],"type":"Point"}
}
