{
  "type": "Feature",
  "properties": {
    "iso:country":"GB",
    "wof:name":"ST1 3ER",
    "wof:placetype":"postalcode"
},
  "geometry": {"coordinates":[-2.16703033502081,53.01756335974053],"type":"Point"}
}