{
  "type": "Feature",
  "properties": {
    "date:inception_lower": "1994-05-01",
    "date:inception_upper": "1994-05-01",
    "iso:country": "GB",
    "wof:name": "M9 4JY",
    "wof:placetype": "postalcode"
  },
  "geometry": {"coordinates":[-2.208228,53.510056],"type":"Point"}
}
