{
  "type": "Feature",
  "properties": {
    "iso:country": "GB",
    "wof:name": "BB9 7HY",
    "wof:placetype": "postalcode"
  },
  "geometry": {"coordinates":[-2.22255,53.836153],"type":"Point"}
}
