{
  "type": "Feature",
  "properties": {
    "date:inception_lower": "1980-01-01",
    "date:inception_upper": "1980-01-01",
    "iso:country": "GB",
    "wof:name": "B49 5HD",
    "wof:placetype": "postalcode"
  },
  "geometry": {"coordinates":[-1.87709,52.21227],"type":"Point"}
}
