{
  "type": "Feature",
  "properties": {
    "iso:country":"GB",
    "wof:name":"B49 5HD",
    "wof:placetype":"postalcode"
},
  "geometry": {"coordinates":[-1.87709049067976,52.21227037148343],"type":"Point"}
}