{
  "type": "Feature",
  "properties": {
    "date:inception_lower": "2020-04-01",
    "date:inception_upper": "2020-04-01",
    "iso:country": "GB",
    "wof:name": "SO41 5AB",
    "wof:placetype": "postalcode"
  },
  "geometry": {"coordinates":[-1.492968,50.762786],"type":"Point"}
}
