{
  "type": "Feature",
  "properties": {
    "iso:country":"GB",
    "wof:name":"KY14 6EB",
    "wof:placetype":"postalcode"
},
  "geometry": {"coordinates":[-3.2409046002511,56.35097908416397],"type":"Point"}
}