{
  "type": "Feature",
  "properties": {
    "iso:country": "GB",
    "wof:name": "KY14 6EB",
    "wof:placetype": "postalcode"
  },
  "geometry": {"coordinates":[-3.240905,56.350979],"type":"Point"}
}
