{
  "type": "Feature",
  "properties": {
    "date:inception_lower": "2008-10-01",
    "date:inception_upper": "2008-10-01",
    "iso:country": "GB",
    "wof:name": "CB2 3WD",
    "wof:placetype": "postalcode"
  },
  "geometry": {"coordinates":[0.137179,52.192254],"type":"Point"}
}
