{
  "type": "Feature",
  "properties": {
    "iso:country": "GB",
    "wof:name": "NR4 6HU",
    "wof:placetype": "postalcode"
  },
  "geometry": {"coordinates":[1.264608,52.608286],"type":"Point"}
}
