{
  "type": "Feature",
  "properties": {
    "iso:country":"GB",
    "wof:name":"PL9 9LG",
    "wof:placetype":"postalcode"
},
  "geometry": {"coordinates":[-4.09462470123301,50.35575962163674],"type":"Point"}
}