{
  "type": "Feature",
  "properties": {
    "date:inception_lower": "1980-01-01",
    "date:inception_upper": "1980-01-01",
    "iso:country": "GB",
    "wof:name": "CA16 6AY",
    "wof:placetype": "postalcode"
  },
  "geometry": {"coordinates":[-2.583882,54.604063],"type":"Point"}
}
