{
  "type": "Feature",
  "properties": {
    "iso:country":"GB",
    "wof:name":"NG10 2DJ",
    "wof:placetype":"postalcode"
},
  "geometry": {"coordinates":[-1.26352227868067,52.89711047923003],"type":"Point"}
}