{
  "type": "Feature",
  "properties": {
    "iso:country":"GB",
    "wof:name":"SY14 7BL",
    "wof:placetype":"postalcode"
},
  "geometry": {"coordinates":[-2.83816583073666,53.03728914032596],"type":"Point"}
}