{
  "type": "Feature",
  "properties": {
    "iso:country": "GB",
    "wof:name": "SY14 7BL",
    "wof:placetype": "postalcode"
  },
  "geometry": {"coordinates":[-2.838166,53.037289],"type":"Point"}
}
