{
  "type": "Feature",
  "properties": {
    "iso:country":"GB",
    "wof:name":"NN9 5ET",
    "wof:placetype":"postalcode"
},
  "geometry": {"coordinates":[-0.64344422287123,52.33981722573204],"type":"Point"}
}