{
  "type": "Feature",
  "properties": {
    "iso:country": "GB",
    "wof:name": "ST18 0ZT",
    "wof:placetype": "postalcode"
  },
  "geometry": {"coordinates":[-2.081492,52.809668],"type":"Point"}
}
