{
  "type": "Feature",
  "properties": {
    "date:inception_lower":"2016-06-01",
    "date:inception_upper":"2016-06-30",
    "iso:country":"GB",
    "wof:name":"ST18 0ZT",
    "wof:placetype":"postalcode"
},
  "geometry": {"coordinates":[-2.081492,52.809668],"type":"Point"}
}