{
  "type": "Feature",
  "properties": {
    "iso:country":"GB",
    "wof:name":"BA1 5UF",
    "wof:placetype":"postalcode"
},
  "geometry": {"coordinates":[-2.35766564738788,51.38885922023205],"type":"Point"}
}