{
  "type": "Feature",
  "properties": {
    "date:inception_lower": "1992-01-01",
    "date:inception_upper": "1992-01-01",
    "iso:country": "GB",
    "wof:name": "BA1 5UF",
    "wof:placetype": "postalcode"
  },
  "geometry": {"coordinates":[-2.357666,51.388859],"type":"Point"}
}
