{
  "type": "Feature",
  "properties": {
    "iso:country":"GB",
    "wof:name":"HA1 4AG",
    "wof:placetype":"postalcode"
},
  "geometry": {"coordinates":[-0.35432422896637,51.57489287523261],"type":"Point"}
}