{
  "type": "Feature",
  "properties": {
    "iso:country": "GB",
    "wof:name": "B78 2AQ",
    "wof:placetype": "postalcode"
  },
  "geometry": {"coordinates":[-1.738574,52.581817],"type":"Point"}
}
