{
  "type": "Feature",
  "properties": {
    "iso:country":"GB",
    "wof:name":"B78 2AQ",
    "wof:placetype":"postalcode"
},
  "geometry": {"coordinates":[-1.73857417699634,52.58181730998778],"type":"Point"}
}