{
  "type": "Feature",
  "properties": {
    "iso:country":"GB",
    "wof:name":"BD18 4QR",
    "wof:placetype":"postalcode"
},
  "geometry": {"coordinates":[-1.78665551261022,53.83160001401072],"type":"Point"}
}