{
  "type": "Feature",
  "properties": {
    "iso:country":"GB",
    "wof:name":"BA3 5EH",
    "wof:placetype":"postalcode"
},
  "geometry": {"coordinates":[-2.4629404779223,51.24972883585752],"type":"Point"}
}