{
  "type": "Feature",
  "properties": {
    "date:inception_lower":"2018-12-01",
    "date:inception_upper":"2018-12-31",
    "iso:country":"GB",
    "wof:name":"IV25 3SJ",
    "wof:placetype":"postalcode"
},
  "geometry": {"coordinates":[-4.031007,57.880508],"type":"Point"}
}