{
  "type": "Feature",
  "properties": {
    "iso:country":"GB",
    "wof:name":"AB51 5JQ",
    "wof:placetype":"postalcode"
},
  "geometry": {"coordinates":[-2.43011793610602,57.27126316967083],"type":"Point"}
}