{
  "type": "Feature",
  "properties": {
    "iso:country":"GB",
    "wof:name":"WA7 2EQ",
    "wof:placetype":"postalcode"
},
  "geometry": {"coordinates":[-2.69891794040839,53.33633847670481],"type":"Point"}
}