{
  "type": "Feature",
  "properties": {
    "iso:country": "GB",
    "wof:name": "L31 1EL",
    "wof:placetype": "postalcode"
  },
  "geometry": {"coordinates":[-2.92215,53.492459],"type":"Point"}
}
