{
  "type": "Feature",
  "properties": {
    "iso:country":"GB",
    "wof:name":"L31 1EL",
    "wof:placetype":"postalcode"
},
  "geometry": {"coordinates":[-2.92215032368488,53.49245950219437],"type":"Point"}
}