{
  "type": "Feature",
  "properties": {
    "iso:country": "GB",
    "wof:name": "PE6 9LH",
    "wof:placetype": "postalcode"
  },
  "geometry": {"coordinates":[-0.333428,52.701636],"type":"Point"}
}
