{
  "type": "Feature",
  "properties": {
    "iso:country":"GB",
    "wof:name":"RG17 9UE",
    "wof:placetype":"postalcode"
},
  "geometry": {"coordinates":[-1.44604657882153,51.39059753646856],"type":"Point"}
}