{
  "type": "Feature",
  "properties": {
    "date:inception_lower":"1995-07-01",
    "date:inception_upper":"1995-07-31",
    "iso:country":"GB",
    "wof:name":"RG17 9UE",
    "wof:placetype":"postalcode"
},
  "geometry": {"coordinates":[-1.446047,51.390598],"type":"Point"}
}