{
  "type": "Feature",
  "properties": {
    "iso:country":"GB",
    "wof:name":"DG10 9RZ",
    "wof:placetype":"postalcode"
},
  "geometry": {"coordinates":[-3.45737547090742,55.3388045784812],"type":"Point"}
}