{
  "type": "Feature",
  "properties": {
    "date:inception_lower":"2016-02-01",
    "date:inception_upper":"2016-02-29",
    "iso:country":"GB",
    "wof:name":"LD7 9AP",
    "wof:placetype":"postalcode"
},
  "geometry": {"coordinates":[-3.378457,52.241656],"type":"Point"}
}