{
  "type": "Feature",
  "properties": {
    "date:inception_lower": "1980-01-01",
    "date:inception_upper": "1980-01-01",
    "iso:country": "GB",
    "wof:name": "SY21 9JS",
    "wof:placetype": "postalcode"
  },
  "geometry": {"coordinates":[-3.102611,52.694956],"type":"Point"}
}
