{
  "type": "Feature",
  "properties": {
    "iso:country":"GB",
    "wof:name":"EH9 1BT",
    "wof:placetype":"postalcode"
},
  "geometry": {"coordinates":[-3.19564139639777,55.93676575422342],"type":"Point"}
}