{
  "type": "Feature",
  "properties": {
    "iso:country":"GB",
    "wof:name":"PA8 7BZ",
    "wof:placetype":"postalcode"
},
  "geometry": {"coordinates":[-4.43058558356838,55.894800841208],"type":"Point"}
}