{
  "type": "Feature",
  "properties": {
    "iso:country":"GB",
    "wof:name":"CW12 2BH",
    "wof:placetype":"postalcode"
},
  "geometry": {"coordinates":[-2.19502594952078,53.17286018653574],"type":"Point"}
}