{
  "type": "Feature",
  "properties": {
    "date:inception_lower": "1980-01-01",
    "date:inception_upper": "1980-01-01",
    "iso:country": "GB",
    "wof:name": "CW12 2BH",
    "wof:placetype": "postalcode"
  },
  "geometry": {"coordinates":[-2.195026,53.17286],"type":"Point"}
}
