{
  "type": "Feature",
  "properties": {
    "iso:country":"GB",
    "wof:name":"DT10 1PJ",
    "wof:placetype":"postalcode"
},
  "geometry": {"coordinates":[-2.31979036239024,50.96636314504918],"type":"Point"}
}