{
  "type": "Feature",
  "properties": {
    "iso:country": "GB",
    "wof:name": "CV33 9UU",
    "wof:placetype": "postalcode"
  },
  "geometry": {"coordinates":[-1.543684,52.26078],"type":"Point"}
}
