{
  "type": "Feature",
  "properties": {
    "iso:country": "GB",
    "wof:name": "NP22 4RQ",
    "wof:placetype": "postalcode"
  },
  "geometry": {"coordinates":[-3.247128,51.78435],"type":"Point"}
}
