{
  "type": "Feature",
  "properties": {
    "iso:country":"GB",
    "wof:name":"SE1 9RB",
    "wof:placetype":"postalcode"
},
  "geometry": {"coordinates":[-0.10720845161634,51.50764416045447],"type":"Point"}
}