{
  "type": "Feature",
  "properties": {
    "date:inception_lower": "2023-09-01",
    "date:inception_upper": "2023-09-01",
    "iso:country": "GB",
    "wof:name": "CB25 9RS",
    "wof:placetype": "postalcode"
  },
  "geometry": {"coordinates":[0.1785,52.286522],"type":"Point"}
}
