{
  "type": "Feature",
  "properties": {
    "date:inception_lower": "1994-12-01",
    "date:inception_upper": "1994-12-01",
    "iso:country": "GB",
    "wof:name": "SO41 3PP",
    "wof:placetype": "postalcode"
  },
  "geometry": {"coordinates":[-1.542648,50.753711],"type":"Point"}
}
