{
  "type": "Feature",
  "properties": {
    "iso:country":"GB",
    "wof:name":"PL14 6NA",
    "wof:placetype":"postalcode"
},
  "geometry": {"coordinates":[-4.55866843675621,50.4820221307834],"type":"Point"}
}