{
  "type": "Feature",
  "properties": {
    "date:inception_lower": "2016-08-01",
    "date:inception_upper": "2016-08-01",
    "iso:country": "GB",
    "wof:name": "B70 9BQ",
    "wof:placetype": "postalcode"
  },
  "geometry": {"coordinates":[-2.015455,52.521016],"type":"Point"}
}
