{
  "type": "Feature",
  "properties": {
    "date:inception_lower":"1980-01-01",
    "date:inception_upper":"1980-01-31",
    "iso:country":"GB",
    "wof:name":"SE15 4RF",
    "wof:placetype":"postalcode"
},
  "geometry": {"coordinates":[-0.072935,51.46884],"type":"Point"}
}