{
  "type": "Feature",
  "properties": {
    "iso:country":"GB",
    "wof:name":"NG23 5FL",
    "wof:placetype":"postalcode"
},
  "geometry": {"coordinates":[-0.73456772064905,53.03285946195543],"type":"Point"}
}