{
  "type": "Feature",
  "properties": {
    "iso:country":"GB",
    "wof:name":"SA3 4HZ",
    "wof:placetype":"postalcode"
},
  "geometry": {"coordinates":[-3.9869441095107,51.56933194507514],"type":"Point"}
}