{
  "type": "Feature",
  "properties": {
    "date:inception_lower":"1980-01-01",
    "date:inception_upper":"1980-01-31",
    "iso:country":"GB",
    "wof:name":"SA3 4HZ",
    "wof:placetype":"postalcode"
},
  "geometry": {"coordinates":[-3.986919,51.56931],"type":"Point"}
}