{
  "type": "Feature",
  "properties": {
    "iso:country": "GB",
    "wof:name": "TA10 9QX",
    "wof:placetype": "postalcode"
  },
  "geometry": {"coordinates":[-2.812383,51.03622],"type":"Point"}
}
