{
  "type": "Feature",
  "properties": {
    "iso:country":"GB",
    "wof:name":"TS5 7SF",
    "wof:placetype":"postalcode"
},
  "geometry": {"coordinates":[-1.25047875657813,54.54977939982808],"type":"Point"}
}