{
  "type": "Feature",
  "properties": {
    "iso:country": "GB",
    "wof:name": "S6 5JH",
    "wof:placetype": "postalcode"
  },
  "geometry": {"coordinates":[-1.522831,53.400651],"type":"Point"}
}
