{
  "type": "Feature",
  "properties": {
    "date:inception_lower": "1980-01-01",
    "date:inception_upper": "1980-01-01",
    "iso:country": "GB",
    "wof:name": "WF3 3BH",
    "wof:placetype": "postalcode"
  },
  "geometry": {"coordinates":[-1.506646,53.735754],"type":"Point"}
}
