{
  "type": "Feature",
  "properties": {
    "iso:country": "GB",
    "wof:name": "WF3 3BH",
    "wof:placetype": "postalcode"
  },
  "geometry": {"coordinates":[-1.506646,53.735754],"type":"Point"}
}
