{
  "type": "Feature",
  "properties": {
    "iso:country":"GB",
    "wof:name":"WF3 3BH",
    "wof:placetype":"postalcode"
},
  "geometry": {"coordinates":[-1.50664556675935,53.73575400741868],"type":"Point"}
}