{
  "type": "Feature",
  "properties": {
    "date:inception_lower": "2019-02-01",
    "date:inception_upper": "2019-02-01",
    "iso:country": "GB",
    "wof:name": "EH53 0FT",
    "wof:placetype": "postalcode"
  },
  "geometry": {"coordinates":[-3.491665,55.911912],"type":"Point"}
}
