{
  "type": "Feature",
  "properties": {
    "iso:country": "GB",
    "wof:name": "NE61 6BT",
    "wof:placetype": "postalcode"
  },
  "geometry": {"coordinates":[-1.717189,55.125523],"type":"Point"}
}
