{
  "type": "Feature",
  "properties": {
    "iso:country":"GB",
    "wof:name":"SA18 1AJ",
    "wof:placetype":"postalcode"
},
  "geometry": {"coordinates":[-3.8988122034321,51.80210094077755],"type":"Point"}
}