{
  "type": "Feature",
  "properties": {
    "date:inception_lower": "2007-08-01",
    "date:inception_upper": "2007-08-01",
    "iso:country": "GB",
    "wof:name": "SA18 1AJ",
    "wof:placetype": "postalcode"
  },
  "geometry": {"coordinates":[-3.898812,51.802101],"type":"Point"}
}
