{
  "type": "Feature",
  "properties": {
    "iso:country": "GB",
    "wof:name": "SG4 8RP",
    "wof:placetype": "postalcode"
  },
  "geometry": {"coordinates":[-0.292542,51.852072],"type":"Point"}
}
