{
  "type": "Feature",
  "properties": {
    "iso:country":"GB",
    "wof:name":"SG4 8RP",
    "wof:placetype":"postalcode"
},
  "geometry": {"coordinates":[-0.29254233087743,51.85207168943995],"type":"Point"}
}