{
  "type": "Feature",
  "properties": {
    "iso:country": "GB",
    "wof:name": "EC3N 2PX",
    "wof:placetype": "postalcode"
  },
  "geometry": {"coordinates":[-0.076294,51.511844],"type":"Point"}
}
