{
  "type": "Feature",
  "properties": {
    "iso:country":"GB",
    "wof:name":"EC3N 2PX",
    "wof:placetype":"postalcode"
},
  "geometry": {"coordinates":[-0.07629424044315,51.51184428279144],"type":"Point"}
}