{
  "type": "Feature",
  "properties": {
    "date:inception_lower": "1997-12-01",
    "date:inception_upper": "1997-12-01",
    "iso:country": "GB",
    "wof:name": "BS32 4BZ",
    "wof:placetype": "postalcode"
  },
  "geometry": {"coordinates":[-2.590453,51.542762],"type":"Point"}
}
