{
  "type": "Feature",
  "properties": {
    "date:inception_lower":"1980-01-01",
    "date:inception_upper":"1980-01-31",
    "iso:country":"GB",
    "wof:name":"CW10 0DH",
    "wof:placetype":"postalcode"
},
  "geometry": {"coordinates":[-2.438649,53.182594],"type":"Point"}
}