{
  "type": "Feature",
  "properties": {
    "iso:country":"GB",
    "wof:name":"CW10 0DH",
    "wof:placetype":"postalcode"
},
  "geometry": {"coordinates":[-2.438648594092,53.18259396231937],"type":"Point"}
}