{
  "type": "Feature",
  "properties": {
    "iso:country": "GB",
    "wof:name": "CW10 0DH",
    "wof:placetype": "postalcode"
  },
  "geometry": {"coordinates":[-2.438649,53.182594],"type":"Point"}
}
