{
  "type": "Feature",
  "properties": {
    "iso:country":"GB",
    "wof:name":"S42 7DB",
    "wof:placetype":"postalcode"
},
  "geometry": {"coordinates":[-1.54578390973303,53.22789575232783],"type":"Point"}
}