{
  "type": "Feature",
  "properties": {
    "date:inception_lower": "2010-05-01",
    "date:inception_upper": "2010-05-01",
    "iso:country": "GB",
    "wof:name": "BN8 5FG",
    "wof:placetype": "postalcode"
  },
  "geometry": {"coordinates":[0.054045,50.896255],"type":"Point"}
}
