{
  "type": "Feature",
  "properties": {
    "date:inception_lower": "2022-05-01",
    "date:inception_upper": "2022-05-01",
    "iso:country": "GB",
    "wof:name": "HX7 8FF",
    "wof:placetype": "postalcode"
  },
  "geometry": {"coordinates":[-2.003695,53.751847],"type":"Point"}
}
