{
  "type": "Feature",
  "properties": {
    "iso:country":"GB",
    "wof:name":"FK7 9EH",
    "wof:placetype":"postalcode"
},
  "geometry": {"coordinates":[-3.94479039260292,56.10071872397509],"type":"Point"}
}