{
  "type": "Feature",
  "properties": {
    "iso:country":"GB",
    "wof:name":"TS13 5HG",
    "wof:placetype":"postalcode"
},
  "geometry": {"coordinates":[-0.77318577550569,54.53639998905964],"type":"Point"}
}