{
  "type": "Feature",
  "properties": {
    "iso:country":"GB",
    "wof:name":"WF15 7QR",
    "wof:placetype":"postalcode"
},
  "geometry": {"coordinates":[-1.70051362072014,53.69819534566718],"type":"Point"}
}