{
  "type": "Feature",
  "properties": {
    "iso:country": "GB",
    "wof:name": "WF15 7QR",
    "wof:placetype": "postalcode"
  },
  "geometry": {"coordinates":[-1.700514,53.698195],"type":"Point"}
}
