{
  "type": "Feature",
  "properties": {
    "date:inception_lower": "1996-06-01",
    "date:inception_upper": "1996-06-01",
    "iso:country": "GB",
    "wof:name": "AB15 7PS",
    "wof:placetype": "postalcode"
  },
  "geometry": {"coordinates":[-2.143524,57.124229],"type":"Point"}
}
