{
  "type": "Feature",
  "properties": {
    "iso:country":"GB",
    "wof:name":"PE28 2LG",
    "wof:placetype":"postalcode"
},
  "geometry": {"coordinates":[-0.20157964308531,52.38936663550317],"type":"Point"}
}