{
  "type": "Feature",
  "properties": {
    "iso:country":"GB",
    "wof:name":"BS5 9RX",
    "wof:placetype":"postalcode"
},
  "geometry": {"coordinates":[-2.55891163124308,51.45520365410321],"type":"Point"}
}