{
  "type": "Feature",
  "properties": {
    "iso:country":"GB",
    "wof:name":"WF3 1DS",
    "wof:placetype":"postalcode"
},
  "geometry": {"coordinates":[-1.58078948433659,53.7160465077009],"type":"Point"}
}