{
  "type": "Feature",
  "properties": {
    "iso:country": "GB",
    "wof:name": "PA3 2DD",
    "wof:placetype": "postalcode"
  },
  "geometry": {"coordinates":[-4.425182,55.849986],"type":"Point"}
}
