{
  "type": "Feature",
  "properties": {
    "iso:country":"GB",
    "wof:name":"PA3 2DD",
    "wof:placetype":"postalcode"
},
  "geometry": {"coordinates":[-4.42518189336921,55.84998619716331],"type":"Point"}
}