{
  "type": "Feature",
  "properties": {
    "iso:country":"GB",
    "wof:name":"KA7 2LY",
    "wof:placetype":"postalcode"
},
  "geometry": {"coordinates":[-4.61941133954826,55.44701611468581],"type":"Point"}
}