{
  "type": "Feature",
  "properties": {
    "iso:country":"GB",
    "wof:name":"DL5 6RB",
    "wof:placetype":"postalcode"
},
  "geometry": {"coordinates":[-1.61560904246345,54.59425805362634],"type":"Point"}
}