{
  "type": "Feature",
  "properties": {
    "date:inception_lower": "1980-01-01",
    "date:inception_upper": "1980-01-01",
    "iso:country": "GB",
    "wof:name": "DL5 6RB",
    "wof:placetype": "postalcode"
  },
  "geometry": {"coordinates":[-1.615609,54.594258],"type":"Point"}
}
