{
  "type": "Feature",
  "properties": {
    "iso:country":"GB",
    "wof:name":"MK16 8BY",
    "wof:placetype":"postalcode"
},
  "geometry": {"coordinates":[-0.74118687324137,52.08455918943218],"type":"Point"}
}