{
  "type": "Feature",
  "properties": {
    "iso:country": "GB",
    "wof:name": "MK16 8BY",
    "wof:placetype": "postalcode"
  },
  "geometry": {"coordinates":[-0.741187,52.084559],"type":"Point"}
}
