{
  "type": "Feature",
  "properties": {
    "date:inception_lower": "2002-11-01",
    "date:inception_upper": "2002-11-01",
    "iso:country": "GB",
    "wof:name": "DY13 9HR",
    "wof:placetype": "postalcode"
  },
  "geometry": {"coordinates":[-2.276989,52.339104],"type":"Point"}
}
