{
  "type": "Feature",
  "properties": {
    "iso:country":"GB",
    "wof:name":"DY13 9HR",
    "wof:placetype":"postalcode"
},
  "geometry": {"coordinates":[-2.27698903008171,52.33910427306913],"type":"Point"}
}