{
  "type": "Feature",
  "properties": {
    "iso:country":"GB",
    "wof:name":"GL11 4NQ",
    "wof:placetype":"postalcode"
},
  "geometry": {"coordinates":[-2.35239591256449,51.68049485083971],"type":"Point"}
}