{
  "type": "Feature",
  "properties": {
    "iso:country":"GB",
    "wof:name":"NE5 5EA",
    "wof:placetype":"postalcode"
},
  "geometry": {"coordinates":[-1.70413141218783,54.98910398434413],"type":"Point"}
}