{
  "type": "Feature",
  "properties": {
    "date:inception_lower":"1984-02-01",
    "date:inception_upper":"1984-02-29",
    "iso:country":"GB",
    "wof:name":"NE38 0NH",
    "wof:placetype":"postalcode"
},
  "geometry": {"coordinates":[-1.550497,54.896218],"type":"Point"}
}