{
  "type": "Feature",
  "properties": {
    "date:inception_lower": "1980-01-01",
    "date:inception_upper": "1980-01-01",
    "iso:country": "GB",
    "wof:name": "BH12 4DZ",
    "wof:placetype": "postalcode"
  },
  "geometry": {"coordinates":[-1.924743,50.736966],"type":"Point"}
}
