{
  "type": "Feature",
  "properties": {
    "iso:country":"GB",
    "wof:name":"ML5 5RB",
    "wof:placetype":"postalcode"
},
  "geometry": {"coordinates":[-4.05175125523871,55.85384354285062],"type":"Point"}
}