{
  "type": "Feature",
  "properties": {
    "iso:country": "GB",
    "wof:name": "EX1 2BE",
    "wof:placetype": "postalcode"
  },
  "geometry": {"coordinates":[-3.51966,50.727344],"type":"Point"}
}
