{
  "type": "Feature",
  "properties": {
    "iso:country":"GB",
    "wof:name":"CF83 1RY",
    "wof:placetype":"postalcode"
},
  "geometry": {"coordinates":[-3.23452490913627,51.56508645552137],"type":"Point"}
}