{
  "type": "Feature",
  "properties": {
    "iso:country":"GB",
    "wof:name":"WA8 0DF",
    "wof:placetype":"postalcode"
},
  "geometry": {"coordinates":[-2.73369415719421,53.35180620361641],"type":"Point"}
}