{
  "type": "Feature",
  "properties": {
    "iso:country": "GB",
    "wof:name": "W6 8BG",
    "wof:placetype": "postalcode"
  },
  "geometry": {"coordinates":[-0.222596,51.490476],"type":"Point"}
}
