{
  "type": "Feature",
  "properties": {
    "iso:country":"GB",
    "wof:name":"W6 8BG",
    "wof:placetype":"postalcode"
},
  "geometry": {"coordinates":[-0.22259627981895,51.49047553670753],"type":"Point"}
}