{
  "type": "Feature",
  "properties": {
    "iso:country":"GB",
    "wof:name":"KT19 8HR",
    "wof:placetype":"postalcode"
},
  "geometry": {"coordinates":[-0.2726799172279,51.33369326517547],"type":"Point"}
}