{
  "type": "Feature",
  "properties": {
    "iso:country":"GB",
    "wof:name":"CT6 6UG",
    "wof:placetype":"postalcode"
},
  "geometry": {"coordinates":[1.14638000049988,51.36380666013521],"type":"Point"}
}