{
  "type": "Feature",
  "properties": {
    "date:inception_lower": "1980-01-01",
    "date:inception_upper": "1980-01-01",
    "iso:country": "GB",
    "wof:name": "OX17 2HP",
    "wof:placetype": "postalcode"
  },
  "geometry": {"coordinates":[-1.220492,52.104481],"type":"Point"}
}
