{
  "type": "Feature",
  "properties": {
    "iso:country":"GB",
    "wof:name":"YO30 1YN",
    "wof:placetype":"postalcode"
},
  "geometry": {"coordinates":[-1.16068923165422,54.00236099033775],"type":"Point"}
}