{
  "type": "Feature",
  "properties": {
    "date:inception_lower": "1990-08-01",
    "date:inception_upper": "1990-08-01",
    "iso:country": "GB",
    "wof:name": "AB51 7JX",
    "wof:placetype": "postalcode"
  },
  "geometry": {"coordinates":[-2.480846,57.206261],"type":"Point"}
}
