{
  "type": "Feature",
  "properties": {
    "iso:country": "GB",
    "wof:name": "AB51 7JX",
    "wof:placetype": "postalcode"
  },
  "geometry": {"coordinates":[-2.480846,57.206261],"type":"Point"}
}
