{
  "type": "Feature",
  "properties": {
    "date:inception_lower": "2019-09-01",
    "date:inception_upper": "2019-09-01",
    "iso:country": "GB",
    "wof:name": "G69 8DZ",
    "wof:placetype": "postalcode"
  },
  "geometry": {"coordinates":[-4.075684,55.895065],"type":"Point"}
}
