{
  "type": "Feature",
  "properties": {
    "iso:country":"GB",
    "wof:name":"E17 9DS",
    "wof:placetype":"postalcode"
},
  "geometry": {"coordinates":[-0.00238059260501,51.58056226473743],"type":"Point"}
}