{
  "type": "Feature",
  "properties": {
    "iso:country":"GB",
    "wof:name":"TA9 3TE",
    "wof:placetype":"postalcode"
},
  "geometry": {"coordinates":[-2.97652085180338,51.21884707487817],"type":"Point"}
}