{
  "type": "Feature",
  "properties": {
    "date:inception_lower": "2006-09-01",
    "date:inception_upper": "2006-09-01",
    "iso:country": "GB",
    "wof:name": "TA9 3TE",
    "wof:placetype": "postalcode"
  },
  "geometry": {"coordinates":[-2.976715,51.218778],"type":"Point"}
}
