{
  "type": "Feature",
  "properties": {
    "iso:country":"GB",
    "wof:name":"B10 9JS",
    "wof:placetype":"postalcode"
},
  "geometry": {"coordinates":[-1.83312360768613,52.47055829537622],"type":"Point"}
}