{
  "type": "Feature",
  "properties": {
    "iso:country":"GB",
    "wof:name":"YO19 4RH",
    "wof:placetype":"postalcode"
},
  "geometry": {"coordinates":[-1.05884062786036,53.91823345118117],"type":"Point"}
}