{
  "type": "Feature",
  "properties": {
    "iso:country":"GB",
    "wof:name":"NW2 1BW",
    "wof:placetype":"postalcode"
},
  "geometry": {"coordinates":[-0.21626205736442,51.56415302786632],"type":"Point"}
}