{
  "type": "Feature",
  "properties": {
    "date:inception_lower":"1994-12-01",
    "date:inception_upper":"1994-12-31",
    "iso:country":"GB",
    "wof:name":"NW2 1BW",
    "wof:placetype":"postalcode"
},
  "geometry": {"coordinates":[-0.216262,51.564153],"type":"Point"}
}