{
  "type": "Feature",
  "properties": {
    "iso:country":"GB",
    "wof:name":"M8 4GH",
    "wof:placetype":"postalcode"
},
  "geometry": {"coordinates":[-2.23750448438112,53.51961045071555],"type":"Point"}
}