{
  "type": "Feature",
  "properties": {
    "iso:country":"GB",
    "wof:name":"TQ9 7DL",
    "wof:placetype":"postalcode"
},
  "geometry": {"coordinates":[-3.6761499382849,50.37058722355796],"type":"Point"}
}