{
  "type": "Feature",
  "properties": {
    "iso:country":"GB",
    "wof:name":"SO15 3JL",
    "wof:placetype":"postalcode"
},
  "geometry": {"coordinates":[-1.43234491133137,50.91885186706661],"type":"Point"}
}