{
  "type": "Feature",
  "properties": {
    "date:inception_lower": "1980-01-01",
    "date:inception_upper": "1980-01-01",
    "iso:country": "GB",
    "wof:name": "NW6 6NU",
    "wof:placetype": "postalcode"
  },
  "geometry": {"coordinates":[-0.206394,51.536731],"type":"Point"}
}
