{
  "type": "Feature",
  "properties": {
    "iso:country":"GB",
    "wof:name":"NW6 6NU",
    "wof:placetype":"postalcode"
},
  "geometry": {"coordinates":[-0.20626715481555,51.53655591993223],"type":"Point"}
}