{
  "type": "Feature",
  "properties": {
    "iso:country":"GB",
    "wof:name":"SK3 8DY",
    "wof:placetype":"postalcode"
},
  "geometry": {"coordinates":[-2.16140822926606,53.39881557036737],"type":"Point"}
}