{
  "type": "Feature",
  "properties": {
    "iso:country":"GB",
    "wof:name":"SP4 9HG",
    "wof:placetype":"postalcode"
},
  "geometry": {"coordinates":[-1.75268786049045,51.19219791375539],"type":"Point"}
}