{
  "type": "Feature",
  "properties": {
    "date:inception_lower":"2012-10-01",
    "date:inception_upper":"2012-10-31",
    "iso:country":"GB",
    "wof:name":"SE25 4FH",
    "wof:placetype":"postalcode"
},
  "geometry": {"coordinates":[-0.069151,51.403608],"type":"Point"}
}