{
  "type": "Feature",
  "properties": {
    "date:inception_lower": "1980-01-01",
    "date:inception_upper": "1980-01-01",
    "iso:country": "GB",
    "wof:name": "DA2 7NB",
    "wof:placetype": "postalcode"
  },
  "geometry": {"coordinates":[0.171706,51.425732],"type":"Point"}
}
