{
  "type": "Feature",
  "properties": {
    "iso:country":"GB",
    "wof:name":"DA2 7NB",
    "wof:placetype":"postalcode"
},
  "geometry": {"coordinates":[0.17170645731292,51.42573205159112],"type":"Point"}
}