{
  "type": "Feature",
  "properties": {
    "date:inception_lower": "2008-03-01",
    "date:inception_upper": "2008-03-01",
    "iso:country": "GB",
    "wof:name": "DH6 4BP",
    "wof:placetype": "postalcode"
  },
  "geometry": {"coordinates":[-1.500945,54.714281],"type":"Point"}
}
