{
  "type": "Feature",
  "properties": {
    "iso:country":"GB",
    "wof:name":"DH6 4BP",
    "wof:placetype":"postalcode"
},
  "geometry": {"coordinates":[-1.50094546518465,54.71428075865712],"type":"Point"}
}