{
  "type": "Feature",
  "properties": {
    "iso:country":"GB",
    "wof:name":"BD18 3BS",
    "wof:placetype":"postalcode"
},
  "geometry": {"coordinates":[-1.77873214682839,53.83010267284338],"type":"Point"}
}