{
  "type": "Feature",
  "properties": {
    "iso:country":"GB",
    "wof:name":"AB15 9BG",
    "wof:placetype":"postalcode"
},
  "geometry": {"coordinates":[-2.20962445083048,57.11894354133899],"type":"Point"}
}