{
  "type": "Feature",
  "properties": {
    "date:inception_lower": "2003-02-01",
    "date:inception_upper": "2003-02-01",
    "iso:country": "GB",
    "wof:name": "ZE2 9TZ",
    "wof:placetype": "postalcode"
  },
  "geometry": {"coordinates":[-1.37155,60.390812],"type":"Point"}
}
