{
  "type": "Feature",
  "properties": {
    "iso:country":"GB",
    "wof:name":"ZE2 9TZ",
    "wof:placetype":"postalcode"
},
  "geometry": {"coordinates":[-1.37213794275787,60.3906592903705],"type":"Point"}
}