{
  "type": "Feature",
  "properties": {
    "iso:country":"GB",
    "wof:name":"CV21 4HJ",
    "wof:placetype":"postalcode"
},
  "geometry": {"coordinates":[-1.22801753229299,52.36081475419991],"type":"Point"}
}