{
  "type": "Feature",
  "properties": {
    "date:inception_lower": "2017-06-01",
    "date:inception_upper": "2017-06-01",
    "iso:country": "GB",
    "wof:name": "LU7 9ST",
    "wof:placetype": "postalcode"
  },
  "geometry": {"coordinates":[-0.572272,51.91152],"type":"Point"}
}
