{
  "type": "Feature",
  "properties": {
    "iso:country":"GB",
    "wof:name":"WD17 3BJ",
    "wof:placetype":"postalcode"
},
  "geometry": {"coordinates":[-0.42152775496851,51.6661321882681],"type":"Point"}
}