{
  "type": "Feature",
  "properties": {
    "date:inception_lower":"1987-04-01",
    "date:inception_upper":"1987-04-30",
    "iso:country":"GB",
    "wof:name":"SE15 1TL",
    "wof:placetype":"postalcode"
},
  "geometry": {"coordinates":[-0.055738,51.484601],"type":"Point"}
}