{
  "type": "Feature",
  "properties": {
    "iso:country":"GB",
    "wof:name":"SE15 1TL",
    "wof:placetype":"postalcode"
},
  "geometry": {"coordinates":[-0.05576435447877,51.48459981044598],"type":"Point"}
}