{
  "type": "Feature",
  "properties": {
    "date:inception_lower": "1980-01-01",
    "date:inception_upper": "1980-01-01",
    "iso:country": "GB",
    "wof:name": "BD23 3AY",
    "wof:placetype": "postalcode"
  },
  "geometry": {"coordinates":[-2.113086,53.944062],"type":"Point"}
}
