{
  "type": "Feature",
  "properties": {
    "iso:country":"GB",
    "wof:name":"BD23 3AY",
    "wof:placetype":"postalcode"
},
  "geometry": {"coordinates":[-2.11338748092116,53.94435284401604],"type":"Point"}
}