{
  "type": "Feature",
  "properties": {
    "iso:country": "GB",
    "wof:name": "BD23 3AY",
    "wof:placetype": "postalcode"
  },
  "geometry": {"coordinates":[-2.113391,53.944367],"type":"Point"}
}
