{
  "type": "Feature",
  "properties": {
    "iso:country":"GB",
    "wof:name":"BN26 6SG",
    "wof:placetype":"postalcode"
},
  "geometry": {"coordinates":[0.19552256783269,50.85072551846613],"type":"Point"}
}