{
  "type": "Feature",
  "properties": {
    "date:inception_lower": "1980-01-01",
    "date:inception_upper": "1980-01-01",
    "iso:country": "GB",
    "wof:name": "HG3 3EB",
    "wof:placetype": "postalcode"
  },
  "geometry": {"coordinates":[-1.581736,54.049348],"type":"Point"}
}
