{
  "type": "Feature",
  "properties": {
    "date:inception_lower":"1983-07-01",
    "date:inception_upper":"1983-07-31",
    "iso:country":"GB",
    "wof:name":"BD15 7SG",
    "wof:placetype":"postalcode"
},
  "geometry": {"coordinates":[-1.817852,53.799322],"type":"Point"}
}