{
  "type": "Feature",
  "properties": {
    "iso:country":"GB",
    "wof:name":"BD15 7SG",
    "wof:placetype":"postalcode"
},
  "geometry": {"coordinates":[-1.81785176668205,53.79932173400576],"type":"Point"}
}