{
  "type": "Feature",
  "properties": {
    "iso:country":"GB",
    "wof:name":"BA5 3PA",
    "wof:placetype":"postalcode"
},
  "geometry": {"coordinates":[-2.61676927621931,51.19860990646652],"type":"Point"}
}