{
  "type": "Feature",
  "properties": {
    "iso:country": "GB",
    "wof:name": "BA5 3PA",
    "wof:placetype": "postalcode"
  },
  "geometry": {"coordinates":[-2.616769,51.19861],"type":"Point"}
}
