{
  "type": "Feature",
  "properties": {
    "iso:country":"GB",
    "wof:name":"WN2 5QA",
    "wof:placetype":"postalcode"
},
  "geometry": {"coordinates":[-2.59104367355683,53.51508592750636],"type":"Point"}
}