{
  "type": "Feature",
  "properties": {
    "iso:country":"GB",
    "wof:name":"CT14 9JS",
    "wof:placetype":"postalcode"
},
  "geometry": {"coordinates":[1.38533427825231,51.20737822457195],"type":"Point"}
}