{
  "type": "Feature",
  "properties": {
    "iso:country": "GB",
    "wof:name": "WS5 3QL",
    "wof:placetype": "postalcode"
  },
  "geometry": {"coordinates":[-1.949196,52.57555],"type":"Point"}
}
