{
  "type": "Feature",
  "properties": {
    "iso:country":"GB",
    "wof:name":"WS5 3QL",
    "wof:placetype":"postalcode"
},
  "geometry": {"coordinates":[-1.94919575472963,52.57554990071623],"type":"Point"}
}