{
  "type": "Feature",
  "properties": {
    "iso:country": "GB",
    "wof:name": "HP12 9FS",
    "wof:placetype": "postalcode"
  },
  "geometry": {"coordinates":[-0.770369,51.622164],"type":"Point"}
}
