{
  "type": "Feature",
  "properties": {
    "iso:country": "GB",
    "wof:name": "M25 0AW",
    "wof:placetype": "postalcode"
  },
  "geometry": {"coordinates":[-2.269814,53.524872],"type":"Point"}
}
