{
  "type": "Feature",
  "properties": {
    "iso:country":"GB",
    "wof:name":"OL8 2SH",
    "wof:placetype":"postalcode"
},
  "geometry": {"coordinates":[-2.10580384998973,53.51810999687254],"type":"Point"}
}