{
  "type": "Feature",
  "properties": {
    "iso:country":"GB",
    "wof:name":"SL7 2NU",
    "wof:placetype":"postalcode"
},
  "geometry": {"coordinates":[-0.78146675627884,51.57366649610088],"type":"Point"}
}