{
  "type": "Feature",
  "properties": {
    "iso:country":"GB",
    "wof:name":"OL13 9LJ",
    "wof:placetype":"postalcode"
},
  "geometry": {"coordinates":[-2.19037728810276,53.70179687540045],"type":"Point"}
}