{
  "type": "Feature",
  "properties": {
    "date:inception_lower": "2001-12-01",
    "date:inception_upper": "2001-12-01",
    "iso:country": "GB",
    "wof:name": "RG7 5JG",
    "wof:placetype": "postalcode"
  },
  "geometry": {"coordinates":[-1.087598,51.433729],"type":"Point"}
}
