{
  "type": "Feature",
  "properties": {
    "iso:country":"GB",
    "wof:name":"BN18 0AD",
    "wof:placetype":"postalcode"
},
  "geometry": {"coordinates":[-0.58046629191269,50.85663004992346],"type":"Point"}
}