{
  "type": "Feature",
  "properties": {
    "iso:country":"GB",
    "wof:name":"CT2 9AT",
    "wof:placetype":"postalcode"
},
  "geometry": {"coordinates":[1.02869131146324,51.28561843463562],"type":"Point"}
}