{
  "type": "Feature",
  "properties": {
    "iso:country":"GB",
    "wof:name":"NP19 0GT",
    "wof:placetype":"postalcode"
},
  "geometry": {"coordinates":[-2.96917747748405,51.58067935049753],"type":"Point"}
}