{
  "type": "Feature",
  "properties": {
    "iso:country":"GB",
    "wof:name":"L33 9UN",
    "wof:placetype":"postalcode"
},
  "geometry": {"coordinates":[-2.87411137410468,53.49166103974471],"type":"Point"}
}