{
  "type": "Feature",
  "properties": {
    "iso:country":"GB",
    "wof:name":"IP33 3JH",
    "wof:placetype":"postalcode"
},
  "geometry": {"coordinates":[0.68176619655082,52.25218958362309],"type":"Point"}
}