{
  "type": "Feature",
  "properties": {
    "iso:country":"GB",
    "wof:name":"HA4 6EY",
    "wof:placetype":"postalcode"
},
  "geometry": {"coordinates":[-0.43005692348281,51.57117355653655],"type":"Point"}
}