{
  "type": "Feature",
  "properties": {
    "date:inception_lower":"1980-01-01",
    "date:inception_upper":"1980-01-31",
    "iso:country":"GB",
    "wof:name":"HA4 6EY",
    "wof:placetype":"postalcode"
},
  "geometry": {"coordinates":[-0.430057,51.571174],"type":"Point"}
}