{
  "type": "Feature",
  "properties": {
    "iso:country": "GB",
    "wof:name": "HA4 6EY",
    "wof:placetype": "postalcode"
  },
  "geometry": {"coordinates":[-0.430057,51.571174],"type":"Point"}
}
