{
  "type": "Feature",
  "properties": {
    "iso:country":"GB",
    "wof:name":"EH14 7JG",
    "wof:placetype":"postalcode"
},
  "geometry": {"coordinates":[-3.38680111739838,55.87756726403128],"type":"Point"}
}