{
  "type": "Feature",
  "properties": {
    "date:inception_lower": "1980-01-01",
    "date:inception_upper": "1980-01-01",
    "iso:country": "GB",
    "wof:name": "EH14 7JG",
    "wof:placetype": "postalcode"
  },
  "geometry": {"coordinates":[-3.386516,55.877728],"type":"Point"}
}
