{
  "type": "Feature",
  "properties": {
    "iso:country": "GB",
    "wof:name": "NG16 3RZ",
    "wof:placetype": "postalcode"
  },
  "geometry": {"coordinates":[-1.322951,53.020295],"type":"Point"}
}
