{
  "type": "Feature",
  "properties": {
    "date:inception_lower": "1982-03-01",
    "date:inception_upper": "1982-03-01",
    "iso:country": "GB",
    "wof:name": "NG16 3RZ",
    "wof:placetype": "postalcode"
  },
  "geometry": {"coordinates":[-1.322386,53.02005],"type":"Point"}
}
