{
  "type": "Feature",
  "properties": {
    "iso:country":"GB",
    "wof:name":"S44 5HE",
    "wof:placetype":"postalcode"
},
  "geometry": {"coordinates":[-1.34047919464529,53.24704536380474],"type":"Point"}
}