{
  "type": "Feature",
  "properties": {
    "date:inception_lower": "1980-01-01",
    "date:inception_upper": "1980-01-01",
    "iso:country": "GB",
    "wof:name": "TA4 2SH",
    "wof:placetype": "postalcode"
  },
  "geometry": {"coordinates":[-3.34491,51.091829],"type":"Point"}
}
