{
  "type": "Feature",
  "properties": {
    "iso:country":"GB",
    "wof:name":"TA4 2SH",
    "wof:placetype":"postalcode"
},
  "geometry": {"coordinates":[-3.34495618373674,51.09187714296782],"type":"Point"}
}