{
  "type": "Feature",
  "properties": {
    "iso:country":"GB",
    "wof:name":"B44 0SD",
    "wof:placetype":"postalcode"
},
  "geometry": {"coordinates":[-1.86824744087516,52.54967786414085],"type":"Point"}
}