{
  "type": "Feature",
  "properties": {
    "iso:country": "GB",
    "wof:name": "IP8 3NJ",
    "wof:placetype": "postalcode"
  },
  "geometry": {"coordinates":[1.051599,52.05053],"type":"Point"}
}
