{
  "type": "Feature",
  "properties": {
    "iso:country":"GB",
    "wof:name":"IP8 3NJ",
    "wof:placetype":"postalcode"
},
  "geometry": {"coordinates":[1.05137534227907,52.05044854353249],"type":"Point"}
}