{
  "type": "Feature",
  "properties": {
    "iso:country": "GB",
    "wof:name": "DY11 7SG",
    "wof:placetype": "postalcode"
  },
  "geometry": {"coordinates":[-2.228384,52.348909],"type":"Point"}
}
