{
  "type": "Feature",
  "properties": {
    "iso:country":"GB",
    "wof:name":"BN8 4JH",
    "wof:placetype":"postalcode"
},
  "geometry": {"coordinates":[-0.00270150297142,50.98150896664566],"type":"Point"}
}