{
  "type": "Feature",
  "properties": {
    "date:inception_lower":"2003-01-01",
    "date:inception_upper":"2003-01-31",
    "iso:country":"GB",
    "wof:name":"DE22 4FD",
    "wof:placetype":"postalcode"
},
  "geometry": {"coordinates":[-1.523292,52.924353],"type":"Point"}
}