{
  "type": "Feature",
  "properties": {
    "iso:country": "GB",
    "wof:name": "SK6 7LG",
    "wof:placetype": "postalcode"
  },
  "geometry": {"coordinates":[-2.060897,53.386352],"type":"Point"}
}
