{
  "type": "Feature",
  "properties": {
    "iso:country":"GB",
    "wof:name":"SK6 7LG",
    "wof:placetype":"postalcode"
},
  "geometry": {"coordinates":[-2.06089747414678,53.38635231817639],"type":"Point"}
}