{
  "type": "Feature",
  "properties": {
    "iso:country":"GB",
    "wof:name":"PO22 8FG",
    "wof:placetype":"postalcode"
},
  "geometry": {"coordinates":[-0.64474623726934,50.7991284370321],"type":"Point"}
}