{
  "type": "Feature",
  "properties": {
    "date:inception_lower": "1980-01-01",
    "date:inception_upper": "1980-01-01",
    "iso:country": "GB",
    "wof:name": "TQ11 0LU",
    "wof:placetype": "postalcode"
  },
  "geometry": {"coordinates":[-3.790259,50.468521],"type":"Point"}
}
