{
  "type": "Feature",
  "properties": {
    "iso:country":"GB",
    "wof:name":"TQ11 0LU",
    "wof:placetype":"postalcode"
},
  "geometry": {"coordinates":[-3.79025862894583,50.46852124268999],"type":"Point"}
}