{
  "type": "Feature",
  "properties": {
    "iso:country":"GB",
    "wof:name":"TA24 6TX",
    "wof:placetype":"postalcode"
},
  "geometry": {"coordinates":[-3.48063523052938,51.17738497196628],"type":"Point"}
}