{
  "type": "Feature",
  "properties": {
    "date:inception_lower":"2005-02-01",
    "date:inception_upper":"2005-02-28",
    "iso:country":"GB",
    "wof:name":"KA24 4JS",
    "wof:placetype":"postalcode"
},
  "geometry": {"coordinates":[-4.731705,55.704539],"type":"Point"}
}