{
  "type": "Feature",
  "properties": {
    "iso:country":"GB",
    "wof:name":"KA24 4JS",
    "wof:placetype":"postalcode"
},
  "geometry": {"coordinates":[-4.73170534102191,55.70453875997514],"type":"Point"}
}