{
  "type": "Feature",
  "properties": {
    "iso:country": "GB",
    "wof:name": "PE23 5QN",
    "wof:placetype": "postalcode"
  },
  "geometry": {"coordinates":[0.176308,53.147592],"type":"Point"}
}
