{
  "type": "Feature",
  "properties": {
    "date:inception_lower":"1980-01-01",
    "date:inception_upper":"1980-01-31",
    "iso:country":"GB",
    "wof:name":"KA7 4HT",
    "wof:placetype":"postalcode"
},
  "geometry": {"coordinates":[-4.662391,55.430996],"type":"Point"}
}