{
  "type": "Feature",
  "properties": {
    "iso:country":"GB",
    "wof:name":"KA7 4HT",
    "wof:placetype":"postalcode"
},
  "geometry": {"coordinates":[-4.66239093887116,55.43099550499647],"type":"Point"}
}