{
  "type": "Feature",
  "properties": {
    "iso:country":"GB",
    "wof:name":"S20 7LT",
    "wof:placetype":"postalcode"
},
  "geometry": {"coordinates":[-1.34648946979553,53.3355021386105],"type":"Point"}
}