{
  "type": "Feature",
  "properties": {
    "iso:country": "GB",
    "wof:name": "S20 7LT",
    "wof:placetype": "postalcode"
  },
  "geometry": {"coordinates":[-1.346489,53.335502],"type":"Point"}
}
