{
  "type": "Feature",
  "properties": {
    "date:inception_lower": "2017-04-01",
    "date:inception_upper": "2017-04-01",
    "iso:country": "GB",
    "wof:name": "CV10 9AN",
    "wof:placetype": "postalcode"
  },
  "geometry": {"coordinates":[-1.528218,52.534894],"type":"Point"}
}
