{
  "type": "Feature",
  "properties": {
    "iso:country":"GB",
    "wof:name":"TF13 6PA",
    "wof:placetype":"postalcode"
},
  "geometry": {"coordinates":[-2.52110241941167,52.61561361258181],"type":"Point"}
}