{
  "type": "Feature",
  "properties": {
    "iso:country":"GB",
    "wof:name":"PA3 2SR",
    "wof:placetype":"postalcode"
},
  "geometry": {"coordinates":[-4.43208982842106,55.86465282191283],"type":"Point"}
}