{
  "type": "Feature",
  "properties": {
    "iso:country": "GB",
    "wof:name": "YO26 8BD",
    "wof:placetype": "postalcode"
  },
  "geometry": {"coordinates":[-1.295682,53.993988],"type":"Point"}
}
