{
  "type": "Feature",
  "properties": {
    "iso:country": "GB",
    "wof:name": "TR18 5LT",
    "wof:placetype": "postalcode"
  },
  "geometry": {"coordinates":[-5.545253,50.10062],"type":"Point"}
}
