{
  "type": "Feature",
  "properties": {
    "date:inception_lower":"1995-12-01",
    "date:inception_upper":"1995-12-31",
    "iso:country":"GB",
    "wof:name":"TR18 5LT",
    "wof:placetype":"postalcode"
},
  "geometry": {"coordinates":[-5.545253,50.10062],"type":"Point"}
}