{
  "type": "Feature",
  "properties": {
    "iso:country": "GB",
    "wof:name": "SK6 3EU",
    "wof:placetype": "postalcode"
  },
  "geometry": {"coordinates":[-2.105982,53.408262],"type":"Point"}
}
