{
  "type": "Feature",
  "properties": {
    "iso:country":"GB",
    "wof:name":"SK6 3EU",
    "wof:placetype":"postalcode"
},
  "geometry": {"coordinates":[-2.10598169127798,53.40826180041343],"type":"Point"}
}