{
  "type": "Feature",
  "properties": {
    "date:inception_lower": "2023-04-01",
    "date:inception_upper": "2023-04-01",
    "iso:country": "GB",
    "wof:name": "KT12 1GZ",
    "wof:placetype": "postalcode"
  },
  "geometry": {"coordinates":[-0.415013,51.379255],"type":"Point"}
}
