{
  "type": "Feature",
  "properties": {
    "date:inception_lower":"2018-03-01",
    "date:inception_upper":"2018-03-31",
    "iso:country":"GB",
    "wof:name":"TQ2 5DG",
    "wof:placetype":"postalcode"
},
  "geometry": {"coordinates":[-3.537668,50.462398],"type":"Point"}
}