{
  "type": "Feature",
  "properties": {
    "iso:country": "GB",
    "wof:name": "TQ2 5DG",
    "wof:placetype": "postalcode"
  },
  "geometry": {"coordinates":[-3.537668,50.462398],"type":"Point"}
}
