{
  "type": "Feature",
  "properties": {
    "date:inception_lower": "1980-01-01",
    "date:inception_upper": "1980-01-01",
    "iso:country": "GB",
    "wof:name": "WV2 1HF",
    "wof:placetype": "postalcode"
  },
  "geometry": {"coordinates":[-2.120584,52.574375],"type":"Point"}
}
