{
  "type": "Feature",
  "properties": {
    "iso:country":"GB",
    "wof:name":"WV2 1HF",
    "wof:placetype":"postalcode"
},
  "geometry": {"coordinates":[-2.12058448939,52.57437529679647],"type":"Point"}
}