{
  "type": "Feature",
  "properties": {
    "iso:country":"GB",
    "wof:name":"PE7 1UG",
    "wof:placetype":"postalcode"
},
  "geometry": {"coordinates":[-0.12347036978576,52.55136080054184],"type":"Point"}
}