{
  "type": "Feature",
  "properties": {
    "date:inception_lower":"1980-01-01",
    "date:inception_upper":"1980-01-31",
    "iso:country":"GB",
    "wof:name":"PE7 1UG",
    "wof:placetype":"postalcode"
},
  "geometry": {"coordinates":[-0.12347,52.551361],"type":"Point"}
}