{
  "type": "Feature",
  "properties": {
    "iso:country": "GB",
    "wof:name": "BB3 0AR",
    "wof:placetype": "postalcode"
  },
  "geometry": {"coordinates":[-2.482886,53.715077],"type":"Point"}
}
