{
  "type": "Feature",
  "properties": {
    "iso:country":"GB",
    "wof:name":"SW3 5HN",
    "wof:placetype":"postalcode"
},
  "geometry": {"coordinates":[-0.16819374250867,51.48426083726662],"type":"Point"}
}