{
  "type": "Feature",
  "properties": {
    "iso:country":"GB",
    "wof:name":"YO8 8AR",
    "wof:placetype":"postalcode"
},
  "geometry": {"coordinates":[-1.0514686485155,53.77913619756855],"type":"Point"}
}