{
  "type": "Feature",
  "properties": {
    "iso:country":"GB",
    "wof:name":"CT13 0PF",
    "wof:placetype":"postalcode"
},
  "geometry": {"coordinates":[1.30350341348861,51.26804345718617],"type":"Point"}
}