{
  "type": "Feature",
  "properties": {
    "iso:country":"GB",
    "wof:name":"HU12 8EG",
    "wof:placetype":"postalcode"
},
  "geometry": {"coordinates":[-0.20809607753117,53.73766695010534],"type":"Point"}
}