{
  "type": "Feature",
  "properties": {
    "iso:country": "GB",
    "wof:name": "SN1 7BX",
    "wof:placetype": "postalcode"
  },
  "geometry": {"coordinates":[-1.807138,51.544828],"type":"Point"}
}
