{
  "type": "Feature",
  "properties": {
    "iso:country":"GB",
    "wof:name":"SN1 7BX",
    "wof:placetype":"postalcode"
},
  "geometry": {"coordinates":[-1.80713766960315,51.54482792850228],"type":"Point"}
}