{
  "type": "Feature",
  "properties": {
    "date:inception_lower":"2014-04-01",
    "date:inception_upper":"2014-04-30",
    "iso:country":"GB",
    "wof:name":"SN1 7BX",
    "wof:placetype":"postalcode"
},
  "geometry": {"coordinates":[-1.807138,51.544828],"type":"Point"}
}