{
  "type": "Feature",
  "properties": {
    "iso:country":"GB",
    "wof:name":"SA15 4HF",
    "wof:placetype":"postalcode"
},
  "geometry": {"coordinates":[-4.16551748997257,51.6909453306125],"type":"Point"}
}