{
  "type": "Feature",
  "properties": {
    "iso:country":"GB",
    "wof:name":"BA5 2HA",
    "wof:placetype":"postalcode"
},
  "geometry": {"coordinates":[-2.66188638183813,51.2029672295571],"type":"Point"}
}