{
  "type": "Feature",
  "properties": {
    "date:inception_lower": "1983-01-01",
    "date:inception_upper": "1983-01-01",
    "iso:country": "GB",
    "wof:name": "BA12 7BT",
    "wof:placetype": "postalcode"
  },
  "geometry": {"coordinates":[-2.144099,51.179898],"type":"Point"}
}
