{
  "type": "Feature",
  "properties": {
    "date:inception_lower": "2020-01-01",
    "date:inception_upper": "2020-01-01",
    "iso:country": "GB",
    "wof:name": "W2 7YW",
    "wof:placetype": "postalcode"
  },
  "geometry": {"coordinates":[-0.276962,51.500496],"type":"Point"}
}
