{
  "type": "Feature",
  "properties": {
    "iso:country":"GB",
    "wof:name":"GU28 9DH",
    "wof:placetype":"postalcode"
},
  "geometry": {"coordinates":[-0.68131810951,51.00242679004185],"type":"Point"}
}