{
  "type": "Feature",
  "properties": {
    "iso:country": "GB",
    "wof:name": "L20 3PL",
    "wof:placetype": "postalcode"
  },
  "geometry": {"coordinates":[-2.986161,53.450024],"type":"Point"}
}
