{
  "type": "Feature",
  "properties": {
    "date:inception_lower":"1980-01-01",
    "date:inception_upper":"1980-01-31",
    "iso:country":"GB",
    "wof:name":"L20 3PL",
    "wof:placetype":"postalcode"
},
  "geometry": {"coordinates":[-2.986161,53.450024],"type":"Point"}
}