{
  "type": "Feature",
  "properties": {
    "iso:country":"GB",
    "wof:name":"L20 3PL",
    "wof:placetype":"postalcode"
},
  "geometry": {"coordinates":[-2.98616081295832,53.45002442494278],"type":"Point"}
}