{
  "type": "Feature",
  "properties": {
    "iso:country": "GB",
    "wof:name": "SN8 3BZ",
    "wof:placetype": "postalcode"
  },
  "geometry": {"coordinates":[-1.648224,51.342946],"type":"Point"}
}
