{
  "type": "Feature",
  "properties": {
    "iso:country":"GB",
    "wof:name":"SN8 3BZ",
    "wof:placetype":"postalcode"
},
  "geometry": {"coordinates":[-1.64823575212596,51.34294904446976],"type":"Point"}
}