{
  "type": "Feature",
  "properties": {
    "iso:country":"GB",
    "wof:name":"SW7 1HB",
    "wof:placetype":"postalcode"
},
  "geometry": {"coordinates":[-0.16540308235328,51.49960339073611],"type":"Point"}
}