{
  "type": "Feature",
  "properties": {
    "iso:country":"GB",
    "wof:name":"N8 7PX",
    "wof:placetype":"postalcode"
},
  "geometry": {"coordinates":[-0.11922825106667,51.58909360265962],"type":"Point"}
}