{
  "type": "Feature",
  "properties": {
    "iso:country":"GB",
    "wof:name":"SK12 1JB",
    "wof:placetype":"postalcode"
},
  "geometry": {"coordinates":[-2.12754285892364,53.34466431183738],"type":"Point"}
}