{
  "type": "Feature",
  "properties": {
    "iso:country":"GB",
    "wof:name":"HA3 0BU",
    "wof:placetype":"postalcode"
},
  "geometry": {"coordinates":[-0.31381300509901,51.58081918531655],"type":"Point"}
}