{
  "type": "Feature",
  "properties": {
    "iso:country":"GB",
    "wof:name":"PE28 2DB",
    "wof:placetype":"postalcode"
},
  "geometry": {"coordinates":[-0.10859423996548,52.33135937646737],"type":"Point"}
}