{
  "type": "Feature",
  "properties": {
    "iso:country": "GB",
    "wof:name": "PE28 2DB",
    "wof:placetype": "postalcode"
  },
  "geometry": {"coordinates":[-0.108594,52.331359],"type":"Point"}
}
