{
  "type": "Feature",
  "properties": {
    "date:inception_lower": "1980-01-01",
    "date:inception_upper": "1980-01-01",
    "iso:country": "GB",
    "wof:name": "RM18 8EA",
    "wof:placetype": "postalcode"
  },
  "geometry": {"coordinates":[0.367444,51.460729],"type":"Point"}
}
