{
  "type": "Feature",
  "properties": {
    "iso:country":"GB",
    "wof:name":"RM18 8EA",
    "wof:placetype":"postalcode"
},
  "geometry": {"coordinates":[0.36744420802186,51.46072887664184],"type":"Point"}
}