{
  "type": "Feature",
  "properties": {
    "iso:country": "GB",
    "wof:name": "SO19 7RF",
    "wof:placetype": "postalcode"
  },
  "geometry": {"coordinates":[-1.382019,50.899056],"type":"Point"}
}
