{
  "type": "Feature",
  "properties": {
    "iso:country": "GB",
    "wof:name": "CH8 7PU",
    "wof:placetype": "postalcode"
  },
  "geometry": {"coordinates":[-3.220405,53.284356],"type":"Point"}
}
