{
  "type": "Feature",
  "properties": {
    "iso:country":"GB",
    "wof:name":"SO16 5GA",
    "wof:placetype":"postalcode"
},
  "geometry": {"coordinates":[-1.44238276139048,50.93838681696572],"type":"Point"}
}