{
  "type": "Feature",
  "properties": {
    "iso:country": "GB",
    "wof:name": "SO16 5GA",
    "wof:placetype": "postalcode"
  },
  "geometry": {"coordinates":[-1.442383,50.938387],"type":"Point"}
}
