{
  "type": "Feature",
  "properties": {
    "iso:country":"GB",
    "wof:name":"TD7 4LB",
    "wof:placetype":"postalcode"
},
  "geometry": {"coordinates":[-2.84195199659554,55.54837654769551],"type":"Point"}
}