{
  "type": "Feature",
  "properties": {
    "date:inception_lower": "2024-08-01",
    "date:inception_upper": "2024-08-01",
    "iso:country": "GB",
    "wof:name": "ME10 3TZ",
    "wof:placetype": "postalcode"
  },
  "geometry": {"coordinates":[0.73892,51.340241],"type":"Point"}
}
