{
  "type": "Feature",
  "properties": {
    "iso:country":"GB",
    "wof:name":"DE6 1SS",
    "wof:placetype":"postalcode"
},
  "geometry": {"coordinates":[-1.72102913115213,53.01066652686309],"type":"Point"}
}