{
  "type": "Feature",
  "properties": {
    "iso:country": "GB",
    "wof:name": "DE6 1SS",
    "wof:placetype": "postalcode"
  },
  "geometry": {"coordinates":[-1.721029,53.010667],"type":"Point"}
}
