{
  "type": "Feature",
  "properties": {
    "iso:country":"GB",
    "wof:name":"SR6 8AT",
    "wof:placetype":"postalcode"
},
  "geometry": {"coordinates":[-1.37324251789092,54.94253161705042],"type":"Point"}
}