{
  "type": "Feature",
  "properties": {
    "date:inception_lower": "2004-11-01",
    "date:inception_upper": "2004-11-01",
    "iso:country": "GB",
    "wof:name": "KT9 1EB",
    "wof:placetype": "postalcode"
  },
  "geometry": {"coordinates":[-0.304077,51.373862],"type":"Point"}
}
