{
  "type": "Feature",
  "properties": {
    "iso:country": "GB",
    "wof:name": "KT9 1EB",
    "wof:placetype": "postalcode"
  },
  "geometry": {"coordinates":[-0.304077,51.373862],"type":"Point"}
}
