{
  "type": "Feature",
  "properties": {
    "iso:country": "GB",
    "wof:name": "SP4 8FE",
    "wof:placetype": "postalcode"
  },
  "geometry": {"coordinates":[-1.781623,51.201157],"type":"Point"}
}
