{
  "type": "Feature",
  "properties": {
    "date:inception_lower":"2011-12-01",
    "date:inception_upper":"2011-12-31",
    "iso:country":"GB",
    "wof:name":"SP4 8FE",
    "wof:placetype":"postalcode"
},
  "geometry": {"coordinates":[-1.781623,51.201157],"type":"Point"}
}