{
  "type": "Feature",
  "properties": {
    "iso:country": "GB",
    "wof:name": "SN3 1QT",
    "wof:placetype": "postalcode"
  },
  "geometry": {"coordinates":[-1.771801,51.549116],"type":"Point"}
}
