{
  "type": "Feature",
  "properties": {
    "date:inception_lower":"1980-01-01",
    "date:inception_upper":"1980-01-31",
    "iso:country":"GB",
    "wof:name":"SN3 1QT",
    "wof:placetype":"postalcode"
},
  "geometry": {"coordinates":[-1.771801,51.549116],"type":"Point"}
}