{
  "type": "Feature",
  "properties": {
    "iso:country":"GB",
    "wof:name":"B26 1SD",
    "wof:placetype":"postalcode"
},
  "geometry": {"coordinates":[-1.80172400776148,52.4672285619554],"type":"Point"}
}