{
  "type": "Feature",
  "properties": {
    "iso:country":"GB",
    "wof:name":"NR31 6LJ",
    "wof:placetype":"postalcode"
},
  "geometry": {"coordinates":[1.72718117424563,52.58000155149291],"type":"Point"}
}