{
  "type": "Feature",
  "properties": {
    "iso:country":"GB",
    "wof:name":"TN35 5EG",
    "wof:placetype":"postalcode"
},
  "geometry": {"coordinates":[0.61369603980971,50.87580724815842],"type":"Point"}
}