{
  "type": "Feature",
  "properties": {
    "date:inception_lower": "1980-01-01",
    "date:inception_upper": "1980-01-01",
    "iso:country": "GB",
    "wof:name": "KT12 1EP",
    "wof:placetype": "postalcode"
  },
  "geometry": {"coordinates":[-0.420374,51.383824],"type":"Point"}
}
