{
  "type": "Feature",
  "properties": {
    "iso:country":"GB",
    "wof:name":"KT12 1EP",
    "wof:placetype":"postalcode"
},
  "geometry": {"coordinates":[-0.42039493014738,51.38382502629053],"type":"Point"}
}