{
  "type": "Feature",
  "properties": {
    "iso:country": "GB",
    "wof:name": "KT12 1EP",
    "wof:placetype": "postalcode"
  },
  "geometry": {"coordinates":[-0.420374,51.383824],"type":"Point"}
}
