{
  "type": "Feature",
  "properties": {
    "iso:country":"GB",
    "wof:name":"LS12 3QJ",
    "wof:placetype":"postalcode"
},
  "geometry": {"coordinates":[-1.61034714818741,53.8018115607135],"type":"Point"}
}