{
  "type": "Feature",
  "properties": {
    "date:inception_lower": "1980-01-01",
    "date:inception_upper": "1980-01-01",
    "iso:country": "GB",
    "wof:name": "HA8 6NQ",
    "wof:placetype": "postalcode"
  },
  "geometry": {"coordinates":[-0.286658,51.607088],"type":"Point"}
}
