{
  "type": "Feature",
  "properties": {
    "iso:country": "GB",
    "wof:name": "HA8 6NQ",
    "wof:placetype": "postalcode"
  },
  "geometry": {"coordinates":[-0.286658,51.607088],"type":"Point"}
}
