{
  "type": "Feature",
  "properties": {
    "iso:country":"GB",
    "wof:name":"LU7 1YU",
    "wof:placetype":"postalcode"
},
  "geometry": {"coordinates":[-0.66520624661734,51.91808603832099],"type":"Point"}
}