{
  "type": "Feature",
  "properties": {
    "date:inception_lower": "2001-06-01",
    "date:inception_upper": "2001-06-01",
    "iso:country": "GB",
    "wof:name": "LU7 1YU",
    "wof:placetype": "postalcode"
  },
  "geometry": {"coordinates":[-0.665178,51.918186],"type":"Point"}
}
