{
  "type": "Feature",
  "properties": {
    "iso:country": "GB",
    "wof:name": "NR13 6GA",
    "wof:placetype": "postalcode"
  },
  "geometry": {"coordinates":[1.376528,52.6724],"type":"Point"}
}
