{
  "type": "Feature",
  "properties": {
    "iso:country": "GB",
    "wof:name": "LL57 4SP",
    "wof:placetype": "postalcode"
  },
  "geometry": {"coordinates":[-4.14397,53.215698],"type":"Point"}
}
