{
  "type": "Feature",
  "properties": {
    "iso:country":"GB",
    "wof:name":"LL57 4SP",
    "wof:placetype":"postalcode"
},
  "geometry": {"coordinates":[-4.14396992078865,53.21569834450273],"type":"Point"}
}