{
  "type": "Feature",
  "properties": {
    "iso:country": "GB",
    "wof:name": "TN28 8AQ",
    "wof:placetype": "postalcode"
  },
  "geometry": {"coordinates":[0.945973,50.983211],"type":"Point"}
}
