{
  "type": "Feature",
  "properties": {
    "date:inception_lower":"2015-05-01",
    "date:inception_upper":"2015-05-31",
    "iso:country":"GB",
    "wof:name":"TN28 8AQ",
    "wof:placetype":"postalcode"
},
  "geometry": {"coordinates":[0.945973,50.983211],"type":"Point"}
}