{
  "type": "Feature",
  "properties": {
    "iso:country":"GB",
    "wof:name":"SW1V 2LL",
    "wof:placetype":"postalcode"
},
  "geometry": {"coordinates":[-0.13878486194412,51.49199893558343],"type":"Point"}
}