{
  "type": "Feature",
  "properties": {
    "iso:country":"GB",
    "wof:name":"S36 6BQ",
    "wof:placetype":"postalcode"
},
  "geometry": {"coordinates":[-1.63784531805304,53.52431473394475],"type":"Point"}
}