{
  "type": "Feature",
  "properties": {
    "date:inception_lower": "1997-06-01",
    "date:inception_upper": "1997-06-01",
    "iso:country": "GB",
    "wof:name": "S36 6BQ",
    "wof:placetype": "postalcode"
  },
  "geometry": {"coordinates":[-1.637845,53.524315],"type":"Point"}
}
