{
  "type": "Feature",
  "properties": {
    "iso:country":"GB",
    "wof:name":"DY12 1PD",
    "wof:placetype":"postalcode"
},
  "geometry": {"coordinates":[-2.31217509139534,52.40636173121383],"type":"Point"}
}