{
  "type": "Feature",
  "properties": {
    "iso:country":"GB",
    "wof:name":"E14 0FA",
    "wof:placetype":"postalcode"
},
  "geometry": {"coordinates":[-0.00299536217129,51.51614058975382],"type":"Point"}
}