{
  "type": "Feature",
  "properties": {
    "iso:country":"GB",
    "wof:name":"CV2 5DF",
    "wof:placetype":"postalcode"
},
  "geometry": {"coordinates":[-1.46769166674183,52.41170875087717],"type":"Point"}
}