{
  "type": "Feature",
  "properties": {
    "date:inception_lower": "2004-09-01",
    "date:inception_upper": "2004-09-01",
    "iso:country": "GB",
    "wof:name": "CV2 5DF",
    "wof:placetype": "postalcode"
  },
  "geometry": {"coordinates":[-1.467692,52.411709],"type":"Point"}
}
