{
  "type": "Feature",
  "properties": {
    "iso:country":"GB",
    "wof:name":"CO10 8BW",
    "wof:placetype":"postalcode"
},
  "geometry": {"coordinates":[0.60527791963156,52.08748374798409],"type":"Point"}
}