{
  "type": "Feature",
  "properties": {
    "iso:country":"GB",
    "wof:name":"W1U 1NE",
    "wof:placetype":"postalcode"
},
  "geometry": {"coordinates":[-0.15025767140867,51.51568688081716],"type":"Point"}
}