{
  "type": "Feature",
  "properties": {
    "iso:country":"GB",
    "wof:name":"CH2 1RD",
    "wof:placetype":"postalcode"
},
  "geometry": {"coordinates":[-2.88158455676946,53.21639200752763],"type":"Point"}
}