{
  "type": "Feature",
  "properties": {
    "iso:country": "GB",
    "wof:name": "ST6 7AY",
    "wof:placetype": "postalcode"
  },
  "geometry": {"coordinates":[-2.193356,53.057687],"type":"Point"}
}
