{
  "type": "Feature",
  "properties": {
    "iso:country":"GB",
    "wof:name":"S64 8SS",
    "wof:placetype":"postalcode"
},
  "geometry": {"coordinates":[-1.30848344259418,53.48100437913895],"type":"Point"}
}