{
  "type": "Feature",
  "properties": {
    "date:inception_lower":"1980-01-01",
    "date:inception_upper":"1980-01-31",
    "iso:country":"GB",
    "wof:name":"S64 8SS",
    "wof:placetype":"postalcode"
},
  "geometry": {"coordinates":[-1.308483,53.481004],"type":"Point"}
}