{
  "type": "Feature",
  "properties": {
    "iso:country":"GB",
    "wof:name":"OX2 9QL",
    "wof:placetype":"postalcode"
},
  "geometry": {"coordinates":[-1.34199080284068,51.73277084880701],"type":"Point"}
}