{
  "type": "Feature",
  "properties": {
    "iso:country":"GB",
    "wof:name":"LE8 4ED",
    "wof:placetype":"postalcode"
},
  "geometry": {"coordinates":[-1.16668942530961,52.57389813498995],"type":"Point"}
}