{
  "type": "Feature",
  "properties": {
    "iso:country": "GB",
    "wof:name": "SE9 3JW",
    "wof:placetype": "postalcode"
  },
  "geometry": {"coordinates":[0.063003,51.434117],"type":"Point"}
}
