{
  "type": "Feature",
  "properties": {
    "iso:country":"GB",
    "wof:name":"SM6 9DR",
    "wof:placetype":"postalcode"
},
  "geometry": {"coordinates":[-0.13330885474012,51.35543961270728],"type":"Point"}
}