{
  "type": "Feature",
  "properties": {
    "date:inception_lower": "2007-02-01",
    "date:inception_upper": "2007-02-01",
    "iso:country": "GB",
    "wof:name": "TN15 8NQ",
    "wof:placetype": "postalcode"
  },
  "geometry": {"coordinates":[0.32336,51.291854],"type":"Point"}
}
