{
  "type": "Feature",
  "properties": {
    "iso:country":"GB",
    "wof:name":"TN15 8NQ",
    "wof:placetype":"postalcode"
},
  "geometry": {"coordinates":[0.32336009373123,51.29185383266614],"type":"Point"}
}