{
  "type": "Feature",
  "properties": {
    "date:inception_lower": "1980-01-01",
    "date:inception_upper": "1980-01-01",
    "iso:country": "GB",
    "wof:name": "WS13 7JN",
    "wof:placetype": "postalcode"
  },
  "geometry": {"coordinates":[-1.831261,52.69593],"type":"Point"}
}
