{
  "type": "Feature",
  "properties": {
    "date:inception_lower": "1980-01-01",
    "date:inception_upper": "1980-01-01",
    "iso:country": "GB",
    "wof:name": "CF5 3EZ",
    "wof:placetype": "postalcode"
  },
  "geometry": {"coordinates":[-3.24831,51.490174],"type":"Point"}
}
