{
  "type": "Feature",
  "properties": {
    "iso:country":"GB",
    "wof:name":"CF5 3EZ",
    "wof:placetype":"postalcode"
},
  "geometry": {"coordinates":[-3.24832966132077,51.49017271712037],"type":"Point"}
}