{
  "type": "Feature",
  "properties": {
    "date:inception_lower": "1992-01-01",
    "date:inception_upper": "1992-01-01",
    "iso:country": "GB",
    "wof:name": "DN5 0UB",
    "wof:placetype": "postalcode"
  },
  "geometry": {"coordinates":[-1.124427,53.555959],"type":"Point"}
}
