{
  "type": "Feature",
  "properties": {
    "iso:country":"GB",
    "wof:name":"DN5 0UB",
    "wof:placetype":"postalcode"
},
  "geometry": {"coordinates":[-1.12442659974771,53.5559591762949],"type":"Point"}
}