{
  "type": "Feature",
  "properties": {
    "iso:country":"GB",
    "wof:name":"NR3 3AG",
    "wof:placetype":"postalcode"
},
  "geometry": {"coordinates":[1.29067011522717,52.6350846488663],"type":"Point"}
}