{
  "type": "Feature",
  "properties": {
    "iso:country":"GB",
    "wof:name":"M22 4BE",
    "wof:placetype":"postalcode"
},
  "geometry": {"coordinates":[-2.26132627084129,53.4031507579826],"type":"Point"}
}