{
  "type": "Feature",
  "properties": {
    "iso:country": "GB",
    "wof:name": "M22 4BE",
    "wof:placetype": "postalcode"
  },
  "geometry": {"coordinates":[-2.261326,53.403151],"type":"Point"}
}
