{
  "type": "Feature",
  "properties": {
    "iso:country": "GB",
    "wof:name": "NR31 8DE",
    "wof:placetype": "postalcode"
  },
  "geometry": {"coordinates":[1.711624,52.581642],"type":"Point"}
}
