{
  "type": "Feature",
  "properties": {
    "date:inception_lower": "1980-01-01",
    "date:inception_upper": "1980-01-01",
    "iso:country": "GB",
    "wof:name": "NR31 8DE",
    "wof:placetype": "postalcode"
  },
  "geometry": {"coordinates":[1.711624,52.581642],"type":"Point"}
}
