{
  "type": "Feature",
  "properties": {
    "iso:country":"GB",
    "wof:name":"NR31 8DE",
    "wof:placetype":"postalcode"
},
  "geometry": {"coordinates":[1.71162395887735,52.58164212377104],"type":"Point"}
}