{
  "type": "Feature",
  "properties": {
    "iso:country": "GB",
    "wof:name": "SE19 1UP",
    "wof:placetype": "postalcode"
  },
  "geometry": {"coordinates":[-0.076083,51.427949],"type":"Point"}
}
