{
  "type": "Feature",
  "properties": {
    "iso:country": "GB",
    "wof:name": "SS17 0BY",
    "wof:placetype": "postalcode"
  },
  "geometry": {"coordinates":[0.426902,51.513843],"type":"Point"}
}
