{
  "type": "Feature",
  "properties": {
    "iso:country":"GB",
    "wof:name":"E1W 3AU",
    "wof:placetype":"postalcode"
},
  "geometry": {"coordinates":[-0.0577257489283,51.50690705411262],"type":"Point"}
}