{
  "type": "Feature",
  "properties": {
    "iso:country":"GB",
    "wof:name":"EX23 8JG",
    "wof:placetype":"postalcode"
},
  "geometry": {"coordinates":[-4.53938289030478,50.83625219530073],"type":"Point"}
}