{
  "type": "Feature",
  "properties": {
    "date:inception_lower": "2022-06-01",
    "date:inception_upper": "2022-06-01",
    "iso:country": "GB",
    "wof:name": "EX1 4AS",
    "wof:placetype": "postalcode"
  },
  "geometry": {"coordinates":[-3.446435,50.736072],"type":"Point"}
}
