{
  "type": "Feature",
  "properties": {
    "iso:country":"GB",
    "wof:name":"G43 1UP",
    "wof:placetype":"postalcode"
},
  "geometry": {"coordinates":[-4.287728504239,55.82296082995612],"type":"Point"}
}