{
  "type": "Feature",
  "properties": {
    "iso:country": "GB",
    "wof:name": "NG6 8NP",
    "wof:placetype": "postalcode"
  },
  "geometry": {"coordinates":[-1.15221,53.031085],"type":"Point"}
}
