{
  "type": "Feature",
  "properties": {
    "iso:country":"GB",
    "wof:name":"NG6 8NP",
    "wof:placetype":"postalcode"
},
  "geometry": {"coordinates":[-1.15220986191048,53.03108492357963],"type":"Point"}
}