{
  "type": "Feature",
  "properties": {
    "date:inception_lower": "2002-07-01",
    "date:inception_upper": "2002-07-01",
    "iso:country": "GB",
    "wof:name": "NG6 8NP",
    "wof:placetype": "postalcode"
  },
  "geometry": {"coordinates":[-1.15221,53.031085],"type":"Point"}
}
