{
  "type": "Feature",
  "properties": {
    "iso:country":"GB",
    "wof:name":"PE31 6LA",
    "wof:placetype":"postalcode"
},
  "geometry": {"coordinates":[0.50084643435934,52.84109738176938],"type":"Point"}
}