{
  "type": "Feature",
  "properties": {
    "iso:country":"GB",
    "wof:name":"BH24 2HN",
    "wof:placetype":"postalcode"
},
  "geometry": {"coordinates":[-1.84658790510118,50.83359574363745],"type":"Point"}
}