{
  "type": "Feature",
  "properties": {
    "date:inception_lower": "1980-01-01",
    "date:inception_upper": "1980-01-01",
    "iso:country": "GB",
    "wof:name": "YO14 9QY",
    "wof:placetype": "postalcode"
  },
  "geometry": {"coordinates":[-0.28453,54.192027],"type":"Point"}
}
