{
  "type": "Feature",
  "properties": {
    "iso:country":"GB",
    "wof:name":"YO14 9QY",
    "wof:placetype":"postalcode"
},
  "geometry": {"coordinates":[-0.28451416327574,54.19200763301187],"type":"Point"}
}