{
  "type": "Feature",
  "properties": {
    "iso:country":"GB",
    "wof:name":"TA11 6DY",
    "wof:placetype":"postalcode"
},
  "geometry": {"coordinates":[-2.64489127540017,51.07647079935636],"type":"Point"}
}