{
  "type": "Feature",
  "properties": {
    "iso:country": "GB",
    "wof:name": "TA11 6DY",
    "wof:placetype": "postalcode"
  },
  "geometry": {"coordinates":[-2.645254,51.076616],"type":"Point"}
}
