{
  "type": "Feature",
  "properties": {
    "iso:country":"GB",
    "wof:name":"SN14 0FJ",
    "wof:placetype":"postalcode"
},
  "geometry": {"coordinates":[-2.14709860313014,51.44720105996835],"type":"Point"}
}