{
  "type": "Feature",
  "properties": {
    "iso:country": "GB",
    "wof:name": "SN14 0FJ",
    "wof:placetype": "postalcode"
  },
  "geometry": {"coordinates":[-2.147094,51.4472],"type":"Point"}
}
