{
  "type": "Feature",
  "properties": {
    "date:inception_lower": "2016-03-01",
    "date:inception_upper": "2016-03-01",
    "iso:country": "GB",
    "wof:name": "SN14 0FJ",
    "wof:placetype": "postalcode"
  },
  "geometry": {"coordinates":[-2.147094,51.4472],"type":"Point"}
}
