{
  "type": "Feature",
  "properties": {
    "iso:country": "GB",
    "wof:name": "L8 5SD",
    "wof:placetype": "postalcode"
  },
  "geometry": {"coordinates":[-2.978998,53.393282],"type":"Point"}
}
