{
  "type": "Feature",
  "properties": {
    "iso:country": "GB",
    "wof:name": "BH12 1AJ",
    "wof:placetype": "postalcode"
  },
  "geometry": {"coordinates":[-1.907494,50.724337],"type":"Point"}
}
