{
  "type": "Feature",
  "properties": {
    "iso:country":"GB",
    "wof:name":"SO43 7DZ",
    "wof:placetype":"postalcode"
},
  "geometry": {"coordinates":[-1.59700837275553,50.87472655176912],"type":"Point"}
}