{
  "type": "Feature",
  "properties": {
    "iso:country": "GB",
    "wof:name": "EX17 2AP",
    "wof:placetype": "postalcode"
  },
  "geometry": {"coordinates":[-3.653682,50.79154],"type":"Point"}
}
