{
  "type": "Feature",
  "properties": {
    "iso:country": "GB",
    "wof:name": "SS9 3HS",
    "wof:placetype": "postalcode"
  },
  "geometry": {"coordinates":[0.669498,51.55007],"type":"Point"}
}
