{
  "type": "Feature",
  "properties": {
    "date:inception_lower":"2001-12-01",
    "date:inception_upper":"2001-12-31",
    "iso:country":"GB",
    "wof:name":"SP10 4BF",
    "wof:placetype":"postalcode"
},
  "geometry": {"coordinates":[-1.479787,51.219655],"type":"Point"}
}