{
  "type": "Feature",
  "properties": {
    "date:inception_lower":"1980-01-01",
    "date:inception_upper":"1980-01-31",
    "iso:country":"GB",
    "wof:name":"LS2 7JL",
    "wof:placetype":"postalcode"
},
  "geometry": {"coordinates":[-1.539268,53.798664],"type":"Point"}
}