{
  "type": "Feature",
  "properties": {
    "iso:country":"GB",
    "wof:name":"LS2 7JL",
    "wof:placetype":"postalcode"
},
  "geometry": {"coordinates":[-1.53839855568255,53.79859033814675],"type":"Point"}
}