{
  "type": "Feature",
  "properties": {
    "iso:country":"GB",
    "wof:name":"TS12 1HU",
    "wof:placetype":"postalcode"
},
  "geometry": {"coordinates":[-0.97684696379195,54.57826014293367],"type":"Point"}
}