{
  "type": "Feature",
  "properties": {
    "iso:country": "GB",
    "wof:name": "TS12 1HU",
    "wof:placetype": "postalcode"
  },
  "geometry": {"coordinates":[-0.976847,54.57826],"type":"Point"}
}
