{
  "type": "Feature",
  "properties": {
    "date:inception_lower": "1993-08-01",
    "date:inception_upper": "1993-08-01",
    "iso:country": "GB",
    "wof:name": "NN3 6AP",
    "wof:placetype": "postalcode"
  },
  "geometry": {"coordinates":[-0.880436,52.277807],"type":"Point"}
}
