{
  "type": "Feature",
  "properties": {
    "iso:country": "GB",
    "wof:name": "TA2 7AP",
    "wof:placetype": "postalcode"
  },
  "geometry": {"coordinates":[-3.10066,51.03234],"type":"Point"}
}
