{
  "type": "Feature",
  "properties": {
    "date:inception_lower":"1980-01-01",
    "date:inception_upper":"1980-01-31",
    "iso:country":"GB",
    "wof:name":"N19 4NU",
    "wof:placetype":"postalcode"
},
  "geometry": {"coordinates":[-0.123725,51.566145],"type":"Point"}
}