{
  "type": "Feature",
  "properties": {
    "iso:country":"GB",
    "wof:name":"N19 4NU",
    "wof:placetype":"postalcode"
},
  "geometry": {"coordinates":[-0.12372490497892,51.56614493892728],"type":"Point"}
}