{
  "type": "Feature",
  "properties": {
    "iso:country":"GB",
    "wof:name":"BD16 3LS",
    "wof:placetype":"postalcode"
},
  "geometry": {"coordinates":[-1.810549370922,53.84984057829976],"type":"Point"}
}