{
  "type": "Feature",
  "properties": {
    "date:inception_lower": "1980-01-01",
    "date:inception_upper": "1980-01-01",
    "iso:country": "GB",
    "wof:name": "BD16 3LS",
    "wof:placetype": "postalcode"
  },
  "geometry": {"coordinates":[-1.810549,53.849841],"type":"Point"}
}
