{
  "type": "Feature",
  "properties": {
    "iso:country":"GB",
    "wof:name":"WF3 3TP",
    "wof:placetype":"postalcode"
},
  "geometry": {"coordinates":[-1.48608761203767,53.74086281537975],"type":"Point"}
}