{
  "type": "Feature",
  "properties": {
    "iso:country": "GB",
    "wof:name": "WF3 3TP",
    "wof:placetype": "postalcode"
  },
  "geometry": {"coordinates":[-1.486088,53.740863],"type":"Point"}
}
