{
  "type": "Feature",
  "properties": {
    "iso:country":"GB",
    "wof:name":"DD10 8EE",
    "wof:placetype":"postalcode"
},
  "geometry": {"coordinates":[-2.46113002034458,56.70618093042388],"type":"Point"}
}