{
  "type": "Feature",
  "properties": {
    "iso:country":"GB",
    "wof:name":"WA5 3NH",
    "wof:placetype":"postalcode"
},
  "geometry": {"coordinates":[-2.66869173564242,53.39513660553592],"type":"Point"}
}