{
  "type": "Feature",
  "properties": {
    "iso:country":"GB",
    "wof:name":"ML1 1SE",
    "wof:placetype":"postalcode"
},
  "geometry": {"coordinates":[-3.97845035078262,55.78311303240518],"type":"Point"}
}