{
  "type": "Feature",
  "properties": {
    "date:inception_lower": "1980-01-01",
    "date:inception_upper": "1980-01-01",
    "iso:country": "GB",
    "wof:name": "ML1 1SE",
    "wof:placetype": "postalcode"
  },
  "geometry": {"coordinates":[-3.978337,55.783228],"type":"Point"}
}
