{
  "type": "Feature",
  "properties": {
    "iso:country":"GB",
    "wof:name":"SY13 2DE",
    "wof:placetype":"postalcode"
},
  "geometry": {"coordinates":[-2.66374859106246,52.90205771993378],"type":"Point"}
}