{
  "type": "Feature",
  "properties": {
    "iso:country": "GB",
    "wof:name": "SY13 2DE",
    "wof:placetype": "postalcode"
  },
  "geometry": {"coordinates":[-2.663749,52.902058],"type":"Point"}
}
