{
  "type": "Feature",
  "properties": {
    "iso:country":"GB",
    "wof:name":"IP29 4SA",
    "wof:placetype":"postalcode"
},
  "geometry": {"coordinates":[0.74723579703776,52.18177950302204],"type":"Point"}
}