{
  "type": "Feature",
  "properties": {
    "date:inception_lower": "2002-12-01",
    "date:inception_upper": "2002-12-01",
    "iso:country": "GB",
    "wof:name": "TA24 8PX",
    "wof:placetype": "postalcode"
  },
  "geometry": {"coordinates":[-3.596823,51.210235],"type":"Point"}
}
