{
  "type": "Feature",
  "properties": {
    "iso:country":"GB",
    "wof:name":"DH8 9RF",
    "wof:placetype":"postalcode"
},
  "geometry": {"coordinates":[-1.87634715670918,54.83267958226286],"type":"Point"}
}