{
  "type": "Feature",
  "properties": {
    "iso:country": "GB",
    "wof:name": "EH1 1NW",
    "wof:placetype": "postalcode"
  },
  "geometry": {"coordinates":[-3.191608,55.949766],"type":"Point"}
}
