{
  "type": "Feature",
  "properties": {
    "iso:country": "GB",
    "wof:name": "IP25 6LU",
    "wof:placetype": "postalcode"
  },
  "geometry": {"coordinates":[0.778764,52.563163],"type":"Point"}
}
