{
  "type": "Feature",
  "properties": {
    "iso:country":"GB",
    "wof:name":"IP25 6LU",
    "wof:placetype":"postalcode"
},
  "geometry": {"coordinates":[0.778764186906,52.56316317683304],"type":"Point"}
}