{
  "type": "Feature",
  "properties": {
    "iso:country": "GB",
    "wof:name": "GL4 8HF",
    "wof:placetype": "postalcode"
  },
  "geometry": {"coordinates":[-2.13802,51.818354],"type":"Point"}
}
