{
  "type": "Feature",
  "properties": {
    "iso:country":"GB",
    "wof:name":"GL4 8HF",
    "wof:placetype":"postalcode"
},
  "geometry": {"coordinates":[-2.13802043241576,51.8183535561765],"type":"Point"}
}