{
  "type": "Feature",
  "properties": {
    "iso:country": "GB",
    "wof:name": "DH8 8RU",
    "wof:placetype": "postalcode"
  },
  "geometry": {"coordinates":[-1.852504,54.860816],"type":"Point"}
}
