{
  "type": "Feature",
  "properties": {
    "iso:country":"GB",
    "wof:name":"DH8 8RU",
    "wof:placetype":"postalcode"
},
  "geometry": {"coordinates":[-1.85250427619664,54.86081636440667],"type":"Point"}
}