{
  "type": "Feature",
  "properties": {
    "iso:country":"GB",
    "wof:name":"CH4 9AE",
    "wof:placetype":"postalcode"
},
  "geometry": {"coordinates":[-2.97941417701925,53.15234359462036],"type":"Point"}
}