{
  "type": "Feature",
  "properties": {
    "date:inception_lower": "1980-01-01",
    "date:inception_upper": "1980-01-01",
    "iso:country": "GB",
    "wof:name": "CH4 9AE",
    "wof:placetype": "postalcode"
  },
  "geometry": {"coordinates":[-2.979301,53.151937],"type":"Point"}
}
