{
  "type": "Feature",
  "properties": {
    "iso:country": "GB",
    "wof:name": "NR11 7AN",
    "wof:placetype": "postalcode"
  },
  "geometry": {"coordinates":[1.20807,52.831285],"type":"Point"}
}
