{
  "type": "Feature",
  "properties": {
    "iso:country":"GB",
    "wof:name":"CH44 2EE",
    "wof:placetype":"postalcode"
},
  "geometry": {"coordinates":[-3.06212432111097,53.41724652476898],"type":"Point"}
}