{
  "type": "Feature",
  "properties": {
    "iso:country": "GB",
    "wof:name": "IP3 9LT",
    "wof:placetype": "postalcode"
  },
  "geometry": {"coordinates":[1.186808,52.037129],"type":"Point"}
}
