{
  "type": "Feature",
  "properties": {
    "date:inception_lower": "1980-01-01",
    "date:inception_upper": "1980-01-01",
    "iso:country": "GB",
    "wof:name": "IP3 9LT",
    "wof:placetype": "postalcode"
  },
  "geometry": {"coordinates":[1.186808,52.037129],"type":"Point"}
}
