{
  "type": "Feature",
  "properties": {
    "iso:country":"GB",
    "wof:name":"SW6 3AP",
    "wof:placetype":"postalcode"
},
  "geometry": {"coordinates":[-0.19199199516845,51.46993644079433],"type":"Point"}
}