{
  "type": "Feature",
  "properties": {
    "iso:country": "GB",
    "wof:name": "L1 5AJ",
    "wof:placetype": "postalcode"
  },
  "geometry": {"coordinates":[-2.977319,53.400055],"type":"Point"}
}
