{
  "type": "Feature",
  "properties": {
    "iso:country": "GB",
    "wof:name": "BS3 1PX",
    "wof:placetype": "postalcode"
  },
  "geometry": {"coordinates":[-2.608509,51.445424],"type":"Point"}
}
