{
  "type": "Feature",
  "properties": {
    "iso:country":"GB",
    "wof:name":"KA6 7DU",
    "wof:placetype":"postalcode"
},
  "geometry": {"coordinates":[-4.4681925427529,55.43351473380395],"type":"Point"}
}