{
  "type": "Feature",
  "properties": {
    "date:inception_lower": "2000-06-01",
    "date:inception_upper": "2000-06-01",
    "iso:country": "GB",
    "wof:name": "KA6 7DU",
    "wof:placetype": "postalcode"
  },
  "geometry": {"coordinates":[-4.468192,55.433515],"type":"Point"}
}
