{
  "type": "Feature",
  "properties": {
    "date:inception_lower": "1980-01-01",
    "date:inception_upper": "1980-01-01",
    "iso:country": "GB",
    "wof:name": "LS16 5AY",
    "wof:placetype": "postalcode"
  },
  "geometry": {"coordinates":[-1.599979,53.83506],"type":"Point"}
}
