{
  "type": "Feature",
  "properties": {
    "iso:country":"GB",
    "wof:name":"LS16 5AY",
    "wof:placetype":"postalcode"
},
  "geometry": {"coordinates":[-1.59997951964319,53.8350599810414],"type":"Point"}
}