{
  "type": "Feature",
  "properties": {
    "iso:country":"GB",
    "wof:name":"BH12 4PA",
    "wof:placetype":"postalcode"
},
  "geometry": {"coordinates":[-1.94176177200628,50.74911578743133],"type":"Point"}
}