{
  "type": "Feature",
  "properties": {
    "iso:country":"GB",
    "wof:name":"LE67 2FW",
    "wof:placetype":"postalcode"
},
  "geometry": {"coordinates":[-1.37964155725105,52.7100434723246],"type":"Point"}
}