{
  "type": "Feature",
  "properties": {
    "iso:country":"GB",
    "wof:name":"PE2 9QB",
    "wof:placetype":"postalcode"
},
  "geometry": {"coordinates":[-0.26155718016253,52.5625950325377],"type":"Point"}
}