{
  "type": "Feature",
  "properties": {
    "iso:country":"GB",
    "wof:name":"PA6 7DE",
    "wof:placetype":"postalcode"
},
  "geometry": {"coordinates":[-4.52940204399074,55.86573719964492],"type":"Point"}
}