{
  "type": "Feature",
  "properties": {
    "iso:country":"GB",
    "wof:name":"NP26 4LQ",
    "wof:placetype":"postalcode"
},
  "geometry": {"coordinates":[-2.76431944264897,51.59041088394862],"type":"Point"}
}