{
  "type": "Feature",
  "properties": {
    "date:inception_lower": "2023-05-01",
    "date:inception_upper": "2023-05-01",
    "iso:country": "GB",
    "wof:name": "WD25 8DJ",
    "wof:placetype": "postalcode"
  },
  "geometry": {"coordinates":[-0.350528,51.663894],"type":"Point"}
}
