{
  "type": "Feature",
  "properties": {
    "iso:country": "GB",
    "wof:name": "WD25 8DJ",
    "wof:placetype": "postalcode"
  },
  "geometry": {"coordinates":[-0.350552,51.663889],"type":"Point"}
}
