{
  "type": "Feature",
  "properties": {
    "iso:country":"GB",
    "wof:name":"SA32 7PJ",
    "wof:placetype":"postalcode"
},
  "geometry": {"coordinates":[-4.13158573937208,51.9039412536179],"type":"Point"}
}