{
  "type": "Feature",
  "properties": {
    "iso:country": "GB",
    "wof:name": "YO42 4GB",
    "wof:placetype": "postalcode"
  },
  "geometry": {"coordinates":[-0.812234,53.933377],"type":"Point"}
}
