{
  "type": "Feature",
  "properties": {
    "iso:country":"GB",
    "wof:name":"YO42 4GB",
    "wof:placetype":"postalcode"
},
  "geometry": {"coordinates":[-0.81223411969439,53.93337749723972],"type":"Point"}
}