{
  "type": "Feature",
  "properties": {
    "date:inception_lower":"2008-01-01",
    "date:inception_upper":"2008-01-31",
    "iso:country":"GB",
    "wof:name":"YO42 4GB",
    "wof:placetype":"postalcode"
},
  "geometry": {"coordinates":[-0.812234,53.933377],"type":"Point"}
}