{
  "type": "Feature",
  "properties": {
    "iso:country": "GB",
    "wof:name": "CA5 6AH",
    "wof:placetype": "postalcode"
  },
  "geometry": {"coordinates":[-3.057916,54.841708],"type":"Point"}
}
