{
  "type": "Feature",
  "properties": {
    "iso:country": "GB",
    "wof:name": "WV10 8TH",
    "wof:placetype": "postalcode"
  },
  "geometry": {"coordinates":[-2.11281,52.632349],"type":"Point"}
}
