{
  "type": "Feature",
  "properties": {
    "iso:country":"GB",
    "wof:name":"WV10 8TH",
    "wof:placetype":"postalcode"
},
  "geometry": {"coordinates":[-2.11280987102381,52.6323490369185],"type":"Point"}
}