{
  "type": "Feature",
  "properties": {
    "date:inception_lower":"2013-07-01",
    "date:inception_upper":"2013-07-31",
    "iso:country":"GB",
    "wof:name":"RH16 4US",
    "wof:placetype":"postalcode"
},
  "geometry": {"coordinates":[-0.115897,50.993714],"type":"Point"}
}