{
  "type": "Feature",
  "properties": {
    "iso:country":"GB",
    "wof:name":"RH16 4US",
    "wof:placetype":"postalcode"
},
  "geometry": {"coordinates":[-0.11589679343001,50.99371409155285],"type":"Point"}
}