{
  "type": "Feature",
  "properties": {
    "iso:country":"GB",
    "wof:name":"SE1 2JE",
    "wof:placetype":"postalcode"
},
  "geometry": {"coordinates":[-0.07449694400582,51.5014912931858],"type":"Point"}
}