{
  "type": "Feature",
  "properties": {
    "iso:country":"GB",
    "wof:name":"UB9 6PJ",
    "wof:placetype":"postalcode"
},
  "geometry": {"coordinates":[-0.48564937032965,51.61519169801692],"type":"Point"}
}