{
  "type": "Feature",
  "properties": {
    "iso:country":"GB",
    "wof:name":"RG9 1UG",
    "wof:placetype":"postalcode"
},
  "geometry": {"coordinates":[-0.91037884344273,51.53468686843217],"type":"Point"}
}