{
  "type": "Feature",
  "properties": {
    "iso:country": "GB",
    "wof:name": "RG9 1UG",
    "wof:placetype": "postalcode"
  },
  "geometry": {"coordinates":[-0.910379,51.534687],"type":"Point"}
}
