{
  "type": "Feature",
  "properties": {
    "date:inception_lower":"1995-01-01",
    "date:inception_upper":"1995-01-31",
    "iso:country":"GB",
    "wof:name":"TQ2 7SQ",
    "wof:placetype":"postalcode"
},
  "geometry": {"coordinates":[-3.557243,50.493045],"type":"Point"}
}