{
  "type": "Feature",
  "properties": {
    "iso:country":"GB",
    "wof:name":"TQ2 7SQ",
    "wof:placetype":"postalcode"
},
  "geometry": {"coordinates":[-3.55724352592936,50.49304454160294],"type":"Point"}
}