{
  "type": "Feature",
  "properties": {
    "date:inception_lower": "1980-01-01",
    "date:inception_upper": "1980-01-01",
    "iso:country": "GB",
    "wof:name": "CR0 8ED",
    "wof:placetype": "postalcode"
  },
  "geometry": {"coordinates":[-0.026699,51.377074],"type":"Point"}
}
