{
  "type": "Feature",
  "properties": {
    "iso:country":"GB",
    "wof:name":"CR0 8ED",
    "wof:placetype":"postalcode"
},
  "geometry": {"coordinates":[-0.0266995205151,51.37707353322606],"type":"Point"}
}