{
  "type": "Feature",
  "properties": {
    "iso:country":"GB",
    "wof:name":"W1W 7SQ",
    "wof:placetype":"postalcode"
},
  "geometry": {"coordinates":[-0.14083965799623,51.51761524342955],"type":"Point"}
}