{
  "type": "Feature",
  "properties": {
    "iso:country": "GB",
    "wof:name": "IP14 5HT",
    "wof:placetype": "postalcode"
  },
  "geometry": {"coordinates":[1.055433,52.189466],"type":"Point"}
}
