{
  "type": "Feature",
  "properties": {
    "date:inception_lower": "1980-01-01",
    "date:inception_upper": "1980-01-01",
    "iso:country": "GB",
    "wof:name": "TA4 3JB",
    "wof:placetype": "postalcode"
  },
  "geometry": {"coordinates":[-3.206093,51.08449],"type":"Point"}
}
