{
  "type": "Feature",
  "properties": {
    "iso:country":"GB",
    "wof:name":"TA4 3JB",
    "wof:placetype":"postalcode"
},
  "geometry": {"coordinates":[-3.20609349484181,51.08448998565029],"type":"Point"}
}