{
  "type": "Feature",
  "properties": {
    "iso:country": "GB",
    "wof:name": "TA4 3JB",
    "wof:placetype": "postalcode"
  },
  "geometry": {"coordinates":[-3.206093,51.08449],"type":"Point"}
}
