{
  "type": "Feature",
  "properties": {
    "iso:country":"GB",
    "wof:name":"LU7 4PZ",
    "wof:placetype":"postalcode"
},
  "geometry": {"coordinates":[-0.65303126451959,51.91386525386397],"type":"Point"}
}