{
  "type": "Feature",
  "properties": {
    "date:inception_lower": "1980-01-01",
    "date:inception_upper": "1980-01-01",
    "iso:country": "GB",
    "wof:name": "FK3 9XB",
    "wof:placetype": "postalcode"
  },
  "geometry": {"coordinates":[-3.703016,56.00827],"type":"Point"}
}
