{
  "type": "Feature",
  "properties": {
    "iso:country": "GB",
    "wof:name": "NR13 6DQ",
    "wof:placetype": "postalcode"
  },
  "geometry": {"coordinates":[1.496725,52.664838],"type":"Point"}
}
