{
  "type": "Feature",
  "properties": {
    "date:inception_lower": "1980-01-01",
    "date:inception_upper": "1980-01-01",
    "iso:country": "GB",
    "wof:name": "NR13 6DQ",
    "wof:placetype": "postalcode"
  },
  "geometry": {"coordinates":[1.496725,52.664838],"type":"Point"}
}
