{
  "type": "Feature",
  "properties": {
    "date:inception_lower":"1980-01-01",
    "date:inception_upper":"1980-01-31",
    "iso:country":"GB",
    "wof:name":"TN19 7BN",
    "wof:placetype":"postalcode"
},
  "geometry": {"coordinates":[0.387878,50.999934],"type":"Point"}
}