{
  "type": "Feature",
  "properties": {
    "iso:country":"GB",
    "wof:name":"TN19 7BN",
    "wof:placetype":"postalcode"
},
  "geometry": {"coordinates":[0.38787841005589,50.99993399174873],"type":"Point"}
}