{
  "type": "Feature",
  "properties": {
    "iso:country": "GB",
    "wof:name": "IP1 4DT",
    "wof:placetype": "postalcode"
  },
  "geometry": {"coordinates":[1.133947,52.068237],"type":"Point"}
}
