{
  "type": "Feature",
  "properties": {
    "iso:country":"GB",
    "wof:name":"GL54 2PN",
    "wof:placetype":"postalcode"
},
  "geometry": {"coordinates":[-1.72566869209937,51.89345061552349],"type":"Point"}
}