{
  "type": "Feature",
  "properties": {
    "date:inception_lower": "1980-01-01",
    "date:inception_upper": "1980-01-01",
    "iso:country": "GB",
    "wof:name": "GL54 2PN",
    "wof:placetype": "postalcode"
  },
  "geometry": {"coordinates":[-1.725669,51.893451],"type":"Point"}
}
