{
  "type": "Feature",
  "properties": {
    "iso:country":"GB",
    "wof:name":"GU29 0AY",
    "wof:placetype":"postalcode"
},
  "geometry": {"coordinates":[-0.71614071625611,50.98729317458029],"type":"Point"}
}