{
  "type": "Feature",
  "properties": {
    "iso:country":"GB",
    "wof:name":"EX11 1BU",
    "wof:placetype":"postalcode"
},
  "geometry": {"coordinates":[-3.27896210684933,50.75129559843257],"type":"Point"}
}