{
  "type": "Feature",
  "properties": {
    "iso:country":"GB",
    "wof:name":"DH7 8NP",
    "wof:placetype":"postalcode"
},
  "geometry": {"coordinates":[-1.63326723459904,54.75103190633285],"type":"Point"}
}