{
  "type": "Feature",
  "properties": {
    "iso:country":"GB",
    "wof:name":"BH24 3NW",
    "wof:placetype":"postalcode"
},
  "geometry": {"coordinates":[-1.779096129428,50.89057181702399],"type":"Point"}
}