{
  "type": "Feature",
  "properties": {
    "iso:country": "GB",
    "wof:name": "PO21 4LF",
    "wof:placetype": "postalcode"
  },
  "geometry": {"coordinates":[-0.723307,50.779232],"type":"Point"}
}
