{
  "type": "Feature",
  "properties": {
    "date:inception_lower": "1980-01-01",
    "date:inception_upper": "1980-01-01",
    "iso:country": "GB",
    "wof:name": "CT2 8AN",
    "wof:placetype": "postalcode"
  },
  "geometry": {"coordinates":[1.07581,51.283697],"type":"Point"}
}
