{
  "type": "Feature",
  "properties": {
    "iso:country": "GB",
    "wof:name": "NE30 3PS",
    "wof:placetype": "postalcode"
  },
  "geometry": {"coordinates":[-1.450381,55.026558],"type":"Point"}
}
