{
  "type": "Feature",
  "properties": {
    "date:inception_lower":"2006-08-01",
    "date:inception_upper":"2006-08-31",
    "iso:country":"GB",
    "wof:name":"NE30 3PS",
    "wof:placetype":"postalcode"
},
  "geometry": {"coordinates":[-1.450381,55.026558],"type":"Point"}
}