{
  "type": "Feature",
  "properties": {
    "date:inception_lower":"1980-01-01",
    "date:inception_upper":"1980-01-31",
    "iso:country":"GB",
    "wof:name":"LS17 7TL",
    "wof:placetype":"postalcode"
},
  "geometry": {"coordinates":[-1.545951,53.852799],"type":"Point"}
}