{
  "type": "Feature",
  "properties": {
    "date:inception_lower":"2000-12-01",
    "date:inception_upper":"2000-12-31",
    "iso:country":"GB",
    "wof:name":"W1U 7HP",
    "wof:placetype":"postalcode"
},
  "geometry": {"coordinates":[-0.154957,51.518153],"type":"Point"}
}