{
  "type": "Feature",
  "properties": {
    "iso:country":"GB",
    "wof:name":"W1U 7HP",
    "wof:placetype":"postalcode"
},
  "geometry": {"coordinates":[-0.15495747799108,51.51815290582925],"type":"Point"}
}