{
  "type": "Feature",
  "properties": {
    "iso:country": "GB",
    "wof:name": "W1U 7HP",
    "wof:placetype": "postalcode"
  },
  "geometry": {"coordinates":[-0.154957,51.518153],"type":"Point"}
}
