{
  "type": "Feature",
  "properties": {
    "iso:country": "GB",
    "wof:name": "CF62 4LA",
    "wof:placetype": "postalcode"
  },
  "geometry": {"coordinates":[-3.41585,51.415847],"type":"Point"}
}
