{
  "type": "Feature",
  "properties": {
    "date:inception_lower": "1993-01-01",
    "date:inception_upper": "1993-01-01",
    "iso:country": "GB",
    "wof:name": "CF62 4LA",
    "wof:placetype": "postalcode"
  },
  "geometry": {"coordinates":[-3.41585,51.415847],"type":"Point"}
}
