{
  "type": "Feature",
  "properties": {
    "iso:country":"GB",
    "wof:name":"CF62 4LA",
    "wof:placetype":"postalcode"
},
  "geometry": {"coordinates":[-3.41585011941704,51.41584665821163],"type":"Point"}
}