{
  "type": "Feature",
  "properties": {
    "iso:country": "GB",
    "wof:name": "CW11 1JQ",
    "wof:placetype": "postalcode"
  },
  "geometry": {"coordinates":[-2.385421,53.152412],"type":"Point"}
}
