{
  "type": "Feature",
  "properties": {
    "date:inception_lower": "1980-01-01",
    "date:inception_upper": "1980-01-01",
    "iso:country": "GB",
    "wof:name": "SE6 3TP",
    "wof:placetype": "postalcode"
  },
  "geometry": {"coordinates":[-0.02037,51.428181],"type":"Point"}
}
