{
  "type": "Feature",
  "properties": {
    "iso:country":"GB",
    "wof:name":"SE6 3TP",
    "wof:placetype":"postalcode"
},
  "geometry": {"coordinates":[-0.02036975047538,51.42818073654026],"type":"Point"}
}