{
  "type": "Feature",
  "properties": {
    "date:inception_lower": "1996-06-01",
    "date:inception_upper": "1996-06-01",
    "iso:country": "GB",
    "wof:name": "SA62 5TF",
    "wof:placetype": "postalcode"
  },
  "geometry": {"coordinates":[-4.999012,51.926199],"type":"Point"}
}
