{
  "type": "Feature",
  "properties": {
    "iso:country":"GB",
    "wof:name":"SA62 5TF",
    "wof:placetype":"postalcode"
},
  "geometry": {"coordinates":[-4.99896786933888,51.92618466526821],"type":"Point"}
}