{
  "type": "Feature",
  "properties": {
    "date:inception_lower": "2020-12-01",
    "date:inception_upper": "2020-12-01",
    "iso:country": "GB",
    "wof:name": "TW5 0DS",
    "wof:placetype": "postalcode"
  },
  "geometry": {"coordinates":[-0.373602,51.478864],"type":"Point"}
}
