{
  "type": "Feature",
  "properties": {
    "iso:country":"GB",
    "wof:name":"G23 5EH",
    "wof:placetype":"postalcode"
},
  "geometry": {"coordinates":[-4.27428033867036,55.8980492528673],"type":"Point"}
}