{
  "type": "Feature",
  "properties": {
    "date:inception_lower": "1980-01-01",
    "date:inception_upper": "1980-01-01",
    "iso:country": "GB",
    "wof:name": "G23 5EH",
    "wof:placetype": "postalcode"
  },
  "geometry": {"coordinates":[-4.274266,55.898044],"type":"Point"}
}
