{
  "type": "Feature",
  "properties": {
    "iso:country":"GB",
    "wof:name":"CM19 5TF",
    "wof:placetype":"postalcode"
},
  "geometry": {"coordinates":[0.07335879569734,51.76341595249247],"type":"Point"}
}