{
  "type": "Feature",
  "properties": {
    "date:inception_lower": "1980-01-01",
    "date:inception_upper": "1980-01-01",
    "iso:country": "GB",
    "wof:name": "S5 7SR",
    "wof:placetype": "postalcode"
  },
  "geometry": {"coordinates":[-1.460021,53.424545],"type":"Point"}
}
