{
  "type": "Feature",
  "properties": {
    "iso:country":"GB",
    "wof:name":"PL30 4LQ",
    "wof:placetype":"postalcode"
},
  "geometry": {"coordinates":[-4.67121788994894,50.54492036831486],"type":"Point"}
}