{
  "type": "Feature",
  "properties": {
    "iso:country":"GB",
    "wof:name":"GL3 4UW",
    "wof:placetype":"postalcode"
},
  "geometry": {"coordinates":[-2.17237841528429,51.83845689860417],"type":"Point"}
}