{
  "type": "Feature",
  "properties": {
    "date:inception_lower": "2015-09-01",
    "date:inception_upper": "2015-09-01",
    "iso:country": "GB",
    "wof:name": "GL3 4UW",
    "wof:placetype": "postalcode"
  },
  "geometry": {"coordinates":[-2.172213,51.838365],"type":"Point"}
}
