{
  "type": "Feature",
  "properties": {
    "iso:country":"GB",
    "wof:name":"ST1 6PS",
    "wof:placetype":"postalcode"
},
  "geometry": {"coordinates":[-2.15986477233888,53.03084118900477],"type":"Point"}
}