{
  "type": "Feature",
  "properties": {
    "iso:country":"GB",
    "wof:name":"SW15 3DU",
    "wof:placetype":"postalcode"
},
  "geometry": {"coordinates":[-0.2498382975083,51.4377218741428],"type":"Point"}
}