{
  "type": "Feature",
  "properties": {
    "iso:country":"GB",
    "wof:name":"CV10 0TP",
    "wof:placetype":"postalcode"
},
  "geometry": {"coordinates":[-1.46261439962034,52.54272496257196],"type":"Point"}
}