{
  "type": "Feature",
  "properties": {
    "iso:country":"GB",
    "wof:name":"BN12 4HY",
    "wof:placetype":"postalcode"
},
  "geometry": {"coordinates":[-0.41558107678219,50.80884965129168],"type":"Point"}
}