{
  "type": "Feature",
  "properties": {
    "iso:country":"GB",
    "wof:name":"WA15 9BT",
    "wof:placetype":"postalcode"
},
  "geometry": {"coordinates":[-2.34129829371508,53.37490430460934],"type":"Point"}
}