{
  "type": "Feature",
  "properties": {
    "iso:country": "GB",
    "wof:name": "CW1 2PY",
    "wof:placetype": "postalcode"
  },
  "geometry": {"coordinates":[-2.447276,53.099987],"type":"Point"}
}
