{
  "type": "Feature",
  "properties": {
    "date:inception_lower":"1985-10-01",
    "date:inception_upper":"1985-10-31",
    "iso:country":"GB",
    "wof:name":"CW1 2PY",
    "wof:placetype":"postalcode"
},
  "geometry": {"coordinates":[-2.447276,53.099987],"type":"Point"}
}