{
  "type": "Feature",
  "properties": {
    "iso:country":"GB",
    "wof:name":"CW1 2PY",
    "wof:placetype":"postalcode"
},
  "geometry": {"coordinates":[-2.44697832363378,53.10007069263943],"type":"Point"}
}