{
  "type": "Feature",
  "properties": {
    "iso:country":"GB",
    "wof:name":"G84 8TQ",
    "wof:placetype":"postalcode"
},
  "geometry": {"coordinates":[-4.73294088092522,56.00430146288705],"type":"Point"}
}