{
  "type": "Feature",
  "properties": {
    "iso:country": "GB",
    "wof:name": "PL25 3SX",
    "wof:placetype": "postalcode"
  },
  "geometry": {"coordinates":[-4.780461,50.354415],"type":"Point"}
}
