{
  "type": "Feature",
  "properties": {
    "date:inception_lower": "2004-09-01",
    "date:inception_upper": "2004-09-01",
    "iso:country": "GB",
    "wof:name": "PL25 3SX",
    "wof:placetype": "postalcode"
  },
  "geometry": {"coordinates":[-4.780461,50.354415],"type":"Point"}
}
