{
  "type": "Feature",
  "properties": {
    "iso:country":"GB",
    "wof:name":"PL25 3SX",
    "wof:placetype":"postalcode"
},
  "geometry": {"coordinates":[-4.78044551258083,50.35439111541668],"type":"Point"}
}