{
  "type": "Feature",
  "properties": {
    "iso:country":"GB",
    "wof:name":"TA8 1EQ",
    "wof:placetype":"postalcode"
},
  "geometry": {"coordinates":[-2.99703622536657,51.23790830376961],"type":"Point"}
}