{
  "type": "Feature",
  "properties": {
    "iso:country":"GB",
    "wof:name":"ME15 6SF",
    "wof:placetype":"postalcode"
},
  "geometry": {"coordinates":[0.52737911926545,51.27267867793154],"type":"Point"}
}