{
  "type": "Feature",
  "properties": {
    "iso:country":"GB",
    "wof:name":"SA3 5HG",
    "wof:placetype":"postalcode"
},
  "geometry": {"coordinates":[-4.01636739411969,51.59183295021837],"type":"Point"}
}