{
  "type": "Feature",
  "properties": {
    "date:inception_lower":"1980-01-01",
    "date:inception_upper":"1980-01-31",
    "iso:country":"GB",
    "wof:name":"SA3 5HG",
    "wof:placetype":"postalcode"
},
  "geometry": {"coordinates":[-4.016367,51.591833],"type":"Point"}
}