{
  "type": "Feature",
  "properties": {
    "date:inception_lower":"2002-08-01",
    "date:inception_upper":"2002-08-31",
    "iso:country":"GB",
    "wof:name":"ME17 4UW",
    "wof:placetype":"postalcode"
},
  "geometry": {"coordinates":[0.546691,51.242832],"type":"Point"}
}