{
  "type": "Feature",
  "properties": {
    "date:inception_lower": "1980-01-01",
    "date:inception_upper": "1980-01-01",
    "iso:country": "GB",
    "wof:name": "LE5 4EB",
    "wof:placetype": "postalcode"
  },
  "geometry": {"coordinates":[-1.080153,52.637312],"type":"Point"}
}
