{
  "type": "Feature",
  "properties": {
    "iso:country": "GB",
    "wof:name": "LE5 4EB",
    "wof:placetype": "postalcode"
  },
  "geometry": {"coordinates":[-1.080095,52.637249],"type":"Point"}
}
