{
  "type": "Feature",
  "properties": {
    "date:inception_lower": "2021-11-01",
    "date:inception_upper": "2021-11-01",
    "iso:country": "GB",
    "wof:name": "S81 7FZ",
    "wof:placetype": "postalcode"
  },
  "geometry": {"coordinates":[-1.137888,53.335986],"type":"Point"}
}
