{
  "type": "Feature",
  "properties": {
    "iso:country":"GB",
    "wof:name":"PL24 2EQ",
    "wof:placetype":"postalcode"
},
  "geometry": {"coordinates":[-4.72937220826717,50.35080753191927],"type":"Point"}
}