{
  "type": "Feature",
  "properties": {
    "iso:country":"GB",
    "wof:name":"TR18 5PA",
    "wof:placetype":"postalcode"
},
  "geometry": {"coordinates":[-5.54602886524664,50.10108169995392],"type":"Point"}
}