{
  "type": "Feature",
  "properties": {
    "iso:country":"GB",
    "wof:name":"HD5 9SW",
    "wof:placetype":"postalcode"
},
  "geometry": {"coordinates":[-1.74482849863277,53.65088524867667],"type":"Point"}
}