{
  "type": "Feature",
  "properties": {
    "iso:country": "GB",
    "wof:name": "HD5 9SW",
    "wof:placetype": "postalcode"
  },
  "geometry": {"coordinates":[-1.744828,53.650885],"type":"Point"}
}
