{
  "type": "Feature",
  "properties": {
    "iso:country": "GB",
    "wof:name": "CF62 7HL",
    "wof:placetype": "postalcode"
  },
  "geometry": {"coordinates":[-3.284995,51.40384],"type":"Point"}
}
