{
  "type": "Feature",
  "properties": {
    "iso:country":"GB",
    "wof:name":"CW3 9RR",
    "wof:placetype":"postalcode"
},
  "geometry": {"coordinates":[-2.40433704415042,52.96605981422551],"type":"Point"}
}