{
  "type": "Feature",
  "properties": {
    "iso:country":"GB",
    "wof:name":"TD14 5PR",
    "wof:placetype":"postalcode"
},
  "geometry": {"coordinates":[-2.12976055311612,55.89792707183745],"type":"Point"}
}