{
  "type": "Feature",
  "properties": {
    "iso:country":"GB",
    "wof:name":"RM3 8HR",
    "wof:placetype":"postalcode"
},
  "geometry": {"coordinates":[0.22206848334901,51.60665252921709],"type":"Point"}
}