{
  "type": "Feature",
  "properties": {
    "iso:country":"GB",
    "wof:name":"EX18 7QA",
    "wof:placetype":"postalcode"
},
  "geometry": {"coordinates":[-3.91816025483659,50.88030227649443],"type":"Point"}
}