{
  "type": "Feature",
  "properties": {
    "iso:country":"GB",
    "wof:name":"WD19 7PF",
    "wof:placetype":"postalcode"
},
  "geometry": {"coordinates":[-0.40622338823564,51.62754750865883],"type":"Point"}
}