{
  "type": "Feature",
  "properties": {
    "iso:country":"GB",
    "wof:name":"DA17 6DP",
    "wof:placetype":"postalcode"
},
  "geometry": {"coordinates":[0.1530176166256,51.48929728950399],"type":"Point"}
}