{
  "type": "Feature",
  "properties": {
    "iso:country":"GB",
    "wof:name":"CV34 4DD",
    "wof:placetype":"postalcode"
},
  "geometry": {"coordinates":[-1.59123739580016,52.28010682267282],"type":"Point"}
}