{
  "type": "Feature",
  "properties": {
    "date:inception_lower": "1980-01-01",
    "date:inception_upper": "1980-01-01",
    "iso:country": "GB",
    "wof:name": "LL54 6LA",
    "wof:placetype": "postalcode"
  },
  "geometry": {"coordinates":[-4.262415,53.052948],"type":"Point"}
}
