{
  "type": "Feature",
  "properties": {
    "iso:country":"GB",
    "wof:name":"LL54 6LA",
    "wof:placetype":"postalcode"
},
  "geometry": {"coordinates":[-4.26241475731431,53.05294754788954],"type":"Point"}
}