{
  "type": "Feature",
  "properties": {
    "date:inception_lower":"1992-08-01",
    "date:inception_upper":"1992-08-31",
    "iso:country":"GB",
    "wof:name":"DE24 0JZ",
    "wof:placetype":"postalcode"
},
  "geometry": {"coordinates":[-1.425033,52.887052],"type":"Point"}
}