{
  "type": "Feature",
  "properties": {
    "iso:country":"GB",
    "wof:name":"GU11 3AS",
    "wof:placetype":"postalcode"
},
  "geometry": {"coordinates":[-0.77579997646644,51.2439586952657],"type":"Point"}
}