{
  "type": "Feature",
  "properties": {
    "iso:country":"GB",
    "wof:name":"HP5 2DZ",
    "wof:placetype":"postalcode"
},
  "geometry": {"coordinates":[-0.61209266314184,51.71823607139959],"type":"Point"}
}