{
  "type": "Feature",
  "properties": {
    "date:inception_lower":"1980-01-01",
    "date:inception_upper":"1980-01-31",
    "iso:country":"GB",
    "wof:name":"GU29 0QD",
    "wof:placetype":"postalcode"
},
  "geometry": {"coordinates":[-0.763155,51.021712],"type":"Point"}
}