{
  "type": "Feature",
  "properties": {
    "iso:country": "GB",
    "wof:name": "OL3 5SU",
    "wof:placetype": "postalcode"
  },
  "geometry": {"coordinates":[-2.045969,53.581444],"type":"Point"}
}
