{
  "type": "Feature",
  "properties": {
    "date:inception_lower": "2005-07-01",
    "date:inception_upper": "2005-07-01",
    "iso:country": "GB",
    "wof:name": "PO10 8FB",
    "wof:placetype": "postalcode"
  },
  "geometry": {"coordinates":[-0.907431,50.84862],"type":"Point"}
}
