{
  "type": "Feature",
  "properties": {
    "iso:country":"GB",
    "wof:name":"SO40 8BT",
    "wof:placetype":"postalcode"
},
  "geometry": {"coordinates":[-1.50561706240882,50.9167749478075],"type":"Point"}
}