{
  "type": "Feature",
  "properties": {
    "iso:country": "GB",
    "wof:name": "NG19 8ER",
    "wof:placetype": "postalcode"
  },
  "geometry": {"coordinates":[-1.194521,53.165885],"type":"Point"}
}
