{
  "type": "Feature",
  "properties": {
    "iso:country": "GB",
    "wof:name": "YO62 4LH",
    "wof:placetype": "postalcode"
  },
  "geometry": {"coordinates":[-0.963435,54.192562],"type":"Point"}
}
