{
  "type": "Feature",
  "properties": {
    "date:inception_lower": "1998-06-01",
    "date:inception_upper": "1998-06-01",
    "iso:country": "GB",
    "wof:name": "YO62 4LH",
    "wof:placetype": "postalcode"
  },
  "geometry": {"coordinates":[-0.963912,54.192367],"type":"Point"}
}
