{
  "type": "Feature",
  "properties": {
    "iso:country":"GB",
    "wof:name":"E1 7NB",
    "wof:placetype":"postalcode"
},
  "geometry": {"coordinates":[-0.0756895629372,51.51798528782219],"type":"Point"}
}