{
  "type": "Feature",
  "properties": {
    "date:inception_lower": "1980-01-01",
    "date:inception_upper": "1980-01-01",
    "iso:country": "GB",
    "wof:name": "NG23 5SL",
    "wof:placetype": "postalcode"
  },
  "geometry": {"coordinates":[-0.892102,53.055628],"type":"Point"}
}
