{
  "type": "Feature",
  "properties": {
    "iso:country":"GB",
    "wof:name":"LE17 4GP",
    "wof:placetype":"postalcode"
},
  "geometry": {"coordinates":[-1.21955521781361,52.45768338299201],"type":"Point"}
}