{
  "type": "Feature",
  "properties": {
    "iso:country": "GB",
    "wof:name": "LE17 4GP",
    "wof:placetype": "postalcode"
  },
  "geometry": {"coordinates":[-1.219555,52.457683],"type":"Point"}
}
