{
  "type": "Feature",
  "properties": {
    "iso:country":"GB",
    "wof:name":"SG1 2AL",
    "wof:placetype":"postalcode"
},
  "geometry": {"coordinates":[-0.2182929454458,51.91440836323313],"type":"Point"}
}