{
  "type": "Feature",
  "properties": {
    "iso:country": "GB",
    "wof:name": "WF10 3JR",
    "wof:placetype": "postalcode"
  },
  "geometry": {"coordinates":[-1.315072,53.722795],"type":"Point"}
}
