{
  "type": "Feature",
  "properties": {
    "date:inception_lower": "1980-01-01",
    "date:inception_upper": "1980-01-01",
    "iso:country": "GB",
    "wof:name": "B33 9JL",
    "wof:placetype": "postalcode"
  },
  "geometry": {"coordinates":[-1.800706,52.490502],"type":"Point"}
}
