{
  "type": "Feature",
  "properties": {
    "iso:country":"GB",
    "wof:name":"HA1 4LZ",
    "wof:placetype":"postalcode"
},
  "geometry": {"coordinates":[-0.35185765634503,51.58323897816843],"type":"Point"}
}