{
  "type": "Feature",
  "properties": {
    "iso:country": "GB",
    "wof:name": "TN23 4FH",
    "wof:placetype": "postalcode"
  },
  "geometry": {"coordinates":[0.858673,51.145843],"type":"Point"}
}
