{
  "type": "Feature",
  "properties": {
    "iso:country":"GB",
    "wof:name":"WV8 1TT",
    "wof:placetype":"postalcode"
},
  "geometry": {"coordinates":[-2.15453480626961,52.61972522137451],"type":"Point"}
}