{
  "type": "Feature",
  "properties": {
    "date:inception_lower": "1980-01-01",
    "date:inception_upper": "1980-01-01",
    "iso:country": "GB",
    "wof:name": "WV8 1TT",
    "wof:placetype": "postalcode"
  },
  "geometry": {"coordinates":[-2.154535,52.619725],"type":"Point"}
}
