{
  "type": "Feature",
  "properties": {
    "date:inception_lower":"1983-04-01",
    "date:inception_upper":"1983-04-30",
    "iso:country":"GB",
    "wof:name":"PA34 4LE",
    "wof:placetype":"postalcode"
},
  "geometry": {"coordinates":[-5.487368,56.406021],"type":"Point"}
}