{
  "type": "Feature",
  "properties": {
    "iso:country":"GB",
    "wof:name":"NR25 9AG",
    "wof:placetype":"postalcode"
},
  "geometry": {"coordinates":[1.09064437813282,52.90671393941676],"type":"Point"}
}