{
  "type": "Feature",
  "properties": {
    "date:inception_lower": "2021-05-01",
    "date:inception_upper": "2021-05-01",
    "iso:country": "GB",
    "wof:name": "WR9 7UP",
    "wof:placetype": "postalcode"
  },
  "geometry": {"coordinates":[-2.173248,52.253945],"type":"Point"}
}
