{
  "type": "Feature",
  "properties": {
    "date:inception_lower":"1990-02-01",
    "date:inception_upper":"1990-02-28",
    "iso:country":"GB",
    "wof:name":"HU17 7JQ",
    "wof:placetype":"postalcode"
},
  "geometry": {"coordinates":[-0.436685,53.85464],"type":"Point"}
}