{
  "type": "Feature",
  "properties": {
    "iso:country":"GB",
    "wof:name":"NP19 0DQ",
    "wof:placetype":"postalcode"
},
  "geometry": {"coordinates":[-2.98215749732119,51.58629009833655],"type":"Point"}
}