{
  "type": "Feature",
  "properties": {
    "iso:country":"GB",
    "wof:name":"CT6 5RY",
    "wof:placetype":"postalcode"
},
  "geometry": {"coordinates":[1.12010470890488,51.3606962076183],"type":"Point"}
}