{
  "type": "Feature",
  "properties": {
    "iso:country": "GB",
    "wof:name": "NE66 4SD",
    "wof:placetype": "postalcode"
  },
  "geometry": {"coordinates":[-1.853418,55.381358],"type":"Point"}
}
