{
  "type": "Feature",
  "properties": {
    "iso:country":"GB",
    "wof:name":"NE66 4SD",
    "wof:placetype":"postalcode"
},
  "geometry": {"coordinates":[-1.85341778175415,55.38135758726608],"type":"Point"}
}