{
  "type": "Feature",
  "properties": {
    "date:inception_lower": "1980-01-01",
    "date:inception_upper": "1980-01-01",
    "iso:country": "GB",
    "wof:name": "EX31 3PT",
    "wof:placetype": "postalcode"
  },
  "geometry": {"coordinates":[-4.112223,51.00715],"type":"Point"}
}
