{
  "type": "Feature",
  "properties": {
    "iso:country":"GB",
    "wof:name":"TQ3 3FF",
    "wof:placetype":"postalcode"
},
  "geometry": {"coordinates":[-3.56952936963323,50.43747826163118],"type":"Point"}
}