{
  "type": "Feature",
  "properties": {
    "date:inception_lower":"2009-12-01",
    "date:inception_upper":"2009-12-31",
    "iso:country":"GB",
    "wof:name":"TQ3 3FF",
    "wof:placetype":"postalcode"
},
  "geometry": {"coordinates":[-3.569529,50.437478],"type":"Point"}
}