{
  "type": "Feature",
  "properties": {
    "iso:country":"GB",
    "wof:name":"EX1 1GQ",
    "wof:placetype":"postalcode"
},
  "geometry": {"coordinates":[-3.52824356741852,50.72465095412946],"type":"Point"}
}