{
  "type": "Feature",
  "properties": {
    "iso:country":"GB",
    "wof:name":"B93 0EB",
    "wof:placetype":"postalcode"
},
  "geometry": {"coordinates":[-1.71636681456698,52.37266807083375],"type":"Point"}
}