{
  "type": "Feature",
  "properties": {
    "date:inception_lower": "1980-01-01",
    "date:inception_upper": "1980-01-01",
    "iso:country": "GB",
    "wof:name": "B93 0EB",
    "wof:placetype": "postalcode"
  },
  "geometry": {"coordinates":[-1.716211,52.37271],"type":"Point"}
}
