{
  "type": "Feature",
  "properties": {
    "iso:country": "GB",
    "wof:name": "E15 3EG",
    "wof:placetype": "postalcode"
  },
  "geometry": {"coordinates":[0.012883,51.532685],"type":"Point"}
}
