{
  "type": "Feature",
  "properties": {
    "iso:country":"GB",
    "wof:name":"WV7 3NP",
    "wof:placetype":"postalcode"
},
  "geometry": {"coordinates":[-2.29237013519308,52.64520261425132],"type":"Point"}
}