{
  "type": "Feature",
  "properties": {
    "date:inception_lower":"1980-01-01",
    "date:inception_upper":"1980-01-31",
    "iso:country":"GB",
    "wof:name":"WV7 3NP",
    "wof:placetype":"postalcode"
},
  "geometry": {"coordinates":[-2.29237,52.645203],"type":"Point"}
}