{
  "type": "Feature",
  "properties": {
    "iso:country":"GB",
    "wof:name":"BD21 1RJ",
    "wof:placetype":"postalcode"
},
  "geometry": {"coordinates":[-1.92234526029056,53.86031877890114],"type":"Point"}
}