{
  "type": "Feature",
  "properties": {
    "iso:country": "GB",
    "wof:name": "S20 2QB",
    "wof:placetype": "postalcode"
  },
  "geometry": {"coordinates":[-1.335847,53.338159],"type":"Point"}
}
