{
  "type": "Feature",
  "properties": {
    "iso:country": "GB",
    "wof:name": "GL53 8EU",
    "wof:placetype": "postalcode"
  },
  "geometry": {"coordinates":[-2.052911,51.872413],"type":"Point"}
}
