{
  "type": "Feature",
  "properties": {
    "date:inception_lower": "2024-01-01",
    "date:inception_upper": "2024-01-01",
    "iso:country": "GB",
    "wof:name": "PL11 3FE",
    "wof:placetype": "postalcode"
  },
  "geometry": {"coordinates":[-4.393637,50.366092],"type":"Point"}
}
