{
  "type": "Feature",
  "properties": {
    "date:inception_lower":"1996-06-01",
    "date:inception_upper":"1996-06-30",
    "iso:country":"GB",
    "wof:name":"SL5 0AJ",
    "wof:placetype":"postalcode"
},
  "geometry": {"coordinates":[-0.645104,51.398616],"type":"Point"}
}