{
  "type": "Feature",
  "properties": {
    "iso:country":"GB",
    "wof:name":"G34 9QQ",
    "wof:placetype":"postalcode"
},
  "geometry": {"coordinates":[-4.12429041016921,55.8729231843008],"type":"Point"}
}