{
  "type": "Feature",
  "properties": {
    "date:inception_lower": "1980-01-01",
    "date:inception_upper": "1980-01-01",
    "iso:country": "GB",
    "wof:name": "G34 9QQ",
    "wof:placetype": "postalcode"
  },
  "geometry": {"coordinates":[-4.124671,55.873168],"type":"Point"}
}
