{
  "type": "Feature",
  "properties": {
    "date:inception_lower": "2012-11-01",
    "date:inception_upper": "2012-11-01",
    "iso:country": "GB",
    "wof:name": "SP5 2BL",
    "wof:placetype": "postalcode"
  },
  "geometry": {"coordinates":[-1.722292,50.989537],"type":"Point"}
}
