{
  "type": "Feature",
  "properties": {
    "iso:country":"GB",
    "wof:name":"SP5 2BL",
    "wof:placetype":"postalcode"
},
  "geometry": {"coordinates":[-1.72229228757743,50.98953736438696],"type":"Point"}
}