{
  "type": "Feature",
  "properties": {
    "date:inception_lower": "2005-05-01",
    "date:inception_upper": "2005-05-01",
    "iso:country": "GB",
    "wof:name": "CB4 1QD",
    "wof:placetype": "postalcode"
  },
  "geometry": {"coordinates":[0.135564,52.218369],"type":"Point"}
}
