{
  "type": "Feature",
  "properties": {
    "iso:country": "GB",
    "wof:name": "CB4 1QD",
    "wof:placetype": "postalcode"
  },
  "geometry": {"coordinates":[0.135564,52.218369],"type":"Point"}
}
