{
  "type": "Feature",
  "properties": {
    "iso:country":"GB",
    "wof:name":"CB4 1QD",
    "wof:placetype":"postalcode"
},
  "geometry": {"coordinates":[0.13556358763934,52.21836909491383],"type":"Point"}
}