{
  "type": "Feature",
  "properties": {
    "date:inception_lower": "2001-12-01",
    "date:inception_upper": "2001-12-01",
    "iso:country": "GB",
    "wof:name": "NG32 2FH",
    "wof:placetype": "postalcode"
  },
  "geometry": {"coordinates":[-0.721845,52.947653],"type":"Point"}
}
