{
  "type": "Feature",
  "properties": {
    "iso:country":"GB",
    "wof:name":"NG32 2FH",
    "wof:placetype":"postalcode"
},
  "geometry": {"coordinates":[-0.72184467624072,52.94765303500966],"type":"Point"}
}