{
  "type": "Feature",
  "properties": {
    "iso:country": "GB",
    "wof:name": "NG32 2FH",
    "wof:placetype": "postalcode"
  },
  "geometry": {"coordinates":[-0.721845,52.947653],"type":"Point"}
}
