{
  "type": "Feature",
  "properties": {
    "iso:country": "GB",
    "wof:name": "SR6 9TR",
    "wof:placetype": "postalcode"
  },
  "geometry": {"coordinates":[-1.376828,54.921612],"type":"Point"}
}
