{
  "type": "Feature",
  "properties": {
    "iso:country":"GB",
    "wof:name":"SR6 9TR",
    "wof:placetype":"postalcode"
},
  "geometry": {"coordinates":[-1.37682843111797,54.92161164764592],"type":"Point"}
}