{
  "type": "Feature",
  "properties": {
    "iso:country":"GB",
    "wof:name":"BN10 8TD",
    "wof:placetype":"postalcode"
},
  "geometry": {"coordinates":[0.01764966543119,50.78981245246887],"type":"Point"}
}