{
  "type": "Feature",
  "properties": {
    "iso:country": "GB",
    "wof:name": "BN10 8TD",
    "wof:placetype": "postalcode"
  },
  "geometry": {"coordinates":[0.01765,50.789812],"type":"Point"}
}
