{
  "type": "Feature",
  "properties": {
    "iso:country":"GB",
    "wof:name":"E7 9BN",
    "wof:placetype":"postalcode"
},
  "geometry": {"coordinates":[0.01821309398422,51.55182016572606],"type":"Point"}
}