{
  "type": "Feature",
  "properties": {
    "iso:country":"GB",
    "wof:name":"BN2 5UP",
    "wof:placetype":"postalcode"
},
  "geometry": {"coordinates":[-0.10176213699208,50.81077545907029],"type":"Point"}
}