{
  "type": "Feature",
  "properties": {
    "iso:country": "GB",
    "wof:name": "PO18 8JD",
    "wof:placetype": "postalcode"
  },
  "geometry": {"coordinates":[-0.853885,50.829761],"type":"Point"}
}
