{
  "type": "Feature",
  "properties": {
    "date:inception_lower":"1980-01-01",
    "date:inception_upper":"1980-01-31",
    "iso:country":"GB",
    "wof:name":"PO18 8JD",
    "wof:placetype":"postalcode"
},
  "geometry": {"coordinates":[-0.853885,50.829761],"type":"Point"}
}