{
  "type": "Feature",
  "properties": {
    "iso:country":"GB",
    "wof:name":"CT16 3EY",
    "wof:placetype":"postalcode"
},
  "geometry": {"coordinates":[1.2866549474339,51.16132367974166],"type":"Point"}
}