{
  "type": "Feature",
  "properties": {
    "iso:country": "GB",
    "wof:name": "SW19 8RG",
    "wof:placetype": "postalcode"
  },
  "geometry": {"coordinates":[-0.19968,51.420182],"type":"Point"}
}
