{
  "type": "Feature",
  "properties": {
    "iso:country":"GB",
    "wof:name":"CW11 3BU",
    "wof:placetype":"postalcode"
},
  "geometry": {"coordinates":[-2.38736207033633,53.15205656061879],"type":"Point"}
}