{
  "type": "Feature",
  "properties": {
    "date:inception_lower": "1995-12-01",
    "date:inception_upper": "1995-12-01",
    "iso:country": "GB",
    "wof:name": "CW11 3BU",
    "wof:placetype": "postalcode"
  },
  "geometry": {"coordinates":[-2.387288,53.152181],"type":"Point"}
}
