{
  "type": "Feature",
  "properties": {
    "iso:country":"GB",
    "wof:name":"S4 7BH",
    "wof:placetype":"postalcode"
},
  "geometry": {"coordinates":[-1.45498305122168,53.40079250728874],"type":"Point"}
}