{
  "type": "Feature",
  "properties": {
    "iso:country": "GB",
    "wof:name": "DA11 0SQ",
    "wof:placetype": "postalcode"
  },
  "geometry": {"coordinates":[0.363288,51.438223],"type":"Point"}
}
