{
  "type": "Feature",
  "properties": {
    "iso:country": "GB",
    "wof:name": "LE4 2BF",
    "wof:placetype": "postalcode"
  },
  "geometry": {"coordinates":[-1.145955,52.659785],"type":"Point"}
}
