{
  "type": "Feature",
  "properties": {
    "iso:country":"GB",
    "wof:name":"OL14 7QF",
    "wof:placetype":"postalcode"
},
  "geometry": {"coordinates":[-2.10484168024242,53.69586243931655],"type":"Point"}
}