{
  "type": "Feature",
  "properties": {
    "iso:country":"GB",
    "wof:name":"M31 4HB",
    "wof:placetype":"postalcode"
},
  "geometry": {"coordinates":[-2.43812827310677,53.41589978324522],"type":"Point"}
}