{
  "type": "Feature",
  "properties": {
    "iso:country": "GB",
    "wof:name": "ML4 2DZ",
    "wof:placetype": "postalcode"
  },
  "geometry": {"coordinates":[-4.023392,55.816029],"type":"Point"}
}
