{
  "type": "Feature",
  "properties": {
    "iso:country":"GB",
    "wof:name":"CT15 5DH",
    "wof:placetype":"postalcode"
},
  "geometry": {"coordinates":[1.34344828150702,51.19532475212351],"type":"Point"}
}