{
  "type": "Feature",
  "properties": {
    "iso:country": "GB",
    "wof:name": "TN12 9TT",
    "wof:placetype": "postalcode"
  },
  "geometry": {"coordinates":[0.494635,51.173164],"type":"Point"}
}
