{
  "type": "Feature",
  "properties": {
    "iso:country": "GB",
    "wof:name": "BD24 9LR",
    "wof:placetype": "postalcode"
  },
  "geometry": {"coordinates":[-2.278459,54.074791],"type":"Point"}
}
