{
  "type": "Feature",
  "properties": {
    "iso:country":"GB",
    "wof:name":"BD24 9LR",
    "wof:placetype":"postalcode"
},
  "geometry": {"coordinates":[-2.27845953200598,54.0747909404193],"type":"Point"}
}