{
  "type": "Feature",
  "properties": {
    "date:inception_lower": "1980-01-01",
    "date:inception_upper": "1980-01-01",
    "iso:country": "GB",
    "wof:name": "BD24 9LR",
    "wof:placetype": "postalcode"
  },
  "geometry": {"coordinates":[-2.278459,54.074791],"type":"Point"}
}
