{
  "type": "Feature",
  "properties": {
    "iso:country": "GB",
    "wof:name": "EC2R 6LL",
    "wof:placetype": "postalcode"
  },
  "geometry": {"coordinates":[-0.089175,51.516472],"type":"Point"}
}
