{
  "type": "Feature",
  "properties": {
    "date:inception_lower": "2005-12-01",
    "date:inception_upper": "2005-12-01",
    "iso:country": "GB",
    "wof:name": "EC2R 6LL",
    "wof:placetype": "postalcode"
  },
  "geometry": {"coordinates":[-0.089126,51.516597],"type":"Point"}
}
