{
  "type": "Feature",
  "properties": {
    "iso:country":"GB",
    "wof:name":"EC2R 6LL",
    "wof:placetype":"postalcode"
},
  "geometry": {"coordinates":[-0.08915240863861,51.51659572411464],"type":"Point"}
}