{
  "type": "Feature",
  "properties": {
    "iso:country": "GB",
    "wof:name": "AB54 7SS",
    "wof:placetype": "postalcode"
  },
  "geometry": {"coordinates":[-2.602572,57.561077],"type":"Point"}
}
