{
  "type": "Feature",
  "properties": {
    "date:inception_lower":"1996-06-01",
    "date:inception_upper":"1996-06-30",
    "iso:country":"GB",
    "wof:name":"AB54 7SS",
    "wof:placetype":"postalcode"
},
  "geometry": {"coordinates":[-2.602572,57.561077],"type":"Point"}
}