{
  "type": "Feature",
  "properties": {
    "iso:country": "GB",
    "wof:name": "SO15 5WD",
    "wof:placetype": "postalcode"
  },
  "geometry": {"coordinates":[-1.414852,50.911599],"type":"Point"}
}
