{
  "type": "Feature",
  "properties": {
    "date:inception_lower": "2019-02-01",
    "date:inception_upper": "2019-02-01",
    "iso:country": "GB",
    "wof:name": "SK10 4JY",
    "wof:placetype": "postalcode"
  },
  "geometry": {"coordinates":[-2.23384,53.270642],"type":"Point"}
}
