{
  "type": "Feature",
  "properties": {
    "date:inception_lower": "1980-01-01",
    "date:inception_upper": "1980-01-01",
    "iso:country": "GB",
    "wof:name": "S42 6QL",
    "wof:placetype": "postalcode"
  },
  "geometry": {"coordinates":[-1.433135,53.200762],"type":"Point"}
}
