{
  "type": "Feature",
  "properties": {
    "iso:country": "GB",
    "wof:name": "S42 6QL",
    "wof:placetype": "postalcode"
  },
  "geometry": {"coordinates":[-1.433135,53.200762],"type":"Point"}
}
