{
  "type": "Feature",
  "properties": {
    "date:inception_lower":"1999-06-01",
    "date:inception_upper":"1999-06-30",
    "iso:country":"GB",
    "wof:name":"NP12 0SA",
    "wof:placetype":"postalcode"
},
  "geometry": {"coordinates":[-3.214983,51.713135],"type":"Point"}
}