{
  "type": "Feature",
  "properties": {
    "iso:country":"GB",
    "wof:name":"NP12 0SA",
    "wof:placetype":"postalcode"
},
  "geometry": {"coordinates":[-3.21692389528379,51.71352571021209],"type":"Point"}
}