{
  "type": "Feature",
  "properties": {
    "date:inception_lower": "2013-07-01",
    "date:inception_upper": "2013-07-01",
    "iso:country": "GB",
    "wof:name": "DT4 0RT",
    "wof:placetype": "postalcode"
  },
  "geometry": {"coordinates":[-2.47827,50.614721],"type":"Point"}
}
