{
  "type": "Feature",
  "properties": {
    "date:inception_lower":"1980-01-01",
    "date:inception_upper":"1980-01-31",
    "iso:country":"GB",
    "wof:name":"TF2 8JG",
    "wof:placetype":"postalcode"
},
  "geometry": {"coordinates":[-2.431028,52.722837],"type":"Point"}
}