{
  "type": "Feature",
  "properties": {
    "iso:country":"GB",
    "wof:name":"AB42 2WH",
    "wof:placetype":"postalcode"
},
  "geometry": {"coordinates":[-1.80042104174268,57.49508863934026],"type":"Point"}
}