{
  "type": "Feature",
  "properties": {
    "iso:country":"GB",
    "wof:name":"BB9 5DU",
    "wof:placetype":"postalcode"
},
  "geometry": {"coordinates":[-2.22416487880842,53.82304978059626],"type":"Point"}
}