{
  "type": "Feature",
  "properties": {
    "iso:country":"GB",
    "wof:name":"DL9 4RJ",
    "wof:placetype":"postalcode"
},
  "geometry": {"coordinates":[-1.68541171260431,54.38047983817206],"type":"Point"}
}