{
  "type": "Feature",
  "properties": {
    "date:inception_lower": "1980-01-01",
    "date:inception_upper": "1980-01-01",
    "iso:country": "GB",
    "wof:name": "DL9 4RJ",
    "wof:placetype": "postalcode"
  },
  "geometry": {"coordinates":[-1.685412,54.38048],"type":"Point"}
}
