{
  "type": "Feature",
  "properties": {
    "iso:country":"GB",
    "wof:name":"GU35 0DT",
    "wof:placetype":"postalcode"
},
  "geometry": {"coordinates":[-0.85085977397145,51.10861134998823],"type":"Point"}
}