{
  "type": "Feature",
  "properties": {
    "iso:country": "GB",
    "wof:name": "CM20 3FB",
    "wof:placetype": "postalcode"
  },
  "geometry": {"coordinates":[0.123613,51.776652],"type":"Point"}
}
