{
  "type": "Feature",
  "properties": {
    "iso:country":"GB",
    "wof:name":"SY5 9RZ",
    "wof:placetype":"postalcode"
},
  "geometry": {"coordinates":[-3.03060738657835,52.65592241708629],"type":"Point"}
}