{
  "type": "Feature",
  "properties": {
    "date:inception_lower": "1980-01-01",
    "date:inception_upper": "1980-01-01",
    "iso:country": "GB",
    "wof:name": "SY5 9RZ",
    "wof:placetype": "postalcode"
  },
  "geometry": {"coordinates":[-3.030607,52.655922],"type":"Point"}
}
