{
  "type": "Feature",
  "properties": {
    "date:inception_lower": "2001-12-01",
    "date:inception_upper": "2001-12-01",
    "iso:country": "GB",
    "wof:name": "SR3 1DL",
    "wof:placetype": "postalcode"
  },
  "geometry": {"coordinates":[-1.402629,54.890333],"type":"Point"}
}
