{
  "type": "Feature",
  "properties": {
    "iso:country": "GB",
    "wof:name": "BS26 2EF",
    "wof:placetype": "postalcode"
  },
  "geometry": {"coordinates":[-2.836509,51.288883],"type":"Point"}
}
