{
  "type": "Feature",
  "properties": {
    "iso:country":"GB",
    "wof:name":"BS26 2EF",
    "wof:placetype":"postalcode"
},
  "geometry": {"coordinates":[-2.83650944139731,51.28888298191451],"type":"Point"}
}