{
  "type": "Feature",
  "properties": {
    "iso:country":"GB",
    "wof:name":"BB3 1JG",
    "wof:placetype":"postalcode"
},
  "geometry": {"coordinates":[-2.48156914442995,53.70062010527081],"type":"Point"}
}