{
  "type": "Feature",
  "properties": {
    "iso:country": "GB",
    "wof:name": "BB3 1JG",
    "wof:placetype": "postalcode"
  },
  "geometry": {"coordinates":[-2.481569,53.70062],"type":"Point"}
}
