{
  "type": "Feature",
  "properties": {
    "date:inception_lower": "1980-01-01",
    "date:inception_upper": "1980-01-01",
    "iso:country": "GB",
    "wof:name": "NW6 2JG",
    "wof:placetype": "postalcode"
  },
  "geometry": {"coordinates":[-0.19663,51.543989],"type":"Point"}
}
