{
  "type": "Feature",
  "properties": {
    "iso:country":"GB",
    "wof:name":"NW6 2JG",
    "wof:placetype":"postalcode"
},
  "geometry": {"coordinates":[-0.19662965540853,51.54398876468746],"type":"Point"}
}