{
  "type": "Feature",
  "properties": {
    "iso:country":"GB",
    "wof:name":"M15 4EA",
    "wof:placetype":"postalcode"
},
  "geometry": {"coordinates":[-2.25987281819054,53.46814100253985],"type":"Point"}
}