{
  "type": "Feature",
  "properties": {
    "date:inception_lower": "2006-09-01",
    "date:inception_upper": "2006-09-01",
    "iso:country": "GB",
    "wof:name": "CB24 9HN",
    "wof:placetype": "postalcode"
  },
  "geometry": {"coordinates":[0.111947,52.255634],"type":"Point"}
}
