{
  "type": "Feature",
  "properties": {
    "iso:country":"GB",
    "wof:name":"FK3 0JA",
    "wof:placetype":"postalcode"
},
  "geometry": {"coordinates":[-3.71877798295812,56.00148676316326],"type":"Point"}
}