{
  "type": "Feature",
  "properties": {
    "iso:country": "GB",
    "wof:name": "WA9 2PJ",
    "wof:placetype": "postalcode"
  },
  "geometry": {"coordinates":[-2.686336,53.448636],"type":"Point"}
}
