{
  "type": "Feature",
  "properties": {
    "iso:country":"GB",
    "wof:name":"WA9 2PJ",
    "wof:placetype":"postalcode"
},
  "geometry": {"coordinates":[-2.68633589726948,53.44863613000267],"type":"Point"}
}