{
  "type": "Feature",
  "properties": {
    "iso:country":"GB",
    "wof:name":"GL3 4LT",
    "wof:placetype":"postalcode"
},
  "geometry": {"coordinates":[-2.16087630467986,51.84460504224298],"type":"Point"}
}