{
  "type": "Feature",
  "properties": {
    "iso:country": "GB",
    "wof:name": "DN39 6SU",
    "wof:placetype": "postalcode"
  },
  "geometry": {"coordinates":[-0.323664,53.613817],"type":"Point"}
}
