{
  "type": "Feature",
  "properties": {
    "iso:country":"GB",
    "wof:name":"DN39 6SU",
    "wof:placetype":"postalcode"
},
  "geometry": {"coordinates":[-0.32369394370347,53.61407406321489],"type":"Point"}
}