{
  "type": "Feature",
  "properties": {
    "iso:country": "GB",
    "wof:name": "ME9 7LU",
    "wof:placetype": "postalcode"
  },
  "geometry": {"coordinates":[0.668415,51.350178],"type":"Point"}
}
