{
  "type": "Feature",
  "properties": {
    "iso:country":"GB",
    "wof:name":"ME9 7LU",
    "wof:placetype":"postalcode"
},
  "geometry": {"coordinates":[0.66842976669874,51.35017734634546],"type":"Point"}
}