{
  "type": "Feature",
  "properties": {
    "iso:country": "GB",
    "wof:name": "DE45 1SG",
    "wof:placetype": "postalcode"
  },
  "geometry": {"coordinates":[-1.617381,53.250268],"type":"Point"}
}
