{
  "type": "Feature",
  "properties": {
    "date:inception_lower": "1980-01-01",
    "date:inception_upper": "1980-01-01",
    "iso:country": "GB",
    "wof:name": "ST19 5PT",
    "wof:placetype": "postalcode"
  },
  "geometry": {"coordinates":[-2.096275,52.694309],"type":"Point"}
}
