{
  "type": "Feature",
  "properties": {
    "iso:country":"GB",
    "wof:name":"ST19 5PT",
    "wof:placetype":"postalcode"
},
  "geometry": {"coordinates":[-2.09810162581733,52.69511911961882],"type":"Point"}
}