{
  "type": "Feature",
  "properties": {
    "iso:country":"GB",
    "wof:name":"CT2 0EF",
    "wof:placetype":"postalcode"
},
  "geometry": {"coordinates":[1.13027928182851,51.30448678083641],"type":"Point"}
}