{
  "type": "Feature",
  "properties": {
    "date:inception_lower": "1980-01-01",
    "date:inception_upper": "1980-01-01",
    "iso:country": "GB",
    "wof:name": "NR11 7LT",
    "wof:placetype": "postalcode"
  },
  "geometry": {"coordinates":[1.20503,52.854551],"type":"Point"}
}
