{
  "type": "Feature",
  "properties": {
    "iso:country":"GB",
    "wof:name":"NR11 7LT",
    "wof:placetype":"postalcode"
},
  "geometry": {"coordinates":[1.20502957745209,52.85455076881735],"type":"Point"}
}