{
  "type": "Feature",
  "properties": {
    "iso:country":"GB",
    "wof:name":"BS5 9LZ",
    "wof:placetype":"postalcode"
},
  "geometry": {"coordinates":[-2.56261561264427,51.45679543297352],"type":"Point"}
}