{
  "type": "Feature",
  "properties": {
    "iso:country":"GB",
    "wof:name":"B76 9DX",
    "wof:placetype":"postalcode"
},
  "geometry": {"coordinates":[-1.74125794448525,52.53450955389621],"type":"Point"}
}