{
  "type": "Feature",
  "properties": {
    "date:inception_lower": "2000-06-01",
    "date:inception_upper": "2000-06-01",
    "iso:country": "GB",
    "wof:name": "HP19 8RH",
    "wof:placetype": "postalcode"
  },
  "geometry": {"coordinates":[-0.820426,51.816973],"type":"Point"}
}
