{
  "type": "Feature",
  "properties": {
    "iso:country":"GB",
    "wof:name":"CM17 9QJ",
    "wof:placetype":"postalcode"
},
  "geometry": {"coordinates":[0.1461573492649,51.76473485731844],"type":"Point"}
}