{
  "type": "Feature",
  "properties": {
    "iso:country": "GB",
    "wof:name": "SY3 5EL",
    "wof:placetype": "postalcode"
  },
  "geometry": {"coordinates":[-2.80557,52.712918],"type":"Point"}
}
