{
  "type": "Feature",
  "properties": {
    "iso:country":"GB",
    "wof:name":"SY3 5EL",
    "wof:placetype":"postalcode"
},
  "geometry": {"coordinates":[-2.80556972364367,52.71291811892829],"type":"Point"}
}