{
  "type": "Feature",
  "properties": {
    "iso:country":"GB",
    "wof:name":"B47 6HN",
    "wof:placetype":"postalcode"
},
  "geometry": {"coordinates":[-1.86745133829933,52.3826430531608],"type":"Point"}
}