{
  "type": "Feature",
  "properties": {
    "date:inception_lower": "1980-01-01",
    "date:inception_upper": "1980-01-01",
    "iso:country": "GB",
    "wof:name": "B47 6HN",
    "wof:placetype": "postalcode"
  },
  "geometry": {"coordinates":[-1.867451,52.382643],"type":"Point"}
}
