{
  "type": "Feature",
  "properties": {
    "iso:country":"GB",
    "wof:name":"CH3 5LG",
    "wof:placetype":"postalcode"
},
  "geometry": {"coordinates":[-2.85785090268725,53.19481155527268],"type":"Point"}
}