{
  "type": "Feature",
  "properties": {
    "iso:country":"GB",
    "wof:name":"BH22 9TG",
    "wof:placetype":"postalcode"
},
  "geometry": {"coordinates":[-1.90232676293336,50.8113541442272],"type":"Point"}
}