{
  "type": "Feature",
  "properties": {
    "iso:country":"GB",
    "wof:name":"M29 8XD",
    "wof:placetype":"postalcode"
},
  "geometry": {"coordinates":[-2.44916389962658,53.51499335224754],"type":"Point"}
}