{
  "type": "Feature",
  "properties": {
    "iso:country":"GB",
    "wof:name":"BS6 5EE",
    "wof:placetype":"postalcode"
},
  "geometry": {"coordinates":[-2.58957448882764,51.46806430248078],"type":"Point"}
}