{
  "type": "Feature",
  "properties": {
    "iso:country":"GB",
    "wof:name":"PE30 2QJ",
    "wof:placetype":"postalcode"
},
  "geometry": {"coordinates":[0.41075000518009,52.7538730020401],"type":"Point"}
}