{
  "type": "Feature",
  "properties": {
    "date:inception_lower": "1980-01-01",
    "date:inception_upper": "1980-01-01",
    "iso:country": "GB",
    "wof:name": "PE30 2QJ",
    "wof:placetype": "postalcode"
  },
  "geometry": {"coordinates":[0.41075,52.753873],"type":"Point"}
}
