{
  "type": "Feature",
  "properties": {
    "iso:country": "GB",
    "wof:name": "PE30 2QJ",
    "wof:placetype": "postalcode"
  },
  "geometry": {"coordinates":[0.41075,52.753873],"type":"Point"}
}
