{
  "type": "Feature",
  "properties": {
    "iso:country":"GB",
    "wof:name":"DD2 2LE",
    "wof:placetype":"postalcode"
},
  "geometry": {"coordinates":[-2.99443263818009,56.46426084474663],"type":"Point"}
}