{
  "type": "Feature",
  "properties": {
    "date:inception_lower":"2017-07-01",
    "date:inception_upper":"2017-07-31",
    "iso:country":"GB",
    "wof:name":"SY13 1RS",
    "wof:placetype":"postalcode"
},
  "geometry": {"coordinates":[-2.702767,52.968684],"type":"Point"}
}