{
  "type": "Feature",
  "properties": {
    "date:inception_lower": "1996-06-01",
    "date:inception_upper": "1996-06-01",
    "iso:country": "GB",
    "wof:name": "AB43 6TD",
    "wof:placetype": "postalcode"
  },
  "geometry": {"coordinates":[-2.07393,57.563257],"type":"Point"}
}
