{
  "type": "Feature",
  "properties": {
    "iso:country":"GB",
    "wof:name":"RG25 2AX",
    "wof:placetype":"postalcode"
},
  "geometry": {"coordinates":[-1.15932639754117,51.19098723281152],"type":"Point"}
}