{
  "type": "Feature",
  "properties": {
    "iso:country": "GB",
    "wof:name": "RG25 2AX",
    "wof:placetype": "postalcode"
  },
  "geometry": {"coordinates":[-1.159326,51.190987],"type":"Point"}
}
