{
  "type": "Feature",
  "properties": {
    "iso:country": "GB",
    "wof:name": "M33 3PR",
    "wof:placetype": "postalcode"
  },
  "geometry": {"coordinates":[-2.310728,53.408246],"type":"Point"}
}
