{
  "type": "Feature",
  "properties": {
    "iso:country":"GB",
    "wof:name":"SO32 2AQ",
    "wof:placetype":"postalcode"
},
  "geometry": {"coordinates":[-1.28235147093499,50.9479896301513],"type":"Point"}
}