{
  "type": "Feature",
  "properties": {
    "iso:country": "GB",
    "wof:name": "SO32 2AQ",
    "wof:placetype": "postalcode"
  },
  "geometry": {"coordinates":[-1.282311,50.948035],"type":"Point"}
}
