{
  "type": "Feature",
  "properties": {
    "date:inception_lower": "2020-08-01",
    "date:inception_upper": "2020-08-01",
    "iso:country": "GB",
    "wof:name": "RG8 0DQ",
    "wof:placetype": "postalcode"
  },
  "geometry": {"coordinates":[-1.124785,51.529749],"type":"Point"}
}
