{
  "type": "Feature",
  "properties": {
    "iso:country": "GB",
    "wof:name": "TW7 7HP",
    "wof:placetype": "postalcode"
  },
  "geometry": {"coordinates":[-0.327224,51.462735],"type":"Point"}
}
