{
  "type": "Feature",
  "properties": {
    "iso:country": "GB",
    "wof:name": "BR4 9FA",
    "wof:placetype": "postalcode"
  },
  "geometry": {"coordinates":[-0.005591,51.364864],"type":"Point"}
}
