{
  "type": "Feature",
  "properties": {
    "date:inception_lower": "1981-06-01",
    "date:inception_upper": "1981-06-01",
    "iso:country": "GB",
    "wof:name": "TN38 9NU",
    "wof:placetype": "postalcode"
  },
  "geometry": {"coordinates":[0.539812,50.883273],"type":"Point"}
}
