{
  "type": "Feature",
  "properties": {
    "iso:country": "GB",
    "wof:name": "HD4 5ST",
    "wof:placetype": "postalcode"
  },
  "geometry": {"coordinates":[-1.828021,53.636302],"type":"Point"}
}
