{
  "type": "Feature",
  "properties": {
    "iso:country": "GB",
    "wof:name": "BL8 1TR",
    "wof:placetype": "postalcode"
  },
  "geometry": {"coordinates":[-2.323552,53.60318],"type":"Point"}
}
