{
  "type": "Feature",
  "properties": {
    "iso:country":"GB",
    "wof:name":"BL8 1TR",
    "wof:placetype":"postalcode"
},
  "geometry": {"coordinates":[-2.32355216702605,53.60317984311049],"type":"Point"}
}