{
  "type": "Feature",
  "properties": {
    "iso:country":"GB",
    "wof:name":"DG11 3PL",
    "wof:placetype":"postalcode"
},
  "geometry": {"coordinates":[-3.21184730762803,55.05357532684623],"type":"Point"}
}