{
  "type": "Feature",
  "properties": {
    "iso:country": "GB",
    "wof:name": "DG11 3PL",
    "wof:placetype": "postalcode"
  },
  "geometry": {"coordinates":[-3.211847,55.053575],"type":"Point"}
}
