{
  "type": "Feature",
  "properties": {
    "iso:country": "GB",
    "wof:name": "SN8 2HJ",
    "wof:placetype": "postalcode"
  },
  "geometry": {"coordinates":[-1.566771,51.455935],"type":"Point"}
}
