{
  "type": "Feature",
  "properties": {
    "iso:country":"GB",
    "wof:name":"SN8 2HJ",
    "wof:placetype":"postalcode"
},
  "geometry": {"coordinates":[-1.56812364283379,51.45601235871115],"type":"Point"}
}