{
  "type": "Feature",
  "properties": {
    "date:inception_lower": "1980-01-01",
    "date:inception_upper": "1980-01-01",
    "iso:country": "GB",
    "wof:name": "S3 8RW",
    "wof:placetype": "postalcode"
  },
  "geometry": {"coordinates":[-1.47218,53.388133],"type":"Point"}
}
