{
  "type": "Feature",
  "properties": {
    "date:inception_lower":"1980-01-01",
    "date:inception_upper":"1980-01-31",
    "iso:country":"GB",
    "wof:name":"NR3 2AY",
    "wof:placetype":"postalcode"
},
  "geometry": {"coordinates":[1.267536,52.652139],"type":"Point"}
}