{
  "type": "Feature",
  "properties": {
    "iso:country":"GB",
    "wof:name":"SA41 3XE",
    "wof:placetype":"postalcode"
},
  "geometry": {"coordinates":[-4.77986056656422,52.0083790702916],"type":"Point"}
}