{
  "type": "Feature",
  "properties": {
    "iso:country": "GB",
    "wof:name": "SA41 3XE",
    "wof:placetype": "postalcode"
  },
  "geometry": {"coordinates":[-4.779861,52.008379],"type":"Point"}
}
