{
  "type": "Feature",
  "properties": {
    "iso:country":"GB",
    "wof:name":"NW2 5LY",
    "wof:placetype":"postalcode"
},
  "geometry": {"coordinates":[-0.23381193677526,51.5506062590747],"type":"Point"}
}