{
  "type": "Feature",
  "properties": {
    "iso:country": "GB",
    "wof:name": "EX38 8NQ",
    "wof:placetype": "postalcode"
  },
  "geometry": {"coordinates":[-4.209106,50.920826],"type":"Point"}
}
