{
  "type": "Feature",
  "properties": {
    "iso:country":"GB",
    "wof:name":"CR2 8RB",
    "wof:placetype":"postalcode"
},
  "geometry": {"coordinates":[-0.07172892713945,51.33920825676439],"type":"Point"}
}