{
  "type": "Feature",
  "properties": {
    "iso:country": "GB",
    "wof:name": "WA2 9QP",
    "wof:placetype": "postalcode"
  },
  "geometry": {"coordinates":[-2.595123,53.410124],"type":"Point"}
}
