{
  "type": "Feature",
  "properties": {
    "iso:country":"GB",
    "wof:name":"PR9 9TH",
    "wof:placetype":"postalcode"
},
  "geometry": {"coordinates":[-2.96692582515768,53.66421150842233],"type":"Point"}
}