{
  "type": "Feature",
  "properties": {
    "iso:country":"GB",
    "wof:name":"SO32 3QT",
    "wof:placetype":"postalcode"
},
  "geometry": {"coordinates":[-1.12747500585375,50.96385950640794],"type":"Point"}
}