{
  "type": "Feature",
  "properties": {
    "iso:country":"GB",
    "wof:name":"S4 7AG",
    "wof:placetype":"postalcode"
},
  "geometry": {"coordinates":[-1.46071915898381,53.40271514650875],"type":"Point"}
}