{
  "type": "Feature",
  "properties": {
    "iso:country":"GB",
    "wof:name":"CR0 4DN",
    "wof:placetype":"postalcode"
},
  "geometry": {"coordinates":[-0.11156772108896,51.36373316597071],"type":"Point"}
}