{
  "type": "Feature",
  "properties": {
    "iso:country": "GB",
    "wof:name": "EH42 1XX",
    "wof:placetype": "postalcode"
  },
  "geometry": {"coordinates":[-2.53221,55.991567],"type":"Point"}
}
