{
  "type": "Feature",
  "properties": {
    "iso:country": "GB",
    "wof:name": "EH42 1XX",
    "wof:placetype": "postalcode"
  },
  "geometry": {"coordinates":[-2.532358,55.991854],"type":"Point"}
}
