{
  "type": "Feature",
  "properties": {
    "date:inception_lower": "2017-01-01",
    "date:inception_upper": "2017-01-01",
    "iso:country": "GB",
    "wof:name": "EH42 1XX",
    "wof:placetype": "postalcode"
  },
  "geometry": {"coordinates":[-2.532424,55.991997],"type":"Point"}
}
