{
  "type": "Feature",
  "properties": {
    "iso:country":"GB",
    "wof:name":"EX34 0HH",
    "wof:placetype":"postalcode"
},
  "geometry": {"coordinates":[-4.02750737579437,51.2020160448342],"type":"Point"}
}