{
  "type": "Feature",
  "properties": {
    "iso:country":"GB",
    "wof:name":"OX7 6JQ",
    "wof:placetype":"postalcode"
},
  "geometry": {"coordinates":[-1.61785187776146,51.8633272415513],"type":"Point"}
}