{
  "type": "Feature",
  "properties": {
    "iso:country":"GB",
    "wof:name":"LS28 5TU",
    "wof:placetype":"postalcode"
},
  "geometry": {"coordinates":[-1.67960070613396,53.80742717264594],"type":"Point"}
}