{
  "type": "Feature",
  "properties": {
    "iso:country": "GB",
    "wof:name": "LS28 5TU",
    "wof:placetype": "postalcode"
  },
  "geometry": {"coordinates":[-1.679601,53.807427],"type":"Point"}
}
