{
  "type": "Feature",
  "properties": {
    "iso:country": "GB",
    "wof:name": "PE8 4PU",
    "wof:placetype": "postalcode"
  },
  "geometry": {"coordinates":[-0.478134,52.490559],"type":"Point"}
}
