{
  "type": "Feature",
  "properties": {
    "iso:country": "GB",
    "wof:name": "GL51 0RY",
    "wof:placetype": "postalcode"
  },
  "geometry": {"coordinates":[-2.120354,51.90652],"type":"Point"}
}
