{
  "type": "Feature",
  "properties": {
    "iso:country":"GB",
    "wof:name":"NE5 3DX",
    "wof:placetype":"postalcode"
},
  "geometry": {"coordinates":[-1.66478053792383,54.99278520326605],"type":"Point"}
}