{
  "type": "Feature",
  "properties": {
    "iso:country": "GB",
    "wof:name": "NE5 3DX",
    "wof:placetype": "postalcode"
  },
  "geometry": {"coordinates":[-1.66478,54.992785],"type":"Point"}
}
