{
  "type": "Feature",
  "properties": {
    "iso:country":"GB",
    "wof:name":"RM12 5LT",
    "wof:placetype":"postalcode"
},
  "geometry": {"coordinates":[0.20455297131573,51.54379005375968],"type":"Point"}
}