{
  "type": "Feature",
  "properties": {
    "iso:country":"GB",
    "wof:name":"G72 9EU",
    "wof:placetype":"postalcode"
},
  "geometry": {"coordinates":[-4.0985880818861,55.79856426472816],"type":"Point"}
}