{
  "type": "Feature",
  "properties": {
    "iso:country":"GB",
    "wof:name":"ML10 6FN",
    "wof:placetype":"postalcode"
},
  "geometry": {"coordinates":[-4.05896149180103,55.688566346969],"type":"Point"}
}