{
  "type": "Feature",
  "properties": {
    "date:inception_lower": "1999-12-01",
    "date:inception_upper": "1999-12-01",
    "iso:country": "GB",
    "wof:name": "ML10 6FN",
    "wof:placetype": "postalcode"
  },
  "geometry": {"coordinates":[-4.058961,55.688566],"type":"Point"}
}
