{
  "type": "Feature",
  "properties": {
    "iso:country": "GB",
    "wof:name": "CF14 6RN",
    "wof:placetype": "postalcode"
  },
  "geometry": {"coordinates":[-3.212981,51.530261],"type":"Point"}
}
