{
  "type": "Feature",
  "properties": {
    "iso:country":"GB",
    "wof:name":"EH26 8HN",
    "wof:placetype":"postalcode"
},
  "geometry": {"coordinates":[-3.22180046734867,55.82740581249271],"type":"Point"}
}