{
  "type": "Feature",
  "properties": {
    "iso:country":"GB",
    "wof:name":"KY15 7BH",
    "wof:placetype":"postalcode"
},
  "geometry": {"coordinates":[-3.20952991768963,56.25233745454479],"type":"Point"}
}