{
  "type": "Feature",
  "properties": {
    "date:inception_lower": "1995-12-01",
    "date:inception_upper": "1995-12-01",
    "iso:country": "GB",
    "wof:name": "KY15 7BH",
    "wof:placetype": "postalcode"
  },
  "geometry": {"coordinates":[-3.20953,56.25233],"type":"Point"}
}
