{
  "type": "Feature",
  "properties": {
    "iso:country":"GB",
    "wof:name":"IP11 3QU",
    "wof:placetype":"postalcode"
},
  "geometry": {"coordinates":[1.32057595782131,51.96065877621704],"type":"Point"}
}