{
  "type": "Feature",
  "properties": {
    "date:inception_lower": "1999-12-01",
    "date:inception_upper": "1999-12-01",
    "iso:country": "GB",
    "wof:name": "IP11 3QU",
    "wof:placetype": "postalcode"
  },
  "geometry": {"coordinates":[1.320576,51.960659],"type":"Point"}
}
