{
  "type": "Feature",
  "properties": {
    "date:inception_lower": "1996-06-01",
    "date:inception_upper": "1996-06-01",
    "iso:country": "GB",
    "wof:name": "AB56 4JZ",
    "wof:placetype": "postalcode"
  },
  "geometry": {"coordinates":[-2.862597,57.701855],"type":"Point"}
}
