{
  "type": "Feature",
  "properties": {
    "iso:country":"GB",
    "wof:name":"PR8 6PL",
    "wof:placetype":"postalcode"
},
  "geometry": {"coordinates":[-2.98347083142632,53.64030196739017],"type":"Point"}
}