{
  "type": "Feature",
  "properties": {
    "iso:country":"GB",
    "wof:name":"NG16 3AJ",
    "wof:placetype":"postalcode"
},
  "geometry": {"coordinates":[-1.30306212133749,53.01764524262422],"type":"Point"}
}