{
  "type": "Feature",
  "properties": {
    "iso:country":"GB",
    "wof:name":"B23 7QX",
    "wof:placetype":"postalcode"
},
  "geometry": {"coordinates":[-1.85613350299425,52.51545727929402],"type":"Point"}
}