{
  "type": "Feature",
  "properties": {
    "iso:country": "GB",
    "wof:name": "PL9 8LF",
    "wof:placetype": "postalcode"
  },
  "geometry": {"coordinates":[-4.076827,50.35643],"type":"Point"}
}
