{
  "type": "Feature",
  "properties": {
    "iso:country":"GB",
    "wof:name":"M40 2UB",
    "wof:placetype":"postalcode"
},
  "geometry": {"coordinates":[-2.18266431327665,53.49471915348138],"type":"Point"}
}