{
  "type": "Feature",
  "properties": {
    "iso:country":"GB",
    "wof:name":"TF2 7DU",
    "wof:placetype":"postalcode"
},
  "geometry": {"coordinates":[-2.44913265117086,52.71536205725455],"type":"Point"}
}