{
  "type": "Feature",
  "properties": {
    "date:inception_lower": "2005-04-01",
    "date:inception_upper": "2005-04-01",
    "iso:country": "GB",
    "wof:name": "EH54 5FB",
    "wof:placetype": "postalcode"
  },
  "geometry": {"coordinates":[-3.495432,55.902876],"type":"Point"}
}
