{
  "type": "Feature",
  "properties": {
    "iso:country":"GB",
    "wof:name":"EH54 5FB",
    "wof:placetype":"postalcode"
},
  "geometry": {"coordinates":[-3.49543213865436,55.90287571998727],"type":"Point"}
}