{
  "type": "Feature",
  "properties": {
    "iso:country":"GB",
    "wof:name":"CO12 3SF",
    "wof:placetype":"postalcode"
},
  "geometry": {"coordinates":[1.26452463405418,51.92582772024016],"type":"Point"}
}