{
  "type": "Feature",
  "properties": {
    "date:inception_lower": "1980-01-01",
    "date:inception_upper": "1980-01-01",
    "iso:country": "GB",
    "wof:name": "DT5 1HU",
    "wof:placetype": "postalcode"
  },
  "geometry": {"coordinates":[-2.430886,50.538294],"type":"Point"}
}
