{
  "type": "Feature",
  "properties": {
    "date:inception_lower": "2001-12-01",
    "date:inception_upper": "2001-12-01",
    "iso:country": "GB",
    "wof:name": "TR1 1QA",
    "wof:placetype": "postalcode"
  },
  "geometry": {"coordinates":[-5.045604,50.260827],"type":"Point"}
}
