{
  "type": "Feature",
  "properties": {
    "iso:country":"GB",
    "wof:name":"NE28 7NL",
    "wof:placetype":"postalcode"
},
  "geometry": {"coordinates":[-1.53315068273451,54.99394216591902],"type":"Point"}
}