{
  "type": "Feature",
  "properties": {
    "date:inception_lower":"1981-06-01",
    "date:inception_upper":"1981-06-30",
    "iso:country":"GB",
    "wof:name":"NG16 3RR",
    "wof:placetype":"postalcode"
},
  "geometry": {"coordinates":[-1.317082,53.019066],"type":"Point"}
}