{
  "type": "Feature",
  "properties": {
    "iso:country":"GB",
    "wof:name":"BL0 9UA",
    "wof:placetype":"postalcode"
},
  "geometry": {"coordinates":[-2.3270530213696,53.63183391553516],"type":"Point"}
}