{
  "type": "Feature",
  "properties": {
    "date:inception_lower":"1980-01-01",
    "date:inception_upper":"1980-01-31",
    "iso:country":"GB",
    "wof:name":"BL0 9UA",
    "wof:placetype":"postalcode"
},
  "geometry": {"coordinates":[-2.327053,53.631834],"type":"Point"}
}