{
  "type": "Feature",
  "properties": {
    "iso:country": "GB",
    "wof:name": "BL0 9UA",
    "wof:placetype": "postalcode"
  },
  "geometry": {"coordinates":[-2.327053,53.631834],"type":"Point"}
}
