{
  "type": "Feature",
  "properties": {
    "date:inception_lower":"1980-01-01",
    "date:inception_upper":"1980-01-31",
    "iso:country":"GB",
    "wof:name":"IG10 3HZ",
    "wof:placetype":"postalcode"
},
  "geometry": {"coordinates":[0.054907,51.642935],"type":"Point"}
}