{
  "type": "Feature",
  "properties": {
    "iso:country":"GB",
    "wof:name":"IG10 3HZ",
    "wof:placetype":"postalcode"
},
  "geometry": {"coordinates":[0.05490717632464,51.6429349670034],"type":"Point"}
}