{
  "type": "Feature",
  "properties": {
    "iso:country": "GB",
    "wof:name": "M33 3YG",
    "wof:placetype": "postalcode"
  },
  "geometry": {"coordinates":[-2.324066,53.415563],"type":"Point"}
}
