{
  "type": "Feature",
  "properties": {
    "iso:country": "GB",
    "wof:name": "S60 5LG",
    "wof:placetype": "postalcode"
  },
  "geometry": {"coordinates":[-1.35765,53.40137],"type":"Point"}
}
