{
  "type": "Feature",
  "properties": {
    "iso:country":"GB",
    "wof:name":"S60 5LG",
    "wof:placetype":"postalcode"
},
  "geometry": {"coordinates":[-1.35738325578851,53.40102646852932],"type":"Point"}
}