{
  "type": "Feature",
  "properties": {
    "iso:country":"GB",
    "wof:name":"BB9 6LZ",
    "wof:placetype":"postalcode"
},
  "geometry": {"coordinates":[-2.2189795315805,53.87149516544487],"type":"Point"}
}