{
  "type": "Feature",
  "properties": {
    "date:inception_lower": "1980-01-01",
    "date:inception_upper": "1980-01-01",
    "iso:country": "GB",
    "wof:name": "BB9 6LZ",
    "wof:placetype": "postalcode"
  },
  "geometry": {"coordinates":[-2.219012,53.871518],"type":"Point"}
}
