{
  "type": "Feature",
  "properties": {
    "iso:country":"GB",
    "wof:name":"SL3 9DD",
    "wof:placetype":"postalcode"
},
  "geometry": {"coordinates":[-0.57666685365051,51.47904927411233],"type":"Point"}
}