{
  "type": "Feature",
  "properties": {
    "iso:country": "GB",
    "wof:name": "SL3 9DD",
    "wof:placetype": "postalcode"
  },
  "geometry": {"coordinates":[-0.576667,51.479049],"type":"Point"}
}
