{
  "type": "Feature",
  "properties": {
    "iso:country":"GB",
    "wof:name":"IV36 3EF",
    "wof:placetype":"postalcode"
},
  "geometry": {"coordinates":[-3.62255620511786,57.61252431945709],"type":"Point"}
}