{
  "type": "Feature",
  "properties": {
    "iso:country": "GB",
    "wof:name": "IV36 3EF",
    "wof:placetype": "postalcode"
  },
  "geometry": {"coordinates":[-3.622525,57.612591],"type":"Point"}
}
