{
  "type": "Feature",
  "properties": {
    "iso:country":"GB",
    "wof:name":"CF39 0LS",
    "wof:placetype":"postalcode"
},
  "geometry": {"coordinates":[-3.41194801713346,51.62070565073233],"type":"Point"}
}