{
  "type": "Feature",
  "properties": {
    "iso:country":"GB",
    "wof:name":"SW7 3QJ",
    "wof:placetype":"postalcode"
},
  "geometry": {"coordinates":[-0.17678874499991,51.48940361203676],"type":"Point"}
}