{
  "type": "Feature",
  "properties": {
    "iso:country": "GB",
    "wof:name": "SW7 3QJ",
    "wof:placetype": "postalcode"
  },
  "geometry": {"coordinates":[-0.176789,51.489404],"type":"Point"}
}
