{
  "type": "Feature",
  "properties": {
    "iso:country": "GB",
    "wof:name": "PO36 8HQ",
    "wof:placetype": "postalcode"
  },
  "geometry": {"coordinates":[-1.156106,50.656878],"type":"Point"}
}
