{
  "type": "Feature",
  "properties": {
    "iso:country": "GB",
    "wof:name": "M4 4DB",
    "wof:placetype": "postalcode"
  },
  "geometry": {"coordinates":[-2.234497,53.488516],"type":"Point"}
}
