{
  "type": "Feature",
  "properties": {
    "iso:country":"GB",
    "wof:name":"EH6 8PZ",
    "wof:placetype":"postalcode"
},
  "geometry": {"coordinates":[-3.17092019274707,55.96740100209684],"type":"Point"}
}