{
  "type": "Feature",
  "properties": {
    "date:inception_lower": "1980-01-01",
    "date:inception_upper": "1980-01-01",
    "iso:country": "GB",
    "wof:name": "SR3 4JF",
    "wof:placetype": "postalcode"
  },
  "geometry": {"coordinates":[-1.432069,54.884409],"type":"Point"}
}
