{
  "type": "Feature",
  "properties": {
    "iso:country":"GB",
    "wof:name":"SR3 4JF",
    "wof:placetype":"postalcode"
},
  "geometry": {"coordinates":[-1.43206862388883,54.88440869928538],"type":"Point"}
}