{
  "type": "Feature",
  "properties": {
    "iso:country":"GB",
    "wof:name":"SA9 1NT",
    "wof:placetype":"postalcode"
},
  "geometry": {"coordinates":[-3.75782940088061,51.77701214271386],"type":"Point"}
}