{
  "type": "Feature",
  "properties": {
    "iso:country":"GB",
    "wof:name":"CO7 6DS",
    "wof:placetype":"postalcode"
},
  "geometry": {"coordinates":[0.98586857905399,51.95315279350699],"type":"Point"}
}