{
  "type": "Feature",
  "properties": {
    "iso:country":"GB",
    "wof:name":"EX31 4NF",
    "wof:placetype":"postalcode"
},
  "geometry": {"coordinates":[-3.97850831552349,51.17063293872211],"type":"Point"}
}