{
  "type": "Feature",
  "properties": {
    "date:inception_lower": "1980-01-01",
    "date:inception_upper": "1980-01-01",
    "iso:country": "GB",
    "wof:name": "EX31 4NF",
    "wof:placetype": "postalcode"
  },
  "geometry": {"coordinates":[-3.978508,51.170633],"type":"Point"}
}
