{
  "type": "Feature",
  "properties": {
    "iso:country":"GB",
    "wof:name":"TQ2 5UJ",
    "wof:placetype":"postalcode"
},
  "geometry": {"coordinates":[-3.5376732985576,50.46738507157526],"type":"Point"}
}