{
  "type": "Feature",
  "properties": {
    "iso:country":"GB",
    "wof:name":"PL27 7XD",
    "wof:placetype":"postalcode"
},
  "geometry": {"coordinates":[-4.84366150550096,50.51651991884318],"type":"Point"}
}