{
  "type": "Feature",
  "properties": {
    "iso:country":"GB",
    "wof:name":"N1 1UG",
    "wof:placetype":"postalcode"
},
  "geometry": {"coordinates":[-0.10385582061633,51.54187853368639],"type":"Point"}
}