{
  "type": "Feature",
  "properties": {
    "date:inception_lower": "2012-11-01",
    "date:inception_upper": "2012-11-01",
    "iso:country": "GB",
    "wof:name": "LA5 9FD",
    "wof:placetype": "postalcode"
  },
  "geometry": {"coordinates":[-2.754658,54.126249],"type":"Point"}
}
