{
  "type": "Feature",
  "properties": {
    "iso:country":"GB",
    "wof:name":"PR2 9HN",
    "wof:placetype":"postalcode"
},
  "geometry": {"coordinates":[-2.69841592949947,53.79585160919492],"type":"Point"}
}