{
  "type": "Feature",
  "properties": {
    "date:inception_lower": "1995-01-01",
    "date:inception_upper": "1995-01-01",
    "iso:country": "GB",
    "wof:name": "PR2 9HN",
    "wof:placetype": "postalcode"
  },
  "geometry": {"coordinates":[-2.699361,53.796266],"type":"Point"}
}
