{
  "type": "Feature",
  "properties": {
    "iso:country":"GB",
    "wof:name":"WS15 1SS",
    "wof:placetype":"postalcode"
},
  "geometry": {"coordinates":[-1.91048843763661,52.75078987176276],"type":"Point"}
}