{
  "type": "Feature",
  "properties": {
    "date:inception_lower": "2016-02-01",
    "date:inception_upper": "2016-02-01",
    "iso:country": "GB",
    "wof:name": "WS15 1SS",
    "wof:placetype": "postalcode"
  },
  "geometry": {"coordinates":[-1.910454,52.750753],"type":"Point"}
}
