{
  "type": "Feature",
  "properties": {
    "iso:country":"GB",
    "wof:name":"CA3 0JF",
    "wof:placetype":"postalcode"
},
  "geometry": {"coordinates":[-2.95764344011836,54.93030706845532],"type":"Point"}
}