{
  "type": "Feature",
  "properties": {
    "iso:country":"GB",
    "wof:name":"SM5 3QZ",
    "wof:placetype":"postalcode"
},
  "geometry": {"coordinates":[-0.17381086886231,51.36013373415924],"type":"Point"}
}