{
  "type": "Feature",
  "properties": {
    "date:inception_lower":"1994-05-01",
    "date:inception_upper":"1994-05-31",
    "iso:country":"GB",
    "wof:name":"M44 5YB",
    "wof:placetype":"postalcode"
},
  "geometry": {"coordinates":[-2.448022,53.426748],"type":"Point"}
}