{
  "type": "Feature",
  "properties": {
    "iso:country":"GB",
    "wof:name":"M44 5YB",
    "wof:placetype":"postalcode"
},
  "geometry": {"coordinates":[-2.44802193464002,53.42674825718352],"type":"Point"}
}