{
  "type": "Feature",
  "properties": {
    "iso:country":"GB",
    "wof:name":"BS5 8FR",
    "wof:placetype":"postalcode"
},
  "geometry": {"coordinates":[-2.54107318148513,51.46073628807495],"type":"Point"}
}