{
  "type": "Feature",
  "properties": {
    "date:inception_lower":"2015-04-01",
    "date:inception_upper":"2015-04-30",
    "iso:country":"GB",
    "wof:name":"BS5 8FR",
    "wof:placetype":"postalcode"
},
  "geometry": {"coordinates":[-2.541073,51.460736],"type":"Point"}
}