{
  "type": "Feature",
  "properties": {
    "date:inception_lower": "2021-11-01",
    "date:inception_upper": "2021-11-01",
    "iso:country": "GB",
    "wof:name": "PL25 3GJ",
    "wof:placetype": "postalcode"
  },
  "geometry": {"coordinates":[-4.75424,50.340808],"type":"Point"}
}
