{
  "type": "Feature",
  "properties": {
    "iso:country": "GB",
    "wof:name": "CB7 4JJ",
    "wof:placetype": "postalcode"
  },
  "geometry": {"coordinates":[0.25232,52.39236],"type":"Point"}
}
