{
  "type": "Feature",
  "properties": {
    "iso:country":"GB",
    "wof:name":"G82 3AX",
    "wof:placetype":"postalcode"
},
  "geometry": {"coordinates":[-4.55580511087775,55.95759839080574],"type":"Point"}
}