{
  "type": "Feature",
  "properties": {
    "iso:country":"GB",
    "wof:name":"M1 1AJ",
    "wof:placetype":"postalcode"
},
  "geometry": {"coordinates":[-2.23226660613526,53.48299291990216],"type":"Point"}
}