{
  "type": "Feature",
  "properties": {
    "iso:country":"GB",
    "wof:name":"L15 5AL",
    "wof:placetype":"postalcode"
},
  "geometry": {"coordinates":[-2.92601522041973,53.39169175654028],"type":"Point"}
}