{
  "type": "Feature",
  "properties": {
    "iso:country":"GB",
    "wof:name":"DA16 2RH",
    "wof:placetype":"postalcode"
},
  "geometry": {"coordinates":[0.09401097153824,51.46374713771044],"type":"Point"}
}