{
  "type": "Feature",
  "properties": {
    "date:inception_lower": "1980-01-01",
    "date:inception_upper": "1980-01-01",
    "iso:country": "GB",
    "wof:name": "G43 2LS",
    "wof:placetype": "postalcode"
  },
  "geometry": {"coordinates":[-4.269181,55.816447],"type":"Point"}
}
