{
  "type": "Feature",
  "properties": {
    "iso:country": "GB",
    "wof:name": "G43 2LS",
    "wof:placetype": "postalcode"
  },
  "geometry": {"coordinates":[-4.269181,55.816447],"type":"Point"}
}
