{
  "type": "Feature",
  "properties": {
    "iso:country":"GB",
    "wof:name":"G43 2LS",
    "wof:placetype":"postalcode"
},
  "geometry": {"coordinates":[-4.26918075348354,55.81644706944908],"type":"Point"}
}