{
  "type": "Feature",
  "properties": {
    "iso:country":"GB",
    "wof:name":"NG11 8BA",
    "wof:placetype":"postalcode"
},
  "geometry": {"coordinates":[-1.18329871859886,52.90948621093756],"type":"Point"}
}