{
  "type": "Feature",
  "properties": {
    "date:inception_lower": "1980-01-01",
    "date:inception_upper": "1980-01-01",
    "iso:country": "GB",
    "wof:name": "TN21 0BG",
    "wof:placetype": "postalcode"
  },
  "geometry": {"coordinates":[0.239068,50.94262],"type":"Point"}
}
