{
  "type": "Feature",
  "properties": {
    "iso:country":"GB",
    "wof:name":"TN21 0BG",
    "wof:placetype":"postalcode"
},
  "geometry": {"coordinates":[0.23906802022929,50.94262395216671],"type":"Point"}
}