{
  "type": "Feature",
  "properties": {
    "iso:country":"GB",
    "wof:name":"E17 4EY",
    "wof:placetype":"postalcode"
},
  "geometry": {"coordinates":[-0.00396285782808,51.59451867721032],"type":"Point"}
}