{
  "type": "Feature",
  "properties": {
    "iso:country":"GB",
    "wof:name":"HX1 1SP",
    "wof:placetype":"postalcode"
},
  "geometry": {"coordinates":[-1.85395773249883,53.72414134042397],"type":"Point"}
}