{
  "type": "Feature",
  "properties": {
    "iso:country": "GB",
    "wof:name": "HU5 1BF",
    "wof:placetype": "postalcode"
  },
  "geometry": {"coordinates":[-0.347314,53.762788],"type":"Point"}
}
