{
  "type": "Feature",
  "properties": {
    "date:inception_lower": "1990-07-01",
    "date:inception_upper": "1990-07-01",
    "iso:country": "GB",
    "wof:name": "HU5 1BF",
    "wof:placetype": "postalcode"
  },
  "geometry": {"coordinates":[-0.347314,53.762788],"type":"Point"}
}
