{
  "type": "Feature",
  "properties": {
    "iso:country":"GB",
    "wof:name":"HU5 1BF",
    "wof:placetype":"postalcode"
},
  "geometry": {"coordinates":[-0.34731410853157,53.76278786705657],"type":"Point"}
}