{
  "type": "Feature",
  "properties": {
    "iso:country":"GB",
    "wof:name":"AB41 6RB",
    "wof:placetype":"postalcode"
},
  "geometry": {"coordinates":[-2.12220917678449,57.29648121516245],"type":"Point"}
}