{
  "type": "Feature",
  "properties": {
    "iso:country": "GB",
    "wof:name": "WD6 1QQ",
    "wof:placetype": "postalcode"
  },
  "geometry": {"coordinates":[-0.26181,51.65832],"type":"Point"}
}
