{
  "type": "Feature",
  "properties": {
    "date:inception_lower": "2016-11-01",
    "date:inception_upper": "2016-11-01",
    "iso:country": "GB",
    "wof:name": "W1S 2QQ",
    "wof:placetype": "postalcode"
  },
  "geometry": {"coordinates":[-0.141672,51.513188],"type":"Point"}
}
