{
  "type": "Feature",
  "properties": {
    "iso:country":"GB",
    "wof:name":"KT4 7EL",
    "wof:placetype":"postalcode"
},
  "geometry": {"coordinates":[-0.24720724409284,51.38013933710484],"type":"Point"}
}