{
  "type": "Feature",
  "properties": {
    "date:inception_lower": "1993-01-01",
    "date:inception_upper": "1993-01-01",
    "iso:country": "GB",
    "wof:name": "HP27 0QD",
    "wof:placetype": "postalcode"
  },
  "geometry": {"coordinates":[-0.81321,51.697807],"type":"Point"}
}
