{
  "type": "Feature",
  "properties": {
    "date:inception_lower": "1996-12-01",
    "date:inception_upper": "1996-12-01",
    "iso:country": "GB",
    "wof:name": "SK23 7BP",
    "wof:placetype": "postalcode"
  },
  "geometry": {"coordinates":[-1.996011,53.327913],"type":"Point"}
}
