{
  "type": "Feature",
  "properties": {
    "iso:country":"GB",
    "wof:name":"SY10 8HA",
    "wof:placetype":"postalcode"
},
  "geometry": {"coordinates":[-3.04223204839811,52.849131362481],"type":"Point"}
}