{
  "type": "Feature",
  "properties": {
    "iso:country": "GB",
    "wof:name": "SY10 8HA",
    "wof:placetype": "postalcode"
  },
  "geometry": {"coordinates":[-3.042313,52.848237],"type":"Point"}
}
