{
  "type": "Feature",
  "properties": {
    "iso:country": "GB",
    "wof:name": "EX20 2EY",
    "wof:placetype": "postalcode"
  },
  "geometry": {"coordinates":[-3.893159,50.801109],"type":"Point"}
}
