{
  "type": "Feature",
  "properties": {
    "iso:country":"GB",
    "wof:name":"SY11 1ND",
    "wof:placetype":"postalcode"
},
  "geometry": {"coordinates":[-3.05590775242047,52.86256710654573],"type":"Point"}
}