{
  "type": "Feature",
  "properties": {
    "iso:country":"GB",
    "wof:name":"CO5 0PD",
    "wof:placetype":"postalcode"
},
  "geometry": {"coordinates":[0.73927305723602,51.80715592380058],"type":"Point"}
}