{
  "type": "Feature",
  "properties": {
    "date:inception_lower":"2003-05-01",
    "date:inception_upper":"2003-05-31",
    "iso:country":"GB",
    "wof:name":"KY11 8GZ",
    "wof:placetype":"postalcode"
},
  "geometry": {"coordinates":[-3.411046,56.064051],"type":"Point"}
}