{
  "type": "Feature",
  "properties": {
    "iso:country":"GB",
    "wof:name":"LA15 8EF",
    "wof:placetype":"postalcode"
},
  "geometry": {"coordinates":[-3.17534609679997,54.1575875290937],"type":"Point"}
}