{
  "type": "Feature",
  "properties": {
    "iso:country":"GB",
    "wof:name":"M5 4FE",
    "wof:placetype":"postalcode"
},
  "geometry": {"coordinates":[-2.28791341359675,53.48247621087901],"type":"Point"}
}