{
  "type": "Feature",
  "properties": {
    "iso:country": "GB",
    "wof:name": "SY22 5LP",
    "wof:placetype": "postalcode"
  },
  "geometry": {"coordinates":[-3.197955,52.751882],"type":"Point"}
}
