{
  "type": "Feature",
  "properties": {
    "iso:country":"GB",
    "wof:name":"SY22 5LP",
    "wof:placetype":"postalcode"
},
  "geometry": {"coordinates":[-3.19795490772248,52.75188243825584],"type":"Point"}
}