{
  "type": "Feature",
  "properties": {
    "iso:country":"GB",
    "wof:name":"SW6 5PX",
    "wof:placetype":"postalcode"
},
  "geometry": {"coordinates":[-0.19901531906262,51.47915392773231],"type":"Point"}
}