{
  "type": "Feature",
  "properties": {
    "iso:country":"GB",
    "wof:name":"SS2 4DG",
    "wof:placetype":"postalcode"
},
  "geometry": {"coordinates":[0.72811171521313,51.54867142906375],"type":"Point"}
}