{
  "type": "Feature",
  "properties": {
    "iso:country": "GB",
    "wof:name": "BS14 9BZ",
    "wof:placetype": "postalcode"
  },
  "geometry": {"coordinates":[-2.569179,51.423243],"type":"Point"}
}
