{
  "type": "Feature",
  "properties": {
    "iso:country":"GB",
    "wof:name":"BS14 9BZ",
    "wof:placetype":"postalcode"
},
  "geometry": {"coordinates":[-2.56917867731907,51.42324285378791],"type":"Point"}
}