{
  "type": "Feature",
  "properties": {
    "iso:country":"GB",
    "wof:name":"PR3 3FN",
    "wof:placetype":"postalcode"
},
  "geometry": {"coordinates":[-2.6086570852135,53.82785317581418],"type":"Point"}
}