{
  "type": "Feature",
  "properties": {
    "date:inception_lower":"2012-02-01",
    "date:inception_upper":"2012-02-29",
    "iso:country":"GB",
    "wof:name":"FY1 4TQ",
    "wof:placetype":"postalcode"
},
  "geometry": {"coordinates":[-3.055084,53.814914],"type":"Point"}
}