{
  "type": "Feature",
  "properties": {
    "iso:country": "GB",
    "wof:name": "SS12 0PX",
    "wof:placetype": "postalcode"
  },
  "geometry": {"coordinates":[0.515576,51.601748],"type":"Point"}
}
