{
  "type": "Feature",
  "properties": {
    "iso:country": "GB",
    "wof:name": "SN11 9DG",
    "wof:placetype": "postalcode"
  },
  "geometry": {"coordinates":[-2.008787,51.448822],"type":"Point"}
}
