{
  "type": "Feature",
  "properties": {
    "iso:country": "GB",
    "wof:name": "WA7 5GE",
    "wof:placetype": "postalcode"
  },
  "geometry": {"coordinates":[-2.73186,53.337649],"type":"Point"}
}
