{
  "type": "Feature",
  "properties": {
    "iso:country":"GB",
    "wof:name":"TW20 8PG",
    "wof:placetype":"postalcode"
},
  "geometry": {"coordinates":[-0.53775888890517,51.42130833492332],"type":"Point"}
}