{
  "type": "Feature",
  "properties": {
    "iso:country": "GB",
    "wof:name": "BB9 8QT",
    "wof:placetype": "postalcode"
  },
  "geometry": {"coordinates":[-2.218984,53.849088],"type":"Point"}
}
