{
  "type": "Feature",
  "properties": {
    "iso:country":"GB",
    "wof:name":"M33 2WD",
    "wof:placetype":"postalcode"
},
  "geometry": {"coordinates":[-2.29959841533531,53.4278242961196],"type":"Point"}
}