{
  "type": "Feature",
  "properties": {
    "date:inception_lower":"1980-01-01",
    "date:inception_upper":"1980-01-31",
    "iso:country":"GB",
    "wof:name":"EX38 7NP",
    "wof:placetype":"postalcode"
},
  "geometry": {"coordinates":[-4.130774,50.95291],"type":"Point"}
}