{
  "type": "Feature",
  "properties": {
    "iso:country":"GB",
    "wof:name":"PH2 6AS",
    "wof:placetype":"postalcode"
},
  "geometry": {"coordinates":[-3.34037562628466,56.45930889252802],"type":"Point"}
}