{
  "type": "Feature",
  "properties": {
    "iso:country": "GB",
    "wof:name": "LL28 4PL",
    "wof:placetype": "postalcode"
  },
  "geometry": {"coordinates":[-3.743449,53.310623],"type":"Point"}
}
