{
  "type": "Feature",
  "properties": {
    "iso:country": "GB",
    "wof:name": "N3 3HN",
    "wof:placetype": "postalcode"
  },
  "geometry": {"coordinates":[-0.197432,51.597455],"type":"Point"}
}
