{
  "type": "Feature",
  "properties": {
    "iso:country":"GB",
    "wof:name":"L22 2BA",
    "wof:placetype":"postalcode"
},
  "geometry": {"coordinates":[-3.03263484624292,53.48310624354258],"type":"Point"}
}