{
  "type": "Feature",
  "properties": {
    "iso:country":"GB",
    "wof:name":"SR4 6AZ",
    "wof:placetype":"postalcode"
},
  "geometry": {"coordinates":[-1.39612049010453,54.90962220990242],"type":"Point"}
}