{
  "type": "Feature",
  "properties": {
    "iso:country": "GB",
    "wof:name": "SR4 6AZ",
    "wof:placetype": "postalcode"
  },
  "geometry": {"coordinates":[-1.39612,54.909622],"type":"Point"}
}
