{
  "type": "Feature",
  "properties": {
    "date:inception_lower":"1986-04-01",
    "date:inception_upper":"1986-04-30",
    "iso:country":"GB",
    "wof:name":"SR4 6AZ",
    "wof:placetype":"postalcode"
},
  "geometry": {"coordinates":[-1.39612,54.909622],"type":"Point"}
}