{
  "type": "Feature",
  "properties": {
    "iso:country": "GB",
    "wof:name": "RG6 7XH",
    "wof:placetype": "postalcode"
  },
  "geometry": {"coordinates":[-0.903034,51.434683],"type":"Point"}
}
