{
  "type": "Feature",
  "properties": {
    "iso:country":"GB",
    "wof:name":"RG6 7XH",
    "wof:placetype":"postalcode"
},
  "geometry": {"coordinates":[-0.90303424959942,51.43468295971117],"type":"Point"}
}