{
  "type": "Feature",
  "properties": {
    "iso:country": "GB",
    "wof:name": "IP6 9GA",
    "wof:placetype": "postalcode"
  },
  "geometry": {"coordinates":[1.147661,52.173656],"type":"Point"}
}
