{
  "type": "Feature",
  "properties": {
    "date:inception_lower": "1980-01-01",
    "date:inception_upper": "1980-01-01",
    "iso:country": "GB",
    "wof:name": "WF17 8AY",
    "wof:placetype": "postalcode"
  },
  "geometry": {"coordinates":[-1.659493,53.725122],"type":"Point"}
}
