{
  "type": "Feature",
  "properties": {
    "iso:country":"GB",
    "wof:name":"WF17 8AY",
    "wof:placetype":"postalcode"
},
  "geometry": {"coordinates":[-1.65949333583624,53.72512217041463],"type":"Point"}
}