{
  "type": "Feature",
  "properties": {
    "iso:country":"GB",
    "wof:name":"DL3 8RJ",
    "wof:placetype":"postalcode"
},
  "geometry": {"coordinates":[-1.57904707270454,54.52426344148929],"type":"Point"}
}