{
  "type": "Feature",
  "properties": {
    "date:inception_lower": "1980-01-01",
    "date:inception_upper": "1980-01-01",
    "iso:country": "GB",
    "wof:name": "DL3 8RJ",
    "wof:placetype": "postalcode"
  },
  "geometry": {"coordinates":[-1.579047,54.524263],"type":"Point"}
}
