{
  "type": "Feature",
  "properties": {
    "date:inception_lower": "1993-08-01",
    "date:inception_upper": "1993-08-01",
    "iso:country": "GB",
    "wof:name": "CA11 0PU",
    "wof:placetype": "postalcode"
  },
  "geometry": {"coordinates":[-2.964477,54.531501],"type":"Point"}
}
