{
  "type": "Feature",
  "properties": {
    "iso:country":"GB",
    "wof:name":"CA11 0PU",
    "wof:placetype":"postalcode"
},
  "geometry": {"coordinates":[-2.96447721287761,54.53150077255373],"type":"Point"}
}