{
  "type": "Feature",
  "properties": {
    "date:inception_lower": "1999-06-01",
    "date:inception_upper": "1999-06-01",
    "iso:country": "GB",
    "wof:name": "PR5 6HG",
    "wof:placetype": "postalcode"
  },
  "geometry": {"coordinates":[-2.660983,53.735304],"type":"Point"}
}
