{
  "type": "Feature",
  "properties": {
    "iso:country":"GB",
    "wof:name":"PR5 6HG",
    "wof:placetype":"postalcode"
},
  "geometry": {"coordinates":[-2.66098315807027,53.73530372534635],"type":"Point"}
}