{
  "type": "Feature",
  "properties": {
    "iso:country":"GB",
    "wof:name":"SO31 7DB",
    "wof:placetype":"postalcode"
},
  "geometry": {"coordinates":[-1.29412648890925,50.86314497928016],"type":"Point"}
}