{
  "type": "Feature",
  "properties": {
    "date:inception_lower": "1994-12-01",
    "date:inception_upper": "1994-12-01",
    "iso:country": "GB",
    "wof:name": "SO31 7DB",
    "wof:placetype": "postalcode"
  },
  "geometry": {"coordinates":[-1.294126,50.863145],"type":"Point"}
}
