{
  "type": "Feature",
  "properties": {
    "iso:country":"GB",
    "wof:name":"W6 0JA",
    "wof:placetype":"postalcode"
},
  "geometry": {"coordinates":[-0.2343219900725,51.49494205855536],"type":"Point"}
}