{
  "type": "Feature",
  "properties": {
    "iso:country": "GB",
    "wof:name": "AL9 6AA",
    "wof:placetype": "postalcode"
  },
  "geometry": {"coordinates":[-0.142792,51.767174],"type":"Point"}
}
