{
  "type": "Feature",
  "properties": {
    "date:inception_lower":"1980-01-01",
    "date:inception_upper":"1980-01-31",
    "iso:country":"GB",
    "wof:name":"AL9 6AA",
    "wof:placetype":"postalcode"
},
  "geometry": {"coordinates":[-0.142792,51.767174],"type":"Point"}
}