{
  "type": "Feature",
  "properties": {
    "iso:country":"GB",
    "wof:name":"WD3 3DX",
    "wof:placetype":"postalcode"
},
  "geometry": {"coordinates":[-0.44412008922681,51.6469659977821],"type":"Point"}
}