{
  "type": "Feature",
  "properties": {
    "date:inception_lower": "2021-07-01",
    "date:inception_upper": "2021-07-01",
    "iso:country": "GB",
    "wof:name": "CW7 2XP",
    "wof:placetype": "postalcode"
  },
  "geometry": {"coordinates":[-2.558484,53.194674],"type":"Point"}
}
