{
  "type": "Feature",
  "properties": {
    "iso:country":"GB",
    "wof:name":"NW3 2LT",
    "wof:placetype":"postalcode"
},
  "geometry": {"coordinates":[-0.1598323360528,51.55490070661695],"type":"Point"}
}