{
  "type": "Feature",
  "properties": {
    "iso:country":"GB",
    "wof:name":"RG45 7HJ",
    "wof:placetype":"postalcode"
},
  "geometry": {"coordinates":[-0.78209109976483,51.36423214328954],"type":"Point"}
}