{
  "type": "Feature",
  "properties": {
    "iso:country":"GB",
    "wof:name":"SA61 1EX",
    "wof:placetype":"postalcode"
},
  "geometry": {"coordinates":[-4.98832625531737,51.79421061126753],"type":"Point"}
}