{
  "type": "Feature",
  "properties": {
    "iso:country":"GB",
    "wof:name":"DA12 3HQ",
    "wof:placetype":"postalcode"
},
  "geometry": {"coordinates":[0.43537162716619,51.42429900039588],"type":"Point"}
}