{
  "type": "Feature",
  "properties": {
    "iso:country": "GB",
    "wof:name": "DN38 6AH",
    "wof:placetype": "postalcode"
  },
  "geometry": {"coordinates":[-0.359266,53.529797],"type":"Point"}
}
