{
  "type": "Feature",
  "properties": {
    "iso:country":"GB",
    "wof:name":"DN38 6AH",
    "wof:placetype":"postalcode"
},
  "geometry": {"coordinates":[-0.35926616382566,53.52979718389277],"type":"Point"}
}