{
  "type": "Feature",
  "properties": {
    "date:inception_lower": "2010-05-01",
    "date:inception_upper": "2010-05-01",
    "iso:country": "GB",
    "wof:name": "G20 9PR",
    "wof:placetype": "postalcode"
  },
  "geometry": {"coordinates":[-4.277999,55.886998],"type":"Point"}
}
