{
  "type": "Feature",
  "properties": {
    "iso:country":"GB",
    "wof:name":"G20 9PR",
    "wof:placetype":"postalcode"
},
  "geometry": {"coordinates":[-4.27799932866484,55.8869977856853],"type":"Point"}
}