{
  "type": "Feature",
  "properties": {
    "iso:country":"GB",
    "wof:name":"E17 7QA",
    "wof:placetype":"postalcode"
},
  "geometry": {"coordinates":[-0.02345686958552,51.58015479120976],"type":"Point"}
}