{
  "type": "Feature",
  "properties": {
    "iso:country":"GB",
    "wof:name":"TS25 2JT",
    "wof:placetype":"postalcode"
},
  "geometry": {"coordinates":[-1.24454253989801,54.65179892623146],"type":"Point"}
}