{
  "type": "Feature",
  "properties": {
    "iso:country":"GB",
    "wof:name":"DN16 3EB",
    "wof:placetype":"postalcode"
},
  "geometry": {"coordinates":[-0.63900211935485,53.56308009870543],"type":"Point"}
}