{
  "type": "Feature",
  "properties": {
    "iso:country": "GB",
    "wof:name": "DN16 3EB",
    "wof:placetype": "postalcode"
  },
  "geometry": {"coordinates":[-0.639002,53.56308],"type":"Point"}
}
