{
  "type": "Feature",
  "properties": {
    "iso:country": "GB",
    "wof:name": "PH1 1PD",
    "wof:placetype": "postalcode"
  },
  "geometry": {"coordinates":[-3.451079,56.397872],"type":"Point"}
}
