{
  "type": "Feature",
  "properties": {
    "iso:country":"GB",
    "wof:name":"M9 6QZ",
    "wof:placetype":"postalcode"
},
  "geometry": {"coordinates":[-2.21139799012587,53.53486785748061],"type":"Point"}
}