{
  "type": "Feature",
  "properties": {
    "date:inception_lower": "1997-06-01",
    "date:inception_upper": "1997-06-01",
    "iso:country": "GB",
    "wof:name": "S35 0JS",
    "wof:placetype": "postalcode"
  },
  "geometry": {"coordinates":[-1.536484,53.435599],"type":"Point"}
}
