{
  "type": "Feature",
  "properties": {
    "iso:country":"GB",
    "wof:name":"LS29 8SF",
    "wof:placetype":"postalcode"
},
  "geometry": {"coordinates":[-1.79881867728097,53.92194892149714],"type":"Point"}
}