{
  "type": "Feature",
  "properties": {
    "date:inception_lower":"1980-01-01",
    "date:inception_upper":"1980-01-31",
    "iso:country":"GB",
    "wof:name":"LS29 8SF",
    "wof:placetype":"postalcode"
},
  "geometry": {"coordinates":[-1.798819,53.921949],"type":"Point"}
}