{
  "type": "Feature",
  "properties": {
    "date:inception_lower": "2019-06-01",
    "date:inception_upper": "2019-06-01",
    "iso:country": "GB",
    "wof:name": "KY5 0AT",
    "wof:placetype": "postalcode"
  },
  "geometry": {"coordinates":[-3.259827,56.141859],"type":"Point"}
}
