{
  "type": "Feature",
  "properties": {
    "iso:country": "GB",
    "wof:name": "KY5 0AT",
    "wof:placetype": "postalcode"
  },
  "geometry": {"coordinates":[-3.259827,56.141859],"type":"Point"}
}
