{
  "type": "Feature",
  "properties": {
    "iso:country":"GB",
    "wof:name":"MK45 3DU",
    "wof:placetype":"postalcode"
},
  "geometry": {"coordinates":[-0.41682551286578,52.08686231548407],"type":"Point"}
}