{
  "type": "Feature",
  "properties": {
    "date:inception_lower": "1980-01-01",
    "date:inception_upper": "1980-01-01",
    "iso:country": "GB",
    "wof:name": "YO25 9QZ",
    "wof:placetype": "postalcode"
  },
  "geometry": {"coordinates":[-0.430959,53.955512],"type":"Point"}
}
