{
  "type": "Feature",
  "properties": {
    "iso:country": "GB",
    "wof:name": "DN22 6UF",
    "wof:placetype": "postalcode"
  },
  "geometry": {"coordinates":[-0.928032,53.32925],"type":"Point"}
}
