{
  "type": "Feature",
  "properties": {
    "iso:country":"GB",
    "wof:name":"DN22 6UF",
    "wof:placetype":"postalcode"
},
  "geometry": {"coordinates":[-0.92803200075792,53.32925037147778],"type":"Point"}
}