{
  "type": "Feature",
  "properties": {
    "iso:country":"GB",
    "wof:name":"BD7 4PF",
    "wof:placetype":"postalcode"
},
  "geometry": {"coordinates":[-1.7988917886192,53.7733341692124],"type":"Point"}
}