{
  "type": "Feature",
  "properties": {
    "date:inception_lower": "1980-01-01",
    "date:inception_upper": "1980-01-01",
    "iso:country": "GB",
    "wof:name": "LL22 7AR",
    "wof:placetype": "postalcode"
  },
  "geometry": {"coordinates":[-3.581875,53.281672],"type":"Point"}
}
