{
  "type": "Feature",
  "properties": {
    "iso:country": "GB",
    "wof:name": "WA8 8BL",
    "wof:placetype": "postalcode"
  },
  "geometry": {"coordinates":[-2.766177,53.367027],"type":"Point"}
}
