{
  "type": "Feature",
  "properties": {
    "iso:country":"GB",
    "wof:name":"HP16 0BY",
    "wof:placetype":"postalcode"
},
  "geometry": {"coordinates":[-0.70662921521491,51.70228434274114],"type":"Point"}
}