{
  "type": "Feature",
  "properties": {
    "iso:country": "GB",
    "wof:name": "HP16 0BY",
    "wof:placetype": "postalcode"
  },
  "geometry": {"coordinates":[-0.706629,51.702284],"type":"Point"}
}
