{
  "type": "Feature",
  "properties": {
    "iso:country":"GB",
    "wof:name":"TS10 4ND",
    "wof:placetype":"postalcode"
},
  "geometry": {"coordinates":[-1.0651651936057,54.59543886051802],"type":"Point"}
}