{
  "type": "Feature",
  "properties": {
    "iso:country": "GB",
    "wof:name": "PL22 0AJ",
    "wof:placetype": "postalcode"
  },
  "geometry": {"coordinates":[-4.674067,50.409563],"type":"Point"}
}
