{
  "type": "Feature",
  "properties": {
    "iso:country":"GB",
    "wof:name":"TR2 5RD",
    "wof:placetype":"postalcode"
},
  "geometry": {"coordinates":[-4.89159457604804,50.21884259164633],"type":"Point"}
}