{
  "type": "Feature",
  "properties": {
    "iso:country":"GB",
    "wof:name":"LE16 9JH",
    "wof:placetype":"postalcode"
},
  "geometry": {"coordinates":[-0.92550630085114,52.46615779191853],"type":"Point"}
}