{
  "type": "Feature",
  "properties": {
    "iso:country": "GB",
    "wof:name": "ME12 3NS",
    "wof:placetype": "postalcode"
  },
  "geometry": {"coordinates":[0.805549,51.42039],"type":"Point"}
}
