{
  "type": "Feature",
  "properties": {
    "iso:country":"GB",
    "wof:name":"LU7 9DR",
    "wof:placetype":"postalcode"
},
  "geometry": {"coordinates":[-0.64395061854682,51.87744451964369],"type":"Point"}
}