{
  "type": "Feature",
  "properties": {
    "iso:country": "GB",
    "wof:name": "LU7 9DR",
    "wof:placetype": "postalcode"
  },
  "geometry": {"coordinates":[-0.643951,51.877445],"type":"Point"}
}
