{
  "type": "Feature",
  "properties": {
    "iso:country":"GB",
    "wof:name":"NN11 2UZ",
    "wof:placetype":"postalcode"
},
  "geometry": {"coordinates":[-1.11762110160085,52.26911256842934],"type":"Point"}
}