{
  "type": "Feature",
  "properties": {
    "iso:country": "GB",
    "wof:name": "EX22 6NQ",
    "wof:placetype": "postalcode"
  },
  "geometry": {"coordinates":[-4.340809,50.796327],"type":"Point"}
}
