{
  "type": "Feature",
  "properties": {
    "iso:country": "GB",
    "wof:name": "CF31 2QQ",
    "wof:placetype": "postalcode"
  },
  "geometry": {"coordinates":[-3.567032,51.511551],"type":"Point"}
}
