{
  "type": "Feature",
  "properties": {
    "date:inception_lower": "2003-06-01",
    "date:inception_upper": "2003-06-01",
    "iso:country": "GB",
    "wof:name": "N1 3LT",
    "wof:placetype": "postalcode"
  },
  "geometry": {"coordinates":[-0.084572,51.543319],"type":"Point"}
}
