{
  "type": "Feature",
  "properties": {
    "iso:country":"GB",
    "wof:name":"N1 3LT",
    "wof:placetype":"postalcode"
},
  "geometry": {"coordinates":[-0.08457191855895,51.54331880539045],"type":"Point"}
}