{
  "type": "Feature",
  "properties": {
    "iso:country":"GB",
    "wof:name":"WS15 3JD",
    "wof:placetype":"postalcode"
},
  "geometry": {"coordinates":[-1.88910156355749,52.79507218241879],"type":"Point"}
}