{
  "type": "Feature",
  "properties": {
    "date:inception_lower": "1980-01-01",
    "date:inception_upper": "1980-01-01",
    "iso:country": "GB",
    "wof:name": "WS15 3JD",
    "wof:placetype": "postalcode"
  },
  "geometry": {"coordinates":[-1.889102,52.795072],"type":"Point"}
}
