{
  "type": "Feature",
  "properties": {
    "iso:country":"GB",
    "wof:name":"SE25 6BU",
    "wof:placetype":"postalcode"
},
  "geometry": {"coordinates":[-0.07914369603074,51.40084966873427],"type":"Point"}
}