{
  "type": "Feature",
  "properties": {
    "iso:country":"GB",
    "wof:name":"IP2 8GT",
    "wof:placetype":"postalcode"
},
  "geometry": {"coordinates":[1.15316473620376,52.04542824286253],"type":"Point"}
}