{
  "type": "Feature",
  "properties": {
    "iso:country": "GB",
    "wof:name": "IP2 8GT",
    "wof:placetype": "postalcode"
  },
  "geometry": {"coordinates":[1.153165,52.045428],"type":"Point"}
}
