{
  "type": "Feature",
  "properties": {
    "date:inception_lower": "2007-04-01",
    "date:inception_upper": "2007-04-01",
    "iso:country": "GB",
    "wof:name": "IP2 8GT",
    "wof:placetype": "postalcode"
  },
  "geometry": {"coordinates":[1.153165,52.045428],"type":"Point"}
}
