{
  "type": "Feature",
  "properties": {
    "date:inception_lower": "2017-07-01",
    "date:inception_upper": "2017-07-01",
    "iso:country": "GB",
    "wof:name": "NG22 0RZ",
    "wof:placetype": "postalcode"
  },
  "geometry": {"coordinates":[-0.89555,53.249043],"type":"Point"}
}
