{
  "type": "Feature",
  "properties": {
    "date:inception_lower": "2016-06-01",
    "date:inception_upper": "2016-06-01",
    "iso:country": "GB",
    "wof:name": "HA7 1FT",
    "wof:placetype": "postalcode"
  },
  "geometry": {"coordinates":[-0.294939,51.605752],"type":"Point"}
}
