{
  "type": "Feature",
  "properties": {
    "iso:country":"GB",
    "wof:name":"RM6 4FW",
    "wof:placetype":"postalcode"
},
  "geometry": {"coordinates":[0.12024634541805,51.57121639397469],"type":"Point"}
}