{
  "type": "Feature",
  "properties": {
    "iso:country":"GB",
    "wof:name":"PE4 6BY",
    "wof:placetype":"postalcode"
},
  "geometry": {"coordinates":[-0.26789852794775,52.62068801361081],"type":"Point"}
}