{
  "type": "Feature",
  "properties": {
    "iso:country":"GB",
    "wof:name":"HA6 2SD",
    "wof:placetype":"postalcode"
},
  "geometry": {"coordinates":[-0.44295144168292,51.60807798390114],"type":"Point"}
}