{
  "type": "Feature",
  "properties": {
    "date:inception_lower":"1980-01-01",
    "date:inception_upper":"1980-01-31",
    "iso:country":"GB",
    "wof:name":"NN7 4RR",
    "wof:placetype":"postalcode"
},
  "geometry": {"coordinates":[-1.081937,52.229354],"type":"Point"}
}