{
  "type": "Feature",
  "properties": {
    "iso:country":"GB",
    "wof:name":"NN7 4RR",
    "wof:placetype":"postalcode"
},
  "geometry": {"coordinates":[-1.08193740605666,52.2293538794664],"type":"Point"}
}