{
  "type": "Feature",
  "properties": {
    "iso:country": "GB",
    "wof:name": "NN7 4RR",
    "wof:placetype": "postalcode"
  },
  "geometry": {"coordinates":[-1.081937,52.229354],"type":"Point"}
}
