{
  "type": "Feature",
  "properties": {
    "date:inception_lower": "1999-12-01",
    "date:inception_upper": "1999-12-01",
    "iso:country": "GB",
    "wof:name": "CB8 7XA",
    "wof:placetype": "postalcode"
  },
  "geometry": {"coordinates":[0.389699,52.260838],"type":"Point"}
}
