{
  "type": "Feature",
  "properties": {
    "iso:country":"GB",
    "wof:name":"CB8 7XA",
    "wof:placetype":"postalcode"
},
  "geometry": {"coordinates":[0.3896709266796,52.26082218168825],"type":"Point"}
}