{
  "type": "Feature",
  "properties": {
    "iso:country":"GB",
    "wof:name":"NP4 8PL",
    "wof:placetype":"postalcode"
},
  "geometry": {"coordinates":[-3.05834478913726,51.73043693434511],"type":"Point"}
}