{
  "type": "Feature",
  "properties": {
    "iso:country":"GB",
    "wof:name":"BA2 8EE",
    "wof:placetype":"postalcode"
},
  "geometry": {"coordinates":[-2.42271413245548,51.31755376577699],"type":"Point"}
}