{
  "type": "Feature",
  "properties": {
    "date:inception_lower":"1990-02-01",
    "date:inception_upper":"1990-02-28",
    "iso:country":"GB",
    "wof:name":"TS15 0LD",
    "wof:placetype":"postalcode"
},
  "geometry": {"coordinates":[-1.282598,54.452266],"type":"Point"}
}