{
  "type": "Feature",
  "properties": {
    "iso:country": "GB",
    "wof:name": "TS15 0LD",
    "wof:placetype": "postalcode"
  },
  "geometry": {"coordinates":[-1.282598,54.452266],"type":"Point"}
}
