{
  "type": "Feature",
  "properties": {
    "iso:country":"GB",
    "wof:name":"BS30 9DQ",
    "wof:placetype":"postalcode"
},
  "geometry": {"coordinates":[-2.49636085659721,51.44039733262041],"type":"Point"}
}