{
  "type": "Feature",
  "properties": {
    "iso:country":"GB",
    "wof:name":"HD7 5JE",
    "wof:placetype":"postalcode"
},
  "geometry": {"coordinates":[-1.89842178944134,53.6110802261389],"type":"Point"}
}