{
  "type": "Feature",
  "properties": {
    "date:inception_lower":"1980-01-01",
    "date:inception_upper":"1980-01-31",
    "iso:country":"GB",
    "wof:name":"HD7 5JE",
    "wof:placetype":"postalcode"
},
  "geometry": {"coordinates":[-1.898422,53.61108],"type":"Point"}
}