{
  "type": "Feature",
  "properties": {
    "iso:country":"GB",
    "wof:name":"EX13 5NB",
    "wof:placetype":"postalcode"
},
  "geometry": {"coordinates":[-2.99102330515168,50.78338853326264],"type":"Point"}
}