{
  "type": "Feature",
  "properties": {
    "iso:country":"GB",
    "wof:name":"CW7 2NA",
    "wof:placetype":"postalcode"
},
  "geometry": {"coordinates":[-2.54851675550959,53.19348265702768],"type":"Point"}
}