{
  "type": "Feature",
  "properties": {
    "iso:country": "GB",
    "wof:name": "DY4 9SQ",
    "wof:placetype": "postalcode"
  },
  "geometry": {"coordinates":[-2.058201,52.532898],"type":"Point"}
}
