{
  "type": "Feature",
  "properties": {
    "iso:country":"GB",
    "wof:name":"DY4 9SQ",
    "wof:placetype":"postalcode"
},
  "geometry": {"coordinates":[-2.05820127450168,52.53289842610251],"type":"Point"}
}