{
  "type": "Feature",
  "properties": {
    "iso:country": "GB",
    "wof:name": "BS40 7XU",
    "wof:placetype": "postalcode"
  },
  "geometry": {"coordinates":[-2.76619,51.299516],"type":"Point"}
}
