{
  "type": "Feature",
  "properties": {
    "iso:country":"GB",
    "wof:name":"ST8 7BQ",
    "wof:placetype":"postalcode"
},
  "geometry": {"coordinates":[-2.16764449110933,53.10659933776169],"type":"Point"}
}