{
  "type": "Feature",
  "properties": {
    "iso:country":"GB",
    "wof:name":"WV2 2LY",
    "wof:placetype":"postalcode"
},
  "geometry": {"coordinates":[-2.09798534313506,52.57071936624937],"type":"Point"}
}