{
  "type": "Feature",
  "properties": {
    "iso:country":"GB",
    "wof:name":"CF37 4DE",
    "wof:placetype":"postalcode"
},
  "geometry": {"coordinates":[-3.32887382437837,51.60688402851734],"type":"Point"}
}