{
  "type": "Feature",
  "properties": {
    "iso:country":"GB",
    "wof:name":"CR0 4TH",
    "wof:placetype":"postalcode"
},
  "geometry": {"coordinates":[-0.13337911042157,51.37879481732389],"type":"Point"}
}