{
  "type": "Feature",
  "properties": {
    "iso:country":"GB",
    "wof:name":"LE5 6LQ",
    "wof:placetype":"postalcode"
},
  "geometry": {"coordinates":[-1.05867544316939,52.62764084712238],"type":"Point"}
}