{
  "type": "Feature",
  "properties": {
    "iso:country": "GB",
    "wof:name": "TR3 6RE",
    "wof:placetype": "postalcode"
  },
  "geometry": {"coordinates":[-5.056713,50.209384],"type":"Point"}
}
