{
  "type": "Feature",
  "properties": {
    "date:inception_lower":"1998-12-01",
    "date:inception_upper":"1998-12-31",
    "iso:country":"GB",
    "wof:name":"TR3 6RE",
    "wof:placetype":"postalcode"
},
  "geometry": {"coordinates":[-5.056713,50.209384],"type":"Point"}
}