{
  "type": "Feature",
  "properties": {
    "iso:country": "GB",
    "wof:name": "CF47 9TY",
    "wof:placetype": "postalcode"
  },
  "geometry": {"coordinates":[-3.375236,51.762231],"type":"Point"}
}
