{
  "type": "Feature",
  "properties": {
    "iso:country": "GB",
    "wof:name": "AL3 5FD",
    "wof:placetype": "postalcode"
  },
  "geometry": {"coordinates":[-0.339301,51.762487],"type":"Point"}
}
