{
  "type": "Feature",
  "properties": {
    "iso:country":"GB",
    "wof:name":"NG2 6LB",
    "wof:placetype":"postalcode"
},
  "geometry": {"coordinates":[-1.11265533684733,52.92535875145516],"type":"Point"}
}