{
  "type": "Feature",
  "properties": {
    "date:inception_lower": "1980-01-01",
    "date:inception_upper": "1980-01-01",
    "iso:country": "GB",
    "wof:name": "G74 2AU",
    "wof:placetype": "postalcode"
  },
  "geometry": {"coordinates":[-4.15147,55.763714],"type":"Point"}
}
