{
  "type": "Feature",
  "properties": {
    "date:inception_lower":"1980-01-01",
    "date:inception_upper":"1980-01-31",
    "iso:country":"GB",
    "wof:name":"EH47 7BB",
    "wof:placetype":"postalcode"
},
  "geometry": {"coordinates":[-3.587446,55.876832],"type":"Point"}
}