{
  "type": "Feature",
  "properties": {
    "iso:country":"GB",
    "wof:name":"EH47 7BB",
    "wof:placetype":"postalcode"
},
  "geometry": {"coordinates":[-3.58744604929566,55.87683208428632],"type":"Point"}
}