{
  "type": "Feature",
  "properties": {
    "date:inception_lower": "1980-01-01",
    "date:inception_upper": "1980-01-01",
    "iso:country": "GB",
    "wof:name": "SY5 6PW",
    "wof:placetype": "postalcode"
  },
  "geometry": {"coordinates":[-2.633961,52.651616],"type":"Point"}
}
