{
  "type": "Feature",
  "properties": {
    "iso:country":"GB",
    "wof:name":"SY5 6PW",
    "wof:placetype":"postalcode"
},
  "geometry": {"coordinates":[-2.63396152237058,52.65161596303924],"type":"Point"}
}