{
  "type": "Feature",
  "properties": {
    "iso:country":"GB",
    "wof:name":"L23 0TW",
    "wof:placetype":"postalcode"
},
  "geometry": {"coordinates":[-3.01080257177786,53.48517160989487],"type":"Point"}
}