{
  "type": "Feature",
  "properties": {
    "date:inception_lower": "2020-09-01",
    "date:inception_upper": "2020-09-01",
    "iso:country": "GB",
    "wof:name": "IP19 8ST",
    "wof:placetype": "postalcode"
  },
  "geometry": {"coordinates":[1.511765,52.353897],"type":"Point"}
}
