{
  "type": "Feature",
  "properties": {
    "iso:country": "GB",
    "wof:name": "PL31 2EJ",
    "wof:placetype": "postalcode"
  },
  "geometry": {"coordinates":[-4.717622,50.474783],"type":"Point"}
}
