{
  "type": "Feature",
  "properties": {
    "date:inception_lower": "1980-01-01",
    "date:inception_upper": "1980-01-01",
    "iso:country": "GB",
    "wof:name": "PL31 2EJ",
    "wof:placetype": "postalcode"
  },
  "geometry": {"coordinates":[-4.717622,50.474783],"type":"Point"}
}
