{
  "type": "Feature",
  "properties": {
    "iso:country": "GB",
    "wof:name": "CF48 4ET",
    "wof:placetype": "postalcode"
  },
  "geometry": {"coordinates":[-3.347714,51.706604],"type":"Point"}
}
