{
  "type": "Feature",
  "properties": {
    "iso:country": "GB",
    "wof:name": "LA22 9EN",
    "wof:placetype": "postalcode"
  },
  "geometry": {"coordinates":[-2.956914,54.433401],"type":"Point"}
}
