{
  "type": "Feature",
  "properties": {
    "date:inception_lower":"2005-10-01",
    "date:inception_upper":"2005-10-31",
    "iso:country":"GB",
    "wof:name":"OL10 2WP",
    "wof:placetype":"postalcode"
},
  "geometry": {"coordinates":[-2.203889,53.579643],"type":"Point"}
}