{
  "type": "Feature",
  "properties": {
    "iso:country": "GB",
    "wof:name": "CT20 3DQ",
    "wof:placetype": "postalcode"
  },
  "geometry": {"coordinates":[1.135721,51.073147],"type":"Point"}
}
