{
  "type": "Feature",
  "properties": {
    "iso:country":"GB",
    "wof:name":"EH39 5AQ",
    "wof:placetype":"postalcode"
},
  "geometry": {"coordinates":[-2.7815567061148,56.02968763482304],"type":"Point"}
}