{
  "type": "Feature",
  "properties": {
    "iso:country":"GB",
    "wof:name":"CV1 5HU",
    "wof:placetype":"postalcode"
},
  "geometry": {"coordinates":[-1.49834469057252,52.41685921101497],"type":"Point"}
}