{
  "type": "Feature",
  "properties": {
    "date:inception_lower": "1980-01-01",
    "date:inception_upper": "1980-01-01",
    "iso:country": "GB",
    "wof:name": "NR20 5TG",
    "wof:placetype": "postalcode"
  },
  "geometry": {"coordinates":[0.847045,52.772406],"type":"Point"}
}
