{
  "type": "Feature",
  "properties": {
    "iso:country":"GB",
    "wof:name":"NR20 5TG",
    "wof:placetype":"postalcode"
},
  "geometry": {"coordinates":[0.84702646572953,52.7723809854723],"type":"Point"}
}