{
  "type": "Feature",
  "properties": {
    "iso:country":"GB",
    "wof:name":"PO21 4JA",
    "wof:placetype":"postalcode"
},
  "geometry": {"coordinates":[-0.71221342998805,50.78237424457325],"type":"Point"}
}