{
  "type": "Feature",
  "properties": {
    "iso:country":"GB",
    "wof:name":"GL4 6EB",
    "wof:placetype":"postalcode"
},
  "geometry": {"coordinates":[-2.22086041821546,51.83364650786744],"type":"Point"}
}