{
  "type": "Feature",
  "properties": {
    "iso:country": "GB",
    "wof:name": "NE13 6AH",
    "wof:placetype": "postalcode"
  },
  "geometry": {"coordinates":[-1.628672,55.050875],"type":"Point"}
}
