{
  "type": "Feature",
  "properties": {
    "date:inception_lower": "1980-01-01",
    "date:inception_upper": "1980-01-01",
    "iso:country": "GB",
    "wof:name": "NE13 6AH",
    "wof:placetype": "postalcode"
  },
  "geometry": {"coordinates":[-1.628672,55.050875],"type":"Point"}
}
