{
  "type": "Feature",
  "properties": {
    "iso:country":"GB",
    "wof:name":"S60 5HS",
    "wof:placetype":"postalcode"
},
  "geometry": {"coordinates":[-1.36587430731323,53.40046959904174],"type":"Point"}
}