{
  "type": "Feature",
  "properties": {
    "iso:country":"GB",
    "wof:name":"CV3 1BP",
    "wof:placetype":"postalcode"
},
  "geometry": {"coordinates":[-1.48131363428808,52.39845482621736],"type":"Point"}
}