{
  "type": "Feature",
  "properties": {
    "date:inception_lower": "1980-01-01",
    "date:inception_upper": "1980-01-01",
    "iso:country": "GB",
    "wof:name": "BN20 7HR",
    "wof:placetype": "postalcode"
  },
  "geometry": {"coordinates":[0.280414,50.758951],"type":"Point"}
}
