{
  "type": "Feature",
  "properties": {
    "iso:country":"GB",
    "wof:name":"BN20 7HR",
    "wof:placetype":"postalcode"
},
  "geometry": {"coordinates":[0.280413698054,50.75895051253383],"type":"Point"}
}