{
  "type": "Feature",
  "properties": {
    "iso:country":"GB",
    "wof:name":"PE36 6LB",
    "wof:placetype":"postalcode"
},
  "geometry": {"coordinates":[0.54275583117619,52.95819615586259],"type":"Point"}
}