{
  "type": "Feature",
  "properties": {
    "date:inception_lower": "1991-09-01",
    "date:inception_upper": "1991-09-01",
    "iso:country": "GB",
    "wof:name": "PE36 6LB",
    "wof:placetype": "postalcode"
  },
  "geometry": {"coordinates":[0.542766,52.958222],"type":"Point"}
}
