{
  "type": "Feature",
  "properties": {
    "iso:country":"GB",
    "wof:name":"SE10 8TQ",
    "wof:placetype":"postalcode"
},
  "geometry": {"coordinates":[-0.01214772800686,51.47276248672971],"type":"Point"}
}