{
  "type": "Feature",
  "properties": {
    "iso:country":"GB",
    "wof:name":"PR9 0QY",
    "wof:placetype":"postalcode"
},
  "geometry": {"coordinates":[-2.99565156783549,53.64883928800565],"type":"Point"}
}