{
  "type": "Feature",
  "properties": {
    "date:inception_lower": "2021-01-01",
    "date:inception_upper": "2021-01-01",
    "iso:country": "GB",
    "wof:name": "NN2 8GR",
    "wof:placetype": "postalcode"
  },
  "geometry": {"coordinates":[-0.921531,52.277417],"type":"Point"}
}
