{
  "type": "Feature",
  "properties": {
    "iso:country": "GB",
    "wof:name": "OX16 3LW",
    "wof:placetype": "postalcode"
  },
  "geometry": {"coordinates":[-1.322661,52.067162],"type":"Point"}
}
