{
  "type": "Feature",
  "properties": {
    "iso:country":"GB",
    "wof:name":"OX16 3LW",
    "wof:placetype":"postalcode"
},
  "geometry": {"coordinates":[-1.32266149843979,52.06716212142959],"type":"Point"}
}