{
  "type": "Feature",
  "properties": {
    "date:inception_lower": "1980-01-01",
    "date:inception_upper": "1980-01-01",
    "iso:country": "GB",
    "wof:name": "S41 8TD",
    "wof:placetype": "postalcode"
  },
  "geometry": {"coordinates":[-1.43449,53.260553],"type":"Point"}
}
