{
  "type": "Feature",
  "properties": {
    "iso:country":"GB",
    "wof:name":"LE12 8FS",
    "wof:placetype":"postalcode"
},
  "geometry": {"coordinates":[-1.15528036466262,52.75737374099963],"type":"Point"}
}