{
  "type": "Feature",
  "properties": {
    "iso:country": "GB",
    "wof:name": "LE12 8FS",
    "wof:placetype": "postalcode"
  },
  "geometry": {"coordinates":[-1.15528,52.757374],"type":"Point"}
}
