{
  "type": "Feature",
  "properties": {
    "date:inception_lower": "2008-07-01",
    "date:inception_upper": "2008-07-01",
    "iso:country": "GB",
    "wof:name": "LE12 8FS",
    "wof:placetype": "postalcode"
  },
  "geometry": {"coordinates":[-1.15528,52.757374],"type":"Point"}
}
