{
  "type": "Feature",
  "properties": {
    "iso:country":"GB",
    "wof:name":"SW8 4HU",
    "wof:placetype":"postalcode"
},
  "geometry": {"coordinates":[-0.13590170972439,51.47439068346701],"type":"Point"}
}