{
  "type": "Feature",
  "properties": {
    "iso:country": "GB",
    "wof:name": "TS18 1AX",
    "wof:placetype": "postalcode"
  },
  "geometry": {"coordinates":[-1.319009,54.563785],"type":"Point"}
}
