{
  "type": "Feature",
  "properties": {
    "date:inception_lower": "2024-01-01",
    "date:inception_upper": "2024-01-01",
    "iso:country": "GB",
    "wof:name": "PL17 0BE",
    "wof:placetype": "postalcode"
  },
  "geometry": {"coordinates":[-4.303026,50.505486],"type":"Point"}
}
