{
  "type": "Feature",
  "properties": {
    "iso:country":"GB",
    "wof:name":"E13 0DQ",
    "wof:placetype":"postalcode"
},
  "geometry": {"coordinates":[0.01867266296511,51.52863817334843],"type":"Point"}
}