{
  "type": "Feature",
  "properties": {
    "iso:country": "GB",
    "wof:name": "PE6 7EU",
    "wof:placetype": "postalcode"
  },
  "geometry": {"coordinates":[-0.346933,52.633658],"type":"Point"}
}
