{
  "type": "Feature",
  "properties": {
    "date:inception_lower": "2000-12-01",
    "date:inception_upper": "2000-12-01",
    "iso:country": "GB",
    "wof:name": "PE6 7EU",
    "wof:placetype": "postalcode"
  },
  "geometry": {"coordinates":[-0.346933,52.633658],"type":"Point"}
}
