{
  "type": "Feature",
  "properties": {
    "iso:country":"GB",
    "wof:name":"N16 5DH",
    "wof:placetype":"postalcode"
},
  "geometry": {"coordinates":[-0.07558672962621,51.57374632599203],"type":"Point"}
}