{
  "type": "Feature",
  "properties": {
    "iso:country": "GB",
    "wof:name": "N16 5DH",
    "wof:placetype": "postalcode"
  },
  "geometry": {"coordinates":[-0.075587,51.573746],"type":"Point"}
}
