{
  "type": "Feature",
  "properties": {
    "date:inception_lower": "1980-01-01",
    "date:inception_upper": "1980-01-01",
    "iso:country": "GB",
    "wof:name": "GU4 7RP",
    "wof:placetype": "postalcode"
  },
  "geometry": {"coordinates":[-0.476158,51.248139],"type":"Point"}
}
