{
  "type": "Feature",
  "properties": {
    "iso:country":"GB",
    "wof:name":"HU7 4SP",
    "wof:placetype":"postalcode"
},
  "geometry": {"coordinates":[-0.30464776517853,53.78739767109015],"type":"Point"}
}