{
  "type": "Feature",
  "properties": {
    "iso:country":"GB",
    "wof:name":"NR10 4NY",
    "wof:placetype":"postalcode"
},
  "geometry": {"coordinates":[1.12733598327373,52.76041651668618],"type":"Point"}
}