{
  "type": "Feature",
  "properties": {
    "iso:country": "GB",
    "wof:name": "TN4 8DX",
    "wof:placetype": "postalcode"
  },
  "geometry": {"coordinates":[0.249727,51.136007],"type":"Point"}
}
