{
  "type": "Feature",
  "properties": {
    "iso:country":"GB",
    "wof:name":"TN4 8DX",
    "wof:placetype":"postalcode"
},
  "geometry": {"coordinates":[0.24972688263726,51.13600674006553],"type":"Point"}
}