{
  "type": "Feature",
  "properties": {
    "iso:country": "GB",
    "wof:name": "TN25 7FZ",
    "wof:placetype": "postalcode"
  },
  "geometry": {"coordinates":[0.942987,51.095523],"type":"Point"}
}
