{
  "type": "Feature",
  "properties": {
    "date:inception_lower": "1994-12-01",
    "date:inception_upper": "1994-12-01",
    "iso:country": "GB",
    "wof:name": "M90 3FE",
    "wof:placetype": "postalcode"
  },
  "geometry": {"coordinates":[-2.273258,53.361624],"type":"Point"}
}
