{
  "type": "Feature",
  "properties": {
    "iso:country": "GB",
    "wof:name": "GL51 3DW",
    "wof:placetype": "postalcode"
  },
  "geometry": {"coordinates":[-2.096965,51.879524],"type":"Point"}
}
