{
  "type": "Feature",
  "properties": {
    "date:inception_lower": "2005-11-01",
    "date:inception_upper": "2005-11-01",
    "iso:country": "GB",
    "wof:name": "NG24 3NQ",
    "wof:placetype": "postalcode"
  },
  "geometry": {"coordinates":[-0.774145,53.056018],"type":"Point"}
}
