{
  "type": "Feature",
  "properties": {
    "iso:country": "GB",
    "wof:name": "NG24 3NQ",
    "wof:placetype": "postalcode"
  },
  "geometry": {"coordinates":[-0.774145,53.056018],"type":"Point"}
}
