{
  "type": "Feature",
  "properties": {
    "iso:country":"GB",
    "wof:name":"NG24 3NQ",
    "wof:placetype":"postalcode"
},
  "geometry": {"coordinates":[-0.77414537411833,53.05601771416871],"type":"Point"}
}