{
  "type": "Feature",
  "properties": {
    "iso:country": "GB",
    "wof:name": "LL18 5JG",
    "wof:placetype": "postalcode"
  },
  "geometry": {"coordinates":[-3.510894,53.300311],"type":"Point"}
}
