{
  "type": "Feature",
  "properties": {
    "iso:country":"GB",
    "wof:name":"LL18 5JG",
    "wof:placetype":"postalcode"
},
  "geometry": {"coordinates":[-3.51089418280562,53.30031134890417],"type":"Point"}
}