{
  "type": "Feature",
  "properties": {
    "date:inception_lower": "2000-10-01",
    "date:inception_upper": "2000-10-01",
    "iso:country": "GB",
    "wof:name": "OX26 2DX",
    "wof:placetype": "postalcode"
  },
  "geometry": {"coordinates":[-1.159371,51.905578],"type":"Point"}
}
