{
  "type": "Feature",
  "properties": {
    "date:inception_lower": "1997-12-01",
    "date:inception_upper": "1997-12-01",
    "iso:country": "GB",
    "wof:name": "BS34 5TL",
    "wof:placetype": "postalcode"
  },
  "geometry": {"coordinates":[-2.5972,51.530526],"type":"Point"}
}
