{
  "type": "Feature",
  "properties": {
    "iso:country":"GB",
    "wof:name":"BS34 5TL",
    "wof:placetype":"postalcode"
},
  "geometry": {"coordinates":[-2.59720007609398,51.53052613180861],"type":"Point"}
}