{
  "type": "Feature",
  "properties": {
    "date:inception_lower":"1980-01-01",
    "date:inception_upper":"1980-01-31",
    "iso:country":"GB",
    "wof:name":"S6 5SB",
    "wof:placetype":"postalcode"
},
  "geometry": {"coordinates":[-1.537854,53.385582],"type":"Point"}
}