{
  "type": "Feature",
  "properties": {
    "iso:country": "GB",
    "wof:name": "S6 5SB",
    "wof:placetype": "postalcode"
  },
  "geometry": {"coordinates":[-1.537854,53.385582],"type":"Point"}
}
