{
  "type": "Feature",
  "properties": {
    "date:inception_lower": "1980-01-01",
    "date:inception_upper": "1980-01-01",
    "iso:country": "GB",
    "wof:name": "S6 5SB",
    "wof:placetype": "postalcode"
  },
  "geometry": {"coordinates":[-1.537839,53.385564],"type":"Point"}
}
