{
  "type": "Feature",
  "properties": {
    "iso:country":"GB",
    "wof:name":"HA2 6HL",
    "wof:placetype":"postalcode"
},
  "geometry": {"coordinates":[-0.36387354050849,51.59429660166028],"type":"Point"}
}