{
  "type": "Feature",
  "properties": {
    "iso:country":"GB",
    "wof:name":"W3 9NX",
    "wof:placetype":"postalcode"
},
  "geometry": {"coordinates":[-0.27338739237976,51.50800512306969],"type":"Point"}
}