{
  "type": "Feature",
  "properties": {
    "iso:country": "GB",
    "wof:name": "KT17 2LL",
    "wof:placetype": "postalcode"
  },
  "geometry": {"coordinates":[-0.239584,51.364207],"type":"Point"}
}
