{
  "type": "Feature",
  "properties": {
    "date:inception_lower":"1980-01-01",
    "date:inception_upper":"1980-01-31",
    "iso:country":"GB",
    "wof:name":"KT17 2LL",
    "wof:placetype":"postalcode"
},
  "geometry": {"coordinates":[-0.239584,51.364207],"type":"Point"}
}