{
  "type": "Feature",
  "properties": {
    "iso:country": "GB",
    "wof:name": "DN4 6RH",
    "wof:placetype": "postalcode"
  },
  "geometry": {"coordinates":[-1.067416,53.506353],"type":"Point"}
}
