{
  "type": "Feature",
  "properties": {
    "date:inception_lower": "2001-06-01",
    "date:inception_upper": "2001-06-01",
    "iso:country": "GB",
    "wof:name": "OX28 1NB",
    "wof:placetype": "postalcode"
  },
  "geometry": {"coordinates":[-1.479132,51.793339],"type":"Point"}
}
