{
  "type": "Feature",
  "properties": {
    "iso:country": "GB",
    "wof:name": "OX28 1NB",
    "wof:placetype": "postalcode"
  },
  "geometry": {"coordinates":[-1.479132,51.793339],"type":"Point"}
}
