{
  "type": "Feature",
  "properties": {
    "iso:country": "GB",
    "wof:name": "CF64 5SE",
    "wof:placetype": "postalcode"
  },
  "geometry": {"coordinates":[-3.241588,51.402114],"type":"Point"}
}
