{
  "type": "Feature",
  "properties": {
    "iso:country":"GB",
    "wof:name":"SE26 4NE",
    "wof:placetype":"postalcode"
},
  "geometry": {"coordinates":[-0.06323686579788,51.43637888542865],"type":"Point"}
}