{
  "type": "Feature",
  "properties": {
    "iso:country":"GB",
    "wof:name":"EX4 3QG",
    "wof:placetype":"postalcode"
},
  "geometry": {"coordinates":[-3.52861611137318,50.72608499617532],"type":"Point"}
}