{
  "type": "Feature",
  "properties": {
    "iso:country": "GB",
    "wof:name": "EX4 3QG",
    "wof:placetype": "postalcode"
  },
  "geometry": {"coordinates":[-3.528616,50.726085],"type":"Point"}
}
