{
  "type": "Feature",
  "properties": {
    "iso:country": "GB",
    "wof:name": "B75 5SS",
    "wof:placetype": "postalcode"
  },
  "geometry": {"coordinates":[-1.787144,52.609207],"type":"Point"}
}
