{
  "type": "Feature",
  "properties": {
    "iso:country":"GB",
    "wof:name":"B75 5SS",
    "wof:placetype":"postalcode"
},
  "geometry": {"coordinates":[-1.78714378116,52.60920748021203],"type":"Point"}
}