{
  "type": "Feature",
  "properties": {
    "iso:country":"GB",
    "wof:name":"BS16 1NB",
    "wof:placetype":"postalcode"
},
  "geometry": {"coordinates":[-2.5197225102801,51.4945333566417],"type":"Point"}
}