{
  "type": "Feature",
  "properties": {
    "date:inception_lower": "2001-12-01",
    "date:inception_upper": "2001-12-01",
    "iso:country": "GB",
    "wof:name": "WS5 4NY",
    "wof:placetype": "postalcode"
  },
  "geometry": {"coordinates":[-1.984555,52.563909],"type":"Point"}
}
