{
  "type": "Feature",
  "properties": {
    "iso:country":"GB",
    "wof:name":"SE3 0AU",
    "wof:placetype":"postalcode"
},
  "geometry": {"coordinates":[0.0107482738791,51.46623000048631],"type":"Point"}
}