{
  "type": "Feature",
  "properties": {
    "iso:country":"GB",
    "wof:name":"GL7 3PJ",
    "wof:placetype":"postalcode"
},
  "geometry": {"coordinates":[-1.71685068165865,51.72851664178524],"type":"Point"}
}