{
  "type": "Feature",
  "properties": {
    "iso:country":"GB",
    "wof:name":"TN25 4PG",
    "wof:placetype":"postalcode"
},
  "geometry": {"coordinates":[0.87988717935758,51.17723435997905],"type":"Point"}
}