{
  "type": "Feature",
  "properties": {
    "iso:country": "GB",
    "wof:name": "TN25 4PG",
    "wof:placetype": "postalcode"
  },
  "geometry": {"coordinates":[0.879887,51.177234],"type":"Point"}
}
