{
  "type": "Feature",
  "properties": {
    "date:inception_lower": "2021-06-01",
    "date:inception_upper": "2021-06-01",
    "iso:country": "GB",
    "wof:name": "WF9 3FH",
    "wof:placetype": "postalcode"
  },
  "geometry": {"coordinates":[-1.338422,53.586869],"type":"Point"}
}
