{
  "type": "Feature",
  "properties": {
    "iso:country":"GB",
    "wof:name":"B91 2DJ",
    "wof:placetype":"postalcode"
},
  "geometry": {"coordinates":[-1.78126049965362,52.42618004420696],"type":"Point"}
}