{
  "type": "Feature",
  "properties": {
    "iso:country": "GB",
    "wof:name": "IP16 4UP",
    "wof:placetype": "postalcode"
  },
  "geometry": {"coordinates":[1.595146,52.21584],"type":"Point"}
}
