{
  "type": "Feature",
  "properties": {
    "iso:country": "GB",
    "wof:name": "G15 6SN",
    "wof:placetype": "postalcode"
  },
  "geometry": {"coordinates":[-4.370609,55.901966],"type":"Point"}
}
