{
  "type": "Feature",
  "properties": {
    "date:inception_lower": "1980-01-01",
    "date:inception_upper": "1980-01-01",
    "iso:country": "GB",
    "wof:name": "G15 6SN",
    "wof:placetype": "postalcode"
  },
  "geometry": {"coordinates":[-4.370609,55.901966],"type":"Point"}
}
