{
  "type": "Feature",
  "properties": {
    "date:inception_lower": "1980-01-01",
    "date:inception_upper": "1980-01-01",
    "iso:country": "GB",
    "wof:name": "ST3 4PX",
    "wof:placetype": "postalcode"
  },
  "geometry": {"coordinates":[-2.118719,52.980217],"type":"Point"}
}
