{
  "type": "Feature",
  "properties": {
    "date:inception_lower": "2001-12-01",
    "date:inception_upper": "2001-12-01",
    "iso:country": "GB",
    "wof:name": "WR11 2XG",
    "wof:placetype": "postalcode"
  },
  "geometry": {"coordinates":[-1.95419,52.083114],"type":"Point"}
}
