{
  "type": "Feature",
  "properties": {
    "date:inception_lower":"1992-01-01",
    "date:inception_upper":"1992-01-31",
    "iso:country":"GB",
    "wof:name":"BA20 2TA",
    "wof:placetype":"postalcode"
},
  "geometry": {"coordinates":[-2.660764,50.928988],"type":"Point"}
}