{
  "type": "Feature",
  "properties": {
    "iso:country":"GB",
    "wof:name":"BA20 2TA",
    "wof:placetype":"postalcode"
},
  "geometry": {"coordinates":[-2.66076357190347,50.92898840828187],"type":"Point"}
}