{
  "type": "Feature",
  "properties": {
    "date:inception_lower": "2003-02-01",
    "date:inception_upper": "2003-02-01",
    "iso:country": "GB",
    "wof:name": "NG12 3TL",
    "wof:placetype": "postalcode"
  },
  "geometry": {"coordinates":[-0.951899,52.954114],"type":"Point"}
}
