{
  "type": "Feature",
  "properties": {
    "iso:country": "GB",
    "wof:name": "PR4 1HX",
    "wof:placetype": "postalcode"
  },
  "geometry": {"coordinates":[-2.876139,53.766416],"type":"Point"}
}
