{
  "type": "Feature",
  "properties": {
    "date:inception_lower": "1980-01-01",
    "date:inception_upper": "1980-01-01",
    "iso:country": "GB",
    "wof:name": "PR4 1HX",
    "wof:placetype": "postalcode"
  },
  "geometry": {"coordinates":[-2.876139,53.766416],"type":"Point"}
}
