{
  "type": "Feature",
  "properties": {
    "iso:country":"GB",
    "wof:name":"RG12 8DU",
    "wof:placetype":"postalcode"
},
  "geometry": {"coordinates":[-0.78459534775793,51.40311295766822],"type":"Point"}
}