{
  "type": "Feature",
  "properties": {
    "iso:country": "GB",
    "wof:name": "LE13 0JL",
    "wof:placetype": "postalcode"
  },
  "geometry": {"coordinates":[-0.901175,52.771495],"type":"Point"}
}
