{
  "type": "Feature",
  "properties": {
    "iso:country":"GB",
    "wof:name":"NG12 5BP",
    "wof:placetype":"postalcode"
},
  "geometry": {"coordinates":[-1.0465158416636,52.86795999649955],"type":"Point"}
}