{
  "type": "Feature",
  "properties": {
    "date:inception_lower": "1980-01-01",
    "date:inception_upper": "1980-01-01",
    "iso:country": "GB",
    "wof:name": "NG12 5BP",
    "wof:placetype": "postalcode"
  },
  "geometry": {"coordinates":[-1.046516,52.86796],"type":"Point"}
}
