{
  "type": "Feature",
  "properties": {
    "iso:country": "GB",
    "wof:name": "S9 3WL",
    "wof:placetype": "postalcode"
  },
  "geometry": {"coordinates":[-1.434245,53.394961],"type":"Point"}
}
