{
  "type": "Feature",
  "properties": {
    "iso:country":"GB",
    "wof:name":"G83 7AG",
    "wof:placetype":"postalcode"
},
  "geometry": {"coordinates":[-4.74927710680571,56.19401665598298],"type":"Point"}
}