{
  "type": "Feature",
  "properties": {
    "iso:country": "GB",
    "wof:name": "G83 7AG",
    "wof:placetype": "postalcode"
  },
  "geometry": {"coordinates":[-4.749277,56.194017],"type":"Point"}
}
