{
  "type": "Feature",
  "properties": {
    "date:inception_lower":"1980-01-01",
    "date:inception_upper":"1980-01-31",
    "iso:country":"GB",
    "wof:name":"G83 7AG",
    "wof:placetype":"postalcode"
},
  "geometry": {"coordinates":[-4.749277,56.194017],"type":"Point"}
}