{
  "type": "Feature",
  "properties": {
    "iso:country":"GB",
    "wof:name":"FK4 1TF",
    "wof:placetype":"postalcode"
},
  "geometry": {"coordinates":[-3.9534127092911,55.99027239585289],"type":"Point"}
}