{
  "type": "Feature",
  "properties": {
    "iso:country":"GB",
    "wof:name":"SA17 4NF",
    "wof:placetype":"postalcode"
},
  "geometry": {"coordinates":[-4.27815080231743,51.76100785613343],"type":"Point"}
}