{
  "type": "Feature",
  "properties": {
    "iso:country":"GB",
    "wof:name":"B13 9YJ",
    "wof:placetype":"postalcode"
},
  "geometry": {"coordinates":[-1.87369482621341,52.44469930286519],"type":"Point"}
}