{
  "type": "Feature",
  "properties": {
    "iso:country":"GB",
    "wof:name":"LE3 8SY",
    "wof:placetype":"postalcode"
},
  "geometry": {"coordinates":[-1.19934819847072,52.6409100383614],"type":"Point"}
}