{
  "type": "Feature",
  "properties": {
    "date:inception_lower": "2004-08-01",
    "date:inception_upper": "2004-08-01",
    "iso:country": "GB",
    "wof:name": "CV9 1NT",
    "wof:placetype": "postalcode"
  },
  "geometry": {"coordinates":[-1.530944,52.571783],"type":"Point"}
}
