{
  "type": "Feature",
  "properties": {
    "iso:country": "GB",
    "wof:name": "BN1 8YW",
    "wof:placetype": "postalcode"
  },
  "geometry": {"coordinates":[-0.150686,50.864425],"type":"Point"}
}
