{
  "type": "Feature",
  "properties": {
    "iso:country":"GB",
    "wof:name":"SO50 5LW",
    "wof:placetype":"postalcode"
},
  "geometry": {"coordinates":[-1.35427362668003,50.9639571645629],"type":"Point"}
}