{
  "type": "Feature",
  "properties": {
    "date:inception_lower":"1980-01-01",
    "date:inception_upper":"1980-01-31",
    "iso:country":"GB",
    "wof:name":"S66 9LE",
    "wof:placetype":"postalcode"
},
  "geometry": {"coordinates":[-1.255709,53.395888],"type":"Point"}
}