{
  "type": "Feature",
  "properties": {
    "iso:country":"GB",
    "wof:name":"CH47 3BX",
    "wof:placetype":"postalcode"
},
  "geometry": {"coordinates":[-3.16928169445555,53.39567812634385],"type":"Point"}
}