{
  "type": "Feature",
  "properties": {
    "iso:country": "GB",
    "wof:name": "CH47 3BX",
    "wof:placetype": "postalcode"
  },
  "geometry": {"coordinates":[-3.169282,53.395678],"type":"Point"}
}
