{
  "type": "Feature",
  "properties": {
    "iso:country":"GB",
    "wof:name":"CV6 2AB",
    "wof:placetype":"postalcode"
},
  "geometry": {"coordinates":[-1.53518538975568,52.42297913114221],"type":"Point"}
}