{
  "type": "Feature",
  "properties": {
    "date:inception_lower":"1980-01-01",
    "date:inception_upper":"1980-01-31",
    "iso:country":"GB",
    "wof:name":"CV6 2AB",
    "wof:placetype":"postalcode"
},
  "geometry": {"coordinates":[-1.535185,52.422979],"type":"Point"}
}