{
  "type": "Feature",
  "properties": {
    "iso:country":"GB",
    "wof:name":"E9 7AY",
    "wof:placetype":"postalcode"
},
  "geometry": {"coordinates":[-0.04891591483279,51.54007840426684],"type":"Point"}
}