{
  "type": "Feature",
  "properties": {
    "iso:country": "GB",
    "wof:name": "BB5 2DN",
    "wof:placetype": "postalcode"
  },
  "geometry": {"coordinates":[-2.320971,53.727008],"type":"Point"}
}
