{
  "type": "Feature",
  "properties": {
    "iso:country":"GB",
    "wof:name":"BB5 2DN",
    "wof:placetype":"postalcode"
},
  "geometry": {"coordinates":[-2.32097140267292,53.72700820945635],"type":"Point"}
}