{
  "type": "Feature",
  "properties": {
    "iso:country":"GB",
    "wof:name":"AB43 9EZ",
    "wof:placetype":"postalcode"
},
  "geometry": {"coordinates":[-2.02940197032003,57.68546229013588],"type":"Point"}
}