{
  "type": "Feature",
  "properties": {
    "iso:country": "GB",
    "wof:name": "PO18 9JP",
    "wof:placetype": "postalcode"
  },
  "geometry": {"coordinates":[-0.868733,50.904988],"type":"Point"}
}
