{
  "type": "Feature",
  "properties": {
    "date:inception_lower": "2017-06-01",
    "date:inception_upper": "2017-06-01",
    "iso:country": "GB",
    "wof:name": "E3 4US",
    "wof:placetype": "postalcode"
  },
  "geometry": {"coordinates":[-0.028476,51.524892],"type":"Point"}
}
