{
  "type": "Feature",
  "properties": {
    "iso:country":"GB",
    "wof:name":"UB1 2AE",
    "wof:placetype":"postalcode"
},
  "geometry": {"coordinates":[-0.37653866228364,51.51518827737227],"type":"Point"}
}