{
  "type": "Feature",
  "properties": {
    "iso:country":"GB",
    "wof:name":"S35 4EY",
    "wof:placetype":"postalcode"
},
  "geometry": {"coordinates":[-1.49940200037817,53.47467541466611],"type":"Point"}
}