{
  "type": "Feature",
  "properties": {
    "iso:country":"GB",
    "wof:name":"WR14 2PB",
    "wof:placetype":"postalcode"
},
  "geometry": {"coordinates":[-2.30266816412098,52.11232186012391],"type":"Point"}
}