{
  "type": "Feature",
  "properties": {
    "date:inception_lower":"2014-01-01",
    "date:inception_upper":"2014-01-31",
    "iso:country":"GB",
    "wof:name":"SW4 7ED",
    "wof:placetype":"postalcode"
},
  "geometry": {"coordinates":[-0.134356,51.459322],"type":"Point"}
}