{
  "type": "Feature",
  "properties": {
    "iso:country":"GB",
    "wof:name":"SW4 7ED",
    "wof:placetype":"postalcode"
},
  "geometry": {"coordinates":[-0.13435649382285,51.45932152436696],"type":"Point"}
}