{
  "type": "Feature",
  "properties": {
    "iso:country":"GB",
    "wof:name":"B90 2QT",
    "wof:placetype":"postalcode"
},
  "geometry": {"coordinates":[-1.84275474348681,52.40330804516925],"type":"Point"}
}