{
  "type": "Feature",
  "properties": {
    "iso:country":"GB",
    "wof:name":"SW1V 2DL",
    "wof:placetype":"postalcode"
},
  "geometry": {"coordinates":[-0.14306039273294,51.49100559752489],"type":"Point"}
}