{
  "type": "Feature",
  "properties": {
    "iso:country":"GB",
    "wof:name":"WS1 4HD",
    "wof:placetype":"postalcode"
},
  "geometry": {"coordinates":[-1.98667562153019,52.57754671321111],"type":"Point"}
}