{
  "type": "Feature",
  "properties": {
    "date:inception_lower": "1985-10-01",
    "date:inception_upper": "1985-10-01",
    "iso:country": "GB",
    "wof:name": "ME14 5UA",
    "wof:placetype": "postalcode"
  },
  "geometry": {"coordinates":[0.550787,51.276973],"type":"Point"}
}
