{
  "type": "Feature",
  "properties": {
    "iso:country":"GB",
    "wof:name":"ME14 5UA",
    "wof:placetype":"postalcode"
},
  "geometry": {"coordinates":[0.55078726896805,51.27697343707044],"type":"Point"}
}