{
  "type": "Feature",
  "properties": {
    "iso:country":"GB",
    "wof:name":"LE1 6NL",
    "wof:placetype":"postalcode"
},
  "geometry": {"coordinates":[-1.13113100499,52.63268921934343],"type":"Point"}
}