{
  "type": "Feature",
  "properties": {
    "date:inception_lower":"1990-07-01",
    "date:inception_upper":"1990-07-31",
    "iso:country":"GB",
    "wof:name":"CR7 6JL",
    "wof:placetype":"postalcode"
},
  "geometry": {"coordinates":[-0.11644,51.397624],"type":"Point"}
}