{
  "type": "Feature",
  "properties": {
    "iso:country":"GB",
    "wof:name":"CR7 6JL",
    "wof:placetype":"postalcode"
},
  "geometry": {"coordinates":[-0.11644006005278,51.3976242247512],"type":"Point"}
}