{
  "type": "Feature",
  "properties": {
    "date:inception_lower":"1990-02-01",
    "date:inception_upper":"1990-02-28",
    "iso:country":"GB",
    "wof:name":"BA21 3TD",
    "wof:placetype":"postalcode"
},
  "geometry": {"coordinates":[-2.668721,50.949077],"type":"Point"}
}