{
  "type": "Feature",
  "properties": {
    "iso:country":"GB",
    "wof:name":"NE28 8TH",
    "wof:placetype":"postalcode"
},
  "geometry": {"coordinates":[-1.54814924017601,55.00563595498701],"type":"Point"}
}