{
  "type": "Feature",
  "properties": {
    "iso:country":"GB",
    "wof:name":"LU7 0SY",
    "wof:placetype":"postalcode"
},
  "geometry": {"coordinates":[-0.66461282185903,51.84983419589683],"type":"Point"}
}