{
  "type": "Feature",
  "properties": {
    "date:inception_lower": "1984-02-01",
    "date:inception_upper": "1984-02-01",
    "iso:country": "GB",
    "wof:name": "LU7 0SY",
    "wof:placetype": "postalcode"
  },
  "geometry": {"coordinates":[-0.664613,51.849834],"type":"Point"}
}
