{
  "type": "Feature",
  "properties": {
    "iso:country": "GB",
    "wof:name": "HP21 9AJ",
    "wof:placetype": "postalcode"
  },
  "geometry": {"coordinates":[-0.811937,51.794984],"type":"Point"}
}
