{
  "type": "Feature",
  "properties": {
    "iso:country": "GB",
    "wof:name": "ML11 8JE",
    "wof:placetype": "postalcode"
  },
  "geometry": {"coordinates":[-3.621333,55.699459],"type":"Point"}
}
