{
  "type": "Feature",
  "properties": {
    "iso:country":"GB",
    "wof:name":"ML11 8JE",
    "wof:placetype":"postalcode"
},
  "geometry": {"coordinates":[-3.62133269622544,55.69945883521965],"type":"Point"}
}