{
  "type": "Feature",
  "properties": {
    "iso:country":"GB",
    "wof:name":"BR5 4RN",
    "wof:placetype":"postalcode"
},
  "geometry": {"coordinates":[0.11458181962338,51.38174896341066],"type":"Point"}
}