{
  "type": "Feature",
  "properties": {
    "iso:country": "GB",
    "wof:name": "M26 4GN",
    "wof:placetype": "postalcode"
  },
  "geometry": {"coordinates":[-2.33639,53.56996],"type":"Point"}
}
