{
  "type": "Feature",
  "properties": {
    "iso:country":"GB",
    "wof:name":"M26 4GN",
    "wof:placetype":"postalcode"
},
  "geometry": {"coordinates":[-2.33639008806858,53.56995954006393],"type":"Point"}
}