{
  "type": "Feature",
  "properties": {
    "iso:country":"GB",
    "wof:name":"CV11 5SZ",
    "wof:placetype":"postalcode"
},
  "geometry": {"coordinates":[-1.46746134859288,52.52234859478099],"type":"Point"}
}