{
  "type": "Feature",
  "properties": {
    "iso:country":"GB",
    "wof:name":"S62 7NG",
    "wof:placetype":"postalcode"
},
  "geometry": {"coordinates":[-1.36126632597283,53.4731543412202],"type":"Point"}
}