{
  "type": "Feature",
  "properties": {
    "iso:country": "GB",
    "wof:name": "L1 8DP",
    "wof:placetype": "postalcode"
  },
  "geometry": {"coordinates":[-2.985054,53.399588],"type":"Point"}
}
