{
  "type": "Feature",
  "properties": {
    "iso:country":"GB",
    "wof:name":"CM9 6XL",
    "wof:placetype":"postalcode"
},
  "geometry": {"coordinates":[0.66569131713293,51.7188786437068],"type":"Point"}
}