{
  "type": "Feature",
  "properties": {
    "iso:country": "GB",
    "wof:name": "CM9 6XL",
    "wof:placetype": "postalcode"
  },
  "geometry": {"coordinates":[0.665691,51.718879],"type":"Point"}
}
