{
  "type": "Feature",
  "properties": {
    "date:inception_lower": "1994-12-01",
    "date:inception_upper": "1994-12-01",
    "iso:country": "GB",
    "wof:name": "CM9 6XL",
    "wof:placetype": "postalcode"
  },
  "geometry": {"coordinates":[0.665691,51.718879],"type":"Point"}
}
