{
  "type": "Feature",
  "properties": {
    "iso:country": "GB",
    "wof:name": "CW4 7DL",
    "wof:placetype": "postalcode"
  },
  "geometry": {"coordinates":[-2.364315,53.199249],"type":"Point"}
}
