{
  "type": "Feature",
  "properties": {
    "iso:country":"GB",
    "wof:name":"CW4 7DL",
    "wof:placetype":"postalcode"
},
  "geometry": {"coordinates":[-2.36431553811923,53.1992494036862],"type":"Point"}
}