{
  "type": "Feature",
  "properties": {
    "iso:country": "GB",
    "wof:name": "TA6 4ED",
    "wof:placetype": "postalcode"
  },
  "geometry": {"coordinates":[-2.97575,51.126426],"type":"Point"}
}
