{
  "type": "Feature",
  "properties": {
    "iso:country":"GB",
    "wof:name":"B74 3HX",
    "wof:placetype":"postalcode"
},
  "geometry": {"coordinates":[-1.88207026198227,52.58107591290498],"type":"Point"}
}