{
  "type": "Feature",
  "properties": {
    "iso:country":"GB",
    "wof:name":"IG11 9QL",
    "wof:placetype":"postalcode"
},
  "geometry": {"coordinates":[0.10232337724402,51.53680891178163],"type":"Point"}
}