{
  "type": "Feature",
  "properties": {
    "date:inception_lower": "2000-06-01",
    "date:inception_upper": "2000-06-01",
    "iso:country": "GB",
    "wof:name": "HP19 9JX",
    "wof:placetype": "postalcode"
  },
  "geometry": {"coordinates":[-0.830488,51.825633],"type":"Point"}
}
