{
  "type": "Feature",
  "properties": {
    "iso:country":"GB",
    "wof:name":"PR8 2NS",
    "wof:placetype":"postalcode"
},
  "geometry": {"coordinates":[-3.03046106259053,53.62890451875737],"type":"Point"}
}