{
  "type": "Feature",
  "properties": {
    "date:inception_lower":"1980-01-01",
    "date:inception_upper":"1980-01-31",
    "iso:country":"GB",
    "wof:name":"RH4 2DB",
    "wof:placetype":"postalcode"
},
  "geometry": {"coordinates":[-0.328277,51.231435],"type":"Point"}
}