{
  "type": "Feature",
  "properties": {
    "iso:country":"GB",
    "wof:name":"G15 8QW",
    "wof:placetype":"postalcode"
},
  "geometry": {"coordinates":[-4.37711592661574,55.91209503516453],"type":"Point"}
}