{
  "type": "Feature",
  "properties": {
    "iso:country":"GB",
    "wof:name":"RG6 3WF",
    "wof:placetype":"postalcode"
},
  "geometry": {"coordinates":[-0.90738924920149,51.42580362452327],"type":"Point"}
}