{
  "type": "Feature",
  "properties": {
    "iso:country": "GB",
    "wof:name": "RG6 3WF",
    "wof:placetype": "postalcode"
  },
  "geometry": {"coordinates":[-0.907389,51.425804],"type":"Point"}
}
