{
  "type": "Feature",
  "properties": {
    "date:inception_lower": "1980-01-01",
    "date:inception_upper": "1980-01-01",
    "iso:country": "GB",
    "wof:name": "GL7 7DZ",
    "wof:placetype": "postalcode"
  },
  "geometry": {"coordinates":[-1.98407,51.767751],"type":"Point"}
}
