{
  "type": "Feature",
  "properties": {
    "iso:country":"GB",
    "wof:name":"GL7 7DZ",
    "wof:placetype":"postalcode"
},
  "geometry": {"coordinates":[-1.98407033885798,51.76775147303795],"type":"Point"}
}