{
  "type": "Feature",
  "properties": {
    "date:inception_lower": "1980-01-01",
    "date:inception_upper": "1980-01-01",
    "iso:country": "GB",
    "wof:name": "NE13 7JS",
    "wof:placetype": "postalcode"
  },
  "geometry": {"coordinates":[-1.675658,55.05461],"type":"Point"}
}
