{
  "type": "Feature",
  "properties": {
    "iso:country":"GB",
    "wof:name":"WA15 6HJ",
    "wof:placetype":"postalcode"
},
  "geometry": {"coordinates":[-2.32576991004336,53.40424161755031],"type":"Point"}
}