{
  "type": "Feature",
  "properties": {
    "iso:country": "GB",
    "wof:name": "NR17 1NL",
    "wof:placetype": "postalcode"
  },
  "geometry": {"coordinates":[1.029383,52.490822],"type":"Point"}
}
