{
  "type": "Feature",
  "properties": {
    "iso:country":"GB",
    "wof:name":"ME15 8LG",
    "wof:placetype":"postalcode"
},
  "geometry": {"coordinates":[0.56662541098573,51.26578964620381],"type":"Point"}
}