{
  "type": "Feature",
  "properties": {
    "date:inception_lower": "1996-12-01",
    "date:inception_upper": "1996-12-01",
    "iso:country": "GB",
    "wof:name": "TF2 8QZ",
    "wof:placetype": "postalcode"
  },
  "geometry": {"coordinates":[-2.41849,52.721605],"type":"Point"}
}
