{
  "type": "Feature",
  "properties": {
    "iso:country": "GB",
    "wof:name": "DG8 7HY",
    "wof:placetype": "postalcode"
  },
  "geometry": {"coordinates":[-4.379711,54.90229],"type":"Point"}
}
