{
  "type": "Feature",
  "properties": {
    "iso:country": "GB",
    "wof:name": "ML5 2DD",
    "wof:placetype": "postalcode"
  },
  "geometry": {"coordinates":[-4.030199,55.868859],"type":"Point"}
}
