{
  "type": "Feature",
  "properties": {
    "date:inception_lower":"1980-01-01",
    "date:inception_upper":"1980-01-31",
    "iso:country":"GB",
    "wof:name":"ML5 2DD",
    "wof:placetype":"postalcode"
},
  "geometry": {"coordinates":[-4.030199,55.868859],"type":"Point"}
}