{
  "type": "Feature",
  "properties": {
    "iso:country":"GB",
    "wof:name":"ML5 2DD",
    "wof:placetype":"postalcode"
},
  "geometry": {"coordinates":[-4.03019878574229,55.86885888501111],"type":"Point"}
}