{
  "type": "Feature",
  "properties": {
    "date:inception_lower": "1980-01-01",
    "date:inception_upper": "1980-01-01",
    "iso:country": "GB",
    "wof:name": "KT12 3BS",
    "wof:placetype": "postalcode"
  },
  "geometry": {"coordinates":[-0.408914,51.376332],"type":"Point"}
}
