{
  "type": "Feature",
  "properties": {
    "date:inception_lower":"1980-01-01",
    "date:inception_upper":"1980-01-31",
    "iso:country":"GB",
    "wof:name":"SG19 1HB",
    "wof:placetype":"postalcode"
},
  "geometry": {"coordinates":[-0.296718,52.131848],"type":"Point"}
}