{
  "type": "Feature",
  "properties": {
    "iso:country":"GB",
    "wof:name":"CF15 8DB",
    "wof:placetype":"postalcode"
},
  "geometry": {"coordinates":[-3.26082173862866,51.51745549289276],"type":"Point"}
}