{
  "type": "Feature",
  "properties": {
    "iso:country":"GB",
    "wof:name":"TF1 6DB",
    "wof:placetype":"postalcode"
},
  "geometry": {"coordinates":[-2.50770910768379,52.71150275061243],"type":"Point"}
}