{
  "type": "Feature",
  "properties": {
    "date:inception_lower": "2000-06-01",
    "date:inception_upper": "2000-06-01",
    "iso:country": "GB",
    "wof:name": "TF1 6DB",
    "wof:placetype": "postalcode"
  },
  "geometry": {"coordinates":[-2.507721,52.7115],"type":"Point"}
}
