{
  "type": "Feature",
  "properties": {
    "iso:country":"GB",
    "wof:name":"NG8 6NX",
    "wof:placetype":"postalcode"
},
  "geometry": {"coordinates":[-1.22977733058002,52.98012114694258],"type":"Point"}
}