{
  "type": "Feature",
  "properties": {
    "iso:country":"GB",
    "wof:name":"PO19 1PR",
    "wof:placetype":"postalcode"
},
  "geometry": {"coordinates":[-0.77487159596002,50.83764524949282],"type":"Point"}
}