{
  "type": "Feature",
  "properties": {
    "iso:country":"GB",
    "wof:name":"NR11 8UP",
    "wof:placetype":"postalcode"
},
  "geometry": {"coordinates":[1.35442195024647,52.86884812979392],"type":"Point"}
}