{
  "type": "Feature",
  "properties": {
    "iso:country": "GB",
    "wof:name": "NR11 8UP",
    "wof:placetype": "postalcode"
  },
  "geometry": {"coordinates":[1.354426,52.868859],"type":"Point"}
}
