{
  "type": "Feature",
  "properties": {
    "iso:country": "GB",
    "wof:name": "BR5 1EH",
    "wof:placetype": "postalcode"
  },
  "geometry": {"coordinates":[0.079294,51.382237],"type":"Point"}
}
