{
  "type": "Feature",
  "properties": {
    "iso:country":"GB",
    "wof:name":"BR5 1EH",
    "wof:placetype":"postalcode"
},
  "geometry": {"coordinates":[0.07929408805438,51.38223670847646],"type":"Point"}
}