{
  "type": "Feature",
  "properties": {
    "iso:country":"GB",
    "wof:name":"TD15 1SN",
    "wof:placetype":"postalcode"
},
  "geometry": {"coordinates":[-2.01164640121639,55.78599823757619],"type":"Point"}
}