{
  "type": "Feature",
  "properties": {
    "iso:country":"GB",
    "wof:name":"RG40 4LN",
    "wof:placetype":"postalcode"
},
  "geometry": {"coordinates":[-0.86031131860166,51.3685708686782],"type":"Point"}
}