{
  "type": "Feature",
  "properties": {
    "date:inception_lower": "2011-09-01",
    "date:inception_upper": "2011-09-01",
    "iso:country": "GB",
    "wof:name": "CV37 0UB",
    "wof:placetype": "postalcode"
  },
  "geometry": {"coordinates":[-1.728368,52.206987],"type":"Point"}
}
