{
  "type": "Feature",
  "properties": {
    "iso:country":"GB",
    "wof:name":"CV37 0UB",
    "wof:placetype":"postalcode"
},
  "geometry": {"coordinates":[-1.72836801629661,52.20698749837273],"type":"Point"}
}