{
  "type": "Feature",
  "properties": {
    "iso:country":"GB",
    "wof:name":"S73 8SD",
    "wof:placetype":"postalcode"
},
  "geometry": {"coordinates":[-1.41800452556354,53.53040436795732],"type":"Point"}
}