{
  "type": "Feature",
  "properties": {
    "date:inception_lower": "1980-01-01",
    "date:inception_upper": "1980-01-01",
    "iso:country": "GB",
    "wof:name": "S73 8SD",
    "wof:placetype": "postalcode"
  },
  "geometry": {"coordinates":[-1.418004,53.530404],"type":"Point"}
}
