{
  "type": "Feature",
  "properties": {
    "date:inception_lower":"2011-05-01",
    "date:inception_upper":"2011-05-31",
    "iso:country":"GB",
    "wof:name":"SK23 0WA",
    "wof:placetype":"postalcode"
},
  "geometry": {"coordinates":[-1.908009,53.329381],"type":"Point"}
}