{
  "type": "Feature",
  "properties": {
    "iso:country":"GB",
    "wof:name":"UB4 0BB",
    "wof:placetype":"postalcode"
},
  "geometry": {"coordinates":[-0.41036540008382,51.52094796932715],"type":"Point"}
}