{
  "type": "Feature",
  "properties": {
    "iso:country":"GB",
    "wof:name":"GU26 6LF",
    "wof:placetype":"postalcode"
},
  "geometry": {"coordinates":[-0.75476175693454,51.1103613057447],"type":"Point"}
}