{
  "type": "Feature",
  "properties": {
    "iso:country":"GB",
    "wof:name":"EH3 5DU",
    "wof:placetype":"postalcode"
},
  "geometry": {"coordinates":[-3.20165972162592,55.96103090597654],"type":"Point"}
}