{
  "type": "Feature",
  "properties": {
    "iso:country": "GB",
    "wof:name": "KT3 6BA",
    "wof:placetype": "postalcode"
  },
  "geometry": {"coordinates":[-0.247117,51.387755],"type":"Point"}
}
