{
  "type": "Feature",
  "properties": {
    "iso:country":"GB",
    "wof:name":"KT3 6BA",
    "wof:placetype":"postalcode"
},
  "geometry": {"coordinates":[-0.24711748405506,51.38775470029196],"type":"Point"}
}