{
  "type": "Feature",
  "properties": {
    "iso:country":"GB",
    "wof:name":"LS26 0PS",
    "wof:placetype":"postalcode"
},
  "geometry": {"coordinates":[-1.49455393205848,53.75677184396768],"type":"Point"}
}