{
  "type": "Feature",
  "properties": {
    "date:inception_lower": "2005-06-01",
    "date:inception_upper": "2005-06-01",
    "iso:country": "GB",
    "wof:name": "DT9 5LT",
    "wof:placetype": "postalcode"
  },
  "geometry": {"coordinates":[-2.46258,50.969167],"type":"Point"}
}
