{
  "type": "Feature",
  "properties": {
    "iso:country": "GB",
    "wof:name": "DT9 5LT",
    "wof:placetype": "postalcode"
  },
  "geometry": {"coordinates":[-2.46258,50.969167],"type":"Point"}
}
