{
  "type": "Feature",
  "properties": {
    "iso:country":"GB",
    "wof:name":"DT9 5LT",
    "wof:placetype":"postalcode"
},
  "geometry": {"coordinates":[-2.46257967974776,50.96916683637671],"type":"Point"}
}