{
  "type": "Feature",
  "properties": {
    "iso:country":"GB",
    "wof:name":"BS5 7XQ",
    "wof:placetype":"postalcode"
},
  "geometry": {"coordinates":[-2.53114567544291,51.46978229417743],"type":"Point"}
}