{
  "type": "Feature",
  "properties": {
    "date:inception_lower": "1992-08-01",
    "date:inception_upper": "1992-08-01",
    "iso:country": "GB",
    "wof:name": "BS5 7XQ",
    "wof:placetype": "postalcode"
  },
  "geometry": {"coordinates":[-2.531146,51.469782],"type":"Point"}
}
