{
  "type": "Feature",
  "properties": {
    "iso:country":"GB",
    "wof:name":"CM7 5QU",
    "wof:placetype":"postalcode"
},
  "geometry": {"coordinates":[0.54971934792187,51.8939858745223],"type":"Point"}
}