{
  "type": "Feature",
  "properties": {
    "iso:country": "GB",
    "wof:name": "BS8 3EG",
    "wof:placetype": "postalcode"
  },
  "geometry": {"coordinates":[-2.616807,51.463428],"type":"Point"}
}
