{
  "type": "Feature",
  "properties": {
    "date:inception_lower": "1980-01-01",
    "date:inception_upper": "1980-01-01",
    "iso:country": "GB",
    "wof:name": "BS8 3EG",
    "wof:placetype": "postalcode"
  },
  "geometry": {"coordinates":[-2.616807,51.463428],"type":"Point"}
}
