{
  "type": "Feature",
  "properties": {
    "iso:country":"GB",
    "wof:name":"CM23 1JB",
    "wof:placetype":"postalcode"
},
  "geometry": {"coordinates":[0.16007345685959,51.89067112384648],"type":"Point"}
}