{
  "type": "Feature",
  "properties": {
    "iso:country": "GB",
    "wof:name": "CM23 1JB",
    "wof:placetype": "postalcode"
  },
  "geometry": {"coordinates":[0.157943,51.890224],"type":"Point"}
}
