{
  "type": "Feature",
  "properties": {
    "iso:country":"GB",
    "wof:name":"S62 7SU",
    "wof:placetype":"postalcode"
},
  "geometry": {"coordinates":[-1.33801638922911,53.47530198236458],"type":"Point"}
}