{
  "type": "Feature",
  "properties": {
    "iso:country":"GB",
    "wof:name":"CH43 3DJ",
    "wof:placetype":"postalcode"
},
  "geometry": {"coordinates":[-3.05590991064207,53.36621710714989],"type":"Point"}
}