{
  "type": "Feature",
  "properties": {
    "date:inception_lower": "1999-06-01",
    "date:inception_upper": "1999-06-01",
    "iso:country": "GB",
    "wof:name": "CH43 3DJ",
    "wof:placetype": "postalcode"
  },
  "geometry": {"coordinates":[-3.05591,53.366217],"type":"Point"}
}
