{
  "type": "Feature",
  "properties": {
    "iso:country":"GB",
    "wof:name":"PO1 2DF",
    "wof:placetype":"postalcode"
},
  "geometry": {"coordinates":[-1.09437405042839,50.79625438949903],"type":"Point"}
}