{
  "type": "Feature",
  "properties": {
    "iso:country":"GB",
    "wof:name":"BA2 3LA",
    "wof:placetype":"postalcode"
},
  "geometry": {"coordinates":[-2.37187757266422,51.37629852440688],"type":"Point"}
}