{
  "type": "Feature",
  "properties": {
    "iso:country":"GB",
    "wof:name":"EN1 4PW",
    "wof:placetype":"postalcode"
},
  "geometry": {"coordinates":[-0.05154913117996,51.67176314868065],"type":"Point"}
}