{
  "type": "Feature",
  "properties": {
    "iso:country":"GB",
    "wof:name":"RG20 5RY",
    "wof:placetype":"postalcode"
},
  "geometry": {"coordinates":[-1.23855418828334,51.32498886640683],"type":"Point"}
}