{
  "type": "Feature",
  "properties": {
    "iso:country": "GB",
    "wof:name": "LN2 2NR",
    "wof:placetype": "postalcode"
  },
  "geometry": {"coordinates":[-0.488538,53.265733],"type":"Point"}
}
