{
  "type": "Feature",
  "properties": {
    "iso:country":"GB",
    "wof:name":"CM23 3TG",
    "wof:placetype":"postalcode"
},
  "geometry": {"coordinates":[0.15919203657241,51.86712723264189],"type":"Point"}
}