{
  "type": "Feature",
  "properties": {
    "date:inception_lower": "1980-01-01",
    "date:inception_upper": "1980-01-01",
    "iso:country": "GB",
    "wof:name": "CM23 3TG",
    "wof:placetype": "postalcode"
  },
  "geometry": {"coordinates":[0.159192,51.867127],"type":"Point"}
}
