{
  "type": "Feature",
  "properties": {
    "date:inception_lower": "1980-01-01",
    "date:inception_upper": "1980-01-01",
    "iso:country": "GB",
    "wof:name": "B71 2AP",
    "wof:placetype": "postalcode"
  },
  "geometry": {"coordinates":[-2.003755,52.541028],"type":"Point"}
}
