{
  "type": "Feature",
  "properties": {
    "iso:country":"GB",
    "wof:name":"B71 2AP",
    "wof:placetype":"postalcode"
},
  "geometry": {"coordinates":[-2.00352467101711,52.5408059099671],"type":"Point"}
}