{
  "type": "Feature",
  "properties": {
    "date:inception_lower": "1980-01-01",
    "date:inception_upper": "1980-01-01",
    "iso:country": "GB",
    "wof:name": "CV32 4TQ",
    "wof:placetype": "postalcode"
  },
  "geometry": {"coordinates":[-1.530663,52.29376],"type":"Point"}
}
