{
  "type": "Feature",
  "properties": {
    "iso:country":"GB",
    "wof:name":"CV32 4TQ",
    "wof:placetype":"postalcode"
},
  "geometry": {"coordinates":[-1.53067366052804,52.29374488516025],"type":"Point"}
}