{
  "type": "Feature",
  "properties": {
    "iso:country":"GB",
    "wof:name":"HX2 0UH",
    "wof:placetype":"postalcode"
},
  "geometry": {"coordinates":[-1.91857696315509,53.7411450129559],"type":"Point"}
}