{
  "type": "Feature",
  "properties": {
    "iso:country":"GB",
    "wof:name":"TN34 3UE",
    "wof:placetype":"postalcode"
},
  "geometry": {"coordinates":[0.58525252296711,50.86275169744549],"type":"Point"}
}