{
  "type": "Feature",
  "properties": {
    "iso:country":"GB",
    "wof:name":"NG4 2BW",
    "wof:placetype":"postalcode"
},
  "geometry": {"coordinates":[-1.08698633547905,52.95902802746511],"type":"Point"}
}