{
  "type": "Feature",
  "properties": {
    "iso:country":"GB",
    "wof:name":"OX11 0TD",
    "wof:placetype":"postalcode"
},
  "geometry": {"coordinates":[-1.32415907889189,51.56694065692511],"type":"Point"}
}