{
  "type": "Feature",
  "properties": {
    "iso:country": "GB",
    "wof:name": "OX11 0TD",
    "wof:placetype": "postalcode"
  },
  "geometry": {"coordinates":[-1.324159,51.566941],"type":"Point"}
}
