{
  "type": "Feature",
  "properties": {
    "iso:country":"GB",
    "wof:name":"CF82 8HZ",
    "wof:placetype":"postalcode"
},
  "geometry": {"coordinates":[-3.24358660165605,51.66604024799874],"type":"Point"}
}