{
  "type": "Feature",
  "properties": {
    "iso:country":"GB",
    "wof:name":"PL15 8HA",
    "wof:placetype":"postalcode"
},
  "geometry": {"coordinates":[-4.37298541695224,50.64586963072087],"type":"Point"}
}