{
  "type": "Feature",
  "properties": {
    "iso:country":"GB",
    "wof:name":"CF32 8DW",
    "wof:placetype":"postalcode"
},
  "geometry": {"coordinates":[-3.58211244739027,51.60441765443491],"type":"Point"}
}