{
  "type": "Feature",
  "properties": {
    "iso:country":"GB",
    "wof:name":"DL17 8DL",
    "wof:placetype":"postalcode"
},
  "geometry": {"coordinates":[-1.55116505595254,54.68570158405439],"type":"Point"}
}