{
  "type": "Feature",
  "properties": {
    "iso:country":"GB",
    "wof:name":"TW1 1BL",
    "wof:placetype":"postalcode"
},
  "geometry": {"coordinates":[-0.33330692900675,51.45105109484895],"type":"Point"}
}