{
  "type": "Feature",
  "properties": {
    "date:inception_lower": "1980-01-01",
    "date:inception_upper": "1980-01-01",
    "iso:country": "GB",
    "wof:name": "LU7 9ES",
    "wof:placetype": "postalcode"
  },
  "geometry": {"coordinates":[-0.631612,51.834988],"type":"Point"}
}
