{
  "type": "Feature",
  "properties": {
    "iso:country":"GB",
    "wof:name":"LU7 9ES",
    "wof:placetype":"postalcode"
},
  "geometry": {"coordinates":[-0.63161232701411,51.83498759492372],"type":"Point"}
}