{
  "type": "Feature",
  "properties": {
    "iso:country": "GB",
    "wof:name": "LU7 9ES",
    "wof:placetype": "postalcode"
  },
  "geometry": {"coordinates":[-0.631612,51.834988],"type":"Point"}
}
