{
  "type": "Feature",
  "properties": {
    "iso:country":"GB",
    "wof:name":"SE3 7JR",
    "wof:placetype":"postalcode"
},
  "geometry": {"coordinates":[0.02316412992116,51.47513505161762],"type":"Point"}
}