{
  "type": "Feature",
  "properties": {
    "iso:country":"GB",
    "wof:name":"CW11 3QE",
    "wof:placetype":"postalcode"
},
  "geometry": {"coordinates":[-2.41411571597723,53.15232604483815],"type":"Point"}
}