{
  "type": "Feature",
  "properties": {
    "date:inception_lower":"1999-06-01",
    "date:inception_upper":"1999-06-30",
    "iso:country":"GB",
    "wof:name":"ZE1 0EE",
    "wof:placetype":"postalcode"
},
  "geometry": {"coordinates":[-1.139522,60.149859],"type":"Point"}
}