{
  "type": "Feature",
  "properties": {
    "date:inception_lower":"2010-11-01",
    "date:inception_upper":"2010-11-30",
    "iso:country":"GB",
    "wof:name":"M24 2JT",
    "wof:placetype":"postalcode"
},
  "geometry": {"coordinates":[-2.186549,53.548625],"type":"Point"}
}