{
  "type": "Feature",
  "properties": {
    "iso:country":"GB",
    "wof:name":"M24 2JT",
    "wof:placetype":"postalcode"
},
  "geometry": {"coordinates":[-2.18654904361613,53.54862548814116],"type":"Point"}
}