{
  "type": "Feature",
  "properties": {
    "iso:country":"GB",
    "wof:name":"S73 9PZ",
    "wof:placetype":"postalcode"
},
  "geometry": {"coordinates":[-1.38804265647909,53.53359857763934],"type":"Point"}
}