{
  "type": "Feature",
  "properties": {
    "iso:country":"GB",
    "wof:name":"LE2 1WL",
    "wof:placetype":"postalcode"
},
  "geometry": {"coordinates":[-1.12138211542971,52.61630047170878],"type":"Point"}
}