{
  "type": "Feature",
  "properties": {
    "iso:country": "GB",
    "wof:name": "LE2 1WL",
    "wof:placetype": "postalcode"
  },
  "geometry": {"coordinates":[-1.121382,52.6163],"type":"Point"}
}
