{
  "type": "Feature",
  "properties": {
    "iso:country":"GB",
    "wof:name":"PO31 7TL",
    "wof:placetype":"postalcode"
},
  "geometry": {"coordinates":[-1.30038204251872,50.76215906894101],"type":"Point"}
}