{
  "type": "Feature",
  "properties": {
    "iso:country": "GB",
    "wof:name": "PO31 7TL",
    "wof:placetype": "postalcode"
  },
  "geometry": {"coordinates":[-1.300372,50.762148],"type":"Point"}
}
