{
  "type": "Feature",
  "properties": {
    "iso:country":"GB",
    "wof:name":"NR3 1PE",
    "wof:placetype":"postalcode"
},
  "geometry": {"coordinates":[1.30767692822988,52.6367421374663],"type":"Point"}
}