{
  "type": "Feature",
  "properties": {
    "iso:country": "GB",
    "wof:name": "NR3 1PE",
    "wof:placetype": "postalcode"
  },
  "geometry": {"coordinates":[1.307677,52.636742],"type":"Point"}
}
