{
  "type": "Feature",
  "properties": {
    "date:inception_lower": "1980-01-01",
    "date:inception_upper": "1980-01-01",
    "iso:country": "GB",
    "wof:name": "NE66 2SZ",
    "wof:placetype": "postalcode"
  },
  "geometry": {"coordinates":[-1.652112,55.401384],"type":"Point"}
}
