{
  "type": "Feature",
  "properties": {
    "iso:country":"GB",
    "wof:name":"NE66 2SZ",
    "wof:placetype":"postalcode"
},
  "geometry": {"coordinates":[-1.6521122681514,55.40138434195766],"type":"Point"}
}