{
  "type": "Feature",
  "properties": {
    "iso:country":"GB",
    "wof:name":"EH39 5NY",
    "wof:placetype":"postalcode"
},
  "geometry": {"coordinates":[-2.70846297698833,56.03477435245073],"type":"Point"}
}