{
  "type": "Feature",
  "properties": {
    "iso:country":"GB",
    "wof:name":"OL13 9LF",
    "wof:placetype":"postalcode"
},
  "geometry": {"coordinates":[-2.19389545792988,53.70267206076485],"type":"Point"}
}