{
  "type": "Feature",
  "properties": {
    "iso:country":"GB",
    "wof:name":"BR6 0TS",
    "wof:placetype":"postalcode"
},
  "geometry": {"coordinates":[0.08974545902427,51.38168203194599],"type":"Point"}
}