{
  "type": "Feature",
  "properties": {
    "date:inception_lower":"1980-01-01",
    "date:inception_upper":"1980-01-31",
    "iso:country":"GB",
    "wof:name":"DE11 0HX",
    "wof:placetype":"postalcode"
},
  "geometry": {"coordinates":[-1.576175,52.785145],"type":"Point"}
}