{
  "type": "Feature",
  "properties": {
    "date:inception_lower": "1994-12-01",
    "date:inception_upper": "1994-12-01",
    "iso:country": "GB",
    "wof:name": "SO32 2JD",
    "wof:placetype": "postalcode"
  },
  "geometry": {"coordinates":[-1.197518,50.914444],"type":"Point"}
}
