{
  "type": "Feature",
  "properties": {
    "iso:country":"GB",
    "wof:name":"SO32 2JD",
    "wof:placetype":"postalcode"
},
  "geometry": {"coordinates":[-1.19751804721,50.91444414993895],"type":"Point"}
}