{
  "type": "Feature",
  "properties": {
    "iso:country":"GB",
    "wof:name":"IG11 9AW",
    "wof:placetype":"postalcode"
},
  "geometry": {"coordinates":[0.10540960123788,51.54650171849676],"type":"Point"}
}