{
  "type": "Feature",
  "properties": {
    "iso:country": "GB",
    "wof:name": "WF16 0AF",
    "wof:placetype": "postalcode"
  },
  "geometry": {"coordinates":[-1.672905,53.70766],"type":"Point"}
}
