{
  "type": "Feature",
  "properties": {
    "iso:country": "GB",
    "wof:name": "PA7 5HT",
    "wof:placetype": "postalcode"
  },
  "geometry": {"coordinates":[-4.509505,55.901452],"type":"Point"}
}
