{
  "type": "Feature",
  "properties": {
    "date:inception_lower": "2019-12-01",
    "date:inception_upper": "2019-12-01",
    "iso:country": "GB",
    "wof:name": "PA7 5HT",
    "wof:placetype": "postalcode"
  },
  "geometry": {"coordinates":[-4.5097,55.901251],"type":"Point"}
}
