{
  "type": "Feature",
  "properties": {
    "iso:country":"GB",
    "wof:name":"CB6 2EH",
    "wof:placetype":"postalcode"
},
  "geometry": {"coordinates":[0.21900643110083,52.46949189099745],"type":"Point"}
}