{
  "type": "Feature",
  "properties": {
    "date:inception_lower": "1987-04-01",
    "date:inception_upper": "1987-04-01",
    "iso:country": "GB",
    "wof:name": "WN1 2BL",
    "wof:placetype": "postalcode"
  },
  "geometry": {"coordinates":[-2.628734,53.554021],"type":"Point"}
}
