{
  "type": "Feature",
  "properties": {
    "iso:country": "GB",
    "wof:name": "WN1 2BL",
    "wof:placetype": "postalcode"
  },
  "geometry": {"coordinates":[-2.628734,53.554021],"type":"Point"}
}
