{
  "type": "Feature",
  "properties": {
    "iso:country":"GB",
    "wof:name":"TN23 5AT",
    "wof:placetype":"postalcode"
},
  "geometry": {"coordinates":[0.85235232835189,51.13521312563469],"type":"Point"}
}