{
  "type": "Feature",
  "properties": {
    "iso:country": "GB",
    "wof:name": "TN23 5AT",
    "wof:placetype": "postalcode"
  },
  "geometry": {"coordinates":[0.852352,51.135213],"type":"Point"}
}
