{
  "type": "Feature",
  "properties": {
    "iso:country":"GB",
    "wof:name":"HP15 7DX",
    "wof:placetype":"postalcode"
},
  "geometry": {"coordinates":[-0.71621503928319,51.6560372182749],"type":"Point"}
}