{
  "type": "Feature",
  "properties": {
    "iso:country":"GB",
    "wof:name":"ME17 1HU",
    "wof:placetype":"postalcode"
},
  "geometry": {"coordinates":[0.67502053370989,51.24234287000388],"type":"Point"}
}