{
  "type": "Feature",
  "properties": {
    "date:inception_lower":"1980-01-01",
    "date:inception_upper":"1980-01-31",
    "iso:country":"GB",
    "wof:name":"S42 6BY",
    "wof:placetype":"postalcode"
},
  "geometry": {"coordinates":[-1.396705,53.182084],"type":"Point"}
}