{
  "type": "Feature",
  "properties": {
    "date:inception_lower": "2024-05-01",
    "date:inception_upper": "2024-05-01",
    "iso:country": "GB",
    "wof:name": "MK18 3SQ",
    "wof:placetype": "postalcode"
  },
  "geometry": {"coordinates":[-0.884309,51.950388],"type":"Point"}
}
