{
  "type": "Feature",
  "properties": {
    "iso:country": "GB",
    "wof:name": "SE1 2NR",
    "wof:placetype": "postalcode"
  },
  "geometry": {"coordinates":[-0.07668,51.501662],"type":"Point"}
}
