{
  "type": "Feature",
  "properties": {
    "iso:country":"GB",
    "wof:name":"SE1 2NR",
    "wof:placetype":"postalcode"
},
  "geometry": {"coordinates":[-0.0766798403972,51.50166200254032],"type":"Point"}
}