{
  "type": "Feature",
  "properties": {
    "iso:country":"GB",
    "wof:name":"SA15 3RS",
    "wof:placetype":"postalcode"
},
  "geometry": {"coordinates":[-4.15358689611344,51.68986082935967],"type":"Point"}
}