{
  "type": "Feature",
  "properties": {
    "date:inception_lower": "1980-01-01",
    "date:inception_upper": "1980-01-01",
    "iso:country": "GB",
    "wof:name": "SA15 3RS",
    "wof:placetype": "postalcode"
  },
  "geometry": {"coordinates":[-4.153587,51.689861],"type":"Point"}
}
