{
  "type": "Feature",
  "properties": {
    "iso:country":"GB",
    "wof:name":"TF2 7BF",
    "wof:placetype":"postalcode"
},
  "geometry": {"coordinates":[-2.43626578999625,52.70767001289629],"type":"Point"}
}