{
  "type": "Feature",
  "properties": {
    "date:inception_lower": "2008-06-01",
    "date:inception_upper": "2008-06-01",
    "iso:country": "GB",
    "wof:name": "TF2 7BF",
    "wof:placetype": "postalcode"
  },
  "geometry": {"coordinates":[-2.436264,52.707685],"type":"Point"}
}
