{
  "type": "Feature",
  "properties": {
    "iso:country": "GB",
    "wof:name": "TF2 7BF",
    "wof:placetype": "postalcode"
  },
  "geometry": {"coordinates":[-2.436471,52.707621],"type":"Point"}
}
