{
  "type": "Feature",
  "properties": {
    "iso:country":"GB",
    "wof:name":"TR13 8NT",
    "wof:placetype":"postalcode"
},
  "geometry": {"coordinates":[-5.27231684616573,50.1050978591048],"type":"Point"}
}