{
  "type": "Feature",
  "properties": {
    "iso:country": "GB",
    "wof:name": "TR13 8NT",
    "wof:placetype": "postalcode"
  },
  "geometry": {"coordinates":[-5.272317,50.105098],"type":"Point"}
}
