{
  "type": "Feature",
  "properties": {
    "iso:country": "GB",
    "wof:name": "PE7 8HF",
    "wof:placetype": "postalcode"
  },
  "geometry": {"coordinates":[-0.278201,52.538815],"type":"Point"}
}
