{
  "type": "Feature",
  "properties": {
    "iso:country":"GB",
    "wof:name":"PE7 8HF",
    "wof:placetype":"postalcode"
},
  "geometry": {"coordinates":[-0.27820074192688,52.53881455923293],"type":"Point"}
}