{
  "type": "Feature",
  "properties": {
    "date:inception_lower":"2007-01-01",
    "date:inception_upper":"2007-01-31",
    "iso:country":"GB",
    "wof:name":"PE7 8HF",
    "wof:placetype":"postalcode"
},
  "geometry": {"coordinates":[-0.278201,52.538815],"type":"Point"}
}