{
  "type": "Feature",
  "properties": {
    "iso:country": "GB",
    "wof:name": "NG2 7YG",
    "wof:placetype": "postalcode"
  },
  "geometry": {"coordinates":[-1.145819,52.923347],"type":"Point"}
}
