{
  "type": "Feature",
  "properties": {
    "iso:country":"GB",
    "wof:name":"SW3 5QG",
    "wof:placetype":"postalcode"
},
  "geometry": {"coordinates":[-0.16668196036416,51.48532530573677],"type":"Point"}
}