{
  "type": "Feature",
  "properties": {
    "iso:country":"GB",
    "wof:name":"PR4 5QD",
    "wof:placetype":"postalcode"
},
  "geometry": {"coordinates":[-2.79140276151636,53.71443325090658],"type":"Point"}
}