{
  "type": "Feature",
  "properties": {
    "iso:country": "GB",
    "wof:name": "BL8 1QB",
    "wof:placetype": "postalcode"
  },
  "geometry": {"coordinates":[-2.326923,53.597445],"type":"Point"}
}
