{
  "type": "Feature",
  "properties": {
    "iso:country":"GB",
    "wof:name":"BL8 1QB",
    "wof:placetype":"postalcode"
},
  "geometry": {"coordinates":[-2.32692314046579,53.59744512943774],"type":"Point"}
}