{
  "type": "Feature",
  "properties": {
    "iso:country":"GB",
    "wof:name":"LU3 2HH",
    "wof:placetype":"postalcode"
},
  "geometry": {"coordinates":[-0.43212016188506,51.90928664673501],"type":"Point"}
}