{
  "type": "Feature",
  "properties": {
    "iso:country": "GB",
    "wof:name": "LU3 2HH",
    "wof:placetype": "postalcode"
  },
  "geometry": {"coordinates":[-0.43212,51.909287],"type":"Point"}
}
