{
  "type": "Feature",
  "properties": {
    "iso:country":"GB",
    "wof:name":"HP7 9LW",
    "wof:placetype":"postalcode"
},
  "geometry": {"coordinates":[-0.57671879236989,51.67005748064891],"type":"Point"}
}