{
  "type": "Feature",
  "properties": {
    "iso:country": "GB",
    "wof:name": "IG6 3SY",
    "wof:placetype": "postalcode"
  },
  "geometry": {"coordinates":[0.117961,51.609279],"type":"Point"}
}
