{
  "type": "Feature",
  "properties": {
    "date:inception_lower": "1980-01-01",
    "date:inception_upper": "1980-01-01",
    "iso:country": "GB",
    "wof:name": "SW16 4TT",
    "wof:placetype": "postalcode"
  },
  "geometry": {"coordinates":[-0.13272,51.404872],"type":"Point"}
}
