{
  "type": "Feature",
  "properties": {
    "iso:country":"GB",
    "wof:name":"SW16 4TT",
    "wof:placetype":"postalcode"
},
  "geometry": {"coordinates":[-0.132720039259,51.40487208902141],"type":"Point"}
}