{
  "type": "Feature",
  "properties": {
    "iso:country": "GB",
    "wof:name": "SW16 4TT",
    "wof:placetype": "postalcode"
  },
  "geometry": {"coordinates":[-0.13272,51.404872],"type":"Point"}
}
