{
  "type": "Feature",
  "properties": {
    "date:inception_lower": "1994-05-01",
    "date:inception_upper": "1994-05-01",
    "iso:country": "GB",
    "wof:name": "M23 1AR",
    "wof:placetype": "postalcode"
  },
  "geometry": {"coordinates":[-2.27492,53.400361],"type":"Point"}
}
