{
  "type": "Feature",
  "properties": {
    "date:inception_lower":"1997-06-01",
    "date:inception_upper":"1997-06-30",
    "iso:country":"GB",
    "wof:name":"DL14 6NT",
    "wof:placetype":"postalcode"
},
  "geometry": {"coordinates":[-1.69408,54.653462],"type":"Point"}
}