{
  "type": "Feature",
  "properties": {
    "iso:country":"GB",
    "wof:name":"YO8 3UA",
    "wof:placetype":"postalcode"
},
  "geometry": {"coordinates":[-1.14711944319787,53.82257568369583],"type":"Point"}
}