{
  "type": "Feature",
  "properties": {
    "iso:country": "GB",
    "wof:name": "WF9 3RD",
    "wof:placetype": "postalcode"
  },
  "geometry": {"coordinates":[-1.326763,53.588477],"type":"Point"}
}
