{
  "type": "Feature",
  "properties": {
    "iso:country":"GB",
    "wof:name":"SE23 2BL",
    "wof:placetype":"postalcode"
},
  "geometry": {"coordinates":[-0.049710875166,51.43201795234568],"type":"Point"}
}