{
  "type": "Feature",
  "properties": {
    "iso:country":"GB",
    "wof:name":"HX3 8AQ",
    "wof:placetype":"postalcode"
},
  "geometry": {"coordinates":[-1.8075315094671,53.72543307026506],"type":"Point"}
}