{
  "type": "Feature",
  "properties": {
    "iso:country": "GB",
    "wof:name": "HX3 8AQ",
    "wof:placetype": "postalcode"
  },
  "geometry": {"coordinates":[-1.80764,53.725457],"type":"Point"}
}
