{
  "type": "Feature",
  "properties": {
    "iso:country":"GB",
    "wof:name":"BB2 4PB",
    "wof:placetype":"postalcode"
},
  "geometry": {"coordinates":[-2.50020941118376,53.73206523585201],"type":"Point"}
}