{
  "type": "Feature",
  "properties": {
    "iso:country":"GB",
    "wof:name":"M34 7QQ",
    "wof:placetype":"postalcode"
},
  "geometry": {"coordinates":[-2.09947216522602,53.44210021334052],"type":"Point"}
}