{
  "type": "Feature",
  "properties": {
    "iso:country": "GB",
    "wof:name": "CF10 3NB",
    "wof:placetype": "postalcode"
  },
  "geometry": {"coordinates":[-3.182662,51.486484],"type":"Point"}
}
