{
  "type": "Feature",
  "properties": {
    "iso:country":"GB",
    "wof:name":"HP9 2ES",
    "wof:placetype":"postalcode"
},
  "geometry": {"coordinates":[-0.63305949704781,51.61043639462375],"type":"Point"}
}