{
  "type": "Feature",
  "properties": {
    "date:inception_lower": "1980-01-01",
    "date:inception_upper": "1980-01-01",
    "iso:country": "GB",
    "wof:name": "YO11 2YA",
    "wof:placetype": "postalcode"
  },
  "geometry": {"coordinates":[-0.39436,54.264997],"type":"Point"}
}
