{
  "type": "Feature",
  "properties": {
    "iso:country":"GB",
    "wof:name":"YO11 2YA",
    "wof:placetype":"postalcode"
},
  "geometry": {"coordinates":[-0.39434399266267,54.26497957066875],"type":"Point"}
}