{
  "type": "Feature",
  "properties": {
    "iso:country": "GB",
    "wof:name": "ST17 0NZ",
    "wof:placetype": "postalcode"
  },
  "geometry": {"coordinates":[-2.09071,52.76225],"type":"Point"}
}
