{
  "type": "Feature",
  "properties": {
    "iso:country":"GB",
    "wof:name":"ST17 0NZ",
    "wof:placetype":"postalcode"
},
  "geometry": {"coordinates":[-2.09070988286378,52.76225022215297],"type":"Point"}
}