{
  "type": "Feature",
  "properties": {
    "date:inception_lower": "1980-01-01",
    "date:inception_upper": "1980-01-01",
    "iso:country": "GB",
    "wof:name": "WV1 4EL",
    "wof:placetype": "postalcode"
  },
  "geometry": {"coordinates":[-2.136456,52.586791],"type":"Point"}
}
