{
  "type": "Feature",
  "properties": {
    "iso:country":"GB",
    "wof:name":"WV1 4EL",
    "wof:placetype":"postalcode"
},
  "geometry": {"coordinates":[-2.13651498908942,52.58678188688761],"type":"Point"}
}