{
  "type": "Feature",
  "properties": {
    "iso:country":"GB",
    "wof:name":"SY13 1GW",
    "wof:placetype":"postalcode"
},
  "geometry": {"coordinates":[-2.68877914992048,52.97196087369625],"type":"Point"}
}