{
  "type": "Feature",
  "properties": {
    "date:inception_lower": "2004-05-01",
    "date:inception_upper": "2004-05-01",
    "iso:country": "GB",
    "wof:name": "SY13 1GW",
    "wof:placetype": "postalcode"
  },
  "geometry": {"coordinates":[-2.688779,52.971961],"type":"Point"}
}
