{
  "type": "Feature",
  "properties": {
    "date:inception_lower": "2006-07-01",
    "date:inception_upper": "2006-07-01",
    "iso:country": "GB",
    "wof:name": "ME14 3EN",
    "wof:placetype": "postalcode"
  },
  "geometry": {"coordinates":[0.548162,51.286033],"type":"Point"}
}
