{
  "type": "Feature",
  "properties": {
    "iso:country":"GB",
    "wof:name":"ME14 3EN",
    "wof:placetype":"postalcode"
},
  "geometry": {"coordinates":[0.54522667812476,51.28610622165655],"type":"Point"}
}