{
  "type": "Feature",
  "properties": {
    "iso:country": "GB",
    "wof:name": "ME14 3EN",
    "wof:placetype": "postalcode"
  },
  "geometry": {"coordinates":[0.545592,51.286242],"type":"Point"}
}
