{
  "type": "Feature",
  "properties": {
    "date:inception_lower":"1997-06-01",
    "date:inception_upper":"1997-06-30",
    "iso:country":"GB",
    "wof:name":"GL7 1LN",
    "wof:placetype":"postalcode"
},
  "geometry": {"coordinates":[-1.957273,51.709411],"type":"Point"}
}