{
  "type": "Feature",
  "properties": {
    "iso:country":"GB",
    "wof:name":"GL7 1LN",
    "wof:placetype":"postalcode"
},
  "geometry": {"coordinates":[-1.95727281176118,51.70941061399787],"type":"Point"}
}