{
  "type": "Feature",
  "properties": {
    "date:inception_lower":"2011-08-01",
    "date:inception_upper":"2011-08-31",
    "iso:country":"GB",
    "wof:name":"CM5 0FJ",
    "wof:placetype":"postalcode"
},
  "geometry": {"coordinates":[0.238401,51.715452],"type":"Point"}
}