{
  "type": "Feature",
  "properties": {
    "iso:country": "GB",
    "wof:name": "CM5 0FJ",
    "wof:placetype": "postalcode"
  },
  "geometry": {"coordinates":[0.238401,51.715452],"type":"Point"}
}
