{
  "type": "Feature",
  "properties": {
    "iso:country": "GB",
    "wof:name": "GU9 7HL",
    "wof:placetype": "postalcode"
  },
  "geometry": {"coordinates":[-0.800762,51.214578],"type":"Point"}
}
