{
  "type": "Feature",
  "properties": {
    "iso:country":"GB",
    "wof:name":"NG21 0NB",
    "wof:placetype":"postalcode"
},
  "geometry": {"coordinates":[-1.15314647256004,53.09972517799068],"type":"Point"}
}