{
  "type": "Feature",
  "properties": {
    "iso:country":"GB",
    "wof:name":"B14 7RS",
    "wof:placetype":"postalcode"
},
  "geometry": {"coordinates":[-1.89868490649055,52.43453759707199],"type":"Point"}
}