{
  "type": "Feature",
  "properties": {
    "date:inception_lower":"1980-01-01",
    "date:inception_upper":"1980-01-31",
    "iso:country":"GB",
    "wof:name":"B14 7RS",
    "wof:placetype":"postalcode"
},
  "geometry": {"coordinates":[-1.898685,52.434538],"type":"Point"}
}