{
  "type": "Feature",
  "properties": {
    "iso:country":"GB",
    "wof:name":"EC1A 7ES",
    "wof:placetype":"postalcode"
},
  "geometry": {"coordinates":[-0.09819790822589,51.51846931190847],"type":"Point"}
}