{
  "type": "Feature",
  "properties": {
    "date:inception_lower": "2022-04-01",
    "date:inception_upper": "2022-04-01",
    "iso:country": "GB",
    "wof:name": "LU1 5GA",
    "wof:placetype": "postalcode"
  },
  "geometry": {"coordinates":[-0.420165,51.877242],"type":"Point"}
}
