{
  "type": "Feature",
  "properties": {
    "date:inception_lower": "2002-06-01",
    "date:inception_upper": "2002-06-01",
    "iso:country": "GB",
    "wof:name": "TN23 3GT",
    "wof:placetype": "postalcode"
  },
  "geometry": {"coordinates":[0.849019,51.125428],"type":"Point"}
}
