{
  "type": "Feature",
  "properties": {
    "iso:country":"GB",
    "wof:name":"TN23 3GT",
    "wof:placetype":"postalcode"
},
  "geometry": {"coordinates":[0.8490191864095,51.1254275771016],"type":"Point"}
}