{
  "type": "Feature",
  "properties": {
    "iso:country":"GB",
    "wof:name":"YO21 1SA",
    "wof:placetype":"postalcode"
},
  "geometry": {"coordinates":[-0.65304877375146,54.46733676806559],"type":"Point"}
}