{
  "type": "Feature",
  "properties": {
    "date:inception_lower":"2006-07-01",
    "date:inception_upper":"2006-07-31",
    "iso:country":"GB",
    "wof:name":"TW9 1RB",
    "wof:placetype":"postalcode"
},
  "geometry": {"coordinates":[-0.304048,51.459579],"type":"Point"}
}