{
  "type": "Feature",
  "properties": {
    "iso:country":"GB",
    "wof:name":"TW9 1RB",
    "wof:placetype":"postalcode"
},
  "geometry": {"coordinates":[-0.3040483558479,51.45957894257242],"type":"Point"}
}