{
  "type": "Feature",
  "properties": {
    "iso:country":"GB",
    "wof:name":"S64 8BN",
    "wof:placetype":"postalcode"
},
  "geometry": {"coordinates":[-1.30090757428812,53.49086578126393],"type":"Point"}
}