{
  "type": "Feature",
  "properties": {
    "date:inception_lower":"1995-01-01",
    "date:inception_upper":"1995-01-31",
    "iso:country":"GB",
    "wof:name":"S64 8BN",
    "wof:placetype":"postalcode"
},
  "geometry": {"coordinates":[-1.300878,53.490912],"type":"Point"}
}