{
  "type": "Feature",
  "properties": {
    "date:inception_lower":"2009-01-01",
    "date:inception_upper":"2009-01-31",
    "iso:country":"GB",
    "wof:name":"GL20 5GF",
    "wof:placetype":"postalcode"
},
  "geometry": {"coordinates":[-2.149131,52.00187],"type":"Point"}
}