{
  "type": "Feature",
  "properties": {
    "iso:country": "GB",
    "wof:name": "GL20 5GF",
    "wof:placetype": "postalcode"
  },
  "geometry": {"coordinates":[-2.149131,52.00187],"type":"Point"}
}
