{
  "type": "Feature",
  "properties": {
    "iso:country":"GB",
    "wof:name":"GL20 5GF",
    "wof:placetype":"postalcode"
},
  "geometry": {"coordinates":[-2.14913152353577,52.00186996932933],"type":"Point"}
}