{
  "type": "Feature",
  "properties": {
    "iso:country":"GB",
    "wof:name":"SA5 4TG",
    "wof:placetype":"postalcode"
},
  "geometry": {"coordinates":[-4.00660474055087,51.64119852787078],"type":"Point"}
}