{
  "type": "Feature",
  "properties": {
    "date:inception_lower": "2002-10-01",
    "date:inception_upper": "2002-10-01",
    "iso:country": "GB",
    "wof:name": "CA15 7BF",
    "wof:placetype": "postalcode"
  },
  "geometry": {"coordinates":[-3.479425,54.71014],"type":"Point"}
}
