{
  "type": "Feature",
  "properties": {
    "iso:country":"GB",
    "wof:name":"CM2 7BA",
    "wof:placetype":"postalcode"
},
  "geometry": {"coordinates":[0.5135054598748,51.71554330358021],"type":"Point"}
}