{
  "type": "Feature",
  "properties": {
    "date:inception_lower": "2023-01-01",
    "date:inception_upper": "2023-01-01",
    "iso:country": "GB",
    "wof:name": "B77 4QH",
    "wof:placetype": "postalcode"
  },
  "geometry": {"coordinates":[-1.641076,52.628506],"type":"Point"}
}
