{
  "type": "Feature",
  "properties": {
    "iso:country": "GB",
    "wof:name": "OL16 3FP",
    "wof:placetype": "postalcode"
  },
  "geometry": {"coordinates":[-2.095942,53.599614],"type":"Point"}
}
