{
  "type": "Feature",
  "properties": {
    "date:inception_lower":"2005-08-01",
    "date:inception_upper":"2005-08-31",
    "iso:country":"GB",
    "wof:name":"TR7 1LF",
    "wof:placetype":"postalcode"
},
  "geometry": {"coordinates":[-5.089989,50.415136],"type":"Point"}
}