{
  "type": "Feature",
  "properties": {
    "iso:country":"GB",
    "wof:name":"DH1 2AY",
    "wof:placetype":"postalcode"
},
  "geometry": {"coordinates":[-1.51857164992484,54.78564294824805],"type":"Point"}
}