{
  "type": "Feature",
  "properties": {
    "iso:country": "GB",
    "wof:name": "NR7 8NG",
    "wof:placetype": "postalcode"
  },
  "geometry": {"coordinates":[1.323494,52.654466],"type":"Point"}
}
