{
  "type": "Feature",
  "properties": {
    "iso:country":"GB",
    "wof:name":"NR7 8NG",
    "wof:placetype":"postalcode"
},
  "geometry": {"coordinates":[1.32349438547181,52.65446634571088],"type":"Point"}
}