{
  "type": "Feature",
  "properties": {
    "iso:country":"GB",
    "wof:name":"RG7 3BU",
    "wof:placetype":"postalcode"
},
  "geometry": {"coordinates":[-1.05986374440713,51.39720042414447],"type":"Point"}
}