{
  "type": "Feature",
  "properties": {
    "date:inception_lower":"1997-12-01",
    "date:inception_upper":"1997-12-31",
    "iso:country":"GB",
    "wof:name":"BS32 8AX",
    "wof:placetype":"postalcode"
},
  "geometry": {"coordinates":[-2.543985,51.525237],"type":"Point"}
}