{
  "type": "Feature",
  "properties": {
    "iso:country": "GB",
    "wof:name": "OX16 9BB",
    "wof:placetype": "postalcode"
  },
  "geometry": {"coordinates":[-1.33433,52.049634],"type":"Point"}
}
