{
  "type": "Feature",
  "properties": {
    "date:inception_lower": "1980-01-01",
    "date:inception_upper": "1980-01-01",
    "iso:country": "GB",
    "wof:name": "CF33 6AR",
    "wof:placetype": "postalcode"
  },
  "geometry": {"coordinates":[-3.698123,51.526092],"type":"Point"}
}
