{
  "type": "Feature",
  "properties": {
    "iso:country":"GB",
    "wof:name":"CF33 6AR",
    "wof:placetype":"postalcode"
},
  "geometry": {"coordinates":[-3.69812317563373,51.52609227967776],"type":"Point"}
}