{
  "type": "Feature",
  "properties": {
    "iso:country":"GB",
    "wof:name":"DY8 3JD",
    "wof:placetype":"postalcode"
},
  "geometry": {"coordinates":[-2.17017795689322,52.44094875289886],"type":"Point"}
}