{
  "type": "Feature",
  "properties": {
    "iso:country": "GB",
    "wof:name": "DY8 3JD",
    "wof:placetype": "postalcode"
  },
  "geometry": {"coordinates":[-2.170173,52.440981],"type":"Point"}
}
