{
  "type": "Feature",
  "properties": {
    "iso:country": "GB",
    "wof:name": "HX7 7DX",
    "wof:placetype": "postalcode"
  },
  "geometry": {"coordinates":[-2.015172,53.745699],"type":"Point"}
}
