{
  "type": "Feature",
  "properties": {
    "iso:country":"GB",
    "wof:name":"HX7 7DX",
    "wof:placetype":"postalcode"
},
  "geometry": {"coordinates":[-2.01517116413687,53.74568349221692],"type":"Point"}
}