{
  "type": "Feature",
  "properties": {
    "iso:country":"GB",
    "wof:name":"CO16 8XH",
    "wof:placetype":"postalcode"
},
  "geometry": {"coordinates":[1.12779349770252,51.80697220234856],"type":"Point"}
}