{
  "type": "Feature",
  "properties": {
    "iso:country":"GB",
    "wof:name":"B76 1JS",
    "wof:placetype":"postalcode"
},
  "geometry": {"coordinates":[-1.81307297038316,52.53680215142305],"type":"Point"}
}