{
  "type": "Feature",
  "properties": {
    "iso:country":"GB",
    "wof:name":"SM1 1SE",
    "wof:placetype":"postalcode"
},
  "geometry": {"coordinates":[-0.19600313058576,51.36780659889377],"type":"Point"}
}