{
  "type": "Feature",
  "properties": {
    "date:inception_lower":"1980-01-01",
    "date:inception_upper":"1980-01-31",
    "iso:country":"GB",
    "wof:name":"ST7 2NW",
    "wof:placetype":"postalcode"
},
  "geometry": {"coordinates":[-2.303876,53.098751],"type":"Point"}
}