{
  "type": "Feature",
  "properties": {
    "iso:country":"GB",
    "wof:name":"ST7 2NW",
    "wof:placetype":"postalcode"
},
  "geometry": {"coordinates":[-2.30387649093609,53.09875148164068],"type":"Point"}
}