{
  "type": "Feature",
  "properties": {
    "iso:country":"GB",
    "wof:name":"TR9 6FL",
    "wof:placetype":"postalcode"
},
  "geometry": {"coordinates":[-4.93125114710629,50.38152988161658],"type":"Point"}
}