{
  "type": "Feature",
  "properties": {
    "iso:country": "GB",
    "wof:name": "TR9 6FL",
    "wof:placetype": "postalcode"
  },
  "geometry": {"coordinates":[-4.931251,50.38153],"type":"Point"}
}
