{
  "type": "Feature",
  "properties": {
    "iso:country": "GB",
    "wof:name": "B79 9JD",
    "wof:placetype": "postalcode"
  },
  "geometry": {"coordinates":[-1.683306,52.706595],"type":"Point"}
}
