{
  "type": "Feature",
  "properties": {
    "iso:country": "GB",
    "wof:name": "NG8 4ER",
    "wof:placetype": "postalcode"
  },
  "geometry": {"coordinates":[-1.219403,52.964719],"type":"Point"}
}
