{
  "type": "Feature",
  "properties": {
    "iso:country":"GB",
    "wof:name":"NG8 4ER",
    "wof:placetype":"postalcode"
},
  "geometry": {"coordinates":[-1.21938917735119,52.9648073352456],"type":"Point"}
}