{
  "type": "Feature",
  "properties": {
    "iso:country":"GB",
    "wof:name":"NE65 0AF",
    "wof:placetype":"postalcode"
},
  "geometry": {"coordinates":[-1.57857420744287,55.33474895651579],"type":"Point"}
}