{
  "type": "Feature",
  "properties": {
    "iso:country":"GB",
    "wof:name":"YO13 0QL",
    "wof:placetype":"postalcode"
},
  "geometry": {"coordinates":[-0.44178245373534,54.3022202381232],"type":"Point"}
}