{
  "type": "Feature",
  "properties": {
    "iso:country":"GB",
    "wof:name":"PO9 3JJ",
    "wof:placetype":"postalcode"
},
  "geometry": {"coordinates":[-1.00356419762316,50.85360763052912],"type":"Point"}
}