{
  "type": "Feature",
  "properties": {
    "date:inception_lower":"1980-01-01",
    "date:inception_upper":"1980-01-31",
    "iso:country":"GB",
    "wof:name":"EH8 9JE",
    "wof:placetype":"postalcode"
},
  "geometry": {"coordinates":[-3.181362,55.940992],"type":"Point"}
}