{
  "type": "Feature",
  "properties": {
    "iso:country":"GB",
    "wof:name":"EH8 9JE",
    "wof:placetype":"postalcode"
},
  "geometry": {"coordinates":[-3.18136232404252,55.94099192258429],"type":"Point"}
}