{
  "type": "Feature",
  "properties": {
    "iso:country": "GB",
    "wof:name": "NW9 8XB",
    "wof:placetype": "postalcode"
  },
  "geometry": {"coordinates":[-0.25712,51.580045],"type":"Point"}
}
