{
  "type": "Feature",
  "properties": {
    "iso:country": "GB",
    "wof:name": "PO38 1EP",
    "wof:placetype": "postalcode"
  },
  "geometry": {"coordinates":[-1.202374,50.59455],"type":"Point"}
}
