{
  "type": "Feature",
  "properties": {
    "iso:country":"GB",
    "wof:name":"PO38 1EP",
    "wof:placetype":"postalcode"
},
  "geometry": {"coordinates":[-1.20237448172756,50.59454990275727],"type":"Point"}
}