{
  "type": "Feature",
  "properties": {
    "iso:country": "GB",
    "wof:name": "IP4 2BT",
    "wof:placetype": "postalcode"
  },
  "geometry": {"coordinates":[1.159607,52.060239],"type":"Point"}
}
