{
  "type": "Feature",
  "properties": {
    "iso:country":"GB",
    "wof:name":"GU46 6HY",
    "wof:placetype":"postalcode"
},
  "geometry": {"coordinates":[-0.83378047699319,51.33736803084189],"type":"Point"}
}