{
  "type": "Feature",
  "properties": {
    "date:inception_lower":"1980-01-01",
    "date:inception_upper":"1980-01-31",
    "iso:country":"GB",
    "wof:name":"HU6 7UG",
    "wof:placetype":"postalcode"
},
  "geometry": {"coordinates":[-0.363577,53.779578],"type":"Point"}
}