{
  "type": "Feature",
  "properties": {
    "date:inception_lower":"2000-06-01",
    "date:inception_upper":"2000-06-30",
    "iso:country":"GB",
    "wof:name":"PE28 9AR",
    "wof:placetype":"postalcode"
},
  "geometry": {"coordinates":[-0.12747,52.326463],"type":"Point"}
}