{
  "type": "Feature",
  "properties": {
    "iso:country": "GB",
    "wof:name": "PE28 9AR",
    "wof:placetype": "postalcode"
  },
  "geometry": {"coordinates":[-0.12747,52.326463],"type":"Point"}
}
