{
  "type": "Feature",
  "properties": {
    "date:inception_lower": "1980-01-01",
    "date:inception_upper": "1980-01-01",
    "iso:country": "GB",
    "wof:name": "WR9 0BY",
    "wof:placetype": "postalcode"
  },
  "geometry": {"coordinates":[-2.127733,52.292458],"type":"Point"}
}
