{
  "type": "Feature",
  "properties": {
    "date:inception_lower": "2011-05-01",
    "date:inception_upper": "2011-05-01",
    "iso:country": "GB",
    "wof:name": "B10 0EU",
    "wof:placetype": "postalcode"
  },
  "geometry": {"coordinates":[-1.849938,52.460952],"type":"Point"}
}
