{
  "type": "Feature",
  "properties": {
    "iso:country":"GB",
    "wof:name":"HG5 8HS",
    "wof:placetype":"postalcode"
},
  "geometry": {"coordinates":[-1.45140322230298,54.00210626694003],"type":"Point"}
}