{
  "type": "Feature",
  "properties": {
    "iso:country": "GB",
    "wof:name": "CA7 2HL",
    "wof:placetype": "postalcode"
  },
  "geometry": {"coordinates":[-3.273398,54.740755],"type":"Point"}
}
