{
  "type": "Feature",
  "properties": {
    "iso:country": "GB",
    "wof:name": "CA20 1NJ",
    "wof:placetype": "postalcode"
  },
  "geometry": {"coordinates":[-3.477516,54.395834],"type":"Point"}
}
