{
  "type": "Feature",
  "properties": {
    "date:inception_lower":"1983-03-01",
    "date:inception_upper":"1983-03-31",
    "iso:country":"GB",
    "wof:name":"GL54 5TG",
    "wof:placetype":"postalcode"
},
  "geometry": {"coordinates":[-1.958076,51.92185],"type":"Point"}
}