{
  "type": "Feature",
  "properties": {
    "iso:country":"GB",
    "wof:name":"SR3 1YT",
    "wof:placetype":"postalcode"
},
  "geometry": {"coordinates":[-1.39429132315768,54.89015739762522],"type":"Point"}
}