{
  "type": "Feature",
  "properties": {
    "iso:country": "GB",
    "wof:name": "PE32 1LP",
    "wof:placetype": "postalcode"
  },
  "geometry": {"coordinates":[0.531862,52.748058],"type":"Point"}
}
