{
  "type": "Feature",
  "properties": {
    "iso:country":"GB",
    "wof:name":"BB2 6LN",
    "wof:placetype":"postalcode"
},
  "geometry": {"coordinates":[-2.49965940179887,53.74830910906984],"type":"Point"}
}