{
  "type": "Feature",
  "properties": {
    "date:inception_lower": "2001-06-01",
    "date:inception_upper": "2001-06-01",
    "iso:country": "GB",
    "wof:name": "WF10 5TQ",
    "wof:placetype": "postalcode"
  },
  "geometry": {"coordinates":[-1.374986,53.714197],"type":"Point"}
}
