{
  "type": "Feature",
  "properties": {
    "iso:country":"GB",
    "wof:name":"S36 1AY",
    "wof:placetype":"postalcode"
},
  "geometry": {"coordinates":[-1.61864078890469,53.48596424742447],"type":"Point"}
}