{
  "type": "Feature",
  "properties": {
    "date:inception_lower": "2023-04-01",
    "date:inception_upper": "2023-04-01",
    "iso:country": "GB",
    "wof:name": "PR4 0YS",
    "wof:placetype": "postalcode"
  },
  "geometry": {"coordinates":[-2.809196,53.767721],"type":"Point"}
}
