{
  "type": "Feature",
  "properties": {
    "iso:country": "GB",
    "wof:name": "CH64 3AB",
    "wof:placetype": "postalcode"
  },
  "geometry": {"coordinates":[-3.053929,53.303659],"type":"Point"}
}
