{
  "type": "Feature",
  "properties": {
    "iso:country": "GB",
    "wof:name": "CH64 3AB",
    "wof:placetype": "postalcode"
  },
  "geometry": {"coordinates":[-3.054027,53.303371],"type":"Point"}
}
