{
  "type": "Feature",
  "properties": {
    "date:inception_lower": "2019-07-01",
    "date:inception_upper": "2019-07-01",
    "iso:country": "GB",
    "wof:name": "CH64 3AB",
    "wof:placetype": "postalcode"
  },
  "geometry": {"coordinates":[-3.053929,53.303659],"type":"Point"}
}
