{
  "type": "Feature",
  "properties": {
    "iso:country":"GB",
    "wof:name":"EN3 6LL",
    "wof:placetype":"postalcode"
},
  "geometry": {"coordinates":[-0.0279858847301,51.67884253655603],"type":"Point"}
}