{
  "type": "Feature",
  "properties": {
    "date:inception_lower": "2001-06-01",
    "date:inception_upper": "2001-06-01",
    "iso:country": "GB",
    "wof:name": "HD9 4DN",
    "wof:placetype": "postalcode"
  },
  "geometry": {"coordinates":[-1.838117,53.590458],"type":"Point"}
}
