{
  "type": "Feature",
  "properties": {
    "iso:country": "GB",
    "wof:name": "TR11 5TZ",
    "wof:placetype": "postalcode"
  },
  "geometry": {"coordinates":[-5.069052,50.162702],"type":"Point"}
}
