{
  "type": "Feature",
  "properties": {
    "iso:country":"GB",
    "wof:name":"SN8 3RJ",
    "wof:placetype":"postalcode"
},
  "geometry": {"coordinates":[-1.53299411324802,51.33148669757563],"type":"Point"}
}