{
  "type": "Feature",
  "properties": {
    "date:inception_lower": "1980-01-01",
    "date:inception_upper": "1980-01-01",
    "iso:country": "GB",
    "wof:name": "SN8 3RJ",
    "wof:placetype": "postalcode"
  },
  "geometry": {"coordinates":[-1.533009,51.331478],"type":"Point"}
}
