{
  "type": "Feature",
  "properties": {
    "iso:country": "GB",
    "wof:name": "SN8 3RJ",
    "wof:placetype": "postalcode"
  },
  "geometry": {"coordinates":[-1.533009,51.331478],"type":"Point"}
}
