{
  "type": "Feature",
  "properties": {
    "iso:country":"GB",
    "wof:name":"HA4 9JL",
    "wof:placetype":"postalcode"
},
  "geometry": {"coordinates":[-0.3976454481735,51.56876621990628],"type":"Point"}
}