{
  "type": "Feature",
  "properties": {
    "iso:country":"GB",
    "wof:name":"DL3 0SN",
    "wof:placetype":"postalcode"
},
  "geometry": {"coordinates":[-1.55847839839532,54.54331435278283],"type":"Point"}
}