{
  "type": "Feature",
  "properties": {
    "date:inception_lower":"1988-03-01",
    "date:inception_upper":"1988-03-31",
    "iso:country":"GB",
    "wof:name":"NR18 0TR",
    "wof:placetype":"postalcode"
},
  "geometry": {"coordinates":[1.108951,52.580245],"type":"Point"}
}