{
  "type": "Feature",
  "properties": {
    "iso:country":"GB",
    "wof:name":"NR18 0TR",
    "wof:placetype":"postalcode"
},
  "geometry": {"coordinates":[1.1089511194342,52.58024545196695],"type":"Point"}
}