{
  "type": "Feature",
  "properties": {
    "iso:country":"GB",
    "wof:name":"L20 1BN",
    "wof:placetype":"postalcode"
},
  "geometry": {"coordinates":[-3.00094047971499,53.44458904658183],"type":"Point"}
}