{
  "type": "Feature",
  "properties": {
    "iso:country":"GB",
    "wof:name":"IP24 1TB",
    "wof:placetype":"postalcode"
},
  "geometry": {"coordinates":[0.75255896586122,52.42430918604666],"type":"Point"}
}