{
  "type": "Feature",
  "properties": {
    "iso:country": "GB",
    "wof:name": "G66 2RD",
    "wof:placetype": "postalcode"
  },
  "geometry": {"coordinates":[-4.134059,55.945748],"type":"Point"}
}
