{
  "type": "Feature",
  "properties": {
    "date:inception_lower": "1980-01-01",
    "date:inception_upper": "1980-01-01",
    "iso:country": "GB",
    "wof:name": "G66 2RD",
    "wof:placetype": "postalcode"
  },
  "geometry": {"coordinates":[-4.134059,55.945748],"type":"Point"}
}
