{
  "type": "Feature",
  "properties": {
    "iso:country":"GB",
    "wof:name":"G66 2RD",
    "wof:placetype":"postalcode"
},
  "geometry": {"coordinates":[-4.13405882801769,55.94574757740283],"type":"Point"}
}