{
  "type": "Feature",
  "properties": {
    "date:inception_lower": "2015-07-01",
    "date:inception_upper": "2015-07-01",
    "iso:country": "GB",
    "wof:name": "BN12 6BW",
    "wof:placetype": "postalcode"
  },
  "geometry": {"coordinates":[-0.430463,50.825158],"type":"Point"}
}
