{
  "type": "Feature",
  "properties": {
    "iso:country":"GB",
    "wof:name":"EH4 6RB",
    "wof:placetype":"postalcode"
},
  "geometry": {"coordinates":[-3.30881827537531,55.97221358666595],"type":"Point"}
}