{
  "type": "Feature",
  "properties": {
    "iso:country": "GB",
    "wof:name": "EH4 6RB",
    "wof:placetype": "postalcode"
  },
  "geometry": {"coordinates":[-3.308818,55.972214],"type":"Point"}
}
