{
  "type": "Feature",
  "properties": {
    "date:inception_lower": "2003-10-01",
    "date:inception_upper": "2003-10-01",
    "iso:country": "GB",
    "wof:name": "PL25 3NZ",
    "wof:placetype": "postalcode"
  },
  "geometry": {"coordinates":[-4.760978,50.33437],"type":"Point"}
}
