{
  "type": "Feature",
  "properties": {
    "iso:country":"GB",
    "wof:name":"PL25 3NZ",
    "wof:placetype":"postalcode"
},
  "geometry": {"coordinates":[-4.76075507223015,50.33440553706365],"type":"Point"}
}