{
  "type": "Feature",
  "properties": {
    "iso:country": "GB",
    "wof:name": "NE33 4BG",
    "wof:placetype": "postalcode"
  },
  "geometry": {"coordinates":[-1.427733,54.984605],"type":"Point"}
}
