{
  "type": "Feature",
  "properties": {
    "iso:country":"GB",
    "wof:name":"CF32 8TN",
    "wof:placetype":"postalcode"
},
  "geometry": {"coordinates":[-3.58995539242602,51.56685049127029],"type":"Point"}
}