{
  "type": "Feature",
  "properties": {
    "iso:country":"GB",
    "wof:name":"KA11 2AN",
    "wof:placetype":"postalcode"
},
  "geometry": {"coordinates":[-4.60549369435681,55.64173879612311],"type":"Point"}
}