{
  "type": "Feature",
  "properties": {
    "iso:country":"GB",
    "wof:name":"ST16 1HP",
    "wof:placetype":"postalcode"
},
  "geometry": {"coordinates":[-2.12692449024406,52.81704382936471],"type":"Point"}
}