{
  "type": "Feature",
  "properties": {
    "iso:country": "GB",
    "wof:name": "TR11 5TQ",
    "wof:placetype": "postalcode"
  },
  "geometry": {"coordinates":[-5.070836,50.167452],"type":"Point"}
}
