{
  "type": "Feature",
  "properties": {
    "iso:country":"GB",
    "wof:name":"TR11 5TQ",
    "wof:placetype":"postalcode"
},
  "geometry": {"coordinates":[-5.07083600209386,50.16745209798882],"type":"Point"}
}