{
  "type": "Feature",
  "properties": {
    "date:inception_lower":"1980-01-01",
    "date:inception_upper":"1980-01-31",
    "iso:country":"GB",
    "wof:name":"TR11 5TQ",
    "wof:placetype":"postalcode"
},
  "geometry": {"coordinates":[-5.070836,50.167452],"type":"Point"}
}