{
  "type": "Feature",
  "properties": {
    "iso:country":"GB",
    "wof:name":"EN11 9AP",
    "wof:placetype":"postalcode"
},
  "geometry": {"coordinates":[-0.0181034384653,51.77392328033603],"type":"Point"}
}