{
  "type": "Feature",
  "properties": {
    "iso:country":"GB",
    "wof:name":"BR6 7AR",
    "wof:placetype":"postalcode"
},
  "geometry": {"coordinates":[0.06305722491495,51.36535624260127],"type":"Point"}
}