{
  "type": "Feature",
  "properties": {
    "iso:country": "GB",
    "wof:name": "SW4 7PS",
    "wof:placetype": "postalcode"
  },
  "geometry": {"coordinates":[-0.12649,51.46229],"type":"Point"}
}
