{
  "type": "Feature",
  "properties": {
    "iso:country":"GB",
    "wof:name":"ME1 3PY",
    "wof:placetype":"postalcode"
},
  "geometry": {"coordinates":[0.48254234198842,51.3714975755819],"type":"Point"}
}