{
  "type": "Feature",
  "properties": {
    "iso:country": "GB",
    "wof:name": "CF31 4LZ",
    "wof:placetype": "postalcode"
  },
  "geometry": {"coordinates":[-3.594847,51.52685],"type":"Point"}
}
