{
  "type": "Feature",
  "properties": {
    "iso:country":"GB",
    "wof:name":"TN10 4RL",
    "wof:placetype":"postalcode"
},
  "geometry": {"coordinates":[0.28919014094178,51.21907804644241],"type":"Point"}
}