{
  "type": "Feature",
  "properties": {
    "iso:country": "GB",
    "wof:name": "ME20 6PP",
    "wof:placetype": "postalcode"
  },
  "geometry": {"coordinates":[0.441691,51.300966],"type":"Point"}
}
