{
  "type": "Feature",
  "properties": {
    "iso:country":"GB",
    "wof:name":"SM5 3NY",
    "wof:placetype":"postalcode"
},
  "geometry": {"coordinates":[-0.16620848033744,51.36526670137632],"type":"Point"}
}