{
  "type": "Feature",
  "properties": {
    "iso:country": "GB",
    "wof:name": "SM5 3NY",
    "wof:placetype": "postalcode"
  },
  "geometry": {"coordinates":[-0.165881,51.365288],"type":"Point"}
}
