{
  "type": "Feature",
  "properties": {
    "iso:country":"GB",
    "wof:name":"BN11 5EL",
    "wof:placetype":"postalcode"
},
  "geometry": {"coordinates":[-0.40172909365516,50.80757252416437],"type":"Point"}
}