{
  "type": "Feature",
  "properties": {
    "iso:country":"GB",
    "wof:name":"N17 0LG",
    "wof:placetype":"postalcode"
},
  "geometry": {"coordinates":[-0.06333559597522,51.60155639148269],"type":"Point"}
}