{
  "type": "Feature",
  "properties": {
    "iso:country": "GB",
    "wof:name": "AL10 0JT",
    "wof:placetype": "postalcode"
  },
  "geometry": {"coordinates":[-0.226395,51.763259],"type":"Point"}
}
