{
  "type": "Feature",
  "properties": {
    "iso:country": "GB",
    "wof:name": "B46 2NP",
    "wof:placetype": "postalcode"
  },
  "geometry": {"coordinates":[-1.608527,52.521865],"type":"Point"}
}
