{
  "type": "Feature",
  "properties": {
    "iso:country":"GB",
    "wof:name":"B46 2NP",
    "wof:placetype":"postalcode"
},
  "geometry": {"coordinates":[-1.6085266613114,52.52186506161894],"type":"Point"}
}