{
  "type": "Feature",
  "properties": {
    "iso:country":"GB",
    "wof:name":"E1 1ES",
    "wof:placetype":"postalcode"
},
  "geometry": {"coordinates":[-0.06465127487723,51.516904409185],"type":"Point"}
}