{
  "type": "Feature",
  "properties": {
    "iso:country":"GB",
    "wof:name":"HP9 2JN",
    "wof:placetype":"postalcode"
},
  "geometry": {"coordinates":[-0.63554219275967,51.59988182904031],"type":"Point"}
}