{
  "type": "Feature",
  "properties": {
    "iso:country": "GB",
    "wof:name": "SW6 2TF",
    "wof:placetype": "postalcode"
  },
  "geometry": {"coordinates":[-0.192214,51.473547],"type":"Point"}
}
