{
  "type": "Feature",
  "properties": {
    "iso:country":"GB",
    "wof:name":"SW6 2TF",
    "wof:placetype":"postalcode"
},
  "geometry": {"coordinates":[-0.1921956012858,51.47352759012289],"type":"Point"}
}