{
  "type": "Feature",
  "properties": {
    "iso:country": "GB",
    "wof:name": "G66 2PJ",
    "wof:placetype": "postalcode"
  },
  "geometry": {"coordinates":[-4.121406,55.945148],"type":"Point"}
}
