{
  "type": "Feature",
  "properties": {
    "iso:country":"GB",
    "wof:name":"OX28 5FP",
    "wof:placetype":"postalcode"
},
  "geometry": {"coordinates":[-1.50706044467807,51.78379429461194],"type":"Point"}
}