{
  "type": "Feature",
  "properties": {
    "iso:country": "GB",
    "wof:name": "PE28 4TQ",
    "wof:placetype": "postalcode"
  },
  "geometry": {"coordinates":[-0.22611,52.322923],"type":"Point"}
}
