{
  "type": "Feature",
  "properties": {
    "iso:country":"GB",
    "wof:name":"NW1 2NB",
    "wof:placetype":"postalcode"
},
  "geometry": {"coordinates":[-0.13700641539909,51.52678072472083],"type":"Point"}
}