{
  "type": "Feature",
  "properties": {
    "date:inception_lower": "1980-01-01",
    "date:inception_upper": "1980-01-01",
    "iso:country": "GB",
    "wof:name": "EH4 6DW",
    "wof:placetype": "postalcode"
  },
  "geometry": {"coordinates":[-3.315998,55.966602],"type":"Point"}
}
