{
  "type": "Feature",
  "properties": {
    "iso:country": "GB",
    "wof:name": "EH4 6DW",
    "wof:placetype": "postalcode"
  },
  "geometry": {"coordinates":[-3.315998,55.966602],"type":"Point"}
}
