{
  "type": "Feature",
  "properties": {
    "iso:country":"GB",
    "wof:name":"EH4 6DW",
    "wof:placetype":"postalcode"
},
  "geometry": {"coordinates":[-3.31599853968306,55.96660198648821],"type":"Point"}
}