{
  "type": "Feature",
  "properties": {
    "iso:country":"GB",
    "wof:name":"HU9 4EW",
    "wof:placetype":"postalcode"
},
  "geometry": {"coordinates":[-0.27601863633905,53.76887619815999],"type":"Point"}
}