{
  "type": "Feature",
  "properties": {
    "iso:country":"GB",
    "wof:name":"RH5 6AB",
    "wof:placetype":"postalcode"
},
  "geometry": {"coordinates":[-0.32798694566724,51.24930879214595],"type":"Point"}
}