{
  "type": "Feature",
  "properties": {
    "iso:country": "GB",
    "wof:name": "RH5 6AB",
    "wof:placetype": "postalcode"
  },
  "geometry": {"coordinates":[-0.327987,51.249309],"type":"Point"}
}
