{
  "type": "Feature",
  "properties": {
    "date:inception_lower": "2007-01-01",
    "date:inception_upper": "2007-01-01",
    "iso:country": "GB",
    "wof:name": "CF31 3BQ",
    "wof:placetype": "postalcode"
  },
  "geometry": {"coordinates":[-3.533058,51.495456],"type":"Point"}
}
