{
  "type": "Feature",
  "properties": {
    "iso:country": "GB",
    "wof:name": "CF31 3BQ",
    "wof:placetype": "postalcode"
  },
  "geometry": {"coordinates":[-3.533058,51.495456],"type":"Point"}
}
