{
  "type": "Feature",
  "properties": {
    "iso:country":"GB",
    "wof:name":"B69 1DE",
    "wof:placetype":"postalcode"
},
  "geometry": {"coordinates":[-2.03509747313658,52.49192258862476],"type":"Point"}
}