{
  "type": "Feature",
  "properties": {
    "iso:country":"GB",
    "wof:name":"NE38 8JX",
    "wof:placetype":"postalcode"
},
  "geometry": {"coordinates":[-1.49566582763957,54.89069214752744],"type":"Point"}
}