{
  "type": "Feature",
  "properties": {
    "iso:country": "GB",
    "wof:name": "NE38 8JX",
    "wof:placetype": "postalcode"
  },
  "geometry": {"coordinates":[-1.495666,54.890692],"type":"Point"}
}
