{
  "type": "Feature",
  "properties": {
    "date:inception_lower": "1980-01-01",
    "date:inception_upper": "1980-01-01",
    "iso:country": "GB",
    "wof:name": "NE38 8JX",
    "wof:placetype": "postalcode"
  },
  "geometry": {"coordinates":[-1.495666,54.890692],"type":"Point"}
}
