{
  "type": "Feature",
  "properties": {
    "iso:country":"GB",
    "wof:name":"PH23 3AG",
    "wof:placetype":"postalcode"
},
  "geometry": {"coordinates":[-3.79050140198574,57.28200135589118],"type":"Point"}
}