{
  "type": "Feature",
  "properties": {
    "iso:country":"GB",
    "wof:name":"SS2 5HJ",
    "wof:placetype":"postalcode"
},
  "geometry": {"coordinates":[0.71858302000233,51.5470849834058],"type":"Point"}
}