{
  "type": "Feature",
  "properties": {
    "iso:country": "GB",
    "wof:name": "PE22 8AP",
    "wof:placetype": "postalcode"
  },
  "geometry": {"coordinates":[-0.004786,53.090861],"type":"Point"}
}
