{
  "type": "Feature",
  "properties": {
    "iso:country":"GB",
    "wof:name":"PE22 8AP",
    "wof:placetype":"postalcode"
},
  "geometry": {"coordinates":[-0.00632603360798,53.09114750875915],"type":"Point"}
}