{
  "type": "Feature",
  "properties": {
    "iso:country":"GB",
    "wof:name":"EN7 5NX",
    "wof:placetype":"postalcode"
},
  "geometry": {"coordinates":[-0.09282261509791,51.71037026440315],"type":"Point"}
}