{
  "type": "Feature",
  "properties": {
    "date:inception_lower":"1980-01-01",
    "date:inception_upper":"1980-01-31",
    "iso:country":"GB",
    "wof:name":"OX12 7NR",
    "wof:placetype":"postalcode"
},
  "geometry": {"coordinates":[-1.418325,51.610055],"type":"Point"}
}