{
  "type": "Feature",
  "properties": {
    "iso:country":"GB",
    "wof:name":"G13 3QJ",
    "wof:placetype":"postalcode"
},
  "geometry": {"coordinates":[-4.34638850688977,55.8908536581104],"type":"Point"}
}