{
  "type": "Feature",
  "properties": {
    "iso:country": "GB",
    "wof:name": "WA6 0JY",
    "wof:placetype": "postalcode"
  },
  "geometry": {"coordinates":[-2.790689,53.264822],"type":"Point"}
}
