{
  "type": "Feature",
  "properties": {
    "iso:country":"GB",
    "wof:name":"TS19 8UH",
    "wof:placetype":"postalcode"
},
  "geometry": {"coordinates":[-1.36138784134484,54.57754712190988],"type":"Point"}
}