{
  "type": "Feature",
  "properties": {
    "iso:country": "GB",
    "wof:name": "TD11 3NW",
    "wof:placetype": "postalcode"
  },
  "geometry": {"coordinates":[-2.355939,55.782257],"type":"Point"}
}
