{
  "type": "Feature",
  "properties": {
    "iso:country":"GB",
    "wof:name":"LE8 5WT",
    "wof:placetype":"postalcode"
},
  "geometry": {"coordinates":[-1.13525634210112,52.55228538851378],"type":"Point"}
}