{
  "type": "Feature",
  "properties": {
    "iso:country": "GB",
    "wof:name": "LE8 5WT",
    "wof:placetype": "postalcode"
  },
  "geometry": {"coordinates":[-1.135256,52.552285],"type":"Point"}
}
