{
  "type": "Feature",
  "properties": {
    "date:inception_lower": "1994-05-01",
    "date:inception_upper": "1994-05-01",
    "iso:country": "GB",
    "wof:name": "LE8 5WT",
    "wof:placetype": "postalcode"
  },
  "geometry": {"coordinates":[-1.135218,52.552295],"type":"Point"}
}
