{
  "type": "Feature",
  "properties": {
    "iso:country":"GB",
    "wof:name":"SN9 5HW",
    "wof:placetype":"postalcode"
},
  "geometry": {"coordinates":[-1.76448209936675,51.33483288863916],"type":"Point"}
}