{
  "type": "Feature",
  "properties": {
    "iso:country":"GB",
    "wof:name":"NG34 9RU",
    "wof:placetype":"postalcode"
},
  "geometry": {"coordinates":[-0.29706136920413,52.98668370429537],"type":"Point"}
}