{
  "type": "Feature",
  "properties": {
    "iso:country": "GB",
    "wof:name": "OL10 4EF",
    "wof:placetype": "postalcode"
  },
  "geometry": {"coordinates":[-2.211169,53.59482],"type":"Point"}
}
