{
  "type": "Feature",
  "properties": {
    "iso:country":"GB",
    "wof:name":"BS3 3JB",
    "wof:placetype":"postalcode"
},
  "geometry": {"coordinates":[-2.60988840470978,51.43465528484735],"type":"Point"}
}