{
  "type": "Feature",
  "properties": {
    "iso:country": "GB",
    "wof:name": "NR31 6PY",
    "wof:placetype": "postalcode"
  },
  "geometry": {"coordinates":[1.730287,52.579111],"type":"Point"}
}
