{
  "type": "Feature",
  "properties": {
    "iso:country":"GB",
    "wof:name":"DN11 9JF",
    "wof:placetype":"postalcode"
},
  "geometry": {"coordinates":[-1.1128691258849,53.43866108500593],"type":"Point"}
}