{
  "type": "Feature",
  "properties": {
    "date:inception_lower": "2021-06-01",
    "date:inception_upper": "2021-06-01",
    "iso:country": "GB",
    "wof:name": "CB24 1DU",
    "wof:placetype": "postalcode"
  },
  "geometry": {"coordinates":[0.053343,52.28498],"type":"Point"}
}
