{
  "type": "Feature",
  "properties": {
    "iso:country":"GB",
    "wof:name":"RG10 9SJ",
    "wof:placetype":"postalcode"
},
  "geometry": {"coordinates":[-0.87958195184599,51.47478095328063],"type":"Point"}
}