{
  "type": "Feature",
  "properties": {
    "date:inception_lower": "1997-12-01",
    "date:inception_upper": "1997-12-01",
    "iso:country": "GB",
    "wof:name": "RG10 9SJ",
    "wof:placetype": "postalcode"
  },
  "geometry": {"coordinates":[-0.879582,51.474781],"type":"Point"}
}
