{
  "type": "Feature",
  "properties": {
    "iso:country":"GB",
    "wof:name":"S21 4LE",
    "wof:placetype":"postalcode"
},
  "geometry": {"coordinates":[-1.36699375758427,53.30670453866147],"type":"Point"}
}