{
  "type": "Feature",
  "properties": {
    "iso:country": "GB",
    "wof:name": "S21 4LE",
    "wof:placetype": "postalcode"
  },
  "geometry": {"coordinates":[-1.366994,53.306705],"type":"Point"}
}
