{
  "type": "Feature",
  "properties": {
    "date:inception_lower": "1980-01-01",
    "date:inception_upper": "1980-01-01",
    "iso:country": "GB",
    "wof:name": "WS12 4BB",
    "wof:placetype": "postalcode"
  },
  "geometry": {"coordinates":[-2.008114,52.716213],"type":"Point"}
}
