{
  "type": "Feature",
  "properties": {
    "date:inception_lower": "1997-12-01",
    "date:inception_upper": "1997-12-01",
    "iso:country": "GB",
    "wof:name": "BS37 6PL",
    "wof:placetype": "postalcode"
  },
  "geometry": {"coordinates":[-2.371662,51.553684],"type":"Point"}
}
