{
  "type": "Feature",
  "properties": {
    "iso:country":"GB",
    "wof:name":"BS37 6PL",
    "wof:placetype":"postalcode"
},
  "geometry": {"coordinates":[-2.37162137962251,51.55369382544193],"type":"Point"}
}