{
  "type": "Feature",
  "properties": {
    "iso:country":"GB",
    "wof:name":"LS21 3HR",
    "wof:placetype":"postalcode"
},
  "geometry": {"coordinates":[-1.69612609823278,53.90351490991924],"type":"Point"}
}