{
  "type": "Feature",
  "properties": {
    "iso:country": "GB",
    "wof:name": "SS14 1FS",
    "wof:placetype": "postalcode"
  },
  "geometry": {"coordinates":[0.463384,51.571852],"type":"Point"}
}
