{
  "type": "Feature",
  "properties": {
    "iso:country":"GB",
    "wof:name":"S42 6EQ",
    "wof:placetype":"postalcode"
},
  "geometry": {"coordinates":[-1.41526605892553,53.19165895459578],"type":"Point"}
}