{
  "type": "Feature",
  "properties": {
    "iso:country":"GB",
    "wof:name":"CM3 3LD",
    "wof:placetype":"postalcode"
},
  "geometry": {"coordinates":[0.48949166469959,51.80570639341273],"type":"Point"}
}