{
  "type": "Feature",
  "properties": {
    "iso:country": "GB",
    "wof:name": "CM3 3LD",
    "wof:placetype": "postalcode"
  },
  "geometry": {"coordinates":[0.489492,51.805706],"type":"Point"}
}
