{
  "type": "Feature",
  "properties": {
    "iso:country": "GB",
    "wof:name": "OL6 8TA",
    "wof:placetype": "postalcode"
  },
  "geometry": {"coordinates":[-2.093932,53.496548],"type":"Point"}
}
