{
  "type": "Feature",
  "properties": {
    "iso:country":"GB",
    "wof:name":"OL6 8TA",
    "wof:placetype":"postalcode"
},
  "geometry": {"coordinates":[-2.09393209644467,53.49654778407904],"type":"Point"}
}