{
  "type": "Feature",
  "properties": {
    "iso:country":"GB",
    "wof:name":"PE25 3PZ",
    "wof:placetype":"postalcode"
},
  "geometry": {"coordinates":[0.33833303152274,53.1403032786621],"type":"Point"}
}