{
  "type": "Feature",
  "properties": {
    "iso:country": "GB",
    "wof:name": "IP6 0HJ",
    "wof:placetype": "postalcode"
  },
  "geometry": {"coordinates":[1.152647,52.099154],"type":"Point"}
}
