{
  "type": "Feature",
  "properties": {
    "iso:country":"GB",
    "wof:name":"IP6 0HJ",
    "wof:placetype":"postalcode"
},
  "geometry": {"coordinates":[1.15264698977185,52.09915371449427],"type":"Point"}
}