{
  "type": "Feature",
  "properties": {
    "iso:country": "GB",
    "wof:name": "IP6 0HJ",
    "wof:placetype": "postalcode"
  },
  "geometry": {"coordinates":[1.152676,52.099142],"type":"Point"}
}
