{
  "type": "Feature",
  "properties": {
    "date:inception_lower": "1980-01-01",
    "date:inception_upper": "1980-01-01",
    "iso:country": "GB",
    "wof:name": "IP6 0HJ",
    "wof:placetype": "postalcode"
  },
  "geometry": {"coordinates":[1.152697,52.09924],"type":"Point"}
}
