{
  "type": "Feature",
  "properties": {
    "iso:country": "GB",
    "wof:name": "SN14 6JJ",
    "wof:placetype": "postalcode"
  },
  "geometry": {"coordinates":[-2.145635,51.499677],"type":"Point"}
}
