{
  "type": "Feature",
  "properties": {
    "iso:country":"GB",
    "wof:name":"SN14 6JJ",
    "wof:placetype":"postalcode"
},
  "geometry": {"coordinates":[-2.14562551158525,51.49968635342815],"type":"Point"}
}