{
  "type": "Feature",
  "properties": {
    "iso:country":"GB",
    "wof:name":"SR7 9SL",
    "wof:placetype":"postalcode"
},
  "geometry": {"coordinates":[-1.40555822774331,54.81947103194806],"type":"Point"}
}