{
  "type": "Feature",
  "properties": {
    "iso:country": "GB",
    "wof:name": "SN16 9BU",
    "wof:placetype": "postalcode"
  },
  "geometry": {"coordinates":[-2.095926,51.582584],"type":"Point"}
}
