{
  "type": "Feature",
  "properties": {
    "iso:country":"GB",
    "wof:name":"NE48 4AT",
    "wof:placetype":"postalcode"
},
  "geometry": {"coordinates":[-2.15020311452843,55.06886130431356],"type":"Point"}
}