{
  "type": "Feature",
  "properties": {
    "iso:country":"GB",
    "wof:name":"SY5 6DF",
    "wof:placetype":"postalcode"
},
  "geometry": {"coordinates":[-2.60403283612677,52.63158117183673],"type":"Point"}
}