{
  "type": "Feature",
  "properties": {
    "iso:country": "GB",
    "wof:name": "SY5 6DF",
    "wof:placetype": "postalcode"
  },
  "geometry": {"coordinates":[-2.604033,52.631581],"type":"Point"}
}
