{
  "type": "Feature",
  "properties": {
    "iso:country":"GB",
    "wof:name":"W8 6XA",
    "wof:placetype":"postalcode"
},
  "geometry": {"coordinates":[-0.19546344993,51.49799251881149],"type":"Point"}
}