{
  "type": "Feature",
  "properties": {
    "iso:country":"GB",
    "wof:name":"DN22 9AE",
    "wof:placetype":"postalcode"
},
  "geometry": {"coordinates":[-0.90798712685403,53.38682352966325],"type":"Point"}
}