{
  "type": "Feature",
  "properties": {
    "iso:country":"GB",
    "wof:name":"WF12 9NS",
    "wof:placetype":"postalcode"
},
  "geometry": {"coordinates":[-1.6349911942557,53.6808104096503],"type":"Point"}
}