{
  "type": "Feature",
  "properties": {
    "date:inception_lower":"1980-01-01",
    "date:inception_upper":"1980-01-31",
    "iso:country":"GB",
    "wof:name":"WF12 9NS",
    "wof:placetype":"postalcode"
},
  "geometry": {"coordinates":[-1.634991,53.68081],"type":"Point"}
}