{
  "type": "Feature",
  "properties": {
    "iso:country":"GB",
    "wof:name":"OX18 1BY",
    "wof:placetype":"postalcode"
},
  "geometry": {"coordinates":[-1.60181358928143,51.773426789691],"type":"Point"}
}