{
  "type": "Feature",
  "properties": {
    "date:inception_lower": "2015-06-01",
    "date:inception_upper": "2015-06-01",
    "iso:country": "GB",
    "wof:name": "OX18 1BY",
    "wof:placetype": "postalcode"
  },
  "geometry": {"coordinates":[-1.601814,51.773427],"type":"Point"}
}
