{
  "type": "Feature",
  "properties": {
    "iso:country":"GB",
    "wof:name":"N1 5JW",
    "wof:placetype":"postalcode"
},
  "geometry": {"coordinates":[-0.07966377157859,51.53418307548665],"type":"Point"}
}