{
  "type": "Feature",
  "properties": {
    "date:inception_lower": "1992-01-01",
    "date:inception_upper": "1992-01-01",
    "iso:country": "GB",
    "wof:name": "LA4 4DB",
    "wof:placetype": "postalcode"
  },
  "geometry": {"coordinates":[-2.874901,54.071142],"type":"Point"}
}
