{
  "type": "Feature",
  "properties": {
    "iso:country":"GB",
    "wof:name":"LA4 4DB",
    "wof:placetype":"postalcode"
},
  "geometry": {"coordinates":[-2.874902865704,54.07113068399504],"type":"Point"}
}