{
  "type": "Feature",
  "properties": {
    "date:inception_lower":"1995-07-01",
    "date:inception_upper":"1995-07-31",
    "iso:country":"GB",
    "wof:name":"RG21 8UL",
    "wof:placetype":"postalcode"
},
  "geometry": {"coordinates":[-1.09405,51.260738],"type":"Point"}
}