{
  "type": "Feature",
  "properties": {
    "iso:country": "GB",
    "wof:name": "RG21 8UL",
    "wof:placetype": "postalcode"
  },
  "geometry": {"coordinates":[-1.09405,51.260738],"type":"Point"}
}
