{
  "type": "Feature",
  "properties": {
    "date:inception_lower": "1980-01-01",
    "date:inception_upper": "1980-01-01",
    "iso:country": "GB",
    "wof:name": "BL3 1SW",
    "wof:placetype": "postalcode"
  },
  "geometry": {"coordinates":[-2.395637,53.569374],"type":"Point"}
}
