{
  "type": "Feature",
  "properties": {
    "iso:country":"GB",
    "wof:name":"BL3 1SW",
    "wof:placetype":"postalcode"
},
  "geometry": {"coordinates":[-2.39563731922643,53.56937366638967],"type":"Point"}
}