{
  "type": "Feature",
  "properties": {
    "iso:country": "GB",
    "wof:name": "IV30 5RZ",
    "wof:placetype": "postalcode"
  },
  "geometry": {"coordinates":[-3.438208,57.707897],"type":"Point"}
}
