{
  "type": "Feature",
  "properties": {
    "iso:country": "GB",
    "wof:name": "NW2 3ND",
    "wof:placetype": "postalcode"
  },
  "geometry": {"coordinates":[-0.207548,51.552504],"type":"Point"}
}
