{
  "type": "Feature",
  "properties": {
    "iso:country":"GB",
    "wof:name":"NW2 3ND",
    "wof:placetype":"postalcode"
},
  "geometry": {"coordinates":[-0.20739039387725,51.55237271429706],"type":"Point"}
}