{
  "type": "Feature",
  "properties": {
    "iso:country":"GB",
    "wof:name":"SO31 6BN",
    "wof:placetype":"postalcode"
},
  "geometry": {"coordinates":[-1.28810635635148,50.86097718513074],"type":"Point"}
}