{
  "type": "Feature",
  "properties": {
    "date:inception_lower": "2015-04-01",
    "date:inception_upper": "2015-04-01",
    "iso:country": "GB",
    "wof:name": "SO31 6BN",
    "wof:placetype": "postalcode"
  },
  "geometry": {"coordinates":[-1.288106,50.860977],"type":"Point"}
}
