{
  "type": "Feature",
  "properties": {
    "iso:country":"GB",
    "wof:name":"RM14 3BT",
    "wof:placetype":"postalcode"
},
  "geometry": {"coordinates":[0.25228367333858,51.55619283522297],"type":"Point"}
}