{
  "type": "Feature",
  "properties": {
    "date:inception_lower":"1980-01-01",
    "date:inception_upper":"1980-01-31",
    "iso:country":"GB",
    "wof:name":"RM14 3BT",
    "wof:placetype":"postalcode"
},
  "geometry": {"coordinates":[0.252052,51.556179],"type":"Point"}
}