{
  "type": "Feature",
  "properties": {
    "iso:country": "GB",
    "wof:name": "TS20 1QF",
    "wof:placetype": "postalcode"
  },
  "geometry": {"coordinates":[-1.331089,54.595025],"type":"Point"}
}
