{
  "type": "Feature",
  "properties": {
    "iso:country":"GB",
    "wof:name":"EX39 2QX",
    "wof:placetype":"postalcode"
},
  "geometry": {"coordinates":[-4.20448085995578,51.02696691584583],"type":"Point"}
}