{
  "type": "Feature",
  "properties": {
    "iso:country":"GB",
    "wof:name":"TA7 9NA",
    "wof:placetype":"postalcode"
},
  "geometry": {"coordinates":[-2.82761469864219,51.13219571192717],"type":"Point"}
}