{
  "type": "Feature",
  "properties": {
    "iso:country": "GB",
    "wof:name": "TA7 9NA",
    "wof:placetype": "postalcode"
  },
  "geometry": {"coordinates":[-2.827621,51.13219],"type":"Point"}
}
