{
  "type": "Feature",
  "properties": {
    "date:inception_lower": "1980-01-01",
    "date:inception_upper": "1980-01-01",
    "iso:country": "GB",
    "wof:name": "TA7 9NA",
    "wof:placetype": "postalcode"
  },
  "geometry": {"coordinates":[-2.831237,51.135374],"type":"Point"}
}
