{
  "type": "Feature",
  "properties": {
    "iso:country":"GB",
    "wof:name":"WA4 2HG",
    "wof:placetype":"postalcode"
},
  "geometry": {"coordinates":[-2.53871933648281,53.38112448766806],"type":"Point"}
}