{
  "type": "Feature",
  "properties": {
    "iso:country": "GB",
    "wof:name": "WA4 2HG",
    "wof:placetype": "postalcode"
  },
  "geometry": {"coordinates":[-2.538719,53.381124],"type":"Point"}
}
