{
  "type": "Feature",
  "properties": {
    "iso:country": "GB",
    "wof:name": "LE15 9LZ",
    "wof:placetype": "postalcode"
  },
  "geometry": {"coordinates":[-0.709621,52.564262],"type":"Point"}
}
