{
  "type": "Feature",
  "properties": {
    "iso:country":"GB",
    "wof:name":"LE15 9LZ",
    "wof:placetype":"postalcode"
},
  "geometry": {"coordinates":[-0.70963384022984,52.56424429478451],"type":"Point"}
}