{
  "type": "Feature",
  "properties": {
    "date:inception_lower": "1980-01-01",
    "date:inception_upper": "1980-01-01",
    "iso:country": "GB",
    "wof:name": "GU27 3PY",
    "wof:placetype": "postalcode"
  },
  "geometry": {"coordinates":[-0.727945,51.072996],"type":"Point"}
}
