{
  "type": "Feature",
  "properties": {
    "iso:country": "GB",
    "wof:name": "GU27 3PY",
    "wof:placetype": "postalcode"
  },
  "geometry": {"coordinates":[-0.727945,51.072996],"type":"Point"}
}
