{
  "type": "Feature",
  "properties": {
    "date:inception_lower": "1996-06-01",
    "date:inception_upper": "1996-06-01",
    "iso:country": "GB",
    "wof:name": "AB24 4HP",
    "wof:placetype": "postalcode"
  },
  "geometry": {"coordinates":[-2.12509,57.167727],"type":"Point"}
}
