{
  "type": "Feature",
  "properties": {
    "date:inception_lower": "1980-01-01",
    "date:inception_upper": "1980-01-01",
    "iso:country": "GB",
    "wof:name": "B78 2EF",
    "wof:placetype": "postalcode"
  },
  "geometry": {"coordinates":[-1.673103,52.57332],"type":"Point"}
}
