{
  "type": "Feature",
  "properties": {
    "iso:country":"GB",
    "wof:name":"B78 2EF",
    "wof:placetype":"postalcode"
},
  "geometry": {"coordinates":[-1.67169170469351,52.56772565540889],"type":"Point"}
}