{
  "type": "Feature",
  "properties": {
    "iso:country":"GB",
    "wof:name":"RG1 2RE",
    "wof:placetype":"postalcode"
},
  "geometry": {"coordinates":[-0.9690024294871,51.44648544511056],"type":"Point"}
}