{
  "type": "Feature",
  "properties": {
    "date:inception_lower":"1980-01-01",
    "date:inception_upper":"1980-01-31",
    "iso:country":"GB",
    "wof:name":"DG9 0RY",
    "wof:placetype":"postalcode"
},
  "geometry": {"coordinates":[-5.171557,54.947572],"type":"Point"}
}