{
  "type": "Feature",
  "properties": {
    "iso:country":"GB",
    "wof:name":"DG9 0RY",
    "wof:placetype":"postalcode"
},
  "geometry": {"coordinates":[-5.17155683226777,54.94757194226307],"type":"Point"}
}