{
  "type": "Feature",
  "properties": {
    "iso:country":"GB",
    "wof:name":"RM15 4QP",
    "wof:placetype":"postalcode"
},
  "geometry": {"coordinates":[0.25381213354189,51.50655818605361],"type":"Point"}
}