{
  "type": "Feature",
  "properties": {
    "iso:country":"GB",
    "wof:name":"BN25 1QE",
    "wof:placetype":"postalcode"
},
  "geometry": {"coordinates":[0.10537202070899,50.77041813023401],"type":"Point"}
}