{
  "type": "Feature",
  "properties": {
    "iso:country": "GB",
    "wof:name": "BN25 1QE",
    "wof:placetype": "postalcode"
  },
  "geometry": {"coordinates":[0.105372,50.770418],"type":"Point"}
}
