{
  "type": "Feature",
  "properties": {
    "iso:country": "GB",
    "wof:name": "TQ12 6EQ",
    "wof:placetype": "postalcode"
  },
  "geometry": {"coordinates":[-3.688576,50.504982],"type":"Point"}
}
