{
  "type": "Feature",
  "properties": {
    "iso:country": "GB",
    "wof:name": "CV13 0JB",
    "wof:placetype": "postalcode"
  },
  "geometry": {"coordinates":[-1.364547,52.657832],"type":"Point"}
}
