{
  "type": "Feature",
  "properties": {
    "iso:country":"GB",
    "wof:name":"LL15 1YG",
    "wof:placetype":"postalcode"
},
  "geometry": {"coordinates":[-3.24919977491293,53.11277263630111],"type":"Point"}
}