{
  "type": "Feature",
  "properties": {
    "iso:country": "GB",
    "wof:name": "EX4 2ED",
    "wof:placetype": "postalcode"
  },
  "geometry": {"coordinates":[-3.555241,50.72701],"type":"Point"}
}
