{
  "type": "Feature",
  "properties": {
    "date:inception_lower": "1980-01-01",
    "date:inception_upper": "1980-01-01",
    "iso:country": "GB",
    "wof:name": "EX4 2ED",
    "wof:placetype": "postalcode"
  },
  "geometry": {"coordinates":[-3.555241,50.72701],"type":"Point"}
}
