{
  "type": "Feature",
  "properties": {
    "iso:country":"GB",
    "wof:name":"EX4 2ED",
    "wof:placetype":"postalcode"
},
  "geometry": {"coordinates":[-3.55524107108073,50.72700982634826],"type":"Point"}
}