{
  "type": "Feature",
  "properties": {
    "iso:country":"GB",
    "wof:name":"SK12 1PA",
    "wof:placetype":"postalcode"
},
  "geometry": {"coordinates":[-2.11557058232195,53.34425406605291],"type":"Point"}
}