{
  "type": "Feature",
  "properties": {
    "iso:country": "GB",
    "wof:name": "BL3 2DQ",
    "wof:placetype": "postalcode"
  },
  "geometry": {"coordinates":[-2.42984,53.563593],"type":"Point"}
}
