{
  "type": "Feature",
  "properties": {
    "date:inception_lower":"1985-10-01",
    "date:inception_upper":"1985-10-31",
    "iso:country":"GB",
    "wof:name":"BL3 2DQ",
    "wof:placetype":"postalcode"
},
  "geometry": {"coordinates":[-2.42984,53.563593],"type":"Point"}
}