{
  "type": "Feature",
  "properties": {
    "iso:country":"GB",
    "wof:name":"DN35 0DW",
    "wof:placetype":"postalcode"
},
  "geometry": {"coordinates":[-0.02406225981867,53.54882901684128],"type":"Point"}
}