{
  "type": "Feature",
  "properties": {
    "iso:country": "GB",
    "wof:name": "SM6 9QR",
    "wof:placetype": "postalcode"
  },
  "geometry": {"coordinates":[-0.139529,51.357886],"type":"Point"}
}
