{
  "type": "Feature",
  "properties": {
    "date:inception_lower": "1980-01-01",
    "date:inception_upper": "1980-01-01",
    "iso:country": "GB",
    "wof:name": "PH11 8BW",
    "wof:placetype": "postalcode"
  },
  "geometry": {"coordinates":[-3.231228,56.618184],"type":"Point"}
}
