{
  "type": "Feature",
  "properties": {
    "iso:country":"GB",
    "wof:name":"CV2 2NA",
    "wof:placetype":"postalcode"
},
  "geometry": {"coordinates":[-1.44806445442237,52.4353258305277],"type":"Point"}
}