{
  "type": "Feature",
  "properties": {
    "date:inception_lower": "2000-10-01",
    "date:inception_upper": "2000-10-01",
    "iso:country": "GB",
    "wof:name": "WD17 4SB",
    "wof:placetype": "postalcode"
  },
  "geometry": {"coordinates":[-0.412973,51.671535],"type":"Point"}
}
