{
  "type": "Feature",
  "properties": {
    "iso:country": "GB",
    "wof:name": "WD17 4SB",
    "wof:placetype": "postalcode"
  },
  "geometry": {"coordinates":[-0.412996,51.671529],"type":"Point"}
}
