{
  "type": "Feature",
  "properties": {
    "iso:country":"GB",
    "wof:name":"PR5 5UX",
    "wof:placetype":"postalcode"
},
  "geometry": {"coordinates":[-2.67933916403138,53.73235176807388],"type":"Point"}
}