{
  "type": "Feature",
  "properties": {
    "iso:country": "GB",
    "wof:name": "PR5 5UX",
    "wof:placetype": "postalcode"
  },
  "geometry": {"coordinates":[-2.679339,53.732352],"type":"Point"}
}
