{
  "type": "Feature",
  "properties": {
    "date:inception_lower": "1980-01-01",
    "date:inception_upper": "1980-01-01",
    "iso:country": "GB",
    "wof:name": "PR5 5UX",
    "wof:placetype": "postalcode"
  },
  "geometry": {"coordinates":[-2.679339,53.732352],"type":"Point"}
}
