{
  "type": "Feature",
  "properties": {
    "date:inception_lower": "1980-01-01",
    "date:inception_upper": "1980-01-01",
    "iso:country": "GB",
    "wof:name": "CM24 8AU",
    "wof:placetype": "postalcode"
  },
  "geometry": {"coordinates":[0.196817,51.901474],"type":"Point"}
}
