{
  "type": "Feature",
  "properties": {
    "iso:country":"GB",
    "wof:name":"DT2 9QA",
    "wof:placetype":"postalcode"
},
  "geometry": {"coordinates":[-2.44922660272938,50.72879478277677],"type":"Point"}
}