{
  "type": "Feature",
  "properties": {
    "iso:country":"GB",
    "wof:name":"DE21 4FW",
    "wof:placetype":"postalcode"
},
  "geometry": {"coordinates":[-1.45033020510794,52.94800348208278],"type":"Point"}
}