{
  "type": "Feature",
  "properties": {
    "iso:country":"GB",
    "wof:name":"SW17 0PW",
    "wof:placetype":"postalcode"
},
  "geometry": {"coordinates":[-0.17849860206669,51.43527714263974],"type":"Point"}
}