{
  "type": "Feature",
  "properties": {
    "iso:country":"GB",
    "wof:name":"DN18 5AA",
    "wof:placetype":"postalcode"
},
  "geometry": {"coordinates":[-0.44899438906581,53.6856272081538],"type":"Point"}
}