{
  "type": "Feature",
  "properties": {
    "iso:country": "GB",
    "wof:name": "DN18 5AA",
    "wof:placetype": "postalcode"
  },
  "geometry": {"coordinates":[-0.448994,53.685627],"type":"Point"}
}
