{
  "type": "Feature",
  "properties": {
    "iso:country":"GB",
    "wof:name":"G84 9BQ",
    "wof:placetype":"postalcode"
},
  "geometry": {"coordinates":[-4.72720422074095,56.01303951585826],"type":"Point"}
}