{
  "type": "Feature",
  "properties": {
    "date:inception_lower": "1980-01-01",
    "date:inception_upper": "1980-01-01",
    "iso:country": "GB",
    "wof:name": "G84 9BQ",
    "wof:placetype": "postalcode"
  },
  "geometry": {"coordinates":[-4.727204,56.01304],"type":"Point"}
}
