{
  "type": "Feature",
  "properties": {
    "iso:country":"GB",
    "wof:name":"IP2 9TE",
    "wof:placetype":"postalcode"
},
  "geometry": {"coordinates":[1.13968047243844,52.03784697125172],"type":"Point"}
}