{
  "type": "Feature",
  "properties": {
    "iso:country": "GB",
    "wof:name": "HP15 7QH",
    "wof:placetype": "postalcode"
  },
  "geometry": {"coordinates":[-0.716013,51.649691],"type":"Point"}
}
