{
  "type": "Feature",
  "properties": {
    "date:inception_lower": "1982-03-01",
    "date:inception_upper": "1982-03-01",
    "iso:country": "GB",
    "wof:name": "HP15 7QH",
    "wof:placetype": "postalcode"
  },
  "geometry": {"coordinates":[-0.716013,51.649691],"type":"Point"}
}
