{
  "type": "Feature",
  "properties": {
    "date:inception_lower": "2001-06-01",
    "date:inception_upper": "2001-06-01",
    "iso:country": "GB",
    "wof:name": "HU15 1FX",
    "wof:placetype": "postalcode"
  },
  "geometry": {"coordinates":[-0.539169,53.732202],"type":"Point"}
}
