{
  "type": "Feature",
  "properties": {
    "iso:country":"GB",
    "wof:name":"HU15 1FX",
    "wof:placetype":"postalcode"
},
  "geometry": {"coordinates":[-0.53914821654489,53.73219087917499],"type":"Point"}
}