{
  "type": "Feature",
  "properties": {
    "iso:country":"GB",
    "wof:name":"CV34 5SX",
    "wof:placetype":"postalcode"
},
  "geometry": {"coordinates":[-1.57389055771368,52.29455591315335],"type":"Point"}
}