{
  "type": "Feature",
  "properties": {
    "iso:country": "GB",
    "wof:name": "PO13 8AA",
    "wof:placetype": "postalcode"
  },
  "geometry": {"coordinates":[-1.16962,50.803495],"type":"Point"}
}
