{
  "type": "Feature",
  "properties": {
    "date:inception_lower": "1980-01-01",
    "date:inception_upper": "1980-01-01",
    "iso:country": "GB",
    "wof:name": "PO13 8AA",
    "wof:placetype": "postalcode"
  },
  "geometry": {"coordinates":[-1.16962,50.803495],"type":"Point"}
}
