{
  "type": "Feature",
  "properties": {
    "iso:country": "GB",
    "wof:name": "HA9 6HH",
    "wof:placetype": "postalcode"
  },
  "geometry": {"coordinates":[-0.284327,51.548586],"type":"Point"}
}
