{
  "type": "Feature",
  "properties": {
    "iso:country":"GB",
    "wof:name":"B70 0HD",
    "wof:placetype":"postalcode"
},
  "geometry": {"coordinates":[-2.02844582000138,52.5228856608333],"type":"Point"}
}