{
  "type": "Feature",
  "properties": {
    "date:inception_lower": "2018-04-01",
    "date:inception_upper": "2018-04-01",
    "iso:country": "GB",
    "wof:name": "WS13 6FJ",
    "wof:placetype": "postalcode"
  },
  "geometry": {"coordinates":[-1.832712,52.682006],"type":"Point"}
}
