{
  "type": "Feature",
  "properties": {
    "iso:country":"GB",
    "wof:name":"CT15 7NH",
    "wof:placetype":"postalcode"
},
  "geometry": {"coordinates":[1.22838582522489,51.18584015276512],"type":"Point"}
}