{
  "type": "Feature",
  "properties": {
    "iso:country":"GB",
    "wof:name":"BD17 5JB",
    "wof:placetype":"postalcode"
},
  "geometry": {"coordinates":[-1.78043451917579,53.84160134351739],"type":"Point"}
}