{
  "type": "Feature",
  "properties": {
    "date:inception_lower": "1992-01-01",
    "date:inception_upper": "1992-01-01",
    "iso:country": "GB",
    "wof:name": "BD20 6TU",
    "wof:placetype": "postalcode"
  },
  "geometry": {"coordinates":[-1.953429,53.895774],"type":"Point"}
}
