{
  "type": "Feature",
  "properties": {
    "iso:country":"GB",
    "wof:name":"BD20 6TU",
    "wof:placetype":"postalcode"
},
  "geometry": {"coordinates":[-1.95342937378323,53.89577383173253],"type":"Point"}
}