{
  "type": "Feature",
  "properties": {
    "iso:country":"GB",
    "wof:name":"LE7 7LE",
    "wof:placetype":"postalcode"
},
  "geometry": {"coordinates":[-1.15324832060245,52.70778033130698],"type":"Point"}
}