{
  "type": "Feature",
  "properties": {
    "iso:country":"GB",
    "wof:name":"SN15 5JP",
    "wof:placetype":"postalcode"
},
  "geometry": {"coordinates":[-2.0447121015817,51.55926467405991],"type":"Point"}
}