{
  "type": "Feature",
  "properties": {
    "iso:country":"GB",
    "wof:name":"WF2 6QE",
    "wof:placetype":"postalcode"
},
  "geometry": {"coordinates":[-1.49690349081505,53.64251465116052],"type":"Point"}
}