{
  "type": "Feature",
  "properties": {
    "iso:country":"GB",
    "wof:name":"IP21 5TE",
    "wof:placetype":"postalcode"
},
  "geometry": {"coordinates":[1.31816298638125,52.35324182846718],"type":"Point"}
}