{
  "type": "Feature",
  "properties": {
    "iso:country":"GB",
    "wof:name":"IP3 9NY",
    "wof:placetype":"postalcode"
},
  "geometry": {"coordinates":[1.18478305462168,52.03346960207514],"type":"Point"}
}