{
  "type": "Feature",
  "properties": {
    "iso:country": "GB",
    "wof:name": "YO26 9RD",
    "wof:placetype": "postalcode"
  },
  "geometry": {"coordinates":[-1.31477,54.048457],"type":"Point"}
}
