{
  "type": "Feature",
  "properties": {
    "date:inception_lower": "1998-06-01",
    "date:inception_upper": "1998-06-01",
    "iso:country": "GB",
    "wof:name": "YO26 9RD",
    "wof:placetype": "postalcode"
  },
  "geometry": {"coordinates":[-1.31477,54.048457],"type":"Point"}
}
