{
  "type": "Feature",
  "properties": {
    "iso:country":"GB",
    "wof:name":"BD5 7PD",
    "wof:placetype":"postalcode"
},
  "geometry": {"coordinates":[-1.76368810558256,53.77919313084951],"type":"Point"}
}