{
  "type": "Feature",
  "properties": {
    "iso:country": "GB",
    "wof:name": "SW1P 2QF",
    "wof:placetype": "postalcode"
  },
  "geometry": {"coordinates":[-0.134819,51.495281],"type":"Point"}
}
