{
  "type": "Feature",
  "properties": {
    "iso:country":"GB",
    "wof:name":"SW1P 2QF",
    "wof:placetype":"postalcode"
},
  "geometry": {"coordinates":[-0.13481907427915,51.49528115055109],"type":"Point"}
}