{
  "type": "Feature",
  "properties": {
    "iso:country":"GB",
    "wof:name":"BS5 8EJ",
    "wof:placetype":"postalcode"
},
  "geometry": {"coordinates":[-2.54604580888248,51.45888792782447],"type":"Point"}
}