{
  "type": "Feature",
  "properties": {
    "date:inception_lower": "2006-03-01",
    "date:inception_upper": "2006-03-01",
    "iso:country": "GB",
    "wof:name": "CV34 6LW",
    "wof:placetype": "postalcode"
  },
  "geometry": {"coordinates":[-1.55215,52.275566],"type":"Point"}
}
