{
  "type": "Feature",
  "properties": {
    "iso:country": "GB",
    "wof:name": "HR3 6BH",
    "wof:placetype": "postalcode"
  },
  "geometry": {"coordinates":[-2.991493,52.055916],"type":"Point"}
}
