{
  "type": "Feature",
  "properties": {
    "date:inception_lower": "1980-01-01",
    "date:inception_upper": "1980-01-01",
    "iso:country": "GB",
    "wof:name": "HR3 6BH",
    "wof:placetype": "postalcode"
  },
  "geometry": {"coordinates":[-2.991493,52.055916],"type":"Point"}
}
