{
  "type": "Feature",
  "properties": {
    "iso:country":"GB",
    "wof:name":"HR3 6BH",
    "wof:placetype":"postalcode"
},
  "geometry": {"coordinates":[-2.99149275188636,52.05591634652134],"type":"Point"}
}