{
  "type": "Feature",
  "properties": {
    "iso:country": "GB",
    "wof:name": "RM13 8JE",
    "wof:placetype": "postalcode"
  },
  "geometry": {"coordinates":[0.170943,51.521244],"type":"Point"}
}
