{
  "type": "Feature",
  "properties": {
    "iso:country":"GB",
    "wof:name":"S40 2JE",
    "wof:placetype":"postalcode"
},
  "geometry": {"coordinates":[-1.42902415830978,53.21731727164945],"type":"Point"}
}