{
  "type": "Feature",
  "properties": {
    "iso:country": "GB",
    "wof:name": "SE9 6QN",
    "wof:placetype": "postalcode"
  },
  "geometry": {"coordinates":[0.044456,51.45535],"type":"Point"}
}
