{
  "type": "Feature",
  "properties": {
    "iso:country":"GB",
    "wof:name":"CV6 7NS",
    "wof:placetype":"postalcode"
},
  "geometry": {"coordinates":[-1.48437991264791,52.42792896290661],"type":"Point"}
}