{
  "type": "Feature",
  "properties": {
    "date:inception_lower": "1980-01-01",
    "date:inception_upper": "1980-01-01",
    "iso:country": "GB",
    "wof:name": "TA8 2LY",
    "wof:placetype": "postalcode"
  },
  "geometry": {"coordinates":[-3.005289,51.265578],"type":"Point"}
}
