{
  "type": "Feature",
  "properties": {
    "iso:country":"GB",
    "wof:name":"TA8 2LY",
    "wof:placetype":"postalcode"
},
  "geometry": {"coordinates":[-3.00528895839906,51.26557846245604],"type":"Point"}
}