{
  "type": "Feature",
  "properties": {
    "iso:country":"GB",
    "wof:name":"L38 0AA",
    "wof:placetype":"postalcode"
},
  "geometry": {"coordinates":[-3.05815520888256,53.52636199528833],"type":"Point"}
}