{
  "type": "Feature",
  "properties": {
    "date:inception_lower":"2016-03-01",
    "date:inception_upper":"2016-03-31",
    "iso:country":"GB",
    "wof:name":"L38 0AA",
    "wof:placetype":"postalcode"
},
  "geometry": {"coordinates":[-3.058096,53.526505],"type":"Point"}
}