{
  "type": "Feature",
  "properties": {
    "date:inception_lower": "1995-01-01",
    "date:inception_upper": "1995-01-01",
    "iso:country": "GB",
    "wof:name": "DE13 7LB",
    "wof:placetype": "postalcode"
  },
  "geometry": {"coordinates":[-1.629188,52.815734],"type":"Point"}
}
