{
  "type": "Feature",
  "properties": {
    "date:inception_lower": "1980-01-01",
    "date:inception_upper": "1980-01-01",
    "iso:country": "GB",
    "wof:name": "B5 5NR",
    "wof:placetype": "postalcode"
  },
  "geometry": {"coordinates":[-1.887275,52.476966],"type":"Point"}
}
