{
  "type": "Feature",
  "properties": {
    "iso:country":"GB",
    "wof:name":"IG3 9LD",
    "wof:placetype":"postalcode"
},
  "geometry": {"coordinates":[0.10007544744416,51.56095874897458],"type":"Point"}
}