{
  "type": "Feature",
  "properties": {
    "iso:country": "GB",
    "wof:name": "HD9 1QD",
    "wof:placetype": "postalcode"
  },
  "geometry": {"coordinates":[-1.770877,53.57878],"type":"Point"}
}
