{
  "type": "Feature",
  "properties": {
    "iso:country": "GB",
    "wof:name": "G46 7NG",
    "wof:placetype": "postalcode"
  },
  "geometry": {"coordinates":[-4.298852,55.800109],"type":"Point"}
}
