{
  "type": "Feature",
  "properties": {
    "date:inception_lower": "1980-01-01",
    "date:inception_upper": "1980-01-01",
    "iso:country": "GB",
    "wof:name": "G46 7NG",
    "wof:placetype": "postalcode"
  },
  "geometry": {"coordinates":[-4.298852,55.800109],"type":"Point"}
}
