{
  "type": "Feature",
  "properties": {
    "iso:country":"GB",
    "wof:name":"CA12 4SU",
    "wof:placetype":"postalcode"
},
  "geometry": {"coordinates":[-3.04558973776662,54.62442907256197],"type":"Point"}
}