{
  "type": "Feature",
  "properties": {
    "iso:country":"GB",
    "wof:name":"S65 1QD",
    "wof:placetype":"postalcode"
},
  "geometry": {"coordinates":[-1.34651997380243,53.43369539086785],"type":"Point"}
}