{
  "type": "Feature",
  "properties": {
    "date:inception_lower":"1980-01-01",
    "date:inception_upper":"1980-01-31",
    "iso:country":"GB",
    "wof:name":"E14 0QX",
    "wof:placetype":"postalcode"
},
  "geometry": {"coordinates":[-0.009751,51.512919],"type":"Point"}
}