{
  "type": "Feature",
  "properties": {
    "iso:country":"GB",
    "wof:name":"E14 0QX",
    "wof:placetype":"postalcode"
},
  "geometry": {"coordinates":[-0.00975145110646,51.51291915487145],"type":"Point"}
}