{
  "type": "Feature",
  "properties": {
    "date:inception_lower": "2017-09-01",
    "date:inception_upper": "2017-09-01",
    "iso:country": "GB",
    "wof:name": "LE11 5BP",
    "wof:placetype": "postalcode"
  },
  "geometry": {"coordinates":[-1.213215,52.776158],"type":"Point"}
}
