{
  "type": "Feature",
  "properties": {
    "iso:country":"GB",
    "wof:name":"IV25 3NA",
    "wof:placetype":"postalcode"
},
  "geometry": {"coordinates":[-4.07329927920727,57.90358548359821],"type":"Point"}
}