{
  "type": "Feature",
  "properties": {
    "date:inception_lower": "1996-06-01",
    "date:inception_upper": "1996-06-01",
    "iso:country": "GB",
    "wof:name": "B98 7WX",
    "wof:placetype": "postalcode"
  },
  "geometry": {"coordinates":[-1.933856,52.280216],"type":"Point"}
}
