{
  "type": "Feature",
  "properties": {
    "iso:country": "GB",
    "wof:name": "TF2 8SQ",
    "wof:placetype": "postalcode"
  },
  "geometry": {"coordinates":[-2.415372,52.720645],"type":"Point"}
}
