{
  "type": "Feature",
  "properties": {
    "date:inception_lower":"1999-12-01",
    "date:inception_upper":"1999-12-31",
    "iso:country":"GB",
    "wof:name":"TF2 8SQ",
    "wof:placetype":"postalcode"
},
  "geometry": {"coordinates":[-2.415372,52.720645],"type":"Point"}
}