{
  "type": "Feature",
  "properties": {
    "iso:country":"GB",
    "wof:name":"TF2 8SQ",
    "wof:placetype":"postalcode"
},
  "geometry": {"coordinates":[-2.41537206210649,52.7206452587983],"type":"Point"}
}