{
  "type": "Feature",
  "properties": {
    "iso:country":"GB",
    "wof:name":"CT6 6QZ",
    "wof:placetype":"postalcode"
},
  "geometry": {"coordinates":[1.16765626517737,51.37166988794733],"type":"Point"}
}