{
  "type": "Feature",
  "properties": {
    "iso:country": "GB",
    "wof:name": "CT6 6QZ",
    "wof:placetype": "postalcode"
  },
  "geometry": {"coordinates":[1.167656,51.37167],"type":"Point"}
}
