{
  "type": "Feature",
  "properties": {
    "iso:country":"GB",
    "wof:name":"IP25 7JF",
    "wof:placetype":"postalcode"
},
  "geometry": {"coordinates":[0.80831636058413,52.5965565336969],"type":"Point"}
}