{
  "type": "Feature",
  "properties": {
    "iso:country":"GB",
    "wof:name":"IP8 4QL",
    "wof:placetype":"postalcode"
},
  "geometry": {"coordinates":[1.03441786400598,52.09982124240441],"type":"Point"}
}