{
  "type": "Feature",
  "properties": {
    "iso:country": "GB",
    "wof:name": "IP8 4QL",
    "wof:placetype": "postalcode"
  },
  "geometry": {"coordinates":[1.034418,52.099821],"type":"Point"}
}
