{
  "type": "Feature",
  "properties": {
    "date:inception_lower": "2019-09-01",
    "date:inception_upper": "2019-09-01",
    "iso:country": "GB",
    "wof:name": "ME15 7FB",
    "wof:placetype": "postalcode"
  },
  "geometry": {"coordinates":[0.534287,51.258795],"type":"Point"}
}
