{
  "type": "Feature",
  "properties": {
    "date:inception_lower": "1980-01-01",
    "date:inception_upper": "1980-01-01",
    "iso:country": "GB",
    "wof:name": "TN26 2JW",
    "wof:placetype": "postalcode"
  },
  "geometry": {"coordinates":[0.852861,51.065296],"type":"Point"}
}
