{
  "type": "Feature",
  "properties": {
    "iso:country": "GB",
    "wof:name": "LS22 6WD",
    "wof:placetype": "postalcode"
  },
  "geometry": {"coordinates":[-1.396735,53.935928],"type":"Point"}
}
