{
  "type": "Feature",
  "properties": {
    "iso:country":"GB",
    "wof:name":"LS22 6WD",
    "wof:placetype":"postalcode"
},
  "geometry": {"coordinates":[-1.39673525451002,53.93592757147961],"type":"Point"}
}