{
  "type": "Feature",
  "properties": {
    "date:inception_lower": "1980-01-01",
    "date:inception_upper": "1980-01-01",
    "iso:country": "GB",
    "wof:name": "TN12 7HB",
    "wof:placetype": "postalcode"
  },
  "geometry": {"coordinates":[0.348917,51.136232],"type":"Point"}
}
