{
  "type": "Feature",
  "properties": {
    "iso:country":"GB",
    "wof:name":"TN12 7HB",
    "wof:placetype":"postalcode"
},
  "geometry": {"coordinates":[0.34891727446857,51.13623240073834],"type":"Point"}
}