{
  "type": "Feature",
  "properties": {
    "iso:country":"GB",
    "wof:name":"NE38 0HY",
    "wof:placetype":"postalcode"
},
  "geometry": {"coordinates":[-1.53967121942961,54.89936788179245],"type":"Point"}
}