{
  "type": "Feature",
  "properties": {
    "iso:country": "GB",
    "wof:name": "GL1 2PG",
    "wof:placetype": "postalcode"
  },
  "geometry": {"coordinates":[-2.250202,51.867151],"type":"Point"}
}
