{
  "type": "Feature",
  "properties": {
    "date:inception_lower": "1980-01-01",
    "date:inception_upper": "1980-01-01",
    "iso:country": "GB",
    "wof:name": "SG5 3NS",
    "wof:placetype": "postalcode"
  },
  "geometry": {"coordinates":[-0.366815,51.99551],"type":"Point"}
}
