{
  "type": "Feature",
  "properties": {
    "date:inception_lower": "1980-01-01",
    "date:inception_upper": "1980-01-01",
    "iso:country": "GB",
    "wof:name": "NR22 6AY",
    "wof:placetype": "postalcode"
  },
  "geometry": {"coordinates":[0.827002,52.905505],"type":"Point"}
}
