{
  "type": "Feature",
  "properties": {
    "iso:country":"GB",
    "wof:name":"NR22 6AY",
    "wof:placetype":"postalcode"
},
  "geometry": {"coordinates":[0.82697121615959,52.90548023584184],"type":"Point"}
}