{
  "type": "Feature",
  "properties": {
    "date:inception_lower": "2024-01-01",
    "date:inception_upper": "2024-01-01",
    "iso:country": "GB",
    "wof:name": "FY8 9LX",
    "wof:placetype": "postalcode"
  },
  "geometry": {"coordinates":[-3.030492,53.74871],"type":"Point"}
}
