{
  "type": "Feature",
  "properties": {
    "date:inception_lower":"2010-12-01",
    "date:inception_upper":"2010-12-31",
    "iso:country":"GB",
    "wof:name":"S70 4FD",
    "wof:placetype":"postalcode"
},
  "geometry": {"coordinates":[-1.475379,53.543694],"type":"Point"}
}