{
  "type": "Feature",
  "properties": {
    "iso:country": "GB",
    "wof:name": "S70 4FD",
    "wof:placetype": "postalcode"
  },
  "geometry": {"coordinates":[-1.475379,53.543694],"type":"Point"}
}
