{
  "type": "Feature",
  "properties": {
    "iso:country":"GB",
    "wof:name":"SY11 3LS",
    "wof:placetype":"postalcode"
},
  "geometry": {"coordinates":[-3.0384475161637,52.89523704573316],"type":"Point"}
}