{
  "type": "Feature",
  "properties": {
    "iso:country":"GB",
    "wof:name":"CA2 5QY",
    "wof:placetype":"postalcode"
},
  "geometry": {"coordinates":[-2.95669293535807,54.88697163192552],"type":"Point"}
}