{
  "type": "Feature",
  "properties": {
    "date:inception_lower": "1980-01-01",
    "date:inception_upper": "1980-01-01",
    "iso:country": "GB",
    "wof:name": "BB11 2BN",
    "wof:placetype": "postalcode"
  },
  "geometry": {"coordinates":[-2.244796,53.786941],"type":"Point"}
}
