{
  "type": "Feature",
  "properties": {
    "iso:country": "GB",
    "wof:name": "BB11 2BN",
    "wof:placetype": "postalcode"
  },
  "geometry": {"coordinates":[-2.244796,53.786941],"type":"Point"}
}
