{
  "type": "Feature",
  "properties": {
    "iso:country":"GB",
    "wof:name":"E16 3AH",
    "wof:placetype":"postalcode"
},
  "geometry": {"coordinates":[0.02372032275106,51.51046688416631],"type":"Point"}
}