{
  "type": "Feature",
  "properties": {
    "date:inception_lower":"2012-03-01",
    "date:inception_upper":"2012-03-31",
    "iso:country":"GB",
    "wof:name":"L23 7WD",
    "wof:placetype":"postalcode"
},
  "geometry": {"coordinates":[-3.027269,53.475593],"type":"Point"}
}