{
  "type": "Feature",
  "properties": {
    "iso:country": "GB",
    "wof:name": "ML4 2AD",
    "wof:placetype": "postalcode"
  },
  "geometry": {"coordinates":[-4.032742,55.811687],"type":"Point"}
}
