{
  "type": "Feature",
  "properties": {
    "date:inception_lower": "1980-01-01",
    "date:inception_upper": "1980-01-01",
    "iso:country": "GB",
    "wof:name": "ML4 2AD",
    "wof:placetype": "postalcode"
  },
  "geometry": {"coordinates":[-4.032742,55.811687],"type":"Point"}
}
