{
  "type": "Feature",
  "properties": {
    "iso:country":"GB",
    "wof:name":"ML4 2AD",
    "wof:placetype":"postalcode"
},
  "geometry": {"coordinates":[-4.03274227939954,55.81168653163168],"type":"Point"}
}