{
  "type": "Feature",
  "properties": {
    "iso:country":"GB",
    "wof:name":"NW1 8RT",
    "wof:placetype":"postalcode"
},
  "geometry": {"coordinates":[-0.14392419888882,51.54349049353139],"type":"Point"}
}