{
  "type": "Feature",
  "properties": {
    "iso:country":"GB",
    "wof:name":"UB8 1LX",
    "wof:placetype":"postalcode"
},
  "geometry": {"coordinates":[-0.48565106455226,51.54827288536235],"type":"Point"}
}