{
  "type": "Feature",
  "properties": {
    "iso:country":"GB",
    "wof:name":"BD12 9HH",
    "wof:placetype":"postalcode"
},
  "geometry": {"coordinates":[-1.75837746573118,53.74469547490594],"type":"Point"}
}