{
  "type": "Feature",
  "properties": {
    "iso:country":"GB",
    "wof:name":"CW2 8PS",
    "wof:placetype":"postalcode"
},
  "geometry": {"coordinates":[-2.47133105349955,53.09129323151078],"type":"Point"}
}