{
  "type": "Feature",
  "properties": {
    "iso:country": "GB",
    "wof:name": "CW2 8PS",
    "wof:placetype": "postalcode"
  },
  "geometry": {"coordinates":[-2.471331,53.091293],"type":"Point"}
}
