{
  "type": "Feature",
  "properties": {
    "iso:country":"GB",
    "wof:name":"CM23 5LF",
    "wof:placetype":"postalcode"
},
  "geometry": {"coordinates":[0.17425464819606,51.86229958912152],"type":"Point"}
}