{
  "type": "Feature",
  "properties": {
    "date:inception_lower":"1980-01-01",
    "date:inception_upper":"1980-01-31",
    "iso:country":"GB",
    "wof:name":"CM23 5LF",
    "wof:placetype":"postalcode"
},
  "geometry": {"coordinates":[0.174255,51.8623],"type":"Point"}
}