{
  "type": "Feature",
  "properties": {
    "iso:country": "GB",
    "wof:name": "CM23 5LF",
    "wof:placetype": "postalcode"
  },
  "geometry": {"coordinates":[0.174255,51.8623],"type":"Point"}
}
