{
  "type": "Feature",
  "properties": {
    "iso:country":"GB",
    "wof:name":"NE15 9JU",
    "wof:placetype":"postalcode"
},
  "geometry": {"coordinates":[-1.76340312370349,54.99535316150637],"type":"Point"}
}