{
  "type": "Feature",
  "properties": {
    "date:inception_lower": "2010-05-01",
    "date:inception_upper": "2010-05-01",
    "iso:country": "GB",
    "wof:name": "YO25 9BF",
    "wof:placetype": "postalcode"
  },
  "geometry": {"coordinates":[-0.567265,53.95876],"type":"Point"}
}
