{
  "type": "Feature",
  "properties": {
    "iso:country":"GB",
    "wof:name":"YO25 9BF",
    "wof:placetype":"postalcode"
},
  "geometry": {"coordinates":[-0.56725497924668,53.95875867308401],"type":"Point"}
}