{
  "type": "Feature",
  "properties": {
    "iso:country": "GB",
    "wof:name": "YO25 9BF",
    "wof:placetype": "postalcode"
  },
  "geometry": {"coordinates":[-0.567265,53.95876],"type":"Point"}
}
