{
  "type": "Feature",
  "properties": {
    "iso:country":"GB",
    "wof:name":"B65 9ED",
    "wof:placetype":"postalcode"
},
  "geometry": {"coordinates":[-2.04122233961315,52.48978099360709],"type":"Point"}
}