{
  "type": "Feature",
  "properties": {
    "iso:country":"GB",
    "wof:name":"TR13 0JU",
    "wof:placetype":"postalcode"
},
  "geometry": {"coordinates":[-5.22919949995434,50.14590735410248],"type":"Point"}
}