{
  "type": "Feature",
  "properties": {
    "date:inception_lower":"1980-01-01",
    "date:inception_upper":"1980-01-31",
    "iso:country":"GB",
    "wof:name":"TR13 0JU",
    "wof:placetype":"postalcode"
},
  "geometry": {"coordinates":[-5.229199,50.145907],"type":"Point"}
}