{
  "type": "Feature",
  "properties": {
    "iso:country":"GB",
    "wof:name":"TR26 2NR",
    "wof:placetype":"postalcode"
},
  "geometry": {"coordinates":[-5.46004130079384,50.19629817574422],"type":"Point"}
}