{
  "type": "Feature",
  "properties": {
    "iso:country": "GB",
    "wof:name": "CF44 0DA",
    "wof:placetype": "postalcode"
  },
  "geometry": {"coordinates":[-3.405126,51.702811],"type":"Point"}
}
