{
  "type": "Feature",
  "properties": {
    "iso:country":"GB",
    "wof:name":"CF44 0DA",
    "wof:placetype":"postalcode"
},
  "geometry": {"coordinates":[-3.40512564119481,51.70281104553747],"type":"Point"}
}