{
  "type": "Feature",
  "properties": {
    "iso:country":"GB",
    "wof:name":"IV2 3XN",
    "wof:placetype":"postalcode"
},
  "geometry": {"coordinates":[-4.20186476355008,57.47387514816922],"type":"Point"}
}