{
  "type": "Feature",
  "properties": {
    "iso:country":"GB",
    "wof:name":"WF10 2DU",
    "wof:placetype":"postalcode"
},
  "geometry": {"coordinates":[-1.37412427510343,53.7498042442956],"type":"Point"}
}