{
  "type": "Feature",
  "properties": {
    "iso:country":"GB",
    "wof:name":"WR4 0EZ",
    "wof:placetype":"postalcode"
},
  "geometry": {"coordinates":[-2.178040075669,52.20162671304383],"type":"Point"}
}