{
  "type": "Feature",
  "properties": {
    "date:inception_lower": "1980-01-01",
    "date:inception_upper": "1980-01-01",
    "iso:country": "GB",
    "wof:name": "G61 2JA",
    "wof:placetype": "postalcode"
  },
  "geometry": {"coordinates":[-4.319795,55.910196],"type":"Point"}
}
