{
  "type": "Feature",
  "properties": {
    "iso:country":"GB",
    "wof:name":"G61 2JA",
    "wof:placetype":"postalcode"
},
  "geometry": {"coordinates":[-4.31979482005953,55.91019576949414],"type":"Point"}
}