{
  "type": "Feature",
  "properties": {
    "iso:country": "GB",
    "wof:name": "S10 1BA",
    "wof:placetype": "postalcode"
  },
  "geometry": {"coordinates":[-1.493487,53.385474],"type":"Point"}
}
