{
  "type": "Feature",
  "properties": {
    "iso:country": "GB",
    "wof:name": "BR2 9HP",
    "wof:placetype": "postalcode"
  },
  "geometry": {"coordinates":[0.031935,51.393194],"type":"Point"}
}
