{
  "type": "Feature",
  "properties": {
    "iso:country": "GB",
    "wof:name": "SA19 8TP",
    "wof:placetype": "postalcode"
  },
  "geometry": {"coordinates":[-3.940886,52.014724],"type":"Point"}
}
