{
  "type": "Feature",
  "properties": {
    "iso:country":"GB",
    "wof:name":"M43 6GX",
    "wof:placetype":"postalcode"
},
  "geometry": {"coordinates":[-2.14996666396671,53.47659908982617],"type":"Point"}
}