{
  "type": "Feature",
  "properties": {
    "date:inception_lower":"1994-05-01",
    "date:inception_upper":"1994-05-31",
    "iso:country":"GB",
    "wof:name":"M43 6GX",
    "wof:placetype":"postalcode"
},
  "geometry": {"coordinates":[-2.149967,53.476599],"type":"Point"}
}