{
  "type": "Feature",
  "properties": {
    "date:inception_lower":"1980-01-01",
    "date:inception_upper":"1980-01-31",
    "iso:country":"GB",
    "wof:name":"LS15 8QE",
    "wof:placetype":"postalcode"
},
  "geometry": {"coordinates":[-1.429732,53.797259],"type":"Point"}
}