{
  "type": "Feature",
  "properties": {
    "iso:country":"GB",
    "wof:name":"LS15 8QE",
    "wof:placetype":"postalcode"
},
  "geometry": {"coordinates":[-1.42992532443129,53.79721622553059],"type":"Point"}
}