{
  "type": "Feature",
  "properties": {
    "iso:country": "GB",
    "wof:name": "LS15 8QE",
    "wof:placetype": "postalcode"
  },
  "geometry": {"coordinates":[-1.429732,53.797259],"type":"Point"}
}
