{
  "type": "Feature",
  "properties": {
    "date:inception_lower": "1980-01-01",
    "date:inception_upper": "1980-01-01",
    "iso:country": "GB",
    "wof:name": "SN8 2LY",
    "wof:placetype": "postalcode"
  },
  "geometry": {"coordinates":[-1.692944,51.424494],"type":"Point"}
}
