{
  "type": "Feature",
  "properties": {
    "iso:country": "GB",
    "wof:name": "ST9 9AH",
    "wof:placetype": "postalcode"
  },
  "geometry": {"coordinates":[-2.113062,53.100102],"type":"Point"}
}
