{
  "type": "Feature",
  "properties": {
    "iso:country":"GB",
    "wof:name":"ST9 9AH",
    "wof:placetype":"postalcode"
},
  "geometry": {"coordinates":[-2.11306176850758,53.10010183027507],"type":"Point"}
}