{
  "type": "Feature",
  "properties": {
    "date:inception_lower": "1980-01-01",
    "date:inception_upper": "1980-01-01",
    "iso:country": "GB",
    "wof:name": "HR1 1ER",
    "wof:placetype": "postalcode"
  },
  "geometry": {"coordinates":[-2.708371,52.063039],"type":"Point"}
}
