{
  "type": "Feature",
  "properties": {
    "iso:country":"GB",
    "wof:name":"HR1 1ER",
    "wof:placetype":"postalcode"
},
  "geometry": {"coordinates":[-2.70837116289595,52.06303863405657],"type":"Point"}
}