{
  "type": "Feature",
  "properties": {
    "iso:country":"GB",
    "wof:name":"ST14 7HQ",
    "wof:placetype":"postalcode"
},
  "geometry": {"coordinates":[-1.88609272789437,52.9081379514496],"type":"Point"}
}