{
  "type": "Feature",
  "properties": {
    "iso:country": "GB",
    "wof:name": "N13 4NP",
    "wof:placetype": "postalcode"
  },
  "geometry": {"coordinates":[-0.120284,51.612926],"type":"Point"}
}
