{
  "type": "Feature",
  "properties": {
    "iso:country":"GB",
    "wof:name":"N13 4NP",
    "wof:placetype":"postalcode"
},
  "geometry": {"coordinates":[-0.1207814604465,51.61302030466397],"type":"Point"}
}