{
  "type": "Feature",
  "properties": {
    "date:inception_lower": "1980-01-01",
    "date:inception_upper": "1980-01-01",
    "iso:country": "GB",
    "wof:name": "DY1 4DX",
    "wof:placetype": "postalcode"
  },
  "geometry": {"coordinates":[-2.091122,52.52698],"type":"Point"}
}
