{
  "type": "Feature",
  "properties": {
    "date:inception_lower": "1980-01-01",
    "date:inception_upper": "1980-01-01",
    "iso:country": "GB",
    "wof:name": "DN18 5AE",
    "wof:placetype": "postalcode"
  },
  "geometry": {"coordinates":[-0.454921,53.685884],"type":"Point"}
}
