{
  "type": "Feature",
  "properties": {
    "iso:country":"GB",
    "wof:name":"EC2V 7DE",
    "wof:placetype":"postalcode"
},
  "geometry": {"coordinates":[-0.09515713059651,51.51672936817619],"type":"Point"}
}