{
  "type": "Feature",
  "properties": {
    "iso:country":"GB",
    "wof:name":"B67 6LZ",
    "wof:placetype":"postalcode"
},
  "geometry": {"coordinates":[-1.99109196151911,52.48175992611935],"type":"Point"}
}