{
  "type": "Feature",
  "properties": {
    "iso:country":"GB",
    "wof:name":"DE21 7AW",
    "wof:placetype":"postalcode"
},
  "geometry": {"coordinates":[-1.40710464414506,52.92558302227194],"type":"Point"}
}