{
  "type": "Feature",
  "properties": {
    "iso:country":"GB",
    "wof:name":"LS29 0PR",
    "wof:placetype":"postalcode"
},
  "geometry": {"coordinates":[-1.89719994069832,53.94625026772242],"type":"Point"}
}