{
  "type": "Feature",
  "properties": {
    "iso:country":"GB",
    "wof:name":"GL4 0BJ",
    "wof:placetype":"postalcode"
},
  "geometry": {"coordinates":[-2.24335477877512,51.83367399845059],"type":"Point"}
}