{
  "type": "Feature",
  "properties": {
    "date:inception_lower": "1980-01-01",
    "date:inception_upper": "1980-01-01",
    "iso:country": "GB",
    "wof:name": "FK1 5BH",
    "wof:placetype": "postalcode"
  },
  "geometry": {"coordinates":[-3.789012,55.999247],"type":"Point"}
}
