{
  "type": "Feature",
  "properties": {
    "iso:country":"GB",
    "wof:name":"FK1 5BH",
    "wof:placetype":"postalcode"
},
  "geometry": {"coordinates":[-3.78901216519998,55.99924740187792],"type":"Point"}
}