{
  "type": "Feature",
  "properties": {
    "iso:country": "GB",
    "wof:name": "NP11 5LS",
    "wof:placetype": "postalcode"
  },
  "geometry": {"coordinates":[-3.131201,51.674496],"type":"Point"}
}
