{
  "type": "Feature",
  "properties": {
    "iso:country":"GB",
    "wof:name":"NP11 5LS",
    "wof:placetype":"postalcode"
},
  "geometry": {"coordinates":[-3.13120139043228,51.67449590204593],"type":"Point"}
}