{
  "type": "Feature",
  "properties": {
    "iso:country":"GB",
    "wof:name":"SP7 8RU",
    "wof:placetype":"postalcode"
},
  "geometry": {"coordinates":[-2.18208435992959,51.0062792141511],"type":"Point"}
}