{
  "type": "Feature",
  "properties": {
    "iso:country": "GB",
    "wof:name": "S5 6GD",
    "wof:placetype": "postalcode"
  },
  "geometry": {"coordinates":[-1.436131,53.417235],"type":"Point"}
}
