{
  "type": "Feature",
  "properties": {
    "iso:country":"GB",
    "wof:name":"WN3 5TY",
    "wof:placetype":"postalcode"
},
  "geometry": {"coordinates":[-2.64172744721431,53.5348689411442],"type":"Point"}
}