{
  "type": "Feature",
  "properties": {
    "date:inception_lower": "1980-01-01",
    "date:inception_upper": "1980-01-01",
    "iso:country": "GB",
    "wof:name": "LL41 4UL",
    "wof:placetype": "postalcode"
  },
  "geometry": {"coordinates":[-3.922841,52.90656],"type":"Point"}
}
