{
  "type": "Feature",
  "properties": {
    "iso:country": "GB",
    "wof:name": "NE10 0TJ",
    "wof:placetype": "postalcode"
  },
  "geometry": {"coordinates":[-1.532291,54.96033],"type":"Point"}
}
