{
  "type": "Feature",
  "properties": {
    "iso:country":"GB",
    "wof:name":"NE10 0TJ",
    "wof:placetype":"postalcode"
},
  "geometry": {"coordinates":[-1.53229088330937,54.96033014070844],"type":"Point"}
}