{
  "type": "Feature",
  "properties": {
    "date:inception_lower":"1980-01-01",
    "date:inception_upper":"1980-01-31",
    "iso:country":"GB",
    "wof:name":"NE10 0TJ",
    "wof:placetype":"postalcode"
},
  "geometry": {"coordinates":[-1.532291,54.96033],"type":"Point"}
}