{
  "type": "Feature",
  "properties": {
    "date:inception_lower": "1980-01-01",
    "date:inception_upper": "1980-01-01",
    "iso:country": "GB",
    "wof:name": "EX17 6DH",
    "wof:placetype": "postalcode"
  },
  "geometry": {"coordinates":[-3.821567,50.822243],"type":"Point"}
}
