{
  "type": "Feature",
  "properties": {
    "iso:country":"GB",
    "wof:name":"EX17 6DH",
    "wof:placetype":"postalcode"
},
  "geometry": {"coordinates":[-3.81947932738957,50.82239159917884],"type":"Point"}
}