{
  "type": "Feature",
  "properties": {
    "iso:country": "GB",
    "wof:name": "SL6 0DD",
    "wof:placetype": "postalcode"
  },
  "geometry": {"coordinates":[-0.690598,51.530012],"type":"Point"}
}
