{
  "type": "Feature",
  "properties": {
    "iso:country":"GB",
    "wof:name":"SL6 0DD",
    "wof:placetype":"postalcode"
},
  "geometry": {"coordinates":[-0.69059803423506,51.53001235092416],"type":"Point"}
}