{
  "type": "Feature",
  "properties": {
    "iso:country":"GB",
    "wof:name":"G33 4UG",
    "wof:placetype":"postalcode"
},
  "geometry": {"coordinates":[-4.12936611380068,55.8564338568482],"type":"Point"}
}