{
  "type": "Feature",
  "properties": {
    "iso:country":"GB",
    "wof:name":"ML1 2NE",
    "wof:placetype":"postalcode"
},
  "geometry": {"coordinates":[-3.9597490681989,55.77051643423155],"type":"Point"}
}