{
  "type": "Feature",
  "properties": {
    "iso:country":"GB",
    "wof:name":"B70 6RN",
    "wof:placetype":"postalcode"
},
  "geometry": {"coordinates":[-1.98246713807147,52.50954686761344],"type":"Point"}
}