{
  "type": "Feature",
  "properties": {
    "iso:country": "GB",
    "wof:name": "EX37 9SR",
    "wof:placetype": "postalcode"
  },
  "geometry": {"coordinates":[-3.877387,50.956941],"type":"Point"}
}
