{
  "type": "Feature",
  "properties": {
    "date:inception_lower": "1999-06-01",
    "date:inception_upper": "1999-06-01",
    "iso:country": "GB",
    "wof:name": "G45 9DE",
    "wof:placetype": "postalcode"
  },
  "geometry": {"coordinates":[-4.239601,55.806151],"type":"Point"}
}
