{
  "type": "Feature",
  "properties": {
    "iso:country":"GB",
    "wof:name":"G45 9DE",
    "wof:placetype":"postalcode"
},
  "geometry": {"coordinates":[-4.23960130340552,55.80615059396536],"type":"Point"}
}