{
  "type": "Feature",
  "properties": {
    "iso:country":"GB",
    "wof:name":"SP8 5AQ",
    "wof:placetype":"postalcode"
},
  "geometry": {"coordinates":[-2.30632829021772,51.07156343510714],"type":"Point"}
}