{
  "type": "Feature",
  "properties": {
    "iso:country":"GB",
    "wof:name":"CF44 0BJ",
    "wof:placetype":"postalcode"
},
  "geometry": {"coordinates":[-3.45274863498065,51.73749747264579],"type":"Point"}
}