{
  "type": "Feature",
  "properties": {
    "iso:country":"GB",
    "wof:name":"DN6 0JG",
    "wof:placetype":"postalcode"
},
  "geometry": {"coordinates":[-1.14912430581944,53.61757421624741],"type":"Point"}
}