{
  "type": "Feature",
  "properties": {
    "iso:country":"GB",
    "wof:name":"S21 1ET",
    "wof:placetype":"postalcode"
},
  "geometry": {"coordinates":[-1.31573717540759,53.31652514700472],"type":"Point"}
}