{
  "type": "Feature",
  "properties": {
    "iso:country": "GB",
    "wof:name": "S21 1ET",
    "wof:placetype": "postalcode"
  },
  "geometry": {"coordinates":[-1.315737,53.316525],"type":"Point"}
}
