{
  "type": "Feature",
  "properties": {
    "date:inception_lower": "1980-01-01",
    "date:inception_upper": "1980-01-01",
    "iso:country": "GB",
    "wof:name": "WA11 7QE",
    "wof:placetype": "postalcode"
  },
  "geometry": {"coordinates":[-2.768327,53.469744],"type":"Point"}
}
