{
  "type": "Feature",
  "properties": {
    "iso:country": "GB",
    "wof:name": "SP2 0NT",
    "wof:placetype": "postalcode"
  },
  "geometry": {"coordinates":[-1.886188,51.115657],"type":"Point"}
}
