{
  "type": "Feature",
  "properties": {
    "iso:country":"GB",
    "wof:name":"SP2 0NT",
    "wof:placetype":"postalcode"
},
  "geometry": {"coordinates":[-1.88618769492321,51.11565687613071],"type":"Point"}
}