{
  "type": "Feature",
  "properties": {
    "iso:country":"GB",
    "wof:name":"CM3 4JG",
    "wof:placetype":"postalcode"
},
  "geometry": {"coordinates":[0.59143122809821,51.70931709736524],"type":"Point"}
}