{
  "type": "Feature",
  "properties": {
    "iso:country": "GB",
    "wof:name": "GU14 7BY",
    "wof:placetype": "postalcode"
  },
  "geometry": {"coordinates":[-0.748397,51.293414],"type":"Point"}
}
