{
  "type": "Feature",
  "properties": {
    "iso:country":"GB",
    "wof:name":"PR3 0JS",
    "wof:placetype":"postalcode"
},
  "geometry": {"coordinates":[-2.79997229582584,53.91580175241388],"type":"Point"}
}