{
  "type": "Feature",
  "properties": {
    "date:inception_lower": "2018-04-01",
    "date:inception_upper": "2018-04-01",
    "iso:country": "GB",
    "wof:name": "NG2 2JA",
    "wof:placetype": "postalcode"
  },
  "geometry": {"coordinates":[-1.144442,52.942683],"type":"Point"}
}
