{
  "type": "Feature",
  "properties": {
    "iso:country":"GB",
    "wof:name":"CT1 3UD",
    "wof:placetype":"postalcode"
},
  "geometry": {"coordinates":[1.06042741998812,51.26892612469662],"type":"Point"}
}