{
  "type": "Feature",
  "properties": {
    "iso:country":"GB",
    "wof:name":"OX14 4RX",
    "wof:placetype":"postalcode"
},
  "geometry": {"coordinates":[-1.29747117190227,51.62197364615403],"type":"Point"}
}