{
  "type": "Feature",
  "properties": {
    "iso:country":"GB",
    "wof:name":"BH21 3XA",
    "wof:placetype":"postalcode"
},
  "geometry": {"coordinates":[-2.01285525233924,50.77964135777795],"type":"Point"}
}