{
  "type": "Feature",
  "properties": {
    "date:inception_lower": "1990-07-01",
    "date:inception_upper": "1990-07-01",
    "iso:country": "GB",
    "wof:name": "BH21 3XA",
    "wof:placetype": "postalcode"
  },
  "geometry": {"coordinates":[-2.012855,50.779641],"type":"Point"}
}
