{
  "type": "Feature",
  "properties": {
    "iso:country": "GB",
    "wof:name": "BH21 3XA",
    "wof:placetype": "postalcode"
  },
  "geometry": {"coordinates":[-2.012855,50.779641],"type":"Point"}
}
