{
  "type": "Feature",
  "properties": {
    "iso:country":"GB",
    "wof:name":"CO7 0LJ",
    "wof:placetype":"postalcode"
},
  "geometry": {"coordinates":[1.01949874028889,51.81388828124542],"type":"Point"}
}