{
  "type": "Feature",
  "properties": {
    "date:inception_lower": "1994-05-01",
    "date:inception_upper": "1994-05-01",
    "iso:country": "GB",
    "wof:name": "HD2 1FG",
    "wof:placetype": "postalcode"
  },
  "geometry": {"coordinates":[-1.750489,53.6658],"type":"Point"}
}
