{
  "type": "Feature",
  "properties": {
    "iso:country":"GB",
    "wof:name":"HD2 1FG",
    "wof:placetype":"postalcode"
},
  "geometry": {"coordinates":[-1.75048952541257,53.66579958733156],"type":"Point"}
}