{
  "type": "Feature",
  "properties": {
    "iso:country":"GB",
    "wof:name":"B34 7SW",
    "wof:placetype":"postalcode"
},
  "geometry": {"coordinates":[-1.76368653645408,52.49224081860417],"type":"Point"}
}