{
  "type": "Feature",
  "properties": {
    "iso:country":"GB",
    "wof:name":"SO21 3DN",
    "wof:placetype":"postalcode"
},
  "geometry": {"coordinates":[-1.25005543234888,51.15014099631622],"type":"Point"}
}