{
  "type": "Feature",
  "properties": {
    "iso:country":"GB",
    "wof:name":"HP27 9UA",
    "wof:placetype":"postalcode"
},
  "geometry": {"coordinates":[-0.84996020746844,51.71103973451313],"type":"Point"}
}