{
  "type": "Feature",
  "properties": {
    "date:inception_lower": "1997-06-01",
    "date:inception_upper": "1997-06-01",
    "iso:country": "GB",
    "wof:name": "HP27 9UA",
    "wof:placetype": "postalcode"
  },
  "geometry": {"coordinates":[-0.84996,51.71104],"type":"Point"}
}
