{
  "type": "Feature",
  "properties": {
    "iso:country": "GB",
    "wof:name": "HP27 9UA",
    "wof:placetype": "postalcode"
  },
  "geometry": {"coordinates":[-0.84996,51.71104],"type":"Point"}
}
