{
  "type": "Feature",
  "properties": {
    "date:inception_lower":"1980-01-01",
    "date:inception_upper":"1980-01-31",
    "iso:country":"GB",
    "wof:name":"DN11 0BT",
    "wof:placetype":"postalcode"
},
  "geometry": {"coordinates":[-1.066126,53.470999],"type":"Point"}
}