{
  "type": "Feature",
  "properties": {
    "iso:country":"GB",
    "wof:name":"SO31 9FH",
    "wof:placetype":"postalcode"
},
  "geometry": {"coordinates":[-1.30030463752032,50.85383886318355],"type":"Point"}
}