{
  "type": "Feature",
  "properties": {
    "iso:country": "GB",
    "wof:name": "PE19 7BA",
    "wof:placetype": "postalcode"
  },
  "geometry": {"coordinates":[-0.28311,52.223711],"type":"Point"}
}
