{
  "type": "Feature",
  "properties": {
    "iso:country":"GB",
    "wof:name":"CM18 7NN",
    "wof:placetype":"postalcode"
},
  "geometry": {"coordinates":[0.08798577379904,51.75314838288056],"type":"Point"}
}