{
  "type": "Feature",
  "properties": {
    "iso:country": "GB",
    "wof:name": "HU15 1SR",
    "wof:placetype": "postalcode"
  },
  "geometry": {"coordinates":[-0.564442,53.727517],"type":"Point"}
}
