{
  "type": "Feature",
  "properties": {
    "iso:country":"GB",
    "wof:name":"HU15 1SR",
    "wof:placetype":"postalcode"
},
  "geometry": {"coordinates":[-0.56444192498892,53.72751668086131],"type":"Point"}
}