{
  "type": "Feature",
  "properties": {
    "date:inception_lower": "2018-05-01",
    "date:inception_upper": "2018-05-01",
    "iso:country": "GB",
    "wof:name": "IP25 7FL",
    "wof:placetype": "postalcode"
  },
  "geometry": {"coordinates":[0.7757,52.598652],"type":"Point"}
}
