{
  "type": "Feature",
  "properties": {
    "iso:country": "GB",
    "wof:name": "IP25 7FL",
    "wof:placetype": "postalcode"
  },
  "geometry": {"coordinates":[0.7757,52.598652],"type":"Point"}
}
