{
  "type": "Feature",
  "properties": {
    "iso:country":"GB",
    "wof:name":"CT14 9HR",
    "wof:placetype":"postalcode"
},
  "geometry": {"coordinates":[1.37859512519816,51.21390586268572],"type":"Point"}
}