{
  "type": "Feature",
  "properties": {
    "iso:country": "GB",
    "wof:name": "ML8 5GN",
    "wof:placetype": "postalcode"
  },
  "geometry": {"coordinates":[-3.843766,55.731961],"type":"Point"}
}
