{
  "type": "Feature",
  "properties": {
    "iso:country":"GB",
    "wof:name":"HG1 5BS",
    "wof:placetype":"postalcode"
},
  "geometry": {"coordinates":[-1.52955877338902,53.99683800206238],"type":"Point"}
}