{
  "type": "Feature",
  "properties": {
    "iso:country":"GB",
    "wof:name":"BH23 3BZ",
    "wof:placetype":"postalcode"
},
  "geometry": {"coordinates":[-1.74693801524452,50.74302897847107],"type":"Point"}
}