{
  "type": "Feature",
  "properties": {
    "iso:country":"GB",
    "wof:name":"M18 8QQ",
    "wof:placetype":"postalcode"
},
  "geometry": {"coordinates":[-2.16567713632852,53.46778759643062],"type":"Point"}
}