{
  "type": "Feature",
  "properties": {
    "iso:country": "GB",
    "wof:name": "LS22 6YU",
    "wof:placetype": "postalcode"
  },
  "geometry": {"coordinates":[-1.379475,53.931939],"type":"Point"}
}
