{
  "type": "Feature",
  "properties": {
    "iso:country":"GB",
    "wof:name":"LS22 6YU",
    "wof:placetype":"postalcode"
},
  "geometry": {"coordinates":[-1.37947554601284,53.93193893189829],"type":"Point"}
}