{
  "type": "Feature",
  "properties": {
    "iso:country":"GB",
    "wof:name":"CV34 5AD",
    "wof:placetype":"postalcode"
},
  "geometry": {"coordinates":[-1.59190673004006,52.29022323839167],"type":"Point"}
}