{
  "type": "Feature",
  "properties": {
    "iso:country":"GB",
    "wof:name":"E5 9JE",
    "wof:placetype":"postalcode"
},
  "geometry": {"coordinates":[-0.05608074283171,51.56686026238291],"type":"Point"}
}