{
  "type": "Feature",
  "properties": {
    "date:inception_lower":"1980-01-01",
    "date:inception_upper":"1980-01-31",
    "iso:country":"GB",
    "wof:name":"S2 5HQ",
    "wof:placetype":"postalcode"
},
  "geometry": {"coordinates":[-1.444908,53.372818],"type":"Point"}
}