{
  "type": "Feature",
  "properties": {
    "iso:country": "GB",
    "wof:name": "NE34 8TZ",
    "wof:placetype": "postalcode"
  },
  "geometry": {"coordinates":[-1.42313,54.961227],"type":"Point"}
}
