{
  "type": "Feature",
  "properties": {
    "iso:country": "GB",
    "wof:name": "BD19 3RT",
    "wof:placetype": "postalcode"
  },
  "geometry": {"coordinates":[-1.712532,53.723742],"type":"Point"}
}
