{
  "type": "Feature",
  "properties": {
    "iso:country":"GB",
    "wof:name":"BD19 3RT",
    "wof:placetype":"postalcode"
},
  "geometry": {"coordinates":[-1.71253213646228,53.7237420340151],"type":"Point"}
}