{
  "type": "Feature",
  "properties": {
    "iso:country": "GB",
    "wof:name": "CM18 6RS",
    "wof:placetype": "postalcode"
  },
  "geometry": {"coordinates":[0.09354,51.759515],"type":"Point"}
}
