{
  "type": "Feature",
  "properties": {
    "date:inception_lower": "1980-01-01",
    "date:inception_upper": "1980-01-01",
    "iso:country": "GB",
    "wof:name": "CM18 6RS",
    "wof:placetype": "postalcode"
  },
  "geometry": {"coordinates":[0.09354,51.759515],"type":"Point"}
}
