{
  "type": "Feature",
  "properties": {
    "date:inception_lower": "1993-01-01",
    "date:inception_upper": "1993-01-01",
    "iso:country": "GB",
    "wof:name": "CF61 1GZ",
    "wof:placetype": "postalcode"
  },
  "geometry": {"coordinates":[-3.465393,51.40826],"type":"Point"}
}
