{
  "type": "Feature",
  "properties": {
    "iso:country":"GB",
    "wof:name":"CF61 1GZ",
    "wof:placetype":"postalcode"
},
  "geometry": {"coordinates":[-3.4653934184391,51.408259548551],"type":"Point"}
}