{
  "type": "Feature",
  "properties": {
    "date:inception_lower": "1980-01-01",
    "date:inception_upper": "1980-01-01",
    "iso:country": "GB",
    "wof:name": "RM14 1AS",
    "wof:placetype": "postalcode"
  },
  "geometry": {"coordinates":[0.254327,51.570419],"type":"Point"}
}
