{
  "type": "Feature",
  "properties": {
    "iso:country": "GB",
    "wof:name": "PO37 6BB",
    "wof:placetype": "postalcode"
  },
  "geometry": {"coordinates":[-1.174033,50.630055],"type":"Point"}
}
