{
  "type": "Feature",
  "properties": {
    "iso:country":"GB",
    "wof:name":"PO37 6BB",
    "wof:placetype":"postalcode"
},
  "geometry": {"coordinates":[-1.17403351264153,50.6300547496668],"type":"Point"}
}