{
  "type": "Feature",
  "properties": {
    "iso:country":"GB",
    "wof:name":"IG1 3RT",
    "wof:placetype":"postalcode"
},
  "geometry": {"coordinates":[0.06451023596874,51.57335240403643],"type":"Point"}
}