{
  "type": "Feature",
  "properties": {
    "iso:country": "GB",
    "wof:name": "IG1 3RT",
    "wof:placetype": "postalcode"
  },
  "geometry": {"coordinates":[0.06451,51.573352],"type":"Point"}
}
