{
  "type": "Feature",
  "properties": {
    "iso:country":"GB",
    "wof:name":"MK45 4JT",
    "wof:placetype":"postalcode"
},
  "geometry": {"coordinates":[-0.42694706226918,51.96412033243813],"type":"Point"}
}