{
  "type": "Feature",
  "properties": {
    "iso:country": "GB",
    "wof:name": "MK45 4JT",
    "wof:placetype": "postalcode"
  },
  "geometry": {"coordinates":[-0.426922,51.964129],"type":"Point"}
}
