{
  "type": "Feature",
  "properties": {
    "iso:country": "GB",
    "wof:name": "PR25 2XP",
    "wof:placetype": "postalcode"
  },
  "geometry": {"coordinates":[-2.702336,53.696994],"type":"Point"}
}
