{
  "type": "Feature",
  "properties": {
    "date:inception_lower":"1999-06-01",
    "date:inception_upper":"1999-06-30",
    "iso:country":"GB",
    "wof:name":"SA73 1PG",
    "wof:placetype":"postalcode"
},
  "geometry": {"coordinates":[-4.921535,51.711362],"type":"Point"}
}