{
  "type": "Feature",
  "properties": {
    "date:inception_lower":"1985-04-01",
    "date:inception_upper":"1985-04-30",
    "iso:country":"GB",
    "wof:name":"DN22 7FU",
    "wof:placetype":"postalcode"
},
  "geometry": {"coordinates":[-0.956836,53.310611],"type":"Point"}
}