{
  "type": "Feature",
  "properties": {
    "iso:country":"GB",
    "wof:name":"DN22 7FU",
    "wof:placetype":"postalcode"
},
  "geometry": {"coordinates":[-0.95683600125737,53.31061052818976],"type":"Point"}
}