{
  "type": "Feature",
  "properties": {
    "iso:country":"GB",
    "wof:name":"BH21 5JY",
    "wof:placetype":"postalcode"
},
  "geometry": {"coordinates":[-2.03966068586717,50.89410067226402],"type":"Point"}
}