{
  "type": "Feature",
  "properties": {
    "iso:country": "GB",
    "wof:name": "KT22 9JF",
    "wof:placetype": "postalcode"
  },
  "geometry": {"coordinates":[-0.356614,51.297195],"type":"Point"}
}
