{
  "type": "Feature",
  "properties": {
    "iso:country":"GB",
    "wof:name":"TN5 6NS",
    "wof:placetype":"postalcode"
},
  "geometry": {"coordinates":[0.31947312626667,51.04641615390516],"type":"Point"}
}