{
  "type": "Feature",
  "properties": {
    "date:inception_lower":"1980-01-01",
    "date:inception_upper":"1980-01-31",
    "iso:country":"GB",
    "wof:name":"LA12 9HJ",
    "wof:placetype":"postalcode"
},
  "geometry": {"coordinates":[-3.088671,54.184504],"type":"Point"}
}