{
  "type": "Feature",
  "properties": {
    "iso:country":"GB",
    "wof:name":"LA12 9HJ",
    "wof:placetype":"postalcode"
},
  "geometry": {"coordinates":[-3.08830338947554,54.18450674504291],"type":"Point"}
}