{
  "type": "Feature",
  "properties": {
    "iso:country":"GB",
    "wof:name":"DN18 5HF",
    "wof:placetype":"postalcode"
},
  "geometry": {"coordinates":[-0.43689395869284,53.68647668688526],"type":"Point"}
}