{
  "type": "Feature",
  "properties": {
    "date:inception_lower": "1980-01-01",
    "date:inception_upper": "1980-01-01",
    "iso:country": "GB",
    "wof:name": "DN18 5HF",
    "wof:placetype": "postalcode"
  },
  "geometry": {"coordinates":[-0.436894,53.686477],"type":"Point"}
}
