{
  "type": "Feature",
  "properties": {
    "iso:country": "GB",
    "wof:name": "DN18 5HF",
    "wof:placetype": "postalcode"
  },
  "geometry": {"coordinates":[-0.436894,53.686477],"type":"Point"}
}
