{
  "type": "Feature",
  "properties": {
    "iso:country":"GB",
    "wof:name":"NE16 3AD",
    "wof:placetype":"postalcode"
},
  "geometry": {"coordinates":[-1.68696761105586,54.95345757573821],"type":"Point"}
}