{
  "type": "Feature",
  "properties": {
    "iso:country":"GB",
    "wof:name":"UB8 9ST",
    "wof:placetype":"postalcode"
},
  "geometry": {"coordinates":[-0.47659755126543,51.54383948167423],"type":"Point"}
}