{
  "type": "Feature",
  "properties": {
    "date:inception_lower": "1980-01-01",
    "date:inception_upper": "1980-01-01",
    "iso:country": "GB",
    "wof:name": "NE63 0AG",
    "wof:placetype": "postalcode"
  },
  "geometry": {"coordinates":[-1.568572,55.181303],"type":"Point"}
}
