{
  "type": "Feature",
  "properties": {
    "iso:country": "GB",
    "wof:name": "HP10 8DH",
    "wof:placetype": "postalcode"
  },
  "geometry": {"coordinates":[-0.696784,51.640456],"type":"Point"}
}
