{
  "type": "Feature",
  "properties": {
    "date:inception_lower": "1984-10-01",
    "date:inception_upper": "1984-10-01",
    "iso:country": "GB",
    "wof:name": "L2 1XA",
    "wof:placetype": "postalcode"
  },
  "geometry": {"coordinates":[-2.989685,53.404062],"type":"Point"}
}
