{
  "type": "Feature",
  "properties": {
    "iso:country":"GB",
    "wof:name":"CF82 8HN",
    "wof:placetype":"postalcode"
},
  "geometry": {"coordinates":[-3.24136224180222,51.66665723701688],"type":"Point"}
}