{
  "type": "Feature",
  "properties": {
    "date:inception_lower": "1995-07-01",
    "date:inception_upper": "1995-07-01",
    "iso:country": "GB",
    "wof:name": "CF82 8HN",
    "wof:placetype": "postalcode"
  },
  "geometry": {"coordinates":[-3.241362,51.666657],"type":"Point"}
}
