{
  "type": "Feature",
  "properties": {
    "iso:country":"GB",
    "wof:name":"DY2 9PE",
    "wof:placetype":"postalcode"
},
  "geometry": {"coordinates":[-2.07504182949339,52.4843523539339],"type":"Point"}
}