{
  "type": "Feature",
  "properties": {
    "iso:country":"GB",
    "wof:name":"FK6 5DN",
    "wof:placetype":"postalcode"
},
  "geometry": {"coordinates":[-3.90754924338724,56.01741116961234],"type":"Point"}
}