{
  "type": "Feature",
  "properties": {
    "iso:country":"GB",
    "wof:name":"SG8 6HB",
    "wof:placetype":"postalcode"
},
  "geometry": {"coordinates":[0.02459105623268,52.08654477979844],"type":"Point"}
}