{
  "type": "Feature",
  "properties": {
    "iso:country":"GB",
    "wof:name":"IV27 4RQ",
    "wof:placetype":"postalcode"
},
  "geometry": {"coordinates":[-5.01904590392717,58.45518537347858],"type":"Point"}
}