{
  "type": "Feature",
  "properties": {
    "date:inception_lower": "1999-06-01",
    "date:inception_upper": "1999-06-01",
    "iso:country": "GB",
    "wof:name": "CF3 2UE",
    "wof:placetype": "postalcode"
  },
  "geometry": {"coordinates":[-3.066008,51.529702],"type":"Point"}
}
