{
  "type": "Feature",
  "properties": {
    "iso:country": "GB",
    "wof:name": "CF3 2UE",
    "wof:placetype": "postalcode"
  },
  "geometry": {"coordinates":[-3.066008,51.529702],"type":"Point"}
}
