{
  "type": "Feature",
  "properties": {
    "iso:country":"GB",
    "wof:name":"SO21 1RP",
    "wof:placetype":"postalcode"
},
  "geometry": {"coordinates":[-1.31635867834985,51.00042147757578],"type":"Point"}
}