{
  "type": "Feature",
  "properties": {
    "iso:country": "GB",
    "wof:name": "CT6 6PG",
    "wof:placetype": "postalcode"
  },
  "geometry": {"coordinates":[1.15424,51.370917],"type":"Point"}
}
