{
  "type": "Feature",
  "properties": {
    "iso:country":"GB",
    "wof:name":"CT6 6PG",
    "wof:placetype":"postalcode"
},
  "geometry": {"coordinates":[1.15423975621444,51.37091680393399],"type":"Point"}
}