{
  "type": "Feature",
  "properties": {
    "date:inception_lower": "2000-10-01",
    "date:inception_upper": "2000-10-01",
    "iso:country": "GB",
    "wof:name": "OX49 5AW",
    "wof:placetype": "postalcode"
  },
  "geometry": {"coordinates":[-1.007525,51.656576],"type":"Point"}
}
