{
  "type": "Feature",
  "properties": {
    "iso:country":"GB",
    "wof:name":"DT11 7EN",
    "wof:placetype":"postalcode"
},
  "geometry": {"coordinates":[-2.15836881843587,50.85596171321395],"type":"Point"}
}