{
  "type": "Feature",
  "properties": {
    "iso:country":"GB",
    "wof:name":"MK6 3BU",
    "wof:placetype":"postalcode"
},
  "geometry": {"coordinates":[-0.72072923589196,52.01701317294154],"type":"Point"}
}