{
  "type": "Feature",
  "properties": {
    "iso:country": "GB",
    "wof:name": "IP3 0BF",
    "wof:placetype": "postalcode"
  },
  "geometry": {"coordinates":[1.166238,52.050231],"type":"Point"}
}
