{
  "type": "Feature",
  "properties": {
    "date:inception_lower":"2008-07-01",
    "date:inception_upper":"2008-07-31",
    "iso:country":"GB",
    "wof:name":"IP3 0BF",
    "wof:placetype":"postalcode"
},
  "geometry": {"coordinates":[1.166238,52.050231],"type":"Point"}
}