{
  "type": "Feature",
  "properties": {
    "iso:country":"GB",
    "wof:name":"NE42 6JA",
    "wof:placetype":"postalcode"
},
  "geometry": {"coordinates":[-1.8626091376339,54.9587968044864],"type":"Point"}
}