{
  "type": "Feature",
  "properties": {
    "iso:country":"GB",
    "wof:name":"AB51 8QS",
    "wof:placetype":"postalcode"
},
  "geometry": {"coordinates":[-2.42038898044999,57.40392766788377],"type":"Point"}
}