{
  "type": "Feature",
  "properties": {
    "iso:country": "GB",
    "wof:name": "AB51 8QS",
    "wof:placetype": "postalcode"
  },
  "geometry": {"coordinates":[-2.420389,57.403928],"type":"Point"}
}
