{
  "type": "Feature",
  "properties": {
    "date:inception_lower": "1999-06-01",
    "date:inception_upper": "1999-06-01",
    "iso:country": "GB",
    "wof:name": "CH41 9BJ",
    "wof:placetype": "postalcode"
  },
  "geometry": {"coordinates":[-3.015834,53.381604],"type":"Point"}
}
