{
  "type": "Feature",
  "properties": {
    "iso:country": "GB",
    "wof:name": "NN16 8XE",
    "wof:placetype": "postalcode"
  },
  "geometry": {"coordinates":[-0.747737,52.405692],"type":"Point"}
}
