{
  "type": "Feature",
  "properties": {
    "iso:country":"GB",
    "wof:name":"AB31 4DG",
    "wof:placetype":"postalcode"
},
  "geometry": {"coordinates":[-2.55814883282101,57.07606795440578],"type":"Point"}
}