{
  "type": "Feature",
  "properties": {
    "date:inception_lower": "2012-12-01",
    "date:inception_upper": "2012-12-01",
    "iso:country": "GB",
    "wof:name": "SE20 7NN",
    "wof:placetype": "postalcode"
  },
  "geometry": {"coordinates":[-0.046959,51.415246],"type":"Point"}
}
