{
  "type": "Feature",
  "properties": {
    "iso:country":"GB",
    "wof:name":"B23 5TZ",
    "wof:placetype":"postalcode"
},
  "geometry": {"coordinates":[-1.83457403791126,52.53137724192833],"type":"Point"}
}