{
  "type": "Feature",
  "properties": {
    "iso:country":"GB",
    "wof:name":"CT1 3HJ",
    "wof:placetype":"postalcode"
},
  "geometry": {"coordinates":[1.0844134046754,51.27488921925734],"type":"Point"}
}