{
  "type": "Feature",
  "properties": {
    "iso:country":"GB",
    "wof:name":"EX36 3DQ",
    "wof:placetype":"postalcode"
},
  "geometry": {"coordinates":[-3.82696517969772,51.01822049302793],"type":"Point"}
}