{
  "type": "Feature",
  "properties": {
    "iso:country": "GB",
    "wof:name": "TR2 5HP",
    "wof:placetype": "postalcode"
  },
  "geometry": {"coordinates":[-4.976697,50.178709],"type":"Point"}
}
