{
  "type": "Feature",
  "properties": {
    "date:inception_lower":"1980-01-01",
    "date:inception_upper":"1980-01-31",
    "iso:country":"GB",
    "wof:name":"TR2 5HP",
    "wof:placetype":"postalcode"
},
  "geometry": {"coordinates":[-4.976697,50.178709],"type":"Point"}
}