{
  "type": "Feature",
  "properties": {
    "date:inception_lower": "2004-05-01",
    "date:inception_upper": "2004-05-01",
    "iso:country": "GB",
    "wof:name": "WS13 8FG",
    "wof:placetype": "postalcode"
  },
  "geometry": {"coordinates":[-1.84219,52.676842],"type":"Point"}
}
