{
  "type": "Feature",
  "properties": {
    "date:inception_lower":"1998-06-01",
    "date:inception_upper":"1998-06-30",
    "iso:country":"GB",
    "wof:name":"S64 8DE",
    "wof:placetype":"postalcode"
},
  "geometry": {"coordinates":[-1.321101,53.49109],"type":"Point"}
}