{
  "type": "Feature",
  "properties": {
    "iso:country": "GB",
    "wof:name": "S64 8DE",
    "wof:placetype": "postalcode"
  },
  "geometry": {"coordinates":[-1.321101,53.49109],"type":"Point"}
}
