{
  "type": "Feature",
  "properties": {
    "iso:country":"GB",
    "wof:name":"S64 8DE",
    "wof:placetype":"postalcode"
},
  "geometry": {"coordinates":[-1.32110073653446,53.49109000211133],"type":"Point"}
}