{
  "type": "Feature",
  "properties": {
    "iso:country":"GB",
    "wof:name":"BH31 6UT",
    "wof:placetype":"postalcode"
},
  "geometry": {"coordinates":[-1.87832495587232,50.87739041290811],"type":"Point"}
}