{
  "type": "Feature",
  "properties": {
    "iso:country":"GB",
    "wof:name":"NE23 6DP",
    "wof:placetype":"postalcode"
},
  "geometry": {"coordinates":[-1.58249624641897,55.08262627590877],"type":"Point"}
}