{
  "type": "Feature",
  "properties": {
    "iso:country": "GB",
    "wof:name": "BD19 5HZ",
    "wof:placetype": "postalcode"
  },
  "geometry": {"coordinates":[-1.718872,53.720647],"type":"Point"}
}
