{
  "type": "Feature",
  "properties": {
    "iso:country":"GB",
    "wof:name":"BD19 5HZ",
    "wof:placetype":"postalcode"
},
  "geometry": {"coordinates":[-1.71887242563373,53.72064717873769],"type":"Point"}
}