{
  "type": "Feature",
  "properties": {
    "iso:country": "GB",
    "wof:name": "EH21 6PU",
    "wof:placetype": "postalcode"
  },
  "geometry": {"coordinates":[-3.061828,55.943266],"type":"Point"}
}
