{
  "type": "Feature",
  "properties": {
    "iso:country":"GB",
    "wof:name":"W14 9QR",
    "wof:placetype":"postalcode"
},
  "geometry": {"coordinates":[-0.20433628461124,51.48594391997602],"type":"Point"}
}