{
  "type": "Feature",
  "properties": {
    "iso:country":"GB",
    "wof:name":"S80 2HY",
    "wof:placetype":"postalcode"
},
  "geometry": {"coordinates":[-1.11328028893557,53.30233832024779],"type":"Point"}
}