{
  "type": "Feature",
  "properties": {
    "iso:country": "GB",
    "wof:name": "S80 2HY",
    "wof:placetype": "postalcode"
  },
  "geometry": {"coordinates":[-1.11328,53.302338],"type":"Point"}
}
