{
  "type": "Feature",
  "properties": {
    "iso:country": "GB",
    "wof:name": "BS16 2ES",
    "wof:placetype": "postalcode"
  },
  "geometry": {"coordinates":[-2.533711,51.482386],"type":"Point"}
}
