{
  "type": "Feature",
  "properties": {
    "iso:country":"GB",
    "wof:name":"G71 7PF",
    "wof:placetype":"postalcode"
},
  "geometry": {"coordinates":[-4.08142946518848,55.82054199981736],"type":"Point"}
}