{
  "type": "Feature",
  "properties": {
    "date:inception_lower":"2007-07-01",
    "date:inception_upper":"2007-07-31",
    "iso:country":"GB",
    "wof:name":"CH66 1TY",
    "wof:placetype":"postalcode"
},
  "geometry": {"coordinates":[-2.921095,53.28913],"type":"Point"}
}