{
  "type": "Feature",
  "properties": {
    "iso:country":"GB",
    "wof:name":"S6 1JQ",
    "wof:placetype":"postalcode"
},
  "geometry": {"coordinates":[-1.49758846355349,53.42152729978292],"type":"Point"}
}