{
  "type": "Feature",
  "properties": {
    "date:inception_lower": "1980-01-01",
    "date:inception_upper": "1980-01-01",
    "iso:country": "GB",
    "wof:name": "PE14 0DD",
    "wof:placetype": "postalcode"
  },
  "geometry": {"coordinates":[0.173592,52.646587],"type":"Point"}
}
