{
  "type": "Feature",
  "properties": {
    "iso:country": "GB",
    "wof:name": "PE14 0DD",
    "wof:placetype": "postalcode"
  },
  "geometry": {"coordinates":[0.173592,52.646587],"type":"Point"}
}
