{
  "type": "Feature",
  "properties": {
    "iso:country":"GB",
    "wof:name":"CB24 9PP",
    "wof:placetype":"postalcode"
},
  "geometry": {"coordinates":[0.11125041425817,52.23850781410955],"type":"Point"}
}