{
  "type": "Feature",
  "properties": {
    "iso:country":"GB",
    "wof:name":"PE25 2NQ",
    "wof:placetype":"postalcode"
},
  "geometry": {"coordinates":[0.32643034210593,53.15301602555564],"type":"Point"}
}