{
  "type": "Feature",
  "properties": {
    "date:inception_lower": "1980-01-01",
    "date:inception_upper": "1980-01-01",
    "iso:country": "GB",
    "wof:name": "PE25 2NQ",
    "wof:placetype": "postalcode"
  },
  "geometry": {"coordinates":[0.326418,53.153071],"type":"Point"}
}
