{
  "type": "Feature",
  "properties": {
    "iso:country": "GB",
    "wof:name": "CM11 2UL",
    "wof:placetype": "postalcode"
  },
  "geometry": {"coordinates":[0.461971,51.599647],"type":"Point"}
}
