{
  "type": "Feature",
  "properties": {
    "date:inception_lower": "1980-01-01",
    "date:inception_upper": "1980-01-01",
    "iso:country": "GB",
    "wof:name": "CM11 2UL",
    "wof:placetype": "postalcode"
  },
  "geometry": {"coordinates":[0.461839,51.599605],"type":"Point"}
}
