{
  "type": "Feature",
  "properties": {
    "iso:country":"GB",
    "wof:name":"CM11 2UL",
    "wof:placetype":"postalcode"
},
  "geometry": {"coordinates":[0.46190877055153,51.59955465896515],"type":"Point"}
}