{
  "type": "Feature",
  "properties": {
    "iso:country":"GB",
    "wof:name":"B30 2RY",
    "wof:placetype":"postalcode"
},
  "geometry": {"coordinates":[-1.91371661598565,52.42741139734534],"type":"Point"}
}