{
  "type": "Feature",
  "properties": {
    "date:inception_lower":"1980-01-01",
    "date:inception_upper":"1980-01-31",
    "iso:country":"GB",
    "wof:name":"LE5 1JD",
    "wof:placetype":"postalcode"
},
  "geometry": {"coordinates":[-1.064016,52.647407],"type":"Point"}
}