{
  "type": "Feature",
  "properties": {
    "iso:country":"GB",
    "wof:name":"WA15 0JT",
    "wof:placetype":"postalcode"
},
  "geometry": {"coordinates":[-2.34261576790096,53.36863544172974],"type":"Point"}
}