{
  "type": "Feature",
  "properties": {
    "iso:country":"GB",
    "wof:name":"N11 2NH",
    "wof:placetype":"postalcode"
},
  "geometry": {"coordinates":[-0.13433055117057,51.60806581324683],"type":"Point"}
}