{
  "type": "Feature",
  "properties": {
    "iso:country":"GB",
    "wof:name":"L32 8TA",
    "wof:placetype":"postalcode"
},
  "geometry": {"coordinates":[-2.87604931934585,53.47891879994572],"type":"Point"}
}