{
  "type": "Feature",
  "properties": {
    "iso:country":"GB",
    "wof:name":"LL24 0AF",
    "wof:placetype":"postalcode"
},
  "geometry": {"coordinates":[-3.80293492978928,53.09022638232602],"type":"Point"}
}