{
  "type": "Feature",
  "properties": {
    "date:inception_lower": "2000-12-01",
    "date:inception_upper": "2000-12-01",
    "iso:country": "GB",
    "wof:name": "LL24 0AF",
    "wof:placetype": "postalcode"
  },
  "geometry": {"coordinates":[-3.802935,53.090226],"type":"Point"}
}
