{
  "type": "Feature",
  "properties": {
    "iso:country": "GB",
    "wof:name": "WR10 3LH",
    "wof:placetype": "postalcode"
  },
  "geometry": {"coordinates":[-1.969897,52.107675],"type":"Point"}
}
