{
  "type": "Feature",
  "properties": {
    "iso:country":"GB",
    "wof:name":"KA19 8JN",
    "wof:placetype":"postalcode"
},
  "geometry": {"coordinates":[-4.7405482468945,55.36120220375916],"type":"Point"}
}