{
  "type": "Feature",
  "properties": {
    "iso:country":"GB",
    "wof:name":"SE18 5TL",
    "wof:placetype":"postalcode"
},
  "geometry": {"coordinates":[0.04407572677192,51.49257801206834],"type":"Point"}
}