{
  "type": "Feature",
  "properties": {
    "iso:country": "GB",
    "wof:name": "BA12 8AD",
    "wof:placetype": "postalcode"
  },
  "geometry": {"coordinates":[-2.200847,51.182224],"type":"Point"}
}
