{
  "type": "Feature",
  "properties": {
    "iso:country":"GB",
    "wof:name":"BA12 8AD",
    "wof:placetype":"postalcode"
},
  "geometry": {"coordinates":[-2.20084727350007,51.18222387550772],"type":"Point"}
}