{
  "type": "Feature",
  "properties": {
    "iso:country":"GB",
    "wof:name":"PL31 2GB",
    "wof:placetype":"postalcode"
},
  "geometry": {"coordinates":[-4.70604505423707,50.46556303230624],"type":"Point"}
}