{
  "type": "Feature",
  "properties": {
    "iso:country":"GB",
    "wof:name":"AB10 7HR",
    "wof:placetype":"postalcode"
},
  "geometry": {"coordinates":[-2.12774905202038,57.12365315538679],"type":"Point"}
}