{
  "type": "Feature",
  "properties": {
    "iso:country": "GB",
    "wof:name": "AB10 7HR",
    "wof:placetype": "postalcode"
  },
  "geometry": {"coordinates":[-2.127749,57.123653],"type":"Point"}
}
