{
  "type": "Feature",
  "properties": {
    "date:inception_lower": "1992-08-01",
    "date:inception_upper": "1992-08-01",
    "iso:country": "GB",
    "wof:name": "EC4Y 1BJ",
    "wof:placetype": "postalcode"
  },
  "geometry": {"coordinates":[-0.109195,51.514045],"type":"Point"}
}
