{
  "type": "Feature",
  "properties": {
    "iso:country":"GB",
    "wof:name":"EC4Y 1BJ",
    "wof:placetype":"postalcode"
},
  "geometry": {"coordinates":[-0.10923624085531,51.51400762158657],"type":"Point"}
}