{
  "type": "Feature",
  "properties": {
    "date:inception_lower": "2008-02-01",
    "date:inception_upper": "2008-02-01",
    "iso:country": "GB",
    "wof:name": "TN35 4AF",
    "wof:placetype": "postalcode"
  },
  "geometry": {"coordinates":[0.653235,50.893902],"type":"Point"}
}
