{
  "type": "Feature",
  "properties": {
    "iso:country":"GB",
    "wof:name":"EX8 4LR",
    "wof:placetype":"postalcode"
},
  "geometry": {"coordinates":[-3.38508778486617,50.63708312068191],"type":"Point"}
}