{
  "type": "Feature",
  "properties": {
    "date:inception_lower": "1980-01-01",
    "date:inception_upper": "1980-01-01",
    "iso:country": "GB",
    "wof:name": "PO21 2RE",
    "wof:placetype": "postalcode"
  },
  "geometry": {"coordinates":[-0.69274,50.782284],"type":"Point"}
}
