{
  "type": "Feature",
  "properties": {
    "iso:country":"GB",
    "wof:name":"PO21 2RE",
    "wof:placetype":"postalcode"
},
  "geometry": {"coordinates":[-0.69273962029891,50.78228354816963],"type":"Point"}
}