{
  "type": "Feature",
  "properties": {
    "iso:country":"GB",
    "wof:name":"PO36 9ES",
    "wof:placetype":"postalcode"
},
  "geometry": {"coordinates":[-1.1653429134504,50.65613542175305],"type":"Point"}
}