{
  "type": "Feature",
  "properties": {
    "iso:country":"GB",
    "wof:name":"N22 9GJ",
    "wof:placetype":"postalcode"
},
  "geometry": {"coordinates":[-0.11968718226807,51.59860594381522],"type":"Point"}
}