{
  "type": "Feature",
  "properties": {
    "iso:country":"GB",
    "wof:name":"B96 6HL",
    "wof:placetype":"postalcode"
},
  "geometry": {"coordinates":[-1.95805625940545,52.25640634655297],"type":"Point"}
}