{
  "type": "Feature",
  "properties": {
    "iso:country":"GB",
    "wof:name":"WA2 7DS",
    "wof:placetype":"postalcode"
},
  "geometry": {"coordinates":[-2.59292664588255,53.39714601538088],"type":"Point"}
}