{
  "type": "Feature",
  "properties": {
    "date:inception_lower":"1987-04-01",
    "date:inception_upper":"1987-04-30",
    "iso:country":"GB",
    "wof:name":"WA2 7DS",
    "wof:placetype":"postalcode"
},
  "geometry": {"coordinates":[-2.592927,53.397146],"type":"Point"}
}