{
  "type": "Feature",
  "properties": {
    "iso:country":"GB",
    "wof:name":"TR14 8AA",
    "wof:placetype":"postalcode"
},
  "geometry": {"coordinates":[-5.29826571836225,50.21408957372808],"type":"Point"}
}