{
  "type": "Feature",
  "properties": {
    "iso:country": "GB",
    "wof:name": "SY21 8DF",
    "wof:placetype": "postalcode"
  },
  "geometry": {"coordinates":[-3.03515,52.702493],"type":"Point"}
}
