{
  "type": "Feature",
  "properties": {
    "iso:country":"GB",
    "wof:name":"SY21 8DF",
    "wof:placetype":"postalcode"
},
  "geometry": {"coordinates":[-3.03515237626583,52.70247817501466],"type":"Point"}
}