{
  "type": "Feature",
  "properties": {
    "iso:country": "GB",
    "wof:name": "SO42 7XH",
    "wof:placetype": "postalcode"
  },
  "geometry": {"coordinates":[-1.416733,50.773464],"type":"Point"}
}
