{
  "type": "Feature",
  "properties": {
    "date:inception_lower": "1986-01-01",
    "date:inception_upper": "1986-01-01",
    "iso:country": "GB",
    "wof:name": "SO42 7XH",
    "wof:placetype": "postalcode"
  },
  "geometry": {"coordinates":[-1.416733,50.773464],"type":"Point"}
}
