{
  "type": "Feature",
  "properties": {
    "iso:country":"GB",
    "wof:name":"M40 2SP",
    "wof:placetype":"postalcode"
},
  "geometry": {"coordinates":[-2.19278938561532,53.49712111682464],"type":"Point"}
}