{
  "type": "Feature",
  "properties": {
    "iso:country": "GB",
    "wof:name": "CF14 6SR",
    "wof:placetype": "postalcode"
  },
  "geometry": {"coordinates":[-3.211166,51.531386],"type":"Point"}
}
