{
  "type": "Feature",
  "properties": {
    "iso:country":"GB",
    "wof:name":"CF14 6SR",
    "wof:placetype":"postalcode"
},
  "geometry": {"coordinates":[-3.21116588489867,51.53138572421071],"type":"Point"}
}