{
  "type": "Feature",
  "properties": {
    "iso:country":"GB",
    "wof:name":"DA7 5JQ",
    "wof:placetype":"postalcode"
},
  "geometry": {"coordinates":[0.13198973643921,51.4723882140437],"type":"Point"}
}