{
  "type": "Feature",
  "properties": {
    "iso:country":"GB",
    "wof:name":"PE38 0JU",
    "wof:placetype":"postalcode"
},
  "geometry": {"coordinates":[0.3866654478726,52.55570559709659],"type":"Point"}
}