{
  "type": "Feature",
  "properties": {
    "date:inception_lower": "1986-07-01",
    "date:inception_upper": "1986-07-01",
    "iso:country": "GB",
    "wof:name": "BS16 3HE",
    "wof:placetype": "postalcode"
  },
  "geometry": {"coordinates":[-2.535723,51.477063],"type":"Point"}
}
