{
  "type": "Feature",
  "properties": {
    "iso:country":"GB",
    "wof:name":"BS16 3HE",
    "wof:placetype":"postalcode"
},
  "geometry": {"coordinates":[-2.53572278052844,51.47706263645924],"type":"Point"}
}