{
  "type": "Feature",
  "properties": {
    "iso:country":"GB",
    "wof:name":"SA1 6RU",
    "wof:placetype":"postalcode"
},
  "geometry": {"coordinates":[-3.97160430177006,51.63197188872777],"type":"Point"}
}