{
  "type": "Feature",
  "properties": {
    "iso:country": "GB",
    "wof:name": "PO20 9AW",
    "wof:placetype": "postalcode"
  },
  "geometry": {"coordinates":[-0.796518,50.730342],"type":"Point"}
}
