{
  "type": "Feature",
  "properties": {
    "iso:country":"GB",
    "wof:name":"PO20 9AW",
    "wof:placetype":"postalcode"
},
  "geometry": {"coordinates":[-0.79651760496634,50.73034155868488],"type":"Point"}
}