{
  "type": "Feature",
  "properties": {
    "date:inception_lower":"1980-01-01",
    "date:inception_upper":"1980-01-31",
    "iso:country":"GB",
    "wof:name":"NE61 2ST",
    "wof:placetype":"postalcode"
},
  "geometry": {"coordinates":[-1.686461,55.160802],"type":"Point"}
}