{
  "type": "Feature",
  "properties": {
    "iso:country":"GB",
    "wof:name":"NE61 2ST",
    "wof:placetype":"postalcode"
},
  "geometry": {"coordinates":[-1.68646142525177,55.16080190013176],"type":"Point"}
}