{
  "type": "Feature",
  "properties": {
    "iso:country":"GB",
    "wof:name":"ME10 1YX",
    "wof:placetype":"postalcode"
},
  "geometry": {"coordinates":[0.70245284981162,51.34599729864402],"type":"Point"}
}