{
  "type": "Feature",
  "properties": {
    "date:inception_lower": "1980-01-01",
    "date:inception_upper": "1980-01-01",
    "iso:country": "GB",
    "wof:name": "BL1 7QA",
    "wof:placetype": "postalcode"
  },
  "geometry": {"coordinates":[-2.471437,53.599084],"type":"Point"}
}
