{
  "type": "Feature",
  "properties": {
    "iso:country":"GB",
    "wof:name":"BD20 7LF",
    "wof:placetype":"postalcode"
},
  "geometry": {"coordinates":[-1.98985810253993,53.90104920839039],"type":"Point"}
}