{
  "type": "Feature",
  "properties": {
    "date:inception_lower": "1980-01-01",
    "date:inception_upper": "1980-01-01",
    "iso:country": "GB",
    "wof:name": "BD20 7LF",
    "wof:placetype": "postalcode"
  },
  "geometry": {"coordinates":[-1.99009,53.901216],"type":"Point"}
}
