{
  "type": "Feature",
  "properties": {
    "iso:country":"GB",
    "wof:name":"OX2 8ED",
    "wof:placetype":"postalcode"
},
  "geometry": {"coordinates":[-1.27151320965116,51.78963839726867],"type":"Point"}
}