{
  "type": "Feature",
  "properties": {
    "iso:country":"GB",
    "wof:name":"LS25 4AJ",
    "wof:placetype":"postalcode"
},
  "geometry": {"coordinates":[-1.32882513847259,53.7956146811289],"type":"Point"}
}