{
  "type": "Feature",
  "properties": {
    "iso:country": "GB",
    "wof:name": "EH45 8SP",
    "wof:placetype": "postalcode"
  },
  "geometry": {"coordinates":[-3.190867,55.651857],"type":"Point"}
}
