{
  "type": "Feature",
  "properties": {
    "iso:country":"GB",
    "wof:name":"EH45 8SP",
    "wof:placetype":"postalcode"
},
  "geometry": {"coordinates":[-3.19086654008217,55.65183076397759],"type":"Point"}
}