{
  "type": "Feature",
  "properties": {
    "iso:country": "GB",
    "wof:name": "EH49 6EA",
    "wof:placetype": "postalcode"
  },
  "geometry": {"coordinates":[-3.617263,55.970304],"type":"Point"}
}
