{
  "type": "Feature",
  "properties": {
    "iso:country":"GB",
    "wof:name":"BA11 2BQ",
    "wof:placetype":"postalcode"
},
  "geometry": {"coordinates":[-2.30657937754324,51.23237622320127],"type":"Point"}
}