{
  "type": "Feature",
  "properties": {
    "date:inception_lower": "1980-01-01",
    "date:inception_upper": "1980-01-01",
    "iso:country": "GB",
    "wof:name": "MK41 8BW",
    "wof:placetype": "postalcode"
  },
  "geometry": {"coordinates":[-0.451363,52.154603],"type":"Point"}
}
