{
  "type": "Feature",
  "properties": {
    "date:inception_lower":"1991-09-01",
    "date:inception_upper":"1991-09-30",
    "iso:country":"GB",
    "wof:name":"TR5 0PD",
    "wof:placetype":"postalcode"
},
  "geometry": {"coordinates":[-5.200722,50.298163],"type":"Point"}
}