{
  "type": "Feature",
  "properties": {
    "iso:country":"GB",
    "wof:name":"NE63 0XE",
    "wof:placetype":"postalcode"
},
  "geometry": {"coordinates":[-1.54682029082091,55.17059820501992],"type":"Point"}
}