{
  "type": "Feature",
  "properties": {
    "iso:country":"GB",
    "wof:name":"LE7 9NB",
    "wof:placetype":"postalcode"
},
  "geometry": {"coordinates":[-1.03427064860282,52.63224517280991],"type":"Point"}
}