{
  "type": "Feature",
  "properties": {
    "date:inception_lower": "1998-06-01",
    "date:inception_upper": "1998-06-01",
    "iso:country": "GB",
    "wof:name": "LE7 9NB",
    "wof:placetype": "postalcode"
  },
  "geometry": {"coordinates":[-1.034271,52.632245],"type":"Point"}
}
