{
  "type": "Feature",
  "properties": {
    "iso:country":"GB",
    "wof:name":"PE31 8TD",
    "wof:placetype":"postalcode"
},
  "geometry": {"coordinates":[0.69674688979031,52.8127979288493],"type":"Point"}
}