{
  "type": "Feature",
  "properties": {
    "iso:country":"GB",
    "wof:name":"LE16 9AR",
    "wof:placetype":"postalcode"
},
  "geometry": {"coordinates":[-0.93139479923556,52.47890552540041],"type":"Point"}
}