{
  "type": "Feature",
  "properties": {
    "iso:country":"GB",
    "wof:name":"PO6 2JP",
    "wof:placetype":"postalcode"
},
  "geometry": {"coordinates":[-1.0584605452412,50.8471389233365],"type":"Point"}
}