{
  "type": "Feature",
  "properties": {
    "date:inception_lower":"1994-05-01",
    "date:inception_upper":"1994-05-31",
    "iso:country":"GB",
    "wof:name":"DL3 6RS",
    "wof:placetype":"postalcode"
},
  "geometry": {"coordinates":[-1.567166,54.530099],"type":"Point"}
}