{
  "type": "Feature",
  "properties": {
    "iso:country":"GB",
    "wof:name":"S36 8HQ",
    "wof:placetype":"postalcode"
},
  "geometry": {"coordinates":[-1.62712003952598,53.53126579390484],"type":"Point"}
}