{
  "type": "Feature",
  "properties": {
    "iso:country": "GB",
    "wof:name": "S36 8HQ",
    "wof:placetype": "postalcode"
  },
  "geometry": {"coordinates":[-1.62712,53.531266],"type":"Point"}
}
