{
  "type": "Feature",
  "properties": {
    "date:inception_lower": "2016-09-01",
    "date:inception_upper": "2016-09-01",
    "iso:country": "GB",
    "wof:name": "S45 8JG",
    "wof:placetype": "postalcode"
  },
  "geometry": {"coordinates":[-1.374169,53.158462],"type":"Point"}
}
