{
  "type": "Feature",
  "properties": {
    "iso:country":"GB",
    "wof:name":"SW15 1JX",
    "wof:placetype":"postalcode"
},
  "geometry": {"coordinates":[-0.22024010209133,51.46848919637338],"type":"Point"}
}