{
  "type": "Feature",
  "properties": {
    "iso:country": "GB",
    "wof:name": "TN10 4NA",
    "wof:placetype": "postalcode"
  },
  "geometry": {"coordinates":[0.295155,51.208862],"type":"Point"}
}
