{
  "type": "Feature",
  "properties": {
    "iso:country":"GB",
    "wof:name":"TN10 4NA",
    "wof:placetype":"postalcode"
},
  "geometry": {"coordinates":[0.29515493992908,51.20886152892859],"type":"Point"}
}