{
  "type": "Feature",
  "properties": {
    "iso:country":"GB",
    "wof:name":"S70 1AH",
    "wof:placetype":"postalcode"
},
  "geometry": {"coordinates":[-1.48363327671936,53.55115435667147],"type":"Point"}
}