{
  "type": "Feature",
  "properties": {
    "date:inception_lower": "2006-02-01",
    "date:inception_upper": "2006-02-01",
    "iso:country": "GB",
    "wof:name": "NE1 4BE",
    "wof:placetype": "postalcode"
  },
  "geometry": {"coordinates":[-1.621547,54.966374],"type":"Point"}
}
