{
  "type": "Feature",
  "properties": {
    "iso:country":"GB",
    "wof:name":"NE1 4BE",
    "wof:placetype":"postalcode"
},
  "geometry": {"coordinates":[-1.62154753012992,54.96637370943365],"type":"Point"}
}