{
  "type": "Feature",
  "properties": {
    "iso:country":"GB",
    "wof:name":"TW8 9NY",
    "wof:placetype":"postalcode"
},
  "geometry": {"coordinates":[-0.30845748924178,51.49177239638044],"type":"Point"}
}