{
  "type": "Feature",
  "properties": {
    "iso:country":"GB",
    "wof:name":"TD6 0PU",
    "wof:placetype":"postalcode"
},
  "geometry": {"coordinates":[-2.67656064880778,55.57600775344071],"type":"Point"}
}