{
  "type": "Feature",
  "properties": {
    "date:inception_lower":"1999-12-01",
    "date:inception_upper":"1999-12-31",
    "iso:country":"GB",
    "wof:name":"IP22 4AQ",
    "wof:placetype":"postalcode"
},
  "geometry": {"coordinates":[1.099353,52.375179],"type":"Point"}
}