{
  "type": "Feature",
  "properties": {
    "iso:country": "GB",
    "wof:name": "WF4 2BB",
    "wof:placetype": "postalcode"
  },
  "geometry": {"coordinates":[-1.41325,53.622207],"type":"Point"}
}
