{
  "type": "Feature",
  "properties": {
    "iso:country":"GB",
    "wof:name":"WF4 2BB",
    "wof:placetype":"postalcode"
},
  "geometry": {"coordinates":[-1.41325050233616,53.6222069299513],"type":"Point"}
}