{
  "type": "Feature",
  "properties": {
    "iso:country": "GB",
    "wof:name": "SN14 8DN",
    "wof:placetype": "postalcode"
  },
  "geometry": {"coordinates":[-2.260737,51.437778],"type":"Point"}
}
