{
  "type": "Feature",
  "properties": {
    "iso:country":"GB",
    "wof:name":"LL19 8HE",
    "wof:placetype":"postalcode"
},
  "geometry": {"coordinates":[-3.41309977419556,53.32394809654586],"type":"Point"}
}