{
  "type": "Feature",
  "properties": {
    "iso:country":"GB",
    "wof:name":"OL12 7PZ",
    "wof:placetype":"postalcode"
},
  "geometry": {"coordinates":[-2.19448351134067,53.62658623177345],"type":"Point"}
}