{
  "type": "Feature",
  "properties": {
    "iso:country":"GB",
    "wof:name":"TS19 9LG",
    "wof:placetype":"postalcode"
},
  "geometry": {"coordinates":[-1.34382991012276,54.59096963985395],"type":"Point"}
}