{
  "type": "Feature",
  "properties": {
    "date:inception_lower":"1980-01-01",
    "date:inception_upper":"1980-01-31",
    "iso:country":"GB",
    "wof:name":"TS19 9LG",
    "wof:placetype":"postalcode"
},
  "geometry": {"coordinates":[-1.34383,54.59097],"type":"Point"}
}