{
  "type": "Feature",
  "properties": {
    "date:inception_lower": "1980-01-01",
    "date:inception_upper": "1980-01-01",
    "iso:country": "GB",
    "wof:name": "CF37 5LH",
    "wof:placetype": "postalcode"
  },
  "geometry": {"coordinates":[-3.312374,51.581551],"type":"Point"}
}
