{
  "type": "Feature",
  "properties": {
    "iso:country":"GB",
    "wof:name":"CF37 5LH",
    "wof:placetype":"postalcode"
},
  "geometry": {"coordinates":[-3.31237390426244,51.5815508157883],"type":"Point"}
}