{
  "type": "Feature",
  "properties": {
    "iso:country":"GB",
    "wof:name":"B36 0SR",
    "wof:placetype":"postalcode"
},
  "geometry": {"coordinates":[-1.75428604353084,52.50616510467358],"type":"Point"}
}