{
  "type": "Feature",
  "properties": {
    "iso:country":"GB",
    "wof:name":"CV31 1TL",
    "wof:placetype":"postalcode"
},
  "geometry": {"coordinates":[-1.50109819887124,52.27558909823273],"type":"Point"}
}