{
  "type": "Feature",
  "properties": {
    "iso:country":"GB",
    "wof:name":"WS15 3ED",
    "wof:placetype":"postalcode"
},
  "geometry": {"coordinates":[-1.88616537034701,52.81776780544595],"type":"Point"}
}