{
  "type": "Feature",
  "properties": {
    "iso:country": "GB",
    "wof:name": "WS15 3ED",
    "wof:placetype": "postalcode"
  },
  "geometry": {"coordinates":[-1.886165,52.817768],"type":"Point"}
}
