{
  "type": "Feature",
  "properties": {
    "date:inception_lower":"1980-01-01",
    "date:inception_upper":"1980-01-31",
    "iso:country":"GB",
    "wof:name":"WS15 3ED",
    "wof:placetype":"postalcode"
},
  "geometry": {"coordinates":[-1.886165,52.817768],"type":"Point"}
}