{
  "type": "Feature",
  "properties": {
    "iso:country":"GB",
    "wof:name":"KA6 6LJ",
    "wof:placetype":"postalcode"
},
  "geometry": {"coordinates":[-4.51762650480645,55.44643923999673],"type":"Point"}
}