{
  "type": "Feature",
  "properties": {
    "iso:country":"GB",
    "wof:name":"DL12 0HA",
    "wof:placetype":"postalcode"
},
  "geometry": {"coordinates":[-2.20691875198011,54.66440023887505],"type":"Point"}
}