{
  "type": "Feature",
  "properties": {
    "iso:country":"GB",
    "wof:name":"L11 3BY",
    "wof:placetype":"postalcode"
},
  "geometry": {"coordinates":[-2.92419110578141,53.44767056837561],"type":"Point"}
}