{
  "type": "Feature",
  "properties": {
    "iso:country": "GB",
    "wof:name": "L11 3BY",
    "wof:placetype": "postalcode"
  },
  "geometry": {"coordinates":[-2.924191,53.447671],"type":"Point"}
}
