{
  "type": "Feature",
  "properties": {
    "iso:country":"GB",
    "wof:name":"PR4 1RS",
    "wof:placetype":"postalcode"
},
  "geometry": {"coordinates":[-2.87616137843544,53.75220558845311],"type":"Point"}
}