{
  "type": "Feature",
  "properties": {
    "iso:country":"GB",
    "wof:name":"HU8 7HX",
    "wof:placetype":"postalcode"
},
  "geometry": {"coordinates":[-0.32636160257151,53.75061348243608],"type":"Point"}
}