{
  "type": "Feature",
  "properties": {
    "date:inception_lower":"2015-04-01",
    "date:inception_upper":"2015-04-30",
    "iso:country":"GB",
    "wof:name":"DY9 0WS",
    "wof:placetype":"postalcode"
},
  "geometry": {"coordinates":[-2.133939,52.421555],"type":"Point"}
}