{
  "type": "Feature",
  "properties": {
    "iso:country": "GB",
    "wof:name": "DY9 0WS",
    "wof:placetype": "postalcode"
  },
  "geometry": {"coordinates":[-2.133939,52.421555],"type":"Point"}
}
