{
  "type": "Feature",
  "properties": {
    "iso:country":"GB",
    "wof:name":"NN2 8HW",
    "wof:placetype":"postalcode"
},
  "geometry": {"coordinates":[-0.91179979770869,52.26537258371567],"type":"Point"}
}