{
  "type": "Feature",
  "properties": {
    "date:inception_lower":"1980-01-01",
    "date:inception_upper":"1980-01-31",
    "iso:country":"GB",
    "wof:name":"NN2 8HW",
    "wof:placetype":"postalcode"
},
  "geometry": {"coordinates":[-0.9118,52.265373],"type":"Point"}
}