{
  "type": "Feature",
  "properties": {
    "iso:country":"GB",
    "wof:name":"NW3 5AG",
    "wof:placetype":"postalcode"
},
  "geometry": {"coordinates":[-0.16956736616351,51.55027800958163],"type":"Point"}
}