{
  "type": "Feature",
  "properties": {
    "date:inception_lower": "1980-01-01",
    "date:inception_upper": "1980-01-01",
    "iso:country": "GB",
    "wof:name": "NW3 5AG",
    "wof:placetype": "postalcode"
  },
  "geometry": {"coordinates":[-0.169567,51.550278],"type":"Point"}
}
