{
  "type": "Feature",
  "properties": {
    "iso:country":"GB",
    "wof:name":"KA24 4HT",
    "wof:placetype":"postalcode"
},
  "geometry": {"coordinates":[-4.68516017593694,55.7173142572994],"type":"Point"}
}