{
  "type": "Feature",
  "properties": {
    "iso:country":"GB",
    "wof:name":"CH4 0PA",
    "wof:placetype":"postalcode"
},
  "geometry": {"coordinates":[-2.99109766742269,53.16098451419433],"type":"Point"}
}