{
  "type": "Feature",
  "properties": {
    "date:inception_lower": "1983-03-01",
    "date:inception_upper": "1983-03-01",
    "iso:country": "GB",
    "wof:name": "CH4 0PA",
    "wof:placetype": "postalcode"
  },
  "geometry": {"coordinates":[-2.991098,53.160985],"type":"Point"}
}
