{
  "type": "Feature",
  "properties": {
    "date:inception_lower": "1998-06-01",
    "date:inception_upper": "1998-06-01",
    "iso:country": "GB",
    "wof:name": "YO32 5TU",
    "wof:placetype": "postalcode"
  },
  "geometry": {"coordinates":[-1.041666,54.078784],"type":"Point"}
}
