{
  "type": "Feature",
  "properties": {
    "iso:country": "GB",
    "wof:name": "YO32 5TU",
    "wof:placetype": "postalcode"
  },
  "geometry": {"coordinates":[-1.044223,54.074123],"type":"Point"}
}
