{
  "type": "Feature",
  "properties": {
    "iso:country":"GB",
    "wof:name":"YO32 5TU",
    "wof:placetype":"postalcode"
},
  "geometry": {"coordinates":[-1.04422344438784,54.07412346857496],"type":"Point"}
}