{
  "type": "Feature",
  "properties": {
    "iso:country":"GB",
    "wof:name":"SP1 3LB",
    "wof:placetype":"postalcode"
},
  "geometry": {"coordinates":[-1.80756558225975,51.08572734015015],"type":"Point"}
}