{
  "type": "Feature",
  "properties": {
    "iso:country":"GB",
    "wof:name":"SM6 0SW",
    "wof:placetype":"postalcode"
},
  "geometry": {"coordinates":[-0.15327623842446,51.34106199953919],"type":"Point"}
}