{
  "type": "Feature",
  "properties": {
    "iso:country": "GB",
    "wof:name": "SM6 0SW",
    "wof:placetype": "postalcode"
  },
  "geometry": {"coordinates":[-0.153276,51.341062],"type":"Point"}
}
