{
  "type": "Feature",
  "properties": {
    "iso:country":"GB",
    "wof:name":"G66 3HS",
    "wof:placetype":"postalcode"
},
  "geometry": {"coordinates":[-4.13533426150044,55.93400630631235],"type":"Point"}
}