{
  "type": "Feature",
  "properties": {
    "iso:country":"GB",
    "wof:name":"TR13 8BY",
    "wof:placetype":"postalcode"
},
  "geometry": {"coordinates":[-5.26440722524675,50.09574878265251],"type":"Point"}
}