{
  "type": "Feature",
  "properties": {
    "iso:country": "GB",
    "wof:name": "TR13 8BY",
    "wof:placetype": "postalcode"
  },
  "geometry": {"coordinates":[-5.26454,50.095699],"type":"Point"}
}
