{
  "type": "Feature",
  "properties": {
    "iso:country": "GB",
    "wof:name": "SE1 9JR",
    "wof:placetype": "postalcode"
  },
  "geometry": {"coordinates":[-0.101933,51.507676],"type":"Point"}
}
