{
  "type": "Feature",
  "properties": {
    "iso:country":"GB",
    "wof:name":"SN14 6AU",
    "wof:placetype":"postalcode"
},
  "geometry": {"coordinates":[-2.17871778381197,51.53684712858956],"type":"Point"}
}