{
  "type": "Feature",
  "properties": {
    "date:inception_lower":"1980-01-01",
    "date:inception_upper":"1980-01-31",
    "iso:country":"GB",
    "wof:name":"SN14 6AU",
    "wof:placetype":"postalcode"
},
  "geometry": {"coordinates":[-2.178713,51.536847],"type":"Point"}
}