{
  "type": "Feature",
  "properties": {
    "date:inception_lower":"1998-12-01",
    "date:inception_upper":"1998-12-31",
    "iso:country":"GB",
    "wof:name":"KY13 8YZ",
    "wof:placetype":"postalcode"
},
  "geometry": {"coordinates":[-3.431644,56.210566],"type":"Point"}
}