{
  "type": "Feature",
  "properties": {
    "iso:country": "GB",
    "wof:name": "KY13 8YZ",
    "wof:placetype": "postalcode"
  },
  "geometry": {"coordinates":[-3.431644,56.210566],"type":"Point"}
}
