{
  "type": "Feature",
  "properties": {
    "iso:country":"GB",
    "wof:name":"NE49 0NA",
    "wof:placetype":"postalcode"
},
  "geometry": {"coordinates":[-2.40325347700477,54.9690960453438],"type":"Point"}
}