{
  "type": "Feature",
  "properties": {
    "iso:country": "GB",
    "wof:name": "NE49 0NA",
    "wof:placetype": "postalcode"
  },
  "geometry": {"coordinates":[-2.403261,54.969102],"type":"Point"}
}
