{
  "type": "Feature",
  "properties": {
    "date:inception_lower": "1980-01-01",
    "date:inception_upper": "1980-01-01",
    "iso:country": "GB",
    "wof:name": "LL13 0HP",
    "wof:placetype": "postalcode"
  },
  "geometry": {"coordinates":[-2.916488,52.978001],"type":"Point"}
}
