{
  "type": "Feature",
  "properties": {
    "iso:country": "GB",
    "wof:name": "LL13 0HP",
    "wof:placetype": "postalcode"
  },
  "geometry": {"coordinates":[-2.916488,52.978001],"type":"Point"}
}
