{
  "type": "Feature",
  "properties": {
    "iso:country":"GB",
    "wof:name":"ST7 1NJ",
    "wof:placetype":"postalcode"
},
  "geometry": {"coordinates":[-2.26004274580848,53.08870677037353],"type":"Point"}
}