{
  "type": "Feature",
  "properties": {
    "iso:country":"GB",
    "wof:name":"BL1 5FQ",
    "wof:placetype":"postalcode"
},
  "geometry": {"coordinates":[-2.47115595762481,53.58195329561747],"type":"Point"}
}