{
  "type": "Feature",
  "properties": {
    "date:inception_lower":"1995-01-01",
    "date:inception_upper":"1995-01-31",
    "iso:country":"GB",
    "wof:name":"SN11 0SB",
    "wof:placetype":"postalcode"
},
  "geometry": {"coordinates":[-2.009704,51.433788],"type":"Point"}
}