{
  "type": "Feature",
  "properties": {
    "iso:country":"GB",
    "wof:name":"SN11 0SB",
    "wof:placetype":"postalcode"
},
  "geometry": {"coordinates":[-2.00970437819068,51.43378792572788],"type":"Point"}
}