{
  "type": "Feature",
  "properties": {
    "iso:country":"GB",
    "wof:name":"SW19 4HE",
    "wof:placetype":"postalcode"
},
  "geometry": {"coordinates":[-0.21495870579886,51.4167558659109],"type":"Point"}
}