{
  "type": "Feature",
  "properties": {
    "iso:country":"GB",
    "wof:name":"CR5 1DA",
    "wof:placetype":"postalcode"
},
  "geometry": {"coordinates":[-0.13392321171183,51.29823738784829],"type":"Point"}
}