{
  "type": "Feature",
  "properties": {
    "iso:country": "GB",
    "wof:name": "LE12 9FT",
    "wof:placetype": "postalcode"
  },
  "geometry": {"coordinates":[-1.307699,52.767927],"type":"Point"}
}
