{
  "type": "Feature",
  "properties": {
    "date:inception_lower": "1980-01-01",
    "date:inception_upper": "1980-01-01",
    "iso:country": "GB",
    "wof:name": "HD6 2DE",
    "wof:placetype": "postalcode"
  },
  "geometry": {"coordinates":[-1.787943,53.703188],"type":"Point"}
}
