{
  "type": "Feature",
  "properties": {
    "iso:country":"GB",
    "wof:name":"HD6 2DE",
    "wof:placetype":"postalcode"
},
  "geometry": {"coordinates":[-1.78794099864088,53.70317247743687],"type":"Point"}
}