{
  "type": "Feature",
  "properties": {
    "date:inception_lower": "2024-08-01",
    "date:inception_upper": "2024-08-01",
    "iso:country": "GB",
    "wof:name": "SA4 9HQ",
    "wof:placetype": "postalcode"
  },
  "geometry": {"coordinates":[-4.017281,51.705048],"type":"Point"}
}
