{
  "type": "Feature",
  "properties": {
    "date:inception_lower":"1980-01-01",
    "date:inception_upper":"1980-01-31",
    "iso:country":"GB",
    "wof:name":"SN9 6LG",
    "wof:placetype":"postalcode"
},
  "geometry": {"coordinates":[-1.846684,51.32783],"type":"Point"}
}