{
  "type": "Feature",
  "properties": {
    "iso:country":"GB",
    "wof:name":"SN9 6LG",
    "wof:placetype":"postalcode"
},
  "geometry": {"coordinates":[-1.84668405727889,51.32782969385929],"type":"Point"}
}