{
  "type": "Feature",
  "properties": {
    "iso:country": "GB",
    "wof:name": "SN9 6LG",
    "wof:placetype": "postalcode"
  },
  "geometry": {"coordinates":[-1.846684,51.32783],"type":"Point"}
}
