{
  "type": "Feature",
  "properties": {
    "iso:country": "GB",
    "wof:name": "BS3 1XA",
    "wof:placetype": "postalcode"
  },
  "geometry": {"coordinates":[-2.599271,51.442326],"type":"Point"}
}
