{
  "type": "Feature",
  "properties": {
    "iso:country":"GB",
    "wof:name":"CH49 6LL",
    "wof:placetype":"postalcode"
},
  "geometry": {"coordinates":[-3.09925248813794,53.38664439047189],"type":"Point"}
}