{
  "type": "Feature",
  "properties": {
    "iso:country":"GB",
    "wof:name":"CM23 4EL",
    "wof:placetype":"postalcode"
},
  "geometry": {"coordinates":[0.14728894123286,51.85722868711723],"type":"Point"}
}