{
  "type": "Feature",
  "properties": {
    "iso:country": "GB",
    "wof:name": "WN8 8QP",
    "wof:placetype": "postalcode"
  },
  "geometry": {"coordinates":[-2.792199,53.55349],"type":"Point"}
}
