{
  "type": "Feature",
  "properties": {
    "iso:country":"GB",
    "wof:name":"DT3 4AX",
    "wof:placetype":"postalcode"
},
  "geometry": {"coordinates":[-2.50138419397128,50.62158562313786],"type":"Point"}
}