{
  "type": "Feature",
  "properties": {
    "iso:country":"GB",
    "wof:name":"OX12 9XW",
    "wof:placetype":"postalcode"
},
  "geometry": {"coordinates":[-1.4286987582934,51.59818364635203],"type":"Point"}
}