{
  "type": "Feature",
  "properties": {
    "date:inception_lower": "1998-06-01",
    "date:inception_upper": "1998-06-01",
    "iso:country": "GB",
    "wof:name": "OX12 9XW",
    "wof:placetype": "postalcode"
  },
  "geometry": {"coordinates":[-1.428699,51.598184],"type":"Point"}
}
