{
  "type": "Feature",
  "properties": {
    "iso:country": "GB",
    "wof:name": "AB21 9PB",
    "wof:placetype": "postalcode"
  },
  "geometry": {"coordinates":[-2.16842,57.178818],"type":"Point"}
}
