{
  "type": "Feature",
  "properties": {
    "iso:country":"GB",
    "wof:name":"AB21 9PB",
    "wof:placetype":"postalcode"
},
  "geometry": {"coordinates":[-2.16864416365146,57.17848201789728],"type":"Point"}
}