{
  "type": "Feature",
  "properties": {
    "iso:country":"GB",
    "wof:name":"E18 2ER",
    "wof:placetype":"postalcode"
},
  "geometry": {"coordinates":[0.02098123377775,51.58432581687042],"type":"Point"}
}