{
  "type": "Feature",
  "properties": {
    "iso:country":"GB",
    "wof:name":"ML5 2HA",
    "wof:placetype":"postalcode"
},
  "geometry": {"coordinates":[-4.03974557087649,55.86864706164919],"type":"Point"}
}