{
  "type": "Feature",
  "properties": {
    "date:inception_lower": "1990-07-01",
    "date:inception_upper": "1990-07-01",
    "iso:country": "GB",
    "wof:name": "CR8 2LN",
    "wof:placetype": "postalcode"
  },
  "geometry": {"coordinates":[-0.115677,51.339555],"type":"Point"}
}
