{
  "type": "Feature",
  "properties": {
    "iso:country":"GB",
    "wof:name":"CR8 2LN",
    "wof:placetype":"postalcode"
},
  "geometry": {"coordinates":[-0.11567717343845,51.33955486471756],"type":"Point"}
}