{
  "type": "Feature",
  "properties": {
    "date:inception_lower":"1980-01-01",
    "date:inception_upper":"1980-01-31",
    "iso:country":"GB",
    "wof:name":"BA3 3QT",
    "wof:placetype":"postalcode"
},
  "geometry": {"coordinates":[-2.444989,51.288419],"type":"Point"}
}