{
  "type": "Feature",
  "properties": {
    "iso:country":"GB",
    "wof:name":"BA3 3QT",
    "wof:placetype":"postalcode"
},
  "geometry": {"coordinates":[-2.44498881074594,51.28841861312141],"type":"Point"}
}