{
  "type": "Feature",
  "properties": {
    "iso:country":"GB",
    "wof:name":"PE20 1ED",
    "wof:placetype":"postalcode"
},
  "geometry": {"coordinates":[-0.05772341579194,52.92896249856371],"type":"Point"}
}