{
  "type": "Feature",
  "properties": {
    "iso:country": "GB",
    "wof:name": "CF83 2JN",
    "wof:placetype": "postalcode"
  },
  "geometry": {"coordinates":[-3.239886,51.589793],"type":"Point"}
}
