{
  "type": "Feature",
  "properties": {
    "iso:country":"GB",
    "wof:name":"CF83 2JN",
    "wof:placetype":"postalcode"
},
  "geometry": {"coordinates":[-3.23988617835334,51.58979339502778],"type":"Point"}
}