{
  "type": "Feature",
  "properties": {
    "iso:country": "GB",
    "wof:name": "SO40 8TE",
    "wof:placetype": "postalcode"
  },
  "geometry": {"coordinates":[-1.512123,50.917675],"type":"Point"}
}
