{
  "type": "Feature",
  "properties": {
    "iso:country":"GB",
    "wof:name":"FY4 2DH",
    "wof:placetype":"postalcode"
},
  "geometry": {"coordinates":[-3.04485677620197,53.79149912558153],"type":"Point"}
}