{
  "type": "Feature",
  "properties": {
    "iso:country": "GB",
    "wof:name": "ML7 4AA",
    "wof:placetype": "postalcode"
  },
  "geometry": {"coordinates":[-3.808245,55.820528],"type":"Point"}
}
