{
  "type": "Feature",
  "properties": {
    "iso:country":"GB",
    "wof:name":"NN13 7EE",
    "wof:placetype":"postalcode"
},
  "geometry": {"coordinates":[-1.14117124141122,52.02900036013948],"type":"Point"}
}