{
  "type": "Feature",
  "properties": {
    "iso:country": "GB",
    "wof:name": "NN13 7EE",
    "wof:placetype": "postalcode"
  },
  "geometry": {"coordinates":[-1.141171,52.029],"type":"Point"}
}
