{
  "type": "Feature",
  "properties": {
    "iso:country":"GB",
    "wof:name":"CR4 3BU",
    "wof:placetype":"postalcode"
},
  "geometry": {"coordinates":[-0.1720164519566,51.40266797750546],"type":"Point"}
}