{
  "type": "Feature",
  "properties": {
    "iso:country": "GB",
    "wof:name": "LE19 1LW",
    "wof:placetype": "postalcode"
  },
  "geometry": {"coordinates":[-1.191301,52.615306],"type":"Point"}
}
