{
  "type": "Feature",
  "properties": {
    "iso:country":"GB",
    "wof:name":"BH11 8BT",
    "wof:placetype":"postalcode"
},
  "geometry": {"coordinates":[-1.90558570643092,50.75759022186153],"type":"Point"}
}