{
  "type": "Feature",
  "properties": {
    "iso:country": "GB",
    "wof:name": "BH11 8BT",
    "wof:placetype": "postalcode"
  },
  "geometry": {"coordinates":[-1.905586,50.75759],"type":"Point"}
}
