{
  "type": "Feature",
  "properties": {
    "iso:country":"GB",
    "wof:name":"IG11 9HZ",
    "wof:placetype":"postalcode"
},
  "geometry": {"coordinates":[0.10059061703136,51.54176799089213],"type":"Point"}
}