{
  "type": "Feature",
  "properties": {
    "date:inception_lower": "1997-12-01",
    "date:inception_upper": "1997-12-01",
    "iso:country": "GB",
    "wof:name": "WN7 3LF",
    "wof:placetype": "postalcode"
  },
  "geometry": {"coordinates":[-2.522301,53.486481],"type":"Point"}
}
