{
  "type": "Feature",
  "properties": {
    "iso:country": "GB",
    "wof:name": "KA11 5DP",
    "wof:placetype": "postalcode"
  },
  "geometry": {"coordinates":[-4.641711,55.601575],"type":"Point"}
}
