{
  "type": "Feature",
  "properties": {
    "iso:country":"GB",
    "wof:name":"KA11 5DP",
    "wof:placetype":"postalcode"
},
  "geometry": {"coordinates":[-4.64171081477877,55.60157540827174],"type":"Point"}
}