{
  "type": "Feature",
  "properties": {
    "date:inception_lower":"2001-12-01",
    "date:inception_upper":"2001-12-31",
    "iso:country":"GB",
    "wof:name":"KA11 5DP",
    "wof:placetype":"postalcode"
},
  "geometry": {"coordinates":[-4.641711,55.601575],"type":"Point"}
}