{
  "type": "Feature",
  "properties": {
    "iso:country":"GB",
    "wof:name":"SA18 1HG",
    "wof:placetype":"postalcode"
},
  "geometry": {"coordinates":[-3.88186917135023,51.79020706170186],"type":"Point"}
}