{
  "type": "Feature",
  "properties": {
    "date:inception_lower":"1980-01-01",
    "date:inception_upper":"1980-01-31",
    "iso:country":"GB",
    "wof:name":"SA18 1HG",
    "wof:placetype":"postalcode"
},
  "geometry": {"coordinates":[-3.881665,51.790469],"type":"Point"}
}