{
  "type": "Feature",
  "properties": {
    "iso:country":"GB",
    "wof:name":"RH17 6PP",
    "wof:placetype":"postalcode"
},
  "geometry": {"coordinates":[-0.15651064200865,51.06559692370111],"type":"Point"}
}