{
  "type": "Feature",
  "properties": {
    "iso:country":"GB",
    "wof:name":"BN27 1LY",
    "wof:placetype":"postalcode"
},
  "geometry": {"coordinates":[0.25104297925199,50.8772336367782],"type":"Point"}
}