{
  "type": "Feature",
  "properties": {
    "iso:country":"GB",
    "wof:name":"TN35 5PJ",
    "wof:placetype":"postalcode"
},
  "geometry": {"coordinates":[0.6040817844294,50.86731574435534],"type":"Point"}
}