{
  "type": "Feature",
  "properties": {
    "date:inception_lower": "1980-01-01",
    "date:inception_upper": "1980-01-01",
    "iso:country": "GB",
    "wof:name": "DA15 9HB",
    "wof:placetype": "postalcode"
  },
  "geometry": {"coordinates":[0.104253,51.446342],"type":"Point"}
}
