{
  "type": "Feature",
  "properties": {
    "iso:country":"GB",
    "wof:name":"DA15 9HB",
    "wof:placetype":"postalcode"
},
  "geometry": {"coordinates":[0.10425277098899,51.4463423718432],"type":"Point"}
}