{
  "type": "Feature",
  "properties": {
    "date:inception_lower": "1981-09-01",
    "date:inception_upper": "1981-09-01",
    "iso:country": "GB",
    "wof:name": "SY3 7TD",
    "wof:placetype": "postalcode"
  },
  "geometry": {"coordinates":[-2.742256,52.693599],"type":"Point"}
}
