{
  "type": "Feature",
  "properties": {
    "iso:country":"GB",
    "wof:name":"SY3 7TD",
    "wof:placetype":"postalcode"
},
  "geometry": {"coordinates":[-2.74225605705804,52.69359885001629],"type":"Point"}
}