{
  "type": "Feature",
  "properties": {
    "iso:country":"GB",
    "wof:name":"DD8 3DZ",
    "wof:placetype":"postalcode"
},
  "geometry": {"coordinates":[-2.87055467347063,56.65271114026568],"type":"Point"}
}