{
  "type": "Feature",
  "properties": {
    "iso:country":"GB",
    "wof:name":"CF32 7SW",
    "wof:placetype":"postalcode"
},
  "geometry": {"coordinates":[-3.53535607907646,51.61730382206041],"type":"Point"}
}