{
  "type": "Feature",
  "properties": {
    "date:inception_lower": "1980-01-01",
    "date:inception_upper": "1980-01-01",
    "iso:country": "GB",
    "wof:name": "CF32 7SW",
    "wof:placetype": "postalcode"
  },
  "geometry": {"coordinates":[-3.535369,51.617312],"type":"Point"}
}
