{
  "type": "Feature",
  "properties": {
    "iso:country":"GB",
    "wof:name":"B77 2RY",
    "wof:placetype":"postalcode"
},
  "geometry": {"coordinates":[-1.67569632174769,52.62488495163856],"type":"Point"}
}