{
  "type": "Feature",
  "properties": {
    "date:inception_lower":"2013-08-01",
    "date:inception_upper":"2013-08-31",
    "iso:country":"GB",
    "wof:name":"WR7 4GA",
    "wof:placetype":"postalcode"
},
  "geometry": {"coordinates":[-1.978518,52.219385],"type":"Point"}
}