{
  "type": "Feature",
  "properties": {
    "iso:country": "GB",
    "wof:name": "WR7 4GA",
    "wof:placetype": "postalcode"
  },
  "geometry": {"coordinates":[-1.978518,52.219385],"type":"Point"}
}
