{
  "type": "Feature",
  "properties": {
    "iso:country":"GB",
    "wof:name":"M32 9XA",
    "wof:placetype":"postalcode"
},
  "geometry": {"coordinates":[-2.33736255174501,53.45119260833398],"type":"Point"}
}