{
  "type": "Feature",
  "properties": {
    "date:inception_lower":"1994-12-01",
    "date:inception_upper":"1994-12-31",
    "iso:country":"GB",
    "wof:name":"M32 9XA",
    "wof:placetype":"postalcode"
},
  "geometry": {"coordinates":[-2.337363,53.451193],"type":"Point"}
}