{
  "type": "Feature",
  "properties": {
    "iso:country": "GB",
    "wof:name": "PA18 6DP",
    "wof:placetype": "postalcode"
  },
  "geometry": {"coordinates":[-4.890119,55.889683],"type":"Point"}
}
