{
  "type": "Feature",
  "properties": {
    "iso:country":"GB",
    "wof:name":"PA18 6DP",
    "wof:placetype":"postalcode"
},
  "geometry": {"coordinates":[-4.89011855523791,55.88968286281735],"type":"Point"}
}