{
  "type": "Feature",
  "properties": {
    "iso:country": "GB",
    "wof:name": "SA20 0DT",
    "wof:placetype": "postalcode"
  },
  "geometry": {"coordinates":[-3.804875,51.991503],"type":"Point"}
}
