{
  "type": "Feature",
  "properties": {
    "date:inception_lower":"1998-12-01",
    "date:inception_upper":"1998-12-31",
    "iso:country":"GB",
    "wof:name":"SA20 0DT",
    "wof:placetype":"postalcode"
},
  "geometry": {"coordinates":[-3.804875,51.991503],"type":"Point"}
}