{
  "type": "Feature",
  "properties": {
    "date:inception_lower":"1998-06-01",
    "date:inception_upper":"1998-06-30",
    "iso:country":"GB",
    "wof:name":"YO17 6ST",
    "wof:placetype":"postalcode"
},
  "geometry": {"coordinates":[-0.840951,54.150578],"type":"Point"}
}