{
  "type": "Feature",
  "properties": {
    "iso:country": "GB",
    "wof:name": "IV55 8WX",
    "wof:placetype": "postalcode"
  },
  "geometry": {"coordinates":[-6.723177,57.401025],"type":"Point"}
}
