{
  "type": "Feature",
  "properties": {
    "iso:country":"GB",
    "wof:name":"IV55 8WX",
    "wof:placetype":"postalcode"
},
  "geometry": {"coordinates":[-6.72317675716241,57.40102512789407],"type":"Point"}
}