{
  "type": "Feature",
  "properties": {
    "date:inception_lower": "1980-01-01",
    "date:inception_upper": "1980-01-01",
    "iso:country": "GB",
    "wof:name": "IV55 8WX",
    "wof:placetype": "postalcode"
  },
  "geometry": {"coordinates":[-6.723164,57.401005],"type":"Point"}
}
