{
  "type": "Feature",
  "properties": {
    "date:inception_lower": "1995-07-01",
    "date:inception_upper": "1995-07-01",
    "iso:country": "GB",
    "wof:name": "CO4 5DT",
    "wof:placetype": "postalcode"
  },
  "geometry": {"coordinates":[0.882333,51.906603],"type":"Point"}
}
