{
  "type": "Feature",
  "properties": {
    "iso:country": "GB",
    "wof:name": "EC2V 6DT",
    "wof:placetype": "postalcode"
  },
  "geometry": {"coordinates":[-0.093166,51.514091],"type":"Point"}
}
