{
  "type": "Feature",
  "properties": {
    "date:inception_lower":"2010-04-01",
    "date:inception_upper":"2010-04-30",
    "iso:country":"GB",
    "wof:name":"EC2V 6DT",
    "wof:placetype":"postalcode"
},
  "geometry": {"coordinates":[-0.09328,51.514111],"type":"Point"}
}