{
  "type": "Feature",
  "properties": {
    "iso:country": "GB",
    "wof:name": "BB5 2AY",
    "wof:placetype": "postalcode"
  },
  "geometry": {"coordinates":[-2.358473,53.75072],"type":"Point"}
}
