{
  "type": "Feature",
  "properties": {
    "iso:country":"GB",
    "wof:name":"NE40 3HZ",
    "wof:placetype":"postalcode"
},
  "geometry": {"coordinates":[-1.75413998672721,54.97137758748659],"type":"Point"}
}