{
  "type": "Feature",
  "properties": {
    "date:inception_lower": "2008-12-01",
    "date:inception_upper": "2008-12-01",
    "iso:country": "GB",
    "wof:name": "HU1 1AZ",
    "wof:placetype": "postalcode"
  },
  "geometry": {"coordinates":[-0.335179,53.73781],"type":"Point"}
}
