{
  "type": "Feature",
  "properties": {
    "iso:country":"GB",
    "wof:name":"HU1 1AZ",
    "wof:placetype":"postalcode"
},
  "geometry": {"coordinates":[-0.3351791342604,53.73780985202186],"type":"Point"}
}