{
  "type": "Feature",
  "properties": {
    "iso:country":"GB",
    "wof:name":"BB3 2PU",
    "wof:placetype":"postalcode"
},
  "geometry": {"coordinates":[-2.46391151831643,53.68580536008552],"type":"Point"}
}