{
  "type": "Feature",
  "properties": {
    "iso:country": "GB",
    "wof:name": "LL57 2YA",
    "wof:placetype": "postalcode"
  },
  "geometry": {"coordinates":[-4.139403,53.220842],"type":"Point"}
}
