{
  "type": "Feature",
  "properties": {
    "iso:country":"GB",
    "wof:name":"DY2 7NT",
    "wof:placetype":"postalcode"
},
  "geometry": {"coordinates":[-2.06228193298704,52.51016089413237],"type":"Point"}
}