{
  "type": "Feature",
  "properties": {
    "date:inception_lower":"2015-05-01",
    "date:inception_upper":"2015-05-31",
    "iso:country":"GB",
    "wof:name":"PE7 8PD",
    "wof:placetype":"postalcode"
},
  "geometry": {"coordinates":[-0.281509,52.529242],"type":"Point"}
}