{
  "type": "Feature",
  "properties": {
    "iso:country": "GB",
    "wof:name": "PE7 8PD",
    "wof:placetype": "postalcode"
  },
  "geometry": {"coordinates":[-0.281509,52.529242],"type":"Point"}
}
