{
  "type": "Feature",
  "properties": {
    "iso:country":"GB",
    "wof:name":"PE7 8PD",
    "wof:placetype":"postalcode"
},
  "geometry": {"coordinates":[-0.28136013324827,52.52927615103989],"type":"Point"}
}