{
  "type": "Feature",
  "properties": {
    "iso:country":"GB",
    "wof:name":"LN1 2RN",
    "wof:placetype":"postalcode"
},
  "geometry": {"coordinates":[-0.5757394165327,53.27798417739907],"type":"Point"}
}