{
  "type": "Feature",
  "properties": {
    "iso:country":"GB",
    "wof:name":"FK3 8BX",
    "wof:placetype":"postalcode"
},
  "geometry": {"coordinates":[-3.72562055238534,56.0164789861269],"type":"Point"}
}