{
  "type": "Feature",
  "properties": {
    "iso:country": "GB",
    "wof:name": "FK3 8BX",
    "wof:placetype": "postalcode"
  },
  "geometry": {"coordinates":[-3.72562,56.016479],"type":"Point"}
}
