{
  "type": "Feature",
  "properties": {
    "iso:country":"GB",
    "wof:name":"PL15 9JE",
    "wof:placetype":"postalcode"
},
  "geometry": {"coordinates":[-4.36396003835529,50.63402781999363],"type":"Point"}
}