{
  "type": "Feature",
  "properties": {
    "date:inception_lower": "1980-01-01",
    "date:inception_upper": "1980-01-01",
    "iso:country": "GB",
    "wof:name": "TS6 0JG",
    "wof:placetype": "postalcode"
  },
  "geometry": {"coordinates":[-1.163364,54.555688],"type":"Point"}
}
