{
  "type": "Feature",
  "properties": {
    "iso:country":"GB",
    "wof:name":"TS6 0JG",
    "wof:placetype":"postalcode"
},
  "geometry": {"coordinates":[-1.16336397779235,54.55568825877008],"type":"Point"}
}