{
  "type": "Feature",
  "properties": {
    "iso:country": "GB",
    "wof:name": "TS6 0JG",
    "wof:placetype": "postalcode"
  },
  "geometry": {"coordinates":[-1.163364,54.555688],"type":"Point"}
}
