{
  "type": "Feature",
  "properties": {
    "iso:country":"GB",
    "wof:name":"CO6 4TT",
    "wof:placetype":"postalcode"
},
  "geometry": {"coordinates":[0.87909510051354,51.92507415180657],"type":"Point"}
}