{
  "type": "Feature",
  "properties": {
    "iso:country": "GB",
    "wof:name": "CO6 4TT",
    "wof:placetype": "postalcode"
  },
  "geometry": {"coordinates":[0.879095,51.925074],"type":"Point"}
}
