{
  "type": "Feature",
  "properties": {
    "date:inception_lower": "1980-01-01",
    "date:inception_upper": "1980-01-01",
    "iso:country": "GB",
    "wof:name": "CO6 4TT",
    "wof:placetype": "postalcode"
  },
  "geometry": {"coordinates":[0.879095,51.925074],"type":"Point"}
}
