{
  "type": "Feature",
  "properties": {
    "iso:country":"GB",
    "wof:name":"RG26 5QL",
    "wof:placetype":"postalcode"
},
  "geometry": {"coordinates":[-1.14065704785032,51.32602920629901],"type":"Point"}
}