{
  "type": "Feature",
  "properties": {
    "date:inception_lower": "1980-01-01",
    "date:inception_upper": "1980-01-01",
    "iso:country": "GB",
    "wof:name": "TS8 9JU",
    "wof:placetype": "postalcode"
  },
  "geometry": {"coordinates":[-1.231712,54.521676],"type":"Point"}
}
