{
  "type": "Feature",
  "properties": {
    "iso:country":"GB",
    "wof:name":"WF5 8NZ",
    "wof:placetype":"postalcode"
},
  "geometry": {"coordinates":[-1.59315077044222,53.67707141978443],"type":"Point"}
}