{
  "type": "Feature",
  "properties": {
    "iso:country":"GB",
    "wof:name":"TS1 3LH",
    "wof:placetype":"postalcode"
},
  "geometry": {"coordinates":[-1.2341590433153,54.56761543271718],"type":"Point"}
}