{
  "type": "Feature",
  "properties": {
    "date:inception_lower": "2007-04-01",
    "date:inception_upper": "2007-04-01",
    "iso:country": "GB",
    "wof:name": "S45 9HZ",
    "wof:placetype": "postalcode"
  },
  "geometry": {"coordinates":[-1.395307,53.167659],"type":"Point"}
}
