{
  "type": "Feature",
  "properties": {
    "date:inception_lower":"1991-09-01",
    "date:inception_upper":"1991-09-30",
    "iso:country":"GB",
    "wof:name":"OX20 1QE",
    "wof:placetype":"postalcode"
},
  "geometry": {"coordinates":[-1.326582,51.833223],"type":"Point"}
}