{
  "type": "Feature",
  "properties": {
    "iso:country":"GB",
    "wof:name":"OX20 1QE",
    "wof:placetype":"postalcode"
},
  "geometry": {"coordinates":[-1.32662623178297,51.83316919673377],"type":"Point"}
}