{
  "type": "Feature",
  "properties": {
    "iso:country": "GB",
    "wof:name": "CH5 4TW",
    "wof:placetype": "postalcode"
  },
  "geometry": {"coordinates":[-3.068328,53.214909],"type":"Point"}
}
