{
  "type": "Feature",
  "properties": {
    "date:inception_lower":"1980-01-01",
    "date:inception_upper":"1980-01-31",
    "iso:country":"GB",
    "wof:name":"CH5 4TW",
    "wof:placetype":"postalcode"
},
  "geometry": {"coordinates":[-3.068328,53.214909],"type":"Point"}
}