{
  "type": "Feature",
  "properties": {
    "iso:country":"GB",
    "wof:name":"CH5 4TW",
    "wof:placetype":"postalcode"
},
  "geometry": {"coordinates":[-3.06832806260875,53.21490877239136],"type":"Point"}
}