{
  "type": "Feature",
  "properties": {
    "iso:country": "GB",
    "wof:name": "HR5 3PJ",
    "wof:placetype": "postalcode"
  },
  "geometry": {"coordinates":[-3.123788,52.164202],"type":"Point"}
}
