{
  "type": "Feature",
  "properties": {
    "date:inception_lower": "1980-01-01",
    "date:inception_upper": "1980-01-01",
    "iso:country": "GB",
    "wof:name": "HR5 3PJ",
    "wof:placetype": "postalcode"
  },
  "geometry": {"coordinates":[-3.123978,52.166538],"type":"Point"}
}
