{
  "type": "Feature",
  "properties": {
    "iso:country":"GB",
    "wof:name":"HR5 3PJ",
    "wof:placetype":"postalcode"
},
  "geometry": {"coordinates":[-3.1239750599456,52.16652935627843],"type":"Point"}
}