{
  "type": "Feature",
  "properties": {
    "iso:country": "GB",
    "wof:name": "HP14 3JP",
    "wof:placetype": "postalcode"
  },
  "geometry": {"coordinates":[-0.831101,51.617179],"type":"Point"}
}
