{
  "type": "Feature",
  "properties": {
    "iso:country":"GB",
    "wof:name":"SW15 5LB",
    "wof:placetype":"postalcode"
},
  "geometry": {"coordinates":[-0.24750794949027,51.46439470791582],"type":"Point"}
}