{
  "type": "Feature",
  "properties": {
    "iso:country": "GB",
    "wof:name": "WV16 4BP",
    "wof:placetype": "postalcode"
  },
  "geometry": {"coordinates":[-2.418876,52.534607],"type":"Point"}
}
