{
  "type": "Feature",
  "properties": {
    "date:inception_lower": "2012-03-01",
    "date:inception_upper": "2012-03-01",
    "iso:country": "GB",
    "wof:name": "WV16 4BP",
    "wof:placetype": "postalcode"
  },
  "geometry": {"coordinates":[-2.418876,52.534607],"type":"Point"}
}
