{
  "type": "Feature",
  "properties": {
    "iso:country":"GB",
    "wof:name":"WV16 4BP",
    "wof:placetype":"postalcode"
},
  "geometry": {"coordinates":[-2.4188762852862,52.53460709156872],"type":"Point"}
}