{
  "type": "Feature",
  "properties": {
    "iso:country":"GB",
    "wof:name":"WF6 2BQ",
    "wof:placetype":"postalcode"
},
  "geometry": {"coordinates":[-1.42165439228062,53.69978086718571],"type":"Point"}
}