{
  "type": "Feature",
  "properties": {
    "iso:country":"GB",
    "wof:name":"MK41 6BL",
    "wof:placetype":"postalcode"
},
  "geometry": {"coordinates":[-0.49077698580607,52.18471302189914],"type":"Point"}
}