{
  "type": "Feature",
  "properties": {
    "iso:country": "GB",
    "wof:name": "MK41 6BL",
    "wof:placetype": "postalcode"
  },
  "geometry": {"coordinates":[-0.490777,52.184713],"type":"Point"}
}
