{
  "type": "Feature",
  "properties": {
    "iso:country":"GB",
    "wof:name":"EH54 6TQ",
    "wof:placetype":"postalcode"
},
  "geometry": {"coordinates":[-3.52988712402179,55.89030327945733],"type":"Point"}
}