{
  "type": "Feature",
  "properties": {
    "iso:country": "GB",
    "wof:name": "EH54 6TQ",
    "wof:placetype": "postalcode"
  },
  "geometry": {"coordinates":[-3.529887,55.890303],"type":"Point"}
}
