{
  "type": "Feature",
  "properties": {
    "date:inception_lower": "2006-04-01",
    "date:inception_upper": "2006-04-01",
    "iso:country": "GB",
    "wof:name": "EH54 6TQ",
    "wof:placetype": "postalcode"
  },
  "geometry": {"coordinates":[-3.529887,55.890303],"type":"Point"}
}
