{
  "type": "Feature",
  "properties": {
    "iso:country":"GB",
    "wof:name":"E8 4AB",
    "wof:placetype":"postalcode"
},
  "geometry": {"coordinates":[-0.07647749727428,51.54409461222892],"type":"Point"}
}