{
  "type": "Feature",
  "properties": {
    "iso:country":"GB",
    "wof:name":"FK2 8PB",
    "wof:placetype":"postalcode"
},
  "geometry": {"coordinates":[-3.76317015844316,56.03180847319882],"type":"Point"}
}