{
  "type": "Feature",
  "properties": {
    "date:inception_lower": "1980-01-01",
    "date:inception_upper": "1980-01-01",
    "iso:country": "GB",
    "wof:name": "DL13 1PT",
    "wof:placetype": "postalcode"
  },
  "geometry": {"coordinates":[-2.202341,54.750814],"type":"Point"}
}
