{
  "type": "Feature",
  "properties": {
    "iso:country":"GB",
    "wof:name":"DL13 1PT",
    "wof:placetype":"postalcode"
},
  "geometry": {"coordinates":[-2.20234150743728,54.75081421983747],"type":"Point"}
}