{
  "type": "Feature",
  "properties": {
    "iso:country": "GB",
    "wof:name": "DD11 1HB",
    "wof:placetype": "postalcode"
  },
  "geometry": {"coordinates":[-2.57864,56.56113],"type":"Point"}
}
