{
  "type": "Feature",
  "properties": {
    "iso:country":"GB",
    "wof:name":"PE10 0LY",
    "wof:placetype":"postalcode"
},
  "geometry": {"coordinates":[-0.4493220685052,52.79484800993535],"type":"Point"}
}