{
  "type": "Feature",
  "properties": {
    "iso:country": "GB",
    "wof:name": "PE10 0LY",
    "wof:placetype": "postalcode"
  },
  "geometry": {"coordinates":[-0.447809,52.794019],"type":"Point"}
}
