{
  "type": "Feature",
  "properties": {
    "date:inception_lower": "1980-01-01",
    "date:inception_upper": "1980-01-01",
    "iso:country": "GB",
    "wof:name": "DY8 3RW",
    "wof:placetype": "postalcode"
  },
  "geometry": {"coordinates":[-2.164155,52.452686],"type":"Point"}
}
