{
  "type": "Feature",
  "properties": {
    "iso:country":"GB",
    "wof:name":"DL14 7RD",
    "wof:placetype":"postalcode"
},
  "geometry": {"coordinates":[-1.68376789698863,54.66018426520708],"type":"Point"}
}