{
  "type": "Feature",
  "properties": {
    "iso:country":"GB",
    "wof:name":"SG14 2JE",
    "wof:placetype":"postalcode"
},
  "geometry": {"coordinates":[-0.10683142521906,51.80466435599911],"type":"Point"}
}