{
  "type": "Feature",
  "properties": {
    "date:inception_lower": "1980-01-01",
    "date:inception_upper": "1980-01-01",
    "iso:country": "GB",
    "wof:name": "WS13 6RL",
    "wof:placetype": "postalcode"
  },
  "geometry": {"coordinates":[-1.811277,52.690929],"type":"Point"}
}
