{
  "type": "Feature",
  "properties": {
    "iso:country":"GB",
    "wof:name":"SW9 8AQ",
    "wof:placetype":"postalcode"
},
  "geometry": {"coordinates":[-0.12052659560776,51.46343505955721],"type":"Point"}
}