{
  "type": "Feature",
  "properties": {
    "iso:country":"GB",
    "wof:name":"SR4 7QA",
    "wof:placetype":"postalcode"
},
  "geometry": {"coordinates":[-1.41304846160538,54.89535373376377],"type":"Point"}
}