{
  "type": "Feature",
  "properties": {
    "iso:country": "GB",
    "wof:name": "BB2 9QG",
    "wof:placetype": "postalcode"
  },
  "geometry": {"coordinates":[-2.484901,53.742938],"type":"Point"}
}
