{
  "type": "Feature",
  "properties": {
    "iso:country":"GB",
    "wof:name":"KY9 1JB",
    "wof:placetype":"postalcode"
},
  "geometry": {"coordinates":[-2.87032973680714,56.25844066589198],"type":"Point"}
}