{
  "type": "Feature",
  "properties": {
    "date:inception_lower": "1980-01-01",
    "date:inception_upper": "1980-01-01",
    "iso:country": "GB",
    "wof:name": "KY9 1JB",
    "wof:placetype": "postalcode"
  },
  "geometry": {"coordinates":[-2.87033,56.258441],"type":"Point"}
}
