{
  "type": "Feature",
  "properties": {
    "date:inception_lower": "2019-10-01",
    "date:inception_upper": "2019-10-01",
    "iso:country": "GB",
    "wof:name": "CT21 5FH",
    "wof:placetype": "postalcode"
  },
  "geometry": {"coordinates":[1.085252,51.070752],"type":"Point"}
}
