{
  "type": "Feature",
  "properties": {
    "iso:country": "GB",
    "wof:name": "GL52 5DR",
    "wof:placetype": "postalcode"
  },
  "geometry": {"coordinates":[-2.056907,51.90815],"type":"Point"}
}
