{
  "type": "Feature",
  "properties": {
    "date:inception_lower": "1980-01-01",
    "date:inception_upper": "1980-01-01",
    "iso:country": "GB",
    "wof:name": "GL52 5DR",
    "wof:placetype": "postalcode"
  },
  "geometry": {"coordinates":[-2.056907,51.90815],"type":"Point"}
}
