{
  "type": "Feature",
  "properties": {
    "iso:country":"GB",
    "wof:name":"CH47 9RA",
    "wof:placetype":"postalcode"
},
  "geometry": {"coordinates":[-3.15322621526634,53.39813552841851],"type":"Point"}
}