{
  "type": "Feature",
  "properties": {
    "iso:country": "GB",
    "wof:name": "CH47 9RA",
    "wof:placetype": "postalcode"
  },
  "geometry": {"coordinates":[-3.153225,53.398153],"type":"Point"}
}
