{
  "type": "Feature",
  "properties": {
    "date:inception_lower": "2005-09-01",
    "date:inception_upper": "2005-09-01",
    "iso:country": "GB",
    "wof:name": "SS17 0BF",
    "wof:placetype": "postalcode"
  },
  "geometry": {"coordinates":[0.42797,51.514718],"type":"Point"}
}
