{
  "type": "Feature",
  "properties": {
    "iso:country":"GB",
    "wof:name":"SS17 0BF",
    "wof:placetype":"postalcode"
},
  "geometry": {"coordinates":[0.42796974588473,51.51471849979508],"type":"Point"}
}