{
  "type": "Feature",
  "properties": {
    "iso:country":"GB",
    "wof:name":"NR2 3DR",
    "wof:placetype":"postalcode"
},
  "geometry": {"coordinates":[1.27712925361809,52.6273750606406],"type":"Point"}
}