{
  "type": "Feature",
  "properties": {
    "iso:country":"GB",
    "wof:name":"B23 5PT",
    "wof:placetype":"postalcode"
},
  "geometry": {"coordinates":[-1.84431644423559,52.5360022447856],"type":"Point"}
}