{
  "type": "Feature",
  "properties": {
    "iso:country": "GB",
    "wof:name": "DL17 0BL",
    "wof:placetype": "postalcode"
  },
  "geometry": {"coordinates":[-1.559581,54.665756],"type":"Point"}
}
