{
  "type": "Feature",
  "properties": {
    "iso:country":"GB",
    "wof:name":"HU5 2QU",
    "wof:placetype":"postalcode"
},
  "geometry": {"coordinates":[-0.35597164777156,53.76058772181921],"type":"Point"}
}