{
  "type": "Feature",
  "properties": {
    "iso:country": "GB",
    "wof:name": "HU5 2QU",
    "wof:placetype": "postalcode"
  },
  "geometry": {"coordinates":[-0.355972,53.760588],"type":"Point"}
}
