{
  "type": "Feature",
  "properties": {
    "iso:country":"GB",
    "wof:name":"OX2 7ES",
    "wof:placetype":"postalcode"
},
  "geometry": {"coordinates":[-1.26266689708372,51.77998966587892],"type":"Point"}
}