{
  "type": "Feature",
  "properties": {
    "iso:country": "GB",
    "wof:name": "CF46 5BU",
    "wof:placetype": "postalcode"
  },
  "geometry": {"coordinates":[-3.300938,51.6556],"type":"Point"}
}
