{
  "type": "Feature",
  "properties": {
    "iso:country":"GB",
    "wof:name":"CF46 5BU",
    "wof:placetype":"postalcode"
},
  "geometry": {"coordinates":[-3.30093781006179,51.65559983717771],"type":"Point"}
}