{
  "type": "Feature",
  "properties": {
    "iso:country":"GB",
    "wof:name":"PR4 3RY",
    "wof:placetype":"postalcode"
},
  "geometry": {"coordinates":[-2.83711145659268,53.77746321883294],"type":"Point"}
}