{
  "type": "Feature",
  "properties": {
    "iso:country":"GB",
    "wof:name":"KY11 2RR",
    "wof:placetype":"postalcode"
},
  "geometry": {"coordinates":[-3.42483305257977,56.03809502396095],"type":"Point"}
}