{
  "type": "Feature",
  "properties": {
    "iso:country": "GB",
    "wof:name": "TR19 7DL",
    "wof:placetype": "postalcode"
  },
  "geometry": {"coordinates":[-5.664236,50.151993],"type":"Point"}
}
