{
  "type": "Feature",
  "properties": {
    "iso:country": "GB",
    "wof:name": "KY1 1BL",
    "wof:placetype": "postalcode"
  },
  "geometry": {"coordinates":[-3.15699,56.116752],"type":"Point"}
}
