{
  "type": "Feature",
  "properties": {
    "iso:country": "GB",
    "wof:name": "SK22 1AJ",
    "wof:placetype": "postalcode"
  },
  "geometry": {"coordinates":[-1.97908,53.378266],"type":"Point"}
}
