{
  "type": "Feature",
  "properties": {
    "date:inception_lower": "1996-12-01",
    "date:inception_upper": "1996-12-01",
    "iso:country": "GB",
    "wof:name": "SK22 1AJ",
    "wof:placetype": "postalcode"
  },
  "geometry": {"coordinates":[-1.979005,53.378284],"type":"Point"}
}
