{
  "type": "Feature",
  "properties": {
    "iso:country":"GB",
    "wof:name":"DL3 9DT",
    "wof:placetype":"postalcode"
},
  "geometry": {"coordinates":[-1.59494281132234,54.53231605268081],"type":"Point"}
}