{
  "type": "Feature",
  "properties": {
    "iso:country": "GB",
    "wof:name": "DL3 9DT",
    "wof:placetype": "postalcode"
  },
  "geometry": {"coordinates":[-1.594943,54.532316],"type":"Point"}
}
