{
  "type": "Feature",
  "properties": {
    "iso:country":"GB",
    "wof:name":"B63 4AT",
    "wof:placetype":"postalcode"
},
  "geometry": {"coordinates":[-2.05510563973704,52.45092064535179],"type":"Point"}
}