{
  "type": "Feature",
  "properties": {
    "iso:country": "GB",
    "wof:name": "TN9 2LQ",
    "wof:placetype": "postalcode"
  },
  "geometry": {"coordinates":[0.27068,51.187197],"type":"Point"}
}
