{
  "type": "Feature",
  "properties": {
    "iso:country": "GB",
    "wof:name": "NG23 6AU",
    "wof:placetype": "postalcode"
  },
  "geometry": {"coordinates":[-0.908099,53.142788],"type":"Point"}
}
