{
  "type": "Feature",
  "properties": {
    "iso:country":"GB",
    "wof:name":"NG23 6AU",
    "wof:placetype":"postalcode"
},
  "geometry": {"coordinates":[-0.90805675611896,53.1427577247156],"type":"Point"}
}