{
  "type": "Feature",
  "properties": {
    "iso:country":"GB",
    "wof:name":"PE22 7LF",
    "wof:placetype":"postalcode"
},
  "geometry": {"coordinates":[-0.06043803548391,53.09634820277592],"type":"Point"}
}