{
  "type": "Feature",
  "properties": {
    "date:inception_lower": "2004-01-01",
    "date:inception_upper": "2004-01-01",
    "iso:country": "GB",
    "wof:name": "BA3 2DJ",
    "wof:placetype": "postalcode"
  },
  "geometry": {"coordinates":[-2.47637,51.293097],"type":"Point"}
}
