{
  "type": "Feature",
  "properties": {
    "iso:country":"GB",
    "wof:name":"BA3 2DJ",
    "wof:placetype":"postalcode"
},
  "geometry": {"coordinates":[-2.47637004367845,51.29309673478707],"type":"Point"}
}