{
  "type": "Feature",
  "properties": {
    "iso:country":"GB",
    "wof:name":"CW5 5XF",
    "wof:placetype":"postalcode"
},
  "geometry": {"coordinates":[-2.53605873857762,53.05983578394567],"type":"Point"}
}