{
  "type": "Feature",
  "properties": {
    "iso:country":"GB",
    "wof:name":"MK5 8AF",
    "wof:placetype":"postalcode"
},
  "geometry": {"coordinates":[-0.78461015106677,52.02632993563279],"type":"Point"}
}