{
  "type": "Feature",
  "properties": {
    "iso:country": "GB",
    "wof:name": "MK5 8AF",
    "wof:placetype": "postalcode"
  },
  "geometry": {"coordinates":[-0.78461,52.02633],"type":"Point"}
}
