{
  "type": "Feature",
  "properties": {
    "iso:country":"GB",
    "wof:name":"GL20 7LR",
    "wof:placetype":"postalcode"
},
  "geometry": {"coordinates":[-2.11179359968825,52.02965662322088],"type":"Point"}
}