{
  "type": "Feature",
  "properties": {
    "iso:country": "GB",
    "wof:name": "LA9 6LS",
    "wof:placetype": "postalcode"
  },
  "geometry": {"coordinates":[-2.72917,54.330145],"type":"Point"}
}
