{
  "type": "Feature",
  "properties": {
    "iso:country":"GB",
    "wof:name":"LA9 6LS",
    "wof:placetype":"postalcode"
},
  "geometry": {"coordinates":[-2.72917023936718,54.330144935468],"type":"Point"}
}