{
  "type": "Feature",
  "properties": {
    "iso:country":"GB",
    "wof:name":"M25 3DF",
    "wof:placetype":"postalcode"
},
  "geometry": {"coordinates":[-2.2783351677732,53.53851475815001],"type":"Point"}
}