{
  "type": "Feature",
  "properties": {
    "iso:country":"GB",
    "wof:name":"HU17 9QP",
    "wof:placetype":"postalcode"
},
  "geometry": {"coordinates":[-0.42010455516749,53.85405451895615],"type":"Point"}
}