{
  "type": "Feature",
  "properties": {
    "iso:country": "GB",
    "wof:name": "PO11 9BH",
    "wof:placetype": "postalcode"
  },
  "geometry": {"coordinates":[-0.975931,50.787478],"type":"Point"}
}
