{
  "type": "Feature",
  "properties": {
    "iso:country":"GB",
    "wof:name":"LN4 1PU",
    "wof:placetype":"postalcode"
},
  "geometry": {"coordinates":[-0.4760913246839,53.1957012777554],"type":"Point"}
}