{
  "type": "Feature",
  "properties": {
    "iso:country":"GB",
    "wof:name":"TS18 5DH",
    "wof:placetype":"postalcode"
},
  "geometry": {"coordinates":[-1.34705896671657,54.55257672626615],"type":"Point"}
}