{
  "type": "Feature",
  "properties": {
    "iso:country":"GB",
    "wof:name":"GL6 8FH",
    "wof:placetype":"postalcode"
},
  "geometry": {"coordinates":[-2.16123094589835,51.72862026441282],"type":"Point"}
}