{
  "type": "Feature",
  "properties": {
    "date:inception_lower":"2000-06-01",
    "date:inception_upper":"2000-06-30",
    "iso:country":"GB",
    "wof:name":"GL6 8FH",
    "wof:placetype":"postalcode"
},
  "geometry": {"coordinates":[-2.161231,51.72862],"type":"Point"}
}