{
  "type": "Feature",
  "properties": {
    "iso:country":"GB",
    "wof:name":"TR1 1NW",
    "wof:placetype":"postalcode"
},
  "geometry": {"coordinates":[-5.04119797399709,50.26742869107645],"type":"Point"}
}