{
  "type": "Feature",
  "properties": {
    "iso:country": "GB",
    "wof:name": "S41 8JP",
    "wof:placetype": "postalcode"
  },
  "geometry": {"coordinates":[-1.442711,53.262291],"type":"Point"}
}
