{
  "type": "Feature",
  "properties": {
    "iso:country":"GB",
    "wof:name":"S41 8JP",
    "wof:placetype":"postalcode"
},
  "geometry": {"coordinates":[-1.44274256416121,53.26229081770595],"type":"Point"}
}