{
  "type": "Feature",
  "properties": {
    "date:inception_lower": "2009-12-01",
    "date:inception_upper": "2009-12-01",
    "iso:country": "GB",
    "wof:name": "SW1W 8BA",
    "wof:placetype": "postalcode"
  },
  "geometry": {"coordinates":[-0.149198,51.488126],"type":"Point"}
}
