{
  "type": "Feature",
  "properties": {
    "iso:country": "GB",
    "wof:name": "RG40 1UB",
    "wof:placetype": "postalcode"
  },
  "geometry": {"coordinates":[-0.825278,51.413195],"type":"Point"}
}
