{
  "type": "Feature",
  "properties": {
    "iso:country": "GB",
    "wof:name": "L25 6HS",
    "wof:placetype": "postalcode"
  },
  "geometry": {"coordinates":[-2.875614,53.379434],"type":"Point"}
}
