{
  "type": "Feature",
  "properties": {
    "iso:country": "GB",
    "wof:name": "IV30 8SU",
    "wof:placetype": "postalcode"
  },
  "geometry": {"coordinates":[-3.330211,57.612313],"type":"Point"}
}
