{
  "type": "Feature",
  "properties": {
    "iso:country":"GB",
    "wof:name":"LA15 8NF",
    "wof:placetype":"postalcode"
},
  "geometry": {"coordinates":[-3.18475604359364,54.1487229792119],"type":"Point"}
}