{
  "type": "Feature",
  "properties": {
    "iso:country":"GB",
    "wof:name":"M33 5BS",
    "wof:placetype":"postalcode"
},
  "geometry": {"coordinates":[-2.34353668381632,53.41953530533156],"type":"Point"}
}