{
  "type": "Feature",
  "properties": {
    "iso:country":"GB",
    "wof:name":"DT4 8PY",
    "wof:placetype":"postalcode"
},
  "geometry": {"coordinates":[-2.45455647887895,50.60896295950691],"type":"Point"}
}