{
  "type": "Feature",
  "properties": {
    "iso:country": "GB",
    "wof:name": "DT4 8PY",
    "wof:placetype": "postalcode"
  },
  "geometry": {"coordinates":[-2.454468,50.608943],"type":"Point"}
}
