{
  "type": "Feature",
  "properties": {
    "iso:country":"GB",
    "wof:name":"SO41 8JR",
    "wof:placetype":"postalcode"
},
  "geometry": {"coordinates":[-1.54884767523824,50.75618114056861],"type":"Point"}
}