{
  "type": "Feature",
  "properties": {
    "date:inception_lower":"1980-01-01",
    "date:inception_upper":"1980-01-31",
    "iso:country":"GB",
    "wof:name":"G78 3BP",
    "wof:placetype":"postalcode"
},
  "geometry": {"coordinates":[-4.438687,55.775317],"type":"Point"}
}