{
  "type": "Feature",
  "properties": {
    "iso:country": "GB",
    "wof:name": "G78 3BP",
    "wof:placetype": "postalcode"
  },
  "geometry": {"coordinates":[-4.438687,55.775317],"type":"Point"}
}
