{
  "type": "Feature",
  "properties": {
    "date:inception_lower":"1980-01-01",
    "date:inception_upper":"1980-01-31",
    "iso:country":"GB",
    "wof:name":"DT5 1BS",
    "wof:placetype":"postalcode"
},
  "geometry": {"coordinates":[-2.436186,50.5468],"type":"Point"}
}