{
  "type": "Feature",
  "properties": {
    "iso:country":"GB",
    "wof:name":"DT5 1BS",
    "wof:placetype":"postalcode"
},
  "geometry": {"coordinates":[-2.4361467821213,50.54682019963769],"type":"Point"}
}