{
  "type": "Feature",
  "properties": {
    "iso:country": "GB",
    "wof:name": "RM1 4NF",
    "wof:placetype": "postalcode"
  },
  "geometry": {"coordinates":[0.173437,51.586037],"type":"Point"}
}
