{
  "type": "Feature",
  "properties": {
    "iso:country":"GB",
    "wof:name":"PL14 5AA",
    "wof:placetype":"postalcode"
},
  "geometry": {"coordinates":[-4.4222389885838,50.51592931250811],"type":"Point"}
}