{
  "type": "Feature",
  "properties": {
    "iso:country":"GB",
    "wof:name":"N5 1HX",
    "wof:placetype":"postalcode"
},
  "geometry": {"coordinates":[-0.09953250538859,51.54838210129481],"type":"Point"}
}