{
  "type": "Feature",
  "properties": {
    "iso:country":"GB",
    "wof:name":"E2 0PU",
    "wof:placetype":"postalcode"
},
  "geometry": {"coordinates":[-0.04711303686656,51.52762064818346],"type":"Point"}
}