{
  "type": "Feature",
  "properties": {
    "date:inception_lower":"1980-01-01",
    "date:inception_upper":"1980-01-31",
    "iso:country":"GB",
    "wof:name":"E2 0PU",
    "wof:placetype":"postalcode"
},
  "geometry": {"coordinates":[-0.047113,51.527621],"type":"Point"}
}