{
  "type": "Feature",
  "properties": {
    "date:inception_lower": "2017-06-01",
    "date:inception_upper": "2017-06-01",
    "iso:country": "GB",
    "wof:name": "DA6 7AX",
    "wof:placetype": "postalcode"
  },
  "geometry": {"coordinates":[0.140067,51.456711],"type":"Point"}
}
