{
  "type": "Feature",
  "properties": {
    "date:inception_lower":"1999-06-01",
    "date:inception_upper":"1999-06-30",
    "iso:country":"GB",
    "wof:name":"CH43 1TW",
    "wof:placetype":"postalcode"
},
  "geometry": {"coordinates":[-3.042968,53.387644],"type":"Point"}
}