{
  "type": "Feature",
  "properties": {
    "date:inception_lower": "2000-12-01",
    "date:inception_upper": "2000-12-01",
    "iso:country": "GB",
    "wof:name": "DN4 8TG",
    "wof:placetype": "postalcode"
  },
  "geometry": {"coordinates":[-1.144027,53.492794],"type":"Point"}
}
