{
  "type": "Feature",
  "properties": {
    "iso:country":"GB",
    "wof:name":"B38 8HE",
    "wof:placetype":"postalcode"
},
  "geometry": {"coordinates":[-1.94844253311088,52.39887912408899],"type":"Point"}
}