{
  "type": "Feature",
  "properties": {
    "iso:country": "GB",
    "wof:name": "B38 8HE",
    "wof:placetype": "postalcode"
  },
  "geometry": {"coordinates":[-1.948442,52.398879],"type":"Point"}
}
