{
  "type": "Feature",
  "properties": {
    "iso:country":"GB",
    "wof:name":"DH9 6NB",
    "wof:placetype":"postalcode"
},
  "geometry": {"coordinates":[-1.69783650140167,54.86573352417488],"type":"Point"}
}