{
  "type": "Feature",
  "properties": {
    "iso:country": "GB",
    "wof:name": "SK6 7DB",
    "wof:placetype": "postalcode"
  },
  "geometry": {"coordinates":[-2.057304,53.39777],"type":"Point"}
}
