{
  "type": "Feature",
  "properties": {
    "date:inception_lower":"1980-01-01",
    "date:inception_upper":"1980-01-31",
    "iso:country":"GB",
    "wof:name":"TN13 2HG",
    "wof:placetype":"postalcode"
},
  "geometry": {"coordinates":[0.168388,51.277102],"type":"Point"}
}