{
  "type": "Feature",
  "properties": {
    "iso:country": "GB",
    "wof:name": "TN13 2HG",
    "wof:placetype": "postalcode"
  },
  "geometry": {"coordinates":[0.168388,51.277102],"type":"Point"}
}
