{
  "type": "Feature",
  "properties": {
    "iso:country":"GB",
    "wof:name":"G33 4TE",
    "wof:placetype":"postalcode"
},
  "geometry": {"coordinates":[-4.1373410279586,55.855010378074],"type":"Point"}
}