{
  "type": "Feature",
  "properties": {
    "date:inception_lower":"1990-02-01",
    "date:inception_upper":"1990-02-28",
    "iso:country":"GB",
    "wof:name":"LN11 8HZ",
    "wof:placetype":"postalcode"
},
  "geometry": {"coordinates":[0.09291,53.369974],"type":"Point"}
}