{
  "type": "Feature",
  "properties": {
    "iso:country":"GB",
    "wof:name":"LN11 8HZ",
    "wof:placetype":"postalcode"
},
  "geometry": {"coordinates":[0.09291019939969,53.36997438855667],"type":"Point"}
}