{
  "type": "Feature",
  "properties": {
    "iso:country": "GB",
    "wof:name": "LN11 8HZ",
    "wof:placetype": "postalcode"
  },
  "geometry": {"coordinates":[0.09291,53.369974],"type":"Point"}
}
