{
  "type": "Feature",
  "properties": {
    "iso:country":"GB",
    "wof:name":"ML8 4PZ",
    "wof:placetype":"postalcode"
},
  "geometry": {"coordinates":[-3.81469308613093,55.7300934945449],"type":"Point"}
}