{
  "type": "Feature",
  "properties": {
    "iso:country": "GB",
    "wof:name": "ML8 4PZ",
    "wof:placetype": "postalcode"
  },
  "geometry": {"coordinates":[-3.814693,55.730093],"type":"Point"}
}
