{
  "type": "Feature",
  "properties": {
    "iso:country": "GB",
    "wof:name": "HG4 5LL",
    "wof:placetype": "postalcode"
  },
  "geometry": {"coordinates":[-1.574554,54.202111],"type":"Point"}
}
