{
  "type": "Feature",
  "properties": {
    "date:inception_lower": "1980-01-01",
    "date:inception_upper": "1980-01-01",
    "iso:country": "GB",
    "wof:name": "HG4 5LL",
    "wof:placetype": "postalcode"
  },
  "geometry": {"coordinates":[-1.574554,54.202111],"type":"Point"}
}
