{
  "type": "Feature",
  "properties": {
    "iso:country":"GB",
    "wof:name":"DA7 5ES",
    "wof:placetype":"postalcode"
},
  "geometry": {"coordinates":[0.14101139649037,51.47100975828324],"type":"Point"}
}