{
  "type": "Feature",
  "properties": {
    "iso:country":"GB",
    "wof:name":"TR26 3EE",
    "wof:placetype":"postalcode"
},
  "geometry": {"coordinates":[-5.44422949180563,50.17776814936384],"type":"Point"}
}