{
  "type": "Feature",
  "properties": {
    "date:inception_lower": "1997-06-01",
    "date:inception_upper": "1997-06-01",
    "iso:country": "GB",
    "wof:name": "WA9 1RL",
    "wof:placetype": "postalcode"
  },
  "geometry": {"coordinates":[-2.712353,53.44681],"type":"Point"}
}
