{
  "type": "Feature",
  "properties": {
    "iso:country":"GB",
    "wof:name":"M30 9GS",
    "wof:placetype":"postalcode"
},
  "geometry": {"coordinates":[-2.34994014315303,53.49013952287857],"type":"Point"}
}