{
  "type": "Feature",
  "properties": {
    "iso:country":"GB",
    "wof:name":"CM1 4XR",
    "wof:placetype":"postalcode"
},
  "geometry": {"coordinates":[0.45445659775601,51.75306098755539],"type":"Point"}
}