{
  "type": "Feature",
  "properties": {
    "iso:country":"GB",
    "wof:name":"LN2 5HS",
    "wof:placetype":"postalcode"
},
  "geometry": {"coordinates":[-0.52985136785775,53.23057343580068],"type":"Point"}
}