{
  "type": "Feature",
  "properties": {
    "date:inception_lower": "2014-11-01",
    "date:inception_upper": "2014-11-01",
    "iso:country": "GB",
    "wof:name": "PR25 3NX",
    "wof:placetype": "postalcode"
  },
  "geometry": {"coordinates":[-2.694557,53.701012],"type":"Point"}
}
