{
  "type": "Feature",
  "properties": {
    "iso:country":"GB",
    "wof:name":"PR25 3NX",
    "wof:placetype":"postalcode"
},
  "geometry": {"coordinates":[-2.69455694122206,53.70101227079919],"type":"Point"}
}