{
  "type": "Feature",
  "properties": {
    "iso:country": "GB",
    "wof:name": "BS21 6EH",
    "wof:placetype": "postalcode"
  },
  "geometry": {"coordinates":[-2.846731,51.433289],"type":"Point"}
}
