{
  "type": "Feature",
  "properties": {
    "iso:country":"GB",
    "wof:name":"BS21 6EH",
    "wof:placetype":"postalcode"
},
  "geometry": {"coordinates":[-2.8467685538576,51.43324600896833],"type":"Point"}
}