{
  "type": "Feature",
  "properties": {
    "date:inception_lower": "2005-08-01",
    "date:inception_upper": "2005-08-01",
    "iso:country": "GB",
    "wof:name": "E1 0EF",
    "wof:placetype": "postalcode"
  },
  "geometry": {"coordinates":[-0.048809,51.511903],"type":"Point"}
}
