{
  "type": "Feature",
  "properties": {
    "iso:country":"GB",
    "wof:name":"E1 0EF",
    "wof:placetype":"postalcode"
},
  "geometry": {"coordinates":[-0.04880855224901,51.51190281275287],"type":"Point"}
}