{
  "type": "Feature",
  "properties": {
    "iso:country":"GB",
    "wof:name":"BA11 3JL",
    "wof:placetype":"postalcode"
},
  "geometry": {"coordinates":[-2.34543258264623,51.23379654491091],"type":"Point"}
}