{
  "type": "Feature",
  "properties": {
    "iso:country":"GB",
    "wof:name":"SL2 1QX",
    "wof:placetype":"postalcode"
},
  "geometry": {"coordinates":[-0.62419145705959,51.53349668768782],"type":"Point"}
}