{
  "type": "Feature",
  "properties": {
    "iso:country": "GB",
    "wof:name": "SL2 1QX",
    "wof:placetype": "postalcode"
  },
  "geometry": {"coordinates":[-0.624191,51.533497],"type":"Point"}
}
