{
  "type": "Feature",
  "properties": {
    "iso:country":"GB",
    "wof:name":"LD1 6BN",
    "wof:placetype":"postalcode"
},
  "geometry": {"coordinates":[-3.38155849138493,52.24767032545062],"type":"Point"}
}