{
  "type": "Feature",
  "properties": {
    "date:inception_lower": "1980-01-01",
    "date:inception_upper": "1980-01-01",
    "iso:country": "GB",
    "wof:name": "LL76 8SJ",
    "wof:placetype": "postalcode"
  },
  "geometry": {"coordinates":[-4.236101,53.297879],"type":"Point"}
}
