{
  "type": "Feature",
  "properties": {
    "iso:country":"GB",
    "wof:name":"LL76 8SJ",
    "wof:placetype":"postalcode"
},
  "geometry": {"coordinates":[-4.23610146887655,53.2978787620275],"type":"Point"}
}