{
  "type": "Feature",
  "properties": {
    "iso:country": "GB",
    "wof:name": "PR5 0LJ",
    "wof:placetype": "postalcode"
  },
  "geometry": {"coordinates":[-2.635579,53.738497],"type":"Point"}
}
