{
  "type": "Feature",
  "properties": {
    "iso:country":"GB",
    "wof:name":"PR5 0LJ",
    "wof:placetype":"postalcode"
},
  "geometry": {"coordinates":[-2.63557860265502,53.73849719389386],"type":"Point"}
}