{
  "type": "Feature",
  "properties": {
    "iso:country": "GB",
    "wof:name": "TA5 1QY",
    "wof:placetype": "postalcode"
  },
  "geometry": {"coordinates":[-3.142721,51.181912],"type":"Point"}
}
