{
  "type": "Feature",
  "properties": {
    "iso:country":"GB",
    "wof:name":"CV3 6NG",
    "wof:placetype":"postalcode"
},
  "geometry": {"coordinates":[-1.51728084482989,52.38196625938003],"type":"Point"}
}