{
  "type": "Feature",
  "properties": {
    "date:inception_lower": "2018-01-01",
    "date:inception_upper": "2018-01-01",
    "iso:country": "GB",
    "wof:name": "EX2 5FN",
    "wof:placetype": "postalcode"
  },
  "geometry": {"coordinates":[-3.502162,50.717605],"type":"Point"}
}
