{
  "type": "Feature",
  "properties": {
    "date:inception_lower":"1980-01-01",
    "date:inception_upper":"1980-01-31",
    "iso:country":"GB",
    "wof:name":"BD18 2NG",
    "wof:placetype":"postalcode"
},
  "geometry": {"coordinates":[-1.765875,53.833449],"type":"Point"}
}