{
  "type": "Feature",
  "properties": {
    "iso:country":"GB",
    "wof:name":"TS17 9HZ",
    "wof:placetype":"postalcode"
},
  "geometry": {"coordinates":[-1.29247384029858,54.53514961209215],"type":"Point"}
}