{
  "type": "Feature",
  "properties": {
    "iso:country": "GB",
    "wof:name": "TS17 9HZ",
    "wof:placetype": "postalcode"
  },
  "geometry": {"coordinates":[-1.292474,54.53515],"type":"Point"}
}
