{
  "type": "Feature",
  "properties": {
    "date:inception_lower":"1980-01-01",
    "date:inception_upper":"1980-01-31",
    "iso:country":"GB",
    "wof:name":"SP8 5SJ",
    "wof:placetype":"postalcode"
},
  "geometry": {"coordinates":[-2.372418,50.99768],"type":"Point"}
}