{
  "type": "Feature",
  "properties": {
    "iso:country":"GB",
    "wof:name":"S10 1SQ",
    "wof:placetype":"postalcode"
},
  "geometry": {"coordinates":[-1.51187676601339,53.38530834286058],"type":"Point"}
}