{
  "type": "Feature",
  "properties": {
    "iso:country": "GB",
    "wof:name": "SA35 0BH",
    "wof:placetype": "postalcode"
  },
  "geometry": {"coordinates":[-4.555311,51.964645],"type":"Point"}
}
