{
  "type": "Feature",
  "properties": {
    "date:inception_lower":"1998-12-01",
    "date:inception_upper":"1998-12-31",
    "iso:country":"GB",
    "wof:name":"IV3 8HD",
    "wof:placetype":"postalcode"
},
  "geometry": {"coordinates":[-4.234101,57.48392],"type":"Point"}
}