{
  "type": "Feature",
  "properties": {
    "iso:country":"GB",
    "wof:name":"IV3 8HD",
    "wof:placetype":"postalcode"
},
  "geometry": {"coordinates":[-4.23410108581002,57.48391973325019],"type":"Point"}
}