{
  "type": "Feature",
  "properties": {
    "date:inception_lower": "1980-01-01",
    "date:inception_upper": "1980-01-01",
    "iso:country": "GB",
    "wof:name": "RH4 3BG",
    "wof:placetype": "postalcode"
  },
  "geometry": {"coordinates":[-0.335534,51.22323],"type":"Point"}
}
