{
  "type": "Feature",
  "properties": {
    "date:inception_lower": "1998-12-01",
    "date:inception_upper": "1998-12-01",
    "iso:country": "GB",
    "wof:name": "G32 0HY",
    "wof:placetype": "postalcode"
  },
  "geometry": {"coordinates":[-4.154949,55.851845],"type":"Point"}
}
