{
  "type": "Feature",
  "properties": {
    "iso:country":"GB",
    "wof:name":"OX17 2NH",
    "wof:placetype":"postalcode"
},
  "geometry": {"coordinates":[-1.26436059174093,52.07288155640789],"type":"Point"}
}