{
  "type": "Feature",
  "properties": {
    "date:inception_lower": "2000-06-01",
    "date:inception_upper": "2000-06-01",
    "iso:country": "GB",
    "wof:name": "OX17 2NH",
    "wof:placetype": "postalcode"
  },
  "geometry": {"coordinates":[-1.264361,52.072882],"type":"Point"}
}
