{
  "type": "Feature",
  "properties": {
    "iso:country": "GB",
    "wof:name": "RH1 1TL",
    "wof:placetype": "postalcode"
  },
  "geometry": {"coordinates":[-0.160248,51.246837],"type":"Point"}
}
