{
  "type": "Feature",
  "properties": {
    "iso:country":"GB",
    "wof:name":"CF23 9HS",
    "wof:placetype":"postalcode"
},
  "geometry": {"coordinates":[-3.15425880652404,51.50500201432919],"type":"Point"}
}