{
  "type": "Feature",
  "properties": {
    "date:inception_lower":"1980-01-01",
    "date:inception_upper":"1980-01-31",
    "iso:country":"GB",
    "wof:name":"CF32 7PA",
    "wof:placetype":"postalcode"
},
  "geometry": {"coordinates":[-3.539632,51.625059],"type":"Point"}
}