{
  "type": "Feature",
  "properties": {
    "iso:country":"GB",
    "wof:name":"CF32 7PA",
    "wof:placetype":"postalcode"
},
  "geometry": {"coordinates":[-3.53957497942898,51.62501765883717],"type":"Point"}
}