{
  "type": "Feature",
  "properties": {
    "date:inception_lower":"2015-04-01",
    "date:inception_upper":"2015-04-30",
    "iso:country":"GB",
    "wof:name":"DN20 8NU",
    "wof:placetype":"postalcode"
},
  "geometry": {"coordinates":[-0.492356,53.551344],"type":"Point"}
}