{
  "type": "Feature",
  "properties": {
    "iso:country": "GB",
    "wof:name": "DN20 8NU",
    "wof:placetype": "postalcode"
  },
  "geometry": {"coordinates":[-0.492356,53.551344],"type":"Point"}
}
