{
  "type": "Feature",
  "properties": {
    "iso:country":"GB",
    "wof:name":"DN20 8NU",
    "wof:placetype":"postalcode"
},
  "geometry": {"coordinates":[-0.49235588449419,53.55134367007598],"type":"Point"}
}