{
  "type": "Feature",
  "properties": {
    "iso:country":"GB",
    "wof:name":"DY9 8PB",
    "wof:placetype":"postalcode"
},
  "geometry": {"coordinates":[-2.1052114490208,52.45844716828855],"type":"Point"}
}