{
  "type": "Feature",
  "properties": {
    "date:inception_lower": "2015-01-01",
    "date:inception_upper": "2015-01-01",
    "iso:country": "GB",
    "wof:name": "DY9 8PB",
    "wof:placetype": "postalcode"
  },
  "geometry": {"coordinates":[-2.105191,52.458471],"type":"Point"}
}
