{
  "type": "Feature",
  "properties": {
    "date:inception_lower": "1980-01-01",
    "date:inception_upper": "1980-01-01",
    "iso:country": "GB",
    "wof:name": "DH8 6NE",
    "wof:placetype": "postalcode"
  },
  "geometry": {"coordinates":[-1.825671,54.853977],"type":"Point"}
}
