{
  "type": "Feature",
  "properties": {
    "iso:country":"GB",
    "wof:name":"DH8 6NE",
    "wof:placetype":"postalcode"
},
  "geometry": {"coordinates":[-1.8257702737591,54.85393339350309],"type":"Point"}
}