{
  "type": "Feature",
  "properties": {
    "iso:country":"GB",
    "wof:name":"WS10 0AT",
    "wof:placetype":"postalcode"
},
  "geometry": {"coordinates":[-2.02192935506474,52.54800476777977],"type":"Point"}
}