{
  "type": "Feature",
  "properties": {
    "iso:country":"GB",
    "wof:name":"ME5 0DJ",
    "wof:placetype":"postalcode"
},
  "geometry": {"coordinates":[0.53087028469497,51.35883445183288],"type":"Point"}
}