{
  "type": "Feature",
  "properties": {
    "iso:country":"GB",
    "wof:name":"SA44 5SD",
    "wof:placetype":"postalcode"
},
  "geometry": {"coordinates":[-4.40014329319858,52.10596618762204],"type":"Point"}
}