{
  "type": "Feature",
  "properties": {
    "iso:country": "GB",
    "wof:name": "SY6 6PX",
    "wof:placetype": "postalcode"
  },
  "geometry": {"coordinates":[-2.850284,52.49315],"type":"Point"}
}
