{
  "type": "Feature",
  "properties": {
    "iso:country":"GB",
    "wof:name":"NG6 0BH",
    "wof:placetype":"postalcode"
},
  "geometry": {"coordinates":[-1.18564967695831,52.98867277839179],"type":"Point"}
}