{
  "type": "Feature",
  "properties": {
    "date:inception_lower":"1980-01-01",
    "date:inception_upper":"1980-01-31",
    "iso:country":"GB",
    "wof:name":"NG6 0BH",
    "wof:placetype":"postalcode"
},
  "geometry": {"coordinates":[-1.18565,52.988673],"type":"Point"}
}