{
  "type": "Feature",
  "properties": {
    "iso:country":"GB",
    "wof:name":"BR2 8BW",
    "wof:placetype":"postalcode"
},
  "geometry": {"coordinates":[0.06378275398385,51.38724126545466],"type":"Point"}
}