{
  "type": "Feature",
  "properties": {
    "iso:country":"GB",
    "wof:name":"WC2E 9BL",
    "wof:placetype":"postalcode"
},
  "geometry": {"coordinates":[-0.12658888847786,51.51154335481685],"type":"Point"}
}