{
  "type": "Feature",
  "properties": {
    "iso:country":"GB",
    "wof:name":"SK11 7AE",
    "wof:placetype":"postalcode"
},
  "geometry": {"coordinates":[-2.12184025487334,53.25702134165038],"type":"Point"}
}