{
  "type": "Feature",
  "properties": {
    "date:inception_lower":"1983-07-01",
    "date:inception_upper":"1983-07-31",
    "iso:country":"GB",
    "wof:name":"PE14 7HA",
    "wof:placetype":"postalcode"
},
  "geometry": {"coordinates":[0.188173,52.695529],"type":"Point"}
}