{
  "type": "Feature",
  "properties": {
    "iso:country":"GB",
    "wof:name":"PE14 7HA",
    "wof:placetype":"postalcode"
},
  "geometry": {"coordinates":[0.18817262516896,52.6955285802408],"type":"Point"}
}