{
  "type": "Feature",
  "properties": {
    "iso:country": "GB",
    "wof:name": "DL8 1TD",
    "wof:placetype": "postalcode"
  },
  "geometry": {"coordinates":[-1.676532,54.295626],"type":"Point"}
}
