{
  "type": "Feature",
  "properties": {
    "iso:country":"GB",
    "wof:name":"NG24 3QE",
    "wof:placetype":"postalcode"
},
  "geometry": {"coordinates":[-0.78157412840203,53.05713680950594],"type":"Point"}
}