{
  "type": "Feature",
  "properties": {
    "iso:country":"GB",
    "wof:name":"KY16 0UA",
    "wof:placetype":"postalcode"
},
  "geometry": {"coordinates":[-2.89189673535313,56.35904089467308],"type":"Point"}
}