{
  "type": "Feature",
  "properties": {
    "iso:country":"GB",
    "wof:name":"W2 2JW",
    "wof:placetype":"postalcode"
},
  "geometry": {"coordinates":[-0.16809859855568,51.51322417837348],"type":"Point"}
}