{
  "type": "Feature",
  "properties": {
    "iso:country": "GB",
    "wof:name": "RG42 1SR",
    "wof:placetype": "postalcode"
  },
  "geometry": {"coordinates":[-0.770056,51.422573],"type":"Point"}
}
