{
  "type": "Feature",
  "properties": {
    "iso:country":"GB",
    "wof:name":"RG42 1SR",
    "wof:placetype":"postalcode"
},
  "geometry": {"coordinates":[-0.77005632439572,51.42257297578708],"type":"Point"}
}