{
  "type": "Feature",
  "properties": {
    "iso:country":"GB",
    "wof:name":"B3 3HN",
    "wof:placetype":"postalcode"
},
  "geometry": {"coordinates":[-1.90540950459039,52.48152486315343],"type":"Point"}
}