{
  "type": "Feature",
  "properties": {
    "iso:country":"GB",
    "wof:name":"GL4 0JA",
    "wof:placetype":"postalcode"
},
  "geometry": {"coordinates":[-2.24811141027922,51.83568701860906],"type":"Point"}
}