{
  "type": "Feature",
  "properties": {
    "iso:country":"GB",
    "wof:name":"NE47 0BY",
    "wof:placetype":"postalcode"
},
  "geometry": {"coordinates":[-2.03693892086577,54.89747428784537],"type":"Point"}
}