{
  "type": "Feature",
  "properties": {
    "date:inception_lower": "1980-01-01",
    "date:inception_upper": "1980-01-01",
    "iso:country": "GB",
    "wof:name": "GU11 3NP",
    "wof:placetype": "postalcode"
  },
  "geometry": {"coordinates":[-0.768169,51.2486],"type":"Point"}
}
