{
  "type": "Feature",
  "properties": {
    "iso:country":"GB",
    "wof:name":"NE9 6XY",
    "wof:placetype":"postalcode"
},
  "geometry": {"coordinates":[-1.58492612266985,54.93548520315687],"type":"Point"}
}