{
  "type": "Feature",
  "properties": {
    "date:inception_lower":"1980-01-01",
    "date:inception_upper":"1980-01-31",
    "iso:country":"GB",
    "wof:name":"NE9 6XY",
    "wof:placetype":"postalcode"
},
  "geometry": {"coordinates":[-1.584926,54.935485],"type":"Point"}
}