{
  "type": "Feature",
  "properties": {
    "date:inception_lower": "1991-01-01",
    "date:inception_upper": "1991-01-01",
    "iso:country": "GB",
    "wof:name": "NR31 9ET",
    "wof:placetype": "postalcode"
  },
  "geometry": {"coordinates":[1.731541,52.539396],"type":"Point"}
}
