{
  "type": "Feature",
  "properties": {
    "iso:country":"GB",
    "wof:name":"NR31 9ET",
    "wof:placetype":"postalcode"
},
  "geometry": {"coordinates":[1.73154077123787,52.53939641674432],"type":"Point"}
}