{
  "type": "Feature",
  "properties": {
    "iso:country":"GB",
    "wof:name":"AB41 7HP",
    "wof:placetype":"postalcode"
},
  "geometry": {"coordinates":[-2.25694200341251,57.44084588807782],"type":"Point"}
}