{
  "type": "Feature",
  "properties": {
    "iso:country": "GB",
    "wof:name": "AB41 7HP",
    "wof:placetype": "postalcode"
  },
  "geometry": {"coordinates":[-2.256942,57.440846],"type":"Point"}
}
