{
  "type": "Feature",
  "properties": {
    "date:inception_lower": "1980-01-01",
    "date:inception_upper": "1980-01-01",
    "iso:country": "GB",
    "wof:name": "OX12 0AL",
    "wof:placetype": "postalcode"
  },
  "geometry": {"coordinates":[-1.42105,51.61157],"type":"Point"}
}
