{
  "type": "Feature",
  "properties": {
    "iso:country":"GB",
    "wof:name":"OX12 0AL",
    "wof:placetype":"postalcode"
},
  "geometry": {"coordinates":[-1.42105005133535,51.61157036051043],"type":"Point"}
}