{
  "type": "Feature",
  "properties": {
    "iso:country":"GB",
    "wof:name":"LE9 8JG",
    "wof:placetype":"postalcode"
},
  "geometry": {"coordinates":[-1.36079282901064,52.58370793270556],"type":"Point"}
}