{
  "type": "Feature",
  "properties": {
    "iso:country": "GB",
    "wof:name": "WR4 9DU",
    "wof:placetype": "postalcode"
  },
  "geometry": {"coordinates":[-2.187497,52.20737],"type":"Point"}
}
