{
  "type": "Feature",
  "properties": {
    "iso:country":"GB",
    "wof:name":"WR4 9DU",
    "wof:placetype":"postalcode"
},
  "geometry": {"coordinates":[-2.18745792906177,52.20735696815385],"type":"Point"}
}