{
  "type": "Feature",
  "properties": {
    "date:inception_lower": "1980-01-01",
    "date:inception_upper": "1980-01-01",
    "iso:country": "GB",
    "wof:name": "WR4 9DU",
    "wof:placetype": "postalcode"
  },
  "geometry": {"coordinates":[-2.187497,52.20737],"type":"Point"}
}
