{
  "type": "Feature",
  "properties": {
    "date:inception_lower": "1980-01-01",
    "date:inception_upper": "1980-01-01",
    "iso:country": "GB",
    "wof:name": "ME16 8BD",
    "wof:placetype": "postalcode"
  },
  "geometry": {"coordinates":[0.508943,51.273777],"type":"Point"}
}
