{
  "type": "Feature",
  "properties": {
    "iso:country":"GB",
    "wof:name":"ME16 8BD",
    "wof:placetype":"postalcode"
},
  "geometry": {"coordinates":[0.50894300141611,51.27377690149075],"type":"Point"}
}