{
  "type": "Feature",
  "properties": {
    "iso:country":"GB",
    "wof:name":"RG10 0PA",
    "wof:placetype":"postalcode"
},
  "geometry": {"coordinates":[-0.81038701181697,51.46569207080376],"type":"Point"}
}