{
  "type": "Feature",
  "properties": {
    "iso:country":"GB",
    "wof:name":"B90 2LH",
    "wof:placetype":"postalcode"
},
  "geometry": {"coordinates":[-1.83741211109042,52.40923428348663],"type":"Point"}
}