{
  "type": "Feature",
  "properties": {
    "date:inception_lower": "2017-05-01",
    "date:inception_upper": "2017-05-01",
    "iso:country": "GB",
    "wof:name": "EH22 2RH",
    "wof:placetype": "postalcode"
  },
  "geometry": {"coordinates":[-3.050069,55.897268],"type":"Point"}
}
