{
  "type": "Feature",
  "properties": {
    "iso:country":"GB",
    "wof:name":"NG9 7GE",
    "wof:placetype":"postalcode"
},
  "geometry": {"coordinates":[-1.27711256100918,52.92282298064065],"type":"Point"}
}