{
  "type": "Feature",
  "properties": {
    "iso:country":"GB",
    "wof:name":"B97 6TU",
    "wof:placetype":"postalcode"
},
  "geometry": {"coordinates":[-1.96558776789809,52.31174380435672],"type":"Point"}
}