{
  "type": "Feature",
  "properties": {
    "date:inception_lower": "2000-06-01",
    "date:inception_upper": "2000-06-01",
    "iso:country": "GB",
    "wof:name": "B97 6TU",
    "wof:placetype": "postalcode"
  },
  "geometry": {"coordinates":[-1.965588,52.311744],"type":"Point"}
}
