{
  "type": "Feature",
  "properties": {
    "date:inception_lower": "1980-01-01",
    "date:inception_upper": "1980-01-01",
    "iso:country": "GB",
    "wof:name": "TQ14 8AW",
    "wof:placetype": "postalcode"
  },
  "geometry": {"coordinates":[-3.496443,50.546329],"type":"Point"}
}
