{
  "type": "Feature",
  "properties": {
    "iso:country":"GB",
    "wof:name":"TQ14 8AW",
    "wof:placetype":"postalcode"
},
  "geometry": {"coordinates":[-3.49644284727485,50.54632875942445],"type":"Point"}
}