{
  "type": "Feature",
  "properties": {
    "iso:country":"GB",
    "wof:name":"ST3 1QQ",
    "wof:placetype":"postalcode"
},
  "geometry": {"coordinates":[-2.12589698118865,52.98467778868239],"type":"Point"}
}