{
  "type": "Feature",
  "properties": {
    "iso:country":"GB",
    "wof:name":"TS17 5BE",
    "wof:placetype":"postalcode"
},
  "geometry": {"coordinates":[-1.32588577110983,54.5107876814746],"type":"Point"}
}