{
  "type": "Feature",
  "properties": {
    "iso:country": "GB",
    "wof:name": "TS17 5BE",
    "wof:placetype": "postalcode"
  },
  "geometry": {"coordinates":[-1.325886,54.510788],"type":"Point"}
}
