{
  "type": "Feature",
  "properties": {
    "date:inception_lower": "2019-06-01",
    "date:inception_upper": "2019-06-01",
    "iso:country": "GB",
    "wof:name": "SK10 5GN",
    "wof:placetype": "postalcode"
  },
  "geometry": {"coordinates":[-2.097757,53.318292],"type":"Point"}
}
