{
  "type": "Feature",
  "properties": {
    "iso:country": "GB",
    "wof:name": "SK10 5GN",
    "wof:placetype": "postalcode"
  },
  "geometry": {"coordinates":[-2.097757,53.318292],"type":"Point"}
}
