{
  "type": "Feature",
  "properties": {
    "iso:country":"GB",
    "wof:name":"PE19 7LS",
    "wof:placetype":"postalcode"
},
  "geometry": {"coordinates":[-0.28144405071513,52.23197643479447],"type":"Point"}
}