{
  "type": "Feature",
  "properties": {
    "iso:country":"GB",
    "wof:name":"DA7 4AZ",
    "wof:placetype":"postalcode"
},
  "geometry": {"coordinates":[0.13362153952805,51.45952564911609],"type":"Point"}
}