{
  "type": "Feature",
  "properties": {
    "date:inception_lower":"2004-01-01",
    "date:inception_upper":"2004-01-31",
    "iso:country":"GB",
    "wof:name":"SW11 4AW",
    "wof:placetype":"postalcode"
},
  "geometry": {"coordinates":[-0.16954,51.480127],"type":"Point"}
}