{
  "type": "Feature",
  "properties": {
    "iso:country":"GB",
    "wof:name":"CM2 5PD",
    "wof:placetype":"postalcode"
},
  "geometry": {"coordinates":[0.51759673138445,51.75008818417886],"type":"Point"}
}