{
  "type": "Feature",
  "properties": {
    "iso:country": "GB",
    "wof:name": "CM2 5PD",
    "wof:placetype": "postalcode"
  },
  "geometry": {"coordinates":[0.517597,51.750088],"type":"Point"}
}
