{
  "type": "Feature",
  "properties": {
    "date:inception_lower": "1980-01-01",
    "date:inception_upper": "1980-01-01",
    "iso:country": "GB",
    "wof:name": "GL14 1QD",
    "wof:placetype": "postalcode"
  },
  "geometry": {"coordinates":[-2.38743,51.828178],"type":"Point"}
}
