{
  "type": "Feature",
  "properties": {
    "iso:country": "GB",
    "wof:name": "KA26 0LJ",
    "wof:placetype": "postalcode"
  },
  "geometry": {"coordinates":[-4.903864,55.105431],"type":"Point"}
}
