{
  "type": "Feature",
  "properties": {
    "iso:country":"GB",
    "wof:name":"NG5 9DY",
    "wof:placetype":"postalcode"
},
  "geometry": {"coordinates":[-1.16138015361362,53.00649198368918],"type":"Point"}
}