{
  "type": "Feature",
  "properties": {
    "date:inception_lower": "2021-01-01",
    "date:inception_upper": "2021-01-01",
    "iso:country": "GB",
    "wof:name": "PR3 6DH",
    "wof:placetype": "postalcode"
  },
  "geometry": {"coordinates":[-2.887083,53.922906],"type":"Point"}
}
