{
  "type": "Feature",
  "properties": {
    "iso:country": "GB",
    "wof:name": "PE19 1HT",
    "wof:placetype": "postalcode"
  },
  "geometry": {"coordinates":[-0.268191,52.230101],"type":"Point"}
}
