{
  "type": "Feature",
  "properties": {
    "date:inception_lower": "1996-06-01",
    "date:inception_upper": "1996-06-01",
    "iso:country": "GB",
    "wof:name": "PE19 1HT",
    "wof:placetype": "postalcode"
  },
  "geometry": {"coordinates":[-0.268191,52.230101],"type":"Point"}
}
