{
  "type": "Feature",
  "properties": {
    "iso:country":"GB",
    "wof:name":"PE19 1HT",
    "wof:placetype":"postalcode"
},
  "geometry": {"coordinates":[-0.26819139240089,52.23010133810579],"type":"Point"}
}