{
  "type": "Feature",
  "properties": {
    "iso:country":"GB",
    "wof:name":"TS29 6PN",
    "wof:placetype":"postalcode"
},
  "geometry": {"coordinates":[-1.4330713448726,54.70278503474369],"type":"Point"}
}