{
  "type": "Feature",
  "properties": {
    "iso:country": "GB",
    "wof:name": "DN22 9NL",
    "wof:placetype": "postalcode"
  },
  "geometry": {"coordinates":[-0.914053,53.336333],"type":"Point"}
}
