{
  "type": "Feature",
  "properties": {
    "iso:country":"GB",
    "wof:name":"LS27 7HH",
    "wof:placetype":"postalcode"
},
  "geometry": {"coordinates":[-1.63115529210485,53.74904558327533],"type":"Point"}
}