{
  "type": "Feature",
  "properties": {
    "date:inception_lower": "2000-12-01",
    "date:inception_upper": "2000-12-01",
    "iso:country": "GB",
    "wof:name": "CF31 2BY",
    "wof:placetype": "postalcode"
  },
  "geometry": {"coordinates":[-3.558549,51.503662],"type":"Point"}
}
