{
  "type": "Feature",
  "properties": {
    "iso:country": "GB",
    "wof:name": "CF31 2BY",
    "wof:placetype": "postalcode"
  },
  "geometry": {"coordinates":[-3.558549,51.503662],"type":"Point"}
}
