{
  "type": "Feature",
  "properties": {
    "date:inception_lower":"1980-01-01",
    "date:inception_upper":"1980-01-31",
    "iso:country":"GB",
    "wof:name":"B67 6NP",
    "wof:placetype":"postalcode"
},
  "geometry": {"coordinates":[-1.977707,52.482334],"type":"Point"}
}