{
  "type": "Feature",
  "properties": {
    "iso:country":"GB",
    "wof:name":"S81 9SB",
    "wof:placetype":"postalcode"
},
  "geometry": {"coordinates":[-1.12143363176623,53.38029685739959],"type":"Point"}
}