{
  "type": "Feature",
  "properties": {
    "iso:country":"GB",
    "wof:name":"TS12 2PS",
    "wof:placetype":"postalcode"
},
  "geometry": {"coordinates":[-0.93412117380949,54.5685536725769],"type":"Point"}
}