{
  "type": "Feature",
  "properties": {
    "iso:country":"GB",
    "wof:name":"B44 0UL",
    "wof:placetype":"postalcode"
},
  "geometry": {"coordinates":[-1.87596960096298,52.55162799722064],"type":"Point"}
}