{
  "type": "Feature",
  "properties": {
    "iso:country":"GB",
    "wof:name":"YO51 9NA",
    "wof:placetype":"postalcode"
},
  "geometry": {"coordinates":[-1.42778669800326,54.08663360217302],"type":"Point"}
}