{
  "type": "Feature",
  "properties": {
    "iso:country": "GB",
    "wof:name": "YO51 9NA",
    "wof:placetype": "postalcode"
  },
  "geometry": {"coordinates":[-1.427787,54.086634],"type":"Point"}
}
