{
  "type": "Feature",
  "properties": {
    "iso:country": "GB",
    "wof:name": "WA7 5RB",
    "wof:placetype": "postalcode"
  },
  "geometry": {"coordinates":[-2.706275,53.339891],"type":"Point"}
}
