{
  "type": "Feature",
  "properties": {
    "iso:country":"GB",
    "wof:name":"WA7 5RB",
    "wof:placetype":"postalcode"
},
  "geometry": {"coordinates":[-2.70627523625423,53.33989067973107],"type":"Point"}
}