{
  "type": "Feature",
  "properties": {
    "date:inception_lower": "2019-11-01",
    "date:inception_upper": "2019-11-01",
    "iso:country": "GB",
    "wof:name": "BS5 9FN",
    "wof:placetype": "postalcode"
  },
  "geometry": {"coordinates":[-2.557352,51.459427],"type":"Point"}
}
