{
  "type": "Feature",
  "properties": {
    "iso:country": "GB",
    "wof:name": "BS5 9FN",
    "wof:placetype": "postalcode"
  },
  "geometry": {"coordinates":[-2.557438,51.459435],"type":"Point"}
}
