{
  "type": "Feature",
  "properties": {
    "iso:country": "GB",
    "wof:name": "MK43 8JS",
    "wof:placetype": "postalcode"
  },
  "geometry": {"coordinates":[-0.52604,52.151649],"type":"Point"}
}
