{
  "type": "Feature",
  "properties": {
    "iso:country":"GB",
    "wof:name":"MK43 8JS",
    "wof:placetype":"postalcode"
},
  "geometry": {"coordinates":[-0.52604005682985,52.15164872489245],"type":"Point"}
}