{
  "type": "Feature",
  "properties": {
    "iso:country":"GB",
    "wof:name":"CT11 0JA",
    "wof:placetype":"postalcode"
},
  "geometry": {"coordinates":[1.39890567912401,51.33042627823674],"type":"Point"}
}