{
  "type": "Feature",
  "properties": {
    "date:inception_lower":"1980-01-01",
    "date:inception_upper":"1980-01-31",
    "iso:country":"GB",
    "wof:name":"WF2 6PQ",
    "wof:placetype":"postalcode"
},
  "geometry": {"coordinates":[-1.468268,53.651216],"type":"Point"}
}