{
  "type": "Feature",
  "properties": {
    "iso:country":"GB",
    "wof:name":"WF2 6PQ",
    "wof:placetype":"postalcode"
},
  "geometry": {"coordinates":[-1.46838767150499,53.65119103513333],"type":"Point"}
}