{
  "type": "Feature",
  "properties": {
    "iso:country":"GB",
    "wof:name":"LD7 1HD",
    "wof:placetype":"postalcode"
},
  "geometry": {"coordinates":[-3.05501804880551,52.34350965451541],"type":"Point"}
}