{
  "type": "Feature",
  "properties": {
    "iso:country": "GB",
    "wof:name": "LL53 5PP",
    "wof:placetype": "postalcode"
  },
  "geometry": {"coordinates":[-4.429117,52.880773],"type":"Point"}
}
