{
  "type": "Feature",
  "properties": {
    "iso:country":"GB",
    "wof:name":"LL53 5PP",
    "wof:placetype":"postalcode"
},
  "geometry": {"coordinates":[-4.42911660981359,52.88077268218944],"type":"Point"}
}