{
  "type": "Feature",
  "properties": {
    "date:inception_lower": "1986-04-01",
    "date:inception_upper": "1986-04-01",
    "iso:country": "GB",
    "wof:name": "LL53 5PP",
    "wof:placetype": "postalcode"
  },
  "geometry": {"coordinates":[-4.429117,52.880773],"type":"Point"}
}
