{
  "type": "Feature",
  "properties": {
    "iso:country":"GB",
    "wof:name":"WF1 4DX",
    "wof:placetype":"postalcode"
},
  "geometry": {"coordinates":[-1.48982665000758,53.68245553582163],"type":"Point"}
}