{
  "type": "Feature",
  "properties": {
    "iso:country":"GB",
    "wof:name":"TQ12 6DS",
    "wof:placetype":"postalcode"
},
  "geometry": {"coordinates":[-3.66341246120175,50.50804282345835],"type":"Point"}
}