{
  "type": "Feature",
  "properties": {
    "iso:country": "GB",
    "wof:name": "TQ12 6DS",
    "wof:placetype": "postalcode"
  },
  "geometry": {"coordinates":[-3.663412,50.508043],"type":"Point"}
}
