{
  "type": "Feature",
  "properties": {
    "iso:country":"GB",
    "wof:name":"WF10 3RY",
    "wof:placetype":"postalcode"
},
  "geometry": {"coordinates":[-1.30716252702149,53.72733395926104],"type":"Point"}
}