{
  "type": "Feature",
  "properties": {
    "iso:country":"GB",
    "wof:name":"CF14 2NB",
    "wof:placetype":"postalcode"
},
  "geometry": {"coordinates":[-3.22604296696758,51.50451622086558],"type":"Point"}
}