{
  "type": "Feature",
  "properties": {
    "iso:country":"GB",
    "wof:name":"L39 4SZ",
    "wof:placetype":"postalcode"
},
  "geometry": {"coordinates":[-2.90017406902314,53.5593231675756],"type":"Point"}
}