{
  "type": "Feature",
  "properties": {
    "iso:country":"GB",
    "wof:name":"NW6 3HA",
    "wof:placetype":"postalcode"
},
  "geometry": {"coordinates":[-0.18063962799689,51.54317536486673],"type":"Point"}
}