{
  "type": "Feature",
  "properties": {
    "iso:country":"GB",
    "wof:name":"LE16 8UE",
    "wof:placetype":"postalcode"
},
  "geometry": {"coordinates":[-0.83915434791717,52.5619167470457],"type":"Point"}
}