{
  "type": "Feature",
  "properties": {
    "date:inception_lower": "1980-01-01",
    "date:inception_upper": "1980-01-01",
    "iso:country": "GB",
    "wof:name": "LE16 8UE",
    "wof:placetype": "postalcode"
  },
  "geometry": {"coordinates":[-0.839154,52.561917],"type":"Point"}
}
