{
  "type": "Feature",
  "properties": {
    "iso:country": "GB",
    "wof:name": "NE19 1HT",
    "wof:placetype": "postalcode"
  },
  "geometry": {"coordinates":[-2.181006,55.23523],"type":"Point"}
}
