{
  "type": "Feature",
  "properties": {
    "iso:country":"GB",
    "wof:name":"NE19 1HT",
    "wof:placetype":"postalcode"
},
  "geometry": {"coordinates":[-2.18100560882187,55.23523004950388],"type":"Point"}
}