{
  "type": "Feature",
  "properties": {
    "date:inception_lower": "2001-12-01",
    "date:inception_upper": "2001-12-01",
    "iso:country": "GB",
    "wof:name": "NE19 1HT",
    "wof:placetype": "postalcode"
  },
  "geometry": {"coordinates":[-2.181006,55.23523],"type":"Point"}
}
