{
  "type": "Feature",
  "properties": {
    "date:inception_lower": "2007-03-01",
    "date:inception_upper": "2007-03-01",
    "iso:country": "GB",
    "wof:name": "HP2 7FW",
    "wof:placetype": "postalcode"
  },
  "geometry": {"coordinates":[-0.444802,51.77056],"type":"Point"}
}
