{
  "type": "Feature",
  "properties": {
    "iso:country":"GB",
    "wof:name":"HP2 7FW",
    "wof:placetype":"postalcode"
},
  "geometry": {"coordinates":[-0.44480167974887,51.7705597998277],"type":"Point"}
}