{
  "type": "Feature",
  "properties": {
    "iso:country":"GB",
    "wof:name":"PE29 6HR",
    "wof:placetype":"postalcode"
},
  "geometry": {"coordinates":[-0.19133740358614,52.33684518039865],"type":"Point"}
}