{
  "type": "Feature",
  "properties": {
    "iso:country":"GB",
    "wof:name":"EN1 2EY",
    "wof:placetype":"postalcode"
},
  "geometry": {"coordinates":[-0.07957239036588,51.64076040258096],"type":"Point"}
}