{
  "type": "Feature",
  "properties": {
    "date:inception_lower": "1980-01-01",
    "date:inception_upper": "1980-01-01",
    "iso:country": "GB",
    "wof:name": "GU3 1AR",
    "wof:placetype": "postalcode"
  },
  "geometry": {"coordinates":[-0.666859,51.222131],"type":"Point"}
}
