{
  "type": "Feature",
  "properties": {
    "iso:country": "GB",
    "wof:name": "GU3 1AR",
    "wof:placetype": "postalcode"
  },
  "geometry": {"coordinates":[-0.666859,51.222131],"type":"Point"}
}
