{
  "type": "Feature",
  "properties": {
    "iso:country":"GB",
    "wof:name":"GU3 1AR",
    "wof:placetype":"postalcode"
},
  "geometry": {"coordinates":[-0.66685953814641,51.22213120295708],"type":"Point"}
}