{
  "type": "Feature",
  "properties": {
    "iso:country":"GB",
    "wof:name":"DN16 1AX",
    "wof:placetype":"postalcode"
},
  "geometry": {"coordinates":[-0.62383561648447,53.57679468434394],"type":"Point"}
}