{
  "type": "Feature",
  "properties": {
    "iso:country":"GB",
    "wof:name":"DL8 2HA",
    "wof:placetype":"postalcode"
},
  "geometry": {"coordinates":[-1.54966018485013,54.27810781513409],"type":"Point"}
}