{
  "type": "Feature",
  "properties": {
    "iso:country": "GB",
    "wof:name": "DL8 2HA",
    "wof:placetype": "postalcode"
  },
  "geometry": {"coordinates":[-1.549684,54.278129],"type":"Point"}
}
