{
  "type": "Feature",
  "properties": {
    "date:inception_lower":"1980-01-01",
    "date:inception_upper":"1980-01-31",
    "iso:country":"GB",
    "wof:name":"DL8 2HA",
    "wof:placetype":"postalcode"
},
  "geometry": {"coordinates":[-1.549684,54.278129],"type":"Point"}
}