{
  "type": "Feature",
  "properties": {
    "iso:country":"GB",
    "wof:name":"LA20 6AZ",
    "wof:placetype":"postalcode"
},
  "geometry": {"coordinates":[-3.19609862556521,54.3135931080271],"type":"Point"}
}