{
  "type": "Feature",
  "properties": {
    "iso:country":"GB",
    "wof:name":"DY8 5AQ",
    "wof:placetype":"postalcode"
},
  "geometry": {"coordinates":[-2.16155080891837,52.47532065258697],"type":"Point"}
}