{
  "type": "Feature",
  "properties": {
    "date:inception_lower":"1980-01-01",
    "date:inception_upper":"1980-01-31",
    "iso:country":"GB",
    "wof:name":"DY8 5AQ",
    "wof:placetype":"postalcode"
},
  "geometry": {"coordinates":[-2.161427,52.475353],"type":"Point"}
}