{
  "type": "Feature",
  "properties": {
    "iso:country":"GB",
    "wof:name":"IP2 0EL",
    "wof:placetype":"postalcode"
},
  "geometry": {"coordinates":[1.13889142290876,52.05363432779498],"type":"Point"}
}