{
  "type": "Feature",
  "properties": {
    "date:inception_lower": "1984-10-01",
    "date:inception_upper": "1984-10-01",
    "iso:country": "GB",
    "wof:name": "RG6 3DY",
    "wof:placetype": "postalcode"
  },
  "geometry": {"coordinates":[-0.918899,51.43055],"type":"Point"}
}
