{
  "type": "Feature",
  "properties": {
    "iso:country":"GB",
    "wof:name":"RG6 3DY",
    "wof:placetype":"postalcode"
},
  "geometry": {"coordinates":[-0.91889903396588,51.43055015572235],"type":"Point"}
}