{
  "type": "Feature",
  "properties": {
    "iso:country": "GB",
    "wof:name": "LL24 0NY",
    "wof:placetype": "postalcode"
  },
  "geometry": {"coordinates":[-3.736929,53.019017],"type":"Point"}
}
