{
  "type": "Feature",
  "properties": {
    "iso:country":"GB",
    "wof:name":"B96 6HN",
    "wof:placetype":"postalcode"
},
  "geometry": {"coordinates":[-1.98833910317333,52.25092007696615],"type":"Point"}
}