{
  "type": "Feature",
  "properties": {
    "iso:country":"GB",
    "wof:name":"M24 1LB",
    "wof:placetype":"postalcode"
},
  "geometry": {"coordinates":[-2.20276929023372,53.5383073859995],"type":"Point"}
}