{
  "type": "Feature",
  "properties": {
    "iso:country":"GB",
    "wof:name":"BH1 4AE",
    "wof:placetype":"postalcode"
},
  "geometry": {"coordinates":[-1.84392376466246,50.72524055242646],"type":"Point"}
}