{
  "type": "Feature",
  "properties": {
    "iso:country":"GB",
    "wof:name":"NE63 8DH",
    "wof:placetype":"postalcode"
},
  "geometry": {"coordinates":[-1.57941449436009,55.17777788980364],"type":"Point"}
}