{
  "type": "Feature",
  "properties": {
    "iso:country": "GB",
    "wof:name": "NE63 8DH",
    "wof:placetype": "postalcode"
  },
  "geometry": {"coordinates":[-1.579414,55.177778],"type":"Point"}
}
