{
  "type": "Feature",
  "properties": {
    "date:inception_lower": "1980-01-01",
    "date:inception_upper": "1980-01-01",
    "iso:country": "GB",
    "wof:name": "NE63 8DH",
    "wof:placetype": "postalcode"
  },
  "geometry": {"coordinates":[-1.579414,55.177778],"type":"Point"}
}
