{
  "type": "Feature",
  "properties": {
    "iso:country": "GB",
    "wof:name": "SG19 3AX",
    "wof:placetype": "postalcode"
  },
  "geometry": {"coordinates":[-0.146466,52.187485],"type":"Point"}
}
