{
  "type": "Feature",
  "properties": {
    "date:inception_lower": "2009-06-01",
    "date:inception_upper": "2009-06-01",
    "iso:country": "GB",
    "wof:name": "L28 5RY",
    "wof:placetype": "postalcode"
  },
  "geometry": {"coordinates":[-2.860081,53.435889],"type":"Point"}
}
