{
  "type": "Feature",
  "properties": {
    "date:inception_lower": "1981-06-01",
    "date:inception_upper": "1981-06-01",
    "iso:country": "GB",
    "wof:name": "IP25 6BN",
    "wof:placetype": "postalcode"
  },
  "geometry": {"coordinates":[0.821388,52.566714],"type":"Point"}
}
