{
  "type": "Feature",
  "properties": {
    "iso:country":"GB",
    "wof:name":"WC1N 1DP",
    "wof:placetype":"postalcode"
},
  "geometry": {"coordinates":[-0.11666502423257,51.52433366048614],"type":"Point"}
}