{
  "type": "Feature",
  "properties": {
    "iso:country": "GB",
    "wof:name": "OX26 2LA",
    "wof:placetype": "postalcode"
  },
  "geometry": {"coordinates":[-1.165782,51.900813],"type":"Point"}
}
