{
  "type": "Feature",
  "properties": {
    "iso:country":"GB",
    "wof:name":"GU1 4QS",
    "wof:placetype":"postalcode"
},
  "geometry": {"coordinates":[-0.57742724321185,51.23988162030236],"type":"Point"}
}