{
  "type": "Feature",
  "properties": {
    "iso:country": "GB",
    "wof:name": "NG5 9PZ",
    "wof:placetype": "postalcode"
  },
  "geometry": {"coordinates":[-1.156175,53.015103],"type":"Point"}
}
