{
  "type": "Feature",
  "properties": {
    "iso:country":"GB",
    "wof:name":"NG5 9PZ",
    "wof:placetype":"postalcode"
},
  "geometry": {"coordinates":[-1.15617502573344,53.01510299276811],"type":"Point"}
}