{
  "type": "Feature",
  "properties": {
    "date:inception_lower": "1980-01-01",
    "date:inception_upper": "1980-01-01",
    "iso:country": "GB",
    "wof:name": "NG15 0AA",
    "wof:placetype": "postalcode"
  },
  "geometry": {"coordinates":[-1.233621,53.076799],"type":"Point"}
}
