{
  "type": "Feature",
  "properties": {
    "iso:country": "GB",
    "wof:name": "NG15 0AA",
    "wof:placetype": "postalcode"
  },
  "geometry": {"coordinates":[-1.233621,53.076799],"type":"Point"}
}
