{
  "type": "Feature",
  "properties": {
    "iso:country":"GB",
    "wof:name":"NG15 0AA",
    "wof:placetype":"postalcode"
},
  "geometry": {"coordinates":[-1.2336215007862,53.07679939168034],"type":"Point"}
}