{
  "type": "Feature",
  "properties": {
    "date:inception_lower":"1980-01-01",
    "date:inception_upper":"1980-01-31",
    "iso:country":"GB",
    "wof:name":"BN8 5HH",
    "wof:placetype":"postalcode"
},
  "geometry": {"coordinates":[0.05519,50.891909],"type":"Point"}
}