{
  "type": "Feature",
  "properties": {
    "iso:country":"GB",
    "wof:name":"BN8 5HH",
    "wof:placetype":"postalcode"
},
  "geometry": {"coordinates":[0.05519020835204,50.89190940401147],"type":"Point"}
}