{
  "type": "Feature",
  "properties": {
    "date:inception_lower": "1980-01-01",
    "date:inception_upper": "1980-01-01",
    "iso:country": "GB",
    "wof:name": "SY3 7ND",
    "wof:placetype": "postalcode"
  },
  "geometry": {"coordinates":[-2.747215,52.699084],"type":"Point"}
}
