{
  "type": "Feature",
  "properties": {
    "iso:country":"GB",
    "wof:name":"SY3 7ND",
    "wof:placetype":"postalcode"
},
  "geometry": {"coordinates":[-2.74709753647645,52.6989803053287],"type":"Point"}
}