{
  "type": "Feature",
  "properties": {
    "iso:country":"GB",
    "wof:name":"L36 5XS",
    "wof:placetype":"postalcode"
},
  "geometry": {"coordinates":[-2.84631326946238,53.40285436899863],"type":"Point"}
}