{
  "type": "Feature",
  "properties": {
    "iso:country":"GB",
    "wof:name":"OX4 1HS",
    "wof:placetype":"postalcode"
},
  "geometry": {"coordinates":[-1.24198591051384,51.74945881327465],"type":"Point"}
}