{
  "type": "Feature",
  "properties": {
    "iso:country":"GB",
    "wof:name":"HP22 5HP",
    "wof:placetype":"postalcode"
},
  "geometry": {"coordinates":[-0.72162810236802,51.7995487375284],"type":"Point"}
}