{
  "type": "Feature",
  "properties": {
    "date:inception_lower": "1995-01-01",
    "date:inception_upper": "1995-01-01",
    "iso:country": "GB",
    "wof:name": "N14 4HN",
    "wof:placetype": "postalcode"
  },
  "geometry": {"coordinates":[-0.14602,51.643423],"type":"Point"}
}
