{
  "type": "Feature",
  "properties": {
    "iso:country": "GB",
    "wof:name": "SW16 2XT",
    "wof:placetype": "postalcode"
  },
  "geometry": {"coordinates":[-0.119424,51.428616],"type":"Point"}
}
