{
  "type": "Feature",
  "properties": {
    "iso:country":"GB",
    "wof:name":"SW16 2XT",
    "wof:placetype":"postalcode"
},
  "geometry": {"coordinates":[-0.11942391271938,51.42861592412834],"type":"Point"}
}