{
  "type": "Feature",
  "properties": {
    "iso:country": "GB",
    "wof:name": "ME2 3TA",
    "wof:placetype": "postalcode"
  },
  "geometry": {"coordinates":[0.47532,51.399548],"type":"Point"}
}
