{
  "type": "Feature",
  "properties": {
    "iso:country":"GB",
    "wof:name":"LL62 5NE",
    "wof:placetype":"postalcode"
},
  "geometry": {"coordinates":[-4.40323044203895,53.20523771885693],"type":"Point"}
}