{
  "type": "Feature",
  "properties": {
    "date:inception_lower": "1980-01-01",
    "date:inception_upper": "1980-01-01",
    "iso:country": "GB",
    "wof:name": "LL62 5NE",
    "wof:placetype": "postalcode"
  },
  "geometry": {"coordinates":[-4.403367,53.205433],"type":"Point"}
}
