{
  "type": "Feature",
  "properties": {
    "iso:country":"GB",
    "wof:name":"LS8 1JZ",
    "wof:placetype":"postalcode"
},
  "geometry": {"coordinates":[-1.51359876585143,53.83334794153567],"type":"Point"}
}