{
  "type": "Feature",
  "properties": {
    "iso:country":"GB",
    "wof:name":"TR11 5HF",
    "wof:placetype":"postalcode"
},
  "geometry": {"coordinates":[-5.10813279432696,50.11782708904769],"type":"Point"}
}