{
  "type": "Feature",
  "properties": {
    "date:inception_lower":"1980-01-01",
    "date:inception_upper":"1980-01-31",
    "iso:country":"GB",
    "wof:name":"TR11 5HF",
    "wof:placetype":"postalcode"
},
  "geometry": {"coordinates":[-5.108133,50.117827],"type":"Point"}
}