{
  "type": "Feature",
  "properties": {
    "iso:country": "GB",
    "wof:name": "NR23 1EP",
    "wof:placetype": "postalcode"
  },
  "geometry": {"coordinates":[0.852586,52.953723],"type":"Point"}
}
