{
  "type": "Feature",
  "properties": {
    "iso:country":"GB",
    "wof:name":"OL12 9TY",
    "wof:placetype":"postalcode"
},
  "geometry": {"coordinates":[-2.15659808724595,53.63631319181126],"type":"Point"}
}