{
  "type": "Feature",
  "properties": {
    "iso:country": "GB",
    "wof:name": "WR2 5NN",
    "wof:placetype": "postalcode"
  },
  "geometry": {"coordinates":[-2.235179,52.193498],"type":"Point"}
}
