{
  "type": "Feature",
  "properties": {
    "iso:country":"GB",
    "wof:name":"WR2 5NN",
    "wof:placetype":"postalcode"
},
  "geometry": {"coordinates":[-2.23517878164687,52.19349811356005],"type":"Point"}
}