{
  "type": "Feature",
  "properties": {
    "date:inception_lower": "1980-01-01",
    "date:inception_upper": "1980-01-01",
    "iso:country": "GB",
    "wof:name": "WA11 0XL",
    "wof:placetype": "postalcode"
  },
  "geometry": {"coordinates":[-2.670701,53.464527],"type":"Point"}
}
