{
  "type": "Feature",
  "properties": {
    "date:inception_lower": "2023-12-01",
    "date:inception_upper": "2023-12-01",
    "iso:country": "GB",
    "wof:name": "DN35 8BY",
    "wof:placetype": "postalcode"
  },
  "geometry": {"coordinates":[-0.031348,53.561767],"type":"Point"}
}
