{
  "type": "Feature",
  "properties": {
    "date:inception_lower": "1983-07-01",
    "date:inception_upper": "1983-07-01",
    "iso:country": "GB",
    "wof:name": "B74 4XH",
    "wof:placetype": "postalcode"
  },
  "geometry": {"coordinates":[-1.849207,52.601805],"type":"Point"}
}
