{
  "type": "Feature",
  "properties": {
    "iso:country":"GB",
    "wof:name":"B74 4XH",
    "wof:placetype":"postalcode"
},
  "geometry": {"coordinates":[-1.84920707709374,52.60180512994639],"type":"Point"}
}