{
  "type": "Feature",
  "properties": {
    "date:inception_lower": "1983-01-01",
    "date:inception_upper": "1983-01-01",
    "iso:country": "GB",
    "wof:name": "SK9 2QH",
    "wof:placetype": "postalcode"
  },
  "geometry": {"coordinates":[-2.212053,53.333713],"type":"Point"}
}
