{
  "type": "Feature",
  "properties": {
    "iso:country":"GB",
    "wof:name":"LU3 3JS",
    "wof:placetype":"postalcode"
},
  "geometry": {"coordinates":[-0.4666715079815,51.92097233961778],"type":"Point"}
}