{
  "type": "Feature",
  "properties": {
    "iso:country": "GB",
    "wof:name": "CB8 8AZ",
    "wof:placetype": "postalcode"
  },
  "geometry": {"coordinates":[0.409581,52.240985],"type":"Point"}
}
