{
  "type": "Feature",
  "properties": {
    "iso:country":"GB",
    "wof:name":"LU7 3AD",
    "wof:placetype":"postalcode"
},
  "geometry": {"coordinates":[-0.65870021021838,51.92708440888433],"type":"Point"}
}