{
  "type": "Feature",
  "properties": {
    "iso:country":"GB",
    "wof:name":"S60 2NE",
    "wof:placetype":"postalcode"
},
  "geometry": {"coordinates":[-1.35231654371107,53.42863935793623],"type":"Point"}
}