{
  "type": "Feature",
  "properties": {
    "date:inception_lower":"1981-06-01",
    "date:inception_upper":"1981-06-30",
    "iso:country":"GB",
    "wof:name":"CT6 7TF",
    "wof:placetype":"postalcode"
},
  "geometry": {"coordinates":[1.137558,51.346792],"type":"Point"}
}