{
  "type": "Feature",
  "properties": {
    "iso:country":"GB",
    "wof:name":"CT6 7TF",
    "wof:placetype":"postalcode"
},
  "geometry": {"coordinates":[1.13755824268924,51.3467916968839],"type":"Point"}
}