{
  "type": "Feature",
  "properties": {
    "date:inception_lower":"1980-01-01",
    "date:inception_upper":"1980-01-31",
    "iso:country":"GB",
    "wof:name":"YO21 3DZ",
    "wof:placetype":"postalcode"
},
  "geometry": {"coordinates":[-0.626538,54.487665],"type":"Point"}
}