{
  "type": "Feature",
  "properties": {
    "iso:country": "GB",
    "wof:name": "NN6 9SX",
    "wof:placetype": "postalcode"
  },
  "geometry": {"coordinates":[-0.811222,52.331465],"type":"Point"}
}
