{
  "type": "Feature",
  "properties": {
    "iso:country":"GB",
    "wof:name":"NN6 9SX",
    "wof:placetype":"postalcode"
},
  "geometry": {"coordinates":[-0.81122221491489,52.33146474348219],"type":"Point"}
}