{
  "type": "Feature",
  "properties": {
    "iso:country":"GB",
    "wof:name":"RG6 7EY",
    "wof:placetype":"postalcode"
},
  "geometry": {"coordinates":[-0.90868694331497,51.4341242568378],"type":"Point"}
}