{
  "type": "Feature",
  "properties": {
    "iso:country":"GB",
    "wof:name":"PA7 5NP",
    "wof:placetype":"postalcode"
},
  "geometry": {"coordinates":[-4.48874634260972,55.90206006352439],"type":"Point"}
}