{
  "type": "Feature",
  "properties": {
    "iso:country": "GB",
    "wof:name": "S36 6PH",
    "wof:placetype": "postalcode"
  },
  "geometry": {"coordinates":[-1.61587,53.52244],"type":"Point"}
}
