{
  "type": "Feature",
  "properties": {
    "date:inception_lower": "1997-06-01",
    "date:inception_upper": "1997-06-01",
    "iso:country": "GB",
    "wof:name": "S36 6PH",
    "wof:placetype": "postalcode"
  },
  "geometry": {"coordinates":[-1.61587,53.52244],"type":"Point"}
}
