{
  "type": "Feature",
  "properties": {
    "iso:country":"GB",
    "wof:name":"S36 6PH",
    "wof:placetype":"postalcode"
},
  "geometry": {"coordinates":[-1.61587002911928,53.52243953118298],"type":"Point"}
}