{
  "type": "Feature",
  "properties": {
    "iso:country":"GB",
    "wof:name":"BN24 6NR",
    "wof:placetype":"postalcode"
},
  "geometry": {"coordinates":[0.36383775518316,50.81669484718908],"type":"Point"}
}