{
  "type": "Feature",
  "properties": {
    "date:inception_lower": "2021-02-01",
    "date:inception_upper": "2021-02-01",
    "iso:country": "GB",
    "wof:name": "AB25 1PW",
    "wof:placetype": "postalcode"
  },
  "geometry": {"coordinates":[-2.109498,57.148879],"type":"Point"}
}
