{
  "type": "Feature",
  "properties": {
    "iso:country": "GB",
    "wof:name": "KT16 8JS",
    "wof:placetype": "postalcode"
  },
  "geometry": {"coordinates":[-0.493805,51.386779],"type":"Point"}
}
