{
  "type": "Feature",
  "properties": {
    "iso:country": "GB",
    "wof:name": "NE5 2YB",
    "wof:placetype": "postalcode"
  },
  "geometry": {"coordinates":[-1.692933,54.99223],"type":"Point"}
}
