{
  "type": "Feature",
  "properties": {
    "iso:country":"GB",
    "wof:name":"NE5 2YB",
    "wof:placetype":"postalcode"
},
  "geometry": {"coordinates":[-1.69293350162258,54.9922304205277],"type":"Point"}
}