{
  "type": "Feature",
  "properties": {
    "date:inception_lower": "2006-02-01",
    "date:inception_upper": "2006-02-01",
    "iso:country": "GB",
    "wof:name": "G51 4FD",
    "wof:placetype": "postalcode"
  },
  "geometry": {"coordinates":[-4.350517,55.859678],"type":"Point"}
}
