{
  "type": "Feature",
  "properties": {
    "iso:country": "GB",
    "wof:name": "ME9 9ST",
    "wof:placetype": "postalcode"
  },
  "geometry": {"coordinates":[0.808956,51.33142],"type":"Point"}
}
