{
  "type": "Feature",
  "properties": {
    "date:inception_lower":"1980-01-01",
    "date:inception_upper":"1980-01-31",
    "iso:country":"GB",
    "wof:name":"ME9 9ST",
    "wof:placetype":"postalcode"
},
  "geometry": {"coordinates":[0.808956,51.33142],"type":"Point"}
}