{
  "type": "Feature",
  "properties": {
    "iso:country":"GB",
    "wof:name":"M9 8GD",
    "wof:placetype":"postalcode"
},
  "geometry": {"coordinates":[-2.23375475305443,53.52885791406815],"type":"Point"}
}