{
  "type": "Feature",
  "properties": {
    "iso:country": "GB",
    "wof:name": "M9 8GD",
    "wof:placetype": "postalcode"
  },
  "geometry": {"coordinates":[-2.233755,53.528858],"type":"Point"}
}
