{
  "type": "Feature",
  "properties": {
    "iso:country":"GB",
    "wof:name":"TN16 1HL",
    "wof:placetype":"postalcode"
},
  "geometry": {"coordinates":[0.10235484043067,51.27479884382495],"type":"Point"}
}