{
  "type": "Feature",
  "properties": {
    "iso:country":"GB",
    "wof:name":"TR1 2QU",
    "wof:placetype":"postalcode"
},
  "geometry": {"coordinates":[-5.05155643565071,50.26305489116158],"type":"Point"}
}