{
  "type": "Feature",
  "properties": {
    "iso:country":"GB",
    "wof:name":"HP4 1NW",
    "wof:placetype":"postalcode"
},
  "geometry": {"coordinates":[-0.54704519188779,51.78340428308337],"type":"Point"}
}