{
  "type": "Feature",
  "properties": {
    "date:inception_lower":"1980-01-01",
    "date:inception_upper":"1980-01-31",
    "iso:country":"GB",
    "wof:name":"HP4 1NW",
    "wof:placetype":"postalcode"
},
  "geometry": {"coordinates":[-0.547045,51.783404],"type":"Point"}
}