{
  "type": "Feature",
  "properties": {
    "iso:country": "GB",
    "wof:name": "GU3 3DE",
    "wof:placetype": "postalcode"
  },
  "geometry": {"coordinates":[-0.625408,51.249192],"type":"Point"}
}
