{
  "type": "Feature",
  "properties": {
    "iso:country":"GB",
    "wof:name":"GU3 3DE",
    "wof:placetype":"postalcode"
},
  "geometry": {"coordinates":[-0.62491018759318,51.24923463852489],"type":"Point"}
}