{
  "type": "Feature",
  "properties": {
    "iso:country":"GB",
    "wof:name":"ST1 2HR",
    "wof:placetype":"postalcode"
},
  "geometry": {"coordinates":[-2.16945810746808,53.02845475817706],"type":"Point"}
}