{
  "type": "Feature",
  "properties": {
    "iso:country":"GB",
    "wof:name":"LL55 3NR",
    "wof:placetype":"postalcode"
},
  "geometry": {"coordinates":[-4.15437791465479,53.14222752266664],"type":"Point"}
}