{
  "type": "Feature",
  "properties": {
    "date:inception_lower": "1980-01-01",
    "date:inception_upper": "1980-01-01",
    "iso:country": "GB",
    "wof:name": "LL55 3NR",
    "wof:placetype": "postalcode"
  },
  "geometry": {"coordinates":[-4.154378,53.142228],"type":"Point"}
}
