{
  "type": "Feature",
  "properties": {
    "iso:country":"GB",
    "wof:name":"CT21 5NR",
    "wof:placetype":"postalcode"
},
  "geometry": {"coordinates":[1.08445439424085,51.07064432542379],"type":"Point"}
}