{
  "type": "Feature",
  "properties": {
    "date:inception_lower": "2006-07-01",
    "date:inception_upper": "2006-07-01",
    "iso:country": "GB",
    "wof:name": "M18 7GB",
    "wof:placetype": "postalcode"
  },
  "geometry": {"coordinates":[-2.172357,53.450799],"type":"Point"}
}
