{
  "type": "Feature",
  "properties": {
    "iso:country":"GB",
    "wof:name":"BR6 9AN",
    "wof:placetype":"postalcode"
},
  "geometry": {"coordinates":[0.0999201487654,51.371320035829],"type":"Point"}
}