{
  "type": "Feature",
  "properties": {
    "iso:country":"GB",
    "wof:name":"DH6 3SL",
    "wof:placetype":"postalcode"
},
  "geometry": {"coordinates":[-1.42003949118366,54.74607533814001],"type":"Point"}
}