{
  "type": "Feature",
  "properties": {
    "iso:country":"GB",
    "wof:name":"B75 6ES",
    "wof:placetype":"postalcode"
},
  "geometry": {"coordinates":[-1.8051404920889,52.57362980857503],"type":"Point"}
}