{
  "type": "Feature",
  "properties": {
    "iso:country":"GB",
    "wof:name":"SM1 1NS",
    "wof:placetype":"postalcode"
},
  "geometry": {"coordinates":[-0.19352714804059,51.36464799605186],"type":"Point"}
}