{
  "type": "Feature",
  "properties": {
    "date:inception_lower": "2002-07-01",
    "date:inception_upper": "2002-07-01",
    "iso:country": "GB",
    "wof:name": "AB24 5EB",
    "wof:placetype": "postalcode"
  },
  "geometry": {"coordinates":[-2.084624,57.151519],"type":"Point"}
}
