{
  "type": "Feature",
  "properties": {
    "iso:country":"GB",
    "wof:name":"LL40 1NY",
    "wof:placetype":"postalcode"
},
  "geometry": {"coordinates":[-3.88194239737721,52.73992422626807],"type":"Point"}
}