{
  "type": "Feature",
  "properties": {
    "date:inception_lower": "2024-07-01",
    "date:inception_upper": "2024-07-01",
    "iso:country": "GB",
    "wof:name": "LN2 4HH",
    "wof:placetype": "postalcode"
  },
  "geometry": {"coordinates":[-0.49462,53.24027],"type":"Point"}
}
