{
  "type": "Feature",
  "properties": {
    "date:inception_lower":"2001-12-01",
    "date:inception_upper":"2001-12-31",
    "iso:country":"GB",
    "wof:name":"CA2 5TP",
    "wof:placetype":"postalcode"
},
  "geometry": {"coordinates":[-2.94694,54.893878],"type":"Point"}
}