{
  "type": "Feature",
  "properties": {
    "iso:country": "GB",
    "wof:name": "CA2 5TP",
    "wof:placetype": "postalcode"
  },
  "geometry": {"coordinates":[-2.94694,54.893878],"type":"Point"}
}
