{
  "type": "Feature",
  "properties": {
    "iso:country":"GB",
    "wof:name":"CA2 5TP",
    "wof:placetype":"postalcode"
},
  "geometry": {"coordinates":[-2.9469402656537,54.89387797678993],"type":"Point"}
}