{
  "type": "Feature",
  "properties": {
    "iso:country":"GB",
    "wof:name":"GL2 8LX",
    "wof:placetype":"postalcode"
},
  "geometry": {"coordinates":[-2.29254812772762,51.88231070393412],"type":"Point"}
}