{
  "type": "Feature",
  "properties": {
    "iso:country":"GB",
    "wof:name":"BS9 4NP",
    "wof:placetype":"postalcode"
},
  "geometry": {"coordinates":[-2.60728390506045,51.48880744807844],"type":"Point"}
}