{
  "type": "Feature",
  "properties": {
    "date:inception_lower": "1980-01-01",
    "date:inception_upper": "1980-01-01",
    "iso:country": "GB",
    "wof:name": "BS9 4NP",
    "wof:placetype": "postalcode"
  },
  "geometry": {"coordinates":[-2.607284,51.488807],"type":"Point"}
}
