{
  "type": "Feature",
  "properties": {
    "iso:country":"GB",
    "wof:name":"S3 7EU",
    "wof:placetype":"postalcode"
},
  "geometry": {"coordinates":[-1.48138770014876,53.38766973168315],"type":"Point"}
}