{
  "type": "Feature",
  "properties": {
    "iso:country":"GB",
    "wof:name":"TS29 6HD",
    "wof:placetype":"postalcode"
},
  "geometry": {"coordinates":[-1.42815303351245,54.7115509733043],"type":"Point"}
}