{
  "type": "Feature",
  "properties": {
    "iso:country": "GB",
    "wof:name": "SA19 9HB",
    "wof:placetype": "postalcode"
  },
  "geometry": {"coordinates":[-3.850928,51.920085],"type":"Point"}
}
