{
  "type": "Feature",
  "properties": {
    "date:inception_lower": "1980-01-01",
    "date:inception_upper": "1980-01-01",
    "iso:country": "GB",
    "wof:name": "NE35 9DY",
    "wof:placetype": "postalcode"
  },
  "geometry": {"coordinates":[-1.452175,54.948871],"type":"Point"}
}
