{
  "type": "Feature",
  "properties": {
    "iso:country": "GB",
    "wof:name": "BH21 1RP",
    "wof:placetype": "postalcode"
  },
  "geometry": {"coordinates":[-1.976686,50.781609],"type":"Point"}
}
