{
  "type": "Feature",
  "properties": {
    "iso:country":"GB",
    "wof:name":"BH21 1RP",
    "wof:placetype":"postalcode"
},
  "geometry": {"coordinates":[-1.97668587279959,50.78160919321682],"type":"Point"}
}