{
  "type": "Feature",
  "properties": {
    "iso:country": "GB",
    "wof:name": "UB9 4AL",
    "wof:placetype": "postalcode"
  },
  "geometry": {"coordinates":[-0.486459,51.554353],"type":"Point"}
}
