{
  "type": "Feature",
  "properties": {
    "iso:country":"GB",
    "wof:name":"UB9 4AL",
    "wof:placetype":"postalcode"
},
  "geometry": {"coordinates":[-0.48645888062234,51.55435297053991],"type":"Point"}
}