{
  "type": "Feature",
  "properties": {
    "date:inception_lower": "1999-12-01",
    "date:inception_upper": "1999-12-01",
    "iso:country": "GB",
    "wof:name": "PO15 7LP",
    "wof:placetype": "postalcode"
  },
  "geometry": {"coordinates":[-1.262782,50.887384],"type":"Point"}
}
