{
  "type": "Feature",
  "properties": {
    "iso:country":"GB",
    "wof:name":"PO15 7LP",
    "wof:placetype":"postalcode"
},
  "geometry": {"coordinates":[-1.26278237274143,50.88738412138839],"type":"Point"}
}