{
  "type": "Feature",
  "properties": {
    "date:inception_lower": "1980-01-01",
    "date:inception_upper": "1980-01-01",
    "iso:country": "GB",
    "wof:name": "SO21 3SB",
    "wof:placetype": "postalcode"
  },
  "geometry": {"coordinates":[-1.372786,51.168888],"type":"Point"}
}
