{
  "type": "Feature",
  "properties": {
    "iso:country":"GB",
    "wof:name":"SO21 3SB",
    "wof:placetype":"postalcode"
},
  "geometry": {"coordinates":[-1.37252895176148,51.16883705009731],"type":"Point"}
}