{
  "type": "Feature",
  "properties": {
    "iso:country":"GB",
    "wof:name":"IV6 7UZ",
    "wof:placetype":"postalcode"
},
  "geometry": {"coordinates":[-4.54152254420573,57.53837647814953],"type":"Point"}
}