{
  "type": "Feature",
  "properties": {
    "iso:country": "GB",
    "wof:name": "IV6 7UZ",
    "wof:placetype": "postalcode"
  },
  "geometry": {"coordinates":[-4.541522,57.538376],"type":"Point"}
}
