{
  "type": "Feature",
  "properties": {
    "iso:country":"GB",
    "wof:name":"CB4 2NB",
    "wof:placetype":"postalcode"
},
  "geometry": {"coordinates":[0.13247146604438,52.22838804556086],"type":"Point"}
}