{
  "type": "Feature",
  "properties": {
    "date:inception_lower": "1980-01-01",
    "date:inception_upper": "1980-01-01",
    "iso:country": "GB",
    "wof:name": "CB4 2NB",
    "wof:placetype": "postalcode"
  },
  "geometry": {"coordinates":[0.132472,52.228388],"type":"Point"}
}
