{
  "type": "Feature",
  "properties": {
    "iso:country":"GB",
    "wof:name":"UB4 0DA",
    "wof:placetype":"postalcode"
},
  "geometry": {"coordinates":[-0.41041808309326,51.52316076623306],"type":"Point"}
}