{
  "type": "Feature",
  "properties": {
    "iso:country":"GB",
    "wof:name":"HP4 1PD",
    "wof:placetype":"postalcode"
},
  "geometry": {"coordinates":[-0.56224192411822,51.81293090592951],"type":"Point"}
}