{
  "type": "Feature",
  "properties": {
    "date:inception_lower": "1980-01-01",
    "date:inception_upper": "1980-01-01",
    "iso:country": "GB",
    "wof:name": "EX9 6HL",
    "wof:placetype": "postalcode"
  },
  "geometry": {"coordinates":[-3.318051,50.632834],"type":"Point"}
}
