{
  "type": "Feature",
  "properties": {
    "iso:country":"GB",
    "wof:name":"KA1 1TP",
    "wof:placetype":"postalcode"
},
  "geometry": {"coordinates":[-4.5109654983518,55.59953310279965],"type":"Point"}
}