{
  "type": "Feature",
  "properties": {
    "iso:country": "GB",
    "wof:name": "KA1 1TP",
    "wof:placetype": "postalcode"
  },
  "geometry": {"coordinates":[-4.510965,55.599533],"type":"Point"}
}
