{
  "type": "Feature",
  "properties": {
    "iso:country":"GB",
    "wof:name":"NP23 5DE",
    "wof:placetype":"postalcode"
},
  "geometry": {"coordinates":[-3.21409571108975,51.80080885541689],"type":"Point"}
}