{
  "type": "Feature",
  "properties": {
    "iso:country":"GB",
    "wof:name":"OX13 5LB",
    "wof:placetype":"postalcode"
},
  "geometry": {"coordinates":[-1.37282736092179,51.70496760645905],"type":"Point"}
}