{
  "type": "Feature",
  "properties": {
    "iso:country": "GB",
    "wof:name": "S12 4FN",
    "wof:placetype": "postalcode"
  },
  "geometry": {"coordinates":[-1.372658,53.349261],"type":"Point"}
}
