{
  "type": "Feature",
  "properties": {
    "iso:country":"GB",
    "wof:name":"S12 4FN",
    "wof:placetype":"postalcode"
},
  "geometry": {"coordinates":[-1.37265806497718,53.34926055502383],"type":"Point"}
}