{
  "type": "Feature",
  "properties": {
    "date:inception_lower": "2006-08-01",
    "date:inception_upper": "2006-08-01",
    "iso:country": "GB",
    "wof:name": "M15 4LE",
    "wof:placetype": "postalcode"
  },
  "geometry": {"coordinates":[-2.262103,53.473233],"type":"Point"}
}
