{
  "type": "Feature",
  "properties": {
    "iso:country":"GB",
    "wof:name":"M15 4LE",
    "wof:placetype":"postalcode"
},
  "geometry": {"coordinates":[-2.26210354183532,53.47323259232984],"type":"Point"}
}