{
  "type": "Feature",
  "properties": {
    "iso:country":"GB",
    "wof:name":"SA73 1ND",
    "wof:placetype":"postalcode"
},
  "geometry": {"coordinates":[-4.92276865225982,51.73436044183172],"type":"Point"}
}