{
  "type": "Feature",
  "properties": {
    "iso:country":"GB",
    "wof:name":"NP7 9HT",
    "wof:placetype":"postalcode"
},
  "geometry": {"coordinates":[-3.00910600438833,51.79118440394657],"type":"Point"}
}