{
  "type": "Feature",
  "properties": {
    "iso:country":"GB",
    "wof:name":"BS6 5BS",
    "wof:placetype":"postalcode"
},
  "geometry": {"coordinates":[-2.58738848906922,51.47159999094767],"type":"Point"}
}