{
  "type": "Feature",
  "properties": {
    "iso:country": "GB",
    "wof:name": "B49 5BS",
    "wof:placetype": "postalcode"
  },
  "geometry": {"coordinates":[-1.872248,52.211609],"type":"Point"}
}
