{
  "type": "Feature",
  "properties": {
    "iso:country":"GB",
    "wof:name":"BH9 3LD",
    "wof:placetype":"postalcode"
},
  "geometry": {"coordinates":[-1.8589649298634,50.75509727785024],"type":"Point"}
}