{
  "type": "Feature",
  "properties": {
    "iso:country":"GB",
    "wof:name":"BD23 5LD",
    "wof:placetype":"postalcode"
},
  "geometry": {"coordinates":[-1.99628175055907,54.07097048536183],"type":"Point"}
}