{
  "type": "Feature",
  "properties": {
    "iso:country":"GB",
    "wof:name":"NE8 3QA",
    "wof:placetype":"postalcode"
},
  "geometry": {"coordinates":[-1.58302140017936,54.95365800927814],"type":"Point"}
}