{
  "type": "Feature",
  "properties": {
    "iso:country":"GB",
    "wof:name":"BS15 4LN",
    "wof:placetype":"postalcode"
},
  "geometry": {"coordinates":[-2.48911684223914,51.46530757756656],"type":"Point"}
}