{
  "type": "Feature",
  "properties": {
    "date:inception_lower": "1980-01-01",
    "date:inception_upper": "1980-01-01",
    "iso:country": "GB",
    "wof:name": "BS15 4LN",
    "wof:placetype": "postalcode"
  },
  "geometry": {"coordinates":[-2.489117,51.465308],"type":"Point"}
}
