{
  "type": "Feature",
  "properties": {
    "iso:country":"GB",
    "wof:name":"SA4 8NJ",
    "wof:placetype":"postalcode"
},
  "geometry": {"coordinates":[-4.017811624583,51.716147506319],"type":"Point"}
}