{
  "type": "Feature",
  "properties": {
    "iso:country":"GB",
    "wof:name":"LA6 1AQ",
    "wof:placetype":"postalcode"
},
  "geometry": {"coordinates":[-2.69760649831465,54.14228601933996],"type":"Point"}
}