{
  "type": "Feature",
  "properties": {
    "date:inception_lower": "2022-12-01",
    "date:inception_upper": "2022-12-01",
    "iso:country": "GB",
    "wof:name": "G45 9BW",
    "wof:placetype": "postalcode"
  },
  "geometry": {"coordinates":[-4.242308,55.807391],"type":"Point"}
}
