{
  "type": "Feature",
  "properties": {
    "iso:country":"GB",
    "wof:name":"PO1 1EW",
    "wof:placetype":"postalcode"
},
  "geometry": {"coordinates":[-1.08777442548563,50.80217418632905],"type":"Point"}
}