{
  "type": "Feature",
  "properties": {
    "date:inception_lower": "2008-04-01",
    "date:inception_upper": "2008-04-01",
    "iso:country": "GB",
    "wof:name": "LE3 9SR",
    "wof:placetype": "postalcode"
  },
  "geometry": {"coordinates":[-1.177825,52.651479],"type":"Point"}
}
