{
  "type": "Feature",
  "properties": {
    "iso:country":"GB",
    "wof:name":"TF9 1EZ",
    "wof:placetype":"postalcode"
},
  "geometry": {"coordinates":[-2.47922319281559,52.90640670914027],"type":"Point"}
}