{
  "type": "Feature",
  "properties": {
    "date:inception_lower":"1980-01-01",
    "date:inception_upper":"1980-01-31",
    "iso:country":"GB",
    "wof:name":"TF9 1EZ",
    "wof:placetype":"postalcode"
},
  "geometry": {"coordinates":[-2.479223,52.906422],"type":"Point"}
}