{
  "type": "Feature",
  "properties": {
    "iso:country":"GB",
    "wof:name":"E5 9GX",
    "wof:placetype":"postalcode"
},
  "geometry": {"coordinates":[-0.04945095029838,51.56432225159898],"type":"Point"}
}