{
  "type": "Feature",
  "properties": {
    "date:inception_lower": "2007-07-01",
    "date:inception_upper": "2007-07-01",
    "iso:country": "GB",
    "wof:name": "E5 9GX",
    "wof:placetype": "postalcode"
  },
  "geometry": {"coordinates":[-0.049451,51.564322],"type":"Point"}
}
