{
  "type": "Feature",
  "properties": {
    "iso:country":"GB",
    "wof:name":"MK45 2LG",
    "wof:placetype":"postalcode"
},
  "geometry": {"coordinates":[-0.49432600289894,52.03097138299266],"type":"Point"}
}