{
  "type": "Feature",
  "properties": {
    "iso:country":"GB",
    "wof:name":"CF34 0NN",
    "wof:placetype":"postalcode"
},
  "geometry": {"coordinates":[-3.64382414901037,51.60502616192179],"type":"Point"}
}