{
  "type": "Feature",
  "properties": {
    "iso:country": "GB",
    "wof:name": "BD20 9AH",
    "wof:placetype": "postalcode"
  },
  "geometry": {"coordinates":[-1.986143,53.915488],"type":"Point"}
}
