{
  "type": "Feature",
  "properties": {
    "iso:country":"GB",
    "wof:name":"BD20 9AH",
    "wof:placetype":"postalcode"
},
  "geometry": {"coordinates":[-1.98655109126374,53.9152226340134],"type":"Point"}
}