{
  "type": "Feature",
  "properties": {
    "iso:country": "GB",
    "wof:name": "NP11 5LZ",
    "wof:placetype": "postalcode"
  },
  "geometry": {"coordinates":[-3.127685,51.676148],"type":"Point"}
}
