{
  "type": "Feature",
  "properties": {
    "iso:country":"GB",
    "wof:name":"PE31 6TD",
    "wof:placetype":"postalcode"
},
  "geometry": {"coordinates":[0.74758338791428,52.83477725778501],"type":"Point"}
}