{
  "type": "Feature",
  "properties": {
    "date:inception_lower":"1980-01-01",
    "date:inception_upper":"1980-01-31",
    "iso:country":"GB",
    "wof:name":"PE31 6TD",
    "wof:placetype":"postalcode"
},
  "geometry": {"coordinates":[0.747643,52.834775],"type":"Point"}
}