{
  "type": "Feature",
  "properties": {
    "iso:country": "GB",
    "wof:name": "PE31 6TD",
    "wof:placetype": "postalcode"
  },
  "geometry": {"coordinates":[0.747643,52.834775],"type":"Point"}
}
