{
  "type": "Feature",
  "properties": {
    "iso:country":"GB",
    "wof:name":"SA3 1AQ",
    "wof:placetype":"postalcode"
},
  "geometry": {"coordinates":[-4.18268413825106,51.58155442561398],"type":"Point"}
}