{
  "type": "Feature",
  "properties": {
    "date:inception_lower":"1980-01-01",
    "date:inception_upper":"1980-01-31",
    "iso:country":"GB",
    "wof:name":"SA3 1AQ",
    "wof:placetype":"postalcode"
},
  "geometry": {"coordinates":[-4.182684,51.581554],"type":"Point"}
}