{
  "type": "Feature",
  "properties": {
    "iso:country":"GB",
    "wof:name":"BN3 2PA",
    "wof:placetype":"postalcode"
},
  "geometry": {"coordinates":[-0.1697164481549,50.82699741254057],"type":"Point"}
}