{
  "type": "Feature",
  "properties": {
    "date:inception_lower": "2020-09-01",
    "date:inception_upper": "2020-09-01",
    "iso:country": "GB",
    "wof:name": "WD23 2FZ",
    "wof:placetype": "postalcode"
  },
  "geometry": {"coordinates":[-0.374319,51.663776],"type":"Point"}
}
