{
  "type": "Feature",
  "properties": {
    "iso:country": "GB",
    "wof:name": "PA5 0AF",
    "wof:placetype": "postalcode"
  },
  "geometry": {"coordinates":[-4.525011,55.825174],"type":"Point"}
}
