{
  "type": "Feature",
  "properties": {
    "iso:country":"GB",
    "wof:name":"TN13 3SL",
    "wof:placetype":"postalcode"
},
  "geometry": {"coordinates":[0.2076084586229,51.28675555816408],"type":"Point"}
}