{
  "type": "Feature",
  "properties": {
    "iso:country":"GB",
    "wof:name":"S60 3DB",
    "wof:placetype":"postalcode"
},
  "geometry": {"coordinates":[-1.33827274229469,53.40743896139305],"type":"Point"}
}