{
  "type": "Feature",
  "properties": {
    "date:inception_lower":"1980-01-01",
    "date:inception_upper":"1980-01-31",
    "iso:country":"GB",
    "wof:name":"S60 3DB",
    "wof:placetype":"postalcode"
},
  "geometry": {"coordinates":[-1.338273,53.407439],"type":"Point"}
}