{
  "type": "Feature",
  "properties": {
    "iso:country": "GB",
    "wof:name": "CO3 3SU",
    "wof:placetype": "postalcode"
  },
  "geometry": {"coordinates":[0.873132,51.888427],"type":"Point"}
}
