{
  "type": "Feature",
  "properties": {
    "iso:country":"GB",
    "wof:name":"CO15 5XR",
    "wof:placetype":"postalcode"
},
  "geometry": {"coordinates":[1.19333054729589,51.80902280326127],"type":"Point"}
}