{
  "type": "Feature",
  "properties": {
    "date:inception_lower": "1980-01-01",
    "date:inception_upper": "1980-01-01",
    "iso:country": "GB",
    "wof:name": "SA11 4DW",
    "wof:placetype": "postalcode"
  },
  "geometry": {"coordinates":[-3.704924,51.712887],"type":"Point"}
}
