{
  "type": "Feature",
  "properties": {
    "date:inception_lower":"1995-07-01",
    "date:inception_upper":"1995-07-31",
    "iso:country":"GB",
    "wof:name":"RG31 6HL",
    "wof:placetype":"postalcode"
},
  "geometry": {"coordinates":[-1.037177,51.464178],"type":"Point"}
}