{
  "type": "Feature",
  "properties": {
    "iso:country": "GB",
    "wof:name": "RG31 6HL",
    "wof:placetype": "postalcode"
  },
  "geometry": {"coordinates":[-1.037077,51.464168],"type":"Point"}
}
