{
  "type": "Feature",
  "properties": {
    "date:inception_lower": "1980-01-01",
    "date:inception_upper": "1980-01-01",
    "iso:country": "GB",
    "wof:name": "EH48 3NE",
    "wof:placetype": "postalcode"
  },
  "geometry": {"coordinates":[-3.706068,55.900074],"type":"Point"}
}
