{
  "type": "Feature",
  "properties": {
    "date:inception_lower":"1994-05-01",
    "date:inception_upper":"1994-05-31",
    "iso:country":"GB",
    "wof:name":"M9 6RL",
    "wof:placetype":"postalcode"
},
  "geometry": {"coordinates":[-2.214062,53.530675],"type":"Point"}
}