{
  "type": "Feature",
  "properties": {
    "iso:country":"GB",
    "wof:name":"M9 6RL",
    "wof:placetype":"postalcode"
},
  "geometry": {"coordinates":[-2.21406239607789,53.53067452961257],"type":"Point"}
}