{
  "type": "Feature",
  "properties": {
    "iso:country": "GB",
    "wof:name": "LL12 9UU",
    "wof:placetype": "postalcode"
  },
  "geometry": {"coordinates":[-3.030401,53.098417],"type":"Point"}
}
