{
  "type": "Feature",
  "properties": {
    "date:inception_lower": "1993-08-01",
    "date:inception_upper": "1993-08-01",
    "iso:country": "GB",
    "wof:name": "LL12 9UU",
    "wof:placetype": "postalcode"
  },
  "geometry": {"coordinates":[-3.030401,53.098417],"type":"Point"}
}
