{
  "type": "Feature",
  "properties": {
    "iso:country":"GB",
    "wof:name":"LL12 9UU",
    "wof:placetype":"postalcode"
},
  "geometry": {"coordinates":[-3.03040138372984,53.09841745059403],"type":"Point"}
}