{
  "type": "Feature",
  "properties": {
    "date:inception_lower":"1980-01-01",
    "date:inception_upper":"1980-01-31",
    "iso:country":"GB",
    "wof:name":"SY4 2AU",
    "wof:placetype":"postalcode"
},
  "geometry": {"coordinates":[-2.85184,52.79326],"type":"Point"}
}