{
  "type": "Feature",
  "properties": {
    "iso:country":"GB",
    "wof:name":"DN9 2AU",
    "wof:placetype":"postalcode"
},
  "geometry": {"coordinates":[-0.86710931805901,53.48909717719223],"type":"Point"}
}