{
  "type": "Feature",
  "properties": {
    "iso:country": "GB",
    "wof:name": "SM1 1EA",
    "wof:placetype": "postalcode"
  },
  "geometry": {"coordinates":[-0.194924,51.36163],"type":"Point"}
}
