{
  "type": "Feature",
  "properties": {
    "iso:country": "GB",
    "wof:name": "SP8 5DR",
    "wof:placetype": "postalcode"
  },
  "geometry": {"coordinates":[-2.300936,51.034611],"type":"Point"}
}
