{
  "type": "Feature",
  "properties": {
    "iso:country":"GB",
    "wof:name":"SP8 5DR",
    "wof:placetype":"postalcode"
},
  "geometry": {"coordinates":[-2.3009360144721,51.03461059799821],"type":"Point"}
}