{
  "type": "Feature",
  "properties": {
    "iso:country":"GB",
    "wof:name":"BA2 3RF",
    "wof:placetype":"postalcode"
},
  "geometry": {"coordinates":[-2.37732009557548,51.3812085619949],"type":"Point"}
}