{
  "type": "Feature",
  "properties": {
    "iso:country":"GB",
    "wof:name":"G12 8RH",
    "wof:placetype":"postalcode"
},
  "geometry": {"coordinates":[-4.28821787932898,55.87613103634484],"type":"Point"}
}