{
  "type": "Feature",
  "properties": {
    "date:inception_lower": "1980-01-01",
    "date:inception_upper": "1980-01-01",
    "iso:country": "GB",
    "wof:name": "G12 8RH",
    "wof:placetype": "postalcode"
  },
  "geometry": {"coordinates":[-4.288218,55.876131],"type":"Point"}
}
