{
  "type": "Feature",
  "properties": {
    "iso:country":"GB",
    "wof:name":"LS20 8DG",
    "wof:placetype":"postalcode"
},
  "geometry": {"coordinates":[-1.71357618264951,53.87340351863548],"type":"Point"}
}