{
  "type": "Feature",
  "properties": {
    "date:inception_lower": "1980-01-01",
    "date:inception_upper": "1980-01-01",
    "iso:country": "GB",
    "wof:name": "LS20 8DG",
    "wof:placetype": "postalcode"
  },
  "geometry": {"coordinates":[-1.713626,53.873346],"type":"Point"}
}
