{
  "type": "Feature",
  "properties": {
    "iso:country":"GB",
    "wof:name":"LL36 9EP",
    "wof:placetype":"postalcode"
},
  "geometry": {"coordinates":[-4.08425745475698,52.58709627756095],"type":"Point"}
}