{
  "type": "Feature",
  "properties": {
    "iso:country": "GB",
    "wof:name": "WA8 9WW",
    "wof:placetype": "postalcode"
  },
  "geometry": {"coordinates":[-2.720977,53.386967],"type":"Point"}
}
