{
  "type": "Feature",
  "properties": {
    "iso:country":"GB",
    "wof:name":"WA8 9WW",
    "wof:placetype":"postalcode"
},
  "geometry": {"coordinates":[-2.7209773278879,53.38696704821098],"type":"Point"}
}