{
  "type": "Feature",
  "properties": {
    "iso:country":"GB",
    "wof:name":"DT4 9JQ",
    "wof:placetype":"postalcode"
},
  "geometry": {"coordinates":[-2.47067528204995,50.59134474650298],"type":"Point"}
}