{
  "type": "Feature",
  "properties": {
    "iso:country":"GB",
    "wof:name":"RG27 0NH",
    "wof:placetype":"postalcode"
},
  "geometry": {"coordinates":[-0.86549542888076,51.34713012571167],"type":"Point"}
}