{
  "type": "Feature",
  "properties": {
    "iso:country":"GB",
    "wof:name":"W1H 2PP",
    "wof:placetype":"postalcode"
},
  "geometry": {"coordinates":[-0.16130571118524,51.51907090729183],"type":"Point"}
}