{
  "type": "Feature",
  "properties": {
    "date:inception_lower": "1980-01-01",
    "date:inception_upper": "1980-01-01",
    "iso:country": "GB",
    "wof:name": "CV21 3LX",
    "wof:placetype": "postalcode"
  },
  "geometry": {"coordinates":[-1.250495,52.374219],"type":"Point"}
}
