{
  "type": "Feature",
  "properties": {
    "iso:country": "GB",
    "wof:name": "YO8 3AJ",
    "wof:placetype": "postalcode"
  },
  "geometry": {"coordinates":[-1.068478,53.789516],"type":"Point"}
}
