{
  "type": "Feature",
  "properties": {
    "date:inception_lower": "2013-07-01",
    "date:inception_upper": "2013-07-01",
    "iso:country": "GB",
    "wof:name": "YO8 3AJ",
    "wof:placetype": "postalcode"
  },
  "geometry": {"coordinates":[-1.068478,53.789516],"type":"Point"}
}
