{
  "type": "Feature",
  "properties": {
    "iso:country":"GB",
    "wof:name":"YO8 3AJ",
    "wof:placetype":"postalcode"
},
  "geometry": {"coordinates":[-1.06847828015705,53.78951621815913],"type":"Point"}
}