{
  "type": "Feature",
  "properties": {
    "iso:country":"GB",
    "wof:name":"EX13 5QY",
    "wof:placetype":"postalcode"
},
  "geometry": {"coordinates":[-3.00221418957609,50.77470471423814],"type":"Point"}
}