{
  "type": "Feature",
  "properties": {
    "iso:country":"GB",
    "wof:name":"NW2 4AQ",
    "wof:placetype":"postalcode"
},
  "geometry": {"coordinates":[-0.22743746748293,51.55281217234521],"type":"Point"}
}