{
  "type": "Feature",
  "properties": {
    "date:inception_lower":"2009-10-01",
    "date:inception_upper":"2009-10-31",
    "iso:country":"GB",
    "wof:name":"NW2 4AQ",
    "wof:placetype":"postalcode"
},
  "geometry": {"coordinates":[-0.227437,51.552812],"type":"Point"}
}