{
  "type": "Feature",
  "properties": {
    "iso:country": "GB",
    "wof:name": "SL8 5AU",
    "wof:placetype": "postalcode"
  },
  "geometry": {"coordinates":[-0.706452,51.57677],"type":"Point"}
}
