{
  "type": "Feature",
  "properties": {
    "iso:country":"GB",
    "wof:name":"SL8 5AU",
    "wof:placetype":"postalcode"
},
  "geometry": {"coordinates":[-0.70621057296623,51.57680853810302],"type":"Point"}
}