{
  "type": "Feature",
  "properties": {
    "date:inception_lower": "1992-08-01",
    "date:inception_upper": "1992-08-01",
    "iso:country": "GB",
    "wof:name": "SL8 5AU",
    "wof:placetype": "postalcode"
  },
  "geometry": {"coordinates":[-0.706191,51.576812],"type":"Point"}
}
