{
  "type": "Feature",
  "properties": {
    "iso:country": "GB",
    "wof:name": "LE7 7HW",
    "wof:placetype": "postalcode"
  },
  "geometry": {"coordinates":[-1.178647,52.666785],"type":"Point"}
}
