{
  "type": "Feature",
  "properties": {
    "date:inception_lower": "2002-06-01",
    "date:inception_upper": "2002-06-01",
    "iso:country": "GB",
    "wof:name": "WF4 4TT",
    "wof:placetype": "postalcode"
  },
  "geometry": {"coordinates":[-1.641064,53.630692],"type":"Point"}
}
