{
  "type": "Feature",
  "properties": {
    "iso:country": "GB",
    "wof:name": "PH7 3DS",
    "wof:placetype": "postalcode"
  },
  "geometry": {"coordinates":[-3.836528,56.374628],"type":"Point"}
}
