{
  "type": "Feature",
  "properties": {
    "iso:country":"GB",
    "wof:name":"BA2 5DX",
    "wof:placetype":"postalcode"
},
  "geometry": {"coordinates":[-2.3742629588447,51.35873910572421],"type":"Point"}
}