{
  "type": "Feature",
  "properties": {
    "date:inception_lower":"2007-05-01",
    "date:inception_upper":"2007-05-31",
    "iso:country":"GB",
    "wof:name":"BA2 5DX",
    "wof:placetype":"postalcode"
},
  "geometry": {"coordinates":[-2.374263,51.358739],"type":"Point"}
}