{
  "type": "Feature",
  "properties": {
    "iso:country":"GB",
    "wof:name":"SN15 2LW",
    "wof:placetype":"postalcode"
},
  "geometry": {"coordinates":[-2.12224099256348,51.41236033248632],"type":"Point"}
}