{
  "type": "Feature",
  "properties": {
    "iso:country":"GB",
    "wof:name":"TN39 4TE",
    "wof:placetype":"postalcode"
},
  "geometry": {"coordinates":[0.43193743723221,50.83817576722117],"type":"Point"}
}