{
  "type": "Feature",
  "properties": {
    "date:inception_lower": "2022-02-01",
    "date:inception_upper": "2022-02-01",
    "iso:country": "GB",
    "wof:name": "PO9 5FQ",
    "wof:placetype": "postalcode"
  },
  "geometry": {"coordinates":[-0.961858,50.863595],"type":"Point"}
}
