{
  "type": "Feature",
  "properties": {
    "iso:country": "GB",
    "wof:name": "AL6 9BD",
    "wof:placetype": "postalcode"
  },
  "geometry": {"coordinates":[-0.232783,51.814502],"type":"Point"}
}
