{
  "type": "Feature",
  "properties": {
    "date:inception_lower": "2012-12-01",
    "date:inception_upper": "2012-12-01",
    "iso:country": "GB",
    "wof:name": "L39 2AF",
    "wof:placetype": "postalcode"
  },
  "geometry": {"coordinates":[-2.878104,53.567406],"type":"Point"}
}
