{
  "type": "Feature",
  "properties": {
    "date:inception_lower": "1993-01-01",
    "date:inception_upper": "1993-01-01",
    "iso:country": "GB",
    "wof:name": "GU21 2BL",
    "wof:placetype": "postalcode"
  },
  "geometry": {"coordinates":[-0.605257,51.317209],"type":"Point"}
}
