{
  "type": "Feature",
  "properties": {
    "iso:country":"GB",
    "wof:name":"GU21 2BL",
    "wof:placetype":"postalcode"
},
  "geometry": {"coordinates":[-0.60525749685358,51.31720930897289],"type":"Point"}
}