{
  "type": "Feature",
  "properties": {
    "date:inception_lower": "1999-06-01",
    "date:inception_upper": "1999-06-01",
    "iso:country": "GB",
    "wof:name": "HX3 5FB",
    "wof:placetype": "postalcode"
  },
  "geometry": {"coordinates":[-1.897738,53.738037],"type":"Point"}
}
