{
  "type": "Feature",
  "properties": {
    "date:inception_lower": "1980-01-01",
    "date:inception_upper": "1980-01-01",
    "iso:country": "GB",
    "wof:name": "ME15 9TX",
    "wof:placetype": "postalcode"
  },
  "geometry": {"coordinates":[0.527452,51.253871],"type":"Point"}
}
