{
  "type": "Feature",
  "properties": {
    "iso:country":"GB",
    "wof:name":"EN2 7PG",
    "wof:placetype":"postalcode"
},
  "geometry": {"coordinates":[-0.10152340285683,51.65777125443208],"type":"Point"}
}