{
  "type": "Feature",
  "properties": {
    "date:inception_lower": "2012-10-01",
    "date:inception_upper": "2012-10-01",
    "iso:country": "GB",
    "wof:name": "EN2 7PG",
    "wof:placetype": "postalcode"
  },
  "geometry": {"coordinates":[-0.101523,51.657771],"type":"Point"}
}
