{
  "type": "Feature",
  "properties": {
    "iso:country":"GB",
    "wof:name":"DD8 4TG",
    "wof:placetype":"postalcode"
},
  "geometry": {"coordinates":[-3.00854684559335,56.68108398339743],"type":"Point"}
}