{
  "type": "Feature",
  "properties": {
    "iso:country":"GB",
    "wof:name":"M7 4FB",
    "wof:placetype":"postalcode"
},
  "geometry": {"coordinates":[-2.24828776109822,53.51180456134107],"type":"Point"}
}