{
  "type": "Feature",
  "properties": {
    "iso:country": "GB",
    "wof:name": "M7 4FB",
    "wof:placetype": "postalcode"
  },
  "geometry": {"coordinates":[-2.248288,53.511805],"type":"Point"}
}
