{
  "type": "Feature",
  "properties": {
    "date:inception_lower": "1990-02-01",
    "date:inception_upper": "1990-02-01",
    "iso:country": "GB",
    "wof:name": "PO30 1SR",
    "wof:placetype": "postalcode"
  },
  "geometry": {"coordinates":[-1.293858,50.700043],"type":"Point"}
}
