{
  "type": "Feature",
  "properties": {
    "iso:country": "GB",
    "wof:name": "PO30 1SR",
    "wof:placetype": "postalcode"
  },
  "geometry": {"coordinates":[-1.293858,50.700043],"type":"Point"}
}
