{
  "type": "Feature",
  "properties": {
    "iso:country": "GB",
    "wof:name": "PL21 0UH",
    "wof:placetype": "postalcode"
  },
  "geometry": {"coordinates":[-3.9213,50.38579],"type":"Point"}
}
