{
  "type": "Feature",
  "properties": {
    "date:inception_lower":"1980-01-01",
    "date:inception_upper":"1980-01-31",
    "iso:country":"GB",
    "wof:name":"BL7 9EH",
    "wof:placetype":"postalcode"
},
  "geometry": {"coordinates":[-2.434589,53.620319],"type":"Point"}
}