{
  "type": "Feature",
  "properties": {
    "iso:country":"GB",
    "wof:name":"BL7 9EH",
    "wof:placetype":"postalcode"
},
  "geometry": {"coordinates":[-2.43458935045139,53.62031914530765],"type":"Point"}
}