{
  "type": "Feature",
  "properties": {
    "date:inception_lower": "1992-08-01",
    "date:inception_upper": "1992-08-01",
    "iso:country": "GB",
    "wof:name": "OX44 9NX",
    "wof:placetype": "postalcode"
  },
  "geometry": {"coordinates":[-1.201646,51.688464],"type":"Point"}
}
