{
  "type": "Feature",
  "properties": {
    "iso:country":"GB",
    "wof:name":"OX44 9NX",
    "wof:placetype":"postalcode"
},
  "geometry": {"coordinates":[-1.20164587354181,51.68846439231559],"type":"Point"}
}