{
  "type": "Feature",
  "properties": {
    "iso:country":"GB",
    "wof:name":"M26 1BR",
    "wof:placetype":"postalcode"
},
  "geometry": {"coordinates":[-2.32432128072373,53.54973313670735],"type":"Point"}
}