{
  "type": "Feature",
  "properties": {
    "iso:country":"GB",
    "wof:name":"TR11 3YL",
    "wof:placetype":"postalcode"
},
  "geometry": {"coordinates":[-5.06005592718118,50.15151738357485],"type":"Point"}
}