{
  "type": "Feature",
  "properties": {
    "date:inception_lower":"1991-01-01",
    "date:inception_upper":"1991-01-31",
    "iso:country":"GB",
    "wof:name":"TR11 3YL",
    "wof:placetype":"postalcode"
},
  "geometry": {"coordinates":[-5.060056,50.151517],"type":"Point"}
}