{
  "type": "Feature",
  "properties": {
    "date:inception_lower": "1980-01-01",
    "date:inception_upper": "1980-01-01",
    "iso:country": "GB",
    "wof:name": "CA11 8JJ",
    "wof:placetype": "postalcode"
  },
  "geometry": {"coordinates":[-2.747993,54.662375],"type":"Point"}
}
