{
  "type": "Feature",
  "properties": {
    "iso:country":"GB",
    "wof:name":"SA71 4QX",
    "wof:placetype":"postalcode"
},
  "geometry": {"coordinates":[-4.911225533935,51.68053131126973],"type":"Point"}
}