{
  "type": "Feature",
  "properties": {
    "date:inception_lower": "1996-06-01",
    "date:inception_upper": "1996-06-01",
    "iso:country": "GB",
    "wof:name": "SA71 4QX",
    "wof:placetype": "postalcode"
  },
  "geometry": {"coordinates":[-4.911225,51.680531],"type":"Point"}
}
