{
  "type": "Feature",
  "properties": {
    "iso:country":"GB",
    "wof:name":"TA24 5BY",
    "wof:placetype":"postalcode"
},
  "geometry": {"coordinates":[-3.46585120568772,51.20291227063181],"type":"Point"}
}