{
  "type": "Feature",
  "properties": {
    "date:inception_lower": "1984-10-01",
    "date:inception_upper": "1984-10-01",
    "iso:country": "GB",
    "wof:name": "TA24 5BY",
    "wof:placetype": "postalcode"
  },
  "geometry": {"coordinates":[-3.465295,51.20298],"type":"Point"}
}
