{
  "type": "Feature",
  "properties": {
    "iso:country":"GB",
    "wof:name":"AB33 8RZ",
    "wof:placetype":"postalcode"
},
  "geometry": {"coordinates":[-2.91683078511983,57.21007434611593],"type":"Point"}
}