{
  "type": "Feature",
  "properties": {
    "date:inception_lower": "1990-08-01",
    "date:inception_upper": "1990-08-01",
    "iso:country": "GB",
    "wof:name": "AB33 8RZ",
    "wof:placetype": "postalcode"
  },
  "geometry": {"coordinates":[-2.916831,57.210074],"type":"Point"}
}
