{
  "type": "Feature",
  "properties": {
    "date:inception_lower": "1980-01-01",
    "date:inception_upper": "1980-01-01",
    "iso:country": "GB",
    "wof:name": "WA15 9HN",
    "wof:placetype": "postalcode"
  },
  "geometry": {"coordinates":[-2.342419,53.381634],"type":"Point"}
}
