{
  "type": "Feature",
  "properties": {
    "iso:country": "GB",
    "wof:name": "WV6 9PA",
    "wof:placetype": "postalcode"
  },
  "geometry": {"coordinates":[-2.157473,52.602928],"type":"Point"}
}
