{
  "type": "Feature",
  "properties": {
    "date:inception_lower":"1980-01-01",
    "date:inception_upper":"1980-01-31",
    "iso:country":"GB",
    "wof:name":"WV6 9PA",
    "wof:placetype":"postalcode"
},
  "geometry": {"coordinates":[-2.157473,52.602928],"type":"Point"}
}