{
  "type": "Feature",
  "properties": {
    "iso:country":"GB",
    "wof:name":"WV6 9PA",
    "wof:placetype":"postalcode"
},
  "geometry": {"coordinates":[-2.1574729410259,52.60292846311591],"type":"Point"}
}