{
  "type": "Feature",
  "properties": {
    "iso:country": "GB",
    "wof:name": "NP7 7NH",
    "wof:placetype": "postalcode"
  },
  "geometry": {"coordinates":[-3.029636,51.924688],"type":"Point"}
}
