{
  "type": "Feature",
  "properties": {
    "iso:country":"GB",
    "wof:name":"NP7 7NH",
    "wof:placetype":"postalcode"
},
  "geometry": {"coordinates":[-3.02963599012714,51.92468834777048],"type":"Point"}
}