{
  "type": "Feature",
  "properties": {
    "date:inception_lower": "1980-01-01",
    "date:inception_upper": "1980-01-01",
    "iso:country": "GB",
    "wof:name": "NP7 7NH",
    "wof:placetype": "postalcode"
  },
  "geometry": {"coordinates":[-3.029636,51.924688],"type":"Point"}
}
