{
  "type": "Feature",
  "properties": {
    "date:inception_lower": "1980-01-01",
    "date:inception_upper": "1980-01-01",
    "iso:country": "GB",
    "wof:name": "NW9 5GF",
    "wof:placetype": "postalcode"
  },
  "geometry": {"coordinates":[-0.247618,51.600055],"type":"Point"}
}
