{
  "type": "Feature",
  "properties": {
    "iso:country":"GB",
    "wof:name":"NW9 5GF",
    "wof:placetype":"postalcode"
},
  "geometry": {"coordinates":[-0.24761853010044,51.6000551170371],"type":"Point"}
}