{
  "type": "Feature",
  "properties": {
    "iso:country":"GB",
    "wof:name":"NP26 5TN",
    "wof:placetype":"postalcode"
},
  "geometry": {"coordinates":[-2.71263093293253,51.59246255040438],"type":"Point"}
}