{
  "type": "Feature",
  "properties": {
    "iso:country":"GB",
    "wof:name":"NG2 1QE",
    "wof:placetype":"postalcode"
},
  "geometry": {"coordinates":[-1.15808723981375,52.94284126547272],"type":"Point"}
}