{
  "type": "Feature",
  "properties": {
    "iso:country": "GB",
    "wof:name": "NG2 1QE",
    "wof:placetype": "postalcode"
  },
  "geometry": {"coordinates":[-1.158087,52.942841],"type":"Point"}
}
