{
  "type": "Feature",
  "properties": {
    "date:inception_lower": "1980-01-01",
    "date:inception_upper": "1980-01-01",
    "iso:country": "GB",
    "wof:name": "NG2 1QE",
    "wof:placetype": "postalcode"
  },
  "geometry": {"coordinates":[-1.158087,52.942841],"type":"Point"}
}
