{
  "type": "Feature",
  "properties": {
    "iso:country": "GB",
    "wof:name": "NR19 2BT",
    "wof:placetype": "postalcode"
  },
  "geometry": {"coordinates":[0.943649,52.683457],"type":"Point"}
}
