{
  "type": "Feature",
  "properties": {
    "iso:country":"GB",
    "wof:name":"W1G 9JW",
    "wof:placetype":"postalcode"
},
  "geometry": {"coordinates":[-0.14872347619182,51.51762303911725],"type":"Point"}
}