{
  "type": "Feature",
  "properties": {
    "date:inception_lower": "2020-10-01",
    "date:inception_upper": "2020-10-01",
    "iso:country": "GB",
    "wof:name": "SL9 0FQ",
    "wof:placetype": "postalcode"
  },
  "geometry": {"coordinates":[-0.550075,51.621124],"type":"Point"}
}
