{
  "type": "Feature",
  "properties": {
    "iso:country":"GB",
    "wof:name":"CA20 1HJ",
    "wof:placetype":"postalcode"
},
  "geometry": {"coordinates":[-3.46482255220642,54.40789728688389],"type":"Point"}
}