{
  "type": "Feature",
  "properties": {
    "iso:country":"GB",
    "wof:name":"L33 7DR",
    "wof:placetype":"postalcode"
},
  "geometry": {"coordinates":[-2.87014673302447,53.46807656376789],"type":"Point"}
}