{
  "type": "Feature",
  "properties": {
    "iso:country": "GB",
    "wof:name": "BH20 7JQ",
    "wof:placetype": "postalcode"
  },
  "geometry": {"coordinates":[-2.217673,50.76336],"type":"Point"}
}
