{
  "type": "Feature",
  "properties": {
    "iso:country": "GB",
    "wof:name": "PA3 3LQ",
    "wof:placetype": "postalcode"
  },
  "geometry": {"coordinates":[-4.509235,55.84697],"type":"Point"}
}
