{
  "type": "Feature",
  "properties": {
    "date:inception_lower": "1980-01-01",
    "date:inception_upper": "1980-01-01",
    "iso:country": "GB",
    "wof:name": "PA3 3LQ",
    "wof:placetype": "postalcode"
  },
  "geometry": {"coordinates":[-4.509235,55.84697],"type":"Point"}
}
