{
  "type": "Feature",
  "properties": {
    "date:inception_lower": "2015-07-01",
    "date:inception_upper": "2015-07-01",
    "iso:country": "GB",
    "wof:name": "PE10 0YB",
    "wof:placetype": "postalcode"
  },
  "geometry": {"coordinates":[-0.39087,52.758683],"type":"Point"}
}
