{
  "type": "Feature",
  "properties": {
    "date:inception_lower":"1996-06-01",
    "date:inception_upper":"1996-06-30",
    "iso:country":"GB",
    "wof:name":"G74 5BY",
    "wof:placetype":"postalcode"
},
  "geometry": {"coordinates":[-4.218244,55.773797],"type":"Point"}
}