{
  "type": "Feature",
  "properties": {
    "iso:country":"GB",
    "wof:name":"YO23 2RX",
    "wof:placetype":"postalcode"
},
  "geometry": {"coordinates":[-1.10156825149282,53.91877634050102],"type":"Point"}
}