{
  "type": "Feature",
  "properties": {
    "iso:country":"GB",
    "wof:name":"SG12 9NA",
    "wof:placetype":"postalcode"
},
  "geometry": {"coordinates":[-0.0277477102143,51.80405672182448],"type":"Point"}
}