{
  "type": "Feature",
  "properties": {
    "iso:country": "GB",
    "wof:name": "NE1 4BJ",
    "wof:placetype": "postalcode"
  },
  "geometry": {"coordinates":[-1.61946,54.975704],"type":"Point"}
}
