{
  "type": "Feature",
  "properties": {
    "iso:country":"GB",
    "wof:name":"LE8 5XP",
    "wof:placetype":"postalcode"
},
  "geometry": {"coordinates":[-1.15554782265457,52.55627058999234],"type":"Point"}
}