{
  "type": "Feature",
  "properties": {
    "date:inception_lower": "1990-02-01",
    "date:inception_upper": "1990-02-01",
    "iso:country": "GB",
    "wof:name": "LL21 9LQ",
    "wof:placetype": "postalcode"
  },
  "geometry": {"coordinates":[-3.27497,53.014692],"type":"Point"}
}
