{
  "type": "Feature",
  "properties": {
    "iso:country": "GB",
    "wof:name": "LL21 9LQ",
    "wof:placetype": "postalcode"
  },
  "geometry": {"coordinates":[-3.27497,53.014692],"type":"Point"}
}
