{
  "type": "Feature",
  "properties": {
    "date:inception_lower": "2005-03-01",
    "date:inception_upper": "2005-03-01",
    "iso:country": "GB",
    "wof:name": "NE12 8WH",
    "wof:placetype": "postalcode"
  },
  "geometry": {"coordinates":[-1.599519,55.010884],"type":"Point"}
}
