{
  "type": "Feature",
  "properties": {
    "iso:country":"GB",
    "wof:name":"SY11 4JZ",
    "wof:placetype":"postalcode"
},
  "geometry": {"coordinates":[-2.98969508002502,52.82236000118938],"type":"Point"}
}