{
  "type": "Feature",
  "properties": {
    "date:inception_lower": "2022-08-01",
    "date:inception_upper": "2022-08-01",
    "iso:country": "GB",
    "wof:name": "CF72 4AT",
    "wof:placetype": "postalcode"
  },
  "geometry": {"coordinates":[-3.458104,51.527508],"type":"Point"}
}
