{
  "type": "Feature",
  "properties": {
    "iso:country": "GB",
    "wof:name": "IV15 9TQ",
    "wof:placetype": "postalcode"
  },
  "geometry": {"coordinates":[-4.497014,57.587799],"type":"Point"}
}
