{
  "type": "Feature",
  "properties": {
    "date:inception_lower":"1980-01-01",
    "date:inception_upper":"1980-01-31",
    "iso:country":"GB",
    "wof:name":"IV15 9TQ",
    "wof:placetype":"postalcode"
},
  "geometry": {"coordinates":[-4.497228,57.587741],"type":"Point"}
}