{
  "type": "Feature",
  "properties": {
    "iso:country":"GB",
    "wof:name":"IV15 9TQ",
    "wof:placetype":"postalcode"
},
  "geometry": {"coordinates":[-4.49701636777461,57.58781663054038],"type":"Point"}
}