{
  "type": "Feature",
  "properties": {
    "iso:country": "GB",
    "wof:name": "IV15 9TQ",
    "wof:placetype": "postalcode"
  },
  "geometry": {"coordinates":[-4.497228,57.587741],"type":"Point"}
}
