{
  "type": "Feature",
  "properties": {
    "date:inception_lower": "1980-01-01",
    "date:inception_upper": "1980-01-01",
    "iso:country": "GB",
    "wof:name": "DD4 9AF",
    "wof:placetype": "postalcode"
  },
  "geometry": {"coordinates":[-2.97099,56.479882],"type":"Point"}
}
