{
  "type": "Feature",
  "properties": {
    "iso:country":"GB",
    "wof:name":"M44 6FJ",
    "wof:placetype":"postalcode"
},
  "geometry": {"coordinates":[-2.41362135196495,53.45020672760756],"type":"Point"}
}