{
  "type": "Feature",
  "properties": {
    "iso:country": "GB",
    "wof:name": "SN3 6FH",
    "wof:placetype": "postalcode"
  },
  "geometry": {"coordinates":[-1.724494,51.535753],"type":"Point"}
}
