{
  "type": "Feature",
  "properties": {
    "iso:country":"GB",
    "wof:name":"LD3 8NB",
    "wof:placetype":"postalcode"
},
  "geometry": {"coordinates":[-3.44015227420128,51.9304508293515],"type":"Point"}
}