{
  "type": "Feature",
  "properties": {
    "iso:country": "GB",
    "wof:name": "LD3 8NB",
    "wof:placetype": "postalcode"
  },
  "geometry": {"coordinates":[-3.434309,51.930726],"type":"Point"}
}
