{
  "type": "Feature",
  "properties": {
    "date:inception_lower":"1980-01-01",
    "date:inception_upper":"1980-01-31",
    "iso:country":"GB",
    "wof:name":"NG24 4UU",
    "wof:placetype":"postalcode"
},
  "geometry": {"coordinates":[-0.814092,53.072694],"type":"Point"}
}