{
  "type": "Feature",
  "properties": {
    "iso:country": "GB",
    "wof:name": "NG24 4UU",
    "wof:placetype": "postalcode"
  },
  "geometry": {"coordinates":[-0.814092,53.072694],"type":"Point"}
}
