{
  "type": "Feature",
  "properties": {
    "iso:country":"GB",
    "wof:name":"NG24 4UU",
    "wof:placetype":"postalcode"
},
  "geometry": {"coordinates":[-0.81409253220331,53.07269370438568],"type":"Point"}
}