{
  "type": "Feature",
  "properties": {
    "iso:country":"GB",
    "wof:name":"EN10 7JU",
    "wof:placetype":"postalcode"
},
  "geometry": {"coordinates":[-0.01462868063875,51.74674380042779],"type":"Point"}
}