{
  "type": "Feature",
  "properties": {
    "date:inception_lower": "2016-07-01",
    "date:inception_upper": "2016-07-01",
    "iso:country": "GB",
    "wof:name": "TN40 2FL",
    "wof:placetype": "postalcode"
  },
  "geometry": {"coordinates":[0.493472,50.853377],"type":"Point"}
}
