{
  "type": "Feature",
  "properties": {
    "iso:country": "GB",
    "wof:name": "DN14 7YD",
    "wof:placetype": "postalcode"
  },
  "geometry": {"coordinates":[-0.779563,53.722638],"type":"Point"}
}
