{
  "type": "Feature",
  "properties": {
    "iso:country":"GB",
    "wof:name":"N14 4NE",
    "wof:placetype":"postalcode"
},
  "geometry": {"coordinates":[-0.13199745618015,51.63956492708185],"type":"Point"}
}