{
  "type": "Feature",
  "properties": {
    "date:inception_lower": "2018-04-01",
    "date:inception_upper": "2018-04-01",
    "iso:country": "GB",
    "wof:name": "MK11 4BH",
    "wof:placetype": "postalcode"
  },
  "geometry": {"coordinates":[-0.839395,52.043824],"type":"Point"}
}
