{
  "type": "Feature",
  "properties": {
    "date:inception_lower": "1980-01-01",
    "date:inception_upper": "1980-01-01",
    "iso:country": "GB",
    "wof:name": "BS14 0DP",
    "wof:placetype": "postalcode"
  },
  "geometry": {"coordinates":[-2.580791,51.40558],"type":"Point"}
}
