{
  "type": "Feature",
  "properties": {
    "iso:country": "GB",
    "wof:name": "DA16 2JY",
    "wof:placetype": "postalcode"
  },
  "geometry": {"coordinates":[0.10637,51.453562],"type":"Point"}
}
