{
  "type": "Feature",
  "properties": {
    "iso:country":"GB",
    "wof:name":"AB22 8PX",
    "wof:placetype":"postalcode"
},
  "geometry": {"coordinates":[-2.11826774918918,57.18529487931115],"type":"Point"}
}