{
  "type": "Feature",
  "properties": {
    "date:inception_lower": "1996-06-01",
    "date:inception_upper": "1996-06-01",
    "iso:country": "GB",
    "wof:name": "AB22 8PX",
    "wof:placetype": "postalcode"
  },
  "geometry": {"coordinates":[-2.118268,57.185295],"type":"Point"}
}
