{
  "type": "Feature",
  "properties": {
    "iso:country":"GB",
    "wof:name":"BS48 4SZ",
    "wof:placetype":"postalcode"
},
  "geometry": {"coordinates":[-2.78131697442978,51.42832358552206],"type":"Point"}
}