{
  "type": "Feature",
  "properties": {
    "date:inception_lower": "1980-01-01",
    "date:inception_upper": "1980-01-01",
    "iso:country": "GB",
    "wof:name": "TN17 4LA",
    "wof:placetype": "postalcode"
  },
  "geometry": {"coordinates":[0.581438,51.043763],"type":"Point"}
}
