{
  "type": "Feature",
  "properties": {
    "iso:country":"GB",
    "wof:name":"TS19 7PG",
    "wof:placetype":"postalcode"
},
  "geometry": {"coordinates":[-1.36095335146373,54.56872860855115],"type":"Point"}
}