{
  "type": "Feature",
  "properties": {
    "iso:country":"GB",
    "wof:name":"SN2 2JB",
    "wof:placetype":"postalcode"
},
  "geometry": {"coordinates":[-1.80641864779719,51.5817813083074],"type":"Point"}
}