{
  "type": "Feature",
  "properties": {
    "iso:country":"GB",
    "wof:name":"NN3 9TZ",
    "wof:placetype":"postalcode"
},
  "geometry": {"coordinates":[-0.83325474487506,52.25147819124339],"type":"Point"}
}