{
  "type": "Feature",
  "properties": {
    "iso:country": "GB",
    "wof:name": "CF62 3DH",
    "wof:placetype": "postalcode"
  },
  "geometry": {"coordinates":[-3.38803,51.389958],"type":"Point"}
}
