{
  "type": "Feature",
  "properties": {
    "iso:country":"GB",
    "wof:name":"CF62 3DH",
    "wof:placetype":"postalcode"
},
  "geometry": {"coordinates":[-3.38803033401912,51.38995826463986],"type":"Point"}
}