{
  "type": "Feature",
  "properties": {
    "date:inception_lower": "1980-01-01",
    "date:inception_upper": "1980-01-01",
    "iso:country": "GB",
    "wof:name": "NN1 4JJ",
    "wof:placetype": "postalcode"
  },
  "geometry": {"coordinates":[-0.879303,52.24599],"type":"Point"}
}
