{
  "type": "Feature",
  "properties": {
    "iso:country":"GB",
    "wof:name":"L31 9AU",
    "wof:placetype":"postalcode"
},
  "geometry": {"coordinates":[-2.92984137332692,53.52155937337459],"type":"Point"}
}