{
  "type": "Feature",
  "properties": {
    "iso:country":"GB",
    "wof:name":"WV8 1PR",
    "wof:placetype":"postalcode"
},
  "geometry": {"coordinates":[-2.19936743596285,52.63007728107841],"type":"Point"}
}