{
  "type": "Feature",
  "properties": {
    "iso:country":"GB",
    "wof:name":"DT4 7DH",
    "wof:placetype":"postalcode"
},
  "geometry": {"coordinates":[-2.45493503853057,50.61304425561887],"type":"Point"}
}