{
  "type": "Feature",
  "properties": {
    "iso:country":"GB",
    "wof:name":"AL10 9UW",
    "wof:placetype":"postalcode"
},
  "geometry": {"coordinates":[-0.23735991883309,51.75258857401999],"type":"Point"}
}