{
  "type": "Feature",
  "properties": {
    "iso:country": "GB",
    "wof:name": "AL10 9UW",
    "wof:placetype": "postalcode"
  },
  "geometry": {"coordinates":[-0.23736,51.752589],"type":"Point"}
}
