{
  "type": "Feature",
  "properties": {
    "date:inception_lower": "1992-08-01",
    "date:inception_upper": "1992-08-01",
    "iso:country": "GB",
    "wof:name": "DA1 5LR",
    "wof:placetype": "postalcode"
  },
  "geometry": {"coordinates":[0.221166,51.449536],"type":"Point"}
}
