{
  "type": "Feature",
  "properties": {
    "iso:country":"GB",
    "wof:name":"NW6 3EE",
    "wof:placetype":"postalcode"
},
  "geometry": {"coordinates":[-0.1879219348406,51.54427723598148],"type":"Point"}
}