{
  "type": "Feature",
  "properties": {
    "date:inception_lower": "2009-06-01",
    "date:inception_upper": "2009-06-01",
    "iso:country": "GB",
    "wof:name": "LS2 8NU",
    "wof:placetype": "postalcode"
  },
  "geometry": {"coordinates":[-1.546317,53.803465],"type":"Point"}
}
