{
  "type": "Feature",
  "properties": {
    "iso:country":"GB",
    "wof:name":"LS2 8NU",
    "wof:placetype":"postalcode"
},
  "geometry": {"coordinates":[-1.54631659381637,53.80346508559263],"type":"Point"}
}