{
  "type": "Feature",
  "properties": {
    "iso:country":"GB",
    "wof:name":"DE7 4DW",
    "wof:placetype":"postalcode"
},
  "geometry": {"coordinates":[-1.29936653761533,52.95678349530965],"type":"Point"}
}