{
  "type": "Feature",
  "properties": {
    "iso:country":"GB",
    "wof:name":"TA9 3NT",
    "wof:placetype":"postalcode"
},
  "geometry": {"coordinates":[-2.93756298113727,51.20561456657823],"type":"Point"}
}