{
  "type": "Feature",
  "properties": {
    "date:inception_lower": "2011-05-01",
    "date:inception_upper": "2011-05-01",
    "iso:country": "GB",
    "wof:name": "TA9 3NT",
    "wof:placetype": "postalcode"
  },
  "geometry": {"coordinates":[-2.937563,51.205615],"type":"Point"}
}
