{
  "type": "Feature",
  "properties": {
    "iso:country":"GB",
    "wof:name":"TF3 1QA",
    "wof:placetype":"postalcode"
},
  "geometry": {"coordinates":[-2.44389362051485,52.64696102423163],"type":"Point"}
}