{
  "type": "Feature",
  "properties": {
    "iso:country":"GB",
    "wof:name":"GU33 6JP",
    "wof:placetype":"postalcode"
},
  "geometry": {"coordinates":[-0.91342900363214,51.04939161384121],"type":"Point"}
}