{
  "type": "Feature",
  "properties": {
    "iso:country":"GB",
    "wof:name":"RG10 9UU",
    "wof:placetype":"postalcode"
},
  "geometry": {"coordinates":[-0.81932946162524,51.50519399134501],"type":"Point"}
}