{
  "type": "Feature",
  "properties": {
    "iso:country": "GB",
    "wof:name": "ST10 4DB",
    "wof:placetype": "postalcode"
  },
  "geometry": {"coordinates":[-1.888713,52.98828],"type":"Point"}
}
