{
  "type": "Feature",
  "properties": {
    "iso:country":"GB",
    "wof:name":"ST10 4DB",
    "wof:placetype":"postalcode"
},
  "geometry": {"coordinates":[-1.8887128093582,52.98827957285632],"type":"Point"}
}