{
  "type": "Feature",
  "properties": {
    "date:inception_lower": "1980-01-01",
    "date:inception_upper": "1980-01-01",
    "iso:country": "GB",
    "wof:name": "PL4 9PR",
    "wof:placetype": "postalcode"
  },
  "geometry": {"coordinates":[-4.118856,50.372365],"type":"Point"}
}
