{
  "type": "Feature",
  "properties": {
    "date:inception_lower": "2021-11-01",
    "date:inception_upper": "2021-11-01",
    "iso:country": "GB",
    "wof:name": "GU12 6TU",
    "wof:placetype": "postalcode"
  },
  "geometry": {"coordinates":[-0.70869,51.250582],"type":"Point"}
}
