{
  "type": "Feature",
  "properties": {
    "date:inception_lower":"1980-01-01",
    "date:inception_upper":"1980-01-31",
    "iso:country":"GB",
    "wof:name":"OL5 9EW",
    "wof:placetype":"postalcode"
},
  "geometry": {"coordinates":[-2.029084,53.517938],"type":"Point"}
}