{
  "type": "Feature",
  "properties": {
    "iso:country":"GB",
    "wof:name":"OL5 9EW",
    "wof:placetype":"postalcode"
},
  "geometry": {"coordinates":[-2.02908389347253,53.51793772006185],"type":"Point"}
}