{
  "type": "Feature",
  "properties": {
    "iso:country": "GB",
    "wof:name": "ME1 1UA",
    "wof:placetype": "postalcode"
  },
  "geometry": {"coordinates":[0.502317,51.38472],"type":"Point"}
}
