{
  "type": "Feature",
  "properties": {
    "iso:country":"GB",
    "wof:name":"ME1 1UA",
    "wof:placetype":"postalcode"
},
  "geometry": {"coordinates":[0.50231654256444,51.38471994979507],"type":"Point"}
}