{
  "type": "Feature",
  "properties": {
    "date:inception_lower":"1980-01-01",
    "date:inception_upper":"1980-01-31",
    "iso:country":"GB",
    "wof:name":"ME1 1UA",
    "wof:placetype":"postalcode"
},
  "geometry": {"coordinates":[0.502317,51.38472],"type":"Point"}
}