{
  "type": "Feature",
  "properties": {
    "date:inception_lower": "1980-01-01",
    "date:inception_upper": "1980-01-01",
    "iso:country": "GB",
    "wof:name": "BB1 4JR",
    "wof:placetype": "postalcode"
  },
  "geometry": {"coordinates":[-2.413368,53.767594],"type":"Point"}
}
