{
  "type": "Feature",
  "properties": {
    "date:inception_lower": "1980-01-01",
    "date:inception_upper": "1980-01-01",
    "iso:country": "GB",
    "wof:name": "TN36 4EL",
    "wof:placetype": "postalcode"
  },
  "geometry": {"coordinates":[0.709808,50.925195],"type":"Point"}
}
