{
  "type": "Feature",
  "properties": {
    "iso:country":"GB",
    "wof:name":"TN36 4EL",
    "wof:placetype":"postalcode"
},
  "geometry": {"coordinates":[0.7097772043775,50.9251981598639],"type":"Point"}
}