{
  "type": "Feature",
  "properties": {
    "iso:country": "GB",
    "wof:name": "NR9 4EF",
    "wof:placetype": "postalcode"
  },
  "geometry": {"coordinates":[1.034985,52.606267],"type":"Point"}
}
