{
  "type": "Feature",
  "properties": {
    "iso:country":"GB",
    "wof:name":"NR9 4EF",
    "wof:placetype":"postalcode"
},
  "geometry": {"coordinates":[1.03498528947873,52.60626719879158],"type":"Point"}
}