{
  "type": "Feature",
  "properties": {
    "iso:country":"GB",
    "wof:name":"NE3 4RN",
    "wof:placetype":"postalcode"
},
  "geometry": {"coordinates":[-1.63830369956254,55.00326823388122],"type":"Point"}
}