{
  "type": "Feature",
  "properties": {
    "iso:country": "GB",
    "wof:name": "CW11 3GQ",
    "wof:placetype": "postalcode"
  },
  "geometry": {"coordinates":[-2.398046,53.14154],"type":"Point"}
}
