{
  "type": "Feature",
  "properties": {
    "iso:country": "GB",
    "wof:name": "NN16 0BN",
    "wof:placetype": "postalcode"
  },
  "geometry": {"coordinates":[-0.725594,52.400247],"type":"Point"}
}
