{
  "type": "Feature",
  "properties": {
    "iso:country":"GB",
    "wof:name":"NN16 0BN",
    "wof:placetype":"postalcode"
},
  "geometry": {"coordinates":[-0.72603249096736,52.40032677569722],"type":"Point"}
}