{
  "type": "Feature",
  "properties": {
    "date:inception_lower": "1990-07-01",
    "date:inception_upper": "1990-07-01",
    "iso:country": "GB",
    "wof:name": "CR5 1JB",
    "wof:placetype": "postalcode"
  },
  "geometry": {"coordinates":[-0.113441,51.307289],"type":"Point"}
}
