{
  "type": "Feature",
  "properties": {
    "iso:country":"GB",
    "wof:name":"CR5 1JB",
    "wof:placetype":"postalcode"
},
  "geometry": {"coordinates":[-0.11344100260161,51.30728867364327],"type":"Point"}
}