{
  "type": "Feature",
  "properties": {
    "iso:country":"GB",
    "wof:name":"LE4 1BW",
    "wof:placetype":"postalcode"
},
  "geometry": {"coordinates":[-1.16293490306556,52.67338185566533],"type":"Point"}
}