{
  "type": "Feature",
  "properties": {
    "date:inception_lower": "1984-10-01",
    "date:inception_upper": "1984-10-01",
    "iso:country": "GB",
    "wof:name": "LE4 1BW",
    "wof:placetype": "postalcode"
  },
  "geometry": {"coordinates":[-1.162935,52.673382],"type":"Point"}
}
