{
  "type": "Feature",
  "properties": {
    "iso:country": "GB",
    "wof:name": "LS11 6JY",
    "wof:placetype": "postalcode"
  },
  "geometry": {"coordinates":[-1.548297,53.773138],"type":"Point"}
}
