{
  "type": "Feature",
  "properties": {
    "iso:country":"GB",
    "wof:name":"LS11 6JY",
    "wof:placetype":"postalcode"
},
  "geometry": {"coordinates":[-1.54829734193996,53.773137876346],"type":"Point"}
}