{
  "type": "Feature",
  "properties": {
    "date:inception_lower": "1980-01-01",
    "date:inception_upper": "1980-01-01",
    "iso:country": "GB",
    "wof:name": "LS11 6JY",
    "wof:placetype": "postalcode"
  },
  "geometry": {"coordinates":[-1.548297,53.773138],"type":"Point"}
}
