{
  "type": "Feature",
  "properties": {
    "iso:country": "GB",
    "wof:name": "CA6 6LQ",
    "wof:placetype": "postalcode"
  },
  "geometry": {"coordinates":[-2.75652,55.043508],"type":"Point"}
}
