{
  "type": "Feature",
  "properties": {
    "date:inception_lower": "1980-01-01",
    "date:inception_upper": "1980-01-01",
    "iso:country": "GB",
    "wof:name": "CA6 6LQ",
    "wof:placetype": "postalcode"
  },
  "geometry": {"coordinates":[-2.75652,55.043508],"type":"Point"}
}
