{
  "type": "Feature",
  "properties": {
    "date:inception_lower": "2017-08-01",
    "date:inception_upper": "2017-08-01",
    "iso:country": "GB",
    "wof:name": "AB21 9PJ",
    "wof:placetype": "postalcode"
  },
  "geometry": {"coordinates":[-2.161258,57.178953],"type":"Point"}
}
