{
  "type": "Feature",
  "properties": {
    "iso:country": "GB",
    "wof:name": "DE21 7FN",
    "wof:placetype": "postalcode"
  },
  "geometry": {"coordinates":[-1.405088,52.917491],"type":"Point"}
}
