{
  "type": "Feature",
  "properties": {
    "iso:country":"GB",
    "wof:name":"SO16 4LN",
    "wof:placetype":"postalcode"
},
  "geometry": {"coordinates":[-1.44367230865212,50.92333963534675],"type":"Point"}
}