{
  "type": "Feature",
  "properties": {
    "iso:country": "GB",
    "wof:name": "DE13 9EH",
    "wof:placetype": "postalcode"
  },
  "geometry": {"coordinates":[-1.650824,52.842579],"type":"Point"}
}
