{
  "type": "Feature",
  "properties": {
    "iso:country":"GB",
    "wof:name":"KT10 8BG",
    "wof:placetype":"postalcode"
},
  "geometry": {"coordinates":[-0.36264186635635,51.38010072098314],"type":"Point"}
}