{
  "type": "Feature",
  "properties": {
    "iso:country":"GB",
    "wof:name":"OL3 7AS",
    "wof:placetype":"postalcode"
},
  "geometry": {"coordinates":[-2.00488105929865,53.5422727009997],"type":"Point"}
}