{
  "type": "Feature",
  "properties": {
    "iso:country":"GB",
    "wof:name":"CV6 4DL",
    "wof:placetype":"postalcode"
},
  "geometry": {"coordinates":[-1.50881051652032,52.44623787557497],"type":"Point"}
}