{
  "type": "Feature",
  "properties": {
    "date:inception_lower":"1980-01-01",
    "date:inception_upper":"1980-01-31",
    "iso:country":"GB",
    "wof:name":"GU21 5NL",
    "wof:placetype":"postalcode"
},
  "geometry": {"coordinates":[-0.543267,51.338927],"type":"Point"}
}