{
  "type": "Feature",
  "properties": {
    "iso:country":"GB",
    "wof:name":"TA3 6BS",
    "wof:placetype":"postalcode"
},
  "geometry": {"coordinates":[-2.99443665720289,51.00740297318307],"type":"Point"}
}