{
  "type": "Feature",
  "properties": {
    "iso:country":"GB",
    "wof:name":"OL2 5AG",
    "wof:placetype":"postalcode"
},
  "geometry": {"coordinates":[-2.12130468195369,53.55919897884072],"type":"Point"}
}