{
  "type": "Feature",
  "properties": {
    "iso:country":"GB",
    "wof:name":"DN17 1LY",
    "wof:placetype":"postalcode"
},
  "geometry": {"coordinates":[-0.67055665030537,53.56891823563791],"type":"Point"}
}