{
  "type": "Feature",
  "properties": {
    "iso:country": "GB",
    "wof:name": "DN17 1LY",
    "wof:placetype": "postalcode"
  },
  "geometry": {"coordinates":[-0.670557,53.568918],"type":"Point"}
}
