{
  "type": "Feature",
  "properties": {
    "iso:country":"GB",
    "wof:name":"NG11 8NL",
    "wof:placetype":"postalcode"
},
  "geometry": {"coordinates":[-1.19301926059477,52.9081142871362],"type":"Point"}
}