{
  "type": "Feature",
  "properties": {
    "iso:country": "GB",
    "wof:name": "NG11 8NL",
    "wof:placetype": "postalcode"
  },
  "geometry": {"coordinates":[-1.193019,52.908114],"type":"Point"}
}
