{
  "type": "Feature",
  "properties": {
    "iso:country":"GB",
    "wof:name":"B94 6PT",
    "wof:placetype":"postalcode"
},
  "geometry": {"coordinates":[-1.75005074714056,52.35904303125459],"type":"Point"}
}