{
  "type": "Feature",
  "properties": {
    "iso:country": "GB",
    "wof:name": "B94 6PT",
    "wof:placetype": "postalcode"
  },
  "geometry": {"coordinates":[-1.750051,52.359043],"type":"Point"}
}
