{
  "type": "Feature",
  "properties": {
    "date:inception_lower":"1980-01-01",
    "date:inception_upper":"1980-01-31",
    "iso:country":"GB",
    "wof:name":"BA15 1BA",
    "wof:placetype":"postalcode"
},
  "geometry": {"coordinates":[-2.242164,51.348063],"type":"Point"}
}