{
  "type": "Feature",
  "properties": {
    "iso:country":"GB",
    "wof:name":"YO7 1HG",
    "wof:placetype":"postalcode"
},
  "geometry": {"coordinates":[-1.34406771163295,54.2323448284887],"type":"Point"}
}