{
  "type": "Feature",
  "properties": {
    "iso:country":"GB",
    "wof:name":"NR29 4AN",
    "wof:placetype":"postalcode"
},
  "geometry": {"coordinates":[1.68878815389137,52.71477532473283],"type":"Point"}
}