{
  "type": "Feature",
  "properties": {
    "iso:country": "GB",
    "wof:name": "NR29 4AN",
    "wof:placetype": "postalcode"
  },
  "geometry": {"coordinates":[1.688788,52.714775],"type":"Point"}
}
