{
  "type": "Feature",
  "properties": {
    "date:inception_lower": "1980-01-01",
    "date:inception_upper": "1980-01-01",
    "iso:country": "GB",
    "wof:name": "NR29 4AN",
    "wof:placetype": "postalcode"
  },
  "geometry": {"coordinates":[1.688788,52.714775],"type":"Point"}
}
