{
  "type": "Feature",
  "properties": {
    "iso:country":"GB",
    "wof:name":"CW2 6QT",
    "wof:placetype":"postalcode"
},
  "geometry": {"coordinates":[-2.47691669866,53.07518942643649],"type":"Point"}
}