{
  "type": "Feature",
  "properties": {
    "date:inception_lower": "1980-01-01",
    "date:inception_upper": "1980-01-01",
    "iso:country": "GB",
    "wof:name": "G69 7QU",
    "wof:placetype": "postalcode"
  },
  "geometry": {"coordinates":[-4.082341,55.855513],"type":"Point"}
}
