{
  "type": "Feature",
  "properties": {
    "iso:country":"GB",
    "wof:name":"G69 7QU",
    "wof:placetype":"postalcode"
},
  "geometry": {"coordinates":[-4.08234078196148,55.8555133715052],"type":"Point"}
}