{
  "type": "Feature",
  "properties": {
    "date:inception_lower": "1986-07-01",
    "date:inception_upper": "1986-07-01",
    "iso:country": "GB",
    "wof:name": "ST3 7UH",
    "wof:placetype": "postalcode"
  },
  "geometry": {"coordinates":[-2.098942,52.967399],"type":"Point"}
}
