{
  "type": "Feature",
  "properties": {
    "iso:country": "GB",
    "wof:name": "ST3 7UH",
    "wof:placetype": "postalcode"
  },
  "geometry": {"coordinates":[-2.098942,52.967399],"type":"Point"}
}
