{
  "type": "Feature",
  "properties": {
    "iso:country": "GB",
    "wof:name": "CW7 2LD",
    "wof:placetype": "postalcode"
  },
  "geometry": {"coordinates":[-2.550851,53.198128],"type":"Point"}
}
