{
  "type": "Feature",
  "properties": {
    "date:inception_lower":"1998-12-01",
    "date:inception_upper":"1998-12-31",
    "iso:country":"GB",
    "wof:name":"CW7 2LD",
    "wof:placetype":"postalcode"
},
  "geometry": {"coordinates":[-2.550851,53.198128],"type":"Point"}
}