{
  "type": "Feature",
  "properties": {
    "iso:country":"GB",
    "wof:name":"NP4 0AU",
    "wof:placetype":"postalcode"
},
  "geometry": {"coordinates":[-2.97897026406048,51.73798561024368],"type":"Point"}
}