{
  "type": "Feature",
  "properties": {
    "iso:country":"GB",
    "wof:name":"WS10 8BE",
    "wof:placetype":"postalcode"
},
  "geometry": {"coordinates":[-2.0279159589468,52.57006455481179],"type":"Point"}
}