{
  "type": "Feature",
  "properties": {
    "iso:country":"GB",
    "wof:name":"SW4 7PX",
    "wof:placetype":"postalcode"
},
  "geometry": {"coordinates":[-0.12395985408015,51.46221309937496],"type":"Point"}
}