{
  "type": "Feature",
  "properties": {
    "date:inception_lower": "1980-01-01",
    "date:inception_upper": "1980-01-01",
    "iso:country": "GB",
    "wof:name": "SW4 7PX",
    "wof:placetype": "postalcode"
  },
  "geometry": {"coordinates":[-0.12396,51.462213],"type":"Point"}
}
