{
  "type": "Feature",
  "properties": {
    "date:inception_lower": "2013-07-01",
    "date:inception_upper": "2013-07-01",
    "iso:country": "GB",
    "wof:name": "TN40 1RA",
    "wof:placetype": "postalcode"
  },
  "geometry": {"coordinates":[0.490382,50.842348],"type":"Point"}
}
