{
  "type": "Feature",
  "properties": {
    "iso:country": "GB",
    "wof:name": "OX17 2AD",
    "wof:placetype": "postalcode"
  },
  "geometry": {"coordinates":[-1.297144,52.063623],"type":"Point"}
}
