{
  "type": "Feature",
  "properties": {
    "date:inception_lower": "1980-01-01",
    "date:inception_upper": "1980-01-01",
    "iso:country": "GB",
    "wof:name": "OX17 2AD",
    "wof:placetype": "postalcode"
  },
  "geometry": {"coordinates":[-1.297144,52.063623],"type":"Point"}
}
