{
  "type": "Feature",
  "properties": {
    "date:inception_lower": "1980-01-01",
    "date:inception_upper": "1980-01-01",
    "iso:country": "GB",
    "wof:name": "AL1 4NT",
    "wof:placetype": "postalcode"
  },
  "geometry": {"coordinates":[-0.322716,51.756688],"type":"Point"}
}
