{
  "type": "Feature",
  "properties": {
    "iso:country":"GB",
    "wof:name":"SO20 6EP",
    "wof:placetype":"postalcode"
},
  "geometry": {"coordinates":[-1.48662008258883,51.13301113958963],"type":"Point"}
}