{
  "type": "Feature",
  "properties": {
    "iso:country": "GB",
    "wof:name": "N15 3DD",
    "wof:placetype": "postalcode"
  },
  "geometry": {"coordinates":[-0.099965,51.587488],"type":"Point"}
}
