{
  "type": "Feature",
  "properties": {
    "iso:country":"GB",
    "wof:name":"N15 3DD",
    "wof:placetype":"postalcode"
},
  "geometry": {"coordinates":[-0.09996528781733,51.58748840701993],"type":"Point"}
}