{
  "type": "Feature",
  "properties": {
    "iso:country":"GB",
    "wof:name":"LL65 2NA",
    "wof:placetype":"postalcode"
},
  "geometry": {"coordinates":[-4.67602559098062,53.29116960776669],"type":"Point"}
}