{
  "type": "Feature",
  "properties": {
    "iso:country": "GB",
    "wof:name": "LL65 2NA",
    "wof:placetype": "postalcode"
  },
  "geometry": {"coordinates":[-4.675825,53.291003],"type":"Point"}
}
