{
  "type": "Feature",
  "properties": {
    "iso:country":"GB",
    "wof:name":"CA8 1NX",
    "wof:placetype":"postalcode"
},
  "geometry": {"coordinates":[-2.7362845514751,54.94104304103992],"type":"Point"}
}