{
  "type": "Feature",
  "properties": {
    "iso:country": "GB",
    "wof:name": "CA8 1NX",
    "wof:placetype": "postalcode"
  },
  "geometry": {"coordinates":[-2.736285,54.941043],"type":"Point"}
}
