{
  "type": "Feature",
  "properties": {
    "iso:country": "GB",
    "wof:name": "CF83 8EE",
    "wof:placetype": "postalcode"
  },
  "geometry": {"coordinates":[-3.199853,51.593474],"type":"Point"}
}
