{
  "type": "Feature",
  "properties": {
    "date:inception_lower": "1980-01-01",
    "date:inception_upper": "1980-01-01",
    "iso:country": "GB",
    "wof:name": "CW9 8NX",
    "wof:placetype": "postalcode"
  },
  "geometry": {"coordinates":[-2.515992,53.222078],"type":"Point"}
}
