{
  "type": "Feature",
  "properties": {
    "iso:country":"GB",
    "wof:name":"SS3 9JY",
    "wof:placetype":"postalcode"
},
  "geometry": {"coordinates":[0.77626086934505,51.52612718744449],"type":"Point"}
}