{
  "type": "Feature",
  "properties": {
    "iso:country": "GB",
    "wof:name": "SP10 2DJ",
    "wof:placetype": "postalcode"
  },
  "geometry": {"coordinates":[-1.471404,51.202722],"type":"Point"}
}
