{
  "type": "Feature",
  "properties": {
    "iso:country":"GB",
    "wof:name":"TS28 5LQ",
    "wof:placetype":"postalcode"
},
  "geometry": {"coordinates":[-1.38209081272492,54.73163508203772],"type":"Point"}
}