{
  "type": "Feature",
  "properties": {
    "iso:country":"GB",
    "wof:name":"OL1 2XL",
    "wof:placetype":"postalcode"
},
  "geometry": {"coordinates":[-2.11705051666712,53.54935201830041],"type":"Point"}
}