{
  "type": "Feature",
  "properties": {
    "date:inception_lower": "1980-01-01",
    "date:inception_upper": "1980-01-01",
    "iso:country": "GB",
    "wof:name": "OL1 2XL",
    "wof:placetype": "postalcode"
  },
  "geometry": {"coordinates":[-2.11705,53.549352],"type":"Point"}
}
