{
  "type": "Feature",
  "properties": {
    "iso:country": "GB",
    "wof:name": "OL1 2XL",
    "wof:placetype": "postalcode"
  },
  "geometry": {"coordinates":[-2.11705,53.549352],"type":"Point"}
}
