{
  "type": "Feature",
  "properties": {
    "iso:country":"GB",
    "wof:name":"NE61 1BW",
    "wof:placetype":"postalcode"
},
  "geometry": {"coordinates":[-1.68943393942982,55.17011894983906],"type":"Point"}
}