{
  "type": "Feature",
  "properties": {
    "iso:country":"GB",
    "wof:name":"IP5 3RU",
    "wof:placetype":"postalcode"
},
  "geometry": {"coordinates":[1.27814705862895,52.06661364045544],"type":"Point"}
}