{
  "type": "Feature",
  "properties": {
    "iso:country":"GB",
    "wof:name":"ST17 9JY",
    "wof:placetype":"postalcode"
},
  "geometry": {"coordinates":[-2.14011538735628,52.78944926440751],"type":"Point"}
}