{
  "type": "Feature",
  "properties": {
    "iso:country": "GB",
    "wof:name": "ST17 9JY",
    "wof:placetype": "postalcode"
  },
  "geometry": {"coordinates":[-2.140115,52.789449],"type":"Point"}
}
