{
  "type": "Feature",
  "properties": {
    "iso:country":"GB",
    "wof:name":"B50 4JT",
    "wof:placetype":"postalcode"
},
  "geometry": {"coordinates":[-1.854686636115,52.17988851469388],"type":"Point"}
}