{
  "type": "Feature",
  "properties": {
    "iso:country": "GB",
    "wof:name": "B50 4JT",
    "wof:placetype": "postalcode"
  },
  "geometry": {"coordinates":[-1.855316,52.179575],"type":"Point"}
}
