{
  "type": "Feature",
  "properties": {
    "date:inception_lower":"1980-01-01",
    "date:inception_upper":"1980-01-31",
    "iso:country":"GB",
    "wof:name":"B50 4JT",
    "wof:placetype":"postalcode"
},
  "geometry": {"coordinates":[-1.855316,52.179575],"type":"Point"}
}