{
  "type": "Feature",
  "properties": {
    "iso:country":"GB",
    "wof:name":"EX12 2LL",
    "wof:placetype":"postalcode"
},
  "geometry": {"coordinates":[-3.07063154177645,50.70387961500052],"type":"Point"}
}