{
  "type": "Feature",
  "properties": {
    "iso:country": "GB",
    "wof:name": "EX12 2LL",
    "wof:placetype": "postalcode"
  },
  "geometry": {"coordinates":[-3.07064,50.703868],"type":"Point"}
}
