{
  "type": "Feature",
  "properties": {
    "iso:country":"GB",
    "wof:name":"DE14 1NB",
    "wof:placetype":"postalcode"
},
  "geometry": {"coordinates":[-1.63292490052324,52.80541620597688],"type":"Point"}
}