{
  "type": "Feature",
  "properties": {
    "date:inception_lower": "1980-01-01",
    "date:inception_upper": "1980-01-01",
    "iso:country": "GB",
    "wof:name": "EX22 6AF",
    "wof:placetype": "postalcode"
  },
  "geometry": {"coordinates":[-4.356466,50.81078],"type":"Point"}
}
