{
  "type": "Feature",
  "properties": {
    "iso:country":"GB",
    "wof:name":"EX22 6AF",
    "wof:placetype":"postalcode"
},
  "geometry": {"coordinates":[-4.35646569817885,50.81078028508148],"type":"Point"}
}