{
  "type": "Feature",
  "properties": {
    "iso:country":"GB",
    "wof:name":"TS11 7DA",
    "wof:placetype":"postalcode"
},
  "geometry": {"coordinates":[-1.01741450551377,54.58781709759975],"type":"Point"}
}