{
  "type": "Feature",
  "properties": {
    "iso:country":"GB",
    "wof:name":"HU12 8AF",
    "wof:placetype":"postalcode"
},
  "geometry": {"coordinates":[-0.23240892103366,53.71905154407292],"type":"Point"}
}