{
  "type": "Feature",
  "properties": {
    "iso:country":"GB",
    "wof:name":"SP7 8QR",
    "wof:placetype":"postalcode"
},
  "geometry": {"coordinates":[-2.20925852966293,51.00816697737191],"type":"Point"}
}