{
  "type": "Feature",
  "properties": {
    "date:inception_lower": "1980-01-01",
    "date:inception_upper": "1980-01-01",
    "iso:country": "GB",
    "wof:name": "SP7 8QR",
    "wof:placetype": "postalcode"
  },
  "geometry": {"coordinates":[-2.209258,51.008167],"type":"Point"}
}
