{
  "type": "Feature",
  "properties": {
    "date:inception_lower": "1980-01-01",
    "date:inception_upper": "1980-01-01",
    "iso:country": "GB",
    "wof:name": "EX34 9PQ",
    "wof:placetype": "postalcode"
  },
  "geometry": {"coordinates":[-4.107911,51.205703],"type":"Point"}
}
