{
  "type": "Feature",
  "properties": {
    "iso:country":"GB",
    "wof:name":"EX34 9PQ",
    "wof:placetype":"postalcode"
},
  "geometry": {"coordinates":[-4.10791135565009,51.20570269339831],"type":"Point"}
}