{
  "type": "Feature",
  "properties": {
    "iso:country":"GB",
    "wof:name":"LL63 5EY",
    "wof:placetype":"postalcode"
},
  "geometry": {"coordinates":[-4.46723145261352,53.19084670965056],"type":"Point"}
}