{
  "type": "Feature",
  "properties": {
    "date:inception_lower": "1997-06-01",
    "date:inception_upper": "1997-06-01",
    "iso:country": "GB",
    "wof:name": "LL63 5EY",
    "wof:placetype": "postalcode"
  },
  "geometry": {"coordinates":[-4.467231,53.190847],"type":"Point"}
}
