{
  "type": "Feature",
  "properties": {
    "iso:country": "GB",
    "wof:name": "LL63 5EY",
    "wof:placetype": "postalcode"
  },
  "geometry": {"coordinates":[-4.467231,53.190847],"type":"Point"}
}
