{
  "type": "Feature",
  "properties": {
    "iso:country":"GB",
    "wof:name":"PH2 0YA",
    "wof:placetype":"postalcode"
},
  "geometry": {"coordinates":[-3.43177317275683,56.38035992170364],"type":"Point"}
}