{
  "type": "Feature",
  "properties": {
    "iso:country":"GB",
    "wof:name":"DH6 1LR",
    "wof:placetype":"postalcode"
},
  "geometry": {"coordinates":[-1.43902679828422,54.76601614018218],"type":"Point"}
}