{
  "type": "Feature",
  "properties": {
    "iso:country": "GB",
    "wof:name": "DH6 1LR",
    "wof:placetype": "postalcode"
  },
  "geometry": {"coordinates":[-1.439027,54.766016],"type":"Point"}
}
