{
  "type": "Feature",
  "properties": {
    "iso:country": "GB",
    "wof:name": "DG12 6UA",
    "wof:placetype": "postalcode"
  },
  "geometry": {"coordinates":[-3.16976,54.986053],"type":"Point"}
}
