{
  "type": "Feature",
  "properties": {
    "date:inception_lower": "2016-03-01",
    "date:inception_upper": "2016-03-01",
    "iso:country": "GB",
    "wof:name": "DG12 6UA",
    "wof:placetype": "postalcode"
  },
  "geometry": {"coordinates":[-3.169699,54.986125],"type":"Point"}
}
