{
  "type": "Feature",
  "properties": {
    "iso:country":"GB",
    "wof:name":"DG12 6UA",
    "wof:placetype":"postalcode"
},
  "geometry": {"coordinates":[-3.1698908322996,54.98527301500657],"type":"Point"}
}