{
  "type": "Feature",
  "properties": {
    "date:inception_lower": "1996-06-01",
    "date:inception_upper": "1996-06-01",
    "iso:country": "GB",
    "wof:name": "LE11 5HE",
    "wof:placetype": "postalcode"
  },
  "geometry": {"coordinates":[-1.221701,52.779421],"type":"Point"}
}
