{
  "type": "Feature",
  "properties": {
    "iso:country":"GB",
    "wof:name":"LE11 5HE",
    "wof:placetype":"postalcode"
},
  "geometry": {"coordinates":[-1.22170112645302,52.77942132580985],"type":"Point"}
}