{
  "type": "Feature",
  "properties": {
    "iso:country":"GB",
    "wof:name":"WN7 1BU",
    "wof:placetype":"postalcode"
},
  "geometry": {"coordinates":[-2.5125222927839,53.4966535325847],"type":"Point"}
}