{
  "type": "Feature",
  "properties": {
    "iso:country": "GB",
    "wof:name": "HU9 5DN",
    "wof:placetype": "postalcode"
  },
  "geometry": {"coordinates":[-0.25086,53.756484],"type":"Point"}
}
