{
  "type": "Feature",
  "properties": {
    "iso:country":"GB",
    "wof:name":"HU9 5DN",
    "wof:placetype":"postalcode"
},
  "geometry": {"coordinates":[-0.25086043066244,53.75648411229483],"type":"Point"}
}