{
  "type": "Feature",
  "properties": {
    "iso:country":"GB",
    "wof:name":"FY5 5AZ",
    "wof:placetype":"postalcode"
},
  "geometry": {"coordinates":[-2.99341169483044,53.86534405659663],"type":"Point"}
}