{
  "type": "Feature",
  "properties": {
    "date:inception_lower": "1994-02-01",
    "date:inception_upper": "1994-02-01",
    "iso:country": "GB",
    "wof:name": "FK4 1SN",
    "wof:placetype": "postalcode"
  },
  "geometry": {"coordinates":[-3.858521,56.009111],"type":"Point"}
}
