{
  "type": "Feature",
  "properties": {
    "date:inception_lower": "2003-11-01",
    "date:inception_upper": "2003-11-01",
    "iso:country": "GB",
    "wof:name": "SO31 1AE",
    "wof:placetype": "postalcode"
  },
  "geometry": {"coordinates":[-1.267206,50.874526],"type":"Point"}
}
