{
  "type": "Feature",
  "properties": {
    "iso:country":"GB",
    "wof:name":"BN25 2RF",
    "wof:placetype":"postalcode"
},
  "geometry": {"coordinates":[0.08488905466158,50.77960005856617],"type":"Point"}
}