{
  "type": "Feature",
  "properties": {
    "iso:country":"GB",
    "wof:name":"SO45 6JY",
    "wof:placetype":"postalcode"
},
  "geometry": {"coordinates":[-1.39522129104792,50.86782195601602],"type":"Point"}
}