{
  "type": "Feature",
  "properties": {
    "date:inception_lower": "2001-12-01",
    "date:inception_upper": "2001-12-01",
    "iso:country": "GB",
    "wof:name": "SO45 6JY",
    "wof:placetype": "postalcode"
  },
  "geometry": {"coordinates":[-1.395221,50.867822],"type":"Point"}
}
