{
  "type": "Feature",
  "properties": {
    "date:inception_lower":"1983-03-01",
    "date:inception_upper":"1983-03-31",
    "iso:country":"GB",
    "wof:name":"CA16 6HL",
    "wof:placetype":"postalcode"
},
  "geometry": {"coordinates":[-2.483397,54.577716],"type":"Point"}
}