{
  "type": "Feature",
  "properties": {
    "iso:country":"GB",
    "wof:name":"CA16 6HL",
    "wof:placetype":"postalcode"
},
  "geometry": {"coordinates":[-2.48339663337259,54.57771595241112],"type":"Point"}
}