{
  "type": "Feature",
  "properties": {
    "iso:country":"GB",
    "wof:name":"LL45 2LL",
    "wof:placetype":"postalcode"
},
  "geometry": {"coordinates":[-4.10021835722764,52.81796942176442],"type":"Point"}
}