{
  "type": "Feature",
  "properties": {
    "iso:country": "GB",
    "wof:name": "LL45 2LL",
    "wof:placetype": "postalcode"
  },
  "geometry": {"coordinates":[-4.100218,52.817969],"type":"Point"}
}
