{
  "type": "Feature",
  "properties": {
    "iso:country":"GB",
    "wof:name":"CW12 3NB",
    "wof:placetype":"postalcode"
},
  "geometry": {"coordinates":[-2.18637366065568,53.13716098947143],"type":"Point"}
}