{
  "type": "Feature",
  "properties": {
    "date:inception_lower":"1980-01-01",
    "date:inception_upper":"1980-01-31",
    "iso:country":"GB",
    "wof:name":"CW12 3NB",
    "wof:placetype":"postalcode"
},
  "geometry": {"coordinates":[-2.186374,53.137161],"type":"Point"}
}