{
  "type": "Feature",
  "properties": {
    "iso:country":"GB",
    "wof:name":"TD9 9TQ",
    "wof:placetype":"postalcode"
},
  "geometry": {"coordinates":[-2.68638906316064,55.36730548593359],"type":"Point"}
}