{
  "type": "Feature",
  "properties": {
    "iso:country":"GB",
    "wof:name":"NG23 6TA",
    "wof:placetype":"postalcode"
},
  "geometry": {"coordinates":[-0.85531622370933,53.20497261059598],"type":"Point"}
}