{
  "type": "Feature",
  "properties": {
    "iso:country":"GB",
    "wof:name":"N5 2EU",
    "wof:placetype":"postalcode"
},
  "geometry": {"coordinates":[-0.09255070314333,51.55323266106675],"type":"Point"}
}