{
  "type": "Feature",
  "properties": {
    "iso:country":"GB",
    "wof:name":"TF9 4AE",
    "wof:placetype":"postalcode"
},
  "geometry": {"coordinates":[-2.45999567768838,52.9299989397015],"type":"Point"}
}