{
  "type": "Feature",
  "properties": {
    "iso:country": "GB",
    "wof:name": "TF9 4AE",
    "wof:placetype": "postalcode"
  },
  "geometry": {"coordinates":[-2.459996,52.929999],"type":"Point"}
}
