{
  "type": "Feature",
  "properties": {
    "date:inception_lower": "1980-01-01",
    "date:inception_upper": "1980-01-01",
    "iso:country": "GB",
    "wof:name": "CV1 1FQ",
    "wof:placetype": "postalcode"
  },
  "geometry": {"coordinates":[-1.510696,52.407534],"type":"Point"}
}
