{
  "type": "Feature",
  "properties": {
    "iso:country":"GB",
    "wof:name":"CV1 1FQ",
    "wof:placetype":"postalcode"
},
  "geometry": {"coordinates":[-1.51069560802614,52.407534216664],"type":"Point"}
}