{
  "type": "Feature",
  "properties": {
    "iso:country": "GB",
    "wof:name": "PE32 2HN",
    "wof:placetype": "postalcode"
  },
  "geometry": {"coordinates":[0.663452,52.773839],"type":"Point"}
}
