{
  "type": "Feature",
  "properties": {
    "date:inception_lower": "2023-03-01",
    "date:inception_upper": "2023-03-01",
    "iso:country": "GB",
    "wof:name": "M32 0GU",
    "wof:placetype": "postalcode"
  },
  "geometry": {"coordinates":[-2.29963,53.451598],"type":"Point"}
}
