{
  "type": "Feature",
  "properties": {
    "date:inception_lower":"1980-01-01",
    "date:inception_upper":"1980-01-31",
    "iso:country":"GB",
    "wof:name":"SA31 3ES",
    "wof:placetype":"postalcode"
},
  "geometry": {"coordinates":[-4.331968,51.860626],"type":"Point"}
}