{
  "type": "Feature",
  "properties": {
    "iso:country": "GB",
    "wof:name": "SA31 3ES",
    "wof:placetype": "postalcode"
  },
  "geometry": {"coordinates":[-4.331968,51.860626],"type":"Point"}
}
