{
  "type": "Feature",
  "properties": {
    "iso:country": "GB",
    "wof:name": "KA16 9DZ",
    "wof:placetype": "postalcode"
  },
  "geometry": {"coordinates":[-4.319245,55.610286],"type":"Point"}
}
