{
  "type": "Feature",
  "properties": {
    "date:inception_lower":"1980-01-01",
    "date:inception_upper":"1980-01-31",
    "iso:country":"GB",
    "wof:name":"KA16 9DZ",
    "wof:placetype":"postalcode"
},
  "geometry": {"coordinates":[-4.319245,55.610286],"type":"Point"}
}