{
  "type": "Feature",
  "properties": {
    "iso:country":"GB",
    "wof:name":"KA16 9DZ",
    "wof:placetype":"postalcode"
},
  "geometry": {"coordinates":[-4.31924498419567,55.61028560989988],"type":"Point"}
}