{
  "type": "Feature",
  "properties": {
    "date:inception_lower": "2023-03-01",
    "date:inception_upper": "2023-03-01",
    "iso:country": "GB",
    "wof:name": "DY9 8TS",
    "wof:placetype": "postalcode"
  },
  "geometry": {"coordinates":[-2.103374,52.455802],"type":"Point"}
}
