{
  "type": "Feature",
  "properties": {
    "iso:country":"GB",
    "wof:name":"BS5 8AU",
    "wof:placetype":"postalcode"
},
  "geometry": {"coordinates":[-2.55194190233525,51.45607290632206],"type":"Point"}
}