{
  "type": "Feature",
  "properties": {
    "iso:country": "GB",
    "wof:name": "BS5 8AU",
    "wof:placetype": "postalcode"
  },
  "geometry": {"coordinates":[-2.551937,51.45565],"type":"Point"}
}
