{
  "type": "Feature",
  "properties": {
    "iso:country":"GB",
    "wof:name":"BS16 2DL",
    "wof:placetype":"postalcode"
},
  "geometry": {"coordinates":[-2.53600825096176,51.48053208300503],"type":"Point"}
}