{
  "type": "Feature",
  "properties": {
    "date:inception_lower": "2021-10-01",
    "date:inception_upper": "2021-10-01",
    "iso:country": "GB",
    "wof:name": "LE12 9WL",
    "wof:placetype": "postalcode"
  },
  "geometry": {"coordinates":[-1.299406,52.773065],"type":"Point"}
}
