{
  "type": "Feature",
  "properties": {
    "iso:country":"GB",
    "wof:name":"NG32 2LX",
    "wof:placetype":"postalcode"
},
  "geometry": {"coordinates":[-0.61766753030142,52.94975944686223],"type":"Point"}
}