{
  "type": "Feature",
  "properties": {
    "iso:country":"GB",
    "wof:name":"NG7 4EQ",
    "wof:placetype":"postalcode"
},
  "geometry": {"coordinates":[-1.16428025734879,52.96202360390939],"type":"Point"}
}