{
  "type": "Feature",
  "properties": {
    "iso:country": "GB",
    "wof:name": "GL17 9SY",
    "wof:placetype": "postalcode"
  },
  "geometry": {"coordinates":[-2.576448,51.843032],"type":"Point"}
}
