{
  "type": "Feature",
  "properties": {
    "iso:country":"GB",
    "wof:name":"GL17 9SY",
    "wof:placetype":"postalcode"
},
  "geometry": {"coordinates":[-2.57644839166063,51.84303201800753],"type":"Point"}
}