{
  "type": "Feature",
  "properties": {
    "date:inception_lower":"1994-12-01",
    "date:inception_upper":"1994-12-31",
    "iso:country":"GB",
    "wof:name":"GL17 9SY",
    "wof:placetype":"postalcode"
},
  "geometry": {"coordinates":[-2.576448,51.843032],"type":"Point"}
}