{
  "type": "Feature",
  "properties": {
    "iso:country":"GB",
    "wof:name":"ME10 1LB",
    "wof:placetype":"postalcode"
},
  "geometry": {"coordinates":[0.72337841471706,51.3394774856337],"type":"Point"}
}