{
  "type": "Feature",
  "properties": {
    "iso:country": "GB",
    "wof:name": "PL14 3PP",
    "wof:placetype": "postalcode"
  },
  "geometry": {"coordinates":[-4.411348,50.429259],"type":"Point"}
}
