{
  "type": "Feature",
  "properties": {
    "date:inception_lower": "1980-01-01",
    "date:inception_upper": "1980-01-01",
    "iso:country": "GB",
    "wof:name": "PL14 3PP",
    "wof:placetype": "postalcode"
  },
  "geometry": {"coordinates":[-4.411348,50.429259],"type":"Point"}
}
