{
  "type": "Feature",
  "properties": {
    "iso:country": "GB",
    "wof:name": "KA10 6AP",
    "wof:placetype": "postalcode"
  },
  "geometry": {"coordinates":[-4.672535,55.541698],"type":"Point"}
}
