{
  "type": "Feature",
  "properties": {
    "iso:country":"GB",
    "wof:name":"W1G 8HQ",
    "wof:placetype":"postalcode"
},
  "geometry": {"coordinates":[-0.14849392907265,51.51795213804641],"type":"Point"}
}