{
  "type": "Feature",
  "properties": {
    "date:inception_lower": "1980-01-01",
    "date:inception_upper": "1980-01-01",
    "iso:country": "GB",
    "wof:name": "ST13 8BE",
    "wof:placetype": "postalcode"
  },
  "geometry": {"coordinates":[-2.034059,53.104322],"type":"Point"}
}
