{
  "type": "Feature",
  "properties": {
    "iso:country": "GB",
    "wof:name": "HD9 1LQ",
    "wof:placetype": "postalcode"
  },
  "geometry": {"coordinates":[-1.763953,53.577533],"type":"Point"}
}
