{
  "type": "Feature",
  "properties": {
    "iso:country":"GB",
    "wof:name":"BA3 5HQ",
    "wof:placetype":"postalcode"
},
  "geometry": {"coordinates":[-2.47504532967202,51.2370016953733],"type":"Point"}
}