{
  "type": "Feature",
  "properties": {
    "date:inception_lower": "1993-01-01",
    "date:inception_upper": "1993-01-01",
    "iso:country": "GB",
    "wof:name": "BA3 5HQ",
    "wof:placetype": "postalcode"
  },
  "geometry": {"coordinates":[-2.475045,51.237002],"type":"Point"}
}
