{
  "type": "Feature",
  "properties": {
    "date:inception_lower":"1983-01-01",
    "date:inception_upper":"1983-01-31",
    "iso:country":"GB",
    "wof:name":"LS24 8LZ",
    "wof:placetype":"postalcode"
},
  "geometry": {"coordinates":[-1.252463,53.889538],"type":"Point"}
}