{
  "type": "Feature",
  "properties": {
    "iso:country":"GB",
    "wof:name":"SN25 1HY",
    "wof:placetype":"postalcode"
},
  "geometry": {"coordinates":[-1.80591271054621,51.58875775681311],"type":"Point"}
}