{
  "type": "Feature",
  "properties": {
    "iso:country":"GB",
    "wof:name":"TQ5 9HF",
    "wof:placetype":"postalcode"
},
  "geometry": {"coordinates":[-3.50697097068211,50.39250948123135],"type":"Point"}
}