{
  "type": "Feature",
  "properties": {
    "date:inception_lower": "2023-03-01",
    "date:inception_upper": "2023-03-01",
    "iso:country": "GB",
    "wof:name": "LE14 3XW",
    "wof:placetype": "postalcode"
  },
  "geometry": {"coordinates":[-0.965681,52.761628],"type":"Point"}
}
