{
  "type": "Feature",
  "properties": {
    "date:inception_lower":"1980-01-01",
    "date:inception_upper":"1980-01-31",
    "iso:country":"GB",
    "wof:name":"G72 9PH",
    "wof:placetype":"postalcode"
},
  "geometry": {"coordinates":[-4.097177,55.79369],"type":"Point"}
}