{
  "type": "Feature",
  "properties": {
    "date:inception_lower": "1980-01-01",
    "date:inception_upper": "1980-01-01",
    "iso:country": "GB",
    "wof:name": "OL8 2RD",
    "wof:placetype": "postalcode"
  },
  "geometry": {"coordinates":[-2.10881,53.519995],"type":"Point"}
}
