{
  "type": "Feature",
  "properties": {
    "iso:country":"GB",
    "wof:name":"NE21 5DB",
    "wof:placetype":"postalcode"
},
  "geometry": {"coordinates":[-1.71795335462861,54.95690317212808],"type":"Point"}
}