{
  "type": "Feature",
  "properties": {
    "iso:country": "GB",
    "wof:name": "NE21 5DB",
    "wof:placetype": "postalcode"
  },
  "geometry": {"coordinates":[-1.717953,54.956903],"type":"Point"}
}
