{
  "type": "Feature",
  "properties": {
    "date:inception_lower": "1991-09-01",
    "date:inception_upper": "1991-09-01",
    "iso:country": "GB",
    "wof:name": "DN12 1AW",
    "wof:placetype": "postalcode"
  },
  "geometry": {"coordinates":[-1.190317,53.484947],"type":"Point"}
}
