{
  "type": "Feature",
  "properties": {
    "iso:country":"GB",
    "wof:name":"KY11 1FB",
    "wof:placetype":"postalcode"
},
  "geometry": {"coordinates":[-3.39407286774018,56.03524762076903],"type":"Point"}
}