{
  "type": "Feature",
  "properties": {
    "iso:country": "GB",
    "wof:name": "KY11 1FB",
    "wof:placetype": "postalcode"
  },
  "geometry": {"coordinates":[-3.394073,56.035248],"type":"Point"}
}
