{
  "type": "Feature",
  "properties": {
    "date:inception_lower": "2014-03-01",
    "date:inception_upper": "2014-03-01",
    "iso:country": "GB",
    "wof:name": "KY11 1FB",
    "wof:placetype": "postalcode"
  },
  "geometry": {"coordinates":[-3.394073,56.035248],"type":"Point"}
}
