{
  "type": "Feature",
  "properties": {
    "date:inception_lower":"2008-01-01",
    "date:inception_upper":"2008-01-31",
    "iso:country":"GB",
    "wof:name":"NE13 9AG",
    "wof:placetype":"postalcode"
},
  "geometry": {"coordinates":[-1.658517,55.021757],"type":"Point"}
}