{
  "type": "Feature",
  "properties": {
    "iso:country": "GB",
    "wof:name": "S74 8DL",
    "wof:placetype": "postalcode"
  },
  "geometry": {"coordinates":[-1.429934,53.501438],"type":"Point"}
}
