{
  "type": "Feature",
  "properties": {
    "date:inception_lower": "2007-01-01",
    "date:inception_upper": "2007-01-01",
    "iso:country": "GB",
    "wof:name": "CT1 3BS",
    "wof:placetype": "postalcode"
  },
  "geometry": {"coordinates":[1.06806,51.267269],"type":"Point"}
}
