{
  "type": "Feature",
  "properties": {
    "date:inception_lower":"1980-01-01",
    "date:inception_upper":"1980-01-31",
    "iso:country":"GB",
    "wof:name":"ST18 0LZ",
    "wof:placetype":"postalcode"
},
  "geometry": {"coordinates":[-1.996083,52.842525],"type":"Point"}
}