{
  "type": "Feature",
  "properties": {
    "date:inception_lower": "2020-08-01",
    "date:inception_upper": "2020-08-01",
    "iso:country": "GB",
    "wof:name": "CV9 3FH",
    "wof:placetype": "postalcode"
  },
  "geometry": {"coordinates":[-1.563419,52.651412],"type":"Point"}
}
