{
  "type": "Feature",
  "properties": {
    "iso:country":"GB",
    "wof:name":"TA3 5TB",
    "wof:placetype":"postalcode"
},
  "geometry": {"coordinates":[-3.03780205388415,51.02619777036978],"type":"Point"}
}