{
  "type": "Feature",
  "properties": {
    "date:inception_lower":"1991-01-01",
    "date:inception_upper":"1991-01-31",
    "iso:country":"GB",
    "wof:name":"TA3 5TB",
    "wof:placetype":"postalcode"
},
  "geometry": {"coordinates":[-3.037802,51.026198],"type":"Point"}
}