{
  "type": "Feature",
  "properties": {
    "iso:country": "GB",
    "wof:name": "LA2 8PG",
    "wof:placetype": "postalcode"
  },
  "geometry": {"coordinates":[-2.571067,54.11182],"type":"Point"}
}
