{
  "type": "Feature",
  "properties": {
    "date:inception_lower": "1999-06-01",
    "date:inception_upper": "1999-06-01",
    "iso:country": "GB",
    "wof:name": "CH42 3XX",
    "wof:placetype": "postalcode"
  },
  "geometry": {"coordinates":[-3.013442,53.372653],"type":"Point"}
}
