{
  "type": "Feature",
  "properties": {
    "iso:country":"GB",
    "wof:name":"TA6 3LF",
    "wof:placetype":"postalcode"
},
  "geometry": {"coordinates":[-3.0007844940506,51.12804500910896],"type":"Point"}
}