{
  "type": "Feature",
  "properties": {
    "date:inception_lower": "1998-06-01",
    "date:inception_upper": "1998-06-01",
    "iso:country": "GB",
    "wof:name": "YO23 3YB",
    "wof:placetype": "postalcode"
  },
  "geometry": {"coordinates":[-1.133399,53.916503],"type":"Point"}
}
