{
  "type": "Feature",
  "properties": {
    "date:inception_lower":"2001-12-01",
    "date:inception_upper":"2001-12-31",
    "iso:country":"GB",
    "wof:name":"WR11 8YG",
    "wof:placetype":"postalcode"
},
  "geometry": {"coordinates":[-1.886529,52.114778],"type":"Point"}
}