{
  "type": "Feature",
  "properties": {
    "iso:country": "GB",
    "wof:name": "OL16 3XE",
    "wof:placetype": "postalcode"
  },
  "geometry": {"coordinates":[-2.116115,53.615963],"type":"Point"}
}
