{
  "type": "Feature",
  "properties": {
    "iso:country":"GB",
    "wof:name":"OL16 3XE",
    "wof:placetype":"postalcode"
},
  "geometry": {"coordinates":[-2.11611643835506,53.61594714029187],"type":"Point"}
}