{
  "type": "Feature",
  "properties": {
    "date:inception_lower": "1983-03-01",
    "date:inception_upper": "1983-03-01",
    "iso:country": "GB",
    "wof:name": "OL16 3XE",
    "wof:placetype": "postalcode"
  },
  "geometry": {"coordinates":[-2.116115,53.615963],"type":"Point"}
}
