{
  "type": "Feature",
  "properties": {
    "iso:country": "GB",
    "wof:name": "OL16 3XE",
    "wof:placetype": "postalcode"
  },
  "geometry": {"coordinates":[-2.11607,53.61599],"type":"Point"}
}
