{
  "type": "Feature",
  "properties": {
    "date:inception_lower":"1980-01-01",
    "date:inception_upper":"1980-01-31",
    "iso:country":"GB",
    "wof:name":"TS13 4AS",
    "wof:placetype":"postalcode"
},
  "geometry": {"coordinates":[-0.899692,54.566205],"type":"Point"}
}