{
  "type": "Feature",
  "properties": {
    "iso:country":"GB",
    "wof:name":"TS13 4AS",
    "wof:placetype":"postalcode"
},
  "geometry": {"coordinates":[-0.89969163991194,54.56620545121514],"type":"Point"}
}