{
  "type": "Feature",
  "properties": {
    "iso:country":"GB",
    "wof:name":"LS16 9HL",
    "wof:placetype":"postalcode"
},
  "geometry": {"coordinates":[-1.62234738958672,53.8755691075463],"type":"Point"}
}