{
  "type": "Feature",
  "properties": {
    "date:inception_lower": "1980-01-01",
    "date:inception_upper": "1980-01-01",
    "iso:country": "GB",
    "wof:name": "S81 9QS",
    "wof:placetype": "postalcode"
  },
  "geometry": {"coordinates":[-1.121159,53.369526],"type":"Point"}
}
