{
  "type": "Feature",
  "properties": {
    "iso:country":"GB",
    "wof:name":"S81 9QS",
    "wof:placetype":"postalcode"
},
  "geometry": {"coordinates":[-1.12115922857046,53.36952613785825],"type":"Point"}
}