{
  "type": "Feature",
  "properties": {
    "iso:country": "GB",
    "wof:name": "RH12 3XE",
    "wof:placetype": "postalcode"
  },
  "geometry": {"coordinates":[-0.357879,51.072912],"type":"Point"}
}
