{
  "type": "Feature",
  "properties": {
    "iso:country":"GB",
    "wof:name":"SY13 2BW",
    "wof:placetype":"postalcode"
},
  "geometry": {"coordinates":[-2.66023031443345,52.88088910140573],"type":"Point"}
}