{
  "type": "Feature",
  "properties": {
    "iso:country": "GB",
    "wof:name": "PA13 4DS",
    "wof:placetype": "postalcode"
  },
  "geometry": {"coordinates":[-4.620203,55.896743],"type":"Point"}
}
