{
  "type": "Feature",
  "properties": {
    "iso:country":"GB",
    "wof:name":"HA0 2PJ",
    "wof:placetype":"postalcode"
},
  "geometry": {"coordinates":[-0.31911791877276,51.55634648451499],"type":"Point"}
}