{
  "type": "Feature",
  "properties": {
    "iso:country":"GB",
    "wof:name":"CH66 4XY",
    "wof:placetype":"postalcode"
},
  "geometry": {"coordinates":[-2.95947717847906,53.28282220675778],"type":"Point"}
}