{
  "type": "Feature",
  "properties": {
    "iso:country":"GB",
    "wof:name":"W1G 8GW",
    "wof:placetype":"postalcode"
},
  "geometry": {"coordinates":[-0.14835482913611,51.51889415373338],"type":"Point"}
}