{
  "type": "Feature",
  "properties": {
    "iso:country":"GB",
    "wof:name":"BH2 5JA",
    "wof:placetype":"postalcode"
},
  "geometry": {"coordinates":[-1.8852570948725,50.71638571056076],"type":"Point"}
}