{
  "type": "Feature",
  "properties": {
    "iso:country": "GB",
    "wof:name": "BH2 5JA",
    "wof:placetype": "postalcode"
  },
  "geometry": {"coordinates":[-1.885257,50.716386],"type":"Point"}
}
