{
  "type": "Feature",
  "properties": {
    "iso:country":"GB",
    "wof:name":"LS22 5EA",
    "wof:placetype":"postalcode"
},
  "geometry": {"coordinates":[-1.36897060389346,53.93671073523667],"type":"Point"}
}