{
  "type": "Feature",
  "properties": {
    "iso:country":"GB",
    "wof:name":"LE15 9DN",
    "wof:placetype":"postalcode"
},
  "geometry": {"coordinates":[-0.63625216446509,52.59606629839541],"type":"Point"}
}