{
  "type": "Feature",
  "properties": {
    "iso:country": "GB",
    "wof:name": "S6 1BJ",
    "wof:placetype": "postalcode"
  },
  "geometry": {"coordinates":[-1.508736,53.41521],"type":"Point"}
}
