{
  "type": "Feature",
  "properties": {
    "iso:country": "GB",
    "wof:name": "TR7 1SS",
    "wof:placetype": "postalcode"
  },
  "geometry": {"coordinates":[-5.077111,50.412599],"type":"Point"}
}
