{
  "type": "Feature",
  "properties": {
    "date:inception_lower":"2002-10-01",
    "date:inception_upper":"2002-10-31",
    "iso:country":"GB",
    "wof:name":"TR7 1SS",
    "wof:placetype":"postalcode"
},
  "geometry": {"coordinates":[-5.077111,50.412599],"type":"Point"}
}