{
  "type": "Feature",
  "properties": {
    "iso:country":"GB",
    "wof:name":"TR7 1SS",
    "wof:placetype":"postalcode"
},
  "geometry": {"coordinates":[-5.07711142567378,50.41259906729837],"type":"Point"}
}