{
  "type": "Feature",
  "properties": {
    "iso:country":"GB",
    "wof:name":"PA3 4AG",
    "wof:placetype":"postalcode"
},
  "geometry": {"coordinates":[-4.41968696048824,55.8487192892462],"type":"Point"}
}