{
  "type": "Feature",
  "properties": {
    "date:inception_lower": "1980-01-01",
    "date:inception_upper": "1980-01-01",
    "iso:country": "GB",
    "wof:name": "PE12 9HP",
    "wof:placetype": "postalcode"
  },
  "geometry": {"coordinates":[0.127901,52.810008],"type":"Point"}
}
