{
  "type": "Feature",
  "properties": {
    "iso:country": "GB",
    "wof:name": "PO30 2DR",
    "wof:placetype": "postalcode"
  },
  "geometry": {"coordinates":[-1.278342,50.703545],"type":"Point"}
}
