{
  "type": "Feature",
  "properties": {
    "iso:country":"GB",
    "wof:name":"PO30 2DR",
    "wof:placetype":"postalcode"
},
  "geometry": {"coordinates":[-1.2783419110238,50.70354469817903],"type":"Point"}
}