{
  "type": "Feature",
  "properties": {
    "iso:country":"GB",
    "wof:name":"B78 3HU",
    "wof:placetype":"postalcode"
},
  "geometry": {"coordinates":[-1.70770490563154,52.62991254084768],"type":"Point"}
}