{
  "type": "Feature",
  "properties": {
    "iso:country":"GB",
    "wof:name":"LE13 1LR",
    "wof:placetype":"postalcode"
},
  "geometry": {"coordinates":[-0.89334310679841,52.77779360955794],"type":"Point"}
}