{
  "type": "Feature",
  "properties": {
    "iso:country":"GB",
    "wof:name":"TR27 6DP",
    "wof:placetype":"postalcode"
},
  "geometry": {"coordinates":[-5.35611083250657,50.16197110594935],"type":"Point"}
}