{
  "type": "Feature",
  "properties": {
    "date:inception_lower": "1994-05-01",
    "date:inception_upper": "1994-05-01",
    "iso:country": "GB",
    "wof:name": "PO12 1BU",
    "wof:placetype": "postalcode"
  },
  "geometry": {"coordinates":[-1.12538,50.795331],"type":"Point"}
}
