{
  "type": "Feature",
  "properties": {
    "iso:country":"GB",
    "wof:name":"G3 7LL",
    "wof:placetype":"postalcode"
},
  "geometry": {"coordinates":[-4.27304894939682,55.86414429283102],"type":"Point"}
}