{
  "type": "Feature",
  "properties": {
    "date:inception_lower": "1985-09-01",
    "date:inception_upper": "1985-09-01",
    "iso:country": "GB",
    "wof:name": "G3 7LL",
    "wof:placetype": "postalcode"
  },
  "geometry": {"coordinates":[-4.273049,55.864144],"type":"Point"}
}
