{
  "type": "Feature",
  "properties": {
    "iso:country": "GB",
    "wof:name": "GU14 6GE",
    "wof:placetype": "postalcode"
  },
  "geometry": {"coordinates":[-0.758624,51.274208],"type":"Point"}
}
