{
  "type": "Feature",
  "properties": {
    "iso:country":"GB",
    "wof:name":"GU14 6GE",
    "wof:placetype":"postalcode"
},
  "geometry": {"coordinates":[-0.75862446169077,51.27420774003345],"type":"Point"}
}