{
  "type": "Feature",
  "properties": {
    "iso:country":"GB",
    "wof:name":"HA9 0FP",
    "wof:placetype":"postalcode"
},
  "geometry": {"coordinates":[-0.27186270379676,51.55932888885287],"type":"Point"}
}