{
  "type": "Feature",
  "properties": {
    "iso:country":"GB",
    "wof:name":"WD18 9PX",
    "wof:placetype":"postalcode"
},
  "geometry": {"coordinates":[-0.43587405475699,51.6396178887753],"type":"Point"}
}