{
  "type": "Feature",
  "properties": {
    "date:inception_lower":"2000-12-01",
    "date:inception_upper":"2000-12-31",
    "iso:country":"GB",
    "wof:name":"WD18 9PX",
    "wof:placetype":"postalcode"
},
  "geometry": {"coordinates":[-0.435874,51.639618],"type":"Point"}
}