{
  "type": "Feature",
  "properties": {
    "iso:country": "GB",
    "wof:name": "L10 7NS",
    "wof:placetype": "postalcode"
  },
  "geometry": {"coordinates":[-2.915024,53.465296],"type":"Point"}
}
