{
  "type": "Feature",
  "properties": {
    "iso:country":"GB",
    "wof:name":"CV31 1RY",
    "wof:placetype":"postalcode"
},
  "geometry": {"coordinates":[-1.50849037498749,52.28173351794871],"type":"Point"}
}