{
  "type": "Feature",
  "properties": {
    "iso:country": "GB",
    "wof:name": "IP4 5SG",
    "wof:placetype": "postalcode"
  },
  "geometry": {"coordinates":[1.204371,52.05268],"type":"Point"}
}
