{
  "type": "Feature",
  "properties": {
    "date:inception_lower":"1985-04-01",
    "date:inception_upper":"1985-04-30",
    "iso:country":"GB",
    "wof:name":"L9 1LB",
    "wof:placetype":"postalcode"
},
  "geometry": {"coordinates":[-2.949311,53.452615],"type":"Point"}
}