{
  "type": "Feature",
  "properties": {
    "iso:country": "GB",
    "wof:name": "L9 1LB",
    "wof:placetype": "postalcode"
  },
  "geometry": {"coordinates":[-2.949311,53.452615],"type":"Point"}
}
