{
  "type": "Feature",
  "properties": {
    "date:inception_lower":"1990-02-01",
    "date:inception_upper":"1990-02-28",
    "iso:country":"GB",
    "wof:name":"TQ12 6SA",
    "wof:placetype":"postalcode"
},
  "geometry": {"coordinates":[-3.656179,50.568907],"type":"Point"}
}