{
  "type": "Feature",
  "properties": {
    "iso:country": "GB",
    "wof:name": "LL14 6TA",
    "wof:placetype": "postalcode"
  },
  "geometry": {"coordinates":[-3.044308,52.984983],"type":"Point"}
}
