{
  "type": "Feature",
  "properties": {
    "date:inception_lower":"1993-01-01",
    "date:inception_upper":"1993-01-31",
    "iso:country":"GB",
    "wof:name":"LL14 6TA",
    "wof:placetype":"postalcode"
},
  "geometry": {"coordinates":[-3.044308,52.984983],"type":"Point"}
}