{
  "type": "Feature",
  "properties": {
    "iso:country":"GB",
    "wof:name":"DN22 0JZ",
    "wof:placetype":"postalcode"
},
  "geometry": {"coordinates":[-0.82702946192074,53.28131361071959],"type":"Point"}
}