{
  "type": "Feature",
  "properties": {
    "date:inception_lower": "1991-09-01",
    "date:inception_upper": "1991-09-01",
    "iso:country": "GB",
    "wof:name": "DN22 0JZ",
    "wof:placetype": "postalcode"
  },
  "geometry": {"coordinates":[-0.825738,53.283021],"type":"Point"}
}
