{
  "type": "Feature",
  "properties": {
    "iso:country": "GB",
    "wof:name": "DN22 0JZ",
    "wof:placetype": "postalcode"
  },
  "geometry": {"coordinates":[-0.826964,53.281529],"type":"Point"}
}
