{
  "type": "Feature",
  "properties": {
    "date:inception_lower": "1980-01-01",
    "date:inception_upper": "1980-01-01",
    "iso:country": "GB",
    "wof:name": "LL41 3RD",
    "wof:placetype": "postalcode"
  },
  "geometry": {"coordinates":[-3.9508,52.99227],"type":"Point"}
}
