{
  "type": "Feature",
  "properties": {
    "iso:country":"GB",
    "wof:name":"LL41 3RD",
    "wof:placetype":"postalcode"
},
  "geometry": {"coordinates":[-3.95080034195006,52.99227020057175],"type":"Point"}
}