{
  "type": "Feature",
  "properties": {
    "date:inception_lower": "2017-07-01",
    "date:inception_upper": "2017-07-01",
    "iso:country": "GB",
    "wof:name": "EH6 4EA",
    "wof:placetype": "postalcode"
  },
  "geometry": {"coordinates":[-3.18468,55.976725],"type":"Point"}
}
