{
  "type": "Feature",
  "properties": {
    "iso:country":"GB",
    "wof:name":"SY5 7BY",
    "wof:placetype":"postalcode"
},
  "geometry": {"coordinates":[-2.73715660031094,52.63856772782494],"type":"Point"}
}