{
  "type": "Feature",
  "properties": {
    "iso:country":"GB",
    "wof:name":"B19 3NF",
    "wof:placetype":"postalcode"
},
  "geometry": {"coordinates":[-1.89734946932812,52.49031033646059],"type":"Point"}
}