{
  "type": "Feature",
  "properties": {
    "date:inception_lower": "2017-12-01",
    "date:inception_upper": "2017-12-01",
    "iso:country": "GB",
    "wof:name": "LE11 1SW",
    "wof:placetype": "postalcode"
  },
  "geometry": {"coordinates":[-1.196957,52.769424],"type":"Point"}
}
