{
  "type": "Feature",
  "properties": {
    "iso:country": "GB",
    "wof:name": "EH54 8HB",
    "wof:placetype": "postalcode"
  },
  "geometry": {"coordinates":[-3.519095,55.906702],"type":"Point"}
}
