{
  "type": "Feature",
  "properties": {
    "date:inception_lower":"1993-01-01",
    "date:inception_upper":"1993-01-31",
    "iso:country":"GB",
    "wof:name":"SA4 6AU",
    "wof:placetype":"postalcode"
},
  "geometry": {"coordinates":[-4.041734,51.662301],"type":"Point"}
}