{
  "type": "Feature",
  "properties": {
    "iso:country":"GB",
    "wof:name":"PR3 0YH",
    "wof:placetype":"postalcode"
},
  "geometry": {"coordinates":[-2.87189210409348,53.85353443939158],"type":"Point"}
}