{
  "type": "Feature",
  "properties": {
    "date:inception_lower": "1980-01-01",
    "date:inception_upper": "1980-01-01",
    "iso:country": "GB",
    "wof:name": "PR3 0YH",
    "wof:placetype": "postalcode"
  },
  "geometry": {"coordinates":[-2.871892,53.853534],"type":"Point"}
}
