{
  "type": "Feature",
  "properties": {
    "iso:country": "GB",
    "wof:name": "EH20 9NP",
    "wof:placetype": "postalcode"
  },
  "geometry": {"coordinates":[-3.166908,55.884638],"type":"Point"}
}
