{
  "type": "Feature",
  "properties": {
    "iso:country":"GB",
    "wof:name":"G13 3DF",
    "wof:placetype":"postalcode"
},
  "geometry": {"coordinates":[-4.35349721877635,55.89018763724632],"type":"Point"}
}