{
  "type": "Feature",
  "properties": {
    "iso:country":"GB",
    "wof:name":"CF24 5HH",
    "wof:placetype":"postalcode"
},
  "geometry": {"coordinates":[-3.152163293509,51.47561915661733],"type":"Point"}
}