{
  "type": "Feature",
  "properties": {
    "iso:country":"GB",
    "wof:name":"KY1 3LN",
    "wof:placetype":"postalcode"
},
  "geometry": {"coordinates":[-3.14266924045797,56.13009305631312],"type":"Point"}
}