{
  "type": "Feature",
  "properties": {
    "iso:country":"GB",
    "wof:name":"TN12 8AP",
    "wof:placetype":"postalcode"
},
  "geometry": {"coordinates":[0.43625206180346,51.13659452392],"type":"Point"}
}