{
  "type": "Feature",
  "properties": {
    "iso:country":"GB",
    "wof:name":"WV14 9QU",
    "wof:placetype":"postalcode"
},
  "geometry": {"coordinates":[-2.09708234267533,52.54271674831125],"type":"Point"}
}