{
  "type": "Feature",
  "properties": {
    "iso:country":"GB",
    "wof:name":"NR13 3QA",
    "wof:placetype":"postalcode"
},
  "geometry": {"coordinates":[1.57589716656616,52.60830022123083],"type":"Point"}
}