{
  "type": "Feature",
  "properties": {
    "iso:country":"GB",
    "wof:name":"PE8 5HX",
    "wof:placetype":"postalcode"
},
  "geometry": {"coordinates":[-0.46921661132602,52.52594791772439],"type":"Point"}
}