{
  "type": "Feature",
  "properties": {
    "iso:country":"GB",
    "wof:name":"TW3 4BL",
    "wof:placetype":"postalcode"
},
  "geometry": {"coordinates":[-0.36103171357773,51.47781648175261],"type":"Point"}
}