{
  "type": "Feature",
  "properties": {
    "iso:country": "GB",
    "wof:name": "PR3 5BP",
    "wof:placetype": "postalcode"
  },
  "geometry": {"coordinates":[-2.736848,53.822449],"type":"Point"}
}
