{
  "type": "Feature",
  "properties": {
    "date:inception_lower": "2019-05-01",
    "date:inception_upper": "2019-05-01",
    "iso:country": "GB",
    "wof:name": "UB7 7GF",
    "wof:placetype": "postalcode"
  },
  "geometry": {"coordinates":[-0.475099,51.510812],"type":"Point"}
}
