{
  "type": "Feature",
  "properties": {
    "iso:country":"GB",
    "wof:name":"AB39 2WU",
    "wof:placetype":"postalcode"
},
  "geometry": {"coordinates":[-2.23658511270639,56.97033156039527],"type":"Point"}
}