{
  "type": "Feature",
  "properties": {
    "iso:country":"GB",
    "wof:name":"DY4 9BQ",
    "wof:placetype":"postalcode"
},
  "geometry": {"coordinates":[-2.06856065257718,52.53027680110718],"type":"Point"}
}