{
  "type": "Feature",
  "properties": {
    "iso:country":"GB",
    "wof:name":"L32 1TF",
    "wof:placetype":"postalcode"
},
  "geometry": {"coordinates":[-2.88856184897398,53.48641289534792],"type":"Point"}
}