{
  "type": "Feature",
  "properties": {
    "iso:country":"GB",
    "wof:name":"TQ2 8HL",
    "wof:placetype":"postalcode"
},
  "geometry": {"coordinates":[-3.53553140496354,50.49130051148306],"type":"Point"}
}