{
  "type": "Feature",
  "properties": {
    "iso:country":"GB",
    "wof:name":"B78 3RH",
    "wof:placetype":"postalcode"
},
  "geometry": {"coordinates":[-1.69934038028189,52.61513042332089],"type":"Point"}
}