{
  "type": "Feature",
  "properties": {
    "iso:country": "GB",
    "wof:name": "YO21 2AF",
    "wof:placetype": "postalcode"
  },
  "geometry": {"coordinates":[-0.814472,54.461559],"type":"Point"}
}
