{
  "type": "Feature",
  "properties": {
    "iso:country":"GB",
    "wof:name":"M24 2RJ",
    "wof:placetype":"postalcode"
},
  "geometry": {"coordinates":[-2.19020735509528,53.54994999337973],"type":"Point"}
}