{
  "type": "Feature",
  "properties": {
    "iso:country":"GB",
    "wof:name":"S3 9EG",
    "wof:placetype":"postalcode"
},
  "geometry": {"coordinates":[-1.46000305662365,53.39274347125231],"type":"Point"}
}