{
  "type": "Feature",
  "properties": {
    "iso:country":"GB",
    "wof:name":"OL2 7RB",
    "wof:placetype":"postalcode"
},
  "geometry": {"coordinates":[-2.1058766274549,53.58341017228667],"type":"Point"}
}