{
  "type": "Feature",
  "properties": {
    "iso:country": "GB",
    "wof:name": "OL2 7RB",
    "wof:placetype": "postalcode"
  },
  "geometry": {"coordinates":[-2.105877,53.58341],"type":"Point"}
}
