{
  "type": "Feature",
  "properties": {
    "iso:country": "GB",
    "wof:name": "ME10 4BY",
    "wof:placetype": "postalcode"
  },
  "geometry": {"coordinates":[0.73652,51.326274],"type":"Point"}
}
