{
  "type": "Feature",
  "properties": {
    "iso:country":"GB",
    "wof:name":"ME10 4BY",
    "wof:placetype":"postalcode"
},
  "geometry": {"coordinates":[0.73652033930099,51.32627368512681],"type":"Point"}
}