{
  "type": "Feature",
  "properties": {
    "iso:country":"GB",
    "wof:name":"DH3 3BE",
    "wof:placetype":"postalcode"
},
  "geometry": {"coordinates":[-1.57365061686725,54.85786668635457],"type":"Point"}
}