{
  "type": "Feature",
  "properties": {
    "iso:country": "GB",
    "wof:name": "DH3 3BE",
    "wof:placetype": "postalcode"
  },
  "geometry": {"coordinates":[-1.573651,54.857867],"type":"Point"}
}
