{
  "type": "Feature",
  "properties": {
    "date:inception_lower": "1980-01-01",
    "date:inception_upper": "1980-01-01",
    "iso:country": "GB",
    "wof:name": "NG24 1JY",
    "wof:placetype": "postalcode"
  },
  "geometry": {"coordinates":[-0.805934,53.076687],"type":"Point"}
}
