{
  "type": "Feature",
  "properties": {
    "iso:country":"GB",
    "wof:name":"GL7 1BJ",
    "wof:placetype":"postalcode"
},
  "geometry": {"coordinates":[-1.94829089256846,51.71727426864509],"type":"Point"}
}