{
  "type": "Feature",
  "properties": {
    "date:inception_lower": "1980-01-01",
    "date:inception_upper": "1980-01-01",
    "iso:country": "GB",
    "wof:name": "EH11 2PX",
    "wof:placetype": "postalcode"
  },
  "geometry": {"coordinates":[-3.236231,55.939528],"type":"Point"}
}
