{
  "type": "Feature",
  "properties": {
    "iso:country":"GB",
    "wof:name":"EH11 2PX",
    "wof:placetype":"postalcode"
},
  "geometry": {"coordinates":[-3.23623127589596,55.93952798024483],"type":"Point"}
}