{
  "type": "Feature",
  "properties": {
    "iso:country": "GB",
    "wof:name": "PE30 2RE",
    "wof:placetype": "postalcode"
  },
  "geometry": {"coordinates":[0.411637,52.76215],"type":"Point"}
}
