{
  "type": "Feature",
  "properties": {
    "date:inception_lower": "2019-12-01",
    "date:inception_upper": "2019-12-01",
    "iso:country": "GB",
    "wof:name": "PE30 2RE",
    "wof:placetype": "postalcode"
  },
  "geometry": {"coordinates":[0.41166,52.762041],"type":"Point"}
}
