{
  "type": "Feature",
  "properties": {
    "iso:country":"GB",
    "wof:name":"NE24 4JR",
    "wof:placetype":"postalcode"
},
  "geometry": {"coordinates":[-1.55198067804452,55.12477053859562],"type":"Point"}
}