{
  "type": "Feature",
  "properties": {
    "date:inception_lower": "2012-06-01",
    "date:inception_upper": "2012-06-01",
    "iso:country": "GB",
    "wof:name": "CF44 0BT",
    "wof:placetype": "postalcode"
  },
  "geometry": {"coordinates":[-3.40838,51.69904],"type":"Point"}
}
