{
  "type": "Feature",
  "properties": {
    "iso:country":"GB",
    "wof:name":"CF44 0BT",
    "wof:placetype":"postalcode"
},
  "geometry": {"coordinates":[-3.40838038714389,51.69904047331804],"type":"Point"}
}