{
  "type": "Feature",
  "properties": {
    "iso:country": "GB",
    "wof:name": "ME8 0LQ",
    "wof:placetype": "postalcode"
  },
  "geometry": {"coordinates":[0.588381,51.341137],"type":"Point"}
}
