{
  "type": "Feature",
  "properties": {
    "iso:country":"GB",
    "wof:name":"TR11 2DT",
    "wof:placetype":"postalcode"
},
  "geometry": {"coordinates":[-5.07993348746699,50.15603812421252],"type":"Point"}
}