{
  "type": "Feature",
  "properties": {
    "iso:country": "GB",
    "wof:name": "AL3 7EX",
    "wof:placetype": "postalcode"
  },
  "geometry": {"coordinates":[-0.404033,51.800927],"type":"Point"}
}
