{
  "type": "Feature",
  "properties": {
    "iso:country":"GB",
    "wof:name":"AL3 7EX",
    "wof:placetype":"postalcode"
},
  "geometry": {"coordinates":[-0.4040329040803,51.80092732179495],"type":"Point"}
}