{
  "type": "Feature",
  "properties": {
    "iso:country":"GB",
    "wof:name":"WF11 8QW",
    "wof:placetype":"postalcode"
},
  "geometry": {"coordinates":[-1.27455256455017,53.71106100543901],"type":"Point"}
}