{
  "type": "Feature",
  "properties": {
    "date:inception_lower": "2018-07-01",
    "date:inception_upper": "2018-07-01",
    "iso:country": "GB",
    "wof:name": "BD4 0BN",
    "wof:placetype": "postalcode"
  },
  "geometry": {"coordinates":[-1.710247,53.783315],"type":"Point"}
}
