{
  "type": "Feature",
  "properties": {
    "iso:country": "GB",
    "wof:name": "SL6 0QF",
    "wof:placetype": "postalcode"
  },
  "geometry": {"coordinates":[-0.670001,51.520978],"type":"Point"}
}
