{
  "type": "Feature",
  "properties": {
    "date:inception_lower": "2005-07-01",
    "date:inception_upper": "2005-07-01",
    "iso:country": "GB",
    "wof:name": "SL6 0QF",
    "wof:placetype": "postalcode"
  },
  "geometry": {"coordinates":[-0.670001,51.520978],"type":"Point"}
}
