{
  "type": "Feature",
  "properties": {
    "date:inception_lower":"1981-06-01",
    "date:inception_upper":"1981-06-30",
    "iso:country":"GB",
    "wof:name":"TN38 9QZ",
    "wof:placetype":"postalcode"
},
  "geometry": {"coordinates":[0.538812,50.869609],"type":"Point"}
}