{
  "type": "Feature",
  "properties": {
    "iso:country": "GB",
    "wof:name": "TN38 9QZ",
    "wof:placetype": "postalcode"
  },
  "geometry": {"coordinates":[0.538812,50.869609],"type":"Point"}
}
