{
  "type": "Feature",
  "properties": {
    "iso:country":"GB",
    "wof:name":"SG4 7DD",
    "wof:placetype":"postalcode"
},
  "geometry": {"coordinates":[-0.17013350092578,51.95415990132345],"type":"Point"}
}