{
  "type": "Feature",
  "properties": {
    "iso:country": "GB",
    "wof:name": "SG4 7DD",
    "wof:placetype": "postalcode"
  },
  "geometry": {"coordinates":[-0.170133,51.95416],"type":"Point"}
}
