{
  "type": "Feature",
  "properties": {
    "iso:country": "GB",
    "wof:name": "SA17 5UD",
    "wof:placetype": "postalcode"
  },
  "geometry": {"coordinates":[-4.353536,51.761266],"type":"Point"}
}
