{
  "type": "Feature",
  "properties": {
    "iso:country": "GB",
    "wof:name": "RH4 2NH",
    "wof:placetype": "postalcode"
  },
  "geometry": {"coordinates":[-0.326325,51.217334],"type":"Point"}
}
