{
  "type": "Feature",
  "properties": {
    "iso:country":"GB",
    "wof:name":"SM4 6JZ",
    "wof:placetype":"postalcode"
},
  "geometry": {"coordinates":[-0.18878410333194,51.39092319812942],"type":"Point"}
}