{
  "type": "Feature",
  "properties": {
    "iso:country":"GB",
    "wof:name":"M46 0LD",
    "wof:placetype":"postalcode"
},
  "geometry": {"coordinates":[-2.51154296161582,53.51672006155673],"type":"Point"}
}