{
  "type": "Feature",
  "properties": {
    "iso:country":"GB",
    "wof:name":"ST21 6LJ",
    "wof:placetype":"postalcode"
},
  "geometry": {"coordinates":[-2.28359089379017,52.84806484862858],"type":"Point"}
}