{
  "type": "Feature",
  "properties": {
    "date:inception_lower":"2007-01-01",
    "date:inception_upper":"2007-01-31",
    "iso:country":"GB",
    "wof:name":"ST21 6LJ",
    "wof:placetype":"postalcode"
},
  "geometry": {"coordinates":[-2.283591,52.848065],"type":"Point"}
}