{
  "type": "Feature",
  "properties": {
    "iso:country": "GB",
    "wof:name": "WR11 2LN",
    "wof:placetype": "postalcode"
  },
  "geometry": {"coordinates":[-1.952229,52.074653],"type":"Point"}
}
