{
  "type": "Feature",
  "properties": {
    "date:inception_lower": "1980-01-01",
    "date:inception_upper": "1980-01-01",
    "iso:country": "GB",
    "wof:name": "DL13 2LJ",
    "wof:placetype": "postalcode"
  },
  "geometry": {"coordinates":[-2.055662,54.737554],"type":"Point"}
}
