{
  "type": "Feature",
  "properties": {
    "iso:country": "GB",
    "wof:name": "DL13 2LJ",
    "wof:placetype": "postalcode"
  },
  "geometry": {"coordinates":[-2.055662,54.737554],"type":"Point"}
}
