{
  "type": "Feature",
  "properties": {
    "date:inception_lower":"2006-02-01",
    "date:inception_upper":"2006-02-28",
    "iso:country":"GB",
    "wof:name":"CH62 3RP",
    "wof:placetype":"postalcode"
},
  "geometry": {"coordinates":[-2.96817,53.336264],"type":"Point"}
}