{
  "type": "Feature",
  "properties": {
    "date:inception_lower": "1980-01-01",
    "date:inception_upper": "1980-01-01",
    "iso:country": "GB",
    "wof:name": "LN9 5DS",
    "wof:placetype": "postalcode"
  },
  "geometry": {"coordinates":[-0.114981,53.21079],"type":"Point"}
}
