{
  "type": "Feature",
  "properties": {
    "iso:country":"GB",
    "wof:name":"LN9 5DS",
    "wof:placetype":"postalcode"
},
  "geometry": {"coordinates":[-0.11498099010478,53.21079000023524],"type":"Point"}
}