{
  "type": "Feature",
  "properties": {
    "iso:country":"GB",
    "wof:name":"TR8 5HN",
    "wof:placetype":"postalcode"
},
  "geometry": {"coordinates":[-5.11835806698723,50.3857991281957],"type":"Point"}
}