{
  "type": "Feature",
  "properties": {
    "iso:country":"GB",
    "wof:name":"RM16 4LP",
    "wof:placetype":"postalcode"
},
  "geometry": {"coordinates":[0.37751342482524,51.48022924501339],"type":"Point"}
}