{
  "type": "Feature",
  "properties": {
    "iso:country":"GB",
    "wof:name":"L17 8XN",
    "wof:placetype":"postalcode"
},
  "geometry": {"coordinates":[-2.943775349972,53.38018165337927],"type":"Point"}
}