{
  "type": "Feature",
  "properties": {
    "iso:country":"GB",
    "wof:name":"GL8 8JB",
    "wof:placetype":"postalcode"
},
  "geometry": {"coordinates":[-2.15369618536764,51.64161368079024],"type":"Point"}
}