{
  "type": "Feature",
  "properties": {
    "iso:country":"GB",
    "wof:name":"N10 2LW",
    "wof:placetype":"postalcode"
},
  "geometry": {"coordinates":[-0.14567780469187,51.601789096229],"type":"Point"}
}