{
  "type": "Feature",
  "properties": {
    "iso:country":"GB",
    "wof:name":"SM1 9SP",
    "wof:placetype":"postalcode"
},
  "geometry": {"coordinates":[-0.19473769050412,51.36162713935606],"type":"Point"}
}