{
  "type": "Feature",
  "properties": {
    "iso:country":"GB",
    "wof:name":"MK13 8BS",
    "wof:placetype":"postalcode"
},
  "geometry": {"coordinates":[-0.7685268033727,52.04461277166978],"type":"Point"}
}