{
  "type": "Feature",
  "properties": {
    "iso:country":"GB",
    "wof:name":"PE25 2HE",
    "wof:placetype":"postalcode"
},
  "geometry": {"coordinates":[0.32540822322079,53.15707295511363],"type":"Point"}
}