{
  "type": "Feature",
  "properties": {
    "date:inception_lower": "1994-12-01",
    "date:inception_upper": "1994-12-01",
    "iso:country": "GB",
    "wof:name": "PE25 2HE",
    "wof:placetype": "postalcode"
  },
  "geometry": {"coordinates":[0.325408,53.157073],"type":"Point"}
}
