{
  "type": "Feature",
  "properties": {
    "iso:country": "GB",
    "wof:name": "KA10 6PS",
    "wof:placetype": "postalcode"
  },
  "geometry": {"coordinates":[-4.653927,55.54808],"type":"Point"}
}
