{
  "type": "Feature",
  "properties": {
    "iso:country":"GB",
    "wof:name":"KA10 6PS",
    "wof:placetype":"postalcode"
},
  "geometry": {"coordinates":[-4.6539267720316,55.54807990587977],"type":"Point"}
}