{
  "type": "Feature",
  "properties": {
    "iso:country": "GB",
    "wof:name": "B69 4RG",
    "wof:placetype": "postalcode"
  },
  "geometry": {"coordinates":[-2.005436,52.497825],"type":"Point"}
}
