{
  "type": "Feature",
  "properties": {
    "iso:country":"GB",
    "wof:name":"B69 4RG",
    "wof:placetype":"postalcode"
},
  "geometry": {"coordinates":[-2.00543588233888,52.49782513245243],"type":"Point"}
}