{
  "type": "Feature",
  "properties": {
    "iso:country":"GB",
    "wof:name":"S25 5HT",
    "wof:placetype":"postalcode"
},
  "geometry": {"coordinates":[-1.22738067255485,53.34912789878243],"type":"Point"}
}