{
  "type": "Feature",
  "properties": {
    "date:inception_lower": "1980-01-01",
    "date:inception_upper": "1980-01-01",
    "iso:country": "GB",
    "wof:name": "SE21 7LH",
    "wof:placetype": "postalcode"
  },
  "geometry": {"coordinates":[-0.07429,51.437667],"type":"Point"}
}
