{
  "type": "Feature",
  "properties": {
    "iso:country":"GB",
    "wof:name":"SE21 7LH",
    "wof:placetype":"postalcode"
},
  "geometry": {"coordinates":[-0.07787799870288,51.43788786461587],"type":"Point"}
}