{
  "type": "Feature",
  "properties": {
    "iso:country":"GB",
    "wof:name":"OX29 7SE",
    "wof:placetype":"postalcode"
},
  "geometry": {"coordinates":[-1.42490037453818,51.72739730040334],"type":"Point"}
}