{
  "type": "Feature",
  "properties": {
    "iso:country":"GB",
    "wof:name":"ME17 1NG",
    "wof:placetype":"postalcode"
},
  "geometry": {"coordinates":[0.68408017802542,51.24289984636216],"type":"Point"}
}