{
  "type": "Feature",
  "properties": {
    "date:inception_lower": "1992-01-01",
    "date:inception_upper": "1992-01-01",
    "iso:country": "GB",
    "wof:name": "ME17 1NG",
    "wof:placetype": "postalcode"
  },
  "geometry": {"coordinates":[0.68408,51.2429],"type":"Point"}
}
