{
  "type": "Feature",
  "properties": {
    "iso:country":"GB",
    "wof:name":"SS8 9XE",
    "wof:placetype":"postalcode"
},
  "geometry": {"coordinates":[0.58322427225144,51.53029608302384],"type":"Point"}
}