{
  "type": "Feature",
  "properties": {
    "iso:country": "GB",
    "wof:name": "TR7 2BY",
    "wof:placetype": "postalcode"
  },
  "geometry": {"coordinates":[-5.079154,50.412833],"type":"Point"}
}
