{
  "type": "Feature",
  "properties": {
    "date:inception_lower": "2022-03-01",
    "date:inception_upper": "2022-03-01",
    "iso:country": "GB",
    "wof:name": "DE11 0YE",
    "wof:placetype": "postalcode"
  },
  "geometry": {"coordinates":[-1.584239,52.783249],"type":"Point"}
}
