{
  "type": "Feature",
  "properties": {
    "iso:country":"GB",
    "wof:name":"SN1 2PR",
    "wof:placetype":"postalcode"
},
  "geometry": {"coordinates":[-1.7594530155318,51.57156129590508],"type":"Point"}
}