{
  "type": "Feature",
  "properties": {
    "date:inception_lower": "1980-01-01",
    "date:inception_upper": "1980-01-01",
    "iso:country": "GB",
    "wof:name": "SN1 2PR",
    "wof:placetype": "postalcode"
  },
  "geometry": {"coordinates":[-1.759453,51.571561],"type":"Point"}
}
