{
  "type": "Feature",
  "properties": {
    "iso:country":"GB",
    "wof:name":"M4 7DJ",
    "wof:placetype":"postalcode"
},
  "geometry": {"coordinates":[-2.21677945775921,53.47785368618012],"type":"Point"}
}