{
  "type": "Feature",
  "properties": {
    "iso:country":"GB",
    "wof:name":"NW6 5UA",
    "wof:placetype":"postalcode"
},
  "geometry": {"coordinates":[-0.19202738966725,51.53711966946351],"type":"Point"}
}