{
  "type": "Feature",
  "properties": {
    "iso:country":"GB",
    "wof:name":"N5 2PJ",
    "wof:placetype":"postalcode"
},
  "geometry": {"coordinates":[-0.09622780826185,51.55360712300223],"type":"Point"}
}