{
  "type": "Feature",
  "properties": {
    "iso:country":"GB",
    "wof:name":"TR16 5BX",
    "wof:placetype":"postalcode"
},
  "geometry": {"coordinates":[-5.19716853108593,50.2576162478279],"type":"Point"}
}