{
  "type": "Feature",
  "properties": {
    "date:inception_lower":"2013-02-01",
    "date:inception_upper":"2013-02-28",
    "iso:country":"GB",
    "wof:name":"MK18 7RJ",
    "wof:placetype":"postalcode"
},
  "geometry": {"coordinates":[-0.976824,51.987401],"type":"Point"}
}