{
  "type": "Feature",
  "properties": {
    "iso:country":"GB",
    "wof:name":"MK18 7RJ",
    "wof:placetype":"postalcode"
},
  "geometry": {"coordinates":[-0.97682437087519,51.98757913400807],"type":"Point"}
}