{
  "type": "Feature",
  "properties": {
    "date:inception_lower": "2022-08-01",
    "date:inception_upper": "2022-08-01",
    "iso:country": "GB",
    "wof:name": "OL9 7FQ",
    "wof:placetype": "postalcode"
  },
  "geometry": {"coordinates":[-2.137136,53.530561],"type":"Point"}
}
