{
  "type": "Feature",
  "properties": {
    "iso:country": "GB",
    "wof:name": "KT8 1NX",
    "wof:placetype": "postalcode"
  },
  "geometry": {"coordinates":[-0.366168,51.405356],"type":"Point"}
}
