{
  "type": "Feature",
  "properties": {
    "iso:country":"GB",
    "wof:name":"KT8 1NX",
    "wof:placetype":"postalcode"
},
  "geometry": {"coordinates":[-0.36616837147204,51.40535574147722],"type":"Point"}
}