{
  "type": "Feature",
  "properties": {
    "date:inception_lower": "1980-01-01",
    "date:inception_upper": "1980-01-01",
    "iso:country": "GB",
    "wof:name": "NP4 7HJ",
    "wof:placetype": "postalcode"
  },
  "geometry": {"coordinates":[-3.065573,51.728106],"type":"Point"}
}
