{
  "type": "Feature",
  "properties": {
    "date:inception_lower": "2018-05-01",
    "date:inception_upper": "2018-05-01",
    "iso:country": "GB",
    "wof:name": "SY10 7HE",
    "wof:placetype": "postalcode"
  },
  "geometry": {"coordinates":[-3.026318,52.919216],"type":"Point"}
}
