{
  "type": "Feature",
  "properties": {
    "iso:country": "GB",
    "wof:name": "B79 7LU",
    "wof:placetype": "postalcode"
  },
  "geometry": {"coordinates":[-1.696306,52.633228],"type":"Point"}
}
