{
  "type": "Feature",
  "properties": {
    "iso:country":"GB",
    "wof:name":"B79 7LU",
    "wof:placetype":"postalcode"
},
  "geometry": {"coordinates":[-1.6963056694508,52.63322808707055],"type":"Point"}
}