{
  "type": "Feature",
  "properties": {
    "date:inception_lower":"1985-10-01",
    "date:inception_upper":"1985-10-31",
    "iso:country":"GB",
    "wof:name":"CH7 2BN",
    "wof:placetype":"postalcode"
},
  "geometry": {"coordinates":[-3.081274,53.159301],"type":"Point"}
}