{
  "type": "Feature",
  "properties": {
    "date:inception_lower": "2000-10-01",
    "date:inception_upper": "2000-10-01",
    "iso:country": "GB",
    "wof:name": "GU16 8DL",
    "wof:placetype": "postalcode"
  },
  "geometry": {"coordinates":[-0.731895,51.3156],"type":"Point"}
}
