{
  "type": "Feature",
  "properties": {
    "date:inception_lower": "1995-07-01",
    "date:inception_upper": "1995-07-01",
    "iso:country": "GB",
    "wof:name": "RG45 7HB",
    "wof:placetype": "postalcode"
  },
  "geometry": {"coordinates":[-0.77961,51.364539],"type":"Point"}
}
