{
  "type": "Feature",
  "properties": {
    "iso:country": "GB",
    "wof:name": "RG45 7HB",
    "wof:placetype": "postalcode"
  },
  "geometry": {"coordinates":[-0.77961,51.364539],"type":"Point"}
}
