{
  "type": "Feature",
  "properties": {
    "iso:country":"GB",
    "wof:name":"PE12 8TG",
    "wof:placetype":"postalcode"
},
  "geometry": {"coordinates":[0.06310912624719,52.80256278255179],"type":"Point"}
}