{
  "type": "Feature",
  "properties": {
    "iso:country": "GB",
    "wof:name": "PE12 8TG",
    "wof:placetype": "postalcode"
  },
  "geometry": {"coordinates":[0.063109,52.802563],"type":"Point"}
}
