{
  "type": "Feature",
  "properties": {
    "date:inception_lower":"2005-06-01",
    "date:inception_upper":"2005-06-30",
    "iso:country":"GB",
    "wof:name":"GU51 3AL",
    "wof:placetype":"postalcode"
},
  "geometry": {"coordinates":[-0.844087,51.279138],"type":"Point"}
}