{
  "type": "Feature",
  "properties": {
    "iso:country":"GB",
    "wof:name":"PR5 4JJ",
    "wof:placetype":"postalcode"
},
  "geometry": {"coordinates":[-2.67164947872441,53.74633587099687],"type":"Point"}
}