{
  "type": "Feature",
  "properties": {
    "iso:country":"GB",
    "wof:name":"HU9 3SY",
    "wof:placetype":"postalcode"
},
  "geometry": {"coordinates":[-0.28499386047846,53.75751671658578],"type":"Point"}
}