{
  "type": "Feature",
  "properties": {
    "iso:country":"GB",
    "wof:name":"GU22 8AH",
    "wof:placetype":"postalcode"
},
  "geometry": {"coordinates":[-0.54125079240202,51.32194194493191],"type":"Point"}
}