{
  "type": "Feature",
  "properties": {
    "date:inception_lower": "1980-01-01",
    "date:inception_upper": "1980-01-01",
    "iso:country": "GB",
    "wof:name": "MK6 2DY",
    "wof:placetype": "postalcode"
  },
  "geometry": {"coordinates":[-0.742681,52.033982],"type":"Point"}
}
