{
  "type": "Feature",
  "properties": {
    "iso:country":"GB",
    "wof:name":"NN7 4EL",
    "wof:placetype":"postalcode"
},
  "geometry": {"coordinates":[-0.98353300354053,52.26903263227015],"type":"Point"}
}