{
  "type": "Feature",
  "properties": {
    "iso:country": "GB",
    "wof:name": "LN4 4UW",
    "wof:placetype": "postalcode"
  },
  "geometry": {"coordinates":[-0.18248,53.079931],"type":"Point"}
}
