{
  "type": "Feature",
  "properties": {
    "iso:country":"GB",
    "wof:name":"LN4 4UW",
    "wof:placetype":"postalcode"
},
  "geometry": {"coordinates":[-0.1823576773886,53.0800943500396],"type":"Point"}
}