{
  "type": "Feature",
  "properties": {
    "date:inception_lower": "1980-01-01",
    "date:inception_upper": "1980-01-01",
    "iso:country": "GB",
    "wof:name": "LN4 4UW",
    "wof:placetype": "postalcode"
  },
  "geometry": {"coordinates":[-0.182353,53.080118],"type":"Point"}
}
