{
  "type": "Feature",
  "properties": {
    "iso:country": "GB",
    "wof:name": "NR21 9EU",
    "wof:placetype": "postalcode"
  },
  "geometry": {"coordinates":[0.837748,52.83643],"type":"Point"}
}
