{
  "type": "Feature",
  "properties": {
    "date:inception_lower": "2007-01-01",
    "date:inception_upper": "2007-01-01",
    "iso:country": "GB",
    "wof:name": "SN1 2NZ",
    "wof:placetype": "postalcode"
  },
  "geometry": {"coordinates":[-1.768814,51.563659],"type":"Point"}
}
