{
  "type": "Feature",
  "properties": {
    "iso:country":"GB",
    "wof:name":"SN1 2NZ",
    "wof:placetype":"postalcode"
},
  "geometry": {"coordinates":[-1.76881405116221,51.56365868468198],"type":"Point"}
}