{
  "type": "Feature",
  "properties": {
    "date:inception_lower":"2004-06-01",
    "date:inception_upper":"2004-06-30",
    "iso:country":"GB",
    "wof:name":"SN9 5JT",
    "wof:placetype":"postalcode"
},
  "geometry": {"coordinates":[-1.777852,51.342583],"type":"Point"}
}