{
  "type": "Feature",
  "properties": {
    "iso:country": "GB",
    "wof:name": "SN9 5JT",
    "wof:placetype": "postalcode"
  },
  "geometry": {"coordinates":[-1.777852,51.342583],"type":"Point"}
}
