{
  "type": "Feature",
  "properties": {
    "iso:country":"GB",
    "wof:name":"HD1 4PT",
    "wof:placetype":"postalcode"
},
  "geometry": {"coordinates":[-1.80412594043259,53.65259670069494],"type":"Point"}
}