{
  "type": "Feature",
  "properties": {
    "iso:country": "GB",
    "wof:name": "HD1 4PT",
    "wof:placetype": "postalcode"
  },
  "geometry": {"coordinates":[-1.804126,53.652597],"type":"Point"}
}
