{
  "type": "Feature",
  "properties": {
    "iso:country":"GB",
    "wof:name":"B33 8DH",
    "wof:placetype":"postalcode"
},
  "geometry": {"coordinates":[-1.80296262022886,52.48325077070937],"type":"Point"}
}