{
  "type": "Feature",
  "properties": {
    "iso:country":"GB",
    "wof:name":"PR2 8NR",
    "wof:placetype":"postalcode"
},
  "geometry": {"coordinates":[-2.70694068959735,53.77737587581442],"type":"Point"}
}