{
  "type": "Feature",
  "properties": {
    "date:inception_lower": "1980-01-01",
    "date:inception_upper": "1980-01-01",
    "iso:country": "GB",
    "wof:name": "WF10 1JD",
    "wof:placetype": "postalcode"
  },
  "geometry": {"coordinates":[-1.354065,53.726796],"type":"Point"}
}
