{
  "type": "Feature",
  "properties": {
    "iso:country":"GB",
    "wof:name":"WF10 1JD",
    "wof:placetype":"postalcode"
},
  "geometry": {"coordinates":[-1.35406536124844,53.72679589790782],"type":"Point"}
}