{
  "type": "Feature",
  "properties": {
    "date:inception_lower":"1998-12-01",
    "date:inception_upper":"1998-12-31",
    "iso:country":"GB",
    "wof:name":"SL4 5AA",
    "wof:placetype":"postalcode"
},
  "geometry": {"coordinates":[-0.626439,51.480839],"type":"Point"}
}