{
  "type": "Feature",
  "properties": {
    "iso:country":"GB",
    "wof:name":"SL4 5AA",
    "wof:placetype":"postalcode"
},
  "geometry": {"coordinates":[-0.62643887050883,51.48083870402863],"type":"Point"}
}