{
  "type": "Feature",
  "properties": {
    "date:inception_lower":"2006-09-01",
    "date:inception_upper":"2006-09-30",
    "iso:country":"GB",
    "wof:name":"CB22 3AB",
    "wof:placetype":"postalcode"
},
  "geometry": {"coordinates":[0.161635,52.165552],"type":"Point"}
}