{
  "type": "Feature",
  "properties": {
    "iso:country":"GB",
    "wof:name":"CA9 3SR",
    "wof:placetype":"postalcode"
},
  "geometry": {"coordinates":[-2.43741038782735,54.81046669596385],"type":"Point"}
}