{
  "type": "Feature",
  "properties": {
    "iso:country":"GB",
    "wof:name":"M32 8DT",
    "wof:placetype":"postalcode"
},
  "geometry": {"coordinates":[-2.31563862836639,53.44978689247568],"type":"Point"}
}