{
  "type": "Feature",
  "properties": {
    "date:inception_lower": "2017-11-01",
    "date:inception_upper": "2017-11-01",
    "iso:country": "GB",
    "wof:name": "SW4 6BF",
    "wof:placetype": "postalcode"
  },
  "geometry": {"coordinates":[-0.126918,51.469851],"type":"Point"}
}
