{
  "type": "Feature",
  "properties": {
    "iso:country":"GB",
    "wof:name":"M11 2FZ",
    "wof:placetype":"postalcode"
},
  "geometry": {"coordinates":[-2.18148973737987,53.47383180511019],"type":"Point"}
}