{
  "type": "Feature",
  "properties": {
    "date:inception_lower": "1983-07-01",
    "date:inception_upper": "1983-07-01",
    "iso:country": "GB",
    "wof:name": "M11 2FZ",
    "wof:placetype": "postalcode"
  },
  "geometry": {"coordinates":[-2.18149,53.473832],"type":"Point"}
}
