{
  "type": "Feature",
  "properties": {
    "date:inception_lower":"1998-12-01",
    "date:inception_upper":"1998-12-31",
    "iso:country":"GB",
    "wof:name":"BN43 6NR",
    "wof:placetype":"postalcode"
},
  "geometry": {"coordinates":[-0.254326,50.834365],"type":"Point"}
}