{
  "type": "Feature",
  "properties": {
    "iso:country": "GB",
    "wof:name": "BN43 6NR",
    "wof:placetype": "postalcode"
  },
  "geometry": {"coordinates":[-0.254326,50.834365],"type":"Point"}
}
