{
  "type": "Feature",
  "properties": {
    "iso:country":"GB",
    "wof:name":"TF2 7RR",
    "wof:placetype":"postalcode"
},
  "geometry": {"coordinates":[-2.42568107581457,52.71504407919215],"type":"Point"}
}