{
  "type": "Feature",
  "properties": {
    "date:inception_lower":"1980-01-01",
    "date:inception_upper":"1980-01-31",
    "iso:country":"GB",
    "wof:name":"EX31 2PA",
    "wof:placetype":"postalcode"
},
  "geometry": {"coordinates":[-4.103501,51.061778],"type":"Point"}
}