{
  "type": "Feature",
  "properties": {
    "iso:country": "GB",
    "wof:name": "EX31 2PA",
    "wof:placetype": "postalcode"
  },
  "geometry": {"coordinates":[-4.103501,51.061778],"type":"Point"}
}
