{
  "type": "Feature",
  "properties": {
    "iso:country":"GB",
    "wof:name":"EX31 2PA",
    "wof:placetype":"postalcode"
},
  "geometry": {"coordinates":[-4.10347750618474,51.06178158398959],"type":"Point"}
}