{
  "type": "Feature",
  "properties": {
    "date:inception_lower": "2004-05-01",
    "date:inception_upper": "2004-05-01",
    "iso:country": "GB",
    "wof:name": "NR32 1PX",
    "wof:placetype": "postalcode"
  },
  "geometry": {"coordinates":[1.755348,52.480886],"type":"Point"}
}
