{
  "type": "Feature",
  "properties": {
    "date:inception_lower": "2002-07-01",
    "date:inception_upper": "2002-07-01",
    "iso:country": "GB",
    "wof:name": "IP12 4UD",
    "wof:placetype": "postalcode"
  },
  "geometry": {"coordinates":[1.282984,52.076049],"type":"Point"}
}
