{
  "type": "Feature",
  "properties": {
    "iso:country": "GB",
    "wof:name": "IP12 4UD",
    "wof:placetype": "postalcode"
  },
  "geometry": {"coordinates":[1.282984,52.076049],"type":"Point"}
}
