{
  "type": "Feature",
  "properties": {
    "iso:country":"GB",
    "wof:name":"LE19 1SD",
    "wof:placetype":"postalcode"
},
  "geometry": {"coordinates":[-1.19050836655211,52.59537867071522],"type":"Point"}
}