{
  "type": "Feature",
  "properties": {
    "date:inception_lower":"2007-08-01",
    "date:inception_upper":"2007-08-31",
    "iso:country":"GB",
    "wof:name":"LE19 1SD",
    "wof:placetype":"postalcode"
},
  "geometry": {"coordinates":[-1.190508,52.595379],"type":"Point"}
}