{
  "type": "Feature",
  "properties": {
    "iso:country":"GB",
    "wof:name":"WR4 0NR",
    "wof:placetype":"postalcode"
},
  "geometry": {"coordinates":[-2.17138524344413,52.19473195338423],"type":"Point"}
}