{
  "type": "Feature",
  "properties": {
    "date:inception_lower": "1997-06-01",
    "date:inception_upper": "1997-06-01",
    "iso:country": "GB",
    "wof:name": "WR4 0NR",
    "wof:placetype": "postalcode"
  },
  "geometry": {"coordinates":[-2.171385,52.194732],"type":"Point"}
}
