{
  "type": "Feature",
  "properties": {
    "iso:country":"GB",
    "wof:name":"AB51 7QX",
    "wof:placetype":"postalcode"
},
  "geometry": {"coordinates":[-2.55377995247265,57.18682329844705],"type":"Point"}
}