{
  "type": "Feature",
  "properties": {
    "iso:country": "GB",
    "wof:name": "AB51 7QX",
    "wof:placetype": "postalcode"
  },
  "geometry": {"coordinates":[-2.55378,57.186823],"type":"Point"}
}
