{
  "type": "Feature",
  "properties": {
    "iso:country":"GB",
    "wof:name":"WS3 5BJ",
    "wof:placetype":"postalcode"
},
  "geometry": {"coordinates":[-1.97073012746773,52.63466485010782],"type":"Point"}
}