{
  "type": "Feature",
  "properties": {
    "date:inception_lower": "1980-01-01",
    "date:inception_upper": "1980-01-01",
    "iso:country": "GB",
    "wof:name": "WS3 5BJ",
    "wof:placetype": "postalcode"
  },
  "geometry": {"coordinates":[-1.97073,52.634665],"type":"Point"}
}
