{
  "type": "Feature",
  "properties": {
    "iso:country":"GB",
    "wof:name":"TW5 0DQ",
    "wof:placetype":"postalcode"
},
  "geometry": {"coordinates":[-0.38219824998321,51.47624899794668],"type":"Point"}
}