{
  "type": "Feature",
  "properties": {
    "iso:country": "GB",
    "wof:name": "TW5 0DQ",
    "wof:placetype": "postalcode"
  },
  "geometry": {"coordinates":[-0.382198,51.476249],"type":"Point"}
}
