{
  "type": "Feature",
  "properties": {
    "iso:country": "GB",
    "wof:name": "LE11 5QN",
    "wof:placetype": "postalcode"
  },
  "geometry": {"coordinates":[-1.24276,52.77989],"type":"Point"}
}
