{
  "type": "Feature",
  "properties": {
    "date:inception_lower":"1996-06-01",
    "date:inception_upper":"1996-06-30",
    "iso:country":"GB",
    "wof:name":"LE11 5QN",
    "wof:placetype":"postalcode"
},
  "geometry": {"coordinates":[-1.24276,52.77989],"type":"Point"}
}