{
  "type": "Feature",
  "properties": {
    "date:inception_lower": "1980-01-01",
    "date:inception_upper": "1980-01-01",
    "iso:country": "GB",
    "wof:name": "SA37 0JB",
    "wof:placetype": "postalcode"
  },
  "geometry": {"coordinates":[-4.6704,52.002276],"type":"Point"}
}
