{
  "type": "Feature",
  "properties": {
    "iso:country": "GB",
    "wof:name": "SA37 0JB",
    "wof:placetype": "postalcode"
  },
  "geometry": {"coordinates":[-4.670419,52.002356],"type":"Point"}
}
