{
  "type": "Feature",
  "properties": {
    "iso:country": "GB",
    "wof:name": "AL1 3RY",
    "wof:placetype": "postalcode"
  },
  "geometry": {"coordinates":[-0.332595,51.754551],"type":"Point"}
}
