{
  "type": "Feature",
  "properties": {
    "iso:country":"GB",
    "wof:name":"EN3 6FQ",
    "wof:placetype":"postalcode"
},
  "geometry": {"coordinates":[-0.02699280506976,51.67440158757752],"type":"Point"}
}