{
  "type": "Feature",
  "properties": {
    "date:inception_lower":"2001-12-01",
    "date:inception_upper":"2001-12-31",
    "iso:country":"GB",
    "wof:name":"EN3 6FQ",
    "wof:placetype":"postalcode"
},
  "geometry": {"coordinates":[-0.026993,51.674402],"type":"Point"}
}