{
  "type": "Feature",
  "properties": {
    "date:inception_lower": "2019-01-01",
    "date:inception_upper": "2019-01-01",
    "iso:country": "GB",
    "wof:name": "CT16 3FR",
    "wof:placetype": "postalcode"
  },
  "geometry": {"coordinates":[1.307232,51.160571],"type":"Point"}
}
