{
  "type": "Feature",
  "properties": {
    "date:inception_lower": "1988-03-01",
    "date:inception_upper": "1988-03-01",
    "iso:country": "GB",
    "wof:name": "HA2 9TJ",
    "wof:placetype": "postalcode"
  },
  "geometry": {"coordinates":[-0.369725,51.574406],"type":"Point"}
}
