{
  "type": "Feature",
  "properties": {
    "iso:country":"GB",
    "wof:name":"HA2 9TJ",
    "wof:placetype":"postalcode"
},
  "geometry": {"coordinates":[-0.36972524176767,51.57440643601299],"type":"Point"}
}