{
  "type": "Feature",
  "properties": {
    "iso:country":"GB",
    "wof:name":"PO36 9AJ",
    "wof:placetype":"postalcode"
},
  "geometry": {"coordinates":[-1.15535068977068,50.66112648627198],"type":"Point"}
}