{
  "type": "Feature",
  "properties": {
    "iso:country": "GB",
    "wof:name": "PO36 9AJ",
    "wof:placetype": "postalcode"
  },
  "geometry": {"coordinates":[-1.15534,50.661124],"type":"Point"}
}
