{
  "type": "Feature",
  "properties": {
    "iso:country":"GB",
    "wof:name":"ML3 7DP",
    "wof:placetype":"postalcode"
},
  "geometry": {"coordinates":[-4.02981914334768,55.77300960890437],"type":"Point"}
}