{
  "type": "Feature",
  "properties": {
    "iso:country": "GB",
    "wof:name": "YO60 7HU",
    "wof:placetype": "postalcode"
  },
  "geometry": {"coordinates":[-0.851592,54.109641],"type":"Point"}
}
