{
  "type": "Feature",
  "properties": {
    "iso:country":"GB",
    "wof:name":"YO60 7HU",
    "wof:placetype":"postalcode"
},
  "geometry": {"coordinates":[-0.85159242015727,54.10964082066037],"type":"Point"}
}