{
  "type": "Feature",
  "properties": {
    "date:inception_lower":"1998-06-01",
    "date:inception_upper":"1998-06-30",
    "iso:country":"GB",
    "wof:name":"YO60 7HU",
    "wof:placetype":"postalcode"
},
  "geometry": {"coordinates":[-0.851592,54.109641],"type":"Point"}
}