{
  "type": "Feature",
  "properties": {
    "date:inception_lower": "2007-07-01",
    "date:inception_upper": "2007-07-01",
    "iso:country": "GB",
    "wof:name": "KA6 7PJ",
    "wof:placetype": "postalcode"
  },
  "geometry": {"coordinates":[-4.498572,55.355632],"type":"Point"}
}
