{
  "type": "Feature",
  "properties": {
    "iso:country":"GB",
    "wof:name":"M38 0FQ",
    "wof:placetype":"postalcode"
},
  "geometry": {"coordinates":[-2.43554117191547,53.52773547416437],"type":"Point"}
}