{
  "type": "Feature",
  "properties": {
    "date:inception_lower":"2012-03-01",
    "date:inception_upper":"2012-03-31",
    "iso:country":"GB",
    "wof:name":"MK45 4GD",
    "wof:placetype":"postalcode"
},
  "geometry": {"coordinates":[-0.431289,51.966093],"type":"Point"}
}