{
  "type": "Feature",
  "properties": {
    "iso:country": "GB",
    "wof:name": "MK45 4GD",
    "wof:placetype": "postalcode"
  },
  "geometry": {"coordinates":[-0.431289,51.966093],"type":"Point"}
}
