{
  "type": "Feature",
  "properties": {
    "iso:country":"GB",
    "wof:name":"MK45 4GD",
    "wof:placetype":"postalcode"
},
  "geometry": {"coordinates":[-0.43128857639524,51.96609345184504],"type":"Point"}
}