{
  "type": "Feature",
  "properties": {
    "date:inception_lower":"1998-12-01",
    "date:inception_upper":"1998-12-31",
    "iso:country":"GB",
    "wof:name":"DA2 6JR",
    "wof:placetype":"postalcode"
},
  "geometry": {"coordinates":[0.252838,51.434201],"type":"Point"}
}