{
  "type": "Feature",
  "properties": {
    "iso:country": "GB",
    "wof:name": "DA2 6JR",
    "wof:placetype": "postalcode"
  },
  "geometry": {"coordinates":[0.252838,51.434201],"type":"Point"}
}
