{
  "type": "Feature",
  "properties": {
    "iso:country":"GB",
    "wof:name":"DA2 6JR",
    "wof:placetype":"postalcode"
},
  "geometry": {"coordinates":[0.25283823077508,51.43420074543065],"type":"Point"}
}