{
  "type": "Feature",
  "properties": {
    "iso:country":"GB",
    "wof:name":"SA38 9AT",
    "wof:placetype":"postalcode"
},
  "geometry": {"coordinates":[-4.46909224437198,52.03757345532367],"type":"Point"}
}