{
  "type": "Feature",
  "properties": {
    "iso:country":"GB",
    "wof:name":"DE11 7DA",
    "wof:placetype":"postalcode"
},
  "geometry": {"coordinates":[-1.51977720324181,52.76721141776049],"type":"Point"}
}