{
  "type": "Feature",
  "properties": {
    "iso:country":"GB",
    "wof:name":"S43 2HW",
    "wof:placetype":"postalcode"
},
  "geometry": {"coordinates":[-1.38683880118334,53.26438964055045],"type":"Point"}
}