{
  "type": "Feature",
  "properties": {
    "iso:country":"GB",
    "wof:name":"NR27 9AP",
    "wof:placetype":"postalcode"
},
  "geometry": {"coordinates":[1.29230345045214,52.93223765132844],"type":"Point"}
}