{
  "type": "Feature",
  "properties": {
    "iso:country": "GB",
    "wof:name": "NR27 9AP",
    "wof:placetype": "postalcode"
  },
  "geometry": {"coordinates":[1.292304,52.932247],"type":"Point"}
}
