{
  "type": "Feature",
  "properties": {
    "date:inception_lower": "1980-01-01",
    "date:inception_upper": "1980-01-01",
    "iso:country": "GB",
    "wof:name": "PH2 0RB",
    "wof:placetype": "postalcode"
  },
  "geometry": {"coordinates":[-3.566475,56.288202],"type":"Point"}
}
