{
  "type": "Feature",
  "properties": {
    "iso:country":"GB",
    "wof:name":"WA4 6HJ",
    "wof:placetype":"postalcode"
},
  "geometry": {"coordinates":[-2.58216067046592,53.3719497159282],"type":"Point"}
}