{
  "type": "Feature",
  "properties": {
    "iso:country":"GB",
    "wof:name":"PE34 3HZ",
    "wof:placetype":"postalcode"
},
  "geometry": {"coordinates":[0.39730445540903,52.62632831628979],"type":"Point"}
}