{
  "type": "Feature",
  "properties": {
    "iso:country": "GB",
    "wof:name": "PE34 3HZ",
    "wof:placetype": "postalcode"
  },
  "geometry": {"coordinates":[0.397305,52.626328],"type":"Point"}
}
