{
  "type": "Feature",
  "properties": {
    "date:inception_lower": "1992-01-01",
    "date:inception_upper": "1992-01-01",
    "iso:country": "GB",
    "wof:name": "CF3 0EG",
    "wof:placetype": "postalcode"
  },
  "geometry": {"coordinates":[-3.092322,51.53018],"type":"Point"}
}
