{
  "type": "Feature",
  "properties": {
    "iso:country":"GB",
    "wof:name":"BN25 2DY",
    "wof:placetype":"postalcode"
},
  "geometry": {"coordinates":[0.09620853364389,50.77482829046046],"type":"Point"}
}