{
  "type": "Feature",
  "properties": {
    "iso:country": "GB",
    "wof:name": "W10 5SJ",
    "wof:placetype": "postalcode"
  },
  "geometry": {"coordinates":[-0.214249,51.52604],"type":"Point"}
}
