{
  "type": "Feature",
  "properties": {
    "date:inception_lower":"2015-11-01",
    "date:inception_upper":"2015-11-30",
    "iso:country":"GB",
    "wof:name":"W10 5SJ",
    "wof:placetype":"postalcode"
},
  "geometry": {"coordinates":[-0.214249,51.52604],"type":"Point"}
}