{
  "type": "Feature",
  "properties": {
    "iso:country": "GB",
    "wof:name": "PL12 6RT",
    "wof:placetype": "postalcode"
  },
  "geometry": {"coordinates":[-4.274697,50.488371],"type":"Point"}
}
