{
  "type": "Feature",
  "properties": {
    "iso:country":"GB",
    "wof:name":"PL12 6RT",
    "wof:placetype":"postalcode"
},
  "geometry": {"coordinates":[-4.27469728679084,50.4883713949346],"type":"Point"}
}