{
  "type": "Feature",
  "properties": {
    "date:inception_lower":"1980-01-01",
    "date:inception_upper":"1980-01-31",
    "iso:country":"GB",
    "wof:name":"PL12 6RT",
    "wof:placetype":"postalcode"
},
  "geometry": {"coordinates":[-4.274697,50.488371],"type":"Point"}
}