{
  "type": "Feature",
  "properties": {
    "iso:country":"GB",
    "wof:name":"NP7 7HG",
    "wof:placetype":"postalcode"
},
  "geometry": {"coordinates":[-3.03501647361962,51.83614051531178],"type":"Point"}
}