{
  "type": "Feature",
  "properties": {
    "iso:country":"GB",
    "wof:name":"LA9 6AE",
    "wof:placetype":"postalcode"
},
  "geometry": {"coordinates":[-2.73294406718357,54.32963674456953],"type":"Point"}
}