{
  "type": "Feature",
  "properties": {
    "date:inception_lower": "2000-06-01",
    "date:inception_upper": "2000-06-01",
    "iso:country": "GB",
    "wof:name": "LA9 6AE",
    "wof:placetype": "postalcode"
  },
  "geometry": {"coordinates":[-2.732944,54.329637],"type":"Point"}
}
