{
  "type": "Feature",
  "properties": {
    "iso:country":"GB",
    "wof:name":"WN6 0JL",
    "wof:placetype":"postalcode"
},
  "geometry": {"coordinates":[-2.66531158050678,53.58788894740302],"type":"Point"}
}