{
  "type": "Feature",
  "properties": {
    "iso:country":"GB",
    "wof:name":"TS26 8QA",
    "wof:placetype":"postalcode"
},
  "geometry": {"coordinates":[-1.22848356895833,54.68955961563763],"type":"Point"}
}