{
  "type": "Feature",
  "properties": {
    "iso:country": "GB",
    "wof:name": "TS26 8QA",
    "wof:placetype": "postalcode"
  },
  "geometry": {"coordinates":[-1.228484,54.68956],"type":"Point"}
}
