{
  "type": "Feature",
  "properties": {
    "iso:country": "GB",
    "wof:name": "HP21 7PF",
    "wof:placetype": "postalcode"
  },
  "geometry": {"coordinates":[-0.79016,51.803547],"type":"Point"}
}
