{
  "type": "Feature",
  "properties": {
    "date:inception_lower": "1980-01-01",
    "date:inception_upper": "1980-01-01",
    "iso:country": "GB",
    "wof:name": "TS11 8HF",
    "wof:placetype": "postalcode"
  },
  "geometry": {"coordinates":[-1.074199,54.579952],"type":"Point"}
}
