{
  "type": "Feature",
  "properties": {
    "iso:country":"GB",
    "wof:name":"TS11 8HF",
    "wof:placetype":"postalcode"
},
  "geometry": {"coordinates":[-1.07419928035251,54.5799515094725],"type":"Point"}
}