{
  "type": "Feature",
  "properties": {
    "iso:country": "GB",
    "wof:name": "OX15 5NN",
    "wof:placetype": "postalcode"
  },
  "geometry": {"coordinates":[-1.48621,51.995821],"type":"Point"}
}
