{
  "type": "Feature",
  "properties": {
    "iso:country":"GB",
    "wof:name":"OX15 5NN",
    "wof:placetype":"postalcode"
},
  "geometry": {"coordinates":[-1.48622471414033,51.99581061612526],"type":"Point"}
}