{
  "type": "Feature",
  "properties": {
    "iso:country":"GB",
    "wof:name":"W9 3JW",
    "wof:placetype":"postalcode"
},
  "geometry": {"coordinates":[-0.19972542203698,51.52839851231026],"type":"Point"}
}