{
  "type": "Feature",
  "properties": {
    "iso:country":"GB",
    "wof:name":"SY1 2LA",
    "wof:placetype":"postalcode"
},
  "geometry": {"coordinates":[-2.74205267118957,52.71475315859225],"type":"Point"}
}