{
  "type": "Feature",
  "properties": {
    "iso:country":"GB",
    "wof:name":"RH15 8DJ",
    "wof:placetype":"postalcode"
},
  "geometry": {"coordinates":[-0.1275241377256,50.96647161964083],"type":"Point"}
}