{
  "type": "Feature",
  "properties": {
    "iso:country":"GB",
    "wof:name":"IG10 3ND",
    "wof:placetype":"postalcode"
},
  "geometry": {"coordinates":[0.07197288715276,51.64189763265031],"type":"Point"}
}