{
  "type": "Feature",
  "properties": {
    "iso:country":"GB",
    "wof:name":"LU7 9JB",
    "wof:placetype":"postalcode"
},
  "geometry": {"coordinates":[-0.59075340678038,51.90710284480934],"type":"Point"}
}