{
  "type": "Feature",
  "properties": {
    "iso:country": "GB",
    "wof:name": "LE10 3LP",
    "wof:placetype": "postalcode"
  },
  "geometry": {"coordinates":[-1.371161,52.48543],"type":"Point"}
}
