{
  "type": "Feature",
  "properties": {
    "iso:country":"GB",
    "wof:name":"OL9 0AQ",
    "wof:placetype":"postalcode"
},
  "geometry": {"coordinates":[-2.14404499308617,53.55193810120421],"type":"Point"}
}