{
  "type": "Feature",
  "properties": {
    "date:inception_lower": "1980-01-01",
    "date:inception_upper": "1980-01-01",
    "iso:country": "GB",
    "wof:name": "OL9 0AQ",
    "wof:placetype": "postalcode"
  },
  "geometry": {"coordinates":[-2.144045,53.551938],"type":"Point"}
}
