{
  "type": "Feature",
  "properties": {
    "date:inception_lower": "2021-01-01",
    "date:inception_upper": "2021-01-01",
    "iso:country": "GB",
    "wof:name": "WF3 2GH",
    "wof:placetype": "postalcode"
  },
  "geometry": {"coordinates":[-1.547842,53.725452],"type":"Point"}
}
