{
  "type": "Feature",
  "properties": {
    "iso:country":"GB",
    "wof:name":"S18 2EP",
    "wof:placetype":"postalcode"
},
  "geometry": {"coordinates":[-1.45733147060635,53.30476745857367],"type":"Point"}
}