{
  "type": "Feature",
  "properties": {
    "date:inception_lower": "1986-01-01",
    "date:inception_upper": "1986-01-01",
    "iso:country": "GB",
    "wof:name": "SO41 9JZ",
    "wof:placetype": "postalcode"
  },
  "geometry": {"coordinates":[-1.555262,50.758499],"type":"Point"}
}
