{
  "type": "Feature",
  "properties": {
    "iso:country":"GB",
    "wof:name":"TW1 3RR",
    "wof:placetype":"postalcode"
},
  "geometry": {"coordinates":[-0.32846239808193,51.44774486260082],"type":"Point"}
}