{
  "type": "Feature",
  "properties": {
    "iso:country": "GB",
    "wof:name": "TN1 2SH",
    "wof:placetype": "postalcode"
  },
  "geometry": {"coordinates":[0.269962,51.131506],"type":"Point"}
}
