{
  "type": "Feature",
  "properties": {
    "date:inception_lower": "1980-01-01",
    "date:inception_upper": "1980-01-01",
    "iso:country": "GB",
    "wof:name": "TN1 2SH",
    "wof:placetype": "postalcode"
  },
  "geometry": {"coordinates":[0.269962,51.131506],"type":"Point"}
}
