{
  "type": "Feature",
  "properties": {
    "iso:country":"GB",
    "wof:name":"BS41 9DA",
    "wof:placetype":"postalcode"
},
  "geometry": {"coordinates":[-2.67503554439101,51.42741046787887],"type":"Point"}
}