{
  "type": "Feature",
  "properties": {
    "iso:country":"GB",
    "wof:name":"DT4 7SW",
    "wof:placetype":"postalcode"
},
  "geometry": {"coordinates":[-2.4479945582598,50.62187519861436],"type":"Point"}
}