{
  "type": "Feature",
  "properties": {
    "date:inception_lower": "1980-01-01",
    "date:inception_upper": "1980-01-01",
    "iso:country": "GB",
    "wof:name": "DT4 7SW",
    "wof:placetype": "postalcode"
  },
  "geometry": {"coordinates":[-2.448005,50.621855],"type":"Point"}
}
