{
  "type": "Feature",
  "properties": {
    "iso:country":"GB",
    "wof:name":"S70 4LJ",
    "wof:placetype":"postalcode"
},
  "geometry": {"coordinates":[-1.48331781026483,53.54111290470937],"type":"Point"}
}