{
  "type": "Feature",
  "properties": {
    "date:inception_lower": "1980-01-01",
    "date:inception_upper": "1980-01-01",
    "iso:country": "GB",
    "wof:name": "BN22 8TH",
    "wof:placetype": "postalcode"
  },
  "geometry": {"coordinates":[0.293362,50.786839],"type":"Point"}
}
