{
  "type": "Feature",
  "properties": {
    "iso:country": "GB",
    "wof:name": "BN22 8TH",
    "wof:placetype": "postalcode"
  },
  "geometry": {"coordinates":[0.293362,50.786839],"type":"Point"}
}
