{
  "type": "Feature",
  "properties": {
    "iso:country":"GB",
    "wof:name":"N20 9PU",
    "wof:placetype":"postalcode"
},
  "geometry": {"coordinates":[-0.17731894412675,51.63884746130651],"type":"Point"}
}