{
  "type": "Feature",
  "properties": {
    "date:inception_lower":"1980-01-01",
    "date:inception_upper":"1980-01-31",
    "iso:country":"GB",
    "wof:name":"EH5 1DP",
    "wof:placetype":"postalcode"
},
  "geometry": {"coordinates":[-3.226169,55.977772],"type":"Point"}
}