{
  "type": "Feature",
  "properties": {
    "iso:country":"GB",
    "wof:name":"MK3 5FR",
    "wof:placetype":"postalcode"
},
  "geometry": {"coordinates":[-0.73654431339365,51.98168648440089],"type":"Point"}
}