{
  "type": "Feature",
  "properties": {
    "iso:country":"GB",
    "wof:name":"LE17 5DH",
    "wof:placetype":"postalcode"
},
  "geometry": {"coordinates":[-1.25442505600994,52.48438427784844],"type":"Point"}
}