{
  "type": "Feature",
  "properties": {
    "iso:country":"GB",
    "wof:name":"TN6 2LL",
    "wof:placetype":"postalcode"
},
  "geometry": {"coordinates":[0.16520432167426,51.04954776136498],"type":"Point"}
}