{
  "type": "Feature",
  "properties": {
    "date:inception_lower": "1980-01-01",
    "date:inception_upper": "1980-01-01",
    "iso:country": "GB",
    "wof:name": "NN13 6AG",
    "wof:placetype": "postalcode"
  },
  "geometry": {"coordinates":[-1.153399,52.030493],"type":"Point"}
}
