{
  "type": "Feature",
  "properties": {
    "iso:country": "GB",
    "wof:name": "NN13 6AG",
    "wof:placetype": "postalcode"
  },
  "geometry": {"coordinates":[-1.153399,52.030493],"type":"Point"}
}
