{
  "type": "Feature",
  "properties": {
    "iso:country":"GB",
    "wof:name":"BD3 7AX",
    "wof:placetype":"postalcode"
},
  "geometry": {"coordinates":[-1.70345339884342,53.80143955226713],"type":"Point"}
}