{
  "type": "Feature",
  "properties": {
    "iso:country":"GB",
    "wof:name":"RH3 7BJ",
    "wof:placetype":"postalcode"
},
  "geometry": {"coordinates":[-0.2502458173392,51.24531275505048],"type":"Point"}
}