{
  "type": "Feature",
  "properties": {
    "date:inception_lower": "1980-01-01",
    "date:inception_upper": "1980-01-01",
    "iso:country": "GB",
    "wof:name": "L6 7UA",
    "wof:placetype": "postalcode"
  },
  "geometry": {"coordinates":[-2.946997,53.420353],"type":"Point"}
}
