{
  "type": "Feature",
  "properties": {
    "iso:country": "GB",
    "wof:name": "NN17 2UH",
    "wof:placetype": "postalcode"
  },
  "geometry": {"coordinates":[-0.741435,52.487637],"type":"Point"}
}
