{
  "type": "Feature",
  "properties": {
    "iso:country":"GB",
    "wof:name":"NN17 2UH",
    "wof:placetype":"postalcode"
},
  "geometry": {"coordinates":[-0.7414349924536,52.48763730901985],"type":"Point"}
}