{
  "type": "Feature",
  "properties": {
    "iso:country":"GB",
    "wof:name":"FK6 5DU",
    "wof:placetype":"postalcode"
},
  "geometry": {"coordinates":[-3.90527472480288,56.01813829903523],"type":"Point"}
}