{
  "type": "Feature",
  "properties": {
    "iso:country":"GB",
    "wof:name":"AL3 5AP",
    "wof:placetype":"postalcode"
},
  "geometry": {"coordinates":[-0.32436605231525,51.7668995613395],"type":"Point"}
}