{
  "type": "Feature",
  "properties": {
    "date:inception_lower": "1980-01-01",
    "date:inception_upper": "1980-01-01",
    "iso:country": "GB",
    "wof:name": "DH2 2JS",
    "wof:placetype": "postalcode"
  },
  "geometry": {"coordinates":[-1.585665,54.861997],"type":"Point"}
}
