{
  "type": "Feature",
  "properties": {
    "iso:country":"GB",
    "wof:name":"DH2 2JS",
    "wof:placetype":"postalcode"
},
  "geometry": {"coordinates":[-1.58566516984836,54.86199707266783],"type":"Point"}
}