{
  "type": "Feature",
  "properties": {
    "iso:country":"GB",
    "wof:name":"LS15 0HX",
    "wof:placetype":"postalcode"
},
  "geometry": {"coordinates":[-1.46762269420263,53.79352453614533],"type":"Point"}
}