{
  "type": "Feature",
  "properties": {
    "iso:country":"GB",
    "wof:name":"M41 8SQ",
    "wof:placetype":"postalcode"
},
  "geometry": {"coordinates":[-2.39012047292862,53.45557108639313],"type":"Point"}
}