{
  "type": "Feature",
  "properties": {
    "date:inception_lower": "1994-05-01",
    "date:inception_upper": "1994-05-01",
    "iso:country": "GB",
    "wof:name": "M41 8SQ",
    "wof:placetype": "postalcode"
  },
  "geometry": {"coordinates":[-2.39012,53.455571],"type":"Point"}
}
