{
  "type": "Feature",
  "properties": {
    "iso:country":"GB",
    "wof:name":"MK19 7HR",
    "wof:placetype":"postalcode"
},
  "geometry": {"coordinates":[-0.84064138003254,52.08931041088091],"type":"Point"}
}