{
  "type": "Feature",
  "properties": {
    "iso:country": "GB",
    "wof:name": "MK19 7HR",
    "wof:placetype": "postalcode"
  },
  "geometry": {"coordinates":[-0.840641,52.08931],"type":"Point"}
}
