{
  "type": "Feature",
  "properties": {
    "date:inception_lower": "1980-01-01",
    "date:inception_upper": "1980-01-01",
    "iso:country": "GB",
    "wof:name": "EH26 0QP",
    "wof:placetype": "postalcode"
  },
  "geometry": {"coordinates":[-3.20893,55.846812],"type":"Point"}
}
