{
  "type": "Feature",
  "properties": {
    "iso:country": "GB",
    "wof:name": "EH26 0QP",
    "wof:placetype": "postalcode"
  },
  "geometry": {"coordinates":[-3.20893,55.846812],"type":"Point"}
}
