{
  "type": "Feature",
  "properties": {
    "iso:country":"GB",
    "wof:name":"S74 0BJ",
    "wof:placetype":"postalcode"
},
  "geometry": {"coordinates":[-1.45422992513587,53.49724574243304],"type":"Point"}
}