{
  "type": "Feature",
  "properties": {
    "iso:country": "GB",
    "wof:name": "LL24 0PG",
    "wof:placetype": "postalcode"
  },
  "geometry": {"coordinates":[-3.723349,53.045149],"type":"Point"}
}
