{
  "type": "Feature",
  "properties": {
    "date:inception_lower":"1980-01-01",
    "date:inception_upper":"1980-01-31",
    "iso:country":"GB",
    "wof:name":"LL24 0PG",
    "wof:placetype":"postalcode"
},
  "geometry": {"coordinates":[-3.730017,53.041807],"type":"Point"}
}