{
  "type": "Feature",
  "properties": {
    "iso:country":"GB",
    "wof:name":"LL24 0PG",
    "wof:placetype":"postalcode"
},
  "geometry": {"coordinates":[-3.73001328864859,53.04179107024623],"type":"Point"}
}