{
  "type": "Feature",
  "properties": {
    "iso:country":"GB",
    "wof:name":"SO53 2HG",
    "wof:placetype":"postalcode"
},
  "geometry": {"coordinates":[-1.3771435240865,50.98415231092223],"type":"Point"}
}