{
  "type": "Feature",
  "properties": {
    "iso:country": "GB",
    "wof:name": "PL31 2TY",
    "wof:placetype": "postalcode"
  },
  "geometry": {"coordinates":[-4.706511,50.463896],"type":"Point"}
}
