{
  "type": "Feature",
  "properties": {
    "iso:country":"GB",
    "wof:name":"NR31 7EH",
    "wof:placetype":"postalcode"
},
  "geometry": {"coordinates":[1.71389713849586,52.56732307686583],"type":"Point"}
}