{
  "type": "Feature",
  "properties": {
    "date:inception_lower": "2018-08-01",
    "date:inception_upper": "2018-08-01",
    "iso:country": "GB",
    "wof:name": "RG19 9LX",
    "wof:placetype": "postalcode"
  },
  "geometry": {"coordinates":[-0.971231,51.431562],"type":"Point"}
}
