{
  "type": "Feature",
  "properties": {
    "iso:country":"GB",
    "wof:name":"GL7 1PQ",
    "wof:placetype":"postalcode"
},
  "geometry": {"coordinates":[-1.95400746763867,51.70399671892572],"type":"Point"}
}