{
  "type": "Feature",
  "properties": {
    "iso:country":"GB",
    "wof:name":"AB53 6YT",
    "wof:placetype":"postalcode"
},
  "geometry": {"coordinates":[-2.25236597463106,57.53338446119329],"type":"Point"}
}