{
  "type": "Feature",
  "properties": {
    "iso:country":"GB",
    "wof:name":"CH64 9SQ",
    "wof:placetype":"postalcode"
},
  "geometry": {"coordinates":[-3.0628030900697,53.28508311256008],"type":"Point"}
}