{
  "type": "Feature",
  "properties": {
    "iso:country":"GB",
    "wof:name":"DE24 3HH",
    "wof:placetype":"postalcode"
},
  "geometry": {"coordinates":[-1.48678613174666,52.87178348380457],"type":"Point"}
}