{
  "type": "Feature",
  "properties": {
    "iso:country":"GB",
    "wof:name":"L12 4ZF",
    "wof:placetype":"postalcode"
},
  "geometry": {"coordinates":[-2.88588793556823,53.43402817711893],"type":"Point"}
}