{
  "type": "Feature",
  "properties": {
    "iso:country": "GB",
    "wof:name": "L12 4ZF",
    "wof:placetype": "postalcode"
  },
  "geometry": {"coordinates":[-2.885888,53.434028],"type":"Point"}
}
