{
  "type": "Feature",
  "properties": {
    "date:inception_lower": "1980-01-01",
    "date:inception_upper": "1980-01-01",
    "iso:country": "GB",
    "wof:name": "PO21 4SU",
    "wof:placetype": "postalcode"
  },
  "geometry": {"coordinates":[-0.736075,50.768597],"type":"Point"}
}
