{
  "type": "Feature",
  "properties": {
    "iso:country":"GB",
    "wof:name":"PO21 4SU",
    "wof:placetype":"postalcode"
},
  "geometry": {"coordinates":[-0.73607550117794,50.768597112196],"type":"Point"}
}