{
  "type": "Feature",
  "properties": {
    "date:inception_lower":"1980-01-01",
    "date:inception_upper":"1980-01-31",
    "iso:country":"GB",
    "wof:name":"AL1 2JT",
    "wof:placetype":"postalcode"
},
  "geometry": {"coordinates":[-0.340915,51.739646],"type":"Point"}
}