{
  "type": "Feature",
  "properties": {
    "iso:country":"GB",
    "wof:name":"MK4 2NP",
    "wof:placetype":"postalcode"
},
  "geometry": {"coordinates":[-0.78417462412486,52.00368570344276],"type":"Point"}
}