{
  "type": "Feature",
  "properties": {
    "date:inception_lower": "1993-08-01",
    "date:inception_upper": "1993-08-01",
    "iso:country": "GB",
    "wof:name": "MK4 2NP",
    "wof:placetype": "postalcode"
  },
  "geometry": {"coordinates":[-0.784175,52.003686],"type":"Point"}
}
