{
  "type": "Feature",
  "properties": {
    "iso:country": "GB",
    "wof:name": "RH1 4DY",
    "wof:placetype": "postalcode"
  },
  "geometry": {"coordinates":[-0.152684,51.23],"type":"Point"}
}
