{
  "type": "Feature",
  "properties": {
    "iso:country":"GB",
    "wof:name":"RH1 4DY",
    "wof:placetype":"postalcode"
},
  "geometry": {"coordinates":[-0.15268404665687,51.23000047349679],"type":"Point"}
}