{
  "type": "Feature",
  "properties": {
    "iso:country":"GB",
    "wof:name":"AL2 3XG",
    "wof:placetype":"postalcode"
},
  "geometry": {"coordinates":[-0.37200191913878,51.70726900107607],"type":"Point"}
}