{
  "type": "Feature",
  "properties": {
    "iso:country": "GB",
    "wof:name": "CA13 9YW",
    "wof:placetype": "postalcode"
  },
  "geometry": {"coordinates":[-3.264056,54.660118],"type":"Point"}
}
