{
  "type": "Feature",
  "properties": {
    "iso:country":"GB",
    "wof:name":"CA13 9YW",
    "wof:placetype":"postalcode"
},
  "geometry": {"coordinates":[-3.26449726633767,54.66044704690376],"type":"Point"}
}