{
  "type": "Feature",
  "properties": {
    "date:inception_lower": "1986-07-01",
    "date:inception_upper": "1986-07-01",
    "iso:country": "GB",
    "wof:name": "PO14 4SD",
    "wof:placetype": "postalcode"
  },
  "geometry": {"coordinates":[-1.257379,50.865992],"type":"Point"}
}
