{
  "type": "Feature",
  "properties": {
    "iso:country":"GB",
    "wof:name":"PO14 4SD",
    "wof:placetype":"postalcode"
},
  "geometry": {"coordinates":[-1.25737880265824,50.86599250382774],"type":"Point"}
}