{
  "type": "Feature",
  "properties": {
    "date:inception_lower":"1980-01-01",
    "date:inception_upper":"1980-01-31",
    "iso:country":"GB",
    "wof:name":"TS17 0JH",
    "wof:placetype":"postalcode"
},
  "geometry": {"coordinates":[-1.308353,54.506357],"type":"Point"}
}