{
  "type": "Feature",
  "properties": {
    "iso:country": "GB",
    "wof:name": "TS17 0JH",
    "wof:placetype": "postalcode"
  },
  "geometry": {"coordinates":[-1.308353,54.506357],"type":"Point"}
}
