{
  "type": "Feature",
  "properties": {
    "iso:country": "GB",
    "wof:name": "BB10 4AP",
    "wof:placetype": "postalcode"
  },
  "geometry": {"coordinates":[-2.232811,53.787935],"type":"Point"}
}
