{
  "type": "Feature",
  "properties": {
    "iso:country":"GB",
    "wof:name":"BB10 4AP",
    "wof:placetype":"postalcode"
},
  "geometry": {"coordinates":[-2.23281113321754,53.78793528631336],"type":"Point"}
}