{
  "type": "Feature",
  "properties": {
    "iso:country":"GB",
    "wof:name":"PR25 4UB",
    "wof:placetype":"postalcode"
},
  "geometry": {"coordinates":[-2.68162717716629,53.71074896895858],"type":"Point"}
}