{
  "type": "Feature",
  "properties": {
    "iso:country":"GB",
    "wof:name":"PO13 0PQ",
    "wof:placetype":"postalcode"
},
  "geometry": {"coordinates":[-1.18200570201014,50.82469805677322],"type":"Point"}
}