{
  "type": "Feature",
  "properties": {
    "date:inception_lower":"1980-01-01",
    "date:inception_upper":"1980-01-31",
    "iso:country":"GB",
    "wof:name":"PO13 0PQ",
    "wof:placetype":"postalcode"
},
  "geometry": {"coordinates":[-1.182006,50.824698],"type":"Point"}
}