{
  "type": "Feature",
  "properties": {
    "iso:country":"GB",
    "wof:name":"OL9 0ES",
    "wof:placetype":"postalcode"
},
  "geometry": {"coordinates":[-2.13569755253878,53.55172317265981],"type":"Point"}
}