{
  "type": "Feature",
  "properties": {
    "iso:country": "GB",
    "wof:name": "L34 0ES",
    "wof:placetype": "postalcode"
  },
  "geometry": {"coordinates":[-2.847536,53.449983],"type":"Point"}
}
