{
  "type": "Feature",
  "properties": {
    "date:inception_lower": "1980-01-01",
    "date:inception_upper": "1980-01-01",
    "iso:country": "GB",
    "wof:name": "L34 0ES",
    "wof:placetype": "postalcode"
  },
  "geometry": {"coordinates":[-2.847536,53.449983],"type":"Point"}
}
