{
  "type": "Feature",
  "properties": {
    "iso:country":"GB",
    "wof:name":"L34 0ES",
    "wof:placetype":"postalcode"
},
  "geometry": {"coordinates":[-2.84753625219153,53.44998296653976],"type":"Point"}
}