{
  "type": "Feature",
  "properties": {
    "iso:country":"GB",
    "wof:name":"NR3 2QP",
    "wof:placetype":"postalcode"
},
  "geometry": {"coordinates":[1.27385177910597,52.64898739985538],"type":"Point"}
}