{
  "type": "Feature",
  "properties": {
    "iso:country":"GB",
    "wof:name":"PL6 6AY",
    "wof:placetype":"postalcode"
},
  "geometry": {"coordinates":[-4.11519482922123,50.42628939015609],"type":"Point"}
}