{
  "type": "Feature",
  "properties": {
    "iso:country":"GB",
    "wof:name":"S41 9DU",
    "wof:placetype":"postalcode"
},
  "geometry": {"coordinates":[-1.43652870322983,53.26969543544931],"type":"Point"}
}