{
  "type": "Feature",
  "properties": {
    "date:inception_lower":"1980-01-01",
    "date:inception_upper":"1980-01-31",
    "iso:country":"GB",
    "wof:name":"S41 9DU",
    "wof:placetype":"postalcode"
},
  "geometry": {"coordinates":[-1.436452,53.269696],"type":"Point"}
}