{
  "type": "Feature",
  "properties": {
    "date:inception_lower":"1980-01-01",
    "date:inception_upper":"1980-01-31",
    "iso:country":"GB",
    "wof:name":"S61 3BQ",
    "wof:placetype":"postalcode"
},
  "geometry": {"coordinates":[-1.405528,53.447406],"type":"Point"}
}