{
  "type": "Feature",
  "properties": {
    "iso:country":"GB",
    "wof:name":"S61 3BQ",
    "wof:placetype":"postalcode"
},
  "geometry": {"coordinates":[-1.40552785013996,53.44740554939339],"type":"Point"}
}