{
  "type": "Feature",
  "properties": {
    "iso:country": "GB",
    "wof:name": "EX32 8JU",
    "wof:placetype": "postalcode"
  },
  "geometry": {"coordinates":[-4.054003,51.078014],"type":"Point"}
}
