{
  "type": "Feature",
  "properties": {
    "date:inception_lower": "1981-06-01",
    "date:inception_upper": "1981-06-01",
    "iso:country": "GB",
    "wof:name": "EX32 8JU",
    "wof:placetype": "postalcode"
  },
  "geometry": {"coordinates":[-4.054003,51.078014],"type":"Point"}
}
