{
  "type": "Feature",
  "properties": {
    "iso:country":"GB",
    "wof:name":"CV31 1SR",
    "wof:placetype":"postalcode"
},
  "geometry": {"coordinates":[-1.51128474015403,52.28089102601555],"type":"Point"}
}