{
  "type": "Feature",
  "properties": {
    "iso:country":"GB",
    "wof:name":"SK8 6BH",
    "wof:placetype":"postalcode"
},
  "geometry": {"coordinates":[-2.2080821766473,53.37249655801786],"type":"Point"}
}