{
  "type": "Feature",
  "properties": {
    "iso:country":"GB",
    "wof:name":"OL13 8AS",
    "wof:placetype":"postalcode"
},
  "geometry": {"coordinates":[-2.20354193592644,53.70216169304066],"type":"Point"}
}