{
  "type": "Feature",
  "properties": {
    "iso:country": "GB",
    "wof:name": "OL13 8AS",
    "wof:placetype": "postalcode"
  },
  "geometry": {"coordinates":[-2.203542,53.702162],"type":"Point"}
}
