{
  "type": "Feature",
  "properties": {
    "iso:country":"GB",
    "wof:name":"CF62 7JJ",
    "wof:placetype":"postalcode"
},
  "geometry": {"coordinates":[-3.28588438846506,51.40632065572477],"type":"Point"}
}