{
  "type": "Feature",
  "properties": {
    "iso:country":"GB",
    "wof:name":"KY4 0AT",
    "wof:placetype":"postalcode"
},
  "geometry": {"coordinates":[-3.38482006256942,56.1393594619692],"type":"Point"}
}