{
  "type": "Feature",
  "properties": {
    "iso:country": "GB",
    "wof:name": "KY4 0AT",
    "wof:placetype": "postalcode"
  },
  "geometry": {"coordinates":[-3.38482,56.139359],"type":"Point"}
}
