{
  "type": "Feature",
  "properties": {
    "date:inception_lower": "1980-01-01",
    "date:inception_upper": "1980-01-01",
    "iso:country": "GB",
    "wof:name": "KY4 0AT",
    "wof:placetype": "postalcode"
  },
  "geometry": {"coordinates":[-3.38482,56.139359],"type":"Point"}
}
