{
  "type": "Feature",
  "properties": {
    "iso:country":"GB",
    "wof:name":"SY2 6RE",
    "wof:placetype":"postalcode"
},
  "geometry": {"coordinates":[-2.73387792088995,52.69339032310474],"type":"Point"}
}