{
  "type": "Feature",
  "properties": {
    "iso:country":"GB",
    "wof:name":"TS20 1AL",
    "wof:placetype":"postalcode"
},
  "geometry": {"coordinates":[-1.30967489291102,54.58642106424875],"type":"Point"}
}