{
  "type": "Feature",
  "properties": {
    "date:inception_lower": "1980-01-01",
    "date:inception_upper": "1980-01-01",
    "iso:country": "GB",
    "wof:name": "TS20 1AL",
    "wof:placetype": "postalcode"
  },
  "geometry": {"coordinates":[-1.309675,54.586421],"type":"Point"}
}
