{
  "type": "Feature",
  "properties": {
    "iso:country":"GB",
    "wof:name":"NE9 5AL",
    "wof:placetype":"postalcode"
},
  "geometry": {"coordinates":[-1.59924875389805,54.93911877096289],"type":"Point"}
}