{
  "type": "Feature",
  "properties": {
    "iso:country": "GB",
    "wof:name": "NG5 5WH",
    "wof:placetype": "postalcode"
  },
  "geometry": {"coordinates":[-1.158157,53.002686],"type":"Point"}
}
