{
  "type": "Feature",
  "properties": {
    "date:inception_lower": "2017-12-01",
    "date:inception_upper": "2017-12-01",
    "iso:country": "GB",
    "wof:name": "NG5 5WH",
    "wof:placetype": "postalcode"
  },
  "geometry": {"coordinates":[-1.158157,53.002686],"type":"Point"}
}
