{
  "type": "Feature",
  "properties": {
    "date:inception_lower":"1997-12-01",
    "date:inception_upper":"1997-12-31",
    "iso:country":"GB",
    "wof:name":"CO1 2WG",
    "wof:placetype":"postalcode"
},
  "geometry": {"coordinates":[0.927114,51.887549],"type":"Point"}
}