{
  "type": "Feature",
  "properties": {
    "iso:country":"GB",
    "wof:name":"NG7 7HF",
    "wof:placetype":"postalcode"
},
  "geometry": {"coordinates":[-1.16867644307493,52.97344408271996],"type":"Point"}
}