{
  "type": "Feature",
  "properties": {
    "iso:country":"GB",
    "wof:name":"HU17 0JU",
    "wof:placetype":"postalcode"
},
  "geometry": {"coordinates":[-0.40882945158216,53.84467391289493],"type":"Point"}
}