{
  "type": "Feature",
  "properties": {
    "date:inception_lower":"1980-01-01",
    "date:inception_upper":"1980-01-31",
    "iso:country":"GB",
    "wof:name":"G33 6JH",
    "wof:placetype":"postalcode"
},
  "geometry": {"coordinates":[-4.165381,55.885715],"type":"Point"}
}