{
  "type": "Feature",
  "properties": {
    "iso:country":"GB",
    "wof:name":"G33 6JH",
    "wof:placetype":"postalcode"
},
  "geometry": {"coordinates":[-4.16538124477321,55.88571467977187],"type":"Point"}
}