{
  "type": "Feature",
  "properties": {
    "iso:country": "GB",
    "wof:name": "B37 6AT",
    "wof:placetype": "postalcode"
  },
  "geometry": {"coordinates":[-1.753098,52.494745],"type":"Point"}
}
