{
  "type": "Feature",
  "properties": {
    "iso:country":"GB",
    "wof:name":"B37 6AT",
    "wof:placetype":"postalcode"
},
  "geometry": {"coordinates":[-1.75309766263201,52.49474540003384],"type":"Point"}
}