{
  "type": "Feature",
  "properties": {
    "date:inception_lower": "1991-01-01",
    "date:inception_upper": "1991-01-01",
    "iso:country": "GB",
    "wof:name": "KT15 1UU",
    "wof:placetype": "postalcode"
  },
  "geometry": {"coordinates":[-0.498051,51.365935],"type":"Point"}
}
