{
  "type": "Feature",
  "properties": {
    "date:inception_lower":"1996-12-01",
    "date:inception_upper":"1996-12-31",
    "iso:country":"GB",
    "wof:name":"EC2Y 8HQ",
    "wof:placetype":"postalcode"
},
  "geometry": {"coordinates":[-0.092381,51.52038],"type":"Point"}
}