{
  "type": "Feature",
  "properties": {
    "iso:country": "GB",
    "wof:name": "EC2Y 8HQ",
    "wof:placetype": "postalcode"
  },
  "geometry": {"coordinates":[-0.092381,51.52038],"type":"Point"}
}
