{
  "type": "Feature",
  "properties": {
    "iso:country":"GB",
    "wof:name":"EC2Y 8HQ",
    "wof:placetype":"postalcode"
},
  "geometry": {"coordinates":[-0.09238138117341,51.52038019579161],"type":"Point"}
}