{
  "type": "Feature",
  "properties": {
    "date:inception_lower":"2014-10-01",
    "date:inception_upper":"2014-10-31",
    "iso:country":"GB",
    "wof:name":"WD25 7NL",
    "wof:placetype":"postalcode"
},
  "geometry": {"coordinates":[-0.412898,51.695192],"type":"Point"}
}