{
  "type": "Feature",
  "properties": {
    "iso:country": "GB",
    "wof:name": "EH54 6QU",
    "wof:placetype": "postalcode"
  },
  "geometry": {"coordinates":[-3.511263,55.886732],"type":"Point"}
}
