{
  "type": "Feature",
  "properties": {
    "date:inception_lower": "2013-11-01",
    "date:inception_upper": "2013-11-01",
    "iso:country": "GB",
    "wof:name": "NR12 8JU",
    "wof:placetype": "postalcode"
  },
  "geometry": {"coordinates":[1.457577,52.710005],"type":"Point"}
}
