{
  "type": "Feature",
  "properties": {
    "iso:country":"GB",
    "wof:name":"NR12 8JU",
    "wof:placetype":"postalcode"
},
  "geometry": {"coordinates":[1.45756837563082,52.70996873115126],"type":"Point"}
}