{
  "type": "Feature",
  "properties": {
    "date:inception_lower":"1994-05-01",
    "date:inception_upper":"1994-05-31",
    "iso:country":"GB",
    "wof:name":"M11 3UQ",
    "wof:placetype":"postalcode"
},
  "geometry": {"coordinates":[-2.199618,53.481137],"type":"Point"}
}