{
  "type": "Feature",
  "properties": {
    "iso:country":"GB",
    "wof:name":"M11 3UQ",
    "wof:placetype":"postalcode"
},
  "geometry": {"coordinates":[-2.19961817279767,53.48113743946325],"type":"Point"}
}