{
  "type": "Feature",
  "properties": {
    "iso:country":"GB",
    "wof:name":"DL8 4JP",
    "wof:placetype":"postalcode"
},
  "geometry": {"coordinates":[-1.97348986786048,54.27662610633032],"type":"Point"}
}