{
  "type": "Feature",
  "properties": {
    "iso:country":"GB",
    "wof:name":"TA20 3JW",
    "wof:placetype":"postalcode"
},
  "geometry": {"coordinates":[-3.00457845321111,50.92855025641359],"type":"Point"}
}