{
  "type": "Feature",
  "properties": {
    "iso:country": "GB",
    "wof:name": "TA20 3JW",
    "wof:placetype": "postalcode"
  },
  "geometry": {"coordinates":[-3.004578,50.92855],"type":"Point"}
}
