{
  "type": "Feature",
  "properties": {
    "iso:country":"GB",
    "wof:name":"CW8 1DN",
    "wof:placetype":"postalcode"
},
  "geometry": {"coordinates":[-2.52038817037945,53.25238750278346],"type":"Point"}
}