{
  "type": "Feature",
  "properties": {
    "date:inception_lower":"1980-01-01",
    "date:inception_upper":"1980-01-31",
    "iso:country":"GB",
    "wof:name":"CT4 5DB",
    "wof:placetype":"postalcode"
},
  "geometry": {"coordinates":[1.136632,51.257085],"type":"Point"}
}