{
  "type": "Feature",
  "properties": {
    "iso:country": "GB",
    "wof:name": "CT4 5DB",
    "wof:placetype": "postalcode"
  },
  "geometry": {"coordinates":[1.136632,51.257085],"type":"Point"}
}
