{
  "type": "Feature",
  "properties": {
    "iso:country":"GB",
    "wof:name":"CT4 5DB",
    "wof:placetype":"postalcode"
},
  "geometry": {"coordinates":[1.13663185332416,51.25708533836496],"type":"Point"}
}