{
  "type": "Feature",
  "properties": {
    "iso:country": "GB",
    "wof:name": "GL6 8EJ",
    "wof:placetype": "postalcode"
  },
  "geometry": {"coordinates":[-2.150101,51.725632],"type":"Point"}
}
