{
  "type": "Feature",
  "properties": {
    "iso:country":"GB",
    "wof:name":"GL6 8EJ",
    "wof:placetype":"postalcode"
},
  "geometry": {"coordinates":[-2.15010137187322,51.72563199690523],"type":"Point"}
}