{
  "type": "Feature",
  "properties": {
    "date:inception_lower": "2018-04-01",
    "date:inception_upper": "2018-04-01",
    "iso:country": "GB",
    "wof:name": "GU7 3FJ",
    "wof:placetype": "postalcode"
  },
  "geometry": {"coordinates":[-0.598392,51.194665],"type":"Point"}
}
