{
  "type": "Feature",
  "properties": {
    "date:inception_lower": "1992-01-01",
    "date:inception_upper": "1992-01-01",
    "iso:country": "GB",
    "wof:name": "EX34 8PR",
    "wof:placetype": "postalcode"
  },
  "geometry": {"coordinates":[-4.126871,51.204568],"type":"Point"}
}
