{
  "type": "Feature",
  "properties": {
    "iso:country": "GB",
    "wof:name": "EX34 8PR",
    "wof:placetype": "postalcode"
  },
  "geometry": {"coordinates":[-4.126871,51.204568],"type":"Point"}
}
