{
  "type": "Feature",
  "properties": {
    "iso:country":"GB",
    "wof:name":"EX34 8PR",
    "wof:placetype":"postalcode"
},
  "geometry": {"coordinates":[-4.12687104669371,51.204568040544],"type":"Point"}
}