{
  "type": "Feature",
  "properties": {
    "iso:country":"GB",
    "wof:name":"G42 8DW",
    "wof:placetype":"postalcode"
},
  "geometry": {"coordinates":[-4.26254686764651,55.83387930090696],"type":"Point"}
}