{
  "type": "Feature",
  "properties": {
    "iso:country":"GB",
    "wof:name":"TN2 5PR",
    "wof:placetype":"postalcode"
},
  "geometry": {"coordinates":[0.24894367892618,51.12106561207207],"type":"Point"}
}