{
  "type": "Feature",
  "properties": {
    "iso:country": "GB",
    "wof:name": "TN2 5PR",
    "wof:placetype": "postalcode"
  },
  "geometry": {"coordinates":[0.248944,51.121066],"type":"Point"}
}
