{
  "type": "Feature",
  "properties": {
    "iso:country": "GB",
    "wof:name": "BL4 8RP",
    "wof:placetype": "postalcode"
  },
  "geometry": {"coordinates":[-2.354192,53.531923],"type":"Point"}
}
