{
  "type": "Feature",
  "properties": {
    "iso:country":"GB",
    "wof:name":"BL4 8RP",
    "wof:placetype":"postalcode"
},
  "geometry": {"coordinates":[-2.35419218660412,53.53192323036385],"type":"Point"}
}