{
  "type": "Feature",
  "properties": {
    "iso:country":"GB",
    "wof:name":"TA10 9EY",
    "wof:placetype":"postalcode"
},
  "geometry": {"coordinates":[-2.80978826890455,51.04120165778171],"type":"Point"}
}