{
  "type": "Feature",
  "properties": {
    "iso:country":"GB",
    "wof:name":"SS9 3QQ",
    "wof:placetype":"postalcode"
},
  "geometry": {"coordinates":[0.6325552337303,51.5498391339038],"type":"Point"}
}