{
  "type": "Feature",
  "properties": {
    "iso:country":"GB",
    "wof:name":"PE6 0EJ",
    "wof:placetype":"postalcode"
},
  "geometry": {"coordinates":[-0.16835481906666,52.67663352062266],"type":"Point"}
}