{
  "type": "Feature",
  "properties": {
    "iso:country": "GB",
    "wof:name": "PE6 0EJ",
    "wof:placetype": "postalcode"
  },
  "geometry": {"coordinates":[-0.168355,52.676634],"type":"Point"}
}
