{
  "type": "Feature",
  "properties": {
    "iso:country": "GB",
    "wof:name": "SW15 3AF",
    "wof:placetype": "postalcode"
  },
  "geometry": {"coordinates":[-0.233165,51.453676],"type":"Point"}
}
