{
  "type": "Feature",
  "properties": {
    "iso:country":"GB",
    "wof:name":"SW15 3AF",
    "wof:placetype":"postalcode"
},
  "geometry": {"coordinates":[-0.23316553567504,51.45367623880294],"type":"Point"}
}