{
  "type": "Feature",
  "properties": {
    "iso:country":"GB",
    "wof:name":"WD25 0AG",
    "wof:placetype":"postalcode"
},
  "geometry": {"coordinates":[-0.39737436189712,51.68184683293612],"type":"Point"}
}