{
  "type": "Feature",
  "properties": {
    "date:inception_lower": "2000-10-01",
    "date:inception_upper": "2000-10-01",
    "iso:country": "GB",
    "wof:name": "WD25 0AG",
    "wof:placetype": "postalcode"
  },
  "geometry": {"coordinates":[-0.397374,51.681847],"type":"Point"}
}
