{
  "type": "Feature",
  "properties": {
    "iso:country":"GB",
    "wof:name":"LA4 4RG",
    "wof:placetype":"postalcode"
},
  "geometry": {"coordinates":[-2.84757964398758,54.06365971591801],"type":"Point"}
}