{
  "type": "Feature",
  "properties": {
    "date:inception_lower": "1980-01-01",
    "date:inception_upper": "1980-01-01",
    "iso:country": "GB",
    "wof:name": "LA4 4RG",
    "wof:placetype": "postalcode"
  },
  "geometry": {"coordinates":[-2.84758,54.06366],"type":"Point"}
}
