{
  "type": "Feature",
  "properties": {
    "iso:country":"GB",
    "wof:name":"PA2 8RE",
    "wof:placetype":"postalcode"
},
  "geometry": {"coordinates":[-4.44162889250983,55.8208005198955],"type":"Point"}
}