{
  "type": "Feature",
  "properties": {
    "iso:country":"GB",
    "wof:name":"SE5 9HB",
    "wof:placetype":"postalcode"
},
  "geometry": {"coordinates":[-0.09624655300649,51.47088487456033],"type":"Point"}
}