{
  "type": "Feature",
  "properties": {
    "iso:country":"GB",
    "wof:name":"M25 0JG",
    "wof:placetype":"postalcode"
},
  "geometry": {"coordinates":[-2.26850231468156,53.52263680185112],"type":"Point"}
}