{
  "type": "Feature",
  "properties": {
    "date:inception_lower":"1990-08-01",
    "date:inception_upper":"1990-08-31",
    "iso:country":"GB",
    "wof:name":"AB53 6XR",
    "wof:placetype":"postalcode"
},
  "geometry": {"coordinates":[-2.269718,57.481438],"type":"Point"}
}