{
  "type": "Feature",
  "properties": {
    "date:inception_lower": "1980-01-01",
    "date:inception_upper": "1980-01-01",
    "iso:country": "GB",
    "wof:name": "CT1 3JS",
    "wof:placetype": "postalcode"
  },
  "geometry": {"coordinates":[1.082294,51.272989],"type":"Point"}
}
