{
  "type": "Feature",
  "properties": {
    "date:inception_lower": "2020-09-01",
    "date:inception_upper": "2020-09-01",
    "iso:country": "GB",
    "wof:name": "CT9 4FX",
    "wof:placetype": "postalcode"
  },
  "geometry": {"coordinates":[1.388333,51.360947],"type":"Point"}
}
