{
  "type": "Feature",
  "properties": {
    "iso:country":"GB",
    "wof:name":"PA2 6JN",
    "wof:placetype":"postalcode"
},
  "geometry": {"coordinates":[-4.4296409218179,55.83106854488668],"type":"Point"}
}