{
  "type": "Feature",
  "properties": {
    "date:inception_lower":"1994-02-01",
    "date:inception_upper":"1994-02-28",
    "iso:country":"GB",
    "wof:name":"DD1 5DF",
    "wof:placetype":"postalcode"
},
  "geometry": {"coordinates":[-2.98224,56.462193],"type":"Point"}
}