{
  "type": "Feature",
  "properties": {
    "iso:country":"GB",
    "wof:name":"SG5 2UG",
    "wof:placetype":"postalcode"
},
  "geometry": {"coordinates":[-0.28612975080678,51.96001485075387],"type":"Point"}
}