{
  "type": "Feature",
  "properties": {
    "iso:country": "GB",
    "wof:name": "SG5 2UG",
    "wof:placetype": "postalcode"
  },
  "geometry": {"coordinates":[-0.28613,51.960015],"type":"Point"}
}
