{
  "type": "Feature",
  "properties": {
    "iso:country": "GB",
    "wof:name": "TF11 9LY",
    "wof:placetype": "postalcode"
  },
  "geometry": {"coordinates":[-2.401743,52.635955],"type":"Point"}
}
