{
  "type": "Feature",
  "properties": {
    "iso:country":"GB",
    "wof:name":"HU5 4DS",
    "wof:placetype":"postalcode"
},
  "geometry": {"coordinates":[-0.37514052793311,53.76035468846543],"type":"Point"}
}