{
  "type": "Feature",
  "properties": {
    "iso:country":"GB",
    "wof:name":"DT3 6JN",
    "wof:placetype":"postalcode"
},
  "geometry": {"coordinates":[-2.43461380369327,50.63635046024992],"type":"Point"}
}