{
  "type": "Feature",
  "properties": {
    "iso:country": "GB",
    "wof:name": "YO60 7NX",
    "wof:placetype": "postalcode"
  },
  "geometry": {"coordinates":[-0.91158,54.032074],"type":"Point"}
}
