{
  "type": "Feature",
  "properties": {
    "iso:country":"GB",
    "wof:name":"YO60 7NX",
    "wof:placetype":"postalcode"
},
  "geometry": {"coordinates":[-0.91158046785373,54.03207407251828],"type":"Point"}
}