{
  "type": "Feature",
  "properties": {
    "iso:country":"GB",
    "wof:name":"NE66 2PL",
    "wof:placetype":"postalcode"
},
  "geometry": {"coordinates":[-1.69320218515892,55.40501657520857],"type":"Point"}
}