{
  "type": "Feature",
  "properties": {
    "date:inception_lower": "1980-01-01",
    "date:inception_upper": "1980-01-01",
    "iso:country": "GB",
    "wof:name": "CV6 3BN",
    "wof:placetype": "postalcode"
  },
  "geometry": {"coordinates":[-1.517366,52.418664],"type":"Point"}
}
