{
  "type": "Feature",
  "properties": {
    "iso:country":"GB",
    "wof:name":"DY4 8XF",
    "wof:placetype":"postalcode"
},
  "geometry": {"coordinates":[-2.05956707551287,52.51823523404087],"type":"Point"}
}