{
  "type": "Feature",
  "properties": {
    "date:inception_lower": "1980-01-01",
    "date:inception_upper": "1980-01-01",
    "iso:country": "GB",
    "wof:name": "WA13 0NX",
    "wof:placetype": "postalcode"
  },
  "geometry": {"coordinates":[-2.490853,53.377142],"type":"Point"}
}
