{
  "type": "Feature",
  "properties": {
    "date:inception_lower":"1980-01-01",
    "date:inception_upper":"1980-01-31",
    "iso:country":"GB",
    "wof:name":"S6 5PE",
    "wof:placetype":"postalcode"
},
  "geometry": {"coordinates":[-1.528287,53.392826],"type":"Point"}
}