{
  "type": "Feature",
  "properties": {
    "iso:country":"GB",
    "wof:name":"BD20 6PH",
    "wof:placetype":"postalcode"
},
  "geometry": {"coordinates":[-1.95668617650079,53.89546047036599],"type":"Point"}
}