{
  "type": "Feature",
  "properties": {
    "iso:country": "GB",
    "wof:name": "BD20 6PH",
    "wof:placetype": "postalcode"
  },
  "geometry": {"coordinates":[-1.956686,53.89546],"type":"Point"}
}
