{
  "type": "Feature",
  "properties": {
    "iso:country":"GB",
    "wof:name":"CF15 8DH",
    "wof:placetype":"postalcode"
},
  "geometry": {"coordinates":[-3.25453218723002,51.5167226629392],"type":"Point"}
}