{
  "type": "Feature",
  "properties": {
    "date:inception_lower":"1980-01-01",
    "date:inception_upper":"1980-01-31",
    "iso:country":"GB",
    "wof:name":"SP1 3TH",
    "wof:placetype":"postalcode"
},
  "geometry": {"coordinates":[-1.793989,51.075822],"type":"Point"}
}