{
  "type": "Feature",
  "properties": {
    "iso:country":"GB",
    "wof:name":"SP1 3TH",
    "wof:placetype":"postalcode"
},
  "geometry": {"coordinates":[-1.79398915667881,51.07582189281116],"type":"Point"}
}