{
  "type": "Feature",
  "properties": {
    "date:inception_lower":"1980-01-01",
    "date:inception_upper":"1980-01-31",
    "iso:country":"GB",
    "wof:name":"ME8 8RY",
    "wof:placetype":"postalcode"
},
  "geometry": {"coordinates":[0.598028,51.341085],"type":"Point"}
}