{
  "type": "Feature",
  "properties": {
    "iso:country":"GB",
    "wof:name":"ME8 8RY",
    "wof:placetype":"postalcode"
},
  "geometry": {"coordinates":[0.5980276375586,51.34108508419702],"type":"Point"}
}