{
  "type": "Feature",
  "properties": {
    "iso:country": "GB",
    "wof:name": "ME8 8RY",
    "wof:placetype": "postalcode"
  },
  "geometry": {"coordinates":[0.598028,51.341085],"type":"Point"}
}
