{
  "type": "Feature",
  "properties": {
    "iso:country":"GB",
    "wof:name":"NN15 6LP",
    "wof:placetype":"postalcode"
},
  "geometry": {"coordinates":[-0.71486958680463,52.38031860594266],"type":"Point"}
}