{
  "type": "Feature",
  "properties": {
    "date:inception_lower": "1980-01-01",
    "date:inception_upper": "1980-01-01",
    "iso:country": "GB",
    "wof:name": "NN15 6LP",
    "wof:placetype": "postalcode"
  },
  "geometry": {"coordinates":[-0.71487,52.380319],"type":"Point"}
}
