{
  "type": "Feature",
  "properties": {
    "iso:country": "GB",
    "wof:name": "TS18 4LR",
    "wof:placetype": "postalcode"
  },
  "geometry": {"coordinates":[-1.331542,54.569226],"type":"Point"}
}
