{
  "type": "Feature",
  "properties": {
    "iso:country":"GB",
    "wof:name":"TS18 4LR",
    "wof:placetype":"postalcode"
},
  "geometry": {"coordinates":[-1.33154226452649,54.56922583817254],"type":"Point"}
}