{
  "type": "Feature",
  "properties": {
    "iso:country": "GB",
    "wof:name": "NE26 3PL",
    "wof:placetype": "postalcode"
  },
  "geometry": {"coordinates":[-1.454625,55.043507],"type":"Point"}
}
