{
  "type": "Feature",
  "properties": {
    "iso:country":"GB",
    "wof:name":"NE26 3PL",
    "wof:placetype":"postalcode"
},
  "geometry": {"coordinates":[-1.45462523080942,55.04350742049031],"type":"Point"}
}