{
  "type": "Feature",
  "properties": {
    "iso:country":"GB",
    "wof:name":"CV4 9QD",
    "wof:placetype":"postalcode"
},
  "geometry": {"coordinates":[-1.58389477667745,52.4098640738618],"type":"Point"}
}