{
  "type": "Feature",
  "properties": {
    "date:inception_lower": "1995-07-01",
    "date:inception_upper": "1995-07-01",
    "iso:country": "GB",
    "wof:name": "WA5 3HW",
    "wof:placetype": "postalcode"
  },
  "geometry": {"coordinates":[-2.670502,53.398389],"type":"Point"}
}
