{
  "type": "Feature",
  "properties": {
    "date:inception_lower":"2002-06-01",
    "date:inception_upper":"2002-06-30",
    "iso:country":"GB",
    "wof:name":"BH15 1JX",
    "wof:placetype":"postalcode"
},
  "geometry": {"coordinates":[-1.989254,50.713177],"type":"Point"}
}