{
  "type": "Feature",
  "properties": {
    "iso:country":"GB",
    "wof:name":"BH15 1JX",
    "wof:placetype":"postalcode"
},
  "geometry": {"coordinates":[-1.98925425421958,50.71317709444914],"type":"Point"}
}