{
  "type": "Feature",
  "properties": {
    "iso:country":"GB",
    "wof:name":"B69 2DR",
    "wof:placetype":"postalcode"
},
  "geometry": {"coordinates":[-2.03245506647678,52.50357429942142],"type":"Point"}
}