{
  "type": "Feature",
  "properties": {
    "iso:country":"GB",
    "wof:name":"NE25 9YB",
    "wof:placetype":"postalcode"
},
  "geometry": {"coordinates":[-1.47619167792912,55.04578572795704],"type":"Point"}
}