{
  "type": "Feature",
  "properties": {
    "iso:country": "GB",
    "wof:name": "NE25 9YB",
    "wof:placetype": "postalcode"
  },
  "geometry": {"coordinates":[-1.476192,55.045786],"type":"Point"}
}
