{
  "type": "Feature",
  "properties": {
    "date:inception_lower": "2006-03-01",
    "date:inception_upper": "2006-03-01",
    "iso:country": "GB",
    "wof:name": "FY6 7JP",
    "wof:placetype": "postalcode"
  },
  "geometry": {"coordinates":[-2.979174,53.84566],"type":"Point"}
}
