{
  "type": "Feature",
  "properties": {
    "date:inception_lower": "1980-01-01",
    "date:inception_upper": "1980-01-01",
    "iso:country": "GB",
    "wof:name": "FK15 9NB",
    "wof:placetype": "postalcode"
  },
  "geometry": {"coordinates":[-3.96339,56.208722],"type":"Point"}
}
