{
  "type": "Feature",
  "properties": {
    "iso:country":"GB",
    "wof:name":"FK15 9NB",
    "wof:placetype":"postalcode"
},
  "geometry": {"coordinates":[-3.96728422157603,56.20590829280057],"type":"Point"}
}