{
  "type": "Feature",
  "properties": {
    "iso:country": "GB",
    "wof:name": "FK15 9NB",
    "wof:placetype": "postalcode"
  },
  "geometry": {"coordinates":[-3.967277,56.205901],"type":"Point"}
}
