{
  "type": "Feature",
  "properties": {
    "iso:country":"GB",
    "wof:name":"PE12 9FR",
    "wof:placetype":"postalcode"
},
  "geometry": {"coordinates":[0.12265844194294,52.78032024899866],"type":"Point"}
}