{
  "type": "Feature",
  "properties": {
    "date:inception_lower": "1997-06-01",
    "date:inception_upper": "1997-06-01",
    "iso:country": "GB",
    "wof:name": "WA3 2GP",
    "wof:placetype": "postalcode"
  },
  "geometry": {"coordinates":[-2.570039,53.480465],"type":"Point"}
}
