{
  "type": "Feature",
  "properties": {
    "iso:country":"GB",
    "wof:name":"WA3 2GP",
    "wof:placetype":"postalcode"
},
  "geometry": {"coordinates":[-2.57003900289262,53.48046524223621],"type":"Point"}
}