{
  "type": "Feature",
  "properties": {
    "iso:country": "GB",
    "wof:name": "GL51 0ER",
    "wof:placetype": "postalcode"
  },
  "geometry": {"coordinates":[-2.111556,51.910763],"type":"Point"}
}
