{
  "type": "Feature",
  "properties": {
    "iso:country":"GB",
    "wof:name":"GL51 0ER",
    "wof:placetype":"postalcode"
},
  "geometry": {"coordinates":[-2.11155559451044,51.91076325483095],"type":"Point"}
}