{
  "type": "Feature",
  "properties": {
    "date:inception_lower": "2021-09-01",
    "date:inception_upper": "2021-09-01",
    "iso:country": "GB",
    "wof:name": "AL4 0BB",
    "wof:placetype": "postalcode"
  },
  "geometry": {"coordinates":[-0.297354,51.758128],"type":"Point"}
}
