{
  "type": "Feature",
  "properties": {
    "iso:country":"GB",
    "wof:name":"PO4 9BD",
    "wof:placetype":"postalcode"
},
  "geometry": {"coordinates":[-1.06509420588751,50.79024110467026],"type":"Point"}
}