{
  "type": "Feature",
  "properties": {
    "iso:country":"GB",
    "wof:name":"BH20 6FE",
    "wof:placetype":"postalcode"
},
  "geometry": {"coordinates":[-2.22964853145342,50.68028931313624],"type":"Point"}
}