{
  "type": "Feature",
  "properties": {
    "date:inception_lower":"2012-11-01",
    "date:inception_upper":"2012-11-30",
    "iso:country":"GB",
    "wof:name":"BH20 6FE",
    "wof:placetype":"postalcode"
},
  "geometry": {"coordinates":[-2.229648,50.680289],"type":"Point"}
}