{
  "type": "Feature",
  "properties": {
    "date:inception_lower": "1980-01-01",
    "date:inception_upper": "1980-01-01",
    "iso:country": "GB",
    "wof:name": "RH12 2LR",
    "wof:placetype": "postalcode"
  },
  "geometry": {"coordinates":[-0.328193,51.076332],"type":"Point"}
}
