{
  "type": "Feature",
  "properties": {
    "iso:country":"GB",
    "wof:name":"RH12 2LR",
    "wof:placetype":"postalcode"
},
  "geometry": {"coordinates":[-0.3282892700504,51.0763726088923],"type":"Point"}
}