{
  "type": "Feature",
  "properties": {
    "iso:country": "GB",
    "wof:name": "CM77 8FH",
    "wof:placetype": "postalcode"
  },
  "geometry": {"coordinates":[0.56291,51.852214],"type":"Point"}
}
