{
  "type": "Feature",
  "properties": {
    "iso:country":"GB",
    "wof:name":"CV11 4EG",
    "wof:placetype":"postalcode"
},
  "geometry": {"coordinates":[-1.46777797486683,52.52297931773475],"type":"Point"}
}