{
  "type": "Feature",
  "properties": {
    "iso:country": "GB",
    "wof:name": "CV11 4EG",
    "wof:placetype": "postalcode"
  },
  "geometry": {"coordinates":[-1.467778,52.522979],"type":"Point"}
}
