{
  "type": "Feature",
  "properties": {
    "iso:country":"GB",
    "wof:name":"DN9 1QL",
    "wof:placetype":"postalcode"
},
  "geometry": {"coordinates":[-0.8088362155622,53.57097716153151],"type":"Point"}
}