{
  "type": "Feature",
  "properties": {
    "date:inception_lower": "2021-06-01",
    "date:inception_upper": "2021-06-01",
    "iso:country": "GB",
    "wof:name": "MK45 4SY",
    "wof:placetype": "postalcode"
  },
  "geometry": {"coordinates":[-0.38143,52.009119],"type":"Point"}
}
