{
  "type": "Feature",
  "properties": {
    "date:inception_lower": "1980-01-01",
    "date:inception_upper": "1980-01-01",
    "iso:country": "GB",
    "wof:name": "SE13 7XG",
    "wof:placetype": "postalcode"
  },
  "geometry": {"coordinates":[-0.021248,51.454805],"type":"Point"}
}
