{
  "type": "Feature",
  "properties": {
    "iso:country": "GB",
    "wof:name": "SE13 7XG",
    "wof:placetype": "postalcode"
  },
  "geometry": {"coordinates":[-0.021248,51.454805],"type":"Point"}
}
