{
  "type": "Feature",
  "properties": {
    "iso:country":"GB",
    "wof:name":"SE13 7XG",
    "wof:placetype":"postalcode"
},
  "geometry": {"coordinates":[-0.02124761194024,51.45480509424228],"type":"Point"}
}