{
  "type": "Feature",
  "properties": {
    "iso:country":"GB",
    "wof:name":"RG40 5PJ",
    "wof:placetype":"postalcode"
},
  "geometry": {"coordinates":[-0.81413041824872,51.41733513943383],"type":"Point"}
}