{
  "type": "Feature",
  "properties": {
    "date:inception_lower": "1980-01-01",
    "date:inception_upper": "1980-01-01",
    "iso:country": "GB",
    "wof:name": "S6 1EX",
    "wof:placetype": "postalcode"
  },
  "geometry": {"coordinates":[-1.512039,53.430387],"type":"Point"}
}
