{
  "type": "Feature",
  "properties": {
    "iso:country":"GB",
    "wof:name":"S6 1EX",
    "wof:placetype":"postalcode"
},
  "geometry": {"coordinates":[-1.51202306812665,53.43037797582441],"type":"Point"}
}