{
  "type": "Feature",
  "properties": {
    "iso:country": "GB",
    "wof:name": "DG3 4NL",
    "wof:placetype": "postalcode"
  },
  "geometry": {"coordinates":[-3.9786,55.314652],"type":"Point"}
}
