{
  "type": "Feature",
  "properties": {
    "iso:country":"GB",
    "wof:name":"BL6 5LB",
    "wof:placetype":"postalcode"
},
  "geometry": {"coordinates":[-2.59519600195539,53.60253201266591],"type":"Point"}
}