{
  "type": "Feature",
  "properties": {
    "iso:country": "GB",
    "wof:name": "M38 9ER",
    "wof:placetype": "postalcode"
  },
  "geometry": {"coordinates":[-2.415672,53.536714],"type":"Point"}
}
