{
  "type": "Feature",
  "properties": {
    "iso:country":"GB",
    "wof:name":"M38 9ER",
    "wof:placetype":"postalcode"
},
  "geometry": {"coordinates":[-2.41567157107019,53.53671376938696],"type":"Point"}
}