{
  "type": "Feature",
  "properties": {
    "iso:country":"GB",
    "wof:name":"NW8 0DP",
    "wof:placetype":"postalcode"
},
  "geometry": {"coordinates":[-0.17798770961161,51.54060733832797],"type":"Point"}
}