{
  "type": "Feature",
  "properties": {
    "iso:country":"GB",
    "wof:name":"FY4 3BD",
    "wof:placetype":"postalcode"
},
  "geometry": {"coordinates":[-3.0401263727499,53.79786809920193],"type":"Point"}
}