{
  "type": "Feature",
  "properties": {
    "iso:country":"GB",
    "wof:name":"MK5 7EZ",
    "wof:placetype":"postalcode"
},
  "geometry": {"coordinates":[-0.78373267373148,52.01031662615996],"type":"Point"}
}