{
  "type": "Feature",
  "properties": {
    "iso:country":"GB",
    "wof:name":"ML6 9AB",
    "wof:placetype":"postalcode"
},
  "geometry": {"coordinates":[-4.00056905623039,55.86300846579873],"type":"Point"}
}