{
  "type": "Feature",
  "properties": {
    "date:inception_lower": "1994-10-01",
    "date:inception_upper": "1994-10-01",
    "iso:country": "GB",
    "wof:name": "ML6 9AB",
    "wof:placetype": "postalcode"
  },
  "geometry": {"coordinates":[-4.000569,55.863008],"type":"Point"}
}
