{
  "type": "Feature",
  "properties": {
    "iso:country":"GB",
    "wof:name":"CB23 6AS",
    "wof:placetype":"postalcode"
},
  "geometry": {"coordinates":[-0.05693419033103,52.2170293237137],"type":"Point"}
}