{
  "type": "Feature",
  "properties": {
    "iso:country":"GB",
    "wof:name":"HS6 5ET",
    "wof:placetype":"postalcode"
},
  "geometry": {"coordinates":[-7.35463210254581,57.54886005544688],"type":"Point"}
}