{
  "type": "Feature",
  "properties": {
    "date:inception_lower": "1995-07-01",
    "date:inception_upper": "1995-07-01",
    "iso:country": "GB",
    "wof:name": "HS6 5ET",
    "wof:placetype": "postalcode"
  },
  "geometry": {"coordinates":[-7.354632,57.54886],"type":"Point"}
}
