{
  "type": "Feature",
  "properties": {
    "iso:country": "GB",
    "wof:name": "TF2 8NW",
    "wof:placetype": "postalcode"
  },
  "geometry": {"coordinates":[-2.422715,52.726687],"type":"Point"}
}
