{
  "type": "Feature",
  "properties": {
    "iso:country":"GB",
    "wof:name":"WA11 7SS",
    "wof:placetype":"postalcode"
},
  "geometry": {"coordinates":[-2.81290833096,53.51250636043891],"type":"Point"}
}