{
  "type": "Feature",
  "properties": {
    "date:inception_lower": "1980-01-01",
    "date:inception_upper": "1980-01-01",
    "iso:country": "GB",
    "wof:name": "WA11 7SS",
    "wof:placetype": "postalcode"
  },
  "geometry": {"coordinates":[-2.812908,53.512522],"type":"Point"}
}
