{
  "type": "Feature",
  "properties": {
    "date:inception_lower": "1980-01-01",
    "date:inception_upper": "1980-01-01",
    "iso:country": "GB",
    "wof:name": "LA8 8LF",
    "wof:placetype": "postalcode"
  },
  "geometry": {"coordinates":[-2.844274,54.337717],"type":"Point"}
}
