{
  "type": "Feature",
  "properties": {
    "iso:country":"GB",
    "wof:name":"LA8 8LF",
    "wof:placetype":"postalcode"
},
  "geometry": {"coordinates":[-2.8442412738933,54.33768089166619],"type":"Point"}
}