{
  "type": "Feature",
  "properties": {
    "iso:country":"GB",
    "wof:name":"CO15 3AT",
    "wof:placetype":"postalcode"
},
  "geometry": {"coordinates":[1.1480328538523,51.79468525793111],"type":"Point"}
}