{
  "type": "Feature",
  "properties": {
    "date:inception_lower": "1980-01-01",
    "date:inception_upper": "1980-01-01",
    "iso:country": "GB",
    "wof:name": "CO15 3AT",
    "wof:placetype": "postalcode"
  },
  "geometry": {"coordinates":[1.148065,51.794696],"type":"Point"}
}
