{
  "type": "Feature",
  "properties": {
    "date:inception_lower": "2001-06-01",
    "date:inception_upper": "2001-06-01",
    "iso:country": "GB",
    "wof:name": "GU27 2AD",
    "wof:placetype": "postalcode"
  },
  "geometry": {"coordinates":[-0.70984,51.088598],"type":"Point"}
}
