{
  "type": "Feature",
  "properties": {
    "iso:country":"GB",
    "wof:name":"GU27 2AD",
    "wof:placetype":"postalcode"
},
  "geometry": {"coordinates":[-0.7098399539544,51.0885979404667],"type":"Point"}
}