{
  "type": "Feature",
  "properties": {
    "iso:country":"GB",
    "wof:name":"WN5 8BN",
    "wof:placetype":"postalcode"
},
  "geometry": {"coordinates":[-2.68162309704923,53.53320993580633],"type":"Point"}
}