{
  "type": "Feature",
  "properties": {
    "iso:country": "GB",
    "wof:name": "CM9 6BX",
    "wof:placetype": "postalcode"
  },
  "geometry": {"coordinates":[0.679425,51.719744],"type":"Point"}
}
