{
  "type": "Feature",
  "properties": {
    "iso:country":"GB",
    "wof:name":"CM9 6BX",
    "wof:placetype":"postalcode"
},
  "geometry": {"coordinates":[0.67942540005397,51.71974423596565],"type":"Point"}
}