{
  "type": "Feature",
  "properties": {
    "iso:country":"GB",
    "wof:name":"G73 1JJ",
    "wof:placetype":"postalcode"
},
  "geometry": {"coordinates":[-4.22183940255736,55.82966051653117],"type":"Point"}
}