{
  "type": "Feature",
  "properties": {
    "iso:country": "GB",
    "wof:name": "G73 1JJ",
    "wof:placetype": "postalcode"
  },
  "geometry": {"coordinates":[-4.221839,55.829661],"type":"Point"}
}
