{
  "type": "Feature",
  "properties": {
    "iso:country": "GB",
    "wof:name": "CH7 5LZ",
    "wof:placetype": "postalcode"
  },
  "geometry": {"coordinates":[-3.200304,53.141862],"type":"Point"}
}
