{
  "type": "Feature",
  "properties": {
    "iso:country": "GB",
    "wof:name": "DN20 9LL",
    "wof:placetype": "postalcode"
  },
  "geometry": {"coordinates":[-0.503842,53.550949],"type":"Point"}
}
