{
  "type": "Feature",
  "properties": {
    "iso:country":"GB",
    "wof:name":"TR14 8EP",
    "wof:placetype":"postalcode"
},
  "geometry": {"coordinates":[-5.30007962615137,50.21294947517134],"type":"Point"}
}