{
  "type": "Feature",
  "properties": {
    "iso:country": "GB",
    "wof:name": "SO22 5SE",
    "wof:placetype": "postalcode"
  },
  "geometry": {"coordinates":[-1.351871,51.054931],"type":"Point"}
}
