{
  "type": "Feature",
  "properties": {
    "iso:country":"GB",
    "wof:name":"LN2 4BY",
    "wof:placetype":"postalcode"
},
  "geometry": {"coordinates":[-0.5201012291348,53.24265173909127],"type":"Point"}
}