{
  "type": "Feature",
  "properties": {
    "date:inception_lower": "1980-01-01",
    "date:inception_upper": "1980-01-01",
    "iso:country": "GB",
    "wof:name": "LN2 4BY",
    "wof:placetype": "postalcode"
  },
  "geometry": {"coordinates":[-0.520101,53.242652],"type":"Point"}
}
