{
  "type": "Feature",
  "properties": {
    "iso:country": "GB",
    "wof:name": "PO18 9JG",
    "wof:placetype": "postalcode"
  },
  "geometry": {"coordinates":[-0.846465,50.908959],"type":"Point"}
}
