{
  "type": "Feature",
  "properties": {
    "iso:country":"GB",
    "wof:name":"PO18 9JG",
    "wof:placetype":"postalcode"
},
  "geometry": {"coordinates":[-0.84646553188557,50.90895933040241],"type":"Point"}
}