{
  "type": "Feature",
  "properties": {
    "iso:country": "GB",
    "wof:name": "WD3 5BL",
    "wof:placetype": "postalcode"
  },
  "geometry": {"coordinates":[-0.528441,51.646147],"type":"Point"}
}
