{
  "type": "Feature",
  "properties": {
    "iso:country":"GB",
    "wof:name":"CV3 2LT",
    "wof:placetype":"postalcode"
},
  "geometry": {"coordinates":[-1.44793455467847,52.39389854811835],"type":"Point"}
}