{
  "type": "Feature",
  "properties": {
    "iso:country":"GB",
    "wof:name":"PE21 0LP",
    "wof:placetype":"postalcode"
},
  "geometry": {"coordinates":[-0.01219966662576,52.9723719343809],"type":"Point"}
}