{
  "type": "Feature",
  "properties": {
    "iso:country":"GB",
    "wof:name":"LE4 6DS",
    "wof:placetype":"postalcode"
},
  "geometry": {"coordinates":[-1.11789335730708,52.6465798611293],"type":"Point"}
}