{
  "type": "Feature",
  "properties": {
    "iso:country":"GB",
    "wof:name":"TS8 0RZ",
    "wof:placetype":"postalcode"
},
  "geometry": {"coordinates":[-1.22212786133457,54.52768093583753],"type":"Point"}
}