{
  "type": "Feature",
  "properties": {
    "iso:country":"GB",
    "wof:name":"CO1 1XF",
    "wof:placetype":"postalcode"
},
  "geometry": {"coordinates":[0.89752035453994,51.89925987172933],"type":"Point"}
}