{
  "type": "Feature",
  "properties": {
    "iso:country":"GB",
    "wof:name":"DD8 4TP",
    "wof:placetype":"postalcode"
},
  "geometry": {"coordinates":[-3.00624592578214,56.68477714726271],"type":"Point"}
}