{
  "type": "Feature",
  "properties": {
    "iso:country":"GB",
    "wof:name":"G84 0EA",
    "wof:placetype":"postalcode"
},
  "geometry": {"coordinates":[-4.83479297270465,56.0848228442997],"type":"Point"}
}