{
  "type": "Feature",
  "properties": {
    "date:inception_lower": "2016-01-01",
    "date:inception_upper": "2016-01-01",
    "iso:country": "GB",
    "wof:name": "SK9 2EH",
    "wof:placetype": "postalcode"
  },
  "geometry": {"coordinates":[-2.204778,53.329427],"type":"Point"}
}
