{
  "type": "Feature",
  "properties": {
    "iso:country": "GB",
    "wof:name": "SK9 2EH",
    "wof:placetype": "postalcode"
  },
  "geometry": {"coordinates":[-2.204853,53.329355],"type":"Point"}
}
