{
  "type": "Feature",
  "properties": {
    "iso:country":"GB",
    "wof:name":"DN5 7QW",
    "wof:placetype":"postalcode"
},
  "geometry": {"coordinates":[-1.19436707704941,53.52399271630977],"type":"Point"}
}