{
  "type": "Feature",
  "properties": {
    "iso:country": "GB",
    "wof:name": "BS39 7NR",
    "wof:placetype": "postalcode"
  },
  "geometry": {"coordinates":[-2.501611,51.308907],"type":"Point"}
}
