{
  "type": "Feature",
  "properties": {
    "date:inception_lower": "1997-12-01",
    "date:inception_upper": "1997-12-01",
    "iso:country": "GB",
    "wof:name": "BS39 7NR",
    "wof:placetype": "postalcode"
  },
  "geometry": {"coordinates":[-2.501611,51.308907],"type":"Point"}
}
