{
  "type": "Feature",
  "properties": {
    "iso:country":"GB",
    "wof:name":"G53 6PS",
    "wof:placetype":"postalcode"
},
  "geometry": {"coordinates":[-4.34083332952019,55.8161191672811],"type":"Point"}
}