{
  "type": "Feature",
  "properties": {
    "iso:country":"GB",
    "wof:name":"SW2 1DG",
    "wof:placetype":"postalcode"
},
  "geometry": {"coordinates":[-0.11267802320711,51.45616884166698],"type":"Point"}
}