{
  "type": "Feature",
  "properties": {
    "iso:country": "GB",
    "wof:name": "HA2 8JX",
    "wof:placetype": "postalcode"
  },
  "geometry": {"coordinates":[-0.356167,51.562204],"type":"Point"}
}
