{
  "type": "Feature",
  "properties": {
    "iso:country": "GB",
    "wof:name": "L40 7AS",
    "wof:placetype": "postalcode"
  },
  "geometry": {"coordinates":[-2.847666,53.597061],"type":"Point"}
}
