{
  "type": "Feature",
  "properties": {
    "iso:country":"GB",
    "wof:name":"S73 8LR",
    "wof:placetype":"postalcode"
},
  "geometry": {"coordinates":[-1.41046623195552,53.52788663136776],"type":"Point"}
}