{
  "type": "Feature",
  "properties": {
    "iso:country": "GB",
    "wof:name": "S73 8LR",
    "wof:placetype": "postalcode"
  },
  "geometry": {"coordinates":[-1.410466,53.527887],"type":"Point"}
}
