{
  "type": "Feature",
  "properties": {
    "iso:country":"GB",
    "wof:name":"ST6 7JH",
    "wof:placetype":"postalcode"
},
  "geometry": {"coordinates":[-2.18984068457922,53.05904084408672],"type":"Point"}
}