{
  "type": "Feature",
  "properties": {
    "iso:country":"GB",
    "wof:name":"TW1 2DZ",
    "wof:placetype":"postalcode"
},
  "geometry": {"coordinates":[-0.30878912932212,51.454773539947],"type":"Point"}
}