{
  "type": "Feature",
  "properties": {
    "iso:country":"GB",
    "wof:name":"BR3 3XP",
    "wof:placetype":"postalcode"
},
  "geometry": {"coordinates":[-0.01765493225023,51.39451080514179],"type":"Point"}
}