{
  "type": "Feature",
  "properties": {
    "iso:country":"GB",
    "wof:name":"PE20 2PY",
    "wof:placetype":"postalcode"
},
  "geometry": {"coordinates":[-0.13615949371077,52.90649273177575],"type":"Point"}
}