{
  "type": "Feature",
  "properties": {
    "iso:country":"GB",
    "wof:name":"LS9 8SG",
    "wof:placetype":"postalcode"
},
  "geometry": {"coordinates":[-1.52563655509425,53.795349810781],"type":"Point"}
}