{
  "type": "Feature",
  "properties": {
    "date:inception_lower":"2003-06-01",
    "date:inception_upper":"2003-06-30",
    "iso:country":"GB",
    "wof:name":"KA27 8BP",
    "wof:placetype":"postalcode"
},
  "geometry": {"coordinates":[-5.158462,55.578133],"type":"Point"}
}