{
  "type": "Feature",
  "properties": {
    "iso:country": "GB",
    "wof:name": "KA27 8BP",
    "wof:placetype": "postalcode"
  },
  "geometry": {"coordinates":[-5.158462,55.578133],"type":"Point"}
}
