{
  "type": "Feature",
  "properties": {
    "iso:country":"GB",
    "wof:name":"SA3 3DE",
    "wof:placetype":"postalcode"
},
  "geometry": {"coordinates":[-4.04422672412394,51.5779068567914],"type":"Point"}
}