{
  "type": "Feature",
  "properties": {
    "iso:country": "GB",
    "wof:name": "SA3 3DE",
    "wof:placetype": "postalcode"
  },
  "geometry": {"coordinates":[-4.044227,51.577907],"type":"Point"}
}
