{
  "type": "Feature",
  "properties": {
    "iso:country":"GB",
    "wof:name":"ST4 8LG",
    "wof:placetype":"postalcode"
},
  "geometry": {"coordinates":[-2.19505051880149,52.96715421425803],"type":"Point"}
}