{
  "type": "Feature",
  "properties": {
    "date:inception_lower":"1980-01-01",
    "date:inception_upper":"1980-01-31",
    "iso:country":"GB",
    "wof:name":"ST4 8LG",
    "wof:placetype":"postalcode"
},
  "geometry": {"coordinates":[-2.19505,52.967154],"type":"Point"}
}