{
  "type": "Feature",
  "properties": {
    "date:inception_lower": "1980-01-01",
    "date:inception_upper": "1980-01-01",
    "iso:country": "GB",
    "wof:name": "CO10 0BD",
    "wof:placetype": "postalcode"
  },
  "geometry": {"coordinates":[0.746063,52.078393],"type":"Point"}
}
