{
  "type": "Feature",
  "properties": {
    "iso:country":"GB",
    "wof:name":"KT12 4SG",
    "wof:placetype":"postalcode"
},
  "geometry": {"coordinates":[-0.39107060279538,51.3762590913698],"type":"Point"}
}