{
  "type": "Feature",
  "properties": {
    "iso:country":"GB",
    "wof:name":"EH22 5AY",
    "wof:placetype":"postalcode"
},
  "geometry": {"coordinates":[-3.04336730388744,55.87713907104369],"type":"Point"}
}