{
  "type": "Feature",
  "properties": {
    "iso:country":"GB",
    "wof:name":"B25 8TP",
    "wof:placetype":"postalcode"
},
  "geometry": {"coordinates":[-1.81429097825184,52.46812994775171],"type":"Point"}
}