{
  "type": "Feature",
  "properties": {
    "iso:country": "GB",
    "wof:name": "SY5 7LW",
    "wof:placetype": "postalcode"
  },
  "geometry": {"coordinates":[-2.757381,52.628017],"type":"Point"}
}
