{
  "type": "Feature",
  "properties": {
    "iso:country":"GB",
    "wof:name":"SY5 7LW",
    "wof:placetype":"postalcode"
},
  "geometry": {"coordinates":[-2.75728012932679,52.62723932621618],"type":"Point"}
}