{
  "type": "Feature",
  "properties": {
    "iso:country":"GB",
    "wof:name":"NR10 5PF",
    "wof:placetype":"postalcode"
},
  "geometry": {"coordinates":[1.28246815370337,52.76089817526044],"type":"Point"}
}