{
  "type": "Feature",
  "properties": {
    "iso:country": "GB",
    "wof:name": "L1 9DH",
    "wof:placetype": "postalcode"
  },
  "geometry": {"coordinates":[-2.96946,53.401675],"type":"Point"}
}
