{
  "type": "Feature",
  "properties": {
    "iso:country":"GB",
    "wof:name":"M40 1EP",
    "wof:placetype":"postalcode"
},
  "geometry": {"coordinates":[-2.17899535910713,53.50398278361654],"type":"Point"}
}