{
  "type": "Feature",
  "properties": {
    "date:inception_lower": "1994-05-01",
    "date:inception_upper": "1994-05-01",
    "iso:country": "GB",
    "wof:name": "M40 1EP",
    "wof:placetype": "postalcode"
  },
  "geometry": {"coordinates":[-2.178995,53.503983],"type":"Point"}
}
