{
  "type": "Feature",
  "properties": {
    "iso:country":"GB",
    "wof:name":"KY2 6AP",
    "wof:placetype":"postalcode"
},
  "geometry": {"coordinates":[-3.17698455018685,56.12528721337321],"type":"Point"}
}