{
  "type": "Feature",
  "properties": {
    "iso:country":"GB",
    "wof:name":"SS8 7NA",
    "wof:placetype":"postalcode"
},
  "geometry": {"coordinates":[0.60856351538861,51.51752191922738],"type":"Point"}
}