{
  "type": "Feature",
  "properties": {
    "iso:country": "GB",
    "wof:name": "WA8 3EQ",
    "wof:placetype": "postalcode"
  },
  "geometry": {"coordinates":[-2.711382,53.384085],"type":"Point"}
}
