{
  "type": "Feature",
  "properties": {
    "date:inception_lower":"2003-11-01",
    "date:inception_upper":"2003-11-30",
    "iso:country":"GB",
    "wof:name":"WA8 3EQ",
    "wof:placetype":"postalcode"
},
  "geometry": {"coordinates":[-2.711382,53.384085],"type":"Point"}
}