{
  "type": "Feature",
  "properties": {
    "date:inception_lower": "2023-06-01",
    "date:inception_upper": "2023-06-01",
    "iso:country": "GB",
    "wof:name": "CH7 3FQ",
    "wof:placetype": "postalcode"
  },
  "geometry": {"coordinates":[-3.087841,53.175312],"type":"Point"}
}
