{
  "type": "Feature",
  "properties": {
    "iso:country":"GB",
    "wof:name":"ML6 9AG",
    "wof:placetype":"postalcode"
},
  "geometry": {"coordinates":[-4.00021158671303,55.86258290678049],"type":"Point"}
}