{
  "type": "Feature",
  "properties": {
    "iso:country": "GB",
    "wof:name": "EX7 9ES",
    "wof:placetype": "postalcode"
  },
  "geometry": {"coordinates":[-3.472179,50.577105],"type":"Point"}
}
