{
  "type": "Feature",
  "properties": {
    "date:inception_lower":"1994-12-01",
    "date:inception_upper":"1994-12-31",
    "iso:country":"GB",
    "wof:name":"SO32 1SS",
    "wof:placetype":"postalcode"
},
  "geometry": {"coordinates":[-1.222565,50.953884],"type":"Point"}
}