{
  "type": "Feature",
  "properties": {
    "iso:country": "GB",
    "wof:name": "PO33 3TD",
    "wof:placetype": "postalcode"
  },
  "geometry": {"coordinates":[-1.191006,50.726288],"type":"Point"}
}
