{
  "type": "Feature",
  "properties": {
    "iso:country": "GB",
    "wof:name": "LS13 1LD",
    "wof:placetype": "postalcode"
  },
  "geometry": {"coordinates":[-1.652879,53.819828],"type":"Point"}
}
