{
  "type": "Feature",
  "properties": {
    "date:inception_lower": "1988-03-01",
    "date:inception_upper": "1988-03-01",
    "iso:country": "GB",
    "wof:name": "RH12 1LZ",
    "wof:placetype": "postalcode"
  },
  "geometry": {"coordinates":[-0.342212,51.065474],"type":"Point"}
}
