{
  "type": "Feature",
  "properties": {
    "iso:country": "GB",
    "wof:name": "TA2 6NY",
    "wof:placetype": "postalcode"
  },
  "geometry": {"coordinates":[-3.143177,51.035394],"type":"Point"}
}
