{
  "type": "Feature",
  "properties": {
    "iso:country":"GB",
    "wof:name":"TA2 6NY",
    "wof:placetype":"postalcode"
},
  "geometry": {"coordinates":[-3.14317669079301,51.03539370815291],"type":"Point"}
}