{
  "type": "Feature",
  "properties": {
    "iso:country":"GB",
    "wof:name":"CB4 3XG",
    "wof:placetype":"postalcode"
},
  "geometry": {"coordinates":[0.11624003789554,52.22855437033775],"type":"Point"}
}