{
  "type": "Feature",
  "properties": {
    "date:inception_lower":"1996-12-01",
    "date:inception_upper":"1996-12-31",
    "iso:country":"GB",
    "wof:name":"CB4 3XG",
    "wof:placetype":"postalcode"
},
  "geometry": {"coordinates":[0.11624,52.228554],"type":"Point"}
}