{
  "type": "Feature",
  "properties": {
    "date:inception_lower": "1980-01-01",
    "date:inception_upper": "1980-01-01",
    "iso:country": "GB",
    "wof:name": "SA65 9LP",
    "wof:placetype": "postalcode"
  },
  "geometry": {"coordinates":[-4.969728,51.991562],"type":"Point"}
}
