{
  "type": "Feature",
  "properties": {
    "iso:country":"GB",
    "wof:name":"KA28 0ES",
    "wof:placetype":"postalcode"
},
  "geometry": {"coordinates":[-4.93554494111881,55.75067556160583],"type":"Point"}
}