{
  "type": "Feature",
  "properties": {
    "date:inception_lower": "1993-01-01",
    "date:inception_upper": "1993-01-01",
    "iso:country": "GB",
    "wof:name": "LS22 6TA",
    "wof:placetype": "postalcode"
  },
  "geometry": {"coordinates":[-1.383557,53.930323],"type":"Point"}
}
