{
  "type": "Feature",
  "properties": {
    "iso:country":"GB",
    "wof:name":"LS22 6TA",
    "wof:placetype":"postalcode"
},
  "geometry": {"coordinates":[-1.38393179907328,53.93029909768541],"type":"Point"}
}