{
  "type": "Feature",
  "properties": {
    "iso:country":"GB",
    "wof:name":"CM19 5BX",
    "wof:placetype":"postalcode"
},
  "geometry": {"coordinates":[0.06193220871539,51.76421947954859],"type":"Point"}
}