{
  "type": "Feature",
  "properties": {
    "date:inception_lower": "1980-01-01",
    "date:inception_upper": "1980-01-01",
    "iso:country": "GB",
    "wof:name": "BB4 8NZ",
    "wof:placetype": "postalcode"
  },
  "geometry": {"coordinates":[-2.285576,53.723934],"type":"Point"}
}
