{
  "type": "Feature",
  "properties": {
    "iso:country":"GB",
    "wof:name":"BS20 7BB",
    "wof:placetype":"postalcode"
},
  "geometry": {"coordinates":[-2.76210208499772,51.48978253694191],"type":"Point"}
}