{
  "type": "Feature",
  "properties": {
    "date:inception_lower": "2004-03-01",
    "date:inception_upper": "2004-03-01",
    "iso:country": "GB",
    "wof:name": "BS20 7BB",
    "wof:placetype": "postalcode"
  },
  "geometry": {"coordinates":[-2.762102,51.489783],"type":"Point"}
}
