{
  "type": "Feature",
  "properties": {
    "iso:country": "GB",
    "wof:name": "SN3 4LF",
    "wof:placetype": "postalcode"
  },
  "geometry": {"coordinates":[-1.74774,51.584369],"type":"Point"}
}
