{
  "type": "Feature",
  "properties": {
    "iso:country":"GB",
    "wof:name":"SN3 4LF",
    "wof:placetype":"postalcode"
},
  "geometry": {"coordinates":[-1.74781077888588,51.58428663708623],"type":"Point"}
}