{
  "type": "Feature",
  "properties": {
    "iso:country":"GB",
    "wof:name":"BA13 3QQ",
    "wof:placetype":"postalcode"
},
  "geometry": {"coordinates":[-2.19003678986556,51.25649713414333],"type":"Point"}
}