{
  "type": "Feature",
  "properties": {
    "iso:country": "GB",
    "wof:name": "LL68 9ST",
    "wof:placetype": "postalcode"
  },
  "geometry": {"coordinates":[-4.37575,53.421382],"type":"Point"}
}
