{
  "type": "Feature",
  "properties": {
    "date:inception_lower":"1980-01-01",
    "date:inception_upper":"1980-01-31",
    "iso:country":"GB",
    "wof:name":"LL68 9ST",
    "wof:placetype":"postalcode"
},
  "geometry": {"coordinates":[-4.37575,53.421382],"type":"Point"}
}