{
  "type": "Feature",
  "properties": {
    "iso:country": "GB",
    "wof:name": "OX11 6HG",
    "wof:placetype": "postalcode"
  },
  "geometry": {"coordinates":[-1.26413,51.600444],"type":"Point"}
}
