{
  "type": "Feature",
  "properties": {
    "iso:country":"GB",
    "wof:name":"SL4 4FB",
    "wof:placetype":"postalcode"
},
  "geometry": {"coordinates":[-0.66717789537482,51.44827191466741],"type":"Point"}
}