{
  "type": "Feature",
  "properties": {
    "iso:country":"GB",
    "wof:name":"DH7 9RJ",
    "wof:placetype":"postalcode"
},
  "geometry": {"coordinates":[-1.67030428042127,54.7875606308764],"type":"Point"}
}