{
  "type": "Feature",
  "properties": {
    "iso:country": "GB",
    "wof:name": "OX3 0DA",
    "wof:placetype": "postalcode"
  },
  "geometry": {"coordinates":[-1.226909,51.760312],"type":"Point"}
}
