{
  "type": "Feature",
  "properties": {
    "iso:country":"GB",
    "wof:name":"OX3 0DA",
    "wof:placetype":"postalcode"
},
  "geometry": {"coordinates":[-1.22690940030362,51.7603120058882],"type":"Point"}
}