{
  "type": "Feature",
  "properties": {
    "date:inception_lower": "2001-06-01",
    "date:inception_upper": "2001-06-01",
    "iso:country": "GB",
    "wof:name": "KA27 8GB",
    "wof:placetype": "postalcode"
  },
  "geometry": {"coordinates":[-5.08745,55.533274],"type":"Point"}
}
