{
  "type": "Feature",
  "properties": {
    "iso:country":"GB",
    "wof:name":"KA27 8GB",
    "wof:placetype":"postalcode"
},
  "geometry": {"coordinates":[-5.06922019705752,55.51277022902708],"type":"Point"}
}