{
  "type": "Feature",
  "properties": {
    "iso:country": "GB",
    "wof:name": "KA27 8GB",
    "wof:placetype": "postalcode"
  },
  "geometry": {"coordinates":[-5.08745,55.533274],"type":"Point"}
}
