{
  "type": "Feature",
  "properties": {
    "iso:country":"GB",
    "wof:name":"SA11 4HL",
    "wof:placetype":"postalcode"
},
  "geometry": {"coordinates":[-3.69809651006771,51.70953320757075],"type":"Point"}
}