{
  "type": "Feature",
  "properties": {
    "date:inception_lower": "1980-01-01",
    "date:inception_upper": "1980-01-01",
    "iso:country": "GB",
    "wof:name": "GU32 1EX",
    "wof:placetype": "postalcode"
  },
  "geometry": {"coordinates":[-1.024464,51.005238],"type":"Point"}
}
