{
  "type": "Feature",
  "properties": {
    "iso:country": "GB",
    "wof:name": "GU32 1EX",
    "wof:placetype": "postalcode"
  },
  "geometry": {"coordinates":[-1.024464,51.005238],"type":"Point"}
}
