{
  "type": "Feature",
  "properties": {
    "iso:country": "GB",
    "wof:name": "PL7 1SZ",
    "wof:placetype": "postalcode"
  },
  "geometry": {"coordinates":[-4.058988,50.385691],"type":"Point"}
}
