{
  "type": "Feature",
  "properties": {
    "date:inception_lower":"1980-01-01",
    "date:inception_upper":"1980-01-31",
    "iso:country":"GB",
    "wof:name":"HD8 0QL",
    "wof:placetype":"postalcode"
},
  "geometry": {"coordinates":[-1.71138,53.615144],"type":"Point"}
}