{
  "type": "Feature",
  "properties": {
    "iso:country":"GB",
    "wof:name":"HD8 0QL",
    "wof:placetype":"postalcode"
},
  "geometry": {"coordinates":[-1.71138016206963,53.61514404140841],"type":"Point"}
}