{
  "type": "Feature",
  "properties": {
    "iso:country": "GB",
    "wof:name": "S8 8TE",
    "wof:placetype": "postalcode"
  },
  "geometry": {"coordinates":[-1.477724,53.346665],"type":"Point"}
}
