{
  "type": "Feature",
  "properties": {
    "iso:country":"GB",
    "wof:name":"SL4 5SF",
    "wof:placetype":"postalcode"
},
  "geometry": {"coordinates":[-0.65381698542289,51.48322431820797],"type":"Point"}
}