{
  "type": "Feature",
  "properties": {
    "iso:country": "GB",
    "wof:name": "RG29 1HR",
    "wof:placetype": "postalcode"
  },
  "geometry": {"coordinates":[-0.919034,51.254523],"type":"Point"}
}
