{
  "type": "Feature",
  "properties": {
    "iso:country":"GB",
    "wof:name":"RG29 1HR",
    "wof:placetype":"postalcode"
},
  "geometry": {"coordinates":[-0.91903376307121,51.25452289958593],"type":"Point"}
}