{
  "type": "Feature",
  "properties": {
    "iso:country":"GB",
    "wof:name":"HX3 8EQ",
    "wof:placetype":"postalcode"
},
  "geometry": {"coordinates":[-1.81305979293403,53.72280830182864],"type":"Point"}
}