{
  "type": "Feature",
  "properties": {
    "iso:country": "GB",
    "wof:name": "NE37 3BD",
    "wof:placetype": "postalcode"
  },
  "geometry": {"coordinates":[-1.512886,54.915852],"type":"Point"}
}
