{
  "type": "Feature",
  "properties": {
    "iso:country":"GB",
    "wof:name":"SE1 3ER",
    "wof:placetype":"postalcode"
},
  "geometry": {"coordinates":[-0.0843103345284,51.50008729665537],"type":"Point"}
}