{
  "type": "Feature",
  "properties": {
    "date:inception_lower": "1980-01-01",
    "date:inception_upper": "1980-01-01",
    "iso:country": "GB",
    "wof:name": "NR16 2JJ",
    "wof:placetype": "postalcode"
  },
  "geometry": {"coordinates":[0.968861,52.473778],"type":"Point"}
}
