{
  "type": "Feature",
  "properties": {
    "iso:country": "GB",
    "wof:name": "NR16 2JJ",
    "wof:placetype": "postalcode"
  },
  "geometry": {"coordinates":[0.968861,52.473778],"type":"Point"}
}
