{
  "type": "Feature",
  "properties": {
    "iso:country":"GB",
    "wof:name":"NR16 2JJ",
    "wof:placetype":"postalcode"
},
  "geometry": {"coordinates":[0.96886047972406,52.47377767932923],"type":"Point"}
}