{
  "type": "Feature",
  "properties": {
    "date:inception_lower":"1980-01-01",
    "date:inception_upper":"1980-01-31",
    "iso:country":"GB",
    "wof:name":"SR6 9AH",
    "wof:placetype":"postalcode"
},
  "geometry": {"coordinates":[-1.384532,54.926953],"type":"Point"}
}