{
  "type": "Feature",
  "properties": {
    "iso:country": "GB",
    "wof:name": "SR6 9AH",
    "wof:placetype": "postalcode"
  },
  "geometry": {"coordinates":[-1.384532,54.926953],"type":"Point"}
}
