{
  "type": "Feature",
  "properties": {
    "iso:country": "GB",
    "wof:name": "HP14 3BU",
    "wof:placetype": "postalcode"
  },
  "geometry": {"coordinates":[-0.830251,51.639569],"type":"Point"}
}
