{
  "type": "Feature",
  "properties": {
    "date:inception_lower": "1986-07-01",
    "date:inception_upper": "1986-07-01",
    "iso:country": "GB",
    "wof:name": "HP14 3BU",
    "wof:placetype": "postalcode"
  },
  "geometry": {"coordinates":[-0.830251,51.639569],"type":"Point"}
}
