{
  "type": "Feature",
  "properties": {
    "iso:country":"GB",
    "wof:name":"LS9 7TW",
    "wof:placetype":"postalcode"
},
  "geometry": {"coordinates":[-1.52743678430014,53.8013159887703],"type":"Point"}
}