{
  "type": "Feature",
  "properties": {
    "iso:country":"GB",
    "wof:name":"SS16 4JL",
    "wof:placetype":"postalcode"
},
  "geometry": {"coordinates":[0.48459192099931,51.56483920263025],"type":"Point"}
}