{
  "type": "Feature",
  "properties": {
    "date:inception_lower": "2009-05-01",
    "date:inception_upper": "2009-05-01",
    "iso:country": "GB",
    "wof:name": "SS16 4JL",
    "wof:placetype": "postalcode"
  },
  "geometry": {"coordinates":[0.484592,51.564839],"type":"Point"}
}
