{
  "type": "Feature",
  "properties": {
    "iso:country": "GB",
    "wof:name": "YO23 3RB",
    "wof:placetype": "postalcode"
  },
  "geometry": {"coordinates":[-1.198082,53.95595],"type":"Point"}
}
