{
  "type": "Feature",
  "properties": {
    "date:inception_lower":"1998-06-01",
    "date:inception_upper":"1998-06-30",
    "iso:country":"GB",
    "wof:name":"YO23 3RB",
    "wof:placetype":"postalcode"
},
  "geometry": {"coordinates":[-1.198105,53.955933],"type":"Point"}
}