{
  "type": "Feature",
  "properties": {
    "iso:country":"GB",
    "wof:name":"YO23 3RB",
    "wof:placetype":"postalcode"
},
  "geometry": {"coordinates":[-1.19810522538727,53.95593291356526],"type":"Point"}
}