{
  "type": "Feature",
  "properties": {
    "date:inception_lower": "1980-01-01",
    "date:inception_upper": "1980-01-01",
    "iso:country": "GB",
    "wof:name": "DL11 7DT",
    "wof:placetype": "postalcode"
  },
  "geometry": {"coordinates":[-1.876162,54.487224],"type":"Point"}
}
