{
  "type": "Feature",
  "properties": {
    "iso:country":"GB",
    "wof:name":"DL11 7DT",
    "wof:placetype":"postalcode"
},
  "geometry": {"coordinates":[-1.87615471257558,54.48721389602013],"type":"Point"}
}