{
  "type": "Feature",
  "properties": {
    "date:inception_lower":"1980-01-01",
    "date:inception_upper":"1980-01-31",
    "iso:country":"GB",
    "wof:name":"CH5 2DR",
    "wof:placetype":"postalcode"
},
  "geometry": {"coordinates":[-3.009277,53.199522],"type":"Point"}
}