{
  "type": "Feature",
  "properties": {
    "iso:country":"GB",
    "wof:name":"CH5 2DR",
    "wof:placetype":"postalcode"
},
  "geometry": {"coordinates":[-3.00927717479443,53.19952168054263],"type":"Point"}
}