{
  "type": "Feature",
  "properties": {
    "date:inception_lower":"2003-10-01",
    "date:inception_upper":"2003-10-31",
    "iso:country":"GB",
    "wof:name":"WV16 5JS",
    "wof:placetype":"postalcode"
},
  "geometry": {"coordinates":[-2.428053,52.531011],"type":"Point"}
}