{
  "type": "Feature",
  "properties": {
    "iso:country": "GB",
    "wof:name": "WV16 5JS",
    "wof:placetype": "postalcode"
  },
  "geometry": {"coordinates":[-2.428053,52.531011],"type":"Point"}
}
