{
  "type": "Feature",
  "properties": {
    "date:inception_lower":"2015-04-01",
    "date:inception_upper":"2015-04-30",
    "iso:country":"GB",
    "wof:name":"NE24 4GQ",
    "wof:placetype":"postalcode"
},
  "geometry": {"coordinates":[-1.543013,55.118956],"type":"Point"}
}