{
  "type": "Feature",
  "properties": {
    "iso:country": "GB",
    "wof:name": "NE24 4GQ",
    "wof:placetype": "postalcode"
  },
  "geometry": {"coordinates":[-1.542373,55.118756],"type":"Point"}
}
