{
  "type": "Feature",
  "properties": {
    "date:inception_lower": "2023-06-01",
    "date:inception_upper": "2023-06-01",
    "iso:country": "GB",
    "wof:name": "CH41 1BT",
    "wof:placetype": "postalcode"
  },
  "geometry": {"coordinates":[-3.034387,53.405273],"type":"Point"}
}
