{
  "type": "Feature",
  "properties": {
    "iso:country":"GB",
    "wof:name":"DN21 2EE",
    "wof:placetype":"postalcode"
},
  "geometry": {"coordinates":[-0.77418965455084,53.39754347095161],"type":"Point"}
}