{
  "type": "Feature",
  "properties": {
    "date:inception_lower": "1980-01-01",
    "date:inception_upper": "1980-01-01",
    "iso:country": "GB",
    "wof:name": "TN39 4NA",
    "wof:placetype": "postalcode"
  },
  "geometry": {"coordinates":[0.434444,50.850859],"type":"Point"}
}
