{
  "type": "Feature",
  "properties": {
    "date:inception_lower":"1980-01-01",
    "date:inception_upper":"1980-01-31",
    "iso:country":"GB",
    "wof:name":"SN1 2BN",
    "wof:placetype":"postalcode"
},
  "geometry": {"coordinates":[-1.779282,51.564758],"type":"Point"}
}