{
  "type": "Feature",
  "properties": {
    "iso:country":"GB",
    "wof:name":"B45 8BX",
    "wof:placetype":"postalcode"
},
  "geometry": {"coordinates":[-1.99992622092435,52.35370592511035],"type":"Point"}
}