{
  "type": "Feature",
  "properties": {
    "date:inception_lower": "1980-01-01",
    "date:inception_upper": "1980-01-01",
    "iso:country": "GB",
    "wof:name": "B45 8BX",
    "wof:placetype": "postalcode"
  },
  "geometry": {"coordinates":[-1.999904,52.353945],"type":"Point"}
}
