{
  "type": "Feature",
  "properties": {
    "iso:country":"GB",
    "wof:name":"YO61 3HR",
    "wof:placetype":"postalcode"
},
  "geometry": {"coordinates":[-1.20294044333186,54.12736350998252],"type":"Point"}
}