{
  "type": "Feature",
  "properties": {
    "iso:country":"GB",
    "wof:name":"EH39 4QX",
    "wof:placetype":"postalcode"
},
  "geometry": {"coordinates":[-2.7294282223568,56.05210978322398],"type":"Point"}
}