{
  "type": "Feature",
  "properties": {
    "iso:country": "GB",
    "wof:name": "LE2 4QG",
    "wof:placetype": "postalcode"
  },
  "geometry": {"coordinates":[-1.050529,52.593072],"type":"Point"}
}
