{
  "type": "Feature",
  "properties": {
    "iso:country":"GB",
    "wof:name":"LE2 4QG",
    "wof:placetype":"postalcode"
},
  "geometry": {"coordinates":[-1.05052925517034,52.59307192762181],"type":"Point"}
}