{
  "type": "Feature",
  "properties": {
    "date:inception_lower":"2003-09-01",
    "date:inception_upper":"2003-09-30",
    "iso:country":"GB",
    "wof:name":"LE2 4QG",
    "wof:placetype":"postalcode"
},
  "geometry": {"coordinates":[-1.050529,52.593072],"type":"Point"}
}