{
  "type": "Feature",
  "properties": {
    "date:inception_lower": "2017-05-01",
    "date:inception_upper": "2017-05-01",
    "iso:country": "GB",
    "wof:name": "NN2 8EZ",
    "wof:placetype": "postalcode"
  },
  "geometry": {"coordinates":[-0.906398,52.280658],"type":"Point"}
}
