{
  "type": "Feature",
  "properties": {
    "iso:country":"GB",
    "wof:name":"CM3 4AN",
    "wof:placetype":"postalcode"
},
  "geometry": {"coordinates":[0.55562339171035,51.71044353181075],"type":"Point"}
}