{
  "type": "Feature",
  "properties": {
    "iso:country": "GB",
    "wof:name": "CM3 4AN",
    "wof:placetype": "postalcode"
  },
  "geometry": {"coordinates":[0.555623,51.710444],"type":"Point"}
}
