{
  "type": "Feature",
  "properties": {
    "iso:country":"GB",
    "wof:name":"PE9 2YB",
    "wof:placetype":"postalcode"
},
  "geometry": {"coordinates":[-0.48295473349945,52.65248786328711],"type":"Point"}
}