{
  "type": "Feature",
  "properties": {
    "iso:country": "GB",
    "wof:name": "KY1 4AU",
    "wof:placetype": "postalcode"
  },
  "geometry": {"coordinates":[-3.142304,56.167699],"type":"Point"}
}
