{
  "type": "Feature",
  "properties": {
    "date:inception_lower": "2005-01-01",
    "date:inception_upper": "2005-01-01",
    "iso:country": "GB",
    "wof:name": "PR2 5LU",
    "wof:placetype": "postalcode"
  },
  "geometry": {"coordinates":[-2.630492,53.800713],"type":"Point"}
}
