{
  "type": "Feature",
  "properties": {
    "date:inception_lower":"2009-02-01",
    "date:inception_upper":"2009-02-28",
    "iso:country":"GB",
    "wof:name":"CB11 4FD",
    "wof:placetype":"postalcode"
},
  "geometry": {"coordinates":[0.210475,52.034152],"type":"Point"}
}