{
  "type": "Feature",
  "properties": {
    "iso:country":"GB",
    "wof:name":"CB11 4FD",
    "wof:placetype":"postalcode"
},
  "geometry": {"coordinates":[0.21047492886077,52.03415216296181],"type":"Point"}
}