{
  "type": "Feature",
  "properties": {
    "iso:country":"GB",
    "wof:name":"EX15 1UB",
    "wof:placetype":"postalcode"
},
  "geometry": {"coordinates":[-3.40162966237395,50.8509945909507],"type":"Point"}
}