{
  "type": "Feature",
  "properties": {
    "iso:country": "GB",
    "wof:name": "EX15 1UB",
    "wof:placetype": "postalcode"
  },
  "geometry": {"coordinates":[-3.40163,50.850995],"type":"Point"}
}
