{
  "type": "Feature",
  "properties": {
    "iso:country":"GB",
    "wof:name":"PO13 8EG",
    "wof:placetype":"postalcode"
},
  "geometry": {"coordinates":[-1.17277947432428,50.80528071687579],"type":"Point"}
}