{
  "type": "Feature",
  "properties": {
    "iso:country": "GB",
    "wof:name": "PO13 8EG",
    "wof:placetype": "postalcode"
  },
  "geometry": {"coordinates":[-1.172779,50.805281],"type":"Point"}
}
