{
  "type": "Feature",
  "properties": {
    "date:inception_lower": "1990-02-01",
    "date:inception_upper": "1990-02-01",
    "iso:country": "GB",
    "wof:name": "DY3 1QW",
    "wof:placetype": "postalcode"
  },
  "geometry": {"coordinates":[-2.12514,52.549223],"type":"Point"}
}
