{
  "type": "Feature",
  "properties": {
    "iso:country":"GB",
    "wof:name":"DH6 2DP",
    "wof:placetype":"postalcode"
},
  "geometry": {"coordinates":[-1.41613959307317,54.78069123045561],"type":"Point"}
}