{
  "type": "Feature",
  "properties": {
    "iso:country":"GB",
    "wof:name":"HD1 3DH",
    "wof:placetype":"postalcode"
},
  "geometry": {"coordinates":[-1.77686394128933,53.64372264771489],"type":"Point"}
}