{
  "type": "Feature",
  "properties": {
    "iso:country": "GB",
    "wof:name": "CF11 7JR",
    "wof:placetype": "postalcode"
  },
  "geometry": {"coordinates":[-3.179272,51.463157],"type":"Point"}
}
