{
  "type": "Feature",
  "properties": {
    "iso:country":"GB",
    "wof:name":"CF11 7JR",
    "wof:placetype":"postalcode"
},
  "geometry": {"coordinates":[-3.17927221292235,51.46315653327099],"type":"Point"}
}