{
  "type": "Feature",
  "properties": {
    "date:inception_lower": "2004-06-01",
    "date:inception_upper": "2004-06-01",
    "iso:country": "GB",
    "wof:name": "CF11 7JR",
    "wof:placetype": "postalcode"
  },
  "geometry": {"coordinates":[-3.179272,51.463157],"type":"Point"}
}
