{
  "type": "Feature",
  "properties": {
    "iso:country":"GB",
    "wof:name":"KW15 1AX",
    "wof:placetype":"postalcode"
},
  "geometry": {"coordinates":[-2.9636230823485,58.97884359148178],"type":"Point"}
}