{
  "type": "Feature",
  "properties": {
    "iso:country":"GB",
    "wof:name":"CH62 3LT",
    "wof:placetype":"postalcode"
},
  "geometry": {"coordinates":[-2.98024429694244,53.34409352084278],"type":"Point"}
}