{
  "type": "Feature",
  "properties": {
    "iso:country":"GB",
    "wof:name":"TR10 8NE",
    "wof:placetype":"postalcode"
},
  "geometry": {"coordinates":[-5.10817985961194,50.16904863785653],"type":"Point"}
}