{
  "type": "Feature",
  "properties": {
    "iso:country":"GB",
    "wof:name":"CH65 5BQ",
    "wof:placetype":"postalcode"
},
  "geometry": {"coordinates":[-2.89162383887732,53.27719146699058],"type":"Point"}
}