{
  "type": "Feature",
  "properties": {
    "iso:country": "GB",
    "wof:name": "CH65 5BQ",
    "wof:placetype": "postalcode"
  },
  "geometry": {"coordinates":[-2.891624,53.277191],"type":"Point"}
}
