{
  "type": "Feature",
  "properties": {
    "iso:country": "GB",
    "wof:name": "GL50 2XQ",
    "wof:placetype": "postalcode"
  },
  "geometry": {"coordinates":[-2.079222,51.892754],"type":"Point"}
}
