{
  "type": "Feature",
  "properties": {
    "iso:country":"GB",
    "wof:name":"W1T 6HD",
    "wof:placetype":"postalcode"
},
  "geometry": {"coordinates":[-0.13908462654899,51.52212862400066],"type":"Point"}
}