{
  "type": "Feature",
  "properties": {
    "date:inception_lower":"2000-12-01",
    "date:inception_upper":"2000-12-31",
    "iso:country":"GB",
    "wof:name":"W1T 6HD",
    "wof:placetype":"postalcode"
},
  "geometry": {"coordinates":[-0.139085,51.522129],"type":"Point"}
}