{
  "type": "Feature",
  "properties": {
    "date:inception_lower": "1980-01-01",
    "date:inception_upper": "1980-01-01",
    "iso:country": "GB",
    "wof:name": "LA11 7BD",
    "wof:placetype": "postalcode"
  },
  "geometry": {"coordinates":[-2.929792,54.168022],"type":"Point"}
}
