{
  "type": "Feature",
  "properties": {
    "iso:country": "GB",
    "wof:name": "LA11 7BD",
    "wof:placetype": "postalcode"
  },
  "geometry": {"coordinates":[-2.93081,54.167664],"type":"Point"}
}
