{
  "type": "Feature",
  "properties": {
    "iso:country": "GB",
    "wof:name": "BH16 6BQ",
    "wof:placetype": "postalcode"
  },
  "geometry": {"coordinates":[-2.077761,50.758213],"type":"Point"}
}
