{
  "type": "Feature",
  "properties": {
    "iso:country": "GB",
    "wof:name": "HD3 4UT",
    "wof:placetype": "postalcode"
  },
  "geometry": {"coordinates":[-1.829789,53.644133],"type":"Point"}
}
