{
  "type": "Feature",
  "properties": {
    "date:inception_lower": "1980-01-01",
    "date:inception_upper": "1980-01-01",
    "iso:country": "GB",
    "wof:name": "PL30 3BJ",
    "wof:placetype": "postalcode"
  },
  "geometry": {"coordinates":[-4.766995,50.525853],"type":"Point"}
}
