{
  "type": "Feature",
  "properties": {
    "iso:country":"GB",
    "wof:name":"DN32 0PB",
    "wof:placetype":"postalcode"
},
  "geometry": {"coordinates":[-0.08279479460653,53.56056388439291],"type":"Point"}
}