{
  "type": "Feature",
  "properties": {
    "iso:country":"GB",
    "wof:name":"WD3 5ES",
    "wof:placetype":"postalcode"
},
  "geometry": {"coordinates":[-0.50453885796895,51.65043052627708],"type":"Point"}
}