{
  "type": "Feature",
  "properties": {
    "iso:country":"GB",
    "wof:name":"BN16 4FN",
    "wof:placetype":"postalcode"
},
  "geometry": {"coordinates":[-0.48120661804028,50.82346397469434],"type":"Point"}
}