{
  "type": "Feature",
  "properties": {
    "iso:country":"GB",
    "wof:name":"LL41 3BW",
    "wof:placetype":"postalcode"
},
  "geometry": {"coordinates":[-3.93417485428659,52.99567065290624],"type":"Point"}
}