{
  "type": "Feature",
  "properties": {
    "iso:country":"GB",
    "wof:name":"NP11 7ND",
    "wof:placetype":"postalcode"
},
  "geometry": {"coordinates":[-3.13004616188943,51.636796149713],"type":"Point"}
}