{
  "type": "Feature",
  "properties": {
    "iso:country": "GB",
    "wof:name": "TD12 4AQ",
    "wof:placetype": "postalcode"
  },
  "geometry": {"coordinates":[-2.250564,55.651908],"type":"Point"}
}
