{
  "type": "Feature",
  "properties": {
    "date:inception_lower":"1980-01-01",
    "date:inception_upper":"1980-01-31",
    "iso:country":"GB",
    "wof:name":"TD12 4AQ",
    "wof:placetype":"postalcode"
},
  "geometry": {"coordinates":[-2.250564,55.651908],"type":"Point"}
}