{
  "type": "Feature",
  "properties": {
    "date:inception_lower": "2018-10-01",
    "date:inception_upper": "2018-10-01",
    "iso:country": "GB",
    "wof:name": "KY11 1FE",
    "wof:placetype": "postalcode"
  },
  "geometry": {"coordinates":[-3.388601,56.032195],"type":"Point"}
}
