{
  "type": "Feature",
  "properties": {
    "iso:country": "GB",
    "wof:name": "KY11 1FE",
    "wof:placetype": "postalcode"
  },
  "geometry": {"coordinates":[-3.388659,56.032464],"type":"Point"}
}
