{
  "type": "Feature",
  "properties": {
    "iso:country":"GB",
    "wof:name":"DT2 7EL",
    "wof:placetype":"postalcode"
},
  "geometry": {"coordinates":[-2.29861108011678,50.75019504066083],"type":"Point"}
}