{
  "type": "Feature",
  "properties": {
    "iso:country": "GB",
    "wof:name": "EX32 0FG",
    "wof:placetype": "postalcode"
  },
  "geometry": {"coordinates":[-4.003711,51.065376],"type":"Point"}
}
