{
  "type": "Feature",
  "properties": {
    "iso:country":"GB",
    "wof:name":"AB51 5HB",
    "wof:placetype":"postalcode"
},
  "geometry": {"coordinates":[-2.44801182138986,57.30280256009623],"type":"Point"}
}