{
  "type": "Feature",
  "properties": {
    "iso:country":"GB",
    "wof:name":"LL57 2HG",
    "wof:placetype":"postalcode"
},
  "geometry": {"coordinates":[-4.13715294513799,53.22829080557663],"type":"Point"}
}