{
  "type": "Feature",
  "properties": {
    "iso:country": "GB",
    "wof:name": "LL57 2HG",
    "wof:placetype": "postalcode"
  },
  "geometry": {"coordinates":[-4.136504,53.22867],"type":"Point"}
}
