{
  "type": "Feature",
  "properties": {
    "iso:country":"GB",
    "wof:name":"FY7 7DB",
    "wof:placetype":"postalcode"
},
  "geometry": {"coordinates":[-3.02634135867331,53.91901438334919],"type":"Point"}
}