{
  "type": "Feature",
  "properties": {
    "iso:country":"GB",
    "wof:name":"DY13 8LR",
    "wof:placetype":"postalcode"
},
  "geometry": {"coordinates":[-2.29300581295764,52.35743256208158],"type":"Point"}
}