{
  "type": "Feature",
  "properties": {
    "iso:country": "GB",
    "wof:name": "CH62 7BH",
    "wof:placetype": "postalcode"
  },
  "geometry": {"coordinates":[-2.9882,53.328935],"type":"Point"}
}
