{
  "type": "Feature",
  "properties": {
    "iso:country":"GB",
    "wof:name":"B45 8HS",
    "wof:placetype":"postalcode"
},
  "geometry": {"coordinates":[-2.01155944196103,52.37244976909193],"type":"Point"}
}