{
  "type": "Feature",
  "properties": {
    "iso:country":"GB",
    "wof:name":"NR24 2DE",
    "wof:placetype":"postalcode"
},
  "geometry": {"coordinates":[1.03693454633696,52.85591512848663],"type":"Point"}
}