{
  "type": "Feature",
  "properties": {
    "iso:country":"GB",
    "wof:name":"E6 5QJ",
    "wof:placetype":"postalcode"
},
  "geometry": {"coordinates":[0.05159733760363,51.51122352133438],"type":"Point"}
}