{
  "type": "Feature",
  "properties": {
    "iso:country":"GB",
    "wof:name":"KY14 7EY",
    "wof:placetype":"postalcode"
},
  "geometry": {"coordinates":[-3.21406539664322,56.27731643307162],"type":"Point"}
}