{
  "type": "Feature",
  "properties": {
    "iso:country": "GB",
    "wof:name": "KY14 7EY",
    "wof:placetype": "postalcode"
  },
  "geometry": {"coordinates":[-3.214065,56.277316],"type":"Point"}
}
