{
  "type": "Feature",
  "properties": {
    "iso:country":"GB",
    "wof:name":"EH9 3AR",
    "wof:placetype":"postalcode"
},
  "geometry": {"coordinates":[-3.1736441670949,55.92560169505747],"type":"Point"}
}