{
  "type": "Feature",
  "properties": {
    "date:inception_lower":"1980-01-01",
    "date:inception_upper":"1980-01-31",
    "iso:country":"GB",
    "wof:name":"EH9 3AR",
    "wof:placetype":"postalcode"
},
  "geometry": {"coordinates":[-3.173644,55.925602],"type":"Point"}
}