{
  "type": "Feature",
  "properties": {
    "iso:country":"GB",
    "wof:name":"BD24 9EX",
    "wof:placetype":"postalcode"
},
  "geometry": {"coordinates":[-2.2758776815523,54.06802026203228],"type":"Point"}
}