{
  "type": "Feature",
  "properties": {
    "iso:country":"GB",
    "wof:name":"YO8 9FX",
    "wof:placetype":"postalcode"
},
  "geometry": {"coordinates":[-1.13074414887996,53.77260025817852],"type":"Point"}
}