{
  "type": "Feature",
  "properties": {
    "date:inception_lower": "2013-12-01",
    "date:inception_upper": "2013-12-01",
    "iso:country": "GB",
    "wof:name": "YO8 9FX",
    "wof:placetype": "postalcode"
  },
  "geometry": {"coordinates":[-1.130773,53.772681],"type":"Point"}
}
