{
  "type": "Feature",
  "properties": {
    "iso:country":"GB",
    "wof:name":"SO31 6PZ",
    "wof:placetype":"postalcode"
},
  "geometry": {"coordinates":[-1.28278429448766,50.86057591770722],"type":"Point"}
}