{
  "type": "Feature",
  "properties": {
    "iso:country":"GB",
    "wof:name":"SE22 9EQ",
    "wof:placetype":"postalcode"
},
  "geometry": {"coordinates":[-0.07416475707959,51.45227814664258],"type":"Point"}
}