{
  "type": "Feature",
  "properties": {
    "iso:country":"GB",
    "wof:name":"SA11 5ED",
    "wof:placetype":"postalcode"
},
  "geometry": {"coordinates":[-3.62740758511163,51.74788649821873],"type":"Point"}
}