{
  "type": "Feature",
  "properties": {
    "iso:country":"GB",
    "wof:name":"DL14 6HL",
    "wof:placetype":"postalcode"
},
  "geometry": {"coordinates":[-1.67648945445965,54.65340705656949],"type":"Point"}
}