{
  "type": "Feature",
  "properties": {
    "iso:country": "GB",
    "wof:name": "DL14 6HL",
    "wof:placetype": "postalcode"
  },
  "geometry": {"coordinates":[-1.676489,54.653407],"type":"Point"}
}
