{
  "type": "Feature",
  "properties": {
    "iso:country": "GB",
    "wof:name": "SS13 1TB",
    "wof:placetype": "postalcode"
  },
  "geometry": {"coordinates":[0.514384,51.583306],"type":"Point"}
}
