{
  "type": "Feature",
  "properties": {
    "date:inception_lower":"1988-03-01",
    "date:inception_upper":"1988-03-31",
    "iso:country":"GB",
    "wof:name":"SS13 1TB",
    "wof:placetype":"postalcode"
},
  "geometry": {"coordinates":[0.514384,51.583306],"type":"Point"}
}