{
  "type": "Feature",
  "properties": {
    "date:inception_lower":"2011-10-01",
    "date:inception_upper":"2011-10-31",
    "iso:country":"GB",
    "wof:name":"WF10 3UD",
    "wof:placetype":"postalcode"
},
  "geometry": {"coordinates":[-1.315568,53.715608],"type":"Point"}
}