{
  "type": "Feature",
  "properties": {
    "iso:country":"GB",
    "wof:name":"WF10 3UD",
    "wof:placetype":"postalcode"
},
  "geometry": {"coordinates":[-1.31556778188504,53.71560761877804],"type":"Point"}
}