{
  "type": "Feature",
  "properties": {
    "iso:country": "GB",
    "wof:name": "WF10 3UD",
    "wof:placetype": "postalcode"
  },
  "geometry": {"coordinates":[-1.315568,53.715608],"type":"Point"}
}
