{
  "type": "Feature",
  "properties": {
    "iso:country":"GB",
    "wof:name":"ME8 7AA",
    "wof:placetype":"postalcode"
},
  "geometry": {"coordinates":[0.58963590638579,51.36797330086233],"type":"Point"}
}