{
  "type": "Feature",
  "properties": {
    "iso:country":"GB",
    "wof:name":"B63 4QY",
    "wof:placetype":"postalcode"
},
  "geometry": {"coordinates":[-2.05385981231646,52.44291112353039],"type":"Point"}
}