{
  "type": "Feature",
  "properties": {
    "date:inception_lower": "1993-01-01",
    "date:inception_upper": "1993-01-01",
    "iso:country": "GB",
    "wof:name": "SN10 1HN",
    "wof:placetype": "postalcode"
  },
  "geometry": {"coordinates":[-1.995011,51.35298],"type":"Point"}
}
