{
  "type": "Feature",
  "properties": {
    "iso:country":"GB",
    "wof:name":"TR2 4LQ",
    "wof:placetype":"postalcode"
},
  "geometry": {"coordinates":[-4.95558352226535,50.29273091537135],"type":"Point"}
}