{
  "type": "Feature",
  "properties": {
    "iso:country": "GB",
    "wof:name": "TR2 4LQ",
    "wof:placetype": "postalcode"
  },
  "geometry": {"coordinates":[-4.955583,50.292731],"type":"Point"}
}
