{
  "type": "Feature",
  "properties": {
    "iso:country":"GB",
    "wof:name":"EH32 0EW",
    "wof:placetype":"postalcode"
},
  "geometry": {"coordinates":[-2.94414215815957,55.96998508655361],"type":"Point"}
}