{
  "type": "Feature",
  "properties": {
    "iso:country": "GB",
    "wof:name": "EH32 0EW",
    "wof:placetype": "postalcode"
  },
  "geometry": {"coordinates":[-2.944142,55.969985],"type":"Point"}
}
