{
  "type": "Feature",
  "properties": {
    "iso:country":"GB",
    "wof:name":"CT9 1QQ",
    "wof:placetype":"postalcode"
},
  "geometry": {"coordinates":[1.38673497680586,51.38966133710858],"type":"Point"}
}