{
  "type": "Feature",
  "properties": {
    "iso:country":"GB",
    "wof:name":"RM14 3RP",
    "wof:placetype":"postalcode"
},
  "geometry": {"coordinates":[0.34826783298645,51.54843813932003],"type":"Point"}
}