{
  "type": "Feature",
  "properties": {
    "date:inception_lower":"2013-10-01",
    "date:inception_upper":"2013-10-31",
    "iso:country":"GB",
    "wof:name":"PA20 0LU",
    "wof:placetype":"postalcode"
},
  "geometry": {"coordinates":[-5.085574,55.860079],"type":"Point"}
}