{
  "type": "Feature",
  "properties": {
    "iso:country":"GB",
    "wof:name":"PA20 0LU",
    "wof:placetype":"postalcode"
},
  "geometry": {"coordinates":[-5.08557422257594,55.86007892600136],"type":"Point"}
}