{
  "type": "Feature",
  "properties": {
    "iso:country": "GB",
    "wof:name": "PA20 0LU",
    "wof:placetype": "postalcode"
  },
  "geometry": {"coordinates":[-5.085574,55.860079],"type":"Point"}
}
