{
  "type": "Feature",
  "properties": {
    "iso:country":"GB",
    "wof:name":"EX4 7AP",
    "wof:placetype":"postalcode"
},
  "geometry": {"coordinates":[-3.51227864187829,50.73264736477735],"type":"Point"}
}