{
  "type": "Feature",
  "properties": {
    "date:inception_lower": "2005-05-01",
    "date:inception_upper": "2005-05-01",
    "iso:country": "GB",
    "wof:name": "NR11 7AZ",
    "wof:placetype": "postalcode"
  },
  "geometry": {"coordinates":[1.255995,52.838919],"type":"Point"}
}
