{
  "type": "Feature",
  "properties": {
    "iso:country":"GB",
    "wof:name":"NR11 7AZ",
    "wof:placetype":"postalcode"
},
  "geometry": {"coordinates":[1.255988913977,52.83888164680076],"type":"Point"}
}