{
  "type": "Feature",
  "properties": {
    "iso:country": "GB",
    "wof:name": "NR11 7AZ",
    "wof:placetype": "postalcode"
  },
  "geometry": {"coordinates":[1.255995,52.838919],"type":"Point"}
}
