{
  "type": "Feature",
  "properties": {
    "date:inception_lower":"1990-08-01",
    "date:inception_upper":"1990-08-31",
    "iso:country":"GB",
    "wof:name":"AB41 8XR",
    "wof:placetype":"postalcode"
},
  "geometry": {"coordinates":[-2.108242,57.465641],"type":"Point"}
}