{
  "type": "Feature",
  "properties": {
    "date:inception_lower":"1995-07-01",
    "date:inception_upper":"1995-07-31",
    "iso:country":"GB",
    "wof:name":"TS10 3DB",
    "wof:placetype":"postalcode"
},
  "geometry": {"coordinates":[-1.061064,54.617632],"type":"Point"}
}