{
  "type": "Feature",
  "properties": {
    "iso:country": "GB",
    "wof:name": "TS10 3DB",
    "wof:placetype": "postalcode"
  },
  "geometry": {"coordinates":[-1.061064,54.617632],"type":"Point"}
}
