{
  "type": "Feature",
  "properties": {
    "iso:country":"GB",
    "wof:name":"TS10 3DB",
    "wof:placetype":"postalcode"
},
  "geometry": {"coordinates":[-1.0610638960157,54.61763231591947],"type":"Point"}
}