{
  "type": "Feature",
  "properties": {
    "iso:country":"GB",
    "wof:name":"GU2 9NG",
    "wof:placetype":"postalcode"
},
  "geometry": {"coordinates":[-0.58670483035163,51.25127952318783],"type":"Point"}
}