{
  "type": "Feature",
  "properties": {
    "iso:country": "GB",
    "wof:name": "L36 5UX",
    "wof:placetype": "postalcode"
  },
  "geometry": {"coordinates":[-2.838312,53.406713],"type":"Point"}
}
