{
  "type": "Feature",
  "properties": {
    "date:inception_lower": "1980-01-01",
    "date:inception_upper": "1980-01-01",
    "iso:country": "GB",
    "wof:name": "BA12 9DD",
    "wof:placetype": "postalcode"
  },
  "geometry": {"coordinates":[-2.173742,51.204472],"type":"Point"}
}
