{
  "type": "Feature",
  "properties": {
    "iso:country":"GB",
    "wof:name":"HP9 1UT",
    "wof:placetype":"postalcode"
},
  "geometry": {"coordinates":[-0.63955759631763,51.60611484387701],"type":"Point"}
}