{
  "type": "Feature",
  "properties": {
    "iso:country": "GB",
    "wof:name": "HP9 1UT",
    "wof:placetype": "postalcode"
  },
  "geometry": {"coordinates":[-0.639558,51.606115],"type":"Point"}
}
