{
  "type": "Feature",
  "properties": {
    "iso:country":"GB",
    "wof:name":"YO42 1QE",
    "wof:placetype":"postalcode"
},
  "geometry": {"coordinates":[-0.70211078704,53.90183010750207],"type":"Point"}
}