{
  "type": "Feature",
  "properties": {
    "iso:country": "GB",
    "wof:name": "YO42 1QE",
    "wof:placetype": "postalcode"
  },
  "geometry": {"coordinates":[-0.702118,53.901849],"type":"Point"}
}
