{
  "type": "Feature",
  "properties": {
    "date:inception_lower": "2005-10-01",
    "date:inception_upper": "2005-10-01",
    "iso:country": "GB",
    "wof:name": "YO42 1QE",
    "wof:placetype": "postalcode"
  },
  "geometry": {"coordinates":[-0.702118,53.901849],"type":"Point"}
}
