{
  "type": "Feature",
  "properties": {
    "date:inception_lower": "2018-06-01",
    "date:inception_upper": "2018-06-01",
    "iso:country": "GB",
    "wof:name": "SW8 2FN",
    "wof:placetype": "postalcode"
  },
  "geometry": {"coordinates":[-0.129452,51.481124],"type":"Point"}
}
