{
  "type": "Feature",
  "properties": {
    "date:inception_lower": "1980-01-01",
    "date:inception_upper": "1980-01-01",
    "iso:country": "GB",
    "wof:name": "CA2 7LN",
    "wof:placetype": "postalcode"
  },
  "geometry": {"coordinates":[-2.964403,54.895178],"type":"Point"}
}
