{
  "type": "Feature",
  "properties": {
    "iso:country": "GB",
    "wof:name": "SO51 8BZ",
    "wof:placetype": "postalcode"
  },
  "geometry": {"coordinates":[-1.494113,50.988503],"type":"Point"}
}
