{
  "type": "Feature",
  "properties": {
    "iso:country":"GB",
    "wof:name":"DT3 5EY",
    "wof:placetype":"postalcode"
},
  "geometry": {"coordinates":[-2.46423997551033,50.62933860358334],"type":"Point"}
}