{
  "type": "Feature",
  "properties": {
    "date:inception_lower": "1984-02-01",
    "date:inception_upper": "1984-02-01",
    "iso:country": "GB",
    "wof:name": "DT3 5EY",
    "wof:placetype": "postalcode"
  },
  "geometry": {"coordinates":[-2.464251,50.629346],"type":"Point"}
}
