{
  "type": "Feature",
  "properties": {
    "date:inception_lower":"1999-06-01",
    "date:inception_upper":"1999-06-30",
    "iso:country":"GB",
    "wof:name":"CF15 9TR",
    "wof:placetype":"postalcode"
},
  "geometry": {"coordinates":[-3.267428,51.539459],"type":"Point"}
}