{
  "type": "Feature",
  "properties": {
    "iso:country":"GB",
    "wof:name":"CF15 9TR",
    "wof:placetype":"postalcode"
},
  "geometry": {"coordinates":[-3.26742834547633,51.5394594300473],"type":"Point"}
}