{
  "type": "Feature",
  "properties": {
    "iso:country":"GB",
    "wof:name":"CO16 0ER",
    "wof:placetype":"postalcode"
},
  "geometry": {"coordinates":[1.16123124358309,51.8595117251657],"type":"Point"}
}