{
  "type": "Feature",
  "properties": {
    "iso:country": "GB",
    "wof:name": "NE46 2RF",
    "wof:placetype": "postalcode"
  },
  "geometry": {"coordinates":[-2.123255,54.962514],"type":"Point"}
}
