{
  "type": "Feature",
  "properties": {
    "iso:country": "GB",
    "wof:name": "YO12 5DX",
    "wof:placetype": "postalcode"
  },
  "geometry": {"coordinates":[-0.434748,54.279811],"type":"Point"}
}
