{
  "type": "Feature",
  "properties": {
    "date:inception_lower":"1983-01-01",
    "date:inception_upper":"1983-01-31",
    "iso:country":"GB",
    "wof:name":"YO12 5DX",
    "wof:placetype":"postalcode"
},
  "geometry": {"coordinates":[-0.434748,54.279811],"type":"Point"}
}