{
  "type": "Feature",
  "properties": {
    "iso:country":"GB",
    "wof:name":"YO12 5DX",
    "wof:placetype":"postalcode"
},
  "geometry": {"coordinates":[-0.43474841470898,54.27981126927529],"type":"Point"}
}