{
  "type": "Feature",
  "properties": {
    "iso:country":"GB",
    "wof:name":"M41 9LH",
    "wof:placetype":"postalcode"
},
  "geometry": {"coordinates":[-2.34262032108074,53.44590136803068],"type":"Point"}
}