{
  "type": "Feature",
  "properties": {
    "iso:country":"GB",
    "wof:name":"NR19 1HN",
    "wof:placetype":"postalcode"
},
  "geometry": {"coordinates":[0.95732253433778,52.66988820637965],"type":"Point"}
}