{
  "type": "Feature",
  "properties": {
    "iso:country":"GB",
    "wof:name":"SS6 9EA",
    "wof:placetype":"postalcode"
},
  "geometry": {"coordinates":[0.58682540548324,51.59478961896137],"type":"Point"}
}