{
  "type": "Feature",
  "properties": {
    "iso:country": "GB",
    "wof:name": "CB7 5ZN",
    "wof:placetype": "postalcode"
  },
  "geometry": {"coordinates":[0.334769,52.339316],"type":"Point"}
}
