{
  "type": "Feature",
  "properties": {
    "iso:country":"GB",
    "wof:name":"WR15 8DR",
    "wof:placetype":"postalcode"
},
  "geometry": {"coordinates":[-2.59355368614405,52.30207499521536],"type":"Point"}
}