{
  "type": "Feature",
  "properties": {
    "iso:country":"GB",
    "wof:name":"N16 0PR",
    "wof:placetype":"postalcode"
},
  "geometry": {"coordinates":[-0.08242763418533,51.5627615728364],"type":"Point"}
}