{
  "type": "Feature",
  "properties": {
    "iso:country":"GB",
    "wof:name":"W1F 8PX",
    "wof:placetype":"postalcode"
},
  "geometry": {"coordinates":[-0.13659285357533,51.51431054938129],"type":"Point"}
}