{
  "type": "Feature",
  "properties": {
    "iso:country":"GB",
    "wof:name":"WV13 1PT",
    "wof:placetype":"postalcode"
},
  "geometry": {"coordinates":[-2.05369415266085,52.58414264744484],"type":"Point"}
}