{
  "type": "Feature",
  "properties": {
    "date:inception_lower": "1980-01-01",
    "date:inception_upper": "1980-01-01",
    "iso:country": "GB",
    "wof:name": "WV13 1PT",
    "wof:placetype": "postalcode"
  },
  "geometry": {"coordinates":[-2.053689,52.584158],"type":"Point"}
}
