{
  "type": "Feature",
  "properties": {
    "iso:country":"GB",
    "wof:name":"RH2 0RE",
    "wof:placetype":"postalcode"
},
  "geometry": {"coordinates":[-0.1884574898255,51.23671981097642],"type":"Point"}
}