{
  "type": "Feature",
  "properties": {
    "date:inception_lower": "1980-01-01",
    "date:inception_upper": "1980-01-01",
    "iso:country": "GB",
    "wof:name": "TA3 5AX",
    "wof:placetype": "postalcode"
  },
  "geometry": {"coordinates":[-3.064892,50.980029],"type":"Point"}
}
