{
  "type": "Feature",
  "properties": {
    "iso:country":"GB",
    "wof:name":"WD6 3PZ",
    "wof:placetype":"postalcode"
},
  "geometry": {"coordinates":[-0.28327972401495,51.64685592499283],"type":"Point"}
}