{
  "type": "Feature",
  "properties": {
    "date:inception_lower": "2021-12-01",
    "date:inception_upper": "2021-12-01",
    "iso:country": "GB",
    "wof:name": "CM1 4GD",
    "wof:placetype": "postalcode"
  },
  "geometry": {"coordinates":[0.452282,51.757907],"type":"Point"}
}
