{
  "type": "Feature",
  "properties": {
    "date:inception_lower": "2022-10-01",
    "date:inception_upper": "2022-10-01",
    "iso:country": "GB",
    "wof:name": "HD9 7FH",
    "wof:placetype": "postalcode"
  },
  "geometry": {"coordinates":[-1.777988,53.579537],"type":"Point"}
}
