{
  "type": "Feature",
  "properties": {
    "date:inception_lower": "2019-07-01",
    "date:inception_upper": "2019-07-01",
    "iso:country": "GB",
    "wof:name": "RG2 9UA",
    "wof:placetype": "postalcode"
  },
  "geometry": {"coordinates":[-0.904852,51.379472],"type":"Point"}
}
