{
  "type": "Feature",
  "properties": {
    "iso:country": "GB",
    "wof:name": "RG2 9UA",
    "wof:placetype": "postalcode"
  },
  "geometry": {"coordinates":[-0.903607,51.379272],"type":"Point"}
}
