{
  "type": "Feature",
  "properties": {
    "iso:country": "GB",
    "wof:name": "RG2 9UA",
    "wof:placetype": "postalcode"
  },
  "geometry": {"coordinates":[-0.903564,51.379271],"type":"Point"}
}
