{
  "type": "Feature",
  "properties": {
    "date:inception_lower": "2000-12-01",
    "date:inception_upper": "2000-12-01",
    "iso:country": "GB",
    "wof:name": "W1T 4JB",
    "wof:placetype": "postalcode"
  },
  "geometry": {"coordinates":[-0.137492,51.519561],"type":"Point"}
}
