{
  "type": "Feature",
  "properties": {
    "iso:country": "GB",
    "wof:name": "HX5 0QF",
    "wof:placetype": "postalcode"
  },
  "geometry": {"coordinates":[-1.849638,53.681685],"type":"Point"}
}
