{
  "type": "Feature",
  "properties": {
    "iso:country":"GB",
    "wof:name":"HX5 0QF",
    "wof:placetype":"postalcode"
},
  "geometry": {"coordinates":[-1.84963810175718,53.68168517489116],"type":"Point"}
}