{
  "type": "Feature",
  "properties": {
    "iso:country":"GB",
    "wof:name":"G69 8AL",
    "wof:placetype":"postalcode"
},
  "geometry": {"coordinates":[-4.08210539435809,55.88963224008391],"type":"Point"}
}