{
  "type": "Feature",
  "properties": {
    "iso:country": "GB",
    "wof:name": "S45 8EW",
    "wof:placetype": "postalcode"
  },
  "geometry": {"coordinates":[-1.370227,53.158091],"type":"Point"}
}
