{
  "type": "Feature",
  "properties": {
    "date:inception_lower": "1981-06-01",
    "date:inception_upper": "1981-06-01",
    "iso:country": "GB",
    "wof:name": "S45 8EW",
    "wof:placetype": "postalcode"
  },
  "geometry": {"coordinates":[-1.370227,53.158091],"type":"Point"}
}
