{
  "type": "Feature",
  "properties": {
    "date:inception_lower": "2023-09-01",
    "date:inception_upper": "2023-09-01",
    "iso:country": "GB",
    "wof:name": "CF14 4BB",
    "wof:placetype": "postalcode"
  },
  "geometry": {"coordinates":[-3.199455,51.510583],"type":"Point"}
}
