{
  "type": "Feature",
  "properties": {
    "iso:country":"GB",
    "wof:name":"TA3 6ER",
    "wof:placetype":"postalcode"
},
  "geometry": {"coordinates":[-2.9216405428481,51.04674846254579],"type":"Point"}
}