{
  "type": "Feature",
  "properties": {
    "iso:country": "GB",
    "wof:name": "TA3 6ER",
    "wof:placetype": "postalcode"
  },
  "geometry": {"coordinates":[-2.921641,51.046748],"type":"Point"}
}
