{
  "type": "Feature",
  "properties": {
    "iso:country":"GB",
    "wof:name":"RG12 7PD",
    "wof:placetype":"postalcode"
},
  "geometry": {"coordinates":[-0.76658253618328,51.39292560589413],"type":"Point"}
}