{
  "type": "Feature",
  "properties": {
    "date:inception_lower": "1998-12-01",
    "date:inception_upper": "1998-12-01",
    "iso:country": "GB",
    "wof:name": "CO10 8NR",
    "wof:placetype": "postalcode"
  },
  "geometry": {"coordinates":[0.634768,52.089993],"type":"Point"}
}
