{
  "type": "Feature",
  "properties": {
    "iso:country":"GB",
    "wof:name":"CO10 8NR",
    "wof:placetype":"postalcode"
},
  "geometry": {"coordinates":[0.63476838910803,52.08999344835552],"type":"Point"}
}