{
  "type": "Feature",
  "properties": {
    "iso:country":"GB",
    "wof:name":"W1T 2PT",
    "wof:placetype":"postalcode"
},
  "geometry": {"coordinates":[-0.13515791746139,51.51944944279388],"type":"Point"}
}