{
  "type": "Feature",
  "properties": {
    "iso:country":"GB",
    "wof:name":"CH43 0TG",
    "wof:placetype":"postalcode"
},
  "geometry": {"coordinates":[-3.05694786111573,53.36807763966173],"type":"Point"}
}