{
  "type": "Feature",
  "properties": {
    "date:inception_lower": "1999-06-01",
    "date:inception_upper": "1999-06-01",
    "iso:country": "GB",
    "wof:name": "CH43 0TG",
    "wof:placetype": "postalcode"
  },
  "geometry": {"coordinates":[-3.056948,53.368078],"type":"Point"}
}
