{
  "type": "Feature",
  "properties": {
    "iso:country":"GB",
    "wof:name":"YO11 3BL",
    "wof:placetype":"postalcode"
},
  "geometry": {"coordinates":[-0.39190416186793,54.26533355385966],"type":"Point"}
}