{
  "type": "Feature",
  "properties": {
    "iso:country":"GB",
    "wof:name":"EH39 5NU",
    "wof:placetype":"postalcode"
},
  "geometry": {"coordinates":[-2.69820211089076,56.0388850417513],"type":"Point"}
}