{
  "type": "Feature",
  "properties": {
    "date:inception_lower":"1980-01-01",
    "date:inception_upper":"1980-01-31",
    "iso:country":"GB",
    "wof:name":"EH39 5NU",
    "wof:placetype":"postalcode"
},
  "geometry": {"coordinates":[-2.69754,56.039217],"type":"Point"}
}