{
  "type": "Feature",
  "properties": {
    "iso:country": "GB",
    "wof:name": "EH39 5NU",
    "wof:placetype": "postalcode"
  },
  "geometry": {"coordinates":[-2.69754,56.039217],"type":"Point"}
}
