{
  "type": "Feature",
  "properties": {
    "date:inception_lower": "1980-01-01",
    "date:inception_upper": "1980-01-01",
    "iso:country": "GB",
    "wof:name": "CW5 6DG",
    "wof:placetype": "postalcode"
  },
  "geometry": {"coordinates":[-2.52895,53.083653],"type":"Point"}
}
