{
  "type": "Feature",
  "properties": {
    "iso:country":"GB",
    "wof:name":"CW5 6DG",
    "wof:placetype":"postalcode"
},
  "geometry": {"coordinates":[-2.52894973397663,53.08365293556876],"type":"Point"}
}