{
  "type": "Feature",
  "properties": {
    "iso:country":"GB",
    "wof:name":"KY11 8BQ",
    "wof:placetype":"postalcode"
},
  "geometry": {"coordinates":[-3.43527626622499,56.05695167945606],"type":"Point"}
}