{
  "type": "Feature",
  "properties": {
    "date:inception_lower": "2014-03-01",
    "date:inception_upper": "2014-03-01",
    "iso:country": "GB",
    "wof:name": "PL25 4FY",
    "wof:placetype": "postalcode"
  },
  "geometry": {"coordinates":[-4.781024,50.347685],"type":"Point"}
}
