{
  "type": "Feature",
  "properties": {
    "date:inception_lower": "1980-01-01",
    "date:inception_upper": "1980-01-01",
    "iso:country": "GB",
    "wof:name": "SA33 6EP",
    "wof:placetype": "postalcode"
  },
  "geometry": {"coordinates":[-4.379468,51.905051],"type":"Point"}
}
