{
  "type": "Feature",
  "properties": {
    "iso:country":"GB",
    "wof:name":"SW19 1TB",
    "wof:placetype":"postalcode"
},
  "geometry": {"coordinates":[-0.19616403379416,51.4170706047403],"type":"Point"}
}