{
  "type": "Feature",
  "properties": {
    "date:inception_lower": "1980-01-01",
    "date:inception_upper": "1980-01-01",
    "iso:country": "GB",
    "wof:name": "WS9 9EE",
    "wof:placetype": "postalcode"
  },
  "geometry": {"coordinates":[-1.891884,52.632747],"type":"Point"}
}
