{
  "type": "Feature",
  "properties": {
    "iso:country":"GB",
    "wof:name":"WS9 9EE",
    "wof:placetype":"postalcode"
},
  "geometry": {"coordinates":[-1.89189030758158,52.6327314793327],"type":"Point"}
}