{
  "type": "Feature",
  "properties": {
    "iso:country": "GB",
    "wof:name": "WS9 9EE",
    "wof:placetype": "postalcode"
  },
  "geometry": {"coordinates":[-1.891757,52.632758],"type":"Point"}
}
