{
  "type": "Feature",
  "properties": {
    "date:inception_lower":"1997-06-01",
    "date:inception_upper":"1997-06-30",
    "iso:country":"GB",
    "wof:name":"S66 3YR",
    "wof:placetype":"postalcode"
},
  "geometry": {"coordinates":[-1.264951,53.427747],"type":"Point"}
}