{
  "type": "Feature",
  "properties": {
    "date:inception_lower":"1980-01-01",
    "date:inception_upper":"1980-01-31",
    "iso:country":"GB",
    "wof:name":"PO16 0RG",
    "wof:placetype":"postalcode"
},
  "geometry": {"coordinates":[-1.179295,50.846486],"type":"Point"}
}