{
  "type": "Feature",
  "properties": {
    "date:inception_lower": "1980-01-01",
    "date:inception_upper": "1980-01-01",
    "iso:country": "GB",
    "wof:name": "SL5 8DW",
    "wof:placetype": "postalcode"
  },
  "geometry": {"coordinates":[-0.703063,51.411375],"type":"Point"}
}
