{
  "type": "Feature",
  "properties": {
    "iso:country": "GB",
    "wof:name": "LE16 8TX",
    "wof:placetype": "postalcode"
  },
  "geometry": {"coordinates":[-0.788845,52.486496],"type":"Point"}
}
