{
  "type": "Feature",
  "properties": {
    "date:inception_lower":"2012-03-01",
    "date:inception_upper":"2012-03-31",
    "iso:country":"GB",
    "wof:name":"LE16 8TX",
    "wof:placetype":"postalcode"
},
  "geometry": {"coordinates":[-0.788845,52.486496],"type":"Point"}
}