{
  "type": "Feature",
  "properties": {
    "iso:country":"GB",
    "wof:name":"OL9 6RQ",
    "wof:placetype":"postalcode"
},
  "geometry": {"coordinates":[-2.13308339011016,53.55077335210989],"type":"Point"}
}