{
  "type": "Feature",
  "properties": {
    "iso:country":"GB",
    "wof:name":"SP3 6NT",
    "wof:placetype":"postalcode"
},
  "geometry": {"coordinates":[-2.09823854133766,51.06143015131799],"type":"Point"}
}