{
  "type": "Feature",
  "properties": {
    "iso:country":"GB",
    "wof:name":"CH6 6LY",
    "wof:placetype":"postalcode"
},
  "geometry": {"coordinates":[-3.18905894949421,53.27641170310955],"type":"Point"}
}