{
  "type": "Feature",
  "properties": {
    "date:inception_lower":"1993-01-01",
    "date:inception_upper":"1993-01-31",
    "iso:country":"GB",
    "wof:name":"CH6 6LY",
    "wof:placetype":"postalcode"
},
  "geometry": {"coordinates":[-3.189059,53.276412],"type":"Point"}
}