{
  "type": "Feature",
  "properties": {
    "iso:country":"GB",
    "wof:name":"GU14 0AB",
    "wof:placetype":"postalcode"
},
  "geometry": {"coordinates":[-0.76721283374994,51.28756204678882],"type":"Point"}
}