{
  "type": "Feature",
  "properties": {
    "iso:country": "GB",
    "wof:name": "LL18 2TZ",
    "wof:placetype": "postalcode"
  },
  "geometry": {"coordinates":[-3.463292,53.292347],"type":"Point"}
}
