{
  "type": "Feature",
  "properties": {
    "date:inception_lower": "1982-03-01",
    "date:inception_upper": "1982-03-01",
    "iso:country": "GB",
    "wof:name": "DL1 2JG",
    "wof:placetype": "postalcode"
  },
  "geometry": {"coordinates":[-1.550318,54.539835],"type":"Point"}
}
