{
  "type": "Feature",
  "properties": {
    "iso:country": "GB",
    "wof:name": "GL52 3HS",
    "wof:placetype": "postalcode"
  },
  "geometry": {"coordinates":[-2.057215,51.910362],"type":"Point"}
}
