{
  "type": "Feature",
  "properties": {
    "iso:country": "GB",
    "wof:name": "B61 7AF",
    "wof:placetype": "postalcode"
  },
  "geometry": {"coordinates":[-2.06317,52.333186],"type":"Point"}
}
