{
  "type": "Feature",
  "properties": {
    "iso:country": "GB",
    "wof:name": "CM0 7TB",
    "wof:placetype": "postalcode"
  },
  "geometry": {"coordinates":[0.882596,51.696145],"type":"Point"}
}
