{
  "type": "Feature",
  "properties": {
    "iso:country":"GB",
    "wof:name":"CM0 7TB",
    "wof:placetype":"postalcode"
},
  "geometry": {"coordinates":[0.88259642154474,51.69614470861355],"type":"Point"}
}