{
  "type": "Feature",
  "properties": {
    "iso:country": "GB",
    "wof:name": "PR3 2JX",
    "wof:placetype": "postalcode"
  },
  "geometry": {"coordinates":[-2.66989,53.833],"type":"Point"}
}
