{
  "type": "Feature",
  "properties": {
    "iso:country":"GB",
    "wof:name":"PR3 2JX",
    "wof:placetype":"postalcode"
},
  "geometry": {"coordinates":[-2.66989049981342,53.83300049975115],"type":"Point"}
}