{
  "type": "Feature",
  "properties": {
    "date:inception_lower":"1980-01-01",
    "date:inception_upper":"1980-01-31",
    "iso:country":"GB",
    "wof:name":"PR3 2JX",
    "wof:placetype":"postalcode"
},
  "geometry": {"coordinates":[-2.66989,53.833],"type":"Point"}
}