{
  "type": "Feature",
  "properties": {
    "iso:country": "GB",
    "wof:name": "M15 4HU",
    "wof:placetype": "postalcode"
  },
  "geometry": {"coordinates":[-2.25961,53.469553],"type":"Point"}
}
