{
  "type": "Feature",
  "properties": {
    "iso:country": "GB",
    "wof:name": "PA31 8BA",
    "wof:placetype": "postalcode"
  },
  "geometry": {"coordinates":[-5.470892,56.061484],"type":"Point"}
}
