{
  "type": "Feature",
  "properties": {
    "iso:country":"GB",
    "wof:name":"PA31 8BA",
    "wof:placetype":"postalcode"
},
  "geometry": {"coordinates":[-5.47090742515327,56.06153015555854],"type":"Point"}
}