{
  "type": "Feature",
  "properties": {
    "date:inception_lower":"2001-06-01",
    "date:inception_upper":"2001-06-30",
    "iso:country":"GB",
    "wof:name":"YO41 5RZ",
    "wof:placetype":"postalcode"
},
  "geometry": {"coordinates":[-0.82492,53.961105],"type":"Point"}
}