{
  "type": "Feature",
  "properties": {
    "iso:country":"GB",
    "wof:name":"YO41 5RZ",
    "wof:placetype":"postalcode"
},
  "geometry": {"coordinates":[-0.82492003841897,53.96110535677409],"type":"Point"}
}