{
  "type": "Feature",
  "properties": {
    "iso:country": "GB",
    "wof:name": "YO41 5RZ",
    "wof:placetype": "postalcode"
  },
  "geometry": {"coordinates":[-0.82492,53.961105],"type":"Point"}
}
