{
  "type": "Feature",
  "properties": {
    "iso:country":"GB",
    "wof:name":"LE2 6LL",
    "wof:placetype":"postalcode"
},
  "geometry": {"coordinates":[-1.13673396339725,52.60399808092362],"type":"Point"}
}