{
  "type": "Feature",
  "properties": {
    "iso:country": "GB",
    "wof:name": "CH60 0BA",
    "wof:placetype": "postalcode"
  },
  "geometry": {"coordinates":[-3.093015,53.325081],"type":"Point"}
}
