{
  "type": "Feature",
  "properties": {
    "date:inception_lower": "1980-01-01",
    "date:inception_upper": "1980-01-01",
    "iso:country": "GB",
    "wof:name": "LA15 8RU",
    "wof:placetype": "postalcode"
  },
  "geometry": {"coordinates":[-3.179174,54.158116],"type":"Point"}
}
