{
  "type": "Feature",
  "properties": {
    "iso:country": "GB",
    "wof:name": "LA15 8RU",
    "wof:placetype": "postalcode"
  },
  "geometry": {"coordinates":[-3.179174,54.158116],"type":"Point"}
}
