{
  "type": "Feature",
  "properties": {
    "iso:country":"GB",
    "wof:name":"LS19 7ER",
    "wof:placetype":"postalcode"
},
  "geometry": {"coordinates":[-1.68881432025985,53.8653876523943],"type":"Point"}
}