{
  "type": "Feature",
  "properties": {
    "date:inception_lower":"1980-01-01",
    "date:inception_upper":"1980-01-31",
    "iso:country":"GB",
    "wof:name":"LS19 7ER",
    "wof:placetype":"postalcode"
},
  "geometry": {"coordinates":[-1.688577,53.865177],"type":"Point"}
}