{
  "type": "Feature",
  "properties": {
    "iso:country": "GB",
    "wof:name": "KY15 7TW",
    "wof:placetype": "postalcode"
  },
  "geometry": {"coordinates":[-3.092283,56.256106],"type":"Point"}
}
