{
  "type": "Feature",
  "properties": {
    "iso:country": "GB",
    "wof:name": "WA8 9WN",
    "wof:placetype": "postalcode"
  },
  "geometry": {"coordinates":[-2.722459,53.38659],"type":"Point"}
}
