{
  "type": "Feature",
  "properties": {
    "iso:country":"GB",
    "wof:name":"PO40 9RB",
    "wof:placetype":"postalcode"
},
  "geometry": {"coordinates":[-1.5138218971225,50.66940435365017],"type":"Point"}
}