{
  "type": "Feature",
  "properties": {
    "iso:country": "GB",
    "wof:name": "PO40 9RB",
    "wof:placetype": "postalcode"
  },
  "geometry": {"coordinates":[-1.513822,50.669404],"type":"Point"}
}
