{
  "type": "Feature",
  "properties": {
    "date:inception_lower": "2003-07-01",
    "date:inception_upper": "2003-07-01",
    "iso:country": "GB",
    "wof:name": "LS13 1PY",
    "wof:placetype": "postalcode"
  },
  "geometry": {"coordinates":[-1.665226,53.827728],"type":"Point"}
}
