{
  "type": "Feature",
  "properties": {
    "iso:country": "GB",
    "wof:name": "LS13 1PY",
    "wof:placetype": "postalcode"
  },
  "geometry": {"coordinates":[-1.665226,53.827728],"type":"Point"}
}
