{
  "type": "Feature",
  "properties": {
    "iso:country":"GB",
    "wof:name":"LS13 1PY",
    "wof:placetype":"postalcode"
},
  "geometry": {"coordinates":[-1.66522567592575,53.82772772428437],"type":"Point"}
}