{
  "type": "Feature",
  "properties": {
    "iso:country":"GB",
    "wof:name":"NG3 5AA",
    "wof:placetype":"postalcode"
},
  "geometry": {"coordinates":[-1.15102921338957,52.9651120086402],"type":"Point"}
}