{
  "type": "Feature",
  "properties": {
    "iso:country": "GB",
    "wof:name": "NG3 5AA",
    "wof:placetype": "postalcode"
  },
  "geometry": {"coordinates":[-1.151105,52.965059],"type":"Point"}
}
