{
  "type": "Feature",
  "properties": {
    "iso:country":"GB",
    "wof:name":"SE19 3NJ",
    "wof:placetype":"postalcode"
},
  "geometry": {"coordinates":[-0.10053727052442,51.42372510212],"type":"Point"}
}