{
  "type": "Feature",
  "properties": {
    "date:inception_lower": "1991-09-01",
    "date:inception_upper": "1991-09-01",
    "iso:country": "GB",
    "wof:name": "SE19 3NJ",
    "wof:placetype": "postalcode"
  },
  "geometry": {"coordinates":[-0.100537,51.423725],"type":"Point"}
}
