{
  "type": "Feature",
  "properties": {
    "iso:country": "GB",
    "wof:name": "MK43 8QG",
    "wof:placetype": "postalcode"
  },
  "geometry": {"coordinates":[-0.535732,52.143147],"type":"Point"}
}
