{
  "type": "Feature",
  "properties": {
    "date:inception_lower":"2006-02-01",
    "date:inception_upper":"2006-02-28",
    "iso:country":"GB",
    "wof:name":"NE66 1PA",
    "wof:placetype":"postalcode"
},
  "geometry": {"coordinates":[-1.702549,55.411563],"type":"Point"}
}