{
  "type": "Feature",
  "properties": {
    "iso:country":"GB",
    "wof:name":"NE66 1PA",
    "wof:placetype":"postalcode"
},
  "geometry": {"coordinates":[-1.70254915884145,55.4115631809187],"type":"Point"}
}