{
  "type": "Feature",
  "properties": {
    "iso:country":"GB",
    "wof:name":"NE39 1JL",
    "wof:placetype":"postalcode"
},
  "geometry": {"coordinates":[-1.74205952813626,54.92094863316129],"type":"Point"}
}