{
  "type": "Feature",
  "properties": {
    "iso:country":"GB",
    "wof:name":"CH8 7HB",
    "wof:placetype":"postalcode"
},
  "geometry": {"coordinates":[-3.20548509787244,53.27709173135544],"type":"Point"}
}