{
  "type": "Feature",
  "properties": {
    "iso:country": "GB",
    "wof:name": "FK8 2JD",
    "wof:placetype": "postalcode"
  },
  "geometry": {"coordinates":[-3.945044,56.112875],"type":"Point"}
}
