{
  "type": "Feature",
  "properties": {
    "iso:country":"GB",
    "wof:name":"FK8 2JD",
    "wof:placetype":"postalcode"
},
  "geometry": {"coordinates":[-3.94508420387325,56.11291773050257],"type":"Point"}
}