{
  "type": "Feature",
  "properties": {
    "iso:country":"GB",
    "wof:name":"KY8 4RQ",
    "wof:placetype":"postalcode"
},
  "geometry": {"coordinates":[-2.99377044481358,56.19995390233873],"type":"Point"}
}