{
  "type": "Feature",
  "properties": {
    "iso:country":"GB",
    "wof:name":"DN10 4DL",
    "wof:placetype":"postalcode"
},
  "geometry": {"coordinates":[-0.83174334755117,53.43831049498544],"type":"Point"}
}