{
  "type": "Feature",
  "properties": {
    "date:inception_lower": "1993-08-01",
    "date:inception_upper": "1993-08-01",
    "iso:country": "GB",
    "wof:name": "WN4 8DP",
    "wof:placetype": "postalcode"
  },
  "geometry": {"coordinates":[-2.644011,53.499424],"type":"Point"}
}
