{
  "type": "Feature",
  "properties": {
    "iso:country":"GB",
    "wof:name":"WN4 8DP",
    "wof:placetype":"postalcode"
},
  "geometry": {"coordinates":[-2.64401092425734,53.49942381401773],"type":"Point"}
}