{
  "type": "Feature",
  "properties": {
    "iso:country":"GB",
    "wof:name":"HX6 2DR",
    "wof:placetype":"postalcode"
},
  "geometry": {"coordinates":[-1.90557904102953,53.70932673254951],"type":"Point"}
}