{
  "type": "Feature",
  "properties": {
    "date:inception_lower": "2022-03-01",
    "date:inception_upper": "2022-03-01",
    "iso:country": "GB",
    "wof:name": "WF3 4GA",
    "wof:placetype": "postalcode"
  },
  "geometry": {"coordinates":[-1.477749,53.69947],"type":"Point"}
}
