{
  "type": "Feature",
  "properties": {
    "iso:country":"GB",
    "wof:name":"CO15 3PU",
    "wof:placetype":"postalcode"
},
  "geometry": {"coordinates":[1.15423945433224,51.7967403497352],"type":"Point"}
}