{
  "type": "Feature",
  "properties": {
    "iso:country":"GB",
    "wof:name":"L35 2UG",
    "wof:placetype":"postalcode"
},
  "geometry": {"coordinates":[-2.78985008163202,53.41916945239743],"type":"Point"}
}