{
  "type": "Feature",
  "properties": {
    "iso:country":"GB",
    "wof:name":"DH8 5RY",
    "wof:placetype":"postalcode"
},
  "geometry": {"coordinates":[-1.83324861278349,54.84966635493582],"type":"Point"}
}