{
  "type": "Feature",
  "properties": {
    "date:inception_lower": "1983-07-01",
    "date:inception_upper": "1983-07-01",
    "iso:country": "GB",
    "wof:name": "S12 2UX",
    "wof:placetype": "postalcode"
  },
  "geometry": {"coordinates":[-1.433464,53.355129],"type":"Point"}
}
