{
  "type": "Feature",
  "properties": {
    "iso:country":"GB",
    "wof:name":"S12 2UX",
    "wof:placetype":"postalcode"
},
  "geometry": {"coordinates":[-1.43351026461321,53.35511083729551],"type":"Point"}
}