{
  "type": "Feature",
  "properties": {
    "date:inception_lower": "1980-01-01",
    "date:inception_upper": "1980-01-01",
    "iso:country": "GB",
    "wof:name": "OX9 7DY",
    "wof:placetype": "postalcode"
  },
  "geometry": {"coordinates":[-0.977839,51.693546],"type":"Point"}
}
