{
  "type": "Feature",
  "properties": {
    "iso:country": "GB",
    "wof:name": "OX9 7DY",
    "wof:placetype": "postalcode"
  },
  "geometry": {"coordinates":[-0.977839,51.693546],"type":"Point"}
}
