{
  "type": "Feature",
  "properties": {
    "date:inception_lower": "1987-10-01",
    "date:inception_upper": "1987-10-01",
    "iso:country": "GB",
    "wof:name": "PL19 9RL",
    "wof:placetype": "postalcode"
  },
  "geometry": {"coordinates":[-4.147037,50.544322],"type":"Point"}
}
