{
  "type": "Feature",
  "properties": {
    "iso:country":"GB",
    "wof:name":"CM1 4RA",
    "wof:placetype":"postalcode"
},
  "geometry": {"coordinates":[0.35570563691334,51.81390435206362],"type":"Point"}
}