{
  "type": "Feature",
  "properties": {
    "iso:country": "GB",
    "wof:name": "CM1 4RA",
    "wof:placetype": "postalcode"
  },
  "geometry": {"coordinates":[0.355706,51.813904],"type":"Point"}
}
