{
  "type": "Feature",
  "properties": {
    "iso:country": "GB",
    "wof:name": "PE27 6RR",
    "wof:placetype": "postalcode"
  },
  "geometry": {"coordinates":[-0.085362,52.330985],"type":"Point"}
}
