{
  "type": "Feature",
  "properties": {
    "iso:country":"GB",
    "wof:name":"NE32 5SD",
    "wof:placetype":"postalcode"
},
  "geometry": {"coordinates":[-1.49470410439504,54.97624739752183],"type":"Point"}
}