{
  "type": "Feature",
  "properties": {
    "iso:country":"GB",
    "wof:name":"B38 9BU",
    "wof:placetype":"postalcode"
},
  "geometry": {"coordinates":[-1.92519076575409,52.39946009520872],"type":"Point"}
}