{
  "type": "Feature",
  "properties": {
    "iso:country": "GB",
    "wof:name": "HU1 3TN",
    "wof:placetype": "postalcode"
  },
  "geometry": {"coordinates":[-0.340491,53.746909],"type":"Point"}
}
