{
  "type": "Feature",
  "properties": {
    "iso:country":"GB",
    "wof:name":"HU1 3TN",
    "wof:placetype":"postalcode"
},
  "geometry": {"coordinates":[-0.3404912425564,53.74690865598719],"type":"Point"}
}