{
  "type": "Feature",
  "properties": {
    "date:inception_lower":"2010-03-01",
    "date:inception_upper":"2010-03-31",
    "iso:country":"GB",
    "wof:name":"HU1 3TN",
    "wof:placetype":"postalcode"
},
  "geometry": {"coordinates":[-0.340491,53.746909],"type":"Point"}
}