{
  "type": "Feature",
  "properties": {
    "iso:country": "GB",
    "wof:name": "TD15 1XB",
    "wof:placetype": "postalcode"
  },
  "geometry": {"coordinates":[-2.055123,55.815196],"type":"Point"}
}
