{
  "type": "Feature",
  "properties": {
    "iso:country":"GB",
    "wof:name":"TD15 1XB",
    "wof:placetype":"postalcode"
},
  "geometry": {"coordinates":[-2.05512320015304,55.81519648400551],"type":"Point"}
}