{
  "type": "Feature",
  "properties": {
    "date:inception_lower": "1984-10-01",
    "date:inception_upper": "1984-10-01",
    "iso:country": "GB",
    "wof:name": "GU7 1YB",
    "wof:placetype": "postalcode"
  },
  "geometry": {"coordinates":[-0.621024,51.175505],"type":"Point"}
}
