{
  "type": "Feature",
  "properties": {
    "iso:country":"GB",
    "wof:name":"GU7 1YB",
    "wof:placetype":"postalcode"
},
  "geometry": {"coordinates":[-0.62102449096562,51.17550466644961],"type":"Point"}
}