{
  "type": "Feature",
  "properties": {
    "iso:country":"GB",
    "wof:name":"B45 9RH",
    "wof:placetype":"postalcode"
},
  "geometry": {"coordinates":[-2.01681195129883,52.39522106319617],"type":"Point"}
}