{
  "type": "Feature",
  "properties": {
    "iso:country":"GB",
    "wof:name":"WS8 6HS",
    "wof:placetype":"postalcode"
},
  "geometry": {"coordinates":[-1.92885873840712,52.6506578774721],"type":"Point"}
}