{
  "type": "Feature",
  "properties": {
    "iso:country": "GB",
    "wof:name": "WS8 6HS",
    "wof:placetype": "postalcode"
  },
  "geometry": {"coordinates":[-1.928859,52.650658],"type":"Point"}
}
