{
  "type": "Feature",
  "properties": {
    "iso:country":"GB",
    "wof:name":"E15 3AB",
    "wof:placetype":"postalcode"
},
  "geometry": {"coordinates":[0.00603171822567,51.52640904162119],"type":"Point"}
}