{
  "type": "Feature",
  "properties": {
    "iso:country":"GB",
    "wof:name":"NW8 8QJ",
    "wof:placetype":"postalcode"
},
  "geometry": {"coordinates":[-0.17542870295792,51.52742961506858],"type":"Point"}
}