{
  "type": "Feature",
  "properties": {
    "date:inception_lower": "1997-06-01",
    "date:inception_upper": "1997-06-01",
    "iso:country": "GB",
    "wof:name": "NW8 8QJ",
    "wof:placetype": "postalcode"
  },
  "geometry": {"coordinates":[-0.175429,51.52743],"type":"Point"}
}
