{
  "type": "Feature",
  "properties": {
    "iso:country": "GB",
    "wof:name": "HR2 6LN",
    "wof:placetype": "postalcode"
  },
  "geometry": {"coordinates":[-2.655646,52.015522],"type":"Point"}
}
