{
  "type": "Feature",
  "properties": {
    "iso:country":"GB",
    "wof:name":"HR2 6LN",
    "wof:placetype":"postalcode"
},
  "geometry": {"coordinates":[-2.65585235617578,52.0158174624761],"type":"Point"}
}