{
  "type": "Feature",
  "properties": {
    "date:inception_lower": "1991-09-01",
    "date:inception_upper": "1991-09-01",
    "iso:country": "GB",
    "wof:name": "CB11 3TQ",
    "wof:placetype": "postalcode"
  },
  "geometry": {"coordinates":[0.212628,51.992118],"type":"Point"}
}
