{
  "type": "Feature",
  "properties": {
    "iso:country": "GB",
    "wof:name": "CB11 3TQ",
    "wof:placetype": "postalcode"
  },
  "geometry": {"coordinates":[0.212628,51.992118],"type":"Point"}
}
