{
  "type": "Feature",
  "properties": {
    "date:inception_lower": "1999-12-01",
    "date:inception_upper": "1999-12-01",
    "iso:country": "GB",
    "wof:name": "TN23 3PG",
    "wof:placetype": "postalcode"
  },
  "geometry": {"coordinates":[0.841726,51.15445],"type":"Point"}
}
