{
  "type": "Feature",
  "properties": {
    "iso:country":"GB",
    "wof:name":"TW12 1NJ",
    "wof:placetype":"postalcode"
},
  "geometry": {"coordinates":[-0.35666112600459,51.42631002185106],"type":"Point"}
}