{
  "type": "Feature",
  "properties": {
    "iso:country": "GB",
    "wof:name": "G72 7SX",
    "wof:placetype": "postalcode"
  },
  "geometry": {"coordinates":[-4.143843,55.821348],"type":"Point"}
}
