{
  "type": "Feature",
  "properties": {
    "date:inception_lower":"2003-09-01",
    "date:inception_upper":"2003-09-30",
    "iso:country":"GB",
    "wof:name":"PA16 8UB",
    "wof:placetype":"postalcode"
},
  "geometry": {"coordinates":[-4.773236,55.949191],"type":"Point"}
}