{
  "type": "Feature",
  "properties": {
    "iso:country": "GB",
    "wof:name": "PA16 8UB",
    "wof:placetype": "postalcode"
  },
  "geometry": {"coordinates":[-4.773236,55.949191],"type":"Point"}
}
