{
  "type": "Feature",
  "properties": {
    "iso:country":"GB",
    "wof:name":"PA16 8UB",
    "wof:placetype":"postalcode"
},
  "geometry": {"coordinates":[-4.77323598183667,55.94919070042801],"type":"Point"}
}