{
  "type": "Feature",
  "properties": {
    "iso:country":"GB",
    "wof:name":"SG3 6SX",
    "wof:placetype":"postalcode"
},
  "geometry": {"coordinates":[-0.1584884865399,51.8511464106757],"type":"Point"}
}