{
  "type": "Feature",
  "properties": {
    "iso:country": "GB",
    "wof:name": "SG3 6SX",
    "wof:placetype": "postalcode"
  },
  "geometry": {"coordinates":[-0.158488,51.851146],"type":"Point"}
}
