{
  "type": "Feature",
  "properties": {
    "date:inception_lower": "1992-08-01",
    "date:inception_upper": "1992-08-01",
    "iso:country": "GB",
    "wof:name": "M12 4LA",
    "wof:placetype": "postalcode"
  },
  "geometry": {"coordinates":[-2.196906,53.458491],"type":"Point"}
}
