{
  "type": "Feature",
  "properties": {
    "iso:country":"GB",
    "wof:name":"M12 4LA",
    "wof:placetype":"postalcode"
},
  "geometry": {"coordinates":[-2.19690634921076,53.45849100817385],"type":"Point"}
}