{
  "type": "Feature",
  "properties": {
    "iso:country":"GB",
    "wof:name":"IP14 5HD",
    "wof:placetype":"postalcode"
},
  "geometry": {"coordinates":[1.06908538251885,52.21344815781897],"type":"Point"}
}