{
  "type": "Feature",
  "properties": {
    "date:inception_lower": "1980-01-01",
    "date:inception_upper": "1980-01-01",
    "iso:country": "GB",
    "wof:name": "LA12 0LE",
    "wof:placetype": "postalcode"
  },
  "geometry": {"coordinates":[-3.147129,54.179458],"type":"Point"}
}
