{
  "type": "Feature",
  "properties": {
    "iso:country":"GB",
    "wof:name":"LA12 0LE",
    "wof:placetype":"postalcode"
},
  "geometry": {"coordinates":[-3.14715875321787,54.1793855998702],"type":"Point"}
}