{
  "type": "Feature",
  "properties": {
    "date:inception_lower": "1995-12-01",
    "date:inception_upper": "1995-12-01",
    "iso:country": "GB",
    "wof:name": "SK17 6PE",
    "wof:placetype": "postalcode"
  },
  "geometry": {"coordinates":[-1.906654,53.255304],"type":"Point"}
}
