{
  "type": "Feature",
  "properties": {
    "iso:country": "GB",
    "wof:name": "LE8 4BX",
    "wof:placetype": "postalcode"
  },
  "geometry": {"coordinates":[-1.170384,52.565294],"type":"Point"}
}
