{
  "type": "Feature",
  "properties": {
    "iso:country": "GB",
    "wof:name": "LE8 4BX",
    "wof:placetype": "postalcode"
  },
  "geometry": {"coordinates":[-1.169971,52.565327],"type":"Point"}
}
