{
  "type": "Feature",
  "properties": {
    "iso:country": "GB",
    "wof:name": "CB6 3FT",
    "wof:placetype": "postalcode"
  },
  "geometry": {"coordinates":[0.22365,52.325185],"type":"Point"}
}
