{
  "type": "Feature",
  "properties": {
    "date:inception_lower": "1980-01-01",
    "date:inception_upper": "1980-01-01",
    "iso:country": "GB",
    "wof:name": "DE12 7RD",
    "wof:placetype": "postalcode"
  },
  "geometry": {"coordinates":[-1.52389,52.715654],"type":"Point"}
}
