{
  "type": "Feature",
  "properties": {
    "date:inception_lower": "1980-01-01",
    "date:inception_upper": "1980-01-01",
    "iso:country": "GB",
    "wof:name": "BA2 2DL",
    "wof:placetype": "postalcode"
  },
  "geometry": {"coordinates":[-2.375992,51.371673],"type":"Point"}
}
