{
  "type": "Feature",
  "properties": {
    "iso:country":"GB",
    "wof:name":"NG17 8PD",
    "wof:placetype":"postalcode"
},
  "geometry": {"coordinates":[-1.26052474571963,53.1105263375697],"type":"Point"}
}