{
  "type": "Feature",
  "properties": {
    "iso:country":"GB",
    "wof:name":"YO16 7PZ",
    "wof:placetype":"postalcode"
},
  "geometry": {"coordinates":[-0.19974123284028,54.09868900655374],"type":"Point"}
}