{
  "type": "Feature",
  "properties": {
    "date:inception_lower":"1980-01-01",
    "date:inception_upper":"1980-01-31",
    "iso:country":"GB",
    "wof:name":"SY4 3QH",
    "wof:placetype":"postalcode"
},
  "geometry": {"coordinates":[-2.803414,52.785828],"type":"Point"}
}