{
  "type": "Feature",
  "properties": {
    "iso:country":"GB",
    "wof:name":"SY4 3QH",
    "wof:placetype":"postalcode"
},
  "geometry": {"coordinates":[-2.80341652442831,52.78581289427274],"type":"Point"}
}