{
  "type": "Feature",
  "properties": {
    "iso:country": "GB",
    "wof:name": "SY4 3QH",
    "wof:placetype": "postalcode"
  },
  "geometry": {"coordinates":[-2.802017,52.784831],"type":"Point"}
}
