{
  "type": "Feature",
  "properties": {
    "date:inception_lower":"1980-01-01",
    "date:inception_upper":"1980-01-31",
    "iso:country":"GB",
    "wof:name":"B70 8BY",
    "wof:placetype":"postalcode"
},
  "geometry": {"coordinates":[-2.003169,52.520848],"type":"Point"}
}