{
  "type": "Feature",
  "properties": {
    "iso:country":"GB",
    "wof:name":"B70 8BY",
    "wof:placetype":"postalcode"
},
  "geometry": {"coordinates":[-2.00316924787943,52.52084838700255],"type":"Point"}
}