{
  "type": "Feature",
  "properties": {
    "iso:country":"GB",
    "wof:name":"SW7 5LF",
    "wof:placetype":"postalcode"
},
  "geometry": {"coordinates":[-0.17837397464125,51.49480575839408],"type":"Point"}
}