{
  "type": "Feature",
  "properties": {
    "iso:country":"GB",
    "wof:name":"AB11 6RR",
    "wof:placetype":"postalcode"
},
  "geometry": {"coordinates":[-2.10413771037975,57.13762568916722],"type":"Point"}
}