{
  "type": "Feature",
  "properties": {
    "iso:country":"GB",
    "wof:name":"SE2 9HJ",
    "wof:placetype":"postalcode"
},
  "geometry": {"coordinates":[0.1033170032043,51.4885986567549],"type":"Point"}
}