{
  "type": "Feature",
  "properties": {
    "iso:country":"GB",
    "wof:name":"LE5 4PW",
    "wof:placetype":"postalcode"
},
  "geometry": {"coordinates":[-1.08176388697491,52.6299256622334],"type":"Point"}
}