{
  "type": "Feature",
  "properties": {
    "iso:country":"GB",
    "wof:name":"NR16 2RS",
    "wof:placetype":"postalcode"
},
  "geometry": {"coordinates":[0.88208615184133,52.43632920859397],"type":"Point"}
}