{
  "type": "Feature",
  "properties": {
    "iso:country": "GB",
    "wof:name": "NR16 2RS",
    "wof:placetype": "postalcode"
  },
  "geometry": {"coordinates":[0.882086,52.436329],"type":"Point"}
}
