{
  "type": "Feature",
  "properties": {
    "iso:country": "GB",
    "wof:name": "RG2 0AZ",
    "wof:placetype": "postalcode"
  },
  "geometry": {"coordinates":[-0.967301,51.443467],"type":"Point"}
}
