{
  "type": "Feature",
  "properties": {
    "date:inception_lower":"1980-01-01",
    "date:inception_upper":"1980-01-31",
    "iso:country":"GB",
    "wof:name":"CF39 9TG",
    "wof:placetype":"postalcode"
},
  "geometry": {"coordinates":[-3.398174,51.611528],"type":"Point"}
}