{
  "type": "Feature",
  "properties": {
    "date:inception_lower": "1980-01-01",
    "date:inception_upper": "1980-01-01",
    "iso:country": "GB",
    "wof:name": "NE28 0JP",
    "wof:placetype": "postalcode"
  },
  "geometry": {"coordinates":[-1.480908,54.994286],"type":"Point"}
}
