{
  "type": "Feature",
  "properties": {
    "iso:country": "GB",
    "wof:name": "ST5 5DP",
    "wof:placetype": "postalcode"
  },
  "geometry": {"coordinates":[-2.30953,52.954191],"type":"Point"}
}
