{
  "type": "Feature",
  "properties": {
    "iso:country":"GB",
    "wof:name":"W1U 4EA",
    "wof:placetype":"postalcode"
},
  "geometry": {"coordinates":[-0.15223148739477,51.51891032533017],"type":"Point"}
}