{
  "type": "Feature",
  "properties": {
    "date:inception_lower":"1980-01-01",
    "date:inception_upper":"1980-01-31",
    "iso:country":"GB",
    "wof:name":"ST15 8HD",
    "wof:placetype":"postalcode"
},
  "geometry": {"coordinates":[-2.149457,52.905779],"type":"Point"}
}