{
  "type": "Feature",
  "properties": {
    "iso:country":"GB",
    "wof:name":"DG11 2QS",
    "wof:placetype":"postalcode"
},
  "geometry": {"coordinates":[-3.34638658318627,55.11899686109766],"type":"Point"}
}