{
  "type": "Feature",
  "properties": {
    "date:inception_lower": "1980-03-01",
    "date:inception_upper": "1980-03-01",
    "iso:country": "GB",
    "wof:name": "DG11 2QS",
    "wof:placetype": "postalcode"
  },
  "geometry": {"coordinates":[-3.346387,55.118997],"type":"Point"}
}
