{
  "type": "Feature",
  "properties": {
    "iso:country":"GB",
    "wof:name":"CF64 3NL",
    "wof:placetype":"postalcode"
},
  "geometry": {"coordinates":[-3.19074179815951,51.43426626670407],"type":"Point"}
}