{
  "type": "Feature",
  "properties": {
    "date:inception_lower": "1993-01-01",
    "date:inception_upper": "1993-01-01",
    "iso:country": "GB",
    "wof:name": "CF64 3NL",
    "wof:placetype": "postalcode"
  },
  "geometry": {"coordinates":[-3.190742,51.434266],"type":"Point"}
}
