{
  "type": "Feature",
  "properties": {
    "iso:country":"GB",
    "wof:name":"PR3 1UJ",
    "wof:placetype":"postalcode"
},
  "geometry": {"coordinates":[-2.70167377203594,53.9262943443538],"type":"Point"}
}