{
  "type": "Feature",
  "properties": {
    "iso:country": "GB",
    "wof:name": "PR3 1UJ",
    "wof:placetype": "postalcode"
  },
  "geometry": {"coordinates":[-2.701674,53.926294],"type":"Point"}
}
