{
  "type": "Feature",
  "properties": {
    "iso:country":"GB",
    "wof:name":"HP2 7ND",
    "wof:placetype":"postalcode"
},
  "geometry": {"coordinates":[-0.44359932307923,51.77896921722935],"type":"Point"}
}