{
  "type": "Feature",
  "properties": {
    "date:inception_lower": "1980-01-01",
    "date:inception_upper": "1980-01-01",
    "iso:country": "GB",
    "wof:name": "HP2 7ND",
    "wof:placetype": "postalcode"
  },
  "geometry": {"coordinates":[-0.443599,51.778969],"type":"Point"}
}
