{
  "type": "Feature",
  "properties": {
    "iso:country":"GB",
    "wof:name":"BS9 1DN",
    "wof:placetype":"postalcode"
},
  "geometry": {"coordinates":[-2.64250294212616,51.4850050940337],"type":"Point"}
}