{
  "type": "Feature",
  "properties": {
    "iso:country": "GB",
    "wof:name": "BS9 1DN",
    "wof:placetype": "postalcode"
  },
  "geometry": {"coordinates":[-2.642503,51.485005],"type":"Point"}
}
