{
  "type": "Feature",
  "properties": {
    "iso:country":"GB",
    "wof:name":"NE26 3JL",
    "wof:placetype":"postalcode"
},
  "geometry": {"coordinates":[-1.46440594208012,55.05056007290982],"type":"Point"}
}