{
  "type": "Feature",
  "properties": {
    "iso:country": "GB",
    "wof:name": "S65 4RG",
    "wof:placetype": "postalcode"
  },
  "geometry": {"coordinates":[-1.259588,53.437548],"type":"Point"}
}
