{
  "type": "Feature",
  "properties": {
    "iso:country":"GB",
    "wof:name":"S65 4RG",
    "wof:placetype":"postalcode"
},
  "geometry": {"coordinates":[-1.25958813601975,53.43754790357895],"type":"Point"}
}