{
  "type": "Feature",
  "properties": {
    "iso:country":"GB",
    "wof:name":"HA5 3TB",
    "wof:placetype":"postalcode"
},
  "geometry": {"coordinates":[-0.39456467276975,51.60214787281591],"type":"Point"}
}