{
  "type": "Feature",
  "properties": {
    "iso:country": "GB",
    "wof:name": "HA5 3TB",
    "wof:placetype": "postalcode"
  },
  "geometry": {"coordinates":[-0.394565,51.602148],"type":"Point"}
}
