{
  "type": "Feature",
  "properties": {
    "iso:country":"GB",
    "wof:name":"DE21 6PN",
    "wof:placetype":"postalcode"
},
  "geometry": {"coordinates":[-1.44203685600875,52.92167092106163],"type":"Point"}
}