{
  "type": "Feature",
  "properties": {
    "date:inception_lower": "1992-08-01",
    "date:inception_upper": "1992-08-01",
    "iso:country": "GB",
    "wof:name": "DE21 6PN",
    "wof:placetype": "postalcode"
  },
  "geometry": {"coordinates":[-1.442037,52.921671],"type":"Point"}
}
