{
  "type": "Feature",
  "properties": {
    "iso:country": "GB",
    "wof:name": "CB21 5JY",
    "wof:placetype": "postalcode"
  },
  "geometry": {"coordinates":[0.253788,52.202871],"type":"Point"}
}
