{
  "type": "Feature",
  "properties": {
    "date:inception_lower": "1980-01-01",
    "date:inception_upper": "1980-01-01",
    "iso:country": "GB",
    "wof:name": "SG11 1LE",
    "wof:placetype": "postalcode"
  },
  "geometry": {"coordinates":[0.027221,51.880536],"type":"Point"}
}
