{
  "type": "Feature",
  "properties": {
    "iso:country":"GB",
    "wof:name":"SG11 1LE",
    "wof:placetype":"postalcode"
},
  "geometry": {"coordinates":[0.02722143267522,51.88053612834027],"type":"Point"}
}