{
  "type": "Feature",
  "properties": {
    "iso:country": "GB",
    "wof:name": "PO17 5FX",
    "wof:placetype": "postalcode"
  },
  "geometry": {"coordinates":[-1.205197,50.881998],"type":"Point"}
}
