{
  "type": "Feature",
  "properties": {
    "date:inception_lower":"1980-01-01",
    "date:inception_upper":"1980-01-31",
    "iso:country":"GB",
    "wof:name":"NE32 5DL",
    "wof:placetype":"postalcode"
},
  "geometry": {"coordinates":[-1.484452,54.964289],"type":"Point"}
}