{
  "type": "Feature",
  "properties": {
    "iso:country":"GB",
    "wof:name":"NE32 5DL",
    "wof:placetype":"postalcode"
},
  "geometry": {"coordinates":[-1.48445216629251,54.96428853614804],"type":"Point"}
}