{
  "type": "Feature",
  "properties": {
    "iso:country": "GB",
    "wof:name": "KY11 9SR",
    "wof:placetype": "postalcode"
  },
  "geometry": {"coordinates":[-3.353318,56.035126],"type":"Point"}
}
