{
  "type": "Feature",
  "properties": {
    "iso:country":"GB",
    "wof:name":"HR9 6EW",
    "wof:placetype":"postalcode"
},
  "geometry": {"coordinates":[-2.68387254839415,51.86850342853018],"type":"Point"}
}