{
  "type": "Feature",
  "properties": {
    "iso:country": "GB",
    "wof:name": "HR9 6EW",
    "wof:placetype": "postalcode"
  },
  "geometry": {"coordinates":[-2.683873,51.868503],"type":"Point"}
}
