{
  "type": "Feature",
  "properties": {
    "iso:country":"GB",
    "wof:name":"NP19 7JX",
    "wof:placetype":"postalcode"
},
  "geometry": {"coordinates":[-2.97923720825457,51.60151033875839],"type":"Point"}
}