{
  "type": "Feature",
  "properties": {
    "date:inception_lower": "2019-12-01",
    "date:inception_upper": "2019-12-01",
    "iso:country": "GB",
    "wof:name": "HP1 1GH",
    "wof:placetype": "postalcode"
  },
  "geometry": {"coordinates":[-0.49162,51.74716],"type":"Point"}
}
