{
  "type": "Feature",
  "properties": {
    "date:inception_lower": "1980-01-01",
    "date:inception_upper": "1980-01-01",
    "iso:country": "GB",
    "wof:name": "CH1 5HE",
    "wof:placetype": "postalcode"
  },
  "geometry": {"coordinates":[-2.93061,53.210599],"type":"Point"}
}
