{
  "type": "Feature",
  "properties": {
    "iso:country":"GB",
    "wof:name":"CH1 5HE",
    "wof:placetype":"postalcode"
},
  "geometry": {"coordinates":[-2.93060984917553,53.21059868064197],"type":"Point"}
}