{
  "type": "Feature",
  "properties": {
    "iso:country":"GB",
    "wof:name":"GL51 0FG",
    "wof:placetype":"postalcode"
},
  "geometry": {"coordinates":[-2.12576919435786,51.90421255238945],"type":"Point"}
}