{
  "type": "Feature",
  "properties": {
    "date:inception_lower": "2001-06-01",
    "date:inception_upper": "2001-06-01",
    "iso:country": "GB",
    "wof:name": "GL51 0FG",
    "wof:placetype": "postalcode"
  },
  "geometry": {"coordinates":[-2.125769,51.904213],"type":"Point"}
}
