{
  "type": "Feature",
  "properties": {
    "iso:country":"GB",
    "wof:name":"SA4 3FN",
    "wof:placetype":"postalcode"
},
  "geometry": {"coordinates":[-4.10923995979174,51.64129641600059],"type":"Point"}
}