{
  "type": "Feature",
  "properties": {
    "iso:country": "GB",
    "wof:name": "SA4 3FN",
    "wof:placetype": "postalcode"
  },
  "geometry": {"coordinates":[-4.10924,51.641296],"type":"Point"}
}
