{
  "type": "Feature",
  "properties": {
    "iso:country":"GB",
    "wof:name":"M21 9WN",
    "wof:placetype":"postalcode"
},
  "geometry": {"coordinates":[-2.28584264133763,53.44569128674478],"type":"Point"}
}