{
  "type": "Feature",
  "properties": {
    "iso:country": "GB",
    "wof:name": "WR9 9LD",
    "wof:placetype": "postalcode"
  },
  "geometry": {"coordinates":[-2.158854,52.270268],"type":"Point"}
}
