{
  "type": "Feature",
  "properties": {
    "iso:country":"GB",
    "wof:name":"ST13 6NN",
    "wof:placetype":"postalcode"
},
  "geometry": {"coordinates":[-2.00436683371291,53.11555383962601],"type":"Point"}
}