{
  "type": "Feature",
  "properties": {
    "iso:country": "GB",
    "wof:name": "NG23 7LT",
    "wof:placetype": "postalcode"
  },
  "geometry": {"coordinates":[-0.761093,53.146902],"type":"Point"}
}
