{
  "type": "Feature",
  "properties": {
    "iso:country":"GB",
    "wof:name":"NG23 7LT",
    "wof:placetype":"postalcode"
},
  "geometry": {"coordinates":[-0.76109263392486,53.14690217626199],"type":"Point"}
}