{
  "type": "Feature",
  "properties": {
    "iso:country":"GB",
    "wof:name":"CV6 1AE",
    "wof:placetype":"postalcode"
},
  "geometry": {"coordinates":[-1.52921711455573,52.4158803034117],"type":"Point"}
}