{
  "type": "Feature",
  "properties": {
    "iso:country":"GB",
    "wof:name":"G31 5ES",
    "wof:placetype":"postalcode"
},
  "geometry": {"coordinates":[-4.1936221010733,55.85258158463773],"type":"Point"}
}