{
  "type": "Feature",
  "properties": {
    "iso:country": "GB",
    "wof:name": "IG11 0PZ",
    "wof:placetype": "postalcode"
  },
  "geometry": {"coordinates":[0.113391,51.52795],"type":"Point"}
}
