{
  "type": "Feature",
  "properties": {
    "date:inception_lower": "1980-01-01",
    "date:inception_upper": "1980-01-01",
    "iso:country": "GB",
    "wof:name": "FY3 7SU",
    "wof:placetype": "postalcode"
  },
  "geometry": {"coordinates":[-3.010449,53.82835],"type":"Point"}
}
