{
  "type": "Feature",
  "properties": {
    "iso:country": "GB",
    "wof:name": "DD10 9RJ",
    "wof:placetype": "postalcode"
  },
  "geometry": {"coordinates":[-2.467302,56.700804],"type":"Point"}
}
