{
  "type": "Feature",
  "properties": {
    "iso:country":"GB",
    "wof:name":"BS16 6LG",
    "wof:placetype":"postalcode"
},
  "geometry": {"coordinates":[-2.50325270798983,51.50188836631461],"type":"Point"}
}