{
  "type": "Feature",
  "properties": {
    "iso:country": "GB",
    "wof:name": "BS16 6LG",
    "wof:placetype": "postalcode"
  },
  "geometry": {"coordinates":[-2.503253,51.501888],"type":"Point"}
}
