{
  "type": "Feature",
  "properties": {
    "iso:country":"GB",
    "wof:name":"N21 1QS",
    "wof:placetype":"postalcode"
},
  "geometry": {"coordinates":[-0.11267226106426,51.63684591667778],"type":"Point"}
}