{
  "type": "Feature",
  "properties": {
    "iso:country":"GB",
    "wof:name":"AB42 3EG",
    "wof:placetype":"postalcode"
},
  "geometry": {"coordinates":[-1.83872602553073,57.55941296063779],"type":"Point"}
}