{
  "type": "Feature",
  "properties": {
    "iso:country":"GB",
    "wof:name":"SW12 0LH",
    "wof:placetype":"postalcode"
},
  "geometry": {"coordinates":[-0.1331601550012,51.44383520802088],"type":"Point"}
}