{
  "type": "Feature",
  "properties": {
    "iso:country":"GB",
    "wof:name":"G52 4ER",
    "wof:placetype":"postalcode"
},
  "geometry": {"coordinates":[-4.37094821593893,55.85430623198541],"type":"Point"}
}