{
  "type": "Feature",
  "properties": {
    "iso:country": "GB",
    "wof:name": "IP32 7FE",
    "wof:placetype": "postalcode"
  },
  "geometry": {"coordinates":[0.763152,52.250626],"type":"Point"}
}
