{
  "type": "Feature",
  "properties": {
    "date:inception_lower":"1986-04-01",
    "date:inception_upper":"1986-04-30",
    "iso:country":"GB",
    "wof:name":"TN33 0LD",
    "wof:placetype":"postalcode"
},
  "geometry": {"coordinates":[0.482904,50.923248],"type":"Point"}
}