{
  "type": "Feature",
  "properties": {
    "iso:country":"GB",
    "wof:name":"TN33 0LD",
    "wof:placetype":"postalcode"
},
  "geometry": {"coordinates":[0.48290399180951,50.92324784349322],"type":"Point"}
}