{
  "type": "Feature",
  "properties": {
    "iso:country":"GB",
    "wof:name":"W6 0AP",
    "wof:placetype":"postalcode"
},
  "geometry": {"coordinates":[-0.23003891807734,51.50026395995261],"type":"Point"}
}