{
  "type": "Feature",
  "properties": {
    "iso:country":"GB",
    "wof:name":"DY8 2JD",
    "wof:placetype":"postalcode"
},
  "geometry": {"coordinates":[-2.14074857726924,52.44790981671606],"type":"Point"}
}