{
  "type": "Feature",
  "properties": {
    "iso:country":"GB",
    "wof:name":"PL30 5EW",
    "wof:placetype":"postalcode"
},
  "geometry": {"coordinates":[-4.75136975987136,50.38062940004296],"type":"Point"}
}