{
  "type": "Feature",
  "properties": {
    "iso:country":"GB",
    "wof:name":"PR5 6UT",
    "wof:placetype":"postalcode"
},
  "geometry": {"coordinates":[-2.67477229332626,53.72830590459219],"type":"Point"}
}