{
  "type": "Feature",
  "properties": {
    "iso:country":"GB",
    "wof:name":"TR1 3DG",
    "wof:placetype":"postalcode"
},
  "geometry": {"coordinates":[-5.05987167276094,50.26295300601119],"type":"Point"}
}