{
  "type": "Feature",
  "properties": {
    "date:inception_lower":"1990-02-01",
    "date:inception_upper":"1990-02-28",
    "iso:country":"GB",
    "wof:name":"CB6 2QR",
    "wof:placetype":"postalcode"
},
  "geometry": {"coordinates":[0.124385,52.390683],"type":"Point"}
}