{
  "type": "Feature",
  "properties": {
    "iso:country":"GB",
    "wof:name":"CB6 2QR",
    "wof:placetype":"postalcode"
},
  "geometry": {"coordinates":[0.12438466424645,52.39068257385937],"type":"Point"}
}