{
  "type": "Feature",
  "properties": {
    "iso:country":"GB",
    "wof:name":"W5 1SR",
    "wof:placetype":"postalcode"
},
  "geometry": {"coordinates":[-0.30863372358427,51.52631447262533],"type":"Point"}
}