{
  "type": "Feature",
  "properties": {
    "iso:country": "GB",
    "wof:name": "LS21 2EY",
    "wof:placetype": "postalcode"
  },
  "geometry": {"coordinates":[-1.696814,53.924108],"type":"Point"}
}
