{
  "type": "Feature",
  "properties": {
    "iso:country":"GB",
    "wof:name":"LS21 2EY",
    "wof:placetype":"postalcode"
},
  "geometry": {"coordinates":[-1.69681420684983,53.92410774047123],"type":"Point"}
}