{
  "type": "Feature",
  "properties": {
    "iso:country":"GB",
    "wof:name":"EX6 8QJ",
    "wof:placetype":"postalcode"
},
  "geometry": {"coordinates":[-3.4519026843708,50.62501877810217],"type":"Point"}
}