{
  "type": "Feature",
  "properties": {
    "iso:country": "GB",
    "wof:name": "LL53 6HT",
    "wof:placetype": "postalcode"
  },
  "geometry": {"coordinates":[-4.515854,52.93431],"type":"Point"}
}
