{
  "type": "Feature",
  "properties": {
    "iso:country":"GB",
    "wof:name":"LL53 6HT",
    "wof:placetype":"postalcode"
},
  "geometry": {"coordinates":[-4.51585398468624,52.93430951579954],"type":"Point"}
}