{
  "type": "Feature",
  "properties": {
    "date:inception_lower":"1980-01-01",
    "date:inception_upper":"1980-01-31",
    "iso:country":"GB",
    "wof:name":"RG7 5PN",
    "wof:placetype":"postalcode"
},
  "geometry": {"coordinates":[-1.159995,51.411799],"type":"Point"}
}