{
  "type": "Feature",
  "properties": {
    "iso:country":"GB",
    "wof:name":"RG7 5PN",
    "wof:placetype":"postalcode"
},
  "geometry": {"coordinates":[-1.16001472819093,51.4117992402664],"type":"Point"}
}