{
  "type": "Feature",
  "properties": {
    "iso:country":"GB",
    "wof:name":"L13 5XF",
    "wof:placetype":"postalcode"
},
  "geometry": {"coordinates":[-2.91151692041773,53.41339464880318],"type":"Point"}
}