{
  "type": "Feature",
  "properties": {
    "iso:country":"GB",
    "wof:name":"OL9 7PJ",
    "wof:placetype":"postalcode"
},
  "geometry": {"coordinates":[-2.14182384753555,53.52418471739151],"type":"Point"}
}