{
  "type": "Feature",
  "properties": {
    "date:inception_lower":"2003-10-01",
    "date:inception_upper":"2003-10-31",
    "iso:country":"GB",
    "wof:name":"TS22 5GE",
    "wof:placetype":"postalcode"
},
  "geometry": {"coordinates":[-1.360474,54.642823],"type":"Point"}
}