{
  "type": "Feature",
  "properties": {
    "iso:country": "GB",
    "wof:name": "TS22 5GE",
    "wof:placetype": "postalcode"
  },
  "geometry": {"coordinates":[-1.360474,54.642823],"type":"Point"}
}
