{
  "type": "Feature",
  "properties": {
    "iso:country":"GB",
    "wof:name":"TS22 5GE",
    "wof:placetype":"postalcode"
},
  "geometry": {"coordinates":[-1.36047401580348,54.64282327831074],"type":"Point"}
}