{
  "type": "Feature",
  "properties": {
    "date:inception_lower": "1999-12-01",
    "date:inception_upper": "1999-12-01",
    "iso:country": "GB",
    "wof:name": "B19 3TD",
    "wof:placetype": "postalcode"
  },
  "geometry": {"coordinates":[-1.897159,52.489825],"type":"Point"}
}
