{
  "type": "Feature",
  "properties": {
    "iso:country":"GB",
    "wof:name":"BB12 7QT",
    "wof:placetype":"postalcode"
},
  "geometry": {"coordinates":[-2.34589366415346,53.81249603190494],"type":"Point"}
}