{
  "type": "Feature",
  "properties": {
    "iso:country":"GB",
    "wof:name":"LU1 5SG",
    "wof:placetype":"postalcode"
},
  "geometry": {"coordinates":[-0.44053580096937,51.87911458674866],"type":"Point"}
}