{
  "type": "Feature",
  "properties": {
    "date:inception_lower": "1980-01-01",
    "date:inception_upper": "1980-01-01",
    "iso:country": "GB",
    "wof:name": "LU1 5SG",
    "wof:placetype": "postalcode"
  },
  "geometry": {"coordinates":[-0.440536,51.879115],"type":"Point"}
}
