{
  "type": "Feature",
  "properties": {
    "iso:country": "GB",
    "wof:name": "HP14 3JR",
    "wof:placetype": "postalcode"
  },
  "geometry": {"coordinates":[-0.835458,51.620783],"type":"Point"}
}
