{
  "type": "Feature",
  "properties": {
    "iso:country": "GB",
    "wof:name": "B23 7JP",
    "wof:placetype": "postalcode"
  },
  "geometry": {"coordinates":[-1.862056,52.520553],"type":"Point"}
}
