{
  "type": "Feature",
  "properties": {
    "iso:country":"GB",
    "wof:name":"DN20 8TE",
    "wof:placetype":"postalcode"
},
  "geometry": {"coordinates":[-0.46102965946923,53.56893220500415],"type":"Point"}
}