{
  "type": "Feature",
  "properties": {
    "date:inception_lower": "1987-04-01",
    "date:inception_upper": "1987-04-01",
    "iso:country": "GB",
    "wof:name": "RG7 3YP",
    "wof:placetype": "postalcode"
  },
  "geometry": {"coordinates":[-1.054688,51.399317],"type":"Point"}
}
