{
  "type": "Feature",
  "properties": {
    "date:inception_lower": "2000-10-01",
    "date:inception_upper": "2000-10-01",
    "iso:country": "GB",
    "wof:name": "OX26 4JP",
    "wof:placetype": "postalcode"
  },
  "geometry": {"coordinates":[-1.14849,51.905203],"type":"Point"}
}
