{
  "type": "Feature",
  "properties": {
    "iso:country":"GB",
    "wof:name":"W11 3TH",
    "wof:placetype":"postalcode"
},
  "geometry": {"coordinates":[-0.20697861579451,51.50486851054863],"type":"Point"}
}