{
  "type": "Feature",
  "properties": {
    "date:inception_lower":"1980-01-01",
    "date:inception_upper":"1980-01-31",
    "iso:country":"GB",
    "wof:name":"W11 3TH",
    "wof:placetype":"postalcode"
},
  "geometry": {"coordinates":[-0.206722,51.50492],"type":"Point"}
}