{
  "type": "Feature",
  "properties": {
    "iso:country":"GB",
    "wof:name":"BL6 6BE",
    "wof:placetype":"postalcode"
},
  "geometry": {"coordinates":[-2.5385878025336,53.59071092626998],"type":"Point"}
}