{
  "type": "Feature",
  "properties": {
    "iso:country":"GB",
    "wof:name":"RM17 9SN",
    "wof:placetype":"postalcode"
},
  "geometry": {"coordinates":[0.32478418469847,51.47567505687777],"type":"Point"}
}