{
  "type": "Feature",
  "properties": {
    "iso:country":"GB",
    "wof:name":"E13 0LT",
    "wof:placetype":"postalcode"
},
  "geometry": {"coordinates":[0.02381243805817,51.53530310471865],"type":"Point"}
}