{
  "type": "Feature",
  "properties": {
    "iso:country":"GB",
    "wof:name":"HD5 8TR",
    "wof:placetype":"postalcode"
},
  "geometry": {"coordinates":[-1.73799204769064,53.63593208415517],"type":"Point"}
}