{
  "type": "Feature",
  "properties": {
    "date:inception_lower": "2006-02-01",
    "date:inception_upper": "2006-02-01",
    "iso:country": "GB",
    "wof:name": "EX12 2GZ",
    "wof:placetype": "postalcode"
  },
  "geometry": {"coordinates":[-3.069187,50.704504],"type":"Point"}
}
