{
  "type": "Feature",
  "properties": {
    "iso:country": "GB",
    "wof:name": "EX12 2GZ",
    "wof:placetype": "postalcode"
  },
  "geometry": {"coordinates":[-3.069187,50.704504],"type":"Point"}
}
