{
  "type": "Feature",
  "properties": {
    "date:inception_lower": "2022-02-01",
    "date:inception_upper": "2022-02-01",
    "iso:country": "GB",
    "wof:name": "CW5 6ZB",
    "wof:placetype": "postalcode"
  },
  "geometry": {"coordinates":[-2.531858,53.077391],"type":"Point"}
}
