{
  "type": "Feature",
  "properties": {
    "iso:country":"GB",
    "wof:name":"S36 1FL",
    "wof:placetype":"postalcode"
},
  "geometry": {"coordinates":[-1.59550376865308,53.47530877185469],"type":"Point"}
}