{
  "type": "Feature",
  "properties": {
    "iso:country":"GB",
    "wof:name":"DL17 8PU",
    "wof:placetype":"postalcode"
},
  "geometry": {"coordinates":[-1.5675538733023,54.68487145198015],"type":"Point"}
}