{
  "type": "Feature",
  "properties": {
    "iso:country": "GB",
    "wof:name": "DL17 8PU",
    "wof:placetype": "postalcode"
  },
  "geometry": {"coordinates":[-1.567554,54.684871],"type":"Point"}
}
