{
  "type": "Feature",
  "properties": {
    "iso:country": "GB",
    "wof:name": "DH5 8LN",
    "wof:placetype": "postalcode"
  },
  "geometry": {"coordinates":[-1.471712,54.833832],"type":"Point"}
}
