{
  "type": "Feature",
  "properties": {
    "iso:country":"GB",
    "wof:name":"LA8 0ES",
    "wof:placetype":"postalcode"
},
  "geometry": {"coordinates":[-2.70738068871215,54.26027163338458],"type":"Point"}
}