{
  "type": "Feature",
  "properties": {
    "iso:country":"GB",
    "wof:name":"LA12 0SU",
    "wof:placetype":"postalcode"
},
  "geometry": {"coordinates":[-3.11598114379628,54.16071404961416],"type":"Point"}
}