{
  "type": "Feature",
  "properties": {
    "date:inception_lower": "1980-01-01",
    "date:inception_upper": "1980-01-01",
    "iso:country": "GB",
    "wof:name": "OX15 6HF",
    "wof:placetype": "postalcode"
  },
  "geometry": {"coordinates":[-1.465707,52.066543],"type":"Point"}
}
