{
  "type": "Feature",
  "properties": {
    "date:inception_lower":"1980-01-01",
    "date:inception_upper":"1980-01-31",
    "iso:country":"GB",
    "wof:name":"OX15 6HF",
    "wof:placetype":"postalcode"
},
  "geometry": {"coordinates":[-1.464206,52.066428],"type":"Point"}
}