{
  "type": "Feature",
  "properties": {
    "iso:country":"GB",
    "wof:name":"OX15 6HF",
    "wof:placetype":"postalcode"
},
  "geometry": {"coordinates":[-1.46421913590476,52.06641581528596],"type":"Point"}
}