{
  "type": "Feature",
  "properties": {
    "date:inception_lower":"2011-06-01",
    "date:inception_upper":"2011-06-30",
    "iso:country":"GB",
    "wof:name":"B60 1JB",
    "wof:placetype":"postalcode"
},
  "geometry": {"coordinates":[-2.035724,52.366822],"type":"Point"}
}