{
  "type": "Feature",
  "properties": {
    "iso:country": "GB",
    "wof:name": "S20 2PP",
    "wof:placetype": "postalcode"
  },
  "geometry": {"coordinates":[-1.333905,53.335487],"type":"Point"}
}
