{
  "type": "Feature",
  "properties": {
    "iso:country":"GB",
    "wof:name":"S20 2PP",
    "wof:placetype":"postalcode"
},
  "geometry": {"coordinates":[-1.3339051840714,53.33548651671481],"type":"Point"}
}