{
  "type": "Feature",
  "properties": {
    "date:inception_lower":"1980-01-01",
    "date:inception_upper":"1980-01-31",
    "iso:country":"GB",
    "wof:name":"CV7 7BU",
    "wof:placetype":"postalcode"
},
  "geometry": {"coordinates":[-1.677012,52.393415],"type":"Point"}
}