{
  "type": "Feature",
  "properties": {
    "iso:country":"GB",
    "wof:name":"CV7 7BU",
    "wof:placetype":"postalcode"
},
  "geometry": {"coordinates":[-1.67701214736833,52.39341530912606],"type":"Point"}
}