{
  "type": "Feature",
  "properties": {
    "iso:country": "GB",
    "wof:name": "LS8 1BW",
    "wof:placetype": "postalcode"
  },
  "geometry": {"coordinates":[-1.505678,53.842717],"type":"Point"}
}
