{
  "type": "Feature",
  "properties": {
    "iso:country":"GB",
    "wof:name":"CO2 8BD",
    "wof:placetype":"postalcode"
},
  "geometry": {"coordinates":[0.92410415818819,51.87118924327965],"type":"Point"}
}