{
  "type": "Feature",
  "properties": {
    "iso:country": "GB",
    "wof:name": "NR12 8RY",
    "wof:placetype": "postalcode"
  },
  "geometry": {"coordinates":[1.402604,52.707936],"type":"Point"}
}
