{
  "type": "Feature",
  "properties": {
    "iso:country": "GB",
    "wof:name": "G84 7PW",
    "wof:placetype": "postalcode"
  },
  "geometry": {"coordinates":[-4.726977,56.00322],"type":"Point"}
}
