{
  "type": "Feature",
  "properties": {
    "iso:country":"GB",
    "wof:name":"NR13 3RE",
    "wof:placetype":"postalcode"
},
  "geometry": {"coordinates":[1.55166694881595,52.64203905875582],"type":"Point"}
}