{
  "type": "Feature",
  "properties": {
    "date:inception_lower": "1980-01-01",
    "date:inception_upper": "1980-01-01",
    "iso:country": "GB",
    "wof:name": "NR13 3RE",
    "wof:placetype": "postalcode"
  },
  "geometry": {"coordinates":[1.551667,52.642039],"type":"Point"}
}
