{
  "type": "Feature",
  "properties": {
    "iso:country":"GB",
    "wof:name":"G76 7HN",
    "wof:placetype":"postalcode"
},
  "geometry": {"coordinates":[-4.28239817683279,55.79328403281477],"type":"Point"}
}