{
  "type": "Feature",
  "properties": {
    "iso:country": "GB",
    "wof:name": "G76 7HN",
    "wof:placetype": "postalcode"
  },
  "geometry": {"coordinates":[-4.282451,55.793314],"type":"Point"}
}
