{
  "type": "Feature",
  "properties": {
    "iso:country":"GB",
    "wof:name":"NE3 3UB",
    "wof:placetype":"postalcode"
},
  "geometry": {"coordinates":[-1.62941163196838,55.00628782175088],"type":"Point"}
}