{
  "type": "Feature",
  "properties": {
    "iso:country": "GB",
    "wof:name": "NE3 3UB",
    "wof:placetype": "postalcode"
  },
  "geometry": {"coordinates":[-1.629412,55.006288],"type":"Point"}
}
