{
  "type": "Feature",
  "properties": {
    "iso:country":"GB",
    "wof:name":"EX15 1LG",
    "wof:placetype":"postalcode"
},
  "geometry": {"coordinates":[-3.39923936298206,50.85561870981326],"type":"Point"}
}