{
  "type": "Feature",
  "properties": {
    "date:inception_lower": "2020-12-01",
    "date:inception_upper": "2020-12-01",
    "iso:country": "GB",
    "wof:name": "TS18 2FT",
    "wof:placetype": "postalcode"
  },
  "geometry": {"coordinates":[-1.310838,54.5687],"type":"Point"}
}
