{
  "type": "Feature",
  "properties": {
    "iso:country":"GB",
    "wof:name":"CV32 7JQ",
    "wof:placetype":"postalcode"
},
  "geometry": {"coordinates":[-1.50357549243103,52.31361063206102],"type":"Point"}
}