{
  "type": "Feature",
  "properties": {
    "date:inception_lower": "1980-01-01",
    "date:inception_upper": "1980-01-01",
    "iso:country": "GB",
    "wof:name": "CV32 7JQ",
    "wof:placetype": "postalcode"
  },
  "geometry": {"coordinates":[-1.503506,52.313644],"type":"Point"}
}
