{
  "type": "Feature",
  "properties": {
    "date:inception_lower": "2021-04-01",
    "date:inception_upper": "2021-04-01",
    "iso:country": "GB",
    "wof:name": "EH17 8YS",
    "wof:placetype": "postalcode"
  },
  "geometry": {"coordinates":[-3.140293,55.897265],"type":"Point"}
}
