{
  "type": "Feature",
  "properties": {
    "iso:country": "GB",
    "wof:name": "HD1 4AL",
    "wof:placetype": "postalcode"
  },
  "geometry": {"coordinates":[-1.788452,53.646467],"type":"Point"}
}
