{
  "type": "Feature",
  "properties": {
    "iso:country": "GB",
    "wof:name": "LL20 7FB",
    "wof:placetype": "postalcode"
  },
  "geometry": {"coordinates":[-3.188384,52.93184],"type":"Point"}
}
