{
  "type": "Feature",
  "properties": {
    "date:inception_lower":"2007-08-01",
    "date:inception_upper":"2007-08-31",
    "iso:country":"GB",
    "wof:name":"LL20 7FB",
    "wof:placetype":"postalcode"
},
  "geometry": {"coordinates":[-3.188384,52.93184],"type":"Point"}
}