{
  "type": "Feature",
  "properties": {
    "iso:country":"GB",
    "wof:name":"LL20 7FB",
    "wof:placetype":"postalcode"
},
  "geometry": {"coordinates":[-3.18838370301168,52.93184020455612],"type":"Point"}
}