{
  "type": "Feature",
  "properties": {
    "iso:country": "GB",
    "wof:name": "PE12 8BH",
    "wof:placetype": "postalcode"
  },
  "geometry": {"coordinates":[0.004272,52.84448],"type":"Point"}
}
