{
  "type": "Feature",
  "properties": {
    "iso:country":"GB",
    "wof:name":"PE12 8BH",
    "wof:placetype":"postalcode"
},
  "geometry": {"coordinates":[0.00415922035509,52.84557869506771],"type":"Point"}
}