{
  "type": "Feature",
  "properties": {
    "iso:country":"GB",
    "wof:name":"RG20 9AE",
    "wof:placetype":"postalcode"
},
  "geometry": {"coordinates":[-1.29817969534921,51.33284241566586],"type":"Point"}
}