{
  "type": "Feature",
  "properties": {
    "iso:country": "GB",
    "wof:name": "RG20 9AE",
    "wof:placetype": "postalcode"
  },
  "geometry": {"coordinates":[-1.29818,51.332842],"type":"Point"}
}
