{
  "type": "Feature",
  "properties": {
    "date:inception_lower": "2020-09-01",
    "date:inception_upper": "2020-09-01",
    "iso:country": "GB",
    "wof:name": "WR11 8AL",
    "wof:placetype": "postalcode"
  },
  "geometry": {"coordinates":[-1.893964,52.160038],"type":"Point"}
}
