{
  "type": "Feature",
  "properties": {
    "date:inception_lower": "2004-06-01",
    "date:inception_upper": "2004-06-01",
    "iso:country": "GB",
    "wof:name": "KY3 0BD",
    "wof:placetype": "postalcode"
  },
  "geometry": {"coordinates":[-3.236544,56.059292],"type":"Point"}
}
