{
  "type": "Feature",
  "properties": {
    "iso:country":"GB",
    "wof:name":"CM2 8SE",
    "wof:placetype":"postalcode"
},
  "geometry": {"coordinates":[0.47619923479149,51.69704558890042],"type":"Point"}
}