{
  "type": "Feature",
  "properties": {
    "iso:country":"GB",
    "wof:name":"DL10 6AB",
    "wof:placetype":"postalcode"
},
  "geometry": {"coordinates":[-1.62399880318727,54.39208647857637],"type":"Point"}
}