{
  "type": "Feature",
  "properties": {
    "iso:country":"GB",
    "wof:name":"SK4 1LY",
    "wof:placetype":"postalcode"
},
  "geometry": {"coordinates":[-2.16883420484798,53.41690823786502],"type":"Point"}
}