{
  "type": "Feature",
  "properties": {
    "iso:country": "GB",
    "wof:name": "LS13 4TJ",
    "wof:placetype": "postalcode"
  },
  "geometry": {"coordinates":[-1.625756,53.800306],"type":"Point"}
}
