{
  "type": "Feature",
  "properties": {
    "iso:country":"GB",
    "wof:name":"SR8 3QA",
    "wof:placetype":"postalcode"
},
  "geometry": {"coordinates":[-1.32506463578401,54.78883721956144],"type":"Point"}
}