{
  "type": "Feature",
  "properties": {
    "iso:country": "GB",
    "wof:name": "SR8 3QA",
    "wof:placetype": "postalcode"
  },
  "geometry": {"coordinates":[-1.325065,54.788837],"type":"Point"}
}
