{
  "type": "Feature",
  "properties": {
    "date:inception_lower": "1980-01-01",
    "date:inception_upper": "1980-01-01",
    "iso:country": "GB",
    "wof:name": "DT9 5HL",
    "wof:placetype": "postalcode"
  },
  "geometry": {"coordinates":[-2.462998,50.968377],"type":"Point"}
}
