{
  "type": "Feature",
  "properties": {
    "date:inception_lower":"1980-01-01",
    "date:inception_upper":"1980-01-31",
    "iso:country":"GB",
    "wof:name":"DT9 5HL",
    "wof:placetype":"postalcode"
},
  "geometry": {"coordinates":[-2.462999,50.968392],"type":"Point"}
}