{
  "type": "Feature",
  "properties": {
    "iso:country":"GB",
    "wof:name":"SM4 6EG",
    "wof:placetype":"postalcode"
},
  "geometry": {"coordinates":[-0.17727545794957,51.39370331496191],"type":"Point"}
}