{
  "type": "Feature",
  "properties": {
    "date:inception_lower":"2007-01-01",
    "date:inception_upper":"2007-01-31",
    "iso:country":"GB",
    "wof:name":"LL13 7ER",
    "wof:placetype":"postalcode"
},
  "geometry": {"coordinates":[-2.993897,53.036081],"type":"Point"}
}