{
  "type": "Feature",
  "properties": {
    "iso:country":"GB",
    "wof:name":"LL13 7ER",
    "wof:placetype":"postalcode"
},
  "geometry": {"coordinates":[-2.99389739740727,53.03608055928453],"type":"Point"}
}