{
  "type": "Feature",
  "properties": {
    "iso:country":"GB",
    "wof:name":"S80 4DD",
    "wof:placetype":"postalcode"
},
  "geometry": {"coordinates":[-1.2184868281068,53.26202113137548],"type":"Point"}
}