{
  "type": "Feature",
  "properties": {
    "iso:country":"GB",
    "wof:name":"TR26 3BW",
    "wof:placetype":"postalcode"
},
  "geometry": {"coordinates":[-5.54231473023969,50.20111178473064],"type":"Point"}
}