{
  "type": "Feature",
  "properties": {
    "iso:country": "GB",
    "wof:name": "TR26 3BW",
    "wof:placetype": "postalcode"
  },
  "geometry": {"coordinates":[-5.542315,50.201112],"type":"Point"}
}
