{
  "type": "Feature",
  "properties": {
    "iso:country":"GB",
    "wof:name":"LA12 7AL",
    "wof:placetype":"postalcode"
},
  "geometry": {"coordinates":[-3.09506378389939,54.19445796010454],"type":"Point"}
}