{
  "type": "Feature",
  "properties": {
    "iso:country": "GB",
    "wof:name": "LA12 7AL",
    "wof:placetype": "postalcode"
  },
  "geometry": {"coordinates":[-3.095064,54.194458],"type":"Point"}
}
