{
  "type": "Feature",
  "properties": {
    "iso:country": "GB",
    "wof:name": "BA2 6RJ",
    "wof:placetype": "postalcode"
  },
  "geometry": {"coordinates":[-2.339649,51.389578],"type":"Point"}
}
