{
  "type": "Feature",
  "properties": {
    "iso:country":"GB",
    "wof:name":"BA2 6RJ",
    "wof:placetype":"postalcode"
},
  "geometry": {"coordinates":[-2.3396493824117,51.38957824407889],"type":"Point"}
}