{
  "type": "Feature",
  "properties": {
    "date:inception_lower": "2018-02-01",
    "date:inception_upper": "2018-02-01",
    "iso:country": "GB",
    "wof:name": "TN6 9BU",
    "wof:placetype": "postalcode"
  },
  "geometry": {"coordinates":[0.160735,51.060213],"type":"Point"}
}
