{
  "type": "Feature",
  "properties": {
    "iso:country":"GB",
    "wof:name":"TN6 9BU",
    "wof:placetype":"postalcode"
},
  "geometry": {"coordinates":[0.16070708948827,51.06021634802138],"type":"Point"}
}