{
  "type": "Feature",
  "properties": {
    "iso:country":"GB",
    "wof:name":"W3 8JT",
    "wof:placetype":"postalcode"
},
  "geometry": {"coordinates":[-0.27256550016767,51.50611361604249],"type":"Point"}
}