{
  "type": "Feature",
  "properties": {
    "date:inception_lower":"1996-06-01",
    "date:inception_upper":"1996-06-30",
    "iso:country":"GB",
    "wof:name":"AB54 8LF",
    "wof:placetype":"postalcode"
},
  "geometry": {"coordinates":[-2.795025,57.447969],"type":"Point"}
}