{
  "type": "Feature",
  "properties": {
    "iso:country":"GB",
    "wof:name":"WD6 3EY",
    "wof:placetype":"postalcode"
},
  "geometry": {"coordinates":[-0.29793376515245,51.64460539804715],"type":"Point"}
}