{
  "type": "Feature",
  "properties": {
    "date:inception_lower":"1980-01-01",
    "date:inception_upper":"1980-01-31",
    "iso:country":"GB",
    "wof:name":"WD6 3EY",
    "wof:placetype":"postalcode"
},
  "geometry": {"coordinates":[-0.297934,51.644605],"type":"Point"}
}