{
  "type": "Feature",
  "properties": {
    "iso:country": "GB",
    "wof:name": "EX36 3PF",
    "wof:placetype": "postalcode"
  },
  "geometry": {"coordinates":[-3.641044,51.024272],"type":"Point"}
}
