{
  "type": "Feature",
  "properties": {
    "iso:country": "GB",
    "wof:name": "SL6 5HG",
    "wof:placetype": "postalcode"
  },
  "geometry": {"coordinates":[-0.749963,51.529041],"type":"Point"}
}
