{
  "type": "Feature",
  "properties": {
    "iso:country":"GB",
    "wof:name":"SL6 5HG",
    "wof:placetype":"postalcode"
},
  "geometry": {"coordinates":[-0.74996266643702,51.52904127652351],"type":"Point"}
}