{
  "type": "Feature",
  "properties": {
    "date:inception_lower": "1980-01-01",
    "date:inception_upper": "1980-01-01",
    "iso:country": "GB",
    "wof:name": "NG3 6FR",
    "wof:placetype": "postalcode"
  },
  "geometry": {"coordinates":[-1.111857,52.978034],"type":"Point"}
}
