{
  "type": "Feature",
  "properties": {
    "iso:country":"GB",
    "wof:name":"NG3 6FR",
    "wof:placetype":"postalcode"
},
  "geometry": {"coordinates":[-1.11171356465231,52.9779045256843],"type":"Point"}
}