{
  "type": "Feature",
  "properties": {
    "iso:country":"GB",
    "wof:name":"HA7 1QP",
    "wof:placetype":"postalcode"
},
  "geometry": {"coordinates":[-0.29712079566761,51.60456942642517],"type":"Point"}
}