{
  "type": "Feature",
  "properties": {
    "iso:country":"GB",
    "wof:name":"EC1Y 8RZ",
    "wof:placetype":"postalcode"
},
  "geometry": {"coordinates":[-0.09004059453541,51.52464953509394],"type":"Point"}
}