{
  "type": "Feature",
  "properties": {
    "iso:country": "GB",
    "wof:name": "EC1Y 8RZ",
    "wof:placetype": "postalcode"
  },
  "geometry": {"coordinates":[-0.090101,51.524644],"type":"Point"}
}
