{
  "type": "Feature",
  "properties": {
    "date:inception_lower":"1999-12-01",
    "date:inception_upper":"1999-12-31",
    "iso:country":"GB",
    "wof:name":"EC1Y 8RZ",
    "wof:placetype":"postalcode"
},
  "geometry": {"coordinates":[-0.090014,51.524651],"type":"Point"}
}