{
  "type": "Feature",
  "properties": {
    "iso:country":"GB",
    "wof:name":"WC1X 8BA",
    "wof:placetype":"postalcode"
},
  "geometry": {"coordinates":[-0.11348585466222,51.52207940418973],"type":"Point"}
}