{
  "type": "Feature",
  "properties": {
    "iso:country": "GB",
    "wof:name": "WC1X 8BA",
    "wof:placetype": "postalcode"
  },
  "geometry": {"coordinates":[-0.113486,51.522079],"type":"Point"}
}
