{
  "type": "Feature",
  "properties": {
    "date:inception_lower":"1986-07-01",
    "date:inception_upper":"1986-07-31",
    "iso:country":"GB",
    "wof:name":"MK17 9PB",
    "wof:placetype":"postalcode"
},
  "geometry": {"coordinates":[-0.680638,51.983879],"type":"Point"}
}