{
  "type": "Feature",
  "properties": {
    "iso:country":"GB",
    "wof:name":"MK17 9PB",
    "wof:placetype":"postalcode"
},
  "geometry": {"coordinates":[-0.68063829440228,51.98387880424516],"type":"Point"}
}