{
  "type": "Feature",
  "properties": {
    "iso:country":"GB",
    "wof:name":"WN7 3UP",
    "wof:placetype":"postalcode"
},
  "geometry": {"coordinates":[-2.52986282255205,53.48740958676689],"type":"Point"}
}