{
  "type": "Feature",
  "properties": {
    "iso:country": "GB",
    "wof:name": "AB56 4PB",
    "wof:placetype": "postalcode"
  },
  "geometry": {"coordinates":[-2.878358,57.70004],"type":"Point"}
}
