{
  "type": "Feature",
  "properties": {
    "iso:country":"GB",
    "wof:name":"AB56 4PB",
    "wof:placetype":"postalcode"
},
  "geometry": {"coordinates":[-2.87835853508676,57.70004023990199],"type":"Point"}
}