{
  "type": "Feature",
  "properties": {
    "iso:country": "GB",
    "wof:name": "DH8 5YN",
    "wof:placetype": "postalcode"
  },
  "geometry": {"coordinates":[-1.845457,54.850186],"type":"Point"}
}
