{
  "type": "Feature",
  "properties": {
    "iso:country":"GB",
    "wof:name":"DH8 5YN",
    "wof:placetype":"postalcode"
},
  "geometry": {"coordinates":[-1.8454566994859,54.85018571542563],"type":"Point"}
}