{
  "type": "Feature",
  "properties": {
    "date:inception_lower": "1980-01-01",
    "date:inception_upper": "1980-01-01",
    "iso:country": "GB",
    "wof:name": "WA16 0TS",
    "wof:placetype": "postalcode"
  },
  "geometry": {"coordinates":[-2.422542,53.276476],"type":"Point"}
}
