{
  "type": "Feature",
  "properties": {
    "iso:country": "GB",
    "wof:name": "WA16 0TS",
    "wof:placetype": "postalcode"
  },
  "geometry": {"coordinates":[-2.422542,53.276476],"type":"Point"}
}
