{
  "type": "Feature",
  "properties": {
    "iso:country": "GB",
    "wof:name": "NR13 3DN",
    "wof:placetype": "postalcode"
  },
  "geometry": {"coordinates":[1.548407,52.632198],"type":"Point"}
}
