{
  "type": "Feature",
  "properties": {
    "date:inception_lower": "2019-07-01",
    "date:inception_upper": "2019-07-01",
    "iso:country": "GB",
    "wof:name": "NR13 3DN",
    "wof:placetype": "postalcode"
  },
  "geometry": {"coordinates":[1.543958,52.634031],"type":"Point"}
}
