{
  "type": "Feature",
  "properties": {
    "iso:country": "GB",
    "wof:name": "CM22 6NY",
    "wof:placetype": "postalcode"
  },
  "geometry": {"coordinates":[0.279801,51.873772],"type":"Point"}
}
