{
  "type": "Feature",
  "properties": {
    "iso:country":"GB",
    "wof:name":"CM22 6NY",
    "wof:placetype":"postalcode"
},
  "geometry": {"coordinates":[0.27980107184385,51.87377190965531],"type":"Point"}
}