{
  "type": "Feature",
  "properties": {
    "iso:country": "GB",
    "wof:name": "BB10 4TL",
    "wof:placetype": "postalcode"
  },
  "geometry": {"coordinates":[-2.19701,53.766258],"type":"Point"}
}
