{
  "type": "Feature",
  "properties": {
    "iso:country":"GB",
    "wof:name":"BB10 4TL",
    "wof:placetype":"postalcode"
},
  "geometry": {"coordinates":[-2.19701037408877,53.76625754539215],"type":"Point"}
}