{
  "type": "Feature",
  "properties": {
    "iso:country":"GB",
    "wof:name":"PR4 3DL",
    "wof:placetype":"postalcode"
},
  "geometry": {"coordinates":[-2.88942119687365,53.78903192907961],"type":"Point"}
}