{
  "type": "Feature",
  "properties": {
    "iso:country": "GB",
    "wof:name": "PR4 3DL",
    "wof:placetype": "postalcode"
  },
  "geometry": {"coordinates":[-2.889421,53.789032],"type":"Point"}
}
