{
  "type": "Feature",
  "properties": {
    "iso:country":"GB",
    "wof:name":"SP5 3AP",
    "wof:placetype":"postalcode"
},
  "geometry": {"coordinates":[-1.74081605065143,51.04807432039974],"type":"Point"}
}