{
  "type": "Feature",
  "properties": {
    "iso:country":"GB",
    "wof:name":"PO1 5HS",
    "wof:placetype":"postalcode"
},
  "geometry": {"coordinates":[-1.07456209368907,50.80292446766844],"type":"Point"}
}