{
  "type": "Feature",
  "properties": {
    "date:inception_lower": "1980-01-01",
    "date:inception_upper": "1980-01-01",
    "iso:country": "GB",
    "wof:name": "CA14 4QA",
    "wof:placetype": "postalcode"
  },
  "geometry": {"coordinates":[-3.517432,54.58395],"type":"Point"}
}
