{
  "type": "Feature",
  "properties": {
    "iso:country":"GB",
    "wof:name":"DL1 4TT",
    "wof:placetype":"postalcode"
},
  "geometry": {"coordinates":[-1.53275952008048,54.5174072873201],"type":"Point"}
}