{
  "type": "Feature",
  "properties": {
    "iso:country":"GB",
    "wof:name":"LN4 3ED",
    "wof:placetype":"postalcode"
},
  "geometry": {"coordinates":[-0.40521428796847,53.14272225044543],"type":"Point"}
}