{
  "type": "Feature",
  "properties": {
    "iso:country": "GB",
    "wof:name": "BD23 2AY",
    "wof:placetype": "postalcode"
  },
  "geometry": {"coordinates":[-2.02334,53.955702],"type":"Point"}
}
