{
  "type": "Feature",
  "properties": {
    "date:inception_lower": "2000-12-01",
    "date:inception_upper": "2000-12-01",
    "iso:country": "GB",
    "wof:name": "CH7 3NR",
    "wof:placetype": "postalcode"
  },
  "geometry": {"coordinates":[-3.086551,53.178706],"type":"Point"}
}
