{
  "type": "Feature",
  "properties": {
    "iso:country":"GB",
    "wof:name":"CH7 3NR",
    "wof:placetype":"postalcode"
},
  "geometry": {"coordinates":[-3.08655075251213,53.17870578909079],"type":"Point"}
}