{
  "type": "Feature",
  "properties": {
    "iso:country":"GB",
    "wof:name":"B14 5HJ",
    "wof:placetype":"postalcode"
},
  "geometry": {"coordinates":[-1.88555257347231,52.41070201420447],"type":"Point"}
}