{
  "type": "Feature",
  "properties": {
    "iso:country":"GB",
    "wof:name":"AL5 2EB",
    "wof:placetype":"postalcode"
},
  "geometry": {"coordinates":[-0.37073555950246,51.81414725452956],"type":"Point"}
}