{
  "type": "Feature",
  "properties": {
    "date:inception_lower":"1994-05-01",
    "date:inception_upper":"1994-05-31",
    "iso:country":"GB",
    "wof:name":"NN29 7PB",
    "wof:placetype":"postalcode"
},
  "geometry": {"coordinates":[-0.668136,52.237539],"type":"Point"}
}