{
  "type": "Feature",
  "properties": {
    "iso:country": "GB",
    "wof:name": "NN29 7PB",
    "wof:placetype": "postalcode"
  },
  "geometry": {"coordinates":[-0.668136,52.237539],"type":"Point"}
}
