{
  "type": "Feature",
  "properties": {
    "iso:country":"GB",
    "wof:name":"NN29 7PB",
    "wof:placetype":"postalcode"
},
  "geometry": {"coordinates":[-0.66813626410085,52.23753938438603],"type":"Point"}
}