{
  "type": "Feature",
  "properties": {
    "iso:country":"GB",
    "wof:name":"NW4 3NE",
    "wof:placetype":"postalcode"
},
  "geometry": {"coordinates":[-0.22564506490314,51.58070628541342],"type":"Point"}
}