{
  "type": "Feature",
  "properties": {
    "iso:country": "GB",
    "wof:name": "KY1 1AF",
    "wof:placetype": "postalcode"
  },
  "geometry": {"coordinates":[-3.167381,56.098695],"type":"Point"}
}
