{
  "type": "Feature",
  "properties": {
    "iso:country": "GB",
    "wof:name": "ML1 5NS",
    "wof:placetype": "postalcode"
  },
  "geometry": {"coordinates":[-3.906848,55.803396],"type":"Point"}
}
