{
  "type": "Feature",
  "properties": {
    "date:inception_lower":"1980-01-01",
    "date:inception_upper":"1980-01-31",
    "iso:country":"GB",
    "wof:name":"ML1 5NS",
    "wof:placetype":"postalcode"
},
  "geometry": {"coordinates":[-3.906848,55.803396],"type":"Point"}
}