{
  "type": "Feature",
  "properties": {
    "iso:country":"GB",
    "wof:name":"ML1 5NS",
    "wof:placetype":"postalcode"
},
  "geometry": {"coordinates":[-3.90684792168877,55.80339579072281],"type":"Point"}
}