{
  "type": "Feature",
  "properties": {
    "iso:country":"GB",
    "wof:name":"WA9 1TE",
    "wof:placetype":"postalcode"
},
  "geometry": {"coordinates":[-2.70791011791047,53.45208768960671],"type":"Point"}
}