{
  "type": "Feature",
  "properties": {
    "date:inception_lower":"1980-01-01",
    "date:inception_upper":"1980-01-31",
    "iso:country":"GB",
    "wof:name":"WA9 1TE",
    "wof:placetype":"postalcode"
},
  "geometry": {"coordinates":[-2.70791,53.452088],"type":"Point"}
}