{
  "type": "Feature",
  "properties": {
    "iso:country":"GB",
    "wof:name":"WC1B 3NA",
    "wof:placetype":"postalcode"
},
  "geometry": {"coordinates":[-0.12932493678051,51.51757604248763],"type":"Point"}
}