{
  "type": "Feature",
  "properties": {
    "iso:country":"GB",
    "wof:name":"FY1 6DL",
    "wof:placetype":"postalcode"
},
  "geometry": {"coordinates":[-3.05198193870014,53.80324758805664],"type":"Point"}
}