{
  "type": "Feature",
  "properties": {
    "iso:country": "GB",
    "wof:name": "FY1 6DL",
    "wof:placetype": "postalcode"
  },
  "geometry": {"coordinates":[-3.05201,53.803289],"type":"Point"}
}
