{
  "type": "Feature",
  "properties": {
    "iso:country": "GB",
    "wof:name": "BB10 1HY",
    "wof:placetype": "postalcode"
  },
  "geometry": {"coordinates":[-2.23951,53.807471],"type":"Point"}
}
