{
  "type": "Feature",
  "properties": {
    "iso:country":"GB",
    "wof:name":"LA2 8QD",
    "wof:placetype":"postalcode"
},
  "geometry": {"coordinates":[-2.60761108078984,54.10143093865173],"type":"Point"}
}