{
  "type": "Feature",
  "properties": {
    "date:inception_lower":"1980-01-01",
    "date:inception_upper":"1980-01-31",
    "iso:country":"GB",
    "wof:name":"LA2 8QD",
    "wof:placetype":"postalcode"
},
  "geometry": {"coordinates":[-2.607704,54.101487],"type":"Point"}
}