{
  "type": "Feature",
  "properties": {
    "iso:country":"GB",
    "wof:name":"LD1 5HF",
    "wof:placetype":"postalcode"
},
  "geometry": {"coordinates":[-3.3774458306187,52.24210803587179],"type":"Point"}
}