{
  "type": "Feature",
  "properties": {
    "iso:country":"GB",
    "wof:name":"BS4 2LA",
    "wof:placetype":"postalcode"
},
  "geometry": {"coordinates":[-2.5662364491383,51.43536888940125],"type":"Point"}
}