{
  "type": "Feature",
  "properties": {
    "date:inception_lower": "1980-01-01",
    "date:inception_upper": "1980-01-01",
    "iso:country": "GB",
    "wof:name": "BS4 2LA",
    "wof:placetype": "postalcode"
  },
  "geometry": {"coordinates":[-2.566236,51.435369],"type":"Point"}
}
