{
  "type": "Feature",
  "properties": {
    "iso:country": "GB",
    "wof:name": "DL1 3JJ",
    "wof:placetype": "postalcode"
  },
  "geometry": {"coordinates":[-1.511053,54.542999],"type":"Point"}
}
