{
  "type": "Feature",
  "properties": {
    "iso:country":"GB",
    "wof:name":"DL1 3JJ",
    "wof:placetype":"postalcode"
},
  "geometry": {"coordinates":[-1.51104377187908,54.54298825168499],"type":"Point"}
}