{
  "type": "Feature",
  "properties": {
    "date:inception_lower": "1980-01-01",
    "date:inception_upper": "1980-01-01",
    "iso:country": "GB",
    "wof:name": "DL1 3JJ",
    "wof:placetype": "postalcode"
  },
  "geometry": {"coordinates":[-1.511053,54.542999],"type":"Point"}
}
