{
  "type": "Feature",
  "properties": {
    "iso:country": "GB",
    "wof:name": "NP18 2PH",
    "wof:placetype": "postalcode"
  },
  "geometry": {"coordinates":[-2.901571,51.538059],"type":"Point"}
}
