{
  "type": "Feature",
  "properties": {
    "iso:country":"GB",
    "wof:name":"NP20 9NW",
    "wof:placetype":"postalcode"
},
  "geometry": {"coordinates":[-2.99704690833976,51.59127177635087],"type":"Point"}
}