{
  "type": "Feature",
  "properties": {
    "date:inception_lower": "1980-01-01",
    "date:inception_upper": "1980-01-01",
    "iso:country": "GB",
    "wof:name": "BH9 1NH",
    "wof:placetype": "postalcode"
  },
  "geometry": {"coordinates":[-1.87457,50.74543],"type":"Point"}
}
