{
  "type": "Feature",
  "properties": {
    "iso:country":"GB",
    "wof:name":"PO9 2GE",
    "wof:placetype":"postalcode"
},
  "geometry": {"coordinates":[-0.97592685031356,50.85386304531491],"type":"Point"}
}