{
  "type": "Feature",
  "properties": {
    "iso:country": "GB",
    "wof:name": "PO9 2GE",
    "wof:placetype": "postalcode"
  },
  "geometry": {"coordinates":[-0.975912,50.853808],"type":"Point"}
}
