{
  "type": "Feature",
  "properties": {
    "iso:country":"GB",
    "wof:name":"OX1 3QR",
    "wof:placetype":"postalcode"
},
  "geometry": {"coordinates":[-1.25486340140198,51.75828062127123],"type":"Point"}
}