{
  "type": "Feature",
  "properties": {
    "iso:country": "GB",
    "wof:name": "YO13 9PN",
    "wof:placetype": "postalcode"
  },
  "geometry": {"coordinates":[-0.604902,54.233085],"type":"Point"}
}
