{
  "type": "Feature",
  "properties": {
    "iso:country": "GB",
    "wof:name": "AB41 8UE",
    "wof:placetype": "postalcode"
  },
  "geometry": {"coordinates":[-2.090781,57.484264],"type":"Point"}
}
