{
  "type": "Feature",
  "properties": {
    "iso:country":"GB",
    "wof:name":"AB41 8UE",
    "wof:placetype":"postalcode"
},
  "geometry": {"coordinates":[-2.0907813743752,57.48426352862456],"type":"Point"}
}