{
  "type": "Feature",
  "properties": {
    "iso:country": "GB",
    "wof:name": "CT14 9QF",
    "wof:placetype": "postalcode"
  },
  "geometry": {"coordinates":[1.390813,51.223267],"type":"Point"}
}
