{
  "type": "Feature",
  "properties": {
    "iso:country": "GB",
    "wof:name": "SA2 0DG",
    "wof:placetype": "postalcode"
  },
  "geometry": {"coordinates":[-3.973435,51.613902],"type":"Point"}
}
