{
  "type": "Feature",
  "properties": {
    "iso:country":"GB",
    "wof:name":"SA2 0DG",
    "wof:placetype":"postalcode"
},
  "geometry": {"coordinates":[-3.97343531286168,51.61390217501408],"type":"Point"}
}