{
  "type": "Feature",
  "properties": {
    "date:inception_lower":"2001-12-01",
    "date:inception_upper":"2001-12-31",
    "iso:country":"GB",
    "wof:name":"SA2 0DG",
    "wof:placetype":"postalcode"
},
  "geometry": {"coordinates":[-3.973435,51.613902],"type":"Point"}
}