{
  "type": "Feature",
  "properties": {
    "iso:country":"GB",
    "wof:name":"EN3 7AB",
    "wof:placetype":"postalcode"
},
  "geometry": {"coordinates":[-0.04267932620669,51.64770480146682],"type":"Point"}
}