{
  "type": "Feature",
  "properties": {
    "iso:country": "GB",
    "wof:name": "ME4 3SU",
    "wof:placetype": "postalcode"
  },
  "geometry": {"coordinates":[0.539113,51.409928],"type":"Point"}
}
