{
  "type": "Feature",
  "properties": {
    "iso:country":"GB",
    "wof:name":"ME4 3SU",
    "wof:placetype":"postalcode"
},
  "geometry": {"coordinates":[0.5391132223356,51.40992846010592],"type":"Point"}
}