{
  "type": "Feature",
  "properties": {
    "iso:country":"GB",
    "wof:name":"W14 8HS",
    "wof:placetype":"postalcode"
},
  "geometry": {"coordinates":[-0.21080400002716,51.49990914704787],"type":"Point"}
}