{
  "type": "Feature",
  "properties": {
    "date:inception_lower": "1980-01-01",
    "date:inception_upper": "1980-01-01",
    "iso:country": "GB",
    "wof:name": "CT3 3DU",
    "wof:placetype": "postalcode"
  },
  "geometry": {"coordinates":[1.197557,51.224472],"type":"Point"}
}
