{
  "type": "Feature",
  "properties": {
    "iso:country":"GB",
    "wof:name":"CT3 3DU",
    "wof:placetype":"postalcode"
},
  "geometry": {"coordinates":[1.19767354192901,51.22431010310136],"type":"Point"}
}