{
  "type": "Feature",
  "properties": {
    "iso:country":"GB",
    "wof:name":"OL5 0QH",
    "wof:placetype":"postalcode"
},
  "geometry": {"coordinates":[-2.04587242185682,53.52054803848766],"type":"Point"}
}