{
  "type": "Feature",
  "properties": {
    "iso:country":"GB",
    "wof:name":"S75 4NJ",
    "wof:placetype":"postalcode"
},
  "geometry": {"coordinates":[-1.58220825923148,53.54811450756818],"type":"Point"}
}