{
  "type": "Feature",
  "properties": {
    "iso:country": "GB",
    "wof:name": "S75 4NJ",
    "wof:placetype": "postalcode"
  },
  "geometry": {"coordinates":[-1.582208,53.548115],"type":"Point"}
}
