{
  "type": "Feature",
  "properties": {
    "iso:country":"GB",
    "wof:name":"HX7 8HR",
    "wof:placetype":"postalcode"
},
  "geometry": {"coordinates":[-2.00991003398118,53.74734684024297],"type":"Point"}
}