{
  "type": "Feature",
  "properties": {
    "iso:country": "GB",
    "wof:name": "HX7 8HR",
    "wof:placetype": "postalcode"
  },
  "geometry": {"coordinates":[-2.00991,53.747347],"type":"Point"}
}
