{
  "type": "Feature",
  "properties": {
    "iso:country": "GB",
    "wof:name": "WV3 8ET",
    "wof:placetype": "postalcode"
  },
  "geometry": {"coordinates":[-2.172752,52.575839],"type":"Point"}
}
