{
  "type": "Feature",
  "properties": {
    "iso:country":"GB",
    "wof:name":"WV3 8ET",
    "wof:placetype":"postalcode"
},
  "geometry": {"coordinates":[-2.17275166547042,52.57583884058597],"type":"Point"}
}