{
  "type": "Feature",
  "properties": {
    "iso:country": "GB",
    "wof:name": "HR3 5SN",
    "wof:placetype": "postalcode"
  },
  "geometry": {"coordinates":[-3.154021,52.099013],"type":"Point"}
}
