{
  "type": "Feature",
  "properties": {
    "date:inception_lower": "1991-09-01",
    "date:inception_upper": "1991-09-01",
    "iso:country": "GB",
    "wof:name": "BH31 6DX",
    "wof:placetype": "postalcode"
  },
  "geometry": {"coordinates":[-1.873836,50.871325],"type":"Point"}
}
