{
  "type": "Feature",
  "properties": {
    "iso:country":"GB",
    "wof:name":"TR2 5QE",
    "wof:placetype":"postalcode"
},
  "geometry": {"coordinates":[-4.91845218465518,50.22220951174577],"type":"Point"}
}