{
  "type": "Feature",
  "properties": {
    "iso:country": "GB",
    "wof:name": "OX9 3XS",
    "wof:placetype": "postalcode"
  },
  "geometry": {"coordinates":[-0.96957,51.748016],"type":"Point"}
}
