{
  "type": "Feature",
  "properties": {
    "date:inception_lower": "1981-06-01",
    "date:inception_upper": "1981-06-01",
    "iso:country": "GB",
    "wof:name": "OX9 3XS",
    "wof:placetype": "postalcode"
  },
  "geometry": {"coordinates":[-0.96957,51.748016],"type":"Point"}
}
