{
  "type": "Feature",
  "properties": {
    "iso:country":"GB",
    "wof:name":"DN21 4DQ",
    "wof:placetype":"postalcode"
},
  "geometry": {"coordinates":[-0.59388163138508,53.47349355409001],"type":"Point"}
}