{
  "type": "Feature",
  "properties": {
    "date:inception_lower": "1990-02-01",
    "date:inception_upper": "1990-02-01",
    "iso:country": "GB",
    "wof:name": "GU27 1SP",
    "wof:placetype": "postalcode"
  },
  "geometry": {"coordinates":[-0.70907,51.094192],"type":"Point"}
}
