{
  "type": "Feature",
  "properties": {
    "date:inception_lower":"1995-12-01",
    "date:inception_upper":"1995-12-31",
    "iso:country":"GB",
    "wof:name":"BL8 3HH",
    "wof:placetype":"postalcode"
},
  "geometry": {"coordinates":[-2.339239,53.610839],"type":"Point"}
}