{
  "type": "Feature",
  "properties": {
    "iso:country":"GB",
    "wof:name":"BL8 3HH",
    "wof:placetype":"postalcode"
},
  "geometry": {"coordinates":[-2.33923930331236,53.61083933370072],"type":"Point"}
}