{
  "type": "Feature",
  "properties": {
    "date:inception_lower":"1980-01-01",
    "date:inception_upper":"1980-01-31",
    "iso:country":"GB",
    "wof:name":"PO9 2HF",
    "wof:placetype":"postalcode"
},
  "geometry": {"coordinates":[-0.97584,50.861722],"type":"Point"}
}