{
  "type": "Feature",
  "properties": {
    "iso:country":"GB",
    "wof:name":"PO9 2HF",
    "wof:placetype":"postalcode"
},
  "geometry": {"coordinates":[-0.97583999713832,50.86172194455929],"type":"Point"}
}