{
  "type": "Feature",
  "properties": {
    "iso:country": "GB",
    "wof:name": "SN10 1RS",
    "wof:placetype": "postalcode"
  },
  "geometry": {"coordinates":[-2.047052,51.33978],"type":"Point"}
}
