{
  "type": "Feature",
  "properties": {
    "iso:country": "GB",
    "wof:name": "SE25 5JR",
    "wof:placetype": "postalcode"
  },
  "geometry": {"coordinates":[-0.07219,51.396977],"type":"Point"}
}
