{
  "type": "Feature",
  "properties": {
    "iso:country":"GB",
    "wof:name":"SE25 5JR",
    "wof:placetype":"postalcode"
},
  "geometry": {"coordinates":[-0.07219005175281,51.39697650724526],"type":"Point"}
}