{
  "type": "Feature",
  "properties": {
    "iso:country":"GB",
    "wof:name":"EH4 4GZ",
    "wof:placetype":"postalcode"
},
  "geometry": {"coordinates":[-3.24286994516936,55.97383980987638],"type":"Point"}
}