{
  "type": "Feature",
  "properties": {
    "iso:country": "GB",
    "wof:name": "EH4 4GZ",
    "wof:placetype": "postalcode"
  },
  "geometry": {"coordinates":[-3.24287,55.97384],"type":"Point"}
}
