{
  "type": "Feature",
  "properties": {
    "iso:country":"GB",
    "wof:name":"W1T 7QQ",
    "wof:placetype":"postalcode"
},
  "geometry": {"coordinates":[-0.13240693329346,51.51904597270538],"type":"Point"}
}