{
  "type": "Feature",
  "properties": {
    "iso:country": "GB",
    "wof:name": "BD22 0RH",
    "wof:placetype": "postalcode"
  },
  "geometry": {"coordinates":[-1.964682,53.850479],"type":"Point"}
}
