{
  "type": "Feature",
  "properties": {
    "iso:country":"GB",
    "wof:name":"SW19 5NJ",
    "wof:placetype":"postalcode"
},
  "geometry": {"coordinates":[-0.22413902283219,51.43740729652693],"type":"Point"}
}