{
  "type": "Feature",
  "properties": {
    "iso:country": "GB",
    "wof:name": "SW19 5NJ",
    "wof:placetype": "postalcode"
  },
  "geometry": {"coordinates":[-0.224115,51.437407],"type":"Point"}
}
