{
  "type": "Feature",
  "properties": {
    "iso:country": "GB",
    "wof:name": "NR26 8HB",
    "wof:placetype": "postalcode"
  },
  "geometry": {"coordinates":[1.205889,52.942294],"type":"Point"}
}
