{
  "type": "Feature",
  "properties": {
    "iso:country": "GB",
    "wof:name": "WA14 5YP",
    "wof:placetype": "postalcode"
  },
  "geometry": {"coordinates":[-2.364535,53.408156],"type":"Point"}
}
