{
  "type": "Feature",
  "properties": {
    "iso:country":"GB",
    "wof:name":"WA14 5YP",
    "wof:placetype":"postalcode"
},
  "geometry": {"coordinates":[-2.36453481233167,53.4081563839608],"type":"Point"}
}