{
  "type": "Feature",
  "properties": {
    "iso:country": "GB",
    "wof:name": "PO15 6BD",
    "wof:placetype": "postalcode"
  },
  "geometry": {"coordinates":[-1.203212,50.860878],"type":"Point"}
}
