{
  "type": "Feature",
  "properties": {
    "date:inception_lower": "1980-01-01",
    "date:inception_upper": "1980-01-01",
    "iso:country": "GB",
    "wof:name": "PO15 6BD",
    "wof:placetype": "postalcode"
  },
  "geometry": {"coordinates":[-1.203212,50.860878],"type":"Point"}
}
