{
  "type": "Feature",
  "properties": {
    "iso:country":"GB",
    "wof:name":"PO15 6BD",
    "wof:placetype":"postalcode"
},
  "geometry": {"coordinates":[-1.20321165333948,50.86087831685214],"type":"Point"}
}