{
  "type": "Feature",
  "properties": {
    "iso:country": "GB",
    "wof:name": "B47 5JP",
    "wof:placetype": "postalcode"
  },
  "geometry": {"coordinates":[-1.87929,52.389084],"type":"Point"}
}
