{
  "type": "Feature",
  "properties": {
    "iso:country":"GB",
    "wof:name":"B47 5JP",
    "wof:placetype":"postalcode"
},
  "geometry": {"coordinates":[-1.87929001348839,52.38908363517231],"type":"Point"}
}