{
  "type": "Feature",
  "properties": {
    "iso:country": "GB",
    "wof:name": "KA5 5RA",
    "wof:placetype": "postalcode"
  },
  "geometry": {"coordinates":[-4.486846,55.513889],"type":"Point"}
}
