{
  "type": "Feature",
  "properties": {
    "date:inception_lower": "1980-01-01",
    "date:inception_upper": "1980-01-01",
    "iso:country": "GB",
    "wof:name": "KA5 5RA",
    "wof:placetype": "postalcode"
  },
  "geometry": {"coordinates":[-4.486846,55.513889],"type":"Point"}
}
