{
  "type": "Feature",
  "properties": {
    "iso:country": "GB",
    "wof:name": "DH6 4DU",
    "wof:placetype": "postalcode"
  },
  "geometry": {"coordinates":[-1.506463,54.713396],"type":"Point"}
}
