{
  "type": "Feature",
  "properties": {
    "date:inception_lower":"1980-01-01",
    "date:inception_upper":"1980-01-31",
    "iso:country":"GB",
    "wof:name":"DH6 4DU",
    "wof:placetype":"postalcode"
},
  "geometry": {"coordinates":[-1.50626,54.713477],"type":"Point"}
}