{
  "type": "Feature",
  "properties": {
    "iso:country":"GB",
    "wof:name":"G81 2NW",
    "wof:placetype":"postalcode"
},
  "geometry": {"coordinates":[-4.4020119329804,55.90763915186481],"type":"Point"}
}