{
  "type": "Feature",
  "properties": {
    "date:inception_lower": "1980-10-01",
    "date:inception_upper": "1980-10-01",
    "iso:country": "GB",
    "wof:name": "G81 2NW",
    "wof:placetype": "postalcode"
  },
  "geometry": {"coordinates":[-4.402012,55.907639],"type":"Point"}
}
