{
  "type": "Feature",
  "properties": {
    "date:inception_lower":"2003-03-01",
    "date:inception_upper":"2003-03-31",
    "iso:country":"GB",
    "wof:name":"WS7 1FP",
    "wof:placetype":"postalcode"
},
  "geometry": {"coordinates":[-1.948981,52.685072],"type":"Point"}
}