{
  "type": "Feature",
  "properties": {
    "iso:country":"GB",
    "wof:name":"WS7 1FP",
    "wof:placetype":"postalcode"
},
  "geometry": {"coordinates":[-1.94898065565387,52.68507167681913],"type":"Point"}
}