{
  "type": "Feature",
  "properties": {
    "iso:country": "GB",
    "wof:name": "DG11 3JB",
    "wof:placetype": "postalcode"
  },
  "geometry": {"coordinates":[-3.293421,55.074888],"type":"Point"}
}
