{
  "type": "Feature",
  "properties": {
    "iso:country":"GB",
    "wof:name":"EX24 6JY",
    "wof:placetype":"postalcode"
},
  "geometry": {"coordinates":[-3.07096329052835,50.74080173441658],"type":"Point"}
}