{
  "type": "Feature",
  "properties": {
    "date:inception_lower": "2023-04-01",
    "date:inception_upper": "2023-04-01",
    "iso:country": "GB",
    "wof:name": "SE18 9RL",
    "wof:placetype": "postalcode"
  },
  "geometry": {"coordinates":[0.084874,51.490736],"type":"Point"}
}
