{
  "type": "Feature",
  "properties": {
    "date:inception_lower": "1980-01-01",
    "date:inception_upper": "1980-01-01",
    "iso:country": "GB",
    "wof:name": "WV10 8EX",
    "wof:placetype": "postalcode"
  },
  "geometry": {"coordinates":[-2.118466,52.625799],"type":"Point"}
}
