{
  "type": "Feature",
  "properties": {
    "iso:country":"GB",
    "wof:name":"WV10 8EX",
    "wof:placetype":"postalcode"
},
  "geometry": {"coordinates":[-2.11846581673577,52.62579897736273],"type":"Point"}
}