{
  "type": "Feature",
  "properties": {
    "iso:country": "GB",
    "wof:name": "HA8 8HP",
    "wof:placetype": "postalcode"
  },
  "geometry": {"coordinates":[-0.280321,51.619989],"type":"Point"}
}
