{
  "type": "Feature",
  "properties": {
    "date:inception_lower": "1980-01-01",
    "date:inception_upper": "1980-01-01",
    "iso:country": "GB",
    "wof:name": "NR10 3DW",
    "wof:placetype": "postalcode"
  },
  "geometry": {"coordinates":[1.243409,52.699864],"type":"Point"}
}
