{
  "type": "Feature",
  "properties": {
    "iso:country":"GB",
    "wof:name":"OL11 4EY",
    "wof:placetype":"postalcode"
},
  "geometry": {"coordinates":[-2.16878946189969,53.61403275770888],"type":"Point"}
}