{
  "type": "Feature",
  "properties": {
    "iso:country": "GB",
    "wof:name": "TQ9 5DR",
    "wof:placetype": "postalcode"
  },
  "geometry": {"coordinates":[-3.683342,50.43032],"type":"Point"}
}
