{
  "type": "Feature",
  "properties": {
    "date:inception_lower": "1980-01-01",
    "date:inception_upper": "1980-01-01",
    "iso:country": "GB",
    "wof:name": "TQ9 5DR",
    "wof:placetype": "postalcode"
  },
  "geometry": {"coordinates":[-3.683342,50.43032],"type":"Point"}
}
