{
  "type": "Feature",
  "properties": {
    "date:inception_lower":"1998-06-01",
    "date:inception_upper":"1998-06-30",
    "iso:country":"GB",
    "wof:name":"PL14 3UH",
    "wof:placetype":"postalcode"
},
  "geometry": {"coordinates":[-4.452012,50.453582],"type":"Point"}
}