{
  "type": "Feature",
  "properties": {
    "iso:country":"GB",
    "wof:name":"PL14 3UH",
    "wof:placetype":"postalcode"
},
  "geometry": {"coordinates":[-4.45213795745287,50.45343815685816],"type":"Point"}
}