{
  "type": "Feature",
  "properties": {
    "date:inception_lower": "1998-06-01",
    "date:inception_upper": "1998-06-01",
    "iso:country": "GB",
    "wof:name": "PL14 3UH",
    "wof:placetype": "postalcode"
  },
  "geometry": {"coordinates":[-4.452173,50.453426],"type":"Point"}
}
