{
  "type": "Feature",
  "properties": {
    "iso:country":"GB",
    "wof:name":"TN16 2JY",
    "wof:placetype":"postalcode"
},
  "geometry": {"coordinates":[0.0318275417805,51.29135943452727],"type":"Point"}
}