{
  "type": "Feature",
  "properties": {
    "date:inception_lower":"1980-01-01",
    "date:inception_upper":"1980-01-31",
    "iso:country":"GB",
    "wof:name":"TN16 2JY",
    "wof:placetype":"postalcode"
},
  "geometry": {"coordinates":[0.031828,51.291359],"type":"Point"}
}