{
  "type": "Feature",
  "properties": {
    "iso:country":"GB",
    "wof:name":"TR7 1BU",
    "wof:placetype":"postalcode"
},
  "geometry": {"coordinates":[-5.07975876938826,50.41434605727817],"type":"Point"}
}