{
  "type": "Feature",
  "properties": {
    "date:inception_lower":"2000-06-01",
    "date:inception_upper":"2000-06-30",
    "iso:country":"GB",
    "wof:name":"TR7 1BU",
    "wof:placetype":"postalcode"
},
  "geometry": {"coordinates":[-5.079759,50.414346],"type":"Point"}
}