{
  "type": "Feature",
  "properties": {
    "iso:country": "GB",
    "wof:name": "NE25 8AX",
    "wof:placetype": "postalcode"
  },
  "geometry": {"coordinates":[-1.459961,55.041031],"type":"Point"}
}
