{
  "type": "Feature",
  "properties": {
    "iso:country":"GB",
    "wof:name":"G13 3SW",
    "wof:placetype":"postalcode"
},
  "geometry": {"coordinates":[-4.36413161163182,55.89043317491053],"type":"Point"}
}