{
  "type": "Feature",
  "properties": {
    "date:inception_lower":"1980-01-01",
    "date:inception_upper":"1980-01-31",
    "iso:country":"GB",
    "wof:name":"SP3 5EH",
    "wof:placetype":"postalcode"
},
  "geometry": {"coordinates":[-1.953881,51.081587],"type":"Point"}
}