{
  "type": "Feature",
  "properties": {
    "iso:country": "GB",
    "wof:name": "SP3 5EH",
    "wof:placetype": "postalcode"
  },
  "geometry": {"coordinates":[-1.953881,51.081587],"type":"Point"}
}
