{
  "type": "Feature",
  "properties": {
    "iso:country":"GB",
    "wof:name":"SP3 5EH",
    "wof:placetype":"postalcode"
},
  "geometry": {"coordinates":[-1.95388141134956,51.08158704136783],"type":"Point"}
}