{
  "type": "Feature",
  "properties": {
    "iso:country":"GB",
    "wof:name":"ML3 7JU",
    "wof:placetype":"postalcode"
},
  "geometry": {"coordinates":[-4.03884805803169,55.76974159586999],"type":"Point"}
}