{
  "type": "Feature",
  "properties": {
    "iso:country":"GB",
    "wof:name":"B74 2RB",
    "wof:placetype":"postalcode"
},
  "geometry": {"coordinates":[-1.84263205964278,52.57833321837234],"type":"Point"}
}