{
  "type": "Feature",
  "properties": {
    "iso:country":"GB",
    "wof:name":"UB3 2JF",
    "wof:placetype":"postalcode"
},
  "geometry": {"coordinates":[-0.4149234246823,51.51628873616282],"type":"Point"}
}