{
  "type": "Feature",
  "properties": {
    "iso:country":"GB",
    "wof:name":"CB4 3QT",
    "wof:placetype":"postalcode"
},
  "geometry": {"coordinates":[0.10977217637879,52.21660309994331],"type":"Point"}
}