{
  "type": "Feature",
  "properties": {
    "iso:country":"GB",
    "wof:name":"WR7 4PN",
    "wof:placetype":"postalcode"
},
  "geometry": {"coordinates":[-2.04274284187202,52.22119075610395],"type":"Point"}
}