{
  "type": "Feature",
  "properties": {
    "iso:country": "GB",
    "wof:name": "WR7 4PN",
    "wof:placetype": "postalcode"
  },
  "geometry": {"coordinates":[-2.042743,52.221191],"type":"Point"}
}
