{
  "type": "Feature",
  "properties": {
    "date:inception_lower": "2003-02-01",
    "date:inception_upper": "2003-02-01",
    "iso:country": "GB",
    "wof:name": "RH6 8EB",
    "wof:placetype": "postalcode"
  },
  "geometry": {"coordinates":[-0.171875,51.179438],"type":"Point"}
}
