{
  "type": "Feature",
  "properties": {
    "iso:country":"GB",
    "wof:name":"NP25 3TB",
    "wof:placetype":"postalcode"
},
  "geometry": {"coordinates":[-2.69949141697238,51.80895343151555],"type":"Point"}
}