{
  "type": "Feature",
  "properties": {
    "iso:country":"GB",
    "wof:name":"NW1 8JT",
    "wof:placetype":"postalcode"
},
  "geometry": {"coordinates":[-0.15059562061939,51.53972010328496],"type":"Point"}
}