{
  "type": "Feature",
  "properties": {
    "date:inception_lower": "2023-09-01",
    "date:inception_upper": "2023-09-01",
    "iso:country": "GB",
    "wof:name": "TN12 5EY",
    "wof:placetype": "postalcode"
  },
  "geometry": {"coordinates":[0.381642,51.209578],"type":"Point"}
}
