{
  "type": "Feature",
  "properties": {
    "iso:country":"GB",
    "wof:name":"ME15 8UA",
    "wof:placetype":"postalcode"
},
  "geometry": {"coordinates":[0.56817731848155,51.26276966007814],"type":"Point"}
}