{
  "type": "Feature",
  "properties": {
    "iso:country":"GB",
    "wof:name":"CM3 4LH",
    "wof:placetype":"postalcode"
},
  "geometry": {"coordinates":[0.59610379343236,51.70850342694617],"type":"Point"}
}