{
  "type": "Feature",
  "properties": {
    "iso:country": "GB",
    "wof:name": "HP16 9LT",
    "wof:placetype": "postalcode"
  },
  "geometry": {"coordinates":[-0.696715,51.715941],"type":"Point"}
}
