{
  "type": "Feature",
  "properties": {
    "iso:country":"GB",
    "wof:name":"HP16 9LT",
    "wof:placetype":"postalcode"
},
  "geometry": {"coordinates":[-0.69671480873353,51.71594105385533],"type":"Point"}
}