{
  "type": "Feature",
  "properties": {
    "date:inception_lower": "1980-01-01",
    "date:inception_upper": "1980-01-01",
    "iso:country": "GB",
    "wof:name": "HP16 9LT",
    "wof:placetype": "postalcode"
  },
  "geometry": {"coordinates":[-0.696715,51.715941],"type":"Point"}
}
