{
  "type": "Feature",
  "properties": {
    "iso:country":"GB",
    "wof:name":"CO11 1UN",
    "wof:placetype":"postalcode"
},
  "geometry": {"coordinates":[1.05714380275245,51.94859717158068],"type":"Point"}
}