{
  "type": "Feature",
  "properties": {
    "date:inception_lower": "1980-01-01",
    "date:inception_upper": "1980-01-01",
    "iso:country": "GB",
    "wof:name": "CO11 1UN",
    "wof:placetype": "postalcode"
  },
  "geometry": {"coordinates":[1.057174,51.948609],"type":"Point"}
}
