{
  "type": "Feature",
  "properties": {
    "iso:country":"GB",
    "wof:name":"NR3 4HW",
    "wof:placetype":"postalcode"
},
  "geometry": {"coordinates":[1.30458170079155,52.64901498345952],"type":"Point"}
}