{
  "type": "Feature",
  "properties": {
    "iso:country": "GB",
    "wof:name": "YO32 5SQ",
    "wof:placetype": "postalcode"
  },
  "geometry": {"coordinates":[-1.041717,54.022098],"type":"Point"}
}
