{
  "type": "Feature",
  "properties": {
    "iso:country":"GB",
    "wof:name":"SA48 8NB",
    "wof:placetype":"postalcode"
},
  "geometry": {"coordinates":[-4.03249257602589,52.15734570781293],"type":"Point"}
}