{
  "type": "Feature",
  "properties": {
    "iso:country": "GB",
    "wof:name": "SA48 8NB",
    "wof:placetype": "postalcode"
  },
  "geometry": {"coordinates":[-4.032493,52.157346],"type":"Point"}
}
