{
  "type": "Feature",
  "properties": {
    "date:inception_lower": "1980-01-01",
    "date:inception_upper": "1980-01-01",
    "iso:country": "GB",
    "wof:name": "SN4 7RP",
    "wof:placetype": "postalcode"
  },
  "geometry": {"coordinates":[-1.872339,51.506074],"type":"Point"}
}
