{
  "type": "Feature",
  "properties": {
    "iso:country":"GB",
    "wof:name":"SN4 7RP",
    "wof:placetype":"postalcode"
},
  "geometry": {"coordinates":[-1.87233917796849,51.50607385514125],"type":"Point"}
}