{
  "type": "Feature",
  "properties": {
    "iso:country":"GB",
    "wof:name":"NR6 5SW",
    "wof:placetype":"postalcode"
},
  "geometry": {"coordinates":[1.25867795661579,52.66783376703744],"type":"Point"}
}