{
  "type": "Feature",
  "properties": {
    "date:inception_lower":"1994-05-01",
    "date:inception_upper":"1994-05-31",
    "iso:country":"GB",
    "wof:name":"M15 6QL",
    "wof:placetype":"postalcode"
},
  "geometry": {"coordinates":[-2.240079,53.463076],"type":"Point"}
}