{
  "type": "Feature",
  "properties": {
    "iso:country":"GB",
    "wof:name":"M15 6QL",
    "wof:placetype":"postalcode"
},
  "geometry": {"coordinates":[-2.24023200137101,53.46324746786354],"type":"Point"}
}