{
  "type": "Feature",
  "properties": {
    "iso:country":"GB",
    "wof:name":"RH20 3HP",
    "wof:placetype":"postalcode"
},
  "geometry": {"coordinates":[-0.41755471432617,50.9255174235293],"type":"Point"}
}