{
  "type": "Feature",
  "properties": {
    "date:inception_lower": "1980-01-01",
    "date:inception_upper": "1980-01-01",
    "iso:country": "GB",
    "wof:name": "SR5 4RA",
    "wof:placetype": "postalcode"
  },
  "geometry": {"coordinates":[-1.461205,54.927443],"type":"Point"}
}
