{
  "type": "Feature",
  "properties": {
    "iso:country":"GB",
    "wof:name":"RG12 8TP",
    "wof:placetype":"postalcode"
},
  "geometry": {"coordinates":[-0.78628467969508,51.41858779060343],"type":"Point"}
}