{
  "type": "Feature",
  "properties": {
    "iso:country": "GB",
    "wof:name": "RG12 8TP",
    "wof:placetype": "postalcode"
  },
  "geometry": {"coordinates":[-0.786285,51.418588],"type":"Point"}
}
