{
  "type": "Feature",
  "properties": {
    "iso:country":"GB",
    "wof:name":"S10 2DA",
    "wof:placetype":"postalcode"
},
  "geometry": {"coordinates":[-1.48414172841649,53.37501659250641],"type":"Point"}
}