{
  "type": "Feature",
  "properties": {
    "date:inception_lower":"1985-10-01",
    "date:inception_upper":"1985-10-31",
    "iso:country":"GB",
    "wof:name":"S10 2DA",
    "wof:placetype":"postalcode"
},
  "geometry": {"coordinates":[-1.484142,53.375017],"type":"Point"}
}