{
  "type": "Feature",
  "properties": {
    "iso:country": "GB",
    "wof:name": "E5 0PP",
    "wof:placetype": "postalcode"
  },
  "geometry": {"coordinates":[-0.048323,51.55461],"type":"Point"}
}
