{
  "type": "Feature",
  "properties": {
    "iso:country":"GB",
    "wof:name":"E5 0PP",
    "wof:placetype":"postalcode"
},
  "geometry": {"coordinates":[-0.04832299664123,51.55460952423964],"type":"Point"}
}