{
  "type": "Feature",
  "properties": {
    "iso:country": "GB",
    "wof:name": "IP3 9TR",
    "wof:placetype": "postalcode"
  },
  "geometry": {"coordinates":[1.194928,52.030335],"type":"Point"}
}
