{
  "type": "Feature",
  "properties": {
    "iso:country":"GB",
    "wof:name":"IP3 9TR",
    "wof:placetype":"postalcode"
},
  "geometry": {"coordinates":[1.19492752516983,52.03033461754371],"type":"Point"}
}