{
  "type": "Feature",
  "properties": {
    "iso:country": "GB",
    "wof:name": "DY10 3SJ",
    "wof:placetype": "postalcode"
  },
  "geometry": {"coordinates":[-2.236293,52.4196],"type":"Point"}
}
