{
  "type": "Feature",
  "properties": {
    "iso:country":"GB",
    "wof:name":"GL11 5EW",
    "wof:placetype":"postalcode"
},
  "geometry": {"coordinates":[-2.33752848001565,51.69811635370105],"type":"Point"}
}