{
  "type": "Feature",
  "properties": {
    "iso:country":"GB",
    "wof:name":"NE16 5LF",
    "wof:placetype":"postalcode"
},
  "geometry": {"coordinates":[-1.66769782206293,54.92715752007339],"type":"Point"}
}