{
  "type": "Feature",
  "properties": {
    "iso:country":"GB",
    "wof:name":"SA44 5AP",
    "wof:placetype":"postalcode"
},
  "geometry": {"coordinates":[-4.31958654458032,52.03724114479535],"type":"Point"}
}