{
  "type": "Feature",
  "properties": {
    "iso:country": "GB",
    "wof:name": "SA44 5AP",
    "wof:placetype": "postalcode"
  },
  "geometry": {"coordinates":[-4.319587,52.037241],"type":"Point"}
}
