{
  "type": "Feature",
  "properties": {
    "date:inception_lower": "1980-01-01",
    "date:inception_upper": "1980-01-01",
    "iso:country": "GB",
    "wof:name": "G73 5HE",
    "wof:placetype": "postalcode"
  },
  "geometry": {"coordinates":[-4.186464,55.809615],"type":"Point"}
}
