{
  "type": "Feature",
  "properties": {
    "iso:country":"GB",
    "wof:name":"G73 5HE",
    "wof:placetype":"postalcode"
},
  "geometry": {"coordinates":[-4.18646376133591,55.80961474870273],"type":"Point"}
}