{
  "type": "Feature",
  "properties": {
    "iso:country":"GB",
    "wof:name":"GU1 2BJ",
    "wof:placetype":"postalcode"
},
  "geometry": {"coordinates":[-0.55575390461919,51.23708932605263],"type":"Point"}
}