{
  "type": "Feature",
  "properties": {
    "iso:country": "GB",
    "wof:name": "GU1 2BJ",
    "wof:placetype": "postalcode"
  },
  "geometry": {"coordinates":[-0.555754,51.237089],"type":"Point"}
}
