{
  "type": "Feature",
  "properties": {
    "iso:country":"GB",
    "wof:name":"AB56 4PQ",
    "wof:placetype":"postalcode"
},
  "geometry": {"coordinates":[-2.90282506133861,57.6995267325923],"type":"Point"}
}