{
  "type": "Feature",
  "properties": {
    "iso:country":"GB",
    "wof:name":"HP13 6NZ",
    "wof:placetype":"postalcode"
},
  "geometry": {"coordinates":[-0.74587071555544,51.63068620144995],"type":"Point"}
}