{
  "type": "Feature",
  "properties": {
    "date:inception_lower": "1990-07-01",
    "date:inception_upper": "1990-07-01",
    "iso:country": "GB",
    "wof:name": "WS14 0LA",
    "wof:placetype": "postalcode"
  },
  "geometry": {"coordinates":[-1.838722,52.642641],"type":"Point"}
}
