{
  "type": "Feature",
  "properties": {
    "iso:country":"GB",
    "wof:name":"WS14 0LA",
    "wof:placetype":"postalcode"
},
  "geometry": {"coordinates":[-1.83872185721759,52.64264076406949],"type":"Point"}
}