{
  "type": "Feature",
  "properties": {
    "iso:country":"GB",
    "wof:name":"G44 5QA",
    "wof:placetype":"postalcode"
},
  "geometry": {"coordinates":[-4.23485434549371,55.81715677118532],"type":"Point"}
}