{
  "type": "Feature",
  "properties": {
    "iso:country": "GB",
    "wof:name": "WS9 9RH",
    "wof:placetype": "postalcode"
  },
  "geometry": {"coordinates":[-1.916657,52.631187],"type":"Point"}
}
