{
  "type": "Feature",
  "properties": {
    "iso:country": "GB",
    "wof:name": "YO13 0LD",
    "wof:placetype": "postalcode"
  },
  "geometry": {"coordinates":[-0.572778,54.34453],"type":"Point"}
}
