{
  "type": "Feature",
  "properties": {
    "date:inception_lower": "1996-12-01",
    "date:inception_upper": "1996-12-01",
    "iso:country": "GB",
    "wof:name": "SO31 8LB",
    "wof:placetype": "postalcode"
  },
  "geometry": {"coordinates":[-1.32022,50.88356],"type":"Point"}
}
