{
  "type": "Feature",
  "properties": {
    "iso:country":"GB",
    "wof:name":"SO31 8LB",
    "wof:placetype":"postalcode"
},
  "geometry": {"coordinates":[-1.32027294255803,50.88356935192992],"type":"Point"}
}