{
  "type": "Feature",
  "properties": {
    "iso:country": "GB",
    "wof:name": "SA7 9EU",
    "wof:placetype": "postalcode"
  },
  "geometry": {"coordinates":[-3.878967,51.687194],"type":"Point"}
}
