{
  "type": "Feature",
  "properties": {
    "iso:country":"GB",
    "wof:name":"SA7 9EU",
    "wof:placetype":"postalcode"
},
  "geometry": {"coordinates":[-3.87896721940691,51.68719366571221],"type":"Point"}
}