{
  "type": "Feature",
  "properties": {
    "iso:country": "GB",
    "wof:name": "DL6 3HH",
    "wof:placetype": "postalcode"
  },
  "geometry": {"coordinates":[-1.278672,54.431495],"type":"Point"}
}
