{
  "type": "Feature",
  "properties": {
    "iso:country":"GB",
    "wof:name":"DL6 3HH",
    "wof:placetype":"postalcode"
},
  "geometry": {"coordinates":[-1.27862930975802,54.43148191439654],"type":"Point"}
}