{
  "type": "Feature",
  "properties": {
    "iso:country":"GB",
    "wof:name":"GL17 9QJ",
    "wof:placetype":"postalcode"
},
  "geometry": {"coordinates":[-2.57768444038342,51.82960230926248],"type":"Point"}
}