{
  "type": "Feature",
  "properties": {
    "iso:country":"GB",
    "wof:name":"CV2 5JJ",
    "wof:placetype":"postalcode"
},
  "geometry": {"coordinates":[-1.46136311781169,52.40744573580425],"type":"Point"}
}