{
  "type": "Feature",
  "properties": {
    "iso:country": "GB",
    "wof:name": "NE66 3EN",
    "wof:placetype": "postalcode"
  },
  "geometry": {"coordinates":[-1.619997,55.514695],"type":"Point"}
}
