{
  "type": "Feature",
  "properties": {
    "iso:country":"GB",
    "wof:name":"NE66 3EN",
    "wof:placetype":"postalcode"
},
  "geometry": {"coordinates":[-1.61999712868492,55.51469542371645],"type":"Point"}
}