{
  "type": "Feature",
  "properties": {
    "date:inception_lower": "1980-01-01",
    "date:inception_upper": "1980-01-01",
    "iso:country": "GB",
    "wof:name": "CT14 6AE",
    "wof:placetype": "postalcode"
  },
  "geometry": {"coordinates":[1.399893,51.223048],"type":"Point"}
}
