{
  "type": "Feature",
  "properties": {
    "iso:country":"GB",
    "wof:name":"CT14 6AE",
    "wof:placetype":"postalcode"
},
  "geometry": {"coordinates":[1.3998930021478,51.22304831135028],"type":"Point"}
}