{
  "type": "Feature",
  "properties": {
    "iso:country": "GB",
    "wof:name": "NE33 4RJ",
    "wof:placetype": "postalcode"
  },
  "geometry": {"coordinates":[-1.43882,54.977368],"type":"Point"}
}
