{
  "type": "Feature",
  "properties": {
    "iso:country":"GB",
    "wof:name":"SA12 6BS",
    "wof:placetype":"postalcode"
},
  "geometry": {"coordinates":[-3.80139834548604,51.58703940410565],"type":"Point"}
}