{
  "type": "Feature",
  "properties": {
    "iso:country": "GB",
    "wof:name": "BB6 8BD",
    "wof:placetype": "postalcode"
  },
  "geometry": {"coordinates":[-2.45163,53.817106],"type":"Point"}
}
