{
  "type": "Feature",
  "properties": {
    "date:inception_lower":"1982-03-01",
    "date:inception_upper":"1982-03-31",
    "iso:country":"GB",
    "wof:name":"MK13 9EH",
    "wof:placetype":"postalcode"
},
  "geometry": {"coordinates":[-0.786907,52.045945],"type":"Point"}
}