{
  "type": "Feature",
  "properties": {
    "iso:country":"GB",
    "wof:name":"TR13 9SX",
    "wof:placetype":"postalcode"
},
  "geometry": {"coordinates":[-5.3669463473477,50.11071983397666],"type":"Point"}
}