{
  "type": "Feature",
  "properties": {
    "iso:country": "GB",
    "wof:name": "IP14 4AA",
    "wof:placetype": "postalcode"
  },
  "geometry": {"coordinates":[1.003298,52.197533],"type":"Point"}
}
