{
  "type": "Feature",
  "properties": {
    "iso:country": "GB",
    "wof:name": "CB2 7TT",
    "wof:placetype": "postalcode"
  },
  "geometry": {"coordinates":[0.122243,52.19077],"type":"Point"}
}
