{
  "type": "Feature",
  "properties": {
    "iso:country": "GB",
    "wof:name": "FY5 1RN",
    "wof:placetype": "postalcode"
  },
  "geometry": {"coordinates":[-3.036425,53.862846],"type":"Point"}
}
