{
  "type": "Feature",
  "properties": {
    "date:inception_lower": "1980-01-01",
    "date:inception_upper": "1980-01-01",
    "iso:country": "GB",
    "wof:name": "G73 2SE",
    "wof:placetype": "postalcode"
  },
  "geometry": {"coordinates":[-4.21964,55.82722],"type":"Point"}
}
