{
  "type": "Feature",
  "properties": {
    "iso:country":"GB",
    "wof:name":"CW5 6GN",
    "wof:placetype":"postalcode"
},
  "geometry": {"coordinates":[-2.51311536290089,53.06531250841701],"type":"Point"}
}