{
  "type": "Feature",
  "properties": {
    "date:inception_lower": "1980-01-01",
    "date:inception_upper": "1980-01-01",
    "iso:country": "GB",
    "wof:name": "TA18 8AL",
    "wof:placetype": "postalcode"
  },
  "geometry": {"coordinates":[-2.779139,50.876272],"type":"Point"}
}
