{
  "type": "Feature",
  "properties": {
    "iso:country":"GB",
    "wof:name":"TA18 8AL",
    "wof:placetype":"postalcode"
},
  "geometry": {"coordinates":[-2.77913859409232,50.87627232823819],"type":"Point"}
}