{
  "type": "Feature",
  "properties": {
    "date:inception_lower": "2018-08-01",
    "date:inception_upper": "2018-08-01",
    "iso:country": "GB",
    "wof:name": "TN40 2FR",
    "wof:placetype": "postalcode"
  },
  "geometry": {"coordinates":[0.482365,50.84623],"type":"Point"}
}
