{
  "type": "Feature",
  "properties": {
    "iso:country":"GB",
    "wof:name":"SO50 5TT",
    "wof:placetype":"postalcode"
},
  "geometry": {"coordinates":[-1.35610141642423,50.96358956943067],"type":"Point"}
}