{
  "type": "Feature",
  "properties": {
    "date:inception_lower": "2005-04-01",
    "date:inception_upper": "2005-04-01",
    "iso:country": "GB",
    "wof:name": "SO50 5TT",
    "wof:placetype": "postalcode"
  },
  "geometry": {"coordinates":[-1.356091,50.96359],"type":"Point"}
}
