{
  "type": "Feature",
  "properties": {
    "iso:country":"GB",
    "wof:name":"OX16 3ES",
    "wof:placetype":"postalcode"
},
  "geometry": {"coordinates":[-1.32671915329082,52.07478253249378],"type":"Point"}
}