{
  "type": "Feature",
  "properties": {
    "iso:country": "GB",
    "wof:name": "BS9 2HJ",
    "wof:placetype": "postalcode"
  },
  "geometry": {"coordinates":[-2.648881,51.484907],"type":"Point"}
}
