{
  "type": "Feature",
  "properties": {
    "iso:country":"GB",
    "wof:name":"BS9 2HJ",
    "wof:placetype":"postalcode"
},
  "geometry": {"coordinates":[-2.64888147320963,51.48490702119917],"type":"Point"}
}