{
  "type": "Feature",
  "properties": {
    "iso:country":"GB",
    "wof:name":"IP32 7BS",
    "wof:placetype":"postalcode"
},
  "geometry": {"coordinates":[0.7479608456568,52.23976707932682],"type":"Point"}
}