{
  "type": "Feature",
  "properties": {
    "iso:country": "GB",
    "wof:name": "IP32 7BS",
    "wof:placetype": "postalcode"
  },
  "geometry": {"coordinates":[0.747961,52.239767],"type":"Point"}
}
