{
  "type": "Feature",
  "properties": {
    "iso:country":"GB",
    "wof:name":"YO17 8DA",
    "wof:placetype":"postalcode"
},
  "geometry": {"coordinates":[-0.63398682444809,54.09278892263573],"type":"Point"}
}