{
  "type": "Feature",
  "properties": {
    "date:inception_lower": "1993-01-01",
    "date:inception_upper": "1993-01-01",
    "iso:country": "GB",
    "wof:name": "YO17 8DA",
    "wof:placetype": "postalcode"
  },
  "geometry": {"coordinates":[-0.633987,54.092789],"type":"Point"}
}
