{
  "type": "Feature",
  "properties": {
    "iso:country":"GB",
    "wof:name":"TN12 9PN",
    "wof:placetype":"postalcode"
},
  "geometry": {"coordinates":[0.45888183212429,51.17666458124904],"type":"Point"}
}