{
  "type": "Feature",
  "properties": {
    "iso:country": "GB",
    "wof:name": "TN12 9PN",
    "wof:placetype": "postalcode"
  },
  "geometry": {"coordinates":[0.458882,51.176665],"type":"Point"}
}
