{
  "type": "Feature",
  "properties": {
    "iso:country":"GB",
    "wof:name":"IP14 4TA",
    "wof:placetype":"postalcode"
},
  "geometry": {"coordinates":[0.99222243697889,52.29290140852211],"type":"Point"}
}