{
  "type": "Feature",
  "properties": {
    "date:inception_lower":"1995-12-01",
    "date:inception_upper":"1995-12-31",
    "iso:country":"GB",
    "wof:name":"GL4 4WJ",
    "wof:placetype":"postalcode"
},
  "geometry": {"coordinates":[-2.207404,51.845422],"type":"Point"}
}