{
  "type": "Feature",
  "properties": {
    "iso:country":"GB",
    "wof:name":"LE15 7RT",
    "wof:placetype":"postalcode"
},
  "geometry": {"coordinates":[-0.7211164120814,52.73585857864851],"type":"Point"}
}