{
  "type": "Feature",
  "properties": {
    "iso:country":"GB",
    "wof:name":"LL54 5DE",
    "wof:placetype":"postalcode"
},
  "geometry": {"coordinates":[-4.32177377291376,53.02491078905958],"type":"Point"}
}