{
  "type": "Feature",
  "properties": {
    "date:inception_lower": "1980-01-01",
    "date:inception_upper": "1980-01-01",
    "iso:country": "GB",
    "wof:name": "LL54 5DE",
    "wof:placetype": "postalcode"
  },
  "geometry": {"coordinates":[-4.321774,53.024911],"type":"Point"}
}
