{
  "type": "Feature",
  "properties": {
    "iso:country": "GB",
    "wof:name": "LL54 5DE",
    "wof:placetype": "postalcode"
  },
  "geometry": {"coordinates":[-4.321774,53.024911],"type":"Point"}
}
