{
  "type": "Feature",
  "properties": {
    "iso:country":"GB",
    "wof:name":"BS13 9RJ",
    "wof:placetype":"postalcode"
},
  "geometry": {"coordinates":[-2.60325731740721,51.41069077935555],"type":"Point"}
}