{
  "type": "Feature",
  "properties": {
    "iso:country":"GB",
    "wof:name":"CF10 5EQ",
    "wof:placetype":"postalcode"
},
  "geometry": {"coordinates":[-3.16647535324914,51.46543364524771],"type":"Point"}
}