{
  "type": "Feature",
  "properties": {
    "iso:country": "GB",
    "wof:name": "BB1 3LZ",
    "wof:placetype": "postalcode"
  },
  "geometry": {"coordinates":[-2.432925,53.748596],"type":"Point"}
}
