{
  "type": "Feature",
  "properties": {
    "date:inception_lower":"1980-01-01",
    "date:inception_upper":"1980-01-31",
    "iso:country":"GB",
    "wof:name":"BB1 3LZ",
    "wof:placetype":"postalcode"
},
  "geometry": {"coordinates":[-2.432925,53.748596],"type":"Point"}
}