{
  "type": "Feature",
  "properties": {
    "iso:country":"GB",
    "wof:name":"WF3 4LX",
    "wof:placetype":"postalcode"
},
  "geometry": {"coordinates":[-1.46262614889069,53.70096026994766],"type":"Point"}
}