{
  "type": "Feature",
  "properties": {
    "iso:country":"GB",
    "wof:name":"RM15 6PY",
    "wof:placetype":"postalcode"
},
  "geometry": {"coordinates":[0.29537509904679,51.52437657240701],"type":"Point"}
}