{
  "type": "Feature",
  "properties": {
    "date:inception_lower":"2002-09-01",
    "date:inception_upper":"2002-09-30",
    "iso:country":"GB",
    "wof:name":"M35 9SA",
    "wof:placetype":"postalcode"
},
  "geometry": {"coordinates":[-2.140605,53.502488],"type":"Point"}
}