{
  "type": "Feature",
  "properties": {
    "date:inception_lower": "1992-01-01",
    "date:inception_upper": "1992-01-01",
    "iso:country": "GB",
    "wof:name": "PE2 5UZ",
    "wof:placetype": "postalcode"
  },
  "geometry": {"coordinates":[-0.295394,52.555553],"type":"Point"}
}
