{
  "type": "Feature",
  "properties": {
    "iso:country":"GB",
    "wof:name":"PE2 5UZ",
    "wof:placetype":"postalcode"
},
  "geometry": {"coordinates":[-0.29539433568428,52.55555270407891],"type":"Point"}
}