{
  "type": "Feature",
  "properties": {
    "iso:country": "GB",
    "wof:name": "L35 5EX",
    "wof:placetype": "postalcode"
  },
  "geometry": {"coordinates":[-2.804903,53.417918],"type":"Point"}
}
