{
  "type": "Feature",
  "properties": {
    "iso:country":"GB",
    "wof:name":"CM12 0NA",
    "wof:placetype":"postalcode"
},
  "geometry": {"coordinates":[0.41037197963085,51.63420487682014],"type":"Point"}
}