{
  "type": "Feature",
  "properties": {
    "date:inception_lower":"1980-01-01",
    "date:inception_upper":"1980-01-31",
    "iso:country":"GB",
    "wof:name":"TR18 3HS",
    "wof:placetype":"postalcode"
},
  "geometry": {"coordinates":[-5.548386,50.128593],"type":"Point"}
}