{
  "type": "Feature",
  "properties": {
    "date:inception_lower": "2003-04-01",
    "date:inception_upper": "2003-04-01",
    "iso:country": "GB",
    "wof:name": "M6 6WE",
    "wof:placetype": "postalcode"
  },
  "geometry": {"coordinates":[-2.288115,53.494412],"type":"Point"}
}
