{
  "type": "Feature",
  "properties": {
    "iso:country":"GB",
    "wof:name":"LL40 2NA",
    "wof:placetype":"postalcode"
},
  "geometry": {"coordinates":[-3.8399421712125,52.76760977473843],"type":"Point"}
}