{
  "type": "Feature",
  "properties": {
    "date:inception_lower": "2022-04-01",
    "date:inception_upper": "2022-04-01",
    "iso:country": "GB",
    "wof:name": "CA14 3FH",
    "wof:placetype": "postalcode"
  },
  "geometry": {"coordinates":[-3.56769,54.632598],"type":"Point"}
}
