{
  "type": "Feature",
  "properties": {
    "iso:country": "GB",
    "wof:name": "NP18 2DN",
    "wof:placetype": "postalcode"
  },
  "geometry": {"coordinates":[-2.911968,51.587855],"type":"Point"}
}
