{
  "type": "Feature",
  "properties": {
    "iso:country":"GB",
    "wof:name":"EX1 3DR",
    "wof:placetype":"postalcode"
},
  "geometry": {"coordinates":[-3.49664770707111,50.72194927120667],"type":"Point"}
}