{
  "type": "Feature",
  "properties": {
    "iso:country": "GB",
    "wof:name": "EN1 4AF",
    "wof:placetype": "postalcode"
  },
  "geometry": {"coordinates":[-0.070947,51.665555],"type":"Point"}
}
