{
  "type": "Feature",
  "properties": {
    "iso:country":"GB",
    "wof:name":"LL27 0NZ",
    "wof:placetype":"postalcode"
},
  "geometry": {"coordinates":[-3.82881250114633,53.15035384102999],"type":"Point"}
}