{
  "type": "Feature",
  "properties": {
    "date:inception_lower": "1980-01-01",
    "date:inception_upper": "1980-01-01",
    "iso:country": "GB",
    "wof:name": "LL27 0NZ",
    "wof:placetype": "postalcode"
  },
  "geometry": {"coordinates":[-3.828812,53.150354],"type":"Point"}
}
