{
  "type": "Feature",
  "properties": {
    "iso:country": "GB",
    "wof:name": "WA8 9RQ",
    "wof:placetype": "postalcode"
  },
  "geometry": {"coordinates":[-2.72488,53.385694],"type":"Point"}
}
