{
  "type": "Feature",
  "properties": {
    "iso:country":"GB",
    "wof:name":"WA8 9RQ",
    "wof:placetype":"postalcode"
},
  "geometry": {"coordinates":[-2.72487996010511,53.38569396774302],"type":"Point"}
}