{
  "type": "Feature",
  "properties": {
    "iso:country":"GB",
    "wof:name":"NN14 4RE",
    "wof:placetype":"postalcode"
},
  "geometry": {"coordinates":[-0.52794464055521,52.39397144096088],"type":"Point"}
}