{
  "type": "Feature",
  "properties": {
    "date:inception_lower": "1998-12-01",
    "date:inception_upper": "1998-12-01",
    "iso:country": "GB",
    "wof:name": "NN14 4RE",
    "wof:placetype": "postalcode"
  },
  "geometry": {"coordinates":[-0.527945,52.393971],"type":"Point"}
}
