{
  "type": "Feature",
  "properties": {
    "iso:country":"GB",
    "wof:name":"SW18 5JR",
    "wof:placetype":"postalcode"
},
  "geometry": {"coordinates":[-0.2085026576167,51.44688129735831],"type":"Point"}
}