{
  "type": "Feature",
  "properties": {
    "date:inception_lower":"2002-10-01",
    "date:inception_upper":"2002-10-31",
    "iso:country":"GB",
    "wof:name":"SW18 5JR",
    "wof:placetype":"postalcode"
},
  "geometry": {"coordinates":[-0.208503,51.446881],"type":"Point"}
}