{
  "type": "Feature",
  "properties": {
    "iso:country":"GB",
    "wof:name":"B4 6BS",
    "wof:placetype":"postalcode"
},
  "geometry": {"coordinates":[-1.89505515610226,52.48276575954661],"type":"Point"}
}