{
  "type": "Feature",
  "properties": {
    "iso:country":"GB",
    "wof:name":"CV4 8BD",
    "wof:placetype":"postalcode"
},
  "geometry": {"coordinates":[-1.58432870329032,52.39340465677833],"type":"Point"}
}