{
  "type": "Feature",
  "properties": {
    "iso:country": "GB",
    "wof:name": "FK6 5BA",
    "wof:placetype": "postalcode"
  },
  "geometry": {"coordinates":[-3.912727,56.016989],"type":"Point"}
}
