{
  "type": "Feature",
  "properties": {
    "iso:country":"GB",
    "wof:name":"FK6 5BA",
    "wof:placetype":"postalcode"
},
  "geometry": {"coordinates":[-3.91272664452264,56.016989473604],"type":"Point"}
}