{
  "type": "Feature",
  "properties": {
    "date:inception_lower": "1980-01-01",
    "date:inception_upper": "1980-01-01",
    "iso:country": "GB",
    "wof:name": "FK6 5BA",
    "wof:placetype": "postalcode"
  },
  "geometry": {"coordinates":[-3.912727,56.016989],"type":"Point"}
}
