{
  "type": "Feature",
  "properties": {
    "iso:country": "GB",
    "wof:name": "LL18 5WT",
    "wof:placetype": "postalcode"
  },
  "geometry": {"coordinates":[-3.501702,53.26971],"type":"Point"}
}
