{
  "type": "Feature",
  "properties": {
    "iso:country":"GB",
    "wof:name":"LL18 5WT",
    "wof:placetype":"postalcode"
},
  "geometry": {"coordinates":[-3.50170215997462,53.26970996946376],"type":"Point"}
}