{
  "type": "Feature",
  "properties": {
    "date:inception_lower":"2012-10-01",
    "date:inception_upper":"2012-10-31",
    "iso:country":"GB",
    "wof:name":"CF24 3UN",
    "wof:placetype":"postalcode"
},
  "geometry": {"coordinates":[-3.170566,51.486317],"type":"Point"}
}