{
  "type": "Feature",
  "properties": {
    "iso:country":"GB",
    "wof:name":"CF24 3UN",
    "wof:placetype":"postalcode"
},
  "geometry": {"coordinates":[-3.1705657342863,51.48631706946123],"type":"Point"}
}