{
  "type": "Feature",
  "properties": {
    "iso:country":"GB",
    "wof:name":"SK1 4DW",
    "wof:placetype":"postalcode"
},
  "geometry": {"coordinates":[-2.14399506674649,53.40841968065367],"type":"Point"}
}