{
  "type": "Feature",
  "properties": {
    "iso:country": "GB",
    "wof:name": "W2 1QZ",
    "wof:placetype": "postalcode"
  },
  "geometry": {"coordinates":[-0.17302,51.516765],"type":"Point"}
}
