{
  "type": "Feature",
  "properties": {
    "date:inception_lower":"1980-01-01",
    "date:inception_upper":"1980-01-31",
    "iso:country":"GB",
    "wof:name":"IG10 3BA",
    "wof:placetype":"postalcode"
},
  "geometry": {"coordinates":[0.052644,51.634108],"type":"Point"}
}