{
  "type": "Feature",
  "properties": {
    "iso:country":"GB",
    "wof:name":"IG10 3BA",
    "wof:placetype":"postalcode"
},
  "geometry": {"coordinates":[0.05264401057538,51.63410788244224],"type":"Point"}
}