{
  "type": "Feature",
  "properties": {
    "iso:country": "GB",
    "wof:name": "B43 7PP",
    "wof:placetype": "postalcode"
  },
  "geometry": {"coordinates":[-1.912693,52.558655],"type":"Point"}
}
