{
  "type": "Feature",
  "properties": {
    "iso:country": "GB",
    "wof:name": "TN6 2PB",
    "wof:placetype": "postalcode"
  },
  "geometry": {"coordinates":[0.168044,51.048648],"type":"Point"}
}
