{
  "type": "Feature",
  "properties": {
    "iso:country":"GB",
    "wof:name":"TN6 2PB",
    "wof:placetype":"postalcode"
},
  "geometry": {"coordinates":[0.16800093065902,51.04863252775198],"type":"Point"}
}