{
  "type": "Feature",
  "properties": {
    "iso:country":"GB",
    "wof:name":"ME9 8QG",
    "wof:placetype":"postalcode"
},
  "geometry": {"coordinates":[0.70102905227066,51.37281391584018],"type":"Point"}
}