{
  "type": "Feature",
  "properties": {
    "iso:country":"GB",
    "wof:name":"E5 8RU",
    "wof:placetype":"postalcode"
},
  "geometry": {"coordinates":[-0.06194540853799,51.56467317481884],"type":"Point"}
}