{
  "type": "Feature",
  "properties": {
    "date:inception_lower": "1980-01-01",
    "date:inception_upper": "1980-01-01",
    "iso:country": "GB",
    "wof:name": "SW9 9PH",
    "wof:placetype": "postalcode"
  },
  "geometry": {"coordinates":[-0.125789,51.465704],"type":"Point"}
}
