{
  "type": "Feature",
  "properties": {
    "date:inception_lower": "1980-01-01",
    "date:inception_upper": "1980-01-01",
    "iso:country": "GB",
    "wof:name": "DE1 2HU",
    "wof:placetype": "postalcode"
  },
  "geometry": {"coordinates":[-1.475036,52.918145],"type":"Point"}
}
