{
  "type": "Feature",
  "properties": {
    "iso:country":"GB",
    "wof:name":"CV5 7NQ",
    "wof:placetype":"postalcode"
},
  "geometry": {"coordinates":[-1.59875377197107,52.41673889756073],"type":"Point"}
}