{
  "type": "Feature",
  "properties": {
    "iso:country":"GB",
    "wof:name":"BS13 0QX",
    "wof:placetype":"postalcode"
},
  "geometry": {"coordinates":[-2.58617063306447,51.40577812316695],"type":"Point"}
}