{
  "type": "Feature",
  "properties": {
    "iso:country":"GB",
    "wof:name":"SM4 4PX",
    "wof:placetype":"postalcode"
},
  "geometry": {"coordinates":[-0.22268876101025,51.38690110867684],"type":"Point"}
}