{
  "type": "Feature",
  "properties": {
    "iso:country":"GB",
    "wof:name":"S3 7HN",
    "wof:placetype":"postalcode"
},
  "geometry": {"coordinates":[-1.48206953614059,53.38351991778377],"type":"Point"}
}