{
  "type": "Feature",
  "properties": {
    "iso:country":"GB",
    "wof:name":"MK19 7DA",
    "wof:placetype":"postalcode"
},
  "geometry": {"coordinates":[-0.83883673261378,52.12228056699202],"type":"Point"}
}