{
  "type": "Feature",
  "properties": {
    "iso:country": "GB",
    "wof:name": "MK19 7DA",
    "wof:placetype": "postalcode"
  },
  "geometry": {"coordinates":[-0.838837,52.122281],"type":"Point"}
}
