{
  "type": "Feature",
  "properties": {
    "iso:country":"GB",
    "wof:name":"DL4 2HL",
    "wof:placetype":"postalcode"
},
  "geometry": {"coordinates":[-1.64373671178654,54.6378310836344],"type":"Point"}
}