{
  "type": "Feature",
  "properties": {
    "iso:country":"GB",
    "wof:name":"SR6 8HG",
    "wof:placetype":"postalcode"
},
  "geometry": {"coordinates":[-1.37920283086962,54.93156279746592],"type":"Point"}
}