{
  "type": "Feature",
  "properties": {
    "date:inception_lower": "1980-01-01",
    "date:inception_upper": "1980-01-01",
    "iso:country": "GB",
    "wof:name": "SR6 8HG",
    "wof:placetype": "postalcode"
  },
  "geometry": {"coordinates":[-1.379203,54.931563],"type":"Point"}
}
