{
  "type": "Feature",
  "properties": {
    "iso:country":"GB",
    "wof:name":"WR14 2RU",
    "wof:placetype":"postalcode"
},
  "geometry": {"coordinates":[-2.312677341939,52.12365078011113],"type":"Point"}
}