{
  "type": "Feature",
  "properties": {
    "iso:country": "GB",
    "wof:name": "PE33 9RN",
    "wof:placetype": "postalcode"
  },
  "geometry": {"coordinates":[0.432677,52.58339],"type":"Point"}
}
