{
  "type": "Feature",
  "properties": {
    "date:inception_lower": "1980-01-01",
    "date:inception_upper": "1980-01-01",
    "iso:country": "GB",
    "wof:name": "PE33 9RN",
    "wof:placetype": "postalcode"
  },
  "geometry": {"coordinates":[0.432677,52.58339],"type":"Point"}
}
