{
  "type": "Feature",
  "properties": {
    "iso:country":"GB",
    "wof:name":"PE33 9RN",
    "wof:placetype":"postalcode"
},
  "geometry": {"coordinates":[0.43267735947932,52.58339004682783],"type":"Point"}
}