{
  "type": "Feature",
  "properties": {
    "iso:country": "GB",
    "wof:name": "N19 4AR",
    "wof:placetype": "postalcode"
  },
  "geometry": {"coordinates":[-0.130224,51.566689],"type":"Point"}
}
