{
  "type": "Feature",
  "properties": {
    "iso:country":"GB",
    "wof:name":"N19 4AR",
    "wof:placetype":"postalcode"
},
  "geometry": {"coordinates":[-0.13022438595193,51.56668931694697],"type":"Point"}
}