{
  "type": "Feature",
  "properties": {
    "date:inception_lower":"1997-12-01",
    "date:inception_upper":"1997-12-31",
    "iso:country":"GB",
    "wof:name":"BS39 5UJ",
    "wof:placetype":"postalcode"
},
  "geometry": {"coordinates":[-2.582975,51.325156],"type":"Point"}
}