{
  "type": "Feature",
  "properties": {
    "iso:country":"GB",
    "wof:name":"BS39 5UJ",
    "wof:placetype":"postalcode"
},
  "geometry": {"coordinates":[-2.58297472274173,51.32515584341407],"type":"Point"}
}