{
  "type": "Feature",
  "properties": {
    "iso:country":"GB",
    "wof:name":"B68 8LS",
    "wof:placetype":"postalcode"
},
  "geometry": {"coordinates":[-2.01649262212943,52.48327835752977],"type":"Point"}
}