{
  "type": "Feature",
  "properties": {
    "iso:country":"GB",
    "wof:name":"SA10 9DU",
    "wof:placetype":"postalcode"
},
  "geometry": {"coordinates":[-3.7149057424803,51.76626249989285],"type":"Point"}
}