{
  "type": "Feature",
  "properties": {
    "iso:country":"GB",
    "wof:name":"KT14 6NA",
    "wof:placetype":"postalcode"
},
  "geometry": {"coordinates":[-0.50435938128974,51.33852625395774],"type":"Point"}
}