{
  "type": "Feature",
  "properties": {
    "date:inception_lower": "1994-05-01",
    "date:inception_upper": "1994-05-01",
    "iso:country": "GB",
    "wof:name": "CM15 0JN",
    "wof:placetype": "postalcode"
  },
  "geometry": {"coordinates":[0.270836,51.657225],"type":"Point"}
}
