{
  "type": "Feature",
  "properties": {
    "iso:country":"GB",
    "wof:name":"SE12 9LY",
    "wof:placetype":"postalcode"
},
  "geometry": {"coordinates":[0.02130803385806,51.44356646194287],"type":"Point"}
}