{
  "type": "Feature",
  "properties": {
    "iso:country":"GB",
    "wof:name":"BB5 6ER",
    "wof:placetype":"postalcode"
},
  "geometry": {"coordinates":[-2.36159048027645,53.75527684655216],"type":"Point"}
}