{
  "type": "Feature",
  "properties": {
    "iso:country":"GB",
    "wof:name":"WV8 2EL",
    "wof:placetype":"postalcode"
},
  "geometry": {"coordinates":[-2.20083899671112,52.62557092963409],"type":"Point"}
}