{
  "type": "Feature",
  "properties": {
    "date:inception_lower": "1980-01-01",
    "date:inception_upper": "1980-01-01",
    "iso:country": "GB",
    "wof:name": "WV8 2EL",
    "wof:placetype": "postalcode"
  },
  "geometry": {"coordinates":[-2.200839,52.625571],"type":"Point"}
}
