{
  "type": "Feature",
  "properties": {
    "iso:country":"GB",
    "wof:name":"DG12 5LQ",
    "wof:placetype":"postalcode"
},
  "geometry": {"coordinates":[-3.24549577173832,54.99530645400355],"type":"Point"}
}