{
  "type": "Feature",
  "properties": {
    "iso:country": "GB",
    "wof:name": "DG12 5LQ",
    "wof:placetype": "postalcode"
  },
  "geometry": {"coordinates":[-3.245496,54.995306],"type":"Point"}
}
