{
  "type": "Feature",
  "properties": {
    "iso:country":"GB",
    "wof:name":"G84 0RG",
    "wof:placetype":"postalcode"
},
  "geometry": {"coordinates":[-4.80192462741424,56.01031175065603],"type":"Point"}
}