{
  "type": "Feature",
  "properties": {
    "iso:country":"GB",
    "wof:name":"EH15 2EP",
    "wof:placetype":"postalcode"
},
  "geometry": {"coordinates":[-3.0981074489341,55.9494177566033],"type":"Point"}
}