{
  "type": "Feature",
  "properties": {
    "iso:country": "GB",
    "wof:name": "PO15 7FL",
    "wof:placetype": "postalcode"
  },
  "geometry": {"coordinates":[-1.239356,50.882845],"type":"Point"}
}
