{
  "type": "Feature",
  "properties": {
    "iso:country": "GB",
    "wof:name": "WF1 4FW",
    "wof:placetype": "postalcode"
  },
  "geometry": {"coordinates":[-1.478538,53.695636],"type":"Point"}
}
