{
  "type": "Feature",
  "properties": {
    "iso:country":"GB",
    "wof:name":"LL17 0BU",
    "wof:placetype":"postalcode"
},
  "geometry": {"coordinates":[-3.44143803926496,53.25819215797001],"type":"Point"}
}