{
  "type": "Feature",
  "properties": {
    "iso:country":"GB",
    "wof:name":"M15 4TB",
    "wof:placetype":"postalcode"
},
  "geometry": {"coordinates":[-2.24899283073353,53.47262247491279],"type":"Point"}
}