{
  "type": "Feature",
  "properties": {
    "iso:country":"GB",
    "wof:name":"IP28 8SQ",
    "wof:placetype":"postalcode"
},
  "geometry": {"coordinates":[0.47899805664745,52.33393089860914],"type":"Point"}
}