{
  "type": "Feature",
  "properties": {
    "iso:country": "GB",
    "wof:name": "GU26 6JT",
    "wof:placetype": "postalcode"
  },
  "geometry": {"coordinates":[-0.748204,51.109329],"type":"Point"}
}
