{
  "type": "Feature",
  "properties": {
    "iso:country":"GB",
    "wof:name":"GU26 6JT",
    "wof:placetype":"postalcode"
},
  "geometry": {"coordinates":[-0.74820407191503,51.10932909577456],"type":"Point"}
}