{
  "type": "Feature",
  "properties": {
    "iso:country":"GB",
    "wof:name":"LS28 9JP",
    "wof:placetype":"postalcode"
},
  "geometry": {"coordinates":[-1.64764002042789,53.7960396944837],"type":"Point"}
}