{
  "type": "Feature",
  "properties": {
    "iso:country":"GB",
    "wof:name":"BS40 8RE",
    "wof:placetype":"postalcode"
},
  "geometry": {"coordinates":[-2.60932001409096,51.36705842221909],"type":"Point"}
}