{
  "type": "Feature",
  "properties": {
    "date:inception_lower":"1997-12-01",
    "date:inception_upper":"1997-12-31",
    "iso:country":"GB",
    "wof:name":"BS40 8RE",
    "wof:placetype":"postalcode"
},
  "geometry": {"coordinates":[-2.60932,51.367058],"type":"Point"}
}