{
  "type": "Feature",
  "properties": {
    "iso:country":"GB",
    "wof:name":"M25 3HG",
    "wof:placetype":"postalcode"
},
  "geometry": {"coordinates":[-2.28927687000766,53.53221487498175],"type":"Point"}
}