{
  "type": "Feature",
  "properties": {
    "date:inception_lower": "1994-05-01",
    "date:inception_upper": "1994-05-01",
    "iso:country": "GB",
    "wof:name": "M25 3HG",
    "wof:placetype": "postalcode"
  },
  "geometry": {"coordinates":[-2.28929,53.532276],"type":"Point"}
}
