{
  "type": "Feature",
  "properties": {
    "iso:country":"GB",
    "wof:name":"S71 2QT",
    "wof:placetype":"postalcode"
},
  "geometry": {"coordinates":[-1.46357320873344,53.56674193922506],"type":"Point"}
}