{
  "type": "Feature",
  "properties": {
    "iso:country": "GB",
    "wof:name": "S71 2QT",
    "wof:placetype": "postalcode"
  },
  "geometry": {"coordinates":[-1.463573,53.566742],"type":"Point"}
}
