{
  "type": "Feature",
  "properties": {
    "date:inception_lower":"1991-01-01",
    "date:inception_upper":"1991-01-31",
    "iso:country":"GB",
    "wof:name":"SM1 4EH",
    "wof:placetype":"postalcode"
},
  "geometry": {"coordinates":[-0.191488,51.369742],"type":"Point"}
}