{
  "type": "Feature",
  "properties": {
    "iso:country":"GB",
    "wof:name":"SM1 4EH",
    "wof:placetype":"postalcode"
},
  "geometry": {"coordinates":[-0.19148770793427,51.36974234162153],"type":"Point"}
}