{
  "type": "Feature",
  "properties": {
    "iso:country":"GB",
    "wof:name":"WA15 0JF",
    "wof:placetype":"postalcode"
},
  "geometry": {"coordinates":[-2.31155670540779,53.36731838415302],"type":"Point"}
}