{
  "type": "Feature",
  "properties": {
    "iso:country": "GB",
    "wof:name": "CO1 2NA",
    "wof:placetype": "postalcode"
  },
  "geometry": {"coordinates":[0.918171,51.883895],"type":"Point"}
}
