{
  "type": "Feature",
  "properties": {
    "iso:country":"GB",
    "wof:name":"CO1 2NA",
    "wof:placetype":"postalcode"
},
  "geometry": {"coordinates":[0.91787678260191,51.88383613328887],"type":"Point"}
}