{
  "type": "Feature",
  "properties": {
    "iso:country":"GB",
    "wof:name":"KW17 2TA",
    "wof:placetype":"postalcode"
},
  "geometry": {"coordinates":[-2.89198831611347,58.84755172507474],"type":"Point"}
}