{
  "type": "Feature",
  "properties": {
    "iso:country": "GB",
    "wof:name": "KW17 2TA",
    "wof:placetype": "postalcode"
  },
  "geometry": {"coordinates":[-2.891988,58.847552],"type":"Point"}
}
