{
  "type": "Feature",
  "properties": {
    "date:inception_lower":"1980-01-01",
    "date:inception_upper":"1980-01-31",
    "iso:country":"GB",
    "wof:name":"KW17 2TA",
    "wof:placetype":"postalcode"
},
  "geometry": {"coordinates":[-2.891988,58.847552],"type":"Point"}
}