{
  "type": "Feature",
  "properties": {
    "iso:country": "GB",
    "wof:name": "S42 7BX",
    "wof:placetype": "postalcode"
  },
  "geometry": {"coordinates":[-1.528617,53.234643],"type":"Point"}
}
