{
  "type": "Feature",
  "properties": {
    "date:inception_lower": "1980-01-01",
    "date:inception_upper": "1980-01-01",
    "iso:country": "GB",
    "wof:name": "S42 7BX",
    "wof:placetype": "postalcode"
  },
  "geometry": {"coordinates":[-1.529127,53.234609],"type":"Point"}
}
