{
  "type": "Feature",
  "properties": {
    "date:inception_lower": "2003-09-01",
    "date:inception_upper": "2003-09-01",
    "iso:country": "GB",
    "wof:name": "SS6 9RP",
    "wof:placetype": "postalcode"
  },
  "geometry": {"coordinates":[0.601784,51.602094],"type":"Point"}
}
