{
  "type": "Feature",
  "properties": {
    "date:inception_lower": "1996-06-01",
    "date:inception_upper": "1996-06-01",
    "iso:country": "GB",
    "wof:name": "AB10 6JN",
    "wof:placetype": "postalcode"
  },
  "geometry": {"coordinates":[-2.123691,57.130125],"type":"Point"}
}
