{
  "type": "Feature",
  "properties": {
    "iso:country": "GB",
    "wof:name": "BL1 8HH",
    "wof:placetype": "postalcode"
  },
  "geometry": {"coordinates":[-2.426089,53.594578],"type":"Point"}
}
