{
  "type": "Feature",
  "properties": {
    "date:inception_lower": "2019-10-01",
    "date:inception_upper": "2019-10-01",
    "iso:country": "GB",
    "wof:name": "BL1 8HH",
    "wof:placetype": "postalcode"
  },
  "geometry": {"coordinates":[-2.426089,53.594578],"type":"Point"}
}
