{
  "type": "Feature",
  "properties": {
    "iso:country":"GB",
    "wof:name":"RG6 5SH",
    "wof:placetype":"postalcode"
},
  "geometry": {"coordinates":[-0.94063456277513,51.43428237364432],"type":"Point"}
}