{
  "type": "Feature",
  "properties": {
    "iso:country": "GB",
    "wof:name": "BB9 5DH",
    "wof:placetype": "postalcode"
  },
  "geometry": {"coordinates":[-2.230651,53.825496],"type":"Point"}
}
