{
  "type": "Feature",
  "properties": {
    "iso:country":"GB",
    "wof:name":"BB9 5DH",
    "wof:placetype":"postalcode"
},
  "geometry": {"coordinates":[-2.23022439696762,53.82551896253895],"type":"Point"}
}