{
  "type": "Feature",
  "properties": {
    "iso:country":"GB",
    "wof:name":"SE3 8TN",
    "wof:placetype":"postalcode"
},
  "geometry": {"coordinates":[0.02641235911917,51.47856814380125],"type":"Point"}
}