{
  "type": "Feature",
  "properties": {
    "iso:country": "GB",
    "wof:name": "BS16 7LT",
    "wof:placetype": "postalcode"
  },
  "geometry": {"coordinates":[-2.463315,51.496018],"type":"Point"}
}
