{
  "type": "Feature",
  "properties": {
    "date:inception_lower":"1980-01-01",
    "date:inception_upper":"1980-01-31",
    "iso:country":"GB",
    "wof:name":"NR14 8BX",
    "wof:placetype":"postalcode"
},
  "geometry": {"coordinates":[1.231837,52.558903],"type":"Point"}
}