{
  "type": "Feature",
  "properties": {
    "iso:country": "GB",
    "wof:name": "NR14 8BX",
    "wof:placetype": "postalcode"
  },
  "geometry": {"coordinates":[1.231837,52.558903],"type":"Point"}
}
