{
  "type": "Feature",
  "properties": {
    "iso:country":"GB",
    "wof:name":"TN5 6UH",
    "wof:placetype":"postalcode"
},
  "geometry": {"coordinates":[0.33186443257477,51.06757450967719],"type":"Point"}
}