{
  "type": "Feature",
  "properties": {
    "date:inception_lower": "1980-01-01",
    "date:inception_upper": "1980-01-01",
    "iso:country": "GB",
    "wof:name": "NG2 4QP",
    "wof:placetype": "postalcode"
  },
  "geometry": {"coordinates":[-1.132506,52.953292],"type":"Point"}
}
