{
  "type": "Feature",
  "properties": {
    "iso:country":"GB",
    "wof:name":"PE11 4NS",
    "wof:placetype":"postalcode"
},
  "geometry": {"coordinates":[-0.14807379286564,52.86526832924007],"type":"Point"}
}