{
  "type": "Feature",
  "properties": {
    "date:inception_lower": "1995-07-01",
    "date:inception_upper": "1995-07-01",
    "iso:country": "GB",
    "wof:name": "SY8 1GT",
    "wof:placetype": "postalcode"
  },
  "geometry": {"coordinates":[-2.715958,52.368905],"type":"Point"}
}
