{
  "type": "Feature",
  "properties": {
    "iso:country":"GB",
    "wof:name":"SY8 1GT",
    "wof:placetype":"postalcode"
},
  "geometry": {"coordinates":[-2.71595811234265,52.36890477715487],"type":"Point"}
}