{
  "type": "Feature",
  "properties": {
    "iso:country":"GB",
    "wof:name":"PE19 2AF",
    "wof:placetype":"postalcode"
},
  "geometry": {"coordinates":[-0.27038336616555,52.22720229714827],"type":"Point"}
}