{
  "type": "Feature",
  "properties": {
    "date:inception_lower": "1980-01-01",
    "date:inception_upper": "1980-01-01",
    "iso:country": "GB",
    "wof:name": "PE19 2AF",
    "wof:placetype": "postalcode"
  },
  "geometry": {"coordinates":[-0.270383,52.227202],"type":"Point"}
}
