{
  "type": "Feature",
  "properties": {
    "iso:country":"GB",
    "wof:name":"G3 6DL",
    "wof:placetype":"postalcode"
},
  "geometry": {"coordinates":[-4.28022411319539,55.86958375716475],"type":"Point"}
}