{
  "type": "Feature",
  "properties": {
    "iso:country":"GB",
    "wof:name":"LS29 8NA",
    "wof:placetype":"postalcode"
},
  "geometry": {"coordinates":[-1.80098099960407,53.92833384305886],"type":"Point"}
}