{
  "type": "Feature",
  "properties": {
    "date:inception_lower": "1980-01-01",
    "date:inception_upper": "1980-01-01",
    "iso:country": "GB",
    "wof:name": "LS29 8NA",
    "wof:placetype": "postalcode"
  },
  "geometry": {"coordinates":[-1.800981,53.928334],"type":"Point"}
}
