{
  "type": "Feature",
  "properties": {
    "iso:country":"GB",
    "wof:name":"PA34 5QD",
    "wof:placetype":"postalcode"
},
  "geometry": {"coordinates":[-5.47476053225791,56.41481725216802],"type":"Point"}
}