{
  "type": "Feature",
  "properties": {
    "date:inception_lower":"1980-01-01",
    "date:inception_upper":"1980-01-31",
    "iso:country":"GB",
    "wof:name":"PA34 5QD",
    "wof:placetype":"postalcode"
},
  "geometry": {"coordinates":[-5.474148,56.41473],"type":"Point"}
}