{
  "type": "Feature",
  "properties": {
    "iso:country": "GB",
    "wof:name": "PA34 5QD",
    "wof:placetype": "postalcode"
  },
  "geometry": {"coordinates":[-5.474105,56.414794],"type":"Point"}
}
