{
  "type": "Feature",
  "properties": {
    "iso:country": "GB",
    "wof:name": "PA34 5QD",
    "wof:placetype": "postalcode"
  },
  "geometry": {"coordinates":[-5.474148,56.41473],"type":"Point"}
}
