{
  "type": "Feature",
  "properties": {
    "date:inception_lower": "1980-01-01",
    "date:inception_upper": "1980-01-01",
    "iso:country": "GB",
    "wof:name": "LE15 8QZ",
    "wof:placetype": "postalcode"
  },
  "geometry": {"coordinates":[-0.770305,52.649444],"type":"Point"}
}
