{
  "type": "Feature",
  "properties": {
    "iso:country":"GB",
    "wof:name":"LE15 8QZ",
    "wof:placetype":"postalcode"
},
  "geometry": {"coordinates":[-0.77030523568731,52.64944368981082],"type":"Point"}
}