{
  "type": "Feature",
  "properties": {
    "iso:country":"GB",
    "wof:name":"PO18 9DA",
    "wof:placetype":"postalcode"
},
  "geometry": {"coordinates":[-0.85265477085864,50.86604382466785],"type":"Point"}
}