{
  "type": "Feature",
  "properties": {
    "date:inception_lower": "1996-12-01",
    "date:inception_upper": "1996-12-01",
    "iso:country": "GB",
    "wof:name": "PO18 9DA",
    "wof:placetype": "postalcode"
  },
  "geometry": {"coordinates":[-0.853326,50.866321],"type":"Point"}
}
