{
  "type": "Feature",
  "properties": {
    "iso:country": "GB",
    "wof:name": "PO18 9DA",
    "wof:placetype": "postalcode"
  },
  "geometry": {"coordinates":[-0.853008,50.865967],"type":"Point"}
}
