{
  "type": "Feature",
  "properties": {
    "date:inception_lower": "2003-03-01",
    "date:inception_upper": "2003-03-01",
    "iso:country": "GB",
    "wof:name": "S11 8HF",
    "wof:placetype": "postalcode"
  },
  "geometry": {"coordinates":[-1.483391,53.372461],"type":"Point"}
}
