{
  "type": "Feature",
  "properties": {
    "iso:country":"GB",
    "wof:name":"S11 8HF",
    "wof:placetype":"postalcode"
},
  "geometry": {"coordinates":[-1.48339102419958,53.37246055667465],"type":"Point"}
}