{
  "type": "Feature",
  "properties": {
    "iso:country":"GB",
    "wof:name":"S72 8JZ",
    "wof:placetype":"postalcode"
},
  "geometry": {"coordinates":[-1.41600645139375,53.5758582704388],"type":"Point"}
}