{
  "type": "Feature",
  "properties": {
    "iso:country":"GB",
    "wof:name":"E18 2BF",
    "wof:placetype":"postalcode"
},
  "geometry": {"coordinates":[0.01900435920318,51.6002947159304],"type":"Point"}
}