{
  "type": "Feature",
  "properties": {
    "iso:country": "GB",
    "wof:name": "E18 2BF",
    "wof:placetype": "postalcode"
  },
  "geometry": {"coordinates":[0.019031,51.600296],"type":"Point"}
}
