{
  "type": "Feature",
  "properties": {
    "date:inception_lower": "2001-12-01",
    "date:inception_upper": "2001-12-01",
    "iso:country": "GB",
    "wof:name": "BN21 2NG",
    "wof:placetype": "postalcode"
  },
  "geometry": {"coordinates":[0.267281,50.778544],"type":"Point"}
}
