{
  "type": "Feature",
  "properties": {
    "iso:country":"GB",
    "wof:name":"W10 5NZ",
    "wof:placetype":"postalcode"
},
  "geometry": {"coordinates":[-0.20987750217774,51.522448027086],"type":"Point"}
}