{
  "type": "Feature",
  "properties": {
    "iso:country":"GB",
    "wof:name":"S65 2BW",
    "wof:placetype":"postalcode"
},
  "geometry": {"coordinates":[-1.34019106901558,53.43512576843347],"type":"Point"}
}