{
  "type": "Feature",
  "properties": {
    "iso:country":"GB",
    "wof:name":"NN2 6QY",
    "wof:placetype":"postalcode"
},
  "geometry": {"coordinates":[-0.90766739710532,52.2606053256937],"type":"Point"}
}