{
  "type": "Feature",
  "properties": {
    "iso:country": "GB",
    "wof:name": "RM15 6SD",
    "wof:placetype": "postalcode"
  },
  "geometry": {"coordinates":[0.29821,51.523423],"type":"Point"}
}
