{
  "type": "Feature",
  "properties": {
    "iso:country":"GB",
    "wof:name":"TS12 1BJ",
    "wof:placetype":"postalcode"
},
  "geometry": {"coordinates":[-0.97469175534716,54.58276249481219],"type":"Point"}
}