{
  "type": "Feature",
  "properties": {
    "iso:country":"GB",
    "wof:name":"G66 2UW",
    "wof:placetype":"postalcode"
},
  "geometry": {"coordinates":[-4.11904725304011,55.94652801482211],"type":"Point"}
}