{
  "type": "Feature",
  "properties": {
    "iso:country": "GB",
    "wof:name": "G66 2UW",
    "wof:placetype": "postalcode"
  },
  "geometry": {"coordinates":[-4.119047,55.946528],"type":"Point"}
}
