{
  "type": "Feature",
  "properties": {
    "date:inception_lower": "1980-01-01",
    "date:inception_upper": "1980-01-01",
    "iso:country": "GB",
    "wof:name": "DL6 3AP",
    "wof:placetype": "postalcode"
  },
  "geometry": {"coordinates":[-1.305771,54.375851],"type":"Point"}
}
