{
  "type": "Feature",
  "properties": {
    "iso:country":"GB",
    "wof:name":"DL6 3AP",
    "wof:placetype":"postalcode"
},
  "geometry": {"coordinates":[-1.30574716546714,54.37569506039964],"type":"Point"}
}