{
  "type": "Feature",
  "properties": {
    "iso:country": "GB",
    "wof:name": "DL6 3AP",
    "wof:placetype": "postalcode"
  },
  "geometry": {"coordinates":[-1.305929,54.375592],"type":"Point"}
}
