{
  "type": "Feature",
  "properties": {
    "iso:country":"GB",
    "wof:name":"LS21 1LS",
    "wof:placetype":"postalcode"
},
  "geometry": {"coordinates":[-1.62866954426071,53.90363997289126],"type":"Point"}
}