{
  "type": "Feature",
  "properties": {
    "date:inception_lower": "1980-01-01",
    "date:inception_upper": "1980-01-01",
    "iso:country": "GB",
    "wof:name": "LS21 1LS",
    "wof:placetype": "postalcode"
  },
  "geometry": {"coordinates":[-1.628669,53.90364],"type":"Point"}
}
