{
  "type": "Feature",
  "properties": {
    "iso:country":"GB",
    "wof:name":"N7 8QJ",
    "wof:placetype":"postalcode"
},
  "geometry": {"coordinates":[-0.11106758000756,51.55055573059239],"type":"Point"}
}