{
  "type": "Feature",
  "properties": {
    "iso:country":"GB",
    "wof:name":"WA7 4XW",
    "wof:placetype":"postalcode"
},
  "geometry": {"coordinates":[-2.71429591315776,53.31656176001611],"type":"Point"}
}