{
  "type": "Feature",
  "properties": {
    "date:inception_lower": "2016-01-01",
    "date:inception_upper": "2016-01-01",
    "iso:country": "GB",
    "wof:name": "SO31 6BS",
    "wof:placetype": "postalcode"
  },
  "geometry": {"coordinates":[-1.286296,50.861371],"type":"Point"}
}
