{
  "type": "Feature",
  "properties": {
    "iso:country": "GB",
    "wof:name": "AB56 4NS",
    "wof:placetype": "postalcode"
  },
  "geometry": {"coordinates":[-2.863752,57.702476],"type":"Point"}
}
