{
  "type": "Feature",
  "properties": {
    "iso:country":"GB",
    "wof:name":"AB56 4NS",
    "wof:placetype":"postalcode"
},
  "geometry": {"coordinates":[-2.86375247636582,57.70247625398721],"type":"Point"}
}