{
  "type": "Feature",
  "properties": {
    "iso:country": "GB",
    "wof:name": "LL33 0SF",
    "wof:placetype": "postalcode"
  },
  "geometry": {"coordinates":[-3.970377,53.250927],"type":"Point"}
}
