{
  "type": "Feature",
  "properties": {
    "iso:country": "GB",
    "wof:name": "PE28 2BJ",
    "wof:placetype": "postalcode"
  },
  "geometry": {"coordinates":[-0.119122,52.334027],"type":"Point"}
}
