{
  "type": "Feature",
  "properties": {
    "iso:country":"GB",
    "wof:name":"PE28 2BJ",
    "wof:placetype":"postalcode"
},
  "geometry": {"coordinates":[-0.11912167068194,52.33402708043938],"type":"Point"}
}