{
  "type": "Feature",
  "properties": {
    "iso:country": "GB",
    "wof:name": "IP31 3PF",
    "wof:placetype": "postalcode"
  },
  "geometry": {"coordinates":[0.807219,52.251655],"type":"Point"}
}
