{
  "type": "Feature",
  "properties": {
    "iso:country":"GB",
    "wof:name":"IP31 3PF",
    "wof:placetype":"postalcode"
},
  "geometry": {"coordinates":[0.80721862890275,52.25165455323241],"type":"Point"}
}