{
  "type": "Feature",
  "properties": {
    "date:inception_lower": "1980-01-01",
    "date:inception_upper": "1980-01-01",
    "iso:country": "GB",
    "wof:name": "EH12 7DP",
    "wof:placetype": "postalcode"
  },
  "geometry": {"coordinates":[-3.279205,55.935729],"type":"Point"}
}
