{
  "type": "Feature",
  "properties": {
    "date:inception_lower": "1980-01-01",
    "date:inception_upper": "1980-01-01",
    "iso:country": "GB",
    "wof:name": "CF42 6AP",
    "wof:placetype": "postalcode"
  },
  "geometry": {"coordinates":[-3.508891,51.660314],"type":"Point"}
}
