{
  "type": "Feature",
  "properties": {
    "iso:country":"GB",
    "wof:name":"CF42 6AP",
    "wof:placetype":"postalcode"
},
  "geometry": {"coordinates":[-3.50889115717184,51.66031391238224],"type":"Point"}
}