{
  "type": "Feature",
  "properties": {
    "iso:country": "GB",
    "wof:name": "TR1 2AX",
    "wof:placetype": "postalcode"
  },
  "geometry": {"coordinates":[-5.053439,50.2644],"type":"Point"}
}
