{
  "type": "Feature",
  "properties": {
    "date:inception_lower": "1980-01-01",
    "date:inception_upper": "1980-01-01",
    "iso:country": "GB",
    "wof:name": "TR1 2AX",
    "wof:placetype": "postalcode"
  },
  "geometry": {"coordinates":[-5.053439,50.2644],"type":"Point"}
}
