{
  "type": "Feature",
  "properties": {
    "iso:country":"GB",
    "wof:name":"DT2 7RF",
    "wof:placetype":"postalcode"
},
  "geometry": {"coordinates":[-2.38108403372765,50.80297503021855],"type":"Point"}
}