{
  "type": "Feature",
  "properties": {
    "date:inception_lower": "1980-01-01",
    "date:inception_upper": "1980-01-01",
    "iso:country": "GB",
    "wof:name": "DT2 7RF",
    "wof:placetype": "postalcode"
  },
  "geometry": {"coordinates":[-2.381084,50.802975],"type":"Point"}
}
