{
  "type": "Feature",
  "properties": {
    "iso:country": "GB",
    "wof:name": "DT2 7RF",
    "wof:placetype": "postalcode"
  },
  "geometry": {"coordinates":[-2.381084,50.802975],"type":"Point"}
}
