{
  "type": "Feature",
  "properties": {
    "iso:country":"GB",
    "wof:name":"SL2 1AJ",
    "wof:placetype":"postalcode"
},
  "geometry": {"coordinates":[-0.61534303988185,51.52956200520127],"type":"Point"}
}