{
  "type": "Feature",
  "properties": {
    "iso:country":"GB",
    "wof:name":"EH16 5LD",
    "wof:placetype":"postalcode"
},
  "geometry": {"coordinates":[-3.16049827204901,55.92966190485754],"type":"Point"}
}