{
  "type": "Feature",
  "properties": {
    "iso:country":"GB",
    "wof:name":"NE65 0AD",
    "wof:placetype":"postalcode"
},
  "geometry": {"coordinates":[-1.579876291428,55.3353464959748],"type":"Point"}
}