{
  "type": "Feature",
  "properties": {
    "iso:country":"GB",
    "wof:name":"WA1 3RF",
    "wof:placetype":"postalcode"
},
  "geometry": {"coordinates":[-2.56962175227338,53.3964325554985],"type":"Point"}
}