{
  "type": "Feature",
  "properties": {
    "iso:country": "GB",
    "wof:name": "NP25 4AY",
    "wof:placetype": "postalcode"
  },
  "geometry": {"coordinates":[-2.722564,51.747633],"type":"Point"}
}
