{
  "type": "Feature",
  "properties": {
    "iso:country":"GB",
    "wof:name":"CA10 3NG",
    "wof:placetype":"postalcode"
},
  "geometry": {"coordinates":[-2.67771734654597,54.53183031371015],"type":"Point"}
}