{
  "type": "Feature",
  "properties": {
    "date:inception_lower":"1980-01-01",
    "date:inception_upper":"1980-01-31",
    "iso:country":"GB",
    "wof:name":"CA10 3NG",
    "wof:placetype":"postalcode"
},
  "geometry": {"coordinates":[-2.677717,54.53183],"type":"Point"}
}