{
  "type": "Feature",
  "properties": {
    "iso:country": "GB",
    "wof:name": "CA10 3NG",
    "wof:placetype": "postalcode"
  },
  "geometry": {"coordinates":[-2.677717,54.53183],"type":"Point"}
}
