{
  "type": "Feature",
  "properties": {
    "iso:country":"GB",
    "wof:name":"FK2 7NJ",
    "wof:placetype":"postalcode"
},
  "geometry": {"coordinates":[-3.78615556531145,56.01518559411625],"type":"Point"}
}