{
  "type": "Feature",
  "properties": {
    "iso:country":"GB",
    "wof:name":"SE7 7SN",
    "wof:placetype":"postalcode"
},
  "geometry": {"coordinates":[0.0291705236373,51.49106532471172],"type":"Point"}
}