{
  "type": "Feature",
  "properties": {
    "iso:country":"GB",
    "wof:name":"PE23 4DT",
    "wof:placetype":"postalcode"
},
  "geometry": {"coordinates":[0.05064331809166,53.18582102033063],"type":"Point"}
}