{
  "type": "Feature",
  "properties": {
    "iso:country": "GB",
    "wof:name": "NE69 7AW",
    "wof:placetype": "postalcode"
  },
  "geometry": {"coordinates":[-1.73408,55.594202],"type":"Point"}
}
