{
  "type": "Feature",
  "properties": {
    "iso:country":"GB",
    "wof:name":"GL50 2UB",
    "wof:placetype":"postalcode"
},
  "geometry": {"coordinates":[-2.08834663470198,51.89214498736981],"type":"Point"}
}