{
  "type": "Feature",
  "properties": {
    "iso:country": "GB",
    "wof:name": "GL50 2UB",
    "wof:placetype": "postalcode"
  },
  "geometry": {"coordinates":[-2.088347,51.892145],"type":"Point"}
}
