{
  "type": "Feature",
  "properties": {
    "iso:country": "GB",
    "wof:name": "RH13 0LU",
    "wof:placetype": "postalcode"
  },
  "geometry": {"coordinates":[-0.366102,51.044434],"type":"Point"}
}
