{
  "type": "Feature",
  "properties": {
    "iso:country":"GB",
    "wof:name":"TR9 6RZ",
    "wof:placetype":"postalcode"
},
  "geometry": {"coordinates":[-4.94396231556611,50.42999952521538],"type":"Point"}
}