{
  "type": "Feature",
  "properties": {
    "date:inception_lower": "2000-12-01",
    "date:inception_upper": "2000-12-01",
    "iso:country": "GB",
    "wof:name": "BD20 0DY",
    "wof:placetype": "postalcode"
  },
  "geometry": {"coordinates":[-1.938526,53.910282],"type":"Point"}
}
