{
  "type": "Feature",
  "properties": {
    "iso:country":"GB",
    "wof:name":"BA3 4TL",
    "wof:placetype":"postalcode"
},
  "geometry": {"coordinates":[-2.54253179554334,51.24117719692508],"type":"Point"}
}