{
  "type": "Feature",
  "properties": {
    "date:inception_lower": "2011-03-01",
    "date:inception_upper": "2011-03-01",
    "iso:country": "GB",
    "wof:name": "NR14 7PP",
    "wof:placetype": "postalcode"
  },
  "geometry": {"coordinates":[1.384242,52.566204],"type":"Point"}
}
