{
  "type": "Feature",
  "properties": {
    "iso:country": "GB",
    "wof:name": "NR14 7PP",
    "wof:placetype": "postalcode"
  },
  "geometry": {"coordinates":[1.384132,52.56603],"type":"Point"}
}
