{
  "type": "Feature",
  "properties": {
    "iso:country":"GB",
    "wof:name":"EX34 8LL",
    "wof:placetype":"postalcode"
},
  "geometry": {"coordinates":[-4.14982589526803,51.1927178796421],"type":"Point"}
}