{
  "type": "Feature",
  "properties": {
    "iso:country": "GB",
    "wof:name": "EH16 4QL",
    "wof:placetype": "postalcode"
  },
  "geometry": {"coordinates":[-3.124124,55.934842],"type":"Point"}
}
