{
  "type": "Feature",
  "properties": {
    "date:inception_lower": "2005-01-01",
    "date:inception_upper": "2005-01-01",
    "iso:country": "GB",
    "wof:name": "EH16 4QL",
    "wof:placetype": "postalcode"
  },
  "geometry": {"coordinates":[-3.124124,55.934842],"type":"Point"}
}
