{
  "type": "Feature",
  "properties": {
    "date:inception_lower": "1986-07-01",
    "date:inception_upper": "1986-07-01",
    "iso:country": "GB",
    "wof:name": "TQ12 1SQ",
    "wof:placetype": "postalcode"
  },
  "geometry": {"coordinates":[-3.629653,50.532327],"type":"Point"}
}
