{
  "type": "Feature",
  "properties": {
    "date:inception_lower": "2005-11-01",
    "date:inception_upper": "2005-11-01",
    "iso:country": "GB",
    "wof:name": "WA5 8GQ",
    "wof:placetype": "postalcode"
  },
  "geometry": {"coordinates":[-2.640149,53.401118],"type":"Point"}
}
