{
  "type": "Feature",
  "properties": {
    "iso:country":"GB",
    "wof:name":"WA5 8GQ",
    "wof:placetype":"postalcode"
},
  "geometry": {"coordinates":[-2.64014856928856,53.40111779764012],"type":"Point"}
}