{
  "type": "Feature",
  "properties": {
    "iso:country":"GB",
    "wof:name":"BA4 6EY",
    "wof:placetype":"postalcode"
},
  "geometry": {"coordinates":[-2.45016301728803,51.14877169818428],"type":"Point"}
}