{
  "type": "Feature",
  "properties": {
    "iso:country":"GB",
    "wof:name":"ML2 0DW",
    "wof:placetype":"postalcode"
},
  "geometry": {"coordinates":[-3.95679259479251,55.76878414003897],"type":"Point"}
}