{
  "type": "Feature",
  "properties": {
    "date:inception_lower": "1990-09-01",
    "date:inception_upper": "1990-09-01",
    "iso:country": "GB",
    "wof:name": "ML2 0DW",
    "wof:placetype": "postalcode"
  },
  "geometry": {"coordinates":[-3.956793,55.768784],"type":"Point"}
}
