{
  "type": "Feature",
  "properties": {
    "iso:country": "GB",
    "wof:name": "TR20 9EE",
    "wof:placetype": "postalcode"
  },
  "geometry": {"coordinates":[-5.415889,50.130664],"type":"Point"}
}
