{
  "type": "Feature",
  "properties": {
    "iso:country":"GB",
    "wof:name":"TR20 9EE",
    "wof:placetype":"postalcode"
},
  "geometry": {"coordinates":[-5.41588933103603,50.13066413786689],"type":"Point"}
}