{
  "type": "Feature",
  "properties": {
    "iso:country":"GB",
    "wof:name":"KA8 9AR",
    "wof:placetype":"postalcode"
},
  "geometry": {"coordinates":[-4.62169126215512,55.47422139377053],"type":"Point"}
}