{
  "type": "Feature",
  "properties": {
    "iso:country":"GB",
    "wof:name":"CR8 5NA",
    "wof:placetype":"postalcode"
},
  "geometry": {"coordinates":[-0.10966635660194,51.32896342105526],"type":"Point"}
}