{
  "type": "Feature",
  "properties": {
    "iso:country": "GB",
    "wof:name": "PE20 3EQ",
    "wof:placetype": "postalcode"
  },
  "geometry": {"coordinates":[-0.158724,52.94456],"type":"Point"}
}
