{
  "type": "Feature",
  "properties": {
    "date:inception_lower":"2007-02-01",
    "date:inception_upper":"2007-02-28",
    "iso:country":"GB",
    "wof:name":"PE20 3EQ",
    "wof:placetype":"postalcode"
},
  "geometry": {"coordinates":[-0.158724,52.94456],"type":"Point"}
}