{
  "type": "Feature",
  "properties": {
    "date:inception_lower":"1995-07-01",
    "date:inception_upper":"1995-07-31",
    "iso:country":"GB",
    "wof:name":"RG18 3DT",
    "wof:placetype":"postalcode"
},
  "geometry": {"coordinates":[-1.27171,51.410811],"type":"Point"}
}