{
  "type": "Feature",
  "properties": {
    "iso:country":"GB",
    "wof:name":"M11 1HH",
    "wof:placetype":"postalcode"
},
  "geometry": {"coordinates":[-2.15534721623937,53.4729428932238],"type":"Point"}
}