{
  "type": "Feature",
  "properties": {
    "date:inception_lower":"1980-01-01",
    "date:inception_upper":"1980-01-31",
    "iso:country":"GB",
    "wof:name":"YO18 7NQ",
    "wof:placetype":"postalcode"
},
  "geometry": {"coordinates":[-0.702998,54.283075],"type":"Point"}
}