{
  "type": "Feature",
  "properties": {
    "iso:country":"GB",
    "wof:name":"TS1 1RU",
    "wof:placetype":"postalcode"
},
  "geometry": {"coordinates":[-1.23609820193414,54.57806165287853],"type":"Point"}
}