{
  "type": "Feature",
  "properties": {
    "iso:country":"GB",
    "wof:name":"G82 9YU",
    "wof:placetype":"postalcode"
},
  "geometry": {"coordinates":[-4.57047616195944,55.94447600665409],"type":"Point"}
}