{
  "type": "Feature",
  "properties": {
    "date:inception_lower":"2016-03-01",
    "date:inception_upper":"2016-03-31",
    "iso:country":"GB",
    "wof:name":"G82 9YU",
    "wof:placetype":"postalcode"
},
  "geometry": {"coordinates":[-4.570476,55.944476],"type":"Point"}
}