{
  "type": "Feature",
  "properties": {
    "date:inception_lower": "2020-09-01",
    "date:inception_upper": "2020-09-01",
    "iso:country": "GB",
    "wof:name": "W1K 4AB",
    "wof:placetype": "postalcode"
  },
  "geometry": {"coordinates":[-0.14979,51.511671],"type":"Point"}
}
