{
  "type": "Feature",
  "properties": {
    "date:inception_lower": "1980-01-01",
    "date:inception_upper": "1980-01-01",
    "iso:country": "GB",
    "wof:name": "IP3 0QN",
    "wof:placetype": "postalcode"
  },
  "geometry": {"coordinates":[1.174011,52.041558],"type":"Point"}
}
