{
  "type": "Feature",
  "properties": {
    "iso:country":"GB",
    "wof:name":"SL6 7DH",
    "wof:placetype":"postalcode"
},
  "geometry": {"coordinates":[-0.72311497711391,51.52818568668811],"type":"Point"}
}