{
  "type": "Feature",
  "properties": {
    "iso:country":"GB",
    "wof:name":"EH6 5QD",
    "wof:placetype":"postalcode"
},
  "geometry": {"coordinates":[-3.18756456050114,55.97100662439655],"type":"Point"}
}