{
  "type": "Feature",
  "properties": {
    "iso:country":"GB",
    "wof:name":"DG2 7AN",
    "wof:placetype":"postalcode"
},
  "geometry": {"coordinates":[-3.62172651737935,55.06535861060438],"type":"Point"}
}