{
  "type": "Feature",
  "properties": {
    "iso:country":"GB",
    "wof:name":"PE26 1HJ",
    "wof:placetype":"postalcode"
},
  "geometry": {"coordinates":[-0.10780358062801,52.45054492394792],"type":"Point"}
}