{
  "type": "Feature",
  "properties": {
    "iso:country":"GB",
    "wof:name":"NG16 3LS",
    "wof:placetype":"postalcode"
},
  "geometry": {"coordinates":[-1.30394756261804,53.0135692732403],"type":"Point"}
}