{
  "type": "Feature",
  "properties": {
    "iso:country":"GB",
    "wof:name":"YO13 9JN",
    "wof:placetype":"postalcode"
},
  "geometry": {"coordinates":[-0.48816668615551,54.2450970674476],"type":"Point"}
}