{
  "type": "Feature",
  "properties": {
    "date:inception_lower": "1980-01-01",
    "date:inception_upper": "1980-01-01",
    "iso:country": "GB",
    "wof:name": "YO13 9JN",
    "wof:placetype": "postalcode"
  },
  "geometry": {"coordinates":[-0.488167,54.245097],"type":"Point"}
}
