{
  "type": "Feature",
  "properties": {
    "date:inception_lower": "1980-01-01",
    "date:inception_upper": "1980-01-01",
    "iso:country": "GB",
    "wof:name": "OL1 4HB",
    "wof:placetype": "postalcode"
  },
  "geometry": {"coordinates":[-2.093099,53.55054],"type":"Point"}
}
