{
  "type": "Feature",
  "properties": {
    "iso:country": "GB",
    "wof:name": "OL1 4HB",
    "wof:placetype": "postalcode"
  },
  "geometry": {"coordinates":[-2.092301,53.550596],"type":"Point"}
}
