{
  "type": "Feature",
  "properties": {
    "iso:country":"GB",
    "wof:name":"CA10 2LB",
    "wof:placetype":"postalcode"
},
  "geometry": {"coordinates":[-2.75949278709332,54.63977285078528],"type":"Point"}
}