{
  "type": "Feature",
  "properties": {
    "iso:country":"GB",
    "wof:name":"TS18 3TU",
    "wof:placetype":"postalcode"
},
  "geometry": {"coordinates":[-1.32020014158856,54.54532011417836],"type":"Point"}
}