{
  "type": "Feature",
  "properties": {
    "iso:country": "GB",
    "wof:name": "DY14 9TD",
    "wof:placetype": "postalcode"
  },
  "geometry": {"coordinates":[-2.39069,52.363632],"type":"Point"}
}
