{
  "type": "Feature",
  "properties": {
    "date:inception_lower": "1997-12-01",
    "date:inception_upper": "1997-12-01",
    "iso:country": "GB",
    "wof:name": "IP33 3ND",
    "wof:placetype": "postalcode"
  },
  "geometry": {"coordinates":[0.708132,52.24075],"type":"Point"}
}
