{
  "type": "Feature",
  "properties": {
    "iso:country": "GB",
    "wof:name": "RH15 9QN",
    "wof:placetype": "postalcode"
  },
  "geometry": {"coordinates":[-0.140527,50.950429],"type":"Point"}
}
