{
  "type": "Feature",
  "properties": {
    "iso:country":"GB",
    "wof:name":"RH1 1EF",
    "wof:placetype":"postalcode"
},
  "geometry": {"coordinates":[-0.17288501959025,51.24324934165023],"type":"Point"}
}