{
  "type": "Feature",
  "properties": {
    "iso:country":"GB",
    "wof:name":"B79 8PA",
    "wof:placetype":"postalcode"
},
  "geometry": {"coordinates":[-1.69527252788479,52.64157691507688],"type":"Point"}
}