{
  "type": "Feature",
  "properties": {
    "iso:country": "GB",
    "wof:name": "NE65 7YJ",
    "wof:placetype": "postalcode"
  },
  "geometry": {"coordinates":[-1.924661,55.311004],"type":"Point"}
}
