{
  "type": "Feature",
  "properties": {
    "iso:country":"GB",
    "wof:name":"RG20 9PG",
    "wof:placetype":"postalcode"
},
  "geometry": {"coordinates":[-1.37375122915405,51.34562542169007],"type":"Point"}
}