{
  "type": "Feature",
  "properties": {
    "iso:country": "GB",
    "wof:name": "CA3 9PT",
    "wof:placetype": "postalcode"
  },
  "geometry": {"coordinates":[-2.953215,54.907354],"type":"Point"}
}
