{
  "type": "Feature",
  "properties": {
    "iso:country":"GB",
    "wof:name":"CA3 9PT",
    "wof:placetype":"postalcode"
},
  "geometry": {"coordinates":[-2.95321470144213,54.90735391809389],"type":"Point"}
}