{
  "type": "Feature",
  "properties": {
    "date:inception_lower": "2006-07-01",
    "date:inception_upper": "2006-07-01",
    "iso:country": "GB",
    "wof:name": "N16 7YG",
    "wof:placetype": "postalcode"
  },
  "geometry": {"coordinates":[-0.077127,51.570085],"type":"Point"}
}
