{
  "type": "Feature",
  "properties": {
    "iso:country": "GB",
    "wof:name": "SN7 7BE",
    "wof:placetype": "postalcode"
  },
  "geometry": {"coordinates":[-1.582665,51.657284],"type":"Point"}
}
