{
  "type": "Feature",
  "properties": {
    "date:inception_lower": "2005-03-01",
    "date:inception_upper": "2005-03-01",
    "iso:country": "GB",
    "wof:name": "DD1 9TN",
    "wof:placetype": "postalcode"
  },
  "geometry": {"coordinates":[-2.969923,56.46016],"type":"Point"}
}
