{
  "type": "Feature",
  "properties": {
    "iso:country": "GB",
    "wof:name": "WR5 3JS",
    "wof:placetype": "postalcode"
  },
  "geometry": {"coordinates":[-2.223168,52.141919],"type":"Point"}
}
