{
  "type": "Feature",
  "properties": {
    "iso:country":"GB",
    "wof:name":"NR31 7BJ",
    "wof:placetype":"postalcode"
},
  "geometry": {"coordinates":[1.71839223649972,52.57909089134596],"type":"Point"}
}