{
  "type": "Feature",
  "properties": {
    "iso:country": "GB",
    "wof:name": "DE75 7UE",
    "wof:placetype": "postalcode"
  },
  "geometry": {"coordinates":[-1.366309,53.011688],"type":"Point"}
}
