{
  "type": "Feature",
  "properties": {
    "iso:country": "GB",
    "wof:name": "SM5 1HJ",
    "wof:placetype": "postalcode"
  },
  "geometry": {"coordinates":[-0.173817,51.387786],"type":"Point"}
}
