{
  "type": "Feature",
  "properties": {
    "iso:country":"GB",
    "wof:name":"SM5 1HJ",
    "wof:placetype":"postalcode"
},
  "geometry": {"coordinates":[-0.17381685958427,51.38778626364105],"type":"Point"}
}