{
  "type": "Feature",
  "properties": {
    "iso:country":"GB",
    "wof:name":"CO2 8WW",
    "wof:placetype":"postalcode"
},
  "geometry": {"coordinates":[0.90089846406329,51.86166422777004],"type":"Point"}
}