{
  "type": "Feature",
  "properties": {
    "date:inception_lower":"2008-01-01",
    "date:inception_upper":"2008-01-31",
    "iso:country":"GB",
    "wof:name":"CO2 8WW",
    "wof:placetype":"postalcode"
},
  "geometry": {"coordinates":[0.900899,51.861664],"type":"Point"}
}