{
  "type": "Feature",
  "properties": {
    "iso:country": "GB",
    "wof:name": "CO2 8WW",
    "wof:placetype": "postalcode"
  },
  "geometry": {"coordinates":[0.900899,51.861664],"type":"Point"}
}
