{
  "type": "Feature",
  "properties": {
    "iso:country":"GB",
    "wof:name":"W1K 6NP",
    "wof:placetype":"postalcode"
},
  "geometry": {"coordinates":[-0.15492179147776,51.51190256554526],"type":"Point"}
}