{
  "type": "Feature",
  "properties": {
    "date:inception_lower": "2020-04-01",
    "date:inception_upper": "2020-04-01",
    "iso:country": "GB",
    "wof:name": "BS3 1FZ",
    "wof:placetype": "postalcode"
  },
  "geometry": {"coordinates":[-2.606058,51.440662],"type":"Point"}
}
