{
  "type": "Feature",
  "properties": {
    "iso:country":"GB",
    "wof:name":"B14 7EN",
    "wof:placetype":"postalcode"
},
  "geometry": {"coordinates":[-1.89070535291506,52.43153682857256],"type":"Point"}
}