{
  "type": "Feature",
  "properties": {
    "date:inception_lower": "1980-01-01",
    "date:inception_upper": "1980-01-01",
    "iso:country": "GB",
    "wof:name": "M12 6FX",
    "wof:placetype": "postalcode"
  },
  "geometry": {"coordinates":[-2.222245,53.471327],"type":"Point"}
}
