{
  "type": "Feature",
  "properties": {
    "iso:country":"GB",
    "wof:name":"L31 3HP",
    "wof:placetype":"postalcode"
},
  "geometry": {"coordinates":[-2.93232918463929,53.50571982460369],"type":"Point"}
}