{
  "type": "Feature",
  "properties": {
    "date:inception_lower": "1980-01-01",
    "date:inception_upper": "1980-01-01",
    "iso:country": "GB",
    "wof:name": "SW6 5EQ",
    "wof:placetype": "postalcode"
  },
  "geometry": {"coordinates":[-0.211844,51.475314],"type":"Point"}
}
