{
  "type": "Feature",
  "properties": {
    "iso:country":"GB",
    "wof:name":"SW6 5EQ",
    "wof:placetype":"postalcode"
},
  "geometry": {"coordinates":[-0.21186736020051,51.47531299578723],"type":"Point"}
}