{
  "type": "Feature",
  "properties": {
    "iso:country":"GB",
    "wof:name":"LA11 7QG",
    "wof:placetype":"postalcode"
},
  "geometry": {"coordinates":[-2.94111670981366,54.18038127806796],"type":"Point"}
}