{
  "type": "Feature",
  "properties": {
    "iso:country":"GB",
    "wof:name":"ST18 0QG",
    "wof:placetype":"postalcode"
},
  "geometry": {"coordinates":[-1.98738220457743,52.79342409688971],"type":"Point"}
}