{
  "type": "Feature",
  "properties": {
    "date:inception_lower": "1980-01-01",
    "date:inception_upper": "1980-01-01",
    "iso:country": "GB",
    "wof:name": "DN31 1TS",
    "wof:placetype": "postalcode"
  },
  "geometry": {"coordinates":[-0.093249,53.570503],"type":"Point"}
}
