{
  "type": "Feature",
  "properties": {
    "iso:country":"GB",
    "wof:name":"DN31 1TS",
    "wof:placetype":"postalcode"
},
  "geometry": {"coordinates":[-0.09324929490445,53.57050290272627],"type":"Point"}
}