{
  "type": "Feature",
  "properties": {
    "iso:country": "GB",
    "wof:name": "RH6 8AH",
    "wof:placetype": "postalcode"
  },
  "geometry": {"coordinates":[-0.172342,51.171972],"type":"Point"}
}
