{
  "type": "Feature",
  "properties": {
    "iso:country":"GB",
    "wof:name":"W1H 2NH",
    "wof:placetype":"postalcode"
},
  "geometry": {"coordinates":[-0.16271346039028,51.51883218468596],"type":"Point"}
}