{
  "type": "Feature",
  "properties": {
    "iso:country":"GB",
    "wof:name":"KT1 2BN",
    "wof:placetype":"postalcode"
},
  "geometry": {"coordinates":[-0.30335458373534,51.40800625279244],"type":"Point"}
}