{
  "type": "Feature",
  "properties": {
    "iso:country":"GB",
    "wof:name":"NR20 3SE",
    "wof:placetype":"postalcode"
},
  "geometry": {"coordinates":[1.03632047442816,52.65499325853031],"type":"Point"}
}