{
  "type": "Feature",
  "properties": {
    "iso:country": "GB",
    "wof:name": "NR20 3SE",
    "wof:placetype": "postalcode"
  },
  "geometry": {"coordinates":[1.036321,52.654993],"type":"Point"}
}
