{
  "type": "Feature",
  "properties": {
    "iso:country":"GB",
    "wof:name":"SG13 8QA",
    "wof:placetype":"postalcode"
},
  "geometry": {"coordinates":[-0.10715701853322,51.74735341767353],"type":"Point"}
}