{
  "type": "Feature",
  "properties": {
    "iso:country":"GB",
    "wof:name":"LS16 5LN",
    "wof:placetype":"postalcode"
},
  "geometry": {"coordinates":[-1.59366630725539,53.8342298634655],"type":"Point"}
}