{
  "type": "Feature",
  "properties": {
    "iso:country": "GB",
    "wof:name": "SE28 8LB",
    "wof:placetype": "postalcode"
  },
  "geometry": {"coordinates":[0.115925,51.507347],"type":"Point"}
}
