{
  "type": "Feature",
  "properties": {
    "iso:country":"GB",
    "wof:name":"SE28 8LB",
    "wof:placetype":"postalcode"
},
  "geometry": {"coordinates":[0.11592506111372,51.50734670289798],"type":"Point"}
}