{
  "type": "Feature",
  "properties": {
    "iso:country":"GB",
    "wof:name":"AL10 0FJ",
    "wof:placetype":"postalcode"
},
  "geometry": {"coordinates":[-0.21937635687675,51.76594947250035],"type":"Point"}
}