{
  "type": "Feature",
  "properties": {
    "date:inception_lower":"2011-08-01",
    "date:inception_upper":"2011-08-31",
    "iso:country":"GB",
    "wof:name":"AL10 0FJ",
    "wof:placetype":"postalcode"
},
  "geometry": {"coordinates":[-0.219376,51.765949],"type":"Point"}
}