{
  "type": "Feature",
  "properties": {
    "date:inception_lower": "2010-09-01",
    "date:inception_upper": "2010-09-01",
    "iso:country": "GB",
    "wof:name": "NP44 3GE",
    "wof:placetype": "postalcode"
  },
  "geometry": {"coordinates":[-3.009535,51.640142],"type":"Point"}
}
