{
  "type": "Feature",
  "properties": {
    "iso:country":"GB",
    "wof:name":"NP44 3GE",
    "wof:placetype":"postalcode"
},
  "geometry": {"coordinates":[-3.00953497908659,51.64014227010059],"type":"Point"}
}