{
  "type": "Feature",
  "properties": {
    "iso:country": "GB",
    "wof:name": "NP44 3GE",
    "wof:placetype": "postalcode"
  },
  "geometry": {"coordinates":[-3.009535,51.640142],"type":"Point"}
}
