{
  "type": "Feature",
  "properties": {
    "iso:country":"GB",
    "wof:name":"MK14 5QH",
    "wof:placetype":"postalcode"
},
  "geometry": {"coordinates":[-0.75195906131021,52.07561069837489],"type":"Point"}
}