{
  "type": "Feature",
  "properties": {
    "iso:country":"GB",
    "wof:name":"NG5 4ND",
    "wof:placetype":"postalcode"
},
  "geometry": {"coordinates":[-1.12065292409888,52.99314519990248],"type":"Point"}
}