{
  "type": "Feature",
  "properties": {
    "date:inception_lower": "2006-10-01",
    "date:inception_upper": "2006-10-01",
    "iso:country": "GB",
    "wof:name": "B70 0JJ",
    "wof:placetype": "postalcode"
  },
  "geometry": {"coordinates":[-2.014315,52.531905],"type":"Point"}
}
