{
  "type": "Feature",
  "properties": {
    "iso:country": "GB",
    "wof:name": "OX17 2HX",
    "wof:placetype": "postalcode"
  },
  "geometry": {"coordinates":[-1.222205,52.100006],"type":"Point"}
}
