{
  "type": "Feature",
  "properties": {
    "iso:country":"GB",
    "wof:name":"EN3 7HJ",
    "wof:placetype":"postalcode"
},
  "geometry": {"coordinates":[-0.04544060199794,51.65878450847725],"type":"Point"}
}