{
  "type": "Feature",
  "properties": {
    "iso:country": "GB",
    "wof:name": "BA2 5LY",
    "wof:placetype": "postalcode"
  },
  "geometry": {"coordinates":[-2.365636,51.366535],"type":"Point"}
}
