{
  "type": "Feature",
  "properties": {
    "iso:country":"GB",
    "wof:name":"BA2 5LY",
    "wof:placetype":"postalcode"
},
  "geometry": {"coordinates":[-2.36563614607117,51.36653520721911],"type":"Point"}
}