{
  "type": "Feature",
  "properties": {
    "date:inception_lower": "2018-06-01",
    "date:inception_upper": "2018-06-01",
    "iso:country": "GB",
    "wof:name": "SO31 1EP",
    "wof:placetype": "postalcode"
  },
  "geometry": {"coordinates":[-1.265044,50.872092],"type":"Point"}
}
