{
  "type": "Feature",
  "properties": {
    "date:inception_lower": "2006-03-01",
    "date:inception_upper": "2006-03-01",
    "iso:country": "GB",
    "wof:name": "BL9 9BX",
    "wof:placetype": "postalcode"
  },
  "geometry": {"coordinates":[-2.283986,53.586877],"type":"Point"}
}
