{
  "type": "Feature",
  "properties": {
    "iso:country":"GB",
    "wof:name":"BL9 9BX",
    "wof:placetype":"postalcode"
},
  "geometry": {"coordinates":[-2.28398556331723,53.58687672376885],"type":"Point"}
}