{
  "type": "Feature",
  "properties": {
    "iso:country":"GB",
    "wof:name":"BN2 6SN",
    "wof:placetype":"postalcode"
},
  "geometry": {"coordinates":[-0.0639484019954,50.83649607208908],"type":"Point"}
}