{
  "type": "Feature",
  "properties": {
    "iso:country": "GB",
    "wof:name": "GL7 2JS",
    "wof:placetype": "postalcode"
  },
  "geometry": {"coordinates":[-1.97758,51.7346],"type":"Point"}
}
