{
  "type": "Feature",
  "properties": {
    "iso:country":"GB",
    "wof:name":"GL7 2JS",
    "wof:placetype":"postalcode"
},
  "geometry": {"coordinates":[-1.97758000329689,51.73460032926372],"type":"Point"}
}