{
  "type": "Feature",
  "properties": {
    "iso:country":"GB",
    "wof:name":"EN9 3RP",
    "wof:placetype":"postalcode"
},
  "geometry": {"coordinates":[0.04450838672752,51.68068730060646],"type":"Point"}
}