{
  "type": "Feature",
  "properties": {
    "iso:country": "GB",
    "wof:name": "EN9 3RP",
    "wof:placetype": "postalcode"
  },
  "geometry": {"coordinates":[0.044522,51.680709],"type":"Point"}
}
