{
  "type": "Feature",
  "properties": {
    "iso:country":"GB",
    "wof:name":"LA8 0EE",
    "wof:placetype":"postalcode"
},
  "geometry": {"coordinates":[-2.71828153726227,54.27005743435274],"type":"Point"}
}