{
  "type": "Feature",
  "properties": {
    "iso:country": "GB",
    "wof:name": "LA8 0EE",
    "wof:placetype": "postalcode"
  },
  "geometry": {"coordinates":[-2.718281,54.270057],"type":"Point"}
}
