{
  "type": "Feature",
  "properties": {
    "iso:country":"GB",
    "wof:name":"BA9 9LT",
    "wof:placetype":"postalcode"
},
  "geometry": {"coordinates":[-2.40363667844398,51.05804022826896],"type":"Point"}
}