{
  "type": "Feature",
  "properties": {
    "date:inception_lower": "1980-01-01",
    "date:inception_upper": "1980-01-01",
    "iso:country": "GB",
    "wof:name": "BA9 9LT",
    "wof:placetype": "postalcode"
  },
  "geometry": {"coordinates":[-2.403637,51.05804],"type":"Point"}
}
