{
  "type": "Feature",
  "properties": {
    "iso:country":"GB",
    "wof:name":"BD7 2SJ",
    "wof:placetype":"postalcode"
},
  "geometry": {"coordinates":[-1.8020979075913,53.78526657194335],"type":"Point"}
}