{
  "type": "Feature",
  "properties": {
    "iso:country": "GB",
    "wof:name": "L36 5TW",
    "wof:placetype": "postalcode"
  },
  "geometry": {"coordinates":[-2.842414,53.404221],"type":"Point"}
}
