{
  "type": "Feature",
  "properties": {
    "iso:country": "GB",
    "wof:name": "BL1 8BE",
    "wof:placetype": "postalcode"
  },
  "geometry": {"coordinates":[-2.444546,53.596733],"type":"Point"}
}
