{
  "type": "Feature",
  "properties": {
    "iso:country":"GB",
    "wof:name":"WA13 9NH",
    "wof:placetype":"postalcode"
},
  "geometry": {"coordinates":[-2.49049069929859,53.3822672996731],"type":"Point"}
}