{
  "type": "Feature",
  "properties": {
    "iso:country": "GB",
    "wof:name": "WA13 9NH",
    "wof:placetype": "postalcode"
  },
  "geometry": {"coordinates":[-2.490491,53.382267],"type":"Point"}
}
