{
  "type": "Feature",
  "properties": {
    "iso:country": "GB",
    "wof:name": "SA15 2DB",
    "wof:placetype": "postalcode"
  },
  "geometry": {"coordinates":[-4.147115,51.667156],"type":"Point"}
}
