{
  "type": "Feature",
  "properties": {
    "iso:country":"GB",
    "wof:name":"LU5 5JW",
    "wof:placetype":"postalcode"
},
  "geometry": {"coordinates":[-0.51422805465687,51.91112504805873],"type":"Point"}
}