{
  "type": "Feature",
  "properties": {
    "date:inception_lower": "2018-09-01",
    "date:inception_upper": "2018-09-01",
    "iso:country": "GB",
    "wof:name": "CO11 2FF",
    "wof:placetype": "postalcode"
  },
  "geometry": {"coordinates":[1.100414,51.926225],"type":"Point"}
}
