{
  "type": "Feature",
  "properties": {
    "iso:country":"GB",
    "wof:name":"TQ9 5BN",
    "wof:placetype":"postalcode"
},
  "geometry": {"coordinates":[-3.67285078159157,50.43268352695462],"type":"Point"}
}