{
  "type": "Feature",
  "properties": {
    "iso:country":"GB",
    "wof:name":"OX2 9SR",
    "wof:placetype":"postalcode"
},
  "geometry": {"coordinates":[-1.30354810188032,51.75240207314005],"type":"Point"}
}