{
  "type": "Feature",
  "properties": {
    "iso:country": "GB",
    "wof:name": "OX2 9SR",
    "wof:placetype": "postalcode"
  },
  "geometry": {"coordinates":[-1.30304,51.752444],"type":"Point"}
}
