{
  "type": "Feature",
  "properties": {
    "iso:country":"GB",
    "wof:name":"LN13 9NA",
    "wof:placetype":"postalcode"
},
  "geometry": {"coordinates":[0.19667512897535,53.22432280565268],"type":"Point"}
}