{
  "type": "Feature",
  "properties": {
    "date:inception_lower": "1980-01-01",
    "date:inception_upper": "1980-01-01",
    "iso:country": "GB",
    "wof:name": "LN13 9NA",
    "wof:placetype": "postalcode"
  },
  "geometry": {"coordinates":[0.196675,53.224323],"type":"Point"}
}
