{
  "type": "Feature",
  "properties": {
    "date:inception_lower":"1980-01-01",
    "date:inception_upper":"1980-01-31",
    "iso:country":"GB",
    "wof:name":"M22 4GA",
    "wof:placetype":"postalcode"
},
  "geometry": {"coordinates":[-2.256686,53.391916],"type":"Point"}
}