{
  "type": "Feature",
  "properties": {
    "iso:country":"GB",
    "wof:name":"M22 4GA",
    "wof:placetype":"postalcode"
},
  "geometry": {"coordinates":[-2.25668615353876,53.39191611027206],"type":"Point"}
}