{
  "type": "Feature",
  "properties": {
    "iso:country":"GB",
    "wof:name":"N8 8RJ",
    "wof:placetype":"postalcode"
},
  "geometry": {"coordinates":[-0.1307316259943,51.58140902046247],"type":"Point"}
}