{
  "type": "Feature",
  "properties": {
    "date:inception_lower": "2007-01-01",
    "date:inception_upper": "2007-01-01",
    "iso:country": "GB",
    "wof:name": "L36 3UX",
    "wof:placetype": "postalcode"
  },
  "geometry": {"coordinates":[-2.856686,53.423545],"type":"Point"}
}
