{
  "type": "Feature",
  "properties": {
    "iso:country": "GB",
    "wof:name": "L36 3UX",
    "wof:placetype": "postalcode"
  },
  "geometry": {"coordinates":[-2.856686,53.423545],"type":"Point"}
}
