{
  "type": "Feature",
  "properties": {
    "iso:country": "GB",
    "wof:name": "SA2 9DH",
    "wof:placetype": "postalcode"
  },
  "geometry": {"coordinates":[-3.991915,51.622933],"type":"Point"}
}
