{
  "type": "Feature",
  "properties": {
    "iso:country": "GB",
    "wof:name": "B79 8QA",
    "wof:placetype": "postalcode"
  },
  "geometry": {"coordinates":[-1.69457,52.649091],"type":"Point"}
}
