{
  "type": "Feature",
  "properties": {
    "iso:country":"GB",
    "wof:name":"B79 8QA",
    "wof:placetype":"postalcode"
},
  "geometry": {"coordinates":[-1.69456998634158,52.64909052937011],"type":"Point"}
}