{
  "type": "Feature",
  "properties": {
    "iso:country":"GB",
    "wof:name":"SA4 3RS",
    "wof:placetype":"postalcode"
},
  "geometry": {"coordinates":[-4.1300031789078,51.6383945016702],"type":"Point"}
}