{
  "type": "Feature",
  "properties": {
    "iso:country": "GB",
    "wof:name": "SK10 3NE",
    "wof:placetype": "postalcode"
  },
  "geometry": {"coordinates":[-2.156692,53.261484],"type":"Point"}
}
