{
  "type": "Feature",
  "properties": {
    "iso:country": "GB",
    "wof:name": "DL11 6QH",
    "wof:placetype": "postalcode"
  },
  "geometry": {"coordinates":[-2.14058,54.376817],"type":"Point"}
}
