{
  "type": "Feature",
  "properties": {
    "iso:country":"GB",
    "wof:name":"LE13 0HX",
    "wof:placetype":"postalcode"
},
  "geometry": {"coordinates":[-0.90551720538735,52.76704665594468],"type":"Point"}
}