{
  "type": "Feature",
  "properties": {
    "iso:country": "GB",
    "wof:name": "TN29 9BQ",
    "wof:placetype": "postalcode"
  },
  "geometry": {"coordinates":[0.898045,50.949008],"type":"Point"}
}
