{
  "type": "Feature",
  "properties": {
    "iso:country":"GB",
    "wof:name":"NG12 4EJ",
    "wof:placetype":"postalcode"
},
  "geometry": {"coordinates":[-1.10310783936659,52.90292097838373],"type":"Point"}
}