{
  "type": "Feature",
  "properties": {
    "iso:country": "GB",
    "wof:name": "SA12 9TL",
    "wof:placetype": "postalcode"
  },
  "geometry": {"coordinates":[-3.745187,51.635602],"type":"Point"}
}
