{
  "type": "Feature",
  "properties": {
    "iso:country":"GB",
    "wof:name":"EX22 7NS",
    "wof:placetype":"postalcode"
},
  "geometry": {"coordinates":[-4.30662665868126,50.87817920528024],"type":"Point"}
}