{
  "type": "Feature",
  "properties": {
    "iso:country": "GB",
    "wof:name": "EX22 7NS",
    "wof:placetype": "postalcode"
  },
  "geometry": {"coordinates":[-4.306627,50.878179],"type":"Point"}
}
