{
  "type": "Feature",
  "properties": {
    "date:inception_lower": "1996-06-01",
    "date:inception_upper": "1996-06-01",
    "iso:country": "GB",
    "wof:name": "WR10 2HQ",
    "wof:placetype": "postalcode"
  },
  "geometry": {"coordinates":[-2.090294,52.152288],"type":"Point"}
}
