{
  "type": "Feature",
  "properties": {
    "iso:country":"GB",
    "wof:name":"WR10 2HQ",
    "wof:placetype":"postalcode"
},
  "geometry": {"coordinates":[-2.09029452612025,52.15228832127619],"type":"Point"}
}