{
  "type": "Feature",
  "properties": {
    "date:inception_lower": "1980-01-01",
    "date:inception_upper": "1980-01-01",
    "iso:country": "GB",
    "wof:name": "SA62 3AS",
    "wof:placetype": "postalcode"
  },
  "geometry": {"coordinates":[-5.173275,51.730186],"type":"Point"}
}
