{
  "type": "Feature",
  "properties": {
    "date:inception_lower": "2019-01-01",
    "date:inception_upper": "2019-01-01",
    "iso:country": "GB",
    "wof:name": "S45 9FR",
    "wof:placetype": "postalcode"
  },
  "geometry": {"coordinates":[-1.392532,53.168157],"type":"Point"}
}
