{
  "type": "Feature",
  "properties": {
    "date:inception_lower": "1980-01-01",
    "date:inception_upper": "1980-01-01",
    "iso:country": "GB",
    "wof:name": "GU19 5LE",
    "wof:placetype": "postalcode"
  },
  "geometry": {"coordinates":[-0.687205,51.360546],"type":"Point"}
}
