{
  "type": "Feature",
  "properties": {
    "date:inception_lower":"1980-01-01",
    "date:inception_upper":"1980-01-31",
    "iso:country":"GB",
    "wof:name":"EX20 2LN",
    "wof:placetype":"postalcode"
},
  "geometry": {"coordinates":[-3.902816,50.733851],"type":"Point"}
}