{
  "type": "Feature",
  "properties": {
    "iso:country": "GB",
    "wof:name": "GU14 8DL",
    "wof:placetype": "postalcode"
  },
  "geometry": {"coordinates":[-0.754082,51.310695],"type":"Point"}
}
