{
  "type": "Feature",
  "properties": {
    "iso:country":"GB",
    "wof:name":"YO18 8NN",
    "wof:placetype":"postalcode"
},
  "geometry": {"coordinates":[-0.78847575609404,54.25288418357962],"type":"Point"}
}