{
  "type": "Feature",
  "properties": {
    "iso:country":"GB",
    "wof:name":"S20 2NS",
    "wof:placetype":"postalcode"
},
  "geometry": {"coordinates":[-1.33036839715071,53.33597909283211],"type":"Point"}
}