{
  "type": "Feature",
  "properties": {
    "iso:country":"GB",
    "wof:name":"LS17 6LH",
    "wof:placetype":"postalcode"
},
  "geometry": {"coordinates":[-1.53381971711342,53.83637623020778],"type":"Point"}
}