{
  "type": "Feature",
  "properties": {
    "iso:country":"GB",
    "wof:name":"PE16 6BZ",
    "wof:placetype":"postalcode"
},
  "geometry": {"coordinates":[0.06018187719707,52.45708873166352],"type":"Point"}
}