{
  "type": "Feature",
  "properties": {
    "date:inception_lower": "1980-01-01",
    "date:inception_upper": "1980-01-01",
    "iso:country": "GB",
    "wof:name": "PE16 6BZ",
    "wof:placetype": "postalcode"
  },
  "geometry": {"coordinates":[0.060182,52.457089],"type":"Point"}
}
