{
  "type": "Feature",
  "properties": {
    "iso:country":"GB",
    "wof:name":"DL14 9TD",
    "wof:placetype":"postalcode"
},
  "geometry": {"coordinates":[-1.69169554324986,54.64090121094027],"type":"Point"}
}