{
  "type": "Feature",
  "properties": {
    "date:inception_lower": "2012-09-01",
    "date:inception_upper": "2012-09-01",
    "iso:country": "GB",
    "wof:name": "KW1 4PP",
    "wof:placetype": "postalcode"
  },
  "geometry": {"coordinates":[-3.073764,58.445391],"type":"Point"}
}
