{
  "type": "Feature",
  "properties": {
    "iso:country":"GB",
    "wof:name":"TW13 4AH",
    "wof:placetype":"postalcode"
},
  "geometry": {"coordinates":[-0.40894480677542,51.44668858426457],"type":"Point"}
}