{
  "type": "Feature",
  "properties": {
    "iso:country": "GB",
    "wof:name": "TW13 4AH",
    "wof:placetype": "postalcode"
  },
  "geometry": {"coordinates":[-0.408945,51.446689],"type":"Point"}
}
