{
  "type": "Feature",
  "properties": {
    "iso:country":"GB",
    "wof:name":"SO23 7QG",
    "wof:placetype":"postalcode"
},
  "geometry": {"coordinates":[-1.29984606699803,51.08721640826879],"type":"Point"}
}