{
  "type": "Feature",
  "properties": {
    "date:inception_lower": "1980-01-01",
    "date:inception_upper": "1980-01-01",
    "iso:country": "GB",
    "wof:name": "KA18 3JN",
    "wof:placetype": "postalcode"
  },
  "geometry": {"coordinates":[-4.255818,55.488695],"type":"Point"}
}
