{
  "type": "Feature",
  "properties": {
    "iso:country":"GB",
    "wof:name":"DH6 4SR",
    "wof:placetype":"postalcode"
},
  "geometry": {"coordinates":[-1.5056326294199,54.71177469161133],"type":"Point"}
}