{
  "type": "Feature",
  "properties": {
    "iso:country": "GB",
    "wof:name": "DH6 4SR",
    "wof:placetype": "postalcode"
  },
  "geometry": {"coordinates":[-1.505633,54.711775],"type":"Point"}
}
