{
  "type": "Feature",
  "properties": {
    "iso:country": "GB",
    "wof:name": "NR18 0YE",
    "wof:placetype": "postalcode"
  },
  "geometry": {"coordinates":[1.130789,52.572421],"type":"Point"}
}
