{
  "type": "Feature",
  "properties": {
    "date:inception_lower": "1980-01-01",
    "date:inception_upper": "1980-01-01",
    "iso:country": "GB",
    "wof:name": "BH18 9BX",
    "wof:placetype": "postalcode"
  },
  "geometry": {"coordinates":[-2.004825,50.762853],"type":"Point"}
}
