{
  "type": "Feature",
  "properties": {
    "date:inception_lower": "1980-01-01",
    "date:inception_upper": "1980-01-01",
    "iso:country": "GB",
    "wof:name": "TN4 9PG",
    "wof:placetype": "postalcode"
  },
  "geometry": {"coordinates":[0.261085,51.142892],"type":"Point"}
}
