{
  "type": "Feature",
  "properties": {
    "iso:country":"GB",
    "wof:name":"TN4 9PG",
    "wof:placetype":"postalcode"
},
  "geometry": {"coordinates":[0.26108473688727,51.14289250480193],"type":"Point"}
}