{
  "type": "Feature",
  "properties": {
    "iso:country":"GB",
    "wof:name":"NW5 2QE",
    "wof:placetype":"postalcode"
},
  "geometry": {"coordinates":[-0.13770134639702,51.55072972690027],"type":"Point"}
}