{
  "type": "Feature",
  "properties": {
    "iso:country":"GB",
    "wof:name":"DN1 3AA",
    "wof:placetype":"postalcode"
},
  "geometry": {"coordinates":[-1.13782210919908,53.52075804918543],"type":"Point"}
}