{
  "type": "Feature",
  "properties": {
    "iso:country": "GB",
    "wof:name": "S70 4JJ",
    "wof:placetype": "postalcode"
  },
  "geometry": {"coordinates":[-1.475744,53.545907],"type":"Point"}
}
