{
  "type": "Feature",
  "properties": {
    "iso:country":"GB",
    "wof:name":"S70 4JJ",
    "wof:placetype":"postalcode"
},
  "geometry": {"coordinates":[-1.47574383924653,53.5459067567931],"type":"Point"}
}