{
  "type": "Feature",
  "properties": {
    "iso:country":"GB",
    "wof:name":"G72 9TD",
    "wof:placetype":"postalcode"
},
  "geometry": {"coordinates":[-4.10780867703397,55.78525818572503],"type":"Point"}
}