{
  "type": "Feature",
  "properties": {
    "iso:country":"GB",
    "wof:name":"L15 9HH",
    "wof:placetype":"postalcode"
},
  "geometry": {"coordinates":[-2.91365515042258,53.39312635391806],"type":"Point"}
}