{
  "type": "Feature",
  "properties": {
    "iso:country":"GB",
    "wof:name":"E8 4ER",
    "wof:placetype":"postalcode"
},
  "geometry": {"coordinates":[-0.07374881891295,51.54006614292508],"type":"Point"}
}