{
  "type": "Feature",
  "properties": {
    "date:inception_lower":"1980-01-01",
    "date:inception_upper":"1980-01-31",
    "iso:country":"GB",
    "wof:name":"E8 4ER",
    "wof:placetype":"postalcode"
},
  "geometry": {"coordinates":[-0.073749,51.540066],"type":"Point"}
}