{
  "type": "Feature",
  "properties": {
    "date:inception_lower": "2003-09-01",
    "date:inception_upper": "2003-09-01",
    "iso:country": "GB",
    "wof:name": "BN23 5AY",
    "wof:placetype": "postalcode"
  },
  "geometry": {"coordinates":[0.33415,50.795024],"type":"Point"}
}
