{
  "type": "Feature",
  "properties": {
    "iso:country":"GB",
    "wof:name":"LE17 5HD",
    "wof:placetype":"postalcode"
},
  "geometry": {"coordinates":[-1.22631056435338,52.50552845955524],"type":"Point"}
}