{
  "type": "Feature",
  "properties": {
    "iso:country": "GB",
    "wof:name": "LE17 5HD",
    "wof:placetype": "postalcode"
  },
  "geometry": {"coordinates":[-1.226311,52.505528],"type":"Point"}
}
