{
  "type": "Feature",
  "properties": {
    "iso:country":"GB",
    "wof:name":"N1 9GA",
    "wof:placetype":"postalcode"
},
  "geometry": {"coordinates":[-0.12205704916149,51.53132635668059],"type":"Point"}
}