{
  "type": "Feature",
  "properties": {
    "iso:country": "GB",
    "wof:name": "N1 9GA",
    "wof:placetype": "postalcode"
  },
  "geometry": {"coordinates":[-0.121957,51.531021],"type":"Point"}
}
