{
  "type": "Feature",
  "properties": {
    "iso:country":"GB",
    "wof:name":"NP12 1SP",
    "wof:placetype":"postalcode"
},
  "geometry": {"coordinates":[-3.20616340312771,51.66161110137512],"type":"Point"}
}