{
  "type": "Feature",
  "properties": {
    "date:inception_lower": "2002-06-01",
    "date:inception_upper": "2002-06-01",
    "iso:country": "GB",
    "wof:name": "NP12 1SP",
    "wof:placetype": "postalcode"
  },
  "geometry": {"coordinates":[-3.206163,51.661611],"type":"Point"}
}
