{
  "type": "Feature",
  "properties": {
    "date:inception_lower": "1998-06-01",
    "date:inception_upper": "1998-06-01",
    "iso:country": "GB",
    "wof:name": "YO19 6QY",
    "wof:placetype": "postalcode"
  },
  "geometry": {"coordinates":[-1.057263,53.837498],"type":"Point"}
}
