{
  "type": "Feature",
  "properties": {
    "iso:country":"GB",
    "wof:name":"YO19 6QY",
    "wof:placetype":"postalcode"
},
  "geometry": {"coordinates":[-1.05726260952935,53.83749801340106],"type":"Point"}
}