{
  "type": "Feature",
  "properties": {
    "date:inception_lower": "2016-07-01",
    "date:inception_upper": "2016-07-01",
    "iso:country": "GB",
    "wof:name": "AB43 7FG",
    "wof:placetype": "postalcode"
  },
  "geometry": {"coordinates":[-2.036582,57.681386],"type":"Point"}
}
