{
  "type": "Feature",
  "properties": {
    "date:inception_lower":"1984-02-01",
    "date:inception_upper":"1984-02-29",
    "iso:country":"GB",
    "wof:name":"AL5 4BJ",
    "wof:placetype":"postalcode"
},
  "geometry": {"coordinates":[-0.359768,51.823733],"type":"Point"}
}