{
  "type": "Feature",
  "properties": {
    "iso:country": "GB",
    "wof:name": "AL5 4BJ",
    "wof:placetype": "postalcode"
  },
  "geometry": {"coordinates":[-0.359768,51.823733],"type":"Point"}
}
