{
  "type": "Feature",
  "properties": {
    "iso:country":"GB",
    "wof:name":"OX2 7NA",
    "wof:placetype":"postalcode"
},
  "geometry": {"coordinates":[-1.26632501640089,51.76893536897023],"type":"Point"}
}