{
  "type": "Feature",
  "properties": {
    "date:inception_lower": "1980-01-01",
    "date:inception_upper": "1980-01-01",
    "iso:country": "GB",
    "wof:name": "AL5 3PW",
    "wof:placetype": "postalcode"
  },
  "geometry": {"coordinates":[-0.398161,51.831959],"type":"Point"}
}
