{
  "type": "Feature",
  "properties": {
    "iso:country":"GB",
    "wof:name":"TR14 8SG",
    "wof:placetype":"postalcode"
},
  "geometry": {"coordinates":[-5.30091238464341,50.21242200792182],"type":"Point"}
}