{
  "type": "Feature",
  "properties": {
    "iso:country":"GB",
    "wof:name":"S63 9DL",
    "wof:placetype":"postalcode"
},
  "geometry": {"coordinates":[-1.30667721921266,53.5317165179944],"type":"Point"}
}