{
  "type": "Feature",
  "properties": {
    "date:inception_lower": "1980-01-01",
    "date:inception_upper": "1980-01-01",
    "iso:country": "GB",
    "wof:name": "S63 9DL",
    "wof:placetype": "postalcode"
  },
  "geometry": {"coordinates":[-1.306677,53.531717],"type":"Point"}
}
