{
  "type": "Feature",
  "properties": {
    "iso:country":"GB",
    "wof:name":"LE15 6LA",
    "wof:placetype":"postalcode"
},
  "geometry": {"coordinates":[-0.74461160330491,52.66760432920443],"type":"Point"}
}