{
  "type": "Feature",
  "properties": {
    "iso:country":"GB",
    "wof:name":"S64 0LX",
    "wof:placetype":"postalcode"
},
  "geometry": {"coordinates":[-1.27216223174999,53.49454139102845],"type":"Point"}
}