{
  "type": "Feature",
  "properties": {
    "iso:country": "GB",
    "wof:name": "BS16 1QR",
    "wof:placetype": "postalcode"
  },
  "geometry": {"coordinates":[-2.527704,51.49965],"type":"Point"}
}
