{
  "type": "Feature",
  "properties": {
    "iso:country":"GB",
    "wof:name":"BS16 1QR",
    "wof:placetype":"postalcode"
},
  "geometry": {"coordinates":[-2.52770413151743,51.49964986059585],"type":"Point"}
}