{
  "type": "Feature",
  "properties": {
    "date:inception_lower": "1980-01-01",
    "date:inception_upper": "1980-01-01",
    "iso:country": "GB",
    "wof:name": "IP14 6BB",
    "wof:placetype": "postalcode"
  },
  "geometry": {"coordinates":[1.170569,52.19854],"type":"Point"}
}
