{
  "type": "Feature",
  "properties": {
    "iso:country":"GB",
    "wof:name":"MK43 7TH",
    "wof:placetype":"postalcode"
},
  "geometry": {"coordinates":[-0.52283022909609,52.16781068580984],"type":"Point"}
}