{
  "type": "Feature",
  "properties": {
    "iso:country": "GB",
    "wof:name": "MK43 7TH",
    "wof:placetype": "postalcode"
  },
  "geometry": {"coordinates":[-0.52283,52.167811],"type":"Point"}
}
