{
  "type": "Feature",
  "properties": {
    "date:inception_lower":"1999-12-01",
    "date:inception_upper":"1999-12-31",
    "iso:country":"GB",
    "wof:name":"MK43 7TH",
    "wof:placetype":"postalcode"
},
  "geometry": {"coordinates":[-0.52283,52.167811],"type":"Point"}
}