{
  "type": "Feature",
  "properties": {
    "iso:country": "GB",
    "wof:name": "BN16 3PL",
    "wof:placetype": "postalcode"
  },
  "geometry": {"coordinates":[-0.51567,50.814788],"type":"Point"}
}
