{
  "type": "Feature",
  "properties": {
    "date:inception_lower": "2005-05-01",
    "date:inception_upper": "2005-05-01",
    "iso:country": "GB",
    "wof:name": "CV36 5HT",
    "wof:placetype": "postalcode"
  },
  "geometry": {"coordinates":[-1.566818,52.026856],"type":"Point"}
}
