{
  "type": "Feature",
  "properties": {
    "iso:country":"GB",
    "wof:name":"CV36 5HT",
    "wof:placetype":"postalcode"
},
  "geometry": {"coordinates":[-1.56681844171534,52.02685574086143],"type":"Point"}
}