{
  "type": "Feature",
  "properties": {
    "date:inception_lower": "1980-01-01",
    "date:inception_upper": "1980-01-01",
    "iso:country": "GB",
    "wof:name": "NE10 8DE",
    "wof:placetype": "postalcode"
  },
  "geometry": {"coordinates":[-1.536362,54.941771],"type":"Point"}
}
