{
  "type": "Feature",
  "properties": {
    "iso:country":"GB",
    "wof:name":"KA5 5RQ",
    "wof:placetype":"postalcode"
},
  "geometry": {"coordinates":[-4.4802530402825,55.51333093241277],"type":"Point"}
}