{
  "type": "Feature",
  "properties": {
    "date:inception_lower": "2006-01-01",
    "date:inception_upper": "2006-01-01",
    "iso:country": "GB",
    "wof:name": "SA1 8PY",
    "wof:placetype": "postalcode"
  },
  "geometry": {"coordinates":[-3.9302,51.618902],"type":"Point"}
}
