{
  "type": "Feature",
  "properties": {
    "iso:country":"GB",
    "wof:name":"SA1 8PY",
    "wof:placetype":"postalcode"
},
  "geometry": {"coordinates":[-3.93019964542883,51.61890169914629],"type":"Point"}
}