{
  "type": "Feature",
  "properties": {
    "iso:country":"GB",
    "wof:name":"HP12 3JX",
    "wof:placetype":"postalcode"
},
  "geometry": {"coordinates":[-0.78103514659327,51.63024721756199],"type":"Point"}
}