{
  "type": "Feature",
  "properties": {
    "iso:country":"GB",
    "wof:name":"YO41 1AE",
    "wof:placetype":"postalcode"
},
  "geometry": {"coordinates":[-0.91193434671767,53.99160371325576],"type":"Point"}
}