{
  "type": "Feature",
  "properties": {
    "iso:country":"GB",
    "wof:name":"TF1 5PL",
    "wof:placetype":"postalcode"
},
  "geometry": {"coordinates":[-2.48630693621083,52.70366359254042],"type":"Point"}
}