{
  "type": "Feature",
  "properties": {
    "iso:country": "GB",
    "wof:name": "TN10 3AL",
    "wof:placetype": "postalcode"
  },
  "geometry": {"coordinates":[0.264442,51.205035],"type":"Point"}
}
