{
  "type": "Feature",
  "properties": {
    "iso:country":"GB",
    "wof:name":"TN10 3AL",
    "wof:placetype":"postalcode"
},
  "geometry": {"coordinates":[0.26444218486096,51.20503532079069],"type":"Point"}
}