{
  "type": "Feature",
  "properties": {
    "date:inception_lower": "2003-05-01",
    "date:inception_upper": "2003-05-01",
    "iso:country": "GB",
    "wof:name": "PR1 0UQ",
    "wof:placetype": "postalcode"
  },
  "geometry": {"coordinates":[-2.733685,53.736013],"type":"Point"}
}
