{
  "type": "Feature",
  "properties": {
    "date:inception_lower": "2019-06-01",
    "date:inception_upper": "2019-06-01",
    "iso:country": "GB",
    "wof:name": "B37 9DU",
    "wof:placetype": "postalcode"
  },
  "geometry": {"coordinates":[-1.740891,52.480323],"type":"Point"}
}
