{
  "type": "Feature",
  "properties": {
    "date:inception_lower":"1980-01-01",
    "date:inception_upper":"1980-01-31",
    "iso:country":"GB",
    "wof:name":"NW2 7TD",
    "wof:placetype":"postalcode"
},
  "geometry": {"coordinates":[-0.246566,51.566375],"type":"Point"}
}