{
  "type": "Feature",
  "properties": {
    "iso:country":"GB",
    "wof:name":"NW2 7TD",
    "wof:placetype":"postalcode"
},
  "geometry": {"coordinates":[-0.246663978564,51.56634674942347],"type":"Point"}
}