{
  "type": "Feature",
  "properties": {
    "iso:country":"GB",
    "wof:name":"HG4 2SF",
    "wof:placetype":"postalcode"
},
  "geometry": {"coordinates":[-1.52707857159647,54.12143314343999],"type":"Point"}
}