{
  "type": "Feature",
  "properties": {
    "iso:country": "GB",
    "wof:name": "N9 7EL",
    "wof:placetype": "postalcode"
  },
  "geometry": {"coordinates":[-0.056501,51.629808],"type":"Point"}
}
