{
  "type": "Feature",
  "properties": {
    "date:inception_lower": "2018-10-01",
    "date:inception_upper": "2018-10-01",
    "iso:country": "GB",
    "wof:name": "G71 8AF",
    "wof:placetype": "postalcode"
  },
  "geometry": {"coordinates":[-4.061028,55.796311],"type":"Point"}
}
