{
  "type": "Feature",
  "properties": {
    "date:inception_lower": "2009-11-01",
    "date:inception_upper": "2009-11-01",
    "iso:country": "GB",
    "wof:name": "CF31 3XY",
    "wof:placetype": "postalcode"
  },
  "geometry": {"coordinates":[-3.558818,51.494226],"type":"Point"}
}
