{
  "type": "Feature",
  "properties": {
    "iso:country": "GB",
    "wof:name": "SN12 6EW",
    "wof:placetype": "postalcode"
  },
  "geometry": {"coordinates":[-2.139523,51.36482],"type":"Point"}
}
