{
  "type": "Feature",
  "properties": {
    "iso:country":"GB",
    "wof:name":"SN12 6EW",
    "wof:placetype":"postalcode"
},
  "geometry": {"coordinates":[-2.13952292962175,51.36482017030304],"type":"Point"}
}