{
  "type": "Feature",
  "properties": {
    "iso:country":"GB",
    "wof:name":"SK3 9PF",
    "wof:placetype":"postalcode"
},
  "geometry": {"coordinates":[-2.1779120629841,53.40377175198011],"type":"Point"}
}