{
  "type": "Feature",
  "properties": {
    "iso:country":"GB",
    "wof:name":"NR21 9NQ",
    "wof:placetype":"postalcode"
},
  "geometry": {"coordinates":[0.82127492897703,52.84780419209984],"type":"Point"}
}