{
  "type": "Feature",
  "properties": {
    "iso:country": "GB",
    "wof:name": "NR21 9NQ",
    "wof:placetype": "postalcode"
  },
  "geometry": {"coordinates":[0.821275,52.847804],"type":"Point"}
}
