{
  "type": "Feature",
  "properties": {
    "iso:country": "GB",
    "wof:name": "BA3 3TR",
    "wof:placetype": "postalcode"
  },
  "geometry": {"coordinates":[-2.457831,51.287785],"type":"Point"}
}
