{
  "type": "Feature",
  "properties": {
    "date:inception_lower":"2006-10-01",
    "date:inception_upper":"2006-10-31",
    "iso:country":"GB",
    "wof:name":"TS17 9JR",
    "wof:placetype":"postalcode"
},
  "geometry": {"coordinates":[-1.288939,54.538436],"type":"Point"}
}