{
  "type": "Feature",
  "properties": {
    "iso:country":"GB",
    "wof:name":"TS17 9JR",
    "wof:placetype":"postalcode"
},
  "geometry": {"coordinates":[-1.28893947872054,54.53843613757501],"type":"Point"}
}