{
  "type": "Feature",
  "properties": {
    "iso:country": "GB",
    "wof:name": "TS17 9JR",
    "wof:placetype": "postalcode"
  },
  "geometry": {"coordinates":[-1.288939,54.538436],"type":"Point"}
}
