{
  "type": "Feature",
  "properties": {
    "iso:country":"GB",
    "wof:name":"HP22 5PZ",
    "wof:placetype":"postalcode"
},
  "geometry": {"coordinates":[-0.72986030400154,51.76978602202219],"type":"Point"}
}