{
  "type": "Feature",
  "properties": {
    "iso:country":"GB",
    "wof:name":"AL5 3EB",
    "wof:placetype":"postalcode"
},
  "geometry": {"coordinates":[-0.3766356116615,51.82517189315064],"type":"Point"}
}