{
  "type": "Feature",
  "properties": {
    "date:inception_lower": "1980-01-01",
    "date:inception_upper": "1980-01-01",
    "iso:country": "GB",
    "wof:name": "AL5 3EB",
    "wof:placetype": "postalcode"
  },
  "geometry": {"coordinates":[-0.376636,51.825172],"type":"Point"}
}
