{
  "type": "Feature",
  "properties": {
    "iso:country":"GB",
    "wof:name":"PA14 5XZ",
    "wof:placetype":"postalcode"
},
  "geometry": {"coordinates":[-4.67465847016593,55.92463976834611],"type":"Point"}
}