{
  "type": "Feature",
  "properties": {
    "iso:country":"GB",
    "wof:name":"PO7 7AN",
    "wof:placetype":"postalcode"
},
  "geometry": {"coordinates":[-1.03722154421868,50.87558946872865],"type":"Point"}
}