{
  "type": "Feature",
  "properties": {
    "iso:country": "GB",
    "wof:name": "PO7 7AN",
    "wof:placetype": "postalcode"
  },
  "geometry": {"coordinates":[-1.037206,50.87558],"type":"Point"}
}
