{
  "type": "Feature",
  "properties": {
    "date:inception_lower":"1980-01-01",
    "date:inception_upper":"1980-01-31",
    "iso:country":"GB",
    "wof:name":"E7 0LB",
    "wof:placetype":"postalcode"
},
  "geometry": {"coordinates":[0.028831,51.551538],"type":"Point"}
}