{
  "type": "Feature",
  "properties": {
    "iso:country":"GB",
    "wof:name":"AB10 6QT",
    "wof:placetype":"postalcode"
},
  "geometry": {"coordinates":[-2.11926355761073,57.14016337081628],"type":"Point"}
}