{
  "type": "Feature",
  "properties": {
    "date:inception_lower":"1980-01-01",
    "date:inception_upper":"1980-01-31",
    "iso:country":"GB",
    "wof:name":"EX16 7PR",
    "wof:placetype":"postalcode"
},
  "geometry": {"coordinates":[-3.472292,50.923597],"type":"Point"}
}