{
  "type": "Feature",
  "properties": {
    "iso:country":"GB",
    "wof:name":"EX16 7PR",
    "wof:placetype":"postalcode"
},
  "geometry": {"coordinates":[-3.47229178702122,50.92359718349847],"type":"Point"}
}