{
  "type": "Feature",
  "properties": {
    "iso:country":"GB",
    "wof:name":"TN26 3JS",
    "wof:placetype":"postalcode"
},
  "geometry": {"coordinates":[0.74428480219057,51.11489216428307],"type":"Point"}
}