{
  "type": "Feature",
  "properties": {
    "iso:country": "GB",
    "wof:name": "TN26 3JS",
    "wof:placetype": "postalcode"
  },
  "geometry": {"coordinates":[0.744285,51.114892],"type":"Point"}
}
