{
  "type": "Feature",
  "properties": {
    "date:inception_lower": "2003-03-01",
    "date:inception_upper": "2003-03-01",
    "iso:country": "GB",
    "wof:name": "L12 5FB",
    "wof:placetype": "postalcode"
  },
  "geometry": {"coordinates":[-2.904727,53.437995],"type":"Point"}
}
