{
  "type": "Feature",
  "properties": {
    "iso:country": "GB",
    "wof:name": "ST18 0LY",
    "wof:placetype": "postalcode"
  },
  "geometry": {"coordinates":[-1.99319,52.831369],"type":"Point"}
}
