{
  "type": "Feature",
  "properties": {
    "iso:country":"GB",
    "wof:name":"BA14 9RN",
    "wof:placetype":"postalcode"
},
  "geometry": {"coordinates":[-2.21779414445285,51.29289259370272],"type":"Point"}
}