{
  "type": "Feature",
  "properties": {
    "iso:country": "GB",
    "wof:name": "PO9 9ST",
    "wof:placetype": "postalcode"
  },
  "geometry": {"coordinates":[-0.984256,50.857596],"type":"Point"}
}
