{
  "type": "Feature",
  "properties": {
    "iso:country":"GB",
    "wof:name":"WR9 9ET",
    "wof:placetype":"postalcode"
},
  "geometry": {"coordinates":[-2.16935724245472,52.27301381637506],"type":"Point"}
}