{
  "type": "Feature",
  "properties": {
    "date:inception_lower": "1980-01-01",
    "date:inception_upper": "1980-01-01",
    "iso:country": "GB",
    "wof:name": "WR9 9ET",
    "wof:placetype": "postalcode"
  },
  "geometry": {"coordinates":[-2.169357,52.273014],"type":"Point"}
}
