{
  "type": "Feature",
  "properties": {
    "iso:country":"GB",
    "wof:name":"SK17 6JR",
    "wof:placetype":"postalcode"
},
  "geometry": {"coordinates":[-1.9183915816037,53.25462015554545],"type":"Point"}
}