{
  "type": "Feature",
  "properties": {
    "iso:country": "GB",
    "wof:name": "SK17 6JR",
    "wof:placetype": "postalcode"
  },
  "geometry": {"coordinates":[-1.91839,53.254636],"type":"Point"}
}
