{
  "type": "Feature",
  "properties": {
    "date:inception_lower": "1980-01-01",
    "date:inception_upper": "1980-01-01",
    "iso:country": "GB",
    "wof:name": "WF2 7PF",
    "wof:placetype": "postalcode"
  },
  "geometry": {"coordinates":[-1.516674,53.638712],"type":"Point"}
}
