{
  "type": "Feature",
  "properties": {
    "iso:country":"GB",
    "wof:name":"WF2 7PF",
    "wof:placetype":"postalcode"
},
  "geometry": {"coordinates":[-1.51647654085382,53.63855052655098],"type":"Point"}
}