{
  "type": "Feature",
  "properties": {
    "iso:country": "GB",
    "wof:name": "CA4 8BU",
    "wof:placetype": "postalcode"
  },
  "geometry": {"coordinates":[-2.874678,54.888399],"type":"Point"}
}
