{
  "type": "Feature",
  "properties": {
    "iso:country":"GB",
    "wof:name":"CA4 8BU",
    "wof:placetype":"postalcode"
},
  "geometry": {"coordinates":[-2.87467840220222,54.88839875676948],"type":"Point"}
}