{
  "type": "Feature",
  "properties": {
    "date:inception_lower": "1997-06-01",
    "date:inception_upper": "1997-06-01",
    "iso:country": "GB",
    "wof:name": "S25 2TA",
    "wof:placetype": "postalcode"
  },
  "geometry": {"coordinates":[-1.205374,53.362826],"type":"Point"}
}
