{
  "type": "Feature",
  "properties": {
    "date:inception_lower": "1980-01-01",
    "date:inception_upper": "1980-01-01",
    "iso:country": "GB",
    "wof:name": "TN27 0EL",
    "wof:placetype": "postalcode"
  },
  "geometry": {"coordinates":[0.805023,51.193985],"type":"Point"}
}
