{
  "type": "Feature",
  "properties": {
    "iso:country":"GB",
    "wof:name":"TN27 0EL",
    "wof:placetype":"postalcode"
},
  "geometry": {"coordinates":[0.80502330206224,51.19398492628109],"type":"Point"}
}