{
  "type": "Feature",
  "properties": {
    "iso:country":"GB",
    "wof:name":"NW4 3XE",
    "wof:placetype":"postalcode"
},
  "geometry": {"coordinates":[-0.23162019491671,51.5821992723145],"type":"Point"}
}