{
  "type": "Feature",
  "properties": {
    "iso:country":"GB",
    "wof:name":"DH7 6EP",
    "wof:placetype":"postalcode"
},
  "geometry": {"coordinates":[-1.66121257846972,54.83718594409788],"type":"Point"}
}