{
  "type": "Feature",
  "properties": {
    "iso:country": "GB",
    "wof:name": "DH7 6EP",
    "wof:placetype": "postalcode"
  },
  "geometry": {"coordinates":[-1.661213,54.837186],"type":"Point"}
}
