{
  "type": "Feature",
  "properties": {
    "iso:country": "GB",
    "wof:name": "G43 2XR",
    "wof:placetype": "postalcode"
  },
  "geometry": {"coordinates":[-4.28736,55.824298],"type":"Point"}
}
