{
  "type": "Feature",
  "properties": {
    "iso:country":"GB",
    "wof:name":"RH8 0DR",
    "wof:placetype":"postalcode"
},
  "geometry": {"coordinates":[0.01396103978135,51.25900553052725],"type":"Point"}
}