{
  "type": "Feature",
  "properties": {
    "iso:country":"GB",
    "wof:name":"OL2 5NN",
    "wof:placetype":"postalcode"
},
  "geometry": {"coordinates":[-2.14291680540092,53.56201537205548],"type":"Point"}
}