{
  "type": "Feature",
  "properties": {
    "date:inception_lower": "1983-03-01",
    "date:inception_upper": "1983-03-01",
    "iso:country": "GB",
    "wof:name": "OL2 5NN",
    "wof:placetype": "postalcode"
  },
  "geometry": {"coordinates":[-2.142764,53.56231],"type":"Point"}
}
