{
  "type": "Feature",
  "properties": {
    "iso:country":"GB",
    "wof:name":"DN40 2LW",
    "wof:placetype":"postalcode"
},
  "geometry": {"coordinates":[-0.20944220836824,53.61959277843793],"type":"Point"}
}