{
  "type": "Feature",
  "properties": {
    "date:inception_lower":"1990-02-01",
    "date:inception_upper":"1990-02-28",
    "iso:country":"GB",
    "wof:name":"PO12 1UA",
    "wof:placetype":"postalcode"
},
  "geometry": {"coordinates":[-1.135917,50.794194],"type":"Point"}
}