{
  "type": "Feature",
  "properties": {
    "iso:country": "GB",
    "wof:name": "PO12 1UA",
    "wof:placetype": "postalcode"
  },
  "geometry": {"coordinates":[-1.136054,50.794447],"type":"Point"}
}
