{
  "type": "Feature",
  "properties": {
    "iso:country":"GB",
    "wof:name":"SY7 9BU",
    "wof:placetype":"postalcode"
},
  "geometry": {"coordinates":[-2.8175008885422,52.44248773553701],"type":"Point"}
}