{
  "type": "Feature",
  "properties": {
    "iso:country": "GB",
    "wof:name": "LN5 0ER",
    "wof:placetype": "postalcode"
  },
  "geometry": {"coordinates":[-0.520558,53.10631],"type":"Point"}
}
