{
  "type": "Feature",
  "properties": {
    "iso:country":"GB",
    "wof:name":"LN5 0ER",
    "wof:placetype":"postalcode"
},
  "geometry": {"coordinates":[-0.52055807066642,53.10631002322391],"type":"Point"}
}