{
  "type": "Feature",
  "properties": {
    "iso:country":"GB",
    "wof:name":"NG9 2EX",
    "wof:placetype":"postalcode"
},
  "geometry": {"coordinates":[-1.20306618766522,52.92619709669462],"type":"Point"}
}