{
  "type": "Feature",
  "properties": {
    "iso:country":"GB",
    "wof:name":"NW1 8JS",
    "wof:placetype":"postalcode"
},
  "geometry": {"coordinates":[-0.1516897781408,51.53976432439651],"type":"Point"}
}