{
  "type": "Feature",
  "properties": {
    "iso:country":"GB",
    "wof:name":"S18 8YT",
    "wof:placetype":"postalcode"
},
  "geometry": {"coordinates":[-1.50590910256575,53.30201214163492],"type":"Point"}
}