{
  "type": "Feature",
  "properties": {
    "iso:country": "GB",
    "wof:name": "DE11 8LZ",
    "wof:placetype": "postalcode"
  },
  "geometry": {"coordinates":[-1.550358,52.77241],"type":"Point"}
}
