{
  "type": "Feature",
  "properties": {
    "iso:country":"GB",
    "wof:name":"DE11 8LZ",
    "wof:placetype":"postalcode"
},
  "geometry": {"coordinates":[-1.55035853010863,52.77241030927485],"type":"Point"}
}