{
  "type": "Feature",
  "properties": {
    "date:inception_lower": "1986-07-01",
    "date:inception_upper": "1986-07-01",
    "iso:country": "GB",
    "wof:name": "SE19 2EE",
    "wof:placetype": "postalcode"
  },
  "geometry": {"coordinates":[-0.080888,51.409664],"type":"Point"}
}
