{
  "type": "Feature",
  "properties": {
    "iso:country": "GB",
    "wof:name": "SE19 2EE",
    "wof:placetype": "postalcode"
  },
  "geometry": {"coordinates":[-0.080888,51.409664],"type":"Point"}
}
