{
  "type": "Feature",
  "properties": {
    "iso:country": "GB",
    "wof:name": "W1B 1QU",
    "wof:placetype": "postalcode"
  },
  "geometry": {"coordinates":[-0.146377,51.522172],"type":"Point"}
}
