{
  "type": "Feature",
  "properties": {
    "iso:country":"GB",
    "wof:name":"W1B 1QU",
    "wof:placetype":"postalcode"
},
  "geometry": {"coordinates":[-0.14637676721549,51.52217214697389],"type":"Point"}
}