{
  "type": "Feature",
  "properties": {
    "date:inception_lower": "1980-01-01",
    "date:inception_upper": "1980-01-01",
    "iso:country": "GB",
    "wof:name": "CB10 1BZ",
    "wof:placetype": "postalcode"
  },
  "geometry": {"coordinates":[0.23517,52.024154],"type":"Point"}
}
