{
  "type": "Feature",
  "properties": {
    "iso:country": "GB",
    "wof:name": "LS12 3PY",
    "wof:placetype": "postalcode"
  },
  "geometry": {"coordinates":[-1.608869,53.799065],"type":"Point"}
}
