{
  "type": "Feature",
  "properties": {
    "iso:country":"GB",
    "wof:name":"LS12 3PY",
    "wof:placetype":"postalcode"
},
  "geometry": {"coordinates":[-1.60886954342149,53.79906541004606],"type":"Point"}
}