{
  "type": "Feature",
  "properties": {
    "iso:country":"GB",
    "wof:name":"M2 5WG",
    "wof:placetype":"postalcode"
},
  "geometry": {"coordinates":[-2.2459694392712,53.47865101506625],"type":"Point"}
}