{
  "type": "Feature",
  "properties": {
    "iso:country":"GB",
    "wof:name":"HP15 7UP",
    "wof:placetype":"postalcode"
},
  "geometry": {"coordinates":[-0.70903792564546,51.65016786642954],"type":"Point"}
}