{
  "type": "Feature",
  "properties": {
    "iso:country":"GB",
    "wof:name":"SW2 2ET",
    "wof:placetype":"postalcode"
},
  "geometry": {"coordinates":[-0.11454781391812,51.45061451208541],"type":"Point"}
}