{
  "type": "Feature",
  "properties": {
    "date:inception_lower":"2015-01-01",
    "date:inception_upper":"2015-01-31",
    "iso:country":"GB",
    "wof:name":"SE1 4GR",
    "wof:placetype":"postalcode"
},
  "geometry": {"coordinates":[-0.085895,51.499412],"type":"Point"}
}