{
  "type": "Feature",
  "properties": {
    "iso:country":"GB",
    "wof:name":"NE65 9DH",
    "wof:placetype":"postalcode"
},
  "geometry": {"coordinates":[-1.71321420801253,55.30182873071809],"type":"Point"}
}