{
  "type": "Feature",
  "properties": {
    "date:inception_lower":"1990-07-01",
    "date:inception_upper":"1990-07-31",
    "iso:country":"GB",
    "wof:name":"NE65 9DH",
    "wof:placetype":"postalcode"
},
  "geometry": {"coordinates":[-1.713214,55.301829],"type":"Point"}
}