{
  "type": "Feature",
  "properties": {
    "iso:country":"GB",
    "wof:name":"BN1 2GB",
    "wof:placetype":"postalcode"
},
  "geometry": {"coordinates":[-0.14961635834686,50.82252537503808],"type":"Point"}
}