{
  "type": "Feature",
  "properties": {
    "iso:country":"GB",
    "wof:name":"SG12 9HU",
    "wof:placetype":"postalcode"
},
  "geometry": {"coordinates":[-0.03320420519056,51.80966036884518],"type":"Point"}
}