{
  "type": "Feature",
  "properties": {
    "iso:country": "GB",
    "wof:name": "E17 3EZ",
    "wof:placetype": "postalcode"
  },
  "geometry": {"coordinates":[-0.010359,51.587244],"type":"Point"}
}
