{
  "type": "Feature",
  "properties": {
    "iso:country":"GB",
    "wof:name":"E17 3EZ",
    "wof:placetype":"postalcode"
},
  "geometry": {"coordinates":[-0.01035915060721,51.58724440205049],"type":"Point"}
}