{
  "type": "Feature",
  "properties": {
    "date:inception_lower":"1980-01-01",
    "date:inception_upper":"1980-01-31",
    "iso:country":"GB",
    "wof:name":"E17 3EZ",
    "wof:placetype":"postalcode"
},
  "geometry": {"coordinates":[-0.010359,51.587244],"type":"Point"}
}