{
  "type": "Feature",
  "properties": {
    "date:inception_lower":"1980-01-01",
    "date:inception_upper":"1980-01-31",
    "iso:country":"GB",
    "wof:name":"HR6 8DL",
    "wof:placetype":"postalcode"
},
  "geometry": {"coordinates":[-2.74177,52.229763],"type":"Point"}
}