{
  "type": "Feature",
  "properties": {
    "iso:country": "GB",
    "wof:name": "HR6 8DL",
    "wof:placetype": "postalcode"
  },
  "geometry": {"coordinates":[-2.74177,52.229763],"type":"Point"}
}
