{
  "type": "Feature",
  "properties": {
    "iso:country":"GB",
    "wof:name":"HR6 8DL",
    "wof:placetype":"postalcode"
},
  "geometry": {"coordinates":[-2.74176984360833,52.22976257377559],"type":"Point"}
}