{
  "type": "Feature",
  "properties": {
    "iso:country":"GB",
    "wof:name":"L35 3QY",
    "wof:placetype":"postalcode"
},
  "geometry": {"coordinates":[-2.79575801214207,53.41565156341656],"type":"Point"}
}