{
  "type": "Feature",
  "properties": {
    "iso:country":"GB",
    "wof:name":"PE19 2GF",
    "wof:placetype":"postalcode"
},
  "geometry": {"coordinates":[-0.27422436558332,52.21348374733547],"type":"Point"}
}