{
  "type": "Feature",
  "properties": {
    "date:inception_lower": "2004-05-01",
    "date:inception_upper": "2004-05-01",
    "iso:country": "GB",
    "wof:name": "PE19 2GF",
    "wof:placetype": "postalcode"
  },
  "geometry": {"coordinates":[-0.274224,52.213484],"type":"Point"}
}
