{
  "type": "Feature",
  "properties": {
    "iso:country": "GB",
    "wof:name": "RM1 1TA",
    "wof:placetype": "postalcode"
  },
  "geometry": {"coordinates":[0.181426,51.573773],"type":"Point"}
}
