{
  "type": "Feature",
  "properties": {
    "iso:country":"GB",
    "wof:name":"OX2 8LZ",
    "wof:placetype":"postalcode"
},
  "geometry": {"coordinates":[-1.26447305283689,51.78926190914661],"type":"Point"}
}