{
  "type": "Feature",
  "properties": {
    "date:inception_lower": "1980-01-01",
    "date:inception_upper": "1980-01-01",
    "iso:country": "GB",
    "wof:name": "DN6 7PS",
    "wof:placetype": "postalcode"
  },
  "geometry": {"coordinates":[-1.185746,53.55979],"type":"Point"}
}
