{
  "type": "Feature",
  "properties": {
    "iso:country":"GB",
    "wof:name":"AL1 3UD",
    "wof:placetype":"postalcode"
},
  "geometry": {"coordinates":[-0.33247689860682,51.75169261782627],"type":"Point"}
}