{
  "type": "Feature",
  "properties": {
    "iso:country":"GB",
    "wof:name":"S73 0YJ",
    "wof:placetype":"postalcode"
},
  "geometry": {"coordinates":[-1.37311093049536,53.51999353965294],"type":"Point"}
}