{
  "type": "Feature",
  "properties": {
    "iso:country": "GB",
    "wof:name": "YO21 2PH",
    "wof:placetype": "postalcode"
  },
  "geometry": {"coordinates":[-0.805584,54.438832],"type":"Point"}
}
