{
  "type": "Feature",
  "properties": {
    "iso:country":"GB",
    "wof:name":"YO21 2PH",
    "wof:placetype":"postalcode"
},
  "geometry": {"coordinates":[-0.80558392110528,54.4388317712201],"type":"Point"}
}