{
  "type": "Feature",
  "properties": {
    "iso:country":"GB",
    "wof:name":"SG6 4PY",
    "wof:placetype":"postalcode"
},
  "geometry": {"coordinates":[-0.22366250214857,51.99567647272828],"type":"Point"}
}