{
  "type": "Feature",
  "properties": {
    "iso:country": "GB",
    "wof:name": "SG6 4PY",
    "wof:placetype": "postalcode"
  },
  "geometry": {"coordinates":[-0.222625,51.995823],"type":"Point"}
}
