{
  "type": "Feature",
  "properties": {
    "iso:country": "GB",
    "wof:name": "KT1 2AY",
    "wof:placetype": "postalcode"
  },
  "geometry": {"coordinates":[-0.305855,51.403375],"type":"Point"}
}
