{
  "type": "Feature",
  "properties": {
    "date:inception_lower":"1980-01-01",
    "date:inception_upper":"1980-01-31",
    "iso:country":"GB",
    "wof:name":"KT1 2AY",
    "wof:placetype":"postalcode"
},
  "geometry": {"coordinates":[-0.305855,51.403375],"type":"Point"}
}