{
  "type": "Feature",
  "properties": {
    "iso:country": "GB",
    "wof:name": "DD9 7PN",
    "wof:placetype": "postalcode"
  },
  "geometry": {"coordinates":[-2.610927,56.721878],"type":"Point"}
}
