{
  "type": "Feature",
  "properties": {
    "date:inception_lower":"1980-01-01",
    "date:inception_upper":"1980-01-31",
    "iso:country":"GB",
    "wof:name":"HU5 2EJ",
    "wof:placetype":"postalcode"
},
  "geometry": {"coordinates":[-0.358654,53.767827],"type":"Point"}
}