{
  "type": "Feature",
  "properties": {
    "iso:country":"GB",
    "wof:name":"HU5 2EJ",
    "wof:placetype":"postalcode"
},
  "geometry": {"coordinates":[-0.35860385253255,53.76777912833954],"type":"Point"}
}