{
  "type": "Feature",
  "properties": {
    "iso:country": "GB",
    "wof:name": "SA11 3PY",
    "wof:placetype": "postalcode"
  },
  "geometry": {"coordinates":[-3.786001,51.650437],"type":"Point"}
}
