{
  "type": "Feature",
  "properties": {
    "iso:country":"GB",
    "wof:name":"SA11 3PY",
    "wof:placetype":"postalcode"
},
  "geometry": {"coordinates":[-3.78600101384391,51.65043655493656],"type":"Point"}
}