{
  "type": "Feature",
  "properties": {
    "iso:country":"GB",
    "wof:name":"CH43 9QA",
    "wof:placetype":"postalcode"
},
  "geometry": {"coordinates":[-3.081135321943,53.39024368529051],"type":"Point"}
}