{
  "type": "Feature",
  "properties": {
    "iso:country": "GB",
    "wof:name": "CH43 9QA",
    "wof:placetype": "postalcode"
  },
  "geometry": {"coordinates":[-3.081135,53.390244],"type":"Point"}
}
