{
  "type": "Feature",
  "properties": {
    "date:inception_lower": "2023-01-01",
    "date:inception_upper": "2023-01-01",
    "iso:country": "GB",
    "wof:name": "BH21 3EX",
    "wof:placetype": "postalcode"
  },
  "geometry": {"coordinates":[-2.017275,50.780207],"type":"Point"}
}
