{
  "type": "Feature",
  "properties": {
    "date:inception_lower": "1980-01-01",
    "date:inception_upper": "1980-01-01",
    "iso:country": "GB",
    "wof:name": "CO2 7BH",
    "wof:placetype": "postalcode"
  },
  "geometry": {"coordinates":[0.895978,51.886131],"type":"Point"}
}
