{
  "type": "Feature",
  "properties": {
    "iso:country":"GB",
    "wof:name":"UB1 1JG",
    "wof:placetype":"postalcode"
},
  "geometry": {"coordinates":[-0.38475173163462,51.50953762804093],"type":"Point"}
}