{
  "type": "Feature",
  "properties": {
    "iso:country":"GB",
    "wof:name":"DE15 9RX",
    "wof:placetype":"postalcode"
},
  "geometry": {"coordinates":[-1.62241359398801,52.78930998334548],"type":"Point"}
}