{
  "type": "Feature",
  "properties": {
    "date:inception_lower":"2015-04-01",
    "date:inception_upper":"2015-04-30",
    "iso:country":"GB",
    "wof:name":"DE15 9RX",
    "wof:placetype":"postalcode"
},
  "geometry": {"coordinates":[-1.622289,52.789399],"type":"Point"}
}