{
  "type": "Feature",
  "properties": {
    "date:inception_lower": "1992-08-01",
    "date:inception_upper": "1992-08-01",
    "iso:country": "GB",
    "wof:name": "DE22 4DR",
    "wof:placetype": "postalcode"
  },
  "geometry": {"coordinates":[-1.513907,52.929609],"type":"Point"}
}
