{
  "type": "Feature",
  "properties": {
    "iso:country":"GB",
    "wof:name":"DE22 4DR",
    "wof:placetype":"postalcode"
},
  "geometry": {"coordinates":[-1.51390671273994,52.9296094911362],"type":"Point"}
}