{
  "type": "Feature",
  "properties": {
    "iso:country": "GB",
    "wof:name": "OL7 0PD",
    "wof:placetype": "postalcode"
  },
  "geometry": {"coordinates":[-2.10901,53.480554],"type":"Point"}
}
