{
  "type": "Feature",
  "properties": {
    "date:inception_lower":"2002-06-01",
    "date:inception_upper":"2002-06-30",
    "iso:country":"GB",
    "wof:name":"OL7 0PD",
    "wof:placetype":"postalcode"
},
  "geometry": {"coordinates":[-2.10901,53.480554],"type":"Point"}
}