{
  "type": "Feature",
  "properties": {
    "date:inception_lower": "1986-07-01",
    "date:inception_upper": "1986-07-01",
    "iso:country": "GB",
    "wof:name": "TA12 6LT",
    "wof:placetype": "postalcode"
  },
  "geometry": {"coordinates":[-2.775616,50.957455],"type":"Point"}
}
