{
  "type": "Feature",
  "properties": {
    "iso:country":"GB",
    "wof:name":"TA12 6LT",
    "wof:placetype":"postalcode"
},
  "geometry": {"coordinates":[-2.7755551617372,50.95744482790521],"type":"Point"}
}