{
  "type": "Feature",
  "properties": {
    "iso:country": "GB",
    "wof:name": "TA12 6LT",
    "wof:placetype": "postalcode"
  },
  "geometry": {"coordinates":[-2.775555,50.957445],"type":"Point"}
}
