{
  "type": "Feature",
  "properties": {
    "iso:country":"GB",
    "wof:name":"E14 6RB",
    "wof:placetype":"postalcode"
},
  "geometry": {"coordinates":[-0.01229833650623,51.51764752122866],"type":"Point"}
}