{
  "type": "Feature",
  "properties": {
    "date:inception_lower": "1981-06-01",
    "date:inception_upper": "1981-06-01",
    "iso:country": "GB",
    "wof:name": "E14 6RB",
    "wof:placetype": "postalcode"
  },
  "geometry": {"coordinates":[-0.012298,51.517648],"type":"Point"}
}
