{
  "type": "Feature",
  "properties": {
    "date:inception_lower": "2014-10-01",
    "date:inception_upper": "2014-10-01",
    "iso:country": "GB",
    "wof:name": "MK42 6DP",
    "wof:placetype": "postalcode"
  },
  "geometry": {"coordinates":[-0.461879,52.09333],"type":"Point"}
}
