{
  "type": "Feature",
  "properties": {
    "iso:country":"GB",
    "wof:name":"DL12 8UE",
    "wof:placetype":"postalcode"
},
  "geometry": {"coordinates":[-1.8921636814497,54.55704820987618],"type":"Point"}
}