{
  "type": "Feature",
  "properties": {
    "iso:country": "GB",
    "wof:name": "DL12 8UE",
    "wof:placetype": "postalcode"
  },
  "geometry": {"coordinates":[-1.892164,54.557048],"type":"Point"}
}
