{
  "type": "Feature",
  "properties": {
    "iso:country":"GB",
    "wof:name":"PE33 9HE",
    "wof:placetype":"postalcode"
},
  "geometry": {"coordinates":[0.48187018623176,52.63074567669323],"type":"Point"}
}