{
  "type": "Feature",
  "properties": {
    "iso:country":"GB",
    "wof:name":"PO9 2LA",
    "wof:placetype":"postalcode"
},
  "geometry": {"coordinates":[-0.9750147304676,50.86501503687268],"type":"Point"}
}