{
  "type": "Feature",
  "properties": {
    "iso:country":"GB",
    "wof:name":"LD1 5UT",
    "wof:placetype":"postalcode"
},
  "geometry": {"coordinates":[-3.19801104317435,52.34461838089173],"type":"Point"}
}