{
  "type": "Feature",
  "properties": {
    "date:inception_lower": "2020-02-01",
    "date:inception_upper": "2020-02-01",
    "iso:country": "GB",
    "wof:name": "MK3 5RX",
    "wof:placetype": "postalcode"
  },
  "geometry": {"coordinates":[-0.741889,51.975675],"type":"Point"}
}
