{
  "type": "Feature",
  "properties": {
    "iso:country":"GB",
    "wof:name":"G41 2NA",
    "wof:placetype":"postalcode"
},
  "geometry": {"coordinates":[-4.27459825723546,55.84225802952994],"type":"Point"}
}