{
  "type": "Feature",
  "properties": {
    "date:inception_lower":"1981-12-01",
    "date:inception_upper":"1981-12-31",
    "iso:country":"GB",
    "wof:name":"LS12 4EB",
    "wof:placetype":"postalcode"
},
  "geometry": {"coordinates":[-1.583733,53.789364],"type":"Point"}
}