{
  "type": "Feature",
  "properties": {
    "iso:country":"GB",
    "wof:name":"LS12 4EB",
    "wof:placetype":"postalcode"
},
  "geometry": {"coordinates":[-1.58373260716704,53.78936365964636],"type":"Point"}
}