{
  "type": "Feature",
  "properties": {
    "iso:country": "GB",
    "wof:name": "OL13 0DP",
    "wof:placetype": "postalcode"
  },
  "geometry": {"coordinates":[-2.210463,53.692856],"type":"Point"}
}
