{
  "type": "Feature",
  "properties": {
    "iso:country":"GB",
    "wof:name":"WF13 4LT",
    "wof:placetype":"postalcode"
},
  "geometry": {"coordinates":[-1.64734802394147,53.69679241566394],"type":"Point"}
}