{
  "type": "Feature",
  "properties": {
    "date:inception_lower": "1980-01-01",
    "date:inception_upper": "1980-01-01",
    "iso:country": "GB",
    "wof:name": "WF13 4LT",
    "wof:placetype": "postalcode"
  },
  "geometry": {"coordinates":[-1.647348,53.696792],"type":"Point"}
}
