{
  "type": "Feature",
  "properties": {
    "date:inception_lower": "1980-01-01",
    "date:inception_upper": "1980-01-01",
    "iso:country": "GB",
    "wof:name": "BL4 8JN",
    "wof:placetype": "postalcode"
  },
  "geometry": {"coordinates":[-2.376113,53.538741],"type":"Point"}
}
