{
  "type": "Feature",
  "properties": {
    "iso:country": "GB",
    "wof:name": "SY13 3DA",
    "wof:placetype": "postalcode"
  },
  "geometry": {"coordinates":[-2.81104,52.966746],"type":"Point"}
}
