{
  "type": "Feature",
  "properties": {
    "date:inception_lower": "1980-01-01",
    "date:inception_upper": "1980-01-01",
    "iso:country": "GB",
    "wof:name": "PO41 0RA",
    "wof:placetype": "postalcode"
  },
  "geometry": {"coordinates":[-1.49799,50.703636],"type":"Point"}
}
