{
  "type": "Feature",
  "properties": {
    "iso:country":"GB",
    "wof:name":"WR2 5JD",
    "wof:placetype":"postalcode"
},
  "geometry": {"coordinates":[-2.23987662148368,52.19383927297966],"type":"Point"}
}