{
  "type": "Feature",
  "properties": {
    "iso:country":"GB",
    "wof:name":"RH2 0QR",
    "wof:placetype":"postalcode"
},
  "geometry": {"coordinates":[-0.19057501233273,51.23751696006965],"type":"Point"}
}