{
  "type": "Feature",
  "properties": {
    "iso:country": "GB",
    "wof:name": "NR25 6TP",
    "wof:placetype": "postalcode"
  },
  "geometry": {"coordinates":[1.12558,52.884971],"type":"Point"}
}
