{
  "type": "Feature",
  "properties": {
    "iso:country":"GB",
    "wof:name":"NR25 6TP",
    "wof:placetype":"postalcode"
},
  "geometry": {"coordinates":[1.12557993544903,52.88497147369806],"type":"Point"}
}