{
  "type": "Feature",
  "properties": {
    "iso:country": "GB",
    "wof:name": "CA14 2DN",
    "wof:placetype": "postalcode"
  },
  "geometry": {"coordinates":[-3.551329,54.645213],"type":"Point"}
}
