{
  "type": "Feature",
  "properties": {
    "date:inception_lower": "2013-09-01",
    "date:inception_upper": "2013-09-01",
    "iso:country": "GB",
    "wof:name": "CA14 2DN",
    "wof:placetype": "postalcode"
  },
  "geometry": {"coordinates":[-3.551329,54.645213],"type":"Point"}
}
