{
  "type": "Feature",
  "properties": {
    "iso:country":"GB",
    "wof:name":"BB5 5SZ",
    "wof:placetype":"postalcode"
},
  "geometry": {"coordinates":[-2.39026199304775,53.77890637300825],"type":"Point"}
}