{
  "type": "Feature",
  "properties": {
    "iso:country":"GB",
    "wof:name":"WF6 1UR",
    "wof:placetype":"postalcode"
},
  "geometry": {"coordinates":[-1.40297152089641,53.69492548404304],"type":"Point"}
}