{
  "type": "Feature",
  "properties": {
    "date:inception_lower":"2000-12-01",
    "date:inception_upper":"2000-12-31",
    "iso:country":"GB",
    "wof:name":"WF6 1UR",
    "wof:placetype":"postalcode"
},
  "geometry": {"coordinates":[-1.402971,53.694925],"type":"Point"}
}