{
  "type": "Feature",
  "properties": {
    "iso:country": "GB",
    "wof:name": "S80 3JD",
    "wof:placetype": "postalcode"
  },
  "geometry": {"coordinates":[-1.15272,53.313504],"type":"Point"}
}
