{
  "type": "Feature",
  "properties": {
    "iso:country":"GB",
    "wof:name":"S80 3JD",
    "wof:placetype":"postalcode"
},
  "geometry": {"coordinates":[-1.15257221180194,53.31338365429207],"type":"Point"}
}