{
  "type": "Feature",
  "properties": {
    "iso:country": "GB",
    "wof:name": "TS6 0QY",
    "wof:placetype": "postalcode"
  },
  "geometry": {"coordinates":[-1.153816,54.557572],"type":"Point"}
}
