{
  "type": "Feature",
  "properties": {
    "iso:country":"GB",
    "wof:name":"TS6 0QY",
    "wof:placetype":"postalcode"
},
  "geometry": {"coordinates":[-1.1538156268282,54.55757208666737],"type":"Point"}
}