{
  "type": "Feature",
  "properties": {
    "iso:country":"GB",
    "wof:name":"PE12 0PB",
    "wof:placetype":"postalcode"
},
  "geometry": {"coordinates":[-0.01568395189698,52.68152127973284],"type":"Point"}
}