{
  "type": "Feature",
  "properties": {
    "iso:country": "GB",
    "wof:name": "EX13 7NZ",
    "wof:placetype": "postalcode"
  },
  "geometry": {"coordinates":[-3.047215,50.770217],"type":"Point"}
}
