{
  "type": "Feature",
  "properties": {
    "iso:country": "GB",
    "wof:name": "WA1 3EP",
    "wof:placetype": "postalcode"
  },
  "geometry": {"coordinates":[-2.555355,53.399124],"type":"Point"}
}
