{
  "type": "Feature",
  "properties": {
    "iso:country":"GB",
    "wof:name":"WA1 3EP",
    "wof:placetype":"postalcode"
},
  "geometry": {"coordinates":[-2.55535500904002,53.39912448843424],"type":"Point"}
}