{
  "type": "Feature",
  "properties": {
    "iso:country":"GB",
    "wof:name":"IG1 2RB",
    "wof:placetype":"postalcode"
},
  "geometry": {"coordinates":[0.08525194114362,51.5472574518764],"type":"Point"}
}