{
  "type": "Feature",
  "properties": {
    "date:inception_lower":"1995-01-01",
    "date:inception_upper":"1995-01-31",
    "iso:country":"GB",
    "wof:name":"IG1 2RB",
    "wof:placetype":"postalcode"
},
  "geometry": {"coordinates":[0.085252,51.547257],"type":"Point"}
}