{
  "type": "Feature",
  "properties": {
    "iso:country":"GB",
    "wof:name":"YO8 9PB",
    "wof:placetype":"postalcode"
},
  "geometry": {"coordinates":[-1.13421903022771,53.77332648179546],"type":"Point"}
}