{
  "type": "Feature",
  "properties": {
    "iso:country": "GB",
    "wof:name": "YO8 9PB",
    "wof:placetype": "postalcode"
  },
  "geometry": {"coordinates":[-1.134219,53.773326],"type":"Point"}
}
