{
  "type": "Feature",
  "properties": {
    "date:inception_lower":"1980-01-01",
    "date:inception_upper":"1980-01-31",
    "iso:country":"GB",
    "wof:name":"OX5 2LB",
    "wof:placetype":"postalcode"
},
  "geometry": {"coordinates":[-1.280723,51.817694],"type":"Point"}
}