{
  "type": "Feature",
  "properties": {
    "iso:country": "GB",
    "wof:name": "OX5 2LB",
    "wof:placetype": "postalcode"
  },
  "geometry": {"coordinates":[-1.280723,51.817694],"type":"Point"}
}
