{
  "type": "Feature",
  "properties": {
    "iso:country": "GB",
    "wof:name": "S18 1RE",
    "wof:placetype": "postalcode"
  },
  "geometry": {"coordinates":[-1.475049,53.296631],"type":"Point"}
}
