{
  "type": "Feature",
  "properties": {
    "date:inception_lower": "2021-08-01",
    "date:inception_upper": "2021-08-01",
    "iso:country": "GB",
    "wof:name": "RG23 7GU",
    "wof:placetype": "postalcode"
  },
  "geometry": {"coordinates":[-1.144788,51.231778],"type":"Point"}
}
