{
  "type": "Feature",
  "properties": {
    "iso:country":"GB",
    "wof:name":"RG7 5DZ",
    "wof:placetype":"postalcode"
},
  "geometry": {"coordinates":[-1.08781573094014,51.44158018822217],"type":"Point"}
}