{
  "type": "Feature",
  "properties": {
    "iso:country": "GB",
    "wof:name": "RG7 5DZ",
    "wof:placetype": "postalcode"
  },
  "geometry": {"coordinates":[-1.087816,51.44158],"type":"Point"}
}
