{
  "type": "Feature",
  "properties": {
    "date:inception_lower": "1983-07-01",
    "date:inception_upper": "1983-07-01",
    "iso:country": "GB",
    "wof:name": "RG7 5DZ",
    "wof:placetype": "postalcode"
  },
  "geometry": {"coordinates":[-1.087816,51.44158],"type":"Point"}
}
