{
  "type": "Feature",
  "properties": {
    "iso:country": "GB",
    "wof:name": "SO20 6DE",
    "wof:placetype": "postalcode"
  },
  "geometry": {"coordinates":[-1.423473,51.129025],"type":"Point"}
}
