{
  "type": "Feature",
  "properties": {
    "iso:country": "GB",
    "wof:name": "SO20 6DE",
    "wof:placetype": "postalcode"
  },
  "geometry": {"coordinates":[-1.423072,51.129113],"type":"Point"}
}
