{
  "type": "Feature",
  "properties": {
    "iso:country":"GB",
    "wof:name":"SK16 5DD",
    "wof:placetype":"postalcode"
},
  "geometry": {"coordinates":[-2.05258344631953,53.47153144730989],"type":"Point"}
}