{
  "type": "Feature",
  "properties": {
    "iso:country":"GB",
    "wof:name":"BS48 3BP",
    "wof:placetype":"postalcode"
},
  "geometry": {"coordinates":[-2.74679613572058,51.40894663232673],"type":"Point"}
}