{
  "type": "Feature",
  "properties": {
    "iso:country": "GB",
    "wof:name": "BS48 3BP",
    "wof:placetype": "postalcode"
  },
  "geometry": {"coordinates":[-2.746796,51.408947],"type":"Point"}
}
