{
  "type": "Feature",
  "properties": {
    "iso:country":"GB",
    "wof:name":"TQ13 9AF",
    "wof:placetype":"postalcode"
},
  "geometry": {"coordinates":[-3.67583752446023,50.59163163347775],"type":"Point"}
}