{
  "type": "Feature",
  "properties": {
    "iso:country":"GB",
    "wof:name":"E14 7GB",
    "wof:placetype":"postalcode"
},
  "geometry": {"coordinates":[-0.02943881203404,51.51257714534122],"type":"Point"}
}