{
  "type": "Feature",
  "properties": {
    "date:inception_lower": "2018-01-01",
    "date:inception_upper": "2018-01-01",
    "iso:country": "GB",
    "wof:name": "LE4 6NQ",
    "wof:placetype": "postalcode"
  },
  "geometry": {"coordinates":[-1.115234,52.653465],"type":"Point"}
}
