{
  "type": "Feature",
  "properties": {
    "iso:country":"GB",
    "wof:name":"EN4 0NB",
    "wof:placetype":"postalcode"
},
  "geometry": {"coordinates":[-0.17931221337432,51.66448837377482],"type":"Point"}
}