{
  "type": "Feature",
  "properties": {
    "iso:country": "GB",
    "wof:name": "PA31 8QB",
    "wof:placetype": "postalcode"
  },
  "geometry": {"coordinates":[-5.444394,56.085497],"type":"Point"}
}
