{
  "type": "Feature",
  "properties": {
    "iso:country":"GB",
    "wof:name":"EX9 7JA",
    "wof:placetype":"postalcode"
},
  "geometry": {"coordinates":[-3.30088172169349,50.65780307789501],"type":"Point"}
}