{
  "type": "Feature",
  "properties": {
    "iso:country": "GB",
    "wof:name": "EX9 7JA",
    "wof:placetype": "postalcode"
  },
  "geometry": {"coordinates":[-3.300882,50.657803],"type":"Point"}
}
