{
  "type": "Feature",
  "properties": {
    "iso:country":"GB",
    "wof:name":"WA5 8TJ",
    "wof:placetype":"postalcode"
},
  "geometry": {"coordinates":[-2.63625186050273,53.40607343492504],"type":"Point"}
}