{
  "type": "Feature",
  "properties": {
    "iso:country": "GB",
    "wof:name": "E13 8FD",
    "wof:placetype": "postalcode"
  },
  "geometry": {"coordinates":[0.022146,51.52178],"type":"Point"}
}
