{
  "type": "Feature",
  "properties": {
    "iso:country": "GB",
    "wof:name": "HU3 2UE",
    "wof:placetype": "postalcode"
  },
  "geometry": {"coordinates":[-0.36643,53.739714],"type":"Point"}
}
