{
  "type": "Feature",
  "properties": {
    "iso:country":"GB",
    "wof:name":"HU3 2UE",
    "wof:placetype":"postalcode"
},
  "geometry": {"coordinates":[-0.36642990200858,53.73971413076828],"type":"Point"}
}