{
  "type": "Feature",
  "properties": {
    "date:inception_lower": "1980-01-01",
    "date:inception_upper": "1980-01-01",
    "iso:country": "GB",
    "wof:name": "HU3 2UE",
    "wof:placetype": "postalcode"
  },
  "geometry": {"coordinates":[-0.366492,53.739852],"type":"Point"}
}
