{
  "type": "Feature",
  "properties": {
    "iso:country":"GB",
    "wof:name":"EX8 1SW",
    "wof:placetype":"postalcode"
},
  "geometry": {"coordinates":[-3.41371982948824,50.62514673210195],"type":"Point"}
}