{
  "type": "Feature",
  "properties": {
    "iso:country":"GB",
    "wof:name":"BS9 4BG",
    "wof:placetype":"postalcode"
},
  "geometry": {"coordinates":[-2.61246054127758,51.49140606379895],"type":"Point"}
}