{
  "type": "Feature",
  "properties": {
    "iso:country":"GB",
    "wof:name":"B76 2UJ",
    "wof:placetype":"postalcode"
},
  "geometry": {"coordinates":[-1.80045720036452,52.5586359564859],"type":"Point"}
}