{
  "type": "Feature",
  "properties": {
    "iso:country":"GB",
    "wof:name":"DN8 4EY",
    "wof:placetype":"postalcode"
},
  "geometry": {"coordinates":[-0.96098374250142,53.62074531900124],"type":"Point"}
}