{
  "type": "Feature",
  "properties": {
    "date:inception_lower": "1980-01-01",
    "date:inception_upper": "1980-01-01",
    "iso:country": "GB",
    "wof:name": "LA10 5AW",
    "wof:placetype": "postalcode"
  },
  "geometry": {"coordinates":[-2.521529,54.322586],"type":"Point"}
}
