{
  "type": "Feature",
  "properties": {
    "date:inception_lower": "1980-01-01",
    "date:inception_upper": "1980-01-01",
    "iso:country": "GB",
    "wof:name": "GL7 2DR",
    "wof:placetype": "postalcode"
  },
  "geometry": {"coordinates":[-1.972925,51.722183],"type":"Point"}
}
