{
  "type": "Feature",
  "properties": {
    "iso:country": "GB",
    "wof:name": "GL7 2DR",
    "wof:placetype": "postalcode"
  },
  "geometry": {"coordinates":[-1.972925,51.722183],"type":"Point"}
}
