{
  "type": "Feature",
  "properties": {
    "iso:country":"GB",
    "wof:name":"G33 6JP",
    "wof:placetype":"postalcode"
},
  "geometry": {"coordinates":[-4.16263755981546,55.88583482573105],"type":"Point"}
}