{
  "type": "Feature",
  "properties": {
    "iso:country": "GB",
    "wof:name": "IV51 9PY",
    "wof:placetype": "postalcode"
  },
  "geometry": {"coordinates":[-6.19611,57.416948],"type":"Point"}
}
