{
  "type": "Feature",
  "properties": {
    "iso:country":"GB",
    "wof:name":"IV51 9PY",
    "wof:placetype":"postalcode"
},
  "geometry": {"coordinates":[-6.19611030217014,57.41694826251672],"type":"Point"}
}