{
  "type": "Feature",
  "properties": {
    "iso:country":"GB",
    "wof:name":"DL7 9LP",
    "wof:placetype":"postalcode"
},
  "geometry": {"coordinates":[-1.57796567922531,54.33213374881147],"type":"Point"}
}