{
  "type": "Feature",
  "properties": {
    "iso:country":"GB",
    "wof:name":"M30 9JH",
    "wof:placetype":"postalcode"
},
  "geometry": {"coordinates":[-2.34474216156475,53.49221299800902],"type":"Point"}
}