{
  "type": "Feature",
  "properties": {
    "iso:country": "GB",
    "wof:name": "PA31 8SE",
    "wof:placetype": "postalcode"
  },
  "geometry": {"coordinates":[-5.361572,56.027241],"type":"Point"}
}
