{
  "type": "Feature",
  "properties": {
    "date:inception_lower": "1980-01-01",
    "date:inception_upper": "1980-01-01",
    "iso:country": "GB",
    "wof:name": "PA31 8SE",
    "wof:placetype": "postalcode"
  },
  "geometry": {"coordinates":[-5.361572,56.027241],"type":"Point"}
}
