{
  "type": "Feature",
  "properties": {
    "iso:country": "GB",
    "wof:name": "WR10 3HS",
    "wof:placetype": "postalcode"
  },
  "geometry": {"coordinates":[-2.027124,52.06942],"type":"Point"}
}
