{
  "type": "Feature",
  "properties": {
    "iso:country": "GB",
    "wof:name": "GU34 5HY",
    "wof:placetype": "postalcode"
  },
  "geometry": {"coordinates":[-1.058313,51.106635],"type":"Point"}
}
