{
  "type": "Feature",
  "properties": {
    "iso:country":"GB",
    "wof:name":"GU34 5HY",
    "wof:placetype":"postalcode"
},
  "geometry": {"coordinates":[-1.05831297862409,51.10663496570303],"type":"Point"}
}