{
  "type": "Feature",
  "properties": {
    "iso:country":"GB",
    "wof:name":"RH19 4SS",
    "wof:placetype":"postalcode"
},
  "geometry": {"coordinates":[-0.01255815829507,51.12320444588424],"type":"Point"}
}