{
  "type": "Feature",
  "properties": {
    "iso:country": "GB",
    "wof:name": "ME15 9UA",
    "wof:placetype": "postalcode"
  },
  "geometry": {"coordinates":[0.526632,51.251739],"type":"Point"}
}
