{
  "type": "Feature",
  "properties": {
    "iso:country":"GB",
    "wof:name":"SW1H 9LQ",
    "wof:placetype":"postalcode"
},
  "geometry": {"coordinates":[-0.13252604139947,51.49957006826785],"type":"Point"}
}