{
  "type": "Feature",
  "properties": {
    "date:inception_lower": "1980-01-01",
    "date:inception_upper": "1980-01-01",
    "iso:country": "GB",
    "wof:name": "SW1H 9LQ",
    "wof:placetype": "postalcode"
  },
  "geometry": {"coordinates":[-0.132526,51.49957],"type":"Point"}
}
