{
  "type": "Feature",
  "properties": {
    "iso:country": "GB",
    "wof:name": "FY4 3EW",
    "wof:placetype": "postalcode"
  },
  "geometry": {"coordinates":[-3.036402,53.793999],"type":"Point"}
}
