{
  "type": "Feature",
  "properties": {
    "iso:country": "GB",
    "wof:name": "SG7 6EF",
    "wof:placetype": "postalcode"
  },
  "geometry": {"coordinates":[-0.18954,51.98871],"type":"Point"}
}
