{
  "type": "Feature",
  "properties": {
    "iso:country":"GB",
    "wof:name":"SG7 6EF",
    "wof:placetype":"postalcode"
},
  "geometry": {"coordinates":[-0.18956569513654,51.98873713078996],"type":"Point"}
}