{
  "type": "Feature",
  "properties": {
    "iso:country":"GB",
    "wof:name":"SW18 1GR",
    "wof:placetype":"postalcode"
},
  "geometry": {"coordinates":[-0.18431813051918,51.46230910098485],"type":"Point"}
}