{
  "type": "Feature",
  "properties": {
    "iso:country":"GB",
    "wof:name":"NG15 9AJ",
    "wof:placetype":"postalcode"
},
  "geometry": {"coordinates":[-1.12983669628213,53.06323123496494],"type":"Point"}
}