{
  "type": "Feature",
  "properties": {
    "iso:country":"GB",
    "wof:name":"WF5 0EF",
    "wof:placetype":"postalcode"
},
  "geometry": {"coordinates":[-1.56151469817736,53.67384992376485],"type":"Point"}
}