{
  "type": "Feature",
  "properties": {
    "iso:country":"GB",
    "wof:name":"NG4 2HQ",
    "wof:placetype":"postalcode"
},
  "geometry": {"coordinates":[-1.07383894815285,52.96262104219499],"type":"Point"}
}