{
  "type": "Feature",
  "properties": {
    "date:inception_lower": "1995-01-01",
    "date:inception_upper": "1995-01-01",
    "iso:country": "GB",
    "wof:name": "UB2 4UZ",
    "wof:placetype": "postalcode"
  },
  "geometry": {"coordinates":[-0.353464,51.506423],"type":"Point"}
}
