{
  "type": "Feature",
  "properties": {
    "iso:country":"GB",
    "wof:name":"IV4 7JG",
    "wof:placetype":"postalcode"
},
  "geometry": {"coordinates":[-4.49293728187981,57.43813519626651],"type":"Point"}
}