{
  "type": "Feature",
  "properties": {
    "iso:country": "GB",
    "wof:name": "TR14 7XN",
    "wof:placetype": "postalcode"
  },
  "geometry": {"coordinates":[-5.293891,50.210831],"type":"Point"}
}
