{
  "type": "Feature",
  "properties": {
    "date:inception_lower":"1995-01-01",
    "date:inception_upper":"1995-01-31",
    "iso:country":"GB",
    "wof:name":"TR14 7XN",
    "wof:placetype":"postalcode"
},
  "geometry": {"coordinates":[-5.293891,50.210831],"type":"Point"}
}