{
  "type": "Feature",
  "properties": {
    "iso:country":"GB",
    "wof:name":"TR14 7XN",
    "wof:placetype":"postalcode"
},
  "geometry": {"coordinates":[-5.29389135811609,50.21083125492066],"type":"Point"}
}