{
  "type": "Feature",
  "properties": {
    "date:inception_lower":"1980-01-01",
    "date:inception_upper":"1980-01-31",
    "iso:country":"GB",
    "wof:name":"BL6 5TG",
    "wof:placetype":"postalcode"
},
  "geometry": {"coordinates":[-2.579218,53.590027],"type":"Point"}
}