{
  "type": "Feature",
  "properties": {
    "iso:country":"GB",
    "wof:name":"BL6 5TG",
    "wof:placetype":"postalcode"
},
  "geometry": {"coordinates":[-2.57921787232532,53.59002669615771],"type":"Point"}
}