{
  "type": "Feature",
  "properties": {
    "iso:country":"GB",
    "wof:name":"B98 8LE",
    "wof:placetype":"postalcode"
},
  "geometry": {"coordinates":[-1.92416436404811,52.30335466909051],"type":"Point"}
}