{
  "type": "Feature",
  "properties": {
    "iso:country": "GB",
    "wof:name": "DN39 6SZ",
    "wof:placetype": "postalcode"
  },
  "geometry": {"coordinates":[-0.330963,53.616441],"type":"Point"}
}
