{
  "type": "Feature",
  "properties": {
    "iso:country":"GB",
    "wof:name":"RH15 8NN",
    "wof:placetype":"postalcode"
},
  "geometry": {"coordinates":[-0.14011586025627,50.9610790152301],"type":"Point"}
}