{
  "type": "Feature",
  "properties": {
    "date:inception_lower": "1980-01-01",
    "date:inception_upper": "1980-01-01",
    "iso:country": "GB",
    "wof:name": "RH15 8NN",
    "wof:placetype": "postalcode"
  },
  "geometry": {"coordinates":[-0.140116,50.961079],"type":"Point"}
}
