{
  "type": "Feature",
  "properties": {
    "iso:country":"GB",
    "wof:name":"WS12 1TA",
    "wof:placetype":"postalcode"
},
  "geometry": {"coordinates":[-1.9920084047421,52.7134625291888],"type":"Point"}
}