{
  "type": "Feature",
  "properties": {
    "date:inception_lower": "2011-05-01",
    "date:inception_upper": "2011-05-01",
    "iso:country": "GB",
    "wof:name": "NN17 5ER",
    "wof:placetype": "postalcode"
  },
  "geometry": {"coordinates":[-0.636824,52.506212],"type":"Point"}
}
