{
  "type": "Feature",
  "properties": {
    "iso:country": "GB",
    "wof:name": "NN17 5ER",
    "wof:placetype": "postalcode"
  },
  "geometry": {"coordinates":[-0.637547,52.506184],"type":"Point"}
}
