{
  "type": "Feature",
  "properties": {
    "iso:country":"GB",
    "wof:name":"NN17 5ER",
    "wof:placetype":"postalcode"
},
  "geometry": {"coordinates":[-0.63756271009523,52.506167301213],"type":"Point"}
}