{
  "type": "Feature",
  "properties": {
    "date:inception_lower":"2011-05-01",
    "date:inception_upper":"2011-05-31",
    "iso:country":"GB",
    "wof:name":"NN17 5ER",
    "wof:placetype":"postalcode"
},
  "geometry": {"coordinates":[-0.637547,52.506184],"type":"Point"}
}