{
  "type": "Feature",
  "properties": {
    "iso:country": "GB",
    "wof:name": "WF17 6FA",
    "wof:placetype": "postalcode"
  },
  "geometry": {"coordinates":[-1.624484,53.706805],"type":"Point"}
}
