{
  "type": "Feature",
  "properties": {
    "date:inception_lower": "2018-12-01",
    "date:inception_upper": "2018-12-01",
    "iso:country": "GB",
    "wof:name": "WF17 6FA",
    "wof:placetype": "postalcode"
  },
  "geometry": {"coordinates":[-1.624484,53.706805],"type":"Point"}
}
