{
  "type": "Feature",
  "properties": {
    "date:inception_lower":"1980-01-01",
    "date:inception_upper":"1980-01-31",
    "iso:country":"GB",
    "wof:name":"SR2 0DS",
    "wof:placetype":"postalcode"
},
  "geometry": {"coordinates":[-1.373804,54.876214],"type":"Point"}
}