{
  "type": "Feature",
  "properties": {
    "iso:country":"GB",
    "wof:name":"YO11 1NF",
    "wof:placetype":"postalcode"
},
  "geometry": {"coordinates":[-0.39725166149674,54.28303990927959],"type":"Point"}
}