{
  "type": "Feature",
  "properties": {
    "date:inception_lower": "2011-08-01",
    "date:inception_upper": "2011-08-01",
    "iso:country": "GB",
    "wof:name": "NE6 4XF",
    "wof:placetype": "postalcode"
  },
  "geometry": {"coordinates":[-1.553589,54.983163],"type":"Point"}
}
