{
  "type": "Feature",
  "properties": {
    "date:inception_lower": "1980-01-01",
    "date:inception_upper": "1980-01-01",
    "iso:country": "GB",
    "wof:name": "S12 4QF",
    "wof:placetype": "postalcode"
  },
  "geometry": {"coordinates":[-1.392223,53.34565],"type":"Point"}
}
