{
  "type": "Feature",
  "properties": {
    "iso:country":"GB",
    "wof:name":"S12 4QF",
    "wof:placetype":"postalcode"
},
  "geometry": {"coordinates":[-1.39225345558043,53.34563156210629],"type":"Point"}
}