{
  "type": "Feature",
  "properties": {
    "iso:country": "GB",
    "wof:name": "BS11 9HP",
    "wof:placetype": "postalcode"
  },
  "geometry": {"coordinates":[-2.701016,51.506248],"type":"Point"}
}
