{
  "type": "Feature",
  "properties": {
    "date:inception_lower": "1987-04-01",
    "date:inception_upper": "1987-04-01",
    "iso:country": "GB",
    "wof:name": "BS11 9HP",
    "wof:placetype": "postalcode"
  },
  "geometry": {"coordinates":[-2.701016,51.506248],"type":"Point"}
}
