{
  "type": "Feature",
  "properties": {
    "iso:country":"GB",
    "wof:name":"BD21 3HB",
    "wof:placetype":"postalcode"
},
  "geometry": {"coordinates":[-1.90472532338307,53.872907096654],"type":"Point"}
}