{
  "type": "Feature",
  "properties": {
    "date:inception_lower": "2019-09-01",
    "date:inception_upper": "2019-09-01",
    "iso:country": "GB",
    "wof:name": "AB45 3AE",
    "wof:placetype": "postalcode"
  },
  "geometry": {"coordinates":[-2.33526,57.666403],"type":"Point"}
}
