{
  "type": "Feature",
  "properties": {
    "iso:country": "GB",
    "wof:name": "MK18 5PA",
    "wof:placetype": "postalcode"
  },
  "geometry": {"coordinates":[-0.926494,52.038191],"type":"Point"}
}
