{
  "type": "Feature",
  "properties": {
    "iso:country":"GB",
    "wof:name":"MK18 5PA",
    "wof:placetype":"postalcode"
},
  "geometry": {"coordinates":[-0.92649417060842,52.03819144182378],"type":"Point"}
}