{
  "type": "Feature",
  "properties": {
    "date:inception_lower": "1980-01-01",
    "date:inception_upper": "1980-01-01",
    "iso:country": "GB",
    "wof:name": "CA2 5TN",
    "wof:placetype": "postalcode"
  },
  "geometry": {"coordinates":[-2.946251,54.893611],"type":"Point"}
}
