{
  "type": "Feature",
  "properties": {
    "iso:country":"GB",
    "wof:name":"CA2 5TN",
    "wof:placetype":"postalcode"
},
  "geometry": {"coordinates":[-2.94626319755871,54.89359567797218],"type":"Point"}
}