{
  "type": "Feature",
  "properties": {
    "iso:country": "GB",
    "wof:name": "CA2 5TN",
    "wof:placetype": "postalcode"
  },
  "geometry": {"coordinates":[-2.946251,54.893611],"type":"Point"}
}
