{
  "type": "Feature",
  "properties": {
    "date:inception_lower": "1980-01-01",
    "date:inception_upper": "1980-01-01",
    "iso:country": "GB",
    "wof:name": "IP33 2RN",
    "wof:placetype": "postalcode"
  },
  "geometry": {"coordinates":[0.726449,52.235824],"type":"Point"}
}
