{
  "type": "Feature",
  "properties": {
    "iso:country":"GB",
    "wof:name":"CF14 6NX",
    "wof:placetype":"postalcode"
},
  "geometry": {"coordinates":[-3.20596853257002,51.52510900400074],"type":"Point"}
}