{
  "type": "Feature",
  "properties": {
    "iso:country": "GB",
    "wof:name": "CF14 6NX",
    "wof:placetype": "postalcode"
  },
  "geometry": {"coordinates":[-3.205968,51.525109],"type":"Point"}
}
