{
  "type": "Feature",
  "properties": {
    "date:inception_lower": "2013-07-01",
    "date:inception_upper": "2013-07-01",
    "iso:country": "GB",
    "wof:name": "HU15 1ZQ",
    "wof:placetype": "postalcode"
  },
  "geometry": {"coordinates":[-0.556612,53.728809],"type":"Point"}
}
