{
  "type": "Feature",
  "properties": {
    "iso:country":"GB",
    "wof:name":"HU15 1ZQ",
    "wof:placetype":"postalcode"
},
  "geometry": {"coordinates":[-0.5575039759003,53.72871878322549],"type":"Point"}
}