{
  "type": "Feature",
  "properties": {
    "iso:country": "GB",
    "wof:name": "SY19 7BD",
    "wof:placetype": "postalcode"
  },
  "geometry": {"coordinates":[-3.643426,52.587884],"type":"Point"}
}
