{
  "type": "Feature",
  "properties": {
    "date:inception_lower": "1980-01-01",
    "date:inception_upper": "1980-01-01",
    "iso:country": "GB",
    "wof:name": "SY19 7BD",
    "wof:placetype": "postalcode"
  },
  "geometry": {"coordinates":[-3.643635,52.587935],"type":"Point"}
}
