{
  "type": "Feature",
  "properties": {
    "iso:country": "GB",
    "wof:name": "L9 1DZ",
    "wof:placetype": "postalcode"
  },
  "geometry": {"coordinates":[-2.971518,53.447115],"type":"Point"}
}
