{
  "type": "Feature",
  "properties": {
    "iso:country": "GB",
    "wof:name": "SY14 7ES",
    "wof:placetype": "postalcode"
  },
  "geometry": {"coordinates":[-2.811216,53.026122],"type":"Point"}
}
