{
  "type": "Feature",
  "properties": {
    "iso:country":"GB",
    "wof:name":"BN2 3AE",
    "wof:placetype":"postalcode"
},
  "geometry": {"coordinates":[-0.12402088500122,50.83270191526269],"type":"Point"}
}