{
  "type": "Feature",
  "properties": {
    "date:inception_lower": "1999-12-01",
    "date:inception_upper": "1999-12-01",
    "iso:country": "GB",
    "wof:name": "SA4 4PS",
    "wof:placetype": "postalcode"
  },
  "geometry": {"coordinates":[-4.033576,51.672244],"type":"Point"}
}
