{
  "type": "Feature",
  "properties": {
    "iso:country":"GB",
    "wof:name":"HA6 2BY",
    "wof:placetype":"postalcode"
},
  "geometry": {"coordinates":[-0.43024082153478,51.61525522458918],"type":"Point"}
}