{
  "type": "Feature",
  "properties": {
    "date:inception_lower":"1994-12-01",
    "date:inception_upper":"1994-12-31",
    "iso:country":"GB",
    "wof:name":"CA13 9AA",
    "wof:placetype":"postalcode"
},
  "geometry": {"coordinates":[-3.355956,54.660671],"type":"Point"}
}