{
  "type": "Feature",
  "properties": {
    "iso:country": "GB",
    "wof:name": "CA13 9AA",
    "wof:placetype": "postalcode"
  },
  "geometry": {"coordinates":[-3.355956,54.660671],"type":"Point"}
}
