{
  "type": "Feature",
  "properties": {
    "iso:country": "GB",
    "wof:name": "BD23 5QQ",
    "wof:placetype": "postalcode"
  },
  "geometry": {"coordinates":[-2.108764,54.145688],"type":"Point"}
}
