{
  "type": "Feature",
  "properties": {
    "iso:country":"GB",
    "wof:name":"BD23 5QQ",
    "wof:placetype":"postalcode"
},
  "geometry": {"coordinates":[-2.10876377912847,54.14568808544171],"type":"Point"}
}