{
  "type": "Feature",
  "properties": {
    "iso:country":"GB",
    "wof:name":"BN5 9HF",
    "wof:placetype":"postalcode"
},
  "geometry": {"coordinates":[-0.27405770116784,50.93808037910917],"type":"Point"}
}