{
  "type": "Feature",
  "properties": {
    "iso:country": "GB",
    "wof:name": "BN5 9HF",
    "wof:placetype": "postalcode"
  },
  "geometry": {"coordinates":[-0.274058,50.93808],"type":"Point"}
}
