{
  "type": "Feature",
  "properties": {
    "iso:country":"GB",
    "wof:name":"SN2 2EU",
    "wof:placetype":"postalcode"
},
  "geometry": {"coordinates":[-1.81167019652698,51.58219445050292],"type":"Point"}
}