{
  "type": "Feature",
  "properties": {
    "date:inception_lower":"2011-07-01",
    "date:inception_upper":"2011-07-31",
    "iso:country":"GB",
    "wof:name":"SN2 2EU",
    "wof:placetype":"postalcode"
},
  "geometry": {"coordinates":[-1.81167,51.582194],"type":"Point"}
}