{
  "type": "Feature",
  "properties": {
    "date:inception_lower":"1994-05-01",
    "date:inception_upper":"1994-05-31",
    "iso:country":"GB",
    "wof:name":"SW6 7NR",
    "wof:placetype":"postalcode"
},
  "geometry": {"coordinates":[-0.214265,51.482508],"type":"Point"}
}