{
  "type": "Feature",
  "properties": {
    "iso:country":"GB",
    "wof:name":"SW6 7NR",
    "wof:placetype":"postalcode"
},
  "geometry": {"coordinates":[-0.21426477276681,51.48250753880392],"type":"Point"}
}