{
  "type": "Feature",
  "properties": {
    "iso:country": "GB",
    "wof:name": "DE7 4GA",
    "wof:placetype": "postalcode"
  },
  "geometry": {"coordinates":[-1.330229,52.956521],"type":"Point"}
}
