{
  "type": "Feature",
  "properties": {
    "iso:country":"GB",
    "wof:name":"DE7 4GA",
    "wof:placetype":"postalcode"
},
  "geometry": {"coordinates":[-1.33022889390545,52.95652085757455],"type":"Point"}
}