{
  "type": "Feature",
  "properties": {
    "date:inception_lower":"1985-10-01",
    "date:inception_upper":"1985-10-31",
    "iso:country":"GB",
    "wof:name":"DE7 4GA",
    "wof:placetype":"postalcode"
},
  "geometry": {"coordinates":[-1.330229,52.956521],"type":"Point"}
}