{
  "type": "Feature",
  "properties": {
    "iso:country": "GB",
    "wof:name": "G2 3DH",
    "wof:placetype": "postalcode"
  },
  "geometry": {"coordinates":[-4.258004,55.865149],"type":"Point"}
}
