{
  "type": "Feature",
  "properties": {
    "iso:country":"GB",
    "wof:name":"LL20 7LB",
    "wof:placetype":"postalcode"
},
  "geometry": {"coordinates":[-3.24814538322409,52.89192358131452],"type":"Point"}
}