{
  "type": "Feature",
  "properties": {
    "date:inception_lower": "1980-01-01",
    "date:inception_upper": "1980-01-01",
    "iso:country": "GB",
    "wof:name": "LL20 7LB",
    "wof:placetype": "postalcode"
  },
  "geometry": {"coordinates":[-3.248145,52.891924],"type":"Point"}
}
