{
  "type": "Feature",
  "properties": {
    "iso:country": "GB",
    "wof:name": "LL20 7LB",
    "wof:placetype": "postalcode"
  },
  "geometry": {"coordinates":[-3.248145,52.891924],"type":"Point"}
}
