{
  "type": "Feature",
  "properties": {
    "iso:country":"GB",
    "wof:name":"LL53 7DS",
    "wof:placetype":"postalcode"
},
  "geometry": {"coordinates":[-4.50524348479948,52.82349557927745],"type":"Point"}
}