{
  "type": "Feature",
  "properties": {
    "iso:country":"GB",
    "wof:name":"RM11 3DH",
    "wof:placetype":"postalcode"
},
  "geometry": {"coordinates":[0.24197166894168,51.57707408590099],"type":"Point"}
}