{
  "type": "Feature",
  "properties": {
    "iso:country":"GB",
    "wof:name":"CF82 8LA",
    "wof:placetype":"postalcode"
},
  "geometry": {"coordinates":[-3.2383620668954,51.66480965343708],"type":"Point"}
}