{
  "type": "Feature",
  "properties": {
    "iso:country":"GB",
    "wof:name":"WC2H 8AJ",
    "wof:placetype":"postalcode"
},
  "geometry": {"coordinates":[-0.12838738791857,51.51583452287095],"type":"Point"}
}