{
  "type": "Feature",
  "properties": {
    "date:inception_lower":"2010-05-01",
    "date:inception_upper":"2010-05-31",
    "iso:country":"GB",
    "wof:name":"WC2H 8AJ",
    "wof:placetype":"postalcode"
},
  "geometry": {"coordinates":[-0.128387,51.515835],"type":"Point"}
}