{
  "type": "Feature",
  "properties": {
    "iso:country": "GB",
    "wof:name": "WC2H 8AJ",
    "wof:placetype": "postalcode"
  },
  "geometry": {"coordinates":[-0.128387,51.515835],"type":"Point"}
}
