{
  "type": "Feature",
  "properties": {
    "iso:country":"GB",
    "wof:name":"GL6 8FX",
    "wof:placetype":"postalcode"
},
  "geometry": {"coordinates":[-2.14519645104025,51.72206869358737],"type":"Point"}
}