{
  "type": "Feature",
  "properties": {
    "date:inception_lower": "2015-09-01",
    "date:inception_upper": "2015-09-01",
    "iso:country": "GB",
    "wof:name": "GL6 8FX",
    "wof:placetype": "postalcode"
  },
  "geometry": {"coordinates":[-2.145196,51.722069],"type":"Point"}
}
