{
  "type": "Feature",
  "properties": {
    "iso:country":"GB",
    "wof:name":"CM77 7UB",
    "wof:placetype":"postalcode"
},
  "geometry": {"coordinates":[0.52829944577994,51.85989728543985],"type":"Point"}
}