{
  "type": "Feature",
  "properties": {
    "iso:country": "GB",
    "wof:name": "CM77 7UB",
    "wof:placetype": "postalcode"
  },
  "geometry": {"coordinates":[0.528299,51.859897],"type":"Point"}
}
