{
  "type": "Feature",
  "properties": {
    "iso:country":"GB",
    "wof:name":"NE47 9UX",
    "wof:placetype":"postalcode"
},
  "geometry": {"coordinates":[-2.24134604028747,54.84097609204444],"type":"Point"}
}