{
  "type": "Feature",
  "properties": {
    "iso:country": "GB",
    "wof:name": "BN6 9QL",
    "wof:placetype": "postalcode"
  },
  "geometry": {"coordinates":[-0.167763,50.929059],"type":"Point"}
}
