{
  "type": "Feature",
  "properties": {
    "iso:country": "GB",
    "wof:name": "NG12 5AS",
    "wof:placetype": "postalcode"
  },
  "geometry": {"coordinates":[-1.090151,52.869192],"type":"Point"}
}
