{
  "type": "Feature",
  "properties": {
    "iso:country":"GB",
    "wof:name":"IP28 8JG",
    "wof:placetype":"postalcode"
},
  "geometry": {"coordinates":[0.44753513926036,52.32000171165682],"type":"Point"}
}