{
  "type": "Feature",
  "properties": {
    "iso:country":"GB",
    "wof:name":"M9 8GG",
    "wof:placetype":"postalcode"
},
  "geometry": {"coordinates":[-2.23299816997677,53.52843693827176],"type":"Point"}
}