{
  "type": "Feature",
  "properties": {
    "iso:country": "GB",
    "wof:name": "M9 8GG",
    "wof:placetype": "postalcode"
  },
  "geometry": {"coordinates":[-2.232998,53.528437],"type":"Point"}
}
