{
  "type": "Feature",
  "properties": {
    "date:inception_lower": "1990-08-01",
    "date:inception_upper": "1990-08-01",
    "iso:country": "GB",
    "wof:name": "AB45 3RL",
    "wof:placetype": "postalcode"
  },
  "geometry": {"coordinates":[-2.447608,57.660771],"type":"Point"}
}
