{
  "type": "Feature",
  "properties": {
    "iso:country":"GB",
    "wof:name":"AB45 3RL",
    "wof:placetype":"postalcode"
},
  "geometry": {"coordinates":[-2.44760810666152,57.66077133179721],"type":"Point"}
}