{
  "type": "Feature",
  "properties": {
    "iso:country":"GB",
    "wof:name":"PR3 3XE",
    "wof:placetype":"postalcode"
},
  "geometry": {"coordinates":[-2.56439827777675,53.82091516509134],"type":"Point"}
}