{
  "type": "Feature",
  "properties": {
    "iso:country": "GB",
    "wof:name": "PR3 3XE",
    "wof:placetype": "postalcode"
  },
  "geometry": {"coordinates":[-2.564398,53.820974],"type":"Point"}
}
