{
  "type": "Feature",
  "properties": {
    "date:inception_lower":"2004-05-01",
    "date:inception_upper":"2004-05-31",
    "iso:country":"GB",
    "wof:name":"EH5 2GA",
    "wof:placetype":"postalcode"
},
  "geometry": {"coordinates":[-3.228623,55.971754],"type":"Point"}
}