{
  "type": "Feature",
  "properties": {
    "date:inception_lower":"1994-05-01",
    "date:inception_upper":"1994-05-31",
    "iso:country":"GB",
    "wof:name":"M23 2UX",
    "wof:placetype":"postalcode"
},
  "geometry": {"coordinates":[-2.291675,53.380573],"type":"Point"}
}