{
  "type": "Feature",
  "properties": {
    "iso:country":"GB",
    "wof:name":"M23 2UX",
    "wof:placetype":"postalcode"
},
  "geometry": {"coordinates":[-2.29167471560105,53.38057296068148],"type":"Point"}
}