{
  "type": "Feature",
  "properties": {
    "iso:country":"GB",
    "wof:name":"SW2 3JX",
    "wof:placetype":"postalcode"
},
  "geometry": {"coordinates":[-0.1125966602595,51.4389466467446],"type":"Point"}
}