{
  "type": "Feature",
  "properties": {
    "iso:country": "GB",
    "wof:name": "SW2 3JX",
    "wof:placetype": "postalcode"
  },
  "geometry": {"coordinates":[-0.112597,51.438947],"type":"Point"}
}
