{
  "type": "Feature",
  "properties": {
    "iso:country": "GB",
    "wof:name": "PL7 4JA",
    "wof:placetype": "postalcode"
  },
  "geometry": {"coordinates":[-4.054991,50.396698],"type":"Point"}
}
