{
  "type": "Feature",
  "properties": {
    "iso:country":"GB",
    "wof:name":"PL7 4JA",
    "wof:placetype":"postalcode"
},
  "geometry": {"coordinates":[-4.05499056763127,50.3966984795787],"type":"Point"}
}