{
  "type": "Feature",
  "properties": {
    "date:inception_lower": "1980-01-01",
    "date:inception_upper": "1980-01-01",
    "iso:country": "GB",
    "wof:name": "PL7 4JA",
    "wof:placetype": "postalcode"
  },
  "geometry": {"coordinates":[-4.054991,50.396698],"type":"Point"}
}
