{
  "type": "Feature",
  "properties": {
    "iso:country":"GB",
    "wof:name":"SS16 4XD",
    "wof:placetype":"postalcode"
},
  "geometry": {"coordinates":[0.49364035060222,51.5595839701399],"type":"Point"}
}