{
  "type": "Feature",
  "properties": {
    "iso:country": "GB",
    "wof:name": "SS16 4XD",
    "wof:placetype": "postalcode"
  },
  "geometry": {"coordinates":[0.49364,51.559584],"type":"Point"}
}
