{
  "type": "Feature",
  "properties": {
    "iso:country": "GB",
    "wof:name": "BL5 2BD",
    "wof:placetype": "postalcode"
  },
  "geometry": {"coordinates":[-2.52912,53.54874],"type":"Point"}
}
