{
  "type": "Feature",
  "properties": {
    "iso:country": "GB",
    "wof:name": "KA9 1WH",
    "wof:placetype": "postalcode"
  },
  "geometry": {"coordinates":[-4.611207,55.50161],"type":"Point"}
}
