{
  "type": "Feature",
  "properties": {
    "date:inception_lower": "1997-06-01",
    "date:inception_upper": "1997-06-01",
    "iso:country": "GB",
    "wof:name": "IP11 0SF",
    "wof:placetype": "postalcode"
  },
  "geometry": {"coordinates":[1.305098,51.993264],"type":"Point"}
}
