{
  "type": "Feature",
  "properties": {
    "iso:country": "GB",
    "wof:name": "L19 0PF",
    "wof:placetype": "postalcode"
  },
  "geometry": {"coordinates":[-2.915155,53.356494],"type":"Point"}
}
