{
  "type": "Feature",
  "properties": {
    "date:inception_lower": "1980-01-01",
    "date:inception_upper": "1980-01-01",
    "iso:country": "GB",
    "wof:name": "L19 0PF",
    "wof:placetype": "postalcode"
  },
  "geometry": {"coordinates":[-2.915155,53.356494],"type":"Point"}
}
