{
  "type": "Feature",
  "properties": {
    "iso:country": "GB",
    "wof:name": "AB24 2XX",
    "wof:placetype": "postalcode"
  },
  "geometry": {"coordinates":[-2.119141,57.174056],"type":"Point"}
}
