{
  "type": "Feature",
  "properties": {
    "iso:country":"GB",
    "wof:name":"ST7 2PD",
    "wof:placetype":"postalcode"
},
  "geometry": {"coordinates":[-2.30786349570268,53.09449839490881],"type":"Point"}
}