{
  "type": "Feature",
  "properties": {
    "iso:country": "GB",
    "wof:name": "ST7 2PD",
    "wof:placetype": "postalcode"
  },
  "geometry": {"coordinates":[-2.307863,53.094498],"type":"Point"}
}
