{
  "type": "Feature",
  "properties": {
    "iso:country":"GB",
    "wof:name":"CO1 2NH",
    "wof:placetype":"postalcode"
},
  "geometry": {"coordinates":[0.92445851593947,51.88425721523315],"type":"Point"}
}