{
  "type": "Feature",
  "properties": {
    "iso:country": "GB",
    "wof:name": "CF23 9AD",
    "wof:placetype": "postalcode"
  },
  "geometry": {"coordinates":[-3.142806,51.497579],"type":"Point"}
}
