{
  "type": "Feature",
  "properties": {
    "iso:country":"GB",
    "wof:name":"TS15 9PJ",
    "wof:placetype":"postalcode"
},
  "geometry": {"coordinates":[-1.39532822361467,54.48351946192023],"type":"Point"}
}