{
  "type": "Feature",
  "properties": {
    "iso:country": "GB",
    "wof:name": "TS15 9PJ",
    "wof:placetype": "postalcode"
  },
  "geometry": {"coordinates":[-1.395328,54.483519],"type":"Point"}
}
