{
  "type": "Feature",
  "properties": {
    "iso:country":"GB",
    "wof:name":"PL14 4HT",
    "wof:placetype":"postalcode"
},
  "geometry": {"coordinates":[-4.47169546903279,50.4529521863475],"type":"Point"}
}