{
  "type": "Feature",
  "properties": {
    "iso:country":"GB",
    "wof:name":"EH22 4RR",
    "wof:placetype":"postalcode"
},
  "geometry": {"coordinates":[-3.066532624038,55.87148634259547],"type":"Point"}
}