{
  "type": "Feature",
  "properties": {
    "iso:country":"GB",
    "wof:name":"SG14 3GR",
    "wof:placetype":"postalcode"
},
  "geometry": {"coordinates":[-0.07926697793564,51.80444208195298],"type":"Point"}
}