{
  "type": "Feature",
  "properties": {
    "iso:country": "GB",
    "wof:name": "SG14 3GR",
    "wof:placetype": "postalcode"
  },
  "geometry": {"coordinates":[-0.079267,51.804442],"type":"Point"}
}
