{
  "type": "Feature",
  "properties": {
    "iso:country": "GB",
    "wof:name": "CF37 3AL",
    "wof:placetype": "postalcode"
  },
  "geometry": {"coordinates":[-3.34546,51.621939],"type":"Point"}
}
