{
  "type": "Feature",
  "properties": {
    "iso:country":"GB",
    "wof:name":"CF37 3AL",
    "wof:placetype":"postalcode"
},
  "geometry": {"coordinates":[-3.3454352118566,51.62194551514099],"type":"Point"}
}