{
  "type": "Feature",
  "properties": {
    "iso:country":"GB",
    "wof:name":"WF15 8AQ",
    "wof:placetype":"postalcode"
},
  "geometry": {"coordinates":[-1.72204412568518,53.70385578205644],"type":"Point"}
}