{
  "type": "Feature",
  "properties": {
    "iso:country": "GB",
    "wof:name": "WF15 8AQ",
    "wof:placetype": "postalcode"
  },
  "geometry": {"coordinates":[-1.722044,53.703856],"type":"Point"}
}
