{
  "type": "Feature",
  "properties": {
    "iso:country": "GB",
    "wof:name": "IP4 3LS",
    "wof:placetype": "postalcode"
  },
  "geometry": {"coordinates":[1.197771,52.067295],"type":"Point"}
}
