{
  "type": "Feature",
  "properties": {
    "date:inception_lower": "1980-01-01",
    "date:inception_upper": "1980-01-01",
    "iso:country": "GB",
    "wof:name": "DN16 2SQ",
    "wof:placetype": "postalcode"
  },
  "geometry": {"coordinates":[-0.649905,53.566946],"type":"Point"}
}
