{
  "type": "Feature",
  "properties": {
    "iso:country": "GB",
    "wof:name": "DN16 2SQ",
    "wof:placetype": "postalcode"
  },
  "geometry": {"coordinates":[-0.649905,53.566946],"type":"Point"}
}
