{
  "type": "Feature",
  "properties": {
    "iso:country": "GB",
    "wof:name": "NN12 7UJ",
    "wof:placetype": "postalcode"
  },
  "geometry": {"coordinates":[-0.890513,52.095868],"type":"Point"}
}
