{
  "type": "Feature",
  "properties": {
    "date:inception_lower": "1980-01-01",
    "date:inception_upper": "1980-01-01",
    "iso:country": "GB",
    "wof:name": "NN12 7UJ",
    "wof:placetype": "postalcode"
  },
  "geometry": {"coordinates":[-0.890513,52.095868],"type":"Point"}
}
