{
  "type": "Feature",
  "properties": {
    "iso:country":"GB",
    "wof:name":"NN12 7UJ",
    "wof:placetype":"postalcode"
},
  "geometry": {"coordinates":[-0.89051335177528,52.09586814380515],"type":"Point"}
}