{
  "type": "Feature",
  "properties": {
    "iso:country":"GB",
    "wof:name":"SW2 1LP",
    "wof:placetype":"postalcode"
},
  "geometry": {"coordinates":[-0.11595871989815,51.45689605754509],"type":"Point"}
}