{
  "type": "Feature",
  "properties": {
    "iso:country":"GB",
    "wof:name":"SG6 3QD",
    "wof:placetype":"postalcode"
},
  "geometry": {"coordinates":[-0.23842201384993,51.96811367082287],"type":"Point"}
}