{
  "type": "Feature",
  "properties": {
    "iso:country": "GB",
    "wof:name": "CH45 1NA",
    "wof:placetype": "postalcode"
  },
  "geometry": {"coordinates":[-3.039252,53.433214],"type":"Point"}
}
