{
  "type": "Feature",
  "properties": {
    "iso:country":"GB",
    "wof:name":"SE12 8TL",
    "wof:placetype":"postalcode"
},
  "geometry": {"coordinates":[0.01506226835545,51.45467217060747],"type":"Point"}
}