{
  "type": "Feature",
  "properties": {
    "date:inception_lower": "2022-12-01",
    "date:inception_upper": "2022-12-01",
    "iso:country": "GB",
    "wof:name": "CM9 6NA",
    "wof:placetype": "postalcode"
  },
  "geometry": {"coordinates":[0.666369,51.715893],"type":"Point"}
}
