{
  "type": "Feature",
  "properties": {
    "iso:country":"GB",
    "wof:name":"RH17 6TU",
    "wof:placetype":"postalcode"
},
  "geometry": {"coordinates":[-0.07900721418238,51.04672203993746],"type":"Point"}
}