{
  "type": "Feature",
  "properties": {
    "iso:country": "GB",
    "wof:name": "RH17 6TU",
    "wof:placetype": "postalcode"
  },
  "geometry": {"coordinates":[-0.079007,51.046722],"type":"Point"}
}
