{
  "type": "Feature",
  "properties": {
    "iso:country":"GB",
    "wof:name":"TS12 3HX",
    "wof:placetype":"postalcode"
},
  "geometry": {"coordinates":[-0.94911522807009,54.52199562984502],"type":"Point"}
}