{
  "type": "Feature",
  "properties": {
    "iso:country":"GB",
    "wof:name":"NG20 0LB",
    "wof:placetype":"postalcode"
},
  "geometry": {"coordinates":[-1.15053835119169,53.2002419520859],"type":"Point"}
}