{
  "type": "Feature",
  "properties": {
    "iso:country": "GB",
    "wof:name": "NG20 0LB",
    "wof:placetype": "postalcode"
  },
  "geometry": {"coordinates":[-1.150538,53.200242],"type":"Point"}
}
