{
  "type": "Feature",
  "properties": {
    "iso:country":"GB",
    "wof:name":"RM8 1NH",
    "wof:placetype":"postalcode"
},
  "geometry": {"coordinates":[0.14675820735186,51.56636380903169],"type":"Point"}
}