{
  "type": "Feature",
  "properties": {
    "date:inception_lower": "1988-03-01",
    "date:inception_upper": "1988-03-01",
    "iso:country": "GB",
    "wof:name": "DN3 3DQ",
    "wof:placetype": "postalcode"
  },
  "geometry": {"coordinates":[-1.0588,53.530373],"type":"Point"}
}
