{
  "type": "Feature",
  "properties": {
    "iso:country":"GB",
    "wof:name":"DN3 3DQ",
    "wof:placetype":"postalcode"
},
  "geometry": {"coordinates":[-1.05880018448171,53.53037344580446],"type":"Point"}
}