{
  "type": "Feature",
  "properties": {
    "iso:country":"GB",
    "wof:name":"NE37 2AL",
    "wof:placetype":"postalcode"
},
  "geometry": {"coordinates":[-1.52102095909502,54.91255976716369],"type":"Point"}
}