{
  "type": "Feature",
  "properties": {
    "iso:country":"GB",
    "wof:name":"PE21 7TS",
    "wof:placetype":"postalcode"
},
  "geometry": {"coordinates":[-0.05346644917374,52.97541047730392],"type":"Point"}
}