{
  "type": "Feature",
  "properties": {
    "iso:country": "GB",
    "wof:name": "PE21 7TS",
    "wof:placetype": "postalcode"
  },
  "geometry": {"coordinates":[-0.053466,52.97541],"type":"Point"}
}
