{
  "type": "Feature",
  "properties": {
    "iso:country": "GB",
    "wof:name": "BL4 0EG",
    "wof:placetype": "postalcode"
  },
  "geometry": {"coordinates":[-2.419112,53.552018],"type":"Point"}
}
