{
  "type": "Feature",
  "properties": {
    "iso:country":"GB",
    "wof:name":"LS25 6HS",
    "wof:placetype":"postalcode"
},
  "geometry": {"coordinates":[-1.19375207755356,53.79825240673388],"type":"Point"}
}