{
  "type": "Feature",
  "properties": {
    "iso:country":"GB",
    "wof:name":"PE7 2HS",
    "wof:placetype":"postalcode"
},
  "geometry": {"coordinates":[-0.02264990893335,52.5291205442872],"type":"Point"}
}