{
  "type": "Feature",
  "properties": {
    "date:inception_lower": "2009-10-01",
    "date:inception_upper": "2009-10-01",
    "iso:country": "GB",
    "wof:name": "G33 5DJ",
    "wof:placetype": "postalcode"
  },
  "geometry": {"coordinates":[-4.14216,55.87522],"type":"Point"}
}
