{
  "type": "Feature",
  "properties": {
    "iso:country": "GB",
    "wof:name": "G33 5DJ",
    "wof:placetype": "postalcode"
  },
  "geometry": {"coordinates":[-4.14216,55.87522],"type":"Point"}
}
