{
  "type": "Feature",
  "properties": {
    "iso:country":"GB",
    "wof:name":"G33 5DJ",
    "wof:placetype":"postalcode"
},
  "geometry": {"coordinates":[-4.1421604058349,55.87521963914451],"type":"Point"}
}