{
  "type": "Feature",
  "properties": {
    "iso:country":"GB",
    "wof:name":"BN2 9QH",
    "wof:placetype":"postalcode"
},
  "geometry": {"coordinates":[-0.13348511548646,50.82471462597019],"type":"Point"}
}