{
  "type": "Feature",
  "properties": {
    "iso:country": "GB",
    "wof:name": "BN2 9QH",
    "wof:placetype": "postalcode"
  },
  "geometry": {"coordinates":[-0.133485,50.824715],"type":"Point"}
}
