{
  "type": "Feature",
  "properties": {
    "iso:country": "GB",
    "wof:name": "KT14 7SS",
    "wof:placetype": "postalcode"
  },
  "geometry": {"coordinates":[-0.473809,51.332449],"type":"Point"}
}
