{
  "type": "Feature",
  "properties": {
    "iso:country":"GB",
    "wof:name":"KT14 7SS",
    "wof:placetype":"postalcode"
},
  "geometry": {"coordinates":[-0.47380941029406,51.33244900555628],"type":"Point"}
}