{
  "type": "Feature",
  "properties": {
    "iso:country":"GB",
    "wof:name":"HS1 2EY",
    "wof:placetype":"postalcode"
},
  "geometry": {"coordinates":[-6.38562878055569,58.21866276086993],"type":"Point"}
}