{
  "type": "Feature",
  "properties": {
    "iso:country":"GB",
    "wof:name":"WS15 2RL",
    "wof:placetype":"postalcode"
},
  "geometry": {"coordinates":[-1.94620920542454,52.76185051922526],"type":"Point"}
}