{
  "type": "Feature",
  "properties": {
    "date:inception_lower":"1980-01-01",
    "date:inception_upper":"1980-01-31",
    "iso:country":"GB",
    "wof:name":"WS15 2RL",
    "wof:placetype":"postalcode"
},
  "geometry": {"coordinates":[-1.946209,52.761851],"type":"Point"}
}