{
  "type": "Feature",
  "properties": {
    "iso:country":"GB",
    "wof:name":"TR13 8TG",
    "wof:placetype":"postalcode"
},
  "geometry": {"coordinates":[-5.274783734993,50.10148371505493],"type":"Point"}
}