{
  "type": "Feature",
  "properties": {
    "date:inception_lower":"1980-01-01",
    "date:inception_upper":"1980-01-31",
    "iso:country":"GB",
    "wof:name":"MK42 8ES",
    "wof:placetype":"postalcode"
},
  "geometry": {"coordinates":[-0.498513,52.114392],"type":"Point"}
}