{
  "type": "Feature",
  "properties": {
    "date:inception_lower": "2001-06-01",
    "date:inception_upper": "2001-06-01",
    "iso:country": "GB",
    "wof:name": "NP20 1LT",
    "wof:placetype": "postalcode"
  },
  "geometry": {"coordinates":[-2.993552,51.582598],"type":"Point"}
}
