{
  "type": "Feature",
  "properties": {
    "iso:country": "GB",
    "wof:name": "NP20 1LT",
    "wof:placetype": "postalcode"
  },
  "geometry": {"coordinates":[-2.993552,51.582598],"type":"Point"}
}
