{
  "type": "Feature",
  "properties": {
    "iso:country":"GB",
    "wof:name":"NP20 1LT",
    "wof:placetype":"postalcode"
},
  "geometry": {"coordinates":[-2.99355189310945,51.58259751606332],"type":"Point"}
}