{
  "type": "Feature",
  "properties": {
    "iso:country":"GB",
    "wof:name":"TN4 0HB",
    "wof:placetype":"postalcode"
},
  "geometry": {"coordinates":[0.25665510148283,51.1558387687543],"type":"Point"}
}