{
  "type": "Feature",
  "properties": {
    "date:inception_lower": "2021-08-01",
    "date:inception_upper": "2021-08-01",
    "iso:country": "GB",
    "wof:name": "TR4 9GF",
    "wof:placetype": "postalcode"
  },
  "geometry": {"coordinates":[-5.105898,50.339104],"type":"Point"}
}
