{
  "type": "Feature",
  "properties": {
    "iso:country": "GB",
    "wof:name": "UB4 8LE",
    "wof:placetype": "postalcode"
  },
  "geometry": {"coordinates":[-0.423751,51.53655],"type":"Point"}
}
