{
  "type": "Feature",
  "properties": {
    "date:inception_lower":"1980-01-01",
    "date:inception_upper":"1980-01-31",
    "iso:country":"GB",
    "wof:name":"DG3 5AY",
    "wof:placetype":"postalcode"
},
  "geometry": {"coordinates":[-3.780298,55.263966],"type":"Point"}
}