{
  "type": "Feature",
  "properties": {
    "iso:country":"GB",
    "wof:name":"TR7 1HH",
    "wof:placetype":"postalcode"
},
  "geometry": {"coordinates":[-5.08959024378635,50.41788127513873],"type":"Point"}
}