{
  "type": "Feature",
  "properties": {
    "date:inception_lower":"1993-01-01",
    "date:inception_upper":"1993-01-31",
    "iso:country":"GB",
    "wof:name":"CH6 5YN",
    "wof:placetype":"postalcode"
},
  "geometry": {"coordinates":[-3.141417,53.249002],"type":"Point"}
}