{
  "type": "Feature",
  "properties": {
    "iso:country":"GB",
    "wof:name":"CH6 5YN",
    "wof:placetype":"postalcode"
},
  "geometry": {"coordinates":[-3.14141733046901,53.24900163183758],"type":"Point"}
}