{
  "type": "Feature",
  "properties": {
    "iso:country":"GB",
    "wof:name":"DG16 5AT",
    "wof:placetype":"postalcode"
},
  "geometry": {"coordinates":[-3.06551110930944,54.99516513244987],"type":"Point"}
}