{
  "type": "Feature",
  "properties": {
    "iso:country": "GB",
    "wof:name": "FY4 2BH",
    "wof:placetype": "postalcode"
  },
  "geometry": {"coordinates":[-3.040869,53.791696],"type":"Point"}
}
