{
  "type": "Feature",
  "properties": {
    "iso:country":"GB",
    "wof:name":"B23 5JU",
    "wof:placetype":"postalcode"
},
  "geometry": {"coordinates":[-1.84837595900972,52.53876739749781],"type":"Point"}
}