{
  "type": "Feature",
  "properties": {
    "iso:country":"GB",
    "wof:name":"AB15 6DZ",
    "wof:placetype":"postalcode"
},
  "geometry": {"coordinates":[-2.15004233358175,57.14735262702757],"type":"Point"}
}