{
  "type": "Feature",
  "properties": {
    "iso:country":"GB",
    "wof:name":"L15 5AG",
    "wof:placetype":"postalcode"
},
  "geometry": {"coordinates":[-2.9164587122809,53.38923064451181],"type":"Point"}
}