{
  "type": "Feature",
  "properties": {
    "iso:country":"GB",
    "wof:name":"BA1 6TL",
    "wof:placetype":"postalcode"
},
  "geometry": {"coordinates":[-2.34220957065683,51.40140381571779],"type":"Point"}
}