{
  "type": "Feature",
  "properties": {
    "iso:country": "GB",
    "wof:name": "BA1 6TL",
    "wof:placetype": "postalcode"
  },
  "geometry": {"coordinates":[-2.34221,51.401404],"type":"Point"}
}
