{
  "type": "Feature",
  "properties": {
    "iso:country":"GB",
    "wof:name":"TA5 2AY",
    "wof:placetype":"postalcode"
},
  "geometry": {"coordinates":[-3.04319095279686,51.13592928723308],"type":"Point"}
}