{
  "type": "Feature",
  "properties": {
    "iso:country":"GB",
    "wof:name":"GU32 2AE",
    "wof:placetype":"postalcode"
},
  "geometry": {"coordinates":[-0.93755792118977,51.00740253930597],"type":"Point"}
}