{
  "type": "Feature",
  "properties": {
    "date:inception_lower": "2000-12-01",
    "date:inception_upper": "2000-12-01",
    "iso:country": "GB",
    "wof:name": "W1T 5DP",
    "wof:placetype": "postalcode"
  },
  "geometry": {"coordinates":[-0.13831,51.523438],"type":"Point"}
}
