{
  "type": "Feature",
  "properties": {
    "iso:country":"GB",
    "wof:name":"W1T 5DP",
    "wof:placetype":"postalcode"
},
  "geometry": {"coordinates":[-0.13831047374521,51.52343823641282],"type":"Point"}
}