{
  "type": "Feature",
  "properties": {
    "iso:country":"GB",
    "wof:name":"BL9 5PH",
    "wof:placetype":"postalcode"
},
  "geometry": {"coordinates":[-2.31244336716949,53.62956298977844],"type":"Point"}
}