{
  "type": "Feature",
  "properties": {
    "iso:country": "GB",
    "wof:name": "BL9 5PH",
    "wof:placetype": "postalcode"
  },
  "geometry": {"coordinates":[-2.312443,53.629563],"type":"Point"}
}
