{
  "type": "Feature",
  "properties": {
    "iso:country":"GB",
    "wof:name":"HR1 4DZ",
    "wof:placetype":"postalcode"
},
  "geometry": {"coordinates":[-2.64063416887563,52.0684342753269],"type":"Point"}
}