{
  "type": "Feature",
  "properties": {
    "iso:country":"GB",
    "wof:name":"NW3 7RE",
    "wof:placetype":"postalcode"
},
  "geometry": {"coordinates":[-0.1881876710512,51.55646604355494],"type":"Point"}
}