{
  "type": "Feature",
  "properties": {
    "iso:country": "GB",
    "wof:name": "NW3 7RE",
    "wof:placetype": "postalcode"
  },
  "geometry": {"coordinates":[-0.188188,51.556466],"type":"Point"}
}
