{
  "type": "Feature",
  "properties": {
    "iso:country": "GB",
    "wof:name": "KY12 8PR",
    "wof:placetype": "postalcode"
  },
  "geometry": {"coordinates":[-3.499823,56.065781],"type":"Point"}
}
