{
  "type": "Feature",
  "properties": {
    "iso:country":"GB",
    "wof:name":"KY12 8PR",
    "wof:placetype":"postalcode"
},
  "geometry": {"coordinates":[-3.49982310857949,56.06578071052473],"type":"Point"}
}