{
  "type": "Feature",
  "properties": {
    "date:inception_lower": "1980-01-01",
    "date:inception_upper": "1980-01-01",
    "iso:country": "GB",
    "wof:name": "KY12 8PR",
    "wof:placetype": "postalcode"
  },
  "geometry": {"coordinates":[-3.499823,56.065781],"type":"Point"}
}
