{
  "type": "Feature",
  "properties": {
    "date:inception_lower":"1980-01-01",
    "date:inception_upper":"1980-01-31",
    "iso:country":"GB",
    "wof:name":"ME18 6ED",
    "wof:placetype":"postalcode"
},
  "geometry": {"coordinates":[0.447859,51.227845],"type":"Point"}
}