{
  "type": "Feature",
  "properties": {
    "iso:country": "GB",
    "wof:name": "LU1 3XW",
    "wof:placetype": "postalcode"
  },
  "geometry": {"coordinates":[-0.402762,51.875146],"type":"Point"}
}
