{
  "type": "Feature",
  "properties": {
    "date:inception_lower": "1980-01-01",
    "date:inception_upper": "1980-01-01",
    "iso:country": "GB",
    "wof:name": "LU1 3XW",
    "wof:placetype": "postalcode"
  },
  "geometry": {"coordinates":[-0.40232,51.874924],"type":"Point"}
}
