{
  "type": "Feature",
  "properties": {
    "date:inception_lower": "2006-03-01",
    "date:inception_upper": "2006-03-01",
    "iso:country": "GB",
    "wof:name": "GU27 3TJ",
    "wof:placetype": "postalcode"
  },
  "geometry": {"coordinates":[-0.723537,51.052944],"type":"Point"}
}
