{
  "type": "Feature",
  "properties": {
    "iso:country":"GB",
    "wof:name":"GU27 3TJ",
    "wof:placetype":"postalcode"
},
  "geometry": {"coordinates":[-0.72362908965107,51.05294076962221],"type":"Point"}
}