{
  "type": "Feature",
  "properties": {
    "iso:country": "GB",
    "wof:name": "WA9 4AA",
    "wof:placetype": "postalcode"
  },
  "geometry": {"coordinates":[-2.73608,53.414406],"type":"Point"}
}
