{
  "type": "Feature",
  "properties": {
    "iso:country":"GB",
    "wof:name":"GU6 7SW",
    "wof:placetype":"postalcode"
},
  "geometry": {"coordinates":[-0.42059995136507,51.13404108166955],"type":"Point"}
}