{
  "type": "Feature",
  "properties": {
    "iso:country":"GB",
    "wof:name":"IV2 3GA",
    "wof:placetype":"postalcode"
},
  "geometry": {"coordinates":[-4.1923199163847,57.45709518379529],"type":"Point"}
}