{
  "type": "Feature",
  "properties": {
    "iso:country": "GB",
    "wof:name": "CM5 0QF",
    "wof:placetype": "postalcode"
  },
  "geometry": {"coordinates":[0.335129,51.728488],"type":"Point"}
}
