{
  "type": "Feature",
  "properties": {
    "date:inception_lower": "1980-01-01",
    "date:inception_upper": "1980-01-01",
    "iso:country": "GB",
    "wof:name": "IP8 3BN",
    "wof:placetype": "postalcode"
  },
  "geometry": {"coordinates":[1.095335,52.063221],"type":"Point"}
}
