{
  "type": "Feature",
  "properties": {
    "iso:country": "GB",
    "wof:name": "IP8 3BN",
    "wof:placetype": "postalcode"
  },
  "geometry": {"coordinates":[1.095335,52.063221],"type":"Point"}
}
