{
  "type": "Feature",
  "properties": {
    "iso:country": "GB",
    "wof:name": "CM4 9RT",
    "wof:placetype": "postalcode"
  },
  "geometry": {"coordinates":[0.454774,51.65311],"type":"Point"}
}
