{
  "type": "Feature",
  "properties": {
    "iso:country":"GB",
    "wof:name":"CM4 9RT",
    "wof:placetype":"postalcode"
},
  "geometry": {"coordinates":[0.45474775846912,51.65310604727771],"type":"Point"}
}