{
  "type": "Feature",
  "properties": {
    "iso:country":"GB",
    "wof:name":"DT7 3UH",
    "wof:placetype":"postalcode"
},
  "geometry": {"coordinates":[-2.95390183318716,50.73743885192584],"type":"Point"}
}