{
  "type": "Feature",
  "properties": {
    "iso:country": "GB",
    "wof:name": "DT7 3UH",
    "wof:placetype": "postalcode"
  },
  "geometry": {"coordinates":[-2.953651,50.737331],"type":"Point"}
}
