{
  "type": "Feature",
  "properties": {
    "iso:country":"GB",
    "wof:name":"E4 9ND",
    "wof:placetype":"postalcode"
},
  "geometry": {"coordinates":[-0.00823245491612,51.60682107710858],"type":"Point"}
}