{
  "type": "Feature",
  "properties": {
    "iso:country": "GB",
    "wof:name": "OX27 8RH",
    "wof:placetype": "postalcode"
  },
  "geometry": {"coordinates":[-1.131666,51.942231],"type":"Point"}
}
