{
  "type": "Feature",
  "properties": {
    "iso:country":"GB",
    "wof:name":"OX27 8RH",
    "wof:placetype":"postalcode"
},
  "geometry": {"coordinates":[-1.13249325028123,51.94182335508256],"type":"Point"}
}