{
  "type": "Feature",
  "properties": {
    "iso:country":"GB",
    "wof:name":"NP18 2BU",
    "wof:placetype":"postalcode"
},
  "geometry": {"coordinates":[-2.94889696441098,51.56111746924375],"type":"Point"}
}