{
  "type": "Feature",
  "properties": {
    "iso:country": "GB",
    "wof:name": "PE10 9YB",
    "wof:placetype": "postalcode"
  },
  "geometry": {"coordinates":[-0.365331,52.777016],"type":"Point"}
}
