{
  "type": "Feature",
  "properties": {
    "date:inception_lower":"1996-12-01",
    "date:inception_upper":"1996-12-31",
    "iso:country":"GB",
    "wof:name":"PE10 9YB",
    "wof:placetype":"postalcode"
},
  "geometry": {"coordinates":[-0.365331,52.777016],"type":"Point"}
}