{
  "type": "Feature",
  "properties": {
    "iso:country":"GB",
    "wof:name":"PE10 9YB",
    "wof:placetype":"postalcode"
},
  "geometry": {"coordinates":[-0.36533105338486,52.77701642097766],"type":"Point"}
}