{
  "type": "Feature",
  "properties": {
    "date:inception_lower":"2005-01-01",
    "date:inception_upper":"2005-01-31",
    "iso:country":"GB",
    "wof:name":"NG34 9UW",
    "wof:placetype":"postalcode"
},
  "geometry": {"coordinates":[-0.301946,52.979507],"type":"Point"}
}