{
  "type": "Feature",
  "properties": {
    "iso:country":"GB",
    "wof:name":"NG34 9UW",
    "wof:placetype":"postalcode"
},
  "geometry": {"coordinates":[-0.30194616642604,52.97950741376815],"type":"Point"}
}