{
  "type": "Feature",
  "properties": {
    "iso:country": "GB",
    "wof:name": "DN6 9LX",
    "wof:placetype": "postalcode"
  },
  "geometry": {"coordinates":[-1.174451,53.622722],"type":"Point"}
}
