{
  "type": "Feature",
  "properties": {
    "iso:country":"GB",
    "wof:name":"ST18 0EP",
    "wof:placetype":"postalcode"
},
  "geometry": {"coordinates":[-2.04731085023276,52.90375104838988],"type":"Point"}
}