{
  "type": "Feature",
  "properties": {
    "iso:country": "GB",
    "wof:name": "NE37 2HX",
    "wof:placetype": "postalcode"
  },
  "geometry": {"coordinates":[-1.52622,54.912113],"type":"Point"}
}
