{
  "type": "Feature",
  "properties": {
    "iso:country":"GB",
    "wof:name":"KY3 0DG",
    "wof:placetype":"postalcode"
},
  "geometry": {"coordinates":[-3.24352908356055,56.05975199267166],"type":"Point"}
}