{
  "type": "Feature",
  "properties": {
    "iso:country":"GB",
    "wof:name":"KA8 8LW",
    "wof:placetype":"postalcode"
},
  "geometry": {"coordinates":[-4.62434889938727,55.47587228830206],"type":"Point"}
}