{
  "type": "Feature",
  "properties": {
    "iso:country":"GB",
    "wof:name":"LA17 7UQ",
    "wof:placetype":"postalcode"
},
  "geometry": {"coordinates":[-3.17985695209739,54.23320402588808],"type":"Point"}
}