{
  "type": "Feature",
  "properties": {
    "iso:country":"GB",
    "wof:name":"SL6 9QU",
    "wof:placetype":"postalcode"
},
  "geometry": {"coordinates":[-0.70590725098947,51.556996084402],"type":"Point"}
}