{
  "type": "Feature",
  "properties": {
    "date:inception_lower": "1980-01-01",
    "date:inception_upper": "1980-01-01",
    "iso:country": "GB",
    "wof:name": "E10 6EA",
    "wof:placetype": "postalcode"
  },
  "geometry": {"coordinates":[-0.000349,51.580179],"type":"Point"}
}
