{
  "type": "Feature",
  "properties": {
    "iso:country":"GB",
    "wof:name":"RG2 0RB",
    "wof:placetype":"postalcode"
},
  "geometry": {"coordinates":[-0.97645079461914,51.42806339137879],"type":"Point"}
}