{
  "type": "Feature",
  "properties": {
    "iso:country": "GB",
    "wof:name": "NE6 5DU",
    "wof:placetype": "postalcode"
  },
  "geometry": {"coordinates":[-1.570914,54.987789],"type":"Point"}
}
