{
  "type": "Feature",
  "properties": {
    "iso:country":"GB",
    "wof:name":"NE6 5DU",
    "wof:placetype":"postalcode"
},
  "geometry": {"coordinates":[-1.57051199856154,54.98756467748935],"type":"Point"}
}