{
  "type": "Feature",
  "properties": {
    "date:inception_lower":"1997-12-01",
    "date:inception_upper":"1997-12-31",
    "iso:country":"GB",
    "wof:name":"BS34 6NF",
    "wof:placetype":"postalcode"
},
  "geometry": {"coordinates":[-2.566815,51.533032],"type":"Point"}
}