{
  "type": "Feature",
  "properties": {
    "iso:country": "GB",
    "wof:name": "SW11 2SH",
    "wof:placetype": "postalcode"
  },
  "geometry": {"coordinates":[-0.17612,51.467901],"type":"Point"}
}
