{
  "type": "Feature",
  "properties": {
    "iso:country":"GB",
    "wof:name":"SR6 7DA",
    "wof:placetype":"postalcode"
},
  "geometry": {"coordinates":[-1.36351800052522,54.94940965087779],"type":"Point"}
}