{
  "type": "Feature",
  "properties": {
    "iso:country":"GB",
    "wof:name":"SO19 8PH",
    "wof:placetype":"postalcode"
},
  "geometry": {"coordinates":[-1.36015274206333,50.9049630425753],"type":"Point"}
}