{
  "type": "Feature",
  "properties": {
    "date:inception_lower":"2013-07-01",
    "date:inception_upper":"2013-07-31",
    "iso:country":"GB",
    "wof:name":"NE40 3UG",
    "wof:placetype":"postalcode"
},
  "geometry": {"coordinates":[-1.782633,54.968385],"type":"Point"}
}