{
  "type": "Feature",
  "properties": {
    "iso:country":"GB",
    "wof:name":"NE40 3UG",
    "wof:placetype":"postalcode"
},
  "geometry": {"coordinates":[-1.78263347686035,54.96838545544437],"type":"Point"}
}