{
  "type": "Feature",
  "properties": {
    "iso:country":"GB",
    "wof:name":"S6 4SG",
    "wof:placetype":"postalcode"
},
  "geometry": {"coordinates":[-1.5255586758032,53.40692723986724],"type":"Point"}
}