{
  "type": "Feature",
  "properties": {
    "date:inception_lower": "1980-01-01",
    "date:inception_upper": "1980-01-01",
    "iso:country": "GB",
    "wof:name": "S6 4SG",
    "wof:placetype": "postalcode"
  },
  "geometry": {"coordinates":[-1.52559,53.406936],"type":"Point"}
}
