{
  "type": "Feature",
  "properties": {
    "iso:country": "GB",
    "wof:name": "S6 4SG",
    "wof:placetype": "postalcode"
  },
  "geometry": {"coordinates":[-1.52559,53.406936],"type":"Point"}
}
