{
  "type": "Feature",
  "properties": {
    "iso:country":"GB",
    "wof:name":"BA22 8HU",
    "wof:placetype":"postalcode"
},
  "geometry": {"coordinates":[-2.67597277850069,50.95240760495387],"type":"Point"}
}