{
  "type": "Feature",
  "properties": {
    "iso:country":"GB",
    "wof:name":"DY1 3JA",
    "wof:placetype":"postalcode"
},
  "geometry": {"coordinates":[-2.09343763144583,52.51375427269991],"type":"Point"}
}