{
  "type": "Feature",
  "properties": {
    "iso:country": "GB",
    "wof:name": "EX34 0AF",
    "wof:placetype": "postalcode"
  },
  "geometry": {"coordinates":[-4.035317,51.205118],"type":"Point"}
}
