{
  "type": "Feature",
  "properties": {
    "iso:country": "GB",
    "wof:name": "RG22 5FP",
    "wof:placetype": "postalcode"
  },
  "geometry": {"coordinates":[-1.13215,51.241945],"type":"Point"}
}
