{
  "type": "Feature",
  "properties": {
    "iso:country":"GB",
    "wof:name":"GL14 3BG",
    "wof:placetype":"postalcode"
},
  "geometry": {"coordinates":[-2.5046889491858,51.80587826671959],"type":"Point"}
}