{
  "type": "Feature",
  "properties": {
    "iso:country": "GB",
    "wof:name": "NR25 7DG",
    "wof:placetype": "postalcode"
  },
  "geometry": {"coordinates":[0.986041,52.933384],"type":"Point"}
}
