{
  "type": "Feature",
  "properties": {
    "iso:country":"GB",
    "wof:name":"NR25 7DG",
    "wof:placetype":"postalcode"
},
  "geometry": {"coordinates":[0.98604125525156,52.93338355028536],"type":"Point"}
}