{
  "type": "Feature",
  "properties": {
    "iso:country": "GB",
    "wof:name": "CA11 9TE",
    "wof:placetype": "postalcode"
  },
  "geometry": {"coordinates":[-2.874771,54.711924],"type":"Point"}
}
