{
  "type": "Feature",
  "properties": {
    "iso:country":"GB",
    "wof:name":"CA11 9TE",
    "wof:placetype":"postalcode"
},
  "geometry": {"coordinates":[-2.87477066550695,54.711924248023],"type":"Point"}
}