{
  "type": "Feature",
  "properties": {
    "iso:country": "GB",
    "wof:name": "SO45 1EP",
    "wof:placetype": "postalcode"
  },
  "geometry": {"coordinates":[-1.366251,50.821617],"type":"Point"}
}
