{
  "type": "Feature",
  "properties": {
    "iso:country":"GB",
    "wof:name":"SO45 1EP",
    "wof:placetype":"postalcode"
},
  "geometry": {"coordinates":[-1.36626070800432,50.82162631967697],"type":"Point"}
}