{
  "type": "Feature",
  "properties": {
    "iso:country": "GB",
    "wof:name": "SO45 1EP",
    "wof:placetype": "postalcode"
  },
  "geometry": {"coordinates":[-1.366378,50.821627],"type":"Point"}
}
