{
  "type": "Feature",
  "properties": {
    "date:inception_lower": "1980-01-01",
    "date:inception_upper": "1980-01-01",
    "iso:country": "GB",
    "wof:name": "KW1 4HR",
    "wof:placetype": "postalcode"
  },
  "geometry": {"coordinates":[-3.085145,58.445928],"type":"Point"}
}
