{
  "type": "Feature",
  "properties": {
    "iso:country": "GB",
    "wof:name": "LE17 4BN",
    "wof:placetype": "postalcode"
  },
  "geometry": {"coordinates":[-1.200417,52.45315],"type":"Point"}
}
