{
  "type": "Feature",
  "properties": {
    "iso:country":"GB",
    "wof:name":"G82 5BL",
    "wof:placetype":"postalcode"
},
  "geometry": {"coordinates":[-4.58707381791383,55.94886518206252],"type":"Point"}
}