{
  "type": "Feature",
  "properties": {
    "iso:country": "GB",
    "wof:name": "G82 5BL",
    "wof:placetype": "postalcode"
  },
  "geometry": {"coordinates":[-4.587074,55.948865],"type":"Point"}
}
