{
  "type": "Feature",
  "properties": {
    "iso:country":"GB",
    "wof:name":"PL5 3BH",
    "wof:placetype":"postalcode"
},
  "geometry": {"coordinates":[-4.13740465044904,50.40985544005292],"type":"Point"}
}