{
  "type": "Feature",
  "properties": {
    "iso:country": "GB",
    "wof:name": "B61 9AZ",
    "wof:placetype": "postalcode"
  },
  "geometry": {"coordinates":[-2.077614,52.351312],"type":"Point"}
}
