{
  "type": "Feature",
  "properties": {
    "date:inception_lower": "1992-01-01",
    "date:inception_upper": "1992-01-01",
    "iso:country": "GB",
    "wof:name": "B61 9AZ",
    "wof:placetype": "postalcode"
  },
  "geometry": {"coordinates":[-2.077629,52.351411],"type":"Point"}
}
