{
  "type": "Feature",
  "properties": {
    "iso:country": "GB",
    "wof:name": "PE20 3LA",
    "wof:placetype": "postalcode"
  },
  "geometry": {"coordinates":[-0.147974,52.941174],"type":"Point"}
}
