{
  "type": "Feature",
  "properties": {
    "iso:country":"GB",
    "wof:name":"PE20 3LA",
    "wof:placetype":"postalcode"
},
  "geometry": {"coordinates":[-0.1479739851098,52.94117430207543],"type":"Point"}
}