{
  "type": "Feature",
  "properties": {
    "iso:country": "GB",
    "wof:name": "CO2 0NU",
    "wof:placetype": "postalcode"
  },
  "geometry": {"coordinates":[0.810877,51.845974],"type":"Point"}
}
