{
  "type": "Feature",
  "properties": {
    "iso:country":"GB",
    "wof:name":"CO2 0NU",
    "wof:placetype":"postalcode"
},
  "geometry": {"coordinates":[0.81084809783431,51.84596357029142],"type":"Point"}
}