{
  "type": "Feature",
  "properties": {
    "date:inception_lower": "1995-07-01",
    "date:inception_upper": "1995-07-01",
    "iso:country": "GB",
    "wof:name": "RG42 6NS",
    "wof:placetype": "postalcode"
  },
  "geometry": {"coordinates":[-0.699227,51.433534],"type":"Point"}
}
