{
  "type": "Feature",
  "properties": {
    "iso:country":"GB",
    "wof:name":"RG42 6NS",
    "wof:placetype":"postalcode"
},
  "geometry": {"coordinates":[-0.69922738638425,51.43353415622772],"type":"Point"}
}