{
  "type": "Feature",
  "properties": {
    "iso:country":"GB",
    "wof:name":"NE65 8RU",
    "wof:placetype":"postalcode"
},
  "geometry": {"coordinates":[-1.81437112034411,55.2363830607936],"type":"Point"}
}