{
  "type": "Feature",
  "properties": {
    "iso:country": "GB",
    "wof:name": "NE65 8RU",
    "wof:placetype": "postalcode"
  },
  "geometry": {"coordinates":[-1.814371,55.236383],"type":"Point"}
}
