{
  "type": "Feature",
  "properties": {
    "iso:country":"GB",
    "wof:name":"M21 9FB",
    "wof:placetype":"postalcode"
},
  "geometry": {"coordinates":[-2.28060828824318,53.43961847661184],"type":"Point"}
}