{
  "type": "Feature",
  "properties": {
    "iso:country":"GB",
    "wof:name":"SM1 2RY",
    "wof:placetype":"postalcode"
},
  "geometry": {"coordinates":[-0.19878642656476,51.36643757945908],"type":"Point"}
}