{
  "type": "Feature",
  "properties": {
    "iso:country":"GB",
    "wof:name":"BS2 8UU",
    "wof:placetype":"postalcode"
},
  "geometry": {"coordinates":[-2.58672339312476,51.46240489483281],"type":"Point"}
}