{
  "type": "Feature",
  "properties": {
    "iso:country": "GB",
    "wof:name": "BS2 8UU",
    "wof:placetype": "postalcode"
  },
  "geometry": {"coordinates":[-2.587115,51.462501],"type":"Point"}
}
