{
  "type": "Feature",
  "properties": {
    "date:inception_lower": "1980-01-01",
    "date:inception_upper": "1980-01-01",
    "iso:country": "GB",
    "wof:name": "RG7 4QE",
    "wof:placetype": "postalcode"
  },
  "geometry": {"coordinates":[-1.115377,51.373363],"type":"Point"}
}
