{
  "type": "Feature",
  "properties": {
    "iso:country":"GB",
    "wof:name":"RG7 4QE",
    "wof:placetype":"postalcode"
},
  "geometry": {"coordinates":[-1.11537668605416,51.37336340860435],"type":"Point"}
}