{
  "type": "Feature",
  "properties": {
    "iso:country": "GB",
    "wof:name": "RG7 4QE",
    "wof:placetype": "postalcode"
  },
  "geometry": {"coordinates":[-1.115377,51.373363],"type":"Point"}
}
