{
  "type": "Feature",
  "properties": {
    "iso:country":"GB",
    "wof:name":"OX9 7DL",
    "wof:placetype":"postalcode"
},
  "geometry": {"coordinates":[-0.97704263517694,51.69099472670152],"type":"Point"}
}