{
  "type": "Feature",
  "properties": {
    "date:inception_lower": "1980-01-01",
    "date:inception_upper": "1980-01-01",
    "iso:country": "GB",
    "wof:name": "OX9 7DL",
    "wof:placetype": "postalcode"
  },
  "geometry": {"coordinates":[-0.977043,51.690995],"type":"Point"}
}
