{
  "type": "Feature",
  "properties": {
    "iso:country": "GB",
    "wof:name": "TR11 4PB",
    "wof:placetype": "postalcode"
  },
  "geometry": {"coordinates":[-5.09858,50.156414],"type":"Point"}
}
