{
  "type": "Feature",
  "properties": {
    "date:inception_lower": "1980-01-01",
    "date:inception_upper": "1980-01-01",
    "iso:country": "GB",
    "wof:name": "RH10 4NH",
    "wof:placetype": "postalcode"
  },
  "geometry": {"coordinates":[-0.1057,51.123276],"type":"Point"}
}
