{
  "type": "Feature",
  "properties": {
    "date:inception_lower":"1980-01-01",
    "date:inception_upper":"1980-01-31",
    "iso:country":"GB",
    "wof:name":"PR8 1EZ",
    "wof:placetype":"postalcode"
},
  "geometry": {"coordinates":[-3.005707,53.645438],"type":"Point"}
}