{
  "type": "Feature",
  "properties": {
    "iso:country":"GB",
    "wof:name":"PR8 1EZ",
    "wof:placetype":"postalcode"
},
  "geometry": {"coordinates":[-3.0057069398228,53.6454384301386],"type":"Point"}
}