{
  "type": "Feature",
  "properties": {
    "iso:country":"GB",
    "wof:name":"BR6 6DP",
    "wof:placetype":"postalcode"
},
  "geometry": {"coordinates":[0.09528920401811,51.35391158451055],"type":"Point"}
}