{
  "type": "Feature",
  "properties": {
    "iso:country":"GB",
    "wof:name":"BR4 9LD",
    "wof:placetype":"postalcode"
},
  "geometry": {"coordinates":[-0.01662787887439,51.372056313314],"type":"Point"}
}