{
  "type": "Feature",
  "properties": {
    "iso:country": "GB",
    "wof:name": "M41 6PE",
    "wof:placetype": "postalcode"
  },
  "geometry": {"coordinates":[-2.390153,53.446007],"type":"Point"}
}
