{
  "type": "Feature",
  "properties": {
    "iso:country":"GB",
    "wof:name":"TS24 7QS",
    "wof:placetype":"postalcode"
},
  "geometry": {"coordinates":[-1.21387254868207,54.68060466640148],"type":"Point"}
}