{
  "type": "Feature",
  "properties": {
    "date:inception_lower":"2014-09-01",
    "date:inception_upper":"2014-09-30",
    "iso:country":"GB",
    "wof:name":"EH41 4EX",
    "wof:placetype":"postalcode"
},
  "geometry": {"coordinates":[-2.78182,55.950618],"type":"Point"}
}