{
  "type": "Feature",
  "properties": {
    "iso:country":"GB",
    "wof:name":"EH41 4EX",
    "wof:placetype":"postalcode"
},
  "geometry": {"coordinates":[-2.78182018873248,55.95061792552875],"type":"Point"}
}