{
  "type": "Feature",
  "properties": {
    "iso:country":"GB",
    "wof:name":"NR24 2AS",
    "wof:placetype":"postalcode"
},
  "geometry": {"coordinates":[1.12178050626715,52.85651877037433],"type":"Point"}
}