{
  "type": "Feature",
  "properties": {
    "iso:country": "GB",
    "wof:name": "NN7 4HS",
    "wof:placetype": "postalcode"
  },
  "geometry": {"coordinates":[-1.033891,52.267484],"type":"Point"}
}
