{
  "type": "Feature",
  "properties": {
    "iso:country":"GB",
    "wof:name":"NN7 4HS",
    "wof:placetype":"postalcode"
},
  "geometry": {"coordinates":[-1.03390554107647,52.26747748887728],"type":"Point"}
}