{
  "type": "Feature",
  "properties": {
    "iso:country":"GB",
    "wof:name":"PA1 2ST",
    "wof:placetype":"postalcode"
},
  "geometry": {"coordinates":[-4.46321562860471,55.8443138765621],"type":"Point"}
}