{
  "type": "Feature",
  "properties": {
    "iso:country":"GB",
    "wof:name":"LS4 2UA",
    "wof:placetype":"postalcode"
},
  "geometry": {"coordinates":[-1.59612149600838,53.8143477420319],"type":"Point"}
}