{
  "type": "Feature",
  "properties": {
    "iso:country": "GB",
    "wof:name": "SY2 5UZ",
    "wof:placetype": "postalcode"
  },
  "geometry": {"coordinates":[-2.719158,52.71511],"type":"Point"}
}
