{
  "type": "Feature",
  "properties": {
    "iso:country":"GB",
    "wof:name":"NN7 2JP",
    "wof:placetype":"postalcode"
},
  "geometry": {"coordinates":[-0.87018950250162,52.12951708706532],"type":"Point"}
}