{
  "type": "Feature",
  "properties": {
    "date:inception_lower":"1980-01-01",
    "date:inception_upper":"1980-01-31",
    "iso:country":"GB",
    "wof:name":"NN7 2JP",
    "wof:placetype":"postalcode"
},
  "geometry": {"coordinates":[-0.870189,52.129517],"type":"Point"}
}