{
  "type": "Feature",
  "properties": {
    "date:inception_lower": "2016-08-01",
    "date:inception_upper": "2016-08-01",
    "iso:country": "GB",
    "wof:name": "SE5 7FQ",
    "wof:placetype": "postalcode"
  },
  "geometry": {"coordinates":[-0.092767,51.478788],"type":"Point"}
}
