{
  "type": "Feature",
  "properties": {
    "iso:country": "GB",
    "wof:name": "SE5 7FQ",
    "wof:placetype": "postalcode"
  },
  "geometry": {"coordinates":[-0.092434,51.478819],"type":"Point"}
}
