{
  "type": "Feature",
  "properties": {
    "iso:country":"GB",
    "wof:name":"PO9 3TP",
    "wof:placetype":"postalcode"
},
  "geometry": {"coordinates":[-1.0029535197096,50.86292787876],"type":"Point"}
}