{
  "type": "Feature",
  "properties": {
    "date:inception_lower": "1980-01-01",
    "date:inception_upper": "1980-01-01",
    "iso:country": "GB",
    "wof:name": "PO9 3TP",
    "wof:placetype": "postalcode"
  },
  "geometry": {"coordinates":[-1.002953,50.862928],"type":"Point"}
}
