{
  "type": "Feature",
  "properties": {
    "date:inception_lower":"2015-04-01",
    "date:inception_upper":"2015-04-30",
    "iso:country":"GB",
    "wof:name":"CT12 5FP",
    "wof:placetype":"postalcode"
},
  "geometry": {"coordinates":[1.389201,51.356739],"type":"Point"}
}