{
  "type": "Feature",
  "properties": {
    "iso:country":"GB",
    "wof:name":"CT12 5FP",
    "wof:placetype":"postalcode"
},
  "geometry": {"coordinates":[1.38947194025201,51.35687583648335],"type":"Point"}
}