{
  "type": "Feature",
  "properties": {
    "iso:country": "GB",
    "wof:name": "CT12 5FP",
    "wof:placetype": "postalcode"
  },
  "geometry": {"coordinates":[1.389201,51.356739],"type":"Point"}
}
