{
  "type": "Feature",
  "properties": {
    "iso:country":"GB",
    "wof:name":"EH23 4UJ",
    "wof:placetype":"postalcode"
},
  "geometry": {"coordinates":[-3.04651748229354,55.84510620415271],"type":"Point"}
}