{
  "type": "Feature",
  "properties": {
    "iso:country": "GB",
    "wof:name": "SR5 2RB",
    "wof:placetype": "postalcode"
  },
  "geometry": {"coordinates":[-1.405323,54.927459],"type":"Point"}
}
