{
  "type": "Feature",
  "properties": {
    "iso:country":"GB",
    "wof:name":"SR5 2RB",
    "wof:placetype":"postalcode"
},
  "geometry": {"coordinates":[-1.40530981648777,54.92745166663254],"type":"Point"}
}