{
  "type": "Feature",
  "properties": {
    "iso:country":"GB",
    "wof:name":"TN4 8YA",
    "wof:placetype":"postalcode"
},
  "geometry": {"coordinates":[0.25015279990256,51.13330049456704],"type":"Point"}
}