{
  "type": "Feature",
  "properties": {
    "iso:country":"GB",
    "wof:name":"CT14 8AD",
    "wof:placetype":"postalcode"
},
  "geometry": {"coordinates":[1.40405116008057,51.18972556429379],"type":"Point"}
}