{
  "type": "Feature",
  "properties": {
    "date:inception_lower": "2022-10-01",
    "date:inception_upper": "2022-10-01",
    "iso:country": "GB",
    "wof:name": "CH4 7GT",
    "wof:placetype": "postalcode"
  },
  "geometry": {"coordinates":[-2.907916,53.166958],"type":"Point"}
}
