{
  "type": "Feature",
  "properties": {
    "iso:country":"GB",
    "wof:name":"EH4 3JD",
    "wof:placetype":"postalcode"
},
  "geometry": {"coordinates":[-3.23505853069556,55.95096934486477],"type":"Point"}
}