{
  "type": "Feature",
  "properties": {
    "iso:country":"GB",
    "wof:name":"NR9 3NE",
    "wof:placetype":"postalcode"
},
  "geometry": {"coordinates":[1.19688155352385,52.61894837615586],"type":"Point"}
}