{
  "type": "Feature",
  "properties": {
    "iso:country": "GB",
    "wof:name": "NR9 3NE",
    "wof:placetype": "postalcode"
  },
  "geometry": {"coordinates":[1.196882,52.618948],"type":"Point"}
}
