{
  "type": "Feature",
  "properties": {
    "iso:country":"GB",
    "wof:name":"S63 0EH",
    "wof:placetype":"postalcode"
},
  "geometry": {"coordinates":[-1.3029714632705,53.54424298773358],"type":"Point"}
}