{
  "type": "Feature",
  "properties": {
    "date:inception_lower": "1991-09-01",
    "date:inception_upper": "1991-09-01",
    "iso:country": "GB",
    "wof:name": "NN9 5NY",
    "wof:placetype": "postalcode"
  },
  "geometry": {"coordinates":[-0.68742,52.342792],"type":"Point"}
}
