{
  "type": "Feature",
  "properties": {
    "iso:country": "GB",
    "wof:name": "NN9 5NY",
    "wof:placetype": "postalcode"
  },
  "geometry": {"coordinates":[-0.686733,52.343171],"type":"Point"}
}
