{
  "type": "Feature",
  "properties": {
    "date:inception_lower":"1991-09-01",
    "date:inception_upper":"1991-09-30",
    "iso:country":"GB",
    "wof:name":"NN9 5NY",
    "wof:placetype":"postalcode"
},
  "geometry": {"coordinates":[-0.686733,52.343171],"type":"Point"}
}