{
  "type": "Feature",
  "properties": {
    "iso:country":"GB",
    "wof:name":"NN9 5NY",
    "wof:placetype":"postalcode"
},
  "geometry": {"coordinates":[-0.68674962438761,52.34315652134623],"type":"Point"}
}