{
  "type": "Feature",
  "properties": {
    "iso:country": "GB",
    "wof:name": "SA68 0QS",
    "wof:placetype": "postalcode"
  },
  "geometry": {"coordinates":[-4.72125,51.724346],"type":"Point"}
}
