{
  "type": "Feature",
  "properties": {
    "iso:country":"GB",
    "wof:name":"SA68 0QS",
    "wof:placetype":"postalcode"
},
  "geometry": {"coordinates":[-4.72125039758356,51.72434620501963],"type":"Point"}
}