{
  "type": "Feature",
  "properties": {
    "iso:country":"GB",
    "wof:name":"LL77 7SW",
    "wof:placetype":"postalcode"
},
  "geometry": {"coordinates":[-4.26718298823943,53.26505089747624],"type":"Point"}
}