{
  "type": "Feature",
  "properties": {
    "date:inception_lower": "1980-01-01",
    "date:inception_upper": "1980-01-01",
    "iso:country": "GB",
    "wof:name": "CA6 5PY",
    "wof:placetype": "postalcode"
  },
  "geometry": {"coordinates":[-2.907644,55.059015],"type":"Point"}
}
