{
  "type": "Feature",
  "properties": {
    "iso:country":"GB",
    "wof:name":"CA6 5PY",
    "wof:placetype":"postalcode"
},
  "geometry": {"coordinates":[-2.90764064156817,55.05900972188078],"type":"Point"}
}