{
  "type": "Feature",
  "properties": {
    "iso:country": "GB",
    "wof:name": "CA6 5PY",
    "wof:placetype": "postalcode"
  },
  "geometry": {"coordinates":[-2.907644,55.059015],"type":"Point"}
}
