{
  "type": "Feature",
  "properties": {
    "iso:country":"GB",
    "wof:name":"DL4 2DG",
    "wof:placetype":"postalcode"
},
  "geometry": {"coordinates":[-1.63290804585381,54.62739210110897],"type":"Point"}
}