{
  "type": "Feature",
  "properties": {
    "iso:country":"GB",
    "wof:name":"HA2 8QH",
    "wof:placetype":"postalcode"
},
  "geometry": {"coordinates":[-0.37075433103785,51.56136407902558],"type":"Point"}
}