{
  "type": "Feature",
  "properties": {
    "iso:country": "GB",
    "wof:name": "HU17 7QT",
    "wof:placetype": "postalcode"
  },
  "geometry": {"coordinates":[-0.51873,53.877156],"type":"Point"}
}
