{
  "type": "Feature",
  "properties": {
    "date:inception_lower": "2019-07-01",
    "date:inception_upper": "2019-07-01",
    "iso:country": "GB",
    "wof:name": "HU17 7QT",
    "wof:placetype": "postalcode"
  },
  "geometry": {"coordinates":[-0.51873,53.877147],"type":"Point"}
}
