{
  "type": "Feature",
  "properties": {
    "iso:country": "GB",
    "wof:name": "OX25 2DB",
    "wof:placetype": "postalcode"
  },
  "geometry": {"coordinates":[-1.153865,51.881144],"type":"Point"}
}
