{
  "type": "Feature",
  "properties": {
    "date:inception_lower": "1980-01-01",
    "date:inception_upper": "1980-01-01",
    "iso:country": "GB",
    "wof:name": "BA22 8SE",
    "wof:placetype": "postalcode"
  },
  "geometry": {"coordinates":[-2.681248,50.945129],"type":"Point"}
}
