{
  "type": "Feature",
  "properties": {
    "iso:country":"GB",
    "wof:name":"BA22 8SE",
    "wof:placetype":"postalcode"
},
  "geometry": {"coordinates":[-2.68124769839316,50.94512903166546],"type":"Point"}
}