{
  "type": "Feature",
  "properties": {
    "date:inception_lower": "1980-01-01",
    "date:inception_upper": "1980-01-01",
    "iso:country": "GB",
    "wof:name": "L39 3AT",
    "wof:placetype": "postalcode"
  },
  "geometry": {"coordinates":[-2.894242,53.571547],"type":"Point"}
}
