{
  "type": "Feature",
  "properties": {
    "iso:country":"GB",
    "wof:name":"L39 3AT",
    "wof:placetype":"postalcode"
},
  "geometry": {"coordinates":[-2.89424230140171,53.5715472666881],"type":"Point"}
}