{
  "type": "Feature",
  "properties": {
    "iso:country": "GB",
    "wof:name": "ML1 4FH",
    "wof:placetype": "postalcode"
  },
  "geometry": {"coordinates":[-3.968934,55.804071],"type":"Point"}
}
