{
  "type": "Feature",
  "properties": {
    "date:inception_lower":"2002-06-01",
    "date:inception_upper":"2002-06-30",
    "iso:country":"GB",
    "wof:name":"ML1 4FH",
    "wof:placetype":"postalcode"
},
  "geometry": {"coordinates":[-3.968934,55.804071],"type":"Point"}
}