{
  "type": "Feature",
  "properties": {
    "iso:country":"GB",
    "wof:name":"SP2 0LA",
    "wof:placetype":"postalcode"
},
  "geometry": {"coordinates":[-1.87244006332021,51.07557395095617],"type":"Point"}
}