{
  "type": "Feature",
  "properties": {
    "date:inception_lower":"2019-01-01",
    "date:inception_upper":"2019-01-31",
    "iso:country":"GB",
    "wof:name":"MK7 7AL",
    "wof:placetype":"postalcode"
},
  "geometry": {"coordinates":[-0.704703,52.022216],"type":"Point"}
}