{
  "type": "Feature",
  "properties": {
    "iso:country": "GB",
    "wof:name": "MK7 7AL",
    "wof:placetype": "postalcode"
  },
  "geometry": {"coordinates":[-0.704703,52.022216],"type":"Point"}
}
