{
  "type": "Feature",
  "properties": {
    "iso:country":"GB",
    "wof:name":"NE16 6AF",
    "wof:placetype":"postalcode"
},
  "geometry": {"coordinates":[-1.75633977559865,54.90206187741893],"type":"Point"}
}