{
  "type": "Feature",
  "properties": {
    "date:inception_lower": "1980-01-01",
    "date:inception_upper": "1980-01-01",
    "iso:country": "GB",
    "wof:name": "NE16 6AF",
    "wof:placetype": "postalcode"
  },
  "geometry": {"coordinates":[-1.75634,54.902062],"type":"Point"}
}
