{
  "type": "Feature",
  "properties": {
    "iso:country": "GB",
    "wof:name": "RG8 9ER",
    "wof:placetype": "postalcode"
  },
  "geometry": {"coordinates":[-1.135617,51.5191],"type":"Point"}
}
