{
  "type": "Feature",
  "properties": {
    "iso:country":"GB",
    "wof:name":"RG8 9ER",
    "wof:placetype":"postalcode"
},
  "geometry": {"coordinates":[-1.13561695891659,51.5191002336626],"type":"Point"}
}