{
  "type": "Feature",
  "properties": {
    "iso:country": "GB",
    "wof:name": "DY7 5HR",
    "wof:placetype": "postalcode"
  },
  "geometry": {"coordinates":[-2.251708,52.482319],"type":"Point"}
}
