{
  "type": "Feature",
  "properties": {
    "iso:country": "GB",
    "wof:name": "M11 2FB",
    "wof:placetype": "postalcode"
  },
  "geometry": {"coordinates":[-2.18348,53.474564],"type":"Point"}
}
