{
  "type": "Feature",
  "properties": {
    "date:inception_lower": "1992-08-01",
    "date:inception_upper": "1992-08-01",
    "iso:country": "GB",
    "wof:name": "M11 2FB",
    "wof:placetype": "postalcode"
  },
  "geometry": {"coordinates":[-2.18348,53.474564],"type":"Point"}
}
