{
  "type": "Feature",
  "properties": {
    "date:inception_lower": "2014-04-01",
    "date:inception_upper": "2014-04-01",
    "iso:country": "GB",
    "wof:name": "L8 5SP",
    "wof:placetype": "postalcode"
  },
  "geometry": {"coordinates":[-2.97679,53.392716],"type":"Point"}
}
