{
  "type": "Feature",
  "properties": {
    "iso:country":"GB",
    "wof:name":"L8 5SP",
    "wof:placetype":"postalcode"
},
  "geometry": {"coordinates":[-2.9767899768176,53.39271628011085],"type":"Point"}
}