{
  "type": "Feature",
  "properties": {
    "iso:country":"GB",
    "wof:name":"SL9 0BZ",
    "wof:placetype":"postalcode"
},
  "geometry": {"coordinates":[-0.55188948324113,51.61288021739626],"type":"Point"}
}