{
  "type": "Feature",
  "properties": {
    "iso:country": "GB",
    "wof:name": "SL9 0BZ",
    "wof:placetype": "postalcode"
  },
  "geometry": {"coordinates":[-0.551889,51.61288],"type":"Point"}
}
