{
  "type": "Feature",
  "properties": {
    "date:inception_lower":"1980-01-01",
    "date:inception_upper":"1980-01-31",
    "iso:country":"GB",
    "wof:name":"SE20 8HR",
    "wof:placetype":"postalcode"
},
  "geometry": {"coordinates":[-0.054262,51.414962],"type":"Point"}
}