{
  "type": "Feature",
  "properties": {
    "iso:country":"GB",
    "wof:name":"SE20 8HR",
    "wof:placetype":"postalcode"
},
  "geometry": {"coordinates":[-0.05426228285797,51.41496244727934],"type":"Point"}
}