{
  "type": "Feature",
  "properties": {
    "date:inception_lower": "1981-06-01",
    "date:inception_upper": "1981-06-01",
    "iso:country": "GB",
    "wof:name": "FY6 0QE",
    "wof:placetype": "postalcode"
  },
  "geometry": {"coordinates":[-2.977869,53.931113],"type":"Point"}
}
