{
  "type": "Feature",
  "properties": {
    "date:inception_lower": "1980-01-01",
    "date:inception_upper": "1980-01-01",
    "iso:country": "GB",
    "wof:name": "KW1 4TT",
    "wof:placetype": "postalcode"
  },
  "geometry": {"coordinates":[-3.323159,58.533897],"type":"Point"}
}
