{
  "type": "Feature",
  "properties": {
    "date:inception_lower": "1980-01-01",
    "date:inception_upper": "1980-01-01",
    "iso:country": "GB",
    "wof:name": "SP2 0RD",
    "wof:placetype": "postalcode"
  },
  "geometry": {"coordinates":[-1.878456,51.111108],"type":"Point"}
}
