{
  "type": "Feature",
  "properties": {
    "iso:country":"GB",
    "wof:name":"SP2 0RD",
    "wof:placetype":"postalcode"
},
  "geometry": {"coordinates":[-1.87845641561228,51.11110812072205],"type":"Point"}
}