{
  "type": "Feature",
  "properties": {
    "date:inception_lower":"1980-01-01",
    "date:inception_upper":"1980-01-31",
    "iso:country":"GB",
    "wof:name":"BL1 7RT",
    "wof:placetype":"postalcode"
},
  "geometry": {"coordinates":[-2.422849,53.611903],"type":"Point"}
}