{
  "type": "Feature",
  "properties": {
    "date:inception_lower": "1986-04-01",
    "date:inception_upper": "1986-04-01",
    "iso:country": "GB",
    "wof:name": "EN7 6HF",
    "wof:placetype": "postalcode"
  },
  "geometry": {"coordinates":[-0.062187,51.709185],"type":"Point"}
}
