{
  "type": "Feature",
  "properties": {
    "iso:country":"GB",
    "wof:name":"EN7 6HF",
    "wof:placetype":"postalcode"
},
  "geometry": {"coordinates":[-0.06218674440816,51.70918549628357],"type":"Point"}
}