{
  "type": "Feature",
  "properties": {
    "iso:country": "GB",
    "wof:name": "NE29 6AL",
    "wof:placetype": "postalcode"
  },
  "geometry": {"coordinates":[-1.468387,54.999329],"type":"Point"}
}
