{
  "type": "Feature",
  "properties": {
    "iso:country":"GB",
    "wof:name":"NE29 6AL",
    "wof:placetype":"postalcode"
},
  "geometry": {"coordinates":[-1.4683866500808,54.99932893091955],"type":"Point"}
}