{
  "type": "Feature",
  "properties": {
    "date:inception_lower":"1997-06-01",
    "date:inception_upper":"1997-06-30",
    "iso:country":"GB",
    "wof:name":"NE29 6AL",
    "wof:placetype":"postalcode"
},
  "geometry": {"coordinates":[-1.468387,54.999329],"type":"Point"}
}