{
  "type": "Feature",
  "properties": {
    "iso:country": "GB",
    "wof:name": "CA14 5HA",
    "wof:placetype": "postalcode"
  },
  "geometry": {"coordinates":[-3.564297,54.618469],"type":"Point"}
}
