{
  "type": "Feature",
  "properties": {
    "iso:country":"GB",
    "wof:name":"CA14 5HA",
    "wof:placetype":"postalcode"
},
  "geometry": {"coordinates":[-3.5642967156195,54.61846896952628],"type":"Point"}
}