{
  "type": "Feature",
  "properties": {
    "iso:country":"GB",
    "wof:name":"SW16 4NG",
    "wof:placetype":"postalcode"
},
  "geometry": {"coordinates":[-0.12823401136982,51.40205775552087],"type":"Point"}
}