{
  "type": "Feature",
  "properties": {
    "iso:country":"GB",
    "wof:name":"SW19 4QE",
    "wof:placetype":"postalcode"
},
  "geometry": {"coordinates":[-0.21710169354538,51.42414439142998],"type":"Point"}
}