{
  "type": "Feature",
  "properties": {
    "iso:country": "GB",
    "wof:name": "SW19 4QE",
    "wof:placetype": "postalcode"
  },
  "geometry": {"coordinates":[-0.217158,51.424172],"type":"Point"}
}
