{
  "type": "Feature",
  "properties": {
    "date:inception_lower": "1980-01-01",
    "date:inception_upper": "1980-01-01",
    "iso:country": "GB",
    "wof:name": "TA24 8NF",
    "wof:placetype": "postalcode"
  },
  "geometry": {"coordinates":[-3.593731,51.212301],"type":"Point"}
}
