{
  "type": "Feature",
  "properties": {
    "iso:country":"GB",
    "wof:name":"NE32 4TY",
    "wof:placetype":"postalcode"
},
  "geometry": {"coordinates":[-1.48919773908205,54.95586139552939],"type":"Point"}
}