{
  "type": "Feature",
  "properties": {
    "iso:country":"GB",
    "wof:name":"TA20 3ED",
    "wof:placetype":"postalcode"
},
  "geometry": {"coordinates":[-3.02944181156549,50.87524982571754],"type":"Point"}
}