{
  "type": "Feature",
  "properties": {
    "date:inception_lower": "1980-01-01",
    "date:inception_upper": "1980-01-01",
    "iso:country": "GB",
    "wof:name": "TA20 3ED",
    "wof:placetype": "postalcode"
  },
  "geometry": {"coordinates":[-3.029442,50.87525],"type":"Point"}
}
