{
  "type": "Feature",
  "properties": {
    "iso:country":"GB",
    "wof:name":"IP24 2JN",
    "wof:placetype":"postalcode"
},
  "geometry": {"coordinates":[0.76107855418667,52.42058529292778],"type":"Point"}
}