{
  "type": "Feature",
  "properties": {
    "iso:country":"GB",
    "wof:name":"IG3 8DR",
    "wof:placetype":"postalcode"
},
  "geometry": {"coordinates":[0.0997503112024,51.56204369675164],"type":"Point"}
}