{
  "type": "Feature",
  "properties": {
    "date:inception_lower": "1995-12-01",
    "date:inception_upper": "1995-12-01",
    "iso:country": "GB",
    "wof:name": "PA1 1SU",
    "wof:placetype": "postalcode"
  },
  "geometry": {"coordinates":[-4.418082,55.840612],"type":"Point"}
}
