{
  "type": "Feature",
  "properties": {
    "iso:country":"GB",
    "wof:name":"PL7 2AP",
    "wof:placetype":"postalcode"
},
  "geometry": {"coordinates":[-4.05338389116354,50.38817332634986],"type":"Point"}
}