{
  "type": "Feature",
  "properties": {
    "iso:country":"GB",
    "wof:name":"ME8 7SY",
    "wof:placetype":"postalcode"
},
  "geometry": {"coordinates":[0.60835763412479,51.36848415334948],"type":"Point"}
}