{
  "type": "Feature",
  "properties": {
    "iso:country":"GB",
    "wof:name":"BS11 9SF",
    "wof:placetype":"postalcode"
},
  "geometry": {"coordinates":[-2.67620853220552,51.48831326589893],"type":"Point"}
}