{
  "type": "Feature",
  "properties": {
    "iso:country": "GB",
    "wof:name": "BS11 9SF",
    "wof:placetype": "postalcode"
  },
  "geometry": {"coordinates":[-2.676212,51.488312],"type":"Point"}
}
