{
  "type": "Feature",
  "properties": {
    "iso:country":"GB",
    "wof:name":"E10 7NU",
    "wof:placetype":"postalcode"
},
  "geometry": {"coordinates":[-0.03372274349282,51.5670272744923],"type":"Point"}
}