{
  "type": "Feature",
  "properties": {
    "date:inception_lower": "1980-01-01",
    "date:inception_upper": "1980-01-01",
    "iso:country": "GB",
    "wof:name": "E10 7NU",
    "wof:placetype": "postalcode"
  },
  "geometry": {"coordinates":[-0.033401,51.567168],"type":"Point"}
}
