{
  "type": "Feature",
  "properties": {
    "iso:country": "GB",
    "wof:name": "E10 7NU",
    "wof:placetype": "postalcode"
  },
  "geometry": {"coordinates":[-0.033723,51.567027],"type":"Point"}
}
