{
  "type": "Feature",
  "properties": {
    "iso:country":"GB",
    "wof:name":"S63 9JA",
    "wof:placetype":"postalcode"
},
  "geometry": {"coordinates":[-1.29845981879974,53.53507526968861],"type":"Point"}
}