{
  "type": "Feature",
  "properties": {
    "date:inception_lower":"1995-12-01",
    "date:inception_upper":"1995-12-31",
    "iso:country":"GB",
    "wof:name":"DG11 2BY",
    "wof:placetype":"postalcode"
},
  "geometry": {"coordinates":[-3.355487,55.123344],"type":"Point"}
}