{
  "type": "Feature",
  "properties": {
    "iso:country": "GB",
    "wof:name": "DY14 9UU",
    "wof:placetype": "postalcode"
  },
  "geometry": {"coordinates":[-2.386803,52.372509],"type":"Point"}
}
