{
  "type": "Feature",
  "properties": {
    "iso:country":"GB",
    "wof:name":"DY14 9UU",
    "wof:placetype":"postalcode"
},
  "geometry": {"coordinates":[-2.38680292500432,52.37250882347458],"type":"Point"}
}