{
  "type": "Feature",
  "properties": {
    "iso:country": "GB",
    "wof:name": "CV47 2DH",
    "wof:placetype": "postalcode"
  },
  "geometry": {"coordinates":[-1.402825,52.241896],"type":"Point"}
}
