{
  "type": "Feature",
  "properties": {
    "iso:country":"GB",
    "wof:name":"CV47 2DH",
    "wof:placetype":"postalcode"
},
  "geometry": {"coordinates":[-1.40282497334665,52.24189566039657],"type":"Point"}
}