{
  "type": "Feature",
  "properties": {
    "iso:country": "GB",
    "wof:name": "HR2 0EG",
    "wof:placetype": "postalcode"
  },
  "geometry": {"coordinates":[-2.890197,51.955146],"type":"Point"}
}
