{
  "type": "Feature",
  "properties": {
    "iso:country":"GB",
    "wof:name":"HR2 0EG",
    "wof:placetype":"postalcode"
},
  "geometry": {"coordinates":[-2.89019749326107,51.95514555765109],"type":"Point"}
}