{
  "type": "Feature",
  "properties": {
    "date:inception_lower": "1987-04-01",
    "date:inception_upper": "1987-04-01",
    "iso:country": "GB",
    "wof:name": "HR2 0EG",
    "wof:placetype": "postalcode"
  },
  "geometry": {"coordinates":[-2.890197,51.955146],"type":"Point"}
}
