{
  "type": "Feature",
  "properties": {
    "iso:country":"GB",
    "wof:name":"DL6 1RT",
    "wof:placetype":"postalcode"
},
  "geometry": {"coordinates":[-1.43196845070739,54.33981243653176],"type":"Point"}
}