{
  "type": "Feature",
  "properties": {
    "iso:country": "GB",
    "wof:name": "BB4 4PX",
    "wof:placetype": "postalcode"
  },
  "geometry": {"coordinates":[-2.330071,53.691199],"type":"Point"}
}
