{
  "type": "Feature",
  "properties": {
    "iso:country":"GB",
    "wof:name":"DE45 1NR",
    "wof:placetype":"postalcode"
},
  "geometry": {"coordinates":[-1.68138861788417,53.2486947822673],"type":"Point"}
}