{
  "type": "Feature",
  "properties": {
    "date:inception_lower": "1992-08-01",
    "date:inception_upper": "1992-08-01",
    "iso:country": "GB",
    "wof:name": "DE45 1NR",
    "wof:placetype": "postalcode"
  },
  "geometry": {"coordinates":[-1.681389,53.248695],"type":"Point"}
}
