{
  "type": "Feature",
  "properties": {
    "iso:country":"GB",
    "wof:name":"PR2 1UQ",
    "wof:placetype":"postalcode"
},
  "geometry": {"coordinates":[-2.75655016982945,53.769127409249],"type":"Point"}
}