{
  "type": "Feature",
  "properties": {
    "date:inception_lower": "1980-01-01",
    "date:inception_upper": "1980-01-01",
    "iso:country": "GB",
    "wof:name": "PR2 1UQ",
    "wof:placetype": "postalcode"
  },
  "geometry": {"coordinates":[-2.75655,53.769127],"type":"Point"}
}
