{
  "type": "Feature",
  "properties": {
    "iso:country": "GB",
    "wof:name": "SO53 4HG",
    "wof:placetype": "postalcode"
  },
  "geometry": {"coordinates":[-1.408888,50.98608],"type":"Point"}
}
