{
  "type": "Feature",
  "properties": {
    "date:inception_lower":"1999-06-01",
    "date:inception_upper":"1999-06-30",
    "iso:country":"GB",
    "wof:name":"SO53 4HG",
    "wof:placetype":"postalcode"
},
  "geometry": {"coordinates":[-1.408888,50.98608],"type":"Point"}
}