{
  "type": "Feature",
  "properties": {
    "iso:country":"GB",
    "wof:name":"DL8 5LQ",
    "wof:placetype":"postalcode"
},
  "geometry": {"coordinates":[-1.82233556091451,54.31443353656527],"type":"Point"}
}