{
  "type": "Feature",
  "properties": {
    "date:inception_lower": "2000-06-01",
    "date:inception_upper": "2000-06-01",
    "iso:country": "GB",
    "wof:name": "DL8 5LQ",
    "wof:placetype": "postalcode"
  },
  "geometry": {"coordinates":[-1.822336,54.314434],"type":"Point"}
}
