{
  "type": "Feature",
  "properties": {
    "iso:country":"GB",
    "wof:name":"L1 9AH",
    "wof:placetype":"postalcode"
},
  "geometry": {"coordinates":[-2.97593768052179,53.40015710367336],"type":"Point"}
}