{
  "type": "Feature",
  "properties": {
    "date:inception_lower": "2014-11-01",
    "date:inception_upper": "2014-11-01",
    "iso:country": "GB",
    "wof:name": "L1 9AH",
    "wof:placetype": "postalcode"
  },
  "geometry": {"coordinates":[-2.975938,53.400157],"type":"Point"}
}
