{
  "type": "Feature",
  "properties": {
    "iso:country":"GB",
    "wof:name":"IV30 8QW",
    "wof:placetype":"postalcode"
},
  "geometry": {"coordinates":[-3.26668458856771,57.63524143349873],"type":"Point"}
}