{
  "type": "Feature",
  "properties": {
    "date:inception_lower": "1980-01-01",
    "date:inception_upper": "1980-01-01",
    "iso:country": "GB",
    "wof:name": "TA1 3LX",
    "wof:placetype": "postalcode"
  },
  "geometry": {"coordinates":[-3.099479,51.014375],"type":"Point"}
}
