{
  "type": "Feature",
  "properties": {
    "iso:country": "GB",
    "wof:name": "TA1 3LX",
    "wof:placetype": "postalcode"
  },
  "geometry": {"coordinates":[-3.099479,51.014375],"type":"Point"}
}
