{
  "type": "Feature",
  "properties": {
    "date:inception_lower": "1980-01-01",
    "date:inception_upper": "1980-01-01",
    "iso:country": "GB",
    "wof:name": "SK11 0JF",
    "wof:placetype": "postalcode"
  },
  "geometry": {"coordinates":[-2.125621,53.222446],"type":"Point"}
}
