{
  "type": "Feature",
  "properties": {
    "iso:country":"GB",
    "wof:name":"SK11 0JF",
    "wof:placetype":"postalcode"
},
  "geometry": {"coordinates":[-2.12562106522761,53.22244646164372],"type":"Point"}
}