{
  "type": "Feature",
  "properties": {
    "iso:country":"GB",
    "wof:name":"GL50 4SS",
    "wof:placetype":"postalcode"
},
  "geometry": {"coordinates":[-2.08812875562177,51.9144064834887],"type":"Point"}
}