{
  "type": "Feature",
  "properties": {
    "date:inception_lower": "1980-01-01",
    "date:inception_upper": "1980-01-01",
    "iso:country": "GB",
    "wof:name": "WS14 9NH",
    "wof:placetype": "postalcode"
  },
  "geometry": {"coordinates":[-1.762865,52.675056],"type":"Point"}
}
