{
  "type": "Feature",
  "properties": {
    "iso:country": "GB",
    "wof:name": "PH2 8ST",
    "wof:placetype": "postalcode"
  },
  "geometry": {"coordinates":[-3.437618,56.393653],"type":"Point"}
}
