{
  "type": "Feature",
  "properties": {
    "date:inception_lower": "2010-09-01",
    "date:inception_upper": "2010-09-01",
    "iso:country": "GB",
    "wof:name": "PH2 8ST",
    "wof:placetype": "postalcode"
  },
  "geometry": {"coordinates":[-3.437618,56.393653],"type":"Point"}
}
