{
  "type": "Feature",
  "properties": {
    "iso:country":"GB",
    "wof:name":"M22 9WJ",
    "wof:placetype":"postalcode"
},
  "geometry": {"coordinates":[-2.26401545936889,53.38807995830714],"type":"Point"}
}