{
  "type": "Feature",
  "properties": {
    "iso:country": "GB",
    "wof:name": "M22 9WJ",
    "wof:placetype": "postalcode"
  },
  "geometry": {"coordinates":[-2.264015,53.38808],"type":"Point"}
}
