{
  "type": "Feature",
  "properties": {
    "iso:country":"GB",
    "wof:name":"B67 5HZ",
    "wof:placetype":"postalcode"
},
  "geometry": {"coordinates":[-1.97691296882411,52.48005893886626],"type":"Point"}
}