{
  "type": "Feature",
  "properties": {
    "iso:country": "GB",
    "wof:name": "BS31 2SB",
    "wof:placetype": "postalcode"
  },
  "geometry": {"coordinates":[-2.510026,51.406539],"type":"Point"}
}
