{
  "type": "Feature",
  "properties": {
    "iso:country":"GB",
    "wof:name":"BS31 2SB",
    "wof:placetype":"postalcode"
},
  "geometry": {"coordinates":[-2.51002585281699,51.40653899844151],"type":"Point"}
}