{
  "type": "Feature",
  "properties": {
    "iso:country":"GB",
    "wof:name":"SP9 7NF",
    "wof:placetype":"postalcode"
},
  "geometry": {"coordinates":[-1.65609061068339,51.24283046416377],"type":"Point"}
}