{
  "type": "Feature",
  "properties": {
    "iso:country": "GB",
    "wof:name": "SP9 7NF",
    "wof:placetype": "postalcode"
  },
  "geometry": {"coordinates":[-1.656091,51.24283],"type":"Point"}
}
