{
  "type": "Feature",
  "properties": {
    "iso:country":"GB",
    "wof:name":"L3 2DU",
    "wof:placetype":"postalcode"
},
  "geometry": {"coordinates":[-2.98436922002218,53.4122678732898],"type":"Point"}
}