{
  "type": "Feature",
  "properties": {
    "date:inception_lower":"1980-01-01",
    "date:inception_upper":"1980-01-31",
    "iso:country":"GB",
    "wof:name":"DT10 2AG",
    "wof:placetype":"postalcode"
},
  "geometry": {"coordinates":[-2.333846,50.90487],"type":"Point"}
}