{
  "type": "Feature",
  "properties": {
    "iso:country": "GB",
    "wof:name": "B90 4TZ",
    "wof:placetype": "postalcode"
  },
  "geometry": {"coordinates":[-1.793562,52.389918],"type":"Point"}
}
