{
  "type": "Feature",
  "properties": {
    "date:inception_lower":"1984-10-01",
    "date:inception_upper":"1984-10-31",
    "iso:country":"GB",
    "wof:name":"B90 4TZ",
    "wof:placetype":"postalcode"
},
  "geometry": {"coordinates":[-1.793562,52.389918],"type":"Point"}
}