{
  "type": "Feature",
  "properties": {
    "iso:country":"GB",
    "wof:name":"AB39 2NB",
    "wof:placetype":"postalcode"
},
  "geometry": {"coordinates":[-2.22778392839802,56.96469741620103],"type":"Point"}
}