{
  "type": "Feature",
  "properties": {
    "iso:country": "GB",
    "wof:name": "ST18 9QB",
    "wof:placetype": "postalcode"
  },
  "geometry": {"coordinates":[-2.184612,52.844557],"type":"Point"}
}
