{
  "type": "Feature",
  "properties": {
    "iso:country":"GB",
    "wof:name":"ST18 9QB",
    "wof:placetype":"postalcode"
},
  "geometry": {"coordinates":[-2.18461174610527,52.84455657573589],"type":"Point"}
}