{
  "type": "Feature",
  "properties": {
    "iso:country":"GB",
    "wof:name":"BS21 7HT",
    "wof:placetype":"postalcode"
},
  "geometry": {"coordinates":[-2.85000392721459,51.44479500491256],"type":"Point"}
}