{
  "type": "Feature",
  "properties": {
    "iso:country":"GB",
    "wof:name":"LS14 2BB",
    "wof:placetype":"postalcode"
},
  "geometry": {"coordinates":[-1.45560345804417,53.82607928384601],"type":"Point"}
}