{
  "type": "Feature",
  "properties": {
    "iso:country":"GB",
    "wof:name":"LL15 2NP",
    "wof:placetype":"postalcode"
},
  "geometry": {"coordinates":[-3.31036179188376,53.10969672139252],"type":"Point"}
}