{
  "type": "Feature",
  "properties": {
    "date:inception_lower": "1980-01-01",
    "date:inception_upper": "1980-01-01",
    "iso:country": "GB",
    "wof:name": "LL15 2NP",
    "wof:placetype": "postalcode"
  },
  "geometry": {"coordinates":[-3.310064,53.109742],"type":"Point"}
}
