{
  "type": "Feature",
  "properties": {
    "iso:country":"GB",
    "wof:name":"W1S 2XB",
    "wof:placetype":"postalcode"
},
  "geometry": {"coordinates":[-0.14122717251403,51.51305319367541],"type":"Point"}
}