{
  "type": "Feature",
  "properties": {
    "date:inception_lower": "1980-01-01",
    "date:inception_upper": "1980-01-01",
    "iso:country": "GB",
    "wof:name": "NG32 1AL",
    "wof:placetype": "postalcode"
  },
  "geometry": {"coordinates":[-0.692587,52.862392],"type":"Point"}
}
