{
  "type": "Feature",
  "properties": {
    "iso:country":"GB",
    "wof:name":"LA23 1JQ",
    "wof:placetype":"postalcode"
},
  "geometry": {"coordinates":[-2.89186523783316,54.38766796139198],"type":"Point"}
}