{
  "type": "Feature",
  "properties": {
    "date:inception_lower": "1980-01-01",
    "date:inception_upper": "1980-01-01",
    "iso:country": "GB",
    "wof:name": "LA23 1JQ",
    "wof:placetype": "postalcode"
  },
  "geometry": {"coordinates":[-2.891865,54.387668],"type":"Point"}
}
