{
  "type": "Feature",
  "properties": {
    "date:inception_lower": "1980-01-01",
    "date:inception_upper": "1980-01-01",
    "iso:country": "GB",
    "wof:name": "SK5 8DA",
    "wof:placetype": "postalcode"
  },
  "geometry": {"coordinates":[-2.134325,53.423451],"type":"Point"}
}
