{
  "type": "Feature",
  "properties": {
    "iso:country":"GB",
    "wof:name":"SK5 8DA",
    "wof:placetype":"postalcode"
},
  "geometry": {"coordinates":[-2.13432490883108,53.42345082020952],"type":"Point"}
}