{
  "type": "Feature",
  "properties": {
    "iso:country":"GB",
    "wof:name":"DE11 7DZ",
    "wof:placetype":"postalcode"
},
  "geometry": {"coordinates":[-1.53054987796247,52.76603192340092],"type":"Point"}
}