{
  "type": "Feature",
  "properties": {
    "date:inception_lower": "1990-02-01",
    "date:inception_upper": "1990-02-01",
    "iso:country": "GB",
    "wof:name": "SY1 1BY",
    "wof:placetype": "postalcode"
  },
  "geometry": {"coordinates":[-2.754917,52.708897],"type":"Point"}
}
