{
  "type": "Feature",
  "properties": {
    "iso:country": "GB",
    "wof:name": "SY1 1BY",
    "wof:placetype": "postalcode"
  },
  "geometry": {"coordinates":[-2.754919,52.708891],"type":"Point"}
}
