{
  "type": "Feature",
  "properties": {
    "iso:country":"GB",
    "wof:name":"WV6 8HX",
    "wof:placetype":"postalcode"
},
  "geometry": {"coordinates":[-2.18568018882971,52.59028385499596],"type":"Point"}
}