{
  "type": "Feature",
  "properties": {
    "iso:country":"GB",
    "wof:name":"LA23 3JU",
    "wof:placetype":"postalcode"
},
  "geometry": {"coordinates":[-2.91696346150106,54.34265939700219],"type":"Point"}
}