{
  "type": "Feature",
  "properties": {
    "iso:country":"GB",
    "wof:name":"SO15 3FD",
    "wof:placetype":"postalcode"
},
  "geometry": {"coordinates":[-1.42152537143727,50.91258500093181],"type":"Point"}
}