{
  "type": "Feature",
  "properties": {
    "iso:country": "GB",
    "wof:name": "SO15 3FD",
    "wof:placetype": "postalcode"
  },
  "geometry": {"coordinates":[-1.421525,50.912585],"type":"Point"}
}
