{
  "type": "Feature",
  "properties": {
    "date:inception_lower": "1994-12-01",
    "date:inception_upper": "1994-12-01",
    "iso:country": "GB",
    "wof:name": "SO15 3FD",
    "wof:placetype": "postalcode"
  },
  "geometry": {"coordinates":[-1.42146,50.912558],"type":"Point"}
}
