{
  "type": "Feature",
  "properties": {
    "iso:country":"GB",
    "wof:name":"W1F 8TS",
    "wof:placetype":"postalcode"
},
  "geometry": {"coordinates":[-0.13556647639278,51.51403345572969],"type":"Point"}
}