{
  "type": "Feature",
  "properties": {
    "iso:country": "GB",
    "wof:name": "WR2 5BL",
    "wof:placetype": "postalcode"
  },
  "geometry": {"coordinates":[-2.23685,52.189444],"type":"Point"}
}
