{
  "type": "Feature",
  "properties": {
    "date:inception_lower":"1980-01-01",
    "date:inception_upper":"1980-01-31",
    "iso:country":"GB",
    "wof:name":"ST14 5BA",
    "wof:placetype":"postalcode"
},
  "geometry": {"coordinates":[-1.882179,52.920306],"type":"Point"}
}