{
  "type": "Feature",
  "properties": {
    "iso:country":"GB",
    "wof:name":"EX8 4JD",
    "wof:placetype":"postalcode"
},
  "geometry": {"coordinates":[-3.39769651982775,50.6340366631142],"type":"Point"}
}