{
  "type": "Feature",
  "properties": {
    "iso:country": "GB",
    "wof:name": "EX8 4JD",
    "wof:placetype": "postalcode"
  },
  "geometry": {"coordinates":[-3.397696,50.634037],"type":"Point"}
}
