{
  "type": "Feature",
  "properties": {
    "iso:country": "GB",
    "wof:name": "LA22 0EY",
    "wof:placetype": "postalcode"
  },
  "geometry": {"coordinates":[-2.961804,54.41961],"type":"Point"}
}
