{
  "type": "Feature",
  "properties": {
    "date:inception_lower":"1980-01-01",
    "date:inception_upper":"1980-01-31",
    "iso:country":"GB",
    "wof:name":"BN3 8BZ",
    "wof:placetype":"postalcode"
},
  "geometry": {"coordinates":[-0.197584,50.850364],"type":"Point"}
}