{
  "type": "Feature",
  "properties": {
    "iso:country":"GB",
    "wof:name":"BN3 8BZ",
    "wof:placetype":"postalcode"
},
  "geometry": {"coordinates":[-0.19758451797213,50.85036440128388],"type":"Point"}
}