{
  "type": "Feature",
  "properties": {
    "iso:country":"GB",
    "wof:name":"KT6 6PF",
    "wof:placetype":"postalcode"
},
  "geometry": {"coordinates":[-0.31272952873694,51.38729702542156],"type":"Point"}
}