{
  "type": "Feature",
  "properties": {
    "iso:country": "GB",
    "wof:name": "GU24 9FZ",
    "wof:placetype": "postalcode"
  },
  "geometry": {"coordinates":[-0.63516,51.342784],"type":"Point"}
}
