{
  "type": "Feature",
  "properties": {
    "date:inception_lower": "2021-06-01",
    "date:inception_upper": "2021-06-01",
    "iso:country": "GB",
    "wof:name": "TN24 9FH",
    "wof:placetype": "postalcode"
  },
  "geometry": {"coordinates":[0.903155,51.158995],"type":"Point"}
}
