{
  "type": "Feature",
  "properties": {
    "date:inception_lower":"2018-04-01",
    "date:inception_upper":"2018-04-30",
    "iso:country":"GB",
    "wof:name":"SW17 0QP",
    "wof:placetype":"postalcode"
},
  "geometry": {"coordinates":[-0.171292,51.427404],"type":"Point"}
}