{
  "type": "Feature",
  "properties": {
    "date:inception_lower": "1980-01-01",
    "date:inception_upper": "1980-01-01",
    "iso:country": "GB",
    "wof:name": "GL1 5AA",
    "wof:placetype": "postalcode"
  },
  "geometry": {"coordinates":[-2.249928,51.857583],"type":"Point"}
}
