{
  "type": "Feature",
  "properties": {
    "iso:country": "GB",
    "wof:name": "GL1 5AA",
    "wof:placetype": "postalcode"
  },
  "geometry": {"coordinates":[-2.249928,51.857583],"type":"Point"}
}
