{
  "type": "Feature",
  "properties": {
    "iso:country":"GB",
    "wof:name":"GL1 5AA",
    "wof:placetype":"postalcode"
},
  "geometry": {"coordinates":[-2.24990147611201,51.85753123344141],"type":"Point"}
}