{
  "type": "Feature",
  "properties": {
    "iso:country": "GB",
    "wof:name": "CF31 2ET",
    "wof:placetype": "postalcode"
  },
  "geometry": {"coordinates":[-3.565161,51.514104],"type":"Point"}
}
