{
  "type": "Feature",
  "properties": {
    "date:inception_lower":"2004-10-01",
    "date:inception_upper":"2004-10-31",
    "iso:country":"GB",
    "wof:name":"CF31 2ET",
    "wof:placetype":"postalcode"
},
  "geometry": {"coordinates":[-3.565161,51.514104],"type":"Point"}
}