{
  "type": "Feature",
  "properties": {
    "iso:country":"GB",
    "wof:name":"CF31 2ET",
    "wof:placetype":"postalcode"
},
  "geometry": {"coordinates":[-3.56514581211259,51.51412138413755],"type":"Point"}
}