{
  "type": "Feature",
  "properties": {
    "iso:country":"GB",
    "wof:name":"NE26 3UH",
    "wof:placetype":"postalcode"
},
  "geometry": {"coordinates":[-1.46106336975195,55.05353773894814],"type":"Point"}
}