{
  "type": "Feature",
  "properties": {
    "iso:country": "GB",
    "wof:name": "NE26 3UH",
    "wof:placetype": "postalcode"
  },
  "geometry": {"coordinates":[-1.461063,55.053538],"type":"Point"}
}
