{
  "type": "Feature",
  "properties": {
    "iso:country":"GB",
    "wof:name":"GU51 4JE",
    "wof:placetype":"postalcode"
},
  "geometry": {"coordinates":[-0.84307839040265,51.28220341817885],"type":"Point"}
}