{
  "type": "Feature",
  "properties": {
    "iso:country": "GB",
    "wof:name": "FK19 8QD",
    "wof:placetype": "postalcode"
  },
  "geometry": {"coordinates":[-4.289268,56.379511],"type":"Point"}
}
