{
  "type": "Feature",
  "properties": {
    "date:inception_lower": "1980-01-01",
    "date:inception_upper": "1980-01-01",
    "iso:country": "GB",
    "wof:name": "CA16 6PB",
    "wof:placetype": "postalcode"
  },
  "geometry": {"coordinates":[-2.389609,54.534432],"type":"Point"}
}
