{
  "type": "Feature",
  "properties": {
    "iso:country":"GB",
    "wof:name":"LN9 6HE",
    "wof:placetype":"postalcode"
},
  "geometry": {"coordinates":[-0.11295024996468,53.20520189818338],"type":"Point"}
}