{
  "type": "Feature",
  "properties": {
    "iso:country":"GB",
    "wof:name":"CB5 8PQ",
    "wof:placetype":"postalcode"
},
  "geometry": {"coordinates":[0.16208420148133,52.21671714548515],"type":"Point"}
}