{
  "type": "Feature",
  "properties": {
    "iso:country":"GB",
    "wof:name":"IP25 7SY",
    "wof:placetype":"postalcode"
},
  "geometry": {"coordinates":[0.94493855980037,52.61596997841423],"type":"Point"}
}