{
  "type": "Feature",
  "properties": {
    "iso:country":"GB",
    "wof:name":"CO10 7DE",
    "wof:placetype":"postalcode"
},
  "geometry": {"coordinates":[0.58820503395656,52.05355241075777],"type":"Point"}
}