{
  "type": "Feature",
  "properties": {
    "iso:country": "GB",
    "wof:name": "CO10 7DE",
    "wof:placetype": "postalcode"
  },
  "geometry": {"coordinates":[0.588205,52.053552],"type":"Point"}
}
