{
  "type": "Feature",
  "properties": {
    "iso:country": "GB",
    "wof:name": "NR10 5QW",
    "wof:placetype": "postalcode"
  },
  "geometry": {"coordinates":[1.234703,52.747921],"type":"Point"}
}
