{
  "type": "Feature",
  "properties": {
    "iso:country":"GB",
    "wof:name":"NR10 5QW",
    "wof:placetype":"postalcode"
},
  "geometry": {"coordinates":[1.23470307792472,52.74792097731802],"type":"Point"}
}