{
  "type": "Feature",
  "properties": {
    "date:inception_lower": "1980-01-01",
    "date:inception_upper": "1980-01-01",
    "iso:country": "GB",
    "wof:name": "KA1 5EA",
    "wof:placetype": "postalcode"
  },
  "geometry": {"coordinates":[-4.444329,55.594292],"type":"Point"}
}
