{
  "type": "Feature",
  "properties": {
    "iso:country":"GB",
    "wof:name":"KA1 5EA",
    "wof:placetype":"postalcode"
},
  "geometry": {"coordinates":[-4.44432916220356,55.59429187660734],"type":"Point"}
}