{
  "type": "Feature",
  "properties": {
    "iso:country": "GB",
    "wof:name": "NG5 6NJ",
    "wof:placetype": "postalcode"
  },
  "geometry": {"coordinates":[-1.126146,52.999254],"type":"Point"}
}
