{
  "type": "Feature",
  "properties": {
    "iso:country":"GB",
    "wof:name":"NG5 6NJ",
    "wof:placetype":"postalcode"
},
  "geometry": {"coordinates":[-1.12614638451017,52.99925357141281],"type":"Point"}
}