{
  "type": "Feature",
  "properties": {
    "iso:country": "GB",
    "wof:name": "LL77 7ER",
    "wof:placetype": "postalcode"
  },
  "geometry": {"coordinates":[-4.311857,53.25646],"type":"Point"}
}
