{
  "type": "Feature",
  "properties": {
    "date:inception_lower":"1980-01-01",
    "date:inception_upper":"1980-01-31",
    "iso:country":"GB",
    "wof:name":"PR7 5PX",
    "wof:placetype":"postalcode"
},
  "geometry": {"coordinates":[-2.737475,53.619878],"type":"Point"}
}