{
  "type": "Feature",
  "properties": {
    "iso:country":"GB",
    "wof:name":"PR7 5PX",
    "wof:placetype":"postalcode"
},
  "geometry": {"coordinates":[-2.73747463858035,53.61987818508994],"type":"Point"}
}