{
  "type": "Feature",
  "properties": {
    "date:inception_lower":"1980-01-01",
    "date:inception_upper":"1980-01-31",
    "iso:country":"GB",
    "wof:name":"CT4 6LL",
    "wof:placetype":"postalcode"
},
  "geometry": {"coordinates":[1.149944,51.18991],"type":"Point"}
}