{
  "type": "Feature",
  "properties": {
    "iso:country": "GB",
    "wof:name": "CT4 6LL",
    "wof:placetype": "postalcode"
  },
  "geometry": {"coordinates":[1.149976,51.189954],"type":"Point"}
}
