{
  "type": "Feature",
  "properties": {
    "iso:country": "GB",
    "wof:name": "NG20 8RR",
    "wof:placetype": "postalcode"
  },
  "geometry": {"coordinates":[-1.213194,53.19829],"type":"Point"}
}
