{
  "type": "Feature",
  "properties": {
    "date:inception_lower":"1980-01-01",
    "date:inception_upper":"1980-01-31",
    "iso:country":"GB",
    "wof:name":"NG20 8RR",
    "wof:placetype":"postalcode"
},
  "geometry": {"coordinates":[-1.213194,53.19829],"type":"Point"}
}