{
  "type": "Feature",
  "properties": {
    "iso:country":"GB",
    "wof:name":"SE12 8TF",
    "wof:placetype":"postalcode"
},
  "geometry": {"coordinates":[0.01224415671299,51.45605150912911],"type":"Point"}
}