{
  "type": "Feature",
  "properties": {
    "iso:country":"GB",
    "wof:name":"DN35 7TF",
    "wof:placetype":"postalcode"
},
  "geometry": {"coordinates":[-0.0537609680024,53.56578547655792],"type":"Point"}
}