{
  "type": "Feature",
  "properties": {
    "date:inception_lower": "1980-01-01",
    "date:inception_upper": "1980-01-01",
    "iso:country": "GB",
    "wof:name": "DN35 7TF",
    "wof:placetype": "postalcode"
  },
  "geometry": {"coordinates":[-0.053761,53.565785],"type":"Point"}
}
