{
  "type": "Feature",
  "properties": {
    "iso:country":"GB",
    "wof:name":"M25 0JY",
    "wof:placetype":"postalcode"
},
  "geometry": {"coordinates":[-2.26719940296503,53.52172290651513],"type":"Point"}
}