{
  "type": "Feature",
  "properties": {
    "date:inception_lower": "1994-05-01",
    "date:inception_upper": "1994-05-01",
    "iso:country": "GB",
    "wof:name": "M25 0JY",
    "wof:placetype": "postalcode"
  },
  "geometry": {"coordinates":[-2.267199,53.521723],"type":"Point"}
}
