{
  "type": "Feature",
  "properties": {
    "iso:country":"GB",
    "wof:name":"KW16 3NJ",
    "wof:placetype":"postalcode"
},
  "geometry": {"coordinates":[-3.33031355876341,58.91193306156973],"type":"Point"}
}