{
  "type": "Feature",
  "properties": {
    "iso:country":"GB",
    "wof:name":"KA15 2EA",
    "wof:placetype":"postalcode"
},
  "geometry": {"coordinates":[-4.63030631019178,55.7587885700804],"type":"Point"}
}