{
  "type": "Feature",
  "properties": {
    "iso:country": "GB",
    "wof:name": "LE16 7FA",
    "wof:placetype": "postalcode"
  },
  "geometry": {"coordinates":[-0.8645,52.552299],"type":"Point"}
}
