{
  "type": "Feature",
  "properties": {
    "iso:country":"GB",
    "wof:name":"CH2 3LR",
    "wof:placetype":"postalcode"
},
  "geometry": {"coordinates":[-2.86019495886776,53.20572545089184],"type":"Point"}
}