{
  "type": "Feature",
  "properties": {
    "iso:country":"GB",
    "wof:name":"NG9 5AJ",
    "wof:placetype":"postalcode"
},
  "geometry": {"coordinates":[-1.22013471581476,52.91424638359518],"type":"Point"}
}