{
  "type": "Feature",
  "properties": {
    "iso:country": "GB",
    "wof:name": "IG10 3BU",
    "wof:placetype": "postalcode"
  },
  "geometry": {"coordinates":[0.061974,51.637182],"type":"Point"}
}
