{
  "type": "Feature",
  "properties": {
    "date:inception_lower": "1980-01-01",
    "date:inception_upper": "1980-01-01",
    "iso:country": "GB",
    "wof:name": "NW4 2HR",
    "wof:placetype": "postalcode"
  },
  "geometry": {"coordinates":[-0.21765,51.585099],"type":"Point"}
}
