{
  "type": "Feature",
  "properties": {
    "iso:country":"GB",
    "wof:name":"NW4 2HR",
    "wof:placetype":"postalcode"
},
  "geometry": {"coordinates":[-0.21765036605181,51.58509928592492],"type":"Point"}
}