{
  "type": "Feature",
  "properties": {
    "date:inception_lower": "1994-12-01",
    "date:inception_upper": "1994-12-01",
    "iso:country": "GB",
    "wof:name": "SO50 6AD",
    "wof:placetype": "postalcode"
  },
  "geometry": {"coordinates":[-1.34581,50.970637],"type":"Point"}
}
