{
  "type": "Feature",
  "properties": {
    "iso:country":"GB",
    "wof:name":"SO50 6AD",
    "wof:placetype":"postalcode"
},
  "geometry": {"coordinates":[-1.34582088997907,50.97064546246534],"type":"Point"}
}