{
  "type": "Feature",
  "properties": {
    "date:inception_lower":"1980-01-01",
    "date:inception_upper":"1980-01-31",
    "iso:country":"GB",
    "wof:name":"CM23 3RN",
    "wof:placetype":"postalcode"
},
  "geometry": {"coordinates":[0.152937,51.861163],"type":"Point"}
}