{
  "type": "Feature",
  "properties": {
    "iso:country":"GB",
    "wof:name":"CM23 3RN",
    "wof:placetype":"postalcode"
},
  "geometry": {"coordinates":[0.15293719099984,51.8611630216709],"type":"Point"}
}