{
  "type": "Feature",
  "properties": {
    "iso:country":"GB",
    "wof:name":"SN3 4HN",
    "wof:placetype":"postalcode"
},
  "geometry": {"coordinates":[-1.74124796754267,51.57592838552475],"type":"Point"}
}