{
  "type": "Feature",
  "properties": {
    "iso:country":"GB",
    "wof:name":"L9 1BN",
    "wof:placetype":"postalcode"
},
  "geometry": {"coordinates":[-2.96791486718713,53.44823209331779],"type":"Point"}
}