{
  "type": "Feature",
  "properties": {
    "iso:country":"GB",
    "wof:name":"G66 7HT",
    "wof:placetype":"postalcode"
},
  "geometry": {"coordinates":[-4.20401093605764,55.97866704445612],"type":"Point"}
}