{
  "type": "Feature",
  "properties": {
    "iso:country":"GB",
    "wof:name":"LN7 6TX",
    "wof:placetype":"postalcode"
},
  "geometry": {"coordinates":[-0.31468429673026,53.49744409410356],"type":"Point"}
}