{
  "type": "Feature",
  "properties": {
    "date:inception_lower":"2008-02-01",
    "date:inception_upper":"2008-02-29",
    "iso:country":"GB",
    "wof:name":"SS0 7FF",
    "wof:placetype":"postalcode"
},
  "geometry": {"coordinates":[0.697215,51.535788],"type":"Point"}
}