{
  "type": "Feature",
  "properties": {
    "date:inception_lower": "2000-12-01",
    "date:inception_upper": "2000-12-01",
    "iso:country": "GB",
    "wof:name": "BS1 3LH",
    "wof:placetype": "postalcode"
  },
  "geometry": {"coordinates":[-2.592481,51.458904],"type":"Point"}
}
