{
  "type": "Feature",
  "properties": {
    "iso:country":"GB",
    "wof:name":"BS1 3LH",
    "wof:placetype":"postalcode"
},
  "geometry": {"coordinates":[-2.59250874975457,51.45897695466433],"type":"Point"}
}