{
  "type": "Feature",
  "properties": {
    "iso:country": "GB",
    "wof:name": "GL7 1YB",
    "wof:placetype": "postalcode"
  },
  "geometry": {"coordinates":[-1.965161,51.708559],"type":"Point"}
}
