{
  "type": "Feature",
  "properties": {
    "iso:country":"GB",
    "wof:name":"GL7 1YB",
    "wof:placetype":"postalcode"
},
  "geometry": {"coordinates":[-1.96516101601041,51.70855904128004],"type":"Point"}
}