{
  "type": "Feature",
  "properties": {
    "iso:country":"GB",
    "wof:name":"IP1 5LQ",
    "wof:placetype":"postalcode"
},
  "geometry": {"coordinates":[1.11688686730071,52.07430210499424],"type":"Point"}
}