{
  "type": "Feature",
  "properties": {
    "iso:country": "GB",
    "wof:name": "CM22 7TU",
    "wof:placetype": "postalcode"
  },
  "geometry": {"coordinates":[0.201372,51.85666],"type":"Point"}
}
