{
  "type": "Feature",
  "properties": {
    "iso:country": "GB",
    "wof:name": "DL7 0HT",
    "wof:placetype": "postalcode"
  },
  "geometry": {"coordinates":[-1.553281,54.426033],"type":"Point"}
}
