{
  "type": "Feature",
  "properties": {
    "date:inception_lower": "1999-12-01",
    "date:inception_upper": "1999-12-01",
    "iso:country": "GB",
    "wof:name": "MK10 9DW",
    "wof:placetype": "postalcode"
  },
  "geometry": {"coordinates":[-0.700399,52.034153],"type":"Point"}
}
