{
  "type": "Feature",
  "properties": {
    "iso:country":"GB",
    "wof:name":"MK10 9DW",
    "wof:placetype":"postalcode"
},
  "geometry": {"coordinates":[-0.70039937270582,52.03415271688505],"type":"Point"}
}