{
  "type": "Feature",
  "properties": {
    "iso:country":"GB",
    "wof:name":"CV4 9WF",
    "wof:placetype":"postalcode"
},
  "geometry": {"coordinates":[-1.60098547164086,52.41057023560261],"type":"Point"}
}