{
  "type": "Feature",
  "properties": {
    "date:inception_lower": "2008-03-01",
    "date:inception_upper": "2008-03-01",
    "iso:country": "GB",
    "wof:name": "CV4 9WF",
    "wof:placetype": "postalcode"
  },
  "geometry": {"coordinates":[-1.600985,52.41057],"type":"Point"}
}
