{
  "type": "Feature",
  "properties": {
    "iso:country":"GB",
    "wof:name":"LS9 0JT",
    "wof:placetype":"postalcode"
},
  "geometry": {"coordinates":[-1.49638644433786,53.7899725925231],"type":"Point"}
}