{
  "type": "Feature",
  "properties": {
    "date:inception_lower": "1980-01-01",
    "date:inception_upper": "1980-01-01",
    "iso:country": "GB",
    "wof:name": "LS9 0JT",
    "wof:placetype": "postalcode"
  },
  "geometry": {"coordinates":[-1.496386,53.789973],"type":"Point"}
}
