{
  "type": "Feature",
  "properties": {
    "iso:country":"GB",
    "wof:name":"EN4 0QR",
    "wof:placetype":"postalcode"
},
  "geometry": {"coordinates":[-0.15365791368375,51.65565307167311],"type":"Point"}
}