{
  "type": "Feature",
  "properties": {
    "iso:country": "GB",
    "wof:name": "CF40 1SJ",
    "wof:placetype": "postalcode"
  },
  "geometry": {"coordinates":[-3.438204,51.594472],"type":"Point"}
}
