{
  "type": "Feature",
  "properties": {
    "iso:country":"GB",
    "wof:name":"DN11 0NL",
    "wof:placetype":"postalcode"
},
  "geometry": {"coordinates":[-1.06997621925487,53.47470367549138],"type":"Point"}
}