{
  "type": "Feature",
  "properties": {
    "date:inception_lower":"1980-01-01",
    "date:inception_upper":"1980-01-31",
    "iso:country":"GB",
    "wof:name":"IP29 5RG",
    "wof:placetype":"postalcode"
},
  "geometry": {"coordinates":[0.634982,52.20228],"type":"Point"}
}