{
  "type": "Feature",
  "properties": {
    "iso:country":"GB",
    "wof:name":"LL55 2SE",
    "wof:placetype":"postalcode"
},
  "geometry": {"coordinates":[-4.25549289599408,53.13405164131719],"type":"Point"}
}