{
  "type": "Feature",
  "properties": {
    "iso:country": "GB",
    "wof:name": "LL55 2SE",
    "wof:placetype": "postalcode"
  },
  "geometry": {"coordinates":[-4.255493,53.134052],"type":"Point"}
}
