{
  "type": "Feature",
  "properties": {
    "date:inception_lower": "1980-01-01",
    "date:inception_upper": "1980-01-01",
    "iso:country": "GB",
    "wof:name": "LL55 2SE",
    "wof:placetype": "postalcode"
  },
  "geometry": {"coordinates":[-4.255501,53.133521],"type":"Point"}
}
