{
  "type": "Feature",
  "properties": {
    "iso:country": "GB",
    "wof:name": "LE67 6JR",
    "wof:placetype": "postalcode"
  },
  "geometry": {"coordinates":[-1.397623,52.691347],"type":"Point"}
}
