{
  "type": "Feature",
  "properties": {
    "date:inception_lower":"2014-01-01",
    "date:inception_upper":"2014-01-31",
    "iso:country":"GB",
    "wof:name":"LE67 6JR",
    "wof:placetype":"postalcode"
},
  "geometry": {"coordinates":[-1.397623,52.691347],"type":"Point"}
}