{
  "type": "Feature",
  "properties": {
    "iso:country":"GB",
    "wof:name":"EH46 7ER",
    "wof:placetype":"postalcode"
},
  "geometry": {"coordinates":[-3.35689104820184,55.75277233628616],"type":"Point"}
}