{
  "type": "Feature",
  "properties": {
    "iso:country":"GB",
    "wof:name":"HA3 9HB",
    "wof:placetype":"postalcode"
},
  "geometry": {"coordinates":[-0.30119507449179,51.58748930059781],"type":"Point"}
}