{
  "type": "Feature",
  "properties": {
    "date:inception_lower": "2018-08-01",
    "date:inception_upper": "2018-08-01",
    "iso:country": "GB",
    "wof:name": "BH6 4BZ",
    "wof:placetype": "postalcode"
  },
  "geometry": {"coordinates":[-1.790707,50.721478],"type":"Point"}
}
