{
  "type": "Feature",
  "properties": {
    "iso:country": "GB",
    "wof:name": "BH6 4BZ",
    "wof:placetype": "postalcode"
  },
  "geometry": {"coordinates":[-1.790707,50.721478],"type":"Point"}
}
