{
  "type": "Feature",
  "properties": {
    "iso:country":"GB",
    "wof:name":"KA8 9RE",
    "wof:placetype":"postalcode"
},
  "geometry": {"coordinates":[-4.60046908819382,55.47133051515542],"type":"Point"}
}