{
  "type": "Feature",
  "properties": {
    "iso:country":"GB",
    "wof:name":"CT5 1DL",
    "wof:placetype":"postalcode"
},
  "geometry": {"coordinates":[1.02161096212002,51.35402458782141],"type":"Point"}
}