{
  "type": "Feature",
  "properties": {
    "date:inception_lower": "2000-06-01",
    "date:inception_upper": "2000-06-01",
    "iso:country": "GB",
    "wof:name": "CA7 4HG",
    "wof:placetype": "postalcode"
  },
  "geometry": {"coordinates":[-3.389887,54.864072],"type":"Point"}
}
