{
  "type": "Feature",
  "properties": {
    "iso:country": "GB",
    "wof:name": "CA7 4HG",
    "wof:placetype": "postalcode"
  },
  "geometry": {"coordinates":[-3.389886,54.864057],"type":"Point"}
}
