{
  "type": "Feature",
  "properties": {
    "iso:country":"GB",
    "wof:name":"CA7 4HG",
    "wof:placetype":"postalcode"
},
  "geometry": {"coordinates":[-3.38988586864733,54.86405741031708],"type":"Point"}
}