{
  "type": "Feature",
  "properties": {
    "date:inception_lower": "1980-01-01",
    "date:inception_upper": "1980-01-01",
    "iso:country": "GB",
    "wof:name": "CM19 4JA",
    "wof:placetype": "postalcode"
  },
  "geometry": {"coordinates":[0.079543,51.757965],"type":"Point"}
}
