{
  "type": "Feature",
  "properties": {
    "iso:country":"GB",
    "wof:name":"CM19 4JA",
    "wof:placetype":"postalcode"
},
  "geometry": {"coordinates":[0.07954277497319,51.75796517920192],"type":"Point"}
}