{
  "type": "Feature",
  "properties": {
    "iso:country": "GB",
    "wof:name": "CM19 4JA",
    "wof:placetype": "postalcode"
  },
  "geometry": {"coordinates":[0.079543,51.757965],"type":"Point"}
}
