{
  "type": "Feature",
  "properties": {
    "iso:country": "GB",
    "wof:name": "CF45 3RE",
    "wof:placetype": "postalcode"
  },
  "geometry": {"coordinates":[-3.383784,51.683966],"type":"Point"}
}
