{
  "type": "Feature",
  "properties": {
    "date:inception_lower":"1994-12-01",
    "date:inception_upper":"1994-12-31",
    "iso:country":"GB",
    "wof:name":"WF12 8BY",
    "wof:placetype":"postalcode"
},
  "geometry": {"coordinates":[-1.612869,53.684453],"type":"Point"}
}