{
  "type": "Feature",
  "properties": {
    "iso:country":"GB",
    "wof:name":"WF12 8BY",
    "wof:placetype":"postalcode"
},
  "geometry": {"coordinates":[-1.61286898531066,53.68445312253028],"type":"Point"}
}