{
  "type": "Feature",
  "properties": {
    "iso:country":"GB",
    "wof:name":"B71 2PR",
    "wof:placetype":"postalcode"
},
  "geometry": {"coordinates":[-2.01194468033164,52.54418552929169],"type":"Point"}
}