{
  "type": "Feature",
  "properties": {
    "iso:country":"GB",
    "wof:name":"SE5 0AS",
    "wof:placetype":"postalcode"
},
  "geometry": {"coordinates":[-0.09611633722322,51.47850849426882],"type":"Point"}
}