{
  "type": "Feature",
  "properties": {
    "iso:country": "GB",
    "wof:name": "BS16 3TR",
    "wof:placetype": "postalcode"
  },
  "geometry": {"coordinates":[-2.52586,51.479524],"type":"Point"}
}
