{
  "type": "Feature",
  "properties": {
    "iso:country": "GB",
    "wof:name": "PE22 8EA",
    "wof:placetype": "postalcode"
  },
  "geometry": {"coordinates":[0.02829,53.120627],"type":"Point"}
}
