{
  "type": "Feature",
  "properties": {
    "iso:country":"GB",
    "wof:name":"PE22 8EA",
    "wof:placetype":"postalcode"
},
  "geometry": {"coordinates":[0.02828979122963,53.12062699286623],"type":"Point"}
}