{
  "type": "Feature",
  "properties": {
    "date:inception_lower": "2005-04-01",
    "date:inception_upper": "2005-04-01",
    "iso:country": "GB",
    "wof:name": "PE22 8EA",
    "wof:placetype": "postalcode"
  },
  "geometry": {"coordinates":[0.02829,53.120627],"type":"Point"}
}
