{
  "type": "Feature",
  "properties": {
    "iso:country":"GB",
    "wof:name":"CM9 6NG",
    "wof:placetype":"postalcode"
},
  "geometry": {"coordinates":[0.68366401887995,51.72041189450883],"type":"Point"}
}