{
  "type": "Feature",
  "properties": {
    "date:inception_lower": "1999-12-01",
    "date:inception_upper": "1999-12-01",
    "iso:country": "GB",
    "wof:name": "CM9 6NG",
    "wof:placetype": "postalcode"
  },
  "geometry": {"coordinates":[0.683488,51.720387],"type":"Point"}
}
