{
  "type": "Feature",
  "properties": {
    "date:inception_lower": "2003-02-01",
    "date:inception_upper": "2003-02-01",
    "iso:country": "GB",
    "wof:name": "S4 8AQ",
    "wof:placetype": "postalcode"
  },
  "geometry": {"coordinates":[-1.426388,53.409971],"type":"Point"}
}
