{
  "type": "Feature",
  "properties": {
    "iso:country": "GB",
    "wof:name": "S4 8AQ",
    "wof:placetype": "postalcode"
  },
  "geometry": {"coordinates":[-1.430089,53.407715],"type":"Point"}
}
