{
  "type": "Feature",
  "properties": {
    "date:inception_lower":"2005-01-01",
    "date:inception_upper":"2005-01-31",
    "iso:country":"GB",
    "wof:name":"EN10 6FS",
    "wof:placetype":"postalcode"
},
  "geometry": {"coordinates":[-0.030103,51.722707],"type":"Point"}
}