{
  "type": "Feature",
  "properties": {
    "iso:country":"GB",
    "wof:name":"EN10 6FS",
    "wof:placetype":"postalcode"
},
  "geometry": {"coordinates":[-0.03010281680746,51.7227069309241],"type":"Point"}
}