{
  "type": "Feature",
  "properties": {
    "iso:country":"GB",
    "wof:name":"TS18 2BZ",
    "wof:placetype":"postalcode"
},
  "geometry": {"coordinates":[-1.31253916050519,54.56977547123063],"type":"Point"}
}