{
  "type": "Feature",
  "properties": {
    "date:inception_lower": "1980-01-01",
    "date:inception_upper": "1980-01-01",
    "iso:country": "GB",
    "wof:name": "TS18 2BZ",
    "wof:placetype": "postalcode"
  },
  "geometry": {"coordinates":[-1.312539,54.569775],"type":"Point"}
}
