{
  "type": "Feature",
  "properties": {
    "iso:country": "GB",
    "wof:name": "CH65 9DS",
    "wof:placetype": "postalcode"
  },
  "geometry": {"coordinates":[-2.889715,53.267587],"type":"Point"}
}
