{
  "type": "Feature",
  "properties": {
    "iso:country":"GB",
    "wof:name":"BL1 8PT",
    "wof:placetype":"postalcode"
},
  "geometry": {"coordinates":[-2.42902901256126,53.59827290440902],"type":"Point"}
}