{
  "type": "Feature",
  "properties": {
    "iso:country": "GB",
    "wof:name": "LS2 9DB",
    "wof:placetype": "postalcode"
  },
  "geometry": {"coordinates":[-1.563361,53.805998],"type":"Point"}
}
