{
  "type": "Feature",
  "properties": {
    "iso:country":"GB",
    "wof:name":"NR7 0HH",
    "wof:placetype":"postalcode"
},
  "geometry": {"coordinates":[1.34375982309053,52.62682452765509],"type":"Point"}
}