{
  "type": "Feature",
  "properties": {
    "date:inception_lower": "1980-01-01",
    "date:inception_upper": "1980-01-01",
    "iso:country": "GB",
    "wof:name": "PR3 1JR",
    "wof:placetype": "postalcode"
  },
  "geometry": {"coordinates":[-2.773669,53.909503],"type":"Point"}
}
