{
  "type": "Feature",
  "properties": {
    "iso:country":"GB",
    "wof:name":"PR3 1JR",
    "wof:placetype":"postalcode"
},
  "geometry": {"coordinates":[-2.77366896052099,53.90950276915427],"type":"Point"}
}