{
  "type": "Feature",
  "properties": {
    "iso:country": "GB",
    "wof:name": "HP5 2LE",
    "wof:placetype": "postalcode"
  },
  "geometry": {"coordinates":[-0.618696,51.721956],"type":"Point"}
}
