{
  "type": "Feature",
  "properties": {
    "date:inception_lower":"1980-01-01",
    "date:inception_upper":"1980-01-31",
    "iso:country":"GB",
    "wof:name":"B25 8NG",
    "wof:placetype":"postalcode"
},
  "geometry": {"coordinates":[-1.833235,52.464427],"type":"Point"}
}