{
  "type": "Feature",
  "properties": {
    "iso:country":"GB",
    "wof:name":"B25 8NG",
    "wof:placetype":"postalcode"
},
  "geometry": {"coordinates":[-1.8332350689932,52.46442728137397],"type":"Point"}
}