{
  "type": "Feature",
  "properties": {
    "iso:country": "GB",
    "wof:name": "B25 8NG",
    "wof:placetype": "postalcode"
  },
  "geometry": {"coordinates":[-1.833235,52.464427],"type":"Point"}
}
