{
  "type": "Feature",
  "properties": {
    "iso:country": "GB",
    "wof:name": "LS19 6PJ",
    "wof:placetype": "postalcode"
  },
  "geometry": {"coordinates":[-1.668294,53.847078],"type":"Point"}
}
