{
  "type": "Feature",
  "properties": {
    "iso:country":"GB",
    "wof:name":"LS19 6PJ",
    "wof:placetype":"postalcode"
},
  "geometry": {"coordinates":[-1.66829374604631,53.847078288664],"type":"Point"}
}