{
  "type": "Feature",
  "properties": {
    "date:inception_lower":"1980-01-01",
    "date:inception_upper":"1980-01-31",
    "iso:country":"GB",
    "wof:name":"LS19 6PJ",
    "wof:placetype":"postalcode"
},
  "geometry": {"coordinates":[-1.668294,53.847078],"type":"Point"}
}