{
  "type": "Feature",
  "properties": {
    "date:inception_lower": "1980-01-01",
    "date:inception_upper": "1980-01-01",
    "iso:country": "GB",
    "wof:name": "SG1 1UU",
    "wof:placetype": "postalcode"
  },
  "geometry": {"coordinates":[-0.193481,51.902988],"type":"Point"}
}
