{
  "type": "Feature",
  "properties": {
    "iso:country":"GB",
    "wof:name":"SG1 1UU",
    "wof:placetype":"postalcode"
},
  "geometry": {"coordinates":[-0.1934806109393,51.90298806282335],"type":"Point"}
}