{
  "type": "Feature",
  "properties": {
    "date:inception_lower": "2007-07-01",
    "date:inception_upper": "2007-07-01",
    "iso:country": "GB",
    "wof:name": "SG5 4GG",
    "wof:placetype": "postalcode"
  },
  "geometry": {"coordinates":[-0.246542,51.999517],"type":"Point"}
}
