{
  "type": "Feature",
  "properties": {
    "iso:country":"GB",
    "wof:name":"SG5 4GG",
    "wof:placetype":"postalcode"
},
  "geometry": {"coordinates":[-0.24654185544366,51.99951710197985],"type":"Point"}
}