{
  "type": "Feature",
  "properties": {
    "iso:country":"GB",
    "wof:name":"NP25 5GD",
    "wof:placetype":"postalcode"
},
  "geometry": {"coordinates":[-2.73620197791966,51.81602108622796],"type":"Point"}
}