{
  "type": "Feature",
  "properties": {
    "iso:country":"GB",
    "wof:name":"SN3 4QL",
    "wof:placetype":"postalcode"
},
  "geometry": {"coordinates":[-1.75001694579244,51.58729446240577],"type":"Point"}
}