{
  "type": "Feature",
  "properties": {
    "iso:country":"GB",
    "wof:name":"LS1 6LQ",
    "wof:placetype":"postalcode"
},
  "geometry": {"coordinates":[-1.54278571872894,53.79863409785687],"type":"Point"}
}