{
  "type": "Feature",
  "properties": {
    "iso:country":"GB",
    "wof:name":"SW14 8PN",
    "wof:placetype":"postalcode"
},
  "geometry": {"coordinates":[-0.25969715079005,51.46829913540483],"type":"Point"}
}