{
  "type": "Feature",
  "properties": {
    "date:inception_lower": "1996-06-01",
    "date:inception_upper": "1996-06-01",
    "iso:country": "GB",
    "wof:name": "AB21 9LL",
    "wof:placetype": "postalcode"
  },
  "geometry": {"coordinates":[-2.171323,57.177224],"type":"Point"}
}
