{
  "type": "Feature",
  "properties": {
    "iso:country":"GB",
    "wof:name":"SS17 8PJ",
    "wof:placetype":"postalcode"
},
  "geometry": {"coordinates":[0.40689137550303,51.5222666963698],"type":"Point"}
}