{
  "type": "Feature",
  "properties": {
    "iso:country":"GB",
    "wof:name":"CM2 8UG",
    "wof:placetype":"postalcode"
},
  "geometry": {"coordinates":[0.49397205955082,51.67049043281896],"type":"Point"}
}