{
  "type": "Feature",
  "properties": {
    "date:inception_lower":"1980-01-01",
    "date:inception_upper":"1980-01-31",
    "iso:country":"GB",
    "wof:name":"CM2 8UG",
    "wof:placetype":"postalcode"
},
  "geometry": {"coordinates":[0.493972,51.67049],"type":"Point"}
}