{
  "type": "Feature",
  "properties": {
    "iso:country": "GB",
    "wof:name": "TN26 3TW",
    "wof:placetype": "postalcode"
  },
  "geometry": {"coordinates":[0.777679,51.071047],"type":"Point"}
}
