{
  "type": "Feature",
  "properties": {
    "date:inception_lower": "2008-06-01",
    "date:inception_upper": "2008-06-01",
    "iso:country": "GB",
    "wof:name": "WF13 4DG",
    "wof:placetype": "postalcode"
  },
  "geometry": {"coordinates":[-1.657085,53.706321],"type":"Point"}
}
