{
  "type": "Feature",
  "properties": {
    "iso:country": "GB",
    "wof:name": "LL30 3FQ",
    "wof:placetype": "postalcode"
  },
  "geometry": {"coordinates":[-3.782989,53.314299],"type":"Point"}
}
