{
  "type": "Feature",
  "properties": {
    "iso:country":"GB",
    "wof:name":"SW2 3EU",
    "wof:placetype":"postalcode"
},
  "geometry": {"coordinates":[-0.12047188744272,51.44444178720826],"type":"Point"}
}