{
  "type": "Feature",
  "properties": {
    "iso:country": "GB",
    "wof:name": "WF10 2FQ",
    "wof:placetype": "postalcode"
  },
  "geometry": {"coordinates":[-1.360466,53.745696],"type":"Point"}
}
