{
  "type": "Feature",
  "properties": {
    "iso:country":"GB",
    "wof:name":"NG5 9DP",
    "wof:placetype":"postalcode"
},
  "geometry": {"coordinates":[-1.16666077814112,53.00391317325024],"type":"Point"}
}