{
  "type": "Feature",
  "properties": {
    "date:inception_lower": "1980-01-01",
    "date:inception_upper": "1980-01-01",
    "iso:country": "GB",
    "wof:name": "NG5 9DP",
    "wof:placetype": "postalcode"
  },
  "geometry": {"coordinates":[-1.166717,53.003897],"type":"Point"}
}
