{
  "type": "Feature",
  "properties": {
    "iso:country":"GB",
    "wof:name":"N1 3EL",
    "wof:placetype":"postalcode"
},
  "geometry": {"coordinates":[-0.08903249612032,51.54011826979345],"type":"Point"}
}