{
  "type": "Feature",
  "properties": {
    "iso:country":"GB",
    "wof:name":"RM20 4BL",
    "wof:placetype":"postalcode"
},
  "geometry": {"coordinates":[0.29807729126572,51.47639050737374],"type":"Point"}
}