{
  "type": "Feature",
  "properties": {
    "date:inception_lower":"2012-03-01",
    "date:inception_upper":"2012-03-31",
    "iso:country":"GB",
    "wof:name":"RM20 4BL",
    "wof:placetype":"postalcode"
},
  "geometry": {"coordinates":[0.298077,51.476391],"type":"Point"}
}