{
  "type": "Feature",
  "properties": {
    "iso:country": "GB",
    "wof:name": "CH43 3BX",
    "wof:placetype": "postalcode"
  },
  "geometry": {"coordinates":[-3.058448,53.365538],"type":"Point"}
}
