{
  "type": "Feature",
  "properties": {
    "date:inception_lower": "1999-06-01",
    "date:inception_upper": "1999-06-01",
    "iso:country": "GB",
    "wof:name": "CH43 3BX",
    "wof:placetype": "postalcode"
  },
  "geometry": {"coordinates":[-3.058448,53.365538],"type":"Point"}
}
