{
  "type": "Feature",
  "properties": {
    "iso:country":"GB",
    "wof:name":"SS8 7NR",
    "wof:placetype":"postalcode"
},
  "geometry": {"coordinates":[0.60747355195379,51.51686265554034],"type":"Point"}
}