{
  "type": "Feature",
  "properties": {
    "date:inception_lower": "1994-05-01",
    "date:inception_upper": "1994-05-01",
    "iso:country": "GB",
    "wof:name": "PL22 0HF",
    "wof:placetype": "postalcode"
  },
  "geometry": {"coordinates":[-4.661538,50.40779],"type":"Point"}
}
