{
  "type": "Feature",
  "properties": {
    "iso:country":"GB",
    "wof:name":"PE27 6DW",
    "wof:placetype":"postalcode"
},
  "geometry": {"coordinates":[-0.07986746201108,52.32908862915038],"type":"Point"}
}