{
  "type": "Feature",
  "properties": {
    "iso:country": "GB",
    "wof:name": "AB42 5SE",
    "wof:placetype": "postalcode"
  },
  "geometry": {"coordinates":[-2.162423,57.508624],"type":"Point"}
}
