{
  "type": "Feature",
  "properties": {
    "iso:country":"GB",
    "wof:name":"SE7 8HW",
    "wof:placetype":"postalcode"
},
  "geometry": {"coordinates":[0.04349425325258,51.48311876854206],"type":"Point"}
}