{
  "type": "Feature",
  "properties": {
    "iso:country": "GB",
    "wof:name": "M45 8NF",
    "wof:placetype": "postalcode"
  },
  "geometry": {"coordinates":[-2.279798,53.552165],"type":"Point"}
}
