{
  "type": "Feature",
  "properties": {
    "iso:country":"GB",
    "wof:name":"M45 8NF",
    "wof:placetype":"postalcode"
},
  "geometry": {"coordinates":[-2.27979834160977,53.55216467200771],"type":"Point"}
}