{
  "type": "Feature",
  "properties": {
    "iso:country":"GB",
    "wof:name":"SY11 2JN",
    "wof:placetype":"postalcode"
},
  "geometry": {"coordinates":[-3.04788842052003,52.85894336396198],"type":"Point"}
}