{
  "type": "Feature",
  "properties": {
    "iso:country": "GB",
    "wof:name": "SY11 2JN",
    "wof:placetype": "postalcode"
  },
  "geometry": {"coordinates":[-3.047888,52.858943],"type":"Point"}
}
