{
  "type": "Feature",
  "properties": {
    "iso:country": "GB",
    "wof:name": "YO14 9NZ",
    "wof:placetype": "postalcode"
  },
  "geometry": {"coordinates":[-0.288614,54.205577],"type":"Point"}
}
