{
  "type": "Feature",
  "properties": {
    "iso:country": "GB",
    "wof:name": "PE27 5RN",
    "wof:placetype": "postalcode"
  },
  "geometry": {"coordinates":[-0.07675,52.326871],"type":"Point"}
}
