{
  "type": "Feature",
  "properties": {
    "date:inception_lower":"2009-03-01",
    "date:inception_upper":"2009-03-31",
    "iso:country":"GB",
    "wof:name":"PE27 5RN",
    "wof:placetype":"postalcode"
},
  "geometry": {"coordinates":[-0.07675,52.326871],"type":"Point"}
}