{
  "type": "Feature",
  "properties": {
    "iso:country":"GB",
    "wof:name":"PE27 5RN",
    "wof:placetype":"postalcode"
},
  "geometry": {"coordinates":[-0.07674960730531,52.32687096179147],"type":"Point"}
}