{
  "type": "Feature",
  "properties": {
    "date:inception_lower": "1980-01-01",
    "date:inception_upper": "1980-01-01",
    "iso:country": "GB",
    "wof:name": "SK4 3QB",
    "wof:placetype": "postalcode"
  },
  "geometry": {"coordinates":[-2.199694,53.420267],"type":"Point"}
}
