{
  "type": "Feature",
  "properties": {
    "date:inception_lower": "1980-01-01",
    "date:inception_upper": "1980-01-01",
    "iso:country": "GB",
    "wof:name": "WV16 4SH",
    "wof:placetype": "postalcode"
  },
  "geometry": {"coordinates":[-2.42693,52.547182],"type":"Point"}
}
