{
  "type": "Feature",
  "properties": {
    "date:inception_lower": "1980-01-01",
    "date:inception_upper": "1980-01-01",
    "iso:country": "GB",
    "wof:name": "SA14 7NA",
    "wof:placetype": "postalcode"
  },
  "geometry": {"coordinates":[-4.063296,51.81556],"type":"Point"}
}
