{
  "type": "Feature",
  "properties": {
    "iso:country": "GB",
    "wof:name": "SA14 7NA",
    "wof:placetype": "postalcode"
  },
  "geometry": {"coordinates":[-4.063296,51.81556],"type":"Point"}
}
