{
  "type": "Feature",
  "properties": {
    "date:inception_lower": "1992-08-01",
    "date:inception_upper": "1992-08-01",
    "iso:country": "GB",
    "wof:name": "CV9 2BE",
    "wof:placetype": "postalcode"
  },
  "geometry": {"coordinates":[-1.552614,52.573737],"type":"Point"}
}
