{
  "type": "Feature",
  "properties": {
    "iso:country": "GB",
    "wof:name": "RG30 3BU",
    "wof:placetype": "postalcode"
  },
  "geometry": {"coordinates":[-1.012585,51.443992],"type":"Point"}
}
