{
  "type": "Feature",
  "properties": {
    "iso:country":"GB",
    "wof:name":"SK6 1HN",
    "wof:placetype":"postalcode"
},
  "geometry": {"coordinates":[-2.09319247924323,53.42750795441259],"type":"Point"}
}