{
  "type": "Feature",
  "properties": {
    "iso:country":"GB",
    "wof:name":"LE10 3BQ",
    "wof:placetype":"postalcode"
},
  "geometry": {"coordinates":[-1.39032938410078,52.52701999545413],"type":"Point"}
}