{
  "type": "Feature",
  "properties": {
    "iso:country":"GB",
    "wof:name":"NR14 6UT",
    "wof:placetype":"postalcode"
},
  "geometry": {"coordinates":[1.47522147212311,52.53776393454543],"type":"Point"}
}