{
  "type": "Feature",
  "properties": {
    "date:inception_lower":"1995-01-01",
    "date:inception_upper":"1995-01-31",
    "iso:country":"GB",
    "wof:name":"NR14 6UT",
    "wof:placetype":"postalcode"
},
  "geometry": {"coordinates":[1.475222,52.537764],"type":"Point"}
}