{
  "type": "Feature",
  "properties": {
    "iso:country":"GB",
    "wof:name":"DN8 4NQ",
    "wof:placetype":"postalcode"
},
  "geometry": {"coordinates":[-0.94664053478404,53.63513666298492],"type":"Point"}
}