{
  "type": "Feature",
  "properties": {
    "iso:country":"GB",
    "wof:name":"KA29 0BN",
    "wof:placetype":"postalcode"
},
  "geometry": {"coordinates":[-4.8559470031911,55.76264756661796],"type":"Point"}
}