{
  "type": "Feature",
  "properties": {
    "date:inception_lower": "2003-08-01",
    "date:inception_upper": "2003-08-01",
    "iso:country": "GB",
    "wof:name": "DD2 5GD",
    "wof:placetype": "postalcode"
  },
  "geometry": {"coordinates":[-3.140391,56.50394],"type":"Point"}
}
