{
  "type": "Feature",
  "properties": {
    "iso:country":"GB",
    "wof:name":"TN31 7SY",
    "wof:placetype":"postalcode"
},
  "geometry": {"coordinates":[0.70019872946999,50.97037404389034],"type":"Point"}
}