{
  "type": "Feature",
  "properties": {
    "date:inception_lower": "1980-01-01",
    "date:inception_upper": "1980-01-01",
    "iso:country": "GB",
    "wof:name": "TN31 7SY",
    "wof:placetype": "postalcode"
  },
  "geometry": {"coordinates":[0.700199,50.970374],"type":"Point"}
}
