{
  "type": "Feature",
  "properties": {
    "iso:country":"GB",
    "wof:name":"WR5 1DQ",
    "wof:placetype":"postalcode"
},
  "geometry": {"coordinates":[-2.21170353520241,52.18834615671053],"type":"Point"}
}