{
  "type": "Feature",
  "properties": {
    "iso:country":"GB",
    "wof:name":"NR29 4BQ",
    "wof:placetype":"postalcode"
},
  "geometry": {"coordinates":[1.69274398969893,52.7172424778454],"type":"Point"}
}