{
  "type": "Feature",
  "properties": {
    "iso:country": "GB",
    "wof:name": "CV3 1AY",
    "wof:placetype": "postalcode"
  },
  "geometry": {"coordinates":[-1.488192,52.403546],"type":"Point"}
}
