{
  "type": "Feature",
  "properties": {
    "iso:country":"GB",
    "wof:name":"CV3 1AY",
    "wof:placetype":"postalcode"
},
  "geometry": {"coordinates":[-1.48819178277217,52.40354625327853],"type":"Point"}
}