{
  "type": "Feature",
  "properties": {
    "iso:country":"GB",
    "wof:name":"DL14 7DJ",
    "wof:placetype":"postalcode"
},
  "geometry": {"coordinates":[-1.68001565515957,54.6622683237153],"type":"Point"}
}