{
  "type": "Feature",
  "properties": {
    "iso:country": "GB",
    "wof:name": "LL13 8DJ",
    "wof:placetype": "postalcode"
  },
  "geometry": {"coordinates":[-2.98994,53.044321],"type":"Point"}
}
