{
  "type": "Feature",
  "properties": {
    "iso:country":"GB",
    "wof:name":"LL13 8DJ",
    "wof:placetype":"postalcode"
},
  "geometry": {"coordinates":[-2.98994026633829,53.04432095569327],"type":"Point"}
}