{
  "type": "Feature",
  "properties": {
    "date:inception_lower": "1980-01-01",
    "date:inception_upper": "1980-01-01",
    "iso:country": "GB",
    "wof:name": "GL8 8RR",
    "wof:placetype": "postalcode"
  },
  "geometry": {"coordinates":[-2.13112,51.630492],"type":"Point"}
}
