{
  "type": "Feature",
  "properties": {
    "iso:country":"GB",
    "wof:name":"GL8 8RR",
    "wof:placetype":"postalcode"
},
  "geometry": {"coordinates":[-2.13112049431384,51.63049194618457],"type":"Point"}
}