{
  "type": "Feature",
  "properties": {
    "date:inception_lower":"2009-07-01",
    "date:inception_upper":"2009-07-31",
    "iso:country":"GB",
    "wof:name":"SA67 7ET",
    "wof:placetype":"postalcode"
},
  "geometry": {"coordinates":[-4.744105,51.805376],"type":"Point"}
}