{
  "type": "Feature",
  "properties": {
    "iso:country":"GB",
    "wof:name":"SA67 7ET",
    "wof:placetype":"postalcode"
},
  "geometry": {"coordinates":[-4.74410510037215,51.80537604178829],"type":"Point"}
}