{
  "type": "Feature",
  "properties": {
    "iso:country": "GB",
    "wof:name": "HA0 4LR",
    "wof:placetype": "postalcode"
  },
  "geometry": {"coordinates":[-0.296334,51.540308],"type":"Point"}
}
