{
  "type": "Feature",
  "properties": {
    "iso:country":"GB",
    "wof:name":"CR8 3BF",
    "wof:placetype":"postalcode"
},
  "geometry": {"coordinates":[-0.1362595437315,51.33333746657888],"type":"Point"}
}