{
  "type": "Feature",
  "properties": {
    "date:inception_lower": "1980-01-01",
    "date:inception_upper": "1980-01-01",
    "iso:country": "GB",
    "wof:name": "DL9 4BD",
    "wof:placetype": "postalcode"
  },
  "geometry": {"coordinates":[-1.714956,54.378279],"type":"Point"}
}
