{
  "type": "Feature",
  "properties": {
    "iso:country": "GB",
    "wof:name": "DN12 1NQ",
    "wof:placetype": "postalcode"
  },
  "geometry": {"coordinates":[-1.187943,53.478925],"type":"Point"}
}
