{
  "type": "Feature",
  "properties": {
    "iso:country":"GB",
    "wof:name":"DN12 1NQ",
    "wof:placetype":"postalcode"
},
  "geometry": {"coordinates":[-1.187942911499,53.47892504283322],"type":"Point"}
}