{
  "type": "Feature",
  "properties": {
    "iso:country":"GB",
    "wof:name":"E11 4YG",
    "wof:placetype":"postalcode"
},
  "geometry": {"coordinates":[0.00528024890123,51.55654724165916],"type":"Point"}
}