{
  "type": "Feature",
  "properties": {
    "iso:country":"GB",
    "wof:name":"CH2 4RG",
    "wof:placetype":"postalcode"
},
  "geometry": {"coordinates":[-2.87437973663537,53.26335919459102],"type":"Point"}
}