{
  "type": "Feature",
  "properties": {
    "iso:country": "GB",
    "wof:name": "WA10 3PW",
    "wof:placetype": "postalcode"
  },
  "geometry": {"coordinates":[-2.774965,53.437173],"type":"Point"}
}
