{
  "type": "Feature",
  "properties": {
    "date:inception_lower": "1980-01-01",
    "date:inception_upper": "1980-01-01",
    "iso:country": "GB",
    "wof:name": "WA10 3PW",
    "wof:placetype": "postalcode"
  },
  "geometry": {"coordinates":[-2.774965,53.437173],"type":"Point"}
}
