{
  "type": "Feature",
  "properties": {
    "date:inception_lower":"1998-12-01",
    "date:inception_upper":"1998-12-31",
    "iso:country":"GB",
    "wof:name":"ME10 2QX",
    "wof:placetype":"postalcode"
},
  "geometry": {"coordinates":[0.730448,51.347994],"type":"Point"}
}