{
  "type": "Feature",
  "properties": {
    "iso:country": "GB",
    "wof:name": "ME10 2QX",
    "wof:placetype": "postalcode"
  },
  "geometry": {"coordinates":[0.730448,51.347994],"type":"Point"}
}
