{
  "type": "Feature",
  "properties": {
    "iso:country":"GB",
    "wof:name":"ME10 2QX",
    "wof:placetype":"postalcode"
},
  "geometry": {"coordinates":[0.73039322329416,51.34805620488086],"type":"Point"}
}