{
  "type": "Feature",
  "properties": {
    "iso:country":"GB",
    "wof:name":"S20 8LT",
    "wof:placetype":"postalcode"
},
  "geometry": {"coordinates":[-1.34559832732899,53.3319107157192],"type":"Point"}
}