{
  "type": "Feature",
  "properties": {
    "iso:country": "GB",
    "wof:name": "S20 8LT",
    "wof:placetype": "postalcode"
  },
  "geometry": {"coordinates":[-1.345598,53.331911],"type":"Point"}
}
