{
  "type": "Feature",
  "properties": {
    "iso:country": "GB",
    "wof:name": "KA1 3SJ",
    "wof:placetype": "postalcode"
  },
  "geometry": {"coordinates":[-4.491499,55.592218],"type":"Point"}
}
