{
  "type": "Feature",
  "properties": {
    "iso:country": "GB",
    "wof:name": "HP9 1RP",
    "wof:placetype": "postalcode"
  },
  "geometry": {"coordinates":[-0.646352,51.603909],"type":"Point"}
}
