{
  "type": "Feature",
  "properties": {
    "date:inception_lower":"1980-01-01",
    "date:inception_upper":"1980-01-31",
    "iso:country":"GB",
    "wof:name":"LL58 8EU",
    "wof:placetype":"postalcode"
},
  "geometry": {"coordinates":[-4.096258,53.2639],"type":"Point"}
}