{
  "type": "Feature",
  "properties": {
    "iso:country": "GB",
    "wof:name": "LL58 8EU",
    "wof:placetype": "postalcode"
  },
  "geometry": {"coordinates":[-4.096331,53.263863],"type":"Point"}
}
