{
  "type": "Feature",
  "properties": {
    "iso:country":"GB",
    "wof:name":"LL58 8EU",
    "wof:placetype":"postalcode"
},
  "geometry": {"coordinates":[-4.09625267038533,53.26388266082648],"type":"Point"}
}