{
  "type": "Feature",
  "properties": {
    "iso:country":"GB",
    "wof:name":"NW2 3JR",
    "wof:placetype":"postalcode"
},
  "geometry": {"coordinates":[-0.21258834895967,51.55407963439183],"type":"Point"}
}