{
  "type": "Feature",
  "properties": {
    "iso:country":"GB",
    "wof:name":"W12 7PZ",
    "wof:placetype":"postalcode"
},
  "geometry": {"coordinates":[-0.23053188966167,51.51320249154056],"type":"Point"}
}