{
  "type": "Feature",
  "properties": {
    "iso:country": "GB",
    "wof:name": "TQ12 1SD",
    "wof:placetype": "postalcode"
  },
  "geometry": {"coordinates":[-3.638251,50.538565],"type":"Point"}
}
