{
  "type": "Feature",
  "properties": {
    "date:inception_lower":"1993-01-01",
    "date:inception_upper":"1993-01-31",
    "iso:country":"GB",
    "wof:name":"SP11 9RR",
    "wof:placetype":"postalcode"
},
  "geometry": {"coordinates":[-1.639585,51.250861],"type":"Point"}
}