{
  "type": "Feature",
  "properties": {
    "iso:country":"GB",
    "wof:name":"SP11 9RR",
    "wof:placetype":"postalcode"
},
  "geometry": {"coordinates":[-1.63959625179423,51.25086459175267],"type":"Point"}
}