{
  "type": "Feature",
  "properties": {
    "date:inception_lower": "1980-01-01",
    "date:inception_upper": "1980-01-01",
    "iso:country": "GB",
    "wof:name": "CO7 8NP",
    "wof:placetype": "postalcode"
  },
  "geometry": {"coordinates":[1.070766,51.83991],"type":"Point"}
}
