{
  "type": "Feature",
  "properties": {
    "date:inception_lower": "2008-02-01",
    "date:inception_upper": "2008-02-01",
    "iso:country": "GB",
    "wof:name": "EH17 8PR",
    "wof:placetype": "postalcode"
  },
  "geometry": {"coordinates":[-3.138071,55.903876],"type":"Point"}
}
