{
  "type": "Feature",
  "properties": {
    "iso:country": "GB",
    "wof:name": "DN12 1EW",
    "wof:placetype": "postalcode"
  },
  "geometry": {"coordinates":[-1.179414,53.483767],"type":"Point"}
}
