{
  "type": "Feature",
  "properties": {
    "iso:country":"GB",
    "wof:name":"LE4 0PP",
    "wof:placetype":"postalcode"
},
  "geometry": {"coordinates":[-1.1659733202185,52.65982848362717],"type":"Point"}
}