{
  "type": "Feature",
  "properties": {
    "iso:country": "GB",
    "wof:name": "SR7 8LH",
    "wof:placetype": "postalcode"
  },
  "geometry": {"coordinates":[-1.349693,54.83661],"type":"Point"}
}
