{
  "type": "Feature",
  "properties": {
    "iso:country":"GB",
    "wof:name":"SR7 8LH",
    "wof:placetype":"postalcode"
},
  "geometry": {"coordinates":[-1.34969287158754,54.83660975974225],"type":"Point"}
}