{
  "type": "Feature",
  "properties": {
    "iso:country": "GB",
    "wof:name": "M28 3UP",
    "wof:placetype": "postalcode"
  },
  "geometry": {"coordinates":[-2.40716,53.517902],"type":"Point"}
}
