{
  "type": "Feature",
  "properties": {
    "date:inception_lower": "2016-03-01",
    "date:inception_upper": "2016-03-01",
    "iso:country": "GB",
    "wof:name": "M28 3UP",
    "wof:placetype": "postalcode"
  },
  "geometry": {"coordinates":[-2.40716,53.517902],"type":"Point"}
}
