{
  "type": "Feature",
  "properties": {
    "iso:country":"GB",
    "wof:name":"M28 3UP",
    "wof:placetype":"postalcode"
},
  "geometry": {"coordinates":[-2.40751010239681,53.51800099920716],"type":"Point"}
}