{
  "type": "Feature",
  "properties": {
    "iso:country":"GB",
    "wof:name":"LN13 9BQ",
    "wof:placetype":"postalcode"
},
  "geometry": {"coordinates":[0.17744001905184,53.25680840773948],"type":"Point"}
}