{
  "type": "Feature",
  "properties": {
    "iso:country":"GB",
    "wof:name":"BR1 2AN",
    "wof:placetype":"postalcode"
},
  "geometry": {"coordinates":[0.05657536132593,51.4044005620853],"type":"Point"}
}