{
  "type": "Feature",
  "properties": {
    "iso:country":"GB",
    "wof:name":"MK13 0AQ",
    "wof:placetype":"postalcode"
},
  "geometry": {"coordinates":[-0.79032805015912,52.06559899914591],"type":"Point"}
}