{
  "type": "Feature",
  "properties": {
    "date:inception_lower": "2019-12-01",
    "date:inception_upper": "2019-12-01",
    "iso:country": "GB",
    "wof:name": "LN5 5EG",
    "wof:placetype": "postalcode"
  },
  "geometry": {"coordinates":[-0.545234,53.224087],"type":"Point"}
}
