{
  "type": "Feature",
  "properties": {
    "iso:country": "GB",
    "wof:name": "OX11 0EP",
    "wof:placetype": "postalcode"
  },
  "geometry": {"coordinates":[-1.289451,51.599959],"type":"Point"}
}
