{
  "type": "Feature",
  "properties": {
    "iso:country":"GB",
    "wof:name":"SE4 1DW",
    "wof:placetype":"postalcode"
},
  "geometry": {"coordinates":[-0.03455881762926,51.47028964044026],"type":"Point"}
}