{
  "type": "Feature",
  "properties": {
    "date:inception_lower": "1999-06-01",
    "date:inception_upper": "1999-06-01",
    "iso:country": "GB",
    "wof:name": "CH66 4TZ",
    "wof:placetype": "postalcode"
  },
  "geometry": {"coordinates":[-2.930598,53.268084],"type":"Point"}
}
