{
  "type": "Feature",
  "properties": {
    "iso:country": "GB",
    "wof:name": "CT14 7EA",
    "wof:placetype": "postalcode"
  },
  "geometry": {"coordinates":[1.401744,51.21319],"type":"Point"}
}
