{
  "type": "Feature",
  "properties": {
    "iso:country":"GB",
    "wof:name":"BD4 6PF",
    "wof:placetype":"postalcode"
},
  "geometry": {"coordinates":[-1.70589695920518,53.75812331681929],"type":"Point"}
}