{
  "type": "Feature",
  "properties": {
    "date:inception_lower":"1995-07-01",
    "date:inception_upper":"1995-07-31",
    "iso:country":"GB",
    "wof:name":"BD4 6PF",
    "wof:placetype":"postalcode"
},
  "geometry": {"coordinates":[-1.705897,53.758123],"type":"Point"}
}