{
  "type": "Feature",
  "properties": {
    "iso:country": "GB",
    "wof:name": "DL16 7UU",
    "wof:placetype": "postalcode"
  },
  "geometry": {"coordinates":[-1.58735,54.697711],"type":"Point"}
}
