{
  "type": "Feature",
  "properties": {
    "iso:country":"GB",
    "wof:name":"DL16 7UU",
    "wof:placetype":"postalcode"
},
  "geometry": {"coordinates":[-1.58733996695487,54.69770149775633],"type":"Point"}
}