{
  "type": "Feature",
  "properties": {
    "date:inception_lower": "2013-12-01",
    "date:inception_upper": "2013-12-01",
    "iso:country": "GB",
    "wof:name": "DL16 7UU",
    "wof:placetype": "postalcode"
  },
  "geometry": {"coordinates":[-1.587538,54.697577],"type":"Point"}
}
