{
  "type": "Feature",
  "properties": {
    "iso:country":"GB",
    "wof:name":"TA3 5PP",
    "wof:placetype":"postalcode"
},
  "geometry": {"coordinates":[-3.03577696359433,51.02298743402849],"type":"Point"}
}