{
  "type": "Feature",
  "properties": {
    "iso:country":"GB",
    "wof:name":"WF15 6NE",
    "wof:placetype":"postalcode"
},
  "geometry": {"coordinates":[-1.71066142030552,53.71145078880815],"type":"Point"}
}