{
  "type": "Feature",
  "properties": {
    "iso:country": "GB",
    "wof:name": "SM5 2BL",
    "wof:placetype": "postalcode"
  },
  "geometry": {"coordinates":[-0.167576,51.377437],"type":"Point"}
}
