{
  "type": "Feature",
  "properties": {
    "date:inception_lower": "1980-01-01",
    "date:inception_upper": "1980-01-01",
    "iso:country": "GB",
    "wof:name": "LS11 9QG",
    "wof:placetype": "postalcode"
  },
  "geometry": {"coordinates":[-1.553162,53.787014],"type":"Point"}
}
