{
  "type": "Feature",
  "properties": {
    "iso:country":"GB",
    "wof:name":"LS11 9QG",
    "wof:placetype":"postalcode"
},
  "geometry": {"coordinates":[-1.55315728981126,53.786997695168],"type":"Point"}
}