{
  "type": "Feature",
  "properties": {
    "iso:country": "GB",
    "wof:name": "TN11 9BJ",
    "wof:placetype": "postalcode"
  },
  "geometry": {"coordinates":[0.255044,51.210469],"type":"Point"}
}
