{
  "type": "Feature",
  "properties": {
    "iso:country":"GB",
    "wof:name":"SW2 3AF",
    "wof:placetype":"postalcode"
},
  "geometry": {"coordinates":[-0.12165222929417,51.43812090442407],"type":"Point"}
}