{
  "type": "Feature",
  "properties": {
    "iso:country":"GB",
    "wof:name":"BA14 6GB",
    "wof:placetype":"postalcode"
},
  "geometry": {"coordinates":[-2.1555585241635,51.34109782597704],"type":"Point"}
}