{
  "type": "Feature",
  "properties": {
    "date:inception_lower":"2002-06-01",
    "date:inception_upper":"2002-06-30",
    "iso:country":"GB",
    "wof:name":"BA14 6GB",
    "wof:placetype":"postalcode"
},
  "geometry": {"coordinates":[-2.155558,51.341098],"type":"Point"}
}