{
  "type": "Feature",
  "properties": {
    "iso:country":"GB",
    "wof:name":"CB3 9LU",
    "wof:placetype":"postalcode"
},
  "geometry": {"coordinates":[0.09531060245614,52.20078334400252],"type":"Point"}
}