{
  "type": "Feature",
  "properties": {
    "date:inception_lower": "1997-12-01",
    "date:inception_upper": "1997-12-01",
    "iso:country": "GB",
    "wof:name": "EX6 8TJ",
    "wof:placetype": "postalcode"
  },
  "geometry": {"coordinates":[-3.506699,50.682843],"type":"Point"}
}
