{
  "type": "Feature",
  "properties": {
    "iso:country": "GB",
    "wof:name": "EX6 8TJ",
    "wof:placetype": "postalcode"
  },
  "geometry": {"coordinates":[-3.506699,50.682843],"type":"Point"}
}
