{
  "type": "Feature",
  "properties": {
    "iso:country": "GB",
    "wof:name": "HD4 7EG",
    "wof:placetype": "postalcode"
  },
  "geometry": {"coordinates":[-1.833215,53.623159],"type":"Point"}
}
