{
  "type": "Feature",
  "properties": {
    "date:inception_lower": "2014-05-01",
    "date:inception_upper": "2014-05-01",
    "iso:country": "GB",
    "wof:name": "CV21 1GB",
    "wof:placetype": "postalcode"
  },
  "geometry": {"coordinates":[-1.260809,52.383698],"type":"Point"}
}
