{
  "type": "Feature",
  "properties": {
    "iso:country":"GB",
    "wof:name":"NG3 1LH",
    "wof:placetype":"postalcode"
},
  "geometry": {"coordinates":[-1.13953951214126,52.95963571940688],"type":"Point"}
}