{
  "type": "Feature",
  "properties": {
    "iso:country": "GB",
    "wof:name": "L6 5DG",
    "wof:placetype": "postalcode"
  },
  "geometry": {"coordinates":[-2.956305,53.420038],"type":"Point"}
}
