{
  "type": "Feature",
  "properties": {
    "iso:country": "GB",
    "wof:name": "DH1 4PJ",
    "wof:placetype": "postalcode"
  },
  "geometry": {"coordinates":[-1.593729,54.772645],"type":"Point"}
}
