{
  "type": "Feature",
  "properties": {
    "iso:country": "GB",
    "wof:name": "EN6 4RT",
    "wof:placetype": "postalcode"
  },
  "geometry": {"coordinates":[-0.121703,51.715179],"type":"Point"}
}
