{
  "type": "Feature",
  "properties": {
    "iso:country":"GB",
    "wof:name":"EX31 4LP",
    "wof:placetype":"postalcode"
},
  "geometry": {"coordinates":[-3.98223871160157,51.14620735411421],"type":"Point"}
}