{
  "type": "Feature",
  "properties": {
    "date:inception_lower": "1980-01-01",
    "date:inception_upper": "1980-01-01",
    "iso:country": "GB",
    "wof:name": "NE34 6HW",
    "wof:placetype": "postalcode"
  },
  "geometry": {"coordinates":[-1.407515,54.987626],"type":"Point"}
}
