{
  "type": "Feature",
  "properties": {
    "iso:country":"GB",
    "wof:name":"BA12 7NS",
    "wof:placetype":"postalcode"
},
  "geometry": {"coordinates":[-2.2720835553707,51.20444274697098],"type":"Point"}
}