{
  "type": "Feature",
  "properties": {
    "date:inception_lower": "1980-01-01",
    "date:inception_upper": "1980-01-01",
    "iso:country": "GB",
    "wof:name": "BA12 7NS",
    "wof:placetype": "postalcode"
  },
  "geometry": {"coordinates":[-2.272084,51.204443],"type":"Point"}
}
