{
  "type": "Feature",
  "properties": {
    "iso:country":"GB",
    "wof:name":"FK1 5JA",
    "wof:placetype":"postalcode"
},
  "geometry": {"coordinates":[-3.80010772359573,55.99956215082569],"type":"Point"}
}