{
  "type": "Feature",
  "properties": {
    "iso:country":"GB",
    "wof:name":"PE24 4AD",
    "wof:placetype":"postalcode"
},
  "geometry": {"coordinates":[0.24261819066951,53.1060374775316],"type":"Point"}
}