{
  "type": "Feature",
  "properties": {
    "iso:country": "GB",
    "wof:name": "SP3 6LP",
    "wof:placetype": "postalcode"
  },
  "geometry": {"coordinates":[-2.072417,51.065909],"type":"Point"}
}
