{
  "type": "Feature",
  "properties": {
    "date:inception_lower": "1980-01-01",
    "date:inception_upper": "1980-01-01",
    "iso:country": "GB",
    "wof:name": "TR18 5DX",
    "wof:placetype": "postalcode"
  },
  "geometry": {"coordinates":[-5.551738,50.101114],"type":"Point"}
}
