{
  "type": "Feature",
  "properties": {
    "iso:country": "GB",
    "wof:name": "LL28 5PN",
    "wof:placetype": "postalcode"
  },
  "geometry": {"coordinates":[-3.754613,53.248662],"type":"Point"}
}
