{
  "type": "Feature",
  "properties": {
    "iso:country":"GB",
    "wof:name":"LL28 5PN",
    "wof:placetype":"postalcode"
},
  "geometry": {"coordinates":[-3.75461263526734,53.24866199353504],"type":"Point"}
}