{
  "type": "Feature",
  "properties": {
    "iso:country":"GB",
    "wof:name":"LL53 8SL",
    "wof:placetype":"postalcode"
},
  "geometry": {"coordinates":[-4.58452264192482,52.87669003823336],"type":"Point"}
}