{
  "type": "Feature",
  "properties": {
    "iso:country":"GB",
    "wof:name":"TN22 3SL",
    "wof:placetype":"postalcode"
},
  "geometry": {"coordinates":[0.03844115372864,50.99186004417654],"type":"Point"}
}