{
  "type": "Feature",
  "properties": {
    "iso:country": "GB",
    "wof:name": "BN43 5HY",
    "wof:placetype": "postalcode"
  },
  "geometry": {"coordinates":[-0.250819,50.828271],"type":"Point"}
}
