{
  "type": "Feature",
  "properties": {
    "iso:country":"GB",
    "wof:name":"NE49 9LD",
    "wof:placetype":"postalcode"
},
  "geometry": {"coordinates":[-2.46601259506856,54.96879076195762],"type":"Point"}
}