{
  "type": "Feature",
  "properties": {
    "date:inception_lower": "1980-01-01",
    "date:inception_upper": "1980-01-01",
    "iso:country": "GB",
    "wof:name": "NE49 9LD",
    "wof:placetype": "postalcode"
  },
  "geometry": {"coordinates":[-2.466013,54.968791],"type":"Point"}
}
