{
  "type": "Feature",
  "properties": {
    "iso:country":"GB",
    "wof:name":"EX5 4HF",
    "wof:placetype":"postalcode"
},
  "geometry": {"coordinates":[-3.47675375646929,50.83395224295629],"type":"Point"}
}