{
  "type": "Feature",
  "properties": {
    "iso:country": "GB",
    "wof:name": "EX5 4HF",
    "wof:placetype": "postalcode"
  },
  "geometry": {"coordinates":[-3.476754,50.833952],"type":"Point"}
}
