{
  "type": "Feature",
  "properties": {
    "iso:country": "GB",
    "wof:name": "PR8 4AJ",
    "wof:placetype": "postalcode"
  },
  "geometry": {"coordinates":[-3.014922,53.621107],"type":"Point"}
}
