{
  "type": "Feature",
  "properties": {
    "iso:country":"GB",
    "wof:name":"E17 6RD",
    "wof:placetype":"postalcode"
},
  "geometry": {"coordinates":[-0.02692123334351,51.58880996418065],"type":"Point"}
}