{
  "type": "Feature",
  "properties": {
    "iso:country":"GB",
    "wof:name":"CO9 2NY",
    "wof:placetype":"postalcode"
},
  "geometry": {"coordinates":[0.71113971419019,51.98234928065557],"type":"Point"}
}