{
  "type": "Feature",
  "properties": {
    "iso:country": "GB",
    "wof:name": "CO9 2NY",
    "wof:placetype": "postalcode"
  },
  "geometry": {"coordinates":[0.71114,51.982349],"type":"Point"}
}
