{
  "type": "Feature",
  "properties": {
    "date:inception_lower": "1980-01-01",
    "date:inception_upper": "1980-01-01",
    "iso:country": "GB",
    "wof:name": "CO9 2NY",
    "wof:placetype": "postalcode"
  },
  "geometry": {"coordinates":[0.712055,51.982034],"type":"Point"}
}
