{
  "type": "Feature",
  "properties": {
    "iso:country": "GB",
    "wof:name": "GL11 5TF",
    "wof:placetype": "postalcode"
  },
  "geometry": {"coordinates":[-2.311201,51.682167],"type":"Point"}
}
