{
  "type": "Feature",
  "properties": {
    "iso:country": "GB",
    "wof:name": "WV6 8SN",
    "wof:placetype": "postalcode"
  },
  "geometry": {"coordinates":[-2.186578,52.600207],"type":"Point"}
}
