{
  "type": "Feature",
  "properties": {
    "date:inception_lower": "1980-01-01",
    "date:inception_upper": "1980-01-01",
    "iso:country": "GB",
    "wof:name": "TN10 4BJ",
    "wof:placetype": "postalcode"
  },
  "geometry": {"coordinates":[0.29442,51.216547],"type":"Point"}
}
