{
  "type": "Feature",
  "properties": {
    "iso:country":"GB",
    "wof:name":"TN10 4BJ",
    "wof:placetype":"postalcode"
},
  "geometry": {"coordinates":[0.29442025864254,51.21654735738753],"type":"Point"}
}