{
  "type": "Feature",
  "properties": {
    "iso:country":"GB",
    "wof:name":"EH46 7BT",
    "wof:placetype":"postalcode"
},
  "geometry": {"coordinates":[-3.34347589701813,55.74445500096359],"type":"Point"}
}