{
  "type": "Feature",
  "properties": {
    "iso:country": "GB",
    "wof:name": "KY16 0US",
    "wof:placetype": "postalcode"
  },
  "geometry": {"coordinates":[-2.891267,56.364652],"type":"Point"}
}
