{
  "type": "Feature",
  "properties": {
    "iso:country":"GB",
    "wof:name":"KY16 0US",
    "wof:placetype":"postalcode"
},
  "geometry": {"coordinates":[-2.89126700833661,56.36465179524264],"type":"Point"}
}