{
  "type": "Feature",
  "properties": {
    "date:inception_lower": "2013-02-01",
    "date:inception_upper": "2013-02-01",
    "iso:country": "GB",
    "wof:name": "KY16 0US",
    "wof:placetype": "postalcode"
  },
  "geometry": {"coordinates":[-2.891967,56.363991],"type":"Point"}
}
