{
  "type": "Feature",
  "properties": {
    "date:inception_lower":"1980-01-01",
    "date:inception_upper":"1980-01-31",
    "iso:country":"GB",
    "wof:name":"AL4 8EP",
    "wof:placetype":"postalcode"
},
  "geometry": {"coordinates":[-0.252169,51.812535],"type":"Point"}
}