{
  "type": "Feature",
  "properties": {
    "iso:country":"GB",
    "wof:name":"AL4 8EP",
    "wof:placetype":"postalcode"
},
  "geometry": {"coordinates":[-0.25216945482274,51.81253464908843],"type":"Point"}
}