{
  "type": "Feature",
  "properties": {
    "iso:country":"GB",
    "wof:name":"BA3 5TL",
    "wof:placetype":"postalcode"
},
  "geometry": {"coordinates":[-2.45190903356124,51.26882579407575],"type":"Point"}
}