{
  "type": "Feature",
  "properties": {
    "date:inception_lower":"1992-01-01",
    "date:inception_upper":"1992-01-31",
    "iso:country":"GB",
    "wof:name":"NG23 6AP",
    "wof:placetype":"postalcode"
},
  "geometry": {"coordinates":[-0.88401,53.132044],"type":"Point"}
}