{
  "type": "Feature",
  "properties": {
    "iso:country":"GB",
    "wof:name":"NG23 6AP",
    "wof:placetype":"postalcode"
},
  "geometry": {"coordinates":[-0.88400989969732,53.13204417469829],"type":"Point"}
}