{
  "type": "Feature",
  "properties": {
    "iso:country":"GB",
    "wof:name":"PO7 8RU",
    "wof:placetype":"postalcode"
},
  "geometry": {"coordinates":[-1.00700741670841,50.89015636151088],"type":"Point"}
}