{
  "type": "Feature",
  "properties": {
    "date:inception_lower": "1986-07-01",
    "date:inception_upper": "1986-07-01",
    "iso:country": "GB",
    "wof:name": "PO7 8RU",
    "wof:placetype": "postalcode"
  },
  "geometry": {"coordinates":[-1.007007,50.890156],"type":"Point"}
}
