{
  "type": "Feature",
  "properties": {
    "iso:country":"GB",
    "wof:name":"NP7 7RY",
    "wof:placetype":"postalcode"
},
  "geometry": {"coordinates":[-3.0303359914628,51.82502342086635],"type":"Point"}
}