{
  "type": "Feature",
  "properties": {
    "date:inception_lower": "2012-11-01",
    "date:inception_upper": "2012-11-01",
    "iso:country": "GB",
    "wof:name": "NP7 7RY",
    "wof:placetype": "postalcode"
  },
  "geometry": {"coordinates":[-3.030336,51.825023],"type":"Point"}
}
