{
  "type": "Feature",
  "properties": {
    "iso:country": "GB",
    "wof:name": "NP7 7RY",
    "wof:placetype": "postalcode"
  },
  "geometry": {"coordinates":[-3.030336,51.825023],"type":"Point"}
}
