{
  "type": "Feature",
  "properties": {
    "date:inception_lower": "2004-07-01",
    "date:inception_upper": "2004-07-01",
    "iso:country": "GB",
    "wof:name": "LE67 8HY",
    "wof:placetype": "postalcode"
  },
  "geometry": {"coordinates":[-1.42495,52.751633],"type":"Point"}
}
