{
  "type": "Feature",
  "properties": {
    "iso:country":"GB",
    "wof:name":"LE67 8HY",
    "wof:placetype":"postalcode"
},
  "geometry": {"coordinates":[-1.42495030614922,52.75163334731094],"type":"Point"}
}