{
  "type": "Feature",
  "properties": {
    "date:inception_lower": "2010-09-01",
    "date:inception_upper": "2010-09-01",
    "iso:country": "GB",
    "wof:name": "BS16 1EW",
    "wof:placetype": "postalcode"
  },
  "geometry": {"coordinates":[-2.556184,51.496003],"type":"Point"}
}
