{
  "type": "Feature",
  "properties": {
    "iso:country": "GB",
    "wof:name": "BS16 1EW",
    "wof:placetype": "postalcode"
  },
  "geometry": {"coordinates":[-2.556184,51.496003],"type":"Point"}
}
