{
  "type": "Feature",
  "properties": {
    "date:inception_lower": "1980-01-01",
    "date:inception_upper": "1980-01-01",
    "iso:country": "GB",
    "wof:name": "PE30 1LN",
    "wof:placetype": "postalcode"
  },
  "geometry": {"coordinates":[0.392943,52.756697],"type":"Point"}
}
