{
  "type": "Feature",
  "properties": {
    "date:inception_lower": "2023-03-01",
    "date:inception_upper": "2023-03-01",
    "iso:country": "GB",
    "wof:name": "NW10 2FA",
    "wof:placetype": "postalcode"
  },
  "geometry": {"coordinates":[-0.232971,51.545992],"type":"Point"}
}
