{
  "type": "Feature",
  "properties": {
    "iso:country": "GB",
    "wof:name": "IP12 2LD",
    "wof:placetype": "postalcode"
  },
  "geometry": {"coordinates":[1.444727,52.144131],"type":"Point"}
}
