{
  "type": "Feature",
  "properties": {
    "date:inception_lower":"1980-01-01",
    "date:inception_upper":"1980-01-31",
    "iso:country":"GB",
    "wof:name":"W9 2DB",
    "wof:placetype":"postalcode"
},
  "geometry": {"coordinates":[-0.195653,51.526025],"type":"Point"}
}