{
  "type": "Feature",
  "properties": {
    "iso:country":"GB",
    "wof:name":"CR2 9AL",
    "wof:placetype":"postalcode"
},
  "geometry": {"coordinates":[-0.07492954364034,51.3327231235664],"type":"Point"}
}