{
  "type": "Feature",
  "properties": {
    "date:inception_lower": "1990-02-01",
    "date:inception_upper": "1990-02-01",
    "iso:country": "GB",
    "wof:name": "TN30 7AZ",
    "wof:placetype": "postalcode"
  },
  "geometry": {"coordinates":[0.698891,51.074738],"type":"Point"}
}
