{
  "type": "Feature",
  "properties": {
    "iso:country":"GB",
    "wof:name":"TN30 7AZ",
    "wof:placetype":"postalcode"
},
  "geometry": {"coordinates":[0.69889062447971,51.07473792280361],"type":"Point"}
}