{
  "type": "Feature",
  "properties": {
    "iso:country":"GB",
    "wof:name":"S81 0HF",
    "wof:placetype":"postalcode"
},
  "geometry": {"coordinates":[-1.10234391761978,53.3086387441988],"type":"Point"}
}