{
  "type": "Feature",
  "properties": {
    "date:inception_lower": "2004-06-01",
    "date:inception_upper": "2004-06-01",
    "iso:country": "GB",
    "wof:name": "PE31 7UB",
    "wof:placetype": "postalcode"
  },
  "geometry": {"coordinates":[0.495353,52.875543],"type":"Point"}
}
