{
  "type": "Feature",
  "properties": {
    "iso:country":"GB",
    "wof:name":"NP10 8QU",
    "wof:placetype":"postalcode"
},
  "geometry": {"coordinates":[-3.06300794388704,51.57974091629707],"type":"Point"}
}