{
  "type": "Feature",
  "properties": {
    "date:inception_lower": "1993-01-01",
    "date:inception_upper": "1993-01-01",
    "iso:country": "GB",
    "wof:name": "CV23 0UB",
    "wof:placetype": "postalcode"
  },
  "geometry": {"coordinates":[-1.242542,52.394227],"type":"Point"}
}
