{
  "type": "Feature",
  "properties": {
    "iso:country": "GB",
    "wof:name": "CV23 0UB",
    "wof:placetype": "postalcode"
  },
  "geometry": {"coordinates":[-1.242542,52.394227],"type":"Point"}
}
