{
  "type": "Feature",
  "properties": {
    "iso:country":"GB",
    "wof:name":"CV23 0UB",
    "wof:placetype":"postalcode"
},
  "geometry": {"coordinates":[-1.2425421986624,52.39422681258142],"type":"Point"}
}