{
  "type": "Feature",
  "properties": {
    "iso:country":"GB",
    "wof:name":"B31 5RH",
    "wof:placetype":"postalcode"
},
  "geometry": {"coordinates":[-1.98740109100353,52.41110711631368],"type":"Point"}
}