{
  "type": "Feature",
  "properties": {
    "iso:country":"GB",
    "wof:name":"N19 3EU",
    "wof:placetype":"postalcode"
},
  "geometry": {"coordinates":[-0.12955754184676,51.56817143482483],"type":"Point"}
}