{
  "type": "Feature",
  "properties": {
    "iso:country":"GB",
    "wof:name":"EX31 2DH",
    "wof:placetype":"postalcode"
},
  "geometry": {"coordinates":[-4.07814180313632,51.07062581844877],"type":"Point"}
}