{
  "type": "Feature",
  "properties": {
    "iso:country": "GB",
    "wof:name": "EX31 2DH",
    "wof:placetype": "postalcode"
  },
  "geometry": {"coordinates":[-4.078142,51.070626],"type":"Point"}
}
