{
  "type": "Feature",
  "properties": {
    "iso:country":"GB",
    "wof:name":"BS8 3UL",
    "wof:placetype":"postalcode"
},
  "geometry": {"coordinates":[-2.69435450324781,51.4427093773665],"type":"Point"}
}