{
  "type": "Feature",
  "properties": {
    "iso:country": "GB",
    "wof:name": "E5 9HX",
    "wof:placetype": "postalcode"
  },
  "geometry": {"coordinates":[-0.057218,51.56625],"type":"Point"}
}
