{
  "type": "Feature",
  "properties": {
    "iso:country": "GB",
    "wof:name": "LL26 0TG",
    "wof:placetype": "postalcode"
  },
  "geometry": {"coordinates":[-3.760519,53.105379],"type":"Point"}
}
