{
  "type": "Feature",
  "properties": {
    "iso:country":"GB",
    "wof:name":"EH4 4PY",
    "wof:placetype":"postalcode"
},
  "geometry": {"coordinates":[-3.25530123757304,55.96928395043174],"type":"Point"}
}