{
  "type": "Feature",
  "properties": {
    "date:inception_lower":"2007-10-01",
    "date:inception_upper":"2007-10-31",
    "iso:country":"GB",
    "wof:name":"IP11 2JB",
    "wof:placetype":"postalcode"
},
  "geometry": {"coordinates":[1.332737,51.950124],"type":"Point"}
}