{
  "type": "Feature",
  "properties": {
    "iso:country":"GB",
    "wof:name":"IP11 2JB",
    "wof:placetype":"postalcode"
},
  "geometry": {"coordinates":[1.33273716682986,51.95012418900249],"type":"Point"}
}