{
  "type": "Feature",
  "properties": {
    "iso:country": "GB",
    "wof:name": "IP11 2JB",
    "wof:placetype": "postalcode"
  },
  "geometry": {"coordinates":[1.332737,51.950124],"type":"Point"}
}
