{
  "type": "Feature",
  "properties": {
    "iso:country": "GB",
    "wof:name": "SP8 5FN",
    "wof:placetype": "postalcode"
  },
  "geometry": {"coordinates":[-2.322922,51.077519],"type":"Point"}
}
