{
  "type": "Feature",
  "properties": {
    "date:inception_lower": "2018-11-01",
    "date:inception_upper": "2018-11-01",
    "iso:country": "GB",
    "wof:name": "SP8 5FN",
    "wof:placetype": "postalcode"
  },
  "geometry": {"coordinates":[-2.322922,51.077519],"type":"Point"}
}
