{
  "type": "Feature",
  "properties": {
    "iso:country":"GB",
    "wof:name":"SW6 2RB",
    "wof:placetype":"postalcode"
},
  "geometry": {"coordinates":[-0.18598912688123,51.47099476375545],"type":"Point"}
}