{
  "type": "Feature",
  "properties": {
    "date:inception_lower": "1990-02-01",
    "date:inception_upper": "1990-02-01",
    "iso:country": "GB",
    "wof:name": "GL20 8JH",
    "wof:placetype": "postalcode"
  },
  "geometry": {"coordinates":[-2.109411,52.000179],"type":"Point"}
}
