{
  "type": "Feature",
  "properties": {
    "iso:country":"GB",
    "wof:name":"GL20 8JH",
    "wof:placetype":"postalcode"
},
  "geometry": {"coordinates":[-2.10941850453799,52.00016944452517],"type":"Point"}
}