{
  "type": "Feature",
  "properties": {
    "iso:country": "GB",
    "wof:name": "DE21 7FW",
    "wof:placetype": "postalcode"
  },
  "geometry": {"coordinates":[-1.403639,52.917961],"type":"Point"}
}
