{
  "type": "Feature",
  "properties": {
    "date:inception_lower":"1997-12-01",
    "date:inception_upper":"1997-12-31",
    "iso:country":"GB",
    "wof:name":"BB3 0QY",
    "wof:placetype":"postalcode"
},
  "geometry": {"coordinates":[-2.462883,53.723182],"type":"Point"}
}