{
  "type": "Feature",
  "properties": {
    "iso:country": "GB",
    "wof:name": "BB3 0QY",
    "wof:placetype": "postalcode"
  },
  "geometry": {"coordinates":[-2.462883,53.723182],"type":"Point"}
}
