{
  "type": "Feature",
  "properties": {
    "iso:country":"GB",
    "wof:name":"BB3 0QY",
    "wof:placetype":"postalcode"
},
  "geometry": {"coordinates":[-2.46288329973847,53.72318220842082],"type":"Point"}
}