{
  "type": "Feature",
  "properties": {
    "iso:country":"GB",
    "wof:name":"SG11 1NG",
    "wof:placetype":"postalcode"
},
  "geometry": {"coordinates":[0.04448592549513,51.88413099451104],"type":"Point"}
}