{
  "type": "Feature",
  "properties": {
    "date:inception_lower":"2018-08-01",
    "date:inception_upper":"2018-08-31",
    "iso:country":"GB",
    "wof:name":"OX17 2EG",
    "wof:placetype":"postalcode"
},
  "geometry": {"coordinates":[-1.19814,52.078269],"type":"Point"}
}