{
  "type": "Feature",
  "properties": {
    "date:inception_lower": "2018-08-01",
    "date:inception_upper": "2018-08-01",
    "iso:country": "GB",
    "wof:name": "OX17 2EG",
    "wof:placetype": "postalcode"
  },
  "geometry": {"coordinates":[-1.197778,52.080586],"type":"Point"}
}
