{
  "type": "Feature",
  "properties": {
    "iso:country": "GB",
    "wof:name": "OX17 2EG",
    "wof:placetype": "postalcode"
  },
  "geometry": {"coordinates":[-1.19814,52.078269],"type":"Point"}
}
