{
  "type": "Feature",
  "properties": {
    "iso:country": "GB",
    "wof:name": "FY7 8DY",
    "wof:placetype": "postalcode"
  },
  "geometry": {"coordinates":[-3.036104,53.912351],"type":"Point"}
}
