{
  "type": "Feature",
  "properties": {
    "iso:country":"GB",
    "wof:name":"CV6 7FL",
    "wof:placetype":"postalcode"
},
  "geometry": {"coordinates":[-1.49086318435505,52.43580541570149],"type":"Point"}
}