{
  "type": "Feature",
  "properties": {
    "iso:country":"GB",
    "wof:name":"WS2 0ER",
    "wof:placetype":"postalcode"
},
  "geometry": {"coordinates":[-2.02837366783194,52.59321318698202],"type":"Point"}
}