{
  "type": "Feature",
  "properties": {
    "iso:country":"GB",
    "wof:name":"EH4 6AJ",
    "wof:placetype":"postalcode"
},
  "geometry": {"coordinates":[-3.27947440466528,55.96624082978772],"type":"Point"}
}