{
  "type": "Feature",
  "properties": {
    "iso:country":"GB",
    "wof:name":"GL6 0DU",
    "wof:placetype":"postalcode"
},
  "geometry": {"coordinates":[-2.21919891884597,51.69471957645116],"type":"Point"}
}