{
  "type": "Feature",
  "properties": {
    "iso:country": "GB",
    "wof:name": "L9 8HW",
    "wof:placetype": "postalcode"
  },
  "geometry": {"coordinates":[-2.963593,53.46815],"type":"Point"}
}
