{
  "type": "Feature",
  "properties": {
    "iso:country":"GB",
    "wof:name":"L9 8HW",
    "wof:placetype":"postalcode"
},
  "geometry": {"coordinates":[-2.9635926642473,53.46815035266257],"type":"Point"}
}