{
  "type": "Feature",
  "properties": {
    "date:inception_lower":"1998-06-01",
    "date:inception_upper":"1998-06-30",
    "iso:country":"GB",
    "wof:name":"L9 8HW",
    "wof:placetype":"postalcode"
},
  "geometry": {"coordinates":[-2.963593,53.46815],"type":"Point"}
}