{
  "type": "Feature",
  "properties": {
    "iso:country":"GB",
    "wof:name":"BS34 8PX",
    "wof:placetype":"postalcode"
},
  "geometry": {"coordinates":[-2.55989019350892,51.50926539711856],"type":"Point"}
}