{
  "type": "Feature",
  "properties": {
    "iso:country": "GB",
    "wof:name": "B43 6EN",
    "wof:placetype": "postalcode"
  },
  "geometry": {"coordinates":[-1.928445,52.55053],"type":"Point"}
}
