{
  "type": "Feature",
  "properties": {
    "iso:country":"GB",
    "wof:name":"B43 6EN",
    "wof:placetype":"postalcode"
},
  "geometry": {"coordinates":[-1.92844500125644,52.55052951239092],"type":"Point"}
}