{
  "type": "Feature",
  "properties": {
    "iso:country":"GB",
    "wof:name":"DN3 1LX",
    "wof:placetype":"postalcode"
},
  "geometry": {"coordinates":[-1.06281688388321,53.5718877465286],"type":"Point"}
}