{
  "type": "Feature",
  "properties": {
    "iso:country": "GB",
    "wof:name": "DN3 1LX",
    "wof:placetype": "postalcode"
  },
  "geometry": {"coordinates":[-1.062817,53.571888],"type":"Point"}
}
