{
  "type": "Feature",
  "properties": {
    "iso:country":"GB",
    "wof:name":"NG22 0SL",
    "wof:placetype":"postalcode"
},
  "geometry": {"coordinates":[-0.88215256329406,53.25018283286681],"type":"Point"}
}