{
  "type": "Feature",
  "properties": {
    "iso:country":"GB",
    "wof:name":"RH11 9EP",
    "wof:placetype":"postalcode"
},
  "geometry": {"coordinates":[-0.20891536150647,51.10154751392966],"type":"Point"}
}