{
  "type": "Feature",
  "properties": {
    "iso:country": "GB",
    "wof:name": "DN15 8QY",
    "wof:placetype": "postalcode"
  },
  "geometry": {"coordinates":[-0.650879,53.607369],"type":"Point"}
}
