{
  "type": "Feature",
  "properties": {
    "iso:country":"GB",
    "wof:name":"DN15 8QY",
    "wof:placetype":"postalcode"
},
  "geometry": {"coordinates":[-0.65087943010955,53.60736865500282],"type":"Point"}
}