{
  "type": "Feature",
  "properties": {
    "date:inception_lower": "1995-12-01",
    "date:inception_upper": "1995-12-01",
    "iso:country": "GB",
    "wof:name": "M44 5TJ",
    "wof:placetype": "postalcode"
  },
  "geometry": {"coordinates":[-2.441178,53.432877],"type":"Point"}
}
