{
  "type": "Feature",
  "properties": {
    "iso:country":"GB",
    "wof:name":"M44 5TJ",
    "wof:placetype":"postalcode"
},
  "geometry": {"coordinates":[-2.44117779081714,53.43287699912197],"type":"Point"}
}