{
  "type": "Feature",
  "properties": {
    "iso:country":"GB",
    "wof:name":"SW4 7LS",
    "wof:placetype":"postalcode"
},
  "geometry": {"coordinates":[-0.12890589201857,51.46236408152617],"type":"Point"}
}