{
  "type": "Feature",
  "properties": {
    "iso:country": "GB",
    "wof:name": "SG18 8NL",
    "wof:placetype": "postalcode"
  },
  "geometry": {"coordinates":[-0.265392,52.078386],"type":"Point"}
}
