{
  "type": "Feature",
  "properties": {
    "iso:country": "GB",
    "wof:name": "SO51 6JW",
    "wof:placetype": "postalcode"
  },
  "geometry": {"coordinates":[-1.574752,51.012015],"type":"Point"}
}
