{
  "type": "Feature",
  "properties": {
    "iso:country":"GB",
    "wof:name":"SO51 6JW",
    "wof:placetype":"postalcode"
},
  "geometry": {"coordinates":[-1.57475234054948,51.01201517235738],"type":"Point"}
}