{
  "type": "Feature",
  "properties": {
    "iso:country":"GB",
    "wof:name":"UB1 3JG",
    "wof:placetype":"postalcode"
},
  "geometry": {"coordinates":[-0.36305471946533,51.5170331361233],"type":"Point"}
}