{
  "type": "Feature",
  "properties": {
    "iso:country":"GB",
    "wof:name":"LE2 2AA",
    "wof:placetype":"postalcode"
},
  "geometry": {"coordinates":[-1.10711519014871,52.6184233557053],"type":"Point"}
}