{
  "type": "Feature",
  "properties": {
    "iso:country":"GB",
    "wof:name":"SR5 4BA",
    "wof:placetype":"postalcode"
},
  "geometry": {"coordinates":[-1.44435890127498,54.93147353904319],"type":"Point"}
}