{
  "type": "Feature",
  "properties": {
    "date:inception_lower":"1980-01-01",
    "date:inception_upper":"1980-01-31",
    "iso:country":"GB",
    "wof:name":"SR5 4BA",
    "wof:placetype":"postalcode"
},
  "geometry": {"coordinates":[-1.444359,54.931474],"type":"Point"}
}