{
  "type": "Feature",
  "properties": {
    "iso:country": "GB",
    "wof:name": "SR5 4BA",
    "wof:placetype": "postalcode"
  },
  "geometry": {"coordinates":[-1.444359,54.931474],"type":"Point"}
}
