{
  "type": "Feature",
  "properties": {
    "iso:country":"GB",
    "wof:name":"ST5 1NF",
    "wof:placetype":"postalcode"
},
  "geometry": {"coordinates":[-2.21976886018558,53.00573763959576],"type":"Point"}
}