{
  "type": "Feature",
  "properties": {
    "iso:country":"GB",
    "wof:name":"G33 5QP",
    "wof:placetype":"postalcode"
},
  "geometry": {"coordinates":[-4.15608227130636,55.87201068761032],"type":"Point"}
}