{
  "type": "Feature",
  "properties": {
    "iso:country":"GB",
    "wof:name":"L40 5US",
    "wof:placetype":"postalcode"
},
  "geometry": {"coordinates":[-2.82172205021761,53.59230977425705],"type":"Point"}
}