{
  "type": "Feature",
  "properties": {
    "iso:country":"GB",
    "wof:name":"CF3 3BN",
    "wof:placetype":"postalcode"
},
  "geometry": {"coordinates":[-3.12593850982309,51.50176154945615],"type":"Point"}
}