{
  "type": "Feature",
  "properties": {
    "date:inception_lower":"1980-01-01",
    "date:inception_upper":"1980-01-31",
    "iso:country":"GB",
    "wof:name":"KA9 2DL",
    "wof:placetype":"postalcode"
},
  "geometry": {"coordinates":[-4.614184,55.49085],"type":"Point"}
}