{
  "type": "Feature",
  "properties": {
    "iso:country":"GB",
    "wof:name":"SE28 8FB",
    "wof:placetype":"postalcode"
},
  "geometry": {"coordinates":[0.12032458554468,51.50619709046762],"type":"Point"}
}