{
  "type": "Feature",
  "properties": {
    "iso:country":"GB",
    "wof:name":"HA0 1YF",
    "wof:placetype":"postalcode"
},
  "geometry": {"coordinates":[-0.30850621299768,51.54686900902065],"type":"Point"}
}