{
  "type": "Feature",
  "properties": {
    "date:inception_lower":"1980-01-01",
    "date:inception_upper":"1980-01-31",
    "iso:country":"GB",
    "wof:name":"HA0 1YF",
    "wof:placetype":"postalcode"
},
  "geometry": {"coordinates":[-0.308506,51.546869],"type":"Point"}
}