{
  "type": "Feature",
  "properties": {
    "date:inception_lower": "2022-04-01",
    "date:inception_upper": "2022-04-01",
    "iso:country": "GB",
    "wof:name": "BH9 2FD",
    "wof:placetype": "postalcode"
  },
  "geometry": {"coordinates":[-1.8797,50.742358],"type":"Point"}
}
