{
  "type": "Feature",
  "properties": {
    "iso:country":"GB",
    "wof:name":"NP7 7EP",
    "wof:placetype":"postalcode"
},
  "geometry": {"coordinates":[-3.05713991845348,51.83137611765298],"type":"Point"}
}