{
  "type": "Feature",
  "properties": {
    "iso:country":"GB",
    "wof:name":"CR0 4DA",
    "wof:placetype":"postalcode"
},
  "geometry": {"coordinates":[-0.10933291095534,51.36428164710372],"type":"Point"}
}