{
  "type": "Feature",
  "properties": {
    "date:inception_lower": "1990-08-01",
    "date:inception_upper": "1990-08-01",
    "iso:country": "GB",
    "wof:name": "AB32 7BR",
    "wof:placetype": "postalcode"
  },
  "geometry": {"coordinates":[-2.370763,57.184105],"type":"Point"}
}
