{
  "type": "Feature",
  "properties": {
    "iso:country":"GB",
    "wof:name":"AB32 7BR",
    "wof:placetype":"postalcode"
},
  "geometry": {"coordinates":[-2.37181952635054,57.18445813125949],"type":"Point"}
}