{
  "type": "Feature",
  "properties": {
    "iso:country": "GB",
    "wof:name": "B93 8DD",
    "wof:placetype": "postalcode"
  },
  "geometry": {"coordinates":[-1.754078,52.374164],"type":"Point"}
}
