{
  "type": "Feature",
  "properties": {
    "iso:country":"GB",
    "wof:name":"B93 8DD",
    "wof:placetype":"postalcode"
},
  "geometry": {"coordinates":[-1.7540783798769,52.37416391787561],"type":"Point"}
}