{
  "type": "Feature",
  "properties": {
    "iso:country":"GB",
    "wof:name":"CA5 7NP",
    "wof:placetype":"postalcode"
},
  "geometry": {"coordinates":[-2.98285458530337,54.84483033586365],"type":"Point"}
}