{
  "type": "Feature",
  "properties": {
    "iso:country": "GB",
    "wof:name": "BS7 0DW",
    "wof:placetype": "postalcode"
  },
  "geometry": {"coordinates":[-2.572159,51.491376],"type":"Point"}
}
