{
  "type": "Feature",
  "properties": {
    "iso:country":"GB",
    "wof:name":"UB7 9AS",
    "wof:placetype":"postalcode"
},
  "geometry": {"coordinates":[-0.45310722298734,51.50592692267836],"type":"Point"}
}