{
  "type": "Feature",
  "properties": {
    "date:inception_lower": "1981-10-01",
    "date:inception_upper": "1981-10-01",
    "iso:country": "GB",
    "wof:name": "DG8 6PX",
    "wof:placetype": "postalcode"
  },
  "geometry": {"coordinates":[-4.483252,54.966511],"type":"Point"}
}
