{
  "type": "Feature",
  "properties": {
    "iso:country":"GB",
    "wof:name":"IP30 0BA",
    "wof:placetype":"postalcode"
},
  "geometry": {"coordinates":[0.80580464424833,52.21067998457327],"type":"Point"}
}