{
  "type": "Feature",
  "properties": {
    "iso:country": "GB",
    "wof:name": "IP30 0BA",
    "wof:placetype": "postalcode"
  },
  "geometry": {"coordinates":[0.805805,52.21068],"type":"Point"}
}
