{
  "type": "Feature",
  "properties": {
    "date:inception_lower": "1980-01-01",
    "date:inception_upper": "1980-01-01",
    "iso:country": "GB",
    "wof:name": "CT7 0JD",
    "wof:placetype": "postalcode"
  },
  "geometry": {"coordinates":[1.311892,51.353914],"type":"Point"}
}
