{
  "type": "Feature",
  "properties": {
    "iso:country":"GB",
    "wof:name":"CT7 0JD",
    "wof:placetype":"postalcode"
},
  "geometry": {"coordinates":[1.31195137325403,51.35391402164858],"type":"Point"}
}