{
  "type": "Feature",
  "properties": {
    "iso:country":"GB",
    "wof:name":"DN2 4AQ",
    "wof:placetype":"postalcode"
},
  "geometry": {"coordinates":[-1.12070785031293,53.52999065904822],"type":"Point"}
}