{
  "type": "Feature",
  "properties": {
    "iso:country":"GB",
    "wof:name":"CV11 5HQ",
    "wof:placetype":"postalcode"
},
  "geometry": {"coordinates":[-1.4798305514097,52.52453420032385],"type":"Point"}
}