{
  "type": "Feature",
  "properties": {
    "date:inception_lower": "1980-01-01",
    "date:inception_upper": "1980-01-01",
    "iso:country": "GB",
    "wof:name": "CV11 5HQ",
    "wof:placetype": "postalcode"
  },
  "geometry": {"coordinates":[-1.479524,52.524263],"type":"Point"}
}
