{
  "type": "Feature",
  "properties": {
    "date:inception_lower":"1996-06-01",
    "date:inception_upper":"1996-06-30",
    "iso:country":"GB",
    "wof:name":"AB25 1LN",
    "wof:placetype":"postalcode"
},
  "geometry": {"coordinates":[-2.103018,57.150868],"type":"Point"}
}