{
  "type": "Feature",
  "properties": {
    "iso:country":"GB",
    "wof:name":"AB25 1LN",
    "wof:placetype":"postalcode"
},
  "geometry": {"coordinates":[-2.10301804616217,57.15086758604293],"type":"Point"}
}