{
  "type": "Feature",
  "properties": {
    "iso:country":"GB",
    "wof:name":"SM1 1DF",
    "wof:placetype":"postalcode"
},
  "geometry": {"coordinates":[-0.19197228749793,51.35999279045988],"type":"Point"}
}