{
  "type": "Feature",
  "properties": {
    "date:inception_lower": "1980-01-01",
    "date:inception_upper": "1980-01-01",
    "iso:country": "GB",
    "wof:name": "SM1 1DF",
    "wof:placetype": "postalcode"
  },
  "geometry": {"coordinates":[-0.191947,51.359992],"type":"Point"}
}
