{
  "type": "Feature",
  "properties": {
    "date:inception_lower": "2018-01-01",
    "date:inception_upper": "2018-01-01",
    "iso:country": "GB",
    "wof:name": "WA5 3UP",
    "wof:placetype": "postalcode"
  },
  "geometry": {"coordinates":[-2.673872,53.395591],"type":"Point"}
}
