{
  "type": "Feature",
  "properties": {
    "iso:country":"GB",
    "wof:name":"RG18 9UU",
    "wof:placetype":"postalcode"
},
  "geometry": {"coordinates":[-1.23199875466899,51.44416861633186],"type":"Point"}
}