{
  "type": "Feature",
  "properties": {
    "iso:country":"GB",
    "wof:name":"G14 0QL",
    "wof:placetype":"postalcode"
},
  "geometry": {"coordinates":[-4.37857281629467,55.88833038005541],"type":"Point"}
}