{
  "type": "Feature",
  "properties": {
    "date:inception_lower": "1980-01-01",
    "date:inception_upper": "1980-01-01",
    "iso:country": "GB",
    "wof:name": "G14 0QL",
    "wof:placetype": "postalcode"
  },
  "geometry": {"coordinates":[-4.378573,55.88833],"type":"Point"}
}
