{
  "type": "Feature",
  "properties": {
    "iso:country":"GB",
    "wof:name":"PR5 4BQ",
    "wof:placetype":"postalcode"
},
  "geometry": {"coordinates":[-2.66160602436565,53.74696699734135],"type":"Point"}
}