{
  "type": "Feature",
  "properties": {
    "iso:country": "GB",
    "wof:name": "EH3 8EX",
    "wof:placetype": "postalcode"
  },
  "geometry": {"coordinates":[-3.208381,55.945892],"type":"Point"}
}
