{
  "type": "Feature",
  "properties": {
    "iso:country":"GB",
    "wof:name":"WS9 0SJ",
    "wof:placetype":"postalcode"
},
  "geometry": {"coordinates":[-1.89899446188965,52.58889466576396],"type":"Point"}
}