{
  "type": "Feature",
  "properties": {
    "iso:country":"GB",
    "wof:name":"BN1 8UG",
    "wof:placetype":"postalcode"
},
  "geometry": {"coordinates":[-0.14424697841231,50.86626506999831],"type":"Point"}
}