{
  "type": "Feature",
  "properties": {
    "date:inception_lower": "2007-09-01",
    "date:inception_upper": "2007-09-01",
    "iso:country": "GB",
    "wof:name": "BH20 6NA",
    "wof:placetype": "postalcode"
  },
  "geometry": {"coordinates":[-2.234589,50.677708],"type":"Point"}
}
