{
  "type": "Feature",
  "properties": {
    "iso:country":"GB",
    "wof:name":"HX1 4HW",
    "wof:placetype":"postalcode"
},
  "geometry": {"coordinates":[-1.8908105735993,53.72003700267248],"type":"Point"}
}