{
  "type": "Feature",
  "properties": {
    "date:inception_lower":"1980-01-01",
    "date:inception_upper":"1980-01-31",
    "iso:country":"GB",
    "wof:name":"SY8 4AX",
    "wof:placetype":"postalcode"
},
  "geometry": {"coordinates":[-2.669165,52.306786],"type":"Point"}
}