{
  "type": "Feature",
  "properties": {
    "iso:country": "GB",
    "wof:name": "SY8 4AX",
    "wof:placetype": "postalcode"
  },
  "geometry": {"coordinates":[-2.669165,52.306786],"type":"Point"}
}
