{
  "type": "Feature",
  "properties": {
    "iso:country":"GB",
    "wof:name":"SY8 4AX",
    "wof:placetype":"postalcode"
},
  "geometry": {"coordinates":[-2.6691653673817,52.30678618803607],"type":"Point"}
}