{
  "type": "Feature",
  "properties": {
    "iso:country":"GB",
    "wof:name":"OX4 4RQ",
    "wof:placetype":"postalcode"
},
  "geometry": {"coordinates":[-1.22652476458832,51.72598976465265],"type":"Point"}
}