{
  "type": "Feature",
  "properties": {
    "iso:country": "GB",
    "wof:name": "NG32 3AW",
    "wof:placetype": "postalcode"
  },
  "geometry": {"coordinates":[-0.581099,52.99546],"type":"Point"}
}
