{
  "type": "Feature",
  "properties": {
    "date:inception_lower": "1994-05-01",
    "date:inception_upper": "1994-05-01",
    "iso:country": "GB",
    "wof:name": "NG32 3AW",
    "wof:placetype": "postalcode"
  },
  "geometry": {"coordinates":[-0.581099,52.99546],"type":"Point"}
}
