{
  "type": "Feature",
  "properties": {
    "iso:country":"GB",
    "wof:name":"NG32 3AW",
    "wof:placetype":"postalcode"
},
  "geometry": {"coordinates":[-0.58146950984823,52.99567619434075],"type":"Point"}
}