{
  "type": "Feature",
  "properties": {
    "iso:country":"GB",
    "wof:name":"CB6 1RH",
    "wof:placetype":"postalcode"
},
  "geometry": {"coordinates":[0.27607259219221,52.46945036935669],"type":"Point"}
}