{
  "type": "Feature",
  "properties": {
    "iso:country":"GB",
    "wof:name":"WV16 6LG",
    "wof:placetype":"postalcode"
},
  "geometry": {"coordinates":[-2.38173971218135,52.44957956559764],"type":"Point"}
}