{
  "type": "Feature",
  "properties": {
    "iso:country":"GB",
    "wof:name":"B77 3QD",
    "wof:placetype":"postalcode"
},
  "geometry": {"coordinates":[-1.66049811713863,52.63787757297698],"type":"Point"}
}