{
  "type": "Feature",
  "properties": {
    "iso:country": "GB",
    "wof:name": "BN6 9FZ",
    "wof:placetype": "postalcode"
  },
  "geometry": {"coordinates":[-0.174767,50.943536],"type":"Point"}
}
