{
  "type": "Feature",
  "properties": {
    "date:inception_lower":"1980-01-01",
    "date:inception_upper":"1980-01-31",
    "iso:country":"GB",
    "wof:name":"PL18 9AZ",
    "wof:placetype":"postalcode"
},
  "geometry": {"coordinates":[-4.251059,50.525231],"type":"Point"}
}