{
  "type": "Feature",
  "properties": {
    "iso:country":"GB",
    "wof:name":"PL18 9AZ",
    "wof:placetype":"postalcode"
},
  "geometry": {"coordinates":[-4.25105889826764,50.52523121693137],"type":"Point"}
}