{
  "type": "Feature",
  "properties": {
    "iso:country":"GB",
    "wof:name":"S64 8DJ",
    "wof:placetype":"postalcode"
},
  "geometry": {"coordinates":[-1.32245332400173,53.48944377115468],"type":"Point"}
}