{
  "type": "Feature",
  "properties": {
    "iso:country": "GB",
    "wof:name": "BB7 3NA",
    "wof:placetype": "postalcode"
  },
  "geometry": {"coordinates":[-2.45677,53.888801],"type":"Point"}
}
