{
  "type": "Feature",
  "properties": {
    "date:inception_lower":"2005-05-01",
    "date:inception_upper":"2005-05-31",
    "iso:country":"GB",
    "wof:name":"SO40 4BJ",
    "wof:placetype":"postalcode"
},
  "geometry": {"coordinates":[-1.442141,50.897218],"type":"Point"}
}