{
  "type": "Feature",
  "properties": {
    "iso:country":"GB",
    "wof:name":"LS4 2HY",
    "wof:placetype":"postalcode"
},
  "geometry": {"coordinates":[-1.58210291964442,53.80825981332363],"type":"Point"}
}