{
  "type": "Feature",
  "properties": {
    "iso:country":"GB",
    "wof:name":"TA10 9DS",
    "wof:placetype":"postalcode"
},
  "geometry": {"coordinates":[-2.81096911505134,51.06062592714042],"type":"Point"}
}