{
  "type": "Feature",
  "properties": {
    "date:inception_lower": "1980-01-01",
    "date:inception_upper": "1980-01-01",
    "iso:country": "GB",
    "wof:name": "TA10 9DS",
    "wof:placetype": "postalcode"
  },
  "geometry": {"coordinates":[-2.810969,51.060626],"type":"Point"}
}
