{
  "type": "Feature",
  "properties": {
    "iso:country":"GB",
    "wof:name":"WA6 7AL",
    "wof:placetype":"postalcode"
},
  "geometry": {"coordinates":[-2.72457403564043,53.29770396120338],"type":"Point"}
}