{
  "type": "Feature",
  "properties": {
    "date:inception_lower": "2014-02-01",
    "date:inception_upper": "2014-02-01",
    "iso:country": "GB",
    "wof:name": "TF4 2GD",
    "wof:placetype": "postalcode"
  },
  "geometry": {"coordinates":[-2.488102,52.672264],"type":"Point"}
}
