{
  "type": "Feature",
  "properties": {
    "iso:country":"GB",
    "wof:name":"IP19 8SY",
    "wof:placetype":"postalcode"
},
  "geometry": {"coordinates":[1.49959564594105,52.34209302179169],"type":"Point"}
}