{
  "type": "Feature",
  "properties": {
    "iso:country": "GB",
    "wof:name": "IP19 8SY",
    "wof:placetype": "postalcode"
  },
  "geometry": {"coordinates":[1.499863,52.342144],"type":"Point"}
}
