{
  "type": "Feature",
  "properties": {
    "date:inception_lower":"2001-06-01",
    "date:inception_upper":"2001-06-30",
    "iso:country":"GB",
    "wof:name":"IP19 8SY",
    "wof:placetype":"postalcode"
},
  "geometry": {"coordinates":[1.499863,52.342144],"type":"Point"}
}