{
  "type": "Feature",
  "properties": {
    "date:inception_lower": "2017-05-01",
    "date:inception_upper": "2017-05-01",
    "iso:country": "GB",
    "wof:name": "SG18 8SZ",
    "wof:placetype": "postalcode"
  },
  "geometry": {"coordinates":[-0.242147,52.092437],"type":"Point"}
}
