{
  "type": "Feature",
  "properties": {
    "date:inception_lower":"1980-01-01",
    "date:inception_upper":"1980-01-31",
    "iso:country":"GB",
    "wof:name":"NE15 8DU",
    "wof:placetype":"postalcode"
},
  "geometry": {"coordinates":[-1.715571,54.977988],"type":"Point"}
}