{
  "type": "Feature",
  "properties": {
    "iso:country":"GB",
    "wof:name":"NE15 8DU",
    "wof:placetype":"postalcode"
},
  "geometry": {"coordinates":[-1.7155715308571,54.97798833559798],"type":"Point"}
}