{
  "type": "Feature",
  "properties": {
    "iso:country": "GB",
    "wof:name": "NE15 8DU",
    "wof:placetype": "postalcode"
  },
  "geometry": {"coordinates":[-1.715571,54.977988],"type":"Point"}
}
