{
  "type": "Feature",
  "properties": {
    "iso:country":"GB",
    "wof:name":"PO11 9HZ",
    "wof:placetype":"postalcode"
},
  "geometry": {"coordinates":[-0.97472872669815,50.78405036507724],"type":"Point"}
}