{
  "type": "Feature",
  "properties": {
    "date:inception_lower": "1983-03-01",
    "date:inception_upper": "1983-03-01",
    "iso:country": "GB",
    "wof:name": "PO11 9HZ",
    "wof:placetype": "postalcode"
  },
  "geometry": {"coordinates":[-0.974729,50.78405],"type":"Point"}
}
