{
  "type": "Feature",
  "properties": {
    "iso:country":"GB",
    "wof:name":"OX28 6FY",
    "wof:placetype":"postalcode"
},
  "geometry": {"coordinates":[-1.48293557376496,51.78656788473829],"type":"Point"}
}