{
  "type": "Feature",
  "properties": {
    "date:inception_lower": "2007-05-01",
    "date:inception_upper": "2007-05-01",
    "iso:country": "GB",
    "wof:name": "OX28 6FY",
    "wof:placetype": "postalcode"
  },
  "geometry": {"coordinates":[-1.482936,51.786568],"type":"Point"}
}
