{
  "type": "Feature",
  "properties": {
    "iso:country":"GB",
    "wof:name":"CR4 1QE",
    "wof:placetype":"postalcode"
},
  "geometry": {"coordinates":[-0.13166093087102,51.397697041496],"type":"Point"}
}