{
  "type": "Feature",
  "properties": {
    "date:inception_lower": "1980-01-01",
    "date:inception_upper": "1980-01-01",
    "iso:country": "GB",
    "wof:name": "KA13 7HF",
    "wof:placetype": "postalcode"
  },
  "geometry": {"coordinates":[-4.705899,55.655007],"type":"Point"}
}
