{
  "type": "Feature",
  "properties": {
    "iso:country":"GB",
    "wof:name":"KA13 7HF",
    "wof:placetype":"postalcode"
},
  "geometry": {"coordinates":[-4.70589919917313,55.65500693150468],"type":"Point"}
}