{
  "type": "Feature",
  "properties": {
    "date:inception_lower": "2024-10-01",
    "date:inception_upper": "2024-10-01",
    "iso:country": "GB",
    "wof:name": "IP30 9WJ",
    "wof:placetype": "postalcode"
  },
  "geometry": {"coordinates":[0.886015,52.230085],"type":"Point"}
}
