{
  "type": "Feature",
  "properties": {
    "iso:country": "GB",
    "wof:name": "TW17 8SJ",
    "wof:placetype": "postalcode"
  },
  "geometry": {"coordinates":[-0.432611,51.405058],"type":"Point"}
}
