{
  "type": "Feature",
  "properties": {
    "date:inception_lower": "1980-01-01",
    "date:inception_upper": "1980-01-01",
    "iso:country": "GB",
    "wof:name": "TW17 8SJ",
    "wof:placetype": "postalcode"
  },
  "geometry": {"coordinates":[-0.43261,51.405094],"type":"Point"}
}
