{
  "type": "Feature",
  "properties": {
    "iso:country":"GB",
    "wof:name":"TW17 8SJ",
    "wof:placetype":"postalcode"
},
  "geometry": {"coordinates":[-0.43263073812557,51.40509441542611],"type":"Point"}
}