{
  "type": "Feature",
  "properties": {
    "iso:country":"GB",
    "wof:name":"LA4 4JG",
    "wof:placetype":"postalcode"
},
  "geometry": {"coordinates":[-2.87507411914195,54.06619509572977],"type":"Point"}
}