{
  "type": "Feature",
  "properties": {
    "iso:country":"GB",
    "wof:name":"AL3 8AZ",
    "wof:placetype":"postalcode"
},
  "geometry": {"coordinates":[-0.45505340179375,51.8073364900311],"type":"Point"}
}