{
  "type": "Feature",
  "properties": {
    "iso:country":"GB",
    "wof:name":"SE16 2LX",
    "wof:placetype":"postalcode"
},
  "geometry": {"coordinates":[-0.04325346906657,51.49187358763319],"type":"Point"}
}