{
  "type": "Feature",
  "properties": {
    "iso:country":"GB",
    "wof:name":"PO7 6LX",
    "wof:placetype":"postalcode"
},
  "geometry": {"coordinates":[-1.07875084047798,50.90595097071869],"type":"Point"}
}