{
  "type": "Feature",
  "properties": {
    "date:inception_lower": "1992-01-01",
    "date:inception_upper": "1992-01-01",
    "iso:country": "GB",
    "wof:name": "LD3 0YJ",
    "wof:placetype": "postalcode"
  },
  "geometry": {"coordinates":[-3.269656,52.039922],"type":"Point"}
}
