{
  "type": "Feature",
  "properties": {
    "date:inception_lower": "1990-02-01",
    "date:inception_upper": "1990-02-01",
    "iso:country": "GB",
    "wof:name": "BB9 0XF",
    "wof:placetype": "postalcode"
  },
  "geometry": {"coordinates":[-2.207792,53.82671],"type":"Point"}
}
