{
  "type": "Feature",
  "properties": {
    "date:inception_lower": "2016-08-01",
    "date:inception_upper": "2016-08-01",
    "iso:country": "GB",
    "wof:name": "BS1 6WW",
    "wof:placetype": "postalcode"
  },
  "geometry": {"coordinates":[-2.599556,51.446342],"type":"Point"}
}
