{
  "type": "Feature",
  "properties": {
    "date:inception_lower":"1980-01-01",
    "date:inception_upper":"1980-01-31",
    "iso:country":"GB",
    "wof:name":"RG10 8QL",
    "wof:placetype":"postalcode"
},
  "geometry": {"coordinates":[-0.843899,51.523863],"type":"Point"}
}