{
  "type": "Feature",
  "properties": {
    "iso:country": "GB",
    "wof:name": "UB2 4DW",
    "wof:placetype": "postalcode"
  },
  "geometry": {"coordinates":[-0.380802,51.499007],"type":"Point"}
}
