{
  "type": "Feature",
  "properties": {
    "iso:country":"GB",
    "wof:name":"UB2 4DW",
    "wof:placetype":"postalcode"
},
  "geometry": {"coordinates":[-0.38080188489229,51.49900718481174],"type":"Point"}
}