{
  "type": "Feature",
  "properties": {
    "iso:country":"GB",
    "wof:name":"EC4V 5DT",
    "wof:placetype":"postalcode"
},
  "geometry": {"coordinates":[-0.10173220500753,51.5128522671171],"type":"Point"}
}