{
  "type": "Feature",
  "properties": {
    "iso:country":"GB",
    "wof:name":"EH1 1SG",
    "wof:placetype":"postalcode"
},
  "geometry": {"coordinates":[-3.18640963370212,55.9505488861166],"type":"Point"}
}