{
  "type": "Feature",
  "properties": {
    "iso:country":"GB",
    "wof:name":"WF10 5HS",
    "wof:placetype":"postalcode"
},
  "geometry": {"coordinates":[-1.36946712172361,53.71646951960727],"type":"Point"}
}