{
  "type": "Feature",
  "properties": {
    "iso:country": "GB",
    "wof:name": "CB2 9EB",
    "wof:placetype": "postalcode"
  },
  "geometry": {"coordinates":[0.105181,52.172161],"type":"Point"}
}
