{
  "type": "Feature",
  "properties": {
    "iso:country":"GB",
    "wof:name":"CB2 9EB",
    "wof:placetype":"postalcode"
},
  "geometry": {"coordinates":[0.10545347628375,52.17201747846871],"type":"Point"}
}