{
  "type": "Feature",
  "properties": {
    "iso:country":"GB",
    "wof:name":"NE70 7NH",
    "wof:placetype":"postalcode"
},
  "geometry": {"coordinates":[-1.82899892304801,55.59809973512428],"type":"Point"}
}