{
  "type": "Feature",
  "properties": {
    "date:inception_lower": "1980-01-01",
    "date:inception_upper": "1980-01-01",
    "iso:country": "GB",
    "wof:name": "PE1 3RW",
    "wof:placetype": "postalcode"
  },
  "geometry": {"coordinates":[-0.242591,52.597469],"type":"Point"}
}
