{
  "type": "Feature",
  "properties": {
    "iso:country": "GB",
    "wof:name": "PE1 3RW",
    "wof:placetype": "postalcode"
  },
  "geometry": {"coordinates":[-0.242591,52.597469],"type":"Point"}
}
