{
  "type": "Feature",
  "properties": {
    "iso:country": "GB",
    "wof:name": "CW2 5NX",
    "wof:placetype": "postalcode"
  },
  "geometry": {"coordinates":[-2.355193,53.080856],"type":"Point"}
}
