{
  "type": "Feature",
  "properties": {
    "iso:country":"GB",
    "wof:name":"CW2 5NX",
    "wof:placetype":"postalcode"
},
  "geometry": {"coordinates":[-2.35519347189213,53.08085588155625],"type":"Point"}
}