{
  "type": "Feature",
  "properties": {
    "iso:country": "GB",
    "wof:name": "B24 9FQ",
    "wof:placetype": "postalcode"
  },
  "geometry": {"coordinates":[-1.807695,52.510764],"type":"Point"}
}
