{
  "type": "Feature",
  "properties": {
    "date:inception_lower": "1997-12-01",
    "date:inception_upper": "1997-12-01",
    "iso:country": "GB",
    "wof:name": "B24 9FQ",
    "wof:placetype": "postalcode"
  },
  "geometry": {"coordinates":[-1.809453,52.509787],"type":"Point"}
}
