{
  "type": "Feature",
  "properties": {
    "iso:country":"GB",
    "wof:name":"B24 9FQ",
    "wof:placetype":"postalcode"
},
  "geometry": {"coordinates":[-1.80945978710662,52.50977274626175],"type":"Point"}
}