{
  "type": "Feature",
  "properties": {
    "iso:country":"GB",
    "wof:name":"GL16 7NT",
    "wof:placetype":"postalcode"
},
  "geometry": {"coordinates":[-2.62236561578759,51.81809944724053],"type":"Point"}
}