{
  "type": "Feature",
  "properties": {
    "date:inception_lower": "2023-06-01",
    "date:inception_upper": "2023-06-01",
    "iso:country": "GB",
    "wof:name": "CO10 1AU",
    "wof:placetype": "postalcode"
  },
  "geometry": {"coordinates":[0.743409,52.052968],"type":"Point"}
}
