{
  "type": "Feature",
  "properties": {
    "iso:country":"GB",
    "wof:name":"M44 6PT",
    "wof:placetype":"postalcode"
},
  "geometry": {"coordinates":[-2.41922125272307,53.45463652845709],"type":"Point"}
}