{
  "type": "Feature",
  "properties": {
    "iso:country": "GB",
    "wof:name": "M44 6PT",
    "wof:placetype": "postalcode"
  },
  "geometry": {"coordinates":[-2.419221,53.454637],"type":"Point"}
}
