{
  "type": "Feature",
  "properties": {
    "iso:country": "GB",
    "wof:name": "DA2 6FR",
    "wof:placetype": "postalcode"
  },
  "geometry": {"coordinates":[0.24431,51.444257],"type":"Point"}
}
