{
  "type": "Feature",
  "properties": {
    "iso:country":"GB",
    "wof:name":"S18 2LG",
    "wof:placetype":"postalcode"
},
  "geometry": {"coordinates":[-1.46857513997106,53.30445850014863],"type":"Point"}
}