{
  "type": "Feature",
  "properties": {
    "date:inception_lower": "1997-06-01",
    "date:inception_upper": "1997-06-01",
    "iso:country": "GB",
    "wof:name": "S18 2LG",
    "wof:placetype": "postalcode"
  },
  "geometry": {"coordinates":[-1.468575,53.304458],"type":"Point"}
}
