{
  "type": "Feature",
  "properties": {
    "iso:country":"GB",
    "wof:name":"NG9 5LE",
    "wof:placetype":"postalcode"
},
  "geometry": {"coordinates":[-1.23879929289245,52.91503261339255],"type":"Point"}
}