{
  "type": "Feature",
  "properties": {
    "iso:country": "GB",
    "wof:name": "HP21 9JL",
    "wof:placetype": "postalcode"
  },
  "geometry": {"coordinates":[-0.816203,51.797644],"type":"Point"}
}
