{
  "type": "Feature",
  "properties": {
    "date:inception_lower": "1993-08-01",
    "date:inception_upper": "1993-08-01",
    "iso:country": "GB",
    "wof:name": "DN35 0SY",
    "wof:placetype": "postalcode"
  },
  "geometry": {"coordinates":[-0.037133,53.537762],"type":"Point"}
}
