{
  "type": "Feature",
  "properties": {
    "iso:country":"GB",
    "wof:name":"DN35 0SY",
    "wof:placetype":"postalcode"
},
  "geometry": {"coordinates":[-0.03713353327398,53.53776199403201],"type":"Point"}
}