{
  "type": "Feature",
  "properties": {
    "iso:country": "GB",
    "wof:name": "DN35 0SY",
    "wof:placetype": "postalcode"
  },
  "geometry": {"coordinates":[-0.037133,53.537762],"type":"Point"}
}
