{
  "type": "Feature",
  "properties": {
    "iso:country": "GB",
    "wof:name": "PE24 5UH",
    "wof:placetype": "postalcode"
  },
  "geometry": {"coordinates":[0.327983,53.222873],"type":"Point"}
}
