{
  "type": "Feature",
  "properties": {
    "iso:country":"GB",
    "wof:name":"PE24 5UH",
    "wof:placetype":"postalcode"
},
  "geometry": {"coordinates":[0.32792277717301,53.22285565407962],"type":"Point"}
}