{
  "type": "Feature",
  "properties": {
    "iso:country":"GB",
    "wof:name":"SO31 6NE",
    "wof:placetype":"postalcode"
},
  "geometry": {"coordinates":[-1.26667959810108,50.85827269029827],"type":"Point"}
}