{
  "type": "Feature",
  "properties": {
    "iso:country": "GB",
    "wof:name": "SO31 6NE",
    "wof:placetype": "postalcode"
  },
  "geometry": {"coordinates":[-1.26668,50.858273],"type":"Point"}
}
