{
  "type": "Feature",
  "properties": {
    "iso:country": "GB",
    "wof:name": "HR3 5EG",
    "wof:placetype": "postalcode"
  },
  "geometry": {"coordinates":[-3.133238,52.071272],"type":"Point"}
}
