{
  "type": "Feature",
  "properties": {
    "iso:country":"GB",
    "wof:name":"HR3 5EG",
    "wof:placetype":"postalcode"
},
  "geometry": {"coordinates":[-3.13323817003319,52.07127158229763],"type":"Point"}
}