{
  "type": "Feature",
  "properties": {
    "date:inception_lower": "2023-05-01",
    "date:inception_upper": "2023-05-01",
    "iso:country": "GB",
    "wof:name": "CV11 7AP",
    "wof:placetype": "postalcode"
  },
  "geometry": {"coordinates":[-1.433771,52.536369],"type":"Point"}
}
