{
  "type": "Feature",
  "properties": {
    "iso:country":"GB",
    "wof:name":"DE7 8TF",
    "wof:placetype":"postalcode"
},
  "geometry": {"coordinates":[-1.31649587908073,52.98632341967618],"type":"Point"}
}