{
  "type": "Feature",
  "properties": {
    "date:inception_lower": "1980-01-01",
    "date:inception_upper": "1980-01-01",
    "iso:country": "GB",
    "wof:name": "PE12 0PN",
    "wof:placetype": "postalcode"
  },
  "geometry": {"coordinates":[-0.026686,52.683595],"type":"Point"}
}
