{
  "type": "Feature",
  "properties": {
    "iso:country": "GB",
    "wof:name": "PE12 0PN",
    "wof:placetype": "postalcode"
  },
  "geometry": {"coordinates":[-0.026409,52.68384],"type":"Point"}
}
