{
  "type": "Feature",
  "properties": {
    "date:inception_lower": "1980-01-01",
    "date:inception_upper": "1980-01-01",
    "iso:country": "GB",
    "wof:name": "IP9 1QH",
    "wof:placetype": "postalcode"
  },
  "geometry": {"coordinates":[1.267574,51.961762],"type":"Point"}
}
