{
  "type": "Feature",
  "properties": {
    "iso:country": "GB",
    "wof:name": "IP9 1QH",
    "wof:placetype": "postalcode"
  },
  "geometry": {"coordinates":[1.267534,51.961811],"type":"Point"}
}
