{
  "type": "Feature",
  "properties": {
    "iso:country":"GB",
    "wof:name":"IP9 1QH",
    "wof:placetype":"postalcode"
},
  "geometry": {"coordinates":[1.26753357556938,51.9618112504012],"type":"Point"}
}