{
  "type": "Feature",
  "properties": {
    "iso:country":"GB",
    "wof:name":"RH1 4HG",
    "wof:placetype":"postalcode"
},
  "geometry": {"coordinates":[-0.1321162378332,51.23953919614144],"type":"Point"}
}