{
  "type": "Feature",
  "properties": {
    "iso:country": "GB",
    "wof:name": "RH1 4HG",
    "wof:placetype": "postalcode"
  },
  "geometry": {"coordinates":[-0.132116,51.239539],"type":"Point"}
}
