{
  "type": "Feature",
  "properties": {
    "iso:country":"GB",
    "wof:name":"RG18 4ND",
    "wof:placetype":"postalcode"
},
  "geometry": {"coordinates":[-1.25790608604571,51.40462785006887],"type":"Point"}
}