{
  "type": "Feature",
  "properties": {
    "date:inception_lower": "1980-01-01",
    "date:inception_upper": "1980-01-01",
    "iso:country": "GB",
    "wof:name": "S6 6DU",
    "wof:placetype": "postalcode"
  },
  "geometry": {"coordinates":[-1.539173,53.391502],"type":"Point"}
}
