{
  "type": "Feature",
  "properties": {
    "iso:country":"GB",
    "wof:name":"SY4 4QY",
    "wof:placetype":"postalcode"
},
  "geometry": {"coordinates":[-2.61883072822415,52.72734494280648],"type":"Point"}
}