{
  "type": "Feature",
  "properties": {
    "iso:country": "GB",
    "wof:name": "SY4 4QY",
    "wof:placetype": "postalcode"
  },
  "geometry": {"coordinates":[-2.618829,52.72736],"type":"Point"}
}
