{
  "type": "Feature",
  "properties": {
    "date:inception_lower": "1980-01-01",
    "date:inception_upper": "1980-01-01",
    "iso:country": "GB",
    "wof:name": "SY4 4QY",
    "wof:placetype": "postalcode"
  },
  "geometry": {"coordinates":[-2.618592,52.727362],"type":"Point"}
}
