{
  "type": "Feature",
  "properties": {
    "date:inception_lower": "1980-01-01",
    "date:inception_upper": "1980-01-01",
    "iso:country": "GB",
    "wof:name": "DN17 2AA",
    "wof:placetype": "postalcode"
  },
  "geometry": {"coordinates":[-0.689741,53.564926],"type":"Point"}
}
