{
  "type": "Feature",
  "properties": {
    "iso:country":"GB",
    "wof:name":"DN17 2AA",
    "wof:placetype":"postalcode"
},
  "geometry": {"coordinates":[-0.6898212346,53.56513964899416],"type":"Point"}
}