{
  "type": "Feature",
  "properties": {
    "iso:country":"GB",
    "wof:name":"DG7 1PB",
    "wof:placetype":"postalcode"
},
  "geometry": {"coordinates":[-3.84714798547506,54.93765716891568],"type":"Point"}
}