{
  "type": "Feature",
  "properties": {
    "iso:country":"GB",
    "wof:name":"DN17 3SQ",
    "wof:placetype":"postalcode"
},
  "geometry": {"coordinates":[-0.65430290731425,53.53958501905047],"type":"Point"}
}