{
  "type": "Feature",
  "properties": {
    "iso:country": "GB",
    "wof:name": "DN17 3SQ",
    "wof:placetype": "postalcode"
  },
  "geometry": {"coordinates":[-0.654303,53.539585],"type":"Point"}
}
