{
  "type": "Feature",
  "properties": {
    "iso:country":"GB",
    "wof:name":"B48 7JD",
    "wof:placetype":"postalcode"
},
  "geometry": {"coordinates":[-1.88463080351543,52.3525171090654],"type":"Point"}
}