{
  "type": "Feature",
  "properties": {
    "iso:country":"GB",
    "wof:name":"BA22 7QQ",
    "wof:placetype":"postalcode"
},
  "geometry": {"coordinates":[-2.60779463088842,51.01783322000554],"type":"Point"}
}