{
  "type": "Feature",
  "properties": {
    "iso:country":"GB",
    "wof:name":"IP22 1RD",
    "wof:placetype":"postalcode"
},
  "geometry": {"coordinates":[1.0417210696233,52.35402317177377],"type":"Point"}
}