{
  "type": "Feature",
  "properties": {
    "iso:country":"GB",
    "wof:name":"LN11 0BS",
    "wof:placetype":"postalcode"
},
  "geometry": {"coordinates":[0.00330079031845,53.37277085796159],"type":"Point"}
}