{
  "type": "Feature",
  "properties": {
    "date:inception_lower":"1980-01-01",
    "date:inception_upper":"1980-01-31",
    "iso:country":"GB",
    "wof:name":"PL28 8QQ",
    "wof:placetype":"postalcode"
},
  "geometry": {"coordinates":[-4.97181,50.539025],"type":"Point"}
}