{
  "type": "Feature",
  "properties": {
    "iso:country":"GB",
    "wof:name":"PL28 8QQ",
    "wof:placetype":"postalcode"
},
  "geometry": {"coordinates":[-4.97180975489729,50.5390250619347],"type":"Point"}
}