{
  "type": "Feature",
  "properties": {
    "iso:country": "GB",
    "wof:name": "UB3 1TG",
    "wof:placetype": "postalcode"
  },
  "geometry": {"coordinates":[-0.432611,51.50106],"type":"Point"}
}
