{
  "type": "Feature",
  "properties": {
    "iso:country":"GB",
    "wof:name":"UB3 1TG",
    "wof:placetype":"postalcode"
},
  "geometry": {"coordinates":[-0.43261139925574,51.50105981576578],"type":"Point"}
}