{
  "type": "Feature",
  "properties": {
    "date:inception_lower": "1980-01-01",
    "date:inception_upper": "1980-01-01",
    "iso:country": "GB",
    "wof:name": "UB3 1TG",
    "wof:placetype": "postalcode"
  },
  "geometry": {"coordinates":[-0.432611,51.50106],"type":"Point"}
}
