{
  "type": "Feature",
  "properties": {
    "date:inception_lower": "2023-07-01",
    "date:inception_upper": "2023-07-01",
    "iso:country": "GB",
    "wof:name": "G31 1JE",
    "wof:placetype": "postalcode"
  },
  "geometry": {"coordinates":[-4.226948,55.858359],"type":"Point"}
}
