{
  "type": "Feature",
  "properties": {
    "date:inception_lower": "1992-08-01",
    "date:inception_upper": "1992-08-01",
    "iso:country": "GB",
    "wof:name": "CH1 6DQ",
    "wof:placetype": "postalcode"
  },
  "geometry": {"coordinates":[-2.956758,53.223543],"type":"Point"}
}
