{
  "type": "Feature",
  "properties": {
    "iso:country":"GB",
    "wof:name":"M18 7PN",
    "wof:placetype":"postalcode"
},
  "geometry": {"coordinates":[-2.17770136643006,53.45418870568864],"type":"Point"}
}