{
  "type": "Feature",
  "properties": {
    "date:inception_lower": "2000-06-01",
    "date:inception_upper": "2000-06-01",
    "iso:country": "GB",
    "wof:name": "CA7 2EE",
    "wof:placetype": "postalcode"
  },
  "geometry": {"coordinates":[-3.316615,54.762813],"type":"Point"}
}
