{
  "type": "Feature",
  "properties": {
    "iso:country":"GB",
    "wof:name":"CA7 2EE",
    "wof:placetype":"postalcode"
},
  "geometry": {"coordinates":[-3.31659788236054,54.76280627083715],"type":"Point"}
}