{
  "type": "Feature",
  "properties": {
    "iso:country":"GB",
    "wof:name":"TF7 4HZ",
    "wof:placetype":"postalcode"
},
  "geometry": {"coordinates":[-2.43761245136646,52.62776423710104],"type":"Point"}
}