{
  "type": "Feature",
  "properties": {
    "iso:country":"GB",
    "wof:name":"S13 8LX",
    "wof:placetype":"postalcode"
},
  "geometry": {"coordinates":[-1.41107587953383,53.35971240678657],"type":"Point"}
}