{
  "type": "Feature",
  "properties": {
    "iso:country":"GB",
    "wof:name":"B68 9RB",
    "wof:placetype":"postalcode"
},
  "geometry": {"coordinates":[-2.00060422667505,52.48774754574806],"type":"Point"}
}