{
  "type": "Feature",
  "properties": {
    "iso:country": "GB",
    "wof:name": "B68 9RB",
    "wof:placetype": "postalcode"
  },
  "geometry": {"coordinates":[-2.000604,52.487748],"type":"Point"}
}
