{
  "type": "Feature",
  "properties": {
    "date:inception_lower": "1980-01-01",
    "date:inception_upper": "1980-01-01",
    "iso:country": "GB",
    "wof:name": "W3 6JD",
    "wof:placetype": "postalcode"
  },
  "geometry": {"coordinates":[-0.267249,51.515749],"type":"Point"}
}
