{
  "type": "Feature",
  "properties": {
    "date:inception_lower": "1980-01-01",
    "date:inception_upper": "1980-01-01",
    "iso:country": "GB",
    "wof:name": "CA15 8PW",
    "wof:placetype": "postalcode"
  },
  "geometry": {"coordinates":[-3.51778,54.691017],"type":"Point"}
}
