{
  "type": "Feature",
  "properties": {
    "iso:country":"GB",
    "wof:name":"CA15 8PW",
    "wof:placetype":"postalcode"
},
  "geometry": {"coordinates":[-3.51777985966953,54.69101678204232],"type":"Point"}
}