{
  "type": "Feature",
  "properties": {
    "date:inception_lower": "2000-06-01",
    "date:inception_upper": "2000-06-01",
    "iso:country": "GB",
    "wof:name": "PE28 5XQ",
    "wof:placetype": "postalcode"
  },
  "geometry": {"coordinates":[-0.256951,52.445257],"type":"Point"}
}
