{
  "type": "Feature",
  "properties": {
    "iso:country":"GB",
    "wof:name":"CA8 2BQ",
    "wof:placetype":"postalcode"
},
  "geometry": {"coordinates":[-2.73225248976352,55.01287803250033],"type":"Point"}
}