{
  "type": "Feature",
  "properties": {
    "iso:country": "GB",
    "wof:name": "CA8 2BQ",
    "wof:placetype": "postalcode"
  },
  "geometry": {"coordinates":[-2.732252,55.012878],"type":"Point"}
}
