{
  "type": "Feature",
  "properties": {
    "iso:country":"GB",
    "wof:name":"BA22 7QZ",
    "wof:placetype":"postalcode"
},
  "geometry": {"coordinates":[-2.60185064353451,51.02450931445767],"type":"Point"}
}