{
  "type": "Feature",
  "properties": {
    "iso:country":"GB",
    "wof:name":"EX1 3GE",
    "wof:placetype":"postalcode"
},
  "geometry": {"coordinates":[-3.47968787634831,50.72998994507899],"type":"Point"}
}