{
  "type": "Feature",
  "properties": {
    "iso:country": "GB",
    "wof:name": "EX1 3GE",
    "wof:placetype": "postalcode"
  },
  "geometry": {"coordinates":[-3.479688,50.72999],"type":"Point"}
}
