{
  "type": "Feature",
  "properties": {
    "iso:country":"GB",
    "wof:name":"LE14 2AP",
    "wof:placetype":"postalcode"
},
  "geometry": {"coordinates":[-0.74577725142948,52.76009856130764],"type":"Point"}
}