{
  "type": "Feature",
  "properties": {
    "date:inception_lower":"1995-12-01",
    "date:inception_upper":"1995-12-31",
    "iso:country":"GB",
    "wof:name":"TA6 4UX",
    "wof:placetype":"postalcode"
},
  "geometry": {"coordinates":[-2.973615,51.131606],"type":"Point"}
}