{
  "type": "Feature",
  "properties": {
    "iso:country": "GB",
    "wof:name": "TA6 4UX",
    "wof:placetype": "postalcode"
  },
  "geometry": {"coordinates":[-2.973615,51.131606],"type":"Point"}
}
