{
  "type": "Feature",
  "properties": {
    "iso:country":"GB",
    "wof:name":"TA6 4UX",
    "wof:placetype":"postalcode"
},
  "geometry": {"coordinates":[-2.97359418773577,51.13166470189149],"type":"Point"}
}