{
  "type": "Feature",
  "properties": {
    "iso:country":"GB",
    "wof:name":"OX28 1JW",
    "wof:placetype":"postalcode"
},
  "geometry": {"coordinates":[-1.48779092589442,51.79820562280434],"type":"Point"}
}