{
  "type": "Feature",
  "properties": {
    "iso:country":"GB",
    "wof:name":"KT13 0NX",
    "wof:placetype":"postalcode"
},
  "geometry": {"coordinates":[-0.4452979470053,51.3422984483045],"type":"Point"}
}