{
  "type": "Feature",
  "properties": {
    "date:inception_lower": "2023-04-01",
    "date:inception_upper": "2023-04-01",
    "iso:country": "GB",
    "wof:name": "PL7 5FR",
    "wof:placetype": "postalcode"
  },
  "geometry": {"coordinates":[-4.00704,50.37813],"type":"Point"}
}
