{
  "type": "Feature",
  "properties": {
    "iso:country":"GB",
    "wof:name":"E11 3PE",
    "wof:placetype":"postalcode"
},
  "geometry": {"coordinates":[0.0092431572317,51.56070597343732],"type":"Point"}
}