{
  "type": "Feature",
  "properties": {
    "iso:country":"GB",
    "wof:name":"L33 0XE",
    "wof:placetype":"postalcode"
},
  "geometry": {"coordinates":[-2.87470929198455,53.47970165031538],"type":"Point"}
}