{
  "type": "Feature",
  "properties": {
    "iso:country":"GB",
    "wof:name":"PA16 8EA",
    "wof:placetype":"postalcode"
},
  "geometry": {"coordinates":[-4.77350230372799,55.95492846590701],"type":"Point"}
}