{
  "type": "Feature",
  "properties": {
    "iso:country":"GB",
    "wof:name":"YO16 7BZ",
    "wof:placetype":"postalcode"
},
  "geometry": {"coordinates":[-0.19653196868509,54.09510831282055],"type":"Point"}
}