{
  "type": "Feature",
  "properties": {
    "iso:country": "GB",
    "wof:name": "TS7 0DD",
    "wof:placetype": "postalcode"
  },
  "geometry": {"coordinates":[-1.176852,54.526181],"type":"Point"}
}
