{
  "type": "Feature",
  "properties": {
    "iso:country":"GB",
    "wof:name":"TS7 0DD",
    "wof:placetype":"postalcode"
},
  "geometry": {"coordinates":[-1.17647902381658,54.52636329334612],"type":"Point"}
}