{
  "type": "Feature",
  "properties": {
    "iso:country":"GB",
    "wof:name":"N21 3JQ",
    "wof:placetype":"postalcode"
},
  "geometry": {"coordinates":[-0.09469176936358,51.63140285830878],"type":"Point"}
}