{
  "type": "Feature",
  "properties": {
    "date:inception_lower": "1996-12-01",
    "date:inception_upper": "1996-12-01",
    "iso:country": "GB",
    "wof:name": "N21 3JQ",
    "wof:placetype": "postalcode"
  },
  "geometry": {"coordinates":[-0.094692,51.631403],"type":"Point"}
}
