{
  "type": "Feature",
  "properties": {
    "iso:country": "GB",
    "wof:name": "LN2 2DX",
    "wof:placetype": "postalcode"
  },
  "geometry": {"coordinates":[-0.531342,53.248733],"type":"Point"}
}
