{
  "type": "Feature",
  "properties": {
    "iso:country":"GB",
    "wof:name":"SP3 6LR",
    "wof:placetype":"postalcode"
},
  "geometry": {"coordinates":[-2.07266114669059,51.06654744945121],"type":"Point"}
}