{
  "type": "Feature",
  "properties": {
    "iso:country": "GB",
    "wof:name": "SP3 6LR",
    "wof:placetype": "postalcode"
  },
  "geometry": {"coordinates":[-2.072655,51.066541],"type":"Point"}
}
