{
  "type": "Feature",
  "properties": {
    "iso:country": "GB",
    "wof:name": "NR33 0LZ",
    "wof:placetype": "postalcode"
  },
  "geometry": {"coordinates":[1.734826,52.464302],"type":"Point"}
}
