{
  "type": "Feature",
  "properties": {
    "iso:country":"GB",
    "wof:name":"NR33 0LZ",
    "wof:placetype":"postalcode"
},
  "geometry": {"coordinates":[1.73482556576946,52.46430243365896],"type":"Point"}
}