{
  "type": "Feature",
  "properties": {
    "iso:country": "GB",
    "wof:name": "TN11 0RF",
    "wof:placetype": "postalcode"
  },
  "geometry": {"coordinates":[0.342981,51.223058],"type":"Point"}
}
