{
  "type": "Feature",
  "properties": {
    "iso:country":"GB",
    "wof:name":"NP4 8BZ",
    "wof:placetype":"postalcode"
},
  "geometry": {"coordinates":[-3.03583593271102,51.70732267700579],"type":"Point"}
}