{
  "type": "Feature",
  "properties": {
    "date:inception_lower": "1980-01-01",
    "date:inception_upper": "1980-01-01",
    "iso:country": "GB",
    "wof:name": "NP4 8BZ",
    "wof:placetype": "postalcode"
  },
  "geometry": {"coordinates":[-3.035836,51.707323],"type":"Point"}
}
