{
  "type": "Feature",
  "properties": {
    "date:inception_lower": "1980-01-01",
    "date:inception_upper": "1980-01-01",
    "iso:country": "GB",
    "wof:name": "SK17 9TW",
    "wof:placetype": "postalcode"
  },
  "geometry": {"coordinates":[-1.793469,53.237301],"type":"Point"}
}
