{
  "type": "Feature",
  "properties": {
    "iso:country":"GB",
    "wof:name":"SK17 9TW",
    "wof:placetype":"postalcode"
},
  "geometry": {"coordinates":[-1.79346889738263,53.23730086318841],"type":"Point"}
}