{
  "type": "Feature",
  "properties": {
    "iso:country": "GB",
    "wof:name": "BA5 3HU",
    "wof:placetype": "postalcode"
  },
  "geometry": {"coordinates":[-2.626532,51.213485],"type":"Point"}
}
