{
  "type": "Feature",
  "properties": {
    "iso:country":"GB",
    "wof:name":"BA5 3HU",
    "wof:placetype":"postalcode"
},
  "geometry": {"coordinates":[-2.62653165787812,51.21348479552566],"type":"Point"}
}