{
  "type": "Feature",
  "properties": {
    "date:inception_lower":"1980-01-01",
    "date:inception_upper":"1980-01-31",
    "iso:country":"GB",
    "wof:name":"WV13 2EX",
    "wof:placetype":"postalcode"
},
  "geometry": {"coordinates":[-2.053014,52.58301],"type":"Point"}
}