{
  "type": "Feature",
  "properties": {
    "iso:country":"GB",
    "wof:name":"M23 0DH",
    "wof:placetype":"postalcode"
},
  "geometry": {"coordinates":[-2.2720422395915,53.40893342422252],"type":"Point"}
}