{
  "type": "Feature",
  "properties": {
    "date:inception_lower": "1994-05-01",
    "date:inception_upper": "1994-05-01",
    "iso:country": "GB",
    "wof:name": "M23 0DH",
    "wof:placetype": "postalcode"
  },
  "geometry": {"coordinates":[-2.27248,53.409137],"type":"Point"}
}
