{
  "type": "Feature",
  "properties": {
    "iso:country":"GB",
    "wof:name":"BA12 9HZ",
    "wof:placetype":"postalcode"
},
  "geometry": {"coordinates":[-2.17893937397691,51.20331862310746],"type":"Point"}
}