{
  "type": "Feature",
  "properties": {
    "date:inception_lower":"2013-07-01",
    "date:inception_upper":"2013-07-31",
    "iso:country":"GB",
    "wof:name":"BA12 9HZ",
    "wof:placetype":"postalcode"
},
  "geometry": {"coordinates":[-2.178939,51.203319],"type":"Point"}
}