{
  "type": "Feature",
  "properties": {
    "iso:country":"GB",
    "wof:name":"LU2 7JS",
    "wof:placetype":"postalcode"
},
  "geometry": {"coordinates":[-0.41490256910745,51.89207077024174],"type":"Point"}
}