{
  "type": "Feature",
  "properties": {
    "iso:country": "GB",
    "wof:name": "LU2 7JS",
    "wof:placetype": "postalcode"
  },
  "geometry": {"coordinates":[-0.414903,51.892071],"type":"Point"}
}
