{
  "type": "Feature",
  "properties": {
    "iso:country":"GB",
    "wof:name":"HP21 9FF",
    "wof:placetype":"postalcode"
},
  "geometry": {"coordinates":[-0.81291121805986,51.79654934625403],"type":"Point"}
}