{
  "type": "Feature",
  "properties": {
    "date:inception_lower": "1980-01-01",
    "date:inception_upper": "1980-01-01",
    "iso:country": "GB",
    "wof:name": "NG8 2DG",
    "wof:placetype": "postalcode"
  },
  "geometry": {"coordinates":[-1.227598,52.95599],"type":"Point"}
}
