{
  "type": "Feature",
  "properties": {
    "iso:country":"GB",
    "wof:name":"M28 7UJ",
    "wof:placetype":"postalcode"
},
  "geometry": {"coordinates":[-2.41323768894397,53.51300172660992],"type":"Point"}
}