{
  "type": "Feature",
  "properties": {
    "iso:country":"GB",
    "wof:name":"CF3 4BU",
    "wof:placetype":"postalcode"
},
  "geometry": {"coordinates":[-3.13237048402911,51.51305631444443],"type":"Point"}
}