{
  "type": "Feature",
  "properties": {
    "date:inception_lower": "1999-06-01",
    "date:inception_upper": "1999-06-01",
    "iso:country": "GB",
    "wof:name": "CF3 4BU",
    "wof:placetype": "postalcode"
  },
  "geometry": {"coordinates":[-3.13237,51.513056],"type":"Point"}
}
