{
  "type": "Feature",
  "properties": {
    "iso:country":"GB",
    "wof:name":"NR13 6JA",
    "wof:placetype":"postalcode"
},
  "geometry": {"coordinates":[1.48753562040748,52.67223248973809],"type":"Point"}
}