{
  "type": "Feature",
  "properties": {
    "iso:country": "GB",
    "wof:name": "NR13 6JA",
    "wof:placetype": "postalcode"
  },
  "geometry": {"coordinates":[1.487536,52.672232],"type":"Point"}
}
