{
  "type": "Feature",
  "properties": {
    "iso:country":"GB",
    "wof:name":"WA15 8UD",
    "wof:placetype":"postalcode"
},
  "geometry": {"coordinates":[-2.29745312686936,53.37493181154883],"type":"Point"}
}