{
  "type": "Feature",
  "properties": {
    "date:inception_lower": "1980-01-01",
    "date:inception_upper": "1980-01-01",
    "iso:country": "GB",
    "wof:name": "PA34 4HL",
    "wof:placetype": "postalcode"
  },
  "geometry": {"coordinates":[-5.470109,56.411477],"type":"Point"}
}
