{
  "type": "Feature",
  "properties": {
    "date:inception_lower": "2002-06-01",
    "date:inception_upper": "2002-06-01",
    "iso:country": "GB",
    "wof:name": "CW9 8UU",
    "wof:placetype": "postalcode"
  },
  "geometry": {"coordinates":[-2.519509,53.246629],"type":"Point"}
}
