{
  "type": "Feature",
  "properties": {
    "iso:country": "GB",
    "wof:name": "PA38 4DN",
    "wof:placetype": "postalcode"
  },
  "geometry": {"coordinates":[-5.413993,56.552951],"type":"Point"}
}
