{
  "type": "Feature",
  "properties": {
    "date:inception_lower":"1983-03-01",
    "date:inception_upper":"1983-03-31",
    "iso:country":"GB",
    "wof:name":"WS1 1JZ",
    "wof:placetype":"postalcode"
},
  "geometry": {"coordinates":[-1.977709,52.584384],"type":"Point"}
}