{
  "type": "Feature",
  "properties": {
    "iso:country": "GB",
    "wof:name": "WS1 1JZ",
    "wof:placetype": "postalcode"
  },
  "geometry": {"coordinates":[-1.977709,52.584384],"type":"Point"}
}
