{
  "type": "Feature",
  "properties": {
    "iso:country":"GB",
    "wof:name":"WS1 1JZ",
    "wof:placetype":"postalcode"
},
  "geometry": {"coordinates":[-1.97774438814572,52.58433269323113],"type":"Point"}
}