{
  "type": "Feature",
  "properties": {
    "iso:country": "GB",
    "wof:name": "KY12 9HX",
    "wof:placetype": "postalcode"
  },
  "geometry": {"coordinates":[-3.493257,56.084275],"type":"Point"}
}
