{
  "type": "Feature",
  "properties": {
    "date:inception_lower": "2005-01-01",
    "date:inception_upper": "2005-01-01",
    "iso:country": "GB",
    "wof:name": "CH64 3TR",
    "wof:placetype": "postalcode"
  },
  "geometry": {"coordinates":[-3.06431,53.297439],"type":"Point"}
}
