{
  "type": "Feature",
  "properties": {
    "iso:country": "GB",
    "wof:name": "TN25 4FN",
    "wof:placetype": "postalcode"
  },
  "geometry": {"coordinates":[0.860355,51.222939],"type":"Point"}
}
