{
  "type": "Feature",
  "properties": {
    "date:inception_lower": "2018-07-01",
    "date:inception_upper": "2018-07-01",
    "iso:country": "GB",
    "wof:name": "TN25 4FN",
    "wof:placetype": "postalcode"
  },
  "geometry": {"coordinates":[0.860617,51.223238],"type":"Point"}
}
