{
  "type": "Feature",
  "properties": {
    "iso:country":"GB",
    "wof:name":"CT6 6TT",
    "wof:placetype":"postalcode"
},
  "geometry": {"coordinates":[1.19659471492263,51.36831078371951],"type":"Point"}
}