{
  "type": "Feature",
  "properties": {
    "date:inception_lower": "1983-03-01",
    "date:inception_upper": "1983-03-01",
    "iso:country": "GB",
    "wof:name": "CT6 6TT",
    "wof:placetype": "postalcode"
  },
  "geometry": {"coordinates":[1.196595,51.368311],"type":"Point"}
}
