{
  "type": "Feature",
  "properties": {
    "iso:country": "GB",
    "wof:name": "TS23 3UA",
    "wof:placetype": "postalcode"
  },
  "geometry": {"coordinates":[-1.291446,54.616764],"type":"Point"}
}
