{
  "type": "Feature",
  "properties": {
    "date:inception_lower":"1994-12-01",
    "date:inception_upper":"1994-12-31",
    "iso:country":"GB",
    "wof:name":"MK18 2LJ",
    "wof:placetype":"postalcode"
},
  "geometry": {"coordinates":[-1.001657,51.933028],"type":"Point"}
}