{
  "type": "Feature",
  "properties": {
    "iso:country":"GB",
    "wof:name":"MK18 2LJ",
    "wof:placetype":"postalcode"
},
  "geometry": {"coordinates":[-1.0016572422112,51.93302752080323],"type":"Point"}
}