{
  "type": "Feature",
  "properties": {
    "iso:country": "GB",
    "wof:name": "MK18 2LJ",
    "wof:placetype": "postalcode"
  },
  "geometry": {"coordinates":[-1.001657,51.933028],"type":"Point"}
}
