{
  "type": "Feature",
  "properties": {
    "iso:country":"GB",
    "wof:name":"EH48 1DZ",
    "wof:placetype":"postalcode"
},
  "geometry": {"coordinates":[-3.63469380125452,55.89765461768077],"type":"Point"}
}