{
  "type": "Feature",
  "properties": {
    "iso:country": "GB",
    "wof:name": "EH27 8DL",
    "wof:placetype": "postalcode"
  },
  "geometry": {"coordinates":[-3.41939,55.887089],"type":"Point"}
}
