{
  "type": "Feature",
  "properties": {
    "date:inception_lower":"1992-10-01",
    "date:inception_upper":"1992-10-31",
    "iso:country":"GB",
    "wof:name":"EH27 8DL",
    "wof:placetype":"postalcode"
},
  "geometry": {"coordinates":[-3.41939,55.887089],"type":"Point"}
}