{
  "type": "Feature",
  "properties": {
    "iso:country":"GB",
    "wof:name":"IG1 4AZ",
    "wof:placetype":"postalcode"
},
  "geometry": {"coordinates":[0.08850648470317,51.56603931786882],"type":"Point"}
}