{
  "type": "Feature",
  "properties": {
    "date:inception_lower": "2002-05-01",
    "date:inception_upper": "2002-05-01",
    "iso:country": "GB",
    "wof:name": "IG1 4AZ",
    "wof:placetype": "postalcode"
  },
  "geometry": {"coordinates":[0.088487,51.565987],"type":"Point"}
}
