{
  "type": "Feature",
  "properties": {
    "iso:country": "GB",
    "wof:name": "IG1 4AZ",
    "wof:placetype": "postalcode"
  },
  "geometry": {"coordinates":[0.088507,51.566039],"type":"Point"}
}
