{
  "type": "Feature",
  "properties": {
    "date:inception_lower":"1999-12-01",
    "date:inception_upper":"1999-12-31",
    "iso:country":"GB",
    "wof:name":"FK13 6RZ",
    "wof:placetype":"postalcode"
},
  "geometry": {"coordinates":[-3.733867,56.15847],"type":"Point"}
}