{
  "type": "Feature",
  "properties": {
    "iso:country": "GB",
    "wof:name": "SR4 6DJ",
    "wof:placetype": "postalcode"
  },
  "geometry": {"coordinates":[-1.401455,54.913709],"type":"Point"}
}
