{
  "type": "Feature",
  "properties": {
    "iso:country":"GB",
    "wof:name":"MK4 4EZ",
    "wof:placetype":"postalcode"
},
  "geometry": {"coordinates":[-0.80251469247609,52.00536607916175],"type":"Point"}
}