{
  "type": "Feature",
  "properties": {
    "iso:country": "GB",
    "wof:name": "MK4 4EZ",
    "wof:placetype": "postalcode"
  },
  "geometry": {"coordinates":[-0.802515,52.005366],"type":"Point"}
}
