{
  "type": "Feature",
  "properties": {
    "iso:country":"GB",
    "wof:name":"L25 2RU",
    "wof:placetype":"postalcode"
},
  "geometry": {"coordinates":[-2.86908517563076,53.39249738604389],"type":"Point"}
}