{
  "type": "Feature",
  "properties": {
    "iso:country": "GB",
    "wof:name": "HD9 1JB",
    "wof:placetype": "postalcode"
  },
  "geometry": {"coordinates":[-1.755921,53.566392],"type":"Point"}
}
