{
  "type": "Feature",
  "properties": {
    "date:inception_lower":"2001-06-01",
    "date:inception_upper":"2001-06-30",
    "iso:country":"GB",
    "wof:name":"HD9 1JB",
    "wof:placetype":"postalcode"
},
  "geometry": {"coordinates":[-1.755921,53.566392],"type":"Point"}
}