{
  "type": "Feature",
  "properties": {
    "iso:country":"GB",
    "wof:name":"E13 0PX",
    "wof:placetype":"postalcode"
},
  "geometry": {"coordinates":[0.02452540785957,51.53674761460683],"type":"Point"}
}