{
  "type": "Feature",
  "properties": {
    "iso:country":"GB",
    "wof:name":"IG1 2UW",
    "wof:placetype":"postalcode"
},
  "geometry": {"coordinates":[0.08994105233212,51.5516973530184],"type":"Point"}
}