{
  "type": "Feature",
  "properties": {
    "date:inception_lower": "1980-01-01",
    "date:inception_upper": "1980-01-01",
    "iso:country": "GB",
    "wof:name": "YO21 2JN",
    "wof:placetype": "postalcode"
  },
  "geometry": {"coordinates":[-0.910523,54.463838],"type":"Point"}
}
