{
  "type": "Feature",
  "properties": {
    "iso:country": "GB",
    "wof:name": "YO21 2JN",
    "wof:placetype": "postalcode"
  },
  "geometry": {"coordinates":[-0.910523,54.463838],"type":"Point"}
}
