{
  "type": "Feature",
  "properties": {
    "iso:country":"GB",
    "wof:name":"BH25 5LP",
    "wof:placetype":"postalcode"
},
  "geometry": {"coordinates":[-1.66312062682361,50.75689966383992],"type":"Point"}
}