{
  "type": "Feature",
  "properties": {
    "iso:country":"GB",
    "wof:name":"L30 9ST",
    "wof:placetype":"postalcode"
},
  "geometry": {"coordinates":[-2.98038302680922,53.47178904548584],"type":"Point"}
}