{
  "type": "Feature",
  "properties": {
    "iso:country": "GB",
    "wof:name": "WV10 8JS",
    "wof:placetype": "postalcode"
  },
  "geometry": {"coordinates":[-2.111249,52.619349],"type":"Point"}
}
