{
  "type": "Feature",
  "properties": {
    "iso:country": "GB",
    "wof:name": "IP1 4JX",
    "wof:placetype": "postalcode"
  },
  "geometry": {"coordinates":[1.147006,52.073591],"type":"Point"}
}
