{
  "type": "Feature",
  "properties": {
    "iso:country":"GB",
    "wof:name":"IP1 4JX",
    "wof:placetype":"postalcode"
},
  "geometry": {"coordinates":[1.14700591225698,52.07359105776392],"type":"Point"}
}