{
  "type": "Feature",
  "properties": {
    "iso:country": "GB",
    "wof:name": "SA2 0YQ",
    "wof:placetype": "postalcode"
  },
  "geometry": {"coordinates":[-3.978103,51.625568],"type":"Point"}
}
