{
  "type": "Feature",
  "properties": {
    "iso:country":"GB",
    "wof:name":"CM7 9AN",
    "wof:placetype":"postalcode"
},
  "geometry": {"coordinates":[0.55330574918711,51.88212726510626],"type":"Point"}
}