{
  "type": "Feature",
  "properties": {
    "iso:country":"GB",
    "wof:name":"CR0 5QB",
    "wof:placetype":"postalcode"
},
  "geometry": {"coordinates":[-0.07622980165589,51.37161138122543],"type":"Point"}
}