{
  "type": "Feature",
  "properties": {
    "iso:country":"GB",
    "wof:name":"RM13 9GJ",
    "wof:placetype":"postalcode"
},
  "geometry": {"coordinates":[0.22298066989167,51.51203890343408],"type":"Point"}
}