{
  "type": "Feature",
  "properties": {
    "iso:country":"GB",
    "wof:name":"CO1 2TL",
    "wof:placetype":"postalcode"
},
  "geometry": {"coordinates":[0.92770137419011,51.88786391996452],"type":"Point"}
}