{
  "type": "Feature",
  "properties": {
    "date:inception_lower": "1980-01-01",
    "date:inception_upper": "1980-01-01",
    "iso:country": "GB",
    "wof:name": "HA8 5LG",
    "wof:placetype": "postalcode"
  },
  "geometry": {"coordinates":[-0.268692,51.599496],"type":"Point"}
}
