{
  "type": "Feature",
  "properties": {
    "iso:country": "GB",
    "wof:name": "EX17 1FE",
    "wof:placetype": "postalcode"
  },
  "geometry": {"coordinates":[-3.639635,50.794787],"type":"Point"}
}
