{
  "type": "Feature",
  "properties": {
    "iso:country":"GB",
    "wof:name":"PO21 2HX",
    "wof:placetype":"postalcode"
},
  "geometry": {"coordinates":[-0.68002138419854,50.7911423696882],"type":"Point"}
}