{
  "type": "Feature",
  "properties": {
    "date:inception_lower": "1996-06-01",
    "date:inception_upper": "1996-06-01",
    "iso:country": "GB",
    "wof:name": "PO21 2HX",
    "wof:placetype": "postalcode"
  },
  "geometry": {"coordinates":[-0.680021,50.791142],"type":"Point"}
}
