{
  "type": "Feature",
  "properties": {
    "date:inception_lower": "1995-12-01",
    "date:inception_upper": "1995-12-01",
    "iso:country": "GB",
    "wof:name": "M27 0AD",
    "wof:placetype": "postalcode"
  },
  "geometry": {"coordinates":[-2.363492,53.501029],"type":"Point"}
}
