{
  "type": "Feature",
  "properties": {
    "iso:country":"GB",
    "wof:name":"M27 0AD",
    "wof:placetype":"postalcode"
},
  "geometry": {"coordinates":[-2.36349235812689,53.50102902172219],"type":"Point"}
}