{
  "type": "Feature",
  "properties": {
    "date:inception_lower": "2015-07-01",
    "date:inception_upper": "2015-07-01",
    "iso:country": "GB",
    "wof:name": "WF8 4FR",
    "wof:placetype": "postalcode"
  },
  "geometry": {"coordinates":[-1.325852,53.689546],"type":"Point"}
}
