{
  "type": "Feature",
  "properties": {
    "iso:country":"GB",
    "wof:name":"WF8 4FR",
    "wof:placetype":"postalcode"
},
  "geometry": {"coordinates":[-1.32584877950761,53.68952795123053],"type":"Point"}
}