{
  "type": "Feature",
  "properties": {
    "iso:country":"GB",
    "wof:name":"NE46 2HA",
    "wof:placetype":"postalcode"
},
  "geometry": {"coordinates":[-2.10399785345987,54.96818407485805],"type":"Point"}
}