{
  "type": "Feature",
  "properties": {
    "iso:country":"GB",
    "wof:name":"SM4 6LL",
    "wof:placetype":"postalcode"
},
  "geometry": {"coordinates":[-0.19657008683834,51.38701459809655],"type":"Point"}
}