{
  "type": "Feature",
  "properties": {
    "iso:country":"GB",
    "wof:name":"LL41 3UE",
    "wof:placetype":"postalcode"
},
  "geometry": {"coordinates":[-3.9383727185663,52.99357938202257],"type":"Point"}
}