{
  "type": "Feature",
  "properties": {
    "iso:country":"GB",
    "wof:name":"BA8 0TS",
    "wof:placetype":"postalcode"
},
  "geometry": {"coordinates":[-2.3932041991795,50.97356658490826],"type":"Point"}
}