{
  "type": "Feature",
  "properties": {
    "date:inception_lower": "1991-09-01",
    "date:inception_upper": "1991-09-01",
    "iso:country": "GB",
    "wof:name": "BA8 0TS",
    "wof:placetype": "postalcode"
  },
  "geometry": {"coordinates":[-2.393204,50.973567],"type":"Point"}
}
