{
  "type": "Feature",
  "properties": {
    "iso:country": "GB",
    "wof:name": "CF3 5AB",
    "wof:placetype": "postalcode"
  },
  "geometry": {"coordinates":[-3.118873,51.520551],"type":"Point"}
}
