{
  "type": "Feature",
  "properties": {
    "iso:country":"GB",
    "wof:name":"EX6 7TE",
    "wof:placetype":"postalcode"
},
  "geometry": {"coordinates":[-3.53472806646782,50.66856420899493],"type":"Point"}
}