{
  "type": "Feature",
  "properties": {
    "iso:country":"GB",
    "wof:name":"SK17 6QQ",
    "wof:placetype":"postalcode"
},
  "geometry": {"coordinates":[-1.90960274580432,53.25721159248815],"type":"Point"}
}