{
  "type": "Feature",
  "properties": {
    "iso:country":"GB",
    "wof:name":"AB51 4SJ",
    "wof:placetype":"postalcode"
},
  "geometry": {"coordinates":[-2.37807216811809,57.28954906663746],"type":"Point"}
}