{
  "type": "Feature",
  "properties": {
    "iso:country":"GB",
    "wof:name":"SR7 0AF",
    "wof:placetype":"postalcode"
},
  "geometry": {"coordinates":[-1.34802515458325,54.83962031414935],"type":"Point"}
}