{
  "type": "Feature",
  "properties": {
    "iso:country":"GB",
    "wof:name":"E14 9XL",
    "wof:placetype":"postalcode"
},
  "geometry": {"coordinates":[-0.02034991093656,51.50115628181299],"type":"Point"}
}