{
  "type": "Feature",
  "properties": {
    "iso:country":"GB",
    "wof:name":"WD6 1UU",
    "wof:placetype":"postalcode"
},
  "geometry": {"coordinates":[-0.28042408524523,51.65929525443125],"type":"Point"}
}