{
  "type": "Feature",
  "properties": {
    "iso:country": "GB",
    "wof:name": "PA2 8JA",
    "wof:placetype": "postalcode"
  },
  "geometry": {"coordinates":[-4.42697,55.821001],"type":"Point"}
}
