{
  "type": "Feature",
  "properties": {
    "date:inception_lower": "1980-01-01",
    "date:inception_upper": "1980-01-01",
    "iso:country": "GB",
    "wof:name": "PA2 8JA",
    "wof:placetype": "postalcode"
  },
  "geometry": {"coordinates":[-4.42697,55.821001],"type":"Point"}
}
