{
  "type": "Feature",
  "properties": {
    "iso:country": "GB",
    "wof:name": "RM17 6JF",
    "wof:placetype": "postalcode"
  },
  "geometry": {"coordinates":[0.324754,51.471692],"type":"Point"}
}
