{
  "type": "Feature",
  "properties": {
    "iso:country":"GB",
    "wof:name":"RM17 6JF",
    "wof:placetype":"postalcode"
},
  "geometry": {"coordinates":[0.32475443424239,51.47169167800953],"type":"Point"}
}