{
  "type": "Feature",
  "properties": {
    "iso:country":"GB",
    "wof:name":"PO30 1AL",
    "wof:placetype":"postalcode"
},
  "geometry": {"coordinates":[-1.29012383908653,50.69040652303281],"type":"Point"}
}