{
  "type": "Feature",
  "properties": {
    "iso:country": "GB",
    "wof:name": "TW8 0QD",
    "wof:placetype": "postalcode"
  },
  "geometry": {"coordinates":[-0.307692,51.487931],"type":"Point"}
}
