{
  "type": "Feature",
  "properties": {
    "iso:country":"GB",
    "wof:name":"TW8 0QD",
    "wof:placetype":"postalcode"
},
  "geometry": {"coordinates":[-0.30769280910359,51.48752596435435],"type":"Point"}
}