{
  "type": "Feature",
  "properties": {
    "iso:country":"GB",
    "wof:name":"ML1 1XF",
    "wof:placetype":"postalcode"
},
  "geometry": {"coordinates":[-3.98933432620548,55.78513913666441],"type":"Point"}
}