{
  "type": "Feature",
  "properties": {
    "iso:country": "GB",
    "wof:name": "HA4 0ED",
    "wof:placetype": "postalcode"
  },
  "geometry": {"coordinates":[-0.404184,51.561707],"type":"Point"}
}
