{
  "type": "Feature",
  "properties": {
    "iso:country":"GB",
    "wof:name":"HA4 0ED",
    "wof:placetype":"postalcode"
},
  "geometry": {"coordinates":[-0.40417056595913,51.56167040197876],"type":"Point"}
}