{
  "type": "Feature",
  "properties": {
    "iso:country": "GB",
    "wof:name": "BD2 1PA",
    "wof:placetype": "postalcode"
  },
  "geometry": {"coordinates":[-1.74486,53.826135],"type":"Point"}
}
