{
  "type": "Feature",
  "properties": {
    "iso:country":"GB",
    "wof:name":"BD2 1PA",
    "wof:placetype":"postalcode"
},
  "geometry": {"coordinates":[-1.74485970000851,53.82613473178358],"type":"Point"}
}