{
  "type": "Feature",
  "properties": {
    "date:inception_lower": "1980-01-01",
    "date:inception_upper": "1980-01-01",
    "iso:country": "GB",
    "wof:name": "BD2 1PA",
    "wof:placetype": "postalcode"
  },
  "geometry": {"coordinates":[-1.74486,53.826135],"type":"Point"}
}
