{
  "type": "Feature",
  "properties": {
    "iso:country": "GB",
    "wof:name": "CM4 0QS",
    "wof:placetype": "postalcode"
  },
  "geometry": {"coordinates":[0.315976,51.695458],"type":"Point"}
}
