{
  "type": "Feature",
  "properties": {
    "date:inception_lower": "1980-01-01",
    "date:inception_upper": "1980-01-01",
    "iso:country": "GB",
    "wof:name": "CM4 0QS",
    "wof:placetype": "postalcode"
  },
  "geometry": {"coordinates":[0.315976,51.695458],"type":"Point"}
}
