{
  "type": "Feature",
  "properties": {
    "date:inception_lower":"2008-07-01",
    "date:inception_upper":"2008-07-31",
    "iso:country":"GB",
    "wof:name":"LE5 1LY",
    "wof:placetype":"postalcode"
},
  "geometry": {"coordinates":[-1.059266,52.662113],"type":"Point"}
}