{
  "type": "Feature",
  "properties": {
    "iso:country":"GB",
    "wof:name":"LE5 1LY",
    "wof:placetype":"postalcode"
},
  "geometry": {"coordinates":[-1.05926588510438,52.66211328768903],"type":"Point"}
}