{
  "type": "Feature",
  "properties": {
    "iso:country":"GB",
    "wof:name":"EH21 6TL",
    "wof:placetype":"postalcode"
},
  "geometry": {"coordinates":[-3.06960265163838,55.93778092256098],"type":"Point"}
}