{
  "type": "Feature",
  "properties": {
    "date:inception_lower": "1983-02-01",
    "date:inception_upper": "1983-02-01",
    "iso:country": "GB",
    "wof:name": "EH21 6TL",
    "wof:placetype": "postalcode"
  },
  "geometry": {"coordinates":[-3.069603,55.937781],"type":"Point"}
}
