{
  "type": "Feature",
  "properties": {
    "iso:country":"GB",
    "wof:name":"TN39 3HG",
    "wof:placetype":"postalcode"
},
  "geometry": {"coordinates":[0.46667136305383,50.83692474202697],"type":"Point"}
}