{
  "type": "Feature",
  "properties": {
    "iso:country":"GB",
    "wof:name":"AB42 3LE",
    "wof:placetype":"postalcode"
},
  "geometry": {"coordinates":[-1.88851224806916,57.49926611937185],"type":"Point"}
}