{
  "type": "Feature",
  "properties": {
    "iso:country":"GB",
    "wof:name":"IP6 8DY",
    "wof:placetype":"postalcode"
},
  "geometry": {"coordinates":[1.04547849263438,52.16029671256099],"type":"Point"}
}