{
  "type": "Feature",
  "properties": {
    "iso:country": "GB",
    "wof:name": "EX6 7DR",
    "wof:placetype": "postalcode"
  },
  "geometry": {"coordinates":[-3.687237,50.697708],"type":"Point"}
}
