{
  "type": "Feature",
  "properties": {
    "iso:country":"GB",
    "wof:name":"EX6 7DR",
    "wof:placetype":"postalcode"
},
  "geometry": {"coordinates":[-3.6872207317404,50.69771703224118],"type":"Point"}
}