{
  "type": "Feature",
  "properties": {
    "iso:country": "GB",
    "wof:name": "RG9 5SU",
    "wof:placetype": "postalcode"
  },
  "geometry": {"coordinates":[-1.032555,51.579529],"type":"Point"}
}
