{
  "type": "Feature",
  "properties": {
    "date:inception_lower": "1980-01-01",
    "date:inception_upper": "1980-01-01",
    "iso:country": "GB",
    "wof:name": "RG9 5SU",
    "wof:placetype": "postalcode"
  },
  "geometry": {"coordinates":[-1.031829,51.5794],"type":"Point"}
}
