{
  "type": "Feature",
  "properties": {
    "date:inception_lower": "2018-07-01",
    "date:inception_upper": "2018-07-01",
    "iso:country": "GB",
    "wof:name": "TN12 9GB",
    "wof:placetype": "postalcode"
  },
  "geometry": {"coordinates":[0.49677,51.171094],"type":"Point"}
}
