{
  "type": "Feature",
  "properties": {
    "iso:country": "GB",
    "wof:name": "TN12 9GB",
    "wof:placetype": "postalcode"
  },
  "geometry": {"coordinates":[0.49677,51.171094],"type":"Point"}
}
