{
  "type": "Feature",
  "properties": {
    "iso:country":"GB",
    "wof:name":"HP1 3LL",
    "wof:placetype":"postalcode"
},
  "geometry": {"coordinates":[-0.48573911199237,51.7672817271136],"type":"Point"}
}