{
  "type": "Feature",
  "properties": {
    "iso:country": "GB",
    "wof:name": "DA3 7BY",
    "wof:placetype": "postalcode"
  },
  "geometry": {"coordinates":[0.310578,51.387445],"type":"Point"}
}
