{
  "type": "Feature",
  "properties": {
    "date:inception_lower": "1980-01-01",
    "date:inception_upper": "1980-01-01",
    "iso:country": "GB",
    "wof:name": "NR19 1NG",
    "wof:placetype": "postalcode"
  },
  "geometry": {"coordinates":[0.938567,52.661992],"type":"Point"}
}
