{
  "type": "Feature",
  "properties": {
    "date:inception_lower":"1980-01-01",
    "date:inception_upper":"1980-01-31",
    "iso:country":"GB",
    "wof:name":"LN6 0NN",
    "wof:placetype":"postalcode"
},
  "geometry": {"coordinates":[-0.601834,53.219196],"type":"Point"}
}