{
  "type": "Feature",
  "properties": {
    "iso:country":"GB",
    "wof:name":"NG15 7UR",
    "wof:placetype":"postalcode"
},
  "geometry": {"coordinates":[-1.1937994035827,53.03421462067829],"type":"Point"}
}