{
  "type": "Feature",
  "properties": {
    "iso:country": "GB",
    "wof:name": "CO10 7DQ",
    "wof:placetype": "postalcode"
  },
  "geometry": {"coordinates":[0.621013,52.055318],"type":"Point"}
}
