{
  "type": "Feature",
  "properties": {
    "iso:country":"GB",
    "wof:name":"CO10 7DQ",
    "wof:placetype":"postalcode"
},
  "geometry": {"coordinates":[0.62101284682201,52.05531795962406],"type":"Point"}
}