{
  "type": "Feature",
  "properties": {
    "date:inception_lower": "1980-01-01",
    "date:inception_upper": "1980-01-01",
    "iso:country": "GB",
    "wof:name": "CO10 7DQ",
    "wof:placetype": "postalcode"
  },
  "geometry": {"coordinates":[0.621013,52.055318],"type":"Point"}
}
