{
  "type": "Feature",
  "properties": {
    "date:inception_lower": "1985-04-01",
    "date:inception_upper": "1985-04-01",
    "iso:country": "GB",
    "wof:name": "B91 3UZ",
    "wof:placetype": "postalcode"
  },
  "geometry": {"coordinates":[-1.782752,52.40102],"type":"Point"}
}
