{
  "type": "Feature",
  "properties": {
    "iso:country":"GB",
    "wof:name":"RG9 2EG",
    "wof:placetype":"postalcode"
},
  "geometry": {"coordinates":[-0.90752993158268,51.53685437404697],"type":"Point"}
}