{
  "type": "Feature",
  "properties": {
    "iso:country":"GB",
    "wof:name":"NG5 1EP",
    "wof:placetype":"postalcode"
},
  "geometry": {"coordinates":[-1.16661454629022,52.97844576996843],"type":"Point"}
}