{
  "type": "Feature",
  "properties": {
    "iso:country":"GB",
    "wof:name":"WD5 0SA",
    "wof:placetype":"postalcode"
},
  "geometry": {"coordinates":[-0.39307689026706,51.72314218353488],"type":"Point"}
}