{
  "type": "Feature",
  "properties": {
    "iso:country":"GB",
    "wof:name":"WR11 7PQ",
    "wof:placetype":"postalcode"
},
  "geometry": {"coordinates":[-1.83365968404871,52.0925091528562],"type":"Point"}
}