{
  "type": "Feature",
  "properties": {
    "iso:country": "GB",
    "wof:name": "WR11 7PQ",
    "wof:placetype": "postalcode"
  },
  "geometry": {"coordinates":[-1.83366,52.092509],"type":"Point"}
}
