{
  "type": "Feature",
  "properties": {
    "iso:country":"GB",
    "wof:name":"RG12 0UF",
    "wof:placetype":"postalcode"
},
  "geometry": {"coordinates":[-0.738037085286,51.40076857471504],"type":"Point"}
}