{
  "type": "Feature",
  "properties": {
    "date:inception_lower": "1993-01-01",
    "date:inception_upper": "1993-01-01",
    "iso:country": "GB",
    "wof:name": "CF63 3QF",
    "wof:placetype": "postalcode"
  },
  "geometry": {"coordinates":[-3.254647,51.410706],"type":"Point"}
}
