{
  "type": "Feature",
  "properties": {
    "iso:country":"GB",
    "wof:name":"ME15 9DJ",
    "wof:placetype":"postalcode"
},
  "geometry": {"coordinates":[0.54186935272121,51.24556345719213],"type":"Point"}
}