{
  "type": "Feature",
  "properties": {
    "iso:country":"GB",
    "wof:name":"B77 1EP",
    "wof:placetype":"postalcode"
},
  "geometry": {"coordinates":[-1.68336539353702,52.61231099404446],"type":"Point"}
}