{
  "type": "Feature",
  "properties": {
    "iso:country":"GB",
    "wof:name":"B67 5EA",
    "wof:placetype":"postalcode"
},
  "geometry": {"coordinates":[-1.97684435902503,52.47040370287766],"type":"Point"}
}