{
  "type": "Feature",
  "properties": {
    "iso:country": "GB",
    "wof:name": "B67 5EA",
    "wof:placetype": "postalcode"
  },
  "geometry": {"coordinates":[-1.976844,52.470404],"type":"Point"}
}
