{
  "type": "Feature",
  "properties": {
    "date:inception_lower": "2020-04-01",
    "date:inception_upper": "2020-04-01",
    "iso:country": "GB",
    "wof:name": "OX2 9TF",
    "wof:placetype": "postalcode"
  },
  "geometry": {"coordinates":[-1.297518,51.751517],"type":"Point"}
}
