{
  "type": "Feature",
  "properties": {
    "iso:country": "GB",
    "wof:name": "NP23 5UE",
    "wof:placetype": "postalcode"
  },
  "geometry": {"coordinates":[-3.212819,51.791624],"type":"Point"}
}
