{
  "type": "Feature",
  "properties": {
    "iso:country":"GB",
    "wof:name":"NP23 5UE",
    "wof:placetype":"postalcode"
},
  "geometry": {"coordinates":[-3.21281950891889,51.79162374617815],"type":"Point"}
}