{
  "type": "Feature",
  "properties": {
    "date:inception_lower":"1999-06-01",
    "date:inception_upper":"1999-06-30",
    "iso:country":"GB",
    "wof:name":"NP23 5UE",
    "wof:placetype":"postalcode"
},
  "geometry": {"coordinates":[-3.212819,51.791624],"type":"Point"}
}