{
  "type": "Feature",
  "properties": {
    "iso:country":"GB",
    "wof:name":"IV2 5GW",
    "wof:placetype":"postalcode"
},
  "geometry": {"coordinates":[-4.13541193613318,57.47692317148684],"type":"Point"}
}