{
  "type": "Feature",
  "properties": {
    "iso:country":"GB",
    "wof:name":"DY4 7NT",
    "wof:placetype":"postalcode"
},
  "geometry": {"coordinates":[-2.04803983832647,52.52893847123492],"type":"Point"}
}