{
  "type": "Feature",
  "properties": {
    "date:inception_lower": "2004-01-01",
    "date:inception_upper": "2004-01-01",
    "iso:country": "GB",
    "wof:name": "DY4 7NT",
    "wof:placetype": "postalcode"
  },
  "geometry": {"coordinates":[-2.04804,52.528938],"type":"Point"}
}
