{
  "type": "Feature",
  "properties": {
    "iso:country": "GB",
    "wof:name": "TS29 6JG",
    "wof:placetype": "postalcode"
  },
  "geometry": {"coordinates":[-1.433324,54.696927],"type":"Point"}
}
