{
  "type": "Feature",
  "properties": {
    "iso:country":"GB",
    "wof:name":"TS29 6JG",
    "wof:placetype":"postalcode"
},
  "geometry": {"coordinates":[-1.43332366008053,54.69692685503333],"type":"Point"}
}