{
  "type": "Feature",
  "properties": {
    "iso:country":"GB",
    "wof:name":"SO53 1LJ",
    "wof:placetype":"postalcode"
},
  "geometry": {"coordinates":[-1.38293274587547,50.99557634081261],"type":"Point"}
}