{
  "type": "Feature",
  "properties": {
    "iso:country":"GB",
    "wof:name":"BS30 8GA",
    "wof:placetype":"postalcode"
},
  "geometry": {"coordinates":[-2.48401191647925,51.45221901975074],"type":"Point"}
}