{
  "type": "Feature",
  "properties": {
    "date:inception_lower": "2020-11-01",
    "date:inception_upper": "2020-11-01",
    "iso:country": "GB",
    "wof:name": "M11 2PH",
    "wof:placetype": "postalcode"
  },
  "geometry": {"coordinates":[-2.192615,53.475619],"type":"Point"}
}
