{
  "type": "Feature",
  "properties": {
    "iso:country":"GB",
    "wof:name":"NW3 6QD",
    "wof:placetype":"postalcode"
},
  "geometry": {"coordinates":[-0.18528083417273,51.5526622984967],"type":"Point"}
}