{
  "type": "Feature",
  "properties": {
    "iso:country":"GB",
    "wof:name":"CT13 0AW",
    "wof:placetype":"postalcode"
},
  "geometry": {"coordinates":[1.33876554883845,51.26966874744318],"type":"Point"}
}