{
  "type": "Feature",
  "properties": {
    "date:inception_lower": "2022-09-01",
    "date:inception_upper": "2022-09-01",
    "iso:country": "GB",
    "wof:name": "CO11 2GX",
    "wof:placetype": "postalcode"
  },
  "geometry": {"coordinates":[1.165769,51.938327],"type":"Point"}
}
