{
  "type": "Feature",
  "properties": {
    "date:inception_lower": "2003-02-01",
    "date:inception_upper": "2003-02-01",
    "iso:country": "GB",
    "wof:name": "CF72 9UT",
    "wof:placetype": "postalcode"
  },
  "geometry": {"coordinates":[-3.451794,51.534391],"type":"Point"}
}
