{
  "type": "Feature",
  "properties": {
    "iso:country": "GB",
    "wof:name": "CF72 9UT",
    "wof:placetype": "postalcode"
  },
  "geometry": {"coordinates":[-3.451794,51.534391],"type":"Point"}
}
