{
  "type": "Feature",
  "properties": {
    "iso:country":"GB",
    "wof:name":"CF72 9UT",
    "wof:placetype":"postalcode"
},
  "geometry": {"coordinates":[-3.45179369743947,51.53439091830331],"type":"Point"}
}