{
  "type": "Feature",
  "properties": {
    "iso:country":"GB",
    "wof:name":"E6 6HW",
    "wof:placetype":"postalcode"
},
  "geometry": {"coordinates":[0.05999244611515,51.52320756940011],"type":"Point"}
}