{
  "type": "Feature",
  "properties": {
    "date:inception_lower":"1998-06-01",
    "date:inception_upper":"1998-06-30",
    "iso:country":"GB",
    "wof:name":"E6 6HW",
    "wof:placetype":"postalcode"
},
  "geometry": {"coordinates":[0.059992,51.523208],"type":"Point"}
}