{
  "type": "Feature",
  "properties": {
    "iso:country": "GB",
    "wof:name": "E6 6HW",
    "wof:placetype": "postalcode"
  },
  "geometry": {"coordinates":[0.059992,51.523208],"type":"Point"}
}
