{
  "type": "Feature",
  "properties": {
    "date:inception_lower": "2022-04-01",
    "date:inception_upper": "2022-04-01",
    "iso:country": "GB",
    "wof:name": "W7 3FL",
    "wof:placetype": "postalcode"
  },
  "geometry": {"coordinates":[-0.3406,51.508095],"type":"Point"}
}
