{
  "type": "Feature",
  "properties": {
    "date:inception_lower": "1980-01-01",
    "date:inception_upper": "1980-01-01",
    "iso:country": "GB",
    "wof:name": "FK10 3PD",
    "wof:placetype": "postalcode"
  },
  "geometry": {"coordinates":[-3.766033,56.12747],"type":"Point"}
}
