{
  "type": "Feature",
  "properties": {
    "iso:country": "GB",
    "wof:name": "WF17 6LL",
    "wof:placetype": "postalcode"
  },
  "geometry": {"coordinates":[-1.615828,53.707469],"type":"Point"}
}
