{
  "type": "Feature",
  "properties": {
    "date:inception_lower": "1984-10-01",
    "date:inception_upper": "1984-10-01",
    "iso:country": "GB",
    "wof:name": "KT22 0SA",
    "wof:placetype": "postalcode"
  },
  "geometry": {"coordinates":[-0.354409,51.331965],"type":"Point"}
}
