{
  "type": "Feature",
  "properties": {
    "iso:country":"GB",
    "wof:name":"YO32 9JR",
    "wof:placetype":"postalcode"
},
  "geometry": {"coordinates":[-1.04670832244247,53.9849373738059],"type":"Point"}
}