{
  "type": "Feature",
  "properties": {
    "iso:country": "GB",
    "wof:name": "CH62 7JL",
    "wof:placetype": "postalcode"
  },
  "geometry": {"coordinates":[-2.974322,53.328097],"type":"Point"}
}
