{
  "type": "Feature",
  "properties": {
    "iso:country":"GB",
    "wof:name":"CH62 7JL",
    "wof:placetype":"postalcode"
},
  "geometry": {"coordinates":[-2.97432187889047,53.3280966250174],"type":"Point"}
}