{
  "type": "Feature",
  "properties": {
    "date:inception_lower":"1999-06-01",
    "date:inception_upper":"1999-06-30",
    "iso:country":"GB",
    "wof:name":"CH62 7JL",
    "wof:placetype":"postalcode"
},
  "geometry": {"coordinates":[-2.974322,53.328097],"type":"Point"}
}