{
  "type": "Feature",
  "properties": {
    "iso:country":"GB",
    "wof:name":"CM9 6JH",
    "wof:placetype":"postalcode"
},
  "geometry": {"coordinates":[0.67525488983681,51.72096348735768],"type":"Point"}
}