{
  "type": "Feature",
  "properties": {
    "iso:country": "GB",
    "wof:name": "CM9 6JH",
    "wof:placetype": "postalcode"
  },
  "geometry": {"coordinates":[0.675255,51.720963],"type":"Point"}
}
