{
  "type": "Feature",
  "properties": {
    "date:inception_lower": "1990-02-01",
    "date:inception_upper": "1990-02-01",
    "iso:country": "GB",
    "wof:name": "CM9 6JH",
    "wof:placetype": "postalcode"
  },
  "geometry": {"coordinates":[0.675255,51.720963],"type":"Point"}
}
