{
  "type": "Feature",
  "properties": {
    "iso:country":"GB",
    "wof:name":"SP3 4LQ",
    "wof:placetype":"postalcode"
},
  "geometry": {"coordinates":[-1.90057169161419,51.13676529370957],"type":"Point"}
}