{
  "type": "Feature",
  "properties": {
    "iso:country":"GB",
    "wof:name":"EH6 8LN",
    "wof:placetype":"postalcode"
},
  "geometry": {"coordinates":[-3.1717891902856,55.97017822340349],"type":"Point"}
}