{
  "type": "Feature",
  "properties": {
    "date:inception_lower":"2007-01-01",
    "date:inception_upper":"2007-01-31",
    "iso:country":"GB",
    "wof:name":"ME16 8BZ",
    "wof:placetype":"postalcode"
},
  "geometry": {"coordinates":[0.507506,51.268978],"type":"Point"}
}