{
  "type": "Feature",
  "properties": {
    "iso:country": "GB",
    "wof:name": "ME16 8BZ",
    "wof:placetype": "postalcode"
  },
  "geometry": {"coordinates":[0.507506,51.268978],"type":"Point"}
}
