{
  "type": "Feature",
  "properties": {
    "iso:country":"GB",
    "wof:name":"GL1 5HW",
    "wof:placetype":"postalcode"
},
  "geometry": {"coordinates":[-2.25455098145042,51.85036446752057],"type":"Point"}
}