{
  "type": "Feature",
  "properties": {
    "iso:country": "GB",
    "wof:name": "GL1 5HW",
    "wof:placetype": "postalcode"
  },
  "geometry": {"coordinates":[-2.254551,51.850364],"type":"Point"}
}
