{
  "type": "Feature",
  "properties": {
    "iso:country":"GB",
    "wof:name":"PE12 9JD",
    "wof:placetype":"postalcode"
},
  "geometry": {"coordinates":[0.12103894433653,52.78482680820198],"type":"Point"}
}