{
  "type": "Feature",
  "properties": {
    "iso:country": "GB",
    "wof:name": "PE12 9JD",
    "wof:placetype": "postalcode"
  },
  "geometry": {"coordinates":[0.121261,52.78424],"type":"Point"}
}
