{
  "type": "Feature",
  "properties": {
    "iso:country":"GB",
    "wof:name":"HS2 9DZ",
    "wof:placetype":"postalcode"
},
  "geometry": {"coordinates":[-6.73799597384614,58.21002575193829],"type":"Point"}
}