{
  "type": "Feature",
  "properties": {
    "date:inception_lower": "1995-07-01",
    "date:inception_upper": "1995-07-01",
    "iso:country": "GB",
    "wof:name": "HS2 9DZ",
    "wof:placetype": "postalcode"
  },
  "geometry": {"coordinates":[-6.737809,58.210863],"type":"Point"}
}
