{
  "type": "Feature",
  "properties": {
    "date:inception_lower": "1980-01-01",
    "date:inception_upper": "1980-01-01",
    "iso:country": "GB",
    "wof:name": "GL20 8DL",
    "wof:placetype": "postalcode"
  },
  "geometry": {"coordinates":[-2.132675,51.99575],"type":"Point"}
}
