{
  "type": "Feature",
  "properties": {
    "iso:country": "GB",
    "wof:name": "GL20 8DL",
    "wof:placetype": "postalcode"
  },
  "geometry": {"coordinates":[-2.132617,51.995723],"type":"Point"}
}
