{
  "type": "Feature",
  "properties": {
    "iso:country":"GB",
    "wof:name":"WS8 7RJ",
    "wof:placetype":"postalcode"
},
  "geometry": {"coordinates":[-1.94409607929243,52.64077733475973],"type":"Point"}
}