{
  "type": "Feature",
  "properties": {
    "iso:country":"GB",
    "wof:name":"BS5 7HP",
    "wof:placetype":"postalcode"
},
  "geometry": {"coordinates":[-2.54041136477115,51.46198018407912],"type":"Point"}
}