{
  "type": "Feature",
  "properties": {
    "iso:country":"GB",
    "wof:name":"LS29 8SZ",
    "wof:placetype":"postalcode"
},
  "geometry": {"coordinates":[-1.81906936629382,53.92215185952347],"type":"Point"}
}