{
  "type": "Feature",
  "properties": {
    "date:inception_lower": "1980-01-01",
    "date:inception_upper": "1980-01-01",
    "iso:country": "GB",
    "wof:name": "EN1 1BS",
    "wof:placetype": "postalcode"
  },
  "geometry": {"coordinates":[-0.071507,51.645538],"type":"Point"}
}
