{
  "type": "Feature",
  "properties": {
    "iso:country":"GB",
    "wof:name":"EN1 1BS",
    "wof:placetype":"postalcode"
},
  "geometry": {"coordinates":[-0.07150747179187,51.64553806497371],"type":"Point"}
}