{
  "type": "Feature",
  "properties": {
    "iso:country":"GB",
    "wof:name":"L11 2UY",
    "wof:placetype":"postalcode"
},
  "geometry": {"coordinates":[-2.91204296484541,53.4435931446254],"type":"Point"}
}