{
  "type": "Feature",
  "properties": {
    "iso:country":"GB",
    "wof:name":"SL9 0PJ",
    "wof:placetype":"postalcode"
},
  "geometry": {"coordinates":[-0.55491254742404,51.62683697470047],"type":"Point"}
}