{
  "type": "Feature",
  "properties": {
    "iso:country":"GB",
    "wof:name":"LE15 9PP",
    "wof:placetype":"postalcode"
},
  "geometry": {"coordinates":[-0.71850451596302,52.58739200278185],"type":"Point"}
}