{
  "type": "Feature",
  "properties": {
    "iso:country": "GB",
    "wof:name": "LE15 9PP",
    "wof:placetype": "postalcode"
  },
  "geometry": {"coordinates":[-0.718426,52.587643],"type":"Point"}
}
