{
  "type": "Feature",
  "properties": {
    "iso:country":"GB",
    "wof:name":"CH2 1RP",
    "wof:placetype":"postalcode"
},
  "geometry": {"coordinates":[-2.88219087768424,53.21747520482235],"type":"Point"}
}