{
  "type": "Feature",
  "properties": {
    "iso:country":"GB",
    "wof:name":"HD1 5AZ",
    "wof:placetype":"postalcode"
},
  "geometry": {"coordinates":[-1.78498290661499,53.65044268407729],"type":"Point"}
}