{
  "type": "Feature",
  "properties": {
    "iso:country": "GB",
    "wof:name": "HD1 5AZ",
    "wof:placetype": "postalcode"
  },
  "geometry": {"coordinates":[-1.784983,53.650443],"type":"Point"}
}
