{
  "type": "Feature",
  "properties": {
    "iso:country":"GB",
    "wof:name":"WS3 4EW",
    "wof:placetype":"postalcode"
},
  "geometry": {"coordinates":[-1.96387490346964,52.63365612475643],"type":"Point"}
}