{
  "type": "Feature",
  "properties": {
    "iso:country":"GB",
    "wof:name":"M27 8UE",
    "wof:placetype":"postalcode"
},
  "geometry": {"coordinates":[-2.30855892134,53.50958774313455],"type":"Point"}
}