{
  "type": "Feature",
  "properties": {
    "iso:country": "GB",
    "wof:name": "OX15 4RX",
    "wof:placetype": "postalcode"
  },
  "geometry": {"coordinates":[-1.406488,52.008545],"type":"Point"}
}
