{
  "type": "Feature",
  "properties": {
    "iso:country":"GB",
    "wof:name":"OX15 4RX",
    "wof:placetype":"postalcode"
},
  "geometry": {"coordinates":[-1.40648832937663,52.00854461398188],"type":"Point"}
}