{
  "type": "Feature",
  "properties": {
    "iso:country": "GB",
    "wof:name": "SA1 3RD",
    "wof:placetype": "postalcode"
  },
  "geometry": {"coordinates":[-3.938788,51.616368],"type":"Point"}
}
