{
  "type": "Feature",
  "properties": {
    "iso:country":"GB",
    "wof:name":"SA1 3RD",
    "wof:placetype":"postalcode"
},
  "geometry": {"coordinates":[-3.93878791443228,51.61636813475534],"type":"Point"}
}