{
  "type": "Feature",
  "properties": {
    "iso:country": "GB",
    "wof:name": "OX17 3HE",
    "wof:placetype": "postalcode"
  },
  "geometry": {"coordinates":[-1.32376,52.010778],"type":"Point"}
}
