{
  "type": "Feature",
  "properties": {
    "iso:country":"GB",
    "wof:name":"E1W 3EL",
    "wof:placetype":"postalcode"
},
  "geometry": {"coordinates":[-0.04803183935282,51.5108557371863],"type":"Point"}
}