{
  "type": "Feature",
  "properties": {
    "iso:country":"GB",
    "wof:name":"HG1 5QN",
    "wof:placetype":"postalcode"
},
  "geometry": {"coordinates":[-1.53537905723321,53.99059616521128],"type":"Point"}
}