{
  "type": "Feature",
  "properties": {
    "iso:country": "GB",
    "wof:name": "HG1 5QN",
    "wof:placetype": "postalcode"
  },
  "geometry": {"coordinates":[-1.535379,53.990596],"type":"Point"}
}
