{
  "type": "Feature",
  "properties": {
    "iso:country":"GB",
    "wof:name":"SY10 8HE",
    "wof:placetype":"postalcode"
},
  "geometry": {"coordinates":[-3.00901959196794,52.81030372635173],"type":"Point"}
}