{
  "type": "Feature",
  "properties": {
    "iso:country":"GB",
    "wof:name":"TR1 3TJ",
    "wof:placetype":"postalcode"
},
  "geometry": {"coordinates":[-5.06141623115612,50.26712228997138],"type":"Point"}
}