{
  "type": "Feature",
  "properties": {
    "date:inception_lower": "1980-01-01",
    "date:inception_upper": "1980-01-01",
    "iso:country": "GB",
    "wof:name": "WN7 1TX",
    "wof:placetype": "postalcode"
  },
  "geometry": {"coordinates":[-2.514932,53.51142],"type":"Point"}
}
