{
  "type": "Feature",
  "properties": {
    "iso:country":"GB",
    "wof:name":"FK10 4HP",
    "wof:placetype":"postalcode"
},
  "geometry": {"coordinates":[-3.75256032729232,56.10893511923174],"type":"Point"}
}