{
  "type": "Feature",
  "properties": {
    "iso:country":"GB",
    "wof:name":"GU7 1NU",
    "wof:placetype":"postalcode"
},
  "geometry": {"coordinates":[-0.60853088861684,51.18184035530528],"type":"Point"}
}