{
  "type": "Feature",
  "properties": {
    "iso:country":"GB",
    "wof:name":"DT1 2BX",
    "wof:placetype":"postalcode"
},
  "geometry": {"coordinates":[-2.43380927732419,50.70709979194216],"type":"Point"}
}