{
  "type": "Feature",
  "properties": {
    "iso:country": "GB",
    "wof:name": "HX5 0EW",
    "wof:placetype": "postalcode"
  },
  "geometry": {"coordinates":[-1.836192,53.682225],"type":"Point"}
}
