{
  "type": "Feature",
  "properties": {
    "iso:country":"GB",
    "wof:name":"HX5 0EW",
    "wof:placetype":"postalcode"
},
  "geometry": {"coordinates":[-1.83619174726047,53.68222483491293],"type":"Point"}
}