{
  "type": "Feature",
  "properties": {
    "date:inception_lower": "1990-07-01",
    "date:inception_upper": "1990-07-01",
    "iso:country": "GB",
    "wof:name": "E11 3RL",
    "wof:placetype": "postalcode"
  },
  "geometry": {"coordinates":[0.031269,51.563242],"type":"Point"}
}
