{
  "type": "Feature",
  "properties": {
    "iso:country":"GB",
    "wof:name":"E11 3RL",
    "wof:placetype":"postalcode"
},
  "geometry": {"coordinates":[0.03122679665263,51.56321407464856],"type":"Point"}
}