{
  "type": "Feature",
  "properties": {
    "iso:country":"GB",
    "wof:name":"TR12 7BA",
    "wof:placetype":"postalcode"
},
  "geometry": {"coordinates":[-5.21737912147764,50.04674738073877],"type":"Point"}
}