{
  "type": "Feature",
  "properties": {
    "iso:country": "GB",
    "wof:name": "NE39 2HR",
    "wof:placetype": "postalcode"
  },
  "geometry": {"coordinates":[-1.78379,54.93628],"type":"Point"}
}
