{
  "type": "Feature",
  "properties": {
    "iso:country":"GB",
    "wof:name":"NE39 2HR",
    "wof:placetype":"postalcode"
},
  "geometry": {"coordinates":[-1.78378973295102,54.93627965402571],"type":"Point"}
}