{
  "type": "Feature",
  "properties": {
    "date:inception_lower": "2003-09-01",
    "date:inception_upper": "2003-09-01",
    "iso:country": "GB",
    "wof:name": "NE39 2HR",
    "wof:placetype": "postalcode"
  },
  "geometry": {"coordinates":[-1.78379,54.93628],"type":"Point"}
}
