{
  "type": "Feature",
  "properties": {
    "date:inception_lower": "1980-01-01",
    "date:inception_upper": "1980-01-01",
    "iso:country": "GB",
    "wof:name": "L21 7LU",
    "wof:placetype": "postalcode"
  },
  "geometry": {"coordinates":[-2.997126,53.471345],"type":"Point"}
}
