{
  "type": "Feature",
  "properties": {
    "iso:country":"GB",
    "wof:name":"L21 7LU",
    "wof:placetype":"postalcode"
},
  "geometry": {"coordinates":[-2.99712574939022,53.47134485078737],"type":"Point"}
}