{
  "type": "Feature",
  "properties": {
    "iso:country": "GB",
    "wof:name": "EX14 3AY",
    "wof:placetype": "postalcode"
  },
  "geometry": {"coordinates":[-3.228315,50.779098],"type":"Point"}
}
