{
  "type": "Feature",
  "properties": {
    "date:inception_lower": "1999-12-01",
    "date:inception_upper": "1999-12-01",
    "iso:country": "GB",
    "wof:name": "EX14 3AY",
    "wof:placetype": "postalcode"
  },
  "geometry": {"coordinates":[-3.228428,50.779088],"type":"Point"}
}
