{
  "type": "Feature",
  "properties": {
    "iso:country":"GB",
    "wof:name":"BN13 3ST",
    "wof:placetype":"postalcode"
},
  "geometry": {"coordinates":[-0.4274475711043,50.83165507132243],"type":"Point"}
}