{
  "type": "Feature",
  "properties": {
    "iso:country":"GB",
    "wof:name":"DE7 4HU",
    "wof:placetype":"postalcode"
},
  "geometry": {"coordinates":[-1.32872749978228,52.96023400130439],"type":"Point"}
}