{
  "type": "Feature",
  "properties": {
    "iso:country":"GB",
    "wof:name":"TN34 3NZ",
    "wof:placetype":"postalcode"
},
  "geometry": {"coordinates":[0.59592009038689,50.86597760950585],"type":"Point"}
}