{
  "type": "Feature",
  "properties": {
    "date:inception_lower": "1980-01-01",
    "date:inception_upper": "1980-01-01",
    "iso:country": "GB",
    "wof:name": "TN34 3NZ",
    "wof:placetype": "postalcode"
  },
  "geometry": {"coordinates":[0.59592,50.865978],"type":"Point"}
}
