{
  "type": "Feature",
  "properties": {
    "iso:country":"GB",
    "wof:name":"HX2 9XF",
    "wof:placetype":"postalcode"
},
  "geometry": {"coordinates":[-1.87877678599447,53.77344137172019],"type":"Point"}
}