{
  "type": "Feature",
  "properties": {
    "iso:country": "GB",
    "wof:name": "HX2 9XF",
    "wof:placetype": "postalcode"
  },
  "geometry": {"coordinates":[-1.878777,53.773441],"type":"Point"}
}
