{
  "type": "Feature",
  "properties": {
    "iso:country":"GB",
    "wof:name":"PO32 6LU",
    "wof:placetype":"postalcode"
},
  "geometry": {"coordinates":[-1.26888473093526,50.74073402263161],"type":"Point"}
}