{
  "type": "Feature",
  "properties": {
    "iso:country":"GB",
    "wof:name":"DN2 4JJ",
    "wof:placetype":"postalcode"
},
  "geometry": {"coordinates":[-1.10929930012543,53.53374440941369],"type":"Point"}
}