{
  "type": "Feature",
  "properties": {
    "date:inception_lower":"2001-06-01",
    "date:inception_upper":"2001-06-30",
    "iso:country":"GB",
    "wof:name":"OX29 4JD",
    "wof:placetype":"postalcode"
},
  "geometry": {"coordinates":[-1.370604,51.782784],"type":"Point"}
}