{
  "type": "Feature",
  "properties": {
    "iso:country":"GB",
    "wof:name":"OX29 4JD",
    "wof:placetype":"postalcode"
},
  "geometry": {"coordinates":[-1.37060417909274,51.78278366852506],"type":"Point"}
}