{
  "type": "Feature",
  "properties": {
    "iso:country": "GB",
    "wof:name": "CO10 1BB",
    "wof:placetype": "postalcode"
  },
  "geometry": {"coordinates":[0.727583,52.038865],"type":"Point"}
}
