{
  "type": "Feature",
  "properties": {
    "iso:country":"GB",
    "wof:name":"CO10 1BB",
    "wof:placetype":"postalcode"
},
  "geometry": {"coordinates":[0.7274354137408,52.03885442315035],"type":"Point"}
}