{
  "type": "Feature",
  "properties": {
    "iso:country": "GB",
    "wof:name": "DN15 7AQ",
    "wof:placetype": "postalcode"
  },
  "geometry": {"coordinates":[-0.655805,53.585656],"type":"Point"}
}
