{
  "type": "Feature",
  "properties": {
    "iso:country":"GB",
    "wof:name":"SE15 5LL",
    "wof:placetype":"postalcode"
},
  "geometry": {"coordinates":[-0.07531775935861,51.47516539287344],"type":"Point"}
}