{
  "type": "Feature",
  "properties": {
    "iso:country":"GB",
    "wof:name":"BH23 2QF",
    "wof:placetype":"postalcode"
},
  "geometry": {"coordinates":[-1.80881673173239,50.74628512901867],"type":"Point"}
}