{
  "type": "Feature",
  "properties": {
    "iso:country":"GB",
    "wof:name":"SL4 3JS",
    "wof:placetype":"postalcode"
},
  "geometry": {"coordinates":[-0.61455968926405,51.47175185128616],"type":"Point"}
}