{
  "type": "Feature",
  "properties": {
    "iso:country": "GB",
    "wof:name": "SL4 3JS",
    "wof:placetype": "postalcode"
  },
  "geometry": {"coordinates":[-0.61456,51.471752],"type":"Point"}
}
