{
  "type": "Feature",
  "properties": {
    "iso:country":"GB",
    "wof:name":"ME15 6PR",
    "wof:placetype":"postalcode"
},
  "geometry": {"coordinates":[0.52584409290718,51.26612842345518],"type":"Point"}
}