{
  "type": "Feature",
  "properties": {
    "iso:country": "GB",
    "wof:name": "ME15 6PR",
    "wof:placetype": "postalcode"
  },
  "geometry": {"coordinates":[0.526034,51.26616],"type":"Point"}
}
