{
  "type": "Feature",
  "properties": {
    "date:inception_lower":"1999-06-01",
    "date:inception_upper":"1999-06-30",
    "iso:country":"GB",
    "wof:name":"NP25 3JS",
    "wof:placetype":"postalcode"
},
  "geometry": {"coordinates":[-2.695908,51.805851],"type":"Point"}
}