{
  "type": "Feature",
  "properties": {
    "iso:country":"GB",
    "wof:name":"NP25 3JS",
    "wof:placetype":"postalcode"
},
  "geometry": {"coordinates":[-2.69594748842912,51.80581857378471],"type":"Point"}
}