{
  "type": "Feature",
  "properties": {
    "iso:country":"GB",
    "wof:name":"WA15 0SB",
    "wof:placetype":"postalcode"
},
  "geometry": {"coordinates":[-2.30406802359498,53.3624568758794],"type":"Point"}
}