{
  "type": "Feature",
  "properties": {
    "iso:country":"GB",
    "wof:name":"BH7 6NH",
    "wof:placetype":"postalcode"
},
  "geometry": {"coordinates":[-1.82379567903118,50.73562542374817],"type":"Point"}
}