{
  "type": "Feature",
  "properties": {
    "iso:country": "GB",
    "wof:name": "BH7 6NH",
    "wof:placetype": "postalcode"
  },
  "geometry": {"coordinates":[-1.823796,50.735625],"type":"Point"}
}
