{
  "type": "Feature",
  "properties": {
    "iso:country":"GB",
    "wof:name":"BN1 6BN",
    "wof:placetype":"postalcode"
},
  "geometry": {"coordinates":[-0.14806283741958,50.83810435169963],"type":"Point"}
}