{
  "type": "Feature",
  "properties": {
    "date:inception_lower": "2020-02-01",
    "date:inception_upper": "2020-02-01",
    "iso:country": "GB",
    "wof:name": "PR5 9DJ",
    "wof:placetype": "postalcode"
  },
  "geometry": {"coordinates":[-2.658506,53.733185],"type":"Point"}
}
