{
  "type": "Feature",
  "properties": {
    "iso:country":"GB",
    "wof:name":"S35 7DR",
    "wof:placetype":"postalcode"
},
  "geometry": {"coordinates":[-1.53507728807572,53.49000105618605],"type":"Point"}
}