{
  "type": "Feature",
  "properties": {
    "iso:country": "GB",
    "wof:name": "DL13 5AZ",
    "wof:placetype": "postalcode"
  },
  "geometry": {"coordinates":[-1.808202,54.629845],"type":"Point"}
}
