{
  "type": "Feature",
  "properties": {
    "iso:country":"GB",
    "wof:name":"EN2 6EX",
    "wof:placetype":"postalcode"
},
  "geometry": {"coordinates":[-0.08205935642009,51.64655618818096],"type":"Point"}
}