{
  "type": "Feature",
  "properties": {
    "iso:country":"GB",
    "wof:name":"LU4 9JF",
    "wof:placetype":"postalcode"
},
  "geometry": {"coordinates":[-0.4690126459239,51.90772223492045],"type":"Point"}
}