{
  "type": "Feature",
  "properties": {
    "date:inception_lower":"2012-04-01",
    "date:inception_upper":"2012-04-30",
    "iso:country":"GB",
    "wof:name":"EN3 7GJ",
    "wof:placetype":"postalcode"
},
  "geometry": {"coordinates":[-0.021826,51.671824],"type":"Point"}
}