{
  "type": "Feature",
  "properties": {
    "iso:country": "GB",
    "wof:name": "EN3 7GJ",
    "wof:placetype": "postalcode"
  },
  "geometry": {"coordinates":[-0.021826,51.671824],"type":"Point"}
}
