{
  "type": "Feature",
  "properties": {
    "iso:country":"GB",
    "wof:name":"EN3 7GJ",
    "wof:placetype":"postalcode"
},
  "geometry": {"coordinates":[-0.0218259931337,51.67182376702942],"type":"Point"}
}