{
  "type": "Feature",
  "properties": {
    "iso:country":"GB",
    "wof:name":"CF32 9DL",
    "wof:placetype":"postalcode"
},
  "geometry": {"coordinates":[-3.59985650472854,51.55008936867878],"type":"Point"}
}