{
  "type": "Feature",
  "properties": {
    "iso:country": "GB",
    "wof:name": "IP20 9DG",
    "wof:placetype": "postalcode"
  },
  "geometry": {"coordinates":[1.299426,52.399015],"type":"Point"}
}
