{
  "type": "Feature",
  "properties": {
    "iso:country":"GB",
    "wof:name":"IP20 9DG",
    "wof:placetype":"postalcode"
},
  "geometry": {"coordinates":[1.29942626012441,52.39901534316081],"type":"Point"}
}