{
  "type": "Feature",
  "properties": {
    "date:inception_lower":"1980-01-01",
    "date:inception_upper":"1980-01-31",
    "iso:country":"GB",
    "wof:name":"IP20 9DG",
    "wof:placetype":"postalcode"
},
  "geometry": {"coordinates":[1.299426,52.399015],"type":"Point"}
}