{
  "type": "Feature",
  "properties": {
    "iso:country":"GB",
    "wof:name":"NG16 2YN",
    "wof:placetype":"postalcode"
},
  "geometry": {"coordinates":[-1.29848064262929,53.00508718875393],"type":"Point"}
}