{
  "type": "Feature",
  "properties": {
    "iso:country":"GB",
    "wof:name":"EN1 2BH",
    "wof:placetype":"postalcode"
},
  "geometry": {"coordinates":[-0.08026649407206,51.64246232514841],"type":"Point"}
}