{
  "type": "Feature",
  "properties": {
    "iso:country":"GB",
    "wof:name":"B29 6DP",
    "wof:placetype":"postalcode"
},
  "geometry": {"coordinates":[-1.93485769421216,52.4421775220433],"type":"Point"}
}