{
  "type": "Feature",
  "properties": {
    "date:inception_lower": "1980-01-01",
    "date:inception_upper": "1980-01-01",
    "iso:country": "GB",
    "wof:name": "DY3 2JT",
    "wof:placetype": "postalcode"
  },
  "geometry": {"coordinates":[-2.131324,52.524227],"type":"Point"}
}
