{
  "type": "Feature",
  "properties": {
    "iso:country":"GB",
    "wof:name":"DY3 2JT",
    "wof:placetype":"postalcode"
},
  "geometry": {"coordinates":[-2.1313241228579,52.52422741202081],"type":"Point"}
}