{
  "type": "Feature",
  "properties": {
    "date:inception_lower": "1980-01-01",
    "date:inception_upper": "1980-01-01",
    "iso:country": "GB",
    "wof:name": "SN3 5BU",
    "wof:placetype": "postalcode"
  },
  "geometry": {"coordinates":[-1.730731,51.563209],"type":"Point"}
}
