{
  "type": "Feature",
  "properties": {
    "iso:country": "GB",
    "wof:name": "LL30 1EJ",
    "wof:placetype": "postalcode"
  },
  "geometry": {"coordinates":[-3.80686,53.319316],"type":"Point"}
}
