{
  "type": "Feature",
  "properties": {
    "iso:country":"GB",
    "wof:name":"LL30 1EJ",
    "wof:placetype":"postalcode"
},
  "geometry": {"coordinates":[-3.80685970096132,53.31931584488222],"type":"Point"}
}