{
  "type": "Feature",
  "properties": {
    "iso:country":"GB",
    "wof:name":"HU3 4TX",
    "wof:placetype":"postalcode"
},
  "geometry": {"coordinates":[-0.37252201632651,53.73077192446862],"type":"Point"}
}