{
  "type": "Feature",
  "properties": {
    "iso:country":"GB",
    "wof:name":"BS36 1PS",
    "wof:placetype":"postalcode"
},
  "geometry": {"coordinates":[-2.49857849229247,51.52900876825277],"type":"Point"}
}