{
  "type": "Feature",
  "properties": {
    "iso:country": "GB",
    "wof:name": "LA12 0QR",
    "wof:placetype": "postalcode"
  },
  "geometry": {"coordinates":[-3.158727,54.115361],"type":"Point"}
}
