{
  "type": "Feature",
  "properties": {
    "iso:country":"GB",
    "wof:name":"LA12 0QR",
    "wof:placetype":"postalcode"
},
  "geometry": {"coordinates":[-3.15871486812,54.11537023872496],"type":"Point"}
}