{
  "type": "Feature",
  "properties": {
    "date:inception_lower":"1980-01-01",
    "date:inception_upper":"1980-01-31",
    "iso:country":"GB",
    "wof:name":"LA12 0QR",
    "wof:placetype":"postalcode"
},
  "geometry": {"coordinates":[-3.158727,54.115361],"type":"Point"}
}