{
  "type": "Feature",
  "properties": {
    "iso:country": "GB",
    "wof:name": "HR9 6EZ",
    "wof:placetype": "postalcode"
  },
  "geometry": {"coordinates":[-2.691122,51.870547],"type":"Point"}
}
