{
  "type": "Feature",
  "properties": {
    "iso:country":"GB",
    "wof:name":"HR9 6EZ",
    "wof:placetype":"postalcode"
},
  "geometry": {"coordinates":[-2.69112222683795,51.8705469746785],"type":"Point"}
}