{
  "type": "Feature",
  "properties": {
    "date:inception_lower": "1980-01-01",
    "date:inception_upper": "1980-01-01",
    "iso:country": "GB",
    "wof:name": "HR9 6EZ",
    "wof:placetype": "postalcode"
  },
  "geometry": {"coordinates":[-2.690796,51.87087],"type":"Point"}
}
