{
  "type": "Feature",
  "properties": {
    "iso:country":"GB",
    "wof:name":"HR6 8EB",
    "wof:placetype":"postalcode"
},
  "geometry": {"coordinates":[-2.73966290033977,52.23160986766149],"type":"Point"}
}