{
  "type": "Feature",
  "properties": {
    "iso:country": "GB",
    "wof:name": "HR6 8EB",
    "wof:placetype": "postalcode"
  },
  "geometry": {"coordinates":[-2.739663,52.231594],"type":"Point"}
}
