{
  "type": "Feature",
  "properties": {
    "iso:country":"GB",
    "wof:name":"TN37 7RG",
    "wof:placetype":"postalcode"
},
  "geometry": {"coordinates":[0.55531413682921,50.8849435628819],"type":"Point"}
}