{
  "type": "Feature",
  "properties": {
    "iso:country":"GB",
    "wof:name":"TA13 5DE",
    "wof:placetype":"postalcode"
},
  "geometry": {"coordinates":[-2.81121800122064,50.94907327610299],"type":"Point"}
}