{
  "type": "Feature",
  "properties": {
    "date:inception_lower": "2017-02-01",
    "date:inception_upper": "2017-02-01",
    "iso:country": "GB",
    "wof:name": "TF1 3BJ",
    "wof:placetype": "postalcode"
  },
  "geometry": {"coordinates":[-2.511769,52.702008],"type":"Point"}
}
