{
  "type": "Feature",
  "properties": {
    "iso:country":"GB",
    "wof:name":"TF1 3BJ",
    "wof:placetype":"postalcode"
},
  "geometry": {"coordinates":[-2.50880590219357,52.70272409507471],"type":"Point"}
}