{
  "type": "Feature",
  "properties": {
    "iso:country":"GB",
    "wof:name":"SL1 2LW",
    "wof:placetype":"postalcode"
},
  "geometry": {"coordinates":[-0.60021573421479,51.50666861434786],"type":"Point"}
}