{
  "type": "Feature",
  "properties": {
    "iso:country":"GB",
    "wof:name":"EH15 2DU",
    "wof:placetype":"postalcode"
},
  "geometry": {"coordinates":[-3.10245214068206,55.9512838527304],"type":"Point"}
}