{
  "type": "Feature",
  "properties": {
    "iso:country": "GB",
    "wof:name": "LE8 6YB",
    "wof:placetype": "postalcode"
  },
  "geometry": {"coordinates":[-1.182112,52.557401],"type":"Point"}
}
