{
  "type": "Feature",
  "properties": {
    "iso:country":"GB",
    "wof:name":"BA3 5BX",
    "wof:placetype":"postalcode"
},
  "geometry": {"coordinates":[-2.5282699573764,51.22296180791867],"type":"Point"}
}