{
  "type": "Feature",
  "properties": {
    "iso:country":"GB",
    "wof:name":"KY4 0GX",
    "wof:placetype":"postalcode"
},
  "geometry": {"coordinates":[-3.37379757012103,56.13849413684078],"type":"Point"}
}