{
  "type": "Feature",
  "properties": {
    "date:inception_lower":"2007-01-01",
    "date:inception_upper":"2007-01-31",
    "iso:country":"GB",
    "wof:name":"KY4 0GX",
    "wof:placetype":"postalcode"
},
  "geometry": {"coordinates":[-3.373798,56.138494],"type":"Point"}
}