{
  "type": "Feature",
  "properties": {
    "date:inception_lower": "1994-12-01",
    "date:inception_upper": "1994-12-01",
    "iso:country": "GB",
    "wof:name": "SO17 2LA",
    "wof:placetype": "postalcode"
  },
  "geometry": {"coordinates":[-1.391352,50.927035],"type":"Point"}
}
