{
  "type": "Feature",
  "properties": {
    "iso:country": "GB",
    "wof:name": "SO17 2LA",
    "wof:placetype": "postalcode"
  },
  "geometry": {"coordinates":[-1.391352,50.927035],"type":"Point"}
}
