{
  "type": "Feature",
  "properties": {
    "iso:country":"GB",
    "wof:name":"W1U 6JW",
    "wof:placetype":"postalcode"
},
  "geometry": {"coordinates":[-0.15929557821142,51.52030731878313],"type":"Point"}
}