{
  "type": "Feature",
  "properties": {
    "date:inception_lower":"1993-01-01",
    "date:inception_upper":"1993-01-31",
    "iso:country":"GB",
    "wof:name":"NE29 8LY",
    "wof:placetype":"postalcode"
},
  "geometry": {"coordinates":[-1.467619,55.021881],"type":"Point"}
}