{
  "type": "Feature",
  "properties": {
    "iso:country":"GB",
    "wof:name":"NE29 8LY",
    "wof:placetype":"postalcode"
},
  "geometry": {"coordinates":[-1.46761918184633,55.02188111667989],"type":"Point"}
}