{
  "type": "Feature",
  "properties": {
    "iso:country":"GB",
    "wof:name":"WA5 9SE",
    "wof:placetype":"postalcode"
},
  "geometry": {"coordinates":[-2.61277045040033,53.41230859576668],"type":"Point"}
}