{
  "type": "Feature",
  "properties": {
    "iso:country":"GB",
    "wof:name":"PE11 4RH",
    "wof:placetype":"postalcode"
},
  "geometry": {"coordinates":[-0.20014108580871,52.88761036777408],"type":"Point"}
}