{
  "type": "Feature",
  "properties": {
    "iso:country": "GB",
    "wof:name": "PE11 4RH",
    "wof:placetype": "postalcode"
  },
  "geometry": {"coordinates":[-0.200127,52.887592],"type":"Point"}
}
