{
  "type": "Feature",
  "properties": {
    "iso:country": "GB",
    "wof:name": "FK10 2QX",
    "wof:placetype": "postalcode"
  },
  "geometry": {"coordinates":[-3.840028,56.136877],"type":"Point"}
}
