{
  "type": "Feature",
  "properties": {
    "date:inception_lower": "2001-12-01",
    "date:inception_upper": "2001-12-01",
    "iso:country": "GB",
    "wof:name": "OL1 3XH",
    "wof:placetype": "postalcode"
  },
  "geometry": {"coordinates":[-2.099826,53.541494],"type":"Point"}
}
