{
  "type": "Feature",
  "properties": {
    "iso:country":"GB",
    "wof:name":"OL4 3NA",
    "wof:placetype":"postalcode"
},
  "geometry": {"coordinates":[-2.09982634684913,53.54149388562834],"type":"Point"}
}