{
  "type": "Feature",
  "properties": {
    "iso:country": "GB",
    "wof:name": "PL5 3BR",
    "wof:placetype": "postalcode"
  },
  "geometry": {"coordinates":[-4.139092,50.410454],"type":"Point"}
}
