{
  "type": "Feature",
  "properties": {
    "iso:country":"GB",
    "wof:name":"DN5 7LA",
    "wof:placetype":"postalcode"
},
  "geometry": {"coordinates":[-1.17975534196673,53.51437442651196],"type":"Point"}
}