{
  "type": "Feature",
  "properties": {
    "date:inception_lower":"1980-01-01",
    "date:inception_upper":"1980-01-31",
    "iso:country":"GB",
    "wof:name":"DN5 7LA",
    "wof:placetype":"postalcode"
},
  "geometry": {"coordinates":[-1.179755,53.514374],"type":"Point"}
}