{
  "type": "Feature",
  "properties": {
    "date:inception_lower":"2004-01-01",
    "date:inception_upper":"2004-01-31",
    "iso:country":"GB",
    "wof:name":"EX24 6GB",
    "wof:placetype":"postalcode"
},
  "geometry": {"coordinates":[-3.073435,50.729259],"type":"Point"}
}