{
  "type": "Feature",
  "properties": {
    "iso:country":"GB",
    "wof:name":"EX24 6GB",
    "wof:placetype":"postalcode"
},
  "geometry": {"coordinates":[-3.0734346201069,50.72925902214159],"type":"Point"}
}