{
  "type": "Feature",
  "properties": {
    "iso:country": "GB",
    "wof:name": "EX24 6GB",
    "wof:placetype": "postalcode"
  },
  "geometry": {"coordinates":[-3.073435,50.729259],"type":"Point"}
}
