{
  "type": "Feature",
  "properties": {
    "iso:country": "GB",
    "wof:name": "CA6 4NW",
    "wof:placetype": "postalcode"
  },
  "geometry": {"coordinates":[-2.807763,54.940883],"type":"Point"}
}
