{
  "type": "Feature",
  "properties": {
    "iso:country":"GB",
    "wof:name":"CA6 4NW",
    "wof:placetype":"postalcode"
},
  "geometry": {"coordinates":[-2.80701806755039,54.94131286523665],"type":"Point"}
}