{
  "type": "Feature",
  "properties": {
    "date:inception_lower":"1980-01-01",
    "date:inception_upper":"1980-01-31",
    "iso:country":"GB",
    "wof:name":"CA6 4NW",
    "wof:placetype":"postalcode"
},
  "geometry": {"coordinates":[-2.807763,54.940883],"type":"Point"}
}