{
  "type": "Feature",
  "properties": {
    "date:inception_lower":"1980-01-01",
    "date:inception_upper":"1980-01-31",
    "iso:country":"GB",
    "wof:name":"E1 1EG",
    "wof:placetype":"postalcode"
},
  "geometry": {"coordinates":[-0.06755,51.515495],"type":"Point"}
}