{
  "type": "Feature",
  "properties": {
    "iso:country":"GB",
    "wof:name":"E1 1EG",
    "wof:placetype":"postalcode"
},
  "geometry": {"coordinates":[-0.06755033864163,51.515495411095],"type":"Point"}
}