{
  "type": "Feature",
  "properties": {
    "iso:country":"GB",
    "wof:name":"WA5 0AA",
    "wof:placetype":"postalcode"
},
  "geometry": {"coordinates":[-2.60147987443931,53.40113015637425],"type":"Point"}
}