{
  "type": "Feature",
  "properties": {
    "iso:country": "GB",
    "wof:name": "WA5 0AA",
    "wof:placetype": "postalcode"
  },
  "geometry": {"coordinates":[-2.60148,53.40113],"type":"Point"}
}
