{
  "type": "Feature",
  "properties": {
    "date:inception_lower": "1995-07-01",
    "date:inception_upper": "1995-07-01",
    "iso:country": "GB",
    "wof:name": "CF72 8DY",
    "wof:placetype": "postalcode"
  },
  "geometry": {"coordinates":[-3.368432,51.535447],"type":"Point"}
}
