{
  "type": "Feature",
  "properties": {
    "date:inception_lower": "1990-07-01",
    "date:inception_upper": "1990-07-01",
    "iso:country": "GB",
    "wof:name": "CR8 1HB",
    "wof:placetype": "postalcode"
  },
  "geometry": {"coordinates":[-0.104076,51.342704],"type":"Point"}
}
