{
  "type": "Feature",
  "properties": {
    "iso:country":"GB",
    "wof:name":"YO22 4JG",
    "wof:placetype":"postalcode"
},
  "geometry": {"coordinates":[-0.60831174731397,54.47841522965466],"type":"Point"}
}