{
  "type": "Feature",
  "properties": {
    "date:inception_lower":"2002-06-01",
    "date:inception_upper":"2002-06-30",
    "iso:country":"GB",
    "wof:name":"NR29 3SP",
    "wof:placetype":"postalcode"
},
  "geometry": {"coordinates":[1.713295,52.668703],"type":"Point"}
}