{
  "type": "Feature",
  "properties": {
    "iso:country":"GB",
    "wof:name":"IV27 4LA",
    "wof:placetype":"postalcode"
},
  "geometry": {"coordinates":[-5.23855527047515,58.15440519949403],"type":"Point"}
}