{
  "type": "Feature",
  "properties": {
    "iso:country":"GB",
    "wof:name":"W1U 1QY",
    "wof:placetype":"postalcode"
},
  "geometry": {"coordinates":[-0.1540063732648,51.51529631532932],"type":"Point"}
}