{
  "type": "Feature",
  "properties": {
    "date:inception_lower": "1980-01-01",
    "date:inception_upper": "1980-01-01",
    "iso:country": "GB",
    "wof:name": "HP20 2EQ",
    "wof:placetype": "postalcode"
  },
  "geometry": {"coordinates":[-0.809839,51.826199],"type":"Point"}
}
