{
  "type": "Feature",
  "properties": {
    "iso:country":"GB",
    "wof:name":"HP20 2EQ",
    "wof:placetype":"postalcode"
},
  "geometry": {"coordinates":[-0.80983938926043,51.82619903747219],"type":"Point"}
}