{
  "type": "Feature",
  "properties": {
    "iso:country":"GB",
    "wof:name":"EX39 3BX",
    "wof:placetype":"postalcode"
},
  "geometry": {"coordinates":[-4.21421610677387,51.01519000309875],"type":"Point"}
}