{
  "type": "Feature",
  "properties": {
    "iso:country": "GB",
    "wof:name": "EX39 3BX",
    "wof:placetype": "postalcode"
  },
  "geometry": {"coordinates":[-4.214216,51.01519],"type":"Point"}
}
