{
  "type": "Feature",
  "properties": {
    "iso:country": "GB",
    "wof:name": "CH8 7PN",
    "wof:placetype": "postalcode"
  },
  "geometry": {"coordinates":[-3.22317,53.277666],"type":"Point"}
}
