{
  "type": "Feature",
  "properties": {
    "iso:country":"GB",
    "wof:name":"CH8 7PN",
    "wof:placetype":"postalcode"
},
  "geometry": {"coordinates":[-3.22316809644728,53.27764873810802],"type":"Point"}
}