{
  "type": "Feature",
  "properties": {
    "iso:country":"GB",
    "wof:name":"SG8 5AA",
    "wof:placetype":"postalcode"
},
  "geometry": {"coordinates":[-0.0241767067682,52.04884218251165],"type":"Point"}
}