{
  "type": "Feature",
  "properties": {
    "date:inception_lower":"1980-01-01",
    "date:inception_upper":"1980-01-31",
    "iso:country":"GB",
    "wof:name":"SG8 5AA",
    "wof:placetype":"postalcode"
},
  "geometry": {"coordinates":[-0.024276,52.048908],"type":"Point"}
}