{
  "type": "Feature",
  "properties": {
    "iso:country":"GB",
    "wof:name":"S72 8RJ",
    "wof:placetype":"postalcode"
},
  "geometry": {"coordinates":[-1.40596669295871,53.5670001929795],"type":"Point"}
}