{
  "type": "Feature",
  "properties": {
    "iso:country":"GB",
    "wof:name":"NE65 0DY",
    "wof:placetype":"postalcode"
},
  "geometry": {"coordinates":[-1.58317707385815,55.33326411389137],"type":"Point"}
}