{
  "type": "Feature",
  "properties": {
    "iso:country":"GB",
    "wof:name":"CO15 1EP",
    "wof:placetype":"postalcode"
},
  "geometry": {"coordinates":[1.15007410289665,51.79005249382116],"type":"Point"}
}