{
  "type": "Feature",
  "properties": {
    "date:inception_lower":"2009-03-01",
    "date:inception_upper":"2009-03-31",
    "iso:country":"GB",
    "wof:name":"S75 3TX",
    "wof:placetype":"postalcode"
},
  "geometry": {"coordinates":[-1.517856,53.549284],"type":"Point"}
}