{
  "type": "Feature",
  "properties": {
    "iso:country":"GB",
    "wof:name":"S75 3TX",
    "wof:placetype":"postalcode"
},
  "geometry": {"coordinates":[-1.51785630603244,53.54928372725124],"type":"Point"}
}