{
  "type": "Feature",
  "properties": {
    "date:inception_lower": "1980-01-01",
    "date:inception_upper": "1980-01-01",
    "iso:country": "GB",
    "wof:name": "IP27 9BD",
    "wof:placetype": "postalcode"
  },
  "geometry": {"coordinates":[0.527428,52.380312],"type":"Point"}
}
