{
  "type": "Feature",
  "properties": {
    "iso:country":"GB",
    "wof:name":"G81 3DD",
    "wof:placetype":"postalcode"
},
  "geometry": {"coordinates":[-4.40806787871678,55.91137656854456],"type":"Point"}
}