{
  "type": "Feature",
  "properties": {
    "iso:country": "GB",
    "wof:name": "M34 2BL",
    "wof:placetype": "postalcode"
  },
  "geometry": {"coordinates":[-2.119886,53.45276],"type":"Point"}
}
