{
  "type": "Feature",
  "properties": {
    "iso:country":"GB",
    "wof:name":"M34 2BL",
    "wof:placetype":"postalcode"
},
  "geometry": {"coordinates":[-2.11988619921585,53.45275975408642],"type":"Point"}
}