{
  "type": "Feature",
  "properties": {
    "date:inception_lower":"1980-01-01",
    "date:inception_upper":"1980-01-31",
    "iso:country":"GB",
    "wof:name":"CW6 9TU",
    "wof:placetype":"postalcode"
},
  "geometry": {"coordinates":[-2.680788,53.125624],"type":"Point"}
}