{
  "type": "Feature",
  "properties": {
    "iso:country":"GB",
    "wof:name":"CW6 9TU",
    "wof:placetype":"postalcode"
},
  "geometry": {"coordinates":[-2.68078841965794,53.12562448119362],"type":"Point"}
}