{
  "type": "Feature",
  "properties": {
    "iso:country": "GB",
    "wof:name": "CW6 9TU",
    "wof:placetype": "postalcode"
  },
  "geometry": {"coordinates":[-2.680788,53.125624],"type":"Point"}
}
