{
  "type": "Feature",
  "properties": {
    "iso:country": "GB",
    "wof:name": "WR12 7FJ",
    "wof:placetype": "postalcode"
  },
  "geometry": {"coordinates":[-1.84288,52.053415],"type":"Point"}
}
