{
  "type": "Feature",
  "properties": {
    "date:inception_lower": "2003-01-01",
    "date:inception_upper": "2003-01-01",
    "iso:country": "GB",
    "wof:name": "SG14 2WT",
    "wof:placetype": "postalcode"
  },
  "geometry": {"coordinates":[-0.101987,51.810881],"type":"Point"}
}
