{
  "type": "Feature",
  "properties": {
    "iso:country":"GB",
    "wof:name":"BS20 0DF",
    "wof:placetype":"postalcode"
},
  "geometry": {"coordinates":[-2.69183269297668,51.48242250406256],"type":"Point"}
}