{
  "type": "Feature",
  "properties": {
    "iso:country":"GB",
    "wof:name":"EH5 1NA",
    "wof:placetype":"postalcode"
},
  "geometry": {"coordinates":[-3.22951426791988,55.9781430422991],"type":"Point"}
}