{
  "type": "Feature",
  "properties": {
    "iso:country":"GB",
    "wof:name":"SN3 1BL",
    "wof:placetype":"postalcode"
},
  "geometry": {"coordinates":[-1.77129816657645,51.55734260142072],"type":"Point"}
}