{
  "type": "Feature",
  "properties": {
    "iso:country": "GB",
    "wof:name": "CV32 5JA",
    "wof:placetype": "postalcode"
  },
  "geometry": {"coordinates":[-1.544529,52.289529],"type":"Point"}
}
