{
  "type": "Feature",
  "properties": {
    "iso:country":"GB",
    "wof:name":"CV11 4EF",
    "wof:placetype":"postalcode"
},
  "geometry": {"coordinates":[-1.46839815684137,52.5228832135134],"type":"Point"}
}