{
  "type": "Feature",
  "properties": {
    "iso:country": "GB",
    "wof:name": "WA15 9DB",
    "wof:placetype": "postalcode"
  },
  "geometry": {"coordinates":[-2.333829,53.37702],"type":"Point"}
}
