{
  "type": "Feature",
  "properties": {
    "iso:country":"GB",
    "wof:name":"WA15 9DB",
    "wof:placetype":"postalcode"
},
  "geometry": {"coordinates":[-2.333829418651,53.37701979255813],"type":"Point"}
}