{
  "type": "Feature",
  "properties": {
    "iso:country": "GB",
    "wof:name": "BA2 8HQ",
    "wof:placetype": "postalcode"
  },
  "geometry": {"coordinates":[-2.426536,51.314968],"type":"Point"}
}
