{
  "type": "Feature",
  "properties": {
    "iso:country":"GB",
    "wof:name":"BA2 8HQ",
    "wof:placetype":"postalcode"
},
  "geometry": {"coordinates":[-2.42653567858463,51.31496824725919],"type":"Point"}
}