{
  "type": "Feature",
  "properties": {
    "iso:country": "GB",
    "wof:name": "IP17 1SR",
    "wof:placetype": "postalcode"
  },
  "geometry": {"coordinates":[1.496295,52.16376],"type":"Point"}
}
