{
  "type": "Feature",
  "properties": {
    "iso:country":"GB",
    "wof:name":"IP17 1SR",
    "wof:placetype":"postalcode"
},
  "geometry": {"coordinates":[1.49626386697338,52.16374091047164],"type":"Point"}
}