{
  "type": "Feature",
  "properties": {
    "iso:country": "GB",
    "wof:name": "AB38 9QJ",
    "wof:placetype": "postalcode"
  },
  "geometry": {"coordinates":[-3.220074,57.472896],"type":"Point"}
}
