{
  "type": "Feature",
  "properties": {
    "date:inception_lower": "1993-08-01",
    "date:inception_upper": "1993-08-01",
    "iso:country": "GB",
    "wof:name": "KA26 0TT",
    "wof:placetype": "postalcode"
  },
  "geometry": {"coordinates":[-4.785958,55.209637],"type":"Point"}
}
