{
  "type": "Feature",
  "properties": {
    "iso:country": "GB",
    "wof:name": "KA26 0TT",
    "wof:placetype": "postalcode"
  },
  "geometry": {"coordinates":[-4.785958,55.209637],"type":"Point"}
}
