{
  "type": "Feature",
  "properties": {
    "iso:country": "GB",
    "wof:name": "BS40 7AN",
    "wof:placetype": "postalcode"
  },
  "geometry": {"coordinates":[-2.742832,51.329304],"type":"Point"}
}
