{
  "type": "Feature",
  "properties": {
    "iso:country":"GB",
    "wof:name":"BS40 7AN",
    "wof:placetype":"postalcode"
},
  "geometry": {"coordinates":[-2.74283158126538,51.32930420445383],"type":"Point"}
}