{
  "type": "Feature",
  "properties": {
    "iso:country":"GB",
    "wof:name":"SO31 4GB",
    "wof:placetype":"postalcode"
},
  "geometry": {"coordinates":[-1.31492905405237,50.85730680474631],"type":"Point"}
}