{
  "type": "Feature",
  "properties": {
    "iso:country": "GB",
    "wof:name": "CB21 5AJ",
    "wof:placetype": "postalcode"
  },
  "geometry": {"coordinates":[0.213666,52.183906],"type":"Point"}
}
