{
  "type": "Feature",
  "properties": {
    "iso:country":"GB",
    "wof:name":"MK3 5GA",
    "wof:placetype":"postalcode"
},
  "geometry": {"coordinates":[-0.73937403224972,51.97165559283999],"type":"Point"}
}