{
  "type": "Feature",
  "properties": {
    "date:inception_lower":"2012-09-01",
    "date:inception_upper":"2012-09-30",
    "iso:country":"GB",
    "wof:name":"MK3 5GA",
    "wof:placetype":"postalcode"
},
  "geometry": {"coordinates":[-0.739252,51.97161],"type":"Point"}
}