{
  "type": "Feature",
  "properties": {
    "iso:country":"GB",
    "wof:name":"CH66 4LS",
    "wof:placetype":"postalcode"
},
  "geometry": {"coordinates":[-2.94108510177537,53.27312575306133],"type":"Point"}
}