{
  "type": "Feature",
  "properties": {
    "date:inception_lower":"1992-08-01",
    "date:inception_upper":"1992-08-31",
    "iso:country":"GB",
    "wof:name":"DA1 2EN",
    "wof:placetype":"postalcode"
},
  "geometry": {"coordinates":[0.210782,51.445811],"type":"Point"}
}