{
  "type": "Feature",
  "properties": {
    "date:inception_lower": "1980-01-01",
    "date:inception_upper": "1980-01-01",
    "iso:country": "GB",
    "wof:name": "S71 3PD",
    "wof:placetype": "postalcode"
  },
  "geometry": {"coordinates":[-1.482292,53.586895],"type":"Point"}
}
