{
  "type": "Feature",
  "properties": {
    "iso:country":"GB",
    "wof:name":"S71 3PD",
    "wof:placetype":"postalcode"
},
  "geometry": {"coordinates":[-1.48229156275775,53.586895460593],"type":"Point"}
}