{
  "type": "Feature",
  "properties": {
    "iso:country": "GB",
    "wof:name": "GL54 4EX",
    "wof:placetype": "postalcode"
  },
  "geometry": {"coordinates":[-1.994953,51.902769],"type":"Point"}
}
