{
  "type": "Feature",
  "properties": {
    "iso:country":"GB",
    "wof:name":"GL54 4EX",
    "wof:placetype":"postalcode"
},
  "geometry": {"coordinates":[-1.99495346209069,51.90276947235931],"type":"Point"}
}