{
  "type": "Feature",
  "properties": {
    "date:inception_lower":"1985-04-01",
    "date:inception_upper":"1985-04-30",
    "iso:country":"GB",
    "wof:name":"ME4 4TE",
    "wof:placetype":"postalcode"
},
  "geometry": {"coordinates":[0.52749,51.393443],"type":"Point"}
}