{
  "type": "Feature",
  "properties": {
    "iso:country": "GB",
    "wof:name": "ME4 4TE",
    "wof:placetype": "postalcode"
  },
  "geometry": {"coordinates":[0.52749,51.393443],"type":"Point"}
}
