{
  "type": "Feature",
  "properties": {
    "iso:country":"GB",
    "wof:name":"ME4 4TE",
    "wof:placetype":"postalcode"
},
  "geometry": {"coordinates":[0.52749010812195,51.39344280770661],"type":"Point"}
}