{
  "type": "Feature",
  "properties": {
    "date:inception_lower": "1998-12-01",
    "date:inception_upper": "1998-12-01",
    "iso:country": "GB",
    "wof:name": "CB1 9HX",
    "wof:placetype": "postalcode"
  },
  "geometry": {"coordinates":[0.173057,52.186622],"type":"Point"}
}
