{
  "type": "Feature",
  "properties": {
    "iso:country":"GB",
    "wof:name":"TS21 1LH",
    "wof:placetype":"postalcode"
},
  "geometry": {"coordinates":[-1.41251709161486,54.59801758481143],"type":"Point"}
}