{
  "type": "Feature",
  "properties": {
    "iso:country":"GB",
    "wof:name":"DY3 3DN",
    "wof:placetype":"postalcode"
},
  "geometry": {"coordinates":[-2.14348483096907,52.52908579064862],"type":"Point"}
}