{
  "type": "Feature",
  "properties": {
    "iso:country":"GB",
    "wof:name":"SK14 6JH",
    "wof:placetype":"postalcode"
},
  "geometry": {"coordinates":[-2.01104537445441,53.45727791184952],"type":"Point"}
}