{
  "type": "Feature",
  "properties": {
    "iso:country": "GB",
    "wof:name": "PL12 6RB",
    "wof:placetype": "postalcode"
  },
  "geometry": {"coordinates":[-4.279097,50.434397],"type":"Point"}
}
