{
  "type": "Feature",
  "properties": {
    "iso:country":"GB",
    "wof:name":"SE2 0AS",
    "wof:placetype":"postalcode"
},
  "geometry": {"coordinates":[0.11687338667756,51.47805786345265],"type":"Point"}
}