{
  "type": "Feature",
  "properties": {
    "date:inception_lower": "1990-02-01",
    "date:inception_upper": "1990-02-01",
    "iso:country": "GB",
    "wof:name": "SE2 0AS",
    "wof:placetype": "postalcode"
  },
  "geometry": {"coordinates":[0.116405,51.4776],"type":"Point"}
}
