{
  "type": "Feature",
  "properties": {
    "iso:country":"GB",
    "wof:name":"CW7 2HX",
    "wof:placetype":"postalcode"
},
  "geometry": {"coordinates":[-2.5447478485075,53.19489324833754],"type":"Point"}
}