{
  "type": "Feature",
  "properties": {
    "iso:country":"GB",
    "wof:name":"S70 4SB",
    "wof:placetype":"postalcode"
},
  "geometry": {"coordinates":[-1.4590976772175,53.53170280204274],"type":"Point"}
}