{
  "type": "Feature",
  "properties": {
    "iso:country":"GB",
    "wof:name":"DL3 6SH",
    "wof:placetype":"postalcode"
},
  "geometry": {"coordinates":[-1.55516668060136,54.52660450148417],"type":"Point"}
}