{
  "type": "Feature",
  "properties": {
    "date:inception_lower": "1980-01-01",
    "date:inception_upper": "1980-01-01",
    "iso:country": "GB",
    "wof:name": "L35 4NP",
    "wof:placetype": "postalcode"
  },
  "geometry": {"coordinates":[-2.759291,53.41588],"type":"Point"}
}
