{
  "type": "Feature",
  "properties": {
    "iso:country":"GB",
    "wof:name":"L35 4NP",
    "wof:placetype":"postalcode"
},
  "geometry": {"coordinates":[-2.75929137222737,53.41588006844341],"type":"Point"}
}