{
  "type": "Feature",
  "properties": {
    "iso:country":"GB",
    "wof:name":"NR1 2PS",
    "wof:placetype":"postalcode"
},
  "geometry": {"coordinates":[1.29548937984503,52.61621681147423],"type":"Point"}
}