{
  "type": "Feature",
  "properties": {
    "iso:country":"GB",
    "wof:name":"WA4 5AQ",
    "wof:placetype":"postalcode"
},
  "geometry": {"coordinates":[-2.58380341039266,53.36238665838466],"type":"Point"}
}