{
  "type": "Feature",
  "properties": {
    "date:inception_lower": "2006-01-01",
    "date:inception_upper": "2006-01-01",
    "iso:country": "GB",
    "wof:name": "RM19 1SW",
    "wof:placetype": "postalcode"
  },
  "geometry": {"coordinates":[0.250064,51.479327],"type":"Point"}
}
