{
  "type": "Feature",
  "properties": {
    "iso:country":"GB",
    "wof:name":"RM19 1SW",
    "wof:placetype":"postalcode"
},
  "geometry": {"coordinates":[0.25006406231958,51.47932733436068],"type":"Point"}
}