{
  "type": "Feature",
  "properties": {
    "iso:country": "GB",
    "wof:name": "CW12 3ES",
    "wof:placetype": "postalcode"
  },
  "geometry": {"coordinates":[-2.198458,53.161169],"type":"Point"}
}
