{
  "type": "Feature",
  "properties": {
    "iso:country":"GB",
    "wof:name":"RM9 4AU",
    "wof:placetype":"postalcode"
},
  "geometry": {"coordinates":[0.11454461706682,51.5403931814704],"type":"Point"}
}