{
  "type": "Feature",
  "properties": {
    "iso:country":"GB",
    "wof:name":"BB5 5NE",
    "wof:placetype":"postalcode"
},
  "geometry": {"coordinates":[-2.38761632747881,53.77669491273581],"type":"Point"}
}