{
  "type": "Feature",
  "properties": {
    "iso:country": "GB",
    "wof:name": "BB5 5NE",
    "wof:placetype": "postalcode"
  },
  "geometry": {"coordinates":[-2.387616,53.776709],"type":"Point"}
}
