{
  "type": "Feature",
  "properties": {
    "date:inception_lower": "1980-01-01",
    "date:inception_upper": "1980-01-01",
    "iso:country": "GB",
    "wof:name": "CH5 4EF",
    "wof:placetype": "postalcode"
  },
  "geometry": {"coordinates":[-3.052361,53.21788],"type":"Point"}
}
