{
  "type": "Feature",
  "properties": {
    "iso:country":"GB",
    "wof:name":"BS20 7GY",
    "wof:placetype":"postalcode"
},
  "geometry": {"coordinates":[-2.75616517127027,51.48526220709218],"type":"Point"}
}