{
  "type": "Feature",
  "properties": {
    "date:inception_lower":"1980-01-01",
    "date:inception_upper":"1980-01-31",
    "iso:country":"GB",
    "wof:name":"PE37 8DA",
    "wof:placetype":"postalcode"
},
  "geometry": {"coordinates":[0.70379,52.630329],"type":"Point"}
}