{
  "type": "Feature",
  "properties": {
    "iso:country":"GB",
    "wof:name":"CR0 7LP",
    "wof:placetype":"postalcode"
},
  "geometry": {"coordinates":[-0.06090566617943,51.37690728635957],"type":"Point"}
}