{
  "type": "Feature",
  "properties": {
    "date:inception_lower": "2016-11-01",
    "date:inception_upper": "2016-11-01",
    "iso:country": "GB",
    "wof:name": "AB42 3FZ",
    "wof:placetype": "postalcode"
  },
  "geometry": {"coordinates":[-1.82244,57.503308],"type":"Point"}
}
