{
  "type": "Feature",
  "properties": {
    "iso:country":"GB",
    "wof:name":"LA1 1EE",
    "wof:placetype":"postalcode"
},
  "geometry": {"coordinates":[-2.80208712513739,54.05061583478322],"type":"Point"}
}