{
  "type": "Feature",
  "properties": {
    "iso:country": "GB",
    "wof:name": "CA11 7XP",
    "wof:placetype": "postalcode"
  },
  "geometry": {"coordinates":[-2.749697,54.663182],"type":"Point"}
}
