{
  "type": "Feature",
  "properties": {
    "iso:country": "GB",
    "wof:name": "PE30 4BN",
    "wof:placetype": "postalcode"
  },
  "geometry": {"coordinates":[0.421915,52.759593],"type":"Point"}
}
