{
  "type": "Feature",
  "properties": {
    "iso:country":"GB",
    "wof:name":"DD11 1ES",
    "wof:placetype":"postalcode"
},
  "geometry": {"coordinates":[-2.57853534416217,56.56065430504151],"type":"Point"}
}