{
  "type": "Feature",
  "properties": {
    "date:inception_lower": "2005-11-01",
    "date:inception_upper": "2005-11-01",
    "iso:country": "GB",
    "wof:name": "S12 2NQ",
    "wof:placetype": "postalcode"
  },
  "geometry": {"coordinates":[-1.425581,53.34693],"type":"Point"}
}
