{
  "type": "Feature",
  "properties": {
    "iso:country": "GB",
    "wof:name": "S12 2NQ",
    "wof:placetype": "postalcode"
  },
  "geometry": {"coordinates":[-1.425642,53.34692],"type":"Point"}
}
