{
  "type": "Feature",
  "properties": {
    "iso:country":"GB",
    "wof:name":"BS3 4LT",
    "wof:placetype":"postalcode"
},
  "geometry": {"coordinates":[-2.59302270646584,51.43977718455375],"type":"Point"}
}