{
  "type": "Feature",
  "properties": {
    "date:inception_lower": "1980-01-01",
    "date:inception_upper": "1980-01-01",
    "iso:country": "GB",
    "wof:name": "CA1 3RN",
    "wof:placetype": "postalcode"
  },
  "geometry": {"coordinates":[-2.891925,54.884391],"type":"Point"}
}
