{
  "type": "Feature",
  "properties": {
    "iso:country":"GB",
    "wof:name":"CA1 3RN",
    "wof:placetype":"postalcode"
},
  "geometry": {"coordinates":[-2.8919254836656,54.88439107660455],"type":"Point"}
}