{
  "type": "Feature",
  "properties": {
    "date:inception_lower":"1982-03-01",
    "date:inception_upper":"1982-03-31",
    "iso:country":"GB",
    "wof:name":"LE3 8QH",
    "wof:placetype":"postalcode"
},
  "geometry": {"coordinates":[-1.210376,52.646486],"type":"Point"}
}