{
  "type": "Feature",
  "properties": {
    "iso:country":"GB",
    "wof:name":"LE3 8QH",
    "wof:placetype":"postalcode"
},
  "geometry": {"coordinates":[-1.21037598435954,52.64648585433913],"type":"Point"}
}