{
  "type": "Feature",
  "properties": {
    "iso:country":"GB",
    "wof:name":"B98 7UX",
    "wof:placetype":"postalcode"
},
  "geometry": {"coordinates":[-1.9135096627091,52.28461170096897],"type":"Point"}
}