{
  "type": "Feature",
  "properties": {
    "iso:country":"GB",
    "wof:name":"RG40 3SE",
    "wof:placetype":"postalcode"
},
  "geometry": {"coordinates":[-0.85572670839623,51.36346366008343],"type":"Point"}
}