{
  "type": "Feature",
  "properties": {
    "iso:country": "GB",
    "wof:name": "TA7 0NT",
    "wof:placetype": "postalcode"
  },
  "geometry": {"coordinates":[-2.89126,51.09307],"type":"Point"}
}
