{
  "type": "Feature",
  "properties": {
    "date:inception_lower": "1980-01-01",
    "date:inception_upper": "1980-01-01",
    "iso:country": "GB",
    "wof:name": "DY8 5PT",
    "wof:placetype": "postalcode"
  },
  "geometry": {"coordinates":[-2.172072,52.485294],"type":"Point"}
}
