{
  "type": "Feature",
  "properties": {
    "iso:country":"GB",
    "wof:name":"CT10 2EL",
    "wof:placetype":"postalcode"
},
  "geometry": {"coordinates":[1.43110805984495,51.3501665050354],"type":"Point"}
}