{
  "type": "Feature",
  "properties": {
    "date:inception_lower": "2003-11-01",
    "date:inception_upper": "2003-11-01",
    "iso:country": "GB",
    "wof:name": "CT10 2EL",
    "wof:placetype": "postalcode"
  },
  "geometry": {"coordinates":[1.431108,51.350166],"type":"Point"}
}
