{
  "type": "Feature",
  "properties": {
    "iso:country":"GB",
    "wof:name":"OL12 9TH",
    "wof:placetype":"postalcode"
},
  "geometry": {"coordinates":[-2.15373432221695,53.63898640717482],"type":"Point"}
}