{
  "type": "Feature",
  "properties": {
    "iso:country": "GB",
    "wof:name": "BH20 4PS",
    "wof:placetype": "postalcode"
  },
  "geometry": {"coordinates":[-2.115408,50.683849],"type":"Point"}
}
