{
  "type": "Feature",
  "properties": {
    "iso:country":"GB",
    "wof:name":"SL4 5LA",
    "wof:placetype":"postalcode"
},
  "geometry": {"coordinates":[-0.63490739039538,51.48129726049063],"type":"Point"}
}