{
  "type": "Feature",
  "properties": {
    "iso:country":"GB",
    "wof:name":"LE4 9HR",
    "wof:placetype":"postalcode"
},
  "geometry": {"coordinates":[-1.0803944986186,52.66282746198721],"type":"Point"}
}