{
  "type": "Feature",
  "properties": {
    "iso:country": "GB",
    "wof:name": "BR2 0TT",
    "wof:placetype": "postalcode"
  },
  "geometry": {"coordinates":[0.007054,51.393497],"type":"Point"}
}
