{
  "type": "Feature",
  "properties": {
    "iso:country":"GB",
    "wof:name":"BR2 0TT",
    "wof:placetype":"postalcode"
},
  "geometry": {"coordinates":[0.00705428807666,51.39349662098044],"type":"Point"}
}