{
  "type": "Feature",
  "properties": {
    "iso:country": "GB",
    "wof:name": "SK10 2UT",
    "wof:placetype": "postalcode"
  },
  "geometry": {"coordinates":[-2.138505,53.274486],"type":"Point"}
}
