{
  "type": "Feature",
  "properties": {
    "iso:country":"GB",
    "wof:name":"B11 4DX",
    "wof:placetype":"postalcode"
},
  "geometry": {"coordinates":[-1.86063724292757,52.44715692199814],"type":"Point"}
}