{
  "type": "Feature",
  "properties": {
    "iso:country":"GB",
    "wof:name":"WV11 2FE",
    "wof:placetype":"postalcode"
},
  "geometry": {"coordinates":[-2.07221272374315,52.64436411761211],"type":"Point"}
}