{
  "type": "Feature",
  "properties": {
    "iso:country": "GB",
    "wof:name": "WV11 2FE",
    "wof:placetype": "postalcode"
  },
  "geometry": {"coordinates":[-2.072213,52.644364],"type":"Point"}
}
