{
  "type": "Feature",
  "properties": {
    "date:inception_lower": "2012-02-01",
    "date:inception_upper": "2012-02-01",
    "iso:country": "GB",
    "wof:name": "WV11 2FE",
    "wof:placetype": "postalcode"
  },
  "geometry": {"coordinates":[-2.072213,52.644364],"type":"Point"}
}
