{
  "type": "Feature",
  "properties": {
    "iso:country":"GB",
    "wof:name":"S81 9DL",
    "wof:placetype":"postalcode"
},
  "geometry": {"coordinates":[-1.11556876607832,53.35425762602507],"type":"Point"}
}