{
  "type": "Feature",
  "properties": {
    "date:inception_lower": "1980-01-01",
    "date:inception_upper": "1980-01-01",
    "iso:country": "GB",
    "wof:name": "WR4 9RT",
    "wof:placetype": "postalcode"
  },
  "geometry": {"coordinates":[-2.201761,52.202272],"type":"Point"}
}
