{
  "type": "Feature",
  "properties": {
    "date:inception_lower": "1990-08-01",
    "date:inception_upper": "1990-08-01",
    "iso:country": "GB",
    "wof:name": "AB54 6DP",
    "wof:placetype": "postalcode"
  },
  "geometry": {"coordinates":[-2.63657,57.493983],"type":"Point"}
}
