{
  "type": "Feature",
  "properties": {
    "iso:country": "GB",
    "wof:name": "AB54 6DP",
    "wof:placetype": "postalcode"
  },
  "geometry": {"coordinates":[-2.634676,57.495571],"type":"Point"}
}
