{
  "type": "Feature",
  "properties": {
    "iso:country":"GB",
    "wof:name":"PR6 9AN",
    "wof:placetype":"postalcode"
},
  "geometry": {"coordinates":[-2.61143646143055,53.65238945316516],"type":"Point"}
}