{
  "type": "Feature",
  "properties": {
    "iso:country":"GB",
    "wof:name":"TA7 0AQ",
    "wof:placetype":"postalcode"
},
  "geometry": {"coordinates":[-2.98205763730223,51.11023713660482],"type":"Point"}
}