{
  "type": "Feature",
  "properties": {
    "date:inception_lower":"1980-01-01",
    "date:inception_upper":"1980-01-31",
    "iso:country":"GB",
    "wof:name":"TA7 0AQ",
    "wof:placetype":"postalcode"
},
  "geometry": {"coordinates":[-2.982064,51.110231],"type":"Point"}
}