{
  "type": "Feature",
  "properties": {
    "iso:country":"GB",
    "wof:name":"UB5 4RU",
    "wof:placetype":"postalcode"
},
  "geometry": {"coordinates":[-0.35050578606833,51.55120774286806],"type":"Point"}
}