{
  "type": "Feature",
  "properties": {
    "iso:country":"GB",
    "wof:name":"WA3 3BH",
    "wof:placetype":"postalcode"
},
  "geometry": {"coordinates":[-2.59773170378181,53.47596143779701],"type":"Point"}
}