{
  "type": "Feature",
  "properties": {
    "iso:country":"GB",
    "wof:name":"L19 4UH",
    "wof:placetype":"postalcode"
},
  "geometry": {"coordinates":[-2.89745288130323,53.36637244958597],"type":"Point"}
}