{
  "type": "Feature",
  "properties": {
    "iso:country": "GB",
    "wof:name": "M26 4LT",
    "wof:placetype": "postalcode"
  },
  "geometry": {"coordinates":[-2.332483,53.582192],"type":"Point"}
}
