{
  "type": "Feature",
  "properties": {
    "iso:country": "GB",
    "wof:name": "FK8 1ZS",
    "wof:placetype": "postalcode"
  },
  "geometry": {"coordinates":[-3.960361,56.135765],"type":"Point"}
}
