{
  "type": "Feature",
  "properties": {
    "iso:country":"GB",
    "wof:name":"S6 3FA",
    "wof:placetype":"postalcode"
},
  "geometry": {"coordinates":[-1.48611165276211,53.3886878902682],"type":"Point"}
}