{
  "type": "Feature",
  "properties": {
    "iso:country":"GB",
    "wof:name":"SK16 4JY",
    "wof:placetype":"postalcode"
},
  "geometry": {"coordinates":[-2.0926187445195,53.48187071346251],"type":"Point"}
}