{
  "type": "Feature",
  "properties": {
    "iso:country":"GB",
    "wof:name":"DT2 7TL",
    "wof:placetype":"postalcode"
},
  "geometry": {"coordinates":[-2.44253207745137,50.79415207349696],"type":"Point"}
}