{
  "type": "Feature",
  "properties": {
    "iso:country": "GB",
    "wof:name": "DT2 7TL",
    "wof:placetype": "postalcode"
  },
  "geometry": {"coordinates":[-2.442532,50.794152],"type":"Point"}
}
