{
  "type": "Feature",
  "properties": {
    "iso:country":"GB",
    "wof:name":"BA12 8NJ",
    "wof:placetype":"postalcode"
},
  "geometry": {"coordinates":[-2.19482284604168,51.20226814118165],"type":"Point"}
}