{
  "type": "Feature",
  "properties": {
    "iso:country":"GB",
    "wof:name":"NP23 4UU",
    "wof:placetype":"postalcode"
},
  "geometry": {"coordinates":[-3.16426347850503,51.78161269925522],"type":"Point"}
}