{
  "type": "Feature",
  "properties": {
    "date:inception_lower":"1999-06-01",
    "date:inception_upper":"1999-06-30",
    "iso:country":"GB",
    "wof:name":"NP23 4UU",
    "wof:placetype":"postalcode"
},
  "geometry": {"coordinates":[-3.164263,51.781613],"type":"Point"}
}