{
  "type": "Feature",
  "properties": {
    "iso:country": "GB",
    "wof:name": "NP23 4UU",
    "wof:placetype": "postalcode"
  },
  "geometry": {"coordinates":[-3.164263,51.781613],"type":"Point"}
}
