{
  "type": "Feature",
  "properties": {
    "iso:country": "GB",
    "wof:name": "PR4 9BY",
    "wof:placetype": "postalcode"
  },
  "geometry": {"coordinates":[-2.872573,53.777522],"type":"Point"}
}
