{
  "type": "Feature",
  "properties": {
    "iso:country":"GB",
    "wof:name":"SP2 8HD",
    "wof:placetype":"postalcode"
},
  "geometry": {"coordinates":[-1.81070607278762,51.06131881790289],"type":"Point"}
}