{
  "type": "Feature",
  "properties": {
    "iso:country":"GB",
    "wof:name":"BN43 5HE",
    "wof:placetype":"postalcode"
},
  "geometry": {"coordinates":[-0.2576544559409,50.82849669384286],"type":"Point"}
}