{
  "type": "Feature",
  "properties": {
    "iso:country":"GB",
    "wof:name":"HP5 1BW",
    "wof:placetype":"postalcode"
},
  "geometry": {"coordinates":[-0.61231734964183,51.70521867550298],"type":"Point"}
}