{
  "type": "Feature",
  "properties": {
    "iso:country":"GB",
    "wof:name":"LL65 3BZ",
    "wof:placetype":"postalcode"
},
  "geometry": {"coordinates":[-4.38052008884705,53.27824219751422],"type":"Point"}
}