{
  "type": "Feature",
  "properties": {
    "date:inception_lower": "1980-01-01",
    "date:inception_upper": "1980-01-01",
    "iso:country": "GB",
    "wof:name": "LL65 3BZ",
    "wof:placetype": "postalcode"
  },
  "geometry": {"coordinates":[-4.380437,53.278279],"type":"Point"}
}
