{
  "type": "Feature",
  "properties": {
    "date:inception_lower": "1980-01-01",
    "date:inception_upper": "1980-01-01",
    "iso:country": "GB",
    "wof:name": "LL65 3BZ",
    "wof:placetype": "postalcode"
  },
  "geometry": {"coordinates":[-4.38052,53.278242],"type":"Point"}
}
