{
  "type": "Feature",
  "properties": {
    "iso:country": "GB",
    "wof:name": "LL65 3BZ",
    "wof:placetype": "postalcode"
  },
  "geometry": {"coordinates":[-4.38052,53.278242],"type":"Point"}
}
