{
  "type": "Feature",
  "properties": {
    "date:inception_lower": "1980-01-01",
    "date:inception_upper": "1980-01-01",
    "iso:country": "GB",
    "wof:name": "GU8 6LL",
    "wof:placetype": "postalcode"
  },
  "geometry": {"coordinates":[-0.722685,51.167384],"type":"Point"}
}
