{
  "type": "Feature",
  "properties": {
    "iso:country":"GB",
    "wof:name":"GU8 6LL",
    "wof:placetype":"postalcode"
},
  "geometry": {"coordinates":[-0.72136060032912,51.16632088243176],"type":"Point"}
}