{
  "type": "Feature",
  "properties": {
    "iso:country": "GB",
    "wof:name": "GU8 6LL",
    "wof:placetype": "postalcode"
  },
  "geometry": {"coordinates":[-0.722685,51.167384],"type":"Point"}
}
