{
  "type": "Feature",
  "properties": {
    "iso:country": "GB",
    "wof:name": "SY21 8QH",
    "wof:placetype": "postalcode"
  },
  "geometry": {"coordinates":[-3.239745,52.578742],"type":"Point"}
}
