{
  "type": "Feature",
  "properties": {
    "iso:country":"GB",
    "wof:name":"ME12 2LF",
    "wof:placetype":"postalcode"
},
  "geometry": {"coordinates":[0.8037629312543,51.4283385213322],"type":"Point"}
}