{
  "type": "Feature",
  "properties": {
    "iso:country": "GB",
    "wof:name": "ME12 2LF",
    "wof:placetype": "postalcode"
  },
  "geometry": {"coordinates":[0.803888,51.428268],"type":"Point"}
}
