{
  "type": "Feature",
  "properties": {
    "iso:country":"GB",
    "wof:name":"DY12 1JU",
    "wof:placetype":"postalcode"
},
  "geometry": {"coordinates":[-2.30437121048158,52.38098500048042],"type":"Point"}
}