{
  "type": "Feature",
  "properties": {
    "iso:country": "GB",
    "wof:name": "EH6 4EQ",
    "wof:placetype": "postalcode"
  },
  "geometry": {"coordinates":[-3.184824,55.977236],"type":"Point"}
}
