{
  "type": "Feature",
  "properties": {
    "iso:country": "GB",
    "wof:name": "BN14 8FE",
    "wof:placetype": "postalcode"
  },
  "geometry": {"coordinates":[-0.368493,50.819741],"type":"Point"}
}
