{
  "type": "Feature",
  "properties": {
    "iso:country": "GB",
    "wof:name": "ML6 7TZ",
    "wof:placetype": "postalcode"
  },
  "geometry": {"coordinates":[-3.954478,55.910337],"type":"Point"}
}
