{
  "type": "Feature",
  "properties": {
    "iso:country": "GB",
    "wof:name": "SR7 8DG",
    "wof:placetype": "postalcode"
  },
  "geometry": {"coordinates":[-1.369421,54.837469],"type":"Point"}
}
