{
  "type": "Feature",
  "properties": {
    "iso:country":"GB",
    "wof:name":"SR7 8DG",
    "wof:placetype":"postalcode"
},
  "geometry": {"coordinates":[-1.369421418597,54.83746865111533],"type":"Point"}
}