{
  "type": "Feature",
  "properties": {
    "date:inception_lower": "2000-12-01",
    "date:inception_upper": "2000-12-01",
    "iso:country": "GB",
    "wof:name": "ME19 4UY",
    "wof:placetype": "postalcode"
  },
  "geometry": {"coordinates":[0.40219,51.27669],"type":"Point"}
}
