{
  "type": "Feature",
  "properties": {
    "iso:country":"GB",
    "wof:name":"ME19 4UY",
    "wof:placetype":"postalcode"
},
  "geometry": {"coordinates":[0.40224570454402,51.27666323612022],"type":"Point"}
}