{
  "type": "Feature",
  "properties": {
    "iso:country":"GB",
    "wof:name":"BS24 7FW",
    "wof:placetype":"postalcode"
},
  "geometry": {"coordinates":[-2.90031710864026,51.35227966559686],"type":"Point"}
}