{
  "type": "Feature",
  "properties": {
    "iso:country": "GB",
    "wof:name": "BS24 7FW",
    "wof:placetype": "postalcode"
  },
  "geometry": {"coordinates":[-2.900317,51.35228],"type":"Point"}
}
