{
  "type": "Feature",
  "properties": {
    "iso:country":"GB",
    "wof:name":"W3 8DG",
    "wof:placetype":"postalcode"
},
  "geometry": {"coordinates":[-0.27385237929829,51.50142055895952],"type":"Point"}
}