{
  "type": "Feature",
  "properties": {
    "date:inception_lower":"1980-01-01",
    "date:inception_upper":"1980-01-31",
    "iso:country":"GB",
    "wof:name":"TF13 6JF",
    "wof:placetype":"postalcode"
},
  "geometry": {"coordinates":[-2.559165,52.600661],"type":"Point"}
}