{
  "type": "Feature",
  "properties": {
    "iso:country":"GB",
    "wof:name":"TF13 6JF",
    "wof:placetype":"postalcode"
},
  "geometry": {"coordinates":[-2.55916542579483,52.60066063018553],"type":"Point"}
}