{
  "type": "Feature",
  "properties": {
    "iso:country": "GB",
    "wof:name": "TF13 6JF",
    "wof:placetype": "postalcode"
  },
  "geometry": {"coordinates":[-2.559165,52.600661],"type":"Point"}
}
