{
  "type": "Feature",
  "properties": {
    "iso:country": "GB",
    "wof:name": "ME15 9BN",
    "wof:placetype": "postalcode"
  },
  "geometry": {"coordinates":[0.549314,51.247002],"type":"Point"}
}
