{
  "type": "Feature",
  "properties": {
    "iso:country":"GB",
    "wof:name":"SP7 8SJ",
    "wof:placetype":"postalcode"
},
  "geometry": {"coordinates":[-2.19280378115609,51.00661269094583],"type":"Point"}
}