{
  "type": "Feature",
  "properties": {
    "date:inception_lower": "1999-06-01",
    "date:inception_upper": "1999-06-01",
    "iso:country": "GB",
    "wof:name": "SP7 8SJ",
    "wof:placetype": "postalcode"
  },
  "geometry": {"coordinates":[-2.192804,51.006613],"type":"Point"}
}
