{
  "type": "Feature",
  "properties": {
    "iso:country":"GB",
    "wof:name":"SE17 3EN",
    "wof:placetype":"postalcode"
},
  "geometry": {"coordinates":[-0.09945718891639,51.48544203020381],"type":"Point"}
}