{
  "type": "Feature",
  "properties": {
    "iso:country": "GB",
    "wof:name": "SE17 3EN",
    "wof:placetype": "postalcode"
  },
  "geometry": {"coordinates":[-0.099457,51.485442],"type":"Point"}
}
