{
  "type": "Feature",
  "properties": {
    "iso:country":"GB",
    "wof:name":"M30 7LW",
    "wof:placetype":"postalcode"
},
  "geometry": {"coordinates":[-2.37514167846166,53.47496236899618],"type":"Point"}
}