{
  "type": "Feature",
  "properties": {
    "date:inception_lower": "1995-07-01",
    "date:inception_upper": "1995-07-01",
    "iso:country": "GB",
    "wof:name": "SP5 3TN",
    "wof:placetype": "postalcode"
  },
  "geometry": {"coordinates":[-1.739349,51.045176],"type":"Point"}
}
