{
  "type": "Feature",
  "properties": {
    "iso:country":"GB",
    "wof:name":"SP5 3TN",
    "wof:placetype":"postalcode"
},
  "geometry": {"coordinates":[-1.73934868615263,51.04517557740985],"type":"Point"}
}