{
  "type": "Feature",
  "properties": {
    "iso:country":"GB",
    "wof:name":"NG34 0DU",
    "wof:placetype":"postalcode"
},
  "geometry": {"coordinates":[-0.42329748790388,52.92215833886608],"type":"Point"}
}