{
  "type": "Feature",
  "properties": {
    "iso:country":"GB",
    "wof:name":"SN6 8PA",
    "wof:placetype":"postalcode"
},
  "geometry": {"coordinates":[-1.66491017639367,51.56246414927409],"type":"Point"}
}