{
  "type": "Feature",
  "properties": {
    "date:inception_lower": "1980-01-01",
    "date:inception_upper": "1980-01-01",
    "iso:country": "GB",
    "wof:name": "SN6 8PA",
    "wof:placetype": "postalcode"
  },
  "geometry": {"coordinates":[-1.66497,51.562402],"type":"Point"}
}
