{
  "type": "Feature",
  "properties": {
    "iso:country": "GB",
    "wof:name": "OL8 3PB",
    "wof:placetype": "postalcode"
  },
  "geometry": {"coordinates":[-2.129717,53.511048],"type":"Point"}
}
