{
  "type": "Feature",
  "properties": {
    "date:inception_lower": "1980-01-01",
    "date:inception_upper": "1980-01-01",
    "iso:country": "GB",
    "wof:name": "GL6 0HH",
    "wof:placetype": "postalcode"
  },
  "geometry": {"coordinates":[-2.218352,51.694014],"type":"Point"}
}
