{
  "type": "Feature",
  "properties": {
    "iso:country":"GB",
    "wof:name":"GL6 0HH",
    "wof:placetype":"postalcode"
},
  "geometry": {"coordinates":[-2.21827055562383,51.69421780089242],"type":"Point"}
}