{
  "type": "Feature",
  "properties": {
    "date:inception_lower": "1980-01-01",
    "date:inception_upper": "1980-01-01",
    "iso:country": "GB",
    "wof:name": "LL18 1LT",
    "wof:placetype": "postalcode"
  },
  "geometry": {"coordinates":[-3.493142,53.317516],"type":"Point"}
}
