{
  "type": "Feature",
  "properties": {
    "iso:country":"GB",
    "wof:name":"LL18 1LT",
    "wof:placetype":"postalcode"
},
  "geometry": {"coordinates":[-3.49314202655011,53.31751625436755],"type":"Point"}
}