{
  "type": "Feature",
  "properties": {
    "iso:country":"GB",
    "wof:name":"GL13 9JR",
    "wof:placetype":"postalcode"
},
  "geometry": {"coordinates":[-2.44237674902891,51.658629212452],"type":"Point"}
}