{
  "type": "Feature",
  "properties": {
    "date:inception_lower":"1980-01-01",
    "date:inception_upper":"1980-01-31",
    "iso:country":"GB",
    "wof:name":"BS21 6QX",
    "wof:placetype":"postalcode"
},
  "geometry": {"coordinates":[-2.822327,51.440971],"type":"Point"}
}