{
  "type": "Feature",
  "properties": {
    "iso:country":"GB",
    "wof:name":"BS21 6QX",
    "wof:placetype":"postalcode"
},
  "geometry": {"coordinates":[-2.82473648925409,51.44079436426991],"type":"Point"}
}