{
  "type": "Feature",
  "properties": {
    "iso:country":"GB",
    "wof:name":"TR13 8TD",
    "wof:placetype":"postalcode"
},
  "geometry": {"coordinates":[-5.27498155323628,50.10233277119649],"type":"Point"}
}