{
  "type": "Feature",
  "properties": {
    "date:inception_lower":"1980-01-01",
    "date:inception_upper":"1980-01-31",
    "iso:country":"GB",
    "wof:name":"DH7 8EN",
    "wof:placetype":"postalcode"
},
  "geometry": {"coordinates":[-1.659688,54.736946],"type":"Point"}
}