{
  "type": "Feature",
  "properties": {
    "iso:country": "GB",
    "wof:name": "DH7 8EN",
    "wof:placetype": "postalcode"
  },
  "geometry": {"coordinates":[-1.659688,54.736946],"type":"Point"}
}
