{
  "type": "Feature",
  "properties": {
    "iso:country": "GB",
    "wof:name": "RG30 3UL",
    "wof:placetype": "postalcode"
  },
  "geometry": {"coordinates":[-1.006139,51.419805],"type":"Point"}
}
