{
  "type": "Feature",
  "properties": {
    "iso:country": "GB",
    "wof:name": "NN5 6RD",
    "wof:placetype": "postalcode"
  },
  "geometry": {"coordinates":[-0.95151,52.251113],"type":"Point"}
}
