{
  "type": "Feature",
  "properties": {
    "iso:country":"GB",
    "wof:name":"NN5 6RD",
    "wof:placetype":"postalcode"
},
  "geometry": {"coordinates":[-0.95151012176206,52.2511129841923],"type":"Point"}
}