{
  "type": "Feature",
  "properties": {
    "iso:country": "GB",
    "wof:name": "SS6 9HW",
    "wof:placetype": "postalcode"
  },
  "geometry": {"coordinates":[0.602074,51.592024],"type":"Point"}
}
