{
  "type": "Feature",
  "properties": {
    "iso:country":"GB",
    "wof:name":"BS48 2TL",
    "wof:placetype":"postalcode"
},
  "geometry": {"coordinates":[-2.74812310025501,51.42945735918941],"type":"Point"}
}