{
  "type": "Feature",
  "properties": {
    "iso:country":"GB",
    "wof:name":"TF2 8QR",
    "wof:placetype":"postalcode"
},
  "geometry": {"coordinates":[-2.4180092481499,52.72238896869584],"type":"Point"}
}