{
  "type": "Feature",
  "properties": {
    "date:inception_lower": "1990-02-01",
    "date:inception_upper": "1990-02-01",
    "iso:country": "GB",
    "wof:name": "TF2 8QR",
    "wof:placetype": "postalcode"
  },
  "geometry": {"coordinates":[-2.418009,52.722389],"type":"Point"}
}
