{
  "type": "Feature",
  "properties": {
    "iso:country": "GB",
    "wof:name": "PO1 4LP",
    "wof:placetype": "postalcode"
  },
  "geometry": {"coordinates":[-1.08089,50.805888],"type":"Point"}
}
