{
  "type": "Feature",
  "properties": {
    "date:inception_lower": "1980-01-01",
    "date:inception_upper": "1980-01-01",
    "iso:country": "GB",
    "wof:name": "L26 1UP",
    "wof:placetype": "postalcode"
  },
  "geometry": {"coordinates":[-2.841186,53.354926],"type":"Point"}
}
