{
  "type": "Feature",
  "properties": {
    "iso:country":"GB",
    "wof:name":"L26 1UP",
    "wof:placetype":"postalcode"
},
  "geometry": {"coordinates":[-2.84118643385611,53.35492600914772],"type":"Point"}
}