{
  "type": "Feature",
  "properties": {
    "iso:country":"GB",
    "wof:name":"HU10 6LJ",
    "wof:placetype":"postalcode"
},
  "geometry": {"coordinates":[-0.43983171164267,53.75404087100394],"type":"Point"}
}