{
  "type": "Feature",
  "properties": {
    "iso:country": "GB",
    "wof:name": "DD5 3SG",
    "wof:placetype": "postalcode"
  },
  "geometry": {"coordinates":[-2.856987,56.480137],"type":"Point"}
}
