{
  "type": "Feature",
  "properties": {
    "iso:country":"GB",
    "wof:name":"DD5 3SG",
    "wof:placetype":"postalcode"
},
  "geometry": {"coordinates":[-2.85698702686641,56.48013710186618],"type":"Point"}
}