{
  "type": "Feature",
  "properties": {
    "iso:country": "GB",
    "wof:name": "TF1 2DX",
    "wof:placetype": "postalcode"
  },
  "geometry": {"coordinates":[-2.519619,52.692321],"type":"Point"}
}
