{
  "type": "Feature",
  "properties": {
    "iso:country":"GB",
    "wof:name":"M24 2AZ",
    "wof:placetype":"postalcode"
},
  "geometry": {"coordinates":[-2.17056290822072,53.5440653316519],"type":"Point"}
}