{
  "type": "Feature",
  "properties": {
    "iso:country": "GB",
    "wof:name": "KT13 9RW",
    "wof:placetype": "postalcode"
  },
  "geometry": {"coordinates":[-0.428673,51.37524],"type":"Point"}
}
