{
  "type": "Feature",
  "properties": {
    "iso:country":"GB",
    "wof:name":"KT13 9RW",
    "wof:placetype":"postalcode"
},
  "geometry": {"coordinates":[-0.42806923856581,51.37500777094954],"type":"Point"}
}