{
  "type": "Feature",
  "properties": {
    "iso:country":"GB",
    "wof:name":"B31 2JT",
    "wof:placetype":"postalcode"
},
  "geometry": {"coordinates":[-1.96935872796082,52.41701032639564],"type":"Point"}
}