{
  "type": "Feature",
  "properties": {
    "iso:country": "GB",
    "wof:name": "SW17 7ND",
    "wof:placetype": "postalcode"
  },
  "geometry": {"coordinates":[-0.16473,51.434909],"type":"Point"}
}
