{
  "type": "Feature",
  "properties": {
    "date:inception_lower": "1980-01-01",
    "date:inception_upper": "1980-01-01",
    "iso:country": "GB",
    "wof:name": "SW17 7ND",
    "wof:placetype": "postalcode"
  },
  "geometry": {"coordinates":[-0.16473,51.434909],"type":"Point"}
}
