{
  "type": "Feature",
  "properties": {
    "iso:country":"GB",
    "wof:name":"IP2 9JF",
    "wof:placetype":"postalcode"
},
  "geometry": {"coordinates":[1.12088579581318,52.03685370650812],"type":"Point"}
}