{
  "type": "Feature",
  "properties": {
    "iso:country": "GB",
    "wof:name": "BA2 3BD",
    "wof:placetype": "postalcode"
  },
  "geometry": {"coordinates":[-2.368332,51.378707],"type":"Point"}
}
