{
  "type": "Feature",
  "properties": {
    "date:inception_lower": "1980-01-01",
    "date:inception_upper": "1980-01-01",
    "iso:country": "GB",
    "wof:name": "BA2 3BD",
    "wof:placetype": "postalcode"
  },
  "geometry": {"coordinates":[-2.368073,51.378654],"type":"Point"}
}
