{
  "type": "Feature",
  "properties": {
    "iso:country": "GB",
    "wof:name": "HP6 6UP",
    "wof:placetype": "postalcode"
  },
  "geometry": {"coordinates":[-0.58678,51.67668],"type":"Point"}
}
