{
  "type": "Feature",
  "properties": {
    "iso:country": "GB",
    "wof:name": "NE9 6SJ",
    "wof:placetype": "postalcode"
  },
  "geometry": {"coordinates":[-1.57511,54.935424],"type":"Point"}
}
