{
  "type": "Feature",
  "properties": {
    "iso:country":"GB",
    "wof:name":"NE9 6SJ",
    "wof:placetype":"postalcode"
},
  "geometry": {"coordinates":[-1.57510975209633,54.93542435418919],"type":"Point"}
}