{
  "type": "Feature",
  "properties": {
    "iso:country": "GB",
    "wof:name": "EH5 1FL",
    "wof:placetype": "postalcode"
  },
  "geometry": {"coordinates":[-3.251393,55.977737],"type":"Point"}
}
