{
  "type": "Feature",
  "properties": {
    "iso:country": "GB",
    "wof:name": "DE21 5LD",
    "wof:placetype": "postalcode"
  },
  "geometry": {"coordinates":[-1.44944,52.953672],"type":"Point"}
}
