{
  "type": "Feature",
  "properties": {
    "iso:country":"GB",
    "wof:name":"DE21 5LD",
    "wof:placetype":"postalcode"
},
  "geometry": {"coordinates":[-1.44943972024125,52.95367164379785],"type":"Point"}
}