{
  "type": "Feature",
  "properties": {
    "iso:country": "GB",
    "wof:name": "E1 2HR",
    "wof:placetype": "postalcode"
  },
  "geometry": {"coordinates":[-0.055527,51.514541],"type":"Point"}
}
