{
  "type": "Feature",
  "properties": {
    "date:inception_lower": "1993-01-01",
    "date:inception_upper": "1993-01-01",
    "iso:country": "GB",
    "wof:name": "CF62 8DZ",
    "wof:placetype": "postalcode"
  },
  "geometry": {"coordinates":[-3.268522,51.40651],"type":"Point"}
}
