{
  "type": "Feature",
  "properties": {
    "iso:country":"GB",
    "wof:name":"CV3 4LJ",
    "wof:placetype":"postalcode"
},
  "geometry": {"coordinates":[-1.4804420067366,52.39383004826996],"type":"Point"}
}