{
  "type": "Feature",
  "properties": {
    "iso:country":"GB",
    "wof:name":"SO22 6RT",
    "wof:placetype":"postalcode"
},
  "geometry": {"coordinates":[-1.32294100029874,51.06907114477272],"type":"Point"}
}