{
  "type": "Feature",
  "properties": {
    "iso:country": "GB",
    "wof:name": "SO22 6RT",
    "wof:placetype": "postalcode"
  },
  "geometry": {"coordinates":[-1.322941,51.069071],"type":"Point"}
}
