{
  "type": "Feature",
  "properties": {
    "date:inception_lower": "1980-01-01",
    "date:inception_upper": "1980-01-01",
    "iso:country": "GB",
    "wof:name": "UB3 3LP",
    "wof:placetype": "postalcode"
  },
  "geometry": {"coordinates":[-0.411599,51.505616],"type":"Point"}
}
