{
  "type": "Feature",
  "properties": {
    "iso:country": "GB",
    "wof:name": "UB3 3LP",
    "wof:placetype": "postalcode"
  },
  "geometry": {"coordinates":[-0.411599,51.505616],"type":"Point"}
}
