{
  "type": "Feature",
  "properties": {
    "iso:country":"GB",
    "wof:name":"UB3 3LP",
    "wof:placetype":"postalcode"
},
  "geometry": {"coordinates":[-0.41154620955513,51.50565021563624],"type":"Point"}
}