{
  "type": "Feature",
  "properties": {
    "iso:country":"GB",
    "wof:name":"KA6 7QB",
    "wof:placetype":"postalcode"
},
  "geometry": {"coordinates":[-4.43740475921343,55.30788904833319],"type":"Point"}
}