{
  "type": "Feature",
  "properties": {
    "iso:country":"GB",
    "wof:name":"SW15 6UJ",
    "wof:placetype":"postalcode"
},
  "geometry": {"coordinates":[-0.23369519711564,51.46381874347298],"type":"Point"}
}