{
  "type": "Feature",
  "properties": {
    "date:inception_lower":"2005-04-01",
    "date:inception_upper":"2005-04-30",
    "iso:country":"GB",
    "wof:name":"SW15 6UJ",
    "wof:placetype":"postalcode"
},
  "geometry": {"coordinates":[-0.233695,51.463819],"type":"Point"}
}