{
  "type": "Feature",
  "properties": {
    "iso:country": "GB",
    "wof:name": "WV11 1TN",
    "wof:placetype": "postalcode"
  },
  "geometry": {"coordinates":[-2.080021,52.602123],"type":"Point"}
}
