{
  "type": "Feature",
  "properties": {
    "iso:country":"GB",
    "wof:name":"WV11 1TN",
    "wof:placetype":"postalcode"
},
  "geometry": {"coordinates":[-2.08005708729373,52.60215222564717],"type":"Point"}
}