{
  "type": "Feature",
  "properties": {
    "iso:country":"GB",
    "wof:name":"PO22 6LF",
    "wof:placetype":"postalcode"
},
  "geometry": {"coordinates":[-0.60141965734163,50.79210609444208],"type":"Point"}
}