{
  "type": "Feature",
  "properties": {
    "date:inception_lower": "1988-03-01",
    "date:inception_upper": "1988-03-01",
    "iso:country": "GB",
    "wof:name": "PO22 6LF",
    "wof:placetype": "postalcode"
  },
  "geometry": {"coordinates":[-0.60142,50.792106],"type":"Point"}
}
