{
  "type": "Feature",
  "properties": {
    "iso:country": "GB",
    "wof:name": "TR27 5JR",
    "wof:placetype": "postalcode"
  },
  "geometry": {"coordinates":[-5.393854,50.193846],"type":"Point"}
}
