{
  "type": "Feature",
  "properties": {
    "date:inception_lower": "1980-01-01",
    "date:inception_upper": "1980-01-01",
    "iso:country": "GB",
    "wof:name": "ME10 2LT",
    "wof:placetype": "postalcode"
  },
  "geometry": {"coordinates":[0.72523,51.346486],"type":"Point"}
}
