{
  "type": "Feature",
  "properties": {
    "date:inception_lower": "1980-01-01",
    "date:inception_upper": "1980-01-01",
    "iso:country": "GB",
    "wof:name": "LE5 1NL",
    "wof:placetype": "postalcode"
  },
  "geometry": {"coordinates":[-1.051677,52.647938],"type":"Point"}
}
