{
  "type": "Feature",
  "properties": {
    "iso:country":"GB",
    "wof:name":"NE31 1BJ",
    "wof:placetype":"postalcode"
},
  "geometry": {"coordinates":[-1.51969568689387,54.97802004623252],"type":"Point"}
}