{
  "type": "Feature",
  "properties": {
    "date:inception_lower": "2007-07-01",
    "date:inception_upper": "2007-07-01",
    "iso:country": "GB",
    "wof:name": "SA64 0BU",
    "wof:placetype": "postalcode"
  },
  "geometry": {"coordinates":[-4.984155,52.013287],"type":"Point"}
}
