{
  "type": "Feature",
  "properties": {
    "iso:country":"GB",
    "wof:name":"BR4 9BX",
    "wof:placetype":"postalcode"
},
  "geometry": {"coordinates":[0.0026081994157,51.37199884129771],"type":"Point"}
}