{
  "type": "Feature",
  "properties": {
    "iso:country":"GB",
    "wof:name":"NW7 3HR",
    "wof:placetype":"postalcode"
},
  "geometry": {"coordinates":[-0.25508385533101,51.62641467855175],"type":"Point"}
}