{
  "type": "Feature",
  "properties": {
    "iso:country":"GB",
    "wof:name":"DT9 4PF",
    "wof:placetype":"postalcode"
},
  "geometry": {"coordinates":[-2.48030907977193,51.00630546667053],"type":"Point"}
}