{
  "type": "Feature",
  "properties": {
    "iso:country": "GB",
    "wof:name": "KY16 8PF",
    "wof:placetype": "postalcode"
  },
  "geometry": {"coordinates":[-2.840114,56.27767],"type":"Point"}
}
