{
  "type": "Feature",
  "properties": {
    "iso:country":"GB",
    "wof:name":"LU1 2AF",
    "wof:placetype":"postalcode"
},
  "geometry": {"coordinates":[-0.41507716204561,51.87801911648472],"type":"Point"}
}