{
  "type": "Feature",
  "properties": {
    "iso:country":"GB",
    "wof:name":"BD23 2AH",
    "wof:placetype":"postalcode"
},
  "geometry": {"coordinates":[-2.01945592426451,53.9585426737974],"type":"Point"}
}