{
  "type": "Feature",
  "properties": {
    "date:inception_lower": "1980-01-01",
    "date:inception_upper": "1980-01-01",
    "iso:country": "GB",
    "wof:name": "YO7 2JU",
    "wof:placetype": "postalcode"
  },
  "geometry": {"coordinates":[-1.265809,54.317836],"type":"Point"}
}
