{
  "type": "Feature",
  "properties": {
    "iso:country":"GB",
    "wof:name":"YO7 2JU",
    "wof:placetype":"postalcode"
},
  "geometry": {"coordinates":[-1.26579883206715,54.31782284668765],"type":"Point"}
}