{
  "type": "Feature",
  "properties": {
    "iso:country":"GB",
    "wof:name":"SL1 7EW",
    "wof:placetype":"postalcode"
},
  "geometry": {"coordinates":[-0.66107076874995,51.53402223592281],"type":"Point"}
}