{
  "type": "Feature",
  "properties": {
    "iso:country":"GB",
    "wof:name":"CA8 2BA",
    "wof:placetype":"postalcode"
},
  "geometry": {"coordinates":[-2.71824961195337,54.99673209999317],"type":"Point"}
}