{
  "type": "Feature",
  "properties": {
    "iso:country":"GB",
    "wof:name":"BD8 9NX",
    "wof:placetype":"postalcode"
},
  "geometry": {"coordinates":[-1.78900862893084,53.80473920865285],"type":"Point"}
}