{
  "type": "Feature",
  "properties": {
    "iso:country":"GB",
    "wof:name":"E16 2EQ",
    "wof:placetype":"postalcode"
},
  "geometry": {"coordinates":[0.03796885684865,51.50100259638336],"type":"Point"}
}