{
  "type": "Feature",
  "properties": {
    "iso:country": "GB",
    "wof:name": "WF6 2PD",
    "wof:placetype": "postalcode"
  },
  "geometry": {"coordinates":[-1.428883,53.710736],"type":"Point"}
}
