{
  "type": "Feature",
  "properties": {
    "iso:country":"GB",
    "wof:name":"LE5 5HF",
    "wof:placetype":"postalcode"
},
  "geometry": {"coordinates":[-1.10758390213246,52.62733600121959],"type":"Point"}
}