{
  "type": "Feature",
  "properties": {
    "iso:country":"GB",
    "wof:name":"BN22 0JY",
    "wof:placetype":"postalcode"
},
  "geometry": {"coordinates":[0.25820234710926,50.80357922078096],"type":"Point"}
}