{
  "type": "Feature",
  "properties": {
    "iso:country":"GB",
    "wof:name":"HG2 7HH",
    "wof:placetype":"postalcode"
},
  "geometry": {"coordinates":[-1.5039288811331,53.98937403716179],"type":"Point"}
}