{
  "type": "Feature",
  "properties": {
    "iso:country": "GB",
    "wof:name": "BN10 7FB",
    "wof:placetype": "postalcode"
  },
  "geometry": {"coordinates":[-0.010227,50.793574],"type":"Point"}
}
