{
  "type": "Feature",
  "properties": {
    "iso:country":"GB",
    "wof:name":"CF62 5AN",
    "wof:placetype":"postalcode"
},
  "geometry": {"coordinates":[-3.27563110718868,51.40159498232456],"type":"Point"}
}