{
  "type": "Feature",
  "properties": {
    "iso:country": "GB",
    "wof:name": "CF62 5AN",
    "wof:placetype": "postalcode"
  },
  "geometry": {"coordinates":[-3.275631,51.401595],"type":"Point"}
}
