{
  "type": "Feature",
  "properties": {
    "date:inception_lower":"2000-06-01",
    "date:inception_upper":"2000-06-30",
    "iso:country":"GB",
    "wof:name":"CF62 5AN",
    "wof:placetype":"postalcode"
},
  "geometry": {"coordinates":[-3.275631,51.401595],"type":"Point"}
}