{
  "type": "Feature",
  "properties": {
    "iso:country":"GB",
    "wof:name":"TF9 2PD",
    "wof:placetype":"postalcode"
},
  "geometry": {"coordinates":[-2.45840104804145,52.90016937960708],"type":"Point"}
}