{
  "type": "Feature",
  "properties": {
    "date:inception_lower":"1980-01-01",
    "date:inception_upper":"1980-01-31",
    "iso:country":"GB",
    "wof:name":"TF9 2PD",
    "wof:placetype":"postalcode"
},
  "geometry": {"coordinates":[-2.458401,52.900169],"type":"Point"}
}