{
  "type": "Feature",
  "properties": {
    "iso:country":"GB",
    "wof:name":"SN15 5DR",
    "wof:placetype":"postalcode"
},
  "geometry": {"coordinates":[-1.9637545002334,51.56588542381348],"type":"Point"}
}