{
  "type": "Feature",
  "properties": {
    "iso:country":"GB",
    "wof:name":"S63 0JT",
    "wof:placetype":"postalcode"
},
  "geometry": {"coordinates":[-1.31154928826959,53.54573081954089],"type":"Point"}
}