{
  "type": "Feature",
  "properties": {
    "date:inception_lower": "1980-01-01",
    "date:inception_upper": "1980-01-01",
    "iso:country": "GB",
    "wof:name": "S63 0JT",
    "wof:placetype": "postalcode"
  },
  "geometry": {"coordinates":[-1.311549,53.545731],"type":"Point"}
}
