{
  "type": "Feature",
  "properties": {
    "iso:country": "GB",
    "wof:name": "G83 8NQ",
    "wof:placetype": "postalcode"
  },
  "geometry": {"coordinates":[-4.530693,56.052661],"type":"Point"}
}
