{
  "type": "Feature",
  "properties": {
    "iso:country":"GB",
    "wof:name":"DG12 6SQ",
    "wof:placetype":"postalcode"
},
  "geometry": {"coordinates":[-3.26400954426497,54.97411301468595],"type":"Point"}
}