{
  "type": "Feature",
  "properties": {
    "iso:country":"GB",
    "wof:name":"BL2 1PG",
    "wof:placetype":"postalcode"
},
  "geometry": {"coordinates":[-2.4020729091054,53.57128469394815],"type":"Point"}
}