{
  "type": "Feature",
  "properties": {
    "iso:country":"GB",
    "wof:name":"BN23 7AR",
    "wof:placetype":"postalcode"
},
  "geometry": {"coordinates":[0.31466772808564,50.79534892327148],"type":"Point"}
}