{
  "type": "Feature",
  "properties": {
    "iso:country":"GB",
    "wof:name":"EH19 3NP",
    "wof:placetype":"postalcode"
},
  "geometry": {"coordinates":[-3.09633392164911,55.86850185998809],"type":"Point"}
}