{
  "type": "Feature",
  "properties": {
    "iso:country":"GB",
    "wof:name":"BN1 4QR",
    "wof:placetype":"postalcode"
},
  "geometry": {"coordinates":[-0.13441519138095,50.8366458352267],"type":"Point"}
}