{
  "type": "Feature",
  "properties": {
    "iso:country":"GB",
    "wof:name":"OX17 2QY",
    "wof:placetype":"postalcode"
},
  "geometry": {"coordinates":[-1.28048016180769,52.07757529609994],"type":"Point"}
}