{
  "type": "Feature",
  "properties": {
    "iso:country":"GB",
    "wof:name":"DG14 0XR",
    "wof:placetype":"postalcode"
},
  "geometry": {"coordinates":[-3.06386949595092,55.09491299738222],"type":"Point"}
}