{
  "type": "Feature",
  "properties": {
    "iso:country":"GB",
    "wof:name":"IP27 0LZ",
    "wof:placetype":"postalcode"
},
  "geometry": {"coordinates":[0.60778114231304,52.43991212144647],"type":"Point"}
}