{
  "type": "Feature",
  "properties": {
    "iso:country":"GB",
    "wof:name":"OX11 7SB",
    "wof:placetype":"postalcode"
},
  "geometry": {"coordinates":[-1.2296179023251,51.61629717941729],"type":"Point"}
}