{
  "type": "Feature",
  "properties": {
    "iso:country":"GB",
    "wof:name":"YO12 5NG",
    "wof:placetype":"postalcode"
},
  "geometry": {"coordinates":[-0.4325784501653,54.27304185706727],"type":"Point"}
}