{
  "type": "Feature",
  "properties": {
    "date:inception_lower":"1980-01-01",
    "date:inception_upper":"1980-01-31",
    "iso:country":"GB",
    "wof:name":"YO12 5NG",
    "wof:placetype":"postalcode"
},
  "geometry": {"coordinates":[-0.432578,54.273042],"type":"Point"}
}