{
  "type": "Feature",
  "properties": {
    "iso:country":"GB",
    "wof:name":"IP24 3EN",
    "wof:placetype":"postalcode"
},
  "geometry": {"coordinates":[0.74969956679465,52.40507741151051],"type":"Point"}
}