{
  "type": "Feature",
  "properties": {
    "date:inception_lower": "1990-02-01",
    "date:inception_upper": "1990-02-01",
    "iso:country": "GB",
    "wof:name": "LE2 6HZ",
    "wof:placetype": "postalcode"
  },
  "geometry": {"coordinates":[-1.123385,52.604359],"type":"Point"}
}
