{
  "type": "Feature",
  "properties": {
    "iso:country": "GB",
    "wof:name": "LE2 6HZ",
    "wof:placetype": "postalcode"
  },
  "geometry": {"coordinates":[-1.123437,52.604368],"type":"Point"}
}
