{
  "type": "Feature",
  "properties": {
    "date:inception_lower": "1980-01-01",
    "date:inception_upper": "1980-01-01",
    "iso:country": "GB",
    "wof:name": "CV37 7EB",
    "wof:placetype": "postalcode"
  },
  "geometry": {"coordinates":[-1.693818,52.189857],"type":"Point"}
}
