{
  "type": "Feature",
  "properties": {
    "iso:country":"GB",
    "wof:name":"CV37 7EB",
    "wof:placetype":"postalcode"
},
  "geometry": {"coordinates":[-1.6938183356117,52.18985715962839],"type":"Point"}
}