{
  "type": "Feature",
  "properties": {
    "iso:country": "GB",
    "wof:name": "SE23 3QE",
    "wof:placetype": "postalcode"
  },
  "geometry": {"coordinates":[-0.058689,51.442509],"type":"Point"}
}
