{
  "type": "Feature",
  "properties": {
    "iso:country":"GB",
    "wof:name":"DH1 3BG",
    "wof:placetype":"postalcode"
},
  "geometry": {"coordinates":[-1.5666629526638,54.77142763111966],"type":"Point"}
}