{
  "type": "Feature",
  "properties": {
    "iso:country": "GB",
    "wof:name": "NG6 8HQ",
    "wof:placetype": "postalcode"
  },
  "geometry": {"coordinates":[-1.199686,53.00378],"type":"Point"}
}
