{
  "type": "Feature",
  "properties": {
    "iso:country":"GB",
    "wof:name":"SG8 0JA",
    "wof:placetype":"postalcode"
},
  "geometry": {"coordinates":[-0.13479619402922,52.08385180705721],"type":"Point"}
}