{
  "type": "Feature",
  "properties": {
    "iso:country":"GB",
    "wof:name":"SO19 6JY",
    "wof:placetype":"postalcode"
},
  "geometry": {"coordinates":[-1.33624969837512,50.90668210895856],"type":"Point"}
}