{
  "type": "Feature",
  "properties": {
    "date:inception_lower": "1997-06-01",
    "date:inception_upper": "1997-06-01",
    "iso:country": "GB",
    "wof:name": "L23 7YX",
    "wof:placetype": "postalcode"
  },
  "geometry": {"coordinates":[-3.028997,53.493527],"type":"Point"}
}
