{
  "type": "Feature",
  "properties": {
    "iso:country":"GB",
    "wof:name":"L23 7YX",
    "wof:placetype":"postalcode"
},
  "geometry": {"coordinates":[-3.02952159504179,53.49331747307492],"type":"Point"}
}