{
  "type": "Feature",
  "properties": {
    "iso:country": "GB",
    "wof:name": "L23 7YX",
    "wof:placetype": "postalcode"
  },
  "geometry": {"coordinates":[-3.02949,53.493343],"type":"Point"}
}
