{
  "type": "Feature",
  "properties": {
    "iso:country":"GB",
    "wof:name":"SA2 8ES",
    "wof:placetype":"postalcode"
},
  "geometry": {"coordinates":[-3.99978884434909,51.60224232278159],"type":"Point"}
}