{
  "type": "Feature",
  "properties": {
    "date:inception_lower": "2005-03-01",
    "date:inception_upper": "2005-03-01",
    "iso:country": "GB",
    "wof:name": "SG14 3BE",
    "wof:placetype": "postalcode"
  },
  "geometry": {"coordinates":[-0.084948,51.800452],"type":"Point"}
}
