{
  "type": "Feature",
  "properties": {
    "iso:country":"GB",
    "wof:name":"DH7 7RG",
    "wof:placetype":"postalcode"
},
  "geometry": {"coordinates":[-1.64507294354657,54.78145954644271],"type":"Point"}
}