{
  "type": "Feature",
  "properties": {
    "iso:country": "GB",
    "wof:name": "DH7 7RG",
    "wof:placetype": "postalcode"
  },
  "geometry": {"coordinates":[-1.646855,54.781671],"type":"Point"}
}
