{
  "type": "Feature",
  "properties": {
    "iso:country":"GB",
    "wof:name":"IV54 8YA",
    "wof:placetype":"postalcode"
},
  "geometry": {"coordinates":[-5.49059679075819,57.40154775664782],"type":"Point"}
}