{
  "type": "Feature",
  "properties": {
    "date:inception_lower":"1980-01-01",
    "date:inception_upper":"1980-01-31",
    "iso:country":"GB",
    "wof:name":"IV54 8YA",
    "wof:placetype":"postalcode"
},
  "geometry": {"coordinates":[-5.490597,57.401548],"type":"Point"}
}