{
  "type": "Feature",
  "properties": {
    "iso:country": "GB",
    "wof:name": "BL9 6LL",
    "wof:placetype": "postalcode"
  },
  "geometry": {"coordinates":[-2.290648,53.602437],"type":"Point"}
}
