{
  "type": "Feature",
  "properties": {
    "iso:country":"GB",
    "wof:name":"BL9 6LL",
    "wof:placetype":"postalcode"
},
  "geometry": {"coordinates":[-2.29064846756514,53.60243742757899],"type":"Point"}
}