{
  "type": "Feature",
  "properties": {
    "iso:country":"GB",
    "wof:name":"W5 3EZ",
    "wof:placetype":"postalcode"
},
  "geometry": {"coordinates":[-0.28765315917329,51.52645971444925],"type":"Point"}
}