{
  "type": "Feature",
  "properties": {
    "iso:country": "GB",
    "wof:name": "W5 3EZ",
    "wof:placetype": "postalcode"
  },
  "geometry": {"coordinates":[-0.287653,51.52646],"type":"Point"}
}
