{
  "type": "Feature",
  "properties": {
    "iso:country":"GB",
    "wof:name":"NE24 5BW",
    "wof:placetype":"postalcode"
},
  "geometry": {"coordinates":[-1.52146976849248,55.12701795762199],"type":"Point"}
}