{
  "type": "Feature",
  "properties": {
    "date:inception_lower":"1980-01-01",
    "date:inception_upper":"1980-01-31",
    "iso:country":"GB",
    "wof:name":"SA32 8ET",
    "wof:placetype":"postalcode"
},
  "geometry": {"coordinates":[-4.220209,51.842079],"type":"Point"}
}