{
  "type": "Feature",
  "properties": {
    "iso:country":"GB",
    "wof:name":"TS26 8AX",
    "wof:placetype":"postalcode"
},
  "geometry": {"coordinates":[-1.21746099594773,54.68837459376029],"type":"Point"}
}