{
  "type": "Feature",
  "properties": {
    "date:inception_lower": "1980-01-01",
    "date:inception_upper": "1980-01-01",
    "iso:country": "GB",
    "wof:name": "TS26 8AX",
    "wof:placetype": "postalcode"
  },
  "geometry": {"coordinates":[-1.217461,54.688375],"type":"Point"}
}
