{
  "type": "Feature",
  "properties": {
    "iso:country":"GB",
    "wof:name":"CV21 3SX",
    "wof:placetype":"postalcode"
},
  "geometry": {"coordinates":[-1.2520966534474,52.37061616146618],"type":"Point"}
}