{
  "type": "Feature",
  "properties": {
    "iso:country": "GB",
    "wof:name": "ST18 0TJ",
    "wof:placetype": "postalcode"
  },
  "geometry": {"coordinates":[-2.090468,52.831092],"type":"Point"}
}
