{
  "type": "Feature",
  "properties": {
    "date:inception_lower":"1983-03-01",
    "date:inception_upper":"1983-03-31",
    "iso:country":"GB",
    "wof:name":"ST18 0TJ",
    "wof:placetype":"postalcode"
},
  "geometry": {"coordinates":[-2.090468,52.831092],"type":"Point"}
}