{
  "type": "Feature",
  "properties": {
    "iso:country":"GB",
    "wof:name":"BB9 0TF",
    "wof:placetype":"postalcode"
},
  "geometry": {"coordinates":[-2.20508129222147,53.83468737533384],"type":"Point"}
}