{
  "type": "Feature",
  "properties": {
    "iso:country":"GB",
    "wof:name":"BL1 7ND",
    "wof:placetype":"postalcode"
},
  "geometry": {"coordinates":[-2.47103325318071,53.60079337475216],"type":"Point"}
}