{
  "type": "Feature",
  "properties": {
    "iso:country":"GB",
    "wof:name":"RG1 7UR",
    "wof:placetype":"postalcode"
},
  "geometry": {"coordinates":[-0.98147424923246,51.45378791747414],"type":"Point"}
}