{
  "type": "Feature",
  "properties": {
    "iso:country":"GB",
    "wof:name":"WF4 5HQ",
    "wof:placetype":"postalcode"
},
  "geometry": {"coordinates":[-1.54372500282382,53.66435485315598],"type":"Point"}
}