{
  "type": "Feature",
  "properties": {
    "iso:country": "GB",
    "wof:name": "WF4 5HQ",
    "wof:placetype": "postalcode"
  },
  "geometry": {"coordinates":[-1.543576,53.664389],"type":"Point"}
}
