{
  "type": "Feature",
  "properties": {
    "iso:country":"GB",
    "wof:name":"HU5 2AJ",
    "wof:placetype":"postalcode"
},
  "geometry": {"coordinates":[-0.36078898145958,53.76309873372892],"type":"Point"}
}