{
  "type": "Feature",
  "properties": {
    "iso:country": "GB",
    "wof:name": "HU5 2AJ",
    "wof:placetype": "postalcode"
  },
  "geometry": {"coordinates":[-0.360789,53.763099],"type":"Point"}
}
