{
  "type": "Feature",
  "properties": {
    "date:inception_lower": "1980-01-01",
    "date:inception_upper": "1980-01-01",
    "iso:country": "GB",
    "wof:name": "HU5 2AJ",
    "wof:placetype": "postalcode"
  },
  "geometry": {"coordinates":[-0.360789,53.763099],"type":"Point"}
}
