{
  "type": "Feature",
  "properties": {
    "date:inception_lower": "1990-05-01",
    "date:inception_upper": "1990-05-01",
    "iso:country": "GB",
    "wof:name": "PA31 8TT",
    "wof:placetype": "postalcode"
  },
  "geometry": {"coordinates":[-5.423263,56.032932],"type":"Point"}
}
