{
  "type": "Feature",
  "properties": {
    "iso:country":"GB",
    "wof:name":"PA31 8TT",
    "wof:placetype":"postalcode"
},
  "geometry": {"coordinates":[-5.42326264815671,56.03293248669149],"type":"Point"}
}