{
  "type": "Feature",
  "properties": {
    "iso:country":"GB",
    "wof:name":"BN15 0JB",
    "wof:placetype":"postalcode"
},
  "geometry": {"coordinates":[-0.3380676760797,50.83329408949758],"type":"Point"}
}