{
  "type": "Feature",
  "properties": {
    "iso:country": "GB",
    "wof:name": "BN15 0JB",
    "wof:placetype": "postalcode"
  },
  "geometry": {"coordinates":[-0.338068,50.833294],"type":"Point"}
}
