{
  "type": "Feature",
  "properties": {
    "iso:country":"GB",
    "wof:name":"SA3 4EH",
    "wof:placetype":"postalcode"
},
  "geometry": {"coordinates":[-3.98957738176464,51.57180523566358],"type":"Point"}
}