{
  "type": "Feature",
  "properties": {
    "iso:country": "GB",
    "wof:name": "SA3 4EH",
    "wof:placetype": "postalcode"
  },
  "geometry": {"coordinates":[-3.98948,51.571776],"type":"Point"}
}
