{
  "type": "Feature",
  "properties": {
    "date:inception_lower": "1993-08-01",
    "date:inception_upper": "1993-08-01",
    "iso:country": "GB",
    "wof:name": "SA3 4EH",
    "wof:placetype": "postalcode"
  },
  "geometry": {"coordinates":[-3.98948,51.571776],"type":"Point"}
}
