{
  "type": "Feature",
  "properties": {
    "iso:country":"GB",
    "wof:name":"SA16 0PF",
    "wof:placetype":"postalcode"
},
  "geometry": {"coordinates":[-4.24673025422378,51.68680249437087],"type":"Point"}
}