{
  "type": "Feature",
  "properties": {
    "date:inception_lower":"1980-01-01",
    "date:inception_upper":"1980-01-31",
    "iso:country":"GB",
    "wof:name":"SA16 0PF",
    "wof:placetype":"postalcode"
},
  "geometry": {"coordinates":[-4.24673,51.686802],"type":"Point"}
}