{
  "type": "Feature",
  "properties": {
    "iso:country":"GB",
    "wof:name":"PL4 8JL",
    "wof:placetype":"postalcode"
},
  "geometry": {"coordinates":[-4.13414666527217,50.37681610205103],"type":"Point"}
}