{
  "type": "Feature",
  "properties": {
    "iso:country":"GB",
    "wof:name":"G83 8DY",
    "wof:placetype":"postalcode"
},
  "geometry": {"coordinates":[-4.56018062070107,56.00296912584893],"type":"Point"}
}