{
  "type": "Feature",
  "properties": {
    "iso:country": "GB",
    "wof:name": "G71 6FD",
    "wof:placetype": "postalcode"
  },
  "geometry": {"coordinates":[-4.056457,55.826175],"type":"Point"}
}
