{
  "type": "Feature",
  "properties": {
    "iso:country":"GB",
    "wof:name":"G33 3GD",
    "wof:placetype":"postalcode"
},
  "geometry": {"coordinates":[-4.17039635879714,55.86355364600882],"type":"Point"}
}