{
  "type": "Feature",
  "properties": {
    "date:inception_lower":"1980-01-01",
    "date:inception_upper":"1980-01-31",
    "iso:country":"GB",
    "wof:name":"SA10 7BU",
    "wof:placetype":"postalcode"
},
  "geometry": {"coordinates":[-3.822354,51.665497],"type":"Point"}
}