{
  "type": "Feature",
  "properties": {
    "iso:country":"GB",
    "wof:name":"SA10 7BU",
    "wof:placetype":"postalcode"
},
  "geometry": {"coordinates":[-3.8223535596727,51.66549741303938],"type":"Point"}
}