{
  "type": "Feature",
  "properties": {
    "iso:country": "GB",
    "wof:name": "SA10 7BU",
    "wof:placetype": "postalcode"
  },
  "geometry": {"coordinates":[-3.822354,51.665497],"type":"Point"}
}
