{
  "type": "Feature",
  "properties": {
    "iso:country":"GB",
    "wof:name":"G81 5HL",
    "wof:placetype":"postalcode"
},
  "geometry": {"coordinates":[-4.38764540856709,55.92666701868881],"type":"Point"}
}