{
  "type": "Feature",
  "properties": {
    "iso:country": "GB",
    "wof:name": "SW13 9NY",
    "wof:placetype": "postalcode"
  },
  "geometry": {"coordinates":[-0.242238,51.477903],"type":"Point"}
}
