{
  "type": "Feature",
  "properties": {
    "iso:country": "GB",
    "wof:name": "RH17 7AS",
    "wof:placetype": "postalcode"
  },
  "geometry": {"coordinates":[-0.026967,51.036903],"type":"Point"}
}
