{
  "type": "Feature",
  "properties": {
    "iso:country":"GB",
    "wof:name":"IV99 1AF",
    "wof:placetype":"postalcode"
},
  "geometry": {"coordinates":[-4.22395035641382,57.48133169391186],"type":"Point"}
}