{
  "type": "Feature",
  "properties": {
    "iso:country":"GB",
    "wof:name":"PL24 2PF",
    "wof:placetype":"postalcode"
},
  "geometry": {"coordinates":[-4.69924556161682,50.35626964026461],"type":"Point"}
}