{
  "type": "Feature",
  "properties": {
    "iso:country":"GB",
    "wof:name":"G66 5LE",
    "wof:placetype":"postalcode"
},
  "geometry": {"coordinates":[-4.15198816367525,55.90316906284187],"type":"Point"}
}