{
  "type": "Feature",
  "properties": {
    "iso:country":"GB",
    "wof:name":"TQ13 9LZ",
    "wof:placetype":"postalcode"
},
  "geometry": {"coordinates":[-3.67779933514326,50.59872632196469],"type":"Point"}
}