{
  "type": "Feature",
  "properties": {
    "iso:country":"GB",
    "wof:name":"CW7 3HH",
    "wof:placetype":"postalcode"
},
  "geometry": {"coordinates":[-2.50865086761416,53.19286856848615],"type":"Point"}
}