{
  "type": "Feature",
  "properties": {
    "iso:country": "GB",
    "wof:name": "CW7 3HH",
    "wof:placetype": "postalcode"
  },
  "geometry": {"coordinates":[-2.508695,53.192983],"type":"Point"}
}
