{
  "type": "Feature",
  "properties": {
    "date:inception_lower":"1980-01-01",
    "date:inception_upper":"1980-01-31",
    "iso:country":"GB",
    "wof:name":"NG12 1BB",
    "wof:placetype":"postalcode"
},
  "geometry": {"coordinates":[-1.030594,52.955741],"type":"Point"}
}