{
  "type": "Feature",
  "properties": {
    "iso:country":"GB",
    "wof:name":"WA12 8EJ",
    "wof:placetype":"postalcode"
},
  "geometry": {"coordinates":[-2.63073854485955,53.44923933413946],"type":"Point"}
}