{
  "type": "Feature",
  "properties": {
    "iso:country": "GB",
    "wof:name": "EN2 6AH",
    "wof:placetype": "postalcode"
  },
  "geometry": {"coordinates":[-0.083119,51.652607],"type":"Point"}
}
