{
  "type": "Feature",
  "properties": {
    "iso:country":"GB",
    "wof:name":"EN2 6AH",
    "wof:placetype":"postalcode"
},
  "geometry": {"coordinates":[-0.08311944779404,51.65260739100119],"type":"Point"}
}