{
  "type": "Feature",
  "properties": {
    "date:inception_lower": "2012-04-01",
    "date:inception_upper": "2012-04-01",
    "iso:country": "GB",
    "wof:name": "EN2 6AH",
    "wof:placetype": "postalcode"
  },
  "geometry": {"coordinates":[-0.083119,51.652607],"type":"Point"}
}
