{
  "type": "Feature",
  "properties": {
    "date:inception_lower": "1985-10-01",
    "date:inception_upper": "1985-10-01",
    "iso:country": "GB",
    "wof:name": "ME5 8SQ",
    "wof:placetype": "postalcode"
  },
  "geometry": {"coordinates":[0.551697,51.336051],"type":"Point"}
}
