{
  "type": "Feature",
  "properties": {
    "iso:country":"GB",
    "wof:name":"ME5 8SQ",
    "wof:placetype":"postalcode"
},
  "geometry": {"coordinates":[0.5516972089187,51.33605123252141],"type":"Point"}
}