{
  "type": "Feature",
  "properties": {
    "date:inception_lower": "2019-05-01",
    "date:inception_upper": "2019-05-01",
    "iso:country": "GB",
    "wof:name": "DG16 5FH",
    "wof:placetype": "postalcode"
  },
  "geometry": {"coordinates":[-3.075634,54.997176],"type":"Point"}
}
