{
  "type": "Feature",
  "properties": {
    "iso:country":"GB",
    "wof:name":"OL4 2EB",
    "wof:placetype":"postalcode"
},
  "geometry": {"coordinates":[-2.08147520735036,53.54835695076909],"type":"Point"}
}