{
  "type": "Feature",
  "properties": {
    "iso:country": "GB",
    "wof:name": "CV5 7NL",
    "wof:placetype": "postalcode"
  },
  "geometry": {"coordinates":[-1.607074,52.415938],"type":"Point"}
}
