{
  "type": "Feature",
  "properties": {
    "date:inception_lower": "1986-07-01",
    "date:inception_upper": "1986-07-01",
    "iso:country": "GB",
    "wof:name": "SK14 3AS",
    "wof:placetype": "postalcode"
  },
  "geometry": {"coordinates":[-2.026872,53.454642],"type":"Point"}
}
