{
  "type": "Feature",
  "properties": {
    "iso:country":"GB",
    "wof:name":"SK14 3AS",
    "wof:placetype":"postalcode"
},
  "geometry": {"coordinates":[-2.02687173566372,53.45464174351253],"type":"Point"}
}