{
  "type": "Feature",
  "properties": {
    "date:inception_lower": "1980-01-01",
    "date:inception_upper": "1980-01-01",
    "iso:country": "GB",
    "wof:name": "SW10 9HF",
    "wof:placetype": "postalcode"
  },
  "geometry": {"coordinates":[-0.188915,51.487289],"type":"Point"}
}
