{
  "type": "Feature",
  "properties": {
    "iso:country":"GB",
    "wof:name":"SW10 9HF",
    "wof:placetype":"postalcode"
},
  "geometry": {"coordinates":[-0.18895425395331,51.48737997136762],"type":"Point"}
}