{
  "type": "Feature",
  "properties": {
    "iso:country":"GB",
    "wof:name":"LL16 4YH",
    "wof:placetype":"postalcode"
},
  "geometry": {"coordinates":[-3.42037553919483,53.22698149791825],"type":"Point"}
}