{
  "type": "Feature",
  "properties": {
    "iso:country":"GB",
    "wof:name":"WF6 1EW",
    "wof:placetype":"postalcode"
},
  "geometry": {"coordinates":[-1.41904478390927,53.69789869193742],"type":"Point"}
}