{
  "type": "Feature",
  "properties": {
    "date:inception_lower": "2019-10-01",
    "date:inception_upper": "2019-10-01",
    "iso:country": "GB",
    "wof:name": "EH5 1RY",
    "wof:placetype": "postalcode"
  },
  "geometry": {"coordinates":[-3.222753,55.984279],"type":"Point"}
}
