{
  "type": "Feature",
  "properties": {
    "iso:country":"GB",
    "wof:name":"LA1 1UA",
    "wof:placetype":"postalcode"
},
  "geometry": {"coordinates":[-2.79999177595892,54.0480862339725],"type":"Point"}
}