{
  "type": "Feature",
  "properties": {
    "iso:country":"GB",
    "wof:name":"BR7 5BQ",
    "wof:placetype":"postalcode"
},
  "geometry": {"coordinates":[0.06495568375862,51.41935223983536],"type":"Point"}
}