{
  "type": "Feature",
  "properties": {
    "iso:country": "GB",
    "wof:name": "BA13 4EF",
    "wof:placetype": "postalcode"
  },
  "geometry": {"coordinates":[-2.227875,51.266716],"type":"Point"}
}
