{
  "type": "Feature",
  "properties": {
    "iso:country":"GB",
    "wof:name":"NG18 2RS",
    "wof:placetype":"postalcode"
},
  "geometry": {"coordinates":[-1.18867052778766,53.13740370713727],"type":"Point"}
}