{
  "type": "Feature",
  "properties": {
    "date:inception_lower": "1980-01-01",
    "date:inception_upper": "1980-01-01",
    "iso:country": "GB",
    "wof:name": "NG18 2RS",
    "wof:placetype": "postalcode"
  },
  "geometry": {"coordinates":[-1.18867,53.137404],"type":"Point"}
}
