{
  "type": "Feature",
  "properties": {
    "iso:country":"GB",
    "wof:name":"LS17 8FX",
    "wof:placetype":"postalcode"
},
  "geometry": {"coordinates":[-1.48155383241659,53.85420978236923],"type":"Point"}
}