{
  "type": "Feature",
  "properties": {
    "date:inception_lower": "2014-06-01",
    "date:inception_upper": "2014-06-01",
    "iso:country": "GB",
    "wof:name": "LS17 8FX",
    "wof:placetype": "postalcode"
  },
  "geometry": {"coordinates":[-1.481554,53.85421],"type":"Point"}
}
