{
  "type": "Feature",
  "properties": {
    "date:inception_lower": "1999-12-01",
    "date:inception_upper": "1999-12-01",
    "iso:country": "GB",
    "wof:name": "G32 8FD",
    "wof:placetype": "postalcode"
  },
  "geometry": {"coordinates":[-4.171115,55.83342],"type":"Point"}
}
