{
  "type": "Feature",
  "properties": {
    "iso:country": "GB",
    "wof:name": "G32 8FD",
    "wof:placetype": "postalcode"
  },
  "geometry": {"coordinates":[-4.171115,55.83342],"type":"Point"}
}
