{
  "type": "Feature",
  "properties": {
    "iso:country": "GB",
    "wof:name": "ST17 4JS",
    "wof:placetype": "postalcode"
  },
  "geometry": {"coordinates":[-2.098611,52.789509],"type":"Point"}
}
