{
  "type": "Feature",
  "properties": {
    "iso:country": "GB",
    "wof:name": "LL12 8BN",
    "wof:placetype": "postalcode"
  },
  "geometry": {"coordinates":[-2.988209,53.065793],"type":"Point"}
}
