{
  "type": "Feature",
  "properties": {
    "iso:country":"GB",
    "wof:name":"LL12 8BN",
    "wof:placetype":"postalcode"
},
  "geometry": {"coordinates":[-2.98820904448433,53.06579317222153],"type":"Point"}
}