{
  "type": "Feature",
  "properties": {
    "date:inception_lower": "1986-04-01",
    "date:inception_upper": "1986-04-01",
    "iso:country": "GB",
    "wof:name": "OL16 1FF",
    "wof:placetype": "postalcode"
  },
  "geometry": {"coordinates":[-2.157226,53.614102],"type":"Point"}
}
