{
  "type": "Feature",
  "properties": {
    "iso:country":"GB",
    "wof:name":"OL16 1FF",
    "wof:placetype":"postalcode"
},
  "geometry": {"coordinates":[-2.15722619148398,53.61410246068507],"type":"Point"}
}