{
  "type": "Feature",
  "properties": {
    "iso:country":"GB",
    "wof:name":"CV6 4DQ",
    "wof:placetype":"postalcode"
},
  "geometry": {"coordinates":[-1.50426142050381,52.44386350078981],"type":"Point"}
}