{
  "type": "Feature",
  "properties": {
    "date:inception_lower": "2010-01-01",
    "date:inception_upper": "2010-01-01",
    "iso:country": "GB",
    "wof:name": "S4 7TL",
    "wof:placetype": "postalcode"
  },
  "geometry": {"coordinates":[-1.454317,53.385814],"type":"Point"}
}
