{
  "type": "Feature",
  "properties": {
    "iso:country":"GB",
    "wof:name":"S4 7TL",
    "wof:placetype":"postalcode"
},
  "geometry": {"coordinates":[-1.45430304921557,53.38575133439605],"type":"Point"}
}