{
  "type": "Feature",
  "properties": {
    "iso:country":"GB",
    "wof:name":"TA7 9AW",
    "wof:placetype":"postalcode"
},
  "geometry": {"coordinates":[-2.89354414838987,51.13005583936238],"type":"Point"}
}