{
  "type": "Feature",
  "properties": {
    "date:inception_lower": "2019-01-01",
    "date:inception_upper": "2019-01-01",
    "iso:country": "GB",
    "wof:name": "UB8 1GX",
    "wof:placetype": "postalcode"
  },
  "geometry": {"coordinates":[-0.481968,51.546069],"type":"Point"}
}
