{
  "type": "Feature",
  "properties": {
    "iso:country":"GB",
    "wof:name":"B66 2RE",
    "wof:placetype":"postalcode"
},
  "geometry": {"coordinates":[-1.95079722883881,52.48896006119774],"type":"Point"}
}