{
  "type": "Feature",
  "properties": {
    "iso:country":"GB",
    "wof:name":"KT7 0PR",
    "wof:placetype":"postalcode"
},
  "geometry": {"coordinates":[-0.34049948068622,51.39515734163808],"type":"Point"}
}