{
  "type": "Feature",
  "properties": {
    "iso:country":"GB",
    "wof:name":"HX6 3EY",
    "wof:placetype":"postalcode"
},
  "geometry": {"coordinates":[-1.96179748421753,53.69540819191987],"type":"Point"}
}