{
  "type": "Feature",
  "properties": {
    "iso:country": "GB",
    "wof:name": "HX6 3EY",
    "wof:placetype": "postalcode"
  },
  "geometry": {"coordinates":[-1.961797,53.695408],"type":"Point"}
}
