{
  "type": "Feature",
  "properties": {
    "iso:country": "GB",
    "wof:name": "GU18 5SR",
    "wof:placetype": "postalcode"
  },
  "geometry": {"coordinates":[-0.648519,51.350862],"type":"Point"}
}
