{
  "type": "Feature",
  "properties": {
    "iso:country":"GB",
    "wof:name":"SO15 5EG",
    "wof:placetype":"postalcode"
},
  "geometry": {"coordinates":[-1.42105808307457,50.91585594261102],"type":"Point"}
}