{
  "type": "Feature",
  "properties": {
    "iso:country": "GB",
    "wof:name": "GU11 1SG",
    "wof:placetype": "postalcode"
  },
  "geometry": {"coordinates":[-0.758731,51.249361],"type":"Point"}
}
