{
  "type": "Feature",
  "properties": {
    "iso:country":"GB",
    "wof:name":"GU11 1SG",
    "wof:placetype":"postalcode"
},
  "geometry": {"coordinates":[-0.75973927176191,51.24930192805115],"type":"Point"}
}