{
  "type": "Feature",
  "properties": {
    "iso:country": "GB",
    "wof:name": "RG20 4HA",
    "wof:placetype": "postalcode"
  },
  "geometry": {"coordinates":[-1.308922,51.361141],"type":"Point"}
}
