{
  "type": "Feature",
  "properties": {
    "iso:country":"GB",
    "wof:name":"RG20 4HA",
    "wof:placetype":"postalcode"
},
  "geometry": {"coordinates":[-1.30892170018209,51.36114064582038],"type":"Point"}
}