{
  "type": "Feature",
  "properties": {
    "iso:country":"GB",
    "wof:name":"WF9 3LS",
    "wof:placetype":"postalcode"
},
  "geometry": {"coordinates":[-1.3281984522522,53.59319476193578],"type":"Point"}
}