{
  "type": "Feature",
  "properties": {
    "iso:country": "GB",
    "wof:name": "BR6 9JH",
    "wof:placetype": "postalcode"
  },
  "geometry": {"coordinates":[0.097245,51.37126],"type":"Point"}
}
