{
  "type": "Feature",
  "properties": {
    "iso:country":"GB",
    "wof:name":"LL77 7TJ",
    "wof:placetype":"postalcode"
},
  "geometry": {"coordinates":[-4.30991600273712,53.26162288503014],"type":"Point"}
}