{
  "type": "Feature",
  "properties": {
    "date:inception_lower": "1980-01-01",
    "date:inception_upper": "1980-01-01",
    "iso:country": "GB",
    "wof:name": "LL77 7TJ",
    "wof:placetype": "postalcode"
  },
  "geometry": {"coordinates":[-4.309916,53.261623],"type":"Point"}
}
