{
  "type": "Feature",
  "properties": {
    "iso:country":"GB",
    "wof:name":"BH9 2JE",
    "wof:placetype":"postalcode"
},
  "geometry": {"coordinates":[-1.88886615683783,50.74163159642845],"type":"Point"}
}