{
  "type": "Feature",
  "properties": {
    "iso:country":"GB",
    "wof:name":"N7 0QJ",
    "wof:placetype":"postalcode"
},
  "geometry": {"coordinates":[-0.13138153310903,51.55324604859589],"type":"Point"}
}