{
  "type": "Feature",
  "properties": {
    "iso:country":"GB",
    "wof:name":"EH32 9AP",
    "wof:placetype":"postalcode"
},
  "geometry": {"coordinates":[-2.97766320374669,55.96122369451363],"type":"Point"}
}