{
  "type": "Feature",
  "properties": {
    "iso:country":"GB",
    "wof:name":"TN25 6DW",
    "wof:placetype":"postalcode"
},
  "geometry": {"coordinates":[1.0416803835365,51.1080509362484],"type":"Point"}
}