{
  "type": "Feature",
  "properties": {
    "date:inception_lower":"1980-01-01",
    "date:inception_upper":"1980-01-31",
    "iso:country":"GB",
    "wof:name":"TN25 6DW",
    "wof:placetype":"postalcode"
},
  "geometry": {"coordinates":[1.04168,51.108051],"type":"Point"}
}