{
  "type": "Feature",
  "properties": {
    "iso:country":"GB",
    "wof:name":"HU17 9JL",
    "wof:placetype":"postalcode"
},
  "geometry": {"coordinates":[-0.42557883710139,53.8459285855814],"type":"Point"}
}