{
  "type": "Feature",
  "properties": {
    "iso:country": "GB",
    "wof:name": "HU17 9JL",
    "wof:placetype": "postalcode"
  },
  "geometry": {"coordinates":[-0.425579,53.845929],"type":"Point"}
}
