{
  "type": "Feature",
  "properties": {
    "iso:country":"GB",
    "wof:name":"KA25 6HF",
    "wof:placetype":"postalcode"
},
  "geometry": {"coordinates":[-4.69238831669126,55.75013545683802],"type":"Point"}
}