{
  "type": "Feature",
  "properties": {
    "date:inception_lower": "2023-06-01",
    "date:inception_upper": "2023-06-01",
    "iso:country": "GB",
    "wof:name": "NR9 3RT",
    "wof:placetype": "postalcode"
  },
  "geometry": {"coordinates":[1.185263,52.608233],"type":"Point"}
}
