{
  "type": "Feature",
  "properties": {
    "iso:country":"GB",
    "wof:name":"S62 5LP",
    "wof:placetype":"postalcode"
},
  "geometry": {"coordinates":[-1.32293484167044,53.46676820834293],"type":"Point"}
}