{
  "type": "Feature",
  "properties": {
    "iso:country":"GB",
    "wof:name":"N11 1QD",
    "wof:placetype":"postalcode"
},
  "geometry": {"coordinates":[-0.1352509728873,51.61203708582497],"type":"Point"}
}