{
  "type": "Feature",
  "properties": {
    "date:inception_lower": "1980-01-01",
    "date:inception_upper": "1980-01-01",
    "iso:country": "GB",
    "wof:name": "N11 1QD",
    "wof:placetype": "postalcode"
  },
  "geometry": {"coordinates":[-0.136153,51.612324],"type":"Point"}
}
