{
  "type": "Feature",
  "properties": {
    "iso:country":"GB",
    "wof:name":"DE12 6DL",
    "wof:placetype":"postalcode"
},
  "geometry": {"coordinates":[-1.5247683842756,52.738923181945],"type":"Point"}
}