{
  "type": "Feature",
  "properties": {
    "date:inception_lower": "1998-12-01",
    "date:inception_upper": "1998-12-01",
    "iso:country": "GB",
    "wof:name": "DE12 6DL",
    "wof:placetype": "postalcode"
  },
  "geometry": {"coordinates":[-1.524768,52.738923],"type":"Point"}
}
