{
  "type": "Feature",
  "properties": {
    "iso:country": "GB",
    "wof:name": "WA8 7PS",
    "wof:placetype": "postalcode"
  },
  "geometry": {"coordinates":[-2.757313,53.372252],"type":"Point"}
}
