{
  "type": "Feature",
  "properties": {
    "date:inception_lower":"1990-08-01",
    "date:inception_upper":"1990-08-31",
    "iso:country":"GB",
    "wof:name":"AB41 8RR",
    "wof:placetype":"postalcode"
},
  "geometry": {"coordinates":[-1.933751,57.348264],"type":"Point"}
}