{
  "type": "Feature",
  "properties": {
    "date:inception_lower": "1980-01-01",
    "date:inception_upper": "1980-01-01",
    "iso:country": "GB",
    "wof:name": "LA2 6JA",
    "wof:placetype": "postalcode"
  },
  "geometry": {"coordinates":[-2.80773,54.090413],"type":"Point"}
}
