{
  "type": "Feature",
  "properties": {
    "iso:country":"GB",
    "wof:name":"LA2 6JA",
    "wof:placetype":"postalcode"
},
  "geometry": {"coordinates":[-2.8077777831936,54.09041176450352],"type":"Point"}
}