{
  "type": "Feature",
  "properties": {
    "iso:country": "GB",
    "wof:name": "PE29 2PE",
    "wof:placetype": "postalcode"
  },
  "geometry": {"coordinates":[-0.158248,52.311011],"type":"Point"}
}
