{
  "type": "Feature",
  "properties": {
    "iso:country":"GB",
    "wof:name":"SA32 7UL",
    "wof:placetype":"postalcode"
},
  "geometry": {"coordinates":[-4.06014592576639,51.94673105728051],"type":"Point"}
}