{
  "type": "Feature",
  "properties": {
    "iso:country":"GB",
    "wof:name":"BA12 0AP",
    "wof:placetype":"postalcode"
},
  "geometry": {"coordinates":[-2.18086608465061,51.2128381047307],"type":"Point"}
}