{
  "type": "Feature",
  "properties": {
    "iso:country": "GB",
    "wof:name": "IP29 4RS",
    "wof:placetype": "postalcode"
  },
  "geometry": {"coordinates":[0.75314,52.176938],"type":"Point"}
}
