{
  "type": "Feature",
  "properties": {
    "iso:country":"GB",
    "wof:name":"IP29 4RS",
    "wof:placetype":"postalcode"
},
  "geometry": {"coordinates":[0.75313961530414,52.17693846830101],"type":"Point"}
}