{
  "type": "Feature",
  "properties": {
    "iso:country":"GB",
    "wof:name":"B36 0EX",
    "wof:placetype":"postalcode"
},
  "geometry": {"coordinates":[-1.76311493560462,52.50269498980224],"type":"Point"}
}