{
  "type": "Feature",
  "properties": {
    "iso:country":"GB",
    "wof:name":"M29 8QP",
    "wof:placetype":"postalcode"
},
  "geometry": {"coordinates":[-2.46652677717028,53.51683237944403],"type":"Point"}
}