{
  "type": "Feature",
  "properties": {
    "iso:country":"GB",
    "wof:name":"S60 4BW",
    "wof:placetype":"postalcode"
},
  "geometry": {"coordinates":[-1.31583249351098,53.41754172225934],"type":"Point"}
}