{
  "type": "Feature",
  "properties": {
    "iso:country": "GB",
    "wof:name": "NG15 6NY",
    "wof:placetype": "postalcode"
  },
  "geometry": {"coordinates":[-1.231021,53.033391],"type":"Point"}
}
