{
  "type": "Feature",
  "properties": {
    "iso:country":"GB",
    "wof:name":"KT3 6AT",
    "wof:placetype":"postalcode"
},
  "geometry": {"coordinates":[-0.25273928822245,51.38958322091218],"type":"Point"}
}