{
  "type": "Feature",
  "properties": {
    "iso:country":"GB",
    "wof:name":"IG5 0XQ",
    "wof:placetype":"postalcode"
},
  "geometry": {"coordinates":[0.07097362444644,51.59775250920403],"type":"Point"}
}