{
  "type": "Feature",
  "properties": {
    "iso:country":"GB",
    "wof:name":"B72 1EB",
    "wof:placetype":"postalcode"
},
  "geometry": {"coordinates":[-1.82433377395652,52.54493722969514],"type":"Point"}
}