{
  "type": "Feature",
  "properties": {
    "iso:country":"GB",
    "wof:name":"CT2 7DA",
    "wof:placetype":"postalcode"
},
  "geometry": {"coordinates":[1.08449095303322,51.29487323720869],"type":"Point"}
}