{
  "type": "Feature",
  "properties": {
    "iso:country": "GB",
    "wof:name": "CT2 7DA",
    "wof:placetype": "postalcode"
  },
  "geometry": {"coordinates":[1.084491,51.294873],"type":"Point"}
}
