{
  "type": "Feature",
  "properties": {
    "date:inception_lower": "1981-06-01",
    "date:inception_upper": "1981-06-01",
    "iso:country": "GB",
    "wof:name": "TF3 2LN",
    "wof:placetype": "postalcode"
  },
  "geometry": {"coordinates":[-2.435751,52.660512],"type":"Point"}
}
