{
  "type": "Feature",
  "properties": {
    "iso:country": "GB",
    "wof:name": "TF3 2LN",
    "wof:placetype": "postalcode"
  },
  "geometry": {"coordinates":[-2.435751,52.660512],"type":"Point"}
}
