{
  "type": "Feature",
  "properties": {
    "date:inception_lower": "1997-12-01",
    "date:inception_upper": "1997-12-01",
    "iso:country": "GB",
    "wof:name": "LN11 0WA",
    "wof:placetype": "postalcode"
  },
  "geometry": {"coordinates":[-0.007775,53.383151],"type":"Point"}
}
