{
  "type": "Feature",
  "properties": {
    "iso:country":"GB",
    "wof:name":"HA3 9EN",
    "wof:placetype":"postalcode"
},
  "geometry": {"coordinates":[-0.29962683749985,51.5904430179611],"type":"Point"}
}