{
  "type": "Feature",
  "properties": {
    "date:inception_lower":"1980-01-01",
    "date:inception_upper":"1980-01-31",
    "iso:country":"GB",
    "wof:name":"CV5 6AY",
    "wof:placetype":"postalcode"
},
  "geometry": {"coordinates":[-1.543949,52.394488],"type":"Point"}
}