{
  "type": "Feature",
  "properties": {
    "iso:country":"GB",
    "wof:name":"BA4 4QG",
    "wof:placetype":"postalcode"
},
  "geometry": {"coordinates":[-2.50552798972416,51.18615015969248],"type":"Point"}
}