{
  "type": "Feature",
  "properties": {
    "iso:country": "GB",
    "wof:name": "LN1 1EQ",
    "wof:placetype": "postalcode"
  },
  "geometry": {"coordinates":[-0.560797,53.246395],"type":"Point"}
}
