{
  "type": "Feature",
  "properties": {
    "iso:country":"GB",
    "wof:name":"LN1 1EQ",
    "wof:placetype":"postalcode"
},
  "geometry": {"coordinates":[-0.56079724474519,53.24639523365235],"type":"Point"}
}