{
  "type": "Feature",
  "properties": {
    "iso:country": "GB",
    "wof:name": "TW18 3JH",
    "wof:placetype": "postalcode"
  },
  "geometry": {"coordinates":[-0.515108,51.431014],"type":"Point"}
}
