{
  "type": "Feature",
  "properties": {
    "iso:country":"GB",
    "wof:name":"PR8 1DF",
    "wof:placetype":"postalcode"
},
  "geometry": {"coordinates":[-3.00459203651715,53.646265755252],"type":"Point"}
}