{
  "type": "Feature",
  "properties": {
    "iso:country":"GB",
    "wof:name":"SE13 7DB",
    "wof:placetype":"postalcode"
},
  "geometry": {"coordinates":[-0.02257699535601,51.46167997966119],"type":"Point"}
}