{
  "type": "Feature",
  "properties": {
    "date:inception_lower":"1990-02-01",
    "date:inception_upper":"1990-02-28",
    "iso:country":"GB",
    "wof:name":"DT9 6DY",
    "wof:placetype":"postalcode"
},
  "geometry": {"coordinates":[-2.535743,50.94363],"type":"Point"}
}