{
  "type": "Feature",
  "properties": {
    "iso:country":"GB",
    "wof:name":"DT9 6DY",
    "wof:placetype":"postalcode"
},
  "geometry": {"coordinates":[-2.53574319253634,50.94363038184044],"type":"Point"}
}