{
  "type": "Feature",
  "properties": {
    "iso:country": "GB",
    "wof:name": "FY7 6UN",
    "wof:placetype": "postalcode"
  },
  "geometry": {"coordinates":[-3.011857,53.922625],"type":"Point"}
}
