{
  "type": "Feature",
  "properties": {
    "iso:country":"GB",
    "wof:name":"YO10 3JP",
    "wof:placetype":"postalcode"
},
  "geometry": {"coordinates":[-1.05631285328154,53.95403127590399],"type":"Point"}
}