{
  "type": "Feature",
  "properties": {
    "iso:country":"GB",
    "wof:name":"EN3 6TL",
    "wof:placetype":"postalcode"
},
  "geometry": {"coordinates":[-0.03946270832967,51.68070727045605],"type":"Point"}
}