{
  "type": "Feature",
  "properties": {
    "iso:country":"GB",
    "wof:name":"EN5 2PP",
    "wof:placetype":"postalcode"
},
  "geometry": {"coordinates":[-0.20763382902798,51.64336965086567],"type":"Point"}
}