{
  "type": "Feature",
  "properties": {
    "iso:country":"GB",
    "wof:name":"PE31 7HF",
    "wof:placetype":"postalcode"
},
  "geometry": {"coordinates":[0.49187219640866,52.9115020157002],"type":"Point"}
}