{
  "type": "Feature",
  "properties": {
    "date:inception_lower":"2018-07-01",
    "date:inception_upper":"2018-07-31",
    "iso:country":"GB",
    "wof:name":"NG9 2PB",
    "wof:placetype":"postalcode"
},
  "geometry": {"coordinates":[-1.216936,52.928961],"type":"Point"}
}