{
  "type": "Feature",
  "properties": {
    "iso:country": "GB",
    "wof:name": "G52 4FD",
    "wof:placetype": "postalcode"
  },
  "geometry": {"coordinates":[-4.373543,55.852054],"type":"Point"}
}
