{
  "type": "Feature",
  "properties": {
    "iso:country":"GB",
    "wof:name":"G52 4FD",
    "wof:placetype":"postalcode"
},
  "geometry": {"coordinates":[-4.37354317421141,55.85205418446789],"type":"Point"}
}