{
  "type": "Feature",
  "properties": {
    "date:inception_lower": "2006-08-01",
    "date:inception_upper": "2006-08-01",
    "iso:country": "GB",
    "wof:name": "G52 4FD",
    "wof:placetype": "postalcode"
  },
  "geometry": {"coordinates":[-4.373543,55.852054],"type":"Point"}
}
