{
  "type": "Feature",
  "properties": {
    "iso:country":"GB",
    "wof:name":"SS8 8LJ",
    "wof:placetype":"postalcode"
},
  "geometry": {"coordinates":[0.611403697028,51.52105610993977],"type":"Point"}
}