{
  "type": "Feature",
  "properties": {
    "date:inception_lower": "2020-11-01",
    "date:inception_upper": "2020-11-01",
    "iso:country": "GB",
    "wof:name": "MK40 4UJ",
    "wof:placetype": "postalcode"
  },
  "geometry": {"coordinates":[-0.50292,52.146578],"type":"Point"}
}
