{
  "type": "Feature",
  "properties": {
    "iso:country":"GB",
    "wof:name":"YO32 3LY",
    "wof:placetype":"postalcode"
},
  "geometry": {"coordinates":[-1.0634934023638,54.01645547336364],"type":"Point"}
}