{
  "type": "Feature",
  "properties": {
    "iso:country":"GB",
    "wof:name":"G82 2AG",
    "wof:placetype":"postalcode"
},
  "geometry": {"coordinates":[-4.56363240986861,55.95070362611143],"type":"Point"}
}