{
  "type": "Feature",
  "properties": {
    "date:inception_lower": "1980-01-01",
    "date:inception_upper": "1980-01-01",
    "iso:country": "GB",
    "wof:name": "SY8 4HT",
    "wof:placetype": "postalcode"
  },
  "geometry": {"coordinates":[-2.745863,52.299228],"type":"Point"}
}
