{
  "type": "Feature",
  "properties": {
    "iso:country": "GB",
    "wof:name": "SY8 4HT",
    "wof:placetype": "postalcode"
  },
  "geometry": {"coordinates":[-2.745863,52.299228],"type":"Point"}
}
