{
  "type": "Feature",
  "properties": {
    "iso:country": "GB",
    "wof:name": "CV35 0QR",
    "wof:placetype": "postalcode"
  },
  "geometry": {"coordinates":[-1.539152,52.109676],"type":"Point"}
}
