{
  "type": "Feature",
  "properties": {
    "iso:country":"GB",
    "wof:name":"TW16 5DX",
    "wof:placetype":"postalcode"
},
  "geometry": {"coordinates":[-0.41176424057104,51.41809522186006],"type":"Point"}
}