{
  "type": "Feature",
  "properties": {
    "iso:country": "GB",
    "wof:name": "E1 8PU",
    "wof:placetype": "postalcode"
  },
  "geometry": {"coordinates":[-0.070235,51.513705],"type":"Point"}
}
