{
  "type": "Feature",
  "properties": {
    "iso:country": "GB",
    "wof:name": "E11 4AY",
    "wof:placetype": "postalcode"
  },
  "geometry": {"coordinates":[0.00446,51.560194],"type":"Point"}
}
