{
  "type": "Feature",
  "properties": {
    "iso:country":"GB",
    "wof:name":"E11 4AY",
    "wof:placetype":"postalcode"
},
  "geometry": {"coordinates":[0.00445963750824,51.56019428239068],"type":"Point"}
}