{
  "type": "Feature",
  "properties": {
    "date:inception_lower":"1992-08-01",
    "date:inception_upper":"1992-08-31",
    "iso:country":"GB",
    "wof:name":"SK10 2LU",
    "wof:placetype":"postalcode"
},
  "geometry": {"coordinates":[-2.116872,53.271893],"type":"Point"}
}