{
  "type": "Feature",
  "properties": {
    "iso:country":"GB",
    "wof:name":"SK10 2LU",
    "wof:placetype":"postalcode"
},
  "geometry": {"coordinates":[-2.11860023972482,53.27242237436514],"type":"Point"}
}