{
  "type": "Feature",
  "properties": {
    "iso:country":"GB",
    "wof:name":"AB53 4UA",
    "wof:placetype":"postalcode"
},
  "geometry": {"coordinates":[-2.47314838094994,57.54610676183347],"type":"Point"}
}