{
  "type": "Feature",
  "properties": {
    "iso:country":"GB",
    "wof:name":"NR2 4DG",
    "wof:placetype":"postalcode"
},
  "geometry": {"coordinates":[1.26358695432581,52.63764215000877],"type":"Point"}
}