{
  "type": "Feature",
  "properties": {
    "iso:country": "GB",
    "wof:name": "SN16 0NN",
    "wof:placetype": "postalcode"
  },
  "geometry": {"coordinates":[-2.212758,51.574851],"type":"Point"}
}
