{
  "type": "Feature",
  "properties": {
    "iso:country":"GB",
    "wof:name":"BD16 3HW",
    "wof:placetype":"postalcode"
},
  "geometry": {"coordinates":[-1.8444134757021,53.86289464532216],"type":"Point"}
}