{
  "type": "Feature",
  "properties": {
    "date:inception_lower": "2008-10-01",
    "date:inception_upper": "2008-10-01",
    "iso:country": "GB",
    "wof:name": "BD16 3HW",
    "wof:placetype": "postalcode"
  },
  "geometry": {"coordinates":[-1.844413,53.862895],"type":"Point"}
}
