{
  "type": "Feature",
  "properties": {
    "iso:country":"GB",
    "wof:name":"M22 5JS",
    "wof:placetype":"postalcode"
},
  "geometry": {"coordinates":[-2.2480962912559,53.37318405067036],"type":"Point"}
}