{
  "type": "Feature",
  "properties": {
    "iso:country":"GB",
    "wof:name":"M9 6HT",
    "wof:placetype":"postalcode"
},
  "geometry": {"coordinates":[-2.19603505747102,53.5307773879457],"type":"Point"}
}