{
  "type": "Feature",
  "properties": {
    "iso:country": "GB",
    "wof:name": "EX16 9DW",
    "wof:placetype": "postalcode"
  },
  "geometry": {"coordinates":[-3.55321,50.981645],"type":"Point"}
}
