{
  "type": "Feature",
  "properties": {
    "date:inception_lower": "2024-01-01",
    "date:inception_upper": "2024-01-01",
    "iso:country": "GB",
    "wof:name": "PL8 1DU",
    "wof:placetype": "postalcode"
  },
  "geometry": {"coordinates":[-3.951463,50.335507],"type":"Point"}
}
