{
  "type": "Feature",
  "properties": {
    "date:inception_lower":"1999-12-01",
    "date:inception_upper":"1999-12-31",
    "iso:country":"GB",
    "wof:name":"DG5 4XL",
    "wof:placetype":"postalcode"
},
  "geometry": {"coordinates":[-3.783535,54.861843],"type":"Point"}
}