{
  "type": "Feature",
  "properties": {
    "iso:country":"GB",
    "wof:name":"DG5 4XL",
    "wof:placetype":"postalcode"
},
  "geometry": {"coordinates":[-3.78353553926839,54.86184284230085],"type":"Point"}
}