{
  "type": "Feature",
  "properties": {
    "iso:country": "GB",
    "wof:name": "OX2 8HD",
    "wof:placetype": "postalcode"
  },
  "geometry": {"coordinates":[-1.26113,51.808201],"type":"Point"}
}
