{
  "type": "Feature",
  "properties": {
    "iso:country":"GB",
    "wof:name":"OX2 8HD",
    "wof:placetype":"postalcode"
},
  "geometry": {"coordinates":[-1.26114810800045,51.80819447345821],"type":"Point"}
}