{
  "type": "Feature",
  "properties": {
    "date:inception_lower": "1980-01-01",
    "date:inception_upper": "1980-01-01",
    "iso:country": "GB",
    "wof:name": "OX2 8HD",
    "wof:placetype": "postalcode"
  },
  "geometry": {"coordinates":[-1.259426,51.80775],"type":"Point"}
}
