{
  "type": "Feature",
  "properties": {
    "iso:country":"GB",
    "wof:name":"OL9 0DQ",
    "wof:placetype":"postalcode"
},
  "geometry": {"coordinates":[-2.13900400562721,53.5474229428621],"type":"Point"}
}