{
  "type": "Feature",
  "properties": {
    "iso:country":"GB",
    "wof:name":"DD5 3HT",
    "wof:placetype":"postalcode"
},
  "geometry": {"coordinates":[-2.86255590374374,56.47798720774389],"type":"Point"}
}