{
  "type": "Feature",
  "properties": {
    "iso:country":"GB",
    "wof:name":"CV7 8EE",
    "wof:placetype":"postalcode"
},
  "geometry": {"coordinates":[-1.60205626635192,52.49251820979373],"type":"Point"}
}