{
  "type": "Feature",
  "properties": {
    "iso:country":"GB",
    "wof:name":"LE1 4FB",
    "wof:placetype":"postalcode"
},
  "geometry": {"coordinates":[-1.13379348880244,52.636286725155],"type":"Point"}
}