{
  "type": "Feature",
  "properties": {
    "date:inception_lower": "2018-10-01",
    "date:inception_upper": "2018-10-01",
    "iso:country": "GB",
    "wof:name": "PA3 2DQ",
    "wof:placetype": "postalcode"
  },
  "geometry": {"coordinates":[-4.428152,55.853014],"type":"Point"}
}
