{
  "type": "Feature",
  "properties": {
    "iso:country": "GB",
    "wof:name": "PA3 2DQ",
    "wof:placetype": "postalcode"
  },
  "geometry": {"coordinates":[-4.428152,55.853014],"type":"Point"}
}
