{
  "type": "Feature",
  "properties": {
    "date:inception_lower": "2007-09-01",
    "date:inception_upper": "2007-09-01",
    "iso:country": "GB",
    "wof:name": "HU9 3DF",
    "wof:placetype": "postalcode"
  },
  "geometry": {"coordinates":[-0.28839,53.759804],"type":"Point"}
}
