{
  "type": "Feature",
  "properties": {
    "iso:country":"GB",
    "wof:name":"HU9 3DF",
    "wof:placetype":"postalcode"
},
  "geometry": {"coordinates":[-0.2883897875044,53.75980357292816],"type":"Point"}
}