{
  "type": "Feature",
  "properties": {
    "iso:country":"GB",
    "wof:name":"PO5 1RN",
    "wof:placetype":"postalcode"
},
  "geometry": {"coordinates":[-1.07982711796858,50.78990858036053],"type":"Point"}
}