{
  "type": "Feature",
  "properties": {
    "date:inception_lower":"1995-01-01",
    "date:inception_upper":"1995-01-31",
    "iso:country":"GB",
    "wof:name":"SA7 9SH",
    "wof:placetype":"postalcode"
},
  "geometry": {"coordinates":[-3.879438,51.655587],"type":"Point"}
}