{
  "type": "Feature",
  "properties": {
    "iso:country":"GB",
    "wof:name":"SA7 9SH",
    "wof:placetype":"postalcode"
},
  "geometry": {"coordinates":[-3.87943755454292,51.65558715193532],"type":"Point"}
}