{
  "type": "Feature",
  "properties": {
    "date:inception_lower": "2017-04-01",
    "date:inception_upper": "2017-04-01",
    "iso:country": "GB",
    "wof:name": "NN16 9WA",
    "wof:placetype": "postalcode"
  },
  "geometry": {"coordinates":[-0.710599,52.407879],"type":"Point"}
}
