{
  "type": "Feature",
  "properties": {
    "iso:country":"GB",
    "wof:name":"DY1 2UZ",
    "wof:placetype":"postalcode"
},
  "geometry": {"coordinates":[-2.11336782634726,52.51683833420856],"type":"Point"}
}