{
  "type": "Feature",
  "properties": {
    "date:inception_lower": "1990-02-01",
    "date:inception_upper": "1990-02-01",
    "iso:country": "GB",
    "wof:name": "DY1 2UZ",
    "wof:placetype": "postalcode"
  },
  "geometry": {"coordinates":[-2.113377,52.516871],"type":"Point"}
}
