{
  "type": "Feature",
  "properties": {
    "iso:country": "GB",
    "wof:name": "BL3 3SW",
    "wof:placetype": "postalcode"
  },
  "geometry": {"coordinates":[-2.463151,53.558516],"type":"Point"}
}
