{
  "type": "Feature",
  "properties": {
    "iso:country":"GB",
    "wof:name":"BL3 3SW",
    "wof:placetype":"postalcode"
},
  "geometry": {"coordinates":[-2.46315109067341,53.55851589323007],"type":"Point"}
}