{
  "type": "Feature",
  "properties": {
    "iso:country": "GB",
    "wof:name": "M14 5WE",
    "wof:placetype": "postalcode"
  },
  "geometry": {"coordinates":[-2.22676,53.450744],"type":"Point"}
}
