{
  "type": "Feature",
  "properties": {
    "iso:country":"GB",
    "wof:name":"M14 5WE",
    "wof:placetype":"postalcode"
},
  "geometry": {"coordinates":[-2.22675981371554,53.45070791205843],"type":"Point"}
}