{
  "type": "Feature",
  "properties": {
    "iso:country":"GB",
    "wof:name":"LA23 1PQ",
    "wof:placetype":"postalcode"
},
  "geometry": {"coordinates":[-2.91290268656231,54.41827460813336],"type":"Point"}
}