{
  "type": "Feature",
  "properties": {
    "iso:country":"GB",
    "wof:name":"M24 5DA",
    "wof:placetype":"postalcode"
},
  "geometry": {"coordinates":[-2.19807349568246,53.55699305526681],"type":"Point"}
}