{
  "type": "Feature",
  "properties": {
    "date:inception_lower":"2001-12-01",
    "date:inception_upper":"2001-12-31",
    "iso:country":"GB",
    "wof:name":"TS15 0BZ",
    "wof:placetype":"postalcode"
},
  "geometry": {"coordinates":[-1.278597,54.449106],"type":"Point"}
}