{
  "type": "Feature",
  "properties": {
    "iso:country":"GB",
    "wof:name":"TS15 0BZ",
    "wof:placetype":"postalcode"
},
  "geometry": {"coordinates":[-1.27855114851696,54.44909639760672],"type":"Point"}
}