{
  "type": "Feature",
  "properties": {
    "iso:country": "GB",
    "wof:name": "G14 9EH",
    "wof:placetype": "postalcode"
  },
  "geometry": {"coordinates":[-4.349328,55.881019],"type":"Point"}
}
