{
  "type": "Feature",
  "properties": {
    "iso:country":"GB",
    "wof:name":"CV4 9QN",
    "wof:placetype":"postalcode"
},
  "geometry": {"coordinates":[-1.5817511610069,52.40957782136944],"type":"Point"}
}