{
  "type": "Feature",
  "properties": {
    "iso:country":"GB",
    "wof:name":"RG7 1NS",
    "wof:placetype":"postalcode"
},
  "geometry": {"coordinates":[-0.97698656749773,51.41244013857319],"type":"Point"}
}