{
  "type": "Feature",
  "properties": {
    "iso:country":"GB",
    "wof:name":"SM3 9TP",
    "wof:placetype":"postalcode"
},
  "geometry": {"coordinates":[-0.21774226102473,51.36994684860347],"type":"Point"}
}