{
  "type": "Feature",
  "properties": {
    "date:inception_lower":"1980-01-01",
    "date:inception_upper":"1980-01-31",
    "iso:country":"GB",
    "wof:name":"BN1 5PB",
    "wof:placetype":"postalcode"
},
  "geometry": {"coordinates":[-0.151656,50.8363],"type":"Point"}
}