{
  "type": "Feature",
  "properties": {
    "iso:country": "GB",
    "wof:name": "BN1 5PB",
    "wof:placetype": "postalcode"
  },
  "geometry": {"coordinates":[-0.151656,50.8363],"type":"Point"}
}
