{
  "type": "Feature",
  "properties": {
    "iso:country":"GB",
    "wof:name":"BN1 5PB",
    "wof:placetype":"postalcode"
},
  "geometry": {"coordinates":[-0.15165645606407,50.83629969540289],"type":"Point"}
}