{
  "type": "Feature",
  "properties": {
    "iso:country":"GB",
    "wof:name":"PO37 7AR",
    "wof:placetype":"postalcode"
},
  "geometry": {"coordinates":[-1.17994973560661,50.63376566325473],"type":"Point"}
}