{
  "type": "Feature",
  "properties": {
    "date:inception_lower": "1980-01-01",
    "date:inception_upper": "1980-01-01",
    "iso:country": "GB",
    "wof:name": "CV10 7NF",
    "wof:placetype": "postalcode"
  },
  "geometry": {"coordinates":[-1.509768,52.515662],"type":"Point"}
}
