{
  "type": "Feature",
  "properties": {
    "iso:country":"GB",
    "wof:name":"CV10 7NF",
    "wof:placetype":"postalcode"
},
  "geometry": {"coordinates":[-1.50937834011918,52.51564334781432],"type":"Point"}
}