{
  "type": "Feature",
  "properties": {
    "iso:country":"GB",
    "wof:name":"G12 0JW",
    "wof:placetype":"postalcode"
},
  "geometry": {"coordinates":[-4.30320566899068,55.88651959252664],"type":"Point"}
}