{
  "type": "Feature",
  "properties": {
    "iso:country":"GB",
    "wof:name":"GU20 6PF",
    "wof:placetype":"postalcode"
},
  "geometry": {"coordinates":[-0.66787770988519,51.37126219067392],"type":"Point"}
}