{
  "type": "Feature",
  "properties": {
    "date:inception_lower": "1980-01-01",
    "date:inception_upper": "1980-01-01",
    "iso:country": "GB",
    "wof:name": "GU20 6PF",
    "wof:placetype": "postalcode"
  },
  "geometry": {"coordinates":[-0.667878,51.371262],"type":"Point"}
}
