{
  "type": "Feature",
  "properties": {
    "iso:country":"GB",
    "wof:name":"DG10 9LT",
    "wof:placetype":"postalcode"
},
  "geometry": {"coordinates":[-3.46646919859515,55.38391662340894],"type":"Point"}
}