{
  "type": "Feature",
  "properties": {
    "date:inception_lower": "1980-01-01",
    "date:inception_upper": "1980-01-01",
    "iso:country": "GB",
    "wof:name": "DG10 9LT",
    "wof:placetype": "postalcode"
  },
  "geometry": {"coordinates":[-3.463531,55.382687],"type":"Point"}
}
