{
  "type": "Feature",
  "properties": {
    "iso:country": "GB",
    "wof:name": "NP12 1PT",
    "wof:placetype": "postalcode"
  },
  "geometry": {"coordinates":[-3.197829,51.668485],"type":"Point"}
}
