{
  "type": "Feature",
  "properties": {
    "iso:country":"GB",
    "wof:name":"NP12 1PT",
    "wof:placetype":"postalcode"
},
  "geometry": {"coordinates":[-3.19782891718769,51.66848512724552],"type":"Point"}
}