{
  "type": "Feature",
  "properties": {
    "iso:country": "GB",
    "wof:name": "EH24 9DD",
    "wof:placetype": "postalcode"
  },
  "geometry": {"coordinates":[-3.144568,55.851777],"type":"Point"}
}
