{
  "type": "Feature",
  "properties": {
    "date:inception_lower":"1999-06-01",
    "date:inception_upper":"1999-06-30",
    "iso:country":"GB",
    "wof:name":"CH41 0DA",
    "wof:placetype":"postalcode"
},
  "geometry": {"coordinates":[-3.052414,53.39691],"type":"Point"}
}