{
  "type": "Feature",
  "properties": {
    "date:inception_lower": "1998-06-01",
    "date:inception_upper": "1998-06-01",
    "iso:country": "GB",
    "wof:name": "NG24 2SP",
    "wof:placetype": "postalcode"
  },
  "geometry": {"coordinates":[-0.720004,53.061848],"type":"Point"}
}
