{
  "type": "Feature",
  "properties": {
    "iso:country":"GB",
    "wof:name":"NG24 2SP",
    "wof:placetype":"postalcode"
},
  "geometry": {"coordinates":[-0.72000445203894,53.06184830695103],"type":"Point"}
}