{
  "type": "Feature",
  "properties": {
    "date:inception_lower": "2022-08-01",
    "date:inception_upper": "2022-08-01",
    "iso:country": "GB",
    "wof:name": "SM1 2EX",
    "wof:placetype": "postalcode"
  },
  "geometry": {"coordinates":[-0.211725,51.367408],"type":"Point"}
}
