{
  "type": "Feature",
  "properties": {
    "date:inception_lower": "2023-02-01",
    "date:inception_upper": "2023-02-01",
    "iso:country": "GB",
    "wof:name": "SM1 2EX",
    "wof:placetype": "postalcode"
  },
  "geometry": {"coordinates":[-0.211666,51.367434],"type":"Point"}
}
