{
  "type": "Feature",
  "properties": {
    "iso:country":"GB",
    "wof:name":"BA14 7LX",
    "wof:placetype":"postalcode"
},
  "geometry": {"coordinates":[-2.19781935639409,51.32681806278984],"type":"Point"}
}