{
  "type": "Feature",
  "properties": {
    "iso:country":"GB",
    "wof:name":"HP2 5RA",
    "wof:placetype":"postalcode"
},
  "geometry": {"coordinates":[-0.45801761170256,51.76466442290261],"type":"Point"}
}