{
  "type": "Feature",
  "properties": {
    "iso:country": "GB",
    "wof:name": "DL2 3EL",
    "wof:placetype": "postalcode"
  },
  "geometry": {"coordinates":[-1.738081,54.549884],"type":"Point"}
}
