{
  "type": "Feature",
  "properties": {
    "date:inception_lower": "1980-01-01",
    "date:inception_upper": "1980-01-01",
    "iso:country": "GB",
    "wof:name": "CF5 2BP",
    "wof:placetype": "postalcode"
  },
  "geometry": {"coordinates":[-3.217887,51.491527],"type":"Point"}
}
