{
  "type": "Feature",
  "properties": {
    "iso:country":"GB",
    "wof:name":"DY14 0NW",
    "wof:placetype":"postalcode"
},
  "geometry": {"coordinates":[-2.57584465296765,52.37824749350514],"type":"Point"}
}