{
  "type": "Feature",
  "properties": {
    "iso:country":"GB",
    "wof:name":"AB10 6AB",
    "wof:placetype":"postalcode"
},
  "geometry": {"coordinates":[-2.11452123336879,57.13476899781346],"type":"Point"}
}