{
  "type": "Feature",
  "properties": {
    "date:inception_lower": "2021-04-01",
    "date:inception_upper": "2021-04-01",
    "iso:country": "GB",
    "wof:name": "YO25 5GG",
    "wof:placetype": "postalcode"
  },
  "geometry": {"coordinates":[-0.425907,54.006295],"type":"Point"}
}
