{
  "type": "Feature",
  "properties": {
    "iso:country":"GB",
    "wof:name":"KA21 5SA",
    "wof:placetype":"postalcode"
},
  "geometry": {"coordinates":[-4.78979771757508,55.64429072503023],"type":"Point"}
}