{
  "type": "Feature",
  "properties": {
    "date:inception_lower": "1980-01-01",
    "date:inception_upper": "1980-01-01",
    "iso:country": "GB",
    "wof:name": "KA21 5SA",
    "wof:placetype": "postalcode"
  },
  "geometry": {"coordinates":[-4.789798,55.644291],"type":"Point"}
}
