{
  "type": "Feature",
  "properties": {
    "iso:country": "GB",
    "wof:name": "CB24 1DD",
    "wof:placetype": "postalcode"
  },
  "geometry": {"coordinates":[0.054485,52.289681],"type":"Point"}
}
