{
  "type": "Feature",
  "properties": {
    "date:inception_lower": "2019-12-01",
    "date:inception_upper": "2019-12-01",
    "iso:country": "GB",
    "wof:name": "CB24 1DD",
    "wof:placetype": "postalcode"
  },
  "geometry": {"coordinates":[0.055868,52.290115],"type":"Point"}
}
