{
  "type": "Feature",
  "properties": {
    "date:inception_lower":"1980-01-01",
    "date:inception_upper":"1980-01-31",
    "iso:country":"GB",
    "wof:name":"SY3 8EU",
    "wof:placetype":"postalcode"
},
  "geometry": {"coordinates":[-2.822344,52.731969],"type":"Point"}
}