{
  "type": "Feature",
  "properties": {
    "iso:country": "GB",
    "wof:name": "SY3 8EU",
    "wof:placetype": "postalcode"
  },
  "geometry": {"coordinates":[-2.822344,52.731969],"type":"Point"}
}
