{
  "type": "Feature",
  "properties": {
    "iso:country":"GB",
    "wof:name":"SY3 8EU",
    "wof:placetype":"postalcode"
},
  "geometry": {"coordinates":[-2.82234441243261,52.73196925502819],"type":"Point"}
}