{
  "type": "Feature",
  "properties": {
    "date:inception_lower": "2024-05-01",
    "date:inception_upper": "2024-05-01",
    "iso:country": "GB",
    "wof:name": "RH14 9ZY",
    "wof:placetype": "postalcode"
  },
  "geometry": {"coordinates":[-0.444437,51.025696],"type":"Point"}
}
