{
  "type": "Feature",
  "properties": {
    "date:inception_lower":"1980-01-01",
    "date:inception_upper":"1980-01-31",
    "iso:country":"GB",
    "wof:name":"BN23 7HG",
    "wof:placetype":"postalcode"
},
  "geometry": {"coordinates":[0.310992,50.798507],"type":"Point"}
}