{
  "type": "Feature",
  "properties": {
    "date:inception_lower": "1980-01-01",
    "date:inception_upper": "1980-01-01",
    "iso:country": "GB",
    "wof:name": "PL9 8JA",
    "wof:placetype": "postalcode"
  },
  "geometry": {"coordinates":[-4.06963,50.363232],"type":"Point"}
}
