{
  "type": "Feature",
  "properties": {
    "iso:country":"GB",
    "wof:name":"PL9 8JA",
    "wof:placetype":"postalcode"
},
  "geometry": {"coordinates":[-4.06963000290778,50.36323189848351],"type":"Point"}
}