{
  "type": "Feature",
  "properties": {
    "iso:country":"GB",
    "wof:name":"DG11 1AA",
    "wof:placetype":"postalcode"
},
  "geometry": {"coordinates":[-3.33117138633015,55.09290454936934],"type":"Point"}
}