{
  "type": "Feature",
  "properties": {
    "date:inception_lower": "1980-01-01",
    "date:inception_upper": "1980-01-01",
    "iso:country": "GB",
    "wof:name": "DN10 6NF",
    "wof:placetype": "postalcode"
  },
  "geometry": {"coordinates":[-1.021052,53.434214],"type":"Point"}
}
