{
  "type": "Feature",
  "properties": {
    "iso:country":"GB",
    "wof:name":"S43 4DX",
    "wof:placetype":"postalcode"
},
  "geometry": {"coordinates":[-1.25843380198724,53.27189438142589],"type":"Point"}
}