{
  "type": "Feature",
  "properties": {
    "date:inception_lower": "2022-04-01",
    "date:inception_upper": "2022-04-01",
    "iso:country": "GB",
    "wof:name": "PR8 5FF",
    "wof:placetype": "postalcode"
  },
  "geometry": {"coordinates":[-2.966168,53.631174],"type":"Point"}
}
