{
  "type": "Feature",
  "properties": {
    "date:inception_lower": "2010-10-01",
    "date:inception_upper": "2010-10-01",
    "iso:country": "GB",
    "wof:name": "KY11 4FB",
    "wof:placetype": "postalcode"
  },
  "geometry": {"coordinates":[-3.416892,56.067619],"type":"Point"}
}
