{
  "type": "Feature",
  "properties": {
    "iso:country":"GB",
    "wof:name":"KY11 4FB",
    "wof:placetype":"postalcode"
},
  "geometry": {"coordinates":[-3.41689483373711,56.06762339628224],"type":"Point"}
}