{
  "type": "Feature",
  "properties": {
    "iso:country": "GB",
    "wof:name": "WD3 5HF",
    "wof:placetype": "postalcode"
  },
  "geometry": {"coordinates":[-0.517858,51.64801],"type":"Point"}
}
