{
  "type": "Feature",
  "properties": {
    "iso:country":"GB",
    "wof:name":"WD3 5HF",
    "wof:placetype":"postalcode"
},
  "geometry": {"coordinates":[-0.51785850114543,51.6480097061964],"type":"Point"}
}