{
  "type": "Feature",
  "properties": {
    "iso:country":"GB",
    "wof:name":"EX8 4SB",
    "wof:placetype":"postalcode"
},
  "geometry": {"coordinates":[-3.38592929631071,50.62867335232109],"type":"Point"}
}