{
  "type": "Feature",
  "properties": {
    "iso:country": "GB",
    "wof:name": "PR2 1RH",
    "wof:placetype": "postalcode"
  },
  "geometry": {"coordinates":[-2.763335,53.764258],"type":"Point"}
}
