{
  "type": "Feature",
  "properties": {
    "iso:country":"GB",
    "wof:name":"RM1 4AZ",
    "wof:placetype":"postalcode"
},
  "geometry": {"coordinates":[0.17837071093297,51.59920738844788],"type":"Point"}
}