{
  "type": "Feature",
  "properties": {
    "iso:country":"GB",
    "wof:name":"RG1 2LU",
    "wof:placetype":"postalcode"
},
  "geometry": {"coordinates":[-0.9724357698607,51.45187473093563],"type":"Point"}
}