{
  "type": "Feature",
  "properties": {
    "iso:country":"GB",
    "wof:name":"PR1 4SQ",
    "wof:placetype":"postalcode"
},
  "geometry": {"coordinates":[-2.67443725420594,53.76322702873404],"type":"Point"}
}