{
  "type": "Feature",
  "properties": {
    "date:inception_lower": "1998-12-01",
    "date:inception_upper": "1998-12-01",
    "iso:country": "GB",
    "wof:name": "IV63 6UW",
    "wof:placetype": "postalcode"
  },
  "geometry": {"coordinates":[-4.480039,57.32582],"type":"Point"}
}
