{
  "type": "Feature",
  "properties": {
    "iso:country":"GB",
    "wof:name":"IV63 6UW",
    "wof:placetype":"postalcode"
},
  "geometry": {"coordinates":[-4.47979707878876,57.32592332122719],"type":"Point"}
}