{
  "type": "Feature",
  "properties": {
    "date:inception_lower":"1980-01-01",
    "date:inception_upper":"1980-01-31",
    "iso:country":"GB",
    "wof:name":"TA21 8NF",
    "wof:placetype":"postalcode"
},
  "geometry": {"coordinates":[-3.234126,50.977914],"type":"Point"}
}