{
  "type": "Feature",
  "properties": {
    "iso:country":"GB",
    "wof:name":"HA5 3UJ",
    "wof:placetype":"postalcode"
},
  "geometry": {"coordinates":[-0.3979278317578,51.60218482825436],"type":"Point"}
}