{
  "type": "Feature",
  "properties": {
    "iso:country":"GB",
    "wof:name":"BA1 5SX",
    "wof:placetype":"postalcode"
},
  "geometry": {"coordinates":[-2.36358932467256,51.39282428927146],"type":"Point"}
}