{
  "type": "Feature",
  "properties": {
    "date:inception_lower": "1980-01-01",
    "date:inception_upper": "1980-01-01",
    "iso:country": "GB",
    "wof:name": "BA1 5SX",
    "wof:placetype": "postalcode"
  },
  "geometry": {"coordinates":[-2.364313,51.3937],"type":"Point"}
}
