{
  "type": "Feature",
  "properties": {
    "iso:country":"GB",
    "wof:name":"TA2 6SB",
    "wof:placetype":"postalcode"
},
  "geometry": {"coordinates":[-3.15082498694057,51.02748609419601],"type":"Point"}
}