{
  "type": "Feature",
  "properties": {
    "iso:country": "GB",
    "wof:name": "TA2 6SB",
    "wof:placetype": "postalcode"
  },
  "geometry": {"coordinates":[-3.150825,51.027486],"type":"Point"}
}
