{
  "type": "Feature",
  "properties": {
    "iso:country":"GB",
    "wof:name":"WN6 7RZ",
    "wof:placetype":"postalcode"
},
  "geometry": {"coordinates":[-2.65695338692041,53.55742828409328],"type":"Point"}
}