{
  "type": "Feature",
  "properties": {
    "iso:country":"GB",
    "wof:name":"PA16 8LJ",
    "wof:placetype":"postalcode"
},
  "geometry": {"coordinates":[-4.76932406480298,55.95026749584805],"type":"Point"}
}