{
  "type": "Feature",
  "properties": {
    "iso:country":"GB",
    "wof:name":"TQ3 3DE",
    "wof:placetype":"postalcode"
},
  "geometry": {"coordinates":[-3.57260275148378,50.4371579454974],"type":"Point"}
}