{
  "type": "Feature",
  "properties": {
    "iso:country":"GB",
    "wof:name":"NE34 6AF",
    "wof:placetype":"postalcode"
},
  "geometry": {"coordinates":[-1.41205158842985,54.97770036824851],"type":"Point"}
}