{
  "type": "Feature",
  "properties": {
    "date:inception_lower": "1980-01-01",
    "date:inception_upper": "1980-01-01",
    "iso:country": "GB",
    "wof:name": "L8 6RW",
    "wof:placetype": "postalcode"
  },
  "geometry": {"coordinates":[-2.9754,53.3839],"type":"Point"}
}
