{
  "type": "Feature",
  "properties": {
    "iso:country":"GB",
    "wof:name":"CF40 2LQ",
    "wof:placetype":"postalcode"
},
  "geometry": {"coordinates":[-3.45210005945428,51.62594362262257],"type":"Point"}
}