{
  "type": "Feature",
  "properties": {
    "date:inception_lower": "2014-07-01",
    "date:inception_upper": "2014-07-01",
    "iso:country": "GB",
    "wof:name": "CF40 2LQ",
    "wof:placetype": "postalcode"
  },
  "geometry": {"coordinates":[-3.452147,51.626162],"type":"Point"}
}
