{
  "type": "Feature",
  "properties": {
    "date:inception_lower": "2005-05-01",
    "date:inception_upper": "2005-05-01",
    "iso:country": "GB",
    "wof:name": "G33 6FE",
    "wof:placetype": "postalcode"
  },
  "geometry": {"coordinates":[-4.136457,55.888665],"type":"Point"}
}
