{
  "type": "Feature",
  "properties": {
    "iso:country":"GB",
    "wof:name":"LS22 7TQ",
    "wof:placetype":"postalcode"
},
  "geometry": {"coordinates":[-1.38195890372434,53.93498065630357],"type":"Point"}
}