{
  "type": "Feature",
  "properties": {
    "date:inception_lower": "1980-01-01",
    "date:inception_upper": "1980-01-01",
    "iso:country": "GB",
    "wof:name": "GL6 8PB",
    "wof:placetype": "postalcode"
  },
  "geometry": {"coordinates":[-2.165948,51.711908],"type":"Point"}
}
