{
  "type": "Feature",
  "properties": {
    "date:inception_lower": "1980-01-01",
    "date:inception_upper": "1980-01-01",
    "iso:country": "GB",
    "wof:name": "UB10 8TF",
    "wof:placetype": "postalcode"
  },
  "geometry": {"coordinates":[-0.449134,51.557993],"type":"Point"}
}
