{
  "type": "Feature",
  "properties": {
    "iso:country": "GB",
    "wof:name": "OX18 4NG",
    "wof:placetype": "postalcode"
  },
  "geometry": {"coordinates":[-1.631398,51.803185],"type":"Point"}
}
