{
  "type": "Feature",
  "properties": {
    "iso:country": "GB",
    "wof:name": "HP18 0BZ",
    "wof:placetype": "postalcode"
  },
  "geometry": {"coordinates":[-0.956934,51.789103],"type":"Point"}
}
