{
  "type": "Feature",
  "properties": {
    "iso:country": "GB",
    "wof:name": "RM17 5PA",
    "wof:placetype": "postalcode"
  },
  "geometry": {"coordinates":[0.33864,51.48585],"type":"Point"}
}
