{
  "type": "Feature",
  "properties": {
    "iso:country":"GB",
    "wof:name":"RM17 5PA",
    "wof:placetype":"postalcode"
},
  "geometry": {"coordinates":[0.33864019436246,51.4858495109269],"type":"Point"}
}