{
  "type": "Feature",
  "properties": {
    "date:inception_lower": "1980-01-01",
    "date:inception_upper": "1980-01-01",
    "iso:country": "GB",
    "wof:name": "RM17 5PA",
    "wof:placetype": "postalcode"
  },
  "geometry": {"coordinates":[0.33864,51.48585],"type":"Point"}
}
