{
  "type": "Feature",
  "properties": {
    "iso:country": "GB",
    "wof:name": "WV2 2NR",
    "wof:placetype": "postalcode"
  },
  "geometry": {"coordinates":[-2.095405,52.571387],"type":"Point"}
}
