{
  "type": "Feature",
  "properties": {
    "date:inception_lower": "1980-01-01",
    "date:inception_upper": "1980-01-01",
    "iso:country": "GB",
    "wof:name": "WV2 2NR",
    "wof:placetype": "postalcode"
  },
  "geometry": {"coordinates":[-2.095405,52.571387],"type":"Point"}
}
