{
  "type": "Feature",
  "properties": {
    "iso:country":"GB",
    "wof:name":"WV2 2NR",
    "wof:placetype":"postalcode"
},
  "geometry": {"coordinates":[-2.09540476317678,52.57138672600118],"type":"Point"}
}