{
  "type": "Feature",
  "properties": {
    "iso:country":"GB",
    "wof:name":"DD5 2LG",
    "wof:placetype":"postalcode"
},
  "geometry": {"coordinates":[-2.86496223336261,56.46957905110349],"type":"Point"}
}