{
  "type": "Feature",
  "properties": {
    "iso:country":"GB",
    "wof:name":"AB10 7DA",
    "wof:placetype":"postalcode"
},
  "geometry": {"coordinates":[-2.12866460290284,57.12096628450299],"type":"Point"}
}