{
  "type": "Feature",
  "properties": {
    "iso:country": "GB",
    "wof:name": "ME1 2LL",
    "wof:placetype": "postalcode"
  },
  "geometry": {"coordinates":[0.506093,51.372291],"type":"Point"}
}
