{
  "type": "Feature",
  "properties": {
    "iso:country":"GB",
    "wof:name":"ME1 2LL",
    "wof:placetype":"postalcode"
},
  "geometry": {"coordinates":[0.50609301722861,51.372291070778],"type":"Point"}
}