{
  "type": "Feature",
  "properties": {
    "iso:country": "GB",
    "wof:name": "MK5 6AR",
    "wof:placetype": "postalcode"
  },
  "geometry": {"coordinates":[-0.790888,52.021081],"type":"Point"}
}
