{
  "type": "Feature",
  "properties": {
    "date:inception_lower": "1987-10-01",
    "date:inception_upper": "1987-10-01",
    "iso:country": "GB",
    "wof:name": "MK5 6AR",
    "wof:placetype": "postalcode"
  },
  "geometry": {"coordinates":[-0.790888,52.021081],"type":"Point"}
}
