{
  "type": "Feature",
  "properties": {
    "iso:country":"GB",
    "wof:name":"CW8 3QX",
    "wof:placetype":"postalcode"
},
  "geometry": {"coordinates":[-2.6064315867854,53.27120798327574],"type":"Point"}
}