{
  "type": "Feature",
  "properties": {
    "date:inception_lower":"1980-01-01",
    "date:inception_upper":"1980-01-31",
    "iso:country":"GB",
    "wof:name":"CW8 3QX",
    "wof:placetype":"postalcode"
},
  "geometry": {"coordinates":[-2.606432,53.271208],"type":"Point"}
}