{
  "type": "Feature",
  "properties": {
    "iso:country":"GB",
    "wof:name":"WA13 0NT",
    "wof:placetype":"postalcode"
},
  "geometry": {"coordinates":[-2.48859470165021,53.37817623966832],"type":"Point"}
}