{
  "type": "Feature",
  "properties": {
    "date:inception_lower": "2001-12-01",
    "date:inception_upper": "2001-12-01",
    "iso:country": "GB",
    "wof:name": "BA14 8EB",
    "wof:placetype": "postalcode"
  },
  "geometry": {"coordinates":[-2.205559,51.321311],"type":"Point"}
}
