{
  "type": "Feature",
  "properties": {
    "iso:country":"GB",
    "wof:name":"BA14 8EB",
    "wof:placetype":"postalcode"
},
  "geometry": {"coordinates":[-2.20555905328732,51.32131076065626],"type":"Point"}
}