{
  "type": "Feature",
  "properties": {
    "iso:country": "GB",
    "wof:name": "TF10 9EH",
    "wof:placetype": "postalcode"
  },
  "geometry": {"coordinates":[-2.386022,52.760101],"type":"Point"}
}
