{
  "type": "Feature",
  "properties": {
    "iso:country":"GB",
    "wof:name":"TF10 9EH",
    "wof:placetype":"postalcode"
},
  "geometry": {"coordinates":[-2.38732617504813,52.76015070999891],"type":"Point"}
}