{
  "type": "Feature",
  "properties": {
    "date:inception_lower": "1980-01-01",
    "date:inception_upper": "1980-01-01",
    "iso:country": "GB",
    "wof:name": "TF10 9EH",
    "wof:placetype": "postalcode"
  },
  "geometry": {"coordinates":[-2.387325,52.760157],"type":"Point"}
}
