{
  "type": "Feature",
  "properties": {
    "iso:country": "GB",
    "wof:name": "PE3 7DD",
    "wof:placetype": "postalcode"
  },
  "geometry": {"coordinates":[-0.273399,52.587511],"type":"Point"}
}
