{
  "type": "Feature",
  "properties": {
    "date:inception_lower": "2000-06-01",
    "date:inception_upper": "2000-06-01",
    "iso:country": "GB",
    "wof:name": "PE28 2UN",
    "wof:placetype": "postalcode"
  },
  "geometry": {"coordinates":[-0.078686,52.404058],"type":"Point"}
}
