{
  "type": "Feature",
  "properties": {
    "iso:country":"GB",
    "wof:name":"PE28 2UN",
    "wof:placetype":"postalcode"
},
  "geometry": {"coordinates":[-0.07868644411956,52.40405781023821],"type":"Point"}
}