{
  "type": "Feature",
  "properties": {
    "iso:country": "GB",
    "wof:name": "PE28 2UN",
    "wof:placetype": "postalcode"
  },
  "geometry": {"coordinates":[-0.078686,52.404058],"type":"Point"}
}
