{
  "type": "Feature",
  "properties": {
    "iso:country": "GB",
    "wof:name": "YO8 5BQ",
    "wof:placetype": "postalcode"
  },
  "geometry": {"coordinates":[-1.043099,53.79017],"type":"Point"}
}
