{
  "type": "Feature",
  "properties": {
    "date:inception_lower": "1980-01-01",
    "date:inception_upper": "1980-01-01",
    "iso:country": "GB",
    "wof:name": "PO4 9ER",
    "wof:placetype": "postalcode"
  },
  "geometry": {"coordinates":[-1.061831,50.789531],"type":"Point"}
}
