{
  "type": "Feature",
  "properties": {
    "iso:country": "GB",
    "wof:name": "NR1 2LN",
    "wof:placetype": "postalcode"
  },
  "geometry": {"coordinates":[1.299109,52.609928],"type":"Point"}
}
