{
  "type": "Feature",
  "properties": {
    "iso:country":"GB",
    "wof:name":"NG4 1RU",
    "wof:placetype":"postalcode"
},
  "geometry": {"coordinates":[-1.09290580087194,52.96853930890423],"type":"Point"}
}