{
  "type": "Feature",
  "properties": {
    "iso:country":"GB",
    "wof:name":"TS5 8DX",
    "wof:placetype":"postalcode"
},
  "geometry": {"coordinates":[-1.24721303668537,54.53149736025978],"type":"Point"}
}