{
  "type": "Feature",
  "properties": {
    "iso:country":"GB",
    "wof:name":"BS4 4JF",
    "wof:placetype":"postalcode"
},
  "geometry": {"coordinates":[-2.55075727815606,51.43537972418011],"type":"Point"}
}