{
  "type": "Feature",
  "properties": {
    "date:inception_lower": "2021-03-01",
    "date:inception_upper": "2021-03-01",
    "iso:country": "GB",
    "wof:name": "KY1 2FJ",
    "wof:placetype": "postalcode"
  },
  "geometry": {"coordinates":[-3.126176,56.142035],"type":"Point"}
}
