{
  "type": "Feature",
  "properties": {
    "date:inception_lower":"2007-09-01",
    "date:inception_upper":"2007-09-30",
    "iso:country":"GB",
    "wof:name":"FK4 2GA",
    "wof:placetype":"postalcode"
},
  "geometry": {"coordinates":[-3.880871,55.99965],"type":"Point"}
}