{
  "type": "Feature",
  "properties": {
    "iso:country":"GB",
    "wof:name":"FK4 2GA",
    "wof:placetype":"postalcode"
},
  "geometry": {"coordinates":[-3.88087106947154,55.99965035714502],"type":"Point"}
}