{
  "type": "Feature",
  "properties": {
    "iso:country":"GB",
    "wof:name":"NG33 5HU",
    "wof:placetype":"postalcode"
},
  "geometry": {"coordinates":[-0.62017486242614,52.80487785899521],"type":"Point"}
}