{
  "type": "Feature",
  "properties": {
    "iso:country": "GB",
    "wof:name": "KA4 8NP",
    "wof:placetype": "postalcode"
  },
  "geometry": {"coordinates":[-4.331727,55.557326],"type":"Point"}
}
