{
  "type": "Feature",
  "properties": {
    "date:inception_lower": "1985-10-01",
    "date:inception_upper": "1985-10-01",
    "iso:country": "GB",
    "wof:name": "B78 3PJ",
    "wof:placetype": "postalcode"
  },
  "geometry": {"coordinates":[-1.736961,52.614636],"type":"Point"}
}
