{
  "type": "Feature",
  "properties": {
    "iso:country":"GB",
    "wof:name":"B78 3PJ",
    "wof:placetype":"postalcode"
},
  "geometry": {"coordinates":[-1.73696109704782,52.61463550799891],"type":"Point"}
}