{
  "type": "Feature",
  "properties": {
    "iso:country":"GB",
    "wof:name":"LE3 6SG",
    "wof:placetype":"postalcode"
},
  "geometry": {"coordinates":[-1.18566533449995,52.63284273127407],"type":"Point"}
}