{
  "type": "Feature",
  "properties": {
    "date:inception_lower": "1999-06-01",
    "date:inception_upper": "1999-06-01",
    "iso:country": "GB",
    "wof:name": "CH46 9PY",
    "wof:placetype": "postalcode"
  },
  "geometry": {"coordinates":[-3.104323,53.402472],"type":"Point"}
}
