{
  "type": "Feature",
  "properties": {
    "date:inception_lower": "2000-12-01",
    "date:inception_upper": "2000-12-01",
    "iso:country": "GB",
    "wof:name": "IV36 2QS",
    "wof:placetype": "postalcode"
  },
  "geometry": {"coordinates":[-3.567235,57.616532],"type":"Point"}
}
