{
  "type": "Feature",
  "properties": {
    "date:inception_lower": "1980-01-01",
    "date:inception_upper": "1980-01-01",
    "iso:country": "GB",
    "wof:name": "ST4 7BH",
    "wof:placetype": "postalcode"
  },
  "geometry": {"coordinates":[-2.204449,53.021549],"type":"Point"}
}
