{
  "type": "Feature",
  "properties": {
    "iso:country": "GB",
    "wof:name": "PO16 9AD",
    "wof:placetype": "postalcode"
  },
  "geometry": {"coordinates":[-1.133305,50.84404],"type":"Point"}
}
