{
  "type": "Feature",
  "properties": {
    "iso:country":"GB",
    "wof:name":"DN15 8TL",
    "wof:placetype":"postalcode"
},
  "geometry": {"coordinates":[-0.72895084612317,53.59310388793333],"type":"Point"}
}