{
  "type": "Feature",
  "properties": {
    "iso:country": "GB",
    "wof:name": "DN15 8TL",
    "wof:placetype": "postalcode"
  },
  "geometry": {"coordinates":[-0.728951,53.593104],"type":"Point"}
}
