{
  "type": "Feature",
  "properties": {
    "iso:country":"GB",
    "wof:name":"WF8 4AP",
    "wof:placetype":"postalcode"
},
  "geometry": {"coordinates":[-1.32254962466604,53.68940148564617],"type":"Point"}
}