{
  "type": "Feature",
  "properties": {
    "date:inception_lower": "1980-01-01",
    "date:inception_upper": "1980-01-01",
    "iso:country": "GB",
    "wof:name": "WF8 4AP",
    "wof:placetype": "postalcode"
  },
  "geometry": {"coordinates":[-1.32255,53.689401],"type":"Point"}
}
