{
  "type": "Feature",
  "properties": {
    "iso:country":"GB",
    "wof:name":"ST5 9NQ",
    "wof:placetype":"postalcode"
},
  "geometry": {"coordinates":[-2.22085494726782,53.02579942765803],"type":"Point"}
}