{
  "type": "Feature",
  "properties": {
    "date:inception_lower": "2016-03-01",
    "date:inception_upper": "2016-03-01",
    "iso:country": "GB",
    "wof:name": "SO31 7PG",
    "wof:placetype": "postalcode"
  },
  "geometry": {"coordinates":[-1.277434,50.871378],"type":"Point"}
}
