{
  "type": "Feature",
  "properties": {
    "iso:country":"GB",
    "wof:name":"SO31 7PG",
    "wof:placetype":"postalcode"
},
  "geometry": {"coordinates":[-1.27695289100097,50.87198751646504],"type":"Point"}
}