{
  "type": "Feature",
  "properties": {
    "date:inception_lower": "2006-08-01",
    "date:inception_upper": "2006-08-01",
    "iso:country": "GB",
    "wof:name": "EN11 9JX",
    "wof:placetype": "postalcode"
  },
  "geometry": {"coordinates":[-0.017903,51.766258],"type":"Point"}
}
