{
  "type": "Feature",
  "properties": {
    "iso:country":"GB",
    "wof:name":"EN11 9JX",
    "wof:placetype":"postalcode"
},
  "geometry": {"coordinates":[-0.01790295788688,51.76625845773069],"type":"Point"}
}