{
  "type": "Feature",
  "properties": {
    "iso:country": "GB",
    "wof:name": "TS6 6SY",
    "wof:placetype": "postalcode"
  },
  "geometry": {"coordinates":[-1.170292,54.571625],"type":"Point"}
}
