{
  "type": "Feature",
  "properties": {
    "iso:country":"GB",
    "wof:name":"TS6 6SY",
    "wof:placetype":"postalcode"
},
  "geometry": {"coordinates":[-1.17029239566802,54.5716251686949],"type":"Point"}
}