{
  "type": "Feature",
  "properties": {
    "date:inception_lower":"1980-01-01",
    "date:inception_upper":"1980-01-31",
    "iso:country":"GB",
    "wof:name":"TS6 6SY",
    "wof:placetype":"postalcode"
},
  "geometry": {"coordinates":[-1.170292,54.571625],"type":"Point"}
}