{
  "type": "Feature",
  "properties": {
    "iso:country":"GB",
    "wof:name":"N19 3TS",
    "wof:placetype":"postalcode"
},
  "geometry": {"coordinates":[-0.1362765261216,51.56970814160001],"type":"Point"}
}