{
  "type": "Feature",
  "properties": {
    "iso:country":"GB",
    "wof:name":"YO19 6AX",
    "wof:placetype":"postalcode"
},
  "geometry": {"coordinates":[-0.95546994295936,53.89752398664082],"type":"Point"}
}