{
  "type": "Feature",
  "properties": {
    "date:inception_lower":"1989-02-01",
    "date:inception_upper":"1989-02-28",
    "iso:country":"GB",
    "wof:name":"PA2 9PG",
    "wof:placetype":"postalcode"
},
  "geometry": {"coordinates":[-4.45123,55.837893],"type":"Point"}
}