{
  "type": "Feature",
  "properties": {
    "iso:country":"GB",
    "wof:name":"PA2 9PG",
    "wof:placetype":"postalcode"
},
  "geometry": {"coordinates":[-4.45122967675275,55.83789330962043],"type":"Point"}
}