{
  "type": "Feature",
  "properties": {
    "iso:country": "GB",
    "wof:name": "PA2 9PG",
    "wof:placetype": "postalcode"
  },
  "geometry": {"coordinates":[-4.45123,55.837893],"type":"Point"}
}
