{
  "type": "Feature",
  "properties": {
    "iso:country": "GB",
    "wof:name": "SG18 0HG",
    "wof:placetype": "postalcode"
  },
  "geometry": {"coordinates":[-0.265541,52.09698],"type":"Point"}
}
