{
  "type": "Feature",
  "properties": {
    "iso:country":"GB",
    "wof:name":"SG18 0HG",
    "wof:placetype":"postalcode"
},
  "geometry": {"coordinates":[-0.26554123102938,52.09697984354348],"type":"Point"}
}