{
  "type": "Feature",
  "properties": {
    "iso:country":"GB",
    "wof:name":"S13 9BL",
    "wof:placetype":"postalcode"
},
  "geometry": {"coordinates":[-1.39140583910241,53.37457106009773],"type":"Point"}
}