{
  "type": "Feature",
  "properties": {
    "iso:country":"GB",
    "wof:name":"PE1 1XL",
    "wof:placetype":"postalcode"
},
  "geometry": {"coordinates":[-0.24250734516002,52.57226672646721],"type":"Point"}
}