{
  "type": "Feature",
  "properties": {
    "iso:country": "GB",
    "wof:name": "BA14 0XG",
    "wof:placetype": "postalcode"
  },
  "geometry": {"coordinates":[-2.196404,51.298861],"type":"Point"}
}
