{
  "type": "Feature",
  "properties": {
    "iso:country":"GB",
    "wof:name":"BA14 0XG",
    "wof:placetype":"postalcode"
},
  "geometry": {"coordinates":[-2.19645140663974,51.29891892338231],"type":"Point"}
}