{
  "type": "Feature",
  "properties": {
    "iso:country": "GB",
    "wof:name": "NN15 7QP",
    "wof:placetype": "postalcode"
  },
  "geometry": {"coordinates":[-0.725649,52.397293],"type":"Point"}
}
