{
  "type": "Feature",
  "properties": {
    "iso:country":"GB",
    "wof:name":"NN15 7QP",
    "wof:placetype":"postalcode"
},
  "geometry": {"coordinates":[-0.72564954028591,52.39729280046082],"type":"Point"}
}