{
  "type": "Feature",
  "properties": {
    "iso:country": "GB",
    "wof:name": "MK43 9DW",
    "wof:placetype": "postalcode"
  },
  "geometry": {"coordinates":[-0.533898,52.098402],"type":"Point"}
}
