{
  "type": "Feature",
  "properties": {
    "date:inception_lower":"2007-11-01",
    "date:inception_upper":"2007-11-30",
    "iso:country":"GB",
    "wof:name":"PA16 8AQ",
    "wof:placetype":"postalcode"
},
  "geometry": {"coordinates":[-4.764615,55.952522],"type":"Point"}
}