{
  "type": "Feature",
  "properties": {
    "iso:country": "GB",
    "wof:name": "PA16 8AQ",
    "wof:placetype": "postalcode"
  },
  "geometry": {"coordinates":[-4.764615,55.952522],"type":"Point"}
}
