{
  "type": "Feature",
  "properties": {
    "iso:country":"GB",
    "wof:name":"DE74 2EW",
    "wof:placetype":"postalcode"
},
  "geometry": {"coordinates":[-1.27785423767957,52.83436140312807],"type":"Point"}
}