{
  "type": "Feature",
  "properties": {
    "iso:country":"GB",
    "wof:name":"B4 7SF",
    "wof:placetype":"postalcode"
},
  "geometry": {"coordinates":[-1.89415180512397,52.47875543446003],"type":"Point"}
}