{
  "type": "Feature",
  "properties": {
    "date:inception_lower": "2024-05-01",
    "date:inception_upper": "2024-05-01",
    "iso:country": "GB",
    "wof:name": "TR13 8XF",
    "wof:placetype": "postalcode"
  },
  "geometry": {"coordinates":[-5.26194,50.096753],"type":"Point"}
}
