{
  "type": "Feature",
  "properties": {
    "iso:country":"GB",
    "wof:name":"NG13 9HD",
    "wof:placetype":"postalcode"
},
  "geometry": {"coordinates":[-0.92574570038245,52.90255559121207],"type":"Point"}
}