{
  "type": "Feature",
  "properties": {
    "iso:country":"GB",
    "wof:name":"NR18 0DA",
    "wof:placetype":"postalcode"
},
  "geometry": {"coordinates":[1.10849363787114,52.57586875824963],"type":"Point"}
}