{
  "type": "Feature",
  "properties": {
    "iso:country":"GB",
    "wof:name":"PE14 0SH",
    "wof:placetype":"postalcode"
},
  "geometry": {"coordinates":[0.1462891814254,52.64933274825248],"type":"Point"}
}