{
  "type": "Feature",
  "properties": {
    "date:inception_lower": "1980-01-01",
    "date:inception_upper": "1980-01-01",
    "iso:country": "GB",
    "wof:name": "TQ9 5PY",
    "wof:placetype": "postalcode"
  },
  "geometry": {"coordinates":[-3.690436,50.433823],"type":"Point"}
}
