{
  "type": "Feature",
  "properties": {
    "iso:country": "GB",
    "wof:name": "SO21 2NF",
    "wof:placetype": "postalcode"
  },
  "geometry": {"coordinates":[-1.394883,51.08468],"type":"Point"}
}
