{
  "type": "Feature",
  "properties": {
    "iso:country": "GB",
    "wof:name": "BA2 4SA",
    "wof:placetype": "postalcode"
  },
  "geometry": {"coordinates":[-2.36628,51.369806],"type":"Point"}
}
