{
  "type": "Feature",
  "properties": {
    "iso:country":"GB",
    "wof:name":"BA2 4SA",
    "wof:placetype":"postalcode"
},
  "geometry": {"coordinates":[-2.36627992513453,51.36980617669227],"type":"Point"}
}