{
  "type": "Feature",
  "properties": {
    "iso:country":"GB",
    "wof:name":"PL4 0JW",
    "wof:placetype":"postalcode"
},
  "geometry": {"coordinates":[-4.12569861572455,50.36812043001938],"type":"Point"}
}