{
  "type": "Feature",
  "properties": {
    "iso:country":"GB",
    "wof:name":"G21 4JN",
    "wof:placetype":"postalcode"
},
  "geometry": {"coordinates":[-4.2259453374548,55.88640455795557],"type":"Point"}
}