{
  "type": "Feature",
  "properties": {
    "iso:country":"GB",
    "wof:name":"BN1 8NP",
    "wof:placetype":"postalcode"
},
  "geometry": {"coordinates":[-0.14059713286827,50.86298733441534],"type":"Point"}
}