{
  "type": "Feature",
  "properties": {
    "date:inception_lower": "1997-12-01",
    "date:inception_upper": "1997-12-01",
    "iso:country": "GB",
    "wof:name": "BS36 1LB",
    "wof:placetype": "postalcode"
  },
  "geometry": {"coordinates":[-2.503398,51.52157],"type":"Point"}
}
