{
  "type": "Feature",
  "properties": {
    "iso:country":"GB",
    "wof:name":"KA19 7SL",
    "wof:placetype":"postalcode"
},
  "geometry": {"coordinates":[-4.68994765518666,55.28896643584469],"type":"Point"}
}