{
  "type": "Feature",
  "properties": {
    "iso:country":"GB",
    "wof:name":"E3 4XS",
    "wof:placetype":"postalcode"
},
  "geometry": {"coordinates":[-0.02354694406373,51.52416843161702],"type":"Point"}
}