{
  "type": "Feature",
  "properties": {
    "iso:country": "GB",
    "wof:name": "E3 4XS",
    "wof:placetype": "postalcode"
  },
  "geometry": {"coordinates":[-0.023547,51.524168],"type":"Point"}
}
