{
  "type": "Feature",
  "properties": {
    "date:inception_lower":"1995-07-01",
    "date:inception_upper":"1995-07-31",
    "iso:country":"GB",
    "wof:name":"E3 4XS",
    "wof:placetype":"postalcode"
},
  "geometry": {"coordinates":[-0.023547,51.524168],"type":"Point"}
}