{
  "type": "Feature",
  "properties": {
    "iso:country":"GB",
    "wof:name":"ST6 1HW",
    "wof:placetype":"postalcode"
},
  "geometry": {"coordinates":[-2.18514804324036,53.05033781644012],"type":"Point"}
}