{
  "type": "Feature",
  "properties": {
    "date:inception_lower":"1996-06-01",
    "date:inception_upper":"1996-06-30",
    "iso:country":"GB",
    "wof:name":"SW15 2DE",
    "wof:placetype":"postalcode"
},
  "geometry": {"coordinates":[-0.2129,51.456993],"type":"Point"}
}