{
  "type": "Feature",
  "properties": {
    "iso:country": "GB",
    "wof:name": "SW15 2DE",
    "wof:placetype": "postalcode"
  },
  "geometry": {"coordinates":[-0.2129,51.456993],"type":"Point"}
}
