{
  "type": "Feature",
  "properties": {
    "iso:country":"GB",
    "wof:name":"SW15 2DE",
    "wof:placetype":"postalcode"
},
  "geometry": {"coordinates":[-0.21290004628761,51.45699305049897],"type":"Point"}
}