{
  "type": "Feature",
  "properties": {
    "iso:country":"GB",
    "wof:name":"TN23 1JY",
    "wof:placetype":"postalcode"
},
  "geometry": {"coordinates":[0.86771634157828,51.14921021724961],"type":"Point"}
}