{
  "type": "Feature",
  "properties": {
    "date:inception_lower":"1980-01-01",
    "date:inception_upper":"1980-01-31",
    "iso:country":"GB",
    "wof:name":"TN23 1JY",
    "wof:placetype":"postalcode"
},
  "geometry": {"coordinates":[0.867716,51.14921],"type":"Point"}
}