{
  "type": "Feature",
  "properties": {
    "iso:country": "GB",
    "wof:name": "WA7 1NJ",
    "wof:placetype": "postalcode"
  },
  "geometry": {"coordinates":[-2.746562,53.342827],"type":"Point"}
}
