{
  "type": "Feature",
  "properties": {
    "iso:country":"GB",
    "wof:name":"NE24 1DD",
    "wof:placetype":"postalcode"
},
  "geometry": {"coordinates":[-1.51255852207934,55.12604810902863],"type":"Point"}
}