{
  "type": "Feature",
  "properties": {
    "iso:country": "GB",
    "wof:name": "LU6 1HD",
    "wof:placetype": "postalcode"
  },
  "geometry": {"coordinates":[-0.530127,51.887704],"type":"Point"}
}
