{
  "type": "Feature",
  "properties": {
    "date:inception_lower":"2001-12-01",
    "date:inception_upper":"2001-12-31",
    "iso:country":"GB",
    "wof:name":"LU6 1HD",
    "wof:placetype":"postalcode"
},
  "geometry": {"coordinates":[-0.530127,51.887704],"type":"Point"}
}