{
  "type": "Feature",
  "properties": {
    "iso:country":"GB",
    "wof:name":"LU6 1HD",
    "wof:placetype":"postalcode"
},
  "geometry": {"coordinates":[-0.53012714963397,51.88770386506818],"type":"Point"}
}