{
  "type": "Feature",
  "properties": {
    "date:inception_lower": "1983-03-01",
    "date:inception_upper": "1983-03-01",
    "iso:country": "GB",
    "wof:name": "PO1 4LQ",
    "wof:placetype": "postalcode"
  },
  "geometry": {"coordinates":[-1.08613,50.807152],"type":"Point"}
}
