{
  "type": "Feature",
  "properties": {
    "iso:country":"GB",
    "wof:name":"RH10 7RD",
    "wof:placetype":"postalcode"
},
  "geometry": {"coordinates":[-0.13904137616414,51.11255180895029],"type":"Point"}
}