{
  "type": "Feature",
  "properties": {
    "date:inception_lower":"2010-01-01",
    "date:inception_upper":"2010-01-31",
    "iso:country":"GB",
    "wof:name":"BS39 6AD",
    "wof:placetype":"postalcode"
},
  "geometry": {"coordinates":[-2.527221,51.310305],"type":"Point"}
}