{
  "type": "Feature",
  "properties": {
    "date:inception_lower": "2010-01-01",
    "date:inception_upper": "2010-01-01",
    "iso:country": "GB",
    "wof:name": "BS39 6AD",
    "wof:placetype": "postalcode"
  },
  "geometry": {"coordinates":[-2.527051,51.310274],"type":"Point"}
}
