{
  "type": "Feature",
  "properties": {
    "iso:country":"GB",
    "wof:name":"BS39 6AD",
    "wof:placetype":"postalcode"
},
  "geometry": {"coordinates":[-2.52722118585317,51.31030492815292],"type":"Point"}
}