{
  "type": "Feature",
  "properties": {
    "iso:country":"GB",
    "wof:name":"B15 3RJ",
    "wof:placetype":"postalcode"
},
  "geometry": {"coordinates":[-1.93505921314885,52.46529991103919],"type":"Point"}
}