{
  "type": "Feature",
  "properties": {
    "iso:country":"GB",
    "wof:name":"TA6 6NH",
    "wof:placetype":"postalcode"
},
  "geometry": {"coordinates":[-3.01915851973676,51.08956979866181],"type":"Point"}
}