{
  "type": "Feature",
  "properties": {
    "iso:country":"GB",
    "wof:name":"SR6 7RH",
    "wof:placetype":"postalcode"
},
  "geometry": {"coordinates":[-1.40458611698152,54.95427254951091],"type":"Point"}
}