{
  "type": "Feature",
  "properties": {
    "iso:country":"GB",
    "wof:name":"G60 5JQ",
    "wof:placetype":"postalcode"
},
  "geometry": {"coordinates":[-4.45963997372476,55.92547442965309],"type":"Point"}
}