{
  "type": "Feature",
  "properties": {
    "iso:country":"GB",
    "wof:name":"EH1 1BS",
    "wof:placetype":"postalcode"
},
  "geometry": {"coordinates":[-3.18913731498745,55.95072026883511],"type":"Point"}
}