{
  "type": "Feature",
  "properties": {
    "iso:country": "GB",
    "wof:name": "DE23 8LJ",
    "wof:placetype": "postalcode"
  },
  "geometry": {"coordinates":[-1.468139,52.908387],"type":"Point"}
}
