{
  "type": "Feature",
  "properties": {
    "iso:country":"GB",
    "wof:name":"PO20 0LJ",
    "wof:placetype":"postalcode"
},
  "geometry": {"coordinates":[-0.79511098158524,50.72496717499306],"type":"Point"}
}