{
  "type": "Feature",
  "properties": {
    "iso:country": "GB",
    "wof:name": "PO20 0LJ",
    "wof:placetype": "postalcode"
  },
  "geometry": {"coordinates":[-0.795111,50.724967],"type":"Point"}
}
