{
  "type": "Feature",
  "properties": {
    "iso:country":"GB",
    "wof:name":"KA24 5AH",
    "wof:placetype":"postalcode"
},
  "geometry": {"coordinates":[-4.71964268422984,55.70779995521492],"type":"Point"}
}