{
  "type": "Feature",
  "properties": {
    "date:inception_lower": "1980-01-01",
    "date:inception_upper": "1980-01-01",
    "iso:country": "GB",
    "wof:name": "IP23 7BJ",
    "wof:placetype": "postalcode"
  },
  "geometry": {"coordinates":[1.142485,52.323524],"type":"Point"}
}
