{
  "type": "Feature",
  "properties": {
    "iso:country": "GB",
    "wof:name": "IP23 7BJ",
    "wof:placetype": "postalcode"
  },
  "geometry": {"coordinates":[1.14192,52.3236],"type":"Point"}
}
