{
  "type": "Feature",
  "properties": {
    "iso:country":"GB",
    "wof:name":"BB11 3LN",
    "wof:placetype":"postalcode"
},
  "geometry": {"coordinates":[-2.23687534170415,53.78192333576295],"type":"Point"}
}