{
  "type": "Feature",
  "properties": {
    "date:inception_lower": "1980-01-01",
    "date:inception_upper": "1980-01-01",
    "iso:country": "GB",
    "wof:name": "BB11 3LN",
    "wof:placetype": "postalcode"
  },
  "geometry": {"coordinates":[-2.2363,53.782055],"type":"Point"}
}
