{
  "type": "Feature",
  "properties": {
    "iso:country": "GB",
    "wof:name": "LD8 2HR",
    "wof:placetype": "postalcode"
  },
  "geometry": {"coordinates":[-2.935636,52.279739],"type":"Point"}
}
