{
  "type": "Feature",
  "properties": {
    "date:inception_lower": "1980-01-01",
    "date:inception_upper": "1980-01-01",
    "iso:country": "GB",
    "wof:name": "LD8 2HR",
    "wof:placetype": "postalcode"
  },
  "geometry": {"coordinates":[-2.933525,52.279713],"type":"Point"}
}
