{
  "type": "Feature",
  "properties": {
    "iso:country":"GB",
    "wof:name":"LD8 2HR",
    "wof:placetype":"postalcode"
},
  "geometry": {"coordinates":[-2.93563595953453,52.27973891846084],"type":"Point"}
}