{
  "type": "Feature",
  "properties": {
    "iso:country":"GB",
    "wof:name":"PH10 7DH",
    "wof:placetype":"postalcode"
},
  "geometry": {"coordinates":[-3.32144682201197,56.59403293866694],"type":"Point"}
}