{
  "type": "Feature",
  "properties": {
    "date:inception_lower": "1989-06-01",
    "date:inception_upper": "1989-06-01",
    "iso:country": "GB",
    "wof:name": "PH10 7DH",
    "wof:placetype": "postalcode"
  },
  "geometry": {"coordinates":[-3.321447,56.594033],"type":"Point"}
}
