{
  "type": "Feature",
  "properties": {
    "iso:country":"GB",
    "wof:name":"NE45 5QZ",
    "wof:placetype":"postalcode"
},
  "geometry": {"coordinates":[-2.04031297711736,54.96553511794993],"type":"Point"}
}