{
  "type": "Feature",
  "properties": {
    "date:inception_lower": "1993-01-01",
    "date:inception_upper": "1993-01-01",
    "iso:country": "GB",
    "wof:name": "SN4 0QS",
    "wof:placetype": "postalcode"
  },
  "geometry": {"coordinates":[-1.787348,51.511885],"type":"Point"}
}
