{
  "type": "Feature",
  "properties": {
    "iso:country":"GB",
    "wof:name":"M44 6WA",
    "wof:placetype":"postalcode"
},
  "geometry": {"coordinates":[-2.42151296911646,53.44731178070405],"type":"Point"}
}