{
  "type": "Feature",
  "properties": {
    "iso:country": "GB",
    "wof:name": "NE22 6EP",
    "wof:placetype": "postalcode"
  },
  "geometry": {"coordinates":[-1.606241,55.133926],"type":"Point"}
}
