{
  "type": "Feature",
  "properties": {
    "date:inception_lower": "1996-12-01",
    "date:inception_upper": "1996-12-01",
    "iso:country": "GB",
    "wof:name": "LA2 8DY",
    "wof:placetype": "postalcode"
  },
  "geometry": {"coordinates":[-2.392552,54.120465],"type":"Point"}
}
