{
  "type": "Feature",
  "properties": {
    "iso:country": "GB",
    "wof:name": "NE33 3EL",
    "wof:placetype": "postalcode"
  },
  "geometry": {"coordinates":[-1.415937,54.988781],"type":"Point"}
}
