{
  "type": "Feature",
  "properties": {
    "date:inception_lower": "1980-01-01",
    "date:inception_upper": "1980-01-01",
    "iso:country": "GB",
    "wof:name": "CT11 0AT",
    "wof:placetype": "postalcode"
  },
  "geometry": {"coordinates":[1.403596,51.333654],"type":"Point"}
}
