{
  "type": "Feature",
  "properties": {
    "iso:country":"GB",
    "wof:name":"CT11 0AT",
    "wof:placetype":"postalcode"
},
  "geometry": {"coordinates":[1.40359605171582,51.33365414421285],"type":"Point"}
}