{
  "type": "Feature",
  "properties": {
    "iso:country":"GB",
    "wof:name":"TN23 4EY",
    "wof:placetype":"postalcode"
},
  "geometry": {"coordinates":[0.85546570914173,51.13863592082372],"type":"Point"}
}