{
  "type": "Feature",
  "properties": {
    "date:inception_lower":"1994-12-01",
    "date:inception_upper":"1994-12-31",
    "iso:country":"GB",
    "wof:name":"TN23 4EY",
    "wof:placetype":"postalcode"
},
  "geometry": {"coordinates":[0.855466,51.138636],"type":"Point"}
}