{
  "type": "Feature",
  "properties": {
    "iso:country":"GB",
    "wof:name":"FY8 3PT",
    "wof:placetype":"postalcode"
},
  "geometry": {"coordinates":[-3.00401260846929,53.75232611592136],"type":"Point"}
}