{
  "type": "Feature",
  "properties": {
    "iso:country":"GB",
    "wof:name":"WA15 0QJ",
    "wof:placetype":"postalcode"
},
  "geometry": {"coordinates":[-2.32692330133958,53.35262573979183],"type":"Point"}
}