{
  "type": "Feature",
  "properties": {
    "iso:country": "GB",
    "wof:name": "FK1 3HN",
    "wof:placetype": "postalcode"
  },
  "geometry": {"coordinates":[-3.835057,55.934048],"type":"Point"}
}
