{
  "type": "Feature",
  "properties": {
    "iso:country":"GB",
    "wof:name":"AB39 2TP",
    "wof:placetype":"postalcode"
},
  "geometry": {"coordinates":[-2.20004441384887,56.91025199770091],"type":"Point"}
}