{
  "type": "Feature",
  "properties": {
    "iso:country":"GB",
    "wof:name":"B12 8JG",
    "wof:placetype":"postalcode"
},
  "geometry": {"coordinates":[-1.87368575845849,52.45818430382396],"type":"Point"}
}