{
  "type": "Feature",
  "properties": {
    "iso:country": "GB",
    "wof:name": "G77 6AT",
    "wof:placetype": "postalcode"
  },
  "geometry": {"coordinates":[-4.342611,55.788071],"type":"Point"}
}
