{
  "type": "Feature",
  "properties": {
    "date:inception_lower": "1980-01-01",
    "date:inception_upper": "1980-01-01",
    "iso:country": "GB",
    "wof:name": "IP17 1HN",
    "wof:placetype": "postalcode"
  },
  "geometry": {"coordinates":[1.487187,52.196141],"type":"Point"}
}
