{
  "type": "Feature",
  "properties": {
    "iso:country":"GB",
    "wof:name":"IP17 1HN",
    "wof:placetype":"postalcode"
},
  "geometry": {"coordinates":[1.48614462868034,52.19517084611717],"type":"Point"}
}