{
  "type": "Feature",
  "properties": {
    "iso:country": "GB",
    "wof:name": "DE1 9UA",
    "wof:placetype": "postalcode"
  },
  "geometry": {"coordinates":[-1.474217,52.923454],"type":"Point"}
}
