{
  "type": "Feature",
  "properties": {
    "date:inception_lower": "1997-06-01",
    "date:inception_upper": "1997-06-01",
    "iso:country": "GB",
    "wof:name": "EN8 9RW",
    "wof:placetype": "postalcode"
  },
  "geometry": {"coordinates":[-0.031007,51.703901],"type":"Point"}
}
