{
  "type": "Feature",
  "properties": {
    "iso:country":"GB",
    "wof:name":"EN8 9RW",
    "wof:placetype":"postalcode"
},
  "geometry": {"coordinates":[-0.03100666543358,51.70390106560104],"type":"Point"}
}