{
  "type": "Feature",
  "properties": {
    "date:inception_lower": "2021-07-01",
    "date:inception_upper": "2021-07-01",
    "iso:country": "GB",
    "wof:name": "GL8 8GQ",
    "wof:placetype": "postalcode"
  },
  "geometry": {"coordinates":[-2.146144,51.644809],"type":"Point"}
}
