{
  "type": "Feature",
  "properties": {
    "date:inception_lower": "1999-12-01",
    "date:inception_upper": "1999-12-01",
    "iso:country": "GB",
    "wof:name": "LA14 5UT",
    "wof:placetype": "postalcode"
  },
  "geometry": {"coordinates":[-3.237832,54.125008],"type":"Point"}
}
