{
  "type": "Feature",
  "properties": {
    "iso:country":"GB",
    "wof:name":"LA14 5UT",
    "wof:placetype":"postalcode"
},
  "geometry": {"coordinates":[-3.23778010734563,54.12417320216781],"type":"Point"}
}