{
  "type": "Feature",
  "properties": {
    "iso:country":"GB",
    "wof:name":"S10 2HQ",
    "wof:placetype":"postalcode"
},
  "geometry": {"coordinates":[-1.490628778475,53.37807362343332],"type":"Point"}
}