{
  "type": "Feature",
  "properties": {
    "iso:country": "GB",
    "wof:name": "S10 2HQ",
    "wof:placetype": "postalcode"
  },
  "geometry": {"coordinates":[-1.490629,53.378074],"type":"Point"}
}
