{
  "type": "Feature",
  "properties": {
    "iso:country":"GB",
    "wof:name":"RG25 3HN",
    "wof:placetype":"postalcode"
},
  "geometry": {"coordinates":[-1.26816483755205,51.24264038761556],"type":"Point"}
}