{
  "type": "Feature",
  "properties": {
    "iso:country": "GB",
    "wof:name": "DL11 6EA",
    "wof:placetype": "postalcode"
  },
  "geometry": {"coordinates":[-2.175193,54.414256],"type":"Point"}
}
