{
  "type": "Feature",
  "properties": {
    "iso:country":"GB",
    "wof:name":"DL11 6EA",
    "wof:placetype":"postalcode"
},
  "geometry": {"coordinates":[-2.17490080058693,54.41444544196817],"type":"Point"}
}