{
  "type": "Feature",
  "properties": {
    "date:inception_lower":"1980-01-01",
    "date:inception_upper":"1980-01-31",
    "iso:country":"GB",
    "wof:name":"DL11 6EA",
    "wof:placetype":"postalcode"
},
  "geometry": {"coordinates":[-2.175193,54.414256],"type":"Point"}
}