{
  "type": "Feature",
  "properties": {
    "date:inception_lower":"1998-06-01",
    "date:inception_upper":"1998-06-30",
    "iso:country":"GB",
    "wof:name":"TA11 6QD",
    "wof:placetype":"postalcode"
},
  "geometry": {"coordinates":[-2.743174,51.054983],"type":"Point"}
}