{
  "type": "Feature",
  "properties": {
    "iso:country": "GB",
    "wof:name": "CH48 4AB",
    "wof:placetype": "postalcode"
  },
  "geometry": {"coordinates":[-3.18342,53.372463],"type":"Point"}
}
