{
  "type": "Feature",
  "properties": {
    "iso:country":"GB",
    "wof:name":"S14 1JG",
    "wof:placetype":"postalcode"
},
  "geometry": {"coordinates":[-1.44610498643495,53.34896768592179],"type":"Point"}
}