{
  "type": "Feature",
  "properties": {
    "date:inception_lower": "2021-12-01",
    "date:inception_upper": "2021-12-01",
    "iso:country": "GB",
    "wof:name": "CA15 7FD",
    "wof:placetype": "postalcode"
  },
  "geometry": {"coordinates":[-3.464564,54.688443],"type":"Point"}
}
