{
  "type": "Feature",
  "properties": {
    "iso:country":"GB",
    "wof:name":"NG13 0FD",
    "wof:placetype":"postalcode"
},
  "geometry": {"coordinates":[-0.76898670613238,52.93222064897923],"type":"Point"}
}