{
  "type": "Feature",
  "properties": {
    "iso:country": "GB",
    "wof:name": "DY11 5SZ",
    "wof:placetype": "postalcode"
  },
  "geometry": {"coordinates":[-2.279578,52.425952],"type":"Point"}
}
