{
  "type": "Feature",
  "properties": {
    "iso:country": "GB",
    "wof:name": "BS40 5AR",
    "wof:placetype": "postalcode"
  },
  "geometry": {"coordinates":[-2.726683,51.345291],"type":"Point"}
}
