{
  "type": "Feature",
  "properties": {
    "iso:country":"GB",
    "wof:name":"S43 4TD",
    "wof:placetype":"postalcode"
},
  "geometry": {"coordinates":[-1.25497772246483,53.28783723013279],"type":"Point"}
}