{
  "type": "Feature",
  "properties": {
    "iso:country":"GB",
    "wof:name":"AB21 9TN",
    "wof:placetype":"postalcode"
},
  "geometry": {"coordinates":[-2.22220811134705,57.19057046589029],"type":"Point"}
}