{
  "type": "Feature",
  "properties": {
    "iso:country":"GB",
    "wof:name":"M33 5NR",
    "wof:placetype":"postalcode"
},
  "geometry": {"coordinates":[-2.34489365818462,53.42916713556449],"type":"Point"}
}