{
  "type": "Feature",
  "properties": {
    "date:inception_lower": "1980-01-01",
    "date:inception_upper": "1980-01-01",
    "iso:country": "GB",
    "wof:name": "M33 5NR",
    "wof:placetype": "postalcode"
  },
  "geometry": {"coordinates":[-2.344894,53.429167],"type":"Point"}
}
