{
  "type": "Feature",
  "properties": {
    "date:inception_lower": "2016-08-01",
    "date:inception_upper": "2016-08-01",
    "iso:country": "GB",
    "wof:name": "TR1 3FW",
    "wof:placetype": "postalcode"
  },
  "geometry": {"coordinates":[-5.066236,50.27106],"type":"Point"}
}
