{
  "type": "Feature",
  "properties": {
    "date:inception_lower":"2004-09-01",
    "date:inception_upper":"2004-09-30",
    "iso:country":"GB",
    "wof:name":"NE47 9AT",
    "wof:placetype":"postalcode"
},
  "geometry": {"coordinates":[-2.264955,54.907947],"type":"Point"}
}