{
  "type": "Feature",
  "properties": {
    "iso:country":"GB",
    "wof:name":"SO30 0GX",
    "wof:placetype":"postalcode"
},
  "geometry": {"coordinates":[-1.30002757593293,50.91220787203471],"type":"Point"}
}