{
  "type": "Feature",
  "properties": {
    "date:inception_lower": "1995-07-01",
    "date:inception_upper": "1995-07-01",
    "iso:country": "GB",
    "wof:name": "CH2 4RS",
    "wof:placetype": "postalcode"
  },
  "geometry": {"coordinates":[-2.808396,53.272715],"type":"Point"}
}
