{
  "type": "Feature",
  "properties": {
    "iso:country":"GB",
    "wof:name":"CH2 4RS",
    "wof:placetype":"postalcode"
},
  "geometry": {"coordinates":[-2.80839555134077,53.27271509502739],"type":"Point"}
}