{
  "type": "Feature",
  "properties": {
    "date:inception_lower": "1980-01-01",
    "date:inception_upper": "1980-01-01",
    "iso:country": "GB",
    "wof:name": "UB8 3AB",
    "wof:placetype": "postalcode"
  },
  "geometry": {"coordinates":[-0.477126,51.53061],"type":"Point"}
}
