{
  "type": "Feature",
  "properties": {
    "iso:country":"GB",
    "wof:name":"UB8 3AB",
    "wof:placetype":"postalcode"
},
  "geometry": {"coordinates":[-0.47712566504795,51.53060993406628],"type":"Point"}
}