{
  "type": "Feature",
  "properties": {
    "iso:country":"GB",
    "wof:name":"OX7 4BG",
    "wof:placetype":"postalcode"
},
  "geometry": {"coordinates":[-1.45201786323163,51.97860095420678],"type":"Point"}
}