{
  "type": "Feature",
  "properties": {
    "date:inception_lower": "1980-01-01",
    "date:inception_upper": "1980-01-01",
    "iso:country": "GB",
    "wof:name": "OX7 4BG",
    "wof:placetype": "postalcode"
  },
  "geometry": {"coordinates":[-1.451885,51.978646],"type":"Point"}
}
