{
  "type": "Feature",
  "properties": {
    "iso:country": "GB",
    "wof:name": "OX7 4BG",
    "wof:placetype": "postalcode"
  },
  "geometry": {"coordinates":[-1.452018,51.978601],"type":"Point"}
}
