{
  "type": "Feature",
  "properties": {
    "iso:country":"GB",
    "wof:name":"HP5 2SG",
    "wof:placetype":"postalcode"
},
  "geometry": {"coordinates":[-0.63346825923141,51.71699396125391],"type":"Point"}
}