{
  "type": "Feature",
  "properties": {
    "iso:country": "GB",
    "wof:name": "HP5 2SG",
    "wof:placetype": "postalcode"
  },
  "geometry": {"coordinates":[-0.633468,51.716994],"type":"Point"}
}
