{
  "type": "Feature",
  "properties": {
    "date:inception_lower": "2000-12-01",
    "date:inception_upper": "2000-12-01",
    "iso:country": "GB",
    "wof:name": "RM12 4PB",
    "wof:placetype": "postalcode"
  },
  "geometry": {"coordinates":[0.194838,51.549334],"type":"Point"}
}
