{
  "type": "Feature",
  "properties": {
    "iso:country": "GB",
    "wof:name": "RM12 4PB",
    "wof:placetype": "postalcode"
  },
  "geometry": {"coordinates":[0.194838,51.549334],"type":"Point"}
}
