{
  "type": "Feature",
  "properties": {
    "iso:country":"GB",
    "wof:name":"BR4 9NH",
    "wof:placetype":"postalcode"
},
  "geometry": {"coordinates":[-0.01691078457771,51.37116181815688],"type":"Point"}
}