{
  "type": "Feature",
  "properties": {
    "date:inception_lower": "1980-01-01",
    "date:inception_upper": "1980-01-01",
    "iso:country": "GB",
    "wof:name": "S64 8JA",
    "wof:placetype": "postalcode"
  },
  "geometry": {"coordinates":[-1.316249,53.483494],"type":"Point"}
}
