{
  "type": "Feature",
  "properties": {
    "iso:country":"GB",
    "wof:name":"S64 8JA",
    "wof:placetype":"postalcode"
},
  "geometry": {"coordinates":[-1.31624901432183,53.48349394655434],"type":"Point"}
}