{
  "type": "Feature",
  "properties": {
    "date:inception_lower":"1980-01-01",
    "date:inception_upper":"1980-01-31",
    "iso:country":"GB",
    "wof:name":"L37 1PL",
    "wof:placetype":"postalcode"
},
  "geometry": {"coordinates":[-3.081978,53.559632],"type":"Point"}
}