{
  "type": "Feature",
  "properties": {
    "iso:country": "GB",
    "wof:name": "MK5 8AS",
    "wof:placetype": "postalcode"
  },
  "geometry": {"coordinates":[-0.781261,52.033722],"type":"Point"}
}
