{
  "type": "Feature",
  "properties": {
    "iso:country":"GB",
    "wof:name":"MK5 8AS",
    "wof:placetype":"postalcode"
},
  "geometry": {"coordinates":[-0.78126092675623,52.03372202429436],"type":"Point"}
}