{
  "type": "Feature",
  "properties": {
    "iso:country": "GB",
    "wof:name": "TA6 6WW",
    "wof:placetype": "postalcode"
  },
  "geometry": {"coordinates":[-2.999712,51.10882],"type":"Point"}
}
