{
  "type": "Feature",
  "properties": {
    "date:inception_lower": "2013-07-01",
    "date:inception_upper": "2013-07-01",
    "iso:country": "GB",
    "wof:name": "TA6 6WW",
    "wof:placetype": "postalcode"
  },
  "geometry": {"coordinates":[-2.999712,51.10882],"type":"Point"}
}
