{
  "type": "Feature",
  "properties": {
    "iso:country":"GB",
    "wof:name":"TA6 6WW",
    "wof:placetype":"postalcode"
},
  "geometry": {"coordinates":[-2.99971199078962,51.10881956438782],"type":"Point"}
}