{
  "type": "Feature",
  "properties": {
    "iso:country":"GB",
    "wof:name":"N4 2PA",
    "wof:placetype":"postalcode"
},
  "geometry": {"coordinates":[-0.092673567472,51.5661568785651],"type":"Point"}
}