{
  "type": "Feature",
  "properties": {
    "date:inception_lower": "1980-01-01",
    "date:inception_upper": "1980-01-01",
    "iso:country": "GB",
    "wof:name": "SK2 5BG",
    "wof:placetype": "postalcode"
  },
  "geometry": {"coordinates":[-2.133411,53.406139],"type":"Point"}
}
