{
  "type": "Feature",
  "properties": {
    "iso:country":"GB",
    "wof:name":"SO17 1TX",
    "wof:placetype":"postalcode"
},
  "geometry": {"coordinates":[-1.40442367716821,50.9218332371314],"type":"Point"}
}