{
  "type": "Feature",
  "properties": {
    "date:inception_lower":"1994-12-01",
    "date:inception_upper":"1994-12-31",
    "iso:country":"GB",
    "wof:name":"SO17 1TX",
    "wof:placetype":"postalcode"
},
  "geometry": {"coordinates":[-1.404424,50.921833],"type":"Point"}
}