{
  "type": "Feature",
  "properties": {
    "date:inception_lower": "1980-01-01",
    "date:inception_upper": "1980-01-01",
    "iso:country": "GB",
    "wof:name": "CT15 4JZ",
    "wof:placetype": "postalcode"
  },
  "geometry": {"coordinates":[1.225654,51.225185],"type":"Point"}
}
