{
  "type": "Feature",
  "properties": {
    "date:inception_lower": "2020-04-01",
    "date:inception_upper": "2020-04-01",
    "iso:country": "GB",
    "wof:name": "LL18 6JB",
    "wof:placetype": "postalcode"
  },
  "geometry": {"coordinates":[-3.457892,53.296754],"type":"Point"}
}
