{
  "type": "Feature",
  "properties": {
    "iso:country": "GB",
    "wof:name": "LL18 6JB",
    "wof:placetype": "postalcode"
  },
  "geometry": {"coordinates":[-3.457572,53.296174],"type":"Point"}
}
