{
  "type": "Feature",
  "properties": {
    "iso:country":"GB",
    "wof:name":"HU7 6AQ",
    "wof:placetype":"postalcode"
},
  "geometry": {"coordinates":[-0.31558975134589,53.78140330759039],"type":"Point"}
}