{
  "type": "Feature",
  "properties": {
    "iso:country": "GB",
    "wof:name": "HU7 6AQ",
    "wof:placetype": "postalcode"
  },
  "geometry": {"coordinates":[-0.31559,53.781403],"type":"Point"}
}
