{
  "type": "Feature",
  "properties": {
    "date:inception_lower": "1992-08-01",
    "date:inception_upper": "1992-08-01",
    "iso:country": "GB",
    "wof:name": "HD3 4GX",
    "wof:placetype": "postalcode"
  },
  "geometry": {"coordinates":[-1.83714,53.656107],"type":"Point"}
}
