{
  "type": "Feature",
  "properties": {
    "iso:country":"GB",
    "wof:name":"HD3 4GX",
    "wof:placetype":"postalcode"
},
  "geometry": {"coordinates":[-1.83714017606332,53.65610653235493],"type":"Point"}
}