{
  "type": "Feature",
  "properties": {
    "date:inception_lower": "2013-01-01",
    "date:inception_upper": "2013-01-01",
    "iso:country": "GB",
    "wof:name": "CV23 0JW",
    "wof:placetype": "postalcode"
  },
  "geometry": {"coordinates":[-1.309672,52.417806],"type":"Point"}
}
