{
  "type": "Feature",
  "properties": {
    "iso:country":"GB",
    "wof:name":"CV23 0JW",
    "wof:placetype":"postalcode"
},
  "geometry": {"coordinates":[-1.30967233958795,52.41780557447524],"type":"Point"}
}