{
  "type": "Feature",
  "properties": {
    "iso:country":"GB",
    "wof:name":"CF23 9DU",
    "wof:placetype":"postalcode"
},
  "geometry": {"coordinates":[-3.15198806151308,51.50523115704159],"type":"Point"}
}