{
  "type": "Feature",
  "properties": {
    "iso:country": "GB",
    "wof:name": "CV3 3EF",
    "wof:placetype": "postalcode"
  },
  "geometry": {"coordinates":[-1.466181,52.380982],"type":"Point"}
}
