{
  "type": "Feature",
  "properties": {
    "iso:country":"GB",
    "wof:name":"CV3 3EF",
    "wof:placetype":"postalcode"
},
  "geometry": {"coordinates":[-1.46618058209172,52.38098247963781],"type":"Point"}
}