{
  "type": "Feature",
  "properties": {
    "date:inception_lower":"1980-01-01",
    "date:inception_upper":"1980-01-31",
    "iso:country":"GB",
    "wof:name":"CV3 3EF",
    "wof:placetype":"postalcode"
},
  "geometry": {"coordinates":[-1.466181,52.380982],"type":"Point"}
}