{
  "type": "Feature",
  "properties": {
    "iso:country":"GB",
    "wof:name":"N14 6DJ",
    "wof:placetype":"postalcode"
},
  "geometry": {"coordinates":[-0.12590766650663,51.62882992244714],"type":"Point"}
}