{
  "type": "Feature",
  "properties": {
    "date:inception_lower":"1980-01-01",
    "date:inception_upper":"1980-01-31",
    "iso:country":"GB",
    "wof:name":"PO9 3DX",
    "wof:placetype":"postalcode"
},
  "geometry": {"coordinates":[-0.992957,50.859946],"type":"Point"}
}