{
  "type": "Feature",
  "properties": {
    "iso:country":"GB",
    "wof:name":"PO9 3DX",
    "wof:placetype":"postalcode"
},
  "geometry": {"coordinates":[-0.99295748794547,50.85994641785287],"type":"Point"}
}