{
  "type": "Feature",
  "properties": {
    "date:inception_lower":"1980-01-01",
    "date:inception_upper":"1980-01-31",
    "iso:country":"GB",
    "wof:name":"NE13 7NL",
    "wof:placetype":"postalcode"
},
  "geometry": {"coordinates":[-1.635382,55.040975],"type":"Point"}
}