{
  "type": "Feature",
  "properties": {
    "iso:country":"GB",
    "wof:name":"B43 7LL",
    "wof:placetype":"postalcode"
},
  "geometry": {"coordinates":[-1.90503080415988,52.56184030260405],"type":"Point"}
}