{
  "type": "Feature",
  "properties": {
    "iso:country": "GB",
    "wof:name": "B43 7LL",
    "wof:placetype": "postalcode"
  },
  "geometry": {"coordinates":[-1.905031,52.56184],"type":"Point"}
}
