{
  "type": "Feature",
  "properties": {
    "iso:country":"GB",
    "wof:name":"BN21 1QP",
    "wof:placetype":"postalcode"
},
  "geometry": {"coordinates":[0.26015628021331,50.77288994076851],"type":"Point"}
}