{
  "type": "Feature",
  "properties": {
    "iso:country":"GB",
    "wof:name":"SY1 3HA",
    "wof:placetype":"postalcode"
},
  "geometry": {"coordinates":[-2.74287780736714,52.73281746025906],"type":"Point"}
}