{
  "type": "Feature",
  "properties": {
    "iso:country":"GB",
    "wof:name":"HU4 6TA",
    "wof:placetype":"postalcode"
},
  "geometry": {"coordinates":[-0.39996948585381,53.74290827878124],"type":"Point"}
}