{
  "type": "Feature",
  "properties": {
    "iso:country": "GB",
    "wof:name": "GL14 2SL",
    "wof:placetype": "postalcode"
  },
  "geometry": {"coordinates":[-2.499726,51.825264],"type":"Point"}
}
