{
  "type": "Feature",
  "properties": {
    "date:inception_lower":"1980-01-01",
    "date:inception_upper":"1980-01-31",
    "iso:country":"GB",
    "wof:name":"GL14 2SL",
    "wof:placetype":"postalcode"
},
  "geometry": {"coordinates":[-2.499711,51.825257],"type":"Point"}
}