{
  "type": "Feature",
  "properties": {
    "iso:country": "GB",
    "wof:name": "E14 7LP",
    "wof:placetype": "postalcode"
  },
  "geometry": {"coordinates":[-0.038178,51.513128],"type":"Point"}
}
