{
  "type": "Feature",
  "properties": {
    "iso:country":"GB",
    "wof:name":"E14 7LP",
    "wof:placetype":"postalcode"
},
  "geometry": {"coordinates":[-0.0381776434522,51.51312831689933],"type":"Point"}
}