{
  "type": "Feature",
  "properties": {
    "iso:country":"GB",
    "wof:name":"LE7 1ZH",
    "wof:placetype":"postalcode"
},
  "geometry": {"coordinates":[-1.08733281029593,52.69956008206963],"type":"Point"}
}