{
  "type": "Feature",
  "properties": {
    "date:inception_lower": "2021-05-01",
    "date:inception_upper": "2021-05-01",
    "iso:country": "GB",
    "wof:name": "PE28 4FP",
    "wof:placetype": "postalcode"
  },
  "geometry": {"coordinates":[-0.22983,52.317428],"type":"Point"}
}
