{
  "type": "Feature",
  "properties": {
    "date:inception_lower": "1980-01-01",
    "date:inception_upper": "1980-01-01",
    "iso:country": "GB",
    "wof:name": "M30 8LT",
    "wof:placetype": "postalcode"
  },
  "geometry": {"coordinates":[-2.366685,53.486629],"type":"Point"}
}
