{
  "type": "Feature",
  "properties": {
    "iso:country":"GB",
    "wof:name":"M30 8LT",
    "wof:placetype":"postalcode"
},
  "geometry": {"coordinates":[-2.36668465015944,53.48662872727701],"type":"Point"}
}