{
  "type": "Feature",
  "properties": {
    "iso:country":"GB",
    "wof:name":"S73 0JX",
    "wof:placetype":"postalcode"
},
  "geometry": {"coordinates":[-1.39859913298921,53.51687954809643],"type":"Point"}
}