{
  "type": "Feature",
  "properties": {
    "iso:country":"GB",
    "wof:name":"NG12 2NT",
    "wof:placetype":"postalcode"
},
  "geometry": {"coordinates":[-1.00493878350882,52.94437282507527],"type":"Point"}
}