{
  "type": "Feature",
  "properties": {
    "date:inception_lower": "1998-06-01",
    "date:inception_upper": "1998-06-01",
    "iso:country": "GB",
    "wof:name": "NG12 2NT",
    "wof:placetype": "postalcode"
  },
  "geometry": {"coordinates":[-1.004939,52.944373],"type":"Point"}
}
