{
  "type": "Feature",
  "properties": {
    "iso:country":"GB",
    "wof:name":"LA4 4TD",
    "wof:placetype":"postalcode"
},
  "geometry": {"coordinates":[-2.85722051868907,54.06142530022893],"type":"Point"}
}