{
  "type": "Feature",
  "properties": {
    "date:inception_lower":"1996-06-01",
    "date:inception_upper":"1996-06-30",
    "iso:country":"GB",
    "wof:name":"LA4 4TD",
    "wof:placetype":"postalcode"
},
  "geometry": {"coordinates":[-2.85722,54.061425],"type":"Point"}
}