{
  "type": "Feature",
  "properties": {
    "iso:country":"GB",
    "wof:name":"IP5 3QY",
    "wof:placetype":"postalcode"
},
  "geometry": {"coordinates":[1.27059615403955,52.06812776877577],"type":"Point"}
}