{
  "type": "Feature",
  "properties": {
    "iso:country": "GB",
    "wof:name": "HS6 5EH",
    "wof:placetype": "postalcode"
  },
  "geometry": {"coordinates":[-7.3157,57.52102],"type":"Point"}
}
