{
  "type": "Feature",
  "properties": {
    "iso:country":"GB",
    "wof:name":"HS6 5EH",
    "wof:placetype":"postalcode"
},
  "geometry": {"coordinates":[-7.31570013749392,57.52102008709551],"type":"Point"}
}