{
  "type": "Feature",
  "properties": {
    "date:inception_lower": "1995-07-01",
    "date:inception_upper": "1995-07-01",
    "iso:country": "GB",
    "wof:name": "HS6 5EH",
    "wof:placetype": "postalcode"
  },
  "geometry": {"coordinates":[-7.3157,57.52102],"type":"Point"}
}
