{
  "type": "Feature",
  "properties": {
    "iso:country": "GB",
    "wof:name": "CH41 0DU",
    "wof:placetype": "postalcode"
  },
  "geometry": {"coordinates":[-3.060961,53.397104],"type":"Point"}
}
