{
  "type": "Feature",
  "properties": {
    "iso:country":"GB",
    "wof:name":"M34 3BP",
    "wof:placetype":"postalcode"
},
  "geometry": {"coordinates":[-2.10549547154778,53.46087197472228],"type":"Point"}
}