{
  "type": "Feature",
  "properties": {
    "iso:country":"GB",
    "wof:name":"TA4 1PL",
    "wof:placetype":"postalcode"
},
  "geometry": {"coordinates":[-3.25062030997868,51.02396041626363],"type":"Point"}
}