{
  "type": "Feature",
  "properties": {
    "iso:country":"GB",
    "wof:name":"B21 8JY",
    "wof:placetype":"postalcode"
},
  "geometry": {"coordinates":[-1.95669579508391,52.51121242493851],"type":"Point"}
}