{
  "type": "Feature",
  "properties": {
    "iso:country": "GB",
    "wof:name": "RH20 3HW",
    "wof:placetype": "postalcode"
  },
  "geometry": {"coordinates":[-0.443335,50.925741],"type":"Point"}
}
