{
  "type": "Feature",
  "properties": {
    "iso:country": "GB",
    "wof:name": "CH63 5PD",
    "wof:placetype": "postalcode"
  },
  "geometry": {"coordinates":[-3.03102,53.362992],"type":"Point"}
}
