{
  "type": "Feature",
  "properties": {
    "iso:country":"GB",
    "wof:name":"CH63 5PD",
    "wof:placetype":"postalcode"
},
  "geometry": {"coordinates":[-3.03101985730411,53.36299195914372],"type":"Point"}
}