{
  "type": "Feature",
  "properties": {
    "iso:country": "GB",
    "wof:name": "CA20 1NX",
    "wof:placetype": "postalcode"
  },
  "geometry": {"coordinates":[-3.478875,54.391646],"type":"Point"}
}
