{
  "type": "Feature",
  "properties": {
    "iso:country":"GB",
    "wof:name":"YO18 8AA",
    "wof:placetype":"postalcode"
},
  "geometry": {"coordinates":[-0.78146043010554,54.24613546428983],"type":"Point"}
}