{
  "type": "Feature",
  "properties": {
    "date:inception_lower": "1980-01-01",
    "date:inception_upper": "1980-01-01",
    "iso:country": "GB",
    "wof:name": "YO18 8AA",
    "wof:placetype": "postalcode"
  },
  "geometry": {"coordinates":[-0.781425,54.246223],"type":"Point"}
}
