{
  "type": "Feature",
  "properties": {
    "iso:country": "GB",
    "wof:name": "YO18 8AA",
    "wof:placetype": "postalcode"
  },
  "geometry": {"coordinates":[-0.78146,54.246135],"type":"Point"}
}
