{
  "type": "Feature",
  "properties": {
    "date:inception_lower": "2016-03-01",
    "date:inception_upper": "2016-03-01",
    "iso:country": "GB",
    "wof:name": "BB5 4EG",
    "wof:placetype": "postalcode"
  },
  "geometry": {"coordinates":[-2.385041,53.757334],"type":"Point"}
}
