{
  "type": "Feature",
  "properties": {
    "iso:country":"GB",
    "wof:name":"IP30 0QG",
    "wof:placetype":"postalcode"
},
  "geometry": {"coordinates":[0.84281497330266,52.18251748048779],"type":"Point"}
}