{
  "type": "Feature",
  "properties": {
    "iso:country": "GB",
    "wof:name": "IP30 0QG",
    "wof:placetype": "postalcode"
  },
  "geometry": {"coordinates":[0.842714,52.182977],"type":"Point"}
}
