{
  "type": "Feature",
  "properties": {
    "iso:country": "GB",
    "wof:name": "OX26 4YL",
    "wof:placetype": "postalcode"
  },
  "geometry": {"coordinates":[-1.138693,51.909034],"type":"Point"}
}
