{
  "type": "Feature",
  "properties": {
    "iso:country":"GB",
    "wof:name":"OX26 4YL",
    "wof:placetype":"postalcode"
},
  "geometry": {"coordinates":[-1.13869268434465,51.90903354305228],"type":"Point"}
}