{
  "type": "Feature",
  "properties": {
    "iso:country":"GB",
    "wof:name":"G76 7AW",
    "wof:placetype":"postalcode"
},
  "geometry": {"coordinates":[-4.27893580222145,55.78699405524105],"type":"Point"}
}