{
  "type": "Feature",
  "properties": {
    "iso:country": "GB",
    "wof:name": "HR4 9LZ",
    "wof:placetype": "postalcode"
  },
  "geometry": {"coordinates":[-2.738467,52.072042],"type":"Point"}
}
