{
  "type": "Feature",
  "properties": {
    "iso:country":"GB",
    "wof:name":"HR4 9LZ",
    "wof:placetype":"postalcode"
},
  "geometry": {"coordinates":[-2.7384665868194,52.07204240952049],"type":"Point"}
}