{
  "type": "Feature",
  "properties": {
    "iso:country":"GB",
    "wof:name":"DE24 9RQ",
    "wof:placetype":"postalcode"
},
  "geometry": {"coordinates":[-1.49680034431668,52.87941340738972],"type":"Point"}
}