{
  "type": "Feature",
  "properties": {
    "iso:country":"GB",
    "wof:name":"WF3 4DU",
    "wof:placetype":"postalcode"
},
  "geometry": {"coordinates":[-1.4833763825795,53.71466862581397],"type":"Point"}
}