{
  "type": "Feature",
  "properties": {
    "iso:country": "GB",
    "wof:name": "KT8 2QD",
    "wof:placetype": "postalcode"
  },
  "geometry": {"coordinates":[-0.37104,51.403391],"type":"Point"}
}
