{
  "type": "Feature",
  "properties": {
    "iso:country":"GB",
    "wof:name":"S35 2WA",
    "wof:placetype":"postalcode"
},
  "geometry": {"coordinates":[-1.47282733320841,53.46354122317693],"type":"Point"}
}