{
  "type": "Feature",
  "properties": {
    "iso:country":"GB",
    "wof:name":"SA43 1LH",
    "wof:placetype":"postalcode"
},
  "geometry": {"coordinates":[-4.66198400049791,52.08421679195201],"type":"Point"}
}