{
  "type": "Feature",
  "properties": {
    "iso:country": "GB",
    "wof:name": "SA43 1LH",
    "wof:placetype": "postalcode"
  },
  "geometry": {"coordinates":[-4.661984,52.084217],"type":"Point"}
}
