{
  "type": "Feature",
  "properties": {
    "iso:country": "GB",
    "wof:name": "DE12 6HY",
    "wof:placetype": "postalcode"
  },
  "geometry": {"coordinates":[-1.559701,52.726401],"type":"Point"}
}
