{
  "type": "Feature",
  "properties": {
    "iso:country":"GB",
    "wof:name":"HU3 6EB",
    "wof:placetype":"postalcode"
},
  "geometry": {"coordinates":[-0.37516455867918,53.74243971886096],"type":"Point"}
}