{
  "type": "Feature",
  "properties": {
    "iso:country":"GB",
    "wof:name":"RG20 8AT",
    "wof:placetype":"postalcode"
},
  "geometry": {"coordinates":[-1.33955368705443,51.45225970433757],"type":"Point"}
}