{
  "type": "Feature",
  "properties": {
    "iso:country":"GB",
    "wof:name":"SO14 0LH",
    "wof:placetype":"postalcode"
},
  "geometry": {"coordinates":[-1.39921341088564,50.91434281210652],"type":"Point"}
}