{
  "type": "Feature",
  "properties": {
    "date:inception_lower": "1994-12-01",
    "date:inception_upper": "1994-12-01",
    "iso:country": "GB",
    "wof:name": "SO14 0LH",
    "wof:placetype": "postalcode"
  },
  "geometry": {"coordinates":[-1.399204,50.914334],"type":"Point"}
}
