{
  "type": "Feature",
  "properties": {
    "iso:country":"GB",
    "wof:name":"W14 8XL",
    "wof:placetype":"postalcode"
},
  "geometry": {"coordinates":[-0.2078489653106,51.49553865858021],"type":"Point"}
}