{
  "type": "Feature",
  "properties": {
    "date:inception_lower": "2009-05-01",
    "date:inception_upper": "2009-05-01",
    "iso:country": "GB",
    "wof:name": "DA9 9FF",
    "wof:placetype": "postalcode"
  },
  "geometry": {"coordinates":[0.292441,51.455034],"type":"Point"}
}
