{
  "type": "Feature",
  "properties": {
    "iso:country":"GB",
    "wof:name":"CV9 1JG",
    "wof:placetype":"postalcode"
},
  "geometry": {"coordinates":[-1.53690591597316,52.57868371494587],"type":"Point"}
}