{
  "type": "Feature",
  "properties": {
    "date:inception_lower": "1980-01-01",
    "date:inception_upper": "1980-01-01",
    "iso:country": "GB",
    "wof:name": "CV9 1JG",
    "wof:placetype": "postalcode"
  },
  "geometry": {"coordinates":[-1.536906,52.578684],"type":"Point"}
}
