{
  "type": "Feature",
  "properties": {
    "date:inception_lower":"1998-12-01",
    "date:inception_upper":"1998-12-31",
    "iso:country":"GB",
    "wof:name":"CT18 7PG",
    "wof:placetype":"postalcode"
},
  "geometry": {"coordinates":[1.167311,51.111288],"type":"Point"}
}