{
  "type": "Feature",
  "properties": {
    "iso:country": "GB",
    "wof:name": "CT18 7PG",
    "wof:placetype": "postalcode"
  },
  "geometry": {"coordinates":[1.167311,51.111288],"type":"Point"}
}
