{
  "type": "Feature",
  "properties": {
    "iso:country":"GB",
    "wof:name":"SY20 8JA",
    "wof:placetype":"postalcode"
},
  "geometry": {"coordinates":[-3.84395239317945,52.59364584690601],"type":"Point"}
}