{
  "type": "Feature",
  "properties": {
    "date:inception_lower": "1980-01-01",
    "date:inception_upper": "1980-01-01",
    "iso:country": "GB",
    "wof:name": "SY20 8JA",
    "wof:placetype": "postalcode"
  },
  "geometry": {"coordinates":[-3.845854,52.5948],"type":"Point"}
}
