{
  "type": "Feature",
  "properties": {
    "date:inception_lower": "1980-01-01",
    "date:inception_upper": "1980-01-01",
    "iso:country": "GB",
    "wof:name": "CO10 0SE",
    "wof:placetype": "postalcode"
  },
  "geometry": {"coordinates":[0.777886,52.059894],"type":"Point"}
}
