{
  "type": "Feature",
  "properties": {
    "iso:country":"GB",
    "wof:name":"CO10 0SE",
    "wof:placetype":"postalcode"
},
  "geometry": {"coordinates":[0.77783895192089,52.05986243462625],"type":"Point"}
}