{
  "type": "Feature",
  "properties": {
    "iso:country":"GB",
    "wof:name":"NW9 5HF",
    "wof:placetype":"postalcode"
},
  "geometry": {"coordinates":[-0.24193729792237,51.59611247618223],"type":"Point"}
}