{
  "type": "Feature",
  "properties": {
    "date:inception_lower": "1996-06-01",
    "date:inception_upper": "1996-06-01",
    "iso:country": "GB",
    "wof:name": "HR2 6PY",
    "wof:placetype": "postalcode"
  },
  "geometry": {"coordinates":[-2.704669,52.04008],"type":"Point"}
}
