{
  "type": "Feature",
  "properties": {
    "iso:country":"GB",
    "wof:name":"HR2 6PY",
    "wof:placetype":"postalcode"
},
  "geometry": {"coordinates":[-2.7046693731142,52.04008040008193],"type":"Point"}
}