{
  "type": "Feature",
  "properties": {
    "iso:country":"GB",
    "wof:name":"OL16 2DT",
    "wof:placetype":"postalcode"
},
  "geometry": {"coordinates":[-2.14512010414219,53.62337565896362],"type":"Point"}
}