{
  "type": "Feature",
  "properties": {
    "iso:country":"GB",
    "wof:name":"NR20 4RE",
    "wof:placetype":"postalcode"
},
  "geometry": {"coordinates":[0.98187453617462,52.74295997234584],"type":"Point"}
}