{
  "type": "Feature",
  "properties": {
    "date:inception_lower": "2018-03-01",
    "date:inception_upper": "2018-03-01",
    "iso:country": "GB",
    "wof:name": "SN25 2TE",
    "wof:placetype": "postalcode"
  },
  "geometry": {"coordinates":[-1.816923,51.611597],"type":"Point"}
}
