{
  "type": "Feature",
  "properties": {
    "iso:country": "GB",
    "wof:name": "SN25 2TE",
    "wof:placetype": "postalcode"
  },
  "geometry": {"coordinates":[-1.816967,51.611552],"type":"Point"}
}
