{
  "type": "Feature",
  "properties": {
    "iso:country":"GB",
    "wof:name":"N9 9TS",
    "wof:placetype":"postalcode"
},
  "geometry": {"coordinates":[-0.07469684230414,51.62176949026014],"type":"Point"}
}