{
  "type": "Feature",
  "properties": {
    "iso:country":"GB",
    "wof:name":"HP8 4QF",
    "wof:placetype":"postalcode"
},
  "geometry": {"coordinates":[-0.56961596068198,51.63201650716095],"type":"Point"}
}