{
  "type": "Feature",
  "properties": {
    "iso:country": "GB",
    "wof:name": "HR3 6PD",
    "wof:placetype": "postalcode"
  },
  "geometry": {"coordinates":[-2.95185,52.134023],"type":"Point"}
}
