{
  "type": "Feature",
  "properties": {
    "iso:country": "GB",
    "wof:name": "WV1 1PB",
    "wof:placetype": "postalcode"
  },
  "geometry": {"coordinates":[-2.128086,52.596437],"type":"Point"}
}
