{
  "type": "Feature",
  "properties": {
    "iso:country":"GB",
    "wof:name":"WV1 1PB",
    "wof:placetype":"postalcode"
},
  "geometry": {"coordinates":[-2.1280857927741,52.59643736952001],"type":"Point"}
}