{
  "type": "Feature",
  "properties": {
    "date:inception_lower": "1987-04-01",
    "date:inception_upper": "1987-04-01",
    "iso:country": "GB",
    "wof:name": "WV1 1PB",
    "wof:placetype": "postalcode"
  },
  "geometry": {"coordinates":[-2.128086,52.596437],"type":"Point"}
}
