{
  "type": "Feature",
  "properties": {
    "iso:country":"GB",
    "wof:name":"NN12 6RE",
    "wof:placetype":"postalcode"
},
  "geometry": {"coordinates":[-0.98742361344316,52.12060193003889],"type":"Point"}
}