{
  "type": "Feature",
  "properties": {
    "date:inception_lower":"1993-08-01",
    "date:inception_upper":"1993-08-31",
    "iso:country":"GB",
    "wof:name":"NN12 6RE",
    "wof:placetype":"postalcode"
},
  "geometry": {"coordinates":[-0.987424,52.120602],"type":"Point"}
}