{
  "type": "Feature",
  "properties": {
    "iso:country": "GB",
    "wof:name": "SK11 6SH",
    "wof:placetype": "postalcode"
  },
  "geometry": {"coordinates":[-2.131003,53.254458],"type":"Point"}
}
