{
  "type": "Feature",
  "properties": {
    "date:inception_lower": "1995-07-01",
    "date:inception_upper": "1995-07-01",
    "iso:country": "GB",
    "wof:name": "SK11 6SH",
    "wof:placetype": "postalcode"
  },
  "geometry": {"coordinates":[-2.131003,53.254458],"type":"Point"}
}
