{
  "type": "Feature",
  "properties": {
    "date:inception_lower":"2007-02-01",
    "date:inception_upper":"2007-02-28",
    "iso:country":"GB",
    "wof:name":"B23 6QT",
    "wof:placetype":"postalcode"
},
  "geometry": {"coordinates":[-1.84057,52.524176],"type":"Point"}
}