{
  "type": "Feature",
  "properties": {
    "iso:country":"GB",
    "wof:name":"B23 6QT",
    "wof:placetype":"postalcode"
},
  "geometry": {"coordinates":[-1.84057029645469,52.52417556161466],"type":"Point"}
}