{
  "type": "Feature",
  "properties": {
    "date:inception_lower": "1980-01-01",
    "date:inception_upper": "1980-01-01",
    "iso:country": "GB",
    "wof:name": "CH2 4EJ",
    "wof:placetype": "postalcode"
  },
  "geometry": {"coordinates":[-2.82854,53.221834],"type":"Point"}
}
