{
  "type": "Feature",
  "properties": {
    "iso:country":"GB",
    "wof:name":"NW10 1BJ",
    "wof:placetype":"postalcode"
},
  "geometry": {"coordinates":[-0.24337787743566,51.55389718526007],"type":"Point"}
}