{
  "type": "Feature",
  "properties": {
    "iso:country":"GB",
    "wof:name":"RH2 9QQ",
    "wof:placetype":"postalcode"
},
  "geometry": {"coordinates":[-0.20491752901943,51.24186553077226],"type":"Point"}
}