{
  "type": "Feature",
  "properties": {
    "date:inception_lower": "1999-06-01",
    "date:inception_upper": "1999-06-01",
    "iso:country": "GB",
    "wof:name": "RH2 9QQ",
    "wof:placetype": "postalcode"
  },
  "geometry": {"coordinates":[-0.204917,51.241866],"type":"Point"}
}
