{
  "type": "Feature",
  "properties": {
    "date:inception_lower": "1980-01-01",
    "date:inception_upper": "1980-01-01",
    "iso:country": "GB",
    "wof:name": "BR2 0AA",
    "wof:placetype": "postalcode"
  },
  "geometry": {"coordinates":[-0.003321,51.407775],"type":"Point"}
}
