{
  "type": "Feature",
  "properties": {
    "iso:country":"GB",
    "wof:name":"DG12 5RR",
    "wof:placetype":"postalcode"
},
  "geometry": {"coordinates":[-3.35941923145711,55.01607766173717],"type":"Point"}
}