{
  "type": "Feature",
  "properties": {
    "iso:country": "GB",
    "wof:name": "GL19 3QL",
    "wof:placetype": "postalcode"
  },
  "geometry": {"coordinates":[-2.337055,51.961238],"type":"Point"}
}
