{
  "type": "Feature",
  "properties": {
    "iso:country":"GB",
    "wof:name":"HP20 2RB",
    "wof:placetype":"postalcode"
},
  "geometry": {"coordinates":[-0.81705364891309,51.81668695651243],"type":"Point"}
}