{
  "type": "Feature",
  "properties": {
    "date:inception_lower": "1980-01-01",
    "date:inception_upper": "1980-01-01",
    "iso:country": "GB",
    "wof:name": "HP20 2RB",
    "wof:placetype": "postalcode"
  },
  "geometry": {"coordinates":[-0.817054,51.816687],"type":"Point"}
}
