{
  "type": "Feature",
  "properties": {
    "iso:country": "GB",
    "wof:name": "S72 8NG",
    "wof:placetype": "postalcode"
  },
  "geometry": {"coordinates":[-1.408158,53.592853],"type":"Point"}
}
