{
  "type": "Feature",
  "properties": {
    "date:inception_lower": "2021-07-01",
    "date:inception_upper": "2021-07-01",
    "iso:country": "GB",
    "wof:name": "WN8 0BW",
    "wof:placetype": "postalcode"
  },
  "geometry": {"coordinates":[-2.739192,53.533891],"type":"Point"}
}
