{
  "type": "Feature",
  "properties": {
    "iso:country":"GB",
    "wof:name":"OX7 4DX",
    "wof:placetype":"postalcode"
},
  "geometry": {"coordinates":[-1.43625295066545,51.91336067898306],"type":"Point"}
}