{
  "type": "Feature",
  "properties": {
    "iso:country": "GB",
    "wof:name": "SP11 8AX",
    "wof:placetype": "postalcode"
  },
  "geometry": {"coordinates":[-1.563464,51.198488],"type":"Point"}
}
