{
  "type": "Feature",
  "properties": {
    "iso:country":"GB",
    "wof:name":"KY11 1AF",
    "wof:placetype":"postalcode"
},
  "geometry": {"coordinates":[-3.39878765913478,56.03026113006328],"type":"Point"}
}