{
  "type": "Feature",
  "properties": {
    "iso:country":"GB",
    "wof:name":"CT2 8LS",
    "wof:placetype":"postalcode"
},
  "geometry": {"coordinates":[1.06942296097279,51.28341461592785],"type":"Point"}
}