{
  "type": "Feature",
  "properties": {
    "iso:country":"GB",
    "wof:name":"AL3 8RW",
    "wof:placetype":"postalcode"
},
  "geometry": {"coordinates":[-0.46487088542188,51.83345115530039],"type":"Point"}
}