{
  "type": "Feature",
  "properties": {
    "date:inception_lower": "1980-01-01",
    "date:inception_upper": "1980-01-01",
    "iso:country": "GB",
    "wof:name": "SY14 7DS",
    "wof:placetype": "postalcode"
  },
  "geometry": {"coordinates":[-2.8055,53.056213],"type":"Point"}
}
