{
  "type": "Feature",
  "properties": {
    "iso:country":"GB",
    "wof:name":"SO14 0PL",
    "wof:placetype":"postalcode"
},
  "geometry": {"coordinates":[-1.3899884934346,50.91054513999554],"type":"Point"}
}