{
  "type": "Feature",
  "properties": {
    "iso:country":"GB",
    "wof:name":"TQ5 9QD",
    "wof:placetype":"postalcode"
},
  "geometry": {"coordinates":[-3.51413548550817,50.38555416828855],"type":"Point"}
}