{
  "type": "Feature",
  "properties": {
    "date:inception_lower": "1980-01-01",
    "date:inception_upper": "1980-01-01",
    "iso:country": "GB",
    "wof:name": "TQ5 9QD",
    "wof:placetype": "postalcode"
  },
  "geometry": {"coordinates":[-3.514134,50.385467],"type":"Point"}
}
