{
  "type": "Feature",
  "properties": {
    "iso:country": "GB",
    "wof:name": "G21 3DX",
    "wof:placetype": "postalcode"
  },
  "geometry": {"coordinates":[-4.202784,55.889072],"type":"Point"}
}
