{
  "type": "Feature",
  "properties": {
    "iso:country":"GB",
    "wof:name":"DY8 1NN",
    "wof:placetype":"postalcode"
},
  "geometry": {"coordinates":[-2.13586973029468,52.4498573751717],"type":"Point"}
}