{
  "type": "Feature",
  "properties": {
    "iso:country":"GB",
    "wof:name":"BN13 2NJ",
    "wof:placetype":"postalcode"
},
  "geometry": {"coordinates":[-0.4069841301176,50.83125158719074],"type":"Point"}
}