{
  "type": "Feature",
  "properties": {
    "iso:country": "GB",
    "wof:name": "HR9 6BH",
    "wof:placetype": "postalcode"
  },
  "geometry": {"coordinates":[-2.598537,51.916],"type":"Point"}
}
