{
  "type": "Feature",
  "properties": {
    "iso:country":"GB",
    "wof:name":"HR9 6BH",
    "wof:placetype":"postalcode"
},
  "geometry": {"coordinates":[-2.59853715412784,51.91600046286376],"type":"Point"}
}