{
  "type": "Feature",
  "properties": {
    "date:inception_lower": "1994-05-01",
    "date:inception_upper": "1994-05-01",
    "iso:country": "GB",
    "wof:name": "HR9 6BH",
    "wof:placetype": "postalcode"
  },
  "geometry": {"coordinates":[-2.598537,51.916],"type":"Point"}
}
