{
  "type": "Feature",
  "properties": {
    "iso:country":"GB",
    "wof:name":"MK41 9SR",
    "wof:placetype":"postalcode"
},
  "geometry": {"coordinates":[-0.43407661351581,52.1398269600982],"type":"Point"}
}