{
  "type": "Feature",
  "properties": {
    "iso:country":"GB",
    "wof:name":"SN15 3FT",
    "wof:placetype":"postalcode"
},
  "geometry": {"coordinates":[-2.11066041519405,51.44560473267141],"type":"Point"}
}