{
  "type": "Feature",
  "properties": {
    "date:inception_lower": "1980-01-01",
    "date:inception_upper": "1980-01-01",
    "iso:country": "GB",
    "wof:name": "SA69 9HE",
    "wof:placetype": "postalcode"
  },
  "geometry": {"coordinates":[-4.699041,51.710794],"type":"Point"}
}
