{
  "type": "Feature",
  "properties": {
    "iso:country":"GB",
    "wof:name":"SY12 9BD",
    "wof:placetype":"postalcode"
},
  "geometry": {"coordinates":[-2.9152831267713,52.86876883797186],"type":"Point"}
}