{
  "type": "Feature",
  "properties": {
    "date:inception_lower": "1992-08-01",
    "date:inception_upper": "1992-08-01",
    "iso:country": "GB",
    "wof:name": "IP25 6HQ",
    "wof:placetype": "postalcode"
  },
  "geometry": {"coordinates":[0.805905,52.570607],"type":"Point"}
}
