{
  "type": "Feature",
  "properties": {
    "iso:country":"GB",
    "wof:name":"HA5 4TT",
    "wof:placetype":"postalcode"
},
  "geometry": {"coordinates":[-0.3875989714727,51.60638659908769],"type":"Point"}
}