{
  "type": "Feature",
  "properties": {
    "date:inception_lower": "1980-01-01",
    "date:inception_upper": "1980-01-01",
    "iso:country": "GB",
    "wof:name": "IP19 0RB",
    "wof:placetype": "postalcode"
  },
  "geometry": {"coordinates":[1.49669,52.355878],"type":"Point"}
}
