{
  "type": "Feature",
  "properties": {
    "iso:country": "GB",
    "wof:name": "GU21 5EJ",
    "wof:placetype": "postalcode"
  },
  "geometry": {"coordinates":[-0.543606,51.325505],"type":"Point"}
}
