{
  "type": "Feature",
  "properties": {
    "iso:country": "GB",
    "wof:name": "B91 3XD",
    "wof:placetype": "postalcode"
  },
  "geometry": {"coordinates":[-1.783064,52.400247],"type":"Point"}
}
