{
  "type": "Feature",
  "properties": {
    "iso:country":"GB",
    "wof:name":"LS29 7RA",
    "wof:placetype":"postalcode"
},
  "geometry": {"coordinates":[-1.74997667726727,53.9057331572707],"type":"Point"}
}