{
  "type": "Feature",
  "properties": {
    "iso:country": "GB",
    "wof:name": "LS29 7RA",
    "wof:placetype": "postalcode"
  },
  "geometry": {"coordinates":[-1.749977,53.905733],"type":"Point"}
}
