{
  "type": "Feature",
  "properties": {
    "iso:country": "GB",
    "wof:name": "GU18 5TH",
    "wof:placetype": "postalcode"
  },
  "geometry": {"coordinates":[-0.669847,51.34991],"type":"Point"}
}
