{
  "type": "Feature",
  "properties": {
    "iso:country":"GB",
    "wof:name":"LE8 4GB",
    "wof:placetype":"postalcode"
},
  "geometry": {"coordinates":[-1.15981143358147,52.57707698099637],"type":"Point"}
}