{
  "type": "Feature",
  "properties": {
    "date:inception_lower": "1980-01-01",
    "date:inception_upper": "1980-01-01",
    "iso:country": "GB",
    "wof:name": "NR32 3JN",
    "wof:placetype": "postalcode"
  },
  "geometry": {"coordinates":[1.698417,52.482151],"type":"Point"}
}
