{
  "type": "Feature",
  "properties": {
    "iso:country":"GB",
    "wof:name":"ME2 2EW",
    "wof:placetype":"postalcode"
},
  "geometry": {"coordinates":[0.48632173311243,51.39324465338518],"type":"Point"}
}