{
  "type": "Feature",
  "properties": {
    "iso:country":"GB",
    "wof:name":"CO2 0NR",
    "wof:placetype":"postalcode"
},
  "geometry": {"coordinates":[0.81821864757042,51.8347160987917],"type":"Point"}
}