{
  "type": "Feature",
  "properties": {
    "date:inception_lower": "2000-06-01",
    "date:inception_upper": "2000-06-01",
    "iso:country": "GB",
    "wof:name": "CA7 3LY",
    "wof:placetype": "postalcode"
  },
  "geometry": {"coordinates":[-3.293471,54.797339],"type":"Point"}
}
