{
  "type": "Feature",
  "properties": {
    "iso:country": "GB",
    "wof:name": "IP12 2JA",
    "wof:placetype": "postalcode"
  },
  "geometry": {"coordinates":[1.44781,52.143924],"type":"Point"}
}
