{
  "type": "Feature",
  "properties": {
    "date:inception_lower":"1996-12-01",
    "date:inception_upper":"1996-12-31",
    "iso:country":"GB",
    "wof:name":"SN16 9UX",
    "wof:placetype":"postalcode"
},
  "geometry": {"coordinates":[-2.096356,51.594516],"type":"Point"}
}