{
  "type": "Feature",
  "properties": {
    "iso:country":"GB",
    "wof:name":"NR6 5PG",
    "wof:placetype":"postalcode"
},
  "geometry": {"coordinates":[1.26202006586575,52.66087069013036],"type":"Point"}
}