{
  "type": "Feature",
  "properties": {
    "iso:country": "GB",
    "wof:name": "NR6 5PG",
    "wof:placetype": "postalcode"
  },
  "geometry": {"coordinates":[1.26202,52.660871],"type":"Point"}
}
