{
  "type": "Feature",
  "properties": {
    "date:inception_lower": "1980-01-01",
    "date:inception_upper": "1980-01-01",
    "iso:country": "GB",
    "wof:name": "IP16 4TB",
    "wof:placetype": "postalcode"
  },
  "geometry": {"coordinates":[1.570452,52.219617],"type":"Point"}
}
