{
  "type": "Feature",
  "properties": {
    "iso:country":"GB",
    "wof:name":"HS5 3UB",
    "wof:placetype":"postalcode"
},
  "geometry": {"coordinates":[-7.01982336910954,57.76583863980958],"type":"Point"}
}