{
  "type": "Feature",
  "properties": {
    "date:inception_lower":"1980-01-01",
    "date:inception_upper":"1980-01-31",
    "iso:country":"GB",
    "wof:name":"FK1 1JJ",
    "wof:placetype":"postalcode"
},
  "geometry": {"coordinates":[-3.784818,56.00044],"type":"Point"}
}