{
  "type": "Feature",
  "properties": {
    "iso:country":"GB",
    "wof:name":"FK1 1JJ",
    "wof:placetype":"postalcode"
},
  "geometry": {"coordinates":[-3.78481762312151,56.00044047980845],"type":"Point"}
}