{
  "type": "Feature",
  "properties": {
    "iso:country":"GB",
    "wof:name":"ME20 7RA",
    "wof:placetype":"postalcode"
},
  "geometry": {"coordinates":[0.47268461677194,51.29598940502739],"type":"Point"}
}