{
  "type": "Feature",
  "properties": {
    "iso:country": "GB",
    "wof:name": "LL12 0DU",
    "wof:placetype": "postalcode"
  },
  "geometry": {"coordinates":[-2.927388,53.107812],"type":"Point"}
}
