{
  "type": "Feature",
  "properties": {
    "iso:country":"GB",
    "wof:name":"LL12 0DU",
    "wof:placetype":"postalcode"
},
  "geometry": {"coordinates":[-2.92738753257868,53.10779575039162],"type":"Point"}
}