{
  "type": "Feature",
  "properties": {
    "date:inception_lower": "1980-01-01",
    "date:inception_upper": "1980-01-01",
    "iso:country": "GB",
    "wof:name": "LL12 0DU",
    "wof:placetype": "postalcode"
  },
  "geometry": {"coordinates":[-2.927284,53.107821],"type":"Point"}
}
