{
  "type": "Feature",
  "properties": {
    "iso:country":"GB",
    "wof:name":"TW13 6JA",
    "wof:placetype":"postalcode"
},
  "geometry": {"coordinates":[-0.37670359769275,51.43590539040205],"type":"Point"}
}