{
  "type": "Feature",
  "properties": {
    "date:inception_lower":"1994-05-01",
    "date:inception_upper":"1994-05-31",
    "iso:country":"GB",
    "wof:name":"M44 6JL",
    "wof:placetype":"postalcode"
},
  "geometry": {"coordinates":[-2.412948,53.452231],"type":"Point"}
}