{
  "type": "Feature",
  "properties": {
    "iso:country":"GB",
    "wof:name":"M44 6JL",
    "wof:placetype":"postalcode"
},
  "geometry": {"coordinates":[-2.41294835422622,53.45223148015566],"type":"Point"}
}