{
  "type": "Feature",
  "properties": {
    "iso:country":"GB",
    "wof:name":"G42 8UQ",
    "wof:placetype":"postalcode"
},
  "geometry": {"coordinates":[-4.25407254147397,55.83149147676554],"type":"Point"}
}