{
  "type": "Feature",
  "properties": {
    "iso:country": "GB",
    "wof:name": "WS5 3JH",
    "wof:placetype": "postalcode"
  },
  "geometry": {"coordinates":[-1.950577,52.567801],"type":"Point"}
}
