{
  "type": "Feature",
  "properties": {
    "date:inception_lower": "1980-01-01",
    "date:inception_upper": "1980-01-01",
    "iso:country": "GB",
    "wof:name": "WS5 3JH",
    "wof:placetype": "postalcode"
  },
  "geometry": {"coordinates":[-1.950577,52.567801],"type":"Point"}
}
