{
  "type": "Feature",
  "properties": {
    "iso:country": "GB",
    "wof:name": "KY4 9NQ",
    "wof:placetype": "postalcode"
  },
  "geometry": {"coordinates":[-3.344661,56.111041],"type":"Point"}
}
