{
  "type": "Feature",
  "properties": {
    "date:inception_lower":"2009-07-01",
    "date:inception_upper":"2009-07-31",
    "iso:country":"GB",
    "wof:name":"SP4 6FT",
    "wof:placetype":"postalcode"
},
  "geometry": {"coordinates":[-1.78985,51.101055],"type":"Point"}
}