{
  "type": "Feature",
  "properties": {
    "iso:country":"GB",
    "wof:name":"SP4 6FT",
    "wof:placetype":"postalcode"
},
  "geometry": {"coordinates":[-1.78984969696541,51.10105539464799],"type":"Point"}
}