{
  "type": "Feature",
  "properties": {
    "iso:country": "GB",
    "wof:name": "SP4 6FT",
    "wof:placetype": "postalcode"
  },
  "geometry": {"coordinates":[-1.78985,51.101055],"type":"Point"}
}
