{
  "type": "Feature",
  "properties": {
    "iso:country":"GB",
    "wof:name":"DN32 9LJ",
    "wof:placetype":"postalcode"
},
  "geometry": {"coordinates":[-0.07667800186565,53.56126576118022],"type":"Point"}
}