{
  "type": "Feature",
  "properties": {
    "iso:country": "GB",
    "wof:name": "M33 3YS",
    "wof:placetype": "postalcode"
  },
  "geometry": {"coordinates":[-2.318299,53.423012],"type":"Point"}
}
