{
  "type": "Feature",
  "properties": {
    "iso:country":"GB",
    "wof:name":"B8 3LT",
    "wof:placetype":"postalcode"
},
  "geometry": {"coordinates":[-1.83564228892114,52.48997115417514],"type":"Point"}
}