{
  "type": "Feature",
  "properties": {
    "date:inception_lower": "2008-11-01",
    "date:inception_upper": "2008-11-01",
    "iso:country": "GB",
    "wof:name": "SL1 7AQ",
    "wof:placetype": "postalcode"
  },
  "geometry": {"coordinates":[-0.664693,51.532304],"type":"Point"}
}
