{
  "type": "Feature",
  "properties": {
    "iso:country":"GB",
    "wof:name":"SL1 7AQ",
    "wof:placetype":"postalcode"
},
  "geometry": {"coordinates":[-0.66484111901957,51.53229378294948],"type":"Point"}
}