{
  "type": "Feature",
  "properties": {
    "iso:country": "GB",
    "wof:name": "SL1 7AQ",
    "wof:placetype": "postalcode"
  },
  "geometry": {"coordinates":[-0.664693,51.532304],"type":"Point"}
}
