{
  "type": "Feature",
  "properties": {
    "date:inception_lower":"1980-01-01",
    "date:inception_upper":"1980-01-31",
    "iso:country":"GB",
    "wof:name":"DN10 4JB",
    "wof:placetype":"postalcode"
},
  "geometry": {"coordinates":[-0.83987,53.422362],"type":"Point"}
}