{
  "type": "Feature",
  "properties": {
    "iso:country":"GB",
    "wof:name":"DN10 4JB",
    "wof:placetype":"postalcode"
},
  "geometry": {"coordinates":[-0.83987032848323,53.42236222215794],"type":"Point"}
}