{
  "type": "Feature",
  "properties": {
    "date:inception_lower": "1999-12-01",
    "date:inception_upper": "1999-12-01",
    "iso:country": "GB",
    "wof:name": "TR18 4BZ",
    "wof:placetype": "postalcode"
  },
  "geometry": {"coordinates":[-5.531827,50.116414],"type":"Point"}
}
