{
  "type": "Feature",
  "properties": {
    "iso:country":"GB",
    "wof:name":"TR18 4BZ",
    "wof:placetype":"postalcode"
},
  "geometry": {"coordinates":[-5.53230843652916,50.11666882995851],"type":"Point"}
}