{
  "type": "Feature",
  "properties": {
    "date:inception_lower": "1980-01-01",
    "date:inception_upper": "1980-01-01",
    "iso:country": "GB",
    "wof:name": "PO40 9TD",
    "wof:placetype": "postalcode"
  },
  "geometry": {"coordinates":[-1.52447,50.691184],"type":"Point"}
}
