{
  "type": "Feature",
  "properties": {
    "iso:country":"GB",
    "wof:name":"CF24 0HG",
    "wof:placetype":"postalcode"
},
  "geometry": {"coordinates":[-3.1566037560057,51.48323653516945],"type":"Point"}
}