{
  "type": "Feature",
  "properties": {
    "iso:country": "GB",
    "wof:name": "ST10 1EW",
    "wof:placetype": "postalcode"
  },
  "geometry": {"coordinates":[-1.986494,52.98425],"type":"Point"}
}
