{
  "type": "Feature",
  "properties": {
    "date:inception_lower":"1980-01-01",
    "date:inception_upper":"1980-01-31",
    "iso:country":"GB",
    "wof:name":"ST10 1EW",
    "wof:placetype":"postalcode"
},
  "geometry": {"coordinates":[-1.986494,52.98425],"type":"Point"}
}