{
  "type": "Feature",
  "properties": {
    "iso:country":"GB",
    "wof:name":"W1U 4QJ",
    "wof:placetype":"postalcode"
},
  "geometry": {"coordinates":[-0.1521342938853,51.52059938122508],"type":"Point"}
}