{
  "type": "Feature",
  "properties": {
    "iso:country": "GB",
    "wof:name": "DN14 0SU",
    "wof:placetype": "postalcode"
  },
  "geometry": {"coordinates":[-1.196392,53.721466],"type":"Point"}
}
