{
  "type": "Feature",
  "properties": {
    "iso:country":"GB",
    "wof:name":"BD1 1QN",
    "wof:placetype":"postalcode"
},
  "geometry": {"coordinates":[-1.75304869869962,53.79500856427742],"type":"Point"}
}