{
  "type": "Feature",
  "properties": {
    "iso:country": "GB",
    "wof:name": "BD1 1QN",
    "wof:placetype": "postalcode"
  },
  "geometry": {"coordinates":[-1.753049,53.795009],"type":"Point"}
}
