{
  "type": "Feature",
  "properties": {
    "iso:country":"GB",
    "wof:name":"BR1 2JX",
    "wof:placetype":"postalcode"
},
  "geometry": {"coordinates":[0.0508360653557,51.39181218349305],"type":"Point"}
}