{
  "type": "Feature",
  "properties": {
    "date:inception_lower": "1980-01-01",
    "date:inception_upper": "1980-01-01",
    "iso:country": "GB",
    "wof:name": "EX18 7NH",
    "wof:placetype": "postalcode"
  },
  "geometry": {"coordinates":[-3.958488,50.893788],"type":"Point"}
}
