{
  "type": "Feature",
  "properties": {
    "iso:country":"GB",
    "wof:name":"EX18 7NH",
    "wof:placetype":"postalcode"
},
  "geometry": {"coordinates":[-3.9584877276915,50.89378805720074],"type":"Point"}
}