{
  "type": "Feature",
  "properties": {
    "iso:country": "GB",
    "wof:name": "EX18 7NH",
    "wof:placetype": "postalcode"
  },
  "geometry": {"coordinates":[-3.958488,50.893788],"type":"Point"}
}
