{
  "type": "Feature",
  "properties": {
    "iso:country":"GB",
    "wof:name":"N12 7DQ",
    "wof:placetype":"postalcode"
},
  "geometry": {"coordinates":[-0.18665093038537,51.62082752712345],"type":"Point"}
}