{
  "type": "Feature",
  "properties": {
    "iso:country":"GB",
    "wof:name":"SA5 7AL",
    "wof:placetype":"postalcode"
},
  "geometry": {"coordinates":[-3.95705788033949,51.64818593822761],"type":"Point"}
}