{
  "type": "Feature",
  "properties": {
    "iso:country":"GB",
    "wof:name":"TQ2 6UX",
    "wof:placetype":"postalcode"
},
  "geometry": {"coordinates":[-3.55678619779147,50.4555380182965],"type":"Point"}
}