{
  "type": "Feature",
  "properties": {
    "date:inception_lower": "1980-01-01",
    "date:inception_upper": "1980-01-01",
    "iso:country": "GB",
    "wof:name": "TQ2 6UX",
    "wof:placetype": "postalcode"
  },
  "geometry": {"coordinates":[-3.556786,50.455538],"type":"Point"}
}
