{
  "type": "Feature",
  "properties": {
    "iso:country": "GB",
    "wof:name": "G53 7PJ",
    "wof:placetype": "postalcode"
  },
  "geometry": {"coordinates":[-4.346921,55.809056],"type":"Point"}
}
