{
  "type": "Feature",
  "properties": {
    "date:inception_lower": "1980-01-01",
    "date:inception_upper": "1980-01-01",
    "iso:country": "GB",
    "wof:name": "SW11 5AS",
    "wof:placetype": "postalcode"
  },
  "geometry": {"coordinates":[-0.159422,51.471121],"type":"Point"}
}
