{
  "type": "Feature",
  "properties": {
    "date:inception_lower": "2022-11-01",
    "date:inception_upper": "2022-11-01",
    "iso:country": "GB",
    "wof:name": "OX20 1GQ",
    "wof:placetype": "postalcode"
  },
  "geometry": {"coordinates":[-1.343694,51.843909],"type":"Point"}
}
