{
  "type": "Feature",
  "properties": {
    "iso:country":"GB",
    "wof:name":"EX19 8AF",
    "wof:placetype":"postalcode"
},
  "geometry": {"coordinates":[-4.04913041549729,50.93305316699139],"type":"Point"}
}