{
  "type": "Feature",
  "properties": {
    "iso:country": "GB",
    "wof:name": "EX19 8AF",
    "wof:placetype": "postalcode"
  },
  "geometry": {"coordinates":[-4.049153,50.933047],"type":"Point"}
}
