{
  "type": "Feature",
  "properties": {
    "date:inception_lower": "1980-01-01",
    "date:inception_upper": "1980-01-01",
    "iso:country": "GB",
    "wof:name": "RH12 3JU",
    "wof:placetype": "postalcode"
  },
  "geometry": {"coordinates":[-0.358813,51.071514],"type":"Point"}
}
