{
  "type": "Feature",
  "properties": {
    "date:inception_lower": "1995-07-01",
    "date:inception_upper": "1995-07-01",
    "iso:country": "GB",
    "wof:name": "RG45 6SB",
    "wof:placetype": "postalcode"
  },
  "geometry": {"coordinates":[-0.794882,51.377673],"type":"Point"}
}
