{
  "type": "Feature",
  "properties": {
    "iso:country":"GB",
    "wof:name":"ST7 4EB",
    "wof:placetype":"postalcode"
},
  "geometry": {"coordinates":[-2.22624600629406,53.09291084527829],"type":"Point"}
}