{
  "type": "Feature",
  "properties": {
    "iso:country":"GB",
    "wof:name":"MK14 7PF",
    "wof:placetype":"postalcode"
},
  "geometry": {"coordinates":[-0.74576651806922,52.05602526166746],"type":"Point"}
}