{
  "type": "Feature",
  "properties": {
    "iso:country": "GB",
    "wof:name": "SY16 4HJ",
    "wof:placetype": "postalcode"
  },
  "geometry": {"coordinates":[-3.172081,52.497409],"type":"Point"}
}
