{
  "type": "Feature",
  "properties": {
    "iso:country":"GB",
    "wof:name":"HP3 9BT",
    "wof:placetype":"postalcode"
},
  "geometry": {"coordinates":[-0.48057433107457,51.74068026016347],"type":"Point"}
}