{
  "type": "Feature",
  "properties": {
    "iso:country": "GB",
    "wof:name": "SO45 6BP",
    "wof:placetype": "postalcode"
  },
  "geometry": {"coordinates":[-1.398929,50.8683],"type":"Point"}
}
