{
  "type": "Feature",
  "properties": {
    "date:inception_lower": "2021-11-01",
    "date:inception_upper": "2021-11-01",
    "iso:country": "GB",
    "wof:name": "TR27 4FZ",
    "wof:placetype": "postalcode"
  },
  "geometry": {"coordinates":[-5.422192,50.187607],"type":"Point"}
}
