{
  "type": "Feature",
  "properties": {
    "iso:country": "GB",
    "wof:name": "TN27 8JF",
    "wof:placetype": "postalcode"
  },
  "geometry": {"coordinates":[0.663734,51.116117],"type":"Point"}
}
