{
  "type": "Feature",
  "properties": {
    "iso:country":"GB",
    "wof:name":"TS17 5FA",
    "wof:placetype":"postalcode"
},
  "geometry": {"coordinates":[-1.3209738931084,54.51919009517783],"type":"Point"}
}