{
  "type": "Feature",
  "properties": {
    "iso:country": "GB",
    "wof:name": "TS17 5FA",
    "wof:placetype": "postalcode"
  },
  "geometry": {"coordinates":[-1.320974,54.51919],"type":"Point"}
}
