{
  "type": "Feature",
  "properties": {
    "date:inception_lower":"2013-11-01",
    "date:inception_upper":"2013-11-30",
    "iso:country":"GB",
    "wof:name":"TS17 5FA",
    "wof:placetype":"postalcode"
},
  "geometry": {"coordinates":[-1.320974,54.51919],"type":"Point"}
}