{
  "type": "Feature",
  "properties": {
    "iso:country": "GB",
    "wof:name": "BN42 4SP",
    "wof:placetype": "postalcode"
  },
  "geometry": {"coordinates":[-0.244096,50.834481],"type":"Point"}
}
