{
  "type": "Feature",
  "properties": {
    "iso:country": "GB",
    "wof:name": "YO24 2SE",
    "wof:placetype": "postalcode"
  },
  "geometry": {"coordinates":[-1.124834,53.940627],"type":"Point"}
}
