{
  "type": "Feature",
  "properties": {
    "iso:country": "GB",
    "wof:name": "DD11 4BY",
    "wof:placetype": "postalcode"
  },
  "geometry": {"coordinates":[-2.593137,56.56842],"type":"Point"}
}
