{
  "type": "Feature",
  "properties": {
    "date:inception_lower": "1981-06-01",
    "date:inception_upper": "1981-06-01",
    "iso:country": "GB",
    "wof:name": "SW1A 1RG",
    "wof:placetype": "postalcode"
  },
  "geometry": {"coordinates":[-0.140917,51.50652],"type":"Point"}
}
