{
  "type": "Feature",
  "properties": {
    "iso:country":"GB",
    "wof:name":"IP3 8ND",
    "wof:placetype":"postalcode"
},
  "geometry": {"coordinates":[1.20055872215277,52.0511827366992],"type":"Point"}
}