{
  "type": "Feature",
  "properties": {
    "iso:country":"GB",
    "wof:name":"SS17 0LJ",
    "wof:placetype":"postalcode"
},
  "geometry": {"coordinates":[0.42118365124564,51.51205292560454],"type":"Point"}
}