{
  "type": "Feature",
  "properties": {
    "iso:country":"GB",
    "wof:name":"NW7 4LS",
    "wof:placetype":"postalcode"
},
  "geometry": {"coordinates":[-0.25007354419339,51.62558475887651],"type":"Point"}
}