{
  "type": "Feature",
  "properties": {
    "iso:country":"GB",
    "wof:name":"LS28 8EU",
    "wof:placetype":"postalcode"
},
  "geometry": {"coordinates":[-1.69892538205323,53.80192262049031],"type":"Point"}
}