{
  "type": "Feature",
  "properties": {
    "iso:country":"GB",
    "wof:name":"OX2 8EW",
    "wof:placetype":"postalcode"
},
  "geometry": {"coordinates":[-1.26915413877084,51.78848188166759],"type":"Point"}
}