{
  "type": "Feature",
  "properties": {
    "iso:country":"GB",
    "wof:name":"TN9 2NQ",
    "wof:placetype":"postalcode"
},
  "geometry": {"coordinates":[0.27030543489824,51.18452453976099],"type":"Point"}
}