{
  "type": "Feature",
  "properties": {
    "date:inception_lower": "1990-02-01",
    "date:inception_upper": "1990-02-01",
    "iso:country": "GB",
    "wof:name": "PL19 8DN",
    "wof:placetype": "postalcode"
  },
  "geometry": {"coordinates":[-4.149313,50.54222],"type":"Point"}
}
