{
  "type": "Feature",
  "properties": {
    "iso:country": "GB",
    "wof:name": "G20 8RW",
    "wof:placetype": "postalcode"
  },
  "geometry": {"coordinates":[-4.288145,55.884908],"type":"Point"}
}
