{
  "type": "Feature",
  "properties": {
    "iso:country":"GB",
    "wof:name":"LD8 2SJ",
    "wof:placetype":"postalcode"
},
  "geometry": {"coordinates":[-3.08075735676742,52.25524963616142],"type":"Point"}
}