{
  "type": "Feature",
  "properties": {
    "date:inception_lower": "2001-12-01",
    "date:inception_upper": "2001-12-01",
    "iso:country": "GB",
    "wof:name": "LD8 2SJ",
    "wof:placetype": "postalcode"
  },
  "geometry": {"coordinates":[-3.080757,52.25525],"type":"Point"}
}
