{
  "type": "Feature",
  "properties": {
    "date:inception_lower": "1980-01-01",
    "date:inception_upper": "1980-01-01",
    "iso:country": "GB",
    "wof:name": "TN39 5JB",
    "wof:placetype": "postalcode"
  },
  "geometry": {"coordinates":[0.464408,50.876957],"type":"Point"}
}
