{
  "type": "Feature",
  "properties": {
    "iso:country":"GB",
    "wof:name":"DY2 9NE",
    "wof:placetype":"postalcode"
},
  "geometry": {"coordinates":[-2.07350338096972,52.48017299340843],"type":"Point"}
}