{
  "type": "Feature",
  "properties": {
    "date:inception_lower": "1980-01-01",
    "date:inception_upper": "1980-01-01",
    "iso:country": "GB",
    "wof:name": "DG2 9BD",
    "wof:placetype": "postalcode"
  },
  "geometry": {"coordinates":[-3.625786,55.069699],"type":"Point"}
}
