{
  "type": "Feature",
  "properties": {
    "iso:country":"GB",
    "wof:name":"NW2 1DB",
    "wof:placetype":"postalcode"
},
  "geometry": {"coordinates":[-0.22068606141093,51.5683566724104],"type":"Point"}
}