{
  "type": "Feature",
  "properties": {
    "iso:country":"GB",
    "wof:name":"BL6 4EW",
    "wof:placetype":"postalcode"
},
  "geometry": {"coordinates":[-2.49989572404864,53.56498336541983],"type":"Point"}
}