{
  "type": "Feature",
  "properties": {
    "iso:country":"GB",
    "wof:name":"B7 5ER",
    "wof:placetype":"postalcode"
},
  "geometry": {"coordinates":[-1.87862883735328,52.49636985824537],"type":"Point"}
}