{
  "type": "Feature",
  "properties": {
    "date:inception_lower": "1980-01-01",
    "date:inception_upper": "1980-01-01",
    "iso:country": "GB",
    "wof:name": "CT14 7BH",
    "wof:placetype": "postalcode"
  },
  "geometry": {"coordinates":[1.40284,51.22066],"type":"Point"}
}
