{
  "type": "Feature",
  "properties": {
    "iso:country": "GB",
    "wof:name": "G67 2LU",
    "wof:placetype": "postalcode"
  },
  "geometry": {"coordinates":[-3.985012,55.944879],"type":"Point"}
}
