{
  "type": "Feature",
  "properties": {
    "iso:country": "GB",
    "wof:name": "BS9 1RF",
    "wof:placetype": "postalcode"
  },
  "geometry": {"coordinates":[-2.640649,51.47704],"type":"Point"}
}
