{
  "type": "Feature",
  "properties": {
    "iso:country": "GB",
    "wof:name": "RM13 9TU",
    "wof:placetype": "postalcode"
  },
  "geometry": {"coordinates":[0.195421,51.515573],"type":"Point"}
}
