{
  "type": "Feature",
  "properties": {
    "date:inception_lower":"1980-01-01",
    "date:inception_upper":"1980-01-31",
    "iso:country":"GB",
    "wof:name":"RM13 9TU",
    "wof:placetype":"postalcode"
},
  "geometry": {"coordinates":[0.195421,51.515573],"type":"Point"}
}