{
  "type": "Feature",
  "properties": {
    "iso:country": "GB",
    "wof:name": "TW15 1AS",
    "wof:placetype": "postalcode"
  },
  "geometry": {"coordinates":[-0.441446,51.433376],"type":"Point"}
}
