{
  "type": "Feature",
  "properties": {
    "iso:country":"GB",
    "wof:name":"LS22 4ET",
    "wof:placetype":"postalcode"
},
  "geometry": {"coordinates":[-1.41285132172188,53.97603932944603],"type":"Point"}
}