{
  "type": "Feature",
  "properties": {
    "iso:country":"GB",
    "wof:name":"RG7 3LX",
    "wof:placetype":"postalcode"
},
  "geometry": {"coordinates":[-1.06536962573073,51.39999596794666],"type":"Point"}
}