{
  "type": "Feature",
  "properties": {
    "iso:country": "GB",
    "wof:name": "RG7 3LX",
    "wof:placetype": "postalcode"
  },
  "geometry": {"coordinates":[-1.06537,51.399996],"type":"Point"}
}
