{
  "type": "Feature",
  "properties": {
    "date:inception_lower": "2018-07-01",
    "date:inception_upper": "2018-07-01",
    "iso:country": "GB",
    "wof:name": "M29 7SG",
    "wof:placetype": "postalcode"
  },
  "geometry": {"coordinates":[-2.449753,53.498145],"type":"Point"}
}
