{
  "type": "Feature",
  "properties": {
    "iso:country":"GB",
    "wof:name":"DN3 1JZ",
    "wof:placetype":"postalcode"
},
  "geometry": {"coordinates":[-1.06723568976103,53.56117184293748],"type":"Point"}
}