{
  "type": "Feature",
  "properties": {
    "iso:country": "GB",
    "wof:name": "SW16 3SJ",
    "wof:placetype": "postalcode"
  },
  "geometry": {"coordinates":[-0.107724,51.418626],"type":"Point"}
}
