{
  "type": "Feature",
  "properties": {
    "date:inception_lower":"1980-01-01",
    "date:inception_upper":"1980-01-31",
    "iso:country":"GB",
    "wof:name":"BL0 9YF",
    "wof:placetype":"postalcode"
},
  "geometry": {"coordinates":[-2.318898,53.653365],"type":"Point"}
}