{
  "type": "Feature",
  "properties": {
    "iso:country":"GB",
    "wof:name":"BL0 9YF",
    "wof:placetype":"postalcode"
},
  "geometry": {"coordinates":[-2.31889834959469,53.65336477085364],"type":"Point"}
}