{
  "type": "Feature",
  "properties": {
    "date:inception_lower": "1980-01-01",
    "date:inception_upper": "1980-01-01",
    "iso:country": "GB",
    "wof:name": "BN26 5QH",
    "wof:placetype": "postalcode"
  },
  "geometry": {"coordinates":[0.217488,50.79051],"type":"Point"}
}
