{
  "type": "Feature",
  "properties": {
    "iso:country":"GB",
    "wof:name":"BN26 5QH",
    "wof:placetype":"postalcode"
},
  "geometry": {"coordinates":[0.21748804114352,50.79050985372701],"type":"Point"}
}