{
  "type": "Feature",
  "properties": {
    "iso:country": "GB",
    "wof:name": "OX28 1GJ",
    "wof:placetype": "postalcode"
  },
  "geometry": {"coordinates":[-1.480834,51.788884],"type":"Point"}
}
