{
  "type": "Feature",
  "properties": {
    "iso:country":"GB",
    "wof:name":"LS21 1TR",
    "wof:placetype":"postalcode"
},
  "geometry": {"coordinates":[-1.62056922907706,53.89894996844613],"type":"Point"}
}