{
  "type": "Feature",
  "properties": {
    "date:inception_lower":"1985-06-01",
    "date:inception_upper":"1985-06-30",
    "iso:country":"GB",
    "wof:name":"TD7 4NQ",
    "wof:placetype":"postalcode"
},
  "geometry": {"coordinates":[-2.837803,55.54854],"type":"Point"}
}