{
  "type": "Feature",
  "properties": {
    "iso:country": "GB",
    "wof:name": "TD7 4NQ",
    "wof:placetype": "postalcode"
  },
  "geometry": {"coordinates":[-2.837803,55.54854],"type":"Point"}
}
