{
  "type": "Feature",
  "properties": {
    "date:inception_lower":"1980-01-01",
    "date:inception_upper":"1980-01-31",
    "iso:country":"GB",
    "wof:name":"DD3 6QN",
    "wof:placetype":"postalcode"
},
  "geometry": {"coordinates":[-2.981051,56.473361],"type":"Point"}
}