{
  "type": "Feature",
  "properties": {
    "iso:country":"GB",
    "wof:name":"NG19 0GJ",
    "wof:placetype":"postalcode"
},
  "geometry": {"coordinates":[-1.17200977258237,53.1580541190311],"type":"Point"}
}