{
  "type": "Feature",
  "properties": {
    "date:inception_lower": "2012-12-01",
    "date:inception_upper": "2012-12-01",
    "iso:country": "GB",
    "wof:name": "NG19 0GJ",
    "wof:placetype": "postalcode"
  },
  "geometry": {"coordinates":[-1.17201,53.158054],"type":"Point"}
}
