{
  "type": "Feature",
  "properties": {
    "iso:country":"GB",
    "wof:name":"MK7 7NB",
    "wof:placetype":"postalcode"
},
  "geometry": {"coordinates":[-0.69384303043627,52.02201401540641],"type":"Point"}
}