{
  "type": "Feature",
  "properties": {
    "iso:country":"GB",
    "wof:name":"GL5 3HQ",
    "wof:placetype":"postalcode"
},
  "geometry": {"coordinates":[-2.24201705941523,51.74118593771703],"type":"Point"}
}