{
  "type": "Feature",
  "properties": {
    "iso:country": "GB",
    "wof:name": "CO10 5PX",
    "wof:placetype": "postalcode"
  },
  "geometry": {"coordinates":[0.844406,52.048048],"type":"Point"}
}
