{
  "type": "Feature",
  "properties": {
    "iso:country":"GB",
    "wof:name":"CO10 5PX",
    "wof:placetype":"postalcode"
},
  "geometry": {"coordinates":[0.84440558118859,52.04804822365483],"type":"Point"}
}