{
  "type": "Feature",
  "properties": {
    "date:inception_lower": "1980-01-01",
    "date:inception_upper": "1980-01-01",
    "iso:country": "GB",
    "wof:name": "ME5 8AA",
    "wof:placetype": "postalcode"
  },
  "geometry": {"coordinates":[0.52725,51.341339],"type":"Point"}
}
