{
  "type": "Feature",
  "properties": {
    "iso:country": "GB",
    "wof:name": "WA6 6NL",
    "wof:placetype": "postalcode"
  },
  "geometry": {"coordinates":[-2.669076,53.243219],"type":"Point"}
}
