{
  "type": "Feature",
  "properties": {
    "date:inception_lower":"1980-01-01",
    "date:inception_upper":"1980-01-31",
    "iso:country":"GB",
    "wof:name":"WA6 6NL",
    "wof:placetype":"postalcode"
},
  "geometry": {"coordinates":[-2.669076,53.243219],"type":"Point"}
}