{
  "type": "Feature",
  "properties": {
    "iso:country":"GB",
    "wof:name":"WA6 6NL",
    "wof:placetype":"postalcode"
},
  "geometry": {"coordinates":[-2.66929967724389,53.24305076351465],"type":"Point"}
}