{
  "type": "Feature",
  "properties": {
    "iso:country":"GB",
    "wof:name":"SE8 4PZ",
    "wof:placetype":"postalcode"
},
  "geometry": {"coordinates":[-0.02748365252311,51.47275172248062],"type":"Point"}
}