{
  "type": "Feature",
  "properties": {
    "iso:country": "GB",
    "wof:name": "TS14 6AQ",
    "wof:placetype": "postalcode"
  },
  "geometry": {"coordinates":[-1.055296,54.533656],"type":"Point"}
}
