{
  "type": "Feature",
  "properties": {
    "iso:country":"GB",
    "wof:name":"TS14 6AQ",
    "wof:placetype":"postalcode"
},
  "geometry": {"coordinates":[-1.05529569464508,54.5336561259737],"type":"Point"}
}