{
  "type": "Feature",
  "properties": {
    "iso:country":"GB",
    "wof:name":"DL6 1DN",
    "wof:placetype":"postalcode"
},
  "geometry": {"coordinates":[-1.4269257270816,54.33190675427825],"type":"Point"}
}