{
  "type": "Feature",
  "properties": {
    "iso:country":"GB",
    "wof:name":"KA23 9AQ",
    "wof:placetype":"postalcode"
},
  "geometry": {"coordinates":[-4.85931700803467,55.69260642604362],"type":"Point"}
}