{
  "type": "Feature",
  "properties": {
    "iso:country":"GB",
    "wof:name":"CM8 1QN",
    "wof:placetype":"postalcode"
},
  "geometry": {"coordinates":[0.64025442334781,51.78921425896382],"type":"Point"}
}