{
  "type": "Feature",
  "properties": {
    "iso:country":"GB",
    "wof:name":"TR26 1QR",
    "wof:placetype":"postalcode"
},
  "geometry": {"coordinates":[-5.48608235250389,50.21054283301076],"type":"Point"}
}