{
  "type": "Feature",
  "properties": {
    "iso:country":"GB",
    "wof:name":"CT9 2HG",
    "wof:placetype":"postalcode"
},
  "geometry": {"coordinates":[1.39775708994332,51.38998060440952],"type":"Point"}
}