{
  "type": "Feature",
  "properties": {
    "date:inception_lower": "1980-01-01",
    "date:inception_upper": "1980-01-01",
    "iso:country": "GB",
    "wof:name": "CT9 2HG",
    "wof:placetype": "postalcode"
  },
  "geometry": {"coordinates":[1.397757,51.389981],"type":"Point"}
}
