{
  "type": "Feature",
  "properties": {
    "iso:country": "GB",
    "wof:name": "CT9 2HG",
    "wof:placetype": "postalcode"
  },
  "geometry": {"coordinates":[1.397757,51.389981],"type":"Point"}
}
