{
  "type": "Feature",
  "properties": {
    "iso:country":"GB",
    "wof:name":"BD18 1QJ",
    "wof:placetype":"postalcode"
},
  "geometry": {"coordinates":[-1.7566277883512,53.82449638711088],"type":"Point"}
}