{
  "type": "Feature",
  "properties": {
    "date:inception_lower": "2006-04-01",
    "date:inception_upper": "2006-04-01",
    "iso:country": "GB",
    "wof:name": "BD18 1QJ",
    "wof:placetype": "postalcode"
  },
  "geometry": {"coordinates":[-1.756628,53.824496],"type":"Point"}
}
