{
  "type": "Feature",
  "properties": {
    "iso:country": "GB",
    "wof:name": "BD18 1QJ",
    "wof:placetype": "postalcode"
  },
  "geometry": {"coordinates":[-1.756628,53.824496],"type":"Point"}
}
