{
  "type": "Feature",
  "properties": {
    "iso:country":"GB",
    "wof:name":"SW8 1HB",
    "wof:placetype":"postalcode"
},
  "geometry": {"coordinates":[-0.12337444870796,51.48104319316303],"type":"Point"}
}