{
  "type": "Feature",
  "properties": {
    "date:inception_lower": "1980-01-01",
    "date:inception_upper": "1980-01-01",
    "iso:country": "GB",
    "wof:name": "HD3 4LL",
    "wof:placetype": "postalcode"
  },
  "geometry": {"coordinates":[-1.826535,53.637429],"type":"Point"}
}
