{
  "type": "Feature",
  "properties": {
    "iso:country":"GB",
    "wof:name":"M6 5DW",
    "wof:placetype":"postalcode"
},
  "geometry": {"coordinates":[-2.29198154025555,53.48678978343104],"type":"Point"}
}