{
  "type": "Feature",
  "properties": {
    "iso:country": "GB",
    "wof:name": "DN21 4UF",
    "wof:placetype": "postalcode"
  },
  "geometry": {"coordinates":[-0.513069,53.441039],"type":"Point"}
}
