{
  "type": "Feature",
  "properties": {
    "iso:country":"GB",
    "wof:name":"DN21 4UF",
    "wof:placetype":"postalcode"
},
  "geometry": {"coordinates":[-0.5130665940659,53.44101666020421],"type":"Point"}
}