{
  "type": "Feature",
  "properties": {
    "iso:country":"GB",
    "wof:name":"ST7 8HB",
    "wof:placetype":"postalcode"
},
  "geometry": {"coordinates":[-2.30770815573534,53.04972413631271],"type":"Point"}
}