{
  "type": "Feature",
  "properties": {
    "date:inception_lower": "1980-01-01",
    "date:inception_upper": "1980-01-01",
    "iso:country": "GB",
    "wof:name": "ST7 8HB",
    "wof:placetype": "postalcode"
  },
  "geometry": {"coordinates":[-2.307738,53.049723],"type":"Point"}
}
