{
  "type": "Feature",
  "properties": {
    "iso:country":"GB",
    "wof:name":"NE47 0BG",
    "wof:placetype":"postalcode"
},
  "geometry": {"coordinates":[-2.01130514655819,54.89844096625581],"type":"Point"}
}