{
  "type": "Feature",
  "properties": {
    "date:inception_lower": "1998-12-01",
    "date:inception_upper": "1998-12-01",
    "iso:country": "GB",
    "wof:name": "NE47 0BG",
    "wof:placetype": "postalcode"
  },
  "geometry": {"coordinates":[-2.011305,54.898441],"type":"Point"}
}
