{
  "type": "Feature",
  "properties": {
    "iso:country":"GB",
    "wof:name":"SE20 7PF",
    "wof:placetype":"postalcode"
},
  "geometry": {"coordinates":[-0.05089448408405,51.41333275168002],"type":"Point"}
}