{
  "type": "Feature",
  "properties": {
    "iso:country":"GB",
    "wof:name":"ST6 7AF",
    "wof:placetype":"postalcode"
},
  "geometry": {"coordinates":[-2.18779957460861,53.05631140417056],"type":"Point"}
}