{
  "type": "Feature",
  "properties": {
    "iso:country":"GB",
    "wof:name":"WA2 7RU",
    "wof:placetype":"postalcode"
},
  "geometry": {"coordinates":[-2.57898402849448,53.40146611590954],"type":"Point"}
}