{
  "type": "Feature",
  "properties": {
    "iso:country": "GB",
    "wof:name": "WF4 1EP",
    "wof:placetype": "postalcode"
  },
  "geometry": {"coordinates":[-1.411535,53.660776],"type":"Point"}
}
