{
  "type": "Feature",
  "properties": {
    "iso:country":"GB",
    "wof:name":"WF4 1EP",
    "wof:placetype":"postalcode"
},
  "geometry": {"coordinates":[-1.41153485180661,53.66077643078348],"type":"Point"}
}