{
  "type": "Feature",
  "properties": {
    "date:inception_lower": "1980-01-01",
    "date:inception_upper": "1980-01-01",
    "iso:country": "GB",
    "wof:name": "BS1 2LY",
    "wof:placetype": "postalcode"
  },
  "geometry": {"coordinates":[-2.595196,51.458613],"type":"Point"}
}
