{
  "type": "Feature",
  "properties": {
    "iso:country":"GB",
    "wof:name":"BS1 2LY",
    "wof:placetype":"postalcode"
},
  "geometry": {"coordinates":[-2.59519557683223,51.45861266726538],"type":"Point"}
}