{
  "type": "Feature",
  "properties": {
    "iso:country":"GB",
    "wof:name":"BS48 1AQ",
    "wof:placetype":"postalcode"
},
  "geometry": {"coordinates":[-2.75707144322257,51.43475896893452],"type":"Point"}
}