{
  "type": "Feature",
  "properties": {
    "iso:country": "GB",
    "wof:name": "BS48 1AQ",
    "wof:placetype": "postalcode"
  },
  "geometry": {"coordinates":[-2.757071,51.434759],"type":"Point"}
}
