{
  "type": "Feature",
  "properties": {
    "iso:country":"GB",
    "wof:name":"ME10 2TZ",
    "wof:placetype":"postalcode"
},
  "geometry": {"coordinates":[0.74555137275647,51.35776595647557],"type":"Point"}
}