{
  "type": "Feature",
  "properties": {
    "date:inception_lower": "2019-06-01",
    "date:inception_upper": "2019-06-01",
    "iso:country": "GB",
    "wof:name": "WR10 2FX",
    "wof:placetype": "postalcode"
  },
  "geometry": {"coordinates":[-2.110162,52.133341],"type":"Point"}
}
