{
  "type": "Feature",
  "properties": {
    "iso:country": "GB",
    "wof:name": "WR10 2FX",
    "wof:placetype": "postalcode"
  },
  "geometry": {"coordinates":[-2.11082,52.13352],"type":"Point"}
}
