{
  "type": "Feature",
  "properties": {
    "date:inception_lower": "1994-05-01",
    "date:inception_upper": "1994-05-01",
    "iso:country": "GB",
    "wof:name": "IV4 7LJ",
    "wof:placetype": "postalcode"
  },
  "geometry": {"coordinates":[-4.75615,57.344344],"type":"Point"}
}
