{
  "type": "Feature",
  "properties": {
    "iso:country":"GB",
    "wof:name":"IV4 7LJ",
    "wof:placetype":"postalcode"
},
  "geometry": {"coordinates":[-4.7560535868177,57.34394195957979],"type":"Point"}
}