{
  "type": "Feature",
  "properties": {
    "iso:country":"GB",
    "wof:name":"SN11 8HB",
    "wof:placetype":"postalcode"
},
  "geometry": {"coordinates":[-1.99921742908861,51.4383200959772],"type":"Point"}
}