{
  "type": "Feature",
  "properties": {
    "iso:country":"GB",
    "wof:name":"B93 8SL",
    "wof:placetype":"postalcode"
},
  "geometry": {"coordinates":[-1.76503586581474,52.37701807644754],"type":"Point"}
}