{
  "type": "Feature",
  "properties": {
    "date:inception_lower": "2022-02-01",
    "date:inception_upper": "2022-02-01",
    "iso:country": "GB",
    "wof:name": "GU14 7HN",
    "wof:placetype": "postalcode"
  },
  "geometry": {"coordinates":[-0.753745,51.295989],"type":"Point"}
}
