{
  "type": "Feature",
  "properties": {
    "iso:country":"GB",
    "wof:name":"LA13 0RD",
    "wof:placetype":"postalcode"
},
  "geometry": {"coordinates":[-3.18396880911485,54.12274628111811],"type":"Point"}
}