{
  "type": "Feature",
  "properties": {
    "iso:country": "GB",
    "wof:name": "LA13 0RD",
    "wof:placetype": "postalcode"
  },
  "geometry": {"coordinates":[-3.183969,54.122746],"type":"Point"}
}
