{
  "type": "Feature",
  "properties": {
    "iso:country": "GB",
    "wof:name": "GL7 5UH",
    "wof:placetype": "postalcode"
  },
  "geometry": {"coordinates":[-1.931187,51.668978],"type":"Point"}
}
