{
  "type": "Feature",
  "properties": {
    "iso:country": "GB",
    "wof:name": "BS37 7DY",
    "wof:placetype": "postalcode"
  },
  "geometry": {"coordinates":[-2.415265,51.558564],"type":"Point"}
}
