{
  "type": "Feature",
  "properties": {
    "iso:country":"GB",
    "wof:name":"PR8 4HW",
    "wof:placetype":"postalcode"
},
  "geometry": {"coordinates":[-3.0065676532123,53.62758880401256],"type":"Point"}
}