{
  "type": "Feature",
  "properties": {
    "iso:country": "GB",
    "wof:name": "PR25 3ND",
    "wof:placetype": "postalcode"
  },
  "geometry": {"coordinates":[-2.692196,53.696505],"type":"Point"}
}
