{
  "type": "Feature",
  "properties": {
    "iso:country":"GB",
    "wof:name":"PR25 3ND",
    "wof:placetype":"postalcode"
},
  "geometry": {"coordinates":[-2.69217969832285,53.69645098984195],"type":"Point"}
}