{
  "type": "Feature",
  "properties": {
    "iso:country":"GB",
    "wof:name":"CM5 9QF",
    "wof:placetype":"postalcode"
},
  "geometry": {"coordinates":[0.21414506977275,51.67647836718349],"type":"Point"}
}