{
  "type": "Feature",
  "properties": {
    "iso:country": "GB",
    "wof:name": "AB39 2AX",
    "wof:placetype": "postalcode"
  },
  "geometry": {"coordinates":[-2.209497,56.964792],"type":"Point"}
}
