{
  "type": "Feature",
  "properties": {
    "date:inception_lower":"1996-06-01",
    "date:inception_upper":"1996-06-30",
    "iso:country":"GB",
    "wof:name":"AB39 2AX",
    "wof:placetype":"postalcode"
},
  "geometry": {"coordinates":[-2.209497,56.964792],"type":"Point"}
}