{
  "type": "Feature",
  "properties": {
    "iso:country":"GB",
    "wof:name":"ST15 0ES",
    "wof:placetype":"postalcode"
},
  "geometry": {"coordinates":[-2.14244172333637,52.89308543981132],"type":"Point"}
}