{
  "type": "Feature",
  "properties": {
    "iso:country": "GB",
    "wof:name": "OX16 3SP",
    "wof:placetype": "postalcode"
  },
  "geometry": {"coordinates":[-1.321473,52.066661],"type":"Point"}
}
