{
  "type": "Feature",
  "properties": {
    "iso:country":"GB",
    "wof:name":"OX16 3SP",
    "wof:placetype":"postalcode"
},
  "geometry": {"coordinates":[-1.32147286238951,52.06666079635084],"type":"Point"}
}