{
  "type": "Feature",
  "properties": {
    "iso:country":"GB",
    "wof:name":"DD3 6ND",
    "wof:placetype":"postalcode"
},
  "geometry": {"coordinates":[-2.97606856654125,56.46772189657516],"type":"Point"}
}