{
  "type": "Feature",
  "properties": {
    "date:inception_lower": "1980-01-01",
    "date:inception_upper": "1980-01-01",
    "iso:country": "GB",
    "wof:name": "AL3 6LN",
    "wof:placetype": "postalcode"
  },
  "geometry": {"coordinates":[-0.323016,51.767885],"type":"Point"}
}
