{
  "type": "Feature",
  "properties": {
    "iso:country":"GB",
    "wof:name":"AL3 6LN",
    "wof:placetype":"postalcode"
},
  "geometry": {"coordinates":[-0.32303994123743,51.76787875646981],"type":"Point"}
}