{
  "type": "Feature",
  "properties": {
    "iso:country": "GB",
    "wof:name": "NG11 8BB",
    "wof:placetype": "postalcode"
  },
  "geometry": {"coordinates":[-1.183411,52.909073],"type":"Point"}
}
