{
  "type": "Feature",
  "properties": {
    "iso:country":"GB",
    "wof:name":"PO12 2NF",
    "wof:placetype":"postalcode"
},
  "geometry": {"coordinates":[-1.15637861546693,50.78688105263266],"type":"Point"}
}