{
  "type": "Feature",
  "properties": {
    "date:inception_lower":"1980-01-01",
    "date:inception_upper":"1980-01-31",
    "iso:country":"GB",
    "wof:name":"PO12 2NF",
    "wof:placetype":"postalcode"
},
  "geometry": {"coordinates":[-1.156379,50.786881],"type":"Point"}
}