{
  "type": "Feature",
  "properties": {
    "date:inception_lower": "1991-01-01",
    "date:inception_upper": "1991-01-01",
    "iso:country": "GB",
    "wof:name": "NG17 8NZ",
    "wof:placetype": "postalcode"
  },
  "geometry": {"coordinates":[-1.260138,53.108699],"type":"Point"}
}
