{
  "type": "Feature",
  "properties": {
    "iso:country":"GB",
    "wof:name":"NG17 8NZ",
    "wof:placetype":"postalcode"
},
  "geometry": {"coordinates":[-1.26013780758013,53.10869912545074],"type":"Point"}
}