{
  "type": "Feature",
  "properties": {
    "date:inception_lower": "2005-05-01",
    "date:inception_upper": "2005-05-01",
    "iso:country": "GB",
    "wof:name": "CW5 5UH",
    "wof:placetype": "postalcode"
  },
  "geometry": {"coordinates":[-2.531171,53.068838],"type":"Point"}
}
