{
  "type": "Feature",
  "properties": {
    "date:inception_lower": "2021-11-01",
    "date:inception_upper": "2021-11-01",
    "iso:country": "GB",
    "wof:name": "NN1 2FP",
    "wof:placetype": "postalcode"
  },
  "geometry": {"coordinates":[-0.898256,52.240124],"type":"Point"}
}
