{
  "type": "Feature",
  "properties": {
    "iso:country":"GB",
    "wof:name":"HU9 1RT",
    "wof:placetype":"postalcode"
},
  "geometry": {"coordinates":[-0.30120509439814,53.74973818649115],"type":"Point"}
}