{
  "type": "Feature",
  "properties": {
    "iso:country": "GB",
    "wof:name": "SL9 7EE",
    "wof:placetype": "postalcode"
  },
  "geometry": {"coordinates":[-0.551329,51.576024],"type":"Point"}
}
