{
  "type": "Feature",
  "properties": {
    "date:inception_lower": "1992-08-01",
    "date:inception_upper": "1992-08-01",
    "iso:country": "GB",
    "wof:name": "DE55 7HG",
    "wof:placetype": "postalcode"
  },
  "geometry": {"coordinates":[-1.371138,53.093705],"type":"Point"}
}
