{
  "type": "Feature",
  "properties": {
    "iso:country":"GB",
    "wof:name":"PE36 6HZ",
    "wof:placetype":"postalcode"
},
  "geometry": {"coordinates":[0.50843309675276,52.95122899599944],"type":"Point"}
}