{
  "type": "Feature",
  "properties": {
    "iso:country": "GB",
    "wof:name": "NR3 4HH",
    "wof:placetype": "postalcode"
  },
  "geometry": {"coordinates":[1.30299,52.652216],"type":"Point"}
}
