{
  "type": "Feature",
  "properties": {
    "date:inception_lower": "1996-06-01",
    "date:inception_upper": "1996-06-01",
    "iso:country": "GB",
    "wof:name": "TQ13 0ND",
    "wof:placetype": "postalcode"
  },
  "geometry": {"coordinates":[-3.599166,50.604222],"type":"Point"}
}
