{
  "type": "Feature",
  "properties": {
    "iso:country":"GB",
    "wof:name":"W14 8JJ",
    "wof:placetype":"postalcode"
},
  "geometry": {"coordinates":[-0.20728621963488,51.49886625794196],"type":"Point"}
}