{
  "type": "Feature",
  "properties": {
    "date:inception_lower":"2016-07-01",
    "date:inception_upper":"2016-07-31",
    "iso:country":"GB",
    "wof:name":"LS25 7BS",
    "wof:placetype":"postalcode"
},
  "geometry": {"coordinates":[-1.348784,53.772615],"type":"Point"}
}