{
  "type": "Feature",
  "properties": {
    "iso:country": "GB",
    "wof:name": "LS25 7BS",
    "wof:placetype": "postalcode"
  },
  "geometry": {"coordinates":[-1.348784,53.772615],"type":"Point"}
}
