{
  "type": "Feature",
  "properties": {
    "iso:country": "GB",
    "wof:name": "L40 2RB",
    "wof:placetype": "postalcode"
  },
  "geometry": {"coordinates":[-2.743733,53.642212],"type":"Point"}
}
