{
  "type": "Feature",
  "properties": {
    "date:inception_lower":"1980-01-01",
    "date:inception_upper":"1980-01-31",
    "iso:country":"GB",
    "wof:name":"BS6 6EQ",
    "wof:placetype":"postalcode"
},
  "geometry": {"coordinates":[-2.602191,51.466265],"type":"Point"}
}