{
  "type": "Feature",
  "properties": {
    "iso:country":"GB",
    "wof:name":"BS6 6EQ",
    "wof:placetype":"postalcode"
},
  "geometry": {"coordinates":[-2.60219071394777,51.4662647811536],"type":"Point"}
}