{
  "type": "Feature",
  "properties": {
    "date:inception_lower": "1980-01-01",
    "date:inception_upper": "1980-01-01",
    "iso:country": "GB",
    "wof:name": "NG16 1HS",
    "wof:placetype": "postalcode"
  },
  "geometry": {"coordinates":[-1.253317,53.006502],"type":"Point"}
}
