{
  "type": "Feature",
  "properties": {
    "iso:country":"GB",
    "wof:name":"WA16 8QF",
    "wof:placetype":"postalcode"
},
  "geometry": {"coordinates":[-2.36945096797273,53.29845238739536],"type":"Point"}
}