{
  "type": "Feature",
  "properties": {
    "date:inception_lower": "2001-06-01",
    "date:inception_upper": "2001-06-01",
    "iso:country": "GB",
    "wof:name": "GU52 0XY",
    "wof:placetype": "postalcode"
  },
  "geometry": {"coordinates":[-0.848944,51.259196],"type":"Point"}
}
