{
  "type": "Feature",
  "properties": {
    "iso:country":"GB",
    "wof:name":"DE72 2BE",
    "wof:placetype":"postalcode"
},
  "geometry": {"coordinates":[-1.39162379015051,52.86051097657314],"type":"Point"}
}