{
  "type": "Feature",
  "properties": {
    "iso:country": "GB",
    "wof:name": "DE72 2BE",
    "wof:placetype": "postalcode"
  },
  "geometry": {"coordinates":[-1.391624,52.860511],"type":"Point"}
}
