{
  "type": "Feature",
  "properties": {
    "date:inception_lower": "1980-01-01",
    "date:inception_upper": "1980-01-01",
    "iso:country": "GB",
    "wof:name": "TR8 4LL",
    "wof:placetype": "postalcode"
  },
  "geometry": {"coordinates":[-4.997656,50.403215],"type":"Point"}
}
