{
  "type": "Feature",
  "properties": {
    "iso:country":"GB",
    "wof:name":"TR8 4LL",
    "wof:placetype":"postalcode"
},
  "geometry": {"coordinates":[-4.99765647230694,50.40321518066681],"type":"Point"}
}