{
  "type": "Feature",
  "properties": {
    "iso:country":"GB",
    "wof:name":"TA22 9DR",
    "wof:placetype":"postalcode"
},
  "geometry": {"coordinates":[-3.54910961679801,51.04080623973215],"type":"Point"}
}