{
  "type": "Feature",
  "properties": {
    "iso:country": "GB",
    "wof:name": "NN2 6EF",
    "wof:placetype": "postalcode"
  },
  "geometry": {"coordinates":[-0.896301,52.25043],"type":"Point"}
}
