{
  "type": "Feature",
  "properties": {
    "date:inception_lower": "1998-06-01",
    "date:inception_upper": "1998-06-01",
    "iso:country": "GB",
    "wof:name": "NN2 6EF",
    "wof:placetype": "postalcode"
  },
  "geometry": {"coordinates":[-0.896301,52.25043],"type":"Point"}
}
