{
  "type": "Feature",
  "properties": {
    "iso:country":"GB",
    "wof:name":"NN2 6EF",
    "wof:placetype":"postalcode"
},
  "geometry": {"coordinates":[-0.89630091973308,52.25043003430955],"type":"Point"}
}