{
  "type": "Feature",
  "properties": {
    "iso:country":"GB",
    "wof:name":"YO24 2NP",
    "wof:placetype":"postalcode"
},
  "geometry": {"coordinates":[-1.11250754026592,53.94142674212857],"type":"Point"}
}