{
  "type": "Feature",
  "properties": {
    "iso:country": "GB",
    "wof:name": "EN1 1GG",
    "wof:placetype": "postalcode"
  },
  "geometry": {"coordinates":[-0.058089,51.649438],"type":"Point"}
}
