{
  "type": "Feature",
  "properties": {
    "iso:country":"GB",
    "wof:name":"DY11 7YL",
    "wof:placetype":"postalcode"
},
  "geometry": {"coordinates":[-2.22276958310111,52.33588369321252],"type":"Point"}
}