{
  "type": "Feature",
  "properties": {
    "iso:country":"GB",
    "wof:name":"SW4 8AB",
    "wof:placetype":"postalcode"
},
  "geometry": {"coordinates":[-0.13145706043121,51.45488696224231],"type":"Point"}
}