{
  "type": "Feature",
  "properties": {
    "iso:country": "GB",
    "wof:name": "DH7 6FG",
    "wof:placetype": "postalcode"
  },
  "geometry": {"coordinates":[-1.640515,54.839589],"type":"Point"}
}
