{
  "type": "Feature",
  "properties": {
    "iso:country":"GB",
    "wof:name":"DH7 6FG",
    "wof:placetype":"postalcode"
},
  "geometry": {"coordinates":[-1.64051515960079,54.8395887645278],"type":"Point"}
}