{
  "type": "Feature",
  "properties": {
    "date:inception_lower":"2011-08-01",
    "date:inception_upper":"2011-08-31",
    "iso:country":"GB",
    "wof:name":"DH7 6FG",
    "wof:placetype":"postalcode"
},
  "geometry": {"coordinates":[-1.640515,54.839589],"type":"Point"}
}