{
  "type": "Feature",
  "properties": {
    "iso:country":"GB",
    "wof:name":"HD5 9LA",
    "wof:placetype":"postalcode"
},
  "geometry": {"coordinates":[-1.76038506669,53.64750183900053],"type":"Point"}
}