{
  "type": "Feature",
  "properties": {
    "date:inception_lower":"1980-01-01",
    "date:inception_upper":"1980-01-31",
    "iso:country":"GB",
    "wof:name":"HD5 9LA",
    "wof:placetype":"postalcode"
},
  "geometry": {"coordinates":[-1.760385,53.647502],"type":"Point"}
}