{
  "type": "Feature",
  "properties": {
    "iso:country":"GB",
    "wof:name":"SY5 8LL",
    "wof:placetype":"postalcode"
},
  "geometry": {"coordinates":[-2.8252177837944,52.68179487001102],"type":"Point"}
}