{
  "type": "Feature",
  "properties": {
    "iso:country": "GB",
    "wof:name": "SY5 8LL",
    "wof:placetype": "postalcode"
  },
  "geometry": {"coordinates":[-2.825218,52.681795],"type":"Point"}
}
