{
  "type": "Feature",
  "properties": {
    "date:inception_lower":"1996-12-01",
    "date:inception_upper":"1996-12-31",
    "iso:country":"GB",
    "wof:name":"SK23 7LY",
    "wof:placetype":"postalcode"
},
  "geometry": {"coordinates":[-1.982136,53.332963],"type":"Point"}
}