{
  "type": "Feature",
  "properties": {
    "iso:country":"GB",
    "wof:name":"SK23 7LY",
    "wof:placetype":"postalcode"
},
  "geometry": {"coordinates":[-1.98218151223398,53.33278553868004],"type":"Point"}
}