{
  "type": "Feature",
  "properties": {
    "iso:country": "GB",
    "wof:name": "BL6 5BR",
    "wof:placetype": "postalcode"
  },
  "geometry": {"coordinates":[-2.571158,53.586102],"type":"Point"}
}
