{
  "type": "Feature",
  "properties": {
    "iso:country":"GB",
    "wof:name":"LE5 6HS",
    "wof:placetype":"postalcode"
},
  "geometry": {"coordinates":[-1.07192688289831,52.62139839336231],"type":"Point"}
}