{
  "type": "Feature",
  "properties": {
    "date:inception_lower": "1980-01-01",
    "date:inception_upper": "1980-01-01",
    "iso:country": "GB",
    "wof:name": "SN14 6JN",
    "wof:placetype": "postalcode"
  },
  "geometry": {"coordinates":[-2.145694,51.498517],"type":"Point"}
}
