{
  "type": "Feature",
  "properties": {
    "iso:country":"GB",
    "wof:name":"EH20 9JX",
    "wof:placetype":"postalcode"
},
  "geometry": {"coordinates":[-3.15828935611405,55.87761172571791],"type":"Point"}
}