{
  "type": "Feature",
  "properties": {
    "iso:country":"GB",
    "wof:name":"SE1 4EE",
    "wof:placetype":"postalcode"
},
  "geometry": {"coordinates":[-0.08757087365145,51.49550932978477],"type":"Point"}
}