{
  "type": "Feature",
  "properties": {
    "iso:country":"GB",
    "wof:name":"L12 0HP",
    "wof:placetype":"postalcode"
},
  "geometry": {"coordinates":[-2.90406564125925,53.44227851132084],"type":"Point"}
}