{
  "type": "Feature",
  "properties": {
    "date:inception_lower": "1994-05-01",
    "date:inception_upper": "1994-05-01",
    "iso:country": "GB",
    "wof:name": "M30 7JX",
    "wof:placetype": "postalcode"
  },
  "geometry": {"coordinates":[-2.365181,53.480018],"type":"Point"}
}
