{
  "type": "Feature",
  "properties": {
    "date:inception_lower": "2018-02-01",
    "date:inception_upper": "2018-02-01",
    "iso:country": "GB",
    "wof:name": "RH13 9FR",
    "wof:placetype": "postalcode"
  },
  "geometry": {"coordinates":[-0.34678,51.013816],"type":"Point"}
}
