{
  "type": "Feature",
  "properties": {
    "date:inception_lower":"1980-01-01",
    "date:inception_upper":"1980-01-31",
    "iso:country":"GB",
    "wof:name":"B64 5DP",
    "wof:placetype":"postalcode"
},
  "geometry": {"coordinates":[-2.080987,52.474235],"type":"Point"}
}