{
  "type": "Feature",
  "properties": {
    "iso:country":"GB",
    "wof:name":"B64 5DP",
    "wof:placetype":"postalcode"
},
  "geometry": {"coordinates":[-2.08098703947773,52.47423471433711],"type":"Point"}
}