{
  "type": "Feature",
  "properties": {
    "iso:country":"GB",
    "wof:name":"NG5 8HA",
    "wof:placetype":"postalcode"
},
  "geometry": {"coordinates":[-1.13276966555454,53.01152768298509],"type":"Point"}
}