{
  "type": "Feature",
  "properties": {
    "iso:country":"GB",
    "wof:name":"OX5 1BH",
    "wof:placetype":"postalcode"
},
  "geometry": {"coordinates":[-1.28527680612916,51.81687613967232],"type":"Point"}
}