{
  "type": "Feature",
  "properties": {
    "iso:country":"GB",
    "wof:name":"B10 0HT",
    "wof:placetype":"postalcode"
},
  "geometry": {"coordinates":[-1.84581538802183,52.4656759472119],"type":"Point"}
}