{
  "type": "Feature",
  "properties": {
    "iso:country": "GB",
    "wof:name": "S70 2RP",
    "wof:placetype": "postalcode"
  },
  "geometry": {"coordinates":[-1.486741,53.553747],"type":"Point"}
}
