{
  "type": "Feature",
  "properties": {
    "iso:country":"GB",
    "wof:name":"S70 2RP",
    "wof:placetype":"postalcode"
},
  "geometry": {"coordinates":[-1.48674135741722,53.55374740764838],"type":"Point"}
}