{
  "type": "Feature",
  "properties": {
    "date:inception_lower":"2010-06-01",
    "date:inception_upper":"2010-06-30",
    "iso:country":"GB",
    "wof:name":"S70 2RP",
    "wof:placetype":"postalcode"
},
  "geometry": {"coordinates":[-1.486741,53.553747],"type":"Point"}
}