{
  "type": "Feature",
  "properties": {
    "iso:country": "GB",
    "wof:name": "LS10 1AZ",
    "wof:placetype": "postalcode"
  },
  "geometry": {"coordinates":[-1.500514,53.765749],"type":"Point"}
}
