{
  "type": "Feature",
  "properties": {
    "iso:country": "GB",
    "wof:name": "PO13 8PA",
    "wof:placetype": "postalcode"
  },
  "geometry": {"coordinates":[-1.16745,50.802634],"type":"Point"}
}
