{
  "type": "Feature",
  "properties": {
    "iso:country": "GB",
    "wof:name": "NE65 0SS",
    "wof:placetype": "postalcode"
  },
  "geometry": {"coordinates":[-1.608754,55.346719],"type":"Point"}
}
