{
  "type": "Feature",
  "properties": {
    "iso:country":"GB",
    "wof:name":"PE2 7BL",
    "wof:placetype":"postalcode"
},
  "geometry": {"coordinates":[-0.2864839347424,52.55405745388214],"type":"Point"}
}