{
  "type": "Feature",
  "properties": {
    "date:inception_lower": "2002-08-01",
    "date:inception_upper": "2002-08-01",
    "iso:country": "GB",
    "wof:name": "PE2 7BL",
    "wof:placetype": "postalcode"
  },
  "geometry": {"coordinates":[-0.286484,52.554057],"type":"Point"}
}
