{
  "type": "Feature",
  "properties": {
    "date:inception_lower": "1981-12-01",
    "date:inception_upper": "1981-12-01",
    "iso:country": "GB",
    "wof:name": "SG8 5SX",
    "wof:placetype": "postalcode"
  },
  "geometry": {"coordinates":[-0.017506,52.060844],"type":"Point"}
}
