{
  "type": "Feature",
  "properties": {
    "iso:country": "GB",
    "wof:name": "BA7 7LY",
    "wof:placetype": "postalcode"
  },
  "geometry": {"coordinates":[-2.483667,51.081026],"type":"Point"}
}
