{
  "type": "Feature",
  "properties": {
    "iso:country":"GB",
    "wof:name":"BA7 7LY",
    "wof:placetype":"postalcode"
},
  "geometry": {"coordinates":[-2.48366671683939,51.08102608351435],"type":"Point"}
}