{
  "type": "Feature",
  "properties": {
    "iso:country": "GB",
    "wof:name": "NW1 9XX",
    "wof:placetype": "postalcode"
  },
  "geometry": {"coordinates":[-0.130078,51.542129],"type":"Point"}
}
