{
  "type": "Feature",
  "properties": {
    "iso:country":"GB",
    "wof:name":"NW1 9XX",
    "wof:placetype":"postalcode"
},
  "geometry": {"coordinates":[-0.13007760599891,51.54212856487608],"type":"Point"}
}