{
  "type": "Feature",
  "properties": {
    "iso:country":"GB",
    "wof:name":"HU17 9JR",
    "wof:placetype":"postalcode"
},
  "geometry": {"coordinates":[-0.42657999144394,53.8512541615365],"type":"Point"}
}