{
  "type": "Feature",
  "properties": {
    "iso:country":"GB",
    "wof:name":"TW14 9EA",
    "wof:placetype":"postalcode"
},
  "geometry": {"coordinates":[-0.41275579175274,51.45672170039265],"type":"Point"}
}