{
  "type": "Feature",
  "properties": {
    "iso:country": "GB",
    "wof:name": "WD23 4AG",
    "wof:placetype": "postalcode"
  },
  "geometry": {"coordinates":[-0.342251,51.639498],"type":"Point"}
}
