{
  "type": "Feature",
  "properties": {
    "iso:country": "GB",
    "wof:name": "CF72 9DD",
    "wof:placetype": "postalcode"
  },
  "geometry": {"coordinates":[-3.410978,51.515872],"type":"Point"}
}
