{
  "type": "Feature",
  "properties": {
    "iso:country": "GB",
    "wof:name": "PR9 7HR",
    "wof:placetype": "postalcode"
  },
  "geometry": {"coordinates":[-2.977106,53.652875],"type":"Point"}
}
