{
  "type": "Feature",
  "properties": {
    "iso:country":"GB",
    "wof:name":"DN16 3JL",
    "wof:placetype":"postalcode"
},
  "geometry": {"coordinates":[-0.64853872206812,53.56373654971363],"type":"Point"}
}