{
  "type": "Feature",
  "properties": {
    "iso:country":"GB",
    "wof:name":"TQ5 8PS",
    "wof:placetype":"postalcode"
},
  "geometry": {"coordinates":[-3.53159663583349,50.39267341131497],"type":"Point"}
}