{
  "type": "Feature",
  "properties": {
    "iso:country":"GB",
    "wof:name":"WN2 5YT",
    "wof:placetype":"postalcode"
},
  "geometry": {"coordinates":[-2.5859562521038,53.50487304750769],"type":"Point"}
}