{
  "type": "Feature",
  "properties": {
    "date:inception_lower": "2004-09-01",
    "date:inception_upper": "2004-09-01",
    "iso:country": "GB",
    "wof:name": "EN5 1RD",
    "wof:placetype": "postalcode"
  },
  "geometry": {"coordinates":[-0.177575,51.649493],"type":"Point"}
}
