{
  "type": "Feature",
  "properties": {
    "date:inception_lower": "2005-09-01",
    "date:inception_upper": "2005-09-01",
    "iso:country": "GB",
    "wof:name": "TQ13 7FJ",
    "wof:placetype": "postalcode"
  },
  "geometry": {"coordinates":[-3.753069,50.515188],"type":"Point"}
}
