{
  "type": "Feature",
  "properties": {
    "date:inception_lower":"2005-09-01",
    "date:inception_upper":"2005-09-30",
    "iso:country":"GB",
    "wof:name":"TQ13 7FJ",
    "wof:placetype":"postalcode"
},
  "geometry": {"coordinates":[-3.753051,50.515199],"type":"Point"}
}