{
  "type": "Feature",
  "properties": {
    "iso:country":"GB",
    "wof:name":"NN7 4AX",
    "wof:placetype":"postalcode"
},
  "geometry": {"coordinates":[-0.98429040902481,52.22625257043934],"type":"Point"}
}