{
  "type": "Feature",
  "properties": {
    "date:inception_lower": "1980-01-01",
    "date:inception_upper": "1980-01-01",
    "iso:country": "GB",
    "wof:name": "NN7 4AX",
    "wof:placetype": "postalcode"
  },
  "geometry": {"coordinates":[-0.984217,52.226285],"type":"Point"}
}
