{
  "type": "Feature",
  "properties": {
    "date:inception_lower": "2018-03-01",
    "date:inception_upper": "2018-03-01",
    "iso:country": "GB",
    "wof:name": "NP20 2QY",
    "wof:placetype": "postalcode"
  },
  "geometry": {"coordinates":[-2.999924,51.573428],"type":"Point"}
}
