{
  "type": "Feature",
  "properties": {
    "iso:country":"GB",
    "wof:name":"NE3 5NP",
    "wof:placetype":"postalcode"
},
  "geometry": {"coordinates":[-1.62574147108497,55.02769968429127],"type":"Point"}
}