{
  "type": "Feature",
  "properties": {
    "iso:country":"GB",
    "wof:name":"E15 1AU",
    "wof:placetype":"postalcode"
},
  "geometry": {"coordinates":[-0.003871183319,51.53896085817259],"type":"Point"}
}