{
  "type": "Feature",
  "properties": {
    "iso:country":"GB",
    "wof:name":"SA70 8AQ",
    "wof:placetype":"postalcode"
},
  "geometry": {"coordinates":[-4.70368188371867,51.68086392081826],"type":"Point"}
}