{
  "type": "Feature",
  "properties": {
    "date:inception_lower":"2002-06-01",
    "date:inception_upper":"2002-06-30",
    "iso:country":"GB",
    "wof:name":"WS10 8UZ",
    "wof:placetype":"postalcode"
},
  "geometry": {"coordinates":[-2.035837,52.568273],"type":"Point"}
}