{
  "type": "Feature",
  "properties": {
    "iso:country": "GB",
    "wof:name": "WS10 8UZ",
    "wof:placetype": "postalcode"
  },
  "geometry": {"coordinates":[-2.035837,52.568273],"type":"Point"}
}
