{
  "type": "Feature",
  "properties": {
    "iso:country":"GB",
    "wof:name":"TF4 2QY",
    "wof:placetype":"postalcode"
},
  "geometry": {"coordinates":[-2.46982663911373,52.66980286786092],"type":"Point"}
}