{
  "type": "Feature",
  "properties": {
    "date:inception_lower": "2021-12-01",
    "date:inception_upper": "2021-12-01",
    "iso:country": "GB",
    "wof:name": "DT3 4GS",
    "wof:placetype": "postalcode"
  },
  "geometry": {"coordinates":[-2.508182,50.626887],"type":"Point"}
}
