{
  "type": "Feature",
  "properties": {
    "date:inception_lower": "2020-04-01",
    "date:inception_upper": "2020-04-01",
    "iso:country": "GB",
    "wof:name": "TR8 4SQ",
    "wof:placetype": "postalcode"
  },
  "geometry": {"coordinates":[-5.042242,50.414975],"type":"Point"}
}
