{
  "type": "Feature",
  "properties": {
    "iso:country": "GB",
    "wof:name": "SS16 4RX",
    "wof:placetype": "postalcode"
  },
  "geometry": {"coordinates":[0.484331,51.556607],"type":"Point"}
}
