{
  "type": "Feature",
  "properties": {
    "date:inception_lower": "1980-01-01",
    "date:inception_upper": "1980-01-01",
    "iso:country": "GB",
    "wof:name": "SS16 4RX",
    "wof:placetype": "postalcode"
  },
  "geometry": {"coordinates":[0.484331,51.556607],"type":"Point"}
}
