{
  "type": "Feature",
  "properties": {
    "iso:country":"GB",
    "wof:name":"SS16 4RX",
    "wof:placetype":"postalcode"
},
  "geometry": {"coordinates":[0.48433067758939,51.55660688779693],"type":"Point"}
}