{
  "type": "Feature",
  "properties": {
    "date:inception_lower":"2003-09-01",
    "date:inception_upper":"2003-09-30",
    "iso:country":"GB",
    "wof:name":"G72 0PB",
    "wof:placetype":"postalcode"
},
  "geometry": {"coordinates":[-4.087078,55.789494],"type":"Point"}
}