{
  "type": "Feature",
  "properties": {
    "iso:country":"GB",
    "wof:name":"OX4 4PY",
    "wof:placetype":"postalcode"
},
  "geometry": {"coordinates":[-1.22620022907294,51.72040402577127],"type":"Point"}
}