{
  "type": "Feature",
  "properties": {
    "iso:country":"GB",
    "wof:name":"LL42 1DX",
    "wof:placetype":"postalcode"
},
  "geometry": {"coordinates":[-4.03052926879847,52.73969311052858],"type":"Point"}
}