{
  "type": "Feature",
  "properties": {
    "iso:country": "GB",
    "wof:name": "RH12 0BD",
    "wof:placetype": "postalcode"
  },
  "geometry": {"coordinates":[-0.235756,51.098498],"type":"Point"}
}
