{
  "type": "Feature",
  "properties": {
    "iso:country": "GB",
    "wof:name": "GU34 2LZ",
    "wof:placetype": "postalcode"
  },
  "geometry": {"coordinates":[-0.965739,51.148216],"type":"Point"}
}
