{
  "type": "Feature",
  "properties": {
    "date:inception_lower": "2008-01-01",
    "date:inception_upper": "2008-01-01",
    "iso:country": "GB",
    "wof:name": "GU34 2LZ",
    "wof:placetype": "postalcode"
  },
  "geometry": {"coordinates":[-0.965739,51.148216],"type":"Point"}
}
