{
  "type": "Feature",
  "properties": {
    "date:inception_lower": "2005-09-01",
    "date:inception_upper": "2005-09-01",
    "iso:country": "GB",
    "wof:name": "ME10 1NP",
    "wof:placetype": "postalcode"
  },
  "geometry": {"coordinates":[0.727447,51.341002],"type":"Point"}
}
