{
  "type": "Feature",
  "properties": {
    "date:inception_lower":"1984-03-01",
    "date:inception_upper":"1984-03-31",
    "iso:country":"GB",
    "wof:name":"KY1 2QY",
    "wof:placetype":"postalcode"
},
  "geometry": {"coordinates":[-3.15611,56.116921],"type":"Point"}
}