{
  "type": "Feature",
  "properties": {
    "date:inception_lower": "1985-10-01",
    "date:inception_upper": "1985-10-01",
    "iso:country": "GB",
    "wof:name": "AL1 2RA",
    "wof:placetype": "postalcode"
  },
  "geometry": {"coordinates":[-0.341137,51.734775],"type":"Point"}
}
