{
  "type": "Feature",
  "properties": {
    "iso:country":"GB",
    "wof:name":"LS29 7JP",
    "wof:placetype":"postalcode"
},
  "geometry": {"coordinates":[-1.75190365177016,53.91447330271978],"type":"Point"}
}