{
  "type": "Feature",
  "properties": {
    "iso:country": "GB",
    "wof:name": "SM5 1AF",
    "wof:placetype": "postalcode"
  },
  "geometry": {"coordinates":[-0.188106,51.383439],"type":"Point"}
}
