{
  "type": "Feature",
  "properties": {
    "iso:country":"GB",
    "wof:name":"SM5 1AF",
    "wof:placetype":"postalcode"
},
  "geometry": {"coordinates":[-0.18813104791598,51.38344022786072],"type":"Point"}
}