{
  "type": "Feature",
  "properties": {
    "iso:country":"GB",
    "wof:name":"RG28 7RB",
    "wof:placetype":"postalcode"
},
  "geometry": {"coordinates":[-1.33822530435471,51.22216886189381],"type":"Point"}
}