{
  "type": "Feature",
  "properties": {
    "iso:country": "GB",
    "wof:name": "LA5 9PH",
    "wof:placetype": "postalcode"
  },
  "geometry": {"coordinates":[-2.768738,54.14464],"type":"Point"}
}
