{
  "type": "Feature",
  "properties": {
    "iso:country":"GB",
    "wof:name":"DN9 2HL",
    "wof:placetype":"postalcode"
},
  "geometry": {"coordinates":[-0.83853557092148,53.49009040973621],"type":"Point"}
}