{
  "type": "Feature",
  "properties": {
    "iso:country":"GB",
    "wof:name":"NR21 7QG",
    "wof:placetype":"postalcode"
},
  "geometry": {"coordinates":[0.73644926854393,52.8541699194518],"type":"Point"}
}