{
  "type": "Feature",
  "properties": {
    "date:inception_lower": "1980-01-01",
    "date:inception_upper": "1980-01-01",
    "iso:country": "GB",
    "wof:name": "NR21 7QG",
    "wof:placetype": "postalcode"
  },
  "geometry": {"coordinates":[0.736449,52.85417],"type":"Point"}
}
