{
  "type": "Feature",
  "properties": {
    "iso:country":"GB",
    "wof:name":"SE10 8GF",
    "wof:placetype":"postalcode"
},
  "geometry": {"coordinates":[-0.01467373140079,51.47162724271602],"type":"Point"}
}