{
  "type": "Feature",
  "properties": {
    "date:inception_lower": "2024-09-01",
    "date:inception_upper": "2024-09-01",
    "iso:country": "GB",
    "wof:name": "LS1 3BZ",
    "wof:placetype": "postalcode"
  },
  "geometry": {"coordinates":[-1.553924,53.80102],"type":"Point"}
}
