{
  "type": "Feature",
  "properties": {
    "iso:country": "GB",
    "wof:name": "WR2 4XJ",
    "wof:placetype": "postalcode"
  },
  "geometry": {"coordinates":[-2.244677,52.175642],"type":"Point"}
}
