{
  "type": "Feature",
  "properties": {
    "iso:country":"GB",
    "wof:name":"WR2 4XJ",
    "wof:placetype":"postalcode"
},
  "geometry": {"coordinates":[-2.24467746618113,52.17564176455944],"type":"Point"}
}