{
  "type": "Feature",
  "properties": {
    "date:inception_lower": "1980-01-01",
    "date:inception_upper": "1980-01-01",
    "iso:country": "GB",
    "wof:name": "WR2 4XJ",
    "wof:placetype": "postalcode"
  },
  "geometry": {"coordinates":[-2.244703,52.175654],"type":"Point"}
}
