{
  "type": "Feature",
  "properties": {
    "iso:country":"GB",
    "wof:name":"NE25 9UF",
    "wof:placetype":"postalcode"
},
  "geometry": {"coordinates":[-1.46934603236004,55.05101303197638],"type":"Point"}
}