{
  "type": "Feature",
  "properties": {
    "iso:country": "GB",
    "wof:name": "NE25 9UF",
    "wof:placetype": "postalcode"
  },
  "geometry": {"coordinates":[-1.469346,55.051013],"type":"Point"}
}
