{
  "type": "Feature",
  "properties": {
    "iso:country":"GB",
    "wof:name":"CT12 6JW",
    "wof:placetype":"postalcode"
},
  "geometry": {"coordinates":[1.39091795313191,51.34533814275899],"type":"Point"}
}