{
  "type": "Feature",
  "properties": {
    "iso:country": "GB",
    "wof:name": "BN11 3GD",
    "wof:placetype": "postalcode"
  },
  "geometry": {"coordinates":[-0.383458,50.809749],"type":"Point"}
}
