{
  "type": "Feature",
  "properties": {
    "date:inception_lower":"2008-06-01",
    "date:inception_upper":"2008-06-30",
    "iso:country":"GB",
    "wof:name":"BN11 3GD",
    "wof:placetype":"postalcode"
},
  "geometry": {"coordinates":[-0.383458,50.809749],"type":"Point"}
}