{
  "type": "Feature",
  "properties": {
    "iso:country":"GB",
    "wof:name":"BN11 3GD",
    "wof:placetype":"postalcode"
},
  "geometry": {"coordinates":[-0.38345820994263,50.80974896148281],"type":"Point"}
}