{
  "type": "Feature",
  "properties": {
    "date:inception_lower": "2006-05-01",
    "date:inception_upper": "2006-05-01",
    "iso:country": "GB",
    "wof:name": "N22 6UL",
    "wof:placetype": "postalcode"
  },
  "geometry": {"coordinates":[-0.113598,51.594411],"type":"Point"}
}
