{
  "type": "Feature",
  "properties": {
    "iso:country":"GB",
    "wof:name":"M44 6YB",
    "wof:placetype":"postalcode"
},
  "geometry": {"coordinates":[-2.41580523001771,53.44717898898416],"type":"Point"}
}