{
  "type": "Feature",
  "properties": {
    "date:inception_lower":"1988-03-01",
    "date:inception_upper":"1988-03-31",
    "iso:country":"GB",
    "wof:name":"TR15 1QJ",
    "wof:placetype":"postalcode"
},
  "geometry": {"coordinates":[-5.217626,50.240643],"type":"Point"}
}