{
  "type": "Feature",
  "properties": {
    "iso:country":"GB",
    "wof:name":"CF81 9LA",
    "wof:placetype":"postalcode"
},
  "geometry": {"coordinates":[-3.29474759348424,51.73760954112485],"type":"Point"}
}