{
  "type": "Feature",
  "properties": {
    "iso:country":"GB",
    "wof:name":"CV2 1GS",
    "wof:placetype":"postalcode"
},
  "geometry": {"coordinates":[-1.46514665920536,52.44223677321051],"type":"Point"}
}