{
  "type": "Feature",
  "properties": {
    "iso:country":"GB",
    "wof:name":"W11 2DY",
    "wof:placetype":"postalcode"
},
  "geometry": {"coordinates":[-0.20420306009856,51.51425911494249],"type":"Point"}
}