{
  "type": "Feature",
  "properties": {
    "iso:country":"GB",
    "wof:name":"PO31 7RZ",
    "wof:placetype":"postalcode"
},
  "geometry": {"coordinates":[-1.29811998778171,50.76172282419282],"type":"Point"}
}