{
  "type": "Feature",
  "properties": {
    "iso:country":"GB",
    "wof:name":"BS8 3QS",
    "wof:placetype":"postalcode"
},
  "geometry": {"coordinates":[-2.65870169356953,51.46180668814212],"type":"Point"}
}