{
  "type": "Feature",
  "properties": {
    "iso:country":"GB",
    "wof:name":"BN13 1NP",
    "wof:placetype":"postalcode"
},
  "geometry": {"coordinates":[-0.40945095388401,50.82008870089765],"type":"Point"}
}