{
  "type": "Feature",
  "properties": {
    "iso:country":"GB",
    "wof:name":"WN2 3AB",
    "wof:placetype":"postalcode"
},
  "geometry": {"coordinates":[-2.57837581841708,53.5350035083878],"type":"Point"}
}