{
  "type": "Feature",
  "properties": {
    "date:inception_lower":"1980-01-01",
    "date:inception_upper":"1980-01-31",
    "iso:country":"GB",
    "wof:name":"WN2 3AB",
    "wof:placetype":"postalcode"
},
  "geometry": {"coordinates":[-2.578481,53.535082],"type":"Point"}
}