{
  "type": "Feature",
  "properties": {
    "iso:country":"GB",
    "wof:name":"DL13 5HH",
    "wof:placetype":"postalcode"
},
  "geometry": {"coordinates":[-1.82697754927962,54.61846026435452],"type":"Point"}
}