{
  "type": "Feature",
  "properties": {
    "date:inception_lower": "2021-11-01",
    "date:inception_upper": "2021-11-01",
    "iso:country": "GB",
    "wof:name": "RG1 1ES",
    "wof:placetype": "postalcode"
  },
  "geometry": {"coordinates":[-0.977092,51.457672],"type":"Point"}
}
