{
  "type": "Feature",
  "properties": {
    "iso:country":"GB",
    "wof:name":"DN9 3GG",
    "wof:placetype":"postalcode"
},
  "geometry": {"coordinates":[-1.01478707720573,53.48639644130603],"type":"Point"}
}