{
  "type": "Feature",
  "properties": {
    "iso:country": "GB",
    "wof:name": "DN9 3GG",
    "wof:placetype": "postalcode"
  },
  "geometry": {"coordinates":[-1.0142,53.487095],"type":"Point"}
}
