{
  "type": "Feature",
  "properties": {
    "iso:country": "GB",
    "wof:name": "RM3 8HF",
    "wof:placetype": "postalcode"
  },
  "geometry": {"coordinates":[0.21521,51.593988],"type":"Point"}
}
