{
  "type": "Feature",
  "properties": {
    "iso:country":"GB",
    "wof:name":"BN25 1RL",
    "wof:placetype":"postalcode"
},
  "geometry": {"coordinates":[0.10471173495352,50.77466612952006],"type":"Point"}
}