{
  "type": "Feature",
  "properties": {
    "date:inception_lower": "1994-05-01",
    "date:inception_upper": "1994-05-01",
    "iso:country": "GB",
    "wof:name": "SY16 2DA",
    "wof:placetype": "postalcode"
  },
  "geometry": {"coordinates":[-3.323847,52.515869],"type":"Point"}
}
