{
  "type": "Feature",
  "properties": {
    "date:inception_lower": "1987-10-01",
    "date:inception_upper": "1987-10-01",
    "iso:country": "GB",
    "wof:name": "S1 4GN",
    "wof:placetype": "postalcode"
  },
  "geometry": {"coordinates":[-1.476123,53.379233],"type":"Point"}
}
