{
  "type": "Feature",
  "properties": {
    "iso:country": "GB",
    "wof:name": "HD5 0DT",
    "wof:placetype": "postalcode"
  },
  "geometry": {"coordinates":[-1.728626,53.655568],"type":"Point"}
}
