{
  "type": "Feature",
  "properties": {
    "date:inception_lower": "1980-01-01",
    "date:inception_upper": "1980-01-01",
    "iso:country": "GB",
    "wof:name": "SG8 9RA",
    "wof:placetype": "postalcode"
  },
  "geometry": {"coordinates":[-0.044478,51.998746],"type":"Point"}
}
