{
  "type": "Feature",
  "properties": {
    "date:inception_lower": "1990-02-01",
    "date:inception_upper": "1990-02-01",
    "iso:country": "GB",
    "wof:name": "S10 4LZ",
    "wof:placetype": "postalcode"
  },
  "geometry": {"coordinates":[-1.563262,53.369436],"type":"Point"}
}
