{
  "type": "Feature",
  "properties": {
    "iso:country":"GB",
    "wof:name":"S10 4LZ",
    "wof:placetype":"postalcode"
},
  "geometry": {"coordinates":[-1.56326236228534,53.36943551934051],"type":"Point"}
}