{
  "type": "Feature",
  "properties": {
    "date:inception_lower":"1980-01-01",
    "date:inception_upper":"1980-01-31",
    "iso:country":"GB",
    "wof:name":"LL13 8EP",
    "wof:placetype":"postalcode"
},
  "geometry": {"coordinates":[-2.98454,53.044276],"type":"Point"}
}