{
  "type": "Feature",
  "properties": {
    "iso:country": "GB",
    "wof:name": "EX22 7LN",
    "wof:placetype": "postalcode"
  },
  "geometry": {"coordinates":[-4.27516,50.894684],"type":"Point"}
}
