{
  "type": "Feature",
  "properties": {
    "iso:country":"GB",
    "wof:name":"EX22 7LN",
    "wof:placetype":"postalcode"
},
  "geometry": {"coordinates":[-4.27513271073368,50.89468980615334],"type":"Point"}
}