{
  "type": "Feature",
  "properties": {
    "iso:country":"GB",
    "wof:name":"BB9 9AP",
    "wof:placetype":"postalcode"
},
  "geometry": {"coordinates":[-2.21416502046054,53.83411423427938],"type":"Point"}
}