{
  "type": "Feature",
  "properties": {
    "iso:country": "GB",
    "wof:name": "WR6 6QA",
    "wof:placetype": "postalcode"
  },
  "geometry": {"coordinates":[-2.357803,52.237378],"type":"Point"}
}
