{
  "type": "Feature",
  "properties": {
    "iso:country":"GB",
    "wof:name":"TN4 8BX",
    "wof:placetype":"postalcode"
},
  "geometry": {"coordinates":[0.25557301833146,51.13101062677541],"type":"Point"}
}