{
  "type": "Feature",
  "properties": {
    "iso:country": "GB",
    "wof:name": "TN4 8BX",
    "wof:placetype": "postalcode"
  },
  "geometry": {"coordinates":[0.255587,51.13101],"type":"Point"}
}
