{
  "type": "Feature",
  "properties": {
    "iso:country":"GB",
    "wof:name":"SG18 9TH",
    "wof:placetype":"postalcode"
},
  "geometry": {"coordinates":[-0.23548577756537,52.05948834427263],"type":"Point"}
}