{
  "type": "Feature",
  "properties": {
    "iso:country": "GB",
    "wof:name": "SG18 9TH",
    "wof:placetype": "postalcode"
  },
  "geometry": {"coordinates":[-0.2355,52.059625],"type":"Point"}
}
