{
  "type": "Feature",
  "properties": {
    "iso:country":"GB",
    "wof:name":"KA7 2PN",
    "wof:placetype":"postalcode"
},
  "geometry": {"coordinates":[-4.62553543564577,55.44897919291244],"type":"Point"}
}