{
  "type": "Feature",
  "properties": {
    "iso:country": "GB",
    "wof:name": "EH52 6UW",
    "wof:placetype": "postalcode"
  },
  "geometry": {"coordinates":[-3.47182,55.959771],"type":"Point"}
}
