{
  "type": "Feature",
  "properties": {
    "iso:country": "GB",
    "wof:name": "BN21 1RP",
    "wof:placetype": "postalcode"
  },
  "geometry": {"coordinates":[0.257402,50.776082],"type":"Point"}
}
