{
  "type": "Feature",
  "properties": {
    "iso:country":"GB",
    "wof:name":"S11 9NS",
    "wof:placetype":"postalcode"
},
  "geometry": {"coordinates":[-1.52412039862492,53.34164569146358],"type":"Point"}
}