{
  "type": "Feature",
  "properties": {
    "date:inception_lower": "2006-03-01",
    "date:inception_upper": "2006-03-01",
    "iso:country": "GB",
    "wof:name": "PR1 0SJ",
    "wof:placetype": "postalcode"
  },
  "geometry": {"coordinates":[-2.730735,53.745091],"type":"Point"}
}
