{
  "type": "Feature",
  "properties": {
    "iso:country":"GB",
    "wof:name":"PR1 0SJ",
    "wof:placetype":"postalcode"
},
  "geometry": {"coordinates":[-2.73073516656111,53.74509125765819],"type":"Point"}
}