{
  "type": "Feature",
  "properties": {
    "iso:country": "GB",
    "wof:name": "RG21 6AX",
    "wof:placetype": "postalcode"
  },
  "geometry": {"coordinates":[-1.096707,51.269022],"type":"Point"}
}
