{
  "type": "Feature",
  "properties": {
    "date:inception_lower": "1980-01-01",
    "date:inception_upper": "1980-01-01",
    "iso:country": "GB",
    "wof:name": "G13 4SA",
    "wof:placetype": "postalcode"
  },
  "geometry": {"coordinates":[-4.367063,55.894179],"type":"Point"}
}
