{
  "type": "Feature",
  "properties": {
    "iso:country":"GB",
    "wof:name":"MK41 8AF",
    "wof:placetype":"postalcode"
},
  "geometry": {"coordinates":[-0.45241825459139,52.15999372184768],"type":"Point"}
}