{
  "type": "Feature",
  "properties": {
    "iso:country":"GB",
    "wof:name":"SG17 5AP",
    "wof:placetype":"postalcode"
},
  "geometry": {"coordinates":[-0.32193730801821,52.03862287765569],"type":"Point"}
}