{
  "type": "Feature",
  "properties": {
    "iso:country":"GB",
    "wof:name":"BN1 3HA",
    "wof:placetype":"postalcode"
},
  "geometry": {"coordinates":[-0.14713277495888,50.8264430765016],"type":"Point"}
}