{
  "type": "Feature",
  "properties": {
    "iso:country": "GB",
    "wof:name": "BN1 3HA",
    "wof:placetype": "postalcode"
  },
  "geometry": {"coordinates":[-0.147133,50.826443],"type":"Point"}
}
