{
  "type": "Feature",
  "properties": {
    "iso:country":"GB",
    "wof:name":"CT19 4LT",
    "wof:placetype":"postalcode"
},
  "geometry": {"coordinates":[1.13841636147375,51.0918740736088],"type":"Point"}
}