{
  "type": "Feature",
  "properties": {
    "iso:country": "GB",
    "wof:name": "IP13 0NE",
    "wof:placetype": "postalcode"
  },
  "geometry": {"coordinates":[1.352042,52.154665],"type":"Point"}
}
