{
  "type": "Feature",
  "properties": {
    "iso:country": "GB",
    "wof:name": "B32 1AE",
    "wof:placetype": "postalcode"
  },
  "geometry": {"coordinates":[-2.012186,52.459887],"type":"Point"}
}
