{
  "type": "Feature",
  "properties": {
    "iso:country":"GB",
    "wof:name":"B32 1AE",
    "wof:placetype":"postalcode"
},
  "geometry": {"coordinates":[-2.01218626307148,52.45988698512801],"type":"Point"}
}