{
  "type": "Feature",
  "properties": {
    "date:inception_lower": "1980-01-01",
    "date:inception_upper": "1980-01-01",
    "iso:country": "GB",
    "wof:name": "NW3 1AR",
    "wof:placetype": "postalcode"
  },
  "geometry": {"coordinates":[-0.176092,51.562855],"type":"Point"}
}
