{
  "type": "Feature",
  "properties": {
    "iso:country":"GB",
    "wof:name":"AB42 5GZ",
    "wof:placetype":"postalcode"
},
  "geometry": {"coordinates":[-2.01716551260296,57.52314447186014],"type":"Point"}
}