{
  "type": "Feature",
  "properties": {
    "iso:country":"GB",
    "wof:name":"BN25 3DD",
    "wof:placetype":"postalcode"
},
  "geometry": {"coordinates":[0.11922774125931,50.78357690297694],"type":"Point"}
}