{
  "type": "Feature",
  "properties": {
    "date:inception_lower":"1980-01-01",
    "date:inception_upper":"1980-01-31",
    "iso:country":"GB",
    "wof:name":"PE30 4NP",
    "wof:placetype":"postalcode"
},
  "geometry": {"coordinates":[0.420657,52.754013],"type":"Point"}
}