{
  "type": "Feature",
  "properties": {
    "iso:country":"GB",
    "wof:name":"FK4 1TT",
    "wof:placetype":"postalcode"
},
  "geometry": {"coordinates":[-3.96699456569539,55.98936441099909],"type":"Point"}
}