{
  "type": "Feature",
  "properties": {
    "date:inception_lower":"1980-01-01",
    "date:inception_upper":"1980-01-31",
    "iso:country":"GB",
    "wof:name":"FK4 1TT",
    "wof:placetype":"postalcode"
},
  "geometry": {"coordinates":[-3.966995,55.989364],"type":"Point"}
}