{
  "type": "Feature",
  "properties": {
    "iso:country":"GB",
    "wof:name":"TR6 0DE",
    "wof:placetype":"postalcode"
},
  "geometry": {"coordinates":[-5.14798937515822,50.3420544766691],"type":"Point"}
}