{
  "type": "Feature",
  "properties": {
    "iso:country": "GB",
    "wof:name": "TR6 0DE",
    "wof:placetype": "postalcode"
  },
  "geometry": {"coordinates":[-5.147989,50.342054],"type":"Point"}
}
