{
  "type": "Feature",
  "properties": {
    "iso:country":"GB",
    "wof:name":"NE63 0LW",
    "wof:placetype":"postalcode"
},
  "geometry": {"coordinates":[-1.56398256028308,55.17462356201439],"type":"Point"}
}