{
  "type": "Feature",
  "properties": {
    "iso:country": "GB",
    "wof:name": "HP22 4FG",
    "wof:placetype": "postalcode"
  },
  "geometry": {"coordinates":[-0.848164,51.88471],"type":"Point"}
}
