{
  "type": "Feature",
  "properties": {
    "iso:country":"GB",
    "wof:name":"HP22 4FG",
    "wof:placetype":"postalcode"
},
  "geometry": {"coordinates":[-0.84816393257745,51.88470959130024],"type":"Point"}
}