{
  "type": "Feature",
  "properties": {
    "iso:country":"GB",
    "wof:name":"BA2 8QE",
    "wof:placetype":"postalcode"
},
  "geometry": {"coordinates":[-2.37517464744763,51.32267926250062],"type":"Point"}
}