{
  "type": "Feature",
  "properties": {
    "iso:country":"GB",
    "wof:name":"EX5 3AW",
    "wof:placetype":"postalcode"
},
  "geometry": {"coordinates":[-3.43481953497093,50.75431990077335],"type":"Point"}
}