{
  "type": "Feature",
  "properties": {
    "iso:country": "GB",
    "wof:name": "HD1 4EA",
    "wof:placetype": "postalcode"
  },
  "geometry": {"coordinates":[-1.800046,53.651466],"type":"Point"}
}
