{
  "type": "Feature",
  "properties": {
    "iso:country":"GB",
    "wof:name":"HD1 4EA",
    "wof:placetype":"postalcode"
},
  "geometry": {"coordinates":[-1.80004630970423,53.65146644268972],"type":"Point"}
}