{
  "type": "Feature",
  "properties": {
    "date:inception_lower": "1997-06-01",
    "date:inception_upper": "1997-06-01",
    "iso:country": "GB",
    "wof:name": "EX4 8LH",
    "wof:placetype": "postalcode"
  },
  "geometry": {"coordinates":[-3.496575,50.737886],"type":"Point"}
}
