{
  "type": "Feature",
  "properties": {
    "iso:country": "GB",
    "wof:name": "EX4 8LH",
    "wof:placetype": "postalcode"
  },
  "geometry": {"coordinates":[-3.496575,50.737886],"type":"Point"}
}
