{
  "type": "Feature",
  "properties": {
    "iso:country": "GB",
    "wof:name": "EH32 0ET",
    "wof:placetype": "postalcode"
  },
  "geometry": {"coordinates":[-2.945602,55.969426],"type":"Point"}
}
