{
  "type": "Feature",
  "properties": {
    "date:inception_lower": "1980-01-01",
    "date:inception_upper": "1980-01-01",
    "iso:country": "GB",
    "wof:name": "EH32 0ET",
    "wof:placetype": "postalcode"
  },
  "geometry": {"coordinates":[-2.945602,55.969426],"type":"Point"}
}
