{
  "type": "Feature",
  "properties": {
    "iso:country":"GB",
    "wof:name":"EH32 0ET",
    "wof:placetype":"postalcode"
},
  "geometry": {"coordinates":[-2.94560252132398,55.96942579357035],"type":"Point"}
}