{
  "type": "Feature",
  "properties": {
    "iso:country": "GB",
    "wof:name": "BS49 5AD",
    "wof:placetype": "postalcode"
  },
  "geometry": {"coordinates":[-2.810099,51.380319],"type":"Point"}
}
