{
  "type": "Feature",
  "properties": {
    "iso:country":"GB",
    "wof:name":"PA3 3FE",
    "wof:placetype":"postalcode"
},
  "geometry": {"coordinates":[-4.47294484535184,55.8413053632646],"type":"Point"}
}