{
  "type": "Feature",
  "properties": {
    "iso:country":"GB",
    "wof:name":"WD23 1JG",
    "wof:placetype":"postalcode"
},
  "geometry": {"coordinates":[-0.3399896192789,51.63124270750266],"type":"Point"}
}