{
  "type": "Feature",
  "properties": {
    "iso:country":"GB",
    "wof:name":"CM6 3AL",
    "wof:placetype":"postalcode"
},
  "geometry": {"coordinates":[0.42399282217188,51.87619432143889],"type":"Point"}
}