{
  "type": "Feature",
  "properties": {
    "iso:country": "GB",
    "wof:name": "CM6 3AL",
    "wof:placetype": "postalcode"
  },
  "geometry": {"coordinates":[0.423993,51.876194],"type":"Point"}
}
