{
  "type": "Feature",
  "properties": {
    "date:inception_lower": "1980-01-01",
    "date:inception_upper": "1980-01-01",
    "iso:country": "GB",
    "wof:name": "CM6 3AL",
    "wof:placetype": "postalcode"
  },
  "geometry": {"coordinates":[0.423993,51.876194],"type":"Point"}
}
