{
  "type": "Feature",
  "properties": {
    "iso:country":"GB",
    "wof:name":"SR5 4NQ",
    "wof:placetype":"postalcode"
},
  "geometry": {"coordinates":[-1.45708587137584,54.93086602339838],"type":"Point"}
}