{
  "type": "Feature",
  "properties": {
    "iso:country": "GB",
    "wof:name": "SR5 4NQ",
    "wof:placetype": "postalcode"
  },
  "geometry": {"coordinates":[-1.457086,54.930866],"type":"Point"}
}
