{
  "type": "Feature",
  "properties": {
    "iso:country": "GB",
    "wof:name": "RG8 9ED",
    "wof:placetype": "postalcode"
  },
  "geometry": {"coordinates":[-1.138241,51.519803],"type":"Point"}
}
