{
  "type": "Feature",
  "properties": {
    "iso:country":"GB",
    "wof:name":"RG8 9ED",
    "wof:placetype":"postalcode"
},
  "geometry": {"coordinates":[-1.1382695097597,51.5198300839705],"type":"Point"}
}