{
  "type": "Feature",
  "properties": {
    "iso:country":"GB",
    "wof:name":"WF3 3QL",
    "wof:placetype":"postalcode"
},
  "geometry": {"coordinates":[-1.49220587347023,53.73011208185643],"type":"Point"}
}