{
  "type": "Feature",
  "properties": {
    "iso:country":"GB",
    "wof:name":"MK2 2PF",
    "wof:placetype":"postalcode"
},
  "geometry": {"coordinates":[-0.72175363974099,51.99947342828799],"type":"Point"}
}