{
  "type": "Feature",
  "properties": {
    "iso:country":"GB",
    "wof:name":"ME3 8AL",
    "wof:placetype":"postalcode"
},
  "geometry": {"coordinates":[0.50666610286483,51.41143663439272],"type":"Point"}
}