{
  "type": "Feature",
  "properties": {
    "iso:country": "GB",
    "wof:name": "ME3 8AL",
    "wof:placetype": "postalcode"
  },
  "geometry": {"coordinates":[0.506666,51.411437],"type":"Point"}
}
