{
  "type": "Feature",
  "properties": {
    "iso:country":"GB",
    "wof:name":"CA7 9PZ",
    "wof:placetype":"postalcode"
},
  "geometry": {"coordinates":[-3.16004751802336,54.82102347537086],"type":"Point"}
}