{
  "type": "Feature",
  "properties": {
    "date:inception_lower": "2021-06-01",
    "date:inception_upper": "2021-06-01",
    "iso:country": "GB",
    "wof:name": "TN27 8FP",
    "wof:placetype": "postalcode"
  },
  "geometry": {"coordinates":[0.695813,51.150152],"type":"Point"}
}
