{
  "type": "Feature",
  "properties": {
    "iso:country": "GB",
    "wof:name": "BN27 1NU",
    "wof:placetype": "postalcode"
  },
  "geometry": {"coordinates":[0.250611,50.878901],"type":"Point"}
}
