{
  "type": "Feature",
  "properties": {
    "iso:country": "GB",
    "wof:name": "NG13 8BW",
    "wof:placetype": "postalcode"
  },
  "geometry": {"coordinates":[-0.9461,52.948965],"type":"Point"}
}
