{
  "type": "Feature",
  "properties": {
    "iso:country":"GB",
    "wof:name":"LE10 2EF",
    "wof:placetype":"postalcode"
},
  "geometry": {"coordinates":[-1.35034184403965,52.52687029288234],"type":"Point"}
}