{
  "type": "Feature",
  "properties": {
    "date:inception_lower":"1980-01-01",
    "date:inception_upper":"1980-01-31",
    "iso:country":"GB",
    "wof:name":"PE8 4PR",
    "wof:placetype":"postalcode"
},
  "geometry": {"coordinates":[-0.476358,52.48952],"type":"Point"}
}