{
  "type": "Feature",
  "properties": {
    "iso:country":"GB",
    "wof:name":"PE8 4PR",
    "wof:placetype":"postalcode"
},
  "geometry": {"coordinates":[-0.47635845756682,52.48951969966267],"type":"Point"}
}