{
  "type": "Feature",
  "properties": {
    "iso:country":"GB",
    "wof:name":"RM3 8YR",
    "wof:placetype":"postalcode"
},
  "geometry": {"coordinates":[0.21176275495893,51.60440115609294],"type":"Point"}
}