{
  "type": "Feature",
  "properties": {
    "iso:country":"GB",
    "wof:name":"BS6 7BW",
    "wof:placetype":"postalcode"
},
  "geometry": {"coordinates":[-2.59562336577484,51.47156742713658],"type":"Point"}
}