{
  "type": "Feature",
  "properties": {
    "iso:country": "GB",
    "wof:name": "BS6 7BW",
    "wof:placetype": "postalcode"
  },
  "geometry": {"coordinates":[-2.595623,51.471567],"type":"Point"}
}
