{
  "type": "Feature",
  "properties": {
    "iso:country": "GB",
    "wof:name": "IP1 3DB",
    "wof:placetype": "postalcode"
  },
  "geometry": {"coordinates":[1.156467,52.058543],"type":"Point"}
}
