{
  "type": "Feature",
  "properties": {
    "iso:country":"GB",
    "wof:name":"CO1 2EF",
    "wof:placetype":"postalcode"
},
  "geometry": {"coordinates":[0.91092138675141,51.88212885144198],"type":"Point"}
}