{
  "type": "Feature",
  "properties": {
    "date:inception_lower":"1992-01-01",
    "date:inception_upper":"1992-01-31",
    "iso:country":"GB",
    "wof:name":"EX31 3QY",
    "wof:placetype":"postalcode"
},
  "geometry": {"coordinates":[-4.088041,51.066987],"type":"Point"}
}