{
  "type": "Feature",
  "properties": {
    "iso:country":"GB",
    "wof:name":"EX31 3QY",
    "wof:placetype":"postalcode"
},
  "geometry": {"coordinates":[-4.08804144138928,51.06698686470121],"type":"Point"}
}