{
  "type": "Feature",
  "properties": {
    "iso:country":"GB",
    "wof:name":"HA5 2BX",
    "wof:placetype":"postalcode"
},
  "geometry": {"coordinates":[-0.40045932828611,51.59342506703345],"type":"Point"}
}