{
  "type": "Feature",
  "properties": {
    "iso:country":"GB",
    "wof:name":"CM0 7DU",
    "wof:placetype":"postalcode"
},
  "geometry": {"coordinates":[0.84097533478844,51.67677045807014],"type":"Point"}
}