{
  "type": "Feature",
  "properties": {
    "iso:country":"GB",
    "wof:name":"M5 3FW",
    "wof:placetype":"postalcode"
},
  "geometry": {"coordinates":[-2.27810172067763,53.46838756210155],"type":"Point"}
}