{
  "type": "Feature",
  "properties": {
    "iso:country": "GB",
    "wof:name": "TQ13 9JT",
    "wof:placetype": "postalcode"
  },
  "geometry": {"coordinates":[-3.701165,50.57817],"type":"Point"}
}
