{
  "type": "Feature",
  "properties": {
    "iso:country":"GB",
    "wof:name":"TQ13 9JT",
    "wof:placetype":"postalcode"
},
  "geometry": {"coordinates":[-3.70116463761304,50.57816962126869],"type":"Point"}
}