{
  "type": "Feature",
  "properties": {
    "iso:country":"GB",
    "wof:name":"PH1 2HF",
    "wof:placetype":"postalcode"
},
  "geometry": {"coordinates":[-3.46236278204796,56.40100133994342],"type":"Point"}
}