{
  "type": "Feature",
  "properties": {
    "date:inception_lower": "1986-08-01",
    "date:inception_upper": "1986-08-01",
    "iso:country": "GB",
    "wof:name": "G1 4DF",
    "wof:placetype": "postalcode"
  },
  "geometry": {"coordinates":[-4.255832,55.85746],"type":"Point"}
}
