{
  "type": "Feature",
  "properties": {
    "date:inception_lower": "1999-06-01",
    "date:inception_upper": "1999-06-01",
    "iso:country": "GB",
    "wof:name": "CH49 4QQ",
    "wof:placetype": "postalcode"
  },
  "geometry": {"coordinates":[-3.117285,53.387376],"type":"Point"}
}
