{
  "type": "Feature",
  "properties": {
    "iso:country":"GB",
    "wof:name":"PL5 3HR",
    "wof:placetype":"postalcode"
},
  "geometry": {"coordinates":[-4.14854126306219,50.40557576188144],"type":"Point"}
}