{
  "type": "Feature",
  "properties": {
    "iso:country":"GB",
    "wof:name":"BN10 7QT",
    "wof:placetype":"postalcode"
},
  "geometry": {"coordinates":[-0.00279644395642,50.79912205222929],"type":"Point"}
}