{
  "type": "Feature",
  "properties": {
    "iso:country": "GB",
    "wof:name": "BN10 7QT",
    "wof:placetype": "postalcode"
  },
  "geometry": {"coordinates":[-0.002796,50.799122],"type":"Point"}
}
