{
  "type": "Feature",
  "properties": {
    "iso:country": "GB",
    "wof:name": "IP4 5BQ",
    "wof:placetype": "postalcode"
  },
  "geometry": {"coordinates":[1.220928,52.05042],"type":"Point"}
}
