{
  "type": "Feature",
  "properties": {
    "iso:country":"GB",
    "wof:name":"IP4 5BQ",
    "wof:placetype":"postalcode"
},
  "geometry": {"coordinates":[1.22092749113332,52.05042041435209],"type":"Point"}
}