{
  "type": "Feature",
  "properties": {
    "iso:country": "GB",
    "wof:name": "M1 1AN",
    "wof:placetype": "postalcode"
  },
  "geometry": {"coordinates":[-2.235154,53.481927],"type":"Point"}
}
