{
  "type": "Feature",
  "properties": {
    "date:inception_lower": "2014-10-01",
    "date:inception_upper": "2014-10-01",
    "iso:country": "GB",
    "wof:name": "M1 1AN",
    "wof:placetype": "postalcode"
  },
  "geometry": {"coordinates":[-2.235154,53.481927],"type":"Point"}
}
