{
  "type": "Feature",
  "properties": {
    "iso:country": "GB",
    "wof:name": "EH52 6QX",
    "wof:placetype": "postalcode"
  },
  "geometry": {"coordinates":[-3.471441,55.943035],"type":"Point"}
}
