{
  "type": "Feature",
  "properties": {
    "date:inception_lower":"1996-12-01",
    "date:inception_upper":"1996-12-31",
    "iso:country":"GB",
    "wof:name":"EH52 6QX",
    "wof:placetype":"postalcode"
},
  "geometry": {"coordinates":[-3.471441,55.943035],"type":"Point"}
}