{
  "type": "Feature",
  "properties": {
    "iso:country": "GB",
    "wof:name": "TQ7 2LT",
    "wof:placetype": "postalcode"
  },
  "geometry": {"coordinates":[-3.690322,50.272302],"type":"Point"}
}
