{
  "type": "Feature",
  "properties": {
    "iso:country":"GB",
    "wof:name":"SW6 6JY",
    "wof:placetype":"postalcode"
},
  "geometry": {"coordinates":[-0.21943421412888,51.47957367233727],"type":"Point"}
}