{
  "type": "Feature",
  "properties": {
    "iso:country": "GB",
    "wof:name": "NP13 1NP",
    "wof:placetype": "postalcode"
  },
  "geometry": {"coordinates":[-3.139699,51.734118],"type":"Point"}
}
