{
  "type": "Feature",
  "properties": {
    "iso:country":"GB",
    "wof:name":"NP13 1NP",
    "wof:placetype":"postalcode"
},
  "geometry": {"coordinates":[-3.13969864644785,51.73411769647245],"type":"Point"}
}