{
  "type": "Feature",
  "properties": {
    "iso:country":"GB",
    "wof:name":"TW9 1UP",
    "wof:placetype":"postalcode"
},
  "geometry": {"coordinates":[-0.2944299014081,51.46351297929792],"type":"Point"}
}