{
  "type": "Feature",
  "properties": {
    "iso:country":"GB",
    "wof:name":"TA20 1JB",
    "wof:placetype":"postalcode"
},
  "geometry": {"coordinates":[-2.96697004517607,50.87431842444727],"type":"Point"}
}