{
  "type": "Feature",
  "properties": {
    "date:inception_lower": "2001-12-01",
    "date:inception_upper": "2001-12-01",
    "iso:country": "GB",
    "wof:name": "TA20 1JB",
    "wof:placetype": "postalcode"
  },
  "geometry": {"coordinates":[-2.967289,50.874325],"type":"Point"}
}
