{
  "type": "Feature",
  "properties": {
    "date:inception_lower": "1999-06-01",
    "date:inception_upper": "1999-06-01",
    "iso:country": "GB",
    "wof:name": "PH2 9QE",
    "wof:placetype": "postalcode"
  },
  "geometry": {"coordinates":[-3.497985,56.328145],"type":"Point"}
}
