{
  "type": "Feature",
  "properties": {
    "iso:country": "GB",
    "wof:name": "S72 0EE",
    "wof:placetype": "postalcode"
  },
  "geometry": {"coordinates":[-1.345129,53.551537],"type":"Point"}
}
