{
  "type": "Feature",
  "properties": {
    "date:inception_lower": "1996-12-01",
    "date:inception_upper": "1996-12-01",
    "iso:country": "GB",
    "wof:name": "WV14 0UG",
    "wof:placetype": "postalcode"
  },
  "geometry": {"coordinates":[-2.093746,52.561769],"type":"Point"}
}
