{
  "type": "Feature",
  "properties": {
    "iso:country":"GB",
    "wof:name":"WA8 7BN",
    "wof:placetype":"postalcode"
},
  "geometry": {"coordinates":[-2.74314381946881,53.36648940712585],"type":"Point"}
}