{
  "type": "Feature",
  "properties": {
    "date:inception_lower": "1996-06-01",
    "date:inception_upper": "1996-06-01",
    "iso:country": "GB",
    "wof:name": "SE1 5US",
    "wof:placetype": "postalcode"
  },
  "geometry": {"coordinates":[-0.065406,51.487252],"type":"Point"}
}
