{
  "type": "Feature",
  "properties": {
    "iso:country":"GB",
    "wof:name":"SE1 5US",
    "wof:placetype":"postalcode"
},
  "geometry": {"coordinates":[-0.06554552370756,51.48728851356428],"type":"Point"}
}