{
  "type": "Feature",
  "properties": {
    "iso:country":"GB",
    "wof:name":"CV6 6DU",
    "wof:placetype":"postalcode"
},
  "geometry": {"coordinates":[-1.47196747294521,52.45746067847681],"type":"Point"}
}