{
  "type": "Feature",
  "properties": {
    "date:inception_lower": "1996-06-01",
    "date:inception_upper": "1996-06-01",
    "iso:country": "GB",
    "wof:name": "CV6 6DU",
    "wof:placetype": "postalcode"
  },
  "geometry": {"coordinates":[-1.471967,52.457461],"type":"Point"}
}
