{
  "type": "Feature",
  "properties": {
    "iso:country":"GB",
    "wof:name":"CB8 9HN",
    "wof:placetype":"postalcode"
},
  "geometry": {"coordinates":[0.50518092100237,52.17709856434408],"type":"Point"}
}