{
  "type": "Feature",
  "properties": {
    "iso:country":"GB",
    "wof:name":"LE13 1DG",
    "wof:placetype":"postalcode"
},
  "geometry": {"coordinates":[-0.87436752895954,52.77144801471273],"type":"Point"}
}