{
  "type": "Feature",
  "properties": {
    "iso:country":"GB",
    "wof:name":"OL5 0RN",
    "wof:placetype":"postalcode"
},
  "geometry": {"coordinates":[-2.038732300201,53.53028498232609],"type":"Point"}
}