{
  "type": "Feature",
  "properties": {
    "iso:country": "GB",
    "wof:name": "LA1 2UQ",
    "wof:placetype": "postalcode"
  },
  "geometry": {"coordinates":[-2.812892,54.057167],"type":"Point"}
}
