{
  "type": "Feature",
  "properties": {
    "date:inception_lower": "1997-12-01",
    "date:inception_upper": "1997-12-01",
    "iso:country": "GB",
    "wof:name": "CO16 8EZ",
    "wof:placetype": "postalcode"
  },
  "geometry": {"coordinates":[1.065589,51.79834],"type":"Point"}
}
