{
  "type": "Feature",
  "properties": {
    "iso:country":"GB",
    "wof:name":"CO16 8EZ",
    "wof:placetype":"postalcode"
},
  "geometry": {"coordinates":[1.06558870133478,51.79834045443138],"type":"Point"}
}