{
  "type": "Feature",
  "properties": {
    "iso:country":"GB",
    "wof:name":"DH1 3PQ",
    "wof:placetype":"postalcode"
},
  "geometry": {"coordinates":[-1.57569349572537,54.77594383075807],"type":"Point"}
}