{
  "type": "Feature",
  "properties": {
    "iso:country": "GB",
    "wof:name": "SW10 9NR",
    "wof:placetype": "postalcode"
  },
  "geometry": {"coordinates":[-0.181492,51.486311],"type":"Point"}
}
