{
  "type": "Feature",
  "properties": {
    "iso:country": "GB",
    "wof:name": "TA10 0AP",
    "wof:placetype": "postalcode"
  },
  "geometry": {"coordinates":[-2.860865,50.990308],"type":"Point"}
}
