{
  "type": "Feature",
  "properties": {
    "date:inception_lower":"1980-01-01",
    "date:inception_upper":"1980-01-31",
    "iso:country":"GB",
    "wof:name":"SA63 4UP",
    "wof:placetype":"postalcode"
},
  "geometry": {"coordinates":[-4.881634,51.85127],"type":"Point"}
}