{
  "type": "Feature",
  "properties": {
    "iso:country": "GB",
    "wof:name": "SA63 4UP",
    "wof:placetype": "postalcode"
  },
  "geometry": {"coordinates":[-4.881634,51.85127],"type":"Point"}
}
