{
  "type": "Feature",
  "properties": {
    "iso:country":"GB",
    "wof:name":"SA63 4UP",
    "wof:placetype":"postalcode"
},
  "geometry": {"coordinates":[-4.88163453537689,51.85126970812988],"type":"Point"}
}