{
  "type": "Feature",
  "properties": {
    "date:inception_lower": "1980-01-01",
    "date:inception_upper": "1980-01-01",
    "iso:country": "GB",
    "wof:name": "CF47 0NN",
    "wof:placetype": "postalcode"
  },
  "geometry": {"coordinates":[-3.369838,51.745228],"type":"Point"}
}
