{
  "type": "Feature",
  "properties": {
    "date:inception_lower": "2018-03-01",
    "date:inception_upper": "2018-03-01",
    "iso:country": "GB",
    "wof:name": "PE26 2UD",
    "wof:placetype": "postalcode"
  },
  "geometry": {"coordinates":[-0.14824,52.486646],"type":"Point"}
}
