{
  "type": "Feature",
  "properties": {
    "date:inception_lower": "1980-01-01",
    "date:inception_upper": "1980-01-01",
    "iso:country": "GB",
    "wof:name": "OX1 1ND",
    "wof:placetype": "postalcode"
  },
  "geometry": {"coordinates":[-1.26188,51.751815],"type":"Point"}
}
