{
  "type": "Feature",
  "properties": {
    "iso:country": "GB",
    "wof:name": "NP11 7DF",
    "wof:placetype": "postalcode"
  },
  "geometry": {"coordinates":[-3.12803,51.623688],"type":"Point"}
}
