{
  "type": "Feature",
  "properties": {
    "iso:country":"GB",
    "wof:name":"SY3 7PD",
    "wof:placetype":"postalcode"
},
  "geometry": {"coordinates":[-2.74585240047466,52.70146034914466],"type":"Point"}
}