{
  "type": "Feature",
  "properties": {
    "iso:country": "GB",
    "wof:name": "SY3 7PD",
    "wof:placetype": "postalcode"
  },
  "geometry": {"coordinates":[-2.745852,52.70146],"type":"Point"}
}
