{
  "type": "Feature",
  "properties": {
    "iso:country":"GB",
    "wof:name":"WF1 1BB",
    "wof:placetype":"postalcode"
},
  "geometry": {"coordinates":[-1.50103585072411,53.68072306045801],"type":"Point"}
}