{
  "type": "Feature",
  "properties": {
    "date:inception_lower": "1996-12-01",
    "date:inception_upper": "1996-12-01",
    "iso:country": "GB",
    "wof:name": "CH4 0FB",
    "wof:placetype": "postalcode"
  },
  "geometry": {"coordinates":[-3.004193,53.161351],"type":"Point"}
}
