{
  "type": "Feature",
  "properties": {
    "iso:country":"GB",
    "wof:name":"CH4 0FB",
    "wof:placetype":"postalcode"
},
  "geometry": {"coordinates":[-3.00419335077111,53.16135122537396],"type":"Point"}
}