{
  "type": "Feature",
  "properties": {
    "iso:country": "GB",
    "wof:name": "CB10 1SJ",
    "wof:placetype": "postalcode"
  },
  "geometry": {"coordinates":[0.173713,52.069474],"type":"Point"}
}
