{
  "type": "Feature",
  "properties": {
    "iso:country": "GB",
    "wof:name": "LA14 4JR",
    "wof:placetype": "postalcode"
  },
  "geometry": {"coordinates":[-3.20632,54.136401],"type":"Point"}
}
