{
  "type": "Feature",
  "properties": {
    "iso:country": "GB",
    "wof:name": "NR9 3DJ",
    "wof:placetype": "postalcode"
  },
  "geometry": {"coordinates":[1.165172,52.590302],"type":"Point"}
}
