{
  "type": "Feature",
  "properties": {
    "iso:country": "GB",
    "wof:name": "TQ1 4DD",
    "wof:placetype": "postalcode"
  },
  "geometry": {"coordinates":[-3.54566,50.475068],"type":"Point"}
}
