{
  "type": "Feature",
  "properties": {
    "iso:country":"GB",
    "wof:name":"TQ1 4DD",
    "wof:placetype":"postalcode"
},
  "geometry": {"coordinates":[-3.54565983738155,50.47506776760461],"type":"Point"}
}