{
  "type": "Feature",
  "properties": {
    "iso:country":"GB",
    "wof:name":"BA14 7EF",
    "wof:placetype":"postalcode"
},
  "geometry": {"coordinates":[-2.2039784748659,51.3208459562746],"type":"Point"}
}