{
  "type": "Feature",
  "properties": {
    "iso:country":"GB",
    "wof:name":"BS15 1PF",
    "wof:placetype":"postalcode"
},
  "geometry": {"coordinates":[-2.51227083042303,51.46843664507336],"type":"Point"}
}