{
  "type": "Feature",
  "properties": {
    "iso:country":"GB",
    "wof:name":"M17 1HR",
    "wof:placetype":"postalcode"
},
  "geometry": {"coordinates":[-2.31280656409162,53.46804101528661],"type":"Point"}
}