{
  "type": "Feature",
  "properties": {
    "date:inception_lower": "1993-01-01",
    "date:inception_upper": "1993-01-01",
    "iso:country": "GB",
    "wof:name": "M17 1HR",
    "wof:placetype": "postalcode"
  },
  "geometry": {"coordinates":[-2.312807,53.468041],"type":"Point"}
}
