{
  "type": "Feature",
  "properties": {
    "iso:country": "GB",
    "wof:name": "M17 1HR",
    "wof:placetype": "postalcode"
  },
  "geometry": {"coordinates":[-2.312807,53.468041],"type":"Point"}
}
