{
  "type": "Feature",
  "properties": {
    "iso:country":"GB",
    "wof:name":"DY5 2XT",
    "wof:placetype":"postalcode"
},
  "geometry": {"coordinates":[-2.11368964520035,52.47033305673134],"type":"Point"}
}