{
  "type": "Feature",
  "properties": {
    "iso:country":"GB",
    "wof:name":"PO4 8AU",
    "wof:placetype":"postalcode"
},
  "geometry": {"coordinates":[-1.06676906736932,50.79234084158112],"type":"Point"}
}