{
  "type": "Feature",
  "properties": {
    "iso:country":"GB",
    "wof:name":"EN8 0RE",
    "wof:placetype":"postalcode"
},
  "geometry": {"coordinates":[-0.03028351325569,51.70955413713822],"type":"Point"}
}