{
  "type": "Feature",
  "properties": {
    "iso:country": "GB",
    "wof:name": "HP12 3AJ",
    "wof:placetype": "postalcode"
  },
  "geometry": {"coordinates":[-0.773462,51.63515],"type":"Point"}
}
