{
  "type": "Feature",
  "properties": {
    "iso:country": "GB",
    "wof:name": "NP11 7PP",
    "wof:placetype": "postalcode"
  },
  "geometry": {"coordinates":[-3.130116,51.617535],"type":"Point"}
}
