{
  "type": "Feature",
  "properties": {
    "date:inception_lower":"1999-06-01",
    "date:inception_upper":"1999-06-30",
    "iso:country":"GB",
    "wof:name":"NP11 7PP",
    "wof:placetype":"postalcode"
},
  "geometry": {"coordinates":[-3.130116,51.617535],"type":"Point"}
}