{
  "type": "Feature",
  "properties": {
    "iso:country": "GB",
    "wof:name": "PR2 1NL",
    "wof:placetype": "postalcode"
  },
  "geometry": {"coordinates":[-2.749911,53.763498],"type":"Point"}
}
