{
  "type": "Feature",
  "properties": {
    "date:inception_lower": "1981-09-01",
    "date:inception_upper": "1981-09-01",
    "iso:country": "GB",
    "wof:name": "SY22 6HE",
    "wof:placetype": "postalcode"
  },
  "geometry": {"coordinates":[-3.088744,52.779815],"type":"Point"}
}
