{
  "type": "Feature",
  "properties": {
    "iso:country": "GB",
    "wof:name": "SY22 6HE",
    "wof:placetype": "postalcode"
  },
  "geometry": {"coordinates":[-3.088744,52.779815],"type":"Point"}
}
