{
  "type": "Feature",
  "properties": {
    "iso:country":"GB",
    "wof:name":"SY22 6HE",
    "wof:placetype":"postalcode"
},
  "geometry": {"coordinates":[-3.08874372930143,52.77981538132366],"type":"Point"}
}