{
  "type": "Feature",
  "properties": {
    "iso:country":"GB",
    "wof:name":"ST5 1LP",
    "wof:placetype":"postalcode"
},
  "geometry": {"coordinates":[-2.2219714481095,53.00806173972969],"type":"Point"}
}