{
  "type": "Feature",
  "properties": {
    "date:inception_lower": "1980-01-01",
    "date:inception_upper": "1980-01-01",
    "iso:country": "GB",
    "wof:name": "KA18 1PL",
    "wof:placetype": "postalcode"
  },
  "geometry": {"coordinates":[-4.259276,55.45481],"type":"Point"}
}
