{
  "type": "Feature",
  "properties": {
    "iso:country": "GB",
    "wof:name": "KA18 1PL",
    "wof:placetype": "postalcode"
  },
  "geometry": {"coordinates":[-4.259276,55.45481],"type":"Point"}
}
