{
  "type": "Feature",
  "properties": {
    "iso:country":"GB",
    "wof:name":"KA18 1PL",
    "wof:placetype":"postalcode"
},
  "geometry": {"coordinates":[-4.25927578595559,55.4548097972641],"type":"Point"}
}