{
  "type": "Feature",
  "properties": {
    "iso:country": "GB",
    "wof:name": "YO26 5BR",
    "wof:placetype": "postalcode"
  },
  "geometry": {"coordinates":[-1.139592,53.957083],"type":"Point"}
}
