{
  "type": "Feature",
  "properties": {
    "iso:country": "GB",
    "wof:name": "SG12 0LL",
    "wof:placetype": "postalcode"
  },
  "geometry": {"coordinates":[-0.067039,51.873615],"type":"Point"}
}
