{
  "type": "Feature",
  "properties": {
    "iso:country":"GB",
    "wof:name":"SG12 0LL",
    "wof:placetype":"postalcode"
},
  "geometry": {"coordinates":[-0.06699885247503,51.87350753121446],"type":"Point"}
}