{
  "type": "Feature",
  "properties": {
    "date:inception_lower": "2022-07-01",
    "date:inception_upper": "2022-07-01",
    "iso:country": "GB",
    "wof:name": "NN8 1GP",
    "wof:placetype": "postalcode"
  },
  "geometry": {"coordinates":[-0.659678,52.308234],"type":"Point"}
}
