{
  "type": "Feature",
  "properties": {
    "iso:country":"GB",
    "wof:name":"CM77 8BJ",
    "wof:placetype":"postalcode"
},
  "geometry": {"coordinates":[0.63508397814082,51.88849816736096],"type":"Point"}
}