{
  "type": "Feature",
  "properties": {
    "date:inception_lower": "2002-06-01",
    "date:inception_upper": "2002-06-01",
    "iso:country": "GB",
    "wof:name": "CM77 8BJ",
    "wof:placetype": "postalcode"
  },
  "geometry": {"coordinates":[0.635989,51.88857],"type":"Point"}
}
