{
  "type": "Feature",
  "properties": {
    "iso:country":"GB",
    "wof:name":"CH46 6BW",
    "wof:placetype":"postalcode"
},
  "geometry": {"coordinates":[-3.12350420234465,53.40201459432533],"type":"Point"}
}