{
  "type": "Feature",
  "properties": {
    "iso:country": "GB",
    "wof:name": "CH46 6BW",
    "wof:placetype": "postalcode"
  },
  "geometry": {"coordinates":[-3.123504,53.402015],"type":"Point"}
}
