{
  "type": "Feature",
  "properties": {
    "iso:country":"GB",
    "wof:name":"GU7 2LE",
    "wof:placetype":"postalcode"
},
  "geometry": {"coordinates":[-0.63044760542752,51.18192809105249],"type":"Point"}
}