{
  "type": "Feature",
  "properties": {
    "iso:country": "GB",
    "wof:name": "HX2 9SE",
    "wof:placetype": "postalcode"
  },
  "geometry": {"coordinates":[-1.885693,53.757602],"type":"Point"}
}
