{
  "type": "Feature",
  "properties": {
    "iso:country":"GB",
    "wof:name":"ST17 0LD",
    "wof:placetype":"postalcode"
},
  "geometry": {"coordinates":[-2.06149402669675,52.78845546484754],"type":"Point"}
}