{
  "type": "Feature",
  "properties": {
    "iso:country":"GB",
    "wof:name":"NR13 5QB",
    "wof:placetype":"postalcode"
},
  "geometry": {"coordinates":[1.43767496985006,52.62025748552944],"type":"Point"}
}