{
  "type": "Feature",
  "properties": {
    "iso:country":"GB",
    "wof:name":"PR4 0XG",
    "wof:placetype":"postalcode"
},
  "geometry": {"coordinates":[-2.81498362909288,53.75616969255313],"type":"Point"}
}