{
  "type": "Feature",
  "properties": {
    "date:inception_lower": "1999-12-01",
    "date:inception_upper": "1999-12-01",
    "iso:country": "GB",
    "wof:name": "PR4 0XG",
    "wof:placetype": "postalcode"
  },
  "geometry": {"coordinates":[-2.81509,53.756347],"type":"Point"}
}
