{
  "type": "Feature",
  "properties": {
    "iso:country":"GB",
    "wof:name":"TS19 8DE",
    "wof:placetype":"postalcode"
},
  "geometry": {"coordinates":[-1.34440694066863,54.58394496095488],"type":"Point"}
}