{
  "type": "Feature",
  "properties": {
    "iso:country":"GB",
    "wof:name":"CM9 5QH",
    "wof:placetype":"postalcode"
},
  "geometry": {"coordinates":[0.67478292254607,51.73307933849159],"type":"Point"}
}