{
  "type": "Feature",
  "properties": {
    "iso:country": "GB",
    "wof:name": "TA24 8SQ",
    "wof:placetype": "postalcode"
  },
  "geometry": {"coordinates":[-3.503512,51.20729],"type":"Point"}
}
