{
  "type": "Feature",
  "properties": {
    "iso:country": "GB",
    "wof:name": "SA67 8QF",
    "wof:placetype": "postalcode"
  },
  "geometry": {"coordinates":[-4.646932,51.758997],"type":"Point"}
}
