{
  "type": "Feature",
  "properties": {
    "iso:country": "GB",
    "wof:name": "NR20 3GL",
    "wof:placetype": "postalcode"
  },
  "geometry": {"coordinates":[0.968685,52.683324],"type":"Point"}
}
