{
  "type": "Feature",
  "properties": {
    "iso:country":"GB",
    "wof:name":"NR20 3GL",
    "wof:placetype":"postalcode"
},
  "geometry": {"coordinates":[0.96838701685639,52.68318162124762],"type":"Point"}
}