{
  "type": "Feature",
  "properties": {
    "date:inception_lower": "1980-01-01",
    "date:inception_upper": "1980-01-01",
    "iso:country": "GB",
    "wof:name": "KY2 5TS",
    "wof:placetype": "postalcode"
  },
  "geometry": {"coordinates":[-3.180839,56.118781],"type":"Point"}
}
