{
  "type": "Feature",
  "properties": {
    "iso:country":"GB",
    "wof:name":"NE38 8LE",
    "wof:placetype":"postalcode"
},
  "geometry": {"coordinates":[-1.48683841793663,54.90200506653225],"type":"Point"}
}