{
  "type": "Feature",
  "properties": {
    "iso:country":"GB",
    "wof:name":"TR12 7AD",
    "wof:placetype":"postalcode"
},
  "geometry": {"coordinates":[-5.21631295098043,50.1028320890919],"type":"Point"}
}