{
  "type": "Feature",
  "properties": {
    "iso:country": "GB",
    "wof:name": "TR12 7AD",
    "wof:placetype": "postalcode"
  },
  "geometry": {"coordinates":[-5.216313,50.102832],"type":"Point"}
}
