{
  "type": "Feature",
  "properties": {
    "date:inception_lower": "2003-08-01",
    "date:inception_upper": "2003-08-01",
    "iso:country": "GB",
    "wof:name": "S43 4QH",
    "wof:placetype": "postalcode"
  },
  "geometry": {"coordinates":[-1.272201,53.276195],"type":"Point"}
}
