{
  "type": "Feature",
  "properties": {
    "iso:country":"GB",
    "wof:name":"S43 4QH",
    "wof:placetype":"postalcode"
},
  "geometry": {"coordinates":[-1.27220126486975,53.2761949918742],"type":"Point"}
}