{
  "type": "Feature",
  "properties": {
    "iso:country":"GB",
    "wof:name":"EX36 4EE",
    "wof:placetype":"postalcode"
},
  "geometry": {"coordinates":[-3.64533267546337,50.99919316998556],"type":"Point"}
}