{
  "type": "Feature",
  "properties": {
    "date:inception_lower": "1980-01-01",
    "date:inception_upper": "1980-01-01",
    "iso:country": "GB",
    "wof:name": "EX36 4EE",
    "wof:placetype": "postalcode"
  },
  "geometry": {"coordinates":[-3.645333,50.999193],"type":"Point"}
}
