{
  "type": "Feature",
  "properties": {
    "iso:country": "GB",
    "wof:name": "BA20 1NR",
    "wof:placetype": "postalcode"
  },
  "geometry": {"coordinates":[-2.627626,50.940808],"type":"Point"}
}
