{
  "type": "Feature",
  "properties": {
    "iso:country":"GB",
    "wof:name":"BA20 1NR",
    "wof:placetype":"postalcode"
},
  "geometry": {"coordinates":[-2.62762627525254,50.94080751716361],"type":"Point"}
}