{
  "type": "Feature",
  "properties": {
    "iso:country":"GB",
    "wof:name":"BB9 7AR",
    "wof:placetype":"postalcode"
},
  "geometry": {"coordinates":[-2.2218700303037,53.83434289069409],"type":"Point"}
}