{
  "type": "Feature",
  "properties": {
    "iso:country": "GB",
    "wof:name": "WA14 1BD",
    "wof:placetype": "postalcode"
  },
  "geometry": {"coordinates":[-2.348462,53.387106],"type":"Point"}
}
