{
  "type": "Feature",
  "properties": {
    "iso:country":"GB",
    "wof:name":"WA14 1BD",
    "wof:placetype":"postalcode"
},
  "geometry": {"coordinates":[-2.34855202573872,53.38701798608304],"type":"Point"}
}