{
  "type": "Feature",
  "properties": {
    "iso:country":"GB",
    "wof:name":"HU5 4NU",
    "wof:placetype":"postalcode"
},
  "geometry": {"coordinates":[-0.38840604366671,53.76572046454037],"type":"Point"}
}