{
  "type": "Feature",
  "properties": {
    "iso:country": "GB",
    "wof:name": "HU5 4NU",
    "wof:placetype": "postalcode"
  },
  "geometry": {"coordinates":[-0.388406,53.76572],"type":"Point"}
}
