{
  "type": "Feature",
  "properties": {
    "iso:country":"GB",
    "wof:name":"WA15 6TF",
    "wof:placetype":"postalcode"
},
  "geometry": {"coordinates":[-2.33711959948584,53.40341909525762],"type":"Point"}
}