{
  "type": "Feature",
  "properties": {
    "iso:country": "GB",
    "wof:name": "LS21 1EQ",
    "wof:placetype": "postalcode"
  },
  "geometry": {"coordinates":[-1.631895,53.903785],"type":"Point"}
}
