{
  "type": "Feature",
  "properties": {
    "iso:country":"GB",
    "wof:name":"DY5 2LF",
    "wof:placetype":"postalcode"
},
  "geometry": {"coordinates":[-2.1170002850969,52.46420764371297],"type":"Point"}
}