{
  "type": "Feature",
  "properties": {
    "iso:country":"GB",
    "wof:name":"TQ14 9TE",
    "wof:placetype":"postalcode"
},
  "geometry": {"coordinates":[-3.55289292935447,50.56884674618171],"type":"Point"}
}