{
  "type": "Feature",
  "properties": {
    "iso:country": "GB",
    "wof:name": "KY8 2DT",
    "wof:placetype": "postalcode"
  },
  "geometry": {"coordinates":[-3.043777,56.187241],"type":"Point"}
}
