{
  "type": "Feature",
  "properties": {
    "iso:country":"GB",
    "wof:name":"PR7 6FG",
    "wof:placetype":"postalcode"
},
  "geometry": {"coordinates":[-2.66885772228168,53.67366334195312],"type":"Point"}
}