{
  "type": "Feature",
  "properties": {
    "iso:country":"GB",
    "wof:name":"TS12 2WH",
    "wof:placetype":"postalcode"
},
  "geometry": {"coordinates":[-0.9782168587886,54.56802623944946],"type":"Point"}
}