{
  "type": "Feature",
  "properties": {
    "date:inception_lower": "2005-05-01",
    "date:inception_upper": "2005-05-01",
    "iso:country": "GB",
    "wof:name": "TS12 2WH",
    "wof:placetype": "postalcode"
  },
  "geometry": {"coordinates":[-0.978217,54.568026],"type":"Point"}
}
