{
  "type": "Feature",
  "properties": {
    "iso:country":"GB",
    "wof:name":"G20 0QS",
    "wof:placetype":"postalcode"
},
  "geometry": {"coordinates":[-4.28300976100811,55.89552392655541],"type":"Point"}
}