{
  "type": "Feature",
  "properties": {
    "iso:country":"GB",
    "wof:name":"CR8 1DW",
    "wof:placetype":"postalcode"
},
  "geometry": {"coordinates":[-0.10626700998268,51.34109373479702],"type":"Point"}
}