{
  "type": "Feature",
  "properties": {
    "date:inception_lower": "2022-11-01",
    "date:inception_upper": "2022-11-01",
    "iso:country": "GB",
    "wof:name": "NR13 4FU",
    "wof:placetype": "postalcode"
  },
  "geometry": {"coordinates":[1.438779,52.645741],"type":"Point"}
}
