{
  "type": "Feature",
  "properties": {
    "iso:country": "GB",
    "wof:name": "LE12 6NJ",
    "wof:placetype": "postalcode"
  },
  "geometry": {"coordinates":[-1.176109,52.829861],"type":"Point"}
}
