{
  "type": "Feature",
  "properties": {
    "iso:country":"GB",
    "wof:name":"LE12 6NJ",
    "wof:placetype":"postalcode"
},
  "geometry": {"coordinates":[-1.17610950024465,52.8298605253633],"type":"Point"}
}