{
  "type": "Feature",
  "properties": {
    "iso:country":"GB",
    "wof:name":"PE12 8SP",
    "wof:placetype":"postalcode"
},
  "geometry": {"coordinates":[0.01897055452917,52.76244902062156],"type":"Point"}
}