{
  "type": "Feature",
  "properties": {
    "iso:country":"GB",
    "wof:name":"S40 1DB",
    "wof:placetype":"postalcode"
},
  "geometry": {"coordinates":[-1.44473035738806,53.23612439559882],"type":"Point"}
}