{
  "type": "Feature",
  "properties": {
    "date:inception_lower":"1980-01-01",
    "date:inception_upper":"1980-01-31",
    "iso:country":"GB",
    "wof:name":"LS4 2JZ",
    "wof:placetype":"postalcode"
},
  "geometry": {"coordinates":[-1.585431,53.808047],"type":"Point"}
}