{
  "type": "Feature",
  "properties": {
    "date:inception_lower":"1997-06-01",
    "date:inception_upper":"1997-06-30",
    "iso:country":"GB",
    "wof:name":"S36 1EY",
    "wof:placetype":"postalcode"
},
  "geometry": {"coordinates":[-1.604085,53.482501],"type":"Point"}
}