{
  "type": "Feature",
  "properties": {
    "iso:country":"GB",
    "wof:name":"S36 1EY",
    "wof:placetype":"postalcode"
},
  "geometry": {"coordinates":[-1.60408501785525,53.4825013235474],"type":"Point"}
}