{
  "type": "Feature",
  "properties": {
    "iso:country":"GB",
    "wof:name":"W13 0NW",
    "wof:placetype":"postalcode"
},
  "geometry": {"coordinates":[-0.31997530752246,51.51309690114584],"type":"Point"}
}