{
  "type": "Feature",
  "properties": {
    "date:inception_lower": "2007-04-01",
    "date:inception_upper": "2007-04-01",
    "iso:country": "GB",
    "wof:name": "W13 0NW",
    "wof:placetype": "postalcode"
  },
  "geometry": {"coordinates":[-0.319975,51.513097],"type":"Point"}
}
