{
  "type": "Feature",
  "properties": {
    "date:inception_lower": "1980-01-01",
    "date:inception_upper": "1980-01-01",
    "iso:country": "GB",
    "wof:name": "SN10 3RF",
    "wof:placetype": "postalcode"
  },
  "geometry": {"coordinates":[-1.897966,51.329599],"type":"Point"}
}
