{
  "type": "Feature",
  "properties": {
    "iso:country":"GB",
    "wof:name":"SN10 3RF",
    "wof:placetype":"postalcode"
},
  "geometry": {"coordinates":[-1.89796026769205,51.32964784721018],"type":"Point"}
}