{
  "type": "Feature",
  "properties": {
    "iso:country":"GB",
    "wof:name":"DY10 2SZ",
    "wof:placetype":"postalcode"
},
  "geometry": {"coordinates":[-2.22896064380107,52.39502704094786],"type":"Point"}
}