{
  "type": "Feature",
  "properties": {
    "iso:country": "GB",
    "wof:name": "LA12 7SW",
    "wof:placetype": "postalcode"
  },
  "geometry": {"coordinates":[-3.072436,54.234514],"type":"Point"}
}
