{
  "type": "Feature",
  "properties": {
    "date:inception_lower": "1980-01-01",
    "date:inception_upper": "1980-01-01",
    "iso:country": "GB",
    "wof:name": "LA12 7SW",
    "wof:placetype": "postalcode"
  },
  "geometry": {"coordinates":[-3.073758,54.235203],"type":"Point"}
}
