{
  "type": "Feature",
  "properties": {
    "iso:country": "GB",
    "wof:name": "ST4 2DT",
    "wof:placetype": "postalcode"
  },
  "geometry": {"coordinates":[-2.181783,53.012921],"type":"Point"}
}
