{
  "type": "Feature",
  "properties": {
    "date:inception_lower": "1980-01-01",
    "date:inception_upper": "1980-01-01",
    "iso:country": "GB",
    "wof:name": "ST4 2DT",
    "wof:placetype": "postalcode"
  },
  "geometry": {"coordinates":[-2.181783,53.012921],"type":"Point"}
}
