{
  "type": "Feature",
  "properties": {
    "iso:country":"GB",
    "wof:name":"ML6 0DL",
    "wof:placetype":"postalcode"
},
  "geometry": {"coordinates":[-3.9888073371345,55.86550879121918],"type":"Point"}
}