{
  "type": "Feature",
  "properties": {
    "iso:country": "GB",
    "wof:name": "ML6 0DL",
    "wof:placetype": "postalcode"
  },
  "geometry": {"coordinates":[-3.988807,55.865509],"type":"Point"}
}
