{
  "type": "Feature",
  "properties": {
    "iso:country":"GB",
    "wof:name":"CF83 3BD",
    "wof:placetype":"postalcode"
},
  "geometry": {"coordinates":[-3.21325275782209,51.58598951759854],"type":"Point"}
}