{
  "type": "Feature",
  "properties": {
    "iso:country":"GB",
    "wof:name":"AB43 9FA",
    "wof:placetype":"postalcode"
},
  "geometry": {"coordinates":[-2.02985502051426,57.68575859697515],"type":"Point"}
}