{
  "type": "Feature",
  "properties": {
    "iso:country":"GB",
    "wof:name":"SE12 9PP",
    "wof:placetype":"postalcode"
},
  "geometry": {"coordinates":[0.03050944314485,51.4326700056315],"type":"Point"}
}