{
  "type": "Feature",
  "properties": {
    "date:inception_lower":"2002-12-01",
    "date:inception_upper":"2002-12-31",
    "iso:country":"GB",
    "wof:name":"G74 3HA",
    "wof:placetype":"postalcode"
},
  "geometry": {"coordinates":[-4.150065,55.770326],"type":"Point"}
}