{
  "type": "Feature",
  "properties": {
    "iso:country": "GB",
    "wof:name": "LE2 7SX",
    "wof:placetype": "postalcode"
  },
  "geometry": {"coordinates":[-1.136032,52.61639],"type":"Point"}
}
