{
  "type": "Feature",
  "properties": {
    "iso:country":"GB",
    "wof:name":"LE2 7SX",
    "wof:placetype":"postalcode"
},
  "geometry": {"coordinates":[-1.13603241728713,52.61639021319257],"type":"Point"}
}