{
  "type": "Feature",
  "properties": {
    "iso:country":"GB",
    "wof:name":"EH39 5ER",
    "wof:placetype":"postalcode"
},
  "geometry": {"coordinates":[-2.77903200305812,56.04534637791564],"type":"Point"}
}