{
  "type": "Feature",
  "properties": {
    "date:inception_lower":"1980-01-01",
    "date:inception_upper":"1980-01-31",
    "iso:country":"GB",
    "wof:name":"EH39 5ER",
    "wof:placetype":"postalcode"
},
  "geometry": {"coordinates":[-2.77815,56.045914],"type":"Point"}
}