{
  "type": "Feature",
  "properties": {
    "iso:country":"GB",
    "wof:name":"YO11 2AR",
    "wof:placetype":"postalcode"
},
  "geometry": {"coordinates":[-0.398190890895,54.27308431069963],"type":"Point"}
}