{
  "type": "Feature",
  "properties": {
    "iso:country": "GB",
    "wof:name": "GL4 6JE",
    "wof:placetype": "postalcode"
  },
  "geometry": {"coordinates":[-2.219378,51.830278],"type":"Point"}
}
