{
  "type": "Feature",
  "properties": {
    "iso:country":"GB",
    "wof:name":"GL4 6JE",
    "wof:placetype":"postalcode"
},
  "geometry": {"coordinates":[-2.21937827806396,51.83027767184876],"type":"Point"}
}