{
  "type": "Feature",
  "properties": {
    "iso:country": "GB",
    "wof:name": "WN6 9DQ",
    "wof:placetype": "postalcode"
  },
  "geometry": {"coordinates":[-2.712184,53.580509],"type":"Point"}
}
