{
  "type": "Feature",
  "properties": {
    "iso:country":"GB",
    "wof:name":"BN3 2RP",
    "wof:placetype":"postalcode"
},
  "geometry": {"coordinates":[-0.17391627509523,50.82562427573274],"type":"Point"}
}