{
  "type": "Feature",
  "properties": {
    "iso:country":"GB",
    "wof:name":"TA6 5HR",
    "wof:placetype":"postalcode"
},
  "geometry": {"coordinates":[-2.9960152406504,51.12888605440138],"type":"Point"}
}