{
  "type": "Feature",
  "properties": {
    "iso:country":"GB",
    "wof:name":"NE44 6DN",
    "wof:placetype":"postalcode"
},
  "geometry": {"coordinates":[-1.97872211656935,54.94669596738999],"type":"Point"}
}