{
  "type": "Feature",
  "properties": {
    "iso:country":"GB",
    "wof:name":"SS9 1LF",
    "wof:placetype":"postalcode"
},
  "geometry": {"coordinates":[0.66973787544643,51.54333261154479],"type":"Point"}
}