{
  "type": "Feature",
  "properties": {
    "iso:country":"GB",
    "wof:name":"BD16 1BY",
    "wof:placetype":"postalcode"
},
  "geometry": {"coordinates":[-1.87685386849045,53.83956375283137],"type":"Point"}
}