{
  "type": "Feature",
  "properties": {
    "iso:country":"GB",
    "wof:name":"SA4 3TY",
    "wof:placetype":"postalcode"
},
  "geometry": {"coordinates":[-4.14770484646975,51.6233598378855],"type":"Point"}
}