{
  "type": "Feature",
  "properties": {
    "iso:country":"GB",
    "wof:name":"WD25 9RJ",
    "wof:placetype":"postalcode"
},
  "geometry": {"coordinates":[-0.37911785516245,51.69363662613576],"type":"Point"}
}