{
  "type": "Feature",
  "properties": {
    "iso:country":"GB",
    "wof:name":"CF5 5QG",
    "wof:placetype":"postalcode"
},
  "geometry": {"coordinates":[-3.25636873830443,51.47137454621222],"type":"Point"}
}