{
  "type": "Feature",
  "properties": {
    "date:inception_lower": "1980-01-01",
    "date:inception_upper": "1980-01-01",
    "iso:country": "GB",
    "wof:name": "NR27 9HE",
    "wof:placetype": "postalcode"
  },
  "geometry": {"coordinates":[1.30195,52.931846],"type":"Point"}
}
