{
  "type": "Feature",
  "properties": {
    "iso:country":"GB",
    "wof:name":"NR27 9HE",
    "wof:placetype":"postalcode"
},
  "geometry": {"coordinates":[1.30195869778379,52.93178962767762],"type":"Point"}
}