{
  "type": "Feature",
  "properties": {
    "date:inception_lower": "1980-01-01",
    "date:inception_upper": "1980-01-01",
    "iso:country": "GB",
    "wof:name": "WF11 0PQ",
    "wof:placetype": "postalcode"
  },
  "geometry": {"coordinates":[-1.259288,53.703714],"type":"Point"}
}
