{
  "type": "Feature",
  "properties": {
    "iso:country":"GB",
    "wof:name":"WF11 0PQ",
    "wof:placetype":"postalcode"
},
  "geometry": {"coordinates":[-1.25928831910431,53.70371407267044],"type":"Point"}
}