{
  "type": "Feature",
  "properties": {
    "iso:country":"GB",
    "wof:name":"CA11 0HB",
    "wof:placetype":"postalcode"
},
  "geometry": {"coordinates":[-2.81608260118926,54.63228695164721],"type":"Point"}
}