{
  "type": "Feature",
  "properties": {
    "date:inception_lower": "1980-01-01",
    "date:inception_upper": "1980-01-01",
    "iso:country": "GB",
    "wof:name": "EH22 2JL",
    "wof:placetype": "postalcode"
  },
  "geometry": {"coordinates":[-3.050348,55.889992],"type":"Point"}
}
