{
  "type": "Feature",
  "properties": {
    "iso:country": "GB",
    "wof:name": "EH22 2JL",
    "wof:placetype": "postalcode"
  },
  "geometry": {"coordinates":[-3.050348,55.889992],"type":"Point"}
}
