{
  "type": "Feature",
  "properties": {
    "iso:country": "GB",
    "wof:name": "B37 7PD",
    "wof:placetype": "postalcode"
  },
  "geometry": {"coordinates":[-1.727733,52.471136],"type":"Point"}
}
