{
  "type": "Feature",
  "properties": {
    "iso:country":"GB",
    "wof:name":"LE7 7RJ",
    "wof:placetype":"postalcode"
},
  "geometry": {"coordinates":[-1.13859791840052,52.71290693901167],"type":"Point"}
}