{
  "type": "Feature",
  "properties": {
    "date:inception_lower": "1981-06-01",
    "date:inception_upper": "1981-06-01",
    "iso:country": "GB",
    "wof:name": "LE7 7RJ",
    "wof:placetype": "postalcode"
  },
  "geometry": {"coordinates":[-1.138598,52.712907],"type":"Point"}
}
