{
  "type": "Feature",
  "properties": {
    "iso:country": "GB",
    "wof:name": "LE7 7RJ",
    "wof:placetype": "postalcode"
  },
  "geometry": {"coordinates":[-1.138598,52.712907],"type":"Point"}
}
