{
  "type": "Feature",
  "properties": {
    "iso:country":"GB",
    "wof:name":"ME8 9QE",
    "wof:placetype":"postalcode"
},
  "geometry": {"coordinates":[0.59235257090885,51.34637327165166],"type":"Point"}
}