{
  "type": "Feature",
  "properties": {
    "date:inception_lower": "2005-12-01",
    "date:inception_upper": "2005-12-01",
    "iso:country": "GB",
    "wof:name": "TS18 3BU",
    "wof:placetype": "postalcode"
  },
  "geometry": {"coordinates":[-1.313014,54.560818],"type":"Point"}
}
