{
  "type": "Feature",
  "properties": {
    "iso:country":"GB",
    "wof:name":"TS18 3BU",
    "wof:placetype":"postalcode"
},
  "geometry": {"coordinates":[-1.31301453636202,54.56081811734347],"type":"Point"}
}