{
  "type": "Feature",
  "properties": {
    "iso:country":"GB",
    "wof:name":"M22 4GX",
    "wof:placetype":"postalcode"
},
  "geometry": {"coordinates":[-2.26257212728737,53.41006023591071],"type":"Point"}
}