{
  "type": "Feature",
  "properties": {
    "iso:country": "GB",
    "wof:name": "M22 4GX",
    "wof:placetype": "postalcode"
  },
  "geometry": {"coordinates":[-2.262572,53.41006],"type":"Point"}
}
