{
  "type": "Feature",
  "properties": {
    "iso:country":"GB",
    "wof:name":"TF5 0PH",
    "wof:placetype":"postalcode"
},
  "geometry": {"coordinates":[-2.53915238301102,52.72020075895929],"type":"Point"}
}