{
  "type": "Feature",
  "properties": {
    "date:inception_lower":"1994-12-01",
    "date:inception_upper":"1994-12-31",
    "iso:country":"GB",
    "wof:name":"TF5 0PH",
    "wof:placetype":"postalcode"
},
  "geometry": {"coordinates":[-2.539152,52.720201],"type":"Point"}
}