{
  "type": "Feature",
  "properties": {
    "iso:country":"GB",
    "wof:name":"M46 9RX",
    "wof:placetype":"postalcode"
},
  "geometry": {"coordinates":[-2.47645341501473,53.5318938241001],"type":"Point"}
}