{
  "type": "Feature",
  "properties": {
    "iso:country":"GB",
    "wof:name":"SK6 4HW",
    "wof:placetype":"postalcode"
},
  "geometry": {"coordinates":[-2.07077150025016,53.41108337132182],"type":"Point"}
}