{
  "type": "Feature",
  "properties": {
    "iso:country":"GB",
    "wof:name":"WD7 9LU",
    "wof:placetype":"postalcode"
},
  "geometry": {"coordinates":[-0.28532498958561,51.69377075571783],"type":"Point"}
}