{
  "type": "Feature",
  "properties": {
    "date:inception_lower": "2015-03-01",
    "date:inception_upper": "2015-03-01",
    "iso:country": "GB",
    "wof:name": "WD7 9LU",
    "wof:placetype": "postalcode"
  },
  "geometry": {"coordinates":[-0.2853,51.693776],"type":"Point"}
}
