{
  "type": "Feature",
  "properties": {
    "iso:country": "GB",
    "wof:name": "WD7 9LU",
    "wof:placetype": "postalcode"
  },
  "geometry": {"coordinates":[-0.2853,51.693776],"type":"Point"}
}
