{
  "type": "Feature",
  "properties": {
    "iso:country": "GB",
    "wof:name": "LS16 7JH",
    "wof:placetype": "postalcode"
  },
  "geometry": {"coordinates":[-1.628376,53.85434],"type":"Point"}
}
