{
  "type": "Feature",
  "properties": {
    "iso:country":"GB",
    "wof:name":"LS16 7JH",
    "wof:placetype":"postalcode"
},
  "geometry": {"coordinates":[-1.62837606804745,53.85434048758815],"type":"Point"}
}