{
  "type": "Feature",
  "properties": {
    "iso:country":"GB",
    "wof:name":"PO31 8AP",
    "wof:placetype":"postalcode"
},
  "geometry": {"coordinates":[-1.30446330304139,50.7489101749145],"type":"Point"}
}