{
  "type": "Feature",
  "properties": {
    "iso:country": "GB",
    "wof:name": "PO31 8AP",
    "wof:placetype": "postalcode"
  },
  "geometry": {"coordinates":[-1.304463,50.74891],"type":"Point"}
}
