{
  "type": "Feature",
  "properties": {
    "iso:country":"GB",
    "wof:name":"CM2 6AX",
    "wof:placetype":"postalcode"
},
  "geometry": {"coordinates":[0.49632536298452,51.7440131264581],"type":"Point"}
}