{
  "type": "Feature",
  "properties": {
    "iso:country":"GB",
    "wof:name":"WA1 3HD",
    "wof:placetype":"postalcode"
},
  "geometry": {"coordinates":[-2.5563960592914,53.40053086252683],"type":"Point"}
}