{
  "type": "Feature",
  "properties": {
    "date:inception_lower": "1980-01-01",
    "date:inception_upper": "1980-01-01",
    "iso:country": "GB",
    "wof:name": "SW5 9LD",
    "wof:placetype": "postalcode"
  },
  "geometry": {"coordinates":[-0.194968,51.487913],"type":"Point"}
}
