{
  "type": "Feature",
  "properties": {
    "iso:country":"GB",
    "wof:name":"DN8 4NW",
    "wof:placetype":"postalcode"
},
  "geometry": {"coordinates":[-0.94823893523471,53.63471925894286],"type":"Point"}
}