{
  "type": "Feature",
  "properties": {
    "iso:country": "GB",
    "wof:name": "DN8 4NW",
    "wof:placetype": "postalcode"
  },
  "geometry": {"coordinates":[-0.948239,53.634719],"type":"Point"}
}
