{
  "type": "Feature",
  "properties": {
    "iso:country":"GB",
    "wof:name":"SN2 7ND",
    "wof:placetype":"postalcode"
},
  "geometry": {"coordinates":[-1.75968203806507,51.58560626947768],"type":"Point"}
}