{
  "type": "Feature",
  "properties": {
    "date:inception_lower":"1990-02-01",
    "date:inception_upper":"1990-02-28",
    "iso:country":"GB",
    "wof:name":"SK10 2UB",
    "wof:placetype":"postalcode"
},
  "geometry": {"coordinates":[-2.13092,53.270522],"type":"Point"}
}