{
  "type": "Feature",
  "properties": {
    "iso:country":"GB",
    "wof:name":"SK10 2UB",
    "wof:placetype":"postalcode"
},
  "geometry": {"coordinates":[-2.13092026991618,53.27052181898932],"type":"Point"}
}