{
  "type": "Feature",
  "properties": {
    "iso:country":"GB",
    "wof:name":"PL25 4JQ",
    "wof:placetype":"postalcode"
},
  "geometry": {"coordinates":[-4.77944696552173,50.34355778848322],"type":"Point"}
}