{
  "type": "Feature",
  "properties": {
    "iso:country": "GB",
    "wof:name": "CW10 9JB",
    "wof:placetype": "postalcode"
  },
  "geometry": {"coordinates":[-2.468461,53.196791],"type":"Point"}
}
