{
  "type": "Feature",
  "properties": {
    "iso:country":"GB",
    "wof:name":"CM3 4QR",
    "wof:placetype":"postalcode"
},
  "geometry": {"coordinates":[0.59377586086055,51.71563257092757],"type":"Point"}
}