{
  "type": "Feature",
  "properties": {
    "iso:country":"GB",
    "wof:name":"E2 8EE",
    "wof:placetype":"postalcode"
},
  "geometry": {"coordinates":[-0.07615864058143,51.53421556815915],"type":"Point"}
}