{
  "type": "Feature",
  "properties": {
    "date:inception_lower": "2012-03-01",
    "date:inception_upper": "2012-03-01",
    "iso:country": "GB",
    "wof:name": "HA0 4GL",
    "wof:placetype": "postalcode"
  },
  "geometry": {"coordinates":[-0.301847,51.551808],"type":"Point"}
}
