{
  "type": "Feature",
  "properties": {
    "iso:country":"GB",
    "wof:name":"SA9 2JR",
    "wof:placetype":"postalcode"
},
  "geometry": {"coordinates":[-3.7783521101541,51.76771131399776],"type":"Point"}
}