{
  "type": "Feature",
  "properties": {
    "iso:country":"GB",
    "wof:name":"EN6 2EL",
    "wof:placetype":"postalcode"
},
  "geometry": {"coordinates":[-0.19424193487991,51.69049058120666],"type":"Point"}
}