{
  "type": "Feature",
  "properties": {
    "date:inception_lower": "1980-01-01",
    "date:inception_upper": "1980-01-01",
    "iso:country": "GB",
    "wof:name": "EN6 2EL",
    "wof:placetype": "postalcode"
  },
  "geometry": {"coordinates":[-0.194242,51.690491],"type":"Point"}
}
