{
  "type": "Feature",
  "properties": {
    "iso:country":"GB",
    "wof:name":"TS11 8DQ",
    "wof:placetype":"postalcode"
},
  "geometry": {"coordinates":[-1.04287429182336,54.57642757528657],"type":"Point"}
}