{
  "type": "Feature",
  "properties": {
    "date:inception_lower": "1980-01-01",
    "date:inception_upper": "1980-01-01",
    "iso:country": "GB",
    "wof:name": "TS11 8DQ",
    "wof:placetype": "postalcode"
  },
  "geometry": {"coordinates":[-1.042874,54.576428],"type":"Point"}
}
