{
  "type": "Feature",
  "properties": {
    "iso:country":"GB",
    "wof:name":"DE75 7TE",
    "wof:placetype":"postalcode"
},
  "geometry": {"coordinates":[-1.35909229732083,53.01894007780323],"type":"Point"}
}