{
  "type": "Feature",
  "properties": {
    "iso:country":"GB",
    "wof:name":"EX13 7RL",
    "wof:placetype":"postalcode"
},
  "geometry": {"coordinates":[-3.03494019355706,50.77757533953871],"type":"Point"}
}