{
  "type": "Feature",
  "properties": {
    "date:inception_lower":"1998-12-01",
    "date:inception_upper":"1998-12-31",
    "iso:country":"GB",
    "wof:name":"IV36 3JS",
    "wof:placetype":"postalcode"
},
  "geometry": {"coordinates":[-3.600955,57.615028],"type":"Point"}
}