{
  "type": "Feature",
  "properties": {
    "iso:country":"GB",
    "wof:name":"IV36 3JS",
    "wof:placetype":"postalcode"
},
  "geometry": {"coordinates":[-3.60095486594163,57.61502781320075],"type":"Point"}
}