{
  "type": "Feature",
  "properties": {
    "date:inception_lower": "2002-07-01",
    "date:inception_upper": "2002-07-01",
    "iso:country": "GB",
    "wof:name": "WD3 8XD",
    "wof:placetype": "postalcode"
  },
  "geometry": {"coordinates":[-0.499204,51.628575],"type":"Point"}
}
