{
  "type": "Feature",
  "properties": {
    "iso:country":"GB",
    "wof:name":"WD3 8XD",
    "wof:placetype":"postalcode"
},
  "geometry": {"coordinates":[-0.49920389507174,51.6285749658771],"type":"Point"}
}