{
  "type": "Feature",
  "properties": {
    "iso:country":"GB",
    "wof:name":"CW1 3QQ",
    "wof:placetype":"postalcode"
},
  "geometry": {"coordinates":[-2.46300137517661,53.11236940518275],"type":"Point"}
}