{
  "type": "Feature",
  "properties": {
    "date:inception_lower":"2002-08-01",
    "date:inception_upper":"2002-08-31",
    "iso:country":"GB",
    "wof:name":"CW1 3QQ",
    "wof:placetype":"postalcode"
},
  "geometry": {"coordinates":[-2.463001,53.112369],"type":"Point"}
}