{
  "type": "Feature",
  "properties": {
    "iso:country":"GB",
    "wof:name":"DT6 4PT",
    "wof:placetype":"postalcode"
},
  "geometry": {"coordinates":[-2.73930110163251,50.70558909656107],"type":"Point"}
}