{
  "type": "Feature",
  "properties": {
    "iso:country": "GB",
    "wof:name": "ST9 0LT",
    "wof:placetype": "postalcode"
  },
  "geometry": {"coordinates":[-2.097557,53.026711],"type":"Point"}
}
