{
  "type": "Feature",
  "properties": {
    "iso:country":"GB",
    "wof:name":"ST9 0LT",
    "wof:placetype":"postalcode"
},
  "geometry": {"coordinates":[-2.0975571683921,53.02671082268424],"type":"Point"}
}