{
  "type": "Feature",
  "properties": {
    "iso:country":"GB",
    "wof:name":"TS24 0WE",
    "wof:placetype":"postalcode"
},
  "geometry": {"coordinates":[-1.2007215868273,54.6876452901713],"type":"Point"}
}