{
  "type": "Feature",
  "properties": {
    "iso:country": "GB",
    "wof:name": "SW9 6TT",
    "wof:placetype": "postalcode"
  },
  "geometry": {"coordinates":[-0.10431,51.475386],"type":"Point"}
}
