{
  "type": "Feature",
  "properties": {
    "iso:country":"GB",
    "wof:name":"SW9 6TT",
    "wof:placetype":"postalcode"
},
  "geometry": {"coordinates":[-0.10431045111863,51.47538593834706],"type":"Point"}
}