{
  "type": "Feature",
  "properties": {
    "iso:country":"GB",
    "wof:name":"CF83 3PX",
    "wof:placetype":"postalcode"
},
  "geometry": {"coordinates":[-3.21617473684479,51.58838705216518],"type":"Point"}
}