{
  "type": "Feature",
  "properties": {
    "date:inception_lower": "1980-01-01",
    "date:inception_upper": "1980-01-01",
    "iso:country": "GB",
    "wof:name": "BS3 4SQ",
    "wof:placetype": "postalcode"
  },
  "geometry": {"coordinates":[-2.582803,51.440357],"type":"Point"}
}
