{
  "type": "Feature",
  "properties": {
    "iso:country":"GB",
    "wof:name":"BS3 4SQ",
    "wof:placetype":"postalcode"
},
  "geometry": {"coordinates":[-2.58275707715293,51.44032322570236],"type":"Point"}
}