{
  "type": "Feature",
  "properties": {
    "date:inception_lower": "1980-01-01",
    "date:inception_upper": "1980-01-01",
    "iso:country": "GB",
    "wof:name": "SL5 9AT",
    "wof:placetype": "postalcode"
  },
  "geometry": {"coordinates":[-0.659264,51.400074],"type":"Point"}
}
