{
  "type": "Feature",
  "properties": {
    "iso:country": "GB",
    "wof:name": "GL4 0AL",
    "wof:placetype": "postalcode"
  },
  "geometry": {"coordinates":[-2.246427,51.838127],"type":"Point"}
}
