{
  "type": "Feature",
  "properties": {
    "iso:country":"GB",
    "wof:name":"DL5 5JA",
    "wof:placetype":"postalcode"
},
  "geometry": {"coordinates":[-1.57010789112361,54.61043419151153],"type":"Point"}
}