{
  "type": "Feature",
  "properties": {
    "date:inception_lower": "2017-08-01",
    "date:inception_upper": "2017-08-01",
    "iso:country": "GB",
    "wof:name": "CA3 9HY",
    "wof:placetype": "postalcode"
  },
  "geometry": {"coordinates":[-2.938274,54.905922],"type":"Point"}
}
