{
  "type": "Feature",
  "properties": {
    "iso:country": "GB",
    "wof:name": "GU21 5HY",
    "wof:placetype": "postalcode"
  },
  "geometry": {"coordinates":[-0.54867,51.322421],"type":"Point"}
}
