{
  "type": "Feature",
  "properties": {
    "iso:country":"GB",
    "wof:name":"SA3 4TU",
    "wof:placetype":"postalcode"
},
  "geometry": {"coordinates":[-4.0201826954108,51.57728023384759],"type":"Point"}
}