{
  "type": "Feature",
  "properties": {
    "iso:country":"GB",
    "wof:name":"SE18 1TG",
    "wof:placetype":"postalcode"
},
  "geometry": {"coordinates":[0.08564995714162,51.48466064240474],"type":"Point"}
}