{
  "type": "Feature",
  "properties": {
    "iso:country": "GB",
    "wof:name": "ME12 2JG",
    "wof:placetype": "postalcode"
  },
  "geometry": {"coordinates":[0.804541,51.422258],"type":"Point"}
}
