{
  "type": "Feature",
  "properties": {
    "iso:country":"GB",
    "wof:name":"BA2 5SJ",
    "wof:placetype":"postalcode"
},
  "geometry": {"coordinates":[-2.36303659245139,51.35750662112467],"type":"Point"}
}