{
  "type": "Feature",
  "properties": {
    "iso:country": "GB",
    "wof:name": "BA2 5SJ",
    "wof:placetype": "postalcode"
  },
  "geometry": {"coordinates":[-2.363037,51.357507],"type":"Point"}
}
