{
  "type": "Feature",
  "properties": {
    "date:inception_lower": "2021-11-01",
    "date:inception_upper": "2021-11-01",
    "iso:country": "GB",
    "wof:name": "NG10 1RB",
    "wof:placetype": "postalcode"
  },
  "geometry": {"coordinates":[-1.268227,52.896359],"type":"Point"}
}
