{
  "type": "Feature",
  "properties": {
    "iso:country":"GB",
    "wof:name":"DH6 1HY",
    "wof:placetype":"postalcode"
},
  "geometry": {"coordinates":[-1.50663399566095,54.77632984838441],"type":"Point"}
}