{
  "type": "Feature",
  "properties": {
    "iso:country":"GB",
    "wof:name":"DH2 2PR",
    "wof:placetype":"postalcode"
},
  "geometry": {"coordinates":[-1.60685738726563,54.85508500981107],"type":"Point"}
}