{
  "type": "Feature",
  "properties": {
    "date:inception_lower":"1980-01-01",
    "date:inception_upper":"1980-01-31",
    "iso:country":"GB",
    "wof:name":"DH2 2PR",
    "wof:placetype":"postalcode"
},
  "geometry": {"coordinates":[-1.606857,54.855085],"type":"Point"}
}