{
  "type": "Feature",
  "properties": {
    "date:inception_lower": "2018-01-01",
    "date:inception_upper": "2018-01-01",
    "iso:country": "GB",
    "wof:name": "GL2 8FB",
    "wof:placetype": "postalcode"
  },
  "geometry": {"coordinates":[-2.300575,51.881597],"type":"Point"}
}
