{
  "type": "Feature",
  "properties": {
    "iso:country": "GB",
    "wof:name": "PL28 8NE",
    "wof:placetype": "postalcode"
  },
  "geometry": {"coordinates":[-4.990637,50.530512],"type":"Point"}
}
