{
  "type": "Feature",
  "properties": {
    "iso:country": "GB",
    "wof:name": "SA3 3DF",
    "wof:placetype": "postalcode"
  },
  "geometry": {"coordinates":[-4.045711,51.577854],"type":"Point"}
}
