{
  "type": "Feature",
  "properties": {
    "iso:country": "GB",
    "wof:name": "WA5 1NR",
    "wof:placetype": "postalcode"
  },
  "geometry": {"coordinates":[-2.61412,53.389048],"type":"Point"}
}
