{
  "type": "Feature",
  "properties": {
    "iso:country":"GB",
    "wof:name":"WA5 1NR",
    "wof:placetype":"postalcode"
},
  "geometry": {"coordinates":[-2.61412025729715,53.38904787999547],"type":"Point"}
}