{
  "type": "Feature",
  "properties": {
    "iso:country":"GB",
    "wof:name":"HP4 3DQ",
    "wof:placetype":"postalcode"
},
  "geometry": {"coordinates":[-0.57088607877336,51.760228154966],"type":"Point"}
}