{
  "type": "Feature",
  "properties": {
    "iso:country":"GB",
    "wof:name":"BN25 3RY",
    "wof:placetype":"postalcode"
},
  "geometry": {"coordinates":[0.12348319220698,50.77698797297406],"type":"Point"}
}