{
  "type": "Feature",
  "properties": {
    "iso:country":"GB",
    "wof:name":"M11 3TS",
    "wof:placetype":"postalcode"
},
  "geometry": {"coordinates":[-2.19982139070521,53.47949221286946],"type":"Point"}
}