{
  "type": "Feature",
  "properties": {
    "iso:country":"GB",
    "wof:name":"CB21 5DU",
    "wof:placetype":"postalcode"
},
  "geometry": {"coordinates":[0.21095654771255,52.18292751250175],"type":"Point"}
}