{
  "type": "Feature",
  "properties": {
    "date:inception_lower": "1980-01-01",
    "date:inception_upper": "1980-01-01",
    "iso:country": "GB",
    "wof:name": "LS8 1DS",
    "wof:placetype": "postalcode"
  },
  "geometry": {"coordinates":[-1.51135,53.841149],"type":"Point"}
}
