{
  "type": "Feature",
  "properties": {
    "iso:country":"GB",
    "wof:name":"LS8 1DS",
    "wof:placetype":"postalcode"
},
  "geometry": {"coordinates":[-1.51135035056581,53.84114937754861],"type":"Point"}
}