{
  "type": "Feature",
  "properties": {
    "iso:country": "GB",
    "wof:name": "PL17 7LY",
    "wof:placetype": "postalcode"
  },
  "geometry": {"coordinates":[-4.373711,50.537563],"type":"Point"}
}
