{
  "type": "Feature",
  "properties": {
    "date:inception_lower": "1980-01-01",
    "date:inception_upper": "1980-01-01",
    "iso:country": "GB",
    "wof:name": "RH11 8HW",
    "wof:placetype": "postalcode"
  },
  "geometry": {"coordinates":[-0.215052,51.109474],"type":"Point"}
}
