{
  "type": "Feature",
  "properties": {
    "iso:country": "GB",
    "wof:name": "RH11 8HW",
    "wof:placetype": "postalcode"
  },
  "geometry": {"coordinates":[-0.215052,51.109474],"type":"Point"}
}
