{
  "type": "Feature",
  "properties": {
    "date:inception_lower":"2009-09-01",
    "date:inception_upper":"2009-09-30",
    "iso:country":"GB",
    "wof:name":"N11 2AQ",
    "wof:placetype":"postalcode"
},
  "geometry": {"coordinates":[-0.126455,51.611064],"type":"Point"}
}