{
  "type": "Feature",
  "properties": {
    "iso:country":"GB",
    "wof:name":"WF9 2FN",
    "wof:placetype":"postalcode"
},
  "geometry": {"coordinates":[-1.29793406675503,53.58510224491953],"type":"Point"}
}