{
  "type": "Feature",
  "properties": {
    "date:inception_lower": "2015-01-01",
    "date:inception_upper": "2015-01-01",
    "iso:country": "GB",
    "wof:name": "WF9 2FN",
    "wof:placetype": "postalcode"
  },
  "geometry": {"coordinates":[-1.297934,53.585102],"type":"Point"}
}
