{
  "type": "Feature",
  "properties": {
    "iso:country": "GB",
    "wof:name": "CB21 4RF",
    "wof:placetype": "postalcode"
  },
  "geometry": {"coordinates":[0.369272,52.093527],"type":"Point"}
}
