{
  "type": "Feature",
  "properties": {
    "date:inception_lower":"1980-01-01",
    "date:inception_upper":"1980-01-31",
    "iso:country":"GB",
    "wof:name":"RM15 4XL",
    "wof:placetype":"postalcode"
},
  "geometry": {"coordinates":[0.237312,51.503331],"type":"Point"}
}