{
  "type": "Feature",
  "properties": {
    "date:inception_lower": "2004-11-01",
    "date:inception_upper": "2004-11-01",
    "iso:country": "GB",
    "wof:name": "S60 5UX",
    "wof:placetype": "postalcode"
  },
  "geometry": {"coordinates":[-1.343856,53.383775],"type":"Point"}
}
