{
  "type": "Feature",
  "properties": {
    "iso:country":"GB",
    "wof:name":"S60 5UX",
    "wof:placetype":"postalcode"
},
  "geometry": {"coordinates":[-1.34385647469155,53.38377545886473],"type":"Point"}
}