{
  "type": "Feature",
  "properties": {
    "iso:country":"GB",
    "wof:name":"B44 8ND",
    "wof:placetype":"postalcode"
},
  "geometry": {"coordinates":[-1.89730203620439,52.53606894118883],"type":"Point"}
}