{
  "type": "Feature",
  "properties": {
    "iso:country": "GB",
    "wof:name": "B44 8ND",
    "wof:placetype": "postalcode"
  },
  "geometry": {"coordinates":[-1.897302,52.536069],"type":"Point"}
}
