{
  "type": "Feature",
  "properties": {
    "iso:country":"GB",
    "wof:name":"OX16 9DN",
    "wof:placetype":"postalcode"
},
  "geometry": {"coordinates":[-1.33452249252419,52.04648799197843],"type":"Point"}
}