{
  "type": "Feature",
  "properties": {
    "iso:country": "GB",
    "wof:name": "B69 4LB",
    "wof:placetype": "postalcode"
  },
  "geometry": {"coordinates":[-2.011927,52.500726],"type":"Point"}
}
