{
  "type": "Feature",
  "properties": {
    "date:inception_lower": "1980-01-01",
    "date:inception_upper": "1980-01-01",
    "iso:country": "GB",
    "wof:name": "TS21 3BD",
    "wof:placetype": "postalcode"
  },
  "geometry": {"coordinates":[-1.447889,54.654909],"type":"Point"}
}
