{
  "type": "Feature",
  "properties": {
    "iso:country": "GB",
    "wof:name": "SE5 7QZ",
    "wof:placetype": "postalcode"
  },
  "geometry": {"coordinates":[-0.084868,51.477156],"type":"Point"}
}
