{
  "type": "Feature",
  "properties": {
    "iso:country":"GB",
    "wof:name":"SE5 7QZ",
    "wof:placetype":"postalcode"
},
  "geometry": {"coordinates":[-0.08486806235822,51.47715627051905],"type":"Point"}
}