{
  "type": "Feature",
  "properties": {
    "iso:country":"GB",
    "wof:name":"LE19 4AD",
    "wof:placetype":"postalcode"
},
  "geometry": {"coordinates":[-1.22730903848505,52.59895068846104],"type":"Point"}
}