{
  "type": "Feature",
  "properties": {
    "iso:country":"GB",
    "wof:name":"BN13 3LW",
    "wof:placetype":"postalcode"
},
  "geometry": {"coordinates":[-0.41783548720732,50.84000570443835],"type":"Point"}
}