{
  "type": "Feature",
  "properties": {
    "iso:country":"GB",
    "wof:name":"SA62 4NN",
    "wof:placetype":"postalcode"
},
  "geometry": {"coordinates":[-4.96303181525175,51.75508051448998],"type":"Point"}
}