{
  "type": "Feature",
  "properties": {
    "iso:country":"GB",
    "wof:name":"MK16 8QE",
    "wof:placetype":"postalcode"
},
  "geometry": {"coordinates":[-0.74559698999916,52.08706975395888],"type":"Point"}
}