{
  "type": "Feature",
  "properties": {
    "date:inception_lower": "1980-01-01",
    "date:inception_upper": "1980-01-01",
    "iso:country": "GB",
    "wof:name": "BA14 0EP",
    "wof:placetype": "postalcode"
  },
  "geometry": {"coordinates":[-2.213137,51.309248],"type":"Point"}
}
