{
  "type": "Feature",
  "properties": {
    "iso:country":"GB",
    "wof:name":"BN25 2HE",
    "wof:placetype":"postalcode"
},
  "geometry": {"coordinates":[0.10180453816178,50.77910753573728],"type":"Point"}
}