{
  "type": "Feature",
  "properties": {
    "iso:country":"GB",
    "wof:name":"G81 2EU",
    "wof:placetype":"postalcode"
},
  "geometry": {"coordinates":[-4.39338872805176,55.91051243731802],"type":"Point"}
}