{
  "type": "Feature",
  "properties": {
    "iso:country":"GB",
    "wof:name":"W1S 1FX",
    "wof:placetype":"postalcode"
},
  "geometry": {"coordinates":[-0.14278945983547,51.51255637695844],"type":"Point"}
}