{
  "type": "Feature",
  "properties": {
    "iso:country": "GB",
    "wof:name": "HP21 8PS",
    "wof:placetype": "postalcode"
  },
  "geometry": {"coordinates":[-0.827664,51.806426],"type":"Point"}
}
