{
  "type": "Feature",
  "properties": {
    "iso:country":"GB",
    "wof:name":"SW9 9LB",
    "wof:placetype":"postalcode"
},
  "geometry": {"coordinates":[-0.12617282779836,51.46687967415602],"type":"Point"}
}