{
  "type": "Feature",
  "properties": {
    "date:inception_lower": "1980-01-01",
    "date:inception_upper": "1980-01-01",
    "iso:country": "GB",
    "wof:name": "NG11 8RS",
    "wof:placetype": "postalcode"
  },
  "geometry": {"coordinates":[-1.191371,52.903204],"type":"Point"}
}
