{
  "type": "Feature",
  "properties": {
    "iso:country":"GB",
    "wof:name":"S13 7TQ",
    "wof:placetype":"postalcode"
},
  "geometry": {"coordinates":[-1.36676152679129,53.36297327270715],"type":"Point"}
}