{
  "type": "Feature",
  "properties": {
    "iso:country": "GB",
    "wof:name": "DN35 9AL",
    "wof:placetype": "postalcode"
  },
  "geometry": {"coordinates":[-0.038324,53.54954],"type":"Point"}
}
