{
  "type": "Feature",
  "properties": {
    "iso:country":"GB",
    "wof:name":"DN35 9AL",
    "wof:placetype":"postalcode"
},
  "geometry": {"coordinates":[-0.0383243984231,53.54954030696757],"type":"Point"}
}