{
  "type": "Feature",
  "properties": {
    "iso:country": "GB",
    "wof:name": "LL12 9NB",
    "wof:placetype": "postalcode"
  },
  "geometry": {"coordinates":[-3.032805,53.120178],"type":"Point"}
}
