{
  "type": "Feature",
  "properties": {
    "iso:country":"GB",
    "wof:name":"LL12 9NB",
    "wof:placetype":"postalcode"
},
  "geometry": {"coordinates":[-3.03280459447183,53.12017794514714],"type":"Point"}
}