{
  "type": "Feature",
  "properties": {
    "iso:country":"GB",
    "wof:name":"BA1 2QN",
    "wof:placetype":"postalcode"
},
  "geometry": {"coordinates":[-2.36154024693687,51.38632066121408],"type":"Point"}
}