{
  "type": "Feature",
  "properties": {
    "iso:country": "GB",
    "wof:name": "W2 3QE",
    "wof:placetype": "postalcode"
  },
  "geometry": {"coordinates":[-0.179673,51.51246],"type":"Point"}
}
