{
  "type": "Feature",
  "properties": {
    "iso:country":"GB",
    "wof:name":"SO50 5QU",
    "wof:placetype":"postalcode"
},
  "geometry": {"coordinates":[-1.35306519045331,50.9627904594126],"type":"Point"}
}