{
  "type": "Feature",
  "properties": {
    "date:inception_lower":"1995-07-01",
    "date:inception_upper":"1995-07-31",
    "iso:country":"GB",
    "wof:name":"HS3 3AR",
    "wof:placetype":"postalcode"
},
  "geometry": {"coordinates":[-6.949017,57.952233],"type":"Point"}
}