{
  "type": "Feature",
  "properties": {
    "date:inception_lower": "1981-06-01",
    "date:inception_upper": "1981-06-01",
    "iso:country": "GB",
    "wof:name": "NG17 3FY",
    "wof:placetype": "postalcode"
  },
  "geometry": {"coordinates":[-1.277082,53.140499],"type":"Point"}
}
