{
  "type": "Feature",
  "properties": {
    "date:inception_lower": "2011-03-01",
    "date:inception_upper": "2011-03-01",
    "iso:country": "GB",
    "wof:name": "LS27 7FE",
    "wof:placetype": "postalcode"
  },
  "geometry": {"coordinates":[-1.631627,53.750548],"type":"Point"}
}
