{
  "type": "Feature",
  "properties": {
    "iso:country":"GB",
    "wof:name":"LS27 7FE",
    "wof:placetype":"postalcode"
},
  "geometry": {"coordinates":[-1.63162741341221,53.75054804399372],"type":"Point"}
}