{
  "type": "Feature",
  "properties": {
    "iso:country":"GB",
    "wof:name":"GU8 5EB",
    "wof:placetype":"postalcode"
},
  "geometry": {"coordinates":[-0.65453706426866,51.17422225122564],"type":"Point"}
}