{
  "type": "Feature",
  "properties": {
    "iso:country":"GB",
    "wof:name":"KT18 7RA",
    "wof:placetype":"postalcode"
},
  "geometry": {"coordinates":[-0.26850447441582,51.32754360813569],"type":"Point"}
}