{
  "type": "Feature",
  "properties": {
    "iso:country": "GB",
    "wof:name": "KT18 7RA",
    "wof:placetype": "postalcode"
  },
  "geometry": {"coordinates":[-0.268504,51.327544],"type":"Point"}
}
