{
  "type": "Feature",
  "properties": {
    "iso:country": "GB",
    "wof:name": "M22 4JQ",
    "wof:placetype": "postalcode"
  },
  "geometry": {"coordinates":[-2.261644,53.405937],"type":"Point"}
}
