{
  "type": "Feature",
  "properties": {
    "iso:country":"GB",
    "wof:name":"M22 4JQ",
    "wof:placetype":"postalcode"
},
  "geometry": {"coordinates":[-2.26164419685322,53.40593652002349],"type":"Point"}
}