{
  "type": "Feature",
  "properties": {
    "iso:country":"GB",
    "wof:name":"DL1 1SH",
    "wof:placetype":"postalcode"
},
  "geometry": {"coordinates":[-1.54862900000031,54.52537604423],"type":"Point"}
}