{
  "type": "Feature",
  "properties": {
    "iso:country": "GB",
    "wof:name": "G23 5PD",
    "wof:placetype": "postalcode"
  },
  "geometry": {"coordinates":[-4.294753,55.903152],"type":"Point"}
}
