{
  "type": "Feature",
  "properties": {
    "iso:country":"GB",
    "wof:name":"G23 5PD",
    "wof:placetype":"postalcode"
},
  "geometry": {"coordinates":[-4.2947527719388,55.90315161410781],"type":"Point"}
}