{
  "type": "Feature",
  "properties": {
    "iso:country": "GB",
    "wof:name": "SA64 0DG",
    "wof:placetype": "postalcode"
  },
  "geometry": {"coordinates":[-4.994517,52.004785],"type":"Point"}
}
