{
  "type": "Feature",
  "properties": {
    "iso:country":"GB",
    "wof:name":"SA64 0DG",
    "wof:placetype":"postalcode"
},
  "geometry": {"coordinates":[-4.99477061752684,52.00463575613009],"type":"Point"}
}