{
  "type": "Feature",
  "properties": {
    "iso:country":"GB",
    "wof:name":"DT2 7QN",
    "wof:placetype":"postalcode"
},
  "geometry": {"coordinates":[-2.41697185281684,50.79492073516347],"type":"Point"}
}