{
  "type": "Feature",
  "properties": {
    "iso:country":"GB",
    "wof:name":"PR5 0RN",
    "wof:placetype":"postalcode"
},
  "geometry": {"coordinates":[-2.57956996894797,53.75572394751401],"type":"Point"}
}