{
  "type": "Feature",
  "properties": {
    "iso:country":"GB",
    "wof:name":"B73 5NB",
    "wof:placetype":"postalcode"
},
  "geometry": {"coordinates":[-1.82932961964202,52.53809424198177],"type":"Point"}
}