{
  "type": "Feature",
  "properties": {
    "iso:country": "GB",
    "wof:name": "DL16 6YD",
    "wof:placetype": "postalcode"
  },
  "geometry": {"coordinates":[-1.570856,54.708563],"type":"Point"}
}
