{
  "type": "Feature",
  "properties": {
    "date:inception_lower":"1984-10-01",
    "date:inception_upper":"1984-10-31",
    "iso:country":"GB",
    "wof:name":"DL16 6YD",
    "wof:placetype":"postalcode"
},
  "geometry": {"coordinates":[-1.570856,54.708563],"type":"Point"}
}