{
  "type": "Feature",
  "properties": {
    "iso:country":"GB",
    "wof:name":"NE19 2HT",
    "wof:placetype":"postalcode"
},
  "geometry": {"coordinates":[-1.99153808964993,55.02873227633192],"type":"Point"}
}