{
  "type": "Feature",
  "properties": {
    "iso:country": "GB",
    "wof:name": "NE19 2HT",
    "wof:placetype": "postalcode"
  },
  "geometry": {"coordinates":[-1.990905,55.028433],"type":"Point"}
}
