{
  "type": "Feature",
  "properties": {
    "iso:country": "GB",
    "wof:name": "NE19 2HT",
    "wof:placetype": "postalcode"
  },
  "geometry": {"coordinates":[-1.991547,55.028738],"type":"Point"}
}
