{
  "type": "Feature",
  "properties": {
    "iso:country":"GB",
    "wof:name":"CM12 0YH",
    "wof:placetype":"postalcode"
},
  "geometry": {"coordinates":[0.41779092938029,51.63946612519435],"type":"Point"}
}