{
  "type": "Feature",
  "properties": {
    "iso:country": "GB",
    "wof:name": "CM12 0YH",
    "wof:placetype": "postalcode"
  },
  "geometry": {"coordinates":[0.417791,51.639466],"type":"Point"}
}
