{
  "type": "Feature",
  "properties": {
    "iso:country":"GB",
    "wof:name":"SL3 8DG",
    "wof:placetype":"postalcode"
},
  "geometry": {"coordinates":[-0.5498831965475,51.50715423590322],"type":"Point"}
}