{
  "type": "Feature",
  "properties": {
    "date:inception_lower": "1997-12-01",
    "date:inception_upper": "1997-12-01",
    "iso:country": "GB",
    "wof:name": "BA2 1RQ",
    "wof:placetype": "postalcode"
  },
  "geometry": {"coordinates":[-2.407459,51.377232],"type":"Point"}
}
