{
  "type": "Feature",
  "properties": {
    "iso:country":"GB",
    "wof:name":"BA2 1RQ",
    "wof:placetype":"postalcode"
},
  "geometry": {"coordinates":[-2.40745946741516,51.37723215087642],"type":"Point"}
}