{
  "type": "Feature",
  "properties": {
    "iso:country":"GB",
    "wof:name":"S6 6BL",
    "wof:placetype":"postalcode"
},
  "geometry": {"coordinates":[-1.54650670799523,53.39474807944307],"type":"Point"}
}