{
  "type": "Feature",
  "properties": {
    "iso:country":"GB",
    "wof:name":"NP23 5SQ",
    "wof:placetype":"postalcode"
},
  "geometry": {"coordinates":[-3.22678831772062,51.79663990200413],"type":"Point"}
}