{
  "type": "Feature",
  "properties": {
    "date:inception_lower":"1999-06-01",
    "date:inception_upper":"1999-06-30",
    "iso:country":"GB",
    "wof:name":"NP23 5SQ",
    "wof:placetype":"postalcode"
},
  "geometry": {"coordinates":[-3.226796,51.796645],"type":"Point"}
}