{
  "type": "Feature",
  "properties": {
    "iso:country": "GB",
    "wof:name": "NP23 5SQ",
    "wof:placetype": "postalcode"
  },
  "geometry": {"coordinates":[-3.22668,51.796628],"type":"Point"}
}
