{
  "type": "Feature",
  "properties": {
    "iso:country": "GB",
    "wof:name": "GU15 4HQ",
    "wof:placetype": "postalcode"
  },
  "geometry": {"coordinates":[-0.742367,51.341395],"type":"Point"}
}
