{
  "type": "Feature",
  "properties": {
    "iso:country":"GB",
    "wof:name":"B64 6PA",
    "wof:placetype":"postalcode"
},
  "geometry": {"coordinates":[-2.0608877577053,52.47170264902015],"type":"Point"}
}