{
  "type": "Feature",
  "properties": {
    "iso:country": "GB",
    "wof:name": "DL2 3TH",
    "wof:placetype": "postalcode"
  },
  "geometry": {"coordinates":[-1.695167,54.541219],"type":"Point"}
}
