{
  "type": "Feature",
  "properties": {
    "date:inception_lower": "1993-08-01",
    "date:inception_upper": "1993-08-01",
    "iso:country": "GB",
    "wof:name": "OX12 9RJ",
    "wof:placetype": "postalcode"
  },
  "geometry": {"coordinates":[-1.451664,51.588978],"type":"Point"}
}
