{
  "type": "Feature",
  "properties": {
    "iso:country":"GB",
    "wof:name":"M6 7AG",
    "wof:placetype":"postalcode"
},
  "geometry": {"coordinates":[-2.29535487990952,53.49077236284597],"type":"Point"}
}