{
  "type": "Feature",
  "properties": {
    "iso:country": "GB",
    "wof:name": "M6 7AG",
    "wof:placetype": "postalcode"
  },
  "geometry": {"coordinates":[-2.295355,53.490772],"type":"Point"}
}
