{
  "type": "Feature",
  "properties": {
    "iso:country":"GB",
    "wof:name":"TN3 0SF",
    "wof:placetype":"postalcode"
},
  "geometry": {"coordinates":[0.17363816044627,51.14458682259586],"type":"Point"}
}