{
  "type": "Feature",
  "properties": {
    "date:inception_lower": "1985-04-01",
    "date:inception_upper": "1985-04-01",
    "iso:country": "GB",
    "wof:name": "TN3 0SF",
    "wof:placetype": "postalcode"
  },
  "geometry": {"coordinates":[0.173638,51.144587],"type":"Point"}
}
