{
  "type": "Feature",
  "properties": {
    "date:inception_lower": "1980-01-01",
    "date:inception_upper": "1980-01-01",
    "iso:country": "GB",
    "wof:name": "NE31 2NE",
    "wof:placetype": "postalcode"
  },
  "geometry": {"coordinates":[-1.522507,54.963599],"type":"Point"}
}
