{
  "type": "Feature",
  "properties": {
    "iso:country":"GB",
    "wof:name":"TN4 8GG",
    "wof:placetype":"postalcode"
},
  "geometry": {"coordinates":[0.24813644429139,51.13710755851962],"type":"Point"}
}