{
  "type": "Feature",
  "properties": {
    "date:inception_lower": "1980-01-01",
    "date:inception_upper": "1980-01-01",
    "iso:country": "GB",
    "wof:name": "LL28 4LH",
    "wof:placetype": "postalcode"
  },
  "geometry": {"coordinates":[-3.749148,53.31382],"type":"Point"}
}
