{
  "type": "Feature",
  "properties": {
    "iso:country":"GB",
    "wof:name":"LL28 4LH",
    "wof:placetype":"postalcode"
},
  "geometry": {"coordinates":[-3.74914846100917,53.31382041560706],"type":"Point"}
}