{
  "type": "Feature",
  "properties": {
    "iso:country": "GB",
    "wof:name": "N12 0QX",
    "wof:placetype": "postalcode"
  },
  "geometry": {"coordinates":[-0.167441,51.609981],"type":"Point"}
}
