{
  "type": "Feature",
  "properties": {
    "iso:country":"GB",
    "wof:name":"N12 0QX",
    "wof:placetype":"postalcode"
},
  "geometry": {"coordinates":[-0.16744123611655,51.60998122198536],"type":"Point"}
}