{
  "type": "Feature",
  "properties": {
    "date:inception_lower": "1994-12-01",
    "date:inception_upper": "1994-12-01",
    "iso:country": "GB",
    "wof:name": "LA7 7BY",
    "wof:placetype": "postalcode"
  },
  "geometry": {"coordinates":[-2.773178,54.227495],"type":"Point"}
}
