{
  "type": "Feature",
  "properties": {
    "iso:country":"GB",
    "wof:name":"YO11 1PA",
    "wof:placetype":"postalcode"
},
  "geometry": {"coordinates":[-0.39470889710461,54.28324877335099],"type":"Point"}
}