{
  "type": "Feature",
  "properties": {
    "date:inception_lower": "1987-04-01",
    "date:inception_upper": "1987-04-01",
    "iso:country": "GB",
    "wof:name": "WS12 4ST",
    "wof:placetype": "postalcode"
  },
  "geometry": {"coordinates":[-2.017013,52.721777],"type":"Point"}
}
