{
  "type": "Feature",
  "properties": {
    "iso:country":"GB",
    "wof:name":"WS12 4ST",
    "wof:placetype":"postalcode"
},
  "geometry": {"coordinates":[-2.01701323811449,52.72177689760566],"type":"Point"}
}