{
  "type": "Feature",
  "properties": {
    "iso:country":"GB",
    "wof:name":"E11 3JD",
    "wof:placetype":"postalcode"
},
  "geometry": {"coordinates":[0.00592168770534,51.55374856289481],"type":"Point"}
}