{
  "type": "Feature",
  "properties": {
    "iso:country":"GB",
    "wof:name":"BR1 4SE",
    "wof:placetype":"postalcode"
},
  "geometry": {"coordinates":[0.01418748202223,51.42498401744237],"type":"Point"}
}