{
  "type": "Feature",
  "properties": {
    "iso:country": "GB",
    "wof:name": "BR1 4SE",
    "wof:placetype": "postalcode"
  },
  "geometry": {"coordinates":[0.014188,51.424984],"type":"Point"}
}
