{
  "type": "Feature",
  "properties": {
    "iso:country": "GB",
    "wof:name": "DE15 0DZ",
    "wof:placetype": "postalcode"
  },
  "geometry": {"coordinates":[-1.603348,52.810139],"type":"Point"}
}
