{
  "type": "Feature",
  "properties": {
    "iso:country":"GB",
    "wof:name":"NE5 5PS",
    "wof:placetype":"postalcode"
},
  "geometry": {"coordinates":[-1.69838029586961,54.99953184454068],"type":"Point"}
}