{
  "type": "Feature",
  "properties": {
    "iso:country": "GB",
    "wof:name": "NE5 5PS",
    "wof:placetype": "postalcode"
  },
  "geometry": {"coordinates":[-1.69838,54.999532],"type":"Point"}
}
