{
  "type": "Feature",
  "properties": {
    "iso:country":"GB",
    "wof:name":"PR5 4EB",
    "wof:placetype":"postalcode"
},
  "geometry": {"coordinates":[-2.63855335509154,53.73971275997654],"type":"Point"}
}