{
  "type": "Feature",
  "properties": {
    "iso:country":"GB",
    "wof:name":"HP13 7RG",
    "wof:placetype":"postalcode"
},
  "geometry": {"coordinates":[-0.72856183989777,51.62757774901696],"type":"Point"}
}