{
  "type": "Feature",
  "properties": {
    "date:inception_lower":"1998-06-01",
    "date:inception_upper":"1998-06-30",
    "iso:country":"GB",
    "wof:name":"YO60 6QX",
    "wof:placetype":"postalcode"
},
  "geometry": {"coordinates":[-1.006953,54.089299],"type":"Point"}
}