{
  "type": "Feature",
  "properties": {
    "iso:country": "GB",
    "wof:name": "YO60 6QX",
    "wof:placetype": "postalcode"
  },
  "geometry": {"coordinates":[-1.006953,54.089299],"type":"Point"}
}
