{
  "type": "Feature",
  "properties": {
    "iso:country":"GB",
    "wof:name":"WN2 3DX",
    "wof:placetype":"postalcode"
},
  "geometry": {"coordinates":[-2.58082440499543,53.53201644499762],"type":"Point"}
}