{
  "type": "Feature",
  "properties": {
    "date:inception_lower":"1980-01-01",
    "date:inception_upper":"1980-01-31",
    "iso:country":"GB",
    "wof:name":"HG5 9HN",
    "wof:placetype":"postalcode"
},
  "geometry": {"coordinates":[-1.507405,54.026993],"type":"Point"}
}