{
  "type": "Feature",
  "properties": {
    "iso:country":"GB",
    "wof:name":"HG5 9HN",
    "wof:placetype":"postalcode"
},
  "geometry": {"coordinates":[-1.50740468011846,54.02699303156133],"type":"Point"}
}