{
  "type": "Feature",
  "properties": {
    "iso:country":"GB",
    "wof:name":"LU4 9JH",
    "wof:placetype":"postalcode"
},
  "geometry": {"coordinates":[-0.47045163829381,51.90944035611881],"type":"Point"}
}