{
  "type": "Feature",
  "properties": {
    "iso:country":"GB",
    "wof:name":"ME1 1QL",
    "wof:placetype":"postalcode"
},
  "geometry": {"coordinates":[0.49033977099421,51.37961507014949],"type":"Point"}
}