{
  "type": "Feature",
  "properties": {
    "date:inception_lower":"1980-01-01",
    "date:inception_upper":"1980-01-31",
    "iso:country":"GB",
    "wof:name":"ME1 1QL",
    "wof:placetype":"postalcode"
},
  "geometry": {"coordinates":[0.49034,51.379615],"type":"Point"}
}