{
  "type": "Feature",
  "properties": {
    "iso:country":"GB",
    "wof:name":"KT1 3HT",
    "wof:placetype":"postalcode"
},
  "geometry": {"coordinates":[-0.28697532642305,51.40882910057689],"type":"Point"}
}