{
  "type": "Feature",
  "properties": {
    "iso:country":"GB",
    "wof:name":"SN6 7QH",
    "wof:placetype":"postalcode"
},
  "geometry": {"coordinates":[-1.73159036653791,51.64765740316572],"type":"Point"}
}