{
  "type": "Feature",
  "properties": {
    "iso:country":"GB",
    "wof:name":"EN6 5HE",
    "wof:placetype":"postalcode"
},
  "geometry": {"coordinates":[-0.17135809037193,51.69898490433997],"type":"Point"}
}