{
  "type": "Feature",
  "properties": {
    "iso:country": "GB",
    "wof:name": "EN6 5HE",
    "wof:placetype": "postalcode"
  },
  "geometry": {"coordinates":[-0.171358,51.698985],"type":"Point"}
}
