{
  "type": "Feature",
  "properties": {
    "date:inception_lower": "2017-08-01",
    "date:inception_upper": "2017-08-01",
    "iso:country": "GB",
    "wof:name": "EN11 0FL",
    "wof:placetype": "postalcode"
  },
  "geometry": {"coordinates":[0.000074,51.770043],"type":"Point"}
}
