{
  "type": "Feature",
  "properties": {
    "date:inception_lower": "1980-01-01",
    "date:inception_upper": "1980-01-01",
    "iso:country": "GB",
    "wof:name": "RH9 8EW",
    "wof:placetype": "postalcode"
  },
  "geometry": {"coordinates":[-0.050286,51.221531],"type":"Point"}
}
