{
  "type": "Feature",
  "properties": {
    "iso:country":"GB",
    "wof:name":"RH9 8EW",
    "wof:placetype":"postalcode"
},
  "geometry": {"coordinates":[-0.05028604952553,51.22153147629368],"type":"Point"}
}