{
  "type": "Feature",
  "properties": {
    "iso:country":"GB",
    "wof:name":"EC1V 9DX",
    "wof:placetype":"postalcode"
},
  "geometry": {"coordinates":[-0.09173564182718,51.52789645474033],"type":"Point"}
}