{
  "type": "Feature",
  "properties": {
    "iso:country": "GB",
    "wof:name": "EC1V 9DX",
    "wof:placetype": "postalcode"
  },
  "geometry": {"coordinates":[-0.091736,51.527896],"type":"Point"}
}
