{
  "type": "Feature",
  "properties": {
    "date:inception_lower":"1995-12-01",
    "date:inception_upper":"1995-12-31",
    "iso:country":"GB",
    "wof:name":"M40 8RR",
    "wof:placetype":"postalcode"
},
  "geometry": {"coordinates":[-2.212845,53.495451],"type":"Point"}
}