{
  "type": "Feature",
  "properties": {
    "iso:country":"GB",
    "wof:name":"M40 8RR",
    "wof:placetype":"postalcode"
},
  "geometry": {"coordinates":[-2.21284467156531,53.49545115149213],"type":"Point"}
}