{
  "type": "Feature",
  "properties": {
    "date:inception_lower": "1980-01-01",
    "date:inception_upper": "1980-01-01",
    "iso:country": "GB",
    "wof:name": "B70 9PX",
    "wof:placetype": "postalcode"
  },
  "geometry": {"coordinates":[-2.012792,52.518879],"type":"Point"}
}
