{
  "type": "Feature",
  "properties": {
    "iso:country":"GB",
    "wof:name":"TW18 4RP",
    "wof:placetype":"postalcode"
},
  "geometry": {"coordinates":[-0.51139119907943,51.43738729883141],"type":"Point"}
}