{
  "type": "Feature",
  "properties": {
    "date:inception_lower": "1980-01-01",
    "date:inception_upper": "1980-01-01",
    "iso:country": "GB",
    "wof:name": "TW18 4RP",
    "wof:placetype": "postalcode"
  },
  "geometry": {"coordinates":[-0.511391,51.437387],"type":"Point"}
}
