{
  "type": "Feature",
  "properties": {
    "iso:country":"GB",
    "wof:name":"LN4 4TS",
    "wof:placetype":"postalcode"
},
  "geometry": {"coordinates":[-0.17513744576782,53.10360133854198],"type":"Point"}
}