{
  "type": "Feature",
  "properties": {
    "iso:country":"GB",
    "wof:name":"SA6 7HJ",
    "wof:placetype":"postalcode"
},
  "geometry": {"coordinates":[-3.94060919446635,51.66309866519081],"type":"Point"}
}