{
  "type": "Feature",
  "properties": {
    "iso:country":"GB",
    "wof:name":"OL15 0DY",
    "wof:placetype":"postalcode"
},
  "geometry": {"coordinates":[-2.11032472271694,53.63248197257492],"type":"Point"}
}