{
  "type": "Feature",
  "properties": {
    "date:inception_lower": "2020-12-01",
    "date:inception_upper": "2020-12-01",
    "iso:country": "GB",
    "wof:name": "ME3 8GW",
    "wof:placetype": "postalcode"
  },
  "geometry": {"coordinates":[0.531141,51.416604],"type":"Point"}
}
