{
  "type": "Feature",
  "properties": {
    "iso:country":"GB",
    "wof:name":"BR6 9JY",
    "wof:placetype":"postalcode"
},
  "geometry": {"coordinates":[0.09163722445747,51.36359936517943],"type":"Point"}
}