{
  "type": "Feature",
  "properties": {
    "iso:country":"GB",
    "wof:name":"DN5 0DL",
    "wof:placetype":"postalcode"
},
  "geometry": {"coordinates":[-1.14573968714447,53.54555162229424],"type":"Point"}
}