{
  "type": "Feature",
  "properties": {
    "iso:country": "GB",
    "wof:name": "DN5 0DL",
    "wof:placetype": "postalcode"
  },
  "geometry": {"coordinates":[-1.14574,53.545552],"type":"Point"}
}
