{
  "type": "Feature",
  "properties": {
    "iso:country":"GB",
    "wof:name":"TR11 5UT",
    "wof:placetype":"postalcode"
},
  "geometry": {"coordinates":[-5.07651746337988,50.19025898967946],"type":"Point"}
}