{
  "type": "Feature",
  "properties": {
    "iso:country":"GB",
    "wof:name":"LL68 9BE",
    "wof:placetype":"postalcode"
},
  "geometry": {"coordinates":[-4.35260074684608,53.40474896201805],"type":"Point"}
}