{
  "type": "Feature",
  "properties": {
    "date:inception_lower": "1980-01-01",
    "date:inception_upper": "1980-01-01",
    "iso:country": "GB",
    "wof:name": "LL68 9BE",
    "wof:placetype": "postalcode"
  },
  "geometry": {"coordinates":[-4.352601,53.404749],"type":"Point"}
}
