{
  "type": "Feature",
  "properties": {
    "iso:country":"GB",
    "wof:name":"SW8 3PE",
    "wof:placetype":"postalcode"
},
  "geometry": {"coordinates":[-0.1506074367469,51.46931795134392],"type":"Point"}
}