{
  "type": "Feature",
  "properties": {
    "iso:country":"GB",
    "wof:name":"LA21 8BH",
    "wof:placetype":"postalcode"
},
  "geometry": {"coordinates":[-3.09824465021456,54.33738854234633],"type":"Point"}
}