{
  "type": "Feature",
  "properties": {
    "iso:country": "GB",
    "wof:name": "LA21 8BH",
    "wof:placetype": "postalcode"
  },
  "geometry": {"coordinates":[-3.098199,54.337334],"type":"Point"}
}
