{
  "type": "Feature",
  "properties": {
    "iso:country":"GB",
    "wof:name":"GL52 8DS",
    "wof:placetype":"postalcode"
},
  "geometry": {"coordinates":[-2.06320656722843,51.9429324019434],"type":"Point"}
}