{
  "type": "Feature",
  "properties": {
    "iso:country": "GB",
    "wof:name": "BL9 5HA",
    "wof:placetype": "postalcode"
  },
  "geometry": {"coordinates":[-2.293328,53.610033],"type":"Point"}
}
