{
  "type": "Feature",
  "properties": {
    "iso:country":"GB",
    "wof:name":"BL9 5HA",
    "wof:placetype":"postalcode"
},
  "geometry": {"coordinates":[-2.29333045300637,53.61001698593696],"type":"Point"}
}