{
  "type": "Feature",
  "properties": {
    "iso:country":"GB",
    "wof:name":"SK17 8HZ",
    "wof:placetype":"postalcode"
},
  "geometry": {"coordinates":[-1.78914965343543,53.28088893203825],"type":"Point"}
}