{
  "type": "Feature",
  "properties": {
    "iso:country":"GB",
    "wof:name":"OX5 2HX",
    "wof:placetype":"postalcode"
},
  "geometry": {"coordinates":[-1.27686471617717,51.82218345419663],"type":"Point"}
}