{
  "type": "Feature",
  "properties": {
    "date:inception_lower": "1993-01-01",
    "date:inception_upper": "1993-01-01",
    "iso:country": "GB",
    "wof:name": "CO10 5JL",
    "wof:placetype": "postalcode"
  },
  "geometry": {"coordinates":[0.877798,52.019047],"type":"Point"}
}
