{
  "type": "Feature",
  "properties": {
    "iso:country":"GB",
    "wof:name":"CO10 5JL",
    "wof:placetype":"postalcode"
},
  "geometry": {"coordinates":[0.87749578347697,52.01890613098291],"type":"Point"}
}