{
  "type": "Feature",
  "properties": {
    "iso:country": "GB",
    "wof:name": "OX13 6RX",
    "wof:placetype": "postalcode"
  },
  "geometry": {"coordinates":[-1.319733,51.621826],"type":"Point"}
}
