{
  "type": "Feature",
  "properties": {
    "iso:country":"GB",
    "wof:name":"CT6 7TS",
    "wof:placetype":"postalcode"
},
  "geometry": {"coordinates":[1.11113957946809,51.35751686830012],"type":"Point"}
}