{
  "type": "Feature",
  "properties": {
    "iso:country":"GB",
    "wof:name":"SE18 3SW",
    "wof:placetype":"postalcode"
},
  "geometry": {"coordinates":[0.06810280358943,51.48043908995555],"type":"Point"}
}