{
  "type": "Feature",
  "properties": {
    "iso:country":"GB",
    "wof:name":"EH14 4AT",
    "wof:placetype":"postalcode"
},
  "geometry": {"coordinates":[-3.31426448716191,55.91733424364013],"type":"Point"}
}