{
  "type": "Feature",
  "properties": {
    "date:inception_lower":"2005-07-01",
    "date:inception_upper":"2005-07-31",
    "iso:country":"GB",
    "wof:name":"EH14 4AT",
    "wof:placetype":"postalcode"
},
  "geometry": {"coordinates":[-3.314264,55.917334],"type":"Point"}
}