{
  "type": "Feature",
  "properties": {
    "iso:country": "GB",
    "wof:name": "N7 9HH",
    "wof:placetype": "postalcode"
  },
  "geometry": {"coordinates":[-0.119062,51.550183],"type":"Point"}
}
