{
  "type": "Feature",
  "properties": {
    "iso:country":"GB",
    "wof:name":"N7 9HH",
    "wof:placetype":"postalcode"
},
  "geometry": {"coordinates":[-0.11908828857226,51.55018101303605],"type":"Point"}
}