{
  "type": "Feature",
  "properties": {
    "date:inception_lower":"2005-08-01",
    "date:inception_upper":"2005-08-31",
    "iso:country":"GB",
    "wof:name":"N7 9HH",
    "wof:placetype":"postalcode"
},
  "geometry": {"coordinates":[-0.119062,51.550183],"type":"Point"}
}