{
  "type": "Feature",
  "properties": {
    "iso:country":"GB",
    "wof:name":"NW8 9NN",
    "wof:placetype":"postalcode"
},
  "geometry": {"coordinates":[-0.17534203826535,51.53248202048763],"type":"Point"}
}