{
  "type": "Feature",
  "properties": {
    "date:inception_lower": "2021-09-01",
    "date:inception_upper": "2021-09-01",
    "iso:country": "GB",
    "wof:name": "PA14 6AJ",
    "wof:placetype": "postalcode"
  },
  "geometry": {"coordinates":[-4.656191,55.924296],"type":"Point"}
}
