{
  "type": "Feature",
  "properties": {
    "iso:country":"GB",
    "wof:name":"W11 1BS",
    "wof:placetype":"postalcode"
},
  "geometry": {"coordinates":[-0.20033014733313,51.51891179089874],"type":"Point"}
}