{
  "type": "Feature",
  "properties": {
    "iso:country":"GB",
    "wof:name":"CH1 6AX",
    "wof:placetype":"postalcode"
},
  "geometry": {"coordinates":[-2.95148244999541,53.22271303195283],"type":"Point"}
}