{
  "type": "Feature",
  "properties": {
    "iso:country":"GB",
    "wof:name":"YO60 6SL",
    "wof:placetype":"postalcode"
},
  "geometry": {"coordinates":[-1.01159351770779,54.08895062893497],"type":"Point"}
}