{
  "type": "Feature",
  "properties": {
    "iso:country": "GB",
    "wof:name": "RG26 4QX",
    "wof:placetype": "postalcode"
  },
  "geometry": {"coordinates":[-1.155612,51.359642],"type":"Point"}
}
