{
  "type": "Feature",
  "properties": {
    "iso:country":"GB",
    "wof:name":"RG26 4QX",
    "wof:placetype":"postalcode"
},
  "geometry": {"coordinates":[-1.15561163193374,51.35964182937255],"type":"Point"}
}