{
  "type": "Feature",
  "properties": {
    "iso:country":"GB",
    "wof:name":"DH2 1PE",
    "wof:placetype":"postalcode"
},
  "geometry": {"coordinates":[-1.62352297087973,54.86858146986229],"type":"Point"}
}