{
  "type": "Feature",
  "properties": {
    "date:inception_lower": "1980-01-01",
    "date:inception_upper": "1980-01-01",
    "iso:country": "GB",
    "wof:name": "DH2 1PE",
    "wof:placetype": "postalcode"
  },
  "geometry": {"coordinates":[-1.623523,54.868581],"type":"Point"}
}
