{
  "type": "Feature",
  "properties": {
    "date:inception_lower":"1980-01-01",
    "date:inception_upper":"1980-01-31",
    "iso:country":"GB",
    "wof:name":"LN2 2RA",
    "wof:placetype":"postalcode"
},
  "geometry": {"coordinates":[-0.446754,53.272194],"type":"Point"}
}