{
  "type": "Feature",
  "properties": {
    "iso:country":"GB",
    "wof:name":"ME14 5NQ",
    "wof:placetype":"postalcode"
},
  "geometry": {"coordinates":[0.53780416863492,51.27868570857503],"type":"Point"}
}