{
  "type": "Feature",
  "properties": {
    "iso:country":"GB",
    "wof:name":"BA3 2XB",
    "wof:placetype":"postalcode"
},
  "geometry": {"coordinates":[-2.46051222189606,51.29777302142043],"type":"Point"}
}