{
  "type": "Feature",
  "properties": {
    "iso:country": "GB",
    "wof:name": "BA3 2XB",
    "wof:placetype": "postalcode"
  },
  "geometry": {"coordinates":[-2.460485,51.297832],"type":"Point"}
}
