{
  "type": "Feature",
  "properties": {
    "date:inception_lower":"1980-01-01",
    "date:inception_upper":"1980-01-31",
    "iso:country":"GB",
    "wof:name":"SK2 7JR",
    "wof:placetype":"postalcode"
},
  "geometry": {"coordinates":[-2.138128,53.385128],"type":"Point"}
}