{
  "type": "Feature",
  "properties": {
    "iso:country":"GB",
    "wof:name":"BN17 6BZ",
    "wof:placetype":"postalcode"
},
  "geometry": {"coordinates":[-0.53091650042048,50.81341661765983],"type":"Point"}
}