{
  "type": "Feature",
  "properties": {
    "iso:country": "GB",
    "wof:name": "WF1 3AU",
    "wof:placetype": "postalcode"
  },
  "geometry": {"coordinates":[-1.499063,53.706923],"type":"Point"}
}
