{
  "type": "Feature",
  "properties": {
    "iso:country":"GB",
    "wof:name":"WF1 3AU",
    "wof:placetype":"postalcode"
},
  "geometry": {"coordinates":[-1.49915110574878,53.7068798906691],"type":"Point"}
}