{
  "type": "Feature",
  "properties": {
    "date:inception_lower":"2007-02-01",
    "date:inception_upper":"2007-02-28",
    "iso:country":"GB",
    "wof:name":"WF1 3AU",
    "wof:placetype":"postalcode"
},
  "geometry": {"coordinates":[-1.499063,53.706923],"type":"Point"}
}