{
  "type": "Feature",
  "properties": {
    "iso:country":"GB",
    "wof:name":"SW9 0RF",
    "wof:placetype":"postalcode"
},
  "geometry": {"coordinates":[-0.11523057118985,51.47631736186948],"type":"Point"}
}