{
  "type": "Feature",
  "properties": {
    "iso:country":"GB",
    "wof:name":"NR8 5AQ",
    "wof:placetype":"postalcode"
},
  "geometry": {"coordinates":[1.183236725147,52.66423799561818],"type":"Point"}
}