{
  "type": "Feature",
  "properties": {
    "date:inception_lower":"2007-07-01",
    "date:inception_upper":"2007-07-31",
    "iso:country":"GB",
    "wof:name":"NR8 5AQ",
    "wof:placetype":"postalcode"
},
  "geometry": {"coordinates":[1.183237,52.664238],"type":"Point"}
}