{
  "type": "Feature",
  "properties": {
    "iso:country": "GB",
    "wof:name": "NR8 5AQ",
    "wof:placetype": "postalcode"
  },
  "geometry": {"coordinates":[1.183237,52.664238],"type":"Point"}
}
