{
  "type": "Feature",
  "properties": {
    "iso:country":"GB",
    "wof:name":"PE20 3UA",
    "wof:placetype":"postalcode"
},
  "geometry": {"coordinates":[-0.15711243250522,52.94325833653519],"type":"Point"}
}