{
  "type": "Feature",
  "properties": {
    "iso:country":"GB",
    "wof:name":"NE13 7NG",
    "wof:placetype":"postalcode"
},
  "geometry": {"coordinates":[-1.63369622551798,55.04054712583862],"type":"Point"}
}