{
  "type": "Feature",
  "properties": {
    "date:inception_lower": "1980-01-01",
    "date:inception_upper": "1980-01-01",
    "iso:country": "GB",
    "wof:name": "NE13 7NG",
    "wof:placetype": "postalcode"
  },
  "geometry": {"coordinates":[-1.633696,55.040547],"type":"Point"}
}
