{
  "type": "Feature",
  "properties": {
    "iso:country":"GB",
    "wof:name":"NE9 6YZ",
    "wof:placetype":"postalcode"
},
  "geometry": {"coordinates":[-1.594988203254,54.92506801239863],"type":"Point"}
}