{
  "type": "Feature",
  "properties": {
    "iso:country": "GB",
    "wof:name": "NE9 6YZ",
    "wof:placetype": "postalcode"
  },
  "geometry": {"coordinates":[-1.594988,54.925068],"type":"Point"}
}
