{
  "type": "Feature",
  "properties": {
    "iso:country":"GB",
    "wof:name":"EH14 5NU",
    "wof:placetype":"postalcode"
},
  "geometry": {"coordinates":[-3.31010260483518,55.89593874526394],"type":"Point"}
}