{
  "type": "Feature",
  "properties": {
    "date:inception_lower": "1980-01-01",
    "date:inception_upper": "1980-01-01",
    "iso:country": "GB",
    "wof:name": "ME15 6QH",
    "wof:placetype": "postalcode"
  },
  "geometry": {"coordinates":[0.518661,51.264799],"type":"Point"}
}
