{
  "type": "Feature",
  "properties": {
    "date:inception_lower":"1991-09-01",
    "date:inception_upper":"1991-09-30",
    "iso:country":"GB",
    "wof:name":"NG5 8AZ",
    "wof:placetype":"postalcode"
},
  "geometry": {"coordinates":[-1.107487,53.010999],"type":"Point"}
}