{
  "type": "Feature",
  "properties": {
    "iso:country":"GB",
    "wof:name":"G40 2BA",
    "wof:placetype":"postalcode"
},
  "geometry": {"coordinates":[-4.22285782701137,55.85058277294165],"type":"Point"}
}