{
  "type": "Feature",
  "properties": {
    "iso:country":"GB",
    "wof:name":"GL5 1HU",
    "wof:placetype":"postalcode"
},
  "geometry": {"coordinates":[-2.19406468628968,51.74456574555676],"type":"Point"}
}