{
  "type": "Feature",
  "properties": {
    "iso:country":"GB",
    "wof:name":"BS10 7DS",
    "wof:placetype":"postalcode"
},
  "geometry": {"coordinates":[-2.62196391398977,51.50916835612828],"type":"Point"}
}