{
  "type": "Feature",
  "properties": {
    "iso:country": "GB",
    "wof:name": "BS10 7DS",
    "wof:placetype": "postalcode"
  },
  "geometry": {"coordinates":[-2.621964,51.509168],"type":"Point"}
}
