{
  "type": "Feature",
  "properties": {
    "iso:country": "GB",
    "wof:name": "DY7 5NH",
    "wof:placetype": "postalcode"
  },
  "geometry": {"coordinates":[-2.263569,52.449147],"type":"Point"}
}
