{
  "type": "Feature",
  "properties": {
    "iso:country":"GB",
    "wof:name":"SA4 6SY",
    "wof:placetype":"postalcode"
},
  "geometry": {"coordinates":[-4.04676294732714,51.66190737345376],"type":"Point"}
}