{
  "type": "Feature",
  "properties": {
    "date:inception_lower": "1993-01-01",
    "date:inception_upper": "1993-01-01",
    "iso:country": "GB",
    "wof:name": "SA4 6SY",
    "wof:placetype": "postalcode"
  },
  "geometry": {"coordinates":[-4.046763,51.661907],"type":"Point"}
}
