{
  "type": "Feature",
  "properties": {
    "iso:country":"GB",
    "wof:name":"N22 5LE",
    "wof:placetype":"postalcode"
},
  "geometry": {"coordinates":[-0.10172179638656,51.59902715693796],"type":"Point"}
}