{
  "type": "Feature",
  "properties": {
    "iso:country": "GB",
    "wof:name": "N22 5LE",
    "wof:placetype": "postalcode"
  },
  "geometry": {"coordinates":[-0.101796,51.598974],"type":"Point"}
}
