{
  "type": "Feature",
  "properties": {
    "date:inception_lower": "1980-01-01",
    "date:inception_upper": "1980-01-01",
    "iso:country": "GB",
    "wof:name": "PA17 5AH",
    "wof:placetype": "postalcode"
  },
  "geometry": {"coordinates":[-4.884259,55.870862],"type":"Point"}
}
