{
  "type": "Feature",
  "properties": {
    "iso:country":"GB",
    "wof:name":"PA17 5AH",
    "wof:placetype":"postalcode"
},
  "geometry": {"coordinates":[-4.88425884106807,55.8708624221205],"type":"Point"}
}