{
  "type": "Feature",
  "properties": {
    "iso:country":"GB",
    "wof:name":"ME15 0LF",
    "wof:placetype":"postalcode"
},
  "geometry": {"coordinates":[0.47601060175647,51.24795604290297],"type":"Point"}
}