{
  "type": "Feature",
  "properties": {
    "date:inception_lower": "1980-01-01",
    "date:inception_upper": "1980-01-01",
    "iso:country": "GB",
    "wof:name": "ME15 0LF",
    "wof:placetype": "postalcode"
  },
  "geometry": {"coordinates":[0.476011,51.247956],"type":"Point"}
}
