{
  "type": "Feature",
  "properties": {
    "date:inception_lower":"1980-01-01",
    "date:inception_upper":"1980-01-31",
    "iso:country":"GB",
    "wof:name":"PA4 0SL",
    "wof:placetype":"postalcode"
},
  "geometry": {"coordinates":[-4.392811,55.872559],"type":"Point"}
}