{
  "type": "Feature",
  "properties": {
    "iso:country": "GB",
    "wof:name": "OL11 2HF",
    "wof:placetype": "postalcode"
  },
  "geometry": {"coordinates":[-2.149527,53.600385],"type":"Point"}
}
