{
  "type": "Feature",
  "properties": {
    "iso:country": "GB",
    "wof:name": "HX2 9UX",
    "wof:placetype": "postalcode"
  },
  "geometry": {"coordinates":[-1.886371,53.764973],"type":"Point"}
}
