{
  "type": "Feature",
  "properties": {
    "iso:country":"GB",
    "wof:name":"HX2 9UX",
    "wof:placetype":"postalcode"
},
  "geometry": {"coordinates":[-1.88637089292684,53.76497310488319],"type":"Point"}
}