{
  "type": "Feature",
  "properties": {
    "iso:country":"GB",
    "wof:name":"BS31 1EP",
    "wof:placetype":"postalcode"
},
  "geometry": {"coordinates":[-2.49726159051287,51.41206081588369],"type":"Point"}
}