{
  "type": "Feature",
  "properties": {
    "iso:country":"GB",
    "wof:name":"E14 8LR",
    "wof:placetype":"postalcode"
},
  "geometry": {"coordinates":[-0.02620677218047,51.5013269467925],"type":"Point"}
}