{
  "type": "Feature",
  "properties": {
    "iso:country":"GB",
    "wof:name":"BH5 2ER",
    "wof:placetype":"postalcode"
},
  "geometry": {"coordinates":[-1.81915045752979,50.7238739024014],"type":"Point"}
}