{
  "type": "Feature",
  "properties": {
    "iso:country": "GB",
    "wof:name": "BB2 6AA",
    "wof:placetype": "postalcode"
  },
  "geometry": {"coordinates":[-2.487153,53.751468],"type":"Point"}
}
