{
  "type": "Feature",
  "properties": {
    "iso:country":"GB",
    "wof:name":"G71 8PT",
    "wof:placetype":"postalcode"
},
  "geometry": {"coordinates":[-4.0769142289763,55.81100213411764],"type":"Point"}
}