{
  "type": "Feature",
  "properties": {
    "date:inception_lower": "2022-08-01",
    "date:inception_upper": "2022-08-01",
    "iso:country": "GB",
    "wof:name": "CH7 3FL",
    "wof:placetype": "postalcode"
  },
  "geometry": {"coordinates":[-3.064416,53.169474],"type":"Point"}
}
