{
  "type": "Feature",
  "properties": {
    "iso:country":"GB",
    "wof:name":"PE11 1HU",
    "wof:placetype":"postalcode"
},
  "geometry": {"coordinates":[-0.16901456023596,52.79270581680063],"type":"Point"}
}