{
  "type": "Feature",
  "properties": {
    "iso:country": "GB",
    "wof:name": "BN17 5JB",
    "wof:placetype": "postalcode"
  },
  "geometry": {"coordinates":[-0.538334,50.809535],"type":"Point"}
}
