{
  "type": "Feature",
  "properties": {
    "iso:country": "GB",
    "wof:name": "DY4 8PE",
    "wof:placetype": "postalcode"
  },
  "geometry": {"coordinates":[-2.06882,52.526609],"type":"Point"}
}
