{
  "type": "Feature",
  "properties": {
    "iso:country":"GB",
    "wof:name":"DY4 8PE",
    "wof:placetype":"postalcode"
},
  "geometry": {"coordinates":[-2.06882023338607,52.52660877664064],"type":"Point"}
}