{
  "type": "Feature",
  "properties": {
    "iso:country":"GB",
    "wof:name":"LA1 5UH",
    "wof:placetype":"postalcode"
},
  "geometry": {"coordinates":[-2.81469253033994,54.04224427212532],"type":"Point"}
}