{
  "type": "Feature",
  "properties": {
    "date:inception_lower":"1985-10-01",
    "date:inception_upper":"1985-10-31",
    "iso:country":"GB",
    "wof:name":"LA1 5UH",
    "wof:placetype":"postalcode"
},
  "geometry": {"coordinates":[-2.814692,54.042244],"type":"Point"}
}