{
  "type": "Feature",
  "properties": {
    "iso:country": "GB",
    "wof:name": "LA1 5UH",
    "wof:placetype": "postalcode"
  },
  "geometry": {"coordinates":[-2.814692,54.042244],"type":"Point"}
}
