{
  "type": "Feature",
  "properties": {
    "iso:country":"GB",
    "wof:name":"EX8 2HR",
    "wof:placetype":"postalcode"
},
  "geometry": {"coordinates":[-3.39828263292744,50.61804846818043],"type":"Point"}
}