{
  "type": "Feature",
  "properties": {
    "date:inception_lower": "2017-12-01",
    "date:inception_upper": "2017-12-01",
    "iso:country": "GB",
    "wof:name": "CH42 2ES",
    "wof:placetype": "postalcode"
  },
  "geometry": {"coordinates":[-3.006084,53.37106],"type":"Point"}
}
