{
  "type": "Feature",
  "properties": {
    "iso:country": "GB",
    "wof:name": "CH42 2ES",
    "wof:placetype": "postalcode"
  },
  "geometry": {"coordinates":[-3.006115,53.371105],"type":"Point"}
}
