{
  "type": "Feature",
  "properties": {
    "iso:country": "GB",
    "wof:name": "CT5 1JG",
    "wof:placetype": "postalcode"
  },
  "geometry": {"coordinates":[1.025745,51.358559],"type":"Point"}
}
