{
  "type": "Feature",
  "properties": {
    "iso:country":"GB",
    "wof:name":"TF9 1RT",
    "wof:placetype":"postalcode"
},
  "geometry": {"coordinates":[-2.48239493226219,52.90817376560415],"type":"Point"}
}