{
  "type": "Feature",
  "properties": {
    "date:inception_lower": "2021-04-01",
    "date:inception_upper": "2021-04-01",
    "iso:country": "GB",
    "wof:name": "L11 4WB",
    "wof:placetype": "postalcode"
  },
  "geometry": {"coordinates":[-2.904926,53.429668],"type":"Point"}
}
