{
  "type": "Feature",
  "properties": {
    "date:inception_lower": "2002-11-01",
    "date:inception_upper": "2002-11-01",
    "iso:country": "GB",
    "wof:name": "BA20 2FD",
    "wof:placetype": "postalcode"
  },
  "geometry": {"coordinates":[-2.661447,50.942078],"type":"Point"}
}
