{
  "type": "Feature",
  "properties": {
    "iso:country":"GB",
    "wof:name":"BA20 2FD",
    "wof:placetype":"postalcode"
},
  "geometry": {"coordinates":[-2.66144732670698,50.94207755694737],"type":"Point"}
}