{
  "type": "Feature",
  "properties": {
    "iso:country":"GB",
    "wof:name":"CH2 4PL",
    "wof:placetype":"postalcode"
},
  "geometry": {"coordinates":[-2.82058718282131,53.27194863029545],"type":"Point"}
}