{
  "type": "Feature",
  "properties": {
    "date:inception_lower":"1980-01-01",
    "date:inception_upper":"1980-01-31",
    "iso:country":"GB",
    "wof:name":"CH2 4PL",
    "wof:placetype":"postalcode"
},
  "geometry": {"coordinates":[-2.820587,53.271949],"type":"Point"}
}