{
  "type": "Feature",
  "properties": {
    "iso:country":"GB",
    "wof:name":"M9 4DY",
    "wof:placetype":"postalcode"
},
  "geometry": {"coordinates":[-2.20748656396615,53.51560362012848],"type":"Point"}
}