{
  "type": "Feature",
  "properties": {
    "iso:country":"GB",
    "wof:name":"CV36 4QH",
    "wof:placetype":"postalcode"
},
  "geometry": {"coordinates":[-1.62573073462744,52.06522286076429],"type":"Point"}
}