{
  "type": "Feature",
  "properties": {
    "iso:country": "GB",
    "wof:name": "S35 9WW",
    "wof:placetype": "postalcode"
  },
  "geometry": {"coordinates":[-1.457283,53.435166],"type":"Point"}
}
