{
  "type": "Feature",
  "properties": {
    "date:inception_lower": "1997-06-01",
    "date:inception_upper": "1997-06-01",
    "iso:country": "GB",
    "wof:name": "S35 9WW",
    "wof:placetype": "postalcode"
  },
  "geometry": {"coordinates":[-1.457283,53.435166],"type":"Point"}
}
