{
  "type": "Feature",
  "properties": {
    "date:inception_lower": "1980-01-01",
    "date:inception_upper": "1980-01-01",
    "iso:country": "GB",
    "wof:name": "KA6 6DW",
    "wof:placetype": "postalcode"
  },
  "geometry": {"coordinates":[-4.591678,55.398861],"type":"Point"}
}
