{
  "type": "Feature",
  "properties": {
    "date:inception_lower": "1999-06-01",
    "date:inception_upper": "1999-06-01",
    "iso:country": "GB",
    "wof:name": "CH41 1AT",
    "wof:placetype": "postalcode"
  },
  "geometry": {"coordinates":[-3.016247,53.395802],"type":"Point"}
}
