{
  "type": "Feature",
  "properties": {
    "iso:country": "GB",
    "wof:name": "CH41 1AT",
    "wof:placetype": "postalcode"
  },
  "geometry": {"coordinates":[-3.016247,53.395785],"type":"Point"}
}
