{
  "type": "Feature",
  "properties": {
    "date:inception_lower": "1999-06-01",
    "date:inception_upper": "1999-06-01",
    "iso:country": "GB",
    "wof:name": "CH41 1AT",
    "wof:placetype": "postalcode"
  },
  "geometry": {"coordinates":[-3.014525,53.395484],"type":"Point"}
}
