{
  "type": "Feature",
  "properties": {
    "iso:country":"GB",
    "wof:name":"M35 0BE",
    "wof:placetype":"postalcode"
},
  "geometry": {"coordinates":[-2.16006848797644,53.51043637505122],"type":"Point"}
}