{
  "type": "Feature",
  "properties": {
    "iso:country":"GB",
    "wof:name":"AL10 8NW",
    "wof:placetype":"postalcode"
},
  "geometry": {"coordinates":[-0.22385510584021,51.7563327790855],"type":"Point"}
}