{
  "type": "Feature",
  "properties": {
    "date:inception_lower": "1980-01-01",
    "date:inception_upper": "1980-01-01",
    "iso:country": "GB",
    "wof:name": "AL10 8NW",
    "wof:placetype": "postalcode"
  },
  "geometry": {"coordinates":[-0.223855,51.756333],"type":"Point"}
}
