{
  "type": "Feature",
  "properties": {
    "iso:country":"GB",
    "wof:name":"HU7 4PD",
    "wof:placetype":"postalcode"
},
  "geometry": {"coordinates":[-0.30660665991872,53.78210377137149],"type":"Point"}
}