{
  "type": "Feature",
  "properties": {
    "date:inception_lower": "1981-09-01",
    "date:inception_upper": "1981-09-01",
    "iso:country": "GB",
    "wof:name": "HU7 4PD",
    "wof:placetype": "postalcode"
  },
  "geometry": {"coordinates":[-0.306725,53.781991],"type":"Point"}
}
