{
  "type": "Feature",
  "properties": {
    "iso:country":"GB",
    "wof:name":"L22 0PB",
    "wof:placetype":"postalcode"
},
  "geometry": {"coordinates":[-3.02256315974945,53.47475233383913],"type":"Point"}
}