{
  "type": "Feature",
  "properties": {
    "date:inception_lower":"1980-01-01",
    "date:inception_upper":"1980-01-31",
    "iso:country":"GB",
    "wof:name":"L22 0PB",
    "wof:placetype":"postalcode"
},
  "geometry": {"coordinates":[-3.022563,53.474752],"type":"Point"}
}