{
  "type": "Feature",
  "properties": {
    "iso:country":"GB",
    "wof:name":"BD4 8SL",
    "wof:placetype":"postalcode"
},
  "geometry": {"coordinates":[-1.73888409696168,53.78782414964633],"type":"Point"}
}