{
  "type": "Feature",
  "properties": {
    "date:inception_lower":"1997-12-01",
    "date:inception_upper":"1997-12-31",
    "iso:country":"GB",
    "wof:name":"BD4 8SL",
    "wof:placetype":"postalcode"
},
  "geometry": {"coordinates":[-1.737751,53.787513],"type":"Point"}
}