{
  "type": "Feature",
  "properties": {
    "iso:country": "GB",
    "wof:name": "ST4 6RL",
    "wof:placetype": "postalcode"
  },
  "geometry": {"coordinates":[-2.203735,53.002746],"type":"Point"}
}
