{
  "type": "Feature",
  "properties": {
    "date:inception_lower":"1980-01-01",
    "date:inception_upper":"1980-01-31",
    "iso:country":"GB",
    "wof:name":"ST4 6RL",
    "wof:placetype":"postalcode"
},
  "geometry": {"coordinates":[-2.203735,53.002746],"type":"Point"}
}