{
  "type": "Feature",
  "properties": {
    "iso:country":"GB",
    "wof:name":"ST4 6RL",
    "wof:placetype":"postalcode"
},
  "geometry": {"coordinates":[-2.20373468728343,53.00274586214304],"type":"Point"}
}