{
  "type": "Feature",
  "properties": {
    "iso:country":"GB",
    "wof:name":"S61 2QL",
    "wof:placetype":"postalcode"
},
  "geometry": {"coordinates":[-1.43333293722321,53.46020554767824],"type":"Point"}
}