{
  "type": "Feature",
  "properties": {
    "iso:country": "GB",
    "wof:name": "NP11 5FR",
    "wof:placetype": "postalcode"
  },
  "geometry": {"coordinates":[-3.140817,51.664882],"type":"Point"}
}
