{
  "type": "Feature",
  "properties": {
    "iso:country": "GB",
    "wof:name": "DD11 3FF",
    "wof:placetype": "postalcode"
  },
  "geometry": {"coordinates":[-2.615819,56.564858],"type":"Point"}
}
