{
  "type": "Feature",
  "properties": {
    "iso:country":"GB",
    "wof:name":"SA3 4DB",
    "wof:placetype":"postalcode"
},
  "geometry": {"coordinates":[-3.99929004523206,51.57346559810897],"type":"Point"}
}