{
  "type": "Feature",
  "properties": {
    "date:inception_lower":"1995-07-01",
    "date:inception_upper":"1995-07-31",
    "iso:country":"GB",
    "wof:name":"CT18 7FB",
    "wof:placetype":"postalcode"
},
  "geometry": {"coordinates":[1.162036,51.115434],"type":"Point"}
}