{
  "type": "Feature",
  "properties": {
    "iso:country":"GB",
    "wof:name":"NE34 0LZ",
    "wof:placetype":"postalcode"
},
  "geometry": {"coordinates":[-1.4387298498062,54.96925336908149],"type":"Point"}
}