{
  "type": "Feature",
  "properties": {
    "iso:country": "GB",
    "wof:name": "IP16 4LL",
    "wof:placetype": "postalcode"
  },
  "geometry": {"coordinates":[1.587168,52.207704],"type":"Point"}
}
