{
  "type": "Feature",
  "properties": {
    "date:inception_lower":"1990-08-01",
    "date:inception_upper":"1990-08-31",
    "iso:country":"GB",
    "wof:name":"AB34 5NE",
    "wof:placetype":"postalcode"
},
  "geometry": {"coordinates":[-2.915967,57.108316],"type":"Point"}
}