{
  "type": "Feature",
  "properties": {
    "iso:country":"GB",
    "wof:name":"AB34 5NE",
    "wof:placetype":"postalcode"
},
  "geometry": {"coordinates":[-2.91596659011319,57.10831597348192],"type":"Point"}
}