{
  "type": "Feature",
  "properties": {
    "iso:country":"GB",
    "wof:name":"SO45 5BL",
    "wof:placetype":"postalcode"
},
  "geometry": {"coordinates":[-1.40951723445945,50.85993671894146],"type":"Point"}
}