{
  "type": "Feature",
  "properties": {
    "iso:country": "GB",
    "wof:name": "HA8 0PY",
    "wof:placetype": "postalcode"
  },
  "geometry": {"coordinates":[-0.253116,51.60957],"type":"Point"}
}
