{
  "type": "Feature",
  "properties": {
    "iso:country":"GB",
    "wof:name":"HA8 0PY",
    "wof:placetype":"postalcode"
},
  "geometry": {"coordinates":[-0.25311575323311,51.60956993195458],"type":"Point"}
}