{
  "type": "Feature",
  "properties": {
    "iso:country": "GB",
    "wof:name": "CO15 6HQ",
    "wof:placetype": "postalcode"
  },
  "geometry": {"coordinates":[1.168069,51.796404],"type":"Point"}
}
