{
  "type": "Feature",
  "properties": {
    "iso:country":"GB",
    "wof:name":"CO15 6HQ",
    "wof:placetype":"postalcode"
},
  "geometry": {"coordinates":[1.16806881976888,51.7964042113102],"type":"Point"}
}