{
  "type": "Feature",
  "properties": {
    "iso:country": "GB",
    "wof:name": "WS2 8SB",
    "wof:placetype": "postalcode"
  },
  "geometry": {"coordinates":[-2.003337,52.589953],"type":"Point"}
}
