{
  "type": "Feature",
  "properties": {
    "iso:country":"GB",
    "wof:name":"WS2 8SB",
    "wof:placetype":"postalcode"
},
  "geometry": {"coordinates":[-2.00333701613671,52.58995330151412],"type":"Point"}
}