{
  "type": "Feature",
  "properties": {
    "iso:country":"GB",
    "wof:name":"CT9 5DZ",
    "wof:placetype":"postalcode"
},
  "geometry": {"coordinates":[1.35716898537972,51.38505293262889],"type":"Point"}
}