{
  "type": "Feature",
  "properties": {
    "iso:country":"GB",
    "wof:name":"IP28 6AG",
    "wof:placetype":"postalcode"
},
  "geometry": {"coordinates":[0.53351073246527,52.3338350808604],"type":"Point"}
}