{
  "type": "Feature",
  "properties": {
    "date:inception_lower": "1990-02-01",
    "date:inception_upper": "1990-02-01",
    "iso:country": "GB",
    "wof:name": "HP1 1XP",
    "wof:placetype": "postalcode"
  },
  "geometry": {"coordinates":[-0.47647,51.756758],"type":"Point"}
}
