{
  "type": "Feature",
  "properties": {
    "date:inception_lower": "1980-01-01",
    "date:inception_upper": "1980-01-01",
    "iso:country": "GB",
    "wof:name": "NG22 0TL",
    "wof:placetype": "postalcode"
  },
  "geometry": {"coordinates":[-0.832279,53.239475],"type":"Point"}
}
