{
  "type": "Feature",
  "properties": {
    "iso:country":"GB",
    "wof:name":"NG22 0TL",
    "wof:placetype":"postalcode"
},
  "geometry": {"coordinates":[-0.8322792054309,53.23947499504089],"type":"Point"}
}