{
  "type": "Feature",
  "properties": {
    "date:inception_lower": "2005-11-01",
    "date:inception_upper": "2005-11-01",
    "iso:country": "GB",
    "wof:name": "LE7 9RX",
    "wof:placetype": "postalcode"
  },
  "geometry": {"coordinates":[-1.031804,52.629537],"type":"Point"}
}
