{
  "type": "Feature",
  "properties": {
    "iso:country":"GB",
    "wof:name":"LE7 9RX",
    "wof:placetype":"postalcode"
},
  "geometry": {"coordinates":[-1.03180376835068,52.62953701562546],"type":"Point"}
}