{
  "type": "Feature",
  "properties": {
    "iso:country": "GB",
    "wof:name": "RG31 6LP",
    "wof:placetype": "postalcode"
  },
  "geometry": {"coordinates":[-1.043034,51.465969],"type":"Point"}
}
