{
  "type": "Feature",
  "properties": {
    "date:inception_lower": "1980-01-01",
    "date:inception_upper": "1980-01-01",
    "iso:country": "GB",
    "wof:name": "M2 3JL",
    "wof:placetype": "postalcode"
  },
  "geometry": {"coordinates":[-2.24157,53.478777],"type":"Point"}
}
