{
  "type": "Feature",
  "properties": {
    "iso:country": "GB",
    "wof:name": "M2 3JL",
    "wof:placetype": "postalcode"
  },
  "geometry": {"coordinates":[-2.24157,53.478777],"type":"Point"}
}
