{
  "type": "Feature",
  "properties": {
    "date:inception_lower": "1991-09-01",
    "date:inception_upper": "1991-09-01",
    "iso:country": "GB",
    "wof:name": "NR10 5JN",
    "wof:placetype": "postalcode"
  },
  "geometry": {"coordinates":[1.340696,52.759856],"type":"Point"}
}
