{
  "type": "Feature",
  "properties": {
    "iso:country": "GB",
    "wof:name": "NR10 5JN",
    "wof:placetype": "postalcode"
  },
  "geometry": {"coordinates":[1.340696,52.759856],"type":"Point"}
}
