{
  "type": "Feature",
  "properties": {
    "iso:country":"GB",
    "wof:name":"NR10 5JN",
    "wof:placetype":"postalcode"
},
  "geometry": {"coordinates":[1.34069611265967,52.75985570840204],"type":"Point"}
}