{
  "type": "Feature",
  "properties": {
    "iso:country":"GB",
    "wof:name":"WA1 4DG",
    "wof:placetype":"postalcode"
},
  "geometry": {"coordinates":[-2.52358199812585,53.39959169364845],"type":"Point"}
}