{
  "type": "Feature",
  "properties": {
    "date:inception_lower": "1980-01-01",
    "date:inception_upper": "1980-01-01",
    "iso:country": "GB",
    "wof:name": "WF2 8SF",
    "wof:placetype": "postalcode"
  },
  "geometry": {"coordinates":[-1.530661,53.670129],"type":"Point"}
}
