{
  "type": "Feature",
  "properties": {
    "iso:country":"GB",
    "wof:name":"WF2 8SF",
    "wof:placetype":"postalcode"
},
  "geometry": {"coordinates":[-1.53066090269,53.67012877464092],"type":"Point"}
}