{
  "type": "Feature",
  "properties": {
    "iso:country":"GB",
    "wof:name":"SP2 0HU",
    "wof:placetype":"postalcode"
},
  "geometry": {"coordinates":[-1.86376321684643,51.07985342335058],"type":"Point"}
}