{
  "type": "Feature",
  "properties": {
    "iso:country":"GB",
    "wof:name":"RG30 6AX",
    "wof:placetype":"postalcode"
},
  "geometry": {"coordinates":[-1.01463612097481,51.46570665352056],"type":"Point"}
}