{
  "type": "Feature",
  "properties": {
    "date:inception_lower": "1980-01-01",
    "date:inception_upper": "1980-01-01",
    "iso:country": "GB",
    "wof:name": "HD7 5LD",
    "wof:placetype": "postalcode"
  },
  "geometry": {"coordinates":[-1.877858,53.61898],"type":"Point"}
}
