{
  "type": "Feature",
  "properties": {
    "iso:country":"GB",
    "wof:name":"HD7 5LD",
    "wof:placetype":"postalcode"
},
  "geometry": {"coordinates":[-1.87785821672409,53.61897968962257],"type":"Point"}
}