{
  "type": "Feature",
  "properties": {
    "iso:country":"GB",
    "wof:name":"SK3 8RF",
    "wof:placetype":"postalcode"
},
  "geometry": {"coordinates":[-2.16341683941881,53.38924000008804],"type":"Point"}
}