{
  "type": "Feature",
  "properties": {
    "date:inception_lower": "1980-01-01",
    "date:inception_upper": "1980-01-01",
    "iso:country": "GB",
    "wof:name": "SK3 8RF",
    "wof:placetype": "postalcode"
  },
  "geometry": {"coordinates":[-2.163417,53.38924],"type":"Point"}
}
