{
  "type": "Feature",
  "properties": {
    "iso:country":"GB",
    "wof:name":"EH19 3AX",
    "wof:placetype":"postalcode"
},
  "geometry": {"coordinates":[-3.10227207419676,55.87391198606701],"type":"Point"}
}