{
  "type": "Feature",
  "properties": {
    "iso:country":"GB",
    "wof:name":"W10 5HJ",
    "wof:placetype":"postalcode"
},
  "geometry": {"coordinates":[-0.22599151217026,51.52434743494733],"type":"Point"}
}