{
  "type": "Feature",
  "properties": {
    "date:inception_lower":"1999-06-01",
    "date:inception_upper":"1999-06-30",
    "iso:country":"GB",
    "wof:name":"NP13 2DE",
    "wof:placetype":"postalcode"
},
  "geometry": {"coordinates":[-3.150256,51.703363],"type":"Point"}
}