{
  "type": "Feature",
  "properties": {
    "iso:country":"GB",
    "wof:name":"RM2 6NA",
    "wof:placetype":"postalcode"
},
  "geometry": {"coordinates":[0.20358951640274,51.58741457663615],"type":"Point"}
}