{
  "type": "Feature",
  "properties": {
    "date:inception_lower": "1980-01-01",
    "date:inception_upper": "1980-01-01",
    "iso:country": "GB",
    "wof:name": "DE15 9RT",
    "wof:placetype": "postalcode"
  },
  "geometry": {"coordinates":[-1.616372,52.790082],"type":"Point"}
}
