{
  "type": "Feature",
  "properties": {
    "date:inception_lower": "1991-09-01",
    "date:inception_upper": "1991-09-01",
    "iso:country": "GB",
    "wof:name": "KT8 2PU",
    "wof:placetype": "postalcode"
  },
  "geometry": {"coordinates":[-0.367827,51.400361],"type":"Point"}
}
