{
  "type": "Feature",
  "properties": {
    "iso:country":"GB",
    "wof:name":"KT8 2PU",
    "wof:placetype":"postalcode"
},
  "geometry": {"coordinates":[-0.36782708603891,51.40036108386985],"type":"Point"}
}