{
  "type": "Feature",
  "properties": {
    "date:inception_lower": "1980-01-01",
    "date:inception_upper": "1980-01-01",
    "iso:country": "GB",
    "wof:name": "ME9 0RA",
    "wof:placetype": "postalcode"
  },
  "geometry": {"coordinates":[0.771295,51.302999],"type":"Point"}
}
