{
  "type": "Feature",
  "properties": {
    "iso:country":"GB",
    "wof:name":"HP12 3AZ",
    "wof:placetype":"postalcode"
},
  "geometry": {"coordinates":[-0.76832017096084,51.63453848085825],"type":"Point"}
}