{
  "type": "Feature",
  "properties": {
    "iso:country":"GB",
    "wof:name":"EN5 4NP",
    "wof:placetype":"postalcode"
},
  "geometry": {"coordinates":[-0.21320361630789,51.65720366595441],"type":"Point"}
}