{
  "type": "Feature",
  "properties": {
    "date:inception_lower": "1980-01-01",
    "date:inception_upper": "1980-01-01",
    "iso:country": "GB",
    "wof:name": "EN5 4NP",
    "wof:placetype": "postalcode"
  },
  "geometry": {"coordinates":[-0.213377,51.657318],"type":"Point"}
}
