{
  "type": "Feature",
  "properties": {
    "iso:country": "GB",
    "wof:name": "TR2 5LN",
    "wof:placetype": "postalcode"
  },
  "geometry": {"coordinates":[-4.9547,50.210012],"type":"Point"}
}
