{
  "type": "Feature",
  "properties": {
    "iso:country":"GB",
    "wof:name":"TR2 5LN",
    "wof:placetype":"postalcode"
},
  "geometry": {"coordinates":[-4.95469959153154,50.21001210406804],"type":"Point"}
}