{
  "type": "Feature",
  "properties": {
    "iso:country":"GB",
    "wof:name":"WA7 4SD",
    "wof:placetype":"postalcode"
},
  "geometry": {"coordinates":[-2.73711936560576,53.33351973291086],"type":"Point"}
}