{
  "type": "Feature",
  "properties": {
    "iso:country": "GB",
    "wof:name": "WA7 4SD",
    "wof:placetype": "postalcode"
  },
  "geometry": {"coordinates":[-2.738094,53.333421],"type":"Point"}
}
