{
  "type": "Feature",
  "properties": {
    "iso:country": "GB",
    "wof:name": "BN1 1RB",
    "wof:placetype": "postalcode"
  },
  "geometry": {"coordinates":[-0.141242,50.824617],"type":"Point"}
}
