{
  "type": "Feature",
  "properties": {
    "iso:country":"GB",
    "wof:name":"BN1 1RB",
    "wof:placetype":"postalcode"
},
  "geometry": {"coordinates":[-0.14122857988088,50.8245864399363],"type":"Point"}
}