{
  "type": "Feature",
  "properties": {
    "iso:country":"GB",
    "wof:name":"SR3 3DD",
    "wof:placetype":"postalcode"
},
  "geometry": {"coordinates":[-1.42490873919646,54.87600861658257],"type":"Point"}
}