{
  "type": "Feature",
  "properties": {
    "iso:country":"GB",
    "wof:name":"S17 4HG",
    "wof:placetype":"postalcode"
},
  "geometry": {"coordinates":[-1.53039744868669,53.31574698510386],"type":"Point"}
}