{
  "type": "Feature",
  "properties": {
    "iso:country":"GB",
    "wof:name":"WV3 0EX",
    "wof:placetype":"postalcode"
},
  "geometry": {"coordinates":[-2.1417579162934,52.57863094989371],"type":"Point"}
}