{
  "type": "Feature",
  "properties": {
    "iso:country": "GB",
    "wof:name": "DY1 4RF",
    "wof:placetype": "postalcode"
  },
  "geometry": {"coordinates":[-2.064422,52.512866],"type":"Point"}
}
