{
  "type": "Feature",
  "properties": {
    "iso:country":"GB",
    "wof:name":"DY1 4RF",
    "wof:placetype":"postalcode"
},
  "geometry": {"coordinates":[-2.06442236014315,52.51286570684411],"type":"Point"}
}