{
  "type": "Feature",
  "properties": {
    "date:inception_lower":"1980-01-01",
    "date:inception_upper":"1980-01-31",
    "iso:country":"GB",
    "wof:name":"DY1 4RF",
    "wof:placetype":"postalcode"
},
  "geometry": {"coordinates":[-2.064422,52.512866],"type":"Point"}
}