{
  "type": "Feature",
  "properties": {
    "iso:country": "GB",
    "wof:name": "DY10 2EZ",
    "wof:placetype": "postalcode"
  },
  "geometry": {"coordinates":[-2.242829,52.391511],"type":"Point"}
}
