{
  "type": "Feature",
  "properties": {
    "iso:country": "GB",
    "wof:name": "L36 2PB",
    "wof:placetype": "postalcode"
  },
  "geometry": {"coordinates":[-2.867409,53.420274],"type":"Point"}
}
