{
  "type": "Feature",
  "properties": {
    "iso:country":"GB",
    "wof:name":"L36 2PB",
    "wof:placetype":"postalcode"
},
  "geometry": {"coordinates":[-2.86743937014727,53.42025792125349],"type":"Point"}
}