{
  "type": "Feature",
  "properties": {
    "date:inception_lower": "1980-01-01",
    "date:inception_upper": "1980-01-01",
    "iso:country": "GB",
    "wof:name": "L36 2PB",
    "wof:placetype": "postalcode"
  },
  "geometry": {"coordinates":[-2.867439,53.420274],"type":"Point"}
}
