{
  "type": "Feature",
  "properties": {
    "iso:country":"GB",
    "wof:name":"FY7 7EQ",
    "wof:placetype":"postalcode"
},
  "geometry": {"coordinates":[-3.03067421965615,53.91627180976703],"type":"Point"}
}