{
  "type": "Feature",
  "properties": {
    "iso:country": "GB",
    "wof:name": "AB34 5BZ",
    "wof:placetype": "postalcode"
  },
  "geometry": {"coordinates":[-2.679769,57.085857],"type":"Point"}
}
