{
  "type": "Feature",
  "properties": {
    "date:inception_lower": "2017-07-01",
    "date:inception_upper": "2017-07-01",
    "iso:country": "GB",
    "wof:name": "AB34 5BZ",
    "wof:placetype": "postalcode"
  },
  "geometry": {"coordinates":[-2.679767,57.085776],"type":"Point"}
}
