{
  "type": "Feature",
  "properties": {
    "date:inception_lower": "2000-06-01",
    "date:inception_upper": "2000-06-01",
    "iso:country": "GB",
    "wof:name": "PE28 4AX",
    "wof:placetype": "postalcode"
  },
  "geometry": {"coordinates":[-0.207676,52.356776],"type":"Point"}
}
