{
  "type": "Feature",
  "properties": {
    "iso:country":"GB",
    "wof:name":"MK42 9QB",
    "wof:placetype":"postalcode"
},
  "geometry": {"coordinates":[-0.46795506131877,52.12646131328],"type":"Point"}
}