{
  "type": "Feature",
  "properties": {
    "iso:country":"GB",
    "wof:name":"WC1X 9QG",
    "wof:placetype":"postalcode"
},
  "geometry": {"coordinates":[-0.11535187166268,51.5282063292888],"type":"Point"}
}