{
  "type": "Feature",
  "properties": {
    "iso:country": "GB",
    "wof:name": "BD23 4JA",
    "wof:placetype": "postalcode"
  },
  "geometry": {"coordinates":[-2.220326,54.005316],"type":"Point"}
}
