{
  "type": "Feature",
  "properties": {
    "iso:country":"GB",
    "wof:name":"DN18 5AB",
    "wof:placetype":"postalcode"
},
  "geometry": {"coordinates":[-0.44829841446384,53.68602270357673],"type":"Point"}
}