{
  "type": "Feature",
  "properties": {
    "iso:country":"GB",
    "wof:name":"PO9 2QJ",
    "wof:placetype":"postalcode"
},
  "geometry": {"coordinates":[-0.96642513979264,50.85567677279566],"type":"Point"}
}