{
  "type": "Feature",
  "properties": {
    "date:inception_lower": "1980-01-01",
    "date:inception_upper": "1980-01-01",
    "iso:country": "GB",
    "wof:name": "NE11 0RS",
    "wof:placetype": "postalcode"
  },
  "geometry": {"coordinates":[-1.618147,54.926329],"type":"Point"}
}
