{
  "type": "Feature",
  "properties": {
    "iso:country":"GB",
    "wof:name":"GL7 2HD",
    "wof:placetype":"postalcode"
},
  "geometry": {"coordinates":[-1.9673200937716,51.72502241545897],"type":"Point"}
}