{
  "type": "Feature",
  "properties": {
    "iso:country": "GB",
    "wof:name": "BD11 2DZ",
    "wof:placetype": "postalcode"
  },
  "geometry": {"coordinates":[-1.695241,53.750834],"type":"Point"}
}
