{
  "type": "Feature",
  "properties": {
    "iso:country":"GB",
    "wof:name":"NR21 0HL",
    "wof:placetype":"postalcode"
},
  "geometry": {"coordinates":[0.88977871855068,52.87463468349932],"type":"Point"}
}