{
  "type": "Feature",
  "properties": {
    "iso:country": "GB",
    "wof:name": "KT20 6BS",
    "wof:placetype": "postalcode"
  },
  "geometry": {"coordinates":[-0.218213,51.304487],"type":"Point"}
}
