{
  "type": "Feature",
  "properties": {
    "iso:country":"GB",
    "wof:name":"KT20 6BS",
    "wof:placetype":"postalcode"
},
  "geometry": {"coordinates":[-0.21821329988618,51.30448741088055],"type":"Point"}
}