{
  "type": "Feature",
  "properties": {
    "iso:country":"GB",
    "wof:name":"N1 2HS",
    "wof:placetype":"postalcode"
},
  "geometry": {"coordinates":[-0.09689718742802,51.54137018405944],"type":"Point"}
}