{
  "type": "Feature",
  "properties": {
    "date:inception_lower": "1980-01-01",
    "date:inception_upper": "1980-01-01",
    "iso:country": "GB",
    "wof:name": "N1 2HS",
    "wof:placetype": "postalcode"
  },
  "geometry": {"coordinates":[-0.096897,51.54137],"type":"Point"}
}
