{
  "type": "Feature",
  "properties": {
    "date:inception_lower":"1980-01-01",
    "date:inception_upper":"1980-01-31",
    "iso:country":"GB",
    "wof:name":"OX7 5TS",
    "wof:placetype":"postalcode"
},
  "geometry": {"coordinates":[-1.463946,51.955037],"type":"Point"}
}