{
  "type": "Feature",
  "properties": {
    "iso:country":"GB",
    "wof:name":"OX7 5TS",
    "wof:placetype":"postalcode"
},
  "geometry": {"coordinates":[-1.46394637922458,51.95503689081209],"type":"Point"}
}