{
  "type": "Feature",
  "properties": {
    "date:inception_lower": "2023-05-01",
    "date:inception_upper": "2023-05-01",
    "iso:country": "GB",
    "wof:name": "LE5 1GY",
    "wof:placetype": "postalcode"
  },
  "geometry": {"coordinates":[-1.071559,52.650991],"type":"Point"}
}
