{
  "type": "Feature",
  "properties": {
    "date:inception_lower": "1981-12-01",
    "date:inception_upper": "1981-12-01",
    "iso:country": "GB",
    "wof:name": "PA8 7AN",
    "wof:placetype": "postalcode"
  },
  "geometry": {"coordinates":[-4.449563,55.892888],"type":"Point"}
}
