{
  "type": "Feature",
  "properties": {
    "iso:country":"GB",
    "wof:name":"PA8 7AN",
    "wof:placetype":"postalcode"
},
  "geometry": {"coordinates":[-4.44956348378669,55.8928876126894],"type":"Point"}
}