{
  "type": "Feature",
  "properties": {
    "date:inception_lower": "1980-01-01",
    "date:inception_upper": "1980-01-01",
    "iso:country": "GB",
    "wof:name": "TR2 5EJ",
    "wof:placetype": "postalcode"
  },
  "geometry": {"coordinates":[-4.973958,50.197142],"type":"Point"}
}
