{
  "type": "Feature",
  "properties": {
    "iso:country":"GB",
    "wof:name":"CR7 6HZ",
    "wof:placetype":"postalcode"
},
  "geometry": {"coordinates":[-0.11779788234837,51.39711547427698],"type":"Point"}
}