{
  "type": "Feature",
  "properties": {
    "date:inception_lower":"1990-07-01",
    "date:inception_upper":"1990-07-31",
    "iso:country":"GB",
    "wof:name":"CR7 6HZ",
    "wof:placetype":"postalcode"
},
  "geometry": {"coordinates":[-0.117798,51.397115],"type":"Point"}
}