{
  "type": "Feature",
  "properties": {
    "iso:country":"GB",
    "wof:name":"E17 6AH",
    "wof:placetype":"postalcode"
},
  "geometry": {"coordinates":[-0.03863477732057,51.59470757434886],"type":"Point"}
}