{
  "type": "Feature",
  "properties": {
    "iso:country":"GB",
    "wof:name":"BB1 6JU",
    "wof:placetype":"postalcode"
},
  "geometry": {"coordinates":[-2.47037532494415,53.76030995064426],"type":"Point"}
}