{
  "type": "Feature",
  "properties": {
    "date:inception_lower": "1999-06-01",
    "date:inception_upper": "1999-06-01",
    "iso:country": "GB",
    "wof:name": "BB1 6JU",
    "wof:placetype": "postalcode"
  },
  "geometry": {"coordinates":[-2.470375,53.76031],"type":"Point"}
}
