{
  "type": "Feature",
  "properties": {
    "iso:country": "GB",
    "wof:name": "TN29 9RP",
    "wof:placetype": "postalcode"
  },
  "geometry": {"coordinates":[0.838971,51.012333],"type":"Point"}
}
