{
  "type": "Feature",
  "properties": {
    "iso:country":"GB",
    "wof:name":"RG7 2AA",
    "wof:placetype":"postalcode"
},
  "geometry": {"coordinates":[-1.02149693625305,51.37706823725059],"type":"Point"}
}