{
  "type": "Feature",
  "properties": {
    "date:inception_lower": "1980-01-01",
    "date:inception_upper": "1980-01-01",
    "iso:country": "GB",
    "wof:name": "RG7 2AA",
    "wof:placetype": "postalcode"
  },
  "geometry": {"coordinates":[-1.021497,51.377068],"type":"Point"}
}
