{
  "type": "Feature",
  "properties": {
    "iso:country":"GB",
    "wof:name":"CV7 7PG",
    "wof:placetype":"postalcode"
},
  "geometry": {"coordinates":[-1.66336812763886,52.38850462298996],"type":"Point"}
}