{
  "type": "Feature",
  "properties": {
    "iso:country":"GB",
    "wof:name":"WV4 4NE",
    "wof:placetype":"postalcode"
},
  "geometry": {"coordinates":[-2.17450451699473,52.56391575043759],"type":"Point"}
}