{
  "type": "Feature",
  "properties": {
    "iso:country": "GB",
    "wof:name": "LA4 5HJ",
    "wof:placetype": "postalcode"
  },
  "geometry": {"coordinates":[-2.863413,54.07429],"type":"Point"}
}
