{
  "type": "Feature",
  "properties": {
    "iso:country":"GB",
    "wof:name":"LA4 5HJ",
    "wof:placetype":"postalcode"
},
  "geometry": {"coordinates":[-2.86392185471214,54.07439177115573],"type":"Point"}
}