{
  "type": "Feature",
  "properties": {
    "date:inception_lower":"1980-01-01",
    "date:inception_upper":"1980-01-31",
    "iso:country":"GB",
    "wof:name":"WA7 5BD",
    "wof:placetype":"postalcode"
},
  "geometry": {"coordinates":[-2.729484,53.338421],"type":"Point"}
}