{
  "type": "Feature",
  "properties": {
    "iso:country":"GB",
    "wof:name":"HP23 5EQ",
    "wof:placetype":"postalcode"
},
  "geometry": {"coordinates":[-0.65829178696764,51.80508332203653],"type":"Point"}
}