{
  "type": "Feature",
  "properties": {
    "iso:country": "GB",
    "wof:name": "SS16 4LA",
    "wof:placetype": "postalcode"
  },
  "geometry": {"coordinates":[0.489002,51.562353],"type":"Point"}
}
