{
  "type": "Feature",
  "properties": {
    "iso:country":"GB",
    "wof:name":"B47 5DQ",
    "wof:placetype":"postalcode"
},
  "geometry": {"coordinates":[-1.88870427341468,52.39087289194602],"type":"Point"}
}