{
  "type": "Feature",
  "properties": {
    "iso:country":"GB",
    "wof:name":"ZE2 9NS",
    "wof:placetype":"postalcode"
},
  "geometry": {"coordinates":[-1.48564193798008,60.24182029736413],"type":"Point"}
}