{
  "type": "Feature",
  "properties": {
    "iso:country":"GB",
    "wof:name":"TN2 3UU",
    "wof:placetype":"postalcode"
},
  "geometry": {"coordinates":[0.2832649549115,51.1360490737398],"type":"Point"}
}