{
  "type": "Feature",
  "properties": {
    "iso:country":"GB",
    "wof:name":"S64 8EP",
    "wof:placetype":"postalcode"
},
  "geometry": {"coordinates":[-1.31871504895523,53.47724295591796],"type":"Point"}
}