{
  "type": "Feature",
  "properties": {
    "iso:country": "GB",
    "wof:name": "S64 8EP",
    "wof:placetype": "postalcode"
  },
  "geometry": {"coordinates":[-1.318715,53.477243],"type":"Point"}
}
