{
  "type": "Feature",
  "properties": {
    "iso:country": "GB",
    "wof:name": "DG1 4YH",
    "wof:placetype": "postalcode"
  },
  "geometry": {"coordinates":[-3.577833,55.059815],"type":"Point"}
}
