{
  "type": "Feature",
  "properties": {
    "iso:country":"GB",
    "wof:name":"DG1 4YH",
    "wof:placetype":"postalcode"
},
  "geometry": {"coordinates":[-3.57783323405503,55.05981516526953],"type":"Point"}
}