{
  "type": "Feature",
  "properties": {
    "iso:country":"GB",
    "wof:name":"DN21 3NL",
    "wof:placetype":"postalcode"
},
  "geometry": {"coordinates":[-0.72189352833194,53.44027807896835],"type":"Point"}
}