{
  "type": "Feature",
  "properties": {
    "date:inception_lower": "2009-03-01",
    "date:inception_upper": "2009-03-01",
    "iso:country": "GB",
    "wof:name": "KY2 6FL",
    "wof:placetype": "postalcode"
  },
  "geometry": {"coordinates":[-3.187934,56.137115],"type":"Point"}
}
