{
  "type": "Feature",
  "properties": {
    "iso:country":"GB",
    "wof:name":"KY2 6FL",
    "wof:placetype":"postalcode"
},
  "geometry": {"coordinates":[-3.18793434419015,56.13711474686599],"type":"Point"}
}