{
  "type": "Feature",
  "properties": {
    "iso:country": "GB",
    "wof:name": "BD12 0TS",
    "wof:placetype": "postalcode"
  },
  "geometry": {"coordinates":[-1.77555,53.754445],"type":"Point"}
}
