{
  "type": "Feature",
  "properties": {
    "iso:country": "GB",
    "wof:name": "PE34 3AF",
    "wof:placetype": "postalcode"
  },
  "geometry": {"coordinates":[0.389317,52.731873],"type":"Point"}
}
