{
  "type": "Feature",
  "properties": {
    "iso:country":"GB",
    "wof:name":"PE34 3AF",
    "wof:placetype":"postalcode"
},
  "geometry": {"coordinates":[0.38931697971277,52.7318726906737],"type":"Point"}
}