{
  "type": "Feature",
  "properties": {
    "date:inception_lower": "2005-10-01",
    "date:inception_upper": "2005-10-01",
    "iso:country": "GB",
    "wof:name": "TW3 1LX",
    "wof:placetype": "postalcode"
  },
  "geometry": {"coordinates":[-0.363664,51.470255],"type":"Point"}
}
