{
  "type": "Feature",
  "properties": {
    "date:inception_lower": "1994-12-01",
    "date:inception_upper": "1994-12-01",
    "iso:country": "GB",
    "wof:name": "SG8 6NH",
    "wof:placetype": "postalcode"
  },
  "geometry": {"coordinates":[0.027914,52.084509],"type":"Point"}
}
