{
  "type": "Feature",
  "properties": {
    "iso:country":"GB",
    "wof:name":"SL4 1HS",
    "wof:placetype":"postalcode"
},
  "geometry": {"coordinates":[-0.61193610570346,51.47754770265045],"type":"Point"}
}