{
  "type": "Feature",
  "properties": {
    "date:inception_lower": "1980-01-01",
    "date:inception_upper": "1980-01-01",
    "iso:country": "GB",
    "wof:name": "SL4 1HS",
    "wof:placetype": "postalcode"
  },
  "geometry": {"coordinates":[-0.611863,51.477531],"type":"Point"}
}
