{
  "type": "Feature",
  "properties": {
    "iso:country":"GB",
    "wof:name":"SP6 1DR",
    "wof:placetype":"postalcode"
},
  "geometry": {"coordinates":[-1.80995995430316,50.92956310021343],"type":"Point"}
}