{
  "type": "Feature",
  "properties": {
    "iso:country":"GB",
    "wof:name":"SG6 1JE",
    "wof:placetype":"postalcode"
},
  "geometry": {"coordinates":[-0.21925774911183,51.98150188963641],"type":"Point"}
}