{
  "type": "Feature",
  "properties": {
    "iso:country": "GB",
    "wof:name": "NG10 2DW",
    "wof:placetype": "postalcode"
  },
  "geometry": {"coordinates":[-1.261018,52.896645],"type":"Point"}
}
