{
  "type": "Feature",
  "properties": {
    "iso:country":"GB",
    "wof:name":"B90 1QU",
    "wof:placetype":"postalcode"
},
  "geometry": {"coordinates":[-1.85460138333652,52.37655065431739],"type":"Point"}
}