{
  "type": "Feature",
  "properties": {
    "iso:country":"GB",
    "wof:name":"CM6 3AF",
    "wof:placetype":"postalcode"
},
  "geometry": {"coordinates":[0.40317675783631,51.87518264587285],"type":"Point"}
}