{
  "type": "Feature",
  "properties": {
    "iso:country": "GB",
    "wof:name": "CV36 4FW",
    "wof:placetype": "postalcode"
  },
  "geometry": {"coordinates":[-1.642107,52.062553],"type":"Point"}
}
