{
  "type": "Feature",
  "properties": {
    "date:inception_lower": "1980-01-01",
    "date:inception_upper": "1980-01-01",
    "iso:country": "GB",
    "wof:name": "PE13 5QA",
    "wof:placetype": "postalcode"
  },
  "geometry": {"coordinates":[0.150009,52.739881],"type":"Point"}
}
