{
  "type": "Feature",
  "properties": {
    "iso:country":"GB",
    "wof:name":"PE13 5QA",
    "wof:placetype":"postalcode"
},
  "geometry": {"coordinates":[0.1499967393192,52.73961015867242],"type":"Point"}
}