{
  "type": "Feature",
  "properties": {
    "iso:country": "GB",
    "wof:name": "PE13 5QA",
    "wof:placetype": "postalcode"
  },
  "geometry": {"coordinates":[0.14992,52.739883],"type":"Point"}
}
