{
  "type": "Feature",
  "properties": {
    "iso:country":"GB",
    "wof:name":"S60 5NB",
    "wof:placetype":"postalcode"
},
  "geometry": {"coordinates":[-1.3759209195155,53.40871121522118],"type":"Point"}
}