{
  "type": "Feature",
  "properties": {
    "date:inception_lower":"1980-01-01",
    "date:inception_upper":"1980-01-31",
    "iso:country":"GB",
    "wof:name":"S60 5NB",
    "wof:placetype":"postalcode"
},
  "geometry": {"coordinates":[-1.375921,53.408711],"type":"Point"}
}