{
  "type": "Feature",
  "properties": {
    "date:inception_lower": "2022-04-01",
    "date:inception_upper": "2022-04-01",
    "iso:country": "GB",
    "wof:name": "DE6 4PR",
    "wof:placetype": "postalcode"
  },
  "geometry": {"coordinates":[-1.57867,53.000567],"type":"Point"}
}
