{
  "type": "Feature",
  "properties": {
    "iso:country": "GB",
    "wof:name": "WA7 1LS",
    "wof:placetype": "postalcode"
  },
  "geometry": {"coordinates":[-2.721782,53.342099],"type":"Point"}
}
