{
  "type": "Feature",
  "properties": {
    "date:inception_lower":"2003-04-01",
    "date:inception_upper":"2003-04-30",
    "iso:country":"GB",
    "wof:name":"WA7 1LS",
    "wof:placetype":"postalcode"
},
  "geometry": {"coordinates":[-2.721782,53.342099],"type":"Point"}
}