{
  "type": "Feature",
  "properties": {
    "date:inception_lower": "2016-06-01",
    "date:inception_upper": "2016-06-01",
    "iso:country": "GB",
    "wof:name": "ME15 6LN",
    "wof:placetype": "postalcode"
  },
  "geometry": {"coordinates":[0.525724,51.270736],"type":"Point"}
}
