{
  "type": "Feature",
  "properties": {
    "iso:country": "GB",
    "wof:name": "ME15 6LN",
    "wof:placetype": "postalcode"
  },
  "geometry": {"coordinates":[0.525724,51.270736],"type":"Point"}
}
