{
  "type": "Feature",
  "properties": {
    "iso:country":"GB",
    "wof:name":"GU46 7ST",
    "wof:placetype":"postalcode"
},
  "geometry": {"coordinates":[-0.82711250723411,51.34720178876468],"type":"Point"}
}