{
  "type": "Feature",
  "properties": {
    "iso:country": "GB",
    "wof:name": "GU46 7ST",
    "wof:placetype": "postalcode"
  },
  "geometry": {"coordinates":[-0.827112,51.347202],"type":"Point"}
}
