{
  "type": "Feature",
  "properties": {
    "iso:country": "GB",
    "wof:name": "PO39 0HN",
    "wof:placetype": "postalcode"
  },
  "geometry": {"coordinates":[-1.533113,50.677559],"type":"Point"}
}
