{
  "type": "Feature",
  "properties": {
    "date:inception_lower": "1992-08-01",
    "date:inception_upper": "1992-08-01",
    "iso:country": "GB",
    "wof:name": "PO6 1RR",
    "wof:placetype": "postalcode"
  },
  "geometry": {"coordinates":[-1.039151,50.84047],"type":"Point"}
}
