{
  "type": "Feature",
  "properties": {
    "iso:country":"GB",
    "wof:name":"PO6 1RR",
    "wof:placetype":"postalcode"
},
  "geometry": {"coordinates":[-1.03916548140902,50.84047994866606],"type":"Point"}
}