{
  "type": "Feature",
  "properties": {
    "iso:country":"GB",
    "wof:name":"NG23 7PT",
    "wof:placetype":"postalcode"
},
  "geometry": {"coordinates":[-0.75417226624826,53.14629960826267],"type":"Point"}
}