{
  "type": "Feature",
  "properties": {
    "date:inception_lower": "1980-01-01",
    "date:inception_upper": "1980-01-01",
    "iso:country": "GB",
    "wof:name": "NG23 7PT",
    "wof:placetype": "postalcode"
  },
  "geometry": {"coordinates":[-0.754172,53.1463],"type":"Point"}
}
