{
  "type": "Feature",
  "properties": {
    "iso:country": "GB",
    "wof:name": "WN2 1RB",
    "wof:placetype": "postalcode"
  },
  "geometry": {"coordinates":[-2.560322,53.561722],"type":"Point"}
}
