{
  "type": "Feature",
  "properties": {
    "date:inception_lower":"2012-03-01",
    "date:inception_upper":"2012-03-31",
    "iso:country":"GB",
    "wof:name":"WN2 1RB",
    "wof:placetype":"postalcode"
},
  "geometry": {"coordinates":[-2.560322,53.561722],"type":"Point"}
}