{
  "type": "Feature",
  "properties": {
    "iso:country":"GB",
    "wof:name":"WN2 1RB",
    "wof:placetype":"postalcode"
},
  "geometry": {"coordinates":[-2.5603217138108,53.56172230683228],"type":"Point"}
}