{
  "type": "Feature",
  "properties": {
    "iso:country":"GB",
    "wof:name":"LL74 8QF",
    "wof:placetype":"postalcode"
},
  "geometry": {"coordinates":[-4.24334998939292,53.31877173990297],"type":"Point"}
}