{
  "type": "Feature",
  "properties": {
    "iso:country":"GB",
    "wof:name":"TR1 3DD",
    "wof:placetype":"postalcode"
},
  "geometry": {"coordinates":[-5.05882344351595,50.26280071041002],"type":"Point"}
}