{
  "type": "Feature",
  "properties": {
    "iso:country":"GB",
    "wof:name":"BH21 2AW",
    "wof:placetype":"postalcode"
},
  "geometry": {"coordinates":[-1.97534424589281,50.797570720471],"type":"Point"}
}