{
  "type": "Feature",
  "properties": {
    "iso:country":"GB",
    "wof:name":"NP20 3GB",
    "wof:placetype":"postalcode"
},
  "geometry": {"coordinates":[-3.01049396881275,51.57470202501425],"type":"Point"}
}