{
  "type": "Feature",
  "properties": {
    "iso:country": "GB",
    "wof:name": "SY1 2DH",
    "wof:placetype": "postalcode"
  },
  "geometry": {"coordinates":[-2.751804,52.71453],"type":"Point"}
}
