{
  "type": "Feature",
  "properties": {
    "iso:country":"GB",
    "wof:name":"SY1 2DH",
    "wof:placetype":"postalcode"
},
  "geometry": {"coordinates":[-2.75180423608044,52.71452989412366],"type":"Point"}
}