{
  "type": "Feature",
  "properties": {
    "date:inception_lower": "1980-01-01",
    "date:inception_upper": "1980-01-01",
    "iso:country": "GB",
    "wof:name": "SW1V 1RY",
    "wof:placetype": "postalcode"
  },
  "geometry": {"coordinates":[-0.140503,51.491891],"type":"Point"}
}
