{
  "type": "Feature",
  "properties": {
    "date:inception_lower":"2002-10-01",
    "date:inception_upper":"2002-10-31",
    "iso:country":"GB",
    "wof:name":"AL10 9FR",
    "wof:placetype":"postalcode"
},
  "geometry": {"coordinates":[-0.237556,51.772851],"type":"Point"}
}