{
  "type": "Feature",
  "properties": {
    "iso:country": "GB",
    "wof:name": "AL10 9FR",
    "wof:placetype": "postalcode"
  },
  "geometry": {"coordinates":[-0.237556,51.772851],"type":"Point"}
}
