{
  "type": "Feature",
  "properties": {
    "iso:country":"GB",
    "wof:name":"GL1 1SQ",
    "wof:placetype":"postalcode"
},
  "geometry": {"coordinates":[-2.24417024746035,51.86634539621083],"type":"Point"}
}