{
  "type": "Feature",
  "properties": {
    "date:inception_lower": "1980-01-01",
    "date:inception_upper": "1980-01-01",
    "iso:country": "GB",
    "wof:name": "GL1 1SQ",
    "wof:placetype": "postalcode"
  },
  "geometry": {"coordinates":[-2.244268,51.866227],"type":"Point"}
}
