{
  "type": "Feature",
  "properties": {
    "iso:country":"GB",
    "wof:name":"WV15 5DJ",
    "wof:placetype":"postalcode"
},
  "geometry": {"coordinates":[-2.40444098964327,52.53434267565865],"type":"Point"}
}