{
  "type": "Feature",
  "properties": {
    "iso:country":"GB",
    "wof:name":"OX2 6BJ",
    "wof:placetype":"postalcode"
},
  "geometry": {"coordinates":[-1.270206592228,51.75918605793974],"type":"Point"}
}