{
  "type": "Feature",
  "properties": {
    "iso:country": "GB",
    "wof:name": "OX2 6BJ",
    "wof:placetype": "postalcode"
  },
  "geometry": {"coordinates":[-1.270207,51.759186],"type":"Point"}
}
