{
  "type": "Feature",
  "properties": {
    "iso:country":"GB",
    "wof:name":"TW5 9DJ",
    "wof:placetype":"postalcode"
},
  "geometry": {"coordinates":[-0.3846104365896,51.47970831635948],"type":"Point"}
}