{
  "type": "Feature",
  "properties": {
    "iso:country": "GB",
    "wof:name": "TW5 9DJ",
    "wof:placetype": "postalcode"
  },
  "geometry": {"coordinates":[-0.38461,51.479708],"type":"Point"}
}
