{
  "type": "Feature",
  "properties": {
    "date:inception_lower": "2005-01-01",
    "date:inception_upper": "2005-01-01",
    "iso:country": "GB",
    "wof:name": "TA6 3SU",
    "wof:placetype": "postalcode"
  },
  "geometry": {"coordinates":[-3.013412,51.138916],"type":"Point"}
}
