{
  "type": "Feature",
  "properties": {
    "date:inception_lower": "1980-01-01",
    "date:inception_upper": "1980-01-01",
    "iso:country": "GB",
    "wof:name": "DG12 6TF",
    "wof:placetype": "postalcode"
  },
  "geometry": {"coordinates":[-3.161052,54.984423],"type":"Point"}
}
