{
  "type": "Feature",
  "properties": {
    "iso:country":"GB",
    "wof:name":"G75 9AX",
    "wof:placetype":"postalcode"
},
  "geometry": {"coordinates":[-4.19313231440501,55.75167989859744],"type":"Point"}
}