{
  "type": "Feature",
  "properties": {
    "date:inception_lower": "1980-01-01",
    "date:inception_upper": "1980-01-01",
    "iso:country": "GB",
    "wof:name": "G75 9AX",
    "wof:placetype": "postalcode"
  },
  "geometry": {"coordinates":[-4.193132,55.75168],"type":"Point"}
}
