{
  "type": "Feature",
  "properties": {
    "iso:country": "GB",
    "wof:name": "GU22 0SN",
    "wof:placetype": "postalcode"
  },
  "geometry": {"coordinates":[-0.576331,51.290044],"type":"Point"}
}
