{
  "type": "Feature",
  "properties": {
    "iso:country": "GB",
    "wof:name": "TN12 7PD",
    "wof:placetype": "postalcode"
  },
  "geometry": {"coordinates":[0.388536,51.149936],"type":"Point"}
}
