{
  "type": "Feature",
  "properties": {
    "date:inception_lower": "1980-01-01",
    "date:inception_upper": "1980-01-01",
    "iso:country": "GB",
    "wof:name": "TN12 7PD",
    "wof:placetype": "postalcode"
  },
  "geometry": {"coordinates":[0.388536,51.149936],"type":"Point"}
}
