{
  "type": "Feature",
  "properties": {
    "iso:country":"GB",
    "wof:name":"ME1 3SN",
    "wof:placetype":"postalcode"
},
  "geometry": {"coordinates":[0.48651928916161,51.32396321416392],"type":"Point"}
}