{
  "type": "Feature",
  "properties": {
    "iso:country": "GB",
    "wof:name": "SP6 1AN",
    "wof:placetype": "postalcode"
  },
  "geometry": {"coordinates":[-1.787125,50.925693],"type":"Point"}
}
