{
  "type": "Feature",
  "properties": {
    "iso:country":"GB",
    "wof:name":"SP6 1AN",
    "wof:placetype":"postalcode"
},
  "geometry": {"coordinates":[-1.78712541474896,50.92569301372194],"type":"Point"}
}