{
  "type": "Feature",
  "properties": {
    "date:inception_lower": "2007-08-01",
    "date:inception_upper": "2007-08-01",
    "iso:country": "GB",
    "wof:name": "L1 1AH",
    "wof:placetype": "postalcode"
  },
  "geometry": {"coordinates":[-2.977222,53.4083],"type":"Point"}
}
