{
  "type": "Feature",
  "properties": {
    "iso:country":"GB",
    "wof:name":"GU30 7EE",
    "wof:placetype":"postalcode"
},
  "geometry": {"coordinates":[-0.80408512978858,51.07009507180204],"type":"Point"}
}