{
  "type": "Feature",
  "properties": {
    "date:inception_lower": "1980-01-01",
    "date:inception_upper": "1980-01-01",
    "iso:country": "GB",
    "wof:name": "GU30 7EE",
    "wof:placetype": "postalcode"
  },
  "geometry": {"coordinates":[-0.804085,51.070095],"type":"Point"}
}
