{
  "type": "Feature",
  "properties": {
    "iso:country":"GB",
    "wof:name":"KY1 2YP",
    "wof:placetype":"postalcode"
},
  "geometry": {"coordinates":[-3.11855573056065,56.13963135759361],"type":"Point"}
}