{
  "type": "Feature",
  "properties": {
    "iso:country":"GB",
    "wof:name":"DE6 1NF",
    "wof:placetype":"postalcode"
},
  "geometry": {"coordinates":[-1.73014924419404,53.00846722269945],"type":"Point"}
}