{
  "type": "Feature",
  "properties": {
    "iso:country":"GB",
    "wof:name":"S44 6QW",
    "wof:placetype":"postalcode"
},
  "geometry": {"coordinates":[-1.30307395525785,53.24884617856145],"type":"Point"}
}