{
  "type": "Feature",
  "properties": {
    "iso:country":"GB",
    "wof:name":"NG19 8QX",
    "wof:placetype":"postalcode"
},
  "geometry": {"coordinates":[-1.18919005322495,53.17888330139117],"type":"Point"}
}