{
  "type": "Feature",
  "properties": {
    "date:inception_lower": "1980-01-01",
    "date:inception_upper": "1980-01-01",
    "iso:country": "GB",
    "wof:name": "L20 9ES",
    "wof:placetype": "postalcode"
  },
  "geometry": {"coordinates":[-2.971896,53.453791],"type":"Point"}
}
