{
  "type": "Feature",
  "properties": {
    "iso:country":"GB",
    "wof:name":"L20 9ES",
    "wof:placetype":"postalcode"
},
  "geometry": {"coordinates":[-2.97189649841274,53.45379082637282],"type":"Point"}
}