{
  "type": "Feature",
  "properties": {
    "iso:country":"GB",
    "wof:name":"NG16 5NE",
    "wof:placetype":"postalcode"
},
  "geometry": {"coordinates":[-1.34736052540985,53.06042468939192],"type":"Point"}
}