{
  "type": "Feature",
  "properties": {
    "iso:country": "GB",
    "wof:name": "NG16 5NE",
    "wof:placetype": "postalcode"
  },
  "geometry": {"coordinates":[-1.347358,53.060471],"type":"Point"}
}
