{
  "type": "Feature",
  "properties": {
    "date:inception_lower": "1980-01-01",
    "date:inception_upper": "1980-01-01",
    "iso:country": "GB",
    "wof:name": "NW10 3DB",
    "wof:placetype": "postalcode"
  },
  "geometry": {"coordinates":[-0.228514,51.535878],"type":"Point"}
}
