{
  "type": "Feature",
  "properties": {
    "iso:country": "GB",
    "wof:name": "EX37 9NG",
    "wof:placetype": "postalcode"
  },
  "geometry": {"coordinates":[-3.927525,50.941483],"type":"Point"}
}
