{
  "type": "Feature",
  "properties": {
    "iso:country":"GB",
    "wof:name":"EX37 9NG",
    "wof:placetype":"postalcode"
},
  "geometry": {"coordinates":[-3.92752455990804,50.94148303527733],"type":"Point"}
}