{
  "type": "Feature",
  "properties": {
    "date:inception_lower":"1991-01-01",
    "date:inception_upper":"1991-01-31",
    "iso:country":"GB",
    "wof:name":"LL12 9BX",
    "wof:placetype":"postalcode"
},
  "geometry": {"coordinates":[-3.037967,53.109948],"type":"Point"}
}