{
  "type": "Feature",
  "properties": {
    "iso:country":"GB",
    "wof:name":"LL12 9BX",
    "wof:placetype":"postalcode"
},
  "geometry": {"coordinates":[-3.03796732813809,53.10994804307678],"type":"Point"}
}