{
  "type": "Feature",
  "properties": {
    "iso:country": "GB",
    "wof:name": "PE19 6PE",
    "wof:placetype": "postalcode"
  },
  "geometry": {"coordinates":[-0.260621,52.247343],"type":"Point"}
}
