{
  "type": "Feature",
  "properties": {
    "iso:country":"GB",
    "wof:name":"SK9 7AW",
    "wof:placetype":"postalcode"
},
  "geometry": {"coordinates":[-2.23093006985059,53.29513388689709],"type":"Point"}
}