{
  "type": "Feature",
  "properties": {
    "date:inception_lower": "1980-01-01",
    "date:inception_upper": "1980-01-01",
    "iso:country": "GB",
    "wof:name": "SK9 7AW",
    "wof:placetype": "postalcode"
  },
  "geometry": {"coordinates":[-2.23093,53.295134],"type":"Point"}
}
