{
  "type": "Feature",
  "properties": {
    "iso:country": "GB",
    "wof:name": "SK9 7AW",
    "wof:placetype": "postalcode"
  },
  "geometry": {"coordinates":[-2.23093,53.295134],"type":"Point"}
}
