{
  "type": "Feature",
  "properties": {
    "date:inception_lower":"2003-10-01",
    "date:inception_upper":"2003-10-31",
    "iso:country":"GB",
    "wof:name":"TF12 5JD",
    "wof:placetype":"postalcode"
},
  "geometry": {"coordinates":[-2.486717,52.611684],"type":"Point"}
}