{
  "type": "Feature",
  "properties": {
    "iso:country":"GB",
    "wof:name":"ST2 8BH",
    "wof:placetype":"postalcode"
},
  "geometry": {"coordinates":[-2.13979525193704,53.0310642724282],"type":"Point"}
}