{
  "type": "Feature",
  "properties": {
    "iso:country": "GB",
    "wof:name": "PA33 1AT",
    "wof:placetype": "postalcode"
  },
  "geometry": {"coordinates":[-4.998603,56.377846],"type":"Point"}
}
