{
  "type": "Feature",
  "properties": {
    "iso:country":"GB",
    "wof:name":"PA33 1AT",
    "wof:placetype":"postalcode"
},
  "geometry": {"coordinates":[-5.02232784261083,56.38689054012809],"type":"Point"}
}