{
  "type": "Feature",
  "properties": {
    "date:inception_lower":"1980-01-01",
    "date:inception_upper":"1980-01-31",
    "iso:country":"GB",
    "wof:name":"PA33 1AT",
    "wof:placetype":"postalcode"
},
  "geometry": {"coordinates":[-4.998603,56.377846],"type":"Point"}
}