{
  "type": "Feature",
  "properties": {
    "iso:country": "GB",
    "wof:name": "PA33 1AT",
    "wof:placetype": "postalcode"
  },
  "geometry": {"coordinates":[-5.022307,56.386879],"type":"Point"}
}
