{
  "type": "Feature",
  "properties": {
    "iso:country": "GB",
    "wof:name": "NG22 9UE",
    "wof:placetype": "postalcode"
  },
  "geometry": {"coordinates":[-0.998182,53.213174],"type":"Point"}
}
