{
  "type": "Feature",
  "properties": {
    "iso:country":"GB",
    "wof:name":"BN8 5SW",
    "wof:placetype":"postalcode"
},
  "geometry": {"coordinates":[0.03315839203405,50.90288069002817],"type":"Point"}
}