{
  "type": "Feature",
  "properties": {
    "iso:country":"GB",
    "wof:name":"KW17 2UE",
    "wof:placetype":"postalcode"
},
  "geometry": {"coordinates":[-3.11535892681911,59.00386820177222],"type":"Point"}
}