{
  "type": "Feature",
  "properties": {
    "date:inception_lower": "2011-07-01",
    "date:inception_upper": "2011-07-01",
    "iso:country": "GB",
    "wof:name": "KW17 2UE",
    "wof:placetype": "postalcode"
  },
  "geometry": {"coordinates":[-3.115421,59.003887],"type":"Point"}
}
