{
  "type": "Feature",
  "properties": {
    "iso:country": "GB",
    "wof:name": "KW17 2UE",
    "wof:placetype": "postalcode"
  },
  "geometry": {"coordinates":[-3.115421,59.003887],"type":"Point"}
}
