{
  "type": "Feature",
  "properties": {
    "date:inception_lower": "1980-01-01",
    "date:inception_upper": "1980-01-01",
    "iso:country": "GB",
    "wof:name": "NE23 6TN",
    "wof:placetype": "postalcode"
  },
  "geometry": {"coordinates":[-1.575913,55.08299],"type":"Point"}
}
