{
  "type": "Feature",
  "properties": {
    "iso:country":"GB",
    "wof:name":"NE23 6TN",
    "wof:placetype":"postalcode"
},
  "geometry": {"coordinates":[-1.57591328023207,55.08298995079569],"type":"Point"}
}