{
  "type": "Feature",
  "properties": {
    "iso:country":"GB",
    "wof:name":"AL5 4AP",
    "wof:placetype":"postalcode"
},
  "geometry": {"coordinates":[-0.36182357635638,51.82306923070576],"type":"Point"}
}