{
  "type": "Feature",
  "properties": {
    "date:inception_lower": "2000-10-01",
    "date:inception_upper": "2000-10-01",
    "iso:country": "GB",
    "wof:name": "W1U 1QE",
    "wof:placetype": "postalcode"
  },
  "geometry": {"coordinates":[-0.15087,51.515876],"type":"Point"}
}
