{
  "type": "Feature",
  "properties": {
    "iso:country": "GB",
    "wof:name": "BB9 6JU",
    "wof:placetype": "postalcode"
  },
  "geometry": {"coordinates":[-2.219173,53.853249],"type":"Point"}
}
