{
  "type": "Feature",
  "properties": {
    "iso:country":"GB",
    "wof:name":"BL1 5RL",
    "wof:placetype":"postalcode"
},
  "geometry": {"coordinates":[-2.46709301241948,53.59155082912625],"type":"Point"}
}