{
  "type": "Feature",
  "properties": {
    "date:inception_lower":"2016-09-01",
    "date:inception_upper":"2016-09-30",
    "iso:country":"GB",
    "wof:name":"SY2 6BZ",
    "wof:placetype":"postalcode"
},
  "geometry": {"coordinates":[-2.743413,52.708691],"type":"Point"}
}