{
  "type": "Feature",
  "properties": {
    "iso:country": "GB",
    "wof:name": "SY2 6BZ",
    "wof:placetype": "postalcode"
  },
  "geometry": {"coordinates":[-2.743413,52.708691],"type":"Point"}
}
