{
  "type": "Feature",
  "properties": {
    "iso:country":"GB",
    "wof:name":"OX20 1BY",
    "wof:placetype":"postalcode"
},
  "geometry": {"coordinates":[-1.3984872064723,51.90322084368196],"type":"Point"}
}