{
  "type": "Feature",
  "properties": {
    "iso:country": "GB",
    "wof:name": "TS18 1HA",
    "wof:placetype": "postalcode"
  },
  "geometry": {"coordinates":[-1.318169,54.564235],"type":"Point"}
}
