{
  "type": "Feature",
  "properties": {
    "iso:country": "GB",
    "wof:name": "HD2 2HW",
    "wof:placetype": "postalcode"
  },
  "geometry": {"coordinates":[-1.788759,53.672902],"type":"Point"}
}
