{
  "type": "Feature",
  "properties": {
    "iso:country":"GB",
    "wof:name":"HD2 2HW",
    "wof:placetype":"postalcode"
},
  "geometry": {"coordinates":[-1.78875886661245,53.67290186780869],"type":"Point"}
}