{
  "type": "Feature",
  "properties": {
    "date:inception_lower": "1997-12-01",
    "date:inception_upper": "1997-12-01",
    "iso:country": "GB",
    "wof:name": "BS34 7PL",
    "wof:placetype": "postalcode"
  },
  "geometry": {"coordinates":[-2.577902,51.504736],"type":"Point"}
}
