{
  "type": "Feature",
  "properties": {
    "iso:country":"GB",
    "wof:name":"BS34 7PL",
    "wof:placetype":"postalcode"
},
  "geometry": {"coordinates":[-2.577902048214,51.50473617571225],"type":"Point"}
}