{
  "type": "Feature",
  "properties": {
    "iso:country":"GB",
    "wof:name":"CA12 4TX",
    "wof:placetype":"postalcode"
},
  "geometry": {"coordinates":[-3.04684802104311,54.61190799236768],"type":"Point"}
}