{
  "type": "Feature",
  "properties": {
    "iso:country": "GB",
    "wof:name": "CA12 4TX",
    "wof:placetype": "postalcode"
  },
  "geometry": {"coordinates":[-3.046725,54.611844],"type":"Point"}
}
