{
  "type": "Feature",
  "properties": {
    "date:inception_lower": "1980-01-01",
    "date:inception_upper": "1980-01-01",
    "iso:country": "GB",
    "wof:name": "ST3 2BP",
    "wof:placetype": "postalcode"
  },
  "geometry": {"coordinates":[-2.162639,52.983608],"type":"Point"}
}
