{
  "type": "Feature",
  "properties": {
    "date:inception_lower": "1980-01-01",
    "date:inception_upper": "1980-01-01",
    "iso:country": "GB",
    "wof:name": "LE16 8QJ",
    "wof:placetype": "postalcode"
  },
  "geometry": {"coordinates":[-0.799727,52.486004],"type":"Point"}
}
