{
  "type": "Feature",
  "properties": {
    "iso:country":"GB",
    "wof:name":"W1G 9UH",
    "wof:placetype":"postalcode"
},
  "geometry": {"coordinates":[-0.15063111963649,51.5189210733779],"type":"Point"}
}