{
  "type": "Feature",
  "properties": {
    "iso:country":"GB",
    "wof:name":"NW7 1ED",
    "wof:placetype":"postalcode"
},
  "geometry": {"coordinates":[-0.20497831003591,51.61289023698983],"type":"Point"}
}