{
  "type": "Feature",
  "properties": {
    "date:inception_lower": "2008-10-01",
    "date:inception_upper": "2008-10-01",
    "iso:country": "GB",
    "wof:name": "NW7 1ED",
    "wof:placetype": "postalcode"
  },
  "geometry": {"coordinates":[-0.205642,51.612643],"type":"Point"}
}
