{
  "type": "Feature",
  "properties": {
    "iso:country":"GB",
    "wof:name":"S18 7WP",
    "wof:placetype":"postalcode"
},
  "geometry": {"coordinates":[-1.5241623698406,53.29466156163392],"type":"Point"}
}