{
  "type": "Feature",
  "properties": {
    "iso:country": "GB",
    "wof:name": "S18 7WP",
    "wof:placetype": "postalcode"
  },
  "geometry": {"coordinates":[-1.524162,53.294662],"type":"Point"}
}
