{
  "type": "Feature",
  "properties": {
    "iso:country":"GB",
    "wof:name":"IP14 2AN",
    "wof:placetype":"postalcode"
},
  "geometry": {"coordinates":[0.9999556410452,52.17941511970987],"type":"Point"}
}