{
  "type": "Feature",
  "properties": {
    "date:inception_lower": "1980-01-01",
    "date:inception_upper": "1980-01-01",
    "iso:country": "GB",
    "wof:name": "IP14 2AN",
    "wof:placetype": "postalcode"
  },
  "geometry": {"coordinates":[1.00033,52.179521],"type":"Point"}
}
