{
  "type": "Feature",
  "properties": {
    "date:inception_lower": "1980-01-01",
    "date:inception_upper": "1980-01-01",
    "iso:country": "GB",
    "wof:name": "S62 5RQ",
    "wof:placetype": "postalcode"
  },
  "geometry": {"coordinates":[-1.334771,53.466017],"type":"Point"}
}
