{
  "type": "Feature",
  "properties": {
    "iso:country":"GB",
    "wof:name":"PR26 7YH",
    "wof:placetype":"postalcode"
},
  "geometry": {"coordinates":[-2.73467675882956,53.69376196748008],"type":"Point"}
}