{
  "type": "Feature",
  "properties": {
    "iso:country":"GB",
    "wof:name":"BN43 6TQ",
    "wof:placetype":"postalcode"
},
  "geometry": {"coordinates":[-0.25718299720712,50.8407745422013],"type":"Point"}
}