{
  "type": "Feature",
  "properties": {
    "date:inception_lower": "2020-02-01",
    "date:inception_upper": "2020-02-01",
    "iso:country": "GB",
    "wof:name": "L33 0AD",
    "wof:placetype": "postalcode"
  },
  "geometry": {"coordinates":[-2.876472,53.482698],"type":"Point"}
}
