{
  "type": "Feature",
  "properties": {
    "date:inception_lower": "1980-01-01",
    "date:inception_upper": "1980-01-01",
    "iso:country": "GB",
    "wof:name": "NE2 1HB",
    "wof:placetype": "postalcode"
  },
  "geometry": {"coordinates":[-1.591434,54.987915],"type":"Point"}
}
