{
  "type": "Feature",
  "properties": {
    "iso:country":"GB",
    "wof:name":"NE2 1HB",
    "wof:placetype":"postalcode"
},
  "geometry": {"coordinates":[-1.59143370445656,54.98791526893537],"type":"Point"}
}