{
  "type": "Feature",
  "properties": {
    "date:inception_lower": "1997-12-01",
    "date:inception_upper": "1997-12-01",
    "iso:country": "GB",
    "wof:name": "G83 0SH",
    "wof:placetype": "postalcode"
  },
  "geometry": {"coordinates":[-4.579835,55.981869],"type":"Point"}
}
