{
  "type": "Feature",
  "properties": {
    "iso:country":"GB",
    "wof:name":"EH19 2EY",
    "wof:placetype":"postalcode"
},
  "geometry": {"coordinates":[-3.10711715026363,55.88073340051208],"type":"Point"}
}