{
  "type": "Feature",
  "properties": {
    "iso:country": "GB",
    "wof:name": "GU3 3PG",
    "wof:placetype": "postalcode"
  },
  "geometry": {"coordinates":[-0.611738,51.277459],"type":"Point"}
}
