{
  "type": "Feature",
  "properties": {
    "iso:country":"GB",
    "wof:name":"GU3 3PG",
    "wof:placetype":"postalcode"
},
  "geometry": {"coordinates":[-0.61166570387943,51.27746731837905],"type":"Point"}
}