{
  "type": "Feature",
  "properties": {
    "iso:country":"GB",
    "wof:name":"CV8 1NR",
    "wof:placetype":"postalcode"
},
  "geometry": {"coordinates":[-1.67234143990897,52.36528128003278],"type":"Point"}
}