{
  "type": "Feature",
  "properties": {
    "iso:country": "GB",
    "wof:name": "PE7 3XH",
    "wof:placetype": "postalcode"
  },
  "geometry": {"coordinates":[-0.290915,52.487445],"type":"Point"}
}
