{
  "type": "Feature",
  "properties": {
    "iso:country":"GB",
    "wof:name":"PE7 3XH",
    "wof:placetype":"postalcode"
},
  "geometry": {"coordinates":[-0.29091507309565,52.48744477139741],"type":"Point"}
}