{
  "type": "Feature",
  "properties": {
    "iso:country":"GB",
    "wof:name":"NR5 0JA",
    "wof:placetype":"postalcode"
},
  "geometry": {"coordinates":[1.22129116477421,52.64747933517445],"type":"Point"}
}