{
  "type": "Feature",
  "properties": {
    "date:inception_lower":"1980-01-01",
    "date:inception_upper":"1980-01-31",
    "iso:country":"GB",
    "wof:name":"DA12 4LW",
    "wof:placetype":"postalcode"
},
  "geometry": {"coordinates":[0.396814,51.417881],"type":"Point"}
}