{
  "type": "Feature",
  "properties": {
    "iso:country":"GB",
    "wof:name":"DA12 4LW",
    "wof:placetype":"postalcode"
},
  "geometry": {"coordinates":[0.39681436242826,51.41788140526579],"type":"Point"}
}