{
  "type": "Feature",
  "properties": {
    "date:inception_lower":"2002-12-01",
    "date:inception_upper":"2002-12-31",
    "iso:country":"GB",
    "wof:name":"SP10 3GZ",
    "wof:placetype":"postalcode"
},
  "geometry": {"coordinates":[-1.503045,51.207433],"type":"Point"}
}