{
  "type": "Feature",
  "properties": {
    "iso:country": "GB",
    "wof:name": "TA3 5DS",
    "wof:placetype": "postalcode"
  },
  "geometry": {"coordinates":[-3.037271,51.027947],"type":"Point"}
}
