{
  "type": "Feature",
  "properties": {
    "date:inception_lower": "1999-12-01",
    "date:inception_upper": "1999-12-01",
    "iso:country": "GB",
    "wof:name": "CV47 2UA",
    "wof:placetype": "postalcode"
  },
  "geometry": {"coordinates":[-1.443075,52.16071],"type":"Point"}
}
