{
  "type": "Feature",
  "properties": {
    "iso:country":"GB",
    "wof:name":"SR3 1XP",
    "wof:placetype":"postalcode"
},
  "geometry": {"coordinates":[-1.39610701646043,54.89071460735285],"type":"Point"}
}