{
  "type": "Feature",
  "properties": {
    "iso:country":"GB",
    "wof:name":"W1D 4NU",
    "wof:placetype":"postalcode"
},
  "geometry": {"coordinates":[-0.13114311686053,51.51506014509549],"type":"Point"}
}