{
  "type": "Feature",
  "properties": {
    "iso:country":"GB",
    "wof:name":"LL57 3NB",
    "wof:placetype":"postalcode"
},
  "geometry": {"coordinates":[-4.06616163804549,53.18151594630316],"type":"Point"}
}