{
  "type": "Feature",
  "properties": {
    "iso:country": "GB",
    "wof:name": "TS29 6BZ",
    "wof:placetype": "postalcode"
  },
  "geometry": {"coordinates":[-1.413592,54.723524],"type":"Point"}
}
