{
  "type": "Feature",
  "properties": {
    "iso:country":"GB",
    "wof:name":"TS29 6BZ",
    "wof:placetype":"postalcode"
},
  "geometry": {"coordinates":[-1.413592061316,54.72352366533887],"type":"Point"}
}