{
  "type": "Feature",
  "properties": {
    "iso:country":"GB",
    "wof:name":"B66 1DL",
    "wof:placetype":"postalcode"
},
  "geometry": {"coordinates":[-1.97067092753945,52.50090524583803],"type":"Point"}
}