{
  "type": "Feature",
  "properties": {
    "date:inception_lower":"1980-01-01",
    "date:inception_upper":"1980-01-31",
    "iso:country":"GB",
    "wof:name":"B66 1DL",
    "wof:placetype":"postalcode"
},
  "geometry": {"coordinates":[-1.970671,52.500905],"type":"Point"}
}