{
  "type": "Feature",
  "properties": {
    "date:inception_lower": "1980-01-01",
    "date:inception_upper": "1980-01-01",
    "iso:country": "GB",
    "wof:name": "BB11 5NS",
    "wof:placetype": "postalcode"
  },
  "geometry": {"coordinates":[-2.259795,53.762997],"type":"Point"}
}
