{
  "type": "Feature",
  "properties": {
    "iso:country": "GB",
    "wof:name": "BB11 5NS",
    "wof:placetype": "postalcode"
  },
  "geometry": {"coordinates":[-2.261261,53.76209],"type":"Point"}
}
