{
  "type": "Feature",
  "properties": {
    "iso:country":"GB",
    "wof:name":"KW15 1TX",
    "wof:placetype":"postalcode"
},
  "geometry": {"coordinates":[-3.05237435267439,58.99360002692724],"type":"Point"}
}