{
  "type": "Feature",
  "properties": {
    "date:inception_lower":"1980-01-01",
    "date:inception_upper":"1980-01-31",
    "iso:country":"GB",
    "wof:name":"KW15 1TX",
    "wof:placetype":"postalcode"
},
  "geometry": {"coordinates":[-3.052374,58.9936],"type":"Point"}
}