{
  "type": "Feature",
  "properties": {
    "iso:country":"GB",
    "wof:name":"DN20 0JW",
    "wof:placetype":"postalcode"
},
  "geometry": {"coordinates":[-0.54545295573132,53.5656197743545],"type":"Point"}
}