{
  "type": "Feature",
  "properties": {
    "iso:country": "GB",
    "wof:name": "DN20 0JW",
    "wof:placetype": "postalcode"
  },
  "geometry": {"coordinates":[-0.545453,53.56562],"type":"Point"}
}
