{
  "type": "Feature",
  "properties": {
    "date:inception_lower": "1980-01-01",
    "date:inception_upper": "1980-01-01",
    "iso:country": "GB",
    "wof:name": "DN20 0JW",
    "wof:placetype": "postalcode"
  },
  "geometry": {"coordinates":[-0.545453,53.56562],"type":"Point"}
}
