{
  "type": "Feature",
  "properties": {
    "date:inception_lower": "1980-01-01",
    "date:inception_upper": "1980-01-01",
    "iso:country": "GB",
    "wof:name": "G13 1PU",
    "wof:placetype": "postalcode"
  },
  "geometry": {"coordinates":[-4.330039,55.88304],"type":"Point"}
}
