{
  "type": "Feature",
  "properties": {
    "iso:country": "GB",
    "wof:name": "PE28 9JW",
    "wof:placetype": "postalcode"
  },
  "geometry": {"coordinates":[-0.067056,52.300799],"type":"Point"}
}
