{
  "type": "Feature",
  "properties": {
    "date:inception_lower": "1980-01-01",
    "date:inception_upper": "1980-01-01",
    "iso:country": "GB",
    "wof:name": "NW6 4TB",
    "wof:placetype": "postalcode"
  },
  "geometry": {"coordinates":[-0.195365,51.540606],"type":"Point"}
}
