{
  "type": "Feature",
  "properties": {
    "iso:country":"GB",
    "wof:name":"BS14 0LD",
    "wof:placetype":"postalcode"
},
  "geometry": {"coordinates":[-2.580204518922,51.40352392732528],"type":"Point"}
}