{
  "type": "Feature",
  "properties": {
    "iso:country": "GB",
    "wof:name": "SP3 4RR",
    "wof:placetype": "postalcode"
  },
  "geometry": {"coordinates":[-1.918417,51.208908],"type":"Point"}
}
