{
  "type": "Feature",
  "properties": {
    "iso:country":"GB",
    "wof:name":"HR9 5UR",
    "wof:placetype":"postalcode"
},
  "geometry": {"coordinates":[-2.59115613110553,51.90640847855335],"type":"Point"}
}