{
  "type": "Feature",
  "properties": {
    "iso:country":"GB",
    "wof:name":"PL28 8ES",
    "wof:placetype":"postalcode"
},
  "geometry": {"coordinates":[-4.94372040075247,50.5381110696382],"type":"Point"}
}