{
  "type": "Feature",
  "properties": {
    "iso:country":"GB",
    "wof:name":"SO50 4HF",
    "wof:placetype":"postalcode"
},
  "geometry": {"coordinates":[-1.34999051888002,50.97394196321898],"type":"Point"}
}