{
  "type": "Feature",
  "properties": {
    "iso:country": "GB",
    "wof:name": "SO50 4HF",
    "wof:placetype": "postalcode"
  },
  "geometry": {"coordinates":[-1.34998,50.973934],"type":"Point"}
}
