{
  "type": "Feature",
  "properties": {
    "date:inception_lower": "2008-11-01",
    "date:inception_upper": "2008-11-01",
    "iso:country": "GB",
    "wof:name": "SA18 3EF",
    "wof:placetype": "postalcode"
  },
  "geometry": {"coordinates":[-3.989789,51.790713],"type":"Point"}
}
