{
  "type": "Feature",
  "properties": {
    "iso:country":"GB",
    "wof:name":"SA18 3EF",
    "wof:placetype":"postalcode"
},
  "geometry": {"coordinates":[-3.98978864638295,51.79071346656222],"type":"Point"}
}