{
  "type": "Feature",
  "properties": {
    "iso:country":"GB",
    "wof:name":"IP18 6LT",
    "wof:placetype":"postalcode"
},
  "geometry": {"coordinates":[1.68316013417648,52.32896913347894],"type":"Point"}
}