{
  "type": "Feature",
  "properties": {
    "iso:country":"GB",
    "wof:name":"L8 2UX",
    "wof:placetype":"postalcode"
},
  "geometry": {"coordinates":[-2.95587659460105,53.39290356916436],"type":"Point"}
}