{
  "type": "Feature",
  "properties": {
    "date:inception_lower": "1998-06-01",
    "date:inception_upper": "1998-06-01",
    "iso:country": "GB",
    "wof:name": "YO61 1HR",
    "wof:placetype": "postalcode"
  },
  "geometry": {"coordinates":[-1.131891,54.084663],"type":"Point"}
}
