{
  "type": "Feature",
  "properties": {
    "iso:country": "GB",
    "wof:name": "YO61 1HR",
    "wof:placetype": "postalcode"
  },
  "geometry": {"coordinates":[-1.131783,54.084925],"type":"Point"}
}
