{
  "type": "Feature",
  "properties": {
    "iso:country":"GB",
    "wof:name":"YO61 1HR",
    "wof:placetype":"postalcode"
},
  "geometry": {"coordinates":[-1.1317833459442,54.08492535581836],"type":"Point"}
}