{
  "type": "Feature",
  "properties": {
    "iso:country":"GB",
    "wof:name":"B93 9NH",
    "wof:placetype":"postalcode"
},
  "geometry": {"coordinates":[-1.73508389631464,52.394107971149],"type":"Point"}
}