{
  "type": "Feature",
  "properties": {
    "iso:country": "GB",
    "wof:name": "B93 9NH",
    "wof:placetype": "postalcode"
  },
  "geometry": {"coordinates":[-1.735084,52.394108],"type":"Point"}
}
