{
  "type": "Feature",
  "properties": {
    "iso:country":"GB",
    "wof:name":"HX2 9EP",
    "wof:placetype":"postalcode"
},
  "geometry": {"coordinates":[-1.88929451032501,53.75499913447457],"type":"Point"}
}