{
  "type": "Feature",
  "properties": {
    "iso:country":"GB",
    "wof:name":"B26 1JU",
    "wof:placetype":"postalcode"
},
  "geometry": {"coordinates":[-1.80174744368186,52.45872406342691],"type":"Point"}
}