{
  "type": "Feature",
  "properties": {
    "iso:country":"GB",
    "wof:name":"SR2 0HW",
    "wof:placetype":"postalcode"
},
  "geometry": {"coordinates":[-1.36838203648349,54.86914086130218],"type":"Point"}
}