{
  "type": "Feature",
  "properties": {
    "date:inception_lower": "1980-01-01",
    "date:inception_upper": "1980-01-01",
    "iso:country": "GB",
    "wof:name": "ME14 3LN",
    "wof:placetype": "postalcode"
  },
  "geometry": {"coordinates":[0.597478,51.287665],"type":"Point"}
}
