{
  "type": "Feature",
  "properties": {
    "date:inception_lower": "2016-10-01",
    "date:inception_upper": "2016-10-01",
    "iso:country": "GB",
    "wof:name": "S71 5FY",
    "wof:placetype": "postalcode"
  },
  "geometry": {"coordinates":[-1.435082,53.565819],"type":"Point"}
}
