{
  "type": "Feature",
  "properties": {
    "iso:country": "GB",
    "wof:name": "BS22 6DN",
    "wof:placetype": "postalcode"
  },
  "geometry": {"coordinates":[-2.91393,51.36137],"type":"Point"}
}
