{
  "type": "Feature",
  "properties": {
    "iso:country":"GB",
    "wof:name":"BS22 6DN",
    "wof:placetype":"postalcode"
},
  "geometry": {"coordinates":[-2.91388178075363,51.36137335358882],"type":"Point"}
}