{
  "type": "Feature",
  "properties": {
    "iso:country":"GB",
    "wof:name":"SM2 5SJ",
    "wof:placetype":"postalcode"
},
  "geometry": {"coordinates":[-0.19169982448709,51.35268653927882],"type":"Point"}
}