{
  "type": "Feature",
  "properties": {
    "iso:country":"GB",
    "wof:name":"S35 9YJ",
    "wof:placetype":"postalcode"
},
  "geometry": {"coordinates":[-1.46171181764119,53.43609445031421],"type":"Point"}
}