{
  "type": "Feature",
  "properties": {
    "iso:country":"GB",
    "wof:name":"CF71 7PJ",
    "wof:placetype":"postalcode"
},
  "geometry": {"coordinates":[-3.43922891853232,51.43814126073732],"type":"Point"}
}