{
  "type": "Feature",
  "properties": {
    "date:inception_lower":"1980-01-01",
    "date:inception_upper":"1980-01-31",
    "iso:country":"GB",
    "wof:name":"WA12 9LW",
    "wof:placetype":"postalcode"
},
  "geometry": {"coordinates":[-2.64114,53.451027],"type":"Point"}
}