{
  "type": "Feature",
  "properties": {
    "iso:country":"GB",
    "wof:name":"SK15 3EY",
    "wof:placetype":"postalcode"
},
  "geometry": {"coordinates":[-2.02966887991284,53.49200604616286],"type":"Point"}
}