{
  "type": "Feature",
  "properties": {
    "iso:country":"GB",
    "wof:name":"WF4 1DQ",
    "wof:placetype":"postalcode"
},
  "geometry": {"coordinates":[-1.41150736410725,53.67035781890691],"type":"Point"}
}