{
  "type": "Feature",
  "properties": {
    "date:inception_lower": "2001-12-01",
    "date:inception_upper": "2001-12-01",
    "iso:country": "GB",
    "wof:name": "BN7 2UW",
    "wof:placetype": "postalcode"
  },
  "geometry": {"coordinates":[0.018393,50.869609],"type":"Point"}
}
