{
  "type": "Feature",
  "properties": {
    "iso:country": "GB",
    "wof:name": "G77 6DD",
    "wof:placetype": "postalcode"
  },
  "geometry": {"coordinates":[-4.34522,55.771762],"type":"Point"}
}
