{
  "type": "Feature",
  "properties": {
    "iso:country":"GB",
    "wof:name":"G77 6DD",
    "wof:placetype":"postalcode"
},
  "geometry": {"coordinates":[-4.34522020036291,55.77176190416122],"type":"Point"}
}