{
  "type": "Feature",
  "properties": {
    "iso:country":"GB",
    "wof:name":"MK42 7EP",
    "wof:placetype":"postalcode"
},
  "geometry": {"coordinates":[-0.50079114637287,52.11395390042201],"type":"Point"}
}