{
  "type": "Feature",
  "properties": {
    "iso:country":"GB",
    "wof:name":"LL28 5BY",
    "wof:placetype":"postalcode"
},
  "geometry": {"coordinates":[-3.76146201448877,53.29569529916029],"type":"Point"}
}