{
  "type": "Feature",
  "properties": {
    "iso:country":"GB",
    "wof:name":"WD24 5SJ",
    "wof:placetype":"postalcode"
},
  "geometry": {"coordinates":[-0.41082986579133,51.68341440400017],"type":"Point"}
}