{
  "type": "Feature",
  "properties": {
    "date:inception_lower": "2000-12-01",
    "date:inception_upper": "2000-12-01",
    "iso:country": "GB",
    "wof:name": "WD24 5SJ",
    "wof:placetype": "postalcode"
  },
  "geometry": {"coordinates":[-0.41083,51.683414],"type":"Point"}
}
