{
  "type": "Feature",
  "properties": {
    "iso:country":"GB",
    "wof:name":"CT6 8QR",
    "wof:placetype":"postalcode"
},
  "geometry": {"coordinates":[1.11361666937171,51.36692231833041],"type":"Point"}
}