{
  "type": "Feature",
  "properties": {
    "date:inception_lower": "1980-10-01",
    "date:inception_upper": "1980-10-01",
    "iso:country": "GB",
    "wof:name": "G66 5QS",
    "wof:placetype": "postalcode"
  },
  "geometry": {"coordinates":[-4.147934,55.920405],"type":"Point"}
}
