{
  "type": "Feature",
  "properties": {
    "iso:country": "GB",
    "wof:name": "SS7 1SL",
    "wof:placetype": "postalcode"
  },
  "geometry": {"coordinates":[0.591967,51.559809],"type":"Point"}
}
