{
  "type": "Feature",
  "properties": {
    "iso:country":"GB",
    "wof:name":"SS7 1SL",
    "wof:placetype":"postalcode"
},
  "geometry": {"coordinates":[0.59196680439687,51.55980860411379],"type":"Point"}
}