{
  "type": "Feature",
  "properties": {
    "date:inception_lower":"1991-09-01",
    "date:inception_upper":"1991-09-30",
    "iso:country":"GB",
    "wof:name":"HU11 5JE",
    "wof:placetype":"postalcode"
},
  "geometry": {"coordinates":[-0.285984,53.862767],"type":"Point"}
}