{
  "type": "Feature",
  "properties": {
    "iso:country":"GB",
    "wof:name":"HU11 5JE",
    "wof:placetype":"postalcode"
},
  "geometry": {"coordinates":[-0.28598400940521,53.86276687251654],"type":"Point"}
}