{
  "type": "Feature",
  "properties": {
    "iso:country": "GB",
    "wof:name": "HU11 5JE",
    "wof:placetype": "postalcode"
  },
  "geometry": {"coordinates":[-0.285984,53.862767],"type":"Point"}
}
