{
  "type": "Feature",
  "properties": {
    "iso:country":"GB",
    "wof:name":"TS29 6HF",
    "wof:placetype":"postalcode"
},
  "geometry": {"coordinates":[-1.42650255844549,54.71192062306677],"type":"Point"}
}