{
  "type": "Feature",
  "properties": {
    "iso:country": "GB",
    "wof:name": "TS29 6HF",
    "wof:placetype": "postalcode"
  },
  "geometry": {"coordinates":[-1.426503,54.711921],"type":"Point"}
}
