{
  "type": "Feature",
  "properties": {
    "iso:country":"GB",
    "wof:name":"EH20 9SB",
    "wof:placetype":"postalcode"
},
  "geometry": {"coordinates":[-3.13932721652144,55.87853452175548],"type":"Point"}
}