{
  "type": "Feature",
  "properties": {
    "iso:country": "GB",
    "wof:name": "EH20 9SB",
    "wof:placetype": "postalcode"
  },
  "geometry": {"coordinates":[-3.139327,55.878535],"type":"Point"}
}
