{
  "type": "Feature",
  "properties": {
    "iso:country": "GB",
    "wof:name": "SP7 0JY",
    "wof:placetype": "postalcode"
  },
  "geometry": {"coordinates":[-2.226535,50.965631],"type":"Point"}
}
