{
  "type": "Feature",
  "properties": {
    "date:inception_lower":"1980-01-01",
    "date:inception_upper":"1980-01-31",
    "iso:country":"GB",
    "wof:name":"KT11 1DJ",
    "wof:placetype":"postalcode"
},
  "geometry": {"coordinates":[-0.427189,51.333595],"type":"Point"}
}