{
  "type": "Feature",
  "properties": {
    "iso:country": "GB",
    "wof:name": "NE26 1RT",
    "wof:placetype": "postalcode"
  },
  "geometry": {"coordinates":[-1.452338,55.050397],"type":"Point"}
}
