{
  "type": "Feature",
  "properties": {
    "iso:country": "GB",
    "wof:name": "S6 4AJ",
    "wof:placetype": "postalcode"
  },
  "geometry": {"coordinates":[-1.513046,53.414589],"type":"Point"}
}
