{
  "type": "Feature",
  "properties": {
    "iso:country":"GB",
    "wof:name":"S6 4AJ",
    "wof:placetype":"postalcode"
},
  "geometry": {"coordinates":[-1.51304624419491,53.41458914996327],"type":"Point"}
}