{
  "type": "Feature",
  "properties": {
    "date:inception_lower": "1997-06-01",
    "date:inception_upper": "1997-06-01",
    "iso:country": "GB",
    "wof:name": "MK1 1SF",
    "wof:placetype": "postalcode"
  },
  "geometry": {"coordinates":[-0.720719,52.009992],"type":"Point"}
}
