{
  "type": "Feature",
  "properties": {
    "date:inception_lower": "1990-07-01",
    "date:inception_upper": "1990-07-01",
    "iso:country": "GB",
    "wof:name": "OX10 7JX",
    "wof:placetype": "postalcode"
  },
  "geometry": {"coordinates":[-1.156036,51.637722],"type":"Point"}
}
