{
  "type": "Feature",
  "properties": {
    "iso:country":"GB",
    "wof:name":"BL6 7HL",
    "wof:placetype":"postalcode"
},
  "geometry": {"coordinates":[-2.54252403114382,53.6019645622335],"type":"Point"}
}