{
  "type": "Feature",
  "properties": {
    "iso:country":"GB",
    "wof:name":"DY5 2AP",
    "wof:placetype":"postalcode"
},
  "geometry": {"coordinates":[-2.10046972795576,52.47008434240517],"type":"Point"}
}