{
  "type": "Feature",
  "properties": {
    "iso:country": "GB",
    "wof:name": "DY5 2AP",
    "wof:placetype": "postalcode"
  },
  "geometry": {"coordinates":[-2.100419,52.47009],"type":"Point"}
}
