{
  "type": "Feature",
  "properties": {
    "date:inception_lower":"2007-08-01",
    "date:inception_upper":"2007-08-31",
    "iso:country":"GB",
    "wof:name":"BA8 0AU",
    "wof:placetype":"postalcode"
},
  "geometry": {"coordinates":[-2.39714,50.975756],"type":"Point"}
}