{
  "type": "Feature",
  "properties": {
    "date:inception_lower": "2008-02-01",
    "date:inception_upper": "2008-02-01",
    "iso:country": "GB",
    "wof:name": "S5 6BE",
    "wof:placetype": "postalcode"
  },
  "geometry": {"coordinates":[-1.431498,53.417168],"type":"Point"}
}
