{
  "type": "Feature",
  "properties": {
    "iso:country":"GB",
    "wof:name":"RM13 7AD",
    "wof:placetype":"postalcode"
},
  "geometry": {"coordinates":[0.18824344819813,51.53181116613121],"type":"Point"}
}