{
  "type": "Feature",
  "properties": {
    "date:inception_lower": "1980-01-01",
    "date:inception_upper": "1980-01-01",
    "iso:country": "GB",
    "wof:name": "RM13 7AD",
    "wof:placetype": "postalcode"
  },
  "geometry": {"coordinates":[0.188404,51.531855],"type":"Point"}
}
