{
  "type": "Feature",
  "properties": {
    "iso:country": "GB",
    "wof:name": "RM13 7AD",
    "wof:placetype": "postalcode"
  },
  "geometry": {"coordinates":[0.188404,51.531855],"type":"Point"}
}
