{
  "type": "Feature",
  "properties": {
    "iso:country": "GB",
    "wof:name": "RG12 8HN",
    "wof:placetype": "postalcode"
  },
  "geometry": {"coordinates":[-0.778144,51.416391],"type":"Point"}
}
