{
  "type": "Feature",
  "properties": {
    "iso:country":"GB",
    "wof:name":"WR5 3FB",
    "wof:placetype":"postalcode"
},
  "geometry": {"coordinates":[-2.22174307883438,52.18054198474391],"type":"Point"}
}