{
  "type": "Feature",
  "properties": {
    "iso:country": "GB",
    "wof:name": "KA19 8BF",
    "wof:placetype": "postalcode"
  },
  "geometry": {"coordinates":[-4.682029,55.358789],"type":"Point"}
}
