{
  "type": "Feature",
  "properties": {
    "iso:country":"GB",
    "wof:name":"LA7 7PF",
    "wof:placetype":"postalcode"
},
  "geometry": {"coordinates":[-2.70772981892754,54.23674032387689],"type":"Point"}
}