{
  "type": "Feature",
  "properties": {
    "iso:country": "GB",
    "wof:name": "PE25 3LN",
    "wof:placetype": "postalcode"
  },
  "geometry": {"coordinates":[0.337538,53.143565],"type":"Point"}
}
