{
  "type": "Feature",
  "properties": {
    "iso:country":"GB",
    "wof:name":"NR14 7LH",
    "wof:placetype":"postalcode"
},
  "geometry": {"coordinates":[1.34791832708628,52.56127704664814],"type":"Point"}
}