{
  "type": "Feature",
  "properties": {
    "date:inception_lower":"1980-01-01",
    "date:inception_upper":"1980-01-31",
    "iso:country":"GB",
    "wof:name":"FK7 8AD",
    "wof:placetype":"postalcode"
},
  "geometry": {"coordinates":[-3.901781,56.088017],"type":"Point"}
}