{
  "type": "Feature",
  "properties": {
    "date:inception_lower": "1985-10-01",
    "date:inception_upper": "1985-10-01",
    "iso:country": "GB",
    "wof:name": "NG24 3JJ",
    "wof:placetype": "postalcode"
  },
  "geometry": {"coordinates":[-0.801803,53.029685],"type":"Point"}
}
