{
  "type": "Feature",
  "properties": {
    "iso:country":"GB",
    "wof:name":"SY2 5AE",
    "wof:placetype":"postalcode"
},
  "geometry": {"coordinates":[-2.73923344270802,52.70823518759281],"type":"Point"}
}