{
  "type": "Feature",
  "properties": {
    "date:inception_lower": "1980-01-01",
    "date:inception_upper": "1980-01-01",
    "iso:country": "GB",
    "wof:name": "SY2 5AE",
    "wof:placetype": "postalcode"
  },
  "geometry": {"coordinates":[-2.739261,52.70824],"type":"Point"}
}
