{
  "type": "Feature",
  "properties": {
    "date:inception_lower": "1980-01-01",
    "date:inception_upper": "1980-01-01",
    "iso:country": "GB",
    "wof:name": "DL1 1JU",
    "wof:placetype": "postalcode"
  },
  "geometry": {"coordinates":[-1.54525,54.530495],"type":"Point"}
}
