{
  "type": "Feature",
  "properties": {
    "iso:country": "GB",
    "wof:name": "AB45 3XU",
    "wof:placetype": "postalcode"
  },
  "geometry": {"coordinates":[-2.591125,57.578506],"type":"Point"}
}
