{
  "type": "Feature",
  "properties": {
    "iso:country":"GB",
    "wof:name":"AB45 3XU",
    "wof:placetype":"postalcode"
},
  "geometry": {"coordinates":[-2.59340408173256,57.57591503288975],"type":"Point"}
}