{
  "type": "Feature",
  "properties": {
    "iso:country": "GB",
    "wof:name": "EH4 7AL",
    "wof:placetype": "postalcode"
  },
  "geometry": {"coordinates":[-3.273888,55.960045],"type":"Point"}
}
