{
  "type": "Feature",
  "properties": {
    "date:inception_lower":"1980-01-01",
    "date:inception_upper":"1980-01-31",
    "iso:country":"GB",
    "wof:name":"DN9 3LH",
    "wof:placetype":"postalcode"
},
  "geometry": {"coordinates":[-1.015526,53.489621],"type":"Point"}
}