{
  "type": "Feature",
  "properties": {
    "iso:country": "GB",
    "wof:name": "DN9 3LH",
    "wof:placetype": "postalcode"
  },
  "geometry": {"coordinates":[-1.015526,53.489621],"type":"Point"}
}
