{
  "type": "Feature",
  "properties": {
    "iso:country":"GB",
    "wof:name":"DN9 3LH",
    "wof:placetype":"postalcode"
},
  "geometry": {"coordinates":[-1.01552626963454,53.48962052477508],"type":"Point"}
}