{
  "type": "Feature",
  "properties": {
    "iso:country":"GB",
    "wof:name":"SE18 5HR",
    "wof:placetype":"postalcode"
},
  "geometry": {"coordinates":[0.05071086113204,51.49148194757707],"type":"Point"}
}