{
  "type": "Feature",
  "properties": {
    "date:inception_lower": "1980-01-01",
    "date:inception_upper": "1980-01-01",
    "iso:country": "GB",
    "wof:name": "SE18 5HR",
    "wof:placetype": "postalcode"
  },
  "geometry": {"coordinates":[0.050711,51.491482],"type":"Point"}
}
