{
  "type": "Feature",
  "properties": {
    "iso:country":"GB",
    "wof:name":"B19 1HB",
    "wof:placetype":"postalcode"
},
  "geometry": {"coordinates":[-1.91384740976846,52.50384432278128],"type":"Point"}
}