{
  "type": "Feature",
  "properties": {
    "iso:country":"GB",
    "wof:name":"NE23 7RF",
    "wof:placetype":"postalcode"
},
  "geometry": {"coordinates":[-1.58056480589828,55.06060362486437],"type":"Point"}
}