{
  "type": "Feature",
  "properties": {
    "date:inception_lower": "2020-01-01",
    "date:inception_upper": "2020-01-01",
    "iso:country": "GB",
    "wof:name": "PH2 1JP",
    "wof:placetype": "postalcode"
  },
  "geometry": {"coordinates":[-3.431814,56.380198],"type":"Point"}
}
