{
  "type": "Feature",
  "properties": {
    "iso:country": "GB",
    "wof:name": "SN7 7UT",
    "wof:placetype": "postalcode"
  },
  "geometry": {"coordinates":[-1.585161,51.649893],"type":"Point"}
}
