{
  "type": "Feature",
  "properties": {
    "iso:country":"GB",
    "wof:name":"SS14 1LU",
    "wof:placetype":"postalcode"
},
  "geometry": {"coordinates":[0.46614479380662,51.56952725479474],"type":"Point"}
}