{
  "type": "Feature",
  "properties": {
    "iso:country":"GB",
    "wof:name":"NR35 2DG",
    "wof:placetype":"postalcode"
},
  "geometry": {"coordinates":[1.39732815482118,52.47879627114781],"type":"Point"}
}