{
  "type": "Feature",
  "properties": {
    "date:inception_lower": "1980-01-01",
    "date:inception_upper": "1980-01-01",
    "iso:country": "GB",
    "wof:name": "PO30 3HG",
    "wof:placetype": "postalcode"
  },
  "geometry": {"coordinates":[-1.306036,50.639825],"type":"Point"}
}
