{
  "type": "Feature",
  "properties": {
    "iso:country":"GB",
    "wof:name":"PO30 3HG",
    "wof:placetype":"postalcode"
},
  "geometry": {"coordinates":[-1.30589247286226,50.63967365909288],"type":"Point"}
}