{
  "type": "Feature",
  "properties": {
    "iso:country": "GB",
    "wof:name": "PO30 3HG",
    "wof:placetype": "postalcode"
  },
  "geometry": {"coordinates":[-1.306036,50.639825],"type":"Point"}
}
