{
  "type": "Feature",
  "properties": {
    "date:inception_lower":"2006-07-01",
    "date:inception_upper":"2006-07-31",
    "iso:country":"GB",
    "wof:name":"DE4 4JN",
    "wof:placetype":"postalcode"
},
  "geometry": {"coordinates":[-1.624319,53.076929],"type":"Point"}
}