{
  "type": "Feature",
  "properties": {
    "iso:country":"GB",
    "wof:name":"PL7 4AW",
    "wof:placetype":"postalcode"
},
  "geometry": {"coordinates":[-4.05202643195806,50.39452924951448],"type":"Point"}
}