{
  "type": "Feature",
  "properties": {
    "date:inception_lower": "1980-01-01",
    "date:inception_upper": "1980-01-01",
    "iso:country": "GB",
    "wof:name": "PL7 4AW",
    "wof:placetype": "postalcode"
  },
  "geometry": {"coordinates":[-4.051915,50.39458],"type":"Point"}
}
