{
  "type": "Feature",
  "properties": {
    "iso:country":"GB",
    "wof:name":"PA10 2JQ",
    "wof:placetype":"postalcode"
},
  "geometry": {"coordinates":[-4.55407056509343,55.83538663419914],"type":"Point"}
}