{
  "type": "Feature",
  "properties": {
    "iso:country": "GB",
    "wof:name": "PE2 5QN",
    "wof:placetype": "postalcode"
  },
  "geometry": {"coordinates":[-0.28761,52.54484],"type":"Point"}
}
