{
  "type": "Feature",
  "properties": {
    "iso:country":"GB",
    "wof:name":"PE2 5QN",
    "wof:placetype":"postalcode"
},
  "geometry": {"coordinates":[-0.28760981052119,52.54484009660693],"type":"Point"}
}