{
  "type": "Feature",
  "properties": {
    "iso:country": "GB",
    "wof:name": "WA8 3XP",
    "wof:placetype": "postalcode"
  },
  "geometry": {"coordinates":[-2.687457,53.394976],"type":"Point"}
}
