{
  "type": "Feature",
  "properties": {
    "iso:country":"GB",
    "wof:name":"WA8 3XP",
    "wof:placetype":"postalcode"
},
  "geometry": {"coordinates":[-2.6874569963722,53.3949760661744],"type":"Point"}
}