{
  "type": "Feature",
  "properties": {
    "iso:country": "GB",
    "wof:name": "LA6 1EX",
    "wof:placetype": "postalcode"
  },
  "geometry": {"coordinates":[-2.759773,54.104763],"type":"Point"}
}
