{
  "type": "Feature",
  "properties": {
    "date:inception_lower":"2000-06-01",
    "date:inception_upper":"2000-06-30",
    "iso:country":"GB",
    "wof:name":"DA2 6QY",
    "wof:placetype":"postalcode"
},
  "geometry": {"coordinates":[0.262548,51.453079],"type":"Point"}
}