{
  "type": "Feature",
  "properties": {
    "iso:country":"GB",
    "wof:name":"DA2 6QY",
    "wof:placetype":"postalcode"
},
  "geometry": {"coordinates":[0.26254791431207,51.45307907900902],"type":"Point"}
}