{
  "type": "Feature",
  "properties": {
    "iso:country":"GB",
    "wof:name":"TQ2 5BU",
    "wof:placetype":"postalcode"
},
  "geometry": {"coordinates":[-3.53999499291152,50.47118566927713],"type":"Point"}
}