{
  "type": "Feature",
  "properties": {
    "iso:country":"GB",
    "wof:name":"HX1 2LX",
    "wof:placetype":"postalcode"
},
  "geometry": {"coordinates":[-1.85631018461344,53.71868841511371],"type":"Point"}
}