{
  "type": "Feature",
  "properties": {
    "iso:country": "GB",
    "wof:name": "HX1 2LX",
    "wof:placetype": "postalcode"
  },
  "geometry": {"coordinates":[-1.85631,53.718688],"type":"Point"}
}
