{
  "type": "Feature",
  "properties": {
    "iso:country": "GB",
    "wof:name": "HA7 3SR",
    "wof:placetype": "postalcode"
  },
  "geometry": {"coordinates":[-0.319582,51.612231],"type":"Point"}
}
