{
  "type": "Feature",
  "properties": {
    "iso:country":"GB",
    "wof:name":"HA7 3SR",
    "wof:placetype":"postalcode"
},
  "geometry": {"coordinates":[-0.31958196769998,51.61223073117247],"type":"Point"}
}