{
  "type": "Feature",
  "properties": {
    "date:inception_lower": "1980-01-01",
    "date:inception_upper": "1980-01-01",
    "iso:country": "GB",
    "wof:name": "HA7 3SR",
    "wof:placetype": "postalcode"
  },
  "geometry": {"coordinates":[-0.319582,51.612231],"type":"Point"}
}
