{
  "type": "Feature",
  "properties": {
    "iso:country":"GB",
    "wof:name":"LE4 6SD",
    "wof:placetype":"postalcode"
},
  "geometry": {"coordinates":[-1.10670901675624,52.65361616757801],"type":"Point"}
}