{
  "type": "Feature",
  "properties": {
    "iso:country": "GB",
    "wof:name": "LE4 6SD",
    "wof:placetype": "postalcode"
  },
  "geometry": {"coordinates":[-1.106709,52.653616],"type":"Point"}
}
