{
  "type": "Feature",
  "properties": {
    "iso:country":"GB",
    "wof:name":"ST5 7HU",
    "wof:placetype":"postalcode"
},
  "geometry": {"coordinates":[-2.24470946314922,53.03362718048596],"type":"Point"}
}