{
  "type": "Feature",
  "properties": {
    "date:inception_lower":"1980-01-01",
    "date:inception_upper":"1980-01-31",
    "iso:country":"GB",
    "wof:name":"ST5 7HU",
    "wof:placetype":"postalcode"
},
  "geometry": {"coordinates":[-2.245223,53.034731],"type":"Point"}
}