{
  "type": "Feature",
  "properties": {
    "date:inception_lower": "1980-01-01",
    "date:inception_upper": "1980-01-01",
    "iso:country": "GB",
    "wof:name": "ST5 7HU",
    "wof:placetype": "postalcode"
  },
  "geometry": {"coordinates":[-2.245747,53.035098],"type":"Point"}
}
