{
  "type": "Feature",
  "properties": {
    "date:inception_lower": "1980-01-01",
    "date:inception_upper": "1980-01-01",
    "iso:country": "GB",
    "wof:name": "DL10 6RW",
    "wof:placetype": "postalcode"
  },
  "geometry": {"coordinates":[-1.627184,54.446738],"type":"Point"}
}
