{
  "type": "Feature",
  "properties": {
    "iso:country": "GB",
    "wof:name": "DN14 0FX",
    "wof:placetype": "postalcode"
  },
  "geometry": {"coordinates":[-1.145643,53.706312],"type":"Point"}
}
