{
  "type": "Feature",
  "properties": {
    "date:inception_lower": "2019-09-01",
    "date:inception_upper": "2019-09-01",
    "iso:country": "GB",
    "wof:name": "DN14 0FX",
    "wof:placetype": "postalcode"
  },
  "geometry": {"coordinates":[-1.145643,53.706312],"type":"Point"}
}
