{
  "type": "Feature",
  "properties": {
    "iso:country":"GB",
    "wof:name":"BR6 7HS",
    "wof:placetype":"postalcode"
},
  "geometry": {"coordinates":[0.05977881695221,51.36464953654785],"type":"Point"}
}