{
  "type": "Feature",
  "properties": {
    "iso:country":"GB",
    "wof:name":"KA11 1BT",
    "wof:placetype":"postalcode"
},
  "geometry": {"coordinates":[-4.63743804432778,55.63086270211438],"type":"Point"}
}