{
  "type": "Feature",
  "properties": {
    "date:inception_lower": "2000-06-01",
    "date:inception_upper": "2000-06-01",
    "iso:country": "GB",
    "wof:name": "GU2 7QS",
    "wof:placetype": "postalcode"
  },
  "geometry": {"coordinates":[-0.600854,51.234553],"type":"Point"}
}
