{
  "type": "Feature",
  "properties": {
    "iso:country":"GB",
    "wof:name":"GU2 7QS",
    "wof:placetype":"postalcode"
},
  "geometry": {"coordinates":[-0.60085381720718,51.23455269423355],"type":"Point"}
}