{
  "type": "Feature",
  "properties": {
    "iso:country":"GB",
    "wof:name":"NG1 7JE",
    "wof:placetype":"postalcode"
},
  "geometry": {"coordinates":[-1.14449827773647,52.94975607602053],"type":"Point"}
}