{
  "type": "Feature",
  "properties": {
    "iso:country": "GB",
    "wof:name": "M21 7QE",
    "wof:placetype": "postalcode"
  },
  "geometry": {"coordinates":[-2.264782,53.421857],"type":"Point"}
}
