{
  "type": "Feature",
  "properties": {
    "iso:country":"GB",
    "wof:name":"M21 7QE",
    "wof:placetype":"postalcode"
},
  "geometry": {"coordinates":[-2.26478162118624,53.42185733269696],"type":"Point"}
}