{
  "type": "Feature",
  "properties": {
    "iso:country":"GB",
    "wof:name":"IP28 8RA",
    "wof:placetype":"postalcode"
},
  "geometry": {"coordinates":[0.46302006110469,52.36311239807534],"type":"Point"}
}