{
  "type": "Feature",
  "properties": {
    "iso:country":"GB",
    "wof:name":"SG8 9TF",
    "wof:placetype":"postalcode"
},
  "geometry": {"coordinates":[-0.00925156720714,52.04831219226174],"type":"Point"}
}