{
  "type": "Feature",
  "properties": {
    "date:inception_lower":"1980-01-01",
    "date:inception_upper":"1980-01-31",
    "iso:country":"GB",
    "wof:name":"CA13 0LL",
    "wof:placetype":"postalcode"
},
  "geometry": {"coordinates":[-3.433424,54.670274],"type":"Point"}
}