{
  "type": "Feature",
  "properties": {
    "iso:country": "GB",
    "wof:name": "CA13 0LL",
    "wof:placetype": "postalcode"
  },
  "geometry": {"coordinates":[-3.433424,54.670274],"type":"Point"}
}
