{
  "type": "Feature",
  "properties": {
    "date:inception_lower": "1996-06-01",
    "date:inception_upper": "1996-06-01",
    "iso:country": "GB",
    "wof:name": "AB53 4FN",
    "wof:placetype": "postalcode"
  },
  "geometry": {"coordinates":[-2.456299,57.540016],"type":"Point"}
}
