{
  "type": "Feature",
  "properties": {
    "iso:country":"GB",
    "wof:name":"SE20 7JS",
    "wof:placetype":"postalcode"
},
  "geometry": {"coordinates":[-0.04938971056537,51.41726452309872],"type":"Point"}
}