{
  "type": "Feature",
  "properties": {
    "iso:country":"GB",
    "wof:name":"IP7 7HX",
    "wof:placetype":"postalcode"
},
  "geometry": {"coordinates":[0.89272164314043,52.0937357933892],"type":"Point"}
}