{
  "type": "Feature",
  "properties": {
    "iso:country": "GB",
    "wof:name": "IP7 7HX",
    "wof:placetype": "postalcode"
  },
  "geometry": {"coordinates":[0.892722,52.093736],"type":"Point"}
}
