{
  "type": "Feature",
  "properties": {
    "iso:country": "GB",
    "wof:name": "CT3 4LU",
    "wof:placetype": "postalcode"
  },
  "geometry": {"coordinates":[1.166281,51.353201],"type":"Point"}
}
