{
  "type": "Feature",
  "properties": {
    "iso:country":"GB",
    "wof:name":"HG4 4NJ",
    "wof:placetype":"postalcode"
},
  "geometry": {"coordinates":[-1.76809639161141,54.22845927897901],"type":"Point"}
}