{
  "type": "Feature",
  "properties": {
    "iso:country": "GB",
    "wof:name": "SA19 8YY",
    "wof:placetype": "postalcode"
  },
  "geometry": {"coordinates":[-3.971166,52.059406],"type":"Point"}
}
