{
  "type": "Feature",
  "properties": {
    "date:inception_lower": "1980-01-01",
    "date:inception_upper": "1980-01-01",
    "iso:country": "GB",
    "wof:name": "SA19 8YY",
    "wof:placetype": "postalcode"
  },
  "geometry": {"coordinates":[-3.971514,52.06101],"type":"Point"}
}
