{
  "type": "Feature",
  "properties": {
    "iso:country":"GB",
    "wof:name":"GU3 2AB",
    "wof:placetype":"postalcode"
},
  "geometry": {"coordinates":[-0.6775906836531,51.24343002173224],"type":"Point"}
}