{
  "type": "Feature",
  "properties": {
    "date:inception_lower": "2015-06-01",
    "date:inception_upper": "2015-06-01",
    "iso:country": "GB",
    "wof:name": "GU3 2AB",
    "wof:placetype": "postalcode"
  },
  "geometry": {"coordinates":[-0.677208,51.243612],"type":"Point"}
}
