{
  "type": "Feature",
  "properties": {
    "iso:country": "GB",
    "wof:name": "GU3 2AB",
    "wof:placetype": "postalcode"
  },
  "geometry": {"coordinates":[-0.677591,51.24343],"type":"Point"}
}
