{
  "type": "Feature",
  "properties": {
    "iso:country":"GB",
    "wof:name":"ME11 5NB",
    "wof:placetype":"postalcode"
},
  "geometry": {"coordinates":[0.74440748204513,51.40780795690847],"type":"Point"}
}