{
  "type": "Feature",
  "properties": {
    "date:inception_lower":"1995-01-01",
    "date:inception_upper":"1995-01-31",
    "iso:country":"GB",
    "wof:name":"SK8 6SR",
    "wof:placetype":"postalcode"
},
  "geometry": {"coordinates":[-2.20566,53.368815],"type":"Point"}
}