{
  "type": "Feature",
  "properties": {
    "iso:country": "GB",
    "wof:name": "SK8 6SR",
    "wof:placetype": "postalcode"
  },
  "geometry": {"coordinates":[-2.20566,53.368815],"type":"Point"}
}
