{
  "type": "Feature",
  "properties": {
    "iso:country": "GB",
    "wof:name": "LL54 5DG",
    "wof:placetype": "postalcode"
  },
  "geometry": {"coordinates":[-4.322658,53.017781],"type":"Point"}
}
