{
  "type": "Feature",
  "properties": {
    "iso:country": "GB",
    "wof:name": "NR12 0NE",
    "wof:placetype": "postalcode"
  },
  "geometry": {"coordinates":[1.510448,52.836949],"type":"Point"}
}
