{
  "type": "Feature",
  "properties": {
    "iso:country":"GB",
    "wof:name":"NR12 0NE",
    "wof:placetype":"postalcode"
},
  "geometry": {"coordinates":[1.51033850732327,52.83693222437984],"type":"Point"}
}