{
  "type": "Feature",
  "properties": {
    "iso:country": "GB",
    "wof:name": "L14 6TR",
    "wof:placetype": "postalcode"
  },
  "geometry": {"coordinates":[-2.874861,53.409444],"type":"Point"}
}
