{
  "type": "Feature",
  "properties": {
    "date:inception_lower": "1980-01-01",
    "date:inception_upper": "1980-01-01",
    "iso:country": "GB",
    "wof:name": "GL51 7BJ",
    "wof:placetype": "postalcode"
  },
  "geometry": {"coordinates":[-2.105353,51.897002],"type":"Point"}
}
