{
  "type": "Feature",
  "properties": {
    "iso:country":"GB",
    "wof:name":"SL4 1RB",
    "wof:placetype":"postalcode"
},
  "geometry": {"coordinates":[-0.6100979220734,51.48354163664784],"type":"Point"}
}