{
  "type": "Feature",
  "properties": {
    "iso:country": "GB",
    "wof:name": "NN13 6GG",
    "wof:placetype": "postalcode"
  },
  "geometry": {"coordinates":[-1.150075,52.043623],"type":"Point"}
}
