{
  "type": "Feature",
  "properties": {
    "iso:country": "GB",
    "wof:name": "NN13 6GG",
    "wof:placetype": "postalcode"
  },
  "geometry": {"coordinates":[-1.149787,52.043459],"type":"Point"}
}
