{
  "type": "Feature",
  "properties": {
    "iso:country":"GB",
    "wof:name":"TA24 8LY",
    "wof:placetype":"postalcode"
},
  "geometry": {"coordinates":[-3.5936059263055,51.20619650935729],"type":"Point"}
}