{
  "type": "Feature",
  "properties": {
    "date:inception_lower": "1994-12-01",
    "date:inception_upper": "1994-12-01",
    "iso:country": "GB",
    "wof:name": "SA15 2BQ",
    "wof:placetype": "postalcode"
  },
  "geometry": {"coordinates":[-4.145906,51.66788],"type":"Point"}
}
