{
  "type": "Feature",
  "properties": {
    "date:inception_lower": "1990-02-01",
    "date:inception_upper": "1990-02-01",
    "iso:country": "GB",
    "wof:name": "S63 9BU",
    "wof:placetype": "postalcode"
  },
  "geometry": {"coordinates":[-1.317259,53.530375],"type":"Point"}
}
