{
  "type": "Feature",
  "properties": {
    "iso:country":"GB",
    "wof:name":"S63 9BU",
    "wof:placetype":"postalcode"
},
  "geometry": {"coordinates":[-1.31725947372197,53.53037517016209],"type":"Point"}
}