{
  "type": "Feature",
  "properties": {
    "iso:country":"GB",
    "wof:name":"CR8 5EF",
    "wof:placetype":"postalcode"
},
  "geometry": {"coordinates":[-0.10301849423796,51.31370303599927],"type":"Point"}
}