{
  "type": "Feature",
  "properties": {
    "iso:country": "GB",
    "wof:name": "SO31 5JG",
    "wof:placetype": "postalcode"
  },
  "geometry": {"coordinates":[-1.349561,50.875094],"type":"Point"}
}
