{
  "type": "Feature",
  "properties": {
    "iso:country": "GB",
    "wof:name": "BS4 1FB",
    "wof:placetype": "postalcode"
  },
  "geometry": {"coordinates":[-2.582252,51.420947],"type":"Point"}
}
