{
  "type": "Feature",
  "properties": {
    "date:inception_lower": "2019-06-01",
    "date:inception_upper": "2019-06-01",
    "iso:country": "GB",
    "wof:name": "BS4 1FB",
    "wof:placetype": "postalcode"
  },
  "geometry": {"coordinates":[-2.582252,51.420947],"type":"Point"}
}
