{
  "type": "Feature",
  "properties": {
    "iso:country":"GB",
    "wof:name":"CT11 9JY",
    "wof:placetype":"postalcode"
},
  "geometry": {"coordinates":[1.4142963148383,51.32905169281334],"type":"Point"}
}