{
  "type": "Feature",
  "properties": {
    "iso:country": "GB",
    "wof:name": "TN11 9RS",
    "wof:placetype": "postalcode"
  },
  "geometry": {"coordinates":[0.299747,51.247595],"type":"Point"}
}
