{
  "type": "Feature",
  "properties": {
    "date:inception_lower": "1980-01-01",
    "date:inception_upper": "1980-01-01",
    "iso:country": "GB",
    "wof:name": "TN11 9RS",
    "wof:placetype": "postalcode"
  },
  "geometry": {"coordinates":[0.29973,51.247541],"type":"Point"}
}
