{
  "type": "Feature",
  "properties": {
    "iso:country":"GB",
    "wof:name":"CT9 2UE",
    "wof:placetype":"postalcode"
},
  "geometry": {"coordinates":[1.40136425253006,51.38221199455833],"type":"Point"}
}