{
  "type": "Feature",
  "properties": {
    "iso:country": "GB",
    "wof:name": "PR7 5SU",
    "wof:placetype": "postalcode"
  },
  "geometry": {"coordinates":[-2.725231,53.646469],"type":"Point"}
}
