{
  "type": "Feature",
  "properties": {
    "iso:country":"GB",
    "wof:name":"PR7 5SU",
    "wof:placetype":"postalcode"
},
  "geometry": {"coordinates":[-2.72523142322579,53.64646885223699],"type":"Point"}
}