{
  "type": "Feature",
  "properties": {
    "iso:country": "GB",
    "wof:name": "SK9 5JD",
    "wof:placetype": "postalcode"
  },
  "geometry": {"coordinates":[-2.24111,53.323159],"type":"Point"}
}
