{
  "type": "Feature",
  "properties": {
    "date:inception_lower": "1980-01-01",
    "date:inception_upper": "1980-01-01",
    "iso:country": "GB",
    "wof:name": "B19 1HG",
    "wof:placetype": "postalcode"
  },
  "geometry": {"coordinates":[-1.912505,52.504563],"type":"Point"}
}
