{
  "type": "Feature",
  "properties": {
    "iso:country":"GB",
    "wof:name":"B19 1HG",
    "wof:placetype":"postalcode"
},
  "geometry": {"coordinates":[-1.91250536987821,52.50456253505491],"type":"Point"}
}