{
  "type": "Feature",
  "properties": {
    "iso:country":"GB",
    "wof:name":"LE67 2NT",
    "wof:placetype":"postalcode"
},
  "geometry": {"coordinates":[-1.39389497560611,52.72717965639935],"type":"Point"}
}