{
  "type": "Feature",
  "properties": {
    "iso:country":"GB",
    "wof:name":"LA3 3DW",
    "wof:placetype":"postalcode"
},
  "geometry": {"coordinates":[-2.85877472604062,54.05974246626745],"type":"Point"}
}