{
  "type": "Feature",
  "properties": {
    "date:inception_lower": "1980-01-01",
    "date:inception_upper": "1980-01-01",
    "iso:country": "GB",
    "wof:name": "HG1 4DN",
    "wof:placetype": "postalcode"
  },
  "geometry": {"coordinates":[-1.50365,54.01151],"type":"Point"}
}
