{
  "type": "Feature",
  "properties": {
    "iso:country":"GB",
    "wof:name":"HG1 4DN",
    "wof:placetype":"postalcode"
},
  "geometry": {"coordinates":[-1.50365050684178,54.01150972585005],"type":"Point"}
}