{
  "type": "Feature",
  "properties": {
    "iso:country": "GB",
    "wof:name": "YO18 7TH",
    "wof:placetype": "postalcode"
  },
  "geometry": {"coordinates":[-0.723488,54.231946],"type":"Point"}
}
