{
  "type": "Feature",
  "properties": {
    "iso:country":"GB",
    "wof:name":"WF17 0DN",
    "wof:placetype":"postalcode"
},
  "geometry": {"coordinates":[-1.65562398367304,53.73311952564147],"type":"Point"}
}