{
  "type": "Feature",
  "properties": {
    "iso:country":"GB",
    "wof:name":"MK43 0XZ",
    "wof:placetype":"postalcode"
},
  "geometry": {"coordinates":[-0.59642271357892,52.03385022951846],"type":"Point"}
}