{
  "type": "Feature",
  "properties": {
    "iso:country": "GB",
    "wof:name": "MK43 0XZ",
    "wof:placetype": "postalcode"
  },
  "geometry": {"coordinates":[-0.596423,52.03385],"type":"Point"}
}
