{
  "type": "Feature",
  "properties": {
    "date:inception_lower": "1980-01-01",
    "date:inception_upper": "1980-01-01",
    "iso:country": "GB",
    "wof:name": "MK43 0XZ",
    "wof:placetype": "postalcode"
  },
  "geometry": {"coordinates":[-0.596423,52.03385],"type":"Point"}
}
