{
  "type": "Feature",
  "properties": {
    "date:inception_lower": "2000-06-01",
    "date:inception_upper": "2000-06-01",
    "iso:country": "GB",
    "wof:name": "CA7 2JQ",
    "wof:placetype": "postalcode"
  },
  "geometry": {"coordinates":[-3.272545,54.736753],"type":"Point"}
}
