{
  "type": "Feature",
  "properties": {
    "iso:country": "GB",
    "wof:name": "CA7 2JQ",
    "wof:placetype": "postalcode"
  },
  "geometry": {"coordinates":[-3.272572,54.736719],"type":"Point"}
}
