{
  "type": "Feature",
  "properties": {
    "iso:country":"GB",
    "wof:name":"ST5 6HA",
    "wof:placetype":"postalcode"
},
  "geometry": {"coordinates":[-2.24428535239005,53.0166475512272],"type":"Point"}
}