{
  "type": "Feature",
  "properties": {
    "date:inception_lower": "1995-07-01",
    "date:inception_upper": "1995-07-01",
    "iso:country": "GB",
    "wof:name": "RG42 4UF",
    "wof:placetype": "postalcode"
  },
  "geometry": {"coordinates":[-0.772928,51.424366],"type":"Point"}
}
