{
  "type": "Feature",
  "properties": {
    "iso:country":"GB",
    "wof:name":"RG42 4UF",
    "wof:placetype":"postalcode"
},
  "geometry": {"coordinates":[-0.77292797772809,51.42436550765086],"type":"Point"}
}