{
  "type": "Feature",
  "properties": {
    "iso:country": "GB",
    "wof:name": "SN10 4EY",
    "wof:placetype": "postalcode"
  },
  "geometry": {"coordinates":[-1.998029,51.283519],"type":"Point"}
}
