{
  "type": "Feature",
  "properties": {
    "iso:country":"GB",
    "wof:name":"SN10 4EY",
    "wof:placetype":"postalcode"
},
  "geometry": {"coordinates":[-1.99802908836301,51.28351934691674],"type":"Point"}
}