{
  "type": "Feature",
  "properties": {
    "iso:country": "GB",
    "wof:name": "CT18 8EX",
    "wof:placetype": "postalcode"
  },
  "geometry": {"coordinates":[1.080821,51.129602],"type":"Point"}
}
