{
  "type": "Feature",
  "properties": {
    "iso:country":"GB",
    "wof:name":"LE10 1LY",
    "wof:placetype":"postalcode"
},
  "geometry": {"coordinates":[-1.35865322132129,52.54725101751716],"type":"Point"}
}