{
  "type": "Feature",
  "properties": {
    "iso:country":"GB",
    "wof:name":"BR1 4BF",
    "wof:placetype":"postalcode"
},
  "geometry": {"coordinates":[0.01677273878523,51.41607263689744],"type":"Point"}
}