{
  "type": "Feature",
  "properties": {
    "iso:country":"GB",
    "wof:name":"DN14 9LF",
    "wof:placetype":"postalcode"
},
  "geometry": {"coordinates":[-1.027910746916,53.68933283389555],"type":"Point"}
}