{
  "type": "Feature",
  "properties": {
    "iso:country":"GB",
    "wof:name":"BS32 8HJ",
    "wof:placetype":"postalcode"
},
  "geometry": {"coordinates":[-2.55338809988552,51.53274616455717],"type":"Point"}
}