{
  "type": "Feature",
  "properties": {
    "date:inception_lower": "1997-12-01",
    "date:inception_upper": "1997-12-01",
    "iso:country": "GB",
    "wof:name": "BS32 8HJ",
    "wof:placetype": "postalcode"
  },
  "geometry": {"coordinates":[-2.553404,51.532763],"type":"Point"}
}
