{
  "type": "Feature",
  "properties": {
    "iso:country":"GB",
    "wof:name":"CV36 4DG",
    "wof:placetype":"postalcode"
},
  "geometry": {"coordinates":[-1.6329361962107,52.06352829226423],"type":"Point"}
}