{
  "type": "Feature",
  "properties": {
    "iso:country": "GB",
    "wof:name": "CV36 4DG",
    "wof:placetype": "postalcode"
  },
  "geometry": {"coordinates":[-1.632936,52.063528],"type":"Point"}
}
