{
  "type": "Feature",
  "properties": {
    "iso:country":"GB",
    "wof:name":"WA9 4WB",
    "wof:placetype":"postalcode"
},
  "geometry": {"coordinates":[-2.72126104455681,53.41796756247464],"type":"Point"}
}