{
  "type": "Feature",
  "properties": {
    "iso:country": "GB",
    "wof:name": "WA9 4WB",
    "wof:placetype": "postalcode"
  },
  "geometry": {"coordinates":[-2.721261,53.417968],"type":"Point"}
}
