{
  "type": "Feature",
  "properties": {
    "iso:country":"GB",
    "wof:name":"RG30 4LY",
    "wof:placetype":"postalcode"
},
  "geometry": {"coordinates":[-1.02399154860193,51.45566908625133],"type":"Point"}
}