{
  "type": "Feature",
  "properties": {
    "iso:country":"GB",
    "wof:name":"WA9 5QA",
    "wof:placetype":"postalcode"
},
  "geometry": {"coordinates":[-2.75692741392128,53.43441189573738],"type":"Point"}
}