{
  "type": "Feature",
  "properties": {
    "iso:country":"GB",
    "wof:name":"SG1 5RJ",
    "wof:placetype":"postalcode"
},
  "geometry": {"coordinates":[-0.17577363148841,51.91988945963983],"type":"Point"}
}