{
  "type": "Feature",
  "properties": {
    "date:inception_lower": "1980-01-01",
    "date:inception_upper": "1980-01-01",
    "iso:country": "GB",
    "wof:name": "SG1 5RJ",
    "wof:placetype": "postalcode"
  },
  "geometry": {"coordinates":[-0.175774,51.919889],"type":"Point"}
}
