{
  "type": "Feature",
  "properties": {
    "iso:country": "GB",
    "wof:name": "ST13 6LJ",
    "wof:placetype": "postalcode"
  },
  "geometry": {"coordinates":[-2.015686,53.107022],"type":"Point"}
}
