{
  "type": "Feature",
  "properties": {
    "iso:country":"GB",
    "wof:name":"CV12 8EH",
    "wof:placetype":"postalcode"
},
  "geometry": {"coordinates":[-1.479134019311,52.48120823949699],"type":"Point"}
}