{
  "type": "Feature",
  "properties": {
    "iso:country": "GB",
    "wof:name": "YO7 1RP",
    "wof:placetype": "postalcode"
  },
  "geometry": {"coordinates":[-1.35019,54.227381],"type":"Point"}
}
