{
  "type": "Feature",
  "properties": {
    "iso:country":"GB",
    "wof:name":"LS17 9NB",
    "wof:placetype":"postalcode"
},
  "geometry": {"coordinates":[-1.4849117577675,53.85807108900897],"type":"Point"}
}