{
  "type": "Feature",
  "properties": {
    "iso:country": "GB",
    "wof:name": "LS17 9NB",
    "wof:placetype": "postalcode"
  },
  "geometry": {"coordinates":[-1.484912,53.858071],"type":"Point"}
}
