{
  "type": "Feature",
  "properties": {
    "iso:country":"GB",
    "wof:name":"BN9 0QE",
    "wof:placetype":"postalcode"
},
  "geometry": {"coordinates":[0.06540196984688,50.80447272464873],"type":"Point"}
}