{
  "type": "Feature",
  "properties": {
    "date:inception_lower":"1980-01-01",
    "date:inception_upper":"1980-01-31",
    "iso:country":"GB",
    "wof:name":"BN9 0QE",
    "wof:placetype":"postalcode"
},
  "geometry": {"coordinates":[0.065402,50.804473],"type":"Point"}
}