{
  "type": "Feature",
  "properties": {
    "iso:country": "GB",
    "wof:name": "BN9 0QE",
    "wof:placetype": "postalcode"
  },
  "geometry": {"coordinates":[0.065402,50.804473],"type":"Point"}
}
