{
  "type": "Feature",
  "properties": {
    "date:inception_lower": "2018-05-01",
    "date:inception_upper": "2018-05-01",
    "iso:country": "GB",
    "wof:name": "CR0 3FD",
    "wof:placetype": "postalcode"
  },
  "geometry": {"coordinates":[-0.112093,51.377941],"type":"Point"}
}
