{
  "type": "Feature",
  "properties": {
    "date:inception_lower":"2013-07-01",
    "date:inception_upper":"2013-07-31",
    "iso:country":"GB",
    "wof:name":"TR27 4DT",
    "wof:placetype":"postalcode"
},
  "geometry": {"coordinates":[-5.407613,50.185291],"type":"Point"}
}