{
  "type": "Feature",
  "properties": {
    "iso:country": "GB",
    "wof:name": "NE5 2QP",
    "wof:placetype": "postalcode"
  },
  "geometry": {"coordinates":[-1.667276,54.983959],"type":"Point"}
}
