{
  "type": "Feature",
  "properties": {
    "date:inception_lower":"1980-01-01",
    "date:inception_upper":"1980-01-31",
    "iso:country":"GB",
    "wof:name":"NE5 2QP",
    "wof:placetype":"postalcode"
},
  "geometry": {"coordinates":[-1.667276,54.983959],"type":"Point"}
}