{
  "type": "Feature",
  "properties": {
    "iso:country":"GB",
    "wof:name":"NE5 2QP",
    "wof:placetype":"postalcode"
},
  "geometry": {"coordinates":[-1.66727607236418,54.98395859096711],"type":"Point"}
}