{
  "type": "Feature",
  "properties": {
    "iso:country":"GB",
    "wof:name":"SO17 1UH",
    "wof:placetype":"postalcode"
},
  "geometry": {"coordinates":[-1.40300214663564,50.92730238534276],"type":"Point"}
}