{
  "type": "Feature",
  "properties": {
    "iso:country":"GB",
    "wof:name":"WR15 8JJ",
    "wof:placetype":"postalcode"
},
  "geometry": {"coordinates":[-2.44837990083018,52.31190369819136],"type":"Point"}
}