{
  "type": "Feature",
  "properties": {
    "iso:country":"GB",
    "wof:name":"RG7 5UN",
    "wof:placetype":"postalcode"
},
  "geometry": {"coordinates":[-1.20557337021181,51.40559773127768],"type":"Point"}
}