{
  "type": "Feature",
  "properties": {
    "date:inception_lower": "1980-01-01",
    "date:inception_upper": "1980-01-01",
    "iso:country": "GB",
    "wof:name": "RG7 5UN",
    "wof:placetype": "postalcode"
  },
  "geometry": {"coordinates":[-1.205554,51.405598],"type":"Point"}
}
