{
  "type": "Feature",
  "properties": {
    "iso:country":"GB",
    "wof:name":"PA16 7LJ",
    "wof:placetype":"postalcode"
},
  "geometry": {"coordinates":[-4.80430853790144,55.94247346507628],"type":"Point"}
}