{
  "type": "Feature",
  "properties": {
    "date:inception_lower": "1980-01-01",
    "date:inception_upper": "1980-01-01",
    "iso:country": "GB",
    "wof:name": "PA16 7LJ",
    "wof:placetype": "postalcode"
  },
  "geometry": {"coordinates":[-4.804257,55.942477],"type":"Point"}
}
