{
  "type": "Feature",
  "properties": {
    "date:inception_lower": "1980-01-01",
    "date:inception_upper": "1980-01-01",
    "iso:country": "GB",
    "wof:name": "NG6 9AU",
    "wof:placetype": "postalcode"
  },
  "geometry": {"coordinates":[-1.191603,52.99453],"type":"Point"}
}
