{
  "type": "Feature",
  "properties": {
    "iso:country": "GB",
    "wof:name": "LN1 2RF",
    "wof:placetype": "postalcode"
  },
  "geometry": {"coordinates":[-0.559428,53.261265],"type":"Point"}
}
