{
  "type": "Feature",
  "properties": {
    "iso:country":"GB",
    "wof:name":"LN1 2RF",
    "wof:placetype":"postalcode"
},
  "geometry": {"coordinates":[-0.55942851540257,53.26126545258777],"type":"Point"}
}