{
  "type": "Feature",
  "properties": {
    "date:inception_lower": "1980-01-01",
    "date:inception_upper": "1980-01-01",
    "iso:country": "GB",
    "wof:name": "LN1 2RF",
    "wof:placetype": "postalcode"
  },
  "geometry": {"coordinates":[-0.559428,53.261265],"type":"Point"}
}
