{
  "type": "Feature",
  "properties": {
    "iso:country": "GB",
    "wof:name": "MK18 1NJ",
    "wof:placetype": "postalcode"
  },
  "geometry": {"coordinates":[-0.987215,52.000006],"type":"Point"}
}
