{
  "type": "Feature",
  "properties": {
    "iso:country":"GB",
    "wof:name":"NE40 3SW",
    "wof:placetype":"postalcode"
},
  "geometry": {"coordinates":[-1.79214193180882,54.97826891943398],"type":"Point"}
}