{
  "type": "Feature",
  "properties": {
    "iso:country": "GB",
    "wof:name": "DD4 6QU",
    "wof:placetype": "postalcode"
  },
  "geometry": {"coordinates":[-2.961358,56.468807],"type":"Point"}
}
