{
  "type": "Feature",
  "properties": {
    "iso:country":"GB",
    "wof:name":"DD4 6QU",
    "wof:placetype":"postalcode"
},
  "geometry": {"coordinates":[-2.96135834287816,56.46880702191653],"type":"Point"}
}