{
  "type": "Feature",
  "properties": {
    "iso:country":"GB",
    "wof:name":"WS3 3XZ",
    "wof:placetype":"postalcode"
},
  "geometry": {"coordinates":[-2.01431860530365,52.63278865093018],"type":"Point"}
}