{
  "type": "Feature",
  "properties": {
    "iso:country":"GB",
    "wof:name":"ML4 1PW",
    "wof:placetype":"postalcode"
},
  "geometry": {"coordinates":[-4.01431715296468,55.81864018104519],"type":"Point"}
}