{
  "type": "Feature",
  "properties": {
    "iso:country":"GB",
    "wof:name":"DL5 4JA",
    "wof:placetype":"postalcode"
},
  "geometry": {"coordinates":[-1.56919902000165,54.62466606653688],"type":"Point"}
}