{
  "type": "Feature",
  "properties": {
    "iso:country":"GB",
    "wof:name":"LN8 3EY",
    "wof:placetype":"postalcode"
},
  "geometry": {"coordinates":[-0.32989579438886,53.3914994750085],"type":"Point"}
}