{
  "type": "Feature",
  "properties": {
    "iso:country": "GB",
    "wof:name": "KY1 2AT",
    "wof:placetype": "postalcode"
  },
  "geometry": {"coordinates":[-3.129251,56.125131],"type":"Point"}
}
