{
  "type": "Feature",
  "properties": {
    "iso:country":"GB",
    "wof:name":"BD2 4QU",
    "wof:placetype":"postalcode"
},
  "geometry": {"coordinates":[-1.7300069583878,53.80642761901299],"type":"Point"}
}