{
  "type": "Feature",
  "properties": {
    "iso:country":"GB",
    "wof:name":"ML3 7ER",
    "wof:placetype":"postalcode"
},
  "geometry": {"coordinates":[-4.03416335574707,55.77315345614796],"type":"Point"}
}