{
  "type": "Feature",
  "properties": {
    "date:inception_lower": "2021-03-01",
    "date:inception_upper": "2021-03-01",
    "iso:country": "GB",
    "wof:name": "NN17 5GQ",
    "wof:placetype": "postalcode"
  },
  "geometry": {"coordinates":[-0.638356,52.500511],"type":"Point"}
}
