{
  "type": "Feature",
  "properties": {
    "iso:country": "GB",
    "wof:name": "SN25 2RB",
    "wof:placetype": "postalcode"
  },
  "geometry": {"coordinates":[-1.830203,51.609513],"type":"Point"}
}
