{
  "type": "Feature",
  "properties": {
    "iso:country": "GB",
    "wof:name": "RH20 2AF",
    "wof:placetype": "postalcode"
  },
  "geometry": {"coordinates":[-0.507496,50.959025],"type":"Point"}
}
