{
  "type": "Feature",
  "properties": {
    "iso:country":"GB",
    "wof:name":"PH2 8JS",
    "wof:placetype":"postalcode"
},
  "geometry": {"coordinates":[-3.4328975948036,56.39348328910555],"type":"Point"}
}