{
  "type": "Feature",
  "properties": {
    "iso:country":"GB",
    "wof:name":"BS8 1DP",
    "wof:placetype":"postalcode"
},
  "geometry": {"coordinates":[-2.60912109147766,51.45374857613454],"type":"Point"}
}