{
  "type": "Feature",
  "properties": {
    "iso:country": "GB",
    "wof:name": "BS8 1DP",
    "wof:placetype": "postalcode"
  },
  "geometry": {"coordinates":[-2.609121,51.453749],"type":"Point"}
}
