{
  "type": "Feature",
  "properties": {
    "iso:country":"GB",
    "wof:name":"CH4 8DQ",
    "wof:placetype":"postalcode"
},
  "geometry": {"coordinates":[-2.91782465439602,53.17708726925506],"type":"Point"}
}