{
  "type": "Feature",
  "properties": {
    "iso:country": "GB",
    "wof:name": "CH4 8DQ",
    "wof:placetype": "postalcode"
  },
  "geometry": {"coordinates":[-2.917825,53.177087],"type":"Point"}
}
