{
  "type": "Feature",
  "properties": {
    "iso:country":"GB",
    "wof:name":"M6 5HL",
    "wof:placetype":"postalcode"
},
  "geometry": {"coordinates":[-2.28290441763864,53.48834865879934],"type":"Point"}
}