{
  "type": "Feature",
  "properties": {
    "iso:country": "GB",
    "wof:name": "SA33 5HT",
    "wof:placetype": "postalcode"
  },
  "geometry": {"coordinates":[-4.421092,51.812665],"type":"Point"}
}
