{
  "type": "Feature",
  "properties": {
    "iso:country": "GB",
    "wof:name": "MK46 5QJ",
    "wof:placetype": "postalcode"
  },
  "geometry": {"coordinates":[-0.713292,52.154712],"type":"Point"}
}
