{
  "type": "Feature",
  "properties": {
    "iso:country":"GB",
    "wof:name":"MK46 5QJ",
    "wof:placetype":"postalcode"
},
  "geometry": {"coordinates":[-0.7132924768606,52.15471203403065],"type":"Point"}
}