{
  "type": "Feature",
  "properties": {
    "date:inception_lower": "1991-01-01",
    "date:inception_upper": "1991-01-01",
    "iso:country": "GB",
    "wof:name": "MK46 5QJ",
    "wof:placetype": "postalcode"
  },
  "geometry": {"coordinates":[-0.713292,52.154712],"type":"Point"}
}
