{
  "type": "Feature",
  "properties": {
    "date:inception_lower": "2020-11-01",
    "date:inception_upper": "2020-11-01",
    "iso:country": "GB",
    "wof:name": "EN10 7FZ",
    "wof:placetype": "postalcode"
  },
  "geometry": {"coordinates":[-0.051671,51.73504],"type":"Point"}
}
