{
  "type": "Feature",
  "properties": {
    "date:inception_lower":"1994-05-01",
    "date:inception_upper":"1994-05-31",
    "iso:country":"GB",
    "wof:name":"L9 6EE",
    "wof:placetype":"postalcode"
},
  "geometry": {"coordinates":[-2.926174,53.455781],"type":"Point"}
}