{
  "type": "Feature",
  "properties": {
    "iso:country":"GB",
    "wof:name":"TN15 8RX",
    "wof:placetype":"postalcode"
},
  "geometry": {"coordinates":[0.30460147971609,51.2893287982381],"type":"Point"}
}