{
  "type": "Feature",
  "properties": {
    "iso:country":"GB",
    "wof:name":"ML2 8XZ",
    "wof:placetype":"postalcode"
},
  "geometry": {"coordinates":[-3.90420793539935,55.78363878219916],"type":"Point"}
}