{
  "type": "Feature",
  "properties": {
    "iso:country":"GB",
    "wof:name":"DL13 1EA",
    "wof:placetype":"postalcode"
},
  "geometry": {"coordinates":[-2.2209706172223,54.74820253210732],"type":"Point"}
}