{
  "type": "Feature",
  "properties": {
    "date:inception_lower":"1980-01-01",
    "date:inception_upper":"1980-01-31",
    "iso:country":"GB",
    "wof:name":"DL13 1EA",
    "wof:placetype":"postalcode"
},
  "geometry": {"coordinates":[-2.220978,54.74821],"type":"Point"}
}