{
  "type": "Feature",
  "properties": {
    "date:inception_lower": "1980-01-01",
    "date:inception_upper": "1980-01-01",
    "iso:country": "GB",
    "wof:name": "SM6 9LW",
    "wof:placetype": "postalcode"
  },
  "geometry": {"coordinates":[-0.137895,51.349658],"type":"Point"}
}
