{
  "type": "Feature",
  "properties": {
    "iso:country":"GB",
    "wof:name":"SM6 9LW",
    "wof:placetype":"postalcode"
},
  "geometry": {"coordinates":[-0.13789508584641,51.34965833960771],"type":"Point"}
}