{
  "type": "Feature",
  "properties": {
    "iso:country":"GB",
    "wof:name":"SR6 0DN",
    "wof:placetype":"postalcode"
},
  "geometry": {"coordinates":[-1.37995691954761,54.91702657649027],"type":"Point"}
}