{
  "type": "Feature",
  "properties": {
    "iso:country":"GB",
    "wof:name":"IP1 4LW",
    "wof:placetype":"postalcode"
},
  "geometry": {"coordinates":[1.14921332017182,52.07322625764869],"type":"Point"}
}