{
  "type": "Feature",
  "properties": {
    "iso:country":"GB",
    "wof:name":"MK3 5JD",
    "wof:placetype":"postalcode"
},
  "geometry": {"coordinates":[-0.75800599582344,51.99068118304297],"type":"Point"}
}