{
  "type": "Feature",
  "properties": {
    "iso:country":"GB",
    "wof:name":"SP11 6LY",
    "wof:placetype":"postalcode"
},
  "geometry": {"coordinates":[-1.44147812998448,51.22136711429923],"type":"Point"}
}