{
  "type": "Feature",
  "properties": {
    "date:inception_lower": "1980-01-01",
    "date:inception_upper": "1980-01-01",
    "iso:country": "GB",
    "wof:name": "SP11 6LY",
    "wof:placetype": "postalcode"
  },
  "geometry": {"coordinates":[-1.441478,51.221367],"type":"Point"}
}
