{
  "type": "Feature",
  "properties": {
    "date:inception_lower": "1994-05-01",
    "date:inception_upper": "1994-05-01",
    "iso:country": "GB",
    "wof:name": "CF39 8PY",
    "wof:placetype": "postalcode"
  },
  "geometry": {"coordinates":[-3.427974,51.58372],"type":"Point"}
}
