{
  "type": "Feature",
  "properties": {
    "iso:country":"GB",
    "wof:name":"CF39 8PY",
    "wof:placetype":"postalcode"
},
  "geometry": {"coordinates":[-3.42813446453573,51.58367882004046],"type":"Point"}
}