{
  "type": "Feature",
  "properties": {
    "iso:country":"GB",
    "wof:name":"LE3 8ET",
    "wof:placetype":"postalcode"
},
  "geometry": {"coordinates":[-1.20635397950327,52.65066627952343],"type":"Point"}
}