{
  "type": "Feature",
  "properties": {
    "date:inception_lower":"1980-01-01",
    "date:inception_upper":"1980-01-31",
    "iso:country":"GB",
    "wof:name":"B78 3DW",
    "wof:placetype":"postalcode"
},
  "geometry": {"coordinates":[-1.767276,52.624246],"type":"Point"}
}