{
  "type": "Feature",
  "properties": {
    "iso:country":"GB",
    "wof:name":"M35 0HX",
    "wof:placetype":"postalcode"
},
  "geometry": {"coordinates":[-2.17001392958163,53.50502958080465],"type":"Point"}
}