{
  "type": "Feature",
  "properties": {
    "iso:country": "GB",
    "wof:name": "M35 0HX",
    "wof:placetype": "postalcode"
  },
  "geometry": {"coordinates":[-2.170014,53.50503],"type":"Point"}
}
