{
  "type": "Feature",
  "properties": {
    "iso:country":"GB",
    "wof:name":"PE24 5YJ",
    "wof:placetype":"postalcode"
},
  "geometry": {"coordinates":[0.33096291743407,53.2291797686114],"type":"Point"}
}