{
  "type": "Feature",
  "properties": {
    "date:inception_lower": "1993-01-01",
    "date:inception_upper": "1993-01-01",
    "iso:country": "GB",
    "wof:name": "PE24 5YJ",
    "wof:placetype": "postalcode"
  },
  "geometry": {"coordinates":[0.331039,53.229205],"type":"Point"}
}
