{
  "type": "Feature",
  "properties": {
    "iso:country":"GB",
    "wof:name":"YO25 6FH",
    "wof:placetype":"postalcode"
},
  "geometry": {"coordinates":[-0.44302812825347,54.00923960840919],"type":"Point"}
}