{
  "type": "Feature",
  "properties": {
    "iso:country":"GB",
    "wof:name":"SA14 8ST",
    "wof:placetype":"postalcode"
},
  "geometry": {"coordinates":[-4.14019043174887,51.68560047385123],"type":"Point"}
}