{
  "type": "Feature",
  "properties": {
    "iso:country": "GB",
    "wof:name": "SA14 8ST",
    "wof:placetype": "postalcode"
  },
  "geometry": {"coordinates":[-4.14019,51.6856],"type":"Point"}
}
