{
  "type": "Feature",
  "properties": {
    "iso:country": "GB",
    "wof:name": "BB7 9QB",
    "wof:placetype": "postalcode"
  },
  "geometry": {"coordinates":[-2.480933,53.838626],"type":"Point"}
}
