{
  "type": "Feature",
  "properties": {
    "iso:country":"GB",
    "wof:name":"CR4 3DN",
    "wof:placetype":"postalcode"
},
  "geometry": {"coordinates":[-0.17652855384694,51.40887123881285],"type":"Point"}
}