{
  "type": "Feature",
  "properties": {
    "iso:country":"GB",
    "wof:name":"KT6 4TH",
    "wof:placetype":"postalcode"
},
  "geometry": {"coordinates":[-0.30019879026467,51.39655804947441],"type":"Point"}
}