{
  "type": "Feature",
  "properties": {
    "iso:country": "GB",
    "wof:name": "KT6 4TH",
    "wof:placetype": "postalcode"
  },
  "geometry": {"coordinates":[-0.30022,51.396549],"type":"Point"}
}
