{
  "type": "Feature",
  "properties": {
    "date:inception_lower": "2023-07-01",
    "date:inception_upper": "2023-07-01",
    "iso:country": "GB",
    "wof:name": "PL19 8FX",
    "wof:placetype": "postalcode"
  },
  "geometry": {"coordinates":[-4.159016,50.551627],"type":"Point"}
}
