{
  "type": "Feature",
  "properties": {
    "iso:country":"GB",
    "wof:name":"SS13 2DY",
    "wof:placetype":"postalcode"
},
  "geometry": {"coordinates":[0.51644886925777,51.56685809763056],"type":"Point"}
}