{
  "type": "Feature",
  "properties": {
    "date:inception_lower": "1980-01-01",
    "date:inception_upper": "1980-01-01",
    "iso:country": "GB",
    "wof:name": "SS13 2DY",
    "wof:placetype": "postalcode"
  },
  "geometry": {"coordinates":[0.516449,51.566858],"type":"Point"}
}
