{
  "type": "Feature",
  "properties": {
    "date:inception_lower": "1980-01-01",
    "date:inception_upper": "1980-01-01",
    "iso:country": "GB",
    "wof:name": "CM19 4NJ",
    "wof:placetype": "postalcode"
  },
  "geometry": {"coordinates":[0.087173,51.753747],"type":"Point"}
}
