{
  "type": "Feature",
  "properties": {
    "iso:country": "GB",
    "wof:name": "WA6 7BD",
    "wof:placetype": "postalcode"
  },
  "geometry": {"coordinates":[-2.724005,53.29777],"type":"Point"}
}
