{
  "type": "Feature",
  "properties": {
    "iso:country":"GB",
    "wof:name":"LN5 0QD",
    "wof:placetype":"postalcode"
},
  "geometry": {"coordinates":[-0.57103713138315,53.05439915076732],"type":"Point"}
}