{
  "type": "Feature",
  "properties": {
    "date:inception_lower": "1985-04-01",
    "date:inception_upper": "1985-04-01",
    "iso:country": "GB",
    "wof:name": "NR32 3PQ",
    "wof:placetype": "postalcode"
  },
  "geometry": {"coordinates":[1.705807,52.476136],"type":"Point"}
}
