{
  "type": "Feature",
  "properties": {
    "iso:country": "GB",
    "wof:name": "NR32 3PQ",
    "wof:placetype": "postalcode"
  },
  "geometry": {"coordinates":[1.705807,52.476136],"type":"Point"}
}
