{
  "type": "Feature",
  "properties": {
    "date:inception_lower": "1980-01-01",
    "date:inception_upper": "1980-01-01",
    "iso:country": "GB",
    "wof:name": "NG22 8NY",
    "wof:placetype": "postalcode"
  },
  "geometry": {"coordinates":[-0.992372,53.123823],"type":"Point"}
}
