{
  "type": "Feature",
  "properties": {
    "iso:country":"GB",
    "wof:name":"NG22 8NY",
    "wof:placetype":"postalcode"
},
  "geometry": {"coordinates":[-0.99237174137285,53.12382315454403],"type":"Point"}
}