{
  "type": "Feature",
  "properties": {
    "iso:country":"GB",
    "wof:name":"IV30 1TE",
    "wof:placetype":"postalcode"
},
  "geometry": {"coordinates":[-3.32472086090043,57.6426058663051],"type":"Point"}
}