{
  "type": "Feature",
  "properties": {
    "date:inception_lower":"1981-09-01",
    "date:inception_upper":"1981-09-30",
    "iso:country":"GB",
    "wof:name":"NG20 8LY",
    "wof:placetype":"postalcode"
},
  "geometry": {"coordinates":[-1.223501,53.202772],"type":"Point"}
}