{
  "type": "Feature",
  "properties": {
    "date:inception_lower": "1980-01-01",
    "date:inception_upper": "1980-01-01",
    "iso:country": "GB",
    "wof:name": "DD8 4ED",
    "wof:placetype": "postalcode"
  },
  "geometry": {"coordinates":[-3.004703,56.672075],"type":"Point"}
}
