{
  "type": "Feature",
  "properties": {
    "iso:country": "GB",
    "wof:name": "DD8 4ED",
    "wof:placetype": "postalcode"
  },
  "geometry": {"coordinates":[-3.004851,56.67211],"type":"Point"}
}
