{
  "type": "Feature",
  "properties": {
    "iso:country":"GB",
    "wof:name":"RM10 8PH",
    "wof:placetype":"postalcode"
},
  "geometry": {"coordinates":[0.15132096271865,51.54350143935488],"type":"Point"}
}