{
  "type": "Feature",
  "properties": {
    "date:inception_lower": "1991-09-01",
    "date:inception_upper": "1991-09-01",
    "iso:country": "GB",
    "wof:name": "TA11 6TA",
    "wof:placetype": "postalcode"
  },
  "geometry": {"coordinates":[-2.740145,51.057412],"type":"Point"}
}
