{
  "type": "Feature",
  "properties": {
    "iso:country":"GB",
    "wof:name":"TA11 6TA",
    "wof:placetype":"postalcode"
},
  "geometry": {"coordinates":[-2.74014050458199,51.05741818852172],"type":"Point"}
}