{
  "type": "Feature",
  "properties": {
    "date:inception_lower": "2020-06-01",
    "date:inception_upper": "2020-06-01",
    "iso:country": "GB",
    "wof:name": "WR9 7UA",
    "wof:placetype": "postalcode"
  },
  "geometry": {"coordinates":[-2.176389,52.251818],"type":"Point"}
}
