{
  "type": "Feature",
  "properties": {
    "iso:country": "GB",
    "wof:name": "CV8 2LY",
    "wof:placetype": "postalcode"
  },
  "geometry": {"coordinates":[-1.504704,52.341717],"type":"Point"}
}
