{
  "type": "Feature",
  "properties": {
    "iso:country":"GB",
    "wof:name":"BB9 9AY",
    "wof:placetype":"postalcode"
},
  "geometry": {"coordinates":[-2.2133376909928,53.83277650984583],"type":"Point"}
}