{
  "type": "Feature",
  "properties": {
    "iso:country": "GB",
    "wof:name": "LS17 8PT",
    "wof:placetype": "postalcode"
  },
  "geometry": {"coordinates":[-1.521173,53.852694],"type":"Point"}
}
