{
  "type": "Feature",
  "properties": {
    "iso:country":"GB",
    "wof:name":"B36 8TT",
    "wof:placetype":"postalcode"
},
  "geometry": {"coordinates":[-1.81699171110172,52.50554137033126],"type":"Point"}
}