{
  "type": "Feature",
  "properties": {
    "iso:country": "GB",
    "wof:name": "WA11 8RD",
    "wof:placetype": "postalcode"
  },
  "geometry": {"coordinates":[-2.745518,53.504919],"type":"Point"}
}
