{
  "type": "Feature",
  "properties": {
    "iso:country":"GB",
    "wof:name":"DY4 8TD",
    "wof:placetype":"postalcode"
},
  "geometry": {"coordinates":[-2.05788788525401,52.53001282888305],"type":"Point"}
}