{
  "type": "Feature",
  "properties": {
    "iso:country":"GB",
    "wof:name":"CT20 3LF",
    "wof:placetype":"postalcode"
},
  "geometry": {"coordinates":[1.13587329174173,51.08616762053701],"type":"Point"}
}