{
  "type": "Feature",
  "properties": {
    "iso:country":"GB",
    "wof:name":"PO13 9TT",
    "wof:placetype":"postalcode"
},
  "geometry": {"coordinates":[-1.17576309981107,50.80912373450942],"type":"Point"}
}