{
  "type": "Feature",
  "properties": {
    "iso:country": "GB",
    "wof:name": "GL11 4PB",
    "wof:placetype": "postalcode"
  },
  "geometry": {"coordinates":[-2.3421,51.676974],"type":"Point"}
}
