{
  "type": "Feature",
  "properties": {
    "iso:country":"GB",
    "wof:name":"BD8 7LH",
    "wof:placetype":"postalcode"
},
  "geometry": {"coordinates":[-1.7672550117924,53.80650559806656],"type":"Point"}
}