{
  "type": "Feature",
  "properties": {
    "iso:country": "GB",
    "wof:name": "BD8 7LH",
    "wof:placetype": "postalcode"
  },
  "geometry": {"coordinates":[-1.767255,53.806506],"type":"Point"}
}
