{
  "type": "Feature",
  "properties": {
    "iso:country": "GB",
    "wof:name": "SA70 7DR",
    "wof:placetype": "postalcode"
  },
  "geometry": {"coordinates":[-4.701723,51.669838],"type":"Point"}
}
