{
  "type": "Feature",
  "properties": {
    "iso:country": "GB",
    "wof:name": "WV1 2AT",
    "wof:placetype": "postalcode"
  },
  "geometry": {"coordinates":[-2.092594,52.58882],"type":"Point"}
}
