{
  "type": "Feature",
  "properties": {
    "iso:country":"GB",
    "wof:name":"WV1 2AT",
    "wof:placetype":"postalcode"
},
  "geometry": {"coordinates":[-2.09259393627845,52.58882020086357],"type":"Point"}
}