{
  "type": "Feature",
  "properties": {
    "iso:country":"GB",
    "wof:name":"BB3 3NB",
    "wof:placetype":"postalcode"
},
  "geometry": {"coordinates":[-2.43060553082547,53.69523257424785],"type":"Point"}
}