{
  "type": "Feature",
  "properties": {
    "iso:country":"GB",
    "wof:name":"KA21 5TH",
    "wof:placetype":"postalcode"
},
  "geometry": {"coordinates":[-4.78943130680654,55.63913933508777],"type":"Point"}
}