{
  "type": "Feature",
  "properties": {
    "iso:country": "GB",
    "wof:name": "HP17 8LF",
    "wof:placetype": "postalcode"
  },
  "geometry": {"coordinates":[-0.923589,51.776844],"type":"Point"}
}
