{
  "type": "Feature",
  "properties": {
    "iso:country":"GB",
    "wof:name":"HP17 8LF",
    "wof:placetype":"postalcode"
},
  "geometry": {"coordinates":[-0.92358875576202,51.77684432312093],"type":"Point"}
}