{
  "type": "Feature",
  "properties": {
    "date:inception_lower": "1995-01-01",
    "date:inception_upper": "1995-01-01",
    "iso:country": "GB",
    "wof:name": "PR2 8AJ",
    "wof:placetype": "postalcode"
  },
  "geometry": {"coordinates":[-2.69065,53.777821],"type":"Point"}
}
