{
  "type": "Feature",
  "properties": {
    "iso:country":"GB",
    "wof:name":"PR2 8AJ",
    "wof:placetype":"postalcode"
},
  "geometry": {"coordinates":[-2.69065040419585,53.77782139193705],"type":"Point"}
}