{
  "type": "Feature",
  "properties": {
    "iso:country": "GB",
    "wof:name": "PH16 5LD",
    "wof:placetype": "postalcode"
  },
  "geometry": {"coordinates":[-3.773883,56.720757],"type":"Point"}
}
