{
  "type": "Feature",
  "properties": {
    "iso:country":"GB",
    "wof:name":"PH16 5LD",
    "wof:placetype":"postalcode"
},
  "geometry": {"coordinates":[-3.77388328013641,56.72075723355562],"type":"Point"}
}