{
  "type": "Feature",
  "properties": {
    "iso:country":"GB",
    "wof:name":"PE19 2PD",
    "wof:placetype":"postalcode"
},
  "geometry": {"coordinates":[-0.25826437211017,52.21623440619124],"type":"Point"}
}