{
  "type": "Feature",
  "properties": {
    "iso:country": "GB",
    "wof:name": "PE19 2PD",
    "wof:placetype": "postalcode"
  },
  "geometry": {"coordinates":[-0.258264,52.216234],"type":"Point"}
}
