{
  "type": "Feature",
  "properties": {
    "date:inception_lower":"2011-02-01",
    "date:inception_upper":"2011-02-28",
    "iso:country":"GB",
    "wof:name":"IP19 1AL",
    "wof:placetype":"postalcode"
},
  "geometry": {"coordinates":[1.502257,52.345666],"type":"Point"}
}