{
  "type": "Feature",
  "properties": {
    "iso:country":"GB",
    "wof:name":"PH7 3JS",
    "wof:placetype":"postalcode"
},
  "geometry": {"coordinates":[-3.83164302035368,56.37036051781872],"type":"Point"}
}