{
  "type": "Feature",
  "properties": {
    "iso:country": "GB",
    "wof:name": "PH7 3JS",
    "wof:placetype": "postalcode"
  },
  "geometry": {"coordinates":[-3.831643,56.370361],"type":"Point"}
}
