{
  "type": "Feature",
  "properties": {
    "iso:country":"GB",
    "wof:name":"SW1V 4EP",
    "wof:placetype":"postalcode"
},
  "geometry": {"coordinates":[-0.14654927007504,51.49164530675028],"type":"Point"}
}