{
  "type": "Feature",
  "properties": {
    "date:inception_lower": "1980-01-01",
    "date:inception_upper": "1980-01-01",
    "iso:country": "GB",
    "wof:name": "SW1V 4EP",
    "wof:placetype": "postalcode"
  },
  "geometry": {"coordinates":[-0.146549,51.491645],"type":"Point"}
}
