{
  "type": "Feature",
  "properties": {
    "iso:country":"GB",
    "wof:name":"WA2 7SB",
    "wof:placetype":"postalcode"
},
  "geometry": {"coordinates":[-2.57974835885391,53.40015904602831],"type":"Point"}
}