{
  "type": "Feature",
  "properties": {
    "iso:country":"GB",
    "wof:name":"PE12 6PH",
    "wof:placetype":"postalcode"
},
  "geometry": {"coordinates":[-0.06446492300193,52.80410102912646],"type":"Point"}
}