{
  "type": "Feature",
  "properties": {
    "iso:country":"GB",
    "wof:name":"PA34 4TW",
    "wof:placetype":"postalcode"
},
  "geometry": {"coordinates":[-5.58702682607188,56.3122769282895],"type":"Point"}
}