{
  "type": "Feature",
  "properties": {
    "iso:country": "GB",
    "wof:name": "PA34 4TW",
    "wof:placetype": "postalcode"
  },
  "geometry": {"coordinates":[-5.587027,56.312277],"type":"Point"}
}
