{
  "type": "Feature",
  "properties": {
    "iso:country":"GB",
    "wof:name":"DE65 6SE",
    "wof:placetype":"postalcode"
},
  "geometry": {"coordinates":[-1.55078204295796,52.84071438450065],"type":"Point"}
}