{
  "type": "Feature",
  "properties": {
    "date:inception_lower": "1998-06-01",
    "date:inception_upper": "1998-06-01",
    "iso:country": "GB",
    "wof:name": "DE65 6SE",
    "wof:placetype": "postalcode"
  },
  "geometry": {"coordinates":[-1.550575,52.840237],"type":"Point"}
}
