{
  "type": "Feature",
  "properties": {
    "iso:country":"GB",
    "wof:name":"FK2 9XE",
    "wof:placetype":"postalcode"
},
  "geometry": {"coordinates":[-3.73192249693018,55.98666424177437],"type":"Point"}
}