{
  "type": "Feature",
  "properties": {
    "iso:country": "GB",
    "wof:name": "FK2 9XE",
    "wof:placetype": "postalcode"
  },
  "geometry": {"coordinates":[-3.731922,55.986664],"type":"Point"}
}
