{
  "type": "Feature",
  "properties": {
    "iso:country":"GB",
    "wof:name":"BN3 6BP",
    "wof:placetype":"postalcode"
},
  "geometry": {"coordinates":[-0.17486506344305,50.84716934452289],"type":"Point"}
}