{
  "type": "Feature",
  "properties": {
    "iso:country":"GB",
    "wof:name":"L7 4JP",
    "wof:placetype":"postalcode"
},
  "geometry": {"coordinates":[-2.94599202436263,53.39811498923689],"type":"Point"}
}