{
  "type": "Feature",
  "properties": {
    "iso:country":"GB",
    "wof:name":"BN26 6DA",
    "wof:placetype":"postalcode"
},
  "geometry": {"coordinates":[0.24118628376597,50.82347820311185],"type":"Point"}
}