{
  "type": "Feature",
  "properties": {
    "iso:country": "GB",
    "wof:name": "PL13 2SB",
    "wof:placetype": "postalcode"
  },
  "geometry": {"coordinates":[-4.515271,50.333646],"type":"Point"}
}
