{
  "type": "Feature",
  "properties": {
    "date:inception_lower": "1992-08-01",
    "date:inception_upper": "1992-08-01",
    "iso:country": "GB",
    "wof:name": "SK17 9XG",
    "wof:placetype": "postalcode"
  },
  "geometry": {"coordinates":[-1.910476,53.247152],"type":"Point"}
}
