{
  "type": "Feature",
  "properties": {
    "iso:country": "GB",
    "wof:name": "SK17 9XG",
    "wof:placetype": "postalcode"
  },
  "geometry": {"coordinates":[-1.910476,53.247152],"type":"Point"}
}
