{
  "type": "Feature",
  "properties": {
    "iso:country": "GB",
    "wof:name": "SK17 9XG",
    "wof:placetype": "postalcode"
  },
  "geometry": {"coordinates":[-1.910282,53.246999],"type":"Point"}
}
