{
  "type": "Feature",
  "properties": {
    "date:inception_lower":"1990-02-01",
    "date:inception_upper":"1990-02-28",
    "iso:country":"GB",
    "wof:name":"PL12 6PF",
    "wof:placetype":"postalcode"
},
  "geometry": {"coordinates":[-4.207754,50.441646],"type":"Point"}
}