{
  "type": "Feature",
  "properties": {
    "iso:country":"GB",
    "wof:name":"PL12 6PF",
    "wof:placetype":"postalcode"
},
  "geometry": {"coordinates":[-4.20772399273425,50.44165888564807],"type":"Point"}
}