{
  "type": "Feature",
  "properties": {
    "iso:country": "GB",
    "wof:name": "PL12 6PF",
    "wof:placetype": "postalcode"
  },
  "geometry": {"coordinates":[-4.207754,50.441646],"type":"Point"}
}
