{
  "type": "Feature",
  "properties": {
    "iso:country":"GB",
    "wof:name":"N15 6TA",
    "wof:placetype":"postalcode"
},
  "geometry": {"coordinates":[-0.07160791066667,51.57842005443897],"type":"Point"}
}