{
  "type": "Feature",
  "properties": {
    "date:inception_lower": "2023-03-01",
    "date:inception_upper": "2023-03-01",
    "iso:country": "GB",
    "wof:name": "AB10 1DF",
    "wof:placetype": "postalcode"
  },
  "geometry": {"coordinates":[-2.105247,57.147526],"type":"Point"}
}
