{
  "type": "Feature",
  "properties": {
    "iso:country":"GB",
    "wof:name":"SP2 8JN",
    "wof:placetype":"postalcode"
},
  "geometry": {"coordinates":[-1.8025491886417,51.06006442568771],"type":"Point"}
}