{
  "type": "Feature",
  "properties": {
    "iso:country":"GB",
    "wof:name":"NP22 4EB",
    "wof:placetype":"postalcode"
},
  "geometry": {"coordinates":[-3.2479183247018,51.78724613640947],"type":"Point"}
}