{
  "type": "Feature",
  "properties": {
    "iso:country": "GB",
    "wof:name": "HD2 1LR",
    "wof:placetype": "postalcode"
  },
  "geometry": {"coordinates":[-1.753343,53.67216],"type":"Point"}
}
