{
  "type": "Feature",
  "properties": {
    "iso:country": "GB",
    "wof:name": "WA5 7AD",
    "wof:placetype": "postalcode"
  },
  "geometry": {"coordinates":[-2.642552,53.413912],"type":"Point"}
}
