{
  "type": "Feature",
  "properties": {
    "iso:country":"GB",
    "wof:name":"BR7 6DJ",
    "wof:placetype":"postalcode"
},
  "geometry": {"coordinates":[0.05973011642516,51.42404855270699],"type":"Point"}
}