{
  "type": "Feature",
  "properties": {
    "date:inception_lower": "2024-01-01",
    "date:inception_upper": "2024-01-01",
    "iso:country": "GB",
    "wof:name": "LD3 3DT",
    "wof:placetype": "postalcode"
  },
  "geometry": {"coordinates":[-3.411715,51.941196],"type":"Point"}
}
