{
  "type": "Feature",
  "properties": {
    "iso:country":"GB",
    "wof:name":"DN22 7RF",
    "wof:placetype":"postalcode"
},
  "geometry": {"coordinates":[-0.94785351048635,53.33043354833011],"type":"Point"}
}