{
  "type": "Feature",
  "properties": {
    "date:inception_lower": "1980-01-01",
    "date:inception_upper": "1980-01-01",
    "iso:country": "GB",
    "wof:name": "NG8 6DE",
    "wof:placetype": "postalcode"
  },
  "geometry": {"coordinates":[-1.20591,52.985385],"type":"Point"}
}
