{
  "type": "Feature",
  "properties": {
    "date:inception_lower":"2000-06-01",
    "date:inception_upper":"2000-06-30",
    "iso:country":"GB",
    "wof:name":"CA7 3NF",
    "wof:placetype":"postalcode"
},
  "geometry": {"coordinates":[-3.265013,54.799554],"type":"Point"}
}