{
  "type": "Feature",
  "properties": {
    "iso:country":"GB",
    "wof:name":"CA7 3NF",
    "wof:placetype":"postalcode"
},
  "geometry": {"coordinates":[-3.26505587638187,54.79951046479773],"type":"Point"}
}