{
  "type": "Feature",
  "properties": {
    "date:inception_lower":"1980-01-01",
    "date:inception_upper":"1980-01-31",
    "iso:country":"GB",
    "wof:name":"EX10 8EL",
    "wof:placetype":"postalcode"
},
  "geometry": {"coordinates":[-3.237323,50.680124],"type":"Point"}
}