{
  "type": "Feature",
  "properties": {
    "iso:country":"GB",
    "wof:name":"EX10 8EL",
    "wof:placetype":"postalcode"
},
  "geometry": {"coordinates":[-3.23732307244577,50.68012397827714],"type":"Point"}
}