{
  "type": "Feature",
  "properties": {
    "date:inception_lower": "1980-01-01",
    "date:inception_upper": "1980-01-01",
    "iso:country": "GB",
    "wof:name": "EX10 8EL",
    "wof:placetype": "postalcode"
  },
  "geometry": {"coordinates":[-3.237336,50.680193],"type":"Point"}
}
