{
  "type": "Feature",
  "properties": {
    "iso:country":"GB",
    "wof:name":"YO17 7LH",
    "wof:placetype":"postalcode"
},
  "geometry": {"coordinates":[-0.79964711232611,54.13660160103649],"type":"Point"}
}