{
  "type": "Feature",
  "properties": {
    "iso:country":"GB",
    "wof:name":"DL4 1JX",
    "wof:placetype":"postalcode"
},
  "geometry": {"coordinates":[-1.65687310629914,54.63251287808542],"type":"Point"}
}