{
  "type": "Feature",
  "properties": {
    "date:inception_lower":"1997-06-01",
    "date:inception_upper":"1997-06-30",
    "iso:country":"GB",
    "wof:name":"SK9 2GT",
    "wof:placetype":"postalcode"
},
  "geometry": {"coordinates":[-2.221329,53.332923],"type":"Point"}
}