{
  "type": "Feature",
  "properties": {
    "iso:country": "GB",
    "wof:name": "SK9 2GT",
    "wof:placetype": "postalcode"
  },
  "geometry": {"coordinates":[-2.221329,53.332923],"type":"Point"}
}
