{
  "type": "Feature",
  "properties": {
    "iso:country":"GB",
    "wof:name":"SK9 2GT",
    "wof:placetype":"postalcode"
},
  "geometry": {"coordinates":[-2.22132877629741,53.33292265408213],"type":"Point"}
}