{
  "type": "Feature",
  "properties": {
    "iso:country": "GB",
    "wof:name": "YO15 1PL",
    "wof:placetype": "postalcode"
  },
  "geometry": {"coordinates":[-0.12779,54.111785],"type":"Point"}
}
