{
  "type": "Feature",
  "properties": {
    "iso:country":"GB",
    "wof:name":"CT11 9EQ",
    "wof:placetype":"postalcode"
},
  "geometry": {"coordinates":[1.4131772151311,51.33002884085387],"type":"Point"}
}