{
  "type": "Feature",
  "properties": {
    "date:inception_lower": "1980-01-01",
    "date:inception_upper": "1980-01-01",
    "iso:country": "GB",
    "wof:name": "CM16 6DD",
    "wof:placetype": "postalcode"
  },
  "geometry": {"coordinates":[0.169216,51.716372],"type":"Point"}
}
