{
  "type": "Feature",
  "properties": {
    "iso:country":"GB",
    "wof:name":"CM16 6DD",
    "wof:placetype":"postalcode"
},
  "geometry": {"coordinates":[0.16921608538213,51.71637198690831],"type":"Point"}
}