{
  "type": "Feature",
  "properties": {
    "date:inception_lower": "1980-01-01",
    "date:inception_upper": "1980-01-01",
    "iso:country": "GB",
    "wof:name": "BN1 5EL",
    "wof:placetype": "postalcode"
  },
  "geometry": {"coordinates":[-0.157299,50.861795],"type":"Point"}
}
