{
  "type": "Feature",
  "properties": {
    "date:inception_lower": "1980-01-01",
    "date:inception_upper": "1980-01-01",
    "iso:country": "GB",
    "wof:name": "HU6 8SZ",
    "wof:placetype": "postalcode"
  },
  "geometry": {"coordinates":[-0.389473,53.778661],"type":"Point"}
}
