{
  "type": "Feature",
  "properties": {
    "iso:country":"GB",
    "wof:name":"HU6 8SZ",
    "wof:placetype":"postalcode"
},
  "geometry": {"coordinates":[-0.38947345474326,53.77866108004176],"type":"Point"}
}