{
  "type": "Feature",
  "properties": {
    "iso:country": "GB",
    "wof:name": "CM8 3XW",
    "wof:placetype": "postalcode"
  },
  "geometry": {"coordinates":[0.621404,51.850979],"type":"Point"}
}
