{
  "type": "Feature",
  "properties": {
    "date:inception_lower":"1983-03-01",
    "date:inception_upper":"1983-03-31",
    "iso:country":"GB",
    "wof:name":"CM8 3XW",
    "wof:placetype":"postalcode"
},
  "geometry": {"coordinates":[0.621404,51.850979],"type":"Point"}
}