{
  "type": "Feature",
  "properties": {
    "iso:country":"GB",
    "wof:name":"CM8 3XW",
    "wof:placetype":"postalcode"
},
  "geometry": {"coordinates":[0.62140438203897,51.85097877639782],"type":"Point"}
}