{
  "type": "Feature",
  "properties": {
    "iso:country": "GB",
    "wof:name": "MK40 2LX",
    "wof:placetype": "postalcode"
  },
  "geometry": {"coordinates":[-0.45855,52.144388],"type":"Point"}
}
