{
  "type": "Feature",
  "properties": {
    "iso:country": "GB",
    "wof:name": "TN24 9FE",
    "wof:placetype": "postalcode"
  },
  "geometry": {"coordinates":[0.904392,51.157291],"type":"Point"}
}
