{
  "type": "Feature",
  "properties": {
    "iso:country":"GB",
    "wof:name":"LL12 8LL",
    "wof:placetype":"postalcode"
},
  "geometry": {"coordinates":[-2.95483777140901,53.08728967814019],"type":"Point"}
}