{
  "type": "Feature",
  "properties": {
    "date:inception_lower": "1980-01-01",
    "date:inception_upper": "1980-01-01",
    "iso:country": "GB",
    "wof:name": "LL12 8LL",
    "wof:placetype": "postalcode"
  },
  "geometry": {"coordinates":[-2.956048,53.087296],"type":"Point"}
}
