{
  "type": "Feature",
  "properties": {
    "iso:country":"GB",
    "wof:name":"SW9 8ED",
    "wof:placetype":"postalcode"
},
  "geometry": {"coordinates":[-0.11509058719824,51.46329383298171],"type":"Point"}
}