{
  "type": "Feature",
  "properties": {
    "iso:country": "GB",
    "wof:name": "NR14 8GD",
    "wof:placetype": "postalcode"
  },
  "geometry": {"coordinates":[1.320599,52.609642],"type":"Point"}
}
