{
  "type": "Feature",
  "properties": {
    "iso:country":"GB",
    "wof:name":"NR14 8GD",
    "wof:placetype":"postalcode"
},
  "geometry": {"coordinates":[1.32059863981108,52.60964205891221],"type":"Point"}
}