{
  "type": "Feature",
  "properties": {
    "iso:country":"GB",
    "wof:name":"GU15 1LL",
    "wof:placetype":"postalcode"
},
  "geometry": {"coordinates":[-0.71861322124604,51.3401125540236],"type":"Point"}
}