{
  "type": "Feature",
  "properties": {
    "iso:country":"GB",
    "wof:name":"ML8 4QL",
    "wof:placetype":"postalcode"
},
  "geometry": {"coordinates":[-3.81014344251986,55.72813862886096],"type":"Point"}
}