{
  "type": "Feature",
  "properties": {
    "iso:country": "GB",
    "wof:name": "AB33 8QB",
    "wof:placetype": "postalcode"
  },
  "geometry": {"coordinates":[-2.705195,57.233738],"type":"Point"}
}
