{
  "type": "Feature",
  "properties": {
    "iso:country":"GB",
    "wof:name":"PE32 1NR",
    "wof:placetype":"postalcode"
},
  "geometry": {"coordinates":[0.512779354613,52.71875444025724],"type":"Point"}
}