{
  "type": "Feature",
  "properties": {
    "iso:country":"GB",
    "wof:name":"G15 8NZ",
    "wof:placetype":"postalcode"
},
  "geometry": {"coordinates":[-4.38475200366817,55.9077141265055],"type":"Point"}
}