{
  "type": "Feature",
  "properties": {
    "iso:country": "GB",
    "wof:name": "L23 8TR",
    "wof:placetype": "postalcode"
  },
  "geometry": {"coordinates":[-3.044184,53.492552],"type":"Point"}
}
