{
  "type": "Feature",
  "properties": {
    "date:inception_lower":"1980-01-01",
    "date:inception_upper":"1980-01-31",
    "iso:country":"GB",
    "wof:name":"RH18 5AZ",
    "wof:placetype":"postalcode"
},
  "geometry": {"coordinates":[0.035322,51.090542],"type":"Point"}
}