{
  "type": "Feature",
  "properties": {
    "iso:country":"GB",
    "wof:name":"RH18 5AZ",
    "wof:placetype":"postalcode"
},
  "geometry": {"coordinates":[0.0353520265057,51.09055304442019],"type":"Point"}
}