{
  "type": "Feature",
  "properties": {
    "iso:country":"GB",
    "wof:name":"NN10 9HA",
    "wof:placetype":"postalcode"
},
  "geometry": {"coordinates":[-0.60300653460646,52.28058160238056],"type":"Point"}
}