{
  "type": "Feature",
  "properties": {
    "date:inception_lower": "1999-06-01",
    "date:inception_upper": "1999-06-01",
    "iso:country": "GB",
    "wof:name": "CF23 6LQ",
    "wof:placetype": "postalcode"
  },
  "geometry": {"coordinates":[-3.165878,51.517089],"type":"Point"}
}
