{
  "type": "Feature",
  "properties": {
    "iso:country": "GB",
    "wof:name": "NN16 9XZ",
    "wof:placetype": "postalcode"
  },
  "geometry": {"coordinates":[-0.735154,52.404683],"type":"Point"}
}
