{
  "type": "Feature",
  "properties": {
    "iso:country": "GB",
    "wof:name": "NN16 9XZ",
    "wof:placetype": "postalcode"
  },
  "geometry": {"coordinates":[-0.735736,52.404375],"type":"Point"}
}
