{
  "type": "Feature",
  "properties": {
    "iso:country":"GB",
    "wof:name":"IG6 1RB",
    "wof:placetype":"postalcode"
},
  "geometry": {"coordinates":[0.08316168195793,51.58610711095258],"type":"Point"}
}