{
  "type": "Feature",
  "properties": {
    "iso:country":"GB",
    "wof:name":"DA1 1SR",
    "wof:placetype":"postalcode"
},
  "geometry": {"coordinates":[0.23123575093269,51.44056744575664],"type":"Point"}
}