{
  "type": "Feature",
  "properties": {
    "iso:country":"GB",
    "wof:name":"WN6 8PH",
    "wof:placetype":"postalcode"
},
  "geometry": {"coordinates":[-2.65852287921555,53.56128470081079],"type":"Point"}
}