{
  "type": "Feature",
  "properties": {
    "date:inception_lower": "2022-05-01",
    "date:inception_upper": "2022-05-01",
    "iso:country": "GB",
    "wof:name": "LA23 9BL",
    "wof:placetype": "postalcode"
  },
  "geometry": {"coordinates":[-2.905507,54.378372],"type":"Point"}
}
