{
  "type": "Feature",
  "properties": {
    "iso:country":"GB",
    "wof:name":"NW5 3AS",
    "wof:placetype":"postalcode"
},
  "geometry": {"coordinates":[-0.14767372033924,51.54952973526193],"type":"Point"}
}