{
  "type": "Feature",
  "properties": {
    "iso:country":"GB",
    "wof:name":"KT13 0EN",
    "wof:placetype":"postalcode"
},
  "geometry": {"coordinates":[-0.4395884170311,51.36329177571556],"type":"Point"}
}