{
  "type": "Feature",
  "properties": {
    "iso:country":"GB",
    "wof:name":"S20 2QU",
    "wof:placetype":"postalcode"
},
  "geometry": {"coordinates":[-1.3397777073367,53.3354382405893],"type":"Point"}
}