{
  "type": "Feature",
  "properties": {
    "date:inception_lower": "1997-06-01",
    "date:inception_upper": "1997-06-01",
    "iso:country": "GB",
    "wof:name": "S20 2QU",
    "wof:placetype": "postalcode"
  },
  "geometry": {"coordinates":[-1.339748,53.335429],"type":"Point"}
}
