{
  "type": "Feature",
  "properties": {
    "iso:country":"GB",
    "wof:name":"DE21 7PP",
    "wof:placetype":"postalcode"
},
  "geometry": {"coordinates":[-1.3947152309872,52.91480519446093],"type":"Point"}
}