{
  "type": "Feature",
  "properties": {
    "date:inception_lower": "1980-01-01",
    "date:inception_upper": "1980-01-01",
    "iso:country": "GB",
    "wof:name": "OX1 3SU",
    "wof:placetype": "postalcode"
  },
  "geometry": {"coordinates":[-1.253023,51.754762],"type":"Point"}
}
