{
  "type": "Feature",
  "properties": {
    "iso:country":"GB",
    "wof:name":"OX1 3SU",
    "wof:placetype":"postalcode"
},
  "geometry": {"coordinates":[-1.25302344235111,51.75476236146609],"type":"Point"}
}