{
  "type": "Feature",
  "properties": {
    "iso:country": "GB",
    "wof:name": "NP18 2HG",
    "wof:placetype": "postalcode"
  },
  "geometry": {"coordinates":[-2.886616,51.598713],"type":"Point"}
}
