{
  "type": "Feature",
  "properties": {
    "iso:country":"GB",
    "wof:name":"NP18 2HG",
    "wof:placetype":"postalcode"
},
  "geometry": {"coordinates":[-2.88661628467307,51.5987129583908],"type":"Point"}
}