{
  "type": "Feature",
  "properties": {
    "iso:country": "GB",
    "wof:name": "TR13 9AF",
    "wof:placetype": "postalcode"
  },
  "geometry": {"coordinates":[-5.311122,50.088118],"type":"Point"}
}
