{
  "type": "Feature",
  "properties": {
    "iso:country": "GB",
    "wof:name": "DN32 0NS",
    "wof:placetype": "postalcode"
  },
  "geometry": {"coordinates":[-0.079721,53.55975],"type":"Point"}
}
