{
  "type": "Feature",
  "properties": {
    "iso:country":"GB",
    "wof:name":"S10 3EB",
    "wof:placetype":"postalcode"
},
  "geometry": {"coordinates":[-1.50630728248028,53.37547880266474],"type":"Point"}
}