{
  "type": "Feature",
  "properties": {
    "iso:country": "GB",
    "wof:name": "OL16 3LQ",
    "wof:placetype": "postalcode"
  },
  "geometry": {"coordinates":[-2.11344,53.609883],"type":"Point"}
}
