{
  "type": "Feature",
  "properties": {
    "date:inception_lower": "1998-06-01",
    "date:inception_upper": "1998-06-01",
    "iso:country": "GB",
    "wof:name": "NG18 2EN",
    "wof:placetype": "postalcode"
  },
  "geometry": {"coordinates":[-1.172524,53.148412],"type":"Point"}
}
