{
  "type": "Feature",
  "properties": {
    "iso:country":"GB",
    "wof:name":"NG18 2EN",
    "wof:placetype":"postalcode"
},
  "geometry": {"coordinates":[-1.17252413960108,53.14841228794903],"type":"Point"}
}