{
  "type": "Feature",
  "properties": {
    "iso:country":"GB",
    "wof:name":"B98 0TE",
    "wof:placetype":"postalcode"
},
  "geometry": {"coordinates":[-1.90686795560916,52.2991438974507],"type":"Point"}
}