{
  "type": "Feature",
  "properties": {
    "date:inception_lower":"1980-01-01",
    "date:inception_upper":"1980-01-31",
    "iso:country":"GB",
    "wof:name":"B98 0TE",
    "wof:placetype":"postalcode"
},
  "geometry": {"coordinates":[-1.906868,52.299144],"type":"Point"}
}