{
  "type": "Feature",
  "properties": {
    "iso:country": "GB",
    "wof:name": "EC3V 4AB",
    "wof:placetype": "postalcode"
  },
  "geometry": {"coordinates":[-0.082324,51.513769],"type":"Point"}
}
