{
  "type": "Feature",
  "properties": {
    "date:inception_lower": "2016-02-01",
    "date:inception_upper": "2016-02-01",
    "iso:country": "GB",
    "wof:name": "EC3A 8AL",
    "wof:placetype": "postalcode"
  },
  "geometry": {"coordinates":[-0.080455,51.514008],"type":"Point"}
}
