{
  "type": "Feature",
  "properties": {
    "date:inception_lower": "2017-11-01",
    "date:inception_upper": "2017-11-01",
    "iso:country": "GB",
    "wof:name": "N1C 4BS",
    "wof:placetype": "postalcode"
  },
  "geometry": {"coordinates":[-0.123712,51.530429],"type":"Point"}
}
