{
  "type": "Feature",
  "properties": {
    "iso:country": "GB",
    "wof:name": "SW14 8NX",
    "wof:placetype": "postalcode"
  },
  "geometry": {"coordinates":[-0.263435,51.465792],"type":"Point"}
}
