{
  "type": "Feature",
  "properties": {
    "date:inception_lower": "1980-01-01",
    "date:inception_upper": "1980-01-01",
    "iso:country": "GB",
    "wof:name": "MK43 7SE",
    "wof:placetype": "postalcode"
  },
  "geometry": {"coordinates":[-0.526203,52.171512],"type":"Point"}
}
