{
  "type": "Feature",
  "properties": {
    "iso:country":"GB",
    "wof:name":"CV37 9TJ",
    "wof:placetype":"postalcode"
},
  "geometry": {"coordinates":[-1.78680731890201,52.18411892885592],"type":"Point"}
}