{
  "type": "Feature",
  "properties": {
    "iso:country": "GB",
    "wof:name": "CV37 9TJ",
    "wof:placetype": "postalcode"
  },
  "geometry": {"coordinates":[-1.786807,52.184119],"type":"Point"}
}
