{
  "type": "Feature",
  "properties": {
    "date:inception_lower": "2021-09-01",
    "date:inception_upper": "2021-09-01",
    "iso:country": "GB",
    "wof:name": "PH10 6WF",
    "wof:placetype": "postalcode"
  },
  "geometry": {"coordinates":[-3.341101,56.57923],"type":"Point"}
}
