{
  "type": "Feature",
  "properties": {
    "iso:country":"GB",
    "wof:name":"NP4 6QE",
    "wof:placetype":"postalcode"
},
  "geometry": {"coordinates":[-3.0594523104376,51.7103040195514],"type":"Point"}
}