{
  "type": "Feature",
  "properties": {
    "iso:country": "GB",
    "wof:name": "NP4 6QE",
    "wof:placetype": "postalcode"
  },
  "geometry": {"coordinates":[-3.059452,51.710304],"type":"Point"}
}
