{
  "type": "Feature",
  "properties": {
    "date:inception_lower": "2019-07-01",
    "date:inception_upper": "2019-07-01",
    "iso:country": "GB",
    "wof:name": "WD17 3AR",
    "wof:placetype": "postalcode"
  },
  "geometry": {"coordinates":[-0.421937,51.662034],"type":"Point"}
}
