{
  "type": "Feature",
  "properties": {
    "date:inception_lower": "1993-08-01",
    "date:inception_upper": "1993-08-01",
    "iso:country": "GB",
    "wof:name": "BA14 9TX",
    "wof:placetype": "postalcode"
  },
  "geometry": {"coordinates":[-2.221728,51.31755],"type":"Point"}
}
