{
  "type": "Feature",
  "properties": {
    "iso:country": "GB",
    "wof:name": "GU17 0BA",
    "wof:placetype": "postalcode"
  },
  "geometry": {"coordinates":[-0.795637,51.331776],"type":"Point"}
}
