{
  "type": "Feature",
  "properties": {
    "iso:country":"GB",
    "wof:name":"GU17 0BA",
    "wof:placetype":"postalcode"
},
  "geometry": {"coordinates":[-0.79565445091081,51.3317758477348],"type":"Point"}
}