{
  "type": "Feature",
  "properties": {
    "date:inception_lower":"1998-06-01",
    "date:inception_upper":"1998-06-30",
    "iso:country":"GB",
    "wof:name":"PL30 3EB",
    "wof:placetype":"postalcode"
},
  "geometry": {"coordinates":[-4.776716,50.546723],"type":"Point"}
}