{
  "type": "Feature",
  "properties": {
    "iso:country": "GB",
    "wof:name": "PL30 3EB",
    "wof:placetype": "postalcode"
  },
  "geometry": {"coordinates":[-4.776716,50.546723],"type":"Point"}
}
