{
  "type": "Feature",
  "properties": {
    "iso:country": "GB",
    "wof:name": "TQ7 4LW",
    "wof:placetype": "postalcode"
  },
  "geometry": {"coordinates":[-3.836261,50.313601],"type":"Point"}
}
