{
  "type": "Feature",
  "properties": {
    "date:inception_lower":"1980-01-01",
    "date:inception_upper":"1980-01-31",
    "iso:country":"GB",
    "wof:name":"TQ7 4LW",
    "wof:placetype":"postalcode"
},
  "geometry": {"coordinates":[-3.836261,50.313601],"type":"Point"}
}