{
  "type": "Feature",
  "properties": {
    "iso:country":"GB",
    "wof:name":"TQ7 4LW",
    "wof:placetype":"postalcode"
},
  "geometry": {"coordinates":[-3.83626117212852,50.3136013681537],"type":"Point"}
}