{
  "type": "Feature",
  "properties": {
    "date:inception_lower": "1980-01-01",
    "date:inception_upper": "1980-01-01",
    "iso:country": "GB",
    "wof:name": "TN21 0HW",
    "wof:placetype": "postalcode"
  },
  "geometry": {"coordinates":[0.24697,50.93203],"type":"Point"}
}
