{
  "type": "Feature",
  "properties": {
    "iso:country": "GB",
    "wof:name": "TN21 0HW",
    "wof:placetype": "postalcode"
  },
  "geometry": {"coordinates":[0.24697,50.93203],"type":"Point"}
}
