{
  "type": "Feature",
  "properties": {
    "iso:country":"GB",
    "wof:name":"G71 7ER",
    "wof:placetype":"postalcode"
},
  "geometry": {"coordinates":[-4.07257579410013,55.81465222611531],"type":"Point"}
}