{
  "type": "Feature",
  "properties": {
    "date:inception_lower": "2015-01-01",
    "date:inception_upper": "2015-01-01",
    "iso:country": "GB",
    "wof:name": "G71 7ER",
    "wof:placetype": "postalcode"
  },
  "geometry": {"coordinates":[-4.072576,55.814652],"type":"Point"}
}
