{
  "type": "Feature",
  "properties": {
    "iso:country": "GB",
    "wof:name": "G71 7ER",
    "wof:placetype": "postalcode"
  },
  "geometry": {"coordinates":[-4.072576,55.814652],"type":"Point"}
}
