{
  "type": "Feature",
  "properties": {
    "iso:country": "GB",
    "wof:name": "NG31 8JQ",
    "wof:placetype": "postalcode"
  },
  "geometry": {"coordinates":[-0.656513,52.924368],"type":"Point"}
}
