{
  "type": "Feature",
  "properties": {
    "iso:country":"GB",
    "wof:name":"NG31 8JQ",
    "wof:placetype":"postalcode"
},
  "geometry": {"coordinates":[-0.65651319578148,52.92436780084438],"type":"Point"}
}