{
  "type": "Feature",
  "properties": {
    "iso:country":"GB",
    "wof:name":"HR8 2QX",
    "wof:placetype":"postalcode"
},
  "geometry": {"coordinates":[-2.43452165269783,52.04527979501736],"type":"Point"}
}