{
  "type": "Feature",
  "properties": {
    "iso:country":"GB",
    "wof:name":"FY5 3QP",
    "wof:placetype":"postalcode"
},
  "geometry": {"coordinates":[-3.03759315821661,53.87047993920075],"type":"Point"}
}