{
  "type": "Feature",
  "properties": {
    "iso:country": "GB",
    "wof:name": "FY5 3QP",
    "wof:placetype": "postalcode"
  },
  "geometry": {"coordinates":[-3.037593,53.87048],"type":"Point"}
}
