{
  "type": "Feature",
  "properties": {
    "iso:country": "GB",
    "wof:name": "NG19 7QP",
    "wof:placetype": "postalcode"
  },
  "geometry": {"coordinates":[-1.249011,53.172866],"type":"Point"}
}
