{
  "type": "Feature",
  "properties": {
    "iso:country":"GB",
    "wof:name":"HR1 2JP",
    "wof:placetype":"postalcode"
},
  "geometry": {"coordinates":[-2.70838193140642,52.05358027789163],"type":"Point"}
}