{
  "type": "Feature",
  "properties": {
    "date:inception_lower":"1980-01-01",
    "date:inception_upper":"1980-01-31",
    "iso:country":"GB",
    "wof:name":"HR1 2JP",
    "wof:placetype":"postalcode"
},
  "geometry": {"coordinates":[-2.708382,52.05358],"type":"Point"}
}