{
  "type": "Feature",
  "properties": {
    "iso:country":"GB",
    "wof:name":"LE17 5JN",
    "wof:placetype":"postalcode"
},
  "geometry": {"coordinates":[-1.19499267297452,52.5117385915981],"type":"Point"}
}