{
  "type": "Feature",
  "properties": {
    "iso:country":"GB",
    "wof:name":"LS28 6ED",
    "wof:placetype":"postalcode"
},
  "geometry": {"coordinates":[-1.66939608132382,53.80551202503491],"type":"Point"}
}