{
  "type": "Feature",
  "properties": {
    "date:inception_lower": "1980-01-01",
    "date:inception_upper": "1980-01-01",
    "iso:country": "GB",
    "wof:name": "LS28 6ED",
    "wof:placetype": "postalcode"
  },
  "geometry": {"coordinates":[-1.669492,53.805546],"type":"Point"}
}
