{
  "type": "Feature",
  "properties": {
    "iso:country":"GB",
    "wof:name":"SA11 2ND",
    "wof:placetype":"postalcode"
},
  "geometry": {"coordinates":[-3.82391028842052,51.63693175582171],"type":"Point"}
}