{
  "type": "Feature",
  "properties": {
    "date:inception_lower": "1980-01-01",
    "date:inception_upper": "1980-01-01",
    "iso:country": "GB",
    "wof:name": "SA11 2ND",
    "wof:placetype": "postalcode"
  },
  "geometry": {"coordinates":[-3.82391,51.636932],"type":"Point"}
}
