{
  "type": "Feature",
  "properties": {
    "iso:country":"GB",
    "wof:name":"PR2 9SA",
    "wof:placetype":"postalcode"
},
  "geometry": {"coordinates":[-2.71137834555003,53.79301602254741],"type":"Point"}
}