{
  "type": "Feature",
  "properties": {
    "iso:country": "GB",
    "wof:name": "DE21 6TP",
    "wof:placetype": "postalcode"
  },
  "geometry": {"coordinates":[-1.425947,52.916911],"type":"Point"}
}
