{
  "type": "Feature",
  "properties": {
    "iso:country":"GB",
    "wof:name":"DE21 6TP",
    "wof:placetype":"postalcode"
},
  "geometry": {"coordinates":[-1.42594696623365,52.91691083021546],"type":"Point"}
}