{
  "type": "Feature",
  "properties": {
    "iso:country":"GB",
    "wof:name":"L39 4TR",
    "wof:placetype":"postalcode"
},
  "geometry": {"coordinates":[-2.88946063396571,53.56101230491605],"type":"Point"}
}