{
  "type": "Feature",
  "properties": {
    "iso:country":"GB",
    "wof:name":"LS11 8DZ",
    "wof:placetype":"postalcode"
},
  "geometry": {"coordinates":[-1.56750879482578,53.7684629690588],"type":"Point"}
}