{
  "type": "Feature",
  "properties": {
    "iso:country":"GB",
    "wof:name":"BS9 4LH",
    "wof:placetype":"postalcode"
},
  "geometry": {"coordinates":[-2.60762422220185,51.48732207147498],"type":"Point"}
}