{
  "type": "Feature",
  "properties": {
    "iso:country":"GB",
    "wof:name":"SA7 9YF",
    "wof:placetype":"postalcode"
},
  "geometry": {"coordinates":[-3.89086933747921,51.64368653345502],"type":"Point"}
}