{
  "type": "Feature",
  "properties": {
    "iso:country":"GB",
    "wof:name":"CF5 5EP",
    "wof:placetype":"postalcode"
},
  "geometry": {"coordinates":[-3.24089595778902,51.47527101942239],"type":"Point"}
}