{
  "type": "Feature",
  "properties": {
    "iso:country":"GB",
    "wof:name":"BR4 0DU",
    "wof:placetype":"postalcode"
},
  "geometry": {"coordinates":[0.00129377701254,51.38337029209211],"type":"Point"}
}