{
  "type": "Feature",
  "properties": {
    "iso:country":"GB",
    "wof:name":"WS3 4PE",
    "wof:placetype":"postalcode"
},
  "geometry": {"coordinates":[-1.97133783368893,52.63174333704001],"type":"Point"}
}