{
  "type": "Feature",
  "properties": {
    "date:inception_lower":"2016-03-01",
    "date:inception_upper":"2016-03-31",
    "iso:country":"GB",
    "wof:name":"CF37 9ZZ",
    "wof:placetype":"postalcode"
},
  "geometry": {"coordinates":[-3.348968,51.595927],"type":"Point"}
}