{
  "type": "Feature",
  "properties": {
    "iso:country": "GB",
    "wof:name": "L17 3BT",
    "wof:placetype": "postalcode"
  },
  "geometry": {"coordinates":[-2.943472,53.390279],"type":"Point"}
}
