{
  "type": "Feature",
  "properties": {
    "date:inception_lower": "2021-09-01",
    "date:inception_upper": "2021-09-01",
    "iso:country": "GB",
    "wof:name": "HP22 4FR",
    "wof:placetype": "postalcode"
  },
  "geometry": {"coordinates":[-0.734251,51.865295],"type":"Point"}
}
