{
  "type": "Feature",
  "properties": {
    "iso:country":"GB",
    "wof:name":"SM6 7DD",
    "wof:placetype":"postalcode"
},
  "geometry": {"coordinates":[-0.15419316597378,51.36934054018112],"type":"Point"}
}