{
  "type": "Feature",
  "properties": {
    "iso:country":"GB",
    "wof:name":"M44 5DF",
    "wof:placetype":"postalcode"
},
  "geometry": {"coordinates":[-2.43945660233938,53.42652841531702],"type":"Point"}
}