{
  "type": "Feature",
  "properties": {
    "iso:country":"GB",
    "wof:name":"DY14 8LD",
    "wof:placetype":"postalcode"
},
  "geometry": {"coordinates":[-2.45554176465417,52.40645334084778],"type":"Point"}
}