{
  "type": "Feature",
  "properties": {
    "date:inception_lower": "1980-01-01",
    "date:inception_upper": "1980-01-01",
    "iso:country": "GB",
    "wof:name": "LU4 9UQ",
    "wof:placetype": "postalcode"
  },
  "geometry": {"coordinates":[-0.504851,51.931246],"type":"Point"}
}
