{
  "type": "Feature",
  "properties": {
    "iso:country":"GB",
    "wof:name":"LU4 9UQ",
    "wof:placetype":"postalcode"
},
  "geometry": {"coordinates":[-0.50485117346494,51.93124627530072],"type":"Point"}
}