{
  "type": "Feature",
  "properties": {
    "iso:country": "GB",
    "wof:name": "LU4 9UQ",
    "wof:placetype": "postalcode"
  },
  "geometry": {"coordinates":[-0.504851,51.931246],"type":"Point"}
}
