{
  "type": "Feature",
  "properties": {
    "iso:country": "GB",
    "wof:name": "M6 7NR",
    "wof:placetype": "postalcode"
  },
  "geometry": {"coordinates":[-2.312412,53.500401],"type":"Point"}
}
