{
  "type": "Feature",
  "properties": {
    "iso:country":"GB",
    "wof:name":"SK12 1AF",
    "wof:placetype":"postalcode"
},
  "geometry": {"coordinates":[-2.12090767550102,53.35129586177688],"type":"Point"}
}