{
  "type": "Feature",
  "properties": {
    "date:inception_lower": "1999-06-01",
    "date:inception_upper": "1999-06-01",
    "iso:country": "GB",
    "wof:name": "CH64 3TH",
    "wof:placetype": "postalcode"
  },
  "geometry": {"coordinates":[-3.06828,53.313413],"type":"Point"}
}
