{
  "type": "Feature",
  "properties": {
    "iso:country": "GB",
    "wof:name": "CH64 3TH",
    "wof:placetype": "postalcode"
  },
  "geometry": {"coordinates":[-3.06828,53.313413],"type":"Point"}
}
