{
  "type": "Feature",
  "properties": {
    "iso:country":"GB",
    "wof:name":"BL8 2DY",
    "wof:placetype":"postalcode"
},
  "geometry": {"coordinates":[-2.32694237798919,53.58624564305079],"type":"Point"}
}