{
  "type": "Feature",
  "properties": {
    "iso:country":"GB",
    "wof:name":"BB5 3RZ",
    "wof:placetype":"postalcode"
},
  "geometry": {"coordinates":[-2.37419369515026,53.72626949754409],"type":"Point"}
}