{
  "type": "Feature",
  "properties": {
    "iso:country": "GB",
    "wof:name": "WD18 7EJ",
    "wof:placetype": "postalcode"
  },
  "geometry": {"coordinates":[-0.41648,51.65144],"type":"Point"}
}
