{
  "type": "Feature",
  "properties": {
    "iso:country":"GB",
    "wof:name":"SE4 2NF",
    "wof:placetype":"postalcode"
},
  "geometry": {"coordinates":[-0.0381515779497,51.46608728010912],"type":"Point"}
}