{
  "type": "Feature",
  "properties": {
    "iso:country":"GB",
    "wof:name":"SN5 8BJ",
    "wof:placetype":"postalcode"
},
  "geometry": {"coordinates":[-1.82345286422583,51.55078789640453],"type":"Point"}
}