{
  "type": "Feature",
  "properties": {
    "iso:country":"GB",
    "wof:name":"WS2 9RJ",
    "wof:placetype":"postalcode"
},
  "geometry": {"coordinates":[-2.00518056633622,52.57732256300163],"type":"Point"}
}