{
  "type": "Feature",
  "properties": {
    "date:inception_lower":"1995-07-01",
    "date:inception_upper":"1995-07-31",
    "iso:country":"GB",
    "wof:name":"SN9 6NB",
    "wof:placetype":"postalcode"
},
  "geometry": {"coordinates":[-1.808665,51.293335],"type":"Point"}
}