{
  "type": "Feature",
  "properties": {
    "iso:country":"GB",
    "wof:name":"SN9 6NB",
    "wof:placetype":"postalcode"
},
  "geometry": {"coordinates":[-1.80866498420309,51.29333538012783],"type":"Point"}
}