{
  "type": "Feature",
  "properties": {
    "iso:country": "GB",
    "wof:name": "SN9 6NB",
    "wof:placetype": "postalcode"
  },
  "geometry": {"coordinates":[-1.808665,51.293335],"type":"Point"}
}
