{
  "type": "Feature",
  "properties": {
    "date:inception_lower":"1980-01-01",
    "date:inception_upper":"1980-01-31",
    "iso:country":"GB",
    "wof:name":"EH42 1ET",
    "wof:placetype":"postalcode"
},
  "geometry": {"coordinates":[-2.51645,56.003832],"type":"Point"}
}