{
  "type": "Feature",
  "properties": {
    "iso:country":"GB",
    "wof:name":"WD18 0HT",
    "wof:placetype":"postalcode"
},
  "geometry": {"coordinates":[-0.40624337146852,51.64965022792838],"type":"Point"}
}