{
  "type": "Feature",
  "properties": {
    "date:inception_lower": "2023-08-01",
    "date:inception_upper": "2023-08-01",
    "iso:country": "GB",
    "wof:name": "PR3 5EX",
    "wof:placetype": "postalcode"
  },
  "geometry": {"coordinates":[-2.719741,53.806401],"type":"Point"}
}
