{
  "type": "Feature",
  "properties": {
    "date:inception_lower":"2003-02-01",
    "date:inception_upper":"2003-02-28",
    "iso:country":"GB",
    "wof:name":"RH10 9DE",
    "wof:placetype":"postalcode"
},
  "geometry": {"coordinates":[-0.169302,51.130602],"type":"Point"}
}