{
  "type": "Feature",
  "properties": {
    "iso:country": "GB",
    "wof:name": "SR2 9DR",
    "wof:placetype": "postalcode"
  },
  "geometry": {"coordinates":[-1.38798,54.885748],"type":"Point"}
}
