{
  "type": "Feature",
  "properties": {
    "iso:country":"GB",
    "wof:name":"SR2 9DR",
    "wof:placetype":"postalcode"
},
  "geometry": {"coordinates":[-1.3879663732799,54.88574030647982],"type":"Point"}
}