{
  "type": "Feature",
  "properties": {
    "iso:country":"GB",
    "wof:name":"CV10 8HW",
    "wof:placetype":"postalcode"
},
  "geometry": {"coordinates":[-1.50485684524975,52.5193553728399],"type":"Point"}
}