{
  "type": "Feature",
  "properties": {
    "iso:country":"GB",
    "wof:name":"G66 7JJ",
    "wof:placetype":"postalcode"
},
  "geometry": {"coordinates":[-4.20206075462426,55.97453185515294],"type":"Point"}
}