{
  "type": "Feature",
  "properties": {
    "iso:country":"GB",
    "wof:name":"GU47 8JF",
    "wof:placetype":"postalcode"
},
  "geometry": {"coordinates":[-0.82343418085663,51.36019446874367],"type":"Point"}
}