{
  "type": "Feature",
  "properties": {
    "iso:country": "GB",
    "wof:name": "GU47 8JF",
    "wof:placetype": "postalcode"
  },
  "geometry": {"coordinates":[-0.823375,51.360167],"type":"Point"}
}
