{
  "type": "Feature",
  "properties": {
    "iso:country":"GB",
    "wof:name":"SE1 6PH",
    "wof:placetype":"postalcode"
},
  "geometry": {"coordinates":[-0.09750821283491,51.49523932358102],"type":"Point"}
}