{
  "type": "Feature",
  "properties": {
    "date:inception_lower": "1980-01-01",
    "date:inception_upper": "1980-01-01",
    "iso:country": "GB",
    "wof:name": "SE1 6PH",
    "wof:placetype": "postalcode"
  },
  "geometry": {"coordinates":[-0.097508,51.495239],"type":"Point"}
}
