{
  "type": "Feature",
  "properties": {
    "iso:country":"GB",
    "wof:name":"NG8 3FG",
    "wof:placetype":"postalcode"
},
  "geometry": {"coordinates":[-1.20114341076013,52.96277140210936],"type":"Point"}
}