{
  "type": "Feature",
  "properties": {
    "iso:country":"GB",
    "wof:name":"CR7 7BR",
    "wof:placetype":"postalcode"
},
  "geometry": {"coordinates":[-0.10251881423848,51.39393742615809],"type":"Point"}
}