{
  "type": "Feature",
  "properties": {
    "iso:country":"GB",
    "wof:name":"W11 4JX",
    "wof:placetype":"postalcode"
},
  "geometry": {"coordinates":[-0.21780359868879,51.50846860923763],"type":"Point"}
}