{
  "type": "Feature",
  "properties": {
    "iso:country":"GB",
    "wof:name":"ST6 4DY",
    "wof:placetype":"postalcode"
},
  "geometry": {"coordinates":[-2.20512640826551,53.0510690798149],"type":"Point"}
}