{
  "type": "Feature",
  "properties": {
    "date:inception_lower": "1995-07-01",
    "date:inception_upper": "1995-07-01",
    "iso:country": "GB",
    "wof:name": "ST6 4DY",
    "wof:placetype": "postalcode"
  },
  "geometry": {"coordinates":[-2.205126,53.051069],"type":"Point"}
}
