{
  "type": "Feature",
  "properties": {
    "iso:country":"GB",
    "wof:name":"KW15 1UP",
    "wof:placetype":"postalcode"
},
  "geometry": {"coordinates":[-2.95173929854167,58.97307589861494],"type":"Point"}
}