{
  "type": "Feature",
  "properties": {
    "date:inception_lower": "2004-04-01",
    "date:inception_upper": "2004-04-01",
    "iso:country": "GB",
    "wof:name": "KW15 1UP",
    "wof:placetype": "postalcode"
  },
  "geometry": {"coordinates":[-2.951739,58.973076],"type":"Point"}
}
