{
  "type": "Feature",
  "properties": {
    "iso:country": "GB",
    "wof:name": "EX4 8HN",
    "wof:placetype": "postalcode"
  },
  "geometry": {"coordinates":[-3.479069,50.735995],"type":"Point"}
}
