{
  "type": "Feature",
  "properties": {
    "iso:country":"GB",
    "wof:name":"G75 8DE",
    "wof:placetype":"postalcode"
},
  "geometry": {"coordinates":[-4.19384500883578,55.75472290527986],"type":"Point"}
}