{
  "type": "Feature",
  "properties": {
    "iso:country": "GB",
    "wof:name": "G75 8DE",
    "wof:placetype": "postalcode"
  },
  "geometry": {"coordinates":[-4.193845,55.754723],"type":"Point"}
}
