{
  "type": "Feature",
  "properties": {
    "iso:country": "GB",
    "wof:name": "PO19 3BL",
    "wof:placetype": "postalcode"
  },
  "geometry": {"coordinates":[-0.780823,50.841413],"type":"Point"}
}
