{
  "type": "Feature",
  "properties": {
    "iso:country":"GB",
    "wof:name":"LE5 5PA",
    "wof:placetype":"postalcode"
},
  "geometry": {"coordinates":[-1.09690353927669,52.62440525359792],"type":"Point"}
}