{
  "type": "Feature",
  "properties": {
    "iso:country": "GB",
    "wof:name": "DE6 1DF",
    "wof:placetype": "postalcode"
  },
  "geometry": {"coordinates":[-1.734259,53.013951],"type":"Point"}
}
