{
  "type": "Feature",
  "properties": {
    "iso:country":"GB",
    "wof:name":"BL3 1RW",
    "wof:placetype":"postalcode"
},
  "geometry": {"coordinates":[-2.40050196338971,53.56963610797836],"type":"Point"}
}