{
  "type": "Feature",
  "properties": {
    "iso:country":"GB",
    "wof:name":"NE48 3JD",
    "wof:placetype":"postalcode"
},
  "geometry": {"coordinates":[-2.11316485669463,55.10046038603883],"type":"Point"}
}