{
  "type": "Feature",
  "properties": {
    "date:inception_lower": "1980-01-01",
    "date:inception_upper": "1980-01-01",
    "iso:country": "GB",
    "wof:name": "NE48 3JD",
    "wof:placetype": "postalcode"
  },
  "geometry": {"coordinates":[-2.113165,55.10046],"type":"Point"}
}
