{
  "type": "Feature",
  "properties": {
    "iso:country":"GB",
    "wof:name":"E5 9RD",
    "wof:placetype":"postalcode"
},
  "geometry": {"coordinates":[-0.05541306729416,51.56221804283957],"type":"Point"}
}