{
  "type": "Feature",
  "properties": {
    "iso:country": "GB",
    "wof:name": "FY5 2QA",
    "wof:placetype": "postalcode"
  },
  "geometry": {"coordinates":[-3.030222,53.884296],"type":"Point"}
}
