{
  "type": "Feature",
  "properties": {
    "iso:country":"GB",
    "wof:name":"FY5 2QA",
    "wof:placetype":"postalcode"
},
  "geometry": {"coordinates":[-3.03022196276033,53.88429551908966],"type":"Point"}
}