{
  "type": "Feature",
  "properties": {
    "iso:country":"GB",
    "wof:name":"E14 0EG",
    "wof:placetype":"postalcode"
},
  "geometry": {"coordinates":[-0.01010057224694,51.51152222353929],"type":"Point"}
}