{
  "type": "Feature",
  "properties": {
    "iso:country": "GB",
    "wof:name": "E14 0EG",
    "wof:placetype": "postalcode"
  },
  "geometry": {"coordinates":[-0.010059,51.511523],"type":"Point"}
}
