{
  "type": "Feature",
  "properties": {
    "iso:country":"GB",
    "wof:name":"SW6 3LJ",
    "wof:placetype":"postalcode"
},
  "geometry": {"coordinates":[-0.21123757091421,51.47079815585968],"type":"Point"}
}