{
  "type": "Feature",
  "properties": {
    "date:inception_lower": "1980-01-01",
    "date:inception_upper": "1980-01-01",
    "iso:country": "GB",
    "wof:name": "G82 5NJ",
    "wof:placetype": "postalcode"
  },
  "geometry": {"coordinates":[-4.654628,55.967867],"type":"Point"}
}
