{
  "type": "Feature",
  "properties": {
    "iso:country":"GB",
    "wof:name":"G82 5NJ",
    "wof:placetype":"postalcode"
},
  "geometry": {"coordinates":[-4.654627697865,55.96786690668411],"type":"Point"}
}