{
  "type": "Feature",
  "properties": {
    "iso:country":"GB",
    "wof:name":"IG1 4UP",
    "wof:placetype":"postalcode"
},
  "geometry": {"coordinates":[0.06416385744288,51.57239628194602],"type":"Point"}
}