{
  "type": "Feature",
  "properties": {
    "iso:country": "GB",
    "wof:name": "CV47 8LL",
    "wof:placetype": "postalcode"
  },
  "geometry": {"coordinates":[-1.366976,52.277707],"type":"Point"}
}
