{
  "type": "Feature",
  "properties": {
    "iso:country":"GB",
    "wof:name":"CV47 8LL",
    "wof:placetype":"postalcode"
},
  "geometry": {"coordinates":[-1.36697619571992,52.2777066418038],"type":"Point"}
}