{
  "type": "Feature",
  "properties": {
    "iso:country": "GB",
    "wof:name": "SO31 8GQ",
    "wof:placetype": "postalcode"
  },
  "geometry": {"coordinates":[-1.323656,50.881862],"type":"Point"}
}
