{
  "type": "Feature",
  "properties": {
    "date:inception_lower": "1994-12-01",
    "date:inception_upper": "1994-12-01",
    "iso:country": "GB",
    "wof:name": "SO31 8GQ",
    "wof:placetype": "postalcode"
  },
  "geometry": {"coordinates":[-1.323656,50.881862],"type":"Point"}
}
