{
  "type": "Feature",
  "properties": {
    "date:inception_lower": "1980-01-01",
    "date:inception_upper": "1980-01-01",
    "iso:country": "GB",
    "wof:name": "SA18 1EY",
    "wof:placetype": "postalcode"
  },
  "geometry": {"coordinates":[-3.884107,51.791995],"type":"Point"}
}
