{
  "type": "Feature",
  "properties": {
    "date:inception_lower": "1980-01-01",
    "date:inception_upper": "1980-01-01",
    "iso:country": "GB",
    "wof:name": "SA18 1EY",
    "wof:placetype": "postalcode"
  },
  "geometry": {"coordinates":[-3.884556,51.791987],"type":"Point"}
}
