{
  "type": "Feature",
  "properties": {
    "iso:country":"GB",
    "wof:name":"SA18 1EY",
    "wof:placetype":"postalcode"
},
  "geometry": {"coordinates":[-3.88408944632912,51.79198790395935],"type":"Point"}
}