{
  "type": "Feature",
  "properties": {
    "iso:country":"GB",
    "wof:name":"HD9 4EW",
    "wof:placetype":"postalcode"
},
  "geometry": {"coordinates":[-1.84959938904748,53.59034694889773],"type":"Point"}
}