{
  "type": "Feature",
  "properties": {
    "iso:country": "GB",
    "wof:name": "LA16 7EZ",
    "wof:placetype": "postalcode"
  },
  "geometry": {"coordinates":[-3.190889,54.193818],"type":"Point"}
}
