{
  "type": "Feature",
  "properties": {
    "iso:country": "GB",
    "wof:name": "EX4 6TP",
    "wof:placetype": "postalcode"
  },
  "geometry": {"coordinates":[-3.52469,50.735202],"type":"Point"}
}
