{
  "type": "Feature",
  "properties": {
    "date:inception_lower": "1999-06-01",
    "date:inception_upper": "1999-06-01",
    "iso:country": "GB",
    "wof:name": "TW20 9HX",
    "wof:placetype": "postalcode"
  },
  "geometry": {"coordinates":[-0.543031,51.431895],"type":"Point"}
}
