{
  "type": "Feature",
  "properties": {
    "iso:country":"GB",
    "wof:name":"DG9 7PW",
    "wof:placetype":"postalcode"
},
  "geometry": {"coordinates":[-5.03476774828566,54.90188822653033],"type":"Point"}
}