{
  "type": "Feature",
  "properties": {
    "iso:country":"GB",
    "wof:name":"NW10 0TG",
    "wof:placetype":"postalcode"
},
  "geometry": {"coordinates":[-0.26287839056079,51.5554554262635],"type":"Point"}
}