{
  "type": "Feature",
  "properties": {
    "date:inception_lower":"1993-01-01",
    "date:inception_upper":"1993-01-31",
    "iso:country":"GB",
    "wof:name":"NW10 0TG",
    "wof:placetype":"postalcode"
},
  "geometry": {"coordinates":[-0.262878,51.555455],"type":"Point"}
}