{
  "type": "Feature",
  "properties": {
    "iso:country": "GB",
    "wof:name": "GU34 3BY",
    "wof:placetype": "postalcode"
  },
  "geometry": {"coordinates":[-0.922637,51.100055],"type":"Point"}
}
