{
  "type": "Feature",
  "properties": {
    "iso:country": "GB",
    "wof:name": "B61 0FH",
    "wof:placetype": "postalcode"
  },
  "geometry": {"coordinates":[-2.05434,52.347809],"type":"Point"}
}
