{
  "type": "Feature",
  "properties": {
    "iso:country": "GB",
    "wof:name": "CA10 2BQ",
    "wof:placetype": "postalcode"
  },
  "geometry": {"coordinates":[-2.745038,54.651428],"type":"Point"}
}
