{
  "type": "Feature",
  "properties": {
    "iso:country": "GB",
    "wof:name": "CW12 3DA",
    "wof:placetype": "postalcode"
  },
  "geometry": {"coordinates":[-2.191792,53.15896],"type":"Point"}
}
