{
  "type": "Feature",
  "properties": {
    "date:inception_lower": "1985-04-01",
    "date:inception_upper": "1985-04-01",
    "iso:country": "GB",
    "wof:name": "UB10 8UH",
    "wof:placetype": "postalcode"
  },
  "geometry": {"coordinates":[-0.433646,51.567508],"type":"Point"}
}
