{
  "type": "Feature",
  "properties": {
    "iso:country":"GB",
    "wof:name":"UB10 8UH",
    "wof:placetype":"postalcode"
},
  "geometry": {"coordinates":[-0.4336460783715,51.56750777014602],"type":"Point"}
}