{
  "type": "Feature",
  "properties": {
    "iso:country": "GB",
    "wof:name": "DE6 2AD",
    "wof:placetype": "postalcode"
  },
  "geometry": {"coordinates":[-1.812277,53.085131],"type":"Point"}
}
