{
  "type": "Feature",
  "properties": {
    "iso:country":"GB",
    "wof:name":"DE6 2AD",
    "wof:placetype":"postalcode"
},
  "geometry": {"coordinates":[-1.81227707299926,53.08513131534152],"type":"Point"}
}