{
  "type": "Feature",
  "properties": {
    "date:inception_lower": "1980-01-01",
    "date:inception_upper": "1980-01-01",
    "iso:country": "GB",
    "wof:name": "DE6 2AD",
    "wof:placetype": "postalcode"
  },
  "geometry": {"coordinates":[-1.812277,53.085131],"type":"Point"}
}
