{
  "type": "Feature",
  "properties": {
    "iso:country":"GB",
    "wof:name":"S71 4BG",
    "wof:placetype":"postalcode"
},
  "geometry": {"coordinates":[-1.43439519253068,53.60799020755218],"type":"Point"}
}