{
  "type": "Feature",
  "properties": {
    "iso:country":"GB",
    "wof:name":"RM12 4QH",
    "wof:placetype":"postalcode"
},
  "geometry": {"coordinates":[0.199248756317,51.55282855107296],"type":"Point"}
}