{
  "type": "Feature",
  "properties": {
    "date:inception_lower":"2008-02-01",
    "date:inception_upper":"2008-02-29",
    "iso:country":"GB",
    "wof:name":"BS20 0AF",
    "wof:placetype":"postalcode"
},
  "geometry": {"coordinates":[-2.683649,51.478298],"type":"Point"}
}