{
  "type": "Feature",
  "properties": {
    "iso:country":"GB",
    "wof:name":"BS20 0AF",
    "wof:placetype":"postalcode"
},
  "geometry": {"coordinates":[-2.68364892687879,51.47829839418151],"type":"Point"}
}