{
  "type": "Feature",
  "properties": {
    "iso:country":"GB",
    "wof:name":"DY1 2EL",
    "wof:placetype":"postalcode"
},
  "geometry": {"coordinates":[-2.11099445498245,52.499013578667],"type":"Point"}
}