{
  "type": "Feature",
  "properties": {
    "date:inception_lower": "1980-01-01",
    "date:inception_upper": "1980-01-01",
    "iso:country": "GB",
    "wof:name": "TN15 0HL",
    "wof:placetype": "postalcode"
  },
  "geometry": {"coordinates":[0.207451,51.281974],"type":"Point"}
}
