{
  "type": "Feature",
  "properties": {
    "iso:country":"GB",
    "wof:name":"TN15 0HL",
    "wof:placetype":"postalcode"
},
  "geometry": {"coordinates":[0.20745086464474,51.28197412433931],"type":"Point"}
}