{
  "type": "Feature",
  "properties": {
    "iso:country": "GB",
    "wof:name": "TN15 0HL",
    "wof:placetype": "postalcode"
  },
  "geometry": {"coordinates":[0.207451,51.281974],"type":"Point"}
}
