{
  "type": "Feature",
  "properties": {
    "iso:country":"GB",
    "wof:name":"N22 5RR",
    "wof:placetype":"postalcode"
},
  "geometry": {"coordinates":[-0.10477556330819,51.60093794011907],"type":"Point"}
}