{
  "type": "Feature",
  "properties": {
    "iso:country":"GB",
    "wof:name":"CO1 2LF",
    "wof:placetype":"postalcode"
},
  "geometry": {"coordinates":[0.91197890710941,51.88544829840514],"type":"Point"}
}