{
  "type": "Feature",
  "properties": {
    "iso:country":"GB",
    "wof:name":"YO62 5NF",
    "wof:placetype":"postalcode"
},
  "geometry": {"coordinates":[-1.13929046717139,54.32759216316667],"type":"Point"}
}