{
  "type": "Feature",
  "properties": {
    "iso:country": "GB",
    "wof:name": "YO62 5NF",
    "wof:placetype": "postalcode"
  },
  "geometry": {"coordinates":[-1.13929,54.327592],"type":"Point"}
}
