{
  "type": "Feature",
  "properties": {
    "iso:country":"GB",
    "wof:name":"WS5 3EL",
    "wof:placetype":"postalcode"
},
  "geometry": {"coordinates":[-1.94121281190944,52.57547430624115],"type":"Point"}
}