{
  "type": "Feature",
  "properties": {
    "iso:country":"GB",
    "wof:name":"CF83 1RL",
    "wof:placetype":"postalcode"
},
  "geometry": {"coordinates":[-3.2103400189248,51.57795396011613],"type":"Point"}
}