{
  "type": "Feature",
  "properties": {
    "iso:country":"GB",
    "wof:name":"BN27 3PR",
    "wof:placetype":"postalcode"
},
  "geometry": {"coordinates":[0.23515181752216,50.86657564315247],"type":"Point"}
}