{
  "type": "Feature",
  "properties": {
    "date:inception_lower": "1980-01-01",
    "date:inception_upper": "1980-01-01",
    "iso:country": "GB",
    "wof:name": "BN27 3PR",
    "wof:placetype": "postalcode"
  },
  "geometry": {"coordinates":[0.235223,50.866588],"type":"Point"}
}
