{
  "type": "Feature",
  "properties": {
    "iso:country": "GB",
    "wof:name": "PR3 1RA",
    "wof:placetype": "postalcode"
  },
  "geometry": {"coordinates":[-2.773375,53.897694],"type":"Point"}
}
