{
  "type": "Feature",
  "properties": {
    "iso:country": "GB",
    "wof:name": "DY7 5HP",
    "wof:placetype": "postalcode"
  },
  "geometry": {"coordinates":[-2.252928,52.482011],"type":"Point"}
}
