{
  "type": "Feature",
  "properties": {
    "date:inception_lower": "1980-01-01",
    "date:inception_upper": "1980-01-01",
    "iso:country": "GB",
    "wof:name": "DY7 5HP",
    "wof:placetype": "postalcode"
  },
  "geometry": {"coordinates":[-2.252928,52.482011],"type":"Point"}
}
