{
  "type": "Feature",
  "properties": {
    "iso:country": "GB",
    "wof:name": "TW14 8LJ",
    "wof:placetype": "postalcode"
  },
  "geometry": {"coordinates":[-0.440719,51.453878],"type":"Point"}
}
