{
  "type": "Feature",
  "properties": {
    "iso:country":"GB",
    "wof:name":"YO16 7JZ",
    "wof:placetype":"postalcode"
},
  "geometry": {"coordinates":[-0.20349732933262,54.09246191656158],"type":"Point"}
}