{
  "type": "Feature",
  "properties": {
    "iso:country": "GB",
    "wof:name": "LA20 6AX",
    "wof:placetype": "postalcode"
  },
  "geometry": {"coordinates":[-3.197525,54.303898],"type":"Point"}
}
