{
  "type": "Feature",
  "properties": {
    "date:inception_lower": "1980-01-01",
    "date:inception_upper": "1980-01-01",
    "iso:country": "GB",
    "wof:name": "LA20 6AX",
    "wof:placetype": "postalcode"
  },
  "geometry": {"coordinates":[-3.198973,54.303488],"type":"Point"}
}
