{
  "type": "Feature",
  "properties": {
    "iso:country": "GB",
    "wof:name": "NN4 6NA",
    "wof:placetype": "postalcode"
  },
  "geometry": {"coordinates":[-0.890725,52.199094],"type":"Point"}
}
