{
  "type": "Feature",
  "properties": {
    "iso:country":"GB",
    "wof:name":"CW7 2DP",
    "wof:placetype":"postalcode"
},
  "geometry": {"coordinates":[-2.53263586352129,53.19225133916296],"type":"Point"}
}