{
  "type": "Feature",
  "properties": {
    "date:inception_lower": "1998-06-01",
    "date:inception_upper": "1998-06-01",
    "iso:country": "GB",
    "wof:name": "YO19 6NX",
    "wof:placetype": "postalcode"
  },
  "geometry": {"coordinates":[-1.060336,53.835275],"type":"Point"}
}
