{
  "type": "Feature",
  "properties": {
    "iso:country":"GB",
    "wof:name":"ME1 3DQ",
    "wof:placetype":"postalcode"
},
  "geometry": {"coordinates":[0.49488889704687,51.35993932108615],"type":"Point"}
}