{
  "type": "Feature",
  "properties": {
    "iso:country":"GB",
    "wof:name":"EH13 9DJ",
    "wof:placetype":"postalcode"
},
  "geometry": {"coordinates":[-3.23339729029899,55.90778343786676],"type":"Point"}
}