{
  "type": "Feature",
  "properties": {
    "date:inception_lower": "2005-08-01",
    "date:inception_upper": "2005-08-01",
    "iso:country": "GB",
    "wof:name": "HA4 0BG",
    "wof:placetype": "postalcode"
  },
  "geometry": {"coordinates":[-0.382419,51.556256],"type":"Point"}
}
