{
  "type": "Feature",
  "properties": {
    "iso:country":"GB",
    "wof:name":"HA4 0BG",
    "wof:placetype":"postalcode"
},
  "geometry": {"coordinates":[-0.38241933477042,51.55625603677534],"type":"Point"}
}