{
  "type": "Feature",
  "properties": {
    "iso:country": "GB",
    "wof:name": "WR11 7FA",
    "wof:placetype": "postalcode"
  },
  "geometry": {"coordinates":[-1.895704,52.088211],"type":"Point"}
}
