{
  "type": "Feature",
  "properties": {
    "iso:country":"GB",
    "wof:name":"WR11 7FA",
    "wof:placetype":"postalcode"
},
  "geometry": {"coordinates":[-1.89570359263542,52.08821081475097],"type":"Point"}
}