{
  "type": "Feature",
  "properties": {
    "iso:country":"GB",
    "wof:name":"LA5 9QA",
    "wof:placetype":"postalcode"
},
  "geometry": {"coordinates":[-2.76458441040525,54.14926704365789],"type":"Point"}
}