{
  "type": "Feature",
  "properties": {
    "iso:country": "GB",
    "wof:name": "LA5 9QA",
    "wof:placetype": "postalcode"
  },
  "geometry": {"coordinates":[-2.764631,54.149358],"type":"Point"}
}
