{
  "type": "Feature",
  "properties": {
    "iso:country":"GB",
    "wof:name":"DA6 7EQ",
    "wof:placetype":"postalcode"
},
  "geometry": {"coordinates":[0.14404845993676,51.45808538120153],"type":"Point"}
}