{
  "type": "Feature",
  "properties": {
    "date:inception_lower":"1993-01-01",
    "date:inception_upper":"1993-01-31",
    "iso:country":"GB",
    "wof:name":"CV37 0EQ",
    "wof:placetype":"postalcode"
},
  "geometry": {"coordinates":[-1.710192,52.204841],"type":"Point"}
}