{
  "type": "Feature",
  "properties": {
    "iso:country":"GB",
    "wof:name":"CV37 0EQ",
    "wof:placetype":"postalcode"
},
  "geometry": {"coordinates":[-1.71019224486161,52.20484055043453],"type":"Point"}
}