{
  "type": "Feature",
  "properties": {
    "iso:country":"GB",
    "wof:name":"EX7 0JS",
    "wof:placetype":"postalcode"
},
  "geometry": {"coordinates":[-3.48109074191033,50.56448512289271],"type":"Point"}
}