{
  "type": "Feature",
  "properties": {
    "iso:country":"GB",
    "wof:name":"OL8 4HH",
    "wof:placetype":"postalcode"
},
  "geometry": {"coordinates":[-2.11917553609999,53.52682510134057],"type":"Point"}
}