{
  "type": "Feature",
  "properties": {
    "iso:country":"GB",
    "wof:name":"HD2 2PG",
    "wof:placetype":"postalcode"
},
  "geometry": {"coordinates":[-1.79056787481467,53.66522914580882],"type":"Point"}
}