{
  "type": "Feature",
  "properties": {
    "date:inception_lower":"1980-01-01",
    "date:inception_upper":"1980-01-31",
    "iso:country":"GB",
    "wof:name":"HD2 2PG",
    "wof:placetype":"postalcode"
},
  "geometry": {"coordinates":[-1.790568,53.665229],"type":"Point"}
}