{
  "type": "Feature",
  "properties": {
    "iso:country": "GB",
    "wof:name": "S81 7QX",
    "wof:placetype": "postalcode"
  },
  "geometry": {"coordinates":[-1.130818,53.333587],"type":"Point"}
}
