{
  "type": "Feature",
  "properties": {
    "date:inception_lower": "1998-12-01",
    "date:inception_upper": "1998-12-01",
    "iso:country": "GB",
    "wof:name": "S81 7QX",
    "wof:placetype": "postalcode"
  },
  "geometry": {"coordinates":[-1.130818,53.333598],"type":"Point"}
}
