{
  "type": "Feature",
  "properties": {
    "iso:country":"GB",
    "wof:name":"S81 7QX",
    "wof:placetype":"postalcode"
},
  "geometry": {"coordinates":[-1.13081795916704,53.33358719917504],"type":"Point"}
}