{
  "type": "Feature",
  "properties": {
    "iso:country":"GB",
    "wof:name":"NE26 1ED",
    "wof:placetype":"postalcode"
},
  "geometry": {"coordinates":[-1.44974009818823,55.04483338304914],"type":"Point"}
}