{
  "type": "Feature",
  "properties": {
    "date:inception_lower": "1980-01-01",
    "date:inception_upper": "1980-01-01",
    "iso:country": "GB",
    "wof:name": "SN12 7NB",
    "wof:placetype": "postalcode"
  },
  "geometry": {"coordinates":[-2.132923,51.372426],"type":"Point"}
}
