{
  "type": "Feature",
  "properties": {
    "date:inception_lower": "2001-12-01",
    "date:inception_upper": "2001-12-01",
    "iso:country": "GB",
    "wof:name": "LS9 7JD",
    "wof:placetype": "postalcode"
  },
  "geometry": {"coordinates":[-1.52787,53.803295],"type":"Point"}
}
