{
  "type": "Feature",
  "properties": {
    "iso:country": "GB",
    "wof:name": "RM13 9QY",
    "wof:placetype": "postalcode"
  },
  "geometry": {"coordinates":[0.210152,51.528389],"type":"Point"}
}
