{
  "type": "Feature",
  "properties": {
    "date:inception_lower": "1993-08-01",
    "date:inception_upper": "1993-08-01",
    "iso:country": "GB",
    "wof:name": "RM13 9QY",
    "wof:placetype": "postalcode"
  },
  "geometry": {"coordinates":[0.210259,51.528217],"type":"Point"}
}
