{
  "type": "Feature",
  "properties": {
    "iso:country":"GB",
    "wof:name":"SN25 1QH",
    "wof:placetype":"postalcode"
},
  "geometry": {"coordinates":[-1.80741834742814,51.59111596336536],"type":"Point"}
}