{
  "type": "Feature",
  "properties": {
    "date:inception_lower": "1993-08-01",
    "date:inception_upper": "1993-08-01",
    "iso:country": "GB",
    "wof:name": "MK6 1NE",
    "wof:placetype": "postalcode"
  },
  "geometry": {"coordinates":[-0.755101,52.021689],"type":"Point"}
}
