{
  "type": "Feature",
  "properties": {
    "iso:country": "GB",
    "wof:name": "PE27 3EB",
    "wof:placetype": "postalcode"
  },
  "geometry": {"coordinates":[-0.074144,52.341583],"type":"Point"}
}
