{
  "type": "Feature",
  "properties": {
    "date:inception_lower":"2000-06-01",
    "date:inception_upper":"2000-06-30",
    "iso:country":"GB",
    "wof:name":"PE27 3EB",
    "wof:placetype":"postalcode"
},
  "geometry": {"coordinates":[-0.074144,52.341583],"type":"Point"}
}