{
  "type": "Feature",
  "properties": {
    "iso:country":"GB",
    "wof:name":"CV6 3DR",
    "wof:placetype":"postalcode"
},
  "geometry": {"coordinates":[-1.51781388730487,52.43284369198459],"type":"Point"}
}