{
  "type": "Feature",
  "properties": {
    "iso:country": "GB",
    "wof:name": "CV6 3DR",
    "wof:placetype": "postalcode"
  },
  "geometry": {"coordinates":[-1.517814,52.432844],"type":"Point"}
}
