{
  "type": "Feature",
  "properties": {
    "iso:country":"GB",
    "wof:name":"RM3 0RB",
    "wof:placetype":"postalcode"
},
  "geometry": {"coordinates":[0.23777917141174,51.59308952458038],"type":"Point"}
}