{
  "type": "Feature",
  "properties": {
    "iso:country": "GB",
    "wof:name": "RM3 0RB",
    "wof:placetype": "postalcode"
  },
  "geometry": {"coordinates":[0.237724,51.593201],"type":"Point"}
}
