{
  "type": "Feature",
  "properties": {
    "iso:country":"GB",
    "wof:name":"W6 9SR",
    "wof:placetype":"postalcode"
},
  "geometry": {"coordinates":[-0.22145503195134,51.48315636229566],"type":"Point"}
}