{
  "type": "Feature",
  "properties": {
    "date:inception_lower":"1980-01-01",
    "date:inception_upper":"1980-01-31",
    "iso:country":"GB",
    "wof:name":"KA15 1HR",
    "wof:placetype":"postalcode"
},
  "geometry": {"coordinates":[-4.606607,55.730908],"type":"Point"}
}