{
  "type": "Feature",
  "properties": {
    "iso:country":"GB",
    "wof:name":"KA15 1HR",
    "wof:placetype":"postalcode"
},
  "geometry": {"coordinates":[-4.60660722975706,55.73090828458706],"type":"Point"}
}