{
  "type": "Feature",
  "properties": {
    "iso:country":"GB",
    "wof:name":"DN22 8AD",
    "wof:placetype":"postalcode"
},
  "geometry": {"coordinates":[-0.9776815899754,53.270465716933],"type":"Point"}
}