{
  "type": "Feature",
  "properties": {
    "iso:country": "GB",
    "wof:name": "DN22 8AD",
    "wof:placetype": "postalcode"
  },
  "geometry": {"coordinates":[-0.977682,53.270466],"type":"Point"}
}
