{
  "type": "Feature",
  "properties": {
    "date:inception_lower": "1980-01-01",
    "date:inception_upper": "1980-01-01",
    "iso:country": "GB",
    "wof:name": "DN22 8AD",
    "wof:placetype": "postalcode"
  },
  "geometry": {"coordinates":[-0.977725,53.270486],"type":"Point"}
}
