{
  "type": "Feature",
  "properties": {
    "iso:country":"GB",
    "wof:name":"BS9 2EE",
    "wof:placetype":"postalcode"
},
  "geometry": {"coordinates":[-2.64936075869691,51.48823126445572],"type":"Point"}
}