{
  "type": "Feature",
  "properties": {
    "date:inception_lower":"1980-01-01",
    "date:inception_upper":"1980-01-31",
    "iso:country":"GB",
    "wof:name":"CV13 6AB",
    "wof:placetype":"postalcode"
},
  "geometry": {"coordinates":[-1.446474,52.549312],"type":"Point"}
}