{
  "type": "Feature",
  "properties": {
    "iso:country": "GB",
    "wof:name": "CV13 6AB",
    "wof:placetype": "postalcode"
  },
  "geometry": {"coordinates":[-1.446474,52.549312],"type":"Point"}
}
