{
  "type": "Feature",
  "properties": {
    "iso:country":"GB",
    "wof:name":"S17 3PW",
    "wof:placetype":"postalcode"
},
  "geometry": {"coordinates":[-1.53865224459052,53.32000389251073],"type":"Point"}
}