{
  "type": "Feature",
  "properties": {
    "iso:country": "GB",
    "wof:name": "SY11 3DZ",
    "wof:placetype": "postalcode"
  },
  "geometry": {"coordinates":[-2.995612,52.924668],"type":"Point"}
}
