{
  "type": "Feature",
  "properties": {
    "iso:country":"GB",
    "wof:name":"SY11 3DZ",
    "wof:placetype":"postalcode"
},
  "geometry": {"coordinates":[-2.995612268803,52.92466750569235],"type":"Point"}
}