{
  "type": "Feature",
  "properties": {
    "iso:country": "GB",
    "wof:name": "YO10 4JN",
    "wof:placetype": "postalcode"
  },
  "geometry": {"coordinates":[-1.076715,53.940357],"type":"Point"}
}
