{
  "type": "Feature",
  "properties": {
    "date:inception_lower": "1980-01-01",
    "date:inception_upper": "1980-01-01",
    "iso:country": "GB",
    "wof:name": "FK9 5DH",
    "wof:placetype": "postalcode"
  },
  "geometry": {"coordinates":[-3.940544,56.135961],"type":"Point"}
}
