{
  "type": "Feature",
  "properties": {
    "iso:country":"GB",
    "wof:name":"DE15 0SA",
    "wof:placetype":"postalcode"
},
  "geometry": {"coordinates":[-1.58220264142736,52.82918766317812],"type":"Point"}
}