{
  "type": "Feature",
  "properties": {
    "iso:country": "GB",
    "wof:name": "TN12 9HG",
    "wof:placetype": "postalcode"
  },
  "geometry": {"coordinates":[0.499491,51.172736],"type":"Point"}
}
