{
  "type": "Feature",
  "properties": {
    "iso:country":"GB",
    "wof:name":"LE7 7ZJ",
    "wof:placetype":"postalcode"
},
  "geometry": {"coordinates":[-1.13799005772386,52.70919869467281],"type":"Point"}
}