{
  "type": "Feature",
  "properties": {
    "iso:country": "GB",
    "wof:name": "SA14 8WA",
    "wof:placetype": "postalcode"
  },
  "geometry": {"coordinates":[-4.092691,51.691807],"type":"Point"}
}
