{
  "type": "Feature",
  "properties": {
    "date:inception_lower":"1991-09-01",
    "date:inception_upper":"1991-09-30",
    "iso:country":"GB",
    "wof:name":"SA14 8WA",
    "wof:placetype":"postalcode"
},
  "geometry": {"coordinates":[-4.092691,51.691807],"type":"Point"}
}