{
  "type": "Feature",
  "properties": {
    "iso:country":"GB",
    "wof:name":"M35 0NQ",
    "wof:placetype":"postalcode"
},
  "geometry": {"coordinates":[-2.15798359291135,53.50126198974935],"type":"Point"}
}