{
  "type": "Feature",
  "properties": {
    "date:inception_lower": "1994-05-01",
    "date:inception_upper": "1994-05-01",
    "iso:country": "GB",
    "wof:name": "TS15 9QF",
    "wof:placetype": "postalcode"
  },
  "geometry": {"coordinates":[-1.352946,54.501984],"type":"Point"}
}
