{
  "type": "Feature",
  "properties": {
    "date:inception_lower": "2019-12-01",
    "date:inception_upper": "2019-12-01",
    "iso:country": "GB",
    "wof:name": "WA1 2PB",
    "wof:placetype": "postalcode"
  },
  "geometry": {"coordinates":[-2.577486,53.390829],"type":"Point"}
}
