{
  "type": "Feature",
  "properties": {
    "iso:country":"GB",
    "wof:name":"BH20 5HD",
    "wof:placetype":"postalcode"
},
  "geometry": {"coordinates":[-2.05737346912349,50.63746241960606],"type":"Point"}
}