{
  "type": "Feature",
  "properties": {
    "iso:country":"GB",
    "wof:name":"HA3 5PZ",
    "wof:placetype":"postalcode"
},
  "geometry": {"coordinates":[-0.3460165390613,51.60258889084388],"type":"Point"}
}