{
  "type": "Feature",
  "properties": {
    "date:inception_lower": "1980-01-01",
    "date:inception_upper": "1980-01-01",
    "iso:country": "GB",
    "wof:name": "TW3 1UE",
    "wof:placetype": "postalcode"
  },
  "geometry": {"coordinates":[-0.359041,51.469075],"type":"Point"}
}
