{
  "type": "Feature",
  "properties": {
    "iso:country": "GB",
    "wof:name": "TW3 1UE",
    "wof:placetype": "postalcode"
  },
  "geometry": {"coordinates":[-0.359041,51.469075],"type":"Point"}
}
