{
  "type": "Feature",
  "properties": {
    "iso:country":"GB",
    "wof:name":"FY5 4HG",
    "wof:placetype":"postalcode"
},
  "geometry": {"coordinates":[-3.00612131844327,53.87914299703193],"type":"Point"}
}