{
  "type": "Feature",
  "properties": {
    "iso:country": "GB",
    "wof:name": "ME13 0EY",
    "wof:placetype": "postalcode"
  },
  "geometry": {"coordinates":[0.860658,51.294093],"type":"Point"}
}
