{
  "type": "Feature",
  "properties": {
    "iso:country": "GB",
    "wof:name": "WR10 3BZ",
    "wof:placetype": "postalcode"
  },
  "geometry": {"coordinates":[-2.110909,52.093358],"type":"Point"}
}
