{
  "type": "Feature",
  "properties": {
    "iso:country":"GB",
    "wof:name":"WR10 3BZ",
    "wof:placetype":"postalcode"
},
  "geometry": {"coordinates":[-2.11142229950964,52.09121564885492],"type":"Point"}
}