{
  "type": "Feature",
  "properties": {
    "iso:country": "GB",
    "wof:name": "SA69 9HR",
    "wof:placetype": "postalcode"
  },
  "geometry": {"coordinates":[-4.703185,51.706967],"type":"Point"}
}
