{
  "type": "Feature",
  "properties": {
    "iso:country":"GB",
    "wof:name":"YO62 6PA",
    "wof:placetype":"postalcode"
},
  "geometry": {"coordinates":[-0.91843776010446,54.24704660114892],"type":"Point"}
}