{
  "type": "Feature",
  "properties": {
    "iso:country": "GB",
    "wof:name": "YO62 6PA",
    "wof:placetype": "postalcode"
  },
  "geometry": {"coordinates":[-0.918438,54.247047],"type":"Point"}
}
