{
  "type": "Feature",
  "properties": {
    "iso:country": "GB",
    "wof:name": "BD24 9RX",
    "wof:placetype": "postalcode"
  },
  "geometry": {"coordinates":[-2.277763,54.068942],"type":"Point"}
}
