{
  "type": "Feature",
  "properties": {
    "iso:country":"GB",
    "wof:name":"BD24 9RX",
    "wof:placetype":"postalcode"
},
  "geometry": {"coordinates":[-2.27776329615134,54.06894163982399],"type":"Point"}
}