{
  "type": "Feature",
  "properties": {
    "iso:country": "GB",
    "wof:name": "NG31 7RZ",
    "wof:placetype": "postalcode"
  },
  "geometry": {"coordinates":[-0.646224,52.905951],"type":"Point"}
}
