{
  "type": "Feature",
  "properties": {
    "date:inception_lower": "1993-08-01",
    "date:inception_upper": "1993-08-01",
    "iso:country": "GB",
    "wof:name": "CH1 5XT",
    "wof:placetype": "postalcode"
  },
  "geometry": {"coordinates":[-2.910398,53.207905],"type":"Point"}
}
