{
  "type": "Feature",
  "properties": {
    "iso:country":"GB",
    "wof:name":"CH1 5XT",
    "wof:placetype":"postalcode"
},
  "geometry": {"coordinates":[-2.91039749928345,53.20788731144007],"type":"Point"}
}