{
  "type": "Feature",
  "properties": {
    "iso:country":"GB",
    "wof:name":"S25 5EG",
    "wof:placetype":"postalcode"
},
  "geometry": {"coordinates":[-1.22432567693957,53.35108563960215],"type":"Point"}
}