{
  "type": "Feature",
  "properties": {
    "iso:country": "GB",
    "wof:name": "LN5 7UX",
    "wof:placetype": "postalcode"
  },
  "geometry": {"coordinates":[-0.538126,53.221632],"type":"Point"}
}
