{
  "type": "Feature",
  "properties": {
    "iso:country":"GB",
    "wof:name":"LN5 7UX",
    "wof:placetype":"postalcode"
},
  "geometry": {"coordinates":[-0.53812619693017,53.22163162364399],"type":"Point"}
}