{
  "type": "Feature",
  "properties": {
    "date:inception_lower": "2005-06-01",
    "date:inception_upper": "2005-06-01",
    "iso:country": "GB",
    "wof:name": "AB51 0SQ",
    "wof:placetype": "postalcode"
  },
  "geometry": {"coordinates":[-2.356803,57.231285],"type":"Point"}
}
