{
  "type": "Feature",
  "properties": {
    "iso:country":"GB",
    "wof:name":"ME17 3AU",
    "wof:placetype":"postalcode"
},
  "geometry": {"coordinates":[0.58943865133756,51.20771739650483],"type":"Point"}
}