{
  "type": "Feature",
  "properties": {
    "date:inception_lower":"1980-01-01",
    "date:inception_upper":"1980-01-31",
    "iso:country":"GB",
    "wof:name":"ME17 3AU",
    "wof:placetype":"postalcode"
},
  "geometry": {"coordinates":[0.589599,51.208001],"type":"Point"}
}