{
  "type": "Feature",
  "properties": {
    "date:inception_lower": "1980-01-01",
    "date:inception_upper": "1980-01-01",
    "iso:country": "GB",
    "wof:name": "WS3 4DG",
    "wof:placetype": "postalcode"
  },
  "geometry": {"coordinates":[-1.969205,52.618609],"type":"Point"}
}
