{
  "type": "Feature",
  "properties": {
    "date:inception_lower": "2021-09-01",
    "date:inception_upper": "2021-09-01",
    "iso:country": "GB",
    "wof:name": "DY7 5DN",
    "wof:placetype": "postalcode"
  },
  "geometry": {"coordinates":[-2.296206,52.48722],"type":"Point"}
}
