{
  "type": "Feature",
  "properties": {
    "iso:country":"GB",
    "wof:name":"HA7 3JJ",
    "wof:placetype":"postalcode"
},
  "geometry": {"coordinates":[-0.33543369463925,51.61833743421982],"type":"Point"}
}