{
  "type": "Feature",
  "properties": {
    "date:inception_lower": "2010-04-01",
    "date:inception_upper": "2010-04-01",
    "iso:country": "GB",
    "wof:name": "EX8 5RA",
    "wof:placetype": "postalcode"
  },
  "geometry": {"coordinates":[-3.419941,50.660361],"type":"Point"}
}
