{
  "type": "Feature",
  "properties": {
    "iso:country":"GB",
    "wof:name":"EX8 5RA",
    "wof:placetype":"postalcode"
},
  "geometry": {"coordinates":[-3.41994139458328,50.66036087650835],"type":"Point"}
}