{
  "type": "Feature",
  "properties": {
    "iso:country":"GB",
    "wof:name":"G34 0LT",
    "wof:placetype":"postalcode"
},
  "geometry": {"coordinates":[-4.10983480737351,55.86988262743848],"type":"Point"}
}