{
  "type": "Feature",
  "properties": {
    "iso:country": "GB",
    "wof:name": "G34 0LT",
    "wof:placetype": "postalcode"
  },
  "geometry": {"coordinates":[-4.110028,55.86983],"type":"Point"}
}
