{
  "type": "Feature",
  "properties": {
    "date:inception_lower":"1980-01-01",
    "date:inception_upper":"1980-01-31",
    "iso:country":"GB",
    "wof:name":"TR12 6DZ",
    "wof:placetype":"postalcode"
},
  "geometry": {"coordinates":[-5.146586,50.046243],"type":"Point"}
}