{
  "type": "Feature",
  "properties": {
    "iso:country":"GB",
    "wof:name":"NP23 4DX",
    "wof:placetype":"postalcode"
},
  "geometry": {"coordinates":[-3.16948249053205,51.79843784614335],"type":"Point"}
}