{
  "type": "Feature",
  "properties": {
    "iso:country": "GB",
    "wof:name": "NP23 4DX",
    "wof:placetype": "postalcode"
  },
  "geometry": {"coordinates":[-3.169482,51.798438],"type":"Point"}
}
