{
  "type": "Feature",
  "properties": {
    "iso:country": "GB",
    "wof:name": "YO42 2PG",
    "wof:placetype": "postalcode"
  },
  "geometry": {"coordinates":[-0.775664,53.922916],"type":"Point"}
}
