{
  "type": "Feature",
  "properties": {
    "iso:country":"GB",
    "wof:name":"HR1 1AL",
    "wof:placetype":"postalcode"
},
  "geometry": {"coordinates":[-2.70472276196082,52.07126907421019],"type":"Point"}
}