{
  "type": "Feature",
  "properties": {
    "date:inception_lower": "1987-10-01",
    "date:inception_upper": "1987-10-01",
    "iso:country": "GB",
    "wof:name": "HR1 1AL",
    "wof:placetype": "postalcode"
  },
  "geometry": {"coordinates":[-2.704723,52.071269],"type":"Point"}
}
