{
  "type": "Feature",
  "properties": {
    "iso:country":"GB",
    "wof:name":"LL65 3AS",
    "wof:placetype":"postalcode"
},
  "geometry": {"coordinates":[-4.56990232623801,53.28940511474543],"type":"Point"}
}