{
  "type": "Feature",
  "properties": {
    "date:inception_lower": "1980-01-01",
    "date:inception_upper": "1980-01-01",
    "iso:country": "GB",
    "wof:name": "LL65 3AS",
    "wof:placetype": "postalcode"
  },
  "geometry": {"coordinates":[-4.569902,53.289405],"type":"Point"}
}
