{
  "type": "Feature",
  "properties": {
    "date:inception_lower": "1980-01-01",
    "date:inception_upper": "1980-01-01",
    "iso:country": "GB",
    "wof:name": "IP24 2PJ",
    "wof:placetype": "postalcode"
  },
  "geometry": {"coordinates":[0.741818,52.367851],"type":"Point"}
}
