{
  "type": "Feature",
  "properties": {
    "iso:country": "GB",
    "wof:name": "IP6 8DB",
    "wof:placetype": "postalcode"
  },
  "geometry": {"coordinates":[1.044792,52.156888],"type":"Point"}
}
