{
  "type": "Feature",
  "properties": {
    "iso:country":"GB",
    "wof:name":"IP6 8DB",
    "wof:placetype":"postalcode"
},
  "geometry": {"coordinates":[1.04479235791281,52.15688788268986],"type":"Point"}
}