{
  "type": "Feature",
  "properties": {
    "iso:country": "GB",
    "wof:name": "CO15 3NZ",
    "wof:placetype": "postalcode"
  },
  "geometry": {"coordinates":[1.15566,51.7986],"type":"Point"}
}
