{
  "type": "Feature",
  "properties": {
    "iso:country":"GB",
    "wof:name":"CO15 3NZ",
    "wof:placetype":"postalcode"
},
  "geometry": {"coordinates":[1.15566038616925,51.79859996887716],"type":"Point"}
}