{
  "type": "Feature",
  "properties": {
    "date:inception_lower": "2021-04-01",
    "date:inception_upper": "2021-04-01",
    "iso:country": "GB",
    "wof:name": "LS4 2BG",
    "wof:placetype": "postalcode"
  },
  "geometry": {"coordinates":[-1.57608,53.803527],"type":"Point"}
}
