{
  "type": "Feature",
  "properties": {
    "date:inception_lower": "1992-01-01",
    "date:inception_upper": "1992-01-01",
    "iso:country": "GB",
    "wof:name": "L30 6YD",
    "wof:placetype": "postalcode"
  },
  "geometry": {"coordinates":[-2.969997,53.484755],"type":"Point"}
}
