{
  "type": "Feature",
  "properties": {
    "iso:country": "GB",
    "wof:name": "L20 9LX",
    "wof:placetype": "postalcode"
  },
  "geometry": {"coordinates":[-2.97861,53.445143],"type":"Point"}
}
