{
  "type": "Feature",
  "properties": {
    "date:inception_lower":"1980-01-01",
    "date:inception_upper":"1980-01-31",
    "iso:country":"GB",
    "wof:name":"L21 4PF",
    "wof:placetype":"postalcode"
},
  "geometry": {"coordinates":[-3.011519,53.459565],"type":"Point"}
}