{
  "type": "Feature",
  "properties": {
    "iso:country":"GB",
    "wof:name":"L21 4PF",
    "wof:placetype":"postalcode"
},
  "geometry": {"coordinates":[-3.01151951845983,53.45956528433624],"type":"Point"}
}