{
  "type": "Feature",
  "properties": {
    "iso:country": "GB",
    "wof:name": "L21 4PF",
    "wof:placetype": "postalcode"
  },
  "geometry": {"coordinates":[-3.011519,53.459565],"type":"Point"}
}
