{
  "type": "Feature",
  "properties": {
    "iso:country": "GB",
    "wof:name": "NG9 6HU",
    "wof:placetype": "postalcode"
  },
  "geometry": {"coordinates":[-1.267663,52.911627],"type":"Point"}
}
