{
  "type": "Feature",
  "properties": {
    "iso:country":"GB",
    "wof:name":"ME19 5WJ",
    "wof:placetype":"postalcode"
},
  "geometry": {"coordinates":[0.40929134734573,51.31785255491604],"type":"Point"}
}