{
  "type": "Feature",
  "properties": {
    "iso:country": "GB",
    "wof:name": "ME19 5WJ",
    "wof:placetype": "postalcode"
  },
  "geometry": {"coordinates":[0.409291,51.317853],"type":"Point"}
}
