{
  "type": "Feature",
  "properties": {
    "iso:country":"GB",
    "wof:name":"SE28 0NE",
    "wof:placetype":"postalcode"
},
  "geometry": {"coordinates":[0.08787073737974,51.50205817802794],"type":"Point"}
}