{
  "type": "Feature",
  "properties": {
    "date:inception_lower": "1991-01-01",
    "date:inception_upper": "1991-01-01",
    "iso:country": "GB",
    "wof:name": "S44 6HZ",
    "wof:placetype": "postalcode"
  },
  "geometry": {"coordinates":[-1.287679,53.222885],"type":"Point"}
}
