{
  "type": "Feature",
  "properties": {
    "iso:country":"GB",
    "wof:name":"S44 6HZ",
    "wof:placetype":"postalcode"
},
  "geometry": {"coordinates":[-1.28767862333787,53.22288487275814],"type":"Point"}
}