{
  "type": "Feature",
  "properties": {
    "iso:country": "GB",
    "wof:name": "PH1 3XZ",
    "wof:placetype": "postalcode"
  },
  "geometry": {"coordinates":[-3.515328,56.410267],"type":"Point"}
}
