{
  "type": "Feature",
  "properties": {
    "iso:country":"GB",
    "wof:name":"PH1 3XZ",
    "wof:placetype":"postalcode"
},
  "geometry": {"coordinates":[-3.51532828726187,56.41026719442969],"type":"Point"}
}