{
  "type": "Feature",
  "properties": {
    "date:inception_lower":"1992-10-01",
    "date:inception_upper":"1992-10-31",
    "iso:country":"GB",
    "wof:name":"PH1 3XZ",
    "wof:placetype":"postalcode"
},
  "geometry": {"coordinates":[-3.515328,56.410267],"type":"Point"}
}