{
  "type": "Feature",
  "properties": {
    "date:inception_lower": "1985-04-01",
    "date:inception_upper": "1985-04-01",
    "iso:country": "GB",
    "wof:name": "IG8 0UB",
    "wof:placetype": "postalcode"
  },
  "geometry": {"coordinates":[0.024785,51.616625],"type":"Point"}
}
