{
  "type": "Feature",
  "properties": {
    "iso:country":"GB",
    "wof:name":"IG8 0UB",
    "wof:placetype":"postalcode"
},
  "geometry": {"coordinates":[0.02478483113075,51.61662456824726],"type":"Point"}
}