{
  "type": "Feature",
  "properties": {
    "iso:country":"GB",
    "wof:name":"SW18 4RA",
    "wof:placetype":"postalcode"
},
  "geometry": {"coordinates":[-0.19521189693869,51.44160563965436],"type":"Point"}
}