{
  "type": "Feature",
  "properties": {
    "date:inception_lower":"2001-12-01",
    "date:inception_upper":"2001-12-31",
    "iso:country":"GB",
    "wof:name":"LA3 2SJ",
    "wof:placetype":"postalcode"
},
  "geometry": {"coordinates":[-2.892562,54.035921],"type":"Point"}
}