{
  "type": "Feature",
  "properties": {
    "iso:country": "GB",
    "wof:name": "RG20 9RJ",
    "wof:placetype": "postalcode"
  },
  "geometry": {"coordinates":[-1.36083,51.340403],"type":"Point"}
}
