{
  "type": "Feature",
  "properties": {
    "iso:country":"GB",
    "wof:name":"RG20 9RJ",
    "wof:placetype":"postalcode"
},
  "geometry": {"coordinates":[-1.36082994895379,51.34040334709238],"type":"Point"}
}