{
  "type": "Feature",
  "properties": {
    "date:inception_lower":"1980-01-01",
    "date:inception_upper":"1980-01-31",
    "iso:country":"GB",
    "wof:name":"LS26 8PB",
    "wof:placetype":"postalcode"
},
  "geometry": {"coordinates":[-1.451431,53.754677],"type":"Point"}
}