{
  "type": "Feature",
  "properties": {
    "iso:country":"GB",
    "wof:name":"LS26 8PB",
    "wof:placetype":"postalcode"
},
  "geometry": {"coordinates":[-1.45143081273897,53.75467687140672],"type":"Point"}
}