{
  "type": "Feature",
  "properties": {
    "iso:country":"GB",
    "wof:name":"GL52 8LP",
    "wof:placetype":"postalcode"
},
  "geometry": {"coordinates":[-2.05934261425891,51.94724100481902],"type":"Point"}
}