{
  "type": "Feature",
  "properties": {
    "date:inception_lower": "2000-10-01",
    "date:inception_upper": "2000-10-01",
    "iso:country": "GB",
    "wof:name": "GL52 8LP",
    "wof:placetype": "postalcode"
  },
  "geometry": {"coordinates":[-2.059394,51.947277],"type":"Point"}
}
