{
  "type": "Feature",
  "properties": {
    "iso:country":"GB",
    "wof:name":"FY1 6EY",
    "wof:placetype":"postalcode"
},
  "geometry": {"coordinates":[-3.05041680310731,53.79955808707401],"type":"Point"}
}