{
  "type": "Feature",
  "properties": {
    "date:inception_lower": "2023-10-01",
    "date:inception_upper": "2023-10-01",
    "iso:country": "GB",
    "wof:name": "OX9 3SR",
    "wof:placetype": "postalcode"
  },
  "geometry": {"coordinates":[-0.960297,51.740864],"type":"Point"}
}
