{
  "type": "Feature",
  "properties": {
    "iso:country":"GB",
    "wof:name":"SA33 5HS",
    "wof:placetype":"postalcode"
},
  "geometry": {"coordinates":[-4.40813111759979,51.80840675206718],"type":"Point"}
}