{
  "type": "Feature",
  "properties": {
    "iso:country": "GB",
    "wof:name": "SA33 5HS",
    "wof:placetype": "postalcode"
  },
  "geometry": {"coordinates":[-4.408131,51.808407],"type":"Point"}
}
