{
  "type": "Feature",
  "properties": {
    "date:inception_lower": "1982-03-01",
    "date:inception_upper": "1982-03-01",
    "iso:country": "GB",
    "wof:name": "NG10 5PE",
    "wof:placetype": "postalcode"
  },
  "geometry": {"coordinates":[-1.29305,52.915997],"type":"Point"}
}
