{
  "type": "Feature",
  "properties": {
    "date:inception_lower": "1980-01-01",
    "date:inception_upper": "1980-01-01",
    "iso:country": "GB",
    "wof:name": "NE69 7AX",
    "wof:placetype": "postalcode"
  },
  "geometry": {"coordinates":[-1.70277,55.605038],"type":"Point"}
}
