{
  "type": "Feature",
  "properties": {
    "iso:country":"GB",
    "wof:name":"ML8 5PB",
    "wof:placetype":"postalcode"
},
  "geometry": {"coordinates":[-3.83812989556926,55.71201402383688],"type":"Point"}
}