{
  "type": "Feature",
  "properties": {
    "iso:country": "GB",
    "wof:name": "CV37 8FU",
    "wof:placetype": "postalcode"
  },
  "geometry": {"coordinates":[-1.759476,52.124248],"type":"Point"}
}
