{
  "type": "Feature",
  "properties": {
    "iso:country": "GB",
    "wof:name": "CV37 8FU",
    "wof:placetype": "postalcode"
  },
  "geometry": {"coordinates":[-1.759243,52.124086],"type":"Point"}
}
