{
  "type": "Feature",
  "properties": {
    "iso:country":"GB",
    "wof:name":"SA2 0SU",
    "wof:placetype":"postalcode"
},
  "geometry": {"coordinates":[-3.98007579888529,51.61912287277213],"type":"Point"}
}