{
  "type": "Feature",
  "properties": {
    "date:inception_lower": "1980-01-01",
    "date:inception_upper": "1980-01-01",
    "iso:country": "GB",
    "wof:name": "OL6 8XH",
    "wof:placetype": "postalcode"
  },
  "geometry": {"coordinates":[-2.08479,53.508024],"type":"Point"}
}
