{
  "type": "Feature",
  "properties": {
    "iso:country":"GB",
    "wof:name":"DE5 3PF",
    "wof:placetype":"postalcode"
},
  "geometry": {"coordinates":[-1.40794326738495,53.04506422937395],"type":"Point"}
}