{
  "type": "Feature",
  "properties": {
    "iso:country": "GB",
    "wof:name": "DE5 3PF",
    "wof:placetype": "postalcode"
  },
  "geometry": {"coordinates":[-1.407943,53.045064],"type":"Point"}
}
