{
  "type": "Feature",
  "properties": {
    "iso:country":"GB",
    "wof:name":"WN6 0LY",
    "wof:placetype":"postalcode"
},
  "geometry": {"coordinates":[-2.66115068989156,53.58940410277341],"type":"Point"}
}