{
  "type": "Feature",
  "properties": {
    "iso:country":"GB",
    "wof:name":"SN15 5AR",
    "wof:placetype":"postalcode"
},
  "geometry": {"coordinates":[-1.97652055501246,51.56944023023452],"type":"Point"}
}