{
  "type": "Feature",
  "properties": {
    "iso:country":"GB",
    "wof:name":"SG12 9LP",
    "wof:placetype":"postalcode"
},
  "geometry": {"coordinates":[-0.02918845173296,51.80727312721083],"type":"Point"}
}