{
  "type": "Feature",
  "properties": {
    "iso:country": "GB",
    "wof:name": "SG12 9LP",
    "wof:placetype": "postalcode"
  },
  "geometry": {"coordinates":[-0.029188,51.807273],"type":"Point"}
}
