{
  "type": "Feature",
  "properties": {
    "iso:country":"GB",
    "wof:name":"BR5 2ED",
    "wof:placetype":"postalcode"
},
  "geometry": {"coordinates":[0.10826043548973,51.38992060636485],"type":"Point"}
}