{
  "type": "Feature",
  "properties": {
    "date:inception_lower": "1995-07-01",
    "date:inception_upper": "1995-07-01",
    "iso:country": "GB",
    "wof:name": "WA8 5HJ",
    "wof:placetype": "postalcode"
  },
  "geometry": {"coordinates":[-2.764018,53.389171],"type":"Point"}
}
