{
  "type": "Feature",
  "properties": {
    "iso:country":"GB",
    "wof:name":"CF46 6BP",
    "wof:placetype":"postalcode"
},
  "geometry": {"coordinates":[-3.29579050548124,51.66519700012197],"type":"Point"}
}