{
  "type": "Feature",
  "properties": {
    "date:inception_lower": "1990-02-01",
    "date:inception_upper": "1990-02-01",
    "iso:country": "GB",
    "wof:name": "CF46 6BP",
    "wof:placetype": "postalcode"
  },
  "geometry": {"coordinates":[-3.29579,51.665197],"type":"Point"}
}
