{
  "type": "Feature",
  "properties": {
    "iso:country":"GB",
    "wof:name":"CM12 0NT",
    "wof:placetype":"postalcode"
},
  "geometry": {"coordinates":[0.41923405330598,51.63698127793584],"type":"Point"}
}