{
  "type": "Feature",
  "properties": {
    "iso:country": "GB",
    "wof:name": "KT16 9JW",
    "wof:placetype": "postalcode"
  },
  "geometry": {"coordinates":[-0.506703,51.391422],"type":"Point"}
}
