{
  "type": "Feature",
  "properties": {
    "iso:country": "GB",
    "wof:name": "CH45 9JN",
    "wof:placetype": "postalcode"
  },
  "geometry": {"coordinates":[-3.051557,53.435354],"type":"Point"}
}
