{
  "type": "Feature",
  "properties": {
    "iso:country":"GB",
    "wof:name":"M23 9LQ",
    "wof:placetype":"postalcode"
},
  "geometry": {"coordinates":[-2.28867534380422,53.38830147611679],"type":"Point"}
}