{
  "type": "Feature",
  "properties": {
    "iso:country":"GB",
    "wof:name":"OX26 5DJ",
    "wof:placetype":"postalcode"
},
  "geometry": {"coordinates":[-1.11766654087508,51.89967096175803],"type":"Point"}
}