{
  "type": "Feature",
  "properties": {
    "iso:country": "GB",
    "wof:name": "OX26 5DJ",
    "wof:placetype": "postalcode"
  },
  "geometry": {"coordinates":[-1.117666,51.899671],"type":"Point"}
}
