{
  "type": "Feature",
  "properties": {
    "date:inception_lower": "1980-01-01",
    "date:inception_upper": "1980-01-01",
    "iso:country": "GB",
    "wof:name": "N12 9AW",
    "wof:placetype": "postalcode"
  },
  "geometry": {"coordinates":[-0.16084,51.616158],"type":"Point"}
}
