{
  "type": "Feature",
  "properties": {
    "iso:country":"GB",
    "wof:name":"N12 9AW",
    "wof:placetype":"postalcode"
},
  "geometry": {"coordinates":[-0.16086546980833,51.61616402790305],"type":"Point"}
}