{
  "type": "Feature",
  "properties": {
    "iso:country": "GB",
    "wof:name": "PE20 1TB",
    "wof:placetype": "postalcode"
  },
  "geometry": {"coordinates":[-0.094717,52.94507],"type":"Point"}
}
