{
  "type": "Feature",
  "properties": {
    "date:inception_lower": "1980-01-01",
    "date:inception_upper": "1980-01-01",
    "iso:country": "GB",
    "wof:name": "CA11 0QB",
    "wof:placetype": "postalcode"
  },
  "geometry": {"coordinates":[-2.952582,54.544285],"type":"Point"}
}
