{
  "type": "Feature",
  "properties": {
    "date:inception_lower": "1980-01-01",
    "date:inception_upper": "1980-01-01",
    "iso:country": "GB",
    "wof:name": "BN1 6ND",
    "wof:placetype": "postalcode"
  },
  "geometry": {"coordinates":[-0.140247,50.846434],"type":"Point"}
}
