{
  "type": "Feature",
  "properties": {
    "iso:country":"GB",
    "wof:name":"BN1 6ND",
    "wof:placetype":"postalcode"
},
  "geometry": {"coordinates":[-0.14024675789341,50.84643385978462],"type":"Point"}
}