{
  "type": "Feature",
  "properties": {
    "iso:country": "GB",
    "wof:name": "OL2 6JZ",
    "wof:placetype": "postalcode"
  },
  "geometry": {"coordinates":[-2.126899,53.562159],"type":"Point"}
}
