{
  "type": "Feature",
  "properties": {
    "iso:country":"GB",
    "wof:name":"CO12 4UG",
    "wof:placetype":"postalcode"
},
  "geometry": {"coordinates":[1.25062461378865,51.92874912304816],"type":"Point"}
}