{
  "type": "Feature",
  "properties": {
    "date:inception_lower": "1995-12-01",
    "date:inception_upper": "1995-12-01",
    "iso:country": "GB",
    "wof:name": "PL12 4XX",
    "wof:placetype": "postalcode"
  },
  "geometry": {"coordinates":[-4.239618,50.409874],"type":"Point"}
}
