{
  "type": "Feature",
  "properties": {
    "iso:country": "GB",
    "wof:name": "PL12 4XX",
    "wof:placetype": "postalcode"
  },
  "geometry": {"coordinates":[-4.239618,50.409874],"type":"Point"}
}
