{
  "type": "Feature",
  "properties": {
    "iso:country": "GB",
    "wof:name": "CW12 3AX",
    "wof:placetype": "postalcode"
  },
  "geometry": {"coordinates":[-2.201445,53.153919],"type":"Point"}
}
