{
  "type": "Feature",
  "properties": {
    "iso:country": "GB",
    "wof:name": "DH1 4AA",
    "wof:placetype": "postalcode"
  },
  "geometry": {"coordinates":[-1.594756,54.775578],"type":"Point"}
}
