{
  "type": "Feature",
  "properties": {
    "iso:country":"GB",
    "wof:name":"DH1 4AA",
    "wof:placetype":"postalcode"
},
  "geometry": {"coordinates":[-1.59475636683562,54.77557760263935],"type":"Point"}
}