{
  "type": "Feature",
  "properties": {
    "iso:country":"GB",
    "wof:name":"WC2H 9QA",
    "wof:placetype":"postalcode"
},
  "geometry": {"coordinates":[-0.12558818460163,51.51275034973163],"type":"Point"}
}