{
  "type": "Feature",
  "properties": {
    "iso:country": "GB",
    "wof:name": "WC2H 9QA",
    "wof:placetype": "postalcode"
  },
  "geometry": {"coordinates":[-0.125563,51.512752],"type":"Point"}
}
