{
  "type": "Feature",
  "properties": {
    "iso:country": "GB",
    "wof:name": "WA4 1UW",
    "wof:placetype": "postalcode"
  },
  "geometry": {"coordinates":[-2.556961,53.38389],"type":"Point"}
}
