{
  "type": "Feature",
  "properties": {
    "date:inception_lower": "1980-01-01",
    "date:inception_upper": "1980-01-01",
    "iso:country": "GB",
    "wof:name": "SL2 5JN",
    "wof:placetype": "postalcode"
  },
  "geometry": {"coordinates":[-0.579002,51.515567],"type":"Point"}
}
