{
  "type": "Feature",
  "properties": {
    "iso:country": "GB",
    "wof:name": "GL1 5DQ",
    "wof:placetype": "postalcode"
  },
  "geometry": {"coordinates":[-2.243851,51.850279],"type":"Point"}
}
