{
  "type": "Feature",
  "properties": {
    "iso:country":"GB",
    "wof:name":"ST1 3LY",
    "wof:placetype":"postalcode"
},
  "geometry": {"coordinates":[-2.16522726918373,53.02161998648479],"type":"Point"}
}