{
  "type": "Feature",
  "properties": {
    "iso:country":"GB",
    "wof:name":"BS9 1QT",
    "wof:placetype":"postalcode"
},
  "geometry": {"coordinates":[-2.64110114368949,51.47439366403987],"type":"Point"}
}