{
  "type": "Feature",
  "properties": {
    "iso:country": "GB",
    "wof:name": "GL54 5DE",
    "wof:placetype": "postalcode"
  },
  "geometry": {"coordinates":[-1.994713,51.974354],"type":"Point"}
}
