{
  "type": "Feature",
  "properties": {
    "date:inception_lower": "1980-01-01",
    "date:inception_upper": "1980-01-01",
    "iso:country": "GB",
    "wof:name": "PE12 7LW",
    "wof:placetype": "postalcode"
  },
  "geometry": {"coordinates":[0.012704,52.804292],"type":"Point"}
}
