{
  "type": "Feature",
  "properties": {
    "iso:country":"GB",
    "wof:name":"PE12 7LW",
    "wof:placetype":"postalcode"
},
  "geometry": {"coordinates":[0.01270434636406,52.80429164680012],"type":"Point"}
}