{
  "type": "Feature",
  "properties": {
    "iso:country":"GB",
    "wof:name":"TS16 0NU",
    "wof:placetype":"postalcode"
},
  "geometry": {"coordinates":[-1.36387818076422,54.51991756324565],"type":"Point"}
}