{
  "type": "Feature",
  "properties": {
    "iso:country":"GB",
    "wof:name":"BR3 4NN",
    "wof:placetype":"postalcode"
},
  "geometry": {"coordinates":[-0.0531322025085,51.40466496509796],"type":"Point"}
}