{
  "type": "Feature",
  "properties": {
    "iso:country":"GB",
    "wof:name":"DG8 9LA",
    "wof:placetype":"postalcode"
},
  "geometry": {"coordinates":[-4.56650298703836,54.75421400769098],"type":"Point"}
}