{
  "type": "Feature",
  "properties": {
    "iso:country": "GB",
    "wof:name": "DG8 9LA",
    "wof:placetype": "postalcode"
  },
  "geometry": {"coordinates":[-4.566503,54.754214],"type":"Point"}
}
