{
  "type": "Feature",
  "properties": {
    "iso:country":"GB",
    "wof:name":"WF13 3UZ",
    "wof:placetype":"postalcode"
},
  "geometry": {"coordinates":[-1.66009768959986,53.69525631327123],"type":"Point"}
}