{
  "type": "Feature",
  "properties": {
    "iso:country": "GB",
    "wof:name": "WF13 3UZ",
    "wof:placetype": "postalcode"
  },
  "geometry": {"coordinates":[-1.660098,53.695256],"type":"Point"}
}
