{
  "type": "Feature",
  "properties": {
    "iso:country":"GB",
    "wof:name":"WF1 5BA",
    "wof:placetype":"postalcode"
},
  "geometry": {"coordinates":[-1.47971891815873,53.66844433861758],"type":"Point"}
}