{
  "type": "Feature",
  "properties": {
    "date:inception_lower": "1980-01-01",
    "date:inception_upper": "1980-01-01",
    "iso:country": "GB",
    "wof:name": "DD9 6DF",
    "wof:placetype": "postalcode"
  },
  "geometry": {"coordinates":[-2.665432,56.738255],"type":"Point"}
}
