{
  "type": "Feature",
  "properties": {
    "iso:country":"GB",
    "wof:name":"DD9 6DF",
    "wof:placetype":"postalcode"
},
  "geometry": {"coordinates":[-2.66543193706232,56.73825475607389],"type":"Point"}
}