{
  "type": "Feature",
  "properties": {
    "iso:country":"GB",
    "wof:name":"TN5 6LE",
    "wof:placetype":"postalcode"
},
  "geometry": {"coordinates":[0.29911746949643,51.07875497254123],"type":"Point"}
}