{
  "type": "Feature",
  "properties": {
    "iso:country": "GB",
    "wof:name": "FK8 1EL",
    "wof:placetype": "postalcode"
  },
  "geometry": {"coordinates":[-3.944121,56.122845],"type":"Point"}
}
