{
  "type": "Feature",
  "properties": {
    "iso:country":"GB",
    "wof:name":"DE13 0XR",
    "wof:placetype":"postalcode"
},
  "geometry": {"coordinates":[-1.64564096015388,52.83420319737313],"type":"Point"}
}