{
  "type": "Feature",
  "properties": {
    "iso:country":"GB",
    "wof:name":"EN3 5PX",
    "wof:placetype":"postalcode"
},
  "geometry": {"coordinates":[-0.04118245931944,51.66499026323903],"type":"Point"}
}