{
  "type": "Feature",
  "properties": {
    "iso:country":"GB",
    "wof:name":"G2 4ET",
    "wof:placetype":"postalcode"
},
  "geometry": {"coordinates":[-4.26336084316977,55.86436786172919],"type":"Point"}
}