{
  "type": "Feature",
  "properties": {
    "iso:country":"GB",
    "wof:name":"SE24 0QD",
    "wof:placetype":"postalcode"
},
  "geometry": {"coordinates":[-0.10319223512566,51.4617260625753],"type":"Point"}
}