{
  "type": "Feature",
  "properties": {
    "iso:country":"GB",
    "wof:name":"TR15 1AW",
    "wof:placetype":"postalcode"
},
  "geometry": {"coordinates":[-5.23289548009783,50.2350544402254],"type":"Point"}
}