{
  "type": "Feature",
  "properties": {
    "date:inception_lower": "1980-01-01",
    "date:inception_upper": "1980-01-01",
    "iso:country": "GB",
    "wof:name": "TR15 1AW",
    "wof:placetype": "postalcode"
  },
  "geometry": {"coordinates":[-5.23259,50.235414],"type":"Point"}
}
