{
  "type": "Feature",
  "properties": {
    "iso:country": "GB",
    "wof:name": "N17 6HG",
    "wof:placetype": "postalcode"
  },
  "geometry": {"coordinates":[-0.084505,51.595717],"type":"Point"}
}
