{
  "type": "Feature",
  "properties": {
    "iso:country":"GB",
    "wof:name":"NW8 8PD",
    "wof:placetype":"postalcode"
},
  "geometry": {"coordinates":[-0.17312628957009,51.52552335035831],"type":"Point"}
}