{
  "type": "Feature",
  "properties": {
    "iso:country": "GB",
    "wof:name": "NW8 8PD",
    "wof:placetype": "postalcode"
  },
  "geometry": {"coordinates":[-0.173126,51.525523],"type":"Point"}
}
