{
  "type": "Feature",
  "properties": {
    "iso:country":"GB",
    "wof:name":"HA8 5LE",
    "wof:placetype":"postalcode"
},
  "geometry": {"coordinates":[-0.26803335088509,51.59973765569588],"type":"Point"}
}