{
  "type": "Feature",
  "properties": {
    "iso:country": "GB",
    "wof:name": "PA11 3BH",
    "wof:placetype": "postalcode"
  },
  "geometry": {"coordinates":[-4.580107,55.855912],"type":"Point"}
}
