{
  "type": "Feature",
  "properties": {
    "iso:country":"GB",
    "wof:name":"NE11 9YG",
    "wof:placetype":"postalcode"
},
  "geometry": {"coordinates":[-1.66892887671507,54.95588106576133],"type":"Point"}
}