{
  "type": "Feature",
  "properties": {
    "date:inception_lower":"1987-04-01",
    "date:inception_upper":"1987-04-30",
    "iso:country":"GB",
    "wof:name":"NE11 9YG",
    "wof:placetype":"postalcode"
},
  "geometry": {"coordinates":[-1.668929,54.955881],"type":"Point"}
}