{
  "type": "Feature",
  "properties": {
    "iso:country":"GB",
    "wof:name":"WS1 3BD",
    "wof:placetype":"postalcode"
},
  "geometry": {"coordinates":[-1.97032886022941,52.57197908785977],"type":"Point"}
}