{
  "type": "Feature",
  "properties": {
    "date:inception_lower": "2007-12-01",
    "date:inception_upper": "2007-12-01",
    "iso:country": "GB",
    "wof:name": "WS1 3BD",
    "wof:placetype": "postalcode"
  },
  "geometry": {"coordinates":[-1.970329,52.571979],"type":"Point"}
}
