{
  "type": "Feature",
  "properties": {
    "iso:country": "GB",
    "wof:name": "WS1 3BD",
    "wof:placetype": "postalcode"
  },
  "geometry": {"coordinates":[-1.970329,52.571979],"type":"Point"}
}
