{
  "type": "Feature",
  "properties": {
    "date:inception_lower": "2019-07-01",
    "date:inception_upper": "2019-07-01",
    "iso:country": "GB",
    "wof:name": "CW7 2XS",
    "wof:placetype": "postalcode"
  },
  "geometry": {"coordinates":[-2.556005,53.193885],"type":"Point"}
}
