{
  "type": "Feature",
  "properties": {
    "iso:country":"GB",
    "wof:name":"YO11 3QW",
    "wof:placetype":"postalcode"
},
  "geometry": {"coordinates":[-0.38087949077527,54.24495310978437],"type":"Point"}
}