{
  "type": "Feature",
  "properties": {
    "iso:country":"GB",
    "wof:name":"NG16 3BQ",
    "wof:placetype":"postalcode"
},
  "geometry": {"coordinates":[-1.30871329899649,53.01661747110494],"type":"Point"}
}