{
  "type": "Feature",
  "properties": {
    "iso:country":"GB",
    "wof:name":"BS48 2SW",
    "wof:placetype":"postalcode"
},
  "geometry": {"coordinates":[-2.73983500104813,51.43017536706466],"type":"Point"}
}