{
  "type": "Feature",
  "properties": {
    "iso:country":"GB",
    "wof:name":"NR31 7AN",
    "wof:placetype":"postalcode"
},
  "geometry": {"coordinates":[1.72397646731717,52.57494849427412],"type":"Point"}
}