{
  "type": "Feature",
  "properties": {
    "iso:country":"GB",
    "wof:name":"UB10 9NP",
    "wof:placetype":"postalcode"
},
  "geometry": {"coordinates":[-0.46212646605872,51.54703174431341],"type":"Point"}
}