{
  "type": "Feature",
  "properties": {
    "date:inception_lower": "1990-06-01",
    "date:inception_upper": "1990-06-01",
    "iso:country": "GB",
    "wof:name": "EH54 6SZ",
    "wof:placetype": "postalcode"
  },
  "geometry": {"coordinates":[-3.533443,55.893287],"type":"Point"}
}
