{
  "type": "Feature",
  "properties": {
    "iso:country": "GB",
    "wof:name": "BB18 6DP",
    "wof:placetype": "postalcode"
  },
  "geometry": {"coordinates":[-2.1871,53.918555],"type":"Point"}
}
