{
  "type": "Feature",
  "properties": {
    "iso:country":"GB",
    "wof:name":"BB18 6DP",
    "wof:placetype":"postalcode"
},
  "geometry": {"coordinates":[-2.18710016951586,53.91855547595577],"type":"Point"}
}