{
  "type": "Feature",
  "properties": {
    "date:inception_lower": "1980-01-01",
    "date:inception_upper": "1980-01-01",
    "iso:country": "GB",
    "wof:name": "LA14 4NX",
    "wof:placetype": "postalcode"
  },
  "geometry": {"coordinates":[-3.210649,54.141473],"type":"Point"}
}
