{
  "type": "Feature",
  "properties": {
    "iso:country": "GB",
    "wof:name": "G46 6ES",
    "wof:placetype": "postalcode"
  },
  "geometry": {"coordinates":[-4.280953,55.805669],"type":"Point"}
}
