{
  "type": "Feature",
  "properties": {
    "date:inception_lower":"1980-01-01",
    "date:inception_upper":"1980-01-31",
    "iso:country":"GB",
    "wof:name":"TQ2 7LY",
    "wof:placetype":"postalcode"
},
  "geometry": {"coordinates":[-3.56983,50.478036],"type":"Point"}
}