{
  "type": "Feature",
  "properties": {
    "iso:country":"GB",
    "wof:name":"TQ2 7LY",
    "wof:placetype":"postalcode"
},
  "geometry": {"coordinates":[-3.56982960016042,50.47803586556714],"type":"Point"}
}