{
  "type": "Feature",
  "properties": {
    "iso:country":"GB",
    "wof:name":"PA3 2AZ",
    "wof:placetype":"postalcode"
},
  "geometry": {"coordinates":[-4.42347141235828,55.84971432764106],"type":"Point"}
}