{
  "type": "Feature",
  "properties": {
    "date:inception_lower": "2021-08-01",
    "date:inception_upper": "2021-08-01",
    "iso:country": "GB",
    "wof:name": "L37 4EA",
    "wof:placetype": "postalcode"
  },
  "geometry": {"coordinates":[-3.060528,53.556227],"type":"Point"}
}
