{
  "type": "Feature",
  "properties": {
    "date:inception_lower": "2020-02-01",
    "date:inception_upper": "2020-02-01",
    "iso:country": "GB",
    "wof:name": "L37 4EA",
    "wof:placetype": "postalcode"
  },
  "geometry": {"coordinates":[-3.063197,53.556104],"type":"Point"}
}
