{
  "type": "Feature",
  "properties": {
    "iso:country": "GB",
    "wof:name": "G75 8NG",
    "wof:placetype": "postalcode"
  },
  "geometry": {"coordinates":[-4.233739,55.755622],"type":"Point"}
}
