{
  "type": "Feature",
  "properties": {
    "iso:country": "GB",
    "wof:name": "IV14 9EA",
    "wof:placetype": "postalcode"
  },
  "geometry": {"coordinates":[-4.508064,57.598831],"type":"Point"}
}
