{
  "type": "Feature",
  "properties": {
    "iso:country":"GB",
    "wof:name":"IV14 9EA",
    "wof:placetype":"postalcode"
},
  "geometry": {"coordinates":[-4.50806647951205,57.59884815898572],"type":"Point"}
}