{
  "type": "Feature",
  "properties": {
    "date:inception_lower":"2012-09-01",
    "date:inception_upper":"2012-09-30",
    "iso:country":"GB",
    "wof:name":"IV14 9EA",
    "wof:placetype":"postalcode"
},
  "geometry": {"coordinates":[-4.508064,57.598831],"type":"Point"}
}