{
  "type": "Feature",
  "properties": {
    "iso:country":"GB",
    "wof:name":"LL12 8NB",
    "wof:placetype":"postalcode"
},
  "geometry": {"coordinates":[-2.97169741187745,53.08540924152106],"type":"Point"}
}