{
  "type": "Feature",
  "properties": {
    "iso:country": "GB",
    "wof:name": "LL12 8NB",
    "wof:placetype": "postalcode"
  },
  "geometry": {"coordinates":[-2.971698,53.085425],"type":"Point"}
}
