{
  "type": "Feature",
  "properties": {
    "iso:country": "GB",
    "wof:name": "SY11 1QY",
    "wof:placetype": "postalcode"
  },
  "geometry": {"coordinates":[-3.051326,52.861062],"type":"Point"}
}
