{
  "type": "Feature",
  "properties": {
    "date:inception_lower": "1980-01-01",
    "date:inception_upper": "1980-01-01",
    "iso:country": "GB",
    "wof:name": "TS24 9BL",
    "wof:placetype": "postalcode"
  },
  "geometry": {"coordinates":[-1.228487,54.704909],"type":"Point"}
}
