{
  "type": "Feature",
  "properties": {
    "iso:country":"GB",
    "wof:name":"TS24 9BL",
    "wof:placetype":"postalcode"
},
  "geometry": {"coordinates":[-1.22848722329208,54.70490922143535],"type":"Point"}
}