{
  "type": "Feature",
  "properties": {
    "date:inception_lower": "2021-10-01",
    "date:inception_upper": "2021-10-01",
    "iso:country": "GB",
    "wof:name": "NR4 6FR",
    "wof:placetype": "postalcode"
  },
  "geometry": {"coordinates":[1.23288,52.601879],"type":"Point"}
}
