{
  "type": "Feature",
  "properties": {
    "iso:country":"GB",
    "wof:name":"SE9 2SQ",
    "wof:placetype":"postalcode"
},
  "geometry": {"coordinates":[0.06465605231428,51.45035590773661],"type":"Point"}
}