{
  "type": "Feature",
  "properties": {
    "date:inception_lower": "1980-01-01",
    "date:inception_upper": "1980-01-01",
    "iso:country": "GB",
    "wof:name": "WA7 2RL",
    "wof:placetype": "postalcode"
  },
  "geometry": {"coordinates":[-2.701064,53.317926],"type":"Point"}
}
