{
  "type": "Feature",
  "properties": {
    "iso:country":"GB",
    "wof:name":"WA3 3GE",
    "wof:placetype":"postalcode"
},
  "geometry": {"coordinates":[-2.6030761863787,53.48415912668442],"type":"Point"}
}