{
  "type": "Feature",
  "properties": {
    "date:inception_lower": "2002-06-01",
    "date:inception_upper": "2002-06-01",
    "iso:country": "GB",
    "wof:name": "WA3 3GE",
    "wof:placetype": "postalcode"
  },
  "geometry": {"coordinates":[-2.603076,53.484159],"type":"Point"}
}
