{
  "type": "Feature",
  "properties": {
    "iso:country": "GB",
    "wof:name": "TS4 2RW",
    "wof:placetype": "postalcode"
  },
  "geometry": {"coordinates":[-1.223636,54.558148],"type":"Point"}
}
