{
  "type": "Feature",
  "properties": {
    "date:inception_lower":"1980-01-01",
    "date:inception_upper":"1980-01-31",
    "iso:country":"GB",
    "wof:name":"BA22 7BB",
    "wof:placetype":"postalcode"
},
  "geometry": {"coordinates":[-2.523721,51.06554],"type":"Point"}
}