{
  "type": "Feature",
  "properties": {
    "iso:country":"GB",
    "wof:name":"BA22 7BB",
    "wof:placetype":"postalcode"
},
  "geometry": {"coordinates":[-2.5237208965347,51.06553970211539],"type":"Point"}
}