{
  "type": "Feature",
  "properties": {
    "iso:country":"GB",
    "wof:name":"B11 2EW",
    "wof:placetype":"postalcode"
},
  "geometry": {"coordinates":[-1.83711891987752,52.45297043438057],"type":"Point"}
}