{
  "type": "Feature",
  "properties": {
    "iso:country":"GB",
    "wof:name":"B49 5DZ",
    "wof:placetype":"postalcode"
},
  "geometry": {"coordinates":[-1.87323543383531,52.21436105912071],"type":"Point"}
}