{
  "type": "Feature",
  "properties": {
    "iso:country":"GB",
    "wof:name":"NP4 8LR",
    "wof:placetype":"postalcode"
},
  "geometry": {"coordinates":[-3.05563398471732,51.71601202589508],"type":"Point"}
}