{
  "type": "Feature",
  "properties": {
    "date:inception_lower": "2010-04-01",
    "date:inception_upper": "2010-04-01",
    "iso:country": "GB",
    "wof:name": "NE32 4QD",
    "wof:placetype": "postalcode"
  },
  "geometry": {"coordinates":[-1.487726,54.953689],"type":"Point"}
}
