{
  "type": "Feature",
  "properties": {
    "iso:country":"GB",
    "wof:name":"MK1 1JN",
    "wof:placetype":"postalcode"
},
  "geometry": {"coordinates":[-0.72490994403827,52.00989249674003],"type":"Point"}
}