{
  "type": "Feature",
  "properties": {
    "date:inception_lower": "2018-02-01",
    "date:inception_upper": "2018-02-01",
    "iso:country": "GB",
    "wof:name": "G11 6EQ",
    "wof:placetype": "postalcode"
  },
  "geometry": {"coordinates":[-4.298106,55.869201],"type":"Point"}
}
