{
  "type": "Feature",
  "properties": {
    "iso:country": "GB",
    "wof:name": "TD14 5SZ",
    "wof:placetype": "postalcode"
  },
  "geometry": {"coordinates":[-2.06802,55.835262],"type":"Point"}
}
