{
  "type": "Feature",
  "properties": {
    "iso:country":"GB",
    "wof:name":"TD14 5SZ",
    "wof:placetype":"postalcode"
},
  "geometry": {"coordinates":[-2.06801998148322,55.83526234891296],"type":"Point"}
}