{
  "type": "Feature",
  "properties": {
    "date:inception_lower": "2022-11-01",
    "date:inception_upper": "2022-11-01",
    "iso:country": "GB",
    "wof:name": "DT2 9GA",
    "wof:placetype": "postalcode"
  },
  "geometry": {"coordinates":[-2.464593,50.735434],"type":"Point"}
}
