{
  "type": "Feature",
  "properties": {
    "date:inception_lower":"1990-07-01",
    "date:inception_upper":"1990-07-31",
    "iso:country":"GB",
    "wof:name":"TS10 2QN",
    "wof:placetype":"postalcode"
},
  "geometry": {"coordinates":[-1.048135,54.600285],"type":"Point"}
}