{
  "type": "Feature",
  "properties": {
    "iso:country":"GB",
    "wof:name":"TS10 2QN",
    "wof:placetype":"postalcode"
},
  "geometry": {"coordinates":[-1.04813520456797,54.60028506813021],"type":"Point"}
}