{
  "type": "Feature",
  "properties": {
    "iso:country":"GB",
    "wof:name":"HA6 1SE",
    "wof:placetype":"postalcode"
},
  "geometry": {"coordinates":[-0.4147426639049,51.60820400885861],"type":"Point"}
}