{
  "type": "Feature",
  "properties": {
    "iso:country":"GB",
    "wof:name":"CF48 4TU",
    "wof:placetype":"postalcode"
},
  "geometry": {"coordinates":[-3.36671952423441,51.72925030956807],"type":"Point"}
}