{
  "type": "Feature",
  "properties": {
    "iso:country": "GB",
    "wof:name": "TS19 0SQ",
    "wof:placetype": "postalcode"
  },
  "geometry": {"coordinates":[-1.329012,54.570731],"type":"Point"}
}
