{
  "type": "Feature",
  "properties": {
    "iso:country":"GB",
    "wof:name":"CF36 5RN",
    "wof:placetype":"postalcode"
},
  "geometry": {"coordinates":[-3.6801631157624,51.48541791623952],"type":"Point"}
}