{
  "type": "Feature",
  "properties": {
    "iso:country": "GB",
    "wof:name": "CF36 5RN",
    "wof:placetype": "postalcode"
  },
  "geometry": {"coordinates":[-3.680163,51.485418],"type":"Point"}
}
