{
  "type": "Feature",
  "properties": {
    "iso:country":"GB",
    "wof:name":"NR14 8GQ",
    "wof:placetype":"postalcode"
},
  "geometry": {"coordinates":[1.232100175054,52.55304953043276],"type":"Point"}
}