{
  "type": "Feature",
  "properties": {
    "iso:country": "GB",
    "wof:name": "NR14 8GQ",
    "wof:placetype": "postalcode"
  },
  "geometry": {"coordinates":[1.2321,52.55305],"type":"Point"}
}
