{
  "type": "Feature",
  "properties": {
    "iso:country":"GB",
    "wof:name":"S60 4DU",
    "wof:placetype":"postalcode"
},
  "geometry": {"coordinates":[-1.32829236474137,53.40693382658467],"type":"Point"}
}