{
  "type": "Feature",
  "properties": {
    "iso:country": "GB",
    "wof:name": "S60 4DU",
    "wof:placetype": "postalcode"
  },
  "geometry": {"coordinates":[-1.328292,53.406934],"type":"Point"}
}
