{
  "type": "Feature",
  "properties": {
    "date:inception_lower": "1980-01-01",
    "date:inception_upper": "1980-01-01",
    "iso:country": "GB",
    "wof:name": "SE18 3JY",
    "wof:placetype": "postalcode"
  },
  "geometry": {"coordinates":[0.064657,51.472379],"type":"Point"}
}
