{
  "type": "Feature",
  "properties": {
    "iso:country":"GB",
    "wof:name":"BN2 7DH",
    "wof:placetype":"postalcode"
},
  "geometry": {"coordinates":[-0.0551826525406,50.80751694779846],"type":"Point"}
}