{
  "type": "Feature",
  "properties": {
    "date:inception_lower": "1980-01-01",
    "date:inception_upper": "1980-01-01",
    "iso:country": "GB",
    "wof:name": "BN2 7DH",
    "wof:placetype": "postalcode"
  },
  "geometry": {"coordinates":[-0.055283,50.807486],"type":"Point"}
}
