{
  "type": "Feature",
  "properties": {
    "iso:country": "GB",
    "wof:name": "SS1 2DX",
    "wof:placetype": "postalcode"
  },
  "geometry": {"coordinates":[0.721312,51.536728],"type":"Point"}
}
