{
  "type": "Feature",
  "properties": {
    "iso:country":"GB",
    "wof:name":"BN23 7DJ",
    "wof:placetype":"postalcode"
},
  "geometry": {"coordinates":[0.31225118442651,50.79842784835296],"type":"Point"}
}