{
  "type": "Feature",
  "properties": {
    "iso:country":"GB",
    "wof:name":"W1G 6AJ",
    "wof:placetype":"postalcode"
},
  "geometry": {"coordinates":[-0.14822085053437,51.52113116824036],"type":"Point"}
}