{
  "type": "Feature",
  "properties": {
    "date:inception_lower": "1992-01-01",
    "date:inception_upper": "1992-01-01",
    "iso:country": "GB",
    "wof:name": "RH9 8LH",
    "wof:placetype": "postalcode"
  },
  "geometry": {"coordinates":[-0.068761,51.20235],"type":"Point"}
}
