{
  "type": "Feature",
  "properties": {
    "iso:country":"GB",
    "wof:name":"RH9 8LH",
    "wof:placetype":"postalcode"
},
  "geometry": {"coordinates":[-0.06876065834176,51.20235001650186],"type":"Point"}
}