{
  "type": "Feature",
  "properties": {
    "date:inception_lower":"1980-01-01",
    "date:inception_upper":"1980-01-31",
    "iso:country":"GB",
    "wof:name":"LL29 9RH",
    "wof:placetype":"postalcode"
},
  "geometry": {"coordinates":[-3.696598,53.291593],"type":"Point"}
}