{
  "type": "Feature",
  "properties": {
    "iso:country":"GB",
    "wof:name":"LL29 9RH",
    "wof:placetype":"postalcode"
},
  "geometry": {"coordinates":[-3.69659766538557,53.29159264362474],"type":"Point"}
}