{
  "type": "Feature",
  "properties": {
    "iso:country":"GB",
    "wof:name":"RH11 9EZ",
    "wof:placetype":"postalcode"
},
  "geometry": {"coordinates":[-0.20928378549633,51.09866640276554],"type":"Point"}
}