{
  "type": "Feature",
  "properties": {
    "iso:country":"GB",
    "wof:name":"PR1 0JX",
    "wof:placetype":"postalcode"
},
  "geometry": {"coordinates":[-2.74047143789582,53.75121540150014],"type":"Point"}
}