{
  "type": "Feature",
  "properties": {
    "iso:country":"GB",
    "wof:name":"N20 0BT",
    "wof:placetype":"postalcode"
},
  "geometry": {"coordinates":[-0.16290667328404,51.6257098767759],"type":"Point"}
}