{
  "type": "Feature",
  "properties": {
    "iso:country":"GB",
    "wof:name":"EX31 2HU",
    "wof:placetype":"postalcode"
},
  "geometry": {"coordinates":[-4.08505279422641,51.07480152262748],"type":"Point"}
}