{
  "type": "Feature",
  "properties": {
    "iso:country": "GB",
    "wof:name": "NG16 5LF",
    "wof:placetype": "postalcode"
  },
  "geometry": {"coordinates":[-1.337318,53.060441],"type":"Point"}
}
