{
  "type": "Feature",
  "properties": {
    "date:inception_lower": "1980-01-01",
    "date:inception_upper": "1980-01-01",
    "iso:country": "GB",
    "wof:name": "TR7 3DB",
    "wof:placetype": "postalcode"
  },
  "geometry": {"coordinates":[-5.053949,50.421711],"type":"Point"}
}
