{
  "type": "Feature",
  "properties": {
    "iso:country":"GB",
    "wof:name":"TR7 3DB",
    "wof:placetype":"postalcode"
},
  "geometry": {"coordinates":[-5.05394889806142,50.42171076082568],"type":"Point"}
}