{
  "type": "Feature",
  "properties": {
    "iso:country":"GB",
    "wof:name":"BS16 6JS",
    "wof:placetype":"postalcode"
},
  "geometry": {"coordinates":[-2.50761023179561,51.49730187615754],"type":"Point"}
}