{
  "type": "Feature",
  "properties": {
    "date:inception_lower": "1998-06-01",
    "date:inception_upper": "1998-06-01",
    "iso:country": "GB",
    "wof:name": "G68 9AZ",
    "wof:placetype": "postalcode"
  },
  "geometry": {"coordinates":[-4.058582,55.925562],"type":"Point"}
}
