{
  "type": "Feature",
  "properties": {
    "iso:country":"GB",
    "wof:name":"NG17 3BW",
    "wof:placetype":"postalcode"
},
  "geometry": {"coordinates":[-1.2504923245903,53.14194375158758],"type":"Point"}
}