{
  "type": "Feature",
  "properties": {
    "iso:country":"GB",
    "wof:name":"KA6 7EQ",
    "wof:placetype":"postalcode"
},
  "geometry": {"coordinates":[-4.46345134112797,55.43734055464208],"type":"Point"}
}