{
  "type": "Feature",
  "properties": {
    "date:inception_lower": "2004-11-01",
    "date:inception_upper": "2004-11-01",
    "iso:country": "GB",
    "wof:name": "KA6 7EQ",
    "wof:placetype": "postalcode"
  },
  "geometry": {"coordinates":[-4.463451,55.437341],"type":"Point"}
}
