{
  "type": "Feature",
  "properties": {
    "iso:country": "GB",
    "wof:name": "S18 8ZG",
    "wof:placetype": "postalcode"
  },
  "geometry": {"coordinates":[-1.495822,53.303534],"type":"Point"}
}
