{
  "type": "Feature",
  "properties": {
    "date:inception_lower":"2004-11-01",
    "date:inception_upper":"2004-11-30",
    "iso:country":"GB",
    "wof:name":"IV2 4GT",
    "wof:placetype":"postalcode"
},
  "geometry": {"coordinates":[-4.241691,57.444707],"type":"Point"}
}