{
  "type": "Feature",
  "properties": {
    "iso:country":"GB",
    "wof:name":"IV2 4GT",
    "wof:placetype":"postalcode"
},
  "geometry": {"coordinates":[-4.24169147149083,57.44470727921389],"type":"Point"}
}