{
  "type": "Feature",
  "properties": {
    "iso:country": "GB",
    "wof:name": "IV2 4GT",
    "wof:placetype": "postalcode"
  },
  "geometry": {"coordinates":[-4.241691,57.444707],"type":"Point"}
}
