{
  "type": "Feature",
  "properties": {
    "iso:country":"GB",
    "wof:name":"TQ5 8QB",
    "wof:placetype":"postalcode"
},
  "geometry": {"coordinates":[-3.53007910008119,50.39098457074206],"type":"Point"}
}