{
  "type": "Feature",
  "properties": {
    "iso:country":"GB",
    "wof:name":"AL8 6XT",
    "wof:placetype":"postalcode"
},
  "geometry": {"coordinates":[-0.21864983057869,51.79176362833948],"type":"Point"}
}