{
  "type": "Feature",
  "properties": {
    "iso:country":"GB",
    "wof:name":"BS31 2PJ",
    "wof:placetype":"postalcode"
},
  "geometry": {"coordinates":[-2.51241542159209,51.40937893485818],"type":"Point"}
}