{
  "type": "Feature",
  "properties": {
    "date:inception_lower": "2009-03-01",
    "date:inception_upper": "2009-03-01",
    "iso:country": "GB",
    "wof:name": "BS31 2PJ",
    "wof:placetype": "postalcode"
  },
  "geometry": {"coordinates":[-2.512415,51.409379],"type":"Point"}
}
