{
  "type": "Feature",
  "properties": {
    "iso:country": "GB",
    "wof:name": "BS31 2PJ",
    "wof:placetype": "postalcode"
  },
  "geometry": {"coordinates":[-2.512415,51.409379],"type":"Point"}
}
