{
  "type": "Feature",
  "properties": {
    "iso:country": "GB",
    "wof:name": "CT14 0BX",
    "wof:placetype": "postalcode"
  },
  "geometry": {"coordinates":[1.320146,51.253864],"type":"Point"}
}
