{
  "type": "Feature",
  "properties": {
    "iso:country":"GB",
    "wof:name":"CT14 0BX",
    "wof:placetype":"postalcode"
},
  "geometry": {"coordinates":[1.32014598400654,51.25386367244671],"type":"Point"}
}