{
  "type": "Feature",
  "properties": {
    "iso:country": "GB",
    "wof:name": "SO19 9QP",
    "wof:placetype": "postalcode"
  },
  "geometry": {"coordinates":[-1.355842,50.887566],"type":"Point"}
}
