{
  "type": "Feature",
  "properties": {
    "iso:country":"GB",
    "wof:name":"SK8 3JH",
    "wof:placetype":"postalcode"
},
  "geometry": {"coordinates":[-2.2323007008853,53.36790359090928],"type":"Point"}
}