{
  "type": "Feature",
  "properties": {
    "iso:country": "GB",
    "wof:name": "N4 1TG",
    "wof:placetype": "postalcode"
  },
  "geometry": {"coordinates":[-0.091213,51.57553],"type":"Point"}
}
