{
  "type": "Feature",
  "properties": {
    "date:inception_lower": "2021-08-01",
    "date:inception_upper": "2021-08-01",
    "iso:country": "GB",
    "wof:name": "PO14 1FX",
    "wof:placetype": "postalcode"
  },
  "geometry": {"coordinates":[-1.198071,50.849189],"type":"Point"}
}
