{
  "type": "Feature",
  "properties": {
    "iso:country":"GB",
    "wof:name":"SW16 2QN",
    "wof:placetype":"postalcode"
},
  "geometry": {"coordinates":[-0.11523002818661,51.42425906167004],"type":"Point"}
}