{
  "type": "Feature",
  "properties": {
    "iso:country":"GB",
    "wof:name":"S65 4PH",
    "wof:placetype":"postalcode"
},
  "geometry": {"coordinates":[-1.29582206600423,53.45391058879684],"type":"Point"}
}