{
  "type": "Feature",
  "properties": {
    "date:inception_lower":"1980-01-01",
    "date:inception_upper":"1980-01-31",
    "iso:country":"GB",
    "wof:name":"S65 4PH",
    "wof:placetype":"postalcode"
},
  "geometry": {"coordinates":[-1.295822,53.453911],"type":"Point"}
}