{
  "type": "Feature",
  "properties": {
    "date:inception_lower": "1990-07-01",
    "date:inception_upper": "1990-07-01",
    "iso:country": "GB",
    "wof:name": "MK42 7PN",
    "wof:placetype": "postalcode"
  },
  "geometry": {"coordinates":[-0.497386,52.10557],"type":"Point"}
}
