{
  "type": "Feature",
  "properties": {
    "iso:country":"GB",
    "wof:name":"MK42 7PN",
    "wof:placetype":"postalcode"
},
  "geometry": {"coordinates":[-0.49785441749957,52.10573445871396],"type":"Point"}
}