{
  "type": "Feature",
  "properties": {
    "date:inception_lower": "2013-01-01",
    "date:inception_upper": "2013-01-01",
    "iso:country": "GB",
    "wof:name": "MK14 5FX",
    "wof:placetype": "postalcode"
  },
  "geometry": {"coordinates":[-0.751049,52.078937],"type":"Point"}
}
