{
  "type": "Feature",
  "properties": {
    "date:inception_lower": "1980-01-01",
    "date:inception_upper": "1980-01-01",
    "iso:country": "GB",
    "wof:name": "DA14 4DA",
    "wof:placetype": "postalcode"
  },
  "geometry": {"coordinates":[0.104773,51.427601],"type":"Point"}
}
