{
  "type": "Feature",
  "properties": {
    "iso:country":"GB",
    "wof:name":"DA14 4DA",
    "wof:placetype":"postalcode"
},
  "geometry": {"coordinates":[0.10477257302284,51.42760081118897],"type":"Point"}
}