{
  "type": "Feature",
  "properties": {
    "iso:country":"GB",
    "wof:name":"BN6 8LG",
    "wof:placetype":"postalcode"
},
  "geometry": {"coordinates":[-0.14088484087204,50.9214667869955],"type":"Point"}
}