{
  "type": "Feature",
  "properties": {
    "iso:country":"GB",
    "wof:name":"PE6 8JS",
    "wof:placetype":"postalcode"
},
  "geometry": {"coordinates":[-0.31764188449687,52.67800148271185],"type":"Point"}
}