{
  "type": "Feature",
  "properties": {
    "date:inception_lower": "1980-01-01",
    "date:inception_upper": "1980-01-01",
    "iso:country": "GB",
    "wof:name": "PE6 8JS",
    "wof:placetype": "postalcode"
  },
  "geometry": {"coordinates":[-0.317642,52.678001],"type":"Point"}
}
