{
  "type": "Feature",
  "properties": {
    "iso:country":"GB",
    "wof:name":"LU7 4UT",
    "wof:placetype":"postalcode"
},
  "geometry": {"coordinates":[-0.64744445967577,51.90866708749534],"type":"Point"}
}