{
  "type": "Feature",
  "properties": {
    "iso:country":"GB",
    "wof:name":"SK6 8JD",
    "wof:placetype":"postalcode"
},
  "geometry": {"coordinates":[-2.07371151950712,53.37146894855098],"type":"Point"}
}