{
  "type": "Feature",
  "properties": {
    "iso:country": "GB",
    "wof:name": "SK6 8JD",
    "wof:placetype": "postalcode"
  },
  "geometry": {"coordinates":[-2.073711,53.371469],"type":"Point"}
}
