{
  "type": "Feature",
  "properties": {
    "iso:country":"GB",
    "wof:name":"OL13 0DA",
    "wof:placetype":"postalcode"
},
  "geometry": {"coordinates":[-2.20597375125927,53.69455357966244],"type":"Point"}
}