{
  "type": "Feature",
  "properties": {
    "date:inception_lower": "1988-11-01",
    "date:inception_upper": "1988-11-01",
    "iso:country": "GB",
    "wof:name": "ML10 6EN",
    "wof:placetype": "postalcode"
  },
  "geometry": {"coordinates":[-4.072558,55.679393],"type":"Point"}
}
