{
  "type": "Feature",
  "properties": {
    "iso:country":"GB",
    "wof:name":"CT4 5AB",
    "wof:placetype":"postalcode"
},
  "geometry": {"coordinates":[1.10810761834052,51.25456371591807],"type":"Point"}
}