{
  "type": "Feature",
  "properties": {
    "iso:country":"GB",
    "wof:name":"BA3 3QU",
    "wof:placetype":"postalcode"
},
  "geometry": {"coordinates":[-2.45070323296464,51.28328937165717],"type":"Point"}
}