{
  "type": "Feature",
  "properties": {
    "iso:country":"GB",
    "wof:name":"SW17 7QH",
    "wof:placetype":"postalcode"
},
  "geometry": {"coordinates":[-0.15797563494224,51.44116131125593],"type":"Point"}
}