{
  "type": "Feature",
  "properties": {
    "iso:country":"GB",
    "wof:name":"BD19 6ER",
    "wof:placetype":"postalcode"
},
  "geometry": {"coordinates":[-1.74844176026822,53.73015033136331],"type":"Point"}
}