{
  "type": "Feature",
  "properties": {
    "date:inception_lower": "1980-01-01",
    "date:inception_upper": "1980-01-01",
    "iso:country": "GB",
    "wof:name": "HG2 0PW",
    "wof:placetype": "postalcode"
  },
  "geometry": {"coordinates":[-1.551972,53.9884],"type":"Point"}
}
