{
  "type": "Feature",
  "properties": {
    "iso:country":"GB",
    "wof:name":"ST14 8QG",
    "wof:placetype":"postalcode"
},
  "geometry": {"coordinates":[-1.90869605960714,52.87139104051462],"type":"Point"}
}