{
  "type": "Feature",
  "properties": {
    "iso:country": "GB",
    "wof:name": "ST14 8QG",
    "wof:placetype": "postalcode"
  },
  "geometry": {"coordinates":[-1.913166,52.863429],"type":"Point"}
}
