{
  "type": "Feature",
  "properties": {
    "iso:country":"GB",
    "wof:name":"B77 2AU",
    "wof:placetype":"postalcode"
},
  "geometry": {"coordinates":[-1.67485887558628,52.62825382262137],"type":"Point"}
}