{
  "type": "Feature",
  "properties": {
    "iso:country":"GB",
    "wof:name":"NR13 4EB",
    "wof:placetype":"postalcode"
},
  "geometry": {"coordinates":[1.47046125840225,52.64275705804506],"type":"Point"}
}