{
  "type": "Feature",
  "properties": {
    "iso:country": "GB",
    "wof:name": "NR13 4EB",
    "wof:placetype": "postalcode"
  },
  "geometry": {"coordinates":[1.470484,52.642774],"type":"Point"}
}
