{
  "type": "Feature",
  "properties": {
    "iso:country":"GB",
    "wof:name":"SA1 4HZ",
    "wof:placetype":"postalcode"
},
  "geometry": {"coordinates":[-3.95598472393149,51.61855569441642],"type":"Point"}
}