{
  "type": "Feature",
  "properties": {
    "date:inception_lower": "1990-07-01",
    "date:inception_upper": "1990-07-01",
    "iso:country": "GB",
    "wof:name": "SA1 4HZ",
    "wof:placetype": "postalcode"
  },
  "geometry": {"coordinates":[-3.955985,51.618556],"type":"Point"}
}
