{
  "type": "Feature",
  "properties": {
    "date:inception_lower":"1991-09-01",
    "date:inception_upper":"1991-09-30",
    "iso:country":"GB",
    "wof:name":"CB9 7EA",
    "wof:placetype":"postalcode"
},
  "geometry": {"coordinates":[0.449793,52.041875],"type":"Point"}
}