{
  "type": "Feature",
  "properties": {
    "iso:country": "GB",
    "wof:name": "CB9 7EA",
    "wof:placetype": "postalcode"
  },
  "geometry": {"coordinates":[0.449793,52.041875],"type":"Point"}
}
