{
  "type": "Feature",
  "properties": {
    "iso:country":"GB",
    "wof:name":"N1 2XD",
    "wof:placetype":"postalcode"
},
  "geometry": {"coordinates":[-0.1022691697087,51.54396611780593],"type":"Point"}
}