{
  "type": "Feature",
  "properties": {
    "iso:country": "GB",
    "wof:name": "CB22 3LG",
    "wof:placetype": "postalcode"
  },
  "geometry": {"coordinates":[0.176524,52.126342],"type":"Point"}
}
