{
  "type": "Feature",
  "properties": {
    "iso:country": "GB",
    "wof:name": "CR3 7AB",
    "wof:placetype": "postalcode"
  },
  "geometry": {"coordinates":[-0.025189,51.275887],"type":"Point"}
}
