{
  "type": "Feature",
  "properties": {
    "iso:country":"GB",
    "wof:name":"CR3 7AB",
    "wof:placetype":"postalcode"
},
  "geometry": {"coordinates":[-0.02518861842349,51.27588697331276],"type":"Point"}
}