{
  "type": "Feature",
  "properties": {
    "date:inception_lower": "1980-01-01",
    "date:inception_upper": "1980-01-01",
    "iso:country": "GB",
    "wof:name": "CR3 7AB",
    "wof:placetype": "postalcode"
  },
  "geometry": {"coordinates":[-0.025189,51.275887],"type":"Point"}
}
