{
  "type": "Feature",
  "properties": {
    "iso:country": "GB",
    "wof:name": "RH10 7BD",
    "wof:placetype": "postalcode"
  },
  "geometry": {"coordinates":[-0.147622,51.120197],"type":"Point"}
}
