{
  "type": "Feature",
  "properties": {
    "iso:country": "GB",
    "wof:name": "TR16 6AW",
    "wof:placetype": "postalcode"
  },
  "geometry": {"coordinates":[-5.239623,50.205513],"type":"Point"}
}
