{
  "type": "Feature",
  "properties": {
    "iso:country":"GB",
    "wof:name":"DH7 6EB",
    "wof:placetype":"postalcode"
},
  "geometry": {"coordinates":[-1.6447903621182,54.84211754253718],"type":"Point"}
}