{
  "type": "Feature",
  "properties": {
    "iso:country": "GB",
    "wof:name": "DH7 6EB",
    "wof:placetype": "postalcode"
  },
  "geometry": {"coordinates":[-1.644818,54.842126],"type":"Point"}
}
