{
  "type": "Feature",
  "properties": {
    "date:inception_lower": "1980-01-01",
    "date:inception_upper": "1980-01-01",
    "iso:country": "GB",
    "wof:name": "DH7 6EB",
    "wof:placetype": "postalcode"
  },
  "geometry": {"coordinates":[-1.644818,54.842126],"type":"Point"}
}
