{
  "type": "Feature",
  "properties": {
    "iso:country":"GB",
    "wof:name":"PO18 0RL",
    "wof:placetype":"postalcode"
},
  "geometry": {"coordinates":[-0.7941013118439,50.90648786137297],"type":"Point"}
}