{
  "type": "Feature",
  "properties": {
    "date:inception_lower": "2004-09-01",
    "date:inception_upper": "2004-09-01",
    "iso:country": "GB",
    "wof:name": "RG22 4FR",
    "wof:placetype": "postalcode"
  },
  "geometry": {"coordinates":[-1.139345,51.228888],"type":"Point"}
}
