{
  "type": "Feature",
  "properties": {
    "iso:country": "GB",
    "wof:name": "RG22 4FR",
    "wof:placetype": "postalcode"
  },
  "geometry": {"coordinates":[-1.139345,51.228888],"type":"Point"}
}
