{
  "type": "Feature",
  "properties": {
    "iso:country":"GB",
    "wof:name":"RG22 4FR",
    "wof:placetype":"postalcode"
},
  "geometry": {"coordinates":[-1.13934491511878,51.22888770152397],"type":"Point"}
}