{
  "type": "Feature",
  "properties": {
    "iso:country":"GB",
    "wof:name":"N15 4PN",
    "wof:placetype":"postalcode"
},
  "geometry": {"coordinates":[-0.06883413003336,51.58359008823926],"type":"Point"}
}