{
  "type": "Feature",
  "properties": {
    "iso:country":"GB",
    "wof:name":"CV11 6TH",
    "wof:placetype":"postalcode"
},
  "geometry": {"coordinates":[-1.42797921802592,52.50515533429806],"type":"Point"}
}