{
  "type": "Feature",
  "properties": {
    "iso:country": "GB",
    "wof:name": "BA21 3BG",
    "wof:placetype": "postalcode"
  },
  "geometry": {"coordinates":[-2.643836,50.952068],"type":"Point"}
}
