{
  "type": "Feature",
  "properties": {
    "iso:country":"GB",
    "wof:name":"BA21 3BG",
    "wof:placetype":"postalcode"
},
  "geometry": {"coordinates":[-2.64383651615889,50.95206769238645],"type":"Point"}
}