{
  "type": "Feature",
  "properties": {
    "iso:country": "GB",
    "wof:name": "BD23 6LF",
    "wof:placetype": "postalcode"
  },
  "geometry": {"coordinates":[-2.034288,54.036292],"type":"Point"}
}
