{
  "type": "Feature",
  "properties": {
    "date:inception_lower": "1980-01-01",
    "date:inception_upper": "1980-01-01",
    "iso:country": "GB",
    "wof:name": "BD23 6LF",
    "wof:placetype": "postalcode"
  },
  "geometry": {"coordinates":[-2.034292,54.036288],"type":"Point"}
}
