{
  "type": "Feature",
  "properties": {
    "iso:country": "GB",
    "wof:name": "GU34 2FT",
    "wof:placetype": "postalcode"
  },
  "geometry": {"coordinates":[-0.97013,51.164789],"type":"Point"}
}
