{
  "type": "Feature",
  "properties": {
    "iso:country":"GB",
    "wof:name":"CB3 0BT",
    "wof:placetype":"postalcode"
},
  "geometry": {"coordinates":[0.11169150731831,52.21324176868038],"type":"Point"}
}