{
  "type": "Feature",
  "properties": {
    "iso:country":"GB",
    "wof:name":"LL53 7AQ",
    "wof:placetype":"postalcode"
},
  "geometry": {"coordinates":[-4.49585850935087,52.8601817660427],"type":"Point"}
}