{
  "type": "Feature",
  "properties": {
    "date:inception_lower": "2012-04-01",
    "date:inception_upper": "2012-04-01",
    "iso:country": "GB",
    "wof:name": "LL53 7AQ",
    "wof:placetype": "postalcode"
  },
  "geometry": {"coordinates":[-4.495805,52.860164],"type":"Point"}
}
