{
  "type": "Feature",
  "properties": {
    "iso:country":"GB",
    "wof:name":"CH3 9QD",
    "wof:placetype":"postalcode"
},
  "geometry": {"coordinates":[-2.77311152633993,53.11886703832707],"type":"Point"}
}