{
  "type": "Feature",
  "properties": {
    "date:inception_lower": "1980-01-01",
    "date:inception_upper": "1980-01-01",
    "iso:country": "GB",
    "wof:name": "CH3 9QD",
    "wof:placetype": "postalcode"
  },
  "geometry": {"coordinates":[-2.773111,53.118867],"type":"Point"}
}
