{
  "type": "Feature",
  "properties": {
    "iso:country":"GB",
    "wof:name":"PA2 0NW",
    "wof:placetype":"postalcode"
},
  "geometry": {"coordinates":[-4.46371014262273,55.82991420768137],"type":"Point"}
}