{
  "type": "Feature",
  "properties": {
    "iso:country":"GB",
    "wof:name":"CO1 1BX",
    "wof:placetype":"postalcode"
},
  "geometry": {"coordinates":[0.90095993694597,51.89849156526987],"type":"Point"}
}