{
  "type": "Feature",
  "properties": {
    "date:inception_lower":"1984-02-01",
    "date:inception_upper":"1984-02-29",
    "iso:country":"GB",
    "wof:name":"CO1 1BX",
    "wof:placetype":"postalcode"
},
  "geometry": {"coordinates":[0.89975,51.898659],"type":"Point"}
}