{
  "type": "Feature",
  "properties": {
    "iso:country":"GB",
    "wof:name":"G12 9HS",
    "wof:placetype":"postalcode"
},
  "geometry": {"coordinates":[-4.3055143739176,55.87637435494903],"type":"Point"}
}