{
  "type": "Feature",
  "properties": {
    "iso:country":"GB",
    "wof:name":"B15 1AQ",
    "wof:placetype":"postalcode"
},
  "geometry": {"coordinates":[-1.91379884934859,52.47585858764999],"type":"Point"}
}