{
  "type": "Feature",
  "properties": {
    "date:inception_lower": "1980-01-01",
    "date:inception_upper": "1980-01-01",
    "iso:country": "GB",
    "wof:name": "B15 1AQ",
    "wof:placetype": "postalcode"
  },
  "geometry": {"coordinates":[-1.913794,52.475774],"type":"Point"}
}
