{
  "type": "Feature",
  "properties": {
    "iso:country":"GB",
    "wof:name":"MK40 1PW",
    "wof:placetype":"postalcode"
},
  "geometry": {"coordinates":[-0.47090211188639,52.13638996934102],"type":"Point"}
}