{
  "type": "Feature",
  "properties": {
    "iso:country": "GB",
    "wof:name": "MK40 1PW",
    "wof:placetype": "postalcode"
  },
  "geometry": {"coordinates":[-0.470902,52.13639],"type":"Point"}
}
