{
  "type": "Feature",
  "properties": {
    "iso:country":"GB",
    "wof:name":"TS7 8DB",
    "wof:placetype":"postalcode"
},
  "geometry": {"coordinates":[-1.18462302217148,54.53328463585598],"type":"Point"}
}