{
  "type": "Feature",
  "properties": {
    "date:inception_lower":"1980-01-01",
    "date:inception_upper":"1980-01-31",
    "iso:country":"GB",
    "wof:name":"NE66 4UB",
    "wof:placetype":"postalcode"
},
  "geometry": {"coordinates":[-1.99339,55.386621],"type":"Point"}
}