{
  "type": "Feature",
  "properties": {
    "iso:country":"GB",
    "wof:name":"CF37 3JE",
    "wof:placetype":"postalcode"
},
  "geometry": {"coordinates":[-3.33333863346616,51.62766747752688],"type":"Point"}
}