{
  "type": "Feature",
  "properties": {
    "iso:country": "GB",
    "wof:name": "YO17 8HY",
    "wof:placetype": "postalcode"
  },
  "geometry": {"coordinates":[-0.656474,54.150666],"type":"Point"}
}
