{
  "type": "Feature",
  "properties": {
    "iso:country":"GB",
    "wof:name":"YO31 7EY",
    "wof:placetype":"postalcode"
},
  "geometry": {"coordinates":[-1.08004655513329,53.96412016238155],"type":"Point"}
}