{
  "type": "Feature",
  "properties": {
    "date:inception_lower":"2009-03-01",
    "date:inception_upper":"2009-03-31",
    "iso:country":"GB",
    "wof:name":"YO31 7EY",
    "wof:placetype":"postalcode"
},
  "geometry": {"coordinates":[-1.080047,53.96412],"type":"Point"}
}