{
  "type": "Feature",
  "properties": {
    "iso:country": "GB",
    "wof:name": "YO31 7EY",
    "wof:placetype": "postalcode"
  },
  "geometry": {"coordinates":[-1.080047,53.96412],"type":"Point"}
}
