{
  "type": "Feature",
  "properties": {
    "iso:country": "GB",
    "wof:name": "LS21 3AN",
    "wof:placetype": "postalcode"
  },
  "geometry": {"coordinates":[-1.69334,53.906237],"type":"Point"}
}
