{
  "type": "Feature",
  "properties": {
    "date:inception_lower":"1980-01-01",
    "date:inception_upper":"1980-01-31",
    "iso:country":"GB",
    "wof:name":"LS21 3AN",
    "wof:placetype":"postalcode"
},
  "geometry": {"coordinates":[-1.69334,53.906237],"type":"Point"}
}