{
  "type": "Feature",
  "properties": {
    "iso:country":"GB",
    "wof:name":"PH23 3BX",
    "wof:placetype":"postalcode"
},
  "geometry": {"coordinates":[-3.8243924326335,57.28563796147102],"type":"Point"}
}