{
  "type": "Feature",
  "properties": {
    "date:inception_lower": "1998-12-01",
    "date:inception_upper": "1998-12-01",
    "iso:country": "GB",
    "wof:name": "PH23 3BX",
    "wof:placetype": "postalcode"
  },
  "geometry": {"coordinates":[-3.823639,57.285829],"type":"Point"}
}
