{
  "type": "Feature",
  "properties": {
    "date:inception_lower": "1980-01-01",
    "date:inception_upper": "1980-01-01",
    "iso:country": "GB",
    "wof:name": "DL5 6NU",
    "wof:placetype": "postalcode"
  },
  "geometry": {"coordinates":[-1.630419,54.604594],"type":"Point"}
}
