{
  "type": "Feature",
  "properties": {
    "iso:country":"GB",
    "wof:name":"DL5 6NU",
    "wof:placetype":"postalcode"
},
  "geometry": {"coordinates":[-1.6304194365111,54.60459404324187],"type":"Point"}
}