{
  "type": "Feature",
  "properties": {
    "iso:country":"GB",
    "wof:name":"WD3 6HN",
    "wof:placetype":"postalcode"
},
  "geometry": {"coordinates":[-0.49221491426972,51.68073758491639],"type":"Point"}
}