{
  "type": "Feature",
  "properties": {
    "iso:country":"GB",
    "wof:name":"PL25 3UQ",
    "wof:placetype":"postalcode"
},
  "geometry": {"coordinates":[-4.77005529188314,50.34859449569925],"type":"Point"}
}