{
  "type": "Feature",
  "properties": {
    "iso:country":"GB",
    "wof:name":"WS7 9EN",
    "wof:placetype":"postalcode"
},
  "geometry": {"coordinates":[-1.88435752850138,52.68226657257389],"type":"Point"}
}