{
  "type": "Feature",
  "properties": {
    "iso:country": "GB",
    "wof:name": "CT11 9LQ",
    "wof:placetype": "postalcode"
  },
  "geometry": {"coordinates":[1.417078,51.330158],"type":"Point"}
}
