{
  "type": "Feature",
  "properties": {
    "date:inception_lower":"1980-01-01",
    "date:inception_upper":"1980-01-31",
    "iso:country":"GB",
    "wof:name":"CT11 9LQ",
    "wof:placetype":"postalcode"
},
  "geometry": {"coordinates":[1.417078,51.330158],"type":"Point"}
}