{
  "type": "Feature",
  "properties": {
    "date:inception_lower": "1980-01-01",
    "date:inception_upper": "1980-01-01",
    "iso:country": "GB",
    "wof:name": "SA12 7SB",
    "wof:placetype": "postalcode"
  },
  "geometry": {"coordinates":[-3.824751,51.602073],"type":"Point"}
}
