{
  "type": "Feature",
  "properties": {
    "iso:country": "GB",
    "wof:name": "SA12 7SB",
    "wof:placetype": "postalcode"
  },
  "geometry": {"coordinates":[-3.824751,51.602073],"type":"Point"}
}
