{
  "type": "Feature",
  "properties": {
    "iso:country":"GB",
    "wof:name":"NE44 6BJ",
    "wof:placetype":"postalcode"
},
  "geometry": {"coordinates":[-1.98012470466862,54.91965656394847],"type":"Point"}
}