{
  "type": "Feature",
  "properties": {
    "iso:country":"GB",
    "wof:name":"WA7 6NA",
    "wof:placetype":"postalcode"
},
  "geometry": {"coordinates":[-2.66691675043165,53.34027901860136],"type":"Point"}
}