{
  "type": "Feature",
  "properties": {
    "date:inception_lower": "1982-03-01",
    "date:inception_upper": "1982-03-01",
    "iso:country": "GB",
    "wof:name": "WA7 6NA",
    "wof:placetype": "postalcode"
  },
  "geometry": {"coordinates":[-2.666917,53.340279],"type":"Point"}
}
