{
  "type": "Feature",
  "properties": {
    "iso:country":"GB",
    "wof:name":"KT22 8NY",
    "wof:placetype":"postalcode"
},
  "geometry": {"coordinates":[-0.31778618544915,51.28774114098043],"type":"Point"}
}