{
  "type": "Feature",
  "properties": {
    "iso:country":"GB",
    "wof:name":"NN17 1PB",
    "wof:placetype":"postalcode"
},
  "geometry": {"coordinates":[-0.70048799462568,52.48828256393657],"type":"Point"}
}