{
  "type": "Feature",
  "properties": {
    "date:inception_lower":"1994-12-01",
    "date:inception_upper":"1994-12-31",
    "iso:country":"GB",
    "wof:name":"OL16 2BY",
    "wof:placetype":"postalcode"
},
  "geometry": {"coordinates":[-2.151439,53.619],"type":"Point"}
}