{
  "type": "Feature",
  "properties": {
    "iso:country": "GB",
    "wof:name": "CT6 7SW",
    "wof:placetype": "postalcode"
  },
  "geometry": {"coordinates":[1.10818,51.357083],"type":"Point"}
}
