{
  "type": "Feature",
  "properties": {
    "iso:country":"GB",
    "wof:name":"E6 2BP",
    "wof:placetype":"postalcode"
},
  "geometry": {"coordinates":[0.06433524756034,51.53954294533916],"type":"Point"}
}