{
  "type": "Feature",
  "properties": {
    "iso:country":"GB",
    "wof:name":"TA23 0BB",
    "wof:placetype":"postalcode"
},
  "geometry": {"coordinates":[-3.33284499886668,51.18114095387174],"type":"Point"}
}