{
  "type": "Feature",
  "properties": {
    "date:inception_lower": "1983-01-01",
    "date:inception_upper": "1983-01-01",
    "iso:country": "GB",
    "wof:name": "TA23 0BB",
    "wof:placetype": "postalcode"
  },
  "geometry": {"coordinates":[-3.332845,51.181141],"type":"Point"}
}
