{
  "type": "Feature",
  "properties": {
    "date:inception_lower": "2022-10-01",
    "date:inception_upper": "2022-10-01",
    "iso:country": "GB",
    "wof:name": "B78 2BQ",
    "wof:placetype": "postalcode"
  },
  "geometry": {"coordinates":[-1.743827,52.56311],"type":"Point"}
}
