{
  "type": "Feature",
  "properties": {
    "iso:country":"GB",
    "wof:name":"RG12 8TZ",
    "wof:placetype":"postalcode"
},
  "geometry": {"coordinates":[-0.77612522193587,51.40805138820247],"type":"Point"}
}