{
  "type": "Feature",
  "properties": {
    "iso:country":"GB",
    "wof:name":"W1T 5LT",
    "wof:placetype":"postalcode"
},
  "geometry": {"coordinates":[-0.13994848123747,51.52392283961979],"type":"Point"}
}