{
  "type": "Feature",
  "properties": {
    "iso:country": "GB",
    "wof:name": "WF17 0HT",
    "wof:placetype": "postalcode"
  },
  "geometry": {"coordinates":[-1.641845,53.736638],"type":"Point"}
}
