{
  "type": "Feature",
  "properties": {
    "iso:country": "GB",
    "wof:name": "BN2 4RU",
    "wof:placetype": "postalcode"
  },
  "geometry": {"coordinates":[-0.107158,50.848987],"type":"Point"}
}
