{
  "type": "Feature",
  "properties": {
    "iso:country":"GB",
    "wof:name":"BN2 4RU",
    "wof:placetype":"postalcode"
},
  "geometry": {"coordinates":[-0.10715833791598,50.84898654108943],"type":"Point"}
}