{
  "type": "Feature",
  "properties": {
    "date:inception_lower": "1980-01-01",
    "date:inception_upper": "1980-01-01",
    "iso:country": "GB",
    "wof:name": "OL10 4JG",
    "wof:placetype": "postalcode"
  },
  "geometry": {"coordinates":[-2.213443,53.596434],"type":"Point"}
}
