{
  "type": "Feature",
  "properties": {
    "iso:country":"GB",
    "wof:name":"OL10 4JG",
    "wof:placetype":"postalcode"
},
  "geometry": {"coordinates":[-2.21344317196543,53.59643424248672],"type":"Point"}
}