{
  "type": "Feature",
  "properties": {
    "iso:country":"GB",
    "wof:name":"N13 5QX",
    "wof:placetype":"postalcode"
},
  "geometry": {"coordinates":[-0.08802879756908,51.62250894869339],"type":"Point"}
}