{
  "type": "Feature",
  "properties": {
    "date:inception_lower": "1991-09-01",
    "date:inception_upper": "1991-09-01",
    "iso:country": "GB",
    "wof:name": "L12 0NU",
    "wof:placetype": "postalcode"
  },
  "geometry": {"coordinates":[-2.879034,53.441791],"type":"Point"}
}
