{
  "type": "Feature",
  "properties": {
    "iso:country":"GB",
    "wof:name":"L12 0NU",
    "wof:placetype":"postalcode"
},
  "geometry": {"coordinates":[-2.879033827179,53.44179122425403],"type":"Point"}
}