{
  "type": "Feature",
  "properties": {
    "iso:country":"GB",
    "wof:name":"B71 1HG",
    "wof:placetype":"postalcode"
},
  "geometry": {"coordinates":[-1.99394162462193,52.53445898078709],"type":"Point"}
}