{
  "type": "Feature",
  "properties": {
    "iso:country": "GB",
    "wof:name": "B71 1HG",
    "wof:placetype": "postalcode"
  },
  "geometry": {"coordinates":[-1.993942,52.534459],"type":"Point"}
}
