{
  "type": "Feature",
  "properties": {
    "iso:country":"GB",
    "wof:name":"HR3 5RE",
    "wof:placetype":"postalcode"
},
  "geometry": {"coordinates":[-3.11879949097948,52.06915281955375],"type":"Point"}
}