{
  "type": "Feature",
  "properties": {
    "iso:country":"GB",
    "wof:name":"NR35 2NT",
    "wof:placetype":"postalcode"
},
  "geometry": {"coordinates":[1.37135054382783,52.49370565248509],"type":"Point"}
}