{
  "type": "Feature",
  "properties": {
    "date:inception_lower": "1987-04-01",
    "date:inception_upper": "1987-04-01",
    "iso:country": "GB",
    "wof:name": "LA1 4TE",
    "wof:placetype": "postalcode"
  },
  "geometry": {"coordinates":[-2.795684,54.036071],"type":"Point"}
}
