{
  "type": "Feature",
  "properties": {
    "iso:country":"GB",
    "wof:name":"LA1 4TE",
    "wof:placetype":"postalcode"
},
  "geometry": {"coordinates":[-2.7956842132353,54.03607109230581],"type":"Point"}
}