{
  "type": "Feature",
  "properties": {
    "iso:country": "GB",
    "wof:name": "TR8 5PW",
    "wof:placetype": "postalcode"
  },
  "geometry": {"coordinates":[-5.129718,50.385251],"type":"Point"}
}
