{
  "type": "Feature",
  "properties": {
    "iso:country":"GB",
    "wof:name":"TR8 5PW",
    "wof:placetype":"postalcode"
},
  "geometry": {"coordinates":[-5.12971846780954,50.38525082924353],"type":"Point"}
}