{
  "type": "Feature",
  "properties": {
    "iso:country": "GB",
    "wof:name": "TA3 5BP",
    "wof:placetype": "postalcode"
  },
  "geometry": {"coordinates":[-3.048479,50.988136],"type":"Point"}
}
