{
  "type": "Feature",
  "properties": {
    "iso:country":"GB",
    "wof:name":"TA3 5BP",
    "wof:placetype":"postalcode"
},
  "geometry": {"coordinates":[-3.04847911554523,50.98813593513864],"type":"Point"}
}