{
  "type": "Feature",
  "properties": {
    "iso:country":"GB",
    "wof:name":"PH10 7QH",
    "wof:placetype":"postalcode"
},
  "geometry": {"coordinates":[-3.33236243727914,56.59415007545181],"type":"Point"}
}