{
  "type": "Feature",
  "properties": {
    "iso:country": "GB",
    "wof:name": "SN2 2SQ",
    "wof:placetype": "postalcode"
  },
  "geometry": {"coordinates":[-1.821851,51.587938],"type":"Point"}
}
