{
  "type": "Feature",
  "properties": {
    "iso:country":"GB",
    "wof:name":"SN2 2SQ",
    "wof:placetype":"postalcode"
},
  "geometry": {"coordinates":[-1.82185129852876,51.58793780616386],"type":"Point"}
}