{
  "type": "Feature",
  "properties": {
    "date:inception_lower": "1980-01-01",
    "date:inception_upper": "1980-01-01",
    "iso:country": "GB",
    "wof:name": "NN3 2LW",
    "wof:placetype": "postalcode"
  },
  "geometry": {"coordinates":[-0.863936,52.256399],"type":"Point"}
}
