{
  "type": "Feature",
  "properties": {
    "iso:country":"GB",
    "wof:name":"PE29 1BY",
    "wof:placetype":"postalcode"
},
  "geometry": {"coordinates":[-0.17986087421024,52.33429520762147],"type":"Point"}
}