{
  "type": "Feature",
  "properties": {
    "iso:country":"GB",
    "wof:name":"MK7 7HZ",
    "wof:placetype":"postalcode"
},
  "geometry": {"coordinates":[-0.70510483161549,52.01609622026328],"type":"Point"}
}