{
  "type": "Feature",
  "properties": {
    "iso:country":"GB",
    "wof:name":"SA3 5PB",
    "wof:placetype":"postalcode"
},
  "geometry": {"coordinates":[-4.01842616928398,51.58616818519024],"type":"Point"}
}