{
  "type": "Feature",
  "properties": {
    "iso:country": "GB",
    "wof:name": "SA3 5PB",
    "wof:placetype": "postalcode"
  },
  "geometry": {"coordinates":[-4.018426,51.586168],"type":"Point"}
}
