{
  "type": "Feature",
  "properties": {
    "date:inception_lower": "1990-02-01",
    "date:inception_upper": "1990-02-01",
    "iso:country": "GB",
    "wof:name": "NR3 3BL",
    "wof:placetype": "postalcode"
  },
  "geometry": {"coordinates":[1.291926,52.638224],"type":"Point"}
}
