{
  "type": "Feature",
  "properties": {
    "iso:country":"GB",
    "wof:name":"NR3 3BL",
    "wof:placetype":"postalcode"
},
  "geometry": {"coordinates":[1.29192602113858,52.63822447844441],"type":"Point"}
}