{
  "type": "Feature",
  "properties": {
    "iso:country":"GB",
    "wof:name":"MK7 7RU",
    "wof:placetype":"postalcode"
},
  "geometry": {"coordinates":[-0.68602792069913,52.02461549932221],"type":"Point"}
}