{
  "type": "Feature",
  "properties": {
    "date:inception_lower": "1980-01-01",
    "date:inception_upper": "1980-01-01",
    "iso:country": "GB",
    "wof:name": "S40 4PH",
    "wof:placetype": "postalcode"
  },
  "geometry": {"coordinates":[-1.454734,53.248288],"type":"Point"}
}
