{
  "type": "Feature",
  "properties": {
    "iso:country":"GB",
    "wof:name":"CO9 2PR",
    "wof:placetype":"postalcode"
},
  "geometry": {"coordinates":[0.66358882140399,51.99464025979898],"type":"Point"}
}