{
  "type": "Feature",
  "properties": {
    "iso:country": "GB",
    "wof:name": "CO9 2PR",
    "wof:placetype": "postalcode"
  },
  "geometry": {"coordinates":[0.663589,51.99464],"type":"Point"}
}
