{
  "type": "Feature",
  "properties": {
    "date:inception_lower": "2023-10-01",
    "date:inception_upper": "2023-10-01",
    "iso:country": "GB",
    "wof:name": "MK8 1HF",
    "wof:placetype": "postalcode"
  },
  "geometry": {"coordinates":[-0.82062,52.039141],"type":"Point"}
}
