{
  "type": "Feature",
  "properties": {
    "iso:country": "GB",
    "wof:name": "BN3 3HD",
    "wof:placetype": "postalcode"
  },
  "geometry": {"coordinates":[-0.177034,50.83526],"type":"Point"}
}
