{
  "type": "Feature",
  "properties": {
    "iso:country":"GB",
    "wof:name":"BN3 3HD",
    "wof:placetype":"postalcode"
},
  "geometry": {"coordinates":[-0.17703391424584,50.83526001256849],"type":"Point"}
}