{
  "type": "Feature",
  "properties": {
    "iso:country":"GB",
    "wof:name":"EX24 6NW",
    "wof:placetype":"postalcode"
},
  "geometry": {"coordinates":[-3.07160997895195,50.73808891280846],"type":"Point"}
}