{
  "type": "Feature",
  "properties": {
    "date:inception_lower":"1998-12-01",
    "date:inception_upper":"1998-12-31",
    "iso:country":"GB",
    "wof:name":"EX24 6NW",
    "wof:placetype":"postalcode"
},
  "geometry": {"coordinates":[-3.07161,50.738089],"type":"Point"}
}