{
  "type": "Feature",
  "properties": {
    "iso:country": "GB",
    "wof:name": "HU5 1LT",
    "wof:placetype": "postalcode"
  },
  "geometry": {"coordinates":[-0.355501,53.765642],"type":"Point"}
}
