{
  "type": "Feature",
  "properties": {
    "date:inception_lower": "1980-01-01",
    "date:inception_upper": "1980-01-01",
    "iso:country": "GB",
    "wof:name": "MK10 9AE",
    "wof:placetype": "postalcode"
  },
  "geometry": {"coordinates":[-0.707387,52.046116],"type":"Point"}
}
