{
  "type": "Feature",
  "properties": {
    "iso:country":"GB",
    "wof:name":"MK10 9AE",
    "wof:placetype":"postalcode"
},
  "geometry": {"coordinates":[-0.70738714749191,52.04611592351402],"type":"Point"}
}