{
  "type": "Feature",
  "properties": {
    "date:inception_lower":"1980-01-01",
    "date:inception_upper":"1980-01-31",
    "iso:country":"GB",
    "wof:name":"TA7 8RB",
    "wof:placetype":"postalcode"
},
  "geometry": {"coordinates":[-2.943734,51.133537],"type":"Point"}
}