{
  "type": "Feature",
  "properties": {
    "iso:country":"GB",
    "wof:name":"TA7 8RB",
    "wof:placetype":"postalcode"
},
  "geometry": {"coordinates":[-2.94373417754447,51.13353714901219],"type":"Point"}
}