{
  "type": "Feature",
  "properties": {
    "iso:country": "GB",
    "wof:name": "WA7 2EU",
    "wof:placetype": "postalcode"
  },
  "geometry": {"coordinates":[-2.697675,53.327309],"type":"Point"}
}
