{
  "type": "Feature",
  "properties": {
    "date:inception_lower": "1994-12-01",
    "date:inception_upper": "1994-12-01",
    "iso:country": "GB",
    "wof:name": "L7 5LZ",
    "wof:placetype": "postalcode"
  },
  "geometry": {"coordinates":[-2.946799,53.403313],"type":"Point"}
}
