{
  "type": "Feature",
  "properties": {
    "iso:country": "GB",
    "wof:name": "L7 5LZ",
    "wof:placetype": "postalcode"
  },
  "geometry": {"coordinates":[-2.946799,53.403313],"type":"Point"}
}
