{
  "type": "Feature",
  "properties": {
    "date:inception_lower": "2024-07-01",
    "date:inception_upper": "2024-07-01",
    "iso:country": "GB",
    "wof:name": "CH8 8BJ",
    "wof:placetype": "postalcode"
  },
  "geometry": {"coordinates":[-3.269003,53.281214],"type":"Point"}
}
