{
  "type": "Feature",
  "properties": {
    "iso:country":"GB",
    "wof:name":"UB5 6PT",
    "wof:placetype":"postalcode"
},
  "geometry": {"coordinates":[-0.4107508046583,51.53513388832979],"type":"Point"}
}