{
  "type": "Feature",
  "properties": {
    "iso:country":"GB",
    "wof:name":"LE5 3TQ",
    "wof:placetype":"postalcode"
},
  "geometry": {"coordinates":[-1.10156978142042,52.63821342689882],"type":"Point"}
}