{
  "type": "Feature",
  "properties": {
    "date:inception_lower": "1980-01-01",
    "date:inception_upper": "1980-01-01",
    "iso:country": "GB",
    "wof:name": "LE5 3TQ",
    "wof:placetype": "postalcode"
  },
  "geometry": {"coordinates":[-1.101473,52.638204],"type":"Point"}
}
