{
  "type": "Feature",
  "properties": {
    "iso:country": "GB",
    "wof:name": "RH5 6PS",
    "wof:placetype": "postalcode"
  },
  "geometry": {"coordinates":[-0.41441,51.198027],"type":"Point"}
}
