{
  "type": "Feature",
  "properties": {
    "iso:country":"GB",
    "wof:name":"RH5 6PS",
    "wof:placetype":"postalcode"
},
  "geometry": {"coordinates":[-0.41616701374592,51.19882756072185],"type":"Point"}
}