{
  "type": "Feature",
  "properties": {
    "iso:country":"GB",
    "wof:name":"SN2 2JA",
    "wof:placetype":"postalcode"
},
  "geometry": {"coordinates":[-1.80712954989682,51.56382672519919],"type":"Point"}
}