{
  "type": "Feature",
  "properties": {
    "iso:country": "GB",
    "wof:name": "CW9 6GN",
    "wof:placetype": "postalcode"
  },
  "geometry": {"coordinates":[-2.481663,53.272953],"type":"Point"}
}
