{
  "type": "Feature",
  "properties": {
    "date:inception_lower": "2019-03-01",
    "date:inception_upper": "2019-03-01",
    "iso:country": "GB",
    "wof:name": "CW9 6GN",
    "wof:placetype": "postalcode"
  },
  "geometry": {"coordinates":[-2.481663,53.272953],"type":"Point"}
}
