{
  "type": "Feature",
  "properties": {
    "iso:country":"GB",
    "wof:name":"SW17 9QS",
    "wof:placetype":"postalcode"
},
  "geometry": {"coordinates":[-0.15826288391056,51.42149900898561],"type":"Point"}
}