{
  "type": "Feature",
  "properties": {
    "iso:country": "GB",
    "wof:name": "TD2 6RB",
    "wof:placetype": "postalcode"
  },
  "geometry": {"coordinates":[-2.814188,55.788189],"type":"Point"}
}
