{
  "type": "Feature",
  "properties": {
    "iso:country":"GB",
    "wof:name":"TD2 6RB",
    "wof:placetype":"postalcode"
},
  "geometry": {"coordinates":[-2.81418815226578,55.78818937460967],"type":"Point"}
}