{
  "type": "Feature",
  "properties": {
    "date:inception_lower": "1980-01-01",
    "date:inception_upper": "1980-01-01",
    "iso:country": "GB",
    "wof:name": "TD2 6RB",
    "wof:placetype": "postalcode"
  },
  "geometry": {"coordinates":[-2.814188,55.788189],"type":"Point"}
}
