{
  "type": "Feature",
  "properties": {
    "iso:country":"GB",
    "wof:name":"RG5 4NJ",
    "wof:placetype":"postalcode"
},
  "geometry": {"coordinates":[-0.90064941543542,51.46091700649662],"type":"Point"}
}