{
  "type": "Feature",
  "properties": {
    "iso:country": "GB",
    "wof:name": "BH23 5DD",
    "wof:placetype": "postalcode"
  },
  "geometry": {"coordinates":[-1.70232,50.738895],"type":"Point"}
}
