{
  "type": "Feature",
  "properties": {
    "iso:country":"GB",
    "wof:name":"FY3 8BU",
    "wof:placetype":"postalcode"
},
  "geometry": {"coordinates":[-3.03649698643008,53.81876156990594],"type":"Point"}
}