{
  "type": "Feature",
  "properties": {
    "iso:country":"GB",
    "wof:name":"RH15 0AR",
    "wof:placetype":"postalcode"
},
  "geometry": {"coordinates":[-0.12684804287545,50.94609996382832],"type":"Point"}
}