{
  "type": "Feature",
  "properties": {
    "iso:country": "GB",
    "wof:name": "RH15 0AR",
    "wof:placetype": "postalcode"
  },
  "geometry": {"coordinates":[-0.126848,50.9461],"type":"Point"}
}
