{
  "type": "Feature",
  "properties": {
    "iso:country":"GB",
    "wof:name":"PO2 7NQ",
    "wof:placetype":"postalcode"
},
  "geometry": {"coordinates":[-1.06584903451685,50.8114521364187],"type":"Point"}
}