{
  "type": "Feature",
  "properties": {
    "iso:country": "GB",
    "wof:name": "PO2 7NQ",
    "wof:placetype": "postalcode"
  },
  "geometry": {"coordinates":[-1.065849,50.811452],"type":"Point"}
}
