{
  "type": "Feature",
  "properties": {
    "iso:country":"GB",
    "wof:name":"EC1R 3AS",
    "wof:placetype":"postalcode"
},
  "geometry": {"coordinates":[-0.11250190745144,51.52635300866561],"type":"Point"}
}