{
  "type": "Feature",
  "properties": {
    "iso:country":"GB",
    "wof:name":"HA5 3AQ",
    "wof:placetype":"postalcode"
},
  "geometry": {"coordinates":[-0.37241231901035,51.59452321769647],"type":"Point"}
}