{
  "type": "Feature",
  "properties": {
    "iso:country": "GB",
    "wof:name": "PL19 8ND",
    "wof:placetype": "postalcode"
  },
  "geometry": {"coordinates":[-4.154973,50.549653],"type":"Point"}
}
