{
  "type": "Feature",
  "properties": {
    "iso:country":"GB",
    "wof:name":"SO19 6FJ",
    "wof:placetype":"postalcode"
},
  "geometry": {"coordinates":[-1.34228255733637,50.90953088878928],"type":"Point"}
}