{
  "type": "Feature",
  "properties": {
    "date:inception_lower": "2023-03-01",
    "date:inception_upper": "2023-03-01",
    "iso:country": "GB",
    "wof:name": "NE15 9FU",
    "wof:placetype": "postalcode"
  },
  "geometry": {"coordinates":[-1.764197,54.998201],"type":"Point"}
}
