{
  "type": "Feature",
  "properties": {
    "iso:country":"GB",
    "wof:name":"SS7 1LS",
    "wof:placetype":"postalcode"
},
  "geometry": {"coordinates":[0.56622712583121,51.54572430743059],"type":"Point"}
}