{
  "type": "Feature",
  "properties": {
    "iso:country": "GB",
    "wof:name": "SS7 1LS",
    "wof:placetype": "postalcode"
  },
  "geometry": {"coordinates":[0.566227,51.545724],"type":"Point"}
}
