{
  "type": "Feature",
  "properties": {
    "iso:country":"GB",
    "wof:name":"CR4 4LS",
    "wof:placetype":"postalcode"
},
  "geometry": {"coordinates":[-0.16685332019846,51.39695793435823],"type":"Point"}
}