{
  "type": "Feature",
  "properties": {
    "iso:country":"GB",
    "wof:name":"WF2 9RJ",
    "wof:placetype":"postalcode"
},
  "geometry": {"coordinates":[-1.50827749088727,53.67770598215909],"type":"Point"}
}