{
  "type": "Feature",
  "properties": {
    "iso:country":"GB",
    "wof:name":"SM6 8PH",
    "wof:placetype":"postalcode"
},
  "geometry": {"coordinates":[-0.12752675959289,51.36163324961495],"type":"Point"}
}