{
  "type": "Feature",
  "properties": {
    "date:inception_lower": "1994-05-01",
    "date:inception_upper": "1994-05-01",
    "iso:country": "GB",
    "wof:name": "M22 9HT",
    "wof:placetype": "postalcode"
  },
  "geometry": {"coordinates":[-2.270231,53.389046],"type":"Point"}
}
