{
  "type": "Feature",
  "properties": {
    "iso:country":"GB",
    "wof:name":"M22 9HT",
    "wof:placetype":"postalcode"
},
  "geometry": {"coordinates":[-2.27023128332214,53.38904579607647],"type":"Point"}
}