{
  "type": "Feature",
  "properties": {
    "iso:country": "GB",
    "wof:name": "WV1 4AX",
    "wof:placetype": "postalcode"
  },
  "geometry": {"coordinates":[-2.135942,52.592491],"type":"Point"}
}
