{
  "type": "Feature",
  "properties": {
    "iso:country":"GB",
    "wof:name":"WV1 4AX",
    "wof:placetype":"postalcode"
},
  "geometry": {"coordinates":[-2.13594229405177,52.59249106787794],"type":"Point"}
}