{
  "type": "Feature",
  "properties": {
    "date:inception_lower":"1980-01-01",
    "date:inception_upper":"1980-01-31",
    "iso:country":"GB",
    "wof:name":"KA8 9DE",
    "wof:placetype":"postalcode"
},
  "geometry": {"coordinates":[-4.617742,55.481731],"type":"Point"}
}