{
  "type": "Feature",
  "properties": {
    "iso:country":"GB",
    "wof:name":"KA8 9DE",
    "wof:placetype":"postalcode"
},
  "geometry": {"coordinates":[-4.61774242083877,55.4817307011438],"type":"Point"}
}