{
  "type": "Feature",
  "properties": {
    "iso:country":"GB",
    "wof:name":"B98 7TU",
    "wof:placetype":"postalcode"
},
  "geometry": {"coordinates":[-1.92177522875612,52.28589406307353],"type":"Point"}
}