{
  "type": "Feature",
  "properties": {
    "date:inception_lower": "2017-02-01",
    "date:inception_upper": "2017-02-01",
    "iso:country": "GB",
    "wof:name": "FY6 7XH",
    "wof:placetype": "postalcode"
  },
  "geometry": {"coordinates":[-2.98599,53.849403],"type":"Point"}
}
