{
  "type": "Feature",
  "properties": {
    "date:inception_lower": "1980-01-01",
    "date:inception_upper": "1980-01-01",
    "iso:country": "GB",
    "wof:name": "LL19 9LD",
    "wof:placetype": "postalcode"
  },
  "geometry": {"coordinates":[-3.390483,53.338533],"type":"Point"}
}
