{
  "type": "Feature",
  "properties": {
    "iso:country":"GB",
    "wof:name":"S40 4DA",
    "wof:placetype":"postalcode"
},
  "geometry": {"coordinates":[-1.46049860517257,53.24035863545023],"type":"Point"}
}