{
  "type": "Feature",
  "properties": {
    "iso:country": "GB",
    "wof:name": "HR4 8BB",
    "wof:placetype": "postalcode"
  },
  "geometry": {"coordinates":[-2.734982,52.131673],"type":"Point"}
}
