{
  "type": "Feature",
  "properties": {
    "iso:country":"GB",
    "wof:name":"HR4 8BB",
    "wof:placetype":"postalcode"
},
  "geometry": {"coordinates":[-2.73498201468945,52.13167265966618],"type":"Point"}
}