{
  "type": "Feature",
  "properties": {
    "date:inception_lower": "1980-01-01",
    "date:inception_upper": "1980-01-01",
    "iso:country": "GB",
    "wof:name": "NG15 9FJ",
    "wof:placetype": "postalcode"
  },
  "geometry": {"coordinates":[-1.158542,53.090334],"type":"Point"}
}
