{
  "type": "Feature",
  "properties": {
    "iso:country": "GB",
    "wof:name": "NG15 9FJ",
    "wof:placetype": "postalcode"
  },
  "geometry": {"coordinates":[-1.158542,53.090334],"type":"Point"}
}
