{
  "type": "Feature",
  "properties": {
    "iso:country":"GB",
    "wof:name":"BD4 8RS",
    "wof:placetype":"postalcode"
},
  "geometry": {"coordinates":[-1.72109391074695,53.7834519136953],"type":"Point"}
}