{
  "type": "Feature",
  "properties": {
    "iso:country":"GB",
    "wof:name":"EX34 8PG",
    "wof:placetype":"postalcode"
},
  "geometry": {"coordinates":[-4.11295630791847,51.20144779347684],"type":"Point"}
}