{
  "type": "Feature",
  "properties": {
    "iso:country": "GB",
    "wof:name": "RG22 6LT",
    "wof:placetype": "postalcode"
  },
  "geometry": {"coordinates":[-1.124655,51.252851],"type":"Point"}
}
