{
  "type": "Feature",
  "properties": {
    "date:inception_lower": "1980-01-01",
    "date:inception_upper": "1980-01-01",
    "iso:country": "GB",
    "wof:name": "RG22 6LT",
    "wof:placetype": "postalcode"
  },
  "geometry": {"coordinates":[-1.124655,51.252851],"type":"Point"}
}
