{
  "type": "Feature",
  "properties": {
    "iso:country":"GB",
    "wof:name":"RG22 6LT",
    "wof:placetype":"postalcode"
},
  "geometry": {"coordinates":[-1.12465457402787,51.25285060885921],"type":"Point"}
}