{
  "type": "Feature",
  "properties": {
    "iso:country": "GB",
    "wof:name": "CA10 3UL",
    "wof:placetype": "postalcode"
  },
  "geometry": {"coordinates":[-2.550173,54.42422],"type":"Point"}
}
