{
  "type": "Feature",
  "properties": {
    "date:inception_lower": "2001-06-01",
    "date:inception_upper": "2001-06-01",
    "iso:country": "GB",
    "wof:name": "OX29 4LP",
    "wof:placetype": "postalcode"
  },
  "geometry": {"coordinates":[-1.372793,51.784863],"type":"Point"}
}
