{
  "type": "Feature",
  "properties": {
    "iso:country":"GB",
    "wof:name":"OX29 4LP",
    "wof:placetype":"postalcode"
},
  "geometry": {"coordinates":[-1.37279327772397,51.78486332691698],"type":"Point"}
}