{
  "type": "Feature",
  "properties": {
    "iso:country": "GB",
    "wof:name": "KA10 6NF",
    "wof:placetype": "postalcode"
  },
  "geometry": {"coordinates":[-4.653492,55.54328],"type":"Point"}
}
