{
  "type": "Feature",
  "properties": {
    "date:inception_lower":"1980-01-01",
    "date:inception_upper":"1980-01-31",
    "iso:country":"GB",
    "wof:name":"KA10 6NF",
    "wof:placetype":"postalcode"
},
  "geometry": {"coordinates":[-4.653492,55.54328],"type":"Point"}
}