{
  "type": "Feature",
  "properties": {
    "iso:country":"GB",
    "wof:name":"KA10 6NF",
    "wof:placetype":"postalcode"
},
  "geometry": {"coordinates":[-4.65290701717799,55.54353568520077],"type":"Point"}
}