{
  "type": "Feature",
  "properties": {
    "date:inception_lower": "2015-12-01",
    "date:inception_upper": "2015-12-01",
    "iso:country": "GB",
    "wof:name": "WR10 2ND",
    "wof:placetype": "postalcode"
  },
  "geometry": {"coordinates":[-2.066873,52.142193],"type":"Point"}
}
