{
  "type": "Feature",
  "properties": {
    "iso:country":"GB",
    "wof:name":"WR10 2ND",
    "wof:placetype":"postalcode"
},
  "geometry": {"coordinates":[-2.06693782131657,52.14209076704334],"type":"Point"}
}