{
  "type": "Feature",
  "properties": {
    "iso:country":"GB",
    "wof:name":"SO16 7PS",
    "wof:placetype":"postalcode"
},
  "geometry": {"coordinates":[-1.42381023732251,50.96024717163989],"type":"Point"}
}