{
  "type": "Feature",
  "properties": {
    "iso:country": "GB",
    "wof:name": "GU34 1QY",
    "wof:placetype": "postalcode"
  },
  "geometry": {"coordinates":[-0.988805,51.14795],"type":"Point"}
}
