{
  "type": "Feature",
  "properties": {
    "date:inception_lower":"1980-01-01",
    "date:inception_upper":"1980-01-31",
    "iso:country":"GB",
    "wof:name":"TQ11 0JR",
    "wof:placetype":"postalcode"
},
  "geometry": {"coordinates":[-3.767947,50.486149],"type":"Point"}
}