{
  "type": "Feature",
  "properties": {
    "iso:country": "GB",
    "wof:name": "TQ11 0JR",
    "wof:placetype": "postalcode"
  },
  "geometry": {"coordinates":[-3.767947,50.486149],"type":"Point"}
}
