{
  "type": "Feature",
  "properties": {
    "iso:country": "GB",
    "wof:name": "CH1 2BD",
    "wof:placetype": "postalcode"
  },
  "geometry": {"coordinates":[-2.894549,53.190317],"type":"Point"}
}
