{
  "type": "Feature",
  "properties": {
    "date:inception_lower": "1993-01-01",
    "date:inception_upper": "1993-01-01",
    "iso:country": "GB",
    "wof:name": "CF62 7EA",
    "wof:placetype": "postalcode"
  },
  "geometry": {"coordinates":[-3.283847,51.399922],"type":"Point"}
}
