{
  "type": "Feature",
  "properties": {
    "iso:country":"GB",
    "wof:name":"CV31 1LB",
    "wof:placetype":"postalcode"
},
  "geometry": {"coordinates":[-1.51449625596235,52.28344853211158],"type":"Point"}
}