{
  "type": "Feature",
  "properties": {
    "iso:country":"GB",
    "wof:name":"ST3 3JU",
    "wof:placetype":"postalcode"
},
  "geometry": {"coordinates":[-2.15817187627121,52.97168571555792],"type":"Point"}
}