{
  "type": "Feature",
  "properties": {
    "date:inception_lower": "1980-01-01",
    "date:inception_upper": "1980-01-01",
    "iso:country": "GB",
    "wof:name": "ST3 3JU",
    "wof:placetype": "postalcode"
  },
  "geometry": {"coordinates":[-2.158246,52.971685],"type":"Point"}
}
