{
  "type": "Feature",
  "properties": {
    "iso:country":"GB",
    "wof:name":"CO10 9SF",
    "wof:placetype":"postalcode"
},
  "geometry": {"coordinates":[0.78646554453768,52.09998402564643],"type":"Point"}
}