{
  "type": "Feature",
  "properties": {
    "iso:country":"GB",
    "wof:name":"DE21 6EP",
    "wof:placetype":"postalcode"
},
  "geometry": {"coordinates":[-1.45599905057348,52.92319191463213],"type":"Point"}
}