{
  "type": "Feature",
  "properties": {
    "date:inception_lower": "1980-01-01",
    "date:inception_upper": "1980-01-01",
    "iso:country": "GB",
    "wof:name": "GL11 5BN",
    "wof:placetype": "postalcode"
  },
  "geometry": {"coordinates":[-2.310791,51.679662],"type":"Point"}
}
