{
  "type": "Feature",
  "properties": {
    "iso:country":"GB",
    "wof:name":"SW15 2DS",
    "wof:placetype":"postalcode"
},
  "geometry": {"coordinates":[-0.21452359477718,51.46112735952041],"type":"Point"}
}