{
  "type": "Feature",
  "properties": {
    "iso:country":"GB",
    "wof:name":"PE28 4JZ",
    "wof:placetype":"postalcode"
},
  "geometry": {"coordinates":[-0.26982287881734,52.37404836975288],"type":"Point"}
}