{
  "type": "Feature",
  "properties": {
    "iso:country":"GB",
    "wof:name":"OX26 2YX",
    "wof:placetype":"postalcode"
},
  "geometry": {"coordinates":[-1.17015000413002,51.90513257603796],"type":"Point"}
}