{
  "type": "Feature",
  "properties": {
    "iso:country":"GB",
    "wof:name":"BS16 5UE",
    "wof:placetype":"postalcode"
},
  "geometry": {"coordinates":[-2.50756626049674,51.48686287116945],"type":"Point"}
}