{
  "type": "Feature",
  "properties": {
    "date:inception_lower": "2023-04-01",
    "date:inception_upper": "2023-04-01",
    "iso:country": "GB",
    "wof:name": "DE65 5SD",
    "wof:placetype": "postalcode"
  },
  "geometry": {"coordinates":[-1.675187,52.870479],"type":"Point"}
}
