{
  "type": "Feature",
  "properties": {
    "iso:country": "GB",
    "wof:name": "DH1 5YU",
    "wof:placetype": "postalcode"
  },
  "geometry": {"coordinates":[-1.57207,54.792233],"type":"Point"}
}
