{
  "type": "Feature",
  "properties": {
    "date:inception_lower": "1995-12-01",
    "date:inception_upper": "1995-12-01",
    "iso:country": "GB",
    "wof:name": "DH1 5YU",
    "wof:placetype": "postalcode"
  },
  "geometry": {"coordinates":[-1.57207,54.792233],"type":"Point"}
}
