{
  "type": "Feature",
  "properties": {
    "iso:country":"GB",
    "wof:name":"LE12 9RG",
    "wof:placetype":"postalcode"
},
  "geometry": {"coordinates":[-1.28921351324721,52.77589834385627],"type":"Point"}
}