{
  "type": "Feature",
  "properties": {
    "iso:country": "GB",
    "wof:name": "NG18 1BQ",
    "wof:placetype": "postalcode"
  },
  "geometry": {"coordinates":[-1.196383,53.142149],"type":"Point"}
}
