{
  "type": "Feature",
  "properties": {
    "date:inception_lower": "2021-05-01",
    "date:inception_upper": "2021-05-01",
    "iso:country": "GB",
    "wof:name": "IV30 8BS",
    "wof:placetype": "postalcode"
  },
  "geometry": {"coordinates":[-3.283828,57.63084],"type":"Point"}
}
