{
  "type": "Feature",
  "properties": {
    "iso:country":"GB",
    "wof:name":"SN15 3AY",
    "wof:placetype":"postalcode"
},
  "geometry": {"coordinates":[-2.10859406400446,51.45404073844174],"type":"Point"}
}