{
  "type": "Feature",
  "properties": {
    "date:inception_lower": "2002-12-01",
    "date:inception_upper": "2002-12-01",
    "iso:country": "GB",
    "wof:name": "SN15 3AY",
    "wof:placetype": "postalcode"
  },
  "geometry": {"coordinates":[-2.108594,51.454041],"type":"Point"}
}
