{
  "type": "Feature",
  "properties": {
    "iso:country":"GB",
    "wof:name":"M21 9NR",
    "wof:placetype":"postalcode"
},
  "geometry": {"coordinates":[-2.28159389615123,53.4475170664596],"type":"Point"}
}