{
  "type": "Feature",
  "properties": {
    "iso:country": "GB",
    "wof:name": "M21 9NR",
    "wof:placetype": "postalcode"
  },
  "geometry": {"coordinates":[-2.281594,53.447517],"type":"Point"}
}
