{
  "type": "Feature",
  "properties": {
    "date:inception_lower": "2021-07-01",
    "date:inception_upper": "2021-07-01",
    "iso:country": "GB",
    "wof:name": "LS2 9BX",
    "wof:placetype": "postalcode"
  },
  "geometry": {"coordinates":[-1.559633,53.803881],"type":"Point"}
}
