{
  "type": "Feature",
  "properties": {
    "date:inception_lower": "2006-09-01",
    "date:inception_upper": "2006-09-01",
    "iso:country": "GB",
    "wof:name": "PA5 9BL",
    "wof:placetype": "postalcode"
  },
  "geometry": {"coordinates":[-4.480429,55.830903],"type":"Point"}
}
