{
  "type": "Feature",
  "properties": {
    "iso:country":"GB",
    "wof:name":"PA5 9BL",
    "wof:placetype":"postalcode"
},
  "geometry": {"coordinates":[-4.48042899251222,55.83090827186997],"type":"Point"}
}