{
  "type": "Feature",
  "properties": {
    "date:inception_lower":"1980-01-01",
    "date:inception_upper":"1980-01-31",
    "iso:country":"GB",
    "wof:name":"BA2 4SB",
    "wof:placetype":"postalcode"
},
  "geometry": {"coordinates":[-2.366694,51.367728],"type":"Point"}
}