{
  "type": "Feature",
  "properties": {
    "iso:country": "GB",
    "wof:name": "BA2 4SB",
    "wof:placetype": "postalcode"
  },
  "geometry": {"coordinates":[-2.366694,51.367728],"type":"Point"}
}
