{
  "type": "Feature",
  "properties": {
    "date:inception_lower": "2022-02-01",
    "date:inception_upper": "2022-02-01",
    "iso:country": "GB",
    "wof:name": "CO4 6EL",
    "wof:placetype": "postalcode"
  },
  "geometry": {"coordinates":[0.882254,51.913974],"type":"Point"}
}
