{
  "type": "Feature",
  "properties": {
    "iso:country":"GB",
    "wof:name":"CF5 1LA",
    "wof:placetype":"postalcode"
},
  "geometry": {"coordinates":[-3.21548939917206,51.48206534508211],"type":"Point"}
}