{
  "type": "Feature",
  "properties": {
    "iso:country": "GB",
    "wof:name": "SN16 0LT",
    "wof:placetype": "postalcode"
  },
  "geometry": {"coordinates":[-2.209201,51.575424],"type":"Point"}
}
