{
  "type": "Feature",
  "properties": {
    "iso:country":"GB",
    "wof:name":"SN16 0LT",
    "wof:placetype":"postalcode"
},
  "geometry": {"coordinates":[-2.20920112443107,51.57542368444539],"type":"Point"}
}