{
  "type": "Feature",
  "properties": {
    "iso:country":"GB",
    "wof:name":"NG12 3HB",
    "wof:placetype":"postalcode"
},
  "geometry": {"coordinates":[-1.06173979127912,52.92799721675659],"type":"Point"}
}