{
  "type": "Feature",
  "properties": {
    "iso:country": "GB",
    "wof:name": "NG12 3HB",
    "wof:placetype": "postalcode"
  },
  "geometry": {"coordinates":[-1.06174,52.927997],"type":"Point"}
}
