{
  "type": "Feature",
  "properties": {
    "iso:country":"GB",
    "wof:name":"E6 1BF",
    "wof:placetype":"postalcode"
},
  "geometry": {"coordinates":[0.04246055654902,51.53828919257477],"type":"Point"}
}