{
  "type": "Feature",
  "properties": {
    "iso:country":"GB",
    "wof:name":"DG6 4HR",
    "wof:placetype":"postalcode"
},
  "geometry": {"coordinates":[-4.03661274636148,54.8460772726963],"type":"Point"}
}