{
  "type": "Feature",
  "properties": {
    "iso:country":"GB",
    "wof:name":"W1G 7AX",
    "wof:placetype":"postalcode"
},
  "geometry": {"coordinates":[-0.14729143428568,51.52165604095509],"type":"Point"}
}