{
  "type": "Feature",
  "properties": {
    "iso:country":"GB",
    "wof:name":"B20 1NH",
    "wof:placetype":"postalcode"
},
  "geometry": {"coordinates":[-1.9497989978164,52.52512608157667],"type":"Point"}
}