{
  "type": "Feature",
  "properties": {
    "iso:country": "GB",
    "wof:name": "BH25 6SA",
    "wof:placetype": "postalcode"
  },
  "geometry": {"coordinates":[-1.668898,50.75286],"type":"Point"}
}
