{
  "type": "Feature",
  "properties": {
    "iso:country":"GB",
    "wof:name":"BH25 6SA",
    "wof:placetype":"postalcode"
},
  "geometry": {"coordinates":[-1.66861128573799,50.75228416816282],"type":"Point"}
}