{
  "type": "Feature",
  "properties": {
    "iso:country":"GB",
    "wof:name":"BA15 1TY",
    "wof:placetype":"postalcode"
},
  "geometry": {"coordinates":[-2.23501533614445,51.354075114028],"type":"Point"}
}