{
  "type": "Feature",
  "properties": {
    "date:inception_lower":"1980-01-01",
    "date:inception_upper":"1980-01-31",
    "iso:country":"GB",
    "wof:name":"BA15 1TY",
    "wof:placetype":"postalcode"
},
  "geometry": {"coordinates":[-2.235414,51.353981],"type":"Point"}
}