{
  "type": "Feature",
  "properties": {
    "date:inception_lower": "1995-01-01",
    "date:inception_upper": "1995-01-01",
    "iso:country": "GB",
    "wof:name": "IP3 8XE",
    "wof:placetype": "postalcode"
  },
  "geometry": {"coordinates":[1.206376,52.037902],"type":"Point"}
}
