{
  "type": "Feature",
  "properties": {
    "iso:country":"GB",
    "wof:name":"IP3 8XE",
    "wof:placetype":"postalcode"
},
  "geometry": {"coordinates":[1.20637627012519,52.03790213286081],"type":"Point"}
}