{
  "type": "Feature",
  "properties": {
    "iso:country":"GB",
    "wof:name":"GU22 8DF",
    "wof:placetype":"postalcode"
},
  "geometry": {"coordinates":[-0.53581755732054,51.322206869645],"type":"Point"}
}