{
  "type": "Feature",
  "properties": {
    "iso:country":"GB",
    "wof:name":"LE67 1TD",
    "wof:placetype":"postalcode"
},
  "geometry": {"coordinates":[-1.33138179694343,52.70755180645516],"type":"Point"}
}