{
  "type": "Feature",
  "properties": {
    "iso:country":"GB",
    "wof:name":"M33 3HD",
    "wof:placetype":"postalcode"
},
  "geometry": {"coordinates":[-2.30645353551117,53.42050818184785],"type":"Point"}
}