{
  "type": "Feature",
  "properties": {
    "iso:country":"GB",
    "wof:name":"TS26 9HP",
    "wof:placetype":"postalcode"
},
  "geometry": {"coordinates":[-1.21836838851436,54.68232327715546],"type":"Point"}
}