{
  "type": "Feature",
  "properties": {
    "iso:country": "GB",
    "wof:name": "GL7 1PG",
    "wof:placetype": "postalcode"
  },
  "geometry": {"coordinates":[-1.955759,51.703683],"type":"Point"}
}
