{
  "type": "Feature",
  "properties": {
    "iso:country":"GB",
    "wof:name":"GL7 1PG",
    "wof:placetype":"postalcode"
},
  "geometry": {"coordinates":[-1.95575874504066,51.70368269717336],"type":"Point"}
}