{
  "type": "Feature",
  "properties": {
    "iso:country":"GB",
    "wof:name":"BH9 3DA",
    "wof:placetype":"postalcode"
},
  "geometry": {"coordinates":[-1.86616755828982,50.74973715125202],"type":"Point"}
}