{
  "type": "Feature",
  "properties": {
    "iso:country": "GB",
    "wof:name": "SE15 2EF",
    "wof:placetype": "postalcode"
  },
  "geometry": {"coordinates":[-0.05397,51.471252],"type":"Point"}
}
