{
  "type": "Feature",
  "properties": {
    "iso:country": "GB",
    "wof:name": "KA7 2QF",
    "wof:placetype": "postalcode"
  },
  "geometry": {"coordinates":[-4.62592,55.44453],"type":"Point"}
}
