{
  "type": "Feature",
  "properties": {
    "iso:country":"GB",
    "wof:name":"TN22 3HT",
    "wof:placetype":"postalcode"
},
  "geometry": {"coordinates":[0.05844734792424,51.03723171417307],"type":"Point"}
}