{
  "type": "Feature",
  "properties": {
    "iso:country": "GB",
    "wof:name": "DH4 5JN",
    "wof:placetype": "postalcode"
  },
  "geometry": {"coordinates":[-1.486625,54.851312],"type":"Point"}
}
