{
  "type": "Feature",
  "properties": {
    "iso:country":"GB",
    "wof:name":"DH4 5JN",
    "wof:placetype":"postalcode"
},
  "geometry": {"coordinates":[-1.48662510565353,54.85131154923105],"type":"Point"}
}