{
  "type": "Feature",
  "properties": {
    "iso:country":"GB",
    "wof:name":"OX2 9NY",
    "wof:placetype":"postalcode"
},
  "geometry": {"coordinates":[-1.35070866287574,51.76000875982574],"type":"Point"}
}