{
  "type": "Feature",
  "properties": {
    "date:inception_lower": "1980-01-01",
    "date:inception_upper": "1980-01-01",
    "iso:country": "GB",
    "wof:name": "OX2 9NY",
    "wof:placetype": "postalcode"
  },
  "geometry": {"coordinates":[-1.350709,51.760009],"type":"Point"}
}
