{
  "type": "Feature",
  "properties": {
    "iso:country":"GB",
    "wof:name":"BB12 7RB",
    "wof:placetype":"postalcode"
},
  "geometry": {"coordinates":[-2.35868140624672,53.81074174206741],"type":"Point"}
}