{
  "type": "Feature",
  "properties": {
    "iso:country": "GB",
    "wof:name": "BB12 7RB",
    "wof:placetype": "postalcode"
  },
  "geometry": {"coordinates":[-2.358681,53.810742],"type":"Point"}
}
