{
  "type": "Feature",
  "properties": {
    "date:inception_lower": "2015-12-01",
    "date:inception_upper": "2015-12-01",
    "iso:country": "GB",
    "wof:name": "OX2 9SP",
    "wof:placetype": "postalcode"
  },
  "geometry": {"coordinates":[-1.302958,51.752916],"type":"Point"}
}
