{
  "type": "Feature",
  "properties": {
    "iso:country": "GB",
    "wof:name": "CT2 9AZ",
    "wof:placetype": "postalcode"
  },
  "geometry": {"coordinates":[1.014747,51.287337],"type":"Point"}
}
