{
  "type": "Feature",
  "properties": {
    "iso:country":"GB",
    "wof:name":"CT2 9AZ",
    "wof:placetype":"postalcode"
},
  "geometry": {"coordinates":[1.01474745454621,51.28733672714688],"type":"Point"}
}