{
  "type": "Feature",
  "properties": {
    "iso:country": "GB",
    "wof:name": "G42 0QD",
    "wof:placetype": "postalcode"
  },
  "geometry": {"coordinates":[-4.247707,55.835194],"type":"Point"}
}
