{
  "type": "Feature",
  "properties": {
    "date:inception_lower": "1980-01-01",
    "date:inception_upper": "1980-01-01",
    "iso:country": "GB",
    "wof:name": "PE15 8NG",
    "wof:placetype": "postalcode"
  },
  "geometry": {"coordinates":[0.091994,52.557702],"type":"Point"}
}
