{
  "type": "Feature",
  "properties": {
    "iso:country": "GB",
    "wof:name": "PE15 8NG",
    "wof:placetype": "postalcode"
  },
  "geometry": {"coordinates":[0.091994,52.557702],"type":"Point"}
}
