{
  "type": "Feature",
  "properties": {
    "date:inception_lower": "2023-01-01",
    "date:inception_upper": "2023-01-01",
    "iso:country": "GB",
    "wof:name": "DE55 5SN",
    "wof:placetype": "postalcode"
  },
  "geometry": {"coordinates":[-1.334011,53.13063],"type":"Point"}
}
