{
  "type": "Feature",
  "properties": {
    "date:inception_lower":"2000-06-01",
    "date:inception_upper":"2000-06-30",
    "iso:country":"GB",
    "wof:name":"BS4 1UP",
    "wof:placetype":"postalcode"
},
  "geometry": {"coordinates":[-2.589998,51.419453],"type":"Point"}
}