{
  "type": "Feature",
  "properties": {
    "iso:country": "GB",
    "wof:name": "SN15 3RW",
    "wof:placetype": "postalcode"
  },
  "geometry": {"coordinates":[-2.085064,51.446489],"type":"Point"}
}
