{
  "type": "Feature",
  "properties": {
    "iso:country":"GB",
    "wof:name":"SN15 3RW",
    "wof:placetype":"postalcode"
},
  "geometry": {"coordinates":[-2.08506396752425,51.4464893435733],"type":"Point"}
}