{
  "type": "Feature",
  "properties": {
    "iso:country":"GB",
    "wof:name":"SA12 6TG",
    "wof:placetype":"postalcode"
},
  "geometry": {"coordinates":[-3.81056784769906,51.59873218325352],"type":"Point"}
}