{
  "type": "Feature",
  "properties": {
    "date:inception_lower": "2023-11-01",
    "date:inception_upper": "2023-11-01",
    "iso:country": "GB",
    "wof:name": "LL55 1DQ",
    "wof:placetype": "postalcode"
  },
  "geometry": {"coordinates":[-4.259143,53.14282],"type":"Point"}
}
