{
  "type": "Feature",
  "properties": {
    "iso:country":"GB",
    "wof:name":"W5 4XA",
    "wof:placetype":"postalcode"
},
  "geometry": {"coordinates":[-0.31184955662358,51.49821483021338],"type":"Point"}
}