{
  "type": "Feature",
  "properties": {
    "date:inception_lower": "1999-12-01",
    "date:inception_upper": "1999-12-01",
    "iso:country": "GB",
    "wof:name": "CV47 2YQ",
    "wof:placetype": "postalcode"
  },
  "geometry": {"coordinates":[-1.386088,52.170515],"type":"Point"}
}
