{
  "type": "Feature",
  "properties": {
    "iso:country": "GB",
    "wof:name": "LN11 7LP",
    "wof:placetype": "postalcode"
  },
  "geometry": {"coordinates":[0.120151,53.448375],"type":"Point"}
}
