{
  "type": "Feature",
  "properties": {
    "iso:country":"GB",
    "wof:name":"LN11 7LP",
    "wof:placetype":"postalcode"
},
  "geometry": {"coordinates":[0.12015102469005,53.44837460607248],"type":"Point"}
}