{
  "type": "Feature",
  "properties": {
    "iso:country":"GB",
    "wof:name":"CB6 1ND",
    "wof:placetype":"postalcode"
},
  "geometry": {"coordinates":[0.30975962524544,52.45650531590993],"type":"Point"}
}