{
  "type": "Feature",
  "properties": {
    "iso:country":"GB",
    "wof:name":"HD4 6JS",
    "wof:placetype":"postalcode"
},
  "geometry": {"coordinates":[-1.7865170274538,53.62823555135565],"type":"Point"}
}