{
  "type": "Feature",
  "properties": {
    "iso:country":"GB",
    "wof:name":"W1G 9NL",
    "wof:placetype":"postalcode"
},
  "geometry": {"coordinates":[-0.14629898949049,51.51876276414639],"type":"Point"}
}