{
  "type": "Feature",
  "properties": {
    "date:inception_lower":"2000-10-01",
    "date:inception_upper":"2000-10-31",
    "iso:country":"GB",
    "wof:name":"W1G 9NL",
    "wof:placetype":"postalcode"
},
  "geometry": {"coordinates":[-0.146299,51.518763],"type":"Point"}
}