{
  "type": "Feature",
  "properties": {
    "iso:country":"GB",
    "wof:name":"UB1 3HG",
    "wof:placetype":"postalcode"
},
  "geometry": {"coordinates":[-0.37201750870698,51.51102514789434],"type":"Point"}
}