{
  "type": "Feature",
  "properties": {
    "iso:country": "GB",
    "wof:name": "NN12 8EY",
    "wof:placetype": "postalcode"
  },
  "geometry": {"coordinates":[-1.09898,52.191715],"type":"Point"}
}
