{
  "type": "Feature",
  "properties": {
    "iso:country":"GB",
    "wof:name":"NN12 8EY",
    "wof:placetype":"postalcode"
},
  "geometry": {"coordinates":[-1.0989803349275,52.19171546800516],"type":"Point"}
}