{
  "type": "Feature",
  "properties": {
    "iso:country": "GB",
    "wof:name": "FY8 3UD",
    "wof:placetype": "postalcode"
  },
  "geometry": {"coordinates":[-2.999086,53.757545],"type":"Point"}
}
