{
  "type": "Feature",
  "properties": {
    "iso:country":"GB",
    "wof:name":"L28 5RJ",
    "wof:placetype":"postalcode"
},
  "geometry": {"coordinates":[-2.86000890545276,53.43307578373783],"type":"Point"}
}