{
  "type": "Feature",
  "properties": {
    "iso:country": "GB",
    "wof:name": "BH21 1DN",
    "wof:placetype": "postalcode"
  },
  "geometry": {"coordinates":[-1.983841,50.805027],"type":"Point"}
}
