{
  "type": "Feature",
  "properties": {
    "date:inception_lower": "2006-07-01",
    "date:inception_upper": "2006-07-01",
    "iso:country": "GB",
    "wof:name": "DY4 0PZ",
    "wof:placetype": "postalcode"
  },
  "geometry": {"coordinates":[-2.031761,52.542429],"type":"Point"}
}
