{
  "type": "Feature",
  "properties": {
    "iso:country":"GB",
    "wof:name":"DY4 0PZ",
    "wof:placetype":"postalcode"
},
  "geometry": {"coordinates":[-2.03176144325388,52.54242880420198],"type":"Point"}
}