{
  "type": "Feature",
  "properties": {
    "iso:country":"GB",
    "wof:name":"NE15 9HS",
    "wof:placetype":"postalcode"
},
  "geometry": {"coordinates":[-1.75335158609459,54.99809198116768],"type":"Point"}
}