{
  "type": "Feature",
  "properties": {
    "date:inception_lower": "1980-01-01",
    "date:inception_upper": "1980-01-01",
    "iso:country": "GB",
    "wof:name": "NE15 9HS",
    "wof:placetype": "postalcode"
  },
  "geometry": {"coordinates":[-1.753352,54.998092],"type":"Point"}
}
