{
  "type": "Feature",
  "properties": {
    "iso:country":"GB",
    "wof:name":"LA9 5QE",
    "wof:placetype":"postalcode"
},
  "geometry": {"coordinates":[-2.75589440935937,54.34177189132386],"type":"Point"}
}