{
  "type": "Feature",
  "properties": {
    "iso:country": "GB",
    "wof:name": "LA9 5QE",
    "wof:placetype": "postalcode"
  },
  "geometry": {"coordinates":[-2.755894,54.341772],"type":"Point"}
}
