{
  "type": "Feature",
  "properties": {
    "date:inception_lower":"1980-01-01",
    "date:inception_upper":"1980-01-31",
    "iso:country":"GB",
    "wof:name":"SY8 2NX",
    "wof:placetype":"postalcode"
},
  "geometry": {"coordinates":[-2.713696,52.374358],"type":"Point"}
}