{
  "type": "Feature",
  "properties": {
    "iso:country":"GB",
    "wof:name":"WA7 5DX",
    "wof:placetype":"postalcode"
},
  "geometry": {"coordinates":[-2.71421432342262,53.33504336347871],"type":"Point"}
}