{
  "type": "Feature",
  "properties": {
    "iso:country":"GB",
    "wof:name":"BN43 5HB",
    "wof:placetype":"postalcode"
},
  "geometry": {"coordinates":[-0.25904481840887,50.82738428785567],"type":"Point"}
}