{
  "type": "Feature",
  "properties": {
    "iso:country": "GB",
    "wof:name": "YO25 8ES",
    "wof:placetype": "postalcode"
  },
  "geometry": {"coordinates":[-0.272084,53.921805],"type":"Point"}
}
