{
  "type": "Feature",
  "properties": {
    "date:inception_lower": "1981-06-01",
    "date:inception_upper": "1981-06-01",
    "iso:country": "GB",
    "wof:name": "YO25 8ES",
    "wof:placetype": "postalcode"
  },
  "geometry": {"coordinates":[-0.272084,53.921805],"type":"Point"}
}
