{
  "type": "Feature",
  "properties": {
    "iso:country":"GB",
    "wof:name":"YO25 8ES",
    "wof:placetype":"postalcode"
},
  "geometry": {"coordinates":[-0.2720838112991,53.92180542606805],"type":"Point"}
}