{
  "type": "Feature",
  "properties": {
    "date:inception_lower":"1980-01-01",
    "date:inception_upper":"1980-01-31",
    "iso:country":"GB",
    "wof:name":"NR4 7EQ",
    "wof:placetype":"postalcode"
},
  "geometry": {"coordinates":[1.252596,52.621612],"type":"Point"}
}