{
  "type": "Feature",
  "properties": {
    "iso:country":"GB",
    "wof:name":"NR4 7EQ",
    "wof:placetype":"postalcode"
},
  "geometry": {"coordinates":[1.25259571653323,52.62161239430009],"type":"Point"}
}