{
  "type": "Feature",
  "properties": {
    "iso:country": "GB",
    "wof:name": "NR4 7EQ",
    "wof:placetype": "postalcode"
  },
  "geometry": {"coordinates":[1.252596,52.621612],"type":"Point"}
}
