{
  "type": "Feature",
  "properties": {
    "date:inception_lower": "2020-11-01",
    "date:inception_upper": "2020-11-01",
    "iso:country": "GB",
    "wof:name": "NN2 8GN",
    "wof:placetype": "postalcode"
  },
  "geometry": {"coordinates":[-0.917526,52.277578],"type":"Point"}
}
