{
  "type": "Feature",
  "properties": {
    "iso:country":"GB",
    "wof:name":"EN2 8DJ",
    "wof:placetype":"postalcode"
},
  "geometry": {"coordinates":[-0.09256437523011,51.65627721409703],"type":"Point"}
}