{
  "type": "Feature",
  "properties": {
    "iso:country":"GB",
    "wof:name":"PA4 0UN",
    "wof:placetype":"postalcode"
},
  "geometry": {"coordinates":[-4.38018136934684,55.87307406841267],"type":"Point"}
}