{
  "type": "Feature",
  "properties": {
    "date:inception_lower": "2020-07-01",
    "date:inception_upper": "2020-07-01",
    "iso:country": "GB",
    "wof:name": "SS2 6FL",
    "wof:placetype": "postalcode"
  },
  "geometry": {"coordinates":[0.709153,51.543018],"type":"Point"}
}
