{
  "type": "Feature",
  "properties": {
    "date:inception_lower": "2020-04-01",
    "date:inception_upper": "2020-04-01",
    "iso:country": "GB",
    "wof:name": "FY5 3UP",
    "wof:placetype": "postalcode"
  },
  "geometry": {"coordinates":[-3.018288,53.866777],"type":"Point"}
}
