{
  "type": "Feature",
  "properties": {
    "date:inception_lower": "1980-01-01",
    "date:inception_upper": "1980-01-01",
    "iso:country": "GB",
    "wof:name": "NE29 0RG",
    "wof:placetype": "postalcode"
  },
  "geometry": {"coordinates":[-1.45919,55.011348],"type":"Point"}
}
