{
  "type": "Feature",
  "properties": {
    "iso:country":"GB",
    "wof:name":"NE29 0RG",
    "wof:placetype":"postalcode"
},
  "geometry": {"coordinates":[-1.4591896465504,55.01134801067779],"type":"Point"}
}