{
  "type": "Feature",
  "properties": {
    "iso:country":"GB",
    "wof:name":"M25 2QJ",
    "wof:placetype":"postalcode"
},
  "geometry": {"coordinates":[-2.27235724364825,53.53808810429142],"type":"Point"}
}