{
  "type": "Feature",
  "properties": {
    "iso:country": "GB",
    "wof:name": "YO51 9BB",
    "wof:placetype": "postalcode"
  },
  "geometry": {"coordinates":[-1.39867,54.095162],"type":"Point"}
}
