{
  "type": "Feature",
  "properties": {
    "iso:country":"GB",
    "wof:name":"YO51 9BB",
    "wof:placetype":"postalcode"
},
  "geometry": {"coordinates":[-1.39863327729292,54.09514661687133],"type":"Point"}
}