{
  "type": "Feature",
  "properties": {
    "date:inception_lower":"1998-06-01",
    "date:inception_upper":"1998-06-30",
    "iso:country":"GB",
    "wof:name":"YO51 9BB",
    "wof:placetype":"postalcode"
},
  "geometry": {"coordinates":[-1.39867,54.095162],"type":"Point"}
}