{
  "type": "Feature",
  "properties": {
    "iso:country":"GB",
    "wof:name":"G21 3EL",
    "wof:placetype":"postalcode"
},
  "geometry": {"coordinates":[-4.20105968297944,55.88633991253087],"type":"Point"}
}