{
  "type": "Feature",
  "properties": {
    "date:inception_lower": "2007-09-01",
    "date:inception_upper": "2007-09-01",
    "iso:country": "GB",
    "wof:name": "NR9 5HY",
    "wof:placetype": "postalcode"
  },
  "geometry": {"coordinates":[1.148968,52.638712],"type":"Point"}
}
