{
  "type": "Feature",
  "properties": {
    "iso:country":"GB",
    "wof:name":"TN10 4DJ",
    "wof:placetype":"postalcode"
},
  "geometry": {"coordinates":[0.29497959221231,51.21397325232814],"type":"Point"}
}