{
  "type": "Feature",
  "properties": {
    "iso:country":"GB",
    "wof:name":"CV6 1LW",
    "wof:placetype":"postalcode"
},
  "geometry": {"coordinates":[-1.52238911399401,52.41778581467984],"type":"Point"}
}