{
  "type": "Feature",
  "properties": {
    "iso:country":"GB",
    "wof:name":"BH21 4JR",
    "wof:placetype":"postalcode"
},
  "geometry": {"coordinates":[-1.96596888275393,50.85156840201986],"type":"Point"}
}