{
  "type": "Feature",
  "properties": {
    "iso:country": "GB",
    "wof:name": "BH21 4JR",
    "wof:placetype": "postalcode"
  },
  "geometry": {"coordinates":[-1.965969,50.851568],"type":"Point"}
}
