{
  "type": "Feature",
  "properties": {
    "iso:country":"GB",
    "wof:name":"B30 1SG",
    "wof:placetype":"postalcode"
},
  "geometry": {"coordinates":[-1.95110408410168,52.42435808821777],"type":"Point"}
}