{
  "type": "Feature",
  "properties": {
    "iso:country": "GB",
    "wof:name": "CA5 7DQ",
    "wof:placetype": "postalcode"
  },
  "geometry": {"coordinates":[-2.990753,54.772941],"type":"Point"}
}
