{
  "type": "Feature",
  "properties": {
    "date:inception_lower": "1980-01-01",
    "date:inception_upper": "1980-01-01",
    "iso:country": "GB",
    "wof:name": "CA5 7DQ",
    "wof:placetype": "postalcode"
  },
  "geometry": {"coordinates":[-2.990673,54.772843],"type":"Point"}
}
