{
  "type": "Feature",
  "properties": {
    "iso:country":"GB",
    "wof:name":"CA5 7DQ",
    "wof:placetype":"postalcode"
},
  "geometry": {"coordinates":[-2.99066847532306,54.7728357572535],"type":"Point"}
}