{
  "type": "Feature",
  "properties": {
    "iso:country":"GB",
    "wof:name":"LS9 6LT",
    "wof:placetype":"postalcode"
},
  "geometry": {"coordinates":[-1.50370193173286,53.80548050906084],"type":"Point"}
}