{
  "type": "Feature",
  "properties": {
    "iso:country":"GB",
    "wof:name":"KA2 9BW",
    "wof:placetype":"postalcode"
},
  "geometry": {"coordinates":[-4.598287570103,55.58211756353334],"type":"Point"}
}