{
  "type": "Feature",
  "properties": {
    "date:inception_lower": "1999-06-01",
    "date:inception_upper": "1999-06-01",
    "iso:country": "GB",
    "wof:name": "CH41 8AJ",
    "wof:placetype": "postalcode"
  },
  "geometry": {"coordinates":[-3.042751,53.397839],"type":"Point"}
}
