{
  "type": "Feature",
  "properties": {
    "iso:country":"GB",
    "wof:name":"TQ7 4BX",
    "wof:placetype":"postalcode"
},
  "geometry": {"coordinates":[-3.79946940463138,50.32461003170131],"type":"Point"}
}