{
  "type": "Feature",
  "properties": {
    "date:inception_lower": "2014-11-01",
    "date:inception_upper": "2014-11-01",
    "iso:country": "GB",
    "wof:name": "TQ7 4BX",
    "wof:placetype": "postalcode"
  },
  "geometry": {"coordinates":[-3.799469,50.32461],"type":"Point"}
}
