{
  "type": "Feature",
  "properties": {
    "date:inception_lower": "1990-09-01",
    "date:inception_upper": "1990-09-01",
    "iso:country": "GB",
    "wof:name": "KA2 0LN",
    "wof:placetype": "postalcode"
  },
  "geometry": {"coordinates":[-4.521595,55.600411],"type":"Point"}
}
