{
  "type": "Feature",
  "properties": {
    "iso:country": "GB",
    "wof:name": "KA2 0LN",
    "wof:placetype": "postalcode"
  },
  "geometry": {"coordinates":[-4.521595,55.600411],"type":"Point"}
}
