{
  "type": "Feature",
  "properties": {
    "iso:country":"GB",
    "wof:name":"CV6 5QF",
    "wof:placetype":"postalcode"
},
  "geometry": {"coordinates":[-1.50246279390077,52.43374208139556],"type":"Point"}
}