{
  "type": "Feature",
  "properties": {
    "date:inception_lower": "1999-06-01",
    "date:inception_upper": "1999-06-01",
    "iso:country": "GB",
    "wof:name": "NP22 5LW",
    "wof:placetype": "postalcode"
  },
  "geometry": {"coordinates":[-3.289354,51.758754],"type":"Point"}
}
