{
  "type": "Feature",
  "properties": {
    "iso:country": "GB",
    "wof:name": "NE22 5AP",
    "wof:placetype": "postalcode"
  },
  "geometry": {"coordinates":[-1.585455,55.129786],"type":"Point"}
}
