{
  "type": "Feature",
  "properties": {
    "iso:country":"GB",
    "wof:name":"NE22 5AP",
    "wof:placetype":"postalcode"
},
  "geometry": {"coordinates":[-1.58545488761697,55.12978632289058],"type":"Point"}
}