{
  "type": "Feature",
  "properties": {
    "date:inception_lower":"1980-01-01",
    "date:inception_upper":"1980-01-31",
    "iso:country":"GB",
    "wof:name":"NE22 5AP",
    "wof:placetype":"postalcode"
},
  "geometry": {"coordinates":[-1.585455,55.129786],"type":"Point"}
}