{
  "type": "Feature",
  "properties": {
    "iso:country":"GB",
    "wof:name":"TA19 9FE",
    "wof:placetype":"postalcode"
},
  "geometry": {"coordinates":[-2.91980143415411,50.9250135221256],"type":"Point"}
}