{
  "type": "Feature",
  "properties": {
    "date:inception_lower":"2012-08-01",
    "date:inception_upper":"2012-08-31",
    "iso:country":"GB",
    "wof:name":"TA19 9FE",
    "wof:placetype":"postalcode"
},
  "geometry": {"coordinates":[-2.919807,50.925005],"type":"Point"}
}