{
  "type": "Feature",
  "properties": {
    "iso:country": "GB",
    "wof:name": "TA19 9FE",
    "wof:placetype": "postalcode"
  },
  "geometry": {"coordinates":[-2.919807,50.925005],"type":"Point"}
}
