{
  "type": "Feature",
  "properties": {
    "iso:country": "GB",
    "wof:name": "TW9 4FF",
    "wof:placetype": "postalcode"
  },
  "geometry": {"coordinates":[-0.278441,51.479592],"type":"Point"}
}
