{
  "type": "Feature",
  "properties": {
    "iso:country":"GB",
    "wof:name":"DL14 8SW",
    "wof:placetype":"postalcode"
},
  "geometry": {"coordinates":[-1.65442665957212,54.6451772398979],"type":"Point"}
}