{
  "type": "Feature",
  "properties": {
    "iso:country": "GB",
    "wof:name": "DL14 8SW",
    "wof:placetype": "postalcode"
  },
  "geometry": {"coordinates":[-1.654427,54.645177],"type":"Point"}
}
