{
  "type": "Feature",
  "properties": {
    "date:inception_lower": "1995-12-01",
    "date:inception_upper": "1995-12-01",
    "iso:country": "GB",
    "wof:name": "SA16 0LS",
    "wof:placetype": "postalcode"
  },
  "geometry": {"coordinates":[-4.245981,51.682885],"type":"Point"}
}
