{
  "type": "Feature",
  "properties": {
    "iso:country": "GB",
    "wof:name": "SA16 0LS",
    "wof:placetype": "postalcode"
  },
  "geometry": {"coordinates":[-4.245981,51.682885],"type":"Point"}
}
