{
  "type": "Feature",
  "properties": {
    "date:inception_lower": "1980-01-01",
    "date:inception_upper": "1980-01-01",
    "iso:country": "GB",
    "wof:name": "NR23 1DN",
    "wof:placetype": "postalcode"
  },
  "geometry": {"coordinates":[0.848575,52.955257],"type":"Point"}
}
