{
  "type": "Feature",
  "properties": {
    "iso:country":"GB",
    "wof:name":"E17 5LG",
    "wof:placetype":"postalcode"
},
  "geometry": {"coordinates":[-0.02305392082726,51.59143364950302],"type":"Point"}
}