{
  "type": "Feature",
  "properties": {
    "date:inception_lower": "1998-06-01",
    "date:inception_upper": "1998-06-01",
    "iso:country": "GB",
    "wof:name": "YO32 9YE",
    "wof:placetype": "postalcode"
  },
  "geometry": {"coordinates":[-1.054611,53.995597],"type":"Point"}
}
