{
  "type": "Feature",
  "properties": {
    "iso:country":"GB",
    "wof:name":"YO32 9YE",
    "wof:placetype":"postalcode"
},
  "geometry": {"coordinates":[-1.05461064205947,53.99559668188601],"type":"Point"}
}