{
  "type": "Feature",
  "properties": {
    "date:inception_lower": "1998-06-01",
    "date:inception_upper": "1998-06-01",
    "iso:country": "GB",
    "wof:name": "YO32 9YE",
    "wof:placetype": "postalcode"
  },
  "geometry": {"coordinates":[-1.054221,53.99571],"type":"Point"}
}
