{
  "type": "Feature",
  "properties": {
    "date:inception_lower":"1980-01-01",
    "date:inception_upper":"1980-01-31",
    "iso:country":"GB",
    "wof:name":"PO7 6LB",
    "wof:placetype":"postalcode"
},
  "geometry": {"coordinates":[-1.075156,50.901453],"type":"Point"}
}