{
  "type": "Feature",
  "properties": {
    "iso:country": "GB",
    "wof:name": "PO7 6LB",
    "wof:placetype": "postalcode"
  },
  "geometry": {"coordinates":[-1.075156,50.901453],"type":"Point"}
}
