{
  "type": "Feature",
  "properties": {
    "iso:country":"GB",
    "wof:name":"TN9 1XG",
    "wof:placetype":"postalcode"
},
  "geometry": {"coordinates":[0.25873583180079,51.19637705888284],"type":"Point"}
}