{
  "type": "Feature",
  "properties": {
    "date:inception_lower": "1999-06-01",
    "date:inception_upper": "1999-06-01",
    "iso:country": "GB",
    "wof:name": "CH5 4QR",
    "wof:placetype": "postalcode"
  },
  "geometry": {"coordinates":[-3.076976,53.209806],"type":"Point"}
}
