{
  "type": "Feature",
  "properties": {
    "iso:country": "GB",
    "wof:name": "CH5 4QR",
    "wof:placetype": "postalcode"
  },
  "geometry": {"coordinates":[-3.076976,53.209806],"type":"Point"}
}
