{
  "type": "Feature",
  "properties": {
    "iso:country":"GB",
    "wof:name":"RH11 8UW",
    "wof:placetype":"postalcode"
},
  "geometry": {"coordinates":[-0.21824929496144,51.10099767799267],"type":"Point"}
}