{
  "type": "Feature",
  "properties": {
    "iso:country": "GB",
    "wof:name": "RH11 8UW",
    "wof:placetype": "postalcode"
  },
  "geometry": {"coordinates":[-0.218231,51.10111],"type":"Point"}
}
