{
  "type": "Feature",
  "properties": {
    "iso:country": "GB",
    "wof:name": "PO36 0AS",
    "wof:placetype": "postalcode"
  },
  "geometry": {"coordinates":[-1.142243,50.679358],"type":"Point"}
}
