{
  "type": "Feature",
  "properties": {
    "date:inception_lower":"1980-01-01",
    "date:inception_upper":"1980-01-31",
    "iso:country":"GB",
    "wof:name":"PO36 0AS",
    "wof:placetype":"postalcode"
},
  "geometry": {"coordinates":[-1.142243,50.679358],"type":"Point"}
}