{
  "type": "Feature",
  "properties": {
    "iso:country":"GB",
    "wof:name":"PO36 0AS",
    "wof:placetype":"postalcode"
},
  "geometry": {"coordinates":[-1.14224273029171,50.67935840137741],"type":"Point"}
}