{
  "type": "Feature",
  "properties": {
    "date:inception_lower": "1990-07-01",
    "date:inception_upper": "1990-07-01",
    "iso:country": "GB",
    "wof:name": "OX10 6DJ",
    "wof:placetype": "postalcode"
  },
  "geometry": {"coordinates":[-1.078685,51.616334],"type":"Point"}
}
