{
  "type": "Feature",
  "properties": {
    "iso:country":"GB",
    "wof:name":"OX10 6DJ",
    "wof:placetype":"postalcode"
},
  "geometry": {"coordinates":[-1.07868464565805,51.6163340478324],"type":"Point"}
}