{
  "type": "Feature",
  "properties": {
    "date:inception_lower": "1998-06-01",
    "date:inception_upper": "1998-06-01",
    "iso:country": "GB",
    "wof:name": "N22 7UD",
    "wof:placetype": "postalcode"
  },
  "geometry": {"coordinates":[-0.132659,51.59741],"type":"Point"}
}
