{
  "type": "Feature",
  "properties": {
    "iso:country":"GB",
    "wof:name":"N22 7UD",
    "wof:placetype":"postalcode"
},
  "geometry": {"coordinates":[-0.1326592125177,51.59741022913038],"type":"Point"}
}