{
  "type": "Feature",
  "properties": {
    "iso:country":"GB",
    "wof:name":"BA12 6EJ",
    "wof:placetype":"postalcode"
},
  "geometry": {"coordinates":[-2.26726367478895,51.09383395125604],"type":"Point"}
}