{
  "type": "Feature",
  "properties": {
    "iso:country": "GB",
    "wof:name": "OX20 1BQ",
    "wof:placetype": "postalcode"
  },
  "geometry": {"coordinates":[-1.417255,51.897183],"type":"Point"}
}
