{
  "type": "Feature",
  "properties": {
    "iso:country":"GB",
    "wof:name":"OX20 1BQ",
    "wof:placetype":"postalcode"
},
  "geometry": {"coordinates":[-1.41727189857111,51.89717448230349],"type":"Point"}
}