{
  "type": "Feature",
  "properties": {
    "iso:country":"GB",
    "wof:name":"HU3 2TX",
    "wof:placetype":"postalcode"
},
  "geometry": {"coordinates":[-0.36315665409679,53.74005600196426],"type":"Point"}
}