{
  "type": "Feature",
  "properties": {
    "iso:country": "GB",
    "wof:name": "HU3 2TX",
    "wof:placetype": "postalcode"
  },
  "geometry": {"coordinates":[-0.36272,53.740161],"type":"Point"}
}
