{
  "type": "Feature",
  "properties": {
    "iso:country": "GB",
    "wof:name": "WV12 4FA",
    "wof:placetype": "postalcode"
  },
  "geometry": {"coordinates":[-2.038585,52.595474],"type":"Point"}
}
