{
  "type": "Feature",
  "properties": {
    "date:inception_lower": "2019-08-01",
    "date:inception_upper": "2019-08-01",
    "iso:country": "GB",
    "wof:name": "WV12 4FA",
    "wof:placetype": "postalcode"
  },
  "geometry": {"coordinates":[-2.038556,52.595429],"type":"Point"}
}
