{
  "type": "Feature",
  "properties": {
    "iso:country":"GB",
    "wof:name":"M33 4JJ",
    "wof:placetype":"postalcode"
},
  "geometry": {"coordinates":[-2.36253298288869,53.40978941782301],"type":"Point"}
}