{
  "type": "Feature",
  "properties": {
    "date:inception_lower": "1980-01-01",
    "date:inception_upper": "1980-01-01",
    "iso:country": "GB",
    "wof:name": "GU9 9QF",
    "wof:placetype": "postalcode"
  },
  "geometry": {"coordinates":[-0.789726,51.219896],"type":"Point"}
}
