{
  "type": "Feature",
  "properties": {
    "iso:country":"GB",
    "wof:name":"GU9 9QF",
    "wof:placetype":"postalcode"
},
  "geometry": {"coordinates":[-0.78972651366299,51.21989620444335],"type":"Point"}
}