{
  "type": "Feature",
  "properties": {
    "iso:country":"GB",
    "wof:name":"LL13 9NA",
    "wof:placetype":"postalcode"
},
  "geometry": {"coordinates":[-2.96798854385679,53.04720747433107],"type":"Point"}
}