{
  "type": "Feature",
  "properties": {
    "date:inception_lower": "1980-01-01",
    "date:inception_upper": "1980-01-01",
    "iso:country": "GB",
    "wof:name": "LL13 9NA",
    "wof:placetype": "postalcode"
  },
  "geometry": {"coordinates":[-2.967988,53.047207],"type":"Point"}
}
