{
  "type": "Feature",
  "properties": {
    "iso:country":"GB",
    "wof:name":"TS5 8TU",
    "wof:placetype":"postalcode"
},
  "geometry": {"coordinates":[-1.26205648637527,54.53188536923523],"type":"Point"}
}