{
  "type": "Feature",
  "properties": {
    "iso:country":"GB",
    "wof:name":"LA3 3AD",
    "wof:placetype":"postalcode"
},
  "geometry": {"coordinates":[-2.83404454772082,54.06452731027093],"type":"Point"}
}