{
  "type": "Feature",
  "properties": {
    "iso:country":"GB",
    "wof:name":"SW16 3LX",
    "wof:placetype":"postalcode"
},
  "geometry": {"coordinates":[-0.11917827628126,51.41462840028635],"type":"Point"}
}