{
  "type": "Feature",
  "properties": {
    "date:inception_lower": "1980-01-01",
    "date:inception_upper": "1980-01-01",
    "iso:country": "GB",
    "wof:name": "SW16 3LX",
    "wof:placetype": "postalcode"
  },
  "geometry": {"coordinates":[-0.118648,51.414575],"type":"Point"}
}
