{
  "type": "Feature",
  "properties": {
    "iso:country":"GB",
    "wof:name":"LA6 1HY",
    "wof:placetype":"postalcode"
},
  "geometry": {"coordinates":[-2.72273922453287,54.18517947621422],"type":"Point"}
}