{
  "type": "Feature",
  "properties": {
    "iso:country": "GB",
    "wof:name": "PA16 7DJ",
    "wof:placetype": "postalcode"
  },
  "geometry": {"coordinates":[-4.793742,55.944098],"type":"Point"}
}
