{
  "type": "Feature",
  "properties": {
    "iso:country":"GB",
    "wof:name":"SE13 5QQ",
    "wof:placetype":"postalcode"
},
  "geometry": {"coordinates":[0.00030550752834,51.45723604421154],"type":"Point"}
}