{
  "type": "Feature",
  "properties": {
    "iso:country": "GB",
    "wof:name": "SE13 5QQ",
    "wof:placetype": "postalcode"
  },
  "geometry": {"coordinates":[0.000306,51.457236],"type":"Point"}
}
