{
  "type": "Feature",
  "properties": {
    "date:inception_lower": "1980-01-01",
    "date:inception_upper": "1980-01-01",
    "iso:country": "GB",
    "wof:name": "SE13 5QQ",
    "wof:placetype": "postalcode"
  },
  "geometry": {"coordinates":[0.000306,51.457236],"type":"Point"}
}
