{
  "type": "Feature",
  "properties": {
    "iso:country":"GB",
    "wof:name":"G74 3HR",
    "wof:placetype":"postalcode"
},
  "geometry": {"coordinates":[-4.15144620011842,55.77253981326586],"type":"Point"}
}