{
  "type": "Feature",
  "properties": {
    "iso:country":"GB",
    "wof:name":"EX39 4NL",
    "wof:placetype":"postalcode"
},
  "geometry": {"coordinates":[-4.18268255523736,51.03682854392496],"type":"Point"}
}