{
  "type": "Feature",
  "properties": {
    "iso:country": "GB",
    "wof:name": "EX39 4NL",
    "wof:placetype": "postalcode"
  },
  "geometry": {"coordinates":[-4.182683,51.036829],"type":"Point"}
}
