{
  "type": "Feature",
  "properties": {
    "date:inception_lower": "1980-01-01",
    "date:inception_upper": "1980-01-01",
    "iso:country": "GB",
    "wof:name": "NE11 0ST",
    "wof:placetype": "postalcode"
  },
  "geometry": {"coordinates":[-1.616304,54.926512],"type":"Point"}
}
