{
  "type": "Feature",
  "properties": {
    "iso:country":"GB",
    "wof:name":"PR6 0JE",
    "wof:placetype":"postalcode"
},
  "geometry": {"coordinates":[-2.62091266388583,53.66199412755248],"type":"Point"}
}