{
  "type": "Feature",
  "properties": {
    "iso:country":"GB",
    "wof:name":"NG10 4GS",
    "wof:placetype":"postalcode"
},
  "geometry": {"coordinates":[-1.28796245817288,52.91244269623287],"type":"Point"}
}