{
  "type": "Feature",
  "properties": {
    "iso:country":"GB",
    "wof:name":"IV12 4RZ",
    "wof:placetype":"postalcode"
},
  "geometry": {"coordinates":[-3.87789630740883,57.58106411659975],"type":"Point"}
}