{
  "type": "Feature",
  "properties": {
    "iso:country":"GB",
    "wof:name":"GU9 8UF",
    "wof:placetype":"postalcode"
},
  "geometry": {"coordinates":[-0.81823889465624,51.20244570562518],"type":"Point"}
}