{
  "type": "Feature",
  "properties": {
    "iso:country": "GB",
    "wof:name": "BB12 6EG",
    "wof:placetype": "postalcode"
  },
  "geometry": {"coordinates":[-2.273965,53.791165],"type":"Point"}
}
