{
  "type": "Feature",
  "properties": {
    "date:inception_lower": "1980-01-01",
    "date:inception_upper": "1980-01-01",
    "iso:country": "GB",
    "wof:name": "NR14 7EE",
    "wof:placetype": "postalcode"
  },
  "geometry": {"coordinates":[1.389861,52.602012],"type":"Point"}
}
