{
  "type": "Feature",
  "properties": {
    "iso:country": "GB",
    "wof:name": "NR14 7EE",
    "wof:placetype": "postalcode"
  },
  "geometry": {"coordinates":[1.389861,52.602012],"type":"Point"}
}
