{
  "type": "Feature",
  "properties": {
    "iso:country":"GB",
    "wof:name":"NR14 7EE",
    "wof:placetype":"postalcode"
},
  "geometry": {"coordinates":[1.38986122519613,52.602012061159],"type":"Point"}
}