{
  "type": "Feature",
  "properties": {
    "iso:country":"GB",
    "wof:name":"CA1 3AQ",
    "wof:placetype":"postalcode"
},
  "geometry": {"coordinates":[-2.89488339738015,54.88351558183444],"type":"Point"}
}