{
  "type": "Feature",
  "properties": {
    "date:inception_lower": "2006-07-01",
    "date:inception_upper": "2006-07-01",
    "iso:country": "GB",
    "wof:name": "CA1 3AQ",
    "wof:placetype": "postalcode"
  },
  "geometry": {"coordinates":[-2.894883,54.883516],"type":"Point"}
}
