{
  "type": "Feature",
  "properties": {
    "iso:country":"GB",
    "wof:name":"EX14 4AE",
    "wof:placetype":"postalcode"
},
  "geometry": {"coordinates":[-3.22330414212673,50.86143599458985],"type":"Point"}
}