{
  "type": "Feature",
  "properties": {
    "date:inception_lower":"2015-08-01",
    "date:inception_upper":"2015-08-31",
    "iso:country":"GB",
    "wof:name":"EX14 4AE",
    "wof:placetype":"postalcode"
},
  "geometry": {"coordinates":[-3.223223,50.861186],"type":"Point"}
}