{
  "type": "Feature",
  "properties": {
    "date:inception_lower": "2004-07-01",
    "date:inception_upper": "2004-07-01",
    "iso:country": "GB",
    "wof:name": "RG30 2DZ",
    "wof:placetype": "postalcode"
  },
  "geometry": {"coordinates":[-1.002644,51.448548],"type":"Point"}
}
