{
  "type": "Feature",
  "properties": {
    "iso:country":"GB",
    "wof:name":"MK3 7BB",
    "wof:placetype":"postalcode"
},
  "geometry": {"coordinates":[-0.758521704017,51.99836511281917],"type":"Point"}
}