{
  "type": "Feature",
  "properties": {
    "iso:country": "GB",
    "wof:name": "GL51 0BG",
    "wof:placetype": "postalcode"
  },
  "geometry": {"coordinates":[-2.10746,51.912583],"type":"Point"}
}
