{
  "type": "Feature",
  "properties": {
    "iso:country":"GB",
    "wof:name":"NG18 3BP",
    "wof:placetype":"postalcode"
},
  "geometry": {"coordinates":[-1.17186202918049,53.14241188698117],"type":"Point"}
}