{
  "type": "Feature",
  "properties": {
    "iso:country": "GB",
    "wof:name": "WF1 3EB",
    "wof:placetype": "postalcode"
  },
  "geometry": {"coordinates":[-1.493077,53.709317],"type":"Point"}
}
