{
  "type": "Feature",
  "properties": {
    "date:inception_lower": "1980-01-01",
    "date:inception_upper": "1980-01-01",
    "iso:country": "GB",
    "wof:name": "WF1 3EB",
    "wof:placetype": "postalcode"
  },
  "geometry": {"coordinates":[-1.493321,53.709478],"type":"Point"}
}
