{
  "type": "Feature",
  "properties": {
    "iso:country":"GB",
    "wof:name":"LE67 8HX",
    "wof:placetype":"postalcode"
},
  "geometry": {"coordinates":[-1.38730843220671,52.76501938102697],"type":"Point"}
}