{
  "type": "Feature",
  "properties": {
    "date:inception_lower":"2003-03-01",
    "date:inception_upper":"2003-03-31",
    "iso:country":"GB",
    "wof:name":"LE67 8HX",
    "wof:placetype":"postalcode"
},
  "geometry": {"coordinates":[-1.387308,52.765019],"type":"Point"}
}