{
  "type": "Feature",
  "properties": {
    "iso:country": "GB",
    "wof:name": "SO32 1SU",
    "wof:placetype": "postalcode"
  },
  "geometry": {"coordinates":[-1.180895,51.006466],"type":"Point"}
}
