{
  "type": "Feature",
  "properties": {
    "date:inception_lower":"1994-12-01",
    "date:inception_upper":"1994-12-31",
    "iso:country":"GB",
    "wof:name":"SO32 1SU",
    "wof:placetype":"postalcode"
},
  "geometry": {"coordinates":[-1.180895,51.006466],"type":"Point"}
}