{
  "type": "Feature",
  "properties": {
    "date:inception_lower":"1984-10-01",
    "date:inception_upper":"1984-10-31",
    "iso:country":"GB",
    "wof:name":"NR18 9QY",
    "wof:placetype":"postalcode"
},
  "geometry": {"coordinates":[1.143282,52.562386],"type":"Point"}
}