{
  "type": "Feature",
  "properties": {
    "iso:country": "GB",
    "wof:name": "NR18 9QY",
    "wof:placetype": "postalcode"
  },
  "geometry": {"coordinates":[1.143282,52.562386],"type":"Point"}
}
