{
  "type": "Feature",
  "properties": {
    "iso:country":"GB",
    "wof:name":"NR18 9QY",
    "wof:placetype":"postalcode"
},
  "geometry": {"coordinates":[1.14328202721592,52.56238594210993],"type":"Point"}
}