{
  "type": "Feature",
  "properties": {
    "iso:country": "GB",
    "wof:name": "SA39 9LZ",
    "wof:placetype": "postalcode"
  },
  "geometry": {"coordinates":[-4.252512,52.0491],"type":"Point"}
}
