{
  "type": "Feature",
  "properties": {
    "date:inception_lower": "1980-01-01",
    "date:inception_upper": "1980-01-01",
    "iso:country": "GB",
    "wof:name": "SA39 9LZ",
    "wof:placetype": "postalcode"
  },
  "geometry": {"coordinates":[-4.252512,52.0491],"type":"Point"}
}
