{
  "type": "Feature",
  "properties": {
    "iso:country":"GB",
    "wof:name":"SA39 9LZ",
    "wof:placetype":"postalcode"
},
  "geometry": {"coordinates":[-4.25251249948568,52.04910018712246],"type":"Point"}
}