{
  "type": "Feature",
  "properties": {
    "iso:country": "GB",
    "wof:name": "L39 3BD",
    "wof:placetype": "postalcode"
  },
  "geometry": {"coordinates":[-2.894922,53.570841],"type":"Point"}
}
