{
  "type": "Feature",
  "properties": {
    "date:inception_lower": "1984-10-01",
    "date:inception_upper": "1984-10-01",
    "iso:country": "GB",
    "wof:name": "L39 3BD",
    "wof:placetype": "postalcode"
  },
  "geometry": {"coordinates":[-2.894922,53.570841],"type":"Point"}
}
