{
  "type": "Feature",
  "properties": {
    "iso:country":"GB",
    "wof:name":"EC4V 5EX",
    "wof:placetype":"postalcode"
},
  "geometry": {"coordinates":[-0.1027403660163,51.51286857981195],"type":"Point"}
}