{
  "type": "Feature",
  "properties": {
    "date:inception_lower": "1980-01-01",
    "date:inception_upper": "1980-01-01",
    "iso:country": "GB",
    "wof:name": "EC4V 5EX",
    "wof:placetype": "postalcode"
  },
  "geometry": {"coordinates":[-0.10274,51.512869],"type":"Point"}
}
