{
  "type": "Feature",
  "properties": {
    "iso:country": "GB",
    "wof:name": "TW13 7AW",
    "wof:placetype": "postalcode"
  },
  "geometry": {"coordinates":[-0.412361,51.440296],"type":"Point"}
}
