{
  "type": "Feature",
  "properties": {
    "iso:country": "GB",
    "wof:name": "DT2 9JU",
    "wof:placetype": "postalcode"
  },
  "geometry": {"coordinates":[-2.50289,50.700419],"type":"Point"}
}
