{
  "type": "Feature",
  "properties": {
    "date:inception_lower":"1980-01-01",
    "date:inception_upper":"1980-01-31",
    "iso:country":"GB",
    "wof:name":"DT2 9JU",
    "wof:placetype":"postalcode"
},
  "geometry": {"coordinates":[-2.50289,50.700419],"type":"Point"}
}