{
  "type": "Feature",
  "properties": {
    "iso:country": "GB",
    "wof:name": "SP1 3LE",
    "wof:placetype": "postalcode"
  },
  "geometry": {"coordinates":[-1.81006,51.087659],"type":"Point"}
}
