{
  "type": "Feature",
  "properties": {
    "iso:country":"GB",
    "wof:name":"SP1 3LE",
    "wof:placetype":"postalcode"
},
  "geometry": {"coordinates":[-1.81014159823844,51.08771880278389],"type":"Point"}
}