{
  "type": "Feature",
  "properties": {
    "iso:country": "GB",
    "wof:name": "GL56 0AL",
    "wof:placetype": "postalcode"
  },
  "geometry": {"coordinates":[-1.703658,51.990013],"type":"Point"}
}
