{
  "type": "Feature",
  "properties": {
    "iso:country": "GB",
    "wof:name": "YO16 4PG",
    "wof:placetype": "postalcode"
  },
  "geometry": {"coordinates":[-0.203363,54.084244],"type":"Point"}
}
