{
  "type": "Feature",
  "properties": {
    "iso:country":"GB",
    "wof:name":"LN7 6LQ",
    "wof:placetype":"postalcode"
},
  "geometry": {"coordinates":[-0.42197285940583,53.52362050865391],"type":"Point"}
}