{
  "type": "Feature",
  "properties": {
    "date:inception_lower": "1981-06-01",
    "date:inception_upper": "1981-06-01",
    "iso:country": "GB",
    "wof:name": "LN7 6LQ",
    "wof:placetype": "postalcode"
  },
  "geometry": {"coordinates":[-0.421973,53.523621],"type":"Point"}
}
