{
  "type": "Feature",
  "properties": {
    "iso:country": "GB",
    "wof:name": "LN7 6LQ",
    "wof:placetype": "postalcode"
  },
  "geometry": {"coordinates":[-0.421973,53.523621],"type":"Point"}
}
