{
  "type": "Feature",
  "properties": {
    "iso:country":"GB",
    "wof:name":"TQ1 3EA",
    "wof:placetype":"postalcode"
},
  "geometry": {"coordinates":[-3.53560089175697,50.47170242379794],"type":"Point"}
}