{
  "type": "Feature",
  "properties": {
    "iso:country":"GB",
    "wof:name":"SE12 9UA",
    "wof:placetype":"postalcode"
},
  "geometry": {"coordinates":[0.028267639254,51.43240306723963],"type":"Point"}
}