{
  "type": "Feature",
  "properties": {
    "iso:country":"GB",
    "wof:name":"IP3 9ED",
    "wof:placetype":"postalcode"
},
  "geometry": {"coordinates":[1.18914746433944,52.0429480685069],"type":"Point"}
}