{
  "type": "Feature",
  "properties": {
    "date:inception_lower": "1980-01-01",
    "date:inception_upper": "1980-01-01",
    "iso:country": "GB",
    "wof:name": "PO15 5BZ",
    "wof:placetype": "postalcode"
  },
  "geometry": {"coordinates":[-1.209312,50.855524],"type":"Point"}
}
