{
  "type": "Feature",
  "properties": {
    "iso:country": "GB",
    "wof:name": "PO15 5BZ",
    "wof:placetype": "postalcode"
  },
  "geometry": {"coordinates":[-1.209312,50.855524],"type":"Point"}
}
