{
  "type": "Feature",
  "properties": {
    "iso:country":"GB",
    "wof:name":"GU21 3JB",
    "wof:placetype":"postalcode"
},
  "geometry": {"coordinates":[-0.58030930449629,51.31468845763502],"type":"Point"}
}