{
  "type": "Feature",
  "properties": {
    "date:inception_lower": "2008-09-01",
    "date:inception_upper": "2008-09-01",
    "iso:country": "GB",
    "wof:name": "GU15 3GP",
    "wof:placetype": "postalcode"
  },
  "geometry": {"coordinates":[-0.748806,51.337453],"type":"Point"}
}
