{
  "type": "Feature",
  "properties": {
    "iso:country": "GB",
    "wof:name": "GU15 3GP",
    "wof:placetype": "postalcode"
  },
  "geometry": {"coordinates":[-0.748806,51.337453],"type":"Point"}
}
