{
  "type": "Feature",
  "properties": {
    "iso:country":"GB",
    "wof:name":"GU15 3GP",
    "wof:placetype":"postalcode"
},
  "geometry": {"coordinates":[-0.74880605850152,51.33745349550615],"type":"Point"}
}