{
  "type": "Feature",
  "properties": {
    "iso:country":"GB",
    "wof:name":"B67 6DJ",
    "wof:placetype":"postalcode"
},
  "geometry": {"coordinates":[-1.96832181654915,52.48987399577781],"type":"Point"}
}