{
  "type": "Feature",
  "properties": {
    "date:inception_lower": "2023-10-01",
    "date:inception_upper": "2023-10-01",
    "iso:country": "GB",
    "wof:name": "S72 8GP",
    "wof:placetype": "postalcode"
  },
  "geometry": {"coordinates":[-1.4217,53.576199],"type":"Point"}
}
