{
  "type": "Feature",
  "properties": {
    "iso:country": "GB",
    "wof:name": "DY5 2RH",
    "wof:placetype": "postalcode"
  },
  "geometry": {"coordinates":[-2.120998,52.480481],"type":"Point"}
}
