{
  "type": "Feature",
  "properties": {
    "iso:country":"GB",
    "wof:name":"DY5 2RH",
    "wof:placetype":"postalcode"
},
  "geometry": {"coordinates":[-2.12101905861387,52.48046645611577],"type":"Point"}
}