{
  "type": "Feature",
  "properties": {
    "date:inception_lower": "1991-09-01",
    "date:inception_upper": "1991-09-01",
    "iso:country": "GB",
    "wof:name": "BL8 3TA",
    "wof:placetype": "postalcode"
  },
  "geometry": {"coordinates":[-2.337613,53.602188],"type":"Point"}
}
