{
  "type": "Feature",
  "properties": {
    "iso:country":"GB",
    "wof:name":"HD3 4TT",
    "wof:placetype":"postalcode"
},
  "geometry": {"coordinates":[-1.8480348329137,53.64753711331722],"type":"Point"}
}