{
  "type": "Feature",
  "properties": {
    "iso:country":"GB",
    "wof:name":"W1T 3ET",
    "wof:placetype":"postalcode"
},
  "geometry": {"coordinates":[-0.13559198396348,51.51693844164306],"type":"Point"}
}