{
  "type": "Feature",
  "properties": {
    "iso:country":"GB",
    "wof:name":"TN33 9BG",
    "wof:placetype":"postalcode"
},
  "geometry": {"coordinates":[0.45912066690873,50.89238905155667],"type":"Point"}
}