{
  "type": "Feature",
  "properties": {
    "date:inception_lower": "1980-01-01",
    "date:inception_upper": "1980-01-01",
    "iso:country": "GB",
    "wof:name": "TN33 9BG",
    "wof:placetype": "postalcode"
  },
  "geometry": {"coordinates":[0.459121,50.892389],"type":"Point"}
}
