{
  "type": "Feature",
  "properties": {
    "iso:country":"GB",
    "wof:name":"B46 3AJ",
    "wof:placetype":"postalcode"
},
  "geometry": {"coordinates":[-1.70586307922886,52.49893472445079],"type":"Point"}
}