{
  "type": "Feature",
  "properties": {
    "iso:country": "GB",
    "wof:name": "B46 3AJ",
    "wof:placetype": "postalcode"
  },
  "geometry": {"coordinates":[-1.705863,52.498935],"type":"Point"}
}
