{
  "type": "Feature",
  "properties": {
    "iso:country":"GB",
    "wof:name":"G44 4QG",
    "wof:placetype":"postalcode"
},
  "geometry": {"coordinates":[-4.24825771056724,55.82481238598906],"type":"Point"}
}