{
  "type": "Feature",
  "properties": {
    "date:inception_lower": "2019-07-01",
    "date:inception_upper": "2019-07-01",
    "iso:country": "GB",
    "wof:name": "DY2 7AQ",
    "wof:placetype": "postalcode"
  },
  "geometry": {"coordinates":[-2.070324,52.511844],"type":"Point"}
}
