{
  "type": "Feature",
  "properties": {
    "date:inception_lower": "2018-10-01",
    "date:inception_upper": "2018-10-01",
    "iso:country": "GB",
    "wof:name": "SP11 8FH",
    "wof:placetype": "postalcode"
  },
  "geometry": {"coordinates":[-1.535821,51.213772],"type":"Point"}
}
