{
  "type": "Feature",
  "properties": {
    "iso:country":"GB",
    "wof:name":"SL1 2SQ",
    "wof:placetype":"postalcode"
},
  "geometry": {"coordinates":[-0.60796256878073,51.50589756314433],"type":"Point"}
}