{
  "type": "Feature",
  "properties": {
    "iso:country": "GB",
    "wof:name": "SY3 9PJ",
    "wof:placetype": "postalcode"
  },
  "geometry": {"coordinates":[-2.757887,52.686281],"type":"Point"}
}
