{
  "type": "Feature",
  "properties": {
    "iso:country":"GB",
    "wof:name":"KT14 6NQ",
    "wof:placetype":"postalcode"
},
  "geometry": {"coordinates":[-0.50471578603568,51.33816211624132],"type":"Point"}
}