{
  "type": "Feature",
  "properties": {
    "iso:country": "GB",
    "wof:name": "KT14 6NQ",
    "wof:placetype": "postalcode"
  },
  "geometry": {"coordinates":[-0.504716,51.338162],"type":"Point"}
}
