{
  "type": "Feature",
  "properties": {
    "date:inception_lower":"1980-01-01",
    "date:inception_upper":"1980-01-31",
    "iso:country":"GB",
    "wof:name":"KT14 6NQ",
    "wof:placetype":"postalcode"
},
  "geometry": {"coordinates":[-0.504716,51.338162],"type":"Point"}
}