{
  "type": "Feature",
  "properties": {
    "iso:country":"GB",
    "wof:name":"N17 8DN",
    "wof:placetype":"postalcode"
},
  "geometry": {"coordinates":[-0.06917812315089,51.60475505180302],"type":"Point"}
}