{
  "type": "Feature",
  "properties": {
    "iso:country":"GB",
    "wof:name":"NG5 6LB",
    "wof:placetype":"postalcode"
},
  "geometry": {"coordinates":[-1.13291287934129,53.00066049652629],"type":"Point"}
}