{
  "type": "Feature",
  "properties": {
    "date:inception_lower": "1993-08-01",
    "date:inception_upper": "1993-08-01",
    "iso:country": "GB",
    "wof:name": "SY6 6HU",
    "wof:placetype": "postalcode"
  },
  "geometry": {"coordinates":[-2.807098,52.53333],"type":"Point"}
}
