{
  "type": "Feature",
  "properties": {
    "iso:country": "GB",
    "wof:name": "SY6 6HU",
    "wof:placetype": "postalcode"
  },
  "geometry": {"coordinates":[-2.807069,52.533315],"type":"Point"}
}
