{
  "type": "Feature",
  "properties": {
    "iso:country": "GB",
    "wof:name": "LA18 5BQ",
    "wof:placetype": "postalcode"
  },
  "geometry": {"coordinates":[-3.272362,54.211986],"type":"Point"}
}
