{
  "type": "Feature",
  "properties": {
    "date:inception_lower":"1996-12-01",
    "date:inception_upper":"1996-12-31",
    "iso:country":"GB",
    "wof:name":"LA18 5BQ",
    "wof:placetype":"postalcode"
},
  "geometry": {"coordinates":[-3.272362,54.211986],"type":"Point"}
}