{
  "type": "Feature",
  "properties": {
    "iso:country":"GB",
    "wof:name":"B93 0DX",
    "wof:placetype":"postalcode"
},
  "geometry": {"coordinates":[-1.73149618814785,52.37746815017304],"type":"Point"}
}