{
  "type": "Feature",
  "properties": {
    "iso:country": "GB",
    "wof:name": "RH11 8PB",
    "wof:placetype": "postalcode"
  },
  "geometry": {"coordinates":[-0.198022,51.112064],"type":"Point"}
}
