{
  "type": "Feature",
  "properties": {
    "iso:country":"GB",
    "wof:name":"LU2 0LW",
    "wof:placetype":"postalcode"
},
  "geometry": {"coordinates":[-0.39804867643781,51.8870589607241],"type":"Point"}
}