{
  "type": "Feature",
  "properties": {
    "iso:country": "GB",
    "wof:name": "LU2 0LW",
    "wof:placetype": "postalcode"
  },
  "geometry": {"coordinates":[-0.398049,51.887059],"type":"Point"}
}
