{
  "type": "Feature",
  "properties": {
    "iso:country":"GB",
    "wof:name":"IP31 2EN",
    "wof:placetype":"postalcode"
},
  "geometry": {"coordinates":[0.83699331689881,52.29686079325651],"type":"Point"}
}