{
  "type": "Feature",
  "properties": {
    "date:inception_lower":"1980-01-01",
    "date:inception_upper":"1980-01-31",
    "iso:country":"GB",
    "wof:name":"LA7 7JU",
    "wof:placetype":"postalcode"
},
  "geometry": {"coordinates":[-2.810278,54.210722],"type":"Point"}
}