{
  "type": "Feature",
  "properties": {
    "iso:country": "GB",
    "wof:name": "LA7 7JU",
    "wof:placetype": "postalcode"
  },
  "geometry": {"coordinates":[-2.810278,54.210722],"type":"Point"}
}
