{
  "type": "Feature",
  "properties": {
    "iso:country":"GB",
    "wof:name":"LA7 7JU",
    "wof:placetype":"postalcode"
},
  "geometry": {"coordinates":[-2.81027756000076,54.21072235793107],"type":"Point"}
}