{
  "type": "Feature",
  "properties": {
    "iso:country":"GB",
    "wof:name":"CH65 5AD",
    "wof:placetype":"postalcode"
},
  "geometry": {"coordinates":[-2.89245666872654,53.27397614242925],"type":"Point"}
}