{
  "type": "Feature",
  "properties": {
    "date:inception_lower":"1986-04-01",
    "date:inception_upper":"1986-04-30",
    "iso:country":"GB",
    "wof:name":"LE4 1DS",
    "wof:placetype":"postalcode"
},
  "geometry": {"coordinates":[-1.166471,52.666332],"type":"Point"}
}