{
  "type": "Feature",
  "properties": {
    "iso:country":"GB",
    "wof:name":"BL3 4RG",
    "wof:placetype":"postalcode"
},
  "geometry": {"coordinates":[-2.47346114602172,53.5625202876772],"type":"Point"}
}