{
  "type": "Feature",
  "properties": {
    "date:inception_lower": "1980-01-01",
    "date:inception_upper": "1980-01-01",
    "iso:country": "GB",
    "wof:name": "BL3 4RG",
    "wof:placetype": "postalcode"
  },
  "geometry": {"coordinates":[-2.473461,53.56252],"type":"Point"}
}
