{
  "type": "Feature",
  "properties": {
    "iso:country":"GB",
    "wof:name":"B90 1DQ",
    "wof:placetype":"postalcode"
},
  "geometry": {"coordinates":[-1.85105680523972,52.39534456780562],"type":"Point"}
}