{
  "type": "Feature",
  "properties": {
    "date:inception_lower":"1980-01-01",
    "date:inception_upper":"1980-01-31",
    "iso:country":"GB",
    "wof:name":"LE9 8AU",
    "wof:placetype":"postalcode"
},
  "geometry": {"coordinates":[-1.335708,52.572593],"type":"Point"}
}