{
  "type": "Feature",
  "properties": {
    "iso:country":"GB",
    "wof:name":"EX7 9TE",
    "wof:placetype":"postalcode"
},
  "geometry": {"coordinates":[-3.46176595318741,50.59248315811508],"type":"Point"}
}