{
  "type": "Feature",
  "properties": {
    "iso:country":"GB",
    "wof:name":"LS27 7EB",
    "wof:placetype":"postalcode"
},
  "geometry": {"coordinates":[-1.62898925034006,53.75737984065113],"type":"Point"}
}