{
  "type": "Feature",
  "properties": {
    "iso:country": "GB",
    "wof:name": "KA30 9JR",
    "wof:placetype": "postalcode"
  },
  "geometry": {"coordinates":[-4.85685,55.798286],"type":"Point"}
}
