{
  "type": "Feature",
  "properties": {
    "iso:country":"GB",
    "wof:name":"M8 0PX",
    "wof:placetype":"postalcode"
},
  "geometry": {"coordinates":[-2.23495498045168,53.50588120561447],"type":"Point"}
}