{
  "type": "Feature",
  "properties": {
    "iso:country":"GB",
    "wof:name":"LL55 1ED",
    "wof:placetype":"postalcode"
},
  "geometry": {"coordinates":[-4.25797124683111,53.1462412666983],"type":"Point"}
}