{
  "type": "Feature",
  "properties": {
    "iso:country": "GB",
    "wof:name": "LL55 1ED",
    "wof:placetype": "postalcode"
  },
  "geometry": {"coordinates":[-4.257971,53.146241],"type":"Point"}
}
