{
  "type": "Feature",
  "properties": {
    "iso:country":"GB",
    "wof:name":"ME1 1QT",
    "wof:placetype":"postalcode"
},
  "geometry": {"coordinates":[0.50193165376166,51.3905739648856],"type":"Point"}
}