{
  "type": "Feature",
  "properties": {
    "date:inception_lower": "1994-05-01",
    "date:inception_upper": "1994-05-01",
    "iso:country": "GB",
    "wof:name": "M46 9BQ",
    "wof:placetype": "postalcode"
  },
  "geometry": {"coordinates":[-2.480798,53.51718],"type":"Point"}
}
