{
  "type": "Feature",
  "properties": {
    "iso:country": "GB",
    "wof:name": "LE14 2UF",
    "wof:placetype": "postalcode"
  },
  "geometry": {"coordinates":[-0.852693,52.717689],"type":"Point"}
}
