{
  "type": "Feature",
  "properties": {
    "iso:country":"GB",
    "wof:name":"LE14 2UF",
    "wof:placetype":"postalcode"
},
  "geometry": {"coordinates":[-0.85261265570889,52.717659052495],"type":"Point"}
}