{
  "type": "Feature",
  "properties": {
    "iso:country":"GB",
    "wof:name":"DA9 9RA",
    "wof:placetype":"postalcode"
},
  "geometry": {"coordinates":[0.271394183955,51.44976938319761],"type":"Point"}
}