{
  "type": "Feature",
  "properties": {
    "date:inception_lower": "1996-06-01",
    "date:inception_upper": "1996-06-01",
    "iso:country": "GB",
    "wof:name": "DA9 9RA",
    "wof:placetype": "postalcode"
  },
  "geometry": {"coordinates":[0.271394,51.449769],"type":"Point"}
}
