{
  "type": "Feature",
  "properties": {
    "iso:country":"GB",
    "wof:name":"CB24 6DD",
    "wof:placetype":"postalcode"
},
  "geometry": {"coordinates":[0.16432646025139,52.24506358000967],"type":"Point"}
}