{
  "type": "Feature",
  "properties": {
    "iso:country": "GB",
    "wof:name": "CB24 6DD",
    "wof:placetype": "postalcode"
  },
  "geometry": {"coordinates":[0.166595,52.24563],"type":"Point"}
}
