{
  "type": "Feature",
  "properties": {
    "iso:country": "GB",
    "wof:name": "L30 8RS",
    "wof:placetype": "postalcode"
  },
  "geometry": {"coordinates":[-2.955108,53.488812],"type":"Point"}
}
