{
  "type": "Feature",
  "properties": {
    "date:inception_lower": "1980-01-01",
    "date:inception_upper": "1980-01-01",
    "iso:country": "GB",
    "wof:name": "KA13 7LH",
    "wof:placetype": "postalcode"
  },
  "geometry": {"coordinates":[-4.683836,55.65391],"type":"Point"}
}
