{
  "type": "Feature",
  "properties": {
    "iso:country":"GB",
    "wof:name":"KA13 7LH",
    "wof:placetype":"postalcode"
},
  "geometry": {"coordinates":[-4.68383639248266,55.65390972781619],"type":"Point"}
}