{
  "type": "Feature",
  "properties": {
    "iso:country":"GB",
    "wof:name":"LU2 8TR",
    "wof:placetype":"postalcode"
},
  "geometry": {"coordinates":[-0.37380403642519,51.89208546837091],"type":"Point"}
}