{
  "type": "Feature",
  "properties": {
    "iso:country": "GB",
    "wof:name": "LU2 8TR",
    "wof:placetype": "postalcode"
  },
  "geometry": {"coordinates":[-0.373804,51.892085],"type":"Point"}
}
