{
  "type": "Feature",
  "properties": {
    "iso:country":"GB",
    "wof:name":"SE3 7PH",
    "wof:placetype":"postalcode"
},
  "geometry": {"coordinates":[0.01440592564978,51.48062754412862],"type":"Point"}
}