{
  "type": "Feature",
  "properties": {
    "date:inception_lower":"1980-01-01",
    "date:inception_upper":"1980-01-31",
    "iso:country":"GB",
    "wof:name":"SG19 2DR",
    "wof:placetype":"postalcode"
},
  "geometry": {"coordinates":[-0.197209,52.125042],"type":"Point"}
}