{
  "type": "Feature",
  "properties": {
    "iso:country": "GB",
    "wof:name": "SG19 2DR",
    "wof:placetype": "postalcode"
  },
  "geometry": {"coordinates":[-0.197209,52.125042],"type":"Point"}
}
