{
  "type": "Feature",
  "properties": {
    "iso:country": "GB",
    "wof:name": "CV47 8LU",
    "wof:placetype": "postalcode"
  },
  "geometry": {"coordinates":[-1.31831,52.24558],"type":"Point"}
}
