{
  "type": "Feature",
  "properties": {
    "date:inception_lower": "1999-12-01",
    "date:inception_upper": "1999-12-01",
    "iso:country": "GB",
    "wof:name": "CV47 8LU",
    "wof:placetype": "postalcode"
  },
  "geometry": {"coordinates":[-1.31831,52.24558],"type":"Point"}
}
