{
  "type": "Feature",
  "properties": {
    "date:inception_lower": "2021-02-01",
    "date:inception_upper": "2021-02-01",
    "iso:country": "GB",
    "wof:name": "S44 6FW",
    "wof:placetype": "postalcode"
  },
  "geometry": {"coordinates":[-1.274064,53.225455],"type":"Point"}
}
