{
  "type": "Feature",
  "properties": {
    "date:inception_lower": "2022-05-01",
    "date:inception_upper": "2022-05-01",
    "iso:country": "GB",
    "wof:name": "LE9 9RG",
    "wof:placetype": "postalcode"
  },
  "geometry": {"coordinates":[-1.345589,52.635749],"type":"Point"}
}
