{
  "type": "Feature",
  "properties": {
    "iso:country":"GB",
    "wof:name":"EH9 3ER",
    "wof:placetype":"postalcode"
},
  "geometry": {"coordinates":[-3.18551993804064,55.92615287708352],"type":"Point"}
}