{
  "type": "Feature",
  "properties": {
    "iso:country": "GB",
    "wof:name": "TS17 0UP",
    "wof:placetype": "postalcode"
  },
  "geometry": {"coordinates":[-1.303213,54.518011],"type":"Point"}
}
