{
  "type": "Feature",
  "properties": {
    "iso:country": "GB",
    "wof:name": "PE6 0SY",
    "wof:placetype": "postalcode"
  },
  "geometry": {"coordinates":[-0.092368,52.615124],"type":"Point"}
}
