{
  "type": "Feature",
  "properties": {
    "date:inception_lower":"1980-01-01",
    "date:inception_upper":"1980-01-31",
    "iso:country":"GB",
    "wof:name":"PE6 0SY",
    "wof:placetype":"postalcode"
},
  "geometry": {"coordinates":[-0.092335,52.615905],"type":"Point"}
}