{
  "type": "Feature",
  "properties": {
    "date:inception_lower":"1980-01-01",
    "date:inception_upper":"1980-01-31",
    "iso:country":"GB",
    "wof:name":"NN2 7SE",
    "wof:placetype":"postalcode"
},
  "geometry": {"coordinates":[-0.887959,52.265951],"type":"Point"}
}