{
  "type": "Feature",
  "properties": {
    "iso:country":"GB",
    "wof:name":"NN2 7SE",
    "wof:placetype":"postalcode"
},
  "geometry": {"coordinates":[-0.88795862444083,52.26595066204729],"type":"Point"}
}