{
  "type": "Feature",
  "properties": {
    "iso:country": "GB",
    "wof:name": "ME17 4GL",
    "wof:placetype": "postalcode"
  },
  "geometry": {"coordinates":[0.494919,51.237472],"type":"Point"}
}
