{
  "type": "Feature",
  "properties": {
    "iso:country":"GB",
    "wof:name":"FK9 5PB",
    "wof:placetype":"postalcode"
},
  "geometry": {"coordinates":[-3.93934529968734,56.13918550841041],"type":"Point"}
}