{
  "type": "Feature",
  "properties": {
    "iso:country": "GB",
    "wof:name": "WA9 1QX",
    "wof:placetype": "postalcode"
  },
  "geometry": {"coordinates":[-2.705527,53.4555],"type":"Point"}
}
