{
  "type": "Feature",
  "properties": {
    "iso:country":"GB",
    "wof:name":"WA9 1QX",
    "wof:placetype":"postalcode"
},
  "geometry": {"coordinates":[-2.70552721147957,53.45549950864856],"type":"Point"}
}