{
  "type": "Feature",
  "properties": {
    "iso:country":"GB",
    "wof:name":"EH29 9ED",
    "wof:placetype":"postalcode"
},
  "geometry": {"coordinates":[-3.41026505824083,55.95727433574859],"type":"Point"}
}