{
  "type": "Feature",
  "properties": {
    "iso:country":"GB",
    "wof:name":"DE11 0LA",
    "wof:placetype":"postalcode"
},
  "geometry": {"coordinates":[-1.5633318926627,52.7779873259752],"type":"Point"}
}