{
  "type": "Feature",
  "properties": {
    "date:inception_lower": "2003-06-01",
    "date:inception_upper": "2003-06-01",
    "iso:country": "GB",
    "wof:name": "DE11 0LA",
    "wof:placetype": "postalcode"
  },
  "geometry": {"coordinates":[-1.563376,52.778023],"type":"Point"}
}
