{
  "type": "Feature",
  "properties": {
    "date:inception_lower": "1981-06-01",
    "date:inception_upper": "1981-06-01",
    "iso:country": "GB",
    "wof:name": "CH7 5NG",
    "wof:placetype": "postalcode"
  },
  "geometry": {"coordinates":[-3.180911,53.152691],"type":"Point"}
}
