{
  "type": "Feature",
  "properties": {
    "iso:country": "GB",
    "wof:name": "GL6 7NG",
    "wof:placetype": "postalcode"
  },
  "geometry": {"coordinates":[-2.163282,51.764686],"type":"Point"}
}
