{
  "type": "Feature",
  "properties": {
    "iso:country": "GB",
    "wof:name": "GL6 7NG",
    "wof:placetype": "postalcode"
  },
  "geometry": {"coordinates":[-2.167536,51.765718],"type":"Point"}
}
