{
  "type": "Feature",
  "properties": {
    "iso:country":"GB",
    "wof:name":"GL6 7NG",
    "wof:placetype":"postalcode"
},
  "geometry": {"coordinates":[-2.16759416953263,51.76569960138981],"type":"Point"}
}