{
  "type": "Feature",
  "properties": {
    "date:inception_lower":"1980-01-01",
    "date:inception_upper":"1980-01-31",
    "iso:country":"GB",
    "wof:name":"B62 9BE",
    "wof:placetype":"postalcode"
},
  "geometry": {"coordinates":[-2.015955,52.462575],"type":"Point"}
}