{
  "type": "Feature",
  "properties": {
    "iso:country":"GB",
    "wof:name":"B62 9BE",
    "wof:placetype":"postalcode"
},
  "geometry": {"coordinates":[-2.0159549020707,52.46257453445373],"type":"Point"}
}