{
  "type": "Feature",
  "properties": {
    "iso:country":"GB",
    "wof:name":"MK40 4JT",
    "wof:placetype":"postalcode"
},
  "geometry": {"coordinates":[-0.48379482710081,52.13236649860715],"type":"Point"}
}