{
  "type": "Feature",
  "properties": {
    "iso:country":"GB",
    "wof:name":"KA20 4EJ",
    "wof:placetype":"postalcode"
},
  "geometry": {"coordinates":[-4.74868838629345,55.64601920075791],"type":"Point"}
}