{
  "type": "Feature",
  "properties": {
    "iso:country": "GB",
    "wof:name": "DE6 4PD",
    "wof:placetype": "postalcode"
  },
  "geometry": {"coordinates":[-1.566509,52.978814],"type":"Point"}
}
