{
  "type": "Feature",
  "properties": {
    "date:inception_lower":"1980-01-01",
    "date:inception_upper":"1980-01-31",
    "iso:country":"GB",
    "wof:name":"CM9 8SH",
    "wof:placetype":"postalcode"
},
  "geometry": {"coordinates":[0.839284,51.760417],"type":"Point"}
}