{
  "type": "Feature",
  "properties": {
    "iso:country": "GB",
    "wof:name": "CM9 8SH",
    "wof:placetype": "postalcode"
  },
  "geometry": {"coordinates":[0.839284,51.760417],"type":"Point"}
}
