{
  "type": "Feature",
  "properties": {
    "iso:country":"GB",
    "wof:name":"CM9 8SH",
    "wof:placetype":"postalcode"
},
  "geometry": {"coordinates":[0.83928346202959,51.76041671294089],"type":"Point"}
}