{
  "type": "Feature",
  "properties": {
    "iso:country":"GB",
    "wof:name":"TR7 1FW",
    "wof:placetype":"postalcode"
},
  "geometry": {"coordinates":[-5.0889445716003,50.41055802820451],"type":"Point"}
}