{
  "type": "Feature",
  "properties": {
    "date:inception_lower":"2016-01-01",
    "date:inception_upper":"2016-01-31",
    "iso:country":"GB",
    "wof:name":"TR7 1FW",
    "wof:placetype":"postalcode"
},
  "geometry": {"coordinates":[-5.089205,50.410624],"type":"Point"}
}