{
  "type": "Feature",
  "properties": {
    "iso:country":"GB",
    "wof:name":"BH24 3PU",
    "wof:placetype":"postalcode"
},
  "geometry": {"coordinates":[-1.80745198941118,50.899371578499],"type":"Point"}
}