{
  "type": "Feature",
  "properties": {
    "date:inception_lower":"1980-01-01",
    "date:inception_upper":"1980-01-31",
    "iso:country":"GB",
    "wof:name":"BH24 3PU",
    "wof:placetype":"postalcode"
},
  "geometry": {"coordinates":[-1.807452,50.899372],"type":"Point"}
}