{
  "type": "Feature",
  "properties": {
    "iso:country": "GB",
    "wof:name": "ME17 2BQ",
    "wof:placetype": "postalcode"
  },
  "geometry": {"coordinates":[0.709557,51.235333],"type":"Point"}
}
