{
  "type": "Feature",
  "properties": {
    "date:inception_lower":"1980-01-01",
    "date:inception_upper":"1980-01-31",
    "iso:country":"GB",
    "wof:name":"SK9 3HF",
    "wof:placetype":"postalcode"
},
  "geometry": {"coordinates":[-2.221912,53.349721],"type":"Point"}
}