{
  "type": "Feature",
  "properties": {
    "iso:country": "GB",
    "wof:name": "SK9 3HF",
    "wof:placetype": "postalcode"
  },
  "geometry": {"coordinates":[-2.221912,53.349721],"type":"Point"}
}
