{
  "type": "Feature",
  "properties": {
    "iso:country":"GB",
    "wof:name":"OX2 6QR",
    "wof:placetype":"postalcode"
},
  "geometry": {"coordinates":[-1.25978667185904,51.76199812329993],"type":"Point"}
}