{
  "type": "Feature",
  "properties": {
    "iso:country":"GB",
    "wof:name":"BA21 3TS",
    "wof:placetype":"postalcode"
},
  "geometry": {"coordinates":[-2.66189732005013,50.9477042772652],"type":"Point"}
}