{
  "type": "Feature",
  "properties": {
    "iso:country": "GB",
    "wof:name": "S81 7NN",
    "wof:placetype": "postalcode"
  },
  "geometry": {"coordinates":[-1.125279,53.32978],"type":"Point"}
}
