{
  "type": "Feature",
  "properties": {
    "iso:country":"GB",
    "wof:name":"BS4 2TT",
    "wof:placetype":"postalcode"
},
  "geometry": {"coordinates":[-2.57080776263533,51.42817135963176],"type":"Point"}
}