{
  "type": "Feature",
  "properties": {
    "date:inception_lower":"1980-01-01",
    "date:inception_upper":"1980-01-31",
    "iso:country":"GB",
    "wof:name":"BS4 2TT",
    "wof:placetype":"postalcode"
},
  "geometry": {"coordinates":[-2.570808,51.428171],"type":"Point"}
}