{
  "type": "Feature",
  "properties": {
    "iso:country":"GB",
    "wof:name":"LA2 7HU",
    "wof:placetype":"postalcode"
},
  "geometry": {"coordinates":[-2.51575014281782,54.11758817170772],"type":"Point"}
}