{
  "type": "Feature",
  "properties": {
    "iso:country": "GB",
    "wof:name": "WR4 0RZ",
    "wof:placetype": "postalcode"
  },
  "geometry": {"coordinates":[-2.172439,52.202408],"type":"Point"}
}
