{
  "type": "Feature",
  "properties": {
    "date:inception_lower": "1980-01-01",
    "date:inception_upper": "1980-01-01",
    "iso:country": "GB",
    "wof:name": "G83 0EU",
    "wof:placetype": "postalcode"
  },
  "geometry": {"coordinates":[-4.586571,55.986707],"type":"Point"}
}
