{
  "type": "Feature",
  "properties": {
    "iso:country": "GB",
    "wof:name": "G83 0EU",
    "wof:placetype": "postalcode"
  },
  "geometry": {"coordinates":[-4.586571,55.986707],"type":"Point"}
}
