{
  "type": "Feature",
  "properties": {
    "date:inception_lower": "1980-01-01",
    "date:inception_upper": "1980-01-01",
    "iso:country": "GB",
    "wof:name": "LA14 4BX",
    "wof:placetype": "postalcode"
  },
  "geometry": {"coordinates":[-3.231039,54.13793],"type":"Point"}
}
