{
  "type": "Feature",
  "properties": {
    "date:inception_lower": "2014-09-01",
    "date:inception_upper": "2014-09-01",
    "iso:country": "GB",
    "wof:name": "G84 7HZ",
    "wof:placetype": "postalcode"
  },
  "geometry": {"coordinates":[-4.708868,55.997292],"type":"Point"}
}
