{
  "type": "Feature",
  "properties": {
    "iso:country":"GB",
    "wof:name":"G84 7HZ",
    "wof:placetype":"postalcode"
},
  "geometry": {"coordinates":[-4.70886836809531,55.99729166238385],"type":"Point"}
}