{
  "type": "Feature",
  "properties": {
    "iso:country": "GB",
    "wof:name": "G84 7HZ",
    "wof:placetype": "postalcode"
  },
  "geometry": {"coordinates":[-4.708868,55.997292],"type":"Point"}
}
