{
  "type": "Feature",
  "properties": {
    "iso:country":"GB",
    "wof:name":"SS15 5PS",
    "wof:placetype":"postalcode"
},
  "geometry": {"coordinates":[0.42347942039523,51.57536268093597],"type":"Point"}
}