{
  "type": "Feature",
  "properties": {
    "iso:country":"GB",
    "wof:name":"HA5 3BP",
    "wof:placetype":"postalcode"
},
  "geometry": {"coordinates":[-0.37930986597453,51.59705552493488],"type":"Point"}
}