{
  "type": "Feature",
  "properties": {
    "iso:country": "GB",
    "wof:name": "OX7 4BW",
    "wof:placetype": "postalcode"
  },
  "geometry": {"coordinates":[-1.453756,51.984129],"type":"Point"}
}
