{
  "type": "Feature",
  "properties": {
    "iso:country":"GB",
    "wof:name":"OX7 4BW",
    "wof:placetype":"postalcode"
},
  "geometry": {"coordinates":[-1.4537560091509,51.98412938854302],"type":"Point"}
}