{
  "type": "Feature",
  "properties": {
    "iso:country": "GB",
    "wof:name": "NG17 8LN",
    "wof:placetype": "postalcode"
  },
  "geometry": {"coordinates":[-1.271173,53.09478],"type":"Point"}
}
