{
  "type": "Feature",
  "properties": {
    "date:inception_lower": "1999-06-01",
    "date:inception_upper": "1999-06-01",
    "iso:country": "GB",
    "wof:name": "CH61 1AE",
    "wof:placetype": "postalcode"
  },
  "geometry": {"coordinates":[-3.085736,53.345904],"type":"Point"}
}
