{
  "type": "Feature",
  "properties": {
    "iso:country":"GB",
    "wof:name":"DL16 7RL",
    "wof:placetype":"postalcode"
},
  "geometry": {"coordinates":[-1.61798749590765,54.69897016244376],"type":"Point"}
}