{
  "type": "Feature",
  "properties": {
    "iso:country":"GB",
    "wof:name":"HD1 6PX",
    "wof:placetype":"postalcode"
},
  "geometry": {"coordinates":[-1.77320870649426,53.65401626616048],"type":"Point"}
}