{
  "type": "Feature",
  "properties": {
    "iso:country":"GB",
    "wof:name":"GU22 0LU",
    "wof:placetype":"postalcode"
},
  "geometry": {"coordinates":[-0.58869644073565,51.30696647671081],"type":"Point"}
}