{
  "type": "Feature",
  "properties": {
    "date:inception_lower":"2006-10-01",
    "date:inception_upper":"2006-10-31",
    "iso:country":"GB",
    "wof:name":"AL10 9AY",
    "wof:placetype":"postalcode"
},
  "geometry": {"coordinates":[-0.246976,51.764665],"type":"Point"}
}