{
  "type": "Feature",
  "properties": {
    "date:inception_lower": "2006-10-01",
    "date:inception_upper": "2006-10-01",
    "iso:country": "GB",
    "wof:name": "AL10 9AY",
    "wof:placetype": "postalcode"
  },
  "geometry": {"coordinates":[-0.246939,51.764617],"type":"Point"}
}
