{
  "type": "Feature",
  "properties": {
    "iso:country":"GB",
    "wof:name":"AL10 9AY",
    "wof:placetype":"postalcode"
},
  "geometry": {"coordinates":[-0.24697590016357,51.76466484068832],"type":"Point"}
}