{
  "type": "Feature",
  "properties": {
    "iso:country":"GB",
    "wof:name":"TR18 5EF",
    "wof:placetype":"postalcode"
},
  "geometry": {"coordinates":[-5.549034560757,50.10200636863383],"type":"Point"}
}