{
  "type": "Feature",
  "properties": {
    "iso:country":"GB",
    "wof:name":"HP1 3AF",
    "wof:placetype":"postalcode"
},
  "geometry": {"coordinates":[-0.47218706465,51.75960721465893],"type":"Point"}
}