{
  "type": "Feature",
  "properties": {
    "date:inception_lower": "1980-01-01",
    "date:inception_upper": "1980-01-01",
    "iso:country": "GB",
    "wof:name": "HP1 3AF",
    "wof:placetype": "postalcode"
  },
  "geometry": {"coordinates":[-0.472065,51.759577],"type":"Point"}
}
