{
  "type": "Feature",
  "properties": {
    "iso:country":"GB",
    "wof:name":"TA20 2LU",
    "wof:placetype":"postalcode"
},
  "geometry": {"coordinates":[-2.94688441813468,50.86155165254485],"type":"Point"}
}