{
  "type": "Feature",
  "properties": {
    "date:inception_lower": "1980-01-01",
    "date:inception_upper": "1980-01-01",
    "iso:country": "GB",
    "wof:name": "TA20 2LU",
    "wof:placetype": "postalcode"
  },
  "geometry": {"coordinates":[-2.946889,50.861543],"type":"Point"}
}
