{
  "type": "Feature",
  "properties": {
    "iso:country": "GB",
    "wof:name": "TA20 2LU",
    "wof:placetype": "postalcode"
  },
  "geometry": {"coordinates":[-2.946877,50.860913],"type":"Point"}
}
