{
  "type": "Feature",
  "properties": {
    "iso:country":"GB",
    "wof:name":"TD8 6BD",
    "wof:placetype":"postalcode"
},
  "geometry": {"coordinates":[-2.55807070040101,55.47565221624769],"type":"Point"}
}