{
  "type": "Feature",
  "properties": {
    "iso:country":"GB",
    "wof:name":"TN25 7EH",
    "wof:placetype":"postalcode"
},
  "geometry": {"coordinates":[0.96411285158121,51.09581500069111],"type":"Point"}
}