{
  "type": "Feature",
  "properties": {
    "date:inception_lower": "2007-04-01",
    "date:inception_upper": "2007-04-01",
    "iso:country": "GB",
    "wof:name": "DN21 1JE",
    "wof:placetype": "postalcode"
  },
  "geometry": {"coordinates":[-0.764673,53.409895],"type":"Point"}
}
