{
  "type": "Feature",
  "properties": {
    "iso:country": "GB",
    "wof:name": "DD9 6SJ",
    "wof:placetype": "postalcode"
  },
  "geometry": {"coordinates":[-2.708663,56.714452],"type":"Point"}
}
