{
  "type": "Feature",
  "properties": {
    "date:inception_lower": "2018-09-01",
    "date:inception_upper": "2018-09-01",
    "iso:country": "GB",
    "wof:name": "ML6 0AJ",
    "wof:placetype": "postalcode"
  },
  "geometry": {"coordinates":[-3.981856,55.866363],"type":"Point"}
}
