{
  "type": "Feature",
  "properties": {
    "iso:country": "GB",
    "wof:name": "ML6 0AJ",
    "wof:placetype": "postalcode"
  },
  "geometry": {"coordinates":[-3.981936,55.866362],"type":"Point"}
}
