{
  "type": "Feature",
  "properties": {
    "iso:country":"GB",
    "wof:name":"WN8 8DW",
    "wof:placetype":"postalcode"
},
  "geometry": {"coordinates":[-2.79766014224054,53.54930062495579],"type":"Point"}
}