{
  "type": "Feature",
  "properties": {
    "iso:country": "GB",
    "wof:name": "W1K 1HA",
    "wof:placetype": "postalcode"
  },
  "geometry": {"coordinates":[-0.150256,51.506829],"type":"Point"}
}
