{
  "type": "Feature",
  "properties": {
    "iso:country":"GB",
    "wof:name":"W1K 1HA",
    "wof:placetype":"postalcode"
},
  "geometry": {"coordinates":[-0.15025616815553,51.50682924639266],"type":"Point"}
}