{
  "type": "Feature",
  "properties": {
    "iso:country":"GB",
    "wof:name":"B68 8NN",
    "wof:placetype":"postalcode"
},
  "geometry": {"coordinates":[-2.01699266307459,52.48170504368575],"type":"Point"}
}