{
  "type": "Feature",
  "properties": {
    "date:inception_lower":"1984-02-01",
    "date:inception_upper":"1984-02-29",
    "iso:country":"GB",
    "wof:name":"NP7 9LJ",
    "wof:placetype":"postalcode"
},
  "geometry": {"coordinates":[-3.030763,51.814473],"type":"Point"}
}