{
  "type": "Feature",
  "properties": {
    "iso:country":"GB",
    "wof:name":"MK14 6BL",
    "wof:placetype":"postalcode"
},
  "geometry": {"coordinates":[-0.77396276435325,52.06177054194461],"type":"Point"}
}