{
  "type": "Feature",
  "properties": {
    "iso:country":"GB",
    "wof:name":"NE32 5PJ",
    "wof:placetype":"postalcode"
},
  "geometry": {"coordinates":[-1.49212261515053,54.97282185313598],"type":"Point"}
}