{
  "type": "Feature",
  "properties": {
    "iso:country":"GB",
    "wof:name":"SY23 3HQ",
    "wof:placetype":"postalcode"
},
  "geometry": {"coordinates":[-3.99992514114414,52.43861181720395],"type":"Point"}
}