{
  "type": "Feature",
  "properties": {
    "iso:country": "GB",
    "wof:name": "SY23 3HQ",
    "wof:placetype": "postalcode"
  },
  "geometry": {"coordinates":[-3.999925,52.438612],"type":"Point"}
}
