{
  "type": "Feature",
  "properties": {
    "date:inception_lower":"1993-01-01",
    "date:inception_upper":"1993-01-31",
    "iso:country":"GB",
    "wof:name":"SY23 3HQ",
    "wof:placetype":"postalcode"
},
  "geometry": {"coordinates":[-3.999925,52.438612],"type":"Point"}
}