{
  "type": "Feature",
  "properties": {
    "date:inception_lower": "2021-01-01",
    "date:inception_upper": "2021-01-01",
    "iso:country": "GB",
    "wof:name": "HR3 6BP",
    "wof:placetype": "postalcode"
  },
  "geometry": {"coordinates":[-3.03039,52.11779],"type":"Point"}
}
