{
  "type": "Feature",
  "properties": {
    "date:inception_lower": "1980-01-01",
    "date:inception_upper": "1980-01-01",
    "iso:country": "GB",
    "wof:name": "WR9 9HP",
    "wof:placetype": "postalcode"
  },
  "geometry": {"coordinates":[-2.168713,52.277042],"type":"Point"}
}
