{
  "type": "Feature",
  "properties": {
    "date:inception_lower": "1988-03-01",
    "date:inception_upper": "1988-03-01",
    "iso:country": "GB",
    "wof:name": "MK42 8TS",
    "wof:placetype": "postalcode"
  },
  "geometry": {"coordinates":[-0.49386,52.125914],"type":"Point"}
}
