{
  "type": "Feature",
  "properties": {
    "iso:country":"GB",
    "wof:name":"WR2 5LZ",
    "wof:placetype":"postalcode"
},
  "geometry": {"coordinates":[-2.24361221114576,52.19209646116212],"type":"Point"}
}