{
  "type": "Feature",
  "properties": {
    "date:inception_lower": "1986-07-01",
    "date:inception_upper": "1986-07-01",
    "iso:country": "GB",
    "wof:name": "MK10 9AZ",
    "wof:placetype": "postalcode"
  },
  "geometry": {"coordinates":[-0.701152,52.043386],"type":"Point"}
}
