{
  "type": "Feature",
  "properties": {
    "date:inception_lower":"1980-01-01",
    "date:inception_upper":"1980-01-31",
    "iso:country":"GB",
    "wof:name":"LL13 7EL",
    "wof:placetype":"postalcode"
},
  "geometry": {"coordinates":[-2.996694,53.039678],"type":"Point"}
}