{
  "type": "Feature",
  "properties": {
    "iso:country": "GB",
    "wof:name": "RG6 1BX",
    "wof:placetype": "postalcode"
  },
  "geometry": {"coordinates":[-0.925399,51.454555],"type":"Point"}
}
