{
  "type": "Feature",
  "properties": {
    "date:inception_lower": "1986-04-01",
    "date:inception_upper": "1986-04-01",
    "iso:country": "GB",
    "wof:name": "EX17 5PN",
    "wof:placetype": "postalcode"
  },
  "geometry": {"coordinates":[-3.724762,50.779161],"type":"Point"}
}
