{
  "type": "Feature",
  "properties": {
    "iso:country": "GB",
    "wof:name": "WN2 1LL",
    "wof:placetype": "postalcode"
  },
  "geometry": {"coordinates":[-2.603815,53.580638],"type":"Point"}
}
