{
  "type": "Feature",
  "properties": {
    "iso:country":"GB",
    "wof:name":"WN2 1LL",
    "wof:placetype":"postalcode"
},
  "geometry": {"coordinates":[-2.60381475619002,53.5806379827456],"type":"Point"}
}