{
  "type": "Feature",
  "properties": {
    "iso:country": "GB",
    "wof:name": "DA3 8LZ",
    "wof:placetype": "postalcode"
  },
  "geometry": {"coordinates":[0.292358,51.382668],"type":"Point"}
}
