{
  "type": "Feature",
  "properties": {
    "date:inception_lower": "1996-12-01",
    "date:inception_upper": "1996-12-01",
    "iso:country": "GB",
    "wof:name": "SK23 9SA",
    "wof:placetype": "postalcode"
  },
  "geometry": {"coordinates":[-1.925905,53.32213],"type":"Point"}
}
