{
  "type": "Feature",
  "properties": {
    "iso:country":"GB",
    "wof:name":"PR7 5FJ",
    "wof:placetype":"postalcode"
},
  "geometry": {"coordinates":[-2.665105294414,53.63533095188794],"type":"Point"}
}