{
  "type": "Feature",
  "properties": {
    "date:inception_lower":"2011-06-01",
    "date:inception_upper":"2011-06-30",
    "iso:country":"GB",
    "wof:name":"PR7 5FJ",
    "wof:placetype":"postalcode"
},
  "geometry": {"coordinates":[-2.665105,53.635331],"type":"Point"}
}