{
  "type": "Feature",
  "properties": {
    "date:inception_lower":"1980-01-01",
    "date:inception_upper":"1980-01-31",
    "iso:country":"GB",
    "wof:name":"TN1 1NT",
    "wof:placetype":"postalcode"
},
  "geometry": {"coordinates":[0.263172,51.130603],"type":"Point"}
}