{
  "type": "Feature",
  "properties": {
    "iso:country":"GB",
    "wof:name":"TN1 1NT",
    "wof:placetype":"postalcode"
},
  "geometry": {"coordinates":[0.26317146961593,51.13060296935096],"type":"Point"}
}