{
  "type": "Feature",
  "properties": {
    "date:inception_lower": "1980-01-01",
    "date:inception_upper": "1980-01-01",
    "iso:country": "GB",
    "wof:name": "BN25 4LX",
    "wof:placetype": "postalcode"
  },
  "geometry": {"coordinates":[0.117898,50.770785],"type":"Point"}
}
