{
  "type": "Feature",
  "properties": {
    "iso:country":"GB",
    "wof:name":"PE9 3QB",
    "wof:placetype":"postalcode"
},
  "geometry": {"coordinates":[-0.54050372789586,52.59748747595121],"type":"Point"}
}