{
  "type": "Feature",
  "properties": {
    "iso:country": "GB",
    "wof:name": "PE9 3QB",
    "wof:placetype": "postalcode"
  },
  "geometry": {"coordinates":[-0.537957,52.599147],"type":"Point"}
}
