{
  "type": "Feature",
  "properties": {
    "iso:country":"GB",
    "wof:name":"SW1X 8QS",
    "wof:placetype":"postalcode"
},
  "geometry": {"coordinates":[-0.15236062119695,51.50004609819219],"type":"Point"}
}