{
  "type": "Feature",
  "properties": {
    "iso:country": "GB",
    "wof:name": "PO18 0QZ",
    "wof:placetype": "postalcode"
  },
  "geometry": {"coordinates":[-0.775243,50.906435],"type":"Point"}
}
