{
  "type": "Feature",
  "properties": {
    "iso:country":"GB",
    "wof:name":"DA4 9BB",
    "wof:placetype":"postalcode"
},
  "geometry": {"coordinates":[0.2410656249198,51.40296855822103],"type":"Point"}
}