{
  "type": "Feature",
  "properties": {
    "date:inception_lower": "1980-01-01",
    "date:inception_upper": "1980-01-01",
    "iso:country": "GB",
    "wof:name": "DA4 9BB",
    "wof:placetype": "postalcode"
  },
  "geometry": {"coordinates":[0.241066,51.402969],"type":"Point"}
}
