{
  "type": "Feature",
  "properties": {
    "iso:country": "GB",
    "wof:name": "SO30 2FX",
    "wof:placetype": "postalcode"
  },
  "geometry": {"coordinates":[-1.304398,50.924599],"type":"Point"}
}
