{
  "type": "Feature",
  "properties": {
    "iso:country": "GB",
    "wof:name": "EC1M 5SX",
    "wof:placetype": "postalcode"
  },
  "geometry": {"coordinates":[-0.104659,51.521856],"type":"Point"}
}
