{
  "type": "Feature",
  "properties": {
    "iso:country":"GB",
    "wof:name":"EC1M 5SX",
    "wof:placetype":"postalcode"
},
  "geometry": {"coordinates":[-0.10465879921019,51.52185616951829],"type":"Point"}
}