{
  "type": "Feature",
  "properties": {
    "iso:country":"GB",
    "wof:name":"SE10 8BS",
    "wof:placetype":"postalcode"
},
  "geometry": {"coordinates":[-0.01850637993748,51.47456075360594],"type":"Point"}
}