{
  "type": "Feature",
  "properties": {
    "iso:country":"GB",
    "wof:name":"SK6 2BP",
    "wof:placetype":"postalcode"
},
  "geometry": {"coordinates":[-2.13378336726493,53.41394155846935],"type":"Point"}
}