{
  "type": "Feature",
  "properties": {
    "iso:country": "GB",
    "wof:name": "TN33 9NA",
    "wof:placetype": "postalcode"
  },
  "geometry": {"coordinates":[0.419266,50.904024],"type":"Point"}
}
