{
  "type": "Feature",
  "properties": {
    "iso:country":"GB",
    "wof:name":"TN33 9NA",
    "wof:placetype":"postalcode"
},
  "geometry": {"coordinates":[0.41926633518738,50.90402396658706],"type":"Point"}
}