{
  "type": "Feature",
  "properties": {
    "iso:country":"GB",
    "wof:name":"PL29 3SA",
    "wof:placetype":"postalcode"
},
  "geometry": {"coordinates":[-4.83116151524684,50.59446998217513],"type":"Point"}
}