{
  "type": "Feature",
  "properties": {
    "iso:country": "GB",
    "wof:name": "BL1 1AQ",
    "wof:placetype": "postalcode"
  },
  "geometry": {"coordinates":[-2.42674,53.578021],"type":"Point"}
}
