{
  "type": "Feature",
  "properties": {
    "iso:country":"GB",
    "wof:name":"ST8 6TB",
    "wof:placetype":"postalcode"
},
  "geometry": {"coordinates":[-2.18588019451462,53.10252716287577],"type":"Point"}
}