{
  "type": "Feature",
  "properties": {
    "iso:country": "GB",
    "wof:name": "ST8 6TB",
    "wof:placetype": "postalcode"
  },
  "geometry": {"coordinates":[-2.18588,53.102527],"type":"Point"}
}
