{
  "type": "Feature",
  "properties": {
    "date:inception_lower": "1981-06-01",
    "date:inception_upper": "1981-06-01",
    "iso:country": "GB",
    "wof:name": "ST8 6TB",
    "wof:placetype": "postalcode"
  },
  "geometry": {"coordinates":[-2.18588,53.102527],"type":"Point"}
}
