{
  "type": "Feature",
  "properties": {
    "iso:country":"GB",
    "wof:name":"IG9 5RP",
    "wof:placetype":"postalcode"
},
  "geometry": {"coordinates":[0.03277477683516,51.62733150688202],"type":"Point"}
}