{
  "type": "Feature",
  "properties": {
    "iso:country": "GB",
    "wof:name": "DG8 9BL",
    "wof:placetype": "postalcode"
  },
  "geometry": {"coordinates":[-4.46444,54.837318],"type":"Point"}
}
