{
  "type": "Feature",
  "properties": {
    "iso:country":"GB",
    "wof:name":"NE46 2EN",
    "wof:placetype":"postalcode"
},
  "geometry": {"coordinates":[-2.10806041356198,54.96870172453435],"type":"Point"}
}