{
  "type": "Feature",
  "properties": {
    "date:inception_lower": "1980-01-01",
    "date:inception_upper": "1980-01-01",
    "iso:country": "GB",
    "wof:name": "LL23 7HP",
    "wof:placetype": "postalcode"
  },
  "geometry": {"coordinates":[-3.515204,52.921414],"type":"Point"}
}
