{
  "type": "Feature",
  "properties": {
    "iso:country":"GB",
    "wof:name":"LL23 7HP",
    "wof:placetype":"postalcode"
},
  "geometry": {"coordinates":[-3.51520386214362,52.92141446255156],"type":"Point"}
}