{
  "type": "Feature",
  "properties": {
    "date:inception_lower": "1980-01-01",
    "date:inception_upper": "1980-01-01",
    "iso:country": "GB",
    "wof:name": "MK42 9DG",
    "wof:placetype": "postalcode"
  },
  "geometry": {"coordinates":[-0.478921,52.127475],"type":"Point"}
}
