{
  "type": "Feature",
  "properties": {
    "iso:country":"GB",
    "wof:name":"MK42 9DG",
    "wof:placetype":"postalcode"
},
  "geometry": {"coordinates":[-0.4789207811621,52.1274754208443],"type":"Point"}
}