{
  "type": "Feature",
  "properties": {
    "iso:country":"GB",
    "wof:name":"SE3 0QB",
    "wof:placetype":"postalcode"
},
  "geometry": {"coordinates":[0.00530063852742,51.46676395275568],"type":"Point"}
}