{
  "type": "Feature",
  "properties": {
    "iso:country":"GB",
    "wof:name":"NE20 0AY",
    "wof:placetype":"postalcode"
},
  "geometry": {"coordinates":[-1.7845554744982,55.10255169061224],"type":"Point"}
}