{
  "type": "Feature",
  "properties": {
    "date:inception_lower": "1980-01-01",
    "date:inception_upper": "1980-01-01",
    "iso:country": "GB",
    "wof:name": "NE20 0AY",
    "wof:placetype": "postalcode"
  },
  "geometry": {"coordinates":[-1.784568,55.102557],"type":"Point"}
}
