{
  "type": "Feature",
  "properties": {
    "iso:country": "GB",
    "wof:name": "NE20 0AY",
    "wof:placetype": "postalcode"
  },
  "geometry": {"coordinates":[-1.784898,55.102423],"type":"Point"}
}
