{
  "type": "Feature",
  "properties": {
    "iso:country":"GB",
    "wof:name":"SW20 0NR",
    "wof:placetype":"postalcode"
},
  "geometry": {"coordinates":[-0.24435537730232,51.41673229505681],"type":"Point"}
}