{
  "type": "Feature",
  "properties": {
    "iso:country": "GB",
    "wof:name": "NE9 7XN",
    "wof:placetype": "postalcode"
  },
  "geometry": {"coordinates":[-1.573398,54.921633],"type":"Point"}
}
