{
  "type": "Feature",
  "properties": {
    "iso:country":"GB",
    "wof:name":"NE9 7XN",
    "wof:placetype":"postalcode"
},
  "geometry": {"coordinates":[-1.57339835251362,54.92163331160891],"type":"Point"}
}