{
  "type": "Feature",
  "properties": {
    "iso:country":"GB",
    "wof:name":"OL14 8RT",
    "wof:placetype":"postalcode"
},
  "geometry": {"coordinates":[-2.06226039170764,53.7308918305333],"type":"Point"}
}