{
  "type": "Feature",
  "properties": {
    "date:inception_lower": "1984-02-01",
    "date:inception_upper": "1984-02-01",
    "iso:country": "GB",
    "wof:name": "TS23 3NH",
    "wof:placetype": "postalcode"
  },
  "geometry": {"coordinates":[-1.27786,54.625841],"type":"Point"}
}
