{
  "type": "Feature",
  "properties": {
    "iso:country":"GB",
    "wof:name":"EH45 8RW",
    "wof:placetype":"postalcode"
},
  "geometry": {"coordinates":[-3.19018030378988,55.65225975991136],"type":"Point"}
}