{
  "type": "Feature",
  "properties": {
    "date:inception_lower": "1980-01-01",
    "date:inception_upper": "1980-01-01",
    "iso:country": "GB",
    "wof:name": "SK8 2BD",
    "wof:placetype": "postalcode"
  },
  "geometry": {"coordinates":[-2.212422,53.395787],"type":"Point"}
}
