{
  "type": "Feature",
  "properties": {
    "iso:country":"GB",
    "wof:name":"PA3 3BU",
    "wof:placetype":"postalcode"
},
  "geometry": {"coordinates":[-4.48609140858847,55.84281091387824],"type":"Point"}
}