{
  "type": "Feature",
  "properties": {
    "date:inception_lower": "1998-12-01",
    "date:inception_upper": "1998-12-01",
    "iso:country": "GB",
    "wof:name": "KY11 9YW",
    "wof:placetype": "postalcode"
  },
  "geometry": {"coordinates":[-3.365032,56.029606],"type":"Point"}
}
