{
  "type": "Feature",
  "properties": {
    "iso:country":"GB",
    "wof:name":"SL1 3AE",
    "wof:placetype":"postalcode"
},
  "geometry": {"coordinates":[-0.61343816986726,51.52630238470329],"type":"Point"}
}