{
  "type": "Feature",
  "properties": {
    "date:inception_lower": "1980-01-01",
    "date:inception_upper": "1980-01-01",
    "iso:country": "GB",
    "wof:name": "SL1 3AE",
    "wof:placetype": "postalcode"
  },
  "geometry": {"coordinates":[-0.613438,51.526302],"type":"Point"}
}
