{
  "type": "Feature",
  "properties": {
    "iso:country":"GB",
    "wof:name":"PL11 2PY",
    "wof:placetype":"postalcode"
},
  "geometry": {"coordinates":[-4.22091561894328,50.37895049407531],"type":"Point"}
}