{
  "type": "Feature",
  "properties": {
    "date:inception_lower": "1981-06-01",
    "date:inception_upper": "1981-06-01",
    "iso:country": "GB",
    "wof:name": "PL11 2PY",
    "wof:placetype": "postalcode"
  },
  "geometry": {"coordinates":[-4.220916,50.37895],"type":"Point"}
}
