{
  "type": "Feature",
  "properties": {
    "date:inception_lower": "1980-01-01",
    "date:inception_upper": "1980-01-01",
    "iso:country": "GB",
    "wof:name": "LE15 6QT",
    "wof:placetype": "postalcode"
  },
  "geometry": {"coordinates":[-0.730984,52.672621],"type":"Point"}
}
