{
  "type": "Feature",
  "properties": {
    "iso:country":"GB",
    "wof:name":"LE15 6QT",
    "wof:placetype":"postalcode"
},
  "geometry": {"coordinates":[-0.73095320303341,52.67251140721095],"type":"Point"}
}