{
  "type": "Feature",
  "properties": {
    "iso:country": "GB",
    "wof:name": "LE15 6QT",
    "wof:placetype": "postalcode"
  },
  "geometry": {"coordinates":[-0.730984,52.672621],"type":"Point"}
}
