{
  "type": "Feature",
  "properties": {
    "iso:country": "GB",
    "wof:name": "RG45 6GT",
    "wof:placetype": "postalcode"
  },
  "geometry": {"coordinates":[-0.804155,51.369073],"type":"Point"}
}
