{
  "type": "Feature",
  "properties": {
    "date:inception_lower":"2014-06-01",
    "date:inception_upper":"2014-06-30",
    "iso:country":"GB",
    "wof:name":"KT16 8FE",
    "wof:placetype":"postalcode"
},
  "geometry": {"coordinates":[-0.491223,51.386611],"type":"Point"}
}