{
  "type": "Feature",
  "properties": {
    "iso:country":"GB",
    "wof:name":"KT16 8FE",
    "wof:placetype":"postalcode"
},
  "geometry": {"coordinates":[-0.49122321508675,51.38661079919887],"type":"Point"}
}