{
  "type": "Feature",
  "properties": {
    "iso:country": "GB",
    "wof:name": "KT16 8FE",
    "wof:placetype": "postalcode"
  },
  "geometry": {"coordinates":[-0.491223,51.386611],"type":"Point"}
}
