{
  "type": "Feature",
  "properties": {
    "iso:country": "GB",
    "wof:name": "CM20 2GD",
    "wof:placetype": "postalcode"
  },
  "geometry": {"coordinates":[0.12612,51.783354],"type":"Point"}
}
