{
  "type": "Feature",
  "properties": {
    "date:inception_lower":"2006-04-01",
    "date:inception_upper":"2006-04-30",
    "iso:country":"GB",
    "wof:name":"CM20 2GD",
    "wof:placetype":"postalcode"
},
  "geometry": {"coordinates":[0.12612,51.783354],"type":"Point"}
}