{
  "type": "Feature",
  "properties": {
    "iso:country":"GB",
    "wof:name":"CM20 2GD",
    "wof:placetype":"postalcode"
},
  "geometry": {"coordinates":[0.126119535597,51.78335382950595],"type":"Point"}
}