{
  "type": "Feature",
  "properties": {
    "iso:country": "GB",
    "wof:name": "NP19 4DP",
    "wof:placetype": "postalcode"
  },
  "geometry": {"coordinates":[-2.938801,51.578455],"type":"Point"}
}
