{
  "type": "Feature",
  "properties": {
    "date:inception_lower": "1980-01-01",
    "date:inception_upper": "1980-01-01",
    "iso:country": "GB",
    "wof:name": "TN12 8HU",
    "wof:placetype": "postalcode"
  },
  "geometry": {"coordinates":[0.428515,51.138977],"type":"Point"}
}
