{
  "type": "Feature",
  "properties": {
    "iso:country": "GB",
    "wof:name": "TS10 2UF",
    "wof:placetype": "postalcode"
  },
  "geometry": {"coordinates":[-1.044377,54.592216],"type":"Point"}
}
