{
  "type": "Feature",
  "properties": {
    "iso:country":"GB",
    "wof:name":"LE7 7BB",
    "wof:placetype":"postalcode"
},
  "geometry": {"coordinates":[-1.18397947098232,52.67739421821798],"type":"Point"}
}