{
  "type": "Feature",
  "properties": {
    "date:inception_lower": "1980-01-01",
    "date:inception_upper": "1980-01-01",
    "iso:country": "GB",
    "wof:name": "SN11 9BB",
    "wof:placetype": "postalcode"
  },
  "geometry": {"coordinates":[-2.001088,51.445396],"type":"Point"}
}
