{
  "type": "Feature",
  "properties": {
    "iso:country":"GB",
    "wof:name":"SN11 9BB",
    "wof:placetype":"postalcode"
},
  "geometry": {"coordinates":[-2.00108791478761,51.44539644192929],"type":"Point"}
}