{
  "type": "Feature",
  "properties": {
    "iso:country":"GB",
    "wof:name":"PH1 5BT",
    "wof:placetype":"postalcode"
},
  "geometry": {"coordinates":[-3.44772229899625,56.40888243069688],"type":"Point"}
}