{
  "type": "Feature",
  "properties": {
    "iso:country":"GB",
    "wof:name":"MK2 2HY",
    "wof:placetype":"postalcode"
},
  "geometry": {"coordinates":[-0.71465195640696,51.99414527006265],"type":"Point"}
}