{
  "type": "Feature",
  "properties": {
    "date:inception_lower": "1980-01-01",
    "date:inception_upper": "1980-01-01",
    "iso:country": "GB",
    "wof:name": "MK2 2HY",
    "wof:placetype": "postalcode"
  },
  "geometry": {"coordinates":[-0.714633,51.994083],"type":"Point"}
}
