{
  "type": "Feature",
  "properties": {
    "date:inception_lower":"1990-02-01",
    "date:inception_upper":"1990-02-28",
    "iso:country":"GB",
    "wof:name":"SE10 0PU",
    "wof:placetype":"postalcode"
},
  "geometry": {"coordinates":[0.005776,51.494669],"type":"Point"}
}