{
  "type": "Feature",
  "properties": {
    "iso:country": "GB",
    "wof:name": "SE10 0PU",
    "wof:placetype": "postalcode"
  },
  "geometry": {"coordinates":[0.005776,51.494669],"type":"Point"}
}
