{
  "type": "Feature",
  "properties": {
    "iso:country":"GB",
    "wof:name":"SE10 0PU",
    "wof:placetype":"postalcode"
},
  "geometry": {"coordinates":[0.00577599018663,51.49466923896347],"type":"Point"}
}