{
  "type": "Feature",
  "properties": {
    "date:inception_lower": "2013-08-01",
    "date:inception_upper": "2013-08-01",
    "iso:country": "GB",
    "wof:name": "S44 5FA",
    "wof:placetype": "postalcode"
  },
  "geometry": {"coordinates":[-1.358559,53.233616],"type":"Point"}
}
