{
  "type": "Feature",
  "properties": {
    "iso:country":"GB",
    "wof:name":"S44 5FA",
    "wof:placetype":"postalcode"
},
  "geometry": {"coordinates":[-1.35855864102692,53.23361558818362],"type":"Point"}
}