{
  "type": "Feature",
  "properties": {
    "iso:country":"GB",
    "wof:name":"BN8 4EF",
    "wof:placetype":"postalcode"
},
  "geometry": {"coordinates":[-0.03048568243484,50.97201614977273],"type":"Point"}
}