{
  "type": "Feature",
  "properties": {
    "date:inception_lower":"1983-07-01",
    "date:inception_upper":"1983-07-31",
    "iso:country":"GB",
    "wof:name":"BN8 4EF",
    "wof:placetype":"postalcode"
},
  "geometry": {"coordinates":[-0.030486,50.972016],"type":"Point"}
}