{
  "type": "Feature",
  "properties": {
    "iso:country":"GB",
    "wof:name":"SK10 4XB",
    "wof:placetype":"postalcode"
},
  "geometry": {"coordinates":[-2.14652938644682,53.28367214765701],"type":"Point"}
}