{
  "type": "Feature",
  "properties": {
    "iso:country":"GB",
    "wof:name":"HP13 7BJ",
    "wof:placetype":"postalcode"
},
  "geometry": {"coordinates":[-0.70265859928416,51.61538928227632],"type":"Point"}
}