{
  "type": "Feature",
  "properties": {
    "iso:country": "GB",
    "wof:name": "DG3 5LW",
    "wof:placetype": "postalcode"
  },
  "geometry": {"coordinates":[-3.770019,55.244617],"type":"Point"}
}
