{
  "type": "Feature",
  "properties": {
    "date:inception_lower": "1980-01-01",
    "date:inception_upper": "1980-01-01",
    "iso:country": "GB",
    "wof:name": "DG3 5LW",
    "wof:placetype": "postalcode"
  },
  "geometry": {"coordinates":[-3.77041,55.244908],"type":"Point"}
}
