{
  "type": "Feature",
  "properties": {
    "iso:country":"GB",
    "wof:name":"G77 6FH",
    "wof:placetype":"postalcode"
},
  "geometry": {"coordinates":[-4.35284971003213,55.77004315904824],"type":"Point"}
}