{
  "type": "Feature",
  "properties": {
    "date:inception_lower": "2008-12-01",
    "date:inception_upper": "2008-12-01",
    "iso:country": "GB",
    "wof:name": "G77 6FH",
    "wof:placetype": "postalcode"
  },
  "geometry": {"coordinates":[-4.35285,55.770043],"type":"Point"}
}
