{
  "type": "Feature",
  "properties": {
    "iso:country":"GB",
    "wof:name":"TR14 8BH",
    "wof:placetype":"postalcode"
},
  "geometry": {"coordinates":[-5.2962475482691,50.21592814784703],"type":"Point"}
}