{
  "type": "Feature",
  "properties": {
    "date:inception_lower":"2008-04-01",
    "date:inception_upper":"2008-04-30",
    "iso:country":"GB",
    "wof:name":"TA20 2FD",
    "wof:placetype":"postalcode"
},
  "geometry": {"coordinates":[-2.959538,50.868166],"type":"Point"}
}