{
  "type": "Feature",
  "properties": {
    "date:inception_lower": "2005-07-01",
    "date:inception_upper": "2005-07-01",
    "iso:country": "GB",
    "wof:name": "CA10 1BN",
    "wof:placetype": "postalcode"
  },
  "geometry": {"coordinates":[-2.705385,54.749641],"type":"Point"}
}
