{
  "type": "Feature",
  "properties": {
    "iso:country":"GB",
    "wof:name":"CA10 1BN",
    "wof:placetype":"postalcode"
},
  "geometry": {"coordinates":[-2.70538540522647,54.74964069397262],"type":"Point"}
}