{
  "type": "Feature",
  "properties": {
    "date:inception_lower": "1990-07-01",
    "date:inception_upper": "1990-07-01",
    "iso:country": "GB",
    "wof:name": "PL25 5DG",
    "wof:placetype": "postalcode"
  },
  "geometry": {"coordinates":[-4.803288,50.337606],"type":"Point"}
}
