{
  "type": "Feature",
  "properties": {
    "iso:country": "GB",
    "wof:name": "PL25 5DG",
    "wof:placetype": "postalcode"
  },
  "geometry": {"coordinates":[-4.803288,50.337606],"type":"Point"}
}
