{
  "type": "Feature",
  "properties": {
    "date:inception_lower": "1980-01-01",
    "date:inception_upper": "1980-01-01",
    "iso:country": "GB",
    "wof:name": "CF34 0NL",
    "wof:placetype": "postalcode"
  },
  "geometry": {"coordinates":[-3.642449,51.603733],"type":"Point"}
}
