{
  "type": "Feature",
  "properties": {
    "iso:country":"GB",
    "wof:name":"UB2 4RS",
    "wof:placetype":"postalcode"
},
  "geometry": {"coordinates":[-0.37318745773452,51.50245376568516],"type":"Point"}
}