{
  "type": "Feature",
  "properties": {
    "date:inception_lower": "1980-01-01",
    "date:inception_upper": "1980-01-01",
    "iso:country": "GB",
    "wof:name": "DY5 1AU",
    "wof:placetype": "postalcode"
  },
  "geometry": {"coordinates":[-2.098656,52.477778],"type":"Point"}
}
