{
  "type": "Feature",
  "properties": {
    "iso:country":"GB",
    "wof:name":"NG2 7TH",
    "wof:placetype":"postalcode"
},
  "geometry": {"coordinates":[-1.15545163935276,52.91922504092903],"type":"Point"}
}