{
  "type": "Feature",
  "properties": {
    "iso:country": "GB",
    "wof:name": "CW9 7HW",
    "wof:placetype": "postalcode"
  },
  "geometry": {"coordinates":[-2.491687,53.24999],"type":"Point"}
}
