{
  "type": "Feature",
  "properties": {
    "iso:country": "GB",
    "wof:name": "MK41 0JU",
    "wof:placetype": "postalcode"
  },
  "geometry": {"coordinates":[-0.427222,52.161018],"type":"Point"}
}
