{
  "type": "Feature",
  "properties": {
    "date:inception_lower": "2018-11-01",
    "date:inception_upper": "2018-11-01",
    "iso:country": "GB",
    "wof:name": "WS13 8LY",
    "wof:placetype": "postalcode"
  },
  "geometry": {"coordinates":[-1.79785,52.691139],"type":"Point"}
}
