{
  "type": "Feature",
  "properties": {
    "date:inception_lower":"2018-11-01",
    "date:inception_upper":"2018-11-30",
    "iso:country":"GB",
    "wof:name":"WS13 8LY",
    "wof:placetype":"postalcode"
},
  "geometry": {"coordinates":[-1.797806,52.691058],"type":"Point"}
}