{
  "type": "Feature",
  "properties": {
    "iso:country": "GB",
    "wof:name": "WS13 8LY",
    "wof:placetype": "postalcode"
  },
  "geometry": {"coordinates":[-1.797806,52.691058],"type":"Point"}
}
