{
  "type": "Feature",
  "properties": {
    "iso:country": "GB",
    "wof:name": "DG6 4JR",
    "wof:placetype": "postalcode"
  },
  "geometry": {"coordinates":[-4.054722,54.834717],"type":"Point"}
}
