{
  "type": "Feature",
  "properties": {
    "iso:country":"GB",
    "wof:name":"AB22 8UY",
    "wof:placetype":"postalcode"
},
  "geometry": {"coordinates":[-2.11387990617225,57.18404133025409],"type":"Point"}
}