{
  "type": "Feature",
  "properties": {
    "date:inception_lower": "1990-08-01",
    "date:inception_upper": "1990-08-01",
    "iso:country": "GB",
    "wof:name": "AB22 8UY",
    "wof:placetype": "postalcode"
  },
  "geometry": {"coordinates":[-2.11388,57.184041],"type":"Point"}
}
