{
  "type": "Feature",
  "properties": {
    "iso:country":"GB",
    "wof:name":"SW19 3HA",
    "wof:placetype":"postalcode"
},
  "geometry": {"coordinates":[-0.2013978416588,51.41306841302274],"type":"Point"}
}