{
  "type": "Feature",
  "properties": {
    "iso:country":"GB",
    "wof:name":"CA13 0JU",
    "wof:placetype":"postalcode"
},
  "geometry": {"coordinates":[-3.38000442184297,54.6703484715585],"type":"Point"}
}