{
  "type": "Feature",
  "properties": {
    "date:inception_lower":"1980-01-01",
    "date:inception_upper":"1980-01-31",
    "iso:country":"GB",
    "wof:name":"CA13 0JU",
    "wof:placetype":"postalcode"
},
  "geometry": {"coordinates":[-3.380004,54.670348],"type":"Point"}
}