{
  "type": "Feature",
  "properties": {
    "iso:country": "GB",
    "wof:name": "GL1 1PD",
    "wof:placetype": "postalcode"
  },
  "geometry": {"coordinates":[-2.245801,51.865064],"type":"Point"}
}
