{
  "type": "Feature",
  "properties": {
    "iso:country": "GB",
    "wof:name": "LS23 6BR",
    "wof:placetype": "postalcode"
  },
  "geometry": {"coordinates":[-1.347409,53.905003],"type":"Point"}
}
