{
  "type": "Feature",
  "properties": {
    "iso:country":"GB",
    "wof:name":"BL4 8NX",
    "wof:placetype":"postalcode"
},
  "geometry": {"coordinates":[-2.37584548038029,53.54089942475636],"type":"Point"}
}