{
  "type": "Feature",
  "properties": {
    "iso:country": "GB",
    "wof:name": "G44 3TA",
    "wof:placetype": "postalcode"
  },
  "geometry": {"coordinates":[-4.273579,55.801545],"type":"Point"}
}
