{
  "type": "Feature",
  "properties": {
    "iso:country":"GB",
    "wof:name":"BD15 7TA",
    "wof:placetype":"postalcode"
},
  "geometry": {"coordinates":[-1.82845289003085,53.79836664199858],"type":"Point"}
}