{
  "type": "Feature",
  "properties": {
    "iso:country":"GB",
    "wof:name":"SW4 0PN",
    "wof:placetype":"postalcode"
},
  "geometry": {"coordinates":[-0.14984298737966,51.46258844748929],"type":"Point"}
}