{
  "type": "Feature",
  "properties": {
    "iso:country": "GB",
    "wof:name": "TS7 9HA",
    "wof:placetype": "postalcode"
  },
  "geometry": {"coordinates":[-1.172155,54.542268],"type":"Point"}
}
