{
  "type": "Feature",
  "properties": {
    "iso:country":"GB",
    "wof:name":"TS7 9HA",
    "wof:placetype":"postalcode"
},
  "geometry": {"coordinates":[-1.1721554387735,54.54226801175159],"type":"Point"}
}