{
  "type": "Feature",
  "properties": {
    "iso:country":"GB",
    "wof:name":"FK13 6LE",
    "wof:placetype":"postalcode"
},
  "geometry": {"coordinates":[-3.74319944359705,56.14090527578252],"type":"Point"}
}