{
  "type": "Feature",
  "properties": {
    "date:inception_lower": "1980-01-01",
    "date:inception_upper": "1980-01-01",
    "iso:country": "GB",
    "wof:name": "DY13 8JT",
    "wof:placetype": "postalcode"
  },
  "geometry": {"coordinates":[-2.283312,52.350129],"type":"Point"}
}
