{
  "type": "Feature",
  "properties": {
    "iso:country": "GB",
    "wof:name": "HD8 9XB",
    "wof:placetype": "postalcode"
  },
  "geometry": {"coordinates":[-1.619155,53.593431],"type":"Point"}
}
