{
  "type": "Feature",
  "properties": {
    "iso:country":"GB",
    "wof:name":"HD8 9XB",
    "wof:placetype":"postalcode"
},
  "geometry": {"coordinates":[-1.61915507630931,53.59343123654506],"type":"Point"}
}