{
  "type": "Feature",
  "properties": {
    "iso:country": "GB",
    "wof:name": "CB22 3BG",
    "wof:placetype": "postalcode"
  },
  "geometry": {"coordinates":[0.169469,52.123104],"type":"Point"}
}
