{
  "type": "Feature",
  "properties": {
    "iso:country":"GB",
    "wof:name":"CB22 3BG",
    "wof:placetype":"postalcode"
},
  "geometry": {"coordinates":[0.16948007414638,52.12300138196614],"type":"Point"}
}