{
  "type": "Feature",
  "properties": {
    "iso:country":"GB",
    "wof:name":"CV6 5GX",
    "wof:placetype":"postalcode"
},
  "geometry": {"coordinates":[-1.48943128749174,52.4273305499288],"type":"Point"}
}