{
  "type": "Feature",
  "properties": {
    "iso:country": "GB",
    "wof:name": "TF2 8EG",
    "wof:placetype": "postalcode"
  },
  "geometry": {"coordinates":[-2.431039,52.716595],"type":"Point"}
}
