{
  "type": "Feature",
  "properties": {
    "date:inception_lower": "2017-11-01",
    "date:inception_upper": "2017-11-01",
    "iso:country": "GB",
    "wof:name": "TF2 8EG",
    "wof:placetype": "postalcode"
  },
  "geometry": {"coordinates":[-2.431039,52.716595],"type":"Point"}
}
