{
  "type": "Feature",
  "properties": {
    "iso:country": "GB",
    "wof:name": "BS20 0QR",
    "wof:placetype": "postalcode"
  },
  "geometry": {"coordinates":[-2.689199,51.46824],"type":"Point"}
}
