{
  "type": "Feature",
  "properties": {
    "iso:country":"GB",
    "wof:name":"BS20 0QR",
    "wof:placetype":"postalcode"
},
  "geometry": {"coordinates":[-2.68919950573571,51.46824020307446],"type":"Point"}
}