{
  "type": "Feature",
  "properties": {
    "iso:country": "GB",
    "wof:name": "BH23 8BT",
    "wof:placetype": "postalcode"
  },
  "geometry": {"coordinates":[-1.742735,50.781956],"type":"Point"}
}
