{
  "type": "Feature",
  "properties": {
    "date:inception_lower": "2018-05-01",
    "date:inception_upper": "2018-05-01",
    "iso:country": "GB",
    "wof:name": "PL14 5FJ",
    "wof:placetype": "postalcode"
  },
  "geometry": {"coordinates":[-4.469855,50.48886],"type":"Point"}
}
