{
  "type": "Feature",
  "properties": {
    "iso:country": "GB",
    "wof:name": "KT2 5BT",
    "wof:placetype": "postalcode"
  },
  "geometry": {"coordinates":[-0.301801,51.417516],"type":"Point"}
}
