{
  "type": "Feature",
  "properties": {
    "iso:country":"GB",
    "wof:name":"G81 2EZ",
    "wof:placetype":"postalcode"
},
  "geometry": {"coordinates":[-4.39005705212147,55.90967840262881],"type":"Point"}
}