{
  "type": "Feature",
  "properties": {
    "date:inception_lower": "1980-01-01",
    "date:inception_upper": "1980-01-01",
    "iso:country": "GB",
    "wof:name": "G81 2EZ",
    "wof:placetype": "postalcode"
  },
  "geometry": {"coordinates":[-4.390057,55.909678],"type":"Point"}
}
