{
  "type": "Feature",
  "properties": {
    "iso:country":"GB",
    "wof:name":"NG2 5BP",
    "wof:placetype":"postalcode"
},
  "geometry": {"coordinates":[-1.11921492882713,52.93930539665348],"type":"Point"}
}