{
  "type": "Feature",
  "properties": {
    "date:inception_lower": "1980-01-01",
    "date:inception_upper": "1980-01-01",
    "iso:country": "GB",
    "wof:name": "TF1 3NQ",
    "wof:placetype": "postalcode"
  },
  "geometry": {"coordinates":[-2.532851,52.704857],"type":"Point"}
}
