{
  "type": "Feature",
  "properties": {
    "iso:country":"GB",
    "wof:name":"TF1 3NQ",
    "wof:placetype":"postalcode"
},
  "geometry": {"coordinates":[-2.53285083581247,52.70485685885096],"type":"Point"}
}