{
  "type": "Feature",
  "properties": {
    "date:inception_lower": "1980-01-01",
    "date:inception_upper": "1980-01-01",
    "iso:country": "GB",
    "wof:name": "NG2 7HW",
    "wof:placetype": "postalcode"
  },
  "geometry": {"coordinates":[-1.137595,52.921164],"type":"Point"}
}
