{
  "type": "Feature",
  "properties": {
    "iso:country":"GB",
    "wof:name":"NG2 7HW",
    "wof:placetype":"postalcode"
},
  "geometry": {"coordinates":[-1.13759515279596,52.92116441182079],"type":"Point"}
}