{
  "type": "Feature",
  "properties": {
    "iso:country":"GB",
    "wof:name":"LL54 5TY",
    "wof:placetype":"postalcode"
},
  "geometry": {"coordinates":[-4.27800045531456,53.11470595189345],"type":"Point"}
}