{
  "type": "Feature",
  "properties": {
    "date:inception_lower": "1980-01-01",
    "date:inception_upper": "1980-01-01",
    "iso:country": "GB",
    "wof:name": "LL54 5TY",
    "wof:placetype": "postalcode"
  },
  "geometry": {"coordinates":[-4.278,53.114706],"type":"Point"}
}
