{
  "type": "Feature",
  "properties": {
    "iso:country":"GB",
    "wof:name":"SE15 6HF",
    "wof:placetype":"postalcode"
},
  "geometry": {"coordinates":[-0.08096023847376,51.47968225203437],"type":"Point"}
}