{
  "type": "Feature",
  "properties": {
    "date:inception_lower": "2004-08-01",
    "date:inception_upper": "2004-08-01",
    "iso:country": "GB",
    "wof:name": "SE15 6HF",
    "wof:placetype": "postalcode"
  },
  "geometry": {"coordinates":[-0.08096,51.479682],"type":"Point"}
}
