{
  "type": "Feature",
  "properties": {
    "date:inception_lower":"1980-09-01",
    "date:inception_upper":"1980-09-30",
    "iso:country":"GB",
    "wof:name":"EH54 7BE",
    "wof:placetype":"postalcode"
},
  "geometry": {"coordinates":[-3.541246,55.888427],"type":"Point"}
}