{
  "type": "Feature",
  "properties": {
    "date:inception_lower":"2015-02-01",
    "date:inception_upper":"2015-02-28",
    "iso:country":"GB",
    "wof:name":"DH2 2FD",
    "wof:placetype":"postalcode"
},
  "geometry": {"coordinates":[-1.617538,54.866684],"type":"Point"}
}