{
  "type": "Feature",
  "properties": {
    "date:inception_lower": "2015-02-01",
    "date:inception_upper": "2015-02-01",
    "iso:country": "GB",
    "wof:name": "DH2 2FD",
    "wof:placetype": "postalcode"
  },
  "geometry": {"coordinates":[-1.617926,54.866892],"type":"Point"}
}
