{
  "type": "Feature",
  "properties": {
    "iso:country":"GB",
    "wof:name":"TA20 1BP",
    "wof:placetype":"postalcode"
},
  "geometry": {"coordinates":[-2.95945355695806,50.8799559334517],"type":"Point"}
}