{
  "type": "Feature",
  "properties": {
    "iso:country": "GB",
    "wof:name": "L14 9LU",
    "wof:placetype": "postalcode"
  },
  "geometry": {"coordinates":[-2.875159,53.421739],"type":"Point"}
}
