{
  "type": "Feature",
  "properties": {
    "iso:country":"GB",
    "wof:name":"L14 9LU",
    "wof:placetype":"postalcode"
},
  "geometry": {"coordinates":[-2.87515900849763,53.42173867606571],"type":"Point"}
}