{
  "type": "Feature",
  "properties": {
    "date:inception_lower":"1980-01-01",
    "date:inception_upper":"1980-01-31",
    "iso:country":"GB",
    "wof:name":"B17 9EW",
    "wof:placetype":"postalcode"
},
  "geometry": {"coordinates":[-1.957463,52.463746],"type":"Point"}
}