{
  "type": "Feature",
  "properties": {
    "iso:country":"GB",
    "wof:name":"B17 9EW",
    "wof:placetype":"postalcode"
},
  "geometry": {"coordinates":[-1.9574633167474,52.46374578135462],"type":"Point"}
}