{
  "type": "Feature",
  "properties": {
    "iso:country":"GB",
    "wof:name":"SY23 4PZ",
    "wof:placetype":"postalcode"
},
  "geometry": {"coordinates":[-4.08700170196491,52.39361420054875],"type":"Point"}
}