{
  "type": "Feature",
  "properties": {
    "date:inception_lower":"2013-03-01",
    "date:inception_upper":"2013-03-31",
    "iso:country":"GB",
    "wof:name":"SY23 4PZ",
    "wof:placetype":"postalcode"
},
  "geometry": {"coordinates":[-4.087002,52.393614],"type":"Point"}
}