{
  "type": "Feature",
  "properties": {
    "iso:country":"GB",
    "wof:name":"CF14 1RU",
    "wof:placetype":"postalcode"
},
  "geometry": {"coordinates":[-3.20452834938929,51.50986457808375],"type":"Point"}
}