{
  "type": "Feature",
  "properties": {
    "iso:country": "GB",
    "wof:name": "SY20 8AH",
    "wof:placetype": "postalcode"
  },
  "geometry": {"coordinates":[-3.843531,52.588896],"type":"Point"}
}
