{
  "type": "Feature",
  "properties": {
    "date:inception_lower":"1994-05-01",
    "date:inception_upper":"1994-05-31",
    "iso:country":"GB",
    "wof:name":"SY20 8AH",
    "wof:placetype":"postalcode"
},
  "geometry": {"coordinates":[-3.843531,52.588896],"type":"Point"}
}