{
  "type": "Feature",
  "properties": {
    "iso:country":"GB",
    "wof:name":"PO8 8AU",
    "wof:placetype":"postalcode"
},
  "geometry": {"coordinates":[-1.00847250593321,50.89414357521997],"type":"Point"}
}