{
  "type": "Feature",
  "properties": {
    "date:inception_lower": "2000-12-01",
    "date:inception_upper": "2000-12-01",
    "iso:country": "GB",
    "wof:name": "DH5 8QA",
    "wof:placetype": "postalcode"
  },
  "geometry": {"coordinates":[-1.460646,54.834987],"type":"Point"}
}
