{
  "type": "Feature",
  "properties": {
    "iso:country": "GB",
    "wof:name": "BA3 5GT",
    "wof:placetype": "postalcode"
  },
  "geometry": {"coordinates":[-2.481749,51.221886],"type":"Point"}
}
