{
  "type": "Feature",
  "properties": {
    "iso:country":"GB",
    "wof:name":"SE1 3RF",
    "wof:placetype":"postalcode"
},
  "geometry": {"coordinates":[-0.08623544526939,51.50125179409539],"type":"Point"}
}