{
  "type": "Feature",
  "properties": {
    "iso:country": "GB",
    "wof:name": "CH4 7LW",
    "wof:placetype": "postalcode"
  },
  "geometry": {"coordinates":[-2.892769,53.182429],"type":"Point"}
}
