{
  "type": "Feature",
  "properties": {
    "iso:country": "GB",
    "wof:name": "LN4 1NJ",
    "wof:placetype": "postalcode"
  },
  "geometry": {"coordinates":[-0.473093,53.18109],"type":"Point"}
}
