{
  "type": "Feature",
  "properties": {
    "iso:country":"GB",
    "wof:name":"LN4 1NJ",
    "wof:placetype":"postalcode"
},
  "geometry": {"coordinates":[-0.47309258561654,53.18109046130555],"type":"Point"}
}