{
  "type": "Feature",
  "properties": {
    "iso:country":"GB",
    "wof:name":"OX2 9DE",
    "wof:placetype":"postalcode"
},
  "geometry": {"coordinates":[-1.31420401515522,51.74706996705557],"type":"Point"}
}