{
  "type": "Feature",
  "properties": {
    "iso:country":"GB",
    "wof:name":"LL68 9NA",
    "wof:placetype":"postalcode"
},
  "geometry": {"coordinates":[-4.3080478075849,53.39827355360967],"type":"Point"}
}