{
  "type": "Feature",
  "properties": {
    "date:inception_lower": "1980-01-01",
    "date:inception_upper": "1980-01-01",
    "iso:country": "GB",
    "wof:name": "LL68 9NA",
    "wof:placetype": "postalcode"
  },
  "geometry": {"coordinates":[-4.308048,53.398274],"type":"Point"}
}
