{
  "type": "Feature",
  "properties": {
    "iso:country": "GB",
    "wof:name": "LA2 8PF",
    "wof:placetype": "postalcode"
  },
  "geometry": {"coordinates":[-2.570372,54.115672],"type":"Point"}
}
