{
  "type": "Feature",
  "properties": {
    "iso:country":"GB",
    "wof:name":"LA2 8PF",
    "wof:placetype":"postalcode"
},
  "geometry": {"coordinates":[-2.57037007317534,54.11566094294842],"type":"Point"}
}