{
  "type": "Feature",
  "properties": {
    "date:inception_lower": "1980-01-01",
    "date:inception_upper": "1980-01-01",
    "iso:country": "GB",
    "wof:name": "LA2 8PF",
    "wof:placetype": "postalcode"
  },
  "geometry": {"coordinates":[-2.571152,54.116783],"type":"Point"}
}
