{
  "type": "Feature",
  "properties": {
    "iso:country":"GB",
    "wof:name":"SM6 9NS",
    "wof:placetype":"postalcode"
},
  "geometry": {"coordinates":[-0.1442693661127,51.35254724509775],"type":"Point"}
}