{
  "type": "Feature",
  "properties": {
    "iso:country": "GB",
    "wof:name": "SM6 9NS",
    "wof:placetype": "postalcode"
  },
  "geometry": {"coordinates":[-0.144269,51.352547],"type":"Point"}
}
