{
  "type": "Feature",
  "properties": {
    "date:inception_lower": "1980-01-01",
    "date:inception_upper": "1980-01-01",
    "iso:country": "GB",
    "wof:name": "L23 6SP",
    "wof:placetype": "postalcode"
  },
  "geometry": {"coordinates":[-3.045892,53.483655],"type":"Point"}
}
