{
  "type": "Feature",
  "properties": {
    "date:inception_lower": "1980-01-01",
    "date:inception_upper": "1980-01-01",
    "iso:country": "GB",
    "wof:name": "NE5 1YB",
    "wof:placetype": "postalcode"
  },
  "geometry": {"coordinates":[-1.720713,55.004842],"type":"Point"}
}
