{
  "type": "Feature",
  "properties": {
    "iso:country":"GB",
    "wof:name":"NE5 1YB",
    "wof:placetype":"postalcode"
},
  "geometry": {"coordinates":[-1.72071299167136,55.00484202727417],"type":"Point"}
}