{
  "type": "Feature",
  "properties": {
    "iso:country":"GB",
    "wof:name":"TN1 2EJ",
    "wof:placetype":"postalcode"
},
  "geometry": {"coordinates":[0.27311440800339,51.14621168641585],"type":"Point"}
}