{
  "type": "Feature",
  "properties": {
    "iso:country":"GB",
    "wof:name":"WV3 7NW",
    "wof:placetype":"postalcode"
},
  "geometry": {"coordinates":[-2.16778966796838,52.57095552118123],"type":"Point"}
}