{
  "type": "Feature",
  "properties": {
    "iso:country":"GB",
    "wof:name":"SA45 9PQ",
    "wof:placetype":"postalcode"
},
  "geometry": {"coordinates":[-4.36142816454548,52.21583441594025],"type":"Point"}
}