{
  "type": "Feature",
  "properties": {
    "iso:country": "GB",
    "wof:name": "SA45 9PQ",
    "wof:placetype": "postalcode"
  },
  "geometry": {"coordinates":[-4.361449,52.215903],"type":"Point"}
}
