{
  "type": "Feature",
  "properties": {
    "date:inception_lower": "1980-01-01",
    "date:inception_upper": "1980-01-01",
    "iso:country": "GB",
    "wof:name": "PR9 0JX",
    "wof:placetype": "postalcode"
  },
  "geometry": {"coordinates":[-2.991043,53.658127],"type":"Point"}
}
