{
  "type": "Feature",
  "properties": {
    "iso:country":"GB",
    "wof:name":"PR9 0JX",
    "wof:placetype":"postalcode"
},
  "geometry": {"coordinates":[-2.99104333175215,53.65812677338134],"type":"Point"}
}