{
  "type": "Feature",
  "properties": {
    "iso:country": "GB",
    "wof:name": "NG7 3AZ",
    "wof:placetype": "postalcode"
  },
  "geometry": {"coordinates":[-1.175373,52.958829],"type":"Point"}
}
