{
  "type": "Feature",
  "properties": {
    "iso:country":"GB",
    "wof:name":"NG7 3AZ",
    "wof:placetype":"postalcode"
},
  "geometry": {"coordinates":[-1.17537285066458,52.95882888092376],"type":"Point"}
}