{
  "type": "Feature",
  "properties": {
    "date:inception_lower": "1980-01-01",
    "date:inception_upper": "1980-01-01",
    "iso:country": "GB",
    "wof:name": "PR7 2DT",
    "wof:placetype": "postalcode"
  },
  "geometry": {"coordinates":[-2.635406,53.646647],"type":"Point"}
}
