{
  "type": "Feature",
  "properties": {
    "iso:country":"GB",
    "wof:name":"PR7 2DT",
    "wof:placetype":"postalcode"
},
  "geometry": {"coordinates":[-2.6354062899772,53.64664688436039],"type":"Point"}
}