{
  "type": "Feature",
  "properties": {
    "date:inception_lower": "1998-12-01",
    "date:inception_upper": "1998-12-01",
    "iso:country": "GB",
    "wof:name": "EC2M 6XQ",
    "wof:placetype": "postalcode"
  },
  "geometry": {"coordinates":[-0.088074,51.518943],"type":"Point"}
}
