{
  "type": "Feature",
  "properties": {
    "iso:country":"GB",
    "wof:name":"EC2M 6XQ",
    "wof:placetype":"postalcode"
},
  "geometry": {"coordinates":[-0.08807400686593,51.51894319366463],"type":"Point"}
}