{
  "type": "Feature",
  "properties": {
    "iso:country": "GB",
    "wof:name": "EC2M 6XQ",
    "wof:placetype": "postalcode"
  },
  "geometry": {"coordinates":[-0.088074,51.518943],"type":"Point"}
}
