{
  "type": "Feature",
  "properties": {
    "date:inception_lower":"2005-01-01",
    "date:inception_upper":"2005-01-31",
    "iso:country":"GB",
    "wof:name":"RG27 9TX",
    "wof:placetype":"postalcode"
},
  "geometry": {"coordinates":[-0.945338,51.282935],"type":"Point"}
}