{
  "type": "Feature",
  "properties": {
    "iso:country":"GB",
    "wof:name":"RG27 9TX",
    "wof:placetype":"postalcode"
},
  "geometry": {"coordinates":[-0.94533813757155,51.28293519952005],"type":"Point"}
}