{
  "type": "Feature",
  "properties": {
    "date:inception_lower": "2023-10-01",
    "date:inception_upper": "2023-10-01",
    "iso:country": "GB",
    "wof:name": "B97 4DG",
    "wof:placetype": "postalcode"
  },
  "geometry": {"coordinates":[-1.940134,52.308512],"type":"Point"}
}
