{
  "type": "Feature",
  "properties": {
    "iso:country": "GB",
    "wof:name": "WR11 7YE",
    "wof:placetype": "postalcode"
  },
  "geometry": {"coordinates":[-1.90763,52.093867],"type":"Point"}
}
