{
  "type": "Feature",
  "properties": {
    "iso:country":"GB",
    "wof:name":"KT24 6SN",
    "wof:placetype":"postalcode"
},
  "geometry": {"coordinates":[-0.43266346928952,51.27279796500898],"type":"Point"}
}