{
  "type": "Feature",
  "properties": {
    "iso:country": "GB",
    "wof:name": "SO51 0DF",
    "wof:placetype": "postalcode"
  },
  "geometry": {"coordinates":[-1.464272,51.005583],"type":"Point"}
}
