{
  "type": "Feature",
  "properties": {
    "iso:country":"GB",
    "wof:name":"DA6 8DL",
    "wof:placetype":"postalcode"
},
  "geometry": {"coordinates":[0.13446351882964,51.45720813373713],"type":"Point"}
}