{
  "type": "Feature",
  "properties": {
    "iso:country":"GB",
    "wof:name":"TD5 8LE",
    "wof:placetype":"postalcode"
},
  "geometry": {"coordinates":[-2.46522498072723,55.53760911586448],"type":"Point"}
}