{
  "type": "Feature",
  "properties": {
    "iso:country":"GB",
    "wof:name":"ST5 9HQ",
    "wof:placetype":"postalcode"
},
  "geometry": {"coordinates":[-2.23413583345221,53.02243902415344],"type":"Point"}
}