{
  "type": "Feature",
  "properties": {
    "iso:country": "GB",
    "wof:name": "HD8 9TW",
    "wof:placetype": "postalcode"
  },
  "geometry": {"coordinates":[-1.668354,53.62205],"type":"Point"}
}
