{
  "type": "Feature",
  "properties": {
    "date:inception_lower": "1995-01-01",
    "date:inception_upper": "1995-01-01",
    "iso:country": "GB",
    "wof:name": "HD8 9TW",
    "wof:placetype": "postalcode"
  },
  "geometry": {"coordinates":[-1.66858,53.622149],"type":"Point"}
}
