{
  "type": "Feature",
  "properties": {
    "iso:country":"GB",
    "wof:name":"HD8 9TW",
    "wof:placetype":"postalcode"
},
  "geometry": {"coordinates":[-1.66857693344773,53.62213400102456],"type":"Point"}
}