{
  "type": "Feature",
  "properties": {
    "iso:country":"GB",
    "wof:name":"YO51 9HX",
    "wof:placetype":"postalcode"
},
  "geometry": {"coordinates":[-1.39663913238619,54.08399192754187],"type":"Point"}
}