{
  "type": "Feature",
  "properties": {
    "iso:country":"GB",
    "wof:name":"M23 9AY",
    "wof:placetype":"postalcode"
},
  "geometry": {"coordinates":[-2.30133259396472,53.40279575224084],"type":"Point"}
}