{
  "type": "Feature",
  "properties": {
    "date:inception_lower": "1980-01-01",
    "date:inception_upper": "1980-01-01",
    "iso:country": "GB",
    "wof:name": "LL61 5YT",
    "wof:placetype": "postalcode"
  },
  "geometry": {"coordinates":[-4.194087,53.224792],"type":"Point"}
}
