{
  "type": "Feature",
  "properties": {
    "iso:country": "GB",
    "wof:name": "DA1 4FQ",
    "wof:placetype": "postalcode"
  },
  "geometry": {"coordinates":[0.191414,51.451589],"type":"Point"}
}
