{
  "type": "Feature",
  "properties": {
    "date:inception_lower": "1995-01-01",
    "date:inception_upper": "1995-01-01",
    "iso:country": "GB",
    "wof:name": "CW10 9DF",
    "wof:placetype": "postalcode"
  },
  "geometry": {"coordinates":[-2.444028,53.192199],"type":"Point"}
}
