{
  "type": "Feature",
  "properties": {
    "iso:country":"GB",
    "wof:name":"CW10 9DF",
    "wof:placetype":"postalcode"
},
  "geometry": {"coordinates":[-2.44402988810991,53.19218320947034],"type":"Point"}
}