{
  "type": "Feature",
  "properties": {
    "date:inception_lower": "2011-05-01",
    "date:inception_upper": "2011-05-01",
    "iso:country": "GB",
    "wof:name": "DA12 5BA",
    "wof:placetype": "postalcode"
  },
  "geometry": {"coordinates":[0.378665,51.419582],"type":"Point"}
}
