{
  "type": "Feature",
  "properties": {
    "iso:country":"GB",
    "wof:name":"M28 0YR",
    "wof:placetype":"postalcode"
},
  "geometry": {"coordinates":[-2.42331363105294,53.52687158101659],"type":"Point"}
}