{
  "type": "Feature",
  "properties": {
    "iso:country": "GB",
    "wof:name": "M28 0YR",
    "wof:placetype": "postalcode"
  },
  "geometry": {"coordinates":[-2.423314,53.526872],"type":"Point"}
}
