{
  "type": "Feature",
  "properties": {
    "iso:country":"GB",
    "wof:name":"OX15 5AA",
    "wof:placetype":"postalcode"
},
  "geometry": {"coordinates":[-1.46590687995794,52.03619670570885],"type":"Point"}
}