{
  "type": "Feature",
  "properties": {
    "iso:country":"GB",
    "wof:name":"DD9 6AD",
    "wof:placetype":"postalcode"
},
  "geometry": {"coordinates":[-2.65932418625037,56.73299573613984],"type":"Point"}
}