{
  "type": "Feature",
  "properties": {
    "iso:country": "GB",
    "wof:name": "PE31 6UF",
    "wof:placetype": "postalcode"
  },
  "geometry": {"coordinates":[0.498779,52.849314],"type":"Point"}
}
