{
  "type": "Feature",
  "properties": {
    "iso:country":"GB",
    "wof:name":"PE31 6UF",
    "wof:placetype":"postalcode"
},
  "geometry": {"coordinates":[0.49877906630431,52.84931439486785],"type":"Point"}
}