{
  "type": "Feature",
  "properties": {
    "iso:country":"GB",
    "wof:name":"B26 2AA",
    "wof:placetype":"postalcode"
},
  "geometry": {"coordinates":[-1.80274755826282,52.47205789390755],"type":"Point"}
}