{
  "type": "Feature",
  "properties": {
    "iso:country": "GB",
    "wof:name": "SN15 5QH",
    "wof:placetype": "postalcode"
  },
  "geometry": {"coordinates":[-2.12659,51.48739],"type":"Point"}
}
