{
  "type": "Feature",
  "properties": {
    "iso:country":"GB",
    "wof:name":"CF83 3SG",
    "wof:placetype":"postalcode"
},
  "geometry": {"coordinates":[-3.20186654171742,51.57185470606473],"type":"Point"}
}