{
  "type": "Feature",
  "properties": {
    "date:inception_lower":"2012-04-01",
    "date:inception_upper":"2012-04-30",
    "iso:country":"GB",
    "wof:name":"CF83 3SG",
    "wof:placetype":"postalcode"
},
  "geometry": {"coordinates":[-3.201867,51.571855],"type":"Point"}
}