{
  "type": "Feature",
  "properties": {
    "date:inception_lower": "1980-01-01",
    "date:inception_upper": "1980-01-01",
    "iso:country": "GB",
    "wof:name": "IP14 5SW",
    "wof:placetype": "postalcode"
  },
  "geometry": {"coordinates":[1.070821,52.253236],"type":"Point"}
}
