{
  "type": "Feature",
  "properties": {
    "iso:country":"GB",
    "wof:name":"LL49 9BL",
    "wof:placetype":"postalcode"
},
  "geometry": {"coordinates":[-4.13099727868127,52.92249889904851],"type":"Point"}
}