{
  "type": "Feature",
  "properties": {
    "iso:country":"GB",
    "wof:name":"PL3 4SG",
    "wof:placetype":"postalcode"
},
  "geometry": {"coordinates":[-4.13640561951232,50.3873339894154],"type":"Point"}
}