{
  "type": "Feature",
  "properties": {
    "iso:country": "GB",
    "wof:name": "AB51 0WN",
    "wof:placetype": "postalcode"
  },
  "geometry": {"coordinates":[-2.357111,57.23179],"type":"Point"}
}
