{
  "type": "Feature",
  "properties": {
    "iso:country":"GB",
    "wof:name":"G3 8GP",
    "wof:placetype":"postalcode"
},
  "geometry": {"coordinates":[-4.2732921862262,55.8609222745494],"type":"Point"}
}