{
  "type": "Feature",
  "properties": {
    "date:inception_lower": "2010-12-01",
    "date:inception_upper": "2010-12-01",
    "iso:country": "GB",
    "wof:name": "G3 8GP",
    "wof:placetype": "postalcode"
  },
  "geometry": {"coordinates":[-4.273292,55.860922],"type":"Point"}
}
