{
  "type": "Feature",
  "properties": {
    "date:inception_lower": "1980-01-01",
    "date:inception_upper": "1980-01-01",
    "iso:country": "GB",
    "wof:name": "FY8 4AN",
    "wof:placetype": "postalcode"
  },
  "geometry": {"coordinates":[-2.997739,53.74934],"type":"Point"}
}
