{
  "type": "Feature",
  "properties": {
    "iso:country":"GB",
    "wof:name":"FY8 4AN",
    "wof:placetype":"postalcode"
},
  "geometry": {"coordinates":[-2.9977389412646,53.74934042539272],"type":"Point"}
}