{
  "type": "Feature",
  "properties": {
    "iso:country":"GB",
    "wof:name":"SE18 7QY",
    "wof:placetype":"postalcode"
},
  "geometry": {"coordinates":[0.08067920615898,51.48399356160355],"type":"Point"}
}