{
  "type": "Feature",
  "properties": {
    "iso:country":"GB",
    "wof:name":"WA8 3TX",
    "wof:placetype":"postalcode"
},
  "geometry": {"coordinates":[-2.69655325518734,53.38657276803347],"type":"Point"}
}