{
  "type": "Feature",
  "properties": {
    "iso:country": "GB",
    "wof:name": "WA8 3TX",
    "wof:placetype": "postalcode"
  },
  "geometry": {"coordinates":[-2.696479,53.386643],"type":"Point"}
}
