{
  "type": "Feature",
  "properties": {
    "date:inception_lower": "1995-07-01",
    "date:inception_upper": "1995-07-01",
    "iso:country": "GB",
    "wof:name": "WA8 3TX",
    "wof:placetype": "postalcode"
  },
  "geometry": {"coordinates":[-2.69624,53.386735],"type":"Point"}
}
