{
  "type": "Feature",
  "properties": {
    "date:inception_lower":"1980-01-01",
    "date:inception_upper":"1980-01-31",
    "iso:country":"GB",
    "wof:name":"NG14 5GH",
    "wof:placetype":"postalcode"
},
  "geometry": {"coordinates":[-1.029983,52.991694],"type":"Point"}
}