{
  "type": "Feature",
  "properties": {
    "iso:country": "GB",
    "wof:name": "NG14 5GH",
    "wof:placetype": "postalcode"
  },
  "geometry": {"coordinates":[-1.029983,52.991694],"type":"Point"}
}
