{
  "type": "Feature",
  "properties": {
    "iso:country": "GB",
    "wof:name": "PE30 1NF",
    "wof:placetype": "postalcode"
  },
  "geometry": {"coordinates":[0.400965,52.754067],"type":"Point"}
}
