{
  "type": "Feature",
  "properties": {
    "iso:country":"GB",
    "wof:name":"WA1 4PS",
    "wof:placetype":"postalcode"
},
  "geometry": {"coordinates":[-2.52234439661171,53.39923756985785],"type":"Point"}
}