{
  "type": "Feature",
  "properties": {
    "iso:country":"GB",
    "wof:name":"BA3 4LE",
    "wof:placetype":"postalcode"
},
  "geometry": {"coordinates":[-2.51252449116467,51.26216477268854],"type":"Point"}
}