{
  "type": "Feature",
  "properties": {
    "date:inception_lower": "1994-05-01",
    "date:inception_upper": "1994-05-01",
    "iso:country": "GB",
    "wof:name": "BA3 4LE",
    "wof:placetype": "postalcode"
  },
  "geometry": {"coordinates":[-2.512524,51.262165],"type":"Point"}
}
