{
  "type": "Feature",
  "properties": {
    "iso:country": "GB",
    "wof:name": "B79 8HL",
    "wof:placetype": "postalcode"
  },
  "geometry": {"coordinates":[-1.696896,52.641869],"type":"Point"}
}
