{
  "type": "Feature",
  "properties": {
    "iso:country":"GB",
    "wof:name":"PE30 4NU",
    "wof:placetype":"postalcode"
},
  "geometry": {"coordinates":[0.42375123653315,52.75314937598647],"type":"Point"}
}