{
  "type": "Feature",
  "properties": {
    "iso:country":"GB",
    "wof:name":"E1 0AQ",
    "wof:placetype":"postalcode"
},
  "geometry": {"coordinates":[-0.05088446898469,51.51155064841412],"type":"Point"}
}