{
  "type": "Feature",
  "properties": {
    "iso:country":"GB",
    "wof:name":"KY8 3PS",
    "wof:placetype":"postalcode"
},
  "geometry": {"coordinates":[-3.02602218697614,56.17943839843805],"type":"Point"}
}