{
  "type": "Feature",
  "properties": {
    "iso:country":"GB",
    "wof:name":"BN18 0AS",
    "wof:placetype":"postalcode"
},
  "geometry": {"coordinates":[-0.61332500146815,50.83712354490278],"type":"Point"}
}