{
  "type": "Feature",
  "properties": {
    "iso:country": "GB",
    "wof:name": "BN18 0AS",
    "wof:placetype": "postalcode"
  },
  "geometry": {"coordinates":[-0.613325,50.837124],"type":"Point"}
}
