{
  "type": "Feature",
  "properties": {
    "iso:country":"GB",
    "wof:name":"SA66 7QP",
    "wof:placetype":"postalcode"
},
  "geometry": {"coordinates":[-4.77277145280352,51.92954036673645],"type":"Point"}
}