{
  "type": "Feature",
  "properties": {
    "iso:country":"GB",
    "wof:name":"AL10 0PU",
    "wof:placetype":"postalcode"
},
  "geometry": {"coordinates":[-0.22114052240689,51.77120956373711],"type":"Point"}
}