{
  "type": "Feature",
  "properties": {
    "iso:country": "GB",
    "wof:name": "RH12 1BN",
    "wof:placetype": "postalcode"
  },
  "geometry": {"coordinates":[-0.325185,51.060734],"type":"Point"}
}
