{
  "type": "Feature",
  "properties": {
    "iso:country": "GB",
    "wof:name": "HS1 2QS",
    "wof:placetype": "postalcode"
  },
  "geometry": {"coordinates":[-6.384452,58.207893],"type":"Point"}
}
