{
  "type": "Feature",
  "properties": {
    "date:inception_lower":"1995-07-01",
    "date:inception_upper":"1995-07-31",
    "iso:country":"GB",
    "wof:name":"HS1 2QS",
    "wof:placetype":"postalcode"
},
  "geometry": {"coordinates":[-6.384452,58.207893],"type":"Point"}
}