{
  "type": "Feature",
  "properties": {
    "iso:country": "GB",
    "wof:name": "AL5 2PA",
    "wof:placetype": "postalcode"
  },
  "geometry": {"coordinates":[-0.362256,51.792879],"type":"Point"}
}
