{
  "type": "Feature",
  "properties": {
    "iso:country":"GB",
    "wof:name":"AL5 2PA",
    "wof:placetype":"postalcode"
},
  "geometry": {"coordinates":[-0.36227995919346,51.79287196155784],"type":"Point"}
}