{
  "type": "Feature",
  "properties": {
    "iso:country": "GB",
    "wof:name": "ME9 0LT",
    "wof:placetype": "postalcode"
  },
  "geometry": {"coordinates":[0.799283,51.284768],"type":"Point"}
}
