{
  "type": "Feature",
  "properties": {
    "iso:country":"GB",
    "wof:name":"ME9 0LT",
    "wof:placetype":"postalcode"
},
  "geometry": {"coordinates":[0.79925167467919,51.28476658370312],"type":"Point"}
}