{
  "type": "Feature",
  "properties": {
    "iso:country":"GB",
    "wof:name":"CF3 3HQ",
    "wof:placetype":"postalcode"
},
  "geometry": {"coordinates":[-3.12194434212183,51.50514480028352],"type":"Point"}
}