{
  "type": "Feature",
  "properties": {
    "iso:country":"GB",
    "wof:name":"TN35 4RR",
    "wof:placetype":"postalcode"
},
  "geometry": {"coordinates":[0.57113137862306,50.92609545647152],"type":"Point"}
}