{
  "type": "Feature",
  "properties": {
    "date:inception_lower": "1998-12-01",
    "date:inception_upper": "1998-12-01",
    "iso:country": "GB",
    "wof:name": "SG18 9UT",
    "wof:placetype": "postalcode"
  },
  "geometry": {"coordinates":[-0.284829,52.099977],"type":"Point"}
}
