{
  "type": "Feature",
  "properties": {
    "date:inception_lower":"2003-08-01",
    "date:inception_upper":"2003-08-31",
    "iso:country":"GB",
    "wof:name":"RG31 6TB",
    "wof:placetype":"postalcode"
},
  "geometry": {"coordinates":[-1.030773,51.471839],"type":"Point"}
}