{
  "type": "Feature",
  "properties": {
    "iso:country":"GB",
    "wof:name":"RG31 6TB",
    "wof:placetype":"postalcode"
},
  "geometry": {"coordinates":[-1.03077350890412,51.47183864679307],"type":"Point"}
}