{
  "type": "Feature",
  "properties": {
    "iso:country": "GB",
    "wof:name": "RG21 3FE",
    "wof:placetype": "postalcode"
  },
  "geometry": {"coordinates":[-1.087249,51.260433],"type":"Point"}
}
