{
  "type": "Feature",
  "properties": {
    "iso:country":"GB",
    "wof:name":"RG21 3FE",
    "wof:placetype":"postalcode"
},
  "geometry": {"coordinates":[-1.08724864775189,51.2604330767095],"type":"Point"}
}