{
  "type": "Feature",
  "properties": {
    "iso:country": "GB",
    "wof:name": "PA35 1JF",
    "wof:placetype": "postalcode"
  },
  "geometry": {"coordinates":[-5.23709,56.429249],"type":"Point"}
}
