{
  "type": "Feature",
  "properties": {
    "iso:country":"GB",
    "wof:name":"PA35 1JF",
    "wof:placetype":"postalcode"
},
  "geometry": {"coordinates":[-5.23710978224718,56.42926245746465],"type":"Point"}
}