{
  "type": "Feature",
  "properties": {
    "date:inception_lower": "1980-01-01",
    "date:inception_upper": "1980-01-01",
    "iso:country": "GB",
    "wof:name": "PA35 1JF",
    "wof:placetype": "postalcode"
  },
  "geometry": {"coordinates":[-5.23709,56.429249],"type":"Point"}
}
