{
  "type": "Feature",
  "properties": {
    "iso:country":"GB",
    "wof:name":"GL51 8PD",
    "wof:placetype":"postalcode"
},
  "geometry": {"coordinates":[-2.09094315512601,51.9042446918593],"type":"Point"}
}