{
  "type": "Feature",
  "properties": {
    "date:inception_lower": "1980-01-01",
    "date:inception_upper": "1980-01-01",
    "iso:country": "GB",
    "wof:name": "PE6 9NG",
    "wof:placetype": "postalcode"
  },
  "geometry": {"coordinates":[-0.360595,52.68649],"type":"Point"}
}
