{
  "type": "Feature",
  "properties": {
    "iso:country":"GB",
    "wof:name":"PE6 9NG",
    "wof:placetype":"postalcode"
},
  "geometry": {"coordinates":[-0.36115094024913,52.68655876735367],"type":"Point"}
}