{
  "type": "Feature",
  "properties": {
    "iso:country": "GB",
    "wof:name": "PE6 9NG",
    "wof:placetype": "postalcode"
  },
  "geometry": {"coordinates":[-0.360595,52.68649],"type":"Point"}
}
