{
  "type": "Feature",
  "properties": {
    "date:inception_lower":"1980-01-01",
    "date:inception_upper":"1980-01-31",
    "iso:country":"GB",
    "wof:name":"SW15 6RN",
    "wof:placetype":"postalcode"
},
  "geometry": {"coordinates":[-0.22171,51.456614],"type":"Point"}
}