{
  "type": "Feature",
  "properties": {
    "iso:country":"GB",
    "wof:name":"SA17 5YY",
    "wof:placetype":"postalcode"
},
  "geometry": {"coordinates":[-4.30874044923083,51.73653484712716],"type":"Point"}
}