{
  "type": "Feature",
  "properties": {
    "date:inception_lower": "1980-01-01",
    "date:inception_upper": "1980-01-01",
    "iso:country": "GB",
    "wof:name": "BN8 4AT",
    "wof:placetype": "postalcode"
  },
  "geometry": {"coordinates":[-0.01775,50.935584],"type":"Point"}
}
