{
  "type": "Feature",
  "properties": {
    "date:inception_lower": "1986-07-01",
    "date:inception_upper": "1986-07-01",
    "iso:country": "GB",
    "wof:name": "PA15 4NA",
    "wof:placetype": "postalcode"
  },
  "geometry": {"coordinates":[-4.753647,55.944273],"type":"Point"}
}
