{
  "type": "Feature",
  "properties": {
    "iso:country":"GB",
    "wof:name":"PA15 4NA",
    "wof:placetype":"postalcode"
},
  "geometry": {"coordinates":[-4.75364742758929,55.94427309222739],"type":"Point"}
}