{
  "type": "Feature",
  "properties": {
    "iso:country":"GB",
    "wof:name":"EH13 0AG",
    "wof:placetype":"postalcode"
},
  "geometry": {"coordinates":[-3.24247544920516,55.90653302125843],"type":"Point"}
}