{
  "type": "Feature",
  "properties": {
    "iso:country":"GB",
    "wof:name":"N8 7PS",
    "wof:placetype":"postalcode"
},
  "geometry": {"coordinates":[-0.11893732352976,51.58774906826442],"type":"Point"}
}