{
  "type": "Feature",
  "properties": {
    "iso:country":"GB",
    "wof:name":"WR2 5EA",
    "wof:placetype":"postalcode"
},
  "geometry": {"coordinates":[-2.24728255350602,52.1865597077874],"type":"Point"}
}