{
  "type": "Feature",
  "properties": {
    "date:inception_lower": "1980-01-01",
    "date:inception_upper": "1980-01-01",
    "iso:country": "GB",
    "wof:name": "WR2 5EA",
    "wof:placetype": "postalcode"
  },
  "geometry": {"coordinates":[-2.247283,52.18656],"type":"Point"}
}
