{
  "type": "Feature",
  "properties": {
    "date:inception_lower": "1999-06-01",
    "date:inception_upper": "1999-06-01",
    "iso:country": "GB",
    "wof:name": "CH48 2LT",
    "wof:placetype": "postalcode"
  },
  "geometry": {"coordinates":[-3.162203,53.359431],"type":"Point"}
}
