{
  "type": "Feature",
  "properties": {
    "iso:country":"GB",
    "wof:name":"CH48 2LT",
    "wof:placetype":"postalcode"
},
  "geometry": {"coordinates":[-3.16220324563287,53.35943119919002],"type":"Point"}
}