{
  "type": "Feature",
  "properties": {
    "iso:country": "GB",
    "wof:name": "DT2 7LZ",
    "wof:placetype": "postalcode"
  },
  "geometry": {"coordinates":[-2.315521,50.785842],"type":"Point"}
}
