{
  "type": "Feature",
  "properties": {
    "iso:country":"GB",
    "wof:name":"CH63 0JZ",
    "wof:placetype":"postalcode"
},
  "geometry": {"coordinates":[-2.98898500060972,53.3258635233035],"type":"Point"}
}