{
  "type": "Feature",
  "properties": {
    "iso:country": "GB",
    "wof:name": "GL56 0GW",
    "wof:placetype": "postalcode"
  },
  "geometry": {"coordinates":[-1.689174,51.991117],"type":"Point"}
}
