{
  "type": "Feature",
  "properties": {
    "date:inception_lower": "1998-06-01",
    "date:inception_upper": "1998-06-01",
    "iso:country": "GB",
    "wof:name": "YO41 5LJ",
    "wof:placetype": "postalcode"
  },
  "geometry": {"coordinates":[-0.942983,53.931597],"type":"Point"}
}
