{
  "type": "Feature",
  "properties": {
    "iso:country":"GB",
    "wof:name":"YO41 5LJ",
    "wof:placetype":"postalcode"
},
  "geometry": {"coordinates":[-0.94298292584573,53.931597022701],"type":"Point"}
}