{
  "type": "Feature",
  "properties": {
    "date:inception_lower": "1980-01-01",
    "date:inception_upper": "1980-01-01",
    "iso:country": "GB",
    "wof:name": "PO33 4NR",
    "wof:placetype": "postalcode"
  },
  "geometry": {"coordinates":[-1.249339,50.724277],"type":"Point"}
}
