{
  "type": "Feature",
  "properties": {
    "date:inception_lower": "2004-06-01",
    "date:inception_upper": "2004-06-01",
    "iso:country": "GB",
    "wof:name": "PO30 1AE",
    "wof:placetype": "postalcode"
  },
  "geometry": {"coordinates":[-1.296528,50.693863],"type":"Point"}
}
