{
  "type": "Feature",
  "properties": {
    "iso:country":"GB",
    "wof:name":"BN1 6HB",
    "wof:placetype":"postalcode"
},
  "geometry": {"coordinates":[-0.14233032502411,50.84082816797383],"type":"Point"}
}