{
  "type": "Feature",
  "properties": {
    "date:inception_lower": "2023-03-01",
    "date:inception_upper": "2023-03-01",
    "iso:country": "GB",
    "wof:name": "IP8 3GS",
    "wof:placetype": "postalcode"
  },
  "geometry": {"coordinates":[1.078216,52.025193],"type":"Point"}
}
