{
  "type": "Feature",
  "properties": {
    "iso:country":"GB",
    "wof:name":"BR1 1RH",
    "wof:placetype":"postalcode"
},
  "geometry": {"coordinates":[0.01660654903481,51.40674093718899],"type":"Point"}
}