{
  "type": "Feature",
  "properties": {
    "date:inception_lower":"1980-01-01",
    "date:inception_upper":"1980-01-31",
    "iso:country":"GB",
    "wof:name":"TA3 5DE",
    "wof:placetype":"postalcode"
},
  "geometry": {"coordinates":[-3.053953,50.995802],"type":"Point"}
}