{
  "type": "Feature",
  "properties": {
    "iso:country":"GB",
    "wof:name":"NR4 7HR",
    "wof:placetype":"postalcode"
},
  "geometry": {"coordinates":[1.25013107123171,52.62863210504268],"type":"Point"}
}