{
  "type": "Feature",
  "properties": {
    "iso:country": "GB",
    "wof:name": "NR4 7HR",
    "wof:placetype": "postalcode"
  },
  "geometry": {"coordinates":[1.250131,52.628632],"type":"Point"}
}
