{
  "type": "Feature",
  "properties": {
    "iso:country":"GB",
    "wof:name":"GU16 6NL",
    "wof:placetype":"postalcode"
},
  "geometry": {"coordinates":[-0.72701635052971,51.30210411283964],"type":"Point"}
}