{
  "type": "Feature",
  "properties": {
    "iso:country":"GB",
    "wof:name":"OL9 0PT",
    "wof:placetype":"postalcode"
},
  "geometry": {"coordinates":[-2.15407600051101,53.55022678245916],"type":"Point"}
}