{
  "type": "Feature",
  "properties": {
    "date:inception_lower": "1995-07-01",
    "date:inception_upper": "1995-07-01",
    "iso:country": "GB",
    "wof:name": "NR30 3DR",
    "wof:placetype": "postalcode"
  },
  "geometry": {"coordinates":[1.730186,52.594676],"type":"Point"}
}
