{
  "type": "Feature",
  "properties": {
    "date:inception_lower": "2010-12-01",
    "date:inception_upper": "2010-12-01",
    "iso:country": "GB",
    "wof:name": "CF63 1AB",
    "wof:placetype": "postalcode"
  },
  "geometry": {"coordinates":[-3.258957,51.411604],"type":"Point"}
}
