{
  "type": "Feature",
  "properties": {
    "iso:country": "GB",
    "wof:name": "CF63 1AB",
    "wof:placetype": "postalcode"
  },
  "geometry": {"coordinates":[-3.258957,51.411604],"type":"Point"}
}
