{
  "type": "Feature",
  "properties": {
    "iso:country":"GB",
    "wof:name":"CF63 1AB",
    "wof:placetype":"postalcode"
},
  "geometry": {"coordinates":[-3.2589567142755,51.41160369232278],"type":"Point"}
}