{
  "type": "Feature",
  "properties": {
    "iso:country":"GB",
    "wof:name":"GL53 9BJ",
    "wof:placetype":"postalcode"
},
  "geometry": {"coordinates":[-2.06618630118007,51.8821257767483],"type":"Point"}
}