{
  "type": "Feature",
  "properties": {
    "iso:country": "GB",
    "wof:name": "PE6 0UB",
    "wof:placetype": "postalcode"
  },
  "geometry": {"coordinates":[-0.106303,52.622541],"type":"Point"}
}
