{
  "type": "Feature",
  "properties": {
    "iso:country":"GB",
    "wof:name":"SN7 8DG",
    "wof:placetype":"postalcode"
},
  "geometry": {"coordinates":[-1.67484264514148,51.67874072168312],"type":"Point"}
}