{
  "type": "Feature",
  "properties": {
    "date:inception_lower": "1980-01-01",
    "date:inception_upper": "1980-01-01",
    "iso:country": "GB",
    "wof:name": "SN7 8DG",
    "wof:placetype": "postalcode"
  },
  "geometry": {"coordinates":[-1.674843,51.678741],"type":"Point"}
}
