{
  "type": "Feature",
  "properties": {
    "date:inception_lower": "2024-01-01",
    "date:inception_upper": "2024-01-01",
    "iso:country": "GB",
    "wof:name": "NE39 2FD",
    "wof:placetype": "postalcode"
  },
  "geometry": {"coordinates":[-1.780679,54.933487],"type":"Point"}
}
