{
  "type": "Feature",
  "properties": {
    "iso:country":"GB",
    "wof:name":"CR0 8YL",
    "wof:placetype":"postalcode"
},
  "geometry": {"coordinates":[-0.05263181478479,51.37853263644316],"type":"Point"}
}