{
  "type": "Feature",
  "properties": {
    "iso:country":"GB",
    "wof:name":"GU35 9NG",
    "wof:placetype":"postalcode"
},
  "geometry": {"coordinates":[-0.87941454730251,51.13698072888611],"type":"Point"}
}