{
  "type": "Feature",
  "properties": {
    "iso:country":"GB",
    "wof:name":"NE39 2PA",
    "wof:placetype":"postalcode"
},
  "geometry": {"coordinates":[-1.74144578107395,54.92420935755471],"type":"Point"}
}