{
  "type": "Feature",
  "properties": {
    "iso:country":"GB",
    "wof:name":"GU46 7PW",
    "wof:placetype":"postalcode"
},
  "geometry": {"coordinates":[-0.84274772723651,51.34783384246473],"type":"Point"}
}