{
  "type": "Feature",
  "properties": {
    "iso:country":"GB",
    "wof:name":"BS35 2HG",
    "wof:placetype":"postalcode"
},
  "geometry": {"coordinates":[-2.5112312503622,51.60836667769867],"type":"Point"}
}