{
  "type": "Feature",
  "properties": {
    "date:inception_lower":"1980-01-01",
    "date:inception_upper":"1980-01-31",
    "iso:country":"GB",
    "wof:name":"NR29 3SQ",
    "wof:placetype":"postalcode"
},
  "geometry": {"coordinates":[1.693295,52.67576],"type":"Point"}
}