{
  "type": "Feature",
  "properties": {
    "iso:country":"GB",
    "wof:name":"CF32 9AJ",
    "wof:placetype":"postalcode"
},
  "geometry": {"coordinates":[-3.57051982246316,51.54464991929643],"type":"Point"}
}