{
  "type": "Feature",
  "properties": {
    "date:inception_lower":"1980-01-01",
    "date:inception_upper":"1980-01-31",
    "iso:country":"GB",
    "wof:name":"CM15 0TZ",
    "wof:placetype":"postalcode"
},
  "geometry": {"coordinates":[0.349855,51.651925],"type":"Point"}
}