{
  "type": "Feature",
  "properties": {
    "iso:country": "GB",
    "wof:name": "CM15 0TZ",
    "wof:placetype": "postalcode"
  },
  "geometry": {"coordinates":[0.349855,51.651925],"type":"Point"}
}
