{
  "type": "Feature",
  "properties": {
    "iso:country":"GB",
    "wof:name":"TA3 5JS",
    "wof:placetype":"postalcode"
},
  "geometry": {"coordinates":[-3.05361592139676,51.01992331773163],"type":"Point"}
}