{
  "type": "Feature",
  "properties": {
    "iso:country": "GB",
    "wof:name": "ST17 0XU",
    "wof:placetype": "postalcode"
  },
  "geometry": {"coordinates":[-1.983381,52.786888],"type":"Point"}
}
