{
  "type": "Feature",
  "properties": {
    "iso:country":"GB",
    "wof:name":"ST17 0XU",
    "wof:placetype":"postalcode"
},
  "geometry": {"coordinates":[-1.98338063599226,52.78688825787786],"type":"Point"}
}