{
  "type": "Feature",
  "properties": {
    "date:inception_lower": "1980-01-01",
    "date:inception_upper": "1980-01-01",
    "iso:country": "GB",
    "wof:name": "WS10 9LY",
    "wof:placetype": "postalcode"
  },
  "geometry": {"coordinates":[-2.023838,52.560069],"type":"Point"}
}
