{
  "type": "Feature",
  "properties": {
    "iso:country":"GB",
    "wof:name":"WS10 9LY",
    "wof:placetype":"postalcode"
},
  "geometry": {"coordinates":[-2.02383830752054,52.56006876628497],"type":"Point"}
}