{
  "type": "Feature",
  "properties": {
    "iso:country": "GB",
    "wof:name": "UB2 5QJ",
    "wof:placetype": "postalcode"
  },
  "geometry": {"coordinates":[-0.380757,51.496436],"type":"Point"}
}
