{
  "type": "Feature",
  "properties": {
    "iso:country":"GB",
    "wof:name":"UB2 5QJ",
    "wof:placetype":"postalcode"
},
  "geometry": {"coordinates":[-0.38155891467382,51.49675158135408],"type":"Point"}
}