{
  "type": "Feature",
  "properties": {
    "iso:country":"GB",
    "wof:name":"S71 1SD",
    "wof:placetype":"postalcode"
},
  "geometry": {"coordinates":[-1.48267787523957,53.57752224124509],"type":"Point"}
}