{
  "type": "Feature",
  "properties": {
    "iso:country":"GB",
    "wof:name":"ML9 2JU",
    "wof:placetype":"postalcode"
},
  "geometry": {"coordinates":[-3.95596510257588,55.73475471176418],"type":"Point"}
}