{
  "type": "Feature",
  "properties": {
    "iso:country":"GB",
    "wof:name":"SK15 1UJ",
    "wof:placetype":"postalcode"
},
  "geometry": {"coordinates":[-2.06648364602377,53.47805909191455],"type":"Point"}
}