{
  "type": "Feature",
  "properties": {
    "date:inception_lower": "2015-12-01",
    "date:inception_upper": "2015-12-01",
    "iso:country": "GB",
    "wof:name": "AB35 5SW",
    "wof:placetype": "postalcode"
  },
  "geometry": {"coordinates":[-3.035913,57.050973],"type":"Point"}
}
