{
  "type": "Feature",
  "properties": {
    "iso:country":"GB",
    "wof:name":"AB35 5SW",
    "wof:placetype":"postalcode"
},
  "geometry": {"coordinates":[-3.03591301329116,57.05097342513402],"type":"Point"}
}