{
  "type": "Feature",
  "properties": {
    "iso:country": "GB",
    "wof:name": "SO17 1EQ",
    "wof:placetype": "postalcode"
  },
  "geometry": {"coordinates":[-1.399307,50.925099],"type":"Point"}
}
