{
  "type": "Feature",
  "properties": {
    "iso:country":"GB",
    "wof:name":"SO17 1EQ",
    "wof:placetype":"postalcode"
},
  "geometry": {"coordinates":[-1.39931671175334,50.92510732047892],"type":"Point"}
}