{
  "type": "Feature",
  "properties": {
    "iso:country":"GB",
    "wof:name":"B60 1BA",
    "wof:placetype":"postalcode"
},
  "geometry": {"coordinates":[-2.05358363623233,52.33698094056331],"type":"Point"}
}