{
  "type": "Feature",
  "properties": {
    "date:inception_lower": "1980-01-01",
    "date:inception_upper": "1980-01-01",
    "iso:country": "GB",
    "wof:name": "B60 1BA",
    "wof:placetype": "postalcode"
  },
  "geometry": {"coordinates":[-2.052653,52.337552],"type":"Point"}
}
