{
  "type": "Feature",
  "properties": {
    "iso:country": "GB",
    "wof:name": "B60 1BA",
    "wof:placetype": "postalcode"
  },
  "geometry": {"coordinates":[-2.053584,52.336981],"type":"Point"}
}
