{
  "type": "Feature",
  "properties": {
    "iso:country":"GB",
    "wof:name":"EN1 3LH",
    "wof:placetype":"postalcode"
},
  "geometry": {"coordinates":[-0.07699470766728,51.66342399754491],"type":"Point"}
}