{
  "type": "Feature",
  "properties": {
    "iso:country": "GB",
    "wof:name": "SA4 8HZ",
    "wof:placetype": "postalcode"
  },
  "geometry": {"coordinates":[-4.030113,51.712177],"type":"Point"}
}
