{
  "type": "Feature",
  "properties": {
    "iso:country": "GB",
    "wof:name": "OX29 6SF",
    "wof:placetype": "postalcode"
  },
  "geometry": {"coordinates":[-1.433613,51.81451],"type":"Point"}
}
