{
  "type": "Feature",
  "properties": {
    "iso:country":"GB",
    "wof:name":"OX29 6SF",
    "wof:placetype":"postalcode"
},
  "geometry": {"coordinates":[-1.43361348723698,51.81450987756389],"type":"Point"}
}