{
  "type": "Feature",
  "properties": {
    "iso:country":"GB",
    "wof:name":"LU5 5DP",
    "wof:placetype":"postalcode"
},
  "geometry": {"coordinates":[-0.52447746653386,51.90403377061302],"type":"Point"}
}