{
  "type": "Feature",
  "properties": {
    "iso:country": "GB",
    "wof:name": "LU5 5DP",
    "wof:placetype": "postalcode"
  },
  "geometry": {"coordinates":[-0.524477,51.904034],"type":"Point"}
}
