{
  "type": "Feature",
  "properties": {
    "iso:country":"GB",
    "wof:name":"RG22 5DA",
    "wof:placetype":"postalcode"
},
  "geometry": {"coordinates":[-1.13052480922134,51.25766013915929],"type":"Point"}
}