{
  "type": "Feature",
  "properties": {
    "iso:country":"GB",
    "wof:name":"KW14 7EX",
    "wof:placetype":"postalcode"
},
  "geometry": {"coordinates":[-3.53583976510217,58.58780396061364],"type":"Point"}
}