{
  "type": "Feature",
  "properties": {
    "iso:country": "GB",
    "wof:name": "KW14 7EX",
    "wof:placetype": "postalcode"
  },
  "geometry": {"coordinates":[-3.53584,58.587804],"type":"Point"}
}
