{
  "type": "Feature",
  "properties": {
    "date:inception_lower": "1980-01-01",
    "date:inception_upper": "1980-01-01",
    "iso:country": "GB",
    "wof:name": "GL10 3UL",
    "wof:placetype": "postalcode"
  },
  "geometry": {"coordinates":[-2.275527,51.707776],"type":"Point"}
}
