{
  "type": "Feature",
  "properties": {
    "iso:country": "GB",
    "wof:name": "GL10 3UL",
    "wof:placetype": "postalcode"
  },
  "geometry": {"coordinates":[-2.27553,51.707782],"type":"Point"}
}
