{
  "type": "Feature",
  "properties": {
    "iso:country":"GB",
    "wof:name":"GU52 8BY",
    "wof:placetype":"postalcode"
},
  "geometry": {"coordinates":[-0.83361231622837,51.25965594385512],"type":"Point"}
}