{
  "type": "Feature",
  "properties": {
    "iso:country": "GB",
    "wof:name": "PE29 2PD",
    "wof:placetype": "postalcode"
  },
  "geometry": {"coordinates":[-0.157732,52.311066],"type":"Point"}
}
