{
  "type": "Feature",
  "properties": {
    "iso:country": "GB",
    "wof:name": "CV23 8YG",
    "wof:placetype": "postalcode"
  },
  "geometry": {"coordinates":[-1.180779,52.332078],"type":"Point"}
}
