{
  "type": "Feature",
  "properties": {
    "date:inception_lower": "1980-01-01",
    "date:inception_upper": "1980-01-01",
    "iso:country": "GB",
    "wof:name": "CV23 8YG",
    "wof:placetype": "postalcode"
  },
  "geometry": {"coordinates":[-1.180779,52.332078],"type":"Point"}
}
