{
  "type": "Feature",
  "properties": {
    "iso:country":"GB",
    "wof:name":"CV4 9FD",
    "wof:placetype":"postalcode"
},
  "geometry": {"coordinates":[-1.56808306218477,52.40469202010236],"type":"Point"}
}