{
  "type": "Feature",
  "properties": {
    "date:inception_lower": "1980-01-01",
    "date:inception_upper": "1980-01-01",
    "iso:country": "GB",
    "wof:name": "WV5 0DR",
    "wof:placetype": "postalcode"
  },
  "geometry": {"coordinates":[-2.1976,52.529592],"type":"Point"}
}
