{
  "type": "Feature",
  "properties": {
    "iso:country":"GB",
    "wof:name":"WV5 0DR",
    "wof:placetype":"postalcode"
},
  "geometry": {"coordinates":[-2.19759957614001,52.52959204793748],"type":"Point"}
}