{
  "type": "Feature",
  "properties": {
    "iso:country":"GB",
    "wof:name":"CT9 5JN",
    "wof:placetype":"postalcode"
},
  "geometry": {"coordinates":[1.35336324055883,51.38078142317914],"type":"Point"}
}