{
  "type": "Feature",
  "properties": {
    "iso:country": "GB",
    "wof:name": "HX6 2FJ",
    "wof:placetype": "postalcode"
  },
  "geometry": {"coordinates":[-1.888872,53.708617],"type":"Point"}
}
