{
  "type": "Feature",
  "properties": {
    "iso:country":"GB",
    "wof:name":"M25 9GP",
    "wof:placetype":"postalcode"
},
  "geometry": {"coordinates":[-2.29265664654246,53.5235238519134],"type":"Point"}
}