{
  "type": "Feature",
  "properties": {
    "date:inception_lower":"1994-05-01",
    "date:inception_upper":"1994-05-31",
    "iso:country":"GB",
    "wof:name":"M25 9GP",
    "wof:placetype":"postalcode"
},
  "geometry": {"coordinates":[-2.292657,53.523524],"type":"Point"}
}