{
  "type": "Feature",
  "properties": {
    "iso:country":"GB",
    "wof:name":"SR8 5EA",
    "wof:placetype":"postalcode"
},
  "geometry": {"coordinates":[-1.33453376992378,54.76713272853885],"type":"Point"}
}