{
  "type": "Feature",
  "properties": {
    "iso:country":"GB",
    "wof:name":"M43 6WE",
    "wof:placetype":"postalcode"
},
  "geometry": {"coordinates":[-2.16543761851725,53.48364356005636],"type":"Point"}
}