{
  "type": "Feature",
  "properties": {
    "date:inception_lower": "1980-01-01",
    "date:inception_upper": "1980-01-01",
    "iso:country": "GB",
    "wof:name": "LA5 0SU",
    "wof:placetype": "postalcode"
  },
  "geometry": {"coordinates":[-2.822315,54.169855],"type":"Point"}
}
