{
  "type": "Feature",
  "properties": {
    "iso:country":"GB",
    "wof:name":"DA12 3BS",
    "wof:placetype":"postalcode"
},
  "geometry": {"coordinates":[0.41185453096535,51.38937854335408],"type":"Point"}
}