{
  "type": "Feature",
  "properties": {
    "iso:country": "GB",
    "wof:name": "DA12 3BS",
    "wof:placetype": "postalcode"
  },
  "geometry": {"coordinates":[0.411867,51.389342],"type":"Point"}
}
