{
  "type": "Feature",
  "properties": {
    "iso:country":"GB",
    "wof:name":"BS40 7RN",
    "wof:placetype":"postalcode"
},
  "geometry": {"coordinates":[-2.71700376256935,51.32885376219524],"type":"Point"}
}