{
  "type": "Feature",
  "properties": {
    "iso:country":"GB",
    "wof:name":"SN5 8NT",
    "wof:placetype":"postalcode"
},
  "geometry": {"coordinates":[-1.83064668239935,51.5476694764659],"type":"Point"}
}