{
  "type": "Feature",
  "properties": {
    "iso:country": "GB",
    "wof:name": "NG31 6PZ",
    "wof:placetype": "postalcode"
  },
  "geometry": {"coordinates":[-0.639665,52.910889],"type":"Point"}
}
