{
  "type": "Feature",
  "properties": {
    "iso:country":"GB",
    "wof:name":"PE7 3UA",
    "wof:placetype":"postalcode"
},
  "geometry": {"coordinates":[-0.34027669801804,52.54356731666714],"type":"Point"}
}