{
  "type": "Feature",
  "properties": {
    "date:inception_lower": "1991-09-01",
    "date:inception_upper": "1991-09-01",
    "iso:country": "GB",
    "wof:name": "WN4 0QZ",
    "wof:placetype": "postalcode"
  },
  "geometry": {"coordinates":[-2.670323,53.496007],"type":"Point"}
}
