{
  "type": "Feature",
  "properties": {
    "iso:country":"GB",
    "wof:name":"W1H 4AD",
    "wof:placetype":"postalcode"
},
  "geometry": {"coordinates":[-0.16540593365885,51.51998040190401],"type":"Point"}
}