{
  "type": "Feature",
  "properties": {
    "iso:country":"GB",
    "wof:name":"ME3 8FN",
    "wof:placetype":"postalcode"
},
  "geometry": {"coordinates":[0.51183937208416,51.41424872164175],"type":"Point"}
}