{
  "type": "Feature",
  "properties": {
    "date:inception_lower": "2010-09-01",
    "date:inception_upper": "2010-09-01",
    "iso:country": "GB",
    "wof:name": "ME3 8FN",
    "wof:placetype": "postalcode"
  },
  "geometry": {"coordinates":[0.511839,51.414249],"type":"Point"}
}
