{
  "type": "Feature",
  "properties": {
    "date:inception_lower":"1980-01-01",
    "date:inception_upper":"1980-01-31",
    "iso:country":"GB",
    "wof:name":"DN14 6NR",
    "wof:placetype":"postalcode"
},
  "geometry": {"coordinates":[-0.875498,53.708448],"type":"Point"}
}