{
  "type": "Feature",
  "properties": {
    "iso:country":"GB",
    "wof:name":"DN14 6NR",
    "wof:placetype":"postalcode"
},
  "geometry": {"coordinates":[-0.87549778258825,53.70844834015526],"type":"Point"}
}