{
  "type": "Feature",
  "properties": {
    "iso:country":"GB",
    "wof:name":"LL12 9PE",
    "wof:placetype":"postalcode"
},
  "geometry": {"coordinates":[-3.03108569856663,53.11453852079337],"type":"Point"}
}