{
  "type": "Feature",
  "properties": {
    "iso:country":"GB",
    "wof:name":"SN14 7LH",
    "wof:placetype":"postalcode"
},
  "geometry": {"coordinates":[-2.23474064487732,51.51072705767973],"type":"Point"}
}