{
  "type": "Feature",
  "properties": {
    "iso:country":"GB",
    "wof:name":"LA12 7RA",
    "wof:placetype":"postalcode"
},
  "geometry": {"coordinates":[-3.05347943327585,54.23358431146963],"type":"Point"}
}