{
  "type": "Feature",
  "properties": {
    "iso:country":"GB",
    "wof:name":"TN14 5ER",
    "wof:placetype":"postalcode"
},
  "geometry": {"coordinates":[0.19171958285212,51.29130792629227],"type":"Point"}
}