{
  "type": "Feature",
  "properties": {
    "date:inception_lower": "1998-06-01",
    "date:inception_upper": "1998-06-01",
    "iso:country": "GB",
    "wof:name": "YO32 2YX",
    "wof:placetype": "postalcode"
  },
  "geometry": {"coordinates":[-1.080559,54.011912],"type":"Point"}
}
