{
  "type": "Feature",
  "properties": {
    "iso:country":"GB",
    "wof:name":"YO32 2YX",
    "wof:placetype":"postalcode"
},
  "geometry": {"coordinates":[-1.08059498855913,54.01192267365385],"type":"Point"}
}