{
  "type": "Feature",
  "properties": {
    "iso:country":"GB",
    "wof:name":"LL18 1ES",
    "wof:placetype":"postalcode"
},
  "geometry": {"coordinates":[-3.49154428400955,53.32163548151112],"type":"Point"}
}