{
  "type": "Feature",
  "properties": {
    "date:inception_lower": "1980-01-01",
    "date:inception_upper": "1980-01-01",
    "iso:country": "GB",
    "wof:name": "LL18 1ES",
    "wof:placetype": "postalcode"
  },
  "geometry": {"coordinates":[-3.491546,53.321653],"type":"Point"}
}
