{
  "type": "Feature",
  "properties": {
    "date:inception_lower":"1980-01-01",
    "date:inception_upper":"1980-01-31",
    "iso:country":"GB",
    "wof:name":"LU2 9QB",
    "wof:placetype":"postalcode"
},
  "geometry": {"coordinates":[-0.365417,51.844448],"type":"Point"}
}