{
  "type": "Feature",
  "properties": {
    "iso:country":"GB",
    "wof:name":"LU7 9QD",
    "wof:placetype":"postalcode"
},
  "geometry": {"coordinates":[-0.55821953116881,51.93115669581162],"type":"Point"}
}