{
  "type": "Feature",
  "properties": {
    "iso:country": "GB",
    "wof:name": "LU7 9QD",
    "wof:placetype": "postalcode"
  },
  "geometry": {"coordinates":[-0.558219,51.931157],"type":"Point"}
}
