{
  "type": "Feature",
  "properties": {
    "date:inception_lower": "1980-01-01",
    "date:inception_upper": "1980-01-01",
    "iso:country": "GB",
    "wof:name": "LU7 9QD",
    "wof:placetype": "postalcode"
  },
  "geometry": {"coordinates":[-0.558219,51.931157],"type":"Point"}
}
