{
  "type": "Feature",
  "properties": {
    "iso:country":"GB",
    "wof:name":"BN6 8NN",
    "wof:placetype":"postalcode"
},
  "geometry": {"coordinates":[-0.13290481014017,50.9306565259899],"type":"Point"}
}