{
  "type": "Feature",
  "properties": {
    "iso:country": "GB",
    "wof:name": "G51 1AX",
    "wof:placetype": "postalcode"
  },
  "geometry": {"coordinates":[-4.290956,55.853103],"type":"Point"}
}
