{
  "type": "Feature",
  "properties": {
    "iso:country":"GB",
    "wof:name":"DL7 8TB",
    "wof:placetype":"postalcode"
},
  "geometry": {"coordinates":[-1.43887954118026,54.3360521203899],"type":"Point"}
}