{
  "type": "Feature",
  "properties": {
    "date:inception_lower":"1980-01-01",
    "date:inception_upper":"1980-01-31",
    "iso:country":"GB",
    "wof:name":"RM1 4JU",
    "wof:placetype":"postalcode"
},
  "geometry": {"coordinates":[0.178897,51.587618],"type":"Point"}
}