{
  "type": "Feature",
  "properties": {
    "iso:country":"GB",
    "wof:name":"SE19 1HP",
    "wof:placetype":"postalcode"
},
  "geometry": {"coordinates":[-0.08299376352991,51.42704553242125],"type":"Point"}
}