{
  "type": "Feature",
  "properties": {
    "iso:country":"GB",
    "wof:name":"B5 4AN",
    "wof:placetype":"postalcode"
},
  "geometry": {"coordinates":[-1.90116328119247,52.47741298910167],"type":"Point"}
}