{
  "type": "Feature",
  "properties": {
    "iso:country":"GB",
    "wof:name":"TA8 2BH",
    "wof:placetype":"postalcode"
},
  "geometry": {"coordinates":[-2.99304272698689,51.23938100888306],"type":"Point"}
}