{
  "type": "Feature",
  "properties": {
    "iso:country": "GB",
    "wof:name": "CO6 2AX",
    "wof:placetype": "postalcode"
  },
  "geometry": {"coordinates":[0.757607,51.933132],"type":"Point"}
}
