{
  "type": "Feature",
  "properties": {
    "iso:country":"GB",
    "wof:name":"CO6 2AX",
    "wof:placetype":"postalcode"
},
  "geometry": {"coordinates":[0.7593082745679,51.93668629732033],"type":"Point"}
}