{
  "type": "Feature",
  "properties": {
    "iso:country":"GB",
    "wof:name":"LE15 8TU",
    "wof:placetype":"postalcode"
},
  "geometry": {"coordinates":[-0.66122434622466,52.63073045465843],"type":"Point"}
}