{
  "type": "Feature",
  "properties": {
    "iso:country":"GB",
    "wof:name":"SK9 7HT",
    "wof:placetype":"postalcode"
},
  "geometry": {"coordinates":[-2.23011989324154,53.30349497356693],"type":"Point"}
}