{
  "type": "Feature",
  "properties": {
    "date:inception_lower":"1993-08-01",
    "date:inception_upper":"1993-08-31",
    "iso:country":"GB",
    "wof:name":"SG18 9AR",
    "wof:placetype":"postalcode"
},
  "geometry": {"coordinates":[-0.321189,52.104097],"type":"Point"}
}