{
  "type": "Feature",
  "properties": {
    "date:inception_lower": "1980-01-01",
    "date:inception_upper": "1980-01-01",
    "iso:country": "GB",
    "wof:name": "ME17 2NL",
    "wof:placetype": "postalcode"
  },
  "geometry": {"coordinates":[0.682615,51.219162],"type":"Point"}
}
