{
  "type": "Feature",
  "properties": {
    "iso:country":"GB",
    "wof:name":"ME17 2NL",
    "wof:placetype":"postalcode"
},
  "geometry": {"coordinates":[0.68258418897037,51.21916301630493],"type":"Point"}
}