{
  "type": "Feature",
  "properties": {
    "iso:country":"GB",
    "wof:name":"PL12 6TS",
    "wof:placetype":"postalcode"
},
  "geometry": {"coordinates":[-4.24859709890277,50.4850202223539],"type":"Point"}
}