{
  "type": "Feature",
  "properties": {
    "iso:country": "GB",
    "wof:name": "PL12 6TS",
    "wof:placetype": "postalcode"
  },
  "geometry": {"coordinates":[-4.248597,50.48502],"type":"Point"}
}
