{
  "type": "Feature",
  "properties": {
    "iso:country":"GB",
    "wof:name":"TQ9 7DR",
    "wof:placetype":"postalcode"
},
  "geometry": {"coordinates":[-3.64563374909361,50.36284769282618],"type":"Point"}
}