{
  "type": "Feature",
  "properties": {
    "iso:country": "GB",
    "wof:name": "TQ9 7DR",
    "wof:placetype": "postalcode"
  },
  "geometry": {"coordinates":[-3.645634,50.362848],"type":"Point"}
}
