{
  "type": "Feature",
  "properties": {
    "date:inception_lower":"1981-06-01",
    "date:inception_upper":"1981-06-30",
    "iso:country":"GB",
    "wof:name":"TQ9 7DR",
    "wof:placetype":"postalcode"
},
  "geometry": {"coordinates":[-3.645634,50.362848],"type":"Point"}
}