{
  "type": "Feature",
  "properties": {
    "iso:country": "GB",
    "wof:name": "CW5 7DG",
    "wof:placetype": "postalcode"
  },
  "geometry": {"coordinates":[-2.516296,53.05924],"type":"Point"}
}
