{
  "type": "Feature",
  "properties": {
    "iso:country":"GB",
    "wof:name":"CW5 7DG",
    "wof:placetype":"postalcode"
},
  "geometry": {"coordinates":[-2.51629594816998,53.05924004290199],"type":"Point"}
}