{
  "type": "Feature",
  "properties": {
    "iso:country":"GB",
    "wof:name":"M40 0EX",
    "wof:placetype":"postalcode"
},
  "geometry": {"coordinates":[-2.17382115615787,53.52166162088542],"type":"Point"}
}