{
  "type": "Feature",
  "properties": {
    "date:inception_lower":"2003-03-01",
    "date:inception_upper":"2003-03-31",
    "iso:country":"GB",
    "wof:name":"WS11 9NE",
    "wof:placetype":"postalcode"
},
  "geometry": {"coordinates":[-1.993096,52.664083],"type":"Point"}
}