{
  "type": "Feature",
  "properties": {
    "iso:country":"GB",
    "wof:name":"GL4 6EE",
    "wof:placetype":"postalcode"
},
  "geometry": {"coordinates":[-2.22046784693718,51.83052737940051],"type":"Point"}
}