{
  "type": "Feature",
  "properties": {
    "iso:country":"GB",
    "wof:name":"ML3 9NS",
    "wof:placetype":"postalcode"
},
  "geometry": {"coordinates":[-4.08626311324313,55.77842711277203],"type":"Point"}
}