{
  "type": "Feature",
  "properties": {
    "iso:country": "GB",
    "wof:name": "DL17 8RF",
    "wof:placetype": "postalcode"
  },
  "geometry": {"coordinates":[-1.539875,54.688211],"type":"Point"}
}
