{
  "type": "Feature",
  "properties": {
    "date:inception_lower": "2014-04-01",
    "date:inception_upper": "2014-04-01",
    "iso:country": "GB",
    "wof:name": "DL17 8RF",
    "wof:placetype": "postalcode"
  },
  "geometry": {"coordinates":[-1.539875,54.688211],"type":"Point"}
}
