{
  "type": "Feature",
  "properties": {
    "iso:country":"GB",
    "wof:name":"PR2 9PD",
    "wof:placetype":"postalcode"
},
  "geometry": {"coordinates":[-2.66641479995414,53.78922075998008],"type":"Point"}
}