{
  "type": "Feature",
  "properties": {
    "iso:country": "GB",
    "wof:name": "PR2 9PD",
    "wof:placetype": "postalcode"
  },
  "geometry": {"coordinates":[-2.666415,53.789221],"type":"Point"}
}
