{
  "type": "Feature",
  "properties": {
    "iso:country": "GB",
    "wof:name": "NR26 8DU",
    "wof:placetype": "postalcode"
  },
  "geometry": {"coordinates":[1.211377,52.943627],"type":"Point"}
}
