{
  "type": "Feature",
  "properties": {
    "iso:country":"GB",
    "wof:name":"RG19 4YR",
    "wof:placetype":"postalcode"
},
  "geometry": {"coordinates":[-1.23804605180109,51.3998067500797],"type":"Point"}
}