{
  "type": "Feature",
  "properties": {
    "iso:country": "GB",
    "wof:name": "RG19 4YR",
    "wof:placetype": "postalcode"
  },
  "geometry": {"coordinates":[-1.238046,51.399807],"type":"Point"}
}
