{
  "type": "Feature",
  "properties": {
    "iso:country":"GB",
    "wof:name":"SG4 8HF",
    "wof:placetype":"postalcode"
},
  "geometry": {"coordinates":[-0.30580956339612,51.8618398310304],"type":"Point"}
}