{
  "type": "Feature",
  "properties": {
    "date:inception_lower":"2010-10-01",
    "date:inception_upper":"2010-10-31",
    "iso:country":"GB",
    "wof:name":"SG4 8HF",
    "wof:placetype":"postalcode"
},
  "geometry": {"coordinates":[-0.30581,51.86184],"type":"Point"}
}