{
  "type": "Feature",
  "properties": {
    "iso:country": "GB",
    "wof:name": "SG4 8HF",
    "wof:placetype": "postalcode"
  },
  "geometry": {"coordinates":[-0.30581,51.86184],"type":"Point"}
}
