{
  "type": "Feature",
  "properties": {
    "date:inception_lower": "2014-09-01",
    "date:inception_upper": "2014-09-01",
    "iso:country": "GB",
    "wof:name": "TN34 2FD",
    "wof:placetype": "postalcode"
  },
  "geometry": {"coordinates":[0.577976,50.884361],"type":"Point"}
}
