{
  "type": "Feature",
  "properties": {
    "iso:country": "GB",
    "wof:name": "TN34 2FD",
    "wof:placetype": "postalcode"
  },
  "geometry": {"coordinates":[0.577976,50.884361],"type":"Point"}
}
