{
  "type": "Feature",
  "properties": {
    "iso:country":"GB",
    "wof:name":"BD24 0BH",
    "wof:placetype":"postalcode"
},
  "geometry": {"coordinates":[-2.29022444136507,54.07221063826888],"type":"Point"}
}