{
  "type": "Feature",
  "properties": {
    "iso:country": "GB",
    "wof:name": "BD24 0BH",
    "wof:placetype": "postalcode"
  },
  "geometry": {"coordinates":[-2.290224,54.072211],"type":"Point"}
}
