{
  "type": "Feature",
  "properties": {
    "iso:country":"GB",
    "wof:name":"HD3 4RR",
    "wof:placetype":"postalcode"
},
  "geometry": {"coordinates":[-1.83717988030292,53.64185131572303],"type":"Point"}
}