{
  "type": "Feature",
  "properties": {
    "iso:country":"GB",
    "wof:name":"TQ14 9AY",
    "wof:placetype":"postalcode"
},
  "geometry": {"coordinates":[-3.51229632152665,50.54862408825967],"type":"Point"}
}