{
  "type": "Feature",
  "properties": {
    "iso:country": "GB",
    "wof:name": "TQ14 9AY",
    "wof:placetype": "postalcode"
  },
  "geometry": {"coordinates":[-3.512296,50.548624],"type":"Point"}
}
