{
  "type": "Feature",
  "properties": {
    "iso:country":"GB",
    "wof:name":"L20 6NA",
    "wof:placetype":"postalcode"
},
  "geometry": {"coordinates":[-2.98649513041702,53.46509597641375],"type":"Point"}
}