{
  "type": "Feature",
  "properties": {
    "iso:country": "GB",
    "wof:name": "L20 6NA",
    "wof:placetype": "postalcode"
  },
  "geometry": {"coordinates":[-2.986495,53.465096],"type":"Point"}
}
