{
  "type": "Feature",
  "properties": {
    "iso:country":"GB",
    "wof:name":"DY10 3TS",
    "wof:placetype":"postalcode"
},
  "geometry": {"coordinates":[-2.2280172391794,52.41725236650693],"type":"Point"}
}