{
  "type": "Feature",
  "properties": {
    "date:inception_lower": "1980-01-01",
    "date:inception_upper": "1980-01-01",
    "iso:country": "GB",
    "wof:name": "DY10 3TS",
    "wof:placetype": "postalcode"
  },
  "geometry": {"coordinates":[-2.228017,52.417252],"type":"Point"}
}
