{
  "type": "Feature",
  "properties": {
    "iso:country": "GB",
    "wof:name": "EH12 7UL",
    "wof:placetype": "postalcode"
  },
  "geometry": {"coordinates":[-3.290067,55.941294],"type":"Point"}
}
