{
  "type": "Feature",
  "properties": {
    "iso:country":"GB",
    "wof:name":"SE5 8HB",
    "wof:placetype":"postalcode"
},
  "geometry": {"coordinates":[-0.09127912053524,51.46087624920415],"type":"Point"}
}