{
  "type": "Feature",
  "properties": {
    "date:inception_lower":"2005-02-01",
    "date:inception_upper":"2005-02-28",
    "iso:country":"GB",
    "wof:name":"NE8 9SZ",
    "wof:placetype":"postalcode"
},
  "geometry": {"coordinates":[-1.603216,54.959486],"type":"Point"}
}