{
  "type": "Feature",
  "properties": {
    "iso:country":"GB",
    "wof:name":"W1K 5EE",
    "wof:placetype":"postalcode"
},
  "geometry": {"coordinates":[-0.14921228244819,51.51267588890169],"type":"Point"}
}