{
  "type": "Feature",
  "properties": {
    "iso:country":"GB",
    "wof:name":"NG31 6BY",
    "wof:placetype":"postalcode"
},
  "geometry": {"coordinates":[-0.64224377128833,52.90832032370127],"type":"Point"}
}