{
  "type": "Feature",
  "properties": {
    "iso:country":"GB",
    "wof:name":"SE7 7QR",
    "wof:placetype":"postalcode"
},
  "geometry": {"coordinates":[0.02527171876433,51.48630362899092],"type":"Point"}
}