{
  "type": "Feature",
  "properties": {
    "iso:country":"GB",
    "wof:name":"BS15 4QF",
    "wof:placetype":"postalcode"
},
  "geometry": {"coordinates":[-2.49390671642517,51.4689560583729],"type":"Point"}
}