{
  "type": "Feature",
  "properties": {
    "iso:country":"GB",
    "wof:name":"BB10 3EH",
    "wof:placetype":"postalcode"
},
  "geometry": {"coordinates":[-2.22779906682634,53.80412328586915],"type":"Point"}
}