{
  "type": "Feature",
  "properties": {
    "date:inception_lower": "1980-01-01",
    "date:inception_upper": "1980-01-01",
    "iso:country": "GB",
    "wof:name": "TA21 9DN",
    "wof:placetype": "postalcode"
  },
  "geometry": {"coordinates":[-3.245682,50.976433],"type":"Point"}
}
