{
  "type": "Feature",
  "properties": {
    "iso:country":"GB",
    "wof:name":"NR15 1DJ",
    "wof:placetype":"postalcode"
},
  "geometry": {"coordinates":[1.41554722169578,52.53138104769639],"type":"Point"}
}