{
  "type": "Feature",
  "properties": {
    "iso:country":"GB",
    "wof:name":"BH22 9EU",
    "wof:placetype":"postalcode"
},
  "geometry": {"coordinates":[-1.89542191562568,50.80170817264298],"type":"Point"}
}