{
  "type": "Feature",
  "properties": {
    "iso:country": "GB",
    "wof:name": "BH22 9EU",
    "wof:placetype": "postalcode"
  },
  "geometry": {"coordinates":[-1.895513,50.801879],"type":"Point"}
}
