{
  "type": "Feature",
  "properties": {
    "iso:country":"GB",
    "wof:name":"WV14 9NT",
    "wof:placetype":"postalcode"
},
  "geometry": {"coordinates":[-2.08592316954008,52.54417276627755],"type":"Point"}
}