{
  "type": "Feature",
  "properties": {
    "date:inception_lower":"1995-12-01",
    "date:inception_upper":"1995-12-31",
    "iso:country":"GB",
    "wof:name":"CR9 6BX",
    "wof:placetype":"postalcode"
},
  "geometry": {"coordinates":[-0.091025,51.376179],"type":"Point"}
}