{
  "type": "Feature",
  "properties": {
    "iso:country": "GB",
    "wof:name": "CR9 6BX",
    "wof:placetype": "postalcode"
  },
  "geometry": {"coordinates":[-0.091025,51.376179],"type":"Point"}
}
