{
  "type": "Feature",
  "properties": {
    "iso:country":"GB",
    "wof:name":"CT18 7JP",
    "wof:placetype":"postalcode"
},
  "geometry": {"coordinates":[1.20908972040521,51.10071197925376],"type":"Point"}
}