{
  "type": "Feature",
  "properties": {
    "iso:country": "GB",
    "wof:name": "HP20 2NY",
    "wof:placetype": "postalcode"
  },
  "geometry": {"coordinates":[-0.814025,51.820098],"type":"Point"}
}
