{
  "type": "Feature",
  "properties": {
    "date:inception_lower": "1980-01-01",
    "date:inception_upper": "1980-01-01",
    "iso:country": "GB",
    "wof:name": "HP20 2NY",
    "wof:placetype": "postalcode"
  },
  "geometry": {"coordinates":[-0.814025,51.820098],"type":"Point"}
}
