{
  "type": "Feature",
  "properties": {
    "date:inception_lower":"1981-09-01",
    "date:inception_upper":"1981-09-30",
    "iso:country":"GB",
    "wof:name":"SE15 6RJ",
    "wof:placetype":"postalcode"
},
  "geometry": {"coordinates":[-0.070061,51.480304],"type":"Point"}
}