{
  "type": "Feature",
  "properties": {
    "date:inception_lower":"1997-06-01",
    "date:inception_upper":"1997-06-30",
    "iso:country":"GB",
    "wof:name":"CO5 9BU",
    "wof:placetype":"postalcode"
},
  "geometry": {"coordinates":[0.689901,51.827578],"type":"Point"}
}