{
  "type": "Feature",
  "properties": {
    "iso:country": "GB",
    "wof:name": "CO5 9BU",
    "wof:placetype": "postalcode"
  },
  "geometry": {"coordinates":[0.689901,51.827578],"type":"Point"}
}
