{
  "type": "Feature",
  "properties": {
    "iso:country": "GB",
    "wof:name": "SN3 4PA",
    "wof:placetype": "postalcode"
  },
  "geometry": {"coordinates":[-1.755127,51.587224],"type":"Point"}
}
