{
  "type": "Feature",
  "properties": {
    "iso:country":"GB",
    "wof:name":"SN3 4PA",
    "wof:placetype":"postalcode"
},
  "geometry": {"coordinates":[-1.75512687919935,51.58722429972956],"type":"Point"}
}