{
  "type": "Feature",
  "properties": {
    "iso:country": "GB",
    "wof:name": "BS36 1JX",
    "wof:placetype": "postalcode"
  },
  "geometry": {"coordinates":[-2.507819,51.522531],"type":"Point"}
}
