{
  "type": "Feature",
  "properties": {
    "iso:country":"GB",
    "wof:name":"BS36 1JX",
    "wof:placetype":"postalcode"
},
  "geometry": {"coordinates":[-2.50781876314188,51.52253120001804],"type":"Point"}
}