{
  "type": "Feature",
  "properties": {
    "iso:country": "GB",
    "wof:name": "N21 3AY",
    "wof:placetype": "postalcode"
  },
  "geometry": {"coordinates":[-0.094341,51.625642],"type":"Point"}
}
