{
  "type": "Feature",
  "properties": {
    "date:inception_lower": "1980-01-01",
    "date:inception_upper": "1980-01-01",
    "iso:country": "GB",
    "wof:name": "N21 3AY",
    "wof:placetype": "postalcode"
  },
  "geometry": {"coordinates":[-0.094341,51.625642],"type":"Point"}
}
