{
  "type": "Feature",
  "properties": {
    "iso:country":"GB",
    "wof:name":"AL8 7SF",
    "wof:placetype":"postalcode"
},
  "geometry": {"coordinates":[-0.20972264620221,51.81177016649659],"type":"Point"}
}