{
  "type": "Feature",
  "properties": {
    "date:inception_lower": "1980-01-01",
    "date:inception_upper": "1980-01-01",
    "iso:country": "GB",
    "wof:name": "NE27 0LZ",
    "wof:placetype": "postalcode"
  },
  "geometry": {"coordinates":[-1.498547,55.036489],"type":"Point"}
}
