{
  "type": "Feature",
  "properties": {
    "iso:country":"GB",
    "wof:name":"HU3 5AY",
    "wof:placetype":"postalcode"
},
  "geometry": {"coordinates":[-0.37272568856715,53.7349186833205],"type":"Point"}
}