{
  "type": "Feature",
  "properties": {
    "date:inception_lower": "1980-01-01",
    "date:inception_upper": "1980-01-01",
    "iso:country": "GB",
    "wof:name": "LN10 6RJ",
    "wof:placetype": "postalcode"
  },
  "geometry": {"coordinates":[-0.223292,53.15303],"type":"Point"}
}
