{
  "type": "Feature",
  "properties": {
    "iso:country": "GB",
    "wof:name": "LN10 6RJ",
    "wof:placetype": "postalcode"
  },
  "geometry": {"coordinates":[-0.223292,53.15303],"type":"Point"}
}
