{
  "type": "Feature",
  "properties": {
    "iso:country":"GB",
    "wof:name":"NE23 6XF",
    "wof:placetype":"postalcode"
},
  "geometry": {"coordinates":[-1.55526603296867,55.07885462782247],"type":"Point"}
}