{
  "type": "Feature",
  "properties": {
    "iso:country": "GB",
    "wof:name": "NE23 6XF",
    "wof:placetype": "postalcode"
  },
  "geometry": {"coordinates":[-1.55525,55.078855],"type":"Point"}
}
