{
  "type": "Feature",
  "properties": {
    "iso:country":"GB",
    "wof:name":"CR3 5EZ",
    "wof:placetype":"postalcode"
},
  "geometry": {"coordinates":[-0.0992222392114,51.28715754018268],"type":"Point"}
}