{
  "type": "Feature",
  "properties": {
    "iso:country": "GB",
    "wof:name": "GL11 4QF",
    "wof:placetype": "postalcode"
  },
  "geometry": {"coordinates":[-2.343562,51.675243],"type":"Point"}
}
