{
  "type": "Feature",
  "properties": {
    "iso:country":"GB",
    "wof:name":"GL11 4QF",
    "wof:placetype":"postalcode"
},
  "geometry": {"coordinates":[-2.34356238138692,51.67524318708838],"type":"Point"}
}