{
  "type": "Feature",
  "properties": {
    "date:inception_lower":"1988-03-01",
    "date:inception_upper":"1988-03-31",
    "iso:country":"GB",
    "wof:name":"DN7 4JN",
    "wof:placetype":"postalcode"
},
  "geometry": {"coordinates":[-1.032396,53.562936],"type":"Point"}
}