{
  "type": "Feature",
  "properties": {
    "iso:country":"GB",
    "wof:name":"DN7 4JN",
    "wof:placetype":"postalcode"
},
  "geometry": {"coordinates":[-1.0323957901198,53.56293558484789],"type":"Point"}
}