{
  "type": "Feature",
  "properties": {
    "iso:country": "GB",
    "wof:name": "DN7 4JN",
    "wof:placetype": "postalcode"
  },
  "geometry": {"coordinates":[-1.032396,53.562936],"type":"Point"}
}
