{
  "type": "Feature",
  "properties": {
    "iso:country":"GB",
    "wof:name":"EN1 3AR",
    "wof:placetype":"postalcode"
},
  "geometry": {"coordinates":[-0.07592129181388,51.65428813900346],"type":"Point"}
}