{
  "type": "Feature",
  "properties": {
    "date:inception_lower":"1980-01-01",
    "date:inception_upper":"1980-01-31",
    "iso:country":"GB",
    "wof:name":"EN1 3AR",
    "wof:placetype":"postalcode"
},
  "geometry": {"coordinates":[-0.075921,51.654288],"type":"Point"}
}