{
  "type": "Feature",
  "properties": {
    "date:inception_lower": "1995-07-01",
    "date:inception_upper": "1995-07-01",
    "iso:country": "GB",
    "wof:name": "WR11 4BZ",
    "wof:placetype": "postalcode"
  },
  "geometry": {"coordinates":[-1.948122,52.093856],"type":"Point"}
}
