{
  "type": "Feature",
  "properties": {
    "iso:country":"GB",
    "wof:name":"WR11 4BZ",
    "wof:placetype":"postalcode"
},
  "geometry": {"coordinates":[-1.94812162091702,52.09385552323607],"type":"Point"}
}