{
  "type": "Feature",
  "properties": {
    "iso:country": "GB",
    "wof:name": "WR11 4BZ",
    "wof:placetype": "postalcode"
  },
  "geometry": {"coordinates":[-1.948122,52.093856],"type":"Point"}
}
