{
  "type": "Feature",
  "properties": {
    "iso:country":"GB",
    "wof:name":"FK10 2QJ",
    "wof:placetype":"postalcode"
},
  "geometry": {"coordinates":[-3.84553175618103,56.13654310833613],"type":"Point"}
}