{
  "type": "Feature",
  "properties": {
    "iso:country":"GB",
    "wof:name":"CV1 1HU",
    "wof:placetype":"postalcode"
},
  "geometry": {"coordinates":[-1.51156380183294,52.41144851926467],"type":"Point"}
}