{
  "type": "Feature",
  "properties": {
    "date:inception_lower": "1980-01-01",
    "date:inception_upper": "1980-01-01",
    "iso:country": "GB",
    "wof:name": "CV1 1HU",
    "wof:placetype": "postalcode"
  },
  "geometry": {"coordinates":[-1.511555,52.411465],"type":"Point"}
}
