{
  "type": "Feature",
  "properties": {
    "iso:country":"GB",
    "wof:name":"CH3 7HD",
    "wof:placetype":"postalcode"
},
  "geometry": {"coordinates":[-2.82558068115972,53.20968287206635],"type":"Point"}
}