{
  "type": "Feature",
  "properties": {
    "iso:country": "GB",
    "wof:name": "LL41 3BN",
    "wof:placetype": "postalcode"
  },
  "geometry": {"coordinates":[-3.933784,52.995929],"type":"Point"}
}
