{
  "type": "Feature",
  "properties": {
    "iso:country":"GB",
    "wof:name":"LL41 3BN",
    "wof:placetype":"postalcode"
},
  "geometry": {"coordinates":[-3.93378405686097,52.99592874816976],"type":"Point"}
}