{
  "type": "Feature",
  "properties": {
    "date:inception_lower":"1980-01-01",
    "date:inception_upper":"1980-01-31",
    "iso:country":"GB",
    "wof:name":"GU3 2JE",
    "wof:placetype":"postalcode"
},
  "geometry": {"coordinates":[-0.679843,51.248842],"type":"Point"}
}