{
  "type": "Feature",
  "properties": {
    "iso:country":"GB",
    "wof:name":"KA6 7AU",
    "wof:placetype":"postalcode"
},
  "geometry": {"coordinates":[-4.46205602425786,55.43448335832357],"type":"Point"}
}