{
  "type": "Feature",
  "properties": {
    "iso:country": "GB",
    "wof:name": "KA6 7AU",
    "wof:placetype": "postalcode"
  },
  "geometry": {"coordinates":[-4.462056,55.434483],"type":"Point"}
}
