{
  "type": "Feature",
  "properties": {
    "iso:country":"GB",
    "wof:name":"NG12 5NP",
    "wof:placetype":"postalcode"
},
  "geometry": {"coordinates":[-1.07710502912049,52.88889580408803],"type":"Point"}
}