{
  "type": "Feature",
  "properties": {
    "iso:country": "GB",
    "wof:name": "NG12 5NP",
    "wof:placetype": "postalcode"
  },
  "geometry": {"coordinates":[-1.076916,52.888679],"type":"Point"}
}
