{
  "type": "Feature",
  "properties": {
    "iso:country":"GB",
    "wof:name":"RG19 3SF",
    "wof:placetype":"postalcode"
},
  "geometry": {"coordinates":[-1.25794618797987,51.39859461828171],"type":"Point"}
}