{
  "type": "Feature",
  "properties": {
    "iso:country": "GB",
    "wof:name": "RG19 3SF",
    "wof:placetype": "postalcode"
  },
  "geometry": {"coordinates":[-1.257946,51.398595],"type":"Point"}
}
