{
  "type": "Feature",
  "properties": {
    "date:inception_lower":"1980-01-01",
    "date:inception_upper":"1980-01-31",
    "iso:country":"GB",
    "wof:name":"TW10 6AT",
    "wof:placetype":"postalcode"
},
  "geometry": {"coordinates":[-0.297842,51.459255],"type":"Point"}
}