{
  "type": "Feature",
  "properties": {
    "iso:country": "GB",
    "wof:name": "W1U 5LW",
    "wof:placetype": "postalcode"
  },
  "geometry": {"coordinates":[-0.153379,51.521887],"type":"Point"}
}
