{
  "type": "Feature",
  "properties": {
    "iso:country":"GB",
    "wof:name":"W1U 5LW",
    "wof:placetype":"postalcode"
},
  "geometry": {"coordinates":[-0.15337950165911,51.5218869312151],"type":"Point"}
}