{
  "type": "Feature",
  "properties": {
    "iso:country": "GB",
    "wof:name": "NR1 3EF",
    "wof:placetype": "postalcode"
  },
  "geometry": {"coordinates":[1.32296,52.647735],"type":"Point"}
}
