{
  "type": "Feature",
  "properties": {
    "iso:country":"GB",
    "wof:name":"NE34 7DS",
    "wof:placetype":"postalcode"
},
  "geometry": {"coordinates":[-1.39494018877583,54.97687960987511],"type":"Point"}
}