{
  "type": "Feature",
  "properties": {
    "iso:country": "GB",
    "wof:name": "NE34 7DS",
    "wof:placetype": "postalcode"
  },
  "geometry": {"coordinates":[-1.39494,54.97688],"type":"Point"}
}
