{
  "type": "Feature",
  "properties": {
    "date:inception_lower": "1993-08-01",
    "date:inception_upper": "1993-08-01",
    "iso:country": "GB",
    "wof:name": "SY21 8LG",
    "wof:placetype": "postalcode"
  },
  "geometry": {"coordinates":[-3.12353,52.616375],"type":"Point"}
}
