{
  "type": "Feature",
  "properties": {
    "iso:country": "GB",
    "wof:name": "SY21 8LG",
    "wof:placetype": "postalcode"
  },
  "geometry": {"coordinates":[-3.12353,52.616375],"type":"Point"}
}
