{
  "type": "Feature",
  "properties": {
    "iso:country":"GB",
    "wof:name":"CW5 8AF",
    "wof:placetype":"postalcode"
},
  "geometry": {"coordinates":[-2.5297283980314,53.05101878908945],"type":"Point"}
}