{
  "type": "Feature",
  "properties": {
    "iso:country": "GB",
    "wof:name": "CW5 8AF",
    "wof:placetype": "postalcode"
  },
  "geometry": {"coordinates":[-2.529728,53.051019],"type":"Point"}
}
