{
  "type": "Feature",
  "properties": {
    "iso:country":"GB",
    "wof:name":"IG2 7AQ",
    "wof:placetype":"postalcode"
},
  "geometry": {"coordinates":[0.09250920243529,51.56648058304226],"type":"Point"}
}