{
  "type": "Feature",
  "properties": {
    "iso:country":"GB",
    "wof:name":"HP22 4AB",
    "wof:placetype":"postalcode"
},
  "geometry": {"coordinates":[-0.86870777607954,51.85579500342457],"type":"Point"}
}