{
  "type": "Feature",
  "properties": {
    "iso:country":"GB",
    "wof:name":"S7 1FN",
    "wof:placetype":"postalcode"
},
  "geometry": {"coordinates":[-1.47950648556008,53.36067746503714],"type":"Point"}
}