{
  "type": "Feature",
  "properties": {
    "iso:country":"GB",
    "wof:name":"SG5 4RS",
    "wof:placetype":"postalcode"
},
  "geometry": {"coordinates":[-0.22473750137942,52.02483484563319],"type":"Point"}
}