{
  "type": "Feature",
  "properties": {
    "iso:country": "GB",
    "wof:name": "SG5 4RS",
    "wof:placetype": "postalcode"
  },
  "geometry": {"coordinates":[-0.224737,52.024835],"type":"Point"}
}
