{
  "type": "Feature",
  "properties": {
    "iso:country": "GB",
    "wof:name": "TS29 6EG",
    "wof:placetype": "postalcode"
  },
  "geometry": {"coordinates":[-1.425738,54.716581],"type":"Point"}
}
