{
  "type": "Feature",
  "properties": {
    "iso:country": "GB",
    "wof:name": "OX11 8AL",
    "wof:placetype": "postalcode"
  },
  "geometry": {"coordinates":[-1.237849,51.606011],"type":"Point"}
}
