{
  "type": "Feature",
  "properties": {
    "iso:country":"GB",
    "wof:name":"ME15 8LW",
    "wof:placetype":"postalcode"
},
  "geometry": {"coordinates":[0.56211005563602,51.26425173403759],"type":"Point"}
}