{
  "type": "Feature",
  "properties": {
    "date:inception_lower": "1980-01-01",
    "date:inception_upper": "1980-01-01",
    "iso:country": "GB",
    "wof:name": "ME15 8LW",
    "wof:placetype": "postalcode"
  },
  "geometry": {"coordinates":[0.56211,51.264252],"type":"Point"}
}
