{
  "type": "Feature",
  "properties": {
    "iso:country":"GB",
    "wof:name":"L9 8BU",
    "wof:placetype":"postalcode"
},
  "geometry": {"coordinates":[-2.9629418025974,53.46202522085279],"type":"Point"}
}