{
  "type": "Feature",
  "properties": {
    "date:inception_lower": "1990-02-01",
    "date:inception_upper": "1990-02-01",
    "iso:country": "GB",
    "wof:name": "RG7 4PE",
    "wof:placetype": "postalcode"
  },
  "geometry": {"coordinates":[-1.072534,51.432874],"type":"Point"}
}
