{
  "type": "Feature",
  "properties": {
    "iso:country":"GB",
    "wof:name":"RG7 4PE",
    "wof:placetype":"postalcode"
},
  "geometry": {"coordinates":[-1.07238037626816,51.43289889231447],"type":"Point"}
}