{
  "type": "Feature",
  "properties": {
    "iso:country": "GB",
    "wof:name": "RG7 4PE",
    "wof:placetype": "postalcode"
  },
  "geometry": {"coordinates":[-1.07238,51.432899],"type":"Point"}
}
