{
  "type": "Feature",
  "properties": {
    "iso:country":"GB",
    "wof:name":"CT11 0DP",
    "wof:placetype":"postalcode"
},
  "geometry": {"coordinates":[1.39513543743273,51.33283850069772],"type":"Point"}
}