{
  "type": "Feature",
  "properties": {
    "iso:country":"GB",
    "wof:name":"BN8 4BJ",
    "wof:placetype":"postalcode"
},
  "geometry": {"coordinates":[-0.02061735904052,50.94682066761445],"type":"Point"}
}