{
  "type": "Feature",
  "properties": {
    "iso:country":"GB",
    "wof:name":"RH1 5PP",
    "wof:placetype":"postalcode"
},
  "geometry": {"coordinates":[-0.09661395941025,51.19270734805968],"type":"Point"}
}