{
  "type": "Feature",
  "properties": {
    "date:inception_lower": "1980-01-01",
    "date:inception_upper": "1980-01-01",
    "iso:country": "GB",
    "wof:name": "RH1 5PP",
    "wof:placetype": "postalcode"
  },
  "geometry": {"coordinates":[-0.096614,51.192707],"type":"Point"}
}
