{
  "type": "Feature",
  "properties": {
    "iso:country": "GB",
    "wof:name": "RH1 5PP",
    "wof:placetype": "postalcode"
  },
  "geometry": {"coordinates":[-0.096614,51.192707],"type":"Point"}
}
