{
  "type": "Feature",
  "properties": {
    "iso:country":"GB",
    "wof:name":"WF2 9QE",
    "wof:placetype":"postalcode"
},
  "geometry": {"coordinates":[-1.51630650928023,53.68251140764956],"type":"Point"}
}