{
  "type": "Feature",
  "properties": {
    "iso:country":"GB",
    "wof:name":"TW1 4ST",
    "wof:placetype":"postalcode"
},
  "geometry": {"coordinates":[-0.33344334621787,51.4390032267203],"type":"Point"}
}