{
  "type": "Feature",
  "properties": {
    "iso:country": "GB",
    "wof:name": "TW1 4ST",
    "wof:placetype": "postalcode"
  },
  "geometry": {"coordinates":[-0.333443,51.439003],"type":"Point"}
}
