{
  "type": "Feature",
  "properties": {
    "date:inception_lower": "2001-12-01",
    "date:inception_upper": "2001-12-01",
    "iso:country": "GB",
    "wof:name": "KY11 9GX",
    "wof:placetype": "postalcode"
  },
  "geometry": {"coordinates":[-3.372171,56.029086],"type":"Point"}
}
