{
  "type": "Feature",
  "properties": {
    "iso:country":"GB",
    "wof:name":"HD2 1TQ",
    "wof:placetype":"postalcode"
},
  "geometry": {"coordinates":[-1.74833703899839,53.67654494206533],"type":"Point"}
}