{
  "type": "Feature",
  "properties": {
    "iso:country": "GB",
    "wof:name": "HD2 1TQ",
    "wof:placetype": "postalcode"
  },
  "geometry": {"coordinates":[-1.748337,53.676545],"type":"Point"}
}
