{
  "type": "Feature",
  "properties": {
    "iso:country":"GB",
    "wof:name":"LE18 3WH",
    "wof:placetype":"postalcode"
},
  "geometry": {"coordinates":[-1.09297731637902,52.58491788764241],"type":"Point"}
}