{
  "type": "Feature",
  "properties": {
    "date:inception_lower": "1980-01-01",
    "date:inception_upper": "1980-01-01",
    "iso:country": "GB",
    "wof:name": "S81 0RF",
    "wof:placetype": "postalcode"
  },
  "geometry": {"coordinates":[-1.106932,53.316017],"type":"Point"}
}
