{
  "type": "Feature",
  "properties": {
    "date:inception_lower": "2019-04-01",
    "date:inception_upper": "2019-04-01",
    "iso:country": "GB",
    "wof:name": "CF11 1WR",
    "wof:placetype": "postalcode"
  },
  "geometry": {"coordinates":[-3.193643,51.465736],"type":"Point"}
}
