{
  "type": "Feature",
  "properties": {
    "date:inception_lower": "2007-10-01",
    "date:inception_upper": "2007-10-01",
    "iso:country": "GB",
    "wof:name": "PE1 2BT",
    "wof:placetype": "postalcode"
  },
  "geometry": {"coordinates":[-0.260268,52.593317],"type":"Point"}
}
