{
  "type": "Feature",
  "properties": {
    "date:inception_lower":"2007-10-01",
    "date:inception_upper":"2007-10-31",
    "iso:country":"GB",
    "wof:name":"PE1 2BT",
    "wof:placetype":"postalcode"
},
  "geometry": {"coordinates":[-0.260146,52.593026],"type":"Point"}
}