{
  "type": "Feature",
  "properties": {
    "date:inception_lower": "1997-06-01",
    "date:inception_upper": "1997-06-01",
    "iso:country": "GB",
    "wof:name": "S32 2JN",
    "wof:placetype": "postalcode"
  },
  "geometry": {"coordinates":[-1.636713,53.294779],"type":"Point"}
}
