{
  "type": "Feature",
  "properties": {
    "iso:country": "GB",
    "wof:name": "PE19 5XA",
    "wof:placetype": "postalcode"
  },
  "geometry": {"coordinates":[-0.254719,52.292824],"type":"Point"}
}
