{
  "type": "Feature",
  "properties": {
    "iso:country":"GB",
    "wof:name":"PE19 5XA",
    "wof:placetype":"postalcode"
},
  "geometry": {"coordinates":[-0.25471887574631,52.29282424517853],"type":"Point"}
}