{
  "type": "Feature",
  "properties": {
    "iso:country": "GB",
    "wof:name": "BS14 8TU",
    "wof:placetype": "postalcode"
  },
  "geometry": {"coordinates":[-2.53552,51.413016],"type":"Point"}
}
