{
  "type": "Feature",
  "properties": {
    "date:inception_lower":"1980-01-01",
    "date:inception_upper":"1980-01-31",
    "iso:country":"GB",
    "wof:name":"BS14 8TU",
    "wof:placetype":"postalcode"
},
  "geometry": {"coordinates":[-2.53552,51.413016],"type":"Point"}
}