{
  "type": "Feature",
  "properties": {
    "date:inception_lower": "2003-03-01",
    "date:inception_upper": "2003-03-01",
    "iso:country": "GB",
    "wof:name": "WS11 4AF",
    "wof:placetype": "postalcode"
  },
  "geometry": {"coordinates":[-2.032285,52.692036],"type":"Point"}
}
