{
  "type": "Feature",
  "properties": {
    "iso:country":"GB",
    "wof:name":"WS11 4AF",
    "wof:placetype":"postalcode"
},
  "geometry": {"coordinates":[-2.03228506929283,52.69203605463037],"type":"Point"}
}