{
  "type": "Feature",
  "properties": {
    "iso:country":"GB",
    "wof:name":"NN7 3JL",
    "wof:placetype":"postalcode"
},
  "geometry": {"coordinates":[-0.95872009518773,52.20780559587516],"type":"Point"}
}