{
  "type": "Feature",
  "properties": {
    "date:inception_lower": "2003-09-01",
    "date:inception_upper": "2003-09-01",
    "iso:country": "GB",
    "wof:name": "CR3 5XN",
    "wof:placetype": "postalcode"
  },
  "geometry": {"coordinates":[-0.099895,51.282681],"type":"Point"}
}
