{
  "type": "Feature",
  "properties": {
    "iso:country":"GB",
    "wof:name":"AB22 8NP",
    "wof:placetype":"postalcode"
},
  "geometry": {"coordinates":[-2.11131513710077,57.19480521585997],"type":"Point"}
}