{
  "type": "Feature",
  "properties": {
    "date:inception_lower": "1997-12-01",
    "date:inception_upper": "1997-12-01",
    "iso:country": "GB",
    "wof:name": "AB22 8NP",
    "wof:placetype": "postalcode"
  },
  "geometry": {"coordinates":[-2.111315,57.194805],"type":"Point"}
}
