{
  "type": "Feature",
  "properties": {
    "iso:country": "GB",
    "wof:name": "SO32 1QB",
    "wof:placetype": "postalcode"
  },
  "geometry": {"coordinates":[-1.217302,50.957886],"type":"Point"}
}
