{
  "type": "Feature",
  "properties": {
    "iso:country":"GB",
    "wof:name":"SO32 1QB",
    "wof:placetype":"postalcode"
},
  "geometry": {"coordinates":[-1.21730167467538,50.95788631700562],"type":"Point"}
}