{
  "type": "Feature",
  "properties": {
    "iso:country": "GB",
    "wof:name": "CF48 2NY",
    "wof:placetype": "postalcode"
  },
  "geometry": {"coordinates":[-3.405441,51.765704],"type":"Point"}
}
