{
  "type": "Feature",
  "properties": {
    "iso:country":"GB",
    "wof:name":"CF48 2NY",
    "wof:placetype":"postalcode"
},
  "geometry": {"coordinates":[-3.40544057430978,51.76570443311657],"type":"Point"}
}