{
  "type": "Feature",
  "properties": {
    "iso:country": "GB",
    "wof:name": "LU7 4EA",
    "wof:placetype": "postalcode"
  },
  "geometry": {"coordinates":[-0.660568,51.909394],"type":"Point"}
}
