{
  "type": "Feature",
  "properties": {
    "iso:country":"GB",
    "wof:name":"CV6 6AA",
    "wof:placetype":"postalcode"
},
  "geometry": {"coordinates":[-1.49035721235733,52.45417001651241],"type":"Point"}
}