{
  "type": "Feature",
  "properties": {
    "date:inception_lower":"1980-01-01",
    "date:inception_upper":"1980-01-31",
    "iso:country":"GB",
    "wof:name":"LA13 0RN",
    "wof:placetype":"postalcode"
},
  "geometry": {"coordinates":[-3.184187,54.117522],"type":"Point"}
}