{
  "type": "Feature",
  "properties": {
    "iso:country":"GB",
    "wof:name":"LA13 0RN",
    "wof:placetype":"postalcode"
},
  "geometry": {"coordinates":[-3.18418705022318,54.11752206519292],"type":"Point"}
}