{
  "type": "Feature",
  "properties": {
    "iso:country":"GB",
    "wof:name":"IG2 6JG",
    "wof:placetype":"postalcode"
},
  "geometry": {"coordinates":[0.06457304056191,51.57378294729937],"type":"Point"}
}