{
  "type": "Feature",
  "properties": {
    "iso:country": "GB",
    "wof:name": "TA2 6SQ",
    "wof:placetype": "postalcode"
  },
  "geometry": {"coordinates":[-3.155378,51.026515],"type":"Point"}
}
