{
  "type": "Feature",
  "properties": {
    "iso:country":"GB",
    "wof:name":"TA2 6SQ",
    "wof:placetype":"postalcode"
},
  "geometry": {"coordinates":[-3.15537822945344,51.02651491584209],"type":"Point"}
}