{
  "type": "Feature",
  "properties": {
    "date:inception_lower": "2017-06-01",
    "date:inception_upper": "2017-06-01",
    "iso:country": "GB",
    "wof:name": "G61 3EG",
    "wof:placetype": "postalcode"
  },
  "geometry": {"coordinates":[-4.313734,55.93146],"type":"Point"}
}
