{
  "type": "Feature",
  "properties": {
    "iso:country":"GB",
    "wof:name":"PL20 7AW",
    "wof:placetype":"postalcode"
},
  "geometry": {"coordinates":[-4.1944995794725,50.48062971107858],"type":"Point"}
}