{
  "type": "Feature",
  "properties": {
    "date:inception_lower": "1980-01-01",
    "date:inception_upper": "1980-01-01",
    "iso:country": "GB",
    "wof:name": "PL20 7AW",
    "wof:placetype": "postalcode"
  },
  "geometry": {"coordinates":[-4.1945,50.48063],"type":"Point"}
}
