{
  "type": "Feature",
  "properties": {
    "iso:country":"GB",
    "wof:name":"CF5 2RE",
    "wof:placetype":"postalcode"
},
  "geometry": {"coordinates":[-3.24453496454574,51.50368298944911],"type":"Point"}
}