{
  "type": "Feature",
  "properties": {
    "iso:country":"GB",
    "wof:name":"SG8 5DJ",
    "wof:placetype":"postalcode"
},
  "geometry": {"coordinates":[-0.02762464685285,52.05863818743075],"type":"Point"}
}