{
  "type": "Feature",
  "properties": {
    "date:inception_lower": "1980-01-01",
    "date:inception_upper": "1980-01-01",
    "iso:country": "GB",
    "wof:name": "SG8 5DJ",
    "wof:placetype": "postalcode"
  },
  "geometry": {"coordinates":[-0.02761,52.058649],"type":"Point"}
}
