{
  "type": "Feature",
  "properties": {
    "iso:country": "GB",
    "wof:name": "RG5 4SG",
    "wof:placetype": "postalcode"
  },
  "geometry": {"coordinates":[-0.897147,51.451975],"type":"Point"}
}
