{
  "type": "Feature",
  "properties": {
    "iso:country":"GB",
    "wof:name":"SE3 0UW",
    "wof:placetype":"postalcode"
},
  "geometry": {"coordinates":[-0.00130095371516,51.46791085009331],"type":"Point"}
}