{
  "type": "Feature",
  "properties": {
    "iso:country": "GB",
    "wof:name": "SE3 0UW",
    "wof:placetype": "postalcode"
  },
  "geometry": {"coordinates":[-0.001301,51.467911],"type":"Point"}
}
