{
  "type": "Feature",
  "properties": {
    "iso:country":"GB",
    "wof:name":"ST3 4JT",
    "wof:placetype":"postalcode"
},
  "geometry": {"coordinates":[-2.12373023920563,52.97704823779376],"type":"Point"}
}