{
  "type": "Feature",
  "properties": {
    "iso:country": "GB",
    "wof:name": "ST3 4JT",
    "wof:placetype": "postalcode"
  },
  "geometry": {"coordinates":[-2.124088,52.977245],"type":"Point"}
}
