{
  "type": "Feature",
  "properties": {
    "iso:country":"GB",
    "wof:name":"NP19 7NE",
    "wof:placetype":"postalcode"
},
  "geometry": {"coordinates":[-2.97135697968602,51.60166574452683],"type":"Point"}
}