{
  "type": "Feature",
  "properties": {
    "iso:country":"GB",
    "wof:name":"SS9 2DH",
    "wof:placetype":"postalcode"
},
  "geometry": {"coordinates":[0.65447644918616,51.540333447351],"type":"Point"}
}