{
  "type": "Feature",
  "properties": {
    "iso:country":"GB",
    "wof:name":"CM3 3JA",
    "wof:placetype":"postalcode"
},
  "geometry": {"coordinates":[0.53034904389724,51.75815982324553],"type":"Point"}
}