{
  "type": "Feature",
  "properties": {
    "date:inception_lower": "2009-06-01",
    "date:inception_upper": "2009-06-01",
    "iso:country": "GB",
    "wof:name": "SW16 9BY",
    "wof:placetype": "postalcode"
  },
  "geometry": {"coordinates":[-0.130694,51.430918],"type":"Point"}
}
