{
  "type": "Feature",
  "properties": {
    "date:inception_lower": "2005-09-01",
    "date:inception_upper": "2005-09-01",
    "iso:country": "GB",
    "wof:name": "RH10 9ZX",
    "wof:placetype": "postalcode"
  },
  "geometry": {"coordinates":[-0.167025,51.14009],"type":"Point"}
}
