{
  "type": "Feature",
  "properties": {
    "iso:country":"GB",
    "wof:name":"RH10 9ZX",
    "wof:placetype":"postalcode"
},
  "geometry": {"coordinates":[-0.16702543601822,51.14008982868098],"type":"Point"}
}