{
  "type": "Feature",
  "properties": {
    "iso:country": "GB",
    "wof:name": "CR4 1NL",
    "wof:placetype": "postalcode"
  },
  "geometry": {"coordinates":[-0.139497,51.400133],"type":"Point"}
}
