{
  "type": "Feature",
  "properties": {
    "iso:country":"GB",
    "wof:name":"NE26 2JR",
    "wof:placetype":"postalcode"
},
  "geometry": {"coordinates":[-1.45212904050952,55.04064758215487],"type":"Point"}
}