{
  "type": "Feature",
  "properties": {
    "date:inception_lower": "1980-01-01",
    "date:inception_upper": "1980-01-01",
    "iso:country": "GB",
    "wof:name": "NE26 2JR",
    "wof:placetype": "postalcode"
  },
  "geometry": {"coordinates":[-1.452129,55.040648],"type":"Point"}
}
