{
  "type": "Feature",
  "properties": {
    "iso:country":"GB",
    "wof:name":"M44 6JA",
    "wof:placetype":"postalcode"
},
  "geometry": {"coordinates":[-2.41722887090602,53.4572411952357],"type":"Point"}
}