{
  "type": "Feature",
  "properties": {
    "iso:country":"GB",
    "wof:name":"RH10 6SN",
    "wof:placetype":"postalcode"
},
  "geometry": {"coordinates":[-0.16592900824208,51.11039568394361],"type":"Point"}
}