{
  "type": "Feature",
  "properties": {
    "date:inception_lower":"1999-06-01",
    "date:inception_upper":"1999-06-30",
    "iso:country":"GB",
    "wof:name":"NP10 0BL",
    "wof:placetype":"postalcode"
},
  "geometry": {"coordinates":[-3.05137,51.598881],"type":"Point"}
}