{
  "type": "Feature",
  "properties": {
    "iso:country": "GB",
    "wof:name": "G72 9RJ",
    "wof:placetype": "postalcode"
  },
  "geometry": {"coordinates":[-4.106036,55.792317],"type":"Point"}
}
