{
  "type": "Feature",
  "properties": {
    "iso:country":"GB",
    "wof:name":"TQ12 4DT",
    "wof:placetype":"postalcode"
},
  "geometry": {"coordinates":[-3.57935562907279,50.52743502749759],"type":"Point"}
}