{
  "type": "Feature",
  "properties": {
    "date:inception_lower":"1980-01-01",
    "date:inception_upper":"1980-01-31",
    "iso:country":"GB",
    "wof:name":"TQ12 4DT",
    "wof:placetype":"postalcode"
},
  "geometry": {"coordinates":[-3.579356,50.527435],"type":"Point"}
}