{
  "type": "Feature",
  "properties": {
    "iso:country":"GB",
    "wof:name":"PL35 0DP",
    "wof:placetype":"postalcode"
},
  "geometry": {"coordinates":[-4.69785901939455,50.68328395900529],"type":"Point"}
}