{
  "type": "Feature",
  "properties": {
    "iso:country": "GB",
    "wof:name": "PL35 0DP",
    "wof:placetype": "postalcode"
  },
  "geometry": {"coordinates":[-4.697859,50.683284],"type":"Point"}
}
