{
  "type": "Feature",
  "properties": {
    "iso:country":"GB",
    "wof:name":"B60 3HP",
    "wof:placetype":"postalcode"
},
  "geometry": {"coordinates":[-2.06687640877162,52.32452272478905],"type":"Point"}
}