{
  "type": "Feature",
  "properties": {
    "date:inception_lower": "2016-07-01",
    "date:inception_upper": "2016-07-01",
    "iso:country": "GB",
    "wof:name": "CM3 3FQ",
    "wof:placetype": "postalcode"
  },
  "geometry": {"coordinates":[0.496048,51.767931],"type":"Point"}
}
