{
  "type": "Feature",
  "properties": {
    "iso:country":"GB",
    "wof:name":"W1D 6QJ",
    "wof:placetype":"postalcode"
},
  "geometry": {"coordinates":[-0.13187513785494,51.51125897956059],"type":"Point"}
}