{
  "type": "Feature",
  "properties": {
    "date:inception_lower":"2000-10-01",
    "date:inception_upper":"2000-10-31",
    "iso:country":"GB",
    "wof:name":"W1D 6QJ",
    "wof:placetype":"postalcode"
},
  "geometry": {"coordinates":[-0.131875,51.511259],"type":"Point"}
}