{
  "type": "Feature",
  "properties": {
    "date:inception_lower":"2001-06-01",
    "date:inception_upper":"2001-06-30",
    "iso:country":"GB",
    "wof:name":"HD9 2NT",
    "wof:placetype":"postalcode"
},
  "geometry": {"coordinates":[-1.813625,53.560329],"type":"Point"}
}