{
  "type": "Feature",
  "properties": {
    "iso:country": "GB",
    "wof:name": "HD9 2NT",
    "wof:placetype": "postalcode"
  },
  "geometry": {"coordinates":[-1.813625,53.560329],"type":"Point"}
}
