{
  "type": "Feature",
  "properties": {
    "date:inception_lower":"1987-10-01",
    "date:inception_upper":"1987-10-31",
    "iso:country":"GB",
    "wof:name":"RG8 7AT",
    "wof:placetype":"postalcode"
},
  "geometry": {"coordinates":[-1.089067,51.481396],"type":"Point"}
}