{
  "type": "Feature",
  "properties": {
    "iso:country":"GB",
    "wof:name":"RG8 7AT",
    "wof:placetype":"postalcode"
},
  "geometry": {"coordinates":[-1.08906670749486,51.4813965046587],"type":"Point"}
}