{
  "type": "Feature",
  "properties": {
    "iso:country": "GB",
    "wof:name": "CM13 3RR",
    "wof:placetype": "postalcode"
  },
  "geometry": {"coordinates":[0.341779,51.603785],"type":"Point"}
}
