{
  "type": "Feature",
  "properties": {
    "date:inception_lower": "1990-07-01",
    "date:inception_upper": "1990-07-01",
    "iso:country": "GB",
    "wof:name": "L12 9LP",
    "wof:placetype": "postalcode"
  },
  "geometry": {"coordinates":[-2.881484,53.423445],"type":"Point"}
}
