{
  "type": "Feature",
  "properties": {
    "iso:country":"GB",
    "wof:name":"CB24 9JY",
    "wof:placetype":"postalcode"
},
  "geometry": {"coordinates":[0.09706562317526,52.25233837357604],"type":"Point"}
}