{
  "type": "Feature",
  "properties": {
    "iso:country": "GB",
    "wof:name": "CB24 9JY",
    "wof:placetype": "postalcode"
  },
  "geometry": {"coordinates":[0.097066,52.252338],"type":"Point"}
}
