{
  "type": "Feature",
  "properties": {
    "iso:country": "GB",
    "wof:name": "PO17 5DU",
    "wof:placetype": "postalcode"
  },
  "geometry": {"coordinates":[-1.205573,50.881649],"type":"Point"}
}
