{
  "type": "Feature",
  "properties": {
    "date:inception_lower":"1993-01-01",
    "date:inception_upper":"1993-01-31",
    "iso:country":"GB",
    "wof:name":"WR4 0RS",
    "wof:placetype":"postalcode"
},
  "geometry": {"coordinates":[-2.176953,52.204272],"type":"Point"}
}