{
  "type": "Feature",
  "properties": {
    "iso:country": "GB",
    "wof:name": "WR4 0RS",
    "wof:placetype": "postalcode"
  },
  "geometry": {"coordinates":[-2.176953,52.204272],"type":"Point"}
}
