{
  "type": "Feature",
  "properties": {
    "date:inception_lower": "1980-01-01",
    "date:inception_upper": "1980-01-01",
    "iso:country": "GB",
    "wof:name": "PE37 7SE",
    "wof:placetype": "postalcode"
  },
  "geometry": {"coordinates":[0.689272,52.636756],"type":"Point"}
}
