{
  "type": "Feature",
  "properties": {
    "date:inception_lower": "2010-01-01",
    "date:inception_upper": "2010-01-01",
    "iso:country": "GB",
    "wof:name": "L20 4DN",
    "wof:placetype": "postalcode"
  },
  "geometry": {"coordinates":[-3.001258,53.453016],"type":"Point"}
}
