{
  "type": "Feature",
  "properties": {
    "iso:country":"GB",
    "wof:name":"BL1 2JJ",
    "wof:placetype":"postalcode"
},
  "geometry": {"coordinates":[-2.43232847407476,53.58697166659166],"type":"Point"}
}