{
  "type": "Feature",
  "properties": {
    "iso:country":"GB",
    "wof:name":"BD21 3JQ",
    "wof:placetype":"postalcode"
},
  "geometry": {"coordinates":[-1.9070444255783,53.86958340609994],"type":"Point"}
}