{
  "type": "Feature",
  "properties": {
    "date:inception_lower":"2002-09-01",
    "date:inception_upper":"2002-09-30",
    "iso:country":"GB",
    "wof:name":"BS1 5QR",
    "wof:placetype":"postalcode"
},
  "geometry": {"coordinates":[-2.603429,51.451027],"type":"Point"}
}