{
  "type": "Feature",
  "properties": {
    "date:inception_lower":"2000-12-01",
    "date:inception_upper":"2000-12-31",
    "iso:country":"GB",
    "wof:name":"W1J 0QY",
    "wof:placetype":"postalcode"
},
  "geometry": {"coordinates":[-0.140569,51.509401],"type":"Point"}
}