{
  "type": "Feature",
  "properties": {
    "date:inception_lower": "2021-01-01",
    "date:inception_upper": "2021-01-01",
    "iso:country": "GB",
    "wof:name": "GL3 1FG",
    "wof:placetype": "postalcode"
  },
  "geometry": {"coordinates":[-2.209041,51.889527],"type":"Point"}
}
