{
  "type": "Feature",
  "properties": {
    "iso:country": "GB",
    "wof:name": "SA68 0RD",
    "wof:placetype": "postalcode"
  },
  "geometry": {"coordinates":[-4.740474,51.721354],"type":"Point"}
}
