{
  "type": "Feature",
  "properties": {
    "date:inception_lower": "1980-01-01",
    "date:inception_upper": "1980-01-01",
    "iso:country": "GB",
    "wof:name": "SA68 0RD",
    "wof:placetype": "postalcode"
  },
  "geometry": {"coordinates":[-4.740474,51.721354],"type":"Point"}
}
