{
  "type": "Feature",
  "properties": {
    "iso:country":"GB",
    "wof:name":"SA68 0RD",
    "wof:placetype":"postalcode"
},
  "geometry": {"coordinates":[-4.74047409524487,51.72135394654511],"type":"Point"}
}