{
  "type": "Feature",
  "properties": {
    "iso:country":"GB",
    "wof:name":"G74 4RX",
    "wof:placetype":"postalcode"
},
  "geometry": {"coordinates":[-4.18211398731596,55.77438062843501],"type":"Point"}
}