{
  "type": "Feature",
  "properties": {
    "iso:country":"GB",
    "wof:name":"S81 9QW",
    "wof:placetype":"postalcode"
},
  "geometry": {"coordinates":[-1.12126248383171,53.37108197841164],"type":"Point"}
}