{
  "type": "Feature",
  "properties": {
    "date:inception_lower": "2001-12-01",
    "date:inception_upper": "2001-12-01",
    "iso:country": "GB",
    "wof:name": "RG27 8NR",
    "wof:placetype": "postalcode"
  },
  "geometry": {"coordinates":[-0.911254,51.309672],"type":"Point"}
}
