{
  "type": "Feature",
  "properties": {
    "iso:country": "GB",
    "wof:name": "RG27 8NR",
    "wof:placetype": "postalcode"
  },
  "geometry": {"coordinates":[-0.911254,51.309672],"type":"Point"}
}
