{
  "type": "Feature",
  "properties": {
    "iso:country":"GB",
    "wof:name":"EN6 4DJ",
    "wof:placetype":"postalcode"
},
  "geometry": {"coordinates":[-0.12319528271396,51.69381906859769],"type":"Point"}
}