{
  "type": "Feature",
  "properties": {
    "date:inception_lower": "2022-02-01",
    "date:inception_upper": "2022-02-01",
    "iso:country": "GB",
    "wof:name": "HG5 0TW",
    "wof:placetype": "postalcode"
  },
  "geometry": {"coordinates":[-1.439026,54.039238],"type":"Point"}
}
