{
  "type": "Feature",
  "properties": {
    "date:inception_lower":"1980-01-01",
    "date:inception_upper":"1980-01-31",
    "iso:country":"GB",
    "wof:name":"SY2 5TB",
    "wof:placetype":"postalcode"
},
  "geometry": {"coordinates":[-2.7231,52.71986],"type":"Point"}
}