{
  "type": "Feature",
  "properties": {
    "iso:country":"GB",
    "wof:name":"SY2 5TB",
    "wof:placetype":"postalcode"
},
  "geometry": {"coordinates":[-2.72310005703913,52.7198596220454],"type":"Point"}
}