{
  "type": "Feature",
  "properties": {
    "iso:country":"GB",
    "wof:name":"CF11 8DJ",
    "wof:placetype":"postalcode"
},
  "geometry": {"coordinates":[-3.2187187120692,51.48165415882478],"type":"Point"}
}