{
  "type": "Feature",
  "properties": {
    "iso:country": "GB",
    "wof:name": "CF11 8DJ",
    "wof:placetype": "postalcode"
  },
  "geometry": {"coordinates":[-3.218719,51.481654],"type":"Point"}
}
