{
  "type": "Feature",
  "properties": {
    "date:inception_lower": "2002-12-01",
    "date:inception_upper": "2002-12-01",
    "iso:country": "GB",
    "wof:name": "DL8 4DY",
    "wof:placetype": "postalcode"
  },
  "geometry": {"coordinates":[-1.923515,54.311044],"type":"Point"}
}
