{
  "type": "Feature",
  "properties": {
    "date:inception_lower":"1980-01-01",
    "date:inception_upper":"1980-01-31",
    "iso:country":"GB",
    "wof:name":"M33 4LW",
    "wof:placetype":"postalcode"
},
  "geometry": {"coordinates":[-2.356165,53.411076],"type":"Point"}
}