{
  "type": "Feature",
  "properties": {
    "iso:country":"GB",
    "wof:name":"M33 4LW",
    "wof:placetype":"postalcode"
},
  "geometry": {"coordinates":[-2.35616538312497,53.41107598316865],"type":"Point"}
}