{
  "type": "Feature",
  "properties": {
    "iso:country":"GB",
    "wof:name":"SG1 4EU",
    "wof:placetype":"postalcode"
},
  "geometry": {"coordinates":[-0.18796518685867,51.92192113029432],"type":"Point"}
}