{
  "type": "Feature",
  "properties": {
    "iso:country":"GB",
    "wof:name":"GL3 1AR",
    "wof:placetype":"postalcode"
},
  "geometry": {"coordinates":[-2.20843612937509,51.88663473453171],"type":"Point"}
}