{
  "type": "Feature",
  "properties": {
    "iso:country":"GB",
    "wof:name":"PL10 1EE",
    "wof:placetype":"postalcode"
},
  "geometry": {"coordinates":[-4.21711982300992,50.35214746790652],"type":"Point"}
}