{
  "type": "Feature",
  "properties": {
    "iso:country":"GB",
    "wof:name":"NW1 6DB",
    "wof:placetype":"postalcode"
},
  "geometry": {"coordinates":[-0.16147994933305,51.52476587241966],"type":"Point"}
}