{
  "type": "Feature",
  "properties": {
    "iso:country": "GB",
    "wof:name": "LN13 9BB",
    "wof:placetype": "postalcode"
  },
  "geometry": {"coordinates":[0.175951,53.255532],"type":"Point"}
}
