{
  "type": "Feature",
  "properties": {
    "iso:country":"GB",
    "wof:name":"LN13 9BB",
    "wof:placetype":"postalcode"
},
  "geometry": {"coordinates":[0.17595092722518,53.25553196282422],"type":"Point"}
}