{
  "type": "Feature",
  "properties": {
    "iso:country":"GB",
    "wof:name":"PH33 6TR",
    "wof:placetype":"postalcode"
},
  "geometry": {"coordinates":[-5.11307549323794,56.80976187152947],"type":"Point"}
}