{
  "type": "Feature",
  "properties": {
    "date:inception_lower": "2005-06-01",
    "date:inception_upper": "2005-06-01",
    "iso:country": "GB",
    "wof:name": "ME9 8GY",
    "wof:placetype": "postalcode"
  },
  "geometry": {"coordinates":[0.69458,51.369932],"type":"Point"}
}
