{
  "type": "Feature",
  "properties": {
    "iso:country":"GB",
    "wof:name":"G5 0PQ",
    "wof:placetype":"postalcode"
},
  "geometry": {"coordinates":[-4.2452695819879,55.85108341859981],"type":"Point"}
}