{
  "type": "Feature",
  "properties": {
    "date:inception_lower": "1980-01-01",
    "date:inception_upper": "1980-01-01",
    "iso:country": "GB",
    "wof:name": "G5 0PQ",
    "wof:placetype": "postalcode"
  },
  "geometry": {"coordinates":[-4.245287,55.851078],"type":"Point"}
}
