{
  "type": "Feature",
  "properties": {
    "iso:country":"GB",
    "wof:name":"DH8 5TT",
    "wof:placetype":"postalcode"
},
  "geometry": {"coordinates":[-1.83717824684638,54.86392407653414],"type":"Point"}
}