{
  "type": "Feature",
  "properties": {
    "date:inception_lower": "1980-01-01",
    "date:inception_upper": "1980-01-01",
    "iso:country": "GB",
    "wof:name": "DH8 5TT",
    "wof:placetype": "postalcode"
  },
  "geometry": {"coordinates":[-1.837188,54.863932],"type":"Point"}
}
