{
  "type": "Feature",
  "properties": {
    "iso:country":"GB",
    "wof:name":"WA9 5UL",
    "wof:placetype":"postalcode"
},
  "geometry": {"coordinates":[-2.76566979529533,53.43005954091577],"type":"Point"}
}