{
  "type": "Feature",
  "properties": {
    "iso:country":"GB",
    "wof:name":"SO16 8AA",
    "wof:placetype":"postalcode"
},
  "geometry": {"coordinates":[-1.46595521769404,50.95293873413907],"type":"Point"}
}