{
  "type": "Feature",
  "properties": {
    "iso:country": "GB",
    "wof:name": "BB11 5BQ",
    "wof:placetype": "postalcode"
  },
  "geometry": {"coordinates":[-2.266979,53.785896],"type":"Point"}
}
