{
  "type": "Feature",
  "properties": {
    "iso:country":"GB",
    "wof:name":"SE6 4LE",
    "wof:placetype":"postalcode"
},
  "geometry": {"coordinates":[-0.03095163282104,51.43935712189425],"type":"Point"}
}