{
  "type": "Feature",
  "properties": {
    "iso:country": "GB",
    "wof:name": "TQ12 1QS",
    "wof:placetype": "postalcode"
  },
  "geometry": {"coordinates":[-3.612838,50.525843],"type":"Point"}
}
