{
  "type": "Feature",
  "properties": {
    "date:inception_lower":"2003-05-01",
    "date:inception_upper":"2003-05-31",
    "iso:country":"GB",
    "wof:name":"TQ12 1QS",
    "wof:placetype":"postalcode"
},
  "geometry": {"coordinates":[-3.612838,50.525843],"type":"Point"}
}