{
  "type": "Feature",
  "properties": {
    "iso:country":"GB",
    "wof:name":"N21 2LT",
    "wof:placetype":"postalcode"
},
  "geometry": {"coordinates":[-0.09211644470089,51.64043436069971],"type":"Point"}
}