{
  "type": "Feature",
  "properties": {
    "iso:country":"GB",
    "wof:name":"ST18 0PT",
    "wof:placetype":"postalcode"
},
  "geometry": {"coordinates":[-2.00191694118203,52.82596654433398],"type":"Point"}
}