{
  "type": "Feature",
  "properties": {
    "iso:country": "GB",
    "wof:name": "BH6 4EP",
    "wof:placetype": "postalcode"
  },
  "geometry": {"coordinates":[-1.78064,50.72183],"type":"Point"}
}
