{
  "type": "Feature",
  "properties": {
    "iso:country": "GB",
    "wof:name": "SP3 6AS",
    "wof:placetype": "postalcode"
  },
  "geometry": {"coordinates":[-2.171553,51.068431],"type":"Point"}
}
