{
  "type": "Feature",
  "properties": {
    "iso:country":"GB",
    "wof:name":"SP3 6AS",
    "wof:placetype":"postalcode"
},
  "geometry": {"coordinates":[-2.17155326814847,51.0684311901467],"type":"Point"}
}