{
  "type": "Feature",
  "properties": {
    "iso:country":"GB",
    "wof:name":"BS21 6YL",
    "wof:placetype":"postalcode"
},
  "geometry": {"coordinates":[-2.83826193408344,51.43691286777243],"type":"Point"}
}