{
  "type": "Feature",
  "properties": {
    "date:inception_lower": "1980-01-01",
    "date:inception_upper": "1980-01-01",
    "iso:country": "GB",
    "wof:name": "WC1N 1JX",
    "wof:placetype": "postalcode"
  },
  "geometry": {"coordinates":[-0.126077,51.524709],"type":"Point"}
}
