{
  "type": "Feature",
  "properties": {
    "iso:country":"GB",
    "wof:name":"WC1N 1JX",
    "wof:placetype":"postalcode"
},
  "geometry": {"coordinates":[-0.12607739122296,51.52470922014268],"type":"Point"}
}