{
  "type": "Feature",
  "properties": {
    "iso:country":"GB",
    "wof:name":"WR3 7BZ",
    "wof:placetype":"postalcode"
},
  "geometry": {"coordinates":[-2.22706201010955,52.21692502119161],"type":"Point"}
}