{
  "type": "Feature",
  "properties": {
    "iso:country":"GB",
    "wof:name":"KA7 1BJ",
    "wof:placetype":"postalcode"
},
  "geometry": {"coordinates":[-4.63362180919395,55.46399650650478],"type":"Point"}
}