{
  "type": "Feature",
  "properties": {
    "iso:country":"GB",
    "wof:name":"HP23 6BN",
    "wof:placetype":"postalcode"
},
  "geometry": {"coordinates":[-0.66464138188247,51.79046335683911],"type":"Point"}
}