{
  "type": "Feature",
  "properties": {
    "date:inception_lower": "2021-12-01",
    "date:inception_upper": "2021-12-01",
    "iso:country": "GB",
    "wof:name": "HA7 3FW",
    "wof:placetype": "postalcode"
  },
  "geometry": {"coordinates":[-0.312522,51.617753],"type":"Point"}
}
