{
  "type": "Feature",
  "properties": {
    "date:inception_lower": "2000-06-01",
    "date:inception_upper": "2000-06-01",
    "iso:country": "GB",
    "wof:name": "TF1 5RY",
    "wof:placetype": "postalcode"
  },
  "geometry": {"coordinates":[-2.466384,52.704813],"type":"Point"}
}
