{
  "type": "Feature",
  "properties": {
    "iso:country": "GB",
    "wof:name": "ME14 4QR",
    "wof:placetype": "postalcode"
  },
  "geometry": {"coordinates":[0.57556,51.275325],"type":"Point"}
}
