{
  "type": "Feature",
  "properties": {
    "date:inception_lower": "2012-02-01",
    "date:inception_upper": "2012-02-01",
    "iso:country": "GB",
    "wof:name": "ME14 4QR",
    "wof:placetype": "postalcode"
  },
  "geometry": {"coordinates":[0.57556,51.275325],"type":"Point"}
}
