{
  "type": "Feature",
  "properties": {
    "date:inception_lower": "1980-01-01",
    "date:inception_upper": "1980-01-01",
    "iso:country": "GB",
    "wof:name": "OL2 8LR",
    "wof:placetype": "postalcode"
  },
  "geometry": {"coordinates":[-2.075015,53.581753],"type":"Point"}
}
