{
  "type": "Feature",
  "properties": {
    "iso:country":"GB",
    "wof:name":"CA2 4NF",
    "wof:placetype":"postalcode"
},
  "geometry": {"coordinates":[-2.92038480219799,54.87188489821341],"type":"Point"}
}