{
  "type": "Feature",
  "properties": {
    "iso:country": "GB",
    "wof:name": "CA2 4NF",
    "wof:placetype": "postalcode"
  },
  "geometry": {"coordinates":[-2.920483,54.871909],"type":"Point"}
}
