{
  "type": "Feature",
  "properties": {
    "date:inception_lower": "1991-09-01",
    "date:inception_upper": "1991-09-01",
    "iso:country": "GB",
    "wof:name": "S63 6PW",
    "wof:placetype": "postalcode"
  },
  "geometry": {"coordinates":[-1.349107,53.503731],"type":"Point"}
}
