{
  "type": "Feature",
  "properties": {
    "iso:country":"GB",
    "wof:name":"S63 6PW",
    "wof:placetype":"postalcode"
},
  "geometry": {"coordinates":[-1.34910743295264,53.50373087007377],"type":"Point"}
}