{
  "type": "Feature",
  "properties": {
    "iso:country":"GB",
    "wof:name":"W1U 6JD",
    "wof:placetype":"postalcode"
},
  "geometry": {"coordinates":[-0.15886043956971,51.51930232453923],"type":"Point"}
}