{
  "type": "Feature",
  "properties": {
    "iso:country": "GB",
    "wof:name": "WF9 3TB",
    "wof:placetype": "postalcode"
  },
  "geometry": {"coordinates":[-1.321671,53.596052],"type":"Point"}
}
