{
  "type": "Feature",
  "properties": {
    "date:inception_lower": "2003-04-01",
    "date:inception_upper": "2003-04-01",
    "iso:country": "GB",
    "wof:name": "WF9 3TB",
    "wof:placetype": "postalcode"
  },
  "geometry": {"coordinates":[-1.321671,53.596052],"type":"Point"}
}
