{
  "type": "Feature",
  "properties": {
    "iso:country":"GB",
    "wof:name":"AL4 0NR",
    "wof:placetype":"postalcode"
},
  "geometry": {"coordinates":[-0.26360417788913,51.73994977128739],"type":"Point"}
}