{
  "type": "Feature",
  "properties": {
    "iso:country":"GB",
    "wof:name":"SR4 0AH",
    "wof:placetype":"postalcode"
},
  "geometry": {"coordinates":[-1.44575070759306,54.90741426678377],"type":"Point"}
}