{
  "type": "Feature",
  "properties": {
    "iso:country":"GB",
    "wof:name":"CB21 5GA",
    "wof:placetype":"postalcode"
},
  "geometry": {"coordinates":[0.21403246623111,52.18094550935702],"type":"Point"}
}