{
  "type": "Feature",
  "properties": {
    "iso:country": "GB",
    "wof:name": "CB21 5GA",
    "wof:placetype": "postalcode"
  },
  "geometry": {"coordinates":[0.214033,52.180946],"type":"Point"}
}
