{
  "type": "Feature",
  "properties": {
    "iso:country":"GB",
    "wof:name":"BL4 9EB",
    "wof:placetype":"postalcode"
},
  "geometry": {"coordinates":[-2.40038420150953,53.54758800331744],"type":"Point"}
}