{
  "type": "Feature",
  "properties": {
    "iso:country":"GB",
    "wof:name":"SS9 1RN",
    "wof:placetype":"postalcode"
},
  "geometry": {"coordinates":[0.65876287303396,51.54261064706976],"type":"Point"}
}