{
  "type": "Feature",
  "properties": {
    "date:inception_lower": "2016-06-01",
    "date:inception_upper": "2016-06-01",
    "iso:country": "GB",
    "wof:name": "PL27 7FR",
    "wof:placetype": "postalcode"
  },
  "geometry": {"coordinates":[-4.8359,50.513922],"type":"Point"}
}
