{
  "type": "Feature",
  "properties": {
    "date:inception_lower": "2020-12-01",
    "date:inception_upper": "2020-12-01",
    "iso:country": "GB",
    "wof:name": "PE11 4DL",
    "wof:placetype": "postalcode"
  },
  "geometry": {"coordinates":[-0.123218,52.843062],"type":"Point"}
}
