{
  "type": "Feature",
  "properties": {
    "iso:country":"GB",
    "wof:name":"E20 1DL",
    "wof:placetype":"postalcode"
},
  "geometry": {"coordinates":[-0.01061590904928,51.54698894109062],"type":"Point"}
}