{
  "type": "Feature",
  "properties": {
    "iso:country":"GB",
    "wof:name":"NG34 8JN",
    "wof:placetype":"postalcode"
},
  "geometry": {"coordinates":[-0.42378566488326,53.02251273679106],"type":"Point"}
}