{
  "type": "Feature",
  "properties": {
    "iso:country":"GB",
    "wof:name":"NG5 8HR",
    "wof:placetype":"postalcode"
},
  "geometry": {"coordinates":[-1.13108839991876,53.01286382908695],"type":"Point"}
}