{
  "type": "Feature",
  "properties": {
    "date:inception_lower": "1997-12-01",
    "date:inception_upper": "1997-12-01",
    "iso:country": "GB",
    "wof:name": "DN15 8LS",
    "wof:placetype": "postalcode"
  },
  "geometry": {"coordinates":[-0.655832,53.598618],"type":"Point"}
}
