{
  "type": "Feature",
  "properties": {
    "iso:country":"GB",
    "wof:name":"EX31 3BQ",
    "wof:placetype":"postalcode"
},
  "geometry": {"coordinates":[-4.12801690858129,51.06845098181747],"type":"Point"}
}