{
  "type": "Feature",
  "properties": {
    "date:inception_lower": "1980-01-01",
    "date:inception_upper": "1980-01-01",
    "iso:country": "GB",
    "wof:name": "NR14 8HP",
    "wof:placetype": "postalcode"
  },
  "geometry": {"coordinates":[1.224537,52.568608],"type":"Point"}
}
