{
  "type": "Feature",
  "properties": {
    "iso:country":"GB",
    "wof:name":"RH19 4RL",
    "wof:placetype":"postalcode"
},
  "geometry": {"coordinates":[0.00136202344467,51.11992729044361],"type":"Point"}
}