{
  "type": "Feature",
  "properties": {
    "date:inception_lower": "2021-06-01",
    "date:inception_upper": "2021-06-01",
    "iso:country": "GB",
    "wof:name": "PR4 9DF",
    "wof:placetype": "postalcode"
  },
  "geometry": {"coordinates":[-2.872573,53.777522],"type":"Point"}
}
