{
  "type": "Feature",
  "properties": {
    "iso:country": "GB",
    "wof:name": "BH16 6EJ",
    "wof:placetype": "postalcode"
  },
  "geometry": {"coordinates":[-2.082739,50.747779],"type":"Point"}
}
