{
  "type": "Feature",
  "properties": {
    "iso:country":"GB",
    "wof:name":"BH16 6EJ",
    "wof:placetype":"postalcode"
},
  "geometry": {"coordinates":[-2.08273864787754,50.74777874122826],"type":"Point"}
}