{
  "type": "Feature",
  "properties": {
    "iso:country": "GB",
    "wof:name": "SY5 9AJ",
    "wof:placetype": "postalcode"
  },
  "geometry": {"coordinates":[-2.954759,52.726086],"type":"Point"}
}
