{
  "type": "Feature",
  "properties": {
    "iso:country":"GB",
    "wof:name":"SY5 9AJ",
    "wof:placetype":"postalcode"
},
  "geometry": {"coordinates":[-2.95475923796839,52.72608633959648],"type":"Point"}
}