{
  "type": "Feature",
  "properties": {
    "iso:country":"GB",
    "wof:name":"BH9 1ES",
    "wof:placetype":"postalcode"
},
  "geometry": {"coordinates":[-1.87187646465563,50.74060703092567],"type":"Point"}
}