{
  "type": "Feature",
  "properties": {
    "iso:country":"GB",
    "wof:name":"LE9 9PB",
    "wof:placetype":"postalcode"
},
  "geometry": {"coordinates":[-1.34064987240258,52.63169360673356],"type":"Point"}
}