{
  "type": "Feature",
  "properties": {
    "iso:country":"GB",
    "wof:name":"HU6 7TH",
    "wof:placetype":"postalcode"
},
  "geometry": {"coordinates":[-0.35849706626151,53.77246099039482],"type":"Point"}
}