{
  "type": "Feature",
  "properties": {
    "date:inception_lower":"1980-01-01",
    "date:inception_upper":"1980-01-31",
    "iso:country":"GB",
    "wof:name":"HU6 7TH",
    "wof:placetype":"postalcode"
},
  "geometry": {"coordinates":[-0.358497,53.772461],"type":"Point"}
}