{
  "type": "Feature",
  "properties": {
    "iso:country": "GB",
    "wof:name": "HU6 7TH",
    "wof:placetype": "postalcode"
  },
  "geometry": {"coordinates":[-0.358497,53.772461],"type":"Point"}
}
