{
  "type": "Feature",
  "properties": {
    "iso:country":"GB",
    "wof:name":"YO26 5QJ",
    "wof:placetype":"postalcode"
},
  "geometry": {"coordinates":[-1.13300570742406,53.9638217889538],"type":"Point"}
}