{
  "type": "Feature",
  "properties": {
    "iso:country": "GB",
    "wof:name": "YO26 5QJ",
    "wof:placetype": "postalcode"
  },
  "geometry": {"coordinates":[-1.133006,53.963822],"type":"Point"}
}
