{
  "type": "Feature",
  "properties": {
    "date:inception_lower":"1980-01-01",
    "date:inception_upper":"1980-01-31",
    "iso:country":"GB",
    "wof:name":"SA14 6AB",
    "wof:placetype":"postalcode"
},
  "geometry": {"coordinates":[-4.118127,51.755576],"type":"Point"}
}