{
  "type": "Feature",
  "properties": {
    "iso:country":"GB",
    "wof:name":"SA14 6AB",
    "wof:placetype":"postalcode"
},
  "geometry": {"coordinates":[-4.11812708388908,51.75557591564454],"type":"Point"}
}