{
  "type": "Feature",
  "properties": {
    "iso:country": "GB",
    "wof:name": "CH2 3RL",
    "wof:placetype": "postalcode"
  },
  "geometry": {"coordinates":[-2.869636,53.20394],"type":"Point"}
}
