{
  "type": "Feature",
  "properties": {
    "iso:country": "GB",
    "wof:name": "SA11 2BU",
    "wof:placetype": "postalcode"
  },
  "geometry": {"coordinates":[-3.810002,51.651652],"type":"Point"}
}
