{
  "type": "Feature",
  "properties": {
    "iso:country":"GB",
    "wof:name":"HP23 5DT",
    "wof:placetype":"postalcode"
},
  "geometry": {"coordinates":[-0.65880292983538,51.80056639080163],"type":"Point"}
}