{
  "type": "Feature",
  "properties": {
    "iso:country": "GB",
    "wof:name": "OX4 7TT",
    "wof:placetype": "postalcode"
  },
  "geometry": {"coordinates":[-1.188567,51.720078],"type":"Point"}
}
