{
  "type": "Feature",
  "properties": {
    "iso:country":"GB",
    "wof:name":"WR14 2DB",
    "wof:placetype":"postalcode"
},
  "geometry": {"coordinates":[-2.30424758325637,52.11051968118302],"type":"Point"}
}