{
  "type": "Feature",
  "properties": {
    "date:inception_lower": "1980-01-01",
    "date:inception_upper": "1980-01-01",
    "iso:country": "GB",
    "wof:name": "CR4 4HQ",
    "wof:placetype": "postalcode"
  },
  "geometry": {"coordinates":[-0.160773,51.391206],"type":"Point"}
}
