{
  "type": "Feature",
  "properties": {
    "iso:country":"GB",
    "wof:name":"OX15 5QD",
    "wof:placetype":"postalcode"
},
  "geometry": {"coordinates":[-1.48009083147804,51.99347308263889],"type":"Point"}
}