{
  "type": "Feature",
  "properties": {
    "iso:country": "GB",
    "wof:name": "OX15 5QD",
    "wof:placetype": "postalcode"
  },
  "geometry": {"coordinates":[-1.480091,51.993473],"type":"Point"}
}
