{
  "type": "Feature",
  "properties": {
    "iso:country":"GB",
    "wof:name":"L15 3JT",
    "wof:placetype":"postalcode"
},
  "geometry": {"coordinates":[-2.93111914438002,53.39060034755202],"type":"Point"}
}