{
  "type": "Feature",
  "properties": {
    "date:inception_lower":"1998-12-01",
    "date:inception_upper":"1998-12-31",
    "iso:country":"GB",
    "wof:name":"SG1 3XE",
    "wof:placetype":"postalcode"
},
  "geometry": {"coordinates":[-0.202046,51.913829],"type":"Point"}
}