{
  "type": "Feature",
  "properties": {
    "iso:country":"GB",
    "wof:name":"PL25 3RF",
    "wof:placetype":"postalcode"
},
  "geometry": {"coordinates":[-4.73773222939075,50.3436396272177],"type":"Point"}
}