{
  "type": "Feature",
  "properties": {
    "iso:country":"GB",
    "wof:name":"GL51 3XG",
    "wof:placetype":"postalcode"
},
  "geometry": {"coordinates":[-2.10456741193738,51.88135160147274],"type":"Point"}
}