{
  "type": "Feature",
  "properties": {
    "iso:country": "GB",
    "wof:name": "NG17 8BF",
    "wof:placetype": "postalcode"
  },
  "geometry": {"coordinates":[-1.254538,53.099936],"type":"Point"}
}
