{
  "type": "Feature",
  "properties": {
    "iso:country":"GB",
    "wof:name":"DL13 4NL",
    "wof:placetype":"postalcode"
},
  "geometry": {"coordinates":[-1.79612048767921,54.72267558511101],"type":"Point"}
}