{
  "type": "Feature",
  "properties": {
    "iso:country": "GB",
    "wof:name": "IG10 3SL",
    "wof:placetype": "postalcode"
  },
  "geometry": {"coordinates":[0.089896,51.64694],"type":"Point"}
}
