{
  "type": "Feature",
  "properties": {
    "iso:country":"GB",
    "wof:name":"SL1 7DB",
    "wof:placetype":"postalcode"
},
  "geometry": {"coordinates":[-0.66232125242225,51.53759731497603],"type":"Point"}
}