{
  "type": "Feature",
  "properties": {
    "iso:country":"GB",
    "wof:name":"BN7 2LH",
    "wof:placetype":"postalcode"
},
  "geometry": {"coordinates":[0.01430055342749,50.87391568855693],"type":"Point"}
}