{
  "type": "Feature",
  "properties": {
    "iso:country":"GB",
    "wof:name":"BS6 6RH",
    "wof:placetype":"postalcode"
},
  "geometry": {"coordinates":[-2.60566548462795,51.46993344393054],"type":"Point"}
}