{
  "type": "Feature",
  "properties": {
    "date:inception_lower": "1980-01-01",
    "date:inception_upper": "1980-01-01",
    "iso:country": "GB",
    "wof:name": "BS6 6RH",
    "wof:placetype": "postalcode"
  },
  "geometry": {"coordinates":[-2.605665,51.469933],"type":"Point"}
}
