{
  "type": "Feature",
  "properties": {
    "iso:country": "GB",
    "wof:name": "SK6 2AH",
    "wof:placetype": "postalcode"
  },
  "geometry": {"coordinates":[-2.114054,53.422915],"type":"Point"}
}
