{
  "type": "Feature",
  "properties": {
    "iso:country":"GB",
    "wof:name":"DY8 5RE",
    "wof:placetype":"postalcode"
},
  "geometry": {"coordinates":[-2.16049733092902,52.48115657903471],"type":"Point"}
}