{
  "type": "Feature",
  "properties": {
    "iso:country":"GB",
    "wof:name":"M24 5QN",
    "wof:placetype":"postalcode"
},
  "geometry": {"coordinates":[-2.21335013215701,53.55701169111851],"type":"Point"}
}