{
  "type": "Feature",
  "properties": {
    "iso:country":"GB",
    "wof:name":"NR16 2RY",
    "wof:placetype":"postalcode"
},
  "geometry": {"coordinates":[0.878039980193,52.43520477627806],"type":"Point"}
}