{
  "type": "Feature",
  "properties": {
    "iso:country": "GB",
    "wof:name": "NR16 2RY",
    "wof:placetype": "postalcode"
  },
  "geometry": {"coordinates":[0.87804,52.435205],"type":"Point"}
}
