{
  "type": "Feature",
  "properties": {
    "date:inception_lower": "1980-01-01",
    "date:inception_upper": "1980-01-01",
    "iso:country": "GB",
    "wof:name": "NR16 2RY",
    "wof:placetype": "postalcode"
  },
  "geometry": {"coordinates":[0.87804,52.435205],"type":"Point"}
}
