{
  "type": "Feature",
  "properties": {
    "iso:country":"GB",
    "wof:name":"NN11 3TN",
    "wof:placetype":"postalcode"
},
  "geometry": {"coordinates":[-1.21481408033925,52.16923918105487],"type":"Point"}
}