{
  "type": "Feature",
  "properties": {
    "iso:country":"GB",
    "wof:name":"DE13 0RH",
    "wof:placetype":"postalcode"
},
  "geometry": {"coordinates":[-1.65455887774823,52.82897961343102],"type":"Point"}
}