{
  "type": "Feature",
  "properties": {
    "date:inception_lower": "2005-02-01",
    "date:inception_upper": "2005-02-01",
    "iso:country": "GB",
    "wof:name": "HX3 7WN",
    "wof:placetype": "postalcode"
  },
  "geometry": {"coordinates":[-1.832958,53.745838],"type":"Point"}
}
