{
  "type": "Feature",
  "properties": {
    "iso:country":"GB",
    "wof:name":"HX3 7WN",
    "wof:placetype":"postalcode"
},
  "geometry": {"coordinates":[-1.83295771886641,53.74583809871615],"type":"Point"}
}