{
  "type": "Feature",
  "properties": {
    "date:inception_lower": "1980-01-01",
    "date:inception_upper": "1980-01-01",
    "iso:country": "GB",
    "wof:name": "TN30 6ND",
    "wof:placetype": "postalcode"
  },
  "geometry": {"coordinates":[0.695511,51.077458],"type":"Point"}
}
