{
  "type": "Feature",
  "properties": {
    "iso:country":"GB",
    "wof:name":"B16 8DX",
    "wof:placetype":"postalcode"
},
  "geometry": {"coordinates":[-1.92505859731007,52.4777091732433],"type":"Point"}
}