{
  "type": "Feature",
  "properties": {
    "date:inception_lower": "2006-05-01",
    "date:inception_upper": "2006-05-01",
    "iso:country": "GB",
    "wof:name": "PL2 3LX",
    "wof:placetype": "postalcode"
  },
  "geometry": {"coordinates":[-4.150314,50.396549],"type":"Point"}
}
