{
  "type": "Feature",
  "properties": {
    "iso:country":"GB",
    "wof:name":"PL2 3LX",
    "wof:placetype":"postalcode"
},
  "geometry": {"coordinates":[-4.15031396915357,50.39654864266473],"type":"Point"}
}