{
  "type": "Feature",
  "properties": {
    "iso:country": "GB",
    "wof:name": "SA41 3TS",
    "wof:placetype": "postalcode"
  },
  "geometry": {"coordinates":[-4.766975,51.979293],"type":"Point"}
}
