{
  "type": "Feature",
  "properties": {
    "iso:country":"GB",
    "wof:name":"BN18 9JF",
    "wof:placetype":"postalcode"
},
  "geometry": {"coordinates":[-0.5614614932635,50.84952667562352],"type":"Point"}
}