{
  "type": "Feature",
  "properties": {
    "iso:country":"GB",
    "wof:name":"GL7 3PL",
    "wof:placetype":"postalcode"
},
  "geometry": {"coordinates":[-1.72305499017747,51.72967328630333],"type":"Point"}
}