{
  "type": "Feature",
  "properties": {
    "iso:country": "GB",
    "wof:name": "HD7 4ES",
    "wof:placetype": "postalcode"
  },
  "geometry": {"coordinates":[-1.856616,53.632933],"type":"Point"}
}
