{
  "type": "Feature",
  "properties": {
    "date:inception_lower":"1996-06-01",
    "date:inception_upper":"1996-06-30",
    "iso:country":"GB",
    "wof:name":"GU47 9DH",
    "wof:placetype":"postalcode"
},
  "geometry": {"coordinates":[-0.800943,51.346946],"type":"Point"}
}