{
  "type": "Feature",
  "properties": {
    "iso:country":"GB",
    "wof:name":"GU47 9DH",
    "wof:placetype":"postalcode"
},
  "geometry": {"coordinates":[-0.80094297229557,51.34694588666564],"type":"Point"}
}