{
  "type": "Feature",
  "properties": {
    "iso:country":"GB",
    "wof:name":"BH22 9BG",
    "wof:placetype":"postalcode"
},
  "geometry": {"coordinates":[-1.89182019832411,50.80056284314691],"type":"Point"}
}