{
  "type": "Feature",
  "properties": {
    "iso:country":"GB",
    "wof:name":"OX20 1BS",
    "wof:placetype":"postalcode"
},
  "geometry": {"coordinates":[-1.38928039164367,51.91225431696143],"type":"Point"}
}