{
  "type": "Feature",
  "properties": {
    "iso:country": "GB",
    "wof:name": "SS11 8QR",
    "wof:placetype": "postalcode"
  },
  "geometry": {"coordinates":[0.538265,51.609039],"type":"Point"}
}
