{
  "type": "Feature",
  "properties": {
    "iso:country":"GB",
    "wof:name":"SS11 8QR",
    "wof:placetype":"postalcode"
},
  "geometry": {"coordinates":[0.53724774476607,51.60916435970206],"type":"Point"}
}