{
  "type": "Feature",
  "properties": {
    "iso:country":"GB",
    "wof:name":"IG7 5LP",
    "wof:placetype":"postalcode"
},
  "geometry": {"coordinates":[0.08691036811204,51.60836930465295],"type":"Point"}
}