{
  "type": "Feature",
  "properties": {
    "date:inception_lower": "1980-01-01",
    "date:inception_upper": "1980-01-01",
    "iso:country": "GB",
    "wof:name": "IG7 5LP",
    "wof:placetype": "postalcode"
  },
  "geometry": {"coordinates":[0.086937,51.608371],"type":"Point"}
}
