{
  "type": "Feature",
  "properties": {
    "iso:country":"GB",
    "wof:name":"SW18 3RL",
    "wof:placetype":"postalcode"
},
  "geometry": {"coordinates":[-0.17013872647022,51.44933721204958],"type":"Point"}
}