{
  "type": "Feature",
  "properties": {
    "iso:country": "GB",
    "wof:name": "SW18 3RL",
    "wof:placetype": "postalcode"
  },
  "geometry": {"coordinates":[-0.170184,51.449384],"type":"Point"}
}
