{
  "type": "Feature",
  "properties": {
    "date:inception_lower": "2017-12-01",
    "date:inception_upper": "2017-12-01",
    "iso:country": "GB",
    "wof:name": "RG7 4AN",
    "wof:placetype": "postalcode"
  },
  "geometry": {"coordinates":[-1.129439,51.363407],"type":"Point"}
}
