{
  "type": "Feature",
  "properties": {
    "iso:country": "GB",
    "wof:name": "WS4 1LX",
    "wof:placetype": "postalcode"
  },
  "geometry": {"coordinates":[-1.95697,52.602565],"type":"Point"}
}
