{
  "type": "Feature",
  "properties": {
    "iso:country":"GB",
    "wof:name":"IP18 6JL",
    "wof:placetype":"postalcode"
},
  "geometry": {"coordinates":[1.68142772191792,52.32702633175261],"type":"Point"}
}