{
  "type": "Feature",
  "properties": {
    "iso:country":"GB",
    "wof:name":"SG5 3BB",
    "wof:placetype":"postalcode"
},
  "geometry": {"coordinates":[-0.34194225188861,51.93015240958236],"type":"Point"}
}