{
  "type": "Feature",
  "properties": {
    "date:inception_lower":"1997-06-01",
    "date:inception_upper":"1997-06-30",
    "iso:country":"GB",
    "wof:name":"S25 2LD",
    "wof:placetype":"postalcode"
},
  "geometry": {"coordinates":[-1.215443,53.36932],"type":"Point"}
}