{
  "type": "Feature",
  "properties": {
    "iso:country": "GB",
    "wof:name": "SL4 4PH",
    "wof:placetype": "postalcode"
  },
  "geometry": {"coordinates":[-0.65225,51.47434],"type":"Point"}
}
