{
  "type": "Feature",
  "properties": {
    "date:inception_lower": "1980-01-01",
    "date:inception_upper": "1980-01-01",
    "iso:country": "GB",
    "wof:name": "HP9 2RH",
    "wof:placetype": "postalcode"
  },
  "geometry": {"coordinates":[-0.60947,51.623845],"type":"Point"}
}
