{
  "type": "Feature",
  "properties": {
    "iso:country":"GB",
    "wof:name":"HP9 2RH",
    "wof:placetype":"postalcode"
},
  "geometry": {"coordinates":[-0.60947032814959,51.62384503341239],"type":"Point"}
}