{
  "type": "Feature",
  "properties": {
    "date:inception_lower": "1980-01-01",
    "date:inception_upper": "1980-01-01",
    "iso:country": "GB",
    "wof:name": "SG19 2AT",
    "wof:placetype": "postalcode"
  },
  "geometry": {"coordinates":[-0.305077,52.163561],"type":"Point"}
}
