{
  "type": "Feature",
  "properties": {
    "iso:country":"GB",
    "wof:name":"SG19 2AT",
    "wof:placetype":"postalcode"
},
  "geometry": {"coordinates":[-0.30507683171785,52.16356121082112],"type":"Point"}
}