{
  "type": "Feature",
  "properties": {
    "iso:country":"GB",
    "wof:name":"SA12 6DQ",
    "wof:placetype":"postalcode"
},
  "geometry": {"coordinates":[-3.79784786169252,51.59399997244076],"type":"Point"}
}