{
  "type": "Feature",
  "properties": {
    "iso:country": "GB",
    "wof:name": "SK14 6JU",
    "wof:placetype": "postalcode"
  },
  "geometry": {"coordinates":[-2.019324,53.447219],"type":"Point"}
}
