{
  "type": "Feature",
  "properties": {
    "iso:country":"GB",
    "wof:name":"SK14 6JU",
    "wof:placetype":"postalcode"
},
  "geometry": {"coordinates":[-2.0193237362369,53.44721873488744],"type":"Point"}
}