{
  "type": "Feature",
  "properties": {
    "date:inception_lower": "1981-06-01",
    "date:inception_upper": "1981-06-01",
    "iso:country": "GB",
    "wof:name": "SK14 6JU",
    "wof:placetype": "postalcode"
  },
  "geometry": {"coordinates":[-2.019324,53.447219],"type":"Point"}
}
