{
  "type": "Feature",
  "properties": {
    "iso:country": "GB",
    "wof:name": "DE56 2JY",
    "wof:placetype": "postalcode"
  },
  "geometry": {"coordinates":[-1.468258,53.055291],"type":"Point"}
}
