{
  "type": "Feature",
  "properties": {
    "iso:country":"GB",
    "wof:name":"BS21 7UT",
    "wof:placetype":"postalcode"
},
  "geometry": {"coordinates":[-2.86727924967349,51.43004779444128],"type":"Point"}
}