{
  "type": "Feature",
  "properties": {
    "iso:country":"GB",
    "wof:name":"S44 6QE",
    "wof:placetype":"postalcode"
},
  "geometry": {"coordinates":[-1.30468050154458,53.23016745114695],"type":"Point"}
}