{
  "type": "Feature",
  "properties": {
    "iso:country": "GB",
    "wof:name": "S44 6QE",
    "wof:placetype": "postalcode"
  },
  "geometry": {"coordinates":[-1.30468,53.230167],"type":"Point"}
}
