{
  "type": "Feature",
  "properties": {
    "iso:country":"GB",
    "wof:name":"DE23 8WJ",
    "wof:placetype":"postalcode"
},
  "geometry": {"coordinates":[-1.47934772240959,52.89621139381864],"type":"Point"}
}