{
  "type": "Feature",
  "properties": {
    "iso:country": "GB",
    "wof:name": "SA13 2RN",
    "wof:placetype": "postalcode"
  },
  "geometry": {"coordinates":[-3.707102,51.613439],"type":"Point"}
}
