{
  "type": "Feature",
  "properties": {
    "iso:country":"GB",
    "wof:name":"SA13 2RN",
    "wof:placetype":"postalcode"
},
  "geometry": {"coordinates":[-3.70710155258074,51.61343863932387],"type":"Point"}
}