{
  "type": "Feature",
  "properties": {
    "date:inception_lower": "1998-06-01",
    "date:inception_upper": "1998-06-01",
    "iso:country": "GB",
    "wof:name": "DE72 3UL",
    "wof:placetype": "postalcode"
  },
  "geometry": {"coordinates":[-1.41007,52.885775],"type":"Point"}
}
