{
  "type": "Feature",
  "properties": {
    "iso:country":"GB",
    "wof:name":"N17 8AL",
    "wof:placetype":"postalcode"
},
  "geometry": {"coordinates":[-0.07283778827132,51.6018836545657],"type":"Point"}
}