{
  "type": "Feature",
  "properties": {
    "iso:country": "GB",
    "wof:name": "IP28 6SH",
    "wof:placetype": "postalcode"
  },
  "geometry": {"coordinates":[0.516178,52.309585],"type":"Point"}
}
