{
  "type": "Feature",
  "properties": {
    "date:inception_lower": "1980-01-01",
    "date:inception_upper": "1980-01-01",
    "iso:country": "GB",
    "wof:name": "WD3 5BX",
    "wof:placetype": "postalcode"
  },
  "geometry": {"coordinates":[-0.523462,51.64505],"type":"Point"}
}
