{
  "type": "Feature",
  "properties": {
    "iso:country":"GB",
    "wof:name":"WD3 5BX",
    "wof:placetype":"postalcode"
},
  "geometry": {"coordinates":[-0.52346167126929,51.64505001009179],"type":"Point"}
}