{
  "type": "Feature",
  "properties": {
    "iso:country":"GB",
    "wof:name":"N13 5EL",
    "wof:placetype":"postalcode"
},
  "geometry": {"coordinates":[-0.09417434111997,51.61651202401387],"type":"Point"}
}