{
  "type": "Feature",
  "properties": {
    "iso:country":"GB",
    "wof:name":"RG4 6TP",
    "wof:placetype":"postalcode"
},
  "geometry": {"coordinates":[-0.92301970322028,51.47920720824293],"type":"Point"}
}