{
  "type": "Feature",
  "properties": {
    "iso:country":"GB",
    "wof:name":"S40 4SP",
    "wof:placetype":"postalcode"
},
  "geometry": {"coordinates":[-1.43344972909732,53.2394421879851],"type":"Point"}
}