{
  "type": "Feature",
  "properties": {
    "iso:country": "GB",
    "wof:name": "S40 4SP",
    "wof:placetype": "postalcode"
  },
  "geometry": {"coordinates":[-1.43345,53.239442],"type":"Point"}
}
