{
  "type": "Feature",
  "properties": {
    "date:inception_lower": "1980-01-01",
    "date:inception_upper": "1980-01-01",
    "iso:country": "GB",
    "wof:name": "S40 4SP",
    "wof:placetype": "postalcode"
  },
  "geometry": {"coordinates":[-1.43345,53.239442],"type":"Point"}
}
