{
  "type": "Feature",
  "properties": {
    "iso:country":"GB",
    "wof:name":"OL11 1AT",
    "wof:placetype":"postalcode"
},
  "geometry": {"coordinates":[-2.15889065355,53.60652316532138],"type":"Point"}
}