{
  "type": "Feature",
  "properties": {
    "date:inception_lower": "2014-06-01",
    "date:inception_upper": "2014-06-01",
    "iso:country": "GB",
    "wof:name": "OL11 1AT",
    "wof:placetype": "postalcode"
  },
  "geometry": {"coordinates":[-2.158891,53.606523],"type":"Point"}
}
