{
  "type": "Feature",
  "properties": {
    "date:inception_lower": "1980-01-01",
    "date:inception_upper": "1980-01-01",
    "iso:country": "GB",
    "wof:name": "S12 2SD",
    "wof:placetype": "postalcode"
  },
  "geometry": {"coordinates":[-1.429948,53.358582],"type":"Point"}
}
