{
  "type": "Feature",
  "properties": {
    "iso:country":"GB",
    "wof:name":"SN1 3HT",
    "wof:placetype":"postalcode"
},
  "geometry": {"coordinates":[-1.7719001092753,51.5523445558668],"type":"Point"}
}