{
  "type": "Feature",
  "properties": {
    "iso:country":"GB",
    "wof:name":"SA31 1DJ",
    "wof:placetype":"postalcode"
},
  "geometry": {"coordinates":[-4.30826403403272,51.85919586754407],"type":"Point"}
}