{
  "type": "Feature",
  "properties": {
    "iso:country": "GB",
    "wof:name": "EN7 6DH",
    "wof:placetype": "postalcode"
  },
  "geometry": {"coordinates":[-0.062035,51.720522],"type":"Point"}
}
