{
  "type": "Feature",
  "properties": {
    "date:inception_lower": "1995-12-01",
    "date:inception_upper": "1995-12-01",
    "iso:country": "GB",
    "wof:name": "G71 6TU",
    "wof:placetype": "postalcode"
  },
  "geometry": {"coordinates":[-4.070503,55.833317],"type":"Point"}
}
