{
  "type": "Feature",
  "properties": {
    "iso:country": "GB",
    "wof:name": "G71 6TU",
    "wof:placetype": "postalcode"
  },
  "geometry": {"coordinates":[-4.070503,55.833317],"type":"Point"}
}
