{
  "type": "Feature",
  "properties": {
    "iso:country":"GB",
    "wof:name":"G71 6TU",
    "wof:placetype":"postalcode"
},
  "geometry": {"coordinates":[-4.07050289414377,55.83331741027371],"type":"Point"}
}