{
  "type": "Feature",
  "properties": {
    "iso:country": "GB",
    "wof:name": "NE32 5ES",
    "wof:placetype": "postalcode"
  },
  "geometry": {"coordinates":[-1.495198,54.965475],"type":"Point"}
}
