{
  "type": "Feature",
  "properties": {
    "iso:country":"GB",
    "wof:name":"NE32 5ES",
    "wof:placetype":"postalcode"
},
  "geometry": {"coordinates":[-1.49519848961075,54.96547485619226],"type":"Point"}
}