{
  "type": "Feature",
  "properties": {
    "date:inception_lower": "2004-02-01",
    "date:inception_upper": "2004-02-01",
    "iso:country": "GB",
    "wof:name": "NE32 5ES",
    "wof:placetype": "postalcode"
  },
  "geometry": {"coordinates":[-1.495198,54.965475],"type":"Point"}
}
