{
  "type": "Feature",
  "properties": {
    "iso:country": "GB",
    "wof:name": "LN4 4BY",
    "wof:placetype": "postalcode"
  },
  "geometry": {"coordinates":[-0.165218,53.10003],"type":"Point"}
}
