{
  "type": "Feature",
  "properties": {
    "iso:country": "GB",
    "wof:name": "TN13 3AJ",
    "wof:placetype": "postalcode"
  },
  "geometry": {"coordinates":[0.184223,51.276897],"type":"Point"}
}
