{
  "type": "Feature",
  "properties": {
    "date:inception_lower":"1980-01-01",
    "date:inception_upper":"1980-01-31",
    "iso:country":"GB",
    "wof:name":"GU14 0HD",
    "wof:placetype":"postalcode"
},
  "geometry": {"coordinates":[-0.773422,51.291881],"type":"Point"}
}