{
  "type": "Feature",
  "properties": {
    "iso:country": "GB",
    "wof:name": "GU14 0HD",
    "wof:placetype": "postalcode"
  },
  "geometry": {"coordinates":[-0.773422,51.291881],"type":"Point"}
}
