{
  "type": "Feature",
  "properties": {
    "date:inception_lower": "1999-06-01",
    "date:inception_upper": "1999-06-01",
    "iso:country": "GB",
    "wof:name": "NP26 3PF",
    "wof:placetype": "postalcode"
  },
  "geometry": {"coordinates":[-2.814159,51.581291],"type":"Point"}
}
