{
  "type": "Feature",
  "properties": {
    "iso:country":"GB",
    "wof:name":"NP26 3PF",
    "wof:placetype":"postalcode"
},
  "geometry": {"coordinates":[-2.81415935911352,51.58129092556953],"type":"Point"}
}