{
  "type": "Feature",
  "properties": {
    "iso:country":"GB",
    "wof:name":"G74 1HZ",
    "wof:placetype":"postalcode"
},
  "geometry": {"coordinates":[-4.19016956654627,55.76364112169325],"type":"Point"}
}