{
  "type": "Feature",
  "properties": {
    "iso:country": "GB",
    "wof:name": "G74 1HZ",
    "wof:placetype": "postalcode"
  },
  "geometry": {"coordinates":[-4.19017,55.763641],"type":"Point"}
}
