{
  "type": "Feature",
  "properties": {
    "date:inception_lower": "2012-03-01",
    "date:inception_upper": "2012-03-01",
    "iso:country": "GB",
    "wof:name": "BA13 3FQ",
    "wof:placetype": "postalcode"
  },
  "geometry": {"coordinates":[-2.203558,51.252792],"type":"Point"}
}
