{
  "type": "Feature",
  "properties": {
    "iso:country": "GB",
    "wof:name": "BA13 3FQ",
    "wof:placetype": "postalcode"
  },
  "geometry": {"coordinates":[-2.203558,51.252792],"type":"Point"}
}
