{
  "type": "Feature",
  "properties": {
    "iso:country":"GB",
    "wof:name":"SK11 6LQ",
    "wof:placetype":"postalcode"
},
  "geometry": {"coordinates":[-2.12496500523964,53.25939113816569],"type":"Point"}
}