{
  "type": "Feature",
  "properties": {
    "iso:country": "GB",
    "wof:name": "SK11 6LQ",
    "wof:placetype": "postalcode"
  },
  "geometry": {"coordinates":[-2.124965,53.259391],"type":"Point"}
}
