{
  "type": "Feature",
  "properties": {
    "date:inception_lower": "1980-01-01",
    "date:inception_upper": "1980-01-01",
    "iso:country": "GB",
    "wof:name": "LS11 5HU",
    "wof:placetype": "postalcode"
  },
  "geometry": {"coordinates":[-1.544598,53.774229],"type":"Point"}
}
