{
  "type": "Feature",
  "properties": {
    "date:inception_lower":"2013-08-01",
    "date:inception_upper":"2013-08-31",
    "iso:country":"GB",
    "wof:name":"IP25 7FD",
    "wof:placetype":"postalcode"
},
  "geometry": {"coordinates":[0.890584,52.627193],"type":"Point"}
}