{
  "type": "Feature",
  "properties": {
    "iso:country":"GB",
    "wof:name":"IP25 7FD",
    "wof:placetype":"postalcode"
},
  "geometry": {"coordinates":[0.89058346537036,52.62719273145645],"type":"Point"}
}