{
  "type": "Feature",
  "properties": {
    "date:inception_lower": "2004-07-01",
    "date:inception_upper": "2004-07-01",
    "iso:country": "GB",
    "wof:name": "YO26 6QW",
    "wof:placetype": "postalcode"
  },
  "geometry": {"coordinates":[-1.150501,53.967731],"type":"Point"}
}
