{
  "type": "Feature",
  "properties": {
    "date:inception_lower": "2018-10-01",
    "date:inception_upper": "2018-10-01",
    "iso:country": "GB",
    "wof:name": "B5 5AD",
    "wof:placetype": "postalcode"
  },
  "geometry": {"coordinates":[-1.888558,52.482001],"type":"Point"}
}
