{
  "type": "Feature",
  "properties": {
    "iso:country":"GB",
    "wof:name":"NE38 8JZ",
    "wof:placetype":"postalcode"
},
  "geometry": {"coordinates":[-1.49453811556774,54.89110982627039],"type":"Point"}
}