{
  "type": "Feature",
  "properties": {
    "date:inception_lower": "1980-01-01",
    "date:inception_upper": "1980-01-01",
    "iso:country": "GB",
    "wof:name": "NE38 8JZ",
    "wof:placetype": "postalcode"
  },
  "geometry": {"coordinates":[-1.494395,54.891127],"type":"Point"}
}
