{
  "type": "Feature",
  "properties": {
    "iso:country": "GB",
    "wof:name": "CM9 8LQ",
    "wof:placetype": "postalcode"
  },
  "geometry": {"coordinates":[0.747551,51.766537],"type":"Point"}
}
