{
  "type": "Feature",
  "properties": {
    "iso:country":"GB",
    "wof:name":"CM9 8LQ",
    "wof:placetype":"postalcode"
},
  "geometry": {"coordinates":[0.74719233448482,51.76680635724455],"type":"Point"}
}