{
  "type": "Feature",
  "properties": {
    "date:inception_lower": "2024-01-01",
    "date:inception_upper": "2024-01-01",
    "iso:country": "GB",
    "wof:name": "BA11 5FS",
    "wof:placetype": "postalcode"
  },
  "geometry": {"coordinates":[-2.349238,51.186338],"type":"Point"}
}
