{
  "type": "Feature",
  "properties": {
    "date:inception_lower": "2023-07-01",
    "date:inception_upper": "2023-07-01",
    "iso:country": "GB",
    "wof:name": "BA11 5FS",
    "wof:placetype": "postalcode"
  },
  "geometry": {"coordinates":[-2.291446,51.233857],"type":"Point"}
}
