{
  "type": "Feature",
  "properties": {
    "iso:country": "GB",
    "wof:name": "W1J 9HR",
    "wof:placetype": "postalcode"
  },
  "geometry": {"coordinates":[-0.13369,51.509876],"type":"Point"}
}
