{
  "type": "Feature",
  "properties": {
    "iso:country":"GB",
    "wof:name":"W1J 9HR",
    "wof:placetype":"postalcode"
},
  "geometry": {"coordinates":[-0.13368984926975,51.50987604476629],"type":"Point"}
}