{
  "type": "Feature",
  "properties": {
    "iso:country":"GB",
    "wof:name":"LD3 7HA",
    "wof:placetype":"postalcode"
},
  "geometry": {"coordinates":[-3.38583426897913,51.94433838666833],"type":"Point"}
}