{
  "type": "Feature",
  "properties": {
    "iso:country":"GB",
    "wof:name":"NR18 0EA",
    "wof:placetype":"postalcode"
},
  "geometry": {"coordinates":[1.10614291816011,52.5793659191059],"type":"Point"}
}