{
  "type": "Feature",
  "properties": {
    "date:inception_lower":"1980-01-01",
    "date:inception_upper":"1980-01-31",
    "iso:country":"GB",
    "wof:name":"NR18 0EA",
    "wof:placetype":"postalcode"
},
  "geometry": {"coordinates":[1.106143,52.579366],"type":"Point"}
}