{
  "type": "Feature",
  "properties": {
    "date:inception_lower": "1980-01-01",
    "date:inception_upper": "1980-01-01",
    "iso:country": "GB",
    "wof:name": "BA1 2HG",
    "wof:placetype": "postalcode"
  },
  "geometry": {"coordinates":[-2.362768,51.38352],"type":"Point"}
}
