{
  "type": "Feature",
  "properties": {
    "date:inception_lower":"1999-12-01",
    "date:inception_upper":"1999-12-31",
    "iso:country":"GB",
    "wof:name":"BN9 0BG",
    "wof:placetype":"postalcode"
},
  "geometry": {"coordinates":[0.056011,50.789376],"type":"Point"}
}