{
  "type": "Feature",
  "properties": {
    "iso:country":"GB",
    "wof:name":"HP5 1QL",
    "wof:placetype":"postalcode"
},
  "geometry": {"coordinates":[-0.59249023514965,51.69356327782865],"type":"Point"}
}