{
  "type": "Feature",
  "properties": {
    "iso:country": "GB",
    "wof:name": "HP5 1QL",
    "wof:placetype": "postalcode"
  },
  "geometry": {"coordinates":[-0.59249,51.693563],"type":"Point"}
}
