{
  "type": "Feature",
  "properties": {
    "iso:country": "GB",
    "wof:name": "CV1 5QF",
    "wof:placetype": "postalcode"
  },
  "geometry": {"coordinates":[-1.50005,52.410349],"type":"Point"}
}
