{
  "type": "Feature",
  "properties": {
    "iso:country":"GB",
    "wof:name":"CV1 5QF",
    "wof:placetype":"postalcode"
},
  "geometry": {"coordinates":[-1.50005033532317,52.41034857496371],"type":"Point"}
}