{
  "type": "Feature",
  "properties": {
    "iso:country":"GB",
    "wof:name":"RM17 6RT",
    "wof:placetype":"postalcode"
},
  "geometry": {"coordinates":[0.33025386932277,51.47420848836812],"type":"Point"}
}