{
  "type": "Feature",
  "properties": {
    "iso:country":"GB",
    "wof:name":"MK6 5HH",
    "wof:placetype":"postalcode"
},
  "geometry": {"coordinates":[-0.74630471730523,52.02689066539262],"type":"Point"}
}