{
  "type": "Feature",
  "properties": {
    "date:inception_lower": "2000-06-01",
    "date:inception_upper": "2000-06-01",
    "iso:country": "GB",
    "wof:name": "MK6 5HH",
    "wof:placetype": "postalcode"
  },
  "geometry": {"coordinates":[-0.746305,52.026891],"type":"Point"}
}
