{
  "type": "Feature",
  "properties": {
    "iso:country": "GB",
    "wof:name": "MK6 5HH",
    "wof:placetype": "postalcode"
  },
  "geometry": {"coordinates":[-0.746305,52.026891],"type":"Point"}
}
