{
  "type": "Feature",
  "properties": {
    "iso:country":"GB",
    "wof:name":"NG15 8FR",
    "wof:placetype":"postalcode"
},
  "geometry": {"coordinates":[-1.18349509916042,53.05393890721286],"type":"Point"}
}