{
  "type": "Feature",
  "properties": {
    "date:inception_lower":"1997-06-01",
    "date:inception_upper":"1997-06-30",
    "iso:country":"GB",
    "wof:name":"NG15 8FR",
    "wof:placetype":"postalcode"
},
  "geometry": {"coordinates":[-1.183495,53.053939],"type":"Point"}
}