{
  "type": "Feature",
  "properties": {
    "date:inception_lower":"1980-01-01",
    "date:inception_upper":"1980-01-31",
    "iso:country":"GB",
    "wof:name":"HA2 7QD",
    "wof:placetype":"postalcode"
},
  "geometry": {"coordinates":[-0.367766,51.583587],"type":"Point"}
}