{
  "type": "Feature",
  "properties": {
    "iso:country":"GB",
    "wof:name":"HA2 7QD",
    "wof:placetype":"postalcode"
},
  "geometry": {"coordinates":[-0.36776566324117,51.5835871796206],"type":"Point"}
}