{
  "type": "Feature",
  "properties": {
    "iso:country":"GB",
    "wof:name":"CV32 7ET",
    "wof:placetype":"postalcode"
},
  "geometry": {"coordinates":[-1.51600332730683,52.3106234567772],"type":"Point"}
}