{
  "type": "Feature",
  "properties": {
    "iso:country": "GB",
    "wof:name": "CV32 7ET",
    "wof:placetype": "postalcode"
  },
  "geometry": {"coordinates":[-1.515993,52.310639],"type":"Point"}
}
