{
  "type": "Feature",
  "properties": {
    "iso:country": "GB",
    "wof:name": "PE32 1XT",
    "wof:placetype": "postalcode"
  },
  "geometry": {"coordinates":[0.583869,52.68405],"type":"Point"}
}
