{
  "type": "Feature",
  "properties": {
    "iso:country":"GB",
    "wof:name":"PL5 3NH",
    "wof:placetype":"postalcode"
},
  "geometry": {"coordinates":[-4.15801200075317,50.405868081868],"type":"Point"}
}