{
  "type": "Feature",
  "properties": {
    "iso:country":"GB",
    "wof:name":"BA11 1AZ",
    "wof:placetype":"postalcode"
},
  "geometry": {"coordinates":[-2.31799628849166,51.23265146152867],"type":"Point"}
}