{
  "type": "Feature",
  "properties": {
    "date:inception_lower": "2006-02-01",
    "date:inception_upper": "2006-02-01",
    "iso:country": "GB",
    "wof:name": "BA11 1AZ",
    "wof:placetype": "postalcode"
  },
  "geometry": {"coordinates":[-2.317996,51.232651],"type":"Point"}
}
