{
  "type": "Feature",
  "properties": {
    "iso:country":"GB",
    "wof:name":"IV31 6QL",
    "wof:placetype":"postalcode"
},
  "geometry": {"coordinates":[-3.30155507284178,57.69742867471498],"type":"Point"}
}