{
  "type": "Feature",
  "properties": {
    "date:inception_lower": "2004-01-01",
    "date:inception_upper": "2004-01-01",
    "iso:country": "GB",
    "wof:name": "IV31 6QL",
    "wof:placetype": "postalcode"
  },
  "geometry": {"coordinates":[-3.301555,57.697429],"type":"Point"}
}
