{
  "type": "Feature",
  "properties": {
    "iso:country": "GB",
    "wof:name": "M26 3UX",
    "wof:placetype": "postalcode"
  },
  "geometry": {"coordinates":[-2.344176,53.561812],"type":"Point"}
}
