{
  "type": "Feature",
  "properties": {
    "date:inception_lower":"1994-05-01",
    "date:inception_upper":"1994-05-31",
    "iso:country":"GB",
    "wof:name":"M26 3UX",
    "wof:placetype":"postalcode"
},
  "geometry": {"coordinates":[-2.344176,53.561812],"type":"Point"}
}