{
  "type": "Feature",
  "properties": {
    "iso:country":"GB",
    "wof:name":"EN2 8AH",
    "wof:placetype":"postalcode"
},
  "geometry": {"coordinates":[-0.14068830806283,51.68147212348178],"type":"Point"}
}