{
  "type": "Feature",
  "properties": {
    "iso:country":"GB",
    "wof:name":"DA2 6RT",
    "wof:placetype":"postalcode"
},
  "geometry": {"coordinates":[0.2372654141027,51.44557854983803],"type":"Point"}
}