{
  "type": "Feature",
  "properties": {
    "iso:country":"GB",
    "wof:name":"ML3 9DF",
    "wof:placetype":"postalcode"
},
  "geometry": {"coordinates":[-4.08573207759879,55.76819072476282],"type":"Point"}
}