{
  "type": "Feature",
  "properties": {
    "iso:country": "GB",
    "wof:name": "ML3 9DF",
    "wof:placetype": "postalcode"
  },
  "geometry": {"coordinates":[-4.085732,55.768191],"type":"Point"}
}
