{
  "type": "Feature",
  "properties": {
    "iso:country":"GB",
    "wof:name":"NG22 9NP",
    "wof:placetype":"postalcode"
},
  "geometry": {"coordinates":[-0.97957576702368,53.22931145699927],"type":"Point"}
}