{
  "type": "Feature",
  "properties": {
    "iso:country": "GB",
    "wof:name": "AL7 2PW",
    "wof:placetype": "postalcode"
  },
  "geometry": {"coordinates":[-0.161796,51.80167],"type":"Point"}
}
