{
  "type": "Feature",
  "properties": {
    "iso:country":"GB",
    "wof:name":"PE22 7QL",
    "wof:placetype":"postalcode"
},
  "geometry": {"coordinates":[-0.08943709331168,53.13154714056481],"type":"Point"}
}