{
  "type": "Feature",
  "properties": {
    "iso:country":"GB",
    "wof:name":"G84 7NB",
    "wof:placetype":"postalcode"
},
  "geometry": {"coordinates":[-4.71127119535504,56.00503179820764],"type":"Point"}
}