{
  "type": "Feature",
  "properties": {
    "iso:country": "GB",
    "wof:name": "G84 7NB",
    "wof:placetype": "postalcode"
  },
  "geometry": {"coordinates":[-4.711271,56.005032],"type":"Point"}
}
