{
  "type": "Feature",
  "properties": {
    "iso:country": "GB",
    "wof:name": "NE1 2JZ",
    "wof:placetype": "postalcode"
  },
  "geometry": {"coordinates":[-1.600638,54.97222],"type":"Point"}
}
