{
  "type": "Feature",
  "properties": {
    "date:inception_lower": "1980-01-01",
    "date:inception_upper": "1980-01-01",
    "iso:country": "GB",
    "wof:name": "RH12 1EB",
    "wof:placetype": "postalcode"
  },
  "geometry": {"coordinates":[-0.327185,51.063056],"type":"Point"}
}
