{
  "type": "Feature",
  "properties": {
    "date:inception_lower":"1999-06-01",
    "date:inception_upper":"1999-06-30",
    "iso:country":"GB",
    "wof:name":"HU15 2ED",
    "wof:placetype":"postalcode"
},
  "geometry": {"coordinates":[-0.614031,53.766447],"type":"Point"}
}