{
  "type": "Feature",
  "properties": {
    "date:inception_lower": "1999-06-01",
    "date:inception_upper": "1999-06-01",
    "iso:country": "GB",
    "wof:name": "HU15 2ED",
    "wof:placetype": "postalcode"
  },
  "geometry": {"coordinates":[-0.614303,53.766668],"type":"Point"}
}
