{
  "type": "Feature",
  "properties": {
    "iso:country": "GB",
    "wof:name": "HU15 2ED",
    "wof:placetype": "postalcode"
  },
  "geometry": {"coordinates":[-0.614031,53.766447],"type":"Point"}
}
