{
  "type": "Feature",
  "properties": {
    "iso:country":"GB",
    "wof:name":"B61 7NB",
    "wof:placetype":"postalcode"
},
  "geometry": {"coordinates":[-2.07701489420894,52.32442662619066],"type":"Point"}
}