{
  "type": "Feature",
  "properties": {
    "iso:country":"GB",
    "wof:name":"CW1 4RF",
    "wof:placetype":"postalcode"
},
  "geometry": {"coordinates":[-2.48391014313898,53.14239057104267],"type":"Point"}
}