{
  "type": "Feature",
  "properties": {
    "iso:country": "GB",
    "wof:name": "CW1 4RF",
    "wof:placetype": "postalcode"
  },
  "geometry": {"coordinates":[-2.48391,53.142391],"type":"Point"}
}
