{
  "type": "Feature",
  "properties": {
    "iso:country":"GB",
    "wof:name":"TQ12 4RE",
    "wof:placetype":"postalcode"
},
  "geometry": {"coordinates":[-3.54452319022828,50.53096927516122],"type":"Point"}
}