{
  "type": "Feature",
  "properties": {
    "date:inception_lower": "1980-01-01",
    "date:inception_upper": "1980-01-01",
    "iso:country": "GB",
    "wof:name": "TQ12 4RE",
    "wof:placetype": "postalcode"
  },
  "geometry": {"coordinates":[-3.545041,50.530815],"type":"Point"}
}
