{
  "type": "Feature",
  "properties": {
    "iso:country":"GB",
    "wof:name":"WR4 9XT",
    "wof:placetype":"postalcode"
},
  "geometry": {"coordinates":[-2.19866384789173,52.2098289489188],"type":"Point"}
}