{
  "type": "Feature",
  "properties": {
    "iso:country":"GB",
    "wof:name":"PH33 6TQ",
    "wof:placetype":"postalcode"
},
  "geometry": {"coordinates":[-5.07713980215284,56.8317503466582],"type":"Point"}
}