{
  "type": "Feature",
  "properties": {
    "iso:country":"GB",
    "wof:name":"SE21 8QG",
    "wof:placetype":"postalcode"
},
  "geometry": {"coordinates":[-0.08097436213623,51.4285502356606],"type":"Point"}
}