{
  "type": "Feature",
  "properties": {
    "iso:country": "GB",
    "wof:name": "NN14 2WE",
    "wof:placetype": "postalcode"
  },
  "geometry": {"coordinates":[-0.823392,52.44903],"type":"Point"}
}
