{
  "type": "Feature",
  "properties": {
    "iso:country":"GB",
    "wof:name":"NN14 2WE",
    "wof:placetype":"postalcode"
},
  "geometry": {"coordinates":[-0.82339245860984,52.44903046026324],"type":"Point"}
}