{
  "type": "Feature",
  "properties": {
    "date:inception_lower":"2012-08-01",
    "date:inception_upper":"2012-08-31",
    "iso:country":"GB",
    "wof:name":"NN14 2WE",
    "wof:placetype":"postalcode"
},
  "geometry": {"coordinates":[-0.823392,52.44903],"type":"Point"}
}