{
  "type": "Feature",
  "properties": {
    "date:inception_lower": "2022-11-01",
    "date:inception_upper": "2022-11-01",
    "iso:country": "GB",
    "wof:name": "IP25 6YT",
    "wof:placetype": "postalcode"
  },
  "geometry": {"coordinates":[0.851753,52.571755],"type":"Point"}
}
