{
  "type": "Feature",
  "properties": {
    "iso:country":"GB",
    "wof:name":"RM6 4BQ",
    "wof:placetype":"postalcode"
},
  "geometry": {"coordinates":[0.12147431621125,51.57279490655294],"type":"Point"}
}