{
  "type": "Feature",
  "properties": {
    "iso:country": "GB",
    "wof:name": "BB10 1SF",
    "wof:placetype": "postalcode"
  },
  "geometry": {"coordinates":[-2.234573,53.807139],"type":"Point"}
}
