{
  "type": "Feature",
  "properties": {
    "iso:country":"GB",
    "wof:name":"TW2 7HS",
    "wof:placetype":"postalcode"
},
  "geometry": {"coordinates":[-0.35640114141141,51.45439856257143],"type":"Point"}
}