{
  "type": "Feature",
  "properties": {
    "iso:country": "GB",
    "wof:name": "TW2 7HS",
    "wof:placetype": "postalcode"
  },
  "geometry": {"coordinates":[-0.356401,51.454399],"type":"Point"}
}
