{
  "type": "Feature",
  "properties": {
    "iso:country":"GB",
    "wof:name":"LE8 0QB",
    "wof:placetype":"postalcode"
},
  "geometry": {"coordinates":[-0.99968094473457,52.52977608879917],"type":"Point"}
}