{
  "type": "Feature",
  "properties": {
    "date:inception_lower":"1980-01-01",
    "date:inception_upper":"1980-01-31",
    "iso:country":"GB",
    "wof:name":"LE8 0QB",
    "wof:placetype":"postalcode"
},
  "geometry": {"coordinates":[-0.999681,52.529776],"type":"Point"}
}