{
  "type": "Feature",
  "properties": {
    "iso:country": "GB",
    "wof:name": "SK11 8WF",
    "wof:placetype": "postalcode"
  },
  "geometry": {"coordinates":[-2.142948,53.258606],"type":"Point"}
}
