{
  "type": "Feature",
  "properties": {
    "date:inception_lower": "2018-01-01",
    "date:inception_upper": "2018-01-01",
    "iso:country": "GB",
    "wof:name": "SK11 8WF",
    "wof:placetype": "postalcode"
  },
  "geometry": {"coordinates":[-2.142948,53.258606],"type":"Point"}
}
