{
  "type": "Feature",
  "properties": {
    "iso:country":"GB",
    "wof:name":"DA11 7EZ",
    "wof:placetype":"postalcode"
},
  "geometry": {"coordinates":[0.35219589359813,51.4282015770673],"type":"Point"}
}