{
  "type": "Feature",
  "properties": {
    "date:inception_lower":"1980-01-01",
    "date:inception_upper":"1980-01-31",
    "iso:country":"GB",
    "wof:name":"TW19 7SZ",
    "wof:placetype":"postalcode"
},
  "geometry": {"coordinates":[-0.47324,51.451491],"type":"Point"}
}