{
  "type": "Feature",
  "properties": {
    "iso:country":"GB",
    "wof:name":"TW19 7SZ",
    "wof:placetype":"postalcode"
},
  "geometry": {"coordinates":[-0.47323993531989,51.45149109117284],"type":"Point"}
}