{
  "type": "Feature",
  "properties": {
    "iso:country":"GB",
    "wof:name":"NE6 3BE",
    "wof:placetype":"postalcode"
},
  "geometry": {"coordinates":[-1.55548402893882,54.97147920929602],"type":"Point"}
}