{
  "type": "Feature",
  "properties": {
    "iso:country":"GB",
    "wof:name":"DN35 8LD",
    "wof:placetype":"postalcode"
},
  "geometry": {"coordinates":[-0.02932925201452,53.56054884540377],"type":"Point"}
}