{
  "type": "Feature",
  "properties": {
    "iso:country": "GB",
    "wof:name": "IP12 2PP",
    "wof:placetype": "postalcode"
  },
  "geometry": {"coordinates":[1.371904,52.102894],"type":"Point"}
}
