{
  "type": "Feature",
  "properties": {
    "iso:country":"GB",
    "wof:name":"IP12 2PP",
    "wof:placetype":"postalcode"
},
  "geometry": {"coordinates":[1.37190431743984,52.10289364893995],"type":"Point"}
}