{
  "type": "Feature",
  "properties": {
    "iso:country":"GB",
    "wof:name":"DA5 1NF",
    "wof:placetype":"postalcode"
},
  "geometry": {"coordinates":[0.14894201051161,51.44642185145653],"type":"Point"}
}