{
  "type": "Feature",
  "properties": {
    "iso:country":"GB",
    "wof:name":"SO45 6DG",
    "wof:placetype":"postalcode"
},
  "geometry": {"coordinates":[-1.4024233237381,50.87026004175355],"type":"Point"}
}