{
  "type": "Feature",
  "properties": {
    "iso:country":"GB",
    "wof:name":"LU5 6DT",
    "wof:placetype":"postalcode"
},
  "geometry": {"coordinates":[-0.53430343569633,51.9406620934496],"type":"Point"}
}