{
  "type": "Feature",
  "properties": {
    "date:inception_lower": "1991-09-01",
    "date:inception_upper": "1991-09-01",
    "iso:country": "GB",
    "wof:name": "DN31 2TB",
    "wof:placetype": "postalcode"
  },
  "geometry": {"coordinates":[-0.115482,53.580777],"type":"Point"}
}
