{
  "type": "Feature",
  "properties": {
    "iso:country": "GB",
    "wof:name": "DN31 2TB",
    "wof:placetype": "postalcode"
  },
  "geometry": {"coordinates":[-0.115467,53.580785],"type":"Point"}
}
