{
  "type": "Feature",
  "properties": {
    "iso:country": "GB",
    "wof:name": "SO45 4PR",
    "wof:placetype": "postalcode"
  },
  "geometry": {"coordinates":[-1.42079,50.852619],"type":"Point"}
}
