{
  "type": "Feature",
  "properties": {
    "iso:country":"GB",
    "wof:name":"WS3 2RP",
    "wof:placetype":"postalcode"
},
  "geometry": {"coordinates":[-2.02450890438059,52.62449842679771],"type":"Point"}
}