{
  "type": "Feature",
  "properties": {
    "iso:country": "GB",
    "wof:name": "DE55 3NQ",
    "wof:placetype": "postalcode"
  },
  "geometry": {"coordinates":[-1.344253,53.098036],"type":"Point"}
}
