{
  "type": "Feature",
  "properties": {
    "iso:country":"GB",
    "wof:name":"TN12 9DT",
    "wof:placetype":"postalcode"
},
  "geometry": {"coordinates":[0.49779249143328,51.17282700229591],"type":"Point"}
}