{
  "type": "Feature",
  "properties": {
    "iso:country":"GB",
    "wof:name":"LN2 2DL",
    "wof:placetype":"postalcode"
},
  "geometry": {"coordinates":[-0.53443556708554,53.25075767013224],"type":"Point"}
}