{
  "type": "Feature",
  "properties": {
    "iso:country": "GB",
    "wof:name": "PH1 3EA",
    "wof:placetype": "postalcode"
  },
  "geometry": {"coordinates":[-3.521405,56.427705],"type":"Point"}
}
