{
  "type": "Feature",
  "properties": {
    "iso:country": "GB",
    "wof:name": "MK7 7NU",
    "wof:placetype": "postalcode"
  },
  "geometry": {"coordinates":[-0.690007,52.023626],"type":"Point"}
}
