{
  "type": "Feature",
  "properties": {
    "iso:country":"GB",
    "wof:name":"AL10 8DW",
    "wof:placetype":"postalcode"
},
  "geometry": {"coordinates":[-0.23542505533482,51.75836841204327],"type":"Point"}
}