{
  "type": "Feature",
  "properties": {
    "iso:country":"GB",
    "wof:name":"TS5 5DE",
    "wof:placetype":"postalcode"
},
  "geometry": {"coordinates":[-1.25414509069245,54.55643450660183],"type":"Point"}
}