{
  "type": "Feature",
  "properties": {
    "date:inception_lower": "1986-08-01",
    "date:inception_upper": "1986-08-01",
    "iso:country": "GB",
    "wof:name": "G2 6AE",
    "wof:placetype": "postalcode"
  },
  "geometry": {"coordinates":[-4.25946,55.859635],"type":"Point"}
}
