{
  "type": "Feature",
  "properties": {
    "iso:country": "GB",
    "wof:name": "ST15 9DX",
    "wof:placetype": "postalcode"
  },
  "geometry": {"coordinates":[-2.15056,52.886035],"type":"Point"}
}
