{
  "type": "Feature",
  "properties": {
    "iso:country":"GB",
    "wof:name":"TD1 3LX",
    "wof:placetype":"postalcode"
},
  "geometry": {"coordinates":[-2.87410508845785,55.61876073413209],"type":"Point"}
}