{
  "type": "Feature",
  "properties": {
    "iso:country": "GB",
    "wof:name": "TD1 3LX",
    "wof:placetype": "postalcode"
  },
  "geometry": {"coordinates":[-2.874105,55.618761],"type":"Point"}
}
