{
  "type": "Feature",
  "properties": {
    "iso:country": "GB",
    "wof:name": "LE5 0NH",
    "wof:placetype": "postalcode"
  },
  "geometry": {"coordinates":[-1.099806,52.64497],"type":"Point"}
}
