{
  "type": "Feature",
  "properties": {
    "iso:country":"GB",
    "wof:name":"LE5 0NH",
    "wof:placetype":"postalcode"
},
  "geometry": {"coordinates":[-1.09980558201039,52.64496951200925],"type":"Point"}
}