{
  "type": "Feature",
  "properties": {
    "iso:country":"GB",
    "wof:name":"LL64 5RA",
    "wof:placetype":"postalcode"
},
  "geometry": {"coordinates":[-4.51653764726316,53.22981705014711],"type":"Point"}
}