{
  "type": "Feature",
  "properties": {
    "date:inception_lower": "2007-11-01",
    "date:inception_upper": "2007-11-01",
    "iso:country": "GB",
    "wof:name": "LL64 5RA",
    "wof:placetype": "postalcode"
  },
  "geometry": {"coordinates":[-4.516538,53.229817],"type":"Point"}
}
