{
  "type": "Feature",
  "properties": {
    "iso:country": "GB",
    "wof:name": "LL64 5RA",
    "wof:placetype": "postalcode"
  },
  "geometry": {"coordinates":[-4.516538,53.229817],"type":"Point"}
}
