{
  "type": "Feature",
  "properties": {
    "iso:country":"GB",
    "wof:name":"BD21 3LP",
    "wof:placetype":"postalcode"
},
  "geometry": {"coordinates":[-1.90238052668408,53.87403768625317],"type":"Point"}
}