{
  "type": "Feature",
  "properties": {
    "date:inception_lower": "1980-01-01",
    "date:inception_upper": "1980-01-01",
    "iso:country": "GB",
    "wof:name": "BD21 3LP",
    "wof:placetype": "postalcode"
  },
  "geometry": {"coordinates":[-1.90238,53.874038],"type":"Point"}
}
