{
  "type": "Feature",
  "properties": {
    "iso:country": "GB",
    "wof:name": "S62 5AH",
    "wof:placetype": "postalcode"
  },
  "geometry": {"coordinates":[-1.3416,53.462765],"type":"Point"}
}
