{
  "type": "Feature",
  "properties": {
    "iso:country":"GB",
    "wof:name":"L31 4HQ",
    "wof:placetype":"postalcode"
},
  "geometry": {"coordinates":[-2.96126273779551,53.52900516389774],"type":"Point"}
}