{
  "type": "Feature",
  "properties": {
    "date:inception_lower":"1980-01-01",
    "date:inception_upper":"1980-01-31",
    "iso:country":"GB",
    "wof:name":"L31 4HQ",
    "wof:placetype":"postalcode"
},
  "geometry": {"coordinates":[-2.961263,53.529005],"type":"Point"}
}