{
  "type": "Feature",
  "properties": {
    "iso:country": "GB",
    "wof:name": "OL4 5NH",
    "wof:placetype": "postalcode"
  },
  "geometry": {"coordinates":[-2.081921,53.529274],"type":"Point"}
}
