{
  "type": "Feature",
  "properties": {
    "iso:country":"GB",
    "wof:name":"OL4 5NH",
    "wof:placetype":"postalcode"
},
  "geometry": {"coordinates":[-2.0819211975028,53.52927437946096],"type":"Point"}
}