{
  "type": "Feature",
  "properties": {
    "iso:country":"GB",
    "wof:name":"HP15 6LP",
    "wof:placetype":"postalcode"
},
  "geometry": {"coordinates":[-0.74651235288615,51.66978007973269],"type":"Point"}
}