{
  "type": "Feature",
  "properties": {
    "date:inception_lower": "1980-01-01",
    "date:inception_upper": "1980-01-01",
    "iso:country": "GB",
    "wof:name": "HP15 6LP",
    "wof:placetype": "postalcode"
  },
  "geometry": {"coordinates":[-0.746512,51.66978],"type":"Point"}
}
