{
  "type": "Feature",
  "properties": {
    "iso:country":"GB",
    "wof:name":"LL64 5JN",
    "wof:placetype":"postalcode"
},
  "geometry": {"coordinates":[-4.51603364294555,53.22480157668139],"type":"Point"}
}