{
  "type": "Feature",
  "properties": {
    "date:inception_lower":"1980-01-01",
    "date:inception_upper":"1980-01-31",
    "iso:country":"GB",
    "wof:name":"LL64 5JN",
    "wof:placetype":"postalcode"
},
  "geometry": {"coordinates":[-4.517818,53.223712],"type":"Point"}
}