{
  "type": "Feature",
  "properties": {
    "iso:country": "GB",
    "wof:name": "LL64 5JN",
    "wof:placetype": "postalcode"
  },
  "geometry": {"coordinates":[-4.517818,53.223712],"type":"Point"}
}
