{
  "type": "Feature",
  "properties": {
    "iso:country":"GB",
    "wof:name":"W1W 8EX",
    "wof:placetype":"postalcode"
},
  "geometry": {"coordinates":[-0.13805394765929,51.51700452737005],"type":"Point"}
}