{
  "type": "Feature",
  "properties": {
    "iso:country": "GB",
    "wof:name": "CW6 0GL",
    "wof:placetype": "postalcode"
  },
  "geometry": {"coordinates":[-2.673888,53.21942],"type":"Point"}
}
