{
  "type": "Feature",
  "properties": {
    "date:inception_lower":"2004-11-01",
    "date:inception_upper":"2004-11-30",
    "iso:country":"GB",
    "wof:name":"CW6 0GL",
    "wof:placetype":"postalcode"
},
  "geometry": {"coordinates":[-2.673888,53.21942],"type":"Point"}
}