{
  "type": "Feature",
  "properties": {
    "iso:country":"GB",
    "wof:name":"CW6 0GL",
    "wof:placetype":"postalcode"
},
  "geometry": {"coordinates":[-2.67388838434865,53.21941981799065],"type":"Point"}
}