{
  "type": "Feature",
  "properties": {
    "iso:country":"GB",
    "wof:name":"SA70 8TH",
    "wof:placetype":"postalcode"
},
  "geometry": {"coordinates":[-4.71483018064271,51.6819736132956],"type":"Point"}
}