{
  "type": "Feature",
  "properties": {
    "iso:country":"GB",
    "wof:name":"SO42 7RQ",
    "wof:placetype":"postalcode"
},
  "geometry": {"coordinates":[-1.57065056506372,50.81981420950726],"type":"Point"}
}