{
  "type": "Feature",
  "properties": {
    "iso:country":"GB",
    "wof:name":"LA6 2QY",
    "wof:placetype":"postalcode"
},
  "geometry": {"coordinates":[-2.61176490295932,54.13842094723596],"type":"Point"}
}