{
  "type": "Feature",
  "properties": {
    "date:inception_lower":"1980-01-01",
    "date:inception_upper":"1980-01-31",
    "iso:country":"GB",
    "wof:name":"ME13 8SN",
    "wof:placetype":"postalcode"
},
  "geometry": {"coordinates":[0.881668,51.31022],"type":"Point"}
}