{
  "type": "Feature",
  "properties": {
    "iso:country":"GB",
    "wof:name":"PR4 3NG",
    "wof:placetype":"postalcode"
},
  "geometry": {"coordinates":[-2.84276137816208,53.77316318091236],"type":"Point"}
}