{
  "type": "Feature",
  "properties": {
    "iso:country":"GB",
    "wof:name":"IG1 4JY",
    "wof:placetype":"postalcode"
},
  "geometry": {"coordinates":[0.07095954336561,51.56315794692081],"type":"Point"}
}