{
  "type": "Feature",
  "properties": {
    "iso:country":"GB",
    "wof:name":"CF41 7JW",
    "wof:placetype":"postalcode"
},
  "geometry": {"coordinates":[-3.49238757025738,51.65438336848752],"type":"Point"}
}