{
  "type": "Feature",
  "properties": {
    "iso:country":"GB",
    "wof:name":"GU7 1ED",
    "wof:placetype":"postalcode"
},
  "geometry": {"coordinates":[-0.61066801020342,51.18594835387104],"type":"Point"}
}