{
  "type": "Feature",
  "properties": {
    "date:inception_lower": "2013-07-01",
    "date:inception_upper": "2013-07-01",
    "iso:country": "GB",
    "wof:name": "AB21 0BH",
    "wof:placetype": "postalcode"
  },
  "geometry": {"coordinates":[-2.202631,57.195143],"type":"Point"}
}
