{
  "type": "Feature",
  "properties": {
    "iso:country":"GB",
    "wof:name":"S7 1HR",
    "wof:placetype":"postalcode"
},
  "geometry": {"coordinates":[-1.4867366758237,53.36045707420725],"type":"Point"}
}