{
  "type": "Feature",
  "properties": {
    "iso:country":"GB",
    "wof:name":"CF37 3AF",
    "wof:placetype":"postalcode"
},
  "geometry": {"coordinates":[-3.33895353427931,51.62258612021471],"type":"Point"}
}