{
  "type": "Feature",
  "properties": {
    "iso:country":"GB",
    "wof:name":"L23 0QH",
    "wof:placetype":"postalcode"
},
  "geometry": {"coordinates":[-3.02223986049331,53.485119247261],"type":"Point"}
}