{
  "type": "Feature",
  "properties": {
    "date:inception_lower": "1980-01-01",
    "date:inception_upper": "1980-01-01",
    "iso:country": "GB",
    "wof:name": "PO16 0PF",
    "wof:placetype": "postalcode"
  },
  "geometry": {"coordinates":[-1.178642,50.853029],"type":"Point"}
}
