{
  "type": "Feature",
  "properties": {
    "iso:country": "GB",
    "wof:name": "LU5 5UH",
    "wof:placetype": "postalcode"
  },
  "geometry": {"coordinates":[-0.510968,51.908162],"type":"Point"}
}
