{
  "type": "Feature",
  "properties": {
    "iso:country":"GB",
    "wof:name":"LU5 5UH",
    "wof:placetype":"postalcode"
},
  "geometry": {"coordinates":[-0.51096767469632,51.90816159129305],"type":"Point"}
}