{
  "type": "Feature",
  "properties": {
    "iso:country":"GB",
    "wof:name":"PR2 3QN",
    "wof:placetype":"postalcode"
},
  "geometry": {"coordinates":[-2.71929859556433,53.77859664971822],"type":"Point"}
}