{
  "type": "Feature",
  "properties": {
    "iso:country":"GB",
    "wof:name":"G52 4XB",
    "wof:placetype":"postalcode"
},
  "geometry": {"coordinates":[-4.35957981836307,55.86287443027833],"type":"Point"}
}