{
  "type": "Feature",
  "properties": {
    "iso:country":"GB",
    "wof:name":"NW4 2HL",
    "wof:placetype":"postalcode"
},
  "geometry": {"coordinates":[-0.21922530717657,51.58579761744309],"type":"Point"}
}