{
  "type": "Feature",
  "properties": {
    "iso:country": "GB",
    "wof:name": "NW4 2HL",
    "wof:placetype": "postalcode"
  },
  "geometry": {"coordinates":[-0.2192,51.585801],"type":"Point"}
}
