{
  "type": "Feature",
  "properties": {
    "iso:country":"GB",
    "wof:name":"SL1 8BN",
    "wof:placetype":"postalcode"
},
  "geometry": {"coordinates":[-0.65792610516423,51.53407622909463],"type":"Point"}
}