{
  "type": "Feature",
  "properties": {
    "iso:country": "GB",
    "wof:name": "SL1 8BN",
    "wof:placetype": "postalcode"
  },
  "geometry": {"coordinates":[-0.657926,51.534076],"type":"Point"}
}
