{
  "type": "Feature",
  "properties": {
    "date:inception_lower": "2005-01-01",
    "date:inception_upper": "2005-01-01",
    "iso:country": "GB",
    "wof:name": "SL1 8BN",
    "wof:placetype": "postalcode"
  },
  "geometry": {"coordinates":[-0.657926,51.534076],"type":"Point"}
}
