{
  "type": "Feature",
  "properties": {
    "iso:country":"GB",
    "wof:name":"MK40 3UR",
    "wof:placetype":"postalcode"
},
  "geometry": {"coordinates":[-0.45350837642813,52.1386627431861],"type":"Point"}
}