{
  "type": "Feature",
  "properties": {
    "date:inception_lower": "1985-04-01",
    "date:inception_upper": "1985-04-01",
    "iso:country": "GB",
    "wof:name": "MK40 3UR",
    "wof:placetype": "postalcode"
  },
  "geometry": {"coordinates":[-0.453457,52.138683],"type":"Point"}
}
