{
  "type": "Feature",
  "properties": {
    "iso:country":"GB",
    "wof:name":"RM7 8LH",
    "wof:placetype":"postalcode"
},
  "geometry": {"coordinates":[0.15783996497017,51.59043205317916],"type":"Point"}
}