{
  "type": "Feature",
  "properties": {
    "date:inception_lower":"1994-05-01",
    "date:inception_upper":"1994-05-31",
    "iso:country":"GB",
    "wof:name":"BS22 9BT",
    "wof:placetype":"postalcode"
},
  "geometry": {"coordinates":[-2.948907,51.360103],"type":"Point"}
}