{
  "type": "Feature",
  "properties": {
    "iso:country": "GB",
    "wof:name": "TA6 7RN",
    "wof:placetype": "postalcode"
  },
  "geometry": {"coordinates":[-3.020395,51.134692],"type":"Point"}
}
