{
  "type": "Feature",
  "properties": {
    "date:inception_lower": "1980-01-01",
    "date:inception_upper": "1980-01-01",
    "iso:country": "GB",
    "wof:name": "TA6 7RN",
    "wof:placetype": "postalcode"
  },
  "geometry": {"coordinates":[-3.020345,51.134679],"type":"Point"}
}
