{
  "type": "Feature",
  "properties": {
    "iso:country":"GB",
    "wof:name":"S75 4QH",
    "wof:placetype":"postalcode"
},
  "geometry": {"coordinates":[-1.56230315089596,53.53624157001723],"type":"Point"}
}