{
  "type": "Feature",
  "properties": {
    "date:inception_lower": "2020-04-01",
    "date:inception_upper": "2020-04-01",
    "iso:country": "GB",
    "wof:name": "NW9 4ES",
    "wof:placetype": "postalcode"
  },
  "geometry": {"coordinates":[-0.245476,51.593534],"type":"Point"}
}
