{
  "type": "Feature",
  "properties": {
    "iso:country":"GB",
    "wof:name":"TS1 4QJ",
    "wof:placetype":"postalcode"
},
  "geometry": {"coordinates":[-1.24250021692518,54.56569974980912],"type":"Point"}
}