{
  "type": "Feature",
  "properties": {
    "iso:country":"GB",
    "wof:name":"HP10 9SZ",
    "wof:placetype":"postalcode"
},
  "geometry": {"coordinates":[-0.70108701894211,51.61681059696051],"type":"Point"}
}