{
  "type": "Feature",
  "properties": {
    "iso:country":"GB",
    "wof:name":"LS6 2ER",
    "wof:placetype":"postalcode"
},
  "geometry": {"coordinates":[-1.56718331735647,53.82077217207797],"type":"Point"}
}