{
  "type": "Feature",
  "properties": {
    "date:inception_lower": "1991-01-01",
    "date:inception_upper": "1991-01-01",
    "iso:country": "GB",
    "wof:name": "SW19 1TX",
    "wof:placetype": "postalcode"
  },
  "geometry": {"coordinates":[-0.18,51.422126],"type":"Point"}
}
