{
  "type": "Feature",
  "properties": {
    "iso:country":"GB",
    "wof:name":"W1D 5AE",
    "wof:placetype":"postalcode"
},
  "geometry": {"coordinates":[-0.13165641671434,51.51273026860999],"type":"Point"}
}