{
  "type": "Feature",
  "properties": {
    "iso:country":"GB",
    "wof:name":"SL1 2DF",
    "wof:placetype":"postalcode"
},
  "geometry": {"coordinates":[-0.59265836196095,51.50408738851718],"type":"Point"}
}