{
  "type": "Feature",
  "properties": {
    "date:inception_lower": "1999-06-01",
    "date:inception_upper": "1999-06-01",
    "iso:country": "GB",
    "wof:name": "NP26 5XE",
    "wof:placetype": "postalcode"
  },
  "geometry": {"coordinates":[-2.736313,51.58488],"type":"Point"}
}
