{
  "type": "Feature",
  "properties": {
    "iso:country":"GB",
    "wof:name":"NP26 5XE",
    "wof:placetype":"postalcode"
},
  "geometry": {"coordinates":[-2.73631268347756,51.58488036975382],"type":"Point"}
}