{
  "type": "Feature",
  "properties": {
    "iso:country": "GB",
    "wof:name": "CF32 8YG",
    "wof:placetype": "postalcode"
  },
  "geometry": {"coordinates":[-3.573933,51.554121],"type":"Point"}
}
