{
  "type": "Feature",
  "properties": {
    "iso:country":"GB",
    "wof:name":"TN25 4DB",
    "wof:placetype":"postalcode"
},
  "geometry": {"coordinates":[0.87687895642351,51.20750250720563],"type":"Point"}
}