{
  "type": "Feature",
  "properties": {
    "date:inception_lower": "1980-01-01",
    "date:inception_upper": "1980-01-01",
    "iso:country": "GB",
    "wof:name": "TN25 4DB",
    "wof:placetype": "postalcode"
  },
  "geometry": {"coordinates":[0.876879,51.207503],"type":"Point"}
}
