{
  "type": "Feature",
  "properties": {
    "iso:country": "GB",
    "wof:name": "LE5 0HA",
    "wof:placetype": "postalcode"
  },
  "geometry": {"coordinates":[-1.099942,52.646256],"type":"Point"}
}
