{
  "type": "Feature",
  "properties": {
    "iso:country":"GB",
    "wof:name":"LE5 0HA",
    "wof:placetype":"postalcode"
},
  "geometry": {"coordinates":[-1.09994175389287,52.64625611554809],"type":"Point"}
}