{
  "type": "Feature",
  "properties": {
    "date:inception_lower": "1980-01-01",
    "date:inception_upper": "1980-01-01",
    "iso:country": "GB",
    "wof:name": "CA10 1UY",
    "wof:placetype": "postalcode"
  },
  "geometry": {"coordinates":[-2.56583,54.622472],"type":"Point"}
}
