{
  "type": "Feature",
  "properties": {
    "date:inception_lower":"2000-12-01",
    "date:inception_upper":"2000-12-31",
    "iso:country":"GB",
    "wof:name":"MK42 8WA",
    "wof:placetype":"postalcode"
},
  "geometry": {"coordinates":[-0.494582,52.126579],"type":"Point"}
}