{
  "type": "Feature",
  "properties": {
    "iso:country": "GB",
    "wof:name": "MK42 8WA",
    "wof:placetype": "postalcode"
  },
  "geometry": {"coordinates":[-0.494582,52.126579],"type":"Point"}
}
