{
  "type": "Feature",
  "properties": {
    "iso:country":"GB",
    "wof:name":"CF62 9AG",
    "wof:placetype":"postalcode"
},
  "geometry": {"coordinates":[-3.27077681623799,51.41317560003133],"type":"Point"}
}