{
  "type": "Feature",
  "properties": {
    "iso:country":"GB",
    "wof:name":"AB16 5SP",
    "wof:placetype":"postalcode"
},
  "geometry": {"coordinates":[-2.16234646648075,57.16436009162029],"type":"Point"}
}