{
  "type": "Feature",
  "properties": {
    "iso:country":"GB",
    "wof:name":"L35 3XD",
    "wof:placetype":"postalcode"
},
  "geometry": {"coordinates":[-2.79121957144842,53.41188846070506],"type":"Point"}
}