{
  "type": "Feature",
  "properties": {
    "date:inception_lower": "1995-12-01",
    "date:inception_upper": "1995-12-01",
    "iso:country": "GB",
    "wof:name": "L35 3XD",
    "wof:placetype": "postalcode"
  },
  "geometry": {"coordinates":[-2.79122,53.411888],"type":"Point"}
}
