{
  "type": "Feature",
  "properties": {
    "iso:country":"GB",
    "wof:name":"GL2 0DP",
    "wof:placetype":"postalcode"
},
  "geometry": {"coordinates":[-2.2105956459577,51.87927633844947],"type":"Point"}
}