{
  "type": "Feature",
  "properties": {
    "iso:country": "GB",
    "wof:name": "GL2 0DP",
    "wof:placetype": "postalcode"
  },
  "geometry": {"coordinates":[-2.210596,51.879276],"type":"Point"}
}
