{
  "type": "Feature",
  "properties": {
    "iso:country":"GB",
    "wof:name":"B23 7QR",
    "wof:placetype":"postalcode"
},
  "geometry": {"coordinates":[-1.85188001821342,52.51390577712551],"type":"Point"}
}