{
  "type": "Feature",
  "properties": {
    "date:inception_lower": "2021-07-01",
    "date:inception_upper": "2021-07-01",
    "iso:country": "GB",
    "wof:name": "KT19 9GB",
    "wof:placetype": "postalcode"
  },
  "geometry": {"coordinates":[-0.273367,51.360239],"type":"Point"}
}
