{
  "type": "Feature",
  "properties": {
    "iso:country":"GB",
    "wof:name":"IP14 3JR",
    "wof:placetype":"postalcode"
},
  "geometry": {"coordinates":[0.93727032139401,52.22603209283038],"type":"Point"}
}