{
  "type": "Feature",
  "properties": {
    "iso:country": "GB",
    "wof:name": "IP14 3JR",
    "wof:placetype": "postalcode"
  },
  "geometry": {"coordinates":[0.93727,52.226032],"type":"Point"}
}
