{
  "type": "Feature",
  "properties": {
    "iso:country":"GB",
    "wof:name":"SA12 7PE",
    "wof:placetype":"postalcode"
},
  "geometry": {"coordinates":[-3.81690756723402,51.59441677965826],"type":"Point"}
}