{
  "type": "Feature",
  "properties": {
    "date:inception_lower": "1980-01-01",
    "date:inception_upper": "1980-01-01",
    "iso:country": "GB",
    "wof:name": "SA12 7PE",
    "wof:placetype": "postalcode"
  },
  "geometry": {"coordinates":[-3.809653,51.591278],"type":"Point"}
}
