{
  "type": "Feature",
  "properties": {
    "iso:country": "GB",
    "wof:name": "SN7 7UR",
    "wof:placetype": "postalcode"
  },
  "geometry": {"coordinates":[-1.585011,51.648985],"type":"Point"}
}
