{
  "type": "Feature",
  "properties": {
    "iso:country":"GB",
    "wof:name":"SN7 7UR",
    "wof:placetype":"postalcode"
},
  "geometry": {"coordinates":[-1.58501073331909,51.648984559201],"type":"Point"}
}