{
  "type": "Feature",
  "properties": {
    "iso:country":"GB",
    "wof:name":"PA3 3EX",
    "wof:placetype":"postalcode"
},
  "geometry": {"coordinates":[-4.50242086370063,55.84734223506926],"type":"Point"}
}