{
  "type": "Feature",
  "properties": {
    "iso:country":"GB",
    "wof:name":"DL15 9HZ",
    "wof:placetype":"postalcode"
},
  "geometry": {"coordinates":[-1.74913761022261,54.71814820324871],"type":"Point"}
}