{
  "type": "Feature",
  "properties": {
    "date:inception_lower": "1980-01-01",
    "date:inception_upper": "1980-01-01",
    "iso:country": "GB",
    "wof:name": "B6 6SA",
    "wof:placetype": "postalcode"
  },
  "geometry": {"coordinates":[-1.87993,52.509089],"type":"Point"}
}
