{
  "type": "Feature",
  "properties": {
    "iso:country":"GB",
    "wof:name":"RG6 5GN",
    "wof:placetype":"postalcode"
},
  "geometry": {"coordinates":[-0.93873564380664,51.42682889020066],"type":"Point"}
}