{
  "type": "Feature",
  "properties": {
    "iso:country": "GB",
    "wof:name": "EX12 2FR",
    "wof:placetype": "postalcode"
  },
  "geometry": {"coordinates":[-3.063902,50.707131],"type":"Point"}
}
