{
  "type": "Feature",
  "properties": {
    "date:inception_lower": "2018-01-01",
    "date:inception_upper": "2018-01-01",
    "iso:country": "GB",
    "wof:name": "EX12 2FR",
    "wof:placetype": "postalcode"
  },
  "geometry": {"coordinates":[-3.063534,50.707125],"type":"Point"}
}
