{
  "type": "Feature",
  "properties": {
    "iso:country":"GB",
    "wof:name":"BN42 4TQ",
    "wof:placetype":"postalcode"
},
  "geometry": {"coordinates":[-0.23547442302936,50.83979176365089],"type":"Point"}
}