{
  "type": "Feature",
  "properties": {
    "iso:country": "GB",
    "wof:name": "BN42 4TQ",
    "wof:placetype": "postalcode"
  },
  "geometry": {"coordinates":[-0.235474,50.839792],"type":"Point"}
}
