{
  "type": "Feature",
  "properties": {
    "iso:country": "GB",
    "wof:name": "PH10 7BH",
    "wof:placetype": "postalcode"
  },
  "geometry": {"coordinates":[-3.332712,56.5925],"type":"Point"}
}
