{
  "type": "Feature",
  "properties": {
    "iso:country":"GB",
    "wof:name":"PH10 7BH",
    "wof:placetype":"postalcode"
},
  "geometry": {"coordinates":[-3.3343931807057,56.59216063768831],"type":"Point"}
}