{
  "type": "Feature",
  "properties": {
    "date:inception_lower": "1980-01-01",
    "date:inception_upper": "1980-01-01",
    "iso:country": "GB",
    "wof:name": "PH10 7BH",
    "wof:placetype": "postalcode"
  },
  "geometry": {"coordinates":[-3.332712,56.5925],"type":"Point"}
}
