{
  "type": "Feature",
  "properties": {
    "iso:country":"GB",
    "wof:name":"E11 3AE",
    "wof:placetype":"postalcode"
},
  "geometry": {"coordinates":[0.01607210875293,51.57027388150916],"type":"Point"}
}