{
  "type": "Feature",
  "properties": {
    "date:inception_lower": "2005-06-01",
    "date:inception_upper": "2005-06-01",
    "iso:country": "GB",
    "wof:name": "MK44 1LG",
    "wof:placetype": "postalcode"
  },
  "geometry": {"coordinates":[-0.556013,52.224982],"type":"Point"}
}
