{
  "type": "Feature",
  "properties": {
    "iso:country": "GB",
    "wof:name": "MK44 1LG",
    "wof:placetype": "postalcode"
  },
  "geometry": {"coordinates":[-0.556013,52.224982],"type":"Point"}
}
