{
  "type": "Feature",
  "properties": {
    "iso:country":"GB",
    "wof:name":"CW8 3LL",
    "wof:placetype":"postalcode"
},
  "geometry": {"coordinates":[-2.56935346806928,53.26247388593318],"type":"Point"}
}