{
  "type": "Feature",
  "properties": {
    "iso:country": "GB",
    "wof:name": "ST13 8JG",
    "wof:placetype": "postalcode"
  },
  "geometry": {"coordinates":[-2.044706,53.101262],"type":"Point"}
}
