{
  "type": "Feature",
  "properties": {
    "iso:country":"GB",
    "wof:name":"SA12 9AA",
    "wof:placetype":"postalcode"
},
  "geometry": {"coordinates":[-3.75955092785115,51.61132412416326],"type":"Point"}
}