{
  "type": "Feature",
  "properties": {
    "iso:country":"GB",
    "wof:name":"DL17 8RR",
    "wof:placetype":"postalcode"
},
  "geometry": {"coordinates":[-1.57054585406258,54.68943834361448],"type":"Point"}
}