{
  "type": "Feature",
  "properties": {
    "iso:country": "GB",
    "wof:name": "HP1 3JT",
    "wof:placetype": "postalcode"
  },
  "geometry": {"coordinates":[-0.490798,51.762042],"type":"Point"}
}
