{
  "type": "Feature",
  "properties": {
    "iso:country":"GB",
    "wof:name":"HP1 3JT",
    "wof:placetype":"postalcode"
},
  "geometry": {"coordinates":[-0.49079774726482,51.76204162817259],"type":"Point"}
}