{
  "type": "Feature",
  "properties": {
    "date:inception_lower":"1992-01-01",
    "date:inception_upper":"1992-01-31",
    "iso:country":"GB",
    "wof:name":"WF3 1UU",
    "wof:placetype":"postalcode"
},
  "geometry": {"coordinates":[-1.572439,53.729625],"type":"Point"}
}