{
  "type": "Feature",
  "properties": {
    "iso:country": "GB",
    "wof:name": "LU7 9NS",
    "wof:placetype": "postalcode"
  },
  "geometry": {"coordinates":[-0.588365,51.93181],"type":"Point"}
}
