{
  "type": "Feature",
  "properties": {
    "date:inception_lower": "1993-08-01",
    "date:inception_upper": "1993-08-01",
    "iso:country": "GB",
    "wof:name": "LU7 9NS",
    "wof:placetype": "postalcode"
  },
  "geometry": {"coordinates":[-0.588365,51.93181],"type":"Point"}
}
