{
  "type": "Feature",
  "properties": {
    "iso:country":"GB",
    "wof:name":"LU7 9NS",
    "wof:placetype":"postalcode"
},
  "geometry": {"coordinates":[-0.58836511059754,51.93180975290454],"type":"Point"}
}