{
  "type": "Feature",
  "properties": {
    "iso:country":"GB",
    "wof:name":"DE12 7QG",
    "wof:placetype":"postalcode"
},
  "geometry": {"coordinates":[-1.52306315303055,52.72416431543088],"type":"Point"}
}