{
  "type": "Feature",
  "properties": {
    "date:inception_lower": "1980-01-01",
    "date:inception_upper": "1980-01-01",
    "iso:country": "GB",
    "wof:name": "DE12 7QG",
    "wof:placetype": "postalcode"
  },
  "geometry": {"coordinates":[-1.523063,52.724164],"type":"Point"}
}
