{
  "type": "Feature",
  "properties": {
    "iso:country":"GB",
    "wof:name":"NN6 8FE",
    "wof:placetype":"postalcode"
},
  "geometry": {"coordinates":[-1.00901053503728,52.35343670598409],"type":"Point"}
}