{
  "type": "Feature",
  "properties": {
    "iso:country": "GB",
    "wof:name": "NN6 8FE",
    "wof:placetype": "postalcode"
  },
  "geometry": {"coordinates":[-1.00901,52.353437],"type":"Point"}
}
