{
  "type": "Feature",
  "properties": {
    "iso:country": "GB",
    "wof:name": "HR1 1NT",
    "wof:placetype": "postalcode"
  },
  "geometry": {"coordinates":[-2.699643,52.061751],"type":"Point"}
}
