{
  "type": "Feature",
  "properties": {
    "date:inception_lower":"1981-06-01",
    "date:inception_upper":"1981-06-30",
    "iso:country":"GB",
    "wof:name":"HR1 1NT",
    "wof:placetype":"postalcode"
},
  "geometry": {"coordinates":[-2.699643,52.061751],"type":"Point"}
}