{
  "type": "Feature",
  "properties": {
    "iso:country":"GB",
    "wof:name":"HR1 1NT",
    "wof:placetype":"postalcode"
},
  "geometry": {"coordinates":[-2.69964268003602,52.06175116793327],"type":"Point"}
}