{
  "type": "Feature",
  "properties": {
    "iso:country":"GB",
    "wof:name":"TN37 7PP",
    "wof:placetype":"postalcode"
},
  "geometry": {"coordinates":[0.55076179683765,50.89270625289696],"type":"Point"}
}