{
  "type": "Feature",
  "properties": {
    "iso:country":"GB",
    "wof:name":"DN5 0RR",
    "wof:placetype":"postalcode"
},
  "geometry": {"coordinates":[-1.14326108833608,53.54796981568936],"type":"Point"}
}