{
  "type": "Feature",
  "properties": {
    "date:inception_lower": "2020-11-01",
    "date:inception_upper": "2020-11-01",
    "iso:country": "GB",
    "wof:name": "NG12 4GF",
    "wof:placetype": "postalcode"
  },
  "geometry": {"coordinates":[-1.122525,52.901981],"type":"Point"}
}
