{
  "type": "Feature",
  "properties": {
    "iso:country": "GB",
    "wof:name": "DY12 2YW",
    "wof:placetype": "postalcode"
  },
  "geometry": {"coordinates":[-2.329409,52.340093],"type":"Point"}
}
