{
  "type": "Feature",
  "properties": {
    "iso:country":"GB",
    "wof:name":"DY12 2YW",
    "wof:placetype":"postalcode"
},
  "geometry": {"coordinates":[-2.3294090602544,52.34009342187059],"type":"Point"}
}