{
  "type": "Feature",
  "properties": {
    "iso:country":"GB",
    "wof:name":"NG3 4HZ",
    "wof:placetype":"postalcode"
},
  "geometry": {"coordinates":[-1.14425770262111,52.9649645838277],"type":"Point"}
}