{
  "type": "Feature",
  "properties": {
    "date:inception_lower": "1980-01-01",
    "date:inception_upper": "1980-01-01",
    "iso:country": "GB",
    "wof:name": "OX13 6JZ",
    "wof:placetype": "postalcode"
  },
  "geometry": {"coordinates":[-1.312439,51.703002],"type":"Point"}
}
