{
  "type": "Feature",
  "properties": {
    "iso:country":"GB",
    "wof:name":"OX13 6JZ",
    "wof:placetype":"postalcode"
},
  "geometry": {"coordinates":[-1.31243912945256,51.70300245392054],"type":"Point"}
}