{
  "type": "Feature",
  "properties": {
    "iso:country":"GB",
    "wof:name":"G3 8SD",
    "wof:placetype":"postalcode"
},
  "geometry": {"coordinates":[-4.2939525724849,55.86710861637928],"type":"Point"}
}