{
  "type": "Feature",
  "properties": {
    "iso:country":"GB",
    "wof:name":"S7 2DJ",
    "wof:placetype":"postalcode"
},
  "geometry": {"coordinates":[-1.49017585066331,53.3517886972073],"type":"Point"}
}