{
  "type": "Feature",
  "properties": {
    "iso:country": "GB",
    "wof:name": "DE3 9SZ",
    "wof:placetype": "postalcode"
  },
  "geometry": {"coordinates":[-1.534348,52.904503],"type":"Point"}
}
