{
  "type": "Feature",
  "properties": {
    "iso:country":"GB",
    "wof:name":"DE3 9SZ",
    "wof:placetype":"postalcode"
},
  "geometry": {"coordinates":[-1.5343482649025,52.90450308701156],"type":"Point"}
}