{
  "type": "Feature",
  "properties": {
    "iso:country":"GB",
    "wof:name":"ME17 1PJ",
    "wof:placetype":"postalcode"
},
  "geometry": {"coordinates":[0.63536388537767,51.24569827613799],"type":"Point"}
}