{
  "type": "Feature",
  "properties": {
    "iso:country": "GB",
    "wof:name": "ME17 1PJ",
    "wof:placetype": "postalcode"
  },
  "geometry": {"coordinates":[0.635364,51.245698],"type":"Point"}
}
