{
  "type": "Feature",
  "properties": {
    "iso:country":"GB",
    "wof:name":"E14 0GP",
    "wof:placetype":"postalcode"
},
  "geometry": {"coordinates":[-0.00238346306705,51.51431365033729],"type":"Point"}
}