{
  "type": "Feature",
  "properties": {
    "date:inception_lower":"1980-01-01",
    "date:inception_upper":"1980-01-31",
    "iso:country":"GB",
    "wof:name":"SW18 5AR",
    "wof:placetype":"postalcode"
},
  "geometry": {"coordinates":[-0.200692,51.443129],"type":"Point"}
}