{
  "type": "Feature",
  "properties": {
    "iso:country":"GB",
    "wof:name":"SW18 5AR",
    "wof:placetype":"postalcode"
},
  "geometry": {"coordinates":[-0.20069194001244,51.44312868924035],"type":"Point"}
}