{
  "type": "Feature",
  "properties": {
    "iso:country":"GB",
    "wof:name":"NW2 5ED",
    "wof:placetype":"postalcode"
},
  "geometry": {"coordinates":[-0.23235192739146,51.54808439780872],"type":"Point"}
}