{
  "type": "Feature",
  "properties": {
    "iso:country":"GB",
    "wof:name":"YO16 4UE",
    "wof:placetype":"postalcode"
},
  "geometry": {"coordinates":[-0.21780883464138,54.10212204896137],"type":"Point"}
}