{
  "type": "Feature",
  "properties": {
    "iso:country": "GB",
    "wof:name": "WF15 7RD",
    "wof:placetype": "postalcode"
  },
  "geometry": {"coordinates":[-1.681034,53.702504],"type":"Point"}
}
