{
  "type": "Feature",
  "properties": {
    "iso:country": "GB",
    "wof:name": "ME3 7QF",
    "wof:placetype": "postalcode"
  },
  "geometry": {"coordinates":[0.498176,51.461704],"type":"Point"}
}
