{
  "type": "Feature",
  "properties": {
    "iso:country":"GB",
    "wof:name":"ME3 7QF",
    "wof:placetype":"postalcode"
},
  "geometry": {"coordinates":[0.49814730942673,51.46170317790873],"type":"Point"}
}