{
  "type": "Feature",
  "properties": {
    "iso:country": "GB",
    "wof:name": "NR18 9AE",
    "wof:placetype": "postalcode"
  },
  "geometry": {"coordinates":[1.054674,52.55637],"type":"Point"}
}
