{
  "type": "Feature",
  "properties": {
    "iso:country":"GB",
    "wof:name":"AB45 2QS",
    "wof:placetype":"postalcode"
},
  "geometry": {"coordinates":[-2.6894176454508,57.6821496114941],"type":"Point"}
}