{
  "type": "Feature",
  "properties": {
    "iso:country":"GB",
    "wof:name":"SL3 0RG",
    "wof:placetype":"postalcode"
},
  "geometry": {"coordinates":[-0.51915228158674,51.48345368130905],"type":"Point"}
}