{
  "type": "Feature",
  "properties": {
    "date:inception_lower":"2014-04-01",
    "date:inception_upper":"2014-04-30",
    "iso:country":"GB",
    "wof:name":"SL3 0RG",
    "wof:placetype":"postalcode"
},
  "geometry": {"coordinates":[-0.519152,51.483454],"type":"Point"}
}