{
  "type": "Feature",
  "properties": {
    "date:inception_lower":"2012-02-01",
    "date:inception_upper":"2012-02-29",
    "iso:country":"GB",
    "wof:name":"EN3 7GE",
    "wof:placetype":"postalcode"
},
  "geometry": {"coordinates":[-0.022759,51.67166],"type":"Point"}
}