{
  "type": "Feature",
  "properties": {
    "iso:country":"GB",
    "wof:name":"EN3 7GE",
    "wof:placetype":"postalcode"
},
  "geometry": {"coordinates":[-0.02275874646643,51.67165962662601],"type":"Point"}
}