{
  "type": "Feature",
  "properties": {
    "iso:country":"GB",
    "wof:name":"CA20 1DJ",
    "wof:placetype":"postalcode"
},
  "geometry": {"coordinates":[-3.47998546360182,54.4400151783196],"type":"Point"}
}