{
  "type": "Feature",
  "properties": {
    "iso:country": "GB",
    "wof:name": "NE23 6EF",
    "wof:placetype": "postalcode"
  },
  "geometry": {"coordinates":[-1.584044,55.081391],"type":"Point"}
}
