{
  "type": "Feature",
  "properties": {
    "iso:country":"GB",
    "wof:name":"NE23 6EF",
    "wof:placetype":"postalcode"
},
  "geometry": {"coordinates":[-1.58404417987726,55.0813914848869],"type":"Point"}
}