{
  "type": "Feature",
  "properties": {
    "iso:country":"GB",
    "wof:name":"SK11 0NG",
    "wof:placetype":"postalcode"
},
  "geometry": {"coordinates":[-2.07147724936006,53.22232056029683],"type":"Point"}
}