{
  "type": "Feature",
  "properties": {
    "iso:country":"GB",
    "wof:name":"S64 0ND",
    "wof:placetype":"postalcode"
},
  "geometry": {"coordinates":[-1.27389695013468,53.49181939542903],"type":"Point"}
}