{
  "type": "Feature",
  "properties": {
    "iso:country": "GB",
    "wof:name": "S64 0ND",
    "wof:placetype": "postalcode"
  },
  "geometry": {"coordinates":[-1.273897,53.491819],"type":"Point"}
}
