{
  "type": "Feature",
  "properties": {
    "iso:country":"GB",
    "wof:name":"TQ14 9FG",
    "wof:placetype":"postalcode"
},
  "geometry": {"coordinates":[-3.50612722842023,50.56232925429416],"type":"Point"}
}