{
  "type": "Feature",
  "properties": {
    "date:inception_lower": "1981-06-01",
    "date:inception_upper": "1981-06-01",
    "iso:country": "GB",
    "wof:name": "SE8 3HY",
    "wof:placetype": "postalcode"
  },
  "geometry": {"coordinates":[-0.025168,51.482695],"type":"Point"}
}
