{
  "type": "Feature",
  "properties": {
    "iso:country":"GB",
    "wof:name":"SE8 3HY",
    "wof:placetype":"postalcode"
},
  "geometry": {"coordinates":[-0.02516788480783,51.48269462612636],"type":"Point"}
}