{
  "type": "Feature",
  "properties": {
    "iso:country":"GB",
    "wof:name":"LS17 9AZ",
    "wof:placetype":"postalcode"
},
  "geometry": {"coordinates":[-1.43688268207618,53.89095814305484],"type":"Point"}
}