{
  "type": "Feature",
  "properties": {
    "date:inception_lower": "1980-01-01",
    "date:inception_upper": "1980-01-01",
    "iso:country": "GB",
    "wof:name": "DL8 3SY",
    "wof:placetype": "postalcode"
  },
  "geometry": {"coordinates":[-2.005755,54.275523],"type":"Point"}
}
