{
  "type": "Feature",
  "properties": {
    "iso:country":"GB",
    "wof:name":"DL8 3SY",
    "wof:placetype":"postalcode"
},
  "geometry": {"coordinates":[-2.00575514051749,54.2755233826605],"type":"Point"}
}