{
  "type": "Feature",
  "properties": {
    "date:inception_lower":"1980-01-01",
    "date:inception_upper":"1980-01-31",
    "iso:country":"GB",
    "wof:name":"HP2 4TP",
    "wof:placetype":"postalcode"
},
  "geometry": {"coordinates":[-0.467175,51.748651],"type":"Point"}
}