{
  "type": "Feature",
  "properties": {
    "iso:country":"GB",
    "wof:name":"ST2 8JW",
    "wof:placetype":"postalcode"
},
  "geometry": {"coordinates":[-2.13928819321177,53.03565830916313],"type":"Point"}
}