{
  "type": "Feature",
  "properties": {
    "date:inception_lower": "1980-01-01",
    "date:inception_upper": "1980-01-01",
    "iso:country": "GB",
    "wof:name": "SG8 5SG",
    "wof:placetype": "postalcode"
  },
  "geometry": {"coordinates":[-0.031444,52.09618],"type":"Point"}
}
