{
  "type": "Feature",
  "properties": {
    "iso:country":"GB",
    "wof:name":"SR6 9PJ",
    "wof:placetype":"postalcode"
},
  "geometry": {"coordinates":[-1.37278891847167,54.92452944854096],"type":"Point"}
}