{
  "type": "Feature",
  "properties": {
    "date:inception_lower":"1980-01-01",
    "date:inception_upper":"1980-01-31",
    "iso:country":"GB",
    "wof:name":"SR6 9PJ",
    "wof:placetype":"postalcode"
},
  "geometry": {"coordinates":[-1.372789,54.924529],"type":"Point"}
}