{
  "type": "Feature",
  "properties": {
    "iso:country":"GB",
    "wof:name":"RH14 0LY",
    "wof:placetype":"postalcode"
},
  "geometry": {"coordinates":[-0.55185179258051,51.03119066988619],"type":"Point"}
}