{
  "type": "Feature",
  "properties": {
    "iso:country":"GB",
    "wof:name":"KT24 5DU",
    "wof:placetype":"postalcode"
},
  "geometry": {"coordinates":[-0.42735071961264,51.28018153871533],"type":"Point"}
}