{
  "type": "Feature",
  "properties": {
    "iso:country": "GB",
    "wof:name": "CV23 0EP",
    "wof:placetype": "postalcode"
  },
  "geometry": {"coordinates":[-1.252138,52.422095],"type":"Point"}
}
