{
  "type": "Feature",
  "properties": {
    "iso:country":"GB",
    "wof:name":"S5 0NJ",
    "wof:placetype":"postalcode"
},
  "geometry": {"coordinates":[-1.45474624637767,53.42755963450684],"type":"Point"}
}