{
  "type": "Feature",
  "properties": {
    "date:inception_lower": "1980-01-01",
    "date:inception_upper": "1980-01-01",
    "iso:country": "GB",
    "wof:name": "SP4 0DW",
    "wof:placetype": "postalcode"
  },
  "geometry": {"coordinates":[-1.677674,51.180357],"type":"Point"}
}
