{
  "type": "Feature",
  "properties": {
    "iso:country": "GB",
    "wof:name": "BS36 2JG",
    "wof:placetype": "postalcode"
  },
  "geometry": {"coordinates":[-2.478083,51.529283],"type":"Point"}
}
