{
  "type": "Feature",
  "properties": {
    "iso:country":"GB",
    "wof:name":"DL14 9NH",
    "wof:placetype":"postalcode"
},
  "geometry": {"coordinates":[-1.7581473766896,54.61524207603674],"type":"Point"}
}