{
  "type": "Feature",
  "properties": {
    "iso:country":"GB",
    "wof:name":"PH3 1DN",
    "wof:placetype":"postalcode"
},
  "geometry": {"coordinates":[-3.69764248701231,56.29753431196427],"type":"Point"}
}