{
  "type": "Feature",
  "properties": {
    "date:inception_lower": "1980-01-01",
    "date:inception_upper": "1980-01-01",
    "iso:country": "GB",
    "wof:name": "PH3 1DN",
    "wof:placetype": "postalcode"
  },
  "geometry": {"coordinates":[-3.697642,56.297534],"type":"Point"}
}
