{
  "type": "Feature",
  "properties": {
    "iso:country":"GB",
    "wof:name":"BB8 8BG",
    "wof:placetype":"postalcode"
},
  "geometry": {"coordinates":[-2.17969673211128,53.85035809432994],"type":"Point"}
}