{
  "type": "Feature",
  "properties": {
    "date:inception_lower":"1998-06-01",
    "date:inception_upper":"1998-06-30",
    "iso:country":"GB",
    "wof:name":"BB8 8BG",
    "wof:placetype":"postalcode"
},
  "geometry": {"coordinates":[-2.179697,53.850358],"type":"Point"}
}