{
  "type": "Feature",
  "properties": {
    "iso:country": "GB",
    "wof:name": "WR2 5TG",
    "wof:placetype": "postalcode"
  },
  "geometry": {"coordinates":[-2.266667,52.179829],"type":"Point"}
}
