{
  "type": "Feature",
  "properties": {
    "date:inception_lower": "2020-10-01",
    "date:inception_upper": "2020-10-01",
    "iso:country": "GB",
    "wof:name": "NW1 5PT",
    "wof:placetype": "postalcode"
  },
  "geometry": {"coordinates":[-0.159955,51.52121],"type":"Point"}
}
