{
  "type": "Feature",
  "properties": {
    "date:inception_lower":"1980-01-01",
    "date:inception_upper":"1980-01-31",
    "iso:country":"GB",
    "wof:name":"BD22 8RH",
    "wof:placetype":"postalcode"
},
  "geometry": {"coordinates":[-1.944767,53.828918],"type":"Point"}
}