{
  "type": "Feature",
  "properties": {
    "iso:country":"GB",
    "wof:name":"BD22 8RH",
    "wof:placetype":"postalcode"
},
  "geometry": {"coordinates":[-1.94476718721793,53.82891848159696],"type":"Point"}
}