{
  "type": "Feature",
  "properties": {
    "date:inception_lower":"1980-01-01",
    "date:inception_upper":"1980-01-31",
    "iso:country":"GB",
    "wof:name":"IP9 1HD",
    "wof:placetype":"postalcode"
},
  "geometry": {"coordinates":[1.217832,51.978921],"type":"Point"}
}