{
  "type": "Feature",
  "properties": {
    "date:inception_lower": "1980-01-01",
    "date:inception_upper": "1980-01-01",
    "iso:country": "GB",
    "wof:name": "IP9 1HD",
    "wof:placetype": "postalcode"
  },
  "geometry": {"coordinates":[1.217792,51.978972],"type":"Point"}
}
