{
  "type": "Feature",
  "properties": {
    "iso:country":"GB",
    "wof:name":"BS16 9ST",
    "wof:placetype":"postalcode"
},
  "geometry": {"coordinates":[-2.43252056583655,51.48117543174699],"type":"Point"}
}