{
  "type": "Feature",
  "properties": {
    "iso:country":"GB",
    "wof:name":"PL1 1QJ",
    "wof:placetype":"postalcode"
},
  "geometry": {"coordinates":[-4.1409737766164,50.37319175993713],"type":"Point"}
}