{
  "type": "Feature",
  "properties": {
    "iso:country":"GB",
    "wof:name":"AB30 1YD",
    "wof:placetype":"postalcode"
},
  "geometry": {"coordinates":[-2.602445787072,56.84224731925823],"type":"Point"}
}