{
  "type": "Feature",
  "properties": {
    "iso:country":"GB",
    "wof:name":"BS3 1QG",
    "wof:placetype":"postalcode"
},
  "geometry": {"coordinates":[-2.60586994033936,51.44407242459184],"type":"Point"}
}