{
  "type": "Feature",
  "properties": {
    "iso:country":"GB",
    "wof:name":"WF12 0QJ",
    "wof:placetype":"postalcode"
},
  "geometry": {"coordinates":[-1.59268364527066,53.66114271261829],"type":"Point"}
}