{
  "type": "Feature",
  "properties": {
    "date:inception_lower": "1984-10-01",
    "date:inception_upper": "1984-10-01",
    "iso:country": "GB",
    "wof:name": "PO19 1AH",
    "wof:placetype": "postalcode"
  },
  "geometry": {"coordinates":[-0.779728,50.834755],"type":"Point"}
}
