{
  "type": "Feature",
  "properties": {
    "iso:country":"GB",
    "wof:name":"HA0 3NN",
    "wof:placetype":"postalcode"
},
  "geometry": {"coordinates":[-0.30820531997022,51.56236733546537],"type":"Point"}
}