{
  "type": "Feature",
  "properties": {
    "date:inception_lower":"1980-01-01",
    "date:inception_upper":"1980-01-31",
    "iso:country":"GB",
    "wof:name":"B10 9DD",
    "wof:placetype":"postalcode"
},
  "geometry": {"coordinates":[-1.845121,52.470709],"type":"Point"}
}