{
  "type": "Feature",
  "properties": {
    "iso:country": "GB",
    "wof:name": "DD8 2DX",
    "wof:placetype": "postalcode"
  },
  "geometry": {"coordinates":[-2.880463,56.643945],"type":"Point"}
}
