{
  "type": "Feature",
  "properties": {
    "date:inception_lower":"1995-12-01",
    "date:inception_upper":"1995-12-31",
    "iso:country":"GB",
    "wof:name":"BD23 6XH",
    "wof:placetype":"postalcode"
},
  "geometry": {"coordinates":[-2.001828,53.969038],"type":"Point"}
}