{
  "type": "Feature",
  "properties": {
    "iso:country":"GB",
    "wof:name":"DN38 6JS",
    "wof:placetype":"postalcode"
},
  "geometry": {"coordinates":[-0.40817055887798,53.57749947336838],"type":"Point"}
}