{
  "type": "Feature",
  "properties": {
    "iso:country":"GB",
    "wof:name":"SO21 1NA",
    "wof:placetype":"postalcode"
},
  "geometry": {"coordinates":[-1.27021017870311,51.03061756039799],"type":"Point"}
}