{
  "type": "Feature",
  "properties": {
    "iso:country":"GB",
    "wof:name":"DN14 5UJ",
    "wof:placetype":"postalcode"
},
  "geometry": {"coordinates":[-0.86624980219046,53.69402433908643],"type":"Point"}
}