{
  "type": "Feature",
  "properties": {
    "iso:country": "GB",
    "wof:name": "DN14 5UJ",
    "wof:placetype": "postalcode"
  },
  "geometry": {"coordinates":[-0.86625,53.694024],"type":"Point"}
}
