{
  "type": "Feature",
  "properties": {
    "iso:country":"GB",
    "wof:name":"SP5 2NH",
    "wof:placetype":"postalcode"
},
  "geometry": {"coordinates":[-1.72195247745964,50.9772441040562],"type":"Point"}
}