{
  "type": "Feature",
  "properties": {
    "iso:country":"GB",
    "wof:name":"ME7 2PE",
    "wof:placetype":"postalcode"
},
  "geometry": {"coordinates":[0.56041989469809,51.38537084840725],"type":"Point"}
}