{
  "type": "Feature",
  "properties": {
    "iso:country":"GB",
    "wof:name":"W3 0LQ",
    "wof:placetype":"postalcode"
},
  "geometry": {"coordinates":[-0.28217297372943,51.52000402595438],"type":"Point"}
}