{
  "type": "Feature",
  "properties": {
    "date:inception_lower":"1980-01-01",
    "date:inception_upper":"1980-01-31",
    "iso:country":"GB",
    "wof:name":"BR8 7PJ",
    "wof:placetype":"postalcode"
},
  "geometry": {"coordinates":[0.195347,51.406937],"type":"Point"}
}