{
  "type": "Feature",
  "properties": {
    "date:inception_lower": "1980-01-01",
    "date:inception_upper": "1980-01-01",
    "iso:country": "GB",
    "wof:name": "CT12 6ER",
    "wof:placetype": "postalcode"
  },
  "geometry": {"coordinates":[1.398417,51.343025],"type":"Point"}
}
