{
  "type": "Feature",
  "properties": {
    "iso:country":"GB",
    "wof:name":"NG19 7PF",
    "wof:placetype":"postalcode"
},
  "geometry": {"coordinates":[-1.25735880373417,53.17982200747695],"type":"Point"}
}