{
  "type": "Feature",
  "properties": {
    "iso:country":"GB",
    "wof:name":"WS3 1NA",
    "wof:placetype":"postalcode"
},
  "geometry": {"coordinates":[-1.98862880983249,52.61497136712708],"type":"Point"}
}