{
  "type": "Feature",
  "properties": {
    "date:inception_lower": "1980-01-01",
    "date:inception_upper": "1980-01-01",
    "iso:country": "GB",
    "wof:name": "WS3 1NA",
    "wof:placetype": "postalcode"
  },
  "geometry": {"coordinates":[-1.988629,52.614971],"type":"Point"}
}
