{
  "type": "Feature",
  "properties": {
    "iso:country":"GB",
    "wof:name":"BL1 6QL",
    "wof:placetype":"postalcode"
},
  "geometry": {"coordinates":[-2.43708168333092,53.60255814443055],"type":"Point"}
}