{
  "type": "Feature",
  "properties": {
    "iso:country":"GB",
    "wof:name":"NE65 8EE",
    "wof:placetype":"postalcode"
},
  "geometry": {"coordinates":[-1.78220745394125,55.31242147033622],"type":"Point"}
}