{
  "type": "Feature",
  "properties": {
    "date:inception_lower":"1980-01-01",
    "date:inception_upper":"1980-01-31",
    "iso:country":"GB",
    "wof:name":"NE65 8EE",
    "wof:placetype":"postalcode"
},
  "geometry": {"coordinates":[-1.786128,55.312297],"type":"Point"}
}