{
  "type": "Feature",
  "properties": {
    "iso:country": "GB",
    "wof:name": "NE65 8EE",
    "wof:placetype": "postalcode"
  },
  "geometry": {"coordinates":[-1.786128,55.312297],"type":"Point"}
}
