{
  "type": "Feature",
  "properties": {
    "iso:country": "GB",
    "wof:name": "SY2 5YN",
    "wof:placetype": "postalcode"
  },
  "geometry": {"coordinates":[-2.73169,52.720931],"type":"Point"}
}
