{
  "type": "Feature",
  "properties": {
    "date:inception_lower": "1991-09-01",
    "date:inception_upper": "1991-09-01",
    "iso:country": "GB",
    "wof:name": "SY2 5YN",
    "wof:placetype": "postalcode"
  },
  "geometry": {"coordinates":[-2.731658,52.720928],"type":"Point"}
}
