{
  "type": "Feature",
  "properties": {
    "iso:country":"GB",
    "wof:name":"BA8 0QN",
    "wof:placetype":"postalcode"
},
  "geometry": {"coordinates":[-2.39772573576898,50.9776697498409],"type":"Point"}
}