{
  "type": "Feature",
  "properties": {
    "date:inception_lower":"1980-01-01",
    "date:inception_upper":"1980-01-31",
    "iso:country":"GB",
    "wof:name":"BA8 0QN",
    "wof:placetype":"postalcode"
},
  "geometry": {"coordinates":[-2.397726,50.97767],"type":"Point"}
}