{
  "type": "Feature",
  "properties": {
    "iso:country": "GB",
    "wof:name": "BA8 0QN",
    "wof:placetype": "postalcode"
  },
  "geometry": {"coordinates":[-2.397726,50.97767],"type":"Point"}
}
