{
  "type": "Feature",
  "properties": {
    "date:inception_lower":"1980-01-01",
    "date:inception_upper":"1980-01-31",
    "iso:country":"GB",
    "wof:name":"NR10 3JN",
    "wof:placetype":"postalcode"
},
  "geometry": {"coordinates":[1.277474,52.685716],"type":"Point"}
}