{
  "type": "Feature",
  "properties": {
    "iso:country": "GB",
    "wof:name": "NR10 3JN",
    "wof:placetype": "postalcode"
  },
  "geometry": {"coordinates":[1.277474,52.685716],"type":"Point"}
}
