{
  "type": "Feature",
  "properties": {
    "iso:country":"GB",
    "wof:name":"OL12 8JR",
    "wof:placetype":"postalcode"
},
  "geometry": {"coordinates":[-2.17058255110089,53.66502929353268],"type":"Point"}
}