{
  "type": "Feature",
  "properties": {
    "iso:country": "GB",
    "wof:name": "OL12 8JR",
    "wof:placetype": "postalcode"
  },
  "geometry": {"coordinates":[-2.170506,53.665027],"type":"Point"}
}
