{
  "type": "Feature",
  "properties": {
    "date:inception_lower": "1980-01-01",
    "date:inception_upper": "1980-01-01",
    "iso:country": "GB",
    "wof:name": "OL14 5EB",
    "wof:placetype": "postalcode"
  },
  "geometry": {"coordinates":[-2.096277,53.71887],"type":"Point"}
}
