{
  "type": "Feature",
  "properties": {
    "iso:country":"GB",
    "wof:name":"OL14 5EB",
    "wof:placetype":"postalcode"
},
  "geometry": {"coordinates":[-2.09627681717626,53.71887018420858],"type":"Point"}
}