{
  "type": "Feature",
  "properties": {
    "iso:country": "GB",
    "wof:name": "CH49 0UZ",
    "wof:placetype": "postalcode"
  },
  "geometry": {"coordinates":[-3.09397,53.382944],"type":"Point"}
}
