{
  "type": "Feature",
  "properties": {
    "iso:country":"GB",
    "wof:name":"CH49 0UZ",
    "wof:placetype":"postalcode"
},
  "geometry": {"coordinates":[-3.0939702445896,53.38294448835273],"type":"Point"}
}