{
  "type": "Feature",
  "properties": {
    "iso:country":"GB",
    "wof:name":"B76 1HT",
    "wof:placetype":"postalcode"
},
  "geometry": {"coordinates":[-1.8075655408486,52.55557317695193],"type":"Point"}
}