{
  "type": "Feature",
  "properties": {
    "date:inception_lower":"1980-01-01",
    "date:inception_upper":"1980-01-31",
    "iso:country":"GB",
    "wof:name":"PL32 9QF",
    "wof:placetype":"postalcode"
},
  "geometry": {"coordinates":[-4.65807,50.619906],"type":"Point"}
}