{
  "type": "Feature",
  "properties": {
    "iso:country": "GB",
    "wof:name": "YO1 6DA",
    "wof:placetype": "postalcode"
  },
  "geometry": {"coordinates":[-1.084856,53.957497],"type":"Point"}
}
