{
  "type": "Feature",
  "properties": {
    "iso:country":"GB",
    "wof:name":"YO1 6DA",
    "wof:placetype":"postalcode"
},
  "geometry": {"coordinates":[-1.08485585859493,53.95749672583749],"type":"Point"}
}