{
  "type": "Feature",
  "properties": {
    "iso:country":"GB",
    "wof:name":"CM9 8PH",
    "wof:placetype":"postalcode"
},
  "geometry": {"coordinates":[0.68921936774562,51.77616972772691],"type":"Point"}
}