{
  "type": "Feature",
  "properties": {
    "iso:country":"GB",
    "wof:name":"PR4 6RA",
    "wof:placetype":"postalcode"
},
  "geometry": {"coordinates":[-2.8374465153522,53.69747369276756],"type":"Point"}
}