{
  "type": "Feature",
  "properties": {
    "iso:country": "GB",
    "wof:name": "PR4 6RA",
    "wof:placetype": "postalcode"
  },
  "geometry": {"coordinates":[-2.836905,53.697754],"type":"Point"}
}
