{
  "type": "Feature",
  "properties": {
    "iso:country":"GB",
    "wof:name":"G76 7XD",
    "wof:placetype":"postalcode"
},
  "geometry": {"coordinates":[-4.29347326100229,55.78357791553784],"type":"Point"}
}