{
  "type": "Feature",
  "properties": {
    "date:inception_lower": "1992-01-01",
    "date:inception_upper": "1992-01-01",
    "iso:country": "GB",
    "wof:name": "MK42 8UU",
    "wof:placetype": "postalcode"
  },
  "geometry": {"coordinates":[-0.494403,52.123664],"type":"Point"}
}
