{
  "type": "Feature",
  "properties": {
    "iso:country":"GB",
    "wof:name":"MK42 8UU",
    "wof:placetype":"postalcode"
},
  "geometry": {"coordinates":[-0.49440316907198,52.12366400195872],"type":"Point"}
}