{
  "type": "Feature",
  "properties": {
    "date:inception_lower":"1980-01-01",
    "date:inception_upper":"1980-01-31",
    "iso:country":"GB",
    "wof:name":"DY10 1UQ",
    "wof:placetype":"postalcode"
},
  "geometry": {"coordinates":[-2.23767,52.383134],"type":"Point"}
}