{
  "type": "Feature",
  "properties": {
    "iso:country":"GB",
    "wof:name":"DY10 1UQ",
    "wof:placetype":"postalcode"
},
  "geometry": {"coordinates":[-2.23767010086817,52.3831338888517],"type":"Point"}
}