{
  "type": "Feature",
  "properties": {
    "iso:country":"GB",
    "wof:name":"NP4 8NX",
    "wof:placetype":"postalcode"
},
  "geometry": {"coordinates":[-3.05255270957026,51.71173275413413],"type":"Point"}
}