{
  "type": "Feature",
  "properties": {
    "iso:country": "GB",
    "wof:name": "NP4 8NX",
    "wof:placetype": "postalcode"
  },
  "geometry": {"coordinates":[-3.052553,51.711733],"type":"Point"}
}
