{
  "type": "Feature",
  "properties": {
    "iso:country": "GB",
    "wof:name": "BN13 2BH",
    "wof:placetype": "postalcode"
  },
  "geometry": {"coordinates":[-0.40104,50.831071],"type":"Point"}
}
