{
  "type": "Feature",
  "properties": {
    "iso:country":"GB",
    "wof:name":"BN13 2BH",
    "wof:placetype":"postalcode"
},
  "geometry": {"coordinates":[-0.40104030609314,50.83107136285356],"type":"Point"}
}