{
  "type": "Feature",
  "properties": {
    "date:inception_lower": "2022-05-01",
    "date:inception_upper": "2022-05-01",
    "iso:country": "GB",
    "wof:name": "NE29 7FB",
    "wof:placetype": "postalcode"
  },
  "geometry": {"coordinates":[-1.481052,55.008575],"type":"Point"}
}
