{
  "type": "Feature",
  "properties": {
    "iso:country": "GB",
    "wof:name": "LA16 7ET",
    "wof:placetype": "postalcode"
  },
  "geometry": {"coordinates":[-3.192865,54.187912],"type":"Point"}
}
