{
  "type": "Feature",
  "properties": {
    "iso:country":"GB",
    "wof:name":"PR2 6YJ",
    "wof:placetype":"postalcode"
},
  "geometry": {"coordinates":[-2.66524125764108,53.7783695824534],"type":"Point"}
}