{
  "type": "Feature",
  "properties": {
    "date:inception_lower": "2001-12-01",
    "date:inception_upper": "2001-12-01",
    "iso:country": "GB",
    "wof:name": "PE2 6PZ",
    "wof:placetype": "postalcode"
  },
  "geometry": {"coordinates":[-0.325796,52.552462],"type":"Point"}
}
