{
  "type": "Feature",
  "properties": {
    "iso:country":"GB",
    "wof:name":"PE2 6PZ",
    "wof:placetype":"postalcode"
},
  "geometry": {"coordinates":[-0.32579587319337,52.5524621341011],"type":"Point"}
}