{
  "type": "Feature",
  "properties": {
    "date:inception_lower": "2019-01-01",
    "date:inception_upper": "2019-01-01",
    "iso:country": "GB",
    "wof:name": "GL52 5GR",
    "wof:placetype": "postalcode"
  },
  "geometry": {"coordinates":[-2.040206,51.902015],"type":"Point"}
}
