{
  "type": "Feature",
  "properties": {
    "iso:country":"GB",
    "wof:name":"DD8 2QN",
    "wof:placetype":"postalcode"
},
  "geometry": {"coordinates":[-2.75195442574554,56.62025212192088],"type":"Point"}
}