{
  "type": "Feature",
  "properties": {
    "iso:country":"GB",
    "wof:name":"IV32 7LA",
    "wof:placetype":"postalcode"
},
  "geometry": {"coordinates":[-3.0957511455651,57.60819157427585],"type":"Point"}
}