{
  "type": "Feature",
  "properties": {
    "iso:country":"GB",
    "wof:name":"PE28 4EG",
    "wof:placetype":"postalcode"
},
  "geometry": {"coordinates":[-0.25864169613338,52.36923570900434],"type":"Point"}
}