{
  "type": "Feature",
  "properties": {
    "iso:country": "GB",
    "wof:name": "PE28 4EG",
    "wof:placetype": "postalcode"
  },
  "geometry": {"coordinates":[-0.258642,52.369236],"type":"Point"}
}
