{
  "type": "Feature",
  "properties": {
    "date:inception_lower": "1980-01-01",
    "date:inception_upper": "1980-01-01",
    "iso:country": "GB",
    "wof:name": "HD1 5AA",
    "wof:placetype": "postalcode"
  },
  "geometry": {"coordinates":[-1.783142,53.649541],"type":"Point"}
}
