{
  "type": "Feature",
  "properties": {
    "iso:country":"GB",
    "wof:name":"LE16 8DX",
    "wof:placetype":"postalcode"
},
  "geometry": {"coordinates":[-0.82214335210806,52.52836759550497],"type":"Point"}
}