{
  "type": "Feature",
  "properties": {
    "date:inception_lower":"1980-01-01",
    "date:inception_upper":"1980-01-31",
    "iso:country":"GB",
    "wof:name":"LE16 8DX",
    "wof:placetype":"postalcode"
},
  "geometry": {"coordinates":[-0.822143,52.528368],"type":"Point"}
}