{
  "type": "Feature",
  "properties": {
    "iso:country":"GB",
    "wof:name":"BA1 3DD",
    "wof:placetype":"postalcode"
},
  "geometry": {"coordinates":[-2.3816187470431,51.38494416644267],"type":"Point"}
}