{
  "type": "Feature",
  "properties": {
    "iso:country": "GB",
    "wof:name": "DT3 5AW",
    "wof:placetype": "postalcode"
  },
  "geometry": {"coordinates":[-2.470396,50.639836],"type":"Point"}
}
