{
  "type": "Feature",
  "properties": {
    "iso:country":"GB",
    "wof:name":"DT3 5AW",
    "wof:placetype":"postalcode"
},
  "geometry": {"coordinates":[-2.47039606927138,50.63983554992167],"type":"Point"}
}