{
  "type": "Feature",
  "properties": {
    "date:inception_lower": "2006-04-01",
    "date:inception_upper": "2006-04-01",
    "iso:country": "GB",
    "wof:name": "GL50 3NS",
    "wof:placetype": "postalcode"
  },
  "geometry": {"coordinates":[-2.088007,51.904373],"type":"Point"}
}
