{
  "type": "Feature",
  "properties": {
    "iso:country": "GB",
    "wof:name": "BL8 1PR",
    "wof:placetype": "postalcode"
  },
  "geometry": {"coordinates":[-2.324375,53.602054],"type":"Point"}
}
