{
  "type": "Feature",
  "properties": {
    "iso:country":"GB",
    "wof:name":"BL8 1PR",
    "wof:placetype":"postalcode"
},
  "geometry": {"coordinates":[-2.32437468950397,53.60205407813435],"type":"Point"}
}