{
  "type": "Feature",
  "properties": {
    "date:inception_lower": "1980-01-01",
    "date:inception_upper": "1980-01-01",
    "iso:country": "GB",
    "wof:name": "CF5 6SH",
    "wof:placetype": "postalcode"
  },
  "geometry": {"coordinates":[-3.308655,51.460705],"type":"Point"}
}
