{
  "type": "Feature",
  "properties": {
    "iso:country":"GB",
    "wof:name":"TW7 5DB",
    "wof:placetype":"postalcode"
},
  "geometry": {"coordinates":[-0.33658842501919,51.48865876701536],"type":"Point"}
}