{
  "type": "Feature",
  "properties": {
    "date:inception_lower":"2009-10-01",
    "date:inception_upper":"2009-10-31",
    "iso:country":"GB",
    "wof:name":"TW7 5DB",
    "wof:placetype":"postalcode"
},
  "geometry": {"coordinates":[-0.336588,51.488659],"type":"Point"}
}