{
  "type": "Feature",
  "properties": {
    "iso:country":"GB",
    "wof:name":"OX1 2BX",
    "wof:placetype":"postalcode"
},
  "geometry": {"coordinates":[-1.26316090867671,51.75409803342119],"type":"Point"}
}