{
  "type": "Feature",
  "properties": {
    "date:inception_lower": "1980-01-01",
    "date:inception_upper": "1980-01-01",
    "iso:country": "GB",
    "wof:name": "OX1 2BX",
    "wof:placetype": "postalcode"
  },
  "geometry": {"coordinates":[-1.263161,51.754098],"type":"Point"}
}
