{
  "type": "Feature",
  "properties": {
    "date:inception_lower": "1980-01-01",
    "date:inception_upper": "1980-01-01",
    "iso:country": "GB",
    "wof:name": "NE6 2ND",
    "wof:placetype": "postalcode"
  },
  "geometry": {"coordinates":[-1.558492,54.970681],"type":"Point"}
}
