{
  "type": "Feature",
  "properties": {
    "iso:country":"GB",
    "wof:name":"NE6 2ND",
    "wof:placetype":"postalcode"
},
  "geometry": {"coordinates":[-1.55849206507113,54.97068139311686],"type":"Point"}
}