{
  "type": "Feature",
  "properties": {
    "iso:country":"GB",
    "wof:name":"NE28 9XE",
    "wof:placetype":"postalcode"
},
  "geometry": {"coordinates":[-1.50912705935645,55.01317711049459],"type":"Point"}
}