{
  "type": "Feature",
  "properties": {
    "iso:country":"GB",
    "wof:name":"SE26 4NA",
    "wof:placetype":"postalcode"
},
  "geometry": {"coordinates":[-0.06370658503009,51.43547838308384],"type":"Point"}
}