{
  "type": "Feature",
  "properties": {
    "iso:country":"GB",
    "wof:name":"CH8 7HQ",
    "wof:placetype":"postalcode"
},
  "geometry": {"coordinates":[-3.1974552181145,53.2822336316279],"type":"Point"}
}