{
  "type": "Feature",
  "properties": {
    "iso:country":"GB",
    "wof:name":"GU34 2HA",
    "wof:placetype":"postalcode"
},
  "geometry": {"coordinates":[-0.96832572242054,51.154668249562],"type":"Point"}
}