{
  "type": "Feature",
  "properties": {
    "iso:country":"GB",
    "wof:name":"HG2 7JH",
    "wof:placetype":"postalcode"
},
  "geometry": {"coordinates":[-1.49841732054337,53.99874338964358],"type":"Point"}
}