{
  "type": "Feature",
  "properties": {
    "iso:country":"GB",
    "wof:name":"BH16 6ER",
    "wof:placetype":"postalcode"
},
  "geometry": {"coordinates":[-2.08310911340147,50.74089011826415],"type":"Point"}
}