{
  "type": "Feature",
  "properties": {
    "iso:country": "GB",
    "wof:name": "BH16 6ER",
    "wof:placetype": "postalcode"
  },
  "geometry": {"coordinates":[-2.083109,50.74089],"type":"Point"}
}
