{
  "type": "Feature",
  "properties": {
    "iso:country":"GB",
    "wof:name":"EH4 2UU",
    "wof:placetype":"postalcode"
},
  "geometry": {"coordinates":[-3.24732650536775,55.95746809147548],"type":"Point"}
}