{
  "type": "Feature",
  "properties": {
    "date:inception_lower": "1980-01-01",
    "date:inception_upper": "1980-01-01",
    "iso:country": "GB",
    "wof:name": "SG14 3BT",
    "wof:placetype": "postalcode"
  },
  "geometry": {"coordinates":[-0.084095,51.803127],"type":"Point"}
}
