{
  "type": "Feature",
  "properties": {
    "date:inception_lower":"2019-04-01",
    "date:inception_upper":"2019-04-30",
    "iso:country":"GB",
    "wof:name":"CW11 4FU",
    "wof:placetype":"postalcode"
},
  "geometry": {"coordinates":[-2.361873,53.143902],"type":"Point"}
}