{
  "type": "Feature",
  "properties": {
    "iso:country":"GB",
    "wof:name":"PO38 2NB",
    "wof:placetype":"postalcode"
},
  "geometry": {"coordinates":[-1.28637432652009,50.57909601675954],"type":"Point"}
}