{
  "type": "Feature",
  "properties": {
    "iso:country": "GB",
    "wof:name": "TS16 9BE",
    "wof:placetype": "postalcode"
  },
  "geometry": {"coordinates":[-1.344369,54.532129],"type":"Point"}
}
