{
  "type": "Feature",
  "properties": {
    "iso:country":"GB",
    "wof:name":"NG15 0BT",
    "wof:placetype":"postalcode"
},
  "geometry": {"coordinates":[-1.2240040802141,53.07205367491646],"type":"Point"}
}