{
  "type": "Feature",
  "properties": {
    "iso:country": "GB",
    "wof:name": "NR30 3NG",
    "wof:placetype": "postalcode"
  },
  "geometry": {"coordinates":[1.730809,52.592029],"type":"Point"}
}
