{
  "type": "Feature",
  "properties": {
    "iso:country":"GB",
    "wof:name":"HP16 9PW",
    "wof:placetype":"postalcode"
},
  "geometry": {"coordinates":[-0.74192641691346,51.72516463411407],"type":"Point"}
}