{
  "type": "Feature",
  "properties": {
    "iso:country": "GB",
    "wof:name": "HP16 9PW",
    "wof:placetype": "postalcode"
  },
  "geometry": {"coordinates":[-0.741884,51.725323],"type":"Point"}
}
