{
  "type": "Feature",
  "properties": {
    "iso:country":"GB",
    "wof:name":"M30 7EL",
    "wof:placetype":"postalcode"
},
  "geometry": {"coordinates":[-2.36929681989867,53.48026582036116],"type":"Point"}
}