{
  "type": "Feature",
  "properties": {
    "iso:country":"GB",
    "wof:name":"RH8 0JA",
    "wof:placetype":"postalcode"
},
  "geometry": {"coordinates":[0.01288059313317,51.24345715671107],"type":"Point"}
}