{
  "type": "Feature",
  "properties": {
    "iso:country":"GB",
    "wof:name":"SE18 3SG",
    "wof:placetype":"postalcode"
},
  "geometry": {"coordinates":[0.06072227277335,51.47901328958613],"type":"Point"}
}