{
  "type": "Feature",
  "properties": {
    "iso:country":"GB",
    "wof:name":"PE8 6UQ",
    "wof:placetype":"postalcode"
},
  "geometry": {"coordinates":[-0.40864640775947,52.50636725686652],"type":"Point"}
}