{
  "type": "Feature",
  "properties": {
    "iso:country":"GB",
    "wof:name":"S73 9EZ",
    "wof:placetype":"postalcode"
},
  "geometry": {"coordinates":[-1.37329223156184,53.53735132003102],"type":"Point"}
}