{
  "type": "Feature",
  "properties": {
    "date:inception_lower": "2022-04-01",
    "date:inception_upper": "2022-04-01",
    "iso:country": "GB",
    "wof:name": "TA4 1FD",
    "wof:placetype": "postalcode"
  },
  "geometry": {"coordinates":[-3.143411,51.003948],"type":"Point"}
}
