{
  "type": "Feature",
  "properties": {
    "iso:country":"GB",
    "wof:name":"PA5 9UW",
    "wof:placetype":"postalcode"
},
  "geometry": {"coordinates":[-4.48386222159231,55.82264186080509],"type":"Point"}
}