{
  "type": "Feature",
  "properties": {
    "iso:country":"GB",
    "wof:name":"CO12 4DT",
    "wof:placetype":"postalcode"
},
  "geometry": {"coordinates":[1.26657710350234,51.93265136875092],"type":"Point"}
}