{
  "type": "Feature",
  "properties": {
    "date:inception_lower":"1993-01-01",
    "date:inception_upper":"1993-01-31",
    "iso:country":"GB",
    "wof:name":"CO12 4DT",
    "wof:placetype":"postalcode"
},
  "geometry": {"coordinates":[1.266577,51.932651],"type":"Point"}
}