{
  "type": "Feature",
  "properties": {
    "date:inception_lower": "2009-04-01",
    "date:inception_upper": "2009-04-01",
    "iso:country": "GB",
    "wof:name": "LE14 3AT",
    "wof:placetype": "postalcode"
  },
  "geometry": {"coordinates":[-1.000566,52.807207],"type":"Point"}
}
