{
  "type": "Feature",
  "properties": {
    "iso:country": "GB",
    "wof:name": "LE14 3AT",
    "wof:placetype": "postalcode"
  },
  "geometry": {"coordinates":[-1.000566,52.807207],"type":"Point"}
}
