{
  "type": "Feature",
  "properties": {
    "iso:country":"GB",
    "wof:name":"SG13 7AW",
    "wof:placetype":"postalcode"
},
  "geometry": {"coordinates":[-0.06629758120225,51.8021163221366],"type":"Point"}
}