{
  "type": "Feature",
  "properties": {
    "date:inception_lower":"2001-06-01",
    "date:inception_upper":"2001-06-30",
    "iso:country":"GB",
    "wof:name":"SG13 7AW",
    "wof:placetype":"postalcode"
},
  "geometry": {"coordinates":[-0.066298,51.802116],"type":"Point"}
}