{
  "type": "Feature",
  "properties": {
    "date:inception_lower": "1986-01-01",
    "date:inception_upper": "1986-01-01",
    "iso:country": "GB",
    "wof:name": "SO41 8YA",
    "wof:placetype": "postalcode"
  },
  "geometry": {"coordinates":[-1.550494,50.769317],"type":"Point"}
}
