{
  "type": "Feature",
  "properties": {
    "iso:country":"GB",
    "wof:name":"SO41 8YA",
    "wof:placetype":"postalcode"
},
  "geometry": {"coordinates":[-1.55049400213239,50.76931677694095],"type":"Point"}
}