{
  "type": "Feature",
  "properties": {
    "iso:country":"GB",
    "wof:name":"MK5 6EP",
    "wof:placetype":"postalcode"
},
  "geometry": {"coordinates":[-0.78340993520726,52.02436647165114],"type":"Point"}
}