{
  "type": "Feature",
  "properties": {
    "iso:country":"GB",
    "wof:name":"HG4 4DU",
    "wof:placetype":"postalcode"
},
  "geometry": {"coordinates":[-1.65720654805217,54.22495071073566],"type":"Point"}
}