{
  "type": "Feature",
  "properties": {
    "date:inception_lower": "1994-12-01",
    "date:inception_upper": "1994-12-01",
    "iso:country": "GB",
    "wof:name": "HG4 4DU",
    "wof:placetype": "postalcode"
  },
  "geometry": {"coordinates":[-1.657206,54.224951],"type":"Point"}
}
