{
  "type": "Feature",
  "properties": {
    "iso:country":"GB",
    "wof:name":"CH64 3TZ",
    "wof:placetype":"postalcode"
},
  "geometry": {"coordinates":[-3.06562238907999,53.29047841686048],"type":"Point"}
}