{
  "type": "Feature",
  "properties": {
    "date:inception_lower":"1999-06-01",
    "date:inception_upper":"1999-06-30",
    "iso:country":"GB",
    "wof:name":"CH64 3TZ",
    "wof:placetype":"postalcode"
},
  "geometry": {"coordinates":[-3.065622,53.290478],"type":"Point"}
}