{
  "type": "Feature",
  "properties": {
    "date:inception_lower": "2020-05-01",
    "date:inception_upper": "2020-05-01",
    "iso:country": "GB",
    "wof:name": "LN8 3TJ",
    "wof:placetype": "postalcode"
  },
  "geometry": {"coordinates":[-0.335915,53.386447],"type":"Point"}
}
