{
  "type": "Feature",
  "properties": {
    "iso:country":"GB",
    "wof:name":"OX20 1QL",
    "wof:placetype":"postalcode"
},
  "geometry": {"coordinates":[-1.34015198298957,51.84507808435464],"type":"Point"}
}