{
  "type": "Feature",
  "properties": {
    "iso:country":"GB",
    "wof:name":"LS29 0DH",
    "wof:placetype":"postalcode"
},
  "geometry": {"coordinates":[-1.81238857486466,53.93831062269843],"type":"Point"}
}