{
  "type": "Feature",
  "properties": {
    "iso:country":"GB",
    "wof:name":"LE10 0HL",
    "wof:placetype":"postalcode"
},
  "geometry": {"coordinates":[-1.37958509311702,52.54890879408662],"type":"Point"}
}