{
  "type": "Feature",
  "properties": {
    "iso:country":"GB",
    "wof:name":"PE16 6LD",
    "wof:placetype":"postalcode"
},
  "geometry": {"coordinates":[0.05002438748123,52.45325505684556],"type":"Point"}
}