{
  "type": "Feature",
  "properties": {
    "iso:country": "GB",
    "wof:name": "NG8 1NQ",
    "wof:placetype": "postalcode"
  },
  "geometry": {"coordinates":[-1.194259,52.955875],"type":"Point"}
}
