{
  "type": "Feature",
  "properties": {
    "iso:country":"GB",
    "wof:name":"FK2 7NE",
    "wof:placetype":"postalcode"
},
  "geometry": {"coordinates":[-3.78684019854961,56.01264153939572],"type":"Point"}
}