{
  "type": "Feature",
  "properties": {
    "iso:country":"GB",
    "wof:name":"HR2 9PG",
    "wof:placetype":"postalcode"
},
  "geometry": {"coordinates":[-2.86172771830738,52.02536098808594],"type":"Point"}
}