{
  "type": "Feature",
  "properties": {
    "date:inception_lower": "2004-06-01",
    "date:inception_upper": "2004-06-01",
    "iso:country": "GB",
    "wof:name": "HR2 9PG",
    "wof:placetype": "postalcode"
  },
  "geometry": {"coordinates":[-2.861982,52.025547],"type":"Point"}
}
