{
  "type": "Feature",
  "properties": {
    "iso:country":"GB",
    "wof:name":"SG17 5DN",
    "wof:placetype":"postalcode"
},
  "geometry": {"coordinates":[-0.33385945773611,52.03913374886339],"type":"Point"}
}