{
  "type": "Feature",
  "properties": {
    "iso:country":"GB",
    "wof:name":"PE13 1RG",
    "wof:placetype":"postalcode"
},
  "geometry": {"coordinates":[0.15630240905546,52.66565006623123],"type":"Point"}
}