{
  "type": "Feature",
  "properties": {
    "iso:country": "GB",
    "wof:name": "PE13 1RG",
    "wof:placetype": "postalcode"
  },
  "geometry": {"coordinates":[0.156288,52.66567],"type":"Point"}
}
