{
  "type": "Feature",
  "properties": {
    "iso:country": "GB",
    "wof:name": "HP20 2BX",
    "wof:placetype": "postalcode"
  },
  "geometry": {"coordinates":[-0.800255,51.827019],"type":"Point"}
}
