{
  "type": "Feature",
  "properties": {
    "iso:country":"GB",
    "wof:name":"B32 4AJ",
    "wof:placetype":"postalcode"
},
  "geometry": {"coordinates":[-2.01038537849005,52.43765487699954],"type":"Point"}
}