{
  "type": "Feature",
  "properties": {
    "iso:country": "GB",
    "wof:name": "DE72 3WA",
    "wof:placetype": "postalcode"
  },
  "geometry": {"coordinates":[-1.394145,52.884211],"type":"Point"}
}
