{
  "type": "Feature",
  "properties": {
    "iso:country":"GB",
    "wof:name":"DE72 3WA",
    "wof:placetype":"postalcode"
},
  "geometry": {"coordinates":[-1.39414552587303,52.88421118150649],"type":"Point"}
}