{
  "type": "Feature",
  "properties": {
    "date:inception_lower": "2022-07-01",
    "date:inception_upper": "2022-07-01",
    "iso:country": "GB",
    "wof:name": "BS34 8BU",
    "wof:placetype": "postalcode"
  },
  "geometry": {"coordinates":[-2.528429,51.518672],"type":"Point"}
}
