{
  "type": "Feature",
  "properties": {
    "iso:country":"GB",
    "wof:name":"SA12 8US",
    "wof:placetype":"postalcode"
},
  "geometry": {"coordinates":[-3.80081749791741,51.62088640250347],"type":"Point"}
}