{
  "type": "Feature",
  "properties": {
    "iso:country": "GB",
    "wof:name": "SY3 9FR",
    "wof:placetype": "postalcode"
  },
  "geometry": {"coordinates":[-2.775313,52.690507],"type":"Point"}
}
