{
  "type": "Feature",
  "properties": {
    "date:inception_lower":"1997-12-01",
    "date:inception_upper":"1997-12-31",
    "iso:country":"GB",
    "wof:name":"BS30 5JD",
    "wof:placetype":"postalcode"
},
  "geometry": {"coordinates":[-2.470449,51.450159],"type":"Point"}
}