{
  "type": "Feature",
  "properties": {
    "date:inception_lower": "2001-06-01",
    "date:inception_upper": "2001-06-01",
    "iso:country": "GB",
    "wof:name": "BS37 6SP",
    "wof:placetype": "postalcode"
  },
  "geometry": {"coordinates":[-2.362114,51.518882],"type":"Point"}
}
