{
  "type": "Feature",
  "properties": {
    "iso:country":"GB",
    "wof:name":"BS37 6SP",
    "wof:placetype":"postalcode"
},
  "geometry": {"coordinates":[-2.36211400096131,51.51888170738638],"type":"Point"}
}