{
  "type": "Feature",
  "properties": {
    "iso:country":"GB",
    "wof:name":"NE25 0EY",
    "wof:placetype":"postalcode"
},
  "geometry": {"coordinates":[-1.5292431805227,55.07539606516278],"type":"Point"}
}