{
  "type": "Feature",
  "properties": {
    "date:inception_lower": "1996-06-01",
    "date:inception_upper": "1996-06-01",
    "iso:country": "GB",
    "wof:name": "NE25 0EY",
    "wof:placetype": "postalcode"
  },
  "geometry": {"coordinates":[-1.529243,55.075396],"type":"Point"}
}
