{
  "type": "Feature",
  "properties": {
    "iso:country": "GB",
    "wof:name": "NE25 0EY",
    "wof:placetype": "postalcode"
  },
  "geometry": {"coordinates":[-1.529243,55.075396],"type":"Point"}
}
