{
  "type": "Feature",
  "properties": {
    "date:inception_lower": "1980-01-01",
    "date:inception_upper": "1980-01-01",
    "iso:country": "GB",
    "wof:name": "BA6 8HR",
    "wof:placetype": "postalcode"
  },
  "geometry": {"coordinates":[-2.70664,51.153096],"type":"Point"}
}
