{
  "type": "Feature",
  "properties": {
    "date:inception_lower": "2020-12-01",
    "date:inception_upper": "2020-12-01",
    "iso:country": "GB",
    "wof:name": "CA2 4FD",
    "wof:placetype": "postalcode"
  },
  "geometry": {"coordinates":[-2.929097,54.876498],"type":"Point"}
}
