{
  "type": "Feature",
  "properties": {
    "iso:country":"GB",
    "wof:name":"B96 6EQ",
    "wof:placetype":"postalcode"
},
  "geometry": {"coordinates":[-1.94038156921898,52.26154123460616],"type":"Point"}
}