{
  "type": "Feature",
  "properties": {
    "iso:country": "GB",
    "wof:name": "PA2 9QS",
    "wof:placetype": "postalcode"
  },
  "geometry": {"coordinates":[-4.438242,55.83097],"type":"Point"}
}
