{
  "type": "Feature",
  "properties": {
    "date:inception_lower": "1980-01-01",
    "date:inception_upper": "1980-01-01",
    "iso:country": "GB",
    "wof:name": "PA2 9QS",
    "wof:placetype": "postalcode"
  },
  "geometry": {"coordinates":[-4.438242,55.83097],"type":"Point"}
}
