{
  "type": "Feature",
  "properties": {
    "iso:country": "GB",
    "wof:name": "SA17 4NS",
    "wof:placetype": "postalcode"
  },
  "geometry": {"coordinates":[-4.278958,51.755289],"type":"Point"}
}
