{
  "type": "Feature",
  "properties": {
    "date:inception_lower": "1994-05-01",
    "date:inception_upper": "1994-05-01",
    "iso:country": "GB",
    "wof:name": "M26 2SG",
    "wof:placetype": "postalcode"
  },
  "geometry": {"coordinates":[-2.3229,53.561518],"type":"Point"}
}
