{
  "type": "Feature",
  "properties": {
    "iso:country": "GB",
    "wof:name": "M26 2SG",
    "wof:placetype": "postalcode"
  },
  "geometry": {"coordinates":[-2.3229,53.561518],"type":"Point"}
}
