{
  "type": "Feature",
  "properties": {
    "iso:country":"GB",
    "wof:name":"M26 2SG",
    "wof:placetype":"postalcode"
},
  "geometry": {"coordinates":[-2.32285582697313,53.56143096520685],"type":"Point"}
}