{
  "type": "Feature",
  "properties": {
    "iso:country":"GB",
    "wof:name":"SA5 8EG",
    "wof:placetype":"postalcode"
},
  "geometry": {"coordinates":[-3.97344071965069,51.64331650293622],"type":"Point"}
}