{
  "type": "Feature",
  "properties": {
    "iso:country":"GB",
    "wof:name":"SO16 5TA",
    "wof:placetype":"postalcode"
},
  "geometry": {"coordinates":[-1.43864421362127,50.93446620288982],"type":"Point"}
}