{
  "type": "Feature",
  "properties": {
    "iso:country":"GB",
    "wof:name":"ME16 0RX",
    "wof:placetype":"postalcode"
},
  "geometry": {"coordinates":[0.49956471162516,51.28352885755591],"type":"Point"}
}