{
  "type": "Feature",
  "properties": {
    "iso:country":"GB",
    "wof:name":"EN8 7HG",
    "wof:placetype":"postalcode"
},
  "geometry": {"coordinates":[-0.0226188722177,51.6851638883509],"type":"Point"}
}