{
  "type": "Feature",
  "properties": {
    "iso:country": "GB",
    "wof:name": "CV22 5BH",
    "wof:placetype": "postalcode"
  },
  "geometry": {"coordinates":[-1.232524,52.361752],"type":"Point"}
}
