{
  "type": "Feature",
  "properties": {
    "iso:country":"GB",
    "wof:name":"SL6 5ND",
    "wof:placetype":"postalcode"
},
  "geometry": {"coordinates":[-0.80701965507727,51.5495162207698],"type":"Point"}
}