{
  "type": "Feature",
  "properties": {
    "iso:country":"GB",
    "wof:name":"B91 1ER",
    "wof:placetype":"postalcode"
},
  "geometry": {"coordinates":[-1.80366001092958,52.42241651141709],"type":"Point"}
}