{
  "type": "Feature",
  "properties": {
    "iso:country": "GB",
    "wof:name": "B91 1ER",
    "wof:placetype": "postalcode"
  },
  "geometry": {"coordinates":[-1.80366,52.422417],"type":"Point"}
}
