{
  "type": "Feature",
  "properties": {
    "iso:country": "GB",
    "wof:name": "BN44 3DW",
    "wof:placetype": "postalcode"
  },
  "geometry": {"coordinates":[-0.373619,50.914476],"type":"Point"}
}
