{
  "type": "Feature",
  "properties": {
    "iso:country":"GB",
    "wof:name":"BN44 3DW",
    "wof:placetype":"postalcode"
},
  "geometry": {"coordinates":[-0.37490533891608,50.9109473547769],"type":"Point"}
}