{
  "type": "Feature",
  "properties": {
    "iso:country":"GB",
    "wof:name":"CR4 1RA",
    "wof:placetype":"postalcode"
},
  "geometry": {"coordinates":[-0.13353650595518,51.39717837832034],"type":"Point"}
}