{
  "type": "Feature",
  "properties": {
    "iso:country":"GB",
    "wof:name":"E2 7SH",
    "wof:placetype":"postalcode"
},
  "geometry": {"coordinates":[-0.07100399179264,51.53063281051266],"type":"Point"}
}