{
  "type": "Feature",
  "properties": {
    "iso:country":"GB",
    "wof:name":"WN2 1SL",
    "wof:placetype":"postalcode"
},
  "geometry": {"coordinates":[-2.59151656845036,53.57281659084901],"type":"Point"}
}