{
  "type": "Feature",
  "properties": {
    "iso:country":"GB",
    "wof:name":"RG22 5ND",
    "wof:placetype":"postalcode"
},
  "geometry": {"coordinates":[-1.13413723242124,51.24310176791018],"type":"Point"}
}