{
  "type": "Feature",
  "properties": {
    "iso:country": "GB",
    "wof:name": "RG22 5ND",
    "wof:placetype": "postalcode"
  },
  "geometry": {"coordinates":[-1.13412,51.243101],"type":"Point"}
}
