{
  "type": "Feature",
  "properties": {
    "iso:country":"GB",
    "wof:name":"WD17 3TX",
    "wof:placetype":"postalcode"
},
  "geometry": {"coordinates":[-0.42881755293158,51.67568949168945],"type":"Point"}
}