{
  "type": "Feature",
  "properties": {
    "date:inception_lower": "2000-10-01",
    "date:inception_upper": "2000-10-01",
    "iso:country": "GB",
    "wof:name": "WD17 3TX",
    "wof:placetype": "postalcode"
  },
  "geometry": {"coordinates":[-0.428818,51.675689],"type":"Point"}
}
