{
  "type": "Feature",
  "properties": {
    "iso:country":"GB",
    "wof:name":"RH1 3QE",
    "wof:placetype":"postalcode"
},
  "geometry": {"coordinates":[-0.14198882269396,51.25975944323511],"type":"Point"}
}