{
  "type": "Feature",
  "properties": {
    "date:inception_lower": "1997-12-01",
    "date:inception_upper": "1997-12-01",
    "iso:country": "GB",
    "wof:name": "BS41 9BB",
    "wof:placetype": "postalcode"
  },
  "geometry": {"coordinates":[-2.66535,51.427895],"type":"Point"}
}
