{
  "type": "Feature",
  "properties": {
    "iso:country":"GB",
    "wof:name":"ME12 2PA",
    "wof:placetype":"postalcode"
},
  "geometry": {"coordinates":[0.76805291803863,51.43951271736471],"type":"Point"}
}