{
  "type": "Feature",
  "properties": {
    "iso:country": "GB",
    "wof:name": "SE19 3EA",
    "wof:placetype": "postalcode"
  },
  "geometry": {"coordinates":[-0.096851,51.41621],"type":"Point"}
}
