{
  "type": "Feature",
  "properties": {
    "iso:country":"GB",
    "wof:name":"CA11 0TY",
    "wof:placetype":"postalcode"
},
  "geometry": {"coordinates":[-2.87092620791297,54.66942564650764],"type":"Point"}
}