{
  "type": "Feature",
  "properties": {
    "iso:country":"GB",
    "wof:name":"HD9 5JX",
    "wof:placetype":"postalcode"
},
  "geometry": {"coordinates":[-1.8547120835499,53.59287895993629],"type":"Point"}
}