{
  "type": "Feature",
  "properties": {
    "date:inception_lower": "2001-06-01",
    "date:inception_upper": "2001-06-01",
    "iso:country": "GB",
    "wof:name": "HD9 5JX",
    "wof:placetype": "postalcode"
  },
  "geometry": {"coordinates":[-1.854712,53.592879],"type":"Point"}
}
