{
  "type": "Feature",
  "properties": {
    "iso:country": "GB",
    "wof:name": "HD9 5JX",
    "wof:placetype": "postalcode"
  },
  "geometry": {"coordinates":[-1.854712,53.592879],"type":"Point"}
}
