{
  "type": "Feature",
  "properties": {
    "iso:country":"GB",
    "wof:name":"DL17 9LX",
    "wof:placetype":"postalcode"
},
  "geometry": {"coordinates":[-1.5197081890213,54.70408471230305],"type":"Point"}
}