{
  "type": "Feature",
  "properties": {
    "iso:country":"GB",
    "wof:name":"HP10 0QB",
    "wof:placetype":"postalcode"
},
  "geometry": {"coordinates":[-0.69342644353085,51.57875304464909],"type":"Point"}
}