{
  "type": "Feature",
  "properties": {
    "date:inception_lower": "1980-01-01",
    "date:inception_upper": "1980-01-01",
    "iso:country": "GB",
    "wof:name": "RH10 6RB",
    "wof:placetype": "postalcode"
  },
  "geometry": {"coordinates":[-0.163832,51.107071],"type":"Point"}
}
