{
  "type": "Feature",
  "properties": {
    "iso:country": "GB",
    "wof:name": "RH10 6RB",
    "wof:placetype": "postalcode"
  },
  "geometry": {"coordinates":[-0.163832,51.107071],"type":"Point"}
}
