{
  "type": "Feature",
  "properties": {
    "iso:country":"GB",
    "wof:name":"W2 3LH",
    "wof:placetype":"postalcode"
},
  "geometry": {"coordinates":[-0.17885129773793,51.51210570449069],"type":"Point"}
}