{
  "type": "Feature",
  "properties": {
    "iso:country":"GB",
    "wof:name":"TW9 2TF",
    "wof:placetype":"postalcode"
},
  "geometry": {"coordinates":[-0.29897140583863,51.46681621875074],"type":"Point"}
}