{
  "type": "Feature",
  "properties": {
    "iso:country":"GB",
    "wof:name":"TW3 1SW",
    "wof:placetype":"postalcode"
},
  "geometry": {"coordinates":[-0.35128953292891,51.46923611231857],"type":"Point"}
}