{
  "type": "Feature",
  "properties": {
    "iso:country":"GB",
    "wof:name":"LL54 7BT",
    "wof:placetype":"postalcode"
},
  "geometry": {"coordinates":[-4.23225564616033,53.0713735931278],"type":"Point"}
}