{
  "type": "Feature",
  "properties": {
    "iso:country":"GB",
    "wof:name":"SE1 8AP",
    "wof:placetype":"postalcode"
},
  "geometry": {"coordinates":[-0.10714178857702,51.50508020650297],"type":"Point"}
}