{
  "type": "Feature",
  "properties": {
    "date:inception_lower":"2017-01-01",
    "date:inception_upper":"2017-01-31",
    "iso:country":"GB",
    "wof:name":"PE28 2PP",
    "wof:placetype":"postalcode"
},
  "geometry": {"coordinates":[-0.081919,52.403255],"type":"Point"}
}