{
  "type": "Feature",
  "properties": {
    "iso:country": "GB",
    "wof:name": "PE28 2PP",
    "wof:placetype": "postalcode"
  },
  "geometry": {"coordinates":[-0.081919,52.403255],"type":"Point"}
}
