{
  "type": "Feature",
  "properties": {
    "iso:country":"GB",
    "wof:name":"WF7 7NY",
    "wof:placetype":"postalcode"
},
  "geometry": {"coordinates":[-1.3460981375824,53.64433899305686],"type":"Point"}
}