{
  "type": "Feature",
  "properties": {
    "iso:country": "GB",
    "wof:name": "WF7 7NY",
    "wof:placetype": "postalcode"
  },
  "geometry": {"coordinates":[-1.346098,53.644339],"type":"Point"}
}
