{
  "type": "Feature",
  "properties": {
    "date:inception_lower": "2005-08-01",
    "date:inception_upper": "2005-08-01",
    "iso:country": "GB",
    "wof:name": "WF7 7NY",
    "wof:placetype": "postalcode"
  },
  "geometry": {"coordinates":[-1.346098,53.644339],"type":"Point"}
}
