{
  "type": "Feature",
  "properties": {
    "iso:country":"GB",
    "wof:name":"LL33 0SQ",
    "wof:placetype":"postalcode"
},
  "geometry": {"coordinates":[-3.96781465426928,53.24964732543197],"type":"Point"}
}