{
  "type": "Feature",
  "properties": {
    "date:inception_lower": "1999-06-01",
    "date:inception_upper": "1999-06-01",
    "iso:country": "GB",
    "wof:name": "LL33 0SQ",
    "wof:placetype": "postalcode"
  },
  "geometry": {"coordinates":[-3.967772,53.24962],"type":"Point"}
}
