{
  "type": "Feature",
  "properties": {
    "iso:country": "GB",
    "wof:name": "LL33 0SQ",
    "wof:placetype": "postalcode"
  },
  "geometry": {"coordinates":[-3.967835,53.249673],"type":"Point"}
}
