{
  "type": "Feature",
  "properties": {
    "iso:country": "GB",
    "wof:name": "SK11 0QB",
    "wof:placetype": "postalcode"
  },
  "geometry": {"coordinates":[-2.128774,53.195602],"type":"Point"}
}
