{
  "type": "Feature",
  "properties": {
    "iso:country":"GB",
    "wof:name":"SK11 0QB",
    "wof:placetype":"postalcode"
},
  "geometry": {"coordinates":[-2.1287604015874,53.19554845632832],"type":"Point"}
}