{
  "type": "Feature",
  "properties": {
    "date:inception_lower":"2015-12-01",
    "date:inception_upper":"2015-12-31",
    "iso:country":"GB",
    "wof:name":"SK11 0QB",
    "wof:placetype":"postalcode"
},
  "geometry": {"coordinates":[-2.128774,53.195602],"type":"Point"}
}