{
  "type": "Feature",
  "properties": {
    "iso:country":"GB",
    "wof:name":"LE7 7QF",
    "wof:placetype":"postalcode"
},
  "geometry": {"coordinates":[-1.12622693297475,52.70973291926218],"type":"Point"}
}