{
  "type": "Feature",
  "properties": {
    "iso:country":"GB",
    "wof:name":"DT6 6SE",
    "wof:placetype":"postalcode"
},
  "geometry": {"coordinates":[-2.8990356369791,50.73992528123351],"type":"Point"}
}