{
  "type": "Feature",
  "properties": {
    "iso:country":"GB",
    "wof:name":"IV4 7BB",
    "wof:placetype":"postalcode"
},
  "geometry": {"coordinates":[-4.49939645114764,57.44658900938934],"type":"Point"}
}