{
  "type": "Feature",
  "properties": {
    "date:inception_lower": "1992-08-01",
    "date:inception_upper": "1992-08-01",
    "iso:country": "GB",
    "wof:name": "IP23 7AY",
    "wof:placetype": "postalcode"
  },
  "geometry": {"coordinates":[1.146945,52.320185],"type":"Point"}
}
