{
  "type": "Feature",
  "properties": {
    "iso:country":"GB",
    "wof:name":"IP23 7AY",
    "wof:placetype":"postalcode"
},
  "geometry": {"coordinates":[1.14687437151858,52.32019447509494],"type":"Point"}
}