{
  "type": "Feature",
  "properties": {
    "iso:country": "GB",
    "wof:name": "IP23 7AY",
    "wof:placetype": "postalcode"
  },
  "geometry": {"coordinates":[1.146874,52.320194],"type":"Point"}
}
