{
  "type": "Feature",
  "properties": {
    "iso:country": "GB",
    "wof:name": "CH66 1QZ",
    "wof:placetype": "postalcode"
  },
  "geometry": {"coordinates":[-2.952167,53.292697],"type":"Point"}
}
