{
  "type": "Feature",
  "properties": {
    "date:inception_lower": "1980-01-01",
    "date:inception_upper": "1980-01-01",
    "iso:country": "GB",
    "wof:name": "TW12 1RR",
    "wof:placetype": "postalcode"
  },
  "geometry": {"coordinates":[-0.357115,51.427288],"type":"Point"}
}
