{
  "type": "Feature",
  "properties": {
    "date:inception_lower":"1980-01-01",
    "date:inception_upper":"1980-01-31",
    "iso:country":"GB",
    "wof:name":"TD15 1NR",
    "wof:placetype":"postalcode"
},
  "geometry": {"coordinates":[-2.014497,55.775809],"type":"Point"}
}