{
  "type": "Feature",
  "properties": {
    "iso:country": "GB",
    "wof:name": "M1 1LN",
    "wof:placetype": "postalcode"
  },
  "geometry": {"coordinates":[-2.234923,53.48153],"type":"Point"}
}
