{
  "type": "Feature",
  "properties": {
    "iso:country":"GB",
    "wof:name":"IP33 3DX",
    "wof:placetype":"postalcode"
},
  "geometry": {"coordinates":[0.70292284780994,52.24469243134925],"type":"Point"}
}