{
  "type": "Feature",
  "properties": {
    "iso:country":"GB",
    "wof:name":"SK3 8JD",
    "wof:placetype":"postalcode"
},
  "geometry": {"coordinates":[-2.15864834007538,53.39675190389852],"type":"Point"}
}