{
  "type": "Feature",
  "properties": {
    "date:inception_lower": "1980-01-01",
    "date:inception_upper": "1980-01-01",
    "iso:country": "GB",
    "wof:name": "SK3 8JD",
    "wof:placetype": "postalcode"
  },
  "geometry": {"coordinates":[-2.158648,53.396752],"type":"Point"}
}
