{
  "type": "Feature",
  "properties": {
    "iso:country":"GB",
    "wof:name":"FK8 3UJ",
    "wof:placetype":"postalcode"
},
  "geometry": {"coordinates":[-4.37974145447224,56.1785423935894],"type":"Point"}
}