{
  "type": "Feature",
  "properties": {
    "iso:country":"GB",
    "wof:name":"DT5 1HR",
    "wof:placetype":"postalcode"
},
  "geometry": {"coordinates":[-2.430540983739,50.54188593321546],"type":"Point"}
}