{
  "type": "Feature",
  "properties": {
    "iso:country": "GB",
    "wof:name": "DT5 1HR",
    "wof:placetype": "postalcode"
  },
  "geometry": {"coordinates":[-2.430541,50.541886],"type":"Point"}
}
