{
  "type": "Feature",
  "properties": {
    "iso:country":"GB",
    "wof:name":"NE21 6EL",
    "wof:placetype":"postalcode"
},
  "geometry": {"coordinates":[-1.7355702732209,54.95174866204297],"type":"Point"}
}