{
  "type": "Feature",
  "properties": {
    "iso:country":"GB",
    "wof:name":"TW1 3AE",
    "wof:placetype":"postalcode"
},
  "geometry": {"coordinates":[-0.32485784303405,51.44989655093386],"type":"Point"}
}