{
  "type": "Feature",
  "properties": {
    "iso:country":"GB",
    "wof:name":"BN10 8RT",
    "wof:placetype":"postalcode"
},
  "geometry": {"coordinates":[0.01257741502687,50.78998103572951],"type":"Point"}
}