{
  "type": "Feature",
  "properties": {
    "iso:country": "GB",
    "wof:name": "DE55 7HF",
    "wof:placetype": "postalcode"
  },
  "geometry": {"coordinates":[-1.372594,53.093218],"type":"Point"}
}
