{
  "type": "Feature",
  "properties": {
    "iso:country":"GB",
    "wof:name":"DE55 7HF",
    "wof:placetype":"postalcode"
},
  "geometry": {"coordinates":[-1.3725938938233,53.09321811239833],"type":"Point"}
}