{
  "type": "Feature",
  "properties": {
    "date:inception_lower": "1980-01-01",
    "date:inception_upper": "1980-01-01",
    "iso:country": "GB",
    "wof:name": "OL10 2BG",
    "wof:placetype": "postalcode"
  },
  "geometry": {"coordinates":[-2.212749,53.584553],"type":"Point"}
}
