{
  "type": "Feature",
  "properties": {
    "iso:country": "GB",
    "wof:name": "G74 1LT",
    "wof:placetype": "postalcode"
  },
  "geometry": {"coordinates":[-4.177828,55.759861],"type":"Point"}
}
