{
  "type": "Feature",
  "properties": {
    "iso:country":"GB",
    "wof:name":"EX3 0AQ",
    "wof:placetype":"postalcode"
},
  "geometry": {"coordinates":[-3.46041090067428,50.68284753325289],"type":"Point"}
}