{
  "type": "Feature",
  "properties": {
    "iso:country": "GB",
    "wof:name": "EX3 0AQ",
    "wof:placetype": "postalcode"
  },
  "geometry": {"coordinates":[-3.460411,50.682848],"type":"Point"}
}
