{
  "type": "Feature",
  "properties": {
    "iso:country":"GB",
    "wof:name":"SE25 5PQ",
    "wof:placetype":"postalcode"
},
  "geometry": {"coordinates":[-0.09140915640552,51.39216527779683],"type":"Point"}
}