{
  "type": "Feature",
  "properties": {
    "iso:country":"GB",
    "wof:name":"N16 8QQ",
    "wof:placetype":"postalcode"
},
  "geometry": {"coordinates":[-0.08296391534881,51.55687124971887],"type":"Point"}
}