{
  "type": "Feature",
  "properties": {
    "iso:country":"GB",
    "wof:name":"RG12 0GR",
    "wof:placetype":"postalcode"
},
  "geometry": {"coordinates":[-0.73585807502914,51.39376722082256],"type":"Point"}
}