{
  "type": "Feature",
  "properties": {
    "iso:country":"GB",
    "wof:name":"S35 8NN",
    "wof:placetype":"postalcode"
},
  "geometry": {"coordinates":[-1.48595563747231,53.43534726426834],"type":"Point"}
}