{
  "type": "Feature",
  "properties": {
    "iso:country": "GB",
    "wof:name": "S25 3SJ",
    "wof:placetype": "postalcode"
  },
  "geometry": {"coordinates":[-1.22848,53.37558],"type":"Point"}
}
