{
  "type": "Feature",
  "properties": {
    "date:inception_lower": "1980-01-01",
    "date:inception_upper": "1980-01-01",
    "iso:country": "GB",
    "wof:name": "RH16 2QR",
    "wof:placetype": "postalcode"
  },
  "geometry": {"coordinates":[-0.051135,51.020132],"type":"Point"}
}
