{
  "type": "Feature",
  "properties": {
    "iso:country": "GB",
    "wof:name": "RH16 2QR",
    "wof:placetype": "postalcode"
  },
  "geometry": {"coordinates":[-0.051135,51.020132],"type":"Point"}
}
