{
  "type": "Feature",
  "properties": {
    "iso:country": "GB",
    "wof:name": "CF71 7LE",
    "wof:placetype": "postalcode"
  },
  "geometry": {"coordinates":[-3.43006,51.46701],"type":"Point"}
}
