{
  "type": "Feature",
  "properties": {
    "date:inception_lower":"2003-11-01",
    "date:inception_upper":"2003-11-30",
    "iso:country":"GB",
    "wof:name":"CF71 7LE",
    "wof:placetype":"postalcode"
},
  "geometry": {"coordinates":[-3.43006,51.46701],"type":"Point"}
}