{
  "type": "Feature",
  "properties": {
    "iso:country":"GB",
    "wof:name":"CF71 7LE",
    "wof:placetype":"postalcode"
},
  "geometry": {"coordinates":[-3.43005956189889,51.46701043585382],"type":"Point"}
}