{
  "type": "Feature",
  "properties": {
    "date:inception_lower": "1997-12-01",
    "date:inception_upper": "1997-12-01",
    "iso:country": "GB",
    "wof:name": "SK13 6NN",
    "wof:placetype": "postalcode"
  },
  "geometry": {"coordinates":[-1.969041,53.43954],"type":"Point"}
}
