{
  "type": "Feature",
  "properties": {
    "iso:country":"GB",
    "wof:name":"TS14 6BG",
    "wof:placetype":"postalcode"
},
  "geometry": {"coordinates":[-1.05252001618659,54.53539592238702],"type":"Point"}
}