{
  "type": "Feature",
  "properties": {
    "date:inception_lower":"1980-01-01",
    "date:inception_upper":"1980-01-31",
    "iso:country":"GB",
    "wof:name":"TS14 6BG",
    "wof:placetype":"postalcode"
},
  "geometry": {"coordinates":[-1.052133,54.53546],"type":"Point"}
}