{
  "type": "Feature",
  "properties": {
    "iso:country": "GB",
    "wof:name": "YO43 4SQ",
    "wof:placetype": "postalcode"
  },
  "geometry": {"coordinates":[-0.606155,53.822832],"type":"Point"}
}
