{
  "type": "Feature",
  "properties": {
    "date:inception_lower": "1980-01-01",
    "date:inception_upper": "1980-01-01",
    "iso:country": "GB",
    "wof:name": "PL24 2PH",
    "wof:placetype": "postalcode"
  },
  "geometry": {"coordinates":[-4.700989,50.356031],"type":"Point"}
}
