{
  "type": "Feature",
  "properties": {
    "iso:country":"GB",
    "wof:name":"PL24 2PH",
    "wof:placetype":"postalcode"
},
  "geometry": {"coordinates":[-4.7009895290931,50.35603122692692],"type":"Point"}
}