{
  "type": "Feature",
  "properties": {
    "iso:country": "GB",
    "wof:name": "CV10 9HY",
    "wof:placetype": "postalcode"
  },
  "geometry": {"coordinates":[-1.513601,52.524264],"type":"Point"}
}
