{
  "type": "Feature",
  "properties": {
    "iso:country": "GB",
    "wof:name": "GL6 0RR",
    "wof:placetype": "postalcode"
  },
  "geometry": {"coordinates":[-2.223699,51.694747],"type":"Point"}
}
