{
  "type": "Feature",
  "properties": {
    "iso:country":"GB",
    "wof:name":"GL6 0RR",
    "wof:placetype":"postalcode"
},
  "geometry": {"coordinates":[-2.22369857636525,51.69474704988428],"type":"Point"}
}