{
  "type": "Feature",
  "properties": {
    "iso:country":"GB",
    "wof:name":"PO32 6JP",
    "wof:placetype":"postalcode"
},
  "geometry": {"coordinates":[-1.28287969253764,50.74862662089961],"type":"Point"}
}