{
  "type": "Feature",
  "properties": {
    "iso:country": "GB",
    "wof:name": "PO32 6JP",
    "wof:placetype": "postalcode"
  },
  "geometry": {"coordinates":[-1.28287,50.748607],"type":"Point"}
}
