{
  "type": "Feature",
  "properties": {
    "iso:country":"GB",
    "wof:name":"BA14 6DX",
    "wof:placetype":"postalcode"
},
  "geometry": {"coordinates":[-2.15959854187044,51.3221557961552],"type":"Point"}
}