{
  "type": "Feature",
  "properties": {
    "date:inception_lower": "1980-01-01",
    "date:inception_upper": "1980-01-01",
    "iso:country": "GB",
    "wof:name": "B29 5NU",
    "wof:placetype": "postalcode"
  },
  "geometry": {"coordinates":[-1.968449,52.434568],"type":"Point"}
}
