{
  "type": "Feature",
  "properties": {
    "iso:country":"GB",
    "wof:name":"RH2 0HA",
    "wof:placetype":"postalcode"
},
  "geometry": {"coordinates":[-0.19112227113925,51.24766932779139],"type":"Point"}
}