{
  "type": "Feature",
  "properties": {
    "date:inception_lower": "1980-01-01",
    "date:inception_upper": "1980-01-01",
    "iso:country": "GB",
    "wof:name": "RH2 0HA",
    "wof:placetype": "postalcode"
  },
  "geometry": {"coordinates":[-0.191122,51.247669],"type":"Point"}
}
