{
  "type": "Feature",
  "properties": {
    "date:inception_lower": "1980-01-01",
    "date:inception_upper": "1980-01-01",
    "iso:country": "GB",
    "wof:name": "CF33 6DT",
    "wof:placetype": "postalcode"
  },
  "geometry": {"coordinates":[-3.673769,51.534176],"type":"Point"}
}
