{
  "type": "Feature",
  "properties": {
    "iso:country":"GB",
    "wof:name":"CF33 6DT",
    "wof:placetype":"postalcode"
},
  "geometry": {"coordinates":[-3.67376869309364,51.53417576725589],"type":"Point"}
}