{
  "type": "Feature",
  "properties": {
    "iso:country":"GB",
    "wof:name":"KA11 1PL",
    "wof:placetype":"postalcode"
},
  "geometry": {"coordinates":[-4.62939708900035,55.62491414730827],"type":"Point"}
}