{
  "type": "Feature",
  "properties": {
    "iso:country":"GB",
    "wof:name":"PO37 6PL",
    "wof:placetype":"postalcode"
},
  "geometry": {"coordinates":[-1.18157438147182,50.62814747194655],"type":"Point"}
}