{
  "type": "Feature",
  "properties": {
    "iso:country": "GB",
    "wof:name": "BA21 5AX",
    "wof:placetype": "postalcode"
  },
  "geometry": {"coordinates":[-2.614587,50.947109],"type":"Point"}
}
