{
  "type": "Feature",
  "properties": {
    "date:inception_lower":"1981-06-01",
    "date:inception_upper":"1981-06-30",
    "iso:country":"GB",
    "wof:name":"BA21 5AX",
    "wof:placetype":"postalcode"
},
  "geometry": {"coordinates":[-2.614587,50.947109],"type":"Point"}
}