{
  "type": "Feature",
  "properties": {
    "iso:country":"GB",
    "wof:name":"SR5 3TX",
    "wof:placetype":"postalcode"
},
  "geometry": {"coordinates":[-1.41370942409139,54.92177708409405],"type":"Point"}
}