{
  "type": "Feature",
  "properties": {
    "date:inception_lower":"1999-12-01",
    "date:inception_upper":"1999-12-31",
    "iso:country":"GB",
    "wof:name":"EX14 9TB",
    "wof:placetype":"postalcode"
},
  "geometry": {"coordinates":[-3.179882,50.789976],"type":"Point"}
}