{
  "type": "Feature",
  "properties": {
    "iso:country": "GB",
    "wof:name": "EX14 9TB",
    "wof:placetype": "postalcode"
  },
  "geometry": {"coordinates":[-3.179882,50.789976],"type":"Point"}
}
