{
  "type": "Feature",
  "properties": {
    "date:inception_lower": "1980-01-01",
    "date:inception_upper": "1980-01-01",
    "iso:country": "GB",
    "wof:name": "SA61 1EH",
    "wof:placetype": "postalcode"
  },
  "geometry": {"coordinates":[-4.979588,51.796303],"type":"Point"}
}
