{
  "type": "Feature",
  "properties": {
    "iso:country":"GB",
    "wof:name":"SA61 1EH",
    "wof:placetype":"postalcode"
},
  "geometry": {"coordinates":[-4.9795876598589,51.79630330717882],"type":"Point"}
}