{
  "type": "Feature",
  "properties": {
    "iso:country": "GB",
    "wof:name": "HU9 2RL",
    "wof:placetype": "postalcode"
  },
  "geometry": {"coordinates":[-0.305319,53.7519],"type":"Point"}
}
