{
  "type": "Feature",
  "properties": {
    "iso:country":"GB",
    "wof:name":"DY5 3NN",
    "wof:placetype":"postalcode"
},
  "geometry": {"coordinates":[-2.14185196409647,52.47986790909248],"type":"Point"}
}