{
  "type": "Feature",
  "properties": {
    "iso:country": "GB",
    "wof:name": "BS37 4HX",
    "wof:placetype": "postalcode"
  },
  "geometry": {"coordinates":[-2.423337,51.534457],"type":"Point"}
}
