{
  "type": "Feature",
  "properties": {
    "iso:country":"GB",
    "wof:name":"BS37 4HX",
    "wof:placetype":"postalcode"
},
  "geometry": {"coordinates":[-2.42333734964433,51.53445666330546],"type":"Point"}
}