{
  "type": "Feature",
  "properties": {
    "iso:country":"GB",
    "wof:name":"L18 2EE",
    "wof:placetype":"postalcode"
},
  "geometry": {"coordinates":[-2.90676882385177,53.3875158624124],"type":"Point"}
}