{
  "type": "Feature",
  "properties": {
    "iso:country":"GB",
    "wof:name":"CH65 6QE",
    "wof:placetype":"postalcode"
},
  "geometry": {"coordinates":[-2.90561680772046,53.26232593221152],"type":"Point"}
}