{
  "type": "Feature",
  "properties": {
    "iso:country": "GB",
    "wof:name": "NE40 4BJ",
    "wof:placetype": "postalcode"
  },
  "geometry": {"coordinates":[-1.790334,54.950346],"type":"Point"}
}
