{
  "type": "Feature",
  "properties": {
    "iso:country":"GB",
    "wof:name":"NE40 4BJ",
    "wof:placetype":"postalcode"
},
  "geometry": {"coordinates":[-1.79033423829867,54.95034561139843],"type":"Point"}
}