{
  "type": "Feature",
  "properties": {
    "iso:country":"GB",
    "wof:name":"TS6 9RD",
    "wof:placetype":"postalcode"
},
  "geometry": {"coordinates":[-1.15141065699387,54.56988558673921],"type":"Point"}
}