{
  "type": "Feature",
  "properties": {
    "iso:country":"GB",
    "wof:name":"CW8 2XD",
    "wof:placetype":"postalcode"
},
  "geometry": {"coordinates":[-2.62249915003082,53.24390669387325],"type":"Point"}
}