{
  "type": "Feature",
  "properties": {
    "date:inception_lower": "2020-08-01",
    "date:inception_upper": "2020-08-01",
    "iso:country": "GB",
    "wof:name": "PR3 0EU",
    "wof:placetype": "postalcode"
  },
  "geometry": {"coordinates":[-2.875131,53.850892],"type":"Point"}
}
