{
  "type": "Feature",
  "properties": {
    "iso:country":"GB",
    "wof:name":"SG1 3NX",
    "wof:placetype":"postalcode"
},
  "geometry": {"coordinates":[-0.20741566203724,51.91079030956007],"type":"Point"}
}