{
  "type": "Feature",
  "properties": {
    "iso:country": "GB",
    "wof:name": "CF39 9TH",
    "wof:placetype": "postalcode"
  },
  "geometry": {"coordinates":[-3.401493,51.611443],"type":"Point"}
}
