{
  "type": "Feature",
  "properties": {
    "date:inception_lower":"1997-12-01",
    "date:inception_upper":"1997-12-31",
    "iso:country":"GB",
    "wof:name":"NN10 8NA",
    "wof:placetype":"postalcode"
},
  "geometry": {"coordinates":[-0.594605,52.31445],"type":"Point"}
}