{
  "type": "Feature",
  "properties": {
    "iso:country": "GB",
    "wof:name": "EX39 3DJ",
    "wof:placetype": "postalcode"
  },
  "geometry": {"coordinates":[-4.216588,51.012915],"type":"Point"}
}
