{
  "type": "Feature",
  "properties": {
    "iso:country": "GB",
    "wof:name": "SO21 1AB",
    "wof:placetype": "postalcode"
  },
  "geometry": {"coordinates":[-1.287976,51.101536],"type":"Point"}
}
