{
  "type": "Feature",
  "properties": {
    "iso:country":"GB",
    "wof:name":"SO21 1AB",
    "wof:placetype":"postalcode"
},
  "geometry": {"coordinates":[-1.29354950638565,51.10315774274093],"type":"Point"}
}