{
  "type": "Feature",
  "properties": {
    "date:inception_lower": "2003-11-01",
    "date:inception_upper": "2003-11-01",
    "iso:country": "GB",
    "wof:name": "LN5 8GB",
    "wof:placetype": "postalcode"
  },
  "geometry": {"coordinates":[-0.552759,53.201664],"type":"Point"}
}
