{
  "type": "Feature",
  "properties": {
    "iso:country":"GB",
    "wof:name":"LN5 8GB",
    "wof:placetype":"postalcode"
},
  "geometry": {"coordinates":[-0.55275922981363,53.20166439814034],"type":"Point"}
}