{
  "type": "Feature",
  "properties": {
    "iso:country": "GB",
    "wof:name": "SN12 7QA",
    "wof:placetype": "postalcode"
  },
  "geometry": {"coordinates":[-2.126308,51.401332],"type":"Point"}
}
