{
  "type": "Feature",
  "properties": {
    "iso:country":"GB",
    "wof:name":"LN4 1EG",
    "wof:placetype":"postalcode"
},
  "geometry": {"coordinates":[-0.48834340199016,53.22315915035876],"type":"Point"}
}