{
  "type": "Feature",
  "properties": {
    "iso:country":"GB",
    "wof:name":"HX7 8RW",
    "wof:placetype":"postalcode"
},
  "geometry": {"coordinates":[-2.00267731910211,53.75138286061033],"type":"Point"}
}