{
  "type": "Feature",
  "properties": {
    "iso:country": "GB",
    "wof:name": "HX7 8RW",
    "wof:placetype": "postalcode"
  },
  "geometry": {"coordinates":[-2.002677,53.751383],"type":"Point"}
}
