{
  "type": "Feature",
  "properties": {
    "iso:country":"GB",
    "wof:name":"CM20 2LR",
    "wof:placetype":"postalcode"
},
  "geometry": {"coordinates":[0.11823941240503,51.77979120979904],"type":"Point"}
}