{
  "type": "Feature",
  "properties": {
    "iso:country":"GB",
    "wof:name":"OL2 5BA",
    "wof:placetype":"postalcode"
},
  "geometry": {"coordinates":[-2.12334677658447,53.55543077796241],"type":"Point"}
}