{
  "type": "Feature",
  "properties": {
    "iso:country": "GB",
    "wof:name": "CT1 1XH",
    "wof:placetype": "postalcode"
  },
  "geometry": {"coordinates":[1.108248,51.279139],"type":"Point"}
}
