{
  "type": "Feature",
  "properties": {
    "iso:country":"GB",
    "wof:name":"TR11 3HN",
    "wof:placetype":"postalcode"
},
  "geometry": {"coordinates":[-5.06783747927679,50.15147382198271],"type":"Point"}
}