{
  "type": "Feature",
  "properties": {
    "iso:country":"GB",
    "wof:name":"IG11 9DJ",
    "wof:placetype":"postalcode"
},
  "geometry": {"coordinates":[0.09782093635919,51.54802255688566],"type":"Point"}
}