{
  "type": "Feature",
  "properties": {
    "date:inception_lower": "1980-01-01",
    "date:inception_upper": "1980-01-01",
    "iso:country": "GB",
    "wof:name": "TS26 0JU",
    "wof:placetype": "postalcode"
  },
  "geometry": {"coordinates":[-1.237748,54.691892],"type":"Point"}
}
