{
  "type": "Feature",
  "properties": {
    "iso:country": "GB",
    "wof:name": "TS26 0JU",
    "wof:placetype": "postalcode"
  },
  "geometry": {"coordinates":[-1.237748,54.691892],"type":"Point"}
}
