{
  "type": "Feature",
  "properties": {
    "iso:country":"GB",
    "wof:name":"NG12 3LB",
    "wof:placetype":"postalcode"
},
  "geometry": {"coordinates":[-1.03244380177275,52.9095223670594],"type":"Point"}
}