{
  "type": "Feature",
  "properties": {
    "date:inception_lower": "1980-01-01",
    "date:inception_upper": "1980-01-01",
    "iso:country": "GB",
    "wof:name": "EH6 6LU",
    "wof:placetype": "postalcode"
  },
  "geometry": {"coordinates":[-3.171904,55.977168],"type":"Point"}
}
