{
  "type": "Feature",
  "properties": {
    "iso:country":"GB",
    "wof:name":"HU10 6PL",
    "wof:placetype":"postalcode"
},
  "geometry": {"coordinates":[-0.43006307129947,53.75039861182822],"type":"Point"}
}