{
  "type": "Feature",
  "properties": {
    "iso:country": "GB",
    "wof:name": "HU10 6PL",
    "wof:placetype": "postalcode"
  },
  "geometry": {"coordinates":[-0.430063,53.750399],"type":"Point"}
}
