{
  "type": "Feature",
  "properties": {
    "iso:country":"GB",
    "wof:name":"DL13 2PY",
    "wof:placetype":"postalcode"
},
  "geometry": {"coordinates":[-2.00815557493793,54.74966211823212],"type":"Point"}
}