{
  "type": "Feature",
  "properties": {
    "date:inception_lower": "1980-01-01",
    "date:inception_upper": "1980-01-01",
    "iso:country": "GB",
    "wof:name": "DL13 2PY",
    "wof:placetype": "postalcode"
  },
  "geometry": {"coordinates":[-2.008156,54.749662],"type":"Point"}
}
