{
  "type": "Feature",
  "properties": {
    "iso:country": "GB",
    "wof:name": "PO30 2GR",
    "wof:placetype": "postalcode"
  },
  "geometry": {"coordinates":[-1.276776,50.697939],"type":"Point"}
}
