{
  "type": "Feature",
  "properties": {
    "iso:country": "GB",
    "wof:name": "ST7 3RY",
    "wof:placetype": "postalcode"
  },
  "geometry": {"coordinates":[-2.290055,53.113303],"type":"Point"}
}
