{
  "type": "Feature",
  "properties": {
    "iso:country": "GB",
    "wof:name": "S60 3NR",
    "wof:placetype": "postalcode"
  },
  "geometry": {"coordinates":[-1.323889,53.416176],"type":"Point"}
}
