{
  "type": "Feature",
  "properties": {
    "iso:country":"GB",
    "wof:name":"S66 3YZ",
    "wof:placetype":"postalcode"
},
  "geometry": {"coordinates":[-1.28010947985723,53.43555195596364],"type":"Point"}
}