{
  "type": "Feature",
  "properties": {
    "iso:country": "GB",
    "wof:name": "S66 3YZ",
    "wof:placetype": "postalcode"
  },
  "geometry": {"coordinates":[-1.280109,53.435552],"type":"Point"}
}
