{
  "type": "Feature",
  "properties": {
    "date:inception_lower":"2004-01-01",
    "date:inception_upper":"2004-01-31",
    "iso:country":"GB",
    "wof:name":"S66 3YZ",
    "wof:placetype":"postalcode"
},
  "geometry": {"coordinates":[-1.280109,53.435552],"type":"Point"}
}