{
  "type": "Feature",
  "properties": {
    "iso:country":"GB",
    "wof:name":"CM6 3RP",
    "wof:placetype":"postalcode"
},
  "geometry": {"coordinates":[0.40346916259796,51.90163332497131],"type":"Point"}
}