{
  "type": "Feature",
  "properties": {
    "iso:country": "GB",
    "wof:name": "CM6 3RP",
    "wof:placetype": "postalcode"
  },
  "geometry": {"coordinates":[0.403215,51.90153],"type":"Point"}
}
