{
  "type": "Feature",
  "properties": {
    "iso:country": "GB",
    "wof:name": "CH62 9BD",
    "wof:placetype": "postalcode"
  },
  "geometry": {"coordinates":[-2.969991,53.306621],"type":"Point"}
}
