{
  "type": "Feature",
  "properties": {
    "date:inception_lower": "1999-06-01",
    "date:inception_upper": "1999-06-01",
    "iso:country": "GB",
    "wof:name": "CH62 9BD",
    "wof:placetype": "postalcode"
  },
  "geometry": {"coordinates":[-2.969991,53.306621],"type":"Point"}
}
