{
  "type": "Feature",
  "properties": {
    "iso:country":"GB",
    "wof:name":"CH62 9BD",
    "wof:placetype":"postalcode"
},
  "geometry": {"coordinates":[-2.96999081741765,53.30662112712552],"type":"Point"}
}