{
  "type": "Feature",
  "properties": {
    "iso:country": "GB",
    "wof:name": "CM4 0JY",
    "wof:placetype": "postalcode"
  },
  "geometry": {"coordinates":[0.295815,51.693678],"type":"Point"}
}
