{
  "type": "Feature",
  "properties": {
    "iso:country":"GB",
    "wof:name":"DA15 7BG",
    "wof:placetype":"postalcode"
},
  "geometry": {"coordinates":[0.10159468132457,51.4317046537095],"type":"Point"}
}