{
  "type": "Feature",
  "properties": {
    "date:inception_lower": "1980-01-01",
    "date:inception_upper": "1980-01-01",
    "iso:country": "GB",
    "wof:name": "LL54 5LR",
    "wof:placetype": "postalcode"
  },
  "geometry": {"coordinates":[-4.427994,52.993288],"type":"Point"}
}
