{
  "type": "Feature",
  "properties": {
    "iso:country":"GB",
    "wof:name":"LL54 5LR",
    "wof:placetype":"postalcode"
},
  "geometry": {"coordinates":[-4.42799366931096,52.99328788084457],"type":"Point"}
}