{
  "type": "Feature",
  "properties": {
    "iso:country":"GB",
    "wof:name":"SA62 4LH",
    "wof:placetype":"postalcode"
},
  "geometry": {"coordinates":[-4.94191443245391,51.76461425724686],"type":"Point"}
}