{
  "type": "Feature",
  "properties": {
    "iso:country": "GB",
    "wof:name": "SA62 4LH",
    "wof:placetype": "postalcode"
  },
  "geometry": {"coordinates":[-4.941917,51.764601],"type":"Point"}
}
