{
  "type": "Feature",
  "properties": {
    "date:inception_lower": "1980-01-01",
    "date:inception_upper": "1980-01-01",
    "iso:country": "GB",
    "wof:name": "CA16 6QZ",
    "wof:placetype": "postalcode"
  },
  "geometry": {"coordinates":[-2.49271,54.576114],"type":"Point"}
}
