{
  "type": "Feature",
  "properties": {
    "iso:country": "GB",
    "wof:name": "CA16 6QZ",
    "wof:placetype": "postalcode"
  },
  "geometry": {"coordinates":[-2.492602,54.576105],"type":"Point"}
}
