{
  "type": "Feature",
  "properties": {
    "date:inception_lower": "1980-01-01",
    "date:inception_upper": "1980-01-01",
    "iso:country": "GB",
    "wof:name": "NE49 0HZ",
    "wof:placetype": "postalcode"
  },
  "geometry": {"coordinates":[-2.470465,54.961546],"type":"Point"}
}
