{
  "type": "Feature",
  "properties": {
    "iso:country": "GB",
    "wof:name": "SY11 3EW",
    "wof:placetype": "postalcode"
  },
  "geometry": {"coordinates":[-3.048637,52.914008],"type":"Point"}
}
