{
  "type": "Feature",
  "properties": {
    "iso:country":"GB",
    "wof:name":"SY11 3EW",
    "wof:placetype":"postalcode"
},
  "geometry": {"coordinates":[-3.04863743828762,52.91400793072422],"type":"Point"}
}