{
  "type": "Feature",
  "properties": {
    "date:inception_lower": "2017-06-01",
    "date:inception_upper": "2017-06-01",
    "iso:country": "GB",
    "wof:name": "RG14 9NL",
    "wof:placetype": "postalcode"
  },
  "geometry": {"coordinates":[-1.322045,51.40007],"type":"Point"}
}
