{
  "type": "Feature",
  "properties": {
    "iso:country": "GB",
    "wof:name": "BD13 2PQ",
    "wof:placetype": "postalcode"
  },
  "geometry": {"coordinates":[-1.84578,53.76802],"type":"Point"}
}
