{
  "type": "Feature",
  "properties": {
    "iso:country":"GB",
    "wof:name":"SW1V 4EU",
    "wof:placetype":"postalcode"
},
  "geometry": {"coordinates":[-0.14565711630574,51.49020139012553],"type":"Point"}
}