{
  "type": "Feature",
  "properties": {
    "iso:country":"GB",
    "wof:name":"BH20 4BB",
    "wof:placetype":"postalcode"
},
  "geometry": {"coordinates":[-2.12113715254125,50.69332142471596],"type":"Point"}
}