{
  "type": "Feature",
  "properties": {
    "date:inception_lower":"1980-01-01",
    "date:inception_upper":"1980-01-31",
    "iso:country":"GB",
    "wof:name":"SL3 8NA",
    "wof:placetype":"postalcode"
},
  "geometry": {"coordinates":[-0.551883,51.496343],"type":"Point"}
}