{
  "type": "Feature",
  "properties": {
    "iso:country":"GB",
    "wof:name":"SL3 8NA",
    "wof:placetype":"postalcode"
},
  "geometry": {"coordinates":[-0.55188296255924,51.49634345439618],"type":"Point"}
}