{
  "type": "Feature",
  "properties": {
    "date:inception_lower": "1980-01-01",
    "date:inception_upper": "1980-01-01",
    "iso:country": "GB",
    "wof:name": "DT2 0LN",
    "wof:placetype": "postalcode"
  },
  "geometry": {"coordinates":[-2.587067,50.847254],"type":"Point"}
}
