{
  "type": "Feature",
  "properties": {
    "iso:country":"GB",
    "wof:name":"DT2 0LN",
    "wof:placetype":"postalcode"
},
  "geometry": {"coordinates":[-2.58722217747708,50.84723500714715],"type":"Point"}
}