{
  "type": "Feature",
  "properties": {
    "iso:country":"GB",
    "wof:name":"BS16 6SQ",
    "wof:placetype":"postalcode"
},
  "geometry": {"coordinates":[-2.4940751656502,51.50318621763277],"type":"Point"}
}