{
  "type": "Feature",
  "properties": {
    "date:inception_lower": "2017-08-01",
    "date:inception_upper": "2017-08-01",
    "iso:country": "GB",
    "wof:name": "L25 4AF",
    "wof:placetype": "postalcode"
  },
  "geometry": {"coordinates":[-2.869524,53.386766],"type":"Point"}
}
