{
  "type": "Feature",
  "properties": {
    "iso:country":"GB",
    "wof:name":"CT11 8NB",
    "wof:placetype":"postalcode"
},
  "geometry": {"coordinates":[1.42882417116668,51.33594000681999],"type":"Point"}
}