{
  "type": "Feature",
  "properties": {
    "iso:country": "GB",
    "wof:name": "CT11 8NB",
    "wof:placetype": "postalcode"
  },
  "geometry": {"coordinates":[1.428824,51.33594],"type":"Point"}
}
