{
  "type": "Feature",
  "properties": {
    "iso:country":"GB",
    "wof:name":"TS10 2JQ",
    "wof:placetype":"postalcode"
},
  "geometry": {"coordinates":[-1.05987831526177,54.60255169778018],"type":"Point"}
}