{
  "type": "Feature",
  "properties": {
    "iso:country":"GB",
    "wof:name":"LA2 0ES",
    "wof:placetype":"postalcode"
},
  "geometry": {"coordinates":[-2.83031487842306,53.93647496201022],"type":"Point"}
}