{
  "type": "Feature",
  "properties": {
    "iso:country": "GB",
    "wof:name": "AB21 0BX",
    "wof:placetype": "postalcode"
  },
  "geometry": {"coordinates":[-2.212963,57.196114],"type":"Point"}
}
