{
  "type": "Feature",
  "properties": {
    "iso:country":"GB",
    "wof:name":"N7 8DA",
    "wof:placetype":"postalcode"
},
  "geometry": {"coordinates":[-0.11187568428627,51.55263701049514],"type":"Point"}
}