{
  "type": "Feature",
  "properties": {
    "date:inception_lower": "1980-01-01",
    "date:inception_upper": "1980-01-01",
    "iso:country": "GB",
    "wof:name": "N7 8DA",
    "wof:placetype": "postalcode"
  },
  "geometry": {"coordinates":[-0.111876,51.552637],"type":"Point"}
}
