{
  "type": "Feature",
  "properties": {
    "date:inception_lower": "1996-12-01",
    "date:inception_upper": "1996-12-01",
    "iso:country": "GB",
    "wof:name": "TN4 9XT",
    "wof:placetype": "postalcode"
  },
  "geometry": {"coordinates":[0.281752,51.15581],"type":"Point"}
}
