{
  "type": "Feature",
  "properties": {
    "date:inception_lower": "1980-01-01",
    "date:inception_upper": "1980-01-01",
    "iso:country": "GB",
    "wof:name": "SN15 2LD",
    "wof:placetype": "postalcode"
  },
  "geometry": {"coordinates":[-2.120559,51.41809],"type":"Point"}
}
