{
  "type": "Feature",
  "properties": {
    "iso:country": "GB",
    "wof:name": "SN15 2LD",
    "wof:placetype": "postalcode"
  },
  "geometry": {"coordinates":[-2.120559,51.41809],"type":"Point"}
}
