{
  "type": "Feature",
  "properties": {
    "iso:country":"GB",
    "wof:name":"EH10 6NS",
    "wof:placetype":"postalcode"
},
  "geometry": {"coordinates":[-3.21308549407586,55.91047423341872],"type":"Point"}
}