{
  "type": "Feature",
  "properties": {
    "date:inception_lower":"1983-01-01",
    "date:inception_upper":"1983-01-31",
    "iso:country":"GB",
    "wof:name":"BH8 9RU",
    "wof:placetype":"postalcode"
},
  "geometry": {"coordinates":[-1.863018,50.740813],"type":"Point"}
}