{
  "type": "Feature",
  "properties": {
    "iso:country": "GB",
    "wof:name": "NR6 5RQ",
    "wof:placetype": "postalcode"
  },
  "geometry": {"coordinates":[1.254205,52.667561],"type":"Point"}
}
