{
  "type": "Feature",
  "properties": {
    "iso:country":"GB",
    "wof:name":"NR6 5RQ",
    "wof:placetype":"postalcode"
},
  "geometry": {"coordinates":[1.25420484558849,52.66756106860581],"type":"Point"}
}