{
  "type": "Feature",
  "properties": {
    "date:inception_lower": "1985-04-01",
    "date:inception_upper": "1985-04-01",
    "iso:country": "GB",
    "wof:name": "TS17 0SF",
    "wof:placetype": "postalcode"
  },
  "geometry": {"coordinates":[-1.307146,54.526598],"type":"Point"}
}
