{
  "type": "Feature",
  "properties": {
    "iso:country": "GB",
    "wof:name": "GU15 9ZT",
    "wof:placetype": "postalcode"
  },
  "geometry": {"coordinates":[-0.766641,51.330863],"type":"Point"}
}
