{
  "type": "Feature",
  "properties": {
    "date:inception_lower":"2016-03-01",
    "date:inception_upper":"2016-03-31",
    "iso:country":"GB",
    "wof:name":"GU15 9ZT",
    "wof:placetype":"postalcode"
},
  "geometry": {"coordinates":[-0.766641,51.330863],"type":"Point"}
}