{
  "type": "Feature",
  "properties": {
    "iso:country":"GB",
    "wof:name":"SO23 0PF",
    "wof:placetype":"postalcode"
},
  "geometry": {"coordinates":[-1.30249457352297,51.06299809274928],"type":"Point"}
}