{
  "type": "Feature",
  "properties": {
    "date:inception_lower": "1999-06-01",
    "date:inception_upper": "1999-06-01",
    "iso:country": "GB",
    "wof:name": "TS1 1EG",
    "wof:placetype": "postalcode"
  },
  "geometry": {"coordinates":[-1.234921,54.578944],"type":"Point"}
}
