{
  "type": "Feature",
  "properties": {
    "iso:country":"GB",
    "wof:name":"WA7 6DQ",
    "wof:placetype":"postalcode"
},
  "geometry": {"coordinates":[-2.66550523722137,53.32004404262484],"type":"Point"}
}