{
  "type": "Feature",
  "properties": {
    "iso:country": "GB",
    "wof:name": "WA7 6DQ",
    "wof:placetype": "postalcode"
  },
  "geometry": {"coordinates":[-2.665505,53.320044],"type":"Point"}
}
