{
  "type": "Feature",
  "properties": {
    "date:inception_lower": "1980-01-01",
    "date:inception_upper": "1980-01-01",
    "iso:country": "GB",
    "wof:name": "SE26 4NY",
    "wof:placetype": "postalcode"
  },
  "geometry": {"coordinates":[-0.050351,51.4288],"type":"Point"}
}
