{
  "type": "Feature",
  "properties": {
    "date:inception_lower": "1981-06-01",
    "date:inception_upper": "1981-06-01",
    "iso:country": "GB",
    "wof:name": "SE8 4RS",
    "wof:placetype": "postalcode"
  },
  "geometry": {"coordinates":[-0.024359,51.47608],"type":"Point"}
}
