{
  "type": "Feature",
  "properties": {
    "iso:country":"GB",
    "wof:name":"SL6 6DP",
    "wof:placetype":"postalcode"
},
  "geometry": {"coordinates":[-0.74136883238927,51.52335643745953],"type":"Point"}
}