{
  "type": "Feature",
  "properties": {
    "iso:country":"GB",
    "wof:name":"PO36 8EP",
    "wof:placetype":"postalcode"
},
  "geometry": {"coordinates":[-1.15300765040986,50.65530902838398],"type":"Point"}
}