{
  "type": "Feature",
  "properties": {
    "date:inception_lower":"1990-02-01",
    "date:inception_upper":"1990-02-28",
    "iso:country":"GB",
    "wof:name":"PO36 8EP",
    "wof:placetype":"postalcode"
},
  "geometry": {"coordinates":[-1.153008,50.655309],"type":"Point"}
}