{
  "type": "Feature",
  "properties": {
    "iso:country":"GB",
    "wof:name":"W2 5RT",
    "wof:placetype":"postalcode"
},
  "geometry": {"coordinates":[-0.19334958854353,51.5153783611667],"type":"Point"}
}