{
  "type": "Feature",
  "properties": {
    "date:inception_lower": "2005-06-01",
    "date:inception_upper": "2005-06-01",
    "iso:country": "GB",
    "wof:name": "TN23 5DW",
    "wof:placetype": "postalcode"
  },
  "geometry": {"coordinates":[0.859921,51.135316],"type":"Point"}
}
