{
  "type": "Feature",
  "properties": {
    "iso:country":"GB",
    "wof:name":"NP44 8RT",
    "wof:placetype":"postalcode"
},
  "geometry": {"coordinates":[-3.00434112162204,51.64968190418164],"type":"Point"}
}