{
  "type": "Feature",
  "properties": {
    "date:inception_lower": "2023-07-01",
    "date:inception_upper": "2023-07-01",
    "iso:country": "GB",
    "wof:name": "TA21 1DF",
    "wof:placetype": "postalcode"
  },
  "geometry": {"coordinates":[-3.227414,50.978986],"type":"Point"}
}
