{
  "type": "Feature",
  "properties": {
    "date:inception_lower":"1984-10-01",
    "date:inception_upper":"1984-10-31",
    "iso:country":"GB",
    "wof:name":"HR2 6PD",
    "wof:placetype":"postalcode"
},
  "geometry": {"coordinates":[-2.698494,52.024563],"type":"Point"}
}