{
  "type": "Feature",
  "properties": {
    "iso:country":"GB",
    "wof:name":"SN4 9QG",
    "wof:placetype":"postalcode"
},
  "geometry": {"coordinates":[-1.85516613678804,51.4737565312282],"type":"Point"}
}