{
  "type": "Feature",
  "properties": {
    "date:inception_lower": "1997-12-01",
    "date:inception_upper": "1997-12-01",
    "iso:country": "GB",
    "wof:name": "SN4 9QG",
    "wof:placetype": "postalcode"
  },
  "geometry": {"coordinates":[-1.855166,51.473757],"type":"Point"}
}
