{
  "type": "Feature",
  "properties": {
    "iso:country":"GB",
    "wof:name":"EC3A 2DB",
    "wof:placetype":"postalcode"
},
  "geometry": {"coordinates":[-0.07829885816873,51.51318106980989],"type":"Point"}
}