{
  "type": "Feature",
  "properties": {
    "iso:country":"GB",
    "wof:name":"NE2 4DX",
    "wof:placetype":"postalcode"
},
  "geometry": {"coordinates":[-1.60737481357535,54.98301630427213],"type":"Point"}
}