{
  "type": "Feature",
  "properties": {
    "iso:country": "GB",
    "wof:name": "GU51 3DE",
    "wof:placetype": "postalcode"
  },
  "geometry": {"coordinates":[-0.822511,51.28466],"type":"Point"}
}
