{
  "type": "Feature",
  "properties": {
    "iso:country":"GB",
    "wof:name":"GU51 3DE",
    "wof:placetype":"postalcode"
},
  "geometry": {"coordinates":[-0.82251143638631,51.28466011899415],"type":"Point"}
}