{
  "type": "Feature",
  "properties": {
    "iso:country":"GB",
    "wof:name":"HP23 5LT",
    "wof:placetype":"postalcode"
},
  "geometry": {"coordinates":[-0.65908984650968,51.80409435991679],"type":"Point"}
}