{
  "type": "Feature",
  "properties": {
    "date:inception_lower":"1994-05-01",
    "date:inception_upper":"1994-05-31",
    "iso:country":"GB",
    "wof:name":"HP23 5LT",
    "wof:placetype":"postalcode"
},
  "geometry": {"coordinates":[-0.65909,51.804094],"type":"Point"}
}