{
  "type": "Feature",
  "properties": {
    "date:inception_lower": "1994-05-01",
    "date:inception_upper": "1994-05-01",
    "iso:country": "GB",
    "wof:name": "HP23 5LT",
    "wof:placetype": "postalcode"
  },
  "geometry": {"coordinates":[-0.658993,51.804092],"type":"Point"}
}
