{
  "type": "Feature",
  "properties": {
    "iso:country":"GB",
    "wof:name":"YO61 4TJ",
    "wof:placetype":"postalcode"
},
  "geometry": {"coordinates":[-1.16135308649538,54.12486107623688],"type":"Point"}
}