{
  "type": "Feature",
  "properties": {
    "iso:country": "GB",
    "wof:name": "NW8 9LU",
    "wof:placetype": "postalcode"
  },
  "geometry": {"coordinates":[-0.177019,51.533102],"type":"Point"}
}
