{
  "type": "Feature",
  "properties": {
    "iso:country": "GB",
    "wof:name": "SN10 2DF",
    "wof:placetype": "postalcode"
  },
  "geometry": {"coordinates":[-1.999003,51.35914],"type":"Point"}
}
