{
  "type": "Feature",
  "properties": {
    "iso:country":"GB",
    "wof:name":"SW8 2PL",
    "wof:placetype":"postalcode"
},
  "geometry": {"coordinates":[-0.12937465716063,51.47378314809025],"type":"Point"}
}