{
  "type": "Feature",
  "properties": {
    "iso:country": "GB",
    "wof:name": "NG32 3QN",
    "wof:placetype": "postalcode"
  },
  "geometry": {"coordinates":[-0.533057,52.98809],"type":"Point"}
}
