{
  "type": "Feature",
  "properties": {
    "iso:country":"GB",
    "wof:name":"SA1 6LJ",
    "wof:placetype":"postalcode"
},
  "geometry": {"coordinates":[-3.9697926536669,51.62884594837985],"type":"Point"}
}