{
  "type": "Feature",
  "properties": {
    "iso:country": "GB",
    "wof:name": "PO8 9ND",
    "wof:placetype": "postalcode"
  },
  "geometry": {"coordinates":[-1.005749,50.913886],"type":"Point"}
}
