{
  "type": "Feature",
  "properties": {
    "iso:country":"GB",
    "wof:name":"PO8 9ND",
    "wof:placetype":"postalcode"
},
  "geometry": {"coordinates":[-1.00574871543489,50.91388628383051],"type":"Point"}
}