{
  "type": "Feature",
  "properties": {
    "date:inception_lower": "1980-01-01",
    "date:inception_upper": "1980-01-01",
    "iso:country": "GB",
    "wof:name": "L20 4AH",
    "wof:placetype": "postalcode"
  },
  "geometry": {"coordinates":[-2.997882,53.449019],"type":"Point"}
}
