{
  "type": "Feature",
  "properties": {
    "iso:country": "GB",
    "wof:name": "DY7 6LL",
    "wof:placetype": "postalcode"
  },
  "geometry": {"coordinates":[-2.223969,52.451072],"type":"Point"}
}
