{
  "type": "Feature",
  "properties": {
    "iso:country":"GB",
    "wof:name":"DY7 6LL",
    "wof:placetype":"postalcode"
},
  "geometry": {"coordinates":[-2.22396899860068,52.45107167397755],"type":"Point"}
}