{
  "type": "Feature",
  "properties": {
    "date:inception_lower":"1980-01-01",
    "date:inception_upper":"1980-01-31",
    "iso:country":"GB",
    "wof:name":"DY7 6LL",
    "wof:placetype":"postalcode"
},
  "geometry": {"coordinates":[-2.223969,52.451072],"type":"Point"}
}