{
  "type": "Feature",
  "properties": {
    "iso:country":"GB",
    "wof:name":"HA7 4RE",
    "wof:placetype":"postalcode"
},
  "geometry": {"coordinates":[-0.2973166793027,51.61708940647458],"type":"Point"}
}