{
  "type": "Feature",
  "properties": {
    "iso:country":"GB",
    "wof:name":"EH28 8RW",
    "wof:placetype":"postalcode"
},
  "geometry": {"coordinates":[-3.38555698152364,55.92115341937487],"type":"Point"}
}