{
  "type": "Feature",
  "properties": {
    "iso:country": "GB",
    "wof:name": "AB43 7LL",
    "wof:placetype": "postalcode"
  },
  "geometry": {"coordinates":[-2.152622,57.667112],"type":"Point"}
}
