{
  "type": "Feature",
  "properties": {
    "iso:country":"GB",
    "wof:name":"BL2 5JE",
    "wof:placetype":"postalcode"
},
  "geometry": {"coordinates":[-2.383662984175,53.59102966021175],"type":"Point"}
}