{
  "type": "Feature",
  "properties": {
    "date:inception_lower": "1980-01-01",
    "date:inception_upper": "1980-01-01",
    "iso:country": "GB",
    "wof:name": "NN10 9EX",
    "wof:placetype": "postalcode"
  },
  "geometry": {"coordinates":[-0.600517,52.280489],"type":"Point"}
}
