{
  "type": "Feature",
  "properties": {
    "iso:country": "GB",
    "wof:name": "BL6 5EG",
    "wof:placetype": "postalcode"
  },
  "geometry": {"coordinates":[-2.584466,53.593713],"type":"Point"}
}
