{
  "type": "Feature",
  "properties": {
    "iso:country":"GB",
    "wof:name":"ST15 0PG",
    "wof:placetype":"postalcode"
},
  "geometry": {"coordinates":[-2.22931368214679,52.91717555557332],"type":"Point"}
}