{
  "type": "Feature",
  "properties": {
    "iso:country":"GB",
    "wof:name":"SA33 6UD",
    "wof:placetype":"postalcode"
},
  "geometry": {"coordinates":[-4.41824583105459,51.94352248030374],"type":"Point"}
}