{
  "type": "Feature",
  "properties": {
    "iso:country":"GB",
    "wof:name":"YO10 5ZB",
    "wof:placetype":"postalcode"
},
  "geometry": {"coordinates":[-1.0446820734271,53.944843409163],"type":"Point"}
}