{
  "type": "Feature",
  "properties": {
    "date:inception_lower":"1980-01-01",
    "date:inception_upper":"1980-01-31",
    "iso:country":"GB",
    "wof:name":"G69 6LA",
    "wof:placetype":"postalcode"
},
  "geometry": {"coordinates":[-4.117978,55.851517],"type":"Point"}
}