{
  "type": "Feature",
  "properties": {
    "iso:country": "GB",
    "wof:name": "BS15 8NA",
    "wof:placetype": "postalcode"
  },
  "geometry": {"coordinates":[-2.509021,51.461006],"type":"Point"}
}
