{
  "type": "Feature",
  "properties": {
    "iso:country":"GB",
    "wof:name":"BS15 8NA",
    "wof:placetype":"postalcode"
},
  "geometry": {"coordinates":[-2.50902091104741,51.46100576176443],"type":"Point"}
}