{
  "type": "Feature",
  "properties": {
    "iso:country":"GB",
    "wof:name":"LS25 7BF",
    "wof:placetype":"postalcode"
},
  "geometry": {"coordinates":[-1.3500898904022,53.77131994148516],"type":"Point"}
}