{
  "type": "Feature",
  "properties": {
    "iso:country": "GB",
    "wof:name": "LS25 7BF",
    "wof:placetype": "postalcode"
  },
  "geometry": {"coordinates":[-1.35009,53.77132],"type":"Point"}
}
