{
  "type": "Feature",
  "properties": {
    "iso:country":"GB",
    "wof:name":"NR13 6NL",
    "wof:placetype":"postalcode"
},
  "geometry": {"coordinates":[1.36572727893686,52.68632531771476],"type":"Point"}
}