{
  "type": "Feature",
  "properties": {
    "iso:country":"GB",
    "wof:name":"CM2 0DY",
    "wof:placetype":"postalcode"
},
  "geometry": {"coordinates":[0.47450695445141,51.72888078252998],"type":"Point"}
}