{
  "type": "Feature",
  "properties": {
    "date:inception_lower":"1980-01-01",
    "date:inception_upper":"1980-01-31",
    "iso:country":"GB",
    "wof:name":"DD8 5JS",
    "wof:placetype":"postalcode"
},
  "geometry": {"coordinates":[-3.161108,56.717408],"type":"Point"}
}