{
  "type": "Feature",
  "properties": {
    "iso:country":"GB",
    "wof:name":"DD8 5JS",
    "wof:placetype":"postalcode"
},
  "geometry": {"coordinates":[-3.16110791611054,56.71740849831594],"type":"Point"}
}