{
  "type": "Feature",
  "properties": {
    "iso:country":"GB",
    "wof:name":"KY5 9EF",
    "wof:placetype":"postalcode"
},
  "geometry": {"coordinates":[-3.310616433481,56.13420273541655],"type":"Point"}
}