{
  "type": "Feature",
  "properties": {
    "date:inception_lower":"1980-01-01",
    "date:inception_upper":"1980-01-31",
    "iso:country":"GB",
    "wof:name":"NR30 4NB",
    "wof:placetype":"postalcode"
},
  "geometry": {"coordinates":[1.730078,52.621367],"type":"Point"}
}