{
  "type": "Feature",
  "properties": {
    "iso:country":"GB",
    "wof:name":"SR4 0QR",
    "wof:placetype":"postalcode"
},
  "geometry": {"coordinates":[-1.44963557114435,54.90617381317079],"type":"Point"}
}