{
  "type": "Feature",
  "properties": {
    "iso:country":"GB",
    "wof:name":"DA6 7DY",
    "wof:placetype":"postalcode"
},
  "geometry": {"coordinates":[0.146586407565,51.45664502757958],"type":"Point"}
}