{
  "type": "Feature",
  "properties": {
    "date:inception_lower": "1980-01-01",
    "date:inception_upper": "1980-01-01",
    "iso:country": "GB",
    "wof:name": "RG9 4EF",
    "wof:placetype": "postalcode"
  },
  "geometry": {"coordinates":[-0.925729,51.50219],"type":"Point"}
}
