{
  "type": "Feature",
  "properties": {
    "iso:country": "GB",
    "wof:name": "HP13 7EB",
    "wof:placetype": "postalcode"
  },
  "geometry": {"coordinates":[-0.716912,51.6209],"type":"Point"}
}
