{
  "type": "Feature",
  "properties": {
    "iso:country":"GB",
    "wof:name":"SA31 2LS",
    "wof:placetype":"postalcode"
},
  "geometry": {"coordinates":[-4.27642342801924,51.83751498409358],"type":"Point"}
}