{
  "type": "Feature",
  "properties": {
    "date:inception_lower": "1980-01-01",
    "date:inception_upper": "1980-01-01",
    "iso:country": "GB",
    "wof:name": "SA31 2LS",
    "wof:placetype": "postalcode"
  },
  "geometry": {"coordinates":[-4.279802,51.834698],"type":"Point"}
}
