{
  "type": "Feature",
  "properties": {
    "iso:country": "GB",
    "wof:name": "TA9 3PW",
    "wof:placetype": "postalcode"
  },
  "geometry": {"coordinates":[-2.939048,51.202644],"type":"Point"}
}
