{
  "type": "Feature",
  "properties": {
    "iso:country":"GB",
    "wof:name":"KT2 5PW",
    "wof:placetype":"postalcode"
},
  "geometry": {"coordinates":[-0.30454143141911,51.4256756333189],"type":"Point"}
}