{
  "type": "Feature",
  "properties": {
    "iso:country":"GB",
    "wof:name":"SE1 2YN",
    "wof:placetype":"postalcode"
},
  "geometry": {"coordinates":[-0.07256982397826,51.5014056805461],"type":"Point"}
}