{
  "type": "Feature",
  "properties": {
    "date:inception_lower": "1987-04-01",
    "date:inception_upper": "1987-04-01",
    "iso:country": "GB",
    "wof:name": "SE1 2YN",
    "wof:placetype": "postalcode"
  },
  "geometry": {"coordinates":[-0.07257,51.501406],"type":"Point"}
}
