{
  "type": "Feature",
  "properties": {
    "iso:country": "GB",
    "wof:name": "TN19 7BJ",
    "wof:placetype": "postalcode"
  },
  "geometry": {"coordinates":[0.390652,50.998996],"type":"Point"}
}
