{
  "type": "Feature",
  "properties": {
    "iso:country":"GB",
    "wof:name":"W1K 3NU",
    "wof:placetype":"postalcode"
},
  "geometry": {"coordinates":[-0.14792019947814,51.51006565275608],"type":"Point"}
}