{
  "type": "Feature",
  "properties": {
    "date:inception_lower": "2022-02-01",
    "date:inception_upper": "2022-02-01",
    "iso:country": "GB",
    "wof:name": "YO51 9RN",
    "wof:placetype": "postalcode"
  },
  "geometry": {"coordinates":[-1.403108,54.101296],"type":"Point"}
}
