{
  "type": "Feature",
  "properties": {
    "iso:country":"GB",
    "wof:name":"SO21 2PA",
    "wof:placetype":"postalcode"
},
  "geometry": {"coordinates":[-1.38326981304403,51.07226439126908],"type":"Point"}
}