{
  "type": "Feature",
  "properties": {
    "iso:country": "GB",
    "wof:name": "SO21 2PA",
    "wof:placetype": "postalcode"
  },
  "geometry": {"coordinates":[-1.38327,51.072264],"type":"Point"}
}
