{
  "type": "Feature",
  "properties": {
    "iso:country":"GB",
    "wof:name":"EX32 7LN",
    "wof:placetype":"postalcode"
},
  "geometry": {"coordinates":[-3.93332629602848,51.09075640327573],"type":"Point"}
}