{
  "type": "Feature",
  "properties": {
    "date:inception_lower": "1980-01-01",
    "date:inception_upper": "1980-01-01",
    "iso:country": "GB",
    "wof:name": "EX32 7LN",
    "wof:placetype": "postalcode"
  },
  "geometry": {"coordinates":[-3.933326,51.090756],"type":"Point"}
}
