{
  "type": "Feature",
  "properties": {
    "iso:country":"GB",
    "wof:name":"RH16 3RN",
    "wof:placetype":"postalcode"
},
  "geometry": {"coordinates":[-0.08065836149599,50.99467823710449],"type":"Point"}
}