{
  "type": "Feature",
  "properties": {
    "date:inception_lower": "1980-01-01",
    "date:inception_upper": "1980-01-01",
    "iso:country": "GB",
    "wof:name": "TS5 4QG",
    "wof:placetype": "postalcode"
  },
  "geometry": {"coordinates":[-1.266454,54.552079],"type":"Point"}
}
