{
  "type": "Feature",
  "properties": {
    "iso:country":"GB",
    "wof:name":"TS5 4QG",
    "wof:placetype":"postalcode"
},
  "geometry": {"coordinates":[-1.26645409270766,54.55207910980094],"type":"Point"}
}