{
  "type": "Feature",
  "properties": {
    "iso:country": "GB",
    "wof:name": "TS5 4QG",
    "wof:placetype": "postalcode"
  },
  "geometry": {"coordinates":[-1.266454,54.552079],"type":"Point"}
}
