{
  "type": "Feature",
  "properties": {
    "iso:country": "GB",
    "wof:name": "W7 3DJ",
    "wof:placetype": "postalcode"
  },
  "geometry": {"coordinates":[-0.346361,51.523903],"type":"Point"}
}
