{
  "type": "Feature",
  "properties": {
    "iso:country": "GB",
    "wof:name": "DN31 1RH",
    "wof:placetype": "postalcode"
  },
  "geometry": {"coordinates":[-0.088151,53.569693],"type":"Point"}
}
