{
  "type": "Feature",
  "properties": {
    "date:inception_lower": "1980-01-01",
    "date:inception_upper": "1980-01-01",
    "iso:country": "GB",
    "wof:name": "S81 9BU",
    "wof:placetype": "postalcode"
  },
  "geometry": {"coordinates":[-1.116083,53.354837],"type":"Point"}
}
