{
  "type": "Feature",
  "properties": {
    "iso:country":"GB",
    "wof:name":"S81 9BU",
    "wof:placetype":"postalcode"
},
  "geometry": {"coordinates":[-1.11608263350618,53.35483672349043],"type":"Point"}
}