{
  "type": "Feature",
  "properties": {
    "iso:country":"GB",
    "wof:name":"TD1 1JP",
    "wof:placetype":"postalcode"
},
  "geometry": {"coordinates":[-2.81892821980236,55.61417259612756],"type":"Point"}
}