{
  "type": "Feature",
  "properties": {
    "date:inception_lower": "1980-01-01",
    "date:inception_upper": "1980-01-01",
    "iso:country": "GB",
    "wof:name": "LE17 4JW",
    "wof:placetype": "postalcode"
  },
  "geometry": {"coordinates":[-1.166936,52.447876],"type":"Point"}
}
