{
  "type": "Feature",
  "properties": {
    "iso:country":"GB",
    "wof:name":"LE17 4JW",
    "wof:placetype":"postalcode"
},
  "geometry": {"coordinates":[-1.16693555485587,52.44787586248895],"type":"Point"}
}