{
  "type": "Feature",
  "properties": {
    "date:inception_lower":"2012-06-01",
    "date:inception_upper":"2012-06-30",
    "iso:country":"GB",
    "wof:name":"OL16 5AP",
    "wof:placetype":"postalcode"
},
  "geometry": {"coordinates":[-2.142272,53.612674],"type":"Point"}
}