{
  "type": "Feature",
  "properties": {
    "iso:country":"GB",
    "wof:name":"WA15 6BL",
    "wof:placetype":"postalcode"
},
  "geometry": {"coordinates":[-2.33150401899999,53.40660780175106],"type":"Point"}
}