{
  "type": "Feature",
  "properties": {
    "iso:country": "GB",
    "wof:name": "WA15 6BL",
    "wof:placetype": "postalcode"
  },
  "geometry": {"coordinates":[-2.331504,53.406608],"type":"Point"}
}
