{
  "type": "Feature",
  "properties": {
    "date:inception_lower": "1980-01-01",
    "date:inception_upper": "1980-01-01",
    "iso:country": "GB",
    "wof:name": "SK8 6SB",
    "wof:placetype": "postalcode"
  },
  "geometry": {"coordinates":[-2.207066,53.370611],"type":"Point"}
}
