{
  "type": "Feature",
  "properties": {
    "iso:country": "GB",
    "wof:name": "GU14 9SX",
    "wof:placetype": "postalcode"
  },
  "geometry": {"coordinates":[-0.790827,51.296477],"type":"Point"}
}
