{
  "type": "Feature",
  "properties": {
    "iso:country": "GB",
    "wof:name": "SN25 6AB",
    "wof:placetype": "postalcode"
  },
  "geometry": {"coordinates":[-1.754392,51.595424],"type":"Point"}
}
