{
  "type": "Feature",
  "properties": {
    "iso:country":"GB",
    "wof:name":"ME15 8HR",
    "wof:placetype":"postalcode"
},
  "geometry": {"coordinates":[0.55262327987266,51.24853110807548],"type":"Point"}
}