{
  "type": "Feature",
  "properties": {
    "iso:country": "GB",
    "wof:name": "LS10 1TF",
    "wof:placetype": "postalcode"
  },
  "geometry": {"coordinates":[-1.52501,53.782261],"type":"Point"}
}
