{
  "type": "Feature",
  "properties": {
    "iso:country":"GB",
    "wof:name":"LS10 1TF",
    "wof:placetype":"postalcode"
},
  "geometry": {"coordinates":[-1.52501012130684,53.78226071481939],"type":"Point"}
}