{
  "type": "Feature",
  "properties": {
    "date:inception_lower":"1995-12-01",
    "date:inception_upper":"1995-12-31",
    "iso:country":"GB",
    "wof:name":"LS10 1TF",
    "wof:placetype":"postalcode"
},
  "geometry": {"coordinates":[-1.52501,53.782261],"type":"Point"}
}