{
  "type": "Feature",
  "properties": {
    "iso:country":"GB",
    "wof:name":"BS32 0BQ",
    "wof:placetype":"postalcode"
},
  "geometry": {"coordinates":[-2.55903463899099,51.54294272121226],"type":"Point"}
}