{
  "type": "Feature",
  "properties": {
    "date:inception_lower":"2015-02-01",
    "date:inception_upper":"2015-02-28",
    "iso:country":"GB",
    "wof:name":"SW2 4BT",
    "wof:placetype":"postalcode"
},
  "geometry": {"coordinates":[-0.126665,51.43973],"type":"Point"}
}