{
  "type": "Feature",
  "properties": {
    "iso:country": "GB",
    "wof:name": "B90 1HU",
    "wof:placetype": "postalcode"
  },
  "geometry": {"coordinates":[-1.860814,52.40485],"type":"Point"}
}
