{
  "type": "Feature",
  "properties": {
    "iso:country":"GB",
    "wof:name":"B90 1HU",
    "wof:placetype":"postalcode"
},
  "geometry": {"coordinates":[-1.86081443890201,52.40484996819491],"type":"Point"}
}