{
  "type": "Feature",
  "properties": {
    "iso:country":"GB",
    "wof:name":"ST19 5QB",
    "wof:placetype":"postalcode"
},
  "geometry": {"coordinates":[-2.14609155712254,52.69669671563766],"type":"Point"}
}