{
  "type": "Feature",
  "properties": {
    "iso:country": "GB",
    "wof:name": "ST19 5QB",
    "wof:placetype": "postalcode"
  },
  "geometry": {"coordinates":[-2.146092,52.696697],"type":"Point"}
}
