{
  "type": "Feature",
  "properties": {
    "iso:country": "GB",
    "wof:name": "ML2 0ER",
    "wof:placetype": "postalcode"
  },
  "geometry": {"coordinates":[-3.940956,55.770258],"type":"Point"}
}
