{
  "type": "Feature",
  "properties": {
    "date:inception_lower": "1980-01-01",
    "date:inception_upper": "1980-01-01",
    "iso:country": "GB",
    "wof:name": "DN33 2NT",
    "wof:placetype": "postalcode"
  },
  "geometry": {"coordinates":[-0.089008,53.530251],"type":"Point"}
}
