{
  "type": "Feature",
  "properties": {
    "iso:country": "GB",
    "wof:name": "WV6 8DB",
    "wof:placetype": "postalcode"
  },
  "geometry": {"coordinates":[-2.200344,52.585064],"type":"Point"}
}
