{
  "type": "Feature",
  "properties": {
    "iso:country":"GB",
    "wof:name":"WV6 8DB",
    "wof:placetype":"postalcode"
},
  "geometry": {"coordinates":[-2.20034360369706,52.58506381784103],"type":"Point"}
}