{
  "type": "Feature",
  "properties": {
    "iso:country":"GB",
    "wof:name":"RG9 1RH",
    "wof:placetype":"postalcode"
},
  "geometry": {"coordinates":[-0.92314636211259,51.53068649387291],"type":"Point"}
}