{
  "type": "Feature",
  "properties": {
    "iso:country": "GB",
    "wof:name": "RG9 1RH",
    "wof:placetype": "postalcode"
  },
  "geometry": {"coordinates":[-0.923146,51.530686],"type":"Point"}
}
