{
  "type": "Feature",
  "properties": {
    "date:inception_lower": "1980-01-01",
    "date:inception_upper": "1980-01-01",
    "iso:country": "GB",
    "wof:name": "RG9 1RH",
    "wof:placetype": "postalcode"
  },
  "geometry": {"coordinates":[-0.923146,51.530686],"type":"Point"}
}
