{
  "type": "Feature",
  "properties": {
    "iso:country":"GB",
    "wof:name":"ST3 1DX",
    "wof:placetype":"postalcode"
},
  "geometry": {"coordinates":[-2.13254808956465,52.9921046045053],"type":"Point"}
}