{
  "type": "Feature",
  "properties": {
    "iso:country": "GB",
    "wof:name": "CA11 0HP",
    "wof:placetype": "postalcode"
  },
  "geometry": {"coordinates":[-2.808392,54.653027],"type":"Point"}
}
