{
  "type": "Feature",
  "properties": {
    "iso:country":"GB",
    "wof:name":"DE14 9TQ",
    "wof:placetype":"postalcode"
},
  "geometry": {"coordinates":[-1.64560177645965,52.80798974809766],"type":"Point"}
}