{
  "type": "Feature",
  "properties": {
    "iso:country":"GB",
    "wof:name":"HP6 6DG",
    "wof:placetype":"postalcode"
},
  "geometry": {"coordinates":[-0.6000896701282,51.6892301146932],"type":"Point"}
}