{
  "type": "Feature",
  "properties": {
    "date:inception_lower": "1980-01-01",
    "date:inception_upper": "1980-01-01",
    "iso:country": "GB",
    "wof:name": "HP6 6DG",
    "wof:placetype": "postalcode"
  },
  "geometry": {"coordinates":[-0.60009,51.68923],"type":"Point"}
}
