{
  "type": "Feature",
  "properties": {
    "date:inception_lower": "1980-01-01",
    "date:inception_upper": "1980-01-01",
    "iso:country": "GB",
    "wof:name": "G64 3EW",
    "wof:placetype": "postalcode"
  },
  "geometry": {"coordinates":[-4.228027,55.914344],"type":"Point"}
}
