{
  "type": "Feature",
  "properties": {
    "iso:country": "GB",
    "wof:name": "G75 9PH",
    "wof:placetype": "postalcode"
  },
  "geometry": {"coordinates":[-4.198003,55.735402],"type":"Point"}
}
