{
  "type": "Feature",
  "properties": {
    "date:inception_lower": "2019-11-01",
    "date:inception_upper": "2019-11-01",
    "iso:country": "GB",
    "wof:name": "G75 9PH",
    "wof:placetype": "postalcode"
  },
  "geometry": {"coordinates":[-4.198003,55.735402],"type":"Point"}
}
