{
  "type": "Feature",
  "properties": {
    "date:inception_lower":"1980-01-01",
    "date:inception_upper":"1980-01-31",
    "iso:country":"GB",
    "wof:name":"CM17 9DD",
    "wof:placetype":"postalcode"
},
  "geometry": {"coordinates":[0.138938,51.75734],"type":"Point"}
}