{
  "type": "Feature",
  "properties": {
    "iso:country": "GB",
    "wof:name": "CM17 9DD",
    "wof:placetype": "postalcode"
  },
  "geometry": {"coordinates":[0.138938,51.75734],"type":"Point"}
}
