{
  "type": "Feature",
  "properties": {
    "date:inception_lower": "1980-01-01",
    "date:inception_upper": "1980-01-01",
    "iso:country": "GB",
    "wof:name": "SK16 4TG",
    "wof:placetype": "postalcode"
  },
  "geometry": {"coordinates":[-2.087152,53.476157],"type":"Point"}
}
