{
  "type": "Feature",
  "properties": {
    "iso:country":"GB",
    "wof:name":"CH7 6EQ",
    "wof:placetype":"postalcode"
},
  "geometry": {"coordinates":[-3.13440832148134,53.18629605470893],"type":"Point"}
}