{
  "type": "Feature",
  "properties": {
    "date:inception_lower": "1980-01-01",
    "date:inception_upper": "1980-01-01",
    "iso:country": "GB",
    "wof:name": "TA21 0AT",
    "wof:placetype": "postalcode"
  },
  "geometry": {"coordinates":[-3.241727,50.987302],"type":"Point"}
}
