{
  "type": "Feature",
  "properties": {
    "iso:country": "GB",
    "wof:name": "GU1 4HQ",
    "wof:placetype": "postalcode"
  },
  "geometry": {"coordinates":[-0.571026,51.240271],"type":"Point"}
}
