{
  "type": "Feature",
  "properties": {
    "iso:country":"GB",
    "wof:name":"CO5 8HU",
    "wof:placetype":"postalcode"
},
  "geometry": {"coordinates":[0.9149097026069,51.77617420257658],"type":"Point"}
}