{
  "type": "Feature",
  "properties": {
    "iso:country":"GB",
    "wof:name":"TR12 7QH",
    "wof:placetype":"postalcode"
},
  "geometry": {"coordinates":[-5.26766328092214,50.05955514837331],"type":"Point"}
}