{
  "type": "Feature",
  "properties": {
    "iso:country": "GB",
    "wof:name": "TR12 7QH",
    "wof:placetype": "postalcode"
  },
  "geometry": {"coordinates":[-5.267663,50.059555],"type":"Point"}
}
