{
  "type": "Feature",
  "properties": {
    "iso:country":"GB",
    "wof:name":"B24 0BN",
    "wof:placetype":"postalcode"
},
  "geometry": {"coordinates":[-1.81399696384941,52.52746310875294],"type":"Point"}
}