{
  "type": "Feature",
  "properties": {
    "iso:country":"GB",
    "wof:name":"TN2 5HG",
    "wof:placetype":"postalcode"
},
  "geometry": {"coordinates":[0.27957803874404,51.11924013578494],"type":"Point"}
}