{
  "type": "Feature",
  "properties": {
    "iso:country": "GB",
    "wof:name": "PL4 7QD",
    "wof:placetype": "postalcode"
  },
  "geometry": {"coordinates":[-4.112782,50.37838],"type":"Point"}
}
