{
  "type": "Feature",
  "properties": {
    "iso:country":"GB",
    "wof:name":"GU14 8DZ",
    "wof:placetype":"postalcode"
},
  "geometry": {"coordinates":[-0.75952521690341,51.31315368242753],"type":"Point"}
}