{
  "type": "Feature",
  "properties": {
    "iso:country":"GB",
    "wof:name":"WF8 3LF",
    "wof:placetype":"postalcode"
},
  "geometry": {"coordinates":[-1.20725659437855,53.64470492460909],"type":"Point"}
}