{
  "type": "Feature",
  "properties": {
    "iso:country": "GB",
    "wof:name": "PH1 3XU",
    "wof:placetype": "postalcode"
  },
  "geometry": {"coordinates":[-3.480627,56.418656],"type":"Point"}
}
