{
  "type": "Feature",
  "properties": {
    "iso:country":"GB",
    "wof:name":"PH1 3XU",
    "wof:placetype":"postalcode"
},
  "geometry": {"coordinates":[-3.47892800992718,56.41867651484328],"type":"Point"}
}