{
  "type": "Feature",
  "properties": {
    "iso:country": "GB",
    "wof:name": "HD9 3EJ",
    "wof:placetype": "postalcode"
  },
  "geometry": {"coordinates":[-1.791896,53.582935],"type":"Point"}
}
