{
  "type": "Feature",
  "properties": {
    "iso:country":"GB",
    "wof:name":"HD9 3EJ",
    "wof:placetype":"postalcode"
},
  "geometry": {"coordinates":[-1.79189575027107,53.58293517671922],"type":"Point"}
}