{
  "type": "Feature",
  "properties": {
    "iso:country":"GB",
    "wof:name":"TS1 2DU",
    "wof:placetype":"postalcode"
},
  "geometry": {"coordinates":[-1.22696629596447,54.57419317858214],"type":"Point"}
}