{
  "type": "Feature",
  "properties": {
    "iso:country":"GB",
    "wof:name":"AL10 8PJ",
    "wof:placetype":"postalcode"
},
  "geometry": {"coordinates":[-0.22231126158922,51.75395351379196],"type":"Point"}
}