{
  "type": "Feature",
  "properties": {
    "date:inception_lower": "1980-01-01",
    "date:inception_upper": "1980-01-01",
    "iso:country": "GB",
    "wof:name": "SA31 1DZ",
    "wof:placetype": "postalcode"
  },
  "geometry": {"coordinates":[-4.304642,51.863053],"type":"Point"}
}
