{
  "type": "Feature",
  "properties": {
    "iso:country":"GB",
    "wof:name":"SA31 1DZ",
    "wof:placetype":"postalcode"
},
  "geometry": {"coordinates":[-4.30464158272261,51.8630528239231],"type":"Point"}
}