{
  "type": "Feature",
  "properties": {
    "iso:country":"GB",
    "wof:name":"CV6 4HH",
    "wof:placetype":"postalcode"
},
  "geometry": {"coordinates":[-1.51110490953588,52.45030190720182],"type":"Point"}
}