{
  "type": "Feature",
  "properties": {
    "iso:country": "GB",
    "wof:name": "DN40 1QE",
    "wof:placetype": "postalcode"
  },
  "geometry": {"coordinates":[-0.209187,53.616694],"type":"Point"}
}
