{
  "type": "Feature",
  "properties": {
    "iso:country": "GB",
    "wof:name": "DN31 1PE",
    "wof:placetype": "postalcode"
  },
  "geometry": {"coordinates":[-0.080597,53.569096],"type":"Point"}
}
