{
  "type": "Feature",
  "properties": {
    "iso:country":"GB",
    "wof:name":"DT9 3AX",
    "wof:placetype":"postalcode"
},
  "geometry": {"coordinates":[-2.51579807404711,50.948432233691],"type":"Point"}
}