{
  "type": "Feature",
  "properties": {
    "iso:country":"GB",
    "wof:name":"PL23 1NE",
    "wof:placetype":"postalcode"
},
  "geometry": {"coordinates":[-4.6082407753441,50.34995546749077],"type":"Point"}
}