{
  "type": "Feature",
  "properties": {
    "iso:country": "GB",
    "wof:name": "PL23 1NE",
    "wof:placetype": "postalcode"
  },
  "geometry": {"coordinates":[-4.608241,50.349955],"type":"Point"}
}
