{
  "type": "Feature",
  "properties": {
    "date:inception_lower":"1980-01-01",
    "date:inception_upper":"1980-01-31",
    "iso:country":"GB",
    "wof:name":"PL23 1NE",
    "wof:placetype":"postalcode"
},
  "geometry": {"coordinates":[-4.608241,50.349955],"type":"Point"}
}