{
  "type": "Feature",
  "properties": {
    "iso:country":"GB",
    "wof:name":"ME14 2HJ",
    "wof:placetype":"postalcode"
},
  "geometry": {"coordinates":[0.53288299165038,51.28828068162454],"type":"Point"}
}