{
  "type": "Feature",
  "properties": {
    "iso:country":"GB",
    "wof:name":"LL13 9LQ",
    "wof:placetype":"postalcode"
},
  "geometry": {"coordinates":[-2.96998661966566,53.04517755847169],"type":"Point"}
}