{
  "type": "Feature",
  "properties": {
    "iso:country":"GB",
    "wof:name":"SP4 8HP",
    "wof:placetype":"postalcode"
},
  "geometry": {"coordinates":[-1.77446115062253,51.20233981346838],"type":"Point"}
}