{
  "type": "Feature",
  "properties": {
    "date:inception_lower":"1980-01-01",
    "date:inception_upper":"1980-01-31",
    "iso:country":"GB",
    "wof:name":"SP4 8HP",
    "wof:placetype":"postalcode"
},
  "geometry": {"coordinates":[-1.774461,51.20234],"type":"Point"}
}