{
  "type": "Feature",
  "properties": {
    "date:inception_lower": "2008-08-01",
    "date:inception_upper": "2008-08-01",
    "iso:country": "GB",
    "wof:name": "CR8 3BP",
    "wof:placetype": "postalcode"
  },
  "geometry": {"coordinates":[-0.121006,51.335719],"type":"Point"}
}
