{
  "type": "Feature",
  "properties": {
    "iso:country":"GB",
    "wof:name":"CR8 3BP",
    "wof:placetype":"postalcode"
},
  "geometry": {"coordinates":[-0.1199612915981,51.33661113254605],"type":"Point"}
}