{
  "type": "Feature",
  "properties": {
    "iso:country":"GB",
    "wof:name":"N8 8AD",
    "wof:placetype":"postalcode"
},
  "geometry": {"coordinates":[-0.12490466325766,51.57780001957929],"type":"Point"}
}