{
  "type": "Feature",
  "properties": {
    "date:inception_lower": "1980-01-01",
    "date:inception_upper": "1980-01-01",
    "iso:country": "GB",
    "wof:name": "N8 8AD",
    "wof:placetype": "postalcode"
  },
  "geometry": {"coordinates":[-0.124905,51.5778],"type":"Point"}
}
