{
  "type": "Feature",
  "properties": {
    "date:inception_lower":"1980-01-01",
    "date:inception_upper":"1980-01-31",
    "iso:country":"GB",
    "wof:name":"KY6 2EU",
    "wof:placetype":"postalcode"
},
  "geometry": {"coordinates":[-3.19209,56.193367],"type":"Point"}
}