{
  "type": "Feature",
  "properties": {
    "iso:country": "GB",
    "wof:name": "IP25 6WA",
    "wof:placetype": "postalcode"
  },
  "geometry": {"coordinates":[0.840894,52.5693],"type":"Point"}
}
