{
  "type": "Feature",
  "properties": {
    "date:inception_lower":"1996-06-01",
    "date:inception_upper":"1996-06-30",
    "iso:country":"GB",
    "wof:name":"AB53 4WA",
    "wof:placetype":"postalcode"
},
  "geometry": {"coordinates":[-2.465965,57.543573],"type":"Point"}
}