{
  "type": "Feature",
  "properties": {
    "iso:country":"GB",
    "wof:name":"EH15 1SQ",
    "wof:placetype":"postalcode"
},
  "geometry": {"coordinates":[-3.13120066156611,55.94643170405035],"type":"Point"}
}