{
  "type": "Feature",
  "properties": {
    "date:inception_lower": "2014-10-01",
    "date:inception_upper": "2014-10-01",
    "iso:country": "GB",
    "wof:name": "NG31 7RX",
    "wof:placetype": "postalcode"
  },
  "geometry": {"coordinates":[-0.659524,52.908265],"type":"Point"}
}
