{
  "type": "Feature",
  "properties": {
    "iso:country":"GB",
    "wof:name":"NG31 7RX",
    "wof:placetype":"postalcode"
},
  "geometry": {"coordinates":[-0.65952445795431,52.9082648282423],"type":"Point"}
}