{
  "type": "Feature",
  "properties": {
    "iso:country":"GB",
    "wof:name":"E17 7JN",
    "wof:placetype":"postalcode"
},
  "geometry": {"coordinates":[-0.0210608244616,51.58447579729457],"type":"Point"}
}