{
  "type": "Feature",
  "properties": {
    "date:inception_lower": "2019-07-01",
    "date:inception_upper": "2019-07-01",
    "iso:country": "GB",
    "wof:name": "BD20 8EW",
    "wof:placetype": "postalcode"
  },
  "geometry": {"coordinates":[-2.00473,53.900533],"type":"Point"}
}
