{
  "type": "Feature",
  "properties": {
    "iso:country":"GB",
    "wof:name":"BA12 7RU",
    "wof:placetype":"postalcode"
},
  "geometry": {"coordinates":[-2.19995728971517,51.21786045613911],"type":"Point"}
}