{
  "type": "Feature",
  "properties": {
    "date:inception_lower": "1993-08-01",
    "date:inception_upper": "1993-08-01",
    "iso:country": "GB",
    "wof:name": "BA12 7RU",
    "wof:placetype": "postalcode"
  },
  "geometry": {"coordinates":[-2.199957,51.21786],"type":"Point"}
}
