{
  "type": "Feature",
  "properties": {
    "date:inception_lower": "1999-12-01",
    "date:inception_upper": "1999-12-01",
    "iso:country": "GB",
    "wof:name": "SO42 7PJ",
    "wof:placetype": "postalcode"
  },
  "geometry": {"coordinates":[-1.452518,50.818097],"type":"Point"}
}
