{
  "type": "Feature",
  "properties": {
    "iso:country":"GB",
    "wof:name":"NG31 6JX",
    "wof:placetype":"postalcode"
},
  "geometry": {"coordinates":[-0.63287977344871,52.90441017308699],"type":"Point"}
}