{
  "type": "Feature",
  "properties": {
    "iso:country": "GB",
    "wof:name": "NG31 6JX",
    "wof:placetype": "postalcode"
  },
  "geometry": {"coordinates":[-0.63288,52.90441],"type":"Point"}
}
