{
  "type": "Feature",
  "properties": {
    "date:inception_lower": "1990-02-01",
    "date:inception_upper": "1990-02-01",
    "iso:country": "GB",
    "wof:name": "LU4 0XX",
    "wof:placetype": "postalcode"
  },
  "geometry": {"coordinates":[-0.483612,51.90632],"type":"Point"}
}
