{
  "type": "Feature",
  "properties": {
    "iso:country": "GB",
    "wof:name": "LU4 0XX",
    "wof:placetype": "postalcode"
  },
  "geometry": {"coordinates":[-0.483612,51.90632],"type":"Point"}
}
