{
  "type": "Feature",
  "properties": {
    "date:inception_lower": "2001-06-01",
    "date:inception_upper": "2001-06-01",
    "iso:country": "GB",
    "wof:name": "EH49 6BF",
    "wof:placetype": "postalcode"
  },
  "geometry": {"coordinates":[-3.568451,55.974161],"type":"Point"}
}
