{
  "type": "Feature",
  "properties": {
    "iso:country":"GB",
    "wof:name":"EH49 6BF",
    "wof:placetype":"postalcode"
},
  "geometry": {"coordinates":[-3.56845111262224,55.97416079607508],"type":"Point"}
}