{
  "type": "Feature",
  "properties": {
    "iso:country":"GB",
    "wof:name":"LS6 1DF",
    "wof:placetype":"postalcode"
},
  "geometry": {"coordinates":[-1.57310337362032,53.81519384805419],"type":"Point"}
}