{
  "type": "Feature",
  "properties": {
    "iso:country": "GB",
    "wof:name": "CF14 3XG",
    "wof:placetype": "postalcode"
  },
  "geometry": {"coordinates":[-3.191916,51.498691],"type":"Point"}
}
