{
  "type": "Feature",
  "properties": {
    "iso:country":"GB",
    "wof:name":"CF14 3XG",
    "wof:placetype":"postalcode"
},
  "geometry": {"coordinates":[-3.19191616894131,51.49869063824424],"type":"Point"}
}