{
  "type": "Feature",
  "properties": {
    "date:inception_lower": "1999-06-01",
    "date:inception_upper": "1999-06-01",
    "iso:country": "GB",
    "wof:name": "CF14 3XG",
    "wof:placetype": "postalcode"
  },
  "geometry": {"coordinates":[-3.191916,51.498691],"type":"Point"}
}
