{
  "type": "Feature",
  "properties": {
    "iso:country": "GB",
    "wof:name": "SR4 9JL",
    "wof:placetype": "postalcode"
  },
  "geometry": {"coordinates":[-1.462345,54.892194],"type":"Point"}
}
