{
  "type": "Feature",
  "properties": {
    "date:inception_lower":"1980-01-01",
    "date:inception_upper":"1980-01-31",
    "iso:country":"GB",
    "wof:name":"SR4 9JL",
    "wof:placetype":"postalcode"
},
  "geometry": {"coordinates":[-1.462345,54.892194],"type":"Point"}
}