{
  "type": "Feature",
  "properties": {
    "iso:country":"GB",
    "wof:name":"SR4 9JL",
    "wof:placetype":"postalcode"
},
  "geometry": {"coordinates":[-1.46234541368163,54.8921938649481],"type":"Point"}
}