{
  "type": "Feature",
  "properties": {
    "iso:country":"GB",
    "wof:name":"PO4 9EZ",
    "wof:placetype":"postalcode"
},
  "geometry": {"coordinates":[-1.06189642599717,50.78697802907101],"type":"Point"}
}