{
  "type": "Feature",
  "properties": {
    "date:inception_lower": "1980-01-01",
    "date:inception_upper": "1980-01-01",
    "iso:country": "GB",
    "wof:name": "CF46 5BS",
    "wof:placetype": "postalcode"
  },
  "geometry": {"coordinates":[-3.302174,51.656881],"type":"Point"}
}
