{
  "type": "Feature",
  "properties": {
    "iso:country": "GB",
    "wof:name": "LE18 4YE",
    "wof:placetype": "postalcode"
  },
  "geometry": {"coordinates":[-1.132904,52.586665],"type":"Point"}
}
