{
  "type": "Feature",
  "properties": {
    "date:inception_lower": "2022-10-01",
    "date:inception_upper": "2022-10-01",
    "iso:country": "GB",
    "wof:name": "AB21 9HF",
    "wof:placetype": "postalcode"
  },
  "geometry": {"coordinates":[-2.197333,57.182144],"type":"Point"}
}
