{
  "type": "Feature",
  "properties": {
    "iso:country":"GB",
    "wof:name":"WN4 9JN",
    "wof:placetype":"postalcode"
},
  "geometry": {"coordinates":[-2.62493982087311,53.4839838367659],"type":"Point"}
}