{
  "type": "Feature",
  "properties": {
    "date:inception_lower": "2018-01-01",
    "date:inception_upper": "2018-01-01",
    "iso:country": "GB",
    "wof:name": "CM7 5FW",
    "wof:placetype": "postalcode"
  },
  "geometry": {"coordinates":[0.57765,51.909386],"type":"Point"}
}
