{
  "type": "Feature",
  "properties": {
    "iso:country":"GB",
    "wof:name":"KA13 6LH",
    "wof:placetype":"postalcode"
},
  "geometry": {"coordinates":[-4.71253249893244,55.65299071026416],"type":"Point"}
}