{
  "type": "Feature",
  "properties": {
    "iso:country":"GB",
    "wof:name":"WA14 3ES",
    "wof:placetype":"postalcode"
},
  "geometry": {"coordinates":[-2.36036219816019,53.37189097354003],"type":"Point"}
}