{
  "type": "Feature",
  "properties": {
    "iso:country":"GB",
    "wof:name":"BH17 7AR",
    "wof:placetype":"postalcode"
},
  "geometry": {"coordinates":[-1.9917141989814,50.73969664775657],"type":"Point"}
}