{
  "type": "Feature",
  "properties": {
    "iso:country":"GB",
    "wof:name":"S5 6JH",
    "wof:placetype":"postalcode"
},
  "geometry": {"coordinates":[-1.45611429104227,53.41705814852934],"type":"Point"}
}