{
  "type": "Feature",
  "properties": {
    "date:inception_lower": "2008-09-01",
    "date:inception_upper": "2008-09-01",
    "iso:country": "GB",
    "wof:name": "S5 6JH",
    "wof:placetype": "postalcode"
  },
  "geometry": {"coordinates":[-1.456114,53.417058],"type":"Point"}
}
