{
  "type": "Feature",
  "properties": {
    "iso:country": "GB",
    "wof:name": "BD13 1DH",
    "wof:placetype": "postalcode"
  },
  "geometry": {"coordinates":[-1.836432,53.76564],"type":"Point"}
}
