{
  "type": "Feature",
  "properties": {
    "iso:country":"GB",
    "wof:name":"SW7 3DP",
    "wof:placetype":"postalcode"
},
  "geometry": {"coordinates":[-0.17553543793533,51.49373648811989],"type":"Point"}
}