{
  "type": "Feature",
  "properties": {
    "iso:country":"GB",
    "wof:name":"B61 9DA",
    "wof:placetype":"postalcode"
},
  "geometry": {"coordinates":[-2.09677449615684,52.35606645523907],"type":"Point"}
}