{
  "type": "Feature",
  "properties": {
    "iso:country":"GB",
    "wof:name":"SE14 5JD",
    "wof:placetype":"postalcode"
},
  "geometry": {"coordinates":[-0.05246469027748,51.47347509177123],"type":"Point"}
}