{
  "type": "Feature",
  "properties": {
    "iso:country":"GB",
    "wof:name":"WF6 1LN",
    "wof:placetype":"postalcode"
},
  "geometry": {"coordinates":[-1.41073423396244,53.68997542155537],"type":"Point"}
}