{
  "type": "Feature",
  "properties": {
    "iso:country":"GB",
    "wof:name":"OL2 6PT",
    "wof:placetype":"postalcode"
},
  "geometry": {"coordinates":[-2.12489994640583,53.57023292029458],"type":"Point"}
}