{
  "type": "Feature",
  "properties": {
    "iso:country":"GB",
    "wof:name":"L34 7HF",
    "wof:placetype":"postalcode"
},
  "geometry": {"coordinates":[-2.85626262960583,53.4436375672279],"type":"Point"}
}