{
  "type": "Feature",
  "properties": {
    "iso:country": "GB",
    "wof:name": "L34 7HF",
    "wof:placetype": "postalcode"
  },
  "geometry": {"coordinates":[-2.856263,53.443638],"type":"Point"}
}
