{
  "type": "Feature",
  "properties": {
    "iso:country":"GB",
    "wof:name":"DY6 8QP",
    "wof:placetype":"postalcode"
},
  "geometry": {"coordinates":[-2.148466356459,52.48520880654348],"type":"Point"}
}