{
  "type": "Feature",
  "properties": {
    "date:inception_lower":"1980-01-01",
    "date:inception_upper":"1980-01-31",
    "iso:country":"GB",
    "wof:name":"DY6 8QP",
    "wof:placetype":"postalcode"
},
  "geometry": {"coordinates":[-2.148445,52.485223],"type":"Point"}
}