{
  "type": "Feature",
  "properties": {
    "iso:country":"GB",
    "wof:name":"IP8 4BQ",
    "wof:placetype":"postalcode"
},
  "geometry": {"coordinates":[1.0443468873746,52.09615647413352],"type":"Point"}
}