{
  "type": "Feature",
  "properties": {
    "date:inception_lower": "1993-01-01",
    "date:inception_upper": "1993-01-01",
    "iso:country": "GB",
    "wof:name": "IP8 4BQ",
    "wof:placetype": "postalcode"
  },
  "geometry": {"coordinates":[1.044392,52.09618],"type":"Point"}
}
