{
  "type": "Feature",
  "properties": {
    "iso:country": "GB",
    "wof:name": "IP8 4BQ",
    "wof:placetype": "postalcode"
  },
  "geometry": {"coordinates":[1.044347,52.096156],"type":"Point"}
}
