{
  "type": "Feature",
  "properties": {
    "iso:country":"GB",
    "wof:name":"BN22 9JW",
    "wof:placetype":"postalcode"
},
  "geometry": {"coordinates":[0.27760554125505,50.80389443364763],"type":"Point"}
}