{
  "type": "Feature",
  "properties": {
    "iso:country": "GB",
    "wof:name": "NR2 4JG",
    "wof:placetype": "postalcode"
  },
  "geometry": {"coordinates":[1.278022,52.635166],"type":"Point"}
}
