{
  "type": "Feature",
  "properties": {
    "date:inception_lower": "1980-01-01",
    "date:inception_upper": "1980-01-01",
    "iso:country": "GB",
    "wof:name": "NR2 4JG",
    "wof:placetype": "postalcode"
  },
  "geometry": {"coordinates":[1.278022,52.635166],"type":"Point"}
}
