{
  "type": "Feature",
  "properties": {
    "iso:country":"GB",
    "wof:name":"SW12 0HB",
    "wof:placetype":"postalcode"
},
  "geometry": {"coordinates":[-0.14043484622713,51.4425839609213],"type":"Point"}
}