{
  "type": "Feature",
  "properties": {
    "date:inception_lower": "1991-01-01",
    "date:inception_upper": "1991-01-01",
    "iso:country": "GB",
    "wof:name": "OX15 0PW",
    "wof:placetype": "postalcode"
  },
  "geometry": {"coordinates":[-1.364914,51.99477],"type":"Point"}
}
