{
  "type": "Feature",
  "properties": {
    "iso:country": "GB",
    "wof:name": "OX15 0PW",
    "wof:placetype": "postalcode"
  },
  "geometry": {"coordinates":[-1.364914,51.99477],"type":"Point"}
}
