{
  "type": "Feature",
  "properties": {
    "iso:country": "GB",
    "wof:name": "SE10 0FX",
    "wof:placetype": "postalcode"
  },
  "geometry": {"coordinates":[0.012402,51.495635],"type":"Point"}
}
