{
  "type": "Feature",
  "properties": {
    "iso:country": "GB",
    "wof:name": "LL30 1NT",
    "wof:placetype": "postalcode"
  },
  "geometry": {"coordinates":[-3.830345,53.306093],"type":"Point"}
}
