{
  "type": "Feature",
  "properties": {
    "date:inception_lower":"1998-12-01",
    "date:inception_upper":"1998-12-31",
    "iso:country":"GB",
    "wof:name":"TQ1 1RA",
    "wof:placetype":"postalcode"
},
  "geometry": {"coordinates":[-3.515202,50.4675],"type":"Point"}
}