{
  "type": "Feature",
  "properties": {
    "iso:country":"GB",
    "wof:name":"TQ1 1RA",
    "wof:placetype":"postalcode"
},
  "geometry": {"coordinates":[-3.51520180329684,50.46750002002321],"type":"Point"}
}