{
  "type": "Feature",
  "properties": {
    "iso:country": "GB",
    "wof:name": "TQ1 1RA",
    "wof:placetype": "postalcode"
  },
  "geometry": {"coordinates":[-3.515202,50.4675],"type":"Point"}
}
