{
  "type": "Feature",
  "properties": {
    "iso:country": "GB",
    "wof:name": "PO19 7LJ",
    "wof:placetype": "postalcode"
  },
  "geometry": {"coordinates":[-0.77346,50.836758],"type":"Point"}
}
