{
  "type": "Feature",
  "properties": {
    "iso:country": "GB",
    "wof:name": "IV3 5QP",
    "wof:placetype": "postalcode"
  },
  "geometry": {"coordinates":[-4.241731,57.477755],"type":"Point"}
}
