{
  "type": "Feature",
  "properties": {
    "iso:country":"GB",
    "wof:name":"IV3 5QP",
    "wof:placetype":"postalcode"
},
  "geometry": {"coordinates":[-4.24173128027757,57.47775507320588],"type":"Point"}
}