{
  "type": "Feature",
  "properties": {
    "date:inception_lower": "1980-01-01",
    "date:inception_upper": "1980-01-01",
    "iso:country": "GB",
    "wof:name": "B31 2ED",
    "wof:placetype": "postalcode"
  },
  "geometry": {"coordinates":[-1.95323,52.416115],"type":"Point"}
}
