{
  "type": "Feature",
  "properties": {
    "iso:country":"GB",
    "wof:name":"ST5 8NT",
    "wof:placetype":"postalcode"
},
  "geometry": {"coordinates":[-2.22416129701237,53.03948368615946],"type":"Point"}
}