{
  "type": "Feature",
  "properties": {
    "date:inception_lower": "1980-01-01",
    "date:inception_upper": "1980-01-01",
    "iso:country": "GB",
    "wof:name": "SY16 4JQ",
    "wof:placetype": "postalcode"
  },
  "geometry": {"coordinates":[-3.350806,52.496333],"type":"Point"}
}
