{
  "type": "Feature",
  "properties": {
    "date:inception_lower": "1980-01-01",
    "date:inception_upper": "1980-01-01",
    "iso:country": "GB",
    "wof:name": "TQ1 2LY",
    "wof:placetype": "postalcode"
  },
  "geometry": {"coordinates":[-3.51149,50.461568],"type":"Point"}
}
