{
  "type": "Feature",
  "properties": {
    "iso:country":"GB",
    "wof:name":"B43 7LB",
    "wof:placetype":"postalcode"
},
  "geometry": {"coordinates":[-1.9021325470915,52.55833191194945],"type":"Point"}
}