{
  "type": "Feature",
  "properties": {
    "iso:country":"GB",
    "wof:name":"NW2 4LY",
    "wof:placetype":"postalcode"
},
  "geometry": {"coordinates":[-0.22646251307085,51.55303124054942],"type":"Point"}
}