{
  "type": "Feature",
  "properties": {
    "iso:country":"GB",
    "wof:name":"LN1 1LD",
    "wof:placetype":"postalcode"
},
  "geometry": {"coordinates":[-0.5481643486455,53.23307227173635],"type":"Point"}
}