{
  "type": "Feature",
  "properties": {
    "iso:country": "GB",
    "wof:name": "FK8 2RA",
    "wof:placetype": "postalcode"
  },
  "geometry": {"coordinates":[-3.945591,56.116585],"type":"Point"}
}
