{
  "type": "Feature",
  "properties": {
    "iso:country":"GB",
    "wof:name":"TQ5 8HJ",
    "wof:placetype":"postalcode"
},
  "geometry": {"coordinates":[-3.51515777749967,50.39555991075587],"type":"Point"}
}