{
  "type": "Feature",
  "properties": {
    "iso:country":"GB",
    "wof:name":"SW1V 4LX",
    "wof:placetype":"postalcode"
},
  "geometry": {"coordinates":[-0.14486943109096,51.48866919344174],"type":"Point"}
}