{
  "type": "Feature",
  "properties": {
    "date:inception_lower": "1990-02-01",
    "date:inception_upper": "1990-02-01",
    "iso:country": "GB",
    "wof:name": "SG5 1HL",
    "wof:placetype": "postalcode"
  },
  "geometry": {"coordinates":[-0.281039,51.949779],"type":"Point"}
}
