{
  "type": "Feature",
  "properties": {
    "date:inception_lower":"1983-03-01",
    "date:inception_upper":"1983-03-31",
    "iso:country":"GB",
    "wof:name":"CT6 7XA",
    "wof:placetype":"postalcode"
},
  "geometry": {"coordinates":[1.151884,51.357965],"type":"Point"}
}