{
  "type": "Feature",
  "properties": {
    "iso:country":"GB",
    "wof:name":"CT6 7XA",
    "wof:placetype":"postalcode"
},
  "geometry": {"coordinates":[1.15188398054283,51.35796496939354],"type":"Point"}
}