{
  "type": "Feature",
  "properties": {
    "iso:country": "GB",
    "wof:name": "CT6 7XA",
    "wof:placetype": "postalcode"
  },
  "geometry": {"coordinates":[1.151884,51.357965],"type":"Point"}
}
