{
  "type": "Feature",
  "properties": {
    "iso:country":"GB",
    "wof:name":"DN22 7DT",
    "wof:placetype":"postalcode"
},
  "geometry": {"coordinates":[-0.9348507537355,53.3159176403124],"type":"Point"}
}