{
  "type": "Feature",
  "properties": {
    "date:inception_lower": "1980-01-01",
    "date:inception_upper": "1980-01-01",
    "iso:country": "GB",
    "wof:name": "BB1 7ES",
    "wof:placetype": "postalcode"
  },
  "geometry": {"coordinates":[-2.486226,53.753703],"type":"Point"}
}
