{
  "type": "Feature",
  "properties": {
    "date:inception_lower": "2002-06-01",
    "date:inception_upper": "2002-06-01",
    "iso:country": "GB",
    "wof:name": "S20 5ET",
    "wof:placetype": "postalcode"
  },
  "geometry": {"coordinates":[-1.365428,53.328289],"type":"Point"}
}
