{
  "type": "Feature",
  "properties": {
    "date:inception_lower":"2002-06-01",
    "date:inception_upper":"2002-06-30",
    "iso:country":"GB",
    "wof:name":"S20 5ET",
    "wof:placetype":"postalcode"
},
  "geometry": {"coordinates":[-1.365413,53.328278],"type":"Point"}
}