{
  "type": "Feature",
  "properties": {
    "iso:country":"GB",
    "wof:name":"S20 5ET",
    "wof:placetype":"postalcode"
},
  "geometry": {"coordinates":[-1.36541335181288,53.32827834824287],"type":"Point"}
}