{
  "type": "Feature",
  "properties": {
    "date:inception_lower":"1980-01-01",
    "date:inception_upper":"1980-01-31",
    "iso:country":"GB",
    "wof:name":"BS4 4PT",
    "wof:placetype":"postalcode"
},
  "geometry": {"coordinates":[-2.548691,51.438222],"type":"Point"}
}