{
  "type": "Feature",
  "properties": {
    "iso:country":"GB",
    "wof:name":"BS4 4PT",
    "wof:placetype":"postalcode"
},
  "geometry": {"coordinates":[-2.54869099306933,51.43822178847713],"type":"Point"}
}