{
  "type": "Feature",
  "properties": {
    "iso:country":"GB",
    "wof:name":"SO17 2HH",
    "wof:placetype":"postalcode"
},
  "geometry": {"coordinates":[-1.39199691254695,50.92452091395236],"type":"Point"}
}