{
  "type": "Feature",
  "properties": {
    "iso:country":"GB",
    "wof:name":"FY1 2LT",
    "wof:placetype":"postalcode"
},
  "geometry": {"coordinates":[-3.05066277606778,53.83367583684198],"type":"Point"}
}