{
  "type": "Feature",
  "properties": {
    "iso:country":"GB",
    "wof:name":"DL12 9NX",
    "wof:placetype":"postalcode"
},
  "geometry": {"coordinates":[-1.98678796782529,54.5738197736538],"type":"Point"}
}