{
  "type": "Feature",
  "properties": {
    "iso:country":"GB",
    "wof:name":"G15 7DS",
    "wof:placetype":"postalcode"
},
  "geometry": {"coordinates":[-4.37073553247103,55.91295507279976],"type":"Point"}
}