{
  "type": "Feature",
  "properties": {
    "date:inception_lower": "1980-01-01",
    "date:inception_upper": "1980-01-01",
    "iso:country": "GB",
    "wof:name": "SY22 6PH",
    "wof:placetype": "postalcode"
  },
  "geometry": {"coordinates":[-3.11058,52.757605],"type":"Point"}
}
