{
  "type": "Feature",
  "properties": {
    "iso:country":"GB",
    "wof:name":"SY22 6PH",
    "wof:placetype":"postalcode"
},
  "geometry": {"coordinates":[-3.11058005255502,52.75760549926756],"type":"Point"}
}