{
  "type": "Feature",
  "properties": {
    "date:inception_lower":"1990-02-01",
    "date:inception_upper":"1990-02-28",
    "iso:country":"GB",
    "wof:name":"OX13 5LQ",
    "wof:placetype":"postalcode"
},
  "geometry": {"coordinates":[-1.359539,51.708268],"type":"Point"}
}