{
  "type": "Feature",
  "properties": {
    "iso:country":"GB",
    "wof:name":"OX13 5LQ",
    "wof:placetype":"postalcode"
},
  "geometry": {"coordinates":[-1.35953948263437,51.70826768434834],"type":"Point"}
}