{
  "type": "Feature",
  "properties": {
    "iso:country":"GB",
    "wof:name":"ME8 6LG",
    "wof:placetype":"postalcode"
},
  "geometry": {"coordinates":[0.58116797531656,51.37630851266331],"type":"Point"}
}