{
  "type": "Feature",
  "properties": {
    "iso:country":"GB",
    "wof:name":"HR6 9UU",
    "wof:placetype":"postalcode"
},
  "geometry": {"coordinates":[-2.85523889123718,52.31563640444021],"type":"Point"}
}