{
  "type": "Feature",
  "properties": {
    "date:inception_lower": "2017-01-01",
    "date:inception_upper": "2017-01-01",
    "iso:country": "GB",
    "wof:name": "ML3 9GG",
    "wof:placetype": "postalcode"
  },
  "geometry": {"coordinates":[-4.083937,55.773619],"type":"Point"}
}
