{
  "type": "Feature",
  "properties": {
    "date:inception_lower":"1996-06-01",
    "date:inception_upper":"1996-06-30",
    "iso:country":"GB",
    "wof:name":"AB42 1DG",
    "wof:placetype":"postalcode"
},
  "geometry": {"coordinates":[-1.772901,57.504689],"type":"Point"}
}