{
  "type": "Feature",
  "properties": {
    "date:inception_lower": "1980-01-01",
    "date:inception_upper": "1980-01-01",
    "iso:country": "GB",
    "wof:name": "S45 0JA",
    "wof:placetype": "postalcode"
  },
  "geometry": {"coordinates":[-1.516487,53.171725],"type":"Point"}
}
