{
  "type": "Feature",
  "properties": {
    "iso:country":"GB",
    "wof:name":"S45 0JA",
    "wof:placetype":"postalcode"
},
  "geometry": {"coordinates":[-1.51648700419886,53.1717254797237],"type":"Point"}
}