{
  "type": "Feature",
  "properties": {
    "iso:country":"GB",
    "wof:name":"KT8 2EL",
    "wof:placetype":"postalcode"
},
  "geometry": {"coordinates":[-0.38381184605227,51.40040276818206],"type":"Point"}
}