{
  "type": "Feature",
  "properties": {
    "iso:country":"GB",
    "wof:name":"SO18 6BP",
    "wof:placetype":"postalcode"
},
  "geometry": {"coordinates":[-1.35703149177628,50.91680699715771],"type":"Point"}
}