{
  "type": "Feature",
  "properties": {
    "date:inception_lower": "1994-12-01",
    "date:inception_upper": "1994-12-01",
    "iso:country": "GB",
    "wof:name": "SO18 6BP",
    "wof:placetype": "postalcode"
  },
  "geometry": {"coordinates":[-1.357031,50.916807],"type":"Point"}
}
