{
  "type": "Feature",
  "properties": {
    "date:inception_lower": "1980-01-01",
    "date:inception_upper": "1980-01-01",
    "iso:country": "GB",
    "wof:name": "SM5 2HD",
    "wof:placetype": "postalcode"
  },
  "geometry": {"coordinates":[-0.162184,51.376813],"type":"Point"}
}
