{
  "type": "Feature",
  "properties": {
    "iso:country":"GB",
    "wof:name":"SR5 2DZ",
    "wof:placetype":"postalcode"
},
  "geometry": {"coordinates":[-1.40649908903907,54.91874063757091],"type":"Point"}
}