{
  "type": "Feature",
  "properties": {
    "iso:country": "GB",
    "wof:name": "SR5 2DZ",
    "wof:placetype": "postalcode"
  },
  "geometry": {"coordinates":[-1.406499,54.918741],"type":"Point"}
}
