{
  "type": "Feature",
  "properties": {
    "date:inception_lower": "1980-01-01",
    "date:inception_upper": "1980-01-01",
    "iso:country": "GB",
    "wof:name": "CV5 7BX",
    "wof:placetype": "postalcode"
  },
  "geometry": {"coordinates":[-1.601531,52.420165],"type":"Point"}
}
