{
  "type": "Feature",
  "properties": {
    "date:inception_lower": "1980-01-01",
    "date:inception_upper": "1980-01-01",
    "iso:country": "GB",
    "wof:name": "CA14 1UT",
    "wof:placetype": "postalcode"
  },
  "geometry": {"coordinates":[-3.486087,54.653356],"type":"Point"}
}
