{
  "type": "Feature",
  "properties": {
    "iso:country": "GB",
    "wof:name": "BA5 3NX",
    "wof:placetype": "postalcode"
  },
  "geometry": {"coordinates":[-2.625487,51.200821],"type":"Point"}
}
