{
  "type": "Feature",
  "properties": {
    "iso:country":"GB",
    "wof:name":"G82 1EJ",
    "wof:placetype":"postalcode"
},
  "geometry": {"coordinates":[-4.54602879776705,55.94120891640254],"type":"Point"}
}