{
  "type": "Feature",
  "properties": {
    "iso:country":"GB",
    "wof:name":"NG8 5DR",
    "wof:placetype":"postalcode"
},
  "geometry": {"coordinates":[-1.19341736310941,52.97872945969043],"type":"Point"}
}