{
  "type": "Feature",
  "properties": {
    "date:inception_lower": "2010-11-01",
    "date:inception_upper": "2010-11-01",
    "iso:country": "GB",
    "wof:name": "NG8 5DR",
    "wof:placetype": "postalcode"
  },
  "geometry": {"coordinates":[-1.193417,52.978729],"type":"Point"}
}
