{
  "type": "Feature",
  "properties": {
    "date:inception_lower": "2023-06-01",
    "date:inception_upper": "2023-06-01",
    "iso:country": "GB",
    "wof:name": "CB5 8XT",
    "wof:placetype": "postalcode"
  },
  "geometry": {"coordinates":[0.179137,52.214592],"type":"Point"}
}
