{
  "type": "Feature",
  "properties": {
    "iso:country":"GB",
    "wof:name":"NN6 9BG",
    "wof:placetype":"postalcode"
},
  "geometry": {"coordinates":[-0.90898782761368,52.32559297944249],"type":"Point"}
}