{
  "type": "Feature",
  "properties": {
    "iso:country":"GB",
    "wof:name":"CO15 3QG",
    "wof:placetype":"postalcode"
},
  "geometry": {"coordinates":[1.15117832975787,51.79818961482832],"type":"Point"}
}