{
  "type": "Feature",
  "properties": {
    "iso:country":"GB",
    "wof:name":"WN6 0HT",
    "wof:placetype":"postalcode"
},
  "geometry": {"coordinates":[-2.66235464662731,53.58717729468683],"type":"Point"}
}