{
  "type": "Feature",
  "properties": {
    "iso:country":"GB",
    "wof:name":"EX32 0AW",
    "wof:placetype":"postalcode"
},
  "geometry": {"coordinates":[-4.05119980403431,51.05692840667434],"type":"Point"}
}