{
  "type": "Feature",
  "properties": {
    "iso:country":"GB",
    "wof:name":"M21 9NT",
    "wof:placetype":"postalcode"
},
  "geometry": {"coordinates":[-2.28302652148939,53.44785524173395],"type":"Point"}
}