{
  "type": "Feature",
  "properties": {
    "date:inception_lower":"1994-05-01",
    "date:inception_upper":"1994-05-31",
    "iso:country":"GB",
    "wof:name":"M21 9NT",
    "wof:placetype":"postalcode"
},
  "geometry": {"coordinates":[-2.283026,53.447855],"type":"Point"}
}