{
  "type": "Feature",
  "properties": {
    "iso:country": "GB",
    "wof:name": "M21 9NT",
    "wof:placetype": "postalcode"
  },
  "geometry": {"coordinates":[-2.283026,53.447855],"type":"Point"}
}
