{
  "type": "Feature",
  "properties": {
    "iso:country":"GB",
    "wof:name":"TS17 5AS",
    "wof:placetype":"postalcode"
},
  "geometry": {"coordinates":[-1.31585462791019,54.52786074296235],"type":"Point"}
}