{
  "type": "Feature",
  "properties": {
    "iso:country": "GB",
    "wof:name": "TS24 8NF",
    "wof:placetype": "postalcode"
  },
  "geometry": {"coordinates":[-1.215548,54.695039],"type":"Point"}
}
