{
  "type": "Feature",
  "properties": {
    "iso:country":"GB",
    "wof:name":"PO8 9SQ",
    "wof:placetype":"postalcode"
},
  "geometry": {"coordinates":[-1.02316847155271,50.90940207778326],"type":"Point"}
}