{
  "type": "Feature",
  "properties": {
    "iso:country": "GB",
    "wof:name": "DL13 1RY",
    "wof:placetype": "postalcode"
  },
  "geometry": {"coordinates":[-2.144112,54.737687],"type":"Point"}
}
