{
  "type": "Feature",
  "properties": {
    "iso:country":"GB",
    "wof:name":"DL13 1RY",
    "wof:placetype":"postalcode"
},
  "geometry": {"coordinates":[-2.14411207551689,54.7376872861813],"type":"Point"}
}