{
  "type": "Feature",
  "properties": {
    "iso:country": "GB",
    "wof:name": "PO41 0PA",
    "wof:placetype": "postalcode"
  },
  "geometry": {"coordinates":[-1.498553,50.705284],"type":"Point"}
}
