{
  "type": "Feature",
  "properties": {
    "iso:country":"GB",
    "wof:name":"NW10 0TA",
    "wof:placetype":"postalcode"
},
  "geometry": {"coordinates":[-0.26799209862229,51.54311263480803],"type":"Point"}
}