{
  "type": "Feature",
  "properties": {
    "date:inception_lower": "1994-02-01",
    "date:inception_upper": "1994-02-01",
    "iso:country": "GB",
    "wof:name": "PA2 8EE",
    "wof:placetype": "postalcode"
  },
  "geometry": {"coordinates":[-4.45594,55.82065],"type":"Point"}
}
