{
  "type": "Feature",
  "properties": {
    "iso:country": "GB",
    "wof:name": "PA2 8EE",
    "wof:placetype": "postalcode"
  },
  "geometry": {"coordinates":[-4.45594,55.82065],"type":"Point"}
}
