{
  "type": "Feature",
  "properties": {
    "iso:country":"GB",
    "wof:name":"PA2 8EE",
    "wof:placetype":"postalcode"
},
  "geometry": {"coordinates":[-4.45594006325698,55.82065026315822],"type":"Point"}
}