{
  "type": "Feature",
  "properties": {
    "date:inception_lower": "1980-01-01",
    "date:inception_upper": "1980-01-01",
    "iso:country": "GB",
    "wof:name": "S43 2BY",
    "wof:placetype": "postalcode"
  },
  "geometry": {"coordinates":[-1.400854,53.27105],"type":"Point"}
}
