{
  "type": "Feature",
  "properties": {
    "iso:country": "GB",
    "wof:name": "S43 2BY",
    "wof:placetype": "postalcode"
  },
  "geometry": {"coordinates":[-1.400854,53.27105],"type":"Point"}
}
