{
  "type": "Feature",
  "properties": {
    "iso:country": "GB",
    "wof:name": "GU34 2LA",
    "wof:placetype": "postalcode"
  },
  "geometry": {"coordinates":[-0.977356,51.158201],"type":"Point"}
}
