{
  "type": "Feature",
  "properties": {
    "iso:country":"GB",
    "wof:name":"GU34 2LA",
    "wof:placetype":"postalcode"
},
  "geometry": {"coordinates":[-0.97735601756547,51.15820057275673],"type":"Point"}
}