{
  "type": "Feature",
  "properties": {
    "iso:country":"GB",
    "wof:name":"TS24 9LS",
    "wof:placetype":"postalcode"
},
  "geometry": {"coordinates":[-1.22835353379334,54.70950065647048],"type":"Point"}
}