{
  "type": "Feature",
  "properties": {
    "date:inception_lower": "1980-01-01",
    "date:inception_upper": "1980-01-01",
    "iso:country": "GB",
    "wof:name": "CM22 6JD",
    "wof:placetype": "postalcode"
  },
  "geometry": {"coordinates":[0.220486,51.941379],"type":"Point"}
}
