{
  "type": "Feature",
  "properties": {
    "iso:country":"GB",
    "wof:name":"HA8 9JN",
    "wof:placetype":"postalcode"
},
  "geometry": {"coordinates":[-0.26347825793075,51.61164802001554],"type":"Point"}
}