{
  "type": "Feature",
  "properties": {
    "iso:country": "GB",
    "wof:name": "G65 9JZ",
    "wof:placetype": "postalcode"
  },
  "geometry": {"coordinates":[-4.073544,55.976411],"type":"Point"}
}
