{
  "type": "Feature",
  "properties": {
    "date:inception_lower": "2014-07-01",
    "date:inception_upper": "2014-07-01",
    "iso:country": "GB",
    "wof:name": "TA6 4FU",
    "wof:placetype": "postalcode"
  },
  "geometry": {"coordinates":[-2.981417,51.142987],"type":"Point"}
}
