{
  "type": "Feature",
  "properties": {
    "iso:country": "GB",
    "wof:name": "TA6 4FU",
    "wof:placetype": "postalcode"
  },
  "geometry": {"coordinates":[-2.981417,51.142987],"type":"Point"}
}
