{
  "type": "Feature",
  "properties": {
    "iso:country": "GB",
    "wof:name": "B24 9RA",
    "wof:placetype": "postalcode"
  },
  "geometry": {"coordinates":[-1.829658,52.514218],"type":"Point"}
}
