{
  "type": "Feature",
  "properties": {
    "iso:country": "GB",
    "wof:name": "SY3 8PB",
    "wof:placetype": "postalcode"
  },
  "geometry": {"coordinates":[-2.779877,52.713216],"type":"Point"}
}
