{
  "type": "Feature",
  "properties": {
    "iso:country":"GB",
    "wof:name":"SY3 8PB",
    "wof:placetype":"postalcode"
},
  "geometry": {"coordinates":[-2.7798774315566,52.71321579912141],"type":"Point"}
}