{
  "type": "Feature",
  "properties": {
    "iso:country":"GB",
    "wof:name":"FK6 5LW",
    "wof:placetype":"postalcode"
},
  "geometry": {"coordinates":[-3.93527556275948,56.0164938226614],"type":"Point"}
}