{
  "type": "Feature",
  "properties": {
    "date:inception_lower": "1980-01-01",
    "date:inception_upper": "1980-01-01",
    "iso:country": "GB",
    "wof:name": "FK6 5LW",
    "wof:placetype": "postalcode"
  },
  "geometry": {"coordinates":[-3.935276,56.016494],"type":"Point"}
}
