{
  "type": "Feature",
  "properties": {
    "iso:country": "GB",
    "wof:name": "NR9 3FZ",
    "wof:placetype": "postalcode"
  },
  "geometry": {"coordinates":[1.201032,52.593149],"type":"Point"}
}
