{
  "type": "Feature",
  "properties": {
    "iso:country": "GB",
    "wof:name": "CA13 0DJ",
    "wof:placetype": "postalcode"
  },
  "geometry": {"coordinates":[-3.420265,54.663356],"type":"Point"}
}
