{
  "type": "Feature",
  "properties": {
    "iso:country": "GB",
    "wof:name": "IV20 1SU",
    "wof:placetype": "postalcode"
  },
  "geometry": {"coordinates":[-3.964471,57.774747],"type":"Point"}
}
