{
  "type": "Feature",
  "properties": {
    "iso:country":"GB",
    "wof:name":"DG9 9QA",
    "wof:placetype":"postalcode"
},
  "geometry": {"coordinates":[-4.89493739345544,54.68786347634151],"type":"Point"}
}