{
  "type": "Feature",
  "properties": {
    "iso:country": "GB",
    "wof:name": "DG9 9QA",
    "wof:placetype": "postalcode"
  },
  "geometry": {"coordinates":[-4.894937,54.687863],"type":"Point"}
}
