{
  "type": "Feature",
  "properties": {
    "iso:country":"GB",
    "wof:name":"CT21 5PJ",
    "wof:placetype":"postalcode"
},
  "geometry": {"coordinates":[1.09428412394246,51.07567331597568],"type":"Point"}
}