{
  "type": "Feature",
  "properties": {
    "iso:country":"GB",
    "wof:name":"LE4 9EG",
    "wof:placetype":"postalcode"
},
  "geometry": {"coordinates":[-1.09282712653712,52.65508398995067],"type":"Point"}
}