{
  "type": "Feature",
  "properties": {
    "iso:country":"GB",
    "wof:name":"YO1 9QQ",
    "wof:placetype":"postalcode"
},
  "geometry": {"coordinates":[-1.07578616850196,53.9541286931553],"type":"Point"}
}