{
  "type": "Feature",
  "properties": {
    "iso:country":"GB",
    "wof:name":"YO32 9TP",
    "wof:placetype":"postalcode"
},
  "geometry": {"coordinates":[-1.05420993035698,54.01125965382884],"type":"Point"}
}