{
  "type": "Feature",
  "properties": {
    "date:inception_lower": "2004-07-01",
    "date:inception_upper": "2004-07-01",
    "iso:country": "GB",
    "wof:name": "YO32 9TP",
    "wof:placetype": "postalcode"
  },
  "geometry": {"coordinates":[-1.054236,54.011214],"type":"Point"}
}
