{
  "type": "Feature",
  "properties": {
    "iso:country":"GB",
    "wof:name":"PO6 1LH",
    "wof:placetype":"postalcode"
},
  "geometry": {"coordinates":[-1.02812980289736,50.84323029094794],"type":"Point"}
}