{
  "type": "Feature",
  "properties": {
    "iso:country":"GB",
    "wof:name":"B60 3JT",
    "wof:placetype":"postalcode"
},
  "geometry": {"coordinates":[-2.07234586639877,52.32246972451624],"type":"Point"}
}