{
  "type": "Feature",
  "properties": {
    "iso:country": "GB",
    "wof:name": "B60 3JT",
    "wof:placetype": "postalcode"
  },
  "geometry": {"coordinates":[-2.072346,52.32247],"type":"Point"}
}
