{
  "type": "Feature",
  "properties": {
    "date:inception_lower": "1990-02-01",
    "date:inception_upper": "1990-02-01",
    "iso:country": "GB",
    "wof:name": "S63 7SF",
    "wof:placetype": "postalcode"
  },
  "geometry": {"coordinates":[-1.348653,53.495027],"type":"Point"}
}
