{
  "type": "Feature",
  "properties": {
    "iso:country":"GB",
    "wof:name":"S63 7SF",
    "wof:placetype":"postalcode"
},
  "geometry": {"coordinates":[-1.34865279670471,53.49502745374291],"type":"Point"}
}