{
  "type": "Feature",
  "properties": {
    "date:inception_lower": "1990-07-01",
    "date:inception_upper": "1990-07-01",
    "iso:country": "GB",
    "wof:name": "BN25 2XJ",
    "wof:placetype": "postalcode"
  },
  "geometry": {"coordinates":[0.103455,50.789331],"type":"Point"}
}
