{
  "type": "Feature",
  "properties": {
    "iso:country":"GB",
    "wof:name":"BN25 2XJ",
    "wof:placetype":"postalcode"
},
  "geometry": {"coordinates":[0.10345489601309,50.78933068949978],"type":"Point"}
}