{
  "type": "Feature",
  "properties": {
    "iso:country":"GB",
    "wof:name":"M40 2RN",
    "wof:placetype":"postalcode"
},
  "geometry": {"coordinates":[-2.17882001105878,53.49457217141271],"type":"Point"}
}