{
  "type": "Feature",
  "properties": {
    "iso:country":"GB",
    "wof:name":"SK2 5LH",
    "wof:placetype":"postalcode"
},
  "geometry": {"coordinates":[-2.12383125825147,53.39583138573435],"type":"Point"}
}