{
  "type": "Feature",
  "properties": {
    "iso:country":"GB",
    "wof:name":"PE21 7HJ",
    "wof:placetype":"postalcode"
},
  "geometry": {"coordinates":[-0.0371385183069,52.96004664290747],"type":"Point"}
}