{
  "type": "Feature",
  "properties": {
    "date:inception_lower": "1980-01-01",
    "date:inception_upper": "1980-01-01",
    "iso:country": "GB",
    "wof:name": "PE21 7HJ",
    "wof:placetype": "postalcode"
  },
  "geometry": {"coordinates":[-0.037138,52.960047],"type":"Point"}
}
