{
  "type": "Feature",
  "properties": {
    "iso:country":"GB",
    "wof:name":"NE25 0NW",
    "wof:placetype":"postalcode"
},
  "geometry": {"coordinates":[-1.51287184190976,55.06417989327856],"type":"Point"}
}