{
  "type": "Feature",
  "properties": {
    "iso:country": "GB",
    "wof:name": "NE25 0NW",
    "wof:placetype": "postalcode"
  },
  "geometry": {"coordinates":[-1.512872,55.06418],"type":"Point"}
}
