{
  "type": "Feature",
  "properties": {
    "iso:country":"GB",
    "wof:name":"SR8 5LG",
    "wof:placetype":"postalcode"
},
  "geometry": {"coordinates":[-1.326876954969,54.7583554153958],"type":"Point"}
}