{
  "type": "Feature",
  "properties": {
    "date:inception_lower":"1980-01-01",
    "date:inception_upper":"1980-01-31",
    "iso:country":"GB",
    "wof:name":"SR8 5LG",
    "wof:placetype":"postalcode"
},
  "geometry": {"coordinates":[-1.326877,54.758355],"type":"Point"}
}