{
  "type": "Feature",
  "properties": {
    "iso:country": "GB",
    "wof:name": "NG5 5FL",
    "wof:placetype": "postalcode"
  },
  "geometry": {"coordinates":[-1.171816,52.993072],"type":"Point"}
}
