{
  "type": "Feature",
  "properties": {
    "iso:country":"GB",
    "wof:name":"NG5 5FL",
    "wof:placetype":"postalcode"
},
  "geometry": {"coordinates":[-1.17181570618706,52.99307197122777],"type":"Point"}
}