{
  "type": "Feature",
  "properties": {
    "iso:country":"GB",
    "wof:name":"HP23 5NA",
    "wof:placetype":"postalcode"
},
  "geometry": {"coordinates":[-0.65697826467184,51.79657128719568],"type":"Point"}
}