{
  "type": "Feature",
  "properties": {
    "iso:country":"GB",
    "wof:name":"M28 2FL",
    "wof:placetype":"postalcode"
},
  "geometry": {"coordinates":[-2.38197642307651,53.51291700198593],"type":"Point"}
}