{
  "type": "Feature",
  "properties": {
    "iso:country": "GB",
    "wof:name": "LN11 0UD",
    "wof:placetype": "postalcode"
  },
  "geometry": {"coordinates":[-0.003536,53.37765],"type":"Point"}
}
