{
  "type": "Feature",
  "properties": {
    "iso:country":"GB",
    "wof:name":"TS19 9BQ",
    "wof:placetype":"postalcode"
},
  "geometry": {"coordinates":[-1.33894154005735,54.58607211903335],"type":"Point"}
}