{
  "type": "Feature",
  "properties": {
    "iso:country": "GB",
    "wof:name": "TS19 9BQ",
    "wof:placetype": "postalcode"
  },
  "geometry": {"coordinates":[-1.338941,54.586072],"type":"Point"}
}
