{
  "type": "Feature",
  "properties": {
    "date:inception_lower": "2009-07-01",
    "date:inception_upper": "2009-07-01",
    "iso:country": "GB",
    "wof:name": "CM6 1GT",
    "wof:placetype": "postalcode"
  },
  "geometry": {"coordinates":[0.282431,51.868038],"type":"Point"}
}
