{
  "type": "Feature",
  "properties": {
    "iso:country":"GB",
    "wof:name":"CM6 1GT",
    "wof:placetype":"postalcode"
},
  "geometry": {"coordinates":[0.28243078517738,51.86803759758725],"type":"Point"}
}