{
  "type": "Feature",
  "properties": {
    "iso:country": "GB",
    "wof:name": "CV1 4FA",
    "wof:placetype": "postalcode"
  },
  "geometry": {"coordinates":[-1.515806,52.409909],"type":"Point"}
}
