{
  "type": "Feature",
  "properties": {
    "date:inception_lower": "2003-04-01",
    "date:inception_upper": "2003-04-01",
    "iso:country": "GB",
    "wof:name": "S66 9LU",
    "wof:placetype": "postalcode"
  },
  "geometry": {"coordinates":[-1.248681,53.395359],"type":"Point"}
}
