{
  "type": "Feature",
  "properties": {
    "iso:country":"GB",
    "wof:name":"CM7 3YA",
    "wof:placetype":"postalcode"
},
  "geometry": {"coordinates":[0.55175300153789,51.87806015883958],"type":"Point"}
}