{
  "type": "Feature",
  "properties": {
    "iso:country":"GB",
    "wof:name":"TA10 9RY",
    "wof:placetype":"postalcode"
},
  "geometry": {"coordinates":[-2.82370559545446,51.04016915784583],"type":"Point"}
}