{
  "type": "Feature",
  "properties": {
    "iso:country": "GB",
    "wof:name": "SE13 6RT",
    "wof:placetype": "postalcode"
  },
  "geometry": {"coordinates":[-0.006212,51.450701],"type":"Point"}
}
