{
  "type": "Feature",
  "properties": {
    "iso:country":"GB",
    "wof:name":"DD11 5SS",
    "wof:placetype":"postalcode"
},
  "geometry": {"coordinates":[-2.51417647780409,56.64494604687543],"type":"Point"}
}