{
  "type": "Feature",
  "properties": {
    "date:inception_lower": "1980-01-01",
    "date:inception_upper": "1980-01-01",
    "iso:country": "GB",
    "wof:name": "DD11 5SS",
    "wof:placetype": "postalcode"
  },
  "geometry": {"coordinates":[-2.514176,56.644946],"type":"Point"}
}
