{
  "type": "Feature",
  "properties": {
    "iso:country":"GB",
    "wof:name":"TQ6 9AT",
    "wof:placetype":"postalcode"
},
  "geometry": {"coordinates":[-3.57780181342371,50.34825562679791],"type":"Point"}
}