{
  "type": "Feature",
  "properties": {
    "iso:country": "GB",
    "wof:name": "TQ6 9AT",
    "wof:placetype": "postalcode"
  },
  "geometry": {"coordinates":[-3.577802,50.348256],"type":"Point"}
}
