{
  "type": "Feature",
  "properties": {
    "iso:country":"GB",
    "wof:name":"MK18 3RA",
    "wof:placetype":"postalcode"
},
  "geometry": {"coordinates":[-0.87853522298095,51.89853476929753],"type":"Point"}
}