{
  "type": "Feature",
  "properties": {
    "date:inception_lower":"1995-01-01",
    "date:inception_upper":"1995-01-31",
    "iso:country":"GB",
    "wof:name":"MK18 3RA",
    "wof:placetype":"postalcode"
},
  "geometry": {"coordinates":[-0.878535,51.898535],"type":"Point"}
}