{
  "type": "Feature",
  "properties": {
    "iso:country": "GB",
    "wof:name": "MK18 3RA",
    "wof:placetype": "postalcode"
  },
  "geometry": {"coordinates":[-0.878535,51.898535],"type":"Point"}
}
