{
  "type": "Feature",
  "properties": {
    "date:inception_lower": "1995-01-01",
    "date:inception_upper": "1995-01-01",
    "iso:country": "GB",
    "wof:name": "MK18 3RA",
    "wof:placetype": "postalcode"
  },
  "geometry": {"coordinates":[-0.878209,51.898539],"type":"Point"}
}
