{
  "type": "Feature",
  "properties": {
    "date:inception_lower": "2018-05-01",
    "date:inception_upper": "2018-05-01",
    "iso:country": "GB",
    "wof:name": "IV2 6FF",
    "wof:placetype": "postalcode"
  },
  "geometry": {"coordinates":[-4.209783,57.447861],"type":"Point"}
}
