{
  "type": "Feature",
  "properties": {
    "iso:country":"GB",
    "wof:name":"G71 6AR",
    "wof:placetype":"postalcode"
},
  "geometry": {"coordinates":[-4.08224353666245,55.83249007275363],"type":"Point"}
}