{
  "type": "Feature",
  "properties": {
    "iso:country":"GB",
    "wof:name":"IP7 7HJ",
    "wof:placetype":"postalcode"
},
  "geometry": {"coordinates":[0.9275248128055,52.10211230339308],"type":"Point"}
}