{
  "type": "Feature",
  "properties": {
    "iso:country":"GB",
    "wof:name":"YO23 7DG",
    "wof:placetype":"postalcode"
},
  "geometry": {"coordinates":[-1.16102351962345,53.87331306019272],"type":"Point"}
}