{
  "type": "Feature",
  "properties": {
    "date:inception_lower": "1998-06-01",
    "date:inception_upper": "1998-06-01",
    "iso:country": "GB",
    "wof:name": "YO23 7DG",
    "wof:placetype": "postalcode"
  },
  "geometry": {"coordinates":[-1.161023,53.873313],"type":"Point"}
}
