{
  "type": "Feature",
  "properties": {
    "iso:country":"GB",
    "wof:name":"WC1H 9SR",
    "wof:placetype":"postalcode"
},
  "geometry": {"coordinates":[-0.12537901759184,51.52907741110608],"type":"Point"}
}