{
  "type": "Feature",
  "properties": {
    "date:inception_lower": "1980-01-01",
    "date:inception_upper": "1980-01-01",
    "iso:country": "GB",
    "wof:name": "GL53 7AW",
    "wof:placetype": "postalcode"
  },
  "geometry": {"coordinates":[-2.068945,51.890612],"type":"Point"}
}
