{
  "type": "Feature",
  "properties": {
    "date:inception_lower": "2021-04-01",
    "date:inception_upper": "2021-04-01",
    "iso:country": "GB",
    "wof:name": "ML9 3FU",
    "wof:placetype": "postalcode"
  },
  "geometry": {"coordinates":[-3.99549,55.691778],"type":"Point"}
}
