{
  "type": "Feature",
  "properties": {
    "iso:country": "GB",
    "wof:name": "TR20 8NE",
    "wof:placetype": "postalcode"
  },
  "geometry": {"coordinates":[-5.508711,50.174506],"type":"Point"}
}
