{
  "type": "Feature",
  "properties": {
    "iso:country":"GB",
    "wof:name":"TR20 8NE",
    "wof:placetype":"postalcode"
},
  "geometry": {"coordinates":[-5.50871593535325,50.17454028690158],"type":"Point"}
}