{
  "type": "Feature",
  "properties": {
    "date:inception_lower": "1980-01-01",
    "date:inception_upper": "1980-01-01",
    "iso:country": "GB",
    "wof:name": "EX32 0PZ",
    "wof:placetype": "postalcode"
  },
  "geometry": {"coordinates":[-3.96681,51.051967],"type":"Point"}
}
