{
  "type": "Feature",
  "properties": {
    "iso:country": "GB",
    "wof:name": "EX32 0PZ",
    "wof:placetype": "postalcode"
  },
  "geometry": {"coordinates":[-3.96681,51.051967],"type":"Point"}
}
