{
  "type": "Feature",
  "properties": {
    "date:inception_lower":"1998-12-01",
    "date:inception_upper":"1998-12-31",
    "iso:country":"GB",
    "wof:name":"RG18 3LG",
    "wof:placetype":"postalcode"
},
  "geometry": {"coordinates":[-1.259206,51.412288],"type":"Point"}
}