{
  "type": "Feature",
  "properties": {
    "iso:country":"GB",
    "wof:name":"G76 7TU",
    "wof:placetype":"postalcode"
},
  "geometry": {"coordinates":[-4.27821956702475,55.78046435958375],"type":"Point"}
}