{
  "type": "Feature",
  "properties": {
    "date:inception_lower": "2010-02-01",
    "date:inception_upper": "2010-02-01",
    "iso:country": "GB",
    "wof:name": "SW1Y 5DG",
    "wof:placetype": "postalcode"
  },
  "geometry": {"coordinates":[-0.132996,51.505692],"type":"Point"}
}
