{
  "type": "Feature",
  "properties": {
    "iso:country":"GB",
    "wof:name":"SW1Y 5DG",
    "wof:placetype":"postalcode"
},
  "geometry": {"coordinates":[-0.132996216195,51.50569247463581],"type":"Point"}
}