{
  "type": "Feature",
  "properties": {
    "date:inception_lower":"2016-07-01",
    "date:inception_upper":"2016-07-31",
    "iso:country":"GB",
    "wof:name":"TQ9 5HY",
    "wof:placetype":"postalcode"
},
  "geometry": {"coordinates":[-3.676557,50.426617],"type":"Point"}
}