{
  "type": "Feature",
  "properties": {
    "iso:country": "GB",
    "wof:name": "SO40 2PJ",
    "wof:placetype": "postalcode"
  },
  "geometry": {"coordinates":[-1.553617,50.935726],"type":"Point"}
}
