{
  "type": "Feature",
  "properties": {
    "iso:country":"GB",
    "wof:name":"SO40 2PJ",
    "wof:placetype":"postalcode"
},
  "geometry": {"coordinates":[-1.55361738263679,50.93572636544346],"type":"Point"}
}