{
  "type": "Feature",
  "properties": {
    "iso:country":"GB",
    "wof:name":"BS5 8NL",
    "wof:placetype":"postalcode"
},
  "geometry": {"coordinates":[-2.52290446686697,51.45790547630472],"type":"Point"}
}