{
  "type": "Feature",
  "properties": {
    "date:inception_lower":"2004-06-01",
    "date:inception_upper":"2004-06-30",
    "iso:country":"GB",
    "wof:name":"BS5 8NL",
    "wof:placetype":"postalcode"
},
  "geometry": {"coordinates":[-2.522904,51.457905],"type":"Point"}
}