{
  "type": "Feature",
  "properties": {
    "iso:country":"GB",
    "wof:name":"NP44 4UX",
    "wof:placetype":"postalcode"
},
  "geometry": {"coordinates":[-3.04994967451341,51.65118909292543],"type":"Point"}
}