{
  "type": "Feature",
  "properties": {
    "date:inception_lower": "1997-06-01",
    "date:inception_upper": "1997-06-01",
    "iso:country": "GB",
    "wof:name": "S32 5QX",
    "wof:placetype": "postalcode"
  },
  "geometry": {"coordinates":[-1.680069,53.28497],"type":"Point"}
}
