{
  "type": "Feature",
  "properties": {
    "iso:country":"GB",
    "wof:name":"S32 5QX",
    "wof:placetype":"postalcode"
},
  "geometry": {"coordinates":[-1.68006911570911,53.28497004234889],"type":"Point"}
}