{
  "type": "Feature",
  "properties": {
    "iso:country":"GB",
    "wof:name":"ML5 4AL",
    "wof:placetype":"postalcode"
},
  "geometry": {"coordinates":[-4.02805579738307,55.85442521794023],"type":"Point"}
}