{
  "type": "Feature",
  "properties": {
    "iso:country":"GB",
    "wof:name":"BA2 7BA",
    "wof:placetype":"postalcode"
},
  "geometry": {"coordinates":[-2.3270301323028,51.37532639047494],"type":"Point"}
}