{
  "type": "Feature",
  "properties": {
    "iso:country":"GB",
    "wof:name":"OX9 3TG",
    "wof:placetype":"postalcode"
},
  "geometry": {"coordinates":[-0.97217163500581,51.75146472829722],"type":"Point"}
}