{
  "type": "Feature",
  "properties": {
    "iso:country": "GB",
    "wof:name": "OX9 3TG",
    "wof:placetype": "postalcode"
  },
  "geometry": {"coordinates":[-0.972172,51.751465],"type":"Point"}
}
