{
  "type": "Feature",
  "properties": {
    "iso:country":"GB",
    "wof:name":"BA14 0LE",
    "wof:placetype":"postalcode"
},
  "geometry": {"coordinates":[-2.21332420393425,51.30314247985451],"type":"Point"}
}