{
  "type": "Feature",
  "properties": {
    "iso:country": "GB",
    "wof:name": "BA14 0LE",
    "wof:placetype": "postalcode"
  },
  "geometry": {"coordinates":[-2.213324,51.303142],"type":"Point"}
}
