{
  "type": "Feature",
  "properties": {
    "iso:country":"GB",
    "wof:name":"NP44 5LE",
    "wof:placetype":"postalcode"
},
  "geometry": {"coordinates":[-3.03790102837891,51.66096215467295],"type":"Point"}
}