{
  "type": "Feature",
  "properties": {
    "iso:country": "GB",
    "wof:name": "CH41 1LX",
    "wof:placetype": "postalcode"
  },
  "geometry": {"coordinates":[-3.015377,53.395279],"type":"Point"}
}
