{
  "type": "Feature",
  "properties": {
    "iso:country":"GB",
    "wof:name":"IP33 2EZ",
    "wof:placetype":"postalcode"
},
  "geometry": {"coordinates":[0.68844600605194,52.23496026124737],"type":"Point"}
}