{
  "type": "Feature",
  "properties": {
    "iso:country":"GB",
    "wof:name":"G74 1QY",
    "wof:placetype":"postalcode"
},
  "geometry": {"coordinates":[-4.19802842100784,55.76647560505619],"type":"Point"}
}