{
  "type": "Feature",
  "properties": {
    "date:inception_lower": "1980-01-01",
    "date:inception_upper": "1980-01-01",
    "iso:country": "GB",
    "wof:name": "ST11 9PX",
    "wof:placetype": "postalcode"
  },
  "geometry": {"coordinates":[-2.053918,52.968354],"type":"Point"}
}
