{
  "type": "Feature",
  "properties": {
    "iso:country":"GB",
    "wof:name":"ST11 9PX",
    "wof:placetype":"postalcode"
},
  "geometry": {"coordinates":[-2.05391824119859,52.9683540506418],"type":"Point"}
}