{
  "type": "Feature",
  "properties": {
    "iso:country": "GB",
    "wof:name": "ST11 9PX",
    "wof:placetype": "postalcode"
  },
  "geometry": {"coordinates":[-2.053918,52.968354],"type":"Point"}
}
