{
  "type": "Feature",
  "properties": {
    "iso:country":"GB",
    "wof:name":"WS8 7SB",
    "wof:placetype":"postalcode"
},
  "geometry": {"coordinates":[-1.93939339118984,52.64315730689348],"type":"Point"}
}