{
  "type": "Feature",
  "properties": {
    "iso:country": "GB",
    "wof:name": "NG7 1JN",
    "wof:placetype": "postalcode"
  },
  "geometry": {"coordinates":[-1.169509,52.950176],"type":"Point"}
}
