{
  "type": "Feature",
  "properties": {
    "iso:country":"GB",
    "wof:name":"NG7 1JN",
    "wof:placetype":"postalcode"
},
  "geometry": {"coordinates":[-1.16950948816325,52.95017613839875],"type":"Point"}
}