{
  "type": "Feature",
  "properties": {
    "iso:country": "GB",
    "wof:name": "G46 6XW",
    "wof:placetype": "postalcode"
  },
  "geometry": {"coordinates":[-4.294944,55.804738],"type":"Point"}
}
