{
  "type": "Feature",
  "properties": {
    "iso:country":"GB",
    "wof:name":"LN1 3UR",
    "wof:placetype":"postalcode"
},
  "geometry": {"coordinates":[-0.55002129804317,53.24772996438386],"type":"Point"}
}