{
  "type": "Feature",
  "properties": {
    "iso:country": "GB",
    "wof:name": "KY11 8ZX",
    "wof:placetype": "postalcode"
  },
  "geometry": {"coordinates":[-3.390689,56.055894],"type":"Point"}
}
