{
  "type": "Feature",
  "properties": {
    "date:inception_lower": "2019-02-01",
    "date:inception_upper": "2019-02-01",
    "iso:country": "GB",
    "wof:name": "KY11 8ZX",
    "wof:placetype": "postalcode"
  },
  "geometry": {"coordinates":[-3.389199,56.055533],"type":"Point"}
}
