{
  "type": "Feature",
  "properties": {
    "iso:country":"GB",
    "wof:name":"SY10 9BL",
    "wof:placetype":"postalcode"
},
  "geometry": {"coordinates":[-3.15284445787146,52.83732969054734],"type":"Point"}
}