{
  "type": "Feature",
  "properties": {
    "iso:country":"GB",
    "wof:name":"E2 6QE",
    "wof:placetype":"postalcode"
},
  "geometry": {"coordinates":[-0.06135854945213,51.53029394482433],"type":"Point"}
}