{
  "type": "Feature",
  "properties": {
    "date:inception_lower":"1980-01-01",
    "date:inception_upper":"1980-01-31",
    "iso:country":"GB",
    "wof:name":"E2 6QE",
    "wof:placetype":"postalcode"
},
  "geometry": {"coordinates":[-0.061385,51.530348],"type":"Point"}
}