{
  "type": "Feature",
  "properties": {
    "iso:country":"GB",
    "wof:name":"SK8 7DH",
    "wof:placetype":"postalcode"
},
  "geometry": {"coordinates":[-2.18097392311309,53.37037453472824],"type":"Point"}
}