{
  "type": "Feature",
  "properties": {
    "iso:country": "GB",
    "wof:name": "CM17 9RU",
    "wof:placetype": "postalcode"
  },
  "geometry": {"coordinates":[0.13785,51.768076],"type":"Point"}
}
