{
  "type": "Feature",
  "properties": {
    "iso:country":"GB",
    "wof:name":"CM17 9RU",
    "wof:placetype":"postalcode"
},
  "geometry": {"coordinates":[0.13782226457512,51.76807012801412],"type":"Point"}
}