{
  "type": "Feature",
  "properties": {
    "iso:country":"GB",
    "wof:name":"SW8 3TH",
    "wof:placetype":"postalcode"
},
  "geometry": {"coordinates":[-0.14793164870997,51.46961743152336],"type":"Point"}
}