{
  "type": "Feature",
  "properties": {
    "iso:country":"GB",
    "wof:name":"SW19 4NL",
    "wof:placetype":"postalcode"
},
  "geometry": {"coordinates":[-0.21934145719952,51.41943936843155],"type":"Point"}
}