{
  "type": "Feature",
  "properties": {
    "iso:country":"GB",
    "wof:name":"WF6 1AJ",
    "wof:placetype":"postalcode"
},
  "geometry": {"coordinates":[-1.42495352695234,53.69776539927449],"type":"Point"}
}