{
  "type": "Feature",
  "properties": {
    "iso:country": "GB",
    "wof:name": "CF35 5PH",
    "wof:placetype": "postalcode"
  },
  "geometry": {"coordinates":[-3.497978,51.521772],"type":"Point"}
}
