{
  "type": "Feature",
  "properties": {
    "iso:country":"GB",
    "wof:name":"CF35 5PH",
    "wof:placetype":"postalcode"
},
  "geometry": {"coordinates":[-3.49797707349761,51.52172475734622],"type":"Point"}
}