{
  "type": "Feature",
  "properties": {
    "date:inception_lower":"1992-01-01",
    "date:inception_upper":"1992-01-31",
    "iso:country":"GB",
    "wof:name":"ST7 2YJ",
    "wof:placetype":"postalcode"
},
  "geometry": {"coordinates":[-2.322776,53.09578],"type":"Point"}
}