{
  "type": "Feature",
  "properties": {
    "iso:country":"GB",
    "wof:name":"ST7 2YJ",
    "wof:placetype":"postalcode"
},
  "geometry": {"coordinates":[-2.32277630390692,53.09578024945728],"type":"Point"}
}