{
  "type": "Feature",
  "properties": {
    "iso:country": "GB",
    "wof:name": "ST7 2YJ",
    "wof:placetype": "postalcode"
  },
  "geometry": {"coordinates":[-2.322776,53.09578],"type":"Point"}
}
