{
  "type": "Feature",
  "properties": {
    "iso:country": "GB",
    "wof:name": "HU15 1XU",
    "wof:placetype": "postalcode"
  },
  "geometry": {"coordinates":[-0.549462,53.729127],"type":"Point"}
}
