{
  "type": "Feature",
  "properties": {
    "iso:country":"GB",
    "wof:name":"NP44 5UU",
    "wof:placetype":"postalcode"
},
  "geometry": {"coordinates":[-3.05052342873998,51.66037334527626],"type":"Point"}
}