{
  "type": "Feature",
  "properties": {
    "date:inception_lower": "1980-01-01",
    "date:inception_upper": "1980-01-01",
    "iso:country": "GB",
    "wof:name": "NP44 5UU",
    "wof:placetype": "postalcode"
  },
  "geometry": {"coordinates":[-3.050523,51.660373],"type":"Point"}
}
