{
  "type": "Feature",
  "properties": {
    "iso:country":"GB",
    "wof:name":"SS1 2DD",
    "wof:placetype":"postalcode"
},
  "geometry": {"coordinates":[0.71710483008657,51.53704631752043],"type":"Point"}
}