{
  "type": "Feature",
  "properties": {
    "iso:country":"GB",
    "wof:name":"B91 3GX",
    "wof:placetype":"postalcode"
},
  "geometry": {"coordinates":[-1.77561847129319,52.40486301068609],"type":"Point"}
}