{
  "type": "Feature",
  "properties": {
    "date:inception_lower": "1980-01-01",
    "date:inception_upper": "1980-01-01",
    "iso:country": "GB",
    "wof:name": "CV21 4HE",
    "wof:placetype": "postalcode"
  },
  "geometry": {"coordinates":[-1.214309,52.357128],"type":"Point"}
}
