{
  "type": "Feature",
  "properties": {
    "iso:country":"GB",
    "wof:name":"BD4 0TG",
    "wof:placetype":"postalcode"
},
  "geometry": {"coordinates":[-1.70096120987502,53.77183585653457],"type":"Point"}
}