{
  "type": "Feature",
  "properties": {
    "iso:country":"GB",
    "wof:name":"SY11 3DF",
    "wof:placetype":"postalcode"
},
  "geometry": {"coordinates":[-3.00609648633779,52.92519046567553],"type":"Point"}
}