{
  "type": "Feature",
  "properties": {
    "iso:country":"GB",
    "wof:name":"PR8 5AQ",
    "wof:placetype":"postalcode"
},
  "geometry": {"coordinates":[-3.0056065225632,53.63994723921886],"type":"Point"}
}