{
  "type": "Feature",
  "properties": {
    "iso:country":"GB",
    "wof:name":"BA2 1BP",
    "wof:placetype":"postalcode"
},
  "geometry": {"coordinates":[-2.3888313608982,51.37972324333953],"type":"Point"}
}