{
  "type": "Feature",
  "properties": {
    "iso:country": "GB",
    "wof:name": "BA2 1BP",
    "wof:placetype": "postalcode"
  },
  "geometry": {"coordinates":[-2.388831,51.379723],"type":"Point"}
}
