{
  "type": "Feature",
  "properties": {
    "iso:country":"GB",
    "wof:name":"N8 8SG",
    "wof:placetype":"postalcode"
},
  "geometry": {"coordinates":[-0.1206897664938,51.58201299567895],"type":"Point"}
}