{
  "type": "Feature",
  "properties": {
    "iso:country":"GB",
    "wof:name":"SK7 1BW",
    "wof:placetype":"postalcode"
},
  "geometry": {"coordinates":[-2.17306740155964,53.35529437513611],"type":"Point"}
}