{
  "type": "Feature",
  "properties": {
    "date:inception_lower": "2001-06-01",
    "date:inception_upper": "2001-06-01",
    "iso:country": "GB",
    "wof:name": "PR25 4NU",
    "wof:placetype": "postalcode"
  },
  "geometry": {"coordinates":[-2.68416,53.699697],"type":"Point"}
}
