{
  "type": "Feature",
  "properties": {
    "iso:country":"GB",
    "wof:name":"PR25 4NU",
    "wof:placetype":"postalcode"
},
  "geometry": {"coordinates":[-2.68415978003415,53.69969691260164],"type":"Point"}
}