{
  "type": "Feature",
  "properties": {
    "date:inception_lower":"1993-01-01",
    "date:inception_upper":"1993-01-31",
    "iso:country":"GB",
    "wof:name":"PE30 4JH",
    "wof:placetype":"postalcode"
},
  "geometry": {"coordinates":[0.416537,52.740888],"type":"Point"}
}