{
  "type": "Feature",
  "properties": {
    "iso:country": "GB",
    "wof:name": "PE30 4JH",
    "wof:placetype": "postalcode"
  },
  "geometry": {"coordinates":[0.416537,52.740888],"type":"Point"}
}
