{
  "type": "Feature",
  "properties": {
    "date:inception_lower": "1980-01-01",
    "date:inception_upper": "1980-01-01",
    "iso:country": "GB",
    "wof:name": "EX13 5PF",
    "wof:placetype": "postalcode"
  },
  "geometry": {"coordinates":[-3.004531,50.779225],"type":"Point"}
}
