{
  "type": "Feature",
  "properties": {
    "iso:country":"GB",
    "wof:name":"EX13 5PF",
    "wof:placetype":"postalcode"
},
  "geometry": {"coordinates":[-3.00452375965261,50.7792352268436],"type":"Point"}
}