{
  "type": "Feature",
  "properties": {
    "date:inception_lower": "1992-01-01",
    "date:inception_upper": "1992-01-01",
    "iso:country": "GB",
    "wof:name": "DN19 7HH",
    "wof:placetype": "postalcode"
  },
  "geometry": {"coordinates":[-0.382389,53.67235],"type":"Point"}
}
