{
  "type": "Feature",
  "properties": {
    "iso:country":"GB",
    "wof:name":"CO10 1YA",
    "wof:placetype":"postalcode"
},
  "geometry": {"coordinates":[0.72631783125789,52.05259477494692],"type":"Point"}
}