{
  "type": "Feature",
  "properties": {
    "date:inception_lower":"2006-03-01",
    "date:inception_upper":"2006-03-31",
    "iso:country":"GB",
    "wof:name":"CO10 1YA",
    "wof:placetype":"postalcode"
},
  "geometry": {"coordinates":[0.726318,52.052595],"type":"Point"}
}