{
  "type": "Feature",
  "properties": {
    "iso:country":"GB",
    "wof:name":"IG10 3QF",
    "wof:placetype":"postalcode"
},
  "geometry": {"coordinates":[0.07115236150458,51.64260454030818],"type":"Point"}
}