{
  "type": "Feature",
  "properties": {
    "iso:country":"GB",
    "wof:name":"GU27 1QD",
    "wof:placetype":"postalcode"
},
  "geometry": {"coordinates":[-0.75493851520146,51.09527373210421],"type":"Point"}
}