{
  "type": "Feature",
  "properties": {
    "iso:country":"GB",
    "wof:name":"S62 7ND",
    "wof:placetype":"postalcode"
},
  "geometry": {"coordinates":[-1.36534676043576,53.47432661354933],"type":"Point"}
}