{
  "type": "Feature",
  "properties": {
    "date:inception_lower": "1980-01-01",
    "date:inception_upper": "1980-01-01",
    "iso:country": "GB",
    "wof:name": "DH4 7RQ",
    "wof:placetype": "postalcode"
  },
  "geometry": {"coordinates":[-1.489452,54.872909],"type":"Point"}
}
