{
  "type": "Feature",
  "properties": {
    "iso:country":"GB",
    "wof:name":"S5 6AZ",
    "wof:placetype":"postalcode"
},
  "geometry": {"coordinates":[-1.43806105917954,53.41805324974051],"type":"Point"}
}