{
  "type": "Feature",
  "properties": {
    "iso:country":"GB",
    "wof:name":"AB15 9TE",
    "wof:placetype":"postalcode"
},
  "geometry": {"coordinates":[-2.19140635827735,57.11508303468684],"type":"Point"}
}