{
  "type": "Feature",
  "properties": {
    "date:inception_lower":"1996-06-01",
    "date:inception_upper":"1996-06-30",
    "iso:country":"GB",
    "wof:name":"AB15 9TE",
    "wof:placetype":"postalcode"
},
  "geometry": {"coordinates":[-2.191406,57.115083],"type":"Point"}
}