{
  "type": "Feature",
  "properties": {
    "iso:country":"GB",
    "wof:name":"EN2 9JF",
    "wof:placetype":"postalcode"
},
  "geometry": {"coordinates":[-0.09639645223394,51.67350579435216],"type":"Point"}
}