{
  "type": "Feature",
  "properties": {
    "date:inception_lower":"1980-01-01",
    "date:inception_upper":"1980-01-31",
    "iso:country":"GB",
    "wof:name":"BH18 9BP",
    "wof:placetype":"postalcode"
},
  "geometry": {"coordinates":[-2.012141,50.761144],"type":"Point"}
}