{
  "type": "Feature",
  "properties": {
    "iso:country":"GB",
    "wof:name":"BH18 9BP",
    "wof:placetype":"postalcode"
},
  "geometry": {"coordinates":[-2.01214117387783,50.76114367194018],"type":"Point"}
}