{
  "type": "Feature",
  "properties": {
    "date:inception_lower": "2005-03-01",
    "date:inception_upper": "2005-03-01",
    "iso:country": "GB",
    "wof:name": "IP16 4NS",
    "wof:placetype": "postalcode"
  },
  "geometry": {"coordinates":[1.616662,52.181137],"type":"Point"}
}
