{
  "type": "Feature",
  "properties": {
    "iso:country":"GB",
    "wof:name":"IP16 4NS",
    "wof:placetype":"postalcode"
},
  "geometry": {"coordinates":[1.61666231815973,52.18113682290024],"type":"Point"}
}