{
  "type": "Feature",
  "properties": {
    "iso:country": "GB",
    "wof:name": "IP16 4NS",
    "wof:placetype": "postalcode"
  },
  "geometry": {"coordinates":[1.616662,52.181137],"type":"Point"}
}
