{
  "type": "Feature",
  "properties": {
    "iso:country": "GB",
    "wof:name": "RG8 8AT",
    "wof:placetype": "postalcode"
  },
  "geometry": {"coordinates":[-1.050074,51.48258],"type":"Point"}
}
