{
  "type": "Feature",
  "properties": {
    "iso:country": "GB",
    "wof:name": "EX4 7AJ",
    "wof:placetype": "postalcode"
  },
  "geometry": {"coordinates":[-3.515184,50.733527],"type":"Point"}
}
