{
  "type": "Feature",
  "properties": {
    "iso:country":"GB",
    "wof:name":"EX4 7AJ",
    "wof:placetype":"postalcode"
},
  "geometry": {"coordinates":[-3.51518363500952,50.73352695341367],"type":"Point"}
}