{
  "type": "Feature",
  "properties": {
    "date:inception_lower": "1980-01-01",
    "date:inception_upper": "1980-01-01",
    "iso:country": "GB",
    "wof:name": "PE23 4JB",
    "wof:placetype": "postalcode"
  },
  "geometry": {"coordinates":[0.002822,53.191256],"type":"Point"}
}
