{
  "type": "Feature",
  "properties": {
    "iso:country":"GB",
    "wof:name":"PE23 4JB",
    "wof:placetype":"postalcode"
},
  "geometry": {"coordinates":[0.00282148198364,53.19125579863268],"type":"Point"}
}