{
  "type": "Feature",
  "properties": {
    "date:inception_lower": "2020-10-01",
    "date:inception_upper": "2020-10-01",
    "iso:country": "GB",
    "wof:name": "WR9 7TU",
    "wof:placetype": "postalcode"
  },
  "geometry": {"coordinates":[-2.148924,52.248116],"type":"Point"}
}
