{
  "type": "Feature",
  "properties": {
    "iso:country": "GB",
    "wof:name": "CW7 2BY",
    "wof:placetype": "postalcode"
  },
  "geometry": {"coordinates":[-2.534115,53.196892],"type":"Point"}
}
