{
  "type": "Feature",
  "properties": {
    "iso:country":"GB",
    "wof:name":"BA2 3PJ",
    "wof:placetype":"postalcode"
},
  "geometry": {"coordinates":[-2.37870604646019,51.37678017473475],"type":"Point"}
}