{
  "type": "Feature",
  "properties": {
    "iso:country": "GB",
    "wof:name": "RG30 1LB",
    "wof:placetype": "postalcode"
  },
  "geometry": {"coordinates":[-1.00445,51.460774],"type":"Point"}
}
