{
  "type": "Feature",
  "properties": {
    "iso:country":"GB",
    "wof:name":"RG30 1LB",
    "wof:placetype":"postalcode"
},
  "geometry": {"coordinates":[-1.00445041419905,51.4607740457705],"type":"Point"}
}