{
  "type": "Feature",
  "properties": {
    "iso:country":"GB",
    "wof:name":"PE25 2NF",
    "wof:placetype":"postalcode"
},
  "geometry": {"coordinates":[0.32383072469873,53.15611474578417],"type":"Point"}
}