{
  "type": "Feature",
  "properties": {
    "iso:country": "GB",
    "wof:name": "PE25 2NF",
    "wof:placetype": "postalcode"
  },
  "geometry": {"coordinates":[0.323877,53.15615],"type":"Point"}
}
