{
  "type": "Feature",
  "properties": {
    "date:inception_lower": "1994-05-01",
    "date:inception_upper": "1994-05-01",
    "iso:country": "GB",
    "wof:name": "PE25 2NF",
    "wof:placetype": "postalcode"
  },
  "geometry": {"coordinates":[0.323877,53.15615],"type":"Point"}
}
