{
  "type": "Feature",
  "properties": {
    "iso:country": "GB",
    "wof:name": "CF83 8QH",
    "wof:placetype": "postalcode"
  },
  "geometry": {"coordinates":[-3.146413,51.595914],"type":"Point"}
}
