{
  "type": "Feature",
  "properties": {
    "iso:country":"GB",
    "wof:name":"S61 3RG",
    "wof:placetype":"postalcode"
},
  "geometry": {"coordinates":[-1.38258772644524,53.44281290770546],"type":"Point"}
}