{
  "type": "Feature",
  "properties": {
    "iso:country": "GB",
    "wof:name": "S61 3RG",
    "wof:placetype": "postalcode"
  },
  "geometry": {"coordinates":[-1.382588,53.442813],"type":"Point"}
}
