{
  "type": "Feature",
  "properties": {
    "iso:country":"GB",
    "wof:name":"AL10 9JD",
    "wof:placetype":"postalcode"
},
  "geometry": {"coordinates":[-0.23659113831773,51.75372802585741],"type":"Point"}
}