{
  "type": "Feature",
  "properties": {
    "iso:country": "GB",
    "wof:name": "AL10 9JD",
    "wof:placetype": "postalcode"
  },
  "geometry": {"coordinates":[-0.236453,51.753705],"type":"Point"}
}
