{
  "type": "Feature",
  "properties": {
    "date:inception_lower": "1981-06-01",
    "date:inception_upper": "1981-06-01",
    "iso:country": "GB",
    "wof:name": "DN6 9DB",
    "wof:placetype": "postalcode"
  },
  "geometry": {"coordinates":[-1.184091,53.61833],"type":"Point"}
}
