{
  "type": "Feature",
  "properties": {
    "iso:country":"GB",
    "wof:name":"DN6 9DB",
    "wof:placetype":"postalcode"
},
  "geometry": {"coordinates":[-1.18409150344123,53.6183299629801],"type":"Point"}
}