{
  "type": "Feature",
  "properties": {
    "iso:country":"GB",
    "wof:name":"YO41 1LW",
    "wof:placetype":"postalcode"
},
  "geometry": {"coordinates":[-0.97297000866774,54.01976104647029],"type":"Point"}
}