{
  "type": "Feature",
  "properties": {
    "date:inception_lower": "1998-06-01",
    "date:inception_upper": "1998-06-01",
    "iso:country": "GB",
    "wof:name": "YO41 1LW",
    "wof:placetype": "postalcode"
  },
  "geometry": {"coordinates":[-0.97297,54.019761],"type":"Point"}
}
