{
  "type": "Feature",
  "properties": {
    "iso:country":"GB",
    "wof:name":"PE20 1PZ",
    "wof:placetype":"postalcode"
},
  "geometry": {"coordinates":[-0.06188184891795,52.92080393755514],"type":"Point"}
}