{
  "type": "Feature",
  "properties": {
    "iso:country":"GB",
    "wof:name":"SS5 4RN",
    "wof:placetype":"postalcode"
},
  "geometry": {"coordinates":[0.64352622293118,51.60045070830569],"type":"Point"}
}