{
  "type": "Feature",
  "properties": {
    "iso:country":"GB",
    "wof:name":"OL2 8SU",
    "wof:placetype":"postalcode"
},
  "geometry": {"coordinates":[-2.09863953826,53.56965529589151],"type":"Point"}
}