{
  "type": "Feature",
  "properties": {
    "iso:country":"GB",
    "wof:name":"KA23 9JY",
    "wof:placetype":"postalcode"
},
  "geometry": {"coordinates":[-4.86073763997119,55.69157550634051],"type":"Point"}
}