{
  "type": "Feature",
  "properties": {
    "date:inception_lower": "1980-01-01",
    "date:inception_upper": "1980-01-01",
    "iso:country": "GB",
    "wof:name": "NG12 3BS",
    "wof:placetype": "postalcode"
  },
  "geometry": {"coordinates":[-0.98759,52.912847],"type":"Point"}
}
