{
  "type": "Feature",
  "properties": {
    "iso:country":"GB",
    "wof:name":"NG12 3BS",
    "wof:placetype":"postalcode"
},
  "geometry": {"coordinates":[-0.98758675574263,52.91311311156799],"type":"Point"}
}