{
  "type": "Feature",
  "properties": {
    "date:inception_lower": "1990-07-01",
    "date:inception_upper": "1990-07-01",
    "iso:country": "GB",
    "wof:name": "TW18 4QJ",
    "wof:placetype": "postalcode"
  },
  "geometry": {"coordinates":[-0.503931,51.434532],"type":"Point"}
}
