{
  "type": "Feature",
  "properties": {
    "date:inception_lower": "1991-09-01",
    "date:inception_upper": "1991-09-01",
    "iso:country": "GB",
    "wof:name": "IP31 2XD",
    "wof:placetype": "postalcode"
  },
  "geometry": {"coordinates":[0.884002,52.325039],"type":"Point"}
}
