{
  "type": "Feature",
  "properties": {
    "iso:country": "GB",
    "wof:name": "TW3 3TG",
    "wof:placetype": "postalcode"
  },
  "geometry": {"coordinates":[-0.37221,51.45952],"type":"Point"}
}
