{
  "type": "Feature",
  "properties": {
    "iso:country":"GB",
    "wof:name":"PE9 3NA",
    "wof:placetype":"postalcode"
},
  "geometry": {"coordinates":[-0.51230179457638,52.62410825986451],"type":"Point"}
}