{
  "type": "Feature",
  "properties": {
    "iso:country": "GB",
    "wof:name": "S3 9GT",
    "wof:placetype": "postalcode"
  },
  "geometry": {"coordinates":[-1.467621,53.395627],"type":"Point"}
}
