{
  "type": "Feature",
  "properties": {
    "date:inception_lower": "2015-08-01",
    "date:inception_upper": "2015-08-01",
    "iso:country": "GB",
    "wof:name": "SN1 3FF",
    "wof:placetype": "postalcode"
  },
  "geometry": {"coordinates":[-1.776039,51.553091],"type":"Point"}
}
