{
  "type": "Feature",
  "properties": {
    "iso:country":"GB",
    "wof:name":"SN1 3FF",
    "wof:placetype":"postalcode"
},
  "geometry": {"coordinates":[-1.77613673061254,51.55308999939713],"type":"Point"}
}