{
  "type": "Feature",
  "properties": {
    "iso:country": "GB",
    "wof:name": "MK10 7DZ",
    "wof:placetype": "postalcode"
  },
  "geometry": {"coordinates":[-0.685726,52.047333],"type":"Point"}
}
