{
  "type": "Feature",
  "properties": {
    "iso:country":"GB",
    "wof:name":"NR3 1RR",
    "wof:placetype":"postalcode"
},
  "geometry": {"coordinates":[1.29904867681415,52.63307968160291],"type":"Point"}
}