{
  "type": "Feature",
  "properties": {
    "iso:country":"GB",
    "wof:name":"LE2 6EL",
    "wof:placetype":"postalcode"
},
  "geometry": {"coordinates":[-1.11983970672537,52.60556391345319],"type":"Point"}
}