{
  "type": "Feature",
  "properties": {
    "iso:country":"GB",
    "wof:name":"SN16 9SS",
    "wof:placetype":"postalcode"
},
  "geometry": {"coordinates":[-2.04150391612049,51.64729073572376],"type":"Point"}
}