{
  "type": "Feature",
  "properties": {
    "iso:country":"GB",
    "wof:name":"SM6 9RQ",
    "wof:placetype":"postalcode"
},
  "geometry": {"coordinates":[-0.14253871952055,51.35343707261093],"type":"Point"}
}