{
  "type": "Feature",
  "properties": {
    "iso:country":"GB",
    "wof:name":"CW5 8BL",
    "wof:placetype":"postalcode"
},
  "geometry": {"coordinates":[-2.533018937507,53.0287467987857],"type":"Point"}
}