{
  "type": "Feature",
  "properties": {
    "iso:country":"GB",
    "wof:name":"OX28 1EJ",
    "wof:placetype":"postalcode"
},
  "geometry": {"coordinates":[-1.46587765526141,51.79346877133583],"type":"Point"}
}