{
  "type": "Feature",
  "properties": {
    "date:inception_lower": "1980-01-01",
    "date:inception_upper": "1980-01-01",
    "iso:country": "GB",
    "wof:name": "WA3 5BW",
    "wof:placetype": "postalcode"
  },
  "geometry": {"coordinates":[-2.456271,53.425548],"type":"Point"}
}
