{
  "type": "Feature",
  "properties": {
    "iso:country":"GB",
    "wof:name":"WA3 5BW",
    "wof:placetype":"postalcode"
},
  "geometry": {"coordinates":[-2.45627116052114,53.42554849483597],"type":"Point"}
}