{
  "type": "Feature",
  "properties": {
    "iso:country":"GB",
    "wof:name":"NE64 6RJ",
    "wof:placetype":"postalcode"
},
  "geometry": {"coordinates":[-1.51968241333263,55.1818706681178],"type":"Point"}
}