{
  "type": "Feature",
  "properties": {
    "iso:country":"GB",
    "wof:name":"NR2 4SX",
    "wof:placetype":"postalcode"
},
  "geometry": {"coordinates":[1.29801265399296,52.63050938862138],"type":"Point"}
}