{
  "type": "Feature",
  "properties": {
    "iso:country":"GB",
    "wof:name":"L5 6SP",
    "wof:placetype":"postalcode"
},
  "geometry": {"coordinates":[-2.95781300571645,53.42287504170215],"type":"Point"}
}