{
  "type": "Feature",
  "properties": {
    "iso:country":"GB",
    "wof:name":"CV3 2EP",
    "wof:placetype":"postalcode"
},
  "geometry": {"coordinates":[-1.44720745160064,52.39328381864885],"type":"Point"}
}