{
  "type": "Feature",
  "properties": {
    "iso:country":"GB",
    "wof:name":"MK40 3GD",
    "wof:placetype":"postalcode"
},
  "geometry": {"coordinates":[-0.45263546601713,52.14234671117758],"type":"Point"}
}