{
  "type": "Feature",
  "properties": {
    "date:inception_lower":"2002-07-01",
    "date:inception_upper":"2002-07-31",
    "iso:country":"GB",
    "wof:name":"MK40 3GD",
    "wof:placetype":"postalcode"
},
  "geometry": {"coordinates":[-0.452635,52.142347],"type":"Point"}
}