{
  "type": "Feature",
  "properties": {
    "date:inception_lower": "1980-01-01",
    "date:inception_upper": "1980-01-01",
    "iso:country": "GB",
    "wof:name": "PA23 7JB",
    "wof:placetype": "postalcode"
  },
  "geometry": {"coordinates":[-4.933587,55.945493],"type":"Point"}
}
