{
  "type": "Feature",
  "properties": {
    "iso:country":"GB",
    "wof:name":"EN11 9EZ",
    "wof:placetype":"postalcode"
},
  "geometry": {"coordinates":[-0.01235147964883,51.76660532627876],"type":"Point"}
}