{
  "type": "Feature",
  "properties": {
    "iso:country":"GB",
    "wof:name":"SA72 6JF",
    "wof:placetype":"postalcode"
},
  "geometry": {"coordinates":[-4.94483547578821,51.69392117013111],"type":"Point"}
}