{
  "type": "Feature",
  "properties": {
    "iso:country": "GB",
    "wof:name": "DE6 3LB",
    "wof:placetype": "postalcode"
  },
  "geometry": {"coordinates":[-1.623119,53.047118],"type":"Point"}
}
