{
  "type": "Feature",
  "properties": {
    "iso:country":"GB",
    "wof:name":"DE6 3LB",
    "wof:placetype":"postalcode"
},
  "geometry": {"coordinates":[-1.62311952017946,53.04711755662402],"type":"Point"}
}