{
  "type": "Feature",
  "properties": {
    "iso:country": "GB",
    "wof:name": "G21 1ER",
    "wof:placetype": "postalcode"
  },
  "geometry": {"coordinates":[-4.241152,55.878903],"type":"Point"}
}
