{
  "type": "Feature",
  "properties": {
    "iso:country":"GB",
    "wof:name":"PE12 6HW",
    "wof:placetype":"postalcode"
},
  "geometry": {"coordinates":[-0.10900648388914,52.80739956657856],"type":"Point"}
}