{
  "type": "Feature",
  "properties": {
    "iso:country": "GB",
    "wof:name": "PE12 6HW",
    "wof:placetype": "postalcode"
  },
  "geometry": {"coordinates":[-0.10901,52.80743],"type":"Point"}
}
