{
  "type": "Feature",
  "properties": {
    "date:inception_lower": "1980-01-01",
    "date:inception_upper": "1980-01-01",
    "iso:country": "GB",
    "wof:name": "PE12 6HW",
    "wof:placetype": "postalcode"
  },
  "geometry": {"coordinates":[-0.10901,52.80743],"type":"Point"}
}
