{
  "type": "Feature",
  "properties": {
    "iso:country": "GB",
    "wof:name": "HG4 3LR",
    "wof:placetype": "postalcode"
  },
  "geometry": {"coordinates":[-1.501662,54.11148],"type":"Point"}
}
