{
  "type": "Feature",
  "properties": {
    "iso:country":"GB",
    "wof:name":"HG4 3LR",
    "wof:placetype":"postalcode"
},
  "geometry": {"coordinates":[-1.50166234632784,54.11148027257011],"type":"Point"}
}