{
  "type": "Feature",
  "properties": {
    "iso:country": "GB",
    "wof:name": "TS23 3PL",
    "wof:placetype": "postalcode"
  },
  "geometry": {"coordinates":[-1.273205,54.620214],"type":"Point"}
}
