{
  "type": "Feature",
  "properties": {
    "iso:country":"GB",
    "wof:name":"TS23 3PL",
    "wof:placetype":"postalcode"
},
  "geometry": {"coordinates":[-1.27320501870159,54.62021439576773],"type":"Point"}
}