{
  "type": "Feature",
  "properties": {
    "iso:country":"GB",
    "wof:name":"BR1 4QL",
    "wof:placetype":"postalcode"
},
  "geometry": {"coordinates":[0.00659521316461,51.42471857250705],"type":"Point"}
}