{
  "type": "Feature",
  "properties": {
    "iso:country": "GB",
    "wof:name": "RH13 8HX",
    "wof:placetype": "postalcode"
  },
  "geometry": {"coordinates":[-0.306174,50.959509],"type":"Point"}
}
