{
  "type": "Feature",
  "properties": {
    "date:inception_lower": "1995-12-01",
    "date:inception_upper": "1995-12-01",
    "iso:country": "GB",
    "wof:name": "CW11 1XS",
    "wof:placetype": "postalcode"
  },
  "geometry": {"coordinates":[-2.384323,53.151617],"type":"Point"}
}
