{
  "type": "Feature",
  "properties": {
    "date:inception_lower": "1980-01-01",
    "date:inception_upper": "1980-01-01",
    "iso:country": "GB",
    "wof:name": "HX2 7NA",
    "wof:placetype": "postalcode"
  },
  "geometry": {"coordinates":[-1.905102,53.720028],"type":"Point"}
}
