{
  "type": "Feature",
  "properties": {
    "date:inception_lower": "1980-01-01",
    "date:inception_upper": "1980-01-01",
    "iso:country": "GB",
    "wof:name": "BN11 4PG",
    "wof:placetype": "postalcode"
  },
  "geometry": {"coordinates":[-0.38549,50.81297],"type":"Point"}
}
