{
  "type": "Feature",
  "properties": {
    "iso:country": "GB",
    "wof:name": "CB8 9DL",
    "wof:placetype": "postalcode"
  },
  "geometry": {"coordinates":[0.464707,52.223633],"type":"Point"}
}
