{
  "type": "Feature",
  "properties": {
    "date:inception_lower": "2008-01-01",
    "date:inception_upper": "2008-01-01",
    "iso:country": "GB",
    "wof:name": "SA73 1SJ",
    "wof:placetype": "postalcode"
  },
  "geometry": {"coordinates":[-4.950431,51.717408],"type":"Point"}
}
