{
  "type": "Feature",
  "properties": {
    "iso:country":"GB",
    "wof:name":"SA73 1SJ",
    "wof:placetype":"postalcode"
},
  "geometry": {"coordinates":[-4.9504309722341,51.71740764933337],"type":"Point"}
}