{
  "type": "Feature",
  "properties": {
    "date:inception_lower": "1980-01-01",
    "date:inception_upper": "1980-01-01",
    "iso:country": "GB",
    "wof:name": "DG8 9PA",
    "wof:placetype": "postalcode"
  },
  "geometry": {"coordinates":[-4.496442,54.823154],"type":"Point"}
}
