{
  "type": "Feature",
  "properties": {
    "iso:country":"GB",
    "wof:name":"TS13 4TF",
    "wof:placetype":"postalcode"
},
  "geometry": {"coordinates":[-0.91166627294616,54.54226357744596],"type":"Point"}
}