{
  "type": "Feature",
  "properties": {
    "iso:country":"GB",
    "wof:name":"NG13 8RE",
    "wof:placetype":"postalcode"
},
  "geometry": {"coordinates":[-0.96779416720559,52.95060054751308],"type":"Point"}
}