{
  "type": "Feature",
  "properties": {
    "iso:country":"GB",
    "wof:name":"PL10 1BZ",
    "wof:placetype":"postalcode"
},
  "geometry": {"coordinates":[-4.22363393108827,50.34654537674819],"type":"Point"}
}