{
  "type": "Feature",
  "properties": {
    "date:inception_lower": "1980-01-01",
    "date:inception_upper": "1980-01-01",
    "iso:country": "GB",
    "wof:name": "W6 0HJ",
    "wof:placetype": "postalcode"
  },
  "geometry": {"coordinates":[-0.235213,51.497977],"type":"Point"}
}
