{
  "type": "Feature",
  "properties": {
    "iso:country":"GB",
    "wof:name":"W6 0HJ",
    "wof:placetype":"postalcode"
},
  "geometry": {"coordinates":[-0.23521320466764,51.49797692766066],"type":"Point"}
}