{
  "type": "Feature",
  "properties": {
    "iso:country": "GB",
    "wof:name": "UB9 5FG",
    "wof:placetype": "postalcode"
  },
  "geometry": {"coordinates":[-0.498551,51.586433],"type":"Point"}
}
