{
  "type": "Feature",
  "properties": {
    "date:inception_lower": "2018-09-01",
    "date:inception_upper": "2018-09-01",
    "iso:country": "GB",
    "wof:name": "UB9 5FG",
    "wof:placetype": "postalcode"
  },
  "geometry": {"coordinates":[-0.498449,51.586476],"type":"Point"}
}
