{
  "type": "Feature",
  "properties": {
    "iso:country":"GB",
    "wof:name":"CB2 8PL",
    "wof:placetype":"postalcode"
},
  "geometry": {"coordinates":[0.135640680008,52.18274165362353],"type":"Point"}
}