{
  "type": "Feature",
  "properties": {
    "iso:country":"GB",
    "wof:name":"DH8 6LA",
    "wof:placetype":"postalcode"
},
  "geometry": {"coordinates":[-1.81097108271421,54.8677593012419],"type":"Point"}
}