{
  "type": "Feature",
  "properties": {
    "date:inception_lower":"1980-01-01",
    "date:inception_upper":"1980-01-31",
    "iso:country":"GB",
    "wof:name":"SP4 6DL",
    "wof:placetype":"postalcode"
},
  "geometry": {"coordinates":[-1.772898,51.095017],"type":"Point"}
}