{
  "type": "Feature",
  "properties": {
    "iso:country":"GB",
    "wof:name":"CV9 2JF",
    "wof:placetype":"postalcode"
},
  "geometry": {"coordinates":[-1.65395670753527,52.55850552494118],"type":"Point"}
}