{
  "type": "Feature",
  "properties": {
    "iso:country":"GB",
    "wof:name":"M33 6AG",
    "wof:placetype":"postalcode"
},
  "geometry": {"coordinates":[-2.32993745775234,53.42186576108673],"type":"Point"}
}