{
  "type": "Feature",
  "properties": {
    "date:inception_lower":"2010-05-01",
    "date:inception_upper":"2010-05-31",
    "iso:country":"GB",
    "wof:name":"M33 6AG",
    "wof:placetype":"postalcode"
},
  "geometry": {"coordinates":[-2.330133,53.421783],"type":"Point"}
}