{
  "type": "Feature",
  "properties": {
    "iso:country": "GB",
    "wof:name": "M33 6AG",
    "wof:placetype": "postalcode"
  },
  "geometry": {"coordinates":[-2.330133,53.421783],"type":"Point"}
}
