{
  "type": "Feature",
  "properties": {
    "iso:country": "GB",
    "wof:name": "WD6 1DB",
    "wof:placetype": "postalcode"
  },
  "geometry": {"coordinates":[-0.278912,51.652268],"type":"Point"}
}
