{
  "type": "Feature",
  "properties": {
    "date:inception_lower":"2017-09-01",
    "date:inception_upper":"2017-09-30",
    "iso:country":"GB",
    "wof:name":"CB25 9AT",
    "wof:placetype":"postalcode"
},
  "geometry": {"coordinates":[0.201432,52.226138],"type":"Point"}
}