{
  "type": "Feature",
  "properties": {
    "iso:country":"GB",
    "wof:name":"CR0 2XU",
    "wof:placetype":"postalcode"
},
  "geometry": {"coordinates":[-0.09828032838637,51.38487598618988],"type":"Point"}
}