{
  "type": "Feature",
  "properties": {
    "date:inception_lower": "1980-01-01",
    "date:inception_upper": "1980-01-01",
    "iso:country": "GB",
    "wof:name": "CR0 2XU",
    "wof:placetype": "postalcode"
  },
  "geometry": {"coordinates":[-0.09828,51.384876],"type":"Point"}
}
