{
  "type": "Feature",
  "properties": {
    "date:inception_lower": "2002-11-01",
    "date:inception_upper": "2002-11-01",
    "iso:country": "GB",
    "wof:name": "SY11 2NJ",
    "wof:placetype": "postalcode"
  },
  "geometry": {"coordinates":[-3.050345,52.856108],"type":"Point"}
}
