{
  "type": "Feature",
  "properties": {
    "iso:country":"GB",
    "wof:name":"SY11 2NJ",
    "wof:placetype":"postalcode"
},
  "geometry": {"coordinates":[-3.05034489619109,52.8561078501379],"type":"Point"}
}