{
  "type": "Feature",
  "properties": {
    "iso:country":"GB",
    "wof:name":"BA2 7FT",
    "wof:placetype":"postalcode"
},
  "geometry": {"coordinates":[-2.31558786222489,51.34938075159991],"type":"Point"}
}