{
  "type": "Feature",
  "properties": {
    "iso:country":"GB",
    "wof:name":"LA1 1HF",
    "wof:placetype":"postalcode"
},
  "geometry": {"coordinates":[-2.80046561109751,54.05128275399824],"type":"Point"}
}