{
  "type": "Feature",
  "properties": {
    "date:inception_lower": "1980-01-01",
    "date:inception_upper": "1980-01-01",
    "iso:country": "GB",
    "wof:name": "LA1 1HF",
    "wof:placetype": "postalcode"
  },
  "geometry": {"coordinates":[-2.800466,54.051283],"type":"Point"}
}
