{
  "type": "Feature",
  "properties": {
    "iso:country":"GB",
    "wof:name":"EH17 8SD",
    "wof:placetype":"postalcode"
},
  "geometry": {"coordinates":[-3.13810270969888,55.89568119925383],"type":"Point"}
}