{
  "type": "Feature",
  "properties": {
    "iso:country":"GB",
    "wof:name":"WF8 2PR",
    "wof:placetype":"postalcode"
},
  "geometry": {"coordinates":[-1.28882547920013,53.70561874187329],"type":"Point"}
}