{
  "type": "Feature",
  "properties": {
    "date:inception_lower":"2006-09-01",
    "date:inception_upper":"2006-09-30",
    "iso:country":"GB",
    "wof:name":"WF8 2PR",
    "wof:placetype":"postalcode"
},
  "geometry": {"coordinates":[-1.288825,53.705619],"type":"Point"}
}