{
  "type": "Feature",
  "properties": {
    "iso:country": "GB",
    "wof:name": "WF8 2PR",
    "wof:placetype": "postalcode"
  },
  "geometry": {"coordinates":[-1.288705,53.705717],"type":"Point"}
}
