{
  "type": "Feature",
  "properties": {
    "iso:country": "GB",
    "wof:name": "W1S 3HB",
    "wof:placetype": "postalcode"
  },
  "geometry": {"coordinates":[-0.139057,51.510429],"type":"Point"}
}
