{
  "type": "Feature",
  "properties": {
    "iso:country":"GB",
    "wof:name":"W1S 3HB",
    "wof:placetype":"postalcode"
},
  "geometry": {"coordinates":[-0.13905702576158,51.51042893834322],"type":"Point"}
}