{
  "type": "Feature",
  "properties": {
    "iso:country":"GB",
    "wof:name":"PA1 2NX",
    "wof:placetype":"postalcode"
},
  "geometry": {"coordinates":[-4.44718538041567,55.83961865910824],"type":"Point"}
}