{
  "type": "Feature",
  "properties": {
    "iso:country":"GB",
    "wof:name":"GL51 3ET",
    "wof:placetype":"postalcode"
},
  "geometry": {"coordinates":[-2.10736843162055,51.8862491003905],"type":"Point"}
}