{
  "type": "Feature",
  "properties": {
    "iso:country": "GB",
    "wof:name": "NR34 9YS",
    "wof:placetype": "postalcode"
  },
  "geometry": {"coordinates":[1.564787,52.450028],"type":"Point"}
}
