{
  "type": "Feature",
  "properties": {
    "iso:country": "GB",
    "wof:name": "W13 0BU",
    "wof:placetype": "postalcode"
  },
  "geometry": {"coordinates":[-0.327731,51.510285],"type":"Point"}
}
