{
  "type": "Feature",
  "properties": {
    "iso:country":"GB",
    "wof:name":"WV5 8HW",
    "wof:placetype":"postalcode"
},
  "geometry": {"coordinates":[-2.20885723880394,52.52870067480509],"type":"Point"}
}