{
  "type": "Feature",
  "properties": {
    "iso:country":"GB",
    "wof:name":"KA10 6AS",
    "wof:placetype":"postalcode"
},
  "geometry": {"coordinates":[-4.6679096015881,55.54314681275024],"type":"Point"}
}