{
  "type": "Feature",
  "properties": {
    "iso:country":"GB",
    "wof:name":"DA14 6BN",
    "wof:placetype":"postalcode"
},
  "geometry": {"coordinates":[0.10042901586208,51.4235419980334],"type":"Point"}
}