{
  "type": "Feature",
  "properties": {
    "iso:country":"GB",
    "wof:name":"GU3 3HY",
    "wof:placetype":"postalcode"
},
  "geometry": {"coordinates":[-0.6146561181264,51.26146031766055],"type":"Point"}
}