{
  "type": "Feature",
  "properties": {
    "iso:country": "GB",
    "wof:name": "GU3 3HY",
    "wof:placetype": "postalcode"
  },
  "geometry": {"coordinates":[-0.614656,51.26146],"type":"Point"}
}
