{
  "type": "Feature",
  "properties": {
    "date:inception_lower":"1980-01-01",
    "date:inception_upper":"1980-01-31",
    "iso:country":"GB",
    "wof:name":"TR16 4RX",
    "wof:placetype":"postalcode"
},
  "geometry": {"coordinates":[-5.267098,50.246646],"type":"Point"}
}