{
  "type": "Feature",
  "properties": {
    "iso:country":"GB",
    "wof:name":"GL8 8XN",
    "wof:placetype":"postalcode"
},
  "geometry": {"coordinates":[-2.17174389749364,51.64501430034785],"type":"Point"}
}