{
  "type": "Feature",
  "properties": {
    "date:inception_lower": "1980-01-01",
    "date:inception_upper": "1980-01-01",
    "iso:country": "GB",
    "wof:name": "GL8 8XN",
    "wof:placetype": "postalcode"
  },
  "geometry": {"coordinates":[-2.171744,51.645014],"type":"Point"}
}
