{
  "type": "Feature",
  "properties": {
    "date:inception_lower": "1983-01-01",
    "date:inception_upper": "1983-01-01",
    "iso:country": "GB",
    "wof:name": "M29 7PA",
    "wof:placetype": "postalcode"
  },
  "geometry": {"coordinates":[-2.453426,53.511661],"type":"Point"}
}
