{
  "type": "Feature",
  "properties": {
    "iso:country":"GB",
    "wof:name":"M29 7PA",
    "wof:placetype":"postalcode"
},
  "geometry": {"coordinates":[-2.45342626410244,53.51166050945722],"type":"Point"}
}