{
  "type": "Feature",
  "properties": {
    "iso:country":"GB",
    "wof:name":"EN2 7PY",
    "wof:placetype":"postalcode"
},
  "geometry": {"coordinates":[-0.10314948313698,51.6583011041597],"type":"Point"}
}