{
  "type": "Feature",
  "properties": {
    "iso:country": "GB",
    "wof:name": "PE3 6XR",
    "wof:placetype": "postalcode"
  },
  "geometry": {"coordinates":[-0.286105,52.569831],"type":"Point"}
}
