{
  "type": "Feature",
  "properties": {
    "iso:country":"GB",
    "wof:name":"PE3 6XR",
    "wof:placetype":"postalcode"
},
  "geometry": {"coordinates":[-0.28610521457248,52.56983096343352],"type":"Point"}
}