{
  "type": "Feature",
  "properties": {
    "iso:country":"GB",
    "wof:name":"BD4 8AR",
    "wof:placetype":"postalcode"
},
  "geometry": {"coordinates":[-1.71850079943159,53.7922181509318],"type":"Point"}
}