{
  "type": "Feature",
  "properties": {
    "date:inception_lower": "2014-05-01",
    "date:inception_upper": "2014-05-01",
    "iso:country": "GB",
    "wof:name": "DL1 1TX",
    "wof:placetype": "postalcode"
  },
  "geometry": {"coordinates":[-1.548546,54.526717],"type":"Point"}
}
