{
  "type": "Feature",
  "properties": {
    "iso:country": "GB",
    "wof:name": "PR2 7AU",
    "wof:placetype": "postalcode"
  },
  "geometry": {"coordinates":[-2.739151,53.78572],"type":"Point"}
}
