{
  "type": "Feature",
  "properties": {
    "iso:country": "GB",
    "wof:name": "YO10 4PS",
    "wof:placetype": "postalcode"
  },
  "geometry": {"coordinates":[-1.071204,53.933313],"type":"Point"}
}
