{
  "type": "Feature",
  "properties": {
    "iso:country":"GB",
    "wof:name":"YO10 4PS",
    "wof:placetype":"postalcode"
},
  "geometry": {"coordinates":[-1.07120446977519,53.93331288848179],"type":"Point"}
}