{
  "type": "Feature",
  "properties": {
    "date:inception_lower": "2011-11-01",
    "date:inception_upper": "2011-11-01",
    "iso:country": "GB",
    "wof:name": "PE10 0WR",
    "wof:placetype": "postalcode"
  },
  "geometry": {"coordinates":[-0.376863,52.76074],"type":"Point"}
}
