{
  "type": "Feature",
  "properties": {
    "iso:country":"GB",
    "wof:name":"BB18 5EX",
    "wof:placetype":"postalcode"
},
  "geometry": {"coordinates":[-2.19161764212478,53.9208941556962],"type":"Point"}
}