{
  "type": "Feature",
  "properties": {
    "iso:country":"GB",
    "wof:name":"LL77 7LH",
    "wof:placetype":"postalcode"
},
  "geometry": {"coordinates":[-4.29854923199617,53.25909149112698],"type":"Point"}
}