{
  "type": "Feature",
  "properties": {
    "date:inception_lower": "1996-12-01",
    "date:inception_upper": "1996-12-01",
    "iso:country": "GB",
    "wof:name": "ST15 8JD",
    "wof:placetype": "postalcode"
  },
  "geometry": {"coordinates":[-2.146674,52.909432],"type":"Point"}
}
