{
  "type": "Feature",
  "properties": {
    "iso:country": "GB",
    "wof:name": "CF32 7SE",
    "wof:placetype": "postalcode"
  },
  "geometry": {"coordinates":[-3.536155,51.618732],"type":"Point"}
}
