{
  "type": "Feature",
  "properties": {
    "date:inception_lower": "2017-01-01",
    "date:inception_upper": "2017-01-01",
    "iso:country": "GB",
    "wof:name": "LE7 3GB",
    "wof:placetype": "postalcode"
  },
  "geometry": {"coordinates":[-1.048326,52.70259],"type":"Point"}
}
