{
  "type": "Feature",
  "properties": {
    "iso:country": "GB",
    "wof:name": "LE7 3GB",
    "wof:placetype": "postalcode"
  },
  "geometry": {"coordinates":[-1.048598,52.702359],"type":"Point"}
}
