{
  "type": "Feature",
  "properties": {
    "iso:country":"GB",
    "wof:name":"YO25 9RA",
    "wof:placetype":"postalcode"
},
  "geometry": {"coordinates":[-0.4299477862426,53.95414842477983],"type":"Point"}
}