{
  "type": "Feature",
  "properties": {
    "date:inception_lower":"1980-01-01",
    "date:inception_upper":"1980-01-31",
    "iso:country":"GB",
    "wof:name":"YO25 9RA",
    "wof:placetype":"postalcode"
},
  "geometry": {"coordinates":[-0.429948,53.954148],"type":"Point"}
}