{
  "type": "Feature",
  "properties": {
    "iso:country":"GB",
    "wof:name":"IP3 8LD",
    "wof:placetype":"postalcode"
},
  "geometry": {"coordinates":[1.17933992594172,52.05271997351741],"type":"Point"}
}