{
  "type": "Feature",
  "properties": {
    "iso:country": "GB",
    "wof:name": "IP3 8LD",
    "wof:placetype": "postalcode"
  },
  "geometry": {"coordinates":[1.17934,52.05272],"type":"Point"}
}
