{
  "type": "Feature",
  "properties": {
    "iso:country": "GB",
    "wof:name": "UB6 8BD",
    "wof:placetype": "postalcode"
  },
  "geometry": {"coordinates":[-0.341783,51.539206],"type":"Point"}
}
