{
  "type": "Feature",
  "properties": {
    "date:inception_lower":"1980-01-01",
    "date:inception_upper":"1980-01-31",
    "iso:country":"GB",
    "wof:name":"UB6 8BD",
    "wof:placetype":"postalcode"
},
  "geometry": {"coordinates":[-0.341783,51.539206],"type":"Point"}
}