{
  "type": "Feature",
  "properties": {
    "iso:country":"GB",
    "wof:name":"BD13 3SH",
    "wof:placetype":"postalcode"
},
  "geometry": {"coordinates":[-1.87509382501773,53.79255504171306],"type":"Point"}
}