{
  "type": "Feature",
  "properties": {
    "iso:country":"GB",
    "wof:name":"HA3 9NB",
    "wof:placetype":"postalcode"
},
  "geometry": {"coordinates":[-0.29537488289813,51.58987777752291],"type":"Point"}
}