{
  "type": "Feature",
  "properties": {
    "iso:country": "GB",
    "wof:name": "SK8 4JU",
    "wof:placetype": "postalcode"
  },
  "geometry": {"coordinates":[-2.240043,53.384328],"type":"Point"}
}
