{
  "type": "Feature",
  "properties": {
    "date:inception_lower":"2001-12-01",
    "date:inception_upper":"2001-12-31",
    "iso:country":"GB",
    "wof:name":"TW11 9BL",
    "wof:placetype":"postalcode"
},
  "geometry": {"coordinates":[-0.332372,51.425958],"type":"Point"}
}