{
  "type": "Feature",
  "properties": {
    "iso:country":"GB",
    "wof:name":"TW11 9BL",
    "wof:placetype":"postalcode"
},
  "geometry": {"coordinates":[-0.33193120956705,51.42600566808831],"type":"Point"}
}