{
  "type": "Feature",
  "properties": {
    "iso:country": "GB",
    "wof:name": "TW11 9BL",
    "wof:placetype": "postalcode"
  },
  "geometry": {"coordinates":[-0.332372,51.425958],"type":"Point"}
}
