{
  "type": "Feature",
  "properties": {
    "date:inception_lower": "1980-01-01",
    "date:inception_upper": "1980-01-01",
    "iso:country": "GB",
    "wof:name": "BL2 2ND",
    "wof:placetype": "postalcode"
  },
  "geometry": {"coordinates":[-2.407153,53.590817],"type":"Point"}
}
