{
  "type": "Feature",
  "properties": {
    "iso:country":"GB",
    "wof:name":"BL2 2ND",
    "wof:placetype":"postalcode"
},
  "geometry": {"coordinates":[-2.40715326273998,53.59081716093259],"type":"Point"}
}