{
  "type": "Feature",
  "properties": {
    "iso:country":"GB",
    "wof:name":"HA2 9BW",
    "wof:placetype":"postalcode"
},
  "geometry": {"coordinates":[-0.36469501877979,51.5649845790136],"type":"Point"}
}