{
  "type": "Feature",
  "properties": {
    "iso:country": "GB",
    "wof:name": "ST17 0DZ",
    "wof:placetype": "postalcode"
  },
  "geometry": {"coordinates":[-2.073177,52.78755],"type":"Point"}
}
