{
  "type": "Feature",
  "properties": {
    "date:inception_lower": "2002-05-01",
    "date:inception_upper": "2002-05-01",
    "iso:country": "GB",
    "wof:name": "ST17 0DZ",
    "wof:placetype": "postalcode"
  },
  "geometry": {"coordinates":[-2.073177,52.78755],"type":"Point"}
}
