{
  "type": "Feature",
  "properties": {
    "iso:country":"GB",
    "wof:name":"SW19 5PE",
    "wof:placetype":"postalcode"
},
  "geometry": {"coordinates":[-0.21715599844159,51.43900987709458],"type":"Point"}
}