{
  "type": "Feature",
  "properties": {
    "iso:country":"GB",
    "wof:name":"UB2 5QN",
    "wof:placetype":"postalcode"
},
  "geometry": {"coordinates":[-0.38131872685205,51.49743167935473],"type":"Point"}
}