{
  "type": "Feature",
  "properties": {
    "iso:country":"GB",
    "wof:name":"NP11 7QT",
    "wof:placetype":"postalcode"
},
  "geometry": {"coordinates":[-3.15355729830335,51.61461876067631],"type":"Point"}
}