{
  "type": "Feature",
  "properties": {
    "iso:country":"GB",
    "wof:name":"B25 8JR",
    "wof:placetype":"postalcode"
},
  "geometry": {"coordinates":[-1.82236253479981,52.45958385103592],"type":"Point"}
}