{
  "type": "Feature",
  "properties": {
    "iso:country": "GB",
    "wof:name": "B25 8JR",
    "wof:placetype": "postalcode"
  },
  "geometry": {"coordinates":[-1.822357,52.459598],"type":"Point"}
}
