{
  "type": "Feature",
  "properties": {
    "iso:country":"GB",
    "wof:name":"M19 1FQ",
    "wof:placetype":"postalcode"
},
  "geometry": {"coordinates":[-2.20164107796584,53.42794914138544],"type":"Point"}
}