{
  "type": "Feature",
  "properties": {
    "iso:country":"GB",
    "wof:name":"BS29 6PQ",
    "wof:placetype":"postalcode"
},
  "geometry": {"coordinates":[-2.84868511416847,51.33090474419845],"type":"Point"}
}