{
  "type": "Feature",
  "properties": {
    "date:inception_lower": "1997-12-01",
    "date:inception_upper": "1997-12-01",
    "iso:country": "GB",
    "wof:name": "BS29 6PQ",
    "wof:placetype": "postalcode"
  },
  "geometry": {"coordinates":[-2.848685,51.330905],"type":"Point"}
}
