{
  "type": "Feature",
  "properties": {
    "iso:country":"GB",
    "wof:name":"GL1 3NP",
    "wof:placetype":"postalcode"
},
  "geometry": {"coordinates":[-2.23849584691038,51.86711228466998],"type":"Point"}
}