{
  "type": "Feature",
  "properties": {
    "iso:country":"GB",
    "wof:name":"DN10 6QG",
    "wof:placetype":"postalcode"
},
  "geometry": {"coordinates":[-1.01724028799187,53.43565660972746],"type":"Point"}
}