{
  "type": "Feature",
  "properties": {
    "iso:country": "GB",
    "wof:name": "DN10 6QG",
    "wof:placetype": "postalcode"
  },
  "geometry": {"coordinates":[-1.017319,53.435578],"type":"Point"}
}
