{
  "type": "Feature",
  "properties": {
    "iso:country":"GB",
    "wof:name":"NW11 7AH",
    "wof:placetype":"postalcode"
},
  "geometry": {"coordinates":[-0.1893075992865,51.58020521659897],"type":"Point"}
}