{
  "type": "Feature",
  "properties": {
    "iso:country": "GB",
    "wof:name": "EX22 6DQ",
    "wof:placetype": "postalcode"
  },
  "geometry": {"coordinates":[-4.355222,50.811174],"type":"Point"}
}
