{
  "type": "Feature",
  "properties": {
    "iso:country":"GB",
    "wof:name":"CV37 8AN",
    "wof:placetype":"postalcode"
},
  "geometry": {"coordinates":[-1.7917840730622,52.13310691720982],"type":"Point"}
}