{
  "type": "Feature",
  "properties": {
    "iso:country": "GB",
    "wof:name": "CV37 8AN",
    "wof:placetype": "postalcode"
  },
  "geometry": {"coordinates":[-1.792268,52.132802],"type":"Point"}
}
