{
  "type": "Feature",
  "properties": {
    "iso:country":"GB",
    "wof:name":"CF24 3HT",
    "wof:placetype":"postalcode"
},
  "geometry": {"coordinates":[-3.16594732015846,51.49102089174828],"type":"Point"}
}