{
  "type": "Feature",
  "properties": {
    "date:inception_lower": "1980-01-01",
    "date:inception_upper": "1980-01-01",
    "iso:country": "GB",
    "wof:name": "IP13 6UH",
    "wof:placetype": "postalcode"
  },
  "geometry": {"coordinates":[1.253777,52.104136],"type":"Point"}
}
