{
  "type": "Feature",
  "properties": {
    "iso:country":"GB",
    "wof:name":"IP13 6UH",
    "wof:placetype":"postalcode"
},
  "geometry": {"coordinates":[1.25374695624841,52.10412128175418],"type":"Point"}
}