{
  "type": "Feature",
  "properties": {
    "iso:country": "GB",
    "wof:name": "IP13 6UH",
    "wof:placetype": "postalcode"
  },
  "geometry": {"coordinates":[1.25378,52.104181],"type":"Point"}
}
