{
  "type": "Feature",
  "properties": {
    "iso:country":"GB",
    "wof:name":"OX4 7WA",
    "wof:placetype":"postalcode"
},
  "geometry": {"coordinates":[-1.20400256410997,51.71576014169087],"type":"Point"}
}