{
  "type": "Feature",
  "properties": {
    "iso:country":"GB",
    "wof:name":"BA4 5AS",
    "wof:placetype":"postalcode"
},
  "geometry": {"coordinates":[-2.54764664352302,51.18936848594723],"type":"Point"}
}