{
  "type": "Feature",
  "properties": {
    "iso:country":"GB",
    "wof:name":"TS18 5JP",
    "wof:placetype":"postalcode"
},
  "geometry": {"coordinates":[-1.35771671376942,54.55717218505153],"type":"Point"}
}