{
  "type": "Feature",
  "properties": {
    "iso:country":"GB",
    "wof:name":"UB2 5DU",
    "wof:placetype":"postalcode"
},
  "geometry": {"coordinates":[-0.38520302470036,51.50084832988885],"type":"Point"}
}