{
  "type": "Feature",
  "properties": {
    "date:inception_lower": "1980-01-01",
    "date:inception_upper": "1980-01-01",
    "iso:country": "GB",
    "wof:name": "UB2 5DU",
    "wof:placetype": "postalcode"
  },
  "geometry": {"coordinates":[-0.385203,51.500848],"type":"Point"}
}
