{
  "type": "Feature",
  "properties": {
    "iso:country":"GB",
    "wof:name":"PO11 0BT",
    "wof:placetype":"postalcode"
},
  "geometry": {"coordinates":[-0.99892295396849,50.78899069975574],"type":"Point"}
}