{
  "type": "Feature",
  "properties": {
    "iso:country":"GB",
    "wof:name":"HX6 2TH",
    "wof:placetype":"postalcode"
},
  "geometry": {"coordinates":[-1.91084060710855,53.71434610511231],"type":"Point"}
}