{
  "type": "Feature",
  "properties": {
    "iso:country": "GB",
    "wof:name": "M9 8GS",
    "wof:placetype": "postalcode"
  },
  "geometry": {"coordinates":[-2.218232,53.517211],"type":"Point"}
}
