{
  "type": "Feature",
  "properties": {
    "date:inception_lower": "1995-07-01",
    "date:inception_upper": "1995-07-01",
    "iso:country": "GB",
    "wof:name": "RG20 7PE",
    "wof:placetype": "postalcode"
  },
  "geometry": {"coordinates":[-1.256877,51.515706],"type":"Point"}
}
