{
  "type": "Feature",
  "properties": {
    "date:inception_lower": "2002-12-01",
    "date:inception_upper": "2002-12-01",
    "iso:country": "GB",
    "wof:name": "PE12 0ES",
    "wof:placetype": "postalcode"
  },
  "geometry": {"coordinates":[0.070861,52.744357],"type":"Point"}
}
