{
  "type": "Feature",
  "properties": {
    "iso:country":"GB",
    "wof:name":"BA2 1JZ",
    "wof:placetype":"postalcode"
},
  "geometry": {"coordinates":[-2.39720387561536,51.36927375806412],"type":"Point"}
}