{
  "type": "Feature",
  "properties": {
    "iso:country":"GB",
    "wof:name":"CF40 1AN",
    "wof:placetype":"postalcode"
},
  "geometry": {"coordinates":[-3.45217218394397,51.62051160262377],"type":"Point"}
}