{
  "type": "Feature",
  "properties": {
    "iso:country": "GB",
    "wof:name": "WF14 0HL",
    "wof:placetype": "postalcode"
  },
  "geometry": {"coordinates":[-1.701005,53.688741],"type":"Point"}
}
