{
  "type": "Feature",
  "properties": {
    "iso:country":"GB",
    "wof:name":"LU7 3JU",
    "wof:placetype":"postalcode"
},
  "geometry": {"coordinates":[-0.64461086767621,51.91876782891318],"type":"Point"}
}