{
  "type": "Feature",
  "properties": {
    "iso:country":"GB",
    "wof:name":"B70 9AY",
    "wof:placetype":"postalcode"
},
  "geometry": {"coordinates":[-2.02717535741892,52.51813929701527],"type":"Point"}
}