{
  "type": "Feature",
  "properties": {
    "date:inception_lower": "1980-01-01",
    "date:inception_upper": "1980-01-01",
    "iso:country": "GB",
    "wof:name": "B70 9AY",
    "wof:placetype": "postalcode"
  },
  "geometry": {"coordinates":[-2.027175,52.518139],"type":"Point"}
}
