{
  "type": "Feature",
  "properties": {
    "iso:country":"GB",
    "wof:name":"SA7 9RY",
    "wof:placetype":"postalcode"
},
  "geometry": {"coordinates":[-3.88449908567579,51.65980434572214],"type":"Point"}
}