{
  "type": "Feature",
  "properties": {
    "iso:country":"GB",
    "wof:name":"FY2 9EP",
    "wof:placetype":"postalcode"
},
  "geometry": {"coordinates":[-3.0446518183766,53.85285552887817],"type":"Point"}
}