{
  "type": "Feature",
  "properties": {
    "iso:country":"GB",
    "wof:name":"S43 3XL",
    "wof:placetype":"postalcode"
},
  "geometry": {"coordinates":[-1.36078824713747,53.26296747723856],"type":"Point"}
}