{
  "type": "Feature",
  "properties": {
    "iso:country":"GB",
    "wof:name":"EH48 1QR",
    "wof:placetype":"postalcode"
},
  "geometry": {"coordinates":[-3.63643996830032,55.90038118984583],"type":"Point"}
}