{
  "type": "Feature",
  "properties": {
    "date:inception_lower": "1981-07-01",
    "date:inception_upper": "1981-07-01",
    "iso:country": "GB",
    "wof:name": "EH48 1QR",
    "wof:placetype": "postalcode"
  },
  "geometry": {"coordinates":[-3.63644,55.900381],"type":"Point"}
}
