{
  "type": "Feature",
  "properties": {
    "iso:country":"GB",
    "wof:name":"OX7 3HW",
    "wof:placetype":"postalcode"
},
  "geometry": {"coordinates":[-1.52550951413046,51.87822198033065],"type":"Point"}
}