{
  "type": "Feature",
  "properties": {
    "iso:country":"GB",
    "wof:name":"BS9 2ED",
    "wof:placetype":"postalcode"
},
  "geometry": {"coordinates":[-2.65037974260189,51.4889899029009],"type":"Point"}
}