{
  "type": "Feature",
  "properties": {
    "iso:country":"GB",
    "wof:name":"GL5 2QG",
    "wof:placetype":"postalcode"
},
  "geometry": {"coordinates":[-2.19146549239113,51.71905322107465],"type":"Point"}
}