{
  "type": "Feature",
  "properties": {
    "date:inception_lower": "1980-01-01",
    "date:inception_upper": "1980-01-01",
    "iso:country": "GB",
    "wof:name": "DY10 4HB",
    "wof:placetype": "postalcode"
  },
  "geometry": {"coordinates":[-2.220521,52.335268],"type":"Point"}
}
