{
  "type": "Feature",
  "properties": {
    "iso:country":"GB",
    "wof:name":"NE5 3DT",
    "wof:placetype":"postalcode"
},
  "geometry": {"coordinates":[-1.66307056689848,54.99354431191333],"type":"Point"}
}