{
  "type": "Feature",
  "properties": {
    "iso:country":"GB",
    "wof:name":"L4 9RL",
    "wof:placetype":"postalcode"
},
  "geometry": {"coordinates":[-2.93565483928814,53.44311385746376],"type":"Point"}
}