{
  "type": "Feature",
  "properties": {
    "iso:country":"GB",
    "wof:name":"NN29 7TR",
    "wof:placetype":"postalcode"
},
  "geometry": {"coordinates":[-0.70897634707694,52.27501747174269],"type":"Point"}
}