{
  "type": "Feature",
  "properties": {
    "iso:country":"GB",
    "wof:name":"RM8 3NS",
    "wof:placetype":"postalcode"
},
  "geometry": {"coordinates":[0.14710063130923,51.55801222764335],"type":"Point"}
}