{
  "type": "Feature",
  "properties": {
    "iso:country": "GB",
    "wof:name": "PE2 5DZ",
    "wof:placetype": "postalcode"
  },
  "geometry": {"coordinates":[-0.293775,52.552419],"type":"Point"}
}
