{
  "type": "Feature",
  "properties": {
    "iso:country":"GB",
    "wof:name":"B60 1BX",
    "wof:placetype":"postalcode"
},
  "geometry": {"coordinates":[-2.00916054105815,52.35033424178439],"type":"Point"}
}