{
  "type": "Feature",
  "properties": {
    "iso:country": "GB",
    "wof:name": "NN5 5DP",
    "wof:placetype": "postalcode"
  },
  "geometry": {"coordinates":[-0.908778,52.238615],"type":"Point"}
}
