{
  "type": "Feature",
  "properties": {
    "iso:country": "GB",
    "wof:name": "CT21 4NU",
    "wof:placetype": "postalcode"
  },
  "geometry": {"coordinates":[1.035125,51.067979],"type":"Point"}
}
