{
  "type": "Feature",
  "properties": {
    "date:inception_lower": "1980-01-01",
    "date:inception_upper": "1980-01-01",
    "iso:country": "GB",
    "wof:name": "CT21 4NU",
    "wof:placetype": "postalcode"
  },
  "geometry": {"coordinates":[1.035125,51.067979],"type":"Point"}
}
