{
  "type": "Feature",
  "properties": {
    "iso:country":"GB",
    "wof:name":"CT21 4NU",
    "wof:placetype":"postalcode"
},
  "geometry": {"coordinates":[1.03512513971873,51.06797886553955],"type":"Point"}
}