{
  "type": "Feature",
  "properties": {
    "iso:country": "GB",
    "wof:name": "PL24 2RS",
    "wof:placetype": "postalcode"
  },
  "geometry": {"coordinates":[-4.699651,50.366632],"type":"Point"}
}
