{
  "type": "Feature",
  "properties": {
    "iso:country":"GB",
    "wof:name":"SP7 9JX",
    "wof:placetype":"postalcode"
},
  "geometry": {"coordinates":[-2.18963276898761,51.04331509063805],"type":"Point"}
}