{
  "type": "Feature",
  "properties": {
    "iso:country":"GB",
    "wof:name":"DN21 4LE",
    "wof:placetype":"postalcode"
},
  "geometry": {"coordinates":[-0.56823163504336,53.47635322118259],"type":"Point"}
}