{
  "type": "Feature",
  "properties": {
    "iso:country": "GB",
    "wof:name": "GL56 0TR",
    "wof:placetype": "postalcode"
  },
  "geometry": {"coordinates":[-1.704439,51.946499],"type":"Point"}
}
