{
  "type": "Feature",
  "properties": {
    "iso:country":"GB",
    "wof:name":"GL56 0TR",
    "wof:placetype":"postalcode"
},
  "geometry": {"coordinates":[-1.70443884579883,51.94649919394411],"type":"Point"}
}