{
  "type": "Feature",
  "properties": {
    "date:inception_lower":"1986-07-01",
    "date:inception_upper":"1986-07-31",
    "iso:country":"GB",
    "wof:name":"GL56 0TR",
    "wof:placetype":"postalcode"
},
  "geometry": {"coordinates":[-1.704439,51.946499],"type":"Point"}
}