{
  "type": "Feature",
  "properties": {
    "iso:country":"GB",
    "wof:name":"W12 8QA",
    "wof:placetype":"postalcode"
},
  "geometry": {"coordinates":[-0.22275653257549,51.5030224157479],"type":"Point"}
}