{
  "type": "Feature",
  "properties": {
    "date:inception_lower":"1980-01-01",
    "date:inception_upper":"1980-01-31",
    "iso:country":"GB",
    "wof:name":"S62 7QL",
    "wof:placetype":"postalcode"
},
  "geometry": {"coordinates":[-1.349164,53.472487],"type":"Point"}
}