{
  "type": "Feature",
  "properties": {
    "iso:country":"GB",
    "wof:name":"S62 7QL",
    "wof:placetype":"postalcode"
},
  "geometry": {"coordinates":[-1.34916356786616,53.47248682969612],"type":"Point"}
}