{
  "type": "Feature",
  "properties": {
    "date:inception_lower": "1980-01-01",
    "date:inception_upper": "1980-01-01",
    "iso:country": "GB",
    "wof:name": "PA28 6DP",
    "wof:placetype": "postalcode"
  },
  "geometry": {"coordinates":[-5.606515,55.429755],"type":"Point"}
}
