{
  "type": "Feature",
  "properties": {
    "date:inception_lower": "1980-01-01",
    "date:inception_upper": "1980-01-01",
    "iso:country": "GB",
    "wof:name": "B98 7JP",
    "wof:placetype": "postalcode"
  },
  "geometry": {"coordinates":[-1.9297,52.299034],"type":"Point"}
}
