{
  "type": "Feature",
  "properties": {
    "iso:country":"GB",
    "wof:name":"LE3 1RE",
    "wof:placetype":"postalcode"
},
  "geometry": {"coordinates":[-1.18277297884841,52.6223315258738],"type":"Point"}
}