{
  "type": "Feature",
  "properties": {
    "iso:country":"GB",
    "wof:name":"HU5 1PL",
    "wof:placetype":"postalcode"
},
  "geometry": {"coordinates":[-0.3506747482978,53.76529717305993],"type":"Point"}
}