{
  "type": "Feature",
  "properties": {
    "date:inception_lower":"2016-05-01",
    "date:inception_upper":"2016-05-31",
    "iso:country":"GB",
    "wof:name":"PO20 0FL",
    "wof:placetype":"postalcode"
},
  "geometry": {"coordinates":[-0.774357,50.738769],"type":"Point"}
}