{
  "type": "Feature",
  "properties": {
    "iso:country": "GB",
    "wof:name": "PO20 0FL",
    "wof:placetype": "postalcode"
  },
  "geometry": {"coordinates":[-0.774357,50.738769],"type":"Point"}
}
