{
  "type": "Feature",
  "properties": {
    "iso:country":"GB",
    "wof:name":"SP10 3LX",
    "wof:placetype":"postalcode"
},
  "geometry": {"coordinates":[-1.50934302605253,51.21267018669057],"type":"Point"}
}