{
  "type": "Feature",
  "properties": {
    "date:inception_lower": "1990-07-01",
    "date:inception_upper": "1990-07-01",
    "iso:country": "GB",
    "wof:name": "CR5 2PS",
    "wof:placetype": "postalcode"
  },
  "geometry": {"coordinates":[-0.154796,51.326095],"type":"Point"}
}
