{
  "type": "Feature",
  "properties": {
    "iso:country":"GB",
    "wof:name":"CR5 2PS",
    "wof:placetype":"postalcode"
},
  "geometry": {"coordinates":[-0.15479614709656,51.32609505785],"type":"Point"}
}