{
  "type": "Feature",
  "properties": {
    "iso:country":"GB",
    "wof:name":"NE15 9LJ",
    "wof:placetype":"postalcode"
},
  "geometry": {"coordinates":[-1.76374369917079,54.9932510544276],"type":"Point"}
}