{
  "type": "Feature",
  "properties": {
    "iso:country":"GB",
    "wof:name":"BA12 7DQ",
    "wof:placetype":"postalcode"
},
  "geometry": {"coordinates":[-2.19082409331397,51.16636084199838],"type":"Point"}
}