{
  "type": "Feature",
  "properties": {
    "iso:country": "GB",
    "wof:name": "NG34 9NT",
    "wof:placetype": "postalcode"
  },
  "geometry": {"coordinates":[-0.287324,52.971854],"type":"Point"}
}
