{
  "type": "Feature",
  "properties": {
    "date:inception_lower":"2001-12-01",
    "date:inception_upper":"2001-12-31",
    "iso:country":"GB",
    "wof:name":"NG34 9NT",
    "wof:placetype":"postalcode"
},
  "geometry": {"coordinates":[-0.287324,52.971854],"type":"Point"}
}