{
  "type": "Feature",
  "properties": {
    "iso:country":"GB",
    "wof:name":"NG34 9NT",
    "wof:placetype":"postalcode"
},
  "geometry": {"coordinates":[-0.28732390035634,52.97185368037876],"type":"Point"}
}