{
  "type": "Feature",
  "properties": {
    "iso:country":"GB",
    "wof:name":"CT18 8JB",
    "wof:placetype":"postalcode"
},
  "geometry": {"coordinates":[1.08972167435816,51.12844987584747],"type":"Point"}
}