{
  "type": "Feature",
  "properties": {
    "date:inception_lower": "1980-01-01",
    "date:inception_upper": "1980-01-01",
    "iso:country": "GB",
    "wof:name": "TW3 4LY",
    "wof:placetype": "postalcode"
  },
  "geometry": {"coordinates":[-0.379369,51.474411],"type":"Point"}
}
