{
  "type": "Feature",
  "properties": {
    "iso:country":"GB",
    "wof:name":"TW3 4LY",
    "wof:placetype":"postalcode"
},
  "geometry": {"coordinates":[-0.3793689803451,51.47441147013431],"type":"Point"}
}