{
  "type": "Feature",
  "properties": {
    "date:inception_lower":"1980-01-01",
    "date:inception_upper":"1980-01-31",
    "iso:country":"GB",
    "wof:name":"DG9 0DG",
    "wof:placetype":"postalcode"
},
  "geometry": {"coordinates":[-5.03814,54.904816],"type":"Point"}
}