{
  "type": "Feature",
  "properties": {
    "iso:country":"GB",
    "wof:name":"DG9 0DG",
    "wof:placetype":"postalcode"
},
  "geometry": {"coordinates":[-5.03813990218597,54.90481572662883],"type":"Point"}
}