{
  "type": "Feature",
  "properties": {
    "iso:country": "GB",
    "wof:name": "NG7 1NF",
    "wof:placetype": "postalcode"
  },
  "geometry": {"coordinates":[-1.164797,52.955294],"type":"Point"}
}
