{
  "type": "Feature",
  "properties": {
    "iso:country":"GB",
    "wof:name":"NG7 1NF",
    "wof:placetype":"postalcode"
},
  "geometry": {"coordinates":[-1.16479698241658,52.95529410800317],"type":"Point"}
}