{
  "type": "Feature",
  "properties": {
    "iso:country":"GB",
    "wof:name":"BB7 9BD",
    "wof:placetype":"postalcode"
},
  "geometry": {"coordinates":[-2.38941370794924,53.84456645136081],"type":"Point"}
}