{
  "type": "Feature",
  "properties": {
    "iso:country": "GB",
    "wof:name": "NG15 6GP",
    "wof:placetype": "postalcode"
  },
  "geometry": {"coordinates":[-1.210166,53.032015],"type":"Point"}
}
