{
  "type": "Feature",
  "properties": {
    "iso:country": "GB",
    "wof:name": "CH7 1XH",
    "wof:placetype": "postalcode"
  },
  "geometry": {"coordinates":[-3.143712,53.161378],"type":"Point"}
}
