{
  "type": "Feature",
  "properties": {
    "iso:country":"GB",
    "wof:name":"CH7 1XH",
    "wof:placetype":"postalcode"
},
  "geometry": {"coordinates":[-3.14371240955437,53.16137834285925],"type":"Point"}
}