{
  "type": "Feature",
  "properties": {
    "date:inception_lower": "1980-01-01",
    "date:inception_upper": "1980-01-01",
    "iso:country": "GB",
    "wof:name": "WR2 6NP",
    "wof:placetype": "postalcode"
  },
  "geometry": {"coordinates":[-2.265463,52.240292],"type":"Point"}
}
