{
  "type": "Feature",
  "properties": {
    "iso:country":"GB",
    "wof:name":"WR2 6NP",
    "wof:placetype":"postalcode"
},
  "geometry": {"coordinates":[-2.2654625566207,52.24029169040944],"type":"Point"}
}