{
  "type": "Feature",
  "properties": {
    "date:inception_lower": "1991-01-01",
    "date:inception_upper": "1991-01-01",
    "iso:country": "GB",
    "wof:name": "WS13 8RZ",
    "wof:placetype": "postalcode"
  },
  "geometry": {"coordinates":[-1.78241,52.70492],"type":"Point"}
}
