{
  "type": "Feature",
  "properties": {
    "iso:country":"GB",
    "wof:name":"CR0 2NP",
    "wof:placetype":"postalcode"
},
  "geometry": {"coordinates":[-0.10284743991165,51.39085824567758],"type":"Point"}
}