{
  "type": "Feature",
  "properties": {
    "date:inception_lower": "2008-01-01",
    "date:inception_upper": "2008-01-01",
    "iso:country": "GB",
    "wof:name": "CR0 2NP",
    "wof:placetype": "postalcode"
  },
  "geometry": {"coordinates":[-0.102847,51.390858],"type":"Point"}
}
