{
  "type": "Feature",
  "properties": {
    "iso:country":"GB",
    "wof:name":"TS5 7AB",
    "wof:placetype":"postalcode"
},
  "geometry": {"coordinates":[-1.25905032260528,54.54770224314427],"type":"Point"}
}