{
  "type": "Feature",
  "properties": {
    "iso:country": "GB",
    "wof:name": "TS5 7AB",
    "wof:placetype": "postalcode"
  },
  "geometry": {"coordinates":[-1.259079,54.547819],"type":"Point"}
}
