{
  "type": "Feature",
  "properties": {
    "date:inception_lower":"1980-01-01",
    "date:inception_upper":"1980-01-31",
    "iso:country":"GB",
    "wof:name":"HU19 2QH",
    "wof:placetype":"postalcode"
},
  "geometry": {"coordinates":[0.040314,53.710456],"type":"Point"}
}