{
  "type": "Feature",
  "properties": {
    "iso:country":"GB",
    "wof:name":"HU19 2QH",
    "wof:placetype":"postalcode"
},
  "geometry": {"coordinates":[0.04031357468367,53.71045602307468],"type":"Point"}
}