{
  "type": "Feature",
  "properties": {
    "iso:country": "GB",
    "wof:name": "TW17 9DH",
    "wof:placetype": "postalcode"
  },
  "geometry": {"coordinates":[-0.446877,51.392244],"type":"Point"}
}
