{
  "type": "Feature",
  "properties": {
    "iso:country":"GB",
    "wof:name":"BN2 1RP",
    "wof:placetype":"postalcode"
},
  "geometry": {"coordinates":[-0.13239589467261,50.82176532282526],"type":"Point"}
}