{
  "type": "Feature",
  "properties": {
    "date:inception_lower":"1980-01-01",
    "date:inception_upper":"1980-01-31",
    "iso:country":"GB",
    "wof:name":"BN2 1RP",
    "wof:placetype":"postalcode"
},
  "geometry": {"coordinates":[-0.13247,50.821686],"type":"Point"}
}