{
  "type": "Feature",
  "properties": {
    "iso:country": "GB",
    "wof:name": "PE38 0LS",
    "wof:placetype": "postalcode"
  },
  "geometry": {"coordinates":[0.414593,52.573986],"type":"Point"}
}
