{
  "type": "Feature",
  "properties": {
    "iso:country":"GB",
    "wof:name":"CO6 2ES",
    "wof:placetype":"postalcode"
},
  "geometry": {"coordinates":[0.68812045162043,51.93989907177185],"type":"Point"}
}