{
  "type": "Feature",
  "properties": {
    "date:inception_lower": "1980-01-01",
    "date:inception_upper": "1980-01-01",
    "iso:country": "GB",
    "wof:name": "CO6 2ES",
    "wof:placetype": "postalcode"
  },
  "geometry": {"coordinates":[0.688216,51.940034],"type":"Point"}
}
