{
  "type": "Feature",
  "properties": {
    "iso:country":"GB",
    "wof:name":"LL21 9RH",
    "wof:placetype":"postalcode"
},
  "geometry": {"coordinates":[-3.42460549035768,53.03605183027326],"type":"Point"}
}