{
  "type": "Feature",
  "properties": {
    "date:inception_lower": "2019-08-01",
    "date:inception_upper": "2019-08-01",
    "iso:country": "GB",
    "wof:name": "ME13 8GS",
    "wof:placetype": "postalcode"
  },
  "geometry": {"coordinates":[0.907573,51.310938],"type":"Point"}
}
