{
  "type": "Feature",
  "properties": {
    "iso:country":"GB",
    "wof:name":"IP17 2PH",
    "wof:placetype":"postalcode"
},
  "geometry": {"coordinates":[1.51937234964757,52.23591828341488],"type":"Point"}
}