{
  "type": "Feature",
  "properties": {
    "date:inception_lower":"1980-01-01",
    "date:inception_upper":"1980-01-31",
    "iso:country":"GB",
    "wof:name":"IP17 2PH",
    "wof:placetype":"postalcode"
},
  "geometry": {"coordinates":[1.519372,52.235918],"type":"Point"}
}