{
  "type": "Feature",
  "properties": {
    "iso:country": "GB",
    "wof:name": "IP28 8TA",
    "wof:placetype": "postalcode"
  },
  "geometry": {"coordinates":[0.49331,52.305475],"type":"Point"}
}
