{
  "type": "Feature",
  "properties": {
    "iso:country":"GB",
    "wof:name":"IP28 8TA",
    "wof:placetype":"postalcode"
},
  "geometry": {"coordinates":[0.49330947715384,52.3054745591381],"type":"Point"}
}