{
  "type": "Feature",
  "properties": {
    "iso:country":"GB",
    "wof:name":"PO36 9DG",
    "wof:placetype":"postalcode"
},
  "geometry": {"coordinates":[-1.16061186159847,50.65250426800337],"type":"Point"}
}