{
  "type": "Feature",
  "properties": {
    "date:inception_lower": "1980-01-01",
    "date:inception_upper": "1980-01-01",
    "iso:country": "GB",
    "wof:name": "EH20 9DN",
    "wof:placetype": "postalcode"
  },
  "geometry": {"coordinates":[-3.151025,55.877913],"type":"Point"}
}
