{
  "type": "Feature",
  "properties": {
    "iso:country":"GB",
    "wof:name":"EH20 9DN",
    "wof:placetype":"postalcode"
},
  "geometry": {"coordinates":[-3.15102549251172,55.87791349784538],"type":"Point"}
}