{
  "type": "Feature",
  "properties": {
    "iso:country":"GB",
    "wof:name":"E17 8EW",
    "wof:placetype":"postalcode"
},
  "geometry": {"coordinates":[-0.02923001117682,51.57415494017919],"type":"Point"}
}