{
  "type": "Feature",
  "properties": {
    "date:inception_lower": "1999-12-01",
    "date:inception_upper": "1999-12-01",
    "iso:country": "GB",
    "wof:name": "GL50 4AX",
    "wof:placetype": "postalcode"
  },
  "geometry": {"coordinates":[-2.080701,51.907102],"type":"Point"}
}
