{
  "type": "Feature",
  "properties": {
    "date:inception_lower": "1980-01-01",
    "date:inception_upper": "1980-01-01",
    "iso:country": "GB",
    "wof:name": "WV3 8HZ",
    "wof:placetype": "postalcode"
  },
  "geometry": {"coordinates":[-2.187674,52.58014],"type":"Point"}
}
