{
  "type": "Feature",
  "properties": {
    "iso:country":"GB",
    "wof:name":"LA3 1SF",
    "wof:placetype":"postalcode"
},
  "geometry": {"coordinates":[-2.87967634186297,54.06416620848381],"type":"Point"}
}