{
  "type": "Feature",
  "properties": {
    "date:inception_lower": "1980-01-01",
    "date:inception_upper": "1980-01-01",
    "iso:country": "GB",
    "wof:name": "LA3 1SF",
    "wof:placetype": "postalcode"
  },
  "geometry": {"coordinates":[-2.879612,54.06416],"type":"Point"}
}
