{
  "type": "Feature",
  "properties": {
    "iso:country":"GB",
    "wof:name":"SG5 4JL",
    "wof:placetype":"postalcode"
},
  "geometry": {"coordinates":[-0.23309526527986,52.00915308638265],"type":"Point"}
}