{
  "type": "Feature",
  "properties": {
    "iso:country": "GB",
    "wof:name": "SG5 4JL",
    "wof:placetype": "postalcode"
  },
  "geometry": {"coordinates":[-0.233095,52.009153],"type":"Point"}
}
