{
  "type": "Feature",
  "properties": {
    "iso:country": "GB",
    "wof:name": "CH61 9NQ",
    "wof:placetype": "postalcode"
  },
  "geometry": {"coordinates":[-3.093982,53.34528],"type":"Point"}
}
