{
  "type": "Feature",
  "properties": {
    "iso:country":"GB",
    "wof:name":"NG15 8HN",
    "wof:placetype":"postalcode"
},
  "geometry": {"coordinates":[-1.18587309694749,53.04571197368835],"type":"Point"}
}