{
  "type": "Feature",
  "properties": {
    "date:inception_lower":"2012-03-01",
    "date:inception_upper":"2012-03-31",
    "iso:country":"GB",
    "wof:name":"NG15 8HN",
    "wof:placetype":"postalcode"
},
  "geometry": {"coordinates":[-1.185873,53.045712],"type":"Point"}
}