{
  "type": "Feature",
  "properties": {
    "iso:country": "GB",
    "wof:name": "LN11 8XH",
    "wof:placetype": "postalcode"
  },
  "geometry": {"coordinates":[0.010989,53.359507],"type":"Point"}
}
