{
  "type": "Feature",
  "properties": {
    "iso:country":"GB",
    "wof:name":"RG18 9SS",
    "wof:placetype":"postalcode"
},
  "geometry": {"coordinates":[-1.2746211219544,51.45399815564412],"type":"Point"}
}