{
  "type": "Feature",
  "properties": {
    "iso:country":"GB",
    "wof:name":"N4 3JU",
    "wof:placetype":"postalcode"
},
  "geometry": {"coordinates":[-0.10830879320925,51.56524995942704],"type":"Point"}
}