{
  "type": "Feature",
  "properties": {
    "iso:country": "GB",
    "wof:name": "BN20 7DT",
    "wof:placetype": "postalcode"
  },
  "geometry": {"coordinates":[0.277246,50.765848],"type":"Point"}
}
