{
  "type": "Feature",
  "properties": {
    "iso:country":"GB",
    "wof:name":"TS19 7JR",
    "wof:placetype":"postalcode"
},
  "geometry": {"coordinates":[-1.36441024439042,54.57320434583843],"type":"Point"}
}