{
  "type": "Feature",
  "properties": {
    "date:inception_lower":"1984-02-01",
    "date:inception_upper":"1984-02-29",
    "iso:country":"GB",
    "wof:name":"CV6 4NE",
    "wof:placetype":"postalcode"
},
  "geometry": {"coordinates":[-1.499135,52.445766],"type":"Point"}
}