{
  "type": "Feature",
  "properties": {
    "iso:country":"GB",
    "wof:name":"CV6 4NE",
    "wof:placetype":"postalcode"
},
  "geometry": {"coordinates":[-1.49913472729489,52.44576579407662],"type":"Point"}
}