{
  "type": "Feature",
  "properties": {
    "date:inception_lower": "1980-01-01",
    "date:inception_upper": "1980-01-01",
    "iso:country": "GB",
    "wof:name": "EH47 8AZ",
    "wof:placetype": "postalcode"
  },
  "geometry": {"coordinates":[-3.629333,55.848751],"type":"Point"}
}
