{
  "type": "Feature",
  "properties": {
    "date:inception_lower":"1980-01-01",
    "date:inception_upper":"1980-01-31",
    "iso:country":"GB",
    "wof:name":"SW4 7PY",
    "wof:placetype":"postalcode"
},
  "geometry": {"coordinates":[-0.123972,51.462618],"type":"Point"}
}