{
  "type": "Feature",
  "properties": {
    "iso:country":"GB",
    "wof:name":"SW4 7PY",
    "wof:placetype":"postalcode"
},
  "geometry": {"coordinates":[-0.12397204297134,51.46261796122624],"type":"Point"}
}