{
  "type": "Feature",
  "properties": {
    "date:inception_lower": "1996-06-01",
    "date:inception_upper": "1996-06-01",
    "iso:country": "GB",
    "wof:name": "AB39 2GS",
    "wof:placetype": "postalcode"
  },
  "geometry": {"coordinates":[-2.229012,56.963797],"type":"Point"}
}
