{
  "type": "Feature",
  "properties": {
    "iso:country":"GB",
    "wof:name":"AB39 2GS",
    "wof:placetype":"postalcode"
},
  "geometry": {"coordinates":[-2.22901180843179,56.96379684196413],"type":"Point"}
}