{
  "type": "Feature",
  "properties": {
    "date:inception_lower": "2018-09-01",
    "date:inception_upper": "2018-09-01",
    "iso:country": "GB",
    "wof:name": "PR5 4DF",
    "wof:placetype": "postalcode"
  },
  "geometry": {"coordinates":[-2.669904,53.73785],"type":"Point"}
}
