{
  "type": "Feature",
  "properties": {
    "iso:country": "GB",
    "wof:name": "KT22 0SU",
    "wof:placetype": "postalcode"
  },
  "geometry": {"coordinates":[-0.358168,51.333628],"type":"Point"}
}
