{
  "type": "Feature",
  "properties": {
    "iso:country": "GB",
    "wof:name": "BS20 0BN",
    "wof:placetype": "postalcode"
  },
  "geometry": {"coordinates":[-2.691114,51.48347],"type":"Point"}
}
