{
  "type": "Feature",
  "properties": {
    "date:inception_lower": "1994-05-01",
    "date:inception_upper": "1994-05-01",
    "iso:country": "GB",
    "wof:name": "BB3 1BE",
    "wof:placetype": "postalcode"
  },
  "geometry": {"coordinates":[-2.467509,53.696164],"type":"Point"}
}
