{
  "type": "Feature",
  "properties": {
    "iso:country":"GB",
    "wof:name":"BB3 1BE",
    "wof:placetype":"postalcode"
},
  "geometry": {"coordinates":[-2.46750887760898,53.69616375536128],"type":"Point"}
}