{
  "type": "Feature",
  "properties": {
    "iso:country": "GB",
    "wof:name": "GU33 7LF",
    "wof:placetype": "postalcode"
  },
  "geometry": {"coordinates":[-0.890505,51.041533],"type":"Point"}
}
