{
  "type": "Feature",
  "properties": {
    "iso:country":"GB",
    "wof:name":"CO4 0DX",
    "wof:placetype":"postalcode"
},
  "geometry": {"coordinates":[0.92737116680045,51.89575057993349],"type":"Point"}
}