{
  "type": "Feature",
  "properties": {
    "iso:country": "GB",
    "wof:name": "CO4 0DX",
    "wof:placetype": "postalcode"
  },
  "geometry": {"coordinates":[0.927371,51.895751],"type":"Point"}
}
