{
  "type": "Feature",
  "properties": {
    "iso:country":"GB",
    "wof:name":"NE30 4AQ",
    "wof:placetype":"postalcode"
},
  "geometry": {"coordinates":[-1.42962386438009,55.01440321929379],"type":"Point"}
}