{
  "type": "Feature",
  "properties": {
    "date:inception_lower":"1980-01-01",
    "date:inception_upper":"1980-01-31",
    "iso:country":"GB",
    "wof:name":"RM5 3RR",
    "wof:placetype":"postalcode"
},
  "geometry": {"coordinates":[0.170578,51.600521],"type":"Point"}
}