{
  "type": "Feature",
  "properties": {
    "iso:country": "GB",
    "wof:name": "N14 6HJ",
    "wof:placetype": "postalcode"
  },
  "geometry": {"coordinates":[-0.125955,51.635386],"type":"Point"}
}
