{
  "type": "Feature",
  "properties": {
    "iso:country":"GB",
    "wof:name":"N14 6HJ",
    "wof:placetype":"postalcode"
},
  "geometry": {"coordinates":[-0.12595533265851,51.63538611338598],"type":"Point"}
}