{
  "type": "Feature",
  "properties": {
    "iso:country":"GB",
    "wof:name":"BN12 4EB",
    "wof:placetype":"postalcode"
},
  "geometry": {"coordinates":[-0.40946407105994,50.8134338996968],"type":"Point"}
}