{
  "type": "Feature",
  "properties": {
    "iso:country": "GB",
    "wof:name": "DN33 1HL",
    "wof:placetype": "postalcode"
  },
  "geometry": {"coordinates":[-0.110593,53.545301],"type":"Point"}
}
