{
  "type": "Feature",
  "properties": {
    "date:inception_lower":"1998-06-01",
    "date:inception_upper":"1998-06-30",
    "iso:country":"GB",
    "wof:name":"SA62 6NP",
    "wof:placetype":"postalcode"
},
  "geometry": {"coordinates":[-5.137753,51.871376],"type":"Point"}
}