{
  "type": "Feature",
  "properties": {
    "iso:country":"GB",
    "wof:name":"W1S 2SF",
    "wof:placetype":"postalcode"
},
  "geometry": {"coordinates":[-0.14418561766118,51.51224575364765],"type":"Point"}
}