{
  "type": "Feature",
  "properties": {
    "date:inception_lower": "2018-10-01",
    "date:inception_upper": "2018-10-01",
    "iso:country": "GB",
    "wof:name": "M12 5NF",
    "wof:placetype": "postalcode"
  },
  "geometry": {"coordinates":[-2.200712,53.467444],"type":"Point"}
}
