{
  "type": "Feature",
  "properties": {
    "date:inception_lower":"1999-06-01",
    "date:inception_upper":"1999-06-30",
    "iso:country":"GB",
    "wof:name":"TD12 4AN",
    "wof:placetype":"postalcode"
},
  "geometry": {"coordinates":[-2.25134,55.651475],"type":"Point"}
}