{
  "type": "Feature",
  "properties": {
    "iso:country":"GB",
    "wof:name":"TD12 4AN",
    "wof:placetype":"postalcode"
},
  "geometry": {"coordinates":[-2.25133336029306,55.6514767308701],"type":"Point"}
}