{
  "type": "Feature",
  "properties": {
    "iso:country":"GB",
    "wof:name":"NW6 4AA",
    "wof:placetype":"postalcode"
},
  "geometry": {"coordinates":[-0.1906963706069,51.53832211762896],"type":"Point"}
}