{
  "type": "Feature",
  "properties": {
    "date:inception_lower": "1980-01-01",
    "date:inception_upper": "1980-01-01",
    "iso:country": "GB",
    "wof:name": "NW6 4AA",
    "wof:placetype": "postalcode"
  },
  "geometry": {"coordinates":[-0.190696,51.538322],"type":"Point"}
}
