{
  "type": "Feature",
  "properties": {
    "iso:country": "GB",
    "wof:name": "NR8 6LZ",
    "wof:placetype": "postalcode"
  },
  "geometry": {"coordinates":[1.20394,52.683357],"type":"Point"}
}
