{
  "type": "Feature",
  "properties": {
    "iso:country":"GB",
    "wof:name":"NR2 4AQ",
    "wof:placetype":"postalcode"
},
  "geometry": {"coordinates":[1.28928997699049,52.63087801782857],"type":"Point"}
}