{
  "type": "Feature",
  "properties": {
    "date:inception_lower": "2002-07-01",
    "date:inception_upper": "2002-07-01",
    "iso:country": "GB",
    "wof:name": "M13 0FZ",
    "wof:placetype": "postalcode"
  },
  "geometry": {"coordinates":[-2.220649,53.459924],"type":"Point"}
}
