{
  "type": "Feature",
  "properties": {
    "date:inception_lower":"1980-01-01",
    "date:inception_upper":"1980-01-31",
    "iso:country":"GB",
    "wof:name":"NN16 8RH",
    "wof:placetype":"postalcode"
},
  "geometry": {"coordinates":[-0.72237,52.403964],"type":"Point"}
}