{
  "type": "Feature",
  "properties": {
    "iso:country":"GB",
    "wof:name":"SL5 8FQ",
    "wof:placetype":"postalcode"
},
  "geometry": {"coordinates":[-0.70874867364318,51.41728280573143],"type":"Point"}
}