{
  "type": "Feature",
  "properties": {
    "date:inception_lower": "2010-05-01",
    "date:inception_upper": "2010-05-01",
    "iso:country": "GB",
    "wof:name": "SL5 8FQ",
    "wof:placetype": "postalcode"
  },
  "geometry": {"coordinates":[-0.708749,51.417283],"type":"Point"}
}
