{
  "type": "Feature",
  "properties": {
    "iso:country":"GB",
    "wof:name":"TR20 9PP",
    "wof:placetype":"postalcode"
},
  "geometry": {"coordinates":[-5.43571612873231,50.12064122584582],"type":"Point"}
}