{
  "type": "Feature",
  "properties": {
    "iso:country": "GB",
    "wof:name": "RG30 1EN",
    "wof:placetype": "postalcode"
  },
  "geometry": {"coordinates":[-1.012238,51.462081],"type":"Point"}
}
