{
  "type": "Feature",
  "properties": {
    "iso:country":"GB",
    "wof:name":"RG30 1EN",
    "wof:placetype":"postalcode"
},
  "geometry": {"coordinates":[-1.01223830623112,51.46208076574739],"type":"Point"}
}