{
  "type": "Feature",
  "properties": {
    "date:inception_lower":"1980-01-01",
    "date:inception_upper":"1980-01-31",
    "iso:country":"GB",
    "wof:name":"GU34 2ES",
    "wof:placetype":"postalcode"
},
  "geometry": {"coordinates":[-0.971815,51.155263],"type":"Point"}
}