{
  "type": "Feature",
  "properties": {
    "iso:country":"GB",
    "wof:name":"GU34 2ES",
    "wof:placetype":"postalcode"
},
  "geometry": {"coordinates":[-0.97182996543119,51.1552656126764],"type":"Point"}
}