{
  "type": "Feature",
  "properties": {
    "iso:country":"GB",
    "wof:name":"ST7 2QL",
    "wof:placetype":"postalcode"
},
  "geometry": {"coordinates":[-2.29928958157384,53.09201233357228],"type":"Point"}
}