{
  "type": "Feature",
  "properties": {
    "date:inception_lower":"2017-08-01",
    "date:inception_upper":"2017-08-31",
    "iso:country":"GB",
    "wof:name":"SN12 8DZ",
    "wof:placetype":"postalcode"
},
  "geometry": {"coordinates":[-2.144575,51.378865],"type":"Point"}
}