{
  "type": "Feature",
  "properties": {
    "iso:country":"GB",
    "wof:name":"TA1 5JS",
    "wof:placetype":"postalcode"
},
  "geometry": {"coordinates":[-3.14314377851735,51.00681562319767],"type":"Point"}
}