{
  "type": "Feature",
  "properties": {
    "iso:country": "GB",
    "wof:name": "TA1 5JS",
    "wof:placetype": "postalcode"
  },
  "geometry": {"coordinates":[-3.143144,51.006816],"type":"Point"}
}
