{
  "type": "Feature",
  "properties": {
    "date:inception_lower": "1980-01-01",
    "date:inception_upper": "1980-01-01",
    "iso:country": "GB",
    "wof:name": "TA1 5JS",
    "wof:placetype": "postalcode"
  },
  "geometry": {"coordinates":[-3.143628,51.006401],"type":"Point"}
}
