{
  "type": "Feature",
  "properties": {
    "date:inception_lower": "1980-01-01",
    "date:inception_upper": "1980-01-01",
    "iso:country": "GB",
    "wof:name": "EX2 8NY",
    "wof:placetype": "postalcode"
  },
  "geometry": {"coordinates":[-3.527866,50.708682],"type":"Point"}
}
