{
  "type": "Feature",
  "properties": {
    "iso:country": "GB",
    "wof:name": "EX2 8NY",
    "wof:placetype": "postalcode"
  },
  "geometry": {"coordinates":[-3.527657,50.708794],"type":"Point"}
}
