{
  "type": "Feature",
  "properties": {
    "iso:country":"GB",
    "wof:name":"DN7 4AN",
    "wof:placetype":"postalcode"
},
  "geometry": {"coordinates":[-1.02125157505877,53.57936613871817],"type":"Point"}
}