{
  "type": "Feature",
  "properties": {
    "iso:country": "GB",
    "wof:name": "IG9 5LW",
    "wof:placetype": "postalcode"
  },
  "geometry": {"coordinates":[0.041439,51.626949],"type":"Point"}
}
