{
  "type": "Feature",
  "properties": {
    "iso:country": "GB",
    "wof:name": "IG9 5LW",
    "wof:placetype": "postalcode"
  },
  "geometry": {"coordinates":[0.041641,51.626946],"type":"Point"}
}
