{
  "type": "Feature",
  "properties": {
    "iso:country":"GB",
    "wof:name":"B75 7AU",
    "wof:placetype":"postalcode"
},
  "geometry": {"coordinates":[-1.81600332773687,52.56236491739092],"type":"Point"}
}