{
  "type": "Feature",
  "properties": {
    "date:inception_lower": "1983-03-01",
    "date:inception_upper": "1983-03-01",
    "iso:country": "GB",
    "wof:name": "GU4 7XX",
    "wof:placetype": "postalcode"
  },
  "geometry": {"coordinates":[-0.538202,51.252563],"type":"Point"}
}
