{
  "type": "Feature",
  "properties": {
    "date:inception_lower":"1995-12-01",
    "date:inception_upper":"1995-12-31",
    "iso:country":"GB",
    "wof:name":"KW15 1FD",
    "wof:placetype":"postalcode"
},
  "geometry": {"coordinates":[-2.94699,58.970497],"type":"Point"}
}