{
  "type": "Feature",
  "properties": {
    "iso:country": "GB",
    "wof:name": "KW15 1FD",
    "wof:placetype": "postalcode"
  },
  "geometry": {"coordinates":[-2.94699,58.970497],"type":"Point"}
}
