{
  "type": "Feature",
  "properties": {
    "iso:country":"GB",
    "wof:name":"CF82 7GE",
    "wof:placetype":"postalcode"
},
  "geometry": {"coordinates":[-3.2501698432576,51.65778788747765],"type":"Point"}
}