{
  "type": "Feature",
  "properties": {
    "iso:country":"GB",
    "wof:name":"SA5 9AG",
    "wof:placetype":"postalcode"
},
  "geometry": {"coordinates":[-3.95602471567805,51.65373350552461],"type":"Point"}
}