{
  "type": "Feature",
  "properties": {
    "iso:country":"GB",
    "wof:name":"YO25 9QF",
    "wof:placetype":"postalcode"
},
  "geometry": {"coordinates":[-0.39369569766124,53.95958380404635],"type":"Point"}
}