{
  "type": "Feature",
  "properties": {
    "iso:country":"GB",
    "wof:name":"LL22 7RT",
    "wof:placetype":"postalcode"
},
  "geometry": {"coordinates":[-3.57378636960372,53.29258478350163],"type":"Point"}
}