{
  "type": "Feature",
  "properties": {
    "iso:country":"GB",
    "wof:name":"YO43 3HL",
    "wof:placetype":"postalcode"
},
  "geometry": {"coordinates":[-0.6571516259607,53.86519266609888],"type":"Point"}
}