{
  "type": "Feature",
  "properties": {
    "iso:country": "GB",
    "wof:name": "YO43 3HL",
    "wof:placetype": "postalcode"
  },
  "geometry": {"coordinates":[-0.65717,53.865339],"type":"Point"}
}
