{
  "type": "Feature",
  "properties": {
    "date:inception_lower": "1998-06-01",
    "date:inception_upper": "1998-06-01",
    "iso:country": "GB",
    "wof:name": "YO43 3HL",
    "wof:placetype": "postalcode"
  },
  "geometry": {"coordinates":[-0.65717,53.865339],"type":"Point"}
}
