{
  "type": "Feature",
  "properties": {
    "iso:country":"GB",
    "wof:name":"CH7 5UW",
    "wof:placetype":"postalcode"
},
  "geometry": {"coordinates":[-3.28412150946785,53.23369675917645],"type":"Point"}
}