{
  "type": "Feature",
  "properties": {
    "iso:country":"GB",
    "wof:name":"W2 1UL",
    "wof:placetype":"postalcode"
},
  "geometry": {"coordinates":[-0.16860503554021,51.51784522496193],"type":"Point"}
}