{
  "type": "Feature",
  "properties": {
    "date:inception_lower": "2007-04-01",
    "date:inception_upper": "2007-04-01",
    "iso:country": "GB",
    "wof:name": "SO30 2JY",
    "wof:placetype": "postalcode"
  },
  "geometry": {"coordinates":[-1.306808,50.928786],"type":"Point"}
}
