{
  "type": "Feature",
  "properties": {
    "iso:country":"GB",
    "wof:name":"SO30 2JY",
    "wof:placetype":"postalcode"
},
  "geometry": {"coordinates":[-1.30680812302747,50.92878550651666],"type":"Point"}
}