{
  "type": "Feature",
  "properties": {
    "iso:country":"GB",
    "wof:name":"OX4 3PF",
    "wof:placetype":"postalcode"
},
  "geometry": {"coordinates":[-1.22161861692725,51.73346511797534],"type":"Point"}
}