{
  "type": "Feature",
  "properties": {
    "date:inception_lower":"1980-01-01",
    "date:inception_upper":"1980-01-31",
    "iso:country":"GB",
    "wof:name":"OX4 3PF",
    "wof:placetype":"postalcode"
},
  "geometry": {"coordinates":[-1.221619,51.733465],"type":"Point"}
}