{
  "type": "Feature",
  "properties": {
    "iso:country": "GB",
    "wof:name": "LE2 9JW",
    "wof:placetype": "postalcode"
  },
  "geometry": {"coordinates":[-1.167913,52.585657],"type":"Point"}
}
