{
  "type": "Feature",
  "properties": {
    "iso:country":"GB",
    "wof:name":"LE2 9JW",
    "wof:placetype":"postalcode"
},
  "geometry": {"coordinates":[-1.16791295763492,52.58565673432948],"type":"Point"}
}