{
  "type": "Feature",
  "properties": {
    "iso:country":"GB",
    "wof:name":"WA6 0QS",
    "wof:placetype":"postalcode"
},
  "geometry": {"coordinates":[-2.77003953599495,53.269508274659],"type":"Point"}
}