{
  "type": "Feature",
  "properties": {
    "iso:country": "GB",
    "wof:name": "S74 0DQ",
    "wof:placetype": "postalcode"
  },
  "geometry": {"coordinates":[-1.46648,53.497706],"type":"Point"}
}
