{
  "type": "Feature",
  "properties": {
    "iso:country":"GB",
    "wof:name":"SG6 2QZ",
    "wof:placetype":"postalcode"
},
  "geometry": {"coordinates":[-0.20008438002475,51.97158017738552],"type":"Point"}
}