{
  "type": "Feature",
  "properties": {
    "date:inception_lower": "2023-05-01",
    "date:inception_upper": "2023-05-01",
    "iso:country": "GB",
    "wof:name": "HD2 1ZP",
    "wof:placetype": "postalcode"
  },
  "geometry": {"coordinates":[-1.777562,53.669436],"type":"Point"}
}
