{
  "type": "Feature",
  "properties": {
    "iso:country": "GB",
    "wof:name": "TR10 8HY",
    "wof:placetype": "postalcode"
  },
  "geometry": {"coordinates":[-5.109519,50.171559],"type":"Point"}
}
