{
  "type": "Feature",
  "properties": {
    "iso:country": "GB",
    "wof:name": "S10 3RW",
    "wof:placetype": "postalcode"
  },
  "geometry": {"coordinates":[-1.54765,53.366186],"type":"Point"}
}
