{
  "type": "Feature",
  "properties": {
    "date:inception_lower": "1980-01-01",
    "date:inception_upper": "1980-01-01",
    "iso:country": "GB",
    "wof:name": "S10 3RW",
    "wof:placetype": "postalcode"
  },
  "geometry": {"coordinates":[-1.54765,53.366186],"type":"Point"}
}
