{
  "type": "Feature",
  "properties": {
    "iso:country":"GB",
    "wof:name":"S10 3RW",
    "wof:placetype":"postalcode"
},
  "geometry": {"coordinates":[-1.54705312139859,53.36592349624274],"type":"Point"}
}