{
  "type": "Feature",
  "properties": {
    "iso:country":"GB",
    "wof:name":"DN20 0PX",
    "wof:placetype":"postalcode"
},
  "geometry": {"coordinates":[-0.48838515637061,53.62672186153183],"type":"Point"}
}