{
  "type": "Feature",
  "properties": {
    "iso:country": "GB",
    "wof:name": "DN20 0PX",
    "wof:placetype": "postalcode"
  },
  "geometry": {"coordinates":[-0.488385,53.626722],"type":"Point"}
}
