{
  "type": "Feature",
  "properties": {
    "iso:country": "GB",
    "wof:name": "AB30 1UA",
    "wof:placetype": "postalcode"
  },
  "geometry": {"coordinates":[-2.416868,56.922922],"type":"Point"}
}
