{
  "type": "Feature",
  "properties": {
    "iso:country":"GB",
    "wof:name":"AB30 1UA",
    "wof:placetype":"postalcode"
},
  "geometry": {"coordinates":[-2.41686846612114,56.92292219361051],"type":"Point"}
}