{
  "type": "Feature",
  "properties": {
    "date:inception_lower":"1980-01-01",
    "date:inception_upper":"1980-01-31",
    "iso:country":"GB",
    "wof:name":"CF5 6SD",
    "wof:placetype":"postalcode"
},
  "geometry": {"coordinates":[-3.288111,51.463009],"type":"Point"}
}