{
  "type": "Feature",
  "properties": {
    "iso:country":"GB",
    "wof:name":"CF5 6SD",
    "wof:placetype":"postalcode"
},
  "geometry": {"coordinates":[-3.2881108908248,51.46300917811089],"type":"Point"}
}