{
  "type": "Feature",
  "properties": {
    "iso:country": "GB",
    "wof:name": "OX17 1ER",
    "wof:placetype": "postalcode"
  },
  "geometry": {"coordinates":[-1.331494,52.145854],"type":"Point"}
}
