{
  "type": "Feature",
  "properties": {
    "date:inception_lower":"1980-01-01",
    "date:inception_upper":"1980-01-31",
    "iso:country":"GB",
    "wof:name":"CR4 4JW",
    "wof:placetype":"postalcode"
},
  "geometry": {"coordinates":[-0.159578,51.384101],"type":"Point"}
}