{
  "type": "Feature",
  "properties": {
    "iso:country": "GB",
    "wof:name": "CR4 4JW",
    "wof:placetype": "postalcode"
  },
  "geometry": {"coordinates":[-0.159578,51.384101],"type":"Point"}
}
