{
  "type": "Feature",
  "properties": {
    "iso:country": "GB",
    "wof:name": "L20 3NJ",
    "wof:placetype": "postalcode"
  },
  "geometry": {"coordinates":[-2.987519,53.446921],"type":"Point"}
}
