{
  "type": "Feature",
  "properties": {
    "iso:country":"GB",
    "wof:name":"BS26 2UQ",
    "wof:placetype":"postalcode"
},
  "geometry": {"coordinates":[-2.9161951712538,51.27212769110108],"type":"Point"}
}