{
  "type": "Feature",
  "properties": {
    "date:inception_lower": "1980-01-01",
    "date:inception_upper": "1980-01-01",
    "iso:country": "GB",
    "wof:name": "BS26 2UQ",
    "wof:placetype": "postalcode"
  },
  "geometry": {"coordinates":[-2.916231,51.272123],"type":"Point"}
}
