{
  "type": "Feature",
  "properties": {
    "iso:country": "GB",
    "wof:name": "BA4 6RZ",
    "wof:placetype": "postalcode"
  },
  "geometry": {"coordinates":[-2.594173,51.110874],"type":"Point"}
}
