{
  "type": "Feature",
  "properties": {
    "iso:country":"GB",
    "wof:name":"NE9 7EU",
    "wof:placetype":"postalcode"
},
  "geometry": {"coordinates":[-1.57759871862702,54.91981475528187],"type":"Point"}
}