{
  "type": "Feature",
  "properties": {
    "iso:country":"GB",
    "wof:name":"SE27 0UD",
    "wof:placetype":"postalcode"
},
  "geometry": {"coordinates":[-0.10388554683427,51.42623431836792],"type":"Point"}
}