{
  "type": "Feature",
  "properties": {
    "iso:country":"GB",
    "wof:name":"NG3 5DD",
    "wof:placetype":"postalcode"
},
  "geometry": {"coordinates":[-1.15216647800747,52.97090934959817],"type":"Point"}
}