{
  "type": "Feature",
  "properties": {
    "iso:country":"GB",
    "wof:name":"SE8 5DX",
    "wof:placetype":"postalcode"
},
  "geometry": {"coordinates":[-0.04118725527413,51.49201894383576],"type":"Point"}
}