{
  "type": "Feature",
  "properties": {
    "iso:country":"GB",
    "wof:name":"SA6 7JB",
    "wof:placetype":"postalcode"
},
  "geometry": {"coordinates":[-3.94185517790223,51.66788899404983],"type":"Point"}
}