{
  "type": "Feature",
  "properties": {
    "date:inception_lower": "1980-01-01",
    "date:inception_upper": "1980-01-01",
    "iso:country": "GB",
    "wof:name": "SA6 7JB",
    "wof:placetype": "postalcode"
  },
  "geometry": {"coordinates":[-3.941932,51.667911],"type":"Point"}
}
