{
  "type": "Feature",
  "properties": {
    "date:inception_lower":"1980-01-01",
    "date:inception_upper":"1980-01-31",
    "iso:country":"GB",
    "wof:name":"SG14 2QQ",
    "wof:placetype":"postalcode"
},
  "geometry": {"coordinates":[-0.119991,51.825836],"type":"Point"}
}