{
  "type": "Feature",
  "properties": {
    "iso:country":"GB",
    "wof:name":"G3 8BW",
    "wof:placetype":"postalcode"
},
  "geometry": {"coordinates":[-4.27503204112818,55.85842753287185],"type":"Point"}
}