{
  "type": "Feature",
  "properties": {
    "iso:country":"GB",
    "wof:name":"DY1 4DZ",
    "wof:placetype":"postalcode"
},
  "geometry": {"coordinates":[-2.08984028031748,52.52722393443497],"type":"Point"}
}