{
  "type": "Feature",
  "properties": {
    "date:inception_lower": "2023-12-01",
    "date:inception_upper": "2023-12-01",
    "iso:country": "GB",
    "wof:name": "PE14 9ED",
    "wof:placetype": "postalcode"
  },
  "geometry": {"coordinates":[0.24782,52.522251],"type":"Point"}
}
