{
  "type": "Feature",
  "properties": {
    "iso:country":"GB",
    "wof:name":"TA4 2EW",
    "wof:placetype":"postalcode"
},
  "geometry": {"coordinates":[-3.36395600002528,51.06204415603172],"type":"Point"}
}