{
  "type": "Feature",
  "properties": {
    "date:inception_lower": "1980-01-01",
    "date:inception_upper": "1980-01-01",
    "iso:country": "GB",
    "wof:name": "SY1 3RS",
    "wof:placetype": "postalcode"
  },
  "geometry": {"coordinates":[-2.744586,52.74096],"type":"Point"}
}
