{
  "type": "Feature",
  "properties": {
    "iso:country":"GB",
    "wof:name":"SY1 3RS",
    "wof:placetype":"postalcode"
},
  "geometry": {"coordinates":[-2.74458640797984,52.74096046073673],"type":"Point"}
}