{
  "type": "Feature",
  "properties": {
    "iso:country": "GB",
    "wof:name": "DA3 7PL",
    "wof:placetype": "postalcode"
  },
  "geometry": {"coordinates":[0.303262,51.397167],"type":"Point"}
}
