{
  "type": "Feature",
  "properties": {
    "iso:country": "GB",
    "wof:name": "WA2 8XS",
    "wof:placetype": "postalcode"
  },
  "geometry": {"coordinates":[-2.599731,53.429714],"type":"Point"}
}
