{
  "type": "Feature",
  "properties": {
    "iso:country":"GB",
    "wof:name":"WA2 8XS",
    "wof:placetype":"postalcode"
},
  "geometry": {"coordinates":[-2.59973128356651,53.42971395550003],"type":"Point"}
}