{
  "type": "Feature",
  "properties": {
    "date:inception_lower": "2001-12-01",
    "date:inception_upper": "2001-12-01",
    "iso:country": "GB",
    "wof:name": "WA2 8XS",
    "wof:placetype": "postalcode"
  },
  "geometry": {"coordinates":[-2.599731,53.429714],"type":"Point"}
}
