{
  "type": "Feature",
  "properties": {
    "iso:country": "GB",
    "wof:name": "ML11 9XD",
    "wof:placetype": "postalcode"
  },
  "geometry": {"coordinates":[-3.897211,55.672768],"type":"Point"}
}
