{
  "type": "Feature",
  "properties": {
    "iso:country": "GB",
    "wof:name": "BN27 3RY",
    "wof:placetype": "postalcode"
  },
  "geometry": {"coordinates":[0.170855,50.882157],"type":"Point"}
}
