{
  "type": "Feature",
  "properties": {
    "iso:country": "GB",
    "wof:name": "G42 7RS",
    "wof:placetype": "postalcode"
  },
  "geometry": {"coordinates":[-4.265492,55.838112],"type":"Point"}
}
