{
  "type": "Feature",
  "properties": {
    "iso:country":"GB",
    "wof:name":"LS28 7ET",
    "wof:placetype":"postalcode"
},
  "geometry": {"coordinates":[-1.66032134611334,53.79353264830522],"type":"Point"}
}