{
  "type": "Feature",
  "properties": {
    "iso:country":"GB",
    "wof:name":"M22 8ED",
    "wof:placetype":"postalcode"
},
  "geometry": {"coordinates":[-2.26607699157446,53.39316292455884],"type":"Point"}
}