{
  "type": "Feature",
  "properties": {
    "date:inception_lower": "2010-05-01",
    "date:inception_upper": "2010-05-01",
    "iso:country": "GB",
    "wof:name": "DE13 0SY",
    "wof:placetype": "postalcode"
  },
  "geometry": {"coordinates":[-1.637759,52.823518],"type":"Point"}
}
