{
  "type": "Feature",
  "properties": {
    "iso:country":"GB",
    "wof:name":"SN25 2JT",
    "wof:placetype":"postalcode"
},
  "geometry": {"coordinates":[-1.83430307009612,51.60116427347479],"type":"Point"}
}