{
  "type": "Feature",
  "properties": {
    "iso:country": "GB",
    "wof:name": "WN2 3QW",
    "wof:placetype": "postalcode"
  },
  "geometry": {"coordinates":[-2.567051,53.53433],"type":"Point"}
}
