{
  "type": "Feature",
  "properties": {
    "iso:country":"GB",
    "wof:name":"WN2 3QW",
    "wof:placetype":"postalcode"
},
  "geometry": {"coordinates":[-2.56705098571515,53.53432970323966],"type":"Point"}
}