{
  "type": "Feature",
  "properties": {
    "date:inception_lower":"1980-01-01",
    "date:inception_upper":"1980-01-31",
    "iso:country":"GB",
    "wof:name":"WN2 3QW",
    "wof:placetype":"postalcode"
},
  "geometry": {"coordinates":[-2.567051,53.53433],"type":"Point"}
}