{
  "type": "Feature",
  "properties": {
    "iso:country": "GB",
    "wof:name": "SE8 4QB",
    "wof:placetype": "postalcode"
  },
  "geometry": {"coordinates":[-0.02849,51.471788],"type":"Point"}
}
