{
  "type": "Feature",
  "properties": {
    "iso:country":"GB",
    "wof:name":"M11 4FW",
    "wof:placetype":"postalcode"
},
  "geometry": {"coordinates":[-2.18767281290756,53.48543531954832],"type":"Point"}
}