{
  "type": "Feature",
  "properties": {
    "iso:country": "GB",
    "wof:name": "BA5 2SU",
    "wof:placetype": "postalcode"
  },
  "geometry": {"coordinates":[-2.644858,51.21147],"type":"Point"}
}
