{
  "type": "Feature",
  "properties": {
    "iso:country": "GB",
    "wof:name": "IP24 2JH",
    "wof:placetype": "postalcode"
  },
  "geometry": {"coordinates":[0.756266,52.420068],"type":"Point"}
}
