{
  "type": "Feature",
  "properties": {
    "iso:country":"GB",
    "wof:name":"B30 2HL",
    "wof:placetype":"postalcode"
},
  "geometry": {"coordinates":[-1.92720536226063,52.42569435163106],"type":"Point"}
}