{
  "type": "Feature",
  "properties": {
    "date:inception_lower": "1990-02-01",
    "date:inception_upper": "1990-02-01",
    "iso:country": "GB",
    "wof:name": "B30 2HL",
    "wof:placetype": "postalcode"
  },
  "geometry": {"coordinates":[-1.927205,52.425694],"type":"Point"}
}
