{
  "type": "Feature",
  "properties": {
    "date:inception_lower": "1980-01-01",
    "date:inception_upper": "1980-01-01",
    "iso:country": "GB",
    "wof:name": "FK3 8PX",
    "wof:placetype": "postalcode"
  },
  "geometry": {"coordinates":[-3.728663,56.008088],"type":"Point"}
}
