{
  "type": "Feature",
  "properties": {
    "iso:country": "GB",
    "wof:name": "NN4 0UD",
    "wof:placetype": "postalcode"
  },
  "geometry": {"coordinates":[-0.902257,52.20377],"type":"Point"}
}
