{
  "type": "Feature",
  "properties": {
    "iso:country": "GB",
    "wof:name": "CB2 9DZ",
    "wof:placetype": "postalcode"
  },
  "geometry": {"coordinates":[0.10571,52.171878],"type":"Point"}
}
