{
  "type": "Feature",
  "properties": {
    "iso:country":"GB",
    "wof:name":"CB2 9DZ",
    "wof:placetype":"postalcode"
},
  "geometry": {"coordinates":[0.10596678928131,52.17173855599377],"type":"Point"}
}