{
  "type": "Feature",
  "properties": {
    "iso:country": "GB",
    "wof:name": "CV37 8SL",
    "wof:placetype": "postalcode"
  },
  "geometry": {"coordinates":[-1.743386,52.122421],"type":"Point"}
}
