{
  "type": "Feature",
  "properties": {
    "iso:country":"GB",
    "wof:name":"CW9 8TH",
    "wof:placetype":"postalcode"
},
  "geometry": {"coordinates":[-2.51972971530591,53.24752738729446],"type":"Point"}
}