{
  "type": "Feature",
  "properties": {
    "date:inception_lower": "2003-03-01",
    "date:inception_upper": "2003-03-01",
    "iso:country": "GB",
    "wof:name": "CW9 8TH",
    "wof:placetype": "postalcode"
  },
  "geometry": {"coordinates":[-2.51973,53.247527],"type":"Point"}
}
