{
  "type": "Feature",
  "properties": {
    "iso:country":"GB",
    "wof:name":"PL28 8JT",
    "wof:placetype":"postalcode"
},
  "geometry": {"coordinates":[-5.00636179684615,50.51969684306207],"type":"Point"}
}