{
  "type": "Feature",
  "properties": {
    "date:inception_lower":"1980-01-01",
    "date:inception_upper":"1980-01-31",
    "iso:country":"GB",
    "wof:name":"PL28 8JT",
    "wof:placetype":"postalcode"
},
  "geometry": {"coordinates":[-5.006362,50.519697],"type":"Point"}
}