{
  "type": "Feature",
  "properties": {
    "iso:country":"GB",
    "wof:name":"SY22 6PD",
    "wof:placetype":"postalcode"
},
  "geometry": {"coordinates":[-3.10172216726394,52.77769977753129],"type":"Point"}
}