{
  "type": "Feature",
  "properties": {
    "iso:country": "GB",
    "wof:name": "NG34 8TQ",
    "wof:placetype": "postalcode"
  },
  "geometry": {"coordinates":[-0.440814,52.952965],"type":"Point"}
}
