{
  "type": "Feature",
  "properties": {
    "date:inception_lower":"1980-01-01",
    "date:inception_upper":"1980-01-31",
    "iso:country":"GB",
    "wof:name":"NG34 8TQ",
    "wof:placetype":"postalcode"
},
  "geometry": {"coordinates":[-0.440814,52.952965],"type":"Point"}
}