{
  "type": "Feature",
  "properties": {
    "iso:country":"GB",
    "wof:name":"NG34 8TQ",
    "wof:placetype":"postalcode"
},
  "geometry": {"coordinates":[-0.44081421912031,52.95296505229543],"type":"Point"}
}