{
  "type": "Feature",
  "properties": {
    "date:inception_lower": "2010-06-01",
    "date:inception_upper": "2010-06-01",
    "iso:country": "GB",
    "wof:name": "PE31 8SE",
    "wof:placetype": "postalcode"
  },
  "geometry": {"coordinates":[0.72102,52.853076],"type":"Point"}
}
