{
  "type": "Feature",
  "properties": {
    "iso:country":"GB",
    "wof:name":"RG30 2PY",
    "wof:placetype":"postalcode"
},
  "geometry": {"coordinates":[-1.00724082843074,51.45423366347558],"type":"Point"}
}