{
  "type": "Feature",
  "properties": {
    "iso:country":"GB",
    "wof:name":"NR33 8DB",
    "wof:placetype":"postalcode"
},
  "geometry": {"coordinates":[1.69126214519483,52.44265387557541],"type":"Point"}
}