{
  "type": "Feature",
  "properties": {
    "date:inception_lower":"1981-06-01",
    "date:inception_upper":"1981-06-30",
    "iso:country":"GB",
    "wof:name":"DN22 0BH",
    "wof:placetype":"postalcode"
},
  "geometry": {"coordinates":[-0.824406,53.329362],"type":"Point"}
}