{
  "type": "Feature",
  "properties": {
    "iso:country": "GB",
    "wof:name": "DN22 0BH",
    "wof:placetype": "postalcode"
  },
  "geometry": {"coordinates":[-0.824406,53.329362],"type":"Point"}
}
