{
  "type": "Feature",
  "properties": {
    "iso:country":"GB",
    "wof:name":"DN22 0BH",
    "wof:placetype":"postalcode"
},
  "geometry": {"coordinates":[-0.82440569432049,53.32936223204079],"type":"Point"}
}