{
  "type": "Feature",
  "properties": {
    "date:inception_lower": "1980-01-01",
    "date:inception_upper": "1980-01-01",
    "iso:country": "GB",
    "wof:name": "CT20 1JF",
    "wof:placetype": "postalcode"
  },
  "geometry": {"coordinates":[1.183478,51.083926],"type":"Point"}
}
