{
  "type": "Feature",
  "properties": {
    "iso:country":"GB",
    "wof:name":"BN16 1AD",
    "wof:placetype":"postalcode"
},
  "geometry": {"coordinates":[-0.4780026571467,50.81763962902754],"type":"Point"}
}