{
  "type": "Feature",
  "properties": {
    "iso:country":"GB",
    "wof:name":"KT24 5TA",
    "wof:placetype":"postalcode"
},
  "geometry": {"coordinates":[-0.44090571212367,51.24571453237728],"type":"Point"}
}