{
  "type": "Feature",
  "properties": {
    "iso:country":"GB",
    "wof:name":"G61 3QJ",
    "wof:placetype":"postalcode"
},
  "geometry": {"coordinates":[-4.32118241252471,55.92189835340053],"type":"Point"}
}