{
  "type": "Feature",
  "properties": {
    "iso:country": "GB",
    "wof:name": "CV4 9XD",
    "wof:placetype": "postalcode"
  },
  "geometry": {"coordinates":[-1.575446,52.409429],"type":"Point"}
}
