{
  "type": "Feature",
  "properties": {
    "iso:country": "GB",
    "wof:name": "M8 0GJ",
    "wof:placetype": "postalcode"
  },
  "geometry": {"coordinates":[-2.229916,53.505379],"type":"Point"}
}
