{
  "type": "Feature",
  "properties": {
    "iso:country": "GB",
    "wof:name": "SS17 0RG",
    "wof:placetype": "postalcode"
  },
  "geometry": {"coordinates":[0.410941,51.484583],"type":"Point"}
}
