{
  "type": "Feature",
  "properties": {
    "iso:country":"GB",
    "wof:name":"UB8 3NE",
    "wof:placetype":"postalcode"
},
  "geometry": {"coordinates":[-0.47194406786318,51.52734135987036],"type":"Point"}
}