{
  "type": "Feature",
  "properties": {
    "iso:country":"GB",
    "wof:name":"PO22 9NU",
    "wof:placetype":"postalcode"
},
  "geometry": {"coordinates":[-0.67617439087272,50.81130610747207],"type":"Point"}
}