{
  "type": "Feature",
  "properties": {
    "iso:country":"GB",
    "wof:name":"SE13 7HQ",
    "wof:placetype":"postalcode"
},
  "geometry": {"coordinates":[-0.01904360257566,51.45052330044684],"type":"Point"}
}