{
  "type": "Feature",
  "properties": {
    "iso:country": "GB",
    "wof:name": "PE37 7EW",
    "wof:placetype": "postalcode"
  },
  "geometry": {"coordinates":[0.693721,52.641079],"type":"Point"}
}
