{
  "type": "Feature",
  "properties": {
    "iso:country":"GB",
    "wof:name":"LS15 8PF",
    "wof:placetype":"postalcode"
},
  "geometry": {"coordinates":[-1.44259196393825,53.80026876977639],"type":"Point"}
}