{
  "type": "Feature",
  "properties": {
    "iso:country":"GB",
    "wof:name":"EH33 1DH",
    "wof:placetype":"postalcode"
},
  "geometry": {"coordinates":[-2.96442811183512,55.9481826219718],"type":"Point"}
}