{
  "type": "Feature",
  "properties": {
    "date:inception_lower": "1980-01-01",
    "date:inception_upper": "1980-01-01",
    "iso:country": "GB",
    "wof:name": "LU2 0LL",
    "wof:placetype": "postalcode"
  },
  "geometry": {"coordinates":[-0.395985,51.885853],"type":"Point"}
}
