{
  "type": "Feature",
  "properties": {
    "iso:country":"GB",
    "wof:name":"SM2 6NS",
    "wof:placetype":"postalcode"
},
  "geometry": {"coordinates":[-0.20000516116841,51.34707713426258],"type":"Point"}
}