{
  "type": "Feature",
  "properties": {
    "iso:country":"GB",
    "wof:name":"NW8 6BR",
    "wof:placetype":"postalcode"
},
  "geometry": {"coordinates":[-0.1660966466733,51.53758943933588],"type":"Point"}
}