{
  "type": "Feature",
  "properties": {
    "iso:country":"GB",
    "wof:name":"TN9 2ER",
    "wof:placetype":"postalcode"
},
  "geometry": {"coordinates":[0.2847725551167,51.18509719869534],"type":"Point"}
}