{
  "type": "Feature",
  "properties": {
    "iso:country": "GB",
    "wof:name": "AL7 2BJ",
    "wof:placetype": "postalcode"
  },
  "geometry": {"coordinates":[-0.175422,51.802215],"type":"Point"}
}
