{
  "type": "Feature",
  "properties": {
    "iso:country":"GB",
    "wof:name":"AL7 2BJ",
    "wof:placetype":"postalcode"
},
  "geometry": {"coordinates":[-0.17542222368726,51.8022148967593],"type":"Point"}
}