{
  "type": "Feature",
  "properties": {
    "iso:country":"GB",
    "wof:name":"SR8 3ND",
    "wof:placetype":"postalcode"
},
  "geometry": {"coordinates":[-1.32901358388176,54.79171687301244],"type":"Point"}
}