{
  "type": "Feature",
  "properties": {
    "iso:country":"GB",
    "wof:name":"TW8 0AB",
    "wof:placetype":"postalcode"
},
  "geometry": {"coordinates":[-0.30503124196496,51.48355786249649],"type":"Point"}
}