{
  "type": "Feature",
  "properties": {
    "iso:country": "GB",
    "wof:name": "BS15 8AH",
    "wof:placetype": "postalcode"
  },
  "geometry": {"coordinates":[-2.520467,51.459984],"type":"Point"}
}
