{
  "type": "Feature",
  "properties": {
    "iso:country":"GB",
    "wof:name":"BS15 8AH",
    "wof:placetype":"postalcode"
},
  "geometry": {"coordinates":[-2.52046691481847,51.45998439694635],"type":"Point"}
}