{
  "type": "Feature",
  "properties": {
    "date:inception_lower": "1997-12-01",
    "date:inception_upper": "1997-12-01",
    "iso:country": "GB",
    "wof:name": "BS15 8AH",
    "wof:placetype": "postalcode"
  },
  "geometry": {"coordinates":[-2.520467,51.459984],"type":"Point"}
}
