{
  "type": "Feature",
  "properties": {
    "date:inception_lower":"2009-03-01",
    "date:inception_upper":"2009-03-31",
    "iso:country":"GB",
    "wof:name":"GL52 5FR",
    "wof:placetype":"postalcode"
},
  "geometry": {"coordinates":[-2.044152,51.901898],"type":"Point"}
}