{
  "type": "Feature",
  "properties": {
    "date:inception_lower": "1999-12-01",
    "date:inception_upper": "1999-12-01",
    "iso:country": "GB",
    "wof:name": "E1W 2BP",
    "wof:placetype": "postalcode"
  },
  "geometry": {"coordinates":[-0.061777,51.509573],"type":"Point"}
}
