{
  "type": "Feature",
  "properties": {
    "iso:country":"GB",
    "wof:name":"WS3 3DG",
    "wof:placetype":"postalcode"
},
  "geometry": {"coordinates":[-1.98892171338377,52.62504889705249],"type":"Point"}
}