{
  "type": "Feature",
  "properties": {
    "iso:country":"GB",
    "wof:name":"TF3 4DY",
    "wof:placetype":"postalcode"
},
  "geometry": {"coordinates":[-2.44701696631574,52.67639071539381],"type":"Point"}
}