{
  "type": "Feature",
  "properties": {
    "iso:country": "GB",
    "wof:name": "TF3 4DY",
    "wof:placetype": "postalcode"
  },
  "geometry": {"coordinates":[-2.447017,52.676391],"type":"Point"}
}
