{
  "type": "Feature",
  "properties": {
    "iso:country":"GB",
    "wof:name":"AL5 4HT",
    "wof:placetype":"postalcode"
},
  "geometry": {"coordinates":[-0.35481914034158,51.82773712577502],"type":"Point"}
}