{
  "type": "Feature",
  "properties": {
    "iso:country":"GB",
    "wof:name":"FY6 8BL",
    "wof:placetype":"postalcode"
},
  "geometry": {"coordinates":[-2.99593480690622,53.83456521546699],"type":"Point"}
}