{
  "type": "Feature",
  "properties": {
    "iso:country": "GB",
    "wof:name": "FY6 8BL",
    "wof:placetype": "postalcode"
  },
  "geometry": {"coordinates":[-2.995935,53.834565],"type":"Point"}
}
