{
  "type": "Feature",
  "properties": {
    "date:inception_lower":"1980-01-01",
    "date:inception_upper":"1980-01-31",
    "iso:country":"GB",
    "wof:name":"KY4 9LW",
    "wof:placetype":"postalcode"
},
  "geometry": {"coordinates":[-3.358033,56.10491],"type":"Point"}
}