{
  "type": "Feature",
  "properties": {
    "date:inception_lower": "1980-01-01",
    "date:inception_upper": "1980-01-01",
    "iso:country": "GB",
    "wof:name": "NR20 5QF",
    "wof:placetype": "postalcode"
  },
  "geometry": {"coordinates":[1.059947,52.801384],"type":"Point"}
}
