{
  "type": "Feature",
  "properties": {
    "iso:country":"GB",
    "wof:name":"TN6 3HA",
    "wof:placetype":"postalcode"
},
  "geometry": {"coordinates":[0.18619907514758,51.0433200194175],"type":"Point"}
}