{
  "type": "Feature",
  "properties": {
    "iso:country": "GB",
    "wof:name": "TN6 3HA",
    "wof:placetype": "postalcode"
  },
  "geometry": {"coordinates":[0.186199,51.04332],"type":"Point"}
}
