{
  "type": "Feature",
  "properties": {
    "date:inception_lower":"2011-03-01",
    "date:inception_upper":"2011-03-31",
    "iso:country":"GB",
    "wof:name":"PO30 4DG",
    "wof:placetype":"postalcode"
},
  "geometry": {"coordinates":[-1.394148,50.643196],"type":"Point"}
}