{
  "type": "Feature",
  "properties": {
    "iso:country":"GB",
    "wof:name":"PO30 4DG",
    "wof:placetype":"postalcode"
},
  "geometry": {"coordinates":[-1.39414796070733,50.64319633703889],"type":"Point"}
}