{
  "type": "Feature",
  "properties": {
    "iso:country":"GB",
    "wof:name":"KT1 2RW",
    "wof:placetype":"postalcode"
},
  "geometry": {"coordinates":[-0.29794708310583,51.40726240039566],"type":"Point"}
}