{
  "type": "Feature",
  "properties": {
    "iso:country": "GB",
    "wof:name": "SK10 4AA",
    "wof:placetype": "postalcode"
  },
  "geometry": {"coordinates":[-2.150476,53.272206],"type":"Point"}
}
