{
  "type": "Feature",
  "properties": {
    "iso:country":"GB",
    "wof:name":"M21 8AP",
    "wof:placetype":"postalcode"
},
  "geometry": {"coordinates":[-2.27678941982209,53.4403554647316],"type":"Point"}
}