{
  "type": "Feature",
  "properties": {
    "iso:country": "GB",
    "wof:name": "M21 8AP",
    "wof:placetype": "postalcode"
  },
  "geometry": {"coordinates":[-2.276789,53.440355],"type":"Point"}
}
