{
  "type": "Feature",
  "properties": {
    "iso:country":"GB",
    "wof:name":"TW1 3HJ",
    "wof:placetype":"postalcode"
},
  "geometry": {"coordinates":[-0.3260609522336,51.45123561711683],"type":"Point"}
}