{
  "type": "Feature",
  "properties": {
    "date:inception_lower": "1980-01-01",
    "date:inception_upper": "1980-01-01",
    "iso:country": "GB",
    "wof:name": "TS9 7JB",
    "wof:placetype": "postalcode"
  },
  "geometry": {"coordinates":[-1.135971,54.410361],"type":"Point"}
}
