{
  "type": "Feature",
  "properties": {
    "iso:country":"GB",
    "wof:name":"TS9 7JB",
    "wof:placetype":"postalcode"
},
  "geometry": {"coordinates":[-1.1359713658197,54.41036059461652],"type":"Point"}
}