{
  "type": "Feature",
  "properties": {
    "iso:country": "GB",
    "wof:name": "AB21 7FX",
    "wof:placetype": "postalcode"
  },
  "geometry": {"coordinates":[-2.183583,57.202311],"type":"Point"}
}
