{
  "type": "Feature",
  "properties": {
    "iso:country": "GB",
    "wof:name": "LS29 6HT",
    "wof:placetype": "postalcode"
  },
  "geometry": {"coordinates":[-1.738102,53.889053],"type":"Point"}
}
