{
  "type": "Feature",
  "properties": {
    "iso:country": "GB",
    "wof:name": "NN1 4NY",
    "wof:placetype": "postalcode"
  },
  "geometry": {"coordinates":[-0.881054,52.246843],"type":"Point"}
}
