{
  "type": "Feature",
  "properties": {
    "iso:country":"GB",
    "wof:name":"NN1 4NY",
    "wof:placetype":"postalcode"
},
  "geometry": {"coordinates":[-0.88105400147173,52.2468430803661],"type":"Point"}
}