{
  "type": "Feature",
  "properties": {
    "iso:country":"GB",
    "wof:name":"L39 2DH",
    "wof:placetype":"postalcode"
},
  "geometry": {"coordinates":[-2.88119748187733,53.56731158684046],"type":"Point"}
}