{
  "type": "Feature",
  "properties": {
    "iso:country": "GB",
    "wof:name": "L39 2DH",
    "wof:placetype": "postalcode"
  },
  "geometry": {"coordinates":[-2.881197,53.567312],"type":"Point"}
}
