{
  "type": "Feature",
  "properties": {
    "iso:country": "GB",
    "wof:name": "M45 7EG",
    "wof:placetype": "postalcode"
  },
  "geometry": {"coordinates":[-2.290643,53.542314],"type":"Point"}
}
