{
  "type": "Feature",
  "properties": {
    "iso:country":"GB",
    "wof:name":"SW18 1HA",
    "wof:placetype":"postalcode"
},
  "geometry": {"coordinates":[-0.19815622927864,51.46111975660283],"type":"Point"}
}