{
  "type": "Feature",
  "properties": {
    "date:inception_lower": "2015-03-01",
    "date:inception_upper": "2015-03-01",
    "iso:country": "GB",
    "wof:name": "SW18 1HA",
    "wof:placetype": "postalcode"
  },
  "geometry": {"coordinates":[-0.198187,51.461175],"type":"Point"}
}
