{
  "type": "Feature",
  "properties": {
    "iso:country": "GB",
    "wof:name": "SW18 1HA",
    "wof:placetype": "postalcode"
  },
  "geometry": {"coordinates":[-0.198187,51.461175],"type":"Point"}
}
