{
  "type": "Feature",
  "properties": {
    "iso:country":"GB",
    "wof:name":"OL1 2AN",
    "wof:placetype":"postalcode"
},
  "geometry": {"coordinates":[-2.11677091448637,53.54647602393321],"type":"Point"}
}