{
  "type": "Feature",
  "properties": {
    "iso:country": "GB",
    "wof:name": "OL1 2AN",
    "wof:placetype": "postalcode"
  },
  "geometry": {"coordinates":[-2.116771,53.546476],"type":"Point"}
}
