{
  "type": "Feature",
  "properties": {
    "iso:country":"GB",
    "wof:name":"GL2 9BH",
    "wof:placetype":"postalcode"
},
  "geometry": {"coordinates":[-2.2325798362698,51.88300207623253],"type":"Point"}
}