{
  "type": "Feature",
  "properties": {
    "date:inception_lower": "2010-06-01",
    "date:inception_upper": "2010-06-01",
    "iso:country": "GB",
    "wof:name": "GL2 9BH",
    "wof:placetype": "postalcode"
  },
  "geometry": {"coordinates":[-2.23258,51.883002],"type":"Point"}
}
