{
  "type": "Feature",
  "properties": {
    "iso:country":"GB",
    "wof:name":"EC2M 6SX",
    "wof:placetype":"postalcode"
},
  "geometry": {"coordinates":[-0.08759490723236,51.51902530863286],"type":"Point"}
}