{
  "type": "Feature",
  "properties": {
    "date:inception_lower": "2015-07-01",
    "date:inception_upper": "2015-07-01",
    "iso:country": "GB",
    "wof:name": "LA11 7NN",
    "wof:placetype": "postalcode"
  },
  "geometry": {"coordinates":[-2.970182,54.175145],"type":"Point"}
}
