{
  "type": "Feature",
  "properties": {
    "date:inception_lower": "1980-01-01",
    "date:inception_upper": "1980-01-01",
    "iso:country": "GB",
    "wof:name": "BD19 4NN",
    "wof:placetype": "postalcode"
  },
  "geometry": {"coordinates":[-1.689756,53.727622],"type":"Point"}
}
