{
  "type": "Feature",
  "properties": {
    "iso:country":"GB",
    "wof:name":"BD19 4NN",
    "wof:placetype":"postalcode"
},
  "geometry": {"coordinates":[-1.68975582097688,53.72762207130646],"type":"Point"}
}