{
  "type": "Feature",
  "properties": {
    "iso:country": "GB",
    "wof:name": "ST13 7HW",
    "wof:placetype": "postalcode"
  },
  "geometry": {"coordinates":[-2.043147,53.065783],"type":"Point"}
}
