{
  "type": "Feature",
  "properties": {
    "iso:country": "GB",
    "wof:name": "WC1H 8LJ",
    "wof:placetype": "postalcode"
  },
  "geometry": {"coordinates":[-0.12054,51.527912],"type":"Point"}
}
