{
  "type": "Feature",
  "properties": {
    "iso:country":"GB",
    "wof:name":"B7 5QN",
    "wof:placetype":"postalcode"
},
  "geometry": {"coordinates":[-1.86140748621575,52.50185282075252],"type":"Point"}
}