{
  "type": "Feature",
  "properties": {
    "iso:country": "GB",
    "wof:name": "FK8 2AU",
    "wof:placetype": "postalcode"
  },
  "geometry": {"coordinates":[-3.935893,56.1068],"type":"Point"}
}
