{
  "type": "Feature",
  "properties": {
    "iso:country": "GB",
    "wof:name": "HU6 9QH",
    "wof:placetype": "postalcode"
  },
  "geometry": {"coordinates":[-0.378628,53.783234],"type":"Point"}
}
