{
  "type": "Feature",
  "properties": {
    "iso:country": "GB",
    "wof:name": "DN20 0PE",
    "wof:placetype": "postalcode"
  },
  "geometry": {"coordinates":[-0.469783,53.612561],"type":"Point"}
}
