{
  "type": "Feature",
  "properties": {
    "iso:country":"GB",
    "wof:name":"ME8 9UY",
    "wof:placetype":"postalcode"
},
  "geometry": {"coordinates":[0.59074370520696,51.33949271108668],"type":"Point"}
}