{
  "type": "Feature",
  "properties": {
    "iso:country":"GB",
    "wof:name":"CB23 8EA",
    "wof:placetype":"postalcode"
},
  "geometry": {"coordinates":[0.01451804686779,52.25321864187162],"type":"Point"}
}