{
  "type": "Feature",
  "properties": {
    "date:inception_lower": "2006-09-01",
    "date:inception_upper": "2006-09-01",
    "iso:country": "GB",
    "wof:name": "CB23 8EA",
    "wof:placetype": "postalcode"
  },
  "geometry": {"coordinates":[0.014518,52.253219],"type":"Point"}
}
