{
  "type": "Feature",
  "properties": {
    "iso:country":"GB",
    "wof:name":"RM8 3QA",
    "wof:placetype":"postalcode"
},
  "geometry": {"coordinates":[0.13921717624292,51.56002674513729],"type":"Point"}
}