{
  "type": "Feature",
  "properties": {
    "iso:country":"GB",
    "wof:name":"NR16 1EG",
    "wof:placetype":"postalcode"
},
  "geometry": {"coordinates":[1.17670572655434,52.52295616249182],"type":"Point"}
}