{
  "type": "Feature",
  "properties": {
    "date:inception_lower": "1980-01-01",
    "date:inception_upper": "1980-01-01",
    "iso:country": "GB",
    "wof:name": "NE46 1EE",
    "wof:placetype": "postalcode"
  },
  "geometry": {"coordinates":[-2.091015,54.966981],"type":"Point"}
}
