{
  "type": "Feature",
  "properties": {
    "iso:country":"GB",
    "wof:name":"IV36 1BU",
    "wof:placetype":"postalcode"
},
  "geometry": {"coordinates":[-3.60966280674678,57.61206033669391],"type":"Point"}
}