{
  "type": "Feature",
  "properties": {
    "date:inception_lower":"1998-12-01",
    "date:inception_upper":"1998-12-31",
    "iso:country":"GB",
    "wof:name":"IV36 1BU",
    "wof:placetype":"postalcode"
},
  "geometry": {"coordinates":[-3.609663,57.61206],"type":"Point"}
}