{
  "type": "Feature",
  "properties": {
    "iso:country": "GB",
    "wof:name": "IV36 1BU",
    "wof:placetype": "postalcode"
  },
  "geometry": {"coordinates":[-3.609663,57.61206],"type":"Point"}
}
