{
  "type": "Feature",
  "properties": {
    "iso:country":"GB",
    "wof:name":"ME13 9BE",
    "wof:placetype":"postalcode"
},
  "geometry": {"coordinates":[0.95658719657389,51.29498198631367],"type":"Point"}
}