{
  "type": "Feature",
  "properties": {
    "iso:country": "GB",
    "wof:name": "ME13 9BE",
    "wof:placetype": "postalcode"
  },
  "geometry": {"coordinates":[0.956587,51.294982],"type":"Point"}
}
