{
  "type": "Feature",
  "properties": {
    "iso:country":"GB",
    "wof:name":"DH4 6SW",
    "wof:placetype":"postalcode"
},
  "geometry": {"coordinates":[-1.49755048520495,54.81559986379376],"type":"Point"}
}