{
  "type": "Feature",
  "properties": {
    "iso:country": "GB",
    "wof:name": "DH4 6SW",
    "wof:placetype": "postalcode"
  },
  "geometry": {"coordinates":[-1.49755,54.8156],"type":"Point"}
}
