{
  "type": "Feature",
  "properties": {
    "date:inception_lower": "2000-06-01",
    "date:inception_upper": "2000-06-01",
    "iso:country": "GB",
    "wof:name": "DH4 6SW",
    "wof:placetype": "postalcode"
  },
  "geometry": {"coordinates":[-1.49755,54.8156],"type":"Point"}
}
