{
  "type": "Feature",
  "properties": {
    "iso:country": "GB",
    "wof:name": "OX26 2AR",
    "wof:placetype": "postalcode"
  },
  "geometry": {"coordinates":[-1.162273,51.89801],"type":"Point"}
}
