{
  "type": "Feature",
  "properties": {
    "date:inception_lower": "1980-01-01",
    "date:inception_upper": "1980-01-01",
    "iso:country": "GB",
    "wof:name": "DL3 6NL",
    "wof:placetype": "postalcode"
  },
  "geometry": {"coordinates":[-1.558945,54.532981],"type":"Point"}
}
