{
  "type": "Feature",
  "properties": {
    "iso:country":"GB",
    "wof:name":"CT15 4JR",
    "wof:placetype":"postalcode"
},
  "geometry": {"coordinates":[1.21031253544705,51.21923244628118],"type":"Point"}
}