{
  "type": "Feature",
  "properties": {
    "iso:country":"GB",
    "wof:name":"UB4 8QF",
    "wof:placetype":"postalcode"
},
  "geometry": {"coordinates":[-0.43989649289464,51.53538119425968],"type":"Point"}
}