{
  "type": "Feature",
  "properties": {
    "date:inception_lower":"1980-01-01",
    "date:inception_upper":"1980-01-31",
    "iso:country":"GB",
    "wof:name":"CO16 9HU",
    "wof:placetype":"postalcode"
},
  "geometry": {"coordinates":[1.11777,51.854269],"type":"Point"}
}