{
  "type": "Feature",
  "properties": {
    "date:inception_lower":"1980-01-01",
    "date:inception_upper":"1980-01-31",
    "iso:country":"GB",
    "wof:name":"WF17 6AW",
    "wof:placetype":"postalcode"
},
  "geometry": {"coordinates":[-1.629418,53.707323],"type":"Point"}
}