{
  "type": "Feature",
  "properties": {
    "iso:country":"GB",
    "wof:name":"WF17 6AW",
    "wof:placetype":"postalcode"
},
  "geometry": {"coordinates":[-1.62938370898474,53.70735323837769],"type":"Point"}
}