{
  "type": "Feature",
  "properties": {
    "iso:country":"GB",
    "wof:name":"S41 8QP",
    "wof:placetype":"postalcode"
},
  "geometry": {"coordinates":[-1.44643056034834,53.25415506459907],"type":"Point"}
}