{
  "type": "Feature",
  "properties": {
    "iso:country": "GB",
    "wof:name": "LL16 3PW",
    "wof:placetype": "postalcode"
  },
  "geometry": {"coordinates":[-3.425173,53.185599],"type":"Point"}
}
