{
  "type": "Feature",
  "properties": {
    "iso:country":"GB",
    "wof:name":"LL16 3PW",
    "wof:placetype":"postalcode"
},
  "geometry": {"coordinates":[-3.42517329965763,53.18559885660678],"type":"Point"}
}