{
  "type": "Feature",
  "properties": {
    "date:inception_lower": "1980-01-01",
    "date:inception_upper": "1980-01-01",
    "iso:country": "GB",
    "wof:name": "ME12 1LQ",
    "wof:placetype": "postalcode"
  },
  "geometry": {"coordinates":[0.746593,51.428168],"type":"Point"}
}
