{
  "type": "Feature",
  "properties": {
    "iso:country":"GB",
    "wof:name":"ME12 1LQ",
    "wof:placetype":"postalcode"
},
  "geometry": {"coordinates":[0.74647817331088,51.42819351937112],"type":"Point"}
}