{
  "type": "Feature",
  "properties": {
    "iso:country":"GB",
    "wof:name":"TR1 3SF",
    "wof:placetype":"postalcode"
},
  "geometry": {"coordinates":[-5.05838412063786,50.26776892231581],"type":"Point"}
}