{
  "type": "Feature",
  "properties": {
    "iso:country":"GB",
    "wof:name":"UB5 6UF",
    "wof:placetype":"postalcode"
},
  "geometry": {"coordinates":[-0.36626138058284,51.5365730265594],"type":"Point"}
}