{
  "type": "Feature",
  "properties": {
    "date:inception_lower":"2002-12-01",
    "date:inception_upper":"2002-12-31",
    "iso:country":"GB",
    "wof:name":"NR6 7PR",
    "wof:placetype":"postalcode"
},
  "geometry": {"coordinates":[1.316541,52.667127],"type":"Point"}
}