{
  "type": "Feature",
  "properties": {
    "date:inception_lower": "2017-10-01",
    "date:inception_upper": "2017-10-01",
    "iso:country": "GB",
    "wof:name": "WA16 8BF",
    "wof:placetype": "postalcode"
  },
  "geometry": {"coordinates":[-2.326219,53.270406],"type":"Point"}
}
