{
  "type": "Feature",
  "properties": {
    "iso:country":"GB",
    "wof:name":"G84 9ET",
    "wof:placetype":"postalcode"
},
  "geometry": {"coordinates":[-4.71013436048142,56.00666573425526],"type":"Point"}
}