{
  "type": "Feature",
  "properties": {
    "date:inception_lower": "1990-07-01",
    "date:inception_upper": "1990-07-01",
    "iso:country": "GB",
    "wof:name": "YO15 3NX",
    "wof:placetype": "postalcode"
  },
  "geometry": {"coordinates":[-0.211928,54.074574],"type":"Point"}
}
