{
  "type": "Feature",
  "properties": {
    "date:inception_lower": "1980-01-01",
    "date:inception_upper": "1980-01-01",
    "iso:country": "GB",
    "wof:name": "CM23 3PW",
    "wof:placetype": "postalcode"
  },
  "geometry": {"coordinates":[0.155269,51.859196],"type":"Point"}
}
