{
  "type": "Feature",
  "properties": {
    "iso:country":"GB",
    "wof:name":"S6 4NE",
    "wof:placetype":"postalcode"
},
  "geometry": {"coordinates":[-1.51068272105003,53.40159990027448],"type":"Point"}
}