{
  "type": "Feature",
  "properties": {
    "date:inception_lower": "2024-01-01",
    "date:inception_upper": "2024-01-01",
    "iso:country": "GB",
    "wof:name": "SA18 2FQ",
    "wof:placetype": "postalcode"
  },
  "geometry": {"coordinates":[-4.002736,51.819681],"type":"Point"}
}
