{
  "type": "Feature",
  "properties": {
    "date:inception_lower":"1980-01-01",
    "date:inception_upper":"1980-01-31",
    "iso:country":"GB",
    "wof:name":"HR4 8NW",
    "wof:placetype":"postalcode"
},
  "geometry": {"coordinates":[-2.765289,52.116681],"type":"Point"}
}