{
  "type": "Feature",
  "properties": {
    "iso:country": "GB",
    "wof:name": "HR4 8NW",
    "wof:placetype": "postalcode"
  },
  "geometry": {"coordinates":[-2.765289,52.116681],"type":"Point"}
}
