{
  "type": "Feature",
  "properties": {
    "iso:country":"GB",
    "wof:name":"HR4 8NW",
    "wof:placetype":"postalcode"
},
  "geometry": {"coordinates":[-2.76722133870112,52.11701919873467],"type":"Point"}
}