{
  "type": "Feature",
  "properties": {
    "date:inception_lower": "2003-05-01",
    "date:inception_upper": "2003-05-01",
    "iso:country": "GB",
    "wof:name": "IG11 8RU",
    "wof:placetype": "postalcode"
  },
  "geometry": {"coordinates":[0.08212,51.539662],"type":"Point"}
}
