{
  "type": "Feature",
  "properties": {
    "date:inception_lower":"1992-08-01",
    "date:inception_upper":"1992-08-31",
    "iso:country":"GB",
    "wof:name":"CW12 4FJ",
    "wof:placetype":"postalcode"
},
  "geometry": {"coordinates":[-2.22779,53.16188],"type":"Point"}
}