{
  "type": "Feature",
  "properties": {
    "iso:country":"GB",
    "wof:name":"CW12 4FJ",
    "wof:placetype":"postalcode"
},
  "geometry": {"coordinates":[-2.22779048488089,53.16188042024744],"type":"Point"}
}