{
  "type": "Feature",
  "properties": {
    "date:inception_lower": "1995-07-01",
    "date:inception_upper": "1995-07-01",
    "iso:country": "GB",
    "wof:name": "RG30 6AY",
    "wof:placetype": "postalcode"
  },
  "geometry": {"coordinates":[-1.014669,51.466166],"type":"Point"}
}
