{
  "type": "Feature",
  "properties": {
    "iso:country":"GB",
    "wof:name":"RG30 6AY",
    "wof:placetype":"postalcode"
},
  "geometry": {"coordinates":[-1.0146694276463,51.46616551576346],"type":"Point"}
}