{
  "type": "Feature",
  "properties": {
    "date:inception_lower": "2003-06-01",
    "date:inception_upper": "2003-06-01",
    "iso:country": "GB",
    "wof:name": "LL19 7UQ",
    "wof:placetype": "postalcode"
  },
  "geometry": {"coordinates":[-3.427848,53.336672],"type":"Point"}
}
