{
  "type": "Feature",
  "properties": {
    "iso:country":"GB",
    "wof:name":"LL19 7UQ",
    "wof:placetype":"postalcode"
},
  "geometry": {"coordinates":[-3.42784839816386,53.33667232407532],"type":"Point"}
}