{
  "type": "Feature",
  "properties": {
    "iso:country":"GB",
    "wof:name":"SK8 6LR",
    "wof:placetype":"postalcode"
},
  "geometry": {"coordinates":[-2.18925597750982,53.36718869140928],"type":"Point"}
}