{
  "type": "Feature",
  "properties": {
    "iso:country": "GB",
    "wof:name": "SK8 6LR",
    "wof:placetype": "postalcode"
  },
  "geometry": {"coordinates":[-2.189256,53.367189],"type":"Point"}
}
