{
  "type": "Feature",
  "properties": {
    "iso:country":"GB",
    "wof:name":"ST15 0PS",
    "wof:placetype":"postalcode"
},
  "geometry": {"coordinates":[-2.1634199560749,52.91033586693803],"type":"Point"}
}