{
  "type": "Feature",
  "properties": {
    "iso:country":"GB",
    "wof:name":"M44 6PW",
    "wof:placetype":"postalcode"
},
  "geometry": {"coordinates":[-2.4194835424149,53.45527379390526],"type":"Point"}
}