{
  "type": "Feature",
  "properties": {
    "iso:country":"GB",
    "wof:name":"DN11 9UX",
    "wof:placetype":"postalcode"
},
  "geometry": {"coordinates":[-1.1019970796331,53.43809447652303],"type":"Point"}
}