{
  "type": "Feature",
  "properties": {
    "date:inception_lower":"1990-02-01",
    "date:inception_upper":"1990-02-28",
    "iso:country":"GB",
    "wof:name":"DN11 9UX",
    "wof:placetype":"postalcode"
},
  "geometry": {"coordinates":[-1.101997,53.438094],"type":"Point"}
}