{
  "type": "Feature",
  "properties": {
    "iso:country":"GB",
    "wof:name":"YO30 1YT",
    "wof:placetype":"postalcode"
},
  "geometry": {"coordinates":[-1.13044746230725,53.99739145534273],"type":"Point"}
}