{
  "type": "Feature",
  "properties": {
    "iso:country": "GB",
    "wof:name": "YO30 1YT",
    "wof:placetype": "postalcode"
  },
  "geometry": {"coordinates":[-1.130394,53.997426],"type":"Point"}
}
