{
  "type": "Feature",
  "properties": {
    "iso:country": "GB",
    "wof:name": "NR28 0PU",
    "wof:placetype": "postalcode"
  },
  "geometry": {"coordinates":[1.390843,52.863244],"type":"Point"}
}
