{
  "type": "Feature",
  "properties": {
    "date:inception_lower": "1980-01-01",
    "date:inception_upper": "1980-01-01",
    "iso:country": "GB",
    "wof:name": "IP19 9LD",
    "wof:placetype": "postalcode"
  },
  "geometry": {"coordinates":[1.579442,52.329054],"type":"Point"}
}
