{
  "type": "Feature",
  "properties": {
    "iso:country": "GB",
    "wof:name": "IP19 9LD",
    "wof:placetype": "postalcode"
  },
  "geometry": {"coordinates":[1.579442,52.329054],"type":"Point"}
}
