{
  "type": "Feature",
  "properties": {
    "date:inception_lower": "1998-12-01",
    "date:inception_upper": "1998-12-01",
    "iso:country": "GB",
    "wof:name": "KY11 8TT",
    "wof:placetype": "postalcode"
  },
  "geometry": {"coordinates":[-3.413576,56.052009],"type":"Point"}
}
