{
  "type": "Feature",
  "properties": {
    "iso:country": "GB",
    "wof:name": "L16 3GU",
    "wof:placetype": "postalcode"
  },
  "geometry": {"coordinates":[-2.882223,53.400976],"type":"Point"}
}
