{
  "type": "Feature",
  "properties": {
    "iso:country": "GB",
    "wof:name": "OX7 5TH",
    "wof:placetype": "postalcode"
  },
  "geometry": {"coordinates":[-1.482863,51.960111],"type":"Point"}
}
