{
  "type": "Feature",
  "properties": {
    "iso:country":"GB",
    "wof:name":"OX7 5TH",
    "wof:placetype":"postalcode"
},
  "geometry": {"coordinates":[-1.48286340622546,51.96011136800355],"type":"Point"}
}