{
  "type": "Feature",
  "properties": {
    "date:inception_lower": "2000-06-01",
    "date:inception_upper": "2000-06-01",
    "iso:country": "GB",
    "wof:name": "RG41 2XW",
    "wof:placetype": "postalcode"
  },
  "geometry": {"coordinates":[-0.852475,51.405649],"type":"Point"}
}
