{
  "type": "Feature",
  "properties": {
    "iso:country":"GB",
    "wof:name":"RG41 2XW",
    "wof:placetype":"postalcode"
},
  "geometry": {"coordinates":[-0.85247459060856,51.4056494796197],"type":"Point"}
}