{
  "type": "Feature",
  "properties": {
    "iso:country": "GB",
    "wof:name": "TN30 6HG",
    "wof:placetype": "postalcode"
  },
  "geometry": {"coordinates":[0.682045,51.071789],"type":"Point"}
}
