{
  "type": "Feature",
  "properties": {
    "date:inception_lower": "1980-01-01",
    "date:inception_upper": "1980-01-01",
    "iso:country": "GB",
    "wof:name": "TN30 6HG",
    "wof:placetype": "postalcode"
  },
  "geometry": {"coordinates":[0.682045,51.071789],"type":"Point"}
}
