{
  "type": "Feature",
  "properties": {
    "iso:country":"GB",
    "wof:name":"PL6 7SZ",
    "wof:placetype":"postalcode"
},
  "geometry": {"coordinates":[-4.09966229209644,50.43545718704485],"type":"Point"}
}