{
  "type": "Feature",
  "properties": {
    "date:inception_lower": "1990-02-01",
    "date:inception_upper": "1990-02-01",
    "iso:country": "GB",
    "wof:name": "PL6 7SZ",
    "wof:placetype": "postalcode"
  },
  "geometry": {"coordinates":[-4.099662,50.435457],"type":"Point"}
}
