{
  "type": "Feature",
  "properties": {
    "iso:country":"GB",
    "wof:name":"KY4 9BN",
    "wof:placetype":"postalcode"
},
  "geometry": {"coordinates":[-3.34440321392858,56.11702788404731],"type":"Point"}
}