{
  "type": "Feature",
  "properties": {
    "iso:country":"GB",
    "wof:name":"DT11 8PL",
    "wof:placetype":"postalcode"
},
  "geometry": {"coordinates":[-2.11884101714421,50.87097218537523],"type":"Point"}
}