{
  "type": "Feature",
  "properties": {
    "date:inception_lower": "2006-07-01",
    "date:inception_upper": "2006-07-01",
    "iso:country": "GB",
    "wof:name": "DT11 8PL",
    "wof:placetype": "postalcode"
  },
  "geometry": {"coordinates":[-2.118841,50.870972],"type":"Point"}
}
