{
  "type": "Feature",
  "properties": {
    "iso:country":"GB",
    "wof:name":"TS3 8PN",
    "wof:placetype":"postalcode"
},
  "geometry": {"coordinates":[-1.20137941501321,54.56235286968023],"type":"Point"}
}