{
  "type": "Feature",
  "properties": {
    "iso:country": "GB",
    "wof:name": "M24 6AS",
    "wof:placetype": "postalcode"
  },
  "geometry": {"coordinates":[-2.190757,53.555106],"type":"Point"}
}
