{
  "type": "Feature",
  "properties": {
    "iso:country":"GB",
    "wof:name":"M24 6AS",
    "wof:placetype":"postalcode"
},
  "geometry": {"coordinates":[-2.19071359246801,53.55511748195499],"type":"Point"}
}