{
  "type": "Feature",
  "properties": {
    "iso:country":"GB",
    "wof:name":"TR16 5EP",
    "wof:placetype":"postalcode"
},
  "geometry": {"coordinates":[-5.21428581292416,50.23487854668293],"type":"Point"}
}