{
  "type": "Feature",
  "properties": {
    "iso:country": "GB",
    "wof:name": "TR16 5EP",
    "wof:placetype": "postalcode"
  },
  "geometry": {"coordinates":[-5.214286,50.234879],"type":"Point"}
}
