{
  "type": "Feature",
  "properties": {
    "iso:country": "GB",
    "wof:name": "NE33 5LT",
    "wof:placetype": "postalcode"
  },
  "geometry": {"coordinates":[-1.436806,54.982823],"type":"Point"}
}
