{
  "type": "Feature",
  "properties": {
    "iso:country":"GB",
    "wof:name":"SE3 0LR",
    "wof:placetype":"postalcode"
},
  "geometry": {"coordinates":[0.02297688717738,51.47253038348793],"type":"Point"}
}