{
  "type": "Feature",
  "properties": {
    "iso:country": "GB",
    "wof:name": "NN10 0JT",
    "wof:placetype": "postalcode"
  },
  "geometry": {"coordinates":[-0.592932,52.288104],"type":"Point"}
}
