{
  "type": "Feature",
  "properties": {
    "iso:country":"GB",
    "wof:name":"N11 2JP",
    "wof:placetype":"postalcode"
},
  "geometry": {"coordinates":[-0.13078598730938,51.61103086270316],"type":"Point"}
}