{
  "type": "Feature",
  "properties": {
    "iso:country":"GB",
    "wof:name":"SN6 7HT",
    "wof:placetype":"postalcode"
},
  "geometry": {"coordinates":[-1.71973835902097,51.63602201568168],"type":"Point"}
}