{
  "type": "Feature",
  "properties": {
    "iso:country":"GB",
    "wof:name":"ME19 6RW",
    "wof:placetype":"postalcode"
},
  "geometry": {"coordinates":[0.39899716135828,51.29659652064178],"type":"Point"}
}