{
  "type": "Feature",
  "properties": {
    "iso:country": "GB",
    "wof:name": "ME19 6RW",
    "wof:placetype": "postalcode"
  },
  "geometry": {"coordinates":[0.398997,51.296597],"type":"Point"}
}
