{
  "type": "Feature",
  "properties": {
    "date:inception_lower": "2012-12-01",
    "date:inception_upper": "2012-12-01",
    "iso:country": "GB",
    "wof:name": "M8 0AE",
    "wof:placetype": "postalcode"
  },
  "geometry": {"coordinates":[-2.229812,53.500478],"type":"Point"}
}
