{
  "type": "Feature",
  "properties": {
    "date:inception_lower": "2012-12-01",
    "date:inception_upper": "2012-12-01",
    "iso:country": "GB",
    "wof:name": "M8 0AE",
    "wof:placetype": "postalcode"
  },
  "geometry": {"coordinates":[-2.230131,53.501017],"type":"Point"}
}
