{
  "type": "Feature",
  "properties": {
    "iso:country":"GB",
    "wof:name":"M8 0AE",
    "wof:placetype":"postalcode"
},
  "geometry": {"coordinates":[-2.23121208532743,53.49965953442319],"type":"Point"}
}