{
  "type": "Feature",
  "properties": {
    "iso:country":"GB",
    "wof:name":"BS28 4PA",
    "wof:placetype":"postalcode"
},
  "geometry": {"coordinates":[-2.8550780005539,51.22467142485837],"type":"Point"}
}