{
  "type": "Feature",
  "properties": {
    "date:inception_lower":"1980-01-01",
    "date:inception_upper":"1980-01-31",
    "iso:country":"GB",
    "wof:name":"BS28 4PA",
    "wof:placetype":"postalcode"
},
  "geometry": {"coordinates":[-2.855078,51.224671],"type":"Point"}
}