{
  "type": "Feature",
  "properties": {
    "date:inception_lower":"1980-01-01",
    "date:inception_upper":"1980-01-31",
    "iso:country":"GB",
    "wof:name":"BL1 5PS",
    "wof:placetype":"postalcode"
},
  "geometry": {"coordinates":[-2.470502,53.588338],"type":"Point"}
}