{
  "type": "Feature",
  "properties": {
    "iso:country":"GB",
    "wof:name":"BL1 5PS",
    "wof:placetype":"postalcode"
},
  "geometry": {"coordinates":[-2.47054690285249,53.58831046851767],"type":"Point"}
}