{
  "type": "Feature",
  "properties": {
    "iso:country": "GB",
    "wof:name": "BL1 5PS",
    "wof:placetype": "postalcode"
  },
  "geometry": {"coordinates":[-2.470502,53.588338],"type":"Point"}
}
