{
  "type": "Feature",
  "properties": {
    "iso:country":"GB",
    "wof:name":"NG8 1FJ",
    "wof:placetype":"postalcode"
},
  "geometry": {"coordinates":[-1.1981315079866,52.95335713421395],"type":"Point"}
}