{
  "type": "Feature",
  "properties": {
    "iso:country": "GB",
    "wof:name": "M40 0BR",
    "wof:placetype": "postalcode"
  },
  "geometry": {"coordinates":[-2.176953,53.516857],"type":"Point"}
}
