{
  "type": "Feature",
  "properties": {
    "iso:country": "GB",
    "wof:name": "SA14 8PP",
    "wof:placetype": "postalcode"
  },
  "geometry": {"coordinates":[-4.138755,51.693513],"type":"Point"}
}
