{
  "type": "Feature",
  "properties": {
    "iso:country":"GB",
    "wof:name":"SA14 8PP",
    "wof:placetype":"postalcode"
},
  "geometry": {"coordinates":[-4.13879889234939,51.69352134885196],"type":"Point"}
}