{
  "type": "Feature",
  "properties": {
    "date:inception_lower":"1995-01-01",
    "date:inception_upper":"1995-01-31",
    "iso:country":"GB",
    "wof:name":"SA14 8PP",
    "wof:placetype":"postalcode"
},
  "geometry": {"coordinates":[-4.138755,51.693513],"type":"Point"}
}