{
  "type": "Feature",
  "properties": {
    "iso:country":"GB",
    "wof:name":"IV30 8NQ",
    "wof:placetype":"postalcode"
},
  "geometry": {"coordinates":[-3.24745291630438,57.67370104429519],"type":"Point"}
}