{
  "type": "Feature",
  "properties": {
    "iso:country": "GB",
    "wof:name": "IV30 8NQ",
    "wof:placetype": "postalcode"
  },
  "geometry": {"coordinates":[-3.247453,57.673701],"type":"Point"}
}
