{
  "type": "Feature",
  "properties": {
    "iso:country":"GB",
    "wof:name":"DY6 0JB",
    "wof:placetype":"postalcode"
},
  "geometry": {"coordinates":[-2.17841269192632,52.50915254208252],"type":"Point"}
}