{
  "type": "Feature",
  "properties": {
    "iso:country":"GB",
    "wof:name":"UB4 0DR",
    "wof:placetype":"postalcode"
},
  "geometry": {"coordinates":[-0.40645762429741,51.52058022348329],"type":"Point"}
}