{
  "type": "Feature",
  "properties": {
    "iso:country": "GB",
    "wof:name": "NG5 1EB",
    "wof:placetype": "postalcode"
  },
  "geometry": {"coordinates":[-1.159482,52.979737],"type":"Point"}
}
