{
  "type": "Feature",
  "properties": {
    "iso:country": "GB",
    "wof:name": "NR13 4TY",
    "wof:placetype": "postalcode"
  },
  "geometry": {"coordinates":[1.440043,52.633958],"type":"Point"}
}
