{
  "type": "Feature",
  "properties": {
    "iso:country":"GB",
    "wof:name":"SW14 8ET",
    "wof:placetype":"postalcode"
},
  "geometry": {"coordinates":[-0.26436365598318,51.46939344203092],"type":"Point"}
}