{
  "type": "Feature",
  "properties": {
    "iso:country":"GB",
    "wof:name":"NW10 0NS",
    "wof:placetype":"postalcode"
},
  "geometry": {"coordinates":[-0.26310799068417,51.55170003784951],"type":"Point"}
}