{
  "type": "Feature",
  "properties": {
    "iso:country": "GB",
    "wof:name": "BH22 0PJ",
    "wof:placetype": "postalcode"
  },
  "geometry": {"coordinates":[-1.879714,50.81814],"type":"Point"}
}
