{
  "type": "Feature",
  "properties": {
    "date:inception_lower":"1980-01-01",
    "date:inception_upper":"1980-01-31",
    "iso:country":"GB",
    "wof:name":"BH22 0PJ",
    "wof:placetype":"postalcode"
},
  "geometry": {"coordinates":[-1.879714,50.81814],"type":"Point"}
}