{
  "type": "Feature",
  "properties": {
    "date:inception_lower": "1980-01-01",
    "date:inception_upper": "1980-01-01",
    "iso:country": "GB",
    "wof:name": "MK18 2NL",
    "wof:placetype": "postalcode"
  },
  "geometry": {"coordinates":[-0.930086,51.92366],"type":"Point"}
}
