{
  "type": "Feature",
  "properties": {
    "iso:country":"GB",
    "wof:name":"MK18 2NL",
    "wof:placetype":"postalcode"
},
  "geometry": {"coordinates":[-0.93008602483014,51.92365951377803],"type":"Point"}
}