{
  "type": "Feature",
  "properties": {
    "iso:country":"GB",
    "wof:name":"PR2 2AN",
    "wof:placetype":"postalcode"
},
  "geometry": {"coordinates":[-2.7184241894024,53.76827444681569],"type":"Point"}
}