{
  "type": "Feature",
  "properties": {
    "date:inception_lower": "1980-01-01",
    "date:inception_upper": "1980-01-01",
    "iso:country": "GB",
    "wof:name": "SL6 0NS",
    "wof:placetype": "postalcode"
  },
  "geometry": {"coordinates":[-0.677387,51.524121],"type":"Point"}
}
