{
  "type": "Feature",
  "properties": {
    "iso:country":"GB",
    "wof:name":"SL6 0NS",
    "wof:placetype":"postalcode"
},
  "geometry": {"coordinates":[-0.67762851309135,51.52435482521987],"type":"Point"}
}