{
  "type": "Feature",
  "properties": {
    "iso:country": "GB",
    "wof:name": "SL6 0NS",
    "wof:placetype": "postalcode"
  },
  "geometry": {"coordinates":[-0.677214,51.52411],"type":"Point"}
}
