{
  "type": "Feature",
  "properties": {
    "date:inception_lower": "1998-06-01",
    "date:inception_upper": "1998-06-01",
    "iso:country": "GB",
    "wof:name": "YO26 9SD",
    "wof:placetype": "postalcode"
  },
  "geometry": {"coordinates":[-1.330614,54.061809],"type":"Point"}
}
