{
  "type": "Feature",
  "properties": {
    "date:inception_lower":"2008-02-01",
    "date:inception_upper":"2008-02-29",
    "iso:country":"GB",
    "wof:name":"WS12 4FD",
    "wof:placetype":"postalcode"
},
  "geometry": {"coordinates":[-2.007136,52.711916],"type":"Point"}
}