{
  "type": "Feature",
  "properties": {
    "iso:country":"GB",
    "wof:name":"WS12 4FD",
    "wof:placetype":"postalcode"
},
  "geometry": {"coordinates":[-2.00713637441326,52.71191633848818],"type":"Point"}
}