{
  "type": "Feature",
  "properties": {
    "iso:country": "GB",
    "wof:name": "PO8 0UX",
    "wof:placetype": "postalcode"
  },
  "geometry": {"coordinates":[-1.009316,50.946209],"type":"Point"}
}
