{
  "type": "Feature",
  "properties": {
    "iso:country":"GB",
    "wof:name":"PO8 0UX",
    "wof:placetype":"postalcode"
},
  "geometry": {"coordinates":[-1.00931571094072,50.94620909540932],"type":"Point"}
}