{
  "type": "Feature",
  "properties": {
    "date:inception_lower": "2018-09-01",
    "date:inception_upper": "2018-09-01",
    "iso:country": "GB",
    "wof:name": "NN16 9FU",
    "wof:placetype": "postalcode"
  },
  "geometry": {"coordinates":[-0.725353,52.407086],"type":"Point"}
}
