{
  "type": "Feature",
  "properties": {
    "iso:country":"GB",
    "wof:name":"B11 3JD",
    "wof:placetype":"postalcode"
},
  "geometry": {"coordinates":[-1.84558151115381,52.44835191013686],"type":"Point"}
}