{
  "type": "Feature",
  "properties": {
    "iso:country":"GB",
    "wof:name":"TW18 1AB",
    "wof:placetype":"postalcode"
},
  "geometry": {"coordinates":[-0.49859233631051,51.43193664171268],"type":"Point"}
}