{
  "type": "Feature",
  "properties": {
    "iso:country": "GB",
    "wof:name": "TW18 1AB",
    "wof:placetype": "postalcode"
  },
  "geometry": {"coordinates":[-0.498572,51.431936],"type":"Point"}
}
