{
  "type": "Feature",
  "properties": {
    "iso:country":"GB",
    "wof:name":"HA4 0UU",
    "wof:placetype":"postalcode"
},
  "geometry": {"coordinates":[-0.39967642061998,51.56352452999867],"type":"Point"}
}