{
  "type": "Feature",
  "properties": {
    "date:inception_lower": "1980-01-01",
    "date:inception_upper": "1980-01-01",
    "iso:country": "GB",
    "wof:name": "HA4 0UU",
    "wof:placetype": "postalcode"
  },
  "geometry": {"coordinates":[-0.399676,51.563525],"type":"Point"}
}
