{
  "type": "Feature",
  "properties": {
    "iso:country": "GB",
    "wof:name": "PO6 3RN",
    "wof:placetype": "postalcode"
  },
  "geometry": {"coordinates":[-1.080662,50.85219],"type":"Point"}
}
