{
  "type": "Feature",
  "properties": {
    "iso:country":"GB",
    "wof:name":"PO6 3RN",
    "wof:placetype":"postalcode"
},
  "geometry": {"coordinates":[-1.08066239468506,50.85218993451604],"type":"Point"}
}