{
  "type": "Feature",
  "properties": {
    "date:inception_lower":"1996-06-01",
    "date:inception_upper":"1996-06-30",
    "iso:country":"GB",
    "wof:name":"AB21 0GW",
    "wof:placetype":"postalcode"
},
  "geometry": {"coordinates":[-2.213684,57.204293],"type":"Point"}
}