{
  "type": "Feature",
  "properties": {
    "iso:country":"GB",
    "wof:name":"AB21 0GW",
    "wof:placetype":"postalcode"
},
  "geometry": {"coordinates":[-2.21368367557636,57.20429328033696],"type":"Point"}
}