{
  "type": "Feature",
  "properties": {
    "iso:country":"GB",
    "wof:name":"SK9 7TJ",
    "wof:placetype":"postalcode"
},
  "geometry": {"coordinates":[-2.26274530564445,53.29416011613854],"type":"Point"}
}