{
  "type": "Feature",
  "properties": {
    "iso:country":"GB",
    "wof:name":"IG1 2JE",
    "wof:placetype":"postalcode"
},
  "geometry": {"coordinates":[0.07316328413851,51.54689617913528],"type":"Point"}
}