{
  "type": "Feature",
  "properties": {
    "iso:country":"GB",
    "wof:name":"B74 3QN",
    "wof:placetype":"postalcode"
},
  "geometry": {"coordinates":[-1.89059229871026,52.57837814063326],"type":"Point"}
}