{
  "type": "Feature",
  "properties": {
    "iso:country": "GB",
    "wof:name": "NG34 7JH",
    "wof:placetype": "postalcode"
  },
  "geometry": {"coordinates":[-0.394144,52.996036],"type":"Point"}
}
