{
  "type": "Feature",
  "properties": {
    "date:inception_lower": "1994-12-01",
    "date:inception_upper": "1994-12-01",
    "iso:country": "GB",
    "wof:name": "NG34 7JH",
    "wof:placetype": "postalcode"
  },
  "geometry": {"coordinates":[-0.394144,52.996036],"type":"Point"}
}
