{
  "type": "Feature",
  "properties": {
    "iso:country":"GB",
    "wof:name":"BS22 9EF",
    "wof:placetype":"postalcode"
},
  "geometry": {"coordinates":[-2.93351288171799,51.36263026891837],"type":"Point"}
}