{
  "type": "Feature",
  "properties": {
    "iso:country":"GB",
    "wof:name":"YO32 5PB",
    "wof:placetype":"postalcode"
},
  "geometry": {"coordinates":[-1.030373134618,54.04279747120125],"type":"Point"}
}