{
  "type": "Feature",
  "properties": {
    "date:inception_lower": "1980-01-01",
    "date:inception_upper": "1980-01-01",
    "iso:country": "GB",
    "wof:name": "BS21 6DT",
    "wof:placetype": "postalcode"
  },
  "geometry": {"coordinates":[-2.84301,51.43615],"type":"Point"}
}
