{
  "type": "Feature",
  "properties": {
    "iso:country":"GB",
    "wof:name":"BS21 6DT",
    "wof:placetype":"postalcode"
},
  "geometry": {"coordinates":[-2.8430098747792,51.43615047687081],"type":"Point"}
}