{
  "type": "Feature",
  "properties": {
    "iso:country": "GB",
    "wof:name": "WA10 6RL",
    "wof:placetype": "postalcode"
  },
  "geometry": {"coordinates":[-2.754334,53.458779],"type":"Point"}
}
