{
  "type": "Feature",
  "properties": {
    "iso:country":"GB",
    "wof:name":"NE34 0NX",
    "wof:placetype":"postalcode"
},
  "geometry": {"coordinates":[-1.46193515695858,54.97093080097227],"type":"Point"}
}