{
  "type": "Feature",
  "properties": {
    "iso:country": "GB",
    "wof:name": "NE34 0NX",
    "wof:placetype": "postalcode"
  },
  "geometry": {"coordinates":[-1.46187,54.970965],"type":"Point"}
}
