{
  "type": "Feature",
  "properties": {
    "date:inception_lower": "1993-08-01",
    "date:inception_upper": "1993-08-01",
    "iso:country": "GB",
    "wof:name": "NE34 0NX",
    "wof:placetype": "postalcode"
  },
  "geometry": {"coordinates":[-1.461948,54.970939],"type":"Point"}
}
