{
  "type": "Feature",
  "properties": {
    "iso:country":"GB",
    "wof:name":"CF14 5AL",
    "wof:placetype":"postalcode"
},
  "geometry": {"coordinates":[-3.19192373595265,51.53430738027005],"type":"Point"}
}