{
  "type": "Feature",
  "properties": {
    "date:inception_lower": "1999-06-01",
    "date:inception_upper": "1999-06-01",
    "iso:country": "GB",
    "wof:name": "CF14 5AL",
    "wof:placetype": "postalcode"
  },
  "geometry": {"coordinates":[-3.191924,51.534307],"type":"Point"}
}
