{
  "type": "Feature",
  "properties": {
    "iso:country":"GB",
    "wof:name":"CF14 3HW",
    "wof:placetype":"postalcode"
},
  "geometry": {"coordinates":[-3.20405265527339,51.50439339725049],"type":"Point"}
}