{
  "type": "Feature",
  "properties": {
    "date:inception_lower": "2007-07-01",
    "date:inception_upper": "2007-07-01",
    "iso:country": "GB",
    "wof:name": "WN3 6GH",
    "wof:placetype": "postalcode"
  },
  "geometry": {"coordinates":[-2.654283,53.522322],"type":"Point"}
}
