{
  "type": "Feature",
  "properties": {
    "iso:country":"GB",
    "wof:name":"WN3 6GH",
    "wof:placetype":"postalcode"
},
  "geometry": {"coordinates":[-2.65501720819023,53.52199718247537],"type":"Point"}
}