{
  "type": "Feature",
  "properties": {
    "iso:country": "GB",
    "wof:name": "LL28 5UH",
    "wof:placetype": "postalcode"
  },
  "geometry": {"coordinates":[-3.778988,53.211172],"type":"Point"}
}
