{
  "type": "Feature",
  "properties": {
    "date:inception_lower": "1980-01-01",
    "date:inception_upper": "1980-01-01",
    "iso:country": "GB",
    "wof:name": "LL28 5UH",
    "wof:placetype": "postalcode"
  },
  "geometry": {"coordinates":[-3.778988,53.211172],"type":"Point"}
}
