{
  "type": "Feature",
  "properties": {
    "iso:country":"GB",
    "wof:name":"FK12 5DQ",
    "wof:placetype":"postalcode"
},
  "geometry": {"coordinates":[-3.78680752284264,56.15041850494899],"type":"Point"}
}