{
  "type": "Feature",
  "properties": {
    "iso:country": "GB",
    "wof:name": "FK12 5DQ",
    "wof:placetype": "postalcode"
  },
  "geometry": {"coordinates":[-3.78656,56.150433],"type":"Point"}
}
