{
  "type": "Feature",
  "properties": {
    "iso:country":"GB",
    "wof:name":"W1H 4HQ",
    "wof:placetype":"postalcode"
},
  "geometry": {"coordinates":[-0.16479193505523,51.51983590988994],"type":"Point"}
}