{
  "type": "Feature",
  "properties": {
    "date:inception_lower":"1993-01-01",
    "date:inception_upper":"1993-01-31",
    "iso:country":"GB",
    "wof:name":"BR5 2PX",
    "wof:placetype":"postalcode"
},
  "geometry": {"coordinates":[0.108914,51.395682],"type":"Point"}
}