{
  "type": "Feature",
  "properties": {
    "iso:country":"GB",
    "wof:name":"BR5 2PX",
    "wof:placetype":"postalcode"
},
  "geometry": {"coordinates":[0.10891349163935,51.39568234107792],"type":"Point"}
}