{
  "type": "Feature",
  "properties": {
    "iso:country":"GB",
    "wof:name":"W1B 4ES",
    "wof:placetype":"postalcode"
},
  "geometry": {"coordinates":[-0.13764066425103,51.50982194330128],"type":"Point"}
}