{
  "type": "Feature",
  "properties": {
    "date:inception_lower": "1980-01-01",
    "date:inception_upper": "1980-01-01",
    "iso:country": "GB",
    "wof:name": "G43 1UR",
    "wof:placetype": "postalcode"
  },
  "geometry": {"coordinates":[-4.289684,55.822277],"type":"Point"}
}
