{
  "type": "Feature",
  "properties": {
    "iso:country":"GB",
    "wof:name":"FK6 6AY",
    "wof:placetype":"postalcode"
},
  "geometry": {"coordinates":[-3.90759439957286,56.02158021446414],"type":"Point"}
}