{
  "type": "Feature",
  "properties": {
    "iso:country":"GB",
    "wof:name":"MK45 2BW",
    "wof:placetype":"postalcode"
},
  "geometry": {"coordinates":[-0.47338005984026,52.0322034209026],"type":"Point"}
}