{
  "type": "Feature",
  "properties": {
    "date:inception_lower": "1980-01-01",
    "date:inception_upper": "1980-01-01",
    "iso:country": "GB",
    "wof:name": "SW4 7SA",
    "wof:placetype": "postalcode"
  },
  "geometry": {"coordinates":[-0.122921,51.462961],"type":"Point"}
}
