{
  "type": "Feature",
  "properties": {
    "iso:country":"GB",
    "wof:name":"CM6 2NG",
    "wof:placetype":"postalcode"
},
  "geometry": {"coordinates":[0.33309810677121,51.94572878065053],"type":"Point"}
}