{
  "type": "Feature",
  "properties": {
    "iso:country": "GB",
    "wof:name": "CM6 2NG",
    "wof:placetype": "postalcode"
  },
  "geometry": {"coordinates":[0.333926,51.945721],"type":"Point"}
}
