{
  "type": "Feature",
  "properties": {
    "date:inception_lower":"1980-01-01",
    "date:inception_upper":"1980-01-31",
    "iso:country":"GB",
    "wof:name":"CM6 2NG",
    "wof:placetype":"postalcode"
},
  "geometry": {"coordinates":[0.333926,51.945721],"type":"Point"}
}