{
  "type": "Feature",
  "properties": {
    "iso:country":"GB",
    "wof:name":"SA62 3PL",
    "wof:placetype":"postalcode"
},
  "geometry": {"coordinates":[-4.9977196505007,51.75652958824035],"type":"Point"}
}