{
  "type": "Feature",
  "properties": {
    "date:inception_lower": "1980-01-01",
    "date:inception_upper": "1980-01-01",
    "iso:country": "GB",
    "wof:name": "G51 1PN",
    "wof:placetype": "postalcode"
  },
  "geometry": {"coordinates":[-4.297219,55.850969],"type":"Point"}
}
