{
  "type": "Feature",
  "properties": {
    "iso:country":"GB",
    "wof:name":"KW17 2QZ",
    "wof:placetype":"postalcode"
},
  "geometry": {"coordinates":[-2.91820038093441,58.89634192446501],"type":"Point"}
}