{
  "type": "Feature",
  "properties": {
    "date:inception_lower":"2012-02-01",
    "date:inception_upper":"2012-02-29",
    "iso:country":"GB",
    "wof:name":"KW17 2QZ",
    "wof:placetype":"postalcode"
},
  "geometry": {"coordinates":[-2.9182,58.896342],"type":"Point"}
}