{
  "type": "Feature",
  "properties": {
    "iso:country": "GB",
    "wof:name": "KW17 2QZ",
    "wof:placetype": "postalcode"
  },
  "geometry": {"coordinates":[-2.9182,58.896342],"type":"Point"}
}
