{
  "type": "Feature",
  "properties": {
    "iso:country":"GB",
    "wof:name":"TF2 8BY",
    "wof:placetype":"postalcode"
},
  "geometry": {"coordinates":[-2.43758328421896,52.71360733034474],"type":"Point"}
}