{
  "type": "Feature",
  "properties": {
    "iso:country":"GB",
    "wof:name":"W8 7AP",
    "wof:placetype":"postalcode"
},
  "geometry": {"coordinates":[-0.19805708112009,51.50528931173822],"type":"Point"}
}