{
  "type": "Feature",
  "properties": {
    "iso:country":"GB",
    "wof:name":"KY11 3AS",
    "wof:placetype":"postalcode"
},
  "geometry": {"coordinates":[-3.44933982730765,56.06283463705009],"type":"Point"}
}