{
  "type": "Feature",
  "properties": {
    "date:inception_lower": "1990-02-01",
    "date:inception_upper": "1990-02-01",
    "iso:country": "GB",
    "wof:name": "LE12 9UF",
    "wof:placetype": "postalcode"
  },
  "geometry": {"coordinates":[-1.371329,52.772469],"type":"Point"}
}
