{
  "type": "Feature",
  "properties": {
    "iso:country":"GB",
    "wof:name":"LE12 9UF",
    "wof:placetype":"postalcode"
},
  "geometry": {"coordinates":[-1.37132865526033,52.77246915002267],"type":"Point"}
}