{
  "type": "Feature",
  "properties": {
    "date:inception_lower": "1980-01-01",
    "date:inception_upper": "1980-01-01",
    "iso:country": "GB",
    "wof:name": "L3 8DT",
    "wof:placetype": "postalcode"
  },
  "geometry": {"coordinates":[-2.971519,53.413515],"type":"Point"}
}
