{
  "type": "Feature",
  "properties": {
    "iso:country": "GB",
    "wof:name": "L3 8DT",
    "wof:placetype": "postalcode"
  },
  "geometry": {"coordinates":[-2.971519,53.413515],"type":"Point"}
}
