{
  "type": "Feature",
  "properties": {
    "iso:country":"GB",
    "wof:name":"SL9 7HZ",
    "wof:placetype":"postalcode"
},
  "geometry": {"coordinates":[-0.55936196553875,51.5730028586143],"type":"Point"}
}