{
  "type": "Feature",
  "properties": {
    "iso:country": "GB",
    "wof:name": "SL9 7HZ",
    "wof:placetype": "postalcode"
  },
  "geometry": {"coordinates":[-0.559362,51.573003],"type":"Point"}
}
