{
  "type": "Feature",
  "properties": {
    "iso:country":"GB",
    "wof:name":"CF39 8DF",
    "wof:placetype":"postalcode"
},
  "geometry": {"coordinates":[-3.43545244367428,51.58001970615083],"type":"Point"}
}