{
  "type": "Feature",
  "properties": {
    "iso:country":"GB",
    "wof:name":"GU12 6AH",
    "wof:placetype":"postalcode"
},
  "geometry": {"coordinates":[-0.71322771548536,51.25140771627415],"type":"Point"}
}