{
  "type": "Feature",
  "properties": {
    "iso:country":"GB",
    "wof:name":"DN14 9TL",
    "wof:placetype":"postalcode"
},
  "geometry": {"coordinates":[-1.02284342997275,53.68974103825526],"type":"Point"}
}