{
  "type": "Feature",
  "properties": {
    "date:inception_lower":"1990-07-01",
    "date:inception_upper":"1990-07-31",
    "iso:country":"GB",
    "wof:name":"NR8 6XW",
    "wof:placetype":"postalcode"
},
  "geometry": {"coordinates":[1.209528,52.689132],"type":"Point"}
}