{
  "type": "Feature",
  "properties": {
    "iso:country":"GB",
    "wof:name":"NR8 6XW",
    "wof:placetype":"postalcode"
},
  "geometry": {"coordinates":[1.20952844290229,52.68913246276067],"type":"Point"}
}