{
  "type": "Feature",
  "properties": {
    "iso:country": "GB",
    "wof:name": "BA2 8QP",
    "wof:placetype": "postalcode"
  },
  "geometry": {"coordinates":[-2.362363,51.310401],"type":"Point"}
}
