{
  "type": "Feature",
  "properties": {
    "date:inception_lower":"1993-01-01",
    "date:inception_upper":"1993-01-31",
    "iso:country":"GB",
    "wof:name":"BA2 8QP",
    "wof:placetype":"postalcode"
},
  "geometry": {"coordinates":[-2.362363,51.310401],"type":"Point"}
}