{
  "type": "Feature",
  "properties": {
    "iso:country":"GB",
    "wof:name":"BA2 8QP",
    "wof:placetype":"postalcode"
},
  "geometry": {"coordinates":[-2.36236320066851,51.31040087907231],"type":"Point"}
}