{
  "type": "Feature",
  "properties": {
    "iso:country":"GB",
    "wof:name":"EX3 0PZ",
    "wof:placetype":"postalcode"
},
  "geometry": {"coordinates":[-3.43924233472564,50.67015158311795],"type":"Point"}
}