{
  "type": "Feature",
  "properties": {
    "date:inception_lower":"1980-01-01",
    "date:inception_upper":"1980-01-31",
    "iso:country":"GB",
    "wof:name":"EX3 0PZ",
    "wof:placetype":"postalcode"
},
  "geometry": {"coordinates":[-3.439242,50.670152],"type":"Point"}
}