{
  "type": "Feature",
  "properties": {
    "iso:country": "GB",
    "wof:name": "IV2 4BU",
    "wof:placetype": "postalcode"
  },
  "geometry": {"coordinates":[-4.231671,57.454501],"type":"Point"}
}
