{
  "type": "Feature",
  "properties": {
    "iso:country":"GB",
    "wof:name":"PE23 5AR",
    "wof:placetype":"postalcode"
},
  "geometry": {"coordinates":[0.09971109109474,53.1482215334342],"type":"Point"}
}