{
  "type": "Feature",
  "properties": {
    "date:inception_lower":"1980-01-01",
    "date:inception_upper":"1980-01-31",
    "iso:country":"GB",
    "wof:name":"PE23 5AR",
    "wof:placetype":"postalcode"
},
  "geometry": {"coordinates":[0.099491,53.148252],"type":"Point"}
}