{
  "type": "Feature",
  "properties": {
    "iso:country":"GB",
    "wof:name":"NP12 3XY",
    "wof:placetype":"postalcode"
},
  "geometry": {"coordinates":[-3.22374785815766,51.67032191479998],"type":"Point"}
}