{
  "type": "Feature",
  "properties": {
    "iso:country":"GB",
    "wof:name":"CB2 9LS",
    "wof:placetype":"postalcode"
},
  "geometry": {"coordinates":[0.11225542856809,52.17390105853051],"type":"Point"}
}