{
  "type": "Feature",
  "properties": {
    "date:inception_lower": "2006-09-01",
    "date:inception_upper": "2006-09-01",
    "iso:country": "GB",
    "wof:name": "CB2 9LS",
    "wof:placetype": "postalcode"
  },
  "geometry": {"coordinates":[0.112255,52.173901],"type":"Point"}
}
