{
  "type": "Feature",
  "properties": {
    "date:inception_lower": "1995-01-01",
    "date:inception_upper": "1995-01-01",
    "iso:country": "GB",
    "wof:name": "SL2 5AW",
    "wof:placetype": "postalcode"
  },
  "geometry": {"coordinates":[-0.591868,51.514672],"type":"Point"}
}
