{
  "type": "Feature",
  "properties": {
    "iso:country":"GB",
    "wof:name":"SL2 5AW",
    "wof:placetype":"postalcode"
},
  "geometry": {"coordinates":[-0.59224066381782,51.51436929092183],"type":"Point"}
}