{
  "type": "Feature",
  "properties": {
    "date:inception_lower":"1999-06-01",
    "date:inception_upper":"1999-06-30",
    "iso:country":"GB",
    "wof:name":"NP18 1AX",
    "wof:placetype":"postalcode"
},
  "geometry": {"coordinates":[-2.954668,51.610731],"type":"Point"}
}