{
  "type": "Feature",
  "properties": {
    "iso:country": "GB",
    "wof:name": "NP18 1AX",
    "wof:placetype": "postalcode"
  },
  "geometry": {"coordinates":[-2.954668,51.610731],"type":"Point"}
}
