{
  "type": "Feature",
  "properties": {
    "iso:country": "GB",
    "wof:name": "L3 5LD",
    "wof:placetype": "postalcode"
  },
  "geometry": {"coordinates":[-2.972213,53.408322],"type":"Point"}
}
