{
  "type": "Feature",
  "properties": {
    "iso:country":"GB",
    "wof:name":"SN5 5SF",
    "wof:placetype":"postalcode"
},
  "geometry": {"coordinates":[-1.83815796569296,51.56456588083635],"type":"Point"}
}