{
  "type": "Feature",
  "properties": {
    "date:inception_lower":"2000-06-01",
    "date:inception_upper":"2000-06-30",
    "iso:country":"GB",
    "wof:name":"SN5 5SF",
    "wof:placetype":"postalcode"
},
  "geometry": {"coordinates":[-1.838158,51.564566],"type":"Point"}
}