{
  "type": "Feature",
  "properties": {
    "iso:country":"GB",
    "wof:name":"S21 2DD",
    "wof:placetype":"postalcode"
},
  "geometry": {"coordinates":[-1.30379578564323,53.32900453931112],"type":"Point"}
}