{
  "type": "Feature",
  "properties": {
    "iso:country":"GB",
    "wof:name":"NW6 4LR",
    "wof:placetype":"postalcode"
},
  "geometry": {"coordinates":[-0.1946018353335,51.5412958252488],"type":"Point"}
}