{
  "type": "Feature",
  "properties": {
    "iso:country": "GB",
    "wof:name": "GL5 2LU",
    "wof:placetype": "postalcode"
  },
  "geometry": {"coordinates":[-2.209659,51.734226],"type":"Point"}
}
