{
  "type": "Feature",
  "properties": {
    "date:inception_lower":"1994-12-01",
    "date:inception_upper":"1994-12-31",
    "iso:country":"GB",
    "wof:name":"DH8 8LN",
    "wof:placetype":"postalcode"
},
  "geometry": {"coordinates":[-1.84844,54.86038],"type":"Point"}
}