{
  "type": "Feature",
  "properties": {
    "iso:country": "GB",
    "wof:name": "DH8 8LN",
    "wof:placetype": "postalcode"
  },
  "geometry": {"coordinates":[-1.84844,54.86038],"type":"Point"}
}
