{
  "type": "Feature",
  "properties": {
    "iso:country":"GB",
    "wof:name":"DH8 8LN",
    "wof:placetype":"postalcode"
},
  "geometry": {"coordinates":[-1.84843995756714,54.86038002379047],"type":"Point"}
}