{
  "type": "Feature",
  "properties": {
    "iso:country": "GB",
    "wof:name": "SS0 7ES",
    "wof:placetype": "postalcode"
  },
  "geometry": {"coordinates":[0.693397,51.539509],"type":"Point"}
}
