{
  "type": "Feature",
  "properties": {
    "iso:country":"GB",
    "wof:name":"BS20 6NP",
    "wof:placetype":"postalcode"
},
  "geometry": {"coordinates":[-2.77840859284916,51.48144802799261],"type":"Point"}
}