{
  "type": "Feature",
  "properties": {
    "iso:country": "GB",
    "wof:name": "CA16 6BQ",
    "wof:placetype": "postalcode"
  },
  "geometry": {"coordinates":[-2.559018,54.603821],"type":"Point"}
}
