{
  "type": "Feature",
  "properties": {
    "date:inception_lower": "1991-09-01",
    "date:inception_upper": "1991-09-01",
    "iso:country": "GB",
    "wof:name": "CA16 6BQ",
    "wof:placetype": "postalcode"
  },
  "geometry": {"coordinates":[-2.559018,54.603821],"type":"Point"}
}
