{
  "type": "Feature",
  "properties": {
    "iso:country":"GB",
    "wof:name":"NW9 9AY",
    "wof:placetype":"postalcode"
},
  "geometry": {"coordinates":[-0.27135675579383,51.58978726731954],"type":"Point"}
}