{
  "type": "Feature",
  "properties": {
    "iso:country":"GB",
    "wof:name":"LL49 9NJ",
    "wof:placetype":"postalcode"
},
  "geometry": {"coordinates":[-4.13961529880345,52.93073253288435],"type":"Point"}
}