{
  "type": "Feature",
  "properties": {
    "iso:country": "GB",
    "wof:name": "LL49 9NJ",
    "wof:placetype": "postalcode"
  },
  "geometry": {"coordinates":[-4.139615,52.930733],"type":"Point"}
}
