{
  "type": "Feature",
  "properties": {
    "date:inception_lower":"2000-12-01",
    "date:inception_upper":"2000-12-31",
    "iso:country":"GB",
    "wof:name":"LL49 9NJ",
    "wof:placetype":"postalcode"
},
  "geometry": {"coordinates":[-4.139615,52.930733],"type":"Point"}
}