{
  "type": "Feature",
  "properties": {
    "iso:country": "GB",
    "wof:name": "OL8 1RD",
    "wof:placetype": "postalcode"
  },
  "geometry": {"coordinates":[-2.127505,53.533385],"type":"Point"}
}
