{
  "type": "Feature",
  "properties": {
    "iso:country":"GB",
    "wof:name":"OL8 1RD",
    "wof:placetype":"postalcode"
},
  "geometry": {"coordinates":[-2.12758284938315,53.53354869456606],"type":"Point"}
}