{
  "type": "Feature",
  "properties": {
    "iso:country":"GB",
    "wof:name":"EX5 2LR",
    "wof:placetype":"postalcode"
},
  "geometry": {"coordinates":[-3.38751738075344,50.74446040915851],"type":"Point"}
}