{
  "type": "Feature",
  "properties": {
    "iso:country": "GB",
    "wof:name": "EX5 2LR",
    "wof:placetype": "postalcode"
  },
  "geometry": {"coordinates":[-3.387517,50.74446],"type":"Point"}
}
