{
  "type": "Feature",
  "properties": {
    "iso:country":"GB",
    "wof:name":"RH16 4QL",
    "wof:placetype":"postalcode"
},
  "geometry": {"coordinates":[-0.10139985905246,50.99102419693469],"type":"Point"}
}