{
  "type": "Feature",
  "properties": {
    "date:inception_lower": "1980-01-01",
    "date:inception_upper": "1980-01-01",
    "iso:country": "GB",
    "wof:name": "RH16 4QL",
    "wof:placetype": "postalcode"
  },
  "geometry": {"coordinates":[-0.1014,50.991024],"type":"Point"}
}
