{
  "type": "Feature",
  "properties": {
    "date:inception_lower":"1980-01-01",
    "date:inception_upper":"1980-01-31",
    "iso:country":"GB",
    "wof:name":"BB5 4DE",
    "wof:placetype":"postalcode"
},
  "geometry": {"coordinates":[-2.376575,53.767149],"type":"Point"}
}