{
  "type": "Feature",
  "properties": {
    "iso:country":"GB",
    "wof:name":"BB5 4DE",
    "wof:placetype":"postalcode"
},
  "geometry": {"coordinates":[-2.37657505412615,53.76714885752686],"type":"Point"}
}