{
  "type": "Feature",
  "properties": {
    "iso:country": "GB",
    "wof:name": "BB5 4DE",
    "wof:placetype": "postalcode"
  },
  "geometry": {"coordinates":[-2.376575,53.767149],"type":"Point"}
}
