{
  "type": "Feature",
  "properties": {
    "iso:country":"GB",
    "wof:name":"S43 3QQ",
    "wof:placetype":"postalcode"
},
  "geometry": {"coordinates":[-1.35994927041784,53.26393378218516],"type":"Point"}
}