{
  "type": "Feature",
  "properties": {
    "iso:country": "GB",
    "wof:name": "S43 3QQ",
    "wof:placetype": "postalcode"
  },
  "geometry": {"coordinates":[-1.359949,53.263934],"type":"Point"}
}
