{
  "type": "Feature",
  "properties": {
    "iso:country":"GB",
    "wof:name":"BN16 1HF",
    "wof:placetype":"postalcode"
},
  "geometry": {"coordinates":[-0.47682331444352,50.81243518499595],"type":"Point"}
}