{
  "type": "Feature",
  "properties": {
    "iso:country": "GB",
    "wof:name": "DE23 2QL",
    "wof:placetype": "postalcode"
  },
  "geometry": {"coordinates":[-1.504912,52.887412],"type":"Point"}
}
