{
  "type": "Feature",
  "properties": {
    "iso:country":"GB",
    "wof:name":"HU3 4BQ",
    "wof:placetype":"postalcode"
},
  "geometry": {"coordinates":[-0.36525671402447,53.73478107253497],"type":"Point"}
}