{
  "type": "Feature",
  "properties": {
    "iso:country":"GB",
    "wof:name":"BA2 2DS",
    "wof:placetype":"postalcode"
},
  "geometry": {"coordinates":[-2.36844290239982,51.37082444490782],"type":"Point"}
}