{
  "type": "Feature",
  "properties": {
    "iso:country":"GB",
    "wof:name":"GL5 1QT",
    "wof:placetype":"postalcode"
},
  "geometry": {"coordinates":[-2.21120273622817,51.74845628017022],"type":"Point"}
}