{
  "type": "Feature",
  "properties": {
    "iso:country": "GB",
    "wof:name": "GL5 1QT",
    "wof:placetype": "postalcode"
  },
  "geometry": {"coordinates":[-2.211203,51.748456],"type":"Point"}
}
