{
  "type": "Feature",
  "properties": {
    "iso:country":"GB",
    "wof:name":"B42 1BT",
    "wof:placetype":"postalcode"
},
  "geometry": {"coordinates":[-1.91134852703166,52.53044360807215],"type":"Point"}
}