{
  "type": "Feature",
  "properties": {
    "date:inception_lower": "1980-01-01",
    "date:inception_upper": "1980-01-01",
    "iso:country": "GB",
    "wof:name": "B42 1BT",
    "wof:placetype": "postalcode"
  },
  "geometry": {"coordinates":[-1.910666,52.530117],"type":"Point"}
}
