{
  "type": "Feature",
  "properties": {
    "iso:country":"GB",
    "wof:name":"WD25 9RG",
    "wof:placetype":"postalcode"
},
  "geometry": {"coordinates":[-0.38516832554653,51.68787515618954],"type":"Point"}
}