{
  "type": "Feature",
  "properties": {
    "iso:country":"GB",
    "wof:name":"BS48 4JF",
    "wof:placetype":"postalcode"
},
  "geometry": {"coordinates":[-2.76899308504079,51.4267955815345],"type":"Point"}
}