{
  "type": "Feature",
  "properties": {
    "iso:country": "GB",
    "wof:name": "BS48 4JF",
    "wof:placetype": "postalcode"
  },
  "geometry": {"coordinates":[-2.768993,51.426796],"type":"Point"}
}
