{
  "type": "Feature",
  "properties": {
    "date:inception_lower": "1980-01-01",
    "date:inception_upper": "1980-01-01",
    "iso:country": "GB",
    "wof:name": "WC2H 7JE",
    "wof:placetype": "postalcode"
  },
  "geometry": {"coordinates":[-0.127991,51.511782],"type":"Point"}
}
