{
  "type": "Feature",
  "properties": {
    "iso:country":"GB",
    "wof:name":"WC2H 7JE",
    "wof:placetype":"postalcode"
},
  "geometry": {"coordinates":[-0.12799145234771,51.51178157013466],"type":"Point"}
}