{
  "type": "Feature",
  "properties": {
    "iso:country": "GB",
    "wof:name": "ML11 0GZ",
    "wof:placetype": "postalcode"
  },
  "geometry": {"coordinates":[-3.87893,55.625814],"type":"Point"}
}
