{
  "type": "Feature",
  "properties": {
    "date:inception_lower": "2007-09-01",
    "date:inception_upper": "2007-09-01",
    "iso:country": "GB",
    "wof:name": "ML11 0GZ",
    "wof:placetype": "postalcode"
  },
  "geometry": {"coordinates":[-3.87893,55.625814],"type":"Point"}
}
