{
  "type": "Feature",
  "properties": {
    "iso:country":"GB",
    "wof:name":"GL7 9FW",
    "wof:placetype":"postalcode"
},
  "geometry": {"coordinates":[-1.96007270188509,51.70176911725953],"type":"Point"}
}