{
  "type": "Feature",
  "properties": {
    "date:inception_lower": "2016-09-01",
    "date:inception_upper": "2016-09-01",
    "iso:country": "GB",
    "wof:name": "CV10 0FA",
    "wof:placetype": "postalcode"
  },
  "geometry": {"coordinates":[-1.469796,52.540725],"type":"Point"}
}
