{
  "type": "Feature",
  "properties": {
    "iso:country":"GB",
    "wof:name":"DY14 8DQ",
    "wof:placetype":"postalcode"
},
  "geometry": {"coordinates":[-2.48263857345633,52.37865604019267],"type":"Point"}
}