{
  "type": "Feature",
  "properties": {
    "iso:country":"GB",
    "wof:name":"PO1 5HZ",
    "wof:placetype":"postalcode"
},
  "geometry": {"coordinates":[-1.07230171450185,50.80169249466653],"type":"Point"}
}