{
  "type": "Feature",
  "properties": {
    "date:inception_lower": "1980-01-01",
    "date:inception_upper": "1980-01-01",
    "iso:country": "GB",
    "wof:name": "RH17 5BY",
    "wof:placetype": "postalcode"
  },
  "geometry": {"coordinates":[-0.1426,51.014098],"type":"Point"}
}
