{
  "type": "Feature",
  "properties": {
    "iso:country": "GB",
    "wof:name": "SY5 0YW",
    "wof:placetype": "postalcode"
  },
  "geometry": {"coordinates":[-2.888465,52.645827],"type":"Point"}
}
