{
  "type": "Feature",
  "properties": {
    "iso:country":"GB",
    "wof:name":"SY5 0YW",
    "wof:placetype":"postalcode"
},
  "geometry": {"coordinates":[-2.88846455928149,52.6458271982316],"type":"Point"}
}