{
  "type": "Feature",
  "properties": {
    "iso:country":"GB",
    "wof:name":"BL8 3LB",
    "wof:placetype":"postalcode"
},
  "geometry": {"coordinates":[-2.33980404209517,53.60964228846498],"type":"Point"}
}