{
  "type": "Feature",
  "properties": {
    "iso:country": "GB",
    "wof:name": "KA20 3HW",
    "wof:placetype": "postalcode"
  },
  "geometry": {"coordinates":[-4.752567,55.636961],"type":"Point"}
}
