{
  "type": "Feature",
  "properties": {
    "iso:country":"GB",
    "wof:name":"KA20 3HW",
    "wof:placetype":"postalcode"
},
  "geometry": {"coordinates":[-4.75256683342176,55.63696120571178],"type":"Point"}
}