{
  "type": "Feature",
  "properties": {
    "date:inception_lower":"2007-07-01",
    "date:inception_upper":"2007-07-31",
    "iso:country":"GB",
    "wof:name":"KA20 3HW",
    "wof:placetype":"postalcode"
},
  "geometry": {"coordinates":[-4.752567,55.636961],"type":"Point"}
}