{
  "type": "Feature",
  "properties": {
    "iso:country": "GB",
    "wof:name": "N6 5EU",
    "wof:placetype": "postalcode"
  },
  "geometry": {"coordinates":[-0.143467,51.57421],"type":"Point"}
}
