{
  "type": "Feature",
  "properties": {
    "iso:country":"GB",
    "wof:name":"CV37 9LW",
    "wof:placetype":"postalcode"
},
  "geometry": {"coordinates":[-1.73478539781853,52.20075374878967],"type":"Point"}
}