{
  "type": "Feature",
  "properties": {
    "date:inception_lower": "1980-01-01",
    "date:inception_upper": "1980-01-01",
    "iso:country": "GB",
    "wof:name": "CV37 9LW",
    "wof:placetype": "postalcode"
  },
  "geometry": {"coordinates":[-1.734785,52.200754],"type":"Point"}
}
