{
  "type": "Feature",
  "properties": {
    "iso:country": "GB",
    "wof:name": "TN12 9AP",
    "wof:placetype": "postalcode"
  },
  "geometry": {"coordinates":[0.509721,51.188563],"type":"Point"}
}
