{
  "type": "Feature",
  "properties": {
    "iso:country":"GB",
    "wof:name":"W1J 7BA",
    "wof:placetype":"postalcode"
},
  "geometry": {"coordinates":[-0.14497457336267,51.50630519484366],"type":"Point"}
}