{
  "type": "Feature",
  "properties": {
    "iso:country": "GB",
    "wof:name": "TQ9 6LR",
    "wof:placetype": "postalcode"
  },
  "geometry": {"coordinates":[-3.652607,50.455044],"type":"Point"}
}
