{
  "type": "Feature",
  "properties": {
    "date:inception_lower":"1980-01-01",
    "date:inception_upper":"1980-01-31",
    "iso:country":"GB",
    "wof:name":"TQ9 6LR",
    "wof:placetype":"postalcode"
},
  "geometry": {"coordinates":[-3.652607,50.455044],"type":"Point"}
}