{
  "type": "Feature",
  "properties": {
    "iso:country":"GB",
    "wof:name":"TQ9 6LR",
    "wof:placetype":"postalcode"
},
  "geometry": {"coordinates":[-3.65260686808315,50.45504370908969],"type":"Point"}
}