{
  "type": "Feature",
  "properties": {
    "iso:country":"GB",
    "wof:name":"CA15 6HP",
    "wof:placetype":"postalcode"
},
  "geometry": {"coordinates":[-3.4963761397908,54.71733811629768],"type":"Point"}
}