{
  "type": "Feature",
  "properties": {
    "iso:country":"GB",
    "wof:name":"PA2 7NE",
    "wof:placetype":"postalcode"
},
  "geometry": {"coordinates":[-4.38586107122739,55.83379533645282],"type":"Point"}
}