{
  "type": "Feature",
  "properties": {
    "iso:country":"GB",
    "wof:name":"PL13 2PD",
    "wof:placetype":"postalcode"
},
  "geometry": {"coordinates":[-4.58243687166133,50.37959433528637],"type":"Point"}
}