{
  "type": "Feature",
  "properties": {
    "iso:country": "GB",
    "wof:name": "PL13 2PD",
    "wof:placetype": "postalcode"
  },
  "geometry": {"coordinates":[-4.582437,50.379594],"type":"Point"}
}
