{
  "type": "Feature",
  "properties": {
    "iso:country": "GB",
    "wof:name": "NG34 0NS",
    "wof:placetype": "postalcode"
  },
  "geometry": {"coordinates":[-0.343694,52.893844],"type":"Point"}
}
