{
  "type": "Feature",
  "properties": {
    "iso:country":"GB",
    "wof:name":"PO6 4SG",
    "wof:placetype":"postalcode"
},
  "geometry": {"coordinates":[-1.10296750290963,50.84766028532102],"type":"Point"}
}