{
  "type": "Feature",
  "properties": {
    "date:inception_lower": "1980-01-01",
    "date:inception_upper": "1980-01-01",
    "iso:country": "GB",
    "wof:name": "PO6 4SG",
    "wof:placetype": "postalcode"
  },
  "geometry": {"coordinates":[-1.102967,50.84766],"type":"Point"}
}
