{
  "type": "Feature",
  "properties": {
    "date:inception_lower":"2015-06-01",
    "date:inception_upper":"2015-06-30",
    "iso:country":"GB",
    "wof:name":"LE8 6AA",
    "wof:placetype":"postalcode"
},
  "geometry": {"coordinates":[-1.178326,52.564262],"type":"Point"}
}