{
  "type": "Feature",
  "properties": {
    "iso:country":"GB",
    "wof:name":"LE8 6AA",
    "wof:placetype":"postalcode"
},
  "geometry": {"coordinates":[-1.17873934724261,52.56393140425316],"type":"Point"}
}