{
  "type": "Feature",
  "properties": {
    "iso:country":"GB",
    "wof:name":"YO8 9XF",
    "wof:placetype":"postalcode"
},
  "geometry": {"coordinates":[-1.07555422862821,53.77145048242589],"type":"Point"}
}