{
  "type": "Feature",
  "properties": {
    "date:inception_lower": "1984-10-01",
    "date:inception_upper": "1984-10-01",
    "iso:country": "GB",
    "wof:name": "YO8 9XF",
    "wof:placetype": "postalcode"
  },
  "geometry": {"coordinates":[-1.075554,53.77145],"type":"Point"}
}
