{
  "type": "Feature",
  "properties": {
    "iso:country":"GB",
    "wof:name":"SA62 6EA",
    "wof:placetype":"postalcode"
},
  "geometry": {"coordinates":[-5.00318260268578,51.81455368647213],"type":"Point"}
}