{
  "type": "Feature",
  "properties": {
    "iso:country": "GB",
    "wof:name": "SA62 6EA",
    "wof:placetype": "postalcode"
  },
  "geometry": {"coordinates":[-5.000241,51.815669],"type":"Point"}
}
