{
  "type": "Feature",
  "properties": {
    "iso:country":"GB",
    "wof:name":"HU13 0SE",
    "wof:placetype":"postalcode"
},
  "geometry": {"coordinates":[-0.43946644367495,53.72378798707415],"type":"Point"}
}