{
  "type": "Feature",
  "properties": {
    "date:inception_lower": "2019-04-01",
    "date:inception_upper": "2019-04-01",
    "iso:country": "GB",
    "wof:name": "WA5 3YN",
    "wof:placetype": "postalcode"
  },
  "geometry": {"coordinates":[-2.661415,53.403022],"type":"Point"}
}
