{
  "type": "Feature",
  "properties": {
    "date:inception_lower": "1980-01-01",
    "date:inception_upper": "1980-01-01",
    "iso:country": "GB",
    "wof:name": "OL3 5AT",
    "wof:placetype": "postalcode"
  },
  "geometry": {"coordinates":[-2.013593,53.557067],"type":"Point"}
}
