{
  "type": "Feature",
  "properties": {
    "iso:country": "GB",
    "wof:name": "L17 0BQ",
    "wof:placetype": "postalcode"
  },
  "geometry": {"coordinates":[-2.928361,53.373057],"type":"Point"}
}
