{
  "type": "Feature",
  "properties": {
    "date:inception_lower": "1985-01-01",
    "date:inception_upper": "1985-01-01",
    "iso:country": "GB",
    "wof:name": "DG7 1HL",
    "wof:placetype": "postalcode"
  },
  "geometry": {"coordinates":[-3.925716,54.940887],"type":"Point"}
}
