{
  "type": "Feature",
  "properties": {
    "iso:country": "GB",
    "wof:name": "KA5 5LP",
    "wof:placetype": "postalcode"
  },
  "geometry": {"coordinates":[-4.436628,55.533335],"type":"Point"}
}
