{
  "type": "Feature",
  "properties": {
    "iso:country":"GB",
    "wof:name":"KA5 5LP",
    "wof:placetype":"postalcode"
},
  "geometry": {"coordinates":[-4.43664599384125,55.53333378988546],"type":"Point"}
}