{
  "type": "Feature",
  "properties": {
    "iso:country": "GB",
    "wof:name": "DN12 2DL",
    "wof:placetype": "postalcode"
  },
  "geometry": {"coordinates":[-1.218732,53.481953],"type":"Point"}
}
