{
  "type": "Feature",
  "properties": {
    "iso:country":"GB",
    "wof:name":"DN12 2DL",
    "wof:placetype":"postalcode"
},
  "geometry": {"coordinates":[-1.21873164841803,53.48195266305238],"type":"Point"}
}