{
  "type": "Feature",
  "properties": {
    "date:inception_lower": "1980-01-01",
    "date:inception_upper": "1980-01-01",
    "iso:country": "GB",
    "wof:name": "BB6 7DZ",
    "wof:placetype": "postalcode"
  },
  "geometry": {"coordinates":[-2.409405,53.782752],"type":"Point"}
}
