{
  "type": "Feature",
  "properties": {
    "iso:country":"GB",
    "wof:name":"BB6 7DZ",
    "wof:placetype":"postalcode"
},
  "geometry": {"coordinates":[-2.4094047748315,53.78275230079191],"type":"Point"}
}