{
  "type": "Feature",
  "properties": {
    "iso:country": "GB",
    "wof:name": "BB6 7DZ",
    "wof:placetype": "postalcode"
  },
  "geometry": {"coordinates":[-2.409405,53.782752],"type":"Point"}
}
