{
  "type": "Feature",
  "properties": {
    "date:inception_lower": "2022-08-01",
    "date:inception_upper": "2022-08-01",
    "iso:country": "GB",
    "wof:name": "CW7 3SS",
    "wof:placetype": "postalcode"
  },
  "geometry": {"coordinates":[-2.506047,53.20698],"type":"Point"}
}
