{
  "type": "Feature",
  "properties": {
    "date:inception_lower": "2022-08-01",
    "date:inception_upper": "2022-08-01",
    "iso:country": "GB",
    "wof:name": "TF11 8GX",
    "wof:placetype": "postalcode"
  },
  "geometry": {"coordinates":[-2.368361,52.665942],"type":"Point"}
}
