{
  "type": "Feature",
  "properties": {
    "iso:country":"GB",
    "wof:name":"NP15 2AZ",
    "wof:placetype":"postalcode"
},
  "geometry": {"coordinates":[-2.91086394081681,51.7878148005949],"type":"Point"}
}