{
  "type": "Feature",
  "properties": {
    "iso:country": "GB",
    "wof:name": "TS23 2QJ",
    "wof:placetype": "postalcode"
  },
  "geometry": {"coordinates":[-1.287069,54.603168],"type":"Point"}
}
