{
  "type": "Feature",
  "properties": {
    "iso:country":"GB",
    "wof:name":"IP22 5UN",
    "wof:placetype":"postalcode"
},
  "geometry": {"coordinates":[1.14931548160663,52.42614564032549],"type":"Point"}
}