{
  "type": "Feature",
  "properties": {
    "iso:country": "GB",
    "wof:name": "IP22 5UN",
    "wof:placetype": "postalcode"
  },
  "geometry": {"coordinates":[1.149322,52.425879],"type":"Point"}
}
