{
  "type": "Feature",
  "properties": {
    "iso:country":"GB",
    "wof:name":"DE12 6GA",
    "wof:placetype":"postalcode"
},
  "geometry": {"coordinates":[-1.54316192237582,52.7419619922706],"type":"Point"}
}