{
  "type": "Feature",
  "properties": {
    "iso:country": "GB",
    "wof:name": "DE12 6GA",
    "wof:placetype": "postalcode"
  },
  "geometry": {"coordinates":[-1.543162,52.741962],"type":"Point"}
}
