{
  "type": "Feature",
  "properties": {
    "iso:country":"GB",
    "wof:name":"LE10 3AQ",
    "wof:placetype":"postalcode"
},
  "geometry": {"coordinates":[-1.32321738628421,52.52801293549771],"type":"Point"}
}