{
  "type": "Feature",
  "properties": {
    "date:inception_lower":"1980-01-01",
    "date:inception_upper":"1980-01-31",
    "iso:country":"GB",
    "wof:name":"LE10 3AQ",
    "wof:placetype":"postalcode"
},
  "geometry": {"coordinates":[-1.323217,52.528013],"type":"Point"}
}