{
  "type": "Feature",
  "properties": {
    "iso:country":"GB",
    "wof:name":"G14 0AZ",
    "wof:placetype":"postalcode"
},
  "geometry": {"coordinates":[-4.34675560503912,55.87653833155172],"type":"Point"}
}