{
  "type": "Feature",
  "properties": {
    "date:inception_lower":"1990-07-01",
    "date:inception_upper":"1990-07-31",
    "iso:country":"GB",
    "wof:name":"CW5 5HA",
    "wof:placetype":"postalcode"
},
  "geometry": {"coordinates":[-2.526993,53.067733],"type":"Point"}
}