{
  "type": "Feature",
  "properties": {
    "iso:country":"GB",
    "wof:name":"CA1 3LU",
    "wof:placetype":"postalcode"
},
  "geometry": {"coordinates":[-2.90506590967554,54.88020491206473],"type":"Point"}
}