{
  "type": "Feature",
  "properties": {
    "iso:country":"GB",
    "wof:name":"NG14 7WH",
    "wof:placetype":"postalcode"
},
  "geometry": {"coordinates":[-0.99719401003669,53.00834050213538],"type":"Point"}
}