{
  "type": "Feature",
  "properties": {
    "iso:country":"GB",
    "wof:name":"RG14 6DY",
    "wof:placetype":"postalcode"
},
  "geometry": {"coordinates":[-1.33988467049933,51.39333886015057],"type":"Point"}
}