{
  "type": "Feature",
  "properties": {
    "iso:country":"GB",
    "wof:name":"SE1 1JD",
    "wof:placetype":"postalcode"
},
  "geometry": {"coordinates":[-0.09320457581385,51.50101460367461],"type":"Point"}
}