{
  "type": "Feature",
  "properties": {
    "date:inception_lower": "1994-05-01",
    "date:inception_upper": "1994-05-01",
    "iso:country": "GB",
    "wof:name": "SE1 1JD",
    "wof:placetype": "postalcode"
  },
  "geometry": {"coordinates":[-0.093179,51.501016],"type":"Point"}
}
