{
  "type": "Feature",
  "properties": {
    "iso:country": "GB",
    "wof:name": "SE1 1JD",
    "wof:placetype": "postalcode"
  },
  "geometry": {"coordinates":[-0.093179,51.501016],"type":"Point"}
}
