{
  "type": "Feature",
  "properties": {
    "iso:country": "GB",
    "wof:name": "IV30 6AN",
    "wof:placetype": "postalcode"
  },
  "geometry": {"coordinates":[-3.289137,57.643037],"type":"Point"}
}
