{
  "type": "Feature",
  "properties": {
    "date:inception_lower":"1998-12-01",
    "date:inception_upper":"1998-12-31",
    "iso:country":"GB",
    "wof:name":"IV30 6AN",
    "wof:placetype":"postalcode"
},
  "geometry": {"coordinates":[-3.289137,57.643037],"type":"Point"}
}