{
  "type": "Feature",
  "properties": {
    "iso:country":"GB",
    "wof:name":"LE8 4BG",
    "wof:placetype":"postalcode"
},
  "geometry": {"coordinates":[-1.16349864962471,52.5686524155696],"type":"Point"}
}