{
  "type": "Feature",
  "properties": {
    "date:inception_lower": "1980-01-01",
    "date:inception_upper": "1980-01-01",
    "iso:country": "GB",
    "wof:name": "LL12 8SG",
    "wof:placetype": "postalcode"
  },
  "geometry": {"coordinates":[-2.962293,53.090196],"type":"Point"}
}
