{
  "type": "Feature",
  "properties": {
    "iso:country":"GB",
    "wof:name":"EX22 6TW",
    "wof:placetype":"postalcode"
},
  "geometry": {"coordinates":[-4.48062452527153,50.76771268423388],"type":"Point"}
}