{
  "type": "Feature",
  "properties": {
    "date:inception_lower": "2018-03-01",
    "date:inception_upper": "2018-03-01",
    "iso:country": "GB",
    "wof:name": "TR10 9FJ",
    "wof:placetype": "postalcode"
  },
  "geometry": {"coordinates":[-5.18435,50.162916],"type":"Point"}
}
