{
  "type": "Feature",
  "properties": {
    "iso:country": "GB",
    "wof:name": "TR10 9FJ",
    "wof:placetype": "postalcode"
  },
  "geometry": {"coordinates":[-5.18435,50.162916],"type":"Point"}
}
