{
  "type": "Feature",
  "properties": {
    "iso:country":"GB",
    "wof:name":"WR14 4PP",
    "wof:placetype":"postalcode"
},
  "geometry": {"coordinates":[-2.32711431914633,52.08656145351378],"type":"Point"}
}