{
  "type": "Feature",
  "properties": {
    "iso:country":"GB",
    "wof:name":"S66 3RQ",
    "wof:placetype":"postalcode"
},
  "geometry": {"coordinates":[-1.28027161247622,53.43219115486345],"type":"Point"}
}