{
  "type": "Feature",
  "properties": {
    "iso:country":"GB",
    "wof:name":"NE28 0BD",
    "wof:placetype":"postalcode"
},
  "geometry": {"coordinates":[-1.49415116487045,54.99538590781292],"type":"Point"}
}