{
  "type": "Feature",
  "properties": {
    "iso:country":"GB",
    "wof:name":"BB8 0DR",
    "wof:placetype":"postalcode"
},
  "geometry": {"coordinates":[-2.18064075238082,53.85424842990097],"type":"Point"}
}