{
  "type": "Feature",
  "properties": {
    "date:inception_lower":"1995-01-01",
    "date:inception_upper":"1995-01-31",
    "iso:country":"GB",
    "wof:name":"CO10 9LG",
    "wof:placetype":"postalcode"
},
  "geometry": {"coordinates":[0.715898,52.07271],"type":"Point"}
}