{
  "type": "Feature",
  "properties": {
    "date:inception_lower": "1999-12-01",
    "date:inception_upper": "1999-12-01",
    "iso:country": "GB",
    "wof:name": "LE2 7PT",
    "wof:placetype": "postalcode"
  },
  "geometry": {"coordinates":[-1.142062,52.628301],"type":"Point"}
}
