{
  "type": "Feature",
  "properties": {
    "iso:country":"GB",
    "wof:name":"SG18 0LJ",
    "wof:placetype":"postalcode"
},
  "geometry": {"coordinates":[-0.26148053581928,52.08689443388074],"type":"Point"}
}