{
  "type": "Feature",
  "properties": {
    "date:inception_lower": "1980-01-01",
    "date:inception_upper": "1980-01-01",
    "iso:country": "GB",
    "wof:name": "CM2 0BD",
    "wof:placetype": "postalcode"
  },
  "geometry": {"coordinates":[0.460826,51.72737],"type":"Point"}
}
