{
  "type": "Feature",
  "properties": {
    "iso:country": "GB",
    "wof:name": "CM2 0BD",
    "wof:placetype": "postalcode"
  },
  "geometry": {"coordinates":[0.460826,51.72737],"type":"Point"}
}
