{
  "type": "Feature",
  "properties": {
    "iso:country":"GB",
    "wof:name":"CH3 9BN",
    "wof:placetype":"postalcode"
},
  "geometry": {"coordinates":[-2.73247118060258,53.16199337963426],"type":"Point"}
}