{
  "type": "Feature",
  "properties": {
    "iso:country": "GB",
    "wof:name": "CH3 9BN",
    "wof:placetype": "postalcode"
  },
  "geometry": {"coordinates":[-2.732471,53.161993],"type":"Point"}
}
