{
  "type": "Feature",
  "properties": {
    "date:inception_lower":"1980-01-01",
    "date:inception_upper":"1980-01-31",
    "iso:country":"GB",
    "wof:name":"CH3 9BN",
    "wof:placetype":"postalcode"
},
  "geometry": {"coordinates":[-2.732471,53.161993],"type":"Point"}
}