{
  "type": "Feature",
  "properties": {
    "iso:country":"GB",
    "wof:name":"SK7 2EY",
    "wof:placetype":"postalcode"
},
  "geometry": {"coordinates":[-2.15766824654512,53.35948646919192],"type":"Point"}
}