{
  "type": "Feature",
  "properties": {
    "date:inception_lower":"1980-01-01",
    "date:inception_upper":"1980-01-31",
    "iso:country":"GB",
    "wof:name":"SK7 2EY",
    "wof:placetype":"postalcode"
},
  "geometry": {"coordinates":[-2.157668,53.359486],"type":"Point"}
}