{
  "type": "Feature",
  "properties": {
    "iso:country":"GB",
    "wof:name":"DN4 0BB",
    "wof:placetype":"postalcode"
},
  "geometry": {"coordinates":[-1.14481349819199,53.51736558563473],"type":"Point"}
}