{
  "type": "Feature",
  "properties": {
    "iso:country":"GB",
    "wof:name":"OX28 6JA",
    "wof:placetype":"postalcode"
},
  "geometry": {"coordinates":[-1.4841417111662,51.78758917497468],"type":"Point"}
}