{
  "type": "Feature",
  "properties": {
    "iso:country":"GB",
    "wof:name":"B29 6JL",
    "wof:placetype":"postalcode"
},
  "geometry": {"coordinates":[-1.9382913840474,52.43792707612831],"type":"Point"}
}