{
  "type": "Feature",
  "properties": {
    "iso:country":"GB",
    "wof:name":"BS23 1UW",
    "wof:placetype":"postalcode"
},
  "geometry": {"coordinates":[-2.97593850011488,51.34622478102895],"type":"Point"}
}