{
  "type": "Feature",
  "properties": {
    "iso:country": "GB",
    "wof:name": "CA8 2DN",
    "wof:placetype": "postalcode"
  },
  "geometry": {"coordinates":[-2.750513,54.974715],"type":"Point"}
}
