{
  "type": "Feature",
  "properties": {
    "iso:country":"GB",
    "wof:name":"CA8 2DN",
    "wof:placetype":"postalcode"
},
  "geometry": {"coordinates":[-2.74822907337298,54.97313269926489],"type":"Point"}
}