{
  "type": "Feature",
  "properties": {
    "date:inception_lower": "2016-03-01",
    "date:inception_upper": "2016-03-01",
    "iso:country": "GB",
    "wof:name": "CA8 2DN",
    "wof:placetype": "postalcode"
  },
  "geometry": {"coordinates":[-2.749903,54.974674],"type":"Point"}
}
