{
  "type": "Feature",
  "properties": {
    "iso:country": "GB",
    "wof:name": "HD5 0JH",
    "wof:placetype": "postalcode"
  },
  "geometry": {"coordinates":[-1.730674,53.657065],"type":"Point"}
}
