{
  "type": "Feature",
  "properties": {
    "iso:country":"GB",
    "wof:name":"HD5 0JH",
    "wof:placetype":"postalcode"
},
  "geometry": {"coordinates":[-1.73067386091005,53.65706512605671],"type":"Point"}
}