{
  "type": "Feature",
  "properties": {
    "date:inception_lower": "1987-10-01",
    "date:inception_upper": "1987-10-01",
    "iso:country": "GB",
    "wof:name": "TF3 5DQ",
    "wof:placetype": "postalcode"
  },
  "geometry": {"coordinates":[-2.467784,52.680724],"type":"Point"}
}
