{
  "type": "Feature",
  "properties": {
    "iso:country":"GB",
    "wof:name":"OX4 7WD",
    "wof:placetype":"postalcode"
},
  "geometry": {"coordinates":[-1.20166116972917,51.71309181866528],"type":"Point"}
}