{
  "type": "Feature",
  "properties": {
    "date:inception_lower": "1980-01-01",
    "date:inception_upper": "1980-01-01",
    "iso:country": "GB",
    "wof:name": "CT18 8JZ",
    "wof:placetype": "postalcode"
  },
  "geometry": {"coordinates":[1.133752,51.137329],"type":"Point"}
}
