{
  "type": "Feature",
  "properties": {
    "iso:country":"GB",
    "wof:name":"CT18 8JZ",
    "wof:placetype":"postalcode"
},
  "geometry": {"coordinates":[1.13356801458791,51.13716764449598],"type":"Point"}
}