{
  "type": "Feature",
  "properties": {
    "iso:country": "GB",
    "wof:name": "CT18 8JZ",
    "wof:placetype": "postalcode"
  },
  "geometry": {"coordinates":[1.133752,51.137329],"type":"Point"}
}
