{
  "type": "Feature",
  "properties": {
    "iso:country": "GB",
    "wof:name": "KY7 6JH",
    "wof:placetype": "postalcode"
  },
  "geometry": {"coordinates":[-3.15157,56.203931],"type":"Point"}
}
