{
  "type": "Feature",
  "properties": {
    "date:inception_lower":"1992-10-01",
    "date:inception_upper":"1992-10-31",
    "iso:country":"GB",
    "wof:name":"KY7 6JH",
    "wof:placetype":"postalcode"
},
  "geometry": {"coordinates":[-3.15157,56.203931],"type":"Point"}
}