{
  "type": "Feature",
  "properties": {
    "date:inception_lower": "1990-02-01",
    "date:inception_upper": "1990-02-01",
    "iso:country": "GB",
    "wof:name": "E2 8RS",
    "wof:placetype": "postalcode"
  },
  "geometry": {"coordinates":[-0.068805,51.535587],"type":"Point"}
}
