{
  "type": "Feature",
  "properties": {
    "iso:country":"GB",
    "wof:name":"E2 8RS",
    "wof:placetype":"postalcode"
},
  "geometry": {"coordinates":[-0.06880466483374,51.53558749496472],"type":"Point"}
}