{
  "type": "Feature",
  "properties": {
    "iso:country": "GB",
    "wof:name": "TN16 3EP",
    "wof:placetype": "postalcode"
  },
  "geometry": {"coordinates":[0.032205,51.30933],"type":"Point"}
}
