{
  "type": "Feature",
  "properties": {
    "iso:country":"GB",
    "wof:name":"TN16 3EP",
    "wof:placetype":"postalcode"
},
  "geometry": {"coordinates":[0.03220518109418,51.30932988955163],"type":"Point"}
}