{
  "type": "Feature",
  "properties": {
    "iso:country":"GB",
    "wof:name":"IG8 0BD",
    "wof:placetype":"postalcode"
},
  "geometry": {"coordinates":[0.02959023710141,51.60518395030078],"type":"Point"}
}