{
  "type": "Feature",
  "properties": {
    "iso:country": "GB",
    "wof:name": "IG8 0BD",
    "wof:placetype": "postalcode"
  },
  "geometry": {"coordinates":[0.02959,51.605184],"type":"Point"}
}
