{
  "type": "Feature",
  "properties": {
    "iso:country": "GB",
    "wof:name": "ME19 6LG",
    "wof:placetype": "postalcode"
  },
  "geometry": {"coordinates":[0.41118,51.296121],"type":"Point"}
}
