{
  "type": "Feature",
  "properties": {
    "iso:country":"GB",
    "wof:name":"ME19 6LG",
    "wof:placetype":"postalcode"
},
  "geometry": {"coordinates":[0.41117998079584,51.29612136128391],"type":"Point"}
}