{
  "type": "Feature",
  "properties": {
    "date:inception_lower":"2005-01-01",
    "date:inception_upper":"2005-01-31",
    "iso:country":"GB",
    "wof:name":"ME19 6LG",
    "wof:placetype":"postalcode"
},
  "geometry": {"coordinates":[0.41118,51.296121],"type":"Point"}
}