{
  "type": "Feature",
  "properties": {
    "date:inception_lower": "2006-10-01",
    "date:inception_upper": "2006-10-01",
    "iso:country": "GB",
    "wof:name": "NG22 9GS",
    "wof:placetype": "postalcode"
  },
  "geometry": {"coordinates":[-1.010394,53.20114],"type":"Point"}
}
