{
  "type": "Feature",
  "properties": {
    "iso:country":"GB",
    "wof:name":"WR4 9RA",
    "wof:placetype":"postalcode"
},
  "geometry": {"coordinates":[-2.2061861872883,52.20038510731387],"type":"Point"}
}