{
  "type": "Feature",
  "properties": {
    "date:inception_lower": "1980-01-01",
    "date:inception_upper": "1980-01-01",
    "iso:country": "GB",
    "wof:name": "SS1 2LS",
    "wof:placetype": "postalcode"
  },
  "geometry": {"coordinates":[0.720692,51.539877],"type":"Point"}
}
