{
  "type": "Feature",
  "properties": {
    "iso:country":"GB",
    "wof:name":"NG5 1JE",
    "wof:placetype":"postalcode"
},
  "geometry": {"coordinates":[-1.17338185220231,52.98048865929361],"type":"Point"}
}