{
  "type": "Feature",
  "properties": {
    "date:inception_lower": "1993-08-01",
    "date:inception_upper": "1993-08-01",
    "iso:country": "GB",
    "wof:name": "N9 0BD",
    "wof:placetype": "postalcode"
  },
  "geometry": {"coordinates":[-0.039965,51.621233],"type":"Point"}
}
