{
  "type": "Feature",
  "properties": {
    "date:inception_lower":"1997-06-01",
    "date:inception_upper":"1997-06-30",
    "iso:country":"GB",
    "wof:name":"CW9 8GF",
    "wof:placetype":"postalcode"
},
  "geometry": {"coordinates":[-2.518229,53.23868],"type":"Point"}
}