{
  "type": "Feature",
  "properties": {
    "iso:country":"GB",
    "wof:name":"B90 4JA",
    "wof:placetype":"postalcode"
},
  "geometry": {"coordinates":[-1.81535805030261,52.3782759998573],"type":"Point"}
}