{
  "type": "Feature",
  "properties": {
    "date:inception_lower": "1980-01-01",
    "date:inception_upper": "1980-01-01",
    "iso:country": "GB",
    "wof:name": "RG25 2JF",
    "wof:placetype": "postalcode"
  },
  "geometry": {"coordinates":[-1.09968,51.238696],"type":"Point"}
}
