{
  "type": "Feature",
  "properties": {
    "iso:country":"GB",
    "wof:name":"RG25 2JF",
    "wof:placetype":"postalcode"
},
  "geometry": {"coordinates":[-1.09955980956472,51.2383988577721],"type":"Point"}
}