{
  "type": "Feature",
  "properties": {
    "iso:country":"GB",
    "wof:name":"WA10 6RH",
    "wof:placetype":"postalcode"
},
  "geometry": {"coordinates":[-2.75404597841475,53.45954458581169],"type":"Point"}
}