{
  "type": "Feature",
  "properties": {
    "iso:country": "GB",
    "wof:name": "WA10 6RH",
    "wof:placetype": "postalcode"
  },
  "geometry": {"coordinates":[-2.754046,53.459545],"type":"Point"}
}
