{
  "type": "Feature",
  "properties": {
    "iso:country":"GB",
    "wof:name":"ME3 8SE",
    "wof:placetype":"postalcode"
},
  "geometry": {"coordinates":[0.55349148401158,51.45321668295699],"type":"Point"}
}