{
  "type": "Feature",
  "properties": {
    "iso:country": "GB",
    "wof:name": "ME3 8SE",
    "wof:placetype": "postalcode"
  },
  "geometry": {"coordinates":[0.553438,51.454838],"type":"Point"}
}
