{
  "type": "Feature",
  "properties": {
    "iso:country":"GB",
    "wof:name":"WF7 7QQ",
    "wof:placetype":"postalcode"
},
  "geometry": {"coordinates":[-1.33838837213243,53.64112375998359],"type":"Point"}
}