{
  "type": "Feature",
  "properties": {
    "iso:country": "GB",
    "wof:name": "WF7 7QQ",
    "wof:placetype": "postalcode"
  },
  "geometry": {"coordinates":[-1.338388,53.641124],"type":"Point"}
}
