{
  "type": "Feature",
  "properties": {
    "date:inception_lower": "2018-11-01",
    "date:inception_upper": "2018-11-01",
    "iso:country": "GB",
    "wof:name": "PE7 8QQ",
    "wof:placetype": "postalcode"
  },
  "geometry": {"coordinates":[-0.258982,52.529597],"type":"Point"}
}
