{
  "type": "Feature",
  "properties": {
    "iso:country": "GB",
    "wof:name": "PE7 8QQ",
    "wof:placetype": "postalcode"
  },
  "geometry": {"coordinates":[-0.258989,52.529426],"type":"Point"}
}
