{
  "type": "Feature",
  "properties": {
    "iso:country": "GB",
    "wof:name": "G45 9PZ",
    "wof:placetype": "postalcode"
  },
  "geometry": {"coordinates":[-4.248595,55.79939],"type":"Point"}
}
