{
  "type": "Feature",
  "properties": {
    "iso:country": "GB",
    "wof:name": "WA8 7PR",
    "wof:placetype": "postalcode"
  },
  "geometry": {"coordinates":[-2.756375,53.371934],"type":"Point"}
}
