{
  "type": "Feature",
  "properties": {
    "iso:country":"GB",
    "wof:name":"LS28 5LA",
    "wof:placetype":"postalcode"
},
  "geometry": {"coordinates":[-1.67111577850066,53.81667083199001],"type":"Point"}
}