{
  "type": "Feature",
  "properties": {
    "iso:country":"GB",
    "wof:name":"HU12 8FE",
    "wof:placetype":"postalcode"
},
  "geometry": {"coordinates":[-0.20658570161834,53.73681733366942],"type":"Point"}
}