{
  "type": "Feature",
  "properties": {
    "iso:country": "GB",
    "wof:name": "HU12 8FE",
    "wof:placetype": "postalcode"
  },
  "geometry": {"coordinates":[-0.206586,53.736817],"type":"Point"}
}
