{
  "type": "Feature",
  "properties": {
    "date:inception_lower": "2023-03-01",
    "date:inception_upper": "2023-03-01",
    "iso:country": "GB",
    "wof:name": "ME13 7GX",
    "wof:placetype": "postalcode"
  },
  "geometry": {"coordinates":[0.866125,51.315495],"type":"Point"}
}
