{
  "type": "Feature",
  "properties": {
    "iso:country":"GB",
    "wof:name":"HA3 8DW",
    "wof:placetype":"postalcode"
},
  "geometry": {"coordinates":[-0.30320082770038,51.58750932268794],"type":"Point"}
}