{
  "type": "Feature",
  "properties": {
    "iso:country":"GB",
    "wof:name":"LE4 5PN",
    "wof:placetype":"postalcode"
},
  "geometry": {"coordinates":[-1.1244578988218,52.66128218008121],"type":"Point"}
}