{
  "type": "Feature",
  "properties": {
    "iso:country": "GB",
    "wof:name": "G3 7EG",
    "wof:placetype": "postalcode"
  },
  "geometry": {"coordinates":[-4.275051,55.864224],"type":"Point"}
}
