{
  "type": "Feature",
  "properties": {
    "iso:country":"GB",
    "wof:name":"G3 7EG",
    "wof:placetype":"postalcode"
},
  "geometry": {"coordinates":[-4.27505137862349,55.86422411376026],"type":"Point"}
}