{
  "type": "Feature",
  "properties": {
    "iso:country":"GB",
    "wof:name":"WD3 3SR",
    "wof:placetype":"postalcode"
},
  "geometry": {"coordinates":[-0.44152075462479,51.65743417630618],"type":"Point"}
}