{
  "type": "Feature",
  "properties": {
    "date:inception_lower": "1980-01-01",
    "date:inception_upper": "1980-01-01",
    "iso:country": "GB",
    "wof:name": "WD3 3SR",
    "wof:placetype": "postalcode"
  },
  "geometry": {"coordinates":[-0.441521,51.657434],"type":"Point"}
}
