{
  "type": "Feature",
  "properties": {
    "iso:country":"GB",
    "wof:name":"SL6 6EJ",
    "wof:placetype":"postalcode"
},
  "geometry": {"coordinates":[-0.74034068156905,51.52196064834639],"type":"Point"}
}