{
  "type": "Feature",
  "properties": {
    "iso:country":"GB",
    "wof:name":"HA1 2LF",
    "wof:placetype":"postalcode"
},
  "geometry": {"coordinates":[-0.32637391645565,51.58267152956479],"type":"Point"}
}