{
  "type": "Feature",
  "properties": {
    "date:inception_lower": "2002-06-01",
    "date:inception_upper": "2002-06-01",
    "iso:country": "GB",
    "wof:name": "B96 6TN",
    "wof:placetype": "postalcode"
  },
  "geometry": {"coordinates":[-2.023465,52.236404],"type":"Point"}
}
