{
  "type": "Feature",
  "properties": {
    "iso:country":"GB",
    "wof:name":"B96 6TN",
    "wof:placetype":"postalcode"
},
  "geometry": {"coordinates":[-2.02325263402817,52.2364888214254],"type":"Point"}
}