{
  "type": "Feature",
  "properties": {
    "iso:country":"GB",
    "wof:name":"OX10 8AB",
    "wof:placetype":"postalcode"
},
  "geometry": {"coordinates":[-1.13387969515503,51.60609912975364],"type":"Point"}
}