{
  "type": "Feature",
  "properties": {
    "iso:country": "GB",
    "wof:name": "TS14 8BL",
    "wof:placetype": "postalcode"
  },
  "geometry": {"coordinates":[-1.074744,54.527205],"type":"Point"}
}
