{
  "type": "Feature",
  "properties": {
    "iso:country":"GB",
    "wof:name":"TS14 8BL",
    "wof:placetype":"postalcode"
},
  "geometry": {"coordinates":[-1.07460468026342,54.52720871752953],"type":"Point"}
}