{
  "type": "Feature",
  "properties": {
    "date:inception_lower": "1980-01-01",
    "date:inception_upper": "1980-01-01",
    "iso:country": "GB",
    "wof:name": "TS14 8BL",
    "wof:placetype": "postalcode"
  },
  "geometry": {"coordinates":[-1.07462,54.527222],"type":"Point"}
}
