{
  "type": "Feature",
  "properties": {
    "iso:country":"GB",
    "wof:name":"WA3 3JD",
    "wof:placetype":"postalcode"
},
  "geometry": {"coordinates":[-2.59086548904066,53.46867888856698],"type":"Point"}
}