{
  "type": "Feature",
  "properties": {
    "date:inception_lower": "1998-12-01",
    "date:inception_upper": "1998-12-01",
    "iso:country": "GB",
    "wof:name": "WA3 3JD",
    "wof:placetype": "postalcode"
  },
  "geometry": {"coordinates":[-2.591061,53.469835],"type":"Point"}
}
