{
  "type": "Feature",
  "properties": {
    "iso:country": "GB",
    "wof:name": "WA3 3JD",
    "wof:placetype": "postalcode"
  },
  "geometry": {"coordinates":[-2.590865,53.468695],"type":"Point"}
}
