{
  "type": "Feature",
  "properties": {
    "iso:country": "GB",
    "wof:name": "OL2 8HG",
    "wof:placetype": "postalcode"
  },
  "geometry": {"coordinates":[-2.085121,53.582384],"type":"Point"}
}
