{
  "type": "Feature",
  "properties": {
    "iso:country":"GB",
    "wof:name":"OL2 8HG",
    "wof:placetype":"postalcode"
},
  "geometry": {"coordinates":[-2.08512047518388,53.58233021375932],"type":"Point"}
}