{
  "type": "Feature",
  "properties": {
    "iso:country": "GB",
    "wof:name": "PH2 0ND",
    "wof:placetype": "postalcode"
  },
  "geometry": {"coordinates":[-3.458235,56.386287],"type":"Point"}
}
