{
  "type": "Feature",
  "properties": {
    "iso:country":"GB",
    "wof:name":"PH2 0ND",
    "wof:placetype":"postalcode"
},
  "geometry": {"coordinates":[-3.45823529788144,56.38628721834449],"type":"Point"}
}