{
  "type": "Feature",
  "properties": {
    "date:inception_lower": "1980-01-01",
    "date:inception_upper": "1980-01-01",
    "iso:country": "GB",
    "wof:name": "BH14 8SH",
    "wof:placetype": "postalcode"
  },
  "geometry": {"coordinates":[-1.948467,50.722015],"type":"Point"}
}
