{
  "type": "Feature",
  "properties": {
    "iso:country":"GB",
    "wof:name":"BH14 8SH",
    "wof:placetype":"postalcode"
},
  "geometry": {"coordinates":[-1.9484675380306,50.72201508746953],"type":"Point"}
}