{
  "type": "Feature",
  "properties": {
    "date:inception_lower": "2023-12-01",
    "date:inception_upper": "2023-12-01",
    "iso:country": "GB",
    "wof:name": "SO30 2HQ",
    "wof:placetype": "postalcode"
  },
  "geometry": {"coordinates":[-1.247267,50.90188],"type":"Point"}
}
