{
  "type": "Feature",
  "properties": {
    "iso:country":"GB",
    "wof:name":"OL2 5PS",
    "wof:placetype":"postalcode"
},
  "geometry": {"coordinates":[-2.12087978483494,53.56371154568839],"type":"Point"}
}