{
  "type": "Feature",
  "properties": {
    "date:inception_lower": "2004-03-01",
    "date:inception_upper": "2004-03-01",
    "iso:country": "GB",
    "wof:name": "EX13 5GH",
    "wof:placetype": "postalcode"
  },
  "geometry": {"coordinates":[-2.996859,50.782305],"type":"Point"}
}
