{
  "type": "Feature",
  "properties": {
    "iso:country":"GB",
    "wof:name":"EX13 5GH",
    "wof:placetype":"postalcode"
},
  "geometry": {"coordinates":[-2.99685875859875,50.78230461709541],"type":"Point"}
}