{
  "type": "Feature",
  "properties": {
    "iso:country": "GB",
    "wof:name": "GU15 2RG",
    "wof:placetype": "postalcode"
  },
  "geometry": {"coordinates":[-0.754598,51.321302],"type":"Point"}
}
