{
  "type": "Feature",
  "properties": {
    "iso:country":"GB",
    "wof:name":"GU15 2RG",
    "wof:placetype":"postalcode"
},
  "geometry": {"coordinates":[-0.75459836989989,51.32130229492665],"type":"Point"}
}