{
  "type": "Feature",
  "properties": {
    "date:inception_lower": "1980-01-01",
    "date:inception_upper": "1980-01-01",
    "iso:country": "GB",
    "wof:name": "SA10 9AA",
    "wof:placetype": "postalcode"
  },
  "geometry": {"coordinates":[-3.711665,51.765677],"type":"Point"}
}
