{
  "type": "Feature",
  "properties": {
    "iso:country":"GB",
    "wof:name":"SA10 9AA",
    "wof:placetype":"postalcode"
},
  "geometry": {"coordinates":[-3.71165160755198,51.76567151428844],"type":"Point"}
}