{
  "type": "Feature",
  "properties": {
    "iso:country":"GB",
    "wof:name":"TR20 9HE",
    "wof:placetype":"postalcode"
},
  "geometry": {"coordinates":[-5.4301958532245,50.12621150157923],"type":"Point"}
}