{
  "type": "Feature",
  "properties": {
    "date:inception_lower": "1980-01-01",
    "date:inception_upper": "1980-01-01",
    "iso:country": "GB",
    "wof:name": "PR3 5HB",
    "wof:placetype": "postalcode"
  },
  "geometry": {"coordinates":[-2.732441,53.822173],"type":"Point"}
}
