{
  "type": "Feature",
  "properties": {
    "iso:country":"GB",
    "wof:name":"BA1 7RY",
    "wof:placetype":"postalcode"
},
  "geometry": {"coordinates":[-2.30518109412872,51.39739698121231],"type":"Point"}
}