{
  "type": "Feature",
  "properties": {
    "iso:country":"GB",
    "wof:name":"PE19 8NJ",
    "wof:placetype":"postalcode"
},
  "geometry": {"coordinates":[-0.2975495626826,52.21672676091655],"type":"Point"}
}