{
  "type": "Feature",
  "properties": {
    "date:inception_lower":"1980-01-01",
    "date:inception_upper":"1980-01-31",
    "iso:country":"GB",
    "wof:name":"YO14 9LT",
    "wof:placetype":"postalcode"
},
  "geometry": {"coordinates":[-0.29305,54.212515],"type":"Point"}
}