{
  "type": "Feature",
  "properties": {
    "iso:country":"GB",
    "wof:name":"LE7 7AR",
    "wof:placetype":"postalcode"
},
  "geometry": {"coordinates":[-1.18609968856652,52.66756484753948],"type":"Point"}
}