{
  "type": "Feature",
  "properties": {
    "iso:country":"GB",
    "wof:name":"BB3 0PF",
    "wof:placetype":"postalcode"
},
  "geometry": {"coordinates":[-2.48556995469681,53.71131787057438],"type":"Point"}
}