{
  "type": "Feature",
  "properties": {
    "date:inception_lower": "1997-06-01",
    "date:inception_upper": "1997-06-01",
    "iso:country": "GB",
    "wof:name": "OX2 7LT",
    "wof:placetype": "postalcode"
  },
  "geometry": {"coordinates":[-1.263948,51.78319],"type":"Point"}
}
