{
  "type": "Feature",
  "properties": {
    "iso:country":"GB",
    "wof:name":"OX2 7LT",
    "wof:placetype":"postalcode"
},
  "geometry": {"coordinates":[-1.26394842470448,51.78318957012115],"type":"Point"}
}