{
  "type": "Feature",
  "properties": {
    "iso:country":"GB",
    "wof:name":"AL6 9SP",
    "wof:placetype":"postalcode"
},
  "geometry": {"coordinates":[-0.20043778817831,51.84600485236212],"type":"Point"}
}