{
  "type": "Feature",
  "properties": {
    "date:inception_lower": "1980-01-01",
    "date:inception_upper": "1980-01-01",
    "iso:country": "GB",
    "wof:name": "AL6 9SP",
    "wof:placetype": "postalcode"
  },
  "geometry": {"coordinates":[-0.200373,51.84557],"type":"Point"}
}
