{
  "type": "Feature",
  "properties": {
    "date:inception_lower":"1980-01-01",
    "date:inception_upper":"1980-01-31",
    "iso:country":"GB",
    "wof:name":"GU32 3HZ",
    "wof:placetype":"postalcode"
},
  "geometry": {"coordinates":[-0.934534,51.00751],"type":"Point"}
}