{
  "type": "Feature",
  "properties": {
    "iso:country":"GB",
    "wof:name":"GU32 3HZ",
    "wof:placetype":"postalcode"
},
  "geometry": {"coordinates":[-0.93453371046049,51.00750989423057],"type":"Point"}
}