{
  "type": "Feature",
  "properties": {
    "date:inception_lower":"1980-01-01",
    "date:inception_upper":"1980-01-31",
    "iso:country":"GB",
    "wof:name":"GU34 5HZ",
    "wof:placetype":"postalcode"
},
  "geometry": {"coordinates":[-1.058384,51.107355],"type":"Point"}
}