{
  "type": "Feature",
  "properties": {
    "iso:country": "GB",
    "wof:name": "GU34 5HZ",
    "wof:placetype": "postalcode"
  },
  "geometry": {"coordinates":[-1.058384,51.107355],"type":"Point"}
}
