{
  "type": "Feature",
  "properties": {
    "iso:country":"GB",
    "wof:name":"DY11 7FE",
    "wof:placetype":"postalcode"
},
  "geometry": {"coordinates":[-2.27345193856446,52.36051814549312],"type":"Point"}
}