{
  "type": "Feature",
  "properties": {
    "date:inception_lower": "2015-07-01",
    "date:inception_upper": "2015-07-01",
    "iso:country": "GB",
    "wof:name": "DY11 7FE",
    "wof:placetype": "postalcode"
  },
  "geometry": {"coordinates":[-2.273388,52.360361],"type":"Point"}
}
