{
  "type": "Feature",
  "properties": {
    "iso:country":"GB",
    "wof:name":"WF8 3BH",
    "wof:placetype":"postalcode"
},
  "geometry": {"coordinates":[-1.26818998264943,53.67607569510632],"type":"Point"}
}