{
  "type": "Feature",
  "properties": {
    "date:inception_lower": "1997-12-01",
    "date:inception_upper": "1997-12-01",
    "iso:country": "GB",
    "wof:name": "M15 6AX",
    "wof:placetype": "postalcode"
  },
  "geometry": {"coordinates":[-2.24255,53.465697],"type":"Point"}
}
