{
  "type": "Feature",
  "properties": {
    "iso:country":"GB",
    "wof:name":"M15 6AX",
    "wof:placetype":"postalcode"
},
  "geometry": {"coordinates":[-2.24255048274509,53.46569663496577],"type":"Point"}
}