{
  "type": "Feature",
  "properties": {
    "iso:country": "GB",
    "wof:name": "LU2 0GE",
    "wof:placetype": "postalcode"
  },
  "geometry": {"coordinates":[-0.407788,51.886256],"type":"Point"}
}
