{
  "type": "Feature",
  "properties": {
    "date:inception_lower": "2019-06-01",
    "date:inception_upper": "2019-06-01",
    "iso:country": "GB",
    "wof:name": "LU2 0GE",
    "wof:placetype": "postalcode"
  },
  "geometry": {"coordinates":[-0.397306,51.8758],"type":"Point"}
}
