{
  "type": "Feature",
  "properties": {
    "date:inception_lower": "2023-12-01",
    "date:inception_upper": "2023-12-01",
    "iso:country": "GB",
    "wof:name": "EX1 4AW",
    "wof:placetype": "postalcode"
  },
  "geometry": {"coordinates":[-3.44703,50.734688],"type":"Point"}
}
