{
  "type": "Feature",
  "properties": {
    "iso:country":"GB",
    "wof:name":"CR0 1AA",
    "wof:placetype":"postalcode"
},
  "geometry": {"coordinates":[-0.10061645968976,51.36767479637797],"type":"Point"}
}