{
  "type": "Feature",
  "properties": {
    "iso:country": "GB",
    "wof:name": "SP11 0HL",
    "wof:placetype": "postalcode"
  },
  "geometry": {"coordinates":[-1.512544,51.25541],"type":"Point"}
}
