{
  "type": "Feature",
  "properties": {
    "iso:country":"GB",
    "wof:name":"SP11 0HL",
    "wof:placetype":"postalcode"
},
  "geometry": {"coordinates":[-1.51178026664947,51.25432207382615],"type":"Point"}
}