{
  "type": "Feature",
  "properties": {
    "date:inception_lower":"1995-01-01",
    "date:inception_upper":"1995-01-31",
    "iso:country":"GB",
    "wof:name":"PR2 8BA",
    "wof:placetype":"postalcode"
},
  "geometry": {"coordinates":[-2.681568,53.782044],"type":"Point"}
}