{
  "type": "Feature",
  "properties": {
    "iso:country": "GB",
    "wof:name": "E14 9QE",
    "wof:placetype": "postalcode"
  },
  "geometry": {"coordinates":[-0.0064,51.50852],"type":"Point"}
}
