{
  "type": "Feature",
  "properties": {
    "date:inception_lower":"1980-01-01",
    "date:inception_upper":"1980-01-31",
    "iso:country":"GB",
    "wof:name":"E14 9QE",
    "wof:placetype":"postalcode"
},
  "geometry": {"coordinates":[-0.0064,51.50852],"type":"Point"}
}