{
  "type": "Feature",
  "properties": {
    "iso:country": "GB",
    "wof:name": "BN3 7GW",
    "wof:placetype": "postalcode"
  },
  "geometry": {"coordinates":[-0.199739,50.836476],"type":"Point"}
}
