{
  "type": "Feature",
  "properties": {
    "date:inception_lower": "2003-08-01",
    "date:inception_upper": "2003-08-01",
    "iso:country": "GB",
    "wof:name": "G75 8GQ",
    "wof:placetype": "postalcode"
  },
  "geometry": {"coordinates":[-4.209085,55.756211],"type":"Point"}
}
