{
  "type": "Feature",
  "properties": {
    "iso:country":"GB",
    "wof:name":"G75 8GQ",
    "wof:placetype":"postalcode"
},
  "geometry": {"coordinates":[-4.20908525356983,55.7562113074445],"type":"Point"}
}