{
  "type": "Feature",
  "properties": {
    "iso:country": "GB",
    "wof:name": "SA12 7TZ",
    "wof:placetype": "postalcode"
  },
  "geometry": {"coordinates":[-3.827475,51.606266],"type":"Point"}
}
