{
  "type": "Feature",
  "properties": {
    "date:inception_lower": "2004-02-01",
    "date:inception_upper": "2004-02-01",
    "iso:country": "GB",
    "wof:name": "SA12 7TZ",
    "wof:placetype": "postalcode"
  },
  "geometry": {"coordinates":[-3.827475,51.606266],"type":"Point"}
}
