{
  "type": "Feature",
  "properties": {
    "iso:country": "GB",
    "wof:name": "KT22 8LZ",
    "wof:placetype": "postalcode"
  },
  "geometry": {"coordinates":[-0.319749,51.290935],"type":"Point"}
}
