{
  "type": "Feature",
  "properties": {
    "iso:country": "GB",
    "wof:name": "CA13 0QQ",
    "wof:placetype": "postalcode"
  },
  "geometry": {"coordinates":[-3.376095,54.653326],"type":"Point"}
}
