{
  "type": "Feature",
  "properties": {
    "iso:country":"GB",
    "wof:name":"DH2 2JH",
    "wof:placetype":"postalcode"
},
  "geometry": {"coordinates":[-1.58220028826869,54.86110453989251],"type":"Point"}
}