{
  "type": "Feature",
  "properties": {
    "iso:country": "GB",
    "wof:name": "SP10 1PD",
    "wof:placetype": "postalcode"
  },
  "geometry": {"coordinates":[-1.478584,51.207156],"type":"Point"}
}
