{
  "type": "Feature",
  "properties": {
    "iso:country":"GB",
    "wof:name":"SP10 1PD",
    "wof:placetype":"postalcode"
},
  "geometry": {"coordinates":[-1.47824875950352,51.20750923626729],"type":"Point"}
}