{
  "type": "Feature",
  "properties": {
    "date:inception_lower": "1982-03-01",
    "date:inception_upper": "1982-03-01",
    "iso:country": "GB",
    "wof:name": "YO8 8JU",
    "wof:placetype": "postalcode"
  },
  "geometry": {"coordinates":[-1.013937,53.724813],"type":"Point"}
}
