{
  "type": "Feature",
  "properties": {
    "iso:country":"GB",
    "wof:name":"YO8 8JU",
    "wof:placetype":"postalcode"
},
  "geometry": {"coordinates":[-1.0139373257928,53.72481306277666],"type":"Point"}
}