{
  "type": "Feature",
  "properties": {
    "iso:country": "GB",
    "wof:name": "B18 6RU",
    "wof:placetype": "postalcode"
  },
  "geometry": {"coordinates":[-1.917074,52.487755],"type":"Point"}
}
