{
  "type": "Feature",
  "properties": {
    "date:inception_lower": "1980-01-01",
    "date:inception_upper": "1980-01-01",
    "iso:country": "GB",
    "wof:name": "NE5 4PS",
    "wof:placetype": "postalcode"
  },
  "geometry": {"coordinates":[-1.696,55.010489],"type":"Point"}
}
