{
  "type": "Feature",
  "properties": {
    "iso:country":"GB",
    "wof:name":"DN5 8HL",
    "wof:placetype":"postalcode"
},
  "geometry": {"coordinates":[-1.15490552968635,53.53316746793168],"type":"Point"}
}