{
  "type": "Feature",
  "properties": {
    "iso:country":"GB",
    "wof:name":"SY7 9JZ",
    "wof:placetype":"postalcode"
},
  "geometry": {"coordinates":[-2.73068845444241,52.46664638199351],"type":"Point"}
}