{
  "type": "Feature",
  "properties": {
    "iso:country":"GB",
    "wof:name":"WS2 7LQ",
    "wof:placetype":"postalcode"
},
  "geometry": {"coordinates":[-2.0153125940589,52.60255600378048],"type":"Point"}
}