{
  "type": "Feature",
  "properties": {
    "iso:country":"GB",
    "wof:name":"M11 2DY",
    "wof:placetype":"postalcode"
},
  "geometry": {"coordinates":[-2.20169150270954,53.47350275492829],"type":"Point"}
}