{
  "type": "Feature",
  "properties": {
    "iso:country":"GB",
    "wof:name":"PO36 9EX",
    "wof:placetype":"postalcode"
},
  "geometry": {"coordinates":[-1.16232400102101,50.65008848318593],"type":"Point"}
}