{
  "type": "Feature",
  "properties": {
    "date:inception_lower": "1980-01-01",
    "date:inception_upper": "1980-01-01",
    "iso:country": "GB",
    "wof:name": "PO36 9EX",
    "wof:placetype": "postalcode"
  },
  "geometry": {"coordinates":[-1.162324,50.650088],"type":"Point"}
}
