{
  "type": "Feature",
  "properties": {
    "date:inception_lower": "2005-04-01",
    "date:inception_upper": "2005-04-01",
    "iso:country": "GB",
    "wof:name": "CW6 0HU",
    "wof:placetype": "postalcode"
  },
  "geometry": {"coordinates":[-2.713645,53.172175],"type":"Point"}
}
