{
  "type": "Feature",
  "properties": {
    "iso:country":"GB",
    "wof:name":"CW6 0HU",
    "wof:placetype":"postalcode"
},
  "geometry": {"coordinates":[-2.71364506208111,53.17217550321909],"type":"Point"}
}