{
  "type": "Feature",
  "properties": {
    "iso:country":"GB",
    "wof:name":"IP4 5LJ",
    "wof:placetype":"postalcode"
},
  "geometry": {"coordinates":[1.19450897695157,52.05900993261366],"type":"Point"}
}