{
  "type": "Feature",
  "properties": {
    "iso:country": "GB",
    "wof:name": "S12 2BG",
    "wof:placetype": "postalcode"
  },
  "geometry": {"coordinates":[-1.417392,53.359268],"type":"Point"}
}
