{
  "type": "Feature",
  "properties": {
    "iso:country": "GB",
    "wof:name": "KY12 9HZ",
    "wof:placetype": "postalcode"
  },
  "geometry": {"coordinates":[-3.601629,56.091315],"type":"Point"}
}
