{
  "type": "Feature",
  "properties": {
    "iso:country":"GB",
    "wof:name":"KY12 9HZ",
    "wof:placetype":"postalcode"
},
  "geometry": {"coordinates":[-3.60162909559997,56.09131517773925],"type":"Point"}
}