{
  "type": "Feature",
  "properties": {
    "date:inception_lower": "1992-10-01",
    "date:inception_upper": "1992-10-01",
    "iso:country": "GB",
    "wof:name": "KY12 9HZ",
    "wof:placetype": "postalcode"
  },
  "geometry": {"coordinates":[-3.601629,56.091315],"type":"Point"}
}
