{
  "type": "Feature",
  "properties": {
    "iso:country":"GB",
    "wof:name":"DE7 8NF",
    "wof:placetype":"postalcode"
},
  "geometry": {"coordinates":[-1.30716582407507,52.98664699215088],"type":"Point"}
}