{
  "type": "Feature",
  "properties": {
    "iso:country":"GB",
    "wof:name":"HD4 7HD",
    "wof:placetype":"postalcode"
},
  "geometry": {"coordinates":[-1.81325084018303,53.61446526471175],"type":"Point"}
}