{
  "type": "Feature",
  "properties": {
    "iso:country":"GB",
    "wof:name":"DG8 6RL",
    "wof:placetype":"postalcode"
},
  "geometry": {"coordinates":[-4.57643181657988,55.04178945159267],"type":"Point"}
}