{
  "type": "Feature",
  "properties": {
    "date:inception_lower":"1998-12-01",
    "date:inception_upper":"1998-12-31",
    "iso:country":"GB",
    "wof:name":"IV3 8TQ",
    "wof:placetype":"postalcode"
},
  "geometry": {"coordinates":[-4.264737,57.476993],"type":"Point"}
}