{
  "type": "Feature",
  "properties": {
    "iso:country":"GB",
    "wof:name":"IV3 8TQ",
    "wof:placetype":"postalcode"
},
  "geometry": {"coordinates":[-4.26473685527706,57.47699345009166],"type":"Point"}
}