{
  "type": "Feature",
  "properties": {
    "iso:country":"GB",
    "wof:name":"NW6 2DD",
    "wof:placetype":"postalcode"
},
  "geometry": {"coordinates":[-0.20031581617553,51.54413529155745],"type":"Point"}
}