{
  "type": "Feature",
  "properties": {
    "date:inception_lower": "2020-02-01",
    "date:inception_upper": "2020-02-01",
    "iso:country": "GB",
    "wof:name": "IP2 0HZ",
    "wof:placetype": "postalcode"
  },
  "geometry": {"coordinates":[1.124756,52.060744],"type":"Point"}
}
