{
  "type": "Feature",
  "properties": {
    "iso:country": "GB",
    "wof:name": "NG1 3HD",
    "wof:placetype": "postalcode"
  },
  "geometry": {"coordinates":[-1.150011,52.960747],"type":"Point"}
}
