{
  "type": "Feature",
  "properties": {
    "iso:country": "GB",
    "wof:name": "LS12 3JT",
    "wof:placetype": "postalcode"
  },
  "geometry": {"coordinates":[-1.598678,53.797863],"type":"Point"}
}
