{
  "type": "Feature",
  "properties": {
    "iso:country":"GB",
    "wof:name":"LS25 7NJ",
    "wof:placetype":"postalcode"
},
  "geometry": {"coordinates":[-1.37922222116612,53.76609034954524],"type":"Point"}
}