{
  "type": "Feature",
  "properties": {
    "date:inception_lower":"1980-01-01",
    "date:inception_upper":"1980-01-31",
    "iso:country":"GB",
    "wof:name":"LS25 7NJ",
    "wof:placetype":"postalcode"
},
  "geometry": {"coordinates":[-1.379222,53.76609],"type":"Point"}
}