{
  "type": "Feature",
  "properties": {
    "iso:country":"GB",
    "wof:name":"YO8 3XL",
    "wof:placetype":"postalcode"
},
  "geometry": {"coordinates":[-1.10348422913822,53.81503104677636],"type":"Point"}
}