{
  "type": "Feature",
  "properties": {
    "iso:country":"GB",
    "wof:name":"CB21 5AH",
    "wof:placetype":"postalcode"
},
  "geometry": {"coordinates":[0.20603693111777,52.18667939738974],"type":"Point"}
}