{
  "type": "Feature",
  "properties": {
    "iso:country": "GB",
    "wof:name": "NR16 1LX",
    "wof:placetype": "postalcode"
  },
  "geometry": {"coordinates":[1.152856,52.501228],"type":"Point"}
}
