{
  "type": "Feature",
  "properties": {
    "date:inception_lower":"1984-10-01",
    "date:inception_upper":"1984-10-31",
    "iso:country":"GB",
    "wof:name":"NR16 1LX",
    "wof:placetype":"postalcode"
},
  "geometry": {"coordinates":[1.152856,52.501228],"type":"Point"}
}