{
  "type": "Feature",
  "properties": {
    "date:inception_lower": "2016-06-01",
    "date:inception_upper": "2016-06-01",
    "iso:country": "GB",
    "wof:name": "OX25 2AF",
    "wof:placetype": "postalcode"
  },
  "geometry": {"coordinates":[-1.121516,51.868948],"type":"Point"}
}
