{
  "type": "Feature",
  "properties": {
    "date:inception_lower": "2018-07-01",
    "date:inception_upper": "2018-07-01",
    "iso:country": "GB",
    "wof:name": "WF8 2YT",
    "wof:placetype": "postalcode"
  },
  "geometry": {"coordinates":[-1.287341,53.693152],"type":"Point"}
}
