{
  "type": "Feature",
  "properties": {
    "iso:country":"GB",
    "wof:name":"TA20 2QF",
    "wof:placetype":"postalcode"
},
  "geometry": {"coordinates":[-2.94782366052537,50.84270428899539],"type":"Point"}
}