{
  "type": "Feature",
  "properties": {
    "iso:country":"GB",
    "wof:name":"DA13 0RG",
    "wof:placetype":"postalcode"
},
  "geometry": {"coordinates":[0.3445894555948,51.338870662001],"type":"Point"}
}