{
  "type": "Feature",
  "properties": {
    "date:inception_lower": "2024-09-01",
    "date:inception_upper": "2024-09-01",
    "iso:country": "GB",
    "wof:name": "SK17 9YE",
    "wof:placetype": "postalcode"
  },
  "geometry": {"coordinates":[-1.900283,53.241886],"type":"Point"}
}
