{
  "type": "Feature",
  "properties": {
    "date:inception_lower": "1980-01-01",
    "date:inception_upper": "1980-01-01",
    "iso:country": "GB",
    "wof:name": "IP13 6HQ",
    "wof:placetype": "postalcode"
  },
  "geometry": {"coordinates":[1.27111,52.104675],"type":"Point"}
}
