{
  "type": "Feature",
  "properties": {
    "iso:country":"GB",
    "wof:name":"CV6 4HL",
    "wof:placetype":"postalcode"
},
  "geometry": {"coordinates":[-1.51302843531192,52.45066944130343],"type":"Point"}
}