{
  "type": "Feature",
  "properties": {
    "date:inception_lower":"1995-07-01",
    "date:inception_upper":"1995-07-31",
    "iso:country":"GB",
    "wof:name":"RG18 9HX",
    "wof:placetype":"postalcode"
},
  "geometry": {"coordinates":[-1.255158,51.423322],"type":"Point"}
}