{
  "type": "Feature",
  "properties": {
    "iso:country": "GB",
    "wof:name": "RG18 9HX",
    "wof:placetype": "postalcode"
  },
  "geometry": {"coordinates":[-1.255158,51.423322],"type":"Point"}
}
