{
  "type": "Feature",
  "properties": {
    "iso:country":"GB",
    "wof:name":"RG18 9HX",
    "wof:placetype":"postalcode"
},
  "geometry": {"coordinates":[-1.25515845733079,51.42332228846826],"type":"Point"}
}