{
  "type": "Feature",
  "properties": {
    "iso:country":"GB",
    "wof:name":"BH23 2SL",
    "wof:placetype":"postalcode"
},
  "geometry": {"coordinates":[-1.79132804655905,50.74912383985019],"type":"Point"}
}