{
  "type": "Feature",
  "properties": {
    "iso:country": "GB",
    "wof:name": "NG14 5EJ",
    "wof:placetype": "postalcode"
  },
  "geometry": {"coordinates":[-1.033134,52.99136],"type":"Point"}
}
