{
  "type": "Feature",
  "properties": {
    "date:inception_lower": "1980-01-01",
    "date:inception_upper": "1980-01-01",
    "iso:country": "GB",
    "wof:name": "NG14 5EJ",
    "wof:placetype": "postalcode"
  },
  "geometry": {"coordinates":[-1.033134,52.99136],"type":"Point"}
}
