{
  "type": "Feature",
  "properties": {
    "iso:country":"GB",
    "wof:name":"SY22 6BL",
    "wof:placetype":"postalcode"
},
  "geometry": {"coordinates":[-3.16154374404979,52.77444103693914],"type":"Point"}
}