{
  "type": "Feature",
  "properties": {
    "date:inception_lower":"1995-07-01",
    "date:inception_upper":"1995-07-31",
    "iso:country":"GB",
    "wof:name":"SY22 6BL",
    "wof:placetype":"postalcode"
},
  "geometry": {"coordinates":[-3.161544,52.774441],"type":"Point"}
}