{
  "type": "Feature",
  "properties": {
    "iso:country": "GB",
    "wof:name": "SY22 6BL",
    "wof:placetype": "postalcode"
  },
  "geometry": {"coordinates":[-3.161544,52.774441],"type":"Point"}
}
