{
  "type": "Feature",
  "properties": {
    "iso:country":"GB",
    "wof:name":"HU17 8PQ",
    "wof:placetype":"postalcode"
},
  "geometry": {"coordinates":[-0.4425088879122,53.82677845094277],"type":"Point"}
}