{
  "type": "Feature",
  "properties": {
    "iso:country":"GB",
    "wof:name":"BD22 7RD",
    "wof:placetype":"postalcode"
},
  "geometry": {"coordinates":[-1.94992212695296,53.83790863532163],"type":"Point"}
}