{
  "type": "Feature",
  "properties": {
    "iso:country":"GB",
    "wof:name":"BS16 6PZ",
    "wof:placetype":"postalcode"
},
  "geometry": {"coordinates":[-2.50061657096317,51.50191763564144],"type":"Point"}
}