{
  "type": "Feature",
  "properties": {
    "date:inception_lower": "1980-01-01",
    "date:inception_upper": "1980-01-01",
    "iso:country": "GB",
    "wof:name": "BS16 6PZ",
    "wof:placetype": "postalcode"
  },
  "geometry": {"coordinates":[-2.500617,51.501918],"type":"Point"}
}
