{
  "type": "Feature",
  "properties": {
    "date:inception_lower": "1980-01-01",
    "date:inception_upper": "1980-01-01",
    "iso:country": "GB",
    "wof:name": "KY4 8HY",
    "wof:placetype": "postalcode"
  },
  "geometry": {"coordinates":[-3.344414,56.107189],"type":"Point"}
}
