{
  "type": "Feature",
  "properties": {
    "iso:country": "GB",
    "wof:name": "DY11 5HN",
    "wof:placetype": "postalcode"
  },
  "geometry": {"coordinates":[-2.260402,52.398729],"type":"Point"}
}
