{
  "type": "Feature",
  "properties": {
    "date:inception_lower":"1980-01-01",
    "date:inception_upper":"1980-01-31",
    "iso:country":"GB",
    "wof:name":"DY11 5HN",
    "wof:placetype":"postalcode"
},
  "geometry": {"coordinates":[-2.260402,52.398729],"type":"Point"}
}