{
  "type": "Feature",
  "properties": {
    "iso:country":"GB",
    "wof:name":"DY11 5HN",
    "wof:placetype":"postalcode"
},
  "geometry": {"coordinates":[-2.26040215398094,52.39872875226449],"type":"Point"}
}