{
  "type": "Feature",
  "properties": {
    "date:inception_lower":"1980-01-01",
    "date:inception_upper":"1980-01-31",
    "iso:country":"GB",
    "wof:name":"DN17 2SB",
    "wof:placetype":"postalcode"
},
  "geometry": {"coordinates":[-0.666653,53.556677],"type":"Point"}
}