{
  "type": "Feature",
  "properties": {
    "iso:country":"GB",
    "wof:name":"RG1 6LL",
    "wof:placetype":"postalcode"
},
  "geometry": {"coordinates":[-0.98387048598074,51.44827871439663],"type":"Point"}
}