{
  "type": "Feature",
  "properties": {
    "iso:country":"GB",
    "wof:name":"SE4 2JS",
    "wof:placetype":"postalcode"
},
  "geometry": {"coordinates":[-0.04358455671332,51.46327343130821],"type":"Point"}
}