{
  "type": "Feature",
  "properties": {
    "iso:country":"GB",
    "wof:name":"SE3 7NN",
    "wof:placetype":"postalcode"
},
  "geometry": {"coordinates":[0.01289248034976,51.48059957986672],"type":"Point"}
}