{
  "type": "Feature",
  "properties": {
    "iso:country": "GB",
    "wof:name": "SE3 7NN",
    "wof:placetype": "postalcode"
  },
  "geometry": {"coordinates":[0.012893,51.4806],"type":"Point"}
}
