{
  "type": "Feature",
  "properties": {
    "iso:country": "GB",
    "wof:name": "IP29 4AJ",
    "wof:placetype": "postalcode"
  },
  "geometry": {"coordinates":[0.670362,52.160605],"type":"Point"}
}
