{
  "type": "Feature",
  "properties": {
    "iso:country": "GB",
    "wof:name": "PO14 1EF",
    "wof:placetype": "postalcode"
  },
  "geometry": {"coordinates":[-1.194256,50.84213],"type":"Point"}
}
