{
  "type": "Feature",
  "properties": {
    "iso:country":"GB",
    "wof:name":"EX16 9AQ",
    "wof:placetype":"postalcode"
},
  "geometry": {"coordinates":[-3.48852340844935,51.00903084614312],"type":"Point"}
}