{
  "type": "Feature",
  "properties": {
    "iso:country": "GB",
    "wof:name": "EX16 9AQ",
    "wof:placetype": "postalcode"
  },
  "geometry": {"coordinates":[-3.488523,51.009031],"type":"Point"}
}
