{
  "type": "Feature",
  "properties": {
    "iso:country":"GB",
    "wof:name":"NE37 1UL",
    "wof:placetype":"postalcode"
},
  "geometry": {"coordinates":[-1.52964708071737,54.90719261716379],"type":"Point"}
}