{
  "type": "Feature",
  "properties": {
    "iso:country": "GB",
    "wof:name": "RH19 2LS",
    "wof:placetype": "postalcode"
  },
  "geometry": {"coordinates":[-0.004903,51.145971],"type":"Point"}
}
