{
  "type": "Feature",
  "properties": {
    "iso:country":"GB",
    "wof:name":"GL6 0AX",
    "wof:placetype":"postalcode"
},
  "geometry": {"coordinates":[-2.22009135095229,51.69973498169715],"type":"Point"}
}