{
  "type": "Feature",
  "properties": {
    "iso:country": "GB",
    "wof:name": "GL6 0AX",
    "wof:placetype": "postalcode"
  },
  "geometry": {"coordinates":[-2.220091,51.699735],"type":"Point"}
}
