{
  "type": "Feature",
  "properties": {
    "iso:country":"GB",
    "wof:name":"HP22 6QD",
    "wof:placetype":"postalcode"
},
  "geometry": {"coordinates":[-0.73768968970015,51.73432661899752],"type":"Point"}
}