{
  "type": "Feature",
  "properties": {
    "date:inception_lower": "1980-01-01",
    "date:inception_upper": "1980-01-01",
    "iso:country": "GB",
    "wof:name": "HP22 6QD",
    "wof:placetype": "postalcode"
  },
  "geometry": {"coordinates":[-0.73559,51.734508],"type":"Point"}
}
