{
  "type": "Feature",
  "properties": {
    "date:inception_lower":"1981-06-01",
    "date:inception_upper":"1981-06-30",
    "iso:country":"GB",
    "wof:name":"CT3 4HQ",
    "wof:placetype":"postalcode"
},
  "geometry": {"coordinates":[1.170826,51.313775],"type":"Point"}
}