{
  "type": "Feature",
  "properties": {
    "date:inception_lower":"2004-02-01",
    "date:inception_upper":"2004-02-29",
    "iso:country":"GB",
    "wof:name":"HA1 1SR",
    "wof:placetype":"postalcode"
},
  "geometry": {"coordinates":[-0.336024,51.585201],"type":"Point"}
}