{
  "type": "Feature",
  "properties": {
    "iso:country": "GB",
    "wof:name": "HA1 1SR",
    "wof:placetype": "postalcode"
  },
  "geometry": {"coordinates":[-0.336024,51.585201],"type":"Point"}
}
