{
  "type": "Feature",
  "properties": {
    "iso:country":"GB",
    "wof:name":"HA1 1SR",
    "wof:placetype":"postalcode"
},
  "geometry": {"coordinates":[-0.33602425684131,51.58520066985457],"type":"Point"}
}