{
  "type": "Feature",
  "properties": {
    "iso:country":"GB",
    "wof:name":"NN8 3PN",
    "wof:placetype":"postalcode"
},
  "geometry": {"coordinates":[-0.71340211621766,52.29528613482809],"type":"Point"}
}