{
  "type": "Feature",
  "properties": {
    "iso:country":"GB",
    "wof:name":"S20 1AN",
    "wof:placetype":"postalcode"
},
  "geometry": {"coordinates":[-1.34207744451901,53.35092068366329],"type":"Point"}
}