{
  "type": "Feature",
  "properties": {
    "iso:country": "GB",
    "wof:name": "S20 1AN",
    "wof:placetype": "postalcode"
  },
  "geometry": {"coordinates":[-1.342077,53.350957],"type":"Point"}
}
