{
  "type": "Feature",
  "properties": {
    "date:inception_lower":"1997-06-01",
    "date:inception_upper":"1997-06-30",
    "iso:country":"GB",
    "wof:name":"S20 1AN",
    "wof:placetype":"postalcode"
},
  "geometry": {"coordinates":[-1.342077,53.350957],"type":"Point"}
}