{
  "type": "Feature",
  "properties": {
    "iso:country": "GB",
    "wof:name": "SS2 4PT",
    "wof:placetype": "postalcode"
  },
  "geometry": {"coordinates":[0.742359,51.556505],"type":"Point"}
}
