{
  "type": "Feature",
  "properties": {
    "iso:country":"GB",
    "wof:name":"SS2 4PT",
    "wof:placetype":"postalcode"
},
  "geometry": {"coordinates":[0.74235913714793,51.55650540722652],"type":"Point"}
}