{
  "type": "Feature",
  "properties": {
    "iso:country": "GB",
    "wof:name": "SS5 4NZ",
    "wof:placetype": "postalcode"
  },
  "geometry": {"coordinates":[0.657672,51.596372],"type":"Point"}
}
