{
  "type": "Feature",
  "properties": {
    "iso:country":"GB",
    "wof:name":"SS5 4NZ",
    "wof:placetype":"postalcode"
},
  "geometry": {"coordinates":[0.65767166057708,51.59637184596924],"type":"Point"}
}