{
  "type": "Feature",
  "properties": {
    "iso:country":"GB",
    "wof:name":"WS6 6DZ",
    "wof:placetype":"postalcode"
},
  "geometry": {"coordinates":[-2.01691388746117,52.65729424071819],"type":"Point"}
}