{
  "type": "Feature",
  "properties": {
    "iso:country":"GB",
    "wof:name":"DL2 3PQ",
    "wof:placetype":"postalcode"
},
  "geometry": {"coordinates":[-1.80405109021028,54.58132800779876],"type":"Point"}
}