{
  "type": "Feature",
  "properties": {
    "iso:country": "GB",
    "wof:name": "DL2 3PQ",
    "wof:placetype": "postalcode"
  },
  "geometry": {"coordinates":[-1.804051,54.581328],"type":"Point"}
}
