{
  "type": "Feature",
  "properties": {
    "date:inception_lower": "1980-01-01",
    "date:inception_upper": "1980-01-01",
    "iso:country": "GB",
    "wof:name": "EX19 8NU",
    "wof:placetype": "postalcode"
  },
  "geometry": {"coordinates":[-4.054635,50.923936],"type":"Point"}
}
