{
  "type": "Feature",
  "properties": {
    "iso:country": "GB",
    "wof:name": "B73 6NP",
    "wof:placetype": "postalcode"
  },
  "geometry": {"coordinates":[-1.843851,52.550925],"type":"Point"}
}
