{
  "type": "Feature",
  "properties": {
    "iso:country":"GB",
    "wof:name":"B73 6NP",
    "wof:placetype":"postalcode"
},
  "geometry": {"coordinates":[-1.84385079153564,52.55092481569249],"type":"Point"}
}