{
  "type": "Feature",
  "properties": {
    "iso:country": "GB",
    "wof:name": "LS8 4LJ",
    "wof:placetype": "postalcode"
  },
  "geometry": {"coordinates":[-1.523075,53.816372],"type":"Point"}
}
