{
  "type": "Feature",
  "properties": {
    "iso:country":"GB",
    "wof:name":"LS8 4LJ",
    "wof:placetype":"postalcode"
},
  "geometry": {"coordinates":[-1.52307547556221,53.81637166546149],"type":"Point"}
}