{
  "type": "Feature",
  "properties": {
    "iso:country":"GB",
    "wof:name":"GU2 9RZ",
    "wof:placetype":"postalcode"
},
  "geometry": {"coordinates":[-0.59391101795559,51.25414496027113],"type":"Point"}
}