{
  "type": "Feature",
  "properties": {
    "iso:country": "GB",
    "wof:name": "CF35 6AZ",
    "wof:placetype": "postalcode"
  },
  "geometry": {"coordinates":[-3.558333,51.522252],"type":"Point"}
}
