{
  "type": "Feature",
  "properties": {
    "date:inception_lower":"1998-12-01",
    "date:inception_upper":"1998-12-31",
    "iso:country":"GB",
    "wof:name":"CF35 6AZ",
    "wof:placetype":"postalcode"
},
  "geometry": {"coordinates":[-3.558333,51.522252],"type":"Point"}
}