{
  "type": "Feature",
  "properties": {
    "iso:country":"GB",
    "wof:name":"KT10 9RH",
    "wof:placetype":"postalcode"
},
  "geometry": {"coordinates":[-0.36433639415198,51.3700528305033],"type":"Point"}
}