{
  "type": "Feature",
  "properties": {
    "iso:country":"GB",
    "wof:name":"B11 3LL",
    "wof:placetype":"postalcode"
},
  "geometry": {"coordinates":[-1.85983846332954,52.44850448201024],"type":"Point"}
}