{
  "type": "Feature",
  "properties": {
    "iso:country":"GB",
    "wof:name":"OL7 0PP",
    "wof:placetype":"postalcode"
},
  "geometry": {"coordinates":[-2.10045800685167,53.48336543304501],"type":"Point"}
}