{
  "type": "Feature",
  "properties": {
    "iso:country": "GB",
    "wof:name": "OL7 0PP",
    "wof:placetype": "postalcode"
  },
  "geometry": {"coordinates":[-2.100458,53.483365],"type":"Point"}
}
