{
  "type": "Feature",
  "properties": {
    "iso:country": "GB",
    "wof:name": "PO22 7PR",
    "wof:placetype": "postalcode"
  },
  "geometry": {"coordinates":[-0.651775,50.791808],"type":"Point"}
}
