{
  "type": "Feature",
  "properties": {
    "date:inception_lower":"2018-08-01",
    "date:inception_upper":"2018-08-31",
    "iso:country":"GB",
    "wof:name":"PO22 7PR",
    "wof:placetype":"postalcode"
},
  "geometry": {"coordinates":[-0.651775,50.791808],"type":"Point"}
}