{
  "type": "Feature",
  "properties": {
    "iso:country":"GB",
    "wof:name":"SE14 5LJ",
    "wof:placetype":"postalcode"
},
  "geometry": {"coordinates":[-0.05070996382232,51.47106287434198],"type":"Point"}
}