{
  "type": "Feature",
  "properties": {
    "iso:country":"GB",
    "wof:name":"EN2 6TQ",
    "wof:placetype":"postalcode"
},
  "geometry": {"coordinates":[-0.08494938235424,51.65137831687775],"type":"Point"}
}