{
  "type": "Feature",
  "properties": {
    "iso:country":"GB",
    "wof:name":"B90 1DA",
    "wof:placetype":"postalcode"
},
  "geometry": {"coordinates":[-1.84555425907371,52.40136088063758],"type":"Point"}
}