{
  "type": "Feature",
  "properties": {
    "iso:country": "GB",
    "wof:name": "B90 1DA",
    "wof:placetype": "postalcode"
  },
  "geometry": {"coordinates":[-1.845554,52.401361],"type":"Point"}
}
