{
  "type": "Feature",
  "properties": {
    "iso:country":"GB",
    "wof:name":"WA11 8LS",
    "wof:placetype":"postalcode"
},
  "geometry": {"coordinates":[-2.76862191378593,53.49020194819435],"type":"Point"}
}