{
  "type": "Feature",
  "properties": {
    "date:inception_lower":"2015-06-01",
    "date:inception_upper":"2015-06-30",
    "iso:country":"GB",
    "wof:name":"CH7 5FA",
    "wof:placetype":"postalcode"
},
  "geometry": {"coordinates":[-3.190615,53.156424],"type":"Point"}
}