{
  "type": "Feature",
  "properties": {
    "iso:country":"GB",
    "wof:name":"CH7 5FA",
    "wof:placetype":"postalcode"
},
  "geometry": {"coordinates":[-3.19061529085328,53.15642386162311],"type":"Point"}
}