{
  "type": "Feature",
  "properties": {
    "date:inception_lower": "1999-06-01",
    "date:inception_upper": "1999-06-01",
    "iso:country": "GB",
    "wof:name": "CF23 9PF",
    "wof:placetype": "postalcode"
  },
  "geometry": {"coordinates":[-3.149945,51.513928],"type":"Point"}
}
