{
  "type": "Feature",
  "properties": {
    "iso:country": "GB",
    "wof:name": "SK14 5PG",
    "wof:placetype": "postalcode"
  },
  "geometry": {"coordinates":[-2.067113,53.447192],"type":"Point"}
}
