{
  "type": "Feature",
  "properties": {
    "iso:country":"GB",
    "wof:name":"EH23 4HJ",
    "wof:placetype":"postalcode"
},
  "geometry": {"coordinates":[-3.04466773449845,55.84044948726535],"type":"Point"}
}