{
  "type": "Feature",
  "properties": {
    "iso:country": "GB",
    "wof:name": "EH23 4HJ",
    "wof:placetype": "postalcode"
  },
  "geometry": {"coordinates":[-3.044668,55.840449],"type":"Point"}
}
