{
  "type": "Feature",
  "properties": {
    "date:inception_lower": "1980-01-01",
    "date:inception_upper": "1980-01-01",
    "iso:country": "GB",
    "wof:name": "EH23 4HJ",
    "wof:placetype": "postalcode"
  },
  "geometry": {"coordinates":[-3.044668,55.840449],"type":"Point"}
}
