{
  "type": "Feature",
  "properties": {
    "date:inception_lower":"1996-06-01",
    "date:inception_upper":"1996-06-30",
    "iso:country":"GB",
    "wof:name":"AB24 2TD",
    "wof:placetype":"postalcode"
},
  "geometry": {"coordinates":[-2.108442,57.168757],"type":"Point"}
}