{
  "type": "Feature",
  "properties": {
    "iso:country":"GB",
    "wof:name":"BB6 7RW",
    "wof:placetype":"postalcode"
},
  "geometry": {"coordinates":[-2.39809633579907,53.78894720815624],"type":"Point"}
}