{
  "type": "Feature",
  "properties": {
    "iso:country": "GB",
    "wof:name": "B78 3DZ",
    "wof:placetype": "postalcode"
  },
  "geometry": {"coordinates":[-1.756217,52.603312],"type":"Point"}
}
