{
  "type": "Feature",
  "properties": {
    "iso:country":"GB",
    "wof:name":"B78 3DZ",
    "wof:placetype":"postalcode"
},
  "geometry": {"coordinates":[-1.74911177863632,52.6076498082395],"type":"Point"}
}