{
  "type": "Feature",
  "properties": {
    "date:inception_lower":"1980-01-01",
    "date:inception_upper":"1980-01-31",
    "iso:country":"GB",
    "wof:name":"B78 3DZ",
    "wof:placetype":"postalcode"
},
  "geometry": {"coordinates":[-1.756217,52.603312],"type":"Point"}
}