{
  "type": "Feature",
  "properties": {
    "iso:country":"GB",
    "wof:name":"PO6 4LH",
    "wof:placetype":"postalcode"
},
  "geometry": {"coordinates":[-1.11312086525283,50.85530970669311],"type":"Point"}
}