{
  "type": "Feature",
  "properties": {
    "date:inception_lower": "1980-01-01",
    "date:inception_upper": "1980-01-01",
    "iso:country": "GB",
    "wof:name": "PO6 4LH",
    "wof:placetype": "postalcode"
  },
  "geometry": {"coordinates":[-1.113121,50.85531],"type":"Point"}
}
