{
  "type": "Feature",
  "properties": {
    "date:inception_lower": "2024-01-01",
    "date:inception_upper": "2024-01-01",
    "iso:country": "GB",
    "wof:name": "CM3 8FP",
    "wof:placetype": "postalcode"
  },
  "geometry": {"coordinates":[0.533638,51.657722],"type":"Point"}
}
