{
  "type": "Feature",
  "properties": {
    "iso:country":"GB",
    "wof:name":"WV11 2NL",
    "wof:placetype":"postalcode"
},
  "geometry": {"coordinates":[-2.06000175309175,52.62044030573894],"type":"Point"}
}