{
  "type": "Feature",
  "properties": {
    "iso:country": "GB",
    "wof:name": "WV11 2NL",
    "wof:placetype": "postalcode"
  },
  "geometry": {"coordinates":[-2.060002,52.62044],"type":"Point"}
}
