{
  "type": "Feature",
  "properties": {
    "date:inception_lower": "1980-01-01",
    "date:inception_upper": "1980-01-01",
    "iso:country": "GB",
    "wof:name": "WV11 2NL",
    "wof:placetype": "postalcode"
  },
  "geometry": {"coordinates":[-2.060002,52.62044],"type":"Point"}
}
