{
  "type": "Feature",
  "properties": {
    "date:inception_lower": "1980-01-01",
    "date:inception_upper": "1980-01-01",
    "iso:country": "GB",
    "wof:name": "CO7 0QX",
    "wof:placetype": "postalcode"
  },
  "geometry": {"coordinates":[1.01814,51.824167],"type":"Point"}
}
