{
  "type": "Feature",
  "properties": {
    "iso:country":"GB",
    "wof:name":"CO7 0QX",
    "wof:placetype":"postalcode"
},
  "geometry": {"coordinates":[1.01813999240249,51.82416725036523],"type":"Point"}
}