{
  "type": "Feature",
  "properties": {
    "date:inception_lower":"1994-05-01",
    "date:inception_upper":"1994-05-31",
    "iso:country":"GB",
    "wof:name":"LE9 2EE",
    "wof:placetype":"postalcode"
},
  "geometry": {"coordinates":[-1.227207,52.630748],"type":"Point"}
}