{
  "type": "Feature",
  "properties": {
    "iso:country": "GB",
    "wof:name": "LE9 2EE",
    "wof:placetype": "postalcode"
  },
  "geometry": {"coordinates":[-1.227207,52.630748],"type":"Point"}
}
