{
  "type": "Feature",
  "properties": {
    "iso:country":"GB",
    "wof:name":"LE9 2EE",
    "wof:placetype":"postalcode"
},
  "geometry": {"coordinates":[-1.22720724724828,52.63074753260459],"type":"Point"}
}