{
  "type": "Feature",
  "properties": {
    "iso:country":"GB",
    "wof:name":"BH6 3RH",
    "wof:placetype":"postalcode"
},
  "geometry": {"coordinates":[-1.81440121787915,50.72472075455231],"type":"Point"}
}