{
  "type": "Feature",
  "properties": {
    "date:inception_lower": "2002-11-01",
    "date:inception_upper": "2002-11-01",
    "iso:country": "GB",
    "wof:name": "BH6 3RH",
    "wof:placetype": "postalcode"
  },
  "geometry": {"coordinates":[-1.81377,50.724763],"type":"Point"}
}
