{
  "type": "Feature",
  "properties": {
    "iso:country": "GB",
    "wof:name": "BH6 3RH",
    "wof:placetype": "postalcode"
  },
  "geometry": {"coordinates":[-1.814401,50.724721],"type":"Point"}
}
