{
  "type": "Feature",
  "properties": {
    "iso:country": "GB",
    "wof:name": "SN12 8QL",
    "wof:placetype": "postalcode"
  },
  "geometry": {"coordinates":[-2.165048,51.396914],"type":"Point"}
}
