{
  "type": "Feature",
  "properties": {
    "iso:country":"GB",
    "wof:name":"SN12 8QL",
    "wof:placetype":"postalcode"
},
  "geometry": {"coordinates":[-2.1650479116873,51.39691412513594],"type":"Point"}
}