{
  "type": "Feature",
  "properties": {
    "date:inception_lower": "1980-01-01",
    "date:inception_upper": "1980-01-01",
    "iso:country": "GB",
    "wof:name": "SN12 8QL",
    "wof:placetype": "postalcode"
  },
  "geometry": {"coordinates":[-2.165048,51.396914],"type":"Point"}
}
