{
  "type": "Feature",
  "properties": {
    "date:inception_lower": "1980-01-01",
    "date:inception_upper": "1980-01-01",
    "iso:country": "GB",
    "wof:name": "EH39 5HG",
    "wof:placetype": "postalcode"
  },
  "geometry": {"coordinates":[-2.786795,56.043473],"type":"Point"}
}
