{
  "type": "Feature",
  "properties": {
    "iso:country":"GB",
    "wof:name":"SM4 5JS",
    "wof:placetype":"postalcode"
},
  "geometry": {"coordinates":[-0.19484316207525,51.39583673859921],"type":"Point"}
}