{
  "type": "Feature",
  "properties": {
    "iso:country":"GB",
    "wof:name":"M21 0SJ",
    "wof:placetype":"postalcode"
},
  "geometry": {"coordinates":[-2.27238534558398,53.44376325860127],"type":"Point"}
}