{
  "type": "Feature",
  "properties": {
    "date:inception_lower": "1980-01-01",
    "date:inception_upper": "1980-01-01",
    "iso:country": "GB",
    "wof:name": "BD3 0EQ",
    "wof:placetype": "postalcode"
  },
  "geometry": {"coordinates":[-1.745466,53.798741],"type":"Point"}
}
