{
  "type": "Feature",
  "properties": {
    "iso:country": "GB",
    "wof:name": "BD3 0EQ",
    "wof:placetype": "postalcode"
  },
  "geometry": {"coordinates":[-1.745466,53.798741],"type":"Point"}
}
