{
  "type": "Feature",
  "properties": {
    "iso:country":"GB",
    "wof:name":"BD3 0EQ",
    "wof:placetype":"postalcode"
},
  "geometry": {"coordinates":[-1.74546611443538,53.79874071672241],"type":"Point"}
}