{
  "type": "Feature",
  "properties": {
    "iso:country":"GB",
    "wof:name":"TR12 7EY",
    "wof:placetype":"postalcode"
},
  "geometry": {"coordinates":[-5.24328759886884,50.01164180074364],"type":"Point"}
}