{
  "type": "Feature",
  "properties": {
    "iso:country":"GB",
    "wof:name":"L23 5UE",
    "wof:placetype":"postalcode"
},
  "geometry": {"coordinates":[-3.02741306897039,53.49151987602161],"type":"Point"}
}