{
  "type": "Feature",
  "properties": {
    "iso:country":"GB",
    "wof:name":"HA1 4RH",
    "wof:placetype":"postalcode"
},
  "geometry": {"coordinates":[-0.35027286812922,51.58754195039392],"type":"Point"}
}