{
  "type": "Feature",
  "properties": {
    "iso:country":"GB",
    "wof:name":"HU17 9HJ",
    "wof:placetype":"postalcode"
},
  "geometry": {"coordinates":[-0.42873676086017,53.84643740347496],"type":"Point"}
}