{
  "type": "Feature",
  "properties": {
    "iso:country": "GB",
    "wof:name": "CT2 9DX",
    "wof:placetype": "postalcode"
  },
  "geometry": {"coordinates":[1.053444,51.293763],"type":"Point"}
}
