{
  "type": "Feature",
  "properties": {
    "iso:country":"GB",
    "wof:name":"CT2 9DX",
    "wof:placetype":"postalcode"
},
  "geometry": {"coordinates":[1.05344347365906,51.29376275588322],"type":"Point"}
}