{
  "type": "Feature",
  "properties": {
    "date:inception_lower": "2018-11-01",
    "date:inception_upper": "2018-11-01",
    "iso:country": "GB",
    "wof:name": "BB7 4SG",
    "wof:placetype": "postalcode"
  },
  "geometry": {"coordinates":[-2.375479,53.882149],"type":"Point"}
}
