{
  "type": "Feature",
  "properties": {
    "iso:country":"GB",
    "wof:name":"HD8 9RB",
    "wof:placetype":"postalcode"
},
  "geometry": {"coordinates":[-1.63240886671154,53.61042460009777],"type":"Point"}
}