{
  "type": "Feature",
  "properties": {
    "iso:country":"GB",
    "wof:name":"TW14 0PU",
    "wof:placetype":"postalcode"
},
  "geometry": {"coordinates":[-0.4113927802393,51.46447258287733],"type":"Point"}
}