{
  "type": "Feature",
  "properties": {
    "iso:country": "GB",
    "wof:name": "TW14 0PU",
    "wof:placetype": "postalcode"
  },
  "geometry": {"coordinates":[-0.411643,51.46453],"type":"Point"}
}
