{
  "type": "Feature",
  "properties": {
    "iso:country":"GB",
    "wof:name":"S35 1US",
    "wof:placetype":"postalcode"
},
  "geometry": {"coordinates":[-1.48964841930034,53.45881431764708],"type":"Point"}
}