{
  "type": "Feature",
  "properties": {
    "iso:country": "GB",
    "wof:name": "IG1 2NL",
    "wof:placetype": "postalcode"
  },
  "geometry": {"coordinates":[0.074751,51.546969],"type":"Point"}
}
