{
  "type": "Feature",
  "properties": {
    "iso:country":"GB",
    "wof:name":"NE66 9DY",
    "wof:placetype":"postalcode"
},
  "geometry": {"coordinates":[-1.69771704360449,55.40108312731825],"type":"Point"}
}