{
  "type": "Feature",
  "properties": {
    "iso:country":"GB",
    "wof:name":"LE3 2GD",
    "wof:placetype":"postalcode"
},
  "geometry": {"coordinates":[-1.17039170901981,52.61306671380753],"type":"Point"}
}