{
  "type": "Feature",
  "properties": {
    "iso:country":"GB",
    "wof:name":"LS25 1NX",
    "wof:placetype":"postalcode"
},
  "geometry": {"coordinates":[-1.37553905079144,53.79143577318465],"type":"Point"}
}