{
  "type": "Feature",
  "properties": {
    "iso:country":"GB",
    "wof:name":"SP10 2AA",
    "wof:placetype":"postalcode"
},
  "geometry": {"coordinates":[-1.47616619780823,51.20559363386578],"type":"Point"}
}