{
  "type": "Feature",
  "properties": {
    "date:inception_lower": "2016-01-01",
    "date:inception_upper": "2016-01-01",
    "iso:country": "GB",
    "wof:name": "CB2 9EE",
    "wof:placetype": "postalcode"
  },
  "geometry": {"coordinates":[0.104889,52.17062],"type":"Point"}
}
