{
  "type": "Feature",
  "properties": {
    "iso:country":"GB",
    "wof:name":"CB2 9EE",
    "wof:placetype":"postalcode"
},
  "geometry": {"coordinates":[0.10555415226214,52.17043310144685],"type":"Point"}
}