{
  "type": "Feature",
  "properties": {
    "iso:country":"GB",
    "wof:name":"SL2 5DP",
    "wof:placetype":"postalcode"
},
  "geometry": {"coordinates":[-0.58989858955548,51.51320816371282],"type":"Point"}
}