{
  "type": "Feature",
  "properties": {
    "date:inception_lower": "2003-06-01",
    "date:inception_upper": "2003-06-01",
    "iso:country": "GB",
    "wof:name": "SL2 5DP",
    "wof:placetype": "postalcode"
  },
  "geometry": {"coordinates":[-0.589899,51.513208],"type":"Point"}
}
