{
  "type": "Feature",
  "properties": {
    "date:inception_lower":"1991-01-01",
    "date:inception_upper":"1991-01-31",
    "iso:country":"GB",
    "wof:name":"DN9 3BQ",
    "wof:placetype":"postalcode"
},
  "geometry": {"coordinates":[-0.982768,53.498731],"type":"Point"}
}