{
  "type": "Feature",
  "properties": {
    "iso:country":"GB",
    "wof:name":"DN9 3BQ",
    "wof:placetype":"postalcode"
},
  "geometry": {"coordinates":[-0.98276763688846,53.49873060685854],"type":"Point"}
}