{
  "type": "Feature",
  "properties": {
    "iso:country": "GB",
    "wof:name": "DN9 3BQ",
    "wof:placetype": "postalcode"
  },
  "geometry": {"coordinates":[-0.982768,53.498731],"type":"Point"}
}
