{
  "type": "Feature",
  "properties": {
    "iso:country":"GB",
    "wof:name":"SP8 5AB",
    "wof:placetype":"postalcode"
},
  "geometry": {"coordinates":[-2.28920669073388,51.06561830993638],"type":"Point"}
}