{
  "type": "Feature",
  "properties": {
    "iso:country": "GB",
    "wof:name": "NR10 4YA",
    "wof:placetype": "postalcode"
  },
  "geometry": {"coordinates":[1.205686,52.698633],"type":"Point"}
}
