{
  "type": "Feature",
  "properties": {
    "date:inception_lower": "1980-01-01",
    "date:inception_upper": "1980-01-01",
    "iso:country": "GB",
    "wof:name": "TN30 7JP",
    "wof:placetype": "postalcode"
  },
  "geometry": {"coordinates":[0.765152,51.017046],"type":"Point"}
}
