{
  "type": "Feature",
  "properties": {
    "iso:country":"GB",
    "wof:name":"LL53 5AT",
    "wof:placetype":"postalcode"
},
  "geometry": {"coordinates":[-4.41196747681435,52.88296566537112],"type":"Point"}
}