{
  "type": "Feature",
  "properties": {
    "date:inception_lower":"1994-12-01",
    "date:inception_upper":"1994-12-31",
    "iso:country":"GB",
    "wof:name":"SO45 5GW",
    "wof:placetype":"postalcode"
},
  "geometry": {"coordinates":[-1.403194,50.859977],"type":"Point"}
}