{
  "type": "Feature",
  "properties": {
    "date:inception_lower": "2024-06-01",
    "date:inception_upper": "2024-06-01",
    "iso:country": "GB",
    "wof:name": "NN8 1UT",
    "wof:placetype": "postalcode"
  },
  "geometry": {"coordinates":[-0.690374,52.303382],"type":"Point"}
}
