{
  "type": "Feature",
  "properties": {
    "iso:country":"GB",
    "wof:name":"CF14 9HQ",
    "wof:placetype":"postalcode"
},
  "geometry": {"coordinates":[-3.19909378353326,51.53721959281403],"type":"Point"}
}