{
  "type": "Feature",
  "properties": {
    "iso:country": "GB",
    "wof:name": "PE11 3AA",
    "wof:placetype": "postalcode"
  },
  "geometry": {"coordinates":[-0.160773,52.773608],"type":"Point"}
}
