{
  "type": "Feature",
  "properties": {
    "date:inception_lower":"1980-01-01",
    "date:inception_upper":"1980-01-31",
    "iso:country":"GB",
    "wof:name":"CV10 7HW",
    "wof:placetype":"postalcode"
},
  "geometry": {"coordinates":[-1.487362,52.512466],"type":"Point"}
}