{
  "type": "Feature",
  "properties": {
    "iso:country": "GB",
    "wof:name": "CV10 7HW",
    "wof:placetype": "postalcode"
  },
  "geometry": {"coordinates":[-1.487362,52.512466],"type":"Point"}
}
