{
  "type": "Feature",
  "properties": {
    "iso:country":"GB",
    "wof:name":"CV10 7HW",
    "wof:placetype":"postalcode"
},
  "geometry": {"coordinates":[-1.48775633455871,52.51218952979765],"type":"Point"}
}