{
  "type": "Feature",
  "properties": {
    "iso:country":"GB",
    "wof:name":"CF5 2BE",
    "wof:placetype":"postalcode"
},
  "geometry": {"coordinates":[-3.22837602522107,51.48679567910015],"type":"Point"}
}