{
  "type": "Feature",
  "properties": {
    "iso:country":"GB",
    "wof:name":"G62 8EN",
    "wof:placetype":"postalcode"
},
  "geometry": {"coordinates":[-4.34043241969519,55.96559988248127],"type":"Point"}
}