{
  "type": "Feature",
  "properties": {
    "iso:country":"GB",
    "wof:name":"SW20 8EJ",
    "wof:placetype":"postalcode"
},
  "geometry": {"coordinates":[-0.2220716619799,51.40875269989127],"type":"Point"}
}