{
  "type": "Feature",
  "properties": {
    "date:inception_lower": "1980-01-01",
    "date:inception_upper": "1980-01-01",
    "iso:country": "GB",
    "wof:name": "SW20 8EJ",
    "wof:placetype": "postalcode"
  },
  "geometry": {"coordinates":[-0.222133,51.40878],"type":"Point"}
}
