{
  "type": "Feature",
  "properties": {
    "iso:country":"GB",
    "wof:name":"YO25 5JP",
    "wof:placetype":"postalcode"
},
  "geometry": {"coordinates":[-0.43505676941994,54.00979227318771],"type":"Point"}
}