{
  "type": "Feature",
  "properties": {
    "date:inception_lower": "1998-06-01",
    "date:inception_upper": "1998-06-01",
    "iso:country": "GB",
    "wof:name": "YO25 5JP",
    "wof:placetype": "postalcode"
  },
  "geometry": {"coordinates":[-0.435021,54.009847],"type":"Point"}
}
