{
  "type": "Feature",
  "properties": {
    "iso:country":"GB",
    "wof:name":"HG4 4DL",
    "wof:placetype":"postalcode"
},
  "geometry": {"coordinates":[-1.64129883044215,54.20748690579421],"type":"Point"}
}