{
  "type": "Feature",
  "properties": {
    "date:inception_lower":"1980-01-01",
    "date:inception_upper":"1980-01-31",
    "iso:country":"GB",
    "wof:name":"HG4 4DL",
    "wof:placetype":"postalcode"
},
  "geometry": {"coordinates":[-1.641108,54.207345],"type":"Point"}
}