{
  "type": "Feature",
  "properties": {
    "date:inception_lower":"1992-08-01",
    "date:inception_upper":"1992-08-31",
    "iso:country":"GB",
    "wof:name":"DE56 0DP",
    "wof:placetype":"postalcode"
},
  "geometry": {"coordinates":[-1.450095,53.028735],"type":"Point"}
}