{
  "type": "Feature",
  "properties": {
    "date:inception_lower":"1980-01-01",
    "date:inception_upper":"1980-01-31",
    "iso:country":"GB",
    "wof:name":"GU4 7LQ",
    "wof:placetype":"postalcode"
},
  "geometry": {"coordinates":[-0.536115,51.264165],"type":"Point"}
}