{
  "type": "Feature",
  "properties": {
    "iso:country":"GB",
    "wof:name":"GU4 7LQ",
    "wof:placetype":"postalcode"
},
  "geometry": {"coordinates":[-0.53611454512859,51.26416451241604],"type":"Point"}
}