{
  "type": "Feature",
  "properties": {
    "iso:country":"GB",
    "wof:name":"CO9 1DH",
    "wof:placetype":"postalcode"
},
  "geometry": {"coordinates":[0.63435814402883,51.94141179165543],"type":"Point"}
}