{
  "type": "Feature",
  "properties": {
    "iso:country": "GB",
    "wof:name": "CV37 0TP",
    "wof:placetype": "postalcode"
  },
  "geometry": {"coordinates":[-1.726127,52.204888],"type":"Point"}
}
