{
  "type": "Feature",
  "properties": {
    "iso:country":"GB",
    "wof:name":"CV37 0TP",
    "wof:placetype":"postalcode"
},
  "geometry": {"coordinates":[-1.72612732064278,52.20488756095678],"type":"Point"}
}