{
  "type": "Feature",
  "properties": {
    "iso:country": "GB",
    "wof:name": "RM9 4BU",
    "wof:placetype": "postalcode"
  },
  "geometry": {"coordinates":[0.117254,51.53351],"type":"Point"}
}
