{
  "type": "Feature",
  "properties": {
    "date:inception_lower":"2014-08-01",
    "date:inception_upper":"2014-08-31",
    "iso:country":"GB",
    "wof:name":"RM9 4BU",
    "wof:placetype":"postalcode"
},
  "geometry": {"coordinates":[0.117254,51.53351],"type":"Point"}
}