{
  "type": "Feature",
  "properties": {
    "iso:country":"GB",
    "wof:name":"RM9 4BU",
    "wof:placetype":"postalcode"
},
  "geometry": {"coordinates":[0.11725355730555,51.53350979576838],"type":"Point"}
}