{
  "type": "Feature",
  "properties": {
    "iso:country":"GB",
    "wof:name":"GU30 7GN",
    "wof:placetype":"postalcode"
},
  "geometry": {"coordinates":[-0.7956922220339,51.08276033158565],"type":"Point"}
}