{
  "type": "Feature",
  "properties": {
    "date:inception_lower":"2011-03-01",
    "date:inception_upper":"2011-03-31",
    "iso:country":"GB",
    "wof:name":"GU30 7GN",
    "wof:placetype":"postalcode"
},
  "geometry": {"coordinates":[-0.795692,51.08276],"type":"Point"}
}