{
  "type": "Feature",
  "properties": {
    "iso:country":"GB",
    "wof:name":"TA1 2TE",
    "wof:placetype":"postalcode"
},
  "geometry": {"coordinates":[-3.07681778436447,51.01583596036819],"type":"Point"}
}