{
  "type": "Feature",
  "properties": {
    "iso:country":"GB",
    "wof:name":"RM9 6HT",
    "wof:placetype":"postalcode"
},
  "geometry": {"coordinates":[0.14321276340529,51.53975597362087],"type":"Point"}
}