{
  "type": "Feature",
  "properties": {
    "iso:country":"GB",
    "wof:name":"ME7 4QD",
    "wof:placetype":"postalcode"
},
  "geometry": {"coordinates":[0.55024771055365,51.38596151267366],"type":"Point"}
}