{
  "type": "Feature",
  "properties": {
    "iso:country": "GB",
    "wof:name": "NG24 3ED",
    "wof:placetype": "postalcode"
  },
  "geometry": {"coordinates":[-0.788714,53.054084],"type":"Point"}
}
