{
  "type": "Feature",
  "properties": {
    "iso:country":"GB",
    "wof:name":"PA13 4EX",
    "wof:placetype":"postalcode"
},
  "geometry": {"coordinates":[-4.6275233975525,55.89476201092363],"type":"Point"}
}