{
  "type": "Feature",
  "properties": {
    "date:inception_lower":"2005-12-01",
    "date:inception_upper":"2005-12-31",
    "iso:country":"GB",
    "wof:name":"PA13 4EX",
    "wof:placetype":"postalcode"
},
  "geometry": {"coordinates":[-4.627424,55.894731],"type":"Point"}
}