{
  "type": "Feature",
  "properties": {
    "iso:country":"GB",
    "wof:name":"PR7 7ES",
    "wof:placetype":"postalcode"
},
  "geometry": {"coordinates":[-2.65998381578808,53.67731690694761],"type":"Point"}
}