{
  "type": "Feature",
  "properties": {
    "iso:country":"GB",
    "wof:name":"PR1 7TB",
    "wof:placetype":"postalcode"
},
  "geometry": {"coordinates":[-2.7111164092957,53.76856071303965],"type":"Point"}
}