{
  "type": "Feature",
  "properties": {
    "iso:country":"GB",
    "wof:name":"NG6 0JX",
    "wof:placetype":"postalcode"
},
  "geometry": {"coordinates":[-1.18902688288276,52.98492928220727],"type":"Point"}
}