{
  "type": "Feature",
  "properties": {
    "iso:country": "GB",
    "wof:name": "NE32 5JS",
    "wof:placetype": "postalcode"
  },
  "geometry": {"coordinates":[-1.499411,54.977165],"type":"Point"}
}
