{
  "type": "Feature",
  "properties": {
    "iso:country": "GB",
    "wof:name": "UB3 3EH",
    "wof:placetype": "postalcode"
  },
  "geometry": {"coordinates":[-0.410191,51.5152],"type":"Point"}
}
