{
  "type": "Feature",
  "properties": {
    "iso:country":"GB",
    "wof:name":"MK18 1BY",
    "wof:placetype":"postalcode"
},
  "geometry": {"coordinates":[-0.99013875074448,51.99710764179373],"type":"Point"}
}