{
  "type": "Feature",
  "properties": {
    "date:inception_lower": "2023-09-01",
    "date:inception_upper": "2023-09-01",
    "iso:country": "GB",
    "wof:name": "DE74 0AD",
    "wof:placetype": "postalcode"
  },
  "geometry": {"coordinates":[-1.355911,52.843441],"type":"Point"}
}
