{
  "type": "Feature",
  "properties": {
    "iso:country":"GB",
    "wof:name":"SK15 1LZ",
    "wof:placetype":"postalcode"
},
  "geometry": {"coordinates":[-2.06500645074378,53.48748877417211],"type":"Point"}
}