{
  "type": "Feature",
  "properties": {
    "iso:country": "GB",
    "wof:name": "SK15 1LZ",
    "wof:placetype": "postalcode"
  },
  "geometry": {"coordinates":[-2.065006,53.487489],"type":"Point"}
}
