{
  "type": "Feature",
  "properties": {
    "date:inception_lower": "1980-01-01",
    "date:inception_upper": "1980-01-01",
    "iso:country": "GB",
    "wof:name": "SK15 1LZ",
    "wof:placetype": "postalcode"
  },
  "geometry": {"coordinates":[-2.065006,53.487489],"type":"Point"}
}
