{
  "type": "Feature",
  "properties": {
    "iso:country":"GB",
    "wof:name":"AL7 2PR",
    "wof:placetype":"postalcode"
},
  "geometry": {"coordinates":[-0.16213010665552,51.80094680525673],"type":"Point"}
}