{
  "type": "Feature",
  "properties": {
    "iso:country":"GB",
    "wof:name":"IP11 3RF",
    "wof:placetype":"postalcode"
},
  "geometry": {"coordinates":[1.32806952510356,51.94586707378993],"type":"Point"}
}