{
  "type": "Feature",
  "properties": {
    "iso:country":"GB",
    "wof:name":"SA40 9RX",
    "wof:placetype":"postalcode"
},
  "geometry": {"coordinates":[-4.15547089829105,52.07252425069392],"type":"Point"}
}