{
  "type": "Feature",
  "properties": {
    "iso:country":"GB",
    "wof:name":"DD3 0JE",
    "wof:placetype":"postalcode"
},
  "geometry": {"coordinates":[-2.98805334822248,56.49170552798883],"type":"Point"}
}