{
  "type": "Feature",
  "properties": {
    "iso:country": "GB",
    "wof:name": "SL2 4FQ",
    "wof:placetype": "postalcode"
  },
  "geometry": {"coordinates":[-0.586797,51.543899],"type":"Point"}
}
