{
  "type": "Feature",
  "properties": {
    "iso:country":"GB",
    "wof:name":"KT15 2QX",
    "wof:placetype":"postalcode"
},
  "geometry": {"coordinates":[-0.47588146073462,51.37428159083123],"type":"Point"}
}