{
  "type": "Feature",
  "properties": {
    "iso:country":"GB",
    "wof:name":"BA2 7LT",
    "wof:placetype":"postalcode"
},
  "geometry": {"coordinates":[-2.32689520114533,51.30193614448412],"type":"Point"}
}