{
  "type": "Feature",
  "properties": {
    "iso:country":"GB",
    "wof:name":"SK8 6RZ",
    "wof:placetype":"postalcode"
},
  "geometry": {"coordinates":[-2.20885470986114,53.37065254074738],"type":"Point"}
}