{
  "type": "Feature",
  "properties": {
    "date:inception_lower": "1980-01-01",
    "date:inception_upper": "1980-01-01",
    "iso:country": "GB",
    "wof:name": "SK8 6RZ",
    "wof:placetype": "postalcode"
  },
  "geometry": {"coordinates":[-2.208855,53.370653],"type":"Point"}
}
