{
  "type": "Feature",
  "properties": {
    "iso:country": "GB",
    "wof:name": "SK8 6RZ",
    "wof:placetype": "postalcode"
  },
  "geometry": {"coordinates":[-2.208855,53.370653],"type":"Point"}
}
