{
  "type": "Feature",
  "properties": {
    "iso:country":"GB",
    "wof:name":"DN14 7PT",
    "wof:placetype":"postalcode"
},
  "geometry": {"coordinates":[-0.79077201426522,53.75878668118659],"type":"Point"}
}