{
  "type": "Feature",
  "properties": {
    "iso:country":"GB",
    "wof:name":"RG12 2RN",
    "wof:placetype":"postalcode"
},
  "geometry": {"coordinates":[-0.73173211179362,51.41770456507305],"type":"Point"}
}