{
  "type": "Feature",
  "properties": {
    "date:inception_lower":"1980-01-01",
    "date:inception_upper":"1980-01-31",
    "iso:country":"GB",
    "wof:name":"RG12 2RN",
    "wof:placetype":"postalcode"
},
  "geometry": {"coordinates":[-0.731732,51.417705],"type":"Point"}
}