{
  "type": "Feature",
  "properties": {
    "iso:country":"GB",
    "wof:name":"KT13 0XW",
    "wof:placetype":"postalcode"
},
  "geometry": {"coordinates":[-0.46266772892521,51.35011728285442],"type":"Point"}
}