{
  "type": "Feature",
  "properties": {
    "iso:country": "GB",
    "wof:name": "L35 9LY",
    "wof:placetype": "postalcode"
  },
  "geometry": {"coordinates":[-2.773981,53.416981],"type":"Point"}
}
