{
  "type": "Feature",
  "properties": {
    "iso:country":"GB",
    "wof:name":"L35 9LY",
    "wof:placetype":"postalcode"
},
  "geometry": {"coordinates":[-2.77398097261272,53.41698124628923],"type":"Point"}
}