{
  "type": "Feature",
  "properties": {
    "iso:country": "GB",
    "wof:name": "CV47 2QZ",
    "wof:placetype": "postalcode"
  },
  "geometry": {"coordinates":[-1.439116,52.208225],"type":"Point"}
}
