{
  "type": "Feature",
  "properties": {
    "iso:country": "GB",
    "wof:name": "SK16 4UQ",
    "wof:placetype": "postalcode"
  },
  "geometry": {"coordinates":[-2.087392,53.468221],"type":"Point"}
}
