{
  "type": "Feature",
  "properties": {
    "date:inception_lower":"1990-08-01",
    "date:inception_upper":"1990-08-31",
    "iso:country":"GB",
    "wof:name":"AB55 4AG",
    "wof:placetype":"postalcode"
},
  "geometry": {"coordinates":[-3.134433,57.445425],"type":"Point"}
}