{
  "type": "Feature",
  "properties": {
    "iso:country": "GB",
    "wof:name": "DG8 0QJ",
    "wof:placetype": "postalcode"
  },
  "geometry": {"coordinates":[-4.810711,54.880042],"type":"Point"}
}
