{
  "type": "Feature",
  "properties": {
    "iso:country":"GB",
    "wof:name":"GU6 8QJ",
    "wof:placetype":"postalcode"
},
  "geometry": {"coordinates":[-0.48871411172132,51.15044448305446],"type":"Point"}
}