{
  "type": "Feature",
  "properties": {
    "iso:country": "GB",
    "wof:name": "GU6 8QJ",
    "wof:placetype": "postalcode"
  },
  "geometry": {"coordinates":[-0.488714,51.150444],"type":"Point"}
}
