{
  "type": "Feature",
  "properties": {
    "date:inception_lower": "1980-01-01",
    "date:inception_upper": "1980-01-01",
    "iso:country": "GB",
    "wof:name": "GU6 8QJ",
    "wof:placetype": "postalcode"
  },
  "geometry": {"coordinates":[-0.488714,51.150444],"type":"Point"}
}
