{
  "type": "Feature",
  "properties": {
    "iso:country": "GB",
    "wof:name": "CF37 3NR",
    "wof:placetype": "postalcode"
  },
  "geometry": {"coordinates":[-3.3667,51.631582],"type":"Point"}
}
