{
  "type": "Feature",
  "properties": {
    "date:inception_lower": "1980-01-01",
    "date:inception_upper": "1980-01-01",
    "iso:country": "GB",
    "wof:name": "NG14 5EF",
    "wof:placetype": "postalcode"
  },
  "geometry": {"coordinates":[-1.03479,52.990601],"type":"Point"}
}
