{
  "type": "Feature",
  "properties": {
    "date:inception_lower": "2002-06-01",
    "date:inception_upper": "2002-06-01",
    "iso:country": "GB",
    "wof:name": "OX5 1FJ",
    "wof:placetype": "postalcode"
  },
  "geometry": {"coordinates":[-1.306899,51.830472],"type":"Point"}
}
