{
  "type": "Feature",
  "properties": {
    "iso:country":"GB",
    "wof:name":"OX5 1FJ",
    "wof:placetype":"postalcode"
},
  "geometry": {"coordinates":[-1.3085928748489,51.82900962717082],"type":"Point"}
}