{
  "type": "Feature",
  "properties": {
    "iso:country": "GB",
    "wof:name": "RG42 4NY",
    "wof:placetype": "postalcode"
  },
  "geometry": {"coordinates":[-0.792155,51.43364],"type":"Point"}
}
