{
  "type": "Feature",
  "properties": {
    "iso:country": "GB",
    "wof:name": "NE66 4UF",
    "wof:placetype": "postalcode"
  },
  "geometry": {"coordinates":[-2.06306,55.41525],"type":"Point"}
}
