{
  "type": "Feature",
  "properties": {
    "iso:country":"GB",
    "wof:name":"NE66 4UF",
    "wof:placetype":"postalcode"
},
  "geometry": {"coordinates":[-2.06306045241483,55.41525040221912],"type":"Point"}
}