{
  "type": "Feature",
  "properties": {
    "iso:country":"GB",
    "wof:name":"DY6 7AG",
    "wof:placetype":"postalcode"
},
  "geometry": {"coordinates":[-2.16776320916541,52.50223690607624],"type":"Point"}
}