{
  "type": "Feature",
  "properties": {
    "iso:country":"GB",
    "wof:name":"SO53 2FT",
    "wof:placetype":"postalcode"
},
  "geometry": {"coordinates":[-1.38677414366979,50.9873775440927],"type":"Point"}
}