{
  "type": "Feature",
  "properties": {
    "iso:country": "GB",
    "wof:name": "GU31 4BW",
    "wof:placetype": "postalcode"
  },
  "geometry": {"coordinates":[-0.929114,51.007649],"type":"Point"}
}
