{
  "type": "Feature",
  "properties": {
    "iso:country":"GB",
    "wof:name":"GU31 4BW",
    "wof:placetype":"postalcode"
},
  "geometry": {"coordinates":[-0.92911414188651,51.0076492006272],"type":"Point"}
}