{
  "type": "Feature",
  "properties": {
    "date:inception_lower": "1980-01-01",
    "date:inception_upper": "1980-01-01",
    "iso:country": "GB",
    "wof:name": "L24 7RD",
    "wof:placetype": "postalcode"
  },
  "geometry": {"coordinates":[-2.822081,53.342717],"type":"Point"}
}
