{
  "type": "Feature",
  "properties": {
    "date:inception_lower": "1987-04-01",
    "date:inception_upper": "1987-04-01",
    "iso:country": "GB",
    "wof:name": "BR7 6LH",
    "wof:placetype": "postalcode"
  },
  "geometry": {"coordinates":[0.077944,51.413413],"type":"Point"}
}
