{
  "type": "Feature",
  "properties": {
    "iso:country":"GB",
    "wof:name":"BR7 6LH",
    "wof:placetype":"postalcode"
},
  "geometry": {"coordinates":[0.07791853225063,51.41341261198748],"type":"Point"}
}