{
  "type": "Feature",
  "properties": {
    "iso:country": "GB",
    "wof:name": "BR7 6LH",
    "wof:placetype": "postalcode"
  },
  "geometry": {"coordinates":[0.077944,51.413413],"type":"Point"}
}
