{
  "type": "Feature",
  "properties": {
    "date:inception_lower":"2004-11-01",
    "date:inception_upper":"2004-11-30",
    "iso:country":"GB",
    "wof:name":"PA16 0FZ",
    "wof:placetype":"postalcode"
},
  "geometry": {"coordinates":[-4.86448,55.910544],"type":"Point"}
}