{
  "type": "Feature",
  "properties": {
    "iso:country":"GB",
    "wof:name":"PA16 0FZ",
    "wof:placetype":"postalcode"
},
  "geometry": {"coordinates":[-4.86448052702644,55.91054368066852],"type":"Point"}
}