{
  "type": "Feature",
  "properties": {
    "iso:country": "GB",
    "wof:name": "PA16 0FZ",
    "wof:placetype": "postalcode"
  },
  "geometry": {"coordinates":[-4.86448,55.910544],"type":"Point"}
}
