{
  "type": "Feature",
  "properties": {
    "iso:country":"GB",
    "wof:name":"W1T 5HH",
    "wof:placetype":"postalcode"
},
  "geometry": {"coordinates":[-0.13922061240269,51.52338973062385],"type":"Point"}
}