{
  "type": "Feature",
  "properties": {
    "iso:country": "GB",
    "wof:name": "EX1 3PS",
    "wof:placetype": "postalcode"
  },
  "geometry": {"coordinates":[-3.482778,50.730023],"type":"Point"}
}
