{
  "type": "Feature",
  "properties": {
    "iso:country":"GB",
    "wof:name":"CT15 7HX",
    "wof:placetype":"postalcode"
},
  "geometry": {"coordinates":[1.16362283856059,51.14220453464094],"type":"Point"}
}