{
  "type": "Feature",
  "properties": {
    "iso:country": "GB",
    "wof:name": "OX15 4PG",
    "wof:placetype": "postalcode"
  },
  "geometry": {"coordinates":[-1.37484,52.023521],"type":"Point"}
}
