{
  "type": "Feature",
  "properties": {
    "iso:country":"GB",
    "wof:name":"CT17 0QB",
    "wof:placetype":"postalcode"
},
  "geometry": {"coordinates":[1.27307306686732,51.14427230663837],"type":"Point"}
}