{
  "type": "Feature",
  "properties": {
    "iso:country": "GB",
    "wof:name": "CT17 0QB",
    "wof:placetype": "postalcode"
  },
  "geometry": {"coordinates":[1.273073,51.144272],"type":"Point"}
}
