{
  "type": "Feature",
  "properties": {
    "date:inception_lower": "2017-01-01",
    "date:inception_upper": "2017-01-01",
    "iso:country": "GB",
    "wof:name": "WS8 6FN",
    "wof:placetype": "postalcode"
  },
  "geometry": {"coordinates":[-1.928821,52.642547],"type":"Point"}
}
