{
  "type": "Feature",
  "properties": {
    "iso:country":"GB",
    "wof:name":"DD8 3TX",
    "wof:placetype":"postalcode"
},
  "geometry": {"coordinates":[-2.90864471060869,56.72071824564734],"type":"Point"}
}