{
  "type": "Feature",
  "properties": {
    "iso:country": "GB",
    "wof:name": "DE13 9BT",
    "wof:placetype": "postalcode"
  },
  "geometry": {"coordinates":[-1.657126,52.847847],"type":"Point"}
}
