{
  "type": "Feature",
  "properties": {
    "iso:country":"GB",
    "wof:name":"LE65 2QY",
    "wof:placetype":"postalcode"
},
  "geometry": {"coordinates":[-1.47942649069321,52.75048241860775],"type":"Point"}
}