{
  "type": "Feature",
  "properties": {
    "iso:country":"GB",
    "wof:name":"SY23 4DW",
    "wof:placetype":"postalcode"
},
  "geometry": {"coordinates":[-4.10534462352678,52.35100097680611],"type":"Point"}
}