{
  "type": "Feature",
  "properties": {
    "date:inception_lower":"1980-01-01",
    "date:inception_upper":"1980-01-31",
    "iso:country":"GB",
    "wof:name":"SY23 4DW",
    "wof:placetype":"postalcode"
},
  "geometry": {"coordinates":[-4.105345,52.351001],"type":"Point"}
}