{
  "type": "Feature",
  "properties": {
    "iso:country": "GB",
    "wof:name": "SY23 4DW",
    "wof:placetype": "postalcode"
  },
  "geometry": {"coordinates":[-4.105345,52.351001],"type":"Point"}
}
