{
  "type": "Feature",
  "properties": {
    "iso:country":"GB",
    "wof:name":"SE26 6TY",
    "wof:placetype":"postalcode"
},
  "geometry": {"coordinates":[-0.06524496974123,51.43312072067256],"type":"Point"}
}