{
  "type": "Feature",
  "properties": {
    "date:inception_lower":"1980-01-01",
    "date:inception_upper":"1980-01-31",
    "iso:country":"GB",
    "wof:name":"TR11 5PA",
    "wof:placetype":"postalcode"
},
  "geometry": {"coordinates":[-5.103487,50.158658],"type":"Point"}
}