{
  "type": "Feature",
  "properties": {
    "iso:country": "GB",
    "wof:name": "TR11 5PA",
    "wof:placetype": "postalcode"
  },
  "geometry": {"coordinates":[-5.103487,50.158658],"type":"Point"}
}
