{
  "type": "Feature",
  "properties": {
    "iso:country":"GB",
    "wof:name":"TR11 5PA",
    "wof:placetype":"postalcode"
},
  "geometry": {"coordinates":[-5.10348660833526,50.15865805116721],"type":"Point"}
}