{
  "type": "Feature",
  "properties": {
    "iso:country":"GB",
    "wof:name":"SY11 1BF",
    "wof:placetype":"postalcode"
},
  "geometry": {"coordinates":[-3.05970585770942,52.85994420313057],"type":"Point"}
}