{
  "type": "Feature",
  "properties": {
    "iso:country": "GB",
    "wof:name": "RG19 8XL",
    "wof:placetype": "postalcode"
  },
  "geometry": {"coordinates":[-1.31553,51.380035],"type":"Point"}
}
