{
  "type": "Feature",
  "properties": {
    "date:inception_lower": "1995-07-01",
    "date:inception_upper": "1995-07-01",
    "iso:country": "GB",
    "wof:name": "RG19 8XL",
    "wof:placetype": "postalcode"
  },
  "geometry": {"coordinates":[-1.31553,51.380035],"type":"Point"}
}
