{
  "type": "Feature",
  "properties": {
    "iso:country": "GB",
    "wof:name": "TA1 3QA",
    "wof:placetype": "postalcode"
  },
  "geometry": {"coordinates":[-3.10732,51.012008],"type":"Point"}
}
