{
  "type": "Feature",
  "properties": {
    "iso:country":"GB",
    "wof:name":"ST6 8DL",
    "wof:placetype":"postalcode"
},
  "geometry": {"coordinates":[-2.16266628717266,53.0580653893031],"type":"Point"}
}