{
  "type": "Feature",
  "properties": {
    "iso:country":"GB",
    "wof:name":"SE15 4JJ",
    "wof:placetype":"postalcode"
},
  "geometry": {"coordinates":[-0.06715796455099,51.46482450270155],"type":"Point"}
}