{
  "type": "Feature",
  "properties": {
    "date:inception_lower": "2002-06-01",
    "date:inception_upper": "2002-06-01",
    "iso:country": "GB",
    "wof:name": "SE15 4JJ",
    "wof:placetype": "postalcode"
  },
  "geometry": {"coordinates":[-0.067158,51.464824],"type":"Point"}
}
