{
  "type": "Feature",
  "properties": {
    "iso:country": "GB",
    "wof:name": "KW14 8AU",
    "wof:placetype": "postalcode"
  },
  "geometry": {"coordinates":[-3.515964,58.595612],"type":"Point"}
}
