{
  "type": "Feature",
  "properties": {
    "iso:country": "GB",
    "wof:name": "PO1 2JW",
    "wof:placetype": "postalcode"
  },
  "geometry": {"coordinates":[-1.108937,50.79151],"type":"Point"}
}
