{
  "type": "Feature",
  "properties": {
    "date:inception_lower": "1983-07-01",
    "date:inception_upper": "1983-07-01",
    "iso:country": "GB",
    "wof:name": "PO1 2JW",
    "wof:placetype": "postalcode"
  },
  "geometry": {"coordinates":[-1.108842,50.791319],"type":"Point"}
}
