{
  "type": "Feature",
  "properties": {
    "iso:country":"GB",
    "wof:name":"WA8 9PH",
    "wof:placetype":"postalcode"
},
  "geometry": {"coordinates":[-2.75148307110131,53.38006422978123],"type":"Point"}
}