{
  "type": "Feature",
  "properties": {
    "date:inception_lower":"2004-08-01",
    "date:inception_upper":"2004-08-31",
    "iso:country":"GB",
    "wof:name":"WA8 9PH",
    "wof:placetype":"postalcode"
},
  "geometry": {"coordinates":[-2.751483,53.380064],"type":"Point"}
}