{
  "type": "Feature",
  "properties": {
    "iso:country": "GB",
    "wof:name": "WA8 9PH",
    "wof:placetype": "postalcode"
  },
  "geometry": {"coordinates":[-2.751483,53.380064],"type":"Point"}
}
