{
  "type": "Feature",
  "properties": {
    "iso:country":"GB",
    "wof:name":"B49 5RB",
    "wof:placetype":"postalcode"
},
  "geometry": {"coordinates":[-1.86881605375219,52.21411349966799],"type":"Point"}
}