{
  "type": "Feature",
  "properties": {
    "iso:country": "GB",
    "wof:name": "B49 5RB",
    "wof:placetype": "postalcode"
  },
  "geometry": {"coordinates":[-1.868933,52.214204],"type":"Point"}
}
