{
  "type": "Feature",
  "properties": {
    "iso:country": "GB",
    "wof:name": "DE73 7HG",
    "wof:placetype": "postalcode"
  },
  "geometry": {"coordinates":[-1.476544,52.85376],"type":"Point"}
}
