{
  "type": "Feature",
  "properties": {
    "iso:country":"GB",
    "wof:name":"DE73 7HG",
    "wof:placetype":"postalcode"
},
  "geometry": {"coordinates":[-1.47698737822872,52.85393260940455],"type":"Point"}
}