{
  "type": "Feature",
  "properties": {
    "iso:country": "GB",
    "wof:name": "S43 4SS",
    "wof:placetype": "postalcode"
  },
  "geometry": {"coordinates":[-1.247995,53.275425],"type":"Point"}
}
