{
  "type": "Feature",
  "properties": {
    "iso:country":"GB",
    "wof:name":"CT14 9JT",
    "wof:placetype":"postalcode"
},
  "geometry": {"coordinates":[1.38251610678136,51.20761272296496],"type":"Point"}
}