{
  "type": "Feature",
  "properties": {
    "date:inception_lower": "1997-06-01",
    "date:inception_upper": "1997-06-01",
    "iso:country": "GB",
    "wof:name": "BD16 4UN",
    "wof:placetype": "postalcode"
  },
  "geometry": {"coordinates":[-1.829365,53.861823],"type":"Point"}
}
