{
  "type": "Feature",
  "properties": {
    "iso:country": "GB",
    "wof:name": "MK18 4NE",
    "wof:placetype": "postalcode"
  },
  "geometry": {"coordinates":[-1.038118,51.989472],"type":"Point"}
}
