{
  "type": "Feature",
  "properties": {
    "iso:country": "GB",
    "wof:name": "CV47 7RZ",
    "wof:placetype": "postalcode"
  },
  "geometry": {"coordinates":[-1.286748,52.21704],"type":"Point"}
}
