{
  "type": "Feature",
  "properties": {
    "date:inception_lower": "1999-12-01",
    "date:inception_upper": "1999-12-01",
    "iso:country": "GB",
    "wof:name": "CV47 7RZ",
    "wof:placetype": "postalcode"
  },
  "geometry": {"coordinates":[-1.286748,52.21704],"type":"Point"}
}
