{
  "type": "Feature",
  "properties": {
    "iso:country":"GB",
    "wof:name":"CV47 7RZ",
    "wof:placetype":"postalcode"
},
  "geometry": {"coordinates":[-1.28674835795357,52.21704020209961],"type":"Point"}
}