{
  "type": "Feature",
  "properties": {
    "iso:country":"GB",
    "wof:name":"SN7 8LL",
    "wof:placetype":"postalcode"
},
  "geometry": {"coordinates":[-1.50323183747071,51.63852509200808],"type":"Point"}
}