{
  "type": "Feature",
  "properties": {
    "iso:country": "GB",
    "wof:name": "SE6 3JY",
    "wof:placetype": "postalcode"
  },
  "geometry": {"coordinates":[-0.026164,51.436606],"type":"Point"}
}
