{
  "type": "Feature",
  "properties": {
    "iso:country":"GB",
    "wof:name":"IV54 8XJ",
    "wof:placetype":"postalcode"
},
  "geometry": {"coordinates":[-5.64779713657973,57.50845034232273],"type":"Point"}
}