{
  "type": "Feature",
  "properties": {
    "date:inception_lower": "1980-01-01",
    "date:inception_upper": "1980-01-01",
    "iso:country": "GB",
    "wof:name": "IV54 8XJ",
    "wof:placetype": "postalcode"
  },
  "geometry": {"coordinates":[-5.647071,57.510881],"type":"Point"}
}
