{
  "type": "Feature",
  "properties": {
    "iso:country":"GB",
    "wof:name":"CF14 2PA",
    "wof:placetype":"postalcode"
},
  "geometry": {"coordinates":[-3.21525803234696,51.50152627841224],"type":"Point"}
}