{
  "type": "Feature",
  "properties": {
    "iso:country": "GB",
    "wof:name": "CF14 2PA",
    "wof:placetype": "postalcode"
  },
  "geometry": {"coordinates":[-3.214992,51.501467],"type":"Point"}
}
