{
  "type": "Feature",
  "properties": {
    "iso:country":"GB",
    "wof:name":"ST10 1RZ",
    "wof:placetype":"postalcode"
},
  "geometry": {"coordinates":[-1.97825602625128,52.98581249307477],"type":"Point"}
}