{
  "type": "Feature",
  "properties": {
    "date:inception_lower": "1980-01-01",
    "date:inception_upper": "1980-01-01",
    "iso:country": "GB",
    "wof:name": "ST10 1RZ",
    "wof:placetype": "postalcode"
  },
  "geometry": {"coordinates":[-1.978256,52.985812],"type":"Point"}
}
