{
  "type": "Feature",
  "properties": {
    "iso:country":"GB",
    "wof:name":"WS3 2RJ",
    "wof:placetype":"postalcode"
},
  "geometry": {"coordinates":[-2.0243894562143,52.62224202725671],"type":"Point"}
}