{
  "type": "Feature",
  "properties": {
    "iso:country":"GB",
    "wof:name":"DE14 1NT",
    "wof:placetype":"postalcode"
},
  "geometry": {"coordinates":[-1.62810253054674,52.80731596976485],"type":"Point"}
}