{
  "type": "Feature",
  "properties": {
    "date:inception_lower":"2003-09-01",
    "date:inception_upper":"2003-09-30",
    "iso:country":"GB",
    "wof:name":"RG31 5PD",
    "wof:placetype":"postalcode"
},
  "geometry": {"coordinates":[-1.043163,51.459756],"type":"Point"}
}