{
  "type": "Feature",
  "properties": {
    "iso:country": "GB",
    "wof:name": "RG31 5PD",
    "wof:placetype": "postalcode"
  },
  "geometry": {"coordinates":[-1.043163,51.459756],"type":"Point"}
}
