{
  "type": "Feature",
  "properties": {
    "iso:country":"GB",
    "wof:name":"RG31 5PD",
    "wof:placetype":"postalcode"
},
  "geometry": {"coordinates":[-1.04316347545828,51.45975648984633],"type":"Point"}
}