{
  "type": "Feature",
  "properties": {
    "iso:country": "GB",
    "wof:name": "TR11 5JY",
    "wof:placetype": "postalcode"
  },
  "geometry": {"coordinates":[-5.116117,50.104191],"type":"Point"}
}
