{
  "type": "Feature",
  "properties": {
    "iso:country": "GB",
    "wof:name": "ZE1 0WU",
    "wof:placetype": "postalcode"
  },
  "geometry": {"coordinates":[-1.170969,60.160117],"type":"Point"}
}
