{
  "type": "Feature",
  "properties": {
    "date:inception_lower":"2011-02-01",
    "date:inception_upper":"2011-02-28",
    "iso:country":"GB",
    "wof:name":"ZE1 0WU",
    "wof:placetype":"postalcode"
},
  "geometry": {"coordinates":[-1.170969,60.160117],"type":"Point"}
}