{
  "type": "Feature",
  "properties": {
    "iso:country": "GB",
    "wof:name": "LA14 2UB",
    "wof:placetype": "postalcode"
  },
  "geometry": {"coordinates":[-3.223088,54.109026],"type":"Point"}
}
