{
  "type": "Feature",
  "properties": {
    "date:inception_lower":"1991-09-01",
    "date:inception_upper":"1991-09-30",
    "iso:country":"GB",
    "wof:name":"BA1 2LL",
    "wof:placetype":"postalcode"
},
  "geometry": {"coordinates":[-2.365238,51.383315],"type":"Point"}
}