{
  "type": "Feature",
  "properties": {
    "iso:country":"GB",
    "wof:name":"BA1 2LL",
    "wof:placetype":"postalcode"
},
  "geometry": {"coordinates":[-2.36523826130386,51.38331495584264],"type":"Point"}
}