{
  "type": "Feature",
  "properties": {
    "date:inception_lower": "2021-10-01",
    "date:inception_upper": "2021-10-01",
    "iso:country": "GB",
    "wof:name": "IG11 0BU",
    "wof:placetype": "postalcode"
  },
  "geometry": {"coordinates":[0.092115,51.528054],"type":"Point"}
}
