{
  "type": "Feature",
  "properties": {
    "iso:country":"GB",
    "wof:name":"AB31 4SQ",
    "wof:placetype":"postalcode"
},
  "geometry": {"coordinates":[-2.72908024187157,57.11604621718977],"type":"Point"}
}