{
  "type": "Feature",
  "properties": {
    "iso:country":"GB",
    "wof:name":"CV6 1FH",
    "wof:placetype":"postalcode"
},
  "geometry": {"coordinates":[-1.54129413950412,52.41813931562097],"type":"Point"}
}