{
  "type": "Feature",
  "properties": {
    "date:inception_lower": "2022-10-01",
    "date:inception_upper": "2022-10-01",
    "iso:country": "GB",
    "wof:name": "DN9 1NU",
    "wof:placetype": "postalcode"
  },
  "geometry": {"coordinates":[-0.821511,53.545397],"type":"Point"}
}
