{
  "type": "Feature",
  "properties": {
    "iso:country": "GB",
    "wof:name": "TF10 9HT",
    "wof:placetype": "postalcode"
  },
  "geometry": {"coordinates":[-2.436943,52.742967],"type":"Point"}
}
