{
  "type": "Feature",
  "properties": {
    "iso:country": "GB",
    "wof:name": "CT20 1LE",
    "wof:placetype": "postalcode"
  },
  "geometry": {"coordinates":[1.183473,51.082762],"type":"Point"}
}
