{
  "type": "Feature",
  "properties": {
    "date:inception_lower": "1980-01-01",
    "date:inception_upper": "1980-01-01",
    "iso:country": "GB",
    "wof:name": "NR18 0QP",
    "wof:placetype": "postalcode"
  },
  "geometry": {"coordinates":[1.123426,52.571411],"type":"Point"}
}
