{
  "type": "Feature",
  "properties": {
    "iso:country":"GB",
    "wof:name":"NR18 0QP",
    "wof:placetype":"postalcode"
},
  "geometry": {"coordinates":[1.12342558585328,52.5714105427951],"type":"Point"}
}