{
  "type": "Feature",
  "properties": {
    "iso:country": "GB",
    "wof:name": "GU24 9BP",
    "wof:placetype": "postalcode"
  },
  "geometry": {"coordinates":[-0.634418,51.334907],"type":"Point"}
}
