{
  "type": "Feature",
  "properties": {
    "iso:country": "GB",
    "wof:name": "SA18 3NQ",
    "wof:placetype": "postalcode"
  },
  "geometry": {"coordinates":[-4.039399,51.838017],"type":"Point"}
}
