{
  "type": "Feature",
  "properties": {
    "iso:country":"GB",
    "wof:name":"B97 4JB",
    "wof:placetype":"postalcode"
},
  "geometry": {"coordinates":[-1.94271772218634,52.30212443017724],"type":"Point"}
}