{
  "type": "Feature",
  "properties": {
    "iso:country":"GB",
    "wof:name":"CA13 9JH",
    "wof:placetype":"postalcode"
},
  "geometry": {"coordinates":[-3.35643523695302,54.66526715294381],"type":"Point"}
}