{
  "type": "Feature",
  "properties": {
    "date:inception_lower":"1985-04-01",
    "date:inception_upper":"1985-04-30",
    "iso:country":"GB",
    "wof:name":"CA13 9JH",
    "wof:placetype":"postalcode"
},
  "geometry": {"coordinates":[-3.356435,54.665267],"type":"Point"}
}