{
  "type": "Feature",
  "properties": {
    "iso:country":"GB",
    "wof:name":"EN5 1RN",
    "wof:placetype":"postalcode"
},
  "geometry": {"coordinates":[-0.17965364728156,51.64730944969951],"type":"Point"}
}