{
  "type": "Feature",
  "properties": {
    "date:inception_lower": "2008-06-01",
    "date:inception_upper": "2008-06-01",
    "iso:country": "GB",
    "wof:name": "B36 0TW",
    "wof:placetype": "postalcode"
  },
  "geometry": {"coordinates":[-1.749729,52.503114],"type":"Point"}
}
