{
  "type": "Feature",
  "properties": {
    "iso:country":"GB",
    "wof:name":"LS17 5LQ",
    "wof:placetype":"postalcode"
},
  "geometry": {"coordinates":[-1.56241761739103,53.84518422715749],"type":"Point"}
}