{
  "type": "Feature",
  "properties": {
    "date:inception_lower": "1980-01-01",
    "date:inception_upper": "1980-01-01",
    "iso:country": "GB",
    "wof:name": "LS17 5LQ",
    "wof:placetype": "postalcode"
  },
  "geometry": {"coordinates":[-1.562418,53.845184],"type":"Point"}
}
