{
  "type": "Feature",
  "properties": {
    "iso:country":"GB",
    "wof:name":"NW1 8AH",
    "wof:placetype":"postalcode"
},
  "geometry": {"coordinates":[-0.1477639075827,51.54233719665525],"type":"Point"}
}