{
  "type": "Feature",
  "properties": {
    "iso:country":"GB",
    "wof:name":"SY5 8NT",
    "wof:placetype":"postalcode"
},
  "geometry": {"coordinates":[-2.79178082574604,52.69533699649405],"type":"Point"}
}