{
  "type": "Feature",
  "properties": {
    "iso:country":"GB",
    "wof:name":"PO19 3BH",
    "wof:placetype":"postalcode"
},
  "geometry": {"coordinates":[-0.78043206719761,50.84062617894424],"type":"Point"}
}