{
  "type": "Feature",
  "properties": {
    "iso:country": "GB",
    "wof:name": "BL7 0FR",
    "wof:placetype": "postalcode"
  },
  "geometry": {"coordinates":[-2.397508,53.649561],"type":"Point"}
}
