{
  "type": "Feature",
  "properties": {
    "iso:country":"GB",
    "wof:name":"W1U 4QW",
    "wof:placetype":"postalcode"
},
  "geometry": {"coordinates":[-0.15231370282502,51.52044034277429],"type":"Point"}
}