{
  "type": "Feature",
  "properties": {
    "iso:country":"GB",
    "wof:name":"CW3 0AQ",
    "wof:placetype":"postalcode"
},
  "geometry": {"coordinates":[-2.50869140687487,52.98874334925658],"type":"Point"}
}