{
  "type": "Feature",
  "properties": {
    "iso:country": "GB",
    "wof:name": "NR21 8LP",
    "wof:placetype": "postalcode"
  },
  "geometry": {"coordinates":[0.872646,52.829026],"type":"Point"}
}
