{
  "type": "Feature",
  "properties": {
    "iso:country":"GB",
    "wof:name":"NR21 8LP",
    "wof:placetype":"postalcode"
},
  "geometry": {"coordinates":[0.87265839213895,52.82900899609627],"type":"Point"}
}