{
  "type": "Feature",
  "properties": {
    "iso:country": "GB",
    "wof:name": "IP24 1EA",
    "wof:placetype": "postalcode"
  },
  "geometry": {"coordinates":[0.739647,52.418665],"type":"Point"}
}
