{
  "type": "Feature",
  "properties": {
    "date:inception_lower": "1980-01-01",
    "date:inception_upper": "1980-01-01",
    "iso:country": "GB",
    "wof:name": "BS2 9RQ",
    "wof:placetype": "postalcode"
  },
  "geometry": {"coordinates":[-2.576803,51.467912],"type":"Point"}
}
