{
  "type": "Feature",
  "properties": {
    "iso:country": "GB",
    "wof:name": "SG18 9BU",
    "wof:placetype": "postalcode"
  },
  "geometry": {"coordinates":[-0.29986,52.094782],"type":"Point"}
}
