{
  "type": "Feature",
  "properties": {
    "iso:country":"GB",
    "wof:name":"SG18 9BU",
    "wof:placetype":"postalcode"
},
  "geometry": {"coordinates":[-0.29986005925598,52.09478233625762],"type":"Point"}
}