{
  "type": "Feature",
  "properties": {
    "iso:country":"GB",
    "wof:name":"CO7 9QT",
    "wof:placetype":"postalcode"
},
  "geometry": {"coordinates":[0.95667958301842,51.86545499314814],"type":"Point"}
}