{
  "type": "Feature",
  "properties": {
    "iso:country":"GB",
    "wof:name":"OX7 7BY",
    "wof:placetype":"postalcode"
},
  "geometry": {"coordinates":[-1.36211153951215,51.92850077409462],"type":"Point"}
}