{
  "type": "Feature",
  "properties": {
    "iso:country":"GB",
    "wof:name":"SA4 6RB",
    "wof:placetype":"postalcode"
},
  "geometry": {"coordinates":[-4.04481182421469,51.66353305318545],"type":"Point"}
}