{
  "type": "Feature",
  "properties": {
    "date:inception_lower": "1980-01-01",
    "date:inception_upper": "1980-01-01",
    "iso:country": "GB",
    "wof:name": "L13 7EA",
    "wof:placetype": "postalcode"
  },
  "geometry": {"coordinates":[-2.928001,53.422814],"type":"Point"}
}
