{
  "type": "Feature",
  "properties": {
    "iso:country":"GB",
    "wof:name":"L13 7EA",
    "wof:placetype":"postalcode"
},
  "geometry": {"coordinates":[-2.9280007683537,53.42281383771208],"type":"Point"}
}