{
  "type": "Feature",
  "properties": {
    "date:inception_lower":"1980-01-01",
    "date:inception_upper":"1980-01-31",
    "iso:country":"GB",
    "wof:name":"RH17 6PE",
    "wof:placetype":"postalcode"
},
  "geometry": {"coordinates":[-0.131968,51.060495],"type":"Point"}
}