{
  "type": "Feature",
  "properties": {
    "iso:country":"GB",
    "wof:name":"ML2 9RF",
    "wof:placetype":"postalcode"
},
  "geometry": {"coordinates":[-3.86636488442962,55.77731749167752],"type":"Point"}
}