{
  "type": "Feature",
  "properties": {
    "iso:country":"GB",
    "wof:name":"EN2 7AN",
    "wof:placetype":"postalcode"
},
  "geometry": {"coordinates":[-0.09679791165255,51.65357625907513],"type":"Point"}
}