{
  "type": "Feature",
  "properties": {
    "iso:country":"GB",
    "wof:name":"BH2 6NB",
    "wof:placetype":"postalcode"
},
  "geometry": {"coordinates":[-1.87398665077855,50.7305555411989],"type":"Point"}
}