{
  "type": "Feature",
  "properties": {
    "iso:country":"GB",
    "wof:name":"SO50 9FX",
    "wof:placetype":"postalcode"
},
  "geometry": {"coordinates":[-1.3674749239793,50.96598971293004],"type":"Point"}
}