{
  "type": "Feature",
  "properties": {
    "iso:country": "GB",
    "wof:name": "SO50 9FX",
    "wof:placetype": "postalcode"
  },
  "geometry": {"coordinates":[-1.367464,50.965982],"type":"Point"}
}
