{
  "type": "Feature",
  "properties": {
    "iso:country":"GB",
    "wof:name":"G72 0NH",
    "wof:placetype":"postalcode"
},
  "geometry": {"coordinates":[-4.08922753647904,55.79001515573464],"type":"Point"}
}