{
  "type": "Feature",
  "properties": {
    "iso:country": "GB",
    "wof:name": "G72 0NH",
    "wof:placetype": "postalcode"
  },
  "geometry": {"coordinates":[-4.089227,55.790015],"type":"Point"}
}
