{
  "type": "Feature",
  "properties": {
    "iso:country":"GB",
    "wof:name":"G51 4AZ",
    "wof:placetype":"postalcode"
},
  "geometry": {"coordinates":[-4.32813157239983,55.85813499794619],"type":"Point"}
}