{
  "type": "Feature",
  "properties": {
    "iso:country": "GB",
    "wof:name": "G51 4AZ",
    "wof:placetype": "postalcode"
  },
  "geometry": {"coordinates":[-4.328132,55.858135],"type":"Point"}
}
