{
  "type": "Feature",
  "properties": {
    "date:inception_lower": "2016-11-01",
    "date:inception_upper": "2016-11-01",
    "iso:country": "GB",
    "wof:name": "CM5 5BE",
    "wof:placetype": "postalcode"
  },
  "geometry": {"coordinates":[0.245192,51.703816],"type":"Point"}
}
