{
  "type": "Feature",
  "properties": {
    "date:inception_lower":"1996-12-01",
    "date:inception_upper":"1996-12-31",
    "iso:country":"GB",
    "wof:name":"BH1 2JG",
    "wof:placetype":"postalcode"
},
  "geometry": {"coordinates":[-1.874682,50.72157],"type":"Point"}
}