{
  "type": "Feature",
  "properties": {
    "iso:country":"GB",
    "wof:name":"BH1 2JG",
    "wof:placetype":"postalcode"
},
  "geometry": {"coordinates":[-1.87469064438454,50.72158161750436],"type":"Point"}
}