{
  "type": "Feature",
  "properties": {
    "iso:country": "GB",
    "wof:name": "DE72 2GH",
    "wof:placetype": "postalcode"
  },
  "geometry": {"coordinates":[-1.343966,52.869076],"type":"Point"}
}
