{
  "type": "Feature",
  "properties": {
    "date:inception_lower": "2002-06-01",
    "date:inception_upper": "2002-06-01",
    "iso:country": "GB",
    "wof:name": "NN14 2TZ",
    "wof:placetype": "postalcode"
  },
  "geometry": {"coordinates":[-0.825719,52.446761],"type":"Point"}
}
