{
  "type": "Feature",
  "properties": {
    "iso:country":"GB",
    "wof:name":"NN14 2TZ",
    "wof:placetype":"postalcode"
},
  "geometry": {"coordinates":[-0.82571884876198,52.44676100208019],"type":"Point"}
}