{
  "type": "Feature",
  "properties": {
    "iso:country":"GB",
    "wof:name":"G40 3HL",
    "wof:placetype":"postalcode"
},
  "geometry": {"coordinates":[-4.20306736632984,55.8461395989224],"type":"Point"}
}