{
  "type": "Feature",
  "properties": {
    "iso:country":"GB",
    "wof:name":"SY11 2QD",
    "wof:placetype":"postalcode"
},
  "geometry": {"coordinates":[-3.04072000262662,52.85544647214223],"type":"Point"}
}