{
  "type": "Feature",
  "properties": {
    "iso:country":"GB",
    "wof:name":"WF13 3LE",
    "wof:placetype":"postalcode"
},
  "geometry": {"coordinates":[-1.66552322033893,53.67758285602969],"type":"Point"}
}