{
  "type": "Feature",
  "properties": {
    "iso:country":"GB",
    "wof:name":"HR2 9RB",
    "wof:placetype":"postalcode"
},
  "geometry": {"coordinates":[-2.80272637068666,52.03414837923619],"type":"Point"}
}