{
  "type": "Feature",
  "properties": {
    "iso:country":"GB",
    "wof:name":"M40 5PX",
    "wof:placetype":"postalcode"
},
  "geometry": {"coordinates":[-2.18083968671234,53.5228376633335],"type":"Point"}
}