{
  "type": "Feature",
  "properties": {
    "iso:country":"GB",
    "wof:name":"KA13 7LG",
    "wof:placetype":"postalcode"
},
  "geometry": {"coordinates":[-4.68292919763105,55.65412733111986],"type":"Point"}
}