{
  "type": "Feature",
  "properties": {
    "iso:country":"GB",
    "wof:name":"B37 7BN",
    "wof:placetype":"postalcode"
},
  "geometry": {"coordinates":[-1.75002396708041,52.46791286009714],"type":"Point"}
}