{
  "type": "Feature",
  "properties": {
    "iso:country": "GB",
    "wof:name": "B37 7BN",
    "wof:placetype": "postalcode"
  },
  "geometry": {"coordinates":[-1.750024,52.467913],"type":"Point"}
}
