{
  "type": "Feature",
  "properties": {
    "iso:country":"GB",
    "wof:name":"NG5 1BP",
    "wof:placetype":"postalcode"
},
  "geometry": {"coordinates":[-1.15726611027498,52.9743795781275],"type":"Point"}
}