{
  "type": "Feature",
  "properties": {
    "iso:country":"GB",
    "wof:name":"BN2 5RY",
    "wof:placetype":"postalcode"
},
  "geometry": {"coordinates":[-0.10503167889855,50.81767268051098],"type":"Point"}
}