{
  "type": "Feature",
  "properties": {
    "iso:country":"GB",
    "wof:name":"WN1 2HA",
    "wof:placetype":"postalcode"
},
  "geometry": {"coordinates":[-2.6362157534427,53.559706654145],"type":"Point"}
}