{
  "type": "Feature",
  "properties": {
    "iso:country": "GB",
    "wof:name": "DN11 0XB",
    "wof:placetype": "postalcode"
  },
  "geometry": {"coordinates":[-1.070582,53.469063],"type":"Point"}
}
