{
  "type": "Feature",
  "properties": {
    "iso:country":"GB",
    "wof:name":"DN11 0XB",
    "wof:placetype":"postalcode"
},
  "geometry": {"coordinates":[-1.07058156261548,53.46906342281263],"type":"Point"}
}