{
  "type": "Feature",
  "properties": {
    "iso:country": "GB",
    "wof:name": "PR9 8HD",
    "wof:placetype": "postalcode"
  },
  "geometry": {"coordinates":[-2.923322,53.68558],"type":"Point"}
}
