{
  "type": "Feature",
  "properties": {
    "iso:country":"GB",
    "wof:name":"TN22 5AT",
    "wof:placetype":"postalcode"
},
  "geometry": {"coordinates":[0.10256609878696,50.96692642606338],"type":"Point"}
}