{
  "type": "Feature",
  "properties": {
    "date:inception_lower": "1980-01-01",
    "date:inception_upper": "1980-01-01",
    "iso:country": "GB",
    "wof:name": "TN22 5AT",
    "wof:placetype": "postalcode"
  },
  "geometry": {"coordinates":[0.10255,50.966923],"type":"Point"}
}
