{
  "type": "Feature",
  "properties": {
    "iso:country":"GB",
    "wof:name":"KA4 8AZ",
    "wof:placetype":"postalcode"
},
  "geometry": {"coordinates":[-4.38522737196967,55.60174808934566],"type":"Point"}
}