{
  "type": "Feature",
  "properties": {
    "iso:country": "GB",
    "wof:name": "KA4 8AZ",
    "wof:placetype": "postalcode"
  },
  "geometry": {"coordinates":[-4.385227,55.601748],"type":"Point"}
}
