{
  "type": "Feature",
  "properties": {
    "iso:country":"GB",
    "wof:name":"CR8 3BL",
    "wof:placetype":"postalcode"
},
  "geometry": {"coordinates":[-0.13087176079708,51.33521202757125],"type":"Point"}
}