{
  "type": "Feature",
  "properties": {
    "date:inception_lower": "1981-09-01",
    "date:inception_upper": "1981-09-01",
    "iso:country": "GB",
    "wof:name": "MK13 9EB",
    "wof:placetype": "postalcode"
  },
  "geometry": {"coordinates":[-0.782822,52.046559],"type":"Point"}
}
