{
  "type": "Feature",
  "properties": {
    "iso:country":"GB",
    "wof:name":"MK13 9EB",
    "wof:placetype":"postalcode"
},
  "geometry": {"coordinates":[-0.78282202429237,52.04655950114353],"type":"Point"}
}