{
  "type": "Feature",
  "properties": {
    "iso:country":"GB",
    "wof:name":"LL12 8HS",
    "wof:placetype":"postalcode"
},
  "geometry": {"coordinates":[-2.97360968967064,53.08942984576944],"type":"Point"}
}