{
  "type": "Feature",
  "properties": {
    "iso:country":"GB",
    "wof:name":"DH6 3AQ",
    "wof:placetype":"postalcode"
},
  "geometry": {"coordinates":[-1.42635241065262,54.75115586129562],"type":"Point"}
}