{
  "type": "Feature",
  "properties": {
    "iso:country":"GB",
    "wof:name":"CO9 2GZ",
    "wof:placetype":"postalcode"
},
  "geometry": {"coordinates":[0.64999741577407,51.9398825214452],"type":"Point"}
}