{
  "type": "Feature",
  "properties": {
    "iso:country":"GB",
    "wof:name":"M14 6ND",
    "wof:placetype":"postalcode"
},
  "geometry": {"coordinates":[-2.21825397041485,53.44224761072502],"type":"Point"}
}