{
  "type": "Feature",
  "properties": {
    "date:inception_lower": "2018-04-01",
    "date:inception_upper": "2018-04-01",
    "iso:country": "GB",
    "wof:name": "L25 4AH",
    "wof:placetype": "postalcode"
  },
  "geometry": {"coordinates":[-2.871549,53.387992],"type":"Point"}
}
