{
  "type": "Feature",
  "properties": {
    "iso:country": "GB",
    "wof:name": "PH1 0AE",
    "wof:placetype": "postalcode"
  },
  "geometry": {"coordinates":[-3.490784,56.423845],"type":"Point"}
}
