{
  "type": "Feature",
  "properties": {
    "iso:country":"GB",
    "wof:name":"CM4 0FL",
    "wof:placetype":"postalcode"
},
  "geometry": {"coordinates":[0.30549988182518,51.70116822266397],"type":"Point"}
}