{
  "type": "Feature",
  "properties": {
    "iso:country":"GB",
    "wof:name":"SM4 5SD",
    "wof:placetype":"postalcode"
},
  "geometry": {"coordinates":[-0.1901505461692,51.39672656425613],"type":"Point"}
}