{
  "type": "Feature",
  "properties": {
    "iso:country":"GB",
    "wof:name":"DE24 3HL",
    "wof:placetype":"postalcode"
},
  "geometry": {"coordinates":[-1.48576596809104,52.87136555819954],"type":"Point"}
}