{
  "type": "Feature",
  "properties": {
    "date:inception_lower": "2019-06-01",
    "date:inception_upper": "2019-06-01",
    "iso:country": "GB",
    "wof:name": "LE8 8EL",
    "wof:placetype": "postalcode"
  },
  "geometry": {"coordinates":[-1.053705,52.53975],"type":"Point"}
}
