{
  "type": "Feature",
  "properties": {
    "iso:country": "GB",
    "wof:name": "LE8 8EL",
    "wof:placetype": "postalcode"
  },
  "geometry": {"coordinates":[-1.054214,52.538693],"type":"Point"}
}
