{
  "type": "Feature",
  "properties": {
    "date:inception_lower": "1980-01-01",
    "date:inception_upper": "1980-01-01",
    "iso:country": "GB",
    "wof:name": "E1 1EE",
    "wof:placetype": "postalcode"
  },
  "geometry": {"coordinates":[-0.067333,51.515852],"type":"Point"}
}
