{
  "type": "Feature",
  "properties": {
    "iso:country":"GB",
    "wof:name":"E1 1EE",
    "wof:placetype":"postalcode"
},
  "geometry": {"coordinates":[-0.0673334835083,51.51585154147502],"type":"Point"}
}