{
  "type": "Feature",
  "properties": {
    "iso:country":"GB",
    "wof:name":"HD2 1HW",
    "wof:placetype":"postalcode"
},
  "geometry": {"coordinates":[-1.765285899691,53.6694157498186],"type":"Point"}
}