{
  "type": "Feature",
  "properties": {
    "iso:country":"GB",
    "wof:name":"S21 3UA",
    "wof:placetype":"postalcode"
},
  "geometry": {"coordinates":[-1.31481742077353,53.29333753843763],"type":"Point"}
}