{
  "type": "Feature",
  "properties": {
    "iso:country": "GB",
    "wof:name": "S21 3UA",
    "wof:placetype": "postalcode"
  },
  "geometry": {"coordinates":[-1.314817,53.293338],"type":"Point"}
}
