{
  "type": "Feature",
  "properties": {
    "date:inception_lower": "2019-10-01",
    "date:inception_upper": "2019-10-01",
    "iso:country": "GB",
    "wof:name": "PA7 5GU",
    "wof:placetype": "postalcode"
  },
  "geometry": {"coordinates":[-4.508701,55.900642],"type":"Point"}
}
