{
  "type": "Feature",
  "properties": {
    "iso:country": "GB",
    "wof:name": "PA7 5GU",
    "wof:placetype": "postalcode"
  },
  "geometry": {"coordinates":[-4.508701,55.900642],"type":"Point"}
}
