{
  "type": "Feature",
  "properties": {
    "date:inception_lower": "1980-01-01",
    "date:inception_upper": "1980-01-01",
    "iso:country": "GB",
    "wof:name": "TA1 2DN",
    "wof:placetype": "postalcode"
  },
  "geometry": {"coordinates":[-3.078378,51.023501],"type":"Point"}
}
