{
  "type": "Feature",
  "properties": {
    "iso:country":"GB",
    "wof:name":"TA1 2DN",
    "wof:placetype":"postalcode"
},
  "geometry": {"coordinates":[-3.07837848775949,51.02350118968984],"type":"Point"}
}