{
  "type": "Feature",
  "properties": {
    "iso:country": "GB",
    "wof:name": "EX32 9DF",
    "wof:placetype": "postalcode"
  },
  "geometry": {"coordinates":[-4.036388,51.069634],"type":"Point"}
}
