{
  "type": "Feature",
  "properties": {
    "iso:country": "GB",
    "wof:name": "SA6 5SZ",
    "wof:placetype": "postalcode"
  },
  "geometry": {"coordinates":[-3.916101,51.710303],"type":"Point"}
}
