{
  "type": "Feature",
  "properties": {
    "iso:country":"GB",
    "wof:name":"SA6 5SZ",
    "wof:placetype":"postalcode"
},
  "geometry": {"coordinates":[-3.91612561040214,51.71028794975547],"type":"Point"}
}