{
  "type": "Feature",
  "properties": {
    "iso:country":"GB",
    "wof:name":"ST15 0RG",
    "wof:placetype":"postalcode"
},
  "geometry": {"coordinates":[-2.20499946846156,52.92691949965396],"type":"Point"}
}