{
  "type": "Feature",
  "properties": {
    "iso:country": "GB",
    "wof:name": "ST15 0RG",
    "wof:placetype": "postalcode"
  },
  "geometry": {"coordinates":[-2.204999,52.926919],"type":"Point"}
}
