{
  "type": "Feature",
  "properties": {
    "iso:country":"GB",
    "wof:name":"NG17 1EQ",
    "wof:placetype":"postalcode"
},
  "geometry": {"coordinates":[-1.26388238665295,53.12298818265079],"type":"Point"}
}