{
  "type": "Feature",
  "properties": {
    "iso:country": "GB",
    "wof:name": "NG17 1EQ",
    "wof:placetype": "postalcode"
  },
  "geometry": {"coordinates":[-1.26391,53.122989],"type":"Point"}
}
