{
  "type": "Feature",
  "properties": {
    "iso:country":"GB",
    "wof:name":"CV6 4HY",
    "wof:placetype":"postalcode"
},
  "geometry": {"coordinates":[-1.51346804370159,52.44816301498758],"type":"Point"}
}