{
  "type": "Feature",
  "properties": {
    "iso:country":"GB",
    "wof:name":"IP28 7EJ",
    "wof:placetype":"postalcode"
},
  "geometry": {"coordinates":[0.50976222757272,52.34424277126647],"type":"Point"}
}