{
  "type": "Feature",
  "properties": {
    "date:inception_lower": "2009-08-01",
    "date:inception_upper": "2009-08-01",
    "iso:country": "GB",
    "wof:name": "BB1 9JR",
    "wof:placetype": "postalcode"
  },
  "geometry": {"coordinates":[-2.476666,53.770825],"type":"Point"}
}
