{
  "type": "Feature",
  "properties": {
    "iso:country":"GB",
    "wof:name":"BB1 9JR",
    "wof:placetype":"postalcode"
},
  "geometry": {"coordinates":[-2.47692603840886,53.77083608111116],"type":"Point"}
}