{
  "type": "Feature",
  "properties": {
    "iso:country": "GB",
    "wof:name": "BB1 9JR",
    "wof:placetype": "postalcode"
  },
  "geometry": {"coordinates":[-2.476666,53.770825],"type":"Point"}
}
