{
  "type": "Feature",
  "properties": {
    "iso:country": "GB",
    "wof:name": "TA6 3QN",
    "wof:placetype": "postalcode"
  },
  "geometry": {"coordinates":[-3.009979,51.134836],"type":"Point"}
}
