{
  "type": "Feature",
  "properties": {
    "iso:country":"GB",
    "wof:name":"NG6 9AD",
    "wof:placetype":"postalcode"
},
  "geometry": {"coordinates":[-1.19429180591439,53.00057968693723],"type":"Point"}
}