{
  "type": "Feature",
  "properties": {
    "iso:country":"GB",
    "wof:name":"LE3 3SW",
    "wof:placetype":"postalcode"
},
  "geometry": {"coordinates":[-1.19637034423212,52.61711143718197],"type":"Point"}
}