{
  "type": "Feature",
  "properties": {
    "iso:country":"GB",
    "wof:name":"PE9 1UL",
    "wof:placetype":"postalcode"
},
  "geometry": {"coordinates":[-0.46672299950948,52.66261807305181],"type":"Point"}
}