{
  "type": "Feature",
  "properties": {
    "iso:country":"GB",
    "wof:name":"PA4 8UH",
    "wof:placetype":"postalcode"
},
  "geometry": {"coordinates":[-4.38218755582295,55.87555180518435],"type":"Point"}
}