{
  "type": "Feature",
  "properties": {
    "iso:country":"GB",
    "wof:name":"HU19 2RG",
    "wof:placetype":"postalcode"
},
  "geometry": {"coordinates":[0.06730539614845,53.68395859906146],"type":"Point"}
}