{
  "type": "Feature",
  "properties": {
    "date:inception_lower":"2010-07-01",
    "date:inception_upper":"2010-07-31",
    "iso:country":"GB",
    "wof:name":"HU19 2RG",
    "wof:placetype":"postalcode"
},
  "geometry": {"coordinates":[0.067305,53.683959],"type":"Point"}
}