{
  "type": "Feature",
  "properties": {
    "date:inception_lower": "2010-07-01",
    "date:inception_upper": "2010-07-01",
    "iso:country": "GB",
    "wof:name": "HU19 2RG",
    "wof:placetype": "postalcode"
  },
  "geometry": {"coordinates":[0.067341,53.683955],"type":"Point"}
}
