{
  "type": "Feature",
  "properties": {
    "iso:country": "GB",
    "wof:name": "TS10 2JA",
    "wof:placetype": "postalcode"
  },
  "geometry": {"coordinates":[-1.062678,54.602645],"type":"Point"}
}
