{
  "type": "Feature",
  "properties": {
    "iso:country": "GB",
    "wof:name": "NE11 9NG",
    "wof:placetype": "postalcode"
  },
  "geometry": {"coordinates":[-1.632799,54.945165],"type":"Point"}
}
