{
  "type": "Feature",
  "properties": {
    "iso:country": "GB",
    "wof:name": "SW3 1PX",
    "wof:placetype": "postalcode"
  },
  "geometry": {"coordinates":[-0.164077,51.498189],"type":"Point"}
}
