{
  "type": "Feature",
  "properties": {
    "iso:country":"GB",
    "wof:name":"BN43 5HP",
    "wof:placetype":"postalcode"
},
  "geometry": {"coordinates":[-0.25147091253756,50.82867398838327],"type":"Point"}
}