{
  "type": "Feature",
  "properties": {
    "iso:country": "GB",
    "wof:name": "BN43 5HP",
    "wof:placetype": "postalcode"
  },
  "geometry": {"coordinates":[-0.251471,50.828674],"type":"Point"}
}
