{
  "type": "Feature",
  "properties": {
    "date:inception_lower": "1990-07-01",
    "date:inception_upper": "1990-07-01",
    "iso:country": "GB",
    "wof:name": "BN43 5HP",
    "wof:placetype": "postalcode"
  },
  "geometry": {"coordinates":[-0.251471,50.828674],"type":"Point"}
}
