{
  "type": "Feature",
  "properties": {
    "iso:country":"GB",
    "wof:name":"LN1 1ND",
    "wof:placetype":"postalcode"
},
  "geometry": {"coordinates":[-0.55372791133027,53.23603456118613],"type":"Point"}
}