{
  "type": "Feature",
  "properties": {
    "iso:country":"GB",
    "wof:name":"SL5 7JF",
    "wof:placetype":"postalcode"
},
  "geometry": {"coordinates":[-0.67575233234753,51.41103385020369],"type":"Point"}
}