{
  "type": "Feature",
  "properties": {
    "iso:country": "GB",
    "wof:name": "EX31 3SZ",
    "wof:placetype": "postalcode"
  },
  "geometry": {"coordinates":[-4.11303,51.027187],"type":"Point"}
}
