{
  "type": "Feature",
  "properties": {
    "iso:country":"GB",
    "wof:name":"DN11 0FD",
    "wof:placetype":"postalcode"
},
  "geometry": {"coordinates":[-1.05598234477277,53.47388386236096],"type":"Point"}
}