{
  "type": "Feature",
  "properties": {
    "iso:country":"GB",
    "wof:name":"YO43 3LZ",
    "wof:placetype":"postalcode"
},
  "geometry": {"coordinates":[-0.66311709268406,53.86506150975867],"type":"Point"}
}