{
  "type": "Feature",
  "properties": {
    "date:inception_lower":"2006-07-01",
    "date:inception_upper":"2006-07-31",
    "iso:country":"GB",
    "wof:name":"YO43 3LZ",
    "wof:placetype":"postalcode"
},
  "geometry": {"coordinates":[-0.663117,53.865062],"type":"Point"}
}