{
  "type": "Feature",
  "properties": {
    "iso:country": "GB",
    "wof:name": "YO43 3LZ",
    "wof:placetype": "postalcode"
  },
  "geometry": {"coordinates":[-0.663117,53.865062],"type":"Point"}
}
