{
  "type": "Feature",
  "properties": {
    "iso:country": "GB",
    "wof:name": "IV30 1QP",
    "wof:placetype": "postalcode"
  },
  "geometry": {"coordinates":[-3.307326,57.64338],"type":"Point"}
}
