{
  "type": "Feature",
  "properties": {
    "iso:country":"GB",
    "wof:name":"IV30 1QP",
    "wof:placetype":"postalcode"
},
  "geometry": {"coordinates":[-3.3073259284685,57.643379812098],"type":"Point"}
}