{
  "type": "Feature",
  "properties": {
    "date:inception_lower": "2002-06-01",
    "date:inception_upper": "2002-06-01",
    "iso:country": "GB",
    "wof:name": "IV30 1QP",
    "wof:placetype": "postalcode"
  },
  "geometry": {"coordinates":[-3.30737,57.643283],"type":"Point"}
}
