{
  "type": "Feature",
  "properties": {
    "date:inception_lower": "2021-10-01",
    "date:inception_upper": "2021-10-01",
    "iso:country": "GB",
    "wof:name": "SE3 9JF",
    "wof:placetype": "postalcode"
  },
  "geometry": {"coordinates":[0.028163,51.461605],"type":"Point"}
}
