{
  "type": "Feature",
  "properties": {
    "iso:country":"GB",
    "wof:name":"CH1 6PL",
    "wof:placetype":"postalcode"
},
  "geometry": {"coordinates":[-2.90677388464866,53.24686487844883],"type":"Point"}
}