{
  "type": "Feature",
  "properties": {
    "date:inception_lower": "1980-01-01",
    "date:inception_upper": "1980-01-01",
    "iso:country": "GB",
    "wof:name": "LA16 7BZ",
    "wof:placetype": "postalcode"
  },
  "geometry": {"coordinates":[-3.208041,54.181729],"type":"Point"}
}
