{
  "type": "Feature",
  "properties": {
    "iso:country":"GB",
    "wof:name":"PO22 8DR",
    "wof:placetype":"postalcode"
},
  "geometry": {"coordinates":[-0.66483434116674,50.79334371190629],"type":"Point"}
}