{
  "type": "Feature",
  "properties": {
    "date:inception_lower": "1980-01-01",
    "date:inception_upper": "1980-01-01",
    "iso:country": "GB",
    "wof:name": "PO22 8DR",
    "wof:placetype": "postalcode"
  },
  "geometry": {"coordinates":[-0.664834,50.793344],"type":"Point"}
}
