{
  "type": "Feature",
  "properties": {
    "iso:country": "GB",
    "wof:name": "PO22 8DR",
    "wof:placetype": "postalcode"
  },
  "geometry": {"coordinates":[-0.664834,50.793344],"type":"Point"}
}
