{
  "type": "Feature",
  "properties": {
    "iso:country":"GB",
    "wof:name":"SA33 6TZ",
    "wof:placetype":"postalcode"
},
  "geometry": {"coordinates":[-4.3965835770428,51.93322846172745],"type":"Point"}
}