{
  "type": "Feature",
  "properties": {
    "date:inception_lower": "1980-01-01",
    "date:inception_upper": "1980-01-01",
    "iso:country": "GB",
    "wof:name": "SA33 6TZ",
    "wof:placetype": "postalcode"
  },
  "geometry": {"coordinates":[-4.396584,51.933228],"type":"Point"}
}
