{
  "type": "Feature",
  "properties": {
    "iso:country":"GB",
    "wof:name":"EH5 2GB",
    "wof:placetype":"postalcode"
},
  "geometry": {"coordinates":[-3.22721611905153,55.97186712314699],"type":"Point"}
}