{
  "type": "Feature",
  "properties": {
    "iso:country":"GB",
    "wof:name":"KA7 3EN",
    "wof:placetype":"postalcode"
},
  "geometry": {"coordinates":[-4.61737296795098,55.45348677179835],"type":"Point"}
}