{
  "type": "Feature",
  "properties": {
    "date:inception_lower": "1980-01-01",
    "date:inception_upper": "1980-01-01",
    "iso:country": "GB",
    "wof:name": "KA7 3EN",
    "wof:placetype": "postalcode"
  },
  "geometry": {"coordinates":[-4.617373,55.453487],"type":"Point"}
}
