{
  "type": "Feature",
  "properties": {
    "iso:country": "GB",
    "wof:name": "SY11 4FE",
    "wof:placetype": "postalcode"
  },
  "geometry": {"coordinates":[-3.026749,52.880242],"type":"Point"}
}
