{
  "type": "Feature",
  "properties": {
    "date:inception_lower":"1980-01-01",
    "date:inception_upper":"1980-01-31",
    "iso:country":"GB",
    "wof:name":"YO17 9ST",
    "wof:placetype":"postalcode"
},
  "geometry": {"coordinates":[-0.73235,54.059198],"type":"Point"}
}