{
  "type": "Feature",
  "properties": {
    "iso:country":"GB",
    "wof:name":"YO17 9ST",
    "wof:placetype":"postalcode"
},
  "geometry": {"coordinates":[-0.73234968241636,54.05919769703696],"type":"Point"}
}