{
  "type": "Feature",
  "properties": {
    "date:inception_lower": "1980-01-01",
    "date:inception_upper": "1980-01-01",
    "iso:country": "GB",
    "wof:name": "SR7 9AG",
    "wof:placetype": "postalcode"
  },
  "geometry": {"coordinates":[-1.384395,54.818242],"type":"Point"}
}
