{
  "type": "Feature",
  "properties": {
    "iso:country": "GB",
    "wof:name": "SO40 3BH",
    "wof:placetype": "postalcode"
  },
  "geometry": {"coordinates":[-1.487092,50.922811],"type":"Point"}
}
