{
  "type": "Feature",
  "properties": {
    "iso:country":"GB",
    "wof:name":"SO40 3BH",
    "wof:placetype":"postalcode"
},
  "geometry": {"coordinates":[-1.48708592413173,50.92282789917105],"type":"Point"}
}