{
  "type": "Feature",
  "properties": {
    "iso:country":"GB",
    "wof:name":"LE15 6RA",
    "wof:placetype":"postalcode"
},
  "geometry": {"coordinates":[-0.7333542520716,52.67438008714712],"type":"Point"}
}