{
  "type": "Feature",
  "properties": {
    "date:inception_lower": "1996-06-01",
    "date:inception_upper": "1996-06-01",
    "iso:country": "GB",
    "wof:name": "LE15 6RA",
    "wof:placetype": "postalcode"
  },
  "geometry": {"coordinates":[-0.73352,52.674455],"type":"Point"}
}
