{
  "type": "Feature",
  "properties": {
    "date:inception_lower": "1992-08-01",
    "date:inception_upper": "1992-08-01",
    "iso:country": "GB",
    "wof:name": "ST1 3BW",
    "wof:placetype": "postalcode"
  },
  "geometry": {"coordinates":[-2.171346,53.015813],"type":"Point"}
}
