{
  "type": "Feature",
  "properties": {
    "iso:country": "GB",
    "wof:name": "SA4 4BY",
    "wof:placetype": "postalcode"
  },
  "geometry": {"coordinates":[-4.037813,51.670939],"type":"Point"}
}
