{
  "type": "Feature",
  "properties": {
    "iso:country":"GB",
    "wof:name":"SA4 4BY",
    "wof:placetype":"postalcode"
},
  "geometry": {"coordinates":[-4.03781298519602,51.67093868905692],"type":"Point"}
}