{
  "type": "Feature",
  "properties": {
    "iso:country": "GB",
    "wof:name": "SA4 4BY",
    "wof:placetype": "postalcode"
  },
  "geometry": {"coordinates":[-4.037849,51.670989],"type":"Point"}
}
