{
  "type": "Feature",
  "properties": {
    "iso:country":"GB",
    "wof:name":"DG2 7QQ",
    "wof:placetype":"postalcode"
},
  "geometry": {"coordinates":[-3.62421436894901,55.0645345578824],"type":"Point"}
}