{
  "type": "Feature",
  "properties": {
    "iso:country":"GB",
    "wof:name":"HR2 6QB",
    "wof:placetype":"postalcode"
},
  "geometry": {"coordinates":[-2.6707643356448,51.977207687567],"type":"Point"}
}