{
  "type": "Feature",
  "properties": {
    "date:inception_lower": "1980-01-01",
    "date:inception_upper": "1980-01-01",
    "iso:country": "GB",
    "wof:name": "HR2 6QB",
    "wof:placetype": "postalcode"
  },
  "geometry": {"coordinates":[-2.670764,51.977208],"type":"Point"}
}
