{
  "type": "Feature",
  "properties": {
    "iso:country": "GB",
    "wof:name": "WN8 7SH",
    "wof:placetype": "postalcode"
  },
  "geometry": {"coordinates":[-2.763946,53.562914],"type":"Point"}
}
