{
  "type": "Feature",
  "properties": {
    "iso:country":"GB",
    "wof:name":"WN8 7SH",
    "wof:placetype":"postalcode"
},
  "geometry": {"coordinates":[-2.76394606929115,53.56291374792763],"type":"Point"}
}