{
  "type": "Feature",
  "properties": {
    "date:inception_lower": "2016-08-01",
    "date:inception_upper": "2016-08-01",
    "iso:country": "GB",
    "wof:name": "BS16 6FH",
    "wof:placetype": "postalcode"
  },
  "geometry": {"coordinates":[-2.496368,51.499372],"type":"Point"}
}
