{
  "type": "Feature",
  "properties": {
    "iso:country": "GB",
    "wof:name": "BH18 9BB",
    "wof:placetype": "postalcode"
  },
  "geometry": {"coordinates":[-1.996077,50.766279],"type":"Point"}
}
