{
  "type": "Feature",
  "properties": {
    "iso:country":"GB",
    "wof:name":"DN40 3JJ",
    "wof:placetype":"postalcode"
},
  "geometry": {"coordinates":[-0.26799176492937,53.63976371980069],"type":"Point"}
}