{
  "type": "Feature",
  "properties": {
    "iso:country": "GB",
    "wof:name": "S63 8AN",
    "wof:placetype": "postalcode"
  },
  "geometry": {"coordinates":[-1.319412,53.524059],"type":"Point"}
}
