{
  "type": "Feature",
  "properties": {
    "date:inception_lower":"1994-05-01",
    "date:inception_upper":"1994-05-31",
    "iso:country":"GB",
    "wof:name":"ST10 4TT",
    "wof:placetype":"postalcode"
},
  "geometry": {"coordinates":[-1.892533,52.979626],"type":"Point"}
}