{
  "type": "Feature",
  "properties": {
    "iso:country":"GB",
    "wof:name":"DY8 5DJ",
    "wof:placetype":"postalcode"
},
  "geometry": {"coordinates":[-2.16650055850932,52.4722122371189],"type":"Point"}
}