{
  "type": "Feature",
  "properties": {
    "iso:country":"GB",
    "wof:name":"NG19 8SZ",
    "wof:placetype":"postalcode"
},
  "geometry": {"coordinates":[-1.25335895478169,53.18095660954368],"type":"Point"}
}