{
  "type": "Feature",
  "properties": {
    "iso:country": "GB",
    "wof:name": "YO8 9ES",
    "wof:placetype": "postalcode"
  },
  "geometry": {"coordinates":[-1.093947,53.767079],"type":"Point"}
}
