{
  "type": "Feature",
  "properties": {
    "iso:country": "GB",
    "wof:name": "DN17 1SU",
    "wof:placetype": "postalcode"
  },
  "geometry": {"coordinates":[-0.685858,53.56989],"type":"Point"}
}
