{
  "type": "Feature",
  "properties": {
    "iso:country":"GB",
    "wof:name":"DN17 1SU",
    "wof:placetype":"postalcode"
},
  "geometry": {"coordinates":[-0.68585447497602,53.56986929743968],"type":"Point"}
}