{
  "type": "Feature",
  "properties": {
    "date:inception_lower":"1980-01-01",
    "date:inception_upper":"1980-01-31",
    "iso:country":"GB",
    "wof:name":"DN17 1SU",
    "wof:placetype":"postalcode"
},
  "geometry": {"coordinates":[-0.685858,53.56989],"type":"Point"}
}