{
  "type": "Feature",
  "properties": {
    "iso:country": "GB",
    "wof:name": "LN8 3YW",
    "wof:placetype": "postalcode"
  },
  "geometry": {"coordinates":[-0.36024,53.448002],"type":"Point"}
}
