{
  "type": "Feature",
  "properties": {
    "iso:country":"GB",
    "wof:name":"LN8 3YW",
    "wof:placetype":"postalcode"
},
  "geometry": {"coordinates":[-0.36524933535964,53.45118518129679],"type":"Point"}
}