{
  "type": "Feature",
  "properties": {
    "iso:country":"GB",
    "wof:name":"NR32 1LJ",
    "wof:placetype":"postalcode"
},
  "geometry": {"coordinates":[1.75054645194624,52.47546183476695],"type":"Point"}
}