{
  "type": "Feature",
  "properties": {
    "iso:country":"GB",
    "wof:name":"TW7 6LP",
    "wof:placetype":"postalcode"
},
  "geometry": {"coordinates":[-0.3404841147109,51.47062137521668],"type":"Point"}
}