{
  "type": "Feature",
  "properties": {
    "iso:country":"GB",
    "wof:name":"WF17 9QR",
    "wof:placetype":"postalcode"
},
  "geometry": {"coordinates":[-1.65804045842032,53.73795304779721],"type":"Point"}
}