{
  "type": "Feature",
  "properties": {
    "date:inception_lower": "2023-11-01",
    "date:inception_upper": "2023-11-01",
    "iso:country": "GB",
    "wof:name": "CF35 6QR",
    "wof:placetype": "postalcode"
  },
  "geometry": {"coordinates":[-3.565515,51.524414],"type":"Point"}
}
