{
  "type": "Feature",
  "properties": {
    "date:inception_lower": "2013-07-01",
    "date:inception_upper": "2013-07-01",
    "iso:country": "GB",
    "wof:name": "CA6 4BE",
    "wof:placetype": "postalcode"
  },
  "geometry": {"coordinates":[-2.985242,54.928685],"type":"Point"}
}
