{
  "type": "Feature",
  "properties": {
    "iso:country":"GB",
    "wof:name":"CA6 4BE",
    "wof:placetype":"postalcode"
},
  "geometry": {"coordinates":[-2.98524190130064,54.92868452317479],"type":"Point"}
}