{
  "type": "Feature",
  "properties": {
    "date:inception_lower":"1995-07-01",
    "date:inception_upper":"1995-07-31",
    "iso:country":"GB",
    "wof:name":"WV6 0SA",
    "wof:placetype":"postalcode"
},
  "geometry": {"coordinates":[-2.135567,52.595251],"type":"Point"}
}