{
  "type": "Feature",
  "properties": {
    "iso:country": "GB",
    "wof:name": "RH13 0RL",
    "wof:placetype": "postalcode"
  },
  "geometry": {"coordinates":[-0.397513,51.056047],"type":"Point"}
}
