{
  "type": "Feature",
  "properties": {
    "date:inception_lower": "2005-06-01",
    "date:inception_upper": "2005-06-01",
    "iso:country": "GB",
    "wof:name": "DA9 9FH",
    "wof:placetype": "postalcode"
  },
  "geometry": {"coordinates":[0.290059,51.454316],"type":"Point"}
}
