{
  "type": "Feature",
  "properties": {
    "iso:country":"GB",
    "wof:name":"DA9 9FH",
    "wof:placetype":"postalcode"
},
  "geometry": {"coordinates":[0.29005903521276,51.45431642721483],"type":"Point"}
}