{
  "type": "Feature",
  "properties": {
    "iso:country": "GB",
    "wof:name": "GL5 5DQ",
    "wof:placetype": "postalcode"
  },
  "geometry": {"coordinates":[-2.214506,51.721072],"type":"Point"}
}
