{
  "type": "Feature",
  "properties": {
    "iso:country":"GB",
    "wof:name":"GL5 5DQ",
    "wof:placetype":"postalcode"
},
  "geometry": {"coordinates":[-2.21450585904307,51.72107234149115],"type":"Point"}
}