{
  "type": "Feature",
  "properties": {
    "iso:country": "GB",
    "wof:name": "IV30 8AR",
    "wof:placetype": "postalcode"
  },
  "geometry": {"coordinates":[-3.286258,57.633735],"type":"Point"}
}
