{
  "type": "Feature",
  "properties": {
    "date:inception_lower":"2012-09-01",
    "date:inception_upper":"2012-09-30",
    "iso:country":"GB",
    "wof:name":"CF31 9FS",
    "wof:placetype":"postalcode"
},
  "geometry": {"coordinates":[-3.571182,51.50522],"type":"Point"}
}