{
  "type": "Feature",
  "properties": {
    "date:inception_lower":"2001-06-01",
    "date:inception_upper":"2001-06-30",
    "iso:country":"GB",
    "wof:name":"M16 0YZ",
    "wof:placetype":"postalcode"
},
  "geometry": {"coordinates":[-2.262773,53.457321],"type":"Point"}
}