{
  "type": "Feature",
  "properties": {
    "iso:country":"GB",
    "wof:name":"GL7 1JQ",
    "wof:placetype":"postalcode"
},
  "geometry": {"coordinates":[-1.94837369932534,51.72084378222432],"type":"Point"}
}