{
  "type": "Feature",
  "properties": {
    "iso:country":"GB",
    "wof:name":"DY6 7HD",
    "wof:placetype":"postalcode"
},
  "geometry": {"coordinates":[-2.1626311317703,52.50473429256196],"type":"Point"}
}