{
  "type": "Feature",
  "properties": {
    "iso:country": "GB",
    "wof:name": "LN2 2UX",
    "wof:placetype": "postalcode"
  },
  "geometry": {"coordinates":[-0.449242,53.283814],"type":"Point"}
}
