{
  "type": "Feature",
  "properties": {
    "date:inception_lower":"1980-01-01",
    "date:inception_upper":"1980-01-31",
    "iso:country":"GB",
    "wof:name":"CT13 0NP",
    "wof:placetype":"postalcode"
},
  "geometry": {"coordinates":[1.306465,51.26177],"type":"Point"}
}