{
  "type": "Feature",
  "properties": {
    "iso:country":"GB",
    "wof:name":"CT13 0NP",
    "wof:placetype":"postalcode"
},
  "geometry": {"coordinates":[1.30642061637285,51.26174543110584],"type":"Point"}
}