{
  "type": "Feature",
  "properties": {
    "iso:country": "GB",
    "wof:name": "AB15 7YW",
    "wof:placetype": "postalcode"
  },
  "geometry": {"coordinates":[-2.144534,57.133373],"type":"Point"}
}
