{
  "type": "Feature",
  "properties": {
    "iso:country": "GB",
    "wof:name": "GL54 4HS",
    "wof:placetype": "postalcode"
  },
  "geometry": {"coordinates":[-1.959,51.864309],"type":"Point"}
}
