{
  "type": "Feature",
  "properties": {
    "iso:country":"GB",
    "wof:name":"IP21 5UA",
    "wof:placetype":"postalcode"
},
  "geometry": {"coordinates":[1.30703993472089,52.38443911942533],"type":"Point"}
}