{
  "type": "Feature",
  "properties": {
    "iso:country": "GB",
    "wof:name": "IP21 5UA",
    "wof:placetype": "postalcode"
  },
  "geometry": {"coordinates":[1.30704,52.384439],"type":"Point"}
}
