{
  "type": "Feature",
  "properties": {
    "iso:country":"GB",
    "wof:name":"LS15 0LL",
    "wof:placetype":"postalcode"
},
  "geometry": {"coordinates":[-1.47006874075436,53.79216018842994],"type":"Point"}
}