{
  "type": "Feature",
  "properties": {
    "date:inception_lower":"1980-01-01",
    "date:inception_upper":"1980-01-31",
    "iso:country":"GB",
    "wof:name":"LS15 0LL",
    "wof:placetype":"postalcode"
},
  "geometry": {"coordinates":[-1.470069,53.79216],"type":"Point"}
}