{
  "type": "Feature",
  "properties": {
    "date:inception_lower":"2012-02-01",
    "date:inception_upper":"2012-02-29",
    "iso:country":"GB",
    "wof:name":"TA5 2JF",
    "wof:placetype":"postalcode"
},
  "geometry": {"coordinates":[-3.01511,51.114976],"type":"Point"}
}