{
  "type": "Feature",
  "properties": {
    "iso:country":"GB",
    "wof:name":"TA5 2JF",
    "wof:placetype":"postalcode"
},
  "geometry": {"coordinates":[-3.01508877385402,51.11498169971694],"type":"Point"}
}