{
  "type": "Feature",
  "properties": {
    "date:inception_lower": "1992-08-01",
    "date:inception_upper": "1992-08-01",
    "iso:country": "GB",
    "wof:name": "DE21 5AS",
    "wof:placetype": "postalcode"
  },
  "geometry": {"coordinates":[-1.455274,52.980927],"type":"Point"}
}
