{
  "type": "Feature",
  "properties": {
    "iso:country":"GB",
    "wof:name":"PL24 2TB",
    "wof:placetype":"postalcode"
},
  "geometry": {"coordinates":[-4.74001478369641,50.3574023758278],"type":"Point"}
}