{
  "type": "Feature",
  "properties": {
    "iso:country": "GB",
    "wof:name": "PO4 8HQ",
    "wof:placetype": "postalcode"
  },
  "geometry": {"coordinates":[-1.054983,50.79141],"type":"Point"}
}
