{
  "type": "Feature",
  "properties": {
    "date:inception_lower": "2009-12-01",
    "date:inception_upper": "2009-12-01",
    "iso:country": "GB",
    "wof:name": "PO4 8HQ",
    "wof:placetype": "postalcode"
  },
  "geometry": {"coordinates":[-1.054983,50.79141],"type":"Point"}
}
