{
  "type": "Feature",
  "properties": {
    "date:inception_lower":"1997-06-01",
    "date:inception_upper":"1997-06-30",
    "iso:country":"GB",
    "wof:name":"LN12 1RP",
    "wof:placetype":"postalcode"
},
  "geometry": {"coordinates":[0.255239,53.338858],"type":"Point"}
}