{
  "type": "Feature",
  "properties": {
    "iso:country":"GB",
    "wof:name":"LN12 1RP",
    "wof:placetype":"postalcode"
},
  "geometry": {"coordinates":[0.25523867096124,53.33885832839402],"type":"Point"}
}