{
  "type": "Feature",
  "properties": {
    "date:inception_lower":"1980-01-01",
    "date:inception_upper":"1980-01-31",
    "iso:country":"GB",
    "wof:name":"LL40 2BH",
    "wof:placetype":"postalcode"
},
  "geometry": {"coordinates":[-3.762616,52.784617],"type":"Point"}
}