{
  "type": "Feature",
  "properties": {
    "iso:country":"GB",
    "wof:name":"L75 1AH",
    "wof:placetype":"postalcode"
},
  "geometry": {"coordinates":[-2.99157368997582,53.40442383765181],"type":"Point"}
}