{
  "type": "Feature",
  "properties": {
    "iso:country": "GB",
    "wof:name": "WN1 3LG",
    "wof:placetype": "postalcode"
  },
  "geometry": {"coordinates":[-2.618699,53.549012],"type":"Point"}
}
