{
  "type": "Feature",
  "properties": {
    "iso:country": "GB",
    "wof:name": "CV4 9QQ",
    "wof:placetype": "postalcode"
  },
  "geometry": {"coordinates":[-1.581475,52.409262],"type":"Point"}
}
