{
  "type": "Feature",
  "properties": {
    "iso:country":"GB",
    "wof:name":"CV4 9QQ",
    "wof:placetype":"postalcode"
},
  "geometry": {"coordinates":[-1.58147483252393,52.40926218974132],"type":"Point"}
}