{
  "type": "Feature",
  "properties": {
    "date:inception_lower": "2005-02-01",
    "date:inception_upper": "2005-02-01",
    "iso:country": "GB",
    "wof:name": "GU15 9SL",
    "wof:placetype": "postalcode"
  },
  "geometry": {"coordinates":[-0.743166,51.33947],"type":"Point"}
}
