{
  "type": "Feature",
  "properties": {
    "iso:country":"GB",
    "wof:name":"WS9 8HD",
    "wof:placetype":"postalcode"
},
  "geometry": {"coordinates":[-1.9151029969552,52.61707222861795],"type":"Point"}
}