{
  "type": "Feature",
  "properties": {
    "date:inception_lower": "2023-07-01",
    "date:inception_upper": "2023-07-01",
    "iso:country": "GB",
    "wof:name": "BB2 3DZ",
    "wof:placetype": "postalcode"
  },
  "geometry": {"coordinates":[-2.472702,53.728606],"type":"Point"}
}
