{
  "type": "Feature",
  "properties": {
    "iso:country":"GB",
    "wof:name":"YO7 4JZ",
    "wof:placetype":"postalcode"
},
  "geometry": {"coordinates":[-1.48998693029551,54.2351803004882],"type":"Point"}
}