{
  "type": "Feature",
  "properties": {
    "date:inception_lower": "2012-07-01",
    "date:inception_upper": "2012-07-01",
    "iso:country": "GB",
    "wof:name": "TS23 2FA",
    "wof:placetype": "postalcode"
  },
  "geometry": {"coordinates":[-1.293934,54.609004],"type":"Point"}
}
