{
  "type": "Feature",
  "properties": {
    "iso:country": "GB",
    "wof:name": "TS23 2FA",
    "wof:placetype": "postalcode"
  },
  "geometry": {"coordinates":[-1.293934,54.609004],"type":"Point"}
}
