{
  "type": "Feature",
  "properties": {
    "date:inception_lower": "1980-01-01",
    "date:inception_upper": "1980-01-01",
    "iso:country": "GB",
    "wof:name": "TN30 7PU",
    "wof:placetype": "postalcode"
  },
  "geometry": {"coordinates":[0.67011,51.020939],"type":"Point"}
}
