{
  "type": "Feature",
  "properties": {
    "iso:country":"GB",
    "wof:name":"TN30 7PU",
    "wof:placetype":"postalcode"
},
  "geometry": {"coordinates":[0.67010947809245,51.02093933426332],"type":"Point"}
}