{
  "type": "Feature",
  "properties": {
    "iso:country": "GB",
    "wof:name": "TN30 7PU",
    "wof:placetype": "postalcode"
  },
  "geometry": {"coordinates":[0.67011,51.020939],"type":"Point"}
}
