{
  "type": "Feature",
  "properties": {
    "iso:country":"GB",
    "wof:name":"NP20 7LX",
    "wof:placetype":"postalcode"
},
  "geometry": {"coordinates":[-3.01797076569171,51.60965085563451],"type":"Point"}
}