{
  "type": "Feature",
  "properties": {
    "iso:country": "GB",
    "wof:name": "NP20 7LX",
    "wof:placetype": "postalcode"
  },
  "geometry": {"coordinates":[-3.017971,51.609651],"type":"Point"}
}
