{
  "type": "Feature",
  "properties": {
    "iso:country": "GB",
    "wof:name": "PO18 0PD",
    "wof:placetype": "postalcode"
  },
  "geometry": {"coordinates":[-0.739145,50.852193],"type":"Point"}
}
