{
  "type": "Feature",
  "properties": {
    "iso:country":"GB",
    "wof:name":"PO18 0PD",
    "wof:placetype":"postalcode"
},
  "geometry": {"coordinates":[-0.73914515395728,50.85219298296094],"type":"Point"}
}