{
  "type": "Feature",
  "properties": {
    "iso:country":"GB",
    "wof:name":"SR4 8RT",
    "wof:placetype":"postalcode"
},
  "geometry": {"coordinates":[-1.43040593515016,54.89177881137994],"type":"Point"}
}