{
  "type": "Feature",
  "properties": {
    "iso:country":"GB",
    "wof:name":"DH8 5HZ",
    "wof:placetype":"postalcode"
},
  "geometry": {"coordinates":[-1.83268516113313,54.85787913681934],"type":"Point"}
}