{
  "type": "Feature",
  "properties": {
    "iso:country":"GB",
    "wof:name":"SA72 6NL",
    "wof:placetype":"postalcode"
},
  "geometry": {"coordinates":[-4.94728836634191,51.68957849806537],"type":"Point"}
}