{
  "type": "Feature",
  "properties": {
    "date:inception_lower": "1980-01-01",
    "date:inception_upper": "1980-01-01",
    "iso:country": "GB",
    "wof:name": "ML6 8PL",
    "wof:placetype": "postalcode"
  },
  "geometry": {"coordinates":[-3.939394,55.862658],"type":"Point"}
}
