{
  "type": "Feature",
  "properties": {
    "iso:country":"GB",
    "wof:name":"ML6 8PL",
    "wof:placetype":"postalcode"
},
  "geometry": {"coordinates":[-3.93939436651807,55.86265797319584],"type":"Point"}
}