{
  "type": "Feature",
  "properties": {
    "iso:country":"GB",
    "wof:name":"SE1 4DZ",
    "wof:placetype":"postalcode"
},
  "geometry": {"coordinates":[-0.08701789934149,51.49736177701907],"type":"Point"}
}