{
  "type": "Feature",
  "properties": {
    "iso:country": "GB",
    "wof:name": "SG18 8XT",
    "wof:placetype": "postalcode"
  },
  "geometry": {"coordinates":[-0.212874,52.056335],"type":"Point"}
}
