{
  "type": "Feature",
  "properties": {
    "iso:country": "GB",
    "wof:name": "IP14 6ER",
    "wof:placetype": "postalcode"
  },
  "geometry": {"coordinates":[1.180995,52.161717],"type":"Point"}
}
