{
  "type": "Feature",
  "properties": {
    "date:inception_lower": "1980-01-01",
    "date:inception_upper": "1980-01-01",
    "iso:country": "GB",
    "wof:name": "IP14 6ER",
    "wof:placetype": "postalcode"
  },
  "geometry": {"coordinates":[1.180839,52.161577],"type":"Point"}
}
