{
  "type": "Feature",
  "properties": {
    "iso:country": "GB",
    "wof:name": "IP14 6ER",
    "wof:placetype": "postalcode"
  },
  "geometry": {"coordinates":[1.180839,52.161577],"type":"Point"}
}
