{
  "type": "Feature",
  "properties": {
    "iso:country":"GB",
    "wof:name":"IP14 6ER",
    "wof:placetype":"postalcode"
},
  "geometry": {"coordinates":[1.18080690874027,52.16174073167019],"type":"Point"}
}