{
  "type": "Feature",
  "properties": {
    "date:inception_lower": "1980-01-01",
    "date:inception_upper": "1980-01-01",
    "iso:country": "GB",
    "wof:name": "LS29 8SB",
    "wof:placetype": "postalcode"
  },
  "geometry": {"coordinates":[-1.794734,53.91956],"type":"Point"}
}
