{
  "type": "Feature",
  "properties": {
    "iso:country":"GB",
    "wof:name":"LS29 8SB",
    "wof:placetype":"postalcode"
},
  "geometry": {"coordinates":[-1.79473438533056,53.91956025573894],"type":"Point"}
}