{
  "type": "Feature",
  "properties": {
    "iso:country": "GB",
    "wof:name": "LS29 8SB",
    "wof:placetype": "postalcode"
  },
  "geometry": {"coordinates":[-1.794734,53.91956],"type":"Point"}
}
