{
  "type": "Feature",
  "properties": {
    "iso:country":"GB",
    "wof:name":"YO32 5RR",
    "wof:placetype":"postalcode"
},
  "geometry": {"coordinates":[-1.03618825466511,54.04030060627093],"type":"Point"}
}