{
  "type": "Feature",
  "properties": {
    "date:inception_lower":"2003-06-01",
    "date:inception_upper":"2003-06-30",
    "iso:country":"GB",
    "wof:name":"YO32 5RR",
    "wof:placetype":"postalcode"
},
  "geometry": {"coordinates":[-1.036188,54.040301],"type":"Point"}
}