{
  "type": "Feature",
  "properties": {
    "date:inception_lower": "1980-01-01",
    "date:inception_upper": "1980-01-01",
    "iso:country": "GB",
    "wof:name": "KA7 1JQ",
    "wof:placetype": "postalcode"
  },
  "geometry": {"coordinates":[-4.638275,55.464265],"type":"Point"}
}
