{
  "type": "Feature",
  "properties": {
    "iso:country": "GB",
    "wof:name": "GU11 4BP",
    "wof:placetype": "postalcode"
  },
  "geometry": {"coordinates":[-0.767033,51.255573],"type":"Point"}
}
