{
  "type": "Feature",
  "properties": {
    "iso:country": "GB",
    "wof:name": "CT15 7DU",
    "wof:placetype": "postalcode"
  },
  "geometry": {"coordinates":[1.228313,51.143203],"type":"Point"}
}
