{
  "type": "Feature",
  "properties": {
    "date:inception_lower": "1980-01-01",
    "date:inception_upper": "1980-01-01",
    "iso:country": "GB",
    "wof:name": "CT15 7DU",
    "wof:placetype": "postalcode"
  },
  "geometry": {"coordinates":[1.229918,51.143249],"type":"Point"}
}
