{
  "type": "Feature",
  "properties": {
    "iso:country":"GB",
    "wof:name":"SS9 1EY",
    "wof:placetype":"postalcode"
},
  "geometry": {"coordinates":[0.66932925422467,51.53955560636497],"type":"Point"}
}