{
  "type": "Feature",
  "properties": {
    "iso:country": "GB",
    "wof:name": "GL20 6AY",
    "wof:placetype": "postalcode"
  },
  "geometry": {"coordinates":[-2.240018,52.024502],"type":"Point"}
}
