{
  "type": "Feature",
  "properties": {
    "iso:country":"GB",
    "wof:name":"EX22 6RT",
    "wof:placetype":"postalcode"
},
  "geometry": {"coordinates":[-4.38132089080074,50.75157961841956],"type":"Point"}
}