{
  "type": "Feature",
  "properties": {
    "iso:country": "GB",
    "wof:name": "NR32 5JE",
    "wof:placetype": "postalcode"
  },
  "geometry": {"coordinates":[1.74548,52.513401],"type":"Point"}
}
