{
  "type": "Feature",
  "properties": {
    "iso:country":"GB",
    "wof:name":"NR32 5JE",
    "wof:placetype":"postalcode"
},
  "geometry": {"coordinates":[1.74547949983614,52.51340118393858],"type":"Point"}
}