{
  "type": "Feature",
  "properties": {
    "iso:country": "GB",
    "wof:name": "DN36 4ZR",
    "wof:placetype": "postalcode"
  },
  "geometry": {"coordinates":[-0.033858,53.525867],"type":"Point"}
}
