{
  "type": "Feature",
  "properties": {
    "date:inception_lower": "2001-06-01",
    "date:inception_upper": "2001-06-01",
    "iso:country": "GB",
    "wof:name": "SW19 1UZ",
    "wof:placetype": "postalcode"
  },
  "geometry": {"coordinates":[-0.18214,51.419381],"type":"Point"}
}
