{
  "type": "Feature",
  "properties": {
    "iso:country":"GB",
    "wof:name":"SW19 1UZ",
    "wof:placetype":"postalcode"
},
  "geometry": {"coordinates":[-0.18241475518227,51.41961890609035],"type":"Point"}
}