{
  "type": "Feature",
  "properties": {
    "date:inception_lower":"2007-01-01",
    "date:inception_upper":"2007-01-31",
    "iso:country":"GB",
    "wof:name":"LE17 4AZ",
    "wof:placetype":"postalcode"
},
  "geometry": {"coordinates":[-1.200779,52.454447],"type":"Point"}
}