{
  "type": "Feature",
  "properties": {
    "iso:country": "GB",
    "wof:name": "GL52 2PE",
    "wof:placetype": "postalcode"
  },
  "geometry": {"coordinates":[-2.07151,51.904204],"type":"Point"}
}
