{
  "type": "Feature",
  "properties": {
    "iso:country":"GB",
    "wof:name":"GL52 2PE",
    "wof:placetype":"postalcode"
},
  "geometry": {"coordinates":[-2.07150964907122,51.90420420176316],"type":"Point"}
}