{
  "type": "Feature",
  "properties": {
    "date:inception_lower": "2023-05-01",
    "date:inception_upper": "2023-05-01",
    "iso:country": "GB",
    "wof:name": "GL52 2PE",
    "wof:placetype": "postalcode"
  },
  "geometry": {"coordinates":[-2.071502,51.904212],"type":"Point"}
}
