{
  "type": "Feature",
  "properties": {
    "date:inception_lower":"1980-01-01",
    "date:inception_upper":"1980-01-31",
    "iso:country":"GB",
    "wof:name":"GL52 2PE",
    "wof:placetype":"postalcode"
},
  "geometry": {"coordinates":[-2.07151,51.904204],"type":"Point"}
}