{
  "type": "Feature",
  "properties": {
    "date:inception_lower": "1981-06-01",
    "date:inception_upper": "1981-06-01",
    "iso:country": "GB",
    "wof:name": "GL16 8LX",
    "wof:placetype": "postalcode"
  },
  "geometry": {"coordinates":[-2.626552,51.771629],"type":"Point"}
}
