{
  "type": "Feature",
  "properties": {
    "date:inception_lower": "1980-01-01",
    "date:inception_upper": "1980-01-01",
    "iso:country": "GB",
    "wof:name": "CT6 7NZ",
    "wof:placetype": "postalcode"
  },
  "geometry": {"coordinates":[1.077036,51.328588],"type":"Point"}
}
