{
  "type": "Feature",
  "properties": {
    "date:inception_lower": "1993-08-01",
    "date:inception_upper": "1993-08-01",
    "iso:country": "GB",
    "wof:name": "LE67 9TZ",
    "wof:placetype": "postalcode"
  },
  "geometry": {"coordinates":[-1.308028,52.691488],"type":"Point"}
}
