{
  "type": "Feature",
  "properties": {
    "iso:country": "GB",
    "wof:name": "LE67 9TZ",
    "wof:placetype": "postalcode"
  },
  "geometry": {"coordinates":[-1.308028,52.691488],"type":"Point"}
}
