{
  "type": "Feature",
  "properties": {
    "iso:country":"GB",
    "wof:name":"LE67 9TZ",
    "wof:placetype":"postalcode"
},
  "geometry": {"coordinates":[-1.30802843727156,52.69148794987479],"type":"Point"}
}