{
  "type": "Feature",
  "properties": {
    "iso:country":"GB",
    "wof:name":"CM1 1DE",
    "wof:placetype":"postalcode"
},
  "geometry": {"coordinates":[0.47505163959345,51.73169312656825],"type":"Point"}
}