{
  "type": "Feature",
  "properties": {
    "iso:country":"GB",
    "wof:name":"TA1 4LR",
    "wof:placetype":"postalcode"
},
  "geometry": {"coordinates":[-3.12347438571655,51.00447055895484],"type":"Point"}
}