{
  "type": "Feature",
  "properties": {
    "iso:country":"GB",
    "wof:name":"PR25 1JE",
    "wof:placetype":"postalcode"
},
  "geometry": {"coordinates":[-2.71227271056087,53.68897172587862],"type":"Point"}
}