{
  "type": "Feature",
  "properties": {
    "date:inception_lower": "1981-06-01",
    "date:inception_upper": "1981-06-01",
    "iso:country": "GB",
    "wof:name": "HU7 4SX",
    "wof:placetype": "postalcode"
  },
  "geometry": {"coordinates":[-0.305238,53.788188],"type":"Point"}
}
