{
  "type": "Feature",
  "properties": {
    "iso:country":"GB",
    "wof:name":"BD4 6EL",
    "wof:placetype":"postalcode"
},
  "geometry": {"coordinates":[-1.72660891790052,53.7638437490781],"type":"Point"}
}