{
  "type": "Feature",
  "properties": {
    "iso:country":"GB",
    "wof:name":"WF4 1JX",
    "wof:placetype":"postalcode"
},
  "geometry": {"coordinates":[-1.41377681018084,53.65188000869819],"type":"Point"}
}