{
  "type": "Feature",
  "properties": {
    "iso:country":"GB",
    "wof:name":"RH13 8DW",
    "wof:placetype":"postalcode"
},
  "geometry": {"coordinates":[-0.27229339461865,50.98873959470856],"type":"Point"}
}