{
  "type": "Feature",
  "properties": {
    "iso:country": "GB",
    "wof:name": "PE25 3QJ",
    "wof:placetype": "postalcode"
  },
  "geometry": {"coordinates":[0.335652,53.143799],"type":"Point"}
}
