{
  "type": "Feature",
  "properties": {
    "iso:country":"GB",
    "wof:name":"PE25 3QJ",
    "wof:placetype":"postalcode"
},
  "geometry": {"coordinates":[0.33565190407431,53.14379948341272],"type":"Point"}
}