{
  "type": "Feature",
  "properties": {
    "iso:country":"GB",
    "wof:name":"SS1 1HQ",
    "wof:placetype":"postalcode"
},
  "geometry": {"coordinates":[0.70644176379474,51.53549417967036],"type":"Point"}
}