{
  "type": "Feature",
  "properties": {
    "iso:country": "GB",
    "wof:name": "SS1 1HQ",
    "wof:placetype": "postalcode"
  },
  "geometry": {"coordinates":[0.706442,51.535494],"type":"Point"}
}
