{
  "type": "Feature",
  "properties": {
    "date:inception_lower": "1980-01-01",
    "date:inception_upper": "1980-01-01",
    "iso:country": "GB",
    "wof:name": "WN7 2NE",
    "wof:placetype": "postalcode"
  },
  "geometry": {"coordinates":[-2.486327,53.493103],"type":"Point"}
}
