{
  "type": "Feature",
  "properties": {
    "date:inception_lower": "2018-08-01",
    "date:inception_upper": "2018-08-01",
    "iso:country": "GB",
    "wof:name": "HP15 7EG",
    "wof:placetype": "postalcode"
  },
  "geometry": {"coordinates":[-0.713161,51.652402],"type":"Point"}
}
