{
  "type": "Feature",
  "properties": {
    "iso:country":"GB",
    "wof:name":"KT23 4DY",
    "wof:placetype":"postalcode"
},
  "geometry": {"coordinates":[-0.38608972665054,51.27348711125664],"type":"Point"}
}