{
  "type": "Feature",
  "properties": {
    "iso:country": "GB",
    "wof:name": "KT23 4DY",
    "wof:placetype": "postalcode"
  },
  "geometry": {"coordinates":[-0.386383,51.27429],"type":"Point"}
}
