{
  "type": "Feature",
  "properties": {
    "date:inception_lower":"1980-01-01",
    "date:inception_upper":"1980-01-31",
    "iso:country":"GB",
    "wof:name":"KT23 4DY",
    "wof:placetype":"postalcode"
},
  "geometry": {"coordinates":[-0.386014,51.274177],"type":"Point"}
}