{
  "type": "Feature",
  "properties": {
    "date:inception_lower": "1980-01-01",
    "date:inception_upper": "1980-01-01",
    "iso:country": "GB",
    "wof:name": "S7 1BG",
    "wof:placetype": "postalcode"
  },
  "geometry": {"coordinates":[-1.477819,53.365937],"type":"Point"}
}
