{
  "type": "Feature",
  "properties": {
    "date:inception_lower":"1980-01-01",
    "date:inception_upper":"1980-01-31",
    "iso:country":"GB",
    "wof:name":"B24 0LL",
    "wof:placetype":"postalcode"
},
  "geometry": {"coordinates":[-1.810234,52.525093],"type":"Point"}
}