{
  "type": "Feature",
  "properties": {
    "iso:country":"GB",
    "wof:name":"B24 0LL",
    "wof:placetype":"postalcode"
},
  "geometry": {"coordinates":[-1.81023372882289,52.52509280022971],"type":"Point"}
}