{
  "type": "Feature",
  "properties": {
    "iso:country":"GB",
    "wof:name":"SA4 0TP",
    "wof:placetype":"postalcode"
},
  "geometry": {"coordinates":[-4.05625465754463,51.71343044952649],"type":"Point"}
}