{
  "type": "Feature",
  "properties": {
    "date:inception_lower": "2002-06-01",
    "date:inception_upper": "2002-06-01",
    "iso:country": "GB",
    "wof:name": "SA4 0TP",
    "wof:placetype": "postalcode"
  },
  "geometry": {"coordinates":[-4.056255,51.71343],"type":"Point"}
}
