{
  "type": "Feature",
  "properties": {
    "date:inception_lower": "1980-01-01",
    "date:inception_upper": "1980-01-01",
    "iso:country": "GB",
    "wof:name": "LA5 0JA",
    "wof:placetype": "postalcode"
  },
  "geometry": {"coordinates":[-2.819534,54.196522],"type":"Point"}
}
