{
  "type": "Feature",
  "properties": {
    "iso:country":"GB",
    "wof:name":"LA5 0JA",
    "wof:placetype":"postalcode"
},
  "geometry": {"coordinates":[-2.8195336490509,54.1965221902841],"type":"Point"}
}