{
  "type": "Feature",
  "properties": {
    "date:inception_lower": "2020-04-01",
    "date:inception_upper": "2020-04-01",
    "iso:country": "GB",
    "wof:name": "IG10 4FE",
    "wof:placetype": "postalcode"
  },
  "geometry": {"coordinates":[0.050909,51.645039],"type":"Point"}
}
