{
  "type": "Feature",
  "properties": {
    "date:inception_lower": "1980-01-01",
    "date:inception_upper": "1980-01-01",
    "iso:country": "GB",
    "wof:name": "BL9 9RQ",
    "wof:placetype": "postalcode"
  },
  "geometry": {"coordinates":[-2.291914,53.575595],"type":"Point"}
}
