{
  "type": "Feature",
  "properties": {
    "iso:country":"GB",
    "wof:name":"PA15 3EL",
    "wof:placetype":"postalcode"
},
  "geometry": {"coordinates":[-4.74195641817825,55.93251623585152],"type":"Point"}
}