{
  "type": "Feature",
  "properties": {
    "date:inception_lower":"1980-01-01",
    "date:inception_upper":"1980-01-31",
    "iso:country":"GB",
    "wof:name":"LL20 7HD",
    "wof:placetype":"postalcode"
},
  "geometry": {"coordinates":[-3.187375,52.930304],"type":"Point"}
}