{
  "type": "Feature",
  "properties": {
    "iso:country":"GB",
    "wof:name":"LL20 7HD",
    "wof:placetype":"postalcode"
},
  "geometry": {"coordinates":[-3.18737459001957,52.93030405025186],"type":"Point"}
}