{
  "type": "Feature",
  "properties": {
    "date:inception_lower":"2014-10-01",
    "date:inception_upper":"2014-10-31",
    "iso:country":"GB",
    "wof:name":"OX11 6BQ",
    "wof:placetype":"postalcode"
},
  "geometry": {"coordinates":[-1.269802,51.612295],"type":"Point"}
}