{
  "type": "Feature",
  "properties": {
    "iso:country": "GB",
    "wof:name": "OX11 6BQ",
    "wof:placetype": "postalcode"
  },
  "geometry": {"coordinates":[-1.269802,51.612295],"type":"Point"}
}
