{
  "type": "Feature",
  "properties": {
    "date:inception_lower":"1980-01-01",
    "date:inception_upper":"1980-01-31",
    "iso:country":"GB",
    "wof:name":"PO8 9UX",
    "wof:placetype":"postalcode"
},
  "geometry": {"coordinates":[-1.031801,50.900535],"type":"Point"}
}