{
  "type": "Feature",
  "properties": {
    "iso:country":"GB",
    "wof:name":"PO8 9UX",
    "wof:placetype":"postalcode"
},
  "geometry": {"coordinates":[-1.03180112655771,50.90053527742327],"type":"Point"}
}