{
  "type": "Feature",
  "properties": {
    "iso:country":"GB",
    "wof:name":"BS37 5EA",
    "wof:placetype":"postalcode"
},
  "geometry": {"coordinates":[-2.42619507018894,51.54713325703854],"type":"Point"}
}