{
  "type": "Feature",
  "properties": {
    "date:inception_lower": "1997-12-01",
    "date:inception_upper": "1997-12-01",
    "iso:country": "GB",
    "wof:name": "BS37 5EA",
    "wof:placetype": "postalcode"
  },
  "geometry": {"coordinates":[-2.426195,51.547133],"type":"Point"}
}
