{
  "type": "Feature",
  "properties": {
    "date:inception_lower":"1980-01-01",
    "date:inception_upper":"1980-01-31",
    "iso:country":"GB",
    "wof:name":"G42 0BJ",
    "wof:placetype":"postalcode"
},
  "geometry": {"coordinates":[-4.240564,55.826786],"type":"Point"}
}