{
  "type": "Feature",
  "properties": {
    "iso:country":"GB",
    "wof:name":"CA3 0EQ",
    "wof:placetype":"postalcode"
},
  "geometry": {"coordinates":[-2.95382596177921,54.91341514924967],"type":"Point"}
}