{
  "type": "Feature",
  "properties": {
    "iso:country":"GB",
    "wof:name":"MK11 1DS",
    "wof:placetype":"postalcode"
},
  "geometry": {"coordinates":[-0.84603026304919,52.05579977715669],"type":"Point"}
}