{
  "type": "Feature",
  "properties": {
    "iso:country":"GB",
    "wof:name":"BN9 0NG",
    "wof:placetype":"postalcode"
},
  "geometry": {"coordinates":[0.06676825234422,50.80069814318396],"type":"Point"}
}