{
  "type": "Feature",
  "properties": {
    "date:inception_lower":"1988-03-01",
    "date:inception_upper":"1988-03-31",
    "iso:country":"GB",
    "wof:name":"WN3 5RP",
    "wof:placetype":"postalcode"
},
  "geometry": {"coordinates":[-2.643711,53.518463],"type":"Point"}
}