{
  "type": "Feature",
  "properties": {
    "iso:country":"GB",
    "wof:name":"WN3 5RP",
    "wof:placetype":"postalcode"
},
  "geometry": {"coordinates":[-2.64371153913984,53.51846319220225],"type":"Point"}
}