{
  "type": "Feature",
  "properties": {
    "iso:country":"GB",
    "wof:name":"EX8 1AY",
    "wof:placetype":"postalcode"
},
  "geometry": {"coordinates":[-3.416600466257,50.61750335200763],"type":"Point"}
}