{
  "type": "Feature",
  "properties": {
    "date:inception_lower": "2010-03-01",
    "date:inception_upper": "2010-03-01",
    "iso:country": "GB",
    "wof:name": "M9 7HR",
    "wof:placetype": "postalcode"
  },
  "geometry": {"coordinates":[-2.191861,53.528447],"type":"Point"}
}
