{
  "type": "Feature",
  "properties": {
    "iso:country":"GB",
    "wof:name":"M9 7HR",
    "wof:placetype":"postalcode"
},
  "geometry": {"coordinates":[-2.19186075591842,53.5284471897458],"type":"Point"}
}