{
  "type": "Feature",
  "properties": {
    "iso:country": "GB",
    "wof:name": "SW15 4PF",
    "wof:placetype": "postalcode"
  },
  "geometry": {"coordinates":[-0.252057,51.452709],"type":"Point"}
}
