{
  "type": "Feature",
  "properties": {
    "date:inception_lower": "1980-01-01",
    "date:inception_upper": "1980-01-01",
    "iso:country": "GB",
    "wof:name": "SW15 4PF",
    "wof:placetype": "postalcode"
  },
  "geometry": {"coordinates":[-0.252057,51.452709],"type":"Point"}
}
