{
  "type": "Feature",
  "properties": {
    "iso:country":"GB",
    "wof:name":"AB10 6LE",
    "wof:placetype":"postalcode"
},
  "geometry": {"coordinates":[-2.12465212761309,57.13095051135058],"type":"Point"}
}