{
  "type": "Feature",
  "properties": {
    "iso:country":"GB",
    "wof:name":"HA3 0DS",
    "wof:placetype":"postalcode"
},
  "geometry": {"coordinates":[-0.30781960789609,51.58363741231886],"type":"Point"}
}