{
  "type": "Feature",
  "properties": {
    "date:inception_lower": "2003-08-01",
    "date:inception_upper": "2003-08-01",
    "iso:country": "GB",
    "wof:name": "ME19 4HS",
    "wof:placetype": "postalcode"
  },
  "geometry": {"coordinates":[0.401775,51.270386],"type":"Point"}
}
