{
  "type": "Feature",
  "properties": {
    "iso:country":"GB",
    "wof:name":"DH3 3LT",
    "wof:placetype":"postalcode"
},
  "geometry": {"coordinates":[-1.56885740568659,54.84866561595387],"type":"Point"}
}