{
  "type": "Feature",
  "properties": {
    "date:inception_lower":"2010-11-01",
    "date:inception_upper":"2010-11-30",
    "iso:country":"GB",
    "wof:name":"CB23 5AD",
    "wof:placetype":"postalcode"
},
  "geometry": {"coordinates":[-0.074834,52.217125],"type":"Point"}
}