{
  "type": "Feature",
  "properties": {
    "iso:country": "GB",
    "wof:name": "CB23 5AD",
    "wof:placetype": "postalcode"
  },
  "geometry": {"coordinates":[-0.074834,52.217125],"type":"Point"}
}
