{
  "type": "Feature",
  "properties": {
    "iso:country":"GB",
    "wof:name":"CB23 5AD",
    "wof:placetype":"postalcode"
},
  "geometry": {"coordinates":[-0.07483362651699,52.2171248943374],"type":"Point"}
}