{
  "type": "Feature",
  "properties": {
    "iso:country":"GB",
    "wof:name":"IG6 2RU",
    "wof:placetype":"postalcode"
},
  "geometry": {"coordinates":[0.07910462664967,51.6056931394162],"type":"Point"}
}