{
  "type": "Feature",
  "properties": {
    "iso:country":"GB",
    "wof:name":"SY5 0QT",
    "wof:placetype":"postalcode"
},
  "geometry": {"coordinates":[-2.89454247481346,52.64888300364424],"type":"Point"}
}