{
  "type": "Feature",
  "properties": {
    "iso:country": "GB",
    "wof:name": "SA11 5LE",
    "wof:placetype": "postalcode"
  },
  "geometry": {"coordinates":[-3.608883,51.74798],"type":"Point"}
}
