{
  "type": "Feature",
  "properties": {
    "iso:country":"GB",
    "wof:name":"WA1 1EJ",
    "wof:placetype":"postalcode"
},
  "geometry": {"coordinates":[-2.59449623387808,53.3878348951679],"type":"Point"}
}