{
  "type": "Feature",
  "properties": {
    "iso:country":"GB",
    "wof:name":"LL65 4RN",
    "wof:placetype":"postalcode"
},
  "geometry": {"coordinates":[-4.38751502416568,53.26379763649992],"type":"Point"}
}