{
  "type": "Feature",
  "properties": {
    "iso:country": "GB",
    "wof:name": "LL65 4RN",
    "wof:placetype": "postalcode"
  },
  "geometry": {"coordinates":[-4.387515,53.263798],"type":"Point"}
}
