{
  "type": "Feature",
  "properties": {
    "date:inception_lower":"1980-01-01",
    "date:inception_upper":"1980-01-31",
    "iso:country":"GB",
    "wof:name":"LL65 4RN",
    "wof:placetype":"postalcode"
},
  "geometry": {"coordinates":[-4.387515,53.263798],"type":"Point"}
}