{
  "type": "Feature",
  "properties": {
    "date:inception_lower": "1980-01-01",
    "date:inception_upper": "1980-01-01",
    "iso:country": "GB",
    "wof:name": "B1 3NJ",
    "wof:placetype": "postalcode"
  },
  "geometry": {"coordinates":[-1.90965,52.48611],"type":"Point"}
}
