{
  "type": "Feature",
  "properties": {
    "iso:country":"GB",
    "wof:name":"OX16 4FS",
    "wof:placetype":"postalcode"
},
  "geometry": {"coordinates":[-1.31556317261205,52.06676150123405],"type":"Point"}
}