{
  "type": "Feature",
  "properties": {
    "iso:country":"GB",
    "wof:name":"ST10 2AN",
    "wof:placetype":"postalcode"
},
  "geometry": {"coordinates":[-1.98731749110882,53.0203141799262],"type":"Point"}
}