{
  "type": "Feature",
  "properties": {
    "iso:country":"GB",
    "wof:name":"LA17 7UT",
    "wof:placetype":"postalcode"
},
  "geometry": {"coordinates":[-3.1776406165495,54.24103618845346],"type":"Point"}
}