{
  "type": "Feature",
  "properties": {
    "iso:country":"GB",
    "wof:name":"CF14 4HY",
    "wof:placetype":"postalcode"
},
  "geometry": {"coordinates":[-3.19480685742148,51.52107799390077],"type":"Point"}
}