{
  "type": "Feature",
  "properties": {
    "iso:country":"GB",
    "wof:name":"TA21 9BP",
    "wof:placetype":"postalcode"
},
  "geometry": {"coordinates":[-3.21637711244889,50.98225436830275],"type":"Point"}
}