{
  "type": "Feature",
  "properties": {
    "iso:country":"GB",
    "wof:name":"NP44 4PH",
    "wof:placetype":"postalcode"
},
  "geometry": {"coordinates":[-3.03236668912315,51.64646259959594],"type":"Point"}
}