{
  "type": "Feature",
  "properties": {
    "iso:country":"GB",
    "wof:name":"GL7 7EN",
    "wof:placetype":"postalcode"
},
  "geometry": {"coordinates":[-1.99550269894009,51.78077146786092],"type":"Point"}
}