{
  "type": "Feature",
  "properties": {
    "iso:country":"GB",
    "wof:name":"PE11 3RA",
    "wof:placetype":"postalcode"
},
  "geometry": {"coordinates":[-0.16325398340862,52.81678378609718],"type":"Point"}
}