{
  "type": "Feature",
  "properties": {
    "iso:country": "GB",
    "wof:name": "PE11 3RA",
    "wof:placetype": "postalcode"
  },
  "geometry": {"coordinates":[-0.163254,52.816784],"type":"Point"}
}
