{
  "type": "Feature",
  "properties": {
    "iso:country":"GB",
    "wof:name":"NG5 5QD",
    "wof:placetype":"postalcode"
},
  "geometry": {"coordinates":[-1.15351045073165,53.00729922805901],"type":"Point"}
}