{
  "type": "Feature",
  "properties": {
    "iso:country": "GB",
    "wof:name": "CM22 7FF",
    "wof:placetype": "postalcode"
  },
  "geometry": {"coordinates":[0.172993,51.839184],"type":"Point"}
}
