{
  "type": "Feature",
  "properties": {
    "iso:country":"GB",
    "wof:name":"NE66 3JB",
    "wof:placetype":"postalcode"
},
  "geometry": {"coordinates":[-1.61397657216142,55.43238717526381],"type":"Point"}
}