{
  "type": "Feature",
  "properties": {
    "iso:country": "GB",
    "wof:name": "NE66 3JB",
    "wof:placetype": "postalcode"
  },
  "geometry": {"coordinates":[-1.613977,55.432387],"type":"Point"}
}
