{
  "type": "Feature",
  "properties": {
    "iso:country":"GB",
    "wof:name":"PE8 6EW",
    "wof:placetype":"postalcode"
},
  "geometry": {"coordinates":[-0.43628651837913,52.60598418444861],"type":"Point"}
}