{
  "type": "Feature",
  "properties": {
    "iso:country":"GB",
    "wof:name":"BD6 3SQ",
    "wof:placetype":"postalcode"
},
  "geometry": {"coordinates":[-1.79694449537181,53.76810885590877],"type":"Point"}
}