{
  "type": "Feature",
  "properties": {
    "iso:country": "GB",
    "wof:name": "BD6 3SQ",
    "wof:placetype": "postalcode"
  },
  "geometry": {"coordinates":[-1.796944,53.768109],"type":"Point"}
}
