{
  "type": "Feature",
  "properties": {
    "iso:country":"GB",
    "wof:name":"BD8 0PN",
    "wof:placetype":"postalcode"
},
  "geometry": {"coordinates":[-1.81768032458743,53.7968407945696],"type":"Point"}
}