{
  "type": "Feature",
  "properties": {
    "date:inception_lower":"1991-09-01",
    "date:inception_upper":"1991-09-30",
    "iso:country":"GB",
    "wof:name":"BD8 0PN",
    "wof:placetype":"postalcode"
},
  "geometry": {"coordinates":[-1.81768,53.796841],"type":"Point"}
}