{
  "type": "Feature",
  "properties": {
    "date:inception_lower": "1980-01-01",
    "date:inception_upper": "1980-01-01",
    "iso:country": "GB",
    "wof:name": "N4 4NL",
    "wof:placetype": "postalcode"
  },
  "geometry": {"coordinates":[-0.106301,51.573368],"type":"Point"}
}
