{
  "type": "Feature",
  "properties": {
    "iso:country": "GB",
    "wof:name": "N4 4NL",
    "wof:placetype": "postalcode"
  },
  "geometry": {"coordinates":[-0.106367,51.573447],"type":"Point"}
}
