{
  "type": "Feature",
  "properties": {
    "iso:country":"GB",
    "wof:name":"L36 1UD",
    "wof:placetype":"postalcode"
},
  "geometry": {"coordinates":[-2.82366602430913,53.42100837400522],"type":"Point"}
}