{
  "type": "Feature",
  "properties": {
    "date:inception_lower": "1980-01-01",
    "date:inception_upper": "1980-01-01",
    "iso:country": "GB",
    "wof:name": "GL14 3HA",
    "wof:placetype": "postalcode"
  },
  "geometry": {"coordinates":[-2.507821,51.810954],"type":"Point"}
}
