{
  "type": "Feature",
  "properties": {
    "iso:country":"GB",
    "wof:name":"SE8 4SY",
    "wof:placetype":"postalcode"
},
  "geometry": {"coordinates":[-0.02534378546209,51.47495488298139],"type":"Point"}
}