{
  "type": "Feature",
  "properties": {
    "iso:country": "GB",
    "wof:name": "SE8 4SY",
    "wof:placetype": "postalcode"
  },
  "geometry": {"coordinates":[-0.025344,51.474955],"type":"Point"}
}
