{
  "type": "Feature",
  "properties": {
    "iso:country":"GB",
    "wof:name":"PH7 3AN",
    "wof:placetype":"postalcode"
},
  "geometry": {"coordinates":[-3.84051102239873,56.37495573420927],"type":"Point"}
}