{
  "type": "Feature",
  "properties": {
    "iso:country": "GB",
    "wof:name": "DN39 6TY",
    "wof:placetype": "postalcode"
  },
  "geometry": {"coordinates":[-0.29898,53.619245],"type":"Point"}
}
