{
  "type": "Feature",
  "properties": {
    "iso:country":"GB",
    "wof:name":"DN39 6TY",
    "wof:placetype":"postalcode"
},
  "geometry": {"coordinates":[-0.29898034705806,53.61924483495255],"type":"Point"}
}