{
  "type": "Feature",
  "properties": {
    "date:inception_lower": "1980-01-01",
    "date:inception_upper": "1980-01-01",
    "iso:country": "GB",
    "wof:name": "L4 2TA",
    "wof:placetype": "postalcode"
  },
  "geometry": {"coordinates":[-2.953337,53.43065],"type":"Point"}
}
