{
  "type": "Feature",
  "properties": {
    "iso:country":"GB",
    "wof:name":"L4 2TA",
    "wof:placetype":"postalcode"
},
  "geometry": {"coordinates":[-2.9533370414768,53.43065028594247],"type":"Point"}
}