{
  "type": "Feature",
  "properties": {
    "date:inception_lower": "1980-01-01",
    "date:inception_upper": "1980-01-01",
    "iso:country": "GB",
    "wof:name": "LS6 1RR",
    "wof:placetype": "postalcode"
  },
  "geometry": {"coordinates":[-1.572824,53.808263],"type":"Point"}
}
