{
  "type": "Feature",
  "properties": {
    "date:inception_lower": "1980-01-01",
    "date:inception_upper": "1980-01-01",
    "iso:country": "GB",
    "wof:name": "HA2 0XH",
    "wof:placetype": "postalcode"
  },
  "geometry": {"coordinates":[-0.365052,51.570908],"type":"Point"}
}
