{
  "type": "Feature",
  "properties": {
    "iso:country":"GB",
    "wof:name":"DN2 4SR",
    "wof:placetype":"postalcode"
},
  "geometry": {"coordinates":[-1.0993462509824,53.54489672893531],"type":"Point"}
}