{
  "type": "Feature",
  "properties": {
    "date:inception_lower": "1980-01-01",
    "date:inception_upper": "1980-01-01",
    "iso:country": "GB",
    "wof:name": "M19 3QB",
    "wof:placetype": "postalcode"
  },
  "geometry": {"coordinates":[-2.18981,53.444462],"type":"Point"}
}
