{
  "type": "Feature",
  "properties": {
    "iso:country":"GB",
    "wof:name":"M19 3QB",
    "wof:placetype":"postalcode"
},
  "geometry": {"coordinates":[-2.18854495535741,53.44426673961097],"type":"Point"}
}