{
  "type": "Feature",
  "properties": {
    "date:inception_lower": "1994-05-01",
    "date:inception_upper": "1994-05-01",
    "iso:country": "GB",
    "wof:name": "M7 4TA",
    "wof:placetype": "postalcode"
  },
  "geometry": {"coordinates":[-2.247392,53.505577],"type":"Point"}
}
