{
  "type": "Feature",
  "properties": {
    "iso:country":"GB",
    "wof:name":"M7 4TA",
    "wof:placetype":"postalcode"
},
  "geometry": {"coordinates":[-2.24739193558187,53.50557744752785],"type":"Point"}
}