{
  "type": "Feature",
  "properties": {
    "date:inception_lower":"1995-07-01",
    "date:inception_upper":"1995-07-31",
    "iso:country":"GB",
    "wof:name":"RG21 5NW",
    "wof:placetype":"postalcode"
},
  "geometry": {"coordinates":[-1.091556,51.273847],"type":"Point"}
}