{
  "type": "Feature",
  "properties": {
    "iso:country": "GB",
    "wof:name": "RG21 5NW",
    "wof:placetype": "postalcode"
  },
  "geometry": {"coordinates":[-1.091556,51.273847],"type":"Point"}
}
