{
  "type": "Feature",
  "properties": {
    "iso:country":"GB",
    "wof:name":"DG7 3TR",
    "wof:placetype":"postalcode"
},
  "geometry": {"coordinates":[-4.26454289975468,55.21414499172324],"type":"Point"}
}