{
  "type": "Feature",
  "properties": {
    "iso:country": "GB",
    "wof:name": "DG7 3TR",
    "wof:placetype": "postalcode"
  },
  "geometry": {"coordinates":[-4.264543,55.214145],"type":"Point"}
}
