{
  "type": "Feature",
  "properties": {
    "iso:country":"GB",
    "wof:name":"BB11 1PB",
    "wof:placetype":"postalcode"
},
  "geometry": {"coordinates":[-2.24525320590433,53.78984287746815],"type":"Point"}
}