{
  "type": "Feature",
  "properties": {
    "iso:country": "GB",
    "wof:name": "S3 7ES",
    "wof:placetype": "postalcode"
  },
  "geometry": {"coordinates":[-1.480079,53.38894],"type":"Point"}
}
