{
  "type": "Feature",
  "properties": {
    "iso:country":"GB",
    "wof:name":"S3 7ES",
    "wof:placetype":"postalcode"
},
  "geometry": {"coordinates":[-1.4800791652495,53.38894043629092],"type":"Point"}
}