{
  "type": "Feature",
  "properties": {
    "iso:country": "GB",
    "wof:name": "KY13 8ED",
    "wof:placetype": "postalcode"
  },
  "geometry": {"coordinates":[-3.427621,56.202966],"type":"Point"}
}
