{
  "type": "Feature",
  "properties": {
    "iso:country":"GB",
    "wof:name":"KY13 8ED",
    "wof:placetype":"postalcode"
},
  "geometry": {"coordinates":[-3.4276212169397,56.20296569819582],"type":"Point"}
}