{
  "type": "Feature",
  "properties": {
    "iso:country": "GB",
    "wof:name": "NR10 3NR",
    "wof:placetype": "postalcode"
  },
  "geometry": {"coordinates":[1.322523,52.687851],"type":"Point"}
}
