{
  "type": "Feature",
  "properties": {
    "iso:country":"GB",
    "wof:name":"NN6 9LH",
    "wof:placetype":"postalcode"
},
  "geometry": {"coordinates":[-0.9599450250395,52.3914315367196],"type":"Point"}
}