{
  "type": "Feature",
  "properties": {
    "iso:country": "GB",
    "wof:name": "NN6 9LH",
    "wof:placetype": "postalcode"
  },
  "geometry": {"coordinates":[-0.959945,52.391432],"type":"Point"}
}
