{
  "type": "Feature",
  "properties": {
    "iso:country":"GB",
    "wof:name":"M24 5JX",
    "wof:placetype":"postalcode"
},
  "geometry": {"coordinates":[-2.21522587279449,53.56372261120907],"type":"Point"}
}