{
  "type": "Feature",
  "properties": {
    "iso:country": "GB",
    "wof:name": "BD9 6RF",
    "wof:placetype": "postalcode"
  },
  "geometry": {"coordinates":[-1.795995,53.805125],"type":"Point"}
}
