{
  "type": "Feature",
  "properties": {
    "iso:country": "GB",
    "wof:name": "PE11 3TY",
    "wof:placetype": "postalcode"
  },
  "geometry": {"coordinates":[-0.141608,52.806695],"type":"Point"}
}
