{
  "type": "Feature",
  "properties": {
    "iso:country":"GB",
    "wof:name":"G78 1HS",
    "wof:placetype":"postalcode"
},
  "geometry": {"coordinates":[-4.39983594289521,55.80815068316048],"type":"Point"}
}