{
  "type": "Feature",
  "properties": {
    "date:inception_lower":"1986-04-01",
    "date:inception_upper":"1986-04-30",
    "iso:country":"GB",
    "wof:name":"E8 3BZ",
    "wof:placetype":"postalcode"
},
  "geometry": {"coordinates":[-0.068859,51.543844],"type":"Point"}
}