{
  "type": "Feature",
  "properties": {
    "date:inception_lower": "2017-11-01",
    "date:inception_upper": "2017-11-01",
    "iso:country": "GB",
    "wof:name": "PO7 6SZ",
    "wof:placetype": "postalcode"
  },
  "geometry": {"coordinates":[-1.059076,50.903304],"type":"Point"}
}
