{
  "type": "Feature",
  "properties": {
    "iso:country": "GB",
    "wof:name": "PE22 9DT",
    "wof:placetype": "postalcode"
  },
  "geometry": {"coordinates":[0.131722,53.064605],"type":"Point"}
}
