{
  "type": "Feature",
  "properties": {
    "iso:country":"GB",
    "wof:name":"PE22 9DT",
    "wof:placetype":"postalcode"
},
  "geometry": {"coordinates":[0.13166418001089,53.06385107525608],"type":"Point"}
}