{
  "type": "Feature",
  "properties": {
    "iso:country":"GB",
    "wof:name":"W13 9UL",
    "wof:placetype":"postalcode"
},
  "geometry": {"coordinates":[-0.32463833853084,51.49912659017782],"type":"Point"}
}