{
  "type": "Feature",
  "properties": {
    "iso:country": "GB",
    "wof:name": "W13 9UL",
    "wof:placetype": "postalcode"
  },
  "geometry": {"coordinates":[-0.324638,51.499127],"type":"Point"}
}
