{
  "type": "Feature",
  "properties": {
    "date:inception_lower": "2018-06-01",
    "date:inception_upper": "2018-06-01",
    "iso:country": "GB",
    "wof:name": "TF9 3GL",
    "wof:placetype": "postalcode"
  },
  "geometry": {"coordinates":[-2.499979,52.908979],"type":"Point"}
}
