{
  "type": "Feature",
  "properties": {
    "iso:country":"GB",
    "wof:name":"LS8 2DL",
    "wof:placetype":"postalcode"
},
  "geometry": {"coordinates":[-1.50669524995019,53.84413232802646],"type":"Point"}
}