{
  "type": "Feature",
  "properties": {
    "iso:country": "GB",
    "wof:name": "TF9 4AF",
    "wof:placetype": "postalcode"
  },
  "geometry": {"coordinates":[-2.455285,52.929088],"type":"Point"}
}
