{
  "type": "Feature",
  "properties": {
    "iso:country":"GB",
    "wof:name":"TF9 4AF",
    "wof:placetype":"postalcode"
},
  "geometry": {"coordinates":[-2.45174366444182,52.92756753279728],"type":"Point"}
}