{
  "type": "Feature",
  "properties": {
    "date:inception_lower": "1980-01-01",
    "date:inception_upper": "1980-01-01",
    "iso:country": "GB",
    "wof:name": "TF9 4AF",
    "wof:placetype": "postalcode"
  },
  "geometry": {"coordinates":[-2.451743,52.927583],"type":"Point"}
}
