{
  "type": "Feature",
  "properties": {
    "iso:country":"GB",
    "wof:name":"S41 7DQ",
    "wof:placetype":"postalcode"
},
  "geometry": {"coordinates":[-1.43356908748426,53.24969910892264],"type":"Point"}
}