{
  "type": "Feature",
  "properties": {
    "date:inception_lower": "1980-01-01",
    "date:inception_upper": "1980-01-01",
    "iso:country": "GB",
    "wof:name": "RM12 4NG",
    "wof:placetype": "postalcode"
  },
  "geometry": {"coordinates":[0.195216,51.54939],"type":"Point"}
}
