{
  "type": "Feature",
  "properties": {
    "date:inception_lower": "1993-08-01",
    "date:inception_upper": "1993-08-01",
    "iso:country": "GB",
    "wof:name": "NR18 9AQ",
    "wof:placetype": "postalcode"
  },
  "geometry": {"coordinates":[1.117297,52.564204],"type":"Point"}
}
