{
  "type": "Feature",
  "properties": {
    "iso:country": "GB",
    "wof:name": "RH13 8BN",
    "wof:placetype": "postalcode"
  },
  "geometry": {"coordinates":[-0.269401,50.991831],"type":"Point"}
}
