{
  "type": "Feature",
  "properties": {
    "iso:country":"GB",
    "wof:name":"OL14 7HP",
    "wof:placetype":"postalcode"
},
  "geometry": {"coordinates":[-2.15455859639113,53.7112320964445],"type":"Point"}
}