{
  "type": "Feature",
  "properties": {
    "iso:country": "GB",
    "wof:name": "OL14 7HP",
    "wof:placetype": "postalcode"
  },
  "geometry": {"coordinates":[-2.154559,53.711232],"type":"Point"}
}
