{
  "type": "Feature",
  "properties": {
    "iso:country":"GB",
    "wof:name":"LS22 7AD",
    "wof:placetype":"postalcode"
},
  "geometry": {"coordinates":[-1.37837892905247,53.93604073951946],"type":"Point"}
}