{
  "type": "Feature",
  "properties": {
    "iso:country":"GB",
    "wof:name":"PO35 5TH",
    "wof:placetype":"postalcode"
},
  "geometry": {"coordinates":[-1.07154553531049,50.68576841085629],"type":"Point"}
}