{
  "type": "Feature",
  "properties": {
    "date:inception_lower":"1998-06-01",
    "date:inception_upper":"1998-06-30",
    "iso:country":"GB",
    "wof:name":"W8 5SJ",
    "wof:placetype":"postalcode"
},
  "geometry": {"coordinates":[-0.192379,51.499492],"type":"Point"}
}