{
  "type": "Feature",
  "properties": {
    "iso:country": "GB",
    "wof:name": "WS13 8LB",
    "wof:placetype": "postalcode"
  },
  "geometry": {"coordinates":[-1.796151,52.688935],"type":"Point"}
}
