{
  "type": "Feature",
  "properties": {
    "date:inception_lower":"1995-07-01",
    "date:inception_upper":"1995-07-31",
    "iso:country":"GB",
    "wof:name":"WS13 8LB",
    "wof:placetype":"postalcode"
},
  "geometry": {"coordinates":[-1.796151,52.688935],"type":"Point"}
}