{
  "type": "Feature",
  "properties": {
    "iso:country":"GB",
    "wof:name":"PE31 8DD",
    "wof:placetype":"postalcode"
},
  "geometry": {"coordinates":[0.686894567339,52.96589478220177],"type":"Point"}
}