{
  "type": "Feature",
  "properties": {
    "date:inception_lower": "1980-01-01",
    "date:inception_upper": "1980-01-01",
    "iso:country": "GB",
    "wof:name": "PE31 8DD",
    "wof:placetype": "postalcode"
  },
  "geometry": {"coordinates":[0.686895,52.965895],"type":"Point"}
}
