{
  "type": "Feature",
  "properties": {
    "date:inception_lower": "1999-06-01",
    "date:inception_upper": "1999-06-01",
    "iso:country": "GB",
    "wof:name": "SR7 0PT",
    "wof:placetype": "postalcode"
  },
  "geometry": {"coordinates":[-1.371107,54.84915],"type":"Point"}
}
