{
  "type": "Feature",
  "properties": {
    "iso:country":"GB",
    "wof:name":"SR7 0PT",
    "wof:placetype":"postalcode"
},
  "geometry": {"coordinates":[-1.37109277975587,54.84914188285024],"type":"Point"}
}