{
  "type": "Feature",
  "properties": {
    "iso:country": "GB",
    "wof:name": "MK18 3BT",
    "wof:placetype": "postalcode"
  },
  "geometry": {"coordinates":[-0.886031,51.938635],"type":"Point"}
}
