{
  "type": "Feature",
  "properties": {
    "date:inception_lower":"2007-08-01",
    "date:inception_upper":"2007-08-31",
    "iso:country":"GB",
    "wof:name":"YO25 8PE",
    "wof:placetype":"postalcode"
},
  "geometry": {"coordinates":[-0.301911,53.912559],"type":"Point"}
}