{
  "type": "Feature",
  "properties": {
    "iso:country": "GB",
    "wof:name": "NG25 0FX",
    "wof:placetype": "postalcode"
  },
  "geometry": {"coordinates":[-0.950015,53.080975],"type":"Point"}
}
