{
  "type": "Feature",
  "properties": {
    "iso:country":"GB",
    "wof:name":"LL57 3PY",
    "wof:placetype":"postalcode"
},
  "geometry": {"coordinates":[-4.05473926416979,53.17330746185788],"type":"Point"}
}