{
  "type": "Feature",
  "properties": {
    "iso:country": "GB",
    "wof:name": "IP2 9JG",
    "wof:placetype": "postalcode"
  },
  "geometry": {"coordinates":[1.121026,52.037812],"type":"Point"}
}
