{
  "type": "Feature",
  "properties": {
    "iso:country":"GB",
    "wof:name":"IP2 9JG",
    "wof:placetype":"postalcode"
},
  "geometry": {"coordinates":[1.12102552908139,52.03781234716409],"type":"Point"}
}