{
  "type": "Feature",
  "properties": {
    "iso:country": "GB",
    "wof:name": "TD15 2BU",
    "wof:placetype": "postalcode"
  },
  "geometry": {"coordinates":[-2.016496,55.75313],"type":"Point"}
}
