{
  "type": "Feature",
  "properties": {
    "iso:country":"GB",
    "wof:name":"TD15 2BU",
    "wof:placetype":"postalcode"
},
  "geometry": {"coordinates":[-2.01649565560209,55.75313048415683],"type":"Point"}
}