{
  "type": "Feature",
  "properties": {
    "iso:country":"GB",
    "wof:name":"EH13 0LS",
    "wof:placetype":"postalcode"
},
  "geometry": {"coordinates":[-3.2693141494419,55.90839783724383],"type":"Point"}
}