{
  "type": "Feature",
  "properties": {
    "iso:country":"GB",
    "wof:name":"HR4 9YH",
    "wof:placetype":"postalcode"
},
  "geometry": {"coordinates":[-2.72241325429007,52.06001338569062],"type":"Point"}
}