{
  "type": "Feature",
  "properties": {
    "iso:country": "GB",
    "wof:name": "HR4 9YH",
    "wof:placetype": "postalcode"
  },
  "geometry": {"coordinates":[-2.722413,52.060013],"type":"Point"}
}
