{
  "type": "Feature",
  "properties": {
    "iso:country": "GB",
    "wof:name": "WV9 5BG",
    "wof:placetype": "postalcode"
  },
  "geometry": {"coordinates":[-2.181693,52.658466],"type":"Point"}
}
