{
  "type": "Feature",
  "properties": {
    "date:inception_lower": "1980-01-01",
    "date:inception_upper": "1980-01-01",
    "iso:country": "GB",
    "wof:name": "WV9 5BG",
    "wof:placetype": "postalcode"
  },
  "geometry": {"coordinates":[-2.181781,52.658475],"type":"Point"}
}
