{
  "type": "Feature",
  "properties": {
    "iso:country": "GB",
    "wof:name": "SO21 3BW",
    "wof:placetype": "postalcode"
  },
  "geometry": {"coordinates":[-1.223455,51.17528],"type":"Point"}
}
