{
  "type": "Feature",
  "properties": {
    "iso:country":"GB",
    "wof:name":"NE32 4PN",
    "wof:placetype":"postalcode"
},
  "geometry": {"coordinates":[-1.48432421480408,54.95476247566931],"type":"Point"}
}