{
  "type": "Feature",
  "properties": {
    "iso:country": "GB",
    "wof:name": "G41 4JF",
    "wof:placetype": "postalcode"
  },
  "geometry": {"coordinates":[-4.293206,55.840879],"type":"Point"}
}
