{
  "type": "Feature",
  "properties": {
    "iso:country":"GB",
    "wof:name":"LA1 1TJ",
    "wof:placetype":"postalcode"
},
  "geometry": {"coordinates":[-2.8055064477051,54.04813929176751],"type":"Point"}
}