{
  "type": "Feature",
  "properties": {
    "date:inception_lower":"1980-01-01",
    "date:inception_upper":"1980-01-31",
    "iso:country":"GB",
    "wof:name":"LA1 1TJ",
    "wof:placetype":"postalcode"
},
  "geometry": {"coordinates":[-2.805506,54.048139],"type":"Point"}
}