{
  "type": "Feature",
  "properties": {
    "iso:country":"GB",
    "wof:name":"BS28 4DE",
    "wof:placetype":"postalcode"
},
  "geometry": {"coordinates":[-2.80992301475237,51.22450715602124],"type":"Point"}
}