{
  "type": "Feature",
  "properties": {
    "iso:country": "GB",
    "wof:name": "BA22 8WD",
    "wof:placetype": "postalcode"
  },
  "geometry": {"coordinates":[-2.681573,51.012103],"type":"Point"}
}
