{
  "type": "Feature",
  "properties": {
    "iso:country":"GB",
    "wof:name":"BA22 8WD",
    "wof:placetype":"postalcode"
},
  "geometry": {"coordinates":[-2.6815731090318,51.01210253788667],"type":"Point"}
}