{
  "type": "Feature",
  "properties": {
    "iso:country":"GB",
    "wof:name":"WA8 8YQ",
    "wof:placetype":"postalcode"
},
  "geometry": {"coordinates":[-2.76513911192777,53.36866052494766],"type":"Point"}
}