{
  "type": "Feature",
  "properties": {
    "date:inception_lower":"1990-07-01",
    "date:inception_upper":"1990-07-31",
    "iso:country":"GB",
    "wof:name":"WA8 8YQ",
    "wof:placetype":"postalcode"
},
  "geometry": {"coordinates":[-2.765139,53.368661],"type":"Point"}
}