{
  "type": "Feature",
  "properties": {
    "iso:country":"GB",
    "wof:name":"PE11 4PJ",
    "wof:placetype":"postalcode"
},
  "geometry": {"coordinates":[-0.18436023176815,52.88394475632241],"type":"Point"}
}