{
  "type": "Feature",
  "properties": {
    "iso:country": "GB",
    "wof:name": "G46 6HA",
    "wof:placetype": "postalcode"
  },
  "geometry": {"coordinates":[-4.293045,55.806414],"type":"Point"}
}
