{
  "type": "Feature",
  "properties": {
    "date:inception_lower":"1980-01-01",
    "date:inception_upper":"1980-01-31",
    "iso:country":"GB",
    "wof:name":"BS8 1PN",
    "wof:placetype":"postalcode"
},
  "geometry": {"coordinates":[-2.603407,51.461322],"type":"Point"}
}