{
  "type": "Feature",
  "properties": {
    "iso:country":"GB",
    "wof:name":"N13 6AN",
    "wof:placetype":"postalcode"
},
  "geometry": {"coordinates":[-0.09605989689061,51.60907891215845],"type":"Point"}
}