{
  "type": "Feature",
  "properties": {
    "iso:country": "GB",
    "wof:name": "N13 6AN",
    "wof:placetype": "postalcode"
  },
  "geometry": {"coordinates":[-0.09606,51.609079],"type":"Point"}
}
