{
  "type": "Feature",
  "properties": {
    "iso:country": "GB",
    "wof:name": "PR9 0BU",
    "wof:placetype": "postalcode"
  },
  "geometry": {"coordinates":[-3.00632,53.64893],"type":"Point"}
}
