{
  "type": "Feature",
  "properties": {
    "date:inception_lower":"2006-04-01",
    "date:inception_upper":"2006-04-30",
    "iso:country":"GB",
    "wof:name":"PR9 0BU",
    "wof:placetype":"postalcode"
},
  "geometry": {"coordinates":[-3.00632,53.64893],"type":"Point"}
}