{
  "type": "Feature",
  "properties": {
    "iso:country":"GB",
    "wof:name":"PR9 0BU",
    "wof:placetype":"postalcode"
},
  "geometry": {"coordinates":[-3.00631955483085,53.64892984405447],"type":"Point"}
}