{
  "type": "Feature",
  "properties": {
    "date:inception_lower":"1980-01-01",
    "date:inception_upper":"1980-01-31",
    "iso:country":"GB",
    "wof:name":"CA28 6SG",
    "wof:placetype":"postalcode"
},
  "geometry": {"coordinates":[-3.569466,54.551173],"type":"Point"}
}