{
  "type": "Feature",
  "properties": {
    "iso:country":"GB",
    "wof:name":"CA28 6SG",
    "wof:placetype":"postalcode"
},
  "geometry": {"coordinates":[-3.56946615046805,54.5511727181899],"type":"Point"}
}