{
  "type": "Feature",
  "properties": {
    "date:inception_lower": "1997-12-01",
    "date:inception_upper": "1997-12-01",
    "iso:country": "GB",
    "wof:name": "BS34 7HL",
    "wof:placetype": "postalcode"
  },
  "geometry": {"coordinates":[-2.565914,51.512824],"type":"Point"}
}
