{
  "type": "Feature",
  "properties": {
    "date:inception_lower":"2009-10-01",
    "date:inception_upper":"2009-10-31",
    "iso:country":"GB",
    "wof:name":"NE27 0FB",
    "wof:placetype":"postalcode"
},
  "geometry": {"coordinates":[-1.531015,55.044365],"type":"Point"}
}