{
  "type": "Feature",
  "properties": {
    "iso:country": "GB",
    "wof:name": "NE27 0FB",
    "wof:placetype": "postalcode"
  },
  "geometry": {"coordinates":[-1.531015,55.044365],"type":"Point"}
}
