{
  "type": "Feature",
  "properties": {
    "date:inception_lower": "1998-06-01",
    "date:inception_upper": "1998-06-01",
    "iso:country": "GB",
    "wof:name": "YO32 5YZ",
    "wof:placetype": "postalcode"
  },
  "geometry": {"coordinates":[-1.03751,54.034423],"type":"Point"}
}
