{
  "type": "Feature",
  "properties": {
    "iso:country":"GB",
    "wof:name":"TR4 9JE",
    "wof:placetype":"postalcode"
},
  "geometry": {"coordinates":[-5.08585235705947,50.32483971083223],"type":"Point"}
}