{
  "type": "Feature",
  "properties": {
    "date:inception_lower": "1998-06-01",
    "date:inception_upper": "1998-06-01",
    "iso:country": "GB",
    "wof:name": "TR4 9JE",
    "wof:placetype": "postalcode"
  },
  "geometry": {"coordinates":[-5.085852,50.32484],"type":"Point"}
}
