{
  "type": "Feature",
  "properties": {
    "iso:country": "GB",
    "wof:name": "S61 2DJ",
    "wof:placetype": "postalcode"
  },
  "geometry": {"coordinates":[-1.41555,53.429172],"type":"Point"}
}
