{
  "type": "Feature",
  "properties": {
    "iso:country":"GB",
    "wof:name":"S61 2DJ",
    "wof:placetype":"postalcode"
},
  "geometry": {"coordinates":[-1.4155498005456,53.42917209328839],"type":"Point"}
}