{
  "type": "Feature",
  "properties": {
    "date:inception_lower":"1980-01-01",
    "date:inception_upper":"1980-01-31",
    "iso:country":"GB",
    "wof:name":"S61 2DJ",
    "wof:placetype":"postalcode"
},
  "geometry": {"coordinates":[-1.41555,53.429172],"type":"Point"}
}