{
  "type": "Feature",
  "properties": {
    "iso:country":"GB",
    "wof:name":"SY10 7BG",
    "wof:placetype":"postalcode"
},
  "geometry": {"coordinates":[-3.02054220872279,52.91767772475061],"type":"Point"}
}