{
  "type": "Feature",
  "properties": {
    "iso:country": "GB",
    "wof:name": "SY10 7BG",
    "wof:placetype": "postalcode"
  },
  "geometry": {"coordinates":[-3.020542,52.917678],"type":"Point"}
}
