{
  "type": "Feature",
  "properties": {
    "iso:country":"GB",
    "wof:name":"SW16 1NP",
    "wof:placetype":"postalcode"
},
  "geometry": {"coordinates":[-0.12820700664108,51.43686787290937],"type":"Point"}
}