{
  "type": "Feature",
  "properties": {
    "iso:country": "GB",
    "wof:name": "WA8 8RF",
    "wof:placetype": "postalcode"
  },
  "geometry": {"coordinates":[-2.772018,53.364266],"type":"Point"}
}
