{
  "type": "Feature",
  "properties": {
    "iso:country":"GB",
    "wof:name":"WA8 8RF",
    "wof:placetype":"postalcode"
},
  "geometry": {"coordinates":[-2.77201810042259,53.36426561815369],"type":"Point"}
}