{
  "type": "Feature",
  "properties": {
    "date:inception_lower": "1981-07-01",
    "date:inception_upper": "1981-07-01",
    "iso:country": "GB",
    "wof:name": "DD6 8NW",
    "wof:placetype": "postalcode"
  },
  "geometry": {"coordinates":[-2.956229,56.43201],"type":"Point"}
}
