{
  "type": "Feature",
  "properties": {
    "iso:country":"GB",
    "wof:name":"DD6 8NW",
    "wof:placetype":"postalcode"
},
  "geometry": {"coordinates":[-2.95622945849172,56.43201016679713],"type":"Point"}
}