{
  "type": "Feature",
  "properties": {
    "iso:country":"GB",
    "wof:name":"BS25 5RR",
    "wof:placetype":"postalcode"
},
  "geometry": {"coordinates":[-2.82795312893658,51.3321861537292],"type":"Point"}
}