{
  "type": "Feature",
  "properties": {
    "iso:country":"GB",
    "wof:name":"CA11 7BB",
    "wof:placetype":"postalcode"
},
  "geometry": {"coordinates":[-2.75214082727343,54.66200747514637],"type":"Point"}
}