{
  "type": "Feature",
  "properties": {
    "iso:country":"GB",
    "wof:name":"SG7 5QJ",
    "wof:placetype":"postalcode"
},
  "geometry": {"coordinates":[-0.15154429064084,52.04056868230582],"type":"Point"}
}