{
  "type": "Feature",
  "properties": {
    "iso:country": "GB",
    "wof:name": "WR3 7RE",
    "wof:placetype": "postalcode"
  },
  "geometry": {"coordinates":[-2.235374,52.224883],"type":"Point"}
}
