{
  "type": "Feature",
  "properties": {
    "date:inception_lower": "1980-01-01",
    "date:inception_upper": "1980-01-01",
    "iso:country": "GB",
    "wof:name": "WF2 8AF",
    "wof:placetype": "postalcode"
  },
  "geometry": {"coordinates":[-1.539683,53.674226],"type":"Point"}
}
