{
  "type": "Feature",
  "properties": {
    "iso:country":"GB",
    "wof:name":"LS8 3PZ",
    "wof:placetype":"postalcode"
},
  "geometry": {"coordinates":[-1.50666362604672,53.8131864817752],"type":"Point"}
}