{
  "type": "Feature",
  "properties": {
    "iso:country": "GB",
    "wof:name": "PE7 8QS",
    "wof:placetype": "postalcode"
  },
  "geometry": {"coordinates":[-0.257332,52.529932],"type":"Point"}
}
