{
  "type": "Feature",
  "properties": {
    "date:inception_lower": "1980-01-01",
    "date:inception_upper": "1980-01-01",
    "iso:country": "GB",
    "wof:name": "SR7 7QS",
    "wof:placetype": "postalcode"
  },
  "geometry": {"coordinates":[-1.336486,54.83209],"type":"Point"}
}
