{
  "type": "Feature",
  "properties": {
    "iso:country":"GB",
    "wof:name":"SR7 7QS",
    "wof:placetype":"postalcode"
},
  "geometry": {"coordinates":[-1.33654901761515,54.83206335102368],"type":"Point"}
}