{
  "type": "Feature",
  "properties": {
    "iso:country":"GB",
    "wof:name":"CH44 4DF",
    "wof:placetype":"postalcode"
},
  "geometry": {"coordinates":[-3.04585871045997,53.41171807705796],"type":"Point"}
}