{
  "type": "Feature",
  "properties": {
    "iso:country":"GB",
    "wof:name":"TW3 4DW",
    "wof:placetype":"postalcode"
},
  "geometry": {"coordinates":[-0.36676558828884,51.47371505381815],"type":"Point"}
}