{
  "type": "Feature",
  "properties": {
    "iso:country":"GB",
    "wof:name":"ST9 9PD",
    "wof:placetype":"postalcode"
},
  "geometry": {"coordinates":[-2.13666886847331,53.06086678385317],"type":"Point"}
}