{
  "type": "Feature",
  "properties": {
    "date:inception_lower":"2004-08-01",
    "date:inception_upper":"2004-08-31",
    "iso:country":"GB",
    "wof:name":"CF23 8RS",
    "wof:placetype":"postalcode"
},
  "geometry": {"coordinates":[-3.136236,51.540597],"type":"Point"}
}