{
  "type": "Feature",
  "properties": {
    "iso:country":"GB",
    "wof:name":"CF23 8RS",
    "wof:placetype":"postalcode"
},
  "geometry": {"coordinates":[-3.13618248427132,51.54057038089637],"type":"Point"}
}