{
  "type": "Feature",
  "properties": {
    "iso:country": "GB",
    "wof:name": "YO8 4BT",
    "wof:placetype": "postalcode"
  },
  "geometry": {"coordinates":[-1.07681,53.786821],"type":"Point"}
}
