{
  "type": "Feature",
  "properties": {
    "iso:country":"GB",
    "wof:name":"YO8 4BT",
    "wof:placetype":"postalcode"
},
  "geometry": {"coordinates":[-1.07681016352212,53.78682122064985],"type":"Point"}
}