{
  "type": "Feature",
  "properties": {
    "date:inception_lower":"1995-07-01",
    "date:inception_upper":"1995-07-31",
    "iso:country":"GB",
    "wof:name":"L9 6EF",
    "wof:placetype":"postalcode"
},
  "geometry": {"coordinates":[-2.924882,53.454524],"type":"Point"}
}