{
  "type": "Feature",
  "properties": {
    "iso:country":"GB",
    "wof:name":"LU2 7BZ",
    "wof:placetype":"postalcode"
},
  "geometry": {"coordinates":[-0.4233706862475,51.91336886203015],"type":"Point"}
}