{
  "type": "Feature",
  "properties": {
    "date:inception_lower": "1980-01-01",
    "date:inception_upper": "1980-01-01",
    "iso:country": "GB",
    "wof:name": "DA3 7PB",
    "wof:placetype": "postalcode"
  },
  "geometry": {"coordinates":[0.303091,51.396064],"type":"Point"}
}
