{
  "type": "Feature",
  "properties": {
    "iso:country": "GB",
    "wof:name": "IG10 3AD",
    "wof:placetype": "postalcode"
  },
  "geometry": {"coordinates":[0.061116,51.6377],"type":"Point"}
}
