{
  "type": "Feature",
  "properties": {
    "date:inception_lower": "2004-08-01",
    "date:inception_upper": "2004-08-01",
    "iso:country": "GB",
    "wof:name": "BN14 8PQ",
    "wof:placetype": "postalcode"
  },
  "geometry": {"coordinates":[-0.363623,50.830229],"type":"Point"}
}
