{
  "type": "Feature",
  "properties": {
    "date:inception_lower": "1985-10-01",
    "date:inception_upper": "1985-10-01",
    "iso:country": "GB",
    "wof:name": "S43 2QA",
    "wof:placetype": "postalcode"
  },
  "geometry": {"coordinates":[-1.402466,53.278897],"type":"Point"}
}
