{
  "type": "Feature",
  "properties": {
    "iso:country":"GB",
    "wof:name":"S43 2QA",
    "wof:placetype":"postalcode"
},
  "geometry": {"coordinates":[-1.40245359059214,53.27889604755548],"type":"Point"}
}