{
  "type": "Feature",
  "properties": {
    "iso:country":"GB",
    "wof:name":"SN8 1UG",
    "wof:placetype":"postalcode"
},
  "geometry": {"coordinates":[-1.74414284255418,51.41981553527292],"type":"Point"}
}