{
  "type": "Feature",
  "properties": {
    "date:inception_lower": "1990-07-01",
    "date:inception_upper": "1990-07-01",
    "iso:country": "GB",
    "wof:name": "SN8 1UG",
    "wof:placetype": "postalcode"
  },
  "geometry": {"coordinates":[-1.744143,51.419816],"type":"Point"}
}
