{
  "type": "Feature",
  "properties": {
    "iso:country":"GB",
    "wof:name":"WA1 3DQ",
    "wof:placetype":"postalcode"
},
  "geometry": {"coordinates":[-2.56944485900921,53.40232997755332],"type":"Point"}
}