{
  "type": "Feature",
  "properties": {
    "date:inception_lower": "1980-01-01",
    "date:inception_upper": "1980-01-01",
    "iso:country": "GB",
    "wof:name": "WA1 3DQ",
    "wof:placetype": "postalcode"
  },
  "geometry": {"coordinates":[-2.569445,53.40233],"type":"Point"}
}
