{
  "type": "Feature",
  "properties": {
    "iso:country":"GB",
    "wof:name":"HU17 7HT",
    "wof:placetype":"postalcode"
},
  "geometry": {"coordinates":[-0.44276230125743,53.85558216218602],"type":"Point"}
}