{
  "type": "Feature",
  "properties": {
    "iso:country": "GB",
    "wof:name": "TR2 4FR",
    "wof:placetype": "postalcode"
  },
  "geometry": {"coordinates":[-4.928599,50.321074],"type":"Point"}
}
