{
  "type": "Feature",
  "properties": {
    "date:inception_lower": "1980-01-01",
    "date:inception_upper": "1980-01-01",
    "iso:country": "GB",
    "wof:name": "MK18 3ES",
    "wof:placetype": "postalcode"
  },
  "geometry": {"coordinates":[-0.881425,51.947196],"type":"Point"}
}
