{
  "type": "Feature",
  "properties": {
    "iso:country": "GB",
    "wof:name": "MK18 3ES",
    "wof:placetype": "postalcode"
  },
  "geometry": {"coordinates":[-0.881425,51.947196],"type":"Point"}
}
