{
  "type": "Feature",
  "properties": {
    "iso:country":"GB",
    "wof:name":"EX32 0QS",
    "wof:placetype":"postalcode"
},
  "geometry": {"coordinates":[-3.96726691963939,51.05533217922439],"type":"Point"}
}