{
  "type": "Feature",
  "properties": {
    "iso:country":"GB",
    "wof:name":"LU4 9WT",
    "wof:placetype":"postalcode"
},
  "geometry": {"coordinates":[-0.46411507748958,51.8970213492238],"type":"Point"}
}