{
  "type": "Feature",
  "properties": {
    "date:inception_lower": "2004-11-01",
    "date:inception_upper": "2004-11-01",
    "iso:country": "GB",
    "wof:name": "ME13 7JN",
    "wof:placetype": "postalcode"
  },
  "geometry": {"coordinates":[0.888585,51.315955],"type":"Point"}
}
