{
  "type": "Feature",
  "properties": {
    "date:inception_lower":"2013-03-01",
    "date:inception_upper":"2013-03-31",
    "iso:country":"GB",
    "wof:name":"WN2 4AU",
    "wof:placetype":"postalcode"
},
  "geometry": {"coordinates":[-2.547481,53.52839],"type":"Point"}
}