{
  "type": "Feature",
  "properties": {
    "iso:country":"GB",
    "wof:name":"NE9 6PG",
    "wof:placetype":"postalcode"
},
  "geometry": {"coordinates":[-1.59479622637911,54.9193250979406],"type":"Point"}
}