{
  "type": "Feature",
  "properties": {
    "date:inception_lower":"2002-06-01",
    "date:inception_upper":"2002-06-30",
    "iso:country":"GB",
    "wof:name":"N9 0HF",
    "wof:placetype":"postalcode"
},
  "geometry": {"coordinates":[-0.044508,51.623339],"type":"Point"}
}