{
  "type": "Feature",
  "properties": {
    "iso:country": "GB",
    "wof:name": "N9 0HF",
    "wof:placetype": "postalcode"
  },
  "geometry": {"coordinates":[-0.044508,51.623339],"type":"Point"}
}
