{
  "type": "Feature",
  "properties": {
    "iso:country":"GB",
    "wof:name":"SO24 9DU",
    "wof:placetype":"postalcode"
},
  "geometry": {"coordinates":[-1.16045109873709,51.10302447972459],"type":"Point"}
}