{
  "type": "Feature",
  "properties": {
    "iso:country": "GB",
    "wof:name": "SO24 9DU",
    "wof:placetype": "postalcode"
  },
  "geometry": {"coordinates":[-1.160451,51.103024],"type":"Point"}
}
