{
  "type": "Feature",
  "properties": {
    "iso:country": "GB",
    "wof:name": "DN16 3AT",
    "wof:placetype": "postalcode"
  },
  "geometry": {"coordinates":[-0.632059,53.564889],"type":"Point"}
}
