{
  "type": "Feature",
  "properties": {
    "date:inception_lower": "1980-01-01",
    "date:inception_upper": "1980-01-01",
    "iso:country": "GB",
    "wof:name": "DN16 3AT",
    "wof:placetype": "postalcode"
  },
  "geometry": {"coordinates":[-0.632059,53.564889],"type":"Point"}
}
