{
  "type": "Feature",
  "properties": {
    "iso:country": "GB",
    "wof:name": "NG10 3RS",
    "wof:placetype": "postalcode"
  },
  "geometry": {"coordinates":[-1.298685,52.89397],"type":"Point"}
}
