{
  "type": "Feature",
  "properties": {
    "iso:country":"GB",
    "wof:name":"NG10 3RS",
    "wof:placetype":"postalcode"
},
  "geometry": {"coordinates":[-1.2986850065718,52.8939701128275],"type":"Point"}
}