{
  "type": "Feature",
  "properties": {
    "iso:country":"GB",
    "wof:name":"NW3 2QE",
    "wof:placetype":"postalcode"
},
  "geometry": {"coordinates":[-0.1655833150929,51.5546580428345],"type":"Point"}
}