{
  "type": "Feature",
  "properties": {
    "iso:country":"GB",
    "wof:name":"WD6 5LB",
    "wof:placetype":"postalcode"
},
  "geometry": {"coordinates":[-0.27337427744466,51.67359723244919],"type":"Point"}
}