{
  "type": "Feature",
  "properties": {
    "date:inception_lower": "1980-01-01",
    "date:inception_upper": "1980-01-01",
    "iso:country": "GB",
    "wof:name": "HR9 7SL",
    "wof:placetype": "postalcode"
  },
  "geometry": {"coordinates":[-2.472492,51.937604],"type":"Point"}
}
