{
  "type": "Feature",
  "properties": {
    "iso:country":"GB",
    "wof:name":"HR9 7SL",
    "wof:placetype":"postalcode"
},
  "geometry": {"coordinates":[-2.47249239431333,51.93760384700663],"type":"Point"}
}