{
  "type": "Feature",
  "properties": {
    "iso:country": "GB",
    "wof:name": "TN25 6PB",
    "wof:placetype": "postalcode"
  },
  "geometry": {"coordinates":[0.931409,51.122104],"type":"Point"}
}
