{
  "type": "Feature",
  "properties": {
    "iso:country":"GB",
    "wof:name":"TN25 6PB",
    "wof:placetype":"postalcode"
},
  "geometry": {"coordinates":[0.93140892514207,51.12210371843035],"type":"Point"}
}