{
  "type": "Feature",
  "properties": {
    "iso:country":"GB",
    "wof:name":"WS11 8ZJ",
    "wof:placetype":"postalcode"
},
  "geometry": {"coordinates":[-2.02845296800052,52.69186624172153],"type":"Point"}
}