{
  "type": "Feature",
  "properties": {
    "iso:country":"GB",
    "wof:name":"BS5 6UA",
    "wof:placetype":"postalcode"
},
  "geometry": {"coordinates":[-2.56463397421682,51.47921979490644],"type":"Point"}
}