{
  "type": "Feature",
  "properties": {
    "iso:country": "GB",
    "wof:name": "PE11 4BX",
    "wof:placetype": "postalcode"
  },
  "geometry": {"coordinates":[-0.124864,52.843097],"type":"Point"}
}
