{
  "type": "Feature",
  "properties": {
    "iso:country":"GB",
    "wof:name":"ML5 4PT",
    "wof:placetype":"postalcode"
},
  "geometry": {"coordinates":[-3.99846565419257,55.8534805832028],"type":"Point"}
}