{
  "type": "Feature",
  "properties": {
    "iso:country":"GB",
    "wof:name":"TR14 7AS",
    "wof:placetype":"postalcode"
},
  "geometry": {"coordinates":[-5.29125592031602,50.20961057867277],"type":"Point"}
}