{
  "type": "Feature",
  "properties": {
    "iso:country": "GB",
    "wof:name": "L1 8BJ",
    "wof:placetype": "postalcode"
  },
  "geometry": {"coordinates":[-2.987648,53.403799],"type":"Point"}
}
