{
  "type": "Feature",
  "properties": {
    "date:inception_lower": "2024-06-01",
    "date:inception_upper": "2024-06-01",
    "iso:country": "GB",
    "wof:name": "SN15 2GB",
    "wof:placetype": "postalcode"
  },
  "geometry": {"coordinates":[-2.131883,51.441706],"type":"Point"}
}
