{
  "type": "Feature",
  "properties": {
    "iso:country":"GB",
    "wof:name":"SP7 0NF",
    "wof:placetype":"postalcode"
},
  "geometry": {"coordinates":[-2.18027960652081,50.96725557925068],"type":"Point"}
}