{
  "type": "Feature",
  "properties": {
    "iso:country": "GB",
    "wof:name": "SP7 0NF",
    "wof:placetype": "postalcode"
  },
  "geometry": {"coordinates":[-2.18028,50.967256],"type":"Point"}
}
