{
  "type": "Feature",
  "properties": {
    "date:inception_lower":"1981-06-01",
    "date:inception_upper":"1981-06-30",
    "iso:country":"GB",
    "wof:name":"LU2 8QQ",
    "wof:placetype":"postalcode"
},
  "geometry": {"coordinates":[-0.385187,51.896423],"type":"Point"}
}