{
  "type": "Feature",
  "properties": {
    "iso:country": "GB",
    "wof:name": "LU2 8QQ",
    "wof:placetype": "postalcode"
  },
  "geometry": {"coordinates":[-0.385187,51.896423],"type":"Point"}
}
