{
  "type": "Feature",
  "properties": {
    "iso:country": "GB",
    "wof:name": "GL51 8AJ",
    "wof:placetype": "postalcode"
  },
  "geometry": {"coordinates":[-2.099886,51.902294],"type":"Point"}
}
