{
  "type": "Feature",
  "properties": {
    "iso:country":"GB",
    "wof:name":"GL51 8AJ",
    "wof:placetype":"postalcode"
},
  "geometry": {"coordinates":[-2.09983421048859,51.90225048932493],"type":"Point"}
}