{
  "type": "Feature",
  "properties": {
    "iso:country":"GB",
    "wof:name":"ML2 9PL",
    "wof:placetype":"postalcode"
},
  "geometry": {"coordinates":[-3.8436557319497,55.77454190599136],"type":"Point"}
}