{
  "type": "Feature",
  "properties": {
    "iso:country": "GB",
    "wof:name": "ML2 9PL",
    "wof:placetype": "postalcode"
  },
  "geometry": {"coordinates":[-3.843656,55.774542],"type":"Point"}
}
