{
  "type": "Feature",
  "properties": {
    "date:inception_lower": "1980-01-01",
    "date:inception_upper": "1980-01-01",
    "iso:country": "GB",
    "wof:name": "FY7 7AA",
    "wof:placetype": "postalcode"
  },
  "geometry": {"coordinates":[-3.023538,53.92453],"type":"Point"}
}
