{
  "type": "Feature",
  "properties": {
    "iso:country": "GB",
    "wof:name": "PL22 0AD",
    "wof:placetype": "postalcode"
  },
  "geometry": {"coordinates":[-4.670809,50.406948],"type":"Point"}
}
