{
  "type": "Feature",
  "properties": {
    "iso:country":"GB",
    "wof:name":"PL22 0AD",
    "wof:placetype":"postalcode"
},
  "geometry": {"coordinates":[-4.67080875004075,50.40694796288315],"type":"Point"}
}