{
  "type": "Feature",
  "properties": {
    "iso:country":"GB",
    "wof:name":"SA32 8RT",
    "wof:placetype":"postalcode"
},
  "geometry": {"coordinates":[-4.09942856561409,51.88865717307161],"type":"Point"}
}