{
  "type": "Feature",
  "properties": {
    "date:inception_lower":"1995-01-01",
    "date:inception_upper":"1995-01-31",
    "iso:country":"GB",
    "wof:name":"SA32 8RT",
    "wof:placetype":"postalcode"
},
  "geometry": {"coordinates":[-4.099429,51.888657],"type":"Point"}
}