{
  "type": "Feature",
  "properties": {
    "date:inception_lower": "1980-01-01",
    "date:inception_upper": "1980-01-01",
    "iso:country": "GB",
    "wof:name": "KA27 8QA",
    "wof:placetype": "postalcode"
  },
  "geometry": {"coordinates":[-5.095989,55.499788],"type":"Point"}
}
