{
  "type": "Feature",
  "properties": {
    "iso:country":"GB",
    "wof:name":"KA27 8QA",
    "wof:placetype":"postalcode"
},
  "geometry": {"coordinates":[-5.09598893954721,55.49978844589399],"type":"Point"}
}