{
  "type": "Feature",
  "properties": {
    "date:inception_lower": "1980-01-01",
    "date:inception_upper": "1980-01-01",
    "iso:country": "GB",
    "wof:name": "KA27 8QA",
    "wof:placetype": "postalcode"
  },
  "geometry": {"coordinates":[-5.096345,55.49985],"type":"Point"}
}
