{
  "type": "Feature",
  "properties": {
    "iso:country":"GB",
    "wof:name":"SA16 0JD",
    "wof:placetype":"postalcode"
},
  "geometry": {"coordinates":[-4.29766997545781,51.71246239149806],"type":"Point"}
}