{
  "type": "Feature",
  "properties": {
    "iso:country":"GB",
    "wof:name":"KT2 6EL",
    "wof:placetype":"postalcode"
},
  "geometry": {"coordinates":[-0.29930326082845,51.41527639981517],"type":"Point"}
}