{
  "type": "Feature",
  "properties": {
    "iso:country":"GB",
    "wof:name":"PL27 6ER",
    "wof:placetype":"postalcode"
},
  "geometry": {"coordinates":[-4.81552002987679,50.55448887371491],"type":"Point"}
}