{
  "type": "Feature",
  "properties": {
    "iso:country": "GB",
    "wof:name": "PL27 6ER",
    "wof:placetype": "postalcode"
  },
  "geometry": {"coordinates":[-4.81552,50.554489],"type":"Point"}
}
