{
  "type": "Feature",
  "properties": {
    "date:inception_lower": "2013-09-01",
    "date:inception_upper": "2013-09-01",
    "iso:country": "GB",
    "wof:name": "WD17 3EY",
    "wof:placetype": "postalcode"
  },
  "geometry": {"coordinates":[-0.40592,51.660694],"type":"Point"}
}
