{
  "type": "Feature",
  "properties": {
    "iso:country": "GB",
    "wof:name": "WD17 3EY",
    "wof:placetype": "postalcode"
  },
  "geometry": {"coordinates":[-0.406236,51.660566],"type":"Point"}
}
