{
  "type": "Feature",
  "properties": {
    "iso:country":"GB",
    "wof:name":"BN41 1TA",
    "wof:placetype":"postalcode"
},
  "geometry": {"coordinates":[-0.21788641883552,50.83878700687742],"type":"Point"}
}