{
  "type": "Feature",
  "properties": {
    "date:inception_lower":"1990-07-01",
    "date:inception_upper":"1990-07-31",
    "iso:country":"GB",
    "wof:name":"DH1 1TN",
    "wof:placetype":"postalcode"
},
  "geometry": {"coordinates":[-1.535076,54.791881],"type":"Point"}
}