{
  "type": "Feature",
  "properties": {
    "iso:country":"GB",
    "wof:name":"DH1 1TN",
    "wof:placetype":"postalcode"
},
  "geometry": {"coordinates":[-1.53625997005965,54.79170583921633],"type":"Point"}
}