{
  "type": "Feature",
  "properties": {
    "iso:country":"GB",
    "wof:name":"W1T 1QZ",
    "wof:placetype":"postalcode"
},
  "geometry": {"coordinates":[-0.13622660427892,51.51869307351785],"type":"Point"}
}