{
  "type": "Feature",
  "properties": {
    "iso:country":"GB",
    "wof:name":"SR2 8PR",
    "wof:placetype":"postalcode"
},
  "geometry": {"coordinates":[-1.36718076172752,54.89212212096452],"type":"Point"}
}