{
  "type": "Feature",
  "properties": {
    "date:inception_lower": "1980-01-01",
    "date:inception_upper": "1980-01-01",
    "iso:country": "GB",
    "wof:name": "LE15 7HG",
    "wof:placetype": "postalcode"
  },
  "geometry": {"coordinates":[-0.765395,52.722656],"type":"Point"}
}
