{
  "type": "Feature",
  "properties": {
    "iso:country":"GB",
    "wof:name":"LE15 7HG",
    "wof:placetype":"postalcode"
},
  "geometry": {"coordinates":[-0.76486776553766,52.72173124829303],"type":"Point"}
}