{
  "type": "Feature",
  "properties": {
    "date:inception_lower": "1980-01-01",
    "date:inception_upper": "1980-01-01",
    "iso:country": "GB",
    "wof:name": "N10 2AS",
    "wof:placetype": "postalcode"
  },
  "geometry": {"coordinates":[-0.136101,51.594803],"type":"Point"}
}
