{
  "type": "Feature",
  "properties": {
    "iso:country": "GB",
    "wof:name": "M19 3FP",
    "wof:placetype": "postalcode"
  },
  "geometry": {"coordinates":[-2.183837,53.448813],"type":"Point"}
}
