{
  "type": "Feature",
  "properties": {
    "iso:country":"GB",
    "wof:name":"M19 3FP",
    "wof:placetype":"postalcode"
},
  "geometry": {"coordinates":[-2.18383721464078,53.44881327921946],"type":"Point"}
}