{
  "type": "Feature",
  "properties": {
    "iso:country":"GB",
    "wof:name":"NE46 3JJ",
    "wof:placetype":"postalcode"
},
  "geometry": {"coordinates":[-2.11553583750996,54.97184000881266],"type":"Point"}
}