{
  "type": "Feature",
  "properties": {
    "date:inception_lower": "2024-04-01",
    "date:inception_upper": "2024-04-01",
    "iso:country": "GB",
    "wof:name": "ME5 7FN",
    "wof:placetype": "postalcode"
  },
  "geometry": {"coordinates":[0.544163,51.359698],"type":"Point"}
}
