{
  "type": "Feature",
  "properties": {
    "date:inception_lower": "1993-08-01",
    "date:inception_upper": "1993-08-01",
    "iso:country": "GB",
    "wof:name": "KT12 2LN",
    "wof:placetype": "postalcode"
  },
  "geometry": {"coordinates":[-0.417388,51.39391],"type":"Point"}
}
