{
  "type": "Feature",
  "properties": {
    "iso:country":"GB",
    "wof:name":"LE9 4DS",
    "wof:placetype":"postalcode"
},
  "geometry": {"coordinates":[-1.280237611199,52.55486447303517],"type":"Point"}
}