{
  "type": "Feature",
  "properties": {
    "iso:country":"GB",
    "wof:name":"HR9 5QY",
    "wof:placetype":"postalcode"
},
  "geometry": {"coordinates":[-2.57981080693381,51.86182471904048],"type":"Point"}
}