{
  "type": "Feature",
  "properties": {
    "iso:country": "GB",
    "wof:name": "HR9 5QY",
    "wof:placetype": "postalcode"
  },
  "geometry": {"coordinates":[-2.579811,51.861825],"type":"Point"}
}
