{
  "type": "Feature",
  "properties": {
    "date:inception_lower": "2021-06-01",
    "date:inception_upper": "2021-06-01",
    "iso:country": "GB",
    "wof:name": "CO7 8GP",
    "wof:placetype": "postalcode"
  },
  "geometry": {"coordinates":[0.99631,51.857799],"type":"Point"}
}
