{
  "type": "Feature",
  "properties": {
    "iso:country":"GB",
    "wof:name":"LA11 7EL",
    "wof:placetype":"postalcode"
},
  "geometry": {"coordinates":[-2.92353455617759,54.18347437643946],"type":"Point"}
}