{
  "type": "Feature",
  "properties": {
    "iso:country":"GB",
    "wof:name":"TN23 3QB",
    "wof:placetype":"postalcode"
},
  "geometry": {"coordinates":[0.87158070493617,51.11839938498994],"type":"Point"}
}