{
  "type": "Feature",
  "properties": {
    "iso:country": "GB",
    "wof:name": "SY15 6PB",
    "wof:placetype": "postalcode"
  },
  "geometry": {"coordinates":[-3.150346,52.560297],"type":"Point"}
}
