{
  "type": "Feature",
  "properties": {
    "iso:country":"GB",
    "wof:name":"SY15 6PB",
    "wof:placetype":"postalcode"
},
  "geometry": {"coordinates":[-3.15034568828801,52.56029693194503],"type":"Point"}
}