{
  "type": "Feature",
  "properties": {
    "iso:country":"GB",
    "wof:name":"CH2 2BY",
    "wof:placetype":"postalcode"
},
  "geometry": {"coordinates":[-2.88961040306906,53.20693868906736],"type":"Point"}
}