{
  "type": "Feature",
  "properties": {
    "date:inception_lower": "2022-06-01",
    "date:inception_upper": "2022-06-01",
    "iso:country": "GB",
    "wof:name": "NP19 0QE",
    "wof:placetype": "postalcode"
  },
  "geometry": {"coordinates":[-2.984204,51.585205],"type":"Point"}
}
