{
  "type": "Feature",
  "properties": {
    "iso:country": "GB",
    "wof:name": "RG19 8LH",
    "wof:placetype": "postalcode"
  },
  "geometry": {"coordinates":[-1.251692,51.353362],"type":"Point"}
}
