{
  "type": "Feature",
  "properties": {
    "iso:country":"GB",
    "wof:name":"MK3 7TH",
    "wof:placetype":"postalcode"
},
  "geometry": {"coordinates":[-0.77066358770337,51.99806985740523],"type":"Point"}
}