{
  "type": "Feature",
  "properties": {
    "iso:country":"GB",
    "wof:name":"DG1 4HE",
    "wof:placetype":"postalcode"
},
  "geometry": {"coordinates":[-3.58545434666031,55.06327508359067],"type":"Point"}
}