{
  "type": "Feature",
  "properties": {
    "iso:country": "GB",
    "wof:name": "DG1 4HE",
    "wof:placetype": "postalcode"
  },
  "geometry": {"coordinates":[-3.585454,55.063275],"type":"Point"}
}
