{
  "type": "Feature",
  "properties": {
    "iso:country":"GB",
    "wof:name":"PR9 7NE",
    "wof:placetype":"postalcode"
},
  "geometry": {"coordinates":[-2.963418679902,53.65908036328576],"type":"Point"}
}