{
  "type": "Feature",
  "properties": {
    "iso:country":"GB",
    "wof:name":"S72 7FL",
    "wof:placetype":"postalcode"
},
  "geometry": {"coordinates":[-1.37857174943878,53.57764722026834],"type":"Point"}
}