{
  "type": "Feature",
  "properties": {
    "iso:country": "GB",
    "wof:name": "S72 7FL",
    "wof:placetype": "postalcode"
  },
  "geometry": {"coordinates":[-1.378572,53.577647],"type":"Point"}
}
