{
  "type": "Feature",
  "properties": {
    "iso:country":"GB",
    "wof:name":"KY7 6EY",
    "wof:placetype":"postalcode"
},
  "geometry": {"coordinates":[-3.13269370673698,56.20282048570908],"type":"Point"}
}