{
  "type": "Feature",
  "properties": {
    "iso:country": "GB",
    "wof:name": "TS23 3YF",
    "wof:placetype": "postalcode"
  },
  "geometry": {"coordinates":[-1.279031,54.62619],"type":"Point"}
}
