{
  "type": "Feature",
  "properties": {
    "iso:country":"GB",
    "wof:name":"TS23 3YF",
    "wof:placetype":"postalcode"
},
  "geometry": {"coordinates":[-1.27903081310361,54.62618958344876],"type":"Point"}
}