{
  "type": "Feature",
  "properties": {
    "date:inception_lower":"1981-06-01",
    "date:inception_upper":"1981-06-30",
    "iso:country":"GB",
    "wof:name":"LE4 0RU",
    "wof:placetype":"postalcode"
},
  "geometry": {"coordinates":[-1.153826,52.661837],"type":"Point"}
}