{
  "type": "Feature",
  "properties": {
    "iso:country":"GB",
    "wof:name":"LE4 0RU",
    "wof:placetype":"postalcode"
},
  "geometry": {"coordinates":[-1.15382573571271,52.6618370552435],"type":"Point"}
}