{
  "type": "Feature",
  "properties": {
    "iso:country":"GB",
    "wof:name":"CT12 6FH",
    "wof:placetype":"postalcode"
},
  "geometry": {"coordinates":[1.39204701928349,51.34584513144505],"type":"Point"}
}