{
  "type": "Feature",
  "properties": {
    "iso:country": "GB",
    "wof:name": "CT12 6FH",
    "wof:placetype": "postalcode"
  },
  "geometry": {"coordinates":[1.389921,51.35035],"type":"Point"}
}
