{
  "type": "Feature",
  "properties": {
    "iso:country":"GB",
    "wof:name":"CM0 8RA",
    "wof:placetype":"postalcode"
},
  "geometry": {"coordinates":[0.81996715762682,51.63527631149014],"type":"Point"}
}