{
  "type": "Feature",
  "properties": {
    "iso:country":"GB",
    "wof:name":"SS16 4LH",
    "wof:placetype":"postalcode"
},
  "geometry": {"coordinates":[0.48877115084461,51.56130617755187],"type":"Point"}
}