{
  "type": "Feature",
  "properties": {
    "iso:country": "GB",
    "wof:name": "NG6 9JW",
    "wof:placetype": "postalcode"
  },
  "geometry": {"coordinates":[-1.179102,52.995361],"type":"Point"}
}
