{
  "type": "Feature",
  "properties": {
    "iso:country":"GB",
    "wof:name":"NN18 8DL",
    "wof:placetype":"postalcode"
},
  "geometry": {"coordinates":[-0.69588193447859,52.48367368199546],"type":"Point"}
}