{
  "type": "Feature",
  "properties": {
    "iso:country":"GB",
    "wof:name":"BD22 9SF",
    "wof:placetype":"postalcode"
},
  "geometry": {"coordinates":[-1.95338211452636,53.81468525420097],"type":"Point"}
}