{
  "type": "Feature",
  "properties": {
    "date:inception_lower":"1990-07-01",
    "date:inception_upper":"1990-07-31",
    "iso:country":"GB",
    "wof:name":"BD22 9SF",
    "wof:placetype":"postalcode"
},
  "geometry": {"coordinates":[-1.953382,53.814685],"type":"Point"}
}