{
  "type": "Feature",
  "properties": {
    "iso:country":"GB",
    "wof:name":"SE28 8SE",
    "wof:placetype":"postalcode"
},
  "geometry": {"coordinates":[0.10817695864405,51.50432976880513],"type":"Point"}
}