{
  "type": "Feature",
  "properties": {
    "iso:country":"GB",
    "wof:name":"RH5 5LS",
    "wof:placetype":"postalcode"
},
  "geometry": {"coordinates":[-0.34768130203194,51.15311450867725],"type":"Point"}
}