{
  "type": "Feature",
  "properties": {
    "iso:country": "GB",
    "wof:name": "RH5 5LS",
    "wof:placetype": "postalcode"
  },
  "geometry": {"coordinates":[-0.347285,51.153483],"type":"Point"}
}
