{
  "type": "Feature",
  "properties": {
    "iso:country": "GB",
    "wof:name": "RM3 8JH",
    "wof:placetype": "postalcode"
  },
  "geometry": {"coordinates":[0.216898,51.596924],"type":"Point"}
}
