{
  "type": "Feature",
  "properties": {
    "date:inception_lower": "1988-03-01",
    "date:inception_upper": "1988-03-01",
    "iso:country": "GB",
    "wof:name": "RM3 8JH",
    "wof:placetype": "postalcode"
  },
  "geometry": {"coordinates":[0.216898,51.596924],"type":"Point"}
}
