{
  "type": "Feature",
  "properties": {
    "iso:country":"GB",
    "wof:name":"RM3 8JH",
    "wof:placetype":"postalcode"
},
  "geometry": {"coordinates":[0.21691593011989,51.59693878697051],"type":"Point"}
}