{
  "type": "Feature",
  "properties": {
    "iso:country":"GB",
    "wof:name":"BR6 0SB",
    "wof:placetype":"postalcode"
},
  "geometry": {"coordinates":[0.08884299814598,51.38395535969079],"type":"Point"}
}