{
  "type": "Feature",
  "properties": {
    "iso:country":"GB",
    "wof:name":"RG7 1DT",
    "wof:placetype":"postalcode"
},
  "geometry": {"coordinates":[-0.96998354217884,51.39261454728341],"type":"Point"}
}