{
  "type": "Feature",
  "properties": {
    "iso:country":"GB",
    "wof:name":"SW18 3PW",
    "wof:placetype":"postalcode"
},
  "geometry": {"coordinates":[-0.18100119225452,51.43928172706336],"type":"Point"}
}