{
  "type": "Feature",
  "properties": {
    "date:inception_lower":"1980-01-01",
    "date:inception_upper":"1980-01-31",
    "iso:country":"GB",
    "wof:name":"SW18 3PW",
    "wof:placetype":"postalcode"
},
  "geometry": {"coordinates":[-0.181001,51.439282],"type":"Point"}
}