{
  "type": "Feature",
  "properties": {
    "iso:country":"GB",
    "wof:name":"IG6 2GX",
    "wof:placetype":"postalcode"
},
  "geometry": {"coordinates":[0.07774025758067,51.59542071185836],"type":"Point"}
}