{
  "type": "Feature",
  "properties": {
    "iso:country": "GB",
    "wof:name": "IG6 2GX",
    "wof:placetype": "postalcode"
  },
  "geometry": {"coordinates":[0.07774,51.595421],"type":"Point"}
}
