{
  "type": "Feature",
  "properties": {
    "iso:country": "GB",
    "wof:name": "SY5 7LH",
    "wof:placetype": "postalcode"
  },
  "geometry": {"coordinates":[-2.770873,52.623103],"type":"Point"}
}
