{
  "type": "Feature",
  "properties": {
    "date:inception_lower":"1980-01-01",
    "date:inception_upper":"1980-01-31",
    "iso:country":"GB",
    "wof:name":"GL52 6PU",
    "wof:placetype":"postalcode"
},
  "geometry": {"coordinates":[-2.048408,51.899082],"type":"Point"}
}