{
  "type": "Feature",
  "properties": {
    "iso:country":"GB",
    "wof:name":"KT13 8SJ",
    "wof:placetype":"postalcode"
},
  "geometry": {"coordinates":[-0.45525247624167,51.3665028066899],"type":"Point"}
}