{
  "type": "Feature",
  "properties": {
    "iso:country":"GB",
    "wof:name":"BH15 3LD",
    "wof:placetype":"postalcode"
},
  "geometry": {"coordinates":[-1.9719188578195,50.73561993857194],"type":"Point"}
}