{
  "type": "Feature",
  "properties": {
    "date:inception_lower": "1980-01-01",
    "date:inception_upper": "1980-01-01",
    "iso:country": "GB",
    "wof:name": "BH15 3LD",
    "wof:placetype": "postalcode"
  },
  "geometry": {"coordinates":[-1.971919,50.73562],"type":"Point"}
}
