{
  "type": "Feature",
  "properties": {
    "iso:country":"GB",
    "wof:name":"CW10 9AR",
    "wof:placetype":"postalcode"
},
  "geometry": {"coordinates":[-2.44577201043425,53.19131376156597],"type":"Point"}
}