{
  "type": "Feature",
  "properties": {
    "date:inception_lower":"1980-01-01",
    "date:inception_upper":"1980-01-31",
    "iso:country":"GB",
    "wof:name":"BB5 0SE",
    "wof:placetype":"postalcode"
},
  "geometry": {"coordinates":[-2.377478,53.749475],"type":"Point"}
}