{
  "type": "Feature",
  "properties": {
    "iso:country":"GB",
    "wof:name":"BB5 0SE",
    "wof:placetype":"postalcode"
},
  "geometry": {"coordinates":[-2.37752395916082,53.74948430666558],"type":"Point"}
}