{
  "type": "Feature",
  "properties": {
    "iso:country":"GB",
    "wof:name":"AB11 5BJ",
    "wof:placetype":"postalcode"
},
  "geometry": {"coordinates":[-2.09657862285171,57.14701900870784],"type":"Point"}
}