{
  "type": "Feature",
  "properties": {
    "date:inception_lower": "1980-01-01",
    "date:inception_upper": "1980-01-01",
    "iso:country": "GB",
    "wof:name": "YO22 5HR",
    "wof:placetype": "postalcode"
  },
  "geometry": {"coordinates":[-0.624497,54.457398],"type":"Point"}
}
