{
  "type": "Feature",
  "properties": {
    "iso:country":"GB",
    "wof:name":"PR3 1GD",
    "wof:placetype":"postalcode"
},
  "geometry": {"coordinates":[-2.74737104154229,53.89027320668999],"type":"Point"}
}