{
  "type": "Feature",
  "properties": {
    "iso:country": "GB",
    "wof:name": "OX15 5NT",
    "wof:placetype": "postalcode"
  },
  "geometry": {"coordinates":[-1.490905,51.995392],"type":"Point"}
}
