{
  "type": "Feature",
  "properties": {
    "iso:country":"GB",
    "wof:name":"EH47 0RW",
    "wof:placetype":"postalcode"
},
  "geometry": {"coordinates":[-3.67262661439074,55.86856871138477],"type":"Point"}
}