{
  "type": "Feature",
  "properties": {
    "iso:country": "GB",
    "wof:name": "LE5 5GE",
    "wof:placetype": "postalcode"
  },
  "geometry": {"coordinates":[-1.090682,52.629509],"type":"Point"}
}
