{
  "type": "Feature",
  "properties": {
    "date:inception_lower": "1980-01-01",
    "date:inception_upper": "1980-01-01",
    "iso:country": "GB",
    "wof:name": "LE5 5GE",
    "wof:placetype": "postalcode"
  },
  "geometry": {"coordinates":[-1.090682,52.629509],"type":"Point"}
}
