{
  "type": "Feature",
  "properties": {
    "date:inception_lower": "1980-01-01",
    "date:inception_upper": "1980-01-01",
    "iso:country": "GB",
    "wof:name": "CH8 9PD",
    "wof:placetype": "postalcode"
  },
  "geometry": {"coordinates":[-3.256029,53.307322],"type":"Point"}
}
