{
  "type": "Feature",
  "properties": {
    "iso:country":"GB",
    "wof:name":"CH8 9PD",
    "wof:placetype":"postalcode"
},
  "geometry": {"coordinates":[-3.25602872775771,53.30732244761526],"type":"Point"}
}