{
  "type": "Feature",
  "properties": {
    "iso:country":"GB",
    "wof:name":"IP25 7PZ",
    "wof:placetype":"postalcode"
},
  "geometry": {"coordinates":[0.88799768977888,52.62607778708119],"type":"Point"}
}