{
  "type": "Feature",
  "properties": {
    "iso:country": "GB",
    "wof:name": "IP25 7PZ",
    "wof:placetype": "postalcode"
  },
  "geometry": {"coordinates":[0.887998,52.626078],"type":"Point"}
}
