{
  "type": "Feature",
  "properties": {
    "iso:country":"GB",
    "wof:name":"S25 2QR",
    "wof:placetype":"postalcode"
},
  "geometry": {"coordinates":[-1.19774134008355,53.36515731825271],"type":"Point"}
}