{
  "type": "Feature",
  "properties": {
    "iso:country":"GB",
    "wof:name":"M46 9RS",
    "wof:placetype":"postalcode"
},
  "geometry": {"coordinates":[-2.48643372366704,53.52338649277393],"type":"Point"}
}