{
  "type": "Feature",
  "properties": {
    "date:inception_lower": "1997-06-01",
    "date:inception_upper": "1997-06-01",
    "iso:country": "GB",
    "wof:name": "NG31 8QX",
    "wof:placetype": "postalcode"
  },
  "geometry": {"coordinates":[-0.638457,52.929371],"type":"Point"}
}
