{
  "type": "Feature",
  "properties": {
    "iso:country": "GB",
    "wof:name": "NG31 8QX",
    "wof:placetype": "postalcode"
  },
  "geometry": {"coordinates":[-0.638457,52.929371],"type":"Point"}
}
