{
  "type": "Feature",
  "properties": {
    "date:inception_lower": "1980-01-01",
    "date:inception_upper": "1980-01-01",
    "iso:country": "GB",
    "wof:name": "DL14 7ER",
    "wof:placetype": "postalcode"
  },
  "geometry": {"coordinates":[-1.674588,54.662488],"type":"Point"}
}
