{
  "type": "Feature",
  "properties": {
    "date:inception_lower": "2019-11-01",
    "date:inception_upper": "2019-11-01",
    "iso:country": "GB",
    "wof:name": "GU29 0FF",
    "wof:placetype": "postalcode"
  },
  "geometry": {"coordinates":[-0.748004,51.018118],"type":"Point"}
}
