{
  "type": "Feature",
  "properties": {
    "iso:country":"GB",
    "wof:name":"SS3 8BU",
    "wof:placetype":"postalcode"
},
  "geometry": {"coordinates":[0.78839002765916,51.54269375648752],"type":"Point"}
}