{
  "type": "Feature",
  "properties": {
    "iso:country": "GB",
    "wof:name": "NN17 5AS",
    "wof:placetype": "postalcode"
  },
  "geometry": {"coordinates":[-0.640581,52.508629],"type":"Point"}
}
