{
  "type": "Feature",
  "properties": {
    "iso:country":"GB",
    "wof:name":"NE28 6PA",
    "wof:placetype":"postalcode"
},
  "geometry": {"coordinates":[-1.53075662020012,54.99014974189052],"type":"Point"}
}