{
  "type": "Feature",
  "properties": {
    "date:inception_lower": "1991-09-01",
    "date:inception_upper": "1991-09-01",
    "iso:country": "GB",
    "wof:name": "L12 0NS",
    "wof:placetype": "postalcode"
  },
  "geometry": {"coordinates":[-2.875792,53.447415],"type":"Point"}
}
