{
  "type": "Feature",
  "properties": {
    "iso:country":"GB",
    "wof:name":"DA6 7LU",
    "wof:placetype":"postalcode"
},
  "geometry": {"coordinates":[0.14535256157242,51.45396973525147],"type":"Point"}
}