{
  "type": "Feature",
  "properties": {
    "iso:country": "GB",
    "wof:name": "WF5 8NQ",
    "wof:placetype": "postalcode"
  },
  "geometry": {"coordinates":[-1.583786,53.670343],"type":"Point"}
}
