{
  "type": "Feature",
  "properties": {
    "date:inception_lower": "1980-01-01",
    "date:inception_upper": "1980-01-01",
    "iso:country": "GB",
    "wof:name": "WF5 8NQ",
    "wof:placetype": "postalcode"
  },
  "geometry": {"coordinates":[-1.583786,53.670343],"type":"Point"}
}
