{
  "type": "Feature",
  "properties": {
    "iso:country": "GB",
    "wof:name": "BS32 8EU",
    "wof:placetype": "postalcode"
  },
  "geometry": {"coordinates":[-2.535418,51.527273],"type":"Point"}
}
