{
  "type": "Feature",
  "properties": {
    "iso:country":"GB",
    "wof:name":"N4 3DT",
    "wof:placetype":"postalcode"
},
  "geometry": {"coordinates":[-0.12144657687999,51.56716060294284],"type":"Point"}
}