{
  "type": "Feature",
  "properties": {
    "iso:country":"GB",
    "wof:name":"AB15 9JP",
    "wof:placetype":"postalcode"
},
  "geometry": {"coordinates":[-2.17482638999503,57.12168288313599],"type":"Point"}
}