{
  "type": "Feature",
  "properties": {
    "iso:country":"GB",
    "wof:name":"CV5 8AR",
    "wof:placetype":"postalcode"
},
  "geometry": {"coordinates":[-1.55732481077004,52.40894953894893],"type":"Point"}
}