{
  "type": "Feature",
  "properties": {
    "iso:country":"GB",
    "wof:name":"BH23 1LH",
    "wof:placetype":"postalcode"
},
  "geometry": {"coordinates":[-1.78486260400568,50.73404941779121],"type":"Point"}
}