{
  "type": "Feature",
  "properties": {
    "iso:country":"GB",
    "wof:name":"DN22 7EB",
    "wof:placetype":"postalcode"
},
  "geometry": {"coordinates":[-0.93279429659635,53.31411042864065],"type":"Point"}
}