{
  "type": "Feature",
  "properties": {
    "date:inception_lower": "1981-06-01",
    "date:inception_upper": "1981-06-01",
    "iso:country": "GB",
    "wof:name": "DY6 9QW",
    "wof:placetype": "postalcode"
  },
  "geometry": {"coordinates":[-2.174935,52.495534],"type":"Point"}
}
