{
  "type": "Feature",
  "properties": {
    "iso:country": "GB",
    "wof:name": "NE27 0BY",
    "wof:placetype": "postalcode"
  },
  "geometry": {"coordinates":[-1.510464,55.024056],"type":"Point"}
}
