{
  "type": "Feature",
  "properties": {
    "iso:country":"GB",
    "wof:name":"NE27 0BY",
    "wof:placetype":"postalcode"
},
  "geometry": {"coordinates":[-1.51046453235937,55.02405584383394],"type":"Point"}
}