{
  "type": "Feature",
  "properties": {
    "date:inception_lower": "1994-05-01",
    "date:inception_upper": "1994-05-01",
    "iso:country": "GB",
    "wof:name": "M18 8PZ",
    "wof:placetype": "postalcode"
  },
  "geometry": {"coordinates":[-2.166444,53.464028],"type":"Point"}
}
