{
  "type": "Feature",
  "properties": {
    "iso:country":"GB",
    "wof:name":"M18 8PZ",
    "wof:placetype":"postalcode"
},
  "geometry": {"coordinates":[-2.1669876146066,53.46393870510887],"type":"Point"}
}