{
  "type": "Feature",
  "properties": {
    "iso:country": "GB",
    "wof:name": "NR12 7HZ",
    "wof:placetype": "postalcode"
  },
  "geometry": {"coordinates":[1.360334,52.735539],"type":"Point"}
}
