{
  "type": "Feature",
  "properties": {
    "date:inception_lower": "1980-01-01",
    "date:inception_upper": "1980-01-01",
    "iso:country": "GB",
    "wof:name": "EX39 5PF",
    "wof:placetype": "postalcode"
  },
  "geometry": {"coordinates":[-4.289422,50.97227],"type":"Point"}
}
