{
  "type": "Feature",
  "properties": {
    "iso:country": "GB",
    "wof:name": "SS8 7ED",
    "wof:placetype": "postalcode"
  },
  "geometry": {"coordinates":[0.598174,51.521899],"type":"Point"}
}
