{
  "type": "Feature",
  "properties": {
    "date:inception_lower":"1980-01-01",
    "date:inception_upper":"1980-01-31",
    "iso:country":"GB",
    "wof:name":"SS8 7ED",
    "wof:placetype":"postalcode"
},
  "geometry": {"coordinates":[0.598174,51.521899],"type":"Point"}
}