{
  "type": "Feature",
  "properties": {
    "iso:country":"GB",
    "wof:name":"SS8 7ED",
    "wof:placetype":"postalcode"
},
  "geometry": {"coordinates":[0.59817439189644,51.52189860832384],"type":"Point"}
}