{
  "type": "Feature",
  "properties": {
    "iso:country":"GB",
    "wof:name":"B31 4PQ",
    "wof:placetype":"postalcode"
},
  "geometry": {"coordinates":[-1.97829478439084,52.39377294785194],"type":"Point"}
}