{
  "type": "Feature",
  "properties": {
    "date:inception_lower":"1980-01-01",
    "date:inception_upper":"1980-01-31",
    "iso:country":"GB",
    "wof:name":"B31 4PQ",
    "wof:placetype":"postalcode"
},
  "geometry": {"coordinates":[-1.978295,52.393773],"type":"Point"}
}