{
  "type": "Feature",
  "properties": {
    "iso:country":"GB",
    "wof:name":"PO19 1SR",
    "wof:placetype":"postalcode"
},
  "geometry": {"coordinates":[-0.77901421022879,50.83400157284213],"type":"Point"}
}