{
  "type": "Feature",
  "properties": {
    "iso:country":"GB",
    "wof:name":"LA8 8DU",
    "wof:placetype":"postalcode"
},
  "geometry": {"coordinates":[-2.78260956222792,54.27276661952207],"type":"Point"}
}