{
  "type": "Feature",
  "properties": {
    "date:inception_lower": "2017-08-01",
    "date:inception_upper": "2017-08-01",
    "iso:country": "GB",
    "wof:name": "EX15 1TY",
    "wof:placetype": "postalcode"
  },
  "geometry": {"coordinates":[-3.407891,50.85798],"type":"Point"}
}
