{
  "type": "Feature",
  "properties": {
    "iso:country":"GB",
    "wof:name":"M11 1BD",
    "wof:placetype":"postalcode"
},
  "geometry": {"coordinates":[-2.16963656291177,53.47474808955271],"type":"Point"}
}