{
  "type": "Feature",
  "properties": {
    "iso:country": "GB",
    "wof:name": "SR3 1HN",
    "wof:placetype": "postalcode"
  },
  "geometry": {"coordinates":[-1.403117,54.874205],"type":"Point"}
}
