{
  "type": "Feature",
  "properties": {
    "iso:country":"GB",
    "wof:name":"KA13 6NH",
    "wof:placetype":"postalcode"
},
  "geometry": {"coordinates":[-4.71619524780182,55.65262199406093],"type":"Point"}
}