{
  "type": "Feature",
  "properties": {
    "iso:country":"GB",
    "wof:name":"CM15 0BD",
    "wof:placetype":"postalcode"
},
  "geometry": {"coordinates":[0.27911391442886,51.66569395054793],"type":"Point"}
}