{
  "type": "Feature",
  "properties": {
    "date:inception_lower": "1980-01-01",
    "date:inception_upper": "1980-01-01",
    "iso:country": "GB",
    "wof:name": "CM15 0BD",
    "wof:placetype": "postalcode"
  },
  "geometry": {"coordinates":[0.279111,51.66568],"type":"Point"}
}
