{
  "type": "Feature",
  "properties": {
    "iso:country":"GB",
    "wof:name":"DG9 0AY",
    "wof:placetype":"postalcode"
},
  "geometry": {"coordinates":[-5.04241314400208,54.9070642478454],"type":"Point"}
}