{
  "type": "Feature",
  "properties": {
    "iso:country": "GB",
    "wof:name": "SW16 4QH",
    "wof:placetype": "postalcode"
  },
  "geometry": {"coordinates":[-0.135335,51.408088],"type":"Point"}
}
