{
  "type": "Feature",
  "properties": {
    "iso:country":"GB",
    "wof:name":"SW16 4QH",
    "wof:placetype":"postalcode"
},
  "geometry": {"coordinates":[-0.13533540264675,51.40808814322045],"type":"Point"}
}