{
  "type": "Feature",
  "properties": {
    "iso:country": "GB",
    "wof:name": "TQ4 7TW",
    "wof:placetype": "postalcode"
  },
  "geometry": {"coordinates":[-3.584049,50.413343],"type":"Point"}
}
