{
  "type": "Feature",
  "properties": {
    "iso:country":"GB",
    "wof:name":"TQ4 7TW",
    "wof:placetype":"postalcode"
},
  "geometry": {"coordinates":[-3.58403158276236,50.41335824062927],"type":"Point"}
}