{
  "type": "Feature",
  "properties": {
    "iso:country":"GB",
    "wof:name":"CR8 4HD",
    "wof:placetype":"postalcode"
},
  "geometry": {"coordinates":[-0.12276086474063,51.33274418199447],"type":"Point"}
}