{
  "type": "Feature",
  "properties": {
    "iso:country":"GB",
    "wof:name":"LL29 9SE",
    "wof:placetype":"postalcode"
},
  "geometry": {"coordinates":[-3.70137501508634,53.29174931111209],"type":"Point"}
}