{
  "type": "Feature",
  "properties": {
    "date:inception_lower": "1980-01-01",
    "date:inception_upper": "1980-01-01",
    "iso:country": "GB",
    "wof:name": "LL29 9SE",
    "wof:placetype": "postalcode"
  },
  "geometry": {"coordinates":[-3.701375,53.291749],"type":"Point"}
}
