{
  "type": "Feature",
  "properties": {
    "iso:country":"GB",
    "wof:name":"PA80 5UZ",
    "wof:placetype":"postalcode"
},
  "geometry": {"coordinates":[-5.74073154445748,56.56041262156909],"type":"Point"}
}