{
  "type": "Feature",
  "properties": {
    "iso:country": "GB",
    "wof:name": "PA80 5UZ",
    "wof:placetype": "postalcode"
  },
  "geometry": {"coordinates":[-5.740731,56.560413],"type":"Point"}
}
