{
  "type": "Feature",
  "properties": {
    "date:inception_lower":"2010-06-01",
    "date:inception_upper":"2010-06-30",
    "iso:country":"GB",
    "wof:name":"PA80 5UZ",
    "wof:placetype":"postalcode"
},
  "geometry": {"coordinates":[-5.740731,56.560413],"type":"Point"}
}