{
  "type": "Feature",
  "properties": {
    "iso:country": "GB",
    "wof:name": "NE34 8BT",
    "wof:placetype": "postalcode"
  },
  "geometry": {"coordinates":[-1.41642,54.961986],"type":"Point"}
}
