{
  "type": "Feature",
  "properties": {
    "date:inception_lower": "2011-08-01",
    "date:inception_upper": "2011-08-01",
    "iso:country": "GB",
    "wof:name": "NE34 8BT",
    "wof:placetype": "postalcode"
  },
  "geometry": {"coordinates":[-1.41642,54.961986],"type":"Point"}
}
