{
  "type": "Feature",
  "properties": {
    "iso:country":"GB",
    "wof:name":"NE34 8BT",
    "wof:placetype":"postalcode"
},
  "geometry": {"coordinates":[-1.41641967421258,54.96198628209498],"type":"Point"}
}