{
  "type": "Feature",
  "properties": {
    "date:inception_lower": "2018-06-01",
    "date:inception_upper": "2018-06-01",
    "iso:country": "GB",
    "wof:name": "NP10 9PS",
    "wof:placetype": "postalcode"
  },
  "geometry": {"coordinates":[-3.058708,51.584467],"type":"Point"}
}
