{
  "type": "Feature",
  "properties": {
    "iso:country":"GB",
    "wof:name":"SW9 6QF",
    "wof:placetype":"postalcode"
},
  "geometry": {"coordinates":[-0.10997781003191,51.47658351940663],"type":"Point"}
}