{
  "type": "Feature",
  "properties": {
    "iso:country": "GB",
    "wof:name": "ME20 6GJ",
    "wof:placetype": "postalcode"
  },
  "geometry": {"coordinates":[0.447226,51.310887],"type":"Point"}
}
