{
  "type": "Feature",
  "properties": {
    "date:inception_lower":"2002-07-01",
    "date:inception_upper":"2002-07-31",
    "iso:country":"GB",
    "wof:name":"ME20 6GJ",
    "wof:placetype":"postalcode"
},
  "geometry": {"coordinates":[0.447226,51.310887],"type":"Point"}
}