{
  "type": "Feature",
  "properties": {
    "date:inception_lower":"1981-06-01",
    "date:inception_upper":"1981-06-30",
    "iso:country":"GB",
    "wof:name":"PR3 0XB",
    "wof:placetype":"postalcode"
},
  "geometry": {"coordinates":[-2.852558,53.851444],"type":"Point"}
}