{
  "type": "Feature",
  "properties": {
    "date:inception_lower": "2002-06-01",
    "date:inception_upper": "2002-06-01",
    "iso:country": "GB",
    "wof:name": "RG22 4FF",
    "wof:placetype": "postalcode"
  },
  "geometry": {"coordinates":[-1.143893,51.223832],"type":"Point"}
}
