{
  "type": "Feature",
  "properties": {
    "iso:country":"GB",
    "wof:name":"RG22 4FF",
    "wof:placetype":"postalcode"
},
  "geometry": {"coordinates":[-1.14389274777626,51.22383151652957],"type":"Point"}
}