{
  "type": "Feature",
  "properties": {
    "iso:country":"GB",
    "wof:name":"CB10 1UE",
    "wof:placetype":"postalcode"
},
  "geometry": {"coordinates":[0.21552622212692,52.04755464636535],"type":"Point"}
}