{
  "type": "Feature",
  "properties": {
    "iso:country":"GB",
    "wof:name":"BD19 4NU",
    "wof:placetype":"postalcode"
},
  "geometry": {"coordinates":[-1.69330361328746,53.72746042173952],"type":"Point"}
}