{
  "type": "Feature",
  "properties": {
    "iso:country":"GB",
    "wof:name":"SY16 4EH",
    "wof:placetype":"postalcode"
},
  "geometry": {"coordinates":[-3.17992152791244,52.50965973423276],"type":"Point"}
}