{
  "type": "Feature",
  "properties": {
    "iso:country": "GB",
    "wof:name": "SY16 4EH",
    "wof:placetype": "postalcode"
  },
  "geometry": {"coordinates":[-3.179921,52.50966],"type":"Point"}
}
