{
  "type": "Feature",
  "properties": {
    "iso:country":"GB",
    "wof:name":"OX39 4DJ",
    "wof:placetype":"postalcode"
},
  "geometry": {"coordinates":[-0.90578542227053,51.70384007075091],"type":"Point"}
}