{
  "type": "Feature",
  "properties": {
    "iso:country": "GB",
    "wof:name": "OX39 4DJ",
    "wof:placetype": "postalcode"
  },
  "geometry": {"coordinates":[-0.905892,51.703899],"type":"Point"}
}
