{
  "type": "Feature",
  "properties": {
    "date:inception_lower": "2000-10-01",
    "date:inception_upper": "2000-10-01",
    "iso:country": "GB",
    "wof:name": "OX39 4DJ",
    "wof:placetype": "postalcode"
  },
  "geometry": {"coordinates":[-0.905892,51.703899],"type":"Point"}
}
