{
  "type": "Feature",
  "properties": {
    "iso:country":"GB",
    "wof:name":"LE17 4ND",
    "wof:placetype":"postalcode"
},
  "geometry": {"coordinates":[-1.19652486443814,52.46324701330757],"type":"Point"}
}