{
  "type": "Feature",
  "properties": {
    "date:inception_lower": "2013-07-01",
    "date:inception_upper": "2013-07-01",
    "iso:country": "GB",
    "wof:name": "L36 8EQ",
    "wof:placetype": "postalcode"
  },
  "geometry": {"coordinates":[-2.854302,53.429234],"type":"Point"}
}
