{
  "type": "Feature",
  "properties": {
    "iso:country": "GB",
    "wof:name": "S10 1SE",
    "wof:placetype": "postalcode"
  },
  "geometry": {"coordinates":[-1.512529,53.387441],"type":"Point"}
}
