{
  "type": "Feature",
  "properties": {
    "iso:country":"GB",
    "wof:name":"S10 1SE",
    "wof:placetype":"postalcode"
},
  "geometry": {"coordinates":[-1.51252897728414,53.38744132113717],"type":"Point"}
}