{
  "type": "Feature",
  "properties": {
    "iso:country":"GB",
    "wof:name":"SA33 6AG",
    "wof:placetype":"postalcode"
},
  "geometry": {"coordinates":[-4.36420373318261,51.86686123468879],"type":"Point"}
}