{
  "type": "Feature",
  "properties": {
    "date:inception_lower": "1980-01-01",
    "date:inception_upper": "1980-01-01",
    "iso:country": "GB",
    "wof:name": "S74 0AB",
    "wof:placetype": "postalcode"
  },
  "geometry": {"coordinates":[-1.460661,53.497697],"type":"Point"}
}
