{
  "type": "Feature",
  "properties": {
    "iso:country":"GB",
    "wof:name":"S74 0AB",
    "wof:placetype":"postalcode"
},
  "geometry": {"coordinates":[-1.46066093866063,53.49769737834607],"type":"Point"}
}