{
  "type": "Feature",
  "properties": {
    "date:inception_lower":"1980-01-01",
    "date:inception_upper":"1980-01-31",
    "iso:country":"GB",
    "wof:name":"CO7 6JS",
    "wof:placetype":"postalcode"
},
  "geometry": {"coordinates":[0.972104,51.9662],"type":"Point"}
}