{
  "type": "Feature",
  "properties": {
    "iso:country": "GB",
    "wof:name": "CV21 1JG",
    "wof:placetype": "postalcode"
  },
  "geometry": {"coordinates":[-1.242628,52.38922],"type":"Point"}
}
