{
  "type": "Feature",
  "properties": {
    "iso:country":"GB",
    "wof:name":"CV21 1JG",
    "wof:placetype":"postalcode"
},
  "geometry": {"coordinates":[-1.24262788197543,52.38921976850543],"type":"Point"}
}