{
  "type": "Feature",
  "properties": {
    "iso:country":"GB",
    "wof:name":"ST3 7NE",
    "wof:placetype":"postalcode"
},
  "geometry": {"coordinates":[-2.113566486553,52.95735403488688],"type":"Point"}
}