{
  "type": "Feature",
  "properties": {
    "iso:country": "GB",
    "wof:name": "S70 1UR",
    "wof:placetype": "postalcode"
  },
  "geometry": {"coordinates":[-1.46656,53.547772],"type":"Point"}
}
