{
  "type": "Feature",
  "properties": {
    "iso:country":"GB",
    "wof:name":"S70 1UR",
    "wof:placetype":"postalcode"
},
  "geometry": {"coordinates":[-1.46655979239772,53.54777171758871],"type":"Point"}
}