{
  "type": "Feature",
  "properties": {
    "iso:country":"GB",
    "wof:name":"SM2 6TH",
    "wof:placetype":"postalcode"
},
  "geometry": {"coordinates":[-0.19658507391884,51.35482117230329],"type":"Point"}
}