{
  "type": "Feature",
  "properties": {
    "iso:country": "GB",
    "wof:name": "SM2 6TH",
    "wof:placetype": "postalcode"
  },
  "geometry": {"coordinates":[-0.196257,51.35486],"type":"Point"}
}
