{
  "type": "Feature",
  "properties": {
    "iso:country": "GB",
    "wof:name": "TS14 8DG",
    "wof:placetype": "postalcode"
  },
  "geometry": {"coordinates":[-1.089791,54.53082],"type":"Point"}
}
