{
  "type": "Feature",
  "properties": {
    "date:inception_lower":"2016-01-01",
    "date:inception_upper":"2016-01-31",
    "iso:country":"GB",
    "wof:name":"TS14 8DG",
    "wof:placetype":"postalcode"
},
  "geometry": {"coordinates":[-1.089791,54.53082],"type":"Point"}
}