{
  "type": "Feature",
  "properties": {
    "date:inception_lower": "1980-01-01",
    "date:inception_upper": "1980-01-01",
    "iso:country": "GB",
    "wof:name": "LA3 2AU",
    "wof:placetype": "postalcode"
  },
  "geometry": {"coordinates":[-2.888886,54.053277],"type":"Point"}
}
