{
  "type": "Feature",
  "properties": {
    "iso:country":"GB",
    "wof:name":"GL8 8EL",
    "wof:placetype":"postalcode"
},
  "geometry": {"coordinates":[-2.16776923112196,51.64492115082614],"type":"Point"}
}