{
  "type": "Feature",
  "properties": {
    "iso:country":"GB",
    "wof:name":"EX2 5NE",
    "wof:placetype":"postalcode"
},
  "geometry": {"coordinates":[-3.48491160318539,50.7150486567558],"type":"Point"}
}