{
  "type": "Feature",
  "properties": {
    "iso:country":"GB",
    "wof:name":"PO37 7BY",
    "wof:placetype":"postalcode"
},
  "geometry": {"coordinates":[-1.17482357183321,50.63661623316169],"type":"Point"}
}