{
  "type": "Feature",
  "properties": {
    "iso:country": "GB",
    "wof:name": "PO37 7BY",
    "wof:placetype": "postalcode"
  },
  "geometry": {"coordinates":[-1.174824,50.636616],"type":"Point"}
}
