{
  "type": "Feature",
  "properties": {
    "iso:country": "GB",
    "wof:name": "NR30 3AG",
    "wof:placetype": "postalcode"
  },
  "geometry": {"coordinates":[1.735423,52.600672],"type":"Point"}
}
