{
  "type": "Feature",
  "properties": {
    "iso:country": "GB",
    "wof:name": "GU32 9GH",
    "wof:placetype": "postalcode"
  },
  "geometry": {"coordinates":[-0.938263,51.003869],"type":"Point"}
}
