{
  "type": "Feature",
  "properties": {
    "date:inception_lower":"1999-06-01",
    "date:inception_upper":"1999-06-30",
    "iso:country":"GB",
    "wof:name":"CH65 5DA",
    "wof:placetype":"postalcode"
},
  "geometry": {"coordinates":[-2.890954,53.273115],"type":"Point"}
}