{
  "type": "Feature",
  "properties": {
    "iso:country":"GB",
    "wof:name":"WA6 8DY",
    "wof:placetype":"postalcode"
},
  "geometry": {"coordinates":[-2.6771542550307,53.26882266322664],"type":"Point"}
}