{
  "type": "Feature",
  "properties": {
    "iso:country": "GB",
    "wof:name": "WA6 8DY",
    "wof:placetype": "postalcode"
  },
  "geometry": {"coordinates":[-2.677154,53.268823],"type":"Point"}
}
