{
  "type": "Feature",
  "properties": {
    "iso:country":"GB",
    "wof:name":"N14 4NG",
    "wof:placetype":"postalcode"
},
  "geometry": {"coordinates":[-0.13168496425525,51.64013546480998],"type":"Point"}
}