{
  "type": "Feature",
  "properties": {
    "date:inception_lower": "2023-11-01",
    "date:inception_upper": "2023-11-01",
    "iso:country": "GB",
    "wof:name": "WS6 6FA",
    "wof:placetype": "postalcode"
  },
  "geometry": {"coordinates":[-2.009263,52.652861],"type":"Point"}
}
