{
  "type": "Feature",
  "properties": {
    "iso:country":"GB",
    "wof:name":"NG34 9UR",
    "wof:placetype":"postalcode"
},
  "geometry": {"coordinates":[-0.30406114373694,52.98445528368932],"type":"Point"}
}