{
  "type": "Feature",
  "properties": {
    "iso:country":"GB",
    "wof:name":"CW1 4GB",
    "wof:placetype":"postalcode"
},
  "geometry": {"coordinates":[-2.44360038771129,53.11287479327208],"type":"Point"}
}