{
  "type": "Feature",
  "properties": {
    "date:inception_lower": "2002-08-01",
    "date:inception_upper": "2002-08-01",
    "iso:country": "GB",
    "wof:name": "CW1 4GB",
    "wof:placetype": "postalcode"
  },
  "geometry": {"coordinates":[-2.4436,53.112875],"type":"Point"}
}
