{
  "type": "Feature",
  "properties": {
    "iso:country":"GB",
    "wof:name":"AB31 5HJ",
    "wof:placetype":"postalcode"
},
  "geometry": {"coordinates":[-2.37063419747172,57.08425510625988],"type":"Point"}
}