{
  "type": "Feature",
  "properties": {
    "iso:country":"GB",
    "wof:name":"BH21 4AT",
    "wof:placetype":"postalcode"
},
  "geometry": {"coordinates":[-2.07347683178699,50.79798160647577],"type":"Point"}
}