{
  "type": "Feature",
  "properties": {
    "date:inception_lower":"2009-08-01",
    "date:inception_upper":"2009-08-31",
    "iso:country":"GB",
    "wof:name":"S60 1NU",
    "wof:placetype":"postalcode"
},
  "geometry": {"coordinates":[-1.359074,53.429665],"type":"Point"}
}