{
  "type": "Feature",
  "properties": {
    "iso:country":"GB",
    "wof:name":"S60 1NU",
    "wof:placetype":"postalcode"
},
  "geometry": {"coordinates":[-1.3590736882876,53.42966454599521],"type":"Point"}
}