{
  "type": "Feature",
  "properties": {
    "iso:country":"GB",
    "wof:name":"TF2 6AP",
    "wof:placetype":"postalcode"
},
  "geometry": {"coordinates":[-2.45921083532647,52.69676871695668],"type":"Point"}
}