{
  "type": "Feature",
  "properties": {
    "iso:country":"GB",
    "wof:name":"HA1 4SE",
    "wof:placetype":"postalcode"
},
  "geometry": {"coordinates":[-0.34864605136899,51.58861611859079],"type":"Point"}
}