{
  "type": "Feature",
  "properties": {
    "iso:country":"GB",
    "wof:name":"EH48 1SS",
    "wof:placetype":"postalcode"
},
  "geometry": {"coordinates":[-3.60523195345107,55.90071120795056],"type":"Point"}
}