{
  "type": "Feature",
  "properties": {
    "iso:country": "GB",
    "wof:name": "CA12 4AN",
    "wof:placetype": "postalcode"
  },
  "geometry": {"coordinates":[-3.123781,54.59468],"type":"Point"}
}
