{
  "type": "Feature",
  "properties": {
    "iso:country":"GB",
    "wof:name":"KY3 9HF",
    "wof:placetype":"postalcode"
},
  "geometry": {"coordinates":[-3.22662826264021,56.06714538929284],"type":"Point"}
}