{
  "type": "Feature",
  "properties": {
    "iso:country":"GB",
    "wof:name":"WN7 3QU",
    "wof:placetype":"postalcode"
},
  "geometry": {"coordinates":[-2.53804149521518,53.47631711731953],"type":"Point"}
}