{
  "type": "Feature",
  "properties": {
    "iso:country":"GB",
    "wof:name":"UB3 1QZ",
    "wof:placetype":"postalcode"
},
  "geometry": {"coordinates":[-0.43391719068349,51.50331631899837],"type":"Point"}
}