{
  "type": "Feature",
  "properties": {
    "iso:country": "GB",
    "wof:name": "WV10 9BS",
    "wof:placetype": "postalcode"
  },
  "geometry": {"coordinates":[-2.110649,52.613419],"type":"Point"}
}
