{
  "type": "Feature",
  "properties": {
    "iso:country":"GB",
    "wof:name":"TS2 1LH",
    "wof:placetype":"postalcode"
},
  "geometry": {"coordinates":[-1.23799660143837,54.58245030470061],"type":"Point"}
}