{
  "type": "Feature",
  "properties": {
    "date:inception_lower":"2006-09-01",
    "date:inception_upper":"2006-09-30",
    "iso:country":"GB",
    "wof:name":"TS19 8JR",
    "wof:placetype":"postalcode"
},
  "geometry": {"coordinates":[-1.349545,54.586768],"type":"Point"}
}