{
  "type": "Feature",
  "properties": {
    "iso:country": "GB",
    "wof:name": "TS19 8JR",
    "wof:placetype": "postalcode"
  },
  "geometry": {"coordinates":[-1.349545,54.586768],"type":"Point"}
}
