{
  "type": "Feature",
  "properties": {
    "date:inception_lower":"1980-01-01",
    "date:inception_upper":"1980-01-31",
    "iso:country":"GB",
    "wof:name":"BS22 8RG",
    "wof:placetype":"postalcode"
},
  "geometry": {"coordinates":[-2.933836,51.353516],"type":"Point"}
}