{
  "type": "Feature",
  "properties": {
    "iso:country": "GB",
    "wof:name": "TR3 6BL",
    "wof:placetype": "postalcode"
  },
  "geometry": {"coordinates":[-5.113226,50.254338],"type":"Point"}
}
