{
  "type": "Feature",
  "properties": {
    "iso:country":"GB",
    "wof:name":"TR3 6BL",
    "wof:placetype":"postalcode"
},
  "geometry": {"coordinates":[-5.11322583443543,50.25433805253316],"type":"Point"}
}