{
  "type": "Feature",
  "properties": {
    "date:inception_lower": "1980-01-01",
    "date:inception_upper": "1980-01-01",
    "iso:country": "GB",
    "wof:name": "WD4 9AX",
    "wof:placetype": "postalcode"
  },
  "geometry": {"coordinates":[-0.481215,51.693481],"type":"Point"}
}
