{
  "type": "Feature",
  "properties": {
    "iso:country":"GB",
    "wof:name":"WD4 9AX",
    "wof:placetype":"postalcode"
},
  "geometry": {"coordinates":[-0.48121489658436,51.6934812753173],"type":"Point"}
}