{
  "type": "Feature",
  "properties": {
    "date:inception_lower": "1980-01-01",
    "date:inception_upper": "1980-01-01",
    "iso:country": "GB",
    "wof:name": "HA1 1LQ",
    "wof:placetype": "postalcode"
  },
  "geometry": {"coordinates":[-0.334476,51.581143],"type":"Point"}
}
