{
  "type": "Feature",
  "properties": {
    "iso:country": "GB",
    "wof:name": "LA13 9BQ",
    "wof:placetype": "postalcode"
  },
  "geometry": {"coordinates":[-3.211426,54.115246],"type":"Point"}
}
