{
  "type": "Feature",
  "properties": {
    "iso:country":"GB",
    "wof:name":"CH43 4XZ",
    "wof:placetype":"postalcode"
},
  "geometry": {"coordinates":[-3.04201684751346,53.38995338395078],"type":"Point"}
}