{
  "type": "Feature",
  "properties": {
    "date:inception_lower": "1996-06-01",
    "date:inception_upper": "1996-06-01",
    "iso:country": "GB",
    "wof:name": "AB34 4UH",
    "wof:placetype": "postalcode"
  },
  "geometry": {"coordinates":[-2.856394,57.131708],"type":"Point"}
}
