{
  "type": "Feature",
  "properties": {
    "iso:country": "GB",
    "wof:name": "DA6 8LG",
    "wof:placetype": "postalcode"
  },
  "geometry": {"coordinates":[0.131541,51.457819],"type":"Point"}
}
