{
  "type": "Feature",
  "properties": {
    "iso:country":"GB",
    "wof:name":"DA6 8LG",
    "wof:placetype":"postalcode"
},
  "geometry": {"coordinates":[0.13154101961815,51.45781887407463],"type":"Point"}
}