{
  "type": "Feature",
  "properties": {
    "iso:country":"GB",
    "wof:name":"BA2 3BX",
    "wof:placetype":"postalcode"
},
  "geometry": {"coordinates":[-2.37655797335422,51.38113908163535],"type":"Point"}
}