{
  "type": "Feature",
  "properties": {
    "date:inception_lower": "2011-06-01",
    "date:inception_upper": "2011-06-01",
    "iso:country": "GB",
    "wof:name": "BS37 4FJ",
    "wof:placetype": "postalcode"
  },
  "geometry": {"coordinates":[-2.407101,51.537373],"type":"Point"}
}
