{
  "type": "Feature",
  "properties": {
    "iso:country":"GB",
    "wof:name":"BS37 4FJ",
    "wof:placetype":"postalcode"
},
  "geometry": {"coordinates":[-2.40710088160529,51.53737344265668],"type":"Point"}
}