{
  "type": "Feature",
  "properties": {
    "iso:country": "GB",
    "wof:name": "HG2 0EB",
    "wof:placetype": "postalcode"
  },
  "geometry": {"coordinates":[-1.545891,53.980462],"type":"Point"}
}
