{
  "type": "Feature",
  "properties": {
    "date:inception_lower":"1980-01-01",
    "date:inception_upper":"1980-01-31",
    "iso:country":"GB",
    "wof:name":"HG2 0EB",
    "wof:placetype":"postalcode"
},
  "geometry": {"coordinates":[-1.545891,53.980462],"type":"Point"}
}