{
  "type": "Feature",
  "properties": {
    "date:inception_lower": "1996-06-01",
    "date:inception_upper": "1996-06-01",
    "iso:country": "GB",
    "wof:name": "DY11 7NL",
    "wof:placetype": "postalcode"
  },
  "geometry": {"coordinates":[-2.270366,52.374568],"type":"Point"}
}
