{
  "type": "Feature",
  "properties": {
    "iso:country":"GB",
    "wof:name":"HP2 5JL",
    "wof:placetype":"postalcode"
},
  "geometry": {"coordinates":[-0.44913489741459,51.76211078318129],"type":"Point"}
}