{
  "type": "Feature",
  "properties": {
    "iso:country":"GB",
    "wof:name":"BA1 8EY",
    "wof:placetype":"postalcode"
},
  "geometry": {"coordinates":[-2.31590013121849,51.42184378210261],"type":"Point"}
}