{
  "type": "Feature",
  "properties": {
    "iso:country": "GB",
    "wof:name": "BA1 8EY",
    "wof:placetype": "postalcode"
  },
  "geometry": {"coordinates":[-2.3159,51.421844],"type":"Point"}
}
