{
  "type": "Feature",
  "properties": {
    "date:inception_lower": "1982-08-01",
    "date:inception_upper": "1982-08-01",
    "iso:country": "GB",
    "wof:name": "ML9 3HF",
    "wof:placetype": "postalcode"
  },
  "geometry": {"coordinates":[-3.990098,55.69123],"type":"Point"}
}
