{
  "type": "Feature",
  "properties": {
    "iso:country":"GB",
    "wof:name":"ML9 3HF",
    "wof:placetype":"postalcode"
},
  "geometry": {"coordinates":[-3.99009785915665,55.69123012699411],"type":"Point"}
}