{
  "type": "Feature",
  "properties": {
    "date:inception_lower": "1994-05-01",
    "date:inception_upper": "1994-05-01",
    "iso:country": "GB",
    "wof:name": "ST3 1JN",
    "wof:placetype": "postalcode"
  },
  "geometry": {"coordinates":[-2.121834,52.985958],"type":"Point"}
}
