{
  "type": "Feature",
  "properties": {
    "date:inception_lower":"1980-01-01",
    "date:inception_upper":"1980-01-31",
    "iso:country":"GB",
    "wof:name":"SA9 1PL",
    "wof:placetype":"postalcode"
},
  "geometry": {"coordinates":[-3.753513,51.771484],"type":"Point"}
}