{
  "type": "Feature",
  "properties": {
    "iso:country":"GB",
    "wof:name":"SA9 1PL",
    "wof:placetype":"postalcode"
},
  "geometry": {"coordinates":[-3.75351272134286,51.77148359321787],"type":"Point"}
}