{
  "type": "Feature",
  "properties": {
    "iso:country": "GB",
    "wof:name": "SA9 1PL",
    "wof:placetype": "postalcode"
  },
  "geometry": {"coordinates":[-3.753513,51.771484],"type":"Point"}
}
