{
  "type": "Feature",
  "properties": {
    "date:inception_lower": "2021-04-01",
    "date:inception_upper": "2021-04-01",
    "iso:country": "GB",
    "wof:name": "HG4 5FF",
    "wof:placetype": "postalcode"
  },
  "geometry": {"coordinates":[-1.433539,54.131676],"type":"Point"}
}
