{
  "type": "Feature",
  "properties": {
    "date:inception_lower":"1980-01-01",
    "date:inception_upper":"1980-01-31",
    "iso:country":"GB",
    "wof:name":"WV4 5SR",
    "wof:placetype":"postalcode"
},
  "geometry": {"coordinates":[-2.143171,52.563976],"type":"Point"}
}