{
  "type": "Feature",
  "properties": {
    "iso:country": "GB",
    "wof:name": "WV4 5SR",
    "wof:placetype": "postalcode"
  },
  "geometry": {"coordinates":[-2.143171,52.563976],"type":"Point"}
}
