{
  "type": "Feature",
  "properties": {
    "iso:country":"GB",
    "wof:name":"WV4 5SR",
    "wof:placetype":"postalcode"
},
  "geometry": {"coordinates":[-2.14317104773506,52.56397583113593],"type":"Point"}
}