{
  "type": "Feature",
  "properties": {
    "iso:country":"GB",
    "wof:name":"SW2 5DA",
    "wof:placetype":"postalcode"
},
  "geometry": {"coordinates":[-0.12317947160907,51.45421517824375],"type":"Point"}
}