{
  "type": "Feature",
  "properties": {
    "iso:country":"GB",
    "wof:name":"BB4 8JN",
    "wof:placetype":"postalcode"
},
  "geometry": {"coordinates":[-2.28901678622884,53.70637200712319],"type":"Point"}
}