{
  "type": "Feature",
  "properties": {
    "iso:country":"GB",
    "wof:name":"RG9 5WF",
    "wof:placetype":"postalcode"
},
  "geometry": {"coordinates":[-1.01652822980626,51.53637977353638],"type":"Point"}
}