{
  "type": "Feature",
  "properties": {
    "date:inception_lower": "1980-01-01",
    "date:inception_upper": "1980-01-01",
    "iso:country": "GB",
    "wof:name": "PE11 1PA",
    "wof:placetype": "postalcode"
  },
  "geometry": {"coordinates":[-0.161927,52.789836],"type":"Point"}
}
