{
  "type": "Feature",
  "properties": {
    "iso:country":"GB",
    "wof:name":"S81 8RJ",
    "wof:placetype":"postalcode"
},
  "geometry": {"coordinates":[-1.17787075178945,53.34816798953126],"type":"Point"}
}