{
  "type": "Feature",
  "properties": {
    "iso:country":"GB",
    "wof:name":"BB2 3SG",
    "wof:placetype":"postalcode"
},
  "geometry": {"coordinates":[-2.48393170836668,53.7362127256428],"type":"Point"}
}