{
  "type": "Feature",
  "properties": {
    "iso:country":"GB",
    "wof:name":"KT13 0PZ",
    "wof:placetype":"postalcode"
},
  "geometry": {"coordinates":[-0.44406400403378,51.35626528133897],"type":"Point"}
}