{
  "type": "Feature",
  "properties": {
    "iso:country": "GB",
    "wof:name": "KT13 0PZ",
    "wof:placetype": "postalcode"
  },
  "geometry": {"coordinates":[-0.444064,51.356265],"type":"Point"}
}
