{
  "type": "Feature",
  "properties": {
    "date:inception_lower":"1980-01-01",
    "date:inception_upper":"1980-01-31",
    "iso:country":"GB",
    "wof:name":"BS5 0PG",
    "wof:placetype":"postalcode"
},
  "geometry": {"coordinates":[-2.569694,51.464674],"type":"Point"}
}