{
  "type": "Feature",
  "properties": {
    "iso:country":"GB",
    "wof:name":"WA3 3QT",
    "wof:placetype":"postalcode"
},
  "geometry": {"coordinates":[-2.60844004429816,53.47988033055766],"type":"Point"}
}