{
  "type": "Feature",
  "properties": {
    "iso:country":"GB",
    "wof:name":"BA6 9TP",
    "wof:placetype":"postalcode"
},
  "geometry": {"coordinates":[-2.80484837225721,51.17494165590195],"type":"Point"}
}