{
  "type": "Feature",
  "properties": {
    "iso:country":"GB",
    "wof:name":"PE38 9TT",
    "wof:placetype":"postalcode"
},
  "geometry": {"coordinates":[0.38659383689149,52.60491938056461],"type":"Point"}
}