{
  "type": "Feature",
  "properties": {
    "iso:country":"GB",
    "wof:name":"MK18 1XE",
    "wof:placetype":"postalcode"
},
  "geometry": {"coordinates":[-0.9745918029802,52.00435499705654],"type":"Point"}
}