{
  "type": "Feature",
  "properties": {
    "date:inception_lower":"1980-01-01",
    "date:inception_upper":"1980-01-31",
    "iso:country":"GB",
    "wof:name":"S63 0RQ",
    "wof:placetype":"postalcode"
},
  "geometry": {"coordinates":[-1.322286,53.546242],"type":"Point"}
}