{
  "type": "Feature",
  "properties": {
    "iso:country": "GB",
    "wof:name": "HP14 3SP",
    "wof:placetype": "postalcode"
  },
  "geometry": {"coordinates":[-0.892655,51.65777],"type":"Point"}
}
