{
  "type": "Feature",
  "properties": {
    "date:inception_lower":"1990-07-01",
    "date:inception_upper":"1990-07-31",
    "iso:country":"GB",
    "wof:name":"HP14 3SP",
    "wof:placetype":"postalcode"
},
  "geometry": {"coordinates":[-0.892655,51.65777],"type":"Point"}
}