{
  "type": "Feature",
  "properties": {
    "iso:country": "GB",
    "wof:name": "PO12 3BD",
    "wof:placetype": "postalcode"
  },
  "geometry": {"coordinates":[-1.154654,50.811742],"type":"Point"}
}
