{
  "type": "Feature",
  "properties": {
    "date:inception_lower": "1980-01-01",
    "date:inception_upper": "1980-01-01",
    "iso:country": "GB",
    "wof:name": "BN7 3JP",
    "wof:placetype": "postalcode"
  },
  "geometry": {"coordinates":[-0.031004,50.86909],"type":"Point"}
}
