{
  "type": "Feature",
  "properties": {
    "iso:country":"GB",
    "wof:name":"CF5 3DE",
    "wof:placetype":"postalcode"
},
  "geometry": {"coordinates":[-3.24175384786079,51.48830028334953],"type":"Point"}
}