{
  "type": "Feature",
  "properties": {
    "iso:country":"GB",
    "wof:name":"NN15 7JS",
    "wof:placetype":"postalcode"
},
  "geometry": {"coordinates":[-0.74199775765545,52.38937630300476],"type":"Point"}
}