{
  "type": "Feature",
  "properties": {
    "iso:country":"GB",
    "wof:name":"BN27 3SN",
    "wof:placetype":"postalcode"
},
  "geometry": {"coordinates":[0.17519338248145,50.88067778500474],"type":"Point"}
}