{
  "type": "Feature",
  "properties": {
    "iso:country": "GB",
    "wof:name": "WN3 5QJ",
    "wof:placetype": "postalcode"
  },
  "geometry": {"coordinates":[-2.645593,53.519217],"type":"Point"}
}
