{
  "type": "Feature",
  "properties": {
    "iso:country":"GB",
    "wof:name":"WN3 5QJ",
    "wof:placetype":"postalcode"
},
  "geometry": {"coordinates":[-2.64559316613667,53.5192170689296],"type":"Point"}
}