{
  "type": "Feature",
  "properties": {
    "iso:country":"GB",
    "wof:name":"DT4 9SY",
    "wof:placetype":"postalcode"
},
  "geometry": {"coordinates":[-2.49242878608518,50.61142589126791],"type":"Point"}
}