{
  "type": "Feature",
  "properties": {
    "iso:country": "GB",
    "wof:name": "DT4 9SY",
    "wof:placetype": "postalcode"
  },
  "geometry": {"coordinates":[-2.491419,50.611105],"type":"Point"}
}
