{
  "type": "Feature",
  "properties": {
    "iso:country":"GB",
    "wof:name":"LS28 5FS",
    "wof:placetype":"postalcode"
},
  "geometry": {"coordinates":[-1.66642081717754,53.81879701558454],"type":"Point"}
}