{
  "type": "Feature",
  "properties": {
    "date:inception_lower":"2012-08-01",
    "date:inception_upper":"2012-08-31",
    "iso:country":"GB",
    "wof:name":"LS28 5FS",
    "wof:placetype":"postalcode"
},
  "geometry": {"coordinates":[-1.666421,53.818797],"type":"Point"}
}