{
  "type": "Feature",
  "properties": {
    "iso:country":"GB",
    "wof:name":"IP2 0LF",
    "wof:placetype":"postalcode"
},
  "geometry": {"coordinates":[1.12658094932978,52.0492850397439],"type":"Point"}
}