{
  "type": "Feature",
  "properties": {
    "date:inception_lower": "1999-12-01",
    "date:inception_upper": "1999-12-01",
    "iso:country": "GB",
    "wof:name": "CV47 2YD",
    "wof:placetype": "postalcode"
  },
  "geometry": {"coordinates":[-1.392693,52.165461],"type":"Point"}
}
