{
  "type": "Feature",
  "properties": {
    "date:inception_lower": "1999-06-01",
    "date:inception_upper": "1999-06-01",
    "iso:country": "GB",
    "wof:name": "KT10 0RN",
    "wof:placetype": "postalcode"
  },
  "geometry": {"coordinates":[-0.340059,51.361258],"type":"Point"}
}
