{
  "type": "Feature",
  "properties": {
    "date:inception_lower": "2002-06-01",
    "date:inception_upper": "2002-06-01",
    "iso:country": "GB",
    "wof:name": "DE23 3XB",
    "wof:placetype": "postalcode"
  },
  "geometry": {"coordinates":[-1.521228,52.893016],"type":"Point"}
}
