{
  "type": "Feature",
  "properties": {
    "iso:country": "GB",
    "wof:name": "DE23 3XB",
    "wof:placetype": "postalcode"
  },
  "geometry": {"coordinates":[-1.521228,52.893016],"type":"Point"}
}
