{
  "type": "Feature",
  "properties": {
    "iso:country":"GB",
    "wof:name":"UB2 4JA",
    "wof:placetype":"postalcode"
},
  "geometry": {"coordinates":[-0.3688977697016,51.49306019938215],"type":"Point"}
}