{
  "type": "Feature",
  "properties": {
    "iso:country": "GB",
    "wof:name": "GL7 1HR",
    "wof:placetype": "postalcode"
  },
  "geometry": {"coordinates":[-1.948701,51.712815],"type":"Point"}
}
