{
  "type": "Feature",
  "properties": {
    "date:inception_lower": "2006-03-01",
    "date:inception_upper": "2006-03-01",
    "iso:country": "GB",
    "wof:name": "M4 3AJ",
    "wof:placetype": "postalcode"
  },
  "geometry": {"coordinates":[-2.241071,53.484079],"type":"Point"}
}
