{
  "type": "Feature",
  "properties": {
    "date:inception_lower": "2024-02-01",
    "date:inception_upper": "2024-02-01",
    "iso:country": "GB",
    "wof:name": "GU12 6GQ",
    "wof:placetype": "postalcode"
  },
  "geometry": {"coordinates":[-0.722438,51.242577],"type":"Point"}
}
