{
  "type": "Feature",
  "properties": {
    "iso:country":"GB",
    "wof:name":"TW17 9EB",
    "wof:placetype":"postalcode"
},
  "geometry": {"coordinates":[-0.44116323239217,51.39517274822297],"type":"Point"}
}