{
  "type": "Feature",
  "properties": {
    "date:inception_lower":"1980-01-01",
    "date:inception_upper":"1980-01-31",
    "iso:country":"GB",
    "wof:name":"SA38 9JG",
    "wof:placetype":"postalcode"
},
  "geometry": {"coordinates":[-4.443342,52.022347],"type":"Point"}
}