{
  "type": "Feature",
  "properties": {
    "iso:country":"GB",
    "wof:name":"SA38 9JG",
    "wof:placetype":"postalcode"
},
  "geometry": {"coordinates":[-4.44334172654563,52.02234650283518],"type":"Point"}
}