{
  "type": "Feature",
  "properties": {
    "date:inception_lower": "1980-01-01",
    "date:inception_upper": "1980-01-01",
    "iso:country": "GB",
    "wof:name": "WF16 0AT",
    "wof:placetype": "postalcode"
  },
  "geometry": {"coordinates":[-1.67062,53.707339],"type":"Point"}
}
