{
  "type": "Feature",
  "properties": {
    "date:inception_lower": "2021-12-01",
    "date:inception_upper": "2021-12-01",
    "iso:country": "GB",
    "wof:name": "SA14 6EJ",
    "wof:placetype": "postalcode"
  },
  "geometry": {"coordinates":[-4.087878,51.799523],"type":"Point"}
}
