{
  "type": "Feature",
  "properties": {
    "iso:country":"GB",
    "wof:name":"SR1 1LN",
    "wof:placetype":"postalcode"
},
  "geometry": {"coordinates":[-1.37883015517615,54.9050957864233],"type":"Point"}
}