{
  "type": "Feature",
  "properties": {
    "iso:country": "GB",
    "wof:name": "SK14 3PR",
    "wof:placetype": "postalcode"
  },
  "geometry": {"coordinates":[-2.028626,53.442777],"type":"Point"}
}
