{
  "type": "Feature",
  "properties": {
    "iso:country":"GB",
    "wof:name":"SK14 3PR",
    "wof:placetype":"postalcode"
},
  "geometry": {"coordinates":[-2.02862559298036,53.44277653425861],"type":"Point"}
}