{
  "type": "Feature",
  "properties": {
    "iso:country":"GB",
    "wof:name":"SW6 6NH",
    "wof:placetype":"postalcode"
},
  "geometry": {"coordinates":[-0.22039878042984,51.48143176989137],"type":"Point"}
}