{
  "type": "Feature",
  "properties": {
    "iso:country": "GB",
    "wof:name": "SW6 2ST",
    "wof:placetype": "postalcode"
  },
  "geometry": {"coordinates":[-0.185081,51.468849],"type":"Point"}
}
