{
  "type": "Feature",
  "properties": {
    "iso:country":"GB",
    "wof:name":"SW6 2ST",
    "wof:placetype":"postalcode"
},
  "geometry": {"coordinates":[-0.18508075516166,51.4688494802119],"type":"Point"}
}