{
  "type": "Feature",
  "properties": {
    "date:inception_lower": "2021-11-01",
    "date:inception_upper": "2021-11-01",
    "iso:country": "GB",
    "wof:name": "BS14 0GP",
    "wof:placetype": "postalcode"
  },
  "geometry": {"coordinates":[-2.585704,51.411983],"type":"Point"}
}
