{
  "type": "Feature",
  "properties": {
    "iso:country":"GB",
    "wof:name":"NW1 7DB",
    "wof:placetype":"postalcode"
},
  "geometry": {"coordinates":[-0.14689650989397,51.53990452675473],"type":"Point"}
}