{
  "type": "Feature",
  "properties": {
    "iso:country":"GB",
    "wof:name":"ME17 3NH",
    "wof:placetype":"postalcode"
},
  "geometry": {"coordinates":[0.61378114141096,51.22948981010546],"type":"Point"}
}