{
  "type": "Feature",
  "properties": {
    "iso:country": "GB",
    "wof:name": "ME17 3NH",
    "wof:placetype": "postalcode"
  },
  "geometry": {"coordinates":[0.613811,51.229489],"type":"Point"}
}
