{
  "type": "Feature",
  "properties": {
    "iso:country": "GB",
    "wof:name": "CR2 6UR",
    "wof:placetype": "postalcode"
  },
  "geometry": {"coordinates":[-0.0954,51.354604],"type":"Point"}
}
