{
  "type": "Feature",
  "properties": {
    "date:inception_lower": "1996-06-01",
    "date:inception_upper": "1996-06-01",
    "iso:country": "GB",
    "wof:name": "ST14 8HU",
    "wof:placetype": "postalcode"
  },
  "geometry": {"coordinates":[-1.856498,52.90006],"type":"Point"}
}
