{
  "type": "Feature",
  "properties": {
    "date:inception_lower":"1996-06-01",
    "date:inception_upper":"1996-06-30",
    "iso:country":"GB",
    "wof:name":"ST14 8HU",
    "wof:placetype":"postalcode"
},
  "geometry": {"coordinates":[-1.854539,52.899968],"type":"Point"}
}