{
  "type": "Feature",
  "properties": {
    "iso:country":"GB",
    "wof:name":"ST14 8HU",
    "wof:placetype":"postalcode"
},
  "geometry": {"coordinates":[-1.85453858968783,52.89996824614262],"type":"Point"}
}