{
  "type": "Feature",
  "properties": {
    "iso:country": "GB",
    "wof:name": "SY23 4RG",
    "wof:placetype": "postalcode"
  },
  "geometry": {"coordinates":[-3.880762,52.371766],"type":"Point"}
}
