{
  "type": "Feature",
  "properties": {
    "date:inception_lower": "1980-01-01",
    "date:inception_upper": "1980-01-01",
    "iso:country": "GB",
    "wof:name": "SY23 4RG",
    "wof:placetype": "postalcode"
  },
  "geometry": {"coordinates":[-3.880762,52.371766],"type":"Point"}
}
