{
  "type": "Feature",
  "properties": {
    "iso:country":"GB",
    "wof:name":"SY23 4RG",
    "wof:placetype":"postalcode"
},
  "geometry": {"coordinates":[-3.88076216423593,52.37176632426425],"type":"Point"}
}