{
  "type": "Feature",
  "properties": {
    "iso:country":"GB",
    "wof:name":"LN6 9DU",
    "wof:placetype":"postalcode"
},
  "geometry": {"coordinates":[-0.68601411350307,53.19305006649035],"type":"Point"}
}