{
  "type": "Feature",
  "properties": {
    "iso:country": "GB",
    "wof:name": "WV10 0HF",
    "wof:placetype": "postalcode"
  },
  "geometry": {"coordinates":[-2.107417,52.590273],"type":"Point"}
}
