{
  "type": "Feature",
  "properties": {
    "date:inception_lower": "2016-08-01",
    "date:inception_upper": "2016-08-01",
    "iso:country": "GB",
    "wof:name": "DT1 1HE",
    "wof:placetype": "postalcode"
  },
  "geometry": {"coordinates":[-2.437361,50.71009],"type":"Point"}
}
