{
  "type": "Feature",
  "properties": {
    "date:inception_lower":"2001-12-01",
    "date:inception_upper":"2001-12-31",
    "iso:country":"GB",
    "wof:name":"CF32 8RE",
    "wof:placetype":"postalcode"
},
  "geometry": {"coordinates":[-3.588255,51.573132],"type":"Point"}
}