{
  "type": "Feature",
  "properties": {
    "iso:country":"GB",
    "wof:name":"WF4 2HA",
    "wof:placetype":"postalcode"
},
  "geometry": {"coordinates":[-1.40127540681986,53.62334310851266],"type":"Point"}
}