{
  "type": "Feature",
  "properties": {
    "iso:country": "GB",
    "wof:name": "WF4 2HA",
    "wof:placetype": "postalcode"
  },
  "geometry": {"coordinates":[-1.401275,53.623343],"type":"Point"}
}
