{
  "type": "Feature",
  "properties": {
    "iso:country":"GB",
    "wof:name":"EX15 1QX",
    "wof:placetype":"postalcode"
},
  "geometry": {"coordinates":[-3.39213917006662,50.86718769416733],"type":"Point"}
}