{
  "type": "Feature",
  "properties": {
    "iso:country":"GB",
    "wof:name":"BS22 8HB",
    "wof:placetype":"postalcode"
},
  "geometry": {"coordinates":[-2.94660770861481,51.35683326537836],"type":"Point"}
}