{
  "type": "Feature",
  "properties": {
    "iso:country":"GB",
    "wof:name":"LE19 2BT",
    "wof:placetype":"postalcode"
},
  "geometry": {"coordinates":[-1.18442394020944,52.5891248364169],"type":"Point"}
}