{
  "type": "Feature",
  "properties": {
    "date:inception_lower": "1980-01-01",
    "date:inception_upper": "1980-01-01",
    "iso:country": "GB",
    "wof:name": "EX4 6SW",
    "wof:placetype": "postalcode"
  },
  "geometry": {"coordinates":[-3.518838,50.729531],"type":"Point"}
}
