{
  "type": "Feature",
  "properties": {
    "iso:country":"GB",
    "wof:name":"EX22 7XQ",
    "wof:placetype":"postalcode"
},
  "geometry": {"coordinates":[-4.33718736739363,50.92325103817902],"type":"Point"}
}