{
  "type": "Feature",
  "properties": {
    "date:inception_lower": "1980-01-01",
    "date:inception_upper": "1980-01-01",
    "iso:country": "GB",
    "wof:name": "EX22 7XQ",
    "wof:placetype": "postalcode"
  },
  "geometry": {"coordinates":[-4.337187,50.923251],"type":"Point"}
}
