{
  "type": "Feature",
  "properties": {
    "iso:country": "GB",
    "wof:name": "EX22 7XQ",
    "wof:placetype": "postalcode"
  },
  "geometry": {"coordinates":[-4.337187,50.923251],"type":"Point"}
}
