{
  "type": "Feature",
  "properties": {
    "date:inception_lower":"1993-01-01",
    "date:inception_upper":"1993-01-31",
    "iso:country":"GB",
    "wof:name":"GU24 0DT",
    "wof:placetype":"postalcode"
},
  "geometry": {"coordinates":[-0.664589,51.303019],"type":"Point"}
}