{
  "type": "Feature",
  "properties": {
    "iso:country":"GB",
    "wof:name":"GU24 0DT",
    "wof:placetype":"postalcode"
},
  "geometry": {"coordinates":[-0.67385173567003,51.30268318130751],"type":"Point"}
}