{
  "type": "Feature",
  "properties": {
    "date:inception_lower":"2006-09-01",
    "date:inception_upper":"2006-09-30",
    "iso:country":"GB",
    "wof:name":"G53 5TJ",
    "wof:placetype":"postalcode"
},
  "geometry": {"coordinates":[-4.360095,55.83396],"type":"Point"}
}