{
  "type": "Feature",
  "properties": {
    "iso:country":"GB",
    "wof:name":"G53 5TJ",
    "wof:placetype":"postalcode"
},
  "geometry": {"coordinates":[-4.36009540491705,55.83396004044766],"type":"Point"}
}