{
  "type": "Feature",
  "properties": {
    "date:inception_lower": "1987-10-01",
    "date:inception_upper": "1987-10-01",
    "iso:country": "GB",
    "wof:name": "DT1 2BL",
    "wof:placetype": "postalcode"
  },
  "geometry": {"coordinates":[-2.424218,50.708502],"type":"Point"}
}
