{
  "type": "Feature",
  "properties": {
    "iso:country":"GB",
    "wof:name":"DT1 2BL",
    "wof:placetype":"postalcode"
},
  "geometry": {"coordinates":[-2.42431916028459,50.70848364988392],"type":"Point"}
}