{
  "type": "Feature",
  "properties": {
    "iso:country":"GB",
    "wof:name":"PE36 6EF",
    "wof:placetype":"postalcode"
},
  "geometry": {"coordinates":[0.49021305670651,52.94530922860501],"type":"Point"}
}