{
  "type": "Feature",
  "properties": {
    "iso:country":"GB",
    "wof:name":"HG1 5AN",
    "wof:placetype":"postalcode"
},
  "geometry": {"coordinates":[-1.52832993986777,53.99623999765152],"type":"Point"}
}