{
  "type": "Feature",
  "properties": {
    "iso:country": "GB",
    "wof:name": "MK12 5ZQ",
    "wof:placetype": "postalcode"
  },
  "geometry": {"coordinates":[-0.828753,52.047594],"type":"Point"}
}
