{
  "type": "Feature",
  "properties": {
    "date:inception_lower":"1980-01-01",
    "date:inception_upper":"1980-01-31",
    "iso:country":"GB",
    "wof:name":"PL17 8DG",
    "wof:placetype":"postalcode"
},
  "geometry": {"coordinates":[-4.237883,50.505608],"type":"Point"}
}