{
  "type": "Feature",
  "properties": {
    "iso:country":"GB",
    "wof:name":"RG7 6QJ",
    "wof:placetype":"postalcode"
},
  "geometry": {"coordinates":[-1.22045111154937,51.41418584397527],"type":"Point"}
}