{
  "type": "Feature",
  "properties": {
    "iso:country":"GB",
    "wof:name":"L32 8ST",
    "wof:placetype":"postalcode"
},
  "geometry": {"coordinates":[-2.87972259710993,53.48021315368281],"type":"Point"}
}