{
  "type": "Feature",
  "properties": {
    "iso:country": "GB",
    "wof:name": "L32 8ST",
    "wof:placetype": "postalcode"
  },
  "geometry": {"coordinates":[-2.879723,53.480213],"type":"Point"}
}
