{
  "type": "Feature",
  "properties": {
    "iso:country":"GB",
    "wof:name":"CB23 6AL",
    "wof:placetype":"postalcode"
},
  "geometry": {"coordinates":[-0.06778961247392,52.21684791205107],"type":"Point"}
}