{
  "type": "Feature",
  "properties": {
    "iso:country":"GB",
    "wof:name":"SN13 0HT",
    "wof:placetype":"postalcode"
},
  "geometry": {"coordinates":[-2.19921812221012,51.43412216341869],"type":"Point"}
}