{
  "type": "Feature",
  "properties": {
    "iso:country": "GB",
    "wof:name": "SN13 0HT",
    "wof:placetype": "postalcode"
  },
  "geometry": {"coordinates":[-2.199717,51.433976],"type":"Point"}
}
