{
  "type": "Feature",
  "properties": {
    "iso:country":"GB",
    "wof:name":"PE9 4LW",
    "wof:placetype":"postalcode"
},
  "geometry": {"coordinates":[-0.44445079513946,52.71058893395394],"type":"Point"}
}