{
  "type": "Feature",
  "properties": {
    "date:inception_lower": "1980-01-01",
    "date:inception_upper": "1980-01-01",
    "iso:country": "GB",
    "wof:name": "LU1 5LH",
    "wof:placetype": "postalcode"
  },
  "geometry": {"coordinates":[-0.43426,51.873241],"type":"Point"}
}
