{
  "type": "Feature",
  "properties": {
    "iso:country":"GB",
    "wof:name":"LU1 5LH",
    "wof:placetype":"postalcode"
},
  "geometry": {"coordinates":[-0.4342602355721,51.87324060585964],"type":"Point"}
}