{
  "type": "Feature",
  "properties": {
    "iso:country": "GB",
    "wof:name": "TN16 3LL",
    "wof:placetype": "postalcode"
  },
  "geometry": {"coordinates":[0.041532,51.309995],"type":"Point"}
}
