{
  "type": "Feature",
  "properties": {
    "iso:country":"GB",
    "wof:name":"TN16 3LL",
    "wof:placetype":"postalcode"
},
  "geometry": {"coordinates":[0.04153242939609,51.30999498572019],"type":"Point"}
}