{
  "type": "Feature",
  "properties": {
    "iso:country":"GB",
    "wof:name":"S25 4JJ",
    "wof:placetype":"postalcode"
},
  "geometry": {"coordinates":[-1.23571627112654,53.36602665868349],"type":"Point"}
}