{
  "type": "Feature",
  "properties": {
    "iso:country":"GB",
    "wof:name":"WA5 9QG",
    "wof:placetype":"postalcode"
},
  "geometry": {"coordinates":[-2.62204463507657,53.40247193683312],"type":"Point"}
}