{
  "type": "Feature",
  "properties": {
    "iso:country":"GB",
    "wof:name":"CW3 0DP",
    "wof:placetype":"postalcode"
},
  "geometry": {"coordinates":[-2.49417397359763,52.98281774457417],"type":"Point"}
}