{
  "type": "Feature",
  "properties": {
    "iso:country":"GB",
    "wof:name":"BH16 6AH",
    "wof:placetype":"postalcode"
},
  "geometry": {"coordinates":[-2.04393541685853,50.7534652566337],"type":"Point"}
}