{
  "type": "Feature",
  "properties": {
    "iso:country":"GB",
    "wof:name":"PA37 1PP",
    "wof:placetype":"postalcode"
},
  "geometry": {"coordinates":[-5.44285505381835,56.44706618083853],"type":"Point"}
}