{
  "type": "Feature",
  "properties": {
    "iso:country":"GB",
    "wof:name":"SA14 7BD",
    "wof:placetype":"postalcode"
},
  "geometry": {"coordinates":[-4.13479481497454,51.79743104841254],"type":"Point"}
}