{
  "type": "Feature",
  "properties": {
    "iso:country": "GB",
    "wof:name": "NR5 0RT",
    "wof:placetype": "postalcode"
  },
  "geometry": {"coordinates":[1.217839,52.646179],"type":"Point"}
}
