{
  "type": "Feature",
  "properties": {
    "iso:country":"GB",
    "wof:name":"NR5 0RT",
    "wof:placetype":"postalcode"
},
  "geometry": {"coordinates":[1.21783912264958,52.6461792280705],"type":"Point"}
}