{
  "type": "Feature",
  "properties": {
    "date:inception_lower": "1980-01-01",
    "date:inception_upper": "1980-01-01",
    "iso:country": "GB",
    "wof:name": "LL37 2JY",
    "wof:placetype": "postalcode"
  },
  "geometry": {"coordinates":[-4.081942,52.664327],"type":"Point"}
}
