{
  "type": "Feature",
  "properties": {
    "iso:country":"GB",
    "wof:name":"SN10 3AD",
    "wof:placetype":"postalcode"
},
  "geometry": {"coordinates":[-1.98583540986928,51.35119940584956],"type":"Point"}
}