{
  "type": "Feature",
  "properties": {
    "iso:country":"GB",
    "wof:name":"OL4 5BA",
    "wof:placetype":"postalcode"
},
  "geometry": {"coordinates":[-2.07726977654396,53.53475139662202],"type":"Point"}
}