{
  "type": "Feature",
  "properties": {
    "date:inception_lower":"1987-10-01",
    "date:inception_upper":"1987-10-31",
    "iso:country":"GB",
    "wof:name":"OL4 5BA",
    "wof:placetype":"postalcode"
},
  "geometry": {"coordinates":[-2.07727,53.534751],"type":"Point"}
}