{
  "type": "Feature",
  "properties": {
    "iso:country": "GB",
    "wof:name": "EH12 7HQ",
    "wof:placetype": "postalcode"
  },
  "geometry": {"coordinates":[-3.281372,55.940284],"type":"Point"}
}
