{
  "type": "Feature",
  "properties": {
    "date:inception_lower": "2018-04-01",
    "date:inception_upper": "2018-04-01",
    "iso:country": "GB",
    "wof:name": "EX34 7FG",
    "wof:placetype": "postalcode"
  },
  "geometry": {"coordinates":[-4.205836,51.173121],"type":"Point"}
}
