{
  "type": "Feature",
  "properties": {
    "iso:country":"GB",
    "wof:name":"WR9 0AQ",
    "wof:placetype":"postalcode"
},
  "geometry": {"coordinates":[-2.1718386212999,52.25906627756017],"type":"Point"}
}