{
  "type": "Feature",
  "properties": {
    "iso:country": "GB",
    "wof:name": "WR9 0AQ",
    "wof:placetype": "postalcode"
  },
  "geometry": {"coordinates":[-2.171839,52.259066],"type":"Point"}
}
