{
  "type": "Feature",
  "properties": {
    "iso:country":"GB",
    "wof:name":"EX4 1LT",
    "wof:placetype":"postalcode"
},
  "geometry": {"coordinates":[-3.55617103894152,50.71274299132227],"type":"Point"}
}