{
  "type": "Feature",
  "properties": {
    "iso:country": "GB",
    "wof:name": "ML4 1DD",
    "wof:placetype": "postalcode"
  },
  "geometry": {"coordinates":[-4.009537,55.820363],"type":"Point"}
}
