{
  "type": "Feature",
  "properties": {
    "iso:country":"GB",
    "wof:name":"ML4 1DD",
    "wof:placetype":"postalcode"
},
  "geometry": {"coordinates":[-4.00953745355536,55.82036301218591],"type":"Point"}
}