{
  "type": "Feature",
  "properties": {
    "iso:country":"GB",
    "wof:name":"WV6 9QB",
    "wof:placetype":"postalcode"
},
  "geometry": {"coordinates":[-2.16193523968005,52.60778590558175],"type":"Point"}
}