{
  "type": "Feature",
  "properties": {
    "iso:country": "GB",
    "wof:name": "SA14 8DE",
    "wof:placetype": "postalcode"
  },
  "geometry": {"coordinates":[-4.139376,51.704518],"type":"Point"}
}
