{
  "type": "Feature",
  "properties": {
    "iso:country":"GB",
    "wof:name":"SA14 8DE",
    "wof:placetype":"postalcode"
},
  "geometry": {"coordinates":[-4.13951635012723,51.70443429439565],"type":"Point"}
}