{
  "type": "Feature",
  "properties": {
    "date:inception_lower":"2001-12-01",
    "date:inception_upper":"2001-12-31",
    "iso:country":"GB",
    "wof:name":"SL4 5GD",
    "wof:placetype":"postalcode"
},
  "geometry": {"coordinates":[-0.639631,51.485659],"type":"Point"}
}