{
  "type": "Feature",
  "properties": {
    "date:inception_lower": "1980-01-01",
    "date:inception_upper": "1980-01-01",
    "iso:country": "GB",
    "wof:name": "GL15 5QJ",
    "wof:placetype": "postalcode"
  },
  "geometry": {"coordinates":[-2.523153,51.723209],"type":"Point"}
}
