{
  "type": "Feature",
  "properties": {
    "date:inception_lower": "2015-06-01",
    "date:inception_upper": "2015-06-01",
    "iso:country": "GB",
    "wof:name": "IP31 2FG",
    "wof:placetype": "postalcode"
  },
  "geometry": {"coordinates":[0.918868,52.324704],"type":"Point"}
}
