{
  "type": "Feature",
  "properties": {
    "iso:country": "GB",
    "wof:name": "WN2 5RG",
    "wof:placetype": "postalcode"
  },
  "geometry": {"coordinates":[-2.592371,53.510756],"type":"Point"}
}
