{
  "type": "Feature",
  "properties": {
    "iso:country":"GB",
    "wof:name":"WN2 5RG",
    "wof:placetype":"postalcode"
},
  "geometry": {"coordinates":[-2.59237068214814,53.51075587593443],"type":"Point"}
}