{
  "type": "Feature",
  "properties": {
    "date:inception_lower": "2009-03-01",
    "date:inception_upper": "2009-03-01",
    "iso:country": "GB",
    "wof:name": "WS12 4US",
    "wof:placetype": "postalcode"
  },
  "geometry": {"coordinates":[-2.044586,52.712618],"type":"Point"}
}
