{
  "type": "Feature",
  "properties": {
    "iso:country":"GB",
    "wof:name":"WS12 4US",
    "wof:placetype":"postalcode"
},
  "geometry": {"coordinates":[-2.04458628530628,52.7126182663331],"type":"Point"}
}