{
  "type": "Feature",
  "properties": {
    "iso:country":"GB",
    "wof:name":"PE4 6AL",
    "wof:placetype":"postalcode"
},
  "geometry": {"coordinates":[-0.26739379254724,52.60204263562024],"type":"Point"}
}