{
  "type": "Feature",
  "properties": {
    "iso:country":"GB",
    "wof:name":"NE15 8JW",
    "wof:placetype":"postalcode"
},
  "geometry": {"coordinates":[-1.73517893862289,54.99230266019153],"type":"Point"}
}