{
  "type": "Feature",
  "properties": {
    "iso:country":"GB",
    "wof:name":"KY4 9QY",
    "wof:placetype":"postalcode"
},
  "geometry": {"coordinates":[-3.34296783860366,56.10860616966528],"type":"Point"}
}