{
  "type": "Feature",
  "properties": {
    "date:inception_lower":"1993-02-01",
    "date:inception_upper":"1993-02-28",
    "iso:country":"GB",
    "wof:name":"KY4 9QY",
    "wof:placetype":"postalcode"
},
  "geometry": {"coordinates":[-3.342968,56.108606],"type":"Point"}
}