{
  "type": "Feature",
  "properties": {
    "iso:country":"GB",
    "wof:name":"NG2 5NA",
    "wof:placetype":"postalcode"
},
  "geometry": {"coordinates":[-1.12139096791374,52.9266372390236],"type":"Point"}
}