{
  "type": "Feature",
  "properties": {
    "date:inception_lower":"1980-01-01",
    "date:inception_upper":"1980-01-31",
    "iso:country":"GB",
    "wof:name":"CF32 0RH",
    "wof:placetype":"postalcode"
},
  "geometry": {"coordinates":[-3.624021,51.470428],"type":"Point"}
}