{
  "type": "Feature",
  "properties": {
    "iso:country": "GB",
    "wof:name": "CF32 0RH",
    "wof:placetype": "postalcode"
  },
  "geometry": {"coordinates":[-3.624021,51.470428],"type":"Point"}
}
