{
  "type": "Feature",
  "properties": {
    "iso:country":"GB",
    "wof:name":"CF32 0RH",
    "wof:placetype":"postalcode"
},
  "geometry": {"coordinates":[-3.62402085884014,51.47042758436895],"type":"Point"}
}