{
  "type": "Feature",
  "properties": {
    "iso:country":"GB",
    "wof:name":"N1 2BQ",
    "wof:placetype":"postalcode"
},
  "geometry": {"coordinates":[-0.10073092352574,51.53934605023608],"type":"Point"}
}