{
  "type": "Feature",
  "properties": {
    "iso:country": "GB",
    "wof:name": "TF1 5NP",
    "wof:placetype": "postalcode"
  },
  "geometry": {"coordinates":[-2.482535,52.703832],"type":"Point"}
}
