{
  "type": "Feature",
  "properties": {
    "iso:country":"GB",
    "wof:name":"SW19 6AG",
    "wof:placetype":"postalcode"
},
  "geometry": {"coordinates":[-0.22032936378218,51.44546976239245],"type":"Point"}
}