{
  "type": "Feature",
  "properties": {
    "iso:country": "GB",
    "wof:name": "SW19 6AG",
    "wof:placetype": "postalcode"
  },
  "geometry": {"coordinates":[-0.220088,51.445502],"type":"Point"}
}
