{
  "type": "Feature",
  "properties": {
    "iso:country":"GB",
    "wof:name":"DN14 7JG",
    "wof:placetype":"postalcode"
},
  "geometry": {"coordinates":[-0.86759060710377,53.74619784832394],"type":"Point"}
}