{
  "type": "Feature",
  "properties": {
    "iso:country":"GB",
    "wof:name":"CF71 7LD",
    "wof:placetype":"postalcode"
},
  "geometry": {"coordinates":[-3.42944226585434,51.466145727411],"type":"Point"}
}