{
  "type": "Feature",
  "properties": {
    "date:inception_lower": "2003-11-01",
    "date:inception_upper": "2003-11-01",
    "iso:country": "GB",
    "wof:name": "CF71 7LD",
    "wof:placetype": "postalcode"
  },
  "geometry": {"coordinates":[-3.429484,51.466172],"type":"Point"}
}
