{
  "type": "Feature",
  "properties": {
    "iso:country": "GB",
    "wof:name": "DE65 6RT",
    "wof:placetype": "postalcode"
  },
  "geometry": {"coordinates":[-1.597952,52.87845],"type":"Point"}
}
