{
  "type": "Feature",
  "properties": {
    "date:inception_lower": "2017-11-01",
    "date:inception_upper": "2017-11-01",
    "iso:country": "GB",
    "wof:name": "DE65 6RT",
    "wof:placetype": "postalcode"
  },
  "geometry": {"coordinates":[-1.597952,52.87845],"type":"Point"}
}
