{
  "type": "Feature",
  "properties": {
    "iso:country":"GB",
    "wof:name":"EH48 2AU",
    "wof:placetype":"postalcode"
},
  "geometry": {"coordinates":[-3.65811285496285,55.904503413115],"type":"Point"}
}