{
  "type": "Feature",
  "properties": {
    "iso:country":"GB",
    "wof:name":"ME12 3NH",
    "wof:placetype":"postalcode"
},
  "geometry": {"coordinates":[0.79593056801797,51.41858738998103],"type":"Point"}
}