{
  "type": "Feature",
  "properties": {
    "date:inception_lower":"1980-01-01",
    "date:inception_upper":"1980-01-31",
    "iso:country":"GB",
    "wof:name":"BD22 7JA",
    "wof:placetype":"postalcode"
},
  "geometry": {"coordinates":[-1.952314,53.845792],"type":"Point"}
}