{
  "type": "Feature",
  "properties": {
    "iso:country":"GB",
    "wof:name":"NP11 5AE",
    "wof:placetype":"postalcode"
},
  "geometry": {"coordinates":[-3.13193803660382,51.65763852461591],"type":"Point"}
}