{
  "type": "Feature",
  "properties": {
    "iso:country":"GB",
    "wof:name":"DE24 0LQ",
    "wof:placetype":"postalcode"
},
  "geometry": {"coordinates":[-1.41936433323337,52.88867000393525],"type":"Point"}
}