{
  "type": "Feature",
  "properties": {
    "iso:country":"GB",
    "wof:name":"NP7 0PF",
    "wof:placetype":"postalcode"
},
  "geometry": {"coordinates":[-3.13129170979638,51.80044802982768],"type":"Point"}
}