{
  "type": "Feature",
  "properties": {
    "date:inception_lower":"1980-01-01",
    "date:inception_upper":"1980-01-31",
    "iso:country":"GB",
    "wof:name":"NP7 0PF",
    "wof:placetype":"postalcode"
},
  "geometry": {"coordinates":[-3.131292,51.800448],"type":"Point"}
}