{
  "type": "Feature",
  "properties": {
    "iso:country":"GB",
    "wof:name":"LA2 9BZ",
    "wof:placetype":"postalcode"
},
  "geometry": {"coordinates":[-2.7703704954354,53.97423749070644],"type":"Point"}
}