{
  "type": "Feature",
  "properties": {
    "iso:country":"GB",
    "wof:name":"NR6 5HL",
    "wof:placetype":"postalcode"
},
  "geometry": {"coordinates":[1.26589572099272,52.65889319478152],"type":"Point"}
}