{
  "type": "Feature",
  "properties": {
    "iso:country": "GB",
    "wof:name": "NR6 5HL",
    "wof:placetype": "postalcode"
  },
  "geometry": {"coordinates":[1.265896,52.658893],"type":"Point"}
}
