{
  "type": "Feature",
  "properties": {
    "iso:country": "GB",
    "wof:name": "NE48 3BS",
    "wof:placetype": "postalcode"
  },
  "geometry": {"coordinates":[-2.332697,55.114409],"type":"Point"}
}
