{
  "type": "Feature",
  "properties": {
    "iso:country":"GB",
    "wof:name":"NE48 3BS",
    "wof:placetype":"postalcode"
},
  "geometry": {"coordinates":[-2.33269672126527,55.1144089308557],"type":"Point"}
}