{
  "type": "Feature",
  "properties": {
    "iso:country":"GB",
    "wof:name":"CB2 9NT",
    "wof:placetype":"postalcode"
},
  "geometry": {"coordinates":[0.11202079657442,52.16647791703721],"type":"Point"}
}