{
  "type": "Feature",
  "properties": {
    "date:inception_lower": "2014-10-01",
    "date:inception_upper": "2014-10-01",
    "iso:country": "GB",
    "wof:name": "CB2 9NT",
    "wof:placetype": "postalcode"
  },
  "geometry": {"coordinates":[0.112021,52.166478],"type":"Point"}
}
