{
  "type": "Feature",
  "properties": {
    "iso:country":"GB",
    "wof:name":"EX39 3LX",
    "wof:placetype":"postalcode"
},
  "geometry": {"coordinates":[-4.21635221272809,51.02201160458394],"type":"Point"}
}