{
  "type": "Feature",
  "properties": {
    "date:inception_lower":"1995-01-01",
    "date:inception_upper":"1995-01-31",
    "iso:country":"GB",
    "wof:name":"BB7 2EY",
    "wof:placetype":"postalcode"
},
  "geometry": {"coordinates":[-2.380508,53.881441],"type":"Point"}
}