{
  "type": "Feature",
  "properties": {
    "date:inception_lower": "2013-07-01",
    "date:inception_upper": "2013-07-01",
    "iso:country": "GB",
    "wof:name": "CR4 3GE",
    "wof:placetype": "postalcode"
  },
  "geometry": {"coordinates":[-0.17139,51.405401],"type":"Point"}
}
