{
  "type": "Feature",
  "properties": {
    "iso:country":"GB",
    "wof:name":"CA12 4HX",
    "wof:placetype":"postalcode"
},
  "geometry": {"coordinates":[-3.12953589703263,54.60139539335407],"type":"Point"}
}