{
  "type": "Feature",
  "properties": {
    "iso:country": "GB",
    "wof:name": "CA12 4HX",
    "wof:placetype": "postalcode"
  },
  "geometry": {"coordinates":[-3.129536,54.601395],"type":"Point"}
}
