{
  "type": "Feature",
  "properties": {
    "iso:country": "GB",
    "wof:name": "RG5 3AU",
    "wof:placetype": "postalcode"
  },
  "geometry": {"coordinates":[-0.911678,51.459015],"type":"Point"}
}
