{
  "type": "Feature",
  "properties": {
    "iso:country": "GB",
    "wof:name": "BN12 4BQ",
    "wof:placetype": "postalcode"
  },
  "geometry": {"coordinates":[-0.407058,50.812394],"type":"Point"}
}
