{
  "type": "Feature",
  "properties": {
    "iso:country":"GB",
    "wof:name":"BN12 4BQ",
    "wof:placetype":"postalcode"
},
  "geometry": {"coordinates":[-0.40705790649723,50.8123938307218],"type":"Point"}
}