{
  "type": "Feature",
  "properties": {
    "iso:country": "GB",
    "wof:name": "TF1 3QD",
    "wof:placetype": "postalcode"
  },
  "geometry": {"coordinates":[-2.533398,52.71575],"type":"Point"}
}
