{
  "type": "Feature",
  "properties": {
    "iso:country": "GB",
    "wof:name": "HR8 1QJ",
    "wof:placetype": "postalcode"
  },
  "geometry": {"coordinates":[-2.459896,52.109711],"type":"Point"}
}
