{
  "type": "Feature",
  "properties": {
    "iso:country":"GB",
    "wof:name":"HR8 1QJ",
    "wof:placetype":"postalcode"
},
  "geometry": {"coordinates":[-2.45998602580247,52.10971794634838],"type":"Point"}
}