{
  "type": "Feature",
  "properties": {
    "iso:country":"GB",
    "wof:name":"BN17 7AB",
    "wof:placetype":"postalcode"
},
  "geometry": {"coordinates":[-0.54563005014892,50.81042638407513],"type":"Point"}
}