{
  "type": "Feature",
  "properties": {
    "iso:country":"GB",
    "wof:name":"BS26 2BW",
    "wof:placetype":"postalcode"
},
  "geometry": {"coordinates":[-2.81616257038224,51.287381083302],"type":"Point"}
}