{
  "type": "Feature",
  "properties": {
    "iso:country":"GB",
    "wof:name":"BD2 2AF",
    "wof:placetype":"postalcode"
},
  "geometry": {"coordinates":[-1.73204662609718,53.81757726313781],"type":"Point"}
}