{
  "type": "Feature",
  "properties": {
    "iso:country":"GB",
    "wof:name":"YO41 5NF",
    "wof:placetype":"postalcode"
},
  "geometry": {"coordinates":[-0.89049214519501,53.95071808766442],"type":"Point"}
}