{
  "type": "Feature",
  "properties": {
    "date:inception_lower": "1980-01-01",
    "date:inception_upper": "1980-01-01",
    "iso:country": "GB",
    "wof:name": "N8 0QY",
    "wof:placetype": "postalcode"
  },
  "geometry": {"coordinates":[-0.10137,51.586777],"type":"Point"}
}
