{
  "type": "Feature",
  "properties": {
    "iso:country":"GB",
    "wof:name":"N8 0QY",
    "wof:placetype":"postalcode"
},
  "geometry": {"coordinates":[-0.10130876452326,51.58677276937385],"type":"Point"}
}