{
  "type": "Feature",
  "properties": {
    "date:inception_lower":"1987-04-01",
    "date:inception_upper":"1987-04-30",
    "iso:country":"GB",
    "wof:name":"RH14 9UA",
    "wof:placetype":"postalcode"
},
  "geometry": {"coordinates":[-0.451584,51.02209],"type":"Point"}
}