{
  "type": "Feature",
  "properties": {
    "iso:country": "GB",
    "wof:name": "RH14 9UA",
    "wof:placetype": "postalcode"
  },
  "geometry": {"coordinates":[-0.451584,51.02209],"type":"Point"}
}
