{
  "type": "Feature",
  "properties": {
    "iso:country": "GB",
    "wof:name": "BH24 1FB",
    "wof:placetype": "postalcode"
  },
  "geometry": {"coordinates":[-1.780656,50.84287],"type":"Point"}
}
