{
  "type": "Feature",
  "properties": {
    "date:inception_lower": "2024-02-01",
    "date:inception_upper": "2024-02-01",
    "iso:country": "GB",
    "wof:name": "GL3 1QG",
    "wof:placetype": "postalcode"
  },
  "geometry": {"coordinates":[-2.19416,51.878907],"type":"Point"}
}
