{
  "type": "Feature",
  "properties": {
    "iso:country": "GB",
    "wof:name": "CM7 3YU",
    "wof:placetype": "postalcode"
  },
  "geometry": {"coordinates":[0.577252,51.868646],"type":"Point"}
}
