{
  "type": "Feature",
  "properties": {
    "iso:country": "GB",
    "wof:name": "HP19 8LF",
    "wof:placetype": "postalcode"
  },
  "geometry": {"coordinates":[-0.843444,51.826291],"type":"Point"}
}
