{
  "type": "Feature",
  "properties": {
    "iso:country":"GB",
    "wof:name":"HP19 8LF",
    "wof:placetype":"postalcode"
},
  "geometry": {"coordinates":[-0.84344377676959,51.82629146864565],"type":"Point"}
}