{
  "type": "Feature",
  "properties": {
    "iso:country":"GB",
    "wof:name":"E1W 3SR",
    "wof:placetype":"postalcode"
},
  "geometry": {"coordinates":[-0.05114468654186,51.50883021017445],"type":"Point"}
}