{
  "type": "Feature",
  "properties": {
    "iso:country":"GB",
    "wof:name":"NE71 6LD",
    "wof:placetype":"postalcode"
},
  "geometry": {"coordinates":[-2.01556748278979,55.54597698978451],"type":"Point"}
}