{
  "type": "Feature",
  "properties": {
    "date:inception_lower": "1980-01-01",
    "date:inception_upper": "1980-01-01",
    "iso:country": "GB",
    "wof:name": "OL4 4NN",
    "wof:placetype": "postalcode"
  },
  "geometry": {"coordinates":[-2.06485,53.542992],"type":"Point"}
}
