{
  "type": "Feature",
  "properties": {
    "iso:country": "GB",
    "wof:name": "OL4 4NN",
    "wof:placetype": "postalcode"
  },
  "geometry": {"coordinates":[-2.06485,53.542992],"type":"Point"}
}
