{
  "type": "Feature",
  "properties": {
    "date:inception_lower": "1980-01-01",
    "date:inception_upper": "1980-01-01",
    "iso:country": "GB",
    "wof:name": "BA1 2UJ",
    "wof:placetype": "postalcode"
  },
  "geometry": {"coordinates":[-2.374732,51.393284],"type":"Point"}
}
