{
  "type": "Feature",
  "properties": {
    "iso:country": "GB",
    "wof:name": "B80 7HD",
    "wof:placetype": "postalcode"
  },
  "geometry": {"coordinates":[-1.906463,52.278786],"type":"Point"}
}
