{
  "type": "Feature",
  "properties": {
    "iso:country":"GB",
    "wof:name":"B80 7HD",
    "wof:placetype":"postalcode"
},
  "geometry": {"coordinates":[-1.90664701370304,52.27862796522418],"type":"Point"}
}