{
  "type": "Feature",
  "properties": {
    "date:inception_lower": "1980-01-01",
    "date:inception_upper": "1980-01-01",
    "iso:country": "GB",
    "wof:name": "B80 7HD",
    "wof:placetype": "postalcode"
  },
  "geometry": {"coordinates":[-1.906331,52.278822],"type":"Point"}
}
