{
  "type": "Feature",
  "properties": {
    "iso:country":"GB",
    "wof:name":"DD10 0TH",
    "wof:placetype":"postalcode"
},
  "geometry": {"coordinates":[-2.2238952084591,56.87848213127625],"type":"Point"}
}