{
  "type": "Feature",
  "properties": {
    "iso:country":"GB",
    "wof:name":"CW5 5PB",
    "wof:placetype":"postalcode"
},
  "geometry": {"coordinates":[-2.51473551135288,53.06852362805077],"type":"Point"}
}