{
  "type": "Feature",
  "properties": {
    "iso:country": "GB",
    "wof:name": "CW5 5PB",
    "wof:placetype": "postalcode"
  },
  "geometry": {"coordinates":[-2.514735,53.068524],"type":"Point"}
}
