{
  "type": "Feature",
  "properties": {
    "iso:country":"GB",
    "wof:name":"S42 5LT",
    "wof:placetype":"postalcode"
},
  "geometry": {"coordinates":[-1.39251603315819,53.18002125714484],"type":"Point"}
}