{
  "type": "Feature",
  "properties": {
    "iso:country": "GB",
    "wof:name": "TN6 2TG",
    "wof:placetype": "postalcode"
  },
  "geometry": {"coordinates":[0.168535,51.060384],"type":"Point"}
}
