{
  "type": "Feature",
  "properties": {
    "iso:country":"GB",
    "wof:name":"TN6 2TG",
    "wof:placetype":"postalcode"
},
  "geometry": {"coordinates":[0.1685344769477,51.06035914221428],"type":"Point"}
}