{
  "type": "Feature",
  "properties": {
    "iso:country":"GB",
    "wof:name":"SY11 3BQ",
    "wof:placetype":"postalcode"
},
  "geometry": {"coordinates":[-3.00037325175942,52.92470841274871],"type":"Point"}
}