{
  "type": "Feature",
  "properties": {
    "iso:country": "GB",
    "wof:name": "SY11 3BQ",
    "wof:placetype": "postalcode"
  },
  "geometry": {"coordinates":[-3.000373,52.924708],"type":"Point"}
}
