{
  "type": "Feature",
  "properties": {
    "iso:country":"GB",
    "wof:name":"BS27 3UG",
    "wof:placetype":"postalcode"
},
  "geometry": {"coordinates":[-2.75121796476221,51.25753090159549],"type":"Point"}
}