{
  "type": "Feature",
  "properties": {
    "date:inception_lower": "1998-12-01",
    "date:inception_upper": "1998-12-01",
    "iso:country": "GB",
    "wof:name": "BS27 3UG",
    "wof:placetype": "postalcode"
  },
  "geometry": {"coordinates":[-2.751218,51.257531],"type":"Point"}
}
