{
  "type": "Feature",
  "properties": {
    "iso:country":"GB",
    "wof:name":"L4 5UP",
    "wof:placetype":"postalcode"
},
  "geometry": {"coordinates":[-2.96398311093618,53.44349979885109],"type":"Point"}
}