{
  "type": "Feature",
  "properties": {
    "iso:country": "GB",
    "wof:name": "L4 5UP",
    "wof:placetype": "postalcode"
  },
  "geometry": {"coordinates":[-2.963983,53.4435],"type":"Point"}
}
