{
  "type": "Feature",
  "properties": {
    "date:inception_lower": "2012-09-01",
    "date:inception_upper": "2012-09-01",
    "iso:country": "GB",
    "wof:name": "L4 5UP",
    "wof:placetype": "postalcode"
  },
  "geometry": {"coordinates":[-2.963983,53.4435],"type":"Point"}
}
