{
  "type": "Feature",
  "properties": {
    "iso:country":"GB",
    "wof:name":"S70 6ES",
    "wof:placetype":"postalcode"
},
  "geometry": {"coordinates":[-1.49303495304039,53.5512844400423],"type":"Point"}
}