{
  "type": "Feature",
  "properties": {
    "iso:country": "GB",
    "wof:name": "CF62 4PU",
    "wof:placetype": "postalcode"
  },
  "geometry": {"coordinates":[-3.418246,51.399946],"type":"Point"}
}
