{
  "type": "Feature",
  "properties": {
    "iso:country": "GB",
    "wof:name": "CF62 4PU",
    "wof:placetype": "postalcode"
  },
  "geometry": {"coordinates":[-3.417944,51.39986],"type":"Point"}
}
