{
  "type": "Feature",
  "properties": {
    "iso:country":"GB",
    "wof:name":"CF62 4PU",
    "wof:placetype":"postalcode"
},
  "geometry": {"coordinates":[-3.41794392153878,51.39986015845484],"type":"Point"}
}