{
  "type": "Feature",
  "properties": {
    "iso:country":"GB",
    "wof:name":"B34 6HX",
    "wof:placetype":"postalcode"
},
  "geometry": {"coordinates":[-1.79570223649141,52.49616603256919],"type":"Point"}
}