{
  "type": "Feature",
  "properties": {
    "date:inception_lower": "1980-01-01",
    "date:inception_upper": "1980-01-01",
    "iso:country": "GB",
    "wof:name": "B34 6HX",
    "wof:placetype": "postalcode"
  },
  "geometry": {"coordinates":[-1.795702,52.496166],"type":"Point"}
}
