{
  "type": "Feature",
  "properties": {
    "iso:country":"GB",
    "wof:name":"CM17 9DQ",
    "wof:placetype":"postalcode"
},
  "geometry": {"coordinates":[0.13728738905262,51.75981573471682],"type":"Point"}
}