{
  "type": "Feature",
  "properties": {
    "date:inception_lower": "1980-01-01",
    "date:inception_upper": "1980-01-01",
    "iso:country": "GB",
    "wof:name": "CM21 0DZ",
    "wof:placetype": "postalcode"
  },
  "geometry": {"coordinates":[0.145015,51.812164],"type":"Point"}
}
