{
  "type": "Feature",
  "properties": {
    "date:inception_lower": "2022-02-01",
    "date:inception_upper": "2022-02-01",
    "iso:country": "GB",
    "wof:name": "RH14 9YS",
    "wof:placetype": "postalcode"
  },
  "geometry": {"coordinates":[-0.441639,51.024085],"type":"Point"}
}
