{
  "type": "Feature",
  "properties": {
    "iso:country": "GB",
    "wof:name": "G71 6HA",
    "wof:placetype": "postalcode"
  },
  "geometry": {"coordinates":[-4.059955,55.825298],"type":"Point"}
}
