{
  "type": "Feature",
  "properties": {
    "date:inception_lower":"1980-01-01",
    "date:inception_upper":"1980-01-31",
    "iso:country":"GB",
    "wof:name":"G71 6HA",
    "wof:placetype":"postalcode"
},
  "geometry": {"coordinates":[-4.059955,55.825298],"type":"Point"}
}