{
  "type": "Feature",
  "properties": {
    "iso:country":"GB",
    "wof:name":"E2 7LE",
    "wof:placetype":"postalcode"
},
  "geometry": {"coordinates":[-0.07405163959512,51.5267441462271],"type":"Point"}
}