{
  "type": "Feature",
  "properties": {
    "iso:country":"GB",
    "wof:name":"SE5 8SG",
    "wof:placetype":"postalcode"
},
  "geometry": {"coordinates":[-0.09173445053385,51.47170179265389],"type":"Point"}
}