{
  "type": "Feature",
  "properties": {
    "date:inception_lower":"2017-06-01",
    "date:inception_upper":"2017-06-30",
    "iso:country":"GB",
    "wof:name":"ST4 6JR",
    "wof:placetype":"postalcode"
},
  "geometry": {"coordinates":[-2.20787,53.016779],"type":"Point"}
}