{
  "type": "Feature",
  "properties": {
    "iso:country":"GB",
    "wof:name":"ST4 6JR",
    "wof:placetype":"postalcode"
},
  "geometry": {"coordinates":[-2.20787017232667,53.01676179501052],"type":"Point"}
}