{
  "type": "Feature",
  "properties": {
    "iso:country":"GB",
    "wof:name":"DL13 4QD",
    "wof:placetype":"postalcode"
},
  "geometry": {"coordinates":[-1.82515750778684,54.75411091665134],"type":"Point"}
}