{
  "type": "Feature",
  "properties": {
    "date:inception_lower": "1980-01-01",
    "date:inception_upper": "1980-01-01",
    "iso:country": "GB",
    "wof:name": "DL13 4QD",
    "wof:placetype": "postalcode"
  },
  "geometry": {"coordinates":[-1.823053,54.754511],"type":"Point"}
}
