{
  "type": "Feature",
  "properties": {
    "iso:country": "GB",
    "wof:name": "DL13 4QD",
    "wof:placetype": "postalcode"
  },
  "geometry": {"coordinates":[-1.825168,54.754119],"type":"Point"}
}
