{
  "type": "Feature",
  "properties": {
    "iso:country":"GB",
    "wof:name":"WS15 1BW",
    "wof:placetype":"postalcode"
},
  "geometry": {"coordinates":[-1.93341785308059,52.75378943510518],"type":"Point"}
}