{
  "type": "Feature",
  "properties": {
    "date:inception_lower":"2011-05-01",
    "date:inception_upper":"2011-05-31",
    "iso:country":"GB",
    "wof:name":"PE21 6DD",
    "wof:placetype":"postalcode"
},
  "geometry": {"coordinates":[-0.022047,52.975575],"type":"Point"}
}