{
  "type": "Feature",
  "properties": {
    "iso:country":"GB",
    "wof:name":"NR3 3PW",
    "wof:placetype":"postalcode"
},
  "geometry": {"coordinates":[1.28951597166161,52.65436305818719],"type":"Point"}
}