{
  "type": "Feature",
  "properties": {
    "date:inception_lower": "1980-01-01",
    "date:inception_upper": "1980-01-01",
    "iso:country": "GB",
    "wof:name": "NR3 3PW",
    "wof:placetype": "postalcode"
  },
  "geometry": {"coordinates":[1.289516,52.654363],"type":"Point"}
}
