{
  "type": "Feature",
  "properties": {
    "iso:country":"GB",
    "wof:name":"DA12 5AD",
    "wof:placetype":"postalcode"
},
  "geometry": {"coordinates":[0.37067187455396,51.42827890436528],"type":"Point"}
}