{
  "type": "Feature",
  "properties": {
    "iso:country": "GB",
    "wof:name": "DA12 5AD",
    "wof:placetype": "postalcode"
  },
  "geometry": {"coordinates":[0.370715,51.428287],"type":"Point"}
}
