{
  "type": "Feature",
  "properties": {
    "iso:country":"GB",
    "wof:name":"LE8 5RX",
    "wof:placetype":"postalcode"
},
  "geometry": {"coordinates":[-1.14166103750242,52.55662925309414],"type":"Point"}
}