{
  "type": "Feature",
  "properties": {
    "iso:country":"GB",
    "wof:name":"M23 2UG",
    "wof:placetype":"postalcode"
},
  "geometry": {"coordinates":[-2.28833003891228,53.37948448081239],"type":"Point"}
}