{
  "type": "Feature",
  "properties": {
    "iso:country": "GB",
    "wof:name": "M23 2UG",
    "wof:placetype": "postalcode"
  },
  "geometry": {"coordinates":[-2.28833,53.379484],"type":"Point"}
}
