{
  "type": "Feature",
  "properties": {
    "iso:country": "GB",
    "wof:name": "PO33 2DX",
    "wof:placetype": "postalcode"
  },
  "geometry": {"coordinates":[-1.158654,50.725852],"type":"Point"}
}
