{
  "type": "Feature",
  "properties": {
    "date:inception_lower": "1992-08-01",
    "date:inception_upper": "1992-08-01",
    "iso:country": "GB",
    "wof:name": "PO33 2DX",
    "wof:placetype": "postalcode"
  },
  "geometry": {"coordinates":[-1.158654,50.725852],"type":"Point"}
}
