{
  "type": "Feature",
  "properties": {
    "iso:country":"GB",
    "wof:name":"PO33 2DX",
    "wof:placetype":"postalcode"
},
  "geometry": {"coordinates":[-1.15867878876657,50.72586347858702],"type":"Point"}
}