{
  "type": "Feature",
  "properties": {
    "iso:country":"GB",
    "wof:name":"WC1B 3AJ",
    "wof:placetype":"postalcode"
},
  "geometry": {"coordinates":[-0.12972456782985,51.51767234059812],"type":"Point"}
}