{
  "type": "Feature",
  "properties": {
    "iso:country": "GB",
    "wof:name": "DT1 1AG",
    "wof:placetype": "postalcode"
  },
  "geometry": {"coordinates":[-2.439454,50.712483],"type":"Point"}
}
