{
  "type": "Feature",
  "properties": {
    "date:inception_lower": "2005-08-01",
    "date:inception_upper": "2005-08-01",
    "iso:country": "GB",
    "wof:name": "DT1 1AG",
    "wof:placetype": "postalcode"
  },
  "geometry": {"coordinates":[-2.439454,50.712483],"type":"Point"}
}
