{
  "type": "Feature",
  "properties": {
    "iso:country":"GB",
    "wof:name":"DT1 1AG",
    "wof:placetype":"postalcode"
},
  "geometry": {"coordinates":[-2.43945357492046,50.71248327691881],"type":"Point"}
}