{
  "type": "Feature",
  "properties": {
    "iso:country":"GB",
    "wof:name":"TS19 8SY",
    "wof:placetype":"postalcode"
},
  "geometry": {"coordinates":[-1.35999241717638,54.58465742798264],"type":"Point"}
}