{
  "type": "Feature",
  "properties": {
    "iso:country": "GB",
    "wof:name": "RG10 8QY",
    "wof:placetype": "postalcode"
  },
  "geometry": {"coordinates":[-0.824433,51.520021],"type":"Point"}
}
