{
  "type": "Feature",
  "properties": {
    "iso:country":"GB",
    "wof:name":"RG10 8QY",
    "wof:placetype":"postalcode"
},
  "geometry": {"coordinates":[-0.82433113622254,51.51967617187568],"type":"Point"}
}