{
  "type": "Feature",
  "properties": {
    "iso:country":"GB",
    "wof:name":"AB24 2RP",
    "wof:placetype":"postalcode"
},
  "geometry": {"coordinates":[-2.12502021605888,57.17145454500669],"type":"Point"}
}