{
  "type": "Feature",
  "properties": {
    "iso:country": "GB",
    "wof:name": "NR19 2TA",
    "wof:placetype": "postalcode"
  },
  "geometry": {"coordinates":[0.930446,52.679648],"type":"Point"}
}
