{
  "type": "Feature",
  "properties": {
    "iso:country":"GB",
    "wof:name":"BD8 7DY",
    "wof:placetype":"postalcode"
},
  "geometry": {"coordinates":[-1.75948189849591,53.80357817838695],"type":"Point"}
}