{
  "type": "Feature",
  "properties": {
    "iso:country": "GB",
    "wof:name": "TN19 7DH",
    "wof:placetype": "postalcode"
  },
  "geometry": {"coordinates":[0.401233,50.980593],"type":"Point"}
}
