{
  "type": "Feature",
  "properties": {
    "iso:country":"GB",
    "wof:name":"KA13 6QG",
    "wof:placetype":"postalcode"
},
  "geometry": {"coordinates":[-4.72244153841701,55.65260033800489],"type":"Point"}
}