{
  "type": "Feature",
  "properties": {
    "iso:country": "GB",
    "wof:name": "KA13 6QG",
    "wof:placetype": "postalcode"
  },
  "geometry": {"coordinates":[-4.722441,55.6526],"type":"Point"}
}
