{
  "type": "Feature",
  "properties": {
    "iso:country":"GB",
    "wof:name":"SP2 0DL",
    "wof:placetype":"postalcode"
},
  "geometry": {"coordinates":[-1.86514567210421,51.08062834514713],"type":"Point"}
}