{
  "type": "Feature",
  "properties": {
    "iso:country":"GB",
    "wof:name":"GU34 3BU",
    "wof:placetype":"postalcode"
},
  "geometry": {"coordinates":[-0.92226302330856,51.10457013730345],"type":"Point"}
}