{
  "type": "Feature",
  "properties": {
    "iso:country": "GB",
    "wof:name": "GU34 3BU",
    "wof:placetype": "postalcode"
  },
  "geometry": {"coordinates":[-0.922263,51.10457],"type":"Point"}
}
