{
  "type": "Feature",
  "properties": {
    "iso:country": "GB",
    "wof:name": "DE7 5BP",
    "wof:placetype": "postalcode"
  },
  "geometry": {"coordinates":[-1.292614,52.959882],"type":"Point"}
}
