{
  "type": "Feature",
  "properties": {
    "iso:country":"GB",
    "wof:name":"TS26 9QG",
    "wof:placetype":"postalcode"
},
  "geometry": {"coordinates":[-1.2303877029159,54.68320900038929],"type":"Point"}
}