{
  "type": "Feature",
  "properties": {
    "date:inception_lower": "1993-06-01",
    "date:inception_upper": "1993-06-01",
    "iso:country": "GB",
    "wof:name": "AB51 4FS",
    "wof:placetype": "postalcode"
  },
  "geometry": {"coordinates":[-2.395878,57.286862],"type":"Point"}
}
