{
  "type": "Feature",
  "properties": {
    "iso:country":"GB",
    "wof:name":"ST5 9EQ",
    "wof:placetype":"postalcode"
},
  "geometry": {"coordinates":[-2.22999662643367,53.01782668397493],"type":"Point"}
}