{
  "type": "Feature",
  "properties": {
    "iso:country": "GB",
    "wof:name": "IP13 7LJ",
    "wof:placetype": "postalcode"
  },
  "geometry": {"coordinates":[1.320011,52.20227],"type":"Point"}
}
