{
  "type": "Feature",
  "properties": {
    "date:inception_lower": "1999-06-01",
    "date:inception_upper": "1999-06-01",
    "iso:country": "GB",
    "wof:name": "TS16 0RP",
    "wof:placetype": "postalcode"
  },
  "geometry": {"coordinates":[-1.358914,54.526173],"type":"Point"}
}
