{
  "type": "Feature",
  "properties": {
    "date:inception_lower": "1980-01-01",
    "date:inception_upper": "1980-01-01",
    "iso:country": "GB",
    "wof:name": "TA10 9QY",
    "wof:placetype": "postalcode"
  },
  "geometry": {"coordinates":[-2.812651,51.035256],"type":"Point"}
}
