{
  "type": "Feature",
  "properties": {
    "iso:country":"GB",
    "wof:name":"TA10 9QY",
    "wof:placetype":"postalcode"
},
  "geometry": {"coordinates":[-2.81265106531773,51.03525581052754],"type":"Point"}
}