{
  "type": "Feature",
  "properties": {
    "iso:country":"GB",
    "wof:name":"WD3 5PS",
    "wof:placetype":"postalcode"
},
  "geometry": {"coordinates":[-0.53191211967202,51.65324867306374],"type":"Point"}
}