{
  "type": "Feature",
  "properties": {
    "date:inception_lower": "1980-01-01",
    "date:inception_upper": "1980-01-01",
    "iso:country": "GB",
    "wof:name": "WD3 5PS",
    "wof:placetype": "postalcode"
  },
  "geometry": {"coordinates":[-0.531912,51.653249],"type":"Point"}
}
