{
  "type": "Feature",
  "properties": {
    "iso:country":"GB",
    "wof:name":"TS22 5EY",
    "wof:placetype":"postalcode"
},
  "geometry": {"coordinates":[-1.30461003828474,54.61669613007621],"type":"Point"}
}