{
  "type": "Feature",
  "properties": {
    "iso:country":"GB",
    "wof:name":"ML2 8TQ",
    "wof:placetype":"postalcode"
},
  "geometry": {"coordinates":[-3.90748856332263,55.79300609150992],"type":"Point"}
}