{
  "type": "Feature",
  "properties": {
    "iso:country": "GB",
    "wof:name": "PE34 4LJ",
    "wof:placetype": "postalcode"
  },
  "geometry": {"coordinates":[0.306215,52.763181],"type":"Point"}
}
