{
  "type": "Feature",
  "properties": {
    "iso:country": "GB",
    "wof:name": "L11 3DS",
    "wof:placetype": "postalcode"
  },
  "geometry": {"coordinates":[-2.922839,53.453389],"type":"Point"}
}
