{
  "type": "Feature",
  "properties": {
    "iso:country": "GB",
    "wof:name": "SA72 6RA",
    "wof:placetype": "postalcode"
  },
  "geometry": {"coordinates":[-4.973143,51.687748],"type":"Point"}
}
