{
  "type": "Feature",
  "properties": {
    "date:inception_lower":"2004-02-01",
    "date:inception_upper":"2004-02-29",
    "iso:country":"GB",
    "wof:name":"SA72 6RA",
    "wof:placetype":"postalcode"
},
  "geometry": {"coordinates":[-4.973143,51.687748],"type":"Point"}
}