{
  "type": "Feature",
  "properties": {
    "iso:country":"GB",
    "wof:name":"SA72 6RA",
    "wof:placetype":"postalcode"
},
  "geometry": {"coordinates":[-4.97314327911771,51.68774819053446],"type":"Point"}
}