{
  "type": "Feature",
  "properties": {
    "iso:country":"GB",
    "wof:name":"EN1 4TN",
    "wof:placetype":"postalcode"
},
  "geometry": {"coordinates":[-0.06868929697244,51.66627316850524],"type":"Point"}
}