{
  "type": "Feature",
  "properties": {
    "iso:country":"GB",
    "wof:name":"DL1 3JA",
    "wof:placetype":"postalcode"
},
  "geometry": {"coordinates":[-1.52699787447155,54.56151078282972],"type":"Point"}
}