{
  "type": "Feature",
  "properties": {
    "iso:country": "GB",
    "wof:name": "DL1 3JA",
    "wof:placetype": "postalcode"
  },
  "geometry": {"coordinates":[-1.526998,54.561511],"type":"Point"}
}
