{
  "type": "Feature",
  "properties": {
    "iso:country":"GB",
    "wof:name":"OX2 6FA",
    "wof:placetype":"postalcode"
},
  "geometry": {"coordinates":[-1.26337827904406,51.76211058896755],"type":"Point"}
}