{
  "type": "Feature",
  "properties": {
    "date:inception_lower": "1990-07-01",
    "date:inception_upper": "1990-07-01",
    "iso:country": "GB",
    "wof:name": "OX2 6FA",
    "wof:placetype": "postalcode"
  },
  "geometry": {"coordinates":[-1.263378,51.762111],"type":"Point"}
}
