{
  "type": "Feature",
  "properties": {
    "date:inception_lower": "1980-01-01",
    "date:inception_upper": "1980-01-01",
    "iso:country": "GB",
    "wof:name": "NP44 1DU",
    "wof:placetype": "postalcode"
  },
  "geometry": {"coordinates":[-3.025202,51.660103],"type":"Point"}
}
