{
  "type": "Feature",
  "properties": {
    "iso:country":"GB",
    "wof:name":"NP44 1DU",
    "wof:placetype":"postalcode"
},
  "geometry": {"coordinates":[-3.02520224314038,51.66010263416342],"type":"Point"}
}