{
  "type": "Feature",
  "properties": {
    "iso:country":"GB",
    "wof:name":"KA19 8HZ",
    "wof:placetype":"postalcode"
},
  "geometry": {"coordinates":[-4.77689785299661,55.32863075993476],"type":"Point"}
}