{
  "type": "Feature",
  "properties": {
    "date:inception_lower":"1988-03-01",
    "date:inception_upper":"1988-03-31",
    "iso:country":"GB",
    "wof:name":"UB3 3NT",
    "wof:placetype":"postalcode"
},
  "geometry": {"coordinates":[-0.410875,51.504247],"type":"Point"}
}