{
  "type": "Feature",
  "properties": {
    "iso:country":"GB",
    "wof:name":"UB3 3NT",
    "wof:placetype":"postalcode"
},
  "geometry": {"coordinates":[-0.41087455316956,51.50424732203887],"type":"Point"}
}