{
  "type": "Feature",
  "properties": {
    "iso:country": "GB",
    "wof:name": "DA11 0HF",
    "wof:placetype": "postalcode"
  },
  "geometry": {"coordinates":[0.362365,51.441254],"type":"Point"}
}
