{
  "type": "Feature",
  "properties": {
    "iso:country":"GB",
    "wof:name":"BN16 3HU",
    "wof:placetype":"postalcode"
},
  "geometry": {"coordinates":[-0.49802277266745,50.81531803461768],"type":"Point"}
}