{
  "type": "Feature",
  "properties": {
    "iso:country": "GB",
    "wof:name": "MK11 4AE",
    "wof:placetype": "postalcode"
  },
  "geometry": {"coordinates":[-0.834009,52.045704],"type":"Point"}
}
