{
  "type": "Feature",
  "properties": {
    "iso:country": "GB",
    "wof:name": "BS34 5TQ",
    "wof:placetype": "postalcode"
  },
  "geometry": {"coordinates":[-2.601197,51.529696],"type":"Point"}
}
