{
  "type": "Feature",
  "properties": {
    "date:inception_lower":"1997-12-01",
    "date:inception_upper":"1997-12-31",
    "iso:country":"GB",
    "wof:name":"BS34 5TQ",
    "wof:placetype":"postalcode"
},
  "geometry": {"coordinates":[-2.601197,51.529696],"type":"Point"}
}