{
  "type": "Feature",
  "properties": {
    "iso:country":"GB",
    "wof:name":"MK9 2AD",
    "wof:placetype":"postalcode"
},
  "geometry": {"coordinates":[-0.75963214327855,52.04250547873303],"type":"Point"}
}