{
  "type": "Feature",
  "properties": {
    "iso:country":"GB",
    "wof:name":"NW11 7UF",
    "wof:placetype":"postalcode"
},
  "geometry": {"coordinates":[-0.19515923837264,51.5796838761075],"type":"Point"}
}