{
  "type": "Feature",
  "properties": {
    "date:inception_lower":"2017-03-01",
    "date:inception_upper":"2017-03-31",
    "iso:country":"GB",
    "wof:name":"MK18 1WH",
    "wof:placetype":"postalcode"
},
  "geometry": {"coordinates":[-0.99482,51.999298],"type":"Point"}
}