{
  "type": "Feature",
  "properties": {
    "iso:country": "GB",
    "wof:name": "MK18 1WH",
    "wof:placetype": "postalcode"
  },
  "geometry": {"coordinates":[-0.99482,51.999298],"type":"Point"}
}
