{
  "type": "Feature",
  "properties": {
    "iso:country": "GB",
    "wof:name": "L25 6HF",
    "wof:placetype": "postalcode"
  },
  "geometry": {"coordinates":[-2.874186,53.375768],"type":"Point"}
}
