{
  "type": "Feature",
  "properties": {
    "date:inception_lower": "1980-01-01",
    "date:inception_upper": "1980-01-01",
    "iso:country": "GB",
    "wof:name": "L25 6HF",
    "wof:placetype": "postalcode"
  },
  "geometry": {"coordinates":[-2.874186,53.375768],"type":"Point"}
}
