{
  "type": "Feature",
  "properties": {
    "iso:country":"GB",
    "wof:name":"W10 5XP",
    "wof:placetype":"postalcode"
},
  "geometry": {"coordinates":[-0.21242909356612,51.52354804360903],"type":"Point"}
}