{
  "type": "Feature",
  "properties": {
    "date:inception_lower": "1980-01-01",
    "date:inception_upper": "1980-01-01",
    "iso:country": "GB",
    "wof:name": "L14 6UD",
    "wof:placetype": "postalcode"
  },
  "geometry": {"coordinates":[-2.881664,53.413214],"type":"Point"}
}
