{
  "type": "Feature",
  "properties": {
    "iso:country":"GB",
    "wof:name":"CW10 0LE",
    "wof:placetype":"postalcode"
},
  "geometry": {"coordinates":[-2.40275066008062,53.1698216459618],"type":"Point"}
}