{
  "type": "Feature",
  "properties": {
    "iso:country":"GB",
    "wof:name":"WA7 6UT",
    "wof:placetype":"postalcode"
},
  "geometry": {"coordinates":[-2.67911952307991,53.33412473057953],"type":"Point"}
}