{
  "type": "Feature",
  "properties": {
    "date:inception_lower": "2001-12-01",
    "date:inception_upper": "2001-12-01",
    "iso:country": "GB",
    "wof:name": "WA7 6UT",
    "wof:placetype": "postalcode"
  },
  "geometry": {"coordinates":[-2.679119,53.334125],"type":"Point"}
}
