{
  "type": "Feature",
  "properties": {
    "iso:country": "GB",
    "wof:name": "NE38 0DZ",
    "wof:placetype": "postalcode"
  },
  "geometry": {"coordinates":[-1.544917,54.890518],"type":"Point"}
}
