{
  "type": "Feature",
  "properties": {
    "iso:country":"GB",
    "wof:name":"LN4 4RD",
    "wof:placetype":"postalcode"
},
  "geometry": {"coordinates":[-0.15772441725863,53.11152324373475],"type":"Point"}
}