{
  "type": "Feature",
  "properties": {
    "date:inception_lower":"1985-04-01",
    "date:inception_upper":"1985-04-30",
    "iso:country":"GB",
    "wof:name":"LN4 4RD",
    "wof:placetype":"postalcode"
},
  "geometry": {"coordinates":[-0.157704,53.111565],"type":"Point"}
}