{
  "type": "Feature",
  "properties": {
    "iso:country": "GB",
    "wof:name": "G33 1SJ",
    "wof:placetype": "postalcode"
  },
  "geometry": {"coordinates":[-4.193399,55.898502],"type":"Point"}
}
