{
  "type": "Feature",
  "properties": {
    "iso:country":"GB",
    "wof:name":"G33 1SJ",
    "wof:placetype":"postalcode"
},
  "geometry": {"coordinates":[-4.19339874477929,55.89850167747043],"type":"Point"}
}