{
  "type": "Feature",
  "properties": {
    "date:inception_lower": "2009-03-01",
    "date:inception_upper": "2009-03-01",
    "iso:country": "GB",
    "wof:name": "LU7 2AP",
    "wof:placetype": "postalcode"
  },
  "geometry": {"coordinates":[-0.673168,51.916809],"type":"Point"}
}
