{
  "type": "Feature",
  "properties": {
    "iso:country":"GB",
    "wof:name":"LU7 2AP",
    "wof:placetype":"postalcode"
},
  "geometry": {"coordinates":[-0.67316845617066,51.9168093604364],"type":"Point"}
}