{
  "type": "Feature",
  "properties": {
    "date:inception_lower": "1980-01-01",
    "date:inception_upper": "1980-01-01",
    "iso:country": "GB",
    "wof:name": "NE8 1BN",
    "wof:placetype": "postalcode"
  },
  "geometry": {"coordinates":[-1.601067,54.958895],"type":"Point"}
}
