{
  "type": "Feature",
  "properties": {
    "iso:country":"GB",
    "wof:name":"NE8 1BN",
    "wof:placetype":"postalcode"
},
  "geometry": {"coordinates":[-1.60106661403641,54.95889461415361],"type":"Point"}
}