{
  "type": "Feature",
  "properties": {
    "date:inception_lower":"1994-12-01",
    "date:inception_upper":"1994-12-31",
    "iso:country":"GB",
    "wof:name":"SO18 5EE",
    "wof:placetype":"postalcode"
},
  "geometry": {"coordinates":[-1.358402,50.914674],"type":"Point"}
}