{
  "type": "Feature",
  "properties": {
    "iso:country":"GB",
    "wof:name":"SO18 5EE",
    "wof:placetype":"postalcode"
},
  "geometry": {"coordinates":[-1.35838390547584,50.91466523015811],"type":"Point"}
}