{
  "type": "Feature",
  "properties": {
    "iso:country": "GB",
    "wof:name": "SO18 5EE",
    "wof:placetype": "postalcode"
  },
  "geometry": {"coordinates":[-1.358402,50.914674],"type":"Point"}
}
