{
  "type": "Feature",
  "properties": {
    "date:inception_lower": "1980-01-01",
    "date:inception_upper": "1980-01-01",
    "iso:country": "GB",
    "wof:name": "GU9 0AE",
    "wof:placetype": "postalcode"
  },
  "geometry": {"coordinates":[-0.803042,51.218828],"type":"Point"}
}
