{
  "type": "Feature",
  "properties": {
    "iso:country":"GB",
    "wof:name":"GU9 0AE",
    "wof:placetype":"postalcode"
},
  "geometry": {"coordinates":[-0.80327709163462,51.21861474810489],"type":"Point"}
}