{
  "type": "Feature",
  "properties": {
    "iso:country": "GB",
    "wof:name": "BN8 4PY",
    "wof:placetype": "postalcode"
  },
  "geometry": {"coordinates":[-0.031383,50.937308],"type":"Point"}
}
