{
  "type": "Feature",
  "properties": {
    "date:inception_lower":"1980-01-01",
    "date:inception_upper":"1980-01-31",
    "iso:country":"GB",
    "wof:name":"PA2 9ES",
    "wof:placetype":"postalcode"
},
  "geometry": {"coordinates":[-4.451975,55.833744],"type":"Point"}
}