{
  "type": "Feature",
  "properties": {
    "iso:country":"GB",
    "wof:name":"PA2 9ES",
    "wof:placetype":"postalcode"
},
  "geometry": {"coordinates":[-4.45197463233387,55.83374399676074],"type":"Point"}
}