{
  "type": "Feature",
  "properties": {
    "iso:country": "GB",
    "wof:name": "PA2 9ES",
    "wof:placetype": "postalcode"
  },
  "geometry": {"coordinates":[-4.451975,55.833744],"type":"Point"}
}
