{
  "type": "Feature",
  "properties": {
    "iso:country": "GB",
    "wof:name": "NE19 2AD",
    "wof:placetype": "postalcode"
  },
  "geometry": {"coordinates":[-1.9465,55.119251],"type":"Point"}
}
