{
  "type": "Feature",
  "properties": {
    "date:inception_lower": "2002-05-01",
    "date:inception_upper": "2002-05-01",
    "iso:country": "GB",
    "wof:name": "RG14 2FD",
    "wof:placetype": "postalcode"
  },
  "geometry": {"coordinates":[-1.300686,51.405826],"type":"Point"}
}
