{
  "type": "Feature",
  "properties": {
    "iso:country":"GB",
    "wof:name":"RG14 2FD",
    "wof:placetype":"postalcode"
},
  "geometry": {"coordinates":[-1.30068642014471,51.40582595923355],"type":"Point"}
}