{
  "type": "Feature",
  "properties": {
    "date:inception_lower": "2017-12-01",
    "date:inception_upper": "2017-12-01",
    "iso:country": "GB",
    "wof:name": "KA11 2GS",
    "wof:placetype": "postalcode"
  },
  "geometry": {"coordinates":[-4.614218,55.635106],"type":"Point"}
}
