{
  "type": "Feature",
  "properties": {
    "iso:country": "GB",
    "wof:name": "SG1 1ZB",
    "wof:placetype": "postalcode"
  },
  "geometry": {"coordinates":[-0.20122,51.902477],"type":"Point"}
}
