{
  "type": "Feature",
  "properties": {
    "date:inception_lower":"2000-06-01",
    "date:inception_upper":"2000-06-30",
    "iso:country":"GB",
    "wof:name":"SG1 1ZB",
    "wof:placetype":"postalcode"
},
  "geometry": {"coordinates":[-0.20122,51.902477],"type":"Point"}
}