{
  "type": "Feature",
  "properties": {
    "iso:country":"GB",
    "wof:name":"WS3 1PA",
    "wof:placetype":"postalcode"
},
  "geometry": {"coordinates":[-1.98275033606867,52.61568985021854],"type":"Point"}
}