{
  "type": "Feature",
  "properties": {
    "date:inception_lower": "1980-01-01",
    "date:inception_upper": "1980-01-01",
    "iso:country": "GB",
    "wof:name": "HR3 5SU",
    "wof:placetype": "postalcode"
  },
  "geometry": {"coordinates":[-3.027324,52.083095],"type":"Point"}
}
