{
  "type": "Feature",
  "properties": {
    "iso:country": "GB",
    "wof:name": "DY4 0JE",
    "wof:placetype": "postalcode"
  },
  "geometry": {"coordinates":[-2.035676,52.533429],"type":"Point"}
}
