{
  "type": "Feature",
  "properties": {
    "date:inception_lower": "1999-06-01",
    "date:inception_upper": "1999-06-01",
    "iso:country": "GB",
    "wof:name": "NP16 5BZ",
    "wof:placetype": "postalcode"
  },
  "geometry": {"coordinates":[-2.674737,51.640134],"type":"Point"}
}
