{
  "type": "Feature",
  "properties": {
    "iso:country": "GB",
    "wof:name": "DN2 5QG",
    "wof:placetype": "postalcode"
  },
  "geometry": {"coordinates":[-1.093016,53.537442],"type":"Point"}
}
