{
  "type": "Feature",
  "properties": {
    "iso:country":"GB",
    "wof:name":"DN2 5QG",
    "wof:placetype":"postalcode"
},
  "geometry": {"coordinates":[-1.0930161703202,53.53744223639548],"type":"Point"}
}