{
  "type": "Feature",
  "properties": {
    "iso:country":"GB",
    "wof:name":"SG6 1DZ",
    "wof:placetype":"postalcode"
},
  "geometry": {"coordinates":[-0.21181338007952,51.98780021423956],"type":"Point"}
}