{
  "type": "Feature",
  "properties": {
    "iso:country": "GB",
    "wof:name": "SG6 1DZ",
    "wof:placetype": "postalcode"
  },
  "geometry": {"coordinates":[-0.211801,51.987809],"type":"Point"}
}
