{
  "type": "Feature",
  "properties": {
    "iso:country":"GB",
    "wof:name":"CO6 4NL",
    "wof:placetype":"postalcode"
},
  "geometry": {"coordinates":[0.84768370841164,51.97503282728215],"type":"Point"}
}