{
  "type": "Feature",
  "properties": {
    "iso:country": "GB",
    "wof:name": "M17 1HU",
    "wof:placetype": "postalcode"
  },
  "geometry": {"coordinates":[-2.311152,53.468494],"type":"Point"}
}
