{
  "type": "Feature",
  "properties": {
    "iso:country":"GB",
    "wof:name":"KA3 2LY",
    "wof:placetype":"postalcode"
},
  "geometry": {"coordinates":[-4.53146977981744,55.63194597061587],"type":"Point"}
}