{
  "type": "Feature",
  "properties": {
    "iso:country":"GB",
    "wof:name":"B63 2LR",
    "wof:placetype":"postalcode"
},
  "geometry": {"coordinates":[-2.09147470687841,52.45562677035691],"type":"Point"}
}