{
  "type": "Feature",
  "properties": {
    "iso:country":"GB",
    "wof:name":"EH26 8HS",
    "wof:placetype":"postalcode"
},
  "geometry": {"coordinates":[-3.22111097171875,55.82628944983134],"type":"Point"}
}