{
  "type": "Feature",
  "properties": {
    "iso:country":"GB",
    "wof:name":"IP28 7LE",
    "wof:placetype":"postalcode"
},
  "geometry": {"coordinates":[0.51866791769443,52.34335177934592],"type":"Point"}
}