{
  "type": "Feature",
  "properties": {
    "iso:country": "GB",
    "wof:name": "PO8 0LG",
    "wof:placetype": "postalcode"
  },
  "geometry": {"coordinates":[-0.996479,50.942107],"type":"Point"}
}
