{
  "type": "Feature",
  "properties": {
    "iso:country":"GB",
    "wof:name":"PO8 0LG",
    "wof:placetype":"postalcode"
},
  "geometry": {"coordinates":[-0.99647885432077,50.94210680425579],"type":"Point"}
}