{
  "type": "Feature",
  "properties": {
    "iso:country":"GB",
    "wof:name":"KA30 9EY",
    "wof:placetype":"postalcode"
},
  "geometry": {"coordinates":[-4.85634381708701,55.80205555197625],"type":"Point"}
}