{
  "type": "Feature",
  "properties": {
    "iso:country":"GB",
    "wof:name":"SN16 0FB",
    "wof:placetype":"postalcode"
},
  "geometry": {"coordinates":[-2.09458755856038,51.57729860577785],"type":"Point"}
}