{
  "type": "Feature",
  "properties": {
    "date:inception_lower": "2008-06-01",
    "date:inception_upper": "2008-06-01",
    "iso:country": "GB",
    "wof:name": "SN16 0FB",
    "wof:placetype": "postalcode"
  },
  "geometry": {"coordinates":[-2.094631,51.577236],"type":"Point"}
}
