{
  "type": "Feature",
  "properties": {
    "iso:country":"GB",
    "wof:name":"SM2 7BH",
    "wof:placetype":"postalcode"
},
  "geometry": {"coordinates":[-0.2168015508752,51.3549598027876],"type":"Point"}
}