{
  "type": "Feature",
  "properties": {
    "iso:country":"GB",
    "wof:name":"CR4 2JG",
    "wof:placetype":"postalcode"
},
  "geometry": {"coordinates":[-0.16209712196775,51.4076656023424],"type":"Point"}
}