{
  "type": "Feature",
  "properties": {
    "iso:country": "GB",
    "wof:name": "CB24 3AF",
    "wof:placetype": "postalcode"
  },
  "geometry": {"coordinates":[0.066388,52.261197],"type":"Point"}
}
