{
  "type": "Feature",
  "properties": {
    "date:inception_lower": "2016-05-01",
    "date:inception_upper": "2016-05-01",
    "iso:country": "GB",
    "wof:name": "UB10 0GG",
    "wof:placetype": "postalcode"
  },
  "geometry": {"coordinates":[-0.464663,51.540485],"type":"Point"}
}
