{
  "type": "Feature",
  "properties": {
    "iso:country":"GB",
    "wof:name":"OX9 2AJ",
    "wof:placetype":"postalcode"
},
  "geometry": {"coordinates":[-0.99409918152437,51.74647534111009],"type":"Point"}
}