{
  "type": "Feature",
  "properties": {
    "iso:country": "GB",
    "wof:name": "GU14 9XT",
    "wof:placetype": "postalcode"
  },
  "geometry": {"coordinates":[-0.793637,51.298682],"type":"Point"}
}
