{
  "type": "Feature",
  "properties": {
    "date:inception_lower": "1980-10-01",
    "date:inception_upper": "1980-10-01",
    "iso:country": "GB",
    "wof:name": "G73 1NP",
    "wof:placetype": "postalcode"
  },
  "geometry": {"coordinates":[-4.210994,55.833213],"type":"Point"}
}
