{
  "type": "Feature",
  "properties": {
    "iso:country": "GB",
    "wof:name": "G73 1NP",
    "wof:placetype": "postalcode"
  },
  "geometry": {"coordinates":[-4.210994,55.833213],"type":"Point"}
}
