{
  "type": "Feature",
  "properties": {
    "iso:country":"GB",
    "wof:name":"BS5 0EL",
    "wof:placetype":"postalcode"
},
  "geometry": {"coordinates":[-2.56450285322026,51.46160586860012],"type":"Point"}
}