{
  "type": "Feature",
  "properties": {
    "iso:country": "GB",
    "wof:name": "BS5 0EL",
    "wof:placetype": "postalcode"
  },
  "geometry": {"coordinates":[-2.564503,51.461606],"type":"Point"}
}
