{
  "type": "Feature",
  "properties": {
    "iso:country":"GB",
    "wof:name":"CH4 8NZ",
    "wof:placetype":"postalcode"
},
  "geometry": {"coordinates":[-2.91751892390668,53.17397935455963],"type":"Point"}
}