{
  "type": "Feature",
  "properties": {
    "iso:country":"GB",
    "wof:name":"SR4 6DY",
    "wof:placetype":"postalcode"
},
  "geometry": {"coordinates":[-1.39840170531134,54.90935493859058],"type":"Point"}
}