{
  "type": "Feature",
  "properties": {
    "iso:country":"GB",
    "wof:name":"DL7 9NZ",
    "wof:placetype":"postalcode"
},
  "geometry": {"coordinates":[-1.50620951809823,54.32205650907201],"type":"Point"}
}