{
  "type": "Feature",
  "properties": {
    "iso:country": "GB",
    "wof:name": "MK5 8BN",
    "wof:placetype": "postalcode"
  },
  "geometry": {"coordinates":[-0.775848,52.032281],"type":"Point"}
}
