{
  "type": "Feature",
  "properties": {
    "iso:country":"GB",
    "wof:name":"MK5 8BN",
    "wof:placetype":"postalcode"
},
  "geometry": {"coordinates":[-0.77584815238649,52.03228128487084],"type":"Point"}
}