{
  "type": "Feature",
  "properties": {
    "date:inception_lower":"1980-01-01",
    "date:inception_upper":"1980-01-31",
    "iso:country":"GB",
    "wof:name":"CA8 2LG",
    "wof:placetype":"postalcode"
},
  "geometry": {"coordinates":[-2.649512,54.960146],"type":"Point"}
}