{
  "type": "Feature",
  "properties": {
    "iso:country":"GB",
    "wof:name":"TA10 9TD",
    "wof:placetype":"postalcode"
},
  "geometry": {"coordinates":[-2.81667391871434,51.04180117868889],"type":"Point"}
}