{
  "type": "Feature",
  "properties": {
    "iso:country": "GB",
    "wof:name": "TA10 9TD",
    "wof:placetype": "postalcode"
  },
  "geometry": {"coordinates":[-2.816636,51.041795],"type":"Point"}
}
