{
  "type": "Feature",
  "properties": {
    "iso:country":"GB",
    "wof:name":"UB2 5SL",
    "wof:placetype":"postalcode"
},
  "geometry": {"coordinates":[-0.37864322847174,51.49163067361548],"type":"Point"}
}