{
  "type": "Feature",
  "properties": {
    "iso:country":"GB",
    "wof:name":"LA23 2LL",
    "wof:placetype":"postalcode"
},
  "geometry": {"coordinates":[-2.89749838651715,54.37553811440411],"type":"Point"}
}