{
  "type": "Feature",
  "properties": {
    "iso:country":"GB",
    "wof:name":"PH33 7NE",
    "wof:placetype":"postalcode"
},
  "geometry": {"coordinates":[-5.07742712734108,56.83604882985362],"type":"Point"}
}