{
  "type": "Feature",
  "properties": {
    "iso:country": "GB",
    "wof:name": "NE65 0DA",
    "wof:placetype": "postalcode"
  },
  "geometry": {"coordinates":[-1.583753,55.33394],"type":"Point"}
}
