{
  "type": "Feature",
  "properties": {
    "iso:country":"GB",
    "wof:name":"CV2 2AG",
    "wof:placetype":"postalcode"
},
  "geometry": {"coordinates":[-1.4484745494573,52.44018241239056],"type":"Point"}
}