{
  "type": "Feature",
  "properties": {
    "date:inception_lower": "1980-01-01",
    "date:inception_upper": "1980-01-01",
    "iso:country": "GB",
    "wof:name": "CV2 2AG",
    "wof:placetype": "postalcode"
  },
  "geometry": {"coordinates":[-1.448475,52.440182],"type":"Point"}
}
