{
  "type": "Feature",
  "properties": {
    "iso:country": "GB",
    "wof:name": "MK13 7UF",
    "wof:placetype": "postalcode"
  },
  "geometry": {"coordinates":[-0.790693,52.062878],"type":"Point"}
}
