{
  "type": "Feature",
  "properties": {
    "iso:country":"GB",
    "wof:name":"MK13 7UF",
    "wof:placetype":"postalcode"
},
  "geometry": {"coordinates":[-0.79069328959944,52.06287844895776],"type":"Point"}
}