{
  "type": "Feature",
  "properties": {
    "date:inception_lower": "1995-12-01",
    "date:inception_upper": "1995-12-01",
    "iso:country": "GB",
    "wof:name": "MK13 7UF",
    "wof:placetype": "postalcode"
  },
  "geometry": {"coordinates":[-0.790693,52.062878],"type":"Point"}
}
