{
  "type": "Feature",
  "properties": {
    "iso:country": "GB",
    "wof:name": "L26 9TA",
    "wof:placetype": "postalcode"
  },
  "geometry": {"coordinates":[-2.823125,53.362585],"type":"Point"}
}
