{
  "type": "Feature",
  "properties": {
    "iso:country":"GB",
    "wof:name":"L26 9TA",
    "wof:placetype":"postalcode"
},
  "geometry": {"coordinates":[-2.82312455765906,53.36258467029885],"type":"Point"}
}