{
  "type": "Feature",
  "properties": {
    "iso:country": "GB",
    "wof:name": "OX9 2JN",
    "wof:placetype": "postalcode"
  },
  "geometry": {"coordinates":[-1.057004,51.726451],"type":"Point"}
}
