{
  "type": "Feature",
  "properties": {
    "iso:country":"GB",
    "wof:name":"OX9 2JN",
    "wof:placetype":"postalcode"
},
  "geometry": {"coordinates":[-1.0570038369092,51.72645143857066],"type":"Point"}
}