{
  "type": "Feature",
  "properties": {
    "iso:country": "GB",
    "wof:name": "PL14 3LG",
    "wof:placetype": "postalcode"
  },
  "geometry": {"coordinates":[-4.462907,50.452995],"type":"Point"}
}
