{
  "type": "Feature",
  "properties": {
    "iso:country":"GB",
    "wof:name":"LA2 0AX",
    "wof:placetype":"postalcode"
},
  "geometry": {"coordinates":[-2.84630176030669,53.98200448051611],"type":"Point"}
}