{
  "type": "Feature",
  "properties": {
    "date:inception_lower": "1980-01-01",
    "date:inception_upper": "1980-01-01",
    "iso:country": "GB",
    "wof:name": "LA2 0AX",
    "wof:placetype": "postalcode"
  },
  "geometry": {"coordinates":[-2.846302,53.982004],"type":"Point"}
}
