{
  "type": "Feature",
  "properties": {
    "iso:country": "GB",
    "wof:name": "LA2 0AX",
    "wof:placetype": "postalcode"
  },
  "geometry": {"coordinates":[-2.846302,53.982004],"type":"Point"}
}
