{
  "type": "Feature",
  "properties": {
    "iso:country":"GB",
    "wof:name":"B9 4LG",
    "wof:placetype":"postalcode"
},
  "geometry": {"coordinates":[-1.87399525663147,52.47869078001627],"type":"Point"}
}