{
  "type": "Feature",
  "properties": {
    "iso:country":"GB",
    "wof:name":"RM3 8HA",
    "wof:placetype":"postalcode"
},
  "geometry": {"coordinates":[0.21618969449338,51.60574750088305],"type":"Point"}
}