{
  "type": "Feature",
  "properties": {
    "iso:country": "GB",
    "wof:name": "SW11 3UE",
    "wof:placetype": "postalcode"
  },
  "geometry": {"coordinates":[-0.181703,51.466171],"type":"Point"}
}
