{
  "type": "Feature",
  "properties": {
    "iso:country":"GB",
    "wof:name":"SW11 3UE",
    "wof:placetype":"postalcode"
},
  "geometry": {"coordinates":[-0.18170291915864,51.46617132820187],"type":"Point"}
}