{
  "type": "Feature",
  "properties": {
    "iso:country": "GB",
    "wof:name": "G73 3EX",
    "wof:placetype": "postalcode"
  },
  "geometry": {"coordinates":[-4.201206,55.82339],"type":"Point"}
}
