{
  "type": "Feature",
  "properties": {
    "iso:country":"GB",
    "wof:name":"G73 3EX",
    "wof:placetype":"postalcode"
},
  "geometry": {"coordinates":[-4.20120612129389,55.82338994865908],"type":"Point"}
}