{
  "type": "Feature",
  "properties": {
    "iso:country":"GB",
    "wof:name":"DN12 4UG",
    "wof:placetype":"postalcode"
},
  "geometry": {"coordinates":[-1.25273246883755,53.49025081406013],"type":"Point"}
}