{
  "type": "Feature",
  "properties": {
    "date:inception_lower": "1984-02-01",
    "date:inception_upper": "1984-02-01",
    "iso:country": "GB",
    "wof:name": "DN12 4UG",
    "wof:placetype": "postalcode"
  },
  "geometry": {"coordinates":[-1.252732,53.490251],"type":"Point"}
}
