{
  "type": "Feature",
  "properties": {
    "iso:country": "GB",
    "wof:name": "OX13 6HQ",
    "wof:placetype": "postalcode"
  },
  "geometry": {"coordinates":[-1.29937,51.68719],"type":"Point"}
}
