{
  "type": "Feature",
  "properties": {
    "date:inception_lower": "1980-01-01",
    "date:inception_upper": "1980-01-01",
    "iso:country": "GB",
    "wof:name": "GU22 8TY",
    "wof:placetype": "postalcode"
  },
  "geometry": {"coordinates":[-0.502505,51.323602],"type":"Point"}
}
