{
  "type": "Feature",
  "properties": {
    "iso:country": "GB",
    "wof:name": "AB24 3YS",
    "wof:placetype": "postalcode"
  },
  "geometry": {"coordinates":[-2.108841,57.163762],"type":"Point"}
}
