{
  "type": "Feature",
  "properties": {
    "iso:country":"GB",
    "wof:name":"AB24 3YS",
    "wof:placetype":"postalcode"
},
  "geometry": {"coordinates":[-2.10884078157188,57.16376224803454],"type":"Point"}
}