{
  "type": "Feature",
  "properties": {
    "date:inception_lower": "1996-06-01",
    "date:inception_upper": "1996-06-01",
    "iso:country": "GB",
    "wof:name": "AB24 3YS",
    "wof:placetype": "postalcode"
  },
  "geometry": {"coordinates":[-2.108841,57.163762],"type":"Point"}
}
