{
  "type": "Feature",
  "properties": {
    "iso:country":"GB",
    "wof:name":"HR2 7DA",
    "wof:placetype":"postalcode"
},
  "geometry": {"coordinates":[-2.73511450224211,52.04650257564549],"type":"Point"}
}