{
  "type": "Feature",
  "properties": {
    "date:inception_lower":"1980-01-01",
    "date:inception_upper":"1980-01-31",
    "iso:country":"GB",
    "wof:name":"BB4 7RF",
    "wof:placetype":"postalcode"
},
  "geometry": {"coordinates":[-2.282007,53.704726],"type":"Point"}
}