{
  "type": "Feature",
  "properties": {
    "iso:country":"GB",
    "wof:name":"BB4 7RF",
    "wof:placetype":"postalcode"
},
  "geometry": {"coordinates":[-2.28200700767031,53.70472592333035],"type":"Point"}
}