{
  "type": "Feature",
  "properties": {
    "iso:country":"GB",
    "wof:name":"NE46 4JR",
    "wof:placetype":"postalcode"
},
  "geometry": {"coordinates":[-2.08768069836922,54.97790206129226],"type":"Point"}
}