{
  "type": "Feature",
  "properties": {
    "date:inception_lower":"1991-03-01",
    "date:inception_upper":"1991-03-31",
    "iso:country":"GB",
    "wof:name":"KY11 2TD",
    "wof:placetype":"postalcode"
},
  "geometry": {"coordinates":[-3.440732,56.042197],"type":"Point"}
}