{
  "type": "Feature",
  "properties": {
    "iso:country": "GB",
    "wof:name": "KY11 2TD",
    "wof:placetype": "postalcode"
  },
  "geometry": {"coordinates":[-3.440732,56.042197],"type":"Point"}
}
