{
  "type": "Feature",
  "properties": {
    "iso:country":"GB",
    "wof:name":"KY11 2TD",
    "wof:placetype":"postalcode"
},
  "geometry": {"coordinates":[-3.44073205509576,56.04219651909587],"type":"Point"}
}