{
  "type": "Feature",
  "properties": {
    "iso:country":"GB",
    "wof:name":"B8 1NR",
    "wof:placetype":"postalcode"
},
  "geometry": {"coordinates":[-1.8537700546409,52.4904893519432],"type":"Point"}
}