{
  "type": "Feature",
  "properties": {
    "date:inception_lower": "1980-01-01",
    "date:inception_upper": "1980-01-01",
    "iso:country": "GB",
    "wof:name": "E17 9JW",
    "wof:placetype": "postalcode"
  },
  "geometry": {"coordinates":[-0.007184,51.579978],"type":"Point"}
}
