{
  "type": "Feature",
  "properties": {
    "iso:country":"GB",
    "wof:name":"E17 9JW",
    "wof:placetype":"postalcode"
},
  "geometry": {"coordinates":[-0.00718365405139,51.57997847999101],"type":"Point"}
}