{
  "type": "Feature",
  "properties": {
    "iso:country":"GB",
    "wof:name":"IG3 8SD",
    "wof:placetype":"postalcode"
},
  "geometry": {"coordinates":[0.10507356175818,51.56796444541553],"type":"Point"}
}