{
  "type": "Feature",
  "properties": {
    "iso:country":"GB",
    "wof:name":"EX5 1BS",
    "wof:placetype":"postalcode"
},
  "geometry": {"coordinates":[-3.45597948398551,50.71071020589977],"type":"Point"}
}