{
  "type": "Feature",
  "properties": {
    "date:inception_lower": "2004-09-01",
    "date:inception_upper": "2004-09-01",
    "iso:country": "GB",
    "wof:name": "IG10 3BF",
    "wof:placetype": "postalcode"
  },
  "geometry": {"coordinates":[0.060465,51.638685],"type":"Point"}
}
