{
  "type": "Feature",
  "properties": {
    "iso:country": "GB",
    "wof:name": "IG10 3BF",
    "wof:placetype": "postalcode"
  },
  "geometry": {"coordinates":[0.06048,51.638647],"type":"Point"}
}
