{
  "type": "Feature",
  "properties": {
    "iso:country":"GB",
    "wof:name":"NR34 8HF",
    "wof:placetype":"postalcode"
},
  "geometry": {"coordinates":[1.53857176391409,52.45319078464504],"type":"Point"}
}