{
  "type": "Feature",
  "properties": {
    "iso:country":"GB",
    "wof:name":"SR2 0NE",
    "wof:placetype":"postalcode"
},
  "geometry": {"coordinates":[-1.36630497180868,54.86546354064095],"type":"Point"}
}