{
  "type": "Feature",
  "properties": {
    "iso:country": "GB",
    "wof:name": "BN25 3BY",
    "wof:placetype": "postalcode"
  },
  "geometry": {"coordinates":[0.119219,50.782759],"type":"Point"}
}
