{
  "type": "Feature",
  "properties": {
    "iso:country": "GB",
    "wof:name": "FK8 2JS",
    "wof:placetype": "postalcode"
  },
  "geometry": {"coordinates":[-3.946541,56.112472],"type":"Point"}
}
