{
  "type": "Feature",
  "properties": {
    "iso:country":"GB",
    "wof:name":"M24 2AH",
    "wof:placetype":"postalcode"
},
  "geometry": {"coordinates":[-2.18135352474916,53.54422919949498],"type":"Point"}
}