{
  "type": "Feature",
  "properties": {
    "iso:country":"GB",
    "wof:name":"B32 2PE",
    "wof:placetype":"postalcode"
},
  "geometry": {"coordinates":[-1.98132528373153,52.45656890089837],"type":"Point"}
}