{
  "type": "Feature",
  "properties": {
    "iso:country":"GB",
    "wof:name":"UB5 6FU",
    "wof:placetype":"postalcode"
},
  "geometry": {"coordinates":[-0.37938470842664,51.53001986230927],"type":"Point"}
}