{
  "type": "Feature",
  "properties": {
    "iso:country":"GB",
    "wof:name":"LE16 7XE",
    "wof:placetype":"postalcode"
},
  "geometry": {"coordinates":[-0.89861727638819,52.4801243560075],"type":"Point"}
}