{
  "type": "Feature",
  "properties": {
    "iso:country": "GB",
    "wof:name": "LE16 7XE",
    "wof:placetype": "postalcode"
  },
  "geometry": {"coordinates":[-0.898617,52.480124],"type":"Point"}
}
