{
  "type": "Feature",
  "properties": {
    "iso:country":"GB",
    "wof:name":"G20 0BB",
    "wof:placetype":"postalcode"
},
  "geometry": {"coordinates":[-4.29965609232487,55.89950104483417],"type":"Point"}
}