{
  "type": "Feature",
  "properties": {
    "iso:country":"GB",
    "wof:name":"DL5 6JD",
    "wof:placetype":"postalcode"
},
  "geometry": {"coordinates":[-1.5520112446308,54.62147633248417],"type":"Point"}
}