{
  "type": "Feature",
  "properties": {
    "iso:country":"GB",
    "wof:name":"LS28 7PQ",
    "wof:placetype":"postalcode"
},
  "geometry": {"coordinates":[-1.68522183340483,53.79896637107981],"type":"Point"}
}