{
  "type": "Feature",
  "properties": {
    "date:inception_lower": "1983-01-01",
    "date:inception_upper": "1983-01-01",
    "iso:country": "GB",
    "wof:name": "CB7 5TE",
    "wof:placetype": "postalcode"
  },
  "geometry": {"coordinates":[0.406999,52.340438],"type":"Point"}
}
