{
  "type": "Feature",
  "properties": {
    "iso:country":"GB",
    "wof:name":"CB7 5TE",
    "wof:placetype":"postalcode"
},
  "geometry": {"coordinates":[0.40699909496761,52.34043793186682],"type":"Point"}
}