{
  "type": "Feature",
  "properties": {
    "iso:country": "GB",
    "wof:name": "CB7 5TE",
    "wof:placetype": "postalcode"
  },
  "geometry": {"coordinates":[0.406999,52.340438],"type":"Point"}
}
