{
  "type": "Feature",
  "properties": {
    "date:inception_lower": "1986-07-01",
    "date:inception_upper": "1986-07-01",
    "iso:country": "GB",
    "wof:name": "TN39 3LW",
    "wof:placetype": "postalcode"
  },
  "geometry": {"coordinates":[0.455204,50.8417],"type":"Point"}
}
