{
  "type": "Feature",
  "properties": {
    "iso:country": "GB",
    "wof:name": "TS14 6TT",
    "wof:placetype": "postalcode"
  },
  "geometry": {"coordinates":[-1.058328,54.54024],"type":"Point"}
}
