{
  "type": "Feature",
  "properties": {
    "iso:country":"GB",
    "wof:name":"BN21 1HL",
    "wof:placetype":"postalcode"
},
  "geometry": {"coordinates":[0.26157093868488,50.77134252636885],"type":"Point"}
}