{
  "type": "Feature",
  "properties": {
    "iso:country":"GB",
    "wof:name":"M34 7DA",
    "wof:placetype":"postalcode"
},
  "geometry": {"coordinates":[-2.10843414722586,53.43795768509125],"type":"Point"}
}