{
  "type": "Feature",
  "properties": {
    "date:inception_lower":"2013-07-01",
    "date:inception_upper":"2013-07-31",
    "iso:country":"GB",
    "wof:name":"EH4 5ES",
    "wof:placetype":"postalcode"
},
  "geometry": {"coordinates":[-3.279253,55.979425],"type":"Point"}
}