{
  "type": "Feature",
  "properties": {
    "iso:country": "GB",
    "wof:name": "RG7 1JQ",
    "wof:placetype": "postalcode"
  },
  "geometry": {"coordinates":[-0.996589,51.393539],"type":"Point"}
}
