{
  "type": "Feature",
  "properties": {
    "iso:country":"GB",
    "wof:name":"RG7 1JQ",
    "wof:placetype":"postalcode"
},
  "geometry": {"coordinates":[-0.99661070805408,51.39353788223551],"type":"Point"}
}