{
  "type": "Feature",
  "properties": {
    "iso:country": "GB",
    "wof:name": "KT20 5PB",
    "wof:placetype": "postalcode"
  },
  "geometry": {"coordinates":[-0.22052,51.310134],"type":"Point"}
}
