{
  "type": "Feature",
  "properties": {
    "iso:country": "GB",
    "wof:name": "LS13 1DW",
    "wof:placetype": "postalcode"
  },
  "geometry": {"coordinates":[-1.645685,53.817237],"type":"Point"}
}
