{
  "type": "Feature",
  "properties": {
    "iso:country":"GB",
    "wof:name":"TS5 7QN",
    "wof:placetype":"postalcode"
},
  "geometry": {"coordinates":[-1.23794284019055,54.55298140134609],"type":"Point"}
}