{
  "type": "Feature",
  "properties": {
    "iso:country": "GB",
    "wof:name": "L8 8AQ",
    "wof:placetype": "postalcode"
  },
  "geometry": {"coordinates":[-2.960511,53.391033],"type":"Point"}
}
