{
  "type": "Feature",
  "properties": {
    "iso:country":"GB",
    "wof:name":"BB1 1EZ",
    "wof:placetype":"postalcode"
},
  "geometry": {"coordinates":[-2.47890002291863,53.74699174491749],"type":"Point"}
}