{
  "type": "Feature",
  "properties": {
    "iso:country":"GB",
    "wof:name":"IP31 1JH",
    "wof:placetype":"postalcode"
},
  "geometry": {"coordinates":[0.76669932855763,52.30569674283817],"type":"Point"}
}