{
  "type": "Feature",
  "properties": {
    "iso:country": "GB",
    "wof:name": "IP31 1JH",
    "wof:placetype": "postalcode"
  },
  "geometry": {"coordinates":[0.766728,52.305714],"type":"Point"}
}
