{
  "type": "Feature",
  "properties": {
    "date:inception_lower": "1980-01-01",
    "date:inception_upper": "1980-01-01",
    "iso:country": "GB",
    "wof:name": "IP31 1JH",
    "wof:placetype": "postalcode"
  },
  "geometry": {"coordinates":[0.767885,52.305669],"type":"Point"}
}
