{
  "type": "Feature",
  "properties": {
    "iso:country": "GB",
    "wof:name": "SW17 0DZ",
    "wof:placetype": "postalcode"
  },
  "geometry": {"coordinates":[-0.17361,51.430867],"type":"Point"}
}
