{
  "type": "Feature",
  "properties": {
    "date:inception_lower": "1980-01-01",
    "date:inception_upper": "1980-01-01",
    "iso:country": "GB",
    "wof:name": "SW17 0DZ",
    "wof:placetype": "postalcode"
  },
  "geometry": {"coordinates":[-0.173627,51.430885],"type":"Point"}
}
