{
  "type": "Feature",
  "properties": {
    "iso:country":"GB",
    "wof:name":"SW17 0DZ",
    "wof:placetype":"postalcode"
},
  "geometry": {"coordinates":[-0.17361014037019,51.4308666517101],"type":"Point"}
}