{
  "type": "Feature",
  "properties": {
    "iso:country":"GB",
    "wof:name":"CM12 0SU",
    "wof:placetype":"postalcode"
},
  "geometry": {"coordinates":[0.41171070233118,51.63791849763898],"type":"Point"}
}