{
  "type": "Feature",
  "properties": {
    "iso:country":"GB",
    "wof:name":"SM1 3EP",
    "wof:placetype":"postalcode"
},
  "geometry": {"coordinates":[-0.19231860926235,51.37673345609966],"type":"Point"}
}