{
  "type": "Feature",
  "properties": {
    "iso:country": "GB",
    "wof:name": "WA10 4QS",
    "wof:placetype": "postalcode"
  },
  "geometry": {"coordinates":[-2.770636,53.458297],"type":"Point"}
}
