{
  "type": "Feature",
  "properties": {
    "date:inception_lower": "2017-02-01",
    "date:inception_upper": "2017-02-01",
    "iso:country": "GB",
    "wof:name": "W13 0FH",
    "wof:placetype": "postalcode"
  },
  "geometry": {"coordinates":[-0.322929,51.516423],"type":"Point"}
}
