{
  "type": "Feature",
  "properties": {
    "iso:country": "GB",
    "wof:name": "CF15 9QH",
    "wof:placetype": "postalcode"
  },
  "geometry": {"coordinates":[-3.293885,51.526304],"type":"Point"}
}
