{
  "type": "Feature",
  "properties": {
    "iso:country":"GB",
    "wof:name":"CF15 9QH",
    "wof:placetype":"postalcode"
},
  "geometry": {"coordinates":[-3.29403306051761,51.52627450685706],"type":"Point"}
}