{
  "type": "Feature",
  "properties": {
    "iso:country":"GB",
    "wof:name":"WF17 6HH",
    "wof:placetype":"postalcode"
},
  "geometry": {"coordinates":[-1.61269790034728,53.71631560942461],"type":"Point"}
}