{
  "type": "Feature",
  "properties": {
    "date:inception_lower": "1994-05-01",
    "date:inception_upper": "1994-05-01",
    "iso:country": "GB",
    "wof:name": "LL24 0DN",
    "wof:placetype": "postalcode"
  },
  "geometry": {"coordinates":[-3.822722,53.092712],"type":"Point"}
}
