{
  "type": "Feature",
  "properties": {
    "iso:country":"GB",
    "wof:name":"PO5 1LH",
    "wof:placetype":"postalcode"
},
  "geometry": {"coordinates":[-1.08625239153903,50.78998605205803],"type":"Point"}
}