{
  "type": "Feature",
  "properties": {
    "iso:country":"GB",
    "wof:name":"HX4 8HE",
    "wof:placetype":"postalcode"
},
  "geometry": {"coordinates":[-1.86093881944668,53.68897020258345],"type":"Point"}
}