{
  "type": "Feature",
  "properties": {
    "iso:country": "GB",
    "wof:name": "WA11 9PN",
    "wof:placetype": "postalcode"
  },
  "geometry": {"coordinates":[-2.723402,53.466934],"type":"Point"}
}
