{
  "type": "Feature",
  "properties": {
    "iso:country":"GB",
    "wof:name":"CO2 8BY",
    "wof:placetype":"postalcode"
},
  "geometry": {"coordinates":[0.91725769917714,51.8727083636303],"type":"Point"}
}