{
  "type": "Feature",
  "properties": {
    "iso:country":"GB",
    "wof:name":"CO4 5LU",
    "wof:placetype":"postalcode"
},
  "geometry": {"coordinates":[0.90310962432035,51.91536445282816],"type":"Point"}
}