{
  "type": "Feature",
  "properties": {
    "iso:country": "GB",
    "wof:name": "IP10 0AZ",
    "wof:placetype": "postalcode"
  },
  "geometry": {"coordinates":[1.276878,52.037535],"type":"Point"}
}
