{
  "type": "Feature",
  "properties": {
    "iso:country": "GB",
    "wof:name": "HR1 4JE",
    "wof:placetype": "postalcode"
  },
  "geometry": {"coordinates":[-2.539786,52.068598],"type":"Point"}
}
