{
  "type": "Feature",
  "properties": {
    "iso:country":"GB",
    "wof:name":"HR1 4JE",
    "wof:placetype":"postalcode"
},
  "geometry": {"coordinates":[-2.53978554561149,52.0685978473359],"type":"Point"}
}