{
  "type": "Feature",
  "properties": {
    "iso:country": "GB",
    "wof:name": "SW8 5JJ",
    "wof:placetype": "postalcode"
  },
  "geometry": {"coordinates":[-0.13494,51.477487],"type":"Point"}
}
