{
  "type": "Feature",
  "properties": {
    "iso:country":"GB",
    "wof:name":"HU6 7JY",
    "wof:placetype":"postalcode"
},
  "geometry": {"coordinates":[-0.35381494634504,53.77267545319322],"type":"Point"}
}