{
  "type": "Feature",
  "properties": {
    "iso:country": "GB",
    "wof:name": "OX15 0QH",
    "wof:placetype": "postalcode"
  },
  "geometry": {"coordinates":[-1.328423,51.982529],"type":"Point"}
}
