{
  "type": "Feature",
  "properties": {
    "iso:country":"GB",
    "wof:name":"IP22 2EY",
    "wof:placetype":"postalcode"
},
  "geometry": {"coordinates":[1.07597509810746,52.45482396163597],"type":"Point"}
}