{
  "type": "Feature",
  "properties": {
    "iso:country": "GB",
    "wof:name": "CO5 0DG",
    "wof:placetype": "postalcode"
  },
  "geometry": {"coordinates":[0.74917,51.81626],"type":"Point"}
}
