{
  "type": "Feature",
  "properties": {
    "iso:country":"GB",
    "wof:name":"HP6 6RL",
    "wof:placetype":"postalcode"
},
  "geometry": {"coordinates":[-0.56008379213773,51.67066400537976],"type":"Point"}
}