{
  "type": "Feature",
  "properties": {
    "iso:country": "GB",
    "wof:name": "HP6 6RL",
    "wof:placetype": "postalcode"
  },
  "geometry": {"coordinates":[-0.560084,51.670664],"type":"Point"}
}
