{
  "type": "Feature",
  "properties": {
    "date:inception_lower": "1980-01-01",
    "date:inception_upper": "1980-01-01",
    "iso:country": "GB",
    "wof:name": "HP6 6RL",
    "wof:placetype": "postalcode"
  },
  "geometry": {"coordinates":[-0.560084,51.670664],"type":"Point"}
}
