{
  "type": "Feature",
  "properties": {
    "iso:country":"GB",
    "wof:name":"LE16 8LL",
    "wof:placetype":"postalcode"
},
  "geometry": {"coordinates":[-0.89388387753024,52.46629792334292],"type":"Point"}
}