{
  "type": "Feature",
  "properties": {
    "iso:country": "GB",
    "wof:name": "LE16 8LL",
    "wof:placetype": "postalcode"
  },
  "geometry": {"coordinates":[-0.885903,52.461223],"type":"Point"}
}
