{
  "type": "Feature",
  "properties": {
    "iso:country":"GB",
    "wof:name":"DL14 6UB",
    "wof:placetype":"postalcode"
},
  "geometry": {"coordinates":[-1.68498023820774,54.65575697350749],"type":"Point"}
}