{
  "type": "Feature",
  "properties": {
    "iso:country": "GB",
    "wof:name": "EX17 4TX",
    "wof:placetype": "postalcode"
  },
  "geometry": {"coordinates":[-3.774942,50.88979],"type":"Point"}
}
