{
  "type": "Feature",
  "properties": {
    "iso:country":"GB",
    "wof:name":"EX17 4TX",
    "wof:placetype":"postalcode"
},
  "geometry": {"coordinates":[-3.77494205868845,50.88979042599059],"type":"Point"}
}