{
  "type": "Feature",
  "properties": {
    "date:inception_lower": "1980-01-01",
    "date:inception_upper": "1980-01-01",
    "iso:country": "GB",
    "wof:name": "EX17 4TX",
    "wof:placetype": "postalcode"
  },
  "geometry": {"coordinates":[-3.774942,50.88979],"type":"Point"}
}
