{
  "type": "Feature",
  "properties": {
    "iso:country":"GB",
    "wof:name":"G42 8QZ",
    "wof:placetype":"postalcode"
},
  "geometry": {"coordinates":[-4.27016279202592,55.83522187301385],"type":"Point"}
}