{
  "type": "Feature",
  "properties": {
    "iso:country": "GB",
    "wof:name": "PE32 1WH",
    "wof:placetype": "postalcode"
  },
  "geometry": {"coordinates":[0.585668,52.679443],"type":"Point"}
}
