{
  "type": "Feature",
  "properties": {
    "iso:country":"GB",
    "wof:name":"WR8 9DH",
    "wof:placetype":"postalcode"
},
  "geometry": {"coordinates":[-2.18575504571498,52.07279000511888],"type":"Point"}
}