{
  "type": "Feature",
  "properties": {
    "date:inception_lower": "1980-01-01",
    "date:inception_upper": "1980-01-01",
    "iso:country": "GB",
    "wof:name": "WR8 9DH",
    "wof:placetype": "postalcode"
  },
  "geometry": {"coordinates":[-2.186193,52.074382],"type":"Point"}
}
