{
  "type": "Feature",
  "properties": {
    "iso:country":"GB",
    "wof:name":"CV7 8BB",
    "wof:placetype":"postalcode"
},
  "geometry": {"coordinates":[-1.55727741357803,52.4636181184778],"type":"Point"}
}