{
  "type": "Feature",
  "properties": {
    "iso:country":"GB",
    "wof:name":"SL1 5UN",
    "wof:placetype":"postalcode"
},
  "geometry": {"coordinates":[-0.64071142004932,51.51034600489975],"type":"Point"}
}