{
  "type": "Feature",
  "properties": {
    "iso:country":"GB",
    "wof:name":"KA12 9LB",
    "wof:placetype":"postalcode"
},
  "geometry": {"coordinates":[-4.66045584487247,55.62540357724181],"type":"Point"}
}