{
  "type": "Feature",
  "properties": {
    "iso:country":"GB",
    "wof:name":"LL34 6TD",
    "wof:placetype":"postalcode"
},
  "geometry": {"coordinates":[-3.88876468829362,53.27422896141972],"type":"Point"}
}