{
  "type": "Feature",
  "properties": {
    "iso:country": "GB",
    "wof:name": "DL1 4QF",
    "wof:placetype": "postalcode"
  },
  "geometry": {"coordinates":[-1.529168,54.512693],"type":"Point"}
}
