{
  "type": "Feature",
  "properties": {
    "iso:country":"GB",
    "wof:name":"DL1 4QF",
    "wof:placetype":"postalcode"
},
  "geometry": {"coordinates":[-1.52916809097561,54.51269317840713],"type":"Point"}
}