{
  "type": "Feature",
  "properties": {
    "iso:country":"GB",
    "wof:name":"BB7 9EA",
    "wof:placetype":"postalcode"
},
  "geometry": {"coordinates":[-2.34163195866297,53.83187732317759],"type":"Point"}
}