{
  "type": "Feature",
  "properties": {
    "date:inception_lower": "1980-01-01",
    "date:inception_upper": "1980-01-01",
    "iso:country": "GB",
    "wof:name": "G53 5XR",
    "wof:placetype": "postalcode"
  },
  "geometry": {"coordinates":[-4.346097,55.838587],"type":"Point"}
}
