{
  "type": "Feature",
  "properties": {
    "iso:country":"GB",
    "wof:name":"TQ2 8HN",
    "wof:placetype":"postalcode"
},
  "geometry": {"coordinates":[-3.53938192338885,50.49222095024479],"type":"Point"}
}