{
  "type": "Feature",
  "properties": {
    "iso:country":"GB",
    "wof:name":"WF16 9LX",
    "wof:placetype":"postalcode"
},
  "geometry": {"coordinates":[-1.66290125063838,53.71021151427739],"type":"Point"}
}