{
  "type": "Feature",
  "properties": {
    "date:inception_lower": "1996-12-01",
    "date:inception_upper": "1996-12-01",
    "iso:country": "GB",
    "wof:name": "CV4 9UW",
    "wof:placetype": "postalcode"
  },
  "geometry": {"coordinates":[-1.59329,52.404952],"type":"Point"}
}
