{
  "type": "Feature",
  "properties": {
    "iso:country":"GB",
    "wof:name":"CV4 9UW",
    "wof:placetype":"postalcode"
},
  "geometry": {"coordinates":[-1.59328965239453,52.40495217302274],"type":"Point"}
}