{
  "type": "Feature",
  "properties": {
    "iso:country": "GB",
    "wof:name": "CV4 9UW",
    "wof:placetype": "postalcode"
  },
  "geometry": {"coordinates":[-1.59329,52.404952],"type":"Point"}
}
