{
  "type": "Feature",
  "properties": {
    "iso:country":"GB",
    "wof:name":"HD8 8RR",
    "wof:placetype":"postalcode"
},
  "geometry": {"coordinates":[-1.6591312316428,53.57286057470635],"type":"Point"}
}