{
  "type": "Feature",
  "properties": {
    "date:inception_lower": "1980-01-01",
    "date:inception_upper": "1980-01-01",
    "iso:country": "GB",
    "wof:name": "HD8 8RR",
    "wof:placetype": "postalcode"
  },
  "geometry": {"coordinates":[-1.658907,53.572876],"type":"Point"}
}
