{
  "type": "Feature",
  "properties": {
    "iso:country": "GB",
    "wof:name": "HD8 8RR",
    "wof:placetype": "postalcode"
  },
  "geometry": {"coordinates":[-1.659131,53.572861],"type":"Point"}
}
