{
  "type": "Feature",
  "properties": {
    "iso:country": "GB",
    "wof:name": "LN7 6QF",
    "wof:placetype": "postalcode"
  },
  "geometry": {"coordinates":[-0.316274,53.497664],"type":"Point"}
}
