{
  "type": "Feature",
  "properties": {
    "iso:country":"GB",
    "wof:name":"LN7 6QF",
    "wof:placetype":"postalcode"
},
  "geometry": {"coordinates":[-0.31627364116248,53.49766426359473],"type":"Point"}
}