{
  "type": "Feature",
  "properties": {
    "iso:country":"GB",
    "wof:name":"NW7 3PG",
    "wof:placetype":"postalcode"
},
  "geometry": {"coordinates":[-0.25453744028557,51.61316999247226],"type":"Point"}
}