{
  "type": "Feature",
  "properties": {
    "date:inception_lower": "1980-01-01",
    "date:inception_upper": "1980-01-01",
    "iso:country": "GB",
    "wof:name": "NG1 1NN",
    "wof:placetype": "postalcode"
  },
  "geometry": {"coordinates":[-1.144512,52.953471],"type":"Point"}
}
