{
  "type": "Feature",
  "properties": {
    "iso:country":"GB",
    "wof:name":"NG1 1NN",
    "wof:placetype":"postalcode"
},
  "geometry": {"coordinates":[-1.1446045252676,52.9534245611887],"type":"Point"}
}