{
  "type": "Feature",
  "properties": {
    "iso:country":"GB",
    "wof:name":"SA14 8QU",
    "wof:placetype":"postalcode"
},
  "geometry": {"coordinates":[-4.12767613994782,51.6933097631746],"type":"Point"}
}