{
  "type": "Feature",
  "properties": {
    "iso:country": "GB",
    "wof:name": "GL54 5LJ",
    "wof:placetype": "postalcode"
  },
  "geometry": {"coordinates":[-1.964222,51.953508],"type":"Point"}
}
