{
  "type": "Feature",
  "properties": {
    "date:inception_lower": "1980-01-01",
    "date:inception_upper": "1980-01-01",
    "iso:country": "GB",
    "wof:name": "CB1 3QX",
    "wof:placetype": "postalcode"
  },
  "geometry": {"coordinates":[0.142991,52.1908],"type":"Point"}
}
