{
  "type": "Feature",
  "properties": {
    "iso:country":"GB",
    "wof:name":"CB1 3QX",
    "wof:placetype":"postalcode"
},
  "geometry": {"coordinates":[0.14299121955327,52.19080001410796],"type":"Point"}
}