{
  "type": "Feature",
  "properties": {
    "date:inception_lower": "2003-04-01",
    "date:inception_upper": "2003-04-01",
    "iso:country": "GB",
    "wof:name": "CV6 3FA",
    "wof:placetype": "postalcode"
  },
  "geometry": {"coordinates":[-1.517874,52.431352],"type":"Point"}
}
