{
  "type": "Feature",
  "properties": {
    "iso:country":"GB",
    "wof:name":"SS0 8NS",
    "wof:placetype":"postalcode"
},
  "geometry": {"coordinates":[0.67627780025015,51.54024262861372],"type":"Point"}
}