{
  "type": "Feature",
  "properties": {
    "date:inception_lower": "2004-05-01",
    "date:inception_upper": "2004-05-01",
    "iso:country": "GB",
    "wof:name": "LL11 4RJ",
    "wof:placetype": "postalcode"
  },
  "geometry": {"coordinates":[-3.000441,53.068145],"type":"Point"}
}
