{
  "type": "Feature",
  "properties": {
    "iso:country":"GB",
    "wof:name":"NW6 4AL",
    "wof:placetype":"postalcode"
},
  "geometry": {"coordinates":[-0.1843554378589,51.54040031838174],"type":"Point"}
}