{
  "type": "Feature",
  "properties": {
    "iso:country": "GB",
    "wof:name": "SL9 0DP",
    "wof:placetype": "postalcode"
  },
  "geometry": {"coordinates":[-0.547725,51.613485],"type":"Point"}
}
