{
  "type": "Feature",
  "properties": {
    "iso:country":"GB",
    "wof:name":"SL9 0DP",
    "wof:placetype":"postalcode"
},
  "geometry": {"coordinates":[-0.54772506105414,51.61348519074371],"type":"Point"}
}