{
  "type": "Feature",
  "properties": {
    "iso:country":"GB",
    "wof:name":"E11 2EH",
    "wof:placetype":"postalcode"
},
  "geometry": {"coordinates":[0.03260613154254,51.57828882353921],"type":"Point"}
}