{
  "type": "Feature",
  "properties": {
    "iso:country": "GB",
    "wof:name": "SO41 0RQ",
    "wof:placetype": "postalcode"
  },
  "geometry": {"coordinates":[-1.59623,50.730078],"type":"Point"}
}
