{
  "type": "Feature",
  "properties": {
    "iso:country": "GB",
    "wof:name": "MK12 6AJ",
    "wof:placetype": "postalcode"
  },
  "geometry": {"coordinates":[-0.824177,52.053201],"type":"Point"}
}
