{
  "type": "Feature",
  "properties": {
    "iso:country":"GB",
    "wof:name":"MK12 6AJ",
    "wof:placetype":"postalcode"
},
  "geometry": {"coordinates":[-0.82417726653247,52.05320116938768],"type":"Point"}
}