{
  "type": "Feature",
  "properties": {
    "iso:country":"GB",
    "wof:name":"LA14 3YE",
    "wof:placetype":"postalcode"
},
  "geometry": {"coordinates":[-3.25736173342081,54.0972304181038],"type":"Point"}
}