{
  "type": "Feature",
  "properties": {
    "date:inception_lower": "1980-01-01",
    "date:inception_upper": "1980-01-01",
    "iso:country": "GB",
    "wof:name": "TR2 5AA",
    "wof:placetype": "postalcode"
  },
  "geometry": {"coordinates":[-5.016759,50.167179],"type":"Point"}
}
