{
  "type": "Feature",
  "properties": {
    "iso:country": "GB",
    "wof:name": "CT19 5PL",
    "wof:placetype": "postalcode"
  },
  "geometry": {"coordinates":[1.179107,51.090162],"type":"Point"}
}
