{
  "type": "Feature",
  "properties": {
    "iso:country":"GB",
    "wof:name":"CT19 5PL",
    "wof:placetype":"postalcode"
},
  "geometry": {"coordinates":[1.17910700706616,51.09016208713955],"type":"Point"}
}