{
  "type": "Feature",
  "properties": {
    "date:inception_lower": "1990-02-01",
    "date:inception_upper": "1990-02-01",
    "iso:country": "GB",
    "wof:name": "WD6 5QS",
    "wof:placetype": "postalcode"
  },
  "geometry": {"coordinates":[-0.260462,51.663326],"type":"Point"}
}
