{
  "type": "Feature",
  "properties": {
    "iso:country":"GB",
    "wof:name":"ML1 3BG",
    "wof:placetype":"postalcode"
},
  "geometry": {"coordinates":[-4.0067957614431,55.78354313355524],"type":"Point"}
}