{
  "type": "Feature",
  "properties": {
    "iso:country":"GB",
    "wof:name":"TW11 0DG",
    "wof:placetype":"postalcode"
},
  "geometry": {"coordinates":[-0.32885063076505,51.42094401318761],"type":"Point"}
}