{
  "type": "Feature",
  "properties": {
    "date:inception_lower": "1980-01-01",
    "date:inception_upper": "1980-01-01",
    "iso:country": "GB",
    "wof:name": "TW11 0DG",
    "wof:placetype": "postalcode"
  },
  "geometry": {"coordinates":[-0.328851,51.420944],"type":"Point"}
}
