{
  "type": "Feature",
  "properties": {
    "iso:country": "GB",
    "wof:name": "TW11 0DG",
    "wof:placetype": "postalcode"
  },
  "geometry": {"coordinates":[-0.328851,51.420944],"type":"Point"}
}
