{
  "type": "Feature",
  "properties": {
    "iso:country":"GB",
    "wof:name":"SY15 6AJ",
    "wof:placetype":"postalcode"
},
  "geometry": {"coordinates":[-3.06463356520147,52.53816476827131],"type":"Point"}
}