{
  "type": "Feature",
  "properties": {
    "iso:country": "GB",
    "wof:name": "SY15 6AJ",
    "wof:placetype": "postalcode"
  },
  "geometry": {"coordinates":[-3.064634,52.538165],"type":"Point"}
}
