{
  "type": "Feature",
  "properties": {
    "iso:country": "GB",
    "wof:name": "B43 7HA",
    "wof:placetype": "postalcode"
  },
  "geometry": {"coordinates":[-1.910062,52.55118],"type":"Point"}
}
