{
  "type": "Feature",
  "properties": {
    "date:inception_lower":"1984-02-01",
    "date:inception_upper":"1984-02-29",
    "iso:country":"GB",
    "wof:name":"B43 7HA",
    "wof:placetype":"postalcode"
},
  "geometry": {"coordinates":[-1.91002,52.550083],"type":"Point"}
}