{
  "type": "Feature",
  "properties": {
    "iso:country":"GB",
    "wof:name":"B43 7HA",
    "wof:placetype":"postalcode"
},
  "geometry": {"coordinates":[-1.91006807793312,52.55116429005971],"type":"Point"}
}