{
  "type": "Feature",
  "properties": {
    "iso:country": "GB",
    "wof:name": "SN6 6QX",
    "wof:placetype": "postalcode"
  },
  "geometry": {"coordinates":[-1.940724,51.658882],"type":"Point"}
}
