{
  "type": "Feature",
  "properties": {
    "date:inception_lower":"1993-01-01",
    "date:inception_upper":"1993-01-31",
    "iso:country":"GB",
    "wof:name":"SN6 6QX",
    "wof:placetype":"postalcode"
},
  "geometry": {"coordinates":[-1.940724,51.658882],"type":"Point"}
}