{
  "type": "Feature",
  "properties": {
    "iso:country":"GB",
    "wof:name":"SN6 6QX",
    "wof:placetype":"postalcode"
},
  "geometry": {"coordinates":[-1.940724015596,51.65888202299988],"type":"Point"}
}