{
  "type": "Feature",
  "properties": {
    "iso:country": "GB",
    "wof:name": "KA11 4FL",
    "wof:placetype": "postalcode"
  },
  "geometry": {"coordinates":[-4.646285,55.62169],"type":"Point"}
}
