{
  "type": "Feature",
  "properties": {
    "iso:country":"GB",
    "wof:name":"HG2 0QB",
    "wof:placetype":"postalcode"
},
  "geometry": {"coordinates":[-1.56370316396662,53.98754755638638],"type":"Point"}
}