{
  "type": "Feature",
  "properties": {
    "iso:country":"GB",
    "wof:name":"DD6 8BP",
    "wof:placetype":"postalcode"
},
  "geometry": {"coordinates":[-2.93982124200369,56.4412907648962],"type":"Point"}
}