{
  "type": "Feature",
  "properties": {
    "iso:country":"GB",
    "wof:name":"DH7 9LP",
    "wof:placetype":"postalcode"
},
  "geometry": {"coordinates":[-1.70991877943921,54.775565856606],"type":"Point"}
}