{
  "type": "Feature",
  "properties": {
    "iso:country": "GB",
    "wof:name": "DH7 9LP",
    "wof:placetype": "postalcode"
  },
  "geometry": {"coordinates":[-1.709919,54.775566],"type":"Point"}
}
