{
  "type": "Feature",
  "properties": {
    "iso:country": "GB",
    "wof:name": "PE28 5YX",
    "wof:placetype": "postalcode"
  },
  "geometry": {"coordinates":[-0.198059,52.417949],"type":"Point"}
}
