{
  "type": "Feature",
  "properties": {
    "iso:country": "GB",
    "wof:name": "WS6 7ER",
    "wof:placetype": "postalcode"
  },
  "geometry": {"coordinates":[-2.025835,52.668521],"type":"Point"}
}
