{
  "type": "Feature",
  "properties": {
    "date:inception_lower": "2019-09-01",
    "date:inception_upper": "2019-09-01",
    "iso:country": "GB",
    "wof:name": "EH6 7AP",
    "wof:placetype": "postalcode"
  },
  "geometry": {"coordinates":[-3.160825,55.972631],"type":"Point"}
}
