{
  "type": "Feature",
  "properties": {
    "iso:country":"GB",
    "wof:name":"KT4 8SH",
    "wof:placetype":"postalcode"
},
  "geometry": {"coordinates":[-0.23781589853829,51.37659927084116],"type":"Point"}
}