{
  "type": "Feature",
  "properties": {
    "date:inception_lower": "2008-07-01",
    "date:inception_upper": "2008-07-01",
    "iso:country": "GB",
    "wof:name": "BS13 8BU",
    "wof:placetype": "postalcode"
  },
  "geometry": {"coordinates":[-2.620779,51.408162],"type":"Point"}
}
