{
  "type": "Feature",
  "properties": {
    "date:inception_lower":"1980-01-01",
    "date:inception_upper":"1980-01-31",
    "iso:country":"GB",
    "wof:name":"PH7 3SP",
    "wof:placetype":"postalcode"
},
  "geometry": {"coordinates":[-3.826815,56.375042],"type":"Point"}
}