{
  "type": "Feature",
  "properties": {
    "iso:country":"GB",
    "wof:name":"SG18 8BL",
    "wof:placetype":"postalcode"
},
  "geometry": {"coordinates":[-0.26558640791668,52.08301661386673],"type":"Point"}
}