{
  "type": "Feature",
  "properties": {
    "date:inception_lower":"1980-01-01",
    "date:inception_upper":"1980-01-31",
    "iso:country":"GB",
    "wof:name":"CW2 8QJ",
    "wof:placetype":"postalcode"
},
  "geometry": {"coordinates":[-2.468538,53.088509],"type":"Point"}
}