{
  "type": "Feature",
  "properties": {
    "iso:country": "GB",
    "wof:name": "CW2 8QJ",
    "wof:placetype": "postalcode"
  },
  "geometry": {"coordinates":[-2.468538,53.088509],"type":"Point"}
}
