{
  "type": "Feature",
  "properties": {
    "iso:country":"GB",
    "wof:name":"CW2 8QJ",
    "wof:placetype":"postalcode"
},
  "geometry": {"coordinates":[-2.46868913394161,53.088642892719],"type":"Point"}
}