{
  "type": "Feature",
  "properties": {
    "iso:country": "GB",
    "wof:name": "G52 2LS",
    "wof:placetype": "postalcode"
  },
  "geometry": {"coordinates":[-4.33693,55.84659],"type":"Point"}
}
