{
  "type": "Feature",
  "properties": {
    "iso:country":"GB",
    "wof:name":"G52 2LS",
    "wof:placetype":"postalcode"
},
  "geometry": {"coordinates":[-4.3369302504947,55.84658977177295],"type":"Point"}
}