{
  "type": "Feature",
  "properties": {
    "iso:country":"GB",
    "wof:name":"TS16 9EF",
    "wof:placetype":"postalcode"
},
  "geometry": {"coordinates":[-1.34917125765585,54.51699044945057],"type":"Point"}
}