{
  "type": "Feature",
  "properties": {
    "iso:country": "GB",
    "wof:name": "TS16 9EF",
    "wof:placetype": "postalcode"
  },
  "geometry": {"coordinates":[-1.349171,54.51699],"type":"Point"}
}
