{
  "type": "Feature",
  "properties": {
    "date:inception_lower": "1987-04-01",
    "date:inception_upper": "1987-04-01",
    "iso:country": "GB",
    "wof:name": "CB9 9EL",
    "wof:placetype": "postalcode"
  },
  "geometry": {"coordinates":[0.422306,52.088276],"type":"Point"}
}
