{
  "type": "Feature",
  "properties": {
    "iso:country": "GB",
    "wof:name": "GU23 6AR",
    "wof:placetype": "postalcode"
  },
  "geometry": {"coordinates":[-0.489426,51.301906],"type":"Point"}
}
