{
  "type": "Feature",
  "properties": {
    "iso:country":"GB",
    "wof:name":"GU23 6AR",
    "wof:placetype":"postalcode"
},
  "geometry": {"coordinates":[-0.48942594613515,51.30190633176732],"type":"Point"}
}