{
  "type": "Feature",
  "properties": {
    "date:inception_lower": "2005-05-01",
    "date:inception_upper": "2005-05-01",
    "iso:country": "GB",
    "wof:name": "NG7 7HP",
    "wof:placetype": "postalcode"
  },
  "geometry": {"coordinates":[-1.170409,52.973045],"type":"Point"}
}
