{
  "type": "Feature",
  "properties": {
    "date:inception_lower": "2001-06-01",
    "date:inception_upper": "2001-06-01",
    "iso:country": "GB",
    "wof:name": "SL1 2DR",
    "wof:placetype": "postalcode"
  },
  "geometry": {"coordinates":[-0.588061,51.504113],"type":"Point"}
}
