{
  "type": "Feature",
  "properties": {
    "iso:country":"GB",
    "wof:name":"SL1 2DR",
    "wof:placetype":"postalcode"
},
  "geometry": {"coordinates":[-0.58806128215741,51.50411307343344],"type":"Point"}
}