{
  "type": "Feature",
  "properties": {
    "iso:country": "GB",
    "wof:name": "M11 4RD",
    "wof:placetype": "postalcode"
  },
  "geometry": {"coordinates":[-2.176223,53.482558],"type":"Point"}
}
