{
  "type": "Feature",
  "properties": {
    "iso:country":"GB",
    "wof:name":"M11 4RD",
    "wof:placetype":"postalcode"
},
  "geometry": {"coordinates":[-2.17622276112293,53.48255849651822],"type":"Point"}
}