{
  "type": "Feature",
  "properties": {
    "iso:country":"GB",
    "wof:name":"LE7 9YE",
    "wof:placetype":"postalcode"
},
  "geometry": {"coordinates":[-0.90067358567545,52.6172812394969],"type":"Point"}
}