{
  "type": "Feature",
  "properties": {
    "date:inception_lower":"1980-01-01",
    "date:inception_upper":"1980-01-31",
    "iso:country":"GB",
    "wof:name":"LE7 9YE",
    "wof:placetype":"postalcode"
},
  "geometry": {"coordinates":[-0.900674,52.617281],"type":"Point"}
}