{
  "type": "Feature",
  "properties": {
    "date:inception_lower": "2000-12-01",
    "date:inception_upper": "2000-12-01",
    "iso:country": "GB",
    "wof:name": "IP22 1PL",
    "wof:placetype": "postalcode"
  },
  "geometry": {"coordinates":[1.060954,52.352449],"type":"Point"}
}
