{
  "type": "Feature",
  "properties": {
    "iso:country":"GB",
    "wof:name":"IP22 1PL",
    "wof:placetype":"postalcode"
},
  "geometry": {"coordinates":[1.06091027192233,52.35243008619958],"type":"Point"}
}