{
  "type": "Feature",
  "properties": {
    "iso:country": "GB",
    "wof:name": "SS7 2QJ",
    "wof:placetype": "postalcode"
  },
  "geometry": {"coordinates":[0.597625,51.553766],"type":"Point"}
}
