{
  "type": "Feature",
  "properties": {
    "iso:country":"GB",
    "wof:name":"SS7 2QJ",
    "wof:placetype":"postalcode"
},
  "geometry": {"coordinates":[0.59762456664694,51.55376573551971],"type":"Point"}
}