{
  "type": "Feature",
  "properties": {
    "iso:country":"GB",
    "wof:name":"SP6 3BA",
    "wof:placetype":"postalcode"
},
  "geometry": {"coordinates":[-1.82696642206583,50.91735988375715],"type":"Point"}
}