{
  "type": "Feature",
  "properties": {
    "date:inception_lower": "2007-05-01",
    "date:inception_upper": "2007-05-01",
    "iso:country": "GB",
    "wof:name": "E5 9PA",
    "wof:placetype": "postalcode"
  },
  "geometry": {"coordinates":[-0.051371,51.562665],"type":"Point"}
}
