{
  "type": "Feature",
  "properties": {
    "iso:country":"GB",
    "wof:name":"E5 9PA",
    "wof:placetype":"postalcode"
},
  "geometry": {"coordinates":[-0.05139753271952,51.56266399758085],"type":"Point"}
}