{
  "type": "Feature",
  "properties": {
    "iso:country":"GB",
    "wof:name":"SO31 4LD",
    "wof:placetype":"postalcode"
},
  "geometry": {"coordinates":[-1.32978599681048,50.85858005312775],"type":"Point"}
}