{
  "type": "Feature",
  "properties": {
    "iso:country":"GB",
    "wof:name":"S36 7JU",
    "wof:placetype":"postalcode"
},
  "geometry": {"coordinates":[-1.6093982772611,53.54060215017029],"type":"Point"}
}