{
  "type": "Feature",
  "properties": {
    "iso:country": "GB",
    "wof:name": "SA8 4PF",
    "wof:placetype": "postalcode"
  },
  "geometry": {"coordinates":[-3.845134,51.7261],"type":"Point"}
}
