{
  "type": "Feature",
  "properties": {
    "iso:country":"GB",
    "wof:name":"SA8 4PF",
    "wof:placetype":"postalcode"
},
  "geometry": {"coordinates":[-3.8451342322821,51.72609998612339],"type":"Point"}
}