{
  "type": "Feature",
  "properties": {
    "date:inception_lower":"2001-06-01",
    "date:inception_upper":"2001-06-30",
    "iso:country":"GB",
    "wof:name":"LL18 1BX",
    "wof:placetype":"postalcode"
},
  "geometry": {"coordinates":[-3.490663,53.318715],"type":"Point"}
}