{
  "type": "Feature",
  "properties": {
    "iso:country":"GB",
    "wof:name":"LL18 1BX",
    "wof:placetype":"postalcode"
},
  "geometry": {"coordinates":[-3.49066116854653,53.31869795083227],"type":"Point"}
}