{
  "type": "Feature",
  "properties": {
    "iso:country": "GB",
    "wof:name": "IP2 9HX",
    "wof:placetype": "postalcode"
  },
  "geometry": {"coordinates":[1.121497,52.039967],"type":"Point"}
}
