{
  "type": "Feature",
  "properties": {
    "iso:country":"GB",
    "wof:name":"DL4 2LG",
    "wof:placetype":"postalcode"
},
  "geometry": {"coordinates":[-1.63891444480731,54.62427376254193],"type":"Point"}
}