{
  "type": "Feature",
  "properties": {
    "iso:country": "GB",
    "wof:name": "NG16 1EB",
    "wof:placetype": "postalcode"
  },
  "geometry": {"coordinates":[-1.238382,52.99731],"type":"Point"}
}
