{
  "type": "Feature",
  "properties": {
    "iso:country":"GB",
    "wof:name":"IP4 4NP",
    "wof:placetype":"postalcode"
},
  "geometry": {"coordinates":[1.18792331525471,52.06159880708181],"type":"Point"}
}