{
  "type": "Feature",
  "properties": {
    "date:inception_lower": "1980-01-01",
    "date:inception_upper": "1980-01-01",
    "iso:country": "GB",
    "wof:name": "LA14 3LD",
    "wof:placetype": "postalcode"
  },
  "geometry": {"coordinates":[-3.254521,54.105466],"type":"Point"}
}
