{
  "type": "Feature",
  "properties": {
    "date:inception_lower":"1996-06-01",
    "date:inception_upper":"1996-06-30",
    "iso:country":"GB",
    "wof:name":"SY21 7EU",
    "wof:placetype":"postalcode"
},
  "geometry": {"coordinates":[-3.141405,52.663034],"type":"Point"}
}