{
  "type": "Feature",
  "properties": {
    "date:inception_lower": "1980-01-01",
    "date:inception_upper": "1980-01-01",
    "iso:country": "GB",
    "wof:name": "CA8 2PQ",
    "wof:placetype": "postalcode"
  },
  "geometry": {"coordinates":[-2.65105,54.927169],"type":"Point"}
}
