{
  "type": "Feature",
  "properties": {
    "iso:country":"GB",
    "wof:name":"CA8 2PQ",
    "wof:placetype":"postalcode"
},
  "geometry": {"coordinates":[-2.65104971973746,54.92716918504608],"type":"Point"}
}