{
  "type": "Feature",
  "properties": {
    "date:inception_lower": "2018-08-01",
    "date:inception_upper": "2018-08-01",
    "iso:country": "GB",
    "wof:name": "BD22 0FA",
    "wof:placetype": "postalcode"
  },
  "geometry": {"coordinates":[-2.065215,53.874433],"type":"Point"}
}
