{
  "type": "Feature",
  "properties": {
    "date:inception_lower": "1980-01-01",
    "date:inception_upper": "1980-01-01",
    "iso:country": "GB",
    "wof:name": "BL4 9QJ",
    "wof:placetype": "postalcode"
  },
  "geometry": {"coordinates":[-2.405793,53.542184],"type":"Point"}
}
