{
  "type": "Feature",
  "properties": {
    "iso:country": "GB",
    "wof:name": "BR6 7JA",
    "wof:placetype": "postalcode"
  },
  "geometry": {"coordinates":[0.047834,51.344517],"type":"Point"}
}
