{
  "type": "Feature",
  "properties": {
    "iso:country":"GB",
    "wof:name":"BR6 7JA",
    "wof:placetype":"postalcode"
},
  "geometry": {"coordinates":[0.04783359087019,51.34451693038244],"type":"Point"}
}