{
  "type": "Feature",
  "properties": {
    "iso:country":"GB",
    "wof:name":"TR10 8PU",
    "wof:placetype":"postalcode"
},
  "geometry": {"coordinates":[-5.10739977297998,50.16825090375514],"type":"Point"}
}