{
  "type": "Feature",
  "properties": {
    "date:inception_lower": "1980-01-01",
    "date:inception_upper": "1980-01-01",
    "iso:country": "GB",
    "wof:name": "TR10 8PU",
    "wof:placetype": "postalcode"
  },
  "geometry": {"coordinates":[-5.1074,50.168251],"type":"Point"}
}
