{
  "type": "Feature",
  "properties": {
    "iso:country": "GB",
    "wof:name": "TR10 8PU",
    "wof:placetype": "postalcode"
  },
  "geometry": {"coordinates":[-5.1074,50.168251],"type":"Point"}
}
