{
  "type": "Feature",
  "properties": {
    "date:inception_lower": "2023-10-01",
    "date:inception_upper": "2023-10-01",
    "iso:country": "GB",
    "wof:name": "LN8 3WL",
    "wof:placetype": "postalcode"
  },
  "geometry": {"coordinates":[-0.3362,53.396097],"type":"Point"}
}
