{
  "type": "Feature",
  "properties": {
    "iso:country": "GB",
    "wof:name": "RH16 2GA",
    "wof:placetype": "postalcode"
  },
  "geometry": {"coordinates":[-0.076262,51.00007],"type":"Point"}
}
