{
  "type": "Feature",
  "properties": {
    "date:inception_lower":"2015-09-01",
    "date:inception_upper":"2015-09-30",
    "iso:country":"GB",
    "wof:name":"RH16 2GA",
    "wof:placetype":"postalcode"
},
  "geometry": {"coordinates":[-0.076262,51.00007],"type":"Point"}
}