{
  "type": "Feature",
  "properties": {
    "iso:country":"GB",
    "wof:name":"RH16 2GA",
    "wof:placetype":"postalcode"
},
  "geometry": {"coordinates":[-0.07628748531264,51.00009224186794],"type":"Point"}
}