{
  "type": "Feature",
  "properties": {
    "date:inception_lower": "2021-03-01",
    "date:inception_upper": "2021-03-01",
    "iso:country": "GB",
    "wof:name": "CH4 7GG",
    "wof:placetype": "postalcode"
  },
  "geometry": {"coordinates":[-2.905486,53.164504],"type":"Point"}
}
