{
  "type": "Feature",
  "properties": {
    "iso:country":"GB",
    "wof:name":"NP44 6JJ",
    "wof:placetype":"postalcode"
},
  "geometry": {"coordinates":[-3.05676582413429,51.64469895391684],"type":"Point"}
}