{
  "type": "Feature",
  "properties": {
    "date:inception_lower": "1986-04-01",
    "date:inception_upper": "1986-04-01",
    "iso:country": "GB",
    "wof:name": "NP44 6JJ",
    "wof:placetype": "postalcode"
  },
  "geometry": {"coordinates":[-3.056766,51.644699],"type":"Point"}
}
