{
  "type": "Feature",
  "properties": {
    "iso:country":"GB",
    "wof:name":"BA20 2EP",
    "wof:placetype":"postalcode"
},
  "geometry": {"coordinates":[-2.66489163202372,50.94306514483255],"type":"Point"}
}