{
  "type": "Feature",
  "properties": {
    "iso:country": "GB",
    "wof:name": "PE31 8DP",
    "wof:placetype": "postalcode"
  },
  "geometry": {"coordinates":[0.721192,52.950223],"type":"Point"}
}
