{
  "type": "Feature",
  "properties": {
    "iso:country":"GB",
    "wof:name":"PE31 8DP",
    "wof:placetype":"postalcode"
},
  "geometry": {"coordinates":[0.72119194406053,52.95022337809331],"type":"Point"}
}