{
  "type": "Feature",
  "properties": {
    "iso:country":"GB",
    "wof:name":"SO53 2FF",
    "wof:placetype":"postalcode"
},
  "geometry": {"coordinates":[-1.38101669715402,50.98750006415122],"type":"Point"}
}