{
  "type": "Feature",
  "properties": {
    "iso:country":"GB",
    "wof:name":"SN13 8QG",
    "wof:placetype":"postalcode"
},
  "geometry": {"coordinates":[-2.27591729129385,51.42390497062928],"type":"Point"}
}