{
  "type": "Feature",
  "properties": {
    "iso:country":"GB",
    "wof:name":"NE5 2QA",
    "wof:placetype":"postalcode"
},
  "geometry": {"coordinates":[-1.66665647431389,54.98330090124924],"type":"Point"}
}