{
  "type": "Feature",
  "properties": {
    "iso:country":"GB",
    "wof:name":"UB2 4PP",
    "wof:placetype":"postalcode"
},
  "geometry": {"coordinates":[-0.36984232549237,51.50131026331466],"type":"Point"}
}