{
  "type": "Feature",
  "properties": {
    "date:inception_lower":"1980-01-01",
    "date:inception_upper":"1980-01-31",
    "iso:country":"GB",
    "wof:name":"UB2 4PP",
    "wof:placetype":"postalcode"
},
  "geometry": {"coordinates":[-0.369819,51.501365],"type":"Point"}
}