{
  "type": "Feature",
  "properties": {
    "iso:country":"GB",
    "wof:name":"BA3 3FQ",
    "wof:placetype":"postalcode"
},
  "geometry": {"coordinates":[-2.46881276985295,51.28330814380065],"type":"Point"}
}