{
  "type": "Feature",
  "properties": {
    "date:inception_lower":"2015-09-01",
    "date:inception_upper":"2015-09-30",
    "iso:country":"GB",
    "wof:name":"BA3 3FQ",
    "wof:placetype":"postalcode"
},
  "geometry": {"coordinates":[-2.468813,51.283308],"type":"Point"}
}