{
  "type": "Feature",
  "properties": {
    "date:inception_lower": "2017-07-01",
    "date:inception_upper": "2017-07-01",
    "iso:country": "GB",
    "wof:name": "HR3 5TL",
    "wof:placetype": "postalcode"
  },
  "geometry": {"coordinates":[-3.139719,52.071171],"type":"Point"}
}
