{
  "type": "Feature",
  "properties": {
    "iso:country":"GB",
    "wof:name":"WR9 7SL",
    "wof:placetype":"postalcode"
},
  "geometry": {"coordinates":[-2.11935867856628,52.29148711289052],"type":"Point"}
}