{
  "type": "Feature",
  "properties": {
    "date:inception_lower": "2015-07-01",
    "date:inception_upper": "2015-07-01",
    "iso:country": "GB",
    "wof:name": "WR9 7SL",
    "wof:placetype": "postalcode"
  },
  "geometry": {"coordinates":[-2.119359,52.291487],"type":"Point"}
}
