{
  "type": "Feature",
  "properties": {
    "date:inception_lower": "1980-01-01",
    "date:inception_upper": "1980-01-01",
    "iso:country": "GB",
    "wof:name": "IV18 0DS",
    "wof:placetype": "postalcode"
  },
  "geometry": {"coordinates":[-4.168141,57.68809],"type":"Point"}
}
