{
  "type": "Feature",
  "properties": {
    "iso:country": "GB",
    "wof:name": "ME12 3LG",
    "wof:placetype": "postalcode"
  },
  "geometry": {"coordinates":[0.789374,51.41958],"type":"Point"}
}
