{
  "type": "Feature",
  "properties": {
    "iso:country":"GB",
    "wof:name":"EX16 6QZ",
    "wof:placetype":"postalcode"
},
  "geometry": {"coordinates":[-3.48379037943611,50.90622102527592],"type":"Point"}
}