{
  "type": "Feature",
  "properties": {
    "iso:country":"GB",
    "wof:name":"DG9 8BT",
    "wof:placetype":"postalcode"
},
  "geometry": {"coordinates":[-5.00990165244869,54.90255223155507],"type":"Point"}
}