{
  "type": "Feature",
  "properties": {
    "date:inception_lower": "1985-10-01",
    "date:inception_upper": "1985-10-01",
    "iso:country": "GB",
    "wof:name": "EX37 9RX",
    "wof:placetype": "postalcode"
  },
  "geometry": {"coordinates":[-3.961524,51.021758],"type":"Point"}
}
