{
  "type": "Feature",
  "properties": {
    "iso:country": "GB",
    "wof:name": "MK43 7QL",
    "wof:placetype": "postalcode"
  },
  "geometry": {"coordinates":[-0.553104,52.16806],"type":"Point"}
}
