{
  "type": "Feature",
  "properties": {
    "iso:country":"GB",
    "wof:name":"MK43 7QL",
    "wof:placetype":"postalcode"
},
  "geometry": {"coordinates":[-0.55310431529296,52.16805999835194],"type":"Point"}
}