{
  "type": "Feature",
  "properties": {
    "iso:country":"GB",
    "wof:name":"SE12 9AE",
    "wof:placetype":"postalcode"
},
  "geometry": {"coordinates":[0.02639655849505,51.44896420729009],"type":"Point"}
}