{
  "type": "Feature",
  "properties": {
    "date:inception_lower": "1980-01-01",
    "date:inception_upper": "1980-01-01",
    "iso:country": "GB",
    "wof:name": "SE12 9AE",
    "wof:placetype": "postalcode"
  },
  "geometry": {"coordinates":[0.026397,51.448964],"type":"Point"}
}
