{
  "type": "Feature",
  "properties": {
    "iso:country": "GB",
    "wof:name": "FK10 1SH",
    "wof:placetype": "postalcode"
  },
  "geometry": {"coordinates":[-3.780506,56.108323],"type":"Point"}
}
