{
  "type": "Feature",
  "properties": {
    "iso:country":"GB",
    "wof:name":"DH7 9FG",
    "wof:placetype":"postalcode"
},
  "geometry": {"coordinates":[-1.68569888589679,54.79761241756289],"type":"Point"}
}