{
  "type": "Feature",
  "properties": {
    "iso:country": "GB",
    "wof:name": "EX2 8XU",
    "wof:placetype": "postalcode"
  },
  "geometry": {"coordinates":[-3.517924,50.692041],"type":"Point"}
}
