{
  "type": "Feature",
  "properties": {
    "iso:country":"GB",
    "wof:name":"IP11 2XZ",
    "wof:placetype":"postalcode"
},
  "geometry": {"coordinates":[1.3247791566268,51.96276167000082],"type":"Point"}
}