{
  "type": "Feature",
  "properties": {
    "iso:country":"GB",
    "wof:name":"G34 9JE",
    "wof:placetype":"postalcode"
},
  "geometry": {"coordinates":[-4.11377291985099,55.86675940636577],"type":"Point"}
}