{
  "type": "Feature",
  "properties": {
    "iso:country":"GB",
    "wof:name":"NE34 8UD",
    "wof:placetype":"postalcode"
},
  "geometry": {"coordinates":[-1.4206043149798,54.96096386317558],"type":"Point"}
}