{
  "type": "Feature",
  "properties": {
    "date:inception_lower": "1980-01-01",
    "date:inception_upper": "1980-01-01",
    "iso:country": "GB",
    "wof:name": "SR4 7TW",
    "wof:placetype": "postalcode"
  },
  "geometry": {"coordinates":[-1.410927,54.901823],"type":"Point"}
}
