{
  "type": "Feature",
  "properties": {
    "iso:country":"GB",
    "wof:name":"SR4 7TW",
    "wof:placetype":"postalcode"
},
  "geometry": {"coordinates":[-1.41092713718789,54.90182271438447],"type":"Point"}
}