{
  "type": "Feature",
  "properties": {
    "date:inception_lower": "2005-07-01",
    "date:inception_upper": "2005-07-01",
    "iso:country": "GB",
    "wof:name": "HU15 2WG",
    "wof:placetype": "postalcode"
  },
  "geometry": {"coordinates":[-0.740667,53.756338],"type":"Point"}
}
