{
  "type": "Feature",
  "properties": {
    "iso:country":"GB",
    "wof:name":"HU15 2WG",
    "wof:placetype":"postalcode"
},
  "geometry": {"coordinates":[-0.74066722223018,53.75633827852002],"type":"Point"}
}