{
  "type": "Feature",
  "properties": {
    "iso:country":"GB",
    "wof:name":"WC2E 7PY",
    "wof:placetype":"postalcode"
},
  "geometry": {"coordinates":[-0.12088935522043,51.51171296092433],"type":"Point"}
}