{
  "type": "Feature",
  "properties": {
    "iso:country": "GB",
    "wof:name": "WC2E 7PY",
    "wof:placetype": "postalcode"
  },
  "geometry": {"coordinates":[-0.120889,51.511713],"type":"Point"}
}
