{
  "type": "Feature",
  "properties": {
    "date:inception_lower":"1995-12-01",
    "date:inception_upper":"1995-12-31",
    "iso:country":"GB",
    "wof:name":"CV8 2GA",
    "wof:placetype":"postalcode"
},
  "geometry": {"coordinates":[-1.573603,52.344379],"type":"Point"}
}