{
  "type": "Feature",
  "properties": {
    "iso:country":"GB",
    "wof:name":"CV8 2GA",
    "wof:placetype":"postalcode"
},
  "geometry": {"coordinates":[-1.57360286098452,52.34437893055175],"type":"Point"}
}