{
  "type": "Feature",
  "properties": {
    "iso:country": "GB",
    "wof:name": "CV8 2GA",
    "wof:placetype": "postalcode"
  },
  "geometry": {"coordinates":[-1.573603,52.344379],"type":"Point"}
}
