{
  "type": "Feature",
  "properties": {
    "iso:country": "GB",
    "wof:name": "GL56 9RT",
    "wof:placetype": "postalcode"
  },
  "geometry": {"coordinates":[-1.695198,51.992456],"type":"Point"}
}
