{
  "type": "Feature",
  "properties": {
    "iso:country":"GB",
    "wof:name":"B69 4LY",
    "wof:placetype":"postalcode"
},
  "geometry": {"coordinates":[-2.00667230276103,52.49208049799311],"type":"Point"}
}