{
  "type": "Feature",
  "properties": {
    "iso:country":"GB",
    "wof:name":"OX5 2LL",
    "wof:placetype":"postalcode"
},
  "geometry": {"coordinates":[-1.27504634375651,51.81434097919372],"type":"Point"}
}