{
  "type": "Feature",
  "properties": {
    "iso:country": "GB",
    "wof:name": "BS5 6TH",
    "wof:placetype": "postalcode"
  },
  "geometry": {"coordinates":[-2.561598,51.47589],"type":"Point"}
}
