{
  "type": "Feature",
  "properties": {
    "iso:country":"GB",
    "wof:name":"CM6 2PQ",
    "wof:placetype":"postalcode"
},
  "geometry": {"coordinates":[0.34162688508176,51.95358077057344],"type":"Point"}
}