{
  "type": "Feature",
  "properties": {
    "iso:country":"GB",
    "wof:name":"SA19 9LA",
    "wof:placetype":"postalcode"
},
  "geometry": {"coordinates":[-3.83995760103017,51.93701766400966],"type":"Point"}
}