{
  "type": "Feature",
  "properties": {
    "iso:country": "GB",
    "wof:name": "RM8 2NS",
    "wof:placetype": "postalcode"
  },
  "geometry": {"coordinates":[0.126219,51.551387],"type":"Point"}
}
