{
  "type": "Feature",
  "properties": {
    "iso:country":"GB",
    "wof:name":"RM8 2NS",
    "wof:placetype":"postalcode"
},
  "geometry": {"coordinates":[0.126219090087,51.551387164393],"type":"Point"}
}