{
  "type": "Feature",
  "properties": {
    "iso:country":"GB",
    "wof:name":"CM3 3HE",
    "wof:placetype":"postalcode"
},
  "geometry": {"coordinates":[0.53590528049335,51.76059407266381],"type":"Point"}
}