{
  "type": "Feature",
  "properties": {
    "iso:country":"GB",
    "wof:name":"BR5 4PX",
    "wof:placetype":"postalcode"
},
  "geometry": {"coordinates":[0.11725724253379,51.37775271337284],"type":"Point"}
}