{
  "type": "Feature",
  "properties": {
    "iso:country":"GB",
    "wof:name":"BH22 8RY",
    "wof:placetype":"postalcode"
},
  "geometry": {"coordinates":[-1.89255470982475,50.78962856990347],"type":"Point"}
}