{
  "type": "Feature",
  "properties": {
    "date:inception_lower":"1980-01-01",
    "date:inception_upper":"1980-01-31",
    "iso:country":"GB",
    "wof:name":"BH22 8RY",
    "wof:placetype":"postalcode"
},
  "geometry": {"coordinates":[-1.892555,50.789629],"type":"Point"}
}