{
  "type": "Feature",
  "properties": {
    "iso:country": "GB",
    "wof:name": "IP11 9DX",
    "wof:placetype": "postalcode"
  },
  "geometry": {"coordinates":[1.337407,51.97183],"type":"Point"}
}
