{
  "type": "Feature",
  "properties": {
    "date:inception_lower": "2019-08-01",
    "date:inception_upper": "2019-08-01",
    "iso:country": "GB",
    "wof:name": "E7 7FS",
    "wof:placetype": "postalcode"
  },
  "geometry": {"coordinates":[0.023688,51.548787],"type":"Point"}
}
