{
  "type": "Feature",
  "properties": {
    "iso:country":"GB",
    "wof:name":"SP5 1JY",
    "wof:placetype":"postalcode"
},
  "geometry": {"coordinates":[-1.61015837794249,51.06670336586308],"type":"Point"}
}