{
  "type": "Feature",
  "properties": {
    "iso:country": "GB",
    "wof:name": "SP5 1JY",
    "wof:placetype": "postalcode"
  },
  "geometry": {"coordinates":[-1.610158,51.066703],"type":"Point"}
}
