{
  "type": "Feature",
  "properties": {
    "date:inception_lower": "2011-06-01",
    "date:inception_upper": "2011-06-01",
    "iso:country": "GB",
    "wof:name": "IP14 1GB",
    "wof:placetype": "postalcode"
  },
  "geometry": {"coordinates":[0.98565,52.197783],"type":"Point"}
}
