{
  "type": "Feature",
  "properties": {
    "iso:country":"GB",
    "wof:name":"LA3 1QQ",
    "wof:placetype":"postalcode"
},
  "geometry": {"coordinates":[-2.87937926688679,54.06529186654136],"type":"Point"}
}