{
  "type": "Feature",
  "properties": {
    "iso:country":"GB",
    "wof:name":"AB16 7TT",
    "wof:placetype":"postalcode"
},
  "geometry": {"coordinates":[-2.14830901413506,57.17257896338992],"type":"Point"}
}