{
  "type": "Feature",
  "properties": {
    "date:inception_lower": "2019-10-01",
    "date:inception_upper": "2019-10-01",
    "iso:country": "GB",
    "wof:name": "CF31 4FE",
    "wof:placetype": "postalcode"
  },
  "geometry": {"coordinates":[-3.608993,51.507693],"type":"Point"}
}
