{
  "type": "Feature",
  "properties": {
    "iso:country": "GB",
    "wof:name": "NE5 3RW",
    "wof:placetype": "postalcode"
  },
  "geometry": {"coordinates":[-1.674793,54.993477],"type":"Point"}
}
