{
  "type": "Feature",
  "properties": {
    "iso:country":"GB",
    "wof:name":"NE5 3RW",
    "wof:placetype":"postalcode"
},
  "geometry": {"coordinates":[-1.67479345905277,54.99347733810029],"type":"Point"}
}