{
  "type": "Feature",
  "properties": {
    "iso:country": "GB",
    "wof:name": "CF48 1JB",
    "wof:placetype": "postalcode"
  },
  "geometry": {"coordinates":[-3.41742,51.750751],"type":"Point"}
}
