{
  "type": "Feature",
  "properties": {
    "date:inception_lower":"1980-01-01",
    "date:inception_upper":"1980-01-31",
    "iso:country":"GB",
    "wof:name":"CF48 1JB",
    "wof:placetype":"postalcode"
},
  "geometry": {"coordinates":[-3.41742,51.750751],"type":"Point"}
}