{
  "type": "Feature",
  "properties": {
    "iso:country": "GB",
    "wof:name": "BH7 6SW",
    "wof:placetype": "postalcode"
  },
  "geometry": {"coordinates":[-1.8133,50.741679],"type":"Point"}
}
