{
  "type": "Feature",
  "properties": {
    "iso:country":"GB",
    "wof:name":"WF9 1PA",
    "wof:placetype":"postalcode"
},
  "geometry": {"coordinates":[-1.30043408474804,53.62764120171112],"type":"Point"}
}