{
  "type": "Feature",
  "properties": {
    "date:inception_lower": "2015-08-01",
    "date:inception_upper": "2015-08-01",
    "iso:country": "GB",
    "wof:name": "PE34 3QX",
    "wof:placetype": "postalcode"
  },
  "geometry": {"coordinates":[0.389953,52.623213],"type":"Point"}
}
