{
  "type": "Feature",
  "properties": {
    "iso:country": "GB",
    "wof:name": "PE34 3QX",
    "wof:placetype": "postalcode"
  },
  "geometry": {"coordinates":[0.389953,52.623213],"type":"Point"}
}
