{
  "type": "Feature",
  "properties": {
    "iso:country":"GB",
    "wof:name":"N10 2RT",
    "wof:placetype":"postalcode"
},
  "geometry": {"coordinates":[-0.14353222667799,51.60695277403072],"type":"Point"}
}