{
  "type": "Feature",
  "properties": {
    "iso:country":"GB",
    "wof:name":"HX7 5BN",
    "wof:placetype":"postalcode"
},
  "geometry": {"coordinates":[-1.98710900674216,53.73100634297774],"type":"Point"}
}