{
  "type": "Feature",
  "properties": {
    "iso:country":"GB",
    "wof:name":"BR6 7QT",
    "wof:placetype":"postalcode"
},
  "geometry": {"coordinates":[0.13983253864293,51.35125367664024],"type":"Point"}
}