{
  "type": "Feature",
  "properties": {
    "date:inception_lower": "2020-07-01",
    "date:inception_upper": "2020-07-01",
    "iso:country": "GB",
    "wof:name": "PE19 5WD",
    "wof:placetype": "postalcode"
  },
  "geometry": {"coordinates":[-0.253604,52.288938],"type":"Point"}
}
