{
  "type": "Feature",
  "properties": {
    "iso:country":"GB",
    "wof:name":"CH3 8JE",
    "wof:placetype":"postalcode"
},
  "geometry": {"coordinates":[-2.75971192607528,53.20203097527368],"type":"Point"}
}