{
  "type": "Feature",
  "properties": {
    "iso:country":"GB",
    "wof:name":"HX3 8HG",
    "wof:placetype":"postalcode"
},
  "geometry": {"coordinates":[-1.82040894998214,53.72657654193223],"type":"Point"}
}