{
  "type": "Feature",
  "properties": {
    "iso:country":"GB",
    "wof:name":"TA5 2AA",
    "wof:placetype":"postalcode"
},
  "geometry": {"coordinates":[-3.02321382150167,51.11221315535507],"type":"Point"}
}