{
  "type": "Feature",
  "properties": {
    "date:inception_lower":"1980-01-01",
    "date:inception_upper":"1980-01-31",
    "iso:country":"GB",
    "wof:name":"TA5 2AA",
    "wof:placetype":"postalcode"
},
  "geometry": {"coordinates":[-3.023214,51.112213],"type":"Point"}
}