{
  "type": "Feature",
  "properties": {
    "iso:country": "GB",
    "wof:name": "TA5 2AA",
    "wof:placetype": "postalcode"
  },
  "geometry": {"coordinates":[-3.023214,51.112213],"type":"Point"}
}
