{
  "type": "Feature",
  "properties": {
    "date:inception_lower": "2017-05-01",
    "date:inception_upper": "2017-05-01",
    "iso:country": "GB",
    "wof:name": "SP9 7WE",
    "wof:placetype": "postalcode"
  },
  "geometry": {"coordinates":[-1.661736,51.227404],"type":"Point"}
}
