{
  "type": "Feature",
  "properties": {
    "iso:country":"GB",
    "wof:name":"OX3 9TU",
    "wof:placetype":"postalcode"
},
  "geometry": {"coordinates":[-1.21114392431062,51.81442435341374],"type":"Point"}
}