{
  "type": "Feature",
  "properties": {
    "iso:country": "GB",
    "wof:name": "OX3 9TU",
    "wof:placetype": "postalcode"
  },
  "geometry": {"coordinates":[-1.211144,51.814424],"type":"Point"}
}
