{
  "type": "Feature",
  "properties": {
    "iso:country":"GB",
    "wof:name":"BH8 9NH",
    "wof:placetype":"postalcode"
},
  "geometry": {"coordinates":[-1.84266437948628,50.74597592224775],"type":"Point"}
}