{
  "type": "Feature",
  "properties": {
    "date:inception_lower":"1980-01-01",
    "date:inception_upper":"1980-01-31",
    "iso:country":"GB",
    "wof:name":"CV5 9NF",
    "wof:placetype":"postalcode"
},
  "geometry": {"coordinates":[-1.560391,52.417016],"type":"Point"}
}