{
  "type": "Feature",
  "properties": {
    "iso:country":"GB",
    "wof:name":"YO1 9TU",
    "wof:placetype":"postalcode"
},
  "geometry": {"coordinates":[-1.07818333316472,53.95737382404064],"type":"Point"}
}