{
  "type": "Feature",
  "properties": {
    "date:inception_lower": "1998-06-01",
    "date:inception_upper": "1998-06-01",
    "iso:country": "GB",
    "wof:name": "YO1 9TU",
    "wof:placetype": "postalcode"
  },
  "geometry": {"coordinates":[-1.078183,53.957374],"type":"Point"}
}
