{
  "type": "Feature",
  "properties": {
    "iso:country": "GB",
    "wof:name": "DN21 3UG",
    "wof:placetype": "postalcode"
  },
  "geometry": {"coordinates":[-0.664195,53.499056],"type":"Point"}
}
