{
  "type": "Feature",
  "properties": {
    "iso:country":"GB",
    "wof:name":"LE17 4FA",
    "wof:placetype":"postalcode"
},
  "geometry": {"coordinates":[-1.22267518812545,52.45099722466116],"type":"Point"}
}