{
  "type": "Feature",
  "properties": {
    "date:inception_lower": "2003-05-01",
    "date:inception_upper": "2003-05-01",
    "iso:country": "GB",
    "wof:name": "LE17 4FA",
    "wof:placetype": "postalcode"
  },
  "geometry": {"coordinates":[-1.222675,52.450997],"type":"Point"}
}
