{
  "type": "Feature",
  "properties": {
    "iso:country":"GB",
    "wof:name":"CM8 3QD",
    "wof:placetype":"postalcode"
},
  "geometry": {"coordinates":[0.62662107874565,51.84704925292961],"type":"Point"}
}