{
  "type": "Feature",
  "properties": {
    "date:inception_lower":"1997-06-01",
    "date:inception_upper":"1997-06-30",
    "iso:country":"GB",
    "wof:name":"CM8 3QD",
    "wof:placetype":"postalcode"
},
  "geometry": {"coordinates":[0.626621,51.847049],"type":"Point"}
}