{
  "type": "Feature",
  "properties": {
    "date:inception_lower": "1980-01-01",
    "date:inception_upper": "1980-01-01",
    "iso:country": "GB",
    "wof:name": "TN35 4JR",
    "wof:placetype": "postalcode"
  },
  "geometry": {"coordinates":[0.610002,50.876106],"type":"Point"}
}
