{
  "type": "Feature",
  "properties": {
    "iso:country": "GB",
    "wof:name": "DH3 3AY",
    "wof:placetype": "postalcode"
  },
  "geometry": {"coordinates":[-1.573315,54.854244],"type":"Point"}
}
