{
  "type": "Feature",
  "properties": {
    "iso:country":"GB",
    "wof:name":"DH3 3AY",
    "wof:placetype":"postalcode"
},
  "geometry": {"coordinates":[-1.57331497810021,54.85424396815665],"type":"Point"}
}