{
  "type": "Feature",
  "properties": {
    "date:inception_lower": "1998-12-01",
    "date:inception_upper": "1998-12-01",
    "iso:country": "GB",
    "wof:name": "NN9 6UE",
    "wof:placetype": "postalcode"
  },
  "geometry": {"coordinates":[-0.545438,52.339281],"type":"Point"}
}
