{
  "type": "Feature",
  "properties": {
    "iso:country":"GB",
    "wof:name":"NR31 6PS",
    "wof:placetype":"postalcode"
},
  "geometry": {"coordinates":[1.72994129748982,52.57599280650911],"type":"Point"}
}