{
  "type": "Feature",
  "properties": {
    "date:inception_lower":"1980-01-01",
    "date:inception_upper":"1980-01-31",
    "iso:country":"GB",
    "wof:name":"NR31 6PS",
    "wof:placetype":"postalcode"
},
  "geometry": {"coordinates":[1.729941,52.575993],"type":"Point"}
}