{
  "type": "Feature",
  "properties": {
    "iso:country":"GB",
    "wof:name":"AB21 9PS",
    "wof:placetype":"postalcode"
},
  "geometry": {"coordinates":[-2.19009057234402,57.17724761126257],"type":"Point"}
}