{
  "type": "Feature",
  "properties": {
    "iso:country": "GB",
    "wof:name": "AB21 9PS",
    "wof:placetype": "postalcode"
  },
  "geometry": {"coordinates":[-2.190091,57.177248],"type":"Point"}
}
