{
  "type": "Feature",
  "properties": {
    "date:inception_lower":"1993-08-01",
    "date:inception_upper":"1993-08-31",
    "iso:country":"GB",
    "wof:name":"LE11 2NN",
    "wof:placetype":"postalcode"
},
  "geometry": {"coordinates":[-1.211791,52.750256],"type":"Point"}
}