{
  "type": "Feature",
  "properties": {
    "iso:country": "GB",
    "wof:name": "LE11 2NN",
    "wof:placetype": "postalcode"
  },
  "geometry": {"coordinates":[-1.211791,52.750256],"type":"Point"}
}
