{
  "type": "Feature",
  "properties": {
    "iso:country": "GB",
    "wof:name": "BH23 3QR",
    "wof:placetype": "postalcode"
  },
  "geometry": {"coordinates":[-1.754223,50.734915],"type":"Point"}
}
