{
  "type": "Feature",
  "properties": {
    "iso:country":"GB",
    "wof:name":"BH23 3QR",
    "wof:placetype":"postalcode"
},
  "geometry": {"coordinates":[-1.75422266710676,50.73491517901623],"type":"Point"}
}