{
  "type": "Feature",
  "properties": {
    "iso:country":"GB",
    "wof:name":"LS26 0NP",
    "wof:placetype":"postalcode"
},
  "geometry": {"coordinates":[-1.48822029961037,53.75750897600184],"type":"Point"}
}