{
  "type": "Feature",
  "properties": {
    "iso:country": "GB",
    "wof:name": "LS26 0NP",
    "wof:placetype": "postalcode"
  },
  "geometry": {"coordinates":[-1.48822,53.757509],"type":"Point"}
}
