{
  "type": "Feature",
  "properties": {
    "iso:country": "GB",
    "wof:name": "DE23 1TL",
    "wof:placetype": "postalcode"
  },
  "geometry": {"coordinates":[-1.500126,52.897766],"type":"Point"}
}
