{
  "type": "Feature",
  "properties": {
    "iso:country":"GB",
    "wof:name":"S70 5BA",
    "wof:placetype":"postalcode"
},
  "geometry": {"coordinates":[-1.47026435087869,53.52907420219102],"type":"Point"}
}