{
  "type": "Feature",
  "properties": {
    "iso:country": "GB",
    "wof:name": "E14 7QR",
    "wof:placetype": "postalcode"
  },
  "geometry": {"coordinates":[-0.03723,51.51572],"type":"Point"}
}
