{
  "type": "Feature",
  "properties": {
    "date:inception_lower":"1980-01-01",
    "date:inception_upper":"1980-01-31",
    "iso:country":"GB",
    "wof:name":"E14 7QR",
    "wof:placetype":"postalcode"
},
  "geometry": {"coordinates":[-0.03723,51.51572],"type":"Point"}
}