{
  "type": "Feature",
  "properties": {
    "iso:country":"GB",
    "wof:name":"E14 7QR",
    "wof:placetype":"postalcode"
},
  "geometry": {"coordinates":[-0.03723031530717,51.51572032855352],"type":"Point"}
}