{
  "type": "Feature",
  "properties": {
    "date:inception_lower":"1980-01-01",
    "date:inception_upper":"1980-01-31",
    "iso:country":"GB",
    "wof:name":"BD22 0JN",
    "wof:placetype":"postalcode"
},
  "geometry": {"coordinates":[-2.030566,53.83512],"type":"Point"}
}