{
  "type": "Feature",
  "properties": {
    "iso:country":"GB",
    "wof:name":"BD22 0JN",
    "wof:placetype":"postalcode"
},
  "geometry": {"coordinates":[-2.03056637703696,53.83511977958072],"type":"Point"}
}