{
  "type": "Feature",
  "properties": {
    "iso:country": "GB",
    "wof:name": "BD22 0JN",
    "wof:placetype": "postalcode"
  },
  "geometry": {"coordinates":[-2.030566,53.83512],"type":"Point"}
}
