{
  "type": "Feature",
  "properties": {
    "iso:country":"GB",
    "wof:name":"IV19 1DA",
    "wof:placetype":"postalcode"
},
  "geometry": {"coordinates":[-4.05351993266137,57.80771889618599],"type":"Point"}
}