{
  "type": "Feature",
  "properties": {
    "date:inception_lower": "1980-01-01",
    "date:inception_upper": "1980-01-01",
    "iso:country": "GB",
    "wof:name": "SA62 5EN",
    "wof:placetype": "postalcode"
  },
  "geometry": {"coordinates":[-5.056349,51.935707],"type":"Point"}
}
