{
  "type": "Feature",
  "properties": {
    "iso:country":"GB",
    "wof:name":"SA62 5EN",
    "wof:placetype":"postalcode"
},
  "geometry": {"coordinates":[-5.05634883236265,51.93570689387201],"type":"Point"}
}