{
  "type": "Feature",
  "properties": {
    "iso:country": "GB",
    "wof:name": "WD6 4LL",
    "wof:placetype": "postalcode"
  },
  "geometry": {"coordinates":[-0.290281,51.66746],"type":"Point"}
}
