{
  "type": "Feature",
  "properties": {
    "iso:country": "GB",
    "wof:name": "WS11 1AB",
    "wof:placetype": "postalcode"
  },
  "geometry": {"coordinates":[-2.033712,52.688537],"type":"Point"}
}
