{
  "type": "Feature",
  "properties": {
    "iso:country":"GB",
    "wof:name":"WS11 1AB",
    "wof:placetype":"postalcode"
},
  "geometry": {"coordinates":[-2.03374702626519,52.68845776874608],"type":"Point"}
}