{
  "type": "Feature",
  "properties": {
    "iso:country":"GB",
    "wof:name":"PO1 2ET",
    "wof:placetype":"postalcode"
},
  "geometry": {"coordinates":[-1.10221756915708,50.79270889621138],"type":"Point"}
}