{
  "type": "Feature",
  "properties": {
    "date:inception_lower": "2022-04-01",
    "date:inception_upper": "2022-04-01",
    "iso:country": "GB",
    "wof:name": "SK10 4ZH",
    "wof:placetype": "postalcode"
  },
  "geometry": {"coordinates":[-2.231925,53.271544],"type":"Point"}
}
