{
  "type": "Feature",
  "properties": {
    "iso:country": "GB",
    "wof:name": "BH23 5AJ",
    "wof:placetype": "postalcode"
  },
  "geometry": {"coordinates":[-1.712255,50.748083],"type":"Point"}
}
