{
  "type": "Feature",
  "properties": {
    "iso:country":"GB",
    "wof:name":"SA10 7NL",
    "wof:placetype":"postalcode"
},
  "geometry": {"coordinates":[-3.83191092020492,51.66081657074481],"type":"Point"}
}