{
  "type": "Feature",
  "properties": {
    "date:inception_lower": "1995-12-01",
    "date:inception_upper": "1995-12-01",
    "iso:country": "GB",
    "wof:name": "SA10 7NL",
    "wof:placetype": "postalcode"
  },
  "geometry": {"coordinates":[-3.831911,51.660817],"type":"Point"}
}
