{
  "type": "Feature",
  "properties": {
    "iso:country": "GB",
    "wof:name": "SA10 7NL",
    "wof:placetype": "postalcode"
  },
  "geometry": {"coordinates":[-3.831911,51.660817],"type":"Point"}
}
