{
  "type": "Feature",
  "properties": {
    "iso:country": "GB",
    "wof:name": "FY4 5DW",
    "wof:placetype": "postalcode"
  },
  "geometry": {"coordinates":[-3.016557,53.781429],"type":"Point"}
}
