{
  "type": "Feature",
  "properties": {
    "iso:country":"GB",
    "wof:name":"FY4 5DW",
    "wof:placetype":"postalcode"
},
  "geometry": {"coordinates":[-3.0169544364325,53.78141139555195],"type":"Point"}
}