{
  "type": "Feature",
  "properties": {
    "iso:country":"GB",
    "wof:name":"NG6 8JS",
    "wof:placetype":"postalcode"
},
  "geometry": {"coordinates":[-1.20259790057214,53.00509439932035],"type":"Point"}
}