{
  "type": "Feature",
  "properties": {
    "iso:country": "GB",
    "wof:name": "NG23 5PJ",
    "wof:placetype": "postalcode"
  },
  "geometry": {"coordinates":[-0.868092,53.022743],"type":"Point"}
}
