{
  "type": "Feature",
  "properties": {
    "iso:country":"GB",
    "wof:name":"CF83 2JQ",
    "wof:placetype":"postalcode"
},
  "geometry": {"coordinates":[-3.24018627910587,51.58915180558518],"type":"Point"}
}