{
  "type": "Feature",
  "properties": {
    "iso:country":"GB",
    "wof:name":"GL9 1JH",
    "wof:placetype":"postalcode"
},
  "geometry": {"coordinates":[-2.30099225676249,51.5429448497195],"type":"Point"}
}