{
  "type": "Feature",
  "properties": {
    "iso:country": "GB",
    "wof:name": "GL9 1JH",
    "wof:placetype": "postalcode"
  },
  "geometry": {"coordinates":[-2.300992,51.542945],"type":"Point"}
}
