{
  "type": "Feature",
  "properties": {
    "iso:country":"GB",
    "wof:name":"CB23 8AH",
    "wof:placetype":"postalcode"
},
  "geometry": {"coordinates":[0.04509368654556,52.22260641859366],"type":"Point"}
}