{
  "type": "Feature",
  "properties": {
    "iso:country":"GB",
    "wof:name":"L21 0EH",
    "wof:placetype":"postalcode"
},
  "geometry": {"coordinates":[-2.99175579931298,53.48785708515303],"type":"Point"}
}