{
  "type": "Feature",
  "properties": {
    "iso:country":"GB",
    "wof:name":"NG18 4NS",
    "wof:placetype":"postalcode"
},
  "geometry": {"coordinates":[-1.15958042214999,53.12364624813576],"type":"Point"}
}