{
  "type": "Feature",
  "properties": {
    "iso:country":"GB",
    "wof:name":"LA23 3QP",
    "wof:placetype":"postalcode"
},
  "geometry": {"coordinates":[-2.93266620433331,54.33778462961388],"type":"Point"}
}