{
  "type": "Feature",
  "properties": {
    "date:inception_lower": "1994-05-01",
    "date:inception_upper": "1994-05-01",
    "iso:country": "GB",
    "wof:name": "LA23 3QP",
    "wof:placetype": "postalcode"
  },
  "geometry": {"coordinates":[-2.932666,54.337785],"type":"Point"}
}
