{
  "type": "Feature",
  "properties": {
    "iso:country":"GB",
    "wof:name":"SN13 0EL",
    "wof:placetype":"postalcode"
},
  "geometry": {"coordinates":[-2.19082871134395,51.43692352621341],"type":"Point"}
}