{
  "type": "Feature",
  "properties": {
    "iso:country":"GB",
    "wof:name":"EH8 8BD",
    "wof:placetype":"postalcode"
},
  "geometry": {"coordinates":[-3.18398358287346,55.95081483251332],"type":"Point"}
}