{
  "type": "Feature",
  "properties": {
    "date:inception_lower": "2002-10-01",
    "date:inception_upper": "2002-10-01",
    "iso:country": "GB",
    "wof:name": "HU15 1TN",
    "wof:placetype": "postalcode"
  },
  "geometry": {"coordinates":[-0.553145,53.725889],"type":"Point"}
}
