{
  "type": "Feature",
  "properties": {
    "iso:country": "GB",
    "wof:name": "HU15 1TN",
    "wof:placetype": "postalcode"
  },
  "geometry": {"coordinates":[-0.553145,53.725889],"type":"Point"}
}
