{
  "type": "Feature",
  "properties": {
    "iso:country":"GB",
    "wof:name":"HU15 1TN",
    "wof:placetype":"postalcode"
},
  "geometry": {"coordinates":[-0.55314461473166,53.72588865437069],"type":"Point"}
}