{
  "type": "Feature",
  "properties": {
    "iso:country":"GB",
    "wof:name":"LN5 9JS",
    "wof:placetype":"postalcode"
},
  "geometry": {"coordinates":[-0.63561155425121,53.12902577305872],"type":"Point"}
}