{
  "type": "Feature",
  "properties": {
    "date:inception_lower": "2002-08-01",
    "date:inception_upper": "2002-08-01",
    "iso:country": "GB",
    "wof:name": "CM17 9LG",
    "wof:placetype": "postalcode"
  },
  "geometry": {"coordinates":[0.134612,51.771957],"type":"Point"}
}
