{
  "type": "Feature",
  "properties": {
    "date:inception_lower": "1980-01-01",
    "date:inception_upper": "1980-01-01",
    "iso:country": "GB",
    "wof:name": "NG32 1RN",
    "wof:placetype": "postalcode"
  },
  "geometry": {"coordinates":[-0.776978,52.871424],"type":"Point"}
}
