{
  "type": "Feature",
  "properties": {
    "iso:country": "GB",
    "wof:name": "CV47 2SA",
    "wof:placetype": "postalcode"
  },
  "geometry": {"coordinates":[-1.408273,52.217649],"type":"Point"}
}
