{
  "type": "Feature",
  "properties": {
    "iso:country":"GB",
    "wof:name":"CV47 2SA",
    "wof:placetype":"postalcode"
},
  "geometry": {"coordinates":[-1.40827316301503,52.21764884034368],"type":"Point"}
}