{
  "type": "Feature",
  "properties": {
    "iso:country":"GB",
    "wof:name":"TF9 4PR",
    "wof:placetype":"postalcode"
},
  "geometry": {"coordinates":[-2.37750460826698,52.91961048039223],"type":"Point"}
}