{
  "type": "Feature",
  "properties": {
    "iso:country": "GB",
    "wof:name": "TF9 4PR",
    "wof:placetype": "postalcode"
  },
  "geometry": {"coordinates":[-2.377534,52.919607],"type":"Point"}
}
