{
  "type": "Feature",
  "properties": {
    "iso:country": "GB",
    "wof:name": "FK5 4FZ",
    "wof:placetype": "postalcode"
  },
  "geometry": {"coordinates":[-3.830946,56.037201],"type":"Point"}
}
