{
  "type": "Feature",
  "properties": {
    "iso:country": "GB",
    "wof:name": "LE16 8EG",
    "wof:placetype": "postalcode"
  },
  "geometry": {"coordinates":[-0.797678,52.535754],"type":"Point"}
}
