{
  "type": "Feature",
  "properties": {
    "iso:country":"GB",
    "wof:name":"LE16 8EG",
    "wof:placetype":"postalcode"
},
  "geometry": {"coordinates":[-0.79767780526386,52.53575448188762],"type":"Point"}
}