{
  "type": "Feature",
  "properties": {
    "date:inception_lower": "1980-01-01",
    "date:inception_upper": "1980-01-01",
    "iso:country": "GB",
    "wof:name": "KY6 3JH",
    "wof:placetype": "postalcode"
  },
  "geometry": {"coordinates":[-3.284542,56.198157],"type":"Point"}
}
