{
  "type": "Feature",
  "properties": {
    "iso:country":"GB",
    "wof:name":"NG5 8BR",
    "wof:placetype":"postalcode"
},
  "geometry": {"coordinates":[-1.12227470705069,53.01529818878137],"type":"Point"}
}