{
  "type": "Feature",
  "properties": {
    "iso:country": "GB",
    "wof:name": "NG5 8BR",
    "wof:placetype": "postalcode"
  },
  "geometry": {"coordinates":[-1.122275,53.015298],"type":"Point"}
}
