{
  "type": "Feature",
  "properties": {
    "date:inception_lower":"2012-10-01",
    "date:inception_upper":"2012-10-31",
    "iso:country":"GB",
    "wof:name":"NG5 8BR",
    "wof:placetype":"postalcode"
},
  "geometry": {"coordinates":[-1.122275,53.015298],"type":"Point"}
}