{
  "type": "Feature",
  "properties": {
    "iso:country":"GB",
    "wof:name":"S61 2RU",
    "wof:placetype":"postalcode"
},
  "geometry": {"coordinates":[-1.43711555582169,53.46914908295514],"type":"Point"}
}