{
  "type": "Feature",
  "properties": {
    "date:inception_lower": "1980-01-01",
    "date:inception_upper": "1980-01-01",
    "iso:country": "GB",
    "wof:name": "S61 2RU",
    "wof:placetype": "postalcode"
  },
  "geometry": {"coordinates":[-1.437116,53.469149],"type":"Point"}
}
