{
  "type": "Feature",
  "properties": {
    "iso:country": "GB",
    "wof:name": "ME15 8GJ",
    "wof:placetype": "postalcode"
  },
  "geometry": {"coordinates":[0.56337,51.242818],"type":"Point"}
}
