{
  "type": "Feature",
  "properties": {
    "date:inception_lower": "2016-04-01",
    "date:inception_upper": "2016-04-01",
    "iso:country": "GB",
    "wof:name": "ME15 8GJ",
    "wof:placetype": "postalcode"
  },
  "geometry": {"coordinates":[0.56337,51.242818],"type":"Point"}
}
