{
  "type": "Feature",
  "properties": {
    "date:inception_lower": "1996-12-01",
    "date:inception_upper": "1996-12-01",
    "iso:country": "GB",
    "wof:name": "SY1 1RT",
    "wof:placetype": "postalcode"
  },
  "geometry": {"coordinates":[-2.758481,52.709435],"type":"Point"}
}
