{
  "type": "Feature",
  "properties": {
    "iso:country": "GB",
    "wof:name": "SY1 1RT",
    "wof:placetype": "postalcode"
  },
  "geometry": {"coordinates":[-2.758481,52.709435],"type":"Point"}
}
