{
  "type": "Feature",
  "properties": {
    "iso:country":"GB",
    "wof:name":"SY1 1RT",
    "wof:placetype":"postalcode"
},
  "geometry": {"coordinates":[-2.75848093903334,52.70943508470976],"type":"Point"}
}