{
  "type": "Feature",
  "properties": {
    "date:inception_lower": "2019-09-01",
    "date:inception_upper": "2019-09-01",
    "iso:country": "GB",
    "wof:name": "CW8 2FN",
    "wof:placetype": "postalcode"
  },
  "geometry": {"coordinates":[-2.663777,53.22617],"type":"Point"}
}
