{
  "type": "Feature",
  "properties": {
    "iso:country": "GB",
    "wof:name": "CW8 2FN",
    "wof:placetype": "postalcode"
  },
  "geometry": {"coordinates":[-2.663803,53.22688],"type":"Point"}
}
