{
  "type": "Feature",
  "properties": {
    "date:inception_lower": "2019-09-01",
    "date:inception_upper": "2019-09-01",
    "iso:country": "GB",
    "wof:name": "CW8 2FN",
    "wof:placetype": "postalcode"
  },
  "geometry": {"coordinates":[-2.664186,53.226473],"type":"Point"}
}
