{
  "type": "Feature",
  "properties": {
    "iso:country":"GB",
    "wof:name":"HU16 4PL",
    "wof:placetype":"postalcode"
},
  "geometry": {"coordinates":[-0.39638002752701,53.77703674675701],"type":"Point"}
}