{
  "type": "Feature",
  "properties": {
    "iso:country":"GB",
    "wof:name":"HA1 4ND",
    "wof:placetype":"postalcode"
},
  "geometry": {"coordinates":[-0.35303555819912,51.58379504374696],"type":"Point"}
}