{
  "type": "Feature",
  "properties": {
    "iso:country":"GB",
    "wof:name":"EH9 3DB",
    "wof:placetype":"postalcode"
},
  "geometry": {"coordinates":[-3.17561159097047,55.92609510330009],"type":"Point"}
}