{
  "type": "Feature",
  "properties": {
    "date:inception_lower": "1980-01-01",
    "date:inception_upper": "1980-01-01",
    "iso:country": "GB",
    "wof:name": "EH9 3DB",
    "wof:placetype": "postalcode"
  },
  "geometry": {"coordinates":[-3.175612,55.926095],"type":"Point"}
}
