{
  "type": "Feature",
  "properties": {
    "iso:country":"GB",
    "wof:name":"DE22 4LU",
    "wof:placetype":"postalcode"
},
  "geometry": {"coordinates":[-1.52922107595172,52.93037228430752],"type":"Point"}
}