{
  "type": "Feature",
  "properties": {
    "iso:country": "GB",
    "wof:name": "PL5 4EL",
    "wof:placetype": "postalcode"
  },
  "geometry": {"coordinates":[-4.150478,50.419742],"type":"Point"}
}
