{
  "type": "Feature",
  "properties": {
    "iso:country":"GB",
    "wof:name":"PL5 4EL",
    "wof:placetype":"postalcode"
},
  "geometry": {"coordinates":[-4.15047756305378,50.41974202067534],"type":"Point"}
}