{
  "type": "Feature",
  "properties": {
    "date:inception_lower": "2024-04-01",
    "date:inception_upper": "2024-04-01",
    "iso:country": "GB",
    "wof:name": "IP5 4AE",
    "wof:placetype": "postalcode"
  },
  "geometry": {"coordinates":[1.291764,52.053153],"type":"Point"}
}
