{
  "type": "Feature",
  "properties": {
    "iso:country": "GB",
    "wof:name": "M23 0GJ",
    "wof:placetype": "postalcode"
  },
  "geometry": {"coordinates":[-2.293427,53.40144],"type":"Point"}
}
