{
  "type": "Feature",
  "properties": {
    "date:inception_lower":"1980-01-01",
    "date:inception_upper":"1980-01-31",
    "iso:country":"GB",
    "wof:name":"NG11 0JX",
    "wof:placetype":"postalcode"
},
  "geometry": {"coordinates":[-1.206401,52.865783],"type":"Point"}
}