{
  "type": "Feature",
  "properties": {
    "date:inception_lower": "1980-01-01",
    "date:inception_upper": "1980-01-01",
    "iso:country": "GB",
    "wof:name": "PO9 2PL",
    "wof:placetype": "postalcode"
  },
  "geometry": {"coordinates":[-0.964315,50.856018],"type":"Point"}
}
