{
  "type": "Feature",
  "properties": {
    "iso:country":"GB",
    "wof:name":"PO9 2PL",
    "wof:placetype":"postalcode"
},
  "geometry": {"coordinates":[-0.96431492147481,50.85601777968733],"type":"Point"}
}