{
  "type": "Feature",
  "properties": {
    "iso:country":"GB",
    "wof:name":"WS10 0RJ",
    "wof:placetype":"postalcode"
},
  "geometry": {"coordinates":[-2.00132838767943,52.5584170787159],"type":"Point"}
}