{
  "type": "Feature",
  "properties": {
    "date:inception_lower": "1980-01-01",
    "date:inception_upper": "1980-01-01",
    "iso:country": "GB",
    "wof:name": "WS10 0RJ",
    "wof:placetype": "postalcode"
  },
  "geometry": {"coordinates":[-2.001328,52.558417],"type":"Point"}
}
