{
  "type": "Feature",
  "properties": {
    "date:inception_lower":"1984-02-01",
    "date:inception_upper":"1984-02-29",
    "iso:country":"GB",
    "wof:name":"GU22 7EF",
    "wof:placetype":"postalcode"
},
  "geometry": {"coordinates":[-0.542823,51.318985],"type":"Point"}
}