{
  "type": "Feature",
  "properties": {
    "iso:country": "GB",
    "wof:name": "SK6 4AX",
    "wof:placetype": "postalcode"
  },
  "geometry": {"coordinates":[-2.09086,53.420571],"type":"Point"}
}
