{
  "type": "Feature",
  "properties": {
    "iso:country": "GB",
    "wof:name": "IG11 0AS",
    "wof:placetype": "postalcode"
  },
  "geometry": {"coordinates":[0.104943,51.531745],"type":"Point"}
}
