{
  "type": "Feature",
  "properties": {
    "iso:country":"GB",
    "wof:name":"CR0 1JH",
    "wof:placetype":"postalcode"
},
  "geometry": {"coordinates":[-0.097176356187,51.36991212230016],"type":"Point"}
}