{
  "type": "Feature",
  "properties": {
    "iso:country": "GB",
    "wof:name": "CR0 1JH",
    "wof:placetype": "postalcode"
  },
  "geometry": {"coordinates":[-0.097176,51.369912],"type":"Point"}
}
