{
  "type": "Feature",
  "properties": {
    "iso:country":"GB",
    "wof:name":"HU5 5YB",
    "wof:placetype":"postalcode"
},
  "geometry": {"coordinates":[-0.4128340149845,53.74959640681653],"type":"Point"}
}