{
  "type": "Feature",
  "properties": {
    "iso:country":"GB",
    "wof:name":"CF48 4NH",
    "wof:placetype":"postalcode"
},
  "geometry": {"coordinates":[-3.34829647292095,51.71254980584914],"type":"Point"}
}