{
  "type": "Feature",
  "properties": {
    "date:inception_lower": "1994-05-01",
    "date:inception_upper": "1994-05-01",
    "iso:country": "GB",
    "wof:name": "CF48 4NH",
    "wof:placetype": "postalcode"
  },
  "geometry": {"coordinates":[-3.348296,51.71255],"type":"Point"}
}
