{
  "type": "Feature",
  "properties": {
    "iso:country":"GB",
    "wof:name":"GU15 1QG",
    "wof:placetype":"postalcode"
},
  "geometry": {"coordinates":[-0.69694537176001,51.32554893208841],"type":"Point"}
}