{
  "type": "Feature",
  "properties": {
    "date:inception_lower": "2005-01-01",
    "date:inception_upper": "2005-01-01",
    "iso:country": "GB",
    "wof:name": "EX34 7EN",
    "wof:placetype": "postalcode"
  },
  "geometry": {"coordinates":[-4.205102,51.187956],"type":"Point"}
}
