{
  "type": "Feature",
  "properties": {
    "iso:country":"GB",
    "wof:name":"EX34 7EN",
    "wof:placetype":"postalcode"
},
  "geometry": {"coordinates":[-4.20510176789598,51.18795639374428],"type":"Point"}
}