{
  "type": "Feature",
  "properties": {
    "iso:country": "GB",
    "wof:name": "EX34 7EN",
    "wof:placetype": "postalcode"
  },
  "geometry": {"coordinates":[-4.205102,51.187956],"type":"Point"}
}
