{
  "type": "Feature",
  "properties": {
    "iso:country":"GB",
    "wof:name":"BD23 1HF",
    "wof:placetype":"postalcode"
},
  "geometry": {"coordinates":[-2.00641091463262,53.96148308791862],"type":"Point"}
}