{
  "type": "Feature",
  "properties": {
    "date:inception_lower":"1995-07-01",
    "date:inception_upper":"1995-07-31",
    "iso:country":"GB",
    "wof:name":"BD23 1HF",
    "wof:placetype":"postalcode"
},
  "geometry": {"coordinates":[-2.006411,53.961483],"type":"Point"}
}