{
  "type": "Feature",
  "properties": {
    "date:inception_lower":"1997-06-01",
    "date:inception_upper":"1997-06-30",
    "iso:country":"GB",
    "wof:name":"BS24 7SB",
    "wof:placetype":"postalcode"
},
  "geometry": {"coordinates":[-2.918332,51.352407],"type":"Point"}
}