{
  "type": "Feature",
  "properties": {
    "iso:country":"GB",
    "wof:name":"BS24 7SB",
    "wof:placetype":"postalcode"
},
  "geometry": {"coordinates":[-2.91831247123198,51.35238272852068],"type":"Point"}
}