{
  "type": "Feature",
  "properties": {
    "iso:country":"GB",
    "wof:name":"WD3 1FD",
    "wof:placetype":"postalcode"
},
  "geometry": {"coordinates":[-0.47538016030977,51.63931919154138],"type":"Point"}
}