{
  "type": "Feature",
  "properties": {
    "date:inception_lower": "2001-12-01",
    "date:inception_upper": "2001-12-01",
    "iso:country": "GB",
    "wof:name": "TR7 1RX",
    "wof:placetype": "postalcode"
  },
  "geometry": {"coordinates":[-5.092118,50.408279],"type":"Point"}
}
