{
  "type": "Feature",
  "properties": {
    "iso:country": "GB",
    "wof:name": "TR7 1RX",
    "wof:placetype": "postalcode"
  },
  "geometry": {"coordinates":[-5.092118,50.408279],"type":"Point"}
}
