{
  "type": "Feature",
  "properties": {
    "iso:country":"GB",
    "wof:name":"TR7 1RX",
    "wof:placetype":"postalcode"
},
  "geometry": {"coordinates":[-5.09211825902336,50.40827870876719],"type":"Point"}
}