{
  "type": "Feature",
  "properties": {
    "iso:country":"GB",
    "wof:name":"NE16 5DN",
    "wof:placetype":"postalcode"
},
  "geometry": {"coordinates":[-1.68341397006086,54.91684719533477],"type":"Point"}
}