{
  "type": "Feature",
  "properties": {
    "iso:country":"GB",
    "wof:name":"LA5 0DB",
    "wof:placetype":"postalcode"
},
  "geometry": {"coordinates":[-2.83407685789796,54.20169810144914],"type":"Point"}
}