{
  "type": "Feature",
  "properties": {
    "date:inception_lower": "1980-01-01",
    "date:inception_upper": "1980-01-01",
    "iso:country": "GB",
    "wof:name": "LA5 0DB",
    "wof:placetype": "postalcode"
  },
  "geometry": {"coordinates":[-2.834077,54.201698],"type":"Point"}
}
