{
  "type": "Feature",
  "properties": {
    "iso:country": "GB",
    "wof:name": "LA5 0DB",
    "wof:placetype": "postalcode"
  },
  "geometry": {"coordinates":[-2.834077,54.201698],"type":"Point"}
}
