{
  "type": "Feature",
  "properties": {
    "date:inception_lower":"1997-06-01",
    "date:inception_upper":"1997-06-30",
    "iso:country":"GB",
    "wof:name":"CF82 8LF",
    "wof:placetype":"postalcode"
},
  "geometry": {"coordinates":[-3.241162,51.664627],"type":"Point"}
}