{
  "type": "Feature",
  "properties": {
    "iso:country":"GB",
    "wof:name":"G11 5BX",
    "wof:placetype":"postalcode"
},
  "geometry": {"coordinates":[-4.3065097756796,55.87509744049215],"type":"Point"}
}