{
  "type": "Feature",
  "properties": {
    "iso:country":"GB",
    "wof:name":"NP20 4AU",
    "wof:placetype":"postalcode"
},
  "geometry": {"coordinates":[-2.99901013205736,51.58798212351103],"type":"Point"}
}