{
  "type": "Feature",
  "properties": {
    "iso:country": "GB",
    "wof:name": "BA2 0FZ",
    "wof:placetype": "postalcode"
  },
  "geometry": {"coordinates":[-2.494367,51.343588],"type":"Point"}
}
