{
  "type": "Feature",
  "properties": {
    "date:inception_lower": "2001-06-01",
    "date:inception_upper": "2001-06-01",
    "iso:country": "GB",
    "wof:name": "BA2 0FZ",
    "wof:placetype": "postalcode"
  },
  "geometry": {"coordinates":[-2.494367,51.343588],"type":"Point"}
}
