{
  "type": "Feature",
  "properties": {
    "date:inception_lower": "1980-01-01",
    "date:inception_upper": "1980-01-01",
    "iso:country": "GB",
    "wof:name": "HD7 5TR",
    "wof:placetype": "postalcode"
  },
  "geometry": {"coordinates":[-1.855349,53.614313],"type":"Point"}
}
