{
  "type": "Feature",
  "properties": {
    "iso:country":"GB",
    "wof:name":"NP44 2HA",
    "wof:placetype":"postalcode"
},
  "geometry": {"coordinates":[-3.00615572449955,51.66113058311702],"type":"Point"}
}