{
  "type": "Feature",
  "properties": {
    "date:inception_lower": "1980-01-01",
    "date:inception_upper": "1980-01-01",
    "iso:country": "GB",
    "wof:name": "NP44 2HA",
    "wof:placetype": "postalcode"
  },
  "geometry": {"coordinates":[-3.006156,51.661131],"type":"Point"}
}
