{
  "type": "Feature",
  "properties": {
    "date:inception_lower":"1986-01-01",
    "date:inception_upper":"1986-01-31",
    "iso:country":"GB",
    "wof:name":"SO43 7HG",
    "wof:placetype":"postalcode"
},
  "geometry": {"coordinates":[-1.621557,50.925851],"type":"Point"}
}