{
  "type": "Feature",
  "properties": {
    "iso:country": "GB",
    "wof:name": "SO43 7HG",
    "wof:placetype": "postalcode"
  },
  "geometry": {"coordinates":[-1.621557,50.925851],"type":"Point"}
}
