{
  "type": "Feature",
  "properties": {
    "iso:country": "GB",
    "wof:name": "HU15 2AE",
    "wof:placetype": "postalcode"
  },
  "geometry": {"coordinates":[-0.606947,53.780785],"type":"Point"}
}
