{
  "type": "Feature",
  "properties": {
    "iso:country":"GB",
    "wof:name":"HU15 2AE",
    "wof:placetype":"postalcode"
},
  "geometry": {"coordinates":[-0.60941964525254,53.78294171481745],"type":"Point"}
}