{
  "type": "Feature",
  "properties": {
    "iso:country": "GB",
    "wof:name": "LD2 3RX",
    "wof:placetype": "postalcode"
  },
  "geometry": {"coordinates":[-3.410418,52.127586],"type":"Point"}
}
