{
  "type": "Feature",
  "properties": {
    "iso:country": "GB",
    "wof:name": "S26 2BE",
    "wof:placetype": "postalcode"
  },
  "geometry": {"coordinates":[-1.278707,53.36633],"type":"Point"}
}
