{
  "type": "Feature",
  "properties": {
    "iso:country": "GB",
    "wof:name": "SY20 9AA",
    "wof:placetype": "postalcode"
  },
  "geometry": {"coordinates":[-3.707798,52.64636],"type":"Point"}
}
