{
  "type": "Feature",
  "properties": {
    "iso:country":"GB",
    "wof:name":"GL4 0UA",
    "wof:placetype":"postalcode"
},
  "geometry": {"coordinates":[-2.24635957489286,51.82583659746009],"type":"Point"}
}