{
  "type": "Feature",
  "properties": {
    "iso:country": "GB",
    "wof:name": "GL4 0UA",
    "wof:placetype": "postalcode"
  },
  "geometry": {"coordinates":[-2.246356,51.825843],"type":"Point"}
}
