{
  "type": "Feature",
  "properties": {
    "date:inception_lower": "1980-01-01",
    "date:inception_upper": "1980-01-01",
    "iso:country": "GB",
    "wof:name": "GL4 0UA",
    "wof:placetype": "postalcode"
  },
  "geometry": {"coordinates":[-2.246356,51.825843],"type":"Point"}
}
