{
  "type": "Feature",
  "properties": {
    "iso:country":"GB",
    "wof:name":"LE4 9LS",
    "wof:placetype":"postalcode"
},
  "geometry": {"coordinates":[-1.09217903609524,52.65711076508822],"type":"Point"}
}