{
  "type": "Feature",
  "properties": {
    "date:inception_lower": "1980-01-01",
    "date:inception_upper": "1980-01-01",
    "iso:country": "GB",
    "wof:name": "CV35 7DB",
    "wof:placetype": "postalcode"
  },
  "geometry": {"coordinates":[-1.705669,52.329138],"type":"Point"}
}
