{
  "type": "Feature",
  "properties": {
    "iso:country":"GB",
    "wof:name":"SP2 7ST",
    "wof:placetype":"postalcode"
},
  "geometry": {"coordinates":[-1.80217794455853,51.07017996450482],"type":"Point"}
}