{
  "type": "Feature",
  "properties": {
    "iso:country":"GB",
    "wof:name":"HG1 2JB",
    "wof:placetype":"postalcode"
},
  "geometry": {"coordinates":[-1.54612550209045,53.99817792144131],"type":"Point"}
}