{
  "type": "Feature",
  "properties": {
    "iso:country":"GB",
    "wof:name":"HA4 6AB",
    "wof:placetype":"postalcode"
},
  "geometry": {"coordinates":[-0.41098419405902,51.56858790106855],"type":"Point"}
}