{
  "type": "Feature",
  "properties": {
    "iso:country": "GB",
    "wof:name": "SA44 6JG",
    "wof:placetype": "postalcode"
  },
  "geometry": {"coordinates":[-4.342513,52.171583],"type":"Point"}
}
