{
  "type": "Feature",
  "properties": {
    "iso:country":"GB",
    "wof:name":"TR16 5QF",
    "wof:placetype":"postalcode"
},
  "geometry": {"coordinates":[-5.16619195863367,50.24734621687185],"type":"Point"}
}