{
  "type": "Feature",
  "properties": {
    "date:inception_lower": "2020-06-01",
    "date:inception_upper": "2020-06-01",
    "iso:country": "GB",
    "wof:name": "KT20 5FT",
    "wof:placetype": "postalcode"
  },
  "geometry": {"coordinates":[-0.22616,51.305722],"type":"Point"}
}
