{
  "type": "Feature",
  "properties": {
    "iso:country":"GB",
    "wof:name":"WA7 1LX",
    "wof:placetype":"postalcode"
},
  "geometry": {"coordinates":[-2.7327050074787,53.34231107040116],"type":"Point"}
}