{
  "type": "Feature",
  "properties": {
    "date:inception_lower": "1980-01-01",
    "date:inception_upper": "1980-01-01",
    "iso:country": "GB",
    "wof:name": "WA7 1LX",
    "wof:placetype": "postalcode"
  },
  "geometry": {"coordinates":[-2.732767,53.342345],"type":"Point"}
}
