{
  "type": "Feature",
  "properties": {
    "iso:country":"GB",
    "wof:name":"ME10 1AY",
    "wof:placetype":"postalcode"
},
  "geometry": {"coordinates":[0.72917989290156,51.34238233750695],"type":"Point"}
}