{
  "type": "Feature",
  "properties": {
    "date:inception_lower": "1998-06-01",
    "date:inception_upper": "1998-06-01",
    "iso:country": "GB",
    "wof:name": "YO42 1UG",
    "wof:placetype": "postalcode"
  },
  "geometry": {"coordinates":[-0.732309,53.928453],"type":"Point"}
}
