{
  "type": "Feature",
  "properties": {
    "iso:country":"GB",
    "wof:name":"GL7 3BX",
    "wof:placetype":"postalcode"
},
  "geometry": {"coordinates":[-1.69164829679132,51.70007716389812],"type":"Point"}
}