{
  "type": "Feature",
  "properties": {
    "iso:country": "GB",
    "wof:name": "GL7 3BX",
    "wof:placetype": "postalcode"
  },
  "geometry": {"coordinates":[-1.691648,51.700077],"type":"Point"}
}
