{
  "type": "Feature",
  "properties": {
    "iso:country":"GB",
    "wof:name":"WA6 7QR",
    "wof:placetype":"postalcode"
},
  "geometry": {"coordinates":[-2.71893040655841,53.29400772260767],"type":"Point"}
}