{
  "type": "Feature",
  "properties": {
    "iso:country": "GB",
    "wof:name": "LN3 4DA",
    "wof:placetype": "postalcode"
  },
  "geometry": {"coordinates":[-0.451633,53.237602],"type":"Point"}
}
