{
  "type": "Feature",
  "properties": {
    "iso:country":"GB",
    "wof:name":"LN3 4DA",
    "wof:placetype":"postalcode"
},
  "geometry": {"coordinates":[-0.45163258009293,53.23760186257911],"type":"Point"}
}