{
  "type": "Feature",
  "properties": {
    "iso:country": "GB",
    "wof:name": "SK11 7UU",
    "wof:placetype": "postalcode"
  },
  "geometry": {"coordinates":[-2.149626,53.246985],"type":"Point"}
}
