{
  "type": "Feature",
  "properties": {
    "iso:country":"GB",
    "wof:name":"SK11 7UU",
    "wof:placetype":"postalcode"
},
  "geometry": {"coordinates":[-2.1496258043438,53.24698512670594],"type":"Point"}
}