{
  "type": "Feature",
  "properties": {
    "iso:country":"GB",
    "wof:name":"NW3 3DY",
    "wof:placetype":"postalcode"
},
  "geometry": {"coordinates":[-0.16370235035893,51.54405352151986],"type":"Point"}
}