{
  "type": "Feature",
  "properties": {
    "iso:country":"GB",
    "wof:name":"TN29 9AZ",
    "wof:placetype":"postalcode"
},
  "geometry": {"coordinates":[0.90441990043579,50.94985658979748],"type":"Point"}
}