{
  "type": "Feature",
  "properties": {
    "iso:country": "GB",
    "wof:name": "TN29 9AZ",
    "wof:placetype": "postalcode"
  },
  "geometry": {"coordinates":[0.90442,50.949857],"type":"Point"}
}
