{
  "type": "Feature",
  "properties": {
    "iso:country":"GB",
    "wof:name":"SA6 6BJ",
    "wof:placetype":"postalcode"
},
  "geometry": {"coordinates":[-3.95283172756207,51.67193335609068],"type":"Point"}
}