{
  "type": "Feature",
  "properties": {
    "date:inception_lower": "1984-02-01",
    "date:inception_upper": "1984-02-01",
    "iso:country": "GB",
    "wof:name": "SA6 6BJ",
    "wof:placetype": "postalcode"
  },
  "geometry": {"coordinates":[-3.952832,51.671933],"type":"Point"}
}
