{
  "type": "Feature",
  "properties": {
    "iso:country":"GB",
    "wof:name":"NE63 0EP",
    "wof:placetype":"postalcode"
},
  "geometry": {"coordinates":[-1.56678256256022,55.17703279223735],"type":"Point"}
}