{
  "type": "Feature",
  "properties": {
    "iso:country": "GB",
    "wof:name": "SA11 3RG",
    "wof:placetype": "postalcode"
  },
  "geometry": {"coordinates":[-3.782654,51.651342],"type":"Point"}
}
