{
  "type": "Feature",
  "properties": {
    "iso:country":"GB",
    "wof:name":"SA11 3RG",
    "wof:placetype":"postalcode"
},
  "geometry": {"coordinates":[-3.78265397097027,51.65134169141064],"type":"Point"}
}