{
  "type": "Feature",
  "properties": {
    "iso:country":"GB",
    "wof:name":"NR2 4LW",
    "wof:placetype":"postalcode"
},
  "geometry": {"coordinates":[1.27885520955827,52.64076369648637],"type":"Point"}
}