{
  "type": "Feature",
  "properties": {
    "iso:country": "GB",
    "wof:name": "PO7 7RF",
    "wof:placetype": "postalcode"
  },
  "geometry": {"coordinates":[-1.034352,50.885844],"type":"Point"}
}
