{
  "type": "Feature",
  "properties": {
    "date:inception_lower":"1980-01-01",
    "date:inception_upper":"1980-01-31",
    "iso:country":"GB",
    "wof:name":"SL7 1TB",
    "wof:placetype":"postalcode"
},
  "geometry": {"coordinates":[-0.765457,51.571233],"type":"Point"}
}