{
  "type": "Feature",
  "properties": {
    "date:inception_lower":"2016-05-01",
    "date:inception_upper":"2016-05-31",
    "iso:country":"GB",
    "wof:name":"OX28 9FA",
    "wof:placetype":"postalcode"
},
  "geometry": {"coordinates":[-1.485118,51.776948],"type":"Point"}
}