{
  "type": "Feature",
  "properties": {
    "iso:country": "GB",
    "wof:name": "SA14 9EF",
    "wof:placetype": "postalcode"
  },
  "geometry": {"coordinates":[-4.123377,51.683388],"type":"Point"}
}
