{
  "type": "Feature",
  "properties": {
    "iso:country":"GB",
    "wof:name":"SR4 6JR",
    "wof:placetype":"postalcode"
},
  "geometry": {"coordinates":[-1.41036071581523,54.90536961959342],"type":"Point"}
}