{
  "type": "Feature",
  "properties": {
    "iso:country":"GB",
    "wof:name":"WF4 2LB",
    "wof:placetype":"postalcode"
},
  "geometry": {"coordinates":[-1.5187264462675,53.61493831579808],"type":"Point"}
}