{
  "type": "Feature",
  "properties": {
    "iso:country": "GB",
    "wof:name": "WF4 2LB",
    "wof:placetype": "postalcode"
  },
  "geometry": {"coordinates":[-1.518726,53.614938],"type":"Point"}
}
