{
  "type": "Feature",
  "properties": {
    "iso:country": "GB",
    "wof:name": "ME18 5BZ",
    "wof:placetype": "postalcode"
  },
  "geometry": {"coordinates":[0.445125,51.25678],"type":"Point"}
}
