{
  "type": "Feature",
  "properties": {
    "iso:country":"GB",
    "wof:name":"TW18 1UD",
    "wof:placetype":"postalcode"
},
  "geometry": {"coordinates":[-0.49191638067333,51.40880374648475],"type":"Point"}
}