{
  "type": "Feature",
  "properties": {
    "iso:country":"GB",
    "wof:name":"LL65 3HG",
    "wof:placetype":"postalcode"
},
  "geometry": {"coordinates":[-4.55807467088406,53.27026534980993],"type":"Point"}
}