{
  "type": "Feature",
  "properties": {
    "iso:country":"GB",
    "wof:name":"BS40 7TZ",
    "wof:placetype":"postalcode"
},
  "geometry": {"coordinates":[-2.73331694569418,51.31859188777215],"type":"Point"}
}