{
  "type": "Feature",
  "properties": {
    "iso:country": "GB",
    "wof:name": "BS40 7TZ",
    "wof:placetype": "postalcode"
  },
  "geometry": {"coordinates":[-2.733317,51.318592],"type":"Point"}
}
