{
  "type": "Feature",
  "properties": {
    "iso:country": "GB",
    "wof:name": "CM3 1FQ",
    "wof:placetype": "postalcode"
  },
  "geometry": {"coordinates":[0.511256,51.830586],"type":"Point"}
}
