{
  "type": "Feature",
  "properties": {
    "iso:country":"GB",
    "wof:name":"CO1 2SA",
    "wof:placetype":"postalcode"
},
  "geometry": {"coordinates":[0.90873700193036,51.89308317543995],"type":"Point"}
}