{
  "type": "Feature",
  "properties": {
    "iso:country": "GB",
    "wof:name": "KA23 9FF",
    "wof:placetype": "postalcode"
  },
  "geometry": {"coordinates":[-4.857825,55.682282],"type":"Point"}
}
