{
  "type": "Feature",
  "properties": {
    "date:inception_lower": "2018-05-01",
    "date:inception_upper": "2018-05-01",
    "iso:country": "GB",
    "wof:name": "KA23 9FF",
    "wof:placetype": "postalcode"
  },
  "geometry": {"coordinates":[-4.857857,55.682075],"type":"Point"}
}
