{
  "type": "Feature",
  "properties": {
    "date:inception_lower": "1980-01-01",
    "date:inception_upper": "1980-01-01",
    "iso:country": "GB",
    "wof:name": "OL16 3UP",
    "wof:placetype": "postalcode"
  },
  "geometry": {"coordinates":[-2.112125,53.61552],"type":"Point"}
}
