{
  "type": "Feature",
  "properties": {
    "date:inception_lower":"1980-01-01",
    "date:inception_upper":"1980-01-31",
    "iso:country":"GB",
    "wof:name":"WS12 4QL",
    "wof:placetype":"postalcode"
},
  "geometry": {"coordinates":[-2.034928,52.721692],"type":"Point"}
}