{
  "type": "Feature",
  "properties": {
    "iso:country": "GB",
    "wof:name": "WS12 4QL",
    "wof:placetype": "postalcode"
  },
  "geometry": {"coordinates":[-2.034928,52.721692],"type":"Point"}
}
