{
  "type": "Feature",
  "properties": {
    "date:inception_lower": "2015-05-01",
    "date:inception_upper": "2015-05-01",
    "iso:country": "GB",
    "wof:name": "BH2 6DH",
    "wof:placetype": "postalcode"
  },
  "geometry": {"coordinates":[-1.891959,50.721482],"type":"Point"}
}
