{
  "type": "Feature",
  "properties": {
    "iso:country":"GB",
    "wof:name":"IV17 0YG",
    "wof:placetype":"postalcode"
},
  "geometry": {"coordinates":[-4.32528247498359,57.73947183008105],"type":"Point"}
}