{
  "type": "Feature",
  "properties": {
    "date:inception_lower": "1980-01-01",
    "date:inception_upper": "1980-01-01",
    "iso:country": "GB",
    "wof:name": "IV17 0YG",
    "wof:placetype": "postalcode"
  },
  "geometry": {"coordinates":[-4.325282,57.739472],"type":"Point"}
}
