{
  "type": "Feature",
  "properties": {
    "iso:country": "GB",
    "wof:name": "TS22 5FP",
    "wof:placetype": "postalcode"
  },
  "geometry": {"coordinates":[-1.325454,54.638124],"type":"Point"}
}
