{
  "type": "Feature",
  "properties": {
    "date:inception_lower": "1980-01-01",
    "date:inception_upper": "1980-01-01",
    "iso:country": "GB",
    "wof:name": "AL1 1TZ",
    "wof:placetype": "postalcode"
  },
  "geometry": {"coordinates":[-0.333828,51.74727],"type":"Point"}
}
