{
  "type": "Feature",
  "properties": {
    "date:inception_lower": "1980-01-01",
    "date:inception_upper": "1980-01-01",
    "iso:country": "GB",
    "wof:name": "PE31 6DG",
    "wof:placetype": "postalcode"
  },
  "geometry": {"coordinates":[0.554195,52.789859],"type":"Point"}
}
