{
  "type": "Feature",
  "properties": {
    "iso:country": "GB",
    "wof:name": "PE31 6DG",
    "wof:placetype": "postalcode"
  },
  "geometry": {"coordinates":[0.554195,52.789859],"type":"Point"}
}
