{
  "type": "Feature",
  "properties": {
    "iso:country":"GB",
    "wof:name":"PE31 6DG",
    "wof:placetype":"postalcode"
},
  "geometry": {"coordinates":[0.55419454438335,52.78985850660825],"type":"Point"}
}