{
  "type": "Feature",
  "properties": {
    "iso:country":"GB",
    "wof:name":"BR5 2JA",
    "wof:placetype":"postalcode"
},
  "geometry": {"coordinates":[0.09363092534609,51.39281788699751],"type":"Point"}
}