{
  "type": "Feature",
  "properties": {
    "iso:country":"GB",
    "wof:name":"GU10 5DX",
    "wof:placetype":"postalcode"
},
  "geometry": {"coordinates":[-0.83664375984901,51.21959858867371],"type":"Point"}
}