{
  "type": "Feature",
  "properties": {
    "date:inception_lower": "1980-01-01",
    "date:inception_upper": "1980-01-01",
    "iso:country": "GB",
    "wof:name": "GU10 5DX",
    "wof:placetype": "postalcode"
  },
  "geometry": {"coordinates":[-0.836644,51.219599],"type":"Point"}
}
