{
  "type": "Feature",
  "properties": {
    "iso:country":"GB",
    "wof:name":"ST21 6LX",
    "wof:placetype":"postalcode"
},
  "geometry": {"coordinates":[-2.25935253862184,52.88939060460191],"type":"Point"}
}