{
  "type": "Feature",
  "properties": {
    "iso:country":"GB",
    "wof:name":"CF39 9RX",
    "wof:placetype":"postalcode"
},
  "geometry": {"coordinates":[-3.41711397192956,51.59966524078295],"type":"Point"}
}