{
  "type": "Feature",
  "properties": {
    "date:inception_lower": "2005-11-01",
    "date:inception_upper": "2005-11-01",
    "iso:country": "GB",
    "wof:name": "PH2 9GZ",
    "wof:placetype": "postalcode"
  },
  "geometry": {"coordinates":[-3.308288,56.332603],"type":"Point"}
}
