{
  "type": "Feature",
  "properties": {
    "iso:country":"GB",
    "wof:name":"PH2 9GZ",
    "wof:placetype":"postalcode"
},
  "geometry": {"coordinates":[-3.30828799437699,56.33260332163548],"type":"Point"}
}