{
  "type": "Feature",
  "properties": {
    "date:inception_lower": "1986-07-01",
    "date:inception_upper": "1986-07-01",
    "iso:country": "GB",
    "wof:name": "RG4 8XU",
    "wof:placetype": "postalcode"
  },
  "geometry": {"coordinates":[-0.962388,51.483078],"type":"Point"}
}
