{
  "type": "Feature",
  "properties": {
    "iso:country":"GB",
    "wof:name":"RG4 8XU",
    "wof:placetype":"postalcode"
},
  "geometry": {"coordinates":[-0.96238809256126,51.48308686355056],"type":"Point"}
}