{
  "type": "Feature",
  "properties": {
    "iso:country": "GB",
    "wof:name": "S40 2LW",
    "wof:placetype": "postalcode"
  },
  "geometry": {"coordinates":[-1.434012,53.228586],"type":"Point"}
}
