{
  "type": "Feature",
  "properties": {
    "date:inception_lower": "1980-01-01",
    "date:inception_upper": "1980-01-01",
    "iso:country": "GB",
    "wof:name": "TS21 2HN",
    "wof:placetype": "postalcode"
  },
  "geometry": {"coordinates":[-1.467921,54.641088],"type":"Point"}
}
