{
  "type": "Feature",
  "properties": {
    "iso:country": "GB",
    "wof:name": "TS21 2HN",
    "wof:placetype": "postalcode"
  },
  "geometry": {"coordinates":[-1.468494,54.641064],"type":"Point"}
}
