{
  "type": "Feature",
  "properties": {
    "iso:country":"GB",
    "wof:name":"TS21 2HN",
    "wof:placetype":"postalcode"
},
  "geometry": {"coordinates":[-1.46825003458936,54.64107945368572],"type":"Point"}
}