{
  "type": "Feature",
  "properties": {
    "iso:country":"GB",
    "wof:name":"G46 6UG",
    "wof:placetype":"postalcode"
},
  "geometry": {"coordinates":[-4.3018181235226,55.7976942661874],"type":"Point"}
}