{
  "type": "Feature",
  "properties": {
    "date:inception_lower": "1993-01-01",
    "date:inception_upper": "1993-01-01",
    "iso:country": "GB",
    "wof:name": "TW1 3RZ",
    "wof:placetype": "postalcode"
  },
  "geometry": {"coordinates":[-0.328559,51.446685],"type":"Point"}
}
