{
  "type": "Feature",
  "properties": {
    "iso:country":"GB",
    "wof:name":"CO11 2JA",
    "wof:placetype":"postalcode"
},
  "geometry": {"coordinates":[1.04232979532589,51.93638085561015],"type":"Point"}
}