{
  "type": "Feature",
  "properties": {
    "iso:country": "GB",
    "wof:name": "CO11 2JA",
    "wof:placetype": "postalcode"
  },
  "geometry": {"coordinates":[1.04233,51.936381],"type":"Point"}
}
