{
  "type": "Feature",
  "properties": {
    "iso:country":"GB",
    "wof:name":"BD4 8AG",
    "wof:placetype":"postalcode"
},
  "geometry": {"coordinates":[-1.72002437121755,53.79137684247599],"type":"Point"}
}