{
  "type": "Feature",
  "properties": {
    "iso:country":"GB",
    "wof:name":"CM4 9RH",
    "wof:placetype":"postalcode"
},
  "geometry": {"coordinates":[0.44980803796912,51.6454211971656],"type":"Point"}
}