{
  "type": "Feature",
  "properties": {
    "date:inception_lower": "1994-05-01",
    "date:inception_upper": "1994-05-01",
    "iso:country": "GB",
    "wof:name": "CM4 9RH",
    "wof:placetype": "postalcode"
  },
  "geometry": {"coordinates":[0.449808,51.645421],"type":"Point"}
}
