{
  "type": "Feature",
  "properties": {
    "iso:country":"GB",
    "wof:name":"N6 5TH",
    "wof:placetype":"postalcode"
},
  "geometry": {"coordinates":[-0.14167247121362,51.57503630267153],"type":"Point"}
}