{
  "type": "Feature",
  "properties": {
    "iso:country":"GB",
    "wof:name":"SN4 9AD",
    "wof:placetype":"postalcode"
},
  "geometry": {"coordinates":[-1.78509079182319,51.53524977881712],"type":"Point"}
}