{
  "type": "Feature",
  "properties": {
    "date:inception_lower":"1980-01-01",
    "date:inception_upper":"1980-01-31",
    "iso:country":"GB",
    "wof:name":"SN4 9AD",
    "wof:placetype":"postalcode"
},
  "geometry": {"coordinates":[-1.785091,51.53525],"type":"Point"}
}