{
  "type": "Feature",
  "properties": {
    "iso:country": "GB",
    "wof:name": "SN4 9AD",
    "wof:placetype": "postalcode"
  },
  "geometry": {"coordinates":[-1.785091,51.53525],"type":"Point"}
}
