{
  "type": "Feature",
  "properties": {
    "iso:country":"GB",
    "wof:name":"CF31 2NS",
    "wof:placetype":"postalcode"
},
  "geometry": {"coordinates":[-3.54680082785538,51.51415798097439],"type":"Point"}
}