{
  "type": "Feature",
  "properties": {
    "iso:country":"GB",
    "wof:name":"WF9 1DJ",
    "wof:placetype":"postalcode"
},
  "geometry": {"coordinates":[-1.28915361676644,53.61415504852469],"type":"Point"}
}