{
  "type": "Feature",
  "properties": {
    "iso:country": "GB",
    "wof:name": "LN2 4EL",
    "wof:placetype": "postalcode"
  },
  "geometry": {"coordinates":[-0.519714,53.2452],"type":"Point"}
}
