{
  "type": "Feature",
  "properties": {
    "iso:country":"GB",
    "wof:name":"SK8 2LW",
    "wof:placetype":"postalcode"
},
  "geometry": {"coordinates":[-2.1932640349752,53.38941107978716],"type":"Point"}
}