{
  "type": "Feature",
  "properties": {
    "date:inception_lower": "1995-01-01",
    "date:inception_upper": "1995-01-01",
    "iso:country": "GB",
    "wof:name": "DE21 4SR",
    "wof:placetype": "postalcode"
  },
  "geometry": {"coordinates":[-1.456749,52.936985],"type":"Point"}
}
