{
  "type": "Feature",
  "properties": {
    "iso:country":"GB",
    "wof:name":"BN25 1NG",
    "wof:placetype":"postalcode"
},
  "geometry": {"coordinates":[0.10204125757102,50.77268170187347],"type":"Point"}
}