{
  "type": "Feature",
  "properties": {
    "iso:country":"GB",
    "wof:name":"GL50 2ST",
    "wof:placetype":"postalcode"
},
  "geometry": {"coordinates":[-2.09002964827417,51.88359339188952],"type":"Point"}
}