{
  "type": "Feature",
  "properties": {
    "iso:country":"GB",
    "wof:name":"CA9 3AP",
    "wof:placetype":"postalcode"
},
  "geometry": {"coordinates":[-2.45205714627245,54.8095772522992],"type":"Point"}
}