{
  "type": "Feature",
  "properties": {
    "date:inception_lower": "1999-06-01",
    "date:inception_upper": "1999-06-01",
    "iso:country": "GB",
    "wof:name": "CF14 6SS",
    "wof:placetype": "postalcode"
  },
  "geometry": {"coordinates":[-3.20918,51.530426],"type":"Point"}
}
