{
  "type": "Feature",
  "properties": {
    "iso:country":"GB",
    "wof:name":"CF14 6SS",
    "wof:placetype":"postalcode"
},
  "geometry": {"coordinates":[-3.20917977087211,51.53042610347221],"type":"Point"}
}