{
  "type": "Feature",
  "properties": {
    "iso:country":"GB",
    "wof:name":"HD5 0RJ",
    "wof:placetype":"postalcode"
},
  "geometry": {"coordinates":[-1.73687864469243,53.68122115222784],"type":"Point"}
}