{
  "type": "Feature",
  "properties": {
    "iso:country": "GB",
    "wof:name": "HD5 0RJ",
    "wof:placetype": "postalcode"
  },
  "geometry": {"coordinates":[-1.736879,53.681221],"type":"Point"}
}
