{
  "type": "Feature",
  "properties": {
    "date:inception_lower": "1980-01-01",
    "date:inception_upper": "1980-01-01",
    "iso:country": "GB",
    "wof:name": "HD5 0RJ",
    "wof:placetype": "postalcode"
  },
  "geometry": {"coordinates":[-1.736879,53.681221],"type":"Point"}
}
