{
  "type": "Feature",
  "properties": {
    "iso:country":"GB",
    "wof:name":"WV13 3BZ",
    "wof:placetype":"postalcode"
},
  "geometry": {"coordinates":[-2.07133329371243,52.58547277765236],"type":"Point"}
}