{
  "type": "Feature",
  "properties": {
    "iso:country":"GB",
    "wof:name":"TR13 8TE",
    "wof:placetype":"postalcode"
},
  "geometry": {"coordinates":[-5.27490283324958,50.10261387727313],"type":"Point"}
}