{
  "type": "Feature",
  "properties": {
    "iso:country": "GB",
    "wof:name": "BS35 2AH",
    "wof:placetype": "postalcode"
  },
  "geometry": {"coordinates":[-2.526472,51.607625],"type":"Point"}
}
