{
  "type": "Feature",
  "properties": {
    "date:inception_lower": "1997-12-01",
    "date:inception_upper": "1997-12-01",
    "iso:country": "GB",
    "wof:name": "BS35 2AH",
    "wof:placetype": "postalcode"
  },
  "geometry": {"coordinates":[-2.526472,51.607625],"type":"Point"}
}
