{
  "type": "Feature",
  "properties": {
    "iso:country": "GB",
    "wof:name": "WS7 0BA",
    "wof:placetype": "postalcode"
  },
  "geometry": {"coordinates":[-1.913476,52.678111],"type":"Point"}
}
