{
  "type": "Feature",
  "properties": {
    "iso:country":"GB",
    "wof:name":"NR27 9NU",
    "wof:placetype":"postalcode"
},
  "geometry": {"coordinates":[1.27141096563562,52.93545023327241],"type":"Point"}
}