{
  "type": "Feature",
  "properties": {
    "date:inception_lower": "1991-09-01",
    "date:inception_upper": "1991-09-01",
    "iso:country": "GB",
    "wof:name": "HP20 1RQ",
    "wof:placetype": "postalcode"
  },
  "geometry": {"coordinates":[-0.802136,51.815178],"type":"Point"}
}
