{
  "type": "Feature",
  "properties": {
    "iso:country":"GB",
    "wof:name":"HP20 1RQ",
    "wof:placetype":"postalcode"
},
  "geometry": {"coordinates":[-0.8021362581953,51.81517827513866],"type":"Point"}
}