{
  "type": "Feature",
  "properties": {
    "iso:country":"GB",
    "wof:name":"SM4 6QQ",
    "wof:placetype":"postalcode"
},
  "geometry": {"coordinates":[-0.18952077936995,51.39119536891415],"type":"Point"}
}