{
  "type": "Feature",
  "properties": {
    "date:inception_lower": "2009-09-01",
    "date:inception_upper": "2009-09-01",
    "iso:country": "GB",
    "wof:name": "LS10 4GE",
    "wof:placetype": "postalcode"
  },
  "geometry": {"coordinates":[-1.526339,53.746412],"type":"Point"}
}
