{
  "type": "Feature",
  "properties": {
    "iso:country":"GB",
    "wof:name":"BB8 8NT",
    "wof:placetype":"postalcode"
},
  "geometry": {"coordinates":[-2.14271602387596,53.84668686730051],"type":"Point"}
}