{
  "type": "Feature",
  "properties": {
    "iso:country":"GB",
    "wof:name":"DE21 5BB",
    "wof:placetype":"postalcode"
},
  "geometry": {"coordinates":[-1.45051204812911,52.98886080641074],"type":"Point"}
}