{
  "type": "Feature",
  "properties": {
    "iso:country": "GB",
    "wof:name": "DE21 5BB",
    "wof:placetype": "postalcode"
  },
  "geometry": {"coordinates":[-1.450323,52.9885],"type":"Point"}
}
