{
  "type": "Feature",
  "properties": {
    "iso:country":"GB",
    "wof:name":"SE18 6FH",
    "wof:placetype":"postalcode"
},
  "geometry": {"coordinates":[0.06853855977215,51.49038642904983],"type":"Point"}
}