{
  "type": "Feature",
  "properties": {
    "iso:country": "GB",
    "wof:name": "SE18 6FH",
    "wof:placetype": "postalcode"
  },
  "geometry": {"coordinates":[0.068593,51.490359],"type":"Point"}
}
