{
  "type": "Feature",
  "properties": {
    "iso:country": "GB",
    "wof:name": "YO42 2PN",
    "wof:placetype": "postalcode"
  },
  "geometry": {"coordinates":[-0.781326,53.922777],"type":"Point"}
}
