{
  "type": "Feature",
  "properties": {
    "date:inception_lower": "1980-01-01",
    "date:inception_upper": "1980-01-01",
    "iso:country": "GB",
    "wof:name": "SN14 7NF",
    "wof:placetype": "postalcode"
  },
  "geometry": {"coordinates":[-2.233208,51.512519],"type":"Point"}
}
