{
  "type": "Feature",
  "properties": {
    "iso:country": "GB",
    "wof:name": "DL14 8AW",
    "wof:placetype": "postalcode"
  },
  "geometry": {"coordinates":[-1.638443,54.679172],"type":"Point"}
}
