{
  "type": "Feature",
  "properties": {
    "date:inception_lower":"1980-01-01",
    "date:inception_upper":"1980-01-31",
    "iso:country":"GB",
    "wof:name":"DA14 4RQ",
    "wof:placetype":"postalcode"
},
  "geometry": {"coordinates":[0.122349,51.431268],"type":"Point"}
}