{
  "type": "Feature",
  "properties": {
    "iso:country": "GB",
    "wof:name": "SA15 1BA",
    "wof:placetype": "postalcode"
  },
  "geometry": {"coordinates":[-4.158263,51.675018],"type":"Point"}
}
