{
  "type": "Feature",
  "properties": {
    "iso:country":"GB",
    "wof:name":"SA15 1BA",
    "wof:placetype":"postalcode"
},
  "geometry": {"coordinates":[-4.15812614176647,51.67487665772266],"type":"Point"}
}