{
  "type": "Feature",
  "properties": {
    "iso:country":"GB",
    "wof:name":"NR2 2RF",
    "wof:placetype":"postalcode"
},
  "geometry": {"coordinates":[1.28123889476634,52.62699139667903],"type":"Point"}
}