{
  "type": "Feature",
  "properties": {
    "iso:country":"GB",
    "wof:name":"RM6 4QJ",
    "wof:placetype":"postalcode"
},
  "geometry": {"coordinates":[0.11646775268566,51.56846988580727],"type":"Point"}
}