{
  "type": "Feature",
  "properties": {
    "iso:country": "GB",
    "wof:name": "LE1 1RA",
    "wof:placetype": "postalcode"
  },
  "geometry": {"coordinates":[-1.129957,52.63375],"type":"Point"}
}
