{
  "type": "Feature",
  "properties": {
    "iso:country":"GB",
    "wof:name":"LE1 1RA",
    "wof:placetype":"postalcode"
},
  "geometry": {"coordinates":[-1.12995745196525,52.63375041938128],"type":"Point"}
}