{
  "type": "Feature",
  "properties": {
    "iso:country":"GB",
    "wof:name":"PL6 6BR",
    "wof:placetype":"postalcode"
},
  "geometry": {"coordinates":[-4.11919738838525,50.42700801774478],"type":"Point"}
}