{
  "type": "Feature",
  "properties": {
    "iso:country":"GB",
    "wof:name":"TR4 9HW",
    "wof:placetype":"postalcode"
},
  "geometry": {"coordinates":[-5.07832309738493,50.32357319112037],"type":"Point"}
}