{
  "type": "Feature",
  "properties": {
    "date:inception_lower": "1994-05-01",
    "date:inception_upper": "1994-05-01",
    "iso:country": "GB",
    "wof:name": "M26 4HN",
    "wof:placetype": "postalcode"
  },
  "geometry": {"coordinates":[-2.339543,53.575191],"type":"Point"}
}
