{
  "type": "Feature",
  "properties": {
    "iso:country":"GB",
    "wof:name":"M26 4HN",
    "wof:placetype":"postalcode"
},
  "geometry": {"coordinates":[-2.33954263887432,53.57519083045131],"type":"Point"}
}