{
  "type": "Feature",
  "properties": {
    "iso:country":"GB",
    "wof:name":"W4 1ZP",
    "wof:placetype":"postalcode"
},
  "geometry": {"coordinates":[-0.26258663623129,51.4915334330266],"type":"Point"}
}