{
  "type": "Feature",
  "properties": {
    "iso:country":"GB",
    "wof:name":"BN2 6DH",
    "wof:placetype":"postalcode"
},
  "geometry": {"coordinates":[-0.08982155772063,50.8345032932616],"type":"Point"}
}