{
  "type": "Feature",
  "properties": {
    "iso:country": "GB",
    "wof:name": "M20 2SN",
    "wof:placetype": "postalcode"
  },
  "geometry": {"coordinates":[-2.223765,53.41109],"type":"Point"}
}
