{
  "type": "Feature",
  "properties": {
    "iso:country":"GB",
    "wof:name":"BN6 9AN",
    "wof:placetype":"postalcode"
},
  "geometry": {"coordinates":[-0.16625947674149,50.92964729661288],"type":"Point"}
}