{
  "type": "Feature",
  "properties": {
    "iso:country":"GB",
    "wof:name":"CH42 4RA",
    "wof:placetype":"postalcode"
},
  "geometry": {"coordinates":[-3.0185095722199,53.36960744553327],"type":"Point"}
}