{
  "type": "Feature",
  "properties": {
    "date:inception_lower": "1985-10-01",
    "date:inception_upper": "1985-10-01",
    "iso:country": "GB",
    "wof:name": "GL2 9DW",
    "wof:placetype": "postalcode"
  },
  "geometry": {"coordinates":[-2.237795,51.880151],"type":"Point"}
}
