{
  "type": "Feature",
  "properties": {
    "iso:country":"GB",
    "wof:name":"GL2 9DW",
    "wof:placetype":"postalcode"
},
  "geometry": {"coordinates":[-2.23779495612905,51.88015051918466],"type":"Point"}
}