{
  "type": "Feature",
  "properties": {
    "date:inception_lower": "1980-01-01",
    "date:inception_upper": "1980-01-01",
    "iso:country": "GB",
    "wof:name": "SY3 7PL",
    "wof:placetype": "postalcode"
  },
  "geometry": {"coordinates":[-2.741047,52.700843],"type":"Point"}
}
