{
  "type": "Feature",
  "properties": {
    "date:inception_lower": "1980-01-01",
    "date:inception_upper": "1980-01-01",
    "iso:country": "GB",
    "wof:name": "TA3 5JB",
    "wof:placetype": "postalcode"
  },
  "geometry": {"coordinates":[-3.043201,51.014531],"type":"Point"}
}
