{
  "type": "Feature",
  "properties": {
    "iso:country":"GB",
    "wof:name":"YO24 3NF",
    "wof:placetype":"postalcode"
},
  "geometry": {"coordinates":[-1.13590118852061,53.94099505531553],"type":"Point"}
}