{
  "type": "Feature",
  "properties": {
    "iso:country": "GB",
    "wof:name": "LE17 4DL",
    "wof:placetype": "postalcode"
  },
  "geometry": {"coordinates":[-1.195395,52.456578],"type":"Point"}
}
