{
  "type": "Feature",
  "properties": {
    "iso:country": "GB",
    "wof:name": "AL7 4EJ",
    "wof:placetype": "postalcode"
  },
  "geometry": {"coordinates":[-0.203836,51.785037],"type":"Point"}
}
