{
  "type": "Feature",
  "properties": {
    "iso:country":"GB",
    "wof:name":"AL7 4EJ",
    "wof:placetype":"postalcode"
},
  "geometry": {"coordinates":[-0.20383647106025,51.785036989708],"type":"Point"}
}