{
  "type": "Feature",
  "properties": {
    "iso:country":"GB",
    "wof:name":"GL52 8XS",
    "wof:placetype":"postalcode"
},
  "geometry": {"coordinates":[-2.06716200199948,51.95162428390468],"type":"Point"}
}