{
  "type": "Feature",
  "properties": {
    "iso:country": "GB",
    "wof:name": "CF71 7NL",
    "wof:placetype": "postalcode"
  },
  "geometry": {"coordinates":[-3.526364,51.471425],"type":"Point"}
}
