{
  "type": "Feature",
  "properties": {
    "date:inception_lower": "1995-07-01",
    "date:inception_upper": "1995-07-01",
    "iso:country": "GB",
    "wof:name": "CF71 7NL",
    "wof:placetype": "postalcode"
  },
  "geometry": {"coordinates":[-3.526364,51.471425],"type":"Point"}
}
