{
  "type": "Feature",
  "properties": {
    "iso:country":"GB",
    "wof:name":"CF71 7NL",
    "wof:placetype":"postalcode"
},
  "geometry": {"coordinates":[-3.52658253328538,51.47108956677073],"type":"Point"}
}