{
  "type": "Feature",
  "properties": {
    "iso:country": "GB",
    "wof:name": "NG9 3RW",
    "wof:placetype": "postalcode"
  },
  "geometry": {"coordinates":[-1.276588,52.943567],"type":"Point"}
}
