{
  "type": "Feature",
  "properties": {
    "iso:country": "GB",
    "wof:name": "CB2 0AT",
    "wof:placetype": "postalcode"
  },
  "geometry": {"coordinates":[0.13631,52.173207],"type":"Point"}
}
