{
  "type": "Feature",
  "properties": {
    "date:inception_lower": "1996-06-01",
    "date:inception_upper": "1996-06-01",
    "iso:country": "GB",
    "wof:name": "DY10 2YZ",
    "wof:placetype": "postalcode"
  },
  "geometry": {"coordinates":[-2.234749,52.402945],"type":"Point"}
}
