{
  "type": "Feature",
  "properties": {
    "iso:country": "GB",
    "wof:name": "DY10 2YZ",
    "wof:placetype": "postalcode"
  },
  "geometry": {"coordinates":[-2.234749,52.402945],"type":"Point"}
}
