{
  "type": "Feature",
  "properties": {
    "iso:country": "GB",
    "wof:name": "CF40 9YF",
    "wof:placetype": "postalcode"
  },
  "geometry": {"coordinates":[-3.473071,51.623974],"type":"Point"}
}
