{
  "type": "Feature",
  "properties": {
    "iso:country":"GB",
    "wof:name":"GL10 3TJ",
    "wof:placetype":"postalcode"
},
  "geometry": {"coordinates":[-2.33170756798592,51.72915247881981],"type":"Point"}
}