{
  "type": "Feature",
  "properties": {
    "iso:country":"GB",
    "wof:name":"PO37 7AA",
    "wof:placetype":"postalcode"
},
  "geometry": {"coordinates":[-1.17850920169361,50.63041912121098],"type":"Point"}
}