{
  "type": "Feature",
  "properties": {
    "iso:country": "GB",
    "wof:name": "LS29 6QJ",
    "wof:placetype": "postalcode"
  },
  "geometry": {"coordinates":[-1.743135,53.889577],"type":"Point"}
}
