{
  "type": "Feature",
  "properties": {
    "iso:country":"GB",
    "wof:name":"BN16 4LF",
    "wof:placetype":"postalcode"
},
  "geometry": {"coordinates":[-0.48538908181477,50.83286220847543],"type":"Point"}
}