{
  "type": "Feature",
  "properties": {
    "iso:country": "GB",
    "wof:name": "BN16 4LF",
    "wof:placetype": "postalcode"
  },
  "geometry": {"coordinates":[-0.485389,50.832862],"type":"Point"}
}
