{
  "type": "Feature",
  "properties": {
    "iso:country": "GB",
    "wof:name": "PO16 8AQ",
    "wof:placetype": "postalcode"
  },
  "geometry": {"coordinates":[-1.155865,50.847704],"type":"Point"}
}
