{
  "type": "Feature",
  "properties": {
    "iso:country":"GB",
    "wof:name":"HD5 0DP",
    "wof:placetype":"postalcode"
},
  "geometry": {"coordinates":[-1.72731572241513,53.65691372226728],"type":"Point"}
}