{
  "type": "Feature",
  "properties": {
    "iso:country":"GB",
    "wof:name":"BR1 2NS",
    "wof:placetype":"postalcode"
},
  "geometry": {"coordinates":[0.04657181313351,51.40544802049249],"type":"Point"}
}