{
  "type": "Feature",
  "properties": {
    "iso:country":"GB",
    "wof:name":"WF6 1LG",
    "wof:placetype":"postalcode"
},
  "geometry": {"coordinates":[-1.41450655012719,53.68876251957631],"type":"Point"}
}