{
  "type": "Feature",
  "properties": {
    "iso:country":"GB",
    "wof:name":"NE6 2QG",
    "wof:placetype":"postalcode"
},
  "geometry": {"coordinates":[-1.57228576725462,54.97358828939967],"type":"Point"}
}