{
  "type": "Feature",
  "properties": {
    "iso:country": "GB",
    "wof:name": "NE6 2QG",
    "wof:placetype": "postalcode"
  },
  "geometry": {"coordinates":[-1.572286,54.973588],"type":"Point"}
}
