{
  "type": "Feature",
  "properties": {
    "iso:country":"GB",
    "wof:name":"GL7 5SR",
    "wof:placetype":"postalcode"
},
  "geometry": {"coordinates":[-1.8591558971027,51.71642820448552],"type":"Point"}
}