{
  "type": "Feature",
  "properties": {
    "date:inception_lower": "2006-10-01",
    "date:inception_upper": "2006-10-01",
    "iso:country": "GB",
    "wof:name": "CA12 5JQ",
    "wof:placetype": "postalcode"
  },
  "geometry": {"coordinates":[-3.137546,54.602622],"type":"Point"}
}
