{
  "type": "Feature",
  "properties": {
    "iso:country": "GB",
    "wof:name": "CA12 5JQ",
    "wof:placetype": "postalcode"
  },
  "geometry": {"coordinates":[-3.137542,54.602597],"type":"Point"}
}
