{
  "type": "Feature",
  "properties": {
    "iso:country":"GB",
    "wof:name":"CA12 5JQ",
    "wof:placetype":"postalcode"
},
  "geometry": {"coordinates":[-3.13754166761582,54.60259661127431],"type":"Point"}
}