{
  "type": "Feature",
  "properties": {
    "iso:country":"GB",
    "wof:name":"DN12 2BA",
    "wof:placetype":"postalcode"
},
  "geometry": {"coordinates":[-1.25628508895743,53.46981478437323],"type":"Point"}
}