{
  "type": "Feature",
  "properties": {
    "date:inception_lower": "2004-11-01",
    "date:inception_upper": "2004-11-01",
    "iso:country": "GB",
    "wof:name": "PE29 6JN",
    "wof:placetype": "postalcode"
  },
  "geometry": {"coordinates":[-0.210332,52.333556],"type":"Point"}
}
