{
  "type": "Feature",
  "properties": {
    "iso:country":"GB",
    "wof:name":"PE29 6JN",
    "wof:placetype":"postalcode"
},
  "geometry": {"coordinates":[-0.21033186212994,52.33355592402123],"type":"Point"}
}