{
  "type": "Feature",
  "properties": {
    "iso:country":"GB",
    "wof:name":"DN9 1LF",
    "wof:placetype":"postalcode"
},
  "geometry": {"coordinates":[-0.8839488049868,53.54749450286662],"type":"Point"}
}