{
  "type": "Feature",
  "properties": {
    "iso:country": "GB",
    "wof:name": "G11 6JA",
    "wof:placetype": "postalcode"
  },
  "geometry": {"coordinates":[-4.319761,55.870507],"type":"Point"}
}
