{
  "type": "Feature",
  "properties": {
    "iso:country":"GB",
    "wof:name":"M22 5LS",
    "wof:placetype":"postalcode"
},
  "geometry": {"coordinates":[-2.24040967542531,53.36943356142086],"type":"Point"}
}