{
  "type": "Feature",
  "properties": {
    "iso:country": "GB",
    "wof:name": "M22 5LS",
    "wof:placetype": "postalcode"
  },
  "geometry": {"coordinates":[-2.24041,53.369434],"type":"Point"}
}
