{
  "type": "Feature",
  "properties": {
    "iso:country": "GB",
    "wof:name": "CV32 5QA",
    "wof:placetype": "postalcode"
  },
  "geometry": {"coordinates":[-1.538117,52.293232],"type":"Point"}
}
