{
  "type": "Feature",
  "properties": {
    "iso:country":"GB",
    "wof:name":"L13 1BE",
    "wof:placetype":"postalcode"
},
  "geometry": {"coordinates":[-2.91812560366961,53.40868777245058],"type":"Point"}
}