{
  "type": "Feature",
  "properties": {
    "iso:country":"GB",
    "wof:name":"KA7 1DY",
    "wof:placetype":"postalcode"
},
  "geometry": {"coordinates":[-4.63873272511452,55.4630593836883],"type":"Point"}
}