{
  "type": "Feature",
  "properties": {
    "date:inception_lower": "1980-01-01",
    "date:inception_upper": "1980-01-01",
    "iso:country": "GB",
    "wof:name": "BR6 7QF",
    "wof:placetype": "postalcode"
  },
  "geometry": {"coordinates":[0.155448,51.367902],"type":"Point"}
}
