{
  "type": "Feature",
  "properties": {
    "iso:country":"GB",
    "wof:name":"BR6 7QF",
    "wof:placetype":"postalcode"
},
  "geometry": {"coordinates":[0.15542089632989,51.36790179404802],"type":"Point"}
}