{
  "type": "Feature",
  "properties": {
    "iso:country": "GB",
    "wof:name": "BR6 7QF",
    "wof:placetype": "postalcode"
  },
  "geometry": {"coordinates":[0.155448,51.367902],"type":"Point"}
}
