{
  "type": "Feature",
  "properties": {
    "date:inception_lower":"1980-01-01",
    "date:inception_upper":"1980-01-31",
    "iso:country":"GB",
    "wof:name":"BR6 7QF",
    "wof:placetype":"postalcode"
},
  "geometry": {"coordinates":[0.155466,51.367983],"type":"Point"}
}