{
  "type": "Feature",
  "properties": {
    "iso:country":"GB",
    "wof:name":"TN18 4EF",
    "wof:placetype":"postalcode"
},
  "geometry": {"coordinates":[0.51003353980125,51.0477656999282],"type":"Point"}
}