{
  "type": "Feature",
  "properties": {
    "date:inception_lower": "1991-01-01",
    "date:inception_upper": "1991-01-01",
    "iso:country": "GB",
    "wof:name": "BS28 4JW",
    "wof:placetype": "postalcode"
  },
  "geometry": {"coordinates":[-2.807307,51.26039],"type":"Point"}
}
