{
  "type": "Feature",
  "properties": {
    "iso:country":"GB",
    "wof:name":"BS28 4JW",
    "wof:placetype":"postalcode"
},
  "geometry": {"coordinates":[-2.80686196013893,51.25990304716053],"type":"Point"}
}