{
  "type": "Feature",
  "properties": {
    "iso:country": "GB",
    "wof:name": "CV7 7PT",
    "wof:placetype": "postalcode"
  },
  "geometry": {"coordinates":[-1.643384,52.434152],"type":"Point"}
}
