{
  "type": "Feature",
  "properties": {
    "iso:country":"GB",
    "wof:name":"CV7 7PT",
    "wof:placetype":"postalcode"
},
  "geometry": {"coordinates":[-1.6433843351428,52.43415177680983],"type":"Point"}
}