{
  "type": "Feature",
  "properties": {
    "date:inception_lower":"1997-06-01",
    "date:inception_upper":"1997-06-30",
    "iso:country":"GB",
    "wof:name":"CV7 7PT",
    "wof:placetype":"postalcode"
},
  "geometry": {"coordinates":[-1.643384,52.434152],"type":"Point"}
}