{
  "type": "Feature",
  "properties": {
    "iso:country": "GB",
    "wof:name": "LA22 9AZ",
    "wof:placetype": "postalcode"
  },
  "geometry": {"coordinates":[-2.965722,54.434184],"type":"Point"}
}
