{
  "type": "Feature",
  "properties": {
    "iso:country":"GB",
    "wof:name":"LA22 9AZ",
    "wof:placetype":"postalcode"
},
  "geometry": {"coordinates":[-2.96567293313175,54.43416732440583],"type":"Point"}
}