{
  "type": "Feature",
  "properties": {
    "date:inception_lower": "2021-04-01",
    "date:inception_upper": "2021-04-01",
    "iso:country": "GB",
    "wof:name": "TF2 2SN",
    "wof:placetype": "postalcode"
  },
  "geometry": {"coordinates":[-2.451015,52.675545],"type":"Point"}
}
