{
  "type": "Feature",
  "properties": {
    "iso:country":"GB",
    "wof:name":"ME4 6QS",
    "wof:placetype":"postalcode"
},
  "geometry": {"coordinates":[0.51714672737082,51.37183817231335],"type":"Point"}
}