{
  "type": "Feature",
  "properties": {
    "date:inception_lower": "1986-07-01",
    "date:inception_upper": "1986-07-01",
    "iso:country": "GB",
    "wof:name": "GU7 1TB",
    "wof:placetype": "postalcode"
  },
  "geometry": {"coordinates":[-0.616573,51.178456],"type":"Point"}
}
