{
  "type": "Feature",
  "properties": {
    "iso:country":"GB",
    "wof:name":"GU7 1TB",
    "wof:placetype":"postalcode"
},
  "geometry": {"coordinates":[-0.61657294726864,51.17845561617692],"type":"Point"}
}