{
  "type": "Feature",
  "properties": {
    "iso:country":"GB",
    "wof:name":"KY11 3DG",
    "wof:placetype":"postalcode"
},
  "geometry": {"coordinates":[-3.45655964647663,56.05794228442428],"type":"Point"}
}