{
  "type": "Feature",
  "properties": {
    "iso:country":"GB",
    "wof:name":"CM1 2RF",
    "wof:placetype":"postalcode"
},
  "geometry": {"coordinates":[0.45971864068316,51.73790562857594],"type":"Point"}
}