{
  "type": "Feature",
  "properties": {
    "date:inception_lower": "2016-10-01",
    "date:inception_upper": "2016-10-01",
    "iso:country": "GB",
    "wof:name": "GU22 9FE",
    "wof:placetype": "postalcode"
  },
  "geometry": {"coordinates":[-0.56192,51.306055],"type":"Point"}
}
