{
  "type": "Feature",
  "properties": {
    "date:inception_lower":"1980-01-01",
    "date:inception_upper":"1980-01-31",
    "iso:country":"GB",
    "wof:name":"ML6 6JQ",
    "wof:placetype":"postalcode"
},
  "geometry": {"coordinates":[-3.982028,55.868269],"type":"Point"}
}