{
  "type": "Feature",
  "properties": {
    "iso:country": "GB",
    "wof:name": "ML6 6JQ",
    "wof:placetype": "postalcode"
  },
  "geometry": {"coordinates":[-3.982028,55.868269],"type":"Point"}
}
