{
  "type": "Feature",
  "properties": {
    "iso:country":"GB",
    "wof:name":"DE6 2BQ",
    "wof:placetype":"postalcode"
},
  "geometry": {"coordinates":[-1.76455498214587,53.03151651585241],"type":"Point"}
}