{
  "type": "Feature",
  "properties": {
    "date:inception_lower": "1990-02-01",
    "date:inception_upper": "1990-02-01",
    "iso:country": "GB",
    "wof:name": "SW5 0QQ",
    "wof:placetype": "postalcode"
  },
  "geometry": {"coordinates":[-0.191824,51.493845],"type":"Point"}
}
