{
  "type": "Feature",
  "properties": {
    "iso:country": "GB",
    "wof:name": "DY1 2JR",
    "wof:placetype": "postalcode"
  },
  "geometry": {"coordinates":[-2.106123,52.509201],"type":"Point"}
}
