{
  "type": "Feature",
  "properties": {
    "iso:country": "GB",
    "wof:name": "WR10 3DG",
    "wof:placetype": "postalcode"
  },
  "geometry": {"coordinates":[-2.108293,52.070801],"type":"Point"}
}
