{
  "type": "Feature",
  "properties": {
    "date:inception_lower": "2020-02-01",
    "date:inception_upper": "2020-02-01",
    "iso:country": "GB",
    "wof:name": "EX20 1GS",
    "wof:placetype": "postalcode"
  },
  "geometry": {"coordinates":[-4.001618,50.738592],"type":"Point"}
}
