{
  "type": "Feature",
  "properties": {
    "date:inception_lower": "1980-01-01",
    "date:inception_upper": "1980-01-01",
    "iso:country": "GB",
    "wof:name": "WA16 8HB",
    "wof:placetype": "postalcode"
  },
  "geometry": {"coordinates":[-2.359909,53.314535],"type":"Point"}
}
