{
  "type": "Feature",
  "properties": {
    "iso:country":"GB",
    "wof:name":"BR2 9QG",
    "wof:placetype":"postalcode"
},
  "geometry": {"coordinates":[0.03598587374521,51.39177441677077],"type":"Point"}
}