{
  "type": "Feature",
  "properties": {
    "date:inception_lower": "1980-01-01",
    "date:inception_upper": "1980-01-01",
    "iso:country": "GB",
    "wof:name": "DD10 8LU",
    "wof:placetype": "postalcode"
  },
  "geometry": {"coordinates":[-2.467555,56.713245],"type":"Point"}
}
