{
  "type": "Feature",
  "properties": {
    "date:inception_lower": "2017-07-01",
    "date:inception_upper": "2017-07-01",
    "iso:country": "GB",
    "wof:name": "WC1A 1NU",
    "wof:placetype": "postalcode"
  },
  "geometry": {"coordinates":[-0.123523,51.517135],"type":"Point"}
}
