{
  "type": "Feature",
  "properties": {
    "iso:country": "GB",
    "wof:name": "CM7 3NU",
    "wof:placetype": "postalcode"
  },
  "geometry": {"coordinates":[0.574234,51.877354],"type":"Point"}
}
