{
  "type": "Feature",
  "properties": {
    "iso:country":"GB",
    "wof:name":"CM7 3NU",
    "wof:placetype":"postalcode"
},
  "geometry": {"coordinates":[0.57423434421277,51.87735439413669],"type":"Point"}
}