{
  "type": "Feature",
  "properties": {
    "iso:country":"GB",
    "wof:name":"WA4 5LN",
    "wof:placetype":"postalcode"
},
  "geometry": {"coordinates":[-2.61019551204212,53.35538718164747],"type":"Point"}
}