{
  "type": "Feature",
  "properties": {
    "iso:country": "GB",
    "wof:name": "CF64 5RH",
    "wof:placetype": "postalcode"
  },
  "geometry": {"coordinates":[-3.178547,51.42662],"type":"Point"}
}
