{
  "type": "Feature",
  "properties": {
    "iso:country":"GB",
    "wof:name":"CF64 5RH",
    "wof:placetype":"postalcode"
},
  "geometry": {"coordinates":[-3.1785469510586,51.42662045450302],"type":"Point"}
}