{
  "type": "Feature",
  "properties": {
    "date:inception_lower": "1980-01-01",
    "date:inception_upper": "1980-01-01",
    "iso:country": "GB",
    "wof:name": "SG11 2LG",
    "wof:placetype": "postalcode"
  },
  "geometry": {"coordinates":[0.094944,51.90745],"type":"Point"}
}
