{
  "type": "Feature",
  "properties": {
    "iso:country":"GB",
    "wof:name":"N10 1QB",
    "wof:placetype":"postalcode"
},
  "geometry": {"coordinates":[-0.1457200016183,51.595081445247],"type":"Point"}
}