{
  "type": "Feature",
  "properties": {
    "iso:country": "GB",
    "wof:name": "B64 7EW",
    "wof:placetype": "postalcode"
  },
  "geometry": {"coordinates":[-2.074236,52.469636],"type":"Point"}
}
