{
  "type": "Feature",
  "properties": {
    "iso:country": "GB",
    "wof:name": "NG10 3BG",
    "wof:placetype": "postalcode"
  },
  "geometry": {"coordinates":[-1.298546,52.880449],"type":"Point"}
}
