{
  "type": "Feature",
  "properties": {
    "date:inception_lower": "2002-12-01",
    "date:inception_upper": "2002-12-01",
    "iso:country": "GB",
    "wof:name": "SN7 8FB",
    "wof:placetype": "postalcode"
  },
  "geometry": {"coordinates":[-1.510288,51.63672],"type":"Point"}
}
