{
  "type": "Feature",
  "properties": {
    "iso:country": "GB",
    "wof:name": "SN7 8FB",
    "wof:placetype": "postalcode"
  },
  "geometry": {"coordinates":[-1.510288,51.63672],"type":"Point"}
}
