{
  "type": "Feature",
  "properties": {
    "iso:country":"GB",
    "wof:name":"SN7 8FB",
    "wof:placetype":"postalcode"
},
  "geometry": {"coordinates":[-1.51028847477537,51.63672048496081],"type":"Point"}
}