{
  "type": "Feature",
  "properties": {
    "iso:country":"GB",
    "wof:name":"SW9 0PS",
    "wof:placetype":"postalcode"
},
  "geometry": {"coordinates":[-0.11743031764199,51.47500381340917],"type":"Point"}
}