{
  "type": "Feature",
  "properties": {
    "iso:country": "GB",
    "wof:name": "SW9 0PS",
    "wof:placetype": "postalcode"
  },
  "geometry": {"coordinates":[-0.11743,51.475004],"type":"Point"}
}
