{
  "type": "Feature",
  "properties": {
    "date:inception_lower":"2011-10-01",
    "date:inception_upper":"2011-10-31",
    "iso:country":"GB",
    "wof:name":"LL11 2AR",
    "wof:placetype":"postalcode"
},
  "geometry": {"coordinates":[-3.003876,53.050281],"type":"Point"}
}