{
  "type": "Feature",
  "properties": {
    "iso:country":"GB",
    "wof:name":"LL11 2AR",
    "wof:placetype":"postalcode"
},
  "geometry": {"coordinates":[-3.00387635274708,53.05028102338083],"type":"Point"}
}