{
  "type": "Feature",
  "properties": {
    "iso:country": "GB",
    "wof:name": "LL11 2AR",
    "wof:placetype": "postalcode"
  },
  "geometry": {"coordinates":[-3.003876,53.050281],"type":"Point"}
}
