{
  "type": "Feature",
  "properties": {
    "date:inception_lower": "2022-02-01",
    "date:inception_upper": "2022-02-01",
    "iso:country": "GB",
    "wof:name": "SY6 6FD",
    "wof:placetype": "postalcode"
  },
  "geometry": {"coordinates":[-2.805611,52.53824],"type":"Point"}
}
