{
  "type": "Feature",
  "properties": {
    "iso:country":"GB",
    "wof:name":"BA4 6UA",
    "wof:placetype":"postalcode"
},
  "geometry": {"coordinates":[-2.58955315574013,51.13400727558727],"type":"Point"}
}