{
  "type": "Feature",
  "properties": {
    "iso:country": "GB",
    "wof:name": "BA4 6UA",
    "wof:placetype": "postalcode"
  },
  "geometry": {"coordinates":[-2.589553,51.134007],"type":"Point"}
}
