{
  "type": "Feature",
  "properties": {
    "iso:country": "GB",
    "wof:name": "YO19 6HP",
    "wof:placetype": "postalcode"
  },
  "geometry": {"coordinates":[-1.105683,53.861579],"type":"Point"}
}
