{
  "type": "Feature",
  "properties": {
    "date:inception_lower": "1998-06-01",
    "date:inception_upper": "1998-06-01",
    "iso:country": "GB",
    "wof:name": "YO19 6HP",
    "wof:placetype": "postalcode"
  },
  "geometry": {"coordinates":[-1.105683,53.861579],"type":"Point"}
}
