{
  "type": "Feature",
  "properties": {
    "iso:country":"GB",
    "wof:name":"YO19 6HP",
    "wof:placetype":"postalcode"
},
  "geometry": {"coordinates":[-1.10568278552926,53.86157949777964],"type":"Point"}
}