{
  "type": "Feature",
  "properties": {
    "iso:country":"GB",
    "wof:name":"DN15 8HW",
    "wof:placetype":"postalcode"
},
  "geometry": {"coordinates":[-0.66727442317526,53.59502171932924],"type":"Point"}
}