{
  "type": "Feature",
  "properties": {
    "iso:country": "GB",
    "wof:name": "DN15 8HW",
    "wof:placetype": "postalcode"
  },
  "geometry": {"coordinates":[-0.667274,53.595022],"type":"Point"}
}
