{
  "type": "Feature",
  "properties": {
    "iso:country": "GB",
    "wof:name": "HX7 5QZ",
    "wof:placetype": "postalcode"
  },
  "geometry": {"coordinates":[-1.973613,53.740325],"type":"Point"}
}
