{
  "type": "Feature",
  "properties": {
    "iso:country": "GB",
    "wof:name": "HP17 8TU",
    "wof:placetype": "postalcode"
  },
  "geometry": {"coordinates":[-0.905737,51.789196],"type":"Point"}
}
