{
  "type": "Feature",
  "properties": {
    "iso:country":"GB",
    "wof:name":"RG40 4HR",
    "wof:placetype":"postalcode"
},
  "geometry": {"coordinates":[-0.86727310343033,51.3740335963295],"type":"Point"}
}