{
  "type": "Feature",
  "properties": {
    "date:inception_lower": "1980-01-01",
    "date:inception_upper": "1980-01-01",
    "iso:country": "GB",
    "wof:name": "YO13 0SA",
    "wof:placetype": "postalcode"
  },
  "geometry": {"coordinates":[-0.452478,54.298151],"type":"Point"}
}
