{
  "type": "Feature",
  "properties": {
    "iso:country":"GB",
    "wof:name":"YO23 3ST",
    "wof:placetype":"postalcode"
},
  "geometry": {"coordinates":[-1.14172955466225,53.91382994678631],"type":"Point"}
}