{
  "type": "Feature",
  "properties": {
    "iso:country":"GB",
    "wof:name":"SA37 0LQ",
    "wof:placetype":"postalcode"
},
  "geometry": {"coordinates":[-4.54088540151706,52.02202637863154],"type":"Point"}
}