{
  "type": "Feature",
  "properties": {
    "date:inception_lower":"1980-01-01",
    "date:inception_upper":"1980-01-31",
    "iso:country":"GB",
    "wof:name":"SA37 0LQ",
    "wof:placetype":"postalcode"
},
  "geometry": {"coordinates":[-4.540885,52.022026],"type":"Point"}
}