{
  "type": "Feature",
  "properties": {
    "iso:country": "GB",
    "wof:name": "CH64 4DY",
    "wof:placetype": "postalcode"
  },
  "geometry": {"coordinates":[-3.047522,53.284005],"type":"Point"}
}
