{
  "type": "Feature",
  "properties": {
    "iso:country":"GB",
    "wof:name":"G72 7GE",
    "wof:placetype":"postalcode"
},
  "geometry": {"coordinates":[-4.14963319233436,55.81430859691307],"type":"Point"}
}