{
  "type": "Feature",
  "properties": {
    "iso:country":"GB",
    "wof:name":"PE29 3QA",
    "wof:placetype":"postalcode"
},
  "geometry": {"coordinates":[-0.18150425264331,52.330013671057],"type":"Point"}
}