{
  "type": "Feature",
  "properties": {
    "iso:country":"GB",
    "wof:name":"SR3 2EA",
    "wof:placetype":"postalcode"
},
  "geometry": {"coordinates":[-1.39950562013621,54.87184182711808],"type":"Point"}
}