{
  "type": "Feature",
  "properties": {
    "date:inception_lower": "1980-01-01",
    "date:inception_upper": "1980-01-01",
    "iso:country": "GB",
    "wof:name": "HD2 1NT",
    "wof:placetype": "postalcode"
  },
  "geometry": {"coordinates":[-1.773261,53.672478],"type":"Point"}
}
