{
  "type": "Feature",
  "properties": {
    "date:inception_lower": "2021-01-01",
    "date:inception_upper": "2021-01-01",
    "iso:country": "GB",
    "wof:name": "TF9 2FE",
    "wof:placetype": "postalcode"
  },
  "geometry": {"coordinates":[-2.48252,52.902093],"type":"Point"}
}
