{
  "type": "Feature",
  "properties": {
    "iso:country":"GB",
    "wof:name":"EC2V 6AU",
    "wof:placetype":"postalcode"
},
  "geometry": {"coordinates":[-0.09396158858875,51.51394923061368],"type":"Point"}
}