{
  "type": "Feature",
  "properties": {
    "iso:country": "GB",
    "wof:name": "EC2V 6AU",
    "wof:placetype": "postalcode"
  },
  "geometry": {"coordinates":[-0.093593,51.513864],"type":"Point"}
}
