{
  "type": "Feature",
  "properties": {
    "iso:country":"GB",
    "wof:name":"GL52 8AB",
    "wof:placetype":"postalcode"
},
  "geometry": {"coordinates":[-2.05591720899422,51.94212693534772],"type":"Point"}
}