{
  "type": "Feature",
  "properties": {
    "date:inception_lower":"2000-10-01",
    "date:inception_upper":"2000-10-31",
    "iso:country":"GB",
    "wof:name":"GL52 8AB",
    "wof:placetype":"postalcode"
},
  "geometry": {"coordinates":[-2.055917,51.942127],"type":"Point"}
}