{
  "type": "Feature",
  "properties": {
    "iso:country": "GB",
    "wof:name": "LL18 2RD",
    "wof:placetype": "postalcode"
  },
  "geometry": {"coordinates":[-3.470154,53.30954],"type":"Point"}
}
