{
  "type": "Feature",
  "properties": {
    "iso:country":"GB",
    "wof:name":"LL18 2RD",
    "wof:placetype":"postalcode"
},
  "geometry": {"coordinates":[-3.4701544373045,53.30954045736792],"type":"Point"}
}