{
  "type": "Feature",
  "properties": {
    "iso:country": "GB",
    "wof:name": "EX34 8FP",
    "wof:placetype": "postalcode"
  },
  "geometry": {"coordinates":[-4.123696,51.176422],"type":"Point"}
}
