{
  "type": "Feature",
  "properties": {
    "iso:country":"GB",
    "wof:name":"PL14 5BL",
    "wof:placetype":"postalcode"
},
  "geometry": {"coordinates":[-4.44219757584566,50.5191548814494],"type":"Point"}
}