{
  "type": "Feature",
  "properties": {
    "iso:country": "GB",
    "wof:name": "HR2 0AF",
    "wof:placetype": "postalcode"
  },
  "geometry": {"coordinates":[-2.989511,51.958001],"type":"Point"}
}
