{
  "type": "Feature",
  "properties": {
    "iso:country": "GB",
    "wof:name": "SK9 1DL",
    "wof:placetype": "postalcode"
  },
  "geometry": {"coordinates":[-2.226143,53.329065],"type":"Point"}
}
