{
  "type": "Feature",
  "properties": {
    "iso:country": "GB",
    "wof:name": "RG24 8QZ",
    "wof:placetype": "postalcode"
  },
  "geometry": {"coordinates":[-1.069709,51.29085],"type":"Point"}
}
