{
  "type": "Feature",
  "properties": {
    "date:inception_lower":"1998-06-01",
    "date:inception_upper":"1998-06-30",
    "iso:country":"GB",
    "wof:name":"RG24 8QZ",
    "wof:placetype":"postalcode"
},
  "geometry": {"coordinates":[-1.069709,51.29085],"type":"Point"}
}