{
  "type": "Feature",
  "properties": {
    "date:inception_lower":"1980-01-01",
    "date:inception_upper":"1980-01-31",
    "iso:country":"GB",
    "wof:name":"L14 9PE",
    "wof:placetype":"postalcode"
},
  "geometry": {"coordinates":[-2.86481,53.423414],"type":"Point"}
}