{
  "type": "Feature",
  "properties": {
    "iso:country": "GB",
    "wof:name": "LN11 9QA",
    "wof:placetype": "postalcode"
  },
  "geometry": {"coordinates":[-0.006117,53.36651],"type":"Point"}
}
