{
  "type": "Feature",
  "properties": {
    "iso:country":"GB",
    "wof:name":"LN11 9QA",
    "wof:placetype":"postalcode"
},
  "geometry": {"coordinates":[-0.006116576441,53.36650958187012],"type":"Point"}
}