{
  "type": "Feature",
  "properties": {
    "iso:country":"GB",
    "wof:name":"AL5 2EX",
    "wof:placetype":"postalcode"
},
  "geometry": {"coordinates":[-0.36456699189227,51.82103929252913],"type":"Point"}
}