{
  "type": "Feature",
  "properties": {
    "iso:country":"GB",
    "wof:name":"BS4 1TX",
    "wof:placetype":"postalcode"
},
  "geometry": {"coordinates":[-2.5931282917646,51.42016579884279],"type":"Point"}
}