{
  "type": "Feature",
  "properties": {
    "date:inception_lower": "1980-01-01",
    "date:inception_upper": "1980-01-01",
    "iso:country": "GB",
    "wof:name": "BS4 1TX",
    "wof:placetype": "postalcode"
  },
  "geometry": {"coordinates":[-2.593128,51.420166],"type":"Point"}
}
