{
  "type": "Feature",
  "properties": {
    "iso:country": "GB",
    "wof:name": "BS4 1TX",
    "wof:placetype": "postalcode"
  },
  "geometry": {"coordinates":[-2.593128,51.420166],"type":"Point"}
}
