{
  "type": "Feature",
  "properties": {
    "date:inception_lower": "1993-08-01",
    "date:inception_upper": "1993-08-01",
    "iso:country": "GB",
    "wof:name": "NN3 8EZ",
    "wof:placetype": "postalcode"
  },
  "geometry": {"coordinates":[-0.835535,52.261154],"type":"Point"}
}
