{
  "type": "Feature",
  "properties": {
    "iso:country":"GB",
    "wof:name":"PE9 2XR",
    "wof:placetype":"postalcode"
},
  "geometry": {"coordinates":[-0.49605608506221,52.65583749561394],"type":"Point"}
}