{
  "type": "Feature",
  "properties": {
    "date:inception_lower": "1980-01-01",
    "date:inception_upper": "1980-01-01",
    "iso:country": "GB",
    "wof:name": "LN6 7AY",
    "wof:placetype": "postalcode"
  },
  "geometry": {"coordinates":[-0.553319,53.220194],"type":"Point"}
}
