{
  "type": "Feature",
  "properties": {
    "iso:country": "GB",
    "wof:name": "LN6 7AY",
    "wof:placetype": "postalcode"
  },
  "geometry": {"coordinates":[-0.553319,53.220194],"type":"Point"}
}
