{
  "type": "Feature",
  "properties": {
    "iso:country":"GB",
    "wof:name":"LN6 7AY",
    "wof:placetype":"postalcode"
},
  "geometry": {"coordinates":[-0.55341610556582,53.21994833527499],"type":"Point"}
}