{
  "type": "Feature",
  "properties": {
    "iso:country":"GB",
    "wof:name":"BN3 1DH",
    "wof:placetype":"postalcode"
},
  "geometry": {"coordinates":[-0.15597165667501,50.82626834793461],"type":"Point"}
}