{
  "type": "Feature",
  "properties": {
    "iso:country": "GB",
    "wof:name": "BN3 1DH",
    "wof:placetype": "postalcode"
  },
  "geometry": {"coordinates":[-0.155972,50.826268],"type":"Point"}
}
