{
  "type": "Feature",
  "properties": {
    "iso:country":"GB",
    "wof:name":"KT19 8JB",
    "wof:placetype":"postalcode"
},
  "geometry": {"coordinates":[-0.29911325059591,51.34015009982827],"type":"Point"}
}