{
  "type": "Feature",
  "properties": {
    "date:inception_lower": "2012-08-01",
    "date:inception_upper": "2012-08-01",
    "iso:country": "GB",
    "wof:name": "KT19 8JB",
    "wof:placetype": "postalcode"
  },
  "geometry": {"coordinates":[-0.299113,51.34015],"type":"Point"}
}
