{
  "type": "Feature",
  "properties": {
    "iso:country":"GB",
    "wof:name":"NE24 3TJ",
    "wof:placetype":"postalcode"
},
  "geometry": {"coordinates":[-1.50864605981458,55.1151772106941],"type":"Point"}
}