{
  "type": "Feature",
  "properties": {
    "date:inception_lower": "1980-01-01",
    "date:inception_upper": "1980-01-01",
    "iso:country": "GB",
    "wof:name": "NE24 3TJ",
    "wof:placetype": "postalcode"
  },
  "geometry": {"coordinates":[-1.508646,55.115177],"type":"Point"}
}
