{
  "type": "Feature",
  "properties": {
    "iso:country":"GB",
    "wof:name":"G69 9BE",
    "wof:placetype":"postalcode"
},
  "geometry": {"coordinates":[-4.11034968690836,55.90116689573631],"type":"Point"}
}