{
  "type": "Feature",
  "properties": {
    "date:inception_lower":"2000-10-01",
    "date:inception_upper":"2000-10-31",
    "iso:country":"GB",
    "wof:name":"W1W 5BQ",
    "wof:placetype":"postalcode"
},
  "geometry": {"coordinates":[-0.143571,51.522389],"type":"Point"}
}