{
  "type": "Feature",
  "properties": {
    "date:inception_lower":"2008-03-01",
    "date:inception_upper":"2008-03-31",
    "iso:country":"GB",
    "wof:name":"SK8 3AN",
    "wof:placetype":"postalcode"
},
  "geometry": {"coordinates":[-2.215741,53.362362],"type":"Point"}
}