{
  "type": "Feature",
  "properties": {
    "iso:country":"GB",
    "wof:name":"SK8 3AN",
    "wof:placetype":"postalcode"
},
  "geometry": {"coordinates":[-2.21574134414263,53.36236175396173],"type":"Point"}
}