{
  "type": "Feature",
  "properties": {
    "date:inception_lower": "2003-02-01",
    "date:inception_upper": "2003-02-01",
    "iso:country": "GB",
    "wof:name": "BD3 9SR",
    "wof:placetype": "postalcode"
  },
  "geometry": {"coordinates":[-1.732769,53.790459],"type":"Point"}
}
