{
  "type": "Feature",
  "properties": {
    "iso:country":"GB",
    "wof:name":"BD3 9SR",
    "wof:placetype":"postalcode"
},
  "geometry": {"coordinates":[-1.73288659113808,53.79055229304299],"type":"Point"}
}