{
  "type": "Feature",
  "properties": {
    "date:inception_lower": "1980-01-01",
    "date:inception_upper": "1980-01-01",
    "iso:country": "GB",
    "wof:name": "TN38 0AJ",
    "wof:placetype": "postalcode"
  },
  "geometry": {"coordinates":[0.535268,50.850933],"type":"Point"}
}
