{
  "type": "Feature",
  "properties": {
    "date:inception_lower": "1980-01-01",
    "date:inception_upper": "1980-01-01",
    "iso:country": "GB",
    "wof:name": "NR9 3HL",
    "wof:placetype": "postalcode"
  },
  "geometry": {"coordinates":[1.163101,52.599675],"type":"Point"}
}
