{
  "type": "Feature",
  "properties": {
    "date:inception_lower": "1980-01-01",
    "date:inception_upper": "1980-01-01",
    "iso:country": "GB",
    "wof:name": "SW18 5UD",
    "wof:placetype": "postalcode"
  },
  "geometry": {"coordinates":[-0.204905,51.448724],"type":"Point"}
}
