{
  "type": "Feature",
  "properties": {
    "iso:country":"GB",
    "wof:name":"SW18 5UD",
    "wof:placetype":"postalcode"
},
  "geometry": {"coordinates":[-0.20490460931286,51.44872367928745],"type":"Point"}
}