{
  "type": "Feature",
  "properties": {
    "iso:country":"GB",
    "wof:name":"HX2 7LQ",
    "wof:placetype":"postalcode"
},
  "geometry": {"coordinates":[-1.89783230440167,53.71773324352034],"type":"Point"}
}