{
  "type": "Feature",
  "properties": {
    "date:inception_lower": "1981-09-01",
    "date:inception_upper": "1981-09-01",
    "iso:country": "GB",
    "wof:name": "HP2 7QH",
    "wof:placetype": "postalcode"
  },
  "geometry": {"coordinates":[-0.43601,51.78046],"type":"Point"}
}
