{
  "type": "Feature",
  "properties": {
    "iso:country":"GB",
    "wof:name":"RM8 1JZ",
    "wof:placetype":"postalcode"
},
  "geometry": {"coordinates":[0.15412363168084,51.5616154985992],"type":"Point"}
}