{
  "type": "Feature",
  "properties": {
    "iso:country": "GB",
    "wof:name": "PR4 1XR",
    "wof:placetype": "postalcode"
  },
  "geometry": {"coordinates":[-2.887969,53.751876],"type":"Point"}
}
