{
  "type": "Feature",
  "properties": {
    "date:inception_lower": "1981-06-01",
    "date:inception_upper": "1981-06-01",
    "iso:country": "GB",
    "wof:name": "RH6 8AW",
    "wof:placetype": "postalcode"
  },
  "geometry": {"coordinates":[-0.168608,51.184972],"type":"Point"}
}
