{
  "type": "Feature",
  "properties": {
    "iso:country": "GB",
    "wof:name": "RH6 8AW",
    "wof:placetype": "postalcode"
  },
  "geometry": {"coordinates":[-0.168608,51.184972],"type":"Point"}
}
