{
  "type": "Feature",
  "properties": {
    "iso:country":"GB",
    "wof:name":"HA6 1SU",
    "wof:placetype":"postalcode"
},
  "geometry": {"coordinates":[-0.41341512763713,51.60527263958005],"type":"Point"}
}