{
  "type": "Feature",
  "properties": {
    "iso:country":"GB",
    "wof:name":"LE4 3NX",
    "wof:placetype":"postalcode"
},
  "geometry": {"coordinates":[-1.13388959800328,52.68603781736022],"type":"Point"}
}