{
  "type": "Feature",
  "properties": {
    "iso:country": "GB",
    "wof:name": "LE4 3NX",
    "wof:placetype": "postalcode"
  },
  "geometry": {"coordinates":[-1.133882,52.686057],"type":"Point"}
}
