{
  "type": "Feature",
  "properties": {
    "date:inception_lower": "2014-08-01",
    "date:inception_upper": "2014-08-01",
    "iso:country": "GB",
    "wof:name": "LE4 3NX",
    "wof:placetype": "postalcode"
  },
  "geometry": {"coordinates":[-1.133882,52.686057],"type":"Point"}
}
