{
  "type": "Feature",
  "properties": {
    "iso:country": "GB",
    "wof:name": "BB7 4TW",
    "wof:placetype": "postalcode"
  },
  "geometry": {"coordinates":[-2.39664,53.956064],"type":"Point"}
}
