{
  "type": "Feature",
  "properties": {
    "iso:country":"GB",
    "wof:name":"BB7 4TW",
    "wof:placetype":"postalcode"
},
  "geometry": {"coordinates":[-2.39663972923973,53.95606421553509],"type":"Point"}
}