{
  "type": "Feature",
  "properties": {
    "date:inception_lower": "1997-12-01",
    "date:inception_upper": "1997-12-01",
    "iso:country": "GB",
    "wof:name": "BS30 5TX",
    "wof:placetype": "postalcode"
  },
  "geometry": {"coordinates":[-2.44296,51.464709],"type":"Point"}
}
