{
  "type": "Feature",
  "properties": {
    "iso:country":"GB",
    "wof:name":"BD13 3DN",
    "wof:placetype":"postalcode"
},
  "geometry": {"coordinates":[-1.83592073363305,53.79489873100557],"type":"Point"}
}