{
  "type": "Feature",
  "properties": {
    "iso:country":"GB",
    "wof:name":"PE3 9ER",
    "wof:placetype":"postalcode"
},
  "geometry": {"coordinates":[-0.2634587966936,52.58168363197999],"type":"Point"}
}