{
  "type": "Feature",
  "properties": {
    "iso:country":"GB",
    "wof:name":"BA1 0RA",
    "wof:placetype":"postalcode"
},
  "geometry": {"coordinates":[-2.3555616595412,51.37884889440873],"type":"Point"}
}