{
  "type": "Feature",
  "properties": {
    "date:inception_lower":"1980-01-01",
    "date:inception_upper":"1980-01-31",
    "iso:country":"GB",
    "wof:name":"PE6 8DX",
    "wof:placetype":"postalcode"
},
  "geometry": {"coordinates":[-0.327351,52.682499],"type":"Point"}
}