{
  "type": "Feature",
  "properties": {
    "date:inception_lower": "1980-01-01",
    "date:inception_upper": "1980-01-01",
    "iso:country": "GB",
    "wof:name": "IP26 4RN",
    "wof:placetype": "postalcode"
  },
  "geometry": {"coordinates":[0.588833,52.516727],"type":"Point"}
}
