{
  "type": "Feature",
  "properties": {
    "date:inception_lower": "1980-01-01",
    "date:inception_upper": "1980-01-01",
    "iso:country": "GB",
    "wof:name": "YO21 1SP",
    "wof:placetype": "postalcode"
  },
  "geometry": {"coordinates":[-0.679428,54.466064],"type":"Point"}
}
