{
  "type": "Feature",
  "properties": {
    "iso:country":"GB",
    "wof:name":"SO21 1AG",
    "wof:placetype":"postalcode"
},
  "geometry": {"coordinates":[-1.26809389110408,51.11606692862085],"type":"Point"}
}