{
  "type": "Feature",
  "properties": {
    "date:inception_lower": "2000-12-01",
    "date:inception_upper": "2000-12-01",
    "iso:country": "GB",
    "wof:name": "CO12 3TX",
    "wof:placetype": "postalcode"
  },
  "geometry": {"coordinates":[1.247107,51.925968],"type":"Point"}
}
