{
  "type": "Feature",
  "properties": {
    "iso:country":"GB",
    "wof:name":"CO12 3TX",
    "wof:placetype":"postalcode"
},
  "geometry": {"coordinates":[1.24710663932944,51.92596814121614],"type":"Point"}
}