{
  "type": "Feature",
  "properties": {
    "iso:country":"GB",
    "wof:name":"SW9 8QJ",
    "wof:placetype":"postalcode"
},
  "geometry": {"coordinates":[-0.1107803509539,51.4752835346285],"type":"Point"}
}