{
  "type": "Feature",
  "properties": {
    "iso:country": "GB",
    "wof:name": "SW9 8QJ",
    "wof:placetype": "postalcode"
  },
  "geometry": {"coordinates":[-0.11078,51.475284],"type":"Point"}
}
