{
  "type": "Feature",
  "properties": {
    "date:inception_lower":"1995-07-01",
    "date:inception_upper":"1995-07-31",
    "iso:country":"GB",
    "wof:name":"SW9 8QJ",
    "wof:placetype":"postalcode"
},
  "geometry": {"coordinates":[-0.11078,51.475284],"type":"Point"}
}