{
  "type": "Feature",
  "properties": {
    "iso:country":"GB",
    "wof:name":"NE62 5YQ",
    "wof:placetype":"postalcode"
},
  "geometry": {"coordinates":[-1.58969594814586,55.16738915807599],"type":"Point"}
}