{
  "type": "Feature",
  "properties": {
    "date:inception_lower":"1998-12-01",
    "date:inception_upper":"1998-12-31",
    "iso:country":"GB",
    "wof:name":"GL54 5DB",
    "wof:placetype":"postalcode"
},
  "geometry": {"coordinates":[-1.949972,51.992199],"type":"Point"}
}