{
  "type": "Feature",
  "properties": {
    "iso:country":"GB",
    "wof:name":"CM14 4DX",
    "wof:placetype":"postalcode"
},
  "geometry": {"coordinates":[0.30011668833531,51.6163899510666],"type":"Point"}
}