{
  "type": "Feature",
  "properties": {
    "iso:country": "GB",
    "wof:name": "HD7 4FB",
    "wof:placetype": "postalcode"
  },
  "geometry": {"coordinates":[-1.85992,53.639989],"type":"Point"}
}
