{
  "type": "Feature",
  "properties": {
    "date:inception_lower":"1993-08-01",
    "date:inception_upper":"1993-08-31",
    "iso:country":"GB",
    "wof:name":"SY7 0PT",
    "wof:placetype":"postalcode"
},
  "geometry": {"coordinates":[-2.891035,52.401833],"type":"Point"}
}