{
  "type": "Feature",
  "properties": {
    "iso:country": "GB",
    "wof:name": "SY7 0PT",
    "wof:placetype": "postalcode"
  },
  "geometry": {"coordinates":[-2.891035,52.401833],"type":"Point"}
}
