{
  "type": "Feature",
  "properties": {
    "iso:country":"GB",
    "wof:name":"SY7 0PT",
    "wof:placetype":"postalcode"
},
  "geometry": {"coordinates":[-2.89103474554231,52.40181461624015],"type":"Point"}
}