{
  "type": "Feature",
  "properties": {
    "date:inception_lower": "2019-11-01",
    "date:inception_upper": "2019-11-01",
    "iso:country": "GB",
    "wof:name": "TN12 0GT",
    "wof:placetype": "postalcode"
  },
  "geometry": {"coordinates":[0.558275,51.166464],"type":"Point"}
}
