{
  "type": "Feature",
  "properties": {
    "iso:country":"GB",
    "wof:name":"LE4 4FE",
    "wof:placetype":"postalcode"
},
  "geometry": {"coordinates":[-1.11497250902168,52.6843698461284],"type":"Point"}
}