{
  "type": "Feature",
  "properties": {
    "iso:country": "GB",
    "wof:name": "LE4 4FE",
    "wof:placetype": "postalcode"
  },
  "geometry": {"coordinates":[-1.114972,52.68437],"type":"Point"}
}
