{
  "type": "Feature",
  "properties": {
    "iso:country":"GB",
    "wof:name":"S6 4QQ",
    "wof:placetype":"postalcode"
},
  "geometry": {"coordinates":[-1.51033821331901,53.40409733273532],"type":"Point"}
}