{
  "type": "Feature",
  "properties": {
    "iso:country": "GB",
    "wof:name": "L40 3SL",
    "wof:placetype": "postalcode"
  },
  "geometry": {"coordinates":[-2.761415,53.609515],"type":"Point"}
}
