{
  "type": "Feature",
  "properties": {
    "date:inception_lower":"2012-09-01",
    "date:inception_upper":"2012-09-30",
    "iso:country":"GB",
    "wof:name":"SS15 5XG",
    "wof:placetype":"postalcode"
},
  "geometry": {"coordinates":[0.429127,51.570006],"type":"Point"}
}