{
  "type": "Feature",
  "properties": {
    "iso:country": "GB",
    "wof:name": "WA10 3PH",
    "wof:placetype": "postalcode"
  },
  "geometry": {"coordinates":[-2.774366,53.435675],"type":"Point"}
}
