{
  "type": "Feature",
  "properties": {
    "iso:country":"GB",
    "wof:name":"TS20 2BG",
    "wof:placetype":"postalcode"
},
  "geometry": {"coordinates":[-1.30974760944355,54.57479230998928],"type":"Point"}
}