{
  "type": "Feature",
  "properties": {
    "iso:country": "GB",
    "wof:name": "SK7 3JT",
    "wof:placetype": "postalcode"
  },
  "geometry": {"coordinates":[-2.168536,53.379507],"type":"Point"}
}
