{
  "type": "Feature",
  "properties": {
    "date:inception_lower": "1980-01-01",
    "date:inception_upper": "1980-01-01",
    "iso:country": "GB",
    "wof:name": "SK7 3JT",
    "wof:placetype": "postalcode"
  },
  "geometry": {"coordinates":[-2.168536,53.379507],"type":"Point"}
}
