{
  "type": "Feature",
  "properties": {
    "iso:country":"GB",
    "wof:name":"CB1 2QG",
    "wof:placetype":"postalcode"
},
  "geometry": {"coordinates":[0.14054577602907,52.20263285793167],"type":"Point"}
}