{
  "type": "Feature",
  "properties": {
    "iso:country": "GB",
    "wof:name": "CT5 4UJ",
    "wof:placetype": "postalcode"
  },
  "geometry": {"coordinates":[1.009792,51.341143],"type":"Point"}
}
