{
  "type": "Feature",
  "properties": {
    "date:inception_lower": "2004-02-01",
    "date:inception_upper": "2004-02-01",
    "iso:country": "GB",
    "wof:name": "CT5 4UJ",
    "wof:placetype": "postalcode"
  },
  "geometry": {"coordinates":[1.009792,51.341143],"type":"Point"}
}
