{
  "type": "Feature",
  "properties": {
    "iso:country":"GB",
    "wof:name":"CT5 4UJ",
    "wof:placetype":"postalcode"
},
  "geometry": {"coordinates":[1.00979167851539,51.34114324460528],"type":"Point"}
}