{
  "type": "Feature",
  "properties": {
    "iso:country":"GB",
    "wof:name":"SS7 2HG",
    "wof:placetype":"postalcode"
},
  "geometry": {"coordinates":[0.6181777140563,51.55318280540382],"type":"Point"}
}