{
  "type": "Feature",
  "properties": {
    "iso:country": "GB",
    "wof:name": "SS7 2HG",
    "wof:placetype": "postalcode"
  },
  "geometry": {"coordinates":[0.618178,51.553183],"type":"Point"}
}
