{
  "type": "Feature",
  "properties": {
    "iso:country":"GB",
    "wof:name":"PE13 2AB",
    "wof:placetype":"postalcode"
},
  "geometry": {"coordinates":[0.16757851687899,52.66190171484278],"type":"Point"}
}