{
  "type": "Feature",
  "properties": {
    "date:inception_lower": "1998-06-01",
    "date:inception_upper": "1998-06-01",
    "iso:country": "GB",
    "wof:name": "PE13 2AB",
    "wof:placetype": "postalcode"
  },
  "geometry": {"coordinates":[0.167579,52.661902],"type":"Point"}
}
