{
  "type": "Feature",
  "properties": {
    "iso:country":"GB",
    "wof:name":"PO18 9DT",
    "wof:placetype":"postalcode"
},
  "geometry": {"coordinates":[-0.89335914834016,50.8772101346362],"type":"Point"}
}