{
  "type": "Feature",
  "properties": {
    "iso:country": "GB",
    "wof:name": "TQ10 9YT",
    "wof:placetype": "postalcode"
  },
  "geometry": {"coordinates":[-3.838057,50.422338],"type":"Point"}
}
