{
  "type": "Feature",
  "properties": {
    "iso:country": "GB",
    "wof:name": "OL15 9RA",
    "wof:placetype": "postalcode"
  },
  "geometry": {"coordinates":[-2.082803,53.663513],"type":"Point"}
}
