{
  "type": "Feature",
  "properties": {
    "iso:country":"GB",
    "wof:name":"PE31 6SD",
    "wof:placetype":"postalcode"
},
  "geometry": {"coordinates":[0.5723928541077,52.88302547445018],"type":"Point"}
}