{
  "type": "Feature",
  "properties": {
    "date:inception_lower": "1980-01-01",
    "date:inception_upper": "1980-01-01",
    "iso:country": "GB",
    "wof:name": "PE31 6SD",
    "wof:placetype": "postalcode"
  },
  "geometry": {"coordinates":[0.572393,52.883025],"type":"Point"}
}
