{
  "type": "Feature",
  "properties": {
    "iso:country": "GB",
    "wof:name": "PE31 6SD",
    "wof:placetype": "postalcode"
  },
  "geometry": {"coordinates":[0.572393,52.883025],"type":"Point"}
}
