{
  "type": "Feature",
  "properties": {
    "date:inception_lower":"2018-09-01",
    "date:inception_upper":"2018-09-30",
    "iso:country":"GB",
    "wof:name":"IP14 1WW",
    "wof:placetype":"postalcode"
},
  "geometry": {"coordinates":[0.997645,52.186362],"type":"Point"}
}