{
  "type": "Feature",
  "properties": {
    "iso:country":"GB",
    "wof:name":"LE14 3AG",
    "wof:placetype":"postalcode"
},
  "geometry": {"coordinates":[-0.97565574665837,52.85022656764898],"type":"Point"}
}