{
  "type": "Feature",
  "properties": {
    "iso:country": "GB",
    "wof:name": "LE14 3AG",
    "wof:placetype": "postalcode"
  },
  "geometry": {"coordinates":[-0.975656,52.850227],"type":"Point"}
}
