{
  "type": "Feature",
  "properties": {
    "date:inception_lower":"2011-08-01",
    "date:inception_upper":"2011-08-31",
    "iso:country":"GB",
    "wof:name":"DT9 5GA",
    "wof:placetype":"postalcode"
},
  "geometry": {"coordinates":[-2.462951,50.969375],"type":"Point"}
}