{
  "type": "Feature",
  "properties": {
    "iso:country":"GB",
    "wof:name":"DT9 5GA",
    "wof:placetype":"postalcode"
},
  "geometry": {"coordinates":[-2.46295182046096,50.96935420048313],"type":"Point"}
}