{
  "type": "Feature",
  "properties": {
    "date:inception_lower":"1997-12-01",
    "date:inception_upper":"1997-12-31",
    "iso:country":"GB",
    "wof:name":"SP11 9SS",
    "wof:placetype":"postalcode"
},
  "geometry": {"coordinates":[-1.613205,51.25408],"type":"Point"}
}