{
  "type": "Feature",
  "properties": {
    "iso:country": "GB",
    "wof:name": "SP11 9SS",
    "wof:placetype": "postalcode"
  },
  "geometry": {"coordinates":[-1.613205,51.25408],"type":"Point"}
}
