{
  "type": "Feature",
  "properties": {
    "iso:country":"GB",
    "wof:name":"SP11 9SS",
    "wof:placetype":"postalcode"
},
  "geometry": {"coordinates":[-1.61320533432246,51.2540804516259],"type":"Point"}
}