{
  "type": "Feature",
  "properties": {
    "iso:country":"GB",
    "wof:name":"NR21 7HT",
    "wof:placetype":"postalcode"
},
  "geometry": {"coordinates":[0.81359950356243,52.78102031289107],"type":"Point"}
}