{
  "type": "Feature",
  "properties": {
    "iso:country":"GB",
    "wof:name":"HD1 6PQ",
    "wof:placetype":"postalcode"
},
  "geometry": {"coordinates":[-1.76538813049427,53.65644600434067],"type":"Point"}
}