{
  "type": "Feature",
  "properties": {
    "iso:country":"GB",
    "wof:name":"SA44 5XD",
    "wof:placetype":"postalcode"
},
  "geometry": {"coordinates":[-4.38793915043252,52.01446364612902],"type":"Point"}
}