{
  "type": "Feature",
  "properties": {
    "iso:country":"GB",
    "wof:name":"WN4 8SL",
    "wof:placetype":"postalcode"
},
  "geometry": {"coordinates":[-2.62293010962168,53.49286605901602],"type":"Point"}
}