{
  "type": "Feature",
  "properties": {
    "date:inception_lower": "1980-01-01",
    "date:inception_upper": "1980-01-01",
    "iso:country": "GB",
    "wof:name": "WN4 8SL",
    "wof:placetype": "postalcode"
  },
  "geometry": {"coordinates":[-2.62293,53.492866],"type":"Point"}
}
