{
  "type": "Feature",
  "properties": {
    "iso:country":"GB",
    "wof:name":"CH1 2BY",
    "wof:placetype":"postalcode"
},
  "geometry": {"coordinates":[-2.89274697340506,53.19144486509151],"type":"Point"}
}