{
  "type": "Feature",
  "properties": {
    "iso:country": "GB",
    "wof:name": "SO41 8PA",
    "wof:placetype": "postalcode"
  },
  "geometry": {"coordinates":[-1.549587,50.775743],"type":"Point"}
}
