{
  "type": "Feature",
  "properties": {
    "iso:country": "GB",
    "wof:name": "CH7 3QD",
    "wof:placetype": "postalcode"
  },
  "geometry": {"coordinates":[-3.0736,53.178976],"type":"Point"}
}
