{
  "type": "Feature",
  "properties": {
    "date:inception_lower": "1997-06-01",
    "date:inception_upper": "1997-06-01",
    "iso:country": "GB",
    "wof:name": "CH7 3QD",
    "wof:placetype": "postalcode"
  },
  "geometry": {"coordinates":[-3.0736,53.178976],"type":"Point"}
}
