{
  "type": "Feature",
  "properties": {
    "date:inception_lower": "1990-08-01",
    "date:inception_upper": "1990-08-01",
    "iso:country": "GB",
    "wof:name": "AB51 0UF",
    "wof:placetype": "postalcode"
  },
  "geometry": {"coordinates":[-2.352432,57.238331],"type":"Point"}
}
