{
  "type": "Feature",
  "properties": {
    "iso:country": "GB",
    "wof:name": "AB51 0UF",
    "wof:placetype": "postalcode"
  },
  "geometry": {"coordinates":[-2.352432,57.238331],"type":"Point"}
}
