{
  "type": "Feature",
  "properties": {
    "iso:country":"GB",
    "wof:name":"YO22 4AW",
    "wof:placetype":"postalcode"
},
  "geometry": {"coordinates":[-0.61013735925644,54.48511415672954],"type":"Point"}
}