{
  "type": "Feature",
  "properties": {
    "iso:country": "GB",
    "wof:name": "S75 1LQ",
    "wof:placetype": "postalcode"
  },
  "geometry": {"coordinates":[-1.53324,53.568265],"type":"Point"}
}
