{
  "type": "Feature",
  "properties": {
    "iso:country":"GB",
    "wof:name":"S75 1LQ",
    "wof:placetype":"postalcode"
},
  "geometry": {"coordinates":[-1.53343406980095,53.56831999530903],"type":"Point"}
}