{
  "type": "Feature",
  "properties": {
    "iso:country":"GB",
    "wof:name":"SM1 1DZ",
    "wof:placetype":"postalcode"
},
  "geometry": {"coordinates":[-0.19318339977101,51.36170209640736],"type":"Point"}
}