{
  "type": "Feature",
  "properties": {
    "iso:country": "GB",
    "wof:name": "CT1 3TY",
    "wof:placetype": "postalcode"
  },
  "geometry": {"coordinates":[1.065332,51.270875],"type":"Point"}
}
