{
  "type": "Feature",
  "properties": {
    "iso:country":"GB",
    "wof:name":"CT1 3TY",
    "wof:placetype":"postalcode"
},
  "geometry": {"coordinates":[1.0653318517869,51.27087546836477],"type":"Point"}
}