{
  "type": "Feature",
  "properties": {
    "date:inception_lower": "1980-01-01",
    "date:inception_upper": "1980-01-01",
    "iso:country": "GB",
    "wof:name": "L20 5DQ",
    "wof:placetype": "postalcode"
  },
  "geometry": {"coordinates":[-2.995994,53.458392],"type":"Point"}
}
