{
  "type": "Feature",
  "properties": {
    "iso:country":"GB",
    "wof:name":"L20 5DQ",
    "wof:placetype":"postalcode"
},
  "geometry": {"coordinates":[-2.99599381505611,53.458392367046],"type":"Point"}
}