{
  "type": "Feature",
  "properties": {
    "iso:country":"GB",
    "wof:name":"OX5 3HN",
    "wof:placetype":"postalcode"
},
  "geometry": {"coordinates":[-1.27567092833538,51.87490888820368],"type":"Point"}
}