{
  "type": "Feature",
  "properties": {
    "iso:country":"GB",
    "wof:name":"KT23 3NP",
    "wof:placetype":"postalcode"
},
  "geometry": {"coordinates":[-0.37084710471147,51.28573073421702],"type":"Point"}
}