{
  "type": "Feature",
  "properties": {
    "date:inception_lower": "2005-07-01",
    "date:inception_upper": "2005-07-01",
    "iso:country": "GB",
    "wof:name": "LD3 8DX",
    "wof:placetype": "postalcode"
  },
  "geometry": {"coordinates":[-3.405084,51.946232],"type":"Point"}
}
