{
  "type": "Feature",
  "properties": {
    "iso:country":"GB",
    "wof:name":"LD3 8DX",
    "wof:placetype":"postalcode"
},
  "geometry": {"coordinates":[-3.40508371907071,51.94623213276852],"type":"Point"}
}