{
  "type": "Feature",
  "properties": {
    "iso:country": "GB",
    "wof:name": "WF1 3RP",
    "wof:placetype": "postalcode"
  },
  "geometry": {"coordinates":[-1.497727,53.69163],"type":"Point"}
}
