{
  "type": "Feature",
  "properties": {
    "iso:country": "GB",
    "wof:name": "DG9 9NT",
    "wof:placetype": "postalcode"
  },
  "geometry": {"coordinates":[-4.937474,54.7242],"type":"Point"}
}
