{
  "type": "Feature",
  "properties": {
    "iso:country":"GB",
    "wof:name":"HU12 8BU",
    "wof:placetype":"postalcode"
},
  "geometry": {"coordinates":[-0.20405413301938,53.74000660214563],"type":"Point"}
}