{
  "type": "Feature",
  "properties": {
    "iso:country": "GB",
    "wof:name": "HU12 8BU",
    "wof:placetype": "postalcode"
  },
  "geometry": {"coordinates":[-0.204054,53.740007],"type":"Point"}
}
