{
  "type": "Feature",
  "properties": {
    "iso:country":"GB",
    "wof:name":"L25 6EP",
    "wof:placetype":"postalcode"
},
  "geometry": {"coordinates":[-2.87907929843357,53.38199709645917],"type":"Point"}
}