{
  "type": "Feature",
  "properties": {
    "iso:country":"GB",
    "wof:name":"DY9 0PN",
    "wof:placetype":"postalcode"
},
  "geometry": {"coordinates":[-2.14170614879005,52.42539763306483],"type":"Point"}
}