{
  "type": "Feature",
  "properties": {
    "date:inception_lower": "1980-01-01",
    "date:inception_upper": "1980-01-01",
    "iso:country": "GB",
    "wof:name": "DY6 9LY",
    "wof:placetype": "postalcode"
  },
  "geometry": {"coordinates":[-2.170536,52.49558],"type":"Point"}
}
