{
  "type": "Feature",
  "properties": {
    "iso:country":"GB",
    "wof:name":"DY6 9LY",
    "wof:placetype":"postalcode"
},
  "geometry": {"coordinates":[-2.17053640569552,52.49558038102778],"type":"Point"}
}