{
  "type": "Feature",
  "properties": {
    "iso:country":"GB",
    "wof:name":"CV3 1PL",
    "wof:placetype":"postalcode"
},
  "geometry": {"coordinates":[-1.48549407225731,52.40169156569819],"type":"Point"}
}