{
  "type": "Feature",
  "properties": {
    "date:inception_lower": "2010-08-01",
    "date:inception_upper": "2010-08-01",
    "iso:country": "GB",
    "wof:name": "CV3 1PL",
    "wof:placetype": "postalcode"
  },
  "geometry": {"coordinates":[-1.485529,52.401673],"type":"Point"}
}
