{
  "type": "Feature",
  "properties": {
    "date:inception_lower": "2018-07-01",
    "date:inception_upper": "2018-07-01",
    "iso:country": "GB",
    "wof:name": "NG18 6AD",
    "wof:placetype": "postalcode"
  },
  "geometry": {"coordinates":[-1.17802,53.120422],"type":"Point"}
}
