{
  "type": "Feature",
  "properties": {
    "iso:country":"GB",
    "wof:name":"CO6 4JF",
    "wof:placetype":"postalcode"
},
  "geometry": {"coordinates":[0.87419639846031,51.97153737921784],"type":"Point"}
}