{
  "type": "Feature",
  "properties": {
    "date:inception_lower": "2010-10-01",
    "date:inception_upper": "2010-10-01",
    "iso:country": "GB",
    "wof:name": "SO16 6DL",
    "wof:placetype": "postalcode"
  },
  "geometry": {"coordinates":[-1.43689,50.929369],"type":"Point"}
}
