{
  "type": "Feature",
  "properties": {
    "iso:country":"GB",
    "wof:name":"PO3 5DA",
    "wof:placetype":"postalcode"
},
  "geometry": {"coordinates":[-1.06434458888231,50.81642207626722],"type":"Point"}
}