{
  "type": "Feature",
  "properties": {
    "iso:country":"GB",
    "wof:name":"EC1Y 8SE",
    "wof:placetype":"postalcode"
},
  "geometry": {"coordinates":[-0.09129616011539,51.52254773124971],"type":"Point"}
}