{
  "type": "Feature",
  "properties": {
    "date:inception_lower": "2018-02-01",
    "date:inception_upper": "2018-02-01",
    "iso:country": "GB",
    "wof:name": "EC1Y 8SE",
    "wof:placetype": "postalcode"
  },
  "geometry": {"coordinates":[-0.091414,51.522552],"type":"Point"}
}
