{
  "type": "Feature",
  "properties": {
    "iso:country":"GB",
    "wof:name":"DN5 7TD",
    "wof:placetype":"postalcode"
},
  "geometry": {"coordinates":[-1.24366245595592,53.51124516073349],"type":"Point"}
}