{
  "type": "Feature",
  "properties": {
    "iso:country":"GB",
    "wof:name":"SP10 1PJ",
    "wof:placetype":"postalcode"
},
  "geometry": {"coordinates":[-1.46224592346086,51.21232847556918],"type":"Point"}
}