{
  "type": "Feature",
  "properties": {
    "iso:country": "GB",
    "wof:name": "SP10 1PJ",
    "wof:placetype": "postalcode"
  },
  "geometry": {"coordinates":[-1.462246,51.212328],"type":"Point"}
}
