{
  "type": "Feature",
  "properties": {
    "iso:country":"GB",
    "wof:name":"CV33 9ND",
    "wof:placetype":"postalcode"
},
  "geometry": {"coordinates":[-1.45982665881191,52.23569701214837],"type":"Point"}
}