{
  "type": "Feature",
  "properties": {
    "iso:country": "GB",
    "wof:name": "CV33 9ND",
    "wof:placetype": "postalcode"
  },
  "geometry": {"coordinates":[-1.459827,52.235697],"type":"Point"}
}
