{
  "type": "Feature",
  "properties": {
    "date:inception_lower": "1980-01-01",
    "date:inception_upper": "1980-01-01",
    "iso:country": "GB",
    "wof:name": "SK9 4DE",
    "wof:placetype": "postalcode"
  },
  "geometry": {"coordinates":[-2.22669,53.338728],"type":"Point"}
}
