{
  "type": "Feature",
  "properties": {
    "iso:country": "GB",
    "wof:name": "SK9 4DE",
    "wof:placetype": "postalcode"
  },
  "geometry": {"coordinates":[-2.22669,53.338728],"type":"Point"}
}
