{
  "type": "Feature",
  "properties": {
    "iso:country":"GB",
    "wof:name":"DG11 3HE",
    "wof:placetype":"postalcode"
},
  "geometry": {"coordinates":[-3.1502967652817,55.11421240857089],"type":"Point"}
}