{
  "type": "Feature",
  "properties": {
    "iso:country": "GB",
    "wof:name": "G51 4HA",
    "wof:placetype": "postalcode"
  },
  "geometry": {"coordinates":[-4.337659,55.855528],"type":"Point"}
}
