{
  "type": "Feature",
  "properties": {
    "iso:country":"GB",
    "wof:name":"G51 4HA",
    "wof:placetype":"postalcode"
},
  "geometry": {"coordinates":[-4.33765872526577,55.85552763702381],"type":"Point"}
}