{
  "type": "Feature",
  "properties": {
    "iso:country": "GB",
    "wof:name": "CB23 1YL",
    "wof:placetype": "postalcode"
  },
  "geometry": {"coordinates":[-0.010036,52.16022],"type":"Point"}
}
