{
  "type": "Feature",
  "properties": {
    "iso:country":"GB",
    "wof:name":"CB23 1YL",
    "wof:placetype":"postalcode"
},
  "geometry": {"coordinates":[-0.01003632160469,52.16022016142998],"type":"Point"}
}