{
  "type": "Feature",
  "properties": {
    "date:inception_lower": "2006-09-01",
    "date:inception_upper": "2006-09-01",
    "iso:country": "GB",
    "wof:name": "CB23 1YL",
    "wof:placetype": "postalcode"
  },
  "geometry": {"coordinates":[-0.010036,52.16022],"type":"Point"}
}
