{
  "type": "Feature",
  "properties": {
    "iso:country":"GB",
    "wof:name":"WV6 9JZ",
    "wof:placetype":"postalcode"
},
  "geometry": {"coordinates":[-2.15541801633815,52.60637426585252],"type":"Point"}
}