{
  "type": "Feature",
  "properties": {
    "iso:country": "GB",
    "wof:name": "WV6 9JZ",
    "wof:placetype": "postalcode"
  },
  "geometry": {"coordinates":[-2.155413,52.60639],"type":"Point"}
}
