{
  "type": "Feature",
  "properties": {
    "iso:country":"GB",
    "wof:name":"S60 5WG",
    "wof:placetype":"postalcode"
},
  "geometry": {"coordinates":[-1.37822843522714,53.38662899083442],"type":"Point"}
}