{
  "type": "Feature",
  "properties": {
    "date:inception_lower": "1995-07-01",
    "date:inception_upper": "1995-07-01",
    "iso:country": "GB",
    "wof:name": "M40 8RF",
    "wof:placetype": "postalcode"
  },
  "geometry": {"coordinates":[-2.215155,53.499732],"type":"Point"}
}
