{
  "type": "Feature",
  "properties": {
    "date:inception_lower": "1997-06-01",
    "date:inception_upper": "1997-06-01",
    "iso:country": "GB",
    "wof:name": "DL16 7YE",
    "wof:placetype": "postalcode"
  },
  "geometry": {"coordinates":[-1.617624,54.693092],"type":"Point"}
}
