{
  "type": "Feature",
  "properties": {
    "iso:country":"GB",
    "wof:name":"B34 6PP",
    "wof:placetype":"postalcode"
},
  "geometry": {"coordinates":[-1.78564387802183,52.50183889745689],"type":"Point"}
}