{
  "type": "Feature",
  "properties": {
    "iso:country": "GB",
    "wof:name": "LD2 3DQ",
    "wof:placetype": "postalcode"
  },
  "geometry": {"coordinates":[-3.396414,52.145519],"type":"Point"}
}
