{
  "type": "Feature",
  "properties": {
    "iso:country":"GB",
    "wof:name":"LD2 3DQ",
    "wof:placetype":"postalcode"
},
  "geometry": {"coordinates":[-3.39641363556786,52.14551895408967],"type":"Point"}
}