{
  "type": "Feature",
  "properties": {
    "date:inception_lower": "1980-01-01",
    "date:inception_upper": "1980-01-01",
    "iso:country": "GB",
    "wof:name": "PL9 8PG",
    "wof:placetype": "postalcode"
  },
  "geometry": {"coordinates":[-4.077011,50.361922],"type":"Point"}
}
