{
  "type": "Feature",
  "properties": {
    "iso:country":"GB",
    "wof:name":"BH8 8HZ",
    "wof:placetype":"postalcode"
},
  "geometry": {"coordinates":[-1.86728788923644,50.72945102049032],"type":"Point"}
}