{
  "type": "Feature",
  "properties": {
    "iso:country": "GB",
    "wof:name": "BH8 8HZ",
    "wof:placetype": "postalcode"
  },
  "geometry": {"coordinates":[-1.867288,50.729451],"type":"Point"}
}
