{
  "type": "Feature",
  "properties": {
    "iso:country":"GB",
    "wof:name":"YO12 4HA",
    "wof:placetype":"postalcode"
},
  "geometry": {"coordinates":[-0.42092901375534,54.26683173191706],"type":"Point"}
}