{
  "type": "Feature",
  "properties": {
    "date:inception_lower":"1998-12-01",
    "date:inception_upper":"1998-12-31",
    "iso:country":"GB",
    "wof:name":"S71 5DX",
    "wof:placetype":"postalcode"
},
  "geometry": {"coordinates":[-1.423617,53.548121],"type":"Point"}
}