{
  "type": "Feature",
  "properties": {
    "iso:country":"GB",
    "wof:name":"S71 5DX",
    "wof:placetype":"postalcode"
},
  "geometry": {"coordinates":[-1.42361747116897,53.5481208690892],"type":"Point"}
}