{
  "type": "Feature",
  "properties": {
    "iso:country":"GB",
    "wof:name":"EH19 2AB",
    "wof:placetype":"postalcode"
},
  "geometry": {"coordinates":[-3.10709629540408,55.8760701256283],"type":"Point"}
}