{
  "type": "Feature",
  "properties": {
    "iso:country":"GB",
    "wof:name":"BS24 9PE",
    "wof:placetype":"postalcode"
},
  "geometry": {"coordinates":[-2.95230330798827,51.32191618163199],"type":"Point"}
}