{
  "type": "Feature",
  "properties": {
    "date:inception_lower": "1992-08-01",
    "date:inception_upper": "1992-08-01",
    "iso:country": "GB",
    "wof:name": "BS24 9PE",
    "wof:placetype": "postalcode"
  },
  "geometry": {"coordinates":[-2.952267,51.321913],"type":"Point"}
}
