{
  "type": "Feature",
  "properties": {
    "iso:country": "GB",
    "wof:name": "CM0 7QN",
    "wof:placetype": "postalcode"
  },
  "geometry": {"coordinates":[0.900159,51.724987],"type":"Point"}
}
