{
  "type": "Feature",
  "properties": {
    "iso:country":"GB",
    "wof:name":"CM0 7QN",
    "wof:placetype":"postalcode"
},
  "geometry": {"coordinates":[0.90015898790559,51.72498702393428],"type":"Point"}
}