{
  "type": "Feature",
  "properties": {
    "iso:country":"GB",
    "wof:name":"TA6 6PY",
    "wof:placetype":"postalcode"
},
  "geometry": {"coordinates":[-3.01235443898446,51.0931539485353],"type":"Point"}
}