{
  "type": "Feature",
  "properties": {
    "iso:country":"GB",
    "wof:name":"LD3 9EQ",
    "wof:placetype":"postalcode"
},
  "geometry": {"coordinates":[-3.38777580972478,51.9549163736262],"type":"Point"}
}