{
  "type": "Feature",
  "properties": {
    "date:inception_lower":"1990-02-01",
    "date:inception_upper":"1990-02-28",
    "iso:country":"GB",
    "wof:name":"LD3 9EQ",
    "wof:placetype":"postalcode"
},
  "geometry": {"coordinates":[-3.387776,51.954916],"type":"Point"}
}