{
  "type": "Feature",
  "properties": {
    "iso:country":"GB",
    "wof:name":"SP3 6BS",
    "wof:placetype":"postalcode"
},
  "geometry": {"coordinates":[-2.18297517879359,51.07679451345254],"type":"Point"}
}