{
  "type": "Feature",
  "properties": {
    "iso:country": "GB",
    "wof:name": "WD19 4FG",
    "wof:placetype": "postalcode"
  },
  "geometry": {"coordinates":[-0.393093,51.641131],"type":"Point"}
}
