{
  "type": "Feature",
  "properties": {
    "date:inception_lower": "1980-01-01",
    "date:inception_upper": "1980-01-01",
    "iso:country": "GB",
    "wof:name": "BH10 7HG",
    "wof:placetype": "postalcode"
  },
  "geometry": {"coordinates":[-1.893121,50.771536],"type":"Point"}
}
