{
  "type": "Feature",
  "properties": {
    "iso:country":"GB",
    "wof:name":"BH10 7HG",
    "wof:placetype":"postalcode"
},
  "geometry": {"coordinates":[-1.89312076489886,50.77153601698735],"type":"Point"}
}