{
  "type": "Feature",
  "properties": {
    "iso:country":"GB",
    "wof:name":"SO50 5LT",
    "wof:placetype":"postalcode"
},
  "geometry": {"coordinates":[-1.35498586745669,50.9649682480507],"type":"Point"}
}