{
  "type": "Feature",
  "properties": {
    "iso:country":"GB",
    "wof:name":"BS11 9NW",
    "wof:placetype":"postalcode"
},
  "geometry": {"coordinates":[-2.6851249200731,51.49415101053539],"type":"Point"}
}