{
  "type": "Feature",
  "properties": {
    "iso:country": "GB",
    "wof:name": "DG1 3PY",
    "wof:placetype": "postalcode"
  },
  "geometry": {"coordinates":[-3.549389,55.081831],"type":"Point"}
}
