{
  "type": "Feature",
  "properties": {
    "date:inception_lower": "2010-05-01",
    "date:inception_upper": "2010-05-01",
    "iso:country": "GB",
    "wof:name": "DG1 3PY",
    "wof:placetype": "postalcode"
  },
  "geometry": {"coordinates":[-3.549389,55.081831],"type":"Point"}
}
