{
  "type": "Feature",
  "properties": {
    "iso:country":"GB",
    "wof:name":"DG1 3PY",
    "wof:placetype":"postalcode"
},
  "geometry": {"coordinates":[-3.54938872400451,55.08183067792573],"type":"Point"}
}