{
  "type": "Feature",
  "properties": {
    "iso:country": "GB",
    "wof:name": "WA6 0JL",
    "wof:placetype": "postalcode"
  },
  "geometry": {"coordinates":[-2.789455,53.253111],"type":"Point"}
}
