{
  "type": "Feature",
  "properties": {
    "date:inception_lower": "1980-01-01",
    "date:inception_upper": "1980-01-01",
    "iso:country": "GB",
    "wof:name": "WA6 0JL",
    "wof:placetype": "postalcode"
  },
  "geometry": {"coordinates":[-2.789619,53.253152],"type":"Point"}
}
