{
  "type": "Feature",
  "properties": {
    "iso:country":"GB",
    "wof:name":"WA6 0JL",
    "wof:placetype":"postalcode"
},
  "geometry": {"coordinates":[-2.78945493046265,53.25311116450508],"type":"Point"}
}