{
  "type": "Feature",
  "properties": {
    "date:inception_lower":"1987-04-01",
    "date:inception_upper":"1987-04-30",
    "iso:country":"GB",
    "wof:name":"BR1 3HG",
    "wof:placetype":"postalcode"
},
  "geometry": {"coordinates":[0.019661,51.407543],"type":"Point"}
}