{
  "type": "Feature",
  "properties": {
    "iso:country":"GB",
    "wof:name":"BR1 3HG",
    "wof:placetype":"postalcode"
},
  "geometry": {"coordinates":[0.01966142400794,51.40754264380231],"type":"Point"}
}