{
  "type": "Feature",
  "properties": {
    "iso:country": "GB",
    "wof:name": "G13 3YA",
    "wof:placetype": "postalcode"
  },
  "geometry": {"coordinates":[-4.363721,55.897874],"type":"Point"}
}
