{
  "type": "Feature",
  "properties": {
    "iso:country":"GB",
    "wof:name":"G13 3YA",
    "wof:placetype":"postalcode"
},
  "geometry": {"coordinates":[-4.36372056391799,55.89787387430086],"type":"Point"}
}