{
  "type": "Feature",
  "properties": {
    "iso:country": "GB",
    "wof:name": "BN13 3EL",
    "wof:placetype": "postalcode"
  },
  "geometry": {"coordinates":[-0.406875,50.840371],"type":"Point"}
}
