{
  "type": "Feature",
  "properties": {
    "iso:country": "GB",
    "wof:name": "DD11 3DJ",
    "wof:placetype": "postalcode"
  },
  "geometry": {"coordinates":[-2.593835,56.563107],"type":"Point"}
}
