{
  "type": "Feature",
  "properties": {
    "date:inception_lower": "1980-01-01",
    "date:inception_upper": "1980-01-01",
    "iso:country": "GB",
    "wof:name": "DD11 3DJ",
    "wof:placetype": "postalcode"
  },
  "geometry": {"coordinates":[-2.593728,56.563187],"type":"Point"}
}
