{
  "type": "Feature",
  "properties": {
    "iso:country":"GB",
    "wof:name":"S32 5RG",
    "wof:placetype":"postalcode"
},
  "geometry": {"coordinates":[-1.67022535918654,53.28550954522883],"type":"Point"}
}