{
  "type": "Feature",
  "properties": {
    "date:inception_lower":"1980-01-01",
    "date:inception_upper":"1980-01-31",
    "iso:country":"GB",
    "wof:name":"GL4 8JY",
    "wof:placetype":"postalcode"
},
  "geometry": {"coordinates":[-2.096771,51.843354],"type":"Point"}
}