{
  "type": "Feature",
  "properties": {
    "iso:country":"GB",
    "wof:name":"GL4 8JY",
    "wof:placetype":"postalcode"
},
  "geometry": {"coordinates":[-2.09677140304243,51.84335371816461],"type":"Point"}
}