{
  "type": "Feature",
  "properties": {
    "iso:country": "GB",
    "wof:name": "GL4 8JY",
    "wof:placetype": "postalcode"
  },
  "geometry": {"coordinates":[-2.096771,51.843354],"type":"Point"}
}
