{
  "type": "Feature",
  "properties": {
    "date:inception_lower":"2001-06-01",
    "date:inception_upper":"2001-06-30",
    "iso:country":"GB",
    "wof:name":"TQ1 2BQ",
    "wof:placetype":"postalcode"
},
  "geometry": {"coordinates":[-3.549698,50.484772],"type":"Point"}
}