{
  "type": "Feature",
  "properties": {
    "iso:country":"GB",
    "wof:name":"G66 2RQ",
    "wof:placetype":"postalcode"
},
  "geometry": {"coordinates":[-4.13195983273355,55.94718591222937],"type":"Point"}
}