{
  "type": "Feature",
  "properties": {
    "iso:country":"GB",
    "wof:name":"KW1 4ND",
    "wof:placetype":"postalcode"
},
  "geometry": {"coordinates":[-3.09088187910021,58.44327975740417],"type":"Point"}
}