{
  "type": "Feature",
  "properties": {
    "iso:country":"GB",
    "wof:name":"NW2 6XJ",
    "wof:placetype":"postalcode"
},
  "geometry": {"coordinates":[-0.22476864509809,51.55763668649286],"type":"Point"}
}