{
  "type": "Feature",
  "properties": {
    "iso:country":"GB",
    "wof:name":"LL11 3HD",
    "wof:placetype":"postalcode"
},
  "geometry": {"coordinates":[-3.05854638252105,53.05430177644315],"type":"Point"}
}