{
  "type": "Feature",
  "properties": {
    "iso:country":"GB",
    "wof:name":"IG2 7PY",
    "wof:placetype":"postalcode"
},
  "geometry": {"coordinates":[0.09352531040114,51.58168711487393],"type":"Point"}
}