{
  "type": "Feature",
  "properties": {
    "iso:country": "GB",
    "wof:name": "EX39 5HE",
    "wof:placetype": "postalcode"
  },
  "geometry": {"coordinates":[-4.201868,50.998691],"type":"Point"}
}
