{
  "type": "Feature",
  "properties": {
    "iso:country":"GB",
    "wof:name":"W9 1PB",
    "wof:placetype":"postalcode"
},
  "geometry": {"coordinates":[-0.18392742622504,51.52905424232473],"type":"Point"}
}