{
  "type": "Feature",
  "properties": {
    "iso:country": "GB",
    "wof:name": "CA4 8DJ",
    "wof:placetype": "postalcode"
  },
  "geometry": {"coordinates":[-2.853189,54.868152],"type":"Point"}
}
