{
  "type": "Feature",
  "properties": {
    "date:inception_lower": "2022-05-01",
    "date:inception_upper": "2022-05-01",
    "iso:country": "GB",
    "wof:name": "LE65 1XE",
    "wof:placetype": "postalcode"
  },
  "geometry": {"coordinates":[-1.462452,52.73151],"type":"Point"}
}
