{
  "type": "Feature",
  "properties": {
    "iso:country":"GB",
    "wof:name":"NN14 3AH",
    "wof:placetype":"postalcode"
},
  "geometry": {"coordinates":[-0.60421725338695,52.39452795838433],"type":"Point"}
}