{
  "type": "Feature",
  "properties": {
    "date:inception_lower": "1980-01-01",
    "date:inception_upper": "1980-01-01",
    "iso:country": "GB",
    "wof:name": "NN14 3AH",
    "wof:placetype": "postalcode"
  },
  "geometry": {"coordinates":[-0.604217,52.394528],"type":"Point"}
}
