{
  "type": "Feature",
  "properties": {
    "iso:country":"GB",
    "wof:name":"WF4 1QB",
    "wof:placetype":"postalcode"
},
  "geometry": {"coordinates":[-1.41358784159981,53.65677771352335],"type":"Point"}
}