{
  "type": "Feature",
  "properties": {
    "iso:country": "GB",
    "wof:name": "WF4 1QB",
    "wof:placetype": "postalcode"
  },
  "geometry": {"coordinates":[-1.413588,53.656778],"type":"Point"}
}
