{
  "type": "Feature",
  "properties": {
    "date:inception_lower": "2005-09-01",
    "date:inception_upper": "2005-09-01",
    "iso:country": "GB",
    "wof:name": "WF4 1QB",
    "wof:placetype": "postalcode"
  },
  "geometry": {"coordinates":[-1.413588,53.656778],"type":"Point"}
}
