{
  "type": "Feature",
  "properties": {
    "iso:country": "GB",
    "wof:name": "TN4 8RX",
    "wof:placetype": "postalcode"
  },
  "geometry": {"coordinates":[0.228815,51.135454],"type":"Point"}
}
