{
  "type": "Feature",
  "properties": {
    "iso:country":"GB",
    "wof:name":"TN4 8RX",
    "wof:placetype":"postalcode"
},
  "geometry": {"coordinates":[0.22881540071498,51.13545394568038],"type":"Point"}
}