{
  "type": "Feature",
  "properties": {
    "iso:country": "GB",
    "wof:name": "NN14 1QB",
    "wof:placetype": "postalcode"
  },
  "geometry": {"coordinates":[-0.659647,52.470851],"type":"Point"}
}
