{
  "type": "Feature",
  "properties": {
    "date:inception_lower":"1985-04-01",
    "date:inception_upper":"1985-04-30",
    "iso:country":"GB",
    "wof:name":"NN14 1QB",
    "wof:placetype":"postalcode"
},
  "geometry": {"coordinates":[-0.659647,52.470851],"type":"Point"}
}