{
  "type": "Feature",
  "properties": {
    "date:inception_lower": "1985-04-01",
    "date:inception_upper": "1985-04-01",
    "iso:country": "GB",
    "wof:name": "NN14 1QB",
    "wof:placetype": "postalcode"
  },
  "geometry": {"coordinates":[-0.65964,52.470599],"type":"Point"}
}
