{
  "type": "Feature",
  "properties": {
    "iso:country":"GB",
    "wof:name":"EX38 7NH",
    "wof:placetype":"postalcode"
},
  "geometry": {"coordinates":[-4.12685090368399,50.95328338206647],"type":"Point"}
}