{
  "type": "Feature",
  "properties": {
    "date:inception_lower":"1990-02-01",
    "date:inception_upper":"1990-02-28",
    "iso:country":"GB",
    "wof:name":"EX38 7NH",
    "wof:placetype":"postalcode"
},
  "geometry": {"coordinates":[-4.126851,50.953283],"type":"Point"}
}