{
  "type": "Feature",
  "properties": {
    "iso:country":"GB",
    "wof:name":"RH9 8HD",
    "wof:placetype":"postalcode"
},
  "geometry": {"coordinates":[-0.04216430973746,51.2178616052345],"type":"Point"}
}