{
  "type": "Feature",
  "properties": {
    "date:inception_lower": "1990-02-01",
    "date:inception_upper": "1990-02-01",
    "iso:country": "GB",
    "wof:name": "RH9 8HD",
    "wof:placetype": "postalcode"
  },
  "geometry": {"coordinates":[-0.042164,51.217862],"type":"Point"}
}
