{
  "type": "Feature",
  "properties": {
    "iso:country":"GB",
    "wof:name":"HU5 5DS",
    "wof:placetype":"postalcode"
},
  "geometry": {"coordinates":[-0.39246953367353,53.75625559448897],"type":"Point"}
}