{
  "type": "Feature",
  "properties": {
    "iso:country":"GB",
    "wof:name":"NR23 1JX",
    "wof:placetype":"postalcode"
},
  "geometry": {"coordinates":[0.85393407405434,52.95654993313826],"type":"Point"}
}