{
  "type": "Feature",
  "properties": {
    "date:inception_lower": "1980-01-01",
    "date:inception_upper": "1980-01-01",
    "iso:country": "GB",
    "wof:name": "TA18 7TB",
    "wof:placetype": "postalcode"
  },
  "geometry": {"coordinates":[-2.729626,50.873013],"type":"Point"}
}
