{
  "type": "Feature",
  "properties": {
    "iso:country":"GB",
    "wof:name":"SA16 0RW",
    "wof:placetype":"postalcode"
},
  "geometry": {"coordinates":[-4.23041831634018,51.69343540537939],"type":"Point"}
}