{
  "type": "Feature",
  "properties": {
    "date:inception_lower": "1993-01-01",
    "date:inception_upper": "1993-01-01",
    "iso:country": "GB",
    "wof:name": "SA16 0RW",
    "wof:placetype": "postalcode"
  },
  "geometry": {"coordinates":[-4.230418,51.693435],"type":"Point"}
}
