{
  "type": "Feature",
  "properties": {
    "iso:country":"GB",
    "wof:name":"ST5 5HG",
    "wof:placetype":"postalcode"
},
  "geometry": {"coordinates":[-2.29013103517081,52.99359505479053],"type":"Point"}
}