{
  "type": "Feature",
  "properties": {
    "date:inception_lower": "1998-12-01",
    "date:inception_upper": "1998-12-01",
    "iso:country": "GB",
    "wof:name": "WC2B 4JN",
    "wof:placetype": "postalcode"
  },
  "geometry": {"coordinates":[-0.115328,51.513413],"type":"Point"}
}
