{
  "type": "Feature",
  "properties": {
    "date:inception_lower":"1997-12-01",
    "date:inception_upper":"1997-12-31",
    "iso:country":"GB",
    "wof:name":"BS16 9SU",
    "wof:placetype":"postalcode"
},
  "geometry": {"coordinates":[-2.432911,51.4813],"type":"Point"}
}