{
  "type": "Feature",
  "properties": {
    "iso:country":"GB",
    "wof:name":"BS16 9SU",
    "wof:placetype":"postalcode"
},
  "geometry": {"coordinates":[-2.43291055324344,51.48129987367289],"type":"Point"}
}