{
  "type": "Feature",
  "properties": {
    "iso:country":"GB",
    "wof:name":"EX2 7PB",
    "wof:placetype":"postalcode"
},
  "geometry": {"coordinates":[-3.47927415304048,50.71550705572214],"type":"Point"}
}