{
  "type": "Feature",
  "properties": {
    "date:inception_lower": "1995-07-01",
    "date:inception_upper": "1995-07-01",
    "iso:country": "GB",
    "wof:name": "LE3 3EX",
    "wof:placetype": "postalcode"
  },
  "geometry": {"coordinates":[-1.218095,52.619738],"type":"Point"}
}
