{
  "type": "Feature",
  "properties": {
    "iso:country": "GB",
    "wof:name": "LE3 3EX",
    "wof:placetype": "postalcode"
  },
  "geometry": {"coordinates":[-1.218095,52.619738],"type":"Point"}
}
