{
  "type": "Feature",
  "properties": {
    "iso:country": "GB",
    "wof:name": "RG30 4EQ",
    "wof:placetype": "postalcode"
  },
  "geometry": {"coordinates":[-1.015711,51.44784],"type":"Point"}
}
