{
  "type": "Feature",
  "properties": {
    "iso:country":"GB",
    "wof:name":"RG30 4EQ",
    "wof:placetype":"postalcode"
},
  "geometry": {"coordinates":[-1.01571139321656,51.44783993326328],"type":"Point"}
}