{
  "type": "Feature",
  "properties": {
    "iso:country": "GB",
    "wof:name": "NE47 9LH",
    "wof:placetype": "postalcode"
  },
  "geometry": {"coordinates":[-2.27305,54.917329],"type":"Point"}
}
