{
  "type": "Feature",
  "properties": {
    "iso:country": "GB",
    "wof:name": "GL2 2AR",
    "wof:placetype": "postalcode"
  },
  "geometry": {"coordinates":[-2.26939,51.824006],"type":"Point"}
}
