{
  "type": "Feature",
  "properties": {
    "iso:country":"GB",
    "wof:name":"GL2 2AR",
    "wof:placetype":"postalcode"
},
  "geometry": {"coordinates":[-2.26939035178586,51.82400583676588],"type":"Point"}
}