{
  "type": "Feature",
  "properties": {
    "iso:country":"GB",
    "wof:name":"BA2 6NX",
    "wof:placetype":"postalcode"
},
  "geometry": {"coordinates":[-2.35333084307573,51.38768547842923],"type":"Point"}
}