{
  "type": "Feature",
  "properties": {
    "date:inception_lower":"1980-01-01",
    "date:inception_upper":"1980-01-31",
    "iso:country":"GB",
    "wof:name":"BA2 6NX",
    "wof:placetype":"postalcode"
},
  "geometry": {"coordinates":[-2.353331,51.387685],"type":"Point"}
}