{
  "type": "Feature",
  "properties": {
    "iso:country": "GB",
    "wof:name": "BB7 9XS",
    "wof:placetype": "postalcode"
  },
  "geometry": {"coordinates":[-2.398347,53.837756],"type":"Point"}
}
