{
  "type": "Feature",
  "properties": {
    "date:inception_lower":"2015-06-01",
    "date:inception_upper":"2015-06-30",
    "iso:country":"GB",
    "wof:name":"BB7 9XS",
    "wof:placetype":"postalcode"
},
  "geometry": {"coordinates":[-2.398347,53.837756],"type":"Point"}
}