{
  "type": "Feature",
  "properties": {
    "iso:country":"GB",
    "wof:name":"EH42 1GY",
    "wof:placetype":"postalcode"
},
  "geometry": {"coordinates":[-2.51438059177883,56.00133374764991],"type":"Point"}
}