{
  "type": "Feature",
  "properties": {
    "iso:country": "GB",
    "wof:name": "EH42 1GY",
    "wof:placetype": "postalcode"
  },
  "geometry": {"coordinates":[-2.514381,56.001334],"type":"Point"}
}
