{
  "type": "Feature",
  "properties": {
    "iso:country": "GB",
    "wof:name": "GU9 9BL",
    "wof:placetype": "postalcode"
  },
  "geometry": {"coordinates":[-0.784745,51.23943],"type":"Point"}
}
