{
  "type": "Feature",
  "properties": {
    "iso:country":"GB",
    "wof:name":"GU9 9BL",
    "wof:placetype":"postalcode"
},
  "geometry": {"coordinates":[-0.78474457002478,51.23942984776858],"type":"Point"}
}