{
  "type": "Feature",
  "properties": {
    "date:inception_lower": "1997-12-01",
    "date:inception_upper": "1997-12-01",
    "iso:country": "GB",
    "wof:name": "GU9 9BL",
    "wof:placetype": "postalcode"
  },
  "geometry": {"coordinates":[-0.784745,51.23943],"type":"Point"}
}
