{
  "type": "Feature",
  "properties": {
    "iso:country":"GB",
    "wof:name":"AB53 5PR",
    "wof:placetype":"postalcode"
},
  "geometry": {"coordinates":[-2.40754052506792,57.58043326283497],"type":"Point"}
}