{
  "type": "Feature",
  "properties": {
    "iso:country": "GB",
    "wof:name": "AB53 5PR",
    "wof:placetype": "postalcode"
  },
  "geometry": {"coordinates":[-2.40754,57.580433],"type":"Point"}
}
