{
  "type": "Feature",
  "properties": {
    "date:inception_lower": "1996-06-01",
    "date:inception_upper": "1996-06-01",
    "iso:country": "GB",
    "wof:name": "AB15 8QB",
    "wof:placetype": "postalcode"
  },
  "geometry": {"coordinates":[-2.220259,57.138365],"type":"Point"}
}
