{
  "type": "Feature",
  "properties": {
    "iso:country":"GB",
    "wof:name":"SY3 5HH",
    "wof:placetype":"postalcode"
},
  "geometry": {"coordinates":[-2.80440160801387,52.71298898062949],"type":"Point"}
}