{
  "type": "Feature",
  "properties": {
    "date:inception_lower": "1990-02-01",
    "date:inception_upper": "1990-02-01",
    "iso:country": "GB",
    "wof:name": "SY3 5HH",
    "wof:placetype": "postalcode"
  },
  "geometry": {"coordinates":[-2.804402,52.712989],"type":"Point"}
}
