{
  "type": "Feature",
  "properties": {
    "iso:country": "GB",
    "wof:name": "PR6 9JW",
    "wof:placetype": "postalcode"
  },
  "geometry": {"coordinates":[-2.608084,53.624444],"type":"Point"}
}
