{
  "type": "Feature",
  "properties": {
    "iso:country":"GB",
    "wof:name":"PR6 9JW",
    "wof:placetype":"postalcode"
},
  "geometry": {"coordinates":[-2.6080839571088,53.62444378850826],"type":"Point"}
}