{
  "type": "Feature",
  "properties": {
    "iso:country": "GB",
    "wof:name": "NR19 1UR",
    "wof:placetype": "postalcode"
  },
  "geometry": {"coordinates":[0.927944,52.665025],"type":"Point"}
}
