{
  "type": "Feature",
  "properties": {
    "date:inception_lower":"1992-01-01",
    "date:inception_upper":"1992-01-31",
    "iso:country":"GB",
    "wof:name":"NR19 1UR",
    "wof:placetype":"postalcode"
},
  "geometry": {"coordinates":[0.927944,52.665025],"type":"Point"}
}