{
  "type": "Feature",
  "properties": {
    "iso:country":"GB",
    "wof:name":"UB3 1PS",
    "wof:placetype":"postalcode"
},
  "geometry": {"coordinates":[-0.44100170323649,51.50260139715406],"type":"Point"}
}