{
  "type": "Feature",
  "properties": {
    "date:inception_lower":"1980-01-01",
    "date:inception_upper":"1980-01-31",
    "iso:country":"GB",
    "wof:name":"UB3 1PS",
    "wof:placetype":"postalcode"
},
  "geometry": {"coordinates":[-0.441002,51.502601],"type":"Point"}
}