{
  "type": "Feature",
  "properties": {
    "iso:country":"GB",
    "wof:name":"B44 9AR",
    "wof:placetype":"postalcode"
},
  "geometry": {"coordinates":[-1.89000912237253,52.55188456705997],"type":"Point"}
}