{
  "type": "Feature",
  "properties": {
    "iso:country": "GB",
    "wof:name": "BS6 7DX",
    "wof:placetype": "postalcode"
  },
  "geometry": {"coordinates":[-2.599446,51.471044],"type":"Point"}
}
