{
  "type": "Feature",
  "properties": {
    "iso:country":"GB",
    "wof:name":"BS6 7DX",
    "wof:placetype":"postalcode"
},
  "geometry": {"coordinates":[-2.59944620936733,51.4710444088723],"type":"Point"}
}