{
  "type": "Feature",
  "properties": {
    "iso:country": "GB",
    "wof:name": "RM2 5NP",
    "wof:placetype": "postalcode"
  },
  "geometry": {"coordinates":[0.194553,51.58747],"type":"Point"}
}
