{
  "type": "Feature",
  "properties": {
    "iso:country": "GB",
    "wof:name": "IP24 2ZE",
    "wof:placetype": "postalcode"
  },
  "geometry": {"coordinates":[0.769306,52.416922],"type":"Point"}
}
