{
  "type": "Feature",
  "properties": {
    "date:inception_lower":"2013-12-01",
    "date:inception_upper":"2013-12-31",
    "iso:country":"GB",
    "wof:name":"IP24 2ZE",
    "wof:placetype":"postalcode"
},
  "geometry": {"coordinates":[0.769306,52.416922],"type":"Point"}
}