{
  "type": "Feature",
  "properties": {
    "iso:country":"GB",
    "wof:name":"IP24 2ZE",
    "wof:placetype":"postalcode"
},
  "geometry": {"coordinates":[0.76930635450591,52.41692156452351],"type":"Point"}
}