{
  "type": "Feature",
  "properties": {
    "iso:country": "GB",
    "wof:name": "EH22 2EL",
    "wof:placetype": "postalcode"
  },
  "geometry": {"coordinates":[-3.044587,55.896191],"type":"Point"}
}
