{
  "type": "Feature",
  "properties": {
    "date:inception_lower": "2017-06-01",
    "date:inception_upper": "2017-06-01",
    "iso:country": "GB",
    "wof:name": "EH22 2EL",
    "wof:placetype": "postalcode"
  },
  "geometry": {"coordinates":[-3.044587,55.896191],"type":"Point"}
}
