{
  "type": "Feature",
  "properties": {
    "iso:country": "GB",
    "wof:name": "BB1 2QU",
    "wof:placetype": "postalcode"
  },
  "geometry": {"coordinates":[-2.441652,53.730666],"type":"Point"}
}
