{
  "type": "Feature",
  "properties": {
    "date:inception_lower":"2005-05-01",
    "date:inception_upper":"2005-05-31",
    "iso:country":"GB",
    "wof:name":"BB1 2QU",
    "wof:placetype":"postalcode"
},
  "geometry": {"coordinates":[-2.441652,53.730666],"type":"Point"}
}