{
  "type": "Feature",
  "properties": {
    "date:inception_lower": "1980-01-01",
    "date:inception_upper": "1980-01-01",
    "iso:country": "GB",
    "wof:name": "BS10 7SF",
    "wof:placetype": "postalcode"
  },
  "geometry": {"coordinates":[-2.659657,51.532008],"type":"Point"}
}
