{
  "type": "Feature",
  "properties": {
    "iso:country":"GB",
    "wof:name":"G78 2QG",
    "wof:placetype":"postalcode"
},
  "geometry": {"coordinates":[-4.3767950069079,55.79409205336584],"type":"Point"}
}