{
  "type": "Feature",
  "properties": {
    "iso:country": "GB",
    "wof:name": "G78 2QG",
    "wof:placetype": "postalcode"
  },
  "geometry": {"coordinates":[-4.376795,55.794092],"type":"Point"}
}
