{
  "type": "Feature",
  "properties": {
    "date:inception_lower":"1990-02-01",
    "date:inception_upper":"1990-02-28",
    "iso:country":"GB",
    "wof:name":"NG34 8LY",
    "wof:placetype":"postalcode"
},
  "geometry": {"coordinates":[-0.422184,53.024316],"type":"Point"}
}