{
  "type": "Feature",
  "properties": {
    "date:inception_lower":"1994-05-01",
    "date:inception_upper":"1994-05-31",
    "iso:country":"GB",
    "wof:name":"BN1 1DP",
    "wof:placetype":"postalcode"
},
  "geometry": {"coordinates":[-0.138327,50.82186],"type":"Point"}
}