{
  "type": "Feature",
  "properties": {
    "iso:country":"GB",
    "wof:name":"BN1 1DP",
    "wof:placetype":"postalcode"
},
  "geometry": {"coordinates":[-0.13832687123774,50.82186011937868],"type":"Point"}
}