{
  "type": "Feature",
  "properties": {
    "date:inception_lower": "1980-01-01",
    "date:inception_upper": "1980-01-01",
    "iso:country": "GB",
    "wof:name": "GL18 1EB",
    "wof:placetype": "postalcode"
  },
  "geometry": {"coordinates":[-2.391872,51.940246],"type":"Point"}
}
