{
  "type": "Feature",
  "properties": {
    "iso:country":"GB",
    "wof:name":"CO2 8FQ",
    "wof:placetype":"postalcode"
},
  "geometry": {"coordinates":[0.92631928018339,51.8775556124988],"type":"Point"}
}