{
  "type": "Feature",
  "properties": {
    "date:inception_lower":"2008-03-01",
    "date:inception_upper":"2008-03-31",
    "iso:country":"GB",
    "wof:name":"CO2 8FQ",
    "wof:placetype":"postalcode"
},
  "geometry": {"coordinates":[0.926319,51.877556],"type":"Point"}
}