{
  "type": "Feature",
  "properties": {
    "iso:country":"GB",
    "wof:name":"N18 1AN",
    "wof:placetype":"postalcode"
},
  "geometry": {"coordinates":[-0.09443535611697,51.61269448259392],"type":"Point"}
}