{
  "type": "Feature",
  "properties": {
    "iso:country":"GB",
    "wof:name":"SG18 8QB",
    "wof:placetype":"postalcode"
},
  "geometry": {"coordinates":[-0.24096622279741,52.07482006884126],"type":"Point"}
}