{
  "type": "Feature",
  "properties": {
    "date:inception_lower": "1990-02-01",
    "date:inception_upper": "1990-02-01",
    "iso:country": "GB",
    "wof:name": "SG18 8QB",
    "wof:placetype": "postalcode"
  },
  "geometry": {"coordinates":[-0.240942,52.074831],"type":"Point"}
}
