{
  "type": "Feature",
  "properties": {
    "iso:country": "GB",
    "wof:name": "SG18 8QB",
    "wof:placetype": "postalcode"
  },
  "geometry": {"coordinates":[-0.240064,52.075258],"type":"Point"}
}
