{
  "type": "Feature",
  "properties": {
    "iso:country": "GB",
    "wof:name": "NE26 4HT",
    "wof:placetype": "postalcode"
  },
  "geometry": {"coordinates":[-1.482576,55.085963],"type":"Point"}
}
