{
  "type": "Feature",
  "properties": {
    "iso:country":"GB",
    "wof:name":"NE26 4HT",
    "wof:placetype":"postalcode"
},
  "geometry": {"coordinates":[-1.4825756495184,55.08596327519881],"type":"Point"}
}