{
  "type": "Feature",
  "properties": {
    "iso:country": "GB",
    "wof:name": "EX15 1RN",
    "wof:placetype": "postalcode"
  },
  "geometry": {"coordinates":[-3.375626,50.838247],"type":"Point"}
}
