{
  "type": "Feature",
  "properties": {
    "iso:country":"GB",
    "wof:name":"EX15 1RN",
    "wof:placetype":"postalcode"
},
  "geometry": {"coordinates":[-3.37561274308372,50.83825541396593],"type":"Point"}
}