{
  "type": "Feature",
  "properties": {
    "iso:country":"GB",
    "wof:name":"EC1Y 8RY",
    "wof:placetype":"postalcode"
},
  "geometry": {"coordinates":[-0.09264011730798,51.52281239219691],"type":"Point"}
}