{
  "type": "Feature",
  "properties": {
    "date:inception_lower": "1980-01-01",
    "date:inception_upper": "1980-01-01",
    "iso:country": "GB",
    "wof:name": "EC1Y 8RY",
    "wof:placetype": "postalcode"
  },
  "geometry": {"coordinates":[-0.09264,51.522812],"type":"Point"}
}
