{
  "type": "Feature",
  "properties": {
    "iso:country": "GB",
    "wof:name": "SK22 3AU",
    "wof:placetype": "postalcode"
  },
  "geometry": {"coordinates":[-2.022594,53.368649],"type":"Point"}
}
