{
  "type": "Feature",
  "properties": {
    "iso:country":"GB",
    "wof:name":"SK22 3AU",
    "wof:placetype":"postalcode"
},
  "geometry": {"coordinates":[-2.02259399513799,53.36864928170662],"type":"Point"}
}