{
  "type": "Feature",
  "properties": {
    "date:inception_lower": "2018-07-01",
    "date:inception_upper": "2018-07-01",
    "iso:country": "GB",
    "wof:name": "GL10 2BH",
    "wof:placetype": "postalcode"
  },
  "geometry": {"coordinates":[-2.284539,51.741787],"type":"Point"}
}
