{
  "type": "Feature",
  "properties": {
    "iso:country":"GB",
    "wof:name":"HA7 3BG",
    "wof:placetype":"postalcode"
},
  "geometry": {"coordinates":[-0.33349968827126,51.61592707707084],"type":"Point"}
}