{
  "type": "Feature",
  "properties": {
    "iso:country":"GB",
    "wof:name":"BS37 9TN",
    "wof:placetype":"postalcode"
},
  "geometry": {"coordinates":[-2.48208714487995,51.56036803097285],"type":"Point"}
}