{
  "type": "Feature",
  "properties": {
    "date:inception_lower": "1980-01-01",
    "date:inception_upper": "1980-01-01",
    "iso:country": "GB",
    "wof:name": "SG15 6UW",
    "wof:placetype": "postalcode"
  },
  "geometry": {"coordinates":[-0.263239,52.024376],"type":"Point"}
}
