{
  "type": "Feature",
  "properties": {
    "iso:country":"GB",
    "wof:name":"YO31 7UW",
    "wof:placetype":"postalcode"
},
  "geometry": {"coordinates":[-1.06955571280151,53.96292488100928],"type":"Point"}
}