{
  "type": "Feature",
  "properties": {
    "date:inception_lower": "2003-08-01",
    "date:inception_upper": "2003-08-01",
    "iso:country": "GB",
    "wof:name": "YO31 7UW",
    "wof:placetype": "postalcode"
  },
  "geometry": {"coordinates":[-1.069556,53.962925],"type":"Point"}
}
