{
  "type": "Feature",
  "properties": {
    "iso:country":"GB",
    "wof:name":"CV9 2EL",
    "wof:placetype":"postalcode"
},
  "geometry": {"coordinates":[-1.59649362296367,52.59016589363609],"type":"Point"}
}