{
  "type": "Feature",
  "properties": {
    "iso:country": "GB",
    "wof:name": "ME8 9DW",
    "wof:placetype": "postalcode"
  },
  "geometry": {"coordinates":[0.594803,51.353901],"type":"Point"}
}
