{
  "type": "Feature",
  "properties": {
    "iso:country":"GB",
    "wof:name":"ME8 9DW",
    "wof:placetype":"postalcode"
},
  "geometry": {"coordinates":[0.59480286437012,51.35390069904221],"type":"Point"}
}