{
  "type": "Feature",
  "properties": {
    "date:inception_lower":"1980-01-01",
    "date:inception_upper":"1980-01-31",
    "iso:country":"GB",
    "wof:name":"ME8 9DW",
    "wof:placetype":"postalcode"
},
  "geometry": {"coordinates":[0.594803,51.353901],"type":"Point"}
}