{
  "type": "Feature",
  "properties": {
    "iso:country":"GB",
    "wof:name":"SG12 9EL",
    "wof:placetype":"postalcode"
},
  "geometry": {"coordinates":[-0.03123706497346,51.81052666898056],"type":"Point"}
}