{
  "type": "Feature",
  "properties": {
    "date:inception_lower":"2013-01-01",
    "date:inception_upper":"2013-01-31",
    "iso:country":"GB",
    "wof:name":"SG12 9EL",
    "wof:placetype":"postalcode"
},
  "geometry": {"coordinates":[-0.031237,51.810527],"type":"Point"}
}