{
  "type": "Feature",
  "properties": {
    "iso:country":"GB",
    "wof:name":"AB53 5RT",
    "wof:placetype":"postalcode"
},
  "geometry": {"coordinates":[-2.38642641314546,57.60939619211825],"type":"Point"}
}