{
  "type": "Feature",
  "properties": {
    "iso:country":"GB",
    "wof:name":"SW9 8JS",
    "wof:placetype":"postalcode"
},
  "geometry": {"coordinates":[-0.1136609331174,51.4623535931482],"type":"Point"}
}