{
  "type": "Feature",
  "properties": {
    "date:inception_lower": "2020-12-01",
    "date:inception_upper": "2020-12-01",
    "iso:country": "GB",
    "wof:name": "DN14 7FE",
    "wof:placetype": "postalcode"
  },
  "geometry": {"coordinates":[-0.914066,53.744688],"type":"Point"}
}
