{
  "type": "Feature",
  "properties": {
    "iso:country": "GB",
    "wof:name": "IP21 4PE",
    "wof:placetype": "postalcode"
  },
  "geometry": {"coordinates":[1.211827,52.395857],"type":"Point"}
}
