{
  "type": "Feature",
  "properties": {
    "iso:country":"GB",
    "wof:name":"IP21 4PE",
    "wof:placetype":"postalcode"
},
  "geometry": {"coordinates":[1.21182755750539,52.39622259909101],"type":"Point"}
}