{
  "type": "Feature",
  "properties": {
    "iso:country":"GB",
    "wof:name":"PE29 7YD",
    "wof:placetype":"postalcode"
},
  "geometry": {"coordinates":[-0.18571866905647,52.34967953118922],"type":"Point"}
}