{
  "type": "Feature",
  "properties": {
    "iso:country":"GB",
    "wof:name":"DA1 1NJ",
    "wof:placetype":"postalcode"
},
  "geometry": {"coordinates":[0.22533592465663,51.43908784659329],"type":"Point"}
}