{
  "type": "Feature",
  "properties": {
    "date:inception_lower": "2018-01-01",
    "date:inception_upper": "2018-01-01",
    "iso:country": "GB",
    "wof:name": "CW4 8GH",
    "wof:placetype": "postalcode"
  },
  "geometry": {"coordinates":[-2.371058,53.217448],"type":"Point"}
}
