{
  "type": "Feature",
  "properties": {
    "iso:country": "GB",
    "wof:name": "LS9 8FW",
    "wof:placetype": "postalcode"
  },
  "geometry": {"coordinates":[-1.528094,53.794173],"type":"Point"}
}
