{
  "type": "Feature",
  "properties": {
    "iso:country":"GB",
    "wof:name":"BA21 4JA",
    "wof:placetype":"postalcode"
},
  "geometry": {"coordinates":[-2.62423880800277,50.94399101816149],"type":"Point"}
}