{
  "type": "Feature",
  "properties": {
    "iso:country":"GB",
    "wof:name":"NG7 5PJ",
    "wof:placetype":"postalcode"
},
  "geometry": {"coordinates":[-1.18031781203475,52.96814020798988],"type":"Point"}
}