{
  "type": "Feature",
  "properties": {
    "iso:country":"GB",
    "wof:name":"IG8 0PB",
    "wof:placetype":"postalcode"
},
  "geometry": {"coordinates":[0.03184784462356,51.61628669746367],"type":"Point"}
}