{
  "type": "Feature",
  "properties": {
    "iso:country":"GB",
    "wof:name":"LL30 1HT",
    "wof:placetype":"postalcode"
},
  "geometry": {"coordinates":[-3.83144614649304,53.31287254830293],"type":"Point"}
}