{
  "type": "Feature",
  "properties": {
    "iso:country":"GB",
    "wof:name":"LN2 1AP",
    "wof:placetype":"postalcode"
},
  "geometry": {"coordinates":[-0.53980058081009,53.22877194868625],"type":"Point"}
}