{
  "type": "Feature",
  "properties": {
    "date:inception_lower": "2021-12-01",
    "date:inception_upper": "2021-12-01",
    "iso:country": "GB",
    "wof:name": "OL15 9AW",
    "wof:placetype": "postalcode"
  },
  "geometry": {"coordinates":[-2.082877,53.663125],"type":"Point"}
}
