{
  "type": "Feature",
  "properties": {
    "iso:country":"GB",
    "wof:name":"EX16 8RR",
    "wof:placetype":"postalcode"
},
  "geometry": {"coordinates":[-3.52419326078424,50.84813571318484],"type":"Point"}
}