{
  "type": "Feature",
  "properties": {
    "iso:country": "GB",
    "wof:name": "B70 6BW",
    "wof:placetype": "postalcode"
  },
  "geometry": {"coordinates":[-1.991043,52.506806],"type":"Point"}
}
