{
  "type": "Feature",
  "properties": {
    "date:inception_lower": "1981-09-01",
    "date:inception_upper": "1981-09-01",
    "iso:country": "GB",
    "wof:name": "B70 6BW",
    "wof:placetype": "postalcode"
  },
  "geometry": {"coordinates":[-1.991043,52.506806],"type":"Point"}
}
