{
  "type": "Feature",
  "properties": {
    "iso:country":"GB",
    "wof:name":"LE4 7RR",
    "wof:placetype":"postalcode"
},
  "geometry": {"coordinates":[-1.10050648362476,52.66771948152044],"type":"Point"}
}