{
  "type": "Feature",
  "properties": {
    "iso:country":"GB",
    "wof:name":"OL6 9LF",
    "wof:placetype":"postalcode"
},
  "geometry": {"coordinates":[-2.08348455417778,53.49587244063349],"type":"Point"}
}