{
  "type": "Feature",
  "properties": {
    "iso:country":"GB",
    "wof:name":"ME7 4DP",
    "wof:placetype":"postalcode"
},
  "geometry": {"coordinates":[0.55767554940195,51.38332630253856],"type":"Point"}
}