{
  "type": "Feature",
  "properties": {
    "date:inception_lower": "1980-01-01",
    "date:inception_upper": "1980-01-01",
    "iso:country": "GB",
    "wof:name": "SY11 1NQ",
    "wof:placetype": "postalcode"
  },
  "geometry": {"coordinates":[-3.053141,52.863014],"type":"Point"}
}
