{
  "type": "Feature",
  "properties": {
    "date:inception_lower":"1980-01-01",
    "date:inception_upper":"1980-01-31",
    "iso:country":"GB",
    "wof:name":"GL18 1AA",
    "wof:placetype":"postalcode"
},
  "geometry": {"coordinates":[-2.402904,51.931039],"type":"Point"}
}