{
  "type": "Feature",
  "properties": {
    "date:inception_lower": "1980-01-01",
    "date:inception_upper": "1980-01-01",
    "iso:country": "GB",
    "wof:name": "CT1 3PQ",
    "wof:placetype": "postalcode"
  },
  "geometry": {"coordinates":[1.089837,51.271495],"type":"Point"}
}
