{
  "type": "Feature",
  "properties": {
    "iso:country":"GB",
    "wof:name":"B45 9EJ",
    "wof:placetype":"postalcode"
},
  "geometry": {"coordinates":[-2.02996142234821,52.39034580293266],"type":"Point"}
}