{
  "type": "Feature",
  "properties": {
    "iso:country": "GB",
    "wof:name": "KY14 7RE",
    "wof:placetype": "postalcode"
  },
  "geometry": {"coordinates":[-3.27134,56.275501],"type":"Point"}
}
