{
  "type": "Feature",
  "properties": {
    "date:inception_lower": "1991-07-01",
    "date:inception_upper": "1991-07-01",
    "iso:country": "GB",
    "wof:name": "KY14 7RE",
    "wof:placetype": "postalcode"
  },
  "geometry": {"coordinates":[-3.27134,56.275501],"type":"Point"}
}
