{
  "type": "Feature",
  "properties": {
    "iso:country":"GB",
    "wof:name":"B23 5UE",
    "wof:placetype":"postalcode"
},
  "geometry": {"coordinates":[-1.83175627095007,52.53194862976913],"type":"Point"}
}