{
  "type": "Feature",
  "properties": {
    "date:inception_lower":"2008-01-01",
    "date:inception_upper":"2008-01-31",
    "iso:country":"GB",
    "wof:name":"SP4 7QA",
    "wof:placetype":"postalcode"
},
  "geometry": {"coordinates":[-1.759449,51.174435],"type":"Point"}
}