{
  "type": "Feature",
  "properties": {
    "iso:country":"GB",
    "wof:name":"SP4 7QA",
    "wof:placetype":"postalcode"
},
  "geometry": {"coordinates":[-1.75944868936444,51.17443486793499],"type":"Point"}
}