{
  "type": "Feature",
  "properties": {
    "iso:country":"GB",
    "wof:name":"TW13 5EG",
    "wof:placetype":"postalcode"
},
  "geometry": {"coordinates":[-0.39058525275026,51.44128537697267],"type":"Point"}
}