{
  "type": "Feature",
  "properties": {
    "date:inception_lower": "1997-12-01",
    "date:inception_upper": "1997-12-01",
    "iso:country": "GB",
    "wof:name": "BH2 5BX",
    "wof:placetype": "postalcode"
  },
  "geometry": {"coordinates":[-1.879643,50.71826],"type":"Point"}
}
