{
  "type": "Feature",
  "properties": {
    "iso:country":"GB",
    "wof:name":"SP4 7RB",
    "wof:placetype":"postalcode"
},
  "geometry": {"coordinates":[-1.77283239149154,51.1696868454972],"type":"Point"}
}