{
  "type": "Feature",
  "properties": {
    "iso:country":"GB",
    "wof:name":"SL4 4LB",
    "wof:placetype":"postalcode"
},
  "geometry": {"coordinates":[-0.6519599863686,51.47831131453606],"type":"Point"}
}