{
  "type": "Feature",
  "properties": {
    "iso:country":"GB",
    "wof:name":"DN3 2PH",
    "wof:placetype":"postalcode"
},
  "geometry": {"coordinates":[-1.07431625486228,53.55426062094153],"type":"Point"}
}