{
  "type": "Feature",
  "properties": {
    "date:inception_lower": "1980-01-01",
    "date:inception_upper": "1980-01-01",
    "iso:country": "GB",
    "wof:name": "DN3 2PH",
    "wof:placetype": "postalcode"
  },
  "geometry": {"coordinates":[-1.074316,53.554261],"type":"Point"}
}
