{
  "type": "Feature",
  "properties": {
    "iso:country":"GB",
    "wof:name":"EN1 2RS",
    "wof:placetype":"postalcode"
},
  "geometry": {"coordinates":[-0.07269266101132,51.63838158279336],"type":"Point"}
}