{
  "type": "Feature",
  "properties": {
    "iso:country":"GB",
    "wof:name":"KW17 2SE",
    "wof:placetype":"postalcode"
},
  "geometry": {"coordinates":[-2.91171342422263,58.89713327140457],"type":"Point"}
}