{
  "type": "Feature",
  "properties": {
    "iso:country":"GB",
    "wof:name":"W9 3TE",
    "wof:placetype":"postalcode"
},
  "geometry": {"coordinates":[-0.19458391182332,51.52206975568054],"type":"Point"}
}