{
  "type": "Feature",
  "properties": {
    "date:inception_lower": "1992-08-01",
    "date:inception_upper": "1992-08-01",
    "iso:country": "GB",
    "wof:name": "W9 3TE",
    "wof:placetype": "postalcode"
  },
  "geometry": {"coordinates":[-0.194584,51.52207],"type":"Point"}
}
