{
  "type": "Feature",
  "properties": {
    "date:inception_lower": "1993-08-01",
    "date:inception_upper": "1993-08-01",
    "iso:country": "GB",
    "wof:name": "RG24 8UN",
    "wof:placetype": "postalcode"
  },
  "geometry": {"coordinates":[-1.054605,51.277718],"type":"Point"}
}
