{
  "type": "Feature",
  "properties": {
    "iso:country":"GB",
    "wof:name":"RG24 8UN",
    "wof:placetype":"postalcode"
},
  "geometry": {"coordinates":[-1.05460513996361,51.27771763657306],"type":"Point"}
}