{
  "type": "Feature",
  "properties": {
    "iso:country":"GB",
    "wof:name":"CO9 4JL",
    "wof:placetype":"postalcode"
},
  "geometry": {"coordinates":[0.56816829043369,52.02847834278358],"type":"Point"}
}