{
  "type": "Feature",
  "properties": {
    "iso:country":"GB",
    "wof:name":"SO18 4ES",
    "wof:placetype":"postalcode"
},
  "geometry": {"coordinates":[-1.36456632198955,50.91819709980961],"type":"Point"}
}