{
  "type": "Feature",
  "properties": {
    "date:inception_lower": "1980-01-01",
    "date:inception_upper": "1980-01-01",
    "iso:country": "GB",
    "wof:name": "SS5 6JU",
    "wof:placetype": "postalcode"
  },
  "geometry": {"coordinates":[0.60528,51.625328],"type":"Point"}
}
