{
  "type": "Feature",
  "properties": {
    "iso:country": "GB",
    "wof:name": "SS5 6JU",
    "wof:placetype": "postalcode"
  },
  "geometry": {"coordinates":[0.60528,51.625328],"type":"Point"}
}
