{
  "type": "Feature",
  "properties": {
    "iso:country":"GB",
    "wof:name":"BL0 9DF",
    "wof:placetype":"postalcode"
},
  "geometry": {"coordinates":[-2.31782498097713,53.63739554843513],"type":"Point"}
}