{
  "type": "Feature",
  "properties": {
    "iso:country": "GB",
    "wof:name": "BL0 9DF",
    "wof:placetype": "postalcode"
  },
  "geometry": {"coordinates":[-2.317825,53.637396],"type":"Point"}
}
