{
  "type": "Feature",
  "properties": {
    "iso:country":"GB",
    "wof:name":"KW15 1XS",
    "wof:placetype":"postalcode"
},
  "geometry": {"coordinates":[-2.94546442032135,58.97067905470807],"type":"Point"}
}