{
  "type": "Feature",
  "properties": {
    "iso:country":"GB",
    "wof:name":"OX4 6NN",
    "wof:placetype":"postalcode"
},
  "geometry": {"coordinates":[-1.21140366984102,51.72383028786327],"type":"Point"}
}