{
  "type": "Feature",
  "properties": {
    "date:inception_lower":"2000-06-01",
    "date:inception_upper":"2000-06-30",
    "iso:country":"GB",
    "wof:name":"OX4 6NN",
    "wof:placetype":"postalcode"
},
  "geometry": {"coordinates":[-1.211404,51.72383],"type":"Point"}
}