{
  "type": "Feature",
  "properties": {
    "iso:country":"GB",
    "wof:name":"B62 8HZ",
    "wof:placetype":"postalcode"
},
  "geometry": {"coordinates":[-2.03721577448103,52.4716046369224],"type":"Point"}
}