{
  "type": "Feature",
  "properties": {
    "iso:country": "GB",
    "wof:name": "PH8 0HQ",
    "wof:placetype": "postalcode"
  },
  "geometry": {"coordinates":[-3.508521,56.576378],"type":"Point"}
}
