{
  "type": "Feature",
  "properties": {
    "date:inception_lower":"1980-01-01",
    "date:inception_upper":"1980-01-31",
    "iso:country":"GB",
    "wof:name":"PH8 0HQ",
    "wof:placetype":"postalcode"
},
  "geometry": {"coordinates":[-3.508521,56.576378],"type":"Point"}
}