{
  "type": "Feature",
  "properties": {
    "iso:country":"GB",
    "wof:name":"TW9 4DD",
    "wof:placetype":"postalcode"
},
  "geometry": {"coordinates":[-0.28259898260977,51.47762922235506],"type":"Point"}
}