{
  "type": "Feature",
  "properties": {
    "date:inception_lower": "1980-01-01",
    "date:inception_upper": "1980-01-01",
    "iso:country": "GB",
    "wof:name": "KA6 7SS",
    "wof:placetype": "postalcode"
  },
  "geometry": {"coordinates":[-4.394699,55.314406],"type":"Point"}
}
