{
  "type": "Feature",
  "properties": {
    "iso:country":"GB",
    "wof:name":"BD17 6DZ",
    "wof:placetype":"postalcode"
},
  "geometry": {"coordinates":[-1.75905600335295,53.84876866905032],"type":"Point"}
}