{
  "type": "Feature",
  "properties": {
    "iso:country":"GB",
    "wof:name":"CF62 7LY",
    "wof:placetype":"postalcode"
},
  "geometry": {"coordinates":[-3.29562393595866,51.40704063619543],"type":"Point"}
}