{
  "type": "Feature",
  "properties": {
    "iso:country":"GB",
    "wof:name":"TS3 0PG",
    "wof:placetype":"postalcode"
},
  "geometry": {"coordinates":[-1.18272103919957,54.55191112078083],"type":"Point"}
}