{
  "type": "Feature",
  "properties": {
    "iso:country": "GB",
    "wof:name": "NN17 1DE",
    "wof:placetype": "postalcode"
  },
  "geometry": {"coordinates":[-0.683335,52.499466],"type":"Point"}
}
