{
  "type": "Feature",
  "properties": {
    "iso:country": "GB",
    "wof:name": "G64 3BB",
    "wof:placetype": "postalcode"
  },
  "geometry": {"coordinates":[-4.23461,55.915016],"type":"Point"}
}
