{
  "type": "Feature",
  "properties": {
    "date:inception_lower": "1987-04-01",
    "date:inception_upper": "1987-04-01",
    "iso:country": "GB",
    "wof:name": "HU8 7TQ",
    "wof:placetype": "postalcode"
  },
  "geometry": {"coordinates":[-0.321594,53.760246],"type":"Point"}
}
