{
  "type": "Feature",
  "properties": {
    "date:inception_lower": "1980-01-01",
    "date:inception_upper": "1980-01-01",
    "iso:country": "GB",
    "wof:name": "SA12 9DW",
    "wof:placetype": "postalcode"
  },
  "geometry": {"coordinates":[-3.754503,51.617505],"type":"Point"}
}
