{
  "type": "Feature",
  "properties": {
    "iso:country":"GB",
    "wof:name":"SA12 9DW",
    "wof:placetype":"postalcode"
},
  "geometry": {"coordinates":[-3.75450323458917,51.61750543582109],"type":"Point"}
}