{
  "type": "Feature",
  "properties": {
    "iso:country":"GB",
    "wof:name":"WN8 6QN",
    "wof:placetype":"postalcode"
},
  "geometry": {"coordinates":[-2.77896909143569,53.56376961217351],"type":"Point"}
}