{
  "type": "Feature",
  "properties": {
    "date:inception_lower": "1980-01-01",
    "date:inception_upper": "1980-01-01",
    "iso:country": "GB",
    "wof:name": "TW15 1DG",
    "wof:placetype": "postalcode"
  },
  "geometry": {"coordinates":[-0.454287,51.433132],"type":"Point"}
}
