{
  "type": "Feature",
  "properties": {
    "iso:country":"GB",
    "wof:name":"TW15 1DG",
    "wof:placetype":"postalcode"
},
  "geometry": {"coordinates":[-0.45428667852819,51.43313230195835],"type":"Point"}
}