{
  "type": "Feature",
  "properties": {
    "iso:country":"GB",
    "wof:name":"NE25 9EQ",
    "wof:placetype":"postalcode"
},
  "geometry": {"coordinates":[-1.46655016720924,55.03053918152816],"type":"Point"}
}