{
  "type": "Feature",
  "properties": {
    "iso:country": "GB",
    "wof:name": "CW5 6JG",
    "wof:placetype": "postalcode"
  },
  "geometry": {"coordinates":[-2.508636,53.068927],"type":"Point"}
}
