{
  "type": "Feature",
  "properties": {
    "iso:country": "GB",
    "wof:name": "RM7 7JX",
    "wof:placetype": "postalcode"
  },
  "geometry": {"coordinates":[0.168643,51.580865],"type":"Point"}
}
