{
  "type": "Feature",
  "properties": {
    "iso:country":"GB",
    "wof:name":"RM7 7JX",
    "wof:placetype":"postalcode"
},
  "geometry": {"coordinates":[0.16861540293579,51.5808449346309],"type":"Point"}
}