{
  "type": "Feature",
  "properties": {
    "iso:country": "GB",
    "wof:name": "AB53 8RF",
    "wof:placetype": "postalcode"
  },
  "geometry": {"coordinates":[-2.38839,57.432551],"type":"Point"}
}
