{
  "type": "Feature",
  "properties": {
    "date:inception_lower": "1996-06-01",
    "date:inception_upper": "1996-06-01",
    "iso:country": "GB",
    "wof:name": "AB53 8RF",
    "wof:placetype": "postalcode"
  },
  "geometry": {"coordinates":[-2.38839,57.432551],"type":"Point"}
}
