{
  "type": "Feature",
  "properties": {
    "iso:country":"GB",
    "wof:name":"M22 8HR",
    "wof:placetype":"postalcode"
},
  "geometry": {"coordinates":[-2.26914020172351,53.39008195202693],"type":"Point"}
}