{
  "type": "Feature",
  "properties": {
    "iso:country":"GB",
    "wof:name":"S8 8TG",
    "wof:placetype":"postalcode"
},
  "geometry": {"coordinates":[-1.47906049646155,53.34795646396604],"type":"Point"}
}