{
  "type": "Feature",
  "properties": {
    "iso:country": "GB",
    "wof:name": "SE22 9AU",
    "wof:placetype": "postalcode"
  },
  "geometry": {"coordinates":[-0.071276,51.46241],"type":"Point"}
}
