{
  "type": "Feature",
  "properties": {
    "iso:country":"GB",
    "wof:name":"SE22 9AU",
    "wof:placetype":"postalcode"
},
  "geometry": {"coordinates":[-0.07127649206101,51.46241035732801],"type":"Point"}
}