{
  "type": "Feature",
  "properties": {
    "date:inception_lower": "1990-02-01",
    "date:inception_upper": "1990-02-01",
    "iso:country": "GB",
    "wof:name": "CF3 0HW",
    "wof:placetype": "postalcode"
  },
  "geometry": {"coordinates":[-3.097266,51.521474],"type":"Point"}
}
