{
  "type": "Feature",
  "properties": {
    "date:inception_lower":"2001-12-01",
    "date:inception_upper":"2001-12-31",
    "iso:country":"GB",
    "wof:name":"MK10 9GY",
    "wof:placetype":"postalcode"
},
  "geometry": {"coordinates":[-0.701789,52.037009],"type":"Point"}
}