{
  "type": "Feature",
  "properties": {
    "iso:country":"GB",
    "wof:name":"MK10 9GY",
    "wof:placetype":"postalcode"
},
  "geometry": {"coordinates":[-0.7017890292348,52.03700925321685],"type":"Point"}
}