{
  "type": "Feature",
  "properties": {
    "iso:country": "GB",
    "wof:name": "PE25 3JU",
    "wof:placetype": "postalcode"
  },
  "geometry": {"coordinates":[0.341426,53.139991],"type":"Point"}
}
