{
  "type": "Feature",
  "properties": {
    "date:inception_lower":"1981-06-01",
    "date:inception_upper":"1981-06-30",
    "iso:country":"GB",
    "wof:name":"NE8 4HU",
    "wof:placetype":"postalcode"
},
  "geometry": {"coordinates":[-1.602841,54.951559],"type":"Point"}
}