{
  "type": "Feature",
  "properties": {
    "iso:country":"GB",
    "wof:name":"WN7 4EB",
    "wof:placetype":"postalcode"
},
  "geometry": {"coordinates":[-2.52556581324325,53.49701033847084],"type":"Point"}
}