{
  "type": "Feature",
  "properties": {
    "iso:country": "GB",
    "wof:name": "BA22 8AL",
    "wof:placetype": "postalcode"
  },
  "geometry": {"coordinates":[-2.674815,50.942289],"type":"Point"}
}
