{
  "type": "Feature",
  "properties": {
    "iso:country":"GB",
    "wof:name":"BA22 8AL",
    "wof:placetype":"postalcode"
},
  "geometry": {"coordinates":[-2.67481541118464,50.94228880554701],"type":"Point"}
}