{
  "type": "Feature",
  "properties": {
    "date:inception_lower": "2009-01-01",
    "date:inception_upper": "2009-01-01",
    "iso:country": "GB",
    "wof:name": "BA22 8AL",
    "wof:placetype": "postalcode"
  },
  "geometry": {"coordinates":[-2.674815,50.942289],"type":"Point"}
}
