{
  "type": "Feature",
  "properties": {
    "iso:country":"GB",
    "wof:name":"AB45 2HN",
    "wof:placetype":"postalcode"
},
  "geometry": {"coordinates":[-2.73138092571841,57.59000382793226],"type":"Point"}
}