{
  "type": "Feature",
  "properties": {
    "iso:country": "GB",
    "wof:name": "DL1 4RT",
    "wof:placetype": "postalcode"
  },
  "geometry": {"coordinates":[-1.524478,54.512208],"type":"Point"}
}
