{
  "type": "Feature",
  "properties": {
    "iso:country":"GB",
    "wof:name":"CV6 3HJ",
    "wof:placetype":"postalcode"
},
  "geometry": {"coordinates":[-1.51149246631096,52.42589537150193],"type":"Point"}
}