{
  "type": "Feature",
  "properties": {
    "iso:country": "GB",
    "wof:name": "CV6 3HJ",
    "wof:placetype": "postalcode"
  },
  "geometry": {"coordinates":[-1.511492,52.425895],"type":"Point"}
}
