{
  "type": "Feature",
  "properties": {
    "date:inception_lower":"2007-09-01",
    "date:inception_upper":"2007-09-30",
    "iso:country":"GB",
    "wof:name":"CV6 3HJ",
    "wof:placetype":"postalcode"
},
  "geometry": {"coordinates":[-1.511492,52.425895],"type":"Point"}
}