{
  "type": "Feature",
  "properties": {
    "iso:country":"GB",
    "wof:name":"CB22 5DU",
    "wof:placetype":"postalcode"
},
  "geometry": {"coordinates":[0.14492362925739,52.14704583569189],"type":"Point"}
}