{
  "type": "Feature",
  "properties": {
    "iso:country":"GB",
    "wof:name":"IG2 6QG",
    "wof:placetype":"postalcode"
},
  "geometry": {"coordinates":[0.08279065906904,51.57452212215053],"type":"Point"}
}