{
  "type": "Feature",
  "properties": {
    "date:inception_lower":"1986-07-01",
    "date:inception_upper":"1986-07-31",
    "iso:country":"GB",
    "wof:name":"IG2 6QG",
    "wof:placetype":"postalcode"
},
  "geometry": {"coordinates":[0.083032,51.575057],"type":"Point"}
}