{
  "type": "Feature",
  "properties": {
    "iso:country":"GB",
    "wof:name":"M9 8PA",
    "wof:placetype":"postalcode"
},
  "geometry": {"coordinates":[-2.23409466620079,53.53304583371319],"type":"Point"}
}