{
  "type": "Feature",
  "properties": {
    "iso:country":"GB",
    "wof:name":"IP14 2LU",
    "wof:placetype":"postalcode"
},
  "geometry": {"coordinates":[0.94747419107036,52.14593450718748],"type":"Point"}
}