{
  "type": "Feature",
  "properties": {
    "date:inception_lower": "1980-01-01",
    "date:inception_upper": "1980-01-01",
    "iso:country": "GB",
    "wof:name": "IP14 2LU",
    "wof:placetype": "postalcode"
  },
  "geometry": {"coordinates":[0.94752,52.145941],"type":"Point"}
}
