{
  "type": "Feature",
  "properties": {
    "iso:country":"GB",
    "wof:name":"GU52 6HJ",
    "wof:placetype":"postalcode"
},
  "geometry": {"coordinates":[-0.84040139631334,51.26551437367367],"type":"Point"}
}