{
  "type": "Feature",
  "properties": {
    "date:inception_lower":"2001-06-01",
    "date:inception_upper":"2001-06-30",
    "iso:country":"GB",
    "wof:name":"GU52 6HJ",
    "wof:placetype":"postalcode"
},
  "geometry": {"coordinates":[-0.840401,51.265514],"type":"Point"}
}