{
  "type": "Feature",
  "properties": {
    "iso:country": "GB",
    "wof:name": "GU52 6HJ",
    "wof:placetype": "postalcode"
  },
  "geometry": {"coordinates":[-0.840401,51.265514],"type":"Point"}
}
