{
  "type": "Feature",
  "properties": {
    "iso:country": "GB",
    "wof:name": "IV2 3TZ",
    "wof:placetype": "postalcode"
  },
  "geometry": {"coordinates":[-4.19457,57.481002],"type":"Point"}
}
