{
  "type": "Feature",
  "properties": {
    "date:inception_lower": "1980-01-01",
    "date:inception_upper": "1980-01-01",
    "iso:country": "GB",
    "wof:name": "DE6 1PY",
    "wof:placetype": "postalcode"
  },
  "geometry": {"coordinates":[-1.662019,53.049455],"type":"Point"}
}
