{
  "type": "Feature",
  "properties": {
    "iso:country":"GB",
    "wof:name":"BD23 3TJ",
    "wof:placetype":"postalcode"
},
  "geometry": {"coordinates":[-2.14393704885442,53.93215064199512],"type":"Point"}
}