{
  "type": "Feature",
  "properties": {
    "date:inception_lower": "1992-01-01",
    "date:inception_upper": "1992-01-01",
    "iso:country": "GB",
    "wof:name": "PE3 9TF",
    "wof:placetype": "postalcode"
  },
  "geometry": {"coordinates":[-0.289146,52.582309],"type":"Point"}
}
