{
  "type": "Feature",
  "properties": {
    "iso:country": "GB",
    "wof:name": "BN7 3PB",
    "wof:placetype": "postalcode"
  },
  "geometry": {"coordinates":[-0.023572,50.855947],"type":"Point"}
}
