{
  "type": "Feature",
  "properties": {
    "iso:country":"GB",
    "wof:name":"PL5 1JJ",
    "wof:placetype":"postalcode"
},
  "geometry": {"coordinates":[-4.18869088733238,50.40185878960772],"type":"Point"}
}