{
  "type": "Feature",
  "properties": {
    "iso:country": "GB",
    "wof:name": "PL5 1JJ",
    "wof:placetype": "postalcode"
  },
  "geometry": {"coordinates":[-4.188691,50.401859],"type":"Point"}
}
