{
  "type": "Feature",
  "properties": {
    "iso:country":"GB",
    "wof:name":"BH20 9ZG",
    "wof:placetype":"postalcode"
},
  "geometry": {"coordinates":[-2.10639225568463,50.69657322420834],"type":"Point"}
}