{
  "type": "Feature",
  "properties": {
    "date:inception_lower":"2016-03-01",
    "date:inception_upper":"2016-03-31",
    "iso:country":"GB",
    "wof:name":"BH20 9ZG",
    "wof:placetype":"postalcode"
},
  "geometry": {"coordinates":[-2.106392,50.696573],"type":"Point"}
}