{
  "type": "Feature",
  "properties": {
    "iso:country": "GB",
    "wof:name": "OX13 5HJ",
    "wof:placetype": "postalcode"
  },
  "geometry": {"coordinates":[-1.432018,51.676833],"type":"Point"}
}
