{
  "type": "Feature",
  "properties": {
    "date:inception_lower": "1980-01-01",
    "date:inception_upper": "1980-01-01",
    "iso:country": "GB",
    "wof:name": "OX13 5HJ",
    "wof:placetype": "postalcode"
  },
  "geometry": {"coordinates":[-1.430448,51.676294],"type":"Point"}
}
