{
  "type": "Feature",
  "properties": {
    "iso:country": "GB",
    "wof:name": "OX13 5HJ",
    "wof:placetype": "postalcode"
  },
  "geometry": {"coordinates":[-1.432611,51.674647],"type":"Point"}
}
