{
  "type": "Feature",
  "properties": {
    "iso:country": "GB",
    "wof:name": "MK7 7AF",
    "wof:placetype": "postalcode"
  },
  "geometry": {"coordinates":[-0.698914,52.021036],"type":"Point"}
}
