{
  "type": "Feature",
  "properties": {
    "iso:country":"GB",
    "wof:name":"SA14 8AN",
    "wof:placetype":"postalcode"
},
  "geometry": {"coordinates":[-4.14353103636231,51.69506272107252],"type":"Point"}
}