{
  "type": "Feature",
  "properties": {
    "date:inception_lower": "1980-01-01",
    "date:inception_upper": "1980-01-01",
    "iso:country": "GB",
    "wof:name": "SA14 8AN",
    "wof:placetype": "postalcode"
  },
  "geometry": {"coordinates":[-4.143531,51.695063],"type":"Point"}
}
