{
  "type": "Feature",
  "properties": {
    "date:inception_lower":"1981-06-01",
    "date:inception_upper":"1981-06-30",
    "iso:country":"GB",
    "wof:name":"B32 4JU",
    "wof:placetype":"postalcode"
},
  "geometry": {"coordinates":[-2.011619,52.428818],"type":"Point"}
}