{
  "type": "Feature",
  "properties": {
    "iso:country":"GB",
    "wof:name":"B32 4JU",
    "wof:placetype":"postalcode"
},
  "geometry": {"coordinates":[-2.01161863975844,52.42881756059206],"type":"Point"}
}