{
  "type": "Feature",
  "properties": {
    "iso:country": "GB",
    "wof:name": "B32 4JU",
    "wof:placetype": "postalcode"
  },
  "geometry": {"coordinates":[-2.011619,52.428818],"type":"Point"}
}
