{
  "type": "Feature",
  "properties": {
    "iso:country": "GB",
    "wof:name": "DE11 0FP",
    "wof:placetype": "postalcode"
  },
  "geometry": {"coordinates":[-1.567833,52.774992],"type":"Point"}
}
