{
  "type": "Feature",
  "properties": {
    "date:inception_lower":"2007-09-01",
    "date:inception_upper":"2007-09-30",
    "iso:country":"GB",
    "wof:name":"KA27 8NG",
    "wof:placetype":"postalcode"
},
  "geometry": {"coordinates":[-5.133401,55.530273],"type":"Point"}
}