{
  "type": "Feature",
  "properties": {
    "date:inception_lower": "2020-04-01",
    "date:inception_upper": "2020-04-01",
    "iso:country": "GB",
    "wof:name": "S64 0FA",
    "wof:placetype": "postalcode"
  },
  "geometry": {"coordinates":[-1.284527,53.491669],"type":"Point"}
}
