{
  "type": "Feature",
  "properties": {
    "date:inception_lower": "1980-01-01",
    "date:inception_upper": "1980-01-01",
    "iso:country": "GB",
    "wof:name": "SY10 8AQ",
    "wof:placetype": "postalcode"
  },
  "geometry": {"coordinates":[-3.058804,52.810086],"type":"Point"}
}
