{
  "type": "Feature",
  "properties": {
    "iso:country":"GB",
    "wof:name":"SY10 8AQ",
    "wof:placetype":"postalcode"
},
  "geometry": {"coordinates":[-3.05880422711037,52.81008566571319],"type":"Point"}
}