{
  "type": "Feature",
  "properties": {
    "iso:country": "GB",
    "wof:name": "SY10 8AQ",
    "wof:placetype": "postalcode"
  },
  "geometry": {"coordinates":[-3.058804,52.810086],"type":"Point"}
}
