{
  "type": "Feature",
  "properties": {
    "iso:country":"GB",
    "wof:name":"BS20 8BT",
    "wof:placetype":"postalcode"
},
  "geometry": {"coordinates":[-2.7939788384671,51.48163134628764],"type":"Point"}
}