{
  "type": "Feature",
  "properties": {
    "date:inception_lower":"1980-01-01",
    "date:inception_upper":"1980-01-31",
    "iso:country":"GB",
    "wof:name":"BS20 8BT",
    "wof:placetype":"postalcode"
},
  "geometry": {"coordinates":[-2.793979,51.481631],"type":"Point"}
}