{
  "type": "Feature",
  "properties": {
    "date:inception_lower": "1980-01-01",
    "date:inception_upper": "1980-01-01",
    "iso:country": "GB",
    "wof:name": "NR20 3EE",
    "wof:placetype": "postalcode"
  },
  "geometry": {"coordinates":[1.039834,52.71155],"type":"Point"}
}
