{
  "type": "Feature",
  "properties": {
    "iso:country":"GB",
    "wof:name":"NR20 3EE",
    "wof:placetype":"postalcode"
},
  "geometry": {"coordinates":[1.03983396620285,52.71155000587628],"type":"Point"}
}