{
  "type": "Feature",
  "properties": {
    "iso:country": "GB",
    "wof:name": "BA20 1QH",
    "wof:placetype": "postalcode"
  },
  "geometry": {"coordinates":[-2.633945,50.940703],"type":"Point"}
}
