{
  "type": "Feature",
  "properties": {
    "date:inception_lower": "2016-08-01",
    "date:inception_upper": "2016-08-01",
    "iso:country": "GB",
    "wof:name": "BA20 1QH",
    "wof:placetype": "postalcode"
  },
  "geometry": {"coordinates":[-2.633945,50.940703],"type":"Point"}
}
