{
  "type": "Feature",
  "properties": {
    "iso:country":"GB",
    "wof:name":"LE2 1FQ",
    "wof:placetype":"postalcode"
},
  "geometry": {"coordinates":[-1.11564564455247,52.62757623527496],"type":"Point"}
}