{
  "type": "Feature",
  "properties": {
    "iso:country":"GB",
    "wof:name":"HX6 3EB",
    "wof:placetype":"postalcode"
},
  "geometry": {"coordinates":[-1.94166024520218,53.69148130423888],"type":"Point"}
}