{
  "type": "Feature",
  "properties": {
    "iso:country":"GB",
    "wof:name":"GL9 1BU",
    "wof:placetype":"postalcode"
},
  "geometry": {"coordinates":[-2.35678649340709,51.58952564322667],"type":"Point"}
}