{
  "type": "Feature",
  "properties": {
    "iso:country":"GB",
    "wof:name":"M41 9NU",
    "wof:placetype":"postalcode"
},
  "geometry": {"coordinates":[-2.32881090415115,53.44550875332973],"type":"Point"}
}