{
  "type": "Feature",
  "properties": {
    "date:inception_lower": "1996-12-01",
    "date:inception_upper": "1996-12-01",
    "iso:country": "GB",
    "wof:name": "NG15 8GX",
    "wof:placetype": "postalcode"
  },
  "geometry": {"coordinates":[-1.204485,53.049964],"type":"Point"}
}
