{
  "type": "Feature",
  "properties": {
    "iso:country":"GB",
    "wof:name":"UB2 5RX",
    "wof:placetype":"postalcode"
},
  "geometry": {"coordinates":[-0.38009012816368,51.4942943975154],"type":"Point"}
}