{
  "type": "Feature",
  "properties": {
    "date:inception_lower": "1988-03-01",
    "date:inception_upper": "1988-03-01",
    "iso:country": "GB",
    "wof:name": "SS16 6SB",
    "wof:placetype": "postalcode"
  },
  "geometry": {"coordinates":[0.406537,51.566925],"type":"Point"}
}
