{
  "type": "Feature",
  "properties": {
    "iso:country":"GB",
    "wof:name":"SS16 6SB",
    "wof:placetype":"postalcode"
},
  "geometry": {"coordinates":[0.40653688170767,51.56692514086537],"type":"Point"}
}