{
  "type": "Feature",
  "properties": {
    "iso:country": "GB",
    "wof:name": "LL12 0TT",
    "wof:placetype": "postalcode"
  },
  "geometry": {"coordinates":[-2.994575,53.094668],"type":"Point"}
}
