{
  "type": "Feature",
  "properties": {
    "iso:country":"GB",
    "wof:name":"LL12 0TT",
    "wof:placetype":"postalcode"
},
  "geometry": {"coordinates":[-2.99457539062842,53.09466806282987],"type":"Point"}
}