{
  "type": "Feature",
  "properties": {
    "iso:country":"GB",
    "wof:name":"TS5 4AJ",
    "wof:placetype":"postalcode"
},
  "geometry": {"coordinates":[-1.26228407352167,54.56725986015412],"type":"Point"}
}