{
  "type": "Feature",
  "properties": {
    "date:inception_lower":"1980-01-01",
    "date:inception_upper":"1980-01-31",
    "iso:country":"GB",
    "wof:name":"N13 6HH",
    "wof:placetype":"postalcode"
},
  "geometry": {"coordinates":[-0.098598,51.612969],"type":"Point"}
}