{
  "type": "Feature",
  "properties": {
    "iso:country":"GB",
    "wof:name":"N13 6HH",
    "wof:placetype":"postalcode"
},
  "geometry": {"coordinates":[-0.09859809710693,51.61296881157503],"type":"Point"}
}