{
  "type": "Feature",
  "properties": {
    "iso:country":"GB",
    "wof:name":"CT12 5LB",
    "wof:placetype":"postalcode"
},
  "geometry": {"coordinates":[1.36937349765193,51.32949034911981],"type":"Point"}
}