{
  "type": "Feature",
  "properties": {
    "date:inception_lower": "2004-10-01",
    "date:inception_upper": "2004-10-01",
    "iso:country": "GB",
    "wof:name": "CT12 5LB",
    "wof:placetype": "postalcode"
  },
  "geometry": {"coordinates":[1.369374,51.32949],"type":"Point"}
}
