{
  "type": "Feature",
  "properties": {
    "iso:country": "GB",
    "wof:name": "TS24 7LZ",
    "wof:placetype": "postalcode"
  },
  "geometry": {"coordinates":[-1.202448,54.681869],"type":"Point"}
}
