{
  "type": "Feature",
  "properties": {
    "iso:country":"GB",
    "wof:name":"L20 0DL",
    "wof:placetype":"postalcode"
},
  "geometry": {"coordinates":[-2.97425590729059,53.46015368621656],"type":"Point"}
}