{
  "type": "Feature",
  "properties": {
    "date:inception_lower": "1980-01-01",
    "date:inception_upper": "1980-01-01",
    "iso:country": "GB",
    "wof:name": "LU6 3PN",
    "wof:placetype": "postalcode"
  },
  "geometry": {"coordinates":[-0.517818,51.873181],"type":"Point"}
}
