{
  "type": "Feature",
  "properties": {
    "iso:country":"GB",
    "wof:name":"LU6 3PN",
    "wof:placetype":"postalcode"
},
  "geometry": {"coordinates":[-0.51781761770965,51.87318090703843],"type":"Point"}
}