{
  "type": "Feature",
  "properties": {
    "iso:country":"GB",
    "wof:name":"SN13 8AQ",
    "wof:placetype":"postalcode"
},
  "geometry": {"coordinates":[-2.26515109614325,51.41502814767075],"type":"Point"}
}