{
  "type": "Feature",
  "properties": {
    "date:inception_lower": "1995-07-01",
    "date:inception_upper": "1995-07-01",
    "iso:country": "GB",
    "wof:name": "SN13 8AQ",
    "wof:placetype": "postalcode"
  },
  "geometry": {"coordinates":[-2.265151,51.415028],"type":"Point"}
}
