{
  "type": "Feature",
  "properties": {
    "iso:country": "GB",
    "wof:name": "NR21 0AR",
    "wof:placetype": "postalcode"
  },
  "geometry": {"coordinates":[0.843702,52.867321],"type":"Point"}
}
