{
  "type": "Feature",
  "properties": {
    "iso:country":"GB",
    "wof:name":"NN6 0BA",
    "wof:placetype":"postalcode"
},
  "geometry": {"coordinates":[-0.80095172440729,52.29391466627318],"type":"Point"}
}