{
  "type": "Feature",
  "properties": {
    "iso:country":"GB",
    "wof:name":"WN7 3PN",
    "wof:placetype":"postalcode"
},
  "geometry": {"coordinates":[-2.54492085365632,53.47818251835368],"type":"Point"}
}