{
  "type": "Feature",
  "properties": {
    "date:inception_lower": "2005-12-01",
    "date:inception_upper": "2005-12-01",
    "iso:country": "GB",
    "wof:name": "SA2 0RP",
    "wof:placetype": "postalcode"
  },
  "geometry": {"coordinates":[-3.969847,51.62309],"type":"Point"}
}
