{
  "type": "Feature",
  "properties": {
    "iso:country":"GB",
    "wof:name":"SA2 0RP",
    "wof:placetype":"postalcode"
},
  "geometry": {"coordinates":[-3.96984666580161,51.62308985190342],"type":"Point"}
}