{
  "type": "Feature",
  "properties": {
    "date:inception_lower": "1995-07-01",
    "date:inception_upper": "1995-07-01",
    "iso:country": "GB",
    "wof:name": "NG15 8AA",
    "wof:placetype": "postalcode"
  },
  "geometry": {"coordinates":[-1.203068,53.048157],"type":"Point"}
}
