{
  "type": "Feature",
  "properties": {
    "iso:country":"GB",
    "wof:name":"NG15 8AA",
    "wof:placetype":"postalcode"
},
  "geometry": {"coordinates":[-1.20219385978798,53.04802489240831],"type":"Point"}
}