{
  "type": "Feature",
  "properties": {
    "date:inception_lower":"2015-07-01",
    "date:inception_upper":"2015-07-31",
    "iso:country":"GB",
    "wof:name":"WN7 1BN",
    "wof:placetype":"postalcode"
},
  "geometry": {"coordinates":[-2.512742,53.496086],"type":"Point"}
}