{
  "type": "Feature",
  "properties": {
    "iso:country": "GB",
    "wof:name": "WN7 1BN",
    "wof:placetype": "postalcode"
  },
  "geometry": {"coordinates":[-2.512742,53.496086],"type":"Point"}
}
