{
  "type": "Feature",
  "properties": {
    "date:inception_lower": "1999-12-01",
    "date:inception_upper": "1999-12-01",
    "iso:country": "GB",
    "wof:name": "S65 3HD",
    "wof:placetype": "postalcode"
  },
  "geometry": {"coordinates":[-1.317779,53.441751],"type":"Point"}
}
