{
  "type": "Feature",
  "properties": {
    "iso:country":"GB",
    "wof:name":"LL12 9HF",
    "wof:placetype":"postalcode"
},
  "geometry": {"coordinates":[-3.05565881100506,53.10948678808263],"type":"Point"}
}