{
  "type": "Feature",
  "properties": {
    "iso:country": "GB",
    "wof:name": "BS6 6SD",
    "wof:placetype": "postalcode"
  },
  "geometry": {"coordinates":[-2.610092,51.46831],"type":"Point"}
}
