{
  "type": "Feature",
  "properties": {
    "iso:country":"GB",
    "wof:name":"BS6 6SD",
    "wof:placetype":"postalcode"
},
  "geometry": {"coordinates":[-2.61009245331047,51.46830997651072],"type":"Point"}
}