{
  "type": "Feature",
  "properties": {
    "iso:country": "GB",
    "wof:name": "PR3 0BZ",
    "wof:placetype": "postalcode"
  },
  "geometry": {"coordinates":[-2.880028,53.859673],"type":"Point"}
}
