{
  "type": "Feature",
  "properties": {
    "date:inception_lower": "2002-09-01",
    "date:inception_upper": "2002-09-01",
    "iso:country": "GB",
    "wof:name": "CA17 4SW",
    "wof:placetype": "postalcode"
  },
  "geometry": {"coordinates":[-2.353986,54.466834],"type":"Point"}
}
