{
  "type": "Feature",
  "properties": {
    "iso:country":"GB",
    "wof:name":"SY20 8RB",
    "wof:placetype":"postalcode"
},
  "geometry": {"coordinates":[-3.75416356887744,52.56127640968267],"type":"Point"}
}