{
  "type": "Feature",
  "properties": {
    "iso:country": "GB",
    "wof:name": "YO41 1LL",
    "wof:placetype": "postalcode"
  },
  "geometry": {"coordinates":[-0.944826,54.016695],"type":"Point"}
}
