{
  "type": "Feature",
  "properties": {
    "iso:country":"GB",
    "wof:name":"YO41 1LL",
    "wof:placetype":"postalcode"
},
  "geometry": {"coordinates":[-0.94482594623786,54.01669512572606],"type":"Point"}
}