{
  "type": "Feature",
  "properties": {
    "iso:country":"GB",
    "wof:name":"N1 5LP",
    "wof:placetype":"postalcode"
},
  "geometry": {"coordinates":[-0.07851566272836,51.53473979803105],"type":"Point"}
}