{
  "type": "Feature",
  "properties": {
    "iso:country":"GB",
    "wof:name":"W1K 5SS",
    "wof:placetype":"postalcode"
},
  "geometry": {"coordinates":[-0.14697768493434,51.51340496853699],"type":"Point"}
}