{
  "type": "Feature",
  "properties": {
    "date:inception_lower": "1980-01-01",
    "date:inception_upper": "1980-01-01",
    "iso:country": "GB",
    "wof:name": "UB7 8AP",
    "wof:placetype": "postalcode"
  },
  "geometry": {"coordinates":[-0.470897,51.520736],"type":"Point"}
}
