{
  "type": "Feature",
  "properties": {
    "date:inception_lower": "1980-01-01",
    "date:inception_upper": "1980-01-01",
    "iso:country": "GB",
    "wof:name": "W6 9RN",
    "wof:placetype": "postalcode"
  },
  "geometry": {"coordinates":[-0.226678,51.488847],"type":"Point"}
}
