{
  "type": "Feature",
  "properties": {
    "iso:country":"GB",
    "wof:name":"BN18 0EZ",
    "wof:placetype":"postalcode"
},
  "geometry": {"coordinates":[-0.61172482064067,50.81925334765264],"type":"Point"}
}