{
  "type": "Feature",
  "properties": {
    "iso:country": "GB",
    "wof:name": "CT14 9XP",
    "wof:placetype": "postalcode"
  },
  "geometry": {"coordinates":[1.387592,51.213556],"type":"Point"}
}
