{
  "type": "Feature",
  "properties": {
    "iso:country": "GB",
    "wof:name": "SO50 5NL",
    "wof:placetype": "postalcode"
  },
  "geometry": {"coordinates":[-1.355573,50.963947],"type":"Point"}
}
