{
  "type": "Feature",
  "properties": {
    "iso:country":"GB",
    "wof:name":"SO50 5NL",
    "wof:placetype":"postalcode"
},
  "geometry": {"coordinates":[-1.35554200242794,50.96388323504052],"type":"Point"}
}