{
  "type": "Feature",
  "properties": {
    "date:inception_lower":"1980-01-01",
    "date:inception_upper":"1980-01-31",
    "iso:country":"GB",
    "wof:name":"CO12 4DY",
    "wof:placetype":"postalcode"
},
  "geometry": {"coordinates":[1.26462,51.933155],"type":"Point"}
}