{
  "type": "Feature",
  "properties": {
    "iso:country":"GB",
    "wof:name":"CO12 4DY",
    "wof:placetype":"postalcode"
},
  "geometry": {"coordinates":[1.26462037524759,51.93315541379632],"type":"Point"}
}