{
  "type": "Feature",
  "properties": {
    "iso:country":"GB",
    "wof:name":"RG31 7BE",
    "wof:placetype":"postalcode"
},
  "geometry": {"coordinates":[-1.05820720636665,51.43866657216338],"type":"Point"}
}