{
  "type": "Feature",
  "properties": {
    "iso:country":"GB",
    "wof:name":"HU3 6SW",
    "wof:placetype":"postalcode"
},
  "geometry": {"coordinates":[-0.38175483385331,53.74298732993613],"type":"Point"}
}