{
  "type": "Feature",
  "properties": {
    "date:inception_lower": "2022-02-01",
    "date:inception_upper": "2022-02-01",
    "iso:country": "GB",
    "wof:name": "TA4 3FB",
    "wof:placetype": "postalcode"
  },
  "geometry": {"coordinates":[-3.182211,51.052878],"type":"Point"}
}
