{
  "type": "Feature",
  "properties": {
    "date:inception_lower": "1980-01-01",
    "date:inception_upper": "1980-01-01",
    "iso:country": "GB",
    "wof:name": "CF33 4EF",
    "wof:placetype": "postalcode"
  },
  "geometry": {"coordinates":[-3.696566,51.518723],"type":"Point"}
}
