{
  "type": "Feature",
  "properties": {
    "iso:country": "GB",
    "wof:name": "CF33 4EF",
    "wof:placetype": "postalcode"
  },
  "geometry": {"coordinates":[-3.696566,51.518723],"type":"Point"}
}
