{
  "type": "Feature",
  "properties": {
    "iso:country":"GB",
    "wof:name":"CF33 4EF",
    "wof:placetype":"postalcode"
},
  "geometry": {"coordinates":[-3.69656619762745,51.51872313074816],"type":"Point"}
}