{
  "type": "Feature",
  "properties": {
    "iso:country": "GB",
    "wof:name": "NR32 4PU",
    "wof:placetype": "postalcode"
  },
  "geometry": {"coordinates":[1.732704,52.49506],"type":"Point"}
}
