{
  "type": "Feature",
  "properties": {
    "iso:country": "GB",
    "wof:name": "NP4 7TR",
    "wof:placetype": "postalcode"
  },
  "geometry": {"coordinates":[-3.066222,51.722426],"type":"Point"}
}
