{
  "type": "Feature",
  "properties": {
    "iso:country":"GB",
    "wof:name":"NP4 7TR",
    "wof:placetype":"postalcode"
},
  "geometry": {"coordinates":[-3.06622154282618,51.72242623932456],"type":"Point"}
}