{
  "type": "Feature",
  "properties": {
    "date:inception_lower":"2010-09-01",
    "date:inception_upper":"2010-09-30",
    "iso:country":"GB",
    "wof:name":"NP4 7TR",
    "wof:placetype":"postalcode"
},
  "geometry": {"coordinates":[-3.066222,51.722426],"type":"Point"}
}