{
  "type": "Feature",
  "properties": {
    "date:inception_lower": "2015-01-01",
    "date:inception_upper": "2015-01-01",
    "iso:country": "GB",
    "wof:name": "CH34 9UF",
    "wof:placetype": "postalcode"
  },
  "geometry": {"coordinates":[-2.903251,53.277392],"type":"Point"}
}
