{
  "type": "Feature",
  "properties": {
    "iso:country":"GB",
    "wof:name":"SY2 5NT",
    "wof:placetype":"postalcode"
},
  "geometry": {"coordinates":[-2.7211088733656,52.70595555545085],"type":"Point"}
}