{
  "type": "Feature",
  "properties": {
    "date:inception_lower": "1980-01-01",
    "date:inception_upper": "1980-01-01",
    "iso:country": "GB",
    "wof:name": "SY2 5NT",
    "wof:placetype": "postalcode"
  },
  "geometry": {"coordinates":[-2.721109,52.705956],"type":"Point"}
}
