{
  "type": "Feature",
  "properties": {
    "iso:country": "GB",
    "wof:name": "BS16 5US",
    "wof:placetype": "postalcode"
  },
  "geometry": {"coordinates":[-2.513791,51.485791],"type":"Point"}
}
