{
  "type": "Feature",
  "properties": {
    "iso:country":"GB",
    "wof:name":"PO11 9JD",
    "wof:placetype":"postalcode"
},
  "geometry": {"coordinates":[-0.97505063828636,50.78489852212429],"type":"Point"}
}