{
  "type": "Feature",
  "properties": {
    "iso:country": "GB",
    "wof:name": "WR3 8EJ",
    "wof:placetype": "postalcode"
  },
  "geometry": {"coordinates":[-2.208849,52.206638],"type":"Point"}
}
