{
  "type": "Feature",
  "properties": {
    "date:inception_lower": "2005-04-01",
    "date:inception_upper": "2005-04-01",
    "iso:country": "GB",
    "wof:name": "TF9 3FD",
    "wof:placetype": "postalcode"
  },
  "geometry": {"coordinates":[-2.490453,52.906801],"type":"Point"}
}
