{
  "type": "Feature",
  "properties": {
    "iso:country":"GB",
    "wof:name":"IG6 1JU",
    "wof:placetype":"postalcode"
},
  "geometry": {"coordinates":[0.07086009226543,51.58224217500922],"type":"Point"}
}