{
  "type": "Feature",
  "properties": {
    "date:inception_lower":"2000-06-01",
    "date:inception_upper":"2000-06-30",
    "iso:country":"GB",
    "wof:name":"BB9 7NJ",
    "wof:placetype":"postalcode"
},
  "geometry": {"coordinates":[-2.214869,53.83814],"type":"Point"}
}