{
  "type": "Feature",
  "properties": {
    "date:inception_lower": "2007-07-01",
    "date:inception_upper": "2007-07-01",
    "iso:country": "GB",
    "wof:name": "ME14 4FB",
    "wof:placetype": "postalcode"
  },
  "geometry": {"coordinates":[0.574904,51.272326],"type":"Point"}
}
