{
  "type": "Feature",
  "properties": {
    "iso:country":"GB",
    "wof:name":"ME14 4FB",
    "wof:placetype":"postalcode"
},
  "geometry": {"coordinates":[0.57490432039465,51.27232611846095],"type":"Point"}
}