{
  "type": "Feature",
  "properties": {
    "iso:country":"GB",
    "wof:name":"ME7 3QJ",
    "wof:placetype":"postalcode"
},
  "geometry": {"coordinates":[0.56935022781731,51.34362457645],"type":"Point"}
}