{
  "type": "Feature",
  "properties": {
    "iso:country":"GB",
    "wof:name":"NN11 4RX",
    "wof:placetype":"postalcode"
},
  "geometry": {"coordinates":[-1.16837652256758,52.24759788154589],"type":"Point"}
}