{
  "type": "Feature",
  "properties": {
    "date:inception_lower": "1981-06-01",
    "date:inception_upper": "1981-06-01",
    "iso:country": "GB",
    "wof:name": "NN11 4RX",
    "wof:placetype": "postalcode"
  },
  "geometry": {"coordinates":[-1.168376,52.247598],"type":"Point"}
}
