{
  "type": "Feature",
  "properties": {
    "date:inception_lower": "1980-01-01",
    "date:inception_upper": "1980-01-01",
    "iso:country": "GB",
    "wof:name": "SS2 6NQ",
    "wof:placetype": "postalcode"
  },
  "geometry": {"coordinates":[0.702066,51.549265],"type":"Point"}
}
