{
  "type": "Feature",
  "properties": {
    "iso:country":"GB",
    "wof:name":"SS2 6NQ",
    "wof:placetype":"postalcode"
},
  "geometry": {"coordinates":[0.70206619683555,51.54926544905697],"type":"Point"}
}