{
  "type": "Feature",
  "properties": {
    "iso:country":"GB",
    "wof:name":"PA15 4EH",
    "wof:placetype":"postalcode"
},
  "geometry": {"coordinates":[-4.76465423520133,55.94341521080807],"type":"Point"}
}