{
  "type": "Feature",
  "properties": {
    "date:inception_lower": "1980-01-01",
    "date:inception_upper": "1980-01-01",
    "iso:country": "GB",
    "wof:name": "ST4 6PS",
    "wof:placetype": "postalcode"
  },
  "geometry": {"coordinates":[-2.208141,52.992518],"type":"Point"}
}
