{
  "type": "Feature",
  "properties": {
    "iso:country": "GB",
    "wof:name": "ST4 6PS",
    "wof:placetype": "postalcode"
  },
  "geometry": {"coordinates":[-2.208141,52.992518],"type":"Point"}
}
