{
  "type": "Feature",
  "properties": {
    "iso:country":"GB",
    "wof:name":"ST4 6PS",
    "wof:placetype":"postalcode"
},
  "geometry": {"coordinates":[-2.20814094059438,52.9925175195216],"type":"Point"}
}