{
  "type": "Feature",
  "properties": {
    "date:inception_lower": "2023-05-01",
    "date:inception_upper": "2023-05-01",
    "iso:country": "GB",
    "wof:name": "RG40 5SP",
    "wof:placetype": "postalcode"
  },
  "geometry": {"coordinates":[-0.829401,51.421797],"type":"Point"}
}
