{
  "type": "Feature",
  "properties": {
    "date:inception_lower": "1980-01-01",
    "date:inception_upper": "1980-01-01",
    "iso:country": "GB",
    "wof:name": "S81 0QF",
    "wof:placetype": "postalcode"
  },
  "geometry": {"coordinates":[-1.106961,53.313231],"type":"Point"}
}
