{
  "type": "Feature",
  "properties": {
    "iso:country":"GB",
    "wof:name":"S81 0QF",
    "wof:placetype":"postalcode"
},
  "geometry": {"coordinates":[-1.10696067016131,53.31323081032556],"type":"Point"}
}