{
  "type": "Feature",
  "properties": {
    "iso:country":"GB",
    "wof:name":"DL16 7AB",
    "wof:placetype":"postalcode"
},
  "geometry": {"coordinates":[-1.61618678648642,54.692476099089],"type":"Point"}
}