{
  "type": "Feature",
  "properties": {
    "iso:country": "GB",
    "wof:name": "SE15 3AH",
    "wof:placetype": "postalcode"
  },
  "geometry": {"coordinates":[-0.05206,51.457623],"type":"Point"}
}
