{
  "type": "Feature",
  "properties": {
    "iso:country":"GB",
    "wof:name":"G20 8LP",
    "wof:placetype":"postalcode"
},
  "geometry": {"coordinates":[-4.28490356807952,55.88339161981652],"type":"Point"}
}