{
  "type": "Feature",
  "properties": {
    "iso:country": "GB",
    "wof:name": "ST3 7YH",
    "wof:placetype": "postalcode"
  },
  "geometry": {"coordinates":[-2.104026,52.976994],"type":"Point"}
}
