{
  "type": "Feature",
  "properties": {
    "date:inception_lower": "1980-01-01",
    "date:inception_upper": "1980-01-01",
    "iso:country": "GB",
    "wof:name": "EH4 6AL",
    "wof:placetype": "postalcode"
  },
  "geometry": {"coordinates":[-3.280563,55.966715],"type":"Point"}
}
