{
  "type": "Feature",
  "properties": {
    "iso:country":"GB",
    "wof:name":"SW15 6NN",
    "wof:placetype":"postalcode"
},
  "geometry": {"coordinates":[-0.22834323654481,51.46038379928323],"type":"Point"}
}