{
  "type": "Feature",
  "properties": {
    "date:inception_lower": "1994-05-01",
    "date:inception_upper": "1994-05-01",
    "iso:country": "GB",
    "wof:name": "M34 7LL",
    "wof:placetype": "postalcode"
  },
  "geometry": {"coordinates":[-2.103147,53.436686],"type":"Point"}
}
