{
  "type": "Feature",
  "properties": {
    "iso:country": "GB",
    "wof:name": "HR3 6AB",
    "wof:placetype": "postalcode"
  },
  "geometry": {"coordinates":[-3.005095,52.069971],"type":"Point"}
}
