{
  "type": "Feature",
  "properties": {
    "iso:country":"GB",
    "wof:name":"HR3 6AB",
    "wof:placetype":"postalcode"
},
  "geometry": {"coordinates":[-3.00509505826392,52.06997079987968],"type":"Point"}
}