{
  "type": "Feature",
  "properties": {
    "iso:country": "GB",
    "wof:name": "BD7 2LT",
    "wof:placetype": "postalcode"
  },
  "geometry": {"coordinates":[-1.790011,53.787049],"type":"Point"}
}
