{
  "type": "Feature",
  "properties": {
    "iso:country":"GB",
    "wof:name":"BD7 2LT",
    "wof:placetype":"postalcode"
},
  "geometry": {"coordinates":[-1.79009936399572,53.78698087875067],"type":"Point"}
}