{
  "type": "Feature",
  "properties": {
    "iso:country": "GB",
    "wof:name": "ML12 6XW",
    "wof:placetype": "postalcode"
  },
  "geometry": {"coordinates":[-3.753183,55.377543],"type":"Point"}
}
