{
  "type": "Feature",
  "properties": {
    "date:inception_lower":"1980-01-01",
    "date:inception_upper":"1980-01-31",
    "iso:country":"GB",
    "wof:name":"ML12 6XW",
    "wof:placetype":"postalcode"
},
  "geometry": {"coordinates":[-3.753183,55.377543],"type":"Point"}
}