{
  "type": "Feature",
  "properties": {
    "iso:country":"GB",
    "wof:name":"ML12 6XW",
    "wof:placetype":"postalcode"
},
  "geometry": {"coordinates":[-3.75318326174006,55.37754330099702],"type":"Point"}
}