{
  "type": "Feature",
  "properties": {
    "date:inception_lower": "1980-01-01",
    "date:inception_upper": "1980-01-01",
    "iso:country": "GB",
    "wof:name": "LL12 0EH",
    "wof:placetype": "postalcode"
  },
  "geometry": {"coordinates":[-2.93694,53.11155],"type":"Point"}
}
