{
  "type": "Feature",
  "properties": {
    "iso:country":"GB",
    "wof:name":"N4 2BS",
    "wof:placetype":"postalcode"
},
  "geometry": {"coordinates":[-0.08980275687483,51.57130783684856],"type":"Point"}
}