{
  "type": "Feature",
  "properties": {
    "iso:country": "GB",
    "wof:name": "FK3 0LY",
    "wof:placetype": "postalcode"
  },
  "geometry": {"coordinates":[-3.711549,56.007015],"type":"Point"}
}
