{
  "type": "Feature",
  "properties": {
    "date:inception_lower": "1980-01-01",
    "date:inception_upper": "1980-01-01",
    "iso:country": "GB",
    "wof:name": "B48 7TT",
    "wof:placetype": "postalcode"
  },
  "geometry": {"coordinates":[-1.953719,52.37067],"type":"Point"}
}
