{
  "type": "Feature",
  "properties": {
    "iso:country":"GB",
    "wof:name":"B48 7TT",
    "wof:placetype":"postalcode"
},
  "geometry": {"coordinates":[-1.95371873070319,52.37067034818249],"type":"Point"}
}