{
  "type": "Feature",
  "properties": {
    "iso:country": "GB",
    "wof:name": "PO22 6JB",
    "wof:placetype": "postalcode"
  },
  "geometry": {"coordinates":[-0.602731,50.792365],"type":"Point"}
}
