{
  "type": "Feature",
  "properties": {
    "iso:country": "GB",
    "wof:name": "CM9 6AN",
    "wof:placetype": "postalcode"
  },
  "geometry": {"coordinates":[0.673963,51.725813],"type":"Point"}
}
