{
  "type": "Feature",
  "properties": {
    "date:inception_lower":"1980-01-01",
    "date:inception_upper":"1980-01-31",
    "iso:country":"GB",
    "wof:name":"GL6 8LJ",
    "wof:placetype":"postalcode"
},
  "geometry": {"coordinates":[-2.145,51.725796],"type":"Point"}
}