{
  "type": "Feature",
  "properties": {
    "iso:country":"GB",
    "wof:name":"TQ1 1EQ",
    "wof:placetype":"postalcode"
},
  "geometry": {"coordinates":[-3.51633686064171,50.46201708567795],"type":"Point"}
}