{
  "type": "Feature",
  "properties": {
    "date:inception_lower": "1980-01-01",
    "date:inception_upper": "1980-01-01",
    "iso:country": "GB",
    "wof:name": "FY1 5EN",
    "wof:placetype": "postalcode"
  },
  "geometry": {"coordinates":[-3.046607,53.808751],"type":"Point"}
}
