{
  "type": "Feature",
  "properties": {
    "date:inception_lower":"2009-02-01",
    "date:inception_upper":"2009-02-28",
    "iso:country":"GB",
    "wof:name":"NR18 0AF",
    "wof:placetype":"postalcode"
},
  "geometry": {"coordinates":[1.113879,52.567921],"type":"Point"}
}