{
  "type": "Feature",
  "properties": {
    "iso:country": "GB",
    "wof:name": "CH1 6QQ",
    "wof:placetype": "postalcode"
  },
  "geometry": {"coordinates":[-2.944302,53.186335],"type":"Point"}
}
