{
  "type": "Feature",
  "properties": {
    "iso:country": "GB",
    "wof:name": "NE8 3PS",
    "wof:placetype": "postalcode"
  },
  "geometry": {"coordinates":[-1.586451,54.9542],"type":"Point"}
}
