{
  "type": "Feature",
  "properties": {
    "iso:country":"GB",
    "wof:name":"SG5 2UT",
    "wof:placetype":"postalcode"
},
  "geometry": {"coordinates":[-0.28643001872677,51.96168268894922],"type":"Point"}
}