{
  "type": "Feature",
  "properties": {
    "date:inception_lower": "1980-01-01",
    "date:inception_upper": "1980-01-01",
    "iso:country": "GB",
    "wof:name": "MK43 8TE",
    "wof:placetype": "postalcode"
  },
  "geometry": {"coordinates":[-0.573421,52.105657],"type":"Point"}
}
