{
  "type": "Feature",
  "properties": {
    "date:inception_lower": "1980-01-01",
    "date:inception_upper": "1980-01-01",
    "iso:country": "GB",
    "wof:name": "MK42 0PT",
    "wof:placetype": "postalcode"
  },
  "geometry": {"coordinates":[-0.45401,52.122263],"type":"Point"}
}
