{
  "type": "Feature",
  "properties": {
    "iso:country":"GB",
    "wof:name":"SK7 2BR",
    "wof:placetype":"postalcode"
},
  "geometry": {"coordinates":[-2.16915914660641,53.36236505030068],"type":"Point"}
}