{
  "type": "Feature",
  "properties": {
    "iso:country":"GB",
    "wof:name":"NE36 0TG",
    "wof:placetype":"postalcode"
},
  "geometry": {"coordinates":[-1.42650337083663,54.94261466803145],"type":"Point"}
}