{
  "type": "Feature",
  "properties": {
    "date:inception_lower": "1980-01-01",
    "date:inception_upper": "1980-01-01",
    "iso:country": "GB",
    "wof:name": "NE36 0TG",
    "wof:placetype": "postalcode"
  },
  "geometry": {"coordinates":[-1.426503,54.942615],"type":"Point"}
}
