{
  "type": "Feature",
  "properties": {
    "iso:country": "GB",
    "wof:name": "DL12 8UX",
    "wof:placetype": "postalcode"
  },
  "geometry": {"coordinates":[-1.854904,54.532026],"type":"Point"}
}
