{
  "type": "Feature",
  "properties": {
    "iso:country":"GB",
    "wof:name":"DL12 8UX",
    "wof:placetype":"postalcode"
},
  "geometry": {"coordinates":[-1.85480264699077,54.53199884366082],"type":"Point"}
}