{
  "type": "Feature",
  "properties": {
    "date:inception_lower": "1980-01-01",
    "date:inception_upper": "1980-01-01",
    "iso:country": "GB",
    "wof:name": "DL12 8UX",
    "wof:placetype": "postalcode"
  },
  "geometry": {"coordinates":[-1.854904,54.532026],"type":"Point"}
}
