{
  "type": "Feature",
  "properties": {
    "iso:country": "GB",
    "wof:name": "NG13 8UA",
    "wof:placetype": "postalcode"
  },
  "geometry": {"coordinates":[-0.937565,52.949975],"type":"Point"}
}
