{
  "type": "Feature",
  "properties": {
    "iso:country":"GB",
    "wof:name":"SY4 3NA",
    "wof:placetype":"postalcode"
},
  "geometry": {"coordinates":[-2.77617017761175,52.77118823427745],"type":"Point"}
}