{
  "type": "Feature",
  "properties": {
    "date:inception_lower": "1980-01-01",
    "date:inception_upper": "1980-01-01",
    "iso:country": "GB",
    "wof:name": "KY11 1DB",
    "wof:placetype": "postalcode"
  },
  "geometry": {"coordinates":[-3.392178,56.032115],"type":"Point"}
}
