{
  "type": "Feature",
  "properties": {
    "iso:country":"GB",
    "wof:name":"SE12 0PX",
    "wof:placetype":"postalcode"
},
  "geometry": {"coordinates":[0.01861173612814,51.43724602879358],"type":"Point"}
}