{
  "type": "Feature",
  "properties": {
    "iso:country":"GB",
    "wof:name":"HU16 4PU",
    "wof:placetype":"postalcode"
},
  "geometry": {"coordinates":[-0.3961626983358,53.77358204515181],"type":"Point"}
}