{
  "type": "Feature",
  "properties": {
    "date:inception_lower":"1980-01-01",
    "date:inception_upper":"1980-01-31",
    "iso:country":"GB",
    "wof:name":"BR1 4HE",
    "wof:placetype":"postalcode"
},
  "geometry": {"coordinates":[0.014741,51.414678],"type":"Point"}
}