{
  "type": "Feature",
  "properties": {
    "iso:country":"GB",
    "wof:name":"BR1 4HE",
    "wof:placetype":"postalcode"
},
  "geometry": {"coordinates":[0.01474110671578,51.41467772421323],"type":"Point"}
}