{
  "type": "Feature",
  "properties": {
    "iso:country":"GB",
    "wof:name":"SA11 3YH",
    "wof:placetype":"postalcode"
},
  "geometry": {"coordinates":[-3.78059540362053,51.65487990110832],"type":"Point"}
}