{
  "type": "Feature",
  "properties": {
    "iso:country":"GB",
    "wof:name":"NP20 3NG",
    "wof:placetype":"postalcode"
},
  "geometry": {"coordinates":[-3.02612285354024,51.57858565866793],"type":"Point"}
}