{
  "type": "Feature",
  "properties": {
    "date:inception_lower": "1980-01-01",
    "date:inception_upper": "1980-01-01",
    "iso:country": "GB",
    "wof:name": "MK13 7HD",
    "wof:placetype": "postalcode"
  },
  "geometry": {"coordinates":[-0.774874,52.05884],"type":"Point"}
}
