{
  "type": "Feature",
  "properties": {
    "iso:country":"GB",
    "wof:name":"MK13 7HD",
    "wof:placetype":"postalcode"
},
  "geometry": {"coordinates":[-0.77487439590345,52.05883993090598],"type":"Point"}
}