{
  "type": "Feature",
  "properties": {
    "iso:country":"GB",
    "wof:name":"RG40 1QJ",
    "wof:placetype":"postalcode"
},
  "geometry": {"coordinates":[-0.82053890324563,51.41754366240662],"type":"Point"}
}