{
  "type": "Feature",
  "properties": {
    "date:inception_lower":"1995-07-01",
    "date:inception_upper":"1995-07-31",
    "iso:country":"GB",
    "wof:name":"RG40 1QJ",
    "wof:placetype":"postalcode"
},
  "geometry": {"coordinates":[-0.820539,51.417544],"type":"Point"}
}