{
  "type": "Feature",
  "properties": {
    "date:inception_lower": "1980-01-01",
    "date:inception_upper": "1980-01-01",
    "iso:country": "GB",
    "wof:name": "SL7 2RF",
    "wof:placetype": "postalcode"
  },
  "geometry": {"coordinates":[-0.789008,51.572791],"type":"Point"}
}
