{
  "type": "Feature",
  "properties": {
    "date:inception_lower": "2023-09-01",
    "date:inception_upper": "2023-09-01",
    "iso:country": "GB",
    "wof:name": "EX15 1BZ",
    "wof:placetype": "postalcode"
  },
  "geometry": {"coordinates":[-3.389946,50.869427],"type":"Point"}
}
