{
  "type": "Feature",
  "properties": {
    "date:inception_lower": "1980-01-01",
    "date:inception_upper": "1980-01-01",
    "iso:country": "GB",
    "wof:name": "ST14 5HN",
    "wof:placetype": "postalcode"
  },
  "geometry": {"coordinates":[-1.868019,52.959844],"type":"Point"}
}
