{
  "type": "Feature",
  "properties": {
    "iso:country":"GB",
    "wof:name":"ST14 5HN",
    "wof:placetype":"postalcode"
},
  "geometry": {"coordinates":[-1.86801887132131,52.9598435559946],"type":"Point"}
}