{
  "type": "Feature",
  "properties": {
    "iso:country": "GB",
    "wof:name": "MK3 5QY",
    "wof:placetype": "postalcode"
  },
  "geometry": {"coordinates":[-0.737723,51.9768],"type":"Point"}
}
