{
  "type": "Feature",
  "properties": {
    "date:inception_lower": "1980-01-01",
    "date:inception_upper": "1980-01-01",
    "iso:country": "GB",
    "wof:name": "NR12 0XS",
    "wof:placetype": "postalcode"
  },
  "geometry": {"coordinates":[1.570531,52.756653],"type":"Point"}
}
