{
  "type": "Feature",
  "properties": {
    "iso:country":"GB",
    "wof:name":"TA21 0PU",
    "wof:placetype":"postalcode"
},
  "geometry": {"coordinates":[-3.34456152542448,50.957044931845],"type":"Point"}
}