{
  "type": "Feature",
  "properties": {
    "iso:country": "GB",
    "wof:name": "TA21 0PU",
    "wof:placetype": "postalcode"
  },
  "geometry": {"coordinates":[-3.344561,50.957045],"type":"Point"}
}
