{
  "type": "Feature",
  "properties": {
    "iso:country": "GB",
    "wof:name": "LL32 8DD",
    "wof:placetype": "postalcode"
  },
  "geometry": {"coordinates":[-3.829738,53.28092],"type":"Point"}
}
