{
  "type": "Feature",
  "properties": {
    "date:inception_lower":"1980-01-01",
    "date:inception_upper":"1980-01-31",
    "iso:country":"GB",
    "wof:name":"LL32 8DD",
    "wof:placetype":"postalcode"
},
  "geometry": {"coordinates":[-3.829738,53.28092],"type":"Point"}
}