{
  "type": "Feature",
  "properties": {
    "iso:country":"GB",
    "wof:name":"LL32 8DD",
    "wof:placetype":"postalcode"
},
  "geometry": {"coordinates":[-3.82983495435703,53.28082089099308],"type":"Point"}
}