{
  "type": "Feature",
  "properties": {
    "iso:country": "GB",
    "wof:name": "HR3 6JE",
    "wof:placetype": "postalcode"
  },
  "geometry": {"coordinates":[-3.07849,52.129705],"type":"Point"}
}
