{
  "type": "Feature",
  "properties": {
    "iso:country":"GB",
    "wof:name":"HR3 6JE",
    "wof:placetype":"postalcode"
},
  "geometry": {"coordinates":[-3.07853508968877,52.12974051514183],"type":"Point"}
}