{
  "type": "Feature",
  "properties": {
    "iso:country":"GB",
    "wof:name":"NE6 5TL",
    "wof:placetype":"postalcode"
},
  "geometry": {"coordinates":[-1.5659662830681,54.99173615013476],"type":"Point"}
}