{
  "type": "Feature",
  "properties": {
    "date:inception_lower": "1980-01-01",
    "date:inception_upper": "1980-01-01",
    "iso:country": "GB",
    "wof:name": "CV2 5JR",
    "wof:placetype": "postalcode"
  },
  "geometry": {"coordinates":[-1.465053,52.407409],"type":"Point"}
}
