{
  "type": "Feature",
  "properties": {
    "iso:country":"GB",
    "wof:name":"CV2 5JR",
    "wof:placetype":"postalcode"
},
  "geometry": {"coordinates":[-1.46505329104082,52.40740854042279],"type":"Point"}
}