{
  "type": "Feature",
  "properties": {
    "iso:country":"GB",
    "wof:name":"NW1 6HJ",
    "wof:placetype":"postalcode"
},
  "geometry": {"coordinates":[-0.16149319738338,51.52336325510379],"type":"Point"}
}