{
  "type": "Feature",
  "properties": {
    "iso:country": "GB",
    "wof:name": "OX15 5AT",
    "wof:placetype": "postalcode"
  },
  "geometry": {"coordinates":[-1.557021,52.053737],"type":"Point"}
}
