{
  "type": "Feature",
  "properties": {
    "iso:country":"GB",
    "wof:name":"OX15 5AT",
    "wof:placetype":"postalcode"
},
  "geometry": {"coordinates":[-1.55702095152041,52.05373748173347],"type":"Point"}
}