{
  "type": "Feature",
  "properties": {
    "date:inception_lower": "1985-10-01",
    "date:inception_upper": "1985-10-01",
    "iso:country": "GB",
    "wof:name": "NG5 8ND",
    "wof:placetype": "postalcode"
  },
  "geometry": {"coordinates":[-1.152729,53.01373],"type":"Point"}
}
