{
  "type": "Feature",
  "properties": {
    "iso:country":"GB",
    "wof:name":"NG5 8ND",
    "wof:placetype":"postalcode"
},
  "geometry": {"coordinates":[-1.15272880393689,53.01373008701179],"type":"Point"}
}