{
  "type": "Feature",
  "properties": {
    "iso:country":"GB",
    "wof:name":"RM10 7BT",
    "wof:placetype":"postalcode"
},
  "geometry": {"coordinates":[0.16505370627976,51.55419305864578],"type":"Point"}
}