{
  "type": "Feature",
  "properties": {
    "date:inception_lower": "2015-08-01",
    "date:inception_upper": "2015-08-01",
    "iso:country": "GB",
    "wof:name": "PO30 4DN",
    "wof:placetype": "postalcode"
  },
  "geometry": {"coordinates":[-1.403169,50.64486],"type":"Point"}
}
