{
  "type": "Feature",
  "properties": {
    "iso:country": "GB",
    "wof:name": "PO30 4DN",
    "wof:placetype": "postalcode"
  },
  "geometry": {"coordinates":[-1.403169,50.64486],"type":"Point"}
}
