{
  "type": "Feature",
  "properties": {
    "date:inception_lower":"2015-08-01",
    "date:inception_upper":"2015-08-31",
    "iso:country":"GB",
    "wof:name":"PO30 4DN",
    "wof:placetype":"postalcode"
},
  "geometry": {"coordinates":[-1.403812,50.645072],"type":"Point"}
}