{
  "type": "Feature",
  "properties": {
    "iso:country":"GB",
    "wof:name":"PO30 4DN",
    "wof:placetype":"postalcode"
},
  "geometry": {"coordinates":[-1.40381201057776,50.6450717130712],"type":"Point"}
}