{
  "type": "Feature",
  "properties": {
    "date:inception_lower": "1980-01-01",
    "date:inception_upper": "1980-01-01",
    "iso:country": "GB",
    "wof:name": "RG24 9HE",
    "wof:placetype": "postalcode"
  },
  "geometry": {"coordinates":[-1.098388,51.28148],"type":"Point"}
}
