{
  "type": "Feature",
  "properties": {
    "iso:country":"GB",
    "wof:name":"SA4 3FQ",
    "wof:placetype":"postalcode"
},
  "geometry": {"coordinates":[-4.11152791114919,51.64139016667728],"type":"Point"}
}