{
  "type": "Feature",
  "properties": {
    "date:inception_lower":"1980-01-01",
    "date:inception_upper":"1980-01-31",
    "iso:country":"GB",
    "wof:name":"SA4 3FQ",
    "wof:placetype":"postalcode"
},
  "geometry": {"coordinates":[-4.11155,51.641396],"type":"Point"}
}