{
  "type": "Feature",
  "properties": {
    "iso:country": "GB",
    "wof:name": "SA4 3FQ",
    "wof:placetype": "postalcode"
  },
  "geometry": {"coordinates":[-4.11155,51.641396],"type":"Point"}
}
