{
  "type": "Feature",
  "properties": {
    "date:inception_lower":"2005-03-01",
    "date:inception_upper":"2005-03-31",
    "iso:country":"GB",
    "wof:name":"UB3 2RR",
    "wof:placetype":"postalcode"
},
  "geometry": {"coordinates":[-0.423579,51.521721],"type":"Point"}
}