{
  "type": "Feature",
  "properties": {
    "iso:country":"GB",
    "wof:name":"UB3 2RR",
    "wof:placetype":"postalcode"
},
  "geometry": {"coordinates":[-0.42359962095973,51.52172004052515],"type":"Point"}
}