{
  "type": "Feature",
  "properties": {
    "iso:country":"GB",
    "wof:name":"GU8 6HE",
    "wof:placetype":"postalcode"
},
  "geometry": {"coordinates":[-0.7013644529601,51.18468804116046],"type":"Point"}
}