{
  "type": "Feature",
  "properties": {
    "iso:country":"GB",
    "wof:name":"YO31 0NP",
    "wof:placetype":"postalcode"
},
  "geometry": {"coordinates":[-1.04408194279992,53.96642805438648],"type":"Point"}
}