{
  "type": "Feature",
  "properties": {
    "date:inception_lower": "1998-06-01",
    "date:inception_upper": "1998-06-01",
    "iso:country": "GB",
    "wof:name": "YO31 0NP",
    "wof:placetype": "postalcode"
  },
  "geometry": {"coordinates":[-1.044091,53.966437],"type":"Point"}
}
