{
  "type": "Feature",
  "properties": {
    "iso:country": "GB",
    "wof:name": "DA1 5BH",
    "wof:placetype": "postalcode"
  },
  "geometry": {"coordinates":[0.208415,51.454347],"type":"Point"}
}
