{
  "type": "Feature",
  "properties": {
    "iso:country":"GB",
    "wof:name":"SE28 8RD",
    "wof:placetype":"postalcode"
},
  "geometry": {"coordinates":[0.10324919816437,51.50590206946148],"type":"Point"}
}