{
  "type": "Feature",
  "properties": {
    "iso:country": "GB",
    "wof:name": "SO22 5FU",
    "wof:placetype": "postalcode"
  },
  "geometry": {"coordinates":[-1.337013,51.066259],"type":"Point"}
}
