{
  "type": "Feature",
  "properties": {
    "iso:country":"GB",
    "wof:name":"NG5 8HJ",
    "wof:placetype":"postalcode"
},
  "geometry": {"coordinates":[-1.12866407757837,53.01038299240206],"type":"Point"}
}