{
  "type": "Feature",
  "properties": {
    "iso:country":"GB",
    "wof:name":"CF3 3LW",
    "wof:placetype":"postalcode"
},
  "geometry": {"coordinates":[-3.12111247363889,51.51527756205933],"type":"Point"}
}