{
  "type": "Feature",
  "properties": {
    "date:inception_lower":"2008-01-01",
    "date:inception_upper":"2008-01-31",
    "iso:country":"GB",
    "wof:name":"BS1 5JS",
    "wof:placetype":"postalcode"
},
  "geometry": {"coordinates":[-2.604583,51.449015],"type":"Point"}
}