{
  "type": "Feature",
  "properties": {
    "iso:country":"GB",
    "wof:name":"BS1 5JS",
    "wof:placetype":"postalcode"
},
  "geometry": {"coordinates":[-2.60458270345978,51.44901549246352],"type":"Point"}
}