{
  "type": "Feature",
  "properties": {
    "iso:country":"GB",
    "wof:name":"SP5 3QJ",
    "wof:placetype":"postalcode"
},
  "geometry": {"coordinates":[-1.72414040684445,51.01427943344948],"type":"Point"}
}