{
  "type": "Feature",
  "properties": {
    "iso:country":"GB",
    "wof:name":"TD14 5AB",
    "wof:placetype":"postalcode"
},
  "geometry": {"coordinates":[-2.09354249580309,55.87236214561601],"type":"Point"}
}