{
  "type": "Feature",
  "properties": {
    "iso:country":"GB",
    "wof:name":"BB10 1QX",
    "wof:placetype":"postalcode"
},
  "geometry": {"coordinates":[-2.23973895421648,53.79972284592274],"type":"Point"}
}