{
  "type": "Feature",
  "properties": {
    "iso:country": "GB",
    "wof:name": "SG12 8PD",
    "wof:placetype": "postalcode"
  },
  "geometry": {"coordinates":[0.056448,51.80649],"type":"Point"}
}
