{
  "type": "Feature",
  "properties": {
    "iso:country":"GB",
    "wof:name":"SY3 9NF",
    "wof:placetype":"postalcode"
},
  "geometry": {"coordinates":[-2.75774084612878,52.69064208417107],"type":"Point"}
}