{
  "type": "Feature",
  "properties": {
    "date:inception_lower": "1980-01-01",
    "date:inception_upper": "1980-01-01",
    "iso:country": "GB",
    "wof:name": "SY3 9NF",
    "wof:placetype": "postalcode"
  },
  "geometry": {"coordinates":[-2.757741,52.690642],"type":"Point"}
}
