{
  "type": "Feature",
  "properties": {
    "date:inception_lower": "1980-01-01",
    "date:inception_upper": "1980-01-01",
    "iso:country": "GB",
    "wof:name": "HU5 4EE",
    "wof:placetype": "postalcode"
  },
  "geometry": {"coordinates":[-0.372385,53.765306],"type":"Point"}
}
