{
  "type": "Feature",
  "properties": {
    "iso:country":"GB",
    "wof:name":"HU5 4EE",
    "wof:placetype":"postalcode"
},
  "geometry": {"coordinates":[-0.37238530749977,53.76530625880916],"type":"Point"}
}