{
  "type": "Feature",
  "properties": {
    "iso:country": "GB",
    "wof:name": "HU5 4EE",
    "wof:placetype": "postalcode"
  },
  "geometry": {"coordinates":[-0.372385,53.765306],"type":"Point"}
}
