{
  "type": "Feature",
  "properties": {
    "iso:country":"GB",
    "wof:name":"S17 3EG",
    "wof:placetype":"postalcode"
},
  "geometry": {"coordinates":[-1.54103546293348,53.33014340308053],"type":"Point"}
}