{
  "type": "Feature",
  "properties": {
    "date:inception_lower": "1993-02-01",
    "date:inception_upper": "1993-02-01",
    "iso:country": "GB",
    "wof:name": "PH33 7EX",
    "wof:placetype": "postalcode"
  },
  "geometry": {"coordinates":[-5.099034,56.83875],"type":"Point"}
}
