{
  "type": "Feature",
  "properties": {
    "iso:country":"GB",
    "wof:name":"PH33 7EX",
    "wof:placetype":"postalcode"
},
  "geometry": {"coordinates":[-5.09903419303243,56.83874982156829],"type":"Point"}
}