{
  "type": "Feature",
  "properties": {
    "date:inception_lower": "2002-06-01",
    "date:inception_upper": "2002-06-01",
    "iso:country": "GB",
    "wof:name": "DA12 4YP",
    "wof:placetype": "postalcode"
  },
  "geometry": {"coordinates":[0.373299,51.441221],"type":"Point"}
}
