{
  "type": "Feature",
  "properties": {
    "date:inception_lower": "1992-08-01",
    "date:inception_upper": "1992-08-01",
    "iso:country": "GB",
    "wof:name": "LE7 3QY",
    "wof:placetype": "postalcode"
  },
  "geometry": {"coordinates":[-1.051023,52.716789],"type":"Point"}
}
