{
  "type": "Feature",
  "properties": {
    "iso:country":"GB",
    "wof:name":"LE7 3QY",
    "wof:placetype":"postalcode"
},
  "geometry": {"coordinates":[-1.05103009761432,52.71672460305918],"type":"Point"}
}