{
  "type": "Feature",
  "properties": {
    "iso:country":"GB",
    "wof:name":"ML11 9DZ",
    "wof:placetype":"postalcode"
},
  "geometry": {"coordinates":[-3.78077283256311,55.6730931466623],"type":"Point"}
}