{
  "type": "Feature",
  "properties": {
    "iso:country": "GB",
    "wof:name": "ML11 9DZ",
    "wof:placetype": "postalcode"
  },
  "geometry": {"coordinates":[-3.780315,55.673172],"type":"Point"}
}
