{
  "type": "Feature",
  "properties": {
    "iso:country":"GB",
    "wof:name":"CH7 4EN",
    "wof:placetype":"postalcode"
},
  "geometry": {"coordinates":[-3.1552460511045,53.12746664683604],"type":"Point"}
}