{
  "type": "Feature",
  "properties": {
    "date:inception_lower": "1980-01-01",
    "date:inception_upper": "1980-01-01",
    "iso:country": "GB",
    "wof:name": "EX5 4AX",
    "wof:placetype": "postalcode"
  },
  "geometry": {"coordinates":[-3.505358,50.774016],"type":"Point"}
}
