{
  "type": "Feature",
  "properties": {
    "iso:country":"GB",
    "wof:name":"EX5 4AX",
    "wof:placetype":"postalcode"
},
  "geometry": {"coordinates":[-3.50535824514816,50.77401589702239],"type":"Point"}
}