{
  "type": "Feature",
  "properties": {
    "iso:country": "GB",
    "wof:name": "NG32 3RN",
    "wof:placetype": "postalcode"
  },
  "geometry": {"coordinates":[-0.521005,53.016156],"type":"Point"}
}
