{
  "type": "Feature",
  "properties": {
    "iso:country":"GB",
    "wof:name":"NG32 3RN",
    "wof:placetype":"postalcode"
},
  "geometry": {"coordinates":[-0.52100494236383,53.01615586659361],"type":"Point"}
}