{
  "type": "Feature",
  "properties": {
    "date:inception_lower":"1998-12-01",
    "date:inception_upper":"1998-12-31",
    "iso:country":"GB",
    "wof:name":"EX12 4BS",
    "wof:placetype":"postalcode"
},
  "geometry": {"coordinates":[-3.048309,50.713858],"type":"Point"}
}