{
  "type": "Feature",
  "properties": {
    "iso:country": "GB",
    "wof:name": "EX12 4BS",
    "wof:placetype": "postalcode"
  },
  "geometry": {"coordinates":[-3.048309,50.713858],"type":"Point"}
}
