{
  "type": "Feature",
  "properties": {
    "iso:country":"GB",
    "wof:name":"DY5 2PD",
    "wof:placetype":"postalcode"
},
  "geometry": {"coordinates":[-2.1237842231264,52.46892945605986],"type":"Point"}
}