{
  "type": "Feature",
  "properties": {
    "iso:country": "GB",
    "wof:name": "N18 3PU",
    "wof:placetype": "postalcode"
  },
  "geometry": {"coordinates":[-0.049129,51.618011],"type":"Point"}
}
