{
  "type": "Feature",
  "properties": {
    "iso:country":"GB",
    "wof:name":"N18 3PU",
    "wof:placetype":"postalcode"
},
  "geometry": {"coordinates":[-0.0491287047429,51.61801115617902],"type":"Point"}
}