{
  "type": "Feature",
  "properties": {
    "date:inception_lower": "2011-01-01",
    "date:inception_upper": "2011-01-01",
    "iso:country": "GB",
    "wof:name": "N18 3PU",
    "wof:placetype": "postalcode"
  },
  "geometry": {"coordinates":[-0.049129,51.618011],"type":"Point"}
}
