{
  "type": "Feature",
  "properties": {
    "iso:country":"GB",
    "wof:name":"CV5 8BJ",
    "wof:placetype":"postalcode"
},
  "geometry": {"coordinates":[-1.55348030979815,52.4082518407829],"type":"Point"}
}