{
  "type": "Feature",
  "properties": {
    "date:inception_lower":"2014-03-01",
    "date:inception_upper":"2014-03-31",
    "iso:country":"GB",
    "wof:name":"CV35 0EX",
    "wof:placetype":"postalcode"
},
  "geometry": {"coordinates":[-1.47193,52.182229],"type":"Point"}
}