{
  "type": "Feature",
  "properties": {
    "iso:country":"GB",
    "wof:name":"CV35 0EX",
    "wof:placetype":"postalcode"
},
  "geometry": {"coordinates":[-1.47201416247109,52.18222288210074],"type":"Point"}
}