{
  "type": "Feature",
  "properties": {
    "iso:country": "GB",
    "wof:name": "BH24 3HD",
    "wof:placetype": "postalcode"
  },
  "geometry": {"coordinates":[-1.754173,50.844634],"type":"Point"}
}
