{
  "type": "Feature",
  "properties": {
    "date:inception_lower":"1980-01-01",
    "date:inception_upper":"1980-01-31",
    "iso:country":"GB",
    "wof:name":"BH24 3HD",
    "wof:placetype":"postalcode"
},
  "geometry": {"coordinates":[-1.754173,50.844634],"type":"Point"}
}