{
  "type": "Feature",
  "properties": {
    "date:inception_lower": "1980-01-01",
    "date:inception_upper": "1980-01-01",
    "iso:country": "GB",
    "wof:name": "M12 5RB",
    "wof:placetype": "postalcode"
  },
  "geometry": {"coordinates":[-2.187941,53.454011],"type":"Point"}
}
