{
  "type": "Feature",
  "properties": {
    "iso:country":"GB",
    "wof:name":"SY11 1LB",
    "wof:placetype":"postalcode"
},
  "geometry": {"coordinates":[-3.05555963984448,52.86230050877944],"type":"Point"}
}