{
  "type": "Feature",
  "properties": {
    "iso:country": "GB",
    "wof:name": "HA2 9JH",
    "wof:placetype": "postalcode"
  },
  "geometry": {"coordinates":[-0.376476,51.567603],"type":"Point"}
}
