{
  "type": "Feature",
  "properties": {
    "iso:country":"GB",
    "wof:name":"L24 0SN",
    "wof:placetype":"postalcode"
},
  "geometry": {"coordinates":[-2.84776889644026,53.34669051876659],"type":"Point"}
}