{
  "type": "Feature",
  "properties": {
    "iso:country":"GB",
    "wof:name":"TS26 8EN",
    "wof:placetype":"postalcode"
},
  "geometry": {"coordinates":[-1.22438840670036,54.68791584533583],"type":"Point"}
}