{
  "type": "Feature",
  "properties": {
    "iso:country": "GB",
    "wof:name": "TS26 8EN",
    "wof:placetype": "postalcode"
  },
  "geometry": {"coordinates":[-1.224388,54.687916],"type":"Point"}
}
