{
  "type": "Feature",
  "properties": {
    "iso:country":"GB",
    "wof:name":"BA3 2AA",
    "wof:placetype":"postalcode"
},
  "geometry": {"coordinates":[-2.4674428304809,51.2924223742843],"type":"Point"}
}