{
  "type": "Feature",
  "properties": {
    "iso:country": "GB",
    "wof:name": "G82 2BU",
    "wof:placetype": "postalcode"
  },
  "geometry": {"coordinates":[-4.566219,55.948394],"type":"Point"}
}
