{
  "type": "Feature",
  "properties": {
    "iso:country":"GB",
    "wof:name":"PL10 1DH",
    "wof:placetype":"postalcode"
},
  "geometry": {"coordinates":[-4.21239971528192,50.34828882926168],"type":"Point"}
}