{
  "type": "Feature",
  "properties": {
    "iso:country": "GB",
    "wof:name": "PL10 1DH",
    "wof:placetype": "postalcode"
  },
  "geometry": {"coordinates":[-4.2124,50.348289],"type":"Point"}
}
