{
  "type": "Feature",
  "properties": {
    "date:inception_lower": "1996-06-01",
    "date:inception_upper": "1996-06-01",
    "iso:country": "GB",
    "wof:name": "PE25 1TP",
    "wof:placetype": "postalcode"
  },
  "geometry": {"coordinates":[0.315865,53.158464],"type":"Point"}
}
