{
  "type": "Feature",
  "properties": {
    "iso:country": "GB",
    "wof:name": "PE25 1TP",
    "wof:placetype": "postalcode"
  },
  "geometry": {"coordinates":[0.315865,53.158464],"type":"Point"}
}
