{
  "type": "Feature",
  "properties": {
    "date:inception_lower":"1987-10-01",
    "date:inception_upper":"1987-10-31",
    "iso:country":"GB",
    "wof:name":"TS17 0TP",
    "wof:placetype":"postalcode"
},
  "geometry": {"coordinates":[-1.311001,54.521542],"type":"Point"}
}