{
  "type": "Feature",
  "properties": {
    "iso:country": "GB",
    "wof:name": "TS17 0TP",
    "wof:placetype": "postalcode"
  },
  "geometry": {"coordinates":[-1.311001,54.521542],"type":"Point"}
}
