{
  "type": "Feature",
  "properties": {
    "iso:country":"GB",
    "wof:name":"G63 0YE",
    "wof:placetype":"postalcode"
},
  "geometry": {"coordinates":[-4.22552195477042,56.05897639469865],"type":"Point"}
}