{
  "type": "Feature",
  "properties": {
    "iso:country":"GB",
    "wof:name":"N21 1SZ",
    "wof:placetype":"postalcode"
},
  "geometry": {"coordinates":[-0.11021121991867,51.64703064784423],"type":"Point"}
}