{
  "type": "Feature",
  "properties": {
    "date:inception_lower": "1995-07-01",
    "date:inception_upper": "1995-07-01",
    "iso:country": "GB",
    "wof:name": "N21 1SZ",
    "wof:placetype": "postalcode"
  },
  "geometry": {"coordinates":[-0.110211,51.647031],"type":"Point"}
}
