{
  "type": "Feature",
  "properties": {
    "date:inception_lower": "2013-12-01",
    "date:inception_upper": "2013-12-01",
    "iso:country": "GB",
    "wof:name": "MK17 8FJ",
    "wof:placetype": "postalcode"
  },
  "geometry": {"coordinates":[-0.655191,52.016211],"type":"Point"}
}
