{
  "type": "Feature",
  "properties": {
    "iso:country":"GB",
    "wof:name":"SW10 0EY",
    "wof:placetype":"postalcode"
},
  "geometry": {"coordinates":[-0.17729061621852,51.48187569611065],"type":"Point"}
}