{
  "type": "Feature",
  "properties": {
    "iso:country":"GB",
    "wof:name":"BA5 3HW",
    "wof:placetype":"postalcode"
},
  "geometry": {"coordinates":[-2.63438493908328,51.21404493558899],"type":"Point"}
}