{
  "type": "Feature",
  "properties": {
    "date:inception_lower":"1987-04-01",
    "date:inception_upper":"1987-04-30",
    "iso:country":"GB",
    "wof:name":"BA5 3HW",
    "wof:placetype":"postalcode"
},
  "geometry": {"coordinates":[-2.634385,51.214045],"type":"Point"}
}