{
  "type": "Feature",
  "properties": {
    "iso:country":"GB",
    "wof:name":"BN2 1JN",
    "wof:placetype":"postalcode"
},
  "geometry": {"coordinates":[-0.12770339890118,50.81945972446609],"type":"Point"}
}