{
  "type": "Feature",
  "properties": {
    "date:inception_lower": "2021-10-01",
    "date:inception_upper": "2021-10-01",
    "iso:country": "GB",
    "wof:name": "NW7 1TP",
    "wof:placetype": "postalcode"
  },
  "geometry": {"coordinates":[-0.21041,51.611124],"type":"Point"}
}
