{
  "type": "Feature",
  "properties": {
    "date:inception_lower":"1996-12-01",
    "date:inception_upper":"1996-12-31",
    "iso:country":"GB",
    "wof:name":"LE9 6NN",
    "wof:placetype":"postalcode"
},
  "geometry": {"coordinates":[-1.211344,52.521073],"type":"Point"}
}