{
  "type": "Feature",
  "properties": {
    "iso:country":"GB",
    "wof:name":"PE7 3NA",
    "wof:placetype":"postalcode"
},
  "geometry": {"coordinates":[-0.25941488524244,52.50898649798731],"type":"Point"}
}