{
  "type": "Feature",
  "properties": {
    "iso:country":"GB",
    "wof:name":"SW15 2LP",
    "wof:placetype":"postalcode"
},
  "geometry": {"coordinates":[-0.21009480636449,51.46210296020388],"type":"Point"}
}