{
  "type": "Feature",
  "properties": {
    "date:inception_lower": "1980-01-01",
    "date:inception_upper": "1980-01-01",
    "iso:country": "GB",
    "wof:name": "DN36 5UD",
    "wof:placetype": "postalcode"
  },
  "geometry": {"coordinates":[0.073318,53.468633],"type":"Point"}
}
