{
  "type": "Feature",
  "properties": {
    "iso:country": "GB",
    "wof:name": "DN36 5UD",
    "wof:placetype": "postalcode"
  },
  "geometry": {"coordinates":[0.073655,53.468753],"type":"Point"}
}
