{
  "type": "Feature",
  "properties": {
    "date:inception_lower":"1980-01-01",
    "date:inception_upper":"1980-01-31",
    "iso:country":"GB",
    "wof:name":"KY12 0TQ",
    "wof:placetype":"postalcode"
},
  "geometry": {"coordinates":[-3.419451,56.095638],"type":"Point"}
}