{
  "type": "Feature",
  "properties": {
    "date:inception_lower": "2020-12-01",
    "date:inception_upper": "2020-12-01",
    "iso:country": "GB",
    "wof:name": "CV34 6ZE",
    "wof:placetype": "postalcode"
  },
  "geometry": {"coordinates":[-1.565712,52.270501],"type":"Point"}
}
