{
  "type": "Feature",
  "properties": {
    "iso:country": "GB",
    "wof:name": "WD23 3LL",
    "wof:placetype": "postalcode"
  },
  "geometry": {"coordinates":[-0.359058,51.643767],"type":"Point"}
}
