{
  "type": "Feature",
  "properties": {
    "iso:country": "GB",
    "wof:name": "LE2 9RG",
    "wof:placetype": "postalcode"
  },
  "geometry": {"coordinates":[-1.158599,52.583379],"type":"Point"}
}
