{
  "type": "Feature",
  "properties": {
    "iso:country": "GB",
    "wof:name": "CO10 8DL",
    "wof:placetype": "postalcode"
  },
  "geometry": {"coordinates":[0.538648,52.106186],"type":"Point"}
}
