{
  "type": "Feature",
  "properties": {
    "date:inception_lower": "2017-12-01",
    "date:inception_upper": "2017-12-01",
    "iso:country": "GB",
    "wof:name": "BB7 9FL",
    "wof:placetype": "postalcode"
  },
  "geometry": {"coordinates":[-2.396211,53.840064],"type":"Point"}
}
