{
  "type": "Feature",
  "properties": {
    "iso:country":"GB",
    "wof:name":"CT5 2JH",
    "wof:placetype":"postalcode"
},
  "geometry": {"coordinates":[1.04647812459141,51.3590286076055],"type":"Point"}
}