{
  "type": "Feature",
  "properties": {
    "iso:country": "GB",
    "wof:name": "LS14 3JJ",
    "wof:placetype": "postalcode"
  },
  "geometry": {"coordinates":[-1.46564,53.868278],"type":"Point"}
}
