{
  "type": "Feature",
  "properties": {
    "iso:country":"GB",
    "wof:name":"LS14 3JJ",
    "wof:placetype":"postalcode"
},
  "geometry": {"coordinates":[-1.46564030190197,53.86827810315166],"type":"Point"}
}