{
  "type": "Feature",
  "properties": {
    "date:inception_lower": "1980-01-01",
    "date:inception_upper": "1980-01-01",
    "iso:country": "GB",
    "wof:name": "BB10 3JA",
    "wof:placetype": "postalcode"
  },
  "geometry": {"coordinates":[-2.202817,53.790641],"type":"Point"}
}
