{
  "type": "Feature",
  "properties": {
    "iso:country":"GB",
    "wof:name":"OX9 7AQ",
    "wof:placetype":"postalcode"
},
  "geometry": {"coordinates":[-1.00658242661116,51.70894338323839],"type":"Point"}
}