{
  "type": "Feature",
  "properties": {
    "iso:country":"GB",
    "wof:name":"CR0 4QX",
    "wof:placetype":"postalcode"
},
  "geometry": {"coordinates":[-0.12836375058847,51.36541457810331],"type":"Point"}
}