{
  "type": "Feature",
  "properties": {
    "date:inception_lower":"2006-11-01",
    "date:inception_upper":"2006-11-30",
    "iso:country":"GB",
    "wof:name":"TS21 3BP",
    "wof:placetype":"postalcode"
},
  "geometry": {"coordinates":[-1.452681,54.662776],"type":"Point"}
}