{
  "type": "Feature",
  "properties": {
    "iso:country":"GB",
    "wof:name":"TS21 3BP",
    "wof:placetype":"postalcode"
},
  "geometry": {"coordinates":[-1.45268117650101,54.66277618720665],"type":"Point"}
}