{
  "type": "Feature",
  "properties": {
    "iso:country": "GB",
    "wof:name": "LL58 8TR",
    "wof:placetype": "postalcode"
  },
  "geometry": {"coordinates":[-4.158867,53.293854],"type":"Point"}
}
