{
  "type": "Feature",
  "properties": {
    "iso:country":"GB",
    "wof:name":"LL58 8TR",
    "wof:placetype":"postalcode"
},
  "geometry": {"coordinates":[-4.15886747239231,53.29385416352556],"type":"Point"}
}