{
  "type": "Feature",
  "properties": {
    "date:inception_lower":"1980-01-01",
    "date:inception_upper":"1980-01-31",
    "iso:country":"GB",
    "wof:name":"WV4 4TR",
    "wof:placetype":"postalcode"
},
  "geometry": {"coordinates":[-2.180137,52.556077],"type":"Point"}
}