{
  "type": "Feature",
  "properties": {
    "iso:country":"GB",
    "wof:name":"WV4 4TR",
    "wof:placetype":"postalcode"
},
  "geometry": {"coordinates":[-2.18013720490262,52.55607714606113],"type":"Point"}
}