{
  "type": "Feature",
  "properties": {
    "iso:country": "GB",
    "wof:name": "WV4 4TR",
    "wof:placetype": "postalcode"
  },
  "geometry": {"coordinates":[-2.180137,52.556077],"type":"Point"}
}
