{
  "type": "Feature",
  "properties": {
    "date:inception_lower":"1983-07-01",
    "date:inception_upper":"1983-07-31",
    "iso:country":"GB",
    "wof:name":"ST7 4HD",
    "wof:placetype":"postalcode"
},
  "geometry": {"coordinates":[-2.206564,53.095796],"type":"Point"}
}