{
  "type": "Feature",
  "properties": {
    "iso:country":"GB",
    "wof:name":"HX2 0JA",
    "wof:placetype":"postalcode"
},
  "geometry": {"coordinates":[-1.89465170185009,53.72928915696539],"type":"Point"}
}