{
  "type": "Feature",
  "properties": {
    "iso:country":"GB",
    "wof:name":"G14 9YE",
    "wof:placetype":"postalcode"
},
  "geometry": {"coordinates":[-4.35708980838733,55.88165249566728],"type":"Point"}
}