{
  "type": "Feature",
  "properties": {
    "iso:country":"GB",
    "wof:name":"LL56 4JP",
    "wof:placetype":"postalcode"
},
  "geometry": {"coordinates":[-4.2017981227932,53.18878607464665],"type":"Point"}
}