{
  "type": "Feature",
  "properties": {
    "iso:country":"GB",
    "wof:name":"SE20 8DL",
    "wof:placetype":"postalcode"
},
  "geometry": {"coordinates":[-0.07136442600698,51.4148944329084],"type":"Point"}
}