{
  "type": "Feature",
  "properties": {
    "iso:country":"GB",
    "wof:name":"KA9 1LS",
    "wof:placetype":"postalcode"
},
  "geometry": {"coordinates":[-4.6077631438843,55.49814154812623],"type":"Point"}
}