{
  "type": "Feature",
  "properties": {
    "date:inception_lower": "1980-01-01",
    "date:inception_upper": "1980-01-01",
    "iso:country": "GB",
    "wof:name": "BN12 5EE",
    "wof:placetype": "postalcode"
  },
  "geometry": {"coordinates":[-0.444644,50.809007],"type":"Point"}
}
