{
  "type": "Feature",
  "properties": {
    "iso:country":"GB",
    "wof:name":"SG9 9BN",
    "wof:placetype":"postalcode"
},
  "geometry": {"coordinates":[-0.01868193384149,51.95111487756086],"type":"Point"}
}