{
  "type": "Feature",
  "properties": {
    "date:inception_lower":"1980-01-01",
    "date:inception_upper":"1980-01-31",
    "iso:country":"GB",
    "wof:name":"RG1 3HB",
    "wof:placetype":"postalcode"
},
  "geometry": {"coordinates":[-0.951456,51.454252],"type":"Point"}
}