{
  "type": "Feature",
  "properties": {
    "date:inception_lower": "1980-01-01",
    "date:inception_upper": "1980-01-01",
    "iso:country": "GB",
    "wof:name": "KT4 8HG",
    "wof:placetype": "postalcode"
  },
  "geometry": {"coordinates":[-0.244705,51.380686],"type":"Point"}
}
