{
  "type": "Feature",
  "properties": {
    "iso:country": "GB",
    "wof:name": "KT4 8HG",
    "wof:placetype": "postalcode"
  },
  "geometry": {"coordinates":[-0.244705,51.380686],"type":"Point"}
}
