{
  "type": "Feature",
  "properties": {
    "date:inception_lower": "2020-05-01",
    "date:inception_upper": "2020-05-01",
    "iso:country": "GB",
    "wof:name": "E16 1DJ",
    "wof:placetype": "postalcode"
  },
  "geometry": {"coordinates":[0.009586,51.513184],"type":"Point"}
}
