{
  "type": "Feature",
  "properties": {
    "date:inception_lower": "2008-03-01",
    "date:inception_upper": "2008-03-01",
    "iso:country": "GB",
    "wof:name": "NN4 7EH",
    "wof:placetype": "postalcode"
  },
  "geometry": {"coordinates":[-0.871868,52.217464],"type":"Point"}
}
