{
  "type": "Feature",
  "properties": {
    "iso:country":"GB",
    "wof:name":"B75 5AB",
    "wof:placetype":"postalcode"
},
  "geometry": {"coordinates":[-1.82632083554847,52.58326384453327],"type":"Point"}
}