{
  "type": "Feature",
  "properties": {
    "iso:country":"GB",
    "wof:name":"BH15 4FG",
    "wof:placetype":"postalcode"
},
  "geometry": {"coordinates":[-2.00246897900434,50.7142656477352],"type":"Point"}
}