{
  "type": "Feature",
  "properties": {
    "date:inception_lower":"2010-08-01",
    "date:inception_upper":"2010-08-31",
    "iso:country":"GB",
    "wof:name":"BH15 4FG",
    "wof:placetype":"postalcode"
},
  "geometry": {"coordinates":[-2.002469,50.714266],"type":"Point"}
}