{
  "type": "Feature",
  "properties": {
    "iso:country":"GB",
    "wof:name":"G11 7JN",
    "wof:placetype":"postalcode"
},
  "geometry": {"coordinates":[-4.31534773054377,55.87800518819352],"type":"Point"}
}