{
  "type": "Feature",
  "properties": {
    "iso:country":"GB",
    "wof:name":"S9 2QD",
    "wof:placetype":"postalcode"
},
  "geometry": {"coordinates":[-1.43440779191267,53.39853958699981],"type":"Point"}
}