{
  "type": "Feature",
  "properties": {
    "iso:country": "GB",
    "wof:name": "NP23 6LY",
    "wof:placetype": "postalcode"
  },
  "geometry": {"coordinates":[-3.212694,51.781555],"type":"Point"}
}
