{
  "type": "Feature",
  "properties": {
    "iso:country":"GB",
    "wof:name":"EX31 4EH",
    "wof:placetype":"postalcode"
},
  "geometry": {"coordinates":[-4.10965070647477,51.12626068782429],"type":"Point"}
}