{
  "type": "Feature",
  "properties": {
    "iso:country": "GB",
    "wof:name": "NP19 4SJ",
    "wof:placetype": "postalcode"
  },
  "geometry": {"coordinates":[-2.946708,51.572411],"type":"Point"}
}
