{
  "type": "Feature",
  "properties": {
    "iso:country":"GB",
    "wof:name":"MK45 5LX",
    "wof:placetype":"postalcode"
},
  "geometry": {"coordinates":[-0.50548647289089,51.9839085170474],"type":"Point"}
}