{
  "type": "Feature",
  "properties": {
    "date:inception_lower":"2004-06-01",
    "date:inception_upper":"2004-06-30",
    "iso:country":"GB",
    "wof:name":"MK45 5LX",
    "wof:placetype":"postalcode"
},
  "geometry": {"coordinates":[-0.505486,51.983909],"type":"Point"}
}