{
  "type": "Feature",
  "properties": {
    "date:inception_lower": "1980-01-01",
    "date:inception_upper": "1980-01-01",
    "iso:country": "GB",
    "wof:name": "TN24 9AS",
    "wof:placetype": "postalcode"
  },
  "geometry": {"coordinates":[0.884112,51.169494],"type":"Point"}
}
