{
  "type": "Feature",
  "properties": {
    "iso:country":"GB",
    "wof:name":"TN16 3QL",
    "wof:placetype":"postalcode"
},
  "geometry": {"coordinates":[0.02828729644255,51.30670892159002],"type":"Point"}
}