{
  "type": "Feature",
  "properties": {
    "iso:country": "GB",
    "wof:name": "TN16 3QL",
    "wof:placetype": "postalcode"
  },
  "geometry": {"coordinates":[0.028287,51.306709],"type":"Point"}
}
