{
  "type": "Feature",
  "properties": {
    "date:inception_lower":"2000-06-01",
    "date:inception_upper":"2000-06-30",
    "iso:country":"GB",
    "wof:name":"SA13 2UX",
    "wof:placetype":"postalcode"
},
  "geometry": {"coordinates":[-3.70066,51.548518],"type":"Point"}
}