{
  "type": "Feature",
  "properties": {
    "iso:country":"GB",
    "wof:name":"LE10 0NN",
    "wof:placetype":"postalcode"
},
  "geometry": {"coordinates":[-1.38437513816147,52.55332989050964],"type":"Point"}
}