{
  "type": "Feature",
  "properties": {
    "date:inception_lower": "2011-07-01",
    "date:inception_upper": "2011-07-01",
    "iso:country": "GB",
    "wof:name": "LE10 0NN",
    "wof:placetype": "postalcode"
  },
  "geometry": {"coordinates":[-1.384375,52.55333],"type":"Point"}
}
