{
  "type": "Feature",
  "properties": {
    "date:inception_lower": "1980-01-01",
    "date:inception_upper": "1980-01-01",
    "iso:country": "GB",
    "wof:name": "DL3 6NH",
    "wof:placetype": "postalcode"
  },
  "geometry": {"coordinates":[-1.557854,54.533831],"type":"Point"}
}
