{
  "type": "Feature",
  "properties": {
    "iso:country":"GB",
    "wof:name":"DL3 6NH",
    "wof:placetype":"postalcode"
},
  "geometry": {"coordinates":[-1.55785437056995,54.5338308644955],"type":"Point"}
}