{
  "type": "Feature",
  "properties": {
    "iso:country":"GB",
    "wof:name":"HU5 5SL",
    "wof:placetype":"postalcode"
},
  "geometry": {"coordinates":[-0.40126977997242,53.76497582321776],"type":"Point"}
}