{
  "type": "Feature",
  "properties": {
    "iso:country":"GB",
    "wof:name":"B38 9EY",
    "wof:placetype":"postalcode"
},
  "geometry": {"coordinates":[-1.92532154586292,52.3916118298902],"type":"Point"}
}