{
  "type": "Feature",
  "properties": {
    "date:inception_lower": "1980-01-01",
    "date:inception_upper": "1980-01-01",
    "iso:country": "GB",
    "wof:name": "NG12 4AH",
    "wof:placetype": "postalcode"
  },
  "geometry": {"coordinates":[-1.113394,52.91179],"type":"Point"}
}
