{
  "type": "Feature",
  "properties": {
    "date:inception_lower": "1988-03-01",
    "date:inception_upper": "1988-03-01",
    "iso:country": "GB",
    "wof:name": "SK6 1PW",
    "wof:placetype": "postalcode"
  },
  "geometry": {"coordinates":[-2.09711,53.429554],"type":"Point"}
}
