{
  "type": "Feature",
  "properties": {
    "iso:country":"GB",
    "wof:name":"NE26 1DN",
    "wof:placetype":"postalcode"
},
  "geometry": {"coordinates":[-1.44724232665866,55.04438174787371],"type":"Point"}
}