{
  "type": "Feature",
  "properties": {
    "date:inception_lower": "1980-01-01",
    "date:inception_upper": "1980-01-01",
    "iso:country": "GB",
    "wof:name": "LE4 5DB",
    "wof:placetype": "postalcode"
  },
  "geometry": {"coordinates":[-1.11922,52.656299],"type":"Point"}
}
