{
  "type": "Feature",
  "properties": {
    "iso:country":"GB",
    "wof:name":"PA16 7AY",
    "wof:placetype":"postalcode"
},
  "geometry": {"coordinates":[-4.79716960348437,55.95141786839333],"type":"Point"}
}