{
  "type": "Feature",
  "properties": {
    "date:inception_lower": "2018-02-01",
    "date:inception_upper": "2018-02-01",
    "iso:country": "GB",
    "wof:name": "DL16 7FU",
    "wof:placetype": "postalcode"
  },
  "geometry": {"coordinates":[-1.598787,54.677125],"type":"Point"}
}
