{
  "type": "Feature",
  "properties": {
    "iso:country": "GB",
    "wof:name": "B38 8AJ",
    "wof:placetype": "postalcode"
  },
  "geometry": {"coordinates":[-1.944153,52.408694],"type":"Point"}
}
