{
  "type": "Feature",
  "properties": {
    "iso:country":"GB",
    "wof:name":"B38 8AJ",
    "wof:placetype":"postalcode"
},
  "geometry": {"coordinates":[-1.94415334807611,52.408694347877],"type":"Point"}
}