{
  "type": "Feature",
  "properties": {
    "iso:country": "GB",
    "wof:name": "SK4 3RP",
    "wof:placetype": "postalcode"
  },
  "geometry": {"coordinates":[-2.203119,53.41912],"type":"Point"}
}
