{
  "type": "Feature",
  "properties": {
    "iso:country":"GB",
    "wof:name":"GU21 6DE",
    "wof:placetype":"postalcode"
},
  "geometry": {"coordinates":[-0.56420179512931,51.3186195986778],"type":"Point"}
}