{
  "type": "Feature",
  "properties": {
    "iso:country": "GB",
    "wof:name": "GU21 6DE",
    "wof:placetype": "postalcode"
  },
  "geometry": {"coordinates":[-0.564202,51.31862],"type":"Point"}
}
