{
  "type": "Feature",
  "properties": {
    "iso:country": "GB",
    "wof:name": "CF72 8PE",
    "wof:placetype": "postalcode"
  },
  "geometry": {"coordinates":[-3.372461,51.517938],"type":"Point"}
}
