{
  "type": "Feature",
  "properties": {
    "iso:country":"GB",
    "wof:name":"CF72 8PE",
    "wof:placetype":"postalcode"
},
  "geometry": {"coordinates":[-3.37246116952997,51.51793755019163],"type":"Point"}
}