{
  "type": "Feature",
  "properties": {
    "iso:country": "GB",
    "wof:name": "NR35 2BE",
    "wof:placetype": "postalcode"
  },
  "geometry": {"coordinates":[1.318271,52.472534],"type":"Point"}
}
