{
  "type": "Feature",
  "properties": {
    "iso:country":"GB",
    "wof:name":"LA14 4HH",
    "wof:placetype":"postalcode"
},
  "geometry": {"coordinates":[-3.2165617601384,54.13427648015945],"type":"Point"}
}