{
  "type": "Feature",
  "properties": {
    "iso:country": "GB",
    "wof:name": "WR9 7JP",
    "wof:placetype": "postalcode"
  },
  "geometry": {"coordinates":[-2.170693,52.252429],"type":"Point"}
}
