{
  "type": "Feature",
  "properties": {
    "date:inception_lower": "2011-07-01",
    "date:inception_upper": "2011-07-01",
    "iso:country": "GB",
    "wof:name": "HA2 0EJ",
    "wof:placetype": "postalcode"
  },
  "geometry": {"coordinates":[-0.346966,51.568882],"type":"Point"}
}
