{
  "type": "Feature",
  "properties": {
    "iso:country": "GB",
    "wof:name": "SW14 8QR",
    "wof:placetype": "postalcode"
  },
  "geometry": {"coordinates":[-0.264439,51.464745],"type":"Point"}
}
