{
  "type": "Feature",
  "properties": {
    "date:inception_lower": "1998-06-01",
    "date:inception_upper": "1998-06-01",
    "iso:country": "GB",
    "wof:name": "YO16 7QN",
    "wof:placetype": "postalcode"
  },
  "geometry": {"coordinates":[-0.213477,54.097581],"type":"Point"}
}
