{
  "type": "Feature",
  "properties": {
    "iso:country":"GB",
    "wof:name":"YO16 7QN",
    "wof:placetype":"postalcode"
},
  "geometry": {"coordinates":[-0.21347670913612,54.09758135483361],"type":"Point"}
}