{
  "type": "Feature",
  "properties": {
    "iso:country": "GB",
    "wof:name": "YO16 7QN",
    "wof:placetype": "postalcode"
  },
  "geometry": {"coordinates":[-0.213477,54.097581],"type":"Point"}
}
