{
  "type": "Feature",
  "properties": {
    "iso:country":"GB",
    "wof:name":"CV4 8ER",
    "wof:placetype":"postalcode"
},
  "geometry": {"coordinates":[-1.56735700494689,52.39175254401626],"type":"Point"}
}