{
  "type": "Feature",
  "properties": {
    "iso:country": "GB",
    "wof:name": "CV4 8ER",
    "wof:placetype": "postalcode"
  },
  "geometry": {"coordinates":[-1.567357,52.391753],"type":"Point"}
}
