{
  "type": "Feature",
  "properties": {
    "iso:country": "GB",
    "wof:name": "WF2 6QD",
    "wof:placetype": "postalcode"
  },
  "geometry": {"coordinates":[-1.497164,53.638426],"type":"Point"}
}
