{
  "type": "Feature",
  "properties": {
    "iso:country":"GB",
    "wof:name":"LD7 1HU",
    "wof:placetype":"postalcode"
},
  "geometry": {"coordinates":[-3.04731113643372,52.34225662718619],"type":"Point"}
}