{
  "type": "Feature",
  "properties": {
    "iso:country": "GB",
    "wof:name": "LD7 1HU",
    "wof:placetype": "postalcode"
  },
  "geometry": {"coordinates":[-3.04731,52.342269],"type":"Point"}
}
