{
  "type": "Feature",
  "properties": {
    "iso:country":"GB",
    "wof:name":"TN6 3SH",
    "wof:placetype":"postalcode"
},
  "geometry": {"coordinates":[0.16473597605158,51.03736124175327],"type":"Point"}
}