{
  "type": "Feature",
  "properties": {
    "iso:country": "GB",
    "wof:name": "TN6 3SH",
    "wof:placetype": "postalcode"
  },
  "geometry": {"coordinates":[0.164736,51.037361],"type":"Point"}
}
