{
  "type": "Feature",
  "properties": {
    "iso:country": "GB",
    "wof:name": "HD3 4BT",
    "wof:placetype": "postalcode"
  },
  "geometry": {"coordinates":[-1.824788,53.653866],"type":"Point"}
}
