{
  "type": "Feature",
  "properties": {
    "date:inception_lower":"1992-01-01",
    "date:inception_upper":"1992-01-31",
    "iso:country":"GB",
    "wof:name":"PE12 9QX",
    "wof:placetype":"postalcode"
},
  "geometry": {"coordinates":[0.179527,52.769715],"type":"Point"}
}