{
  "type": "Feature",
  "properties": {
    "iso:country":"GB",
    "wof:name":"PE12 9QX",
    "wof:placetype":"postalcode"
},
  "geometry": {"coordinates":[0.17952641651985,52.76968631381173],"type":"Point"}
}