{
  "type": "Feature",
  "properties": {
    "date:inception_lower": "2007-11-01",
    "date:inception_upper": "2007-11-01",
    "iso:country": "GB",
    "wof:name": "WF15 7WT",
    "wof:placetype": "postalcode"
  },
  "geometry": {"coordinates":[-1.611622,53.708106],"type":"Point"}
}
