{
  "type": "Feature",
  "properties": {
    "iso:country":"GB",
    "wof:name":"BN2 8DN",
    "wof:placetype":"postalcode"
},
  "geometry": {"coordinates":[-0.02255277236918,50.80512465274565],"type":"Point"}
}