{
  "type": "Feature",
  "properties": {
    "date:inception_lower": "1980-01-01",
    "date:inception_upper": "1980-01-01",
    "iso:country": "GB",
    "wof:name": "IP19 0BE",
    "wof:placetype": "postalcode"
  },
  "geometry": {"coordinates":[1.436384,52.358836],"type":"Point"}
}
