{
  "type": "Feature",
  "properties": {
    "iso:country":"GB",
    "wof:name":"IP19 0BE",
    "wof:placetype":"postalcode"
},
  "geometry": {"coordinates":[1.43638372664806,52.35883583781606],"type":"Point"}
}