{
  "type": "Feature",
  "properties": {
    "iso:country": "GB",
    "wof:name": "B71 3EN",
    "wof:placetype": "postalcode"
  },
  "geometry": {"coordinates":[-1.9722,52.54392],"type":"Point"}
}
