{
  "type": "Feature",
  "properties": {
    "iso:country":"GB",
    "wof:name":"M33 3RP",
    "wof:placetype":"postalcode"
},
  "geometry": {"coordinates":[-2.32336269987891,53.41010872431765],"type":"Point"}
}