{
  "type": "Feature",
  "properties": {
    "iso:country":"GB",
    "wof:name":"KT11 3DT",
    "wof:placetype":"postalcode"
},
  "geometry": {"coordinates":[-0.40991952076423,51.32779530126192],"type":"Point"}
}