{
  "type": "Feature",
  "properties": {
    "iso:country":"GB",
    "wof:name":"PO20 7JH",
    "wof:placetype":"postalcode"
},
  "geometry": {"coordinates":[-0.8456998683955,50.76664881680936],"type":"Point"}
}