{
  "type": "Feature",
  "properties": {
    "iso:country":"GB",
    "wof:name":"W12 9UH",
    "wof:placetype":"postalcode"
},
  "geometry": {"coordinates":[-0.25267753345724,51.50204221089829],"type":"Point"}
}