{
  "type": "Feature",
  "properties": {
    "iso:country":"GB",
    "wof:name":"DT7 3TE",
    "wof:placetype":"postalcode"
},
  "geometry": {"coordinates":[-2.95775518801694,50.7352939261318],"type":"Point"}
}