{
  "type": "Feature",
  "properties": {
    "iso:country":"GB",
    "wof:name":"EX39 4JT",
    "wof:placetype":"postalcode"
},
  "geometry": {"coordinates":[-4.1771486604539,51.0538756206541],"type":"Point"}
}