{
  "type": "Feature",
  "properties": {
    "iso:country": "GB",
    "wof:name": "EX39 4JT",
    "wof:placetype": "postalcode"
  },
  "geometry": {"coordinates":[-4.177149,51.053876],"type":"Point"}
}
