{
  "type": "Feature",
  "properties": {
    "iso:country": "GB",
    "wof:name": "WD23 2DQ",
    "wof:placetype": "postalcode"
  },
  "geometry": {"coordinates":[-0.380352,51.662307],"type":"Point"}
}
