{
  "type": "Feature",
  "properties": {
    "date:inception_lower": "1995-07-01",
    "date:inception_upper": "1995-07-01",
    "iso:country": "GB",
    "wof:name": "RG40 5RL",
    "wof:placetype": "postalcode"
  },
  "geometry": {"coordinates":[-0.820329,51.437971],"type":"Point"}
}
