{
  "type": "Feature",
  "properties": {
    "iso:country":"GB",
    "wof:name":"RG40 5RL",
    "wof:placetype":"postalcode"
},
  "geometry": {"coordinates":[-0.82032943975997,51.43797137248637],"type":"Point"}
}