{
  "type": "Feature",
  "properties": {
    "iso:country": "GB",
    "wof:name": "RG40 5RL",
    "wof:placetype": "postalcode"
  },
  "geometry": {"coordinates":[-0.820329,51.437971],"type":"Point"}
}
