{
  "type": "Feature",
  "properties": {
    "date:inception_lower":"1999-12-01",
    "date:inception_upper":"1999-12-31",
    "iso:country":"GB",
    "wof:name":"CV47 9PE",
    "wof:placetype":"postalcode"
},
  "geometry": {"coordinates":[-1.396632,52.282798],"type":"Point"}
}