{
  "type": "Feature",
  "properties": {
    "iso:country":"GB",
    "wof:name":"CV47 9PE",
    "wof:placetype":"postalcode"
},
  "geometry": {"coordinates":[-1.39663184957225,52.2827975451235],"type":"Point"}
}