{
  "type": "Feature",
  "properties": {
    "iso:country": "GB",
    "wof:name": "MK6 2LT",
    "wof:placetype": "postalcode"
  },
  "geometry": {"coordinates":[-0.757816,52.028083],"type":"Point"}
}
