{
  "type": "Feature",
  "properties": {
    "date:inception_lower": "1991-07-01",
    "date:inception_upper": "1991-07-01",
    "iso:country": "GB",
    "wof:name": "ML3 8HW",
    "wof:placetype": "postalcode"
  },
  "geometry": {"coordinates":[-4.054429,55.767406],"type":"Point"}
}
