{
  "type": "Feature",
  "properties": {
    "iso:country":"GB",
    "wof:name":"B93 8AN",
    "wof:placetype":"postalcode"
},
  "geometry": {"coordinates":[-1.76122466085064,52.38095711555764],"type":"Point"}
}