{
  "type": "Feature",
  "properties": {
    "iso:country": "GB",
    "wof:name": "LE2 6GF",
    "wof:placetype": "postalcode"
  },
  "geometry": {"coordinates":[-1.121608,52.602035],"type":"Point"}
}
