{
  "type": "Feature",
  "properties": {
    "iso:country":"GB",
    "wof:name":"LE2 6GF",
    "wof:placetype":"postalcode"
},
  "geometry": {"coordinates":[-1.12160845178802,52.60203496182837],"type":"Point"}
}