{
  "type": "Feature",
  "properties": {
    "date:inception_lower": "2011-10-01",
    "date:inception_upper": "2011-10-01",
    "iso:country": "GB",
    "wof:name": "PE30 4SA",
    "wof:placetype": "postalcode"
  },
  "geometry": {"coordinates":[0.432273,52.749702],"type":"Point"}
}
