{
  "type": "Feature",
  "properties": {
    "iso:country": "GB",
    "wof:name": "DH8 0AS",
    "wof:placetype": "postalcode"
  },
  "geometry": {"coordinates":[-1.848563,54.86508],"type":"Point"}
}
