{
  "type": "Feature",
  "properties": {
    "date:inception_lower":"2002-09-01",
    "date:inception_upper":"2002-09-30",
    "iso:country":"GB",
    "wof:name":"DE14 2SY",
    "wof:placetype":"postalcode"
},
  "geometry": {"coordinates":[-1.663844,52.804123],"type":"Point"}
}