{
  "type": "Feature",
  "properties": {
    "date:inception_lower": "2002-09-01",
    "date:inception_upper": "2002-09-01",
    "iso:country": "GB",
    "wof:name": "DE14 2SY",
    "wof:placetype": "postalcode"
  },
  "geometry": {"coordinates":[-1.66396,52.806308],"type":"Point"}
}
