{
  "type": "Feature",
  "properties": {
    "iso:country": "GB",
    "wof:name": "DE14 2SY",
    "wof:placetype": "postalcode"
  },
  "geometry": {"coordinates":[-1.663844,52.804123],"type":"Point"}
}
