{
  "type": "Feature",
  "properties": {
    "iso:country":"GB",
    "wof:name":"M43 7FP",
    "wof:placetype":"postalcode"
},
  "geometry": {"coordinates":[-2.14077147429323,53.47981018152056],"type":"Point"}
}