{
  "type": "Feature",
  "properties": {
    "iso:country": "GB",
    "wof:name": "NG4 1DJ",
    "wof:placetype": "postalcode"
  },
  "geometry": {"coordinates":[-1.090142,52.963286],"type":"Point"}
}
