{
  "type": "Feature",
  "properties": {
    "iso:country":"GB",
    "wof:name":"M2 2EE",
    "wof:placetype":"postalcode"
},
  "geometry": {"coordinates":[-2.24184715908434,53.47974704067003],"type":"Point"}
}