{
  "type": "Feature",
  "properties": {
    "iso:country": "GB",
    "wof:name": "B20 1JL",
    "wof:placetype": "postalcode"
  },
  "geometry": {"coordinates":[-1.934793,52.526126],"type":"Point"}
}
