{
  "type": "Feature",
  "properties": {
    "iso:country":"GB",
    "wof:name":"DN4 9AS",
    "wof:placetype":"postalcode"
},
  "geometry": {"coordinates":[-1.15082392178264,53.49206930817027],"type":"Point"}
}