{
  "type": "Feature",
  "properties": {
    "date:inception_lower":"1980-01-01",
    "date:inception_upper":"1980-01-31",
    "iso:country":"GB",
    "wof:name":"PL1 1PY",
    "wof:placetype":"postalcode"
},
  "geometry": {"coordinates":[-4.147566,50.372477],"type":"Point"}
}