{
  "type": "Feature",
  "properties": {
    "iso:country":"GB",
    "wof:name":"PL1 1PY",
    "wof:placetype":"postalcode"
},
  "geometry": {"coordinates":[-4.14756560895692,50.37247654244533],"type":"Point"}
}