{
  "type": "Feature",
  "properties": {
    "iso:country":"GB",
    "wof:name":"NE65 7DD",
    "wof:placetype":"postalcode"
},
  "geometry": {"coordinates":[-2.26976184479386,55.39173205753596],"type":"Point"}
}