{
  "type": "Feature",
  "properties": {
    "date:inception_lower":"1980-01-01",
    "date:inception_upper":"1980-01-31",
    "iso:country":"GB",
    "wof:name":"NE65 7DD",
    "wof:placetype":"postalcode"
},
  "geometry": {"coordinates":[-2.269762,55.391732],"type":"Point"}
}