{
  "type": "Feature",
  "properties": {
    "iso:country": "GB",
    "wof:name": "LL52 0LL",
    "wof:placetype": "postalcode"
  },
  "geometry": {"coordinates":[-4.240908,52.920224],"type":"Point"}
}
