{
  "type": "Feature",
  "properties": {
    "iso:country":"GB",
    "wof:name":"W9 3UF",
    "wof:placetype":"postalcode"
},
  "geometry": {"coordinates":[-0.19671862970225,51.52167095597758],"type":"Point"}
}