{
  "type": "Feature",
  "properties": {
    "date:inception_lower": "2002-06-01",
    "date:inception_upper": "2002-06-01",
    "iso:country": "GB",
    "wof:name": "W9 3UF",
    "wof:placetype": "postalcode"
  },
  "geometry": {"coordinates":[-0.196719,51.521671],"type":"Point"}
}
