{
  "type": "Feature",
  "properties": {
    "iso:country":"GB",
    "wof:name":"SE18 1LB",
    "wof:placetype":"postalcode"
},
  "geometry": {"coordinates":[0.0942139773333,51.48672921899846],"type":"Point"}
}