{
  "type": "Feature",
  "properties": {
    "date:inception_lower": "1980-01-01",
    "date:inception_upper": "1980-01-01",
    "iso:country": "GB",
    "wof:name": "LS25 1BG",
    "wof:placetype": "postalcode"
  },
  "geometry": {"coordinates":[-1.393915,53.789777],"type":"Point"}
}
