{
  "type": "Feature",
  "properties": {
    "iso:country": "GB",
    "wof:name": "LS25 1BG",
    "wof:placetype": "postalcode"
  },
  "geometry": {"coordinates":[-1.393915,53.789777],"type":"Point"}
}
