{
  "type": "Feature",
  "properties": {
    "iso:country": "GB",
    "wof:name": "LL30 1AD",
    "wof:placetype": "postalcode"
  },
  "geometry": {"coordinates":[-3.824767,53.321327],"type":"Point"}
}
