{
  "type": "Feature",
  "properties": {
    "date:inception_lower": "2005-11-01",
    "date:inception_upper": "2005-11-01",
    "iso:country": "GB",
    "wof:name": "LL30 1AD",
    "wof:placetype": "postalcode"
  },
  "geometry": {"coordinates":[-3.824767,53.321327],"type":"Point"}
}
