{
  "type": "Feature",
  "properties": {
    "iso:country": "GB",
    "wof:name": "CH7 4RE",
    "wof:placetype": "postalcode"
  },
  "geometry": {"coordinates":[-3.08695,53.130589],"type":"Point"}
}
