{
  "type": "Feature",
  "properties": {
    "iso:country":"GB",
    "wof:name":"CH7 4RE",
    "wof:placetype":"postalcode"
},
  "geometry": {"coordinates":[-3.08686148271282,53.13061874772021],"type":"Point"}
}