{
  "type": "Feature",
  "properties": {
    "date:inception_lower": "1980-01-01",
    "date:inception_upper": "1980-01-01",
    "iso:country": "GB",
    "wof:name": "CH7 4RE",
    "wof:placetype": "postalcode"
  },
  "geometry": {"coordinates":[-3.086861,53.130634],"type":"Point"}
}
