{
  "type": "Feature",
  "properties": {
    "iso:country": "GB",
    "wof:name": "AB32 6DA",
    "wof:placetype": "postalcode"
  },
  "geometry": {"coordinates":[-2.30386,57.152159],"type":"Point"}
}
