{
  "type": "Feature",
  "properties": {
    "date:inception_lower":"1997-12-01",
    "date:inception_upper":"1997-12-31",
    "iso:country":"GB",
    "wof:name":"AB32 6DA",
    "wof:placetype":"postalcode"
},
  "geometry": {"coordinates":[-2.30386,57.152159],"type":"Point"}
}