{
  "type": "Feature",
  "properties": {
    "iso:country":"GB",
    "wof:name":"OX26 6JD",
    "wof:placetype":"postalcode"
},
  "geometry": {"coordinates":[-1.15099261746573,51.89738053725359],"type":"Point"}
}