{
  "type": "Feature",
  "properties": {
    "date:inception_lower": "2000-10-01",
    "date:inception_upper": "2000-10-01",
    "iso:country": "GB",
    "wof:name": "OX26 6JD",
    "wof:placetype": "postalcode"
  },
  "geometry": {"coordinates":[-1.150993,51.897381],"type":"Point"}
}
