{
  "type": "Feature",
  "properties": {
    "iso:country": "GB",
    "wof:name": "GL20 6EE",
    "wof:placetype": "postalcode"
  },
  "geometry": {"coordinates":[-2.160354,52.015836],"type":"Point"}
}
