{
  "type": "Feature",
  "properties": {
    "date:inception_lower":"1980-01-01",
    "date:inception_upper":"1980-01-31",
    "iso:country":"GB",
    "wof:name":"GL20 6EE",
    "wof:placetype":"postalcode"
},
  "geometry": {"coordinates":[-2.160354,52.015836],"type":"Point"}
}