{
  "type": "Feature",
  "properties": {
    "iso:country":"GB",
    "wof:name":"ME5 8HD",
    "wof:placetype":"postalcode"
},
  "geometry": {"coordinates":[0.53478182672314,51.34486369533266],"type":"Point"}
}