{
  "type": "Feature",
  "properties": {
    "iso:country":"GB",
    "wof:name":"RG6 1HA",
    "wof:placetype":"postalcode"
},
  "geometry": {"coordinates":[-0.92898256121676,51.44655837275469],"type":"Point"}
}