{
  "type": "Feature",
  "properties": {
    "date:inception_lower":"2006-11-01",
    "date:inception_upper":"2006-11-30",
    "iso:country":"GB",
    "wof:name":"ST14 7FE",
    "wof:placetype":"postalcode"
},
  "geometry": {"coordinates":[-1.886261,52.90643],"type":"Point"}
}