{
  "type": "Feature",
  "properties": {
    "iso:country":"GB",
    "wof:name":"CT5 2HY",
    "wof:placetype":"postalcode"
},
  "geometry": {"coordinates":[1.05229531827454,51.36138654001947],"type":"Point"}
}