{
  "type": "Feature",
  "properties": {
    "iso:country": "GB",
    "wof:name": "CT5 2HY",
    "wof:placetype": "postalcode"
  },
  "geometry": {"coordinates":[1.052295,51.361387],"type":"Point"}
}
