{
  "type": "Feature",
  "properties": {
    "iso:country":"GB",
    "wof:name":"WD23 3BN",
    "wof:placetype":"postalcode"
},
  "geometry": {"coordinates":[-0.35666077422444,51.64931753591762],"type":"Point"}
}