{
  "type": "Feature",
  "properties": {
    "iso:country":"GB",
    "wof:name":"M32 8LS",
    "wof:placetype":"postalcode"
},
  "geometry": {"coordinates":[-2.30617839360381,53.44502064873175],"type":"Point"}
}