{
  "type": "Feature",
  "properties": {
    "iso:country":"GB",
    "wof:name":"ME11 5LU",
    "wof:placetype":"postalcode"
},
  "geometry": {"coordinates":[0.74150817368366,51.40694048666095],"type":"Point"}
}