{
  "type": "Feature",
  "properties": {
    "iso:country": "GB",
    "wof:name": "RG7 3UZ",
    "wof:placetype": "postalcode"
  },
  "geometry": {"coordinates":[-1.066962,51.375425],"type":"Point"}
}
