{
  "type": "Feature",
  "properties": {
    "date:inception_lower":"2012-02-01",
    "date:inception_upper":"2012-02-29",
    "iso:country":"GB",
    "wof:name":"RG7 3UZ",
    "wof:placetype":"postalcode"
},
  "geometry": {"coordinates":[-1.066962,51.375425],"type":"Point"}
}