{
  "type": "Feature",
  "properties": {
    "iso:country":"GB",
    "wof:name":"RG7 3UZ",
    "wof:placetype":"postalcode"
},
  "geometry": {"coordinates":[-1.0669618722439,51.37542479890193],"type":"Point"}
}