{
  "type": "Feature",
  "properties": {
    "iso:country": "GB",
    "wof:name": "BH19 2AG",
    "wof:placetype": "postalcode"
  },
  "geometry": {"coordinates":[-1.955087,50.606638],"type":"Point"}
}
