{
  "type": "Feature",
  "properties": {
    "date:inception_lower":"1980-01-01",
    "date:inception_upper":"1980-01-31",
    "iso:country":"GB",
    "wof:name":"TN12 0AZ",
    "wof:placetype":"postalcode"
},
  "geometry": {"coordinates":[0.553492,51.157333],"type":"Point"}
}