{
  "type": "Feature",
  "properties": {
    "iso:country":"GB",
    "wof:name":"TN12 0AZ",
    "wof:placetype":"postalcode"
},
  "geometry": {"coordinates":[0.55349168711057,51.15733264969462],"type":"Point"}
}