{
  "type": "Feature",
  "properties": {
    "iso:country":"GB",
    "wof:name":"DL14 9NT",
    "wof:placetype":"postalcode"
},
  "geometry": {"coordinates":[-1.72984087199315,54.60836133671822],"type":"Point"}
}