{
  "type": "Feature",
  "properties": {
    "iso:country":"GB",
    "wof:name":"HU3 5DG",
    "wof:placetype":"postalcode"
},
  "geometry": {"coordinates":[-0.3739863981375,53.73525041554376],"type":"Point"}
}