{
  "type": "Feature",
  "properties": {
    "iso:country":"GB",
    "wof:name":"SW19 7HR",
    "wof:placetype":"postalcode"
},
  "geometry": {"coordinates":[-0.20136394060961,51.43518060304266],"type":"Point"}
}