{
  "type": "Feature",
  "properties": {
    "iso:country": "GB",
    "wof:name": "SW19 7HR",
    "wof:placetype": "postalcode"
  },
  "geometry": {"coordinates":[-0.20124,51.435152],"type":"Point"}
}
