{
  "type": "Feature",
  "properties": {
    "date:inception_lower": "1980-01-01",
    "date:inception_upper": "1980-01-01",
    "iso:country": "GB",
    "wof:name": "SA12 7NT",
    "wof:placetype": "postalcode"
  },
  "geometry": {"coordinates":[-3.819441,51.597471],"type":"Point"}
}
