{
  "type": "Feature",
  "properties": {
    "date:inception_lower": "2022-09-01",
    "date:inception_upper": "2022-09-01",
    "iso:country": "GB",
    "wof:name": "WS10 9FE",
    "wof:placetype": "postalcode"
  },
  "geometry": {"coordinates":[-2.017753,52.552408],"type":"Point"}
}
