{
  "type": "Feature",
  "properties": {
    "iso:country":"GB",
    "wof:name":"NP19 0LL",
    "wof:placetype":"postalcode"
},
  "geometry": {"coordinates":[-2.97548685368081,51.5807979069336],"type":"Point"}
}