{
  "type": "Feature",
  "properties": {
    "iso:country": "GB",
    "wof:name": "NP19 0LL",
    "wof:placetype": "postalcode"
  },
  "geometry": {"coordinates":[-2.975493,51.5808],"type":"Point"}
}
