{
  "type": "Feature",
  "properties": {
    "date:inception_lower":"1980-01-01",
    "date:inception_upper":"1980-01-31",
    "iso:country":"GB",
    "wof:name":"SW17 9TW",
    "wof:placetype":"postalcode"
},
  "geometry": {"coordinates":[-0.153965,51.421072],"type":"Point"}
}