{
  "type": "Feature",
  "properties": {
    "iso:country": "GB",
    "wof:name": "SW17 9TW",
    "wof:placetype": "postalcode"
  },
  "geometry": {"coordinates":[-0.153965,51.421072],"type":"Point"}
}
