{
  "type": "Feature",
  "properties": {
    "iso:country":"GB",
    "wof:name":"E1W 1YU",
    "wof:placetype":"postalcode"
},
  "geometry": {"coordinates":[-0.06791224290074,51.50762386132638],"type":"Point"}
}