{
  "type": "Feature",
  "properties": {
    "date:inception_lower": "1999-12-01",
    "date:inception_upper": "1999-12-01",
    "iso:country": "GB",
    "wof:name": "E1W 1YU",
    "wof:placetype": "postalcode"
  },
  "geometry": {"coordinates":[-0.067912,51.507624],"type":"Point"}
}
