{
  "type": "Feature",
  "properties": {
    "date:inception_lower": "1980-01-01",
    "date:inception_upper": "1980-01-01",
    "iso:country": "GB",
    "wof:name": "DD3 7HU",
    "wof:placetype": "postalcode"
  },
  "geometry": {"coordinates":[-2.972497,56.473419],"type":"Point"}
}
