{
  "type": "Feature",
  "properties": {
    "date:inception_lower": "2022-07-01",
    "date:inception_upper": "2022-07-01",
    "iso:country": "GB",
    "wof:name": "FY8 5FU",
    "wof:placetype": "postalcode"
  },
  "geometry": {"coordinates":[-2.954746,53.738748],"type":"Point"}
}
