{
  "type": "Feature",
  "properties": {
    "iso:country":"GB",
    "wof:name":"SA18 3DZ",
    "wof:placetype":"postalcode"
},
  "geometry": {"coordinates":[-4.03785264883765,51.8031265758176],"type":"Point"}
}