{
  "type": "Feature",
  "properties": {
    "iso:country":"GB",
    "wof:name":"SY3 6DR",
    "wof:placetype":"postalcode"
},
  "geometry": {"coordinates":[-2.78002062511327,52.6963499261828],"type":"Point"}
}