{
  "type": "Feature",
  "properties": {
    "iso:country":"GB",
    "wof:name":"DE56 1GP",
    "wof:placetype":"postalcode"
},
  "geometry": {"coordinates":[-1.47358534750306,53.02822122414261],"type":"Point"}
}