{
  "type": "Feature",
  "properties": {
    "iso:country":"GB",
    "wof:name":"WF8 2TR",
    "wof:placetype":"postalcode"
},
  "geometry": {"coordinates":[-1.30376902572255,53.68959944206107],"type":"Point"}
}