{
  "type": "Feature",
  "properties": {
    "iso:country":"GB",
    "wof:name":"BS32 4LB",
    "wof:placetype":"postalcode"
},
  "geometry": {"coordinates":[-2.56585198732365,51.54500504607393],"type":"Point"}
}