{
  "type": "Feature",
  "properties": {
    "date:inception_lower":"1997-12-01",
    "date:inception_upper":"1997-12-31",
    "iso:country":"GB",
    "wof:name":"BS32 4LB",
    "wof:placetype":"postalcode"
},
  "geometry": {"coordinates":[-2.565852,51.545005],"type":"Point"}
}