{
  "type": "Feature",
  "properties": {
    "iso:country":"GB",
    "wof:name":"NR33 9NA",
    "wof:placetype":"postalcode"
},
  "geometry": {"coordinates":[1.72010493727318,52.4729252275038],"type":"Point"}
}