{
  "type": "Feature",
  "properties": {
    "iso:country":"GB",
    "wof:name":"N16 6BX",
    "wof:placetype":"postalcode"
},
  "geometry": {"coordinates":[-0.06363927821381,51.57438608441376],"type":"Point"}
}