{
  "type": "Feature",
  "properties": {
    "iso:country": "GB",
    "wof:name": "DL4 2GU",
    "wof:placetype": "postalcode"
  },
  "geometry": {"coordinates":[-1.631116,54.626372],"type":"Point"}
}
