{
  "type": "Feature",
  "properties": {
    "iso:country":"GB",
    "wof:name":"DL4 2GU",
    "wof:placetype":"postalcode"
},
  "geometry": {"coordinates":[-1.63086024587672,54.62603786525388],"type":"Point"}
}