{
  "type": "Feature",
  "properties": {
    "date:inception_lower": "2013-12-01",
    "date:inception_upper": "2013-12-01",
    "iso:country": "GB",
    "wof:name": "DL4 2GU",
    "wof:placetype": "postalcode"
  },
  "geometry": {"coordinates":[-1.631116,54.626372],"type":"Point"}
}
