{
  "type": "Feature",
  "properties": {
    "date:inception_lower": "1995-07-01",
    "date:inception_upper": "1995-07-01",
    "iso:country": "GB",
    "wof:name": "HS2 0EP",
    "wof:placetype": "postalcode"
  },
  "geometry": {"coordinates":[-6.165448,58.241953],"type":"Point"}
}
