{
  "type": "Feature",
  "properties": {
    "iso:country":"GB",
    "wof:name":"HS2 0EP",
    "wof:placetype":"postalcode"
},
  "geometry": {"coordinates":[-6.16544765432462,58.24195327946167],"type":"Point"}
}