{
  "type": "Feature",
  "properties": {
    "date:inception_lower": "2019-11-01",
    "date:inception_upper": "2019-11-01",
    "iso:country": "GB",
    "wof:name": "CO15 6EY",
    "wof:placetype": "postalcode"
  },
  "geometry": {"coordinates":[1.162509,51.800038],"type":"Point"}
}
