{
  "type": "Feature",
  "properties": {
    "iso:country":"GB",
    "wof:name":"SS0 0PN",
    "wof:placetype":"postalcode"
},
  "geometry": {"coordinates":[0.67948411465147,51.55332706615947],"type":"Point"}
}