{
  "type": "Feature",
  "properties": {
    "iso:country": "GB",
    "wof:name": "SS0 0PN",
    "wof:placetype": "postalcode"
  },
  "geometry": {"coordinates":[0.679484,51.553327],"type":"Point"}
}
