{
  "type": "Feature",
  "properties": {
    "iso:country": "GB",
    "wof:name": "CM3 4LN",
    "wof:placetype": "postalcode"
  },
  "geometry": {"coordinates":[0.602608,51.702784],"type":"Point"}
}
