{
  "type": "Feature",
  "properties": {
    "iso:country":"GB",
    "wof:name":"CM3 4LN",
    "wof:placetype":"postalcode"
},
  "geometry": {"coordinates":[0.60260792690986,51.7027836194229],"type":"Point"}
}