{
  "type": "Feature",
  "properties": {
    "date:inception_lower": "1980-01-01",
    "date:inception_upper": "1980-01-01",
    "iso:country": "GB",
    "wof:name": "CM3 4LN",
    "wof:placetype": "postalcode"
  },
  "geometry": {"coordinates":[0.602608,51.702784],"type":"Point"}
}
