{
  "type": "Feature",
  "properties": {
    "date:inception_lower": "2020-08-01",
    "date:inception_upper": "2020-08-01",
    "iso:country": "GB",
    "wof:name": "GL3 9GQ",
    "wof:placetype": "postalcode"
  },
  "geometry": {"coordinates":[-2.167993,51.839243],"type":"Point"}
}
