{
  "type": "Feature",
  "properties": {
    "iso:country":"GB",
    "wof:name":"GL15 6JY",
    "wof:placetype":"postalcode"
},
  "geometry": {"coordinates":[-2.57101799330736,51.75570091992944],"type":"Point"}
}