{
  "type": "Feature",
  "properties": {
    "iso:country":"GB",
    "wof:name":"DD5 3RA",
    "wof:placetype":"postalcode"
},
  "geometry": {"coordinates":[-2.84811311232907,56.4826417856347],"type":"Point"}
}