{
  "type": "Feature",
  "properties": {
    "iso:country": "GB",
    "wof:name": "DL16 6XW",
    "wof:placetype": "postalcode"
  },
  "geometry": {"coordinates":[-1.611663,54.709725],"type":"Point"}
}
