{
  "type": "Feature",
  "properties": {
    "iso:country":"GB",
    "wof:name":"DL16 6XW",
    "wof:placetype":"postalcode"
},
  "geometry": {"coordinates":[-1.61166276825502,54.7097250872642],"type":"Point"}
}