{
  "type": "Feature",
  "properties": {
    "date:inception_lower": "1984-02-01",
    "date:inception_upper": "1984-02-01",
    "iso:country": "GB",
    "wof:name": "DL16 6XW",
    "wof:placetype": "postalcode"
  },
  "geometry": {"coordinates":[-1.611663,54.709725],"type":"Point"}
}
