{
  "type": "Feature",
  "properties": {
    "iso:country":"GB",
    "wof:name":"LA3 1HU",
    "wof:placetype":"postalcode"
},
  "geometry": {"coordinates":[-2.88028110558189,54.06025205239702],"type":"Point"}
}