{
  "type": "Feature",
  "properties": {
    "iso:country":"GB",
    "wof:name":"BR1 1AJ",
    "wof:placetype":"postalcode"
},
  "geometry": {"coordinates":[0.01883308084946,51.40048854192004],"type":"Point"}
}