{
  "type": "Feature",
  "properties": {
    "iso:country": "GB",
    "wof:name": "BR1 1AJ",
    "wof:placetype": "postalcode"
  },
  "geometry": {"coordinates":[0.018833,51.400489],"type":"Point"}
}
