{
  "type": "Feature",
  "properties": {
    "date:inception_lower":"1997-12-01",
    "date:inception_upper":"1997-12-31",
    "iso:country":"GB",
    "wof:name":"BS35 4PB",
    "wof:placetype":"postalcode"
},
  "geometry": {"coordinates":[-2.663561,51.563519],"type":"Point"}
}