{
  "type": "Feature",
  "properties": {
    "iso:country": "GB",
    "wof:name": "BS35 4PB",
    "wof:placetype": "postalcode"
  },
  "geometry": {"coordinates":[-2.663561,51.563519],"type":"Point"}
}
