{
  "type": "Feature",
  "properties": {
    "iso:country":"GB",
    "wof:name":"BS35 4PB",
    "wof:placetype":"postalcode"
},
  "geometry": {"coordinates":[-2.6635610825804,51.56351900311169],"type":"Point"}
}