{
  "type": "Feature",
  "properties": {
    "iso:country":"GB",
    "wof:name":"NW6 3HN",
    "wof:placetype":"postalcode"
},
  "geometry": {"coordinates":[-0.18703817292227,51.54147593455089],"type":"Point"}
}