{
  "type": "Feature",
  "properties": {
    "date:inception_lower": "1980-01-01",
    "date:inception_upper": "1980-01-01",
    "iso:country": "GB",
    "wof:name": "NE12 8PY",
    "wof:placetype": "postalcode"
  },
  "geometry": {"coordinates":[-1.585256,55.009513],"type":"Point"}
}
