{
  "type": "Feature",
  "properties": {
    "iso:country":"GB",
    "wof:name":"S61 4ER",
    "wof:placetype":"postalcode"
},
  "geometry": {"coordinates":[-1.3698375128981,53.45492596779719],"type":"Point"}
}