{
  "type": "Feature",
  "properties": {
    "iso:country": "GB",
    "wof:name": "TQ6 9DS",
    "wof:placetype": "postalcode"
  },
  "geometry": {"coordinates":[-3.581123,50.350927],"type":"Point"}
}
