{
  "type": "Feature",
  "properties": {
    "iso:country":"GB",
    "wof:name":"OX12 0JB",
    "wof:placetype":"postalcode"
},
  "geometry": {"coordinates":[-1.4016230644168,51.63267468846836],"type":"Point"}
}