{
  "type": "Feature",
  "properties": {
    "iso:country": "GB",
    "wof:name": "OX12 0JB",
    "wof:placetype": "postalcode"
  },
  "geometry": {"coordinates":[-1.401623,51.632675],"type":"Point"}
}
