{
  "type": "Feature",
  "properties": {
    "iso:country":"GB",
    "wof:name":"E18 2DT",
    "wof:placetype":"postalcode"
},
  "geometry": {"coordinates":[0.01776153588798,51.58854479474001],"type":"Point"}
}