{
  "type": "Feature",
  "properties": {
    "iso:country":"GB",
    "wof:name":"CO9 2QB",
    "wof:placetype":"postalcode"
},
  "geometry": {"coordinates":[0.68826255524077,51.97729826579278],"type":"Point"}
}