{
  "type": "Feature",
  "properties": {
    "iso:country": "GB",
    "wof:name": "CO4 5JL",
    "wof:placetype": "postalcode"
  },
  "geometry": {"coordinates":[0.899182,51.910164],"type":"Point"}
}
