{
  "type": "Feature",
  "properties": {
    "date:inception_lower": "1980-01-01",
    "date:inception_upper": "1980-01-01",
    "iso:country": "GB",
    "wof:name": "HR1 3DD",
    "wof:placetype": "postalcode"
  },
  "geometry": {"coordinates":[-2.67668,52.13676],"type":"Point"}
}
