{
  "type": "Feature",
  "properties": {
    "iso:country":"GB",
    "wof:name":"DN31 2EF",
    "wof:placetype":"postalcode"
},
  "geometry": {"coordinates":[-0.09879492467793,53.56606034435679],"type":"Point"}
}