{
  "type": "Feature",
  "properties": {
    "iso:country":"GB",
    "wof:name":"DD4 8NS",
    "wof:placetype":"postalcode"
},
  "geometry": {"coordinates":[-2.91529538232811,56.47898419055469],"type":"Point"}
}