{
  "type": "Feature",
  "properties": {
    "iso:country":"GB",
    "wof:name":"PE11 3JG",
    "wof:placetype":"postalcode"
},
  "geometry": {"coordinates":[-0.13416255033522,52.81310230722816],"type":"Point"}
}