{
  "type": "Feature",
  "properties": {
    "iso:country": "GB",
    "wof:name": "PE11 3JG",
    "wof:placetype": "postalcode"
  },
  "geometry": {"coordinates":[-0.133963,52.81268],"type":"Point"}
}
