{
  "type": "Feature",
  "properties": {
    "iso:country":"GB",
    "wof:name":"BH15 3JG",
    "wof:placetype":"postalcode"
},
  "geometry": {"coordinates":[-1.96119104689322,50.73662406270762],"type":"Point"}
}