{
  "type": "Feature",
  "properties": {
    "iso:country":"GB",
    "wof:name":"IP28 7NZ",
    "wof:placetype":"postalcode"
},
  "geometry": {"coordinates":[0.52119120993584,52.35157091506392],"type":"Point"}
}