{
  "type": "Feature",
  "properties": {
    "iso:country":"GB",
    "wof:name":"B45 8RJ",
    "wof:placetype":"postalcode"
},
  "geometry": {"coordinates":[-1.99880961806763,52.39023279209287],"type":"Point"}
}