{
  "type": "Feature",
  "properties": {
    "iso:country":"GB",
    "wof:name":"PE28 2PQ",
    "wof:placetype":"postalcode"
},
  "geometry": {"coordinates":[-0.17846326770187,52.38472381054582],"type":"Point"}
}