{
  "type": "Feature",
  "properties": {
    "iso:country":"GB",
    "wof:name":"WC1N 2QL",
    "wof:placetype":"postalcode"
},
  "geometry": {"coordinates":[-0.11571138320788,51.52159361083518],"type":"Point"}
}