{
  "type": "Feature",
  "properties": {
    "iso:country": "GB",
    "wof:name": "DN14 0HZ",
    "wof:placetype": "postalcode"
  },
  "geometry": {"coordinates":[-1.151688,53.687235],"type":"Point"}
}
