{
  "type": "Feature",
  "properties": {
    "iso:country":"GB",
    "wof:name":"BB9 7HQ",
    "wof:placetype":"postalcode"
},
  "geometry": {"coordinates":[-2.22113520209838,53.83618677230009],"type":"Point"}
}