{
  "type": "Feature",
  "properties": {
    "iso:country": "GB",
    "wof:name": "BA3 3TY",
    "wof:placetype": "postalcode"
  },
  "geometry": {"coordinates":[-2.460691,51.289886],"type":"Point"}
}
