{
  "type": "Feature",
  "properties": {
    "iso:country":"GB",
    "wof:name":"ML6 8DX",
    "wof:placetype":"postalcode"
},
  "geometry": {"coordinates":[-3.95925978490116,55.85825420832908],"type":"Point"}
}