{
  "type": "Feature",
  "properties": {
    "iso:country": "GB",
    "wof:name": "ML6 8DX",
    "wof:placetype": "postalcode"
  },
  "geometry": {"coordinates":[-3.95926,55.858254],"type":"Point"}
}
