{
  "type": "Feature",
  "properties": {
    "iso:country":"GB",
    "wof:name":"CF37 5XF",
    "wof:placetype":"postalcode"
},
  "geometry": {"coordinates":[-3.29568777780255,51.57286128950012],"type":"Point"}
}