{
  "type": "Feature",
  "properties": {
    "date:inception_lower": "1992-08-01",
    "date:inception_upper": "1992-08-01",
    "iso:country": "GB",
    "wof:name": "CF37 5XF",
    "wof:placetype": "postalcode"
  },
  "geometry": {"coordinates":[-3.295688,51.572861],"type":"Point"}
}
