{
  "type": "Feature",
  "properties": {
    "iso:country": "GB",
    "wof:name": "BA15 1DH",
    "wof:placetype": "postalcode"
  },
  "geometry": {"coordinates":[-2.249812,51.344495],"type":"Point"}
}
