{
  "type": "Feature",
  "properties": {
    "iso:country": "GB",
    "wof:name": "PE33 0AL",
    "wof:placetype": "postalcode"
  },
  "geometry": {"coordinates":[0.392127,52.654667],"type":"Point"}
}
