{
  "type": "Feature",
  "properties": {
    "iso:country":"GB",
    "wof:name":"BD19 5EY",
    "wof:placetype":"postalcode"
},
  "geometry": {"coordinates":[-1.71618916782612,53.72304967110269],"type":"Point"}
}