{
  "type": "Feature",
  "properties": {
    "iso:country":"GB",
    "wof:name":"GU1 2PZ",
    "wof:placetype":"postalcode"
},
  "geometry": {"coordinates":[-0.54183038435497,51.24025291485952],"type":"Point"}
}