{
  "type": "Feature",
  "properties": {
    "iso:country":"GB",
    "wof:name":"RH3 7EB",
    "wof:placetype":"postalcode"
},
  "geometry": {"coordinates":[-0.25561532314788,51.24464650570503],"type":"Point"}
}