{
  "type": "Feature",
  "properties": {
    "iso:country":"GB",
    "wof:name":"LL31 9RN",
    "wof:placetype":"postalcode"
},
  "geometry": {"coordinates":[-3.81486622618985,53.28863729476817],"type":"Point"}
}