{
  "type": "Feature",
  "properties": {
    "iso:country":"GB",
    "wof:name":"AL8 6YQ",
    "wof:placetype":"postalcode"
},
  "geometry": {"coordinates":[-0.21739062490837,51.79354294846524],"type":"Point"}
}