{
  "type": "Feature",
  "properties": {
    "iso:country": "GB",
    "wof:name": "AL8 6YQ",
    "wof:placetype": "postalcode"
  },
  "geometry": {"coordinates":[-0.217391,51.793543],"type":"Point"}
}
