{
  "type": "Feature",
  "properties": {
    "iso:country":"GB",
    "wof:name":"BD19 6PA",
    "wof:placetype":"postalcode"
},
  "geometry": {"coordinates":[-1.7492499525513,53.72933410769129],"type":"Point"}
}