{
  "type": "Feature",
  "properties": {
    "date:inception_lower":"1980-01-01",
    "date:inception_upper":"1980-01-31",
    "iso:country":"GB",
    "wof:name":"MK45 1BG",
    "wof:placetype":"postalcode"
},
  "geometry": {"coordinates":[-0.49918,52.009193],"type":"Point"}
}