{
  "type": "Feature",
  "properties": {
    "iso:country": "GB",
    "wof:name": "MK45 1BG",
    "wof:placetype": "postalcode"
  },
  "geometry": {"coordinates":[-0.49918,52.009193],"type":"Point"}
}
