{
  "type": "Feature",
  "properties": {
    "iso:country":"GB",
    "wof:name":"AB12 3EY",
    "wof:placetype":"postalcode"
},
  "geometry": {"coordinates":[-2.09530518506631,57.09535845597428],"type":"Point"}
}