{
  "type": "Feature",
  "properties": {
    "date:inception_lower": "1996-06-01",
    "date:inception_upper": "1996-06-01",
    "iso:country": "GB",
    "wof:name": "AB12 3EY",
    "wof:placetype": "postalcode"
  },
  "geometry": {"coordinates":[-2.095305,57.095358],"type":"Point"}
}
