{
  "type": "Feature",
  "properties": {
    "iso:country":"GB",
    "wof:name":"CF64 4TZ",
    "wof:placetype":"postalcode"
},
  "geometry": {"coordinates":[-3.21608933798612,51.43152418780605],"type":"Point"}
}