{
  "type": "Feature",
  "properties": {
    "iso:country": "GB",
    "wof:name": "CF64 4TZ",
    "wof:placetype": "postalcode"
  },
  "geometry": {"coordinates":[-3.216089,51.431524],"type":"Point"}
}
