{
  "type": "Feature",
  "properties": {
    "iso:country": "GB",
    "wof:name": "SO24 0JJ",
    "wof:placetype": "postalcode"
  },
  "geometry": {"coordinates":[-1.093542,51.052303],"type":"Point"}
}
