{
  "type": "Feature",
  "properties": {
    "iso:country":"GB",
    "wof:name":"YO42 2HF",
    "wof:placetype":"postalcode"
},
  "geometry": {"coordinates":[-0.77789413835308,53.93519025687535],"type":"Point"}
}