{
  "type": "Feature",
  "properties": {
    "iso:country": "GB",
    "wof:name": "MK2 2XP",
    "wof:placetype": "postalcode"
  },
  "geometry": {"coordinates":[-0.716702,51.999383],"type":"Point"}
}
