{
  "type": "Feature",
  "properties": {
    "iso:country":"GB",
    "wof:name":"MK2 2XP",
    "wof:placetype":"postalcode"
},
  "geometry": {"coordinates":[-0.71670155768174,51.99938253659643],"type":"Point"}
}