{
  "type": "Feature",
  "properties": {
    "date:inception_lower":"1983-07-01",
    "date:inception_upper":"1983-07-31",
    "iso:country":"GB",
    "wof:name":"TW18 4NF",
    "wof:placetype":"postalcode"
},
  "geometry": {"coordinates":[-0.501746,51.433164],"type":"Point"}
}