{
  "type": "Feature",
  "properties": {
    "iso:country":"GB",
    "wof:name":"TW18 4NF",
    "wof:placetype":"postalcode"
},
  "geometry": {"coordinates":[-0.50174584445542,51.4331639645577],"type":"Point"}
}