{
  "type": "Feature",
  "properties": {
    "iso:country":"GB",
    "wof:name":"SW15 5RW",
    "wof:placetype":"postalcode"
},
  "geometry": {"coordinates":[-0.2505152299402,51.46330656987762],"type":"Point"}
}