{
  "type": "Feature",
  "properties": {
    "date:inception_lower":"1984-02-01",
    "date:inception_upper":"1984-02-29",
    "iso:country":"GB",
    "wof:name":"LU7 0NB",
    "wof:placetype":"postalcode"
},
  "geometry": {"coordinates":[-0.781296,51.892326],"type":"Point"}
}