{
  "type": "Feature",
  "properties": {
    "iso:country": "GB",
    "wof:name": "LU7 0NB",
    "wof:placetype": "postalcode"
  },
  "geometry": {"coordinates":[-0.781296,51.892326],"type":"Point"}
}
