{
  "type": "Feature",
  "properties": {
    "iso:country":"GB",
    "wof:name":"LU7 0NB",
    "wof:placetype":"postalcode"
},
  "geometry": {"coordinates":[-0.78129642757167,51.89232618325809],"type":"Point"}
}