{
  "type": "Feature",
  "properties": {
    "iso:country":"GB",
    "wof:name":"L4 6BA",
    "wof:placetype":"postalcode"
},
  "geometry": {"coordinates":[-2.96363649655729,53.44747567073779],"type":"Point"}
}