{
  "type": "Feature",
  "properties": {
    "iso:country": "GB",
    "wof:name": "L4 6BA",
    "wof:placetype": "postalcode"
  },
  "geometry": {"coordinates":[-2.963636,53.447476],"type":"Point"}
}
