{
  "type": "Feature",
  "properties": {
    "date:inception_lower":"2004-08-01",
    "date:inception_upper":"2004-08-31",
    "iso:country":"GB",
    "wof:name":"L4 6BA",
    "wof:placetype":"postalcode"
},
  "geometry": {"coordinates":[-2.963636,53.447476],"type":"Point"}
}