{
  "type": "Feature",
  "properties": {
    "iso:country":"GB",
    "wof:name":"SA10 6JA",
    "wof:placetype":"postalcode"
},
  "geometry": {"coordinates":[-3.86061576445794,51.64044715816721],"type":"Point"}
}