{
  "type": "Feature",
  "properties": {
    "date:inception_lower":"1995-07-01",
    "date:inception_upper":"1995-07-31",
    "iso:country":"GB",
    "wof:name":"NG18 3GY",
    "wof:placetype":"postalcode"
},
  "geometry": {"coordinates":[-1.161541,53.135013],"type":"Point"}
}