{
  "type": "Feature",
  "properties": {
    "iso:country": "GB",
    "wof:name": "BS31 2DN",
    "wof:placetype": "postalcode"
  },
  "geometry": {"coordinates":[-2.503958,51.415656],"type":"Point"}
}
