{
  "type": "Feature",
  "properties": {
    "iso:country":"GB",
    "wof:name":"BS23 1BJ",
    "wof:placetype":"postalcode"
},
  "geometry": {"coordinates":[-2.97966310700139,51.33976440755691],"type":"Point"}
}