{
  "type": "Feature",
  "properties": {
    "date:inception_lower":"1980-01-01",
    "date:inception_upper":"1980-01-31",
    "iso:country":"GB",
    "wof:name":"BS23 1BJ",
    "wof:placetype":"postalcode"
},
  "geometry": {"coordinates":[-2.979663,51.339764],"type":"Point"}
}