{
  "type": "Feature",
  "properties": {
    "iso:country":"GB",
    "wof:name":"LS7 1DH",
    "wof:placetype":"postalcode"
},
  "geometry": {"coordinates":[-1.53217346894962,53.80545106892266],"type":"Point"}
}