{
  "type": "Feature",
  "properties": {
    "date:inception_lower": "2000-12-01",
    "date:inception_upper": "2000-12-01",
    "iso:country": "GB",
    "wof:name": "SE1 1BH",
    "wof:placetype": "postalcode"
  },
  "geometry": {"coordinates":[-0.093932,51.500145],"type":"Point"}
}
