{
  "type": "Feature",
  "properties": {
    "iso:country": "GB",
    "wof:name": "KA22 8GZ",
    "wof:placetype": "postalcode"
  },
  "geometry": {"coordinates":[-4.812587,55.645215],"type":"Point"}
}
