{
  "type": "Feature",
  "properties": {
    "iso:country": "GB",
    "wof:name": "ML5 4HQ",
    "wof:placetype": "postalcode"
  },
  "geometry": {"coordinates":[-4.003663,55.853585],"type":"Point"}
}
