{
  "type": "Feature",
  "properties": {
    "iso:country":"GB",
    "wof:name":"ML5 4HQ",
    "wof:placetype":"postalcode"
},
  "geometry": {"coordinates":[-4.0036634305407,55.8535847539255],"type":"Point"}
}