{
  "type": "Feature",
  "properties": {
    "iso:country": "GB",
    "wof:name": "BN17 7JQ",
    "wof:placetype": "postalcode"
  },
  "geometry": {"coordinates":[-0.544686,50.819336],"type":"Point"}
}
