{
  "type": "Feature",
  "properties": {
    "iso:country": "GB",
    "wof:name": "WD23 3ER",
    "wof:placetype": "postalcode"
  },
  "geometry": {"coordinates":[-0.353112,51.651507],"type":"Point"}
}
