{
  "type": "Feature",
  "properties": {
    "iso:country":"GB",
    "wof:name":"WD23 3ER",
    "wof:placetype":"postalcode"
},
  "geometry": {"coordinates":[-0.35311228155278,51.65150685335932],"type":"Point"}
}