{
  "type": "Feature",
  "properties": {
    "date:inception_lower":"1980-01-01",
    "date:inception_upper":"1980-01-31",
    "iso:country":"GB",
    "wof:name":"EH37 5XT",
    "wof:placetype":"postalcode"
},
  "geometry": {"coordinates":[-2.964714,55.809371],"type":"Point"}
}