{
  "type": "Feature",
  "properties": {
    "iso:country": "GB",
    "wof:name": "EH37 5XT",
    "wof:placetype": "postalcode"
  },
  "geometry": {"coordinates":[-2.964714,55.809371],"type":"Point"}
}
