{
  "type": "Feature",
  "properties": {
    "iso:country":"GB",
    "wof:name":"EH37 5XT",
    "wof:placetype":"postalcode"
},
  "geometry": {"coordinates":[-2.96437878194815,55.80953942204201],"type":"Point"}
}