{
  "type": "Feature",
  "properties": {
    "iso:country":"GB",
    "wof:name":"PE8 6XU",
    "wof:placetype":"postalcode"
},
  "geometry": {"coordinates":[-0.50912758638018,52.56706810715703],"type":"Point"}
}