{
  "type": "Feature",
  "properties": {
    "iso:country": "GB",
    "wof:name": "SL4 5RD",
    "wof:placetype": "postalcode"
  },
  "geometry": {"coordinates":[-0.649939,51.479934],"type":"Point"}
}
