{
  "type": "Feature",
  "properties": {
    "iso:country": "GB",
    "wof:name": "RG9 3DE",
    "wof:placetype": "postalcode"
  },
  "geometry": {"coordinates":[-0.871028,51.551201],"type":"Point"}
}
