{
  "type": "Feature",
  "properties": {
    "iso:country":"GB",
    "wof:name":"RG9 3DE",
    "wof:placetype":"postalcode"
},
  "geometry": {"coordinates":[-0.87102807291362,51.55120146352166],"type":"Point"}
}