{
  "type": "Feature",
  "properties": {
    "iso:country": "GB",
    "wof:name": "BS39 4NR",
    "wof:placetype": "postalcode"
  },
  "geometry": {"coordinates":[-2.525382,51.355179],"type":"Point"}
}
