{
  "type": "Feature",
  "properties": {
    "iso:country":"GB",
    "wof:name":"BS39 4NR",
    "wof:placetype":"postalcode"
},
  "geometry": {"coordinates":[-2.52533897128037,51.35525442973114],"type":"Point"}
}