{
  "type": "Feature",
  "properties": {
    "iso:country":"GB",
    "wof:name":"PL30 3JA",
    "wof:placetype":"postalcode"
},
  "geometry": {"coordinates":[-4.73571269057107,50.59313660127958],"type":"Point"}
}