{
  "type": "Feature",
  "properties": {
    "date:inception_lower": "1980-01-01",
    "date:inception_upper": "1980-01-01",
    "iso:country": "GB",
    "wof:name": "PL30 3JA",
    "wof:placetype": "postalcode"
  },
  "geometry": {"coordinates":[-4.735894,50.593161],"type":"Point"}
}
