{
  "type": "Feature",
  "properties": {
    "iso:country":"GB",
    "wof:name":"CO16 9DG",
    "wof:placetype":"postalcode"
},
  "geometry": {"coordinates":[1.12074484610875,51.84772304131062],"type":"Point"}
}