{
  "type": "Feature",
  "properties": {
    "date:inception_lower":"2008-10-01",
    "date:inception_upper":"2008-10-31",
    "iso:country":"GB",
    "wof:name":"CO16 9DG",
    "wof:placetype":"postalcode"
},
  "geometry": {"coordinates":[1.120745,51.847723],"type":"Point"}
}