{
  "type": "Feature",
  "properties": {
    "iso:country":"GB",
    "wof:name":"LS2 7HJ",
    "wof:placetype":"postalcode"
},
  "geometry": {"coordinates":[-1.53965957199372,53.79712114321737],"type":"Point"}
}