{
  "type": "Feature",
  "properties": {
    "iso:country":"GB",
    "wof:name":"BB5 3NS",
    "wof:placetype":"postalcode"
},
  "geometry": {"coordinates":[-2.40439147342383,53.74119946869234],"type":"Point"}
}