{
  "type": "Feature",
  "properties": {
    "iso:country":"GB",
    "wof:name":"CA28 7XY",
    "wof:placetype":"postalcode"
},
  "geometry": {"coordinates":[-3.59014713473964,54.55217886692364],"type":"Point"}
}