{
  "type": "Feature",
  "properties": {
    "iso:country": "GB",
    "wof:name": "CA28 7XY",
    "wof:placetype": "postalcode"
  },
  "geometry": {"coordinates":[-3.590148,54.552186],"type":"Point"}
}
