{
  "type": "Feature",
  "properties": {
    "date:inception_lower":"1997-12-01",
    "date:inception_upper":"1997-12-31",
    "iso:country":"GB",
    "wof:name":"BS48 3LS",
    "wof:placetype":"postalcode"
},
  "geometry": {"coordinates":[-2.746173,51.419237],"type":"Point"}
}