{
  "type": "Feature",
  "properties": {
    "iso:country": "GB",
    "wof:name": "BS48 3LS",
    "wof:placetype": "postalcode"
  },
  "geometry": {"coordinates":[-2.746173,51.419237],"type":"Point"}
}
