{
  "type": "Feature",
  "properties": {
    "iso:country": "GB",
    "wof:name": "S10 4QR",
    "wof:placetype": "postalcode"
  },
  "geometry": {"coordinates":[-1.58471,53.360002],"type":"Point"}
}
