{
  "type": "Feature",
  "properties": {
    "iso:country":"GB",
    "wof:name":"S10 4QR",
    "wof:placetype":"postalcode"
},
  "geometry": {"coordinates":[-1.58471040087243,53.36000199314326],"type":"Point"}
}