{
  "type": "Feature",
  "properties": {
    "date:inception_lower":"1980-01-01",
    "date:inception_upper":"1980-01-31",
    "iso:country":"GB",
    "wof:name":"LL30 3EN",
    "wof:placetype":"postalcode"
},
  "geometry": {"coordinates":[-3.773804,53.316522],"type":"Point"}
}