{
  "type": "Feature",
  "properties": {
    "iso:country":"GB",
    "wof:name":"DN8 4EN",
    "wof:placetype":"postalcode"
},
  "geometry": {"coordinates":[-0.95731929680661,53.62281680602779],"type":"Point"}
}