{
  "type": "Feature",
  "properties": {
    "iso:country":"GB",
    "wof:name":"S75 5ND",
    "wof:placetype":"postalcode"
},
  "geometry": {"coordinates":[-1.53467171400486,53.58488140267014],"type":"Point"}
}