{
  "type": "Feature",
  "properties": {
    "date:inception_lower":"1980-01-01",
    "date:inception_upper":"1980-01-31",
    "iso:country":"GB",
    "wof:name":"S75 5ND",
    "wof:placetype":"postalcode"
},
  "geometry": {"coordinates":[-1.534672,53.584881],"type":"Point"}
}