{
  "type": "Feature",
  "properties": {
    "date:inception_lower":"2014-11-01",
    "date:inception_upper":"2014-11-30",
    "iso:country":"GB",
    "wof:name":"GU26 6UY",
    "wof:placetype":"postalcode"
},
  "geometry": {"coordinates":[-0.732319,51.114351],"type":"Point"}
}