{
  "type": "Feature",
  "properties": {
    "iso:country":"GB",
    "wof:name":"GU26 6UY",
    "wof:placetype":"postalcode"
},
  "geometry": {"coordinates":[-0.73219855744275,51.11425543624419],"type":"Point"}
}