{
  "type": "Feature",
  "properties": {
    "iso:country":"GB",
    "wof:name":"NG17 5JP",
    "wof:placetype":"postalcode"
},
  "geometry": {"coordinates":[-1.23550715896626,53.12119137436487],"type":"Point"}
}