{
  "type": "Feature",
  "properties": {
    "iso:country": "GB",
    "wof:name": "SN14 0HW",
    "wof:placetype": "postalcode"
  },
  "geometry": {"coordinates":[-2.133312,51.461685],"type":"Point"}
}
