{
  "type": "Feature",
  "properties": {
    "date:inception_lower":"1980-01-01",
    "date:inception_upper":"1980-01-31",
    "iso:country":"GB",
    "wof:name":"SN14 0HW",
    "wof:placetype":"postalcode"
},
  "geometry": {"coordinates":[-2.133312,51.461685],"type":"Point"}
}