{
  "type": "Feature",
  "properties": {
    "iso:country":"GB",
    "wof:name":"SN14 0HW",
    "wof:placetype":"postalcode"
},
  "geometry": {"coordinates":[-2.13331251657161,51.46168496345203],"type":"Point"}
}