{
  "type": "Feature",
  "properties": {
    "date:inception_lower": "2019-02-01",
    "date:inception_upper": "2019-02-01",
    "iso:country": "GB",
    "wof:name": "B29 9ET",
    "wof:placetype": "postalcode"
  },
  "geometry": {"coordinates":[-1.935799,52.438282],"type":"Point"}
}
