{
  "type": "Feature",
  "properties": {
    "iso:country":"GB",
    "wof:name":"SL5 8AZ",
    "wof:placetype":"postalcode"
},
  "geometry": {"coordinates":[-0.70596568338787,51.40277482218472],"type":"Point"}
}