{
  "type": "Feature",
  "properties": {
    "iso:country":"GB",
    "wof:name":"PL1 1PU",
    "wof:placetype":"postalcode"
},
  "geometry": {"coordinates":[-4.1478295999192,50.37209390106098],"type":"Point"}
}