{
  "type": "Feature",
  "properties": {
    "date:inception_lower": "1994-05-01",
    "date:inception_upper": "1994-05-01",
    "iso:country": "GB",
    "wof:name": "CF62 4HJ",
    "wof:placetype": "postalcode"
  },
  "geometry": {"coordinates":[-3.419072,51.414],"type":"Point"}
}
