{
  "type": "Feature",
  "properties": {
    "iso:country": "GB",
    "wof:name": "CF62 4HJ",
    "wof:placetype": "postalcode"
  },
  "geometry": {"coordinates":[-3.419072,51.414],"type":"Point"}
}
