{
  "type": "Feature",
  "properties": {
    "iso:country":"GB",
    "wof:name":"CF62 4HJ",
    "wof:placetype":"postalcode"
},
  "geometry": {"coordinates":[-3.41907172040457,51.41400025312217],"type":"Point"}
}