{
  "type": "Feature",
  "properties": {
    "date:inception_lower": "1980-01-01",
    "date:inception_upper": "1980-01-01",
    "iso:country": "GB",
    "wof:name": "KY1 4TA",
    "wof:placetype": "postalcode"
  },
  "geometry": {"coordinates":[-3.084903,56.140093],"type":"Point"}
}
