{
  "type": "Feature",
  "properties": {
    "iso:country":"GB",
    "wof:name":"WF12 7RP",
    "wof:placetype":"postalcode"
},
  "geometry": {"coordinates":[-1.60056101437685,53.70188575672368],"type":"Point"}
}