{
  "type": "Feature",
  "properties": {
    "iso:country":"GB",
    "wof:name":"FY6 9DZ",
    "wof:placetype":"postalcode"
},
  "geometry": {"coordinates":[-2.96371215302037,53.87656091458896],"type":"Point"}
}