{
  "type": "Feature",
  "properties": {
    "iso:country": "GB",
    "wof:name": "PE27 5GF",
    "wof:placetype": "postalcode"
  },
  "geometry": {"coordinates":[-0.069228,52.321317],"type":"Point"}
}
