{
  "type": "Feature",
  "properties": {
    "iso:country":"GB",
    "wof:name":"CT15 4JF",
    "wof:placetype":"postalcode"
},
  "geometry": {"coordinates":[1.22777381860637,51.21229332613169],"type":"Point"}
}