{
  "type": "Feature",
  "properties": {
    "iso:country": "GB",
    "wof:name": "CV6 4DW",
    "wof:placetype": "postalcode"
  },
  "geometry": {"coordinates":[-1.512063,52.440803],"type":"Point"}
}
