{
  "type": "Feature",
  "properties": {
    "iso:country":"GB",
    "wof:name":"CV6 4DW",
    "wof:placetype":"postalcode"
},
  "geometry": {"coordinates":[-1.51206324611331,52.44080333310859],"type":"Point"}
}