{
  "type": "Feature",
  "properties": {
    "iso:country":"GB",
    "wof:name":"NP10 8LH",
    "wof:placetype":"postalcode"
},
  "geometry": {"coordinates":[-3.05161794579799,51.5771010883841],"type":"Point"}
}