{
  "type": "Feature",
  "properties": {
    "iso:country":"GB",
    "wof:name":"L17 8XP",
    "wof:placetype":"postalcode"
},
  "geometry": {"coordinates":[-2.94472277581287,53.38087529461565],"type":"Point"}
}