{
  "type": "Feature",
  "properties": {
    "date:inception_lower":"1980-01-01",
    "date:inception_upper":"1980-01-31",
    "iso:country":"GB",
    "wof:name":"PR2 6SU",
    "wof:placetype":"postalcode"
},
  "geometry": {"coordinates":[-2.663808,53.781793],"type":"Point"}
}