{
  "type": "Feature",
  "properties": {
    "iso:country":"GB",
    "wof:name":"B75 7PZ",
    "wof:placetype":"postalcode"
},
  "geometry": {"coordinates":[-1.78477917661895,52.56432607625656],"type":"Point"}
}