{
  "type": "Feature",
  "properties": {
    "date:inception_lower": "1980-01-01",
    "date:inception_upper": "1980-01-01",
    "iso:country": "GB",
    "wof:name": "BD24 9PY",
    "wof:placetype": "postalcode"
  },
  "geometry": {"coordinates":[-2.157148,54.131902],"type":"Point"}
}
