{
  "type": "Feature",
  "properties": {
    "iso:country":"GB",
    "wof:name":"BD24 9PY",
    "wof:placetype":"postalcode"
},
  "geometry": {"coordinates":[-2.15714821839379,54.13190172747801],"type":"Point"}
}