{
  "type": "Feature",
  "properties": {
    "iso:country":"GB",
    "wof:name":"B29 5JE",
    "wof:placetype":"postalcode"
},
  "geometry": {"coordinates":[-1.96385353015958,52.44280119417948],"type":"Point"}
}