{
  "type": "Feature",
  "properties": {
    "iso:country":"GB",
    "wof:name":"PH26 3PQ",
    "wof:placetype":"postalcode"
},
  "geometry": {"coordinates":[-3.53670492579419,57.33747728600071],"type":"Point"}
}