{
  "type": "Feature",
  "properties": {
    "iso:country":"GB",
    "wof:name":"L20 3LL",
    "wof:placetype":"postalcode"
},
  "geometry": {"coordinates":[-2.98929854172792,53.45091534051845],"type":"Point"}
}