{
  "type": "Feature",
  "properties": {
    "iso:country":"GB",
    "wof:name":"LL11 4RP",
    "wof:placetype":"postalcode"
},
  "geometry": {"coordinates":[-3.00192772781648,53.06724257841309],"type":"Point"}
}