{
  "type": "Feature",
  "properties": {
    "iso:country": "GB",
    "wof:name": "CH5 2NW",
    "wof:placetype": "postalcode"
  },
  "geometry": {"coordinates":[-3.010432,53.233977],"type":"Point"}
}
