{
  "type": "Feature",
  "properties": {
    "iso:country":"GB",
    "wof:name":"N10 2EA",
    "wof:placetype":"postalcode"
},
  "geometry": {"coordinates":[-0.14208053355337,51.59263191260735],"type":"Point"}
}