{
  "type": "Feature",
  "properties": {
    "iso:country": "GB",
    "wof:name": "SY18 6BZ",
    "wof:placetype": "postalcode"
  },
  "geometry": {"coordinates":[-3.538471,52.447649],"type":"Point"}
}
