{
  "type": "Feature",
  "properties": {
    "date:inception_lower": "2006-09-01",
    "date:inception_upper": "2006-09-01",
    "iso:country": "GB",
    "wof:name": "CB23 1HA",
    "wof:placetype": "postalcode"
  },
  "geometry": {"coordinates":[0.012422,52.154093],"type":"Point"}
}
