{
  "type": "Feature",
  "properties": {
    "iso:country":"GB",
    "wof:name":"CB23 1HA",
    "wof:placetype":"postalcode"
},
  "geometry": {"coordinates":[0.01242222751358,52.15409329905386],"type":"Point"}
}