{
  "type": "Feature",
  "properties": {
    "iso:country":"GB",
    "wof:name":"TF13 6LS",
    "wof:placetype":"postalcode"
},
  "geometry": {"coordinates":[-2.64845217619537,52.51395531529193],"type":"Point"}
}