{
  "type": "Feature",
  "properties": {
    "date:inception_lower":"1980-01-01",
    "date:inception_upper":"1980-01-31",
    "iso:country":"GB",
    "wof:name":"TF13 6LS",
    "wof:placetype":"postalcode"
},
  "geometry": {"coordinates":[-2.648452,52.513955],"type":"Point"}
}