{
  "type": "Feature",
  "properties": {
    "iso:country":"GB",
    "wof:name":"NE5 4PQ",
    "wof:placetype":"postalcode"
},
  "geometry": {"coordinates":[-1.69276456319456,55.00003001943695],"type":"Point"}
}