{
  "type": "Feature",
  "properties": {
    "iso:country": "GB",
    "wof:name": "B92 0EX",
    "wof:placetype": "postalcode"
  },
  "geometry": {"coordinates":[-1.703332,52.424042],"type":"Point"}
}
