{
  "type": "Feature",
  "properties": {
    "iso:country":"GB",
    "wof:name":"NW1 6UE",
    "wof:placetype":"postalcode"
},
  "geometry": {"coordinates":[-0.1661295505454,51.5224196834621],"type":"Point"}
}