{
  "type": "Feature",
  "properties": {
    "date:inception_lower": "1980-01-01",
    "date:inception_upper": "1980-01-01",
    "iso:country": "GB",
    "wof:name": "NW1 6UE",
    "wof:placetype": "postalcode"
  },
  "geometry": {"coordinates":[-0.166016,51.522483],"type":"Point"}
}
