{
  "type": "Feature",
  "properties": {
    "date:inception_lower":"1996-12-01",
    "date:inception_upper":"1996-12-31",
    "iso:country":"GB",
    "wof:name":"LN8 5QA",
    "wof:placetype":"postalcode"
},
  "geometry": {"coordinates":[-0.262878,53.281128],"type":"Point"}
}