{
  "type": "Feature",
  "properties": {
    "iso:country":"GB",
    "wof:name":"LN8 5QA",
    "wof:placetype":"postalcode"
},
  "geometry": {"coordinates":[-0.26287795568109,53.28112785251172],"type":"Point"}
}