{
  "type": "Feature",
  "properties": {
    "iso:country": "GB",
    "wof:name": "LN8 5QA",
    "wof:placetype": "postalcode"
  },
  "geometry": {"coordinates":[-0.262878,53.281128],"type":"Point"}
}
