{
  "type": "Feature",
  "properties": {
    "iso:country":"GB",
    "wof:name":"B48 7RU",
    "wof:placetype":"postalcode"
},
  "geometry": {"coordinates":[-1.95301613257923,52.340535093132],"type":"Point"}
}