{
  "type": "Feature",
  "properties": {
    "iso:country": "GB",
    "wof:name": "B48 7RU",
    "wof:placetype": "postalcode"
  },
  "geometry": {"coordinates":[-1.952216,52.34037],"type":"Point"}
}
