{
  "type": "Feature",
  "properties": {
    "iso:country":"GB",
    "wof:name":"LN11 7QX",
    "wof:placetype":"postalcode"
},
  "geometry": {"coordinates":[0.15100442155395,53.44232984011542],"type":"Point"}
}