{
  "type": "Feature",
  "properties": {
    "date:inception_lower": "1980-01-01",
    "date:inception_upper": "1980-01-01",
    "iso:country": "GB",
    "wof:name": "LN11 7QX",
    "wof:placetype": "postalcode"
  },
  "geometry": {"coordinates":[0.151004,53.44233],"type":"Point"}
}
