{
  "type": "Feature",
  "properties": {
    "iso:country": "GB",
    "wof:name": "DL11 7TG",
    "wof:placetype": "postalcode"
  },
  "geometry": {"coordinates":[-1.685138,54.496753],"type":"Point"}
}
