{
  "type": "Feature",
  "properties": {
    "date:inception_lower": "1996-06-01",
    "date:inception_upper": "1996-06-01",
    "iso:country": "GB",
    "wof:name": "AB42 4JQ",
    "wof:placetype": "postalcode"
  },
  "geometry": {"coordinates":[-2.034039,57.534315],"type":"Point"}
}
