{
  "type": "Feature",
  "properties": {
    "iso:country": "GB",
    "wof:name": "DT2 0DU",
    "wof:placetype": "postalcode"
  },
  "geometry": {"coordinates":[-2.630859,50.77146],"type":"Point"}
}
