{
  "type": "Feature",
  "properties": {
    "date:inception_lower":"1981-06-01",
    "date:inception_upper":"1981-06-30",
    "iso:country":"GB",
    "wof:name":"DT2 0DU",
    "wof:placetype":"postalcode"
},
  "geometry": {"coordinates":[-2.630859,50.77146],"type":"Point"}
}