{
  "type": "Feature",
  "properties": {
    "iso:country":"GB",
    "wof:name":"DT2 0DU",
    "wof:placetype":"postalcode"
},
  "geometry": {"coordinates":[-2.63085875258299,50.77145999553412],"type":"Point"}
}