{
  "type": "Feature",
  "properties": {
    "iso:country":"GB",
    "wof:name":"TW13 4DA",
    "wof:placetype":"postalcode"
},
  "geometry": {"coordinates":[-0.41376098530511,51.44516220658675],"type":"Point"}
}