{
  "type": "Feature",
  "properties": {
    "iso:country": "GB",
    "wof:name": "TW13 4DA",
    "wof:placetype": "postalcode"
  },
  "geometry": {"coordinates":[-0.413761,51.445162],"type":"Point"}
}
