{
  "type": "Feature",
  "properties": {
    "iso:country":"GB",
    "wof:name":"GU32 2HY",
    "wof:placetype":"postalcode"
},
  "geometry": {"coordinates":[-0.9322665393402,51.01499797527088],"type":"Point"}
}