{
  "type": "Feature",
  "properties": {
    "iso:country":"GB",
    "wof:name":"HG2 0ED",
    "wof:placetype":"postalcode"
},
  "geometry": {"coordinates":[-1.54736245601201,53.98116876781928],"type":"Point"}
}