{
  "type": "Feature",
  "properties": {
    "iso:country":"GB",
    "wof:name":"LL29 7RL",
    "wof:placetype":"postalcode"
},
  "geometry": {"coordinates":[-3.72579080789403,53.29038253087151],"type":"Point"}
}