{
  "type": "Feature",
  "properties": {
    "date:inception_lower": "1980-01-01",
    "date:inception_upper": "1980-01-01",
    "iso:country": "GB",
    "wof:name": "DD2 5QD",
    "wof:placetype": "postalcode"
  },
  "geometry": {"coordinates":[-3.05903,56.498218],"type":"Point"}
}
