{
  "type": "Feature",
  "properties": {
    "iso:country":"GB",
    "wof:name":"DD2 5QD",
    "wof:placetype":"postalcode"
},
  "geometry": {"coordinates":[-3.05906691797345,56.49836170659284],"type":"Point"}
}