{
  "type": "Feature",
  "properties": {
    "date:inception_lower": "1981-06-01",
    "date:inception_upper": "1981-06-01",
    "iso:country": "GB",
    "wof:name": "SL6 8AG",
    "wof:placetype": "postalcode"
  },
  "geometry": {"coordinates":[-0.718954,51.523755],"type":"Point"}
}
