{
  "type": "Feature",
  "properties": {
    "iso:country": "GB",
    "wof:name": "CF63 2AG",
    "wof:placetype": "postalcode"
  },
  "geometry": {"coordinates":[-3.246117,51.417972],"type":"Point"}
}
