{
  "type": "Feature",
  "properties": {
    "date:inception_lower":"1993-01-01",
    "date:inception_upper":"1993-01-31",
    "iso:country":"GB",
    "wof:name":"CF63 2AG",
    "wof:placetype":"postalcode"
},
  "geometry": {"coordinates":[-3.246117,51.417972],"type":"Point"}
}