{
  "type": "Feature",
  "properties": {
    "date:inception_lower":"2011-12-01",
    "date:inception_upper":"2011-12-31",
    "iso:country":"GB",
    "wof:name":"RG12 1WB",
    "wof:placetype":"postalcode"
},
  "geometry": {"coordinates":[-0.771363,51.414531],"type":"Point"}
}