{
  "type": "Feature",
  "properties": {
    "date:inception_lower": "1983-03-01",
    "date:inception_upper": "1983-03-01",
    "iso:country": "GB",
    "wof:name": "LE10 3BX",
    "wof:placetype": "postalcode"
  },
  "geometry": {"coordinates":[-1.406247,52.540262],"type":"Point"}
}
