{
  "type": "Feature",
  "properties": {
    "iso:country":"GB",
    "wof:name":"LE10 3BX",
    "wof:placetype":"postalcode"
},
  "geometry": {"coordinates":[-1.40624698256288,52.54026223833369],"type":"Point"}
}