{
  "type": "Feature",
  "properties": {
    "date:inception_lower": "1990-12-01",
    "date:inception_upper": "1990-12-01",
    "iso:country": "GB",
    "wof:name": "G77 5TX",
    "wof:placetype": "postalcode"
  },
  "geometry": {"coordinates":[-4.306078,55.771245],"type":"Point"}
}
