{
  "type": "Feature",
  "properties": {
    "date:inception_lower": "1980-01-01",
    "date:inception_upper": "1980-01-01",
    "iso:country": "GB",
    "wof:name": "NP8 1BD",
    "wof:placetype": "postalcode"
  },
  "geometry": {"coordinates":[-3.137442,51.858955],"type":"Point"}
}
