{
  "type": "Feature",
  "properties": {
    "iso:country":"GB",
    "wof:name":"NP8 1BD",
    "wof:placetype":"postalcode"
},
  "geometry": {"coordinates":[-3.13743466753975,51.85894956195609],"type":"Point"}
}