{
  "type": "Feature",
  "properties": {
    "iso:country": "GB",
    "wof:name": "ME15 6TJ",
    "wof:placetype": "postalcode"
  },
  "geometry": {"coordinates":[0.52557,51.264758],"type":"Point"}
}
