{
  "type": "Feature",
  "properties": {
    "iso:country":"GB",
    "wof:name":"ME15 6TJ",
    "wof:placetype":"postalcode"
},
  "geometry": {"coordinates":[0.52552924238528,51.26483113035661],"type":"Point"}
}