{
  "type": "Feature",
  "properties": {
    "iso:country":"GB",
    "wof:name":"B29 4PR",
    "wof:placetype":"postalcode"
},
  "geometry": {"coordinates":[-1.95714316976342,52.42943978999615],"type":"Point"}
}