{
  "type": "Feature",
  "properties": {
    "iso:country":"GB",
    "wof:name":"LE5 5DE",
    "wof:placetype":"postalcode"
},
  "geometry": {"coordinates":[-1.09977130904128,52.63295860372109],"type":"Point"}
}