{
  "type": "Feature",
  "properties": {
    "iso:country":"GB",
    "wof:name":"LE7 9EB",
    "wof:placetype":"postalcode"
},
  "geometry": {"coordinates":[-0.92972890295292,52.57603056351031],"type":"Point"}
}