{
  "type": "Feature",
  "properties": {
    "iso:country": "GB",
    "wof:name": "LE7 9EB",
    "wof:placetype": "postalcode"
  },
  "geometry": {"coordinates":[-0.929719,52.576049],"type":"Point"}
}
