{
  "type": "Feature",
  "properties": {
    "iso:country":"GB",
    "wof:name":"OX17 1JA",
    "wof:placetype":"postalcode"
},
  "geometry": {"coordinates":[-1.37800821422106,52.10712499393609],"type":"Point"}
}