{
  "type": "Feature",
  "properties": {
    "iso:country": "GB",
    "wof:name": "ST13 8QT",
    "wof:placetype": "postalcode"
  },
  "geometry": {"coordinates":[-2.128184,53.118002],"type":"Point"}
}
