{
  "type": "Feature",
  "properties": {
    "date:inception_lower": "1981-06-01",
    "date:inception_upper": "1981-06-01",
    "iso:country": "GB",
    "wof:name": "MK43 7LN",
    "wof:placetype": "postalcode"
  },
  "geometry": {"coordinates":[-0.603148,52.192103],"type":"Point"}
}
