{
  "type": "Feature",
  "properties": {
    "iso:country":"GB",
    "wof:name":"MK43 7LN",
    "wof:placetype":"postalcode"
},
  "geometry": {"coordinates":[-0.60314820515447,52.19210288507362],"type":"Point"}
}