{
  "type": "Feature",
  "properties": {
    "iso:country": "GB",
    "wof:name": "SY3 7EF",
    "wof:placetype": "postalcode"
  },
  "geometry": {"coordinates":[-2.75044,52.703202],"type":"Point"}
}
