{
  "type": "Feature",
  "properties": {
    "date:inception_lower": "2017-01-01",
    "date:inception_upper": "2017-01-01",
    "iso:country": "GB",
    "wof:name": "NP7 9EQ",
    "wof:placetype": "postalcode"
  },
  "geometry": {"coordinates":[-3.025529,51.770897],"type":"Point"}
}
