{
  "type": "Feature",
  "properties": {
    "iso:country":"GB",
    "wof:name":"B76 2PJ",
    "wof:placetype":"postalcode"
},
  "geometry": {"coordinates":[-1.80021168976622,52.55097618438177],"type":"Point"}
}