{
  "type": "Feature",
  "properties": {
    "date:inception_lower": "1980-01-01",
    "date:inception_upper": "1980-01-01",
    "iso:country": "GB",
    "wof:name": "LL41 4AN",
    "wof:placetype": "postalcode"
  },
  "geometry": {"coordinates":[-3.930861,52.98285],"type":"Point"}
}
