{
  "type": "Feature",
  "properties": {
    "iso:country":"GB",
    "wof:name":"SN10 4HX",
    "wof:placetype":"postalcode"
},
  "geometry": {"coordinates":[-1.99759898769496,51.28245830758351],"type":"Point"}
}