{
  "type": "Feature",
  "properties": {
    "iso:country": "GB",
    "wof:name": "CH64 6RR",
    "wof:placetype": "postalcode"
  },
  "geometry": {"coordinates":[-3.082957,53.299051],"type":"Point"}
}
