{
  "type": "Feature",
  "properties": {
    "iso:country":"GB",
    "wof:name":"SA17 4LY",
    "wof:placetype":"postalcode"
},
  "geometry": {"coordinates":[-4.28956544661948,51.76978767385165],"type":"Point"}
}