{
  "type": "Feature",
  "properties": {
    "iso:country": "GB",
    "wof:name": "SA17 4LY",
    "wof:placetype": "postalcode"
  },
  "geometry": {"coordinates":[-4.289589,51.769795],"type":"Point"}
}
