{
  "type": "Feature",
  "properties": {
    "iso:country": "GB",
    "wof:name": "NG7 2HJ",
    "wof:placetype": "postalcode"
  },
  "geometry": {"coordinates":[-1.18109,52.954841],"type":"Point"}
}
