{
  "type": "Feature",
  "properties": {
    "date:inception_lower":"1980-01-01",
    "date:inception_upper":"1980-01-31",
    "iso:country":"GB",
    "wof:name":"SG17 5DR",
    "wof:placetype":"postalcode"
},
  "geometry": {"coordinates":[-0.337275,52.041781],"type":"Point"}
}