{
  "type": "Feature",
  "properties": {
    "iso:country":"GB",
    "wof:name":"SG17 5DR",
    "wof:placetype":"postalcode"
},
  "geometry": {"coordinates":[-0.3372750970616,52.04178055667222],"type":"Point"}
}