{
  "type": "Feature",
  "properties": {
    "date:inception_lower": "1980-01-01",
    "date:inception_upper": "1980-01-01",
    "iso:country": "GB",
    "wof:name": "EX18 7SL",
    "wof:placetype": "postalcode"
  },
  "geometry": {"coordinates":[-3.88515,50.842942],"type":"Point"}
}
