{
  "type": "Feature",
  "properties": {
    "iso:country":"GB",
    "wof:name":"EX18 7SL",
    "wof:placetype":"postalcode"
},
  "geometry": {"coordinates":[-3.88515019461094,50.84294194611441],"type":"Point"}
}