{
  "type": "Feature",
  "properties": {
    "iso:country":"GB",
    "wof:name":"RG20 0PB",
    "wof:placetype":"postalcode"
},
  "geometry": {"coordinates":[-1.39614538696009,51.36233281115487],"type":"Point"}
}