{
  "type": "Feature",
  "properties": {
    "iso:country":"GB",
    "wof:name":"DT1 1RU",
    "wof:placetype":"postalcode"
},
  "geometry": {"coordinates":[-2.44250429414206,50.7130742446566],"type":"Point"}
}