{
  "type": "Feature",
  "properties": {
    "date:inception_lower":"1980-01-01",
    "date:inception_upper":"1980-01-31",
    "iso:country":"GB",
    "wof:name":"DT1 1RU",
    "wof:placetype":"postalcode"
},
  "geometry": {"coordinates":[-2.442504,50.713074],"type":"Point"}
}