{
  "type": "Feature",
  "properties": {
    "iso:country":"GB",
    "wof:name":"CA11 7PA",
    "wof:placetype":"postalcode"
},
  "geometry": {"coordinates":[-2.76012578370099,54.66870679526145],"type":"Point"}
}