{
  "type": "Feature",
  "properties": {
    "iso:country": "GB",
    "wof:name": "CA11 7PA",
    "wof:placetype": "postalcode"
  },
  "geometry": {"coordinates":[-2.760126,54.668707],"type":"Point"}
}
