{
  "type": "Feature",
  "properties": {
    "iso:country":"GB",
    "wof:name":"B20 3HE",
    "wof:placetype":"postalcode"
},
  "geometry": {"coordinates":[-1.89203446487485,52.51375135093406],"type":"Point"}
}