{
  "type": "Feature",
  "properties": {
    "iso:country": "GB",
    "wof:name": "BH15 3AU",
    "wof:placetype": "postalcode"
  },
  "geometry": {"coordinates":[-1.979686,50.732474],"type":"Point"}
}
