{
  "type": "Feature",
  "properties": {
    "iso:country":"GB",
    "wof:name":"BH15 3AU",
    "wof:placetype":"postalcode"
},
  "geometry": {"coordinates":[-1.979685575482,50.73247410512955],"type":"Point"}
}