{
  "type": "Feature",
  "properties": {
    "iso:country":"GB",
    "wof:name":"BL4 7QL",
    "wof:placetype":"postalcode"
},
  "geometry": {"coordinates":[-2.38982899245139,53.55023851781886],"type":"Point"}
}