{
  "type": "Feature",
  "properties": {
    "iso:country": "GB",
    "wof:name": "S63 8JQ",
    "wof:placetype": "postalcode"
  },
  "geometry": {"coordinates":[-1.306298,53.517045],"type":"Point"}
}
