{
  "type": "Feature",
  "properties": {
    "iso:country":"GB",
    "wof:name":"S63 8JQ",
    "wof:placetype":"postalcode"
},
  "geometry": {"coordinates":[-1.30629832679196,53.51704499002189],"type":"Point"}
}