{
  "type": "Feature",
  "properties": {
    "iso:country":"GB",
    "wof:name":"LA12 0JD",
    "wof:placetype":"postalcode"
},
  "geometry": {"coordinates":[-3.11683778113405,54.18625877999058],"type":"Point"}
}