{
  "type": "Feature",
  "properties": {
    "date:inception_lower": "1980-01-01",
    "date:inception_upper": "1980-01-01",
    "iso:country": "GB",
    "wof:name": "LA12 0JD",
    "wof:placetype": "postalcode"
  },
  "geometry": {"coordinates":[-3.116838,54.186295],"type":"Point"}
}
