{
  "type": "Feature",
  "properties": {
    "date:inception_lower": "1980-01-01",
    "date:inception_upper": "1980-01-01",
    "iso:country": "GB",
    "wof:name": "NE48 1RP",
    "wof:placetype": "postalcode"
  },
  "geometry": {"coordinates":[-2.302776,55.213516],"type":"Point"}
}
