{
  "type": "Feature",
  "properties": {
    "iso:country":"GB",
    "wof:name":"NE48 1RP",
    "wof:placetype":"postalcode"
},
  "geometry": {"coordinates":[-2.30287784587249,55.21355690554119],"type":"Point"}
}