{
  "type": "Feature",
  "properties": {
    "iso:country": "GB",
    "wof:name": "GL4 8AX",
    "wof:placetype": "postalcode"
  },
  "geometry": {"coordinates":[-2.19719,51.833572],"type":"Point"}
}
