{
  "type": "Feature",
  "properties": {
    "iso:country":"GB",
    "wof:name":"GL4 8AX",
    "wof:placetype":"postalcode"
},
  "geometry": {"coordinates":[-2.19719038365668,51.83357174021762],"type":"Point"}
}