{
  "type": "Feature",
  "properties": {
    "iso:country":"GB",
    "wof:name":"LS15 7RN",
    "wof:placetype":"postalcode"
},
  "geometry": {"coordinates":[-1.46780330747209,53.79724640071562],"type":"Point"}
}