{
  "type": "Feature",
  "properties": {
    "date:inception_lower": "1980-01-01",
    "date:inception_upper": "1980-01-01",
    "iso:country": "GB",
    "wof:name": "TA6 3QE",
    "wof:placetype": "postalcode"
  },
  "geometry": {"coordinates":[-3.011843,51.133476],"type":"Point"}
}
