{
  "type": "Feature",
  "properties": {
    "iso:country":"GB",
    "wof:name":"AL1 5SU",
    "wof:placetype":"postalcode"
},
  "geometry": {"coordinates":[-0.31443381037234,51.74368414706426],"type":"Point"}
}