{
  "type": "Feature",
  "properties": {
    "iso:country":"GB",
    "wof:name":"LS18 4SW",
    "wof:placetype":"postalcode"
},
  "geometry": {"coordinates":[-1.61975207441551,53.83467483196908],"type":"Point"}
}