{
  "type": "Feature",
  "properties": {
    "date:inception_lower": "1980-01-01",
    "date:inception_upper": "1980-01-01",
    "iso:country": "GB",
    "wof:name": "CT8 8HD",
    "wof:placetype": "postalcode"
  },
  "geometry": {"coordinates":[1.32925,51.37592],"type":"Point"}
}
