{
  "type": "Feature",
  "properties": {
    "iso:country": "GB",
    "wof:name": "AL7 4FE",
    "wof:placetype": "postalcode"
  },
  "geometry": {"coordinates":[-0.20123,51.786058],"type":"Point"}
}
