{
  "type": "Feature",
  "properties": {
    "iso:country":"GB",
    "wof:name":"AL7 4FE",
    "wof:placetype":"postalcode"
},
  "geometry": {"coordinates":[-0.20122962664274,51.786058194178],"type":"Point"}
}