{
  "type": "Feature",
  "properties": {
    "iso:country":"GB",
    "wof:name":"DN14 0AT",
    "wof:placetype":"postalcode"
},
  "geometry": {"coordinates":[-1.06413647659904,53.68100131872881],"type":"Point"}
}