{
  "type": "Feature",
  "properties": {
    "iso:country":"GB",
    "wof:name":"OX17 3DA",
    "wof:placetype":"postalcode"
},
  "geometry": {"coordinates":[-1.24568771065815,52.01988861698887],"type":"Point"}
}