{
  "type": "Feature",
  "properties": {
    "iso:country":"GB",
    "wof:name":"CH62 8EW",
    "wof:placetype":"postalcode"
},
  "geometry": {"coordinates":[-2.97493785685254,53.31165061910419],"type":"Point"}
}