{
  "type": "Feature",
  "properties": {
    "iso:country": "GB",
    "wof:name": "CM2 6HN",
    "wof:placetype": "postalcode"
  },
  "geometry": {"coordinates":[0.490108,51.731051],"type":"Point"}
}
