{
  "type": "Feature",
  "properties": {
    "iso:country": "GB",
    "wof:name": "TN29 0JH",
    "wof:placetype": "postalcode"
  },
  "geometry": {"coordinates":[0.981953,51.048645],"type":"Point"}
}
