{
  "type": "Feature",
  "properties": {
    "iso:country":"GB",
    "wof:name":"TN29 0JH",
    "wof:placetype":"postalcode"
},
  "geometry": {"coordinates":[0.98108053942261,51.04804427305691],"type":"Point"}
}