{
  "type": "Feature",
  "properties": {
    "iso:country": "GB",
    "wof:name": "PE13 4PR",
    "wof:placetype": "postalcode"
  },
  "geometry": {"coordinates":[0.048122,52.675474],"type":"Point"}
}
