{
  "type": "Feature",
  "properties": {
    "iso:country":"GB",
    "wof:name":"PE13 4PR",
    "wof:placetype":"postalcode"
},
  "geometry": {"coordinates":[0.04810587055974,52.67545492206513],"type":"Point"}
}