{
  "type": "Feature",
  "properties": {
    "date:inception_lower": "1980-01-01",
    "date:inception_upper": "1980-01-01",
    "iso:country": "GB",
    "wof:name": "PE13 4PR",
    "wof:placetype": "postalcode"
  },
  "geometry": {"coordinates":[0.047302,52.674391],"type":"Point"}
}
