{
  "type": "Feature",
  "properties": {
    "iso:country": "GB",
    "wof:name": "DA11 9LX",
    "wof:placetype": "postalcode"
  },
  "geometry": {"coordinates":[0.354777,51.445076],"type":"Point"}
}
