{
  "type": "Feature",
  "properties": {
    "date:inception_lower":"1980-01-01",
    "date:inception_upper":"1980-01-31",
    "iso:country":"GB",
    "wof:name":"DA11 9LX",
    "wof:placetype":"postalcode"
},
  "geometry": {"coordinates":[0.354777,51.445076],"type":"Point"}
}