{
  "type": "Feature",
  "properties": {
    "date:inception_lower": "2001-12-01",
    "date:inception_upper": "2001-12-01",
    "iso:country": "GB",
    "wof:name": "ME1 3QP",
    "wof:placetype": "postalcode"
  },
  "geometry": {"coordinates":[0.489301,51.373441],"type":"Point"}
}
