{
  "type": "Feature",
  "properties": {
    "iso:country":"GB",
    "wof:name":"ME1 3QP",
    "wof:placetype":"postalcode"
},
  "geometry": {"coordinates":[0.4893005012257,51.37344062575839],"type":"Point"}
}