{
  "type": "Feature",
  "properties": {
    "iso:country":"GB",
    "wof:name":"CO15 9SL",
    "wof:placetype":"postalcode"
},
  "geometry": {"coordinates":[1.15328339617598,51.79218796374968],"type":"Point"}
}