{
  "type": "Feature",
  "properties": {
    "iso:country": "GB",
    "wof:name": "BL2 5BA",
    "wof:placetype": "postalcode"
  },
  "geometry": {"coordinates":[-2.382695,53.587813],"type":"Point"}
}
