{
  "type": "Feature",
  "properties": {
    "iso:country": "GB",
    "wof:name": "IV12 4BN",
    "wof:placetype": "postalcode"
  },
  "geometry": {"coordinates":[-3.869134,57.584036],"type":"Point"}
}
