{
  "type": "Feature",
  "properties": {
    "date:inception_lower": "1995-07-01",
    "date:inception_upper": "1995-07-01",
    "iso:country": "GB",
    "wof:name": "CH5 2TF",
    "wof:placetype": "postalcode"
  },
  "geometry": {"coordinates":[-3.018791,53.20807],"type":"Point"}
}
