{
  "type": "Feature",
  "properties": {
    "iso:country":"GB",
    "wof:name":"PL5 4BQ",
    "wof:placetype":"postalcode"
},
  "geometry": {"coordinates":[-4.14012894042968,50.41440143066396],"type":"Point"}
}