{
  "type": "Feature",
  "properties": {
    "iso:country":"GB",
    "wof:name":"CR2 6ND",
    "wof:placetype":"postalcode"
},
  "geometry": {"coordinates":[-0.10681767905098,51.3590881773803],"type":"Point"}
}