{
  "type": "Feature",
  "properties": {
    "date:inception_lower": "1980-01-01",
    "date:inception_upper": "1980-01-01",
    "iso:country": "GB",
    "wof:name": "TN15 0SP",
    "wof:placetype": "postalcode"
  },
  "geometry": {"coordinates":[0.227347,51.256317],"type":"Point"}
}
