{
  "type": "Feature",
  "properties": {
    "iso:country":"GB",
    "wof:name":"TN15 0SP",
    "wof:placetype":"postalcode"
},
  "geometry": {"coordinates":[0.22734714914774,51.25631706955458],"type":"Point"}
}