{
  "type": "Feature",
  "properties": {
    "iso:country": "GB",
    "wof:name": "PE23 5NS",
    "wof:placetype": "postalcode"
  },
  "geometry": {"coordinates":[0.130487,53.190757],"type":"Point"}
}
