{
  "type": "Feature",
  "properties": {
    "iso:country":"GB",
    "wof:name":"PE23 5NS",
    "wof:placetype":"postalcode"
},
  "geometry": {"coordinates":[0.13048399556546,53.19073108500749],"type":"Point"}
}