{
  "type": "Feature",
  "properties": {
    "iso:country": "GB",
    "wof:name": "PE23 5NS",
    "wof:placetype": "postalcode"
  },
  "geometry": {"coordinates":[0.131763,53.190528],"type":"Point"}
}
