{
  "type": "Feature",
  "properties": {
    "date:inception_lower": "1980-01-01",
    "date:inception_upper": "1980-01-01",
    "iso:country": "GB",
    "wof:name": "PE23 5NS",
    "wof:placetype": "postalcode"
  },
  "geometry": {"coordinates":[0.130487,53.190757],"type":"Point"}
}
