{
  "type": "Feature",
  "properties": {
    "date:inception_lower":"1980-01-01",
    "date:inception_upper":"1980-01-31",
    "iso:country":"GB",
    "wof:name":"EX2 5HL",
    "wof:placetype":"postalcode"
},
  "geometry": {"coordinates":[-3.497598,50.718439],"type":"Point"}
}