{
  "type": "Feature",
  "properties": {
    "iso:country":"GB",
    "wof:name":"EX2 5HL",
    "wof:placetype":"postalcode"
},
  "geometry": {"coordinates":[-3.49759831300872,50.71843867582214],"type":"Point"}
}