{
  "type": "Feature",
  "properties": {
    "iso:country": "GB",
    "wof:name": "EX2 5HL",
    "wof:placetype": "postalcode"
  },
  "geometry": {"coordinates":[-3.497598,50.718439],"type":"Point"}
}
