{
  "type": "Feature",
  "properties": {
    "iso:country":"GB",
    "wof:name":"TS11 7EQ",
    "wof:placetype":"postalcode"
},
  "geometry": {"coordinates":[-1.00395402129323,54.58707800049668],"type":"Point"}
}