{
  "type": "Feature",
  "properties": {
    "iso:country":"GB",
    "wof:name":"L31 8EF",
    "wof:placetype":"postalcode"
},
  "geometry": {"coordinates":[-2.95333607679982,53.51394060004133],"type":"Point"}
}