{
  "type": "Feature",
  "properties": {
    "date:inception_lower":"1995-07-01",
    "date:inception_upper":"1995-07-31",
    "iso:country":"GB",
    "wof:name":"LA22 0DD",
    "wof:placetype":"postalcode"
},
  "geometry": {"coordinates":[-2.962617,54.428116],"type":"Point"}
}