{
  "type": "Feature",
  "properties": {
    "iso:country":"GB",
    "wof:name":"LA22 0DD",
    "wof:placetype":"postalcode"
},
  "geometry": {"coordinates":[-2.9626172641715,54.4281162259401],"type":"Point"}
}