{
  "type": "Feature",
  "properties": {
    "iso:country":"GB",
    "wof:name":"ST1 4AZ",
    "wof:placetype":"postalcode"
},
  "geometry": {"coordinates":[-2.18801027236309,53.01906914507893],"type":"Point"}
}