{
  "type": "Feature",
  "properties": {
    "date:inception_lower":"2008-01-01",
    "date:inception_upper":"2008-01-31",
    "iso:country":"GB",
    "wof:name":"ST1 4AZ",
    "wof:placetype":"postalcode"
},
  "geometry": {"coordinates":[-2.188009,53.019087],"type":"Point"}
}