{
  "type": "Feature",
  "properties": {
    "date:inception_lower": "2008-01-01",
    "date:inception_upper": "2008-01-01",
    "iso:country": "GB",
    "wof:name": "ST1 4AZ",
    "wof:placetype": "postalcode"
  },
  "geometry": {"coordinates":[-2.18795,53.019123],"type":"Point"}
}
