{
  "type": "Feature",
  "properties": {
    "iso:country":"GB",
    "wof:name":"CO4 0NB",
    "wof:placetype":"postalcode"
},
  "geometry": {"coordinates":[0.92962969646874,51.9029791922522],"type":"Point"}
}