{
  "type": "Feature",
  "properties": {
    "date:inception_lower":"2002-06-01",
    "date:inception_upper":"2002-06-30",
    "iso:country":"GB",
    "wof:name":"CO4 0NB",
    "wof:placetype":"postalcode"
},
  "geometry": {"coordinates":[0.92963,51.902979],"type":"Point"}
}