{
  "type": "Feature",
  "properties": {
    "iso:country":"GB",
    "wof:name":"PH33 7JB",
    "wof:placetype":"postalcode"
},
  "geometry": {"coordinates":[-5.09738547595173,56.84221547710892],"type":"Point"}
}