{
  "type": "Feature",
  "properties": {
    "iso:country":"GB",
    "wof:name":"PE22 7LD",
    "wof:placetype":"postalcode"
},
  "geometry": {"coordinates":[-0.04665618334216,53.09922450099462],"type":"Point"}
}