{
  "type": "Feature",
  "properties": {
    "iso:country": "GB",
    "wof:name": "PE22 7LD",
    "wof:placetype": "postalcode"
  },
  "geometry": {"coordinates":[-0.046656,53.099224],"type":"Point"}
}
