{
  "type": "Feature",
  "properties": {
    "iso:country": "GB",
    "wof:name": "PA2 8AE",
    "wof:placetype": "postalcode"
  },
  "geometry": {"coordinates":[-4.429573,55.826908],"type":"Point"}
}
