{
  "type": "Feature",
  "properties": {
    "date:inception_lower": "1980-01-01",
    "date:inception_upper": "1980-01-01",
    "iso:country": "GB",
    "wof:name": "PA2 8AE",
    "wof:placetype": "postalcode"
  },
  "geometry": {"coordinates":[-4.429573,55.826908],"type":"Point"}
}
