{
  "type": "Feature",
  "properties": {
    "iso:country": "GB",
    "wof:name": "AB33 8SB",
    "wof:placetype": "postalcode"
  },
  "geometry": {"coordinates":[-2.840282,57.213116],"type":"Point"}
}
