{
  "type": "Feature",
  "properties": {
    "iso:country":"GB",
    "wof:name":"AB33 8SB",
    "wof:placetype":"postalcode"
},
  "geometry": {"coordinates":[-2.84028252580409,57.21311632643566],"type":"Point"}
}