{
  "type": "Feature",
  "properties": {
    "iso:country":"GB",
    "wof:name":"S11 9NL",
    "wof:placetype":"postalcode"
},
  "geometry": {"coordinates":[-1.52460016574936,53.3403712022595],"type":"Point"}
}