{
  "type": "Feature",
  "properties": {
    "iso:country": "GB",
    "wof:name": "GU10 1PX",
    "wof:placetype": "postalcode"
  },
  "geometry": {"coordinates":[-0.74813,51.214063],"type":"Point"}
}
