{
  "type": "Feature",
  "properties": {
    "iso:country": "GB",
    "wof:name": "L14 7AJ",
    "wof:placetype": "postalcode"
  },
  "geometry": {"coordinates":[-2.885234,53.409098],"type":"Point"}
}
