{
  "type": "Feature",
  "properties": {
    "iso:country":"GB",
    "wof:name":"WA15 7SW",
    "wof:placetype":"postalcode"
},
  "geometry": {"coordinates":[-2.32596172074469,53.39392218062694],"type":"Point"}
}