{
  "type": "Feature",
  "properties": {
    "iso:country": "GB",
    "wof:name": "BL1 8GA",
    "wof:placetype": "postalcode"
  },
  "geometry": {"coordinates":[-2.416805,53.593865],"type":"Point"}
}
