{
  "type": "Feature",
  "properties": {
    "iso:country":"GB",
    "wof:name":"SP11 8BZ",
    "wof:placetype":"postalcode"
},
  "geometry": {"coordinates":[-1.54009144017926,51.20293079501636],"type":"Point"}
}