{
  "type": "Feature",
  "properties": {
    "date:inception_lower": "1980-01-01",
    "date:inception_upper": "1980-01-01",
    "iso:country": "GB",
    "wof:name": "SP11 8BZ",
    "wof:placetype": "postalcode"
  },
  "geometry": {"coordinates":[-1.540091,51.202931],"type":"Point"}
}
