{
  "type": "Feature",
  "properties": {
    "iso:country":"GB",
    "wof:name":"UB5 5PB",
    "wof:placetype":"postalcode"
},
  "geometry": {"coordinates":[-0.38778275470991,51.53634019950572],"type":"Point"}
}