{
  "type": "Feature",
  "properties": {
    "iso:country":"GB",
    "wof:name":"YO30 5QU",
    "wof:placetype":"postalcode"
},
  "geometry": {"coordinates":[-1.10531475047638,53.9771278536782],"type":"Point"}
}