{
  "type": "Feature",
  "properties": {
    "date:inception_lower": "1988-03-01",
    "date:inception_upper": "1988-03-01",
    "iso:country": "GB",
    "wof:name": "KT7 0SP",
    "wof:placetype": "postalcode"
  },
  "geometry": {"coordinates":[-0.342099,51.398822],"type":"Point"}
}
