{
  "type": "Feature",
  "properties": {
    "iso:country":"GB",
    "wof:name":"KT7 0SP",
    "wof:placetype":"postalcode"
},
  "geometry": {"coordinates":[-0.34245924671517,51.40019387330914],"type":"Point"}
}