{
  "type": "Feature",
  "properties": {
    "iso:country":"GB",
    "wof:name":"LA3 1NZ",
    "wof:placetype":"postalcode"
},
  "geometry": {"coordinates":[-2.89175094485968,54.0565094637133],"type":"Point"}
}