{
  "type": "Feature",
  "properties": {
    "date:inception_lower": "1980-01-01",
    "date:inception_upper": "1980-01-01",
    "iso:country": "GB",
    "wof:name": "LA3 1NZ",
    "wof:placetype": "postalcode"
  },
  "geometry": {"coordinates":[-2.891751,54.056509],"type":"Point"}
}
