{
  "type": "Feature",
  "properties": {
    "iso:country": "GB",
    "wof:name": "CW8 4GR",
    "wof:placetype": "postalcode"
  },
  "geometry": {"coordinates":[-2.547852,53.270404],"type":"Point"}
}
