{
  "type": "Feature",
  "properties": {
    "date:inception_lower": "2008-06-01",
    "date:inception_upper": "2008-06-01",
    "iso:country": "GB",
    "wof:name": "AB31 4FJ",
    "wof:placetype": "postalcode"
  },
  "geometry": {"coordinates":[-2.500724,57.062189],"type":"Point"}
}
