{
  "type": "Feature",
  "properties": {
    "iso:country":"GB",
    "wof:name":"HP2 6NB",
    "wof:placetype":"postalcode"
},
  "geometry": {"coordinates":[-0.46293571007467,51.77602253577286],"type":"Point"}
}