{
  "type": "Feature",
  "properties": {
    "date:inception_lower": "2013-10-01",
    "date:inception_upper": "2013-10-01",
    "iso:country": "GB",
    "wof:name": "GL1 1PE",
    "wof:placetype": "postalcode"
  },
  "geometry": {"coordinates":[-2.239601,51.864718],"type":"Point"}
}
