{
  "type": "Feature",
  "properties": {
    "iso:country":"GB",
    "wof:name":"RH11 8HH",
    "wof:placetype":"postalcode"
},
  "geometry": {"coordinates":[-0.21619339308065,51.11099351175036],"type":"Point"}
}