{
  "type": "Feature",
  "properties": {
    "iso:country":"GB",
    "wof:name":"TF9 4BA",
    "wof:placetype":"postalcode"
},
  "geometry": {"coordinates":[-2.45990124048206,52.95896292031458],"type":"Point"}
}