{
  "type": "Feature",
  "properties": {
    "iso:country": "GB",
    "wof:name": "HR1 3PU",
    "wof:placetype": "postalcode"
  },
  "geometry": {"coordinates":[-2.639788,52.084739],"type":"Point"}
}
