{
  "type": "Feature",
  "properties": {
    "iso:country":"GB",
    "wof:name":"SM2 6AQ",
    "wof:placetype":"postalcode"
},
  "geometry": {"coordinates":[-0.19332027236744,51.35274751394021],"type":"Point"}
}