{
  "type": "Feature",
  "properties": {
    "iso:country":"GB",
    "wof:name":"RG2 9AJ",
    "wof:placetype":"postalcode"
},
  "geometry": {"coordinates":[-0.94834842877626,51.40657576785307],"type":"Point"}
}