{
  "type": "Feature",
  "properties": {
    "iso:country": "GB",
    "wof:name": "YO7 1NR",
    "wof:placetype": "postalcode"
  },
  "geometry": {"coordinates":[-1.3429,54.222803],"type":"Point"}
}
