{
  "type": "Feature",
  "properties": {
    "iso:country":"GB",
    "wof:name":"YO7 1NR",
    "wof:placetype":"postalcode"
},
  "geometry": {"coordinates":[-1.34289988326473,54.2228027378304],"type":"Point"}
}