{
  "type": "Feature",
  "properties": {
    "iso:country":"GB",
    "wof:name":"PO7 8DG",
    "wof:placetype":"postalcode"
},
  "geometry": {"coordinates":[-1.02133687982464,50.8719232684805],"type":"Point"}
}