{
  "type": "Feature",
  "properties": {
    "iso:country": "GB",
    "wof:name": "PO7 8DG",
    "wof:placetype": "postalcode"
  },
  "geometry": {"coordinates":[-1.021337,50.871923],"type":"Point"}
}
