{
  "type": "Feature",
  "properties": {
    "date:inception_lower": "1995-07-01",
    "date:inception_upper": "1995-07-01",
    "iso:country": "GB",
    "wof:name": "RG21 7SQ",
    "wof:placetype": "postalcode"
  },
  "geometry": {"coordinates":[-1.090338,51.264378],"type":"Point"}
}
