{
  "type": "Feature",
  "properties": {
    "iso:country": "GB",
    "wof:name": "RG21 7SQ",
    "wof:placetype": "postalcode"
  },
  "geometry": {"coordinates":[-1.090338,51.264378],"type":"Point"}
}
