{
  "type": "Feature",
  "properties": {
    "date:inception_lower": "1999-06-01",
    "date:inception_upper": "1999-06-01",
    "iso:country": "GB",
    "wof:name": "S35 9UP",
    "wof:placetype": "postalcode"
  },
  "geometry": {"coordinates":[-1.46542,53.441657],"type":"Point"}
}
