{
  "type": "Feature",
  "properties": {
    "iso:country": "GB",
    "wof:name": "S35 9UP",
    "wof:placetype": "postalcode"
  },
  "geometry": {"coordinates":[-1.46542,53.441657],"type":"Point"}
}
