{
  "type": "Feature",
  "properties": {
    "iso:country":"GB",
    "wof:name":"ML1 3YG",
    "wof:placetype":"postalcode"
},
  "geometry": {"coordinates":[-3.99809164143818,55.8041663112035],"type":"Point"}
}