{
  "type": "Feature",
  "properties": {
    "iso:country":"GB",
    "wof:name":"CO10 7EH",
    "wof:placetype":"postalcode"
},
  "geometry": {"coordinates":[0.69074400371755,52.0225667269734],"type":"Point"}
}