{
  "type": "Feature",
  "properties": {
    "iso:country": "GB",
    "wof:name": "CO10 7EH",
    "wof:placetype": "postalcode"
  },
  "geometry": {"coordinates":[0.69055,52.022499],"type":"Point"}
}
