{
  "type": "Feature",
  "properties": {
    "iso:country": "GB",
    "wof:name": "PL9 7PX",
    "wof:placetype": "postalcode"
  },
  "geometry": {"coordinates":[-4.102517,50.361598],"type":"Point"}
}
