{
  "type": "Feature",
  "properties": {
    "iso:country":"GB",
    "wof:name":"PL9 7PX",
    "wof:placetype":"postalcode"
},
  "geometry": {"coordinates":[-4.10251663995698,50.36159838673822],"type":"Point"}
}