{
  "type": "Feature",
  "properties": {
    "iso:country":"GB",
    "wof:name":"GU6 8LR",
    "wof:placetype":"postalcode"
},
  "geometry": {"coordinates":[-0.50394293878582,51.14642269865086],"type":"Point"}
}