{
  "type": "Feature",
  "properties": {
    "iso:country":"GB",
    "wof:name":"PA3 4SX",
    "wof:placetype":"postalcode"
},
  "geometry": {"coordinates":[-4.40534338640028,55.85575051787973],"type":"Point"}
}