{
  "type": "Feature",
  "properties": {
    "date:inception_lower":"1980-01-01",
    "date:inception_upper":"1980-01-31",
    "iso:country":"GB",
    "wof:name":"HU17 7LN",
    "wof:placetype":"postalcode"
},
  "geometry": {"coordinates":[-0.462227,53.878296],"type":"Point"}
}