{
  "type": "Feature",
  "properties": {
    "iso:country":"GB",
    "wof:name":"HU17 7LN",
    "wof:placetype":"postalcode"
},
  "geometry": {"coordinates":[-0.4622271613481,53.8782962682679],"type":"Point"}
}