{
  "type": "Feature",
  "properties": {
    "iso:country":"GB",
    "wof:name":"LU5 4BP",
    "wof:placetype":"postalcode"
},
  "geometry": {"coordinates":[-0.51288443445962,51.8822541260086],"type":"Point"}
}