{
  "type": "Feature",
  "properties": {
    "date:inception_lower":"2003-11-01",
    "date:inception_upper":"2003-11-30",
    "iso:country":"GB",
    "wof:name":"NW7 1HF",
    "wof:placetype":"postalcode"
},
  "geometry": {"coordinates":[-0.212135,51.608287],"type":"Point"}
}