{
  "type": "Feature",
  "properties": {
    "iso:country":"GB",
    "wof:name":"NW7 1HF",
    "wof:placetype":"postalcode"
},
  "geometry": {"coordinates":[-0.21213535412185,51.60828749898371],"type":"Point"}
}