{
  "type": "Feature",
  "properties": {
    "iso:country": "GB",
    "wof:name": "NW7 1HF",
    "wof:placetype": "postalcode"
  },
  "geometry": {"coordinates":[-0.212135,51.608287],"type":"Point"}
}
