{
  "type": "Feature",
  "properties": {
    "iso:country":"GB",
    "wof:name":"B61 9ER",
    "wof:placetype":"postalcode"
},
  "geometry": {"coordinates":[-2.13807715824675,52.32304934526647],"type":"Point"}
}