{
  "type": "Feature",
  "properties": {
    "date:inception_lower":"1980-01-01",
    "date:inception_upper":"1980-01-31",
    "iso:country":"GB",
    "wof:name":"PA14 6HU",
    "wof:placetype":"postalcode"
},
  "geometry": {"coordinates":[-4.662143,55.919788],"type":"Point"}
}