{
  "type": "Feature",
  "properties": {
    "date:inception_lower": "2008-01-01",
    "date:inception_upper": "2008-01-01",
    "iso:country": "GB",
    "wof:name": "B46 1EZ",
    "wof:placetype": "postalcode"
  },
  "geometry": {"coordinates":[-1.708638,52.509298],"type":"Point"}
}
