{
  "type": "Feature",
  "properties": {
    "iso:country":"GB",
    "wof:name":"NE65 9UU",
    "wof:placetype":"postalcode"
},
  "geometry": {"coordinates":[-1.61503583812678,55.30547678642391],"type":"Point"}
}