{
  "type": "Feature",
  "properties": {
    "iso:country": "GB",
    "wof:name": "NE65 9UU",
    "wof:placetype": "postalcode"
  },
  "geometry": {"coordinates":[-1.614892,55.305515],"type":"Point"}
}
