{
  "type": "Feature",
  "properties": {
    "iso:country": "GB",
    "wof:name": "E5 8AL",
    "wof:placetype": "postalcode"
  },
  "geometry": {"coordinates":[-0.060827,51.561444],"type":"Point"}
}
