{
  "type": "Feature",
  "properties": {
    "iso:country": "GB",
    "wof:name": "BA6 9GT",
    "wof:placetype": "postalcode"
  },
  "geometry": {"coordinates":[-2.785888,51.170359],"type":"Point"}
}
