{
  "type": "Feature",
  "properties": {
    "iso:country":"GB",
    "wof:name":"BA6 9GT",
    "wof:placetype":"postalcode"
},
  "geometry": {"coordinates":[-2.78588794035675,51.17035871731316],"type":"Point"}
}