{
  "type": "Feature",
  "properties": {
    "iso:country":"GB",
    "wof:name":"LD1 5HY",
    "wof:placetype":"postalcode"
},
  "geometry": {"coordinates":[-3.37530064160966,52.24283435104813],"type":"Point"}
}