{
  "type": "Feature",
  "properties": {
    "iso:country": "GB",
    "wof:name": "LD1 5HY",
    "wof:placetype": "postalcode"
  },
  "geometry": {"coordinates":[-3.375301,52.242834],"type":"Point"}
}
