{
  "type": "Feature",
  "properties": {
    "iso:country":"GB",
    "wof:name":"ST15 8PF",
    "wof:placetype":"postalcode"
},
  "geometry": {"coordinates":[-2.13888270123301,52.90030809304327],"type":"Point"}
}