{
  "type": "Feature",
  "properties": {
    "iso:country": "GB",
    "wof:name": "BD8 7NG",
    "wof:placetype": "postalcode"
  },
  "geometry": {"coordinates":[-1.759924,53.803184],"type":"Point"}
}
