{
  "type": "Feature",
  "properties": {
    "iso:country":"GB",
    "wof:name":"TS7 0PS",
    "wof:placetype":"postalcode"
},
  "geometry": {"coordinates":[-1.18498854985307,54.52967426456841],"type":"Point"}
}