{
  "type": "Feature",
  "properties": {
    "date:inception_lower": "1980-01-01",
    "date:inception_upper": "1980-01-01",
    "iso:country": "GB",
    "wof:name": "BL3 2JB",
    "wof:placetype": "postalcode"
  },
  "geometry": {"coordinates":[-2.416982,53.557931],"type":"Point"}
}
