{
  "type": "Feature",
  "properties": {
    "iso:country":"GB",
    "wof:name":"BL3 2JB",
    "wof:placetype":"postalcode"
},
  "geometry": {"coordinates":[-2.41698163689059,53.55793082676853],"type":"Point"}
}