{
  "type": "Feature",
  "properties": {
    "iso:country":"GB",
    "wof:name":"NW8 8EH",
    "wof:placetype":"postalcode"
},
  "geometry": {"coordinates":[-0.16929157754642,51.52444741769278],"type":"Point"}
}