{
  "type": "Feature",
  "properties": {
    "iso:country": "GB",
    "wof:name": "LL22 7NY",
    "wof:placetype": "postalcode"
  },
  "geometry": {"coordinates":[-3.577991,53.289428],"type":"Point"}
}
