{
  "type": "Feature",
  "properties": {
    "iso:country":"GB",
    "wof:name":"LL22 7NY",
    "wof:placetype":"postalcode"
},
  "geometry": {"coordinates":[-3.57799102685641,53.28942776507841],"type":"Point"}
}