{
  "type": "Feature",
  "properties": {
    "iso:country":"GB",
    "wof:name":"BR5 3HS",
    "wof:placetype":"postalcode"
},
  "geometry": {"coordinates":[0.11768861734585,51.40390551333313],"type":"Point"}
}