{
  "type": "Feature",
  "properties": {
    "date:inception_lower": "1980-01-01",
    "date:inception_upper": "1980-01-01",
    "iso:country": "GB",
    "wof:name": "CT16 1PA",
    "wof:placetype": "postalcode"
  },
  "geometry": {"coordinates":[1.31429,51.125335],"type":"Point"}
}
