{
  "type": "Feature",
  "properties": {
    "iso:country": "GB",
    "wof:name": "CT16 1PA",
    "wof:placetype": "postalcode"
  },
  "geometry": {"coordinates":[1.314009,51.125199],"type":"Point"}
}
