{
  "type": "Feature",
  "properties": {
    "iso:country":"GB",
    "wof:name":"OX26 3XD",
    "wof:placetype":"postalcode"
},
  "geometry": {"coordinates":[-1.14904020134704,51.90995394857286],"type":"Point"}
}