{
  "type": "Feature",
  "properties": {
    "iso:country":"GB",
    "wof:name":"BN15 8JG",
    "wof:placetype":"postalcode"
},
  "geometry": {"coordinates":[-0.31055379923688,50.82756593653534],"type":"Point"}
}