{
  "type": "Feature",
  "properties": {
    "iso:country": "GB",
    "wof:name": "DY1 4SP",
    "wof:placetype": "postalcode"
  },
  "geometry": {"coordinates":[-2.073313,52.519627],"type":"Point"}
}
