{
  "type": "Feature",
  "properties": {
    "iso:country":"GB",
    "wof:name":"TN34 2UE",
    "wof:placetype":"postalcode"
},
  "geometry": {"coordinates":[0.58814870061232,50.87988457494517],"type":"Point"}
}