{
  "type": "Feature",
  "properties": {
    "iso:country": "GB",
    "wof:name": "TN34 2UE",
    "wof:placetype": "postalcode"
  },
  "geometry": {"coordinates":[0.588033,50.87983],"type":"Point"}
}
