{
  "type": "Feature",
  "properties": {
    "iso:country":"GB",
    "wof:name":"UB3 4LQ",
    "wof:placetype":"postalcode"
},
  "geometry": {"coordinates":[-0.41967890299271,51.49548195162942],"type":"Point"}
}