{
  "type": "Feature",
  "properties": {
    "iso:country": "GB",
    "wof:name": "NE12 7LA",
    "wof:placetype": "postalcode"
  },
  "geometry": {"coordinates":[-1.567374,55.022178],"type":"Point"}
}
