{
  "type": "Feature",
  "properties": {
    "iso:country":"GB",
    "wof:name":"DH1 3AG",
    "wof:placetype":"postalcode"
},
  "geometry": {"coordinates":[-1.57264936530034,54.77567254279243],"type":"Point"}
}