{
  "type": "Feature",
  "properties": {
    "iso:country": "GB",
    "wof:name": "DH1 3AG",
    "wof:placetype": "postalcode"
  },
  "geometry": {"coordinates":[-1.572649,54.775673],"type":"Point"}
}
