{
  "type": "Feature",
  "properties": {
    "date:inception_lower": "1991-09-01",
    "date:inception_upper": "1991-09-01",
    "iso:country": "GB",
    "wof:name": "MK7 6HB",
    "wof:placetype": "postalcode"
  },
  "geometry": {"coordinates":[-0.698495,52.025941],"type":"Point"}
}
