{
  "type": "Feature",
  "properties": {
    "iso:country":"GB",
    "wof:name":"MK7 6HB",
    "wof:placetype":"postalcode"
},
  "geometry": {"coordinates":[-0.69849481527195,52.02594070561658],"type":"Point"}
}