{
  "type": "Feature",
  "properties": {
    "iso:country": "GB",
    "wof:name": "MK7 6HB",
    "wof:placetype": "postalcode"
  },
  "geometry": {"coordinates":[-0.698495,52.025941],"type":"Point"}
}
