{
  "type": "Feature",
  "properties": {
    "iso:country": "GB",
    "wof:name": "CB24 3YX",
    "wof:placetype": "postalcode"
  },
  "geometry": {"coordinates":[0.052735,52.252143],"type":"Point"}
}
