{
  "type": "Feature",
  "properties": {
    "iso:country":"GB",
    "wof:name":"CB24 3YX",
    "wof:placetype":"postalcode"
},
  "geometry": {"coordinates":[0.05270736974013,52.25212906649988],"type":"Point"}
}