{
  "type": "Feature",
  "properties": {
    "date:inception_lower": "2006-09-01",
    "date:inception_upper": "2006-09-01",
    "iso:country": "GB",
    "wof:name": "CB24 3YX",
    "wof:placetype": "postalcode"
  },
  "geometry": {"coordinates":[0.052616,52.252109],"type":"Point"}
}
