{
  "type": "Feature",
  "properties": {
    "iso:country": "GB",
    "wof:name": "SK13 6EY",
    "wof:placetype": "postalcode"
  },
  "geometry": {"coordinates":[-1.982691,53.447642],"type":"Point"}
}
