{
  "type": "Feature",
  "properties": {
    "iso:country": "GB",
    "wof:name": "BS10 5QR",
    "wof:placetype": "postalcode"
  },
  "geometry": {"coordinates":[-2.600596,51.500513],"type":"Point"}
}
