{
  "type": "Feature",
  "properties": {
    "iso:country":"GB",
    "wof:name":"BS10 5QR",
    "wof:placetype":"postalcode"
},
  "geometry": {"coordinates":[-2.60059645096706,51.50051297336952],"type":"Point"}
}