{
  "type": "Feature",
  "properties": {
    "iso:country": "GB",
    "wof:name": "SO41 8EX",
    "wof:placetype": "postalcode"
  },
  "geometry": {"coordinates":[-1.562021,50.748282],"type":"Point"}
}
