{
  "type": "Feature",
  "properties": {
    "iso:country": "GB",
    "wof:name": "RH2 7QD",
    "wof:placetype": "postalcode"
  },
  "geometry": {"coordinates":[-0.189573,51.219246],"type":"Point"}
}
