{
  "type": "Feature",
  "properties": {
    "date:inception_lower": "1992-08-01",
    "date:inception_upper": "1992-08-01",
    "iso:country": "GB",
    "wof:name": "SA4 3DS",
    "wof:placetype": "postalcode"
  },
  "geometry": {"coordinates":[-4.04415,51.652043],"type":"Point"}
}
