{
  "type": "Feature",
  "properties": {
    "iso:country":"GB",
    "wof:name":"MK18 1AU",
    "wof:placetype":"postalcode"
},
  "geometry": {"coordinates":[-0.9865908756086,51.99425399126054],"type":"Point"}
}