{
  "type": "Feature",
  "properties": {
    "iso:country":"GB",
    "wof:name":"B7 4EG",
    "wof:placetype":"postalcode"
},
  "geometry": {"coordinates":[-1.88107013250107,52.48684298982579],"type":"Point"}
}