{
  "type": "Feature",
  "properties": {
    "iso:country":"GB",
    "wof:name":"M33 5AP",
    "wof:placetype":"postalcode"
},
  "geometry": {"coordinates":[-2.34137325908412,53.42182461030646],"type":"Point"}
}