{
  "type": "Feature",
  "properties": {
    "date:inception_lower": "1980-01-01",
    "date:inception_upper": "1980-01-01",
    "iso:country": "GB",
    "wof:name": "BN8 5RY",
    "wof:placetype": "postalcode"
  },
  "geometry": {"coordinates":[0.044045,50.902367],"type":"Point"}
}
