{
  "type": "Feature",
  "properties": {
    "iso:country":"GB",
    "wof:name":"BN8 5RY",
    "wof:placetype":"postalcode"
},
  "geometry": {"coordinates":[0.04404487541178,50.90236678437015],"type":"Point"}
}