{
  "type": "Feature",
  "properties": {
    "iso:country":"GB",
    "wof:name":"SG5 3TR",
    "wof:placetype":"postalcode"
},
  "geometry": {"coordinates":[-0.27818689846635,51.97852080699898],"type":"Point"}
}