{
  "type": "Feature",
  "properties": {
    "iso:country": "GB",
    "wof:name": "SM4 4RX",
    "wof:placetype": "postalcode"
  },
  "geometry": {"coordinates":[-0.222396,51.384451],"type":"Point"}
}
