{
  "type": "Feature",
  "properties": {
    "iso:country":"GB",
    "wof:name":"SM4 4RX",
    "wof:placetype":"postalcode"
},
  "geometry": {"coordinates":[-0.22239566805332,51.38445067729036],"type":"Point"}
}