{
  "type": "Feature",
  "properties": {
    "date:inception_lower": "1980-01-01",
    "date:inception_upper": "1980-01-01",
    "iso:country": "GB",
    "wof:name": "SM4 4RX",
    "wof:placetype": "postalcode"
  },
  "geometry": {"coordinates":[-0.222396,51.384451],"type":"Point"}
}
