{
  "type": "Feature",
  "properties": {
    "iso:country":"GB",
    "wof:name":"GU34 4AL",
    "wof:placetype":"postalcode"
},
  "geometry": {"coordinates":[-1.02933881292488,51.13966966803923],"type":"Point"}
}