{
  "type": "Feature",
  "properties": {
    "iso:country": "GB",
    "wof:name": "GU34 4AL",
    "wof:placetype": "postalcode"
  },
  "geometry": {"coordinates":[-1.029339,51.13967],"type":"Point"}
}
