{
  "type": "Feature",
  "properties": {
    "iso:country":"GB",
    "wof:name":"B37 7BQ",
    "wof:placetype":"postalcode"
},
  "geometry": {"coordinates":[-1.7238899832479,52.44764524829572],"type":"Point"}
}