{
  "type": "Feature",
  "properties": {
    "date:inception_lower":"2007-09-01",
    "date:inception_upper":"2007-09-30",
    "iso:country":"GB",
    "wof:name":"B37 7BQ",
    "wof:placetype":"postalcode"
},
  "geometry": {"coordinates":[-1.72389,52.447645],"type":"Point"}
}