{
  "type": "Feature",
  "properties": {
    "iso:country": "GB",
    "wof:name": "BA3 5QH",
    "wof:placetype": "postalcode"
  },
  "geometry": {"coordinates":[-2.442638,51.224369],"type":"Point"}
}
