{
  "type": "Feature",
  "properties": {
    "iso:country":"GB",
    "wof:name":"E1 5BF",
    "wof:placetype":"postalcode"
},
  "geometry": {"coordinates":[-0.06277904519733,51.5206054256952],"type":"Point"}
}