{
  "type": "Feature",
  "properties": {
    "iso:country":"GB",
    "wof:name":"HG1 3HP",
    "wof:placetype":"postalcode"
},
  "geometry": {"coordinates":[-1.54823065028313,54.00804538902483],"type":"Point"}
}