{
  "type": "Feature",
  "properties": {
    "iso:country": "GB",
    "wof:name": "G65 0PA",
    "wof:placetype": "postalcode"
  },
  "geometry": {"coordinates":[-4.047952,55.973748],"type":"Point"}
}
