{
  "type": "Feature",
  "properties": {
    "iso:country":"GB",
    "wof:name":"G65 0PA",
    "wof:placetype":"postalcode"
},
  "geometry": {"coordinates":[-4.04795157528256,55.97374766246917],"type":"Point"}
}