{
  "type": "Feature",
  "properties": {
    "iso:country": "GB",
    "wof:name": "FK9 4UR",
    "wof:placetype": "postalcode"
  },
  "geometry": {"coordinates":[-4.035934,56.162973],"type":"Point"}
}
