{
  "type": "Feature",
  "properties": {
    "iso:country":"GB",
    "wof:name":"FK9 4UR",
    "wof:placetype":"postalcode"
},
  "geometry": {"coordinates":[-4.03593386515233,56.16297334603378],"type":"Point"}
}