{
  "type": "Feature",
  "properties": {
    "iso:country":"GB",
    "wof:name":"S42 5JD",
    "wof:placetype":"postalcode"
},
  "geometry": {"coordinates":[-1.39825372131839,53.17952899976701],"type":"Point"}
}