{
  "type": "Feature",
  "properties": {
    "date:inception_lower":"1980-01-01",
    "date:inception_upper":"1980-01-31",
    "iso:country":"GB",
    "wof:name":"B78 2JN",
    "wof:placetype":"postalcode"
},
  "geometry": {"coordinates":[-1.683989,52.570726],"type":"Point"}
}