{
  "type": "Feature",
  "properties": {
    "iso:country":"GB",
    "wof:name":"LU5 4BZ",
    "wof:placetype":"postalcode"
},
  "geometry": {"coordinates":[-0.51126413064717,51.88116363812154],"type":"Point"}
}