{
  "type": "Feature",
  "properties": {
    "date:inception_lower": "2019-12-01",
    "date:inception_upper": "2019-12-01",
    "iso:country": "GB",
    "wof:name": "NP10 9PQ",
    "wof:placetype": "postalcode"
  },
  "geometry": {"coordinates":[-3.059777,51.584493],"type":"Point"}
}
