{
  "type": "Feature",
  "properties": {
    "iso:country": "GB",
    "wof:name": "NP10 9PQ",
    "wof:placetype": "postalcode"
  },
  "geometry": {"coordinates":[-3.059767,51.584673],"type":"Point"}
}
