{
  "type": "Feature",
  "properties": {
    "date:inception_lower": "1996-12-01",
    "date:inception_upper": "1996-12-01",
    "iso:country": "GB",
    "wof:name": "GL19 3PT",
    "wof:placetype": "postalcode"
  },
  "geometry": {"coordinates":[-2.309053,51.998861],"type":"Point"}
}
