{
  "type": "Feature",
  "properties": {
    "iso:country":"GB",
    "wof:name":"CB23 7RY",
    "wof:placetype":"postalcode"
},
  "geometry": {"coordinates":[-0.02460005520822,52.21001843080695],"type":"Point"}
}