{
  "type": "Feature",
  "properties": {
    "iso:country": "GB",
    "wof:name": "CB23 7RY",
    "wof:placetype": "postalcode"
  },
  "geometry": {"coordinates":[-0.024423,52.210119],"type":"Point"}
}
