{
  "type": "Feature",
  "properties": {
    "date:inception_lower": "2019-10-01",
    "date:inception_upper": "2019-10-01",
    "iso:country": "GB",
    "wof:name": "DH2 2FN",
    "wof:placetype": "postalcode"
  },
  "geometry": {"coordinates":[-1.607936,54.86234],"type":"Point"}
}
