{
  "type": "Feature",
  "properties": {
    "iso:country":"GB",
    "wof:name":"SE28 8TE",
    "wof:placetype":"postalcode"
},
  "geometry": {"coordinates":[0.09953271777927,51.50342370165257],"type":"Point"}
}