{
  "type": "Feature",
  "properties": {
    "iso:country":"GB",
    "wof:name":"B92 0LU",
    "wof:placetype":"postalcode"
},
  "geometry": {"coordinates":[-1.66879893653762,52.42268236855124],"type":"Point"}
}