{
  "type": "Feature",
  "properties": {
    "iso:country": "GB",
    "wof:name": "HD3 3XX",
    "wof:placetype": "postalcode"
  },
  "geometry": {"coordinates":[-1.861628,53.658735],"type":"Point"}
}
