{
  "type": "Feature",
  "properties": {
    "iso:country":"GB",
    "wof:name":"HD3 3XX",
    "wof:placetype":"postalcode"
},
  "geometry": {"coordinates":[-1.86162830062599,53.65873486219571],"type":"Point"}
}