{
  "type": "Feature",
  "properties": {
    "date:inception_lower": "1985-04-01",
    "date:inception_upper": "1985-04-01",
    "iso:country": "GB",
    "wof:name": "WD6 5NL",
    "wof:placetype": "postalcode"
  },
  "geometry": {"coordinates":[-0.257212,51.668503],"type":"Point"}
}
