{
  "type": "Feature",
  "properties": {
    "iso:country":"GB",
    "wof:name":"WD4 8HJ",
    "wof:placetype":"postalcode"
},
  "geometry": {"coordinates":[-0.44477877775025,51.71301159185228],"type":"Point"}
}