{
  "type": "Feature",
  "properties": {
    "iso:country":"GB",
    "wof:name":"LL36 9DD",
    "wof:placetype":"postalcode"
},
  "geometry": {"coordinates":[-4.08487465057047,52.58672575438602],"type":"Point"}
}