{
  "type": "Feature",
  "properties": {
    "iso:country": "GB",
    "wof:name": "LL36 9DD",
    "wof:placetype": "postalcode"
  },
  "geometry": {"coordinates":[-4.084883,52.586742],"type":"Point"}
}
