{
  "type": "Feature",
  "properties": {
    "iso:country": "GB",
    "wof:name": "LE2 7JT",
    "wof:placetype": "postalcode"
  },
  "geometry": {"coordinates":[-1.142259,52.626558],"type":"Point"}
}
