{
  "type": "Feature",
  "properties": {
    "iso:country":"GB",
    "wof:name":"YO17 6UJ",
    "wof:placetype":"postalcode"
},
  "geometry": {"coordinates":[-0.75759953739014,54.20514043979472],"type":"Point"}
}