{
  "type": "Feature",
  "properties": {
    "iso:country":"GB",
    "wof:name":"HU8 9SA",
    "wof:placetype":"postalcode"
},
  "geometry": {"coordinates":[-0.26252626908655,53.77887519415678],"type":"Point"}
}