{
  "type": "Feature",
  "properties": {
    "iso:country":"GB",
    "wof:name":"SE2 9DD",
    "wof:placetype":"postalcode"
},
  "geometry": {"coordinates":[0.10877066751841,51.49502950091276],"type":"Point"}
}