{
  "type": "Feature",
  "properties": {
    "date:inception_lower": "1980-01-01",
    "date:inception_upper": "1980-01-01",
    "iso:country": "GB",
    "wof:name": "L25 0PU",
    "wof:placetype": "postalcode"
  },
  "geometry": {"coordinates":[-2.856647,53.357944],"type":"Point"}
}
