{
  "type": "Feature",
  "properties": {
    "date:inception_lower":"1980-01-01",
    "date:inception_upper":"1980-01-31",
    "iso:country":"GB",
    "wof:name":"ML1 4RZ",
    "wof:placetype":"postalcode"
},
  "geometry": {"coordinates":[-3.971808,55.820821],"type":"Point"}
}