{
  "type": "Feature",
  "properties": {
    "iso:country": "GB",
    "wof:name": "SO31 1ET",
    "wof:placetype": "postalcode"
  },
  "geometry": {"coordinates":[-1.306831,50.901583],"type":"Point"}
}
