{
  "type": "Feature",
  "properties": {
    "date:inception_lower":"1980-01-01",
    "date:inception_upper":"1980-01-31",
    "iso:country":"GB",
    "wof:name":"NN13 5QN",
    "wof:placetype":"postalcode"
},
  "geometry": {"coordinates":[-1.138609,52.092565],"type":"Point"}
}