{
  "type": "Feature",
  "properties": {
    "iso:country": "GB",
    "wof:name": "NN13 5QN",
    "wof:placetype": "postalcode"
  },
  "geometry": {"coordinates":[-1.138609,52.092565],"type":"Point"}
}
