{
  "type": "Feature",
  "properties": {
    "date:inception_lower": "1980-01-01",
    "date:inception_upper": "1980-01-01",
    "iso:country": "GB",
    "wof:name": "IP11 7QY",
    "wof:placetype": "postalcode"
  },
  "geometry": {"coordinates":[1.347247,51.965129],"type":"Point"}
}
