{
  "type": "Feature",
  "properties": {
    "iso:country": "GB",
    "wof:name": "BS14 8QJ",
    "wof:placetype": "postalcode"
  },
  "geometry": {"coordinates":[-2.539363,51.413356],"type":"Point"}
}
