{
  "type": "Feature",
  "properties": {
    "date:inception_lower": "1991-09-01",
    "date:inception_upper": "1991-09-01",
    "iso:country": "GB",
    "wof:name": "WF3 3BT",
    "wof:placetype": "postalcode"
  },
  "geometry": {"coordinates":[-1.506154,53.741486],"type":"Point"}
}
