{
  "type": "Feature",
  "properties": {
    "iso:country":"GB",
    "wof:name":"WF3 3BT",
    "wof:placetype":"postalcode"
},
  "geometry": {"coordinates":[-1.50615394044251,53.74148641989047],"type":"Point"}
}