{
  "type": "Feature",
  "properties": {
    "iso:country":"GB",
    "wof:name":"M43 6RN",
    "wof:placetype":"postalcode"
},
  "geometry": {"coordinates":[-2.15129409562361,53.48126241755263],"type":"Point"}
}