{
  "type": "Feature",
  "properties": {
    "date:inception_lower":"1994-05-01",
    "date:inception_upper":"1994-05-31",
    "iso:country":"GB",
    "wof:name":"M43 6RN",
    "wof:placetype":"postalcode"
},
  "geometry": {"coordinates":[-2.151294,53.481262],"type":"Point"}
}