{
  "type": "Feature",
  "properties": {
    "iso:country":"GB",
    "wof:name":"SR7 7QX",
    "wof:placetype":"postalcode"
},
  "geometry": {"coordinates":[-1.33757082305869,54.83145783893858],"type":"Point"}
}