{
  "type": "Feature",
  "properties": {
    "iso:country": "GB",
    "wof:name": "SR7 7QX",
    "wof:placetype": "postalcode"
  },
  "geometry": {"coordinates":[-1.337585,54.831466],"type":"Point"}
}
