{
  "type": "Feature",
  "properties": {
    "iso:country":"GB",
    "wof:name":"HX3 8DH",
    "wof:placetype":"postalcode"
},
  "geometry": {"coordinates":[-1.80835065513774,53.71859444884362],"type":"Point"}
}