{
  "type": "Feature",
  "properties": {
    "date:inception_lower": "2000-06-01",
    "date:inception_upper": "2000-06-01",
    "iso:country": "GB",
    "wof:name": "HX3 8DH",
    "wof:placetype": "postalcode"
  },
  "geometry": {"coordinates":[-1.808351,53.718594],"type":"Point"}
}
