{
  "type": "Feature",
  "properties": {
    "iso:country": "GB",
    "wof:name": "FY1 5DW",
    "wof:placetype": "postalcode"
  },
  "geometry": {"coordinates":[-3.054657,53.814235],"type":"Point"}
}
