{
  "type": "Feature",
  "properties": {
    "iso:country":"GB",
    "wof:name":"FY1 5DW",
    "wof:placetype":"postalcode"
},
  "geometry": {"coordinates":[-3.05465691884207,53.81423487661906],"type":"Point"}
}