{
  "type": "Feature",
  "properties": {
    "iso:country": "GB",
    "wof:name": "LL27 0JR",
    "wof:placetype": "postalcode"
  },
  "geometry": {"coordinates":[-3.82668,53.163872],"type":"Point"}
}
