{
  "type": "Feature",
  "properties": {
    "iso:country":"GB",
    "wof:name":"LL27 0JR",
    "wof:placetype":"postalcode"
},
  "geometry": {"coordinates":[-3.82667972953515,53.1638718958824],"type":"Point"}
}