{
  "type": "Feature",
  "properties": {
    "date:inception_lower": "1980-01-01",
    "date:inception_upper": "1980-01-01",
    "iso:country": "GB",
    "wof:name": "LL27 0JR",
    "wof:placetype": "postalcode"
  },
  "geometry": {"coordinates":[-3.82668,53.163872],"type":"Point"}
}
