{
  "type": "Feature",
  "properties": {
    "iso:country":"GB",
    "wof:name":"ME3 8SX",
    "wof:placetype":"postalcode"
},
  "geometry": {"coordinates":[0.56432158429817,51.45382559386326],"type":"Point"}
}