{
  "type": "Feature",
  "properties": {
    "iso:country": "GB",
    "wof:name": "ME3 8SX",
    "wof:placetype": "postalcode"
  },
  "geometry": {"coordinates":[0.564322,51.453826],"type":"Point"}
}
