{
  "type": "Feature",
  "properties": {
    "iso:country": "GB",
    "wof:name": "S81 7JR",
    "wof:placetype": "postalcode"
  },
  "geometry": {"coordinates":[-1.121754,53.317179],"type":"Point"}
}
