{
  "type": "Feature",
  "properties": {
    "iso:country":"GB",
    "wof:name":"S81 7JR",
    "wof:placetype":"postalcode"
},
  "geometry": {"coordinates":[-1.12175431102306,53.31717890178831],"type":"Point"}
}