{
  "type": "Feature",
  "properties": {
    "iso:country":"GB",
    "wof:name":"ML11 0PL",
    "wof:placetype":"postalcode"
},
  "geometry": {"coordinates":[-3.84530282258842,55.55341334424507],"type":"Point"}
}