{
  "type": "Feature",
  "properties": {
    "iso:country":"GB",
    "wof:name":"TS9 7LB",
    "wof:placetype":"postalcode"
},
  "geometry": {"coordinates":[-1.1223694872257,54.35751543197786],"type":"Point"}
}