{
  "type": "Feature",
  "properties": {
    "date:inception_lower": "1980-01-01",
    "date:inception_upper": "1980-01-01",
    "iso:country": "GB",
    "wof:name": "EX1 3HT",
    "wof:placetype": "postalcode"
  },
  "geometry": {"coordinates":[-3.49164,50.725296],"type":"Point"}
}
