{
  "type": "Feature",
  "properties": {
    "iso:country": "GB",
    "wof:name": "EX1 3HT",
    "wof:placetype": "postalcode"
  },
  "geometry": {"coordinates":[-3.49164,50.725296],"type":"Point"}
}
