{
  "type": "Feature",
  "properties": {
    "iso:country":"GB",
    "wof:name":"NP4 5LY",
    "wof:placetype":"postalcode"
},
  "geometry": {"coordinates":[-3.02853625800154,51.68346944203157],"type":"Point"}
}