{
  "type": "Feature",
  "properties": {
    "iso:country":"GB",
    "wof:name":"G69 6PL",
    "wof:placetype":"postalcode"
},
  "geometry": {"coordinates":[-4.12066538150278,55.85539785755104],"type":"Point"}
}