{
  "type": "Feature",
  "properties": {
    "iso:country":"GB",
    "wof:name":"GL20 8QA",
    "wof:placetype":"postalcode"
},
  "geometry": {"coordinates":[-2.1139385789509,52.00196328845536],"type":"Point"}
}