{
  "type": "Feature",
  "properties": {
    "iso:country": "GB",
    "wof:name": "ME12 4BG",
    "wof:placetype": "postalcode"
  },
  "geometry": {"coordinates":[0.908554,51.366134],"type":"Point"}
}
