{
  "type": "Feature",
  "properties": {
    "iso:country":"GB",
    "wof:name":"UB1 1PA",
    "wof:placetype":"postalcode"
},
  "geometry": {"coordinates":[-0.38569665999747,51.51338133355257],"type":"Point"}
}