{
  "type": "Feature",
  "properties": {
    "iso:country":"GB",
    "wof:name":"ME13 9RT",
    "wof:placetype":"postalcode"
},
  "geometry": {"coordinates":[0.91823994077936,51.26195501382044],"type":"Point"}
}