{
  "type": "Feature",
  "properties": {
    "iso:country": "GB",
    "wof:name": "ME13 9RT",
    "wof:placetype": "postalcode"
  },
  "geometry": {"coordinates":[0.918271,51.261966],"type":"Point"}
}
