{
  "type": "Feature",
  "properties": {
    "iso:country": "GB",
    "wof:name": "WV5 8AB",
    "wof:placetype": "postalcode"
  },
  "geometry": {"coordinates":[-2.202319,52.536434],"type":"Point"}
}
