{
  "type": "Feature",
  "properties": {
    "iso:country": "GB",
    "wof:name": "B28 0NX",
    "wof:placetype": "postalcode"
  },
  "geometry": {"coordinates":[-1.843089,52.420983],"type":"Point"}
}
