{
  "type": "Feature",
  "properties": {
    "iso:country":"GB",
    "wof:name":"B28 0NX",
    "wof:placetype":"postalcode"
},
  "geometry": {"coordinates":[-1.84308899799406,52.42098296653701],"type":"Point"}
}