{
  "type": "Feature",
  "properties": {
    "iso:country":"GB",
    "wof:name":"AL1 5QU",
    "wof:placetype":"postalcode"
},
  "geometry": {"coordinates":[-0.31018655896598,51.74338037044197],"type":"Point"}
}