{
  "type": "Feature",
  "properties": {
    "iso:country":"GB",
    "wof:name":"B97 5NS",
    "wof:placetype":"postalcode"
},
  "geometry": {"coordinates":[-1.9486241147716,52.27978636687046],"type":"Point"}
}