{
  "type": "Feature",
  "properties": {
    "iso:country": "GB",
    "wof:name": "B97 5NS",
    "wof:placetype": "postalcode"
  },
  "geometry": {"coordinates":[-1.948624,52.279786],"type":"Point"}
}
