{
  "type": "Feature",
  "properties": {
    "iso:country":"GB",
    "wof:name":"AB12 4XP",
    "wof:placetype":"postalcode"
},
  "geometry": {"coordinates":[-2.13852388759993,57.06355376077359],"type":"Point"}
}