{
  "type": "Feature",
  "properties": {
    "iso:country": "GB",
    "wof:name": "CH62 4SS",
    "wof:placetype": "postalcode"
  },
  "geometry": {"coordinates":[-2.988366,53.351729],"type":"Point"}
}
