{
  "type": "Feature",
  "properties": {
    "iso:country":"GB",
    "wof:name":"ST6 1EB",
    "wof:placetype":"postalcode"
},
  "geometry": {"coordinates":[-2.18835581575118,53.04702478421476],"type":"Point"}
}