{
  "type": "Feature",
  "properties": {
    "date:inception_lower": "1980-01-01",
    "date:inception_upper": "1980-01-01",
    "iso:country": "GB",
    "wof:name": "SA6 5TP",
    "wof:placetype": "postalcode"
  },
  "geometry": {"coordinates":[-3.905659,51.717406],"type":"Point"}
}
