{
  "type": "Feature",
  "properties": {
    "iso:country": "GB",
    "wof:name": "SA6 5TP",
    "wof:placetype": "postalcode"
  },
  "geometry": {"coordinates":[-3.905659,51.717406],"type":"Point"}
}
