{
  "type": "Feature",
  "properties": {
    "date:inception_lower": "1980-01-01",
    "date:inception_upper": "1980-01-01",
    "iso:country": "GB",
    "wof:name": "BL6 6PX",
    "wof:placetype": "postalcode"
  },
  "geometry": {"coordinates":[-2.509003,53.595425],"type":"Point"}
}
