{
  "type": "Feature",
  "properties": {
    "iso:country":"GB",
    "wof:name":"BL6 6PX",
    "wof:placetype":"postalcode"
},
  "geometry": {"coordinates":[-2.50900342786761,53.59542456411815],"type":"Point"}
}