{
  "type": "Feature",
  "properties": {
    "iso:country": "GB",
    "wof:name": "BL6 6PX",
    "wof:placetype": "postalcode"
  },
  "geometry": {"coordinates":[-2.509003,53.595425],"type":"Point"}
}
