{
  "type": "Feature",
  "properties": {
    "iso:country":"GB",
    "wof:name":"ST5 2QF",
    "wof:placetype":"postalcode"
},
  "geometry": {"coordinates":[-2.24692372136788,53.00099194538251],"type":"Point"}
}