{
  "type": "Feature",
  "properties": {
    "iso:country": "GB",
    "wof:name": "DT9 3DE",
    "wof:placetype": "postalcode"
  },
  "geometry": {"coordinates":[-2.508841,50.948816],"type":"Point"}
}
