{
  "type": "Feature",
  "properties": {
    "date:inception_lower": "2001-06-01",
    "date:inception_upper": "2001-06-01",
    "iso:country": "GB",
    "wof:name": "RH10 8DD",
    "wof:placetype": "postalcode"
  },
  "geometry": {"coordinates":[-0.180301,51.119856],"type":"Point"}
}
