{
  "type": "Feature",
  "properties": {
    "iso:country":"GB",
    "wof:name":"RH10 8DD",
    "wof:placetype":"postalcode"
},
  "geometry": {"coordinates":[-0.18030078284302,51.11985607792307],"type":"Point"}
}