{
  "type": "Feature",
  "properties": {
    "iso:country": "GB",
    "wof:name": "RH10 8DD",
    "wof:placetype": "postalcode"
  },
  "geometry": {"coordinates":[-0.180301,51.119856],"type":"Point"}
}
