{
  "type": "Feature",
  "properties": {
    "date:inception_lower": "1980-01-01",
    "date:inception_upper": "1980-01-01",
    "iso:country": "GB",
    "wof:name": "BB8 9TB",
    "wof:placetype": "postalcode"
  },
  "geometry": {"coordinates":[-2.186282,53.864684],"type":"Point"}
}
