{
  "type": "Feature",
  "properties": {
    "date:inception_lower":"1995-07-01",
    "date:inception_upper":"1995-07-31",
    "iso:country":"GB",
    "wof:name":"RG26 3BB",
    "wof:placetype":"postalcode"
},
  "geometry": {"coordinates":[-1.144832,51.348468],"type":"Point"}
}