{
  "type": "Feature",
  "properties": {
    "iso:country":"GB",
    "wof:name":"RG26 3BB",
    "wof:placetype":"postalcode"
},
  "geometry": {"coordinates":[-1.14483238053549,51.34846765467054],"type":"Point"}
}