{
  "type": "Feature",
  "properties": {
    "iso:country":"GB",
    "wof:name":"S43 4JG",
    "wof:placetype":"postalcode"
},
  "geometry": {"coordinates":[-1.26775311335488,53.27585315821955],"type":"Point"}
}