{
  "type": "Feature",
  "properties": {
    "date:inception_lower":"1980-01-01",
    "date:inception_upper":"1980-01-31",
    "iso:country":"GB",
    "wof:name":"S43 4JG",
    "wof:placetype":"postalcode"
},
  "geometry": {"coordinates":[-1.267737,53.275866],"type":"Point"}
}