{
  "type": "Feature",
  "properties": {
    "iso:country":"GB",
    "wof:name":"YO25 8DH",
    "wof:placetype":"postalcode"
},
  "geometry": {"coordinates":[-0.19270277740853,53.94032310775853],"type":"Point"}
}