{
  "type": "Feature",
  "properties": {
    "iso:country": "GB",
    "wof:name": "YO25 8DH",
    "wof:placetype": "postalcode"
  },
  "geometry": {"coordinates":[-0.192712,53.940344],"type":"Point"}
}
