{
  "type": "Feature",
  "properties": {
    "date:inception_lower": "1985-10-01",
    "date:inception_upper": "1985-10-01",
    "iso:country": "GB",
    "wof:name": "TA8 2TY",
    "wof:placetype": "postalcode"
  },
  "geometry": {"coordinates":[-2.983441,51.241463],"type":"Point"}
}
