{
  "type": "Feature",
  "properties": {
    "iso:country": "GB",
    "wof:name": "GL4 3HW",
    "wof:placetype": "postalcode"
  },
  "geometry": {"coordinates":[-2.201182,51.860571],"type":"Point"}
}
