{
  "type": "Feature",
  "properties": {
    "iso:country":"GB",
    "wof:name":"CR0 1RW",
    "wof:placetype":"postalcode"
},
  "geometry": {"coordinates":[-0.10751055830983,51.37085289614935],"type":"Point"}
}