{
  "type": "Feature",
  "properties": {
    "iso:country":"GB",
    "wof:name":"W1H 5JN",
    "wof:placetype":"postalcode"
},
  "geometry": {"coordinates":[-0.16348967221689,51.51781020610927],"type":"Point"}
}