{
  "type": "Feature",
  "properties": {
    "iso:country":"GB",
    "wof:name":"DN32 8DS",
    "wof:placetype":"postalcode"
},
  "geometry": {"coordinates":[-0.06091054783567,53.563986777211],"type":"Point"}
}