{
  "type": "Feature",
  "properties": {
    "iso:country": "GB",
    "wof:name": "DN32 8DS",
    "wof:placetype": "postalcode"
  },
  "geometry": {"coordinates":[-0.060911,53.563987],"type":"Point"}
}
