{
  "type": "Feature",
  "properties": {
    "date:inception_lower":"1997-06-01",
    "date:inception_upper":"1997-06-30",
    "iso:country":"GB",
    "wof:name":"TD9 0ET",
    "wof:placetype":"postalcode"
},
  "geometry": {"coordinates":[-2.789494,55.418055],"type":"Point"}
}