{
  "type": "Feature",
  "properties": {
    "iso:country":"GB",
    "wof:name":"TD9 0ET",
    "wof:placetype":"postalcode"
},
  "geometry": {"coordinates":[-2.78949385447888,55.41805515877324],"type":"Point"}
}