{
  "type": "Feature",
  "properties": {
    "iso:country":"GB",
    "wof:name":"EX5 3LE",
    "wof:placetype":"postalcode"
},
  "geometry": {"coordinates":[-3.45359012012661,50.79138203472868],"type":"Point"}
}