{
  "type": "Feature",
  "properties": {
    "iso:country":"GB",
    "wof:name":"IG6 2HY",
    "wof:placetype":"postalcode"
},
  "geometry": {"coordinates":[0.08017804986443,51.59726598558294],"type":"Point"}
}