{
  "type": "Feature",
  "properties": {
    "date:inception_lower": "1980-01-01",
    "date:inception_upper": "1980-01-01",
    "iso:country": "GB",
    "wof:name": "WF13 2DN",
    "wof:placetype": "postalcode"
  },
  "geometry": {"coordinates":[-1.635641,53.7007],"type":"Point"}
}
