{
  "type": "Feature",
  "properties": {
    "date:inception_lower":"1998-06-01",
    "date:inception_upper":"1998-06-30",
    "iso:country":"GB",
    "wof:name":"YO31 1AT",
    "wof:placetype":"postalcode"
},
  "geometry": {"coordinates":[-1.053677,53.968122],"type":"Point"}
}