{
  "type": "Feature",
  "properties": {
    "iso:country":"GB",
    "wof:name":"YO31 1AT",
    "wof:placetype":"postalcode"
},
  "geometry": {"coordinates":[-1.0536775158252,53.96812184538318],"type":"Point"}
}