{
  "type": "Feature",
  "properties": {
    "date:inception_lower": "1980-01-01",
    "date:inception_upper": "1980-01-01",
    "iso:country": "GB",
    "wof:name": "YO18 8JA",
    "wof:placetype": "postalcode"
  },
  "geometry": {"coordinates":[-0.775523,54.31544],"type":"Point"}
}
