{
  "type": "Feature",
  "properties": {
    "iso:country":"GB",
    "wof:name":"YO18 8JA",
    "wof:placetype":"postalcode"
},
  "geometry": {"coordinates":[-0.77614266786166,54.31481191689796],"type":"Point"}
}