{
  "type": "Feature",
  "properties": {
    "iso:country":"GB",
    "wof:name":"LS12 5HB",
    "wof:placetype":"postalcode"
},
  "geometry": {"coordinates":[-1.63338246396967,53.78586748938609],"type":"Point"}
}