{
  "type": "Feature",
  "properties": {
    "date:inception_lower":"1980-01-01",
    "date:inception_upper":"1980-01-31",
    "iso:country":"GB",
    "wof:name":"LS12 5HB",
    "wof:placetype":"postalcode"
},
  "geometry": {"coordinates":[-1.633382,53.785867],"type":"Point"}
}