{
  "type": "Feature",
  "properties": {
    "iso:country":"GB",
    "wof:name":"DG13 0LJ",
    "wof:placetype":"postalcode"
},
  "geometry": {"coordinates":[-2.97202787619358,55.1298021711355],"type":"Point"}
}