{
  "type": "Feature",
  "properties": {
    "iso:country": "GB",
    "wof:name": "PO22 0HH",
    "wof:placetype": "postalcode"
  },
  "geometry": {"coordinates":[-0.642135,50.835124],"type":"Point"}
}
