{
  "type": "Feature",
  "properties": {
    "iso:country":"GB",
    "wof:name":"PO22 0HH",
    "wof:placetype":"postalcode"
},
  "geometry": {"coordinates":[-0.64215585511619,50.83513337677152],"type":"Point"}
}