{
  "type": "Feature",
  "properties": {
    "date:inception_lower": "2007-02-01",
    "date:inception_upper": "2007-02-01",
    "iso:country": "GB",
    "wof:name": "E3 2GP",
    "wof:placetype": "postalcode"
  },
  "geometry": {"coordinates":[-0.026279,51.53166],"type":"Point"}
}
