{
  "type": "Feature",
  "properties": {
    "iso:country":"GB",
    "wof:name":"E3 2GP",
    "wof:placetype":"postalcode"
},
  "geometry": {"coordinates":[-0.02627908655792,51.53166032861505],"type":"Point"}
}