{
  "type": "Feature",
  "properties": {
    "iso:country":"GB",
    "wof:name":"DA7 6PS",
    "wof:placetype":"postalcode"
},
  "geometry": {"coordinates":[0.16004683955897,51.46764793304101],"type":"Point"}
}