{
  "type": "Feature",
  "properties": {
    "iso:country": "GB",
    "wof:name": "PO18 8EB",
    "wof:placetype": "postalcode"
  },
  "geometry": {"coordinates":[-0.858572,50.859393],"type":"Point"}
}
