{
  "type": "Feature",
  "properties": {
    "iso:country":"GB",
    "wof:name":"L31 5LD",
    "wof:placetype":"postalcode"
},
  "geometry": {"coordinates":[-2.94334773387012,53.50014122484152],"type":"Point"}
}