{
  "type": "Feature",
  "properties": {
    "iso:country": "GB",
    "wof:name": "LL11 2NX",
    "wof:placetype": "postalcode"
  },
  "geometry": {"coordinates":[-2.999278,53.052064],"type":"Point"}
}
