{
  "type": "Feature",
  "properties": {
    "iso:country":"GB",
    "wof:name":"LL11 2NX",
    "wof:placetype":"postalcode"
},
  "geometry": {"coordinates":[-2.99927799474803,53.05206370260581],"type":"Point"}
}