{
  "type": "Feature",
  "properties": {
    "iso:country": "GB",
    "wof:name": "YO8 4DG",
    "wof:placetype": "postalcode"
  },
  "geometry": {"coordinates":[-1.082811,53.786589],"type":"Point"}
}
