{
  "type": "Feature",
  "properties": {
    "iso:country":"GB",
    "wof:name":"YO8 4DG",
    "wof:placetype":"postalcode"
},
  "geometry": {"coordinates":[-1.08281067751216,53.78658861779682],"type":"Point"}
}