{
  "type": "Feature",
  "properties": {
    "iso:country": "GB",
    "wof:name": "SW14 8LE",
    "wof:placetype": "postalcode"
  },
  "geometry": {"coordinates":[-0.268189,51.461537],"type":"Point"}
}
