{
  "type": "Feature",
  "properties": {
    "date:inception_lower":"1980-01-01",
    "date:inception_upper":"1980-01-31",
    "iso:country":"GB",
    "wof:name":"SW14 8LE",
    "wof:placetype":"postalcode"
},
  "geometry": {"coordinates":[-0.268189,51.461537],"type":"Point"}
}