{
  "type": "Feature",
  "properties": {
    "iso:country":"GB",
    "wof:name":"SW14 8LE",
    "wof:placetype":"postalcode"
},
  "geometry": {"coordinates":[-0.26818863383502,51.46153665825781],"type":"Point"}
}