{
  "type": "Feature",
  "properties": {
    "iso:country":"GB",
    "wof:name":"RH15 8SH",
    "wof:placetype":"postalcode"
},
  "geometry": {"coordinates":[-0.13733339191769,50.96513560012999],"type":"Point"}
}