{
  "type": "Feature",
  "properties": {
    "date:inception_lower": "1983-03-01",
    "date:inception_upper": "1983-03-01",
    "iso:country": "GB",
    "wof:name": "RH15 8SH",
    "wof:placetype": "postalcode"
  },
  "geometry": {"coordinates":[-0.137333,50.965136],"type":"Point"}
}
