{
  "type": "Feature",
  "properties": {
    "date:inception_lower":"2003-02-01",
    "date:inception_upper":"2003-02-28",
    "iso:country":"GB",
    "wof:name":"E9 6RE",
    "wof:placetype":"postalcode"
},
  "geometry": {"coordinates":[-0.047023,51.544543],"type":"Point"}
}