{
  "type": "Feature",
  "properties": {
    "iso:country":"GB",
    "wof:name":"E9 6RE",
    "wof:placetype":"postalcode"
},
  "geometry": {"coordinates":[-0.047023119241,51.54454319643317],"type":"Point"}
}