{
  "type": "Feature",
  "properties": {
    "date:inception_lower":"1980-01-01",
    "date:inception_upper":"1980-01-31",
    "iso:country":"GB",
    "wof:name":"NE30 1AG",
    "wof:placetype":"postalcode"
},
  "geometry": {"coordinates":[-1.443301,55.011429],"type":"Point"}
}