{
  "type": "Feature",
  "properties": {
    "iso:country":"GB",
    "wof:name":"N18 1HP",
    "wof:placetype":"postalcode"
},
  "geometry": {"coordinates":[-0.068580021159,51.61306323650781],"type":"Point"}
}