{
  "type": "Feature",
  "properties": {
    "iso:country":"GB",
    "wof:name":"PE31 6HN",
    "wof:placetype":"postalcode"
},
  "geometry": {"coordinates":[0.50088826856165,52.84570025783257],"type":"Point"}
}