{
  "type": "Feature",
  "properties": {
    "date:inception_lower": "1980-01-01",
    "date:inception_upper": "1980-01-01",
    "iso:country": "GB",
    "wof:name": "PE31 6HN",
    "wof:placetype": "postalcode"
  },
  "geometry": {"coordinates":[0.500841,52.845689],"type":"Point"}
}
