{
  "type": "Feature",
  "properties": {
    "iso:country": "GB",
    "wof:name": "BN2 7GP",
    "wof:placetype": "postalcode"
  },
  "geometry": {"coordinates":[-0.049368,50.803301],"type":"Point"}
}
