{
  "type": "Feature",
  "properties": {
    "iso:country":"GB",
    "wof:name":"OL9 9UT",
    "wof:placetype":"postalcode"
},
  "geometry": {"coordinates":[-2.16842947274436,53.54264820035425],"type":"Point"}
}