{
  "type": "Feature",
  "properties": {
    "iso:country":"GB",
    "wof:name":"ML10 6HB",
    "wof:placetype":"postalcode"
},
  "geometry": {"coordinates":[-4.07588659049487,55.67560914696615],"type":"Point"}
}