{
  "type": "Feature",
  "properties": {
    "iso:country": "GB",
    "wof:name": "TQ9 6RB",
    "wof:placetype": "postalcode"
  },
  "geometry": {"coordinates":[-3.622356,50.402867],"type":"Point"}
}
