{
  "type": "Feature",
  "properties": {
    "iso:country":"GB",
    "wof:name":"BD22 0JB",
    "wof:placetype":"postalcode"
},
  "geometry": {"coordinates":[-1.98031473127226,53.83752193677422],"type":"Point"}
}