{
  "type": "Feature",
  "properties": {
    "date:inception_lower":"1980-01-01",
    "date:inception_upper":"1980-01-31",
    "iso:country":"GB",
    "wof:name":"TA8 2HL",
    "wof:placetype":"postalcode"
},
  "geometry": {"coordinates":[-3.00022,51.248245],"type":"Point"}
}