{
  "type": "Feature",
  "properties": {
    "iso:country":"GB",
    "wof:name":"TA8 2HL",
    "wof:placetype":"postalcode"
},
  "geometry": {"coordinates":[-3.00031209325633,51.24826628477075],"type":"Point"}
}