{
  "type": "Feature",
  "properties": {
    "iso:country":"GB",
    "wof:name":"SP1 3NE",
    "wof:placetype":"postalcode"
},
  "geometry": {"coordinates":[-1.79661771317027,51.0785960650411],"type":"Point"}
}