{
  "type": "Feature",
  "properties": {
    "iso:country":"GB",
    "wof:name":"LA2 7AZ",
    "wof:placetype":"postalcode"
},
  "geometry": {"coordinates":[-2.49811636295631,54.10401032550507],"type":"Point"}
}