{
  "type": "Feature",
  "properties": {
    "date:inception_lower":"1980-01-01",
    "date:inception_upper":"1980-01-31",
    "iso:country":"GB",
    "wof:name":"LA2 7AZ",
    "wof:placetype":"postalcode"
},
  "geometry": {"coordinates":[-2.498119,54.104022],"type":"Point"}
}