{
  "type": "Feature",
  "properties": {
    "iso:country":"GB",
    "wof:name":"B8 3RZ",
    "wof:placetype":"postalcode"
},
  "geometry": {"coordinates":[-1.82848584510693,52.48589755326525],"type":"Point"}
}