{
  "type": "Feature",
  "properties": {
    "iso:country": "GB",
    "wof:name": "RG42 4JQ",
    "wof:placetype": "postalcode"
  },
  "geometry": {"coordinates":[-0.78958,51.418416],"type":"Point"}
}
