{
  "type": "Feature",
  "properties": {
    "iso:country": "GB",
    "wof:name": "RG42 4JQ",
    "wof:placetype": "postalcode"
  },
  "geometry": {"coordinates":[-0.789522,51.418451],"type":"Point"}
}
