{
  "type": "Feature",
  "properties": {
    "date:inception_lower": "2019-12-01",
    "date:inception_upper": "2019-12-01",
    "iso:country": "GB",
    "wof:name": "RG42 4JQ",
    "wof:placetype": "postalcode"
  },
  "geometry": {"coordinates":[-0.789566,51.417876],"type":"Point"}
}
