{
  "type": "Feature",
  "properties": {
    "date:inception_lower": "2012-08-01",
    "date:inception_upper": "2012-08-01",
    "iso:country": "GB",
    "wof:name": "DH3 3EB",
    "wof:placetype": "postalcode"
  },
  "geometry": {"coordinates":[-1.575699,54.858638],"type":"Point"}
}
