{
  "type": "Feature",
  "properties": {
    "iso:country":"GB",
    "wof:name":"DH3 3EB",
    "wof:placetype":"postalcode"
},
  "geometry": {"coordinates":[-1.57569873852281,54.85863770241915],"type":"Point"}
}