{
  "type": "Feature",
  "properties": {
    "iso:country": "GB",
    "wof:name": "DH3 3EB",
    "wof:placetype": "postalcode"
  },
  "geometry": {"coordinates":[-1.575699,54.858638],"type":"Point"}
}
