{
  "type": "Feature",
  "properties": {
    "iso:country":"GB",
    "wof:name":"SM4 6PN",
    "wof:placetype":"postalcode"
},
  "geometry": {"coordinates":[-0.19430192694806,51.38913789484477],"type":"Point"}
}