{
  "type": "Feature",
  "properties": {
    "iso:country": "GB",
    "wof:name": "DD4 8TR",
    "wof:placetype": "postalcode"
  },
  "geometry": {"coordinates":[-2.897327,56.479178],"type":"Point"}
}
