{
  "type": "Feature",
  "properties": {
    "date:inception_lower":"1980-01-01",
    "date:inception_upper":"1980-01-31",
    "iso:country":"GB",
    "wof:name":"DD4 8TR",
    "wof:placetype":"postalcode"
},
  "geometry": {"coordinates":[-2.897327,56.479178],"type":"Point"}
}