{
  "type": "Feature",
  "properties": {
    "date:inception_lower": "2006-09-01",
    "date:inception_upper": "2006-09-01",
    "iso:country": "GB",
    "wof:name": "CB21 4QD",
    "wof:placetype": "postalcode"
  },
  "geometry": {"coordinates":[0.352986,52.101132],"type":"Point"}
}
