{
  "type": "Feature",
  "properties": {
    "iso:country":"GB",
    "wof:name":"CB21 4QD",
    "wof:placetype":"postalcode"
},
  "geometry": {"coordinates":[0.35295539122458,52.1011194127079],"type":"Point"}
}