{
  "type": "Feature",
  "properties": {
    "date:inception_lower": "1980-01-01",
    "date:inception_upper": "1980-01-01",
    "iso:country": "GB",
    "wof:name": "E1 0DE",
    "wof:placetype": "postalcode"
  },
  "geometry": {"coordinates":[-0.057611,51.51097],"type":"Point"}
}
