{
  "type": "Feature",
  "properties": {
    "iso:country":"GB",
    "wof:name":"E1 0DE",
    "wof:placetype":"postalcode"
},
  "geometry": {"coordinates":[-0.05761059892615,51.51096980653722],"type":"Point"}
}