{
  "type": "Feature",
  "properties": {
    "iso:country": "GB",
    "wof:name": "TA21 8QH",
    "wof:placetype": "postalcode"
  },
  "geometry": {"coordinates":[-3.232962,50.976424],"type":"Point"}
}
