{
  "type": "Feature",
  "properties": {
    "date:inception_lower":"1999-12-01",
    "date:inception_upper":"1999-12-31",
    "iso:country":"GB",
    "wof:name":"TA21 8QH",
    "wof:placetype":"postalcode"
},
  "geometry": {"coordinates":[-3.232962,50.976424],"type":"Point"}
}