{
  "type": "Feature",
  "properties": {
    "iso:country":"GB",
    "wof:name":"CF47 9NU",
    "wof:placetype":"postalcode"
},
  "geometry": {"coordinates":[-3.38226047903095,51.75974814657457],"type":"Point"}
}