{
  "type": "Feature",
  "properties": {
    "iso:country":"GB",
    "wof:name":"ST6 8PH",
    "wof:placetype":"postalcode"
},
  "geometry": {"coordinates":[-2.14910903571848,53.06825881543182],"type":"Point"}
}