{
  "type": "Feature",
  "properties": {
    "iso:country":"GB",
    "wof:name":"WS10 0QP",
    "wof:placetype":"postalcode"
},
  "geometry": {"coordinates":[-2.00333391581554,52.55208818546333],"type":"Point"}
}