{
  "type": "Feature",
  "properties": {
    "date:inception_lower": "2007-07-01",
    "date:inception_upper": "2007-07-01",
    "iso:country": "GB",
    "wof:name": "CF48 1BQ",
    "wof:placetype": "postalcode"
  },
  "geometry": {"coordinates":[-3.412227,51.744951],"type":"Point"}
}
