{
  "type": "Feature",
  "properties": {
    "iso:country":"GB",
    "wof:name":"G34 9QR",
    "wof:placetype":"postalcode"
},
  "geometry": {"coordinates":[-4.12392771673395,55.87125783568155],"type":"Point"}
}