{
  "type": "Feature",
  "properties": {
    "date:inception_lower": "2013-07-01",
    "date:inception_upper": "2013-07-01",
    "iso:country": "GB",
    "wof:name": "G34 9QR",
    "wof:placetype": "postalcode"
  },
  "geometry": {"coordinates":[-4.123928,55.871258],"type":"Point"}
}
