{
  "type": "Feature",
  "properties": {
    "date:inception_lower":"1980-01-01",
    "date:inception_upper":"1980-01-31",
    "iso:country":"GB",
    "wof:name":"SW18 4HY",
    "wof:placetype":"postalcode"
},
  "geometry": {"coordinates":[-0.194709,51.457021],"type":"Point"}
}