{
  "type": "Feature",
  "properties": {
    "date:inception_lower": "2009-05-01",
    "date:inception_upper": "2009-05-01",
    "iso:country": "GB",
    "wof:name": "AB10 6TG",
    "wof:placetype": "postalcode"
  },
  "geometry": {"coordinates":[-2.119943,57.138683],"type":"Point"}
}
