{
  "type": "Feature",
  "properties": {
    "iso:country":"GB",
    "wof:name":"B65 8DZ",
    "wof:placetype":"postalcode"
},
  "geometry": {"coordinates":[-2.04683764683415,52.47990792518621],"type":"Point"}
}