{
  "type": "Feature",
  "properties": {
    "iso:country":"GB",
    "wof:name":"CM3 6NR",
    "wof:placetype":"postalcode"
},
  "geometry": {"coordinates":[0.68556860469438,51.66849415909488],"type":"Point"}
}