{
  "type": "Feature",
  "properties": {
    "iso:country": "GB",
    "wof:name": "CM3 6NR",
    "wof:placetype": "postalcode"
  },
  "geometry": {"coordinates":[0.686502,51.668389],"type":"Point"}
}
