{
  "type": "Feature",
  "properties": {
    "date:inception_lower":"1980-01-01",
    "date:inception_upper":"1980-01-31",
    "iso:country":"GB",
    "wof:name":"CM3 6NR",
    "wof:placetype":"postalcode"
},
  "geometry": {"coordinates":[0.686502,51.668389],"type":"Point"}
}