{
  "type": "Feature",
  "properties": {
    "iso:country":"GB",
    "wof:name":"SW17 7NG",
    "wof:placetype":"postalcode"
},
  "geometry": {"coordinates":[-0.16709325225092,51.43553998823835],"type":"Point"}
}