{
  "type": "Feature",
  "properties": {
    "iso:country":"GB",
    "wof:name":"GL52 6YQ",
    "wof:placetype":"postalcode"
},
  "geometry": {"coordinates":[-2.04310627648565,51.88724336147052],"type":"Point"}
}