{
  "type": "Feature",
  "properties": {
    "iso:country": "GB",
    "wof:name": "GL52 6YQ",
    "wof:placetype": "postalcode"
  },
  "geometry": {"coordinates":[-2.043106,51.887243],"type":"Point"}
}
