{
  "type": "Feature",
  "properties": {
    "iso:country":"GB",
    "wof:name":"WS13 8QY",
    "wof:placetype":"postalcode"
},
  "geometry": {"coordinates":[-1.70648235813106,52.70887504060316],"type":"Point"}
}