{
  "type": "Feature",
  "properties": {
    "date:inception_lower": "1980-01-01",
    "date:inception_upper": "1980-01-01",
    "iso:country": "GB",
    "wof:name": "WS13 8QY",
    "wof:placetype": "postalcode"
  },
  "geometry": {"coordinates":[-1.705665,52.71272],"type":"Point"}
}
