{
  "type": "Feature",
  "properties": {
    "date:inception_lower": "2023-08-01",
    "date:inception_upper": "2023-08-01",
    "iso:country": "GB",
    "wof:name": "CM1 7FU",
    "wof:placetype": "postalcode"
  },
  "geometry": {"coordinates":[0.48423,51.738557],"type":"Point"}
}
