{
  "type": "Feature",
  "properties": {
    "date:inception_lower": "1980-01-01",
    "date:inception_upper": "1980-01-01",
    "iso:country": "GB",
    "wof:name": "NE46 4HU",
    "wof:placetype": "postalcode"
  },
  "geometry": {"coordinates":[-2.06905,55.050213],"type":"Point"}
}
