{
  "type": "Feature",
  "properties": {
    "date:inception_lower": "2000-10-01",
    "date:inception_upper": "2000-10-01",
    "iso:country": "GB",
    "wof:name": "W1W 5BG",
    "wof:placetype": "postalcode"
  },
  "geometry": {"coordinates":[-0.142302,51.522764],"type":"Point"}
}
