{
  "type": "Feature",
  "properties": {
    "iso:country":"GB",
    "wof:name":"W1W 5BG",
    "wof:placetype":"postalcode"
},
  "geometry": {"coordinates":[-0.14230210322289,51.52276413704718],"type":"Point"}
}