{
  "type": "Feature",
  "properties": {
    "date:inception_lower":"2014-05-01",
    "date:inception_upper":"2014-05-31",
    "iso:country":"GB",
    "wof:name":"W6 0LF",
    "wof:placetype":"postalcode"
},
  "geometry": {"coordinates":[-0.24462,51.496131],"type":"Point"}
}