{
  "type": "Feature",
  "properties": {
    "iso:country":"GB",
    "wof:name":"W6 0LF",
    "wof:placetype":"postalcode"
},
  "geometry": {"coordinates":[-0.24461989235889,51.49613077655181],"type":"Point"}
}