{
  "type": "Feature",
  "properties": {
    "iso:country":"GB",
    "wof:name":"TF7 4PZ",
    "wof:placetype":"postalcode"
},
  "geometry": {"coordinates":[-2.44063345992306,52.62700688010924],"type":"Point"}
}