{
  "type": "Feature",
  "properties": {
    "date:inception_lower": "1980-01-01",
    "date:inception_upper": "1980-01-01",
    "iso:country": "GB",
    "wof:name": "TF7 4PZ",
    "wof:placetype": "postalcode"
  },
  "geometry": {"coordinates":[-2.440633,52.627007],"type":"Point"}
}
