{
  "type": "Feature",
  "properties": {
    "iso:country":"GB",
    "wof:name":"SO31 5GL",
    "wof:placetype":"postalcode"
},
  "geometry": {"coordinates":[-1.34376720753841,50.87979198335025],"type":"Point"}
}