{
  "type": "Feature",
  "properties": {
    "date:inception_lower":"1980-01-01",
    "date:inception_upper":"1980-01-31",
    "iso:country":"GB",
    "wof:name":"L25 2UF",
    "wof:placetype":"postalcode"
},
  "geometry": {"coordinates":[-2.857159,53.390921],"type":"Point"}
}