{
  "type": "Feature",
  "properties": {
    "iso:country": "GB",
    "wof:name": "CA10 3BG",
    "wof:placetype": "postalcode"
  },
  "geometry": {"coordinates":[-2.620149,54.59565],"type":"Point"}
}
