{
  "type": "Feature",
  "properties": {
    "iso:country":"GB",
    "wof:name":"CA10 3BG",
    "wof:placetype":"postalcode"
},
  "geometry": {"coordinates":[-2.62014904220461,54.59565024493572],"type":"Point"}
}