{
  "type": "Feature",
  "properties": {
    "date:inception_lower":"2006-10-01",
    "date:inception_upper":"2006-10-31",
    "iso:country":"GB",
    "wof:name":"CA10 3BG",
    "wof:placetype":"postalcode"
},
  "geometry": {"coordinates":[-2.620149,54.59565],"type":"Point"}
}