{
  "type": "Feature",
  "properties": {
    "iso:country":"GB",
    "wof:name":"SE16 7EY",
    "wof:placetype":"postalcode"
},
  "geometry": {"coordinates":[-0.03899532250564,51.49307941205747],"type":"Point"}
}