{
  "type": "Feature",
  "properties": {
    "iso:country":"GB",
    "wof:name":"EH6 4PS",
    "wof:placetype":"postalcode"
},
  "geometry": {"coordinates":[-3.18871165629315,55.9765395801121],"type":"Point"}
}