{
  "type": "Feature",
  "properties": {
    "iso:country": "GB",
    "wof:name": "EH6 4PS",
    "wof:placetype": "postalcode"
  },
  "geometry": {"coordinates":[-3.188712,55.97654],"type":"Point"}
}
