{
  "type": "Feature",
  "properties": {
    "iso:country": "GB",
    "wof:name": "DL8 5NP",
    "wof:placetype": "postalcode"
  },
  "geometry": {"coordinates":[-1.720819,54.301444],"type":"Point"}
}
