{
  "type": "Feature",
  "properties": {
    "iso:country":"GB",
    "wof:name":"DL8 5NP",
    "wof:placetype":"postalcode"
},
  "geometry": {"coordinates":[-1.72081915543215,54.30144375565944],"type":"Point"}
}