{
  "type": "Feature",
  "properties": {
    "iso:country": "GB",
    "wof:name": "EX15 1DU",
    "wof:placetype": "postalcode"
  },
  "geometry": {"coordinates":[-3.393921,50.852149],"type":"Point"}
}
