{
  "type": "Feature",
  "properties": {
    "iso:country":"GB",
    "wof:name":"PE27 3FF",
    "wof:placetype":"postalcode"
},
  "geometry": {"coordinates":[-0.06339129952346,52.33804490725371],"type":"Point"}
}