{
  "type": "Feature",
  "properties": {
    "iso:country": "GB",
    "wof:name": "PE27 3FF",
    "wof:placetype": "postalcode"
  },
  "geometry": {"coordinates":[-0.063391,52.338045],"type":"Point"}
}
