{
  "type": "Feature",
  "properties": {
    "iso:country":"GB",
    "wof:name":"IV18 0HS",
    "wof:placetype":"postalcode"
},
  "geometry": {"coordinates":[-4.15564605521186,57.69521283336427],"type":"Point"}
}