{
  "type": "Feature",
  "properties": {
    "iso:country": "GB",
    "wof:name": "YO17 9BL",
    "wof:placetype": "postalcode"
  },
  "geometry": {"coordinates":[-0.780469,54.128248],"type":"Point"}
}
