{
  "type": "Feature",
  "properties": {
    "date:inception_lower": "2024-02-01",
    "date:inception_upper": "2024-02-01",
    "iso:country": "GB",
    "wof:name": "NR9 5GF",
    "wof:placetype": "postalcode"
  },
  "geometry": {"coordinates":[1.165846,52.653784],"type":"Point"}
}
