{
  "type": "Feature",
  "properties": {
    "iso:country":"GB",
    "wof:name":"EX4 1BT",
    "wof:placetype":"postalcode"
},
  "geometry": {"coordinates":[-3.54365946362882,50.71864711919263],"type":"Point"}
}