{
  "type": "Feature",
  "properties": {
    "iso:country": "GB",
    "wof:name": "EX4 1BT",
    "wof:placetype": "postalcode"
  },
  "geometry": {"coordinates":[-3.543659,50.718647],"type":"Point"}
}
