{
  "type": "Feature",
  "properties": {
    "date:inception_lower": "1992-08-01",
    "date:inception_upper": "1992-08-01",
    "iso:country": "GB",
    "wof:name": "OX33 1QS",
    "wof:placetype": "postalcode"
  },
  "geometry": {"coordinates":[-1.155073,51.756092],"type":"Point"}
}
