{
  "type": "Feature",
  "properties": {
    "iso:country": "GB",
    "wof:name": "OX33 1QS",
    "wof:placetype": "postalcode"
  },
  "geometry": {"coordinates":[-1.155073,51.756092],"type":"Point"}
}
