{
  "type": "Feature",
  "properties": {
    "iso:country": "GB",
    "wof:name": "SW20 9NH",
    "wof:placetype": "postalcode"
  },
  "geometry": {"coordinates":[-0.22489,51.393166],"type":"Point"}
}
