{
  "type": "Feature",
  "properties": {
    "iso:country": "GB",
    "wof:name": "CO4 6BH",
    "wof:placetype": "postalcode"
  },
  "geometry": {"coordinates":[0.894796,51.918585],"type":"Point"}
}
