{
  "type": "Feature",
  "properties": {
    "iso:country":"GB",
    "wof:name":"NE19 2PQ",
    "wof:placetype":"postalcode"
},
  "geometry": {"coordinates":[-2.01661119517734,55.13260095597919],"type":"Point"}
}