{
  "type": "Feature",
  "properties": {
    "iso:country": "GB",
    "wof:name": "SY5 0NH",
    "wof:placetype": "postalcode"
  },
  "geometry": {"coordinates":[-2.958735,52.574392],"type":"Point"}
}
