{
  "type": "Feature",
  "properties": {
    "iso:country":"GB",
    "wof:name":"SY5 0NH",
    "wof:placetype":"postalcode"
},
  "geometry": {"coordinates":[-2.9587345487814,52.57439247044246],"type":"Point"}
}