{
  "type": "Feature",
  "properties": {
    "iso:country": "GB",
    "wof:name": "G64 2PA",
    "wof:placetype": "postalcode"
  },
  "geometry": {"coordinates":[-4.231827,55.89693],"type":"Point"}
}
