{
  "type": "Feature",
  "properties": {
    "date:inception_lower": "1992-05-01",
    "date:inception_upper": "1992-05-01",
    "iso:country": "GB",
    "wof:name": "G64 2PA",
    "wof:placetype": "postalcode"
  },
  "geometry": {"coordinates":[-4.231827,55.89693],"type":"Point"}
}
