{
  "type": "Feature",
  "properties": {
    "iso:country":"GB",
    "wof:name":"G64 2PA",
    "wof:placetype":"postalcode"
},
  "geometry": {"coordinates":[-4.2318267761886,55.89693008210838],"type":"Point"}
}