{
  "type": "Feature",
  "properties": {
    "iso:country": "GB",
    "wof:name": "DH4 6BD",
    "wof:placetype": "postalcode"
  },
  "geometry": {"coordinates":[-1.517451,54.847106],"type":"Point"}
}
