{
  "type": "Feature",
  "properties": {
    "iso:country":"GB",
    "wof:name":"SO23 9SE",
    "wof:placetype":"postalcode"
},
  "geometry": {"coordinates":[-1.32031220060236,51.0497584690042],"type":"Point"}
}