{
  "type": "Feature",
  "properties": {
    "iso:country":"GB",
    "wof:name":"B96 6QL",
    "wof:placetype":"postalcode"
},
  "geometry": {"coordinates":[-2.00020419401754,52.26032448138313],"type":"Point"}
}