{
  "type": "Feature",
  "properties": {
    "date:inception_lower": "1980-01-01",
    "date:inception_upper": "1980-01-01",
    "iso:country": "GB",
    "wof:name": "B96 6QL",
    "wof:placetype": "postalcode"
  },
  "geometry": {"coordinates":[-2.000204,52.260324],"type":"Point"}
}
