{
  "type": "Feature",
  "properties": {
    "iso:country":"GB",
    "wof:name":"WV6 9EU",
    "wof:placetype":"postalcode"
},
  "geometry": {"coordinates":[-2.16347094493465,52.61173030151597],"type":"Point"}
}