{
  "type": "Feature",
  "properties": {
    "iso:country": "GB",
    "wof:name": "DL13 1DA",
    "wof:placetype": "postalcode"
  },
  "geometry": {"coordinates":[-2.227225,54.760925],"type":"Point"}
}
