{
  "type": "Feature",
  "properties": {
    "iso:country":"GB",
    "wof:name":"DL13 1DA",
    "wof:placetype":"postalcode"
},
  "geometry": {"coordinates":[-2.22722491270696,54.76092489495776],"type":"Point"}
}