{
  "type": "Feature",
  "properties": {
    "date:inception_lower": "1980-01-01",
    "date:inception_upper": "1980-01-01",
    "iso:country": "GB",
    "wof:name": "EX32 0SN",
    "wof:placetype": "postalcode"
  },
  "geometry": {"coordinates":[-3.9189,51.078269],"type":"Point"}
}
