{
  "type": "Feature",
  "properties": {
    "date:inception_lower": "1980-01-01",
    "date:inception_upper": "1980-01-01",
    "iso:country": "GB",
    "wof:name": "LA14 2AP",
    "wof:placetype": "postalcode"
  },
  "geometry": {"coordinates":[-3.211725,54.110147],"type":"Point"}
}
