{
  "type": "Feature",
  "properties": {
    "iso:country":"GB",
    "wof:name":"LA14 2AP",
    "wof:placetype":"postalcode"
},
  "geometry": {"coordinates":[-3.21172490478702,54.11014730060572],"type":"Point"}
}