{
  "type": "Feature",
  "properties": {
    "iso:country": "GB",
    "wof:name": "MK18 5BN",
    "wof:placetype": "postalcode"
  },
  "geometry": {"coordinates":[-0.986643,52.033887],"type":"Point"}
}
