{
  "type": "Feature",
  "properties": {
    "iso:country":"GB",
    "wof:name":"MK18 5BN",
    "wof:placetype":"postalcode"
},
  "geometry": {"coordinates":[-0.98664276803514,52.03388681606364],"type":"Point"}
}