{
  "type": "Feature",
  "properties": {
    "iso:country":"GB",
    "wof:name":"DG8 0JU",
    "wof:placetype":"postalcode"
},
  "geometry": {"coordinates":[-4.73116004543597,54.82771262882377],"type":"Point"}
}