{
  "type": "Feature",
  "properties": {
    "date:inception_lower": "1980-01-01",
    "date:inception_upper": "1980-01-01",
    "iso:country": "GB",
    "wof:name": "E5 8ED",
    "wof:placetype": "postalcode"
  },
  "geometry": {"coordinates":[-0.05476,51.553862],"type":"Point"}
}
