{
  "type": "Feature",
  "properties": {
    "iso:country": "GB",
    "wof:name": "E5 8ED",
    "wof:placetype": "postalcode"
  },
  "geometry": {"coordinates":[-0.05476,51.553862],"type":"Point"}
}
