{
  "type": "Feature",
  "properties": {
    "date:inception_lower": "1980-01-01",
    "date:inception_upper": "1980-01-01",
    "iso:country": "GB",
    "wof:name": "LU4 9JD",
    "wof:placetype": "postalcode"
  },
  "geometry": {"coordinates":[-0.469783,51.907292],"type":"Point"}
}
