{
  "type": "Feature",
  "properties": {
    "iso:country":"GB",
    "wof:name":"BS30 9XS",
    "wof:placetype":"postalcode"
},
  "geometry": {"coordinates":[-2.48894095752992,51.4394304573499],"type":"Point"}
}