{
  "type": "Feature",
  "properties": {
    "date:inception_lower": "2012-08-01",
    "date:inception_upper": "2012-08-01",
    "iso:country": "GB",
    "wof:name": "CW11 1YS",
    "wof:placetype": "postalcode"
  },
  "geometry": {"coordinates":[-2.383985,53.152327],"type":"Point"}
}
