{
  "type": "Feature",
  "properties": {
    "iso:country": "GB",
    "wof:name": "CW11 1YS",
    "wof:placetype": "postalcode"
  },
  "geometry": {"coordinates":[-2.383985,53.152327],"type":"Point"}
}
