{
  "type": "Feature",
  "properties": {
    "iso:country":"GB",
    "wof:name":"CW11 1YS",
    "wof:placetype":"postalcode"
},
  "geometry": {"coordinates":[-2.38359384588276,53.15205078686378],"type":"Point"}
}