{
  "type": "Feature",
  "properties": {
    "iso:country":"GB",
    "wof:name":"IP4 3DQ",
    "wof:placetype":"postalcode"
},
  "geometry": {"coordinates":[1.18188734211916,52.07089994380507],"type":"Point"}
}