{
  "type": "Feature",
  "properties": {
    "date:inception_lower": "1980-01-01",
    "date:inception_upper": "1980-01-01",
    "iso:country": "GB",
    "wof:name": "EH16 6JH",
    "wof:placetype": "postalcode"
  },
  "geometry": {"coordinates":[-3.158718,55.91346],"type":"Point"}
}
