{
  "type": "Feature",
  "properties": {
    "iso:country":"GB",
    "wof:name":"S64 0JB",
    "wof:placetype":"postalcode"
},
  "geometry": {"coordinates":[-1.26901814847054,53.49505254060315],"type":"Point"}
}