{
  "type": "Feature",
  "properties": {
    "iso:country":"GB",
    "wof:name":"NW3 6YA",
    "wof:placetype":"postalcode"
},
  "geometry": {"coordinates":[-0.18296441974781,51.55468570788234],"type":"Point"}
}