{
  "type": "Feature",
  "properties": {
    "iso:country":"GB",
    "wof:name":"SR6 9AG",
    "wof:placetype":"postalcode"
},
  "geometry": {"coordinates":[-1.38488261646642,54.92854525651534],"type":"Point"}
}