{
  "type": "Feature",
  "properties": {
    "iso:country": "GB",
    "wof:name": "SR6 9AG",
    "wof:placetype": "postalcode"
  },
  "geometry": {"coordinates":[-1.384883,54.928545],"type":"Point"}
}
