{
  "type": "Feature",
  "properties": {
    "iso:country": "GB",
    "wof:name": "EX4 9JZ",
    "wof:placetype": "postalcode"
  },
  "geometry": {"coordinates":[-3.494002,50.741669],"type":"Point"}
}
