{
  "type": "Feature",
  "properties": {
    "iso:country":"GB",
    "wof:name":"BS39 4DQ",
    "wof:placetype":"postalcode"
},
  "geometry": {"coordinates":[-2.57843756269448,51.35691044348786],"type":"Point"}
}