{
  "type": "Feature",
  "properties": {
    "date:inception_lower": "1987-10-01",
    "date:inception_upper": "1987-10-01",
    "iso:country": "GB",
    "wof:name": "ME15 8UG",
    "wof:placetype": "postalcode"
  },
  "geometry": {"coordinates":[0.567772,51.260377],"type":"Point"}
}
