{
  "type": "Feature",
  "properties": {
    "iso:country":"GB",
    "wof:name":"ME15 8UG",
    "wof:placetype":"postalcode"
},
  "geometry": {"coordinates":[0.56777157923231,51.26037722407453],"type":"Point"}
}