{
  "type": "Feature",
  "properties": {
    "iso:country":"GB",
    "wof:name":"SN10 1PZ",
    "wof:placetype":"postalcode"
},
  "geometry": {"coordinates":[-2.01245787433575,51.35140634841116],"type":"Point"}
}