{
  "type": "Feature",
  "properties": {
    "iso:country": "GB",
    "wof:name": "SN10 1PZ",
    "wof:placetype": "postalcode"
  },
  "geometry": {"coordinates":[-2.012509,51.351502],"type":"Point"}
}
