{
  "type": "Feature",
  "properties": {
    "iso:country": "GB",
    "wof:name": "BS20 6YS",
    "wof:placetype": "postalcode"
  },
  "geometry": {"coordinates":[-2.760825,51.478812],"type":"Point"}
}
