{
  "type": "Feature",
  "properties": {
    "iso:country":"GB",
    "wof:name":"PO6 1SX",
    "wof:placetype":"postalcode"
},
  "geometry": {"coordinates":[-1.04488155107625,50.83737041057281],"type":"Point"}
}