{
  "type": "Feature",
  "properties": {
    "iso:country": "GB",
    "wof:name": "NG12 2FG",
    "wof:placetype": "postalcode"
  },
  "geometry": {"coordinates":[-1.038845,52.947475],"type":"Point"}
}
