{
  "type": "Feature",
  "properties": {
    "iso:country":"GB",
    "wof:name":"NG12 2FG",
    "wof:placetype":"postalcode"
},
  "geometry": {"coordinates":[-1.03884533541068,52.94747454399484],"type":"Point"}
}