{
  "type": "Feature",
  "properties": {
    "iso:country":"GB",
    "wof:name":"CT9 5QP",
    "wof:placetype":"postalcode"
},
  "geometry": {"coordinates":[1.36749063551112,51.3834881707699],"type":"Point"}
}