{
  "type": "Feature",
  "properties": {
    "date:inception_lower": "2013-12-01",
    "date:inception_upper": "2013-12-01",
    "iso:country": "GB",
    "wof:name": "EX23 8BG",
    "wof:placetype": "postalcode"
  },
  "geometry": {"coordinates":[-4.52938,50.826477],"type":"Point"}
}
