{
  "type": "Feature",
  "properties": {
    "date:inception_lower": "2020-05-01",
    "date:inception_upper": "2020-05-01",
    "iso:country": "GB",
    "wof:name": "WV14 7DJ",
    "wof:placetype": "postalcode"
  },
  "geometry": {"coordinates":[-2.067044,52.563762],"type":"Point"}
}
