{
  "type": "Feature",
  "properties": {
    "iso:country":"GB",
    "wof:name":"IP12 3PE",
    "wof:placetype":"postalcode"
},
  "geometry": {"coordinates":[1.45787125871698,52.1083162412748],"type":"Point"}
}