{
  "type": "Feature",
  "properties": {
    "date:inception_lower": "1980-01-01",
    "date:inception_upper": "1980-01-01",
    "iso:country": "GB",
    "wof:name": "IP12 3PE",
    "wof:placetype": "postalcode"
  },
  "geometry": {"coordinates":[1.457871,52.108316],"type":"Point"}
}
