{
  "type": "Feature",
  "properties": {
    "iso:country": "GB",
    "wof:name": "M20 2GZ",
    "wof:placetype": "postalcode"
  },
  "geometry": {"coordinates":[-2.236049,53.417945],"type":"Point"}
}
