{
  "type": "Feature",
  "properties": {
    "iso:country":"GB",
    "wof:name":"M20 2GZ",
    "wof:placetype":"postalcode"
},
  "geometry": {"coordinates":[-2.23604928775188,53.41794469606209],"type":"Point"}
}