{
  "type": "Feature",
  "properties": {
    "iso:country":"GB",
    "wof:name":"YO26 9RT",
    "wof:placetype":"postalcode"
},
  "geometry": {"coordinates":[-1.32886604406829,54.05516896697745],"type":"Point"}
}