{
  "type": "Feature",
  "properties": {
    "iso:country":"GB",
    "wof:name":"BL0 0PN",
    "wof:placetype":"postalcode"
},
  "geometry": {"coordinates":[-2.31617076639459,53.6588638062249],"type":"Point"}
}