{
  "type": "Feature",
  "properties": {
    "iso:country": "GB",
    "wof:name": "IP26 4JL",
    "wof:placetype": "postalcode"
  },
  "geometry": {"coordinates":[0.541505,52.455465],"type":"Point"}
}
