{
  "type": "Feature",
  "properties": {
    "iso:country":"GB",
    "wof:name":"IP26 4JL",
    "wof:placetype":"postalcode"
},
  "geometry": {"coordinates":[0.54150472762452,52.45546457803839],"type":"Point"}
}