{
  "type": "Feature",
  "properties": {
    "date:inception_lower":"1980-01-01",
    "date:inception_upper":"1980-01-31",
    "iso:country":"GB",
    "wof:name":"BL0 0DW",
    "wof:placetype":"postalcode"
},
  "geometry": {"coordinates":[-2.303172,53.652444],"type":"Point"}
}