{
  "type": "Feature",
  "properties": {
    "date:inception_lower": "1980-01-01",
    "date:inception_upper": "1980-01-01",
    "iso:country": "GB",
    "wof:name": "SL1 7NQ",
    "wof:placetype": "postalcode"
  },
  "geometry": {"coordinates":[-0.663721,51.526247],"type":"Point"}
}
