{
  "type": "Feature",
  "properties": {
    "iso:country":"GB",
    "wof:name":"DN33 3PD",
    "wof:placetype":"postalcode"
},
  "geometry": {"coordinates":[-0.10650838200487,53.53164400962293],"type":"Point"}
}