{
  "type": "Feature",
  "properties": {
    "date:inception_lower":"1997-12-01",
    "date:inception_upper":"1997-12-31",
    "iso:country":"GB",
    "wof:name":"DN33 3PD",
    "wof:placetype":"postalcode"
},
  "geometry": {"coordinates":[-0.106508,53.531644],"type":"Point"}
}