{
  "type": "Feature",
  "properties": {
    "iso:country":"GB",
    "wof:name":"SE19 1EW",
    "wof:placetype":"postalcode"
},
  "geometry": {"coordinates":[-0.08772757148675,51.42012655057544],"type":"Point"}
}