{
  "type": "Feature",
  "properties": {
    "iso:country":"GB",
    "wof:name":"WF7 7NP",
    "wof:placetype":"postalcode"
},
  "geometry": {"coordinates":[-1.32363601365954,53.65182740101854],"type":"Point"}
}