{
  "type": "Feature",
  "properties": {
    "date:inception_lower": "1980-01-01",
    "date:inception_upper": "1980-01-01",
    "iso:country": "GB",
    "wof:name": "WF7 7NP",
    "wof:placetype": "postalcode"
  },
  "geometry": {"coordinates":[-1.323636,53.651827],"type":"Point"}
}
