{
  "type": "Feature",
  "properties": {
    "iso:country":"GB",
    "wof:name":"SO19 2PF",
    "wof:placetype":"postalcode"
},
  "geometry": {"coordinates":[-1.36183658674048,50.90038607906156],"type":"Point"}
}