{
  "type": "Feature",
  "properties": {
    "date:inception_lower": "1994-12-01",
    "date:inception_upper": "1994-12-01",
    "iso:country": "GB",
    "wof:name": "SO19 2PF",
    "wof:placetype": "postalcode"
  },
  "geometry": {"coordinates":[-1.361837,50.900386],"type":"Point"}
}
