{
  "type": "Feature",
  "properties": {
    "iso:country":"GB",
    "wof:name":"IV31 6QD",
    "wof:placetype":"postalcode"
},
  "geometry": {"coordinates":[-3.2833421851406,57.72326161349824],"type":"Point"}
}