{
  "type": "Feature",
  "properties": {
    "iso:country": "GB",
    "wof:name": "IV31 6QD",
    "wof:placetype": "postalcode"
  },
  "geometry": {"coordinates":[-3.283342,57.723262],"type":"Point"}
}
