{
  "type": "Feature",
  "properties": {
    "iso:country":"GB",
    "wof:name":"NN10 0NA",
    "wof:placetype":"postalcode"
},
  "geometry": {"coordinates":[-0.58907393036779,52.28586447805132],"type":"Point"}
}