{
  "type": "Feature",
  "properties": {
    "iso:country": "GB",
    "wof:name": "CB7 4RJ",
    "wof:placetype": "postalcode"
  },
  "geometry": {"coordinates":[0.27123,52.406268],"type":"Point"}
}
