{
  "type": "Feature",
  "properties": {
    "iso:country":"GB",
    "wof:name":"EC1R 3BH",
    "wof:placetype":"postalcode"
},
  "geometry": {"coordinates":[-0.10731331702323,51.52319395784679],"type":"Point"}
}