{
  "type": "Feature",
  "properties": {
    "iso:country":"GB",
    "wof:name":"LN7 6DY",
    "wof:placetype":"postalcode"
},
  "geometry": {"coordinates":[-0.2268945666921,53.51119567621578],"type":"Point"}
}