{
  "type": "Feature",
  "properties": {
    "iso:country": "GB",
    "wof:name": "LN7 6DY",
    "wof:placetype": "postalcode"
  },
  "geometry": {"coordinates":[-0.226895,53.511196],"type":"Point"}
}
