{
  "type": "Feature",
  "properties": {
    "iso:country":"GB",
    "wof:name":"HG3 5JF",
    "wof:placetype":"postalcode"
},
  "geometry": {"coordinates":[-1.78200397241297,54.07188796373487],"type":"Point"}
}