{
  "type": "Feature",
  "properties": {
    "iso:country": "GB",
    "wof:name": "HG3 5JF",
    "wof:placetype": "postalcode"
  },
  "geometry": {"coordinates":[-1.782148,54.071669],"type":"Point"}
}
