{
  "type": "Feature",
  "properties": {
    "iso:country": "GB",
    "wof:name": "SY10 0AE",
    "wof:placetype": "postalcode"
  },
  "geometry": {"coordinates":[-3.273613,52.812991],"type":"Point"}
}
