{
  "type": "Feature",
  "properties": {
    "iso:country":"GB",
    "wof:name":"BS5 7JE",
    "wof:placetype":"postalcode"
},
  "geometry": {"coordinates":[-2.54377699266304,51.46175781010214],"type":"Point"}
}