{
  "type": "Feature",
  "properties": {
    "iso:country": "GB",
    "wof:name": "SY4 4RD",
    "wof:placetype": "postalcode"
  },
  "geometry": {"coordinates":[-2.625257,52.731473],"type":"Point"}
}
