{
  "type": "Feature",
  "properties": {
    "iso:country":"GB",
    "wof:name":"SY4 4RD",
    "wof:placetype":"postalcode"
},
  "geometry": {"coordinates":[-2.62525703896041,52.73147346125912],"type":"Point"}
}