{
  "type": "Feature",
  "properties": {
    "iso:country":"GB",
    "wof:name":"E14 7LQ",
    "wof:placetype":"postalcode"
},
  "geometry": {"coordinates":[-0.03451015211321,51.51562981187417],"type":"Point"}
}