{
  "type": "Feature",
  "properties": {
    "iso:country": "GB",
    "wof:name": "E14 7LQ",
    "wof:placetype": "postalcode"
  },
  "geometry": {"coordinates":[-0.03451,51.51563],"type":"Point"}
}
