{
  "type": "Feature",
  "properties": {
    "iso:country": "GB",
    "wof:name": "BD15 0NP",
    "wof:placetype": "postalcode"
  },
  "geometry": {"coordinates":[-1.860987,53.816852],"type":"Point"}
}
