{
  "type": "Feature",
  "properties": {
    "iso:country": "GB",
    "wof:name": "GL19 4DH",
    "wof:placetype": "postalcode"
  },
  "geometry": {"coordinates":[-2.207327,51.948682],"type":"Point"}
}
