{
  "type": "Feature",
  "properties": {
    "iso:country":"GB",
    "wof:name":"GL19 4DH",
    "wof:placetype":"postalcode"
},
  "geometry": {"coordinates":[-2.20732726249396,51.94868244414684],"type":"Point"}
}