{
  "type": "Feature",
  "properties": {
    "iso:country":"GB",
    "wof:name":"CA10 3EN",
    "wof:placetype":"postalcode"
},
  "geometry": {"coordinates":[-2.65311642666584,54.55798313154445],"type":"Point"}
}