{
  "type": "Feature",
  "properties": {
    "date:inception_lower":"1980-01-01",
    "date:inception_upper":"1980-01-31",
    "iso:country":"GB",
    "wof:name":"CA10 3EN",
    "wof:placetype":"postalcode"
},
  "geometry": {"coordinates":[-2.653121,54.557991],"type":"Point"}
}