{
  "type": "Feature",
  "properties": {
    "iso:country":"GB",
    "wof:name":"LE2 1LE",
    "wof:placetype":"postalcode"
},
  "geometry": {"coordinates":[-1.11237794354052,52.62405468874517],"type":"Point"}
}