{
  "type": "Feature",
  "properties": {
    "date:inception_lower": "1980-01-01",
    "date:inception_upper": "1980-01-01",
    "iso:country": "GB",
    "wof:name": "LL30 1HA",
    "wof:placetype": "postalcode"
  },
  "geometry": {"coordinates":[-3.82083,53.319499],"type":"Point"}
}
