{
  "type": "Feature",
  "properties": {
    "iso:country":"GB",
    "wof:name":"NG3 5BD",
    "wof:placetype":"postalcode"
},
  "geometry": {"coordinates":[-1.14519464616085,52.97256743838928],"type":"Point"}
}