{
  "type": "Feature",
  "properties": {
    "iso:country":"GB",
    "wof:name":"TQ2 6HS",
    "wof:placetype":"postalcode"
},
  "geometry": {"coordinates":[-3.54593188556185,50.46267086242238],"type":"Point"}
}