{
  "type": "Feature",
  "properties": {
    "date:inception_lower": "1981-06-01",
    "date:inception_upper": "1981-06-01",
    "iso:country": "GB",
    "wof:name": "NP7 6LZ",
    "wof:placetype": "postalcode"
  },
  "geometry": {"coordinates":[-3.008497,51.839275],"type":"Point"}
}
