{
  "type": "Feature",
  "properties": {
    "iso:country": "GB",
    "wof:name": "NP7 6LZ",
    "wof:placetype": "postalcode"
  },
  "geometry": {"coordinates":[-3.008497,51.839275],"type":"Point"}
}
