{
  "type": "Feature",
  "properties": {
    "iso:country": "GB",
    "wof:name": "W5 4SP",
    "wof:placetype": "postalcode"
  },
  "geometry": {"coordinates":[-0.307944,51.499426],"type":"Point"}
}
