{
  "type": "Feature",
  "properties": {
    "iso:country":"GB",
    "wof:name":"W5 4SP",
    "wof:placetype":"postalcode"
},
  "geometry": {"coordinates":[-0.3079436118546,51.49942646413144],"type":"Point"}
}