{
  "type": "Feature",
  "properties": {
    "date:inception_lower":"2000-06-01",
    "date:inception_upper":"2000-06-30",
    "iso:country":"GB",
    "wof:name":"OX16 1DS",
    "wof:placetype":"postalcode"
},
  "geometry": {"coordinates":[-1.361992,52.072192],"type":"Point"}
}