{
  "type": "Feature",
  "properties": {
    "iso:country":"GB",
    "wof:name":"NE6 3AX",
    "wof:placetype":"postalcode"
},
  "geometry": {"coordinates":[-1.55313285232551,54.97219848824572],"type":"Point"}
}