{
  "type": "Feature",
  "properties": {
    "date:inception_lower": "1980-01-01",
    "date:inception_upper": "1980-01-01",
    "iso:country": "GB",
    "wof:name": "NE6 3AX",
    "wof:placetype": "postalcode"
  },
  "geometry": {"coordinates":[-1.553133,54.972198],"type":"Point"}
}
