{
  "type": "Feature",
  "properties": {
    "iso:country":"GB",
    "wof:name":"NW3 5BA",
    "wof:placetype":"postalcode"
},
  "geometry": {"coordinates":[-0.17544320356347,51.5468984596796],"type":"Point"}
}