{
  "type": "Feature",
  "properties": {
    "iso:country": "GB",
    "wof:name": "NW3 5BA",
    "wof:placetype": "postalcode"
  },
  "geometry": {"coordinates":[-0.175443,51.546898],"type":"Point"}
}
