{
  "type": "Feature",
  "properties": {
    "date:inception_lower":"1999-12-01",
    "date:inception_upper":"1999-12-31",
    "iso:country":"GB",
    "wof:name":"LD3 8EX",
    "wof:placetype":"postalcode"
},
  "geometry": {"coordinates":[-3.414432,51.94648],"type":"Point"}
}