{
  "type": "Feature",
  "properties": {
    "iso:country":"GB",
    "wof:name":"LD3 8EX",
    "wof:placetype":"postalcode"
},
  "geometry": {"coordinates":[-3.41443243879109,51.94647981326418],"type":"Point"}
}