{
  "type": "Feature",
  "properties": {
    "iso:country": "GB",
    "wof:name": "HR2 9SD",
    "wof:placetype": "postalcode"
  },
  "geometry": {"coordinates":[-2.782302,52.039087],"type":"Point"}
}
