{
  "type": "Feature",
  "properties": {
    "iso:country":"GB",
    "wof:name":"HR2 9SD",
    "wof:placetype":"postalcode"
},
  "geometry": {"coordinates":[-2.78230201425519,52.03908690921509],"type":"Point"}
}