{
  "type": "Feature",
  "properties": {
    "date:inception_lower": "1980-01-01",
    "date:inception_upper": "1980-01-01",
    "iso:country": "GB",
    "wof:name": "HR2 9SD",
    "wof:placetype": "postalcode"
  },
  "geometry": {"coordinates":[-2.782302,52.039087],"type":"Point"}
}
