{
  "type": "Feature",
  "properties": {
    "date:inception_lower": "2000-12-01",
    "date:inception_upper": "2000-12-01",
    "iso:country": "GB",
    "wof:name": "HP19 7WD",
    "wof:placetype": "postalcode"
  },
  "geometry": {"coordinates":[-0.836907,51.815869],"type":"Point"}
}
