{
  "type": "Feature",
  "properties": {
    "date:inception_lower": "1980-01-01",
    "date:inception_upper": "1980-01-01",
    "iso:country": "GB",
    "wof:name": "ST4 8JY",
    "wof:placetype": "postalcode"
  },
  "geometry": {"coordinates":[-2.191273,52.968248],"type":"Point"}
}
