{
  "type": "Feature",
  "properties": {
    "date:inception_lower": "1990-02-01",
    "date:inception_upper": "1990-02-01",
    "iso:country": "GB",
    "wof:name": "WD4 9JT",
    "wof:placetype": "postalcode"
  },
  "geometry": {"coordinates":[-0.460548,51.717517],"type":"Point"}
}
