{
  "type": "Feature",
  "properties": {
    "iso:country":"GB",
    "wof:name":"WD4 9JT",
    "wof:placetype":"postalcode"
},
  "geometry": {"coordinates":[-0.46054823602368,51.71751737737282],"type":"Point"}
}