{
  "type": "Feature",
  "properties": {
    "date:inception_lower": "1981-06-01",
    "date:inception_upper": "1981-06-01",
    "iso:country": "GB",
    "wof:name": "PR8 6UR",
    "wof:placetype": "postalcode"
  },
  "geometry": {"coordinates":[-2.978464,53.62855],"type":"Point"}
}
