{
  "type": "Feature",
  "properties": {
    "iso:country":"GB",
    "wof:name":"HR4 9QP",
    "wof:placetype":"postalcode"
},
  "geometry": {"coordinates":[-2.73417268024685,52.0762139833333],"type":"Point"}
}