{
  "type": "Feature",
  "properties": {
    "iso:country":"GB",
    "wof:name":"SW9 7NJ",
    "wof:placetype":"postalcode"
},
  "geometry": {"coordinates":[-0.11038992506055,51.46417138059854],"type":"Point"}
}