{
  "type": "Feature",
  "properties": {
    "iso:country":"GB",
    "wof:name":"SO31 9BE",
    "wof:placetype":"postalcode"
},
  "geometry": {"coordinates":[-1.28800740633228,50.8534767547446],"type":"Point"}
}