{
  "type": "Feature",
  "properties": {
    "iso:country": "GB",
    "wof:name": "EH42 1PG",
    "wof:placetype": "postalcode"
  },
  "geometry": {"coordinates":[-2.535383,55.997695],"type":"Point"}
}
