{
  "type": "Feature",
  "properties": {
    "iso:country": "GB",
    "wof:name": "GU10 2DJ",
    "wof:placetype": "postalcode"
  },
  "geometry": {"coordinates":[-0.765612,51.182452],"type":"Point"}
}
