{
  "type": "Feature",
  "properties": {
    "iso:country":"GB",
    "wof:name":"BN3 3PQ",
    "wof:placetype":"postalcode"
},
  "geometry": {"coordinates":[-0.16871013123427,50.83057899162588],"type":"Point"}
}