{
  "type": "Feature",
  "properties": {
    "iso:country":"GB",
    "wof:name":"DY13 9GX",
    "wof:placetype":"postalcode"
},
  "geometry": {"coordinates":[-2.27055340710275,52.34276921809579],"type":"Point"}
}