{
  "type": "Feature",
  "properties": {
    "date:inception_lower": "2010-10-01",
    "date:inception_upper": "2010-10-01",
    "iso:country": "GB",
    "wof:name": "DY13 9GX",
    "wof:placetype": "postalcode"
  },
  "geometry": {"coordinates":[-2.270553,52.342769],"type":"Point"}
}
