{
  "type": "Feature",
  "properties": {
    "iso:country":"GB",
    "wof:name":"GL54 2GZ",
    "wof:placetype":"postalcode"
},
  "geometry": {"coordinates":[-1.75525503928,51.89347084099901],"type":"Point"}
}