{
  "type": "Feature",
  "properties": {
    "iso:country": "GB",
    "wof:name": "GU9 7GN",
    "wof:placetype": "postalcode"
  },
  "geometry": {"coordinates":[-0.789733,51.219004],"type":"Point"}
}
