{
  "type": "Feature",
  "properties": {
    "iso:country": "GB",
    "wof:name": "CF23 5RH",
    "wof:placetype": "postalcode"
  },
  "geometry": {"coordinates":[-3.162651,51.497887],"type":"Point"}
}
