{
  "type": "Feature",
  "properties": {
    "date:inception_lower": "1980-01-01",
    "date:inception_upper": "1980-01-01",
    "iso:country": "GB",
    "wof:name": "LL16 5RE",
    "wof:placetype": "postalcode"
  },
  "geometry": {"coordinates":[-3.480253,53.13489],"type":"Point"}
}
