{
  "type": "Feature",
  "properties": {
    "iso:country": "GB",
    "wof:name": "NG23 5AF",
    "wof:placetype": "postalcode"
  },
  "geometry": {"coordinates":[-0.744746,53.032068],"type":"Point"}
}
