{
  "type": "Feature",
  "properties": {
    "date:inception_lower": "1980-01-01",
    "date:inception_upper": "1980-01-01",
    "iso:country": "GB",
    "wof:name": "WV12 5LR",
    "wof:placetype": "postalcode"
  },
  "geometry": {"coordinates":[-2.03822,52.610246],"type":"Point"}
}
