{
  "type": "Feature",
  "properties": {
    "date:inception_lower": "2000-06-01",
    "date:inception_upper": "2000-06-01",
    "iso:country": "GB",
    "wof:name": "OX16 1QG",
    "wof:placetype": "postalcode"
  },
  "geometry": {"coordinates":[-1.346783,52.073682],"type":"Point"}
}
