{
  "type": "Feature",
  "properties": {
    "iso:country":"GB",
    "wof:name":"OX16 1QG",
    "wof:placetype":"postalcode"
},
  "geometry": {"coordinates":[-1.34678278203049,52.07368163484999],"type":"Point"}
}