{
  "type": "Feature",
  "properties": {
    "date:inception_lower": "1993-01-01",
    "date:inception_upper": "1993-01-01",
    "iso:country": "GB",
    "wof:name": "GL56 0AU",
    "wof:placetype": "postalcode"
  },
  "geometry": {"coordinates":[-1.701297,51.992443],"type":"Point"}
}
