{
  "type": "Feature",
  "properties": {
    "iso:country":"GB",
    "wof:name":"PE3 7DH",
    "wof:placetype":"postalcode"
},
  "geometry": {"coordinates":[-0.27200688236627,52.58763476214696],"type":"Point"}
}