{
  "type": "Feature",
  "properties": {
    "iso:country":"GB",
    "wof:name":"LN6 7QG",
    "wof:placetype":"postalcode"
},
  "geometry": {"coordinates":[-0.55860646418035,53.20454004276495],"type":"Point"}
}