{
  "type": "Feature",
  "properties": {
    "date:inception_lower": "1980-01-01",
    "date:inception_upper": "1980-01-01",
    "iso:country": "GB",
    "wof:name": "LN6 7QG",
    "wof:placetype": "postalcode"
  },
  "geometry": {"coordinates":[-0.558606,53.20454],"type":"Point"}
}
