{
  "type": "Feature",
  "properties": {
    "iso:country": "GB",
    "wof:name": "LN6 7QG",
    "wof:placetype": "postalcode"
  },
  "geometry": {"coordinates":[-0.558606,53.20454],"type":"Point"}
}
