{
  "type": "Feature",
  "properties": {
    "iso:country":"GB",
    "wof:name":"BS1 4TR",
    "wof:placetype":"postalcode"
},
  "geometry": {"coordinates":[-2.59645548080835,51.45589078759779],"type":"Point"}
}