{
  "type": "Feature",
  "properties": {
    "date:inception_lower": "2009-01-01",
    "date:inception_upper": "2009-01-01",
    "iso:country": "GB",
    "wof:name": "LS10 1GX",
    "wof:placetype": "postalcode"
  },
  "geometry": {"coordinates":[-1.539236,53.793181],"type":"Point"}
}
