{
  "type": "Feature",
  "properties": {
    "iso:country":"GB",
    "wof:name":"SN13 8LF",
    "wof:placetype":"postalcode"
},
  "geometry": {"coordinates":[-2.24625936413186,51.41556394026325],"type":"Point"}
}