{
  "type": "Feature",
  "properties": {
    "iso:country":"GB",
    "wof:name":"LA3 1AU",
    "wof:placetype":"postalcode"
},
  "geometry": {"coordinates":[-2.8781742949926,54.06249645279114],"type":"Point"}
}