{
  "type": "Feature",
  "properties": {
    "date:inception_lower": "1980-01-01",
    "date:inception_upper": "1980-01-01",
    "iso:country": "GB",
    "wof:name": "CA14 3QJ",
    "wof:placetype": "postalcode"
  },
  "geometry": {"coordinates":[-3.549993,54.629249],"type":"Point"}
}
