{
  "type": "Feature",
  "properties": {
    "date:inception_lower": "1980-01-01",
    "date:inception_upper": "1980-01-01",
    "iso:country": "GB",
    "wof:name": "CA14 3QJ",
    "wof:placetype": "postalcode"
  },
  "geometry": {"coordinates":[-3.550054,54.629212],"type":"Point"}
}
