{
  "type": "Feature",
  "properties": {
    "iso:country": "GB",
    "wof:name": "WR10 3LQ",
    "wof:placetype": "postalcode"
  },
  "geometry": {"coordinates":[-1.984695,52.110642],"type":"Point"}
}
