{
  "type": "Feature",
  "properties": {
    "iso:country":"GB",
    "wof:name":"WR10 3LQ",
    "wof:placetype":"postalcode"
},
  "geometry": {"coordinates":[-1.98469516658315,52.1106422034431],"type":"Point"}
}