{
  "type": "Feature",
  "properties": {
    "iso:country":"GB",
    "wof:name":"M28 3WY",
    "wof:placetype":"postalcode"
},
  "geometry": {"coordinates":[-2.3938480034601,53.52632516086994],"type":"Point"}
}