{
  "type": "Feature",
  "properties": {
    "date:inception_lower": "1994-05-01",
    "date:inception_upper": "1994-05-01",
    "iso:country": "GB",
    "wof:name": "M28 3WY",
    "wof:placetype": "postalcode"
  },
  "geometry": {"coordinates":[-2.393848,53.526325],"type":"Point"}
}
