{
  "type": "Feature",
  "properties": {
    "iso:country":"GB",
    "wof:name":"NE31 1UD",
    "wof:placetype":"postalcode"
},
  "geometry": {"coordinates":[-1.52634708089313,54.96112490368613],"type":"Point"}
}