{
  "type": "Feature",
  "properties": {
    "date:inception_lower":"2002-11-01",
    "date:inception_upper":"2002-11-30",
    "iso:country":"GB",
    "wof:name":"LU4 9GH",
    "wof:placetype":"postalcode"
},
  "geometry": {"coordinates":[-0.461256,51.89987],"type":"Point"}
}