{
  "type": "Feature",
  "properties": {
    "iso:country": "GB",
    "wof:name": "LU4 9GH",
    "wof:placetype": "postalcode"
  },
  "geometry": {"coordinates":[-0.461256,51.89987],"type":"Point"}
}
