{
  "type": "Feature",
  "properties": {
    "iso:country": "GB",
    "wof:name": "NR34 7TT",
    "wof:placetype": "postalcode"
  },
  "geometry": {"coordinates":[1.60507,52.415148],"type":"Point"}
}
