{
  "type": "Feature",
  "properties": {
    "date:inception_lower": "1980-01-01",
    "date:inception_upper": "1980-01-01",
    "iso:country": "GB",
    "wof:name": "NR34 7TT",
    "wof:placetype": "postalcode"
  },
  "geometry": {"coordinates":[1.60507,52.415148],"type":"Point"}
}
