{
  "type": "Feature",
  "properties": {
    "iso:country":"GB",
    "wof:name":"NR34 7TT",
    "wof:placetype":"postalcode"
},
  "geometry": {"coordinates":[1.60507032775372,52.41514793493262],"type":"Point"}
}