{
  "type": "Feature",
  "properties": {
    "iso:country": "GB",
    "wof:name": "IP30 0LA",
    "wof:placetype": "postalcode"
  },
  "geometry": {"coordinates":[0.782498,52.158902],"type":"Point"}
}
