{
  "type": "Feature",
  "properties": {
    "iso:country":"GB",
    "wof:name":"B12 9ER",
    "wof:placetype":"postalcode"
},
  "geometry": {"coordinates":[-1.8895442211547,52.46069935751856],"type":"Point"}
}