{
  "type": "Feature",
  "properties": {
    "iso:country":"GB",
    "wof:name":"IP4 1DN",
    "wof:placetype":"postalcode"
},
  "geometry": {"coordinates":[1.15614863265534,52.05485488389709],"type":"Point"}
}