{
  "type": "Feature",
  "properties": {
    "date:inception_lower":"2010-10-01",
    "date:inception_upper":"2010-10-31",
    "iso:country":"GB",
    "wof:name":"IP4 1DN",
    "wof:placetype":"postalcode"
},
  "geometry": {"coordinates":[1.156149,52.054855],"type":"Point"}
}