{
  "type": "Feature",
  "properties": {
    "iso:country":"GB",
    "wof:name":"SG16 6HU",
    "wof:placetype":"postalcode"
},
  "geometry": {"coordinates":[-0.29461189266307,52.01070718889719],"type":"Point"}
}