{
  "type": "Feature",
  "properties": {
    "date:inception_lower": "2020-09-01",
    "date:inception_upper": "2020-09-01",
    "iso:country": "GB",
    "wof:name": "EH53 0GL",
    "wof:placetype": "postalcode"
  },
  "geometry": {"coordinates":[-3.445151,55.898916],"type":"Point"}
}
