{
  "type": "Feature",
  "properties": {
    "date:inception_lower": "1999-06-01",
    "date:inception_upper": "1999-06-01",
    "iso:country": "GB",
    "wof:name": "NP10 8SN",
    "wof:placetype": "postalcode"
  },
  "geometry": {"coordinates":[-3.019496,51.534936],"type":"Point"}
}
