{
  "type": "Feature",
  "properties": {
    "iso:country":"GB",
    "wof:name":"NP10 8SN",
    "wof:placetype":"postalcode"
},
  "geometry": {"coordinates":[-3.01948899570104,51.53493484292739],"type":"Point"}
}