{
  "type": "Feature",
  "properties": {
    "iso:country":"GB",
    "wof:name":"DE5 8NQ",
    "wof:placetype":"postalcode"
},
  "geometry": {"coordinates":[-1.4319600249568,53.01540890905855],"type":"Point"}
}