{
  "type": "Feature",
  "properties": {
    "iso:country":"GB",
    "wof:name":"W9 3UJ",
    "wof:placetype":"postalcode"
},
  "geometry": {"coordinates":[-0.19647002849511,51.52212574789431],"type":"Point"}
}