{
  "type": "Feature",
  "properties": {
    "iso:country": "GB",
    "wof:name": "HU11 4TS",
    "wof:placetype": "postalcode"
  },
  "geometry": {"coordinates":[-0.184788,53.848505],"type":"Point"}
}
