{
  "type": "Feature",
  "properties": {
    "date:inception_lower":"1980-01-01",
    "date:inception_upper":"1980-01-31",
    "iso:country":"GB",
    "wof:name":"HU11 4TS",
    "wof:placetype":"postalcode"
},
  "geometry": {"coordinates":[-0.184788,53.848505],"type":"Point"}
}