{
  "type": "Feature",
  "properties": {
    "iso:country":"GB",
    "wof:name":"WA3 5QE",
    "wof:placetype":"postalcode"
},
  "geometry": {"coordinates":[-2.48891257701945,53.47930576702429],"type":"Point"}
}