{
  "type": "Feature",
  "properties": {
    "iso:country": "GB",
    "wof:name": "NR16 1JU",
    "wof:placetype": "postalcode"
  },
  "geometry": {"coordinates":[1.179569,52.502262],"type":"Point"}
}
