{
  "type": "Feature",
  "properties": {
    "iso:country":"GB",
    "wof:name":"NR16 1JU",
    "wof:placetype":"postalcode"
},
  "geometry": {"coordinates":[1.17954363519551,52.502239821357],"type":"Point"}
}