{
  "type": "Feature",
  "properties": {
    "iso:country":"GB",
    "wof:name":"NG33 5BQ",
    "wof:placetype":"postalcode"
},
  "geometry": {"coordinates":[-0.60152129292157,52.85869028092473],"type":"Point"}
}