{
  "type": "Feature",
  "properties": {
    "iso:country": "GB",
    "wof:name": "NG33 5BQ",
    "wof:placetype": "postalcode"
  },
  "geometry": {"coordinates":[-0.601521,52.85869],"type":"Point"}
}
