{
  "type": "Feature",
  "properties": {
    "date:inception_lower": "1980-01-01",
    "date:inception_upper": "1980-01-01",
    "iso:country": "GB",
    "wof:name": "NG33 5BQ",
    "wof:placetype": "postalcode"
  },
  "geometry": {"coordinates":[-0.601521,52.85869],"type":"Point"}
}
