{
  "type": "Feature",
  "properties": {
    "iso:country":"GB",
    "wof:name":"SE28 0LZ",
    "wof:placetype":"postalcode"
},
  "geometry": {"coordinates":[0.0866309937326,51.50141477767037],"type":"Point"}
}