{
  "type": "Feature",
  "properties": {
    "iso:country":"GB",
    "wof:name":"L4 2SA",
    "wof:placetype":"postalcode"
},
  "geometry": {"coordinates":[-2.9517649268975,53.42832572045466],"type":"Point"}
}