{
  "type": "Feature",
  "properties": {
    "iso:country": "GB",
    "wof:name": "PO21 1FW",
    "wof:placetype": "postalcode"
  },
  "geometry": {"coordinates":[-0.669407,50.789718],"type":"Point"}
}
