{
  "type": "Feature",
  "properties": {
    "date:inception_lower": "2009-07-01",
    "date:inception_upper": "2009-07-01",
    "iso:country": "GB",
    "wof:name": "PO21 1FW",
    "wof:placetype": "postalcode"
  },
  "geometry": {"coordinates":[-0.669407,50.789718],"type":"Point"}
}
