{
  "type": "Feature",
  "properties": {
    "date:inception_lower":"1990-02-01",
    "date:inception_upper":"1990-02-28",
    "iso:country":"GB",
    "wof:name":"CB6 3TR",
    "wof:placetype":"postalcode"
},
  "geometry": {"coordinates":[0.149619,52.358306],"type":"Point"}
}