{
  "type": "Feature",
  "properties": {
    "iso:country":"GB",
    "wof:name":"IV2 4NF",
    "wof:placetype":"postalcode"
},
  "geometry": {"coordinates":[-4.22169114271161,57.46308625795677],"type":"Point"}
}