{
  "type": "Feature",
  "properties": {
    "date:inception_lower": "1997-12-01",
    "date:inception_upper": "1997-12-01",
    "iso:country": "GB",
    "wof:name": "ML11 9PE",
    "wof:placetype": "postalcode"
  },
  "geometry": {"coordinates":[-3.839125,55.638325],"type":"Point"}
}
