{
  "type": "Feature",
  "properties": {
    "iso:country":"GB",
    "wof:name":"SS9 1SY",
    "wof:placetype":"postalcode"
},
  "geometry": {"coordinates":[0.65548757390004,51.5470467449188],"type":"Point"}
}