{
  "type": "Feature",
  "properties": {
    "date:inception_lower": "1980-01-01",
    "date:inception_upper": "1980-01-01",
    "iso:country": "GB",
    "wof:name": "SS9 1SY",
    "wof:placetype": "postalcode"
  },
  "geometry": {"coordinates":[0.655488,51.547047],"type":"Point"}
}
