{
  "type": "Feature",
  "properties": {
    "iso:country":"GB",
    "wof:name":"L15 3JY",
    "wof:placetype":"postalcode"
},
  "geometry": {"coordinates":[-2.92916494319093,53.39200885746131],"type":"Point"}
}