{
  "type": "Feature",
  "properties": {
    "iso:country":"GB",
    "wof:name":"CV35 7TL",
    "wof:placetype":"postalcode"
},
  "geometry": {"coordinates":[-1.6377724585184,52.30033394675795],"type":"Point"}
}