{
  "type": "Feature",
  "properties": {
    "date:inception_lower":"1999-12-01",
    "date:inception_upper":"1999-12-31",
    "iso:country":"GB",
    "wof:name":"CV35 7TL",
    "wof:placetype":"postalcode"
},
  "geometry": {"coordinates":[-1.637772,52.300334],"type":"Point"}
}