{
  "type": "Feature",
  "properties": {
    "iso:country": "GB",
    "wof:name": "M18 8GW",
    "wof:placetype": "postalcode"
  },
  "geometry": {"coordinates":[-2.166687,53.46802],"type":"Point"}
}
