{
  "type": "Feature",
  "properties": {
    "iso:country":"GB",
    "wof:name":"M18 8GW",
    "wof:placetype":"postalcode"
},
  "geometry": {"coordinates":[-2.16668731707974,53.46801988950845],"type":"Point"}
}