{
  "type": "Feature",
  "properties": {
    "date:inception_lower": "1980-01-01",
    "date:inception_upper": "1980-01-01",
    "iso:country": "GB",
    "wof:name": "M18 8GW",
    "wof:placetype": "postalcode"
  },
  "geometry": {"coordinates":[-2.166687,53.46802],"type":"Point"}
}
