{
  "type": "Feature",
  "properties": {
    "iso:country":"GB",
    "wof:name":"KA26 0SB",
    "wof:placetype":"postalcode"
},
  "geometry": {"coordinates":[-4.91120232960749,55.13248053655332],"type":"Point"}
}