{
  "type": "Feature",
  "properties": {
    "date:inception_lower":"1980-01-01",
    "date:inception_upper":"1980-01-31",
    "iso:country":"GB",
    "wof:name":"KA26 0SB",
    "wof:placetype":"postalcode"
},
  "geometry": {"coordinates":[-4.911202,55.132481],"type":"Point"}
}