{
  "type": "Feature",
  "properties": {
    "iso:country":"GB",
    "wof:name":"PO1 2NF",
    "wof:placetype":"postalcode"
},
  "geometry": {"coordinates":[-1.1056605438501,50.78923714422147],"type":"Point"}
}