{
  "type": "Feature",
  "properties": {
    "iso:country": "GB",
    "wof:name": "GU35 0GQ",
    "wof:placetype": "postalcode"
  },
  "geometry": {"coordinates":[-0.868606,51.122944],"type":"Point"}
}
