{
  "type": "Feature",
  "properties": {
    "iso:country":"GB",
    "wof:name":"IV27 4JH",
    "wof:placetype":"postalcode"
},
  "geometry": {"coordinates":[-5.37613001392271,58.23349258740244],"type":"Point"}
}