{
  "type": "Feature",
  "properties": {
    "date:inception_lower": "1980-01-01",
    "date:inception_upper": "1980-01-01",
    "iso:country": "GB",
    "wof:name": "IV27 4JH",
    "wof:placetype": "postalcode"
  },
  "geometry": {"coordinates":[-5.377884,58.234372],"type":"Point"}
}
