{
  "type": "Feature",
  "properties": {
    "iso:country":"GB",
    "wof:name":"OX27 8EQ",
    "wof:placetype":"postalcode"
},
  "geometry": {"coordinates":[-1.12221902108978,51.97778318400695],"type":"Point"}
}