{
  "type": "Feature",
  "properties": {
    "date:inception_lower": "1999-12-01",
    "date:inception_upper": "1999-12-01",
    "iso:country": "GB",
    "wof:name": "SW16 1UF",
    "wof:placetype": "postalcode"
  },
  "geometry": {"coordinates":[-0.134819,51.432783],"type":"Point"}
}
