{
  "type": "Feature",
  "properties": {
    "iso:country":"GB",
    "wof:name":"SW16 1UF",
    "wof:placetype":"postalcode"
},
  "geometry": {"coordinates":[-0.13481922653067,51.43278271451292],"type":"Point"}
}