{
  "type": "Feature",
  "properties": {
    "iso:country":"GB",
    "wof:name":"BD1 4EH",
    "wof:placetype":"postalcode"
},
  "geometry": {"coordinates":[-1.74777442044394,53.79610312157126],"type":"Point"}
}