{
  "type": "Feature",
  "properties": {
    "date:inception_lower": "1980-01-01",
    "date:inception_upper": "1980-01-01",
    "iso:country": "GB",
    "wof:name": "SM4 6BW",
    "wof:placetype": "postalcode"
  },
  "geometry": {"coordinates":[-0.186623,51.385953],"type":"Point"}
}
