{
  "type": "Feature",
  "properties": {
    "iso:country":"GB",
    "wof:name":"N1 6JJ",
    "wof:placetype":"postalcode"
},
  "geometry": {"coordinates":[-0.08363178082421,51.53171206835857],"type":"Point"}
}