{
  "type": "Feature",
  "properties": {
    "iso:country": "GB",
    "wof:name": "YO11 1QS",
    "wof:placetype": "postalcode"
  },
  "geometry": {"coordinates":[-0.392155,54.284598],"type":"Point"}
}
