{
  "type": "Feature",
  "properties": {
    "iso:country":"GB",
    "wof:name":"YO11 1QS",
    "wof:placetype":"postalcode"
},
  "geometry": {"coordinates":[-0.39213772921901,54.28458074874695],"type":"Point"}
}