{
  "type": "Feature",
  "properties": {
    "iso:country": "GB",
    "wof:name": "OX26 4AD",
    "wof:placetype": "postalcode"
  },
  "geometry": {"coordinates":[-1.131641,51.907308],"type":"Point"}
}
