{
  "type": "Feature",
  "properties": {
    "iso:country": "GB",
    "wof:name": "PO37 7AY",
    "wof:placetype": "postalcode"
  },
  "geometry": {"coordinates":[-1.182898,50.634991],"type":"Point"}
}
