{
  "type": "Feature",
  "properties": {
    "iso:country":"GB",
    "wof:name":"PO37 7AY",
    "wof:placetype":"postalcode"
},
  "geometry": {"coordinates":[-1.18289789756749,50.63499142734553],"type":"Point"}
}