{
  "type": "Feature",
  "properties": {
    "date:inception_lower":"2007-10-01",
    "date:inception_upper":"2007-10-31",
    "iso:country":"GB",
    "wof:name":"PO37 7AY",
    "wof:placetype":"postalcode"
},
  "geometry": {"coordinates":[-1.182898,50.634991],"type":"Point"}
}