{
  "type": "Feature",
  "properties": {
    "iso:country": "GB",
    "wof:name": "TN3 0XJ",
    "wof:placetype": "postalcode"
  },
  "geometry": {"coordinates":[0.229756,51.168316],"type":"Point"}
}
