{
  "type": "Feature",
  "properties": {
    "iso:country":"GB",
    "wof:name":"TN3 0XJ",
    "wof:placetype":"postalcode"
},
  "geometry": {"coordinates":[0.22975585130809,51.168316058511],"type":"Point"}
}