{
  "type": "Feature",
  "properties": {
    "iso:country":"GB",
    "wof:name":"SM6 8JS",
    "wof:placetype":"postalcode"
},
  "geometry": {"coordinates":[-0.13009809834258,51.36304121708803],"type":"Point"}
}