{
  "type": "Feature",
  "properties": {
    "iso:country":"GB",
    "wof:name":"BS16 1AU",
    "wof:placetype":"postalcode"
},
  "geometry": {"coordinates":[-2.55227413719052,51.48358564813122],"type":"Point"}
}