{
  "type": "Feature",
  "properties": {
    "date:inception_lower": "1980-01-01",
    "date:inception_upper": "1980-01-01",
    "iso:country": "GB",
    "wof:name": "BS16 1AU",
    "wof:placetype": "postalcode"
  },
  "geometry": {"coordinates":[-2.552274,51.483586],"type":"Point"}
}
