{
  "type": "Feature",
  "properties": {
    "iso:country": "GB",
    "wof:name": "TF9 3JQ",
    "wof:placetype": "postalcode"
  },
  "geometry": {"coordinates":[-2.543418,52.846458],"type":"Point"}
}
