{
  "type": "Feature",
  "properties": {
    "iso:country": "GB",
    "wof:name": "NP44 3ES",
    "wof:placetype": "postalcode"
  },
  "geometry": {"coordinates":[-3.033647,51.649044],"type":"Point"}
}
