{
  "type": "Feature",
  "properties": {
    "iso:country":"GB",
    "wof:name":"NP44 3ES",
    "wof:placetype":"postalcode"
},
  "geometry": {"coordinates":[-3.03356551049446,51.64896969144254],"type":"Point"}
}