{
  "type": "Feature",
  "properties": {
    "iso:country":"GB",
    "wof:name":"SO50 9AQ",
    "wof:placetype":"postalcode"
},
  "geometry": {"coordinates":[-1.35579056596138,50.97165404243159],"type":"Point"}
}