{
  "type": "Feature",
  "properties": {
    "iso:country":"GB",
    "wof:name":"BA1 1JW",
    "wof:placetype":"postalcode"
},
  "geometry": {"coordinates":[-2.35671017541291,51.37872850936861],"type":"Point"}
}