{
  "type": "Feature",
  "properties": {
    "iso:country": "GB",
    "wof:name": "BA1 1JW",
    "wof:placetype": "postalcode"
  },
  "geometry": {"coordinates":[-2.356708,51.378725],"type":"Point"}
}
