{
  "type": "Feature",
  "properties": {
    "iso:country":"GB",
    "wof:name":"UB9 5AU",
    "wof:placetype":"postalcode"
},
  "geometry": {"coordinates":[-0.49500072175271,51.56432713730567],"type":"Point"}
}