{
  "type": "Feature",
  "properties": {
    "date:inception_lower": "1980-01-01",
    "date:inception_upper": "1980-01-01",
    "iso:country": "GB",
    "wof:name": "UB9 5AU",
    "wof:placetype": "postalcode"
  },
  "geometry": {"coordinates":[-0.494908,51.564319],"type":"Point"}
}
