{
  "type": "Feature",
  "properties": {
    "iso:country":"GB",
    "wof:name":"DY8 5JN",
    "wof:placetype":"postalcode"
},
  "geometry": {"coordinates":[-2.17620026311095,52.4791294379906],"type":"Point"}
}