{
  "type": "Feature",
  "properties": {
    "iso:country": "GB",
    "wof:name": "DY8 5JN",
    "wof:placetype": "postalcode"
  },
  "geometry": {"coordinates":[-2.17615,52.479144],"type":"Point"}
}
