{
  "type": "Feature",
  "properties": {
    "iso:country": "GB",
    "wof:name": "BN2 9NB",
    "wof:placetype": "postalcode"
  },
  "geometry": {"coordinates":[-0.134112,50.828583],"type":"Point"}
}
