{
  "type": "Feature",
  "properties": {
    "iso:country":"GB",
    "wof:name":"BN2 9NB",
    "wof:placetype":"postalcode"
},
  "geometry": {"coordinates":[-0.13411183847158,50.82858284753161],"type":"Point"}
}