{
  "type": "Feature",
  "properties": {
    "iso:country": "GB",
    "wof:name": "LA14 4TF",
    "wof:placetype": "postalcode"
  },
  "geometry": {"coordinates":[-3.23043,54.138459],"type":"Point"}
}
