{
  "type": "Feature",
  "properties": {
    "iso:country":"GB",
    "wof:name":"LA14 4TF",
    "wof:placetype":"postalcode"
},
  "geometry": {"coordinates":[-3.23043015470519,54.13845876696787],"type":"Point"}
}