{
  "type": "Feature",
  "properties": {
    "iso:country":"GB",
    "wof:name":"EX1 3XS",
    "wof:placetype":"postalcode"
},
  "geometry": {"coordinates":[-3.46640936777795,50.73629113724962],"type":"Point"}
}