{
  "type": "Feature",
  "properties": {
    "iso:country": "GB",
    "wof:name": "EX1 3XS",
    "wof:placetype": "postalcode"
  },
  "geometry": {"coordinates":[-3.466409,50.736291],"type":"Point"}
}
