{
  "type": "Feature",
  "properties": {
    "iso:country":"GB",
    "wof:name":"B65 8BS",
    "wof:placetype":"postalcode"
},
  "geometry": {"coordinates":[-2.0465403036884,52.4772110549439],"type":"Point"}
}