{
  "type": "Feature",
  "properties": {
    "date:inception_lower": "1980-01-01",
    "date:inception_upper": "1980-01-01",
    "iso:country": "GB",
    "wof:name": "B65 8BS",
    "wof:placetype": "postalcode"
  },
  "geometry": {"coordinates":[-2.046549,52.477181],"type":"Point"}
}
