{
  "type": "Feature",
  "properties": {
    "iso:country":"GB",
    "wof:name":"L40 3SG",
    "wof:placetype":"postalcode"
},
  "geometry": {"coordinates":[-2.77302754748606,53.61463820261338],"type":"Point"}
}