{
  "type": "Feature",
  "properties": {
    "iso:country":"GB",
    "wof:name":"LL33 0PF",
    "wof:placetype":"postalcode"
},
  "geometry": {"coordinates":[-3.97324081788325,53.25876365314632],"type":"Point"}
}