{
  "type": "Feature",
  "properties": {
    "iso:country":"GB",
    "wof:name":"BN2 1DU",
    "wof:placetype":"postalcode"
},
  "geometry": {"coordinates":[-0.11937155619159,50.81764392378784],"type":"Point"}
}