{
  "type": "Feature",
  "properties": {
    "iso:country":"GB",
    "wof:name":"L13 7HU",
    "wof:placetype":"postalcode"
},
  "geometry": {"coordinates":[-2.91910417017831,53.42406918162285],"type":"Point"}
}