{
  "type": "Feature",
  "properties": {
    "iso:country": "GB",
    "wof:name": "L13 7HU",
    "wof:placetype": "postalcode"
  },
  "geometry": {"coordinates":[-2.919104,53.424069],"type":"Point"}
}
