{
  "type": "Feature",
  "properties": {
    "date:inception_lower": "1983-03-01",
    "date:inception_upper": "1983-03-01",
    "iso:country": "GB",
    "wof:name": "L13 7HU",
    "wof:placetype": "postalcode"
  },
  "geometry": {"coordinates":[-2.919104,53.424069],"type":"Point"}
}
