{
  "type": "Feature",
  "properties": {
    "date:inception_lower":"1991-01-01",
    "date:inception_upper":"1991-01-31",
    "iso:country":"GB",
    "wof:name":"SG6 1UJ",
    "wof:placetype":"postalcode"
},
  "geometry": {"coordinates":[-0.220821,51.984736],"type":"Point"}
}