{
  "type": "Feature",
  "properties": {
    "iso:country":"GB",
    "wof:name":"SG6 1UJ",
    "wof:placetype":"postalcode"
},
  "geometry": {"coordinates":[-0.22039243812222,51.98483700313719],"type":"Point"}
}