{
  "type": "Feature",
  "properties": {
    "date:inception_lower": "2016-07-01",
    "date:inception_upper": "2016-07-01",
    "iso:country": "GB",
    "wof:name": "HP19 8JP",
    "wof:placetype": "postalcode"
  },
  "geometry": {"coordinates":[-0.828441,51.822014],"type":"Point"}
}
