{
  "type": "Feature",
  "properties": {
    "iso:country": "GB",
    "wof:name": "IV6 7RB",
    "wof:placetype": "postalcode"
  },
  "geometry": {"coordinates":[-4.410104,57.53817],"type":"Point"}
}
