{
  "type": "Feature",
  "properties": {
    "iso:country":"GB",
    "wof:name":"IV6 7RB",
    "wof:placetype":"postalcode"
},
  "geometry": {"coordinates":[-4.41028147090433,57.53805821084154],"type":"Point"}
}