{
  "type": "Feature",
  "properties": {
    "iso:country":"GB",
    "wof:name":"KT6 6PG",
    "wof:placetype":"postalcode"
},
  "geometry": {"coordinates":[-0.3083973175001,51.38785504724528],"type":"Point"}
}