{
  "type": "Feature",
  "properties": {
    "iso:country": "GB",
    "wof:name": "HP27 0AP",
    "wof:placetype": "postalcode"
  },
  "geometry": {"coordinates":[-0.832326,51.724182],"type":"Point"}
}
