{
  "type": "Feature",
  "properties": {
    "iso:country":"GB",
    "wof:name":"HP27 0AP",
    "wof:placetype":"postalcode"
},
  "geometry": {"coordinates":[-0.83232563352824,51.72418233709863],"type":"Point"}
}