{
  "type": "Feature",
  "properties": {
    "iso:country":"GB",
    "wof:name":"LU3 4BD",
    "wof:placetype":"postalcode"
},
  "geometry": {"coordinates":[-0.43535845418334,51.91901371959872],"type":"Point"}
}