{
  "type": "Feature",
  "properties": {
    "date:inception_lower": "1999-06-01",
    "date:inception_upper": "1999-06-01",
    "iso:country": "GB",
    "wof:name": "NP12 2QJ",
    "wof:placetype": "postalcode"
  },
  "geometry": {"coordinates":[-3.20572,51.655807],"type":"Point"}
}
