{
  "type": "Feature",
  "properties": {
    "iso:country":"GB",
    "wof:name":"NP12 2QJ",
    "wof:placetype":"postalcode"
},
  "geometry": {"coordinates":[-3.2057201489728,51.65580703124913],"type":"Point"}
}