{
  "type": "Feature",
  "properties": {
    "iso:country":"GB",
    "wof:name":"WS7 1PT",
    "wof:placetype":"postalcode"
},
  "geometry": {"coordinates":[-1.93734531357857,52.69072959843654],"type":"Point"}
}