{
  "type": "Feature",
  "properties": {
    "iso:country":"GB",
    "wof:name":"OX5 2QX",
    "wof:placetype":"postalcode"
},
  "geometry": {"coordinates":[-1.19944642199812,51.82945949578231],"type":"Point"}
}