{
  "type": "Feature",
  "properties": {
    "date:inception_lower": "2019-04-01",
    "date:inception_upper": "2019-04-01",
    "iso:country": "GB",
    "wof:name": "RH12 3XQ",
    "wof:placetype": "postalcode"
  },
  "geometry": {"coordinates":[-0.441448,51.096089],"type":"Point"}
}
