{
  "type": "Feature",
  "properties": {
    "iso:country": "GB",
    "wof:name": "G81 6DB",
    "wof:placetype": "postalcode"
  },
  "geometry": {"coordinates":[-4.412948,55.921419],"type":"Point"}
}
