{
  "type": "Feature",
  "properties": {
    "iso:country":"GB",
    "wof:name":"M25 1PH",
    "wof:placetype":"postalcode"
},
  "geometry": {"coordinates":[-2.27082296211824,53.53410973956098],"type":"Point"}
}