{
  "type": "Feature",
  "properties": {
    "date:inception_lower": "1980-01-01",
    "date:inception_upper": "1980-01-01",
    "iso:country": "GB",
    "wof:name": "WN8 6JN",
    "wof:placetype": "postalcode"
  },
  "geometry": {"coordinates":[-2.79186,53.561213],"type":"Point"}
}
