{
  "type": "Feature",
  "properties": {
    "iso:country": "GB",
    "wof:name": "E2 8RA",
    "wof:placetype": "postalcode"
  },
  "geometry": {"coordinates":[-0.064873,51.533086],"type":"Point"}
}
