{
  "type": "Feature",
  "properties": {
    "date:inception_lower": "2008-09-01",
    "date:inception_upper": "2008-09-01",
    "iso:country": "GB",
    "wof:name": "HX2 7BW",
    "wof:placetype": "postalcode"
  },
  "geometry": {"coordinates":[-1.920113,53.723347],"type":"Point"}
}
