{
  "type": "Feature",
  "properties": {
    "date:inception_lower":"2008-09-01",
    "date:inception_upper":"2008-09-30",
    "iso:country":"GB",
    "wof:name":"HX2 7BW",
    "wof:placetype":"postalcode"
},
  "geometry": {"coordinates":[-1.920143,53.723455],"type":"Point"}
}