{
  "type": "Feature",
  "properties": {
    "iso:country":"GB",
    "wof:name":"HX2 7BW",
    "wof:placetype":"postalcode"
},
  "geometry": {"coordinates":[-1.92014170476317,53.72343959043934],"type":"Point"}
}