{
  "type": "Feature",
  "properties": {
    "iso:country":"GB",
    "wof:name":"RH16 1JL",
    "wof:placetype":"postalcode"
},
  "geometry": {"coordinates":[-0.11452295843821,51.00370140747319],"type":"Point"}
}