{
  "type": "Feature",
  "properties": {
    "iso:country": "GB",
    "wof:name": "FK7 8JY",
    "wof:placetype": "postalcode"
  },
  "geometry": {"coordinates":[-3.908426,56.091078],"type":"Point"}
}
