{
  "type": "Feature",
  "properties": {
    "iso:country":"GB",
    "wof:name":"SE20 8LP",
    "wof:placetype":"postalcode"
},
  "geometry": {"coordinates":[-0.05725391611907,51.41325849565164],"type":"Point"}
}