{
  "type": "Feature",
  "properties": {
    "iso:country":"GB",
    "wof:name":"WD4 9AJ",
    "wof:placetype":"postalcode"
},
  "geometry": {"coordinates":[-0.46790708233581,51.68223943254699],"type":"Point"}
}