{
  "type": "Feature",
  "properties": {
    "date:inception_lower": "1994-12-01",
    "date:inception_upper": "1994-12-01",
    "iso:country": "GB",
    "wof:name": "M27 6ES",
    "wof:placetype": "postalcode"
  },
  "geometry": {"coordinates":[-2.342009,53.512166],"type":"Point"}
}
