{
  "type": "Feature",
  "properties": {
    "date:inception_lower": "1980-01-01",
    "date:inception_upper": "1980-01-01",
    "iso:country": "GB",
    "wof:name": "S63 7AQ",
    "wof:placetype": "postalcode"
  },
  "geometry": {"coordinates":[-1.335224,53.499717],"type":"Point"}
}
