{
  "type": "Feature",
  "properties": {
    "iso:country": "GB",
    "wof:name": "EH54 7FF",
    "wof:placetype": "postalcode"
  },
  "geometry": {"coordinates":[-3.531729,55.888884],"type":"Point"}
}
