{
  "type": "Feature",
  "properties": {
    "iso:country": "GB",
    "wof:name": "PA3 3FP",
    "wof:placetype": "postalcode"
  },
  "geometry": {"coordinates":[-4.476537,55.844032],"type":"Point"}
}
