{
  "type": "Feature",
  "properties": {
    "date:inception_lower": "2018-09-01",
    "date:inception_upper": "2018-09-01",
    "iso:country": "GB",
    "wof:name": "PA3 3FP",
    "wof:placetype": "postalcode"
  },
  "geometry": {"coordinates":[-4.480435,55.84479],"type":"Point"}
}
