{
  "type": "Feature",
  "properties": {
    "date:inception_lower": "2021-11-01",
    "date:inception_upper": "2021-11-01",
    "iso:country": "GB",
    "wof:name": "WS11 9BE",
    "wof:placetype": "postalcode"
  },
  "geometry": {"coordinates":[-1.978259,52.664825],"type":"Point"}
}
