{
  "type": "Feature",
  "properties": {
    "iso:country": "GB",
    "wof:name": "HD9 1WA",
    "wof:placetype": "postalcode"
  },
  "geometry": {"coordinates":[-1.773004,53.559673],"type":"Point"}
}
