{
  "type": "Feature",
  "properties": {
    "iso:country": "GB",
    "wof:name": "DD8 3JQ",
    "wof:placetype": "postalcode"
  },
  "geometry": {"coordinates":[-2.892226,56.651129],"type":"Point"}
}
