{
  "type": "Feature",
  "properties": {
    "iso:country":"GB",
    "wof:name":"DD8 3JQ",
    "wof:placetype":"postalcode"
},
  "geometry": {"coordinates":[-2.89222609258723,56.65112920273565],"type":"Point"}
}