{
  "type": "Feature",
  "properties": {
    "iso:country": "GB",
    "wof:name": "TW11 8SA",
    "wof:placetype": "postalcode"
  },
  "geometry": {"coordinates":[-0.342064,51.429396],"type":"Point"}
}
