{
  "type": "Feature",
  "properties": {
    "date:inception_lower": "1997-06-01",
    "date:inception_upper": "1997-06-01",
    "iso:country": "GB",
    "wof:name": "TW11 8SA",
    "wof:placetype": "postalcode"
  },
  "geometry": {"coordinates":[-0.342064,51.429396],"type":"Point"}
}
