{
  "type": "Feature",
  "properties": {
    "iso:country":"GB",
    "wof:name":"EH11 1NN",
    "wof:placetype":"postalcode"
},
  "geometry": {"coordinates":[-3.22706581699786,55.93016683559949],"type":"Point"}
}