{
  "type": "Feature",
  "properties": {
    "iso:country": "GB",
    "wof:name": "WA5 9JG",
    "wof:placetype": "postalcode"
  },
  "geometry": {"coordinates":[-2.617915,53.411239],"type":"Point"}
}
