{
  "type": "Feature",
  "properties": {
    "date:inception_lower":"1980-01-01",
    "date:inception_upper":"1980-01-31",
    "iso:country":"GB",
    "wof:name":"PR4 3HD",
    "wof:placetype":"postalcode"
},
  "geometry": {"coordinates":[-2.887614,53.798357],"type":"Point"}
}