{
  "type": "Feature",
  "properties": {
    "iso:country": "GB",
    "wof:name": "EN7 6XJ",
    "wof:placetype": "postalcode"
  },
  "geometry": {"coordinates":[-0.078591,51.720677],"type":"Point"}
}
