{
  "type": "Feature",
  "properties": {
    "iso:country":"GB",
    "wof:name":"SS1 3AR",
    "wof:placetype":"postalcode"
},
  "geometry": {"coordinates":[0.75651336834516,51.53695394027177],"type":"Point"}
}