{
  "type": "Feature",
  "properties": {
    "date:inception_lower": "1980-04-01",
    "date:inception_upper": "1980-04-01",
    "iso:country": "GB",
    "wof:name": "G83 0HS",
    "wof:placetype": "postalcode"
  },
  "geometry": {"coordinates":[-4.593405,55.9937],"type":"Point"}
}
