{
  "type": "Feature",
  "properties": {
    "date:inception_lower": "1999-06-01",
    "date:inception_upper": "1999-06-01",
    "iso:country": "GB",
    "wof:name": "NP11 4FZ",
    "wof:placetype": "postalcode"
  },
  "geometry": {"coordinates":[-3.149752,51.66349],"type":"Point"}
}
