{
  "type": "Feature",
  "properties": {
    "iso:country":"GB",
    "wof:name":"NP11 4FZ",
    "wof:placetype":"postalcode"
},
  "geometry": {"coordinates":[-3.14975229673457,51.66348982177659],"type":"Point"}
}