{
  "type": "Feature",
  "properties": {
    "iso:country": "GB",
    "wof:name": "CV21 1LU",
    "wof:placetype": "postalcode"
  },
  "geometry": {"coordinates":[-1.249165,52.392786],"type":"Point"}
}
