{
  "type": "Feature",
  "properties": {
    "date:inception_lower": "2012-09-01",
    "date:inception_upper": "2012-09-01",
    "iso:country": "GB",
    "wof:name": "GL17 9DN",
    "wof:placetype": "postalcode"
  },
  "geometry": {"coordinates":[-2.575343,51.84631],"type":"Point"}
}
