{
  "type": "Feature",
  "properties": {
    "iso:country":"GB",
    "wof:name":"S44 5NG",
    "wof:placetype":"postalcode"
},
  "geometry": {"coordinates":[-1.28664583963482,53.18496288382581],"type":"Point"}
}