{
  "type": "Feature",
  "properties": {
    "iso:country":"GB",
    "wof:name":"E18 2AL",
    "wof:placetype":"postalcode"
},
  "geometry": {"coordinates":[0.0246448698851,51.59043159056802],"type":"Point"}
}