{
  "type": "Feature",
  "properties": {
    "iso:country":"GB",
    "wof:name":"CT10 2WA",
    "wof:placetype":"postalcode"
},
  "geometry": {"coordinates":[1.40697993831603,51.35990258409871],"type":"Point"}
}