{
  "type": "Feature",
  "properties": {
    "date:inception_lower": "2017-06-01",
    "date:inception_upper": "2017-06-01",
    "iso:country": "GB",
    "wof:name": "NE13 7GD",
    "wof:placetype": "postalcode"
  },
  "geometry": {"coordinates":[-1.640814,55.045796],"type":"Point"}
}
