{
  "type": "Feature",
  "properties": {
    "iso:country":"GB",
    "wof:name":"SO23 7EF",
    "wof:placetype":"postalcode"
},
  "geometry": {"coordinates":[-1.31123295206199,51.07036060448328],"type":"Point"}
}