{
  "type": "Feature",
  "properties": {
    "iso:country":"GB",
    "wof:name":"DG2 8EA",
    "wof:placetype":"postalcode"
},
  "geometry": {"coordinates":[-3.68607656419217,54.98459482622662],"type":"Point"}
}