{
  "type": "Feature",
  "properties": {
    "iso:country": "GB",
    "wof:name": "DG2 8EA",
    "wof:placetype": "postalcode"
  },
  "geometry": {"coordinates":[-3.685587,54.988215],"type":"Point"}
}
