{
  "type": "Feature",
  "properties": {
    "iso:country": "GB",
    "wof:name": "SY23 1HS",
    "wof:placetype": "postalcode"
  },
  "geometry": {"coordinates":[-4.083609,52.414571],"type":"Point"}
}
