{
  "type": "Feature",
  "properties": {
    "iso:country":"GB",
    "wof:name":"SY23 1HS",
    "wof:placetype":"postalcode"
},
  "geometry": {"coordinates":[-4.08360934548182,52.41457052847883],"type":"Point"}
}