{
  "type": "Feature",
  "properties": {
    "iso:country": "GB",
    "wof:name": "BS5 9LF",
    "wof:placetype": "postalcode"
  },
  "geometry": {"coordinates":[-2.557736,51.457916],"type":"Point"}
}
