{
  "type": "Feature",
  "properties": {
    "iso:country": "GB",
    "wof:name": "B64 6RE",
    "wof:placetype": "postalcode"
  },
  "geometry": {"coordinates":[-2.053146,52.473522],"type":"Point"}
}
