{
  "type": "Feature",
  "properties": {
    "date:inception_lower":"1980-01-01",
    "date:inception_upper":"1980-01-31",
    "iso:country":"GB",
    "wof:name":"PO6 3SB",
    "wof:placetype":"postalcode"
},
  "geometry": {"coordinates":[-1.082058,50.852039],"type":"Point"}
}