{
  "type": "Feature",
  "properties": {
    "iso:country":"GB",
    "wof:name":"TR2 5TW",
    "wof:placetype":"postalcode"
},
  "geometry": {"coordinates":[-4.90924178118115,50.26965814601781],"type":"Point"}
}