{
  "type": "Feature",
  "properties": {
    "iso:country":"GB",
    "wof:name":"WC1B 4JP",
    "wof:placetype":"postalcode"
},
  "geometry": {"coordinates":[-0.12584301046264,51.52058690572679],"type":"Point"}
}