{
  "type": "Feature",
  "properties": {
    "date:inception_lower": "1980-01-01",
    "date:inception_upper": "1980-01-01",
    "iso:country": "GB",
    "wof:name": "WC1B 4JP",
    "wof:placetype": "postalcode"
  },
  "geometry": {"coordinates":[-0.12554,51.520683],"type":"Point"}
}
