{
  "type": "Feature",
  "properties": {
    "date:inception_lower": "1980-01-01",
    "date:inception_upper": "1980-01-01",
    "iso:country": "GB",
    "wof:name": "M33 3HU",
    "wof:placetype": "postalcode"
  },
  "geometry": {"coordinates":[-2.306747,53.417343],"type":"Point"}
}
