{
  "type": "Feature",
  "properties": {
    "iso:country": "GB",
    "wof:name": "CF48 2HH",
    "wof:placetype": "postalcode"
  },
  "geometry": {"coordinates":[-3.404252,51.765701],"type":"Point"}
}
