{
  "type": "Feature",
  "properties": {
    "iso:country":"GB",
    "wof:name":"CF48 2HH",
    "wof:placetype":"postalcode"
},
  "geometry": {"coordinates":[-3.40425214695837,51.76570065695842],"type":"Point"}
}