{
  "type": "Feature",
  "properties": {
    "date:inception_lower":"2008-09-01",
    "date:inception_upper":"2008-09-30",
    "iso:country":"GB",
    "wof:name":"CF48 2HH",
    "wof:placetype":"postalcode"
},
  "geometry": {"coordinates":[-3.404252,51.765701],"type":"Point"}
}