{
  "type": "Feature",
  "properties": {
    "iso:country":"GB",
    "wof:name":"GL15 6AY",
    "wof:placetype":"postalcode"
},
  "geometry": {"coordinates":[-2.57564668204936,51.70499486004832],"type":"Point"}
}