{
  "type": "Feature",
  "properties": {
    "iso:country": "GB",
    "wof:name": "SO31 5HB",
    "wof:placetype": "postalcode"
  },
  "geometry": {"coordinates":[-1.356065,50.879941],"type":"Point"}
}
