{
  "type": "Feature",
  "properties": {
    "date:inception_lower":"2004-11-01",
    "date:inception_upper":"2004-11-30",
    "iso:country":"GB",
    "wof:name":"SO31 5HB",
    "wof:placetype":"postalcode"
},
  "geometry": {"coordinates":[-1.356065,50.879941],"type":"Point"}
}