{
  "type": "Feature",
  "properties": {
    "date:inception_lower": "1980-01-01",
    "date:inception_upper": "1980-01-01",
    "iso:country": "GB",
    "wof:name": "SE17 3LH",
    "wof:placetype": "postalcode"
  },
  "geometry": {"coordinates":[-0.100163,51.490282],"type":"Point"}
}
