{
  "type": "Feature",
  "properties": {
    "date:inception_lower":"1980-01-01",
    "date:inception_upper":"1980-01-31",
    "iso:country":"GB",
    "wof:name":"S2 4NS",
    "wof:placetype":"postalcode"
},
  "geometry": {"coordinates":[-1.476979,53.368226],"type":"Point"}
}