{
  "type": "Feature",
  "properties": {
    "iso:country": "GB",
    "wof:name": "AL5 1TH",
    "wof:placetype": "postalcode"
  },
  "geometry": {"coordinates":[-0.341974,51.806444],"type":"Point"}
}
