{
  "type": "Feature",
  "properties": {
    "iso:country": "GB",
    "wof:name": "WV3 0HU",
    "wof:placetype": "postalcode"
  },
  "geometry": {"coordinates":[-2.143303,52.577371],"type":"Point"}
}
