{
  "type": "Feature",
  "properties": {
    "iso:country":"GB",
    "wof:name":"G31 5EL",
    "wof:placetype":"postalcode"
},
  "geometry": {"coordinates":[-4.19595798805108,55.85150636004482],"type":"Point"}
}