{
  "type": "Feature",
  "properties": {
    "iso:country":"GB",
    "wof:name":"CT9 3YJ",
    "wof:placetype":"postalcode"
},
  "geometry": {"coordinates":[1.42716470183746,51.38410405420463],"type":"Point"}
}