{
  "type": "Feature",
  "properties": {
    "date:inception_lower":"1986-07-01",
    "date:inception_upper":"1986-07-31",
    "iso:country":"GB",
    "wof:name":"CT9 3YJ",
    "wof:placetype":"postalcode"
},
  "geometry": {"coordinates":[1.427165,51.384104],"type":"Point"}
}