{
  "type": "Feature",
  "properties": {
    "iso:country": "GB",
    "wof:name": "CT9 3YJ",
    "wof:placetype": "postalcode"
  },
  "geometry": {"coordinates":[1.427165,51.384104],"type":"Point"}
}
