{
  "type": "Feature",
  "properties": {
    "date:inception_lower": "1999-06-01",
    "date:inception_upper": "1999-06-01",
    "iso:country": "GB",
    "wof:name": "DN37 9TT",
    "wof:placetype": "postalcode"
  },
  "geometry": {"coordinates":[-0.130112,53.585612],"type":"Point"}
}
