{
  "type": "Feature",
  "properties": {
    "iso:country": "GB",
    "wof:name": "SA33 6UA",
    "wof:placetype": "postalcode"
  },
  "geometry": {"coordinates":[-4.405551,51.937416],"type":"Point"}
}
