{
  "type": "Feature",
  "properties": {
    "iso:country":"GB",
    "wof:name":"SA33 6UA",
    "wof:placetype":"postalcode"
},
  "geometry": {"coordinates":[-4.40555071176152,51.93741589988887],"type":"Point"}
}