{
  "type": "Feature",
  "properties": {
    "iso:country":"GB",
    "wof:name":"CV1 4JQ",
    "wof:placetype":"postalcode"
},
  "geometry": {"coordinates":[-1.50584758122551,52.42305802019111],"type":"Point"}
}