{
  "type": "Feature",
  "properties": {
    "date:inception_lower": "1980-01-01",
    "date:inception_upper": "1980-01-01",
    "iso:country": "GB",
    "wof:name": "CV1 4JQ",
    "wof:placetype": "postalcode"
  },
  "geometry": {"coordinates":[-1.505848,52.423058],"type":"Point"}
}
