{
  "type": "Feature",
  "properties": {
    "iso:country":"GB",
    "wof:name":"PL19 9ER",
    "wof:placetype":"postalcode"
},
  "geometry": {"coordinates":[-4.12681505215889,50.52465415153221],"type":"Point"}
}