{
  "type": "Feature",
  "properties": {
    "iso:country": "GB",
    "wof:name": "PL19 9ER",
    "wof:placetype": "postalcode"
  },
  "geometry": {"coordinates":[-4.126815,50.524654],"type":"Point"}
}
