{
  "type": "Feature",
  "properties": {
    "iso:country":"GB",
    "wof:name":"CR0 6UU",
    "wof:placetype":"postalcode"
},
  "geometry": {"coordinates":[-0.08607271561598,51.37813048228359],"type":"Point"}
}