{
  "type": "Feature",
  "properties": {
    "iso:country":"GB",
    "wof:name":"PO18 8JX",
    "wof:placetype":"postalcode"
},
  "geometry": {"coordinates":[-0.84159929534395,50.84481047871535],"type":"Point"}
}