{
  "type": "Feature",
  "properties": {
    "date:inception_lower": "2020-06-01",
    "date:inception_upper": "2020-06-01",
    "iso:country": "GB",
    "wof:name": "LL57 2JE",
    "wof:placetype": "postalcode"
  },
  "geometry": {"coordinates":[-4.167504,53.207953],"type":"Point"}
}
