{
  "type": "Feature",
  "properties": {
    "iso:country": "GB",
    "wof:name": "CH65 7AY",
    "wof:placetype": "postalcode"
  },
  "geometry": {"coordinates":[-2.919237,53.272451],"type":"Point"}
}
