{
  "type": "Feature",
  "properties": {
    "iso:country":"GB",
    "wof:name":"CH65 7AY",
    "wof:placetype":"postalcode"
},
  "geometry": {"coordinates":[-2.91923682032121,53.27245125440635],"type":"Point"}
}