{
  "type": "Feature",
  "properties": {
    "iso:country":"GB",
    "wof:name":"NE61 2QG",
    "wof:placetype":"postalcode"
},
  "geometry": {"coordinates":[-1.69259672100733,55.16099722874855],"type":"Point"}
}