{
  "type": "Feature",
  "properties": {
    "iso:country":"GB",
    "wof:name":"CH5 4YW",
    "wof:placetype":"postalcode"
},
  "geometry": {"coordinates":[-3.06597451196397,53.22204935655356],"type":"Point"}
}