{
  "type": "Feature",
  "properties": {
    "date:inception_lower": "2018-09-01",
    "date:inception_upper": "2018-09-01",
    "iso:country": "GB",
    "wof:name": "CV10 7FA",
    "wof:placetype": "postalcode"
  },
  "geometry": {"coordinates":[-1.473591,52.515579],"type":"Point"}
}
