{
  "type": "Feature",
  "properties": {
    "date:inception_lower":"1990-08-01",
    "date:inception_upper":"1990-08-31",
    "iso:country":"GB",
    "wof:name":"AB53 8HG",
    "wof:placetype":"postalcode"
},
  "geometry": {"coordinates":[-2.417043,57.476977],"type":"Point"}
}