{
  "type": "Feature",
  "properties": {
    "date:inception_lower": "1980-01-01",
    "date:inception_upper": "1980-01-01",
    "iso:country": "GB",
    "wof:name": "EH7 6HS",
    "wof:placetype": "postalcode"
  },
  "geometry": {"coordinates":[-3.151107,55.961109],"type":"Point"}
}
