{
  "type": "Feature",
  "properties": {
    "iso:country":"GB",
    "wof:name":"NG32 1LH",
    "wof:placetype":"postalcode"
},
  "geometry": {"coordinates":[-0.7129308008194,52.88289242454793],"type":"Point"}
}