{
  "type": "Feature",
  "properties": {
    "iso:country": "GB",
    "wof:name": "NG32 1LH",
    "wof:placetype": "postalcode"
  },
  "geometry": {"coordinates":[-0.713044,52.883091],"type":"Point"}
}
