{
  "type": "Feature",
  "properties": {
    "iso:country":"GB",
    "wof:name":"KY16 9QW",
    "wof:placetype":"postalcode"
},
  "geometry": {"coordinates":[-2.79421133537138,56.33977781589423],"type":"Point"}
}