{
  "type": "Feature",
  "properties": {
    "date:inception_lower":"1980-01-01",
    "date:inception_upper":"1980-01-31",
    "iso:country":"GB",
    "wof:name":"KY16 9QW",
    "wof:placetype":"postalcode"
},
  "geometry": {"coordinates":[-2.794112,56.33968],"type":"Point"}
}