{
  "type": "Feature",
  "properties": {
    "date:inception_lower":"1980-01-01",
    "date:inception_upper":"1980-01-31",
    "iso:country":"GB",
    "wof:name":"CB11 3PG",
    "wof:placetype":"postalcode"
},
  "geometry": {"coordinates":[0.213654,51.981317],"type":"Point"}
}