{
  "type": "Feature",
  "properties": {
    "date:inception_lower": "1996-12-01",
    "date:inception_upper": "1996-12-01",
    "iso:country": "GB",
    "wof:name": "HU13 9LY",
    "wof:placetype": "postalcode"
  },
  "geometry": {"coordinates":[-0.426848,53.72196],"type":"Point"}
}
