{
  "type": "Feature",
  "properties": {
    "date:inception_lower": "1980-01-01",
    "date:inception_upper": "1980-01-01",
    "iso:country": "GB",
    "wof:name": "SK12 1XH",
    "wof:placetype": "postalcode"
  },
  "geometry": {"coordinates":[-2.143583,53.348727],"type":"Point"}
}
