{
  "type": "Feature",
  "properties": {
    "iso:country":"GB",
    "wof:name":"OL12 9NH",
    "wof:placetype":"postalcode"
},
  "geometry": {"coordinates":[-2.13442995532347,53.65155719897449],"type":"Point"}
}