{
  "type": "Feature",
  "properties": {
    "iso:country": "GB",
    "wof:name": "DL10 7NE",
    "wof:placetype": "postalcode"
  },
  "geometry": {"coordinates":[-1.631646,54.375601],"type":"Point"}
}
