{
  "type": "Feature",
  "properties": {
    "date:inception_lower":"1980-01-01",
    "date:inception_upper":"1980-01-31",
    "iso:country":"GB",
    "wof:name":"DL10 7NE",
    "wof:placetype":"postalcode"
},
  "geometry": {"coordinates":[-1.631646,54.375601],"type":"Point"}
}