{
  "type": "Feature",
  "properties": {
    "iso:country":"GB",
    "wof:name":"DL10 7NE",
    "wof:placetype":"postalcode"
},
  "geometry": {"coordinates":[-1.6316463236715,54.37560066685473],"type":"Point"}
}