{
  "type": "Feature",
  "properties": {
    "iso:country":"GB",
    "wof:name":"HP9 1RW",
    "wof:placetype":"postalcode"
},
  "geometry": {"coordinates":[-0.64104946256088,51.60451358393932],"type":"Point"}
}