{
  "type": "Feature",
  "properties": {
    "iso:country":"GB",
    "wof:name":"SO40 7JY",
    "wof:placetype":"postalcode"
},
  "geometry": {"coordinates":[-1.50206160313811,50.91135539196141],"type":"Point"}
}