{
  "type": "Feature",
  "properties": {
    "date:inception_lower":"1999-06-01",
    "date:inception_upper":"1999-06-30",
    "iso:country":"GB",
    "wof:name":"TA7 9RY",
    "wof:placetype":"postalcode"
},
  "geometry": {"coordinates":[-2.906874,51.140807],"type":"Point"}
}