{
  "type": "Feature",
  "properties": {
    "iso:country":"GB",
    "wof:name":"TA7 9RY",
    "wof:placetype":"postalcode"
},
  "geometry": {"coordinates":[-2.9068740572931,51.14080686563279],"type":"Point"}
}