{
  "type": "Feature",
  "properties": {
    "iso:country":"GB",
    "wof:name":"DA17 5PQ",
    "wof:placetype":"postalcode"
},
  "geometry": {"coordinates":[0.13706056276086,51.47797939977945],"type":"Point"}
}