{
  "type": "Feature",
  "properties": {
    "iso:country": "GB",
    "wof:name": "TW16 7QD",
    "wof:placetype": "postalcode"
  },
  "geometry": {"coordinates":[-0.419934,51.425975],"type":"Point"}
}
