{
  "type": "Feature",
  "properties": {
    "iso:country": "GB",
    "wof:name": "DL16 7HF",
    "wof:placetype": "postalcode"
  },
  "geometry": {"coordinates":[-1.595758,54.684313],"type":"Point"}
}
