{
  "type": "Feature",
  "properties": {
    "iso:country":"GB",
    "wof:name":"LE16 7QB",
    "wof:placetype":"postalcode"
},
  "geometry": {"coordinates":[-0.94233640703798,52.49788354120105],"type":"Point"}
}