{
  "type": "Feature",
  "properties": {
    "date:inception_lower": "2003-04-01",
    "date:inception_upper": "2003-04-01",
    "iso:country": "GB",
    "wof:name": "LE16 7QB",
    "wof:placetype": "postalcode"
  },
  "geometry": {"coordinates":[-0.942324,52.4979],"type":"Point"}
}
