{
  "type": "Feature",
  "properties": {
    "iso:country":"GB",
    "wof:name":"CV12 2BY",
    "wof:placetype":"postalcode"
},
  "geometry": {"coordinates":[-1.47040594654428,52.47967716350393],"type":"Point"}
}