{
  "type": "Feature",
  "properties": {
    "iso:country":"GB",
    "wof:name":"PR7 2LN",
    "wof:placetype":"postalcode"
},
  "geometry": {"coordinates":[-2.63888172961,53.64238587955369],"type":"Point"}
}