{
  "type": "Feature",
  "properties": {
    "iso:country": "GB",
    "wof:name": "PR7 2LN",
    "wof:placetype": "postalcode"
  },
  "geometry": {"coordinates":[-2.638882,53.642386],"type":"Point"}
}
