{
  "type": "Feature",
  "properties": {
    "iso:country":"GB",
    "wof:name":"FY2 0ND",
    "wof:placetype":"postalcode"
},
  "geometry": {"coordinates":[-3.03396350403499,53.84664731318071],"type":"Point"}
}