{
  "type": "Feature",
  "properties": {
    "date:inception_lower": "2005-04-01",
    "date:inception_upper": "2005-04-01",
    "iso:country": "GB",
    "wof:name": "FY2 0ND",
    "wof:placetype": "postalcode"
  },
  "geometry": {"coordinates":[-3.033963,53.846647],"type":"Point"}
}
