{
  "type": "Feature",
  "properties": {
    "iso:country":"GB",
    "wof:name":"NE48 3NX",
    "wof:placetype":"postalcode"
},
  "geometry": {"coordinates":[-2.16770646915871,55.07924427554702],"type":"Point"}
}