{
  "type": "Feature",
  "properties": {
    "iso:country":"GB",
    "wof:name":"BB9 8AA",
    "wof:placetype":"postalcode"
},
  "geometry": {"coordinates":[-2.20381454021171,53.83979467124076],"type":"Point"}
}