{
  "type": "Feature",
  "properties": {
    "date:inception_lower":"1980-01-01",
    "date:inception_upper":"1980-01-31",
    "iso:country":"GB",
    "wof:name":"BB9 8AA",
    "wof:placetype":"postalcode"
},
  "geometry": {"coordinates":[-2.203814,53.839795],"type":"Point"}
}