{
  "type": "Feature",
  "properties": {
    "date:inception_lower": "1995-01-01",
    "date:inception_upper": "1995-01-01",
    "iso:country": "GB",
    "wof:name": "TQ9 7AX",
    "wof:placetype": "postalcode"
  },
  "geometry": {"coordinates":[-3.682166,50.343465],"type":"Point"}
}
