{
  "type": "Feature",
  "properties": {
    "date:inception_lower": "1980-01-01",
    "date:inception_upper": "1980-01-01",
    "iso:country": "GB",
    "wof:name": "NR33 0PX",
    "wof:placetype": "postalcode"
  },
  "geometry": {"coordinates":[1.741645,52.469411],"type":"Point"}
}
