{
  "type": "Feature",
  "properties": {
    "iso:country":"GB",
    "wof:name":"NE28 7EF",
    "wof:placetype":"postalcode"
},
  "geometry": {"coordinates":[-1.50846343966786,55.00094413816208],"type":"Point"}
}