{
  "type": "Feature",
  "properties": {
    "iso:country": "GB",
    "wof:name": "NE28 7EF",
    "wof:placetype": "postalcode"
  },
  "geometry": {"coordinates":[-1.508463,55.000944],"type":"Point"}
}
