{
  "type": "Feature",
  "properties": {
    "iso:country":"GB",
    "wof:name":"DG11 1AQ",
    "wof:placetype":"postalcode"
},
  "geometry": {"coordinates":[-3.30550006812558,55.06969986063874],"type":"Point"}
}