{
  "type": "Feature",
  "properties": {
    "iso:country":"GB",
    "wof:name":"LS18 5HW",
    "wof:placetype":"postalcode"
},
  "geometry": {"coordinates":[-1.63801399083655,53.85790217781837],"type":"Point"}
}