{
  "type": "Feature",
  "properties": {
    "iso:country":"GB",
    "wof:name":"ST7 3AY",
    "wof:placetype":"postalcode"
},
  "geometry": {"coordinates":[-2.25405752560208,53.09666602774185],"type":"Point"}
}