{
  "type": "Feature",
  "properties": {
    "iso:country": "GB",
    "wof:name": "UB7 7ED",
    "wof:placetype": "postalcode"
  },
  "geometry": {"coordinates":[-0.479533,51.498856],"type":"Point"}
}
