{
  "type": "Feature",
  "properties": {
    "iso:country":"GB",
    "wof:name":"UB7 7ED",
    "wof:placetype":"postalcode"
},
  "geometry": {"coordinates":[-0.47946471671081,51.49890696885615],"type":"Point"}
}