{
  "type": "Feature",
  "properties": {
    "date:inception_lower":"1999-12-01",
    "date:inception_upper":"1999-12-31",
    "iso:country":"GB",
    "wof:name":"UB7 7ED",
    "wof:placetype":"postalcode"
},
  "geometry": {"coordinates":[-0.479533,51.498856],"type":"Point"}
}