{
  "type": "Feature",
  "properties": {
    "date:inception_lower": "1991-09-01",
    "date:inception_upper": "1991-09-01",
    "iso:country": "GB",
    "wof:name": "IP31 3QW",
    "wof:placetype": "postalcode"
  },
  "geometry": {"coordinates":[0.812175,52.248937],"type":"Point"}
}
