{
  "type": "Feature",
  "properties": {
    "iso:country":"GB",
    "wof:name":"IP31 3QW",
    "wof:placetype":"postalcode"
},
  "geometry": {"coordinates":[0.81215770690809,52.24889298434098],"type":"Point"}
}