{
  "type": "Feature",
  "properties": {
    "iso:country": "GB",
    "wof:name": "NR29 5JD",
    "wof:placetype": "postalcode"
  },
  "geometry": {"coordinates":[1.580128,52.710825],"type":"Point"}
}
