{
  "type": "Feature",
  "properties": {
    "date:inception_lower":"1980-01-01",
    "date:inception_upper":"1980-01-31",
    "iso:country":"GB",
    "wof:name":"LS27 7PU",
    "wof:placetype":"postalcode"
},
  "geometry": {"coordinates":[-1.59153,53.758937],"type":"Point"}
}