{
  "type": "Feature",
  "properties": {
    "iso:country":"GB",
    "wof:name":"LS27 7PU",
    "wof:placetype":"postalcode"
},
  "geometry": {"coordinates":[-1.59106973013364,53.75909013877769],"type":"Point"}
}