{
  "type": "Feature",
  "properties": {
    "iso:country": "GB",
    "wof:name": "LS27 7PU",
    "wof:placetype": "postalcode"
  },
  "geometry": {"coordinates":[-1.59153,53.758937],"type":"Point"}
}
