{
  "type": "Feature",
  "properties": {
    "date:inception_lower": "1980-01-01",
    "date:inception_upper": "1980-01-01",
    "iso:country": "GB",
    "wof:name": "IG8 7JX",
    "wof:placetype": "postalcode"
  },
  "geometry": {"coordinates":[0.040318,51.603246],"type":"Point"}
}
