{
  "type": "Feature",
  "properties": {
    "iso:country": "GB",
    "wof:name": "CB4 2ZD",
    "wof:placetype": "postalcode"
  },
  "geometry": {"coordinates":[0.118496,52.234741],"type":"Point"}
}
