{
  "type": "Feature",
  "properties": {
    "iso:country":"GB",
    "wof:name":"BA7 7NN",
    "wof:placetype":"postalcode"
},
  "geometry": {"coordinates":[-2.50305069669018,51.08737364733958],"type":"Point"}
}