{
  "type": "Feature",
  "properties": {
    "date:inception_lower":"1999-12-01",
    "date:inception_upper":"1999-12-31",
    "iso:country":"GB",
    "wof:name":"BA7 7NN",
    "wof:placetype":"postalcode"
},
  "geometry": {"coordinates":[-2.503051,51.087374],"type":"Point"}
}