{
  "type": "Feature",
  "properties": {
    "iso:country":"GB",
    "wof:name":"CA1 2RX",
    "wof:placetype":"postalcode"
},
  "geometry": {"coordinates":[-2.90445929818594,54.89417476372172],"type":"Point"}
}