{
  "type": "Feature",
  "properties": {
    "iso:country":"GB",
    "wof:name":"WA12 9JT",
    "wof:placetype":"postalcode"
},
  "geometry": {"coordinates":[-2.65767551623193,53.45211421525618],"type":"Point"}
}