{
  "type": "Feature",
  "properties": {
    "iso:country": "GB",
    "wof:name": "WA12 9JT",
    "wof:placetype": "postalcode"
  },
  "geometry": {"coordinates":[-2.657675,53.452114],"type":"Point"}
}
