{
  "type": "Feature",
  "properties": {
    "date:inception_lower":"1980-01-01",
    "date:inception_upper":"1980-01-31",
    "iso:country":"GB",
    "wof:name":"WA12 9JT",
    "wof:placetype":"postalcode"
},
  "geometry": {"coordinates":[-2.657675,53.452114],"type":"Point"}
}