{
  "type": "Feature",
  "properties": {
    "iso:country": "GB",
    "wof:name": "EX17 5NY",
    "wof:placetype": "postalcode"
  },
  "geometry": {"coordinates":[-3.72833,50.827438],"type":"Point"}
}
