{
  "type": "Feature",
  "properties": {
    "iso:country":"GB",
    "wof:name":"NG9 6AW",
    "wof:placetype":"postalcode"
},
  "geometry": {"coordinates":[-1.22827606081572,52.90633480939131],"type":"Point"}
}