{
  "type": "Feature",
  "properties": {
    "iso:country":"GB",
    "wof:name":"LU2 9JH",
    "wof:placetype":"postalcode"
},
  "geometry": {"coordinates":[-0.3812498026525,51.88830370733172],"type":"Point"}
}