{
  "type": "Feature",
  "properties": {
    "iso:country": "GB",
    "wof:name": "LU2 9JH",
    "wof:placetype": "postalcode"
  },
  "geometry": {"coordinates":[-0.381836,51.888293],"type":"Point"}
}
