{
  "type": "Feature",
  "properties": {
    "iso:country": "GB",
    "wof:name": "TS10 1NJ",
    "wof:placetype": "postalcode"
  },
  "geometry": {"coordinates":[-1.07907,54.60819],"type":"Point"}
}
