{
  "type": "Feature",
  "properties": {
    "date:inception_lower": "1980-01-01",
    "date:inception_upper": "1980-01-01",
    "iso:country": "GB",
    "wof:name": "BL0 0AU",
    "wof:placetype": "postalcode"
  },
  "geometry": {"coordinates":[-2.30784,53.647318],"type":"Point"}
}
