{
  "type": "Feature",
  "properties": {
    "iso:country":"GB",
    "wof:name":"W6 9QR",
    "wof:placetype":"postalcode"
},
  "geometry": {"coordinates":[-0.22560508059809,51.48903734732384],"type":"Point"}
}