{
  "type": "Feature",
  "properties": {
    "iso:country":"GB",
    "wof:name":"BD22 7HY",
    "wof:placetype":"postalcode"
},
  "geometry": {"coordinates":[-1.9501258330396,53.84555741415317],"type":"Point"}
}