{
  "type": "Feature",
  "properties": {
    "iso:country":"GB",
    "wof:name":"L17 2AW",
    "wof:placetype":"postalcode"
},
  "geometry": {"coordinates":[-2.93313288205649,53.39123182317322],"type":"Point"}
}