{
  "type": "Feature",
  "properties": {
    "date:inception_lower": "2022-10-01",
    "date:inception_upper": "2022-10-01",
    "iso:country": "GB",
    "wof:name": "SS7 5FL",
    "wof:placetype": "postalcode"
  },
  "geometry": {"coordinates":[0.553091,51.56438],"type":"Point"}
}
