{
  "type": "Feature",
  "properties": {
    "iso:country":"GB",
    "wof:name":"WA7 2RS",
    "wof:placetype":"postalcode"
},
  "geometry": {"coordinates":[-2.70510783260432,53.31738049217916],"type":"Point"}
}