{
  "type": "Feature",
  "properties": {
    "iso:country":"GB",
    "wof:name":"SG8 6NT",
    "wof:placetype":"postalcode"
},
  "geometry": {"coordinates":[0.01427682501096,52.10384209844938],"type":"Point"}
}