{
  "type": "Feature",
  "properties": {
    "iso:country": "GB",
    "wof:name": "EH49 7RG",
    "wof:placetype": "postalcode"
  },
  "geometry": {"coordinates":[-3.615167,55.981658],"type":"Point"}
}
