{
  "type": "Feature",
  "properties": {
    "iso:country": "GB",
    "wof:name": "OX10 6NS",
    "wof:placetype": "postalcode"
  },
  "geometry": {"coordinates":[-1.104858,51.624296],"type":"Point"}
}
