{
  "type": "Feature",
  "properties": {
    "iso:country":"GB",
    "wof:name":"OX10 6NS",
    "wof:placetype":"postalcode"
},
  "geometry": {"coordinates":[-1.10485830120059,51.62429615634296],"type":"Point"}
}