{
  "type": "Feature",
  "properties": {
    "date:inception_lower":"1990-07-01",
    "date:inception_upper":"1990-07-31",
    "iso:country":"GB",
    "wof:name":"OX10 6NS",
    "wof:placetype":"postalcode"
},
  "geometry": {"coordinates":[-1.104858,51.624296],"type":"Point"}
}