{
  "type": "Feature",
  "properties": {
    "date:inception_lower": "1980-01-01",
    "date:inception_upper": "1980-01-01",
    "iso:country": "GB",
    "wof:name": "RH4 1JT",
    "wof:placetype": "postalcode"
  },
  "geometry": {"coordinates":[-0.329789,51.233579],"type":"Point"}
}
