{
  "type": "Feature",
  "properties": {
    "iso:country":"GB",
    "wof:name":"SG7 5BU",
    "wof:placetype":"postalcode"
},
  "geometry": {"coordinates":[-0.18817870547332,51.99242940966162],"type":"Point"}
}