{
  "type": "Feature",
  "properties": {
    "iso:country": "GB",
    "wof:name": "SG7 5BU",
    "wof:placetype": "postalcode"
  },
  "geometry": {"coordinates":[-0.188166,51.992439],"type":"Point"}
}
