{
  "type": "Feature",
  "properties": {
    "iso:country":"GB",
    "wof:name":"SW9 0UX",
    "wof:placetype":"postalcode"
},
  "geometry": {"coordinates":[-0.11418371972841,51.46818021765982],"type":"Point"}
}