{
  "type": "Feature",
  "properties": {
    "iso:country": "GB",
    "wof:name": "SW9 0UX",
    "wof:placetype": "postalcode"
  },
  "geometry": {"coordinates":[-0.114184,51.46818],"type":"Point"}
}
