{
  "type": "Feature",
  "properties": {
    "date:inception_lower":"2004-10-01",
    "date:inception_upper":"2004-10-31",
    "iso:country":"GB",
    "wof:name":"SW9 0UX",
    "wof:placetype":"postalcode"
},
  "geometry": {"coordinates":[-0.114184,51.46818],"type":"Point"}
}