{
  "type": "Feature",
  "properties": {
    "date:inception_lower": "1993-01-01",
    "date:inception_upper": "1993-01-01",
    "iso:country": "GB",
    "wof:name": "B78 3HD",
    "wof:placetype": "postalcode"
  },
  "geometry": {"coordinates":[-1.706974,52.627851],"type":"Point"}
}
