{
  "type": "Feature",
  "properties": {
    "iso:country": "GB",
    "wof:name": "S43 4RX",
    "wof:placetype": "postalcode"
  },
  "geometry": {"coordinates":[-1.25322,53.276797],"type":"Point"}
}
