{
  "type": "Feature",
  "properties": {
    "iso:country":"GB",
    "wof:name":"S43 4RX",
    "wof:placetype":"postalcode"
},
  "geometry": {"coordinates":[-1.25322006554654,53.27679679723619],"type":"Point"}
}