{
  "type": "Feature",
  "properties": {
    "iso:country": "GB",
    "wof:name": "TQ9 7ES",
    "wof:placetype": "postalcode"
  },
  "geometry": {"coordinates":[-3.651156,50.388521],"type":"Point"}
}
