{
  "type": "Feature",
  "properties": {
    "iso:country":"GB",
    "wof:name":"TQ9 7ES",
    "wof:placetype":"postalcode"
},
  "geometry": {"coordinates":[-3.65147507078118,50.38854138207977],"type":"Point"}
}