{
  "type": "Feature",
  "properties": {
    "date:inception_lower": "1998-06-01",
    "date:inception_upper": "1998-06-01",
    "iso:country": "GB",
    "wof:name": "SE28 8QZ",
    "wof:placetype": "postalcode"
  },
  "geometry": {"coordinates":[0.128801,51.510288],"type":"Point"}
}
