{
  "type": "Feature",
  "properties": {
    "iso:country":"GB",
    "wof:name":"SE28 8QZ",
    "wof:placetype":"postalcode"
},
  "geometry": {"coordinates":[0.12880123058047,51.51028813883818],"type":"Point"}
}