{
  "type": "Feature",
  "properties": {
    "iso:country":"GB",
    "wof:name":"LL65 3AJ",
    "wof:placetype":"postalcode"
},
  "geometry": {"coordinates":[-4.41501465531192,53.28955118921638],"type":"Point"}
}