{
  "type": "Feature",
  "properties": {
    "date:inception_lower": "1980-01-01",
    "date:inception_upper": "1980-01-01",
    "iso:country": "GB",
    "wof:name": "LL65 3AJ",
    "wof:placetype": "postalcode"
  },
  "geometry": {"coordinates":[-4.415004,53.289542],"type":"Point"}
}
