{
  "type": "Feature",
  "properties": {
    "iso:country":"GB",
    "wof:name":"PL9 7AN",
    "wof:placetype":"postalcode"
},
  "geometry": {"coordinates":[-4.09142271589217,50.36031444907069],"type":"Point"}
}