{
  "type": "Feature",
  "properties": {
    "iso:country": "GB",
    "wof:name": "MK42 9AU",
    "wof:placetype": "postalcode"
  },
  "geometry": {"coordinates":[-0.468955,52.130943],"type":"Point"}
}
