{
  "type": "Feature",
  "properties": {
    "iso:country":"GB",
    "wof:name":"MK42 9AU",
    "wof:placetype":"postalcode"
},
  "geometry": {"coordinates":[-0.46895553252966,52.13094297489705],"type":"Point"}
}