{
  "type": "Feature",
  "properties": {
    "iso:country":"GB",
    "wof:name":"PL9 8HA",
    "wof:placetype":"postalcode"
},
  "geometry": {"coordinates":[-4.07354476697752,50.35304351911844],"type":"Point"}
}