{
  "type": "Feature",
  "properties": {
    "iso:country": "GB",
    "wof:name": "SW1W 8HE",
    "wof:placetype": "postalcode"
  },
  "geometry": {"coordinates":[-0.155935,51.492872],"type":"Point"}
}
