{
  "type": "Feature",
  "properties": {
    "iso:country": "GB",
    "wof:name": "CW4 7EH",
    "wof:placetype": "postalcode"
  },
  "geometry": {"coordinates":[-2.364428,53.20191],"type":"Point"}
}
