{
  "type": "Feature",
  "properties": {
    "iso:country":"GB",
    "wof:name":"CW4 7EH",
    "wof:placetype":"postalcode"
},
  "geometry": {"coordinates":[-2.36442793575208,53.20190977731237],"type":"Point"}
}