{
  "type": "Feature",
  "properties": {
    "date:inception_lower":"1988-03-01",
    "date:inception_upper":"1988-03-31",
    "iso:country":"GB",
    "wof:name":"TR27 5EH",
    "wof:placetype":"postalcode"
},
  "geometry": {"coordinates":[-5.372248,50.202967],"type":"Point"}
}