{
  "type": "Feature",
  "properties": {
    "iso:country":"GB",
    "wof:name":"CR5 1AD",
    "wof:placetype":"postalcode"
},
  "geometry": {"coordinates":[-0.14238444230751,51.3068161701073],"type":"Point"}
}