{
  "type": "Feature",
  "properties": {
    "iso:country": "GB",
    "wof:name": "CR5 1AD",
    "wof:placetype": "postalcode"
  },
  "geometry": {"coordinates":[-0.142384,51.306816],"type":"Point"}
}
