{
  "type": "Feature",
  "properties": {
    "iso:country":"GB",
    "wof:name":"B44 8HT",
    "wof:placetype":"postalcode"
},
  "geometry": {"coordinates":[-1.89588734028245,52.53580700219019],"type":"Point"}
}