{
  "type": "Feature",
  "properties": {
    "date:inception_lower": "2015-04-01",
    "date:inception_upper": "2015-04-01",
    "iso:country": "GB",
    "wof:name": "HA1 4FP",
    "wof:placetype": "postalcode"
  },
  "geometry": {"coordinates":[-0.352208,51.579125],"type":"Point"}
}
