{
  "type": "Feature",
  "properties": {
    "iso:country":"GB",
    "wof:name":"NG4 4DY",
    "wof:placetype":"postalcode"
},
  "geometry": {"coordinates":[-1.08672661695521,52.97771525485174],"type":"Point"}
}