{
  "type": "Feature",
  "properties": {
    "iso:country": "GB",
    "wof:name": "NE5 2YH",
    "wof:placetype": "postalcode"
  },
  "geometry": {"coordinates":[-1.689141,54.991556],"type":"Point"}
}
