{
  "type": "Feature",
  "properties": {
    "iso:country": "GB",
    "wof:name": "DL7 0JE",
    "wof:placetype": "postalcode"
  },
  "geometry": {"coordinates":[-1.555966,54.405804],"type":"Point"}
}
