{
  "type": "Feature",
  "properties": {
    "date:inception_lower":"1980-01-01",
    "date:inception_upper":"1980-01-31",
    "iso:country":"GB",
    "wof:name":"DL7 0JE",
    "wof:placetype":"postalcode"
},
  "geometry": {"coordinates":[-1.555966,54.405804],"type":"Point"}
}