{
  "type": "Feature",
  "properties": {
    "iso:country":"GB",
    "wof:name":"DL7 0JE",
    "wof:placetype":"postalcode"
},
  "geometry": {"coordinates":[-1.55596585287263,54.4058036725876],"type":"Point"}
}