{
  "type": "Feature",
  "properties": {
    "date:inception_lower":"1992-01-01",
    "date:inception_upper":"1992-01-31",
    "iso:country":"GB",
    "wof:name":"BB5 3QY",
    "wof:placetype":"postalcode"
},
  "geometry": {"coordinates":[-2.403361,53.736466],"type":"Point"}
}