{
  "type": "Feature",
  "properties": {
    "iso:country": "GB",
    "wof:name": "BB5 3QY",
    "wof:placetype": "postalcode"
  },
  "geometry": {"coordinates":[-2.403361,53.736466],"type":"Point"}
}
