{
  "type": "Feature",
  "properties": {
    "iso:country": "GB",
    "wof:name": "DG13 0HU",
    "wof:placetype": "postalcode"
  },
  "geometry": {"coordinates":[-2.922042,55.207922],"type":"Point"}
}
