{
  "type": "Feature",
  "properties": {
    "iso:country":"GB",
    "wof:name":"GU1 2BA",
    "wof:placetype":"postalcode"
},
  "geometry": {"coordinates":[-0.5606567925377,51.23880433443469],"type":"Point"}
}