{
  "type": "Feature",
  "properties": {
    "iso:country": "GB",
    "wof:name": "NR1 1PW",
    "wof:placetype": "postalcode"
  },
  "geometry": {"coordinates":[1.300308,52.626747],"type":"Point"}
}
