{
  "type": "Feature",
  "properties": {
    "date:inception_lower": "2002-10-01",
    "date:inception_upper": "2002-10-01",
    "iso:country": "GB",
    "wof:name": "NR1 1PW",
    "wof:placetype": "postalcode"
  },
  "geometry": {"coordinates":[1.300335,52.626711],"type":"Point"}
}
