{
  "type": "Feature",
  "properties": {
    "iso:country": "GB",
    "wof:name": "LL14 1PW",
    "wof:placetype": "postalcode"
  },
  "geometry": {"coordinates":[-3.040387,53.010261],"type":"Point"}
}
