{
  "type": "Feature",
  "properties": {
    "iso:country":"GB",
    "wof:name":"BH21 3BU",
    "wof:placetype":"postalcode"
},
  "geometry": {"coordinates":[-2.01747638960558,50.77238373082695],"type":"Point"}
}