{
  "type": "Feature",
  "properties": {
    "date:inception_lower":"2008-06-01",
    "date:inception_upper":"2008-06-30",
    "iso:country":"GB",
    "wof:name":"BH21 3BU",
    "wof:placetype":"postalcode"
},
  "geometry": {"coordinates":[-2.017476,50.772384],"type":"Point"}
}