{
  "type": "Feature",
  "properties": {
    "iso:country":"GB",
    "wof:name":"LE10 0LR",
    "wof:placetype":"postalcode"
},
  "geometry": {"coordinates":[-1.39176889166284,52.53378788686955],"type":"Point"}
}