{
  "type": "Feature",
  "properties": {
    "iso:country":"GB",
    "wof:name":"DE55 4LD",
    "wof:placetype":"postalcode"
},
  "geometry": {"coordinates":[-1.3655093130624,53.07435721054026],"type":"Point"}
}