{
  "type": "Feature",
  "properties": {
    "iso:country":"GB",
    "wof:name":"B93 0QA",
    "wof:placetype":"postalcode"
},
  "geometry": {"coordinates":[-1.74476253480225,52.37979898608193],"type":"Point"}
}