{
  "type": "Feature",
  "properties": {
    "date:inception_lower": "2016-11-01",
    "date:inception_upper": "2016-11-01",
    "iso:country": "GB",
    "wof:name": "SP4 7GL",
    "wof:placetype": "postalcode"
  },
  "geometry": {"coordinates":[-1.762983,51.160751],"type":"Point"}
}
