{
  "type": "Feature",
  "properties": {
    "iso:country": "GB",
    "wof:name": "TF9 4QN",
    "wof:placetype": "postalcode"
  },
  "geometry": {"coordinates":[-2.445274,52.942164],"type":"Point"}
}
