{
  "type": "Feature",
  "properties": {
    "iso:country":"GB",
    "wof:name":"TF9 4QN",
    "wof:placetype":"postalcode"
},
  "geometry": {"coordinates":[-2.44527388552615,52.9421636826257],"type":"Point"}
}