{
  "type": "Feature",
  "properties": {
    "date:inception_lower": "2021-02-01",
    "date:inception_upper": "2021-02-01",
    "iso:country": "GB",
    "wof:name": "SP7 8TH",
    "wof:placetype": "postalcode"
  },
  "geometry": {"coordinates":[-2.191157,51.016393],"type":"Point"}
}
