{
  "type": "Feature",
  "properties": {
    "iso:country":"GB",
    "wof:name":"TA8 2RB",
    "wof:placetype":"postalcode"
},
  "geometry": {"coordinates":[-3.01264980025409,51.28028006360325],"type":"Point"}
}