{
  "type": "Feature",
  "properties": {
    "iso:country": "GB",
    "wof:name": "NR3 3AE",
    "wof:placetype": "postalcode"
  },
  "geometry": {"coordinates":[1.290756,52.633472],"type":"Point"}
}
