{
  "type": "Feature",
  "properties": {
    "iso:country":"GB",
    "wof:name":"NR3 3AE",
    "wof:placetype":"postalcode"
},
  "geometry": {"coordinates":[1.29075598125398,52.63347240274729],"type":"Point"}
}