{
  "type": "Feature",
  "properties": {
    "date:inception_lower":"1980-01-01",
    "date:inception_upper":"1980-01-31",
    "iso:country":"GB",
    "wof:name":"NR3 3AE",
    "wof:placetype":"postalcode"
},
  "geometry": {"coordinates":[1.290756,52.633472],"type":"Point"}
}