{
  "type": "Feature",
  "properties": {
    "date:inception_lower": "2024-01-01",
    "date:inception_upper": "2024-01-01",
    "iso:country": "GB",
    "wof:name": "LL65 4AZ",
    "wof:placetype": "postalcode"
  },
  "geometry": {"coordinates":[-4.497452,53.346519],"type":"Point"}
}
