{
  "type": "Feature",
  "properties": {
    "iso:country":"GB",
    "wof:name":"SY18 6BY",
    "wof:placetype":"postalcode"
},
  "geometry": {"coordinates":[-3.5382142544179,52.44745408097096],"type":"Point"}
}