{
  "type": "Feature",
  "properties": {
    "iso:country":"GB",
    "wof:name":"SR4 6RB",
    "wof:placetype":"postalcode"
},
  "geometry": {"coordinates":[-1.41670534210903,54.90880608883671],"type":"Point"}
}