{
  "type": "Feature",
  "properties": {
    "iso:country":"GB",
    "wof:name":"HX1 2JN",
    "wof:placetype":"postalcode"
},
  "geometry": {"coordinates":[-1.85937088339674,53.71876394414157],"type":"Point"}
}