{
  "type": "Feature",
  "properties": {
    "iso:country": "GB",
    "wof:name": "RH20 4JA",
    "wof:placetype": "postalcode"
  },
  "geometry": {"coordinates":[-0.462082,50.9189],"type":"Point"}
}
