{
  "type": "Feature",
  "properties": {
    "date:inception_lower": "1997-12-01",
    "date:inception_upper": "1997-12-01",
    "iso:country": "GB",
    "wof:name": "RH20 4JA",
    "wof:placetype": "postalcode"
  },
  "geometry": {"coordinates":[-0.462082,50.9189],"type":"Point"}
}
