{
  "type": "Feature",
  "properties": {
    "iso:country":"GB",
    "wof:name":"TQ1 2HR",
    "wof:placetype":"postalcode"
},
  "geometry": {"coordinates":[-3.50392203871875,50.46328445065662],"type":"Point"}
}