{
  "type": "Feature",
  "properties": {
    "iso:country":"GB",
    "wof:name":"AL7 4DD",
    "wof:placetype":"postalcode"
},
  "geometry": {"coordinates":[-0.1796165152831,51.78342353075441],"type":"Point"}
}