{
  "type": "Feature",
  "properties": {
    "iso:country":"GB",
    "wof:name":"WA2 8TF",
    "wof:placetype":"postalcode"
},
  "geometry": {"coordinates":[-2.5963980457506,53.43135759792448],"type":"Point"}
}