{
  "type": "Feature",
  "properties": {
    "date:inception_lower": "1980-01-01",
    "date:inception_upper": "1980-01-01",
    "iso:country": "GB",
    "wof:name": "WA2 8TF",
    "wof:placetype": "postalcode"
  },
  "geometry": {"coordinates":[-2.596398,53.431358],"type":"Point"}
}
