{
  "type": "Feature",
  "properties": {
    "iso:country":"GB",
    "wof:name":"CR0 7TB",
    "wof:placetype":"postalcode"
},
  "geometry": {"coordinates":[-0.04522075535491,51.38788762201659],"type":"Point"}
}