{
  "type": "Feature",
  "properties": {
    "iso:country":"GB",
    "wof:name":"PL15 8JS",
    "wof:placetype":"postalcode"
},
  "geometry": {"coordinates":[-4.36378144299079,50.64765778994452],"type":"Point"}
}