{
  "type": "Feature",
  "properties": {
    "iso:country":"GB",
    "wof:name":"WN5 7TT",
    "wof:placetype":"postalcode"
},
  "geometry": {"coordinates":[-2.71074049078369,53.49171082203227],"type":"Point"}
}