{
  "type": "Feature",
  "properties": {
    "iso:country":"GB",
    "wof:name":"TN23 3NQ",
    "wof:placetype":"postalcode"
},
  "geometry": {"coordinates":[0.86748590796571,51.1249669312772],"type":"Point"}
}