{
  "type": "Feature",
  "properties": {
    "date:inception_lower": "1995-01-01",
    "date:inception_upper": "1995-01-01",
    "iso:country": "GB",
    "wof:name": "TN23 3NQ",
    "wof:placetype": "postalcode"
  },
  "geometry": {"coordinates":[0.867486,51.124967],"type":"Point"}
}
