{
  "type": "Feature",
  "properties": {
    "iso:country": "GB",
    "wof:name": "BN7 2RL",
    "wof:placetype": "postalcode"
  },
  "geometry": {"coordinates":[0.018857,50.882651],"type":"Point"}
}
