{
  "type": "Feature",
  "properties": {
    "iso:country":"GB",
    "wof:name":"BN7 2RL",
    "wof:placetype":"postalcode"
},
  "geometry": {"coordinates":[0.01885697815656,50.88265063924401],"type":"Point"}
}