{
  "type": "Feature",
  "properties": {
    "iso:country":"GB",
    "wof:name":"LL40 2SD",
    "wof:placetype":"postalcode"
},
  "geometry": {"coordinates":[-3.81998707355999,52.75757836125737],"type":"Point"}
}