{
  "type": "Feature",
  "properties": {
    "iso:country": "GB",
    "wof:name": "LL40 2SD",
    "wof:placetype": "postalcode"
  },
  "geometry": {"coordinates":[-3.819987,52.757578],"type":"Point"}
}
