{
  "type": "Feature",
  "properties": {
    "iso:country":"GB",
    "wof:name":"PE1 4UQ",
    "wof:placetype":"postalcode"
},
  "geometry": {"coordinates":[-0.21680958461109,52.59714701239505],"type":"Point"}
}