{
  "type": "Feature",
  "properties": {
    "iso:country":"GB",
    "wof:name":"SK7 4QL",
    "wof:placetype":"postalcode"
},
  "geometry": {"coordinates":[-2.11390655706084,53.37918544691676],"type":"Point"}
}