{
  "type": "Feature",
  "properties": {
    "iso:country":"GB",
    "wof:name":"BA15 2JU",
    "wof:placetype":"postalcode"
},
  "geometry": {"coordinates":[-2.28295765253269,51.35061511831833],"type":"Point"}
}