{
  "type": "Feature",
  "properties": {
    "iso:country":"GB",
    "wof:name":"DY4 7NB",
    "wof:placetype":"postalcode"
},
  "geometry": {"coordinates":[-2.04622904081892,52.53109676801999],"type":"Point"}
}