{
  "type": "Feature",
  "properties": {
    "iso:country": "GB",
    "wof:name": "SG18 9DG",
    "wof:placetype": "postalcode"
  },
  "geometry": {"coordinates":[-0.29989,52.099377],"type":"Point"}
}
