{
  "type": "Feature",
  "properties": {
    "date:inception_lower": "1980-01-01",
    "date:inception_upper": "1980-01-01",
    "iso:country": "GB",
    "wof:name": "NG15 6SE",
    "wof:placetype": "postalcode"
  },
  "geometry": {"coordinates":[-1.229627,53.02362],"type":"Point"}
}
