{
  "type": "Feature",
  "properties": {
    "iso:country":"GB",
    "wof:name":"IV6 7RR",
    "wof:placetype":"postalcode"
},
  "geometry": {"coordinates":[-4.4526923424613,57.51622282216125],"type":"Point"}
}