{
  "type": "Feature",
  "properties": {
    "iso:country": "GB",
    "wof:name": "ME16 0RD",
    "wof:placetype": "postalcode"
  },
  "geometry": {"coordinates":[0.502438,51.284421],"type":"Point"}
}
