{
  "type": "Feature",
  "properties": {
    "iso:country": "GB",
    "wof:name": "CB23 6DU",
    "wof:placetype": "postalcode"
  },
  "geometry": {"coordinates":[-0.055985,52.21598],"type":"Point"}
}
