{
  "type": "Feature",
  "properties": {
    "date:inception_lower":"2009-07-01",
    "date:inception_upper":"2009-07-31",
    "iso:country":"GB",
    "wof:name":"CB23 6DU",
    "wof:placetype":"postalcode"
},
  "geometry": {"coordinates":[-0.055985,52.21598],"type":"Point"}
}