{
  "type": "Feature",
  "properties": {
    "iso:country":"GB",
    "wof:name":"SO50 5NN",
    "wof:placetype":"postalcode"
},
  "geometry": {"coordinates":[-1.3551766297979,50.96558977701057],"type":"Point"}
}