{
  "type": "Feature",
  "properties": {
    "iso:country":"GB",
    "wof:name":"WV2 1ET",
    "wof:placetype":"postalcode"
},
  "geometry": {"coordinates":[-2.12132883757079,52.5767478465449],"type":"Point"}
}