{
  "type": "Feature",
  "properties": {
    "iso:country":"GB",
    "wof:name":"DH6 2XH",
    "wof:placetype":"postalcode"
},
  "geometry": {"coordinates":[-1.41786072652395,54.80159338845557],"type":"Point"}
}