{
  "type": "Feature",
  "properties": {
    "date:inception_lower": "1982-03-01",
    "date:inception_upper": "1982-03-01",
    "iso:country": "GB",
    "wof:name": "DH6 2XH",
    "wof:placetype": "postalcode"
  },
  "geometry": {"coordinates":[-1.417861,54.801593],"type":"Point"}
}
