{
  "type": "Feature",
  "properties": {
    "iso:country":"GB",
    "wof:name":"WA4 5EQ",
    "wof:placetype":"postalcode"
},
  "geometry": {"coordinates":[-2.57150909492252,53.35210013240543],"type":"Point"}
}