{
  "type": "Feature",
  "properties": {
    "iso:country": "GB",
    "wof:name": "LE4 2DN",
    "wof:placetype": "postalcode"
  },
  "geometry": {"coordinates":[-1.142793,52.659708],"type":"Point"}
}
