{
  "type": "Feature",
  "properties": {
    "iso:country":"GB",
    "wof:name":"LE4 2DN",
    "wof:placetype":"postalcode"
},
  "geometry": {"coordinates":[-1.14279299272886,52.659708085989],"type":"Point"}
}