{
  "type": "Feature",
  "properties": {
    "iso:country":"GB",
    "wof:name":"WS3 1LN",
    "wof:placetype":"postalcode"
},
  "geometry": {"coordinates":[-1.98893947890355,52.61288577312448],"type":"Point"}
}