{
  "type": "Feature",
  "properties": {
    "iso:country": "GB",
    "wof:name": "BR4 9NR",
    "wof:placetype": "postalcode"
  },
  "geometry": {"coordinates":[-0.023014,51.369907],"type":"Point"}
}
