{
  "type": "Feature",
  "properties": {
    "iso:country":"GB",
    "wof:name":"NE38 0LZ",
    "wof:placetype":"postalcode"
},
  "geometry": {"coordinates":[-1.54573269612175,54.89698232394792],"type":"Point"}
}