{
  "type": "Feature",
  "properties": {
    "iso:country": "GB",
    "wof:name": "NE38 0LZ",
    "wof:placetype": "postalcode"
  },
  "geometry": {"coordinates":[-1.545774,54.89717],"type":"Point"}
}
