{
  "type": "Feature",
  "properties": {
    "iso:country":"GB",
    "wof:name":"EX31 2LU",
    "wof:placetype":"postalcode"
},
  "geometry": {"coordinates":[-4.10122676262762,51.07321672409228],"type":"Point"}
}