{
  "type": "Feature",
  "properties": {
    "date:inception_lower": "1980-01-01",
    "date:inception_upper": "1980-01-01",
    "iso:country": "GB",
    "wof:name": "EX31 2LU",
    "wof:placetype": "postalcode"
  },
  "geometry": {"coordinates":[-4.101227,51.073217],"type":"Point"}
}
