{
  "type": "Feature",
  "properties": {
    "date:inception_lower": "2019-01-01",
    "date:inception_upper": "2019-01-01",
    "iso:country": "GB",
    "wof:name": "B37 7WJ",
    "wof:placetype": "postalcode"
  },
  "geometry": {"coordinates":[-1.746752,52.467417],"type":"Point"}
}
