{
  "type": "Feature",
  "properties": {
    "date:inception_lower":"1993-08-01",
    "date:inception_upper":"1993-08-31",
    "iso:country":"GB",
    "wof:name":"BA14 9PP",
    "wof:placetype":"postalcode"
},
  "geometry": {"coordinates":[-2.231405,51.290259],"type":"Point"}
}