{
  "type": "Feature",
  "properties": {
    "iso:country": "GB",
    "wof:name": "BA14 9PP",
    "wof:placetype": "postalcode"
  },
  "geometry": {"coordinates":[-2.231405,51.290259],"type":"Point"}
}
