{
  "type": "Feature",
  "properties": {
    "iso:country": "GB",
    "wof:name": "SW1E 6HF",
    "wof:placetype": "postalcode"
  },
  "geometry": {"coordinates":[-0.140718,51.499017],"type":"Point"}
}
