{
  "type": "Feature",
  "properties": {
    "iso:country":"GB",
    "wof:name":"SW1E 6HF",
    "wof:placetype":"postalcode"
},
  "geometry": {"coordinates":[-0.14071773869121,51.49901679367703],"type":"Point"}
}