{
  "type": "Feature",
  "properties": {
    "date:inception_lower": "1980-01-01",
    "date:inception_upper": "1980-01-01",
    "iso:country": "GB",
    "wof:name": "SW1E 6HF",
    "wof:placetype": "postalcode"
  },
  "geometry": {"coordinates":[-0.140718,51.499017],"type":"Point"}
}
