{
  "type": "Feature",
  "properties": {
    "date:inception_lower": "1980-01-01",
    "date:inception_upper": "1980-01-01",
    "iso:country": "GB",
    "wof:name": "M2 4LY",
    "wof:placetype": "postalcode"
  },
  "geometry": {"coordinates":[-2.245664,53.48105],"type":"Point"}
}
