{
  "type": "Feature",
  "properties": {
    "iso:country":"GB",
    "wof:name":"M2 4LY",
    "wof:placetype":"postalcode"
},
  "geometry": {"coordinates":[-2.24575720652808,53.48103339404219],"type":"Point"}
}