{
  "type": "Feature",
  "properties": {
    "iso:country": "GB",
    "wof:name": "RM15 4DJ",
    "wof:placetype": "postalcode"
  },
  "geometry": {"coordinates":[0.251457,51.499121],"type":"Point"}
}
