{
  "type": "Feature",
  "properties": {
    "iso:country":"GB",
    "wof:name":"RM15 4DJ",
    "wof:placetype":"postalcode"
},
  "geometry": {"coordinates":[0.25145680785478,51.49912124340063],"type":"Point"}
}