{
  "type": "Feature",
  "properties": {
    "iso:country": "GB",
    "wof:name": "NG7 1NN",
    "wof:placetype": "postalcode"
  },
  "geometry": {"coordinates":[-1.166252,52.955466],"type":"Point"}
}
