{
  "type": "Feature",
  "properties": {
    "iso:country":"GB",
    "wof:name":"NG7 1NN",
    "wof:placetype":"postalcode"
},
  "geometry": {"coordinates":[-1.16625244853838,52.95546613415068],"type":"Point"}
}