{
  "type": "Feature",
  "properties": {
    "iso:country":"GB",
    "wof:name":"ME15 7AJ",
    "wof:placetype":"postalcode"
},
  "geometry": {"coordinates":[0.54045112923734,51.25986734907487],"type":"Point"}
}