{
  "type": "Feature",
  "properties": {
    "iso:country": "GB",
    "wof:name": "TQ13 8NY",
    "wof:placetype": "postalcode"
  },
  "geometry": {"coordinates":[-3.768218,50.659319],"type":"Point"}
}
