{
  "type": "Feature",
  "properties": {
    "iso:country":"GB",
    "wof:name":"BB2 4LW",
    "wof:placetype":"postalcode"
},
  "geometry": {"coordinates":[-2.49403614440149,53.72785743434918],"type":"Point"}
}