{
  "type": "Feature",
  "properties": {
    "date:inception_lower": "2014-10-01",
    "date:inception_upper": "2014-10-01",
    "iso:country": "GB",
    "wof:name": "CF82 6BF",
    "wof:placetype": "postalcode"
  },
  "geometry": {"coordinates":[-3.240965,51.658114],"type":"Point"}
}
