{
  "type": "Feature",
  "properties": {
    "iso:country":"GB",
    "wof:name":"CF82 6BF",
    "wof:placetype":"postalcode"
},
  "geometry": {"coordinates":[-3.24110016563344,51.65812688615973],"type":"Point"}
}