{
  "type": "Feature",
  "properties": {
    "iso:country":"GB",
    "wof:name":"PH6 2EH",
    "wof:placetype":"postalcode"
},
  "geometry": {"coordinates":[-3.97868428546647,56.36944798247028],"type":"Point"}
}