{
  "type": "Feature",
  "properties": {
    "iso:country":"GB",
    "wof:name":"SO31 8GN",
    "wof:placetype":"postalcode"
},
  "geometry": {"coordinates":[-1.31993295369396,50.89423252212265],"type":"Point"}
}