{
  "type": "Feature",
  "properties": {
    "date:inception_lower": "2004-01-01",
    "date:inception_upper": "2004-01-01",
    "iso:country": "GB",
    "wof:name": "GU1 4QR",
    "wof:placetype": "postalcode"
  },
  "geometry": {"coordinates":[-0.572811,51.242766],"type":"Point"}
}
