{
  "type": "Feature",
  "properties": {
    "iso:country":"GB",
    "wof:name":"WF9 4NT",
    "wof:placetype":"postalcode"
},
  "geometry": {"coordinates":[-1.36339883380288,53.6114628334163],"type":"Point"}
}