{
  "type": "Feature",
  "properties": {
    "iso:country":"GB",
    "wof:name":"KA19 8AU",
    "wof:placetype":"postalcode"
},
  "geometry": {"coordinates":[-4.69235743539052,55.35148695087267],"type":"Point"}
}