{
  "type": "Feature",
  "properties": {
    "iso:country":"GB",
    "wof:name":"YO22 4SE",
    "wof:placetype":"postalcode"
},
  "geometry": {"coordinates":[-0.53383871201399,54.43187628700079],"type":"Point"}
}