{
  "type": "Feature",
  "properties": {
    "date:inception_lower": "2016-09-01",
    "date:inception_upper": "2016-09-01",
    "iso:country": "GB",
    "wof:name": "EH30 9AS",
    "wof:placetype": "postalcode"
  },
  "geometry": {"coordinates":[-3.382168,55.982442],"type":"Point"}
}
