{
  "type": "Feature",
  "properties": {
    "iso:country": "GB",
    "wof:name": "SO31 9FD",
    "wof:placetype": "postalcode"
  },
  "geometry": {"coordinates":[-1.294445,50.859928],"type":"Point"}
}
