{
  "type": "Feature",
  "properties": {
    "iso:country": "GB",
    "wof:name": "GU21 2TN",
    "wof:placetype": "postalcode"
  },
  "geometry": {"coordinates":[-0.618366,51.314091],"type":"Point"}
}
