{
  "type": "Feature",
  "properties": {
    "iso:country": "GB",
    "wof:name": "BN12 5PA",
    "wof:placetype": "postalcode"
  },
  "geometry": {"coordinates":[-0.446823,50.807084],"type":"Point"}
}
