{
  "type": "Feature",
  "properties": {
    "date:inception_lower": "1980-01-01",
    "date:inception_upper": "1980-01-01",
    "iso:country": "GB",
    "wof:name": "BN12 5PA",
    "wof:placetype": "postalcode"
  },
  "geometry": {"coordinates":[-0.446823,50.807084],"type":"Point"}
}
