{
  "type": "Feature",
  "properties": {
    "iso:country":"GB",
    "wof:name":"NG13 0FP",
    "wof:placetype":"postalcode"
},
  "geometry": {"coordinates":[-0.81280331020436,52.94251922686845],"type":"Point"}
}