{
  "type": "Feature",
  "properties": {
    "date:inception_lower":"1994-12-01",
    "date:inception_upper":"1994-12-31",
    "iso:country":"GB",
    "wof:name":"NG13 0FP",
    "wof:placetype":"postalcode"
},
  "geometry": {"coordinates":[-0.812803,52.942519],"type":"Point"}
}