{
  "type": "Feature",
  "properties": {
    "iso:country": "GB",
    "wof:name": "NG13 0FP",
    "wof:placetype": "postalcode"
  },
  "geometry": {"coordinates":[-0.812803,52.942519],"type":"Point"}
}
