{
  "type": "Feature",
  "properties": {
    "iso:country":"GB",
    "wof:name":"BD5 7NR",
    "wof:placetype":"postalcode"
},
  "geometry": {"coordinates":[-1.76346568242409,53.77826692806104],"type":"Point"}
}