{
  "type": "Feature",
  "properties": {
    "iso:country":"GB",
    "wof:name":"KW14 8UL",
    "wof:placetype":"postalcode"
},
  "geometry": {"coordinates":[-3.38538421914068,58.59212758801293],"type":"Point"}
}