{
  "type": "Feature",
  "properties": {
    "date:inception_lower": "2006-07-01",
    "date:inception_upper": "2006-07-01",
    "iso:country": "GB",
    "wof:name": "G74 5QD",
    "wof:placetype": "postalcode"
  },
  "geometry": {"coordinates":[-4.228085,55.760443],"type":"Point"}
}
