{
  "type": "Feature",
  "properties": {
    "iso:country":"GB",
    "wof:name":"G74 5QD",
    "wof:placetype":"postalcode"
},
  "geometry": {"coordinates":[-4.22808525328854,55.76044278383732],"type":"Point"}
}