{
  "type": "Feature",
  "properties": {
    "iso:country": "GB",
    "wof:name": "RM18 7PL",
    "wof:placetype": "postalcode"
  },
  "geometry": {"coordinates":[0.361872,51.459879],"type":"Point"}
}
