{
  "type": "Feature",
  "properties": {
    "iso:country":"GB",
    "wof:name":"LE2 8AU",
    "wof:placetype":"postalcode"
},
  "geometry": {"coordinates":[-1.13802763081943,52.61030950995086],"type":"Point"}
}