{
  "type": "Feature",
  "properties": {
    "iso:country":"GB",
    "wof:name":"CO12 4JZ",
    "wof:placetype":"postalcode"
},
  "geometry": {"coordinates":[1.25764269011771,51.93625404025195],"type":"Point"}
}