{
  "type": "Feature",
  "properties": {
    "iso:country": "GB",
    "wof:name": "BS24 6RT",
    "wof:placetype": "postalcode"
  },
  "geometry": {"coordinates":[-2.866435,51.3745],"type":"Point"}
}
