{
  "type": "Feature",
  "properties": {
    "date:inception_lower": "1980-01-01",
    "date:inception_upper": "1980-01-01",
    "iso:country": "GB",
    "wof:name": "OX17 2HA",
    "wof:placetype": "postalcode"
  },
  "geometry": {"coordinates":[-1.228947,52.096753],"type":"Point"}
}
