{
  "type": "Feature",
  "properties": {
    "iso:country":"GB",
    "wof:name":"OX17 2HA",
    "wof:placetype":"postalcode"
},
  "geometry": {"coordinates":[-1.22896255239294,52.09674164638468],"type":"Point"}
}