{
  "type": "Feature",
  "properties": {
    "iso:country":"GB",
    "wof:name":"HR2 9EP",
    "wof:placetype":"postalcode"
},
  "geometry": {"coordinates":[-2.84247268298556,52.01673416721976],"type":"Point"}
}