{
  "type": "Feature",
  "properties": {
    "date:inception_lower": "1980-01-01",
    "date:inception_upper": "1980-01-01",
    "iso:country": "GB",
    "wof:name": "HR2 9EP",
    "wof:placetype": "postalcode"
  },
  "geometry": {"coordinates":[-2.842473,52.016734],"type":"Point"}
}
