{
  "type": "Feature",
  "properties": {
    "iso:country": "GB",
    "wof:name": "OX25 5AW",
    "wof:placetype": "postalcode"
  },
  "geometry": {"coordinates":[-1.262239,51.925885],"type":"Point"}
}
