{
  "type": "Feature",
  "properties": {
    "iso:country": "GB",
    "wof:name": "CB6 2DB",
    "wof:placetype": "postalcode"
  },
  "geometry": {"coordinates":[0.189622,52.415865],"type":"Point"}
}
