{
  "type": "Feature",
  "properties": {
    "iso:country":"GB",
    "wof:name":"CB6 2DB",
    "wof:placetype":"postalcode"
},
  "geometry": {"coordinates":[0.18962220523104,52.4158646229181],"type":"Point"}
}