{
  "type": "Feature",
  "properties": {
    "iso:country": "GB",
    "wof:name": "SW18 4TE",
    "wof:placetype": "postalcode"
  },
  "geometry": {"coordinates":[-0.19389,51.455165],"type":"Point"}
}
