{
  "type": "Feature",
  "properties": {
    "date:inception_lower": "2021-07-01",
    "date:inception_upper": "2021-07-01",
    "iso:country": "GB",
    "wof:name": "PO2 9DZ",
    "wof:placetype": "postalcode"
  },
  "geometry": {"coordinates":[-1.075872,50.827871],"type":"Point"}
}
