{
  "type": "Feature",
  "properties": {
    "date:inception_lower":"1980-01-01",
    "date:inception_upper":"1980-01-31",
    "iso:country":"GB",
    "wof:name":"SE13 6NP",
    "wof:placetype":"postalcode"
},
  "geometry": {"coordinates":[-0.014083,51.455709],"type":"Point"}
}