{
  "type": "Feature",
  "properties": {
    "iso:country":"GB",
    "wof:name":"SE13 6NP",
    "wof:placetype":"postalcode"
},
  "geometry": {"coordinates":[-0.01408342383474,51.4557091169013],"type":"Point"}
}