{
  "type": "Feature",
  "properties": {
    "iso:country":"GB",
    "wof:name":"ST4 5PD",
    "wof:placetype":"postalcode"
},
  "geometry": {"coordinates":[-2.20063692501572,52.98706500382338],"type":"Point"}
}