{
  "type": "Feature",
  "properties": {
    "date:inception_lower": "1995-01-01",
    "date:inception_upper": "1995-01-01",
    "iso:country": "GB",
    "wof:name": "OL6 6DF",
    "wof:placetype": "postalcode"
  },
  "geometry": {"coordinates":[-2.093014,53.490535],"type":"Point"}
}
