{
  "type": "Feature",
  "properties": {
    "iso:country":"GB",
    "wof:name":"TD12 4LT",
    "wof:placetype":"postalcode"
},
  "geometry": {"coordinates":[-2.29764928716026,55.66327846914885],"type":"Point"}
}