{
  "type": "Feature",
  "properties": {
    "iso:country":"GB",
    "wof:name":"BR3 3GS",
    "wof:placetype":"postalcode"
},
  "geometry": {"coordinates":[-0.01740114234223,51.39107125530251],"type":"Point"}
}