{
  "type": "Feature",
  "properties": {
    "iso:country": "GB",
    "wof:name": "CT13 9HW",
    "wof:placetype": "postalcode"
  },
  "geometry": {"coordinates":[1.340788,51.274019],"type":"Point"}
}
