{
  "type": "Feature",
  "properties": {
    "iso:country": "GB",
    "wof:name": "BH9 1EY",
    "wof:placetype": "postalcode"
  },
  "geometry": {"coordinates":[-1.871381,50.740526],"type":"Point"}
}
