{
  "type": "Feature",
  "properties": {
    "date:inception_lower":"2008-09-01",
    "date:inception_upper":"2008-09-30",
    "iso:country":"GB",
    "wof:name":"BH9 1EY",
    "wof:placetype":"postalcode"
},
  "geometry": {"coordinates":[-1.871381,50.740526],"type":"Point"}
}