{
  "type": "Feature",
  "properties": {
    "iso:country":"GB",
    "wof:name":"BH9 1EY",
    "wof:placetype":"postalcode"
},
  "geometry": {"coordinates":[-1.87138067075296,50.74052555249734],"type":"Point"}
}