{
  "type": "Feature",
  "properties": {
    "iso:country":"GB",
    "wof:name":"PA2 6TR",
    "wof:placetype":"postalcode"
},
  "geometry": {"coordinates":[-4.414918550489,55.83469309120205],"type":"Point"}
}