{
  "type": "Feature",
  "properties": {
    "iso:country":"GB",
    "wof:name":"BR3 1NX",
    "wof:placetype":"postalcode"
},
  "geometry": {"coordinates":[-0.03412518496856,51.41504004114376],"type":"Point"}
}