{
  "type": "Feature",
  "properties": {
    "iso:country":"GB",
    "wof:name":"YO19 6PA",
    "wof:placetype":"postalcode"
},
  "geometry": {"coordinates":[-1.05877244199155,53.83386961698331],"type":"Point"}
}