{
  "type": "Feature",
  "properties": {
    "date:inception_lower": "1998-06-01",
    "date:inception_upper": "1998-06-01",
    "iso:country": "GB",
    "wof:name": "YO19 6PA",
    "wof:placetype": "postalcode"
  },
  "geometry": {"coordinates":[-1.058772,53.83387],"type":"Point"}
}
