{
  "type": "Feature",
  "properties": {
    "iso:country": "GB",
    "wof:name": "HA9 7SE",
    "wof:placetype": "postalcode"
  },
  "geometry": {"coordinates":[-0.29143,51.555722],"type":"Point"}
}
