{
  "type": "Feature",
  "properties": {
    "date:inception_lower": "1980-01-01",
    "date:inception_upper": "1980-01-01",
    "iso:country": "GB",
    "wof:name": "G66 3QE",
    "wof:placetype": "postalcode"
  },
  "geometry": {"coordinates":[-4.118368,55.938191],"type":"Point"}
}
