{
  "type": "Feature",
  "properties": {
    "iso:country": "GB",
    "wof:name": "SA10 9AE",
    "wof:placetype": "postalcode"
  },
  "geometry": {"coordinates":[-3.712561,51.763662],"type":"Point"}
}
