{
  "type": "Feature",
  "properties": {
    "iso:country":"GB",
    "wof:name":"B28 0TD",
    "wof:placetype":"postalcode"
},
  "geometry": {"coordinates":[-1.85625070878089,52.41607311702118],"type":"Point"}
}