{
  "type": "Feature",
  "properties": {
    "iso:country":"GB",
    "wof:name":"NE24 2JP",
    "wof:placetype":"postalcode"
},
  "geometry": {"coordinates":[-1.51126666333532,55.12525216291117],"type":"Point"}
}