{
  "type": "Feature",
  "properties": {
    "iso:country":"GB",
    "wof:name":"GL55 6QT",
    "wof:placetype":"postalcode"
},
  "geometry": {"coordinates":[-1.81491565526929,52.06484420254608],"type":"Point"}
}