{
  "type": "Feature",
  "properties": {
    "iso:country":"GB",
    "wof:name":"ML5 5JH",
    "wof:placetype":"postalcode"
},
  "geometry": {"coordinates":[-4.03886909251999,55.84948335666107],"type":"Point"}
}