{
  "type": "Feature",
  "properties": {
    "iso:country":"GB",
    "wof:name":"PO3 5BU",
    "wof:placetype":"postalcode"
},
  "geometry": {"coordinates":[-1.06385292668404,50.83107631769496],"type":"Point"}
}