{
  "type": "Feature",
  "properties": {
    "date:inception_lower": "1980-01-01",
    "date:inception_upper": "1980-01-01",
    "iso:country": "GB",
    "wof:name": "BB2 7BU",
    "wof:placetype": "postalcode"
  },
  "geometry": {"coordinates":[-2.496831,53.764329],"type":"Point"}
}
