{
  "type": "Feature",
  "properties": {
    "iso:country":"GB",
    "wof:name":"BB2 7BU",
    "wof:placetype":"postalcode"
},
  "geometry": {"coordinates":[-2.49683087682762,53.76432871335488],"type":"Point"}
}