{
  "type": "Feature",
  "properties": {
    "iso:country":"GB",
    "wof:name":"BA11 2SY",
    "wof:placetype":"postalcode"
},
  "geometry": {"coordinates":[-2.32292337945198,51.24084756661945],"type":"Point"}
}