{
  "type": "Feature",
  "properties": {
    "iso:country":"GB",
    "wof:name":"DE7 5AS",
    "wof:placetype":"postalcode"
},
  "geometry": {"coordinates":[-1.29883919366772,52.9617784989243],"type":"Point"}
}