{
  "type": "Feature",
  "properties": {
    "iso:country":"GB",
    "wof:name":"YO25 8QF",
    "wof:placetype":"postalcode"
},
  "geometry": {"coordinates":[-0.30867575688113,53.91546779211232],"type":"Point"}
}