{
  "type": "Feature",
  "properties": {
    "iso:country":"GB",
    "wof:name":"LS8 3PX",
    "wof:placetype":"postalcode"
},
  "geometry": {"coordinates":[-1.5036584636821,53.81302129457109],"type":"Point"}
}