{
  "type": "Feature",
  "properties": {
    "iso:country":"GB",
    "wof:name":"SW3 4BA",
    "wof:placetype":"postalcode"
},
  "geometry": {"coordinates":[-0.16536828082488,51.48755288887349],"type":"Point"}
}