{
  "type": "Feature",
  "properties": {
    "iso:country":"GB",
    "wof:name":"WN2 1RS",
    "wof:placetype":"postalcode"
},
  "geometry": {"coordinates":[-2.58843986112162,53.57092622214694],"type":"Point"}
}