{
  "type": "Feature",
  "properties": {
    "iso:country":"GB",
    "wof:name":"WS10 9QE",
    "wof:placetype":"postalcode"
},
  "geometry": {"coordinates":[-2.01147778116157,52.56276758718866],"type":"Point"}
}