{
  "type": "Feature",
  "properties": {
    "iso:country":"GB",
    "wof:name":"L21 9NQ",
    "wof:placetype":"postalcode"
},
  "geometry": {"coordinates":[-3.0080874030471,53.4742641186045],"type":"Point"}
}