{
  "type": "Feature",
  "properties": {
    "date:inception_lower":"1980-01-01",
    "date:inception_upper":"1980-01-31",
    "iso:country":"GB",
    "wof:name":"NG14 7FU",
    "wof:placetype":"postalcode"
},
  "geometry": {"coordinates":[-0.928548,53.037776],"type":"Point"}
}