{
  "type": "Feature",
  "properties": {
    "iso:country":"GB",
    "wof:name":"NG14 7FU",
    "wof:placetype":"postalcode"
},
  "geometry": {"coordinates":[-0.92854783781043,53.03777608588889],"type":"Point"}
}