{
  "type": "Feature",
  "properties": {
    "iso:country": "GB",
    "wof:name": "NG14 7FU",
    "wof:placetype": "postalcode"
  },
  "geometry": {"coordinates":[-0.928548,53.037776],"type":"Point"}
}
