{
  "type": "Feature",
  "properties": {
    "date:inception_lower": "1980-01-01",
    "date:inception_upper": "1980-01-01",
    "iso:country": "GB",
    "wof:name": "DT6 3HX",
    "wof:placetype": "postalcode"
  },
  "geometry": {"coordinates":[-2.735667,50.744802],"type":"Point"}
}
