{
  "type": "Feature",
  "properties": {
    "iso:country":"GB",
    "wof:name":"DT6 3HX",
    "wof:placetype":"postalcode"
},
  "geometry": {"coordinates":[-2.73560984156193,50.74479412637068],"type":"Point"}
}