{
  "type": "Feature",
  "properties": {
    "iso:country": "GB",
    "wof:name": "DT6 3HX",
    "wof:placetype": "postalcode"
  },
  "geometry": {"coordinates":[-2.735667,50.744802],"type":"Point"}
}
