{
  "type": "Feature",
  "properties": {
    "date:inception_lower": "1993-08-01",
    "date:inception_upper": "1993-08-01",
    "iso:country": "GB",
    "wof:name": "SA73 1RZ",
    "wof:placetype": "postalcode"
  },
  "geometry": {"coordinates":[-4.950965,51.71493],"type":"Point"}
}
