{
  "type": "Feature",
  "properties": {
    "iso:country":"GB",
    "wof:name":"SA73 1RZ",
    "wof:placetype":"postalcode"
},
  "geometry": {"coordinates":[-4.95096456794377,51.71492990974903],"type":"Point"}
}