{
  "type": "Feature",
  "properties": {
    "iso:country":"GB",
    "wof:name":"TN31 6RR",
    "wof:placetype":"postalcode"
},
  "geometry": {"coordinates":[0.63186360196067,50.9834292308818],"type":"Point"}
}