{
  "type": "Feature",
  "properties": {
    "iso:country": "GB",
    "wof:name": "GL7 3DH",
    "wof:placetype": "postalcode"
  },
  "geometry": {"coordinates":[-1.695996,51.694775],"type":"Point"}
}
