{
  "type": "Feature",
  "properties": {
    "iso:country":"GB",
    "wof:name":"IV2 4XU",
    "wof:placetype":"postalcode"
},
  "geometry": {"coordinates":[-4.24598751634678,57.45035452576999],"type":"Point"}
}