{
  "type": "Feature",
  "properties": {
    "iso:country":"GB",
    "wof:name":"SL6 4NU",
    "wof:placetype":"postalcode"
},
  "geometry": {"coordinates":[-0.7535023362569,51.51238994912669],"type":"Point"}
}