{
  "type": "Feature",
  "properties": {
    "iso:country":"GB",
    "wof:name":"PL14 4HP",
    "wof:placetype":"postalcode"
},
  "geometry": {"coordinates":[-4.47027404844912,50.45379190703789],"type":"Point"}
}