{
  "type": "Feature",
  "properties": {
    "iso:country":"GB",
    "wof:name":"EX34 9LR",
    "wof:placetype":"postalcode"
},
  "geometry": {"coordinates":[-4.12043425695661,51.20468491817454],"type":"Point"}
}