{
  "type": "Feature",
  "properties": {
    "date:inception_lower": "2018-03-01",
    "date:inception_upper": "2018-03-01",
    "iso:country": "GB",
    "wof:name": "LE67 3EY",
    "wof:placetype": "postalcode"
  },
  "geometry": {"coordinates":[-1.381074,52.72537],"type":"Point"}
}
