{
  "type": "Feature",
  "properties": {
    "iso:country": "GB",
    "wof:name": "B29 5BZ",
    "wof:placetype": "postalcode"
  },
  "geometry": {"coordinates":[-1.956473,52.437468],"type":"Point"}
}
