{
  "type": "Feature",
  "properties": {
    "iso:country":"GB",
    "wof:name":"B29 5BZ",
    "wof:placetype":"postalcode"
},
  "geometry": {"coordinates":[-1.95647348347447,52.43746764342569],"type":"Point"}
}