{
  "type": "Feature",
  "properties": {
    "date:inception_lower":"2004-09-01",
    "date:inception_upper":"2004-09-30",
    "iso:country":"GB",
    "wof:name":"B29 5BZ",
    "wof:placetype":"postalcode"
},
  "geometry": {"coordinates":[-1.956473,52.437468],"type":"Point"}
}