{
  "type": "Feature",
  "properties": {
    "iso:country":"GB",
    "wof:name":"B65 8DS",
    "wof:placetype":"postalcode"
},
  "geometry": {"coordinates":[-2.04551448728124,52.4818412853406],"type":"Point"}
}