{
  "type": "Feature",
  "properties": {
    "date:inception_lower":"1980-01-01",
    "date:inception_upper":"1980-01-31",
    "iso:country":"GB",
    "wof:name":"B65 8DS",
    "wof:placetype":"postalcode"
},
  "geometry": {"coordinates":[-2.045514,52.481841],"type":"Point"}
}