{
  "type": "Feature",
  "properties": {
    "date:inception_lower": "1980-01-01",
    "date:inception_upper": "1980-01-01",
    "iso:country": "GB",
    "wof:name": "LL40 1BL",
    "wof:placetype": "postalcode"
  },
  "geometry": {"coordinates":[-3.883285,52.743083],"type":"Point"}
}
