{
  "type": "Feature",
  "properties": {
    "iso:country":"GB",
    "wof:name":"KT12 5RG",
    "wof:placetype":"postalcode"
},
  "geometry": {"coordinates":[-0.40491350840697,51.37071118891923],"type":"Point"}
}