{
  "type": "Feature",
  "properties": {
    "date:inception_lower": "1980-01-01",
    "date:inception_upper": "1980-01-01",
    "iso:country": "GB",
    "wof:name": "KT12 5RG",
    "wof:placetype": "postalcode"
  },
  "geometry": {"coordinates":[-0.404913,51.370711],"type":"Point"}
}
