{
  "type": "Feature",
  "properties": {
    "iso:country":"GB",
    "wof:name":"NE30 4DH",
    "wof:placetype":"postalcode"
},
  "geometry": {"coordinates":[-1.42783309188496,55.01606626564029],"type":"Point"}
}