{
  "type": "Feature",
  "properties": {
    "date:inception_lower": "2003-03-01",
    "date:inception_upper": "2003-03-01",
    "iso:country": "GB",
    "wof:name": "NE30 4DH",
    "wof:placetype": "postalcode"
  },
  "geometry": {"coordinates":[-1.427833,55.016066],"type":"Point"}
}
