{
  "type": "Feature",
  "properties": {
    "iso:country":"GB",
    "wof:name":"MK6 5LZ",
    "wof:placetype":"postalcode"
},
  "geometry": {"coordinates":[-0.7567415871289,52.02581441269628],"type":"Point"}
}