{
  "type": "Feature",
  "properties": {
    "iso:country": "GB",
    "wof:name": "MK6 5LZ",
    "wof:placetype": "postalcode"
  },
  "geometry": {"coordinates":[-0.756742,52.025814],"type":"Point"}
}
