{
  "type": "Feature",
  "properties": {
    "iso:country":"GB",
    "wof:name":"CH8 9QB",
    "wof:placetype":"postalcode"
},
  "geometry": {"coordinates":[-3.26699522280653,53.30717048222288],"type":"Point"}
}