{
  "type": "Feature",
  "properties": {
    "iso:country":"GB",
    "wof:name":"SA68 0XG",
    "wof:placetype":"postalcode"
},
  "geometry": {"coordinates":[-4.7395234462859,51.74250185266317],"type":"Point"}
}