{
  "type": "Feature",
  "properties": {
    "iso:country":"GB",
    "wof:name":"SS12 9GR",
    "wof:placetype":"postalcode"
},
  "geometry": {"coordinates":[0.53852832238906,51.60105167426423],"type":"Point"}
}