{
  "type": "Feature",
  "properties": {
    "iso:country": "GB",
    "wof:name": "DT2 0LJ",
    "wof:placetype": "postalcode"
  },
  "geometry": {"coordinates":[-2.578071,50.836535],"type":"Point"}
}
