{
  "type": "Feature",
  "properties": {
    "iso:country":"GB",
    "wof:name":"E13 9NQ",
    "wof:placetype":"postalcode"
},
  "geometry": {"coordinates":[0.03828719734207,51.52395548361107],"type":"Point"}
}