{
  "type": "Feature",
  "properties": {
    "iso:country":"GB",
    "wof:name":"WA5 2JY",
    "wof:placetype":"postalcode"
},
  "geometry": {"coordinates":[-2.64753420247089,53.38334318708064],"type":"Point"}
}