{
  "type": "Feature",
  "properties": {
    "iso:country": "GB",
    "wof:name": "WA5 2JY",
    "wof:placetype": "postalcode"
  },
  "geometry": {"coordinates":[-2.647534,53.383343],"type":"Point"}
}
