{
  "type": "Feature",
  "properties": {
    "date:inception_lower": "1980-01-01",
    "date:inception_upper": "1980-01-01",
    "iso:country": "GB",
    "wof:name": "AL10 8AE",
    "wof:placetype": "postalcode"
  },
  "geometry": {"coordinates":[-0.222376,51.76057],"type":"Point"}
}
