{
  "type": "Feature",
  "properties": {
    "iso:country":"GB",
    "wof:name":"AL10 8AE",
    "wof:placetype":"postalcode"
},
  "geometry": {"coordinates":[-0.22241353481685,51.76057322760354],"type":"Point"}
}