{
  "type": "Feature",
  "properties": {
    "iso:country": "GB",
    "wof:name": "AL10 8AE",
    "wof:placetype": "postalcode"
  },
  "geometry": {"coordinates":[-0.222413,51.760573],"type":"Point"}
}
