{
  "type": "Feature",
  "properties": {
    "iso:country":"GB",
    "wof:name":"SL4 4XJ",
    "wof:placetype":"postalcode"
},
  "geometry": {"coordinates":[-0.65708167044321,51.47700328031951],"type":"Point"}
}