{
  "type": "Feature",
  "properties": {
    "date:inception_lower": "1980-01-01",
    "date:inception_upper": "1980-01-01",
    "iso:country": "GB",
    "wof:name": "SL4 4XJ",
    "wof:placetype": "postalcode"
  },
  "geometry": {"coordinates":[-0.657082,51.477003],"type":"Point"}
}
