{
  "type": "Feature",
  "properties": {
    "iso:country":"GB",
    "wof:name":"EH41 4PJ",
    "wof:placetype":"postalcode"
},
  "geometry": {"coordinates":[-2.6824071388258,55.89501635208544],"type":"Point"}
}