{
  "type": "Feature",
  "properties": {
    "iso:country":"GB",
    "wof:name":"SY10 7NU",
    "wof:placetype":"postalcode"
},
  "geometry": {"coordinates":[-3.11543108215996,52.92058225011693],"type":"Point"}
}