{
  "type": "Feature",
  "properties": {
    "iso:country": "GB",
    "wof:name": "SS9 1BL",
    "wof:placetype": "postalcode"
  },
  "geometry": {"coordinates":[0.655488,51.540373],"type":"Point"}
}
