{
  "type": "Feature",
  "properties": {
    "iso:country":"GB",
    "wof:name":"LS8 4BW",
    "wof:placetype":"postalcode"
},
  "geometry": {"coordinates":[-1.51184317686285,53.82228556479152],"type":"Point"}
}