{
  "type": "Feature",
  "properties": {
    "iso:country":"GB",
    "wof:name":"SE15 1TR",
    "wof:placetype":"postalcode"
},
  "geometry": {"coordinates":[-0.05536659038865,51.48379286892299],"type":"Point"}
}