{
  "type": "Feature",
  "properties": {
    "iso:country": "GB",
    "wof:name": "SE15 1TR",
    "wof:placetype": "postalcode"
  },
  "geometry": {"coordinates":[-0.055367,51.483793],"type":"Point"}
}
