{
  "type": "Feature",
  "properties": {
    "iso:country":"GB",
    "wof:name":"LS15 9ER",
    "wof:placetype":"postalcode"
},
  "geometry": {"coordinates":[-1.44668834400105,53.7912636924265],"type":"Point"}
}