{
  "type": "Feature",
  "properties": {
    "date:inception_lower":"1980-01-01",
    "date:inception_upper":"1980-01-31",
    "iso:country":"GB",
    "wof:name":"TQ2 8HR",
    "wof:placetype":"postalcode"
},
  "geometry": {"coordinates":[-3.540081,50.492904],"type":"Point"}
}