{
  "type": "Feature",
  "properties": {
    "iso:country":"GB",
    "wof:name":"TQ2 8HR",
    "wof:placetype":"postalcode"
},
  "geometry": {"coordinates":[-3.54008086944106,50.49290421224951],"type":"Point"}
}