{
  "type": "Feature",
  "properties": {
    "iso:country":"GB",
    "wof:name":"G68 9DU",
    "wof:placetype":"postalcode"
},
  "geometry": {"coordinates":[-4.04049696055698,55.93474250911719],"type":"Point"}
}