{
  "type": "Feature",
  "properties": {
    "date:inception_lower": "2021-09-01",
    "date:inception_upper": "2021-09-01",
    "iso:country": "GB",
    "wof:name": "SL6 7DF",
    "wof:placetype": "postalcode"
  },
  "geometry": {"coordinates":[-0.724203,51.529837],"type":"Point"}
}
