{
  "type": "Feature",
  "properties": {
    "date:inception_lower":"1980-01-01",
    "date:inception_upper":"1980-01-31",
    "iso:country":"GB",
    "wof:name":"CO7 7DP",
    "wof:placetype":"postalcode"
},
  "geometry": {"coordinates":[1.035246,51.870459],"type":"Point"}
}