{
  "type": "Feature",
  "properties": {
    "iso:country":"GB",
    "wof:name":"CO7 7DP",
    "wof:placetype":"postalcode"
},
  "geometry": {"coordinates":[1.03524622353726,51.87045905022738],"type":"Point"}
}