{
  "type": "Feature",
  "properties": {
    "iso:country": "GB",
    "wof:name": "LS7 3SH",
    "wof:placetype": "postalcode"
  },
  "geometry": {"coordinates":[-1.537967,53.825382],"type":"Point"}
}
