{
  "type": "Feature",
  "properties": {
    "iso:country":"GB",
    "wof:name":"YO21 1PH",
    "wof:placetype":"postalcode"
},
  "geometry": {"coordinates":[-0.61595242227903,54.48067799250808],"type":"Point"}
}