{
  "type": "Feature",
  "properties": {
    "iso:country": "GB",
    "wof:name": "YO21 1PH",
    "wof:placetype": "postalcode"
  },
  "geometry": {"coordinates":[-0.615952,54.480678],"type":"Point"}
}
