{
  "type": "Feature",
  "properties": {
    "date:inception_lower": "1980-01-01",
    "date:inception_upper": "1980-01-01",
    "iso:country": "GB",
    "wof:name": "BA2 8JF",
    "wof:placetype": "postalcode"
  },
  "geometry": {"coordinates":[-2.429835,51.311845],"type":"Point"}
}
