{
  "type": "Feature",
  "properties": {
    "iso:country":"GB",
    "wof:name":"BA2 8JF",
    "wof:placetype":"postalcode"
},
  "geometry": {"coordinates":[-2.42983526223303,51.31184501175256],"type":"Point"}
}