{
  "type": "Feature",
  "properties": {
    "iso:country": "GB",
    "wof:name": "BA2 8JF",
    "wof:placetype": "postalcode"
  },
  "geometry": {"coordinates":[-2.429835,51.311845],"type":"Point"}
}
