{
  "type": "Feature",
  "properties": {
    "iso:country": "GB",
    "wof:name": "HG1 3BW",
    "wof:placetype": "postalcode"
  },
  "geometry": {"coordinates":[-1.535399,54.011283],"type":"Point"}
}
