{
  "type": "Feature",
  "properties": {
    "iso:country":"GB",
    "wof:name":"CF82 7NZ",
    "wof:placetype":"postalcode"
},
  "geometry": {"coordinates":[-3.24145383428989,51.64514810392645],"type":"Point"}
}