{
  "type": "Feature",
  "properties": {
    "iso:country": "GB",
    "wof:name": "CF82 7NZ",
    "wof:placetype": "postalcode"
  },
  "geometry": {"coordinates":[-3.241454,51.645148],"type":"Point"}
}
