{
  "type": "Feature",
  "properties": {
    "date:inception_lower": "2013-11-01",
    "date:inception_upper": "2013-11-01",
    "iso:country": "GB",
    "wof:name": "MK12 5EP",
    "wof:placetype": "postalcode"
  },
  "geometry": {"coordinates":[-0.807091,52.067181],"type":"Point"}
}
