{
  "type": "Feature",
  "properties": {
    "iso:country": "GB",
    "wof:name": "MK12 5EP",
    "wof:placetype": "postalcode"
  },
  "geometry": {"coordinates":[-0.807091,52.067181],"type":"Point"}
}
