{
  "type": "Feature",
  "properties": {
    "iso:country":"GB",
    "wof:name":"MK12 5EP",
    "wof:placetype":"postalcode"
},
  "geometry": {"coordinates":[-0.80709150847118,52.06718143406698],"type":"Point"}
}