{
  "type": "Feature",
  "properties": {
    "iso:country": "GB",
    "wof:name": "NN4 7HT",
    "wof:placetype": "postalcode"
  },
  "geometry": {"coordinates":[-0.849724,52.222992],"type":"Point"}
}
