{
  "type": "Feature",
  "properties": {
    "iso:country": "GB",
    "wof:name": "NN4 7HT",
    "wof:placetype": "postalcode"
  },
  "geometry": {"coordinates":[-0.849683,52.225144],"type":"Point"}
}
