{
  "type": "Feature",
  "properties": {
    "iso:country":"GB",
    "wof:name":"NN4 7HT",
    "wof:placetype":"postalcode"
},
  "geometry": {"coordinates":[-0.84968346361888,52.22514355920524],"type":"Point"}
}