{
  "type": "Feature",
  "properties": {
    "date:inception_lower":"2013-11-01",
    "date:inception_upper":"2013-11-30",
    "iso:country":"GB",
    "wof:name":"NN4 7HT",
    "wof:placetype":"postalcode"
},
  "geometry": {"coordinates":[-0.849683,52.225144],"type":"Point"}
}