{
  "type": "Feature",
  "properties": {
    "iso:country": "GB",
    "wof:name": "NR13 5DD",
    "wof:placetype": "postalcode"
  },
  "geometry": {"coordinates":[1.396386,52.64201],"type":"Point"}
}
