{
  "type": "Feature",
  "properties": {
    "iso:country":"GB",
    "wof:name":"NR13 5DD",
    "wof:placetype":"postalcode"
},
  "geometry": {"coordinates":[1.39638613756929,52.64200966770676],"type":"Point"}
}