{
  "type": "Feature",
  "properties": {
    "date:inception_lower": "1980-01-01",
    "date:inception_upper": "1980-01-01",
    "iso:country": "GB",
    "wof:name": "NR13 5DD",
    "wof:placetype": "postalcode"
  },
  "geometry": {"coordinates":[1.396441,52.642061],"type":"Point"}
}
