{
  "type": "Feature",
  "properties": {
    "iso:country":"GB",
    "wof:name":"SO14 5FL",
    "wof:placetype":"postalcode"
},
  "geometry": {"coordinates":[-1.39295896209643,50.89977862348123],"type":"Point"}
}