{
  "type": "Feature",
  "properties": {
    "date:inception_lower":"1980-01-01",
    "date:inception_upper":"1980-01-31",
    "iso:country":"GB",
    "wof:name":"TA8 2RU",
    "wof:placetype":"postalcode"
},
  "geometry": {"coordinates":[-3.011671,51.293147],"type":"Point"}
}