{
  "type": "Feature",
  "properties": {
    "iso:country":"GB",
    "wof:name":"TA8 2RU",
    "wof:placetype":"postalcode"
},
  "geometry": {"coordinates":[-3.01167084143116,51.29314722783253],"type":"Point"}
}