{
  "type": "Feature",
  "properties": {
    "iso:country": "GB",
    "wof:name": "TA8 2RU",
    "wof:placetype": "postalcode"
  },
  "geometry": {"coordinates":[-3.011671,51.293147],"type":"Point"}
}
