{
  "type": "Feature",
  "properties": {
    "date:inception_lower": "2024-04-01",
    "date:inception_upper": "2024-04-01",
    "iso:country": "GB",
    "wof:name": "S36 2DD",
    "wof:placetype": "postalcode"
  },
  "geometry": {"coordinates":[-1.582097,53.473608],"type":"Point"}
}
