{
  "type": "Feature",
  "properties": {
    "date:inception_lower": "1980-01-01",
    "date:inception_upper": "1980-01-01",
    "iso:country": "GB",
    "wof:name": "NG33 5BA",
    "wof:placetype": "postalcode"
  },
  "geometry": {"coordinates":[-0.608681,52.835436],"type":"Point"}
}
