{
  "type": "Feature",
  "properties": {
    "iso:country": "GB",
    "wof:name": "NG33 5BA",
    "wof:placetype": "postalcode"
  },
  "geometry": {"coordinates":[-0.608681,52.835436],"type":"Point"}
}
