{
  "type": "Feature",
  "properties": {
    "iso:country":"GB",
    "wof:name":"NG33 5BA",
    "wof:placetype":"postalcode"
},
  "geometry": {"coordinates":[-0.60868143265645,52.83543605723541],"type":"Point"}
}