{
  "type": "Feature",
  "properties": {
    "iso:country": "GB",
    "wof:name": "KW10 6TT",
    "wof:placetype": "postalcode"
  },
  "geometry": {"coordinates":[-3.982215,57.970643],"type":"Point"}
}
