{
  "type": "Feature",
  "properties": {
    "date:inception_lower": "1980-01-01",
    "date:inception_upper": "1980-01-01",
    "iso:country": "GB",
    "wof:name": "KW10 6TT",
    "wof:placetype": "postalcode"
  },
  "geometry": {"coordinates":[-3.982235,57.970627],"type":"Point"}
}
