{
  "type": "Feature",
  "properties": {
    "iso:country":"GB",
    "wof:name":"BH9 1LT",
    "wof:placetype":"postalcode"
},
  "geometry": {"coordinates":[-1.87612874909313,50.7457194347337],"type":"Point"}
}