{
  "type": "Feature",
  "properties": {
    "iso:country":"GB",
    "wof:name":"HA3 5RA",
    "wof:placetype":"postalcode"
},
  "geometry": {"coordinates":[-0.33920395080792,51.5949842402088],"type":"Point"}
}