{
  "type": "Feature",
  "properties": {
    "date:inception_lower": "1980-01-01",
    "date:inception_upper": "1980-01-01",
    "iso:country": "GB",
    "wof:name": "BA15 2HJ",
    "wof:placetype": "postalcode"
  },
  "geometry": {"coordinates":[-2.278068,51.347057],"type":"Point"}
}
