{
  "type": "Feature",
  "properties": {
    "date:inception_lower": "2007-07-01",
    "date:inception_upper": "2007-07-01",
    "iso:country": "GB",
    "wof:name": "RH20 1FE",
    "wof:placetype": "postalcode"
  },
  "geometry": {"coordinates":[-0.510183,50.960783],"type":"Point"}
}
