{
  "type": "Feature",
  "properties": {
    "iso:country":"GB",
    "wof:name":"RH20 1FE",
    "wof:placetype":"postalcode"
},
  "geometry": {"coordinates":[-0.51018320261743,50.96078328433855],"type":"Point"}
}