{
  "type": "Feature",
  "properties": {
    "iso:country": "GB",
    "wof:name": "NE9 6AH",
    "wof:placetype": "postalcode"
  },
  "geometry": {"coordinates":[-1.601061,54.931055],"type":"Point"}
}
