{
  "type": "Feature",
  "properties": {
    "date:inception_lower": "1980-01-01",
    "date:inception_upper": "1980-01-01",
    "iso:country": "GB",
    "wof:name": "TD1 2SY",
    "wof:placetype": "postalcode"
  },
  "geometry": {"coordinates":[-2.908649,55.733696],"type":"Point"}
}
