{
  "type": "Feature",
  "properties": {
    "iso:country":"GB",
    "wof:name":"NE34 9RH",
    "wof:placetype":"postalcode"
},
  "geometry": {"coordinates":[-1.45418450950503,54.96766120087328],"type":"Point"}
}