{
  "type": "Feature",
  "properties": {
    "iso:country":"GB",
    "wof:name":"LL23 7AD",
    "wof:placetype":"postalcode"
},
  "geometry": {"coordinates":[-3.5994842443851,52.90969192628673],"type":"Point"}
}