{
  "type": "Feature",
  "properties": {
    "date:inception_lower": "2021-07-01",
    "date:inception_upper": "2021-07-01",
    "iso:country": "GB",
    "wof:name": "MK12 5SB",
    "wof:placetype": "postalcode"
  },
  "geometry": {"coordinates":[-0.810304,52.062478],"type":"Point"}
}
