{
  "type": "Feature",
  "properties": {
    "iso:country":"GB",
    "wof:name":"NW2 4JS",
    "wof:placetype":"postalcode"
},
  "geometry": {"coordinates":[-0.22045951687954,51.55309321788787],"type":"Point"}
}