{
  "type": "Feature",
  "properties": {
    "date:inception_lower": "2019-03-01",
    "date:inception_upper": "2019-03-01",
    "iso:country": "GB",
    "wof:name": "DN31 2FG",
    "wof:placetype": "postalcode"
  },
  "geometry": {"coordinates":[-0.106655,53.569742],"type":"Point"}
}
