{
  "type": "Feature",
  "properties": {
    "iso:country": "GB",
    "wof:name": "EH3 8DQ",
    "wof:placetype": "postalcode"
  },
  "geometry": {"coordinates":[-3.209533,55.943837],"type":"Point"}
}
