{
  "type": "Feature",
  "properties": {
    "iso:country":"GB",
    "wof:name":"ME14 3DQ",
    "wof:placetype":"postalcode"
},
  "geometry": {"coordinates":[0.51380752728076,51.30719190566107],"type":"Point"}
}