{
  "type": "Feature",
  "properties": {
    "iso:country":"GB",
    "wof:name":"SY12 9JP",
    "wof:placetype":"postalcode"
},
  "geometry": {"coordinates":[-2.91516605824348,52.91752953852628],"type":"Point"}
}