{
  "type": "Feature",
  "properties": {
    "iso:country": "GB",
    "wof:name": "SY12 9JP",
    "wof:placetype": "postalcode"
  },
  "geometry": {"coordinates":[-2.914686,52.917413],"type":"Point"}
}
