{
  "type": "Feature",
  "properties": {
    "iso:country": "GB",
    "wof:name": "CF23 5HN",
    "wof:placetype": "postalcode"
  },
  "geometry": {"coordinates":[-3.175267,51.500549],"type":"Point"}
}
