{
  "type": "Feature",
  "properties": {
    "date:inception_lower": "1999-06-01",
    "date:inception_upper": "1999-06-01",
    "iso:country": "GB",
    "wof:name": "CF23 5HN",
    "wof:placetype": "postalcode"
  },
  "geometry": {"coordinates":[-3.175267,51.500549],"type":"Point"}
}
