{
  "type": "Feature",
  "properties": {
    "iso:country":"GB",
    "wof:name":"TR13 9RY",
    "wof:placetype":"postalcode"
},
  "geometry": {"coordinates":[-5.35083972264035,50.1110513670268],"type":"Point"}
}