{
  "type": "Feature",
  "properties": {
    "date:inception_lower":"2014-07-01",
    "date:inception_upper":"2014-07-31",
    "iso:country":"GB",
    "wof:name":"BS22 9WR",
    "wof:placetype":"postalcode"
},
  "geometry": {"coordinates":[-2.956812,51.366558],"type":"Point"}
}