{
  "type": "Feature",
  "properties": {
    "iso:country": "GB",
    "wof:name": "BS22 9WR",
    "wof:placetype": "postalcode"
  },
  "geometry": {"coordinates":[-2.956812,51.366558],"type":"Point"}
}
