{
  "type": "Feature",
  "properties": {
    "iso:country":"GB",
    "wof:name":"YO51 9AU",
    "wof:placetype":"postalcode"
},
  "geometry": {"coordinates":[-1.3916398482613,54.09031206507531],"type":"Point"}
}