{
  "type": "Feature",
  "properties": {
    "iso:country":"GB",
    "wof:name":"TA4 4RJ",
    "wof:placetype":"postalcode"
},
  "geometry": {"coordinates":[-3.30879264837647,51.16592754877582],"type":"Point"}
}