{
  "type": "Feature",
  "properties": {
    "iso:country": "GB",
    "wof:name": "CF5 4SA",
    "wof:placetype": "postalcode"
  },
  "geometry": {"coordinates":[-3.272242,51.468497],"type":"Point"}
}
