{
  "type": "Feature",
  "properties": {
    "date:inception_lower": "1980-01-01",
    "date:inception_upper": "1980-01-01",
    "iso:country": "GB",
    "wof:name": "RH7 6DW",
    "wof:placetype": "postalcode"
  },
  "geometry": {"coordinates":[-0.015007,51.179399],"type":"Point"}
}
