{
  "type": "Feature",
  "properties": {
    "iso:country":"GB",
    "wof:name":"RH7 6DW",
    "wof:placetype":"postalcode"
},
  "geometry": {"coordinates":[-0.01500696199109,51.17939926154185],"type":"Point"}
}