{
  "type": "Feature",
  "properties": {
    "iso:country": "GB",
    "wof:name": "BN3 1HJ",
    "wof:placetype": "postalcode"
  },
  "geometry": {"coordinates":[-0.160676,50.823627],"type":"Point"}
}
