{
  "type": "Feature",
  "properties": {
    "iso:country":"GB",
    "wof:name":"BN3 1HJ",
    "wof:placetype":"postalcode"
},
  "geometry": {"coordinates":[-0.16067604518036,50.82362659160835],"type":"Point"}
}