{
  "type": "Feature",
  "properties": {
    "iso:country":"GB",
    "wof:name":"LL20 7LT",
    "wof:placetype":"postalcode"
},
  "geometry": {"coordinates":[-3.21008298228865,52.96942320709795],"type":"Point"}
}