{
  "type": "Feature",
  "properties": {
    "date:inception_lower": "2006-05-01",
    "date:inception_upper": "2006-05-01",
    "iso:country": "GB",
    "wof:name": "BS41 9EG",
    "wof:placetype": "postalcode"
  },
  "geometry": {"coordinates":[-2.671913,51.427321],"type":"Point"}
}
