{
  "type": "Feature",
  "properties": {
    "iso:country":"GB",
    "wof:name":"LS24 9WN",
    "wof:placetype":"postalcode"
},
  "geometry": {"coordinates":[-1.26552458442921,53.88565528834246],"type":"Point"}
}