{
  "type": "Feature",
  "properties": {
    "date:inception_lower": "1980-01-01",
    "date:inception_upper": "1980-01-01",
    "iso:country": "GB",
    "wof:name": "NP4 6UD",
    "wof:placetype": "postalcode"
  },
  "geometry": {"coordinates":[-3.082589,51.69247],"type":"Point"}
}
