{
  "type": "Feature",
  "properties": {
    "iso:country":"GB",
    "wof:name":"NP4 6UD",
    "wof:placetype":"postalcode"
},
  "geometry": {"coordinates":[-3.08258924299601,51.6924696701183],"type":"Point"}
}