{
  "type": "Feature",
  "properties": {
    "date:inception_lower":"1980-01-01",
    "date:inception_upper":"1980-01-31",
    "iso:country":"GB",
    "wof:name":"WR2 6NQ",
    "wof:placetype":"postalcode"
},
  "geometry": {"coordinates":[-2.260071,52.227331],"type":"Point"}
}