{
  "type": "Feature",
  "properties": {
    "date:inception_lower":"2015-11-01",
    "date:inception_upper":"2015-11-30",
    "iso:country":"GB",
    "wof:name":"WN6 0US",
    "wof:placetype":"postalcode"
},
  "geometry": {"coordinates":[-2.684617,53.591643],"type":"Point"}
}