{
  "type": "Feature",
  "properties": {
    "date:inception_lower": "2016-01-01",
    "date:inception_upper": "2016-01-01",
    "iso:country": "GB",
    "wof:name": "SN15 3HR",
    "wof:placetype": "postalcode"
  },
  "geometry": {"coordinates":[-2.113613,51.45819],"type":"Point"}
}
