{
  "type": "Feature",
  "properties": {
    "iso:country":"GB",
    "wof:name":"BD2 1AN",
    "wof:placetype":"postalcode"
},
  "geometry": {"coordinates":[-1.75851478437592,53.81070369368446],"type":"Point"}
}