{
  "type": "Feature",
  "properties": {
    "iso:country":"GB",
    "wof:name":"EX8 2HX",
    "wof:placetype":"postalcode"
},
  "geometry": {"coordinates":[-3.39044966358125,50.61942829109751],"type":"Point"}
}