{
  "type": "Feature",
  "properties": {
    "date:inception_lower": "2019-09-01",
    "date:inception_upper": "2019-09-01",
    "iso:country": "GB",
    "wof:name": "S3 8BS",
    "wof:placetype": "postalcode"
  },
  "geometry": {"coordinates":[-1.474317,53.38923],"type":"Point"}
}
