{
  "type": "Feature",
  "properties": {
    "iso:country":"GB",
    "wof:name":"BA9 9LL",
    "wof:placetype":"postalcode"
},
  "geometry": {"coordinates":[-2.41163953692926,51.05622285400393],"type":"Point"}
}