{
  "type": "Feature",
  "properties": {
    "iso:country":"GB",
    "wof:name":"DL2 3HH",
    "wof:placetype":"postalcode"
},
  "geometry": {"coordinates":[-1.72112740263198,54.57620481419736],"type":"Point"}
}