{
  "type": "Feature",
  "properties": {
    "date:inception_lower": "1980-01-01",
    "date:inception_upper": "1980-01-01",
    "iso:country": "GB",
    "wof:name": "SL3 8RB",
    "wof:placetype": "postalcode"
  },
  "geometry": {"coordinates":[-0.539829,51.489468],"type":"Point"}
}
