{
  "type": "Feature",
  "properties": {
    "iso:country":"GB",
    "wof:name":"SL3 8RB",
    "wof:placetype":"postalcode"
},
  "geometry": {"coordinates":[-0.53982869355688,51.48946789928566],"type":"Point"}
}