{
  "type": "Feature",
  "properties": {
    "iso:country":"GB",
    "wof:name":"CV2 5GG",
    "wof:placetype":"postalcode"
},
  "geometry": {"coordinates":[-1.46533567425364,52.41323544341365],"type":"Point"}
}