{
  "type": "Feature",
  "properties": {
    "iso:country":"GB",
    "wof:name":"HX3 8PE",
    "wof:placetype":"postalcode"
},
  "geometry": {"coordinates":[-1.8059110923016,53.72845944250241],"type":"Point"}
}