{
  "type": "Feature",
  "properties": {
    "date:inception_lower": "1980-01-01",
    "date:inception_upper": "1980-01-01",
    "iso:country": "GB",
    "wof:name": "IG7 4HG",
    "wof:placetype": "postalcode"
  },
  "geometry": {"coordinates":[0.103706,51.610524],"type":"Point"}
}
