{
  "type": "Feature",
  "properties": {
    "iso:country":"GB",
    "wof:name":"DN16 1DE",
    "wof:placetype":"postalcode"
},
  "geometry": {"coordinates":[-0.62846258652919,53.57709950905453],"type":"Point"}
}