{
  "type": "Feature",
  "properties": {
    "date:inception_lower": "1980-01-01",
    "date:inception_upper": "1980-01-01",
    "iso:country": "GB",
    "wof:name": "DN16 1DE",
    "wof:placetype": "postalcode"
  },
  "geometry": {"coordinates":[-0.628463,53.5771],"type":"Point"}
}
