{
  "type": "Feature",
  "properties": {
    "iso:country": "GB",
    "wof:name": "TF2 6PJ",
    "wof:placetype": "postalcode"
  },
  "geometry": {"coordinates":[-2.460117,52.712578],"type":"Point"}
}
