{
  "type": "Feature",
  "properties": {
    "iso:country":"GB",
    "wof:name":"TF2 6PJ",
    "wof:placetype":"postalcode"
},
  "geometry": {"coordinates":[-2.46011702881589,52.71257806870108],"type":"Point"}
}