{
  "type": "Feature",
  "properties": {
    "date:inception_lower": "1980-01-01",
    "date:inception_upper": "1980-01-01",
    "iso:country": "GB",
    "wof:name": "B79 9HB",
    "wof:placetype": "postalcode"
  },
  "geometry": {"coordinates":[-1.645345,52.690935],"type":"Point"}
}
