{
  "type": "Feature",
  "properties": {
    "iso:country":"GB",
    "wof:name":"B79 9HB",
    "wof:placetype":"postalcode"
},
  "geometry": {"coordinates":[-1.65110308203866,52.68764437511459],"type":"Point"}
}