{
  "type": "Feature",
  "properties": {
    "iso:country": "GB",
    "wof:name": "PO33 3TU",
    "wof:placetype": "postalcode"
  },
  "geometry": {"coordinates":[-1.1859,50.72147],"type":"Point"}
}
