{
  "type": "Feature",
  "properties": {
    "iso:country":"GB",
    "wof:name":"BB9 0SS",
    "wof:placetype":"postalcode"
},
  "geometry": {"coordinates":[-2.20883665009336,53.82597159080992],"type":"Point"}
}