{
  "type": "Feature",
  "properties": {
    "iso:country": "GB",
    "wof:name": "CO5 8DH",
    "wof:placetype": "postalcode"
  },
  "geometry": {"coordinates":[0.914793,51.780206],"type":"Point"}
}
