{
  "type": "Feature",
  "properties": {
    "iso:country":"GB",
    "wof:name":"CO5 8DH",
    "wof:placetype":"postalcode"
},
  "geometry": {"coordinates":[0.91479272648144,51.78020630850252],"type":"Point"}
}