{
  "type": "Feature",
  "properties": {
    "iso:country": "GB",
    "wof:name": "SN14 8LD",
    "wof:placetype": "postalcode"
  },
  "geometry": {"coordinates":[-2.369167,51.458958],"type":"Point"}
}
