{
  "type": "Feature",
  "properties": {
    "iso:country":"GB",
    "wof:name":"SN14 8LD",
    "wof:placetype":"postalcode"
},
  "geometry": {"coordinates":[-2.36916696643153,51.45895818532304],"type":"Point"}
}