{
  "type": "Feature",
  "properties": {
    "iso:country":"GB",
    "wof:name":"HG1 4JY",
    "wof:placetype":"postalcode"
},
  "geometry": {"coordinates":[-1.52233081296367,54.0059500483574],"type":"Point"}
}