{
  "type": "Feature",
  "properties": {
    "iso:country":"GB",
    "wof:name":"SK8 5DL",
    "wof:placetype":"postalcode"
},
  "geometry": {"coordinates":[-2.19440311997128,53.37872178752013],"type":"Point"}
}