{
  "type": "Feature",
  "properties": {
    "iso:country":"GB",
    "wof:name":"AL4 9HN",
    "wof:placetype":"postalcode"
},
  "geometry": {"coordinates":[-0.27600861259676,51.76984202766882],"type":"Point"}
}