{
  "type": "Feature",
  "properties": {
    "iso:country": "GB",
    "wof:name": "AL4 9HN",
    "wof:placetype": "postalcode"
  },
  "geometry": {"coordinates":[-0.275998,51.769875],"type":"Point"}
}
