{
  "type": "Feature",
  "properties": {
    "iso:country": "GB",
    "wof:name": "SK9 7AB",
    "wof:placetype": "postalcode"
  },
  "geometry": {"coordinates":[-2.236386,53.297002],"type":"Point"}
}
