{
  "type": "Feature",
  "properties": {
    "iso:country":"GB",
    "wof:name":"DN11 9EN",
    "wof:placetype":"postalcode"
},
  "geometry": {"coordinates":[-1.09977664188563,53.43417661927604],"type":"Point"}
}