{
  "type": "Feature",
  "properties": {
    "iso:country": "GB",
    "wof:name": "IP26 5NQ",
    "wof:placetype": "postalcode"
  },
  "geometry": {"coordinates":[0.597894,52.538875],"type":"Point"}
}
