{
  "type": "Feature",
  "properties": {
    "iso:country":"GB",
    "wof:name":"IP26 5NQ",
    "wof:placetype":"postalcode"
},
  "geometry": {"coordinates":[0.59934374447107,52.53845607798944],"type":"Point"}
}