{
  "type": "Feature",
  "properties": {
    "iso:country":"GB",
    "wof:name":"HR1 1RH",
    "wof:placetype":"postalcode"
},
  "geometry": {"coordinates":[-2.69414452749099,52.05710849405457],"type":"Point"}
}