{
  "type": "Feature",
  "properties": {
    "iso:country": "GB",
    "wof:name": "HR1 1RH",
    "wof:placetype": "postalcode"
  },
  "geometry": {"coordinates":[-2.694132,52.057127],"type":"Point"}
}
