{
  "type": "Feature",
  "properties": {
    "iso:country":"GB",
    "wof:name":"SO14 3FY",
    "wof:placetype":"postalcode"
},
  "geometry": {"coordinates":[-1.39554542105535,50.89660869362414],"type":"Point"}
}