{
  "type": "Feature",
  "properties": {
    "date:inception_lower": "1998-12-01",
    "date:inception_upper": "1998-12-01",
    "iso:country": "GB",
    "wof:name": "PE9 3BS",
    "wof:placetype": "postalcode"
  },
  "geometry": {"coordinates":[-0.384571,52.622004],"type":"Point"}
}
