{
  "type": "Feature",
  "properties": {
    "iso:country":"GB",
    "wof:name":"CV31 2NN",
    "wof:placetype":"postalcode"
},
  "geometry": {"coordinates":[-1.52677940968269,52.27666570348666],"type":"Point"}
}