{
  "type": "Feature",
  "properties": {
    "iso:country": "GB",
    "wof:name": "CV31 2NN",
    "wof:placetype": "postalcode"
  },
  "geometry": {"coordinates":[-1.526768,52.276671],"type":"Point"}
}
