{
  "type": "Feature",
  "properties": {
    "date:inception_lower": "1980-01-01",
    "date:inception_upper": "1980-01-01",
    "iso:country": "GB",
    "wof:name": "IP13 8EH",
    "wof:placetype": "postalcode"
  },
  "geometry": {"coordinates":[1.336208,52.310266],"type":"Point"}
}
