{
  "type": "Feature",
  "properties": {
    "date:inception_lower": "2011-05-01",
    "date:inception_upper": "2011-05-01",
    "iso:country": "GB",
    "wof:name": "E14 9RR",
    "wof:placetype": "postalcode"
  },
  "geometry": {"coordinates":[-0.018645,51.500976],"type":"Point"}
}
