{
  "type": "Feature",
  "properties": {
    "iso:country":"GB",
    "wof:name":"E14 9RR",
    "wof:placetype":"postalcode"
},
  "geometry": {"coordinates":[-0.01875211089331,51.50145303433114],"type":"Point"}
}