{
  "type": "Feature",
  "properties": {
    "iso:country":"GB",
    "wof:name":"LE7 9XN",
    "wof:placetype":"postalcode"
},
  "geometry": {"coordinates":[-0.84661323760494,52.64028570354188],"type":"Point"}
}