{
  "type": "Feature",
  "properties": {
    "date:inception_lower":"1999-12-01",
    "date:inception_upper":"1999-12-31",
    "iso:country":"GB",
    "wof:name":"LE7 9XN",
    "wof:placetype":"postalcode"
},
  "geometry": {"coordinates":[-0.846604,52.640304],"type":"Point"}
}