{
  "type": "Feature",
  "properties": {
    "iso:country": "GB",
    "wof:name": "LE7 9XN",
    "wof:placetype": "postalcode"
  },
  "geometry": {"coordinates":[-0.846604,52.640304],"type":"Point"}
}
