{
  "type": "Feature",
  "properties": {
    "date:inception_lower": "1980-01-01",
    "date:inception_upper": "1980-01-01",
    "iso:country": "GB",
    "wof:name": "S60 2QG",
    "wof:placetype": "postalcode"
  },
  "geometry": {"coordinates":[-1.348569,53.425707],"type":"Point"}
}
