{
  "type": "Feature",
  "properties": {
    "iso:country":"GB",
    "wof:name":"S60 2QG",
    "wof:placetype":"postalcode"
},
  "geometry": {"coordinates":[-1.34856872885309,53.42570665185416],"type":"Point"}
}