{
  "type": "Feature",
  "properties": {
    "iso:country":"GB",
    "wof:name":"NG31 8UQ",
    "wof:placetype":"postalcode"
},
  "geometry": {"coordinates":[-0.66584493383561,52.91840472345888],"type":"Point"}
}