{
  "type": "Feature",
  "properties": {
    "iso:country": "GB",
    "wof:name": "NG31 8UQ",
    "wof:placetype": "postalcode"
  },
  "geometry": {"coordinates":[-0.665845,52.918405],"type":"Point"}
}
