{
  "type": "Feature",
  "properties": {
    "date:inception_lower":"2014-06-01",
    "date:inception_upper":"2014-06-30",
    "iso:country":"GB",
    "wof:name":"NG31 8UQ",
    "wof:placetype":"postalcode"
},
  "geometry": {"coordinates":[-0.665845,52.918405],"type":"Point"}
}