{
  "type": "Feature",
  "properties": {
    "iso:country":"GB",
    "wof:name":"WV1 2AY",
    "wof:placetype":"postalcode"
},
  "geometry": {"coordinates":[-2.09272603889404,52.58846949522225],"type":"Point"}
}