{
  "type": "Feature",
  "properties": {
    "iso:country": "GB",
    "wof:name": "BS37 6NP",
    "wof:placetype": "postalcode"
  },
  "geometry": {"coordinates":[-2.383749,51.538019],"type":"Point"}
}
