{
  "type": "Feature",
  "properties": {
    "iso:country":"GB",
    "wof:name":"BS37 6NP",
    "wof:placetype":"postalcode"
},
  "geometry": {"coordinates":[-2.38374910702551,51.53801865390442],"type":"Point"}
}