{
  "type": "Feature",
  "properties": {
    "iso:country": "GB",
    "wof:name": "NE71 6HN",
    "wof:placetype": "postalcode"
  },
  "geometry": {"coordinates":[-2.078127,55.589361],"type":"Point"}
}
