{
  "type": "Feature",
  "properties": {
    "iso:country":"GB",
    "wof:name":"NE71 6HN",
    "wof:placetype":"postalcode"
},
  "geometry": {"coordinates":[-2.0781272289635,55.58936100620841],"type":"Point"}
}