{
  "type": "Feature",
  "properties": {
    "date:inception_lower": "2012-11-01",
    "date:inception_upper": "2012-11-01",
    "iso:country": "GB",
    "wof:name": "TA6 3PJ",
    "wof:placetype": "postalcode"
  },
  "geometry": {"coordinates":[-3.005954,51.125267],"type":"Point"}
}
