{
  "type": "Feature",
  "properties": {
    "iso:country": "GB",
    "wof:name": "SA1 6TG",
    "wof:placetype": "postalcode"
  },
  "geometry": {"coordinates":[-3.956757,51.630791],"type":"Point"}
}
