{
  "type": "Feature",
  "properties": {
    "iso:country": "GB",
    "wof:name": "AB41 9JL",
    "wof:placetype": "postalcode"
  },
  "geometry": {"coordinates":[-2.068604,57.36924],"type":"Point"}
}
