{
  "type": "Feature",
  "properties": {
    "iso:country":"GB",
    "wof:name":"AB41 9JL",
    "wof:placetype":"postalcode"
},
  "geometry": {"coordinates":[-2.06801804991479,57.3693005007387],"type":"Point"}
}