{
  "type": "Feature",
  "properties": {
    "iso:country":"GB",
    "wof:name":"PR2 1LQ",
    "wof:placetype":"postalcode"
},
  "geometry": {"coordinates":[-2.754114150444,53.76695862118379],"type":"Point"}
}