{
  "type": "Feature",
  "properties": {
    "date:inception_lower": "1980-01-01",
    "date:inception_upper": "1980-01-01",
    "iso:country": "GB",
    "wof:name": "TR26 3LA",
    "wof:placetype": "postalcode"
  },
  "geometry": {"coordinates":[-5.437539,50.186865],"type":"Point"}
}
