{
  "type": "Feature",
  "properties": {
    "iso:country":"GB",
    "wof:name":"TR26 3LA",
    "wof:placetype":"postalcode"
},
  "geometry": {"coordinates":[-5.43760177555883,50.18671822833421],"type":"Point"}
}