{
  "type": "Feature",
  "properties": {
    "date:inception_lower": "1980-01-01",
    "date:inception_upper": "1980-01-01",
    "iso:country": "GB",
    "wof:name": "G45 9PX",
    "wof:placetype": "postalcode"
  },
  "geometry": {"coordinates":[-4.24666,55.800661],"type":"Point"}
}
