{
  "type": "Feature",
  "properties": {
    "date:inception_lower": "1992-08-01",
    "date:inception_upper": "1992-08-01",
    "iso:country": "GB",
    "wof:name": "OX33 1JG",
    "wof:placetype": "postalcode"
  },
  "geometry": {"coordinates":[-1.120966,51.74204],"type":"Point"}
}
