{
  "type": "Feature",
  "properties": {
    "iso:country": "GB",
    "wof:name": "OX33 1JG",
    "wof:placetype": "postalcode"
  },
  "geometry": {"coordinates":[-1.120966,51.74204],"type":"Point"}
}
