{
  "type": "Feature",
  "properties": {
    "iso:country":"GB",
    "wof:name":"BL8 2JE",
    "wof:placetype":"postalcode"
},
  "geometry": {"coordinates":[-2.33306174685574,53.58643548383348],"type":"Point"}
}