{
  "type": "Feature",
  "properties": {
    "iso:country":"GB",
    "wof:name":"LE4 2PW",
    "wof:placetype":"postalcode"
},
  "geometry": {"coordinates":[-1.14084093757148,52.66802763178251],"type":"Point"}
}