{
  "type": "Feature",
  "properties": {
    "iso:country": "GB",
    "wof:name": "GL54 3LU",
    "wof:placetype": "postalcode"
  },
  "geometry": {"coordinates":[-1.810713,51.830608],"type":"Point"}
}
