{
  "type": "Feature",
  "properties": {
    "iso:country":"GB",
    "wof:name":"GL54 3LU",
    "wof:placetype":"postalcode"
},
  "geometry": {"coordinates":[-1.81072444747726,51.83060061241083],"type":"Point"}
}