{
  "type": "Feature",
  "properties": {
    "date:inception_lower": "1980-01-01",
    "date:inception_upper": "1980-01-01",
    "iso:country": "GB",
    "wof:name": "GL54 3LU",
    "wof:placetype": "postalcode"
  },
  "geometry": {"coordinates":[-1.810713,51.830608],"type":"Point"}
}
