{
  "type": "Feature",
  "properties": {
    "iso:country":"GB",
    "wof:name":"N1 7DE",
    "wof:placetype":"postalcode"
},
  "geometry": {"coordinates":[-0.0950291171278,51.53637599124792],"type":"Point"}
}