{
  "type": "Feature",
  "properties": {
    "date:inception_lower":"1980-01-01",
    "date:inception_upper":"1980-01-31",
    "iso:country":"GB",
    "wof:name":"N1 7DE",
    "wof:placetype":"postalcode"
},
  "geometry": {"coordinates":[-0.09493,51.536404],"type":"Point"}
}