{
  "type": "Feature",
  "properties": {
    "date:inception_lower": "1995-07-01",
    "date:inception_upper": "1995-07-01",
    "iso:country": "GB",
    "wof:name": "PR4 1YF",
    "wof:placetype": "postalcode"
  },
  "geometry": {"coordinates":[-2.89339,53.755773],"type":"Point"}
}
