{
  "type": "Feature",
  "properties": {
    "iso:country":"GB",
    "wof:name":"PR4 1YF",
    "wof:placetype":"postalcode"
},
  "geometry": {"coordinates":[-2.89338961886598,53.75577259206722],"type":"Point"}
}