{
  "type": "Feature",
  "properties": {
    "iso:country": "GB",
    "wof:name": "PR4 1YF",
    "wof:placetype": "postalcode"
  },
  "geometry": {"coordinates":[-2.89339,53.755773],"type":"Point"}
}
