{
  "type": "Feature",
  "properties": {
    "date:inception_lower": "1980-01-01",
    "date:inception_upper": "1980-01-01",
    "iso:country": "GB",
    "wof:name": "KA7 3SY",
    "wof:placetype": "postalcode"
  },
  "geometry": {"coordinates":[-4.603024,55.446962],"type":"Point"}
}
