{
  "type": "Feature",
  "properties": {
    "iso:country":"GB",
    "wof:name":"CW12 4QT",
    "wof:placetype":"postalcode"
},
  "geometry": {"coordinates":[-2.23553123704093,53.1688497506086],"type":"Point"}
}