{
  "type": "Feature",
  "properties": {
    "date:inception_lower": "1980-01-01",
    "date:inception_upper": "1980-01-01",
    "iso:country": "GB",
    "wof:name": "CW12 4QT",
    "wof:placetype": "postalcode"
  },
  "geometry": {"coordinates":[-2.235531,53.16885],"type":"Point"}
}
