{
  "type": "Feature",
  "properties": {
    "iso:country":"GB",
    "wof:name":"EN8 9SE",
    "wof:placetype":"postalcode"
},
  "geometry": {"coordinates":[-0.02557064406342,51.70809019468708],"type":"Point"}
}