{
  "type": "Feature",
  "properties": {
    "date:inception_lower":"1998-12-01",
    "date:inception_upper":"1998-12-31",
    "iso:country":"GB",
    "wof:name":"EN8 9SE",
    "wof:placetype":"postalcode"
},
  "geometry": {"coordinates":[-0.025571,51.70809],"type":"Point"}
}