{
  "type": "Feature",
  "properties": {
    "iso:country":"GB",
    "wof:name":"RH11 9AU",
    "wof:placetype":"postalcode"
},
  "geometry": {"coordinates":[-0.2159852962666,51.08745565495588],"type":"Point"}
}