{
  "type": "Feature",
  "properties": {
    "date:inception_lower":"1980-01-01",
    "date:inception_upper":"1980-01-31",
    "iso:country":"GB",
    "wof:name":"NR3 1JP",
    "wof:placetype":"postalcode"
},
  "geometry": {"coordinates":[1.297577,52.631592],"type":"Point"}
}