{
  "type": "Feature",
  "properties": {
    "iso:country":"GB",
    "wof:name":"NR3 1JP",
    "wof:placetype":"postalcode"
},
  "geometry": {"coordinates":[1.29757676939658,52.63159177672583],"type":"Point"}
}