{
  "type": "Feature",
  "properties": {
    "iso:country":"GB",
    "wof:name":"BN1 3PG",
    "wof:placetype":"postalcode"
},
  "geometry": {"coordinates":[-0.14274546546466,50.82965592629147],"type":"Point"}
}