{
  "type": "Feature",
  "properties": {
    "date:inception_lower": "1994-12-01",
    "date:inception_upper": "1994-12-01",
    "iso:country": "GB",
    "wof:name": "SO18 1BJ",
    "wof:placetype": "postalcode"
  },
  "geometry": {"coordinates":[-1.372286,50.91751],"type":"Point"}
}
