{
  "type": "Feature",
  "properties": {
    "iso:country": "GB",
    "wof:name": "SO18 1BJ",
    "wof:placetype": "postalcode"
  },
  "geometry": {"coordinates":[-1.372286,50.91751],"type":"Point"}
}
