{
  "type": "Feature",
  "properties": {
    "iso:country": "GB",
    "wof:name": "WD24 7QQ",
    "wof:placetype": "postalcode"
  },
  "geometry": {"coordinates":[-0.392762,51.676074],"type":"Point"}
}
