{
  "type": "Feature",
  "properties": {
    "iso:country":"GB",
    "wof:name":"WD24 7QQ",
    "wof:placetype":"postalcode"
},
  "geometry": {"coordinates":[-0.39276188457118,51.67607389165148],"type":"Point"}
}