{
  "type": "Feature",
  "properties": {
    "iso:country": "GB",
    "wof:name": "AB32 6BH",
    "wof:placetype": "postalcode"
  },
  "geometry": {"coordinates":[-2.288441,57.146015],"type":"Point"}
}
