{
  "type": "Feature",
  "properties": {
    "date:inception_lower": "2012-09-01",
    "date:inception_upper": "2012-09-01",
    "iso:country": "GB",
    "wof:name": "AB32 6BH",
    "wof:placetype": "postalcode"
  },
  "geometry": {"coordinates":[-2.288441,57.146015],"type":"Point"}
}
