{
  "type": "Feature",
  "properties": {
    "iso:country":"GB",
    "wof:name":"AB32 6BH",
    "wof:placetype":"postalcode"
},
  "geometry": {"coordinates":[-2.28844064302511,57.14601458722574],"type":"Point"}
}