{
  "type": "Feature",
  "properties": {
    "iso:country":"GB",
    "wof:name":"NW9 5PZ",
    "wof:placetype":"postalcode"
},
  "geometry": {"coordinates":[-0.25280989535886,51.59571730469484],"type":"Point"}
}