{
  "type": "Feature",
  "properties": {
    "date:inception_lower": "2013-04-01",
    "date:inception_upper": "2013-04-01",
    "iso:country": "GB",
    "wof:name": "NW9 5PZ",
    "wof:placetype": "postalcode"
  },
  "geometry": {"coordinates":[-0.252752,51.595828],"type":"Point"}
}
