{
  "type": "Feature",
  "properties": {
    "iso:country":"GB",
    "wof:name":"WN7 4EU",
    "wof:placetype":"postalcode"
},
  "geometry": {"coordinates":[-2.52183130399717,53.4961008904714],"type":"Point"}
}