{
  "type": "Feature",
  "properties": {
    "date:inception_lower": "2009-05-01",
    "date:inception_upper": "2009-05-01",
    "iso:country": "GB",
    "wof:name": "WN7 4EU",
    "wof:placetype": "postalcode"
  },
  "geometry": {"coordinates":[-2.521831,53.496101],"type":"Point"}
}
