{
  "type": "Feature",
  "properties": {
    "iso:country": "GB",
    "wof:name": "WN7 4EU",
    "wof:placetype": "postalcode"
  },
  "geometry": {"coordinates":[-2.521831,53.496101],"type":"Point"}
}
