{
  "type": "Feature",
  "properties": {
    "date:inception_lower": "2007-09-01",
    "date:inception_upper": "2007-09-01",
    "iso:country": "GB",
    "wof:name": "RG12 8AR",
    "wof:placetype": "postalcode"
  },
  "geometry": {"coordinates":[-0.781049,51.408345],"type":"Point"}
}
