{
  "type": "Feature",
  "properties": {
    "iso:country":"GB",
    "wof:name":"RG12 8AR",
    "wof:placetype":"postalcode"
},
  "geometry": {"coordinates":[-0.78104904461803,51.40834547884633],"type":"Point"}
}