{
  "type": "Feature",
  "properties": {
    "iso:country":"GB",
    "wof:name":"CB3 0GT",
    "wof:placetype":"postalcode"
},
  "geometry": {"coordinates":[0.08986207242653,52.20879282841828],"type":"Point"}
}