{
  "type": "Feature",
  "properties": {
    "iso:country":"GB",
    "wof:name":"ST2 9LB",
    "wof:placetype":"postalcode"
},
  "geometry": {"coordinates":[-2.13720578553685,53.01389804084064],"type":"Point"}
}