{
  "type": "Feature",
  "properties": {
    "iso:country":"GB",
    "wof:name":"HD7 6LU",
    "wof:placetype":"postalcode"
},
  "geometry": {"coordinates":[-1.90756864734254,53.60993712453022],"type":"Point"}
}