{
  "type": "Feature",
  "properties": {
    "date:inception_lower": "1980-01-01",
    "date:inception_upper": "1980-01-01",
    "iso:country": "GB",
    "wof:name": "DL13 5DF",
    "wof:placetype": "postalcode"
  },
  "geometry": {"coordinates":[-1.804805,54.611336],"type":"Point"}
}
