{
  "type": "Feature",
  "properties": {
    "date:inception_lower": "1980-01-01",
    "date:inception_upper": "1980-01-01",
    "iso:country": "GB",
    "wof:name": "SL7 2HH",
    "wof:placetype": "postalcode"
  },
  "geometry": {"coordinates":[-0.840239,51.554453],"type":"Point"}
}
