{
  "type": "Feature",
  "properties": {
    "iso:country":"GB",
    "wof:name":"SL7 2HH",
    "wof:placetype":"postalcode"
},
  "geometry": {"coordinates":[-0.84023889790913,51.55445300398087],"type":"Point"}
}