{
  "type": "Feature",
  "properties": {
    "iso:country":"GB",
    "wof:name":"WV11 2EY",
    "wof:placetype":"postalcode"
},
  "geometry": {"coordinates":[-2.06585731880743,52.61473768153421],"type":"Point"}
}