{
  "type": "Feature",
  "properties": {
    "iso:country": "GB",
    "wof:name": "WV11 2EY",
    "wof:placetype": "postalcode"
  },
  "geometry": {"coordinates":[-2.065857,52.614738],"type":"Point"}
}
