{
  "type": "Feature",
  "properties": {
    "date:inception_lower": "1995-01-01",
    "date:inception_upper": "1995-01-01",
    "iso:country": "GB",
    "wof:name": "S81 8UL",
    "wof:placetype": "postalcode"
  },
  "geometry": {"coordinates":[-1.144663,53.324608],"type":"Point"}
}
