{
  "type": "Feature",
  "properties": {
    "iso:country":"GB",
    "wof:name":"L15 3JA",
    "wof:placetype":"postalcode"
},
  "geometry": {"coordinates":[-2.93393881257855,53.39301431348976],"type":"Point"}
}