{
  "type": "Feature",
  "properties": {
    "iso:country":"GB",
    "wof:name":"IP17 3NF",
    "wof:placetype":"postalcode"
},
  "geometry": {"coordinates":[1.55547389225235,52.25116046328166],"type":"Point"}
}