{
  "type": "Feature",
  "properties": {
    "iso:country":"GB",
    "wof:name":"NW2 3LJ",
    "wof:placetype":"postalcode"
},
  "geometry": {"coordinates":[-0.21313604838041,51.55593141187467],"type":"Point"}
}