{
  "type": "Feature",
  "properties": {
    "iso:country": "GB",
    "wof:name": "SK12 2ER",
    "wof:placetype": "postalcode"
  },
  "geometry": {"coordinates":[-2.030598,53.360816],"type":"Point"}
}
