{
  "type": "Feature",
  "properties": {
    "date:inception_lower":"2017-06-01",
    "date:inception_upper":"2017-06-30",
    "iso:country":"GB",
    "wof:name":"MK43 0YN",
    "wof:placetype":"postalcode"
},
  "geometry": {"coordinates":[-0.608509,52.064135],"type":"Point"}
}