{
  "type": "Feature",
  "properties": {
    "date:inception_lower": "2018-10-01",
    "date:inception_upper": "2018-10-01",
    "iso:country": "GB",
    "wof:name": "NG2 9PQ",
    "wof:placetype": "postalcode"
  },
  "geometry": {"coordinates":[-1.198349,52.930141],"type":"Point"}
}
