{
  "type": "Feature",
  "properties": {
    "iso:country":"GB",
    "wof:name":"N7 0DU",
    "wof:placetype":"postalcode"
},
  "geometry": {"coordinates":[-0.12943373951557,51.55782814306102],"type":"Point"}
}