{
  "type": "Feature",
  "properties": {
    "iso:country": "GB",
    "wof:name": "WA10 3NW",
    "wof:placetype": "postalcode"
  },
  "geometry": {"coordinates":[-2.757489,53.441455],"type":"Point"}
}
