{
  "type": "Feature",
  "properties": {
    "iso:country":"GB",
    "wof:name":"WA10 3NW",
    "wof:placetype":"postalcode"
},
  "geometry": {"coordinates":[-2.75748923172393,53.44145549507332],"type":"Point"}
}