{
  "type": "Feature",
  "properties": {
    "iso:country": "GB",
    "wof:name": "NG17 7PS",
    "wof:placetype": "postalcode"
  },
  "geometry": {"coordinates":[-1.231937,53.103541],"type":"Point"}
}
