{
  "type": "Feature",
  "properties": {
    "iso:country":"GB",
    "wof:name":"NG17 7PS",
    "wof:placetype":"postalcode"
},
  "geometry": {"coordinates":[-1.23193656618965,53.1035405447518],"type":"Point"}
}