{
  "type": "Feature",
  "properties": {
    "iso:country":"GB",
    "wof:name":"WF4 5QP",
    "wof:placetype":"postalcode"
},
  "geometry": {"coordinates":[-1.5423394604072,53.66652472327677],"type":"Point"}
}