{
  "type": "Feature",
  "properties": {
    "date:inception_lower": "1995-01-01",
    "date:inception_upper": "1995-01-01",
    "iso:country": "GB",
    "wof:name": "WF4 5QP",
    "wof:placetype": "postalcode"
  },
  "geometry": {"coordinates":[-1.542339,53.666525],"type":"Point"}
}
