{
  "type": "Feature",
  "properties": {
    "date:inception_lower": "2019-05-01",
    "date:inception_upper": "2019-05-01",
    "iso:country": "GB",
    "wof:name": "SO51 8LP",
    "wof:placetype": "postalcode"
  },
  "geometry": {"coordinates":[-1.498336,50.98971],"type":"Point"}
}
