{
  "type": "Feature",
  "properties": {
    "iso:country": "GB",
    "wof:name": "SO51 8LP",
    "wof:placetype": "postalcode"
  },
  "geometry": {"coordinates":[-1.498336,50.98971],"type":"Point"}
}
