{
  "type": "Feature",
  "properties": {
    "iso:country":"GB",
    "wof:name":"WD3 7DN",
    "wof:placetype":"postalcode"
},
  "geometry": {"coordinates":[-0.48320033718779,51.6362283138111],"type":"Point"}
}