{
  "type": "Feature",
  "properties": {
    "iso:country": "GB",
    "wof:name": "EN11 9PE",
    "wof:placetype": "postalcode"
  },
  "geometry": {"coordinates":[-0.002707,51.778896],"type":"Point"}
}
