{
  "type": "Feature",
  "properties": {
    "iso:country":"GB",
    "wof:name":"EN11 9PE",
    "wof:placetype":"postalcode"
},
  "geometry": {"coordinates":[-0.00270733397701,51.77889619102364],"type":"Point"}
}