{
  "type": "Feature",
  "properties": {
    "iso:country": "GB",
    "wof:name": "BR7 6LE",
    "wof:placetype": "postalcode"
  },
  "geometry": {"coordinates":[0.077022,51.412673],"type":"Point"}
}
