{
  "type": "Feature",
  "properties": {
    "iso:country":"GB",
    "wof:name":"BR7 6LE",
    "wof:placetype":"postalcode"
},
  "geometry": {"coordinates":[0.07702215129913,51.41267309961934],"type":"Point"}
}