{
  "type": "Feature",
  "properties": {
    "iso:country":"GB",
    "wof:name":"NN3 8ER",
    "wof:placetype":"postalcode"
},
  "geometry": {"coordinates":[-0.81769187120987,52.2682170460712],"type":"Point"}
}