{
  "type": "Feature",
  "properties": {
    "date:inception_lower":"1980-01-01",
    "date:inception_upper":"1980-01-31",
    "iso:country":"GB",
    "wof:name":"SG12 7DJ",
    "wof:placetype":"postalcode"
},
  "geometry": {"coordinates":[-0.020375,51.81574],"type":"Point"}
}