{
  "type": "Feature",
  "properties": {
    "iso:country":"GB",
    "wof:name":"SG12 7DJ",
    "wof:placetype":"postalcode"
},
  "geometry": {"coordinates":[-0.02037501444929,51.81573962927498],"type":"Point"}
}