{
  "type": "Feature",
  "properties": {
    "iso:country": "GB",
    "wof:name": "LL60 6AJ",
    "wof:placetype": "postalcode"
  },
  "geometry": {"coordinates":[-4.293242,53.228463],"type":"Point"}
}
