{
  "type": "Feature",
  "properties": {
    "iso:country":"GB",
    "wof:name":"LL60 6AJ",
    "wof:placetype":"postalcode"
},
  "geometry": {"coordinates":[-4.29324648341249,53.2283640889888],"type":"Point"}
}