{
  "type": "Feature",
  "properties": {
    "date:inception_lower": "2009-10-01",
    "date:inception_upper": "2009-10-01",
    "iso:country": "GB",
    "wof:name": "LL60 6AJ",
    "wof:placetype": "postalcode"
  },
  "geometry": {"coordinates":[-4.293242,53.228463],"type":"Point"}
}
