{
  "type": "Feature",
  "properties": {
    "date:inception_lower": "2001-06-01",
    "date:inception_upper": "2001-06-01",
    "iso:country": "GB",
    "wof:name": "NG11 7AY",
    "wof:placetype": "postalcode"
  },
  "geometry": {"coordinates":[-1.159024,52.924446],"type":"Point"}
}
