{
  "type": "Feature",
  "properties": {
    "date:inception_lower":"2015-10-01",
    "date:inception_upper":"2015-10-31",
    "iso:country":"GB",
    "wof:name":"ST18 0WF",
    "wof:placetype":"postalcode"
},
  "geometry": {"coordinates":[-2.002361,52.806181],"type":"Point"}
}