{
  "type": "Feature",
  "properties": {
    "iso:country":"GB",
    "wof:name":"ST18 0WF",
    "wof:placetype":"postalcode"
},
  "geometry": {"coordinates":[-2.00236097245393,52.80618076790535],"type":"Point"}
}