{
  "type": "Feature",
  "properties": {
    "iso:country": "GB",
    "wof:name": "ST18 0WF",
    "wof:placetype": "postalcode"
  },
  "geometry": {"coordinates":[-2.002361,52.806181],"type":"Point"}
}
