{
  "type": "Feature",
  "properties": {
    "iso:country": "GB",
    "wof:name": "WS15 2XL",
    "wof:placetype": "postalcode"
  },
  "geometry": {"coordinates":[-1.951862,52.769215],"type":"Point"}
}
