{
  "type": "Feature",
  "properties": {
    "date:inception_lower":"1980-01-01",
    "date:inception_upper":"1980-01-31",
    "iso:country":"GB",
    "wof:name":"WS15 2XL",
    "wof:placetype":"postalcode"
},
  "geometry": {"coordinates":[-1.951862,52.769215],"type":"Point"}
}