{
  "type": "Feature",
  "properties": {
    "iso:country":"GB",
    "wof:name":"DD3 8AR",
    "wof:placetype":"postalcode"
},
  "geometry": {"coordinates":[-2.97873997720875,56.47566112690507],"type":"Point"}
}