{
  "type": "Feature",
  "properties": {
    "date:inception_lower": "1980-01-01",
    "date:inception_upper": "1980-01-01",
    "iso:country": "GB",
    "wof:name": "DG8 6QD",
    "wof:placetype": "postalcode"
  },
  "geometry": {"coordinates":[-4.497247,54.953828],"type":"Point"}
}
