{
  "type": "Feature",
  "properties": {
    "iso:country":"GB",
    "wof:name":"DG8 6QD",
    "wof:placetype":"postalcode"
},
  "geometry": {"coordinates":[-4.50256022349629,54.95615539807215],"type":"Point"}
}