{
  "type": "Feature",
  "properties": {
    "iso:country": "GB",
    "wof:name": "BL9 7AF",
    "wof:placetype": "postalcode"
  },
  "geometry": {"coordinates":[-2.287724,53.596836],"type":"Point"}
}
