{
  "type": "Feature",
  "properties": {
    "iso:country":"GB",
    "wof:name":"BL9 7AF",
    "wof:placetype":"postalcode"
},
  "geometry": {"coordinates":[-2.28772404639644,53.59683580887936],"type":"Point"}
}