{
  "type": "Feature",
  "properties": {
    "iso:country":"GB",
    "wof:name":"ML1 1HG",
    "wof:placetype":"postalcode"
},
  "geometry": {"coordinates":[-3.98666713557941,55.79790783102956],"type":"Point"}
}