{
  "type": "Feature",
  "properties": {
    "iso:country":"GB",
    "wof:name":"CW5 8NF",
    "wof:placetype":"postalcode"
},
  "geometry": {"coordinates":[-2.59804853585213,53.0872628836381],"type":"Point"}
}