{
  "type": "Feature",
  "properties": {
    "iso:country": "GB",
    "wof:name": "CW5 8NF",
    "wof:placetype": "postalcode"
  },
  "geometry": {"coordinates":[-2.598049,53.08728],"type":"Point"}
}
