{
  "type": "Feature",
  "properties": {
    "date:inception_lower": "2002-06-01",
    "date:inception_upper": "2002-06-01",
    "iso:country": "GB",
    "wof:name": "W1W 6QT",
    "wof:placetype": "postalcode"
  },
  "geometry": {"coordinates":[-0.142685,51.520432],"type":"Point"}
}
