{
  "type": "Feature",
  "properties": {
    "iso:country": "GB",
    "wof:name": "DN37 8JU",
    "wof:placetype": "postalcode"
  },
  "geometry": {"coordinates":[-0.283723,53.558141],"type":"Point"}
}
