{
  "type": "Feature",
  "properties": {
    "iso:country": "GB",
    "wof:name": "DN6 9GH",
    "wof:placetype": "postalcode"
  },
  "geometry": {"coordinates":[-1.166523,53.632995],"type":"Point"}
}
