{
  "type": "Feature",
  "properties": {
    "iso:country":"GB",
    "wof:name":"CB9 7YL",
    "wof:placetype":"postalcode"
},
  "geometry": {"coordinates":[0.40887444885376,52.09015189660767],"type":"Point"}
}