{
  "type": "Feature",
  "properties": {
    "iso:country":"GB",
    "wof:name":"TQ4 7AG",
    "wof:placetype":"postalcode"
},
  "geometry": {"coordinates":[-3.57311894312081,50.41237314223843],"type":"Point"}
}