{
  "type": "Feature",
  "properties": {
    "date:inception_lower": "1980-01-01",
    "date:inception_upper": "1980-01-01",
    "iso:country": "GB",
    "wof:name": "ZE2 9PJ",
    "wof:placetype": "postalcode"
  },
  "geometry": {"coordinates":[-1.556446,60.24222],"type":"Point"}
}
