{
  "type": "Feature",
  "properties": {
    "iso:country":"GB",
    "wof:name":"ZE2 9PJ",
    "wof:placetype":"postalcode"
},
  "geometry": {"coordinates":[-1.55605196049556,60.24094297677644],"type":"Point"}
}