{
  "type": "Feature",
  "properties": {
    "date:inception_lower":"1985-10-01",
    "date:inception_upper":"1985-10-31",
    "iso:country":"GB",
    "wof:name":"TW1 2ET",
    "wof:placetype":"postalcode"
},
  "geometry": {"coordinates":[-0.31129,51.455259],"type":"Point"}
}