{
  "type": "Feature",
  "properties": {
    "iso:country":"GB",
    "wof:name":"LN1 2PQ",
    "wof:placetype":"postalcode"
},
  "geometry": {"coordinates":[-0.66272884084818,53.29094725012602],"type":"Point"}
}