{
  "type": "Feature",
  "properties": {
    "iso:country": "GB",
    "wof:name": "LN1 2PQ",
    "wof:placetype": "postalcode"
  },
  "geometry": {"coordinates":[-0.662729,53.290968],"type":"Point"}
}
