{
  "type": "Feature",
  "properties": {
    "date:inception_lower": "1991-09-01",
    "date:inception_upper": "1991-09-01",
    "iso:country": "GB",
    "wof:name": "LN1 2PQ",
    "wof:placetype": "postalcode"
  },
  "geometry": {"coordinates":[-0.662729,53.290968],"type":"Point"}
}
