{
  "type": "Feature",
  "properties": {
    "iso:country": "GB",
    "wof:name": "YO43 3EN",
    "wof:placetype": "postalcode"
  },
  "geometry": {"coordinates":[-0.671074,53.864485],"type":"Point"}
}
