{
  "type": "Feature",
  "properties": {
    "iso:country":"GB",
    "wof:name":"YO43 3EN",
    "wof:placetype":"postalcode"
},
  "geometry": {"coordinates":[-0.6710735826506,53.864484711318],"type":"Point"}
}