{
  "type": "Feature",
  "properties": {
    "iso:country":"GB",
    "wof:name":"PR3 0HQ",
    "wof:placetype":"postalcode"
},
  "geometry": {"coordinates":[-2.78106558344697,53.88249967036996],"type":"Point"}
}