{
  "type": "Feature",
  "properties": {
    "iso:country":"GB",
    "wof:name":"ME10 2DE",
    "wof:placetype":"postalcode"
},
  "geometry": {"coordinates":[0.74539884729234,51.35689711967633],"type":"Point"}
}