{
  "type": "Feature",
  "properties": {
    "iso:country":"GB",
    "wof:name":"TW2 6JB",
    "wof:placetype":"postalcode"
},
  "geometry": {"coordinates":[-0.35658054026245,51.44860100448479],"type":"Point"}
}