{
  "type": "Feature",
  "properties": {
    "iso:country":"GB",
    "wof:name":"GU9 7RA",
    "wof:placetype":"postalcode"
},
  "geometry": {"coordinates":[-0.79729199708355,51.21366157527326],"type":"Point"}
}