{
  "type": "Feature",
  "properties": {
    "iso:country":"GB",
    "wof:name":"NP16 5FY",
    "wof:placetype":"postalcode"
},
  "geometry": {"coordinates":[-2.66968973766632,51.64477581261956],"type":"Point"}
}