{
  "type": "Feature",
  "properties": {
    "iso:country":"GB",
    "wof:name":"WF7 7BA",
    "wof:placetype":"postalcode"
},
  "geometry": {"coordinates":[-1.35358004921544,53.64274372550892],"type":"Point"}
}