{
  "type": "Feature",
  "properties": {
    "iso:country": "GB",
    "wof:name": "SN2 7AR",
    "wof:placetype": "postalcode"
  },
  "geometry": {"coordinates":[-1.765221,51.583856],"type":"Point"}
}
