{
  "type": "Feature",
  "properties": {
    "iso:country":"GB",
    "wof:name":"BH19 3AR",
    "wof:placetype":"postalcode"
},
  "geometry": {"coordinates":[-1.95290924071894,50.64321366352229],"type":"Point"}
}