{
  "type": "Feature",
  "properties": {
    "iso:country":"GB",
    "wof:name":"CV2 5LT",
    "wof:placetype":"postalcode"
},
  "geometry": {"coordinates":[-1.46805226852603,52.40861775679131],"type":"Point"}
}