{
  "type": "Feature",
  "properties": {
    "iso:country": "GB",
    "wof:name": "RG7 2NG",
    "wof:placetype": "postalcode"
  },
  "geometry": {"coordinates":[-1.094835,51.359135],"type":"Point"}
}
