{
  "type": "Feature",
  "properties": {
    "iso:country": "GB",
    "wof:name": "RG7 2NG",
    "wof:placetype": "postalcode"
  },
  "geometry": {"coordinates":[-1.097886,51.35878],"type":"Point"}
}
