{
  "type": "Feature",
  "properties": {
    "iso:country":"GB",
    "wof:name":"RG7 2NG",
    "wof:placetype":"postalcode"
},
  "geometry": {"coordinates":[-1.09790587461813,51.35878023596891],"type":"Point"}
}