{
  "type": "Feature",
  "properties": {
    "date:inception_lower": "1980-01-01",
    "date:inception_upper": "1980-01-01",
    "iso:country": "GB",
    "wof:name": "WA14 5QS",
    "wof:placetype": "postalcode"
  },
  "geometry": {"coordinates":[-2.342116,53.403755],"type":"Point"}
}
