{
  "type": "Feature",
  "properties": {
    "iso:country":"GB",
    "wof:name":"WA14 5QS",
    "wof:placetype":"postalcode"
},
  "geometry": {"coordinates":[-2.34211592268146,53.40375543028711],"type":"Point"}
}