{
  "type": "Feature",
  "properties": {
    "date:inception_lower":"1980-01-01",
    "date:inception_upper":"1980-01-31",
    "iso:country":"GB",
    "wof:name":"CT5 4JJ",
    "wof:placetype":"postalcode"
},
  "geometry": {"coordinates":[1.028851,51.349232],"type":"Point"}
}