{
  "type": "Feature",
  "properties": {
    "iso:country":"GB",
    "wof:name":"KT13 9YA",
    "wof:placetype":"postalcode"
},
  "geometry": {"coordinates":[-0.45481240350129,51.36976123956836],"type":"Point"}
}