{
  "type": "Feature",
  "properties": {
    "iso:country": "GB",
    "wof:name": "KT13 9YA",
    "wof:placetype": "postalcode"
  },
  "geometry": {"coordinates":[-0.454812,51.369761],"type":"Point"}
}
