{
  "type": "Feature",
  "properties": {
    "iso:country":"GB",
    "wof:name":"IP2 0RU",
    "wof:placetype":"postalcode"
},
  "geometry": {"coordinates":[1.1130375330579,52.04332121570818],"type":"Point"}
}