{
  "type": "Feature",
  "properties": {
    "iso:country": "GB",
    "wof:name": "SK2 5QL",
    "wof:placetype": "postalcode"
  },
  "geometry": {"coordinates":[-2.128246,53.398631],"type":"Point"}
}
