{
  "type": "Feature",
  "properties": {
    "date:inception_lower": "1980-01-01",
    "date:inception_upper": "1980-01-01",
    "iso:country": "GB",
    "wof:name": "EX32 7NW",
    "wof:placetype": "postalcode"
  },
  "geometry": {"coordinates":[-4.00293,51.088136],"type":"Point"}
}
