{
  "type": "Feature",
  "properties": {
    "iso:country": "GB",
    "wof:name": "EX32 7NW",
    "wof:placetype": "postalcode"
  },
  "geometry": {"coordinates":[-4.00293,51.088136],"type":"Point"}
}
