{
  "type": "Feature",
  "properties": {
    "iso:country":"GB",
    "wof:name":"EX32 7NW",
    "wof:placetype":"postalcode"
},
  "geometry": {"coordinates":[-4.00293004519805,51.08813622760944],"type":"Point"}
}