{
  "type": "Feature",
  "properties": {
    "iso:country":"GB",
    "wof:name":"WC2H 8LE",
    "wof:placetype":"postalcode"
},
  "geometry": {"coordinates":[-0.1277103940914,51.51547300985878],"type":"Point"}
}