{
  "type": "Feature",
  "properties": {
    "iso:country":"GB",
    "wof:name":"SA70 7SE",
    "wof:placetype":"postalcode"
},
  "geometry": {"coordinates":[-4.76792361756997,51.65038909451294],"type":"Point"}
}