{
  "type": "Feature",
  "properties": {
    "iso:country":"GB",
    "wof:name":"GL7 1GS",
    "wof:placetype":"postalcode"
},
  "geometry": {"coordinates":[-1.96664643484702,51.71572540515621],"type":"Point"}
}