{
  "type": "Feature",
  "properties": {
    "iso:country": "GB",
    "wof:name": "GL7 1GS",
    "wof:placetype": "postalcode"
  },
  "geometry": {"coordinates":[-1.966646,51.715725],"type":"Point"}
}
