{
  "type": "Feature",
  "properties": {
    "iso:country":"GB",
    "wof:name":"BR2 7LD",
    "wof:placetype":"postalcode"
},
  "geometry": {"coordinates":[0.01762866604862,51.37899835983026],"type":"Point"}
}