{
  "type": "Feature",
  "properties": {
    "iso:country":"GB",
    "wof:name":"S17 3LQ",
    "wof:placetype":"postalcode"
},
  "geometry": {"coordinates":[-1.51614581211859,53.32697996096417],"type":"Point"}
}