{
  "type": "Feature",
  "properties": {
    "iso:country": "GB",
    "wof:name": "S17 3LQ",
    "wof:placetype": "postalcode"
  },
  "geometry": {"coordinates":[-1.516145,53.326989],"type":"Point"}
}
