{
  "type": "Feature",
  "properties": {
    "iso:country":"GB",
    "wof:name":"CH7 6NP",
    "wof:placetype":"postalcode"
},
  "geometry": {"coordinates":[-3.08553725900485,53.20019054127602],"type":"Point"}
}