{
  "type": "Feature",
  "properties": {
    "iso:country": "GB",
    "wof:name": "GU32 2HT",
    "wof:placetype": "postalcode"
  },
  "geometry": {"coordinates":[-0.936497,51.015144],"type":"Point"}
}
