{
  "type": "Feature",
  "properties": {
    "iso:country":"GB",
    "wof:name":"EH47 8EY",
    "wof:placetype":"postalcode"
},
  "geometry": {"coordinates":[-3.67228280077441,55.8601981603018],"type":"Point"}
}