{
  "type": "Feature",
  "properties": {
    "date:inception_lower":"1986-09-01",
    "date:inception_upper":"1986-09-30",
    "iso:country":"GB",
    "wof:name":"EH47 8EY",
    "wof:placetype":"postalcode"
},
  "geometry": {"coordinates":[-3.672283,55.860198],"type":"Point"}
}