{
  "type": "Feature",
  "properties": {
    "iso:country":"GB",
    "wof:name":"CR0 0RT",
    "wof:placetype":"postalcode"
},
  "geometry": {"coordinates":[-0.01262540182543,51.35465923582077],"type":"Point"}
}