{
  "type": "Feature",
  "properties": {
    "iso:country":"GB",
    "wof:name":"TN7 4JA",
    "wof:placetype":"postalcode"
},
  "geometry": {"coordinates":[0.11330970012612,51.1037118246524],"type":"Point"}
}