{
  "type": "Feature",
  "properties": {
    "iso:country":"GB",
    "wof:name":"DH5 9LW",
    "wof:placetype":"postalcode"
},
  "geometry": {"coordinates":[-1.46258596438622,54.82253158509311],"type":"Point"}
}