{
  "type": "Feature",
  "properties": {
    "iso:country": "GB",
    "wof:name": "DH5 9LW",
    "wof:placetype": "postalcode"
  },
  "geometry": {"coordinates":[-1.462586,54.822532],"type":"Point"}
}
