{
  "type": "Feature",
  "properties": {
    "date:inception_lower": "1998-06-01",
    "date:inception_upper": "1998-06-01",
    "iso:country": "GB",
    "wof:name": "YO60 7PN",
    "wof:placetype": "postalcode"
  },
  "geometry": {"coordinates":[-0.867319,54.048176],"type":"Point"}
}
