{
  "type": "Feature",
  "properties": {
    "iso:country":"GB",
    "wof:name":"YO60 7PN",
    "wof:placetype":"postalcode"
},
  "geometry": {"coordinates":[-0.867324704678,54.04815863804856],"type":"Point"}
}