{
  "type": "Feature",
  "properties": {
    "iso:country":"GB",
    "wof:name":"CW7 2EN",
    "wof:placetype":"postalcode"
},
  "geometry": {"coordinates":[-2.54135417233718,53.19284125670305],"type":"Point"}
}