{
  "type": "Feature",
  "properties": {
    "date:inception_lower":"1980-01-01",
    "date:inception_upper":"1980-01-31",
    "iso:country":"GB",
    "wof:name":"CW7 2EN",
    "wof:placetype":"postalcode"
},
  "geometry": {"coordinates":[-2.541354,53.192841],"type":"Point"}
}