{
  "type": "Feature",
  "properties": {
    "iso:country": "GB",
    "wof:name": "CW7 2EN",
    "wof:placetype": "postalcode"
  },
  "geometry": {"coordinates":[-2.541354,53.192841],"type":"Point"}
}
