{
  "type": "Feature",
  "properties": {
    "iso:country":"GB",
    "wof:name":"LE7 7ND",
    "wof:placetype":"postalcode"
},
  "geometry": {"coordinates":[-1.12967801781521,52.71110677567983],"type":"Point"}
}