{
  "type": "Feature",
  "properties": {
    "date:inception_lower": "2023-10-01",
    "date:inception_upper": "2023-10-01",
    "iso:country": "GB",
    "wof:name": "NR18 9UJ",
    "wof:placetype": "postalcode"
  },
  "geometry": {"coordinates":[1.122515,52.564327],"type":"Point"}
}
