{
  "type": "Feature",
  "properties": {
    "date:inception_lower":"1996-12-01",
    "date:inception_upper":"1996-12-31",
    "iso:country":"GB",
    "wof:name":"BS4 3DS",
    "wof:placetype":"postalcode"
},
  "geometry": {"coordinates":[-2.556217,51.438357],"type":"Point"}
}