{
  "type": "Feature",
  "properties": {
    "iso:country":"GB",
    "wof:name":"BS4 3DS",
    "wof:placetype":"postalcode"
},
  "geometry": {"coordinates":[-2.55621696609621,51.43835714857084],"type":"Point"}
}