{
  "type": "Feature",
  "properties": {
    "iso:country":"GB",
    "wof:name":"PE1 1TN",
    "wof:placetype":"postalcode"
},
  "geometry": {"coordinates":[-0.24121925526542,52.57384798314536],"type":"Point"}
}