{
  "type": "Feature",
  "properties": {
    "date:inception_lower": "1980-01-01",
    "date:inception_upper": "1980-01-01",
    "iso:country": "GB",
    "wof:name": "NE2 1JX",
    "wof:placetype": "postalcode"
  },
  "geometry": {"coordinates":[-1.596241,54.98697],"type":"Point"}
}
