{
  "type": "Feature",
  "properties": {
    "iso:country": "GB",
    "wof:name": "NE2 1JX",
    "wof:placetype": "postalcode"
  },
  "geometry": {"coordinates":[-1.596241,54.98697],"type":"Point"}
}
