{
  "type": "Feature",
  "properties": {
    "iso:country":"GB",
    "wof:name":"MK43 8GP",
    "wof:placetype":"postalcode"
},
  "geometry": {"coordinates":[-0.54884578997276,52.1533341228485],"type":"Point"}
}