{
  "type": "Feature",
  "properties": {
    "date:inception_lower": "2001-12-01",
    "date:inception_upper": "2001-12-01",
    "iso:country": "GB",
    "wof:name": "MK43 8GP",
    "wof:placetype": "postalcode"
  },
  "geometry": {"coordinates":[-0.548813,52.153301],"type":"Point"}
}
