{
  "type": "Feature",
  "properties": {
    "iso:country":"GB",
    "wof:name":"G78 2NG",
    "wof:placetype":"postalcode"
},
  "geometry": {"coordinates":[-4.37863424398212,55.79599783787157],"type":"Point"}
}