{
  "type": "Feature",
  "properties": {
    "date:inception_lower": "2020-08-01",
    "date:inception_upper": "2020-08-01",
    "iso:country": "GB",
    "wof:name": "TS29 6FA",
    "wof:placetype": "postalcode"
  },
  "geometry": {"coordinates":[-1.424188,54.70198],"type":"Point"}
}
