{
  "type": "Feature",
  "properties": {
    "date:inception_lower": "2000-12-01",
    "date:inception_upper": "2000-12-01",
    "iso:country": "GB",
    "wof:name": "BH5 1AB",
    "wof:placetype": "postalcode"
  },
  "geometry": {"coordinates":[-1.84518,50.722437],"type":"Point"}
}
