{
  "type": "Feature",
  "properties": {
    "iso:country":"GB",
    "wof:name":"BH5 1AB",
    "wof:placetype":"postalcode"
},
  "geometry": {"coordinates":[-1.84517970887656,50.72243651030338],"type":"Point"}
}