{
  "type": "Feature",
  "properties": {
    "iso:country":"GB",
    "wof:name":"IV55 8ZF",
    "wof:placetype":"postalcode"
},
  "geometry": {"coordinates":[-6.51272733930456,57.39038911472831],"type":"Point"}
}