{
  "type": "Feature",
  "properties": {
    "iso:country":"GB",
    "wof:name":"E16 1NG",
    "wof:placetype":"postalcode"
},
  "geometry": {"coordinates":[0.02076277262539,51.51299986767541],"type":"Point"}
}