{
  "type": "Feature",
  "properties": {
    "iso:country":"GB",
    "wof:name":"TR11 5HW",
    "wof:placetype":"postalcode"
},
  "geometry": {"coordinates":[-5.09374155656181,50.10532961032867],"type":"Point"}
}