{
  "type": "Feature",
  "properties": {
    "iso:country":"GB",
    "wof:name":"NW3 1TN",
    "wof:placetype":"postalcode"
},
  "geometry": {"coordinates":[-0.17339116816692,51.55744160963064],"type":"Point"}
}