{
  "type": "Feature",
  "properties": {
    "iso:country": "GB",
    "wof:name": "NW3 1TN",
    "wof:placetype": "postalcode"
  },
  "geometry": {"coordinates":[-0.173391,51.557442],"type":"Point"}
}
