{
  "type": "Feature",
  "properties": {
    "iso:country": "GB",
    "wof:name": "KY7 5DF",
    "wof:placetype": "postalcode"
  },
  "geometry": {"coordinates":[-3.150965,56.192346],"type":"Point"}
}
