{
  "type": "Feature",
  "properties": {
    "iso:country": "GB",
    "wof:name": "RH15 9HD",
    "wof:placetype": "postalcode"
  },
  "geometry": {"coordinates":[-0.134626,50.947416],"type":"Point"}
}
