{
  "type": "Feature",
  "properties": {
    "date:inception_lower":"1980-01-01",
    "date:inception_upper":"1980-01-31",
    "iso:country":"GB",
    "wof:name":"BH19 2RN",
    "wof:placetype":"postalcode"
},
  "geometry": {"coordinates":[-1.967133,50.608057],"type":"Point"}
}