{
  "type": "Feature",
  "properties": {
    "iso:country":"GB",
    "wof:name":"WD5 0DS",
    "wof:placetype":"postalcode"
},
  "geometry": {"coordinates":[-0.41416986094517,51.706227178242],"type":"Point"}
}