{
  "type": "Feature",
  "properties": {
    "iso:country":"GB",
    "wof:name":"S66 3QU",
    "wof:placetype":"postalcode"
},
  "geometry": {"coordinates":[-1.27798511554704,53.43122455721932],"type":"Point"}
}