{
  "type": "Feature",
  "properties": {
    "iso:country": "GB",
    "wof:name": "S66 3QU",
    "wof:placetype": "postalcode"
  },
  "geometry": {"coordinates":[-1.277985,53.431225],"type":"Point"}
}
