{
  "type": "Feature",
  "properties": {
    "iso:country": "GB",
    "wof:name": "M16 8GJ",
    "wof:placetype": "postalcode"
  },
  "geometry": {"coordinates":[-2.25134,53.44407],"type":"Point"}
}
