{
  "type": "Feature",
  "properties": {
    "iso:country":"GB",
    "wof:name":"SN3 2GQ",
    "wof:placetype":"postalcode"
},
  "geometry": {"coordinates":[-1.7577721906635,51.55658719008908],"type":"Point"}
}