{
  "type": "Feature",
  "properties": {
    "date:inception_lower":"1993-08-01",
    "date:inception_upper":"1993-08-31",
    "iso:country":"GB",
    "wof:name":"OL12 9EP",
    "wof:placetype":"postalcode"
},
  "geometry": {"coordinates":[-2.135888,53.634496],"type":"Point"}
}