{
  "type": "Feature",
  "properties": {
    "iso:country": "GB",
    "wof:name": "SW13 0BH",
    "wof:placetype": "postalcode"
  },
  "geometry": {"coordinates":[-0.241166,51.472825],"type":"Point"}
}
