{
  "type": "Feature",
  "properties": {
    "iso:country":"GB",
    "wof:name":"SW13 0BH",
    "wof:placetype":"postalcode"
},
  "geometry": {"coordinates":[-0.24116610143771,51.47282459404926],"type":"Point"}
}