{
  "type": "Feature",
  "properties": {
    "iso:country":"GB",
    "wof:name":"HP7 0QH",
    "wof:placetype":"postalcode"
},
  "geometry": {"coordinates":[-0.64842329522768,51.65622082386955],"type":"Point"}
}