{
  "type": "Feature",
  "properties": {
    "date:inception_lower": "1980-01-01",
    "date:inception_upper": "1980-01-01",
    "iso:country": "GB",
    "wof:name": "EX6 6NA",
    "wof:placetype": "postalcode"
  },
  "geometry": {"coordinates":[-3.76804,50.71786],"type":"Point"}
}
