{
  "type": "Feature",
  "properties": {
    "iso:country":"GB",
    "wof:name":"NP24 6XY",
    "wof:placetype":"postalcode"
},
  "geometry": {"coordinates":[-3.22844096205608,51.70961136846536],"type":"Point"}
}