{
  "type": "Feature",
  "properties": {
    "date:inception_lower":"1997-06-01",
    "date:inception_upper":"1997-06-30",
    "iso:country":"GB",
    "wof:name":"G68 0FB",
    "wof:placetype":"postalcode"
},
  "geometry": {"coordinates":[-3.995874,55.960826],"type":"Point"}
}