{
  "type": "Feature",
  "properties": {
    "iso:country":"GB",
    "wof:name":"LA6 2LS",
    "wof:placetype":"postalcode"
},
  "geometry": {"coordinates":[-2.57454744064337,54.23726927337317],"type":"Point"}
}