{
  "type": "Feature",
  "properties": {
    "iso:country":"GB",
    "wof:name":"G72 7XW",
    "wof:placetype":"postalcode"
},
  "geometry": {"coordinates":[-4.11931811819978,55.80218092750371],"type":"Point"}
}