{
  "type": "Feature",
  "properties": {
    "iso:country": "GB",
    "wof:name": "SG1 1SZ",
    "wof:placetype": "postalcode"
  },
  "geometry": {"coordinates":[-0.193091,51.895095],"type":"Point"}
}
