{
  "type": "Feature",
  "properties": {
    "date:inception_lower": "1980-01-01",
    "date:inception_upper": "1980-01-01",
    "iso:country": "GB",
    "wof:name": "PH31 4AN",
    "wof:placetype": "postalcode"
  },
  "geometry": {"coordinates":[-4.829816,56.892648],"type":"Point"}
}
