{
  "type": "Feature",
  "properties": {
    "iso:country":"GB",
    "wof:name":"N9 0HU",
    "wof:placetype":"postalcode"
},
  "geometry": {"coordinates":[-0.04970387686358,51.62110513032559],"type":"Point"}
}