{
  "type": "Feature",
  "properties": {
    "date:inception_lower": "1980-01-01",
    "date:inception_upper": "1980-01-01",
    "iso:country": "GB",
    "wof:name": "NE30 3PB",
    "wof:placetype": "postalcode"
  },
  "geometry": {"coordinates":[-1.432848,55.026388],"type":"Point"}
}
