{
  "type": "Feature",
  "properties": {
    "date:inception_lower":"2011-12-01",
    "date:inception_upper":"2011-12-31",
    "iso:country":"GB",
    "wof:name":"M1 4RJ",
    "wof:placetype":"postalcode"
},
  "geometry": {"coordinates":[-2.241725,53.47688],"type":"Point"}
}