{
  "type": "Feature",
  "properties": {
    "iso:country": "GB",
    "wof:name": "M1 4RJ",
    "wof:placetype": "postalcode"
  },
  "geometry": {"coordinates":[-2.241725,53.47688],"type":"Point"}
}
