{
  "type": "Feature",
  "properties": {
    "iso:country":"GB",
    "wof:name":"EC1N 8JE",
    "wof:placetype":"postalcode"
},
  "geometry": {"coordinates":[-0.10911681500947,51.52141554652464],"type":"Point"}
}