{
  "type": "Feature",
  "properties": {
    "iso:country": "GB",
    "wof:name": "GL11 5BY",
    "wof:placetype": "postalcode"
  },
  "geometry": {"coordinates":[-2.279349,51.681752],"type":"Point"}
}
