{
  "type": "Feature",
  "properties": {
    "iso:country":"GB",
    "wof:name":"SN8 9BH",
    "wof:placetype":"postalcode"
},
  "geometry": {"coordinates":[-1.73361694697579,51.41964824642094],"type":"Point"}
}