{
  "type": "Feature",
  "properties": {
    "date:inception_lower": "1992-01-01",
    "date:inception_upper": "1992-01-01",
    "iso:country": "GB",
    "wof:name": "GU9 8SU",
    "wof:placetype": "postalcode"
  },
  "geometry": {"coordinates":[-0.815374,51.196958],"type":"Point"}
}
