{
  "type": "Feature",
  "properties": {
    "iso:country":"GB",
    "wof:name":"GU9 8SU",
    "wof:placetype":"postalcode"
},
  "geometry": {"coordinates":[-0.8153737270448,51.19695838933474],"type":"Point"}
}