{
  "type": "Feature",
  "properties": {
    "date:inception_lower": "1985-10-01",
    "date:inception_upper": "1985-10-01",
    "iso:country": "GB",
    "wof:name": "BA21 3RY",
    "wof:placetype": "postalcode"
  },
  "geometry": {"coordinates":[-2.661119,50.947025],"type":"Point"}
}
