{
  "type": "Feature",
  "properties": {
    "iso:country":"GB",
    "wof:name":"BA21 3RY",
    "wof:placetype":"postalcode"
},
  "geometry": {"coordinates":[-2.66111899603619,50.94702526198948],"type":"Point"}
}