{
  "type": "Feature",
  "properties": {
    "iso:country":"GB",
    "wof:name":"FY1 3SA",
    "wof:placetype":"postalcode"
},
  "geometry": {"coordinates":[-3.04044261011436,53.82228679602103],"type":"Point"}
}