{
  "type": "Feature",
  "properties": {
    "iso:country":"GB",
    "wof:name":"LL53 8RB",
    "wof:placetype":"postalcode"
},
  "geometry": {"coordinates":[-4.58546393387627,52.84830024317007],"type":"Point"}
}