{
  "type": "Feature",
  "properties": {
    "iso:country": "GB",
    "wof:name": "TQ8 8PD",
    "wof:placetype": "postalcode"
  },
  "geometry": {"coordinates":[-3.75906,50.234378],"type":"Point"}
}
