{
  "type": "Feature",
  "properties": {
    "iso:country":"GB",
    "wof:name":"NE4 5AP",
    "wof:placetype":"postalcode"
},
  "geometry": {"coordinates":[-1.63802775874295,54.97833062856637],"type":"Point"}
}