{
  "type": "Feature",
  "properties": {
    "date:inception_lower": "1980-01-01",
    "date:inception_upper": "1980-01-01",
    "iso:country": "GB",
    "wof:name": "NE4 5AP",
    "wof:placetype": "postalcode"
  },
  "geometry": {"coordinates":[-1.638028,54.978331],"type":"Point"}
}
