{
  "type": "Feature",
  "properties": {
    "iso:country": "GB",
    "wof:name": "YO62 5QE",
    "wof:placetype": "postalcode"
  },
  "geometry": {"coordinates":[-1.187678,54.31579],"type":"Point"}
}
