{
  "type": "Feature",
  "properties": {
    "iso:country":"GB",
    "wof:name":"YO62 5QE",
    "wof:placetype":"postalcode"
},
  "geometry": {"coordinates":[-1.18766761672927,54.31577640815114],"type":"Point"}
}