{
  "type": "Feature",
  "properties": {
    "date:inception_lower": "2006-04-01",
    "date:inception_upper": "2006-04-01",
    "iso:country": "GB",
    "wof:name": "BN43 5PG",
    "wof:placetype": "postalcode"
  },
  "geometry": {"coordinates":[-0.256656,50.830137],"type":"Point"}
}
