{
  "type": "Feature",
  "properties": {
    "iso:country":"GB",
    "wof:name":"BN43 5PG",
    "wof:placetype":"postalcode"
},
  "geometry": {"coordinates":[-0.25665618189743,50.83013655620256],"type":"Point"}
}