{
  "type": "Feature",
  "properties": {
    "iso:country":"GB",
    "wof:name":"BS4 4EF",
    "wof:placetype":"postalcode"
},
  "geometry": {"coordinates":[-2.550086112237,51.44776437345768],"type":"Point"}
}