{
  "type": "Feature",
  "properties": {
    "iso:country":"GB",
    "wof:name":"ST7 3BU",
    "wof:placetype":"postalcode"
},
  "geometry": {"coordinates":[-2.25426805529089,53.09944319108259],"type":"Point"}
}