{
  "type": "Feature",
  "properties": {
    "iso:country":"GB",
    "wof:name":"B13 0EJ",
    "wof:placetype":"postalcode"
},
  "geometry": {"coordinates":[-1.86177953690025,52.42531248343384],"type":"Point"}
}