{
  "type": "Feature",
  "properties": {
    "iso:country": "GB",
    "wof:name": "BL1 2BP",
    "wof:placetype": "postalcode"
  },
  "geometry": {"coordinates":[-2.437357,53.58681],"type":"Point"}
}
