{
  "type": "Feature",
  "properties": {
    "date:inception_lower": "2014-06-01",
    "date:inception_upper": "2014-06-01",
    "iso:country": "GB",
    "wof:name": "BL1 2BP",
    "wof:placetype": "postalcode"
  },
  "geometry": {"coordinates":[-2.437357,53.58681],"type":"Point"}
}
