{
  "type": "Feature",
  "properties": {
    "iso:country":"GB",
    "wof:name":"BL1 2BP",
    "wof:placetype":"postalcode"
},
  "geometry": {"coordinates":[-2.43735715672402,53.58680956674123],"type":"Point"}
}