{
  "type": "Feature",
  "properties": {
    "date:inception_lower":"2002-06-01",
    "date:inception_upper":"2002-06-30",
    "iso:country":"GB",
    "wof:name":"PE38 9LA",
    "wof:placetype":"postalcode"
},
  "geometry": {"coordinates":[0.388551,52.605878],"type":"Point"}
}