{
  "type": "Feature",
  "properties": {
    "iso:country": "GB",
    "wof:name": "HP27 0BZ",
    "wof:placetype": "postalcode"
  },
  "geometry": {"coordinates":[-0.831056,51.720079],"type":"Point"}
}
