{
  "type": "Feature",
  "properties": {
    "date:inception_lower":"2010-10-01",
    "date:inception_upper":"2010-10-31",
    "iso:country":"GB",
    "wof:name":"HP27 0BZ",
    "wof:placetype":"postalcode"
},
  "geometry": {"coordinates":[-0.831056,51.720079],"type":"Point"}
}