{
  "type": "Feature",
  "properties": {
    "date:inception_lower": "1995-07-01",
    "date:inception_upper": "1995-07-01",
    "iso:country": "GB",
    "wof:name": "SW18 5SD",
    "wof:placetype": "postalcode"
  },
  "geometry": {"coordinates":[-0.201024,51.449698],"type":"Point"}
}
