{
  "type": "Feature",
  "properties": {
    "iso:country":"GB",
    "wof:name":"SW18 5SD",
    "wof:placetype":"postalcode"
},
  "geometry": {"coordinates":[-0.20102374766171,51.44969832972382],"type":"Point"}
}