{
  "type": "Feature",
  "properties": {
    "iso:country":"GB",
    "wof:name":"TW9 2NA",
    "wof:placetype":"postalcode"
},
  "geometry": {"coordinates":[-0.30068451301441,51.46410736988488],"type":"Point"}
}