{
  "type": "Feature",
  "properties": {
    "iso:country": "GB",
    "wof:name": "TW9 2NA",
    "wof:placetype": "postalcode"
  },
  "geometry": {"coordinates":[-0.300684,51.464107],"type":"Point"}
}
