{
  "type": "Feature",
  "properties": {
    "date:inception_lower": "1999-06-01",
    "date:inception_upper": "1999-06-01",
    "iso:country": "GB",
    "wof:name": "CF23 5DL",
    "wof:placetype": "postalcode"
  },
  "geometry": {"coordinates":[-3.159549,51.496578],"type":"Point"}
}
