{
  "type": "Feature",
  "properties": {
    "iso:country":"GB",
    "wof:name":"CF23 5DL",
    "wof:placetype":"postalcode"
},
  "geometry": {"coordinates":[-3.15954894876636,51.4965783860433],"type":"Point"}
}