{
  "type": "Feature",
  "properties": {
    "iso:country":"GB",
    "wof:name":"CV3 4DB",
    "wof:placetype":"postalcode"
},
  "geometry": {"coordinates":[-1.47919880689667,52.38458266437542],"type":"Point"}
}