{
  "type": "Feature",
  "properties": {
    "iso:country":"GB",
    "wof:name":"CR2 7ER",
    "wof:placetype":"postalcode"
},
  "geometry": {"coordinates":[-0.08455476360304,51.36354638456352],"type":"Point"}
}