{
  "type": "Feature",
  "properties": {
    "iso:country":"GB",
    "wof:name":"WS8 7NS",
    "wof:placetype":"postalcode"
},
  "geometry": {"coordinates":[-1.93564902330759,52.65690958111942],"type":"Point"}
}