{
  "type": "Feature",
  "properties": {
    "date:inception_lower": "1980-01-01",
    "date:inception_upper": "1980-01-01",
    "iso:country": "GB",
    "wof:name": "WS8 7NS",
    "wof:placetype": "postalcode"
  },
  "geometry": {"coordinates":[-1.935649,52.65691],"type":"Point"}
}
