{
  "type": "Feature",
  "properties": {
    "iso:country":"GB",
    "wof:name":"WF3 1QG",
    "wof:placetype":"postalcode"
},
  "geometry": {"coordinates":[-1.56457968568869,53.72747558819576],"type":"Point"}
}