{
  "type": "Feature",
  "properties": {
    "date:inception_lower": "1999-12-01",
    "date:inception_upper": "1999-12-01",
    "iso:country": "GB",
    "wof:name": "N7 8ER",
    "wof:placetype": "postalcode"
  },
  "geometry": {"coordinates":[-0.117235,51.548254],"type":"Point"}
}
