{
  "type": "Feature",
  "properties": {
    "iso:country": "GB",
    "wof:name": "PL26 8LT",
    "wof:placetype": "postalcode"
  },
  "geometry": {"coordinates":[-4.83596,50.418607],"type":"Point"}
}
