{
  "type": "Feature",
  "properties": {
    "iso:country": "GB",
    "wof:name": "LS13 4SQ",
    "wof:placetype": "postalcode"
  },
  "geometry": {"coordinates":[-1.618771,53.802135],"type":"Point"}
}
