{
  "type": "Feature",
  "properties": {
    "iso:country":"GB",
    "wof:name":"LS13 4SQ",
    "wof:placetype":"postalcode"
},
  "geometry": {"coordinates":[-1.61877092436782,53.80213521776947],"type":"Point"}
}