{
  "type": "Feature",
  "properties": {
    "iso:country":"GB",
    "wof:name":"WA7 5XP",
    "wof:placetype":"postalcode"
},
  "geometry": {"coordinates":[-2.711037233177,53.33814552023848],"type":"Point"}
}