{
  "type": "Feature",
  "properties": {
    "iso:country": "GB",
    "wof:name": "WA7 5XP",
    "wof:placetype": "postalcode"
  },
  "geometry": {"coordinates":[-2.711037,53.338146],"type":"Point"}
}
