{
  "type": "Feature",
  "properties": {
    "iso:country":"GB",
    "wof:name":"PL9 8EX",
    "wof:placetype":"postalcode"
},
  "geometry": {"coordinates":[-4.0738988487241,50.35407155026839],"type":"Point"}
}