{
  "type": "Feature",
  "properties": {
    "date:inception_lower": "1995-01-01",
    "date:inception_upper": "1995-01-01",
    "iso:country": "GB",
    "wof:name": "BN23 5RL",
    "wof:placetype": "postalcode"
  },
  "geometry": {"coordinates":[0.321085,50.791975],"type":"Point"}
}
