{
  "type": "Feature",
  "properties": {
    "iso:country": "GB",
    "wof:name": "ST13 8SA",
    "wof:placetype": "postalcode"
  },
  "geometry": {"coordinates":[-2.030916,53.115622],"type":"Point"}
}
