{
  "type": "Feature",
  "properties": {
    "date:inception_lower": "2000-12-01",
    "date:inception_upper": "2000-12-01",
    "iso:country": "GB",
    "wof:name": "W1D 4PT",
    "wof:placetype": "postalcode"
  },
  "geometry": {"coordinates":[-0.132071,51.51351],"type":"Point"}
}
