{
  "type": "Feature",
  "properties": {
    "iso:country":"GB",
    "wof:name":"WN5 0DW",
    "wof:placetype":"postalcode"
},
  "geometry": {"coordinates":[-2.68468783590153,53.54455392819962],"type":"Point"}
}