{
  "type": "Feature",
  "properties": {
    "date:inception_lower": "2022-05-01",
    "date:inception_upper": "2022-05-01",
    "iso:country": "GB",
    "wof:name": "DD3 9FB",
    "wof:placetype": "postalcode"
  },
  "geometry": {"coordinates":[-3.006599,56.492068],"type":"Point"}
}
