{
  "type": "Feature",
  "properties": {
    "date:inception_lower": "2011-05-01",
    "date:inception_upper": "2011-05-01",
    "iso:country": "GB",
    "wof:name": "LL53 7UQ",
    "wof:placetype": "postalcode"
  },
  "geometry": {"coordinates":[-4.507869,52.82656],"type":"Point"}
}
