{
  "type": "Feature",
  "properties": {
    "iso:country":"GB",
    "wof:name":"LL53 7UQ",
    "wof:placetype":"postalcode"
},
  "geometry": {"coordinates":[-4.50786928163645,52.82656023207026],"type":"Point"}
}