{
  "type": "Feature",
  "properties": {
    "iso:country":"GB",
    "wof:name":"SA44 6RD",
    "wof:placetype":"postalcode"
},
  "geometry": {"coordinates":[-4.49950740245073,52.13883647953075],"type":"Point"}
}