{
  "type": "Feature",
  "properties": {
    "date:inception_lower": "1980-01-01",
    "date:inception_upper": "1980-01-01",
    "iso:country": "GB",
    "wof:name": "TW11 9RP",
    "wof:placetype": "postalcode"
  },
  "geometry": {"coordinates":[-0.31117,51.418317],"type":"Point"}
}
