{
  "type": "Feature",
  "properties": {
    "iso:country":"GB",
    "wof:name":"TW11 9RP",
    "wof:placetype":"postalcode"
},
  "geometry": {"coordinates":[-0.31117051150112,51.41831659329328],"type":"Point"}
}