{
  "type": "Feature",
  "properties": {
    "date:inception_lower": "1992-01-01",
    "date:inception_upper": "1992-01-01",
    "iso:country": "GB",
    "wof:name": "RH12 5PE",
    "wof:placetype": "postalcode"
  },
  "geometry": {"coordinates":[-0.313899,51.084646],"type":"Point"}
}
