{
  "type": "Feature",
  "properties": {
    "iso:country":"GB",
    "wof:name":"RH12 5PE",
    "wof:placetype":"postalcode"
},
  "geometry": {"coordinates":[-0.3138986076436,51.08464625166563],"type":"Point"}
}