{
  "type": "Feature",
  "properties": {
    "date:inception_lower": "1997-12-01",
    "date:inception_upper": "1997-12-01",
    "iso:country": "GB",
    "wof:name": "BS16 9DE",
    "wof:placetype": "postalcode"
  },
  "geometry": {"coordinates":[-2.488478,51.486367],"type":"Point"}
}
