{
  "type": "Feature",
  "properties": {
    "date:inception_lower":"2001-06-01",
    "date:inception_upper":"2001-06-30",
    "iso:country":"GB",
    "wof:name":"BB11 5FH",
    "wof:placetype":"postalcode"
},
  "geometry": {"coordinates":[-2.278205,53.778185],"type":"Point"}
}