{
  "type": "Feature",
  "properties": {
    "iso:country":"GB",
    "wof:name":"BB11 5FH",
    "wof:placetype":"postalcode"
},
  "geometry": {"coordinates":[-2.27820525930808,53.77818534563409],"type":"Point"}
}