{
  "type": "Feature",
  "properties": {
    "iso:country":"GB",
    "wof:name":"SW13 0PA",
    "wof:placetype":"postalcode"
},
  "geometry": {"coordinates":[-0.25223739176258,51.47022946160249],"type":"Point"}
}