{
  "type": "Feature",
  "properties": {
    "date:inception_lower":"1980-01-01",
    "date:inception_upper":"1980-01-31",
    "iso:country":"GB",
    "wof:name":"SW13 0PA",
    "wof:placetype":"postalcode"
},
  "geometry": {"coordinates":[-0.252237,51.470229],"type":"Point"}
}