{
  "type": "Feature",
  "properties": {
    "iso:country":"GB",
    "wof:name":"HA3 7SU",
    "wof:placetype":"postalcode"
},
  "geometry": {"coordinates":[-0.3301519359035,51.59182544546],"type":"Point"}
}