{
  "type": "Feature",
  "properties": {
    "iso:country":"GB",
    "wof:name":"PL10 1DP",
    "wof:placetype":"postalcode"
},
  "geometry": {"coordinates":[-4.2105807816095,50.34877316277009],"type":"Point"}
}