{
  "type": "Feature",
  "properties": {
    "date:inception_lower":"1984-02-01",
    "date:inception_upper":"1984-02-29",
    "iso:country":"GB",
    "wof:name":"CT2 7UY",
    "wof:placetype":"postalcode"
},
  "geometry": {"coordinates":[1.058312,51.29664],"type":"Point"}
}