{
  "type": "Feature",
  "properties": {
    "iso:country":"GB",
    "wof:name":"KY5 9NY",
    "wof:placetype":"postalcode"
},
  "geometry": {"coordinates":[-3.31753915342137,56.12490109671761],"type":"Point"}
}