{
  "type": "Feature",
  "properties": {
    "date:inception_lower": "1980-01-01",
    "date:inception_upper": "1980-01-01",
    "iso:country": "GB",
    "wof:name": "KY5 9NY",
    "wof:placetype": "postalcode"
  },
  "geometry": {"coordinates":[-3.317539,56.124901],"type":"Point"}
}
