{
  "type": "Feature",
  "properties": {
    "iso:country":"GB",
    "wof:name":"CM7 4JB",
    "wof:placetype":"postalcode"
},
  "geometry": {"coordinates":[0.46588826375529,51.98218475494924],"type":"Point"}
}