{
  "type": "Feature",
  "properties": {
    "date:inception_lower": "1980-01-01",
    "date:inception_upper": "1980-01-01",
    "iso:country": "GB",
    "wof:name": "CV34 6SR",
    "wof:placetype": "postalcode"
  },
  "geometry": {"coordinates":[-1.540406,52.268556],"type":"Point"}
}
