{
  "type": "Feature",
  "properties": {
    "iso:country": "GB",
    "wof:name": "BD21 5QX",
    "wof:placetype": "postalcode"
  },
  "geometry": {"coordinates":[-1.903976,53.854742],"type":"Point"}
}
