{
  "type": "Feature",
  "properties": {
    "iso:country":"GB",
    "wof:name":"SG6 1QQ",
    "wof:placetype":"postalcode"
},
  "geometry": {"coordinates":[-0.21705845639254,51.9763792685597],"type":"Point"}
}