{
  "type": "Feature",
  "properties": {
    "iso:country": "GB",
    "wof:name": "HA4 0BJ",
    "wof:placetype": "postalcode"
  },
  "geometry": {"coordinates":[-0.382855,51.555354],"type":"Point"}
}
