{
  "type": "Feature",
  "properties": {
    "iso:country":"GB",
    "wof:name":"HA4 0BJ",
    "wof:placetype":"postalcode"
},
  "geometry": {"coordinates":[-0.38285523784615,51.55535383408699],"type":"Point"}
}