{
  "type": "Feature",
  "properties": {
    "iso:country": "GB",
    "wof:name": "SK22 4NY",
    "wof:placetype": "postalcode"
  },
  "geometry": {"coordinates":[-1.995062,53.363941],"type":"Point"}
}
