{
  "type": "Feature",
  "properties": {
    "iso:country": "GB",
    "wof:name": "DL10 4BP",
    "wof:placetype": "postalcode"
  },
  "geometry": {"coordinates":[-1.745299,54.408391],"type":"Point"}
}
