{
  "type": "Feature",
  "properties": {
    "date:inception_lower": "1980-01-01",
    "date:inception_upper": "1980-01-01",
    "iso:country": "GB",
    "wof:name": "DL10 4BP",
    "wof:placetype": "postalcode"
  },
  "geometry": {"coordinates":[-1.745299,54.408391],"type":"Point"}
}
