{
  "type": "Feature",
  "properties": {
    "iso:country":"GB",
    "wof:name":"DL10 4BP",
    "wof:placetype":"postalcode"
},
  "geometry": {"coordinates":[-1.74529878618902,54.40839098355703],"type":"Point"}
}