{
  "type": "Feature",
  "properties": {
    "iso:country":"GB",
    "wof:name":"SW4 6PT",
    "wof:placetype":"postalcode"
},
  "geometry": {"coordinates":[-0.12862373380481,51.47066872632876],"type":"Point"}
}