{
  "type": "Feature",
  "properties": {
    "date:inception_lower": "1994-05-01",
    "date:inception_upper": "1994-05-01",
    "iso:country": "GB",
    "wof:name": "NW1 9PW",
    "wof:placetype": "postalcode"
  },
  "geometry": {"coordinates":[-0.140132,51.543475],"type":"Point"}
}
