{
  "type": "Feature",
  "properties": {
    "iso:country":"GB",
    "wof:name":"NW1 9PW",
    "wof:placetype":"postalcode"
},
  "geometry": {"coordinates":[-0.1401319354483,51.54347539737624],"type":"Point"}
}