{
  "type": "Feature",
  "properties": {
    "iso:country":"GB",
    "wof:name":"NP44 3BQ",
    "wof:placetype":"postalcode"
},
  "geometry": {"coordinates":[-3.00921467247521,51.63873334800061],"type":"Point"}
}