{
  "type": "Feature",
  "properties": {
    "iso:country": "GB",
    "wof:name": "NP44 3BQ",
    "wof:placetype": "postalcode"
  },
  "geometry": {"coordinates":[-3.009215,51.638733],"type":"Point"}
}
