{
  "type": "Feature",
  "properties": {
    "iso:country":"GB",
    "wof:name":"IG1 2QF",
    "wof:placetype":"postalcode"
},
  "geometry": {"coordinates":[0.07770486384394,51.54717553837605],"type":"Point"}
}