{
  "type": "Feature",
  "properties": {
    "date:inception_lower": "1980-01-01",
    "date:inception_upper": "1980-01-01",
    "iso:country": "GB",
    "wof:name": "GU22 9QT",
    "wof:placetype": "postalcode"
  },
  "geometry": {"coordinates":[-0.571053,51.294865],"type":"Point"}
}
