{
  "type": "Feature",
  "properties": {
    "iso:country":"GB",
    "wof:name":"BD2 3SS",
    "wof:placetype":"postalcode"
},
  "geometry": {"coordinates":[-1.71977950636292,53.81674933355742],"type":"Point"}
}