{
  "type": "Feature",
  "properties": {
    "iso:country": "GB",
    "wof:name": "TS3 8AL",
    "wof:placetype": "postalcode"
  },
  "geometry": {"coordinates":[-1.20253,54.570704],"type":"Point"}
}
