{
  "type": "Feature",
  "properties": {
    "iso:country":"GB",
    "wof:name":"TW12 1HX",
    "wof:placetype":"postalcode"
},
  "geometry": {"coordinates":[-0.36002347323435,51.43002600791519],"type":"Point"}
}