{
  "type": "Feature",
  "properties": {
    "iso:country":"GB",
    "wof:name":"HX2 0EP",
    "wof:placetype":"postalcode"
},
  "geometry": {"coordinates":[-1.88931929123256,53.72819680674127],"type":"Point"}
}