{
  "type": "Feature",
  "properties": {
    "iso:country": "GB",
    "wof:name": "SY17 5JT",
    "wof:placetype": "postalcode"
  },
  "geometry": {"coordinates":[-3.541775,52.564458],"type":"Point"}
}
