{
  "type": "Feature",
  "properties": {
    "date:inception_lower": "1980-01-01",
    "date:inception_upper": "1980-01-01",
    "iso:country": "GB",
    "wof:name": "SY17 5JT",
    "wof:placetype": "postalcode"
  },
  "geometry": {"coordinates":[-3.541775,52.564458],"type":"Point"}
}
