{
  "type": "Feature",
  "properties": {
    "iso:country":"GB",
    "wof:name":"SY17 5JT",
    "wof:placetype":"postalcode"
},
  "geometry": {"coordinates":[-3.5417745980253,52.56445839987586],"type":"Point"}
}