{
  "type": "Feature",
  "properties": {
    "iso:country":"GB",
    "wof:name":"B14 5RS",
    "wof:placetype":"postalcode"
},
  "geometry": {"coordinates":[-1.89901898677509,52.40412452870239],"type":"Point"}
}