{
  "type": "Feature",
  "properties": {
    "date:inception_lower":"2003-10-01",
    "date:inception_upper":"2003-10-31",
    "iso:country":"GB",
    "wof:name":"NR14 8GG",
    "wof:placetype":"postalcode"
},
  "geometry": {"coordinates":[1.234019,52.554265],"type":"Point"}
}