{
  "type": "Feature",
  "properties": {
    "iso:country":"GB",
    "wof:name":"NR14 8GG",
    "wof:placetype":"postalcode"
},
  "geometry": {"coordinates":[1.23401921136363,52.55426517085547],"type":"Point"}
}