{
  "type": "Feature",
  "properties": {
    "date:inception_lower":"1999-06-01",
    "date:inception_upper":"1999-06-30",
    "iso:country":"GB",
    "wof:name":"CF10 4NG",
    "wof:placetype":"postalcode"
},
  "geometry": {"coordinates":[-3.166036,51.471337],"type":"Point"}
}