{
  "type": "Feature",
  "properties": {
    "iso:country": "GB",
    "wof:name": "BN44 3LB",
    "wof:placetype": "postalcode"
  },
  "geometry": {"coordinates":[-0.327596,50.888255],"type":"Point"}
}
