{
  "type": "Feature",
  "properties": {
    "date:inception_lower": "1990-02-01",
    "date:inception_upper": "1990-02-01",
    "iso:country": "GB",
    "wof:name": "BN44 3LB",
    "wof:placetype": "postalcode"
  },
  "geometry": {"coordinates":[-0.327596,50.888255],"type":"Point"}
}
