{
  "type": "Feature",
  "properties": {
    "iso:country":"GB",
    "wof:name":"BN44 3LB",
    "wof:placetype":"postalcode"
},
  "geometry": {"coordinates":[-0.32759611898612,50.88825496733927],"type":"Point"}
}