{
  "type": "Feature",
  "properties": {
    "iso:country":"GB",
    "wof:name":"IP24 3DZ",
    "wof:placetype":"postalcode"
},
  "geometry": {"coordinates":[0.74395639320152,52.40398792014567],"type":"Point"}
}