{
  "type": "Feature",
  "properties": {
    "iso:country":"GB",
    "wof:name":"RH11 8AJ",
    "wof:placetype":"postalcode"
},
  "geometry": {"coordinates":[-0.19325400875229,51.11270966936148],"type":"Point"}
}