{
  "type": "Feature",
  "properties": {
    "date:inception_lower":"1998-06-01",
    "date:inception_upper":"1998-06-30",
    "iso:country":"GB",
    "wof:name":"RH11 8AJ",
    "wof:placetype":"postalcode"
},
  "geometry": {"coordinates":[-0.193254,51.11271],"type":"Point"}
}