{
  "type": "Feature",
  "properties": {
    "iso:country":"GB",
    "wof:name":"WR11 8TE",
    "wof:placetype":"postalcode"
},
  "geometry": {"coordinates":[-1.89101857223539,52.11226528255234],"type":"Point"}
}