{
  "type": "Feature",
  "properties": {
    "date:inception_lower":"2001-12-01",
    "date:inception_upper":"2001-12-31",
    "iso:country":"GB",
    "wof:name":"WR11 8TE",
    "wof:placetype":"postalcode"
},
  "geometry": {"coordinates":[-1.891019,52.112265],"type":"Point"}
}