{
  "type": "Feature",
  "properties": {
    "iso:country":"GB",
    "wof:name":"NG9 7DZ",
    "wof:placetype":"postalcode"
},
  "geometry": {"coordinates":[-1.27403632003302,52.92266040066755],"type":"Point"}
}