{
  "type": "Feature",
  "properties": {
    "iso:country":"GB",
    "wof:name":"YO21 1JN",
    "wof:placetype":"postalcode"
},
  "geometry": {"coordinates":[-0.63180625879668,54.48385138161303],"type":"Point"}
}