{
  "type": "Feature",
  "properties": {
    "iso:country": "GB",
    "wof:name": "WA9 5QF",
    "wof:placetype": "postalcode"
  },
  "geometry": {"coordinates":[-2.758082,53.435016],"type":"Point"}
}
