{
  "type": "Feature",
  "properties": {
    "date:inception_lower": "1980-01-01",
    "date:inception_upper": "1980-01-01",
    "iso:country": "GB",
    "wof:name": "GL6 8LR",
    "wof:placetype": "postalcode"
  },
  "geometry": {"coordinates":[-2.142989,51.728977],"type":"Point"}
}
