{
  "type": "Feature",
  "properties": {
    "iso:country":"GB",
    "wof:name":"SR2 9BJ",
    "wof:placetype":"postalcode"
},
  "geometry": {"coordinates":[-1.39219149427142,54.88776549609465],"type":"Point"}
}