{
  "type": "Feature",
  "properties": {
    "date:inception_lower": "1984-10-01",
    "date:inception_upper": "1984-10-01",
    "iso:country": "GB",
    "wof:name": "PE30 3SH",
    "wof:placetype": "postalcode"
  },
  "geometry": {"coordinates":[0.425231,52.772316],"type":"Point"}
}
