{
  "type": "Feature",
  "properties": {
    "iso:country":"GB",
    "wof:name":"SA4 3PA",
    "wof:placetype":"postalcode"
},
  "geometry": {"coordinates":[-4.06844014231284,51.62767034363422],"type":"Point"}
}