{
  "type": "Feature",
  "properties": {
    "date:inception_lower": "2000-06-01",
    "date:inception_upper": "2000-06-01",
    "iso:country": "GB",
    "wof:name": "SA4 3PA",
    "wof:placetype": "postalcode"
  },
  "geometry": {"coordinates":[-4.06844,51.62767],"type":"Point"}
}
