{
  "type": "Feature",
  "properties": {
    "iso:country":"GB",
    "wof:name":"DD3 0XA",
    "wof:placetype":"postalcode"
},
  "geometry": {"coordinates":[-2.98406116601845,56.49496265597199],"type":"Point"}
}