{
  "type": "Feature",
  "properties": {
    "iso:country": "GB",
    "wof:name": "DD3 0XA",
    "wof:placetype": "postalcode"
  },
  "geometry": {"coordinates":[-2.984179,56.494961],"type":"Point"}
}
