{
  "type": "Feature",
  "properties": {
    "iso:country":"GB",
    "wof:name":"WS10 8SS",
    "wof:placetype":"postalcode"
},
  "geometry": {"coordinates":[-2.05143848431826,52.5611387116238],"type":"Point"}
}