{
  "type": "Feature",
  "properties": {
    "date:inception_lower":"1980-01-01",
    "date:inception_upper":"1980-01-31",
    "iso:country":"GB",
    "wof:name":"GL20 8RE",
    "wof:placetype":"postalcode"
},
  "geometry": {"coordinates":[-2.115729,52.006942],"type":"Point"}
}