{
  "type": "Feature",
  "properties": {
    "date:inception_lower": "1980-01-01",
    "date:inception_upper": "1980-01-01",
    "iso:country": "GB",
    "wof:name": "GU27 1PW",
    "wof:placetype": "postalcode"
  },
  "geometry": {"coordinates":[-0.743402,51.086751],"type":"Point"}
}
