{
  "type": "Feature",
  "properties": {
    "iso:country":"GB",
    "wof:name":"WD3 5NT",
    "wof:placetype":"postalcode"
},
  "geometry": {"coordinates":[-0.52914364618433,51.6499050113078],"type":"Point"}
}