{
  "type": "Feature",
  "properties": {
    "iso:country":"GB",
    "wof:name":"TS23 1HQ",
    "wof:placetype":"postalcode"
},
  "geometry": {"coordinates":[-1.2891996827615,54.5910567218178],"type":"Point"}
}