{
  "type": "Feature",
  "properties": {
    "iso:country":"GB",
    "wof:name":"W1G 9DG",
    "wof:placetype":"postalcode"
},
  "geometry": {"coordinates":[-0.14466766970991,51.5181164894835],"type":"Point"}
}