{
  "type": "Feature",
  "properties": {
    "iso:country": "GB",
    "wof:name": "LN2 5HR",
    "wof:placetype": "postalcode"
  },
  "geometry": {"coordinates":[-0.530811,53.23058],"type":"Point"}
}
