{
  "type": "Feature",
  "properties": {
    "iso:country": "GB",
    "wof:name": "S70 2EJ",
    "wof:placetype": "postalcode"
  },
  "geometry": {"coordinates":[-1.481058,53.554487],"type":"Point"}
}
