{
  "type": "Feature",
  "properties": {
    "iso:country":"GB",
    "wof:name":"L40 1UD",
    "wof:placetype":"postalcode"
},
  "geometry": {"coordinates":[-2.86224997959301,53.64308832676655],"type":"Point"}
}