{
  "type": "Feature",
  "properties": {
    "iso:country":"GB",
    "wof:name":"BN17 6BJ",
    "wof:placetype":"postalcode"
},
  "geometry": {"coordinates":[-0.52748281884149,50.80975809668838],"type":"Point"}
}