{
  "type": "Feature",
  "properties": {
    "iso:country":"GB",
    "wof:name":"CV32 6HJ",
    "wof:placetype":"postalcode"
},
  "geometry": {"coordinates":[-1.53840067809679,52.30362869790321],"type":"Point"}
}