{
  "type": "Feature",
  "properties": {
    "iso:country": "GB",
    "wof:name": "CV32 6HJ",
    "wof:placetype": "postalcode"
  },
  "geometry": {"coordinates":[-1.538404,52.303644],"type":"Point"}
}
