{
  "type": "Feature",
  "properties": {
    "iso:country":"GB",
    "wof:name":"B94 5JJ",
    "wof:placetype":"postalcode"
},
  "geometry": {"coordinates":[-1.84081521039663,52.36629316172655],"type":"Point"}
}