{
  "type": "Feature",
  "properties": {
    "iso:country": "GB",
    "wof:name": "SO50 9XN",
    "wof:placetype": "postalcode"
  },
  "geometry": {"coordinates":[-1.35084,50.969172],"type":"Point"}
}
