{
  "type": "Feature",
  "properties": {
    "iso:country":"GB",
    "wof:name":"SO50 9XN",
    "wof:placetype":"postalcode"
},
  "geometry": {"coordinates":[-1.35084035798616,50.96917172291606],"type":"Point"}
}