{
  "type": "Feature",
  "properties": {
    "iso:country":"GB",
    "wof:name":"DE14 1QL",
    "wof:placetype":"postalcode"
},
  "geometry": {"coordinates":[-1.62659883940531,52.81314544043369],"type":"Point"}
}