{
  "type": "Feature",
  "properties": {
    "iso:country":"GB",
    "wof:name":"IP1 1BY",
    "wof:placetype":"postalcode"
},
  "geometry": {"coordinates":[1.15346658971679,52.05737309168843],"type":"Point"}
}