{
  "type": "Feature",
  "properties": {
    "iso:country":"GB",
    "wof:name":"NR20 5JX",
    "wof:placetype":"postalcode"
},
  "geometry": {"coordinates":[0.94282109501973,52.75602228757463],"type":"Point"}
}