{
  "type": "Feature",
  "properties": {
    "date:inception_lower": "1980-01-01",
    "date:inception_upper": "1980-01-01",
    "iso:country": "GB",
    "wof:name": "NR20 5JX",
    "wof:placetype": "postalcode"
  },
  "geometry": {"coordinates":[0.942821,52.756022],"type":"Point"}
}
