{
  "type": "Feature",
  "properties": {
    "date:inception_lower": "2000-12-01",
    "date:inception_upper": "2000-12-01",
    "iso:country": "GB",
    "wof:name": "DD11 3RQ",
    "wof:placetype": "postalcode"
  },
  "geometry": {"coordinates":[-2.615634,56.571498],"type":"Point"}
}
