{
  "type": "Feature",
  "properties": {
    "iso:country":"GB",
    "wof:name":"CM11 2BJ",
    "wof:placetype":"postalcode"
},
  "geometry": {"coordinates":[0.42611131807543,51.62584076095868],"type":"Point"}
}