{
  "type": "Feature",
  "properties": {
    "iso:country":"GB",
    "wof:name":"SL3 7FW",
    "wof:placetype":"postalcode"
},
  "geometry": {"coordinates":[-0.55986118298082,51.50922844304734],"type":"Point"}
}