{
  "type": "Feature",
  "properties": {
    "date:inception_lower": "2013-11-01",
    "date:inception_upper": "2013-11-01",
    "iso:country": "GB",
    "wof:name": "SL3 7FW",
    "wof:placetype": "postalcode"
  },
  "geometry": {"coordinates":[-0.560073,51.509233],"type":"Point"}
}
