{
  "type": "Feature",
  "properties": {
    "iso:country":"GB",
    "wof:name":"WF6 2RR",
    "wof:placetype":"postalcode"
},
  "geometry": {"coordinates":[-1.40586912784842,53.69995532770533],"type":"Point"}
}