{
  "type": "Feature",
  "properties": {
    "date:inception_lower": "1980-01-01",
    "date:inception_upper": "1980-01-01",
    "iso:country": "GB",
    "wof:name": "LN11 7LZ",
    "wof:placetype": "postalcode"
  },
  "geometry": {"coordinates":[0.124045,53.436878],"type":"Point"}
}
