{
  "type": "Feature",
  "properties": {
    "iso:country":"GB",
    "wof:name":"HX6 1LH",
    "wof:placetype":"postalcode"
},
  "geometry": {"coordinates":[-1.93550543164509,53.70575127567906],"type":"Point"}
}