{
  "type": "Feature",
  "properties": {
    "iso:country":"GB",
    "wof:name":"CT9 4EQ",
    "wof:placetype":"postalcode"
},
  "geometry": {"coordinates":[1.39400065116829,51.36371583613173],"type":"Point"}
}