{
  "type": "Feature",
  "properties": {
    "iso:country": "GB",
    "wof:name": "CA8 9LZ",
    "wof:placetype": "postalcode"
  },
  "geometry": {"coordinates":[-2.715971,54.891287],"type":"Point"}
}
