{
  "type": "Feature",
  "properties": {
    "iso:country":"GB",
    "wof:name":"YO15 3TD",
    "wof:placetype":"postalcode"
},
  "geometry": {"coordinates":[-0.21047287373433,54.07783308542061],"type":"Point"}
}