{
  "type": "Feature",
  "properties": {
    "iso:country":"GB",
    "wof:name":"SY10 8AZ",
    "wof:placetype":"postalcode"
},
  "geometry": {"coordinates":[-3.0335455583002,52.82101527439416],"type":"Point"}
}