{
  "type": "Feature",
  "properties": {
    "iso:country": "GB",
    "wof:name": "SY10 8AZ",
    "wof:placetype": "postalcode"
  },
  "geometry": {"coordinates":[-3.033546,52.821015],"type":"Point"}
}
