{
  "type": "Feature",
  "properties": {
    "iso:country":"GB",
    "wof:name":"NG14 7BX",
    "wof:placetype":"postalcode"
},
  "geometry": {"coordinates":[-1.01706807213432,53.02180186848323],"type":"Point"}
}