{
  "type": "Feature",
  "properties": {
    "date:inception_lower": "1980-01-01",
    "date:inception_upper": "1980-01-01",
    "iso:country": "GB",
    "wof:name": "NG14 7BX",
    "wof:placetype": "postalcode"
  },
  "geometry": {"coordinates":[-1.017068,53.021802],"type":"Point"}
}
