{
  "type": "Feature",
  "properties": {
    "date:inception_lower": "1980-01-01",
    "date:inception_upper": "1980-01-01",
    "iso:country": "GB",
    "wof:name": "E3 2RW",
    "wof:placetype": "postalcode"
  },
  "geometry": {"coordinates":[-0.027386,51.533747],"type":"Point"}
}
