{
  "type": "Feature",
  "properties": {
    "iso:country":"GB",
    "wof:name":"SL8 5ST",
    "wof:placetype":"postalcode"
},
  "geometry": {"coordinates":[-0.71160639316785,51.57941258462381],"type":"Point"}
}