{
  "type": "Feature",
  "properties": {
    "iso:country":"GB",
    "wof:name":"PL9 8QE",
    "wof:placetype":"postalcode"
},
  "geometry": {"coordinates":[-4.07489243802538,50.35880282403722],"type":"Point"}
}