{
  "type": "Feature",
  "properties": {
    "iso:country":"GB",
    "wof:name":"PO9 2RS",
    "wof:placetype":"postalcode"
},
  "geometry": {"coordinates":[-0.96817354109399,50.85177139796781],"type":"Point"}
}