{
  "type": "Feature",
  "properties": {
    "iso:country":"GB",
    "wof:name":"GU27 1QU",
    "wof:placetype":"postalcode"
},
  "geometry": {"coordinates":[-0.74245131148166,51.08811692286872],"type":"Point"}
}