{
  "type": "Feature",
  "properties": {
    "iso:country": "GB",
    "wof:name": "GU27 1QU",
    "wof:placetype": "postalcode"
  },
  "geometry": {"coordinates":[-0.742451,51.088117],"type":"Point"}
}
