{
  "type": "Feature",
  "properties": {
    "date:inception_lower": "2021-01-01",
    "date:inception_upper": "2021-01-01",
    "iso:country": "GB",
    "wof:name": "B77 4GR",
    "wof:placetype": "postalcode"
  },
  "geometry": {"coordinates":[-1.644184,52.620506],"type":"Point"}
}
