{
  "type": "Feature",
  "properties": {
    "iso:country":"GB",
    "wof:name":"TW1 4PW",
    "wof:placetype":"postalcode"
},
  "geometry": {"coordinates":[-0.33865774241901,51.43923910378052],"type":"Point"}
}