{
  "type": "Feature",
  "properties": {
    "date:inception_lower": "1980-01-01",
    "date:inception_upper": "1980-01-01",
    "iso:country": "GB",
    "wof:name": "DA12 2PN",
    "wof:placetype": "postalcode"
  },
  "geometry": {"coordinates":[0.386014,51.439992],"type":"Point"}
}
