{
  "type": "Feature",
  "properties": {
    "iso:country": "GB",
    "wof:name": "WR2 6RY",
    "wof:placetype": "postalcode"
  },
  "geometry": {"coordinates":[-2.275227,52.20949],"type":"Point"}
}
