{
  "type": "Feature",
  "properties": {
    "iso:country":"GB",
    "wof:name":"M30 7GN",
    "wof:placetype":"postalcode"
},
  "geometry": {"coordinates":[-2.37688502131006,53.47447150102881],"type":"Point"}
}