{
  "type": "Feature",
  "properties": {
    "date:inception_lower": "1994-05-01",
    "date:inception_upper": "1994-05-01",
    "iso:country": "GB",
    "wof:name": "M30 7GN",
    "wof:placetype": "postalcode"
  },
  "geometry": {"coordinates":[-2.376885,53.474471],"type":"Point"}
}
