{
  "type": "Feature",
  "properties": {
    "iso:country":"GB",
    "wof:name":"G75 9PF",
    "wof:placetype":"postalcode"
},
  "geometry": {"coordinates":[-4.2075677600453,55.73894665655946],"type":"Point"}
}