{
  "type": "Feature",
  "properties": {
    "date:inception_lower":"2000-06-01",
    "date:inception_upper":"2000-06-30",
    "iso:country":"GB",
    "wof:name":"G75 9PF",
    "wof:placetype":"postalcode"
},
  "geometry": {"coordinates":[-4.207568,55.738947],"type":"Point"}
}