{
  "type": "Feature",
  "properties": {
    "iso:country":"GB",
    "wof:name":"NR7 0SL",
    "wof:placetype":"postalcode"
},
  "geometry": {"coordinates":[1.36667604570979,52.62460995972609],"type":"Point"}
}