{
  "type": "Feature",
  "properties": {
    "date:inception_lower": "1980-01-01",
    "date:inception_upper": "1980-01-01",
    "iso:country": "GB",
    "wof:name": "NR7 0SL",
    "wof:placetype": "postalcode"
  },
  "geometry": {"coordinates":[1.366171,52.624866],"type":"Point"}
}
