{
  "type": "Feature",
  "properties": {
    "iso:country": "GB",
    "wof:name": "M26 1PL",
    "wof:placetype": "postalcode"
  },
  "geometry": {"coordinates":[-2.362815,53.543537],"type":"Point"}
}
