{
  "type": "Feature",
  "properties": {
    "iso:country":"GB",
    "wof:name":"RG4 6QN",
    "wof:placetype":"postalcode"
},
  "geometry": {"coordinates":[-0.95691620089867,51.48495359104048],"type":"Point"}
}