{
  "type": "Feature",
  "properties": {
    "date:inception_lower": "1980-01-01",
    "date:inception_upper": "1980-01-01",
    "iso:country": "GB",
    "wof:name": "HR9 5QB",
    "wof:placetype": "postalcode"
  },
  "geometry": {"coordinates":[-2.586586,51.902628],"type":"Point"}
}
