{
  "type": "Feature",
  "properties": {
    "iso:country":"GB",
    "wof:name":"HR9 5QB",
    "wof:placetype":"postalcode"
},
  "geometry": {"coordinates":[-2.58658617298952,51.90262818026739],"type":"Point"}
}