{
  "type": "Feature",
  "properties": {
    "iso:country":"GB",
    "wof:name":"NE3 5LL",
    "wof:placetype":"postalcode"
},
  "geometry": {"coordinates":[-1.61425307778647,55.02184079301604],"type":"Point"}
}