{
  "type": "Feature",
  "properties": {
    "iso:country":"GB",
    "wof:name":"DL16 7DZ",
    "wof:placetype":"postalcode"
},
  "geometry": {"coordinates":[-1.61675443911295,54.68820922013347],"type":"Point"}
}