{
  "type": "Feature",
  "properties": {
    "iso:country": "GB",
    "wof:name": "DL16 7DZ",
    "wof:placetype": "postalcode"
  },
  "geometry": {"coordinates":[-1.616754,54.688209],"type":"Point"}
}
