{
  "type": "Feature",
  "properties": {
    "iso:country":"GB",
    "wof:name":"ML11 0GN",
    "wof:placetype":"postalcode"
},
  "geometry": {"coordinates":[-3.94386178876161,55.65658914865872],"type":"Point"}
}