{
  "type": "Feature",
  "properties": {
    "date:inception_lower": "1999-12-01",
    "date:inception_upper": "1999-12-01",
    "iso:country": "GB",
    "wof:name": "ML11 0GN",
    "wof:placetype": "postalcode"
  },
  "geometry": {"coordinates":[-3.943764,55.656481],"type":"Point"}
}
