{
  "type": "Feature",
  "properties": {
    "iso:country":"GB",
    "wof:name":"HA8 5PL",
    "wof:placetype":"postalcode"
},
  "geometry": {"coordinates":[-0.27701574589631,51.59550861497966],"type":"Point"}
}