{
  "type": "Feature",
  "properties": {
    "date:inception_lower": "1980-01-01",
    "date:inception_upper": "1980-01-01",
    "iso:country": "GB",
    "wof:name": "BH17 7XJ",
    "wof:placetype": "postalcode"
  },
  "geometry": {"coordinates":[-1.999168,50.740596],"type":"Point"}
}
