{
  "type": "Feature",
  "properties": {
    "iso:country":"GB",
    "wof:name":"BH17 7XJ",
    "wof:placetype":"postalcode"
},
  "geometry": {"coordinates":[-1.99916846125649,50.74059618614375],"type":"Point"}
}