{
  "type": "Feature",
  "properties": {
    "iso:country": "GB",
    "wof:name": "HU8 8PU",
    "wof:placetype": "postalcode"
  },
  "geometry": {"coordinates":[-0.31705,53.761225],"type":"Point"}
}
