{
  "type": "Feature",
  "properties": {
    "iso:country":"GB",
    "wof:name":"HU8 8PU",
    "wof:placetype":"postalcode"
},
  "geometry": {"coordinates":[-0.3170497550069,53.7612251651377],"type":"Point"}
}