{
  "type": "Feature",
  "properties": {
    "date:inception_lower":"1997-06-01",
    "date:inception_upper":"1997-06-30",
    "iso:country":"GB",
    "wof:name":"S36 6LX",
    "wof:placetype":"postalcode"
},
  "geometry": {"coordinates":[-1.627173,53.521747],"type":"Point"}
}