{
  "type": "Feature",
  "properties": {
    "iso:country":"GB",
    "wof:name":"S36 6LX",
    "wof:placetype":"postalcode"
},
  "geometry": {"coordinates":[-1.62717340430362,53.52174722255025],"type":"Point"}
}