{
  "type": "Feature",
  "properties": {
    "iso:country": "GB",
    "wof:name": "SO22 4HB",
    "wof:placetype": "postalcode"
  },
  "geometry": {"coordinates":[-1.348591,51.045477],"type":"Point"}
}
