{
  "type": "Feature",
  "properties": {
    "iso:country":"GB",
    "wof:name":"WA3 2ER",
    "wof:placetype":"postalcode"
},
  "geometry": {"coordinates":[-2.57761115716218,53.48104009173573],"type":"Point"}
}