{
  "type": "Feature",
  "properties": {
    "date:inception_lower":"1991-09-01",
    "date:inception_upper":"1991-09-30",
    "iso:country":"GB",
    "wof:name":"GU34 3DB",
    "wof:placetype":"postalcode"
},
  "geometry": {"coordinates":[-0.936992,51.091378],"type":"Point"}
}