{
  "type": "Feature",
  "properties": {
    "iso:country":"GB",
    "wof:name":"GU34 3DB",
    "wof:placetype":"postalcode"
},
  "geometry": {"coordinates":[-0.93699177561506,51.09137818975467],"type":"Point"}
}