{
  "type": "Feature",
  "properties": {
    "iso:country": "GB",
    "wof:name": "GU34 3DB",
    "wof:placetype": "postalcode"
  },
  "geometry": {"coordinates":[-0.936992,51.091378],"type":"Point"}
}
