{
  "type": "Feature",
  "properties": {
    "iso:country":"GB",
    "wof:name":"BN43 6LZ",
    "wof:placetype":"postalcode"
},
  "geometry": {"coordinates":[-0.24924745741322,50.83762499257117],"type":"Point"}
}