{
  "type": "Feature",
  "properties": {
    "date:inception_lower":"1987-04-01",
    "date:inception_upper":"1987-04-30",
    "iso:country":"GB",
    "wof:name":"BA12 9NX",
    "wof:placetype":"postalcode"
},
  "geometry": {"coordinates":[-2.188323,51.198268],"type":"Point"}
}