{
  "type": "Feature",
  "properties": {
    "iso:country":"GB",
    "wof:name":"NW7 1GT",
    "wof:placetype":"postalcode"
},
  "geometry": {"coordinates":[-0.21049058124343,51.60641002296961],"type":"Point"}
}