{
  "type": "Feature",
  "properties": {
    "iso:country":"GB",
    "wof:name":"YO61 3RB",
    "wof:placetype":"postalcode"
},
  "geometry": {"coordinates":[-1.16539738946209,54.16270056678311],"type":"Point"}
}