{
  "type": "Feature",
  "properties": {
    "date:inception_lower": "1998-06-01",
    "date:inception_upper": "1998-06-01",
    "iso:country": "GB",
    "wof:name": "YO61 3RB",
    "wof:placetype": "postalcode"
  },
  "geometry": {"coordinates":[-1.165397,54.162701],"type":"Point"}
}
