{
  "type": "Feature",
  "properties": {
    "iso:country": "GB",
    "wof:name": "B44 0HJ",
    "wof:placetype": "postalcode"
  },
  "geometry": {"coordinates":[-1.877636,52.535547],"type":"Point"}
}
