{
  "type": "Feature",
  "properties": {
    "iso:country":"GB",
    "wof:name":"AL3 4AF",
    "wof:placetype":"postalcode"
},
  "geometry": {"coordinates":[-0.3523931100381,51.74424042342696],"type":"Point"}
}