{
  "type": "Feature",
  "properties": {
    "iso:country":"GB",
    "wof:name":"CF32 9YH",
    "wof:placetype":"postalcode"
},
  "geometry": {"coordinates":[-3.56728030475884,51.5490004907604],"type":"Point"}
}