{
  "type": "Feature",
  "properties": {
    "date:inception_lower": "2024-05-01",
    "date:inception_upper": "2024-05-01",
    "iso:country": "GB",
    "wof:name": "DE4 5QJ",
    "wof:placetype": "postalcode"
  },
  "geometry": {"coordinates":[-1.479976,53.075605],"type":"Point"}
}
