{
  "type": "Feature",
  "properties": {
    "date:inception_lower": "1996-06-01",
    "date:inception_upper": "1996-06-01",
    "iso:country": "GB",
    "wof:name": "GU47 0TQ",
    "wof:placetype": "postalcode"
  },
  "geometry": {"coordinates":[-0.78028,51.353441],"type":"Point"}
}
