{
  "type": "Feature",
  "properties": {
    "iso:country":"GB",
    "wof:name":"GU47 0TQ",
    "wof:placetype":"postalcode"
},
  "geometry": {"coordinates":[-0.78028053386875,51.35344074170474],"type":"Point"}
}