{
  "type": "Feature",
  "properties": {
    "iso:country":"GB",
    "wof:name":"GL6 6TJ",
    "wof:placetype":"postalcode"
},
  "geometry": {"coordinates":[-2.1913232435968,51.79496513541643],"type":"Point"}
}