{
  "type": "Feature",
  "properties": {
    "iso:country": "GB",
    "wof:name": "GL6 6TJ",
    "wof:placetype": "postalcode"
  },
  "geometry": {"coordinates":[-2.191323,51.794965],"type":"Point"}
}
