{
  "type": "Feature",
  "properties": {
    "iso:country": "GB",
    "wof:name": "EX34 0JG",
    "wof:placetype": "postalcode"
  },
  "geometry": {"coordinates":[-4.021908,51.197895],"type":"Point"}
}
