{
  "type": "Feature",
  "properties": {
    "iso:country":"GB",
    "wof:name":"M8 8XD",
    "wof:placetype":"postalcode"
},
  "geometry": {"coordinates":[-2.23026889338964,53.50364322894035],"type":"Point"}
}