{
  "type": "Feature",
  "properties": {
    "iso:country":"GB",
    "wof:name":"CM1 4TD",
    "wof:placetype":"postalcode"
},
  "geometry": {"coordinates":[0.40550791770826,51.77835419896846],"type":"Point"}
}