{
  "type": "Feature",
  "properties": {
    "iso:country":"GB",
    "wof:name":"YO8 3SW",
    "wof:placetype":"postalcode"
},
  "geometry": {"coordinates":[-1.12645402163569,53.83233204751286],"type":"Point"}
}