{
  "type": "Feature",
  "properties": {
    "date:inception_lower": "1980-01-01",
    "date:inception_upper": "1980-01-01",
    "iso:country": "GB",
    "wof:name": "SP4 9RN",
    "wof:placetype": "postalcode"
  },
  "geometry": {"coordinates":[-1.787692,51.229133],"type":"Point"}
}
