{
  "type": "Feature",
  "properties": {
    "iso:country":"GB",
    "wof:name":"SP4 9RN",
    "wof:placetype":"postalcode"
},
  "geometry": {"coordinates":[-1.78769226849948,51.22913347047592],"type":"Point"}
}