{
  "type": "Feature",
  "properties": {
    "iso:country":"GB",
    "wof:name":"PR4 4JR",
    "wof:placetype":"postalcode"
},
  "geometry": {"coordinates":[-2.73122663650513,53.72449613321118],"type":"Point"}
}