{
  "type": "Feature",
  "properties": {
    "date:inception_lower": "1980-01-01",
    "date:inception_upper": "1980-01-01",
    "iso:country": "GB",
    "wof:name": "PR4 4JR",
    "wof:placetype": "postalcode"
  },
  "geometry": {"coordinates":[-2.731227,53.724496],"type":"Point"}
}
