{
  "type": "Feature",
  "properties": {
    "iso:country":"GB",
    "wof:name":"SW19 8SW",
    "wof:placetype":"postalcode"
},
  "geometry": {"coordinates":[-0.18722610240877,51.423425343826],"type":"Point"}
}