{
  "type": "Feature",
  "properties": {
    "date:inception_lower": "1987-04-01",
    "date:inception_upper": "1987-04-01",
    "iso:country": "GB",
    "wof:name": "SW19 8SW",
    "wof:placetype": "postalcode"
  },
  "geometry": {"coordinates":[-0.187226,51.423425],"type":"Point"}
}
