{
  "type": "Feature",
  "properties": {
    "iso:country": "GB",
    "wof:name": "EH4 4FS",
    "wof:placetype": "postalcode"
  },
  "geometry": {"coordinates":[-3.254395,55.972945],"type":"Point"}
}
