{
  "type": "Feature",
  "properties": {
    "iso:country": "GB",
    "wof:name": "DG12 5AX",
    "wof:placetype": "postalcode"
  },
  "geometry": {"coordinates":[-3.256361,54.989847],"type":"Point"}
}
