{
  "type": "Feature",
  "properties": {
    "date:inception_lower": "1997-06-01",
    "date:inception_upper": "1997-06-01",
    "iso:country": "GB",
    "wof:name": "M28 7JP",
    "wof:placetype": "postalcode"
  },
  "geometry": {"coordinates":[-2.38451,53.514617],"type":"Point"}
}
