{
  "type": "Feature",
  "properties": {
    "iso:country":"GB",
    "wof:name":"LL16 5PU",
    "wof:placetype":"postalcode"
},
  "geometry": {"coordinates":[-3.49950730458404,53.14821463269749],"type":"Point"}
}