{
  "type": "Feature",
  "properties": {
    "date:inception_lower": "2013-01-01",
    "date:inception_upper": "2013-01-01",
    "iso:country": "GB",
    "wof:name": "BH9 1FH",
    "wof:placetype": "postalcode"
  },
  "geometry": {"coordinates":[-1.876176,50.740583],"type":"Point"}
}
