{
  "type": "Feature",
  "properties": {
    "iso:country":"GB",
    "wof:name":"BH9 1FH",
    "wof:placetype":"postalcode"
},
  "geometry": {"coordinates":[-1.87609975090301,50.74058460686367],"type":"Point"}
}