{
  "type": "Feature",
  "properties": {
    "date:inception_lower": "1980-01-01",
    "date:inception_upper": "1980-01-01",
    "iso:country": "GB",
    "wof:name": "LA2 8PR",
    "wof:placetype": "postalcode"
  },
  "geometry": {"coordinates":[-2.524048,54.093816],"type":"Point"}
}
