{
  "type": "Feature",
  "properties": {
    "iso:country":"GB",
    "wof:name":"LA2 8PR",
    "wof:placetype":"postalcode"
},
  "geometry": {"coordinates":[-2.52404793729394,54.09381603856003],"type":"Point"}
}