{
  "type": "Feature",
  "properties": {
    "date:inception_lower": "1980-01-01",
    "date:inception_upper": "1980-01-01",
    "iso:country": "GB",
    "wof:name": "NN7 2EQ",
    "wof:placetype": "postalcode"
  },
  "geometry": {"coordinates":[-0.847707,52.162881],"type":"Point"}
}
