{
  "type": "Feature",
  "properties": {
    "iso:country": "GB",
    "wof:name": "TA22 9LJ",
    "wof:placetype": "postalcode"
  },
  "geometry": {"coordinates":[-3.506385,51.022678],"type":"Point"}
}
