{
  "type": "Feature",
  "properties": {
    "iso:country":"GB",
    "wof:name":"TA22 9LJ",
    "wof:placetype":"postalcode"
},
  "geometry": {"coordinates":[-3.50638472473466,51.02267783420407],"type":"Point"}
}