{
  "type": "Feature",
  "properties": {
    "date:inception_lower": "1980-01-01",
    "date:inception_upper": "1980-01-01",
    "iso:country": "GB",
    "wof:name": "GU4 8RW",
    "wof:placetype": "postalcode"
  },
  "geometry": {"coordinates":[-0.512791,51.220461],"type":"Point"}
}
