{
  "type": "Feature",
  "properties": {
    "iso:country": "GB",
    "wof:name": "BS34 5QR",
    "wof:placetype": "postalcode"
  },
  "geometry": {"coordinates":[-2.580147,51.52589],"type":"Point"}
}
