{
  "type": "Feature",
  "properties": {
    "date:inception_lower": "2017-06-01",
    "date:inception_upper": "2017-06-01",
    "iso:country": "GB",
    "wof:name": "BS34 5QR",
    "wof:placetype": "postalcode"
  },
  "geometry": {"coordinates":[-2.580147,51.52589],"type":"Point"}
}
