{
  "type": "Feature",
  "properties": {
    "date:inception_lower": "2023-03-01",
    "date:inception_upper": "2023-03-01",
    "iso:country": "GB",
    "wof:name": "SK4 1DA",
    "wof:placetype": "postalcode"
  },
  "geometry": {"coordinates":[-2.163796,53.421722],"type":"Point"}
}
