{
  "type": "Feature",
  "properties": {
    "date:inception_lower": "1980-01-01",
    "date:inception_upper": "1980-01-01",
    "iso:country": "GB",
    "wof:name": "L9 2BH",
    "wof:placetype": "postalcode"
  },
  "geometry": {"coordinates":[-2.957936,53.455151],"type":"Point"}
}
