{
  "type": "Feature",
  "properties": {
    "date:inception_lower":"1980-01-01",
    "date:inception_upper":"1980-01-31",
    "iso:country":"GB",
    "wof:name":"WA4 4QH",
    "wof:placetype":"postalcode"
},
  "geometry": {"coordinates":[-2.57528,53.314158],"type":"Point"}
}