{
  "type": "Feature",
  "properties": {
    "iso:country": "GB",
    "wof:name": "WA4 4QH",
    "wof:placetype": "postalcode"
  },
  "geometry": {"coordinates":[-2.57528,53.314158],"type":"Point"}
}
