{
  "type": "Feature",
  "properties": {
    "iso:country": "GB",
    "wof:name": "EH19 3DR",
    "wof:placetype": "postalcode"
  },
  "geometry": {"coordinates":[-3.109566,55.870755],"type":"Point"}
}
