{
  "type": "Feature",
  "properties": {
    "iso:country":"GB",
    "wof:name":"L35 0QF",
    "wof:placetype":"postalcode"
},
  "geometry": {"coordinates":[-2.75890997516547,53.40967125668224],"type":"Point"}
}