{
  "type": "Feature",
  "properties": {
    "iso:country":"GB",
    "wof:name":"DG2 8HZ",
    "wof:placetype":"postalcode"
},
  "geometry": {"coordinates":[-3.68351808382632,55.03583186695456],"type":"Point"}
}