{
  "type": "Feature",
  "properties": {
    "date:inception_lower":"1980-01-01",
    "date:inception_upper":"1980-01-31",
    "iso:country":"GB",
    "wof:name":"SA15 3EA",
    "wof:placetype":"postalcode"
},
  "geometry": {"coordinates":[-4.170158,51.688591],"type":"Point"}
}