{
  "type": "Feature",
  "properties": {
    "iso:country": "GB",
    "wof:name": "SA15 3EA",
    "wof:placetype": "postalcode"
  },
  "geometry": {"coordinates":[-4.170158,51.688591],"type":"Point"}
}
