{
  "type": "Feature",
  "properties": {
    "iso:country":"GB",
    "wof:name":"M21 8XL",
    "wof:placetype":"postalcode"
},
  "geometry": {"coordinates":[-2.27056132931687,53.43866192601016],"type":"Point"}
}