{
  "type": "Feature",
  "properties": {
    "iso:country":"GB",
    "wof:name":"LN5 9WR",
    "wof:placetype":"postalcode"
},
  "geometry": {"coordinates":[-0.64048934535817,53.13027718954572],"type":"Point"}
}