{
  "type": "Feature",
  "properties": {
    "iso:country": "GB",
    "wof:name": "TS4 2AL",
    "wof:placetype": "postalcode"
  },
  "geometry": {"coordinates":[-1.217514,54.559672],"type":"Point"}
}
