{
  "type": "Feature",
  "properties": {
    "date:inception_lower": "2008-07-01",
    "date:inception_upper": "2008-07-01",
    "iso:country": "GB",
    "wof:name": "TS4 2AL",
    "wof:placetype": "postalcode"
  },
  "geometry": {"coordinates":[-1.217514,54.559672],"type":"Point"}
}
