{
  "type": "Feature",
  "properties": {
    "iso:country":"GB",
    "wof:name":"TS4 2AL",
    "wof:placetype":"postalcode"
},
  "geometry": {"coordinates":[-1.21751415705184,54.55967225194629],"type":"Point"}
}