{
  "type": "Feature",
  "properties": {
    "iso:country": "GB",
    "wof:name": "DN15 6SF",
    "wof:placetype": "postalcode"
  },
  "geometry": {"coordinates":[-0.647637,53.59405],"type":"Point"}
}
