{
  "type": "Feature",
  "properties": {
    "iso:country":"GB",
    "wof:name":"DN15 6SF",
    "wof:placetype":"postalcode"
},
  "geometry": {"coordinates":[-0.64694827352113,53.59369696447444],"type":"Point"}
}