{
  "type": "Feature",
  "properties": {
    "iso:country":"GB",
    "wof:name":"BB1 8AN",
    "wof:placetype":"postalcode"
},
  "geometry": {"coordinates":[-2.48897672301519,53.75291016652834],"type":"Point"}
}