{
  "type": "Feature",
  "properties": {
    "date:inception_lower": "1980-01-01",
    "date:inception_upper": "1980-01-01",
    "iso:country": "GB",
    "wof:name": "LL55 2HS",
    "wof:placetype": "postalcode"
  },
  "geometry": {"coordinates":[-4.26878,53.133709],"type":"Point"}
}
