{
  "type": "Feature",
  "properties": {
    "date:inception_lower": "2021-06-01",
    "date:inception_upper": "2021-06-01",
    "iso:country": "GB",
    "wof:name": "LE12 7YZ",
    "wof:placetype": "postalcode"
  },
  "geometry": {"coordinates":[-1.097668,52.739143],"type":"Point"}
}
