{
  "type": "Feature",
  "properties": {
    "date:inception_lower": "2021-07-01",
    "date:inception_upper": "2021-07-01",
    "iso:country": "GB",
    "wof:name": "NG19 8PZ",
    "wof:placetype": "postalcode"
  },
  "geometry": {"coordinates":[-1.190834,53.170967],"type":"Point"}
}
