{
  "type": "Feature",
  "properties": {
    "date:inception_lower": "1990-07-01",
    "date:inception_upper": "1990-07-01",
    "iso:country": "GB",
    "wof:name": "LE15 6BD",
    "wof:placetype": "postalcode"
  },
  "geometry": {"coordinates":[-0.733168,52.670575],"type":"Point"}
}
