{
  "type": "Feature",
  "properties": {
    "iso:country":"GB",
    "wof:name":"PL20 7RL",
    "wof:placetype":"postalcode"
},
  "geometry": {"coordinates":[-4.09919644712307,50.50446011259439],"type":"Point"}
}