{
  "type": "Feature",
  "properties": {
    "date:inception_lower":"1980-01-01",
    "date:inception_upper":"1980-01-31",
    "iso:country":"GB",
    "wof:name":"PL20 7RL",
    "wof:placetype":"postalcode"
},
  "geometry": {"coordinates":[-4.099196,50.50446],"type":"Point"}
}