{
  "type": "Feature",
  "properties": {
    "iso:country":"GB",
    "wof:name":"CV7 7FS",
    "wof:placetype":"postalcode"
},
  "geometry": {"coordinates":[-1.64999861174692,52.38456410285169],"type":"Point"}
}