{
  "type": "Feature",
  "properties": {
    "iso:country":"GB",
    "wof:name":"ST7 8DN",
    "wof:placetype":"postalcode"
},
  "geometry": {"coordinates":[-2.31767506418958,53.05201711421732],"type":"Point"}
}