{
  "type": "Feature",
  "properties": {
    "iso:country":"GB",
    "wof:name":"S64 8LA",
    "wof:placetype":"postalcode"
},
  "geometry": {"coordinates":[-1.31874915460639,53.4751128459086],"type":"Point"}
}