{
  "type": "Feature",
  "properties": {
    "date:inception_lower": "1980-01-01",
    "date:inception_upper": "1980-01-01",
    "iso:country": "GB",
    "wof:name": "S64 8LA",
    "wof:placetype": "postalcode"
  },
  "geometry": {"coordinates":[-1.318751,53.475132],"type":"Point"}
}
