{
  "type": "Feature",
  "properties": {
    "iso:country": "GB",
    "wof:name": "SW1V 2RX",
    "wof:placetype": "postalcode"
  },
  "geometry": {"coordinates":[-0.132727,51.49041],"type":"Point"}
}
