{
  "type": "Feature",
  "properties": {
    "iso:country":"GB",
    "wof:name":"SW1V 2RX",
    "wof:placetype":"postalcode"
},
  "geometry": {"coordinates":[-0.13272752304884,51.49040987748668],"type":"Point"}
}