{
  "type": "Feature",
  "properties": {
    "iso:country": "GB",
    "wof:name": "CW9 5JQ",
    "wof:placetype": "postalcode"
  },
  "geometry": {"coordinates":[-2.513425,53.25915],"type":"Point"}
}
