{
  "type": "Feature",
  "properties": {
    "iso:country": "GB",
    "wof:name": "SN8 3EZ",
    "wof:placetype": "postalcode"
  },
  "geometry": {"coordinates":[-1.710719,51.281041],"type":"Point"}
}
