{
  "type": "Feature",
  "properties": {
    "iso:country":"GB",
    "wof:name":"SN8 3EZ",
    "wof:placetype":"postalcode"
},
  "geometry": {"coordinates":[-1.71071860316893,51.28104061412655],"type":"Point"}
}