{
  "type": "Feature",
  "properties": {
    "iso:country":"GB",
    "wof:name":"SN15 4LJ",
    "wof:placetype":"postalcode"
},
  "geometry": {"coordinates":[-2.09307403184627,51.47236985272021],"type":"Point"}
}