{
  "type": "Feature",
  "properties": {
    "iso:country":"GB",
    "wof:name":"YO42 2NB",
    "wof:placetype":"postalcode"
},
  "geometry": {"coordinates":[-0.7714179754008,53.93371302188351],"type":"Point"}
}