{
  "type": "Feature",
  "properties": {
    "date:inception_lower":"1998-06-01",
    "date:inception_upper":"1998-06-30",
    "iso:country":"GB",
    "wof:name":"YO42 2NB",
    "wof:placetype":"postalcode"
},
  "geometry": {"coordinates":[-0.771418,53.933713],"type":"Point"}
}