{
  "type": "Feature",
  "properties": {
    "iso:country": "GB",
    "wof:name": "YO42 2NB",
    "wof:placetype": "postalcode"
  },
  "geometry": {"coordinates":[-0.771418,53.933713],"type":"Point"}
}
