{
  "type": "Feature",
  "properties": {
    "iso:country": "GB",
    "wof:name": "BS40 5NA",
    "wof:placetype": "postalcode"
  },
  "geometry": {"coordinates":[-2.761132,51.362277],"type":"Point"}
}
