{
  "type": "Feature",
  "properties": {
    "date:inception_lower": "2015-05-01",
    "date:inception_upper": "2015-05-01",
    "iso:country": "GB",
    "wof:name": "M35 0NF",
    "wof:placetype": "postalcode"
  },
  "geometry": {"coordinates":[-2.171522,53.505135],"type":"Point"}
}
