{
  "type": "Feature",
  "properties": {
    "iso:country": "GB",
    "wof:name": "M35 0NF",
    "wof:placetype": "postalcode"
  },
  "geometry": {"coordinates":[-2.171522,53.505135],"type":"Point"}
}
