{
  "type": "Feature",
  "properties": {
    "date:inception_lower":"1980-01-01",
    "date:inception_upper":"1980-01-31",
    "iso:country":"GB",
    "wof:name":"B64 7LJ",
    "wof:placetype":"postalcode"
},
  "geometry": {"coordinates":[-2.066559,52.464202],"type":"Point"}
}