{
  "type": "Feature",
  "properties": {
    "date:inception_lower": "2018-06-01",
    "date:inception_upper": "2018-06-01",
    "iso:country": "GB",
    "wof:name": "RG8 8AW",
    "wof:placetype": "postalcode"
  },
  "geometry": {"coordinates":[-1.109936,51.481711],"type":"Point"}
}
