{
  "type": "Feature",
  "properties": {
    "iso:country":"GB",
    "wof:name":"EX23 9PN",
    "wof:placetype":"postalcode"
},
  "geometry": {"coordinates":[-4.48017918834194,50.91621613443929],"type":"Point"}
}