{
  "type": "Feature",
  "properties": {
    "iso:country":"GB",
    "wof:name":"TF7 5NF",
    "wof:placetype":"postalcode"
},
  "geometry": {"coordinates":[-2.46239741856756,52.63845780655476],"type":"Point"}
}