{
  "type": "Feature",
  "properties": {
    "iso:country":"GB",
    "wof:name":"PE6 7NN",
    "wof:placetype":"postalcode"
},
  "geometry": {"coordinates":[-0.27665899601188,52.63948966809808],"type":"Point"}
}