{
  "type": "Feature",
  "properties": {
    "date:inception_lower": "2019-06-01",
    "date:inception_upper": "2019-06-01",
    "iso:country": "GB",
    "wof:name": "BS31 2TB",
    "wof:placetype": "postalcode"
  },
  "geometry": {"coordinates":[-2.515164,51.400651],"type":"Point"}
}
