{
  "type": "Feature",
  "properties": {
    "iso:country":"GB",
    "wof:name":"B66 3HE",
    "wof:placetype":"postalcode"
},
  "geometry": {"coordinates":[-1.96008830678272,52.49086940707978],"type":"Point"}
}