{
  "type": "Feature",
  "properties": {
    "date:inception_lower":"1994-12-01",
    "date:inception_upper":"1994-12-31",
    "iso:country":"GB",
    "wof:name":"B66 3HE",
    "wof:placetype":"postalcode"
},
  "geometry": {"coordinates":[-1.960088,52.490869],"type":"Point"}
}