{
  "type": "Feature",
  "properties": {
    "date:inception_lower":"2014-01-01",
    "date:inception_upper":"2014-01-31",
    "iso:country":"GB",
    "wof:name":"M28 1FL",
    "wof:placetype":"postalcode"
},
  "geometry": {"coordinates":[-2.422246,53.504476],"type":"Point"}
}