{
  "type": "Feature",
  "properties": {
    "iso:country":"GB",
    "wof:name":"M28 1FL",
    "wof:placetype":"postalcode"
},
  "geometry": {"coordinates":[-2.42224604010336,53.50447613298351],"type":"Point"}
}