{
  "type": "Feature",
  "properties": {
    "iso:country": "GB",
    "wof:name": "HD7 6BL",
    "wof:placetype": "postalcode"
  },
  "geometry": {"coordinates":[-1.924739,53.601266],"type":"Point"}
}
