{
  "type": "Feature",
  "properties": {
    "iso:country":"GB",
    "wof:name":"HD7 6BL",
    "wof:placetype":"postalcode"
},
  "geometry": {"coordinates":[-1.92473868264064,53.6012664679245],"type":"Point"}
}