{
  "type": "Feature",
  "properties": {
    "date:inception_lower": "1980-01-01",
    "date:inception_upper": "1980-01-01",
    "iso:country": "GB",
    "wof:name": "CF45 4RA",
    "wof:placetype": "postalcode"
  },
  "geometry": {"coordinates":[-3.330191,51.646496],"type":"Point"}
}
