{
  "type": "Feature",
  "properties": {
    "iso:country":"GB",
    "wof:name":"CF45 4RA",
    "wof:placetype":"postalcode"
},
  "geometry": {"coordinates":[-3.33019100135142,51.6464960662444],"type":"Point"}
}