{
  "type": "Feature",
  "properties": {
    "iso:country":"GB",
    "wof:name":"WF11 9BN",
    "wof:placetype":"postalcode"
},
  "geometry": {"coordinates":[-1.23833792969629,53.71044983832552],"type":"Point"}
}