{
  "type": "Feature",
  "properties": {
    "iso:country":"GB",
    "wof:name":"M1 4QD",
    "wof:placetype":"postalcode"
},
  "geometry": {"coordinates":[-2.24148174717692,53.47643103792392],"type":"Point"}
}