{
  "type": "Feature",
  "properties": {
    "iso:country":"GB",
    "wof:name":"CM11 2RQ",
    "wof:placetype":"postalcode"
},
  "geometry": {"coordinates":[0.43196198468727,51.61177132726179],"type":"Point"}
}