{
  "type": "Feature",
  "properties": {
    "iso:country": "GB",
    "wof:name": "CM11 2RQ",
    "wof:placetype": "postalcode"
  },
  "geometry": {"coordinates":[0.431962,51.611771],"type":"Point"}
}
