{
  "type": "Feature",
  "properties": {
    "iso:country": "GB",
    "wof:name": "TF4 3LR",
    "wof:placetype": "postalcode"
  },
  "geometry": {"coordinates":[-2.463143,52.658709],"type":"Point"}
}
