{
  "type": "Feature",
  "properties": {
    "date:inception_lower": "1980-01-01",
    "date:inception_upper": "1980-01-01",
    "iso:country": "GB",
    "wof:name": "SK8 6BA",
    "wof:placetype": "postalcode"
  },
  "geometry": {"coordinates":[-2.195177,53.376932],"type":"Point"}
}
