{
  "type": "Feature",
  "properties": {
    "iso:country":"GB",
    "wof:name":"SK8 6BA",
    "wof:placetype":"postalcode"
},
  "geometry": {"coordinates":[-2.1951766031189,53.37693179131931],"type":"Point"}
}