{
  "type": "Feature",
  "properties": {
    "iso:country": "GB",
    "wof:name": "NE22 7EB",
    "wof:placetype": "postalcode"
  },
  "geometry": {"coordinates":[-1.564727,55.142313],"type":"Point"}
}
