{
  "type": "Feature",
  "properties": {
    "iso:country":"GB",
    "wof:name":"GU15 2NP",
    "wof:placetype":"postalcode"
},
  "geometry": {"coordinates":[-0.74926251744478,51.3301746974177],"type":"Point"}
}