{
  "type": "Feature",
  "properties": {
    "iso:country":"GB",
    "wof:name":"B14 7NE",
    "wof:placetype":"postalcode"
},
  "geometry": {"coordinates":[-1.90642256524972,52.42721707594156],"type":"Point"}
}