{
  "type": "Feature",
  "properties": {
    "date:inception_lower":"1999-06-01",
    "date:inception_upper":"1999-06-30",
    "iso:country":"GB",
    "wof:name":"NP18 3DB",
    "wof:placetype":"postalcode"
},
  "geometry": {"coordinates":[-2.971003,51.614859],"type":"Point"}
}