{
  "type": "Feature",
  "properties": {
    "iso:country": "GB",
    "wof:name": "NP18 3DB",
    "wof:placetype": "postalcode"
  },
  "geometry": {"coordinates":[-2.971003,51.614859],"type":"Point"}
}
