{
  "type": "Feature",
  "properties": {
    "date:inception_lower": "1980-01-01",
    "date:inception_upper": "1980-01-01",
    "iso:country": "GB",
    "wof:name": "TN15 8AW",
    "wof:placetype": "postalcode"
  },
  "geometry": {"coordinates":[0.306212,51.292579],"type":"Point"}
}
