{
  "type": "Feature",
  "properties": {
    "iso:country":"GB",
    "wof:name":"TN15 8AW",
    "wof:placetype":"postalcode"
},
  "geometry": {"coordinates":[0.30613954685792,51.29254511151349],"type":"Point"}
}