{
  "type": "Feature",
  "properties": {
    "iso:country":"GB",
    "wof:name":"KT6 5RP",
    "wof:placetype":"postalcode"
},
  "geometry": {"coordinates":[-0.31558763301239,51.3900898473938],"type":"Point"}
}