{
  "type": "Feature",
  "properties": {
    "date:inception_lower":"2001-06-01",
    "date:inception_upper":"2001-06-30",
    "iso:country":"GB",
    "wof:name":"TS17 5AP",
    "wof:placetype":"postalcode"
},
  "geometry": {"coordinates":[-1.315415,54.526402],"type":"Point"}
}