{
  "type": "Feature",
  "properties": {
    "iso:country":"GB",
    "wof:name":"TS28 5PW",
    "wof:placetype":"postalcode"
},
  "geometry": {"coordinates":[-1.37701124588153,54.73578793063584],"type":"Point"}
}