{
  "type": "Feature",
  "properties": {
    "iso:country": "GB",
    "wof:name": "TS28 5PW",
    "wof:placetype": "postalcode"
  },
  "geometry": {"coordinates":[-1.377011,54.735788],"type":"Point"}
}
