{
  "type": "Feature",
  "properties": {
    "iso:country":"GB",
    "wof:name":"BS3 1JX",
    "wof:placetype":"postalcode"
},
  "geometry": {"coordinates":[-2.6166079982723,51.44330607621467],"type":"Point"}
}