{
  "type": "Feature",
  "properties": {
    "iso:country": "GB",
    "wof:name": "BS3 1JX",
    "wof:placetype": "postalcode"
  },
  "geometry": {"coordinates":[-2.61661,51.443304],"type":"Point"}
}
