{
  "type": "Feature",
  "properties": {
    "iso:country": "GB",
    "wof:name": "SN7 7RG",
    "wof:placetype": "postalcode"
  },
  "geometry": {"coordinates":[-1.567328,51.599513],"type":"Point"}
}
