{
  "type": "Feature",
  "properties": {
    "iso:country":"GB",
    "wof:name":"SN7 7RG",
    "wof:placetype":"postalcode"
},
  "geometry": {"coordinates":[-1.56732774641638,51.59951342286544],"type":"Point"}
}