{
  "type": "Feature",
  "properties": {
    "iso:country":"GB",
    "wof:name":"M40 8DR",
    "wof:placetype":"postalcode"
},
  "geometry": {"coordinates":[-2.2154717498254,53.4933251690486],"type":"Point"}
}