{
  "type": "Feature",
  "properties": {
    "iso:country":"GB",
    "wof:name":"SW15 4NF",
    "wof:placetype":"postalcode"
},
  "geometry": {"coordinates":[-0.24361761885411,51.44685512824481],"type":"Point"}
}