{
  "type": "Feature",
  "properties": {
    "iso:country": "GB",
    "wof:name": "SW15 4NF",
    "wof:placetype": "postalcode"
  },
  "geometry": {"coordinates":[-0.243618,51.446855],"type":"Point"}
}
