{
  "type": "Feature",
  "properties": {
    "iso:country":"GB",
    "wof:name":"EH15 2HW",
    "wof:placetype":"postalcode"
},
  "geometry": {"coordinates":[-3.09994188775796,55.9486016941522],"type":"Point"}
}