{
  "type": "Feature",
  "properties": {
    "iso:country": "GB",
    "wof:name": "GL2 4RY",
    "wof:placetype": "postalcode"
  },
  "geometry": {"coordinates":[-2.29053,51.821771],"type":"Point"}
}
