{
  "type": "Feature",
  "properties": {
    "iso:country":"GB",
    "wof:name":"GL2 4RY",
    "wof:placetype":"postalcode"
},
  "geometry": {"coordinates":[-2.29053053417702,51.82177065892913],"type":"Point"}
}