{
  "type": "Feature",
  "properties": {
    "iso:country":"GB",
    "wof:name":"YO25 6HL",
    "wof:placetype":"postalcode"
},
  "geometry": {"coordinates":[-0.43927826724905,54.00912806166124],"type":"Point"}
}