{
  "type": "Feature",
  "properties": {
    "iso:country":"GB",
    "wof:name":"G62 8BE",
    "wof:placetype":"postalcode"
},
  "geometry": {"coordinates":[-4.31211599070412,55.94461859271972],"type":"Point"}
}