{
  "type": "Feature",
  "properties": {
    "iso:country":"GB",
    "wof:name":"W10 4DA",
    "wof:placetype":"postalcode"
},
  "geometry": {"coordinates":[-0.21400736202221,51.52815821155379],"type":"Point"}
}