{
  "type": "Feature",
  "properties": {
    "iso:country":"GB",
    "wof:name":"ST6 1BB",
    "wof:placetype":"postalcode"
},
  "geometry": {"coordinates":[-2.18639226800518,53.05173817059576],"type":"Point"}
}