{
  "type": "Feature",
  "properties": {
    "date:inception_lower":"1980-01-01",
    "date:inception_upper":"1980-01-31",
    "iso:country":"GB",
    "wof:name":"ST6 1BB",
    "wof:placetype":"postalcode"
},
  "geometry": {"coordinates":[-2.186392,53.051738],"type":"Point"}
}