{
  "type": "Feature",
  "properties": {
    "iso:country":"GB",
    "wof:name":"BN7 3QF",
    "wof:placetype":"postalcode"
},
  "geometry": {"coordinates":[-0.0096009431804,50.88674585201555],"type":"Point"}
}