{
  "type": "Feature",
  "properties": {
    "iso:country": "GB",
    "wof:name": "BN7 3QF",
    "wof:placetype": "postalcode"
  },
  "geometry": {"coordinates":[-0.009601,50.886746],"type":"Point"}
}
