{
  "type": "Feature",
  "properties": {
    "date:inception_lower":"1980-01-01",
    "date:inception_upper":"1980-01-31",
    "iso:country":"GB",
    "wof:name":"BN7 3QF",
    "wof:placetype":"postalcode"
},
  "geometry": {"coordinates":[-0.009601,50.886746],"type":"Point"}
}