{
  "type": "Feature",
  "properties": {
    "date:inception_lower": "2010-12-01",
    "date:inception_upper": "2010-12-01",
    "iso:country": "GB",
    "wof:name": "TS14 6PL",
    "wof:placetype": "postalcode"
  },
  "geometry": {"coordinates":[-1.058627,54.535291],"type":"Point"}
}
