{
  "type": "Feature",
  "properties": {
    "iso:country": "GB",
    "wof:name": "TS14 6PL",
    "wof:placetype": "postalcode"
  },
  "geometry": {"coordinates":[-1.058627,54.535291],"type":"Point"}
}
