{
  "type": "Feature",
  "properties": {
    "iso:country":"GB",
    "wof:name":"TS14 6PL",
    "wof:placetype":"postalcode"
},
  "geometry": {"coordinates":[-1.05862709972426,54.53529080828793],"type":"Point"}
}