{
  "type": "Feature",
  "properties": {
    "iso:country": "GB",
    "wof:name": "BN14 9JP",
    "wof:placetype": "postalcode"
  },
  "geometry": {"coordinates":[-0.364445,50.833937],"type":"Point"}
}
