{
  "type": "Feature",
  "properties": {
    "iso:country":"GB",
    "wof:name":"L8 6TG",
    "wof:placetype":"postalcode"
},
  "geometry": {"coordinates":[-2.97579632645766,53.39003671273207],"type":"Point"}
}