{
  "type": "Feature",
  "properties": {
    "iso:country":"GB",
    "wof:name":"SE12 0BH",
    "wof:placetype":"postalcode"
},
  "geometry": {"coordinates":[0.02152248089778,51.43408435142704],"type":"Point"}
}