{
  "type": "Feature",
  "properties": {
    "iso:country": "GB",
    "wof:name": "SE12 0BH",
    "wof:placetype": "postalcode"
  },
  "geometry": {"coordinates":[0.021483,51.433833],"type":"Point"}
}
