{
  "type": "Feature",
  "properties": {
    "iso:country":"GB",
    "wof:name":"W1T 1UF",
    "wof:placetype":"postalcode"
},
  "geometry": {"coordinates":[-0.13193083534865,51.51694313632625],"type":"Point"}
}