{
  "type": "Feature",
  "properties": {
    "iso:country": "GB",
    "wof:name": "PL26 8QB",
    "wof:placetype": "postalcode"
  },
  "geometry": {"coordinates":[-4.830778,50.411042],"type":"Point"}
}
