{
  "type": "Feature",
  "properties": {
    "iso:country":"GB",
    "wof:name":"PL26 8QB",
    "wof:placetype":"postalcode"
},
  "geometry": {"coordinates":[-4.83077801500533,50.41104224266671],"type":"Point"}
}