{
  "type": "Feature",
  "properties": {
    "iso:country":"GB",
    "wof:name":"BS26 2NH",
    "wof:placetype":"postalcode"
},
  "geometry": {"coordinates":[-2.84796252900492,51.25514341042439],"type":"Point"}
}