{
  "type": "Feature",
  "properties": {
    "date:inception_lower": "1996-06-01",
    "date:inception_upper": "1996-06-01",
    "iso:country": "GB",
    "wof:name": "AB11 8RZ",
    "wof:placetype": "postalcode"
  },
  "geometry": {"coordinates":[-2.081589,57.131947],"type":"Point"}
}
