{
  "type": "Feature",
  "properties": {
    "date:inception_lower": "2021-05-01",
    "date:inception_upper": "2021-05-01",
    "iso:country": "GB",
    "wof:name": "MK44 3FF",
    "wof:placetype": "postalcode"
  },
  "geometry": {"coordinates":[-0.338441,52.129629],"type":"Point"}
}
