{
  "type": "Feature",
  "properties": {
    "iso:country":"GB",
    "wof:name":"KT16 0AW",
    "wof:placetype":"postalcode"
},
  "geometry": {"coordinates":[-0.54768887845609,51.39070527683636],"type":"Point"}
}