{
  "type": "Feature",
  "properties": {
    "iso:country":"GB",
    "wof:name":"ML8 5JZ",
    "wof:placetype":"postalcode"
},
  "geometry": {"coordinates":[-3.87765269606445,55.74712065020918],"type":"Point"}
}