{
  "type": "Feature",
  "properties": {
    "date:inception_lower": "1980-01-01",
    "date:inception_upper": "1980-01-01",
    "iso:country": "GB",
    "wof:name": "ML8 5JZ",
    "wof:placetype": "postalcode"
  },
  "geometry": {"coordinates":[-3.877653,55.747121],"type":"Point"}
}
