{
  "type": "Feature",
  "properties": {
    "iso:country":"GB",
    "wof:name":"CF32 0TH",
    "wof:placetype":"postalcode"
},
  "geometry": {"coordinates":[-3.57486140478829,51.46152156955925],"type":"Point"}
}