{
  "type": "Feature",
  "properties": {
    "iso:country": "GB",
    "wof:name": "DH1 2FB",
    "wof:placetype": "postalcode"
  },
  "geometry": {"coordinates":[-1.536814,54.752338],"type":"Point"}
}
