{
  "type": "Feature",
  "properties": {
    "date:inception_lower": "1999-06-01",
    "date:inception_upper": "1999-06-01",
    "iso:country": "GB",
    "wof:name": "DH1 2FB",
    "wof:placetype": "postalcode"
  },
  "geometry": {"coordinates":[-1.536814,54.752338],"type":"Point"}
}
