{
  "type": "Feature",
  "properties": {
    "iso:country":"GB",
    "wof:name":"DH1 2FB",
    "wof:placetype":"postalcode"
},
  "geometry": {"coordinates":[-1.53647494460055,54.75248917417324],"type":"Point"}
}