{
  "type": "Feature",
  "properties": {
    "iso:country":"GB",
    "wof:name":"PE12 9YW",
    "wof:placetype":"postalcode"
},
  "geometry": {"coordinates":[0.1979474234964,52.76721543324488],"type":"Point"}
}