{
  "type": "Feature",
  "properties": {
    "iso:country": "GB",
    "wof:name": "PE12 9YW",
    "wof:placetype": "postalcode"
  },
  "geometry": {"coordinates":[0.19804,52.767305],"type":"Point"}
}
