{
  "type": "Feature",
  "properties": {
    "iso:country":"GB",
    "wof:name":"EX15 2TT",
    "wof:placetype":"postalcode"
},
  "geometry": {"coordinates":[-3.36564230553103,50.89269904734343],"type":"Point"}
}