{
  "type": "Feature",
  "properties": {
    "iso:country":"GB",
    "wof:name":"HX2 0UU",
    "wof:placetype":"postalcode"
},
  "geometry": {"coordinates":[-1.91974697501357,53.73977961674046],"type":"Point"}
}