{
  "type": "Feature",
  "properties": {
    "iso:country":"GB",
    "wof:name":"BB18 5AW",
    "wof:placetype":"postalcode"
},
  "geometry": {"coordinates":[-2.18740104170782,53.91434871993945],"type":"Point"}
}