{
  "type": "Feature",
  "properties": {
    "iso:country": "GB",
    "wof:name": "M22 5YA",
    "wof:placetype": "postalcode"
  },
  "geometry": {"coordinates":[-2.243885,53.359825],"type":"Point"}
}
