{
  "type": "Feature",
  "properties": {
    "date:inception_lower": "1994-05-01",
    "date:inception_upper": "1994-05-01",
    "iso:country": "GB",
    "wof:name": "M22 5YA",
    "wof:placetype": "postalcode"
  },
  "geometry": {"coordinates":[-2.243885,53.359825],"type":"Point"}
}
