{
  "type": "Feature",
  "properties": {
    "iso:country":"GB",
    "wof:name":"M22 5YA",
    "wof:placetype":"postalcode"
},
  "geometry": {"coordinates":[-2.24388646747637,53.35980866291693],"type":"Point"}
}