{
  "type": "Feature",
  "properties": {
    "iso:country":"GB",
    "wof:name":"LL16 3HT",
    "wof:placetype":"postalcode"
},
  "geometry": {"coordinates":[-3.40062331773445,53.18817346381093],"type":"Point"}
}