{
  "type": "Feature",
  "properties": {
    "iso:country":"GB",
    "wof:name":"NG2 4GG",
    "wof:placetype":"postalcode"
},
  "geometry": {"coordinates":[-1.12209163685862,52.95303571610329],"type":"Point"}
}