{
  "type": "Feature",
  "properties": {
    "iso:country":"GB",
    "wof:name":"TW8 0PJ",
    "wof:placetype":"postalcode"
},
  "geometry": {"coordinates":[-0.30302405247577,51.48641538420576],"type":"Point"}
}