{
  "type": "Feature",
  "properties": {
    "iso:country":"GB",
    "wof:name":"PE11 4QT",
    "wof:placetype":"postalcode"
},
  "geometry": {"coordinates":[-0.25288182081428,52.88455000614669],"type":"Point"}
}