{
  "type": "Feature",
  "properties": {
    "date:inception_lower": "1999-06-01",
    "date:inception_upper": "1999-06-01",
    "iso:country": "GB",
    "wof:name": "NP20 3LA",
    "wof:placetype": "postalcode"
  },
  "geometry": {"coordinates":[-3.022417,51.572297],"type":"Point"}
}
