{
  "type": "Feature",
  "properties": {
    "iso:country":"GB",
    "wof:name":"CW7 1FF",
    "wof:placetype":"postalcode"
},
  "geometry": {"coordinates":[-2.53607479791512,53.18237498664413],"type":"Point"}
}