{
  "type": "Feature",
  "properties": {
    "date:inception_lower": "1980-01-01",
    "date:inception_upper": "1980-01-01",
    "iso:country": "GB",
    "wof:name": "LL53 6TD",
    "wof:placetype": "postalcode"
  },
  "geometry": {"coordinates":[-4.330114,52.955272],"type":"Point"}
}
