{
  "type": "Feature",
  "properties": {
    "iso:country":"GB",
    "wof:name":"LL53 6TD",
    "wof:placetype":"postalcode"
},
  "geometry": {"coordinates":[-4.33011442501574,52.95527240429688],"type":"Point"}
}