{
  "type": "Feature",
  "properties": {
    "iso:country":"GB",
    "wof:name":"CF24 3JT",
    "wof:placetype":"postalcode"
},
  "geometry": {"coordinates":[-3.16675523893917,51.49219978486624],"type":"Point"}
}