{
  "type": "Feature",
  "properties": {
    "iso:country": "GB",
    "wof:name": "NN8 4PT",
    "wof:placetype": "postalcode"
  },
  "geometry": {"coordinates":[-0.694034,52.303593],"type":"Point"}
}
