{
  "type": "Feature",
  "properties": {
    "iso:country":"GB",
    "wof:name":"NN8 4PT",
    "wof:placetype":"postalcode"
},
  "geometry": {"coordinates":[-0.69402285581342,52.3035517990285],"type":"Point"}
}