{
  "type": "Feature",
  "properties": {
    "iso:country": "GB",
    "wof:name": "WA7 4TD",
    "wof:placetype": "postalcode"
  },
  "geometry": {"coordinates":[-2.7214,53.321247],"type":"Point"}
}
