{
  "type": "Feature",
  "properties": {
    "iso:country":"GB",
    "wof:name":"WA7 4TD",
    "wof:placetype":"postalcode"
},
  "geometry": {"coordinates":[-2.72139997775393,53.32124715178968],"type":"Point"}
}