{
  "type": "Feature",
  "properties": {
    "iso:country":"GB",
    "wof:name":"KT3 6DN",
    "wof:placetype":"postalcode"
},
  "geometry": {"coordinates":[-0.25205962419635,51.39723473735685],"type":"Point"}
}