{
  "type": "Feature",
  "properties": {
    "date:inception_lower": "1980-01-01",
    "date:inception_upper": "1980-01-01",
    "iso:country": "GB",
    "wof:name": "DY1 1HP",
    "wof:placetype": "postalcode"
  },
  "geometry": {"coordinates":[-2.08553,52.511492],"type":"Point"}
}
