{
  "type": "Feature",
  "properties": {
    "date:inception_lower": "1995-07-01",
    "date:inception_upper": "1995-07-01",
    "iso:country": "GB",
    "wof:name": "OL12 9DP",
    "wof:placetype": "postalcode"
  },
  "geometry": {"coordinates":[-2.145054,53.634962],"type":"Point"}
}
