{
  "type": "Feature",
  "properties": {
    "date:inception_lower": "1983-03-01",
    "date:inception_upper": "1983-03-01",
    "iso:country": "GB",
    "wof:name": "WS13 7DE",
    "wof:placetype": "postalcode"
  },
  "geometry": {"coordinates":[-1.839264,52.688345],"type":"Point"}
}
