{
  "type": "Feature",
  "properties": {
    "iso:country":"GB",
    "wof:name":"YO19 5XF",
    "wof:placetype":"postalcode"
},
  "geometry": {"coordinates":[-1.01011618669442,53.98006668126529],"type":"Point"}
}