{
  "type": "Feature",
  "properties": {
    "iso:country":"GB",
    "wof:name":"SK14 2BZ",
    "wof:placetype":"postalcode"
},
  "geometry": {"coordinates":[-2.09094691437943,53.45413362220844],"type":"Point"}
}