{
  "type": "Feature",
  "properties": {
    "iso:country": "GB",
    "wof:name": "TQ1 3HD",
    "wof:placetype": "postalcode"
  },
  "geometry": {"coordinates":[-3.528075,50.474733],"type":"Point"}
}
