{
  "type": "Feature",
  "properties": {
    "iso:country": "GB",
    "wof:name": "SG6 4JY",
    "wof:placetype": "postalcode"
  },
  "geometry": {"coordinates":[-0.250449,51.981124],"type":"Point"}
}
