{
  "type": "Feature",
  "properties": {
    "iso:country":"GB",
    "wof:name":"SG6 4JY",
    "wof:placetype":"postalcode"
},
  "geometry": {"coordinates":[-0.25044919105763,51.9811242032748],"type":"Point"}
}