{
  "type": "Feature",
  "properties": {
    "iso:country":"GB",
    "wof:name":"BA15 1DN",
    "wof:placetype":"postalcode"
},
  "geometry": {"coordinates":[-2.25025604756978,51.34434145573433],"type":"Point"}
}